Classfile /Users/mw/Projects/slang-braindump/.jar/jar8/assemble/slang-braindump/assemble/content/shapeless/ops/coproduct$ZipWithKeys$.class
  Last modified May 29, 2022; size 2237 bytes
  SHA-256 checksum fafd6e7e7924ba32e5a1b179fa01dafde13268ed3a64912117752f573b0c334a
  Compiled from "coproduct.scala"
public class shapeless.ops.coproduct$ZipWithKeys$ implements java.io.Serializable
  minor version: 0
  major version: 52
  flags: (0x0021) ACC_PUBLIC, ACC_SUPER
  this_class: #2                          // shapeless/ops/coproduct$ZipWithKeys$
  super_class: #4                         // java/lang/Object
  interfaces: 1, fields: 2, methods: 6, attributes: 4
Constant pool:
   #1 = Utf8               shapeless/ops/coproduct$ZipWithKeys$
   #2 = Class              #1             // shapeless/ops/coproduct$ZipWithKeys$
   #3 = Utf8               java/lang/Object
   #4 = Class              #3             // java/lang/Object
   #5 = Utf8               java/io/Serializable
   #6 = Class              #5             // java/io/Serializable
   #7 = Utf8               coproduct.scala
   #8 = Utf8               shapeless/ops/coproduct$ZipWithKeys
   #9 = Class              #8             // shapeless/ops/coproduct$ZipWithKeys
  #10 = Utf8               shapeless/ops/coproduct
  #11 = Class              #10            // shapeless/ops/coproduct
  #12 = Utf8               ZipWithKeys
  #13 = Utf8               ZipWithKeys$
  #14 = Utf8               shapeless/ops/coproduct$ZipWithKeys$$anon$27
  #15 = Class              #14            // shapeless/ops/coproduct$ZipWithKeys$$anon$27
  #16 = Utf8               shapeless/ops/coproduct$ZipWithKeys$$anon$28
  #17 = Class              #16            // shapeless/ops/coproduct$ZipWithKeys$$anon$28
  #18 = Utf8               MODULE$
  #19 = Utf8               Lshapeless/ops/coproduct$ZipWithKeys$;
  #20 = Utf8               cnilZipWithKeys
  #21 = Utf8               Lshapeless/ops/coproduct$ZipWithKeys;
  #22 = Utf8               Lshapeless/ops/coproduct$ZipWithKeys<Lshapeless/HNil;Lshapeless/CNil;>;
  #23 = Utf8               <clinit>
  #24 = Utf8               ()V
  #25 = Utf8               <init>
  #26 = NameAndType        #25:#24        // "<init>":()V
  #27 = Methodref          #2.#26         // shapeless/ops/coproduct$ZipWithKeys$."<init>":()V
  #28 = NameAndType        #18:#19        // MODULE$:Lshapeless/ops/coproduct$ZipWithKeys$;
  #29 = Fieldref           #2.#28         // shapeless/ops/coproduct$ZipWithKeys$.MODULE$:Lshapeless/ops/coproduct$ZipWithKeys$;
  #30 = Methodref          #15.#26        // shapeless/ops/coproduct$ZipWithKeys$$anon$27."<init>":()V
  #31 = NameAndType        #20:#21        // cnilZipWithKeys:Lshapeless/ops/coproduct$ZipWithKeys;
  #32 = Fieldref           #2.#31         // shapeless/ops/coproduct$ZipWithKeys$.cnilZipWithKeys:Lshapeless/ops/coproduct$ZipWithKeys;
  #33 = Utf8               apply
  #34 = Utf8               (Lshapeless/ops/coproduct$ZipWithKeys;)Lshapeless/ops/coproduct$ZipWithKeys;
  #35 = Utf8               <K::Lshapeless/HList;V::Lshapeless/Coproduct;>(Lshapeless/ops/coproduct$ZipWithKeys<TK;TV;>;)Lshapeless/ops/coproduct$ZipWithKeys<TK;TV;>;
  #36 = Utf8               zipWithKeys
  #37 = Utf8               this
  #38 = Utf8               ()Lshapeless/ops/coproduct$ZipWithKeys;
  #39 = Utf8               ()Lshapeless/ops/coproduct$ZipWithKeys<Lshapeless/HNil;Lshapeless/CNil;>;
  #40 = Utf8               cpZipWithKeys
  #41 = Utf8               (Lshapeless/ops/coproduct$ZipWithKeys;Lshapeless/Witness;)Lshapeless/ops/coproduct$ZipWithKeys;
  #42 = Utf8               <KH:Ljava/lang/Object;VH:Ljava/lang/Object;KT::Lshapeless/HList;VT::Lshapeless/Coproduct;>(Lshapeless/ops/coproduct$ZipWithKeys<TKT;TVT;>;Lshapeless/Witness;)Lshapeless/ops/coproduct$ZipWithKeys<Lshapeless/$colon$colon<TKH;TKT;>;Lshapeless/$colon$plus$colon<TVH;TVT;>;>;
  #43 = Utf8               wkh
  #44 = Utf8               (Lshapeless/ops/coproduct$ZipWithKeys;)V
  #45 = NameAndType        #25:#44        // "<init>":(Lshapeless/ops/coproduct$ZipWithKeys;)V
  #46 = Methodref          #17.#45        // shapeless/ops/coproduct$ZipWithKeys$$anon$28."<init>":(Lshapeless/ops/coproduct$ZipWithKeys;)V
  #47 = Utf8               Lshapeless/Witness;
  #48 = Utf8               writeReplace
  #49 = Utf8               ()Ljava/lang/Object;
  #50 = Utf8               scala/runtime/ModuleSerializationProxy
  #51 = Class              #50            // scala/runtime/ModuleSerializationProxy
  #52 = Utf8               (Ljava/lang/Class;)V
  #53 = NameAndType        #25:#52        // "<init>":(Ljava/lang/Class;)V
  #54 = Methodref          #51.#53        // scala/runtime/ModuleSerializationProxy."<init>":(Ljava/lang/Class;)V
  #55 = Methodref          #4.#26         // java/lang/Object."<init>":()V
  #56 = Utf8               Signature
  #57 = Utf8               Code
  #58 = Utf8               LineNumberTable
  #59 = Utf8               LocalVariableTable
  #60 = Utf8               MethodParameters
  #61 = Utf8               InnerClasses
  #62 = Utf8               SourceFile
  #63 = Utf8               ScalaInlineInfo
  #64 = Utf8               Scala
{
  public static final shapeless.ops.coproduct$ZipWithKeys$ MODULE$;
    descriptor: Lshapeless/ops/coproduct$ZipWithKeys$;
    flags: (0x0019) ACC_PUBLIC, ACC_STATIC, ACC_FINAL

  private static final shapeless.ops.coproduct$ZipWithKeys<shapeless.HNil, shapeless.CNil> cnilZipWithKeys;
    descriptor: Lshapeless/ops/coproduct$ZipWithKeys;
    flags: (0x001a) ACC_PRIVATE, ACC_STATIC, ACC_FINAL
    Signature: #22                          // Lshapeless/ops/coproduct$ZipWithKeys<Lshapeless/HNil;Lshapeless/CNil;>;

  public static {};
    descriptor: ()V
    flags: (0x0009) ACC_PUBLIC, ACC_STATIC
    Code:
      stack=2, locals=0, args_size=0
         0: new           #2                  // class shapeless/ops/coproduct$ZipWithKeys$
         3: dup
         4: invokespecial #27                 // Method "<init>":()V
         7: putstatic     #29                 // Field MODULE$:Lshapeless/ops/coproduct$ZipWithKeys$;
        10: new           #15                 // class shapeless/ops/coproduct$ZipWithKeys$$anon$27
        13: dup
        14: invokespecial #30                 // Method shapeless/ops/coproduct$ZipWithKeys$$anon$27."<init>":()V
        17: putstatic     #32                 // Field cnilZipWithKeys:Lshapeless/ops/coproduct$ZipWithKeys;
        20: return
      LineNumberTable:
        line 432: 0
        line 440: 10
        line 432: 20

  public <K extends shapeless.HList, V extends shapeless.Coproduct> shapeless.ops.coproduct$ZipWithKeys<K, V> apply(shapeless.ops.coproduct$ZipWithKeys<K, V>);
    descriptor: (Lshapeless/ops/coproduct$ZipWithKeys;)Lshapeless/ops/coproduct$ZipWithKeys;
    flags: (0x0001) ACC_PUBLIC
    Code:
      stack=1, locals=2, args_size=2
         0: aload_1
         1: areturn
      LineNumberTable:
        line 436: 0
      LocalVariableTable:
        Start  Length  Slot  Name   Signature
            0       2     0  this   Lshapeless/ops/coproduct$ZipWithKeys$;
            0       2     1 zipWithKeys   Lshapeless/ops/coproduct$ZipWithKeys;
    Signature: #35                          // <K::Lshapeless/HList;V::Lshapeless/Coproduct;>(Lshapeless/ops/coproduct$ZipWithKeys<TK;TV;>;)Lshapeless/ops/coproduct$ZipWithKeys<TK;TV;>;
    MethodParameters:
      Name                           Flags
      zipWithKeys                    final

  public shapeless.ops.coproduct$ZipWithKeys<shapeless.HNil, shapeless.CNil> cnilZipWithKeys();
    descriptor: ()Lshapeless/ops/coproduct$ZipWithKeys;
    flags: (0x0001) ACC_PUBLIC
    Code:
      stack=1, locals=1, args_size=1
         0: getstatic     #32                 // Field cnilZipWithKeys:Lshapeless/ops/coproduct$ZipWithKeys;
         3: areturn
      LineNumberTable:
        line 440: 0
      LocalVariableTable:
        Start  Length  Slot  Name   Signature
            0       4     0  this   Lshapeless/ops/coproduct$ZipWithKeys$;
    Signature: #39                          // ()Lshapeless/ops/coproduct$ZipWithKeys<Lshapeless/HNil;Lshapeless/CNil;>;

  public <KH extends java.lang.Object, VH extends java.lang.Object, KT extends shapeless.HList, VT extends shapeless.Coproduct> shapeless.ops.coproduct$ZipWithKeys<shapeless.$colon$colon<KH, KT>, shapeless.$colon$plus$colon<VH, VT>> cpZipWithKeys(shapeless.ops.coproduct$ZipWithKeys<KT, VT>, shapeless.Witness);
    descriptor: (Lshapeless/ops/coproduct$ZipWithKeys;Lshapeless/Witness;)Lshapeless/ops/coproduct$ZipWithKeys;
    flags: (0x0001) ACC_PUBLIC
    Code:
      stack=3, locals=3, args_size=3
         0: new           #17                 // class shapeless/ops/coproduct$ZipWithKeys$$anon$28
         3: dup
         4: aload_1
         5: invokespecial #46                 // Method shapeless/ops/coproduct$ZipWithKeys$$anon$28."<init>":(Lshapeless/ops/coproduct$ZipWithKeys;)V
         8: areturn
      LineNumberTable:
        line 447: 0
      LocalVariableTable:
        Start  Length  Slot  Name   Signature
            0       9     0  this   Lshapeless/ops/coproduct$ZipWithKeys$;
            0       9     1 zipWithKeys   Lshapeless/ops/coproduct$ZipWithKeys;
            0       9     2   wkh   Lshapeless/Witness;
    Signature: #42                          // <KH:Ljava/lang/Object;VH:Ljava/lang/Object;KT::Lshapeless/HList;VT::Lshapeless/Coproduct;>(Lshapeless/ops/coproduct$ZipWithKeys<TKT;TVT;>;Lshapeless/Witness;)Lshapeless/ops/coproduct$ZipWithKeys<Lshapeless/$colon$colon<TKH;TKT;>;Lshapeless/$colon$plus$colon<TVH;TVT;>;>;
    MethodParameters:
      Name                           Flags
      zipWithKeys                    final
      wkh                            final

  private java.lang.Object writeReplace();
    descriptor: ()Ljava/lang/Object;
    flags: (0x0002) ACC_PRIVATE
    Code:
      stack=3, locals=1, args_size=1
         0: new           #51                 // class scala/runtime/ModuleSerializationProxy
         3: dup
         4: ldc           #2                  // class shapeless/ops/coproduct$ZipWithKeys$
         6: invokespecial #54                 // Method scala/runtime/ModuleSerializationProxy."<init>":(Ljava/lang/Class;)V
         9: areturn
      LineNumberTable:
        line 432: 0
      LocalVariableTable:
        Start  Length  Slot  Name   Signature
            0      10     0  this   Lshapeless/ops/coproduct$ZipWithKeys$;

  public shapeless.ops.coproduct$ZipWithKeys$();
    descriptor: ()V
    flags: (0x0001) ACC_PUBLIC
    Code:
      stack=1, locals=1, args_size=1
         0: aload_0
         1: invokespecial #55                 // Method java/lang/Object."<init>":()V
         4: return
      LineNumberTable:
        line 462: 0
        line 432: 4
      LocalVariableTable:
        Start  Length  Slot  Name   Signature
            0       5     0  this   Lshapeless/ops/coproduct$ZipWithKeys$;
}
InnerClasses:
  public static #12= #9 of #11;           // ZipWithKeys=class shapeless/ops/coproduct$ZipWithKeys of class shapeless/ops/coproduct
  public static #13= #2 of #11;           // ZipWithKeys$=class shapeless/ops/coproduct$ZipWithKeys$ of class shapeless/ops/coproduct
  public final #15;                       // class shapeless/ops/coproduct$ZipWithKeys$$anon$27
  public final #17;                       // class shapeless/ops/coproduct$ZipWithKeys$$anon$28
SourceFile: "coproduct.scala"
  ScalaInlineInfo: length = 0x1D (unknown attribute)
   01 01 00 05 00 19 00 18 01 00 21 00 22 01 00 14
   00 26 01 00 28 00 29 01 00 30 00 31 01
  Scala: length = 0x0 (unknown attribute)

