Classfile /Users/mw/Projects/slang-braindump/.jar/jar8/assemble/slang-braindump/assemble/content/shapeless/ops/coproduct$RotateLeft$Impl$.class
  Last modified May 29, 2022; size 2560 bytes
  SHA-256 checksum d430ea94160a1eba7b52cda748f1c4cfb04480b430f5df0f218ec536deeb291e
  Compiled from "coproduct.scala"
public class shapeless.ops.coproduct$RotateLeft$Impl$ implements java.io.Serializable
  minor version: 0
  major version: 52
  flags: (0x0021) ACC_PUBLIC, ACC_SUPER
  this_class: #2                          // shapeless/ops/coproduct$RotateLeft$Impl$
  super_class: #4                         // java/lang/Object
  interfaces: 1, fields: 1, methods: 5, attributes: 4
Constant pool:
   #1 = Utf8               shapeless/ops/coproduct$RotateLeft$Impl$
   #2 = Class              #1             // shapeless/ops/coproduct$RotateLeft$Impl$
   #3 = Utf8               java/lang/Object
   #4 = Class              #3             // java/lang/Object
   #5 = Utf8               java/io/Serializable
   #6 = Class              #5             // java/io/Serializable
   #7 = Utf8               coproduct.scala
   #8 = Utf8               shapeless/ops/coproduct$ExtendRight
   #9 = Class              #8             // shapeless/ops/coproduct$ExtendRight
  #10 = Utf8               shapeless/ops/coproduct
  #11 = Class              #10            // shapeless/ops/coproduct
  #12 = Utf8               ExtendRight
  #13 = Utf8               shapeless/ops/coproduct$Inject
  #14 = Class              #13            // shapeless/ops/coproduct$Inject
  #15 = Utf8               Inject
  #16 = Utf8               shapeless/ops/coproduct$RotateLeft$
  #17 = Class              #16            // shapeless/ops/coproduct$RotateLeft$
  #18 = Utf8               RotateLeft$
  #19 = Utf8               shapeless/ops/coproduct$RotateLeft$Impl
  #20 = Class              #19            // shapeless/ops/coproduct$RotateLeft$Impl
  #21 = Utf8               Impl
  #22 = Utf8               Impl$
  #23 = Utf8               shapeless/ops/coproduct$RotateLeft$Impl$$anon$46
  #24 = Class              #23            // shapeless/ops/coproduct$RotateLeft$Impl$$anon$46
  #25 = Utf8               shapeless/ops/coproduct$RotateLeft$Impl$$anon$47
  #26 = Class              #25            // shapeless/ops/coproduct$RotateLeft$Impl$$anon$47
  #27 = Utf8               MODULE$
  #28 = Utf8               Lshapeless/ops/coproduct$RotateLeft$Impl$;
  #29 = Utf8               <clinit>
  #30 = Utf8               ()V
  #31 = Utf8               <init>
  #32 = NameAndType        #31:#30        // "<init>":()V
  #33 = Methodref          #2.#32         // shapeless/ops/coproduct$RotateLeft$Impl$."<init>":()V
  #34 = NameAndType        #27:#28        // MODULE$:Lshapeless/ops/coproduct$RotateLeft$Impl$;
  #35 = Fieldref           #2.#34         // shapeless/ops/coproduct$RotateLeft$Impl$.MODULE$:Lshapeless/ops/coproduct$RotateLeft$Impl$;
  #36 = Utf8               rotateCoproductOne
  #37 = Utf8               (Lshapeless/ops/coproduct$ExtendRight;Lshapeless/ops/coproduct$Inject;)Lshapeless/ops/coproduct$RotateLeft$Impl;
  #38 = Utf8               <H:Ljava/lang/Object;T::Lshapeless/Coproduct;TH::Lshapeless/Coproduct;>(Lshapeless/ops/coproduct$ExtendRight<TT;TH;>;Lshapeless/ops/coproduct$Inject<TTH;TH;>;)Lshapeless/ops/coproduct$RotateLeft$Impl<Lshapeless/$colon$plus$colon<TH;TT;>;Lshapeless/Succ<Lshapeless/_0;>;>;
  #39 = Utf8               extendRight
  #40 = Utf8               inject
  #41 = Utf8               (Lshapeless/ops/coproduct$Inject;Lshapeless/ops/coproduct$ExtendRight;)V
  #42 = NameAndType        #31:#41        // "<init>":(Lshapeless/ops/coproduct$Inject;Lshapeless/ops/coproduct$ExtendRight;)V
  #43 = Methodref          #24.#42        // shapeless/ops/coproduct$RotateLeft$Impl$$anon$46."<init>":(Lshapeless/ops/coproduct$Inject;Lshapeless/ops/coproduct$ExtendRight;)V
  #44 = Utf8               this
  #45 = Utf8               Lshapeless/ops/coproduct$ExtendRight;
  #46 = Utf8               Lshapeless/ops/coproduct$Inject;
  #47 = Utf8               rotateCoproductN
  #48 = Utf8               (Lshapeless/ops/coproduct$RotateLeft$Impl;Lshapeless/ops/coproduct$RotateLeft$Impl;)Lshapeless/ops/coproduct$RotateLeft$Impl;
  #49 = Utf8               <C::Lshapeless/Coproduct;N::Lshapeless/Nat;CN::Lshapeless/Coproduct;CSN::Lshapeless/Coproduct;>(Lshapeless/ops/coproduct$RotateLeft$Impl<TC;TN;>;Lshapeless/ops/coproduct$RotateLeft$Impl<TCN;Lshapeless/Succ<Lshapeless/_0;>;>;)Lshapeless/ops/coproduct$RotateLeft$Impl<TC;Lshapeless/Succ<TN;>;>;
  #50 = Utf8               rotateN
  #51 = Utf8               rotate1
  #52 = Utf8               (Lshapeless/ops/coproduct$RotateLeft$Impl;Lshapeless/ops/coproduct$RotateLeft$Impl;)V
  #53 = NameAndType        #31:#52        // "<init>":(Lshapeless/ops/coproduct$RotateLeft$Impl;Lshapeless/ops/coproduct$RotateLeft$Impl;)V
  #54 = Methodref          #26.#53        // shapeless/ops/coproduct$RotateLeft$Impl$$anon$47."<init>":(Lshapeless/ops/coproduct$RotateLeft$Impl;Lshapeless/ops/coproduct$RotateLeft$Impl;)V
  #55 = Utf8               Lshapeless/ops/coproduct$RotateLeft$Impl;
  #56 = Utf8               writeReplace
  #57 = Utf8               ()Ljava/lang/Object;
  #58 = Utf8               scala/runtime/ModuleSerializationProxy
  #59 = Class              #58            // scala/runtime/ModuleSerializationProxy
  #60 = Utf8               (Ljava/lang/Class;)V
  #61 = NameAndType        #31:#60        // "<init>":(Ljava/lang/Class;)V
  #62 = Methodref          #59.#61        // scala/runtime/ModuleSerializationProxy."<init>":(Ljava/lang/Class;)V
  #63 = Methodref          #4.#32         // java/lang/Object."<init>":()V
  #64 = Utf8               Code
  #65 = Utf8               LineNumberTable
  #66 = Utf8               LocalVariableTable
  #67 = Utf8               Signature
  #68 = Utf8               MethodParameters
  #69 = Utf8               InnerClasses
  #70 = Utf8               SourceFile
  #71 = Utf8               ScalaInlineInfo
  #72 = Utf8               Scala
{
  public static final shapeless.ops.coproduct$RotateLeft$Impl$ MODULE$;
    descriptor: Lshapeless/ops/coproduct$RotateLeft$Impl$;
    flags: (0x0019) ACC_PUBLIC, ACC_STATIC, ACC_FINAL

  public static {};
    descriptor: ()V
    flags: (0x0009) ACC_PUBLIC, ACC_STATIC
    Code:
      stack=2, locals=0, args_size=0
         0: new           #2                  // class shapeless/ops/coproduct$RotateLeft$Impl$
         3: dup
         4: invokespecial #33                 // Method "<init>":()V
         7: putstatic     #35                 // Field MODULE$:Lshapeless/ops/coproduct$RotateLeft$Impl$;
        10: return
      LineNumberTable:
        line 719: 0

  public <H extends java.lang.Object, T extends shapeless.Coproduct, TH extends shapeless.Coproduct> shapeless.ops.coproduct$RotateLeft$Impl<shapeless.$colon$plus$colon<H, T>, shapeless.Succ<shapeless._0>> rotateCoproductOne(shapeless.ops.coproduct$ExtendRight<T, H>, shapeless.ops.coproduct$Inject<TH, H>);
    descriptor: (Lshapeless/ops/coproduct$ExtendRight;Lshapeless/ops/coproduct$Inject;)Lshapeless/ops/coproduct$RotateLeft$Impl;
    flags: (0x0001) ACC_PUBLIC
    Code:
      stack=4, locals=3, args_size=3
         0: new           #24                 // class shapeless/ops/coproduct$RotateLeft$Impl$$anon$46
         3: dup
         4: aload_2
         5: aload_1
         6: invokespecial #43                 // Method shapeless/ops/coproduct$RotateLeft$Impl$$anon$46."<init>":(Lshapeless/ops/coproduct$Inject;Lshapeless/ops/coproduct$ExtendRight;)V
         9: areturn
      LineNumberTable:
        line 724: 0
      LocalVariableTable:
        Start  Length  Slot  Name   Signature
            0      10     0  this   Lshapeless/ops/coproduct$RotateLeft$Impl$;
            0      10     1 extendRight   Lshapeless/ops/coproduct$ExtendRight;
            0      10     2 inject   Lshapeless/ops/coproduct$Inject;
    Signature: #38                          // <H:Ljava/lang/Object;T::Lshapeless/Coproduct;TH::Lshapeless/Coproduct;>(Lshapeless/ops/coproduct$ExtendRight<TT;TH;>;Lshapeless/ops/coproduct$Inject<TTH;TH;>;)Lshapeless/ops/coproduct$RotateLeft$Impl<Lshapeless/$colon$plus$colon<TH;TT;>;Lshapeless/Succ<Lshapeless/_0;>;>;
    MethodParameters:
      Name                           Flags
      extendRight                    final
      inject                         final

  public <C extends shapeless.Coproduct, N extends shapeless.Nat, CN extends shapeless.Coproduct, CSN extends shapeless.Coproduct> shapeless.ops.coproduct$RotateLeft$Impl<C, shapeless.Succ<N>> rotateCoproductN(shapeless.ops.coproduct$RotateLeft$Impl<C, N>, shapeless.ops.coproduct$RotateLeft$Impl<CN, shapeless.Succ<shapeless._0>>);
    descriptor: (Lshapeless/ops/coproduct$RotateLeft$Impl;Lshapeless/ops/coproduct$RotateLeft$Impl;)Lshapeless/ops/coproduct$RotateLeft$Impl;
    flags: (0x0001) ACC_PUBLIC
    Code:
      stack=4, locals=3, args_size=3
         0: new           #26                 // class shapeless/ops/coproduct$RotateLeft$Impl$$anon$47
         3: dup
         4: aload_2
         5: aload_1
         6: invokespecial #54                 // Method shapeless/ops/coproduct$RotateLeft$Impl$$anon$47."<init>":(Lshapeless/ops/coproduct$RotateLeft$Impl;Lshapeless/ops/coproduct$RotateLeft$Impl;)V
         9: areturn
      LineNumberTable:
        line 735: 0
      LocalVariableTable:
        Start  Length  Slot  Name   Signature
            0      10     0  this   Lshapeless/ops/coproduct$RotateLeft$Impl$;
            0      10     1 rotateN   Lshapeless/ops/coproduct$RotateLeft$Impl;
            0      10     2 rotate1   Lshapeless/ops/coproduct$RotateLeft$Impl;
    Signature: #49                          // <C::Lshapeless/Coproduct;N::Lshapeless/Nat;CN::Lshapeless/Coproduct;CSN::Lshapeless/Coproduct;>(Lshapeless/ops/coproduct$RotateLeft$Impl<TC;TN;>;Lshapeless/ops/coproduct$RotateLeft$Impl<TCN;Lshapeless/Succ<Lshapeless/_0;>;>;)Lshapeless/ops/coproduct$RotateLeft$Impl<TC;Lshapeless/Succ<TN;>;>;
    MethodParameters:
      Name                           Flags
      rotateN                        final
      rotate1                        final

  private java.lang.Object writeReplace();
    descriptor: ()Ljava/lang/Object;
    flags: (0x0002) ACC_PRIVATE
    Code:
      stack=3, locals=1, args_size=1
         0: new           #59                 // class scala/runtime/ModuleSerializationProxy
         3: dup
         4: ldc           #2                  // class shapeless/ops/coproduct$RotateLeft$Impl$
         6: invokespecial #62                 // Method scala/runtime/ModuleSerializationProxy."<init>":(Ljava/lang/Class;)V
         9: areturn
      LineNumberTable:
        line 719: 0
      LocalVariableTable:
        Start  Length  Slot  Name   Signature
            0      10     0  this   Lshapeless/ops/coproduct$RotateLeft$Impl$;

  public shapeless.ops.coproduct$RotateLeft$Impl$();
    descriptor: ()V
    flags: (0x0001) ACC_PUBLIC
    Code:
      stack=1, locals=1, args_size=1
         0: aload_0
         1: invokespecial #63                 // Method java/lang/Object."<init>":()V
         4: return
      LineNumberTable:
        line 741: 0
        line 719: 4
      LocalVariableTable:
        Start  Length  Slot  Name   Signature
            0       5     0  this   Lshapeless/ops/coproduct$RotateLeft$Impl$;
}
InnerClasses:
  public static #12= #9 of #11;           // ExtendRight=class shapeless/ops/coproduct$ExtendRight of class shapeless/ops/coproduct
  public static #15= #14 of #11;          // Inject=class shapeless/ops/coproduct$Inject of class shapeless/ops/coproduct
  public static #18= #17 of #11;          // RotateLeft$=class shapeless/ops/coproduct$RotateLeft$ of class shapeless/ops/coproduct
  public static #21= #20 of #17;          // Impl=class shapeless/ops/coproduct$RotateLeft$Impl of class shapeless/ops/coproduct$RotateLeft$
  public static #22= #2 of #17;           // Impl$=class shapeless/ops/coproduct$RotateLeft$Impl$ of class shapeless/ops/coproduct$RotateLeft$
  public final #24;                       // class shapeless/ops/coproduct$RotateLeft$Impl$$anon$46
  public final #26;                       // class shapeless/ops/coproduct$RotateLeft$Impl$$anon$47
SourceFile: "coproduct.scala"
  ScalaInlineInfo: length = 0x18 (unknown attribute)
   01 01 00 04 00 1F 00 1E 01 00 2F 00 30 01 00 24
   00 25 01 00 38 00 39 01
  Scala: length = 0x0 (unknown attribute)

