Classfile /Users/mw/Projects/slang-braindump/.jar/jar8/assemble/slang-braindump/assemble/content/shapeless/ops/coproduct$Reverse$Reverse0$.class
  Last modified May 29, 2022; size 1880 bytes
  SHA-256 checksum ff99e6faf13bdc7e80f7627801335e611020a1c1102c6efe9adf122091b87259
  Compiled from "coproduct.scala"
public class shapeless.ops.coproduct$Reverse$Reverse0$ implements java.io.Serializable
  minor version: 0
  major version: 52
  flags: (0x0021) ACC_PUBLIC, ACC_SUPER
  this_class: #2                          // shapeless/ops/coproduct$Reverse$Reverse0$
  super_class: #4                         // java/lang/Object
  interfaces: 1, fields: 1, methods: 5, attributes: 4
Constant pool:
   #1 = Utf8               shapeless/ops/coproduct$Reverse$Reverse0$
   #2 = Class              #1             // shapeless/ops/coproduct$Reverse$Reverse0$
   #3 = Utf8               java/lang/Object
   #4 = Class              #3             // java/lang/Object
   #5 = Utf8               java/io/Serializable
   #6 = Class              #5             // java/io/Serializable
   #7 = Utf8               coproduct.scala
   #8 = Utf8               shapeless/ops/coproduct$Reverse$
   #9 = Class              #8             // shapeless/ops/coproduct$Reverse$
  #10 = Utf8               shapeless/ops/coproduct
  #11 = Class              #10            // shapeless/ops/coproduct
  #12 = Utf8               Reverse$
  #13 = Utf8               shapeless/ops/coproduct$Reverse$Reverse0
  #14 = Class              #13            // shapeless/ops/coproduct$Reverse$Reverse0
  #15 = Utf8               Reverse0
  #16 = Utf8               Reverse0$
  #17 = Utf8               shapeless/ops/coproduct$Reverse$Reverse0$$anon$62
  #18 = Class              #17            // shapeless/ops/coproduct$Reverse$Reverse0$$anon$62
  #19 = Utf8               shapeless/ops/coproduct$Reverse$Reverse0$$anon$63
  #20 = Class              #19            // shapeless/ops/coproduct$Reverse$Reverse0$$anon$63
  #21 = Utf8               MODULE$
  #22 = Utf8               Lshapeless/ops/coproduct$Reverse$Reverse0$;
  #23 = Utf8               <clinit>
  #24 = Utf8               ()V
  #25 = Utf8               <init>
  #26 = NameAndType        #25:#24        // "<init>":()V
  #27 = Methodref          #2.#26         // shapeless/ops/coproduct$Reverse$Reverse0$."<init>":()V
  #28 = NameAndType        #21:#22        // MODULE$:Lshapeless/ops/coproduct$Reverse$Reverse0$;
  #29 = Fieldref           #2.#28         // shapeless/ops/coproduct$Reverse$Reverse0$.MODULE$:Lshapeless/ops/coproduct$Reverse$Reverse0$;
  #30 = Utf8               cnilReverse
  #31 = Utf8               ()Lshapeless/ops/coproduct$Reverse$Reverse0;
  #32 = Utf8               <Out::Lshapeless/Coproduct;>()Lshapeless/ops/coproduct$Reverse$Reverse0<TOut;Lshapeless/CNil;TOut;>;
  #33 = Methodref          #18.#26        // shapeless/ops/coproduct$Reverse$Reverse0$$anon$62."<init>":()V
  #34 = Utf8               this
  #35 = Utf8               cconsReverse
  #36 = Utf8               (Lshapeless/ops/coproduct$Reverse$Reverse0;)Lshapeless/ops/coproduct$Reverse$Reverse0;
  #37 = Utf8               <Acc::Lshapeless/Coproduct;InH:Ljava/lang/Object;InT::Lshapeless/Coproduct;Out::Lshapeless/Coproduct;>(Lshapeless/ops/coproduct$Reverse$Reverse0<Lshapeless/$colon$plus$colon<TInH;TAcc;>;TInT;TOut;>;)Lshapeless/ops/coproduct$Reverse$Reverse0<TAcc;Lshapeless/$colon$plus$colon<TInH;TInT;>;TOut;>;
  #38 = Utf8               rt
  #39 = Utf8               (Lshapeless/ops/coproduct$Reverse$Reverse0;)V
  #40 = NameAndType        #25:#39        // "<init>":(Lshapeless/ops/coproduct$Reverse$Reverse0;)V
  #41 = Methodref          #20.#40        // shapeless/ops/coproduct$Reverse$Reverse0$$anon$63."<init>":(Lshapeless/ops/coproduct$Reverse$Reverse0;)V
  #42 = Utf8               Lshapeless/ops/coproduct$Reverse$Reverse0;
  #43 = Utf8               writeReplace
  #44 = Utf8               ()Ljava/lang/Object;
  #45 = Utf8               scala/runtime/ModuleSerializationProxy
  #46 = Class              #45            // scala/runtime/ModuleSerializationProxy
  #47 = Utf8               (Ljava/lang/Class;)V
  #48 = NameAndType        #25:#47        // "<init>":(Ljava/lang/Class;)V
  #49 = Methodref          #46.#48        // scala/runtime/ModuleSerializationProxy."<init>":(Ljava/lang/Class;)V
  #50 = Methodref          #4.#26         // java/lang/Object."<init>":()V
  #51 = Utf8               Code
  #52 = Utf8               LineNumberTable
  #53 = Utf8               LocalVariableTable
  #54 = Utf8               Signature
  #55 = Utf8               MethodParameters
  #56 = Utf8               InnerClasses
  #57 = Utf8               SourceFile
  #58 = Utf8               ScalaInlineInfo
  #59 = Utf8               Scala
{
  public static final shapeless.ops.coproduct$Reverse$Reverse0$ MODULE$;
    descriptor: Lshapeless/ops/coproduct$Reverse$Reverse0$;
    flags: (0x0019) ACC_PUBLIC, ACC_STATIC, ACC_FINAL

  public static {};
    descriptor: ()V
    flags: (0x0009) ACC_PUBLIC, ACC_STATIC
    Code:
      stack=2, locals=0, args_size=0
         0: new           #2                  // class shapeless/ops/coproduct$Reverse$Reverse0$
         3: dup
         4: invokespecial #27                 // Method "<init>":()V
         7: putstatic     #29                 // Field MODULE$:Lshapeless/ops/coproduct$Reverse$Reverse0$;
        10: return
      LineNumberTable:
        line 994: 0

  public <Out extends shapeless.Coproduct> shapeless.ops.coproduct$Reverse$Reverse0<Out, shapeless.CNil, Out> cnilReverse();
    descriptor: ()Lshapeless/ops/coproduct$Reverse$Reverse0;
    flags: (0x0001) ACC_PUBLIC
    Code:
      stack=2, locals=1, args_size=1
         0: new           #18                 // class shapeless/ops/coproduct$Reverse$Reverse0$$anon$62
         3: dup
         4: invokespecial #33                 // Method shapeless/ops/coproduct$Reverse$Reverse0$$anon$62."<init>":()V
         7: areturn
      LineNumberTable:
        line 996: 0
      LocalVariableTable:
        Start  Length  Slot  Name   Signature
            0       8     0  this   Lshapeless/ops/coproduct$Reverse$Reverse0$;
    Signature: #32                          // <Out::Lshapeless/Coproduct;>()Lshapeless/ops/coproduct$Reverse$Reverse0<TOut;Lshapeless/CNil;TOut;>;

  public <Acc extends shapeless.Coproduct, InH extends java.lang.Object, InT extends shapeless.Coproduct, Out extends shapeless.Coproduct> shapeless.ops.coproduct$Reverse$Reverse0<Acc, shapeless.$colon$plus$colon<InH, InT>, Out> cconsReverse(shapeless.ops.coproduct$Reverse$Reverse0<shapeless.$colon$plus$colon<InH, Acc>, InT, Out>);
    descriptor: (Lshapeless/ops/coproduct$Reverse$Reverse0;)Lshapeless/ops/coproduct$Reverse$Reverse0;
    flags: (0x0001) ACC_PUBLIC
    Code:
      stack=3, locals=2, args_size=2
         0: new           #20                 // class shapeless/ops/coproduct$Reverse$Reverse0$$anon$63
         3: dup
         4: aload_1
         5: invokespecial #41                 // Method shapeless/ops/coproduct$Reverse$Reverse0$$anon$63."<init>":(Lshapeless/ops/coproduct$Reverse$Reverse0;)V
         8: areturn
      LineNumberTable:
        line 1004: 0
      LocalVariableTable:
        Start  Length  Slot  Name   Signature
            0       9     0  this   Lshapeless/ops/coproduct$Reverse$Reverse0$;
            0       9     1    rt   Lshapeless/ops/coproduct$Reverse$Reverse0;
    Signature: #37                          // <Acc::Lshapeless/Coproduct;InH:Ljava/lang/Object;InT::Lshapeless/Coproduct;Out::Lshapeless/Coproduct;>(Lshapeless/ops/coproduct$Reverse$Reverse0<Lshapeless/$colon$plus$colon<TInH;TAcc;>;TInT;TOut;>;)Lshapeless/ops/coproduct$Reverse$Reverse0<TAcc;Lshapeless/$colon$plus$colon<TInH;TInT;>;TOut;>;
    MethodParameters:
      Name                           Flags
      rt                             final

  private java.lang.Object writeReplace();
    descriptor: ()Ljava/lang/Object;
    flags: (0x0002) ACC_PRIVATE
    Code:
      stack=3, locals=1, args_size=1
         0: new           #46                 // class scala/runtime/ModuleSerializationProxy
         3: dup
         4: ldc           #2                  // class shapeless/ops/coproduct$Reverse$Reverse0$
         6: invokespecial #49                 // Method scala/runtime/ModuleSerializationProxy."<init>":(Ljava/lang/Class;)V
         9: areturn
      LineNumberTable:
        line 994: 0
      LocalVariableTable:
        Start  Length  Slot  Name   Signature
            0      10     0  this   Lshapeless/ops/coproduct$Reverse$Reverse0$;

  public shapeless.ops.coproduct$Reverse$Reverse0$();
    descriptor: ()V
    flags: (0x0001) ACC_PUBLIC
    Code:
      stack=1, locals=1, args_size=1
         0: aload_0
         1: invokespecial #50                 // Method java/lang/Object."<init>":()V
         4: return
      LineNumberTable:
        line 1014: 0
        line 994: 4
      LocalVariableTable:
        Start  Length  Slot  Name   Signature
            0       5     0  this   Lshapeless/ops/coproduct$Reverse$Reverse0$;
}
InnerClasses:
  public static #12= #9 of #11;           // Reverse$=class shapeless/ops/coproduct$Reverse$ of class shapeless/ops/coproduct
  public static #15= #14 of #9;           // Reverse0=class shapeless/ops/coproduct$Reverse$Reverse0 of class shapeless/ops/coproduct$Reverse$
  public static #16= #2 of #9;            // Reverse0$=class shapeless/ops/coproduct$Reverse$Reverse0$ of class shapeless/ops/coproduct$Reverse$
  public final #18;                       // class shapeless/ops/coproduct$Reverse$Reverse0$$anon$62
  public final #20;                       // class shapeless/ops/coproduct$Reverse$Reverse0$$anon$63
SourceFile: "coproduct.scala"
  ScalaInlineInfo: length = 0x18 (unknown attribute)
   01 01 00 04 00 19 00 18 01 00 23 00 24 01 00 1E
   00 1F 01 00 2B 00 2C 01
  Scala: length = 0x0 (unknown attribute)

