Classfile /Users/mw/Projects/slang-braindump/.jar/jar8/assemble/slang-braindump/assemble/content/shapeless/ops/coproduct$Partition$$anon$9.class
  Last modified May 29, 2022; size 3380 bytes
  SHA-256 checksum 85bcb8de66b36c36c997359f8ae2da83c425a2ed3409b0517b8687d172629415
  Compiled from "coproduct.scala"
public final class shapeless.ops.coproduct$Partition$$anon$9 extends java.lang.Object implements shapeless.ops.coproduct$Partition<shapeless.$colon$plus$colon<H, T>, U>
  minor version: 0
  major version: 52
  flags: (0x0031) ACC_PUBLIC, ACC_FINAL, ACC_SUPER
  this_class: #2                          // shapeless/ops/coproduct$Partition$$anon$9
  super_class: #5                         // java/lang/Object
  interfaces: 1, fields: 1, methods: 7, attributes: 6
Constant pool:
    #1 = Utf8               shapeless/ops/coproduct$Partition$$anon$9
    #2 = Class              #1            // shapeless/ops/coproduct$Partition$$anon$9
    #3 = Utf8               Ljava/lang/Object;Lshapeless/ops/coproduct$Partition<Lshapeless/$colon$plus$colon<TH;TT;>;TU;>;
    #4 = Utf8               java/lang/Object
    #5 = Class              #4            // java/lang/Object
    #6 = Utf8               shapeless/ops/coproduct$Partition
    #7 = Class              #6            // shapeless/ops/coproduct$Partition
    #8 = Utf8               coproduct.scala
    #9 = Utf8               shapeless/ops/coproduct$Partition$
   #10 = Class              #9            // shapeless/ops/coproduct$Partition$
   #11 = Utf8               coproductPartition_NonMatch
   #12 = Utf8               (Lshapeless/ops/coproduct$Partition;Lshapeless/package$$eq$colon$bang$eq;)Lshapeless/ops/coproduct$Partition;
   #13 = NameAndType        #11:#12       // coproductPartition_NonMatch:(Lshapeless/ops/coproduct$Partition;Lshapeless/package$$eq$colon$bang$eq;)Lshapeless/ops/coproduct$Partition;
   #14 = Utf8               shapeless/ops/coproduct
   #15 = Class              #14           // shapeless/ops/coproduct
   #16 = Utf8               Partition
   #17 = Utf8               Partition$
   #18 = Utf8               partition$2
   #19 = Utf8               Lshapeless/ops/coproduct$Partition;
   #20 = Utf8               filter
   #21 = Utf8               (Lshapeless/Coproduct;)Lscala/Option;
   #22 = Utf8               c
   #23 = Utf8               filter$
   #24 = Utf8               (Lshapeless/ops/coproduct$Partition;Lshapeless/Coproduct;)Lscala/Option;
   #25 = NameAndType        #23:#24       // filter$:(Lshapeless/ops/coproduct$Partition;Lshapeless/Coproduct;)Lscala/Option;
   #26 = InterfaceMethodref #7.#25        // shapeless/ops/coproduct$Partition.filter$:(Lshapeless/ops/coproduct$Partition;Lshapeless/Coproduct;)Lscala/Option;
   #27 = Utf8               this
   #28 = Utf8               Lshapeless/ops/coproduct$Partition$$anon$9;
   #29 = Utf8               Lshapeless/Coproduct;
   #30 = Utf8               filterNot
   #31 = Utf8               filterNot$
   #32 = NameAndType        #31:#24       // filterNot$:(Lshapeless/ops/coproduct$Partition;Lshapeless/Coproduct;)Lscala/Option;
   #33 = InterfaceMethodref #7.#32        // shapeless/ops/coproduct$Partition.filterNot$:(Lshapeless/ops/coproduct$Partition;Lshapeless/Coproduct;)Lscala/Option;
   #34 = Utf8               apply
   #35 = Utf8               (Lshapeless/Coproduct;)Lscala/util/Either;
   #36 = Utf8               apply$
   #37 = Utf8               (Lshapeless/ops/coproduct$Partition;Lshapeless/Coproduct;)Lscala/util/Either;
   #38 = NameAndType        #36:#37       // apply$:(Lshapeless/ops/coproduct$Partition;Lshapeless/Coproduct;)Lscala/util/Either;
   #39 = InterfaceMethodref #7.#38        // shapeless/ops/coproduct$Partition.apply$:(Lshapeless/ops/coproduct$Partition;Lshapeless/Coproduct;)Lscala/util/Either;
   #40 = Utf8               coproduct
   #41 = Utf8               (Lshapeless/$colon$plus$colon;)Lshapeless/$colon$plus$colon;
   #42 = Utf8               (Lshapeless/$colon$plus$colon<TH;TT;>;)Lshapeless/$colon$plus$colon<TTPrefix;Lshapeless/$colon$plus$colon<Lshapeless/$colon$plus$colon<TH;TTSuffix;>;Lshapeless/CNil;>;>;
   #43 = Utf8               shapeless/Inl
   #44 = Class              #43           // shapeless/Inl
   #45 = Utf8               head
   #46 = Utf8               ()Ljava/lang/Object;
   #47 = NameAndType        #45:#46       // head:()Ljava/lang/Object;
   #48 = Methodref          #44.#47       // shapeless/Inl.head:()Ljava/lang/Object;
   #49 = Utf8               shapeless/Inr
   #50 = Class              #49           // shapeless/Inr
   #51 = Utf8               <init>
   #52 = Utf8               (Ljava/lang/Object;)V
   #53 = NameAndType        #51:#52       // "<init>":(Ljava/lang/Object;)V
   #54 = Methodref          #44.#53       // shapeless/Inl."<init>":(Ljava/lang/Object;)V
   #55 = Utf8               (Lshapeless/Coproduct;)V
   #56 = NameAndType        #51:#55       // "<init>":(Lshapeless/Coproduct;)V
   #57 = Methodref          #50.#56       // shapeless/Inr."<init>":(Lshapeless/Coproduct;)V
   #58 = Utf8               tail
   #59 = Utf8               ()Lshapeless/Coproduct;
   #60 = NameAndType        #58:#59       // tail:()Lshapeless/Coproduct;
   #61 = Methodref          #50.#60       // shapeless/Inr.tail:()Lshapeless/Coproduct;
   #62 = NameAndType        #18:#19       // partition$2:Lshapeless/ops/coproduct$Partition;
   #63 = Fieldref           #2.#62        // shapeless/ops/coproduct$Partition$$anon$9.partition$2:Lshapeless/ops/coproduct$Partition;
   #64 = Utf8               (Lshapeless/Coproduct;)Lshapeless/$colon$plus$colon;
   #65 = NameAndType        #40:#64       // coproduct:(Lshapeless/Coproduct;)Lshapeless/$colon$plus$colon;
   #66 = InterfaceMethodref #7.#65        // shapeless/ops/coproduct$Partition.coproduct:(Lshapeless/Coproduct;)Lshapeless/$colon$plus$colon;
   #67 = Utf8               shapeless/Coproduct
   #68 = Class              #67           // shapeless/Coproduct
   #69 = Utf8               shapeless/$colon$plus$colon
   #70 = Class              #69           // shapeless/$colon$plus$colon
   #71 = Utf8               shapeless/CNil
   #72 = Class              #71           // shapeless/CNil
   #73 = Utf8               scala/MatchError
   #74 = Class              #73           // scala/MatchError
   #75 = Methodref          #74.#53       // scala/MatchError."<init>":(Ljava/lang/Object;)V
   #76 = Utf8               h
   #77 = Utf8               Ljava/lang/Object;
   #78 = Utf8               t
   #79 = Utf8               Lshapeless/CNil;
   #80 = Utf8               Lshapeless/$colon$plus$colon;
   #81 = Utf8               (Ljava/lang/Object;)Ljava/lang/Object;
   #82 = NameAndType        #34:#35       // apply:(Lshapeless/Coproduct;)Lscala/util/Either;
   #83 = Methodref          #2.#82        // shapeless/ops/coproduct$Partition$$anon$9.apply:(Lshapeless/Coproduct;)Lscala/util/Either;
   #84 = NameAndType        #40:#41       // coproduct:(Lshapeless/$colon$plus$colon;)Lshapeless/$colon$plus$colon;
   #85 = Methodref          #2.#84        // shapeless/ops/coproduct$Partition$$anon$9.coproduct:(Lshapeless/$colon$plus$colon;)Lshapeless/$colon$plus$colon;
   #86 = Utf8               (Lshapeless/ops/coproduct$Partition;)V
   #87 = Utf8               ()V
   #88 = NameAndType        #51:#87       // "<init>":()V
   #89 = Methodref          #5.#88        // java/lang/Object."<init>":()V
   #90 = Utf8               $init$
   #91 = NameAndType        #90:#86       // $init$:(Lshapeless/ops/coproduct$Partition;)V
   #92 = InterfaceMethodref #7.#91        // shapeless/ops/coproduct$Partition.$init$:(Lshapeless/ops/coproduct$Partition;)V
   #93 = Utf8               Code
   #94 = Utf8               LineNumberTable
   #95 = Utf8               LocalVariableTable
   #96 = Utf8               MethodParameters
   #97 = Utf8               StackMapTable
   #98 = Utf8               Signature
   #99 = Utf8               InnerClasses
  #100 = Utf8               EnclosingMethod
  #101 = Utf8               SourceFile
  #102 = Utf8               ScalaInlineInfo
  #103 = Utf8               Scala
{
  private final shapeless.ops.coproduct$Partition partition$2;
    descriptor: Lshapeless/ops/coproduct$Partition;
    flags: (0x0012) ACC_PRIVATE, ACC_FINAL

  public scala.Option filter(shapeless.Coproduct);
    descriptor: (Lshapeless/Coproduct;)Lscala/Option;
    flags: (0x0001) ACC_PUBLIC
    Code:
      stack=2, locals=2, args_size=2
         0: aload_0
         1: aload_1
         2: invokestatic  #26                 // InterfaceMethod shapeless/ops/coproduct$Partition.filter$:(Lshapeless/ops/coproduct$Partition;Lshapeless/Coproduct;)Lscala/Option;
         5: areturn
      LineNumberTable:
        line 137: 0
      LocalVariableTable:
        Start  Length  Slot  Name   Signature
            0       6     0  this   Lshapeless/ops/coproduct$Partition$$anon$9;
            0       6     1     c   Lshapeless/Coproduct;
    MethodParameters:
      Name                           Flags
      c                              final

  public scala.Option filterNot(shapeless.Coproduct);
    descriptor: (Lshapeless/Coproduct;)Lscala/Option;
    flags: (0x0001) ACC_PUBLIC
    Code:
      stack=2, locals=2, args_size=2
         0: aload_0
         1: aload_1
         2: invokestatic  #33                 // InterfaceMethod shapeless/ops/coproduct$Partition.filterNot$:(Lshapeless/ops/coproduct$Partition;Lshapeless/Coproduct;)Lscala/Option;
         5: areturn
      LineNumberTable:
        line 137: 0
      LocalVariableTable:
        Start  Length  Slot  Name   Signature
            0       6     0  this   Lshapeless/ops/coproduct$Partition$$anon$9;
            0       6     1     c   Lshapeless/Coproduct;
    MethodParameters:
      Name                           Flags
      c                              final

  public scala.util.Either apply(shapeless.Coproduct);
    descriptor: (Lshapeless/Coproduct;)Lscala/util/Either;
    flags: (0x0001) ACC_PUBLIC
    Code:
      stack=2, locals=2, args_size=2
         0: aload_0
         1: aload_1
         2: invokestatic  #39                 // InterfaceMethod shapeless/ops/coproduct$Partition.apply$:(Lshapeless/ops/coproduct$Partition;Lshapeless/Coproduct;)Lscala/util/Either;
         5: areturn
      LineNumberTable:
        line 137: 0
      LocalVariableTable:
        Start  Length  Slot  Name   Signature
            0       6     0  this   Lshapeless/ops/coproduct$Partition$$anon$9;
            0       6     1     c   Lshapeless/Coproduct;
    MethodParameters:
      Name                           Flags
      c                              final

  public shapeless.$colon$plus$colon<TPrefix, shapeless.$colon$plus$colon<shapeless.$colon$plus$colon<H, TSuffix>, shapeless.CNil>> coproduct(shapeless.$colon$plus$colon<H, T>);
    descriptor: (Lshapeless/$colon$plus$colon;)Lshapeless/$colon$plus$colon;
    flags: (0x0001) ACC_PUBLIC
    Code:
      stack=7, locals=20, args_size=2
         0: aload_1
         1: astore        4
         3: aload         4
         5: instanceof    #44                 // class shapeless/Inl
         8: ifeq          52
        11: aload         4
        13: checkcast     #44                 // class shapeless/Inl
        16: astore        5
        18: aload         5
        20: invokevirtual #48                 // Method shapeless/Inl.head:()Ljava/lang/Object;
        23: astore        6
        25: new           #50                 // class shapeless/Inr
        28: dup
        29: new           #44                 // class shapeless/Inl
        32: dup
        33: new           #44                 // class shapeless/Inl
        36: dup
        37: aload         6
        39: invokespecial #54                 // Method shapeless/Inl."<init>":(Ljava/lang/Object;)V
        42: invokespecial #54                 // Method shapeless/Inl."<init>":(Ljava/lang/Object;)V
        45: invokespecial #57                 // Method shapeless/Inr."<init>":(Lshapeless/Coproduct;)V
        48: astore_2
        49: goto          317
        52: goto          55
        55: aload         4
        57: instanceof    #50                 // class shapeless/Inr
        60: ifeq          304
        63: aload         4
        65: checkcast     #50                 // class shapeless/Inr
        68: astore        7
        70: aload         7
        72: invokevirtual #61                 // Method shapeless/Inr.tail:()Lshapeless/Coproduct;
        75: astore        8
        77: iconst_0
        78: istore        9
        80: aconst_null
        81: astore        10
        83: aload_0
        84: getfield      #63                 // Field partition$2:Lshapeless/ops/coproduct$Partition;
        87: aload         8
        89: invokeinterface #66,  2           // InterfaceMethod shapeless/ops/coproduct$Partition.coproduct:(Lshapeless/Coproduct;)Lshapeless/$colon$plus$colon;
        94: astore        11
        96: aload         11
        98: instanceof    #44                 // class shapeless/Inl
       101: ifeq          134
       104: aload         11
       106: checkcast     #44                 // class shapeless/Inl
       109: astore        12
       111: aload         12
       113: invokevirtual #48                 // Method shapeless/Inl.head:()Ljava/lang/Object;
       116: checkcast     #68                 // class shapeless/Coproduct
       119: astore        13
       121: new           #44                 // class shapeless/Inl
       124: dup
       125: aload         13
       127: invokespecial #54                 // Method shapeless/Inl."<init>":(Ljava/lang/Object;)V
       130: astore_3
       131: goto          299
       134: goto          137
       137: aload         11
       139: instanceof    #50                 // class shapeless/Inr
       142: ifeq          220
       145: iconst_1
       146: istore        9
       148: aload         11
       150: checkcast     #50                 // class shapeless/Inr
       153: astore        10
       155: aload         10
       157: invokevirtual #61                 // Method shapeless/Inr.tail:()Lshapeless/Coproduct;
       160: checkcast     #70                 // class shapeless/$colon$plus$colon
       163: astore        14
       165: aload         14
       167: instanceof    #44                 // class shapeless/Inl
       170: ifeq          217
       173: aload         14
       175: checkcast     #44                 // class shapeless/Inl
       178: astore        15
       180: aload         15
       182: invokevirtual #48                 // Method shapeless/Inl.head:()Ljava/lang/Object;
       185: checkcast     #68                 // class shapeless/Coproduct
       188: astore        16
       190: new           #50                 // class shapeless/Inr
       193: dup
       194: new           #44                 // class shapeless/Inl
       197: dup
       198: new           #50                 // class shapeless/Inr
       201: dup
       202: aload         16
       204: invokespecial #57                 // Method shapeless/Inr."<init>":(Lshapeless/Coproduct;)V
       207: invokespecial #54                 // Method shapeless/Inl."<init>":(Ljava/lang/Object;)V
       210: invokespecial #57                 // Method shapeless/Inr."<init>":(Lshapeless/Coproduct;)V
       213: astore_3
       214: goto          299
       217: goto          223
       220: goto          223
       223: iload         9
       225: ifeq          286
       228: aload         10
       230: invokevirtual #61                 // Method shapeless/Inr.tail:()Lshapeless/Coproduct;
       233: checkcast     #70                 // class shapeless/$colon$plus$colon
       236: astore        17
       238: aload         17
       240: instanceof    #50                 // class shapeless/Inr
       243: ifeq          283
       246: aload         17
       248: checkcast     #50                 // class shapeless/Inr
       251: astore        18
       253: aload         18
       255: invokevirtual #61                 // Method shapeless/Inr.tail:()Lshapeless/Coproduct;
       258: checkcast     #72                 // class shapeless/CNil
       261: astore        19
       263: new           #50                 // class shapeless/Inr
       266: dup
       267: new           #50                 // class shapeless/Inr
       270: dup
       271: aload         19
       273: invokespecial #57                 // Method shapeless/Inr."<init>":(Lshapeless/Coproduct;)V
       276: invokespecial #57                 // Method shapeless/Inr."<init>":(Lshapeless/Coproduct;)V
       279: astore_3
       280: goto          299
       283: goto          289
       286: goto          289
       289: new           #74                 // class scala/MatchError
       292: dup
       293: aload         11
       295: invokespecial #75                 // Method scala/MatchError."<init>":(Ljava/lang/Object;)V
       298: athrow
       299: aload_3
       300: astore_2
       301: goto          317
       304: goto          307
       307: new           #74                 // class scala/MatchError
       310: dup
       311: aload         4
       313: invokespecial #75                 // Method scala/MatchError."<init>":(Ljava/lang/Object;)V
       316: athrow
       317: aload_2
       318: areturn
      StackMapTable: number_of_entries = 14
        frame_type = 254 /* append */
          offset_delta = 52
          locals = [ top, top, class shapeless/$colon$plus$colon ]
        frame_type = 2 /* same */
        frame_type = 255 /* full_frame */
          offset_delta = 78
          locals = [ class shapeless/ops/coproduct$Partition$$anon$9, class shapeless/$colon$plus$colon, top, top, class shapeless/$colon$plus$colon, top, top, class shapeless/Inr, class shapeless/Coproduct, int, null, class shapeless/$colon$plus$colon ]
          stack = []
        frame_type = 2 /* same */
        frame_type = 255 /* full_frame */
          offset_delta = 79
          locals = [ class shapeless/ops/coproduct$Partition$$anon$9, class shapeless/$colon$plus$colon, top, top, class shapeless/$colon$plus$colon, top, top, class shapeless/Inr, class shapeless/Coproduct, int, class shapeless/Inr, class shapeless/$colon$plus$colon, top, top, class shapeless/$colon$plus$colon ]
          stack = []
        frame_type = 255 /* full_frame */
          offset_delta = 2
          locals = [ class shapeless/ops/coproduct$Partition$$anon$9, class shapeless/$colon$plus$colon, top, top, class shapeless/$colon$plus$colon, top, top, class shapeless/Inr, class shapeless/Coproduct, int, null, class shapeless/$colon$plus$colon ]
          stack = []
        frame_type = 255 /* full_frame */
          offset_delta = 2
          locals = [ class shapeless/ops/coproduct$Partition$$anon$9, class shapeless/$colon$plus$colon, top, top, class shapeless/$colon$plus$colon, top, top, class shapeless/Inr, class shapeless/Coproduct, int, class shapeless/Inr, class shapeless/$colon$plus$colon ]
          stack = []
        frame_type = 255 /* full_frame */
          offset_delta = 59
          locals = [ class shapeless/ops/coproduct$Partition$$anon$9, class shapeless/$colon$plus$colon, top, top, class shapeless/$colon$plus$colon, top, top, class shapeless/Inr, class shapeless/Coproduct, int, class shapeless/Inr, class shapeless/$colon$plus$colon, top, top, top, top, top, class shapeless/$colon$plus$colon ]
          stack = []
        frame_type = 255 /* full_frame */
          offset_delta = 2
          locals = [ class shapeless/ops/coproduct$Partition$$anon$9, class shapeless/$colon$plus$colon, top, top, class shapeless/$colon$plus$colon, top, top, class shapeless/Inr, class shapeless/Coproduct, int, class shapeless/Inr, class shapeless/$colon$plus$colon ]
          stack = []
        frame_type = 2 /* same */
        frame_type = 255 /* full_frame */
          offset_delta = 9
          locals = [ class shapeless/ops/coproduct$Partition$$anon$9, class shapeless/$colon$plus$colon, top, class java/lang/Object, class shapeless/$colon$plus$colon, top, top, class shapeless/Inr, class shapeless/Coproduct, int, class shapeless/Inr, class shapeless/$colon$plus$colon ]
          stack = []
        frame_type = 255 /* full_frame */
          offset_delta = 4
          locals = [ class shapeless/ops/coproduct$Partition$$anon$9, class shapeless/$colon$plus$colon, top, top, class shapeless/$colon$plus$colon ]
          stack = []
        frame_type = 2 /* same */
        frame_type = 255 /* full_frame */
          offset_delta = 9
          locals = [ class shapeless/ops/coproduct$Partition$$anon$9, class shapeless/$colon$plus$colon, class java/lang/Object, top, class shapeless/$colon$plus$colon ]
          stack = []
      LineNumberTable:
        line 141: 0
        line 142: 3
        line 143: 55
        line 144: 96
        line 145: 137
        line 146: 223
        line 143: 289
        line 141: 307
      LocalVariableTable:
        Start  Length  Slot  Name   Signature
           23      29     6     h   Ljava/lang/Object;
          119      15    13     h   Lshapeless/Coproduct;
          188      29    16     t   Lshapeless/Coproduct;
          261      22    19     c   Lshapeless/CNil;
           75     229     8     t   Lshapeless/Coproduct;
            0     319     0  this   Lshapeless/ops/coproduct$Partition$$anon$9;
            0     319     1     c   Lshapeless/$colon$plus$colon;
    Signature: #42                          // (Lshapeless/$colon$plus$colon<TH;TT;>;)Lshapeless/$colon$plus$colon<TTPrefix;Lshapeless/$colon$plus$colon<Lshapeless/$colon$plus$colon<TH;TTSuffix;>;Lshapeless/CNil;>;>;
    MethodParameters:
      Name                           Flags
      c                              final

  public java.lang.Object apply(java.lang.Object);
    descriptor: (Ljava/lang/Object;)Ljava/lang/Object;
    flags: (0x1041) ACC_PUBLIC, ACC_BRIDGE, ACC_SYNTHETIC
    Code:
      stack=2, locals=2, args_size=2
         0: aload_0
         1: aload_1
         2: checkcast     #68                 // class shapeless/Coproduct
         5: invokevirtual #83                 // Method apply:(Lshapeless/Coproduct;)Lscala/util/Either;
         8: areturn
      LineNumberTable:
        line 137: 0
      LocalVariableTable:
        Start  Length  Slot  Name   Signature
            0       9     0  this   Lshapeless/ops/coproduct$Partition$$anon$9;
            0       9     1     t   Ljava/lang/Object;
    MethodParameters:
      Name                           Flags
      t                              final

  public shapeless.$colon$plus$colon coproduct(shapeless.Coproduct);
    descriptor: (Lshapeless/Coproduct;)Lshapeless/$colon$plus$colon;
    flags: (0x1041) ACC_PUBLIC, ACC_BRIDGE, ACC_SYNTHETIC
    Code:
      stack=2, locals=2, args_size=2
         0: aload_0
         1: aload_1
         2: checkcast     #70                 // class shapeless/$colon$plus$colon
         5: invokevirtual #85                 // Method coproduct:(Lshapeless/$colon$plus$colon;)Lshapeless/$colon$plus$colon;
         8: areturn
      LineNumberTable:
        line 137: 0
      LocalVariableTable:
        Start  Length  Slot  Name   Signature
            0       9     0  this   Lshapeless/ops/coproduct$Partition$$anon$9;
            0       9     1     c   Lshapeless/Coproduct;
    MethodParameters:
      Name                           Flags
      c                              final

  public shapeless.ops.coproduct$Partition$$anon$9(shapeless.ops.coproduct$Partition);
    descriptor: (Lshapeless/ops/coproduct$Partition;)V
    flags: (0x0001) ACC_PUBLIC
    Code:
      stack=2, locals=2, args_size=2
         0: aload_0
         1: aload_1
         2: putfield      #63                 // Field partition$2:Lshapeless/ops/coproduct$Partition;
         5: aload_0
         6: invokespecial #89                 // Method java/lang/Object."<init>":()V
         9: aload_0
        10: invokestatic  #92                 // InterfaceMethod shapeless/ops/coproduct$Partition.$init$:(Lshapeless/ops/coproduct$Partition;)V
        13: return
      LineNumberTable:
        line 136: 0
        line 137: 5
      LocalVariableTable:
        Start  Length  Slot  Name   Signature
            0      14     0  this   Lshapeless/ops/coproduct$Partition$$anon$9;
            0      14     1 partition$2   Lshapeless/ops/coproduct$Partition;
    MethodParameters:
      Name                           Flags
      partition$2                    final
}
InnerClasses:
  public static #16= #7 of #15;           // Partition=class shapeless/ops/coproduct$Partition of class shapeless/ops/coproduct
  public static #17= #10 of #15;          // Partition$=class shapeless/ops/coproduct$Partition$ of class shapeless/ops/coproduct
  public final #2;                        // class shapeless/ops/coproduct$Partition$$anon$9
EnclosingMethod: #10.#13                // shapeless.ops.coproduct$Partition$.coproductPartition_NonMatch
Signature: #3                           // Ljava/lang/Object;Lshapeless/ops/coproduct$Partition<Lshapeless/$colon$plus$colon<TH;TT;>;TU;>;
SourceFile: "coproduct.scala"
  ScalaInlineInfo: length = 0x27 (unknown attribute)
   01 01 00 07 00 33 00 56 01 00 22 00 51 01 00 22
   00 23 01 00 28 00 29 01 00 28 00 40 01 00 14 00
   15 01 00 1E 00 15 01
  Scala: length = 0x0 (unknown attribute)

