Classfile /Users/mw/Projects/slang-braindump/.jar/jar8/assemble/slang-braindump/assemble/content/shapeless/ops/coproduct$Basis$$anon$74.class
  Last modified May 29, 2022; size 1818 bytes
  SHA-256 checksum 664354d8a782e8c2c969e5b788fa51c5e50978791c4a39450088941283e3021b
  Compiled from "coproduct.scala"
public final class shapeless.ops.coproduct$Basis$$anon$74 extends java.lang.Object implements shapeless.ops.coproduct$Basis<Super, shapeless.CNil>
  minor version: 0
  major version: 52
  flags: (0x0031) ACC_PUBLIC, ACC_FINAL, ACC_SUPER
  this_class: #2                          // shapeless/ops/coproduct$Basis$$anon$74
  super_class: #5                         // java/lang/Object
  interfaces: 1, fields: 0, methods: 4, attributes: 6
Constant pool:
   #1 = Utf8               shapeless/ops/coproduct$Basis$$anon$74
   #2 = Class              #1             // shapeless/ops/coproduct$Basis$$anon$74
   #3 = Utf8               Ljava/lang/Object;Lshapeless/ops/coproduct$Basis<TSuper;Lshapeless/CNil;>;
   #4 = Utf8               java/lang/Object
   #5 = Class              #4             // java/lang/Object
   #6 = Utf8               shapeless/ops/coproduct$Basis
   #7 = Class              #6             // shapeless/ops/coproduct$Basis
   #8 = Utf8               coproduct.scala
   #9 = Utf8               shapeless/ops/coproduct$Basis$
  #10 = Class              #9             // shapeless/ops/coproduct$Basis$
  #11 = Utf8               cnilBasis
  #12 = Utf8               ()Lshapeless/ops/coproduct$Basis;
  #13 = NameAndType        #11:#12        // cnilBasis:()Lshapeless/ops/coproduct$Basis;
  #14 = Utf8               shapeless/ops/coproduct
  #15 = Class              #14            // shapeless/ops/coproduct
  #16 = Utf8               Basis
  #17 = Utf8               Basis$
  #18 = Utf8               apply
  #19 = Utf8               (Lshapeless/Coproduct;)Lscala/util/Left;
  #20 = Utf8               (TSuper;)Lscala/util/Left<TSuper;Lscala/runtime/Nothing$;>;
  #21 = Utf8               s
  #22 = Utf8               scala/package$
  #23 = Class              #22            // scala/package$
  #24 = Utf8               MODULE$
  #25 = Utf8               Lscala/package$;
  #26 = NameAndType        #24:#25        // MODULE$:Lscala/package$;
  #27 = Fieldref           #23.#26        // scala/package$.MODULE$:Lscala/package$;
  #28 = Utf8               Left
  #29 = Utf8               ()Lscala/util/Left$;
  #30 = NameAndType        #28:#29        // Left:()Lscala/util/Left$;
  #31 = Methodref          #23.#30        // scala/package$.Left:()Lscala/util/Left$;
  #32 = Utf8               scala/util/Left$
  #33 = Class              #32            // scala/util/Left$
  #34 = Utf8               (Ljava/lang/Object;)Lscala/util/Left;
  #35 = NameAndType        #18:#34        // apply:(Ljava/lang/Object;)Lscala/util/Left;
  #36 = Methodref          #33.#35        // scala/util/Left$.apply:(Ljava/lang/Object;)Lscala/util/Left;
  #37 = Utf8               this
  #38 = Utf8               Lshapeless/ops/coproduct$Basis$$anon$74;
  #39 = Utf8               Lshapeless/Coproduct;
  #40 = Utf8               inverse
  #41 = Utf8               (Lscala/util/Either;)Lshapeless/Coproduct;
  #42 = Utf8               (Lscala/util/Either<TSuper;Lshapeless/CNil;>;)TSuper;
  #43 = Utf8               e
  #44 = Utf8               scala/util/Left
  #45 = Class              #44            // scala/util/Left
  #46 = Utf8               value
  #47 = Utf8               ()Ljava/lang/Object;
  #48 = NameAndType        #46:#47        // value:()Ljava/lang/Object;
  #49 = Methodref          #45.#48        // scala/util/Left.value:()Ljava/lang/Object;
  #50 = Utf8               shapeless/Coproduct
  #51 = Class              #50            // shapeless/Coproduct
  #52 = Utf8               scala/MatchError
  #53 = Class              #52            // scala/MatchError
  #54 = Utf8               <init>
  #55 = Utf8               (Ljava/lang/Object;)V
  #56 = NameAndType        #54:#55        // "<init>":(Ljava/lang/Object;)V
  #57 = Methodref          #53.#56        // scala/MatchError."<init>":(Ljava/lang/Object;)V
  #58 = Utf8               l
  #59 = Utf8               Lscala/util/Either;
  #60 = Utf8               scala/util/Either
  #61 = Class              #60            // scala/util/Either
  #62 = Utf8               (Ljava/lang/Object;)Ljava/lang/Object;
  #63 = Utf8               t
  #64 = NameAndType        #18:#19        // apply:(Lshapeless/Coproduct;)Lscala/util/Left;
  #65 = Methodref          #2.#64         // shapeless/ops/coproduct$Basis$$anon$74.apply:(Lshapeless/Coproduct;)Lscala/util/Left;
  #66 = Utf8               Ljava/lang/Object;
  #67 = Utf8               ()V
  #68 = NameAndType        #54:#67        // "<init>":()V
  #69 = Methodref          #5.#68         // java/lang/Object."<init>":()V
  #70 = Utf8               Code
  #71 = Utf8               LineNumberTable
  #72 = Utf8               LocalVariableTable
  #73 = Utf8               Signature
  #74 = Utf8               MethodParameters
  #75 = Utf8               StackMapTable
  #76 = Utf8               InnerClasses
  #77 = Utf8               EnclosingMethod
  #78 = Utf8               SourceFile
  #79 = Utf8               ScalaInlineInfo
  #80 = Utf8               Scala
{
  public scala.util.Left<Super, scala.runtime.Nothing$> apply(Super);
    descriptor: (Lshapeless/Coproduct;)Lscala/util/Left;
    flags: (0x0001) ACC_PUBLIC
    Code:
      stack=2, locals=2, args_size=2
         0: getstatic     #27                 // Field scala/package$.MODULE$:Lscala/package$;
         3: invokevirtual #31                 // Method scala/package$.Left:()Lscala/util/Left$;
         6: aload_1
         7: invokevirtual #36                 // Method scala/util/Left$.apply:(Ljava/lang/Object;)Lscala/util/Left;
        10: areturn
      LineNumberTable:
        line 1193: 0
      LocalVariableTable:
        Start  Length  Slot  Name   Signature
            0      11     0  this   Lshapeless/ops/coproduct$Basis$$anon$74;
            0      11     1     s   Lshapeless/Coproduct;
    Signature: #20                          // (TSuper;)Lscala/util/Left<TSuper;Lscala/runtime/Nothing$;>;
    MethodParameters:
      Name                           Flags
      s                              final

  public Super inverse(scala.util.Either<Super, shapeless.CNil>);
    descriptor: (Lscala/util/Either;)Lshapeless/Coproduct;
    flags: (0x0001) ACC_PUBLIC
    Code:
      stack=3, locals=6, args_size=2
         0: aload_1
         1: astore_3
         2: aload_3
         3: instanceof    #45                 // class scala/util/Left
         6: ifeq          31
         9: aload_3
        10: checkcast     #45                 // class scala/util/Left
        13: astore        4
        15: aload         4
        17: invokevirtual #49                 // Method scala/util/Left.value:()Ljava/lang/Object;
        20: checkcast     #51                 // class shapeless/Coproduct
        23: astore        5
        25: aload         5
        27: astore_2
        28: goto          43
        31: goto          34
        34: new           #53                 // class scala/MatchError
        37: dup
        38: aload_3
        39: invokespecial #57                 // Method scala/MatchError."<init>":(Ljava/lang/Object;)V
        42: athrow
        43: aload_2
        44: areturn
      StackMapTable: number_of_entries = 3
        frame_type = 253 /* append */
          offset_delta = 31
          locals = [ top, class scala/util/Either ]
        frame_type = 2 /* same */
        frame_type = 255 /* full_frame */
          offset_delta = 8
          locals = [ class shapeless/ops/coproduct$Basis$$anon$74, class scala/util/Either, class shapeless/Coproduct, class scala/util/Either, class scala/util/Left, class shapeless/Coproduct ]
          stack = []
      LineNumberTable:
        line 1194: 0
        line 1195: 2
        line 1194: 34
      LocalVariableTable:
        Start  Length  Slot  Name   Signature
           23       8     5     l   Lshapeless/Coproduct;
            0      45     0  this   Lshapeless/ops/coproduct$Basis$$anon$74;
            0      45     1     e   Lscala/util/Either;
    Signature: #42                          // (Lscala/util/Either<TSuper;Lshapeless/CNil;>;)TSuper;
    MethodParameters:
      Name                           Flags
      e                              final

  public java.lang.Object apply(java.lang.Object);
    descriptor: (Ljava/lang/Object;)Ljava/lang/Object;
    flags: (0x1041) ACC_PUBLIC, ACC_BRIDGE, ACC_SYNTHETIC
    Code:
      stack=2, locals=2, args_size=2
         0: aload_0
         1: aload_1
         2: checkcast     #51                 // class shapeless/Coproduct
         5: invokevirtual #65                 // Method apply:(Lshapeless/Coproduct;)Lscala/util/Left;
         8: areturn
      LineNumberTable:
        line 1191: 0
      LocalVariableTable:
        Start  Length  Slot  Name   Signature
            0       9     0  this   Lshapeless/ops/coproduct$Basis$$anon$74;
            0       9     1     t   Ljava/lang/Object;
    MethodParameters:
      Name                           Flags
      t                              final

  public shapeless.ops.coproduct$Basis$$anon$74();
    descriptor: ()V
    flags: (0x0001) ACC_PUBLIC
    Code:
      stack=1, locals=1, args_size=1
         0: aload_0
         1: invokespecial #69                 // Method java/lang/Object."<init>":()V
         4: return
      LineNumberTable:
        line 1191: 0
      LocalVariableTable:
        Start  Length  Slot  Name   Signature
            0       5     0  this   Lshapeless/ops/coproduct$Basis$$anon$74;
}
InnerClasses:
  public static #16= #7 of #15;           // Basis=class shapeless/ops/coproduct$Basis of class shapeless/ops/coproduct
  public static #17= #10 of #15;          // Basis$=class shapeless/ops/coproduct$Basis$ of class shapeless/ops/coproduct
  public final #2;                        // class shapeless/ops/coproduct$Basis$$anon$74
EnclosingMethod: #10.#13                // shapeless.ops.coproduct$Basis$.cnilBasis
Signature: #3                           // Ljava/lang/Object;Lshapeless/ops/coproduct$Basis<TSuper;Lshapeless/CNil;>;
SourceFile: "coproduct.scala"
  ScalaInlineInfo: length = 0x18 (unknown attribute)
   01 01 00 04 00 36 00 43 01 00 12 00 3E 01 00 12
   00 13 01 00 28 00 29 01
  Scala: length = 0x0 (unknown attribute)

