Classfile /Users/mw/Projects/slang-braindump/.jar/jar8/assemble/slang-braindump/assemble/content/shapeless/ops/coproduct$FlatMap$$anon$17.class
  Last modified May 29, 2022; size 2498 bytes
  SHA-256 checksum 1531af2cdeb581ffbd6bc297a9ffd15c86294fc60d3ec00cb6e8755e5a99c3d1
  Compiled from "coproduct.scala"
public final class shapeless.ops.coproduct$FlatMap$$anon$17 extends java.lang.Object implements shapeless.ops.coproduct$FlatMap<shapeless.$colon$plus$colon<H, T>, F>
  minor version: 0
  major version: 52
  flags: (0x0031) ACC_PUBLIC, ACC_FINAL, ACC_SUPER
  this_class: #2                          // shapeless/ops/coproduct$FlatMap$$anon$17
  super_class: #5                         // java/lang/Object
  interfaces: 1, fields: 3, methods: 3, attributes: 6
Constant pool:
    #1 = Utf8               shapeless/ops/coproduct$FlatMap$$anon$17
    #2 = Class              #1            // shapeless/ops/coproduct$FlatMap$$anon$17
    #3 = Utf8               Ljava/lang/Object;Lshapeless/ops/coproduct$FlatMap<Lshapeless/$colon$plus$colon<TH;TT;>;TF;>;
    #4 = Utf8               java/lang/Object
    #5 = Class              #4            // java/lang/Object
    #6 = Utf8               shapeless/ops/coproduct$FlatMap
    #7 = Class              #6            // shapeless/ops/coproduct$FlatMap
    #8 = Utf8               coproduct.scala
    #9 = Utf8               shapeless/ops/coproduct$FlatMap$
   #10 = Class              #9            // shapeless/ops/coproduct$FlatMap$
   #11 = Utf8               cpFlatMap
   #12 = Utf8               (Lshapeless/PolyDefns$Case;Lshapeless/ops/coproduct$FlatMap;Lshapeless/ops/coproduct$ExtendBy;)Lshapeless/ops/coproduct$FlatMap;
   #13 = NameAndType        #11:#12       // cpFlatMap:(Lshapeless/PolyDefns$Case;Lshapeless/ops/coproduct$FlatMap;Lshapeless/ops/coproduct$ExtendBy;)Lshapeless/ops/coproduct$FlatMap;
   #14 = Utf8               shapeless/PolyDefns$Case
   #15 = Class              #14           // shapeless/PolyDefns$Case
   #16 = Utf8               shapeless/PolyDefns
   #17 = Class              #16           // shapeless/PolyDefns
   #18 = Utf8               Case
   #19 = Utf8               shapeless/ops/coproduct$ExtendBy
   #20 = Class              #19           // shapeless/ops/coproduct$ExtendBy
   #21 = Utf8               shapeless/ops/coproduct
   #22 = Class              #21           // shapeless/ops/coproduct
   #23 = Utf8               ExtendBy
   #24 = Utf8               FlatMap
   #25 = Utf8               FlatMap$
   #26 = Utf8               extendBy$1
   #27 = Utf8               Lshapeless/ops/coproduct$ExtendBy;
   #28 = Utf8               fh$1
   #29 = Utf8               Lshapeless/PolyDefns$Case;
   #30 = Utf8               ft$1
   #31 = Utf8               Lshapeless/ops/coproduct$FlatMap;
   #32 = Utf8               apply
   #33 = Utf8               (Lshapeless/$colon$plus$colon;)Lshapeless/Coproduct;
   #34 = Utf8               (Lshapeless/$colon$plus$colon<TH;TT;>;)Lshapeless/Coproduct;
   #35 = Utf8               c
   #36 = Utf8               shapeless/Inl
   #37 = Class              #36           // shapeless/Inl
   #38 = Utf8               head
   #39 = Utf8               ()Ljava/lang/Object;
   #40 = NameAndType        #38:#39       // head:()Ljava/lang/Object;
   #41 = Methodref          #37.#40       // shapeless/Inl.head:()Ljava/lang/Object;
   #42 = NameAndType        #26:#27       // extendBy$1:Lshapeless/ops/coproduct$ExtendBy;
   #43 = Fieldref           #2.#42        // shapeless/ops/coproduct$FlatMap$$anon$17.extendBy$1:Lshapeless/ops/coproduct$ExtendBy;
   #44 = NameAndType        #28:#29       // fh$1:Lshapeless/PolyDefns$Case;
   #45 = Fieldref           #2.#44        // shapeless/ops/coproduct$FlatMap$$anon$17.fh$1:Lshapeless/PolyDefns$Case;
   #46 = Utf8               scala/$less$colon$less$
   #47 = Class              #46           // scala/$less$colon$less$
   #48 = Utf8               MODULE$
   #49 = Utf8               Lscala/$less$colon$less$;
   #50 = NameAndType        #48:#49       // MODULE$:Lscala/$less$colon$less$;
   #51 = Fieldref           #47.#50       // scala/$less$colon$less$.MODULE$:Lscala/$less$colon$less$;
   #52 = Utf8               refl
   #53 = Utf8               ()Lscala/$eq$colon$eq;
   #54 = NameAndType        #52:#53       // refl:()Lscala/$eq$colon$eq;
   #55 = Methodref          #47.#54       // scala/$less$colon$less$.refl:()Lscala/$eq$colon$eq;
   #56 = Utf8               (Ljava/lang/Object;Lscala/$eq$colon$eq;)Ljava/lang/Object;
   #57 = NameAndType        #32:#56       // apply:(Ljava/lang/Object;Lscala/$eq$colon$eq;)Ljava/lang/Object;
   #58 = Methodref          #15.#57       // shapeless/PolyDefns$Case.apply:(Ljava/lang/Object;Lscala/$eq$colon$eq;)Ljava/lang/Object;
   #59 = Utf8               shapeless/Coproduct
   #60 = Class              #59           // shapeless/Coproduct
   #61 = Utf8               right
   #62 = Utf8               (Lshapeless/Coproduct;)Lshapeless/Coproduct;
   #63 = NameAndType        #61:#62       // right:(Lshapeless/Coproduct;)Lshapeless/Coproduct;
   #64 = InterfaceMethodref #20.#63       // shapeless/ops/coproduct$ExtendBy.right:(Lshapeless/Coproduct;)Lshapeless/Coproduct;
   #65 = Utf8               shapeless/Inr
   #66 = Class              #65           // shapeless/Inr
   #67 = Utf8               tail
   #68 = Utf8               ()Lshapeless/Coproduct;
   #69 = NameAndType        #67:#68       // tail:()Lshapeless/Coproduct;
   #70 = Methodref          #66.#69       // shapeless/Inr.tail:()Lshapeless/Coproduct;
   #71 = NameAndType        #30:#31       // ft$1:Lshapeless/ops/coproduct$FlatMap;
   #72 = Fieldref           #2.#71        // shapeless/ops/coproduct$FlatMap$$anon$17.ft$1:Lshapeless/ops/coproduct$FlatMap;
   #73 = Utf8               (Ljava/lang/Object;)Ljava/lang/Object;
   #74 = NameAndType        #32:#73       // apply:(Ljava/lang/Object;)Ljava/lang/Object;
   #75 = InterfaceMethodref #7.#74        // shapeless/ops/coproduct$FlatMap.apply:(Ljava/lang/Object;)Ljava/lang/Object;
   #76 = Utf8               left
   #77 = NameAndType        #76:#62       // left:(Lshapeless/Coproduct;)Lshapeless/Coproduct;
   #78 = InterfaceMethodref #20.#77       // shapeless/ops/coproduct$ExtendBy.left:(Lshapeless/Coproduct;)Lshapeless/Coproduct;
   #79 = Utf8               scala/MatchError
   #80 = Class              #79           // scala/MatchError
   #81 = Utf8               <init>
   #82 = Utf8               (Ljava/lang/Object;)V
   #83 = NameAndType        #81:#82       // "<init>":(Ljava/lang/Object;)V
   #84 = Methodref          #80.#83       // scala/MatchError."<init>":(Ljava/lang/Object;)V
   #85 = Utf8               h
   #86 = Utf8               Ljava/lang/Object;
   #87 = Utf8               t
   #88 = Utf8               Lshapeless/Coproduct;
   #89 = Utf8               this
   #90 = Utf8               Lshapeless/ops/coproduct$FlatMap$$anon$17;
   #91 = Utf8               Lshapeless/$colon$plus$colon;
   #92 = Utf8               shapeless/$colon$plus$colon
   #93 = Class              #92           // shapeless/$colon$plus$colon
   #94 = NameAndType        #32:#33       // apply:(Lshapeless/$colon$plus$colon;)Lshapeless/Coproduct;
   #95 = Methodref          #2.#94        // shapeless/ops/coproduct$FlatMap$$anon$17.apply:(Lshapeless/$colon$plus$colon;)Lshapeless/Coproduct;
   #96 = Utf8               (Lshapeless/ops/coproduct$ExtendBy;Lshapeless/PolyDefns$Case;Lshapeless/ops/coproduct$FlatMap;)V
   #97 = Utf8               ()V
   #98 = NameAndType        #81:#97       // "<init>":()V
   #99 = Methodref          #5.#98        // java/lang/Object."<init>":()V
  #100 = Utf8               Code
  #101 = Utf8               StackMapTable
  #102 = Utf8               LineNumberTable
  #103 = Utf8               LocalVariableTable
  #104 = Utf8               Signature
  #105 = Utf8               MethodParameters
  #106 = Utf8               InnerClasses
  #107 = Utf8               EnclosingMethod
  #108 = Utf8               SourceFile
  #109 = Utf8               ScalaInlineInfo
  #110 = Utf8               Scala
{
  private final shapeless.ops.coproduct$ExtendBy extendBy$1;
    descriptor: Lshapeless/ops/coproduct$ExtendBy;
    flags: (0x0012) ACC_PRIVATE, ACC_FINAL

  private final shapeless.PolyDefns$Case fh$1;
    descriptor: Lshapeless/PolyDefns$Case;
    flags: (0x0012) ACC_PRIVATE, ACC_FINAL

  private final shapeless.ops.coproduct$FlatMap ft$1;
    descriptor: Lshapeless/ops/coproduct$FlatMap;
    flags: (0x0012) ACC_PRIVATE, ACC_FINAL

  public shapeless.Coproduct apply(shapeless.$colon$plus$colon<H, T>);
    descriptor: (Lshapeless/$colon$plus$colon;)Lshapeless/Coproduct;
    flags: (0x0001) ACC_PUBLIC
    Code:
      stack=4, locals=8, args_size=2
         0: aload_1
         1: astore_3
         2: aload_3
         3: instanceof    #37                 // class shapeless/Inl
         6: ifeq          53
         9: aload_3
        10: checkcast     #37                 // class shapeless/Inl
        13: astore        4
        15: aload         4
        17: invokevirtual #41                 // Method shapeless/Inl.head:()Ljava/lang/Object;
        20: astore        5
        22: aload_0
        23: getfield      #43                 // Field extendBy$1:Lshapeless/ops/coproduct$ExtendBy;
        26: aload_0
        27: getfield      #45                 // Field fh$1:Lshapeless/PolyDefns$Case;
        30: aload         5
        32: getstatic     #51                 // Field scala/$less$colon$less$.MODULE$:Lscala/$less$colon$less$;
        35: invokevirtual #55                 // Method scala/$less$colon$less$.refl:()Lscala/$eq$colon$eq;
        38: invokevirtual #58                 // Method shapeless/PolyDefns$Case.apply:(Ljava/lang/Object;Lscala/$eq$colon$eq;)Ljava/lang/Object;
        41: checkcast     #60                 // class shapeless/Coproduct
        44: invokeinterface #64,  2           // InterfaceMethod shapeless/ops/coproduct$ExtendBy.right:(Lshapeless/Coproduct;)Lshapeless/Coproduct;
        49: astore_2
        50: goto          115
        53: goto          56
        56: aload_3
        57: instanceof    #66                 // class shapeless/Inr
        60: ifeq          103
        63: aload_3
        64: checkcast     #66                 // class shapeless/Inr
        67: astore        6
        69: aload         6
        71: invokevirtual #70                 // Method shapeless/Inr.tail:()Lshapeless/Coproduct;
        74: astore        7
        76: aload_0
        77: getfield      #43                 // Field extendBy$1:Lshapeless/ops/coproduct$ExtendBy;
        80: aload_0
        81: getfield      #72                 // Field ft$1:Lshapeless/ops/coproduct$FlatMap;
        84: aload         7
        86: invokeinterface #75,  2           // InterfaceMethod shapeless/ops/coproduct$FlatMap.apply:(Ljava/lang/Object;)Ljava/lang/Object;
        91: checkcast     #60                 // class shapeless/Coproduct
        94: invokeinterface #78,  2           // InterfaceMethod shapeless/ops/coproduct$ExtendBy.left:(Lshapeless/Coproduct;)Lshapeless/Coproduct;
        99: astore_2
       100: goto          115
       103: goto          106
       106: new           #80                 // class scala/MatchError
       109: dup
       110: aload_3
       111: invokespecial #84                 // Method scala/MatchError."<init>":(Ljava/lang/Object;)V
       114: athrow
       115: aload_2
       116: areturn
      StackMapTable: number_of_entries = 5
        frame_type = 253 /* append */
          offset_delta = 53
          locals = [ top, class shapeless/$colon$plus$colon ]
        frame_type = 2 /* same */
        frame_type = 46 /* same */
        frame_type = 2 /* same */
        frame_type = 255 /* full_frame */
          offset_delta = 8
          locals = [ class shapeless/ops/coproduct$FlatMap$$anon$17, class shapeless/$colon$plus$colon, class shapeless/Coproduct, class shapeless/$colon$plus$colon ]
          stack = []
      LineNumberTable:
        line 304: 0
        line 305: 2
        line 306: 56
        line 304: 106
      LocalVariableTable:
        Start  Length  Slot  Name   Signature
           20      33     5     h   Ljava/lang/Object;
           74      29     7     t   Lshapeless/Coproduct;
            0     117     0  this   Lshapeless/ops/coproduct$FlatMap$$anon$17;
            0     117     1     c   Lshapeless/$colon$plus$colon;
    Signature: #34                          // (Lshapeless/$colon$plus$colon<TH;TT;>;)Lshapeless/Coproduct;
    MethodParameters:
      Name                           Flags
      c                              final

  public java.lang.Object apply(java.lang.Object);
    descriptor: (Ljava/lang/Object;)Ljava/lang/Object;
    flags: (0x1041) ACC_PUBLIC, ACC_BRIDGE, ACC_SYNTHETIC
    Code:
      stack=2, locals=2, args_size=2
         0: aload_0
         1: aload_1
         2: checkcast     #93                 // class shapeless/$colon$plus$colon
         5: invokevirtual #95                 // Method apply:(Lshapeless/$colon$plus$colon;)Lshapeless/Coproduct;
         8: areturn
      LineNumberTable:
        line 301: 0
      LocalVariableTable:
        Start  Length  Slot  Name   Signature
            0       9     0  this   Lshapeless/ops/coproduct$FlatMap$$anon$17;
            0       9     1     t   Ljava/lang/Object;
    MethodParameters:
      Name                           Flags
      t                              final

  public shapeless.ops.coproduct$FlatMap$$anon$17(shapeless.ops.coproduct$ExtendBy, shapeless.PolyDefns$Case, shapeless.ops.coproduct$FlatMap);
    descriptor: (Lshapeless/ops/coproduct$ExtendBy;Lshapeless/PolyDefns$Case;Lshapeless/ops/coproduct$FlatMap;)V
    flags: (0x0001) ACC_PUBLIC
    Code:
      stack=2, locals=4, args_size=4
         0: aload_0
         1: aload_1
         2: putfield      #43                 // Field extendBy$1:Lshapeless/ops/coproduct$ExtendBy;
         5: aload_0
         6: aload_2
         7: putfield      #45                 // Field fh$1:Lshapeless/PolyDefns$Case;
        10: aload_0
        11: aload_3
        12: putfield      #72                 // Field ft$1:Lshapeless/ops/coproduct$FlatMap;
        15: aload_0
        16: invokespecial #99                 // Method java/lang/Object."<init>":()V
        19: return
      LineNumberTable:
        line 300: 0
        line 298: 5
        line 299: 10
        line 301: 15
      LocalVariableTable:
        Start  Length  Slot  Name   Signature
            0      20     0  this   Lshapeless/ops/coproduct$FlatMap$$anon$17;
            0      20     1 extendBy$1   Lshapeless/ops/coproduct$ExtendBy;
            0      20     2  fh$1   Lshapeless/PolyDefns$Case;
            0      20     3  ft$1   Lshapeless/ops/coproduct$FlatMap;
    MethodParameters:
      Name                           Flags
      extendBy$1                     final
      fh$1                           final
      ft$1                           final
}
InnerClasses:
  public static abstract #18= #15 of #17; // Case=class shapeless/PolyDefns$Case of class shapeless/PolyDefns
  public static #23= #20 of #22;          // ExtendBy=class shapeless/ops/coproduct$ExtendBy of class shapeless/ops/coproduct
  public static #24= #7 of #22;           // FlatMap=class shapeless/ops/coproduct$FlatMap of class shapeless/ops/coproduct
  public static #25= #10 of #22;          // FlatMap$=class shapeless/ops/coproduct$FlatMap$ of class shapeless/ops/coproduct
  public final #2;                        // class shapeless/ops/coproduct$FlatMap$$anon$17
EnclosingMethod: #10.#13                // shapeless.ops.coproduct$FlatMap$.cpFlatMap
Signature: #3                           // Ljava/lang/Object;Lshapeless/ops/coproduct$FlatMap<Lshapeless/$colon$plus$colon<TH;TT;>;TF;>;
SourceFile: "coproduct.scala"
  ScalaInlineInfo: length = 0x13 (unknown attribute)
   01 01 00 03 00 51 00 60 01 00 20 00 49 01 00 20
   00 21 01
  Scala: length = 0x0 (unknown attribute)

