Classfile /Users/mw/Projects/slang-braindump/.jar/jar8/assemble/slang-braindump/assemble/content/shapeless/ops/coproduct$Unifier$.class
  Last modified May 29, 2022; size 2121 bytes
  SHA-256 checksum 41f113e62e6d3219bec8920089a819a6227a876eecea5dd138eb4595c9d8133f
  Compiled from "coproduct.scala"
public class shapeless.ops.coproduct$Unifier$ implements java.io.Serializable
  minor version: 0
  major version: 52
  flags: (0x0021) ACC_PUBLIC, ACC_SUPER
  this_class: #2                          // shapeless/ops/coproduct$Unifier$
  super_class: #4                         // java/lang/Object
  interfaces: 1, fields: 1, methods: 6, attributes: 4
Constant pool:
   #1 = Utf8               shapeless/ops/coproduct$Unifier$
   #2 = Class              #1             // shapeless/ops/coproduct$Unifier$
   #3 = Utf8               java/lang/Object
   #4 = Class              #3             // java/lang/Object
   #5 = Utf8               java/io/Serializable
   #6 = Class              #5             // java/io/Serializable
   #7 = Utf8               coproduct.scala
   #8 = Utf8               shapeless/ops/coproduct$Unifier
   #9 = Class              #8             // shapeless/ops/coproduct$Unifier
  #10 = Utf8               shapeless/ops/coproduct
  #11 = Class              #10            // shapeless/ops/coproduct
  #12 = Utf8               Unifier
  #13 = Utf8               Unifier$
  #14 = Utf8               shapeless/ops/coproduct$Unifier$$anon$20
  #15 = Class              #14            // shapeless/ops/coproduct$Unifier$$anon$20
  #16 = Utf8               shapeless/ops/coproduct$Unifier$$anon$21
  #17 = Class              #16            // shapeless/ops/coproduct$Unifier$$anon$21
  #18 = Utf8               MODULE$
  #19 = Utf8               Lshapeless/ops/coproduct$Unifier$;
  #20 = Utf8               <clinit>
  #21 = Utf8               ()V
  #22 = Utf8               <init>
  #23 = NameAndType        #22:#21        // "<init>":()V
  #24 = Methodref          #2.#23         // shapeless/ops/coproduct$Unifier$."<init>":()V
  #25 = NameAndType        #18:#19        // MODULE$:Lshapeless/ops/coproduct$Unifier$;
  #26 = Fieldref           #2.#25         // shapeless/ops/coproduct$Unifier$.MODULE$:Lshapeless/ops/coproduct$Unifier$;
  #27 = Utf8               apply
  #28 = Utf8               (Lshapeless/ops/coproduct$Unifier;)Lshapeless/ops/coproduct$Unifier;
  #29 = Utf8               <C::Lshapeless/Coproduct;>(Lshapeless/ops/coproduct$Unifier<TC;>;)Lshapeless/ops/coproduct$Unifier<TC;>;
  #30 = Utf8               unifier
  #31 = Utf8               this
  #32 = Utf8               Lshapeless/ops/coproduct$Unifier;
  #33 = Utf8               lstUnifier
  #34 = Utf8               ()Lshapeless/ops/coproduct$Unifier;
  #35 = Utf8               <H:Ljava/lang/Object;>()Lshapeless/ops/coproduct$Unifier<Lshapeless/$colon$plus$colon<TH;Lshapeless/CNil;>;>;
  #36 = Methodref          #15.#23        // shapeless/ops/coproduct$Unifier$$anon$20."<init>":()V
  #37 = Utf8               cpUnifier
  #38 = Utf8               (Lshapeless/ops/coproduct$Unifier;Lshapeless/Lub;)Lshapeless/ops/coproduct$Unifier;
  #39 = Utf8               <H1:Ljava/lang/Object;H2:Ljava/lang/Object;T::Lshapeless/Coproduct;L:Ljava/lang/Object;Out0:Ljava/lang/Object;>(Lshapeless/ops/coproduct$Unifier<Lshapeless/$colon$plus$colon<TH2;TT;>;>;Lshapeless/Lub<TH1;TL;TOut0;>;)Lshapeless/ops/coproduct$Unifier<Lshapeless/$colon$plus$colon<TH1;Lshapeless/$colon$plus$colon<TH2;TT;>;>;>;
  #40 = Utf8               lt
  #41 = Utf8               u
  #42 = Utf8               (Lshapeless/Lub;Lshapeless/ops/coproduct$Unifier;)V
  #43 = NameAndType        #22:#42        // "<init>":(Lshapeless/Lub;Lshapeless/ops/coproduct$Unifier;)V
  #44 = Methodref          #17.#43        // shapeless/ops/coproduct$Unifier$$anon$21."<init>":(Lshapeless/Lub;Lshapeless/ops/coproduct$Unifier;)V
  #45 = Utf8               Lshapeless/Lub;
  #46 = Utf8               writeReplace
  #47 = Utf8               ()Ljava/lang/Object;
  #48 = Utf8               scala/runtime/ModuleSerializationProxy
  #49 = Class              #48            // scala/runtime/ModuleSerializationProxy
  #50 = Utf8               (Ljava/lang/Class;)V
  #51 = NameAndType        #22:#50        // "<init>":(Ljava/lang/Class;)V
  #52 = Methodref          #49.#51        // scala/runtime/ModuleSerializationProxy."<init>":(Ljava/lang/Class;)V
  #53 = Methodref          #4.#23         // java/lang/Object."<init>":()V
  #54 = Utf8               Code
  #55 = Utf8               LineNumberTable
  #56 = Utf8               LocalVariableTable
  #57 = Utf8               Signature
  #58 = Utf8               MethodParameters
  #59 = Utf8               InnerClasses
  #60 = Utf8               SourceFile
  #61 = Utf8               ScalaInlineInfo
  #62 = Utf8               Scala
{
  public static final shapeless.ops.coproduct$Unifier$ MODULE$;
    descriptor: Lshapeless/ops/coproduct$Unifier$;
    flags: (0x0019) ACC_PUBLIC, ACC_STATIC, ACC_FINAL

  public static {};
    descriptor: ()V
    flags: (0x0009) ACC_PUBLIC, ACC_STATIC
    Code:
      stack=2, locals=0, args_size=0
         0: new           #2                  // class shapeless/ops/coproduct$Unifier$
         3: dup
         4: invokespecial #24                 // Method "<init>":()V
         7: putstatic     #26                 // Field MODULE$:Lshapeless/ops/coproduct$Unifier$;
        10: return
      LineNumberTable:
        line 338: 0

  public <C extends shapeless.Coproduct> shapeless.ops.coproduct$Unifier<C> apply(shapeless.ops.coproduct$Unifier<C>);
    descriptor: (Lshapeless/ops/coproduct$Unifier;)Lshapeless/ops/coproduct$Unifier;
    flags: (0x0001) ACC_PUBLIC
    Code:
      stack=1, locals=2, args_size=2
         0: aload_1
         1: areturn
      LineNumberTable:
        line 339: 0
      LocalVariableTable:
        Start  Length  Slot  Name   Signature
            0       2     0  this   Lshapeless/ops/coproduct$Unifier$;
            0       2     1 unifier   Lshapeless/ops/coproduct$Unifier;
    Signature: #29                          // <C::Lshapeless/Coproduct;>(Lshapeless/ops/coproduct$Unifier<TC;>;)Lshapeless/ops/coproduct$Unifier<TC;>;
    MethodParameters:
      Name                           Flags
      unifier                        final

  public <H extends java.lang.Object> shapeless.ops.coproduct$Unifier<shapeless.$colon$plus$colon<H, shapeless.CNil>> lstUnifier();
    descriptor: ()Lshapeless/ops/coproduct$Unifier;
    flags: (0x0001) ACC_PUBLIC
    Code:
      stack=2, locals=1, args_size=1
         0: new           #15                 // class shapeless/ops/coproduct$Unifier$$anon$20
         3: dup
         4: invokespecial #36                 // Method shapeless/ops/coproduct$Unifier$$anon$20."<init>":()V
         7: areturn
      LineNumberTable:
        line 344: 0
      LocalVariableTable:
        Start  Length  Slot  Name   Signature
            0       8     0  this   Lshapeless/ops/coproduct$Unifier$;
    Signature: #35                          // <H:Ljava/lang/Object;>()Lshapeless/ops/coproduct$Unifier<Lshapeless/$colon$plus$colon<TH;Lshapeless/CNil;>;>;

  public <H1 extends java.lang.Object, H2 extends java.lang.Object, T extends shapeless.Coproduct, L extends java.lang.Object, Out0 extends java.lang.Object> shapeless.ops.coproduct$Unifier<shapeless.$colon$plus$colon<H1, shapeless.$colon$plus$colon<H2, T>>> cpUnifier(shapeless.ops.coproduct$Unifier<shapeless.$colon$plus$colon<H2, T>>, shapeless.Lub<H1, L, Out0>);
    descriptor: (Lshapeless/ops/coproduct$Unifier;Lshapeless/Lub;)Lshapeless/ops/coproduct$Unifier;
    flags: (0x0001) ACC_PUBLIC
    Code:
      stack=4, locals=3, args_size=3
         0: new           #17                 // class shapeless/ops/coproduct$Unifier$$anon$21
         3: dup
         4: aload_2
         5: aload_1
         6: invokespecial #44                 // Method shapeless/ops/coproduct$Unifier$$anon$21."<init>":(Lshapeless/Lub;Lshapeless/ops/coproduct$Unifier;)V
         9: areturn
      LineNumberTable:
        line 353: 0
      LocalVariableTable:
        Start  Length  Slot  Name   Signature
            0      10     0  this   Lshapeless/ops/coproduct$Unifier$;
            0      10     1    lt   Lshapeless/ops/coproduct$Unifier;
            0      10     2     u   Lshapeless/Lub;
    Signature: #39                          // <H1:Ljava/lang/Object;H2:Ljava/lang/Object;T::Lshapeless/Coproduct;L:Ljava/lang/Object;Out0:Ljava/lang/Object;>(Lshapeless/ops/coproduct$Unifier<Lshapeless/$colon$plus$colon<TH2;TT;>;>;Lshapeless/Lub<TH1;TL;TOut0;>;)Lshapeless/ops/coproduct$Unifier<Lshapeless/$colon$plus$colon<TH1;Lshapeless/$colon$plus$colon<TH2;TT;>;>;>;
    MethodParameters:
      Name                           Flags
      lt                             final
      u                              final

  private java.lang.Object writeReplace();
    descriptor: ()Ljava/lang/Object;
    flags: (0x0002) ACC_PRIVATE
    Code:
      stack=3, locals=1, args_size=1
         0: new           #49                 // class scala/runtime/ModuleSerializationProxy
         3: dup
         4: ldc           #2                  // class shapeless/ops/coproduct$Unifier$
         6: invokespecial #52                 // Method scala/runtime/ModuleSerializationProxy."<init>":(Ljava/lang/Class;)V
         9: areturn
      LineNumberTable:
        line 338: 0
      LocalVariableTable:
        Start  Length  Slot  Name   Signature
            0      10     0  this   Lshapeless/ops/coproduct$Unifier$;

  public shapeless.ops.coproduct$Unifier$();
    descriptor: ()V
    flags: (0x0001) ACC_PUBLIC
    Code:
      stack=1, locals=1, args_size=1
         0: aload_0
         1: invokespecial #53                 // Method java/lang/Object."<init>":()V
         4: return
      LineNumberTable:
        line 362: 0
        line 338: 4
      LocalVariableTable:
        Start  Length  Slot  Name   Signature
            0       5     0  this   Lshapeless/ops/coproduct$Unifier$;
}
InnerClasses:
  public static #12= #9 of #11;           // Unifier=class shapeless/ops/coproduct$Unifier of class shapeless/ops/coproduct
  public static #13= #2 of #11;           // Unifier$=class shapeless/ops/coproduct$Unifier$ of class shapeless/ops/coproduct
  public final #15;                       // class shapeless/ops/coproduct$Unifier$$anon$20
  public final #17;                       // class shapeless/ops/coproduct$Unifier$$anon$21
SourceFile: "coproduct.scala"
  ScalaInlineInfo: length = 0x1D (unknown attribute)
   01 01 00 05 00 16 00 15 01 00 1B 00 1C 01 00 25
   00 26 01 00 21 00 22 01 00 2E 00 2F 01
  Scala: length = 0x0 (unknown attribute)

