Classfile /Users/mw/Projects/slang-braindump/.jar/jar8/assemble/slang-braindump/assemble/content/shapeless/ops/coproduct$InitLast$$anon$70.class
  Last modified May 29, 2022; size 1642 bytes
  SHA-256 checksum a0af02290ad211ec0d267d8a8698fcc5d3753238f60ca31c732bcbebbe31f403
  Compiled from "coproduct.scala"
public final class shapeless.ops.coproduct$InitLast$$anon$70 extends java.lang.Object implements shapeless.ops.coproduct$InitLast<C>
  minor version: 0
  major version: 52
  flags: (0x0031) ACC_PUBLIC, ACC_FINAL, ACC_SUPER
  this_class: #2                          // shapeless/ops/coproduct$InitLast$$anon$70
  super_class: #5                         // java/lang/Object
  interfaces: 1, fields: 2, methods: 3, attributes: 6
Constant pool:
   #1 = Utf8               shapeless/ops/coproduct$InitLast$$anon$70
   #2 = Class              #1             // shapeless/ops/coproduct$InitLast$$anon$70
   #3 = Utf8               Ljava/lang/Object;Lshapeless/ops/coproduct$InitLast<TC;>;
   #4 = Utf8               java/lang/Object
   #5 = Class              #4             // java/lang/Object
   #6 = Utf8               shapeless/ops/coproduct$InitLast
   #7 = Class              #6             // shapeless/ops/coproduct$InitLast
   #8 = Utf8               coproduct.scala
   #9 = Utf8               shapeless/ops/coproduct$InitLast$
  #10 = Class              #9             // shapeless/ops/coproduct$InitLast$
  #11 = Utf8               initLastCoproduct
  #12 = Utf8               (Lshapeless/ops/coproduct$Reverse;Lshapeless/ops/coproduct$IsCCons;)Lshapeless/ops/coproduct$InitLast;
  #13 = NameAndType        #11:#12        // initLastCoproduct:(Lshapeless/ops/coproduct$Reverse;Lshapeless/ops/coproduct$IsCCons;)Lshapeless/ops/coproduct$InitLast;
  #14 = Utf8               shapeless/ops/coproduct
  #15 = Class              #14            // shapeless/ops/coproduct
  #16 = Utf8               InitLast
  #17 = Utf8               InitLast$
  #18 = Utf8               shapeless/ops/coproduct$IsCCons
  #19 = Class              #18            // shapeless/ops/coproduct$IsCCons
  #20 = Utf8               IsCCons
  #21 = Utf8               shapeless/ops/coproduct$Reverse
  #22 = Class              #21            // shapeless/ops/coproduct$Reverse
  #23 = Utf8               Reverse
  #24 = Utf8               isCCons$1
  #25 = Utf8               Lshapeless/ops/coproduct$IsCCons;
  #26 = Utf8               reverse$3
  #27 = Utf8               Lshapeless/ops/coproduct$Reverse;
  #28 = Utf8               init
  #29 = Utf8               (Lshapeless/Coproduct;)Lscala/Option;
  #30 = Utf8               (TC;)Lscala/Option<TT;>;
  #31 = Utf8               c
  #32 = NameAndType        #24:#25        // isCCons$1:Lshapeless/ops/coproduct$IsCCons;
  #33 = Fieldref           #2.#32         // shapeless/ops/coproduct$InitLast$$anon$70.isCCons$1:Lshapeless/ops/coproduct$IsCCons;
  #34 = NameAndType        #26:#27        // reverse$3:Lshapeless/ops/coproduct$Reverse;
  #35 = Fieldref           #2.#34         // shapeless/ops/coproduct$InitLast$$anon$70.reverse$3:Lshapeless/ops/coproduct$Reverse;
  #36 = Utf8               apply
  #37 = Utf8               (Ljava/lang/Object;)Ljava/lang/Object;
  #38 = NameAndType        #36:#37        // apply:(Ljava/lang/Object;)Ljava/lang/Object;
  #39 = InterfaceMethodref #22.#38        // shapeless/ops/coproduct$Reverse.apply:(Ljava/lang/Object;)Ljava/lang/Object;
  #40 = Utf8               shapeless/Coproduct
  #41 = Class              #40            // shapeless/Coproduct
  #42 = Utf8               tail
  #43 = NameAndType        #42:#29        // tail:(Lshapeless/Coproduct;)Lscala/Option;
  #44 = InterfaceMethodref #19.#43        // shapeless/ops/coproduct$IsCCons.tail:(Lshapeless/Coproduct;)Lscala/Option;
  #45 = Utf8               this
  #46 = Utf8               Lshapeless/ops/coproduct$InitLast$$anon$70;
  #47 = Utf8               Lshapeless/Coproduct;
  #48 = Utf8               last
  #49 = Utf8               (TC;)Lscala/Option<TH;>;
  #50 = Utf8               head
  #51 = NameAndType        #50:#29        // head:(Lshapeless/Coproduct;)Lscala/Option;
  #52 = InterfaceMethodref #19.#51        // shapeless/ops/coproduct$IsCCons.head:(Lshapeless/Coproduct;)Lscala/Option;
  #53 = Utf8               <init>
  #54 = Utf8               (Lshapeless/ops/coproduct$IsCCons;Lshapeless/ops/coproduct$Reverse;)V
  #55 = Utf8               ()V
  #56 = NameAndType        #53:#55        // "<init>":()V
  #57 = Methodref          #5.#56         // java/lang/Object."<init>":()V
  #58 = Utf8               Code
  #59 = Utf8               LineNumberTable
  #60 = Utf8               LocalVariableTable
  #61 = Utf8               Signature
  #62 = Utf8               MethodParameters
  #63 = Utf8               InnerClasses
  #64 = Utf8               EnclosingMethod
  #65 = Utf8               SourceFile
  #66 = Utf8               ScalaInlineInfo
  #67 = Utf8               Scala
{
  private final shapeless.ops.coproduct$IsCCons isCCons$1;
    descriptor: Lshapeless/ops/coproduct$IsCCons;
    flags: (0x0012) ACC_PRIVATE, ACC_FINAL

  private final shapeless.ops.coproduct$Reverse reverse$3;
    descriptor: Lshapeless/ops/coproduct$Reverse;
    flags: (0x0012) ACC_PRIVATE, ACC_FINAL

  public scala.Option<T> init(C);
    descriptor: (Lshapeless/Coproduct;)Lscala/Option;
    flags: (0x0001) ACC_PUBLIC
    Code:
      stack=3, locals=2, args_size=2
         0: aload_0
         1: getfield      #33                 // Field isCCons$1:Lshapeless/ops/coproduct$IsCCons;
         4: aload_0
         5: getfield      #35                 // Field reverse$3:Lshapeless/ops/coproduct$Reverse;
         8: aload_1
         9: invokeinterface #39,  2           // InterfaceMethod shapeless/ops/coproduct$Reverse.apply:(Ljava/lang/Object;)Ljava/lang/Object;
        14: checkcast     #41                 // class shapeless/Coproduct
        17: invokeinterface #44,  2           // InterfaceMethod shapeless/ops/coproduct$IsCCons.tail:(Lshapeless/Coproduct;)Lscala/Option;
        22: areturn
      LineNumberTable:
        line 1124: 0
      LocalVariableTable:
        Start  Length  Slot  Name   Signature
            0      23     0  this   Lshapeless/ops/coproduct$InitLast$$anon$70;
            0      23     1     c   Lshapeless/Coproduct;
    Signature: #30                          // (TC;)Lscala/Option<TT;>;
    MethodParameters:
      Name                           Flags
      c                              final

  public scala.Option<H> last(C);
    descriptor: (Lshapeless/Coproduct;)Lscala/Option;
    flags: (0x0001) ACC_PUBLIC
    Code:
      stack=3, locals=2, args_size=2
         0: aload_0
         1: getfield      #33                 // Field isCCons$1:Lshapeless/ops/coproduct$IsCCons;
         4: aload_0
         5: getfield      #35                 // Field reverse$3:Lshapeless/ops/coproduct$Reverse;
         8: aload_1
         9: invokeinterface #39,  2           // InterfaceMethod shapeless/ops/coproduct$Reverse.apply:(Ljava/lang/Object;)Ljava/lang/Object;
        14: checkcast     #41                 // class shapeless/Coproduct
        17: invokeinterface #52,  2           // InterfaceMethod shapeless/ops/coproduct$IsCCons.head:(Lshapeless/Coproduct;)Lscala/Option;
        22: areturn
      LineNumberTable:
        line 1125: 0
      LocalVariableTable:
        Start  Length  Slot  Name   Signature
            0      23     0  this   Lshapeless/ops/coproduct$InitLast$$anon$70;
            0      23     1     c   Lshapeless/Coproduct;
    Signature: #49                          // (TC;)Lscala/Option<TH;>;
    MethodParameters:
      Name                           Flags
      c                              final

  public shapeless.ops.coproduct$InitLast$$anon$70(shapeless.ops.coproduct$IsCCons, shapeless.ops.coproduct$Reverse);
    descriptor: (Lshapeless/ops/coproduct$IsCCons;Lshapeless/ops/coproduct$Reverse;)V
    flags: (0x0001) ACC_PUBLIC
    Code:
      stack=2, locals=3, args_size=3
         0: aload_0
         1: aload_1
         2: putfield      #33                 // Field isCCons$1:Lshapeless/ops/coproduct$IsCCons;
         5: aload_0
         6: aload_2
         7: putfield      #35                 // Field reverse$3:Lshapeless/ops/coproduct$Reverse;
        10: aload_0
        11: invokespecial #57                 // Method java/lang/Object."<init>":()V
        14: return
      LineNumberTable:
        line 1119: 0
        line 1120: 10
      LocalVariableTable:
        Start  Length  Slot  Name   Signature
            0      15     0  this   Lshapeless/ops/coproduct$InitLast$$anon$70;
            0      15     1 isCCons$1   Lshapeless/ops/coproduct$IsCCons;
            0      15     2 reverse$3   Lshapeless/ops/coproduct$Reverse;
    MethodParameters:
      Name                           Flags
      isCCons$1                      final
      reverse$3                      final
}
InnerClasses:
  public static #16= #7 of #15;           // InitLast=class shapeless/ops/coproduct$InitLast of class shapeless/ops/coproduct
  public static #17= #10 of #15;          // InitLast$=class shapeless/ops/coproduct$InitLast$ of class shapeless/ops/coproduct
  public final #2;                        // class shapeless/ops/coproduct$InitLast$$anon$70
  public static #20= #19 of #15;          // IsCCons=class shapeless/ops/coproduct$IsCCons of class shapeless/ops/coproduct
  public static #23= #22 of #15;          // Reverse=class shapeless/ops/coproduct$Reverse of class shapeless/ops/coproduct
EnclosingMethod: #10.#13                // shapeless.ops.coproduct$InitLast$.initLastCoproduct
Signature: #3                           // Ljava/lang/Object;Lshapeless/ops/coproduct$InitLast<TC;>;
SourceFile: "coproduct.scala"
  ScalaInlineInfo: length = 0x13 (unknown attribute)
   01 01 00 03 00 35 00 36 01 00 1C 00 1D 01 00 30
   00 1D 01
  Scala: length = 0x0 (unknown attribute)

