Classfile /Users/mw/Projects/slang-braindump/.jar/jar8/assemble/slang-braindump/assemble/content/shapeless/ops/FnToProductInstances.class
  Last modified May 29, 2022; size 24404 bytes
  SHA-256 checksum 2f1fba1a3d3963b826a26f41f12223fea91524fcdf1b052fc7465983d0b0c431
  Compiled from "fntoproduct.scala"
public interface shapeless.ops.FnToProductInstances
  minor version: 0
  major version: 52
  flags: (0x0601) ACC_PUBLIC, ACC_INTERFACE, ACC_ABSTRACT
  this_class: #2                          // shapeless/ops/FnToProductInstances
  super_class: #4                         // java/lang/Object
  interfaces: 0, fields: 0, methods: 47, attributes: 5
Constant pool:
    #1 = Utf8               shapeless/ops/FnToProductInstances
    #2 = Class              #1            // shapeless/ops/FnToProductInstances
    #3 = Utf8               java/lang/Object
    #4 = Class              #3            // java/lang/Object
    #5 = Utf8               fntoproduct.scala
    #6 = Utf8               Lscala/reflect/ScalaSignature;
    #7 = Utf8               bytes
    #8 = Utf8               \u0006\u0005!\u001dea\u0002\u000e\u001c!\u0003\r\t\u0001\t\u0005\u0006O\u0001!\t\u0001K\u0003\u0005Y\u0001\u0001Q\u0006C\u0003J\u0001\u0011\r!\nC\u0003\\\u0001\u0011\rA\fC\u0003j\u0001\u0011\r!\u000eC\u0003{\u0001\u0011\r1\u0010C\u0004\u0002\u001e\u0001!\u0019!a\b\t\u000f\u0005-\u0003\u0001b\u0001\u0002N!9\u0011q\u0010\u0001\u0005\u0004\u0005\u0005\u0005bBA\\\u0001\u0011\r\u0011\u0011\u0018\u0005\b\u0003o\u0004A1AA}\u0011\u001d\u0011i\u0004\u0001C\u0002\u0005\u007fAqA!#\u0001\t\u0007\u0011Y\tC\u0004\u0003\\\u0002!\u0019A!8\t\u000f\rM\u0002\u0001b\u0001\u00046!91\u0011\u0013\u0001\u0005\u0004\rM\u0005bBB{\u0001\u0011\r1q\u001f\u0005\b\t?\u0002A1\u0001C1\u0011\u001d!y\r\u0001C\u0002\t#Dq!\"\u0012\u0001\t\u0007)9\u0005C\u0004\u0006B\u0002!\u0019!b1\t\u000f\u0019\r\u0003\u0001b\u0001\u0007F!9a1\u001a\u0001\u0005\u0004\u00195\u0007bBD-\u0001\u0011\rq1\f\u0005\b\u000f[\u0004A1ADx\u0005Q1e\u000eV8Qe>$Wo\u0019;J]N$\u0018M\\2fg*\u0011A$H\u0001\u0004_B\u001c(\"\u0001\u0010\u0002\u0013MD\u0017\r]3mKN\u001c8\u0001A\n\u0003\u0001\u0005\u0002\"AI\u0013\u000e\u0003\rR\u0011\u0001J\u0001\u0006g\u000e\fG.Y\u0005\u0003M\r\u0012a!\u00118z%\u00164\u0017A\u0002\u0013j]&$H\u0005F\u0001*!\t\u0011#&\u0003\u0002,G\t!QK\\5u\u0005\r\tU\u000f_\u000b\u0004]m:%CA\u00182\r\u0011\u0001\u0004\u0001\u0001\u0018\u0003\u0019q\u0012XMZ5oK6,g\u000e\u001e \u0011\u0007I2\u0014H\u0004\u00024i5\t1$\u0003\u000267\u0005Aa-\u001e8di&|g.\u0003\u00028q\tYaI\u001c+p!J|G-^2u\u0015\t)4\u0004\u0005\u0002;w1\u0001A!\u0002\u001f\u0003\u0005\u0004i$!\u0001$\u0012\u0005y\n\u0005C\u0001\u0012@\u0013\t\u00015EA\u0004O_RD\u0017N\\4\u0011\u0005\t\u0012\u0015BA\"$\u0005\r\te._\u0003\u0005\u000b>\u0002cIA\u0002PkR\u0004\"AO$\u0005\u000b!\u0013!\u0019A\u001f\u0003\t=+H\u000fM\u0001\rM:$v\u000e\u0015:pIV\u001cG\u000fM\u000b\u0003\u0017J+\u0012\u0001\u0014\t\u0005\u001b\nqE+D\u0001\u0001!\r\u0011s*U\u0005\u0003!\u000e\u0012\u0011BR;oGRLwN\u001c\u0019\u0011\u0005i\u0012F!B*\u0004\u0005\u0004i$a\u0001*fgB!!%V,R\u0013\t16EA\u0005Gk:\u001cG/[8ocA\u0011\u0001,W\u0007\u0002;%\u0011!,\b\u0002\u0005\u0011:KG.\u0001\u0007g]R{\u0007K]8ek\u000e$\u0018\'F\u0002^C\u0012,\u0012A\u0018\t\u0005\u001b\nyV\r\u0005\u0003#+\u0002\u001c\u0007C\u0001\u001eb\t\u0015\u0011GA1\u0001>\u0005\u0005\t\u0005C\u0001\u001ee\t\u0015\u0019FA1\u0001>!\u0011\u0011SKZ2\u0011\ta;\u0007mV\u0005\u0003Qv\u0011A\u0002J2pY>tGeY8m_:\fAB\u001a8U_B\u0013x\u000eZ;diJ*Ba[9tmV\tA\u000e\u0005\u0003N\u00055<\b#\u0002\u0012oaJ,\u0018BA8$\u0005%1UO\\2uS>t\'\u0007\u0005\u0002;c\u0012)!-\u0002b\u0001{A\u0011!h\u001d\u0003\u0006i\u0016\u0011\r!\u0010\u0002\u0002\u0005B\u0011!H\u001e\u0003\u0006\'\u0016\u0011\r!\u0010\t\u0005EUCX\u000f\u0005\u0003YOBL\b\u0003\u0002-he^\u000bAB\u001a8U_B\u0013x\u000eZ;diN*\u0012\u0002`A\u0003\u0003\u0013\ti!a\u0005\u0016\u0003u\u0004R!\u0014\u0002\u007f\u0003+\u0001\"BI@\u0002\u0004\u0005\u001d\u00111BA\t\u0013\r\t\ta\t\u0002\n\rVt7\r^5p]N\u00022AOA\u0003\t\u0015\u0011gA1\u0001>!\rQ\u0014\u0011\u0002\u0003\u0006i\u001a\u0011\r!\u0010\t\u0004u\u00055AABA\b\r\t\u0007QHA\u0001D!\rQ\u00141\u0003\u0003\u0006\'\u001a\u0011\r!\u0010\t\u0007EU\u000b9\"!\u0005\u0011\ra;\u00171AA\r!\u0019Av-a\u0002\u0002\u001cA)\u0001lZA\u0006/\u0006aaM\u001c+p!J|G-^2uiUa\u0011\u0011EA\u0017\u0003c\t)$!\u000f\u0002@U\u0011\u00111\u0005\t\u0007\u001b\n\t)#!\u0011\u0011\u001b\t\n9#a\u000b\u00020\u0005M\u0012qGA\u001f\u0013\r\tIc\t\u0002\n\rVt7\r^5p]R\u00022AOA\u0017\t\u0015\u0011wA1\u0001>!\rQ\u0014\u0011\u0007\u0003\u0006i\u001e\u0011\r!\u0010\t\u0004u\u0005UBABA\b\u000f\t\u0007Q\bE\u0002;\u0003s!a!a\u000f\b\u0005\u0004i$!\u0001#\u0011\u0007i\ny\u0004B\u0003T\u000f\t\u0007Q\b\u0005\u0004#+\u0006\r\u0013Q\b\t\u00071\u001e\fY#!\u0012\u0011\ra;\u0017qFA$!\u0019Av-a\r\u0002JA)\u0001lZA\u001c/\u0006aaM\u001c+p!J|G-^2ukUq\u0011qJA.\u0003?\n\u0019\'a\u001a\u0002l\u0005ETCAA)!\u0019i%!a\u0015\u0002tAy!%!\u0016\u0002Z\u0005u\u0013\u0011MA3\u0003S\ny\'C\u0002\u0002X\r\u0012\u0011BR;oGRLwN\\\u001b\u0011\u0007i\nY\u0006B\u0003c\u0011\t\u0007Q\bE\u0002;\u0003?\"Q\u0001\u001e\u0005C\u0002u\u00022AOA2\t\u0019\ty\u0001\u0003b\u0001{A\u0019!(a\u001a\u0005\r\u0005m\u0002B1\u0001>!\rQ\u00141\u000e\u0003\u0007\u0003[B!\u0019A\u001f\u0003\u0003\u0015\u00032AOA9\t\u0015\u0019\u0006B1\u0001>!\u0019\u0011S+!\u001e\u0002pA1\u0001lZA-\u0003o\u0002b\u0001W4\u0002^\u0005e\u0004C\u0002-h\u0003C\nY\b\u0005\u0004YO\u0006\u0015\u0014Q\u0010\t\u00061\u001e\fIgV\u0001\rM:$v\u000e\u0015:pIV\u001cGON\u000b\u0011\u0003\u0007\u000by)a%\u0002\u0018\u0006m\u0015qTAR\u0003O+\"!!\"\u0011\r5\u0013\u0011qQAU!E\u0011\u0013\u0011RAG\u0003#\u000b)*!\'\u0002\u001e\u0006\u0005\u0016QU\u0005\u0004\u0003\u0017\u001b#!\u0003$v]\u000e$\u0018n\u001c87!\rQ\u0014q\u0012\u0003\u0006E&\u0011\r!\u0010\t\u0004u\u0005ME!\u0002;\n\u0005\u0004i\u0004c\u0001\u001e\u0002\u0018\u00121\u0011qB\u0005C\u0002u\u00022AOAN\t\u0019\tY$\u0003b\u0001{A\u0019!(a(\u0005\r\u00055\u0014B1\u0001>!\rQ\u00141\u0015\u0003\u0006y%\u0011\r!\u0010\t\u0004u\u0005\u001dF!B*\n\u0005\u0004i\u0004C\u0002\u0012V\u0003W\u000b)\u000b\u0005\u0004YO\u00065\u0015Q\u0016\t\u00071\u001e\f\t*a,\u0011\ra;\u0017QSAY!\u0019Av-!\'\u00024B1\u0001lZAO\u0003k\u0003R\u0001W4\u0002\"^\u000bAB\u001a8U_B\u0013x\u000eZ;di^*\"#a/\u0002H\u0006-\u0017qZAj\u0003/\fY.a8\u0002fV\u0011\u0011Q\u0018\t\u0007\u001b\n\ty,a:\u0011\'\t\n\t-!2\u0002J\u00065\u0017\u0011[Ak\u00033\fi.a9\n\u0007\u0005\r7EA\u0005Gk:\u001cG/[8ooA\u0019!(a2\u0005\u000b\tT!\u0019A\u001f\u0011\u0007i\nY\rB\u0003u\u0015\t\u0007Q\bE\u0002;\u0003\u001f$a!a\u0004\u000b\u0005\u0004i\u0004c\u0001\u001e\u0002T\u00121\u00111\b\u0006C\u0002u\u00022AOAl\t\u0019\tiG\u0003b\u0001{A\u0019!(a7\u0005\u000bqR!\u0019A\u001f\u0011\u0007i\ny\u000e\u0002\u0004\u0002b*\u0011\r!\u0010\u0002\u0002\u000fB\u0019!(!:\u0005\u000bMS!\u0019A\u001f\u0011\r\t*\u0016\u0011^Ar!\u0019Av-!2\u0002lB1\u0001lZAe\u0003[\u0004b\u0001W4\u0002N\u0006=\bC\u0002-h\u0003#\f\t\u0010\u0005\u0004YO\u0006U\u00171\u001f\t\u00071\u001e\fI.!>\u0011\u000ba;\u0017Q\\,\u0002\u0019\u0019tGk\u001c)s_\u0012,8\r\u001e\u001d\u0016)\u0005m(q\u0001B\u0006\u0005\u001f\u0011\u0019Ba\u0006\u0003\u001c\t}!1\u0005B\u0015+\t\ti\u0010\u0005\u0004N\u0005\u0005}(1\u0006\t\u0016E\t\u0005!Q\u0001B\u0005\u0005\u001b\u0011\tB!\u0006\u0003\u001a\tu!\u0011\u0005B\u0014\u0013\r\u0011\u0019a\t\u0002\n\rVt7\r^5p]b\u00022A\u000fB\u0004\t\u0015\u00117B1\u0001>!\rQ$1\u0002\u0003\u0006i.\u0011\r!\u0010\t\u0004u\t=AABA\b\u0017\t\u0007Q\bE\u0002;\u0005\'!a!a\u000f\f\u0005\u0004i\u0004c\u0001\u001e\u0003\u0018\u00111\u0011QN\u0006C\u0002u\u00022A\u000fB\u000e\t\u0015a4B1\u0001>!\rQ$q\u0004\u0003\u0007\u0003C\\!\u0019A\u001f\u0011\u0007i\u0012\u0019\u0003\u0002\u0004\u0003&-\u0011\r!\u0010\u0002\u0002\u0011B\u0019!H!\u000b\u0005\u000bM[!\u0019A\u001f\u0011\r\t*&Q\u0006B\u0014!\u0019AvM!\u0002\u00030A1\u0001l\u001aB\u0005\u0005c\u0001b\u0001W4\u0003\u000e\tM\u0002C\u0002-h\u0005#\u0011)\u0004\u0005\u0004YO\nU!q\u0007\t\u00071\u001e\u0014IB!\u000f\u0011\ra;\'Q\u0004B\u001e!\u0015AvM!\tX\u000311g\u000eV8Qe>$Wo\u0019;:+Y\u0011\tE!\u0014\u0003R\tU#\u0011\fB/\u0005C\u0012)G!\u001b\u0003n\tMTC\u0001B\"!\u0019i%A!\u0012\u0003vA9\"Ea\u0012\u0003L\t=#1\u000bB,\u00057\u0012yFa\u0019\u0003h\t-$\u0011O\u0005\u0004\u0005\u0013\u001a#!\u0003$v]\u000e$\u0018n\u001c8:!\rQ$Q\n\u0003\u0006E2\u0011\r!\u0010\t\u0004u\tEC!\u0002;\r\u0005\u0004i\u0004c\u0001\u001e\u0003V\u00111\u0011q\u0002\u0007C\u0002u\u00022A\u000fB-\t\u0019\tY\u0004\u0004b\u0001{A\u0019!H!\u0018\u0005\r\u00055DB1\u0001>!\rQ$\u0011\r\u0003\u0006y1\u0011\r!\u0010\t\u0004u\t\u0015DABAq\u0019\t\u0007Q\bE\u0002;\u0005S\"aA!\n\r\u0005\u0004i\u0004c\u0001\u001e\u0003n\u00111!q\u000e\u0007C\u0002u\u0012\u0011!\u0013\t\u0004u\tMD!B*\r\u0005\u0004i\u0004C\u0002\u0012V\u0005o\u0012\t\b\u0005\u0004YO\n-#\u0011\u0010\t\u00071\u001e\u0014yEa\u001f\u0011\ra;\'1\u000bB?!\u0019AvMa\u0016\u0003\u0000A1\u0001l\u001aB.\u0005\u0003\u0003b\u0001W4\u0003`\t\r\u0005C\u0002-h\u0005G\u0012)\t\u0005\u0004YO\n\u001d$q\u0011\t\u00061\u001e\u0014YgV\u0001\u000eM:$v\u000e\u0015:pIV\u001cG/\r\u0019\u00161\t5%\u0011\u0014BO\u0005C\u0013)K!+\u0003.\nE&Q\u0017B]\u0005{\u0013\u0019-\u0006\u0002\u0003\u0010B1QJ\u0001BI\u0005\u000b\u0004\u0012D\tBJ\u0005/\u0013YJa(\u0003$\n\u001d&1\u0016BX\u0005g\u00139La/\u0003B&\u0019!QS\u0012\u0003\u0015\u0019+hn\u0019;j_:\f\u0004\u0007E\u0002;\u00053#QAY\u0007C\u0002u\u00022A\u000fBO\t\u0015!XB1\u0001>!\rQ$\u0011\u0015\u0003\u0007\u0003\u001fi!\u0019A\u001f\u0011\u0007i\u0012)\u000b\u0002\u0004\u0002<5\u0011\r!\u0010\t\u0004u\t%FABA7\u001b\t\u0007Q\bE\u0002;\u0005[#Q\u0001P\u0007C\u0002u\u00022A\u000fBY\t\u0019\t\t/\u0004b\u0001{A\u0019!H!.\u0005\r\t\u0015RB1\u0001>!\rQ$\u0011\u0018\u0003\u0007\u0005_j!\u0019A\u001f\u0011\u0007i\u0012i\f\u0002\u0004\u0003@6\u0011\r!\u0010\u0002\u0002\u0015B\u0019!Ha1\u0005\u000bMk!\u0019A\u001f\u0011\r\t*&q\u0019Ba!\u0019AvMa&\u0003JB1\u0001l\u001aBN\u0005\u0017\u0004b\u0001W4\u0003 \n5\u0007C\u0002-h\u0005G\u0013y\r\u0005\u0004YO\n\u001d&\u0011\u001b\t\u00071\u001e\u0014YKa5\u0011\ra;\'q\u0016Bk!\u0019AvMa-\u0003XB1\u0001l\u001aB\\\u00053\u0004R\u0001W4\u0003<^\u000bQB\u001a8U_B\u0013x\u000eZ;diF\nTC\u0007Bp\u0005W\u0014yOa=\u0003x\nm(q`B\u0002\u0007\u000f\u0019Yaa\u0004\u0004\u0014\reQC\u0001Bq!\u0019i%Aa9\u0004\u001cAY\"E!:\u0003j\n5(\u0011\u001fB{\u0005s\u0014ip!\u0001\u0004\u0006\r%1QBB\t\u0007/I1Aa:$\u0005)1UO\\2uS>t\u0017\'\r\t\u0004u\t-H!\u00022\u000f\u0005\u0004i\u0004c\u0001\u001e\u0003p\u0012)AO\u0004b\u0001{A\u0019!Ha=\u0005\r\u0005=aB1\u0001>!\rQ$q\u001f\u0003\u0007\u0003wq!\u0019A\u001f\u0011\u0007i\u0012Y\u0010\u0002\u0004\u0002n9\u0011\r!\u0010\t\u0004u\t}H!\u0002\u001f\u000f\u0005\u0004i\u0004c\u0001\u001e\u0004\u0004\u00111\u0011\u0011\u001d\bC\u0002u\u00022AOB\u0004\t\u0019\u0011)C\u0004b\u0001{A\u0019!ha\u0003\u0005\r\t=dB1\u0001>!\rQ4q\u0002\u0003\u0007\u0005\u007fs!\u0019A\u001f\u0011\u0007i\u001a\u0019\u0002\u0002\u0004\u0004\u00169\u0011\r!\u0010\u0002\u0002\u0017B\u0019!h!\u0007\u0005\u000bMs!\u0019A\u001f\u0011\r\t*6QDB\f!\u0019AvM!;\u0004 A1\u0001l\u001aBw\u0007C\u0001b\u0001W4\u0003r\u000e\r\u0002C\u0002-h\u0005k\u001c)\u0003\u0005\u0004YO\ne8q\u0005\t\u00071\u001e\u0014ip!\u000b\u0011\ra;7\u0011AB\u0016!\u0019Avm!\u0002\u0004.A1\u0001lZB\u0005\u0007_\u0001b\u0001W4\u0004\u000e\rE\u0002#\u0002-h\u0007#9\u0016!\u00044o)>\u0004&o\u001c3vGR\f$\'\u0006\u000f\u00048\r\r3qIB&\u0007\u001f\u001a\u0019fa\u0016\u0004\\\r}31MB4\u0007W\u001ayg!\u001e\u0016\u0005\re\u0002CB\'\u0003\u0007w\u00199\bE\u000f#\u0007{\u0019\te!\u0012\u0004J\r53\u0011KB+\u00073\u001aif!\u0019\u0004f\r%4QNB:\u0013\r\u0019yd\t\u0002\u000b\rVt7\r^5p]F\u0012\u0004c\u0001\u001e\u0004D\u0011)!m\u0004b\u0001{A\u0019!ha\u0012\u0005\u000bQ|!\u0019A\u001f\u0011\u0007i\u001aY\u0005\u0002\u0004\u0002\u0010=\u0011\r!\u0010\t\u0004u\r=CABA\u001e\u001f\t\u0007Q\bE\u0002;\u0007\'\"a!!\u001c\u0010\u0005\u0004i\u0004c\u0001\u001e\u0004X\u0011)Ah\u0004b\u0001{A\u0019!ha\u0017\u0005\r\u0005\u0005xB1\u0001>!\rQ4q\f\u0003\u0007\u0005Ky!\u0019A\u001f\u0011\u0007i\u001a\u0019\u0007\u0002\u0004\u0003p=\u0011\r!\u0010\t\u0004u\r\u001dDA\u0002B`\u001f\t\u0007Q\bE\u0002;\u0007W\"aa!\u0006\u0010\u0005\u0004i\u0004c\u0001\u001e\u0004p\u001111\u0011O\bC\u0002u\u0012\u0011\u0001\u0014\t\u0004u\rUD!B*\u0010\u0005\u0004i\u0004C\u0002\u0012V\u0007s\u001a\u0019\b\u0005\u0004YO\u000e\u000531\u0010\t\u00071\u001e\u001c)e! \u0011\ra;7\u0011JB@!\u0019Avm!\u0014\u0004\u0002B1\u0001lZB)\u0007\u0007\u0003b\u0001W4\u0004V\r\u0015\u0005C\u0002-h\u00073\u001a9\t\u0005\u0004YO\u000eu3\u0011\u0012\t\u00071\u001e\u001c\tga#\u0011\ra;7QMBG!\u0019Avm!\u001b\u0004\u0010B)\u0001lZB7/\u0006iaM\u001c+p!J|G-^2ucM*bd!&\u0004\"\u000e\u00156\u0011VBW\u0007c\u001b)l!/\u0004>\u000e\u00057QYBe\u0007\u001b\u001c\tna6\u0016\u0005\r]\u0005CB\'\u0003\u00073\u001bI\u000eE\u0010#\u00077\u001byja)\u0004(\u000e-6qVBZ\u0007o\u001bYla0\u0004D\u000e\u001d71ZBh\u0007+L1a!($\u0005)1UO\\2uS>t\u0017g\r\t\u0004u\r\u0005F!\u00022\u0011\u0005\u0004i\u0004c\u0001\u001e\u0004&\u0012)A\u000f\u0005b\u0001{A\u0019!h!+\u0005\r\u0005=\u0001C1\u0001>!\rQ4Q\u0016\u0003\u0007\u0003w\u0001\"\u0019A\u001f\u0011\u0007i\u001a\t\f\u0002\u0004\u0002nA\u0011\r!\u0010\t\u0004u\rUF!\u0002\u001f\u0011\u0005\u0004i\u0004c\u0001\u001e\u0004:\u00121\u0011\u0011\u001d\tC\u0002u\u00022AOB_\t\u0019\u0011)\u0003\u0005b\u0001{A\u0019!h!1\u0005\r\t=\u0004C1\u0001>!\rQ4Q\u0019\u0003\u0007\u0005\u007f\u0003\"\u0019A\u001f\u0011\u0007i\u001aI\r\u0002\u0004\u0004\u0016A\u0011\r!\u0010\t\u0004u\r5GABB9!\t\u0007Q\bE\u0002;\u0007#$aaa5\u0011\u0005\u0004i$!A\'\u0011\u0007i\u001a9\u000eB\u0003T!\t\u0007Q\b\u0005\u0004#+\u000em7Q\u001b\t\u00071\u001e\u001cyj!8\u0011\ra;71UBp!\u0019Avma*\u0004bB1\u0001lZBV\u0007G\u0004b\u0001W4\u00040\u000e\u0015\bC\u0002-h\u0007g\u001b9\u000f\u0005\u0004YO\u000e]6\u0011\u001e\t\u00071\u001e\u001cYla;\u0011\ra;7qXBw!\u0019Avma1\u0004pB1\u0001lZBd\u0007c\u0004b\u0001W4\u0004L\u000eM\b#\u0002-h\u0007\u001f<\u0016!\u00044o)>\u0004&o\u001c3vGR\fD\'\u0006\u0011\u0004z\u0012\u0015A\u0011\u0002C\u0007\t#!)\u0002\"\u0007\u0005\u001e\u0011\u0005BQ\u0005C\u0015\t[!\t\u0004\"\u000e\u0005:\u0011}RCAB~!\u0019i%a!@\u0005BA\t#ea@\u0005\u0004\u0011\u001dA1\u0002C\b\t\'!9\u0002b\u0007\u0005 \u0011\rBq\u0005C\u0016\t_!\u0019\u0004b\u000e\u0005>%\u0019A\u0011A\u0012\u0003\u0015\u0019+hn\u0019;j_:\fD\u0007E\u0002;\t\u000b!QAY\tC\u0002u\u00022A\u000fC\u0005\t\u0015!\u0018C1\u0001>!\rQDQ\u0002\u0003\u0007\u0003\u001f\t\"\u0019A\u001f\u0011\u0007i\"\t\u0002\u0002\u0004\u0002<E\u0011\r!\u0010\t\u0004u\u0011UAABA7#\t\u0007Q\bE\u0002;\t3!Q\u0001P\tC\u0002u\u00022A\u000fC\u000f\t\u0019\t\t/\u0005b\u0001{A\u0019!\b\"\t\u0005\r\t\u0015\u0012C1\u0001>!\rQDQ\u0005\u0003\u0007\u0005_\n\"\u0019A\u001f\u0011\u0007i\"I\u0003\u0002\u0004\u0003@F\u0011\r!\u0010\t\u0004u\u00115BABB\u000b#\t\u0007Q\bE\u0002;\tc!aa!\u001d\u0012\u0005\u0004i\u0004c\u0001\u001e\u00056\u0011111[\tC\u0002u\u00022A\u000fC\u001d\t\u0019!Y$\u0005b\u0001{\t\ta\nE\u0002;\t\u007f!QaU\tC\u0002u\u0002bAI+\u0005D\u0011u\u0002C\u0002-h\t\u0007!)\u0005\u0005\u0004YO\u0012\u001dAq\t\t\u00071\u001e$Y\u0001\"\u0013\u0011\ra;Gq\u0002C&!\u0019Av\rb\u0005\u0005NA1\u0001l\u001aC\f\t\u001f\u0002b\u0001W4\u0005\u001c\u0011E\u0003C\u0002-h\t?!\u0019\u0006\u0005\u0004YO\u0012\rBQ\u000b\t\u00071\u001e$9\u0003b\u0016\u0011\ra;G1\u0006C-!\u0019Av\rb\f\u0005\\A1\u0001l\u001aC\u001a\t;\u0002R\u0001W4\u00058]\u000bQB\u001a8U_B\u0013x\u000eZ;diF*TC\tC2\t_\"\u0019\bb\u001e\u0005|\u0011}D1\u0011CD\t\u0017#y\tb%\u0005\u0018\u0012mEq\u0014CR\tO#i+\u0006\u0002\u0005fA1QJ\u0001C4\t_\u00032E\tC5\t[\"\t\b\"\u001e\u0005z\u0011uD\u0011\u0011CC\t\u0013#i\t\"%\u0005\u0016\u0012eEQ\u0014CQ\tK#Y+C\u0002\u0005l\r\u0012!BR;oGRLwN\\\u00196!\rQDq\u000e\u0003\u0006EJ\u0011\r!\u0010\t\u0004u\u0011MD!\u0002;\u0013\u0005\u0004i\u0004c\u0001\u001e\u0005x\u00111\u0011q\u0002\nC\u0002u\u00022A\u000fC>\t\u0019\tYD\u0005b\u0001{A\u0019!\bb \u0005\r\u00055$C1\u0001>!\rQD1\u0011\u0003\u0006yI\u0011\r!\u0010\t\u0004u\u0011\u001dEABAq%\t\u0007Q\bE\u0002;\t\u0017#aA!\n\u0013\u0005\u0004i\u0004c\u0001\u001e\u0005\u0010\u00121!q\u000e\nC\u0002u\u00022A\u000fCJ\t\u0019\u0011yL\u0005b\u0001{A\u0019!\bb&\u0005\r\rU!C1\u0001>!\rQD1\u0014\u0003\u0007\u0007c\u0012\"\u0019A\u001f\u0011\u0007i\"y\n\u0002\u0004\u0004TJ\u0011\r!\u0010\t\u0004u\u0011\rFA\u0002C\u001e%\t\u0007Q\bE\u0002;\tO#a\u0001\"+\u0013\u0005\u0004i$!A(\u0011\u0007i\"i\u000bB\u0003T%\t\u0007Q\b\u0005\u0004#+\u0012EF1\u0016\t\u00071\u001e$i\u0007b-\u0011\ra;G\u0011\u000fC[!\u0019Av\r\"\u001e\u00058B1\u0001l\u001aC=\ts\u0003b\u0001W4\u0005~\u0011m\u0006C\u0002-h\t\u0003#i\f\u0005\u0004YO\u0012\u0015Eq\u0018\t\u00071\u001e$I\t\"1\u0011\ra;GQ\u0012Cb!\u0019Av\r\"%\u0005FB1\u0001l\u001aCK\t\u000f\u0004b\u0001W4\u0005\u001a\u0012%\u0007C\u0002-h\t;#Y\r\u0005\u0004YO\u0012\u0005FQ\u001a\t\u00061\u001e$)kV\u0001\u000eM:$v\u000e\u0015:pIV\u001cG/\r\u001c\u0016I\u0011MGq\u001cCr\tO$Y\u000fb<\u0005t\u0012]H1 C\u0000\u000b\u0007)9!b\u0003\u0006\u0010\u0015MQqCC\u000e\u000bC)\"\u0001\"6\u0011\r5\u0013Aq[C\u0012!\u0015\u0012C\u0011\u001cCo\tC$)\u000f\";\u0005n\u0012EHQ\u001fC}\t{,\t!\"\u0002\u0006\n\u00155Q\u0011CC\u000b\u000b3)y\"C\u0002\u0005\\\u000e\u0012!BR;oGRLwN\\\u00197!\rQDq\u001c\u0003\u0006EN\u0011\r!\u0010\t\u0004u\u0011\rH!\u0002;\u0014\u0005\u0004i\u0004c\u0001\u001e\u0005h\u00121\u0011qB\nC\u0002u\u00022A\u000fCv\t\u0019\tYd\u0005b\u0001{A\u0019!\bb<\u0005\r\u000554C1\u0001>!\rQD1\u001f\u0003\u0006yM\u0011\r!\u0010\t\u0004u\u0011]HABAq\'\t\u0007Q\bE\u0002;\tw$aA!\n\u0014\u0005\u0004i\u0004c\u0001\u001e\u0005\u0000\u00121!qN\nC\u0002u\u00022AOC\u0002\t\u0019\u0011yl\u0005b\u0001{A\u0019!(b\u0002\u0005\r\rU1C1\u0001>!\rQT1\u0002\u0003\u0007\u0007c\u001a\"\u0019A\u001f\u0011\u0007i*y\u0001\u0002\u0004\u0004TN\u0011\r!\u0010\t\u0004u\u0015MAA\u0002C\u001e\'\t\u0007Q\bE\u0002;\u000b/!a\u0001\"+\u0014\u0005\u0004i\u0004c\u0001\u001e\u0006\u001c\u00111QQD\nC\u0002u\u0012\u0011\u0001\u0015\t\u0004u\u0015\u0005B!B*\u0014\u0005\u0004i\u0004C\u0002\u0012V\u000bK)y\u0002\u0005\u0004YO\u0012uWq\u0005\t\u00071\u001e$\t/\"\u000b\u0011\ra;GQ]C\u0016!\u0019Av\r\";\u0006.A1\u0001l\u001aCw\u000b_\u0001b\u0001W4\u0005r\u0016E\u0002C\u0002-h\tk,\u0019\u0004\u0005\u0004YO\u0012eXQ\u0007\t\u00071\u001e$i0b\u000e\u0011\ra;W\u0011AC\u001d!\u0019Av-\"\u0002\u0006<A1\u0001lZC\u0005\u000b{\u0001b\u0001W4\u0006\u000e\u0015}\u0002C\u0002-h\u000b#)\t\u0005\u0005\u0004YO\u0016UQ1\t\t\u00061\u001e,IbV\u0001\u000eM:$v\u000e\u0015:pIV\u001cG/M\u001c\u0016M\u0015%SQKC-\u000b;*\t\'\"\u001a\u0006j\u00155T\u0011OC;\u000bs*i(\"!\u0006\u0006\u0016%UQRCI\u000b++Y*\u0006\u0002\u0006LA1QJAC\'\u000b;\u0003rEIC(\u000b\'*9&b\u0017\u0006`\u0015\rTqMC6\u000b_*\u0019(b\u001e\u0006|\u0015}T1QCD\u000b\u0017+y)b%\u0006\u001a&\u0019Q\u0011K\u0012\u0003\u0015\u0019+hn\u0019;j_:\ft\u0007E\u0002;\u000b+\"QA\u0019\u000bC\u0002u\u00022AOC-\t\u0015!HC1\u0001>!\rQTQ\f\u0003\u0007\u0003\u001f!\"\u0019A\u001f\u0011\u0007i*\t\u0007\u0002\u0004\u0002<Q\u0011\r!\u0010\t\u0004u\u0015\u0015DABA7)\t\u0007Q\bE\u0002;\u000bS\"Q\u0001\u0010\u000bC\u0002u\u00022AOC7\t\u0019\t\t\u000f\u0006b\u0001{A\u0019!(\"\u001d\u0005\r\t\u0015BC1\u0001>!\rQTQ\u000f\u0003\u0007\u0005_\"\"\u0019A\u001f\u0011\u0007i*I\b\u0002\u0004\u0003@R\u0011\r!\u0010\t\u0004u\u0015uDABB\u000b)\t\u0007Q\bE\u0002;\u000b\u0003#aa!\u001d\u0015\u0005\u0004i\u0004c\u0001\u001e\u0006\u0006\u0012111\u001b\u000bC\u0002u\u00022AOCE\t\u0019!Y\u0004\u0006b\u0001{A\u0019!(\"$\u0005\r\u0011%FC1\u0001>!\rQT\u0011\u0013\u0003\u0007\u000b;!\"\u0019A\u001f\u0011\u0007i*)\n\u0002\u0004\u0006\u0018R\u0011\r!\u0010\u0002\u0002#B\u0019!(b\'\u0005\u000bM#\"\u0019A\u001f\u0011\r\t*VqTCM!\u0019Av-b\u0015\u0006\"B1\u0001lZC,\u000bG\u0003b\u0001W4\u0006\\\u0015\u0015\u0006C\u0002-h\u000b?*9\u000b\u0005\u0004YO\u0016\rT\u0011\u0016\t\u00071\u001e,9\'b+\u0011\ra;W1NCW!\u0019Av-b\u001c\u00060B1\u0001lZC:\u000bc\u0003b\u0001W4\u0006x\u0015M\u0006C\u0002-h\u000bw*)\f\u0005\u0004YO\u0016}Tq\u0017\t\u00071\u001e,\u0019)\"/\u0011\ra;WqQC^!\u0019Av-b#\u0006>B1\u0001lZCH\u000b\u007f\u0003R\u0001W4\u0006\u0014^\u000bQB\u001a8U_B\u0013x\u000eZ;diFBT\u0003KCc\u000b#,).\"7\u0006^\u0016\u0005XQ]Cu\u000b[,\t0\">\u0006z\u0016uh\u0011\u0001D\u0003\r\u00131iA\"\u0005\u0007\u0016\u0019mQCACd!\u0019i%!\"3\u0007\u001eAI#%b3\u0006P\u0016MWq[Cn\u000b?,\u0019/b:\u0006l\u0016=X1_C|\u000bw,yPb\u0001\u0007\b\u0019-aq\u0002D\n\r3I1!\"4$\u0005)1UO\\2uS>t\u0017\u0007\u000f\t\u0004u\u0015EG!\u00022\u0016\u0005\u0004i\u0004c\u0001\u001e\u0006V\u0012)A/\u0006b\u0001{A\u0019!(\"7\u0005\r\u0005=QC1\u0001>!\rQTQ\u001c\u0003\u0007\u0003w)\"\u0019A\u001f\u0011\u0007i*\t\u000f\u0002\u0004\u0002nU\u0011\r!\u0010\t\u0004u\u0015\u0015H!\u0002\u001f\u0016\u0005\u0004i\u0004c\u0001\u001e\u0006j\u00121\u0011\u0011]\u000bC\u0002u\u00022AOCw\t\u0019\u0011)#\u0006b\u0001{A\u0019!(\"=\u0005\r\t=TC1\u0001>!\rQTQ\u001f\u0003\u0007\u0005\u007f+\"\u0019A\u001f\u0011\u0007i*I\u0010\u0002\u0004\u0004\u0016U\u0011\r!\u0010\t\u0004u\u0015uHABB9+\t\u0007Q\bE\u0002;\r\u0003!aaa5\u0016\u0005\u0004i\u0004c\u0001\u001e\u0007\u0006\u00111A1H\u000bC\u0002u\u00022A\u000fD\u0005\t\u0019!I+\u0006b\u0001{A\u0019!H\"\u0004\u0005\r\u0015uQC1\u0001>!\rQd\u0011\u0003\u0003\u0007\u000b/+\"\u0019A\u001f\u0011\u0007i2)\u0002\u0002\u0004\u0007\u0018U\u0011\r!\u0010\u0002\u0002%B\u0019!Hb\u0007\u0005\u000bM+\"\u0019A\u001f\u0011\r\t*fq\u0004D\r!\u0019Av-b4\u0007\"A1\u0001lZCj\rG\u0001b\u0001W4\u0006X\u001a\u0015\u0002C\u0002-h\u000b749\u0003\u0005\u0004YO\u0016}g\u0011\u0006\t\u00071\u001e,\u0019Ob\u000b\u0011\ra;Wq\u001dD\u0017!\u0019Av-b;\u00070A1\u0001lZCx\rc\u0001b\u0001W4\u0006t\u001aM\u0002C\u0002-h\u000bo4)\u0004\u0005\u0004YO\u0016mhq\u0007\t\u00071\u001e,yP\"\u000f\u0011\ra;g1\u0001D\u001e!\u0019AvMb\u0002\u0007>A1\u0001l\u001aD\u0006\r\u007f\u0001b\u0001W4\u0007\u0010\u0019\u0005\u0003#\u0002-h\r\'9\u0016!\u00044o)>\u0004&o\u001c3vGR\f\u0014(\u0006\u0016\u0007H\u0019Mcq\u000bD.\r?2\u0019Gb\u001a\u0007l\u0019=d1\u000fD<\rw2yHb!\u0007\b\u001a-eq\u0012DJ\r/3YJ\")\u0016\u0005\u0019%\u0003CB\'\u0003\r\u00172\u0019\u000bE\u0016#\r\u001b2\tF\"\u0016\u0007Z\u0019uc\u0011\rD3\rS2iG\"\u001d\u0007v\u0019edQ\u0010DA\r\u000b3II\"$\u0007\u0012\u001aUe\u0011\u0014DP\u0013\r1ye\t\u0002\u000b\rVt7\r^5p]FJ\u0004c\u0001\u001e\u0007T\u0011)!M\u0006b\u0001{A\u0019!Hb\u0016\u0005\u000bQ4\"\u0019A\u001f\u0011\u0007i2Y\u0006\u0002\u0004\u0002\u0010Y\u0011\r!\u0010\t\u0004u\u0019}CABA\u001e-\t\u0007Q\bE\u0002;\rG\"a!!\u001c\u0017\u0005\u0004i\u0004c\u0001\u001e\u0007h\u0011)AH\u0006b\u0001{A\u0019!Hb\u001b\u0005\r\u0005\u0005hC1\u0001>!\rQdq\u000e\u0003\u0007\u0005K1\"\u0019A\u001f\u0011\u0007i2\u0019\b\u0002\u0004\u0003pY\u0011\r!\u0010\t\u0004u\u0019]DA\u0002B`-\t\u0007Q\bE\u0002;\rw\"aa!\u0006\u0017\u0005\u0004i\u0004c\u0001\u001e\u0007\u0000\u001111\u0011\u000f\fC\u0002u\u00022A\u000fDB\t\u0019\u0019\u0019N\u0006b\u0001{A\u0019!Hb\"\u0005\r\u0011mbC1\u0001>!\rQd1\u0012\u0003\u0007\tS3\"\u0019A\u001f\u0011\u0007i2y\t\u0002\u0004\u0006\u001eY\u0011\r!\u0010\t\u0004u\u0019MEABCL-\t\u0007Q\bE\u0002;\r/#aAb\u0006\u0017\u0005\u0004i\u0004c\u0001\u001e\u0007\u001c\u00121aQ\u0014\fC\u0002u\u0012\u0011a\u0015\t\u0004u\u0019\u0005F!B*\u0017\u0005\u0004i\u0004C\u0002\u0012V\rK3y\n\u0005\u0004YO\u001aEcq\u0015\t\u00071\u001e4)F\"+\u0011\ra;g\u0011\fDV!\u0019AvM\"\u0018\u0007.B1\u0001l\u001aD1\r_\u0003b\u0001W4\u0007f\u0019E\u0006C\u0002-h\rS2\u0019\f\u0005\u0004YO\u001a5dQ\u0017\t\u00071\u001e4\tHb.\u0011\ra;gQ\u000fD]!\u0019AvM\"\u001f\u0007<B1\u0001l\u001aD?\r{\u0003b\u0001W4\u0007\u0002\u001a}\u0006C\u0002-h\r\u000b3\t\r\u0005\u0004YO\u001a%e1\u0019\t\u00071\u001e4iI\"2\u0011\ra;g\u0011\u0013Dd!\u0019AvM\"&\u0007JB)\u0001l\u001aDM/\u0006iaM\u001c+p!J|G-^2ueA*BFb4\u0007\\\u001a}g1\u001dDt\rW4yOb=\u0007x\u001amhq`D\u0002\u000f\u000f9Yab\u0004\b\u0014\u001d]q1DD\u0010\u000fG99c\"\f\u0016\u0005\u0019E\u0007CB\'\u0003\r\'<y\u0003E\u0017#\r+4IN\"8\u0007b\u001a\u0015h\u0011\u001eDw\rc4)P\"?\u0007~\u001e\u0005qQAD\u0005\u000f\u001b9\tb\"\u0006\b\u001a\u001duq\u0011ED\u0013\u000fWI1Ab6$\u0005)1UO\\2uS>t\'\u0007\r\t\u0004u\u0019mG!\u00022\u0018\u0005\u0004i\u0004c\u0001\u001e\u0007`\u0012)Ao\u0006b\u0001{A\u0019!Hb9\u0005\r\u0005=qC1\u0001>!\rQdq\u001d\u0003\u0007\u0003w9\"\u0019A\u001f\u0011\u0007i2Y\u000f\u0002\u0004\u0002n]\u0011\r!\u0010\t\u0004u\u0019=H!\u0002\u001f\u0018\u0005\u0004i\u0004c\u0001\u001e\u0007t\u00121\u0011\u0011]\fC\u0002u\u00022A\u000fD|\t\u0019\u0011)c\u0006b\u0001{A\u0019!Hb?\u0005\r\t=tC1\u0001>!\rQdq \u0003\u0007\u0005\u007f;\"\u0019A\u001f\u0011\u0007i:\u0019\u0001\u0002\u0004\u0004\u0016]\u0011\r!\u0010\t\u0004u\u001d\u001dAABB9/\t\u0007Q\bE\u0002;\u000f\u0017!aaa5\u0018\u0005\u0004i\u0004c\u0001\u001e\b\u0010\u00111A1H\fC\u0002u\u00022AOD\n\t\u0019!Ik\u0006b\u0001{A\u0019!hb\u0006\u0005\r\u0015uqC1\u0001>!\rQt1\u0004\u0003\u0007\u000b/;\"\u0019A\u001f\u0011\u0007i:y\u0002\u0002\u0004\u0007\u0018]\u0011\r!\u0010\t\u0004u\u001d\rBA\u0002DO/\t\u0007Q\bE\u0002;\u000fO!aa\"\u000b\u0018\u0005\u0004i$!\u0001+\u0011\u0007i:i\u0003B\u0003T/\t\u0007Q\b\u0005\u0004#+\u001eEr1\u0006\t\u00071\u001e4Inb\r\u0011\ra;gQ\\D\u001b!\u0019AvM\"9\b8A1\u0001l\u001aDs\u000fs\u0001b\u0001W4\u0007j\u001em\u0002C\u0002-h\r[<i\u0004\u0005\u0004YO\u001aExq\b\t\u00071\u001e4)p\"\u0011\u0011\ra;g\u0011`D\"!\u0019AvM\"@\bFA1\u0001lZD\u0001\u000f\u000f\u0002b\u0001W4\b\u0006\u001d%\u0003C\u0002-h\u000f\u00139Y\u0005\u0005\u0004YO\u001e5qQ\n\t\u00071\u001e<\tbb\u0014\u0011\ra;wQCD)!\u0019Avm\"\u0007\bTA1\u0001lZD\u000f\u000f+\u0002b\u0001W4\b\"\u001d]\u0003#\u0002-h\u000fK9\u0016!\u00044o)>\u0004&o\u001c3vGR\u0014\u0014\'\u0006\u0018\b^\u001d%tQND9\u000fk:Ih\" \b\u0002\u001e\u0015u\u0011RDG\u000f#;)j\"\'\b\u001e\u001e\u0005vQUDU\u000f[;\tl\".\b:\u001e}VCAD0!\u0019i%a\"\u0019\bBBy#eb\u0019\bh\u001d-tqND:\u000fo:Yhb \b\u0004\u001e\u001du1RDH\u000f\';9jb\'\b \u001e\rvqUDV\u000f_;\u0019lb.\b>&\u0019qQM\u0012\u0003\u0015\u0019+hn\u0019;j_:\u0014\u0014\u0007E\u0002;\u000fS\"QA\u0019\rC\u0002u\u00022AOD7\t\u0015!\bD1\u0001>!\rQt\u0011\u000f\u0003\u0007\u0003\u001fA\"\u0019A\u001f\u0011\u0007i:)\b\u0002\u0004\u0002<a\u0011\r!\u0010\t\u0004u\u001deDABA71\t\u0007Q\bE\u0002;\u000f{\"Q\u0001\u0010\rC\u0002u\u00022AODA\t\u0019\t\t\u000f\u0007b\u0001{A\u0019!h\"\"\u0005\r\t\u0015\u0002D1\u0001>!\rQt\u0011\u0012\u0003\u0007\u0005_B\"\u0019A\u001f\u0011\u0007i:i\t\u0002\u0004\u0003@b\u0011\r!\u0010\t\u0004u\u001dEEABB\u000b1\t\u0007Q\bE\u0002;\u000f+#aa!\u001d\u0019\u0005\u0004i\u0004c\u0001\u001e\b\u001a\u0012111\u001b\rC\u0002u\u00022AODO\t\u0019!Y\u0004\u0007b\u0001{A\u0019!h\")\u0005\r\u0011%\u0006D1\u0001>!\rQtQ\u0015\u0003\u0007\u000b;A\"\u0019A\u001f\u0011\u0007i:I\u000b\u0002\u0004\u0006\u0018b\u0011\r!\u0010\t\u0004u\u001d5FA\u0002D\f1\t\u0007Q\bE\u0002;\u000fc#aA\"(\u0019\u0005\u0004i\u0004c\u0001\u001e\b6\u00121q\u0011\u0006\rC\u0002u\u00022AOD]\t\u00199Y\f\u0007b\u0001{\t\tQ\u000bE\u0002;\u000f\u007f#Qa\u0015\rC\u0002u\u0002bAI+\bD\u001eu\u0006C\u0002-h\u000fO:)\r\u0005\u0004YO\u001e-tq\u0019\t\u00071\u001e<yg\"3\u0011\ra;w1ODf!\u0019Avmb\u001e\bNB1\u0001lZD>\u000f\u001f\u0004b\u0001W4\b\u0000\u001dE\u0007C\u0002-h\u000f\u0007;\u0019\u000e\u0005\u0004YO\u001e\u001duQ\u001b\t\u00071\u001e<Yib6\u0011\ra;wqRDm!\u0019Avmb%\b\\B1\u0001lZDL\u000f;\u0004b\u0001W4\b\u001c\u001e}\u0007C\u0002-h\u000f?;\t\u000f\u0005\u0004YO\u001e\rv1\u001d\t\u00071\u001e<9k\":\u0011\ra;w1VDt!\u0019Avmb,\bjB1\u0001lZDZ\u000fW\u0004R\u0001W4\b8^\u000bQB\u001a8U_B\u0013x\u000eZ;diJ\u0012T\u0003MDy\u000f{D\t\u0001#\u0002\t\n!5\u0001\u0012\u0003E\u000b\u00113Ai\u0002#\t\t&!%\u0002R\u0006E\u0019\u0011kAI\u0004#\u0010\tB!\u0015\u0003\u0012\nE\'\u0011#B9&\u0006\u0002\btB1QJAD{\u00113\u0002\u0012GID|\u000fw<y\u0010c\u0001\t\b!-\u0001r\u0002E\n\u0011/AY\u0002c\b\t$!\u001d\u00022\u0006E\u0018\u0011gA9\u0004c\u000f\t@!\r\u0003r\tE&\u0011\u001fB)&C\u0002\bz\u000e\u0012!BR;oGRLwN\u001c\u001a3!\rQtQ \u0003\u0006Ef\u0011\r!\u0010\t\u0004u!\u0005A!\u0002;\u001a\u0005\u0004i\u0004c\u0001\u001e\t\u0006\u00111\u0011qB\rC\u0002u\u00022A\u000fE\u0005\t\u0019\tY$\u0007b\u0001{A\u0019!\b#\u0004\u0005\r\u00055\u0014D1\u0001>!\rQ\u0004\u0012\u0003\u0003\u0006ye\u0011\r!\u0010\t\u0004u!UAABAq3\t\u0007Q\bE\u0002;\u00113!aA!\n\u001a\u0005\u0004i\u0004c\u0001\u001e\t\u001e\u00111!qN\rC\u0002u\u00022A\u000fE\u0011\t\u0019\u0011y,\u0007b\u0001{A\u0019!\b#\n\u0005\r\rU\u0011D1\u0001>!\rQ\u0004\u0012\u0006\u0003\u0007\u0007cJ\"\u0019A\u001f\u0011\u0007iBi\u0003\u0002\u0004\u0004Tf\u0011\r!\u0010\t\u0004u!EBA\u0002C\u001e3\t\u0007Q\bE\u0002;\u0011k!a\u0001\"+\u001a\u0005\u0004i\u0004c\u0001\u001e\t:\u00111QQD\rC\u0002u\u00022A\u000fE\u001f\t\u0019)9*\u0007b\u0001{A\u0019!\b#\u0011\u0005\r\u0019]\u0011D1\u0001>!\rQ\u0004R\t\u0003\u0007\r;K\"\u0019A\u001f\u0011\u0007iBI\u0005\u0002\u0004\b*e\u0011\r!\u0010\t\u0004u!5CABD^3\t\u0007Q\bE\u0002;\u0011#\"a\u0001c\u0015\u001a\u0005\u0004i$!\u0001,\u0011\u0007iB9\u0006B\u0003T3\t\u0007Q\b\u0005\u0004#+\"m\u0003R\u000b\t\u00071\u001e<Y\u0010#\u0018\u0011\ra;wq E0!\u0019Av\rc\u0001\tbA1\u0001l\u001aE\u0004\u0011G\u0002b\u0001W4\t\f!\u0015\u0004C\u0002-h\u0011\u001fA9\u0007\u0005\u0004YO\"M\u0001\u0012\u000e\t\u00071\u001eD9\u0002c\u001b\u0011\ra;\u00072\u0004E7!\u0019Av\rc\b\tpA1\u0001l\u001aE\u0012\u0011c\u0002b\u0001W4\t(!M\u0004C\u0002-h\u0011WA)\b\u0005\u0004YO\"=\u0002r\u000f\t\u00071\u001eD\u0019\u0004#\u001f\u0011\ra;\u0007r\u0007E>!\u0019Av\rc\u000f\t~A1\u0001l\u001aE \u0011\u007f\u0002b\u0001W4\tD!\u0005\u0005C\u0002-h\u0011\u000fB\u0019\t\u0005\u0004YO\"-\u0003R\u0011\t\u00061\u001eDye\u0016
    #9 = Utf8               shapeless/ops/FnToProductInstances$$anon$1
   #10 = Class              #9            // shapeless/ops/FnToProductInstances$$anon$1
   #11 = Utf8               shapeless/ops/FnToProductInstances$$anon$10
   #12 = Class              #11           // shapeless/ops/FnToProductInstances$$anon$10
   #13 = Utf8               shapeless/ops/FnToProductInstances$$anon$11
   #14 = Class              #13           // shapeless/ops/FnToProductInstances$$anon$11
   #15 = Utf8               shapeless/ops/FnToProductInstances$$anon$12
   #16 = Class              #15           // shapeless/ops/FnToProductInstances$$anon$12
   #17 = Utf8               shapeless/ops/FnToProductInstances$$anon$13
   #18 = Class              #17           // shapeless/ops/FnToProductInstances$$anon$13
   #19 = Utf8               shapeless/ops/FnToProductInstances$$anon$14
   #20 = Class              #19           // shapeless/ops/FnToProductInstances$$anon$14
   #21 = Utf8               shapeless/ops/FnToProductInstances$$anon$15
   #22 = Class              #21           // shapeless/ops/FnToProductInstances$$anon$15
   #23 = Utf8               shapeless/ops/FnToProductInstances$$anon$16
   #24 = Class              #23           // shapeless/ops/FnToProductInstances$$anon$16
   #25 = Utf8               shapeless/ops/FnToProductInstances$$anon$17
   #26 = Class              #25           // shapeless/ops/FnToProductInstances$$anon$17
   #27 = Utf8               shapeless/ops/FnToProductInstances$$anon$18
   #28 = Class              #27           // shapeless/ops/FnToProductInstances$$anon$18
   #29 = Utf8               shapeless/ops/FnToProductInstances$$anon$19
   #30 = Class              #29           // shapeless/ops/FnToProductInstances$$anon$19
   #31 = Utf8               shapeless/ops/FnToProductInstances$$anon$2
   #32 = Class              #31           // shapeless/ops/FnToProductInstances$$anon$2
   #33 = Utf8               shapeless/ops/FnToProductInstances$$anon$20
   #34 = Class              #33           // shapeless/ops/FnToProductInstances$$anon$20
   #35 = Utf8               shapeless/ops/FnToProductInstances$$anon$21
   #36 = Class              #35           // shapeless/ops/FnToProductInstances$$anon$21
   #37 = Utf8               shapeless/ops/FnToProductInstances$$anon$22
   #38 = Class              #37           // shapeless/ops/FnToProductInstances$$anon$22
   #39 = Utf8               shapeless/ops/FnToProductInstances$$anon$23
   #40 = Class              #39           // shapeless/ops/FnToProductInstances$$anon$23
   #41 = Utf8               shapeless/ops/FnToProductInstances$$anon$3
   #42 = Class              #41           // shapeless/ops/FnToProductInstances$$anon$3
   #43 = Utf8               shapeless/ops/FnToProductInstances$$anon$4
   #44 = Class              #43           // shapeless/ops/FnToProductInstances$$anon$4
   #45 = Utf8               shapeless/ops/FnToProductInstances$$anon$5
   #46 = Class              #45           // shapeless/ops/FnToProductInstances$$anon$5
   #47 = Utf8               shapeless/ops/FnToProductInstances$$anon$6
   #48 = Class              #47           // shapeless/ops/FnToProductInstances$$anon$6
   #49 = Utf8               shapeless/ops/FnToProductInstances$$anon$7
   #50 = Class              #49           // shapeless/ops/FnToProductInstances$$anon$7
   #51 = Utf8               shapeless/ops/FnToProductInstances$$anon$8
   #52 = Class              #51           // shapeless/ops/FnToProductInstances$$anon$8
   #53 = Utf8               shapeless/ops/FnToProductInstances$$anon$9
   #54 = Class              #53           // shapeless/ops/FnToProductInstances$$anon$9
   #55 = Utf8               shapeless/ops/function$FnToProduct
   #56 = Class              #55           // shapeless/ops/function$FnToProduct
   #57 = Utf8               shapeless/ops/function
   #58 = Class              #57           // shapeless/ops/function
   #59 = Utf8               FnToProduct
   #60 = Utf8               fnToProduct0$
   #61 = Utf8               (Lshapeless/ops/FnToProductInstances;)Lshapeless/ops/function$FnToProduct;
   #62 = Utf8               $this
   #63 = Utf8               fnToProduct0
   #64 = Utf8               ()Lshapeless/ops/function$FnToProduct;
   #65 = NameAndType        #63:#64       // fnToProduct0:()Lshapeless/ops/function$FnToProduct;
   #66 = InterfaceMethodref #2.#65        // shapeless/ops/FnToProductInstances.fnToProduct0:()Lshapeless/ops/function$FnToProduct;
   #67 = Utf8               Lshapeless/ops/FnToProductInstances;
   #68 = Utf8               <Res:Ljava/lang/Object;>()Lshapeless/ops/function$FnToProduct<Lscala/Function0<TRes;>;>;
   #69 = Utf8               <init>
   #70 = Utf8               (Lshapeless/ops/FnToProductInstances;)V
   #71 = NameAndType        #69:#70       // "<init>":(Lshapeless/ops/FnToProductInstances;)V
   #72 = Methodref          #10.#71       // shapeless/ops/FnToProductInstances$$anon$1."<init>":(Lshapeless/ops/FnToProductInstances;)V
   #73 = Utf8               this
   #74 = Utf8               fnToProduct1$
   #75 = Utf8               fnToProduct1
   #76 = NameAndType        #75:#64       // fnToProduct1:()Lshapeless/ops/function$FnToProduct;
   #77 = InterfaceMethodref #2.#76        // shapeless/ops/FnToProductInstances.fnToProduct1:()Lshapeless/ops/function$FnToProduct;
   #78 = Utf8               <A:Ljava/lang/Object;Res:Ljava/lang/Object;>()Lshapeless/ops/function$FnToProduct<Lscala/Function1<TA;TRes;>;>;
   #79 = Methodref          #32.#71       // shapeless/ops/FnToProductInstances$$anon$2."<init>":(Lshapeless/ops/FnToProductInstances;)V
   #80 = Utf8               fnToProduct2$
   #81 = Utf8               fnToProduct2
   #82 = NameAndType        #81:#64       // fnToProduct2:()Lshapeless/ops/function$FnToProduct;
   #83 = InterfaceMethodref #2.#82        // shapeless/ops/FnToProductInstances.fnToProduct2:()Lshapeless/ops/function$FnToProduct;
   #84 = Utf8               <A:Ljava/lang/Object;B:Ljava/lang/Object;Res:Ljava/lang/Object;>()Lshapeless/ops/function$FnToProduct<Lscala/Function2<TA;TB;TRes;>;>;
   #85 = Methodref          #42.#71       // shapeless/ops/FnToProductInstances$$anon$3."<init>":(Lshapeless/ops/FnToProductInstances;)V
   #86 = Utf8               fnToProduct3$
   #87 = Utf8               fnToProduct3
   #88 = NameAndType        #87:#64       // fnToProduct3:()Lshapeless/ops/function$FnToProduct;
   #89 = InterfaceMethodref #2.#88        // shapeless/ops/FnToProductInstances.fnToProduct3:()Lshapeless/ops/function$FnToProduct;
   #90 = Utf8               <A:Ljava/lang/Object;B:Ljava/lang/Object;C:Ljava/lang/Object;Res:Ljava/lang/Object;>()Lshapeless/ops/function$FnToProduct<Lscala/Function3<TA;TB;TC;TRes;>;>;
   #91 = Methodref          #44.#71       // shapeless/ops/FnToProductInstances$$anon$4."<init>":(Lshapeless/ops/FnToProductInstances;)V
   #92 = Utf8               fnToProduct4$
   #93 = Utf8               fnToProduct4
   #94 = NameAndType        #93:#64       // fnToProduct4:()Lshapeless/ops/function$FnToProduct;
   #95 = InterfaceMethodref #2.#94        // shapeless/ops/FnToProductInstances.fnToProduct4:()Lshapeless/ops/function$FnToProduct;
   #96 = Utf8               <A:Ljava/lang/Object;B:Ljava/lang/Object;C:Ljava/lang/Object;D:Ljava/lang/Object;Res:Ljava/lang/Object;>()Lshapeless/ops/function$FnToProduct<Lscala/Function4<TA;TB;TC;TD;TRes;>;>;
   #97 = Methodref          #46.#71       // shapeless/ops/FnToProductInstances$$anon$5."<init>":(Lshapeless/ops/FnToProductInstances;)V
   #98 = Utf8               fnToProduct5$
   #99 = Utf8               fnToProduct5
  #100 = NameAndType        #99:#64       // fnToProduct5:()Lshapeless/ops/function$FnToProduct;
  #101 = InterfaceMethodref #2.#100       // shapeless/ops/FnToProductInstances.fnToProduct5:()Lshapeless/ops/function$FnToProduct;
  #102 = Utf8               <A:Ljava/lang/Object;B:Ljava/lang/Object;C:Ljava/lang/Object;D:Ljava/lang/Object;E:Ljava/lang/Object;Res:Ljava/lang/Object;>()Lshapeless/ops/function$FnToProduct<Lscala/Function5<TA;TB;TC;TD;TE;TRes;>;>;
  #103 = Methodref          #48.#71       // shapeless/ops/FnToProductInstances$$anon$6."<init>":(Lshapeless/ops/FnToProductInstances;)V
  #104 = Utf8               fnToProduct6$
  #105 = Utf8               fnToProduct6
  #106 = NameAndType        #105:#64      // fnToProduct6:()Lshapeless/ops/function$FnToProduct;
  #107 = InterfaceMethodref #2.#106       // shapeless/ops/FnToProductInstances.fnToProduct6:()Lshapeless/ops/function$FnToProduct;
  #108 = Utf8               <A:Ljava/lang/Object;B:Ljava/lang/Object;C:Ljava/lang/Object;D:Ljava/lang/Object;E:Ljava/lang/Object;F:Ljava/lang/Object;Res:Ljava/lang/Object;>()Lshapeless/ops/function$FnToProduct<Lscala/Function6<TA;TB;TC;TD;TE;TF;TRes;>;>;
  #109 = Methodref          #50.#71       // shapeless/ops/FnToProductInstances$$anon$7."<init>":(Lshapeless/ops/FnToProductInstances;)V
  #110 = Utf8               fnToProduct7$
  #111 = Utf8               fnToProduct7
  #112 = NameAndType        #111:#64      // fnToProduct7:()Lshapeless/ops/function$FnToProduct;
  #113 = InterfaceMethodref #2.#112       // shapeless/ops/FnToProductInstances.fnToProduct7:()Lshapeless/ops/function$FnToProduct;
  #114 = Utf8               <A:Ljava/lang/Object;B:Ljava/lang/Object;C:Ljava/lang/Object;D:Ljava/lang/Object;E:Ljava/lang/Object;F:Ljava/lang/Object;G:Ljava/lang/Object;Res:Ljava/lang/Object;>()Lshapeless/ops/function$FnToProduct<Lscala/Function7<TA;TB;TC;TD;TE;TF;TG;TRes;>;>;
  #115 = Methodref          #52.#71       // shapeless/ops/FnToProductInstances$$anon$8."<init>":(Lshapeless/ops/FnToProductInstances;)V
  #116 = Utf8               fnToProduct8$
  #117 = Utf8               fnToProduct8
  #118 = NameAndType        #117:#64      // fnToProduct8:()Lshapeless/ops/function$FnToProduct;
  #119 = InterfaceMethodref #2.#118       // shapeless/ops/FnToProductInstances.fnToProduct8:()Lshapeless/ops/function$FnToProduct;
  #120 = Utf8               <A:Ljava/lang/Object;B:Ljava/lang/Object;C:Ljava/lang/Object;D:Ljava/lang/Object;E:Ljava/lang/Object;F:Ljava/lang/Object;G:Ljava/lang/Object;H:Ljava/lang/Object;Res:Ljava/lang/Object;>()Lshapeless/ops/function$FnToProduct<Lscala/Function8<TA;TB;TC;TD;TE;TF;TG;TH;TRes;>;>;
  #121 = Methodref          #54.#71       // shapeless/ops/FnToProductInstances$$anon$9."<init>":(Lshapeless/ops/FnToProductInstances;)V
  #122 = Utf8               fnToProduct9$
  #123 = Utf8               fnToProduct9
  #124 = NameAndType        #123:#64      // fnToProduct9:()Lshapeless/ops/function$FnToProduct;
  #125 = InterfaceMethodref #2.#124       // shapeless/ops/FnToProductInstances.fnToProduct9:()Lshapeless/ops/function$FnToProduct;
  #126 = Utf8               <A:Ljava/lang/Object;B:Ljava/lang/Object;C:Ljava/lang/Object;D:Ljava/lang/Object;E:Ljava/lang/Object;F:Ljava/lang/Object;G:Ljava/lang/Object;H:Ljava/lang/Object;I:Ljava/lang/Object;Res:Ljava/lang/Object;>()Lshapeless/ops/function$FnToProduct<Lscala/Function9<TA;TB;TC;TD;TE;TF;TG;TH;TI;TRes;>;>;
  #127 = Methodref          #12.#71       // shapeless/ops/FnToProductInstances$$anon$10."<init>":(Lshapeless/ops/FnToProductInstances;)V
  #128 = Utf8               fnToProduct10$
  #129 = Utf8               fnToProduct10
  #130 = NameAndType        #129:#64      // fnToProduct10:()Lshapeless/ops/function$FnToProduct;
  #131 = InterfaceMethodref #2.#130       // shapeless/ops/FnToProductInstances.fnToProduct10:()Lshapeless/ops/function$FnToProduct;
  #132 = Utf8               <A:Ljava/lang/Object;B:Ljava/lang/Object;C:Ljava/lang/Object;D:Ljava/lang/Object;E:Ljava/lang/Object;F:Ljava/lang/Object;G:Ljava/lang/Object;H:Ljava/lang/Object;I:Ljava/lang/Object;J:Ljava/lang/Object;Res:Ljava/lang/Object;>()Lshapeless/ops/function$FnToProduct<Lscala/Function10<TA;TB;TC;TD;TE;TF;TG;TH;TI;TJ;TRes;>;>;
  #133 = Methodref          #14.#71       // shapeless/ops/FnToProductInstances$$anon$11."<init>":(Lshapeless/ops/FnToProductInstances;)V
  #134 = Utf8               fnToProduct11$
  #135 = Utf8               fnToProduct11
  #136 = NameAndType        #135:#64      // fnToProduct11:()Lshapeless/ops/function$FnToProduct;
  #137 = InterfaceMethodref #2.#136       // shapeless/ops/FnToProductInstances.fnToProduct11:()Lshapeless/ops/function$FnToProduct;
  #138 = Utf8               <A:Ljava/lang/Object;B:Ljava/lang/Object;C:Ljava/lang/Object;D:Ljava/lang/Object;E:Ljava/lang/Object;F:Ljava/lang/Object;G:Ljava/lang/Object;H:Ljava/lang/Object;I:Ljava/lang/Object;J:Ljava/lang/Object;K:Ljava/lang/Object;Res:Ljava/lang/Object;>()Lshapeless/ops/function$FnToProduct<Lscala/Function11<TA;TB;TC;TD;TE;TF;TG;TH;TI;TJ;TK;TRes;>;>;
  #139 = Methodref          #16.#71       // shapeless/ops/FnToProductInstances$$anon$12."<init>":(Lshapeless/ops/FnToProductInstances;)V
  #140 = Utf8               fnToProduct12$
  #141 = Utf8               fnToProduct12
  #142 = NameAndType        #141:#64      // fnToProduct12:()Lshapeless/ops/function$FnToProduct;
  #143 = InterfaceMethodref #2.#142       // shapeless/ops/FnToProductInstances.fnToProduct12:()Lshapeless/ops/function$FnToProduct;
  #144 = Utf8               <A:Ljava/lang/Object;B:Ljava/lang/Object;C:Ljava/lang/Object;D:Ljava/lang/Object;E:Ljava/lang/Object;F:Ljava/lang/Object;G:Ljava/lang/Object;H:Ljava/lang/Object;I:Ljava/lang/Object;J:Ljava/lang/Object;K:Ljava/lang/Object;L:Ljava/lang/Object;Res:Ljava/lang/Object;>()Lshapeless/ops/function$FnToProduct<Lscala/Function12<TA;TB;TC;TD;TE;TF;TG;TH;TI;TJ;TK;TL;TRes;>;>;
  #145 = Methodref          #18.#71       // shapeless/ops/FnToProductInstances$$anon$13."<init>":(Lshapeless/ops/FnToProductInstances;)V
  #146 = Utf8               fnToProduct13$
  #147 = Utf8               fnToProduct13
  #148 = NameAndType        #147:#64      // fnToProduct13:()Lshapeless/ops/function$FnToProduct;
  #149 = InterfaceMethodref #2.#148       // shapeless/ops/FnToProductInstances.fnToProduct13:()Lshapeless/ops/function$FnToProduct;
  #150 = Utf8               <A:Ljava/lang/Object;B:Ljava/lang/Object;C:Ljava/lang/Object;D:Ljava/lang/Object;E:Ljava/lang/Object;F:Ljava/lang/Object;G:Ljava/lang/Object;H:Ljava/lang/Object;I:Ljava/lang/Object;J:Ljava/lang/Object;K:Ljava/lang/Object;L:Ljava/lang/Object;M:Ljava/lang/Object;Res:Ljava/lang/Object;>()Lshapeless/ops/function$FnToProduct<Lscala/Function13<TA;TB;TC;TD;TE;TF;TG;TH;TI;TJ;TK;TL;TM;TRes;>;>;
  #151 = Methodref          #20.#71       // shapeless/ops/FnToProductInstances$$anon$14."<init>":(Lshapeless/ops/FnToProductInstances;)V
  #152 = Utf8               fnToProduct14$
  #153 = Utf8               fnToProduct14
  #154 = NameAndType        #153:#64      // fnToProduct14:()Lshapeless/ops/function$FnToProduct;
  #155 = InterfaceMethodref #2.#154       // shapeless/ops/FnToProductInstances.fnToProduct14:()Lshapeless/ops/function$FnToProduct;
  #156 = Utf8               <A:Ljava/lang/Object;B:Ljava/lang/Object;C:Ljava/lang/Object;D:Ljava/lang/Object;E:Ljava/lang/Object;F:Ljava/lang/Object;G:Ljava/lang/Object;H:Ljava/lang/Object;I:Ljava/lang/Object;J:Ljava/lang/Object;K:Ljava/lang/Object;L:Ljava/lang/Object;M:Ljava/lang/Object;N:Ljava/lang/Object;Res:Ljava/lang/Object;>()Lshapeless/ops/function$FnToProduct<Lscala/Function14<TA;TB;TC;TD;TE;TF;TG;TH;TI;TJ;TK;TL;TM;TN;TRes;>;>;
  #157 = Methodref          #22.#71       // shapeless/ops/FnToProductInstances$$anon$15."<init>":(Lshapeless/ops/FnToProductInstances;)V
  #158 = Utf8               fnToProduct15$
  #159 = Utf8               fnToProduct15
  #160 = NameAndType        #159:#64      // fnToProduct15:()Lshapeless/ops/function$FnToProduct;
  #161 = InterfaceMethodref #2.#160       // shapeless/ops/FnToProductInstances.fnToProduct15:()Lshapeless/ops/function$FnToProduct;
  #162 = Utf8               <A:Ljava/lang/Object;B:Ljava/lang/Object;C:Ljava/lang/Object;D:Ljava/lang/Object;E:Ljava/lang/Object;F:Ljava/lang/Object;G:Ljava/lang/Object;H:Ljava/lang/Object;I:Ljava/lang/Object;J:Ljava/lang/Object;K:Ljava/lang/Object;L:Ljava/lang/Object;M:Ljava/lang/Object;N:Ljava/lang/Object;O:Ljava/lang/Object;Res:Ljava/lang/Object;>()Lshapeless/ops/function$FnToProduct<Lscala/Function15<TA;TB;TC;TD;TE;TF;TG;TH;TI;TJ;TK;TL;TM;TN;TO;TRes;>;>;
  #163 = Methodref          #24.#71       // shapeless/ops/FnToProductInstances$$anon$16."<init>":(Lshapeless/ops/FnToProductInstances;)V
  #164 = Utf8               fnToProduct16$
  #165 = Utf8               fnToProduct16
  #166 = NameAndType        #165:#64      // fnToProduct16:()Lshapeless/ops/function$FnToProduct;
  #167 = InterfaceMethodref #2.#166       // shapeless/ops/FnToProductInstances.fnToProduct16:()Lshapeless/ops/function$FnToProduct;
  #168 = Utf8               <A:Ljava/lang/Object;B:Ljava/lang/Object;C:Ljava/lang/Object;D:Ljava/lang/Object;E:Ljava/lang/Object;F:Ljava/lang/Object;G:Ljava/lang/Object;H:Ljava/lang/Object;I:Ljava/lang/Object;J:Ljava/lang/Object;K:Ljava/lang/Object;L:Ljava/lang/Object;M:Ljava/lang/Object;N:Ljava/lang/Object;O:Ljava/lang/Object;P:Ljava/lang/Object;Res:Ljava/lang/Object;>()Lshapeless/ops/function$FnToProduct<Lscala/Function16<TA;TB;TC;TD;TE;TF;TG;TH;TI;TJ;TK;TL;TM;TN;TO;TP;TRes;>;>;
  #169 = Methodref          #26.#71       // shapeless/ops/FnToProductInstances$$anon$17."<init>":(Lshapeless/ops/FnToProductInstances;)V
  #170 = Utf8               fnToProduct17$
  #171 = Utf8               fnToProduct17
  #172 = NameAndType        #171:#64      // fnToProduct17:()Lshapeless/ops/function$FnToProduct;
  #173 = InterfaceMethodref #2.#172       // shapeless/ops/FnToProductInstances.fnToProduct17:()Lshapeless/ops/function$FnToProduct;
  #174 = Utf8               <A:Ljava/lang/Object;B:Ljava/lang/Object;C:Ljava/lang/Object;D:Ljava/lang/Object;E:Ljava/lang/Object;F:Ljava/lang/Object;G:Ljava/lang/Object;H:Ljava/lang/Object;I:Ljava/lang/Object;J:Ljava/lang/Object;K:Ljava/lang/Object;L:Ljava/lang/Object;M:Ljava/lang/Object;N:Ljava/lang/Object;O:Ljava/lang/Object;P:Ljava/lang/Object;Q:Ljava/lang/Object;Res:Ljava/lang/Object;>()Lshapeless/ops/function$FnToProduct<Lscala/Function17<TA;TB;TC;TD;TE;TF;TG;TH;TI;TJ;TK;TL;TM;TN;TO;TP;TQ;TRes;>;>;
  #175 = Methodref          #28.#71       // shapeless/ops/FnToProductInstances$$anon$18."<init>":(Lshapeless/ops/FnToProductInstances;)V
  #176 = Utf8               fnToProduct18$
  #177 = Utf8               fnToProduct18
  #178 = NameAndType        #177:#64      // fnToProduct18:()Lshapeless/ops/function$FnToProduct;
  #179 = InterfaceMethodref #2.#178       // shapeless/ops/FnToProductInstances.fnToProduct18:()Lshapeless/ops/function$FnToProduct;
  #180 = Utf8               <A:Ljava/lang/Object;B:Ljava/lang/Object;C:Ljava/lang/Object;D:Ljava/lang/Object;E:Ljava/lang/Object;F:Ljava/lang/Object;G:Ljava/lang/Object;H:Ljava/lang/Object;I:Ljava/lang/Object;J:Ljava/lang/Object;K:Ljava/lang/Object;L:Ljava/lang/Object;M:Ljava/lang/Object;N:Ljava/lang/Object;O:Ljava/lang/Object;P:Ljava/lang/Object;Q:Ljava/lang/Object;R:Ljava/lang/Object;Res:Ljava/lang/Object;>()Lshapeless/ops/function$FnToProduct<Lscala/Function18<TA;TB;TC;TD;TE;TF;TG;TH;TI;TJ;TK;TL;TM;TN;TO;TP;TQ;TR;TRes;>;>;
  #181 = Methodref          #30.#71       // shapeless/ops/FnToProductInstances$$anon$19."<init>":(Lshapeless/ops/FnToProductInstances;)V
  #182 = Utf8               fnToProduct19$
  #183 = Utf8               fnToProduct19
  #184 = NameAndType        #183:#64      // fnToProduct19:()Lshapeless/ops/function$FnToProduct;
  #185 = InterfaceMethodref #2.#184       // shapeless/ops/FnToProductInstances.fnToProduct19:()Lshapeless/ops/function$FnToProduct;
  #186 = Utf8               <A:Ljava/lang/Object;B:Ljava/lang/Object;C:Ljava/lang/Object;D:Ljava/lang/Object;E:Ljava/lang/Object;F:Ljava/lang/Object;G:Ljava/lang/Object;H:Ljava/lang/Object;I:Ljava/lang/Object;J:Ljava/lang/Object;K:Ljava/lang/Object;L:Ljava/lang/Object;M:Ljava/lang/Object;N:Ljava/lang/Object;O:Ljava/lang/Object;P:Ljava/lang/Object;Q:Ljava/lang/Object;R:Ljava/lang/Object;S:Ljava/lang/Object;Res:Ljava/lang/Object;>()Lshapeless/ops/function$FnToProduct<Lscala/Function19<TA;TB;TC;TD;TE;TF;TG;TH;TI;TJ;TK;TL;TM;TN;TO;TP;TQ;TR;TS;TRes;>;>;
  #187 = Methodref          #34.#71       // shapeless/ops/FnToProductInstances$$anon$20."<init>":(Lshapeless/ops/FnToProductInstances;)V
  #188 = Utf8               fnToProduct20$
  #189 = Utf8               fnToProduct20
  #190 = NameAndType        #189:#64      // fnToProduct20:()Lshapeless/ops/function$FnToProduct;
  #191 = InterfaceMethodref #2.#190       // shapeless/ops/FnToProductInstances.fnToProduct20:()Lshapeless/ops/function$FnToProduct;
  #192 = Utf8               <A:Ljava/lang/Object;B:Ljava/lang/Object;C:Ljava/lang/Object;D:Ljava/lang/Object;E:Ljava/lang/Object;F:Ljava/lang/Object;G:Ljava/lang/Object;H:Ljava/lang/Object;I:Ljava/lang/Object;J:Ljava/lang/Object;K:Ljava/lang/Object;L:Ljava/lang/Object;M:Ljava/lang/Object;N:Ljava/lang/Object;O:Ljava/lang/Object;P:Ljava/lang/Object;Q:Ljava/lang/Object;R:Ljava/lang/Object;S:Ljava/lang/Object;T:Ljava/lang/Object;Res:Ljava/lang/Object;>()Lshapeless/ops/function$FnToProduct<Lscala/Function20<TA;TB;TC;TD;TE;TF;TG;TH;TI;TJ;TK;TL;TM;TN;TO;TP;TQ;TR;TS;TT;TRes;>;>;
  #193 = Methodref          #36.#71       // shapeless/ops/FnToProductInstances$$anon$21."<init>":(Lshapeless/ops/FnToProductInstances;)V
  #194 = Utf8               fnToProduct21$
  #195 = Utf8               fnToProduct21
  #196 = NameAndType        #195:#64      // fnToProduct21:()Lshapeless/ops/function$FnToProduct;
  #197 = InterfaceMethodref #2.#196       // shapeless/ops/FnToProductInstances.fnToProduct21:()Lshapeless/ops/function$FnToProduct;
  #198 = Utf8               <A:Ljava/lang/Object;B:Ljava/lang/Object;C:Ljava/lang/Object;D:Ljava/lang/Object;E:Ljava/lang/Object;F:Ljava/lang/Object;G:Ljava/lang/Object;H:Ljava/lang/Object;I:Ljava/lang/Object;J:Ljava/lang/Object;K:Ljava/lang/Object;L:Ljava/lang/Object;M:Ljava/lang/Object;N:Ljava/lang/Object;O:Ljava/lang/Object;P:Ljava/lang/Object;Q:Ljava/lang/Object;R:Ljava/lang/Object;S:Ljava/lang/Object;T:Ljava/lang/Object;U:Ljava/lang/Object;Res:Ljava/lang/Object;>()Lshapeless/ops/function$FnToProduct<Lscala/Function21<TA;TB;TC;TD;TE;TF;TG;TH;TI;TJ;TK;TL;TM;TN;TO;TP;TQ;TR;TS;TT;TU;TRes;>;>;
  #199 = Methodref          #38.#71       // shapeless/ops/FnToProductInstances$$anon$22."<init>":(Lshapeless/ops/FnToProductInstances;)V
  #200 = Utf8               fnToProduct22$
  #201 = Utf8               fnToProduct22
  #202 = NameAndType        #201:#64      // fnToProduct22:()Lshapeless/ops/function$FnToProduct;
  #203 = InterfaceMethodref #2.#202       // shapeless/ops/FnToProductInstances.fnToProduct22:()Lshapeless/ops/function$FnToProduct;
  #204 = Utf8               <A:Ljava/lang/Object;B:Ljava/lang/Object;C:Ljava/lang/Object;D:Ljava/lang/Object;E:Ljava/lang/Object;F:Ljava/lang/Object;G:Ljava/lang/Object;H:Ljava/lang/Object;I:Ljava/lang/Object;J:Ljava/lang/Object;K:Ljava/lang/Object;L:Ljava/lang/Object;M:Ljava/lang/Object;N:Ljava/lang/Object;O:Ljava/lang/Object;P:Ljava/lang/Object;Q:Ljava/lang/Object;R:Ljava/lang/Object;S:Ljava/lang/Object;T:Ljava/lang/Object;U:Ljava/lang/Object;V:Ljava/lang/Object;Res:Ljava/lang/Object;>()Lshapeless/ops/function$FnToProduct<Lscala/Function22<TA;TB;TC;TD;TE;TF;TG;TH;TI;TJ;TK;TL;TM;TN;TO;TP;TQ;TR;TS;TT;TU;TV;TRes;>;>;
  #205 = Methodref          #40.#71       // shapeless/ops/FnToProductInstances$$anon$23."<init>":(Lshapeless/ops/FnToProductInstances;)V
  #206 = Utf8               $init$
  #207 = Utf8               Code
  #208 = Utf8               LineNumberTable
  #209 = Utf8               LocalVariableTable
  #210 = Utf8               MethodParameters
  #211 = Utf8               Signature
  #212 = Utf8               InnerClasses
  #213 = Utf8               SourceFile
  #214 = Utf8               RuntimeVisibleAnnotations
  #215 = Utf8               ScalaInlineInfo
  #216 = Utf8               ScalaSig
{
  public static shapeless.ops.function$FnToProduct fnToProduct0$(shapeless.ops.FnToProductInstances);
    descriptor: (Lshapeless/ops/FnToProductInstances;)Lshapeless/ops/function$FnToProduct;
    flags: (0x1009) ACC_PUBLIC, ACC_STATIC, ACC_SYNTHETIC
    Code:
      stack=1, locals=1, args_size=1
         0: aload_0
         1: invokespecial #66                 // InterfaceMethod fnToProduct0:()Lshapeless/ops/function$FnToProduct;
         4: areturn
      LineNumberTable:
        line 27: 0
      LocalVariableTable:
        Start  Length  Slot  Name   Signature
            0       5     0 $this   Lshapeless/ops/FnToProductInstances;
    MethodParameters:
      Name                           Flags
      $this                          final synthetic

  public default <Res extends java.lang.Object> shapeless.ops.function$FnToProduct<scala.Function0<Res>> fnToProduct0();
    descriptor: ()Lshapeless/ops/function$FnToProduct;
    flags: (0x0001) ACC_PUBLIC
    Code:
      stack=3, locals=1, args_size=1
         0: new           #10                 // class shapeless/ops/FnToProductInstances$$anon$1
         3: dup
         4: aconst_null
         5: invokespecial #72                 // Method shapeless/ops/FnToProductInstances$$anon$1."<init>":(Lshapeless/ops/FnToProductInstances;)V
         8: areturn
      LineNumberTable:
        line 33: 0
      LocalVariableTable:
        Start  Length  Slot  Name   Signature
            0       9     0  this   Lshapeless/ops/FnToProductInstances;
    Signature: #68                          // <Res:Ljava/lang/Object;>()Lshapeless/ops/function$FnToProduct<Lscala/Function0<TRes;>;>;

  public static shapeless.ops.function$FnToProduct fnToProduct1$(shapeless.ops.FnToProductInstances);
    descriptor: (Lshapeless/ops/FnToProductInstances;)Lshapeless/ops/function$FnToProduct;
    flags: (0x1009) ACC_PUBLIC, ACC_STATIC, ACC_SYNTHETIC
    Code:
      stack=1, locals=1, args_size=1
         0: aload_0
         1: invokespecial #77                 // InterfaceMethod fnToProduct1:()Lshapeless/ops/function$FnToProduct;
         4: areturn
      LineNumberTable:
        line 40: 0
      LocalVariableTable:
        Start  Length  Slot  Name   Signature
            0       5     0 $this   Lshapeless/ops/FnToProductInstances;
    MethodParameters:
      Name                           Flags
      $this                          final synthetic

  public default <A extends java.lang.Object, Res extends java.lang.Object> shapeless.ops.function$FnToProduct<scala.Function1<A, Res>> fnToProduct1();
    descriptor: ()Lshapeless/ops/function$FnToProduct;
    flags: (0x0001) ACC_PUBLIC
    Code:
      stack=3, locals=1, args_size=1
         0: new           #32                 // class shapeless/ops/FnToProductInstances$$anon$2
         3: dup
         4: aconst_null
         5: invokespecial #79                 // Method shapeless/ops/FnToProductInstances$$anon$2."<init>":(Lshapeless/ops/FnToProductInstances;)V
         8: areturn
      LineNumberTable:
        line 46: 0
      LocalVariableTable:
        Start  Length  Slot  Name   Signature
            0       9     0  this   Lshapeless/ops/FnToProductInstances;
    Signature: #78                          // <A:Ljava/lang/Object;Res:Ljava/lang/Object;>()Lshapeless/ops/function$FnToProduct<Lscala/Function1<TA;TRes;>;>;

  public static shapeless.ops.function$FnToProduct fnToProduct2$(shapeless.ops.FnToProductInstances);
    descriptor: (Lshapeless/ops/FnToProductInstances;)Lshapeless/ops/function$FnToProduct;
    flags: (0x1009) ACC_PUBLIC, ACC_STATIC, ACC_SYNTHETIC
    Code:
      stack=1, locals=1, args_size=1
         0: aload_0
         1: invokespecial #83                 // InterfaceMethod fnToProduct2:()Lshapeless/ops/function$FnToProduct;
         4: areturn
      LineNumberTable:
        line 53: 0
      LocalVariableTable:
        Start  Length  Slot  Name   Signature
            0       5     0 $this   Lshapeless/ops/FnToProductInstances;
    MethodParameters:
      Name                           Flags
      $this                          final synthetic

  public default <A extends java.lang.Object, B extends java.lang.Object, Res extends java.lang.Object> shapeless.ops.function$FnToProduct<scala.Function2<A, B, Res>> fnToProduct2();
    descriptor: ()Lshapeless/ops/function$FnToProduct;
    flags: (0x0001) ACC_PUBLIC
    Code:
      stack=3, locals=1, args_size=1
         0: new           #42                 // class shapeless/ops/FnToProductInstances$$anon$3
         3: dup
         4: aconst_null
         5: invokespecial #85                 // Method shapeless/ops/FnToProductInstances$$anon$3."<init>":(Lshapeless/ops/FnToProductInstances;)V
         8: areturn
      LineNumberTable:
        line 59: 0
      LocalVariableTable:
        Start  Length  Slot  Name   Signature
            0       9     0  this   Lshapeless/ops/FnToProductInstances;
    Signature: #84                          // <A:Ljava/lang/Object;B:Ljava/lang/Object;Res:Ljava/lang/Object;>()Lshapeless/ops/function$FnToProduct<Lscala/Function2<TA;TB;TRes;>;>;

  public static shapeless.ops.function$FnToProduct fnToProduct3$(shapeless.ops.FnToProductInstances);
    descriptor: (Lshapeless/ops/FnToProductInstances;)Lshapeless/ops/function$FnToProduct;
    flags: (0x1009) ACC_PUBLIC, ACC_STATIC, ACC_SYNTHETIC
    Code:
      stack=1, locals=1, args_size=1
         0: aload_0
         1: invokespecial #89                 // InterfaceMethod fnToProduct3:()Lshapeless/ops/function$FnToProduct;
         4: areturn
      LineNumberTable:
        line 66: 0
      LocalVariableTable:
        Start  Length  Slot  Name   Signature
            0       5     0 $this   Lshapeless/ops/FnToProductInstances;
    MethodParameters:
      Name                           Flags
      $this                          final synthetic

  public default <A extends java.lang.Object, B extends java.lang.Object, C extends java.lang.Object, Res extends java.lang.Object> shapeless.ops.function$FnToProduct<scala.Function3<A, B, C, Res>> fnToProduct3();
    descriptor: ()Lshapeless/ops/function$FnToProduct;
    flags: (0x0001) ACC_PUBLIC
    Code:
      stack=3, locals=1, args_size=1
         0: new           #44                 // class shapeless/ops/FnToProductInstances$$anon$4
         3: dup
         4: aconst_null
         5: invokespecial #91                 // Method shapeless/ops/FnToProductInstances$$anon$4."<init>":(Lshapeless/ops/FnToProductInstances;)V
         8: areturn
      LineNumberTable:
        line 72: 0
      LocalVariableTable:
        Start  Length  Slot  Name   Signature
            0       9     0  this   Lshapeless/ops/FnToProductInstances;
    Signature: #90                          // <A:Ljava/lang/Object;B:Ljava/lang/Object;C:Ljava/lang/Object;Res:Ljava/lang/Object;>()Lshapeless/ops/function$FnToProduct<Lscala/Function3<TA;TB;TC;TRes;>;>;

  public static shapeless.ops.function$FnToProduct fnToProduct4$(shapeless.ops.FnToProductInstances);
    descriptor: (Lshapeless/ops/FnToProductInstances;)Lshapeless/ops/function$FnToProduct;
    flags: (0x1009) ACC_PUBLIC, ACC_STATIC, ACC_SYNTHETIC
    Code:
      stack=1, locals=1, args_size=1
         0: aload_0
         1: invokespecial #95                 // InterfaceMethod fnToProduct4:()Lshapeless/ops/function$FnToProduct;
         4: areturn
      LineNumberTable:
        line 79: 0
      LocalVariableTable:
        Start  Length  Slot  Name   Signature
            0       5     0 $this   Lshapeless/ops/FnToProductInstances;
    MethodParameters:
      Name                           Flags
      $this                          final synthetic

  public default <A extends java.lang.Object, B extends java.lang.Object, C extends java.lang.Object, D extends java.lang.Object, Res extends java.lang.Object> shapeless.ops.function$FnToProduct<scala.Function4<A, B, C, D, Res>> fnToProduct4();
    descriptor: ()Lshapeless/ops/function$FnToProduct;
    flags: (0x0001) ACC_PUBLIC
    Code:
      stack=3, locals=1, args_size=1
         0: new           #46                 // class shapeless/ops/FnToProductInstances$$anon$5
         3: dup
         4: aconst_null
         5: invokespecial #97                 // Method shapeless/ops/FnToProductInstances$$anon$5."<init>":(Lshapeless/ops/FnToProductInstances;)V
         8: areturn
      LineNumberTable:
        line 85: 0
      LocalVariableTable:
        Start  Length  Slot  Name   Signature
            0       9     0  this   Lshapeless/ops/FnToProductInstances;
    Signature: #96                          // <A:Ljava/lang/Object;B:Ljava/lang/Object;C:Ljava/lang/Object;D:Ljava/lang/Object;Res:Ljava/lang/Object;>()Lshapeless/ops/function$FnToProduct<Lscala/Function4<TA;TB;TC;TD;TRes;>;>;

  public static shapeless.ops.function$FnToProduct fnToProduct5$(shapeless.ops.FnToProductInstances);
    descriptor: (Lshapeless/ops/FnToProductInstances;)Lshapeless/ops/function$FnToProduct;
    flags: (0x1009) ACC_PUBLIC, ACC_STATIC, ACC_SYNTHETIC
    Code:
      stack=1, locals=1, args_size=1
         0: aload_0
         1: invokespecial #101                // InterfaceMethod fnToProduct5:()Lshapeless/ops/function$FnToProduct;
         4: areturn
      LineNumberTable:
        line 92: 0
      LocalVariableTable:
        Start  Length  Slot  Name   Signature
            0       5     0 $this   Lshapeless/ops/FnToProductInstances;
    MethodParameters:
      Name                           Flags
      $this                          final synthetic

  public default <A extends java.lang.Object, B extends java.lang.Object, C extends java.lang.Object, D extends java.lang.Object, E extends java.lang.Object, Res extends java.lang.Object> shapeless.ops.function$FnToProduct<scala.Function5<A, B, C, D, E, Res>> fnToProduct5();
    descriptor: ()Lshapeless/ops/function$FnToProduct;
    flags: (0x0001) ACC_PUBLIC
    Code:
      stack=3, locals=1, args_size=1
         0: new           #48                 // class shapeless/ops/FnToProductInstances$$anon$6
         3: dup
         4: aconst_null
         5: invokespecial #103                // Method shapeless/ops/FnToProductInstances$$anon$6."<init>":(Lshapeless/ops/FnToProductInstances;)V
         8: areturn
      LineNumberTable:
        line 98: 0
      LocalVariableTable:
        Start  Length  Slot  Name   Signature
            0       9     0  this   Lshapeless/ops/FnToProductInstances;
    Signature: #102                         // <A:Ljava/lang/Object;B:Ljava/lang/Object;C:Ljava/lang/Object;D:Ljava/lang/Object;E:Ljava/lang/Object;Res:Ljava/lang/Object;>()Lshapeless/ops/function$FnToProduct<Lscala/Function5<TA;TB;TC;TD;TE;TRes;>;>;

  public static shapeless.ops.function$FnToProduct fnToProduct6$(shapeless.ops.FnToProductInstances);
    descriptor: (Lshapeless/ops/FnToProductInstances;)Lshapeless/ops/function$FnToProduct;
    flags: (0x1009) ACC_PUBLIC, ACC_STATIC, ACC_SYNTHETIC
    Code:
      stack=1, locals=1, args_size=1
         0: aload_0
         1: invokespecial #107                // InterfaceMethod fnToProduct6:()Lshapeless/ops/function$FnToProduct;
         4: areturn
      LineNumberTable:
        line 105: 0
      LocalVariableTable:
        Start  Length  Slot  Name   Signature
            0       5     0 $this   Lshapeless/ops/FnToProductInstances;
    MethodParameters:
      Name                           Flags
      $this                          final synthetic

  public default <A extends java.lang.Object, B extends java.lang.Object, C extends java.lang.Object, D extends java.lang.Object, E extends java.lang.Object, F extends java.lang.Object, Res extends java.lang.Object> shapeless.ops.function$FnToProduct<scala.Function6<A, B, C, D, E, F, Res>> fnToProduct6();
    descriptor: ()Lshapeless/ops/function$FnToProduct;
    flags: (0x0001) ACC_PUBLIC
    Code:
      stack=3, locals=1, args_size=1
         0: new           #50                 // class shapeless/ops/FnToProductInstances$$anon$7
         3: dup
         4: aconst_null
         5: invokespecial #109                // Method shapeless/ops/FnToProductInstances$$anon$7."<init>":(Lshapeless/ops/FnToProductInstances;)V
         8: areturn
      LineNumberTable:
        line 111: 0
      LocalVariableTable:
        Start  Length  Slot  Name   Signature
            0       9     0  this   Lshapeless/ops/FnToProductInstances;
    Signature: #108                         // <A:Ljava/lang/Object;B:Ljava/lang/Object;C:Ljava/lang/Object;D:Ljava/lang/Object;E:Ljava/lang/Object;F:Ljava/lang/Object;Res:Ljava/lang/Object;>()Lshapeless/ops/function$FnToProduct<Lscala/Function6<TA;TB;TC;TD;TE;TF;TRes;>;>;

  public static shapeless.ops.function$FnToProduct fnToProduct7$(shapeless.ops.FnToProductInstances);
    descriptor: (Lshapeless/ops/FnToProductInstances;)Lshapeless/ops/function$FnToProduct;
    flags: (0x1009) ACC_PUBLIC, ACC_STATIC, ACC_SYNTHETIC
    Code:
      stack=1, locals=1, args_size=1
         0: aload_0
         1: invokespecial #113                // InterfaceMethod fnToProduct7:()Lshapeless/ops/function$FnToProduct;
         4: areturn
      LineNumberTable:
        line 118: 0
      LocalVariableTable:
        Start  Length  Slot  Name   Signature
            0       5     0 $this   Lshapeless/ops/FnToProductInstances;
    MethodParameters:
      Name                           Flags
      $this                          final synthetic

  public default <A extends java.lang.Object, B extends java.lang.Object, C extends java.lang.Object, D extends java.lang.Object, E extends java.lang.Object, F extends java.lang.Object, G extends java.lang.Object, Res extends java.lang.Object> shapeless.ops.function$FnToProduct<scala.Function7<A, B, C, D, E, F, G, Res>> fnToProduct7();
    descriptor: ()Lshapeless/ops/function$FnToProduct;
    flags: (0x0001) ACC_PUBLIC
    Code:
      stack=3, locals=1, args_size=1
         0: new           #52                 // class shapeless/ops/FnToProductInstances$$anon$8
         3: dup
         4: aconst_null
         5: invokespecial #115                // Method shapeless/ops/FnToProductInstances$$anon$8."<init>":(Lshapeless/ops/FnToProductInstances;)V
         8: areturn
      LineNumberTable:
        line 124: 0
      LocalVariableTable:
        Start  Length  Slot  Name   Signature
            0       9     0  this   Lshapeless/ops/FnToProductInstances;
    Signature: #114                         // <A:Ljava/lang/Object;B:Ljava/lang/Object;C:Ljava/lang/Object;D:Ljava/lang/Object;E:Ljava/lang/Object;F:Ljava/lang/Object;G:Ljava/lang/Object;Res:Ljava/lang/Object;>()Lshapeless/ops/function$FnToProduct<Lscala/Function7<TA;TB;TC;TD;TE;TF;TG;TRes;>;>;

  public static shapeless.ops.function$FnToProduct fnToProduct8$(shapeless.ops.FnToProductInstances);
    descriptor: (Lshapeless/ops/FnToProductInstances;)Lshapeless/ops/function$FnToProduct;
    flags: (0x1009) ACC_PUBLIC, ACC_STATIC, ACC_SYNTHETIC
    Code:
      stack=1, locals=1, args_size=1
         0: aload_0
         1: invokespecial #119                // InterfaceMethod fnToProduct8:()Lshapeless/ops/function$FnToProduct;
         4: areturn
      LineNumberTable:
        line 131: 0
      LocalVariableTable:
        Start  Length  Slot  Name   Signature
            0       5     0 $this   Lshapeless/ops/FnToProductInstances;
    MethodParameters:
      Name                           Flags
      $this                          final synthetic

  public default <A extends java.lang.Object, B extends java.lang.Object, C extends java.lang.Object, D extends java.lang.Object, E extends java.lang.Object, F extends java.lang.Object, G extends java.lang.Object, H extends java.lang.Object, Res extends java.lang.Object> shapeless.ops.function$FnToProduct<scala.Function8<A, B, C, D, E, F, G, H, Res>> fnToProduct8();
    descriptor: ()Lshapeless/ops/function$FnToProduct;
    flags: (0x0001) ACC_PUBLIC
    Code:
      stack=3, locals=1, args_size=1
         0: new           #54                 // class shapeless/ops/FnToProductInstances$$anon$9
         3: dup
         4: aconst_null
         5: invokespecial #121                // Method shapeless/ops/FnToProductInstances$$anon$9."<init>":(Lshapeless/ops/FnToProductInstances;)V
         8: areturn
      LineNumberTable:
        line 137: 0
      LocalVariableTable:
        Start  Length  Slot  Name   Signature
            0       9     0  this   Lshapeless/ops/FnToProductInstances;
    Signature: #120                         // <A:Ljava/lang/Object;B:Ljava/lang/Object;C:Ljava/lang/Object;D:Ljava/lang/Object;E:Ljava/lang/Object;F:Ljava/lang/Object;G:Ljava/lang/Object;H:Ljava/lang/Object;Res:Ljava/lang/Object;>()Lshapeless/ops/function$FnToProduct<Lscala/Function8<TA;TB;TC;TD;TE;TF;TG;TH;TRes;>;>;

  public static shapeless.ops.function$FnToProduct fnToProduct9$(shapeless.ops.FnToProductInstances);
    descriptor: (Lshapeless/ops/FnToProductInstances;)Lshapeless/ops/function$FnToProduct;
    flags: (0x1009) ACC_PUBLIC, ACC_STATIC, ACC_SYNTHETIC
    Code:
      stack=1, locals=1, args_size=1
         0: aload_0
         1: invokespecial #125                // InterfaceMethod fnToProduct9:()Lshapeless/ops/function$FnToProduct;
         4: areturn
      LineNumberTable:
        line 144: 0
      LocalVariableTable:
        Start  Length  Slot  Name   Signature
            0       5     0 $this   Lshapeless/ops/FnToProductInstances;
    MethodParameters:
      Name                           Flags
      $this                          final synthetic

  public default <A extends java.lang.Object, B extends java.lang.Object, C extends java.lang.Object, D extends java.lang.Object, E extends java.lang.Object, F extends java.lang.Object, G extends java.lang.Object, H extends java.lang.Object, I extends java.lang.Object, Res extends java.lang.Object> shapeless.ops.function$FnToProduct<scala.Function9<A, B, C, D, E, F, G, H, I, Res>> fnToProduct9();
    descriptor: ()Lshapeless/ops/function$FnToProduct;
    flags: (0x0001) ACC_PUBLIC
    Code:
      stack=3, locals=1, args_size=1
         0: new           #12                 // class shapeless/ops/FnToProductInstances$$anon$10
         3: dup
         4: aconst_null
         5: invokespecial #127                // Method shapeless/ops/FnToProductInstances$$anon$10."<init>":(Lshapeless/ops/FnToProductInstances;)V
         8: areturn
      LineNumberTable:
        line 150: 0
      LocalVariableTable:
        Start  Length  Slot  Name   Signature
            0       9     0  this   Lshapeless/ops/FnToProductInstances;
    Signature: #126                         // <A:Ljava/lang/Object;B:Ljava/lang/Object;C:Ljava/lang/Object;D:Ljava/lang/Object;E:Ljava/lang/Object;F:Ljava/lang/Object;G:Ljava/lang/Object;H:Ljava/lang/Object;I:Ljava/lang/Object;Res:Ljava/lang/Object;>()Lshapeless/ops/function$FnToProduct<Lscala/Function9<TA;TB;TC;TD;TE;TF;TG;TH;TI;TRes;>;>;

  public static shapeless.ops.function$FnToProduct fnToProduct10$(shapeless.ops.FnToProductInstances);
    descriptor: (Lshapeless/ops/FnToProductInstances;)Lshapeless/ops/function$FnToProduct;
    flags: (0x1009) ACC_PUBLIC, ACC_STATIC, ACC_SYNTHETIC
    Code:
      stack=1, locals=1, args_size=1
         0: aload_0
         1: invokespecial #131                // InterfaceMethod fnToProduct10:()Lshapeless/ops/function$FnToProduct;
         4: areturn
      LineNumberTable:
        line 157: 0
      LocalVariableTable:
        Start  Length  Slot  Name   Signature
            0       5     0 $this   Lshapeless/ops/FnToProductInstances;
    MethodParameters:
      Name                           Flags
      $this                          final synthetic

  public default <A extends java.lang.Object, B extends java.lang.Object, C extends java.lang.Object, D extends java.lang.Object, E extends java.lang.Object, F extends java.lang.Object, G extends java.lang.Object, H extends java.lang.Object, I extends java.lang.Object, J extends java.lang.Object, Res extends java.lang.Object> shapeless.ops.function$FnToProduct<scala.Function10<A, B, C, D, E, F, G, H, I, J, Res>> fnToProduct10();
    descriptor: ()Lshapeless/ops/function$FnToProduct;
    flags: (0x0001) ACC_PUBLIC
    Code:
      stack=3, locals=1, args_size=1
         0: new           #14                 // class shapeless/ops/FnToProductInstances$$anon$11
         3: dup
         4: aconst_null
         5: invokespecial #133                // Method shapeless/ops/FnToProductInstances$$anon$11."<init>":(Lshapeless/ops/FnToProductInstances;)V
         8: areturn
      LineNumberTable:
        line 163: 0
      LocalVariableTable:
        Start  Length  Slot  Name   Signature
            0       9     0  this   Lshapeless/ops/FnToProductInstances;
    Signature: #132                         // <A:Ljava/lang/Object;B:Ljava/lang/Object;C:Ljava/lang/Object;D:Ljava/lang/Object;E:Ljava/lang/Object;F:Ljava/lang/Object;G:Ljava/lang/Object;H:Ljava/lang/Object;I:Ljava/lang/Object;J:Ljava/lang/Object;Res:Ljava/lang/Object;>()Lshapeless/ops/function$FnToProduct<Lscala/Function10<TA;TB;TC;TD;TE;TF;TG;TH;TI;TJ;TRes;>;>;

  public static shapeless.ops.function$FnToProduct fnToProduct11$(shapeless.ops.FnToProductInstances);
    descriptor: (Lshapeless/ops/FnToProductInstances;)Lshapeless/ops/function$FnToProduct;
    flags: (0x1009) ACC_PUBLIC, ACC_STATIC, ACC_SYNTHETIC
    Code:
      stack=1, locals=1, args_size=1
         0: aload_0
         1: invokespecial #137                // InterfaceMethod fnToProduct11:()Lshapeless/ops/function$FnToProduct;
         4: areturn
      LineNumberTable:
        line 170: 0
      LocalVariableTable:
        Start  Length  Slot  Name   Signature
            0       5     0 $this   Lshapeless/ops/FnToProductInstances;
    MethodParameters:
      Name                           Flags
      $this                          final synthetic

  public default <A extends java.lang.Object, B extends java.lang.Object, C extends java.lang.Object, D extends java.lang.Object, E extends java.lang.Object, F extends java.lang.Object, G extends java.lang.Object, H extends java.lang.Object, I extends java.lang.Object, J extends java.lang.Object, K extends java.lang.Object, Res extends java.lang.Object> shapeless.ops.function$FnToProduct<scala.Function11<A, B, C, D, E, F, G, H, I, J, K, Res>> fnToProduct11();
    descriptor: ()Lshapeless/ops/function$FnToProduct;
    flags: (0x0001) ACC_PUBLIC
    Code:
      stack=3, locals=1, args_size=1
         0: new           #16                 // class shapeless/ops/FnToProductInstances$$anon$12
         3: dup
         4: aconst_null
         5: invokespecial #139                // Method shapeless/ops/FnToProductInstances$$anon$12."<init>":(Lshapeless/ops/FnToProductInstances;)V
         8: areturn
      LineNumberTable:
        line 176: 0
      LocalVariableTable:
        Start  Length  Slot  Name   Signature
            0       9     0  this   Lshapeless/ops/FnToProductInstances;
    Signature: #138                         // <A:Ljava/lang/Object;B:Ljava/lang/Object;C:Ljava/lang/Object;D:Ljava/lang/Object;E:Ljava/lang/Object;F:Ljava/lang/Object;G:Ljava/lang/Object;H:Ljava/lang/Object;I:Ljava/lang/Object;J:Ljava/lang/Object;K:Ljava/lang/Object;Res:Ljava/lang/Object;>()Lshapeless/ops/function$FnToProduct<Lscala/Function11<TA;TB;TC;TD;TE;TF;TG;TH;TI;TJ;TK;TRes;>;>;

  public static shapeless.ops.function$FnToProduct fnToProduct12$(shapeless.ops.FnToProductInstances);
    descriptor: (Lshapeless/ops/FnToProductInstances;)Lshapeless/ops/function$FnToProduct;
    flags: (0x1009) ACC_PUBLIC, ACC_STATIC, ACC_SYNTHETIC
    Code:
      stack=1, locals=1, args_size=1
         0: aload_0
         1: invokespecial #143                // InterfaceMethod fnToProduct12:()Lshapeless/ops/function$FnToProduct;
         4: areturn
      LineNumberTable:
        line 183: 0
      LocalVariableTable:
        Start  Length  Slot  Name   Signature
            0       5     0 $this   Lshapeless/ops/FnToProductInstances;
    MethodParameters:
      Name                           Flags
      $this                          final synthetic

  public default <A extends java.lang.Object, B extends java.lang.Object, C extends java.lang.Object, D extends java.lang.Object, E extends java.lang.Object, F extends java.lang.Object, G extends java.lang.Object, H extends java.lang.Object, I extends java.lang.Object, J extends java.lang.Object, K extends java.lang.Object, L extends java.lang.Object, Res extends java.lang.Object> shapeless.ops.function$FnToProduct<scala.Function12<A, B, C, D, E, F, G, H, I, J, K, L, Res>> fnToProduct12();
    descriptor: ()Lshapeless/ops/function$FnToProduct;
    flags: (0x0001) ACC_PUBLIC
    Code:
      stack=3, locals=1, args_size=1
         0: new           #18                 // class shapeless/ops/FnToProductInstances$$anon$13
         3: dup
         4: aconst_null
         5: invokespecial #145                // Method shapeless/ops/FnToProductInstances$$anon$13."<init>":(Lshapeless/ops/FnToProductInstances;)V
         8: areturn
      LineNumberTable:
        line 189: 0
      LocalVariableTable:
        Start  Length  Slot  Name   Signature
            0       9     0  this   Lshapeless/ops/FnToProductInstances;
    Signature: #144                         // <A:Ljava/lang/Object;B:Ljava/lang/Object;C:Ljava/lang/Object;D:Ljava/lang/Object;E:Ljava/lang/Object;F:Ljava/lang/Object;G:Ljava/lang/Object;H:Ljava/lang/Object;I:Ljava/lang/Object;J:Ljava/lang/Object;K:Ljava/lang/Object;L:Ljava/lang/Object;Res:Ljava/lang/Object;>()Lshapeless/ops/function$FnToProduct<Lscala/Function12<TA;TB;TC;TD;TE;TF;TG;TH;TI;TJ;TK;TL;TRes;>;>;

  public static shapeless.ops.function$FnToProduct fnToProduct13$(shapeless.ops.FnToProductInstances);
    descriptor: (Lshapeless/ops/FnToProductInstances;)Lshapeless/ops/function$FnToProduct;
    flags: (0x1009) ACC_PUBLIC, ACC_STATIC, ACC_SYNTHETIC
    Code:
      stack=1, locals=1, args_size=1
         0: aload_0
         1: invokespecial #149                // InterfaceMethod fnToProduct13:()Lshapeless/ops/function$FnToProduct;
         4: areturn
      LineNumberTable:
        line 196: 0
      LocalVariableTable:
        Start  Length  Slot  Name   Signature
            0       5     0 $this   Lshapeless/ops/FnToProductInstances;
    MethodParameters:
      Name                           Flags
      $this                          final synthetic

  public default <A extends java.lang.Object, B extends java.lang.Object, C extends java.lang.Object, D extends java.lang.Object, E extends java.lang.Object, F extends java.lang.Object, G extends java.lang.Object, H extends java.lang.Object, I extends java.lang.Object, J extends java.lang.Object, K extends java.lang.Object, L extends java.lang.Object, M extends java.lang.Object, Res extends java.lang.Object> shapeless.ops.function$FnToProduct<scala.Function13<A, B, C, D, E, F, G, H, I, J, K, L, M, Res>> fnToProduct13();
    descriptor: ()Lshapeless/ops/function$FnToProduct;
    flags: (0x0001) ACC_PUBLIC
    Code:
      stack=3, locals=1, args_size=1
         0: new           #20                 // class shapeless/ops/FnToProductInstances$$anon$14
         3: dup
         4: aconst_null
         5: invokespecial #151                // Method shapeless/ops/FnToProductInstances$$anon$14."<init>":(Lshapeless/ops/FnToProductInstances;)V
         8: areturn
      LineNumberTable:
        line 202: 0
      LocalVariableTable:
        Start  Length  Slot  Name   Signature
            0       9     0  this   Lshapeless/ops/FnToProductInstances;
    Signature: #150                         // <A:Ljava/lang/Object;B:Ljava/lang/Object;C:Ljava/lang/Object;D:Ljava/lang/Object;E:Ljava/lang/Object;F:Ljava/lang/Object;G:Ljava/lang/Object;H:Ljava/lang/Object;I:Ljava/lang/Object;J:Ljava/lang/Object;K:Ljava/lang/Object;L:Ljava/lang/Object;M:Ljava/lang/Object;Res:Ljava/lang/Object;>()Lshapeless/ops/function$FnToProduct<Lscala/Function13<TA;TB;TC;TD;TE;TF;TG;TH;TI;TJ;TK;TL;TM;TRes;>;>;

  public static shapeless.ops.function$FnToProduct fnToProduct14$(shapeless.ops.FnToProductInstances);
    descriptor: (Lshapeless/ops/FnToProductInstances;)Lshapeless/ops/function$FnToProduct;
    flags: (0x1009) ACC_PUBLIC, ACC_STATIC, ACC_SYNTHETIC
    Code:
      stack=1, locals=1, args_size=1
         0: aload_0
         1: invokespecial #155                // InterfaceMethod fnToProduct14:()Lshapeless/ops/function$FnToProduct;
         4: areturn
      LineNumberTable:
        line 209: 0
      LocalVariableTable:
        Start  Length  Slot  Name   Signature
            0       5     0 $this   Lshapeless/ops/FnToProductInstances;
    MethodParameters:
      Name                           Flags
      $this                          final synthetic

  public default <A extends java.lang.Object, B extends java.lang.Object, C extends java.lang.Object, D extends java.lang.Object, E extends java.lang.Object, F extends java.lang.Object, G extends java.lang.Object, H extends java.lang.Object, I extends java.lang.Object, J extends java.lang.Object, K extends java.lang.Object, L extends java.lang.Object, M extends java.lang.Object, N extends java.lang.Object, Res extends java.lang.Object> shapeless.ops.function$FnToProduct<scala.Function14<A, B, C, D, E, F, G, H, I, J, K, L, M, N, Res>> fnToProduct14();
    descriptor: ()Lshapeless/ops/function$FnToProduct;
    flags: (0x0001) ACC_PUBLIC
    Code:
      stack=3, locals=1, args_size=1
         0: new           #22                 // class shapeless/ops/FnToProductInstances$$anon$15
         3: dup
         4: aconst_null
         5: invokespecial #157                // Method shapeless/ops/FnToProductInstances$$anon$15."<init>":(Lshapeless/ops/FnToProductInstances;)V
         8: areturn
      LineNumberTable:
        line 215: 0
      LocalVariableTable:
        Start  Length  Slot  Name   Signature
            0       9     0  this   Lshapeless/ops/FnToProductInstances;
    Signature: #156                         // <A:Ljava/lang/Object;B:Ljava/lang/Object;C:Ljava/lang/Object;D:Ljava/lang/Object;E:Ljava/lang/Object;F:Ljava/lang/Object;G:Ljava/lang/Object;H:Ljava/lang/Object;I:Ljava/lang/Object;J:Ljava/lang/Object;K:Ljava/lang/Object;L:Ljava/lang/Object;M:Ljava/lang/Object;N:Ljava/lang/Object;Res:Ljava/lang/Object;>()Lshapeless/ops/function$FnToProduct<Lscala/Function14<TA;TB;TC;TD;TE;TF;TG;TH;TI;TJ;TK;TL;TM;TN;TRes;>;>;

  public static shapeless.ops.function$FnToProduct fnToProduct15$(shapeless.ops.FnToProductInstances);
    descriptor: (Lshapeless/ops/FnToProductInstances;)Lshapeless/ops/function$FnToProduct;
    flags: (0x1009) ACC_PUBLIC, ACC_STATIC, ACC_SYNTHETIC
    Code:
      stack=1, locals=1, args_size=1
         0: aload_0
         1: invokespecial #161                // InterfaceMethod fnToProduct15:()Lshapeless/ops/function$FnToProduct;
         4: areturn
      LineNumberTable:
        line 222: 0
      LocalVariableTable:
        Start  Length  Slot  Name   Signature
            0       5     0 $this   Lshapeless/ops/FnToProductInstances;
    MethodParameters:
      Name                           Flags
      $this                          final synthetic

  public default <A extends java.lang.Object, B extends java.lang.Object, C extends java.lang.Object, D extends java.lang.Object, E extends java.lang.Object, F extends java.lang.Object, G extends java.lang.Object, H extends java.lang.Object, I extends java.lang.Object, J extends java.lang.Object, K extends java.lang.Object, L extends java.lang.Object, M extends java.lang.Object, N extends java.lang.Object, O extends java.lang.Object, Res extends java.lang.Object> shapeless.ops.function$FnToProduct<scala.Function15<A, B, C, D, E, F, G, H, I, J, K, L, M, N, O, Res>> fnToProduct15();
    descriptor: ()Lshapeless/ops/function$FnToProduct;
    flags: (0x0001) ACC_PUBLIC
    Code:
      stack=3, locals=1, args_size=1
         0: new           #24                 // class shapeless/ops/FnToProductInstances$$anon$16
         3: dup
         4: aconst_null
         5: invokespecial #163                // Method shapeless/ops/FnToProductInstances$$anon$16."<init>":(Lshapeless/ops/FnToProductInstances;)V
         8: areturn
      LineNumberTable:
        line 228: 0
      LocalVariableTable:
        Start  Length  Slot  Name   Signature
            0       9     0  this   Lshapeless/ops/FnToProductInstances;
    Signature: #162                         // <A:Ljava/lang/Object;B:Ljava/lang/Object;C:Ljava/lang/Object;D:Ljava/lang/Object;E:Ljava/lang/Object;F:Ljava/lang/Object;G:Ljava/lang/Object;H:Ljava/lang/Object;I:Ljava/lang/Object;J:Ljava/lang/Object;K:Ljava/lang/Object;L:Ljava/lang/Object;M:Ljava/lang/Object;N:Ljava/lang/Object;O:Ljava/lang/Object;Res:Ljava/lang/Object;>()Lshapeless/ops/function$FnToProduct<Lscala/Function15<TA;TB;TC;TD;TE;TF;TG;TH;TI;TJ;TK;TL;TM;TN;TO;TRes;>;>;

  public static shapeless.ops.function$FnToProduct fnToProduct16$(shapeless.ops.FnToProductInstances);
    descriptor: (Lshapeless/ops/FnToProductInstances;)Lshapeless/ops/function$FnToProduct;
    flags: (0x1009) ACC_PUBLIC, ACC_STATIC, ACC_SYNTHETIC
    Code:
      stack=1, locals=1, args_size=1
         0: aload_0
         1: invokespecial #167                // InterfaceMethod fnToProduct16:()Lshapeless/ops/function$FnToProduct;
         4: areturn
      LineNumberTable:
        line 235: 0
      LocalVariableTable:
        Start  Length  Slot  Name   Signature
            0       5     0 $this   Lshapeless/ops/FnToProductInstances;
    MethodParameters:
      Name                           Flags
      $this                          final synthetic

  public default <A extends java.lang.Object, B extends java.lang.Object, C extends java.lang.Object, D extends java.lang.Object, E extends java.lang.Object, F extends java.lang.Object, G extends java.lang.Object, H extends java.lang.Object, I extends java.lang.Object, J extends java.lang.Object, K extends java.lang.Object, L extends java.lang.Object, M extends java.lang.Object, N extends java.lang.Object, O extends java.lang.Object, P extends java.lang.Object, Res extends java.lang.Object> shapeless.ops.function$FnToProduct<scala.Function16<A, B, C, D, E, F, G, H, I, J, K, L, M, N, O, P, Res>> fnToProduct16();
    descriptor: ()Lshapeless/ops/function$FnToProduct;
    flags: (0x0001) ACC_PUBLIC
    Code:
      stack=3, locals=1, args_size=1
         0: new           #26                 // class shapeless/ops/FnToProductInstances$$anon$17
         3: dup
         4: aconst_null
         5: invokespecial #169                // Method shapeless/ops/FnToProductInstances$$anon$17."<init>":(Lshapeless/ops/FnToProductInstances;)V
         8: areturn
      LineNumberTable:
        line 241: 0
      LocalVariableTable:
        Start  Length  Slot  Name   Signature
            0       9     0  this   Lshapeless/ops/FnToProductInstances;
    Signature: #168                         // <A:Ljava/lang/Object;B:Ljava/lang/Object;C:Ljava/lang/Object;D:Ljava/lang/Object;E:Ljava/lang/Object;F:Ljava/lang/Object;G:Ljava/lang/Object;H:Ljava/lang/Object;I:Ljava/lang/Object;J:Ljava/lang/Object;K:Ljava/lang/Object;L:Ljava/lang/Object;M:Ljava/lang/Object;N:Ljava/lang/Object;O:Ljava/lang/Object;P:Ljava/lang/Object;Res:Ljava/lang/Object;>()Lshapeless/ops/function$FnToProduct<Lscala/Function16<TA;TB;TC;TD;TE;TF;TG;TH;TI;TJ;TK;TL;TM;TN;TO;TP;TRes;>;>;

  public static shapeless.ops.function$FnToProduct fnToProduct17$(shapeless.ops.FnToProductInstances);
    descriptor: (Lshapeless/ops/FnToProductInstances;)Lshapeless/ops/function$FnToProduct;
    flags: (0x1009) ACC_PUBLIC, ACC_STATIC, ACC_SYNTHETIC
    Code:
      stack=1, locals=1, args_size=1
         0: aload_0
         1: invokespecial #173                // InterfaceMethod fnToProduct17:()Lshapeless/ops/function$FnToProduct;
         4: areturn
      LineNumberTable:
        line 248: 0
      LocalVariableTable:
        Start  Length  Slot  Name   Signature
            0       5     0 $this   Lshapeless/ops/FnToProductInstances;
    MethodParameters:
      Name                           Flags
      $this                          final synthetic

  public default <A extends java.lang.Object, B extends java.lang.Object, C extends java.lang.Object, D extends java.lang.Object, E extends java.lang.Object, F extends java.lang.Object, G extends java.lang.Object, H extends java.lang.Object, I extends java.lang.Object, J extends java.lang.Object, K extends java.lang.Object, L extends java.lang.Object, M extends java.lang.Object, N extends java.lang.Object, O extends java.lang.Object, P extends java.lang.Object, Q extends java.lang.Object, Res extends java.lang.Object> shapeless.ops.function$FnToProduct<scala.Function17<A, B, C, D, E, F, G, H, I, J, K, L, M, N, O, P, Q, Res>> fnToProduct17();
    descriptor: ()Lshapeless/ops/function$FnToProduct;
    flags: (0x0001) ACC_PUBLIC
    Code:
      stack=3, locals=1, args_size=1
         0: new           #28                 // class shapeless/ops/FnToProductInstances$$anon$18
         3: dup
         4: aconst_null
         5: invokespecial #175                // Method shapeless/ops/FnToProductInstances$$anon$18."<init>":(Lshapeless/ops/FnToProductInstances;)V
         8: areturn
      LineNumberTable:
        line 254: 0
      LocalVariableTable:
        Start  Length  Slot  Name   Signature
            0       9     0  this   Lshapeless/ops/FnToProductInstances;
    Signature: #174                         // <A:Ljava/lang/Object;B:Ljava/lang/Object;C:Ljava/lang/Object;D:Ljava/lang/Object;E:Ljava/lang/Object;F:Ljava/lang/Object;G:Ljava/lang/Object;H:Ljava/lang/Object;I:Ljava/lang/Object;J:Ljava/lang/Object;K:Ljava/lang/Object;L:Ljava/lang/Object;M:Ljava/lang/Object;N:Ljava/lang/Object;O:Ljava/lang/Object;P:Ljava/lang/Object;Q:Ljava/lang/Object;Res:Ljava/lang/Object;>()Lshapeless/ops/function$FnToProduct<Lscala/Function17<TA;TB;TC;TD;TE;TF;TG;TH;TI;TJ;TK;TL;TM;TN;TO;TP;TQ;TRes;>;>;

  public static shapeless.ops.function$FnToProduct fnToProduct18$(shapeless.ops.FnToProductInstances);
    descriptor: (Lshapeless/ops/FnToProductInstances;)Lshapeless/ops/function$FnToProduct;
    flags: (0x1009) ACC_PUBLIC, ACC_STATIC, ACC_SYNTHETIC
    Code:
      stack=1, locals=1, args_size=1
         0: aload_0
         1: invokespecial #179                // InterfaceMethod fnToProduct18:()Lshapeless/ops/function$FnToProduct;
         4: areturn
      LineNumberTable:
        line 261: 0
      LocalVariableTable:
        Start  Length  Slot  Name   Signature
            0       5     0 $this   Lshapeless/ops/FnToProductInstances;
    MethodParameters:
      Name                           Flags
      $this                          final synthetic

  public default <A extends java.lang.Object, B extends java.lang.Object, C extends java.lang.Object, D extends java.lang.Object, E extends java.lang.Object, F extends java.lang.Object, G extends java.lang.Object, H extends java.lang.Object, I extends java.lang.Object, J extends java.lang.Object, K extends java.lang.Object, L extends java.lang.Object, M extends java.lang.Object, N extends java.lang.Object, O extends java.lang.Object, P extends java.lang.Object, Q extends java.lang.Object, R extends java.lang.Object, Res extends java.lang.Object> shapeless.ops.function$FnToProduct<scala.Function18<A, B, C, D, E, F, G, H, I, J, K, L, M, N, O, P, Q, R, Res>> fnToProduct18();
    descriptor: ()Lshapeless/ops/function$FnToProduct;
    flags: (0x0001) ACC_PUBLIC
    Code:
      stack=3, locals=1, args_size=1
         0: new           #30                 // class shapeless/ops/FnToProductInstances$$anon$19
         3: dup
         4: aconst_null
         5: invokespecial #181                // Method shapeless/ops/FnToProductInstances$$anon$19."<init>":(Lshapeless/ops/FnToProductInstances;)V
         8: areturn
      LineNumberTable:
        line 267: 0
      LocalVariableTable:
        Start  Length  Slot  Name   Signature
            0       9     0  this   Lshapeless/ops/FnToProductInstances;
    Signature: #180                         // <A:Ljava/lang/Object;B:Ljava/lang/Object;C:Ljava/lang/Object;D:Ljava/lang/Object;E:Ljava/lang/Object;F:Ljava/lang/Object;G:Ljava/lang/Object;H:Ljava/lang/Object;I:Ljava/lang/Object;J:Ljava/lang/Object;K:Ljava/lang/Object;L:Ljava/lang/Object;M:Ljava/lang/Object;N:Ljava/lang/Object;O:Ljava/lang/Object;P:Ljava/lang/Object;Q:Ljava/lang/Object;R:Ljava/lang/Object;Res:Ljava/lang/Object;>()Lshapeless/ops/function$FnToProduct<Lscala/Function18<TA;TB;TC;TD;TE;TF;TG;TH;TI;TJ;TK;TL;TM;TN;TO;TP;TQ;TR;TRes;>;>;

  public static shapeless.ops.function$FnToProduct fnToProduct19$(shapeless.ops.FnToProductInstances);
    descriptor: (Lshapeless/ops/FnToProductInstances;)Lshapeless/ops/function$FnToProduct;
    flags: (0x1009) ACC_PUBLIC, ACC_STATIC, ACC_SYNTHETIC
    Code:
      stack=1, locals=1, args_size=1
         0: aload_0
         1: invokespecial #185                // InterfaceMethod fnToProduct19:()Lshapeless/ops/function$FnToProduct;
         4: areturn
      LineNumberTable:
        line 274: 0
      LocalVariableTable:
        Start  Length  Slot  Name   Signature
            0       5     0 $this   Lshapeless/ops/FnToProductInstances;
    MethodParameters:
      Name                           Flags
      $this                          final synthetic

  public default <A extends java.lang.Object, B extends java.lang.Object, C extends java.lang.Object, D extends java.lang.Object, E extends java.lang.Object, F extends java.lang.Object, G extends java.lang.Object, H extends java.lang.Object, I extends java.lang.Object, J extends java.lang.Object, K extends java.lang.Object, L extends java.lang.Object, M extends java.lang.Object, N extends java.lang.Object, O extends java.lang.Object, P extends java.lang.Object, Q extends java.lang.Object, R extends java.lang.Object, S extends java.lang.Object, Res extends java.lang.Object> shapeless.ops.function$FnToProduct<scala.Function19<A, B, C, D, E, F, G, H, I, J, K, L, M, N, O, P, Q, R, S, Res>> fnToProduct19();
    descriptor: ()Lshapeless/ops/function$FnToProduct;
    flags: (0x0001) ACC_PUBLIC
    Code:
      stack=3, locals=1, args_size=1
         0: new           #34                 // class shapeless/ops/FnToProductInstances$$anon$20
         3: dup
         4: aconst_null
         5: invokespecial #187                // Method shapeless/ops/FnToProductInstances$$anon$20."<init>":(Lshapeless/ops/FnToProductInstances;)V
         8: areturn
      LineNumberTable:
        line 280: 0
      LocalVariableTable:
        Start  Length  Slot  Name   Signature
            0       9     0  this   Lshapeless/ops/FnToProductInstances;
    Signature: #186                         // <A:Ljava/lang/Object;B:Ljava/lang/Object;C:Ljava/lang/Object;D:Ljava/lang/Object;E:Ljava/lang/Object;F:Ljava/lang/Object;G:Ljava/lang/Object;H:Ljava/lang/Object;I:Ljava/lang/Object;J:Ljava/lang/Object;K:Ljava/lang/Object;L:Ljava/lang/Object;M:Ljava/lang/Object;N:Ljava/lang/Object;O:Ljava/lang/Object;P:Ljava/lang/Object;Q:Ljava/lang/Object;R:Ljava/lang/Object;S:Ljava/lang/Object;Res:Ljava/lang/Object;>()Lshapeless/ops/function$FnToProduct<Lscala/Function19<TA;TB;TC;TD;TE;TF;TG;TH;TI;TJ;TK;TL;TM;TN;TO;TP;TQ;TR;TS;TRes;>;>;

  public static shapeless.ops.function$FnToProduct fnToProduct20$(shapeless.ops.FnToProductInstances);
    descriptor: (Lshapeless/ops/FnToProductInstances;)Lshapeless/ops/function$FnToProduct;
    flags: (0x1009) ACC_PUBLIC, ACC_STATIC, ACC_SYNTHETIC
    Code:
      stack=1, locals=1, args_size=1
         0: aload_0
         1: invokespecial #191                // InterfaceMethod fnToProduct20:()Lshapeless/ops/function$FnToProduct;
         4: areturn
      LineNumberTable:
        line 287: 0
      LocalVariableTable:
        Start  Length  Slot  Name   Signature
            0       5     0 $this   Lshapeless/ops/FnToProductInstances;
    MethodParameters:
      Name                           Flags
      $this                          final synthetic

  public default <A extends java.lang.Object, B extends java.lang.Object, C extends java.lang.Object, D extends java.lang.Object, E extends java.lang.Object, F extends java.lang.Object, G extends java.lang.Object, H extends java.lang.Object, I extends java.lang.Object, J extends java.lang.Object, K extends java.lang.Object, L extends java.lang.Object, M extends java.lang.Object, N extends java.lang.Object, O extends java.lang.Object, P extends java.lang.Object, Q extends java.lang.Object, R extends java.lang.Object, S extends java.lang.Object, T extends java.lang.Object, Res extends java.lang.Object> shapeless.ops.function$FnToProduct<scala.Function20<A, B, C, D, E, F, G, H, I, J, K, L, M, N, O, P, Q, R, S, T, Res>> fnToProduct20();
    descriptor: ()Lshapeless/ops/function$FnToProduct;
    flags: (0x0001) ACC_PUBLIC
    Code:
      stack=3, locals=1, args_size=1
         0: new           #36                 // class shapeless/ops/FnToProductInstances$$anon$21
         3: dup
         4: aconst_null
         5: invokespecial #193                // Method shapeless/ops/FnToProductInstances$$anon$21."<init>":(Lshapeless/ops/FnToProductInstances;)V
         8: areturn
      LineNumberTable:
        line 293: 0
      LocalVariableTable:
        Start  Length  Slot  Name   Signature
            0       9     0  this   Lshapeless/ops/FnToProductInstances;
    Signature: #192                         // <A:Ljava/lang/Object;B:Ljava/lang/Object;C:Ljava/lang/Object;D:Ljava/lang/Object;E:Ljava/lang/Object;F:Ljava/lang/Object;G:Ljava/lang/Object;H:Ljava/lang/Object;I:Ljava/lang/Object;J:Ljava/lang/Object;K:Ljava/lang/Object;L:Ljava/lang/Object;M:Ljava/lang/Object;N:Ljava/lang/Object;O:Ljava/lang/Object;P:Ljava/lang/Object;Q:Ljava/lang/Object;R:Ljava/lang/Object;S:Ljava/lang/Object;T:Ljava/lang/Object;Res:Ljava/lang/Object;>()Lshapeless/ops/function$FnToProduct<Lscala/Function20<TA;TB;TC;TD;TE;TF;TG;TH;TI;TJ;TK;TL;TM;TN;TO;TP;TQ;TR;TS;TT;TRes;>;>;

  public static shapeless.ops.function$FnToProduct fnToProduct21$(shapeless.ops.FnToProductInstances);
    descriptor: (Lshapeless/ops/FnToProductInstances;)Lshapeless/ops/function$FnToProduct;
    flags: (0x1009) ACC_PUBLIC, ACC_STATIC, ACC_SYNTHETIC
    Code:
      stack=1, locals=1, args_size=1
         0: aload_0
         1: invokespecial #197                // InterfaceMethod fnToProduct21:()Lshapeless/ops/function$FnToProduct;
         4: areturn
      LineNumberTable:
        line 300: 0
      LocalVariableTable:
        Start  Length  Slot  Name   Signature
            0       5     0 $this   Lshapeless/ops/FnToProductInstances;
    MethodParameters:
      Name                           Flags
      $this                          final synthetic

  public default <A extends java.lang.Object, B extends java.lang.Object, C extends java.lang.Object, D extends java.lang.Object, E extends java.lang.Object, F extends java.lang.Object, G extends java.lang.Object, H extends java.lang.Object, I extends java.lang.Object, J extends java.lang.Object, K extends java.lang.Object, L extends java.lang.Object, M extends java.lang.Object, N extends java.lang.Object, O extends java.lang.Object, P extends java.lang.Object, Q extends java.lang.Object, R extends java.lang.Object, S extends java.lang.Object, T extends java.lang.Object, U extends java.lang.Object, Res extends java.lang.Object> shapeless.ops.function$FnToProduct<scala.Function21<A, B, C, D, E, F, G, H, I, J, K, L, M, N, O, P, Q, R, S, T, U, Res>> fnToProduct21();
    descriptor: ()Lshapeless/ops/function$FnToProduct;
    flags: (0x0001) ACC_PUBLIC
    Code:
      stack=3, locals=1, args_size=1
         0: new           #38                 // class shapeless/ops/FnToProductInstances$$anon$22
         3: dup
         4: aconst_null
         5: invokespecial #199                // Method shapeless/ops/FnToProductInstances$$anon$22."<init>":(Lshapeless/ops/FnToProductInstances;)V
         8: areturn
      LineNumberTable:
        line 306: 0
      LocalVariableTable:
        Start  Length  Slot  Name   Signature
            0       9     0  this   Lshapeless/ops/FnToProductInstances;
    Signature: #198                         // <A:Ljava/lang/Object;B:Ljava/lang/Object;C:Ljava/lang/Object;D:Ljava/lang/Object;E:Ljava/lang/Object;F:Ljava/lang/Object;G:Ljava/lang/Object;H:Ljava/lang/Object;I:Ljava/lang/Object;J:Ljava/lang/Object;K:Ljava/lang/Object;L:Ljava/lang/Object;M:Ljava/lang/Object;N:Ljava/lang/Object;O:Ljava/lang/Object;P:Ljava/lang/Object;Q:Ljava/lang/Object;R:Ljava/lang/Object;S:Ljava/lang/Object;T:Ljava/lang/Object;U:Ljava/lang/Object;Res:Ljava/lang/Object;>()Lshapeless/ops/function$FnToProduct<Lscala/Function21<TA;TB;TC;TD;TE;TF;TG;TH;TI;TJ;TK;TL;TM;TN;TO;TP;TQ;TR;TS;TT;TU;TRes;>;>;

  public static shapeless.ops.function$FnToProduct fnToProduct22$(shapeless.ops.FnToProductInstances);
    descriptor: (Lshapeless/ops/FnToProductInstances;)Lshapeless/ops/function$FnToProduct;
    flags: (0x1009) ACC_PUBLIC, ACC_STATIC, ACC_SYNTHETIC
    Code:
      stack=1, locals=1, args_size=1
         0: aload_0
         1: invokespecial #203                // InterfaceMethod fnToProduct22:()Lshapeless/ops/function$FnToProduct;
         4: areturn
      LineNumberTable:
        line 313: 0
      LocalVariableTable:
        Start  Length  Slot  Name   Signature
            0       5     0 $this   Lshapeless/ops/FnToProductInstances;
    MethodParameters:
      Name                           Flags
      $this                          final synthetic

  public default <A extends java.lang.Object, B extends java.lang.Object, C extends java.lang.Object, D extends java.lang.Object, E extends java.lang.Object, F extends java.lang.Object, G extends java.lang.Object, H extends java.lang.Object, I extends java.lang.Object, J extends java.lang.Object, K extends java.lang.Object, L extends java.lang.Object, M extends java.lang.Object, N extends java.lang.Object, O extends java.lang.Object, P extends java.lang.Object, Q extends java.lang.Object, R extends java.lang.Object, S extends java.lang.Object, T extends java.lang.Object, U extends java.lang.Object, V extends java.lang.Object, Res extends java.lang.Object> shapeless.ops.function$FnToProduct<scala.Function22<A, B, C, D, E, F, G, H, I, J, K, L, M, N, O, P, Q, R, S, T, U, V, Res>> fnToProduct22();
    descriptor: ()Lshapeless/ops/function$FnToProduct;
    flags: (0x0001) ACC_PUBLIC
    Code:
      stack=3, locals=1, args_size=1
         0: new           #40                 // class shapeless/ops/FnToProductInstances$$anon$23
         3: dup
         4: aconst_null
         5: invokespecial #205                // Method shapeless/ops/FnToProductInstances$$anon$23."<init>":(Lshapeless/ops/FnToProductInstances;)V
         8: areturn
      LineNumberTable:
        line 319: 0
      LocalVariableTable:
        Start  Length  Slot  Name   Signature
            0       9     0  this   Lshapeless/ops/FnToProductInstances;
    Signature: #204                         // <A:Ljava/lang/Object;B:Ljava/lang/Object;C:Ljava/lang/Object;D:Ljava/lang/Object;E:Ljava/lang/Object;F:Ljava/lang/Object;G:Ljava/lang/Object;H:Ljava/lang/Object;I:Ljava/lang/Object;J:Ljava/lang/Object;K:Ljava/lang/Object;L:Ljava/lang/Object;M:Ljava/lang/Object;N:Ljava/lang/Object;O:Ljava/lang/Object;P:Ljava/lang/Object;Q:Ljava/lang/Object;R:Ljava/lang/Object;S:Ljava/lang/Object;T:Ljava/lang/Object;U:Ljava/lang/Object;V:Ljava/lang/Object;Res:Ljava/lang/Object;>()Lshapeless/ops/function$FnToProduct<Lscala/Function22<TA;TB;TC;TD;TE;TF;TG;TH;TI;TJ;TK;TL;TM;TN;TO;TP;TQ;TR;TS;TT;TU;TV;TRes;>;>;

  public static void $init$(shapeless.ops.FnToProductInstances);
    descriptor: (Lshapeless/ops/FnToProductInstances;)V
    flags: (0x0009) ACC_PUBLIC, ACC_STATIC
    Code:
      stack=0, locals=1, args_size=1
         0: return
      LineNumberTable:
        line 24: 0
      LocalVariableTable:
        Start  Length  Slot  Name   Signature
            0       1     0 $this   Lshapeless/ops/FnToProductInstances;
    MethodParameters:
      Name                           Flags
      $this                          final synthetic
}
InnerClasses:
  public final #10;                       // class shapeless/ops/FnToProductInstances$$anon$1
  public final #12;                       // class shapeless/ops/FnToProductInstances$$anon$10
  public final #14;                       // class shapeless/ops/FnToProductInstances$$anon$11
  public final #16;                       // class shapeless/ops/FnToProductInstances$$anon$12
  public final #18;                       // class shapeless/ops/FnToProductInstances$$anon$13
  public final #20;                       // class shapeless/ops/FnToProductInstances$$anon$14
  public final #22;                       // class shapeless/ops/FnToProductInstances$$anon$15
  public final #24;                       // class shapeless/ops/FnToProductInstances$$anon$16
  public final #26;                       // class shapeless/ops/FnToProductInstances$$anon$17
  public final #28;                       // class shapeless/ops/FnToProductInstances$$anon$18
  public final #30;                       // class shapeless/ops/FnToProductInstances$$anon$19
  public final #32;                       // class shapeless/ops/FnToProductInstances$$anon$2
  public final #34;                       // class shapeless/ops/FnToProductInstances$$anon$20
  public final #36;                       // class shapeless/ops/FnToProductInstances$$anon$21
  public final #38;                       // class shapeless/ops/FnToProductInstances$$anon$22
  public final #40;                       // class shapeless/ops/FnToProductInstances$$anon$23
  public final #42;                       // class shapeless/ops/FnToProductInstances$$anon$3
  public final #44;                       // class shapeless/ops/FnToProductInstances$$anon$4
  public final #46;                       // class shapeless/ops/FnToProductInstances$$anon$5
  public final #48;                       // class shapeless/ops/FnToProductInstances$$anon$6
  public final #50;                       // class shapeless/ops/FnToProductInstances$$anon$7
  public final #52;                       // class shapeless/ops/FnToProductInstances$$anon$8
  public final #54;                       // class shapeless/ops/FnToProductInstances$$anon$9
  public static #59= #56 of #58;          // FnToProduct=class shapeless/ops/function$FnToProduct of class shapeless/ops/function
SourceFile: "fntoproduct.scala"
RuntimeVisibleAnnotations:
  0: #6(#7=s#8)
    scala.reflect.ScalaSignature(
      bytes="\u0006\u0005!\u001dea\u0002\u000e\u001c!\u0003\r\t\u0001\t\u0005\u0006O\u0001!\t\u0001K\u0003\u0005Y\u0001\u0001Q\u0006C\u0003J\u0001\u0011\r!\nC\u0003\\\u0001\u0011\rA\fC\u0003j\u0001\u0011\r!\u000eC\u0003{\u0001\u0011\r1\u0010C\u0004\u0002\u001e\u0001!\u0019!a\b\t\u000f\u0005-\u0003\u0001b\u0001\u0002N!9\u0011q\u0010\u0001\u0005\u0004\u0005\u0005\u0005bBA\\\u0001\u0011\r\u0011\u0011\u0018\u0005\b\u0003o\u0004A1AA}\u0011\u001d\u0011i\u0004\u0001C\u0002\u0005\u007fAqA!#\u0001\t\u0007\u0011Y\tC\u0004\u0003\\\u0002!\u0019A!8\t\u000f\rM\u0002\u0001b\u0001\u00046!91\u0011\u0013\u0001\u0005\u0004\rM\u0005bBB{\u0001\u0011\r1q\u001f\u0005\b\t?\u0002A1\u0001C1\u0011\u001d!y\r\u0001C\u0002\t#Dq!\"\u0012\u0001\t\u0007)9\u0005C\u0004\u0006B\u0002!\u0019!b1\t\u000f\u0019\r\u0003\u0001b\u0001\u0007F!9a1\u001a\u0001\u0005\u0004\u00195\u0007bBD-\u0001\u0011\rq1\f\u0005\b\u000f[\u0004A1ADx\u0005Q1e\u000eV8Qe>$Wo\u0019;J]N$\u0018M\\2fg*\u0011A$H\u0001\u0004_B\u001c(\"\u0001\u0010\u0002\u0013MD\u0017\r]3mKN\u001c8\u0001A\n\u0003\u0001\u0005\u0002\"AI\u0013\u000e\u0003\rR\u0011\u0001J\u0001\u0006g\u000e\fG.Y\u0005\u0003M\r\u0012a!\u00118z%\u00164\u0017A\u0002\u0013j]&$H\u0005F\u0001*!\t\u0011#&\u0003\u0002,G\t!QK\\5u\u0005\r\tU\u000f_\u000b\u0004]m:%CA\u00182\r\u0011\u0001\u0004\u0001\u0001\u0018\u0003\u0019q\u0012XMZ5oK6,g\u000e\u001e \u0011\u0007I2\u0014H\u0004\u00024i5\t1$\u0003\u000267\u0005Aa-\u001e8di&|g.\u0003\u00028q\tYaI\u001c+p!J|G-^2u\u0015\t)4\u0004\u0005\u0002;w1\u0001A!\u0002\u001f\u0003\u0005\u0004i$!\u0001$\u0012\u0005y\n\u0005C\u0001\u0012@\u0013\t\u00015EA\u0004O_RD\u0017N\\4\u0011\u0005\t\u0012\u0015BA\"$\u0005\r\te._\u0003\u0005\u000b>\u0002cIA\u0002PkR\u0004\"AO$\u0005\u000b!\u0013!\u0019A\u001f\u0003\t=+H\u000fM\u0001\rM:$v\u000e\u0015:pIV\u001cG\u000fM\u000b\u0003\u0017J+\u0012\u0001\u0014\t\u0005\u001b\nqE+D\u0001\u0001!\r\u0011s*U\u0005\u0003!\u000e\u0012\u0011BR;oGRLwN\u001c\u0019\u0011\u0005i\u0012F!B*\u0004\u0005\u0004i$a\u0001*fgB!!%V,R\u0013\t16EA\u0005Gk:\u001cG/[8ocA\u0011\u0001,W\u0007\u0002;%\u0011!,\b\u0002\u0005\u0011:KG.\u0001\u0007g]R{\u0007K]8ek\u000e$\u0018\'F\u0002^C\u0012,\u0012A\u0018\t\u0005\u001b\nyV\r\u0005\u0003#+\u0002\u001c\u0007C\u0001\u001eb\t\u0015\u0011GA1\u0001>\u0005\u0005\t\u0005C\u0001\u001ee\t\u0015\u0019FA1\u0001>!\u0011\u0011SKZ2\u0011\ta;\u0007mV\u0005\u0003Qv\u0011A\u0002J2pY>tGeY8m_:\fAB\u001a8U_B\u0013x\u000eZ;diJ*Ba[9tmV\tA\u000e\u0005\u0003N\u00055<\b#\u0002\u0012oaJ,\u0018BA8$\u0005%1UO\\2uS>t\'\u0007\u0005\u0002;c\u0012)!-\u0002b\u0001{A\u0011!h\u001d\u0003\u0006i\u0016\u0011\r!\u0010\u0002\u0002\u0005B\u0011!H\u001e\u0003\u0006\'\u0016\u0011\r!\u0010\t\u0005EUCX\u000f\u0005\u0003YOBL\b\u0003\u0002-he^\u000bAB\u001a8U_B\u0013x\u000eZ;diN*\u0012\u0002`A\u0003\u0003\u0013\ti!a\u0005\u0016\u0003u\u0004R!\u0014\u0002\u007f\u0003+\u0001\"BI@\u0002\u0004\u0005\u001d\u00111BA\t\u0013\r\t\ta\t\u0002\n\rVt7\r^5p]N\u00022AOA\u0003\t\u0015\u0011gA1\u0001>!\rQ\u0014\u0011\u0002\u0003\u0006i\u001a\u0011\r!\u0010\t\u0004u\u00055AABA\b\r\t\u0007QHA\u0001D!\rQ\u00141\u0003\u0003\u0006\'\u001a\u0011\r!\u0010\t\u0007EU\u000b9\"!\u0005\u0011\ra;\u00171AA\r!\u0019Av-a\u0002\u0002\u001cA)\u0001lZA\u0006/\u0006aaM\u001c+p!J|G-^2uiUa\u0011\u0011EA\u0017\u0003c\t)$!\u000f\u0002@U\u0011\u00111\u0005\t\u0007\u001b\n\t)#!\u0011\u0011\u001b\t\n9#a\u000b\u00020\u0005M\u0012qGA\u001f\u0013\r\tIc\t\u0002\n\rVt7\r^5p]R\u00022AOA\u0017\t\u0015\u0011wA1\u0001>!\rQ\u0014\u0011\u0007\u0003\u0006i\u001e\u0011\r!\u0010\t\u0004u\u0005UBABA\b\u000f\t\u0007Q\bE\u0002;\u0003s!a!a\u000f\b\u0005\u0004i$!\u0001#\u0011\u0007i\ny\u0004B\u0003T\u000f\t\u0007Q\b\u0005\u0004#+\u0006\r\u0013Q\b\t\u00071\u001e\fY#!\u0012\u0011\ra;\u0017qFA$!\u0019Av-a\r\u0002JA)\u0001lZA\u001c/\u0006aaM\u001c+p!J|G-^2ukUq\u0011qJA.\u0003?\n\u0019\'a\u001a\u0002l\u0005ETCAA)!\u0019i%!a\u0015\u0002tAy!%!\u0016\u0002Z\u0005u\u0013\u0011MA3\u0003S\ny\'C\u0002\u0002X\r\u0012\u0011BR;oGRLwN\\\u001b\u0011\u0007i\nY\u0006B\u0003c\u0011\t\u0007Q\bE\u0002;\u0003?\"Q\u0001\u001e\u0005C\u0002u\u00022AOA2\t\u0019\ty\u0001\u0003b\u0001{A\u0019!(a\u001a\u0005\r\u0005m\u0002B1\u0001>!\rQ\u00141\u000e\u0003\u0007\u0003[B!\u0019A\u001f\u0003\u0003\u0015\u00032AOA9\t\u0015\u0019\u0006B1\u0001>!\u0019\u0011S+!\u001e\u0002pA1\u0001lZA-\u0003o\u0002b\u0001W4\u0002^\u0005e\u0004C\u0002-h\u0003C\nY\b\u0005\u0004YO\u0006\u0015\u0014Q\u0010\t\u00061\u001e\fIgV\u0001\rM:$v\u000e\u0015:pIV\u001cGON\u000b\u0011\u0003\u0007\u000by)a%\u0002\u0018\u0006m\u0015qTAR\u0003O+\"!!\"\u0011\r5\u0013\u0011qQAU!E\u0011\u0013\u0011RAG\u0003#\u000b)*!\'\u0002\u001e\u0006\u0005\u0016QU\u0005\u0004\u0003\u0017\u001b#!\u0003$v]\u000e$\u0018n\u001c87!\rQ\u0014q\u0012\u0003\u0006E&\u0011\r!\u0010\t\u0004u\u0005ME!\u0002;\n\u0005\u0004i\u0004c\u0001\u001e\u0002\u0018\u00121\u0011qB\u0005C\u0002u\u00022AOAN\t\u0019\tY$\u0003b\u0001{A\u0019!(a(\u0005\r\u00055\u0014B1\u0001>!\rQ\u00141\u0015\u0003\u0006y%\u0011\r!\u0010\t\u0004u\u0005\u001dF!B*\n\u0005\u0004i\u0004C\u0002\u0012V\u0003W\u000b)\u000b\u0005\u0004YO\u00065\u0015Q\u0016\t\u00071\u001e\f\t*a,\u0011\ra;\u0017QSAY!\u0019Av-!\'\u00024B1\u0001lZAO\u0003k\u0003R\u0001W4\u0002\"^\u000bAB\u001a8U_B\u0013x\u000eZ;di^*\"#a/\u0002H\u0006-\u0017qZAj\u0003/\fY.a8\u0002fV\u0011\u0011Q\u0018\t\u0007\u001b\n\ty,a:\u0011\'\t\n\t-!2\u0002J\u00065\u0017\u0011[Ak\u00033\fi.a9\n\u0007\u0005\r7EA\u0005Gk:\u001cG/[8ooA\u0019!(a2\u0005\u000b\tT!\u0019A\u001f\u0011\u0007i\nY\rB\u0003u\u0015\t\u0007Q\bE\u0002;\u0003\u001f$a!a\u0004\u000b\u0005\u0004i\u0004c\u0001\u001e\u0002T\u00121\u00111\b\u0006C\u0002u\u00022AOAl\t\u0019\tiG\u0003b\u0001{A\u0019!(a7\u0005\u000bqR!\u0019A\u001f\u0011\u0007i\ny\u000e\u0002\u0004\u0002b*\u0011\r!\u0010\u0002\u0002\u000fB\u0019!(!:\u0005\u000bMS!\u0019A\u001f\u0011\r\t*\u0016\u0011^Ar!\u0019Av-!2\u0002lB1\u0001lZAe\u0003[\u0004b\u0001W4\u0002N\u0006=\bC\u0002-h\u0003#\f\t\u0010\u0005\u0004YO\u0006U\u00171\u001f\t\u00071\u001e\fI.!>\u0011\u000ba;\u0017Q\\,\u0002\u0019\u0019tGk\u001c)s_\u0012,8\r\u001e\u001d\u0016)\u0005m(q\u0001B\u0006\u0005\u001f\u0011\u0019Ba\u0006\u0003\u001c\t}!1\u0005B\u0015+\t\ti\u0010\u0005\u0004N\u0005\u0005}(1\u0006\t\u0016E\t\u0005!Q\u0001B\u0005\u0005\u001b\u0011\tB!\u0006\u0003\u001a\tu!\u0011\u0005B\u0014\u0013\r\u0011\u0019a\t\u0002\n\rVt7\r^5p]b\u00022A\u000fB\u0004\t\u0015\u00117B1\u0001>!\rQ$1\u0002\u0003\u0006i.\u0011\r!\u0010\t\u0004u\t=AABA\b\u0017\t\u0007Q\bE\u0002;\u0005\'!a!a\u000f\f\u0005\u0004i\u0004c\u0001\u001e\u0003\u0018\u00111\u0011QN\u0006C\u0002u\u00022A\u000fB\u000e\t\u0015a4B1\u0001>!\rQ$q\u0004\u0003\u0007\u0003C\\!\u0019A\u001f\u0011\u0007i\u0012\u0019\u0003\u0002\u0004\u0003&-\u0011\r!\u0010\u0002\u0002\u0011B\u0019!H!\u000b\u0005\u000bM[!\u0019A\u001f\u0011\r\t*&Q\u0006B\u0014!\u0019AvM!\u0002\u00030A1\u0001l\u001aB\u0005\u0005c\u0001b\u0001W4\u0003\u000e\tM\u0002C\u0002-h\u0005#\u0011)\u0004\u0005\u0004YO\nU!q\u0007\t\u00071\u001e\u0014IB!\u000f\u0011\ra;\'Q\u0004B\u001e!\u0015AvM!\tX\u000311g\u000eV8Qe>$Wo\u0019;:+Y\u0011\tE!\u0014\u0003R\tU#\u0011\fB/\u0005C\u0012)G!\u001b\u0003n\tMTC\u0001B\"!\u0019i%A!\u0012\u0003vA9\"Ea\u0012\u0003L\t=#1\u000bB,\u00057\u0012yFa\u0019\u0003h\t-$\u0011O\u0005\u0004\u0005\u0013\u001a#!\u0003$v]\u000e$\u0018n\u001c8:!\rQ$Q\n\u0003\u0006E2\u0011\r!\u0010\t\u0004u\tEC!\u0002;\r\u0005\u0004i\u0004c\u0001\u001e\u0003V\u00111\u0011q\u0002\u0007C\u0002u\u00022A\u000fB-\t\u0019\tY\u0004\u0004b\u0001{A\u0019!H!\u0018\u0005\r\u00055DB1\u0001>!\rQ$\u0011\r\u0003\u0006y1\u0011\r!\u0010\t\u0004u\t\u0015DABAq\u0019\t\u0007Q\bE\u0002;\u0005S\"aA!\n\r\u0005\u0004i\u0004c\u0001\u001e\u0003n\u00111!q\u000e\u0007C\u0002u\u0012\u0011!\u0013\t\u0004u\tMD!B*\r\u0005\u0004i\u0004C\u0002\u0012V\u0005o\u0012\t\b\u0005\u0004YO\n-#\u0011\u0010\t\u00071\u001e\u0014yEa\u001f\u0011\ra;\'1\u000bB?!\u0019AvMa\u0016\u0003\u0000A1\u0001l\u001aB.\u0005\u0003\u0003b\u0001W4\u0003`\t\r\u0005C\u0002-h\u0005G\u0012)\t\u0005\u0004YO\n\u001d$q\u0011\t\u00061\u001e\u0014YgV\u0001\u000eM:$v\u000e\u0015:pIV\u001cG/\r\u0019\u00161\t5%\u0011\u0014BO\u0005C\u0013)K!+\u0003.\nE&Q\u0017B]\u0005{\u0013\u0019-\u0006\u0002\u0003\u0010B1QJ\u0001BI\u0005\u000b\u0004\u0012D\tBJ\u0005/\u0013YJa(\u0003$\n\u001d&1\u0016BX\u0005g\u00139La/\u0003B&\u0019!QS\u0012\u0003\u0015\u0019+hn\u0019;j_:\f\u0004\u0007E\u0002;\u00053#QAY\u0007C\u0002u\u00022A\u000fBO\t\u0015!XB1\u0001>!\rQ$\u0011\u0015\u0003\u0007\u0003\u001fi!\u0019A\u001f\u0011\u0007i\u0012)\u000b\u0002\u0004\u0002<5\u0011\r!\u0010\t\u0004u\t%FABA7\u001b\t\u0007Q\bE\u0002;\u0005[#Q\u0001P\u0007C\u0002u\u00022A\u000fBY\t\u0019\t\t/\u0004b\u0001{A\u0019!H!.\u0005\r\t\u0015RB1\u0001>!\rQ$\u0011\u0018\u0003\u0007\u0005_j!\u0019A\u001f\u0011\u0007i\u0012i\f\u0002\u0004\u0003@6\u0011\r!\u0010\u0002\u0002\u0015B\u0019!Ha1\u0005\u000bMk!\u0019A\u001f\u0011\r\t*&q\u0019Ba!\u0019AvMa&\u0003JB1\u0001l\u001aBN\u0005\u0017\u0004b\u0001W4\u0003 \n5\u0007C\u0002-h\u0005G\u0013y\r\u0005\u0004YO\n\u001d&\u0011\u001b\t\u00071\u001e\u0014YKa5\u0011\ra;\'q\u0016Bk!\u0019AvMa-\u0003XB1\u0001l\u001aB\\\u00053\u0004R\u0001W4\u0003<^\u000bQB\u001a8U_B\u0013x\u000eZ;diF\nTC\u0007Bp\u0005W\u0014yOa=\u0003x\nm(q`B\u0002\u0007\u000f\u0019Yaa\u0004\u0004\u0014\reQC\u0001Bq!\u0019i%Aa9\u0004\u001cAY\"E!:\u0003j\n5(\u0011\u001fB{\u0005s\u0014ip!\u0001\u0004\u0006\r%1QBB\t\u0007/I1Aa:$\u0005)1UO\\2uS>t\u0017\'\r\t\u0004u\t-H!\u00022\u000f\u0005\u0004i\u0004c\u0001\u001e\u0003p\u0012)AO\u0004b\u0001{A\u0019!Ha=\u0005\r\u0005=aB1\u0001>!\rQ$q\u001f\u0003\u0007\u0003wq!\u0019A\u001f\u0011\u0007i\u0012Y\u0010\u0002\u0004\u0002n9\u0011\r!\u0010\t\u0004u\t}H!\u0002\u001f\u000f\u0005\u0004i\u0004c\u0001\u001e\u0004\u0004\u00111\u0011\u0011\u001d\bC\u0002u\u00022AOB\u0004\t\u0019\u0011)C\u0004b\u0001{A\u0019!ha\u0003\u0005\r\t=dB1\u0001>!\rQ4q\u0002\u0003\u0007\u0005\u007fs!\u0019A\u001f\u0011\u0007i\u001a\u0019\u0002\u0002\u0004\u0004\u00169\u0011\r!\u0010\u0002\u0002\u0017B\u0019!h!\u0007\u0005\u000bMs!\u0019A\u001f\u0011\r\t*6QDB\f!\u0019AvM!;\u0004 A1\u0001l\u001aBw\u0007C\u0001b\u0001W4\u0003r\u000e\r\u0002C\u0002-h\u0005k\u001c)\u0003\u0005\u0004YO\ne8q\u0005\t\u00071\u001e\u0014ip!\u000b\u0011\ra;7\u0011AB\u0016!\u0019Avm!\u0002\u0004.A1\u0001lZB\u0005\u0007_\u0001b\u0001W4\u0004\u000e\rE\u0002#\u0002-h\u0007#9\u0016!\u00044o)>\u0004&o\u001c3vGR\f$\'\u0006\u000f\u00048\r\r3qIB&\u0007\u001f\u001a\u0019fa\u0016\u0004\\\r}31MB4\u0007W\u001ayg!\u001e\u0016\u0005\re\u0002CB\'\u0003\u0007w\u00199\bE\u000f#\u0007{\u0019\te!\u0012\u0004J\r53\u0011KB+\u00073\u001aif!\u0019\u0004f\r%4QNB:\u0013\r\u0019yd\t\u0002\u000b\rVt7\r^5p]F\u0012\u0004c\u0001\u001e\u0004D\u0011)!m\u0004b\u0001{A\u0019!ha\u0012\u0005\u000bQ|!\u0019A\u001f\u0011\u0007i\u001aY\u0005\u0002\u0004\u0002\u0010=\u0011\r!\u0010\t\u0004u\r=CABA\u001e\u001f\t\u0007Q\bE\u0002;\u0007\'\"a!!\u001c\u0010\u0005\u0004i\u0004c\u0001\u001e\u0004X\u0011)Ah\u0004b\u0001{A\u0019!ha\u0017\u0005\r\u0005\u0005xB1\u0001>!\rQ4q\f\u0003\u0007\u0005Ky!\u0019A\u001f\u0011\u0007i\u001a\u0019\u0007\u0002\u0004\u0003p=\u0011\r!\u0010\t\u0004u\r\u001dDA\u0002B`\u001f\t\u0007Q\bE\u0002;\u0007W\"aa!\u0006\u0010\u0005\u0004i\u0004c\u0001\u001e\u0004p\u001111\u0011O\bC\u0002u\u0012\u0011\u0001\u0014\t\u0004u\rUD!B*\u0010\u0005\u0004i\u0004C\u0002\u0012V\u0007s\u001a\u0019\b\u0005\u0004YO\u000e\u000531\u0010\t\u00071\u001e\u001c)e! \u0011\ra;7\u0011JB@!\u0019Avm!\u0014\u0004\u0002B1\u0001lZB)\u0007\u0007\u0003b\u0001W4\u0004V\r\u0015\u0005C\u0002-h\u00073\u001a9\t\u0005\u0004YO\u000eu3\u0011\u0012\t\u00071\u001e\u001c\tga#\u0011\ra;7QMBG!\u0019Avm!\u001b\u0004\u0010B)\u0001lZB7/\u0006iaM\u001c+p!J|G-^2ucM*bd!&\u0004\"\u000e\u00156\u0011VBW\u0007c\u001b)l!/\u0004>\u000e\u00057QYBe\u0007\u001b\u001c\tna6\u0016\u0005\r]\u0005CB\'\u0003\u00073\u001bI\u000eE\u0010#\u00077\u001byja)\u0004(\u000e-6qVBZ\u0007o\u001bYla0\u0004D\u000e\u001d71ZBh\u0007+L1a!($\u0005)1UO\\2uS>t\u0017g\r\t\u0004u\r\u0005F!\u00022\u0011\u0005\u0004i\u0004c\u0001\u001e\u0004&\u0012)A\u000f\u0005b\u0001{A\u0019!h!+\u0005\r\u0005=\u0001C1\u0001>!\rQ4Q\u0016\u0003\u0007\u0003w\u0001\"\u0019A\u001f\u0011\u0007i\u001a\t\f\u0002\u0004\u0002nA\u0011\r!\u0010\t\u0004u\rUF!\u0002\u001f\u0011\u0005\u0004i\u0004c\u0001\u001e\u0004:\u00121\u0011\u0011\u001d\tC\u0002u\u00022AOB_\t\u0019\u0011)\u0003\u0005b\u0001{A\u0019!h!1\u0005\r\t=\u0004C1\u0001>!\rQ4Q\u0019\u0003\u0007\u0005\u007f\u0003\"\u0019A\u001f\u0011\u0007i\u001aI\r\u0002\u0004\u0004\u0016A\u0011\r!\u0010\t\u0004u\r5GABB9!\t\u0007Q\bE\u0002;\u0007#$aaa5\u0011\u0005\u0004i$!A\'\u0011\u0007i\u001a9\u000eB\u0003T!\t\u0007Q\b\u0005\u0004#+\u000em7Q\u001b\t\u00071\u001e\u001cyj!8\u0011\ra;71UBp!\u0019Avma*\u0004bB1\u0001lZBV\u0007G\u0004b\u0001W4\u00040\u000e\u0015\bC\u0002-h\u0007g\u001b9\u000f\u0005\u0004YO\u000e]6\u0011\u001e\t\u00071\u001e\u001cYla;\u0011\ra;7qXBw!\u0019Avma1\u0004pB1\u0001lZBd\u0007c\u0004b\u0001W4\u0004L\u000eM\b#\u0002-h\u0007\u001f<\u0016!\u00044o)>\u0004&o\u001c3vGR\fD\'\u0006\u0011\u0004z\u0012\u0015A\u0011\u0002C\u0007\t#!)\u0002\"\u0007\u0005\u001e\u0011\u0005BQ\u0005C\u0015\t[!\t\u0004\"\u000e\u0005:\u0011}RCAB~!\u0019i%a!@\u0005BA\t#ea@\u0005\u0004\u0011\u001dA1\u0002C\b\t\'!9\u0002b\u0007\u0005 \u0011\rBq\u0005C\u0016\t_!\u0019\u0004b\u000e\u0005>%\u0019A\u0011A\u0012\u0003\u0015\u0019+hn\u0019;j_:\fD\u0007E\u0002;\t\u000b!QAY\tC\u0002u\u00022A\u000fC\u0005\t\u0015!\u0018C1\u0001>!\rQDQ\u0002\u0003\u0007\u0003\u001f\t\"\u0019A\u001f\u0011\u0007i\"\t\u0002\u0002\u0004\u0002<E\u0011\r!\u0010\t\u0004u\u0011UAABA7#\t\u0007Q\bE\u0002;\t3!Q\u0001P\tC\u0002u\u00022A\u000fC\u000f\t\u0019\t\t/\u0005b\u0001{A\u0019!\b\"\t\u0005\r\t\u0015\u0012C1\u0001>!\rQDQ\u0005\u0003\u0007\u0005_\n\"\u0019A\u001f\u0011\u0007i\"I\u0003\u0002\u0004\u0003@F\u0011\r!\u0010\t\u0004u\u00115BABB\u000b#\t\u0007Q\bE\u0002;\tc!aa!\u001d\u0012\u0005\u0004i\u0004c\u0001\u001e\u00056\u0011111[\tC\u0002u\u00022A\u000fC\u001d\t\u0019!Y$\u0005b\u0001{\t\ta\nE\u0002;\t\u007f!QaU\tC\u0002u\u0002bAI+\u0005D\u0011u\u0002C\u0002-h\t\u0007!)\u0005\u0005\u0004YO\u0012\u001dAq\t\t\u00071\u001e$Y\u0001\"\u0013\u0011\ra;Gq\u0002C&!\u0019Av\rb\u0005\u0005NA1\u0001l\u001aC\f\t\u001f\u0002b\u0001W4\u0005\u001c\u0011E\u0003C\u0002-h\t?!\u0019\u0006\u0005\u0004YO\u0012\rBQ\u000b\t\u00071\u001e$9\u0003b\u0016\u0011\ra;G1\u0006C-!\u0019Av\rb\f\u0005\\A1\u0001l\u001aC\u001a\t;\u0002R\u0001W4\u00058]\u000bQB\u001a8U_B\u0013x\u000eZ;diF*TC\tC2\t_\"\u0019\bb\u001e\u0005|\u0011}D1\u0011CD\t\u0017#y\tb%\u0005\u0018\u0012mEq\u0014CR\tO#i+\u0006\u0002\u0005fA1QJ\u0001C4\t_\u00032E\tC5\t[\"\t\b\"\u001e\u0005z\u0011uD\u0011\u0011CC\t\u0013#i\t\"%\u0005\u0016\u0012eEQ\u0014CQ\tK#Y+C\u0002\u0005l\r\u0012!BR;oGRLwN\\\u00196!\rQDq\u000e\u0003\u0006EJ\u0011\r!\u0010\t\u0004u\u0011MD!\u0002;\u0013\u0005\u0004i\u0004c\u0001\u001e\u0005x\u00111\u0011q\u0002\nC\u0002u\u00022A\u000fC>\t\u0019\tYD\u0005b\u0001{A\u0019!\bb \u0005\r\u00055$C1\u0001>!\rQD1\u0011\u0003\u0006yI\u0011\r!\u0010\t\u0004u\u0011\u001dEABAq%\t\u0007Q\bE\u0002;\t\u0017#aA!\n\u0013\u0005\u0004i\u0004c\u0001\u001e\u0005\u0010\u00121!q\u000e\nC\u0002u\u00022A\u000fCJ\t\u0019\u0011yL\u0005b\u0001{A\u0019!\bb&\u0005\r\rU!C1\u0001>!\rQD1\u0014\u0003\u0007\u0007c\u0012\"\u0019A\u001f\u0011\u0007i\"y\n\u0002\u0004\u0004TJ\u0011\r!\u0010\t\u0004u\u0011\rFA\u0002C\u001e%\t\u0007Q\bE\u0002;\tO#a\u0001\"+\u0013\u0005\u0004i$!A(\u0011\u0007i\"i\u000bB\u0003T%\t\u0007Q\b\u0005\u0004#+\u0012EF1\u0016\t\u00071\u001e$i\u0007b-\u0011\ra;G\u0011\u000fC[!\u0019Av\r\"\u001e\u00058B1\u0001l\u001aC=\ts\u0003b\u0001W4\u0005~\u0011m\u0006C\u0002-h\t\u0003#i\f\u0005\u0004YO\u0012\u0015Eq\u0018\t\u00071\u001e$I\t\"1\u0011\ra;GQ\u0012Cb!\u0019Av\r\"%\u0005FB1\u0001l\u001aCK\t\u000f\u0004b\u0001W4\u0005\u001a\u0012%\u0007C\u0002-h\t;#Y\r\u0005\u0004YO\u0012\u0005FQ\u001a\t\u00061\u001e$)kV\u0001\u000eM:$v\u000e\u0015:pIV\u001cG/\r\u001c\u0016I\u0011MGq\u001cCr\tO$Y\u000fb<\u0005t\u0012]H1 C\u0000\u000b\u0007)9!b\u0003\u0006\u0010\u0015MQqCC\u000e\u000bC)\"\u0001\"6\u0011\r5\u0013Aq[C\u0012!\u0015\u0012C\u0011\u001cCo\tC$)\u000f\";\u0005n\u0012EHQ\u001fC}\t{,\t!\"\u0002\u0006\n\u00155Q\u0011CC\u000b\u000b3)y\"C\u0002\u0005\\\u000e\u0012!BR;oGRLwN\\\u00197!\rQDq\u001c\u0003\u0006EN\u0011\r!\u0010\t\u0004u\u0011\rH!\u0002;\u0014\u0005\u0004i\u0004c\u0001\u001e\u0005h\u00121\u0011qB\nC\u0002u\u00022A\u000fCv\t\u0019\tYd\u0005b\u0001{A\u0019!\bb<\u0005\r\u000554C1\u0001>!\rQD1\u001f\u0003\u0006yM\u0011\r!\u0010\t\u0004u\u0011]HABAq\'\t\u0007Q\bE\u0002;\tw$aA!\n\u0014\u0005\u0004i\u0004c\u0001\u001e\u0005\u0000\u00121!qN\nC\u0002u\u00022AOC\u0002\t\u0019\u0011yl\u0005b\u0001{A\u0019!(b\u0002\u0005\r\rU1C1\u0001>!\rQT1\u0002\u0003\u0007\u0007c\u001a\"\u0019A\u001f\u0011\u0007i*y\u0001\u0002\u0004\u0004TN\u0011\r!\u0010\t\u0004u\u0015MAA\u0002C\u001e\'\t\u0007Q\bE\u0002;\u000b/!a\u0001\"+\u0014\u0005\u0004i\u0004c\u0001\u001e\u0006\u001c\u00111QQD\nC\u0002u\u0012\u0011\u0001\u0015\t\u0004u\u0015\u0005B!B*\u0014\u0005\u0004i\u0004C\u0002\u0012V\u000bK)y\u0002\u0005\u0004YO\u0012uWq\u0005\t\u00071\u001e$\t/\"\u000b\u0011\ra;GQ]C\u0016!\u0019Av\r\";\u0006.A1\u0001l\u001aCw\u000b_\u0001b\u0001W4\u0005r\u0016E\u0002C\u0002-h\tk,\u0019\u0004\u0005\u0004YO\u0012eXQ\u0007\t\u00071\u001e$i0b\u000e\u0011\ra;W\u0011AC\u001d!\u0019Av-\"\u0002\u0006<A1\u0001lZC\u0005\u000b{\u0001b\u0001W4\u0006\u000e\u0015}\u0002C\u0002-h\u000b#)\t\u0005\u0005\u0004YO\u0016UQ1\t\t\u00061\u001e,IbV\u0001\u000eM:$v\u000e\u0015:pIV\u001cG/M\u001c\u0016M\u0015%SQKC-\u000b;*\t\'\"\u001a\u0006j\u00155T\u0011OC;\u000bs*i(\"!\u0006\u0006\u0016%UQRCI\u000b++Y*\u0006\u0002\u0006LA1QJAC\'\u000b;\u0003rEIC(\u000b\'*9&b\u0017\u0006`\u0015\rTqMC6\u000b_*\u0019(b\u001e\u0006|\u0015}T1QCD\u000b\u0017+y)b%\u0006\u001a&\u0019Q\u0011K\u0012\u0003\u0015\u0019+hn\u0019;j_:\ft\u0007E\u0002;\u000b+\"QA\u0019\u000bC\u0002u\u00022AOC-\t\u0015!HC1\u0001>!\rQTQ\f\u0003\u0007\u0003\u001f!\"\u0019A\u001f\u0011\u0007i*\t\u0007\u0002\u0004\u0002<Q\u0011\r!\u0010\t\u0004u\u0015\u0015DABA7)\t\u0007Q\bE\u0002;\u000bS\"Q\u0001\u0010\u000bC\u0002u\u00022AOC7\t\u0019\t\t\u000f\u0006b\u0001{A\u0019!(\"\u001d\u0005\r\t\u0015BC1\u0001>!\rQTQ\u000f\u0003\u0007\u0005_\"\"\u0019A\u001f\u0011\u0007i*I\b\u0002\u0004\u0003@R\u0011\r!\u0010\t\u0004u\u0015uDABB\u000b)\t\u0007Q\bE\u0002;\u000b\u0003#aa!\u001d\u0015\u0005\u0004i\u0004c\u0001\u001e\u0006\u0006\u0012111\u001b\u000bC\u0002u\u00022AOCE\t\u0019!Y\u0004\u0006b\u0001{A\u0019!(\"$\u0005\r\u0011%FC1\u0001>!\rQT\u0011\u0013\u0003\u0007\u000b;!\"\u0019A\u001f\u0011\u0007i*)\n\u0002\u0004\u0006\u0018R\u0011\r!\u0010\u0002\u0002#B\u0019!(b\'\u0005\u000bM#\"\u0019A\u001f\u0011\r\t*VqTCM!\u0019Av-b\u0015\u0006\"B1\u0001lZC,\u000bG\u0003b\u0001W4\u0006\\\u0015\u0015\u0006C\u0002-h\u000b?*9\u000b\u0005\u0004YO\u0016\rT\u0011\u0016\t\u00071\u001e,9\'b+\u0011\ra;W1NCW!\u0019Av-b\u001c\u00060B1\u0001lZC:\u000bc\u0003b\u0001W4\u0006x\u0015M\u0006C\u0002-h\u000bw*)\f\u0005\u0004YO\u0016}Tq\u0017\t\u00071\u001e,\u0019)\"/\u0011\ra;WqQC^!\u0019Av-b#\u0006>B1\u0001lZCH\u000b\u007f\u0003R\u0001W4\u0006\u0014^\u000bQB\u001a8U_B\u0013x\u000eZ;diFBT\u0003KCc\u000b#,).\"7\u0006^\u0016\u0005XQ]Cu\u000b[,\t0\">\u0006z\u0016uh\u0011\u0001D\u0003\r\u00131iA\"\u0005\u0007\u0016\u0019mQCACd!\u0019i%!\"3\u0007\u001eAI#%b3\u0006P\u0016MWq[Cn\u000b?,\u0019/b:\u0006l\u0016=X1_C|\u000bw,yPb\u0001\u0007\b\u0019-aq\u0002D\n\r3I1!\"4$\u0005)1UO\\2uS>t\u0017\u0007\u000f\t\u0004u\u0015EG!\u00022\u0016\u0005\u0004i\u0004c\u0001\u001e\u0006V\u0012)A/\u0006b\u0001{A\u0019!(\"7\u0005\r\u0005=QC1\u0001>!\rQTQ\u001c\u0003\u0007\u0003w)\"\u0019A\u001f\u0011\u0007i*\t\u000f\u0002\u0004\u0002nU\u0011\r!\u0010\t\u0004u\u0015\u0015H!\u0002\u001f\u0016\u0005\u0004i\u0004c\u0001\u001e\u0006j\u00121\u0011\u0011]\u000bC\u0002u\u00022AOCw\t\u0019\u0011)#\u0006b\u0001{A\u0019!(\"=\u0005\r\t=TC1\u0001>!\rQTQ\u001f\u0003\u0007\u0005\u007f+\"\u0019A\u001f\u0011\u0007i*I\u0010\u0002\u0004\u0004\u0016U\u0011\r!\u0010\t\u0004u\u0015uHABB9+\t\u0007Q\bE\u0002;\r\u0003!aaa5\u0016\u0005\u0004i\u0004c\u0001\u001e\u0007\u0006\u00111A1H\u000bC\u0002u\u00022A\u000fD\u0005\t\u0019!I+\u0006b\u0001{A\u0019!H\"\u0004\u0005\r\u0015uQC1\u0001>!\rQd\u0011\u0003\u0003\u0007\u000b/+\"\u0019A\u001f\u0011\u0007i2)\u0002\u0002\u0004\u0007\u0018U\u0011\r!\u0010\u0002\u0002%B\u0019!Hb\u0007\u0005\u000bM+\"\u0019A\u001f\u0011\r\t*fq\u0004D\r!\u0019Av-b4\u0007\"A1\u0001lZCj\rG\u0001b\u0001W4\u0006X\u001a\u0015\u0002C\u0002-h\u000b749\u0003\u0005\u0004YO\u0016}g\u0011\u0006\t\u00071\u001e,\u0019Ob\u000b\u0011\ra;Wq\u001dD\u0017!\u0019Av-b;\u00070A1\u0001lZCx\rc\u0001b\u0001W4\u0006t\u001aM\u0002C\u0002-h\u000bo4)\u0004\u0005\u0004YO\u0016mhq\u0007\t\u00071\u001e,yP\"\u000f\u0011\ra;g1\u0001D\u001e!\u0019AvMb\u0002\u0007>A1\u0001l\u001aD\u0006\r\u007f\u0001b\u0001W4\u0007\u0010\u0019\u0005\u0003#\u0002-h\r\'9\u0016!\u00044o)>\u0004&o\u001c3vGR\f\u0014(\u0006\u0016\u0007H\u0019Mcq\u000bD.\r?2\u0019Gb\u001a\u0007l\u0019=d1\u000fD<\rw2yHb!\u0007\b\u001a-eq\u0012DJ\r/3YJ\")\u0016\u0005\u0019%\u0003CB\'\u0003\r\u00172\u0019\u000bE\u0016#\r\u001b2\tF\"\u0016\u0007Z\u0019uc\u0011\rD3\rS2iG\"\u001d\u0007v\u0019edQ\u0010DA\r\u000b3II\"$\u0007\u0012\u001aUe\u0011\u0014DP\u0013\r1ye\t\u0002\u000b\rVt7\r^5p]FJ\u0004c\u0001\u001e\u0007T\u0011)!M\u0006b\u0001{A\u0019!Hb\u0016\u0005\u000bQ4\"\u0019A\u001f\u0011\u0007i2Y\u0006\u0002\u0004\u0002\u0010Y\u0011\r!\u0010\t\u0004u\u0019}CABA\u001e-\t\u0007Q\bE\u0002;\rG\"a!!\u001c\u0017\u0005\u0004i\u0004c\u0001\u001e\u0007h\u0011)AH\u0006b\u0001{A\u0019!Hb\u001b\u0005\r\u0005\u0005hC1\u0001>!\rQdq\u000e\u0003\u0007\u0005K1\"\u0019A\u001f\u0011\u0007i2\u0019\b\u0002\u0004\u0003pY\u0011\r!\u0010\t\u0004u\u0019]DA\u0002B`-\t\u0007Q\bE\u0002;\rw\"aa!\u0006\u0017\u0005\u0004i\u0004c\u0001\u001e\u0007\u0000\u001111\u0011\u000f\fC\u0002u\u00022A\u000fDB\t\u0019\u0019\u0019N\u0006b\u0001{A\u0019!Hb\"\u0005\r\u0011mbC1\u0001>!\rQd1\u0012\u0003\u0007\tS3\"\u0019A\u001f\u0011\u0007i2y\t\u0002\u0004\u0006\u001eY\u0011\r!\u0010\t\u0004u\u0019MEABCL-\t\u0007Q\bE\u0002;\r/#aAb\u0006\u0017\u0005\u0004i\u0004c\u0001\u001e\u0007\u001c\u00121aQ\u0014\fC\u0002u\u0012\u0011a\u0015\t\u0004u\u0019\u0005F!B*\u0017\u0005\u0004i\u0004C\u0002\u0012V\rK3y\n\u0005\u0004YO\u001aEcq\u0015\t\u00071\u001e4)F\"+\u0011\ra;g\u0011\fDV!\u0019AvM\"\u0018\u0007.B1\u0001l\u001aD1\r_\u0003b\u0001W4\u0007f\u0019E\u0006C\u0002-h\rS2\u0019\f\u0005\u0004YO\u001a5dQ\u0017\t\u00071\u001e4\tHb.\u0011\ra;gQ\u000fD]!\u0019AvM\"\u001f\u0007<B1\u0001l\u001aD?\r{\u0003b\u0001W4\u0007\u0002\u001a}\u0006C\u0002-h\r\u000b3\t\r\u0005\u0004YO\u001a%e1\u0019\t\u00071\u001e4iI\"2\u0011\ra;g\u0011\u0013Dd!\u0019AvM\"&\u0007JB)\u0001l\u001aDM/\u0006iaM\u001c+p!J|G-^2ueA*BFb4\u0007\\\u001a}g1\u001dDt\rW4yOb=\u0007x\u001amhq`D\u0002\u000f\u000f9Yab\u0004\b\u0014\u001d]q1DD\u0010\u000fG99c\"\f\u0016\u0005\u0019E\u0007CB\'\u0003\r\'<y\u0003E\u0017#\r+4IN\"8\u0007b\u001a\u0015h\u0011\u001eDw\rc4)P\"?\u0007~\u001e\u0005qQAD\u0005\u000f\u001b9\tb\"\u0006\b\u001a\u001duq\u0011ED\u0013\u000fWI1Ab6$\u0005)1UO\\2uS>t\'\u0007\r\t\u0004u\u0019mG!\u00022\u0018\u0005\u0004i\u0004c\u0001\u001e\u0007`\u0012)Ao\u0006b\u0001{A\u0019!Hb9\u0005\r\u0005=qC1\u0001>!\rQdq\u001d\u0003\u0007\u0003w9\"\u0019A\u001f\u0011\u0007i2Y\u000f\u0002\u0004\u0002n]\u0011\r!\u0010\t\u0004u\u0019=H!\u0002\u001f\u0018\u0005\u0004i\u0004c\u0001\u001e\u0007t\u00121\u0011\u0011]\fC\u0002u\u00022A\u000fD|\t\u0019\u0011)c\u0006b\u0001{A\u0019!Hb?\u0005\r\t=tC1\u0001>!\rQdq \u0003\u0007\u0005\u007f;\"\u0019A\u001f\u0011\u0007i:\u0019\u0001\u0002\u0004\u0004\u0016]\u0011\r!\u0010\t\u0004u\u001d\u001dAABB9/\t\u0007Q\bE\u0002;\u000f\u0017!aaa5\u0018\u0005\u0004i\u0004c\u0001\u001e\b\u0010\u00111A1H\fC\u0002u\u00022AOD\n\t\u0019!Ik\u0006b\u0001{A\u0019!hb\u0006\u0005\r\u0015uqC1\u0001>!\rQt1\u0004\u0003\u0007\u000b/;\"\u0019A\u001f\u0011\u0007i:y\u0002\u0002\u0004\u0007\u0018]\u0011\r!\u0010\t\u0004u\u001d\rBA\u0002DO/\t\u0007Q\bE\u0002;\u000fO!aa\"\u000b\u0018\u0005\u0004i$!\u0001+\u0011\u0007i:i\u0003B\u0003T/\t\u0007Q\b\u0005\u0004#+\u001eEr1\u0006\t\u00071\u001e4Inb\r\u0011\ra;gQ\\D\u001b!\u0019AvM\"9\b8A1\u0001l\u001aDs\u000fs\u0001b\u0001W4\u0007j\u001em\u0002C\u0002-h\r[<i\u0004\u0005\u0004YO\u001aExq\b\t\u00071\u001e4)p\"\u0011\u0011\ra;g\u0011`D\"!\u0019AvM\"@\bFA1\u0001lZD\u0001\u000f\u000f\u0002b\u0001W4\b\u0006\u001d%\u0003C\u0002-h\u000f\u00139Y\u0005\u0005\u0004YO\u001e5qQ\n\t\u00071\u001e<\tbb\u0014\u0011\ra;wQCD)!\u0019Avm\"\u0007\bTA1\u0001lZD\u000f\u000f+\u0002b\u0001W4\b\"\u001d]\u0003#\u0002-h\u000fK9\u0016!\u00044o)>\u0004&o\u001c3vGR\u0014\u0014\'\u0006\u0018\b^\u001d%tQND9\u000fk:Ih\" \b\u0002\u001e\u0015u\u0011RDG\u000f#;)j\"\'\b\u001e\u001e\u0005vQUDU\u000f[;\tl\".\b:\u001e}VCAD0!\u0019i%a\"\u0019\bBBy#eb\u0019\bh\u001d-tqND:\u000fo:Yhb \b\u0004\u001e\u001du1RDH\u000f\';9jb\'\b \u001e\rvqUDV\u000f_;\u0019lb.\b>&\u0019qQM\u0012\u0003\u0015\u0019+hn\u0019;j_:\u0014\u0014\u0007E\u0002;\u000fS\"QA\u0019\rC\u0002u\u00022AOD7\t\u0015!\bD1\u0001>!\rQt\u0011\u000f\u0003\u0007\u0003\u001fA\"\u0019A\u001f\u0011\u0007i:)\b\u0002\u0004\u0002<a\u0011\r!\u0010\t\u0004u\u001deDABA71\t\u0007Q\bE\u0002;\u000f{\"Q\u0001\u0010\rC\u0002u\u00022AODA\t\u0019\t\t\u000f\u0007b\u0001{A\u0019!h\"\"\u0005\r\t\u0015\u0002D1\u0001>!\rQt\u0011\u0012\u0003\u0007\u0005_B\"\u0019A\u001f\u0011\u0007i:i\t\u0002\u0004\u0003@b\u0011\r!\u0010\t\u0004u\u001dEEABB\u000b1\t\u0007Q\bE\u0002;\u000f+#aa!\u001d\u0019\u0005\u0004i\u0004c\u0001\u001e\b\u001a\u0012111\u001b\rC\u0002u\u00022AODO\t\u0019!Y\u0004\u0007b\u0001{A\u0019!h\")\u0005\r\u0011%\u0006D1\u0001>!\rQtQ\u0015\u0003\u0007\u000b;A\"\u0019A\u001f\u0011\u0007i:I\u000b\u0002\u0004\u0006\u0018b\u0011\r!\u0010\t\u0004u\u001d5FA\u0002D\f1\t\u0007Q\bE\u0002;\u000fc#aA\"(\u0019\u0005\u0004i\u0004c\u0001\u001e\b6\u00121q\u0011\u0006\rC\u0002u\u00022AOD]\t\u00199Y\f\u0007b\u0001{\t\tQ\u000bE\u0002;\u000f\u007f#Qa\u0015\rC\u0002u\u0002bAI+\bD\u001eu\u0006C\u0002-h\u000fO:)\r\u0005\u0004YO\u001e-tq\u0019\t\u00071\u001e<yg\"3\u0011\ra;w1ODf!\u0019Avmb\u001e\bNB1\u0001lZD>\u000f\u001f\u0004b\u0001W4\b\u0000\u001dE\u0007C\u0002-h\u000f\u0007;\u0019\u000e\u0005\u0004YO\u001e\u001duQ\u001b\t\u00071\u001e<Yib6\u0011\ra;wqRDm!\u0019Avmb%\b\\B1\u0001lZDL\u000f;\u0004b\u0001W4\b\u001c\u001e}\u0007C\u0002-h\u000f?;\t\u000f\u0005\u0004YO\u001e\rv1\u001d\t\u00071\u001e<9k\":\u0011\ra;w1VDt!\u0019Avmb,\bjB1\u0001lZDZ\u000fW\u0004R\u0001W4\b8^\u000bQB\u001a8U_B\u0013x\u000eZ;diJ\u0012T\u0003MDy\u000f{D\t\u0001#\u0002\t\n!5\u0001\u0012\u0003E\u000b\u00113Ai\u0002#\t\t&!%\u0002R\u0006E\u0019\u0011kAI\u0004#\u0010\tB!\u0015\u0003\u0012\nE\'\u0011#B9&\u0006\u0002\btB1QJAD{\u00113\u0002\u0012GID|\u000fw<y\u0010c\u0001\t\b!-\u0001r\u0002E\n\u0011/AY\u0002c\b\t$!\u001d\u00022\u0006E\u0018\u0011gA9\u0004c\u000f\t@!\r\u0003r\tE&\u0011\u001fB)&C\u0002\bz\u000e\u0012!BR;oGRLwN\u001c\u001a3!\rQtQ \u0003\u0006Ef\u0011\r!\u0010\t\u0004u!\u0005A!\u0002;\u001a\u0005\u0004i\u0004c\u0001\u001e\t\u0006\u00111\u0011qB\rC\u0002u\u00022A\u000fE\u0005\t\u0019\tY$\u0007b\u0001{A\u0019!\b#\u0004\u0005\r\u00055\u0014D1\u0001>!\rQ\u0004\u0012\u0003\u0003\u0006ye\u0011\r!\u0010\t\u0004u!UAABAq3\t\u0007Q\bE\u0002;\u00113!aA!\n\u001a\u0005\u0004i\u0004c\u0001\u001e\t\u001e\u00111!qN\rC\u0002u\u00022A\u000fE\u0011\t\u0019\u0011y,\u0007b\u0001{A\u0019!\b#\n\u0005\r\rU\u0011D1\u0001>!\rQ\u0004\u0012\u0006\u0003\u0007\u0007cJ\"\u0019A\u001f\u0011\u0007iBi\u0003\u0002\u0004\u0004Tf\u0011\r!\u0010\t\u0004u!EBA\u0002C\u001e3\t\u0007Q\bE\u0002;\u0011k!a\u0001\"+\u001a\u0005\u0004i\u0004c\u0001\u001e\t:\u00111QQD\rC\u0002u\u00022A\u000fE\u001f\t\u0019)9*\u0007b\u0001{A\u0019!\b#\u0011\u0005\r\u0019]\u0011D1\u0001>!\rQ\u0004R\t\u0003\u0007\r;K\"\u0019A\u001f\u0011\u0007iBI\u0005\u0002\u0004\b*e\u0011\r!\u0010\t\u0004u!5CABD^3\t\u0007Q\bE\u0002;\u0011#\"a\u0001c\u0015\u001a\u0005\u0004i$!\u0001,\u0011\u0007iB9\u0006B\u0003T3\t\u0007Q\b\u0005\u0004#+\"m\u0003R\u000b\t\u00071\u001e<Y\u0010#\u0018\u0011\ra;wq E0!\u0019Av\rc\u0001\tbA1\u0001l\u001aE\u0004\u0011G\u0002b\u0001W4\t\f!\u0015\u0004C\u0002-h\u0011\u001fA9\u0007\u0005\u0004YO\"M\u0001\u0012\u000e\t\u00071\u001eD9\u0002c\u001b\u0011\ra;\u00072\u0004E7!\u0019Av\rc\b\tpA1\u0001l\u001aE\u0012\u0011c\u0002b\u0001W4\t(!M\u0004C\u0002-h\u0011WA)\b\u0005\u0004YO\"=\u0002r\u000f\t\u00071\u001eD\u0019\u0004#\u001f\u0011\ra;\u0007r\u0007E>!\u0019Av\rc\u000f\t~A1\u0001l\u001aE \u0011\u007f\u0002b\u0001W4\tD!\u0005\u0005C\u0002-h\u0011\u000fB\u0019\t\u0005\u0004YO\"-\u0003R\u0011\t\u00061\u001eDye\u0016"
    )
  ScalaInlineInfo: length = 0xEF (unknown attribute)
   01 00 00 2F 00 CE 00 46 01 00 3C 00 3D 01 00 3F
   00 40 00 00 4A 00 3D 01 00 4B 00 40 00 00 80 00
   3D 01 00 81 00 40 00 00 86 00 3D 01 00 87 00 40
   00 00 8C 00 3D 01 00 8D 00 40 00 00 92 00 3D 01
   00 93 00 40 00 00 98 00 3D 01 00 99 00 40 00 00
   9E 00 3D 01 00 9F 00 40 00 00 A4 00 3D 01 00 A5
   00 40 00 00 AA 00 3D 01 00 AB 00 40 00 00 B0 00
   3D 01 00 B1 00 40 00 00 B6 00 3D 01 00 B7 00 40
   00 00 50 00 3D 01 00 51 00 40 00 00 BC 00 3D 01
   00 BD 00 40 00 00 C2 00 3D 01 00 C3 00 40 00 00
   C8 00 3D 01 00 C9 00 40 00 00 56 00 3D 01 00 57
   00 40 00 00 5C 00 3D 01 00 5D 00 40 00 00 62 00
   3D 01 00 63 00 40 00 00 68 00 3D 01 00 69 00 40
   00 00 6E 00 3D 01 00 6F 00 40 00 00 74 00 3D 01
   00 75 00 40 00 00 7A 00 3D 01 00 7B 00 40 00
  ScalaSig: length = 0x3 (unknown attribute)
   05 02 00
