Classfile /Users/mw/Projects/slang-braindump/.jar/jar8/assemble/slang-braindump/assemble/content/shapeless/ops/function$FnFromProduct$.class
  Last modified May 29, 2022; size 19085 bytes
  SHA-256 checksum 220f891e9193e734c82058c872b89a24cf6b9c51866d24eba53bd01e94610ee2
  Compiled from "functions.scala"
public class shapeless.ops.function$FnFromProduct$ implements shapeless.ops.FnFromProductInstances,java.io.Serializable
  minor version: 0
  major version: 52
  flags: (0x0021) ACC_PUBLIC, ACC_SUPER
  this_class: #2                          // shapeless/ops/function$FnFromProduct$
  super_class: #4                         // java/lang/Object
  interfaces: 2, fields: 1, methods: 27, attributes: 4
Constant pool:
    #1 = Utf8               shapeless/ops/function$FnFromProduct$
    #2 = Class              #1            // shapeless/ops/function$FnFromProduct$
    #3 = Utf8               java/lang/Object
    #4 = Class              #3            // java/lang/Object
    #5 = Utf8               shapeless/ops/FnFromProductInstances
    #6 = Class              #5            // shapeless/ops/FnFromProductInstances
    #7 = Utf8               java/io/Serializable
    #8 = Class              #7            // java/io/Serializable
    #9 = Utf8               functions.scala
   #10 = Utf8               shapeless/ops/function$FnFromProduct
   #11 = Class              #10           // shapeless/ops/function$FnFromProduct
   #12 = Utf8               shapeless/ops/function
   #13 = Class              #12           // shapeless/ops/function
   #14 = Utf8               FnFromProduct
   #15 = Utf8               FnFromProduct$
   #16 = Utf8               MODULE$
   #17 = Utf8               Lshapeless/ops/function$FnFromProduct$;
   #18 = Utf8               <clinit>
   #19 = Utf8               ()V
   #20 = Utf8               <init>
   #21 = NameAndType        #20:#19       // "<init>":()V
   #22 = Methodref          #2.#21        // shapeless/ops/function$FnFromProduct$."<init>":()V
   #23 = NameAndType        #16:#17       // MODULE$:Lshapeless/ops/function$FnFromProduct$;
   #24 = Fieldref           #2.#23        // shapeless/ops/function$FnFromProduct$.MODULE$:Lshapeless/ops/function$FnFromProduct$;
   #25 = Utf8               $init$
   #26 = Utf8               (Lshapeless/ops/FnFromProductInstances;)V
   #27 = NameAndType        #25:#26       // $init$:(Lshapeless/ops/FnFromProductInstances;)V
   #28 = InterfaceMethodref #6.#27        // shapeless/ops/FnFromProductInstances.$init$:(Lshapeless/ops/FnFromProductInstances;)V
   #29 = Utf8               fnFromProduct0
   #30 = Utf8               ()Lshapeless/ops/function$FnFromProduct;
   #31 = Utf8               <Res:Ljava/lang/Object;>()Lshapeless/ops/function$FnFromProduct<Lscala/Function1<Lshapeless/HNil;TRes;>;>;
   #32 = Utf8               fnFromProduct0$
   #33 = Utf8               (Lshapeless/ops/FnFromProductInstances;)Lshapeless/ops/function$FnFromProduct;
   #34 = NameAndType        #32:#33       // fnFromProduct0$:(Lshapeless/ops/FnFromProductInstances;)Lshapeless/ops/function$FnFromProduct;
   #35 = InterfaceMethodref #6.#34        // shapeless/ops/FnFromProductInstances.fnFromProduct0$:(Lshapeless/ops/FnFromProductInstances;)Lshapeless/ops/function$FnFromProduct;
   #36 = Utf8               this
   #37 = Utf8               fnFromProduct1
   #38 = Utf8               <A:Ljava/lang/Object;Res:Ljava/lang/Object;>()Lshapeless/ops/function$FnFromProduct<Lscala/Function1<Lshapeless/$colon$colon<TA;Lshapeless/HNil;>;TRes;>;>;
   #39 = Utf8               fnFromProduct1$
   #40 = NameAndType        #39:#33       // fnFromProduct1$:(Lshapeless/ops/FnFromProductInstances;)Lshapeless/ops/function$FnFromProduct;
   #41 = InterfaceMethodref #6.#40        // shapeless/ops/FnFromProductInstances.fnFromProduct1$:(Lshapeless/ops/FnFromProductInstances;)Lshapeless/ops/function$FnFromProduct;
   #42 = Utf8               fnFromProduct2
   #43 = Utf8               <A:Ljava/lang/Object;B:Ljava/lang/Object;Res:Ljava/lang/Object;>()Lshapeless/ops/function$FnFromProduct<Lscala/Function1<Lshapeless/$colon$colon<TA;Lshapeless/$colon$colon<TB;Lshapeless/HNil;>;>;TRes;>;>;
   #44 = Utf8               fnFromProduct2$
   #45 = NameAndType        #44:#33       // fnFromProduct2$:(Lshapeless/ops/FnFromProductInstances;)Lshapeless/ops/function$FnFromProduct;
   #46 = InterfaceMethodref #6.#45        // shapeless/ops/FnFromProductInstances.fnFromProduct2$:(Lshapeless/ops/FnFromProductInstances;)Lshapeless/ops/function$FnFromProduct;
   #47 = Utf8               fnFromProduct3
   #48 = Utf8               <A:Ljava/lang/Object;B:Ljava/lang/Object;C:Ljava/lang/Object;Res:Ljava/lang/Object;>()Lshapeless/ops/function$FnFromProduct<Lscala/Function1<Lshapeless/$colon$colon<TA;Lshapeless/$colon$colon<TB;Lshapeless/$colon$colon<TC;Lshapeless/HNil;>;>;>;TRes;>;>;
   #49 = Utf8               fnFromProduct3$
   #50 = NameAndType        #49:#33       // fnFromProduct3$:(Lshapeless/ops/FnFromProductInstances;)Lshapeless/ops/function$FnFromProduct;
   #51 = InterfaceMethodref #6.#50        // shapeless/ops/FnFromProductInstances.fnFromProduct3$:(Lshapeless/ops/FnFromProductInstances;)Lshapeless/ops/function$FnFromProduct;
   #52 = Utf8               fnFromProduct4
   #53 = Utf8               <A:Ljava/lang/Object;B:Ljava/lang/Object;C:Ljava/lang/Object;D:Ljava/lang/Object;Res:Ljava/lang/Object;>()Lshapeless/ops/function$FnFromProduct<Lscala/Function1<Lshapeless/$colon$colon<TA;Lshapeless/$colon$colon<TB;Lshapeless/$colon$colon<TC;Lshapeless/$colon$colon<TD;Lshapeless/HNil;>;>;>;>;TRes;>;>;
   #54 = Utf8               fnFromProduct4$
   #55 = NameAndType        #54:#33       // fnFromProduct4$:(Lshapeless/ops/FnFromProductInstances;)Lshapeless/ops/function$FnFromProduct;
   #56 = InterfaceMethodref #6.#55        // shapeless/ops/FnFromProductInstances.fnFromProduct4$:(Lshapeless/ops/FnFromProductInstances;)Lshapeless/ops/function$FnFromProduct;
   #57 = Utf8               fnFromProduct5
   #58 = Utf8               <A:Ljava/lang/Object;B:Ljava/lang/Object;C:Ljava/lang/Object;D:Ljava/lang/Object;E:Ljava/lang/Object;Res:Ljava/lang/Object;>()Lshapeless/ops/function$FnFromProduct<Lscala/Function1<Lshapeless/$colon$colon<TA;Lshapeless/$colon$colon<TB;Lshapeless/$colon$colon<TC;Lshapeless/$colon$colon<TD;Lshapeless/$colon$colon<TE;Lshapeless/HNil;>;>;>;>;>;TRes;>;>;
   #59 = Utf8               fnFromProduct5$
   #60 = NameAndType        #59:#33       // fnFromProduct5$:(Lshapeless/ops/FnFromProductInstances;)Lshapeless/ops/function$FnFromProduct;
   #61 = InterfaceMethodref #6.#60        // shapeless/ops/FnFromProductInstances.fnFromProduct5$:(Lshapeless/ops/FnFromProductInstances;)Lshapeless/ops/function$FnFromProduct;
   #62 = Utf8               fnFromProduct6
   #63 = Utf8               <A:Ljava/lang/Object;B:Ljava/lang/Object;C:Ljava/lang/Object;D:Ljava/lang/Object;E:Ljava/lang/Object;F:Ljava/lang/Object;Res:Ljava/lang/Object;>()Lshapeless/ops/function$FnFromProduct<Lscala/Function1<Lshapeless/$colon$colon<TA;Lshapeless/$colon$colon<TB;Lshapeless/$colon$colon<TC;Lshapeless/$colon$colon<TD;Lshapeless/$colon$colon<TE;Lshapeless/$colon$colon<TF;Lshapeless/HNil;>;>;>;>;>;>;TRes;>;>;
   #64 = Utf8               fnFromProduct6$
   #65 = NameAndType        #64:#33       // fnFromProduct6$:(Lshapeless/ops/FnFromProductInstances;)Lshapeless/ops/function$FnFromProduct;
   #66 = InterfaceMethodref #6.#65        // shapeless/ops/FnFromProductInstances.fnFromProduct6$:(Lshapeless/ops/FnFromProductInstances;)Lshapeless/ops/function$FnFromProduct;
   #67 = Utf8               fnFromProduct7
   #68 = Utf8               <A:Ljava/lang/Object;B:Ljava/lang/Object;C:Ljava/lang/Object;D:Ljava/lang/Object;E:Ljava/lang/Object;F:Ljava/lang/Object;G:Ljava/lang/Object;Res:Ljava/lang/Object;>()Lshapeless/ops/function$FnFromProduct<Lscala/Function1<Lshapeless/$colon$colon<TA;Lshapeless/$colon$colon<TB;Lshapeless/$colon$colon<TC;Lshapeless/$colon$colon<TD;Lshapeless/$colon$colon<TE;Lshapeless/$colon$colon<TF;Lshapeless/$colon$colon<TG;Lshapeless/HNil;>;>;>;>;>;>;>;TRes;>;>;
   #69 = Utf8               fnFromProduct7$
   #70 = NameAndType        #69:#33       // fnFromProduct7$:(Lshapeless/ops/FnFromProductInstances;)Lshapeless/ops/function$FnFromProduct;
   #71 = InterfaceMethodref #6.#70        // shapeless/ops/FnFromProductInstances.fnFromProduct7$:(Lshapeless/ops/FnFromProductInstances;)Lshapeless/ops/function$FnFromProduct;
   #72 = Utf8               fnFromProduct8
   #73 = Utf8               <A:Ljava/lang/Object;B:Ljava/lang/Object;C:Ljava/lang/Object;D:Ljava/lang/Object;E:Ljava/lang/Object;F:Ljava/lang/Object;G:Ljava/lang/Object;H:Ljava/lang/Object;Res:Ljava/lang/Object;>()Lshapeless/ops/function$FnFromProduct<Lscala/Function1<Lshapeless/$colon$colon<TA;Lshapeless/$colon$colon<TB;Lshapeless/$colon$colon<TC;Lshapeless/$colon$colon<TD;Lshapeless/$colon$colon<TE;Lshapeless/$colon$colon<TF;Lshapeless/$colon$colon<TG;Lshapeless/$colon$colon<TH;Lshapeless/HNil;>;>;>;>;>;>;>;>;TRes;>;>;
   #74 = Utf8               fnFromProduct8$
   #75 = NameAndType        #74:#33       // fnFromProduct8$:(Lshapeless/ops/FnFromProductInstances;)Lshapeless/ops/function$FnFromProduct;
   #76 = InterfaceMethodref #6.#75        // shapeless/ops/FnFromProductInstances.fnFromProduct8$:(Lshapeless/ops/FnFromProductInstances;)Lshapeless/ops/function$FnFromProduct;
   #77 = Utf8               fnFromProduct9
   #78 = Utf8               <A:Ljava/lang/Object;B:Ljava/lang/Object;C:Ljava/lang/Object;D:Ljava/lang/Object;E:Ljava/lang/Object;F:Ljava/lang/Object;G:Ljava/lang/Object;H:Ljava/lang/Object;I:Ljava/lang/Object;Res:Ljava/lang/Object;>()Lshapeless/ops/function$FnFromProduct<Lscala/Function1<Lshapeless/$colon$colon<TA;Lshapeless/$colon$colon<TB;Lshapeless/$colon$colon<TC;Lshapeless/$colon$colon<TD;Lshapeless/$colon$colon<TE;Lshapeless/$colon$colon<TF;Lshapeless/$colon$colon<TG;Lshapeless/$colon$colon<TH;Lshapeless/$colon$colon<TI;Lshapeless/HNil;>;>;>;>;>;>;>;>;>;TRes;>;>;
   #79 = Utf8               fnFromProduct9$
   #80 = NameAndType        #79:#33       // fnFromProduct9$:(Lshapeless/ops/FnFromProductInstances;)Lshapeless/ops/function$FnFromProduct;
   #81 = InterfaceMethodref #6.#80        // shapeless/ops/FnFromProductInstances.fnFromProduct9$:(Lshapeless/ops/FnFromProductInstances;)Lshapeless/ops/function$FnFromProduct;
   #82 = Utf8               fnFromProduct10
   #83 = Utf8               <A:Ljava/lang/Object;B:Ljava/lang/Object;C:Ljava/lang/Object;D:Ljava/lang/Object;E:Ljava/lang/Object;F:Ljava/lang/Object;G:Ljava/lang/Object;H:Ljava/lang/Object;I:Ljava/lang/Object;J:Ljava/lang/Object;Res:Ljava/lang/Object;>()Lshapeless/ops/function$FnFromProduct<Lscala/Function1<Lshapeless/$colon$colon<TA;Lshapeless/$colon$colon<TB;Lshapeless/$colon$colon<TC;Lshapeless/$colon$colon<TD;Lshapeless/$colon$colon<TE;Lshapeless/$colon$colon<TF;Lshapeless/$colon$colon<TG;Lshapeless/$colon$colon<TH;Lshapeless/$colon$colon<TI;Lshapeless/$colon$colon<TJ;Lshapeless/HNil;>;>;>;>;>;>;>;>;>;>;TRes;>;>;
   #84 = Utf8               fnFromProduct10$
   #85 = NameAndType        #84:#33       // fnFromProduct10$:(Lshapeless/ops/FnFromProductInstances;)Lshapeless/ops/function$FnFromProduct;
   #86 = InterfaceMethodref #6.#85        // shapeless/ops/FnFromProductInstances.fnFromProduct10$:(Lshapeless/ops/FnFromProductInstances;)Lshapeless/ops/function$FnFromProduct;
   #87 = Utf8               fnFromProduct11
   #88 = Utf8               <A:Ljava/lang/Object;B:Ljava/lang/Object;C:Ljava/lang/Object;D:Ljava/lang/Object;E:Ljava/lang/Object;F:Ljava/lang/Object;G:Ljava/lang/Object;H:Ljava/lang/Object;I:Ljava/lang/Object;J:Ljava/lang/Object;K:Ljava/lang/Object;Res:Ljava/lang/Object;>()Lshapeless/ops/function$FnFromProduct<Lscala/Function1<Lshapeless/$colon$colon<TA;Lshapeless/$colon$colon<TB;Lshapeless/$colon$colon<TC;Lshapeless/$colon$colon<TD;Lshapeless/$colon$colon<TE;Lshapeless/$colon$colon<TF;Lshapeless/$colon$colon<TG;Lshapeless/$colon$colon<TH;Lshapeless/$colon$colon<TI;Lshapeless/$colon$colon<TJ;Lshapeless/$colon$colon<TK;Lshapeless/HNil;>;>;>;>;>;>;>;>;>;>;>;TRes;>;>;
   #89 = Utf8               fnFromProduct11$
   #90 = NameAndType        #89:#33       // fnFromProduct11$:(Lshapeless/ops/FnFromProductInstances;)Lshapeless/ops/function$FnFromProduct;
   #91 = InterfaceMethodref #6.#90        // shapeless/ops/FnFromProductInstances.fnFromProduct11$:(Lshapeless/ops/FnFromProductInstances;)Lshapeless/ops/function$FnFromProduct;
   #92 = Utf8               fnFromProduct12
   #93 = Utf8               <A:Ljava/lang/Object;B:Ljava/lang/Object;C:Ljava/lang/Object;D:Ljava/lang/Object;E:Ljava/lang/Object;F:Ljava/lang/Object;G:Ljava/lang/Object;H:Ljava/lang/Object;I:Ljava/lang/Object;J:Ljava/lang/Object;K:Ljava/lang/Object;L:Ljava/lang/Object;Res:Ljava/lang/Object;>()Lshapeless/ops/function$FnFromProduct<Lscala/Function1<Lshapeless/$colon$colon<TA;Lshapeless/$colon$colon<TB;Lshapeless/$colon$colon<TC;Lshapeless/$colon$colon<TD;Lshapeless/$colon$colon<TE;Lshapeless/$colon$colon<TF;Lshapeless/$colon$colon<TG;Lshapeless/$colon$colon<TH;Lshapeless/$colon$colon<TI;Lshapeless/$colon$colon<TJ;Lshapeless/$colon$colon<TK;Lshapeless/$colon$colon<TL;Lshapeless/HNil;>;>;>;>;>;>;>;>;>;>;>;>;TRes;>;>;
   #94 = Utf8               fnFromProduct12$
   #95 = NameAndType        #94:#33       // fnFromProduct12$:(Lshapeless/ops/FnFromProductInstances;)Lshapeless/ops/function$FnFromProduct;
   #96 = InterfaceMethodref #6.#95        // shapeless/ops/FnFromProductInstances.fnFromProduct12$:(Lshapeless/ops/FnFromProductInstances;)Lshapeless/ops/function$FnFromProduct;
   #97 = Utf8               fnFromProduct13
   #98 = Utf8               <A:Ljava/lang/Object;B:Ljava/lang/Object;C:Ljava/lang/Object;D:Ljava/lang/Object;E:Ljava/lang/Object;F:Ljava/lang/Object;G:Ljava/lang/Object;H:Ljava/lang/Object;I:Ljava/lang/Object;J:Ljava/lang/Object;K:Ljava/lang/Object;L:Ljava/lang/Object;M:Ljava/lang/Object;Res:Ljava/lang/Object;>()Lshapeless/ops/function$FnFromProduct<Lscala/Function1<Lshapeless/$colon$colon<TA;Lshapeless/$colon$colon<TB;Lshapeless/$colon$colon<TC;Lshapeless/$colon$colon<TD;Lshapeless/$colon$colon<TE;Lshapeless/$colon$colon<TF;Lshapeless/$colon$colon<TG;Lshapeless/$colon$colon<TH;Lshapeless/$colon$colon<TI;Lshapeless/$colon$colon<TJ;Lshapeless/$colon$colon<TK;Lshapeless/$colon$colon<TL;Lshapeless/$colon$colon<TM;Lshapeless/HNil;>;>;>;>;>;>;>;>;>;>;>;>;>;TRes;>;>;
   #99 = Utf8               fnFromProduct13$
  #100 = NameAndType        #99:#33       // fnFromProduct13$:(Lshapeless/ops/FnFromProductInstances;)Lshapeless/ops/function$FnFromProduct;
  #101 = InterfaceMethodref #6.#100       // shapeless/ops/FnFromProductInstances.fnFromProduct13$:(Lshapeless/ops/FnFromProductInstances;)Lshapeless/ops/function$FnFromProduct;
  #102 = Utf8               fnFromProduct14
  #103 = Utf8               <A:Ljava/lang/Object;B:Ljava/lang/Object;C:Ljava/lang/Object;D:Ljava/lang/Object;E:Ljava/lang/Object;F:Ljava/lang/Object;G:Ljava/lang/Object;H:Ljava/lang/Object;I:Ljava/lang/Object;J:Ljava/lang/Object;K:Ljava/lang/Object;L:Ljava/lang/Object;M:Ljava/lang/Object;N:Ljava/lang/Object;Res:Ljava/lang/Object;>()Lshapeless/ops/function$FnFromProduct<Lscala/Function1<Lshapeless/$colon$colon<TA;Lshapeless/$colon$colon<TB;Lshapeless/$colon$colon<TC;Lshapeless/$colon$colon<TD;Lshapeless/$colon$colon<TE;Lshapeless/$colon$colon<TF;Lshapeless/$colon$colon<TG;Lshapeless/$colon$colon<TH;Lshapeless/$colon$colon<TI;Lshapeless/$colon$colon<TJ;Lshapeless/$colon$colon<TK;Lshapeless/$colon$colon<TL;Lshapeless/$colon$colon<TM;Lshapeless/$colon$colon<TN;Lshapeless/HNil;>;>;>;>;>;>;>;>;>;>;>;>;>;>;TRes;>;>;
  #104 = Utf8               fnFromProduct14$
  #105 = NameAndType        #104:#33      // fnFromProduct14$:(Lshapeless/ops/FnFromProductInstances;)Lshapeless/ops/function$FnFromProduct;
  #106 = InterfaceMethodref #6.#105       // shapeless/ops/FnFromProductInstances.fnFromProduct14$:(Lshapeless/ops/FnFromProductInstances;)Lshapeless/ops/function$FnFromProduct;
  #107 = Utf8               fnFromProduct15
  #108 = Utf8               <A:Ljava/lang/Object;B:Ljava/lang/Object;C:Ljava/lang/Object;D:Ljava/lang/Object;E:Ljava/lang/Object;F:Ljava/lang/Object;G:Ljava/lang/Object;H:Ljava/lang/Object;I:Ljava/lang/Object;J:Ljava/lang/Object;K:Ljava/lang/Object;L:Ljava/lang/Object;M:Ljava/lang/Object;N:Ljava/lang/Object;O:Ljava/lang/Object;Res:Ljava/lang/Object;>()Lshapeless/ops/function$FnFromProduct<Lscala/Function1<Lshapeless/$colon$colon<TA;Lshapeless/$colon$colon<TB;Lshapeless/$colon$colon<TC;Lshapeless/$colon$colon<TD;Lshapeless/$colon$colon<TE;Lshapeless/$colon$colon<TF;Lshapeless/$colon$colon<TG;Lshapeless/$colon$colon<TH;Lshapeless/$colon$colon<TI;Lshapeless/$colon$colon<TJ;Lshapeless/$colon$colon<TK;Lshapeless/$colon$colon<TL;Lshapeless/$colon$colon<TM;Lshapeless/$colon$colon<TN;Lshapeless/$colon$colon<TO;Lshapeless/HNil;>;>;>;>;>;>;>;>;>;>;>;>;>;>;>;TRes;>;>;
  #109 = Utf8               fnFromProduct15$
  #110 = NameAndType        #109:#33      // fnFromProduct15$:(Lshapeless/ops/FnFromProductInstances;)Lshapeless/ops/function$FnFromProduct;
  #111 = InterfaceMethodref #6.#110       // shapeless/ops/FnFromProductInstances.fnFromProduct15$:(Lshapeless/ops/FnFromProductInstances;)Lshapeless/ops/function$FnFromProduct;
  #112 = Utf8               fnFromProduct16
  #113 = Utf8               <A:Ljava/lang/Object;B:Ljava/lang/Object;C:Ljava/lang/Object;D:Ljava/lang/Object;E:Ljava/lang/Object;F:Ljava/lang/Object;G:Ljava/lang/Object;H:Ljava/lang/Object;I:Ljava/lang/Object;J:Ljava/lang/Object;K:Ljava/lang/Object;L:Ljava/lang/Object;M:Ljava/lang/Object;N:Ljava/lang/Object;O:Ljava/lang/Object;P:Ljava/lang/Object;Res:Ljava/lang/Object;>()Lshapeless/ops/function$FnFromProduct<Lscala/Function1<Lshapeless/$colon$colon<TA;Lshapeless/$colon$colon<TB;Lshapeless/$colon$colon<TC;Lshapeless/$colon$colon<TD;Lshapeless/$colon$colon<TE;Lshapeless/$colon$colon<TF;Lshapeless/$colon$colon<TG;Lshapeless/$colon$colon<TH;Lshapeless/$colon$colon<TI;Lshapeless/$colon$colon<TJ;Lshapeless/$colon$colon<TK;Lshapeless/$colon$colon<TL;Lshapeless/$colon$colon<TM;Lshapeless/$colon$colon<TN;Lshapeless/$colon$colon<TO;Lshapeless/$colon$colon<TP;Lshapeless/HNil;>;>;>;>;>;>;>;>;>;>;>;>;>;>;>;>;TRes;>;>;
  #114 = Utf8               fnFromProduct16$
  #115 = NameAndType        #114:#33      // fnFromProduct16$:(Lshapeless/ops/FnFromProductInstances;)Lshapeless/ops/function$FnFromProduct;
  #116 = InterfaceMethodref #6.#115       // shapeless/ops/FnFromProductInstances.fnFromProduct16$:(Lshapeless/ops/FnFromProductInstances;)Lshapeless/ops/function$FnFromProduct;
  #117 = Utf8               fnFromProduct17
  #118 = Utf8               <A:Ljava/lang/Object;B:Ljava/lang/Object;C:Ljava/lang/Object;D:Ljava/lang/Object;E:Ljava/lang/Object;F:Ljava/lang/Object;G:Ljava/lang/Object;H:Ljava/lang/Object;I:Ljava/lang/Object;J:Ljava/lang/Object;K:Ljava/lang/Object;L:Ljava/lang/Object;M:Ljava/lang/Object;N:Ljava/lang/Object;O:Ljava/lang/Object;P:Ljava/lang/Object;Q:Ljava/lang/Object;Res:Ljava/lang/Object;>()Lshapeless/ops/function$FnFromProduct<Lscala/Function1<Lshapeless/$colon$colon<TA;Lshapeless/$colon$colon<TB;Lshapeless/$colon$colon<TC;Lshapeless/$colon$colon<TD;Lshapeless/$colon$colon<TE;Lshapeless/$colon$colon<TF;Lshapeless/$colon$colon<TG;Lshapeless/$colon$colon<TH;Lshapeless/$colon$colon<TI;Lshapeless/$colon$colon<TJ;Lshapeless/$colon$colon<TK;Lshapeless/$colon$colon<TL;Lshapeless/$colon$colon<TM;Lshapeless/$colon$colon<TN;Lshapeless/$colon$colon<TO;Lshapeless/$colon$colon<TP;Lshapeless/$colon$colon<TQ;Lshapeless/HNil;>;>;>;>;>;>;>;>;>;>;>;>;>;>;>;>;>;TRes;>;>;
  #119 = Utf8               fnFromProduct17$
  #120 = NameAndType        #119:#33      // fnFromProduct17$:(Lshapeless/ops/FnFromProductInstances;)Lshapeless/ops/function$FnFromProduct;
  #121 = InterfaceMethodref #6.#120       // shapeless/ops/FnFromProductInstances.fnFromProduct17$:(Lshapeless/ops/FnFromProductInstances;)Lshapeless/ops/function$FnFromProduct;
  #122 = Utf8               fnFromProduct18
  #123 = Utf8               <A:Ljava/lang/Object;B:Ljava/lang/Object;C:Ljava/lang/Object;D:Ljava/lang/Object;E:Ljava/lang/Object;F:Ljava/lang/Object;G:Ljava/lang/Object;H:Ljava/lang/Object;I:Ljava/lang/Object;J:Ljava/lang/Object;K:Ljava/lang/Object;L:Ljava/lang/Object;M:Ljava/lang/Object;N:Ljava/lang/Object;O:Ljava/lang/Object;P:Ljava/lang/Object;Q:Ljava/lang/Object;R:Ljava/lang/Object;Res:Ljava/lang/Object;>()Lshapeless/ops/function$FnFromProduct<Lscala/Function1<Lshapeless/$colon$colon<TA;Lshapeless/$colon$colon<TB;Lshapeless/$colon$colon<TC;Lshapeless/$colon$colon<TD;Lshapeless/$colon$colon<TE;Lshapeless/$colon$colon<TF;Lshapeless/$colon$colon<TG;Lshapeless/$colon$colon<TH;Lshapeless/$colon$colon<TI;Lshapeless/$colon$colon<TJ;Lshapeless/$colon$colon<TK;Lshapeless/$colon$colon<TL;Lshapeless/$colon$colon<TM;Lshapeless/$colon$colon<TN;Lshapeless/$colon$colon<TO;Lshapeless/$colon$colon<TP;Lshapeless/$colon$colon<TQ;Lshapeless/$colon$colon<TR;Lshapeless/HNil;>;>;>;>;>;>;>;>;>;>;>;>;>;>;>;>;>;>;TRes;>;>;
  #124 = Utf8               fnFromProduct18$
  #125 = NameAndType        #124:#33      // fnFromProduct18$:(Lshapeless/ops/FnFromProductInstances;)Lshapeless/ops/function$FnFromProduct;
  #126 = InterfaceMethodref #6.#125       // shapeless/ops/FnFromProductInstances.fnFromProduct18$:(Lshapeless/ops/FnFromProductInstances;)Lshapeless/ops/function$FnFromProduct;
  #127 = Utf8               fnFromProduct19
  #128 = Utf8               <A:Ljava/lang/Object;B:Ljava/lang/Object;C:Ljava/lang/Object;D:Ljava/lang/Object;E:Ljava/lang/Object;F:Ljava/lang/Object;G:Ljava/lang/Object;H:Ljava/lang/Object;I:Ljava/lang/Object;J:Ljava/lang/Object;K:Ljava/lang/Object;L:Ljava/lang/Object;M:Ljava/lang/Object;N:Ljava/lang/Object;O:Ljava/lang/Object;P:Ljava/lang/Object;Q:Ljava/lang/Object;R:Ljava/lang/Object;S:Ljava/lang/Object;Res:Ljava/lang/Object;>()Lshapeless/ops/function$FnFromProduct<Lscala/Function1<Lshapeless/$colon$colon<TA;Lshapeless/$colon$colon<TB;Lshapeless/$colon$colon<TC;Lshapeless/$colon$colon<TD;Lshapeless/$colon$colon<TE;Lshapeless/$colon$colon<TF;Lshapeless/$colon$colon<TG;Lshapeless/$colon$colon<TH;Lshapeless/$colon$colon<TI;Lshapeless/$colon$colon<TJ;Lshapeless/$colon$colon<TK;Lshapeless/$colon$colon<TL;Lshapeless/$colon$colon<TM;Lshapeless/$colon$colon<TN;Lshapeless/$colon$colon<TO;Lshapeless/$colon$colon<TP;Lshapeless/$colon$colon<TQ;Lshapeless/$colon$colon<TR;Lshapeless/$colon$colon<TS;Lshapeless/HNil;>;>;>;>;>;>;>;>;>;>;>;>;>;>;>;>;>;>;>;TRes;>;>;
  #129 = Utf8               fnFromProduct19$
  #130 = NameAndType        #129:#33      // fnFromProduct19$:(Lshapeless/ops/FnFromProductInstances;)Lshapeless/ops/function$FnFromProduct;
  #131 = InterfaceMethodref #6.#130       // shapeless/ops/FnFromProductInstances.fnFromProduct19$:(Lshapeless/ops/FnFromProductInstances;)Lshapeless/ops/function$FnFromProduct;
  #132 = Utf8               fnFromProduct20
  #133 = Utf8               <A:Ljava/lang/Object;B:Ljava/lang/Object;C:Ljava/lang/Object;D:Ljava/lang/Object;E:Ljava/lang/Object;F:Ljava/lang/Object;G:Ljava/lang/Object;H:Ljava/lang/Object;I:Ljava/lang/Object;J:Ljava/lang/Object;K:Ljava/lang/Object;L:Ljava/lang/Object;M:Ljava/lang/Object;N:Ljava/lang/Object;O:Ljava/lang/Object;P:Ljava/lang/Object;Q:Ljava/lang/Object;R:Ljava/lang/Object;S:Ljava/lang/Object;T:Ljava/lang/Object;Res:Ljava/lang/Object;>()Lshapeless/ops/function$FnFromProduct<Lscala/Function1<Lshapeless/$colon$colon<TA;Lshapeless/$colon$colon<TB;Lshapeless/$colon$colon<TC;Lshapeless/$colon$colon<TD;Lshapeless/$colon$colon<TE;Lshapeless/$colon$colon<TF;Lshapeless/$colon$colon<TG;Lshapeless/$colon$colon<TH;Lshapeless/$colon$colon<TI;Lshapeless/$colon$colon<TJ;Lshapeless/$colon$colon<TK;Lshapeless/$colon$colon<TL;Lshapeless/$colon$colon<TM;Lshapeless/$colon$colon<TN;Lshapeless/$colon$colon<TO;Lshapeless/$colon$colon<TP;Lshapeless/$colon$colon<TQ;Lshapeless/$colon$colon<TR;Lshapeless/$colon$colon<TS;Lshapeless/$colon$colon<TT;Lshapeless/HNil;>;>;>;>;>;>;>;>;>;>;>;>;>;>;>;>;>;>;>;>;TRes;>;>;
  #134 = Utf8               fnFromProduct20$
  #135 = NameAndType        #134:#33      // fnFromProduct20$:(Lshapeless/ops/FnFromProductInstances;)Lshapeless/ops/function$FnFromProduct;
  #136 = InterfaceMethodref #6.#135       // shapeless/ops/FnFromProductInstances.fnFromProduct20$:(Lshapeless/ops/FnFromProductInstances;)Lshapeless/ops/function$FnFromProduct;
  #137 = Utf8               fnFromProduct21
  #138 = Utf8               <A:Ljava/lang/Object;B:Ljava/lang/Object;C:Ljava/lang/Object;D:Ljava/lang/Object;E:Ljava/lang/Object;F:Ljava/lang/Object;G:Ljava/lang/Object;H:Ljava/lang/Object;I:Ljava/lang/Object;J:Ljava/lang/Object;K:Ljava/lang/Object;L:Ljava/lang/Object;M:Ljava/lang/Object;N:Ljava/lang/Object;O:Ljava/lang/Object;P:Ljava/lang/Object;Q:Ljava/lang/Object;R:Ljava/lang/Object;S:Ljava/lang/Object;T:Ljava/lang/Object;U:Ljava/lang/Object;Res:Ljava/lang/Object;>()Lshapeless/ops/function$FnFromProduct<Lscala/Function1<Lshapeless/$colon$colon<TA;Lshapeless/$colon$colon<TB;Lshapeless/$colon$colon<TC;Lshapeless/$colon$colon<TD;Lshapeless/$colon$colon<TE;Lshapeless/$colon$colon<TF;Lshapeless/$colon$colon<TG;Lshapeless/$colon$colon<TH;Lshapeless/$colon$colon<TI;Lshapeless/$colon$colon<TJ;Lshapeless/$colon$colon<TK;Lshapeless/$colon$colon<TL;Lshapeless/$colon$colon<TM;Lshapeless/$colon$colon<TN;Lshapeless/$colon$colon<TO;Lshapeless/$colon$colon<TP;Lshapeless/$colon$colon<TQ;Lshapeless/$colon$colon<TR;Lshapeless/$colon$colon<TS;Lshapeless/$colon$colon<TT;Lshapeless/$colon$colon<TU;Lshapeless/HNil;>;>;>;>;>;>;>;>;>;>;>;>;>;>;>;>;>;>;>;>;>;TRes;>;>;
  #139 = Utf8               fnFromProduct21$
  #140 = NameAndType        #139:#33      // fnFromProduct21$:(Lshapeless/ops/FnFromProductInstances;)Lshapeless/ops/function$FnFromProduct;
  #141 = InterfaceMethodref #6.#140       // shapeless/ops/FnFromProductInstances.fnFromProduct21$:(Lshapeless/ops/FnFromProductInstances;)Lshapeless/ops/function$FnFromProduct;
  #142 = Utf8               fnFromProduct22
  #143 = Utf8               <A:Ljava/lang/Object;B:Ljava/lang/Object;C:Ljava/lang/Object;D:Ljava/lang/Object;E:Ljava/lang/Object;F:Ljava/lang/Object;G:Ljava/lang/Object;H:Ljava/lang/Object;I:Ljava/lang/Object;J:Ljava/lang/Object;K:Ljava/lang/Object;L:Ljava/lang/Object;M:Ljava/lang/Object;N:Ljava/lang/Object;O:Ljava/lang/Object;P:Ljava/lang/Object;Q:Ljava/lang/Object;R:Ljava/lang/Object;S:Ljava/lang/Object;T:Ljava/lang/Object;U:Ljava/lang/Object;V:Ljava/lang/Object;Res:Ljava/lang/Object;>()Lshapeless/ops/function$FnFromProduct<Lscala/Function1<Lshapeless/$colon$colon<TA;Lshapeless/$colon$colon<TB;Lshapeless/$colon$colon<TC;Lshapeless/$colon$colon<TD;Lshapeless/$colon$colon<TE;Lshapeless/$colon$colon<TF;Lshapeless/$colon$colon<TG;Lshapeless/$colon$colon<TH;Lshapeless/$colon$colon<TI;Lshapeless/$colon$colon<TJ;Lshapeless/$colon$colon<TK;Lshapeless/$colon$colon<TL;Lshapeless/$colon$colon<TM;Lshapeless/$colon$colon<TN;Lshapeless/$colon$colon<TO;Lshapeless/$colon$colon<TP;Lshapeless/$colon$colon<TQ;Lshapeless/$colon$colon<TR;Lshapeless/$colon$colon<TS;Lshapeless/$colon$colon<TT;Lshapeless/$colon$colon<TU;Lshapeless/$colon$colon<TV;Lshapeless/HNil;>;>;>;>;>;>;>;>;>;>;>;>;>;>;>;>;>;>;>;>;>;>;TRes;>;>;
  #144 = Utf8               fnFromProduct22$
  #145 = NameAndType        #144:#33      // fnFromProduct22$:(Lshapeless/ops/FnFromProductInstances;)Lshapeless/ops/function$FnFromProduct;
  #146 = InterfaceMethodref #6.#145       // shapeless/ops/FnFromProductInstances.fnFromProduct22$:(Lshapeless/ops/FnFromProductInstances;)Lshapeless/ops/function$FnFromProduct;
  #147 = Utf8               apply
  #148 = Utf8               (Lshapeless/ops/function$FnFromProduct;)Lshapeless/ops/function$FnFromProduct;
  #149 = Utf8               <F:Ljava/lang/Object;>(Lshapeless/ops/function$FnFromProduct<TF;>;)Lshapeless/ops/function$FnFromProduct<TF;>;
  #150 = Utf8               fnfromp
  #151 = Utf8               Lshapeless/ops/function$FnFromProduct;
  #152 = Utf8               writeReplace
  #153 = Utf8               ()Ljava/lang/Object;
  #154 = Utf8               scala/runtime/ModuleSerializationProxy
  #155 = Class              #154          // scala/runtime/ModuleSerializationProxy
  #156 = Utf8               (Ljava/lang/Class;)V
  #157 = NameAndType        #20:#156      // "<init>":(Ljava/lang/Class;)V
  #158 = Methodref          #155.#157     // scala/runtime/ModuleSerializationProxy."<init>":(Ljava/lang/Class;)V
  #159 = Methodref          #4.#21        // java/lang/Object."<init>":()V
  #160 = Utf8               Code
  #161 = Utf8               LineNumberTable
  #162 = Utf8               LocalVariableTable
  #163 = Utf8               Signature
  #164 = Utf8               MethodParameters
  #165 = Utf8               InnerClasses
  #166 = Utf8               SourceFile
  #167 = Utf8               ScalaInlineInfo
  #168 = Utf8               Scala
{
  public static final shapeless.ops.function$FnFromProduct$ MODULE$;
    descriptor: Lshapeless/ops/function$FnFromProduct$;
    flags: (0x0019) ACC_PUBLIC, ACC_STATIC, ACC_FINAL

  public static {};
    descriptor: ()V
    flags: (0x0009) ACC_PUBLIC, ACC_STATIC
    Code:
      stack=2, locals=0, args_size=0
         0: new           #2                  // class shapeless/ops/function$FnFromProduct$
         3: dup
         4: invokespecial #22                 // Method "<init>":()V
         7: putstatic     #24                 // Field MODULE$:Lshapeless/ops/function$FnFromProduct$;
        10: getstatic     #24                 // Field MODULE$:Lshapeless/ops/function$FnFromProduct$;
        13: invokestatic  #28                 // InterfaceMethod shapeless/ops/FnFromProductInstances.$init$:(Lshapeless/ops/FnFromProductInstances;)V
        16: return
      LineNumberTable:
        line 43: 0

  public <Res extends java.lang.Object> shapeless.ops.function$FnFromProduct<scala.Function1<shapeless.HNil, Res>> fnFromProduct0();
    descriptor: ()Lshapeless/ops/function$FnFromProduct;
    flags: (0x0001) ACC_PUBLIC
    Code:
      stack=1, locals=1, args_size=1
         0: aload_0
         1: invokestatic  #35                 // InterfaceMethod shapeless/ops/FnFromProductInstances.fnFromProduct0$:(Lshapeless/ops/FnFromProductInstances;)Lshapeless/ops/function$FnFromProduct;
         4: areturn
      LineNumberTable:
        line 43: 0
      LocalVariableTable:
        Start  Length  Slot  Name   Signature
            0       5     0  this   Lshapeless/ops/function$FnFromProduct$;
    Signature: #31                          // <Res:Ljava/lang/Object;>()Lshapeless/ops/function$FnFromProduct<Lscala/Function1<Lshapeless/HNil;TRes;>;>;

  public <A extends java.lang.Object, Res extends java.lang.Object> shapeless.ops.function$FnFromProduct<scala.Function1<shapeless.$colon$colon<A, shapeless.HNil>, Res>> fnFromProduct1();
    descriptor: ()Lshapeless/ops/function$FnFromProduct;
    flags: (0x0001) ACC_PUBLIC
    Code:
      stack=1, locals=1, args_size=1
         0: aload_0
         1: invokestatic  #41                 // InterfaceMethod shapeless/ops/FnFromProductInstances.fnFromProduct1$:(Lshapeless/ops/FnFromProductInstances;)Lshapeless/ops/function$FnFromProduct;
         4: areturn
      LineNumberTable:
        line 43: 0
      LocalVariableTable:
        Start  Length  Slot  Name   Signature
            0       5     0  this   Lshapeless/ops/function$FnFromProduct$;
    Signature: #38                          // <A:Ljava/lang/Object;Res:Ljava/lang/Object;>()Lshapeless/ops/function$FnFromProduct<Lscala/Function1<Lshapeless/$colon$colon<TA;Lshapeless/HNil;>;TRes;>;>;

  public <A extends java.lang.Object, B extends java.lang.Object, Res extends java.lang.Object> shapeless.ops.function$FnFromProduct<scala.Function1<shapeless.$colon$colon<A, shapeless.$colon$colon<B, shapeless.HNil>>, Res>> fnFromProduct2();
    descriptor: ()Lshapeless/ops/function$FnFromProduct;
    flags: (0x0001) ACC_PUBLIC
    Code:
      stack=1, locals=1, args_size=1
         0: aload_0
         1: invokestatic  #46                 // InterfaceMethod shapeless/ops/FnFromProductInstances.fnFromProduct2$:(Lshapeless/ops/FnFromProductInstances;)Lshapeless/ops/function$FnFromProduct;
         4: areturn
      LineNumberTable:
        line 43: 0
      LocalVariableTable:
        Start  Length  Slot  Name   Signature
            0       5     0  this   Lshapeless/ops/function$FnFromProduct$;
    Signature: #43                          // <A:Ljava/lang/Object;B:Ljava/lang/Object;Res:Ljava/lang/Object;>()Lshapeless/ops/function$FnFromProduct<Lscala/Function1<Lshapeless/$colon$colon<TA;Lshapeless/$colon$colon<TB;Lshapeless/HNil;>;>;TRes;>;>;

  public <A extends java.lang.Object, B extends java.lang.Object, C extends java.lang.Object, Res extends java.lang.Object> shapeless.ops.function$FnFromProduct<scala.Function1<shapeless.$colon$colon<A, shapeless.$colon$colon<B, shapeless.$colon$colon<C, shapeless.HNil>>>, Res>> fnFromProduct3();
    descriptor: ()Lshapeless/ops/function$FnFromProduct;
    flags: (0x0001) ACC_PUBLIC
    Code:
      stack=1, locals=1, args_size=1
         0: aload_0
         1: invokestatic  #51                 // InterfaceMethod shapeless/ops/FnFromProductInstances.fnFromProduct3$:(Lshapeless/ops/FnFromProductInstances;)Lshapeless/ops/function$FnFromProduct;
         4: areturn
      LineNumberTable:
        line 43: 0
      LocalVariableTable:
        Start  Length  Slot  Name   Signature
            0       5     0  this   Lshapeless/ops/function$FnFromProduct$;
    Signature: #48                          // <A:Ljava/lang/Object;B:Ljava/lang/Object;C:Ljava/lang/Object;Res:Ljava/lang/Object;>()Lshapeless/ops/function$FnFromProduct<Lscala/Function1<Lshapeless/$colon$colon<TA;Lshapeless/$colon$colon<TB;Lshapeless/$colon$colon<TC;Lshapeless/HNil;>;>;>;TRes;>;>;

  public <A extends java.lang.Object, B extends java.lang.Object, C extends java.lang.Object, D extends java.lang.Object, Res extends java.lang.Object> shapeless.ops.function$FnFromProduct<scala.Function1<shapeless.$colon$colon<A, shapeless.$colon$colon<B, shapeless.$colon$colon<C, shapeless.$colon$colon<D, shapeless.HNil>>>>, Res>> fnFromProduct4();
    descriptor: ()Lshapeless/ops/function$FnFromProduct;
    flags: (0x0001) ACC_PUBLIC
    Code:
      stack=1, locals=1, args_size=1
         0: aload_0
         1: invokestatic  #56                 // InterfaceMethod shapeless/ops/FnFromProductInstances.fnFromProduct4$:(Lshapeless/ops/FnFromProductInstances;)Lshapeless/ops/function$FnFromProduct;
         4: areturn
      LineNumberTable:
        line 43: 0
      LocalVariableTable:
        Start  Length  Slot  Name   Signature
            0       5     0  this   Lshapeless/ops/function$FnFromProduct$;
    Signature: #53                          // <A:Ljava/lang/Object;B:Ljava/lang/Object;C:Ljava/lang/Object;D:Ljava/lang/Object;Res:Ljava/lang/Object;>()Lshapeless/ops/function$FnFromProduct<Lscala/Function1<Lshapeless/$colon$colon<TA;Lshapeless/$colon$colon<TB;Lshapeless/$colon$colon<TC;Lshapeless/$colon$colon<TD;Lshapeless/HNil;>;>;>;>;TRes;>;>;

  public <A extends java.lang.Object, B extends java.lang.Object, C extends java.lang.Object, D extends java.lang.Object, E extends java.lang.Object, Res extends java.lang.Object> shapeless.ops.function$FnFromProduct<scala.Function1<shapeless.$colon$colon<A, shapeless.$colon$colon<B, shapeless.$colon$colon<C, shapeless.$colon$colon<D, shapeless.$colon$colon<E, shapeless.HNil>>>>>, Res>> fnFromProduct5();
    descriptor: ()Lshapeless/ops/function$FnFromProduct;
    flags: (0x0001) ACC_PUBLIC
    Code:
      stack=1, locals=1, args_size=1
         0: aload_0
         1: invokestatic  #61                 // InterfaceMethod shapeless/ops/FnFromProductInstances.fnFromProduct5$:(Lshapeless/ops/FnFromProductInstances;)Lshapeless/ops/function$FnFromProduct;
         4: areturn
      LineNumberTable:
        line 43: 0
      LocalVariableTable:
        Start  Length  Slot  Name   Signature
            0       5     0  this   Lshapeless/ops/function$FnFromProduct$;
    Signature: #58                          // <A:Ljava/lang/Object;B:Ljava/lang/Object;C:Ljava/lang/Object;D:Ljava/lang/Object;E:Ljava/lang/Object;Res:Ljava/lang/Object;>()Lshapeless/ops/function$FnFromProduct<Lscala/Function1<Lshapeless/$colon$colon<TA;Lshapeless/$colon$colon<TB;Lshapeless/$colon$colon<TC;Lshapeless/$colon$colon<TD;Lshapeless/$colon$colon<TE;Lshapeless/HNil;>;>;>;>;>;TRes;>;>;

  public <A extends java.lang.Object, B extends java.lang.Object, C extends java.lang.Object, D extends java.lang.Object, E extends java.lang.Object, F extends java.lang.Object, Res extends java.lang.Object> shapeless.ops.function$FnFromProduct<scala.Function1<shapeless.$colon$colon<A, shapeless.$colon$colon<B, shapeless.$colon$colon<C, shapeless.$colon$colon<D, shapeless.$colon$colon<E, shapeless.$colon$colon<F, shapeless.HNil>>>>>>, Res>> fnFromProduct6();
    descriptor: ()Lshapeless/ops/function$FnFromProduct;
    flags: (0x0001) ACC_PUBLIC
    Code:
      stack=1, locals=1, args_size=1
         0: aload_0
         1: invokestatic  #66                 // InterfaceMethod shapeless/ops/FnFromProductInstances.fnFromProduct6$:(Lshapeless/ops/FnFromProductInstances;)Lshapeless/ops/function$FnFromProduct;
         4: areturn
      LineNumberTable:
        line 43: 0
      LocalVariableTable:
        Start  Length  Slot  Name   Signature
            0       5     0  this   Lshapeless/ops/function$FnFromProduct$;
    Signature: #63                          // <A:Ljava/lang/Object;B:Ljava/lang/Object;C:Ljava/lang/Object;D:Ljava/lang/Object;E:Ljava/lang/Object;F:Ljava/lang/Object;Res:Ljava/lang/Object;>()Lshapeless/ops/function$FnFromProduct<Lscala/Function1<Lshapeless/$colon$colon<TA;Lshapeless/$colon$colon<TB;Lshapeless/$colon$colon<TC;Lshapeless/$colon$colon<TD;Lshapeless/$colon$colon<TE;Lshapeless/$colon$colon<TF;Lshapeless/HNil;>;>;>;>;>;>;TRes;>;>;

  public <A extends java.lang.Object, B extends java.lang.Object, C extends java.lang.Object, D extends java.lang.Object, E extends java.lang.Object, F extends java.lang.Object, G extends java.lang.Object, Res extends java.lang.Object> shapeless.ops.function$FnFromProduct<scala.Function1<shapeless.$colon$colon<A, shapeless.$colon$colon<B, shapeless.$colon$colon<C, shapeless.$colon$colon<D, shapeless.$colon$colon<E, shapeless.$colon$colon<F, shapeless.$colon$colon<G, shapeless.HNil>>>>>>>, Res>> fnFromProduct7();
    descriptor: ()Lshapeless/ops/function$FnFromProduct;
    flags: (0x0001) ACC_PUBLIC
    Code:
      stack=1, locals=1, args_size=1
         0: aload_0
         1: invokestatic  #71                 // InterfaceMethod shapeless/ops/FnFromProductInstances.fnFromProduct7$:(Lshapeless/ops/FnFromProductInstances;)Lshapeless/ops/function$FnFromProduct;
         4: areturn
      LineNumberTable:
        line 43: 0
      LocalVariableTable:
        Start  Length  Slot  Name   Signature
            0       5     0  this   Lshapeless/ops/function$FnFromProduct$;
    Signature: #68                          // <A:Ljava/lang/Object;B:Ljava/lang/Object;C:Ljava/lang/Object;D:Ljava/lang/Object;E:Ljava/lang/Object;F:Ljava/lang/Object;G:Ljava/lang/Object;Res:Ljava/lang/Object;>()Lshapeless/ops/function$FnFromProduct<Lscala/Function1<Lshapeless/$colon$colon<TA;Lshapeless/$colon$colon<TB;Lshapeless/$colon$colon<TC;Lshapeless/$colon$colon<TD;Lshapeless/$colon$colon<TE;Lshapeless/$colon$colon<TF;Lshapeless/$colon$colon<TG;Lshapeless/HNil;>;>;>;>;>;>;>;TRes;>;>;

  public <A extends java.lang.Object, B extends java.lang.Object, C extends java.lang.Object, D extends java.lang.Object, E extends java.lang.Object, F extends java.lang.Object, G extends java.lang.Object, H extends java.lang.Object, Res extends java.lang.Object> shapeless.ops.function$FnFromProduct<scala.Function1<shapeless.$colon$colon<A, shapeless.$colon$colon<B, shapeless.$colon$colon<C, shapeless.$colon$colon<D, shapeless.$colon$colon<E, shapeless.$colon$colon<F, shapeless.$colon$colon<G, shapeless.$colon$colon<H, shapeless.HNil>>>>>>>>, Res>> fnFromProduct8();
    descriptor: ()Lshapeless/ops/function$FnFromProduct;
    flags: (0x0001) ACC_PUBLIC
    Code:
      stack=1, locals=1, args_size=1
         0: aload_0
         1: invokestatic  #76                 // InterfaceMethod shapeless/ops/FnFromProductInstances.fnFromProduct8$:(Lshapeless/ops/FnFromProductInstances;)Lshapeless/ops/function$FnFromProduct;
         4: areturn
      LineNumberTable:
        line 43: 0
      LocalVariableTable:
        Start  Length  Slot  Name   Signature
            0       5     0  this   Lshapeless/ops/function$FnFromProduct$;
    Signature: #73                          // <A:Ljava/lang/Object;B:Ljava/lang/Object;C:Ljava/lang/Object;D:Ljava/lang/Object;E:Ljava/lang/Object;F:Ljava/lang/Object;G:Ljava/lang/Object;H:Ljava/lang/Object;Res:Ljava/lang/Object;>()Lshapeless/ops/function$FnFromProduct<Lscala/Function1<Lshapeless/$colon$colon<TA;Lshapeless/$colon$colon<TB;Lshapeless/$colon$colon<TC;Lshapeless/$colon$colon<TD;Lshapeless/$colon$colon<TE;Lshapeless/$colon$colon<TF;Lshapeless/$colon$colon<TG;Lshapeless/$colon$colon<TH;Lshapeless/HNil;>;>;>;>;>;>;>;>;TRes;>;>;

  public <A extends java.lang.Object, B extends java.lang.Object, C extends java.lang.Object, D extends java.lang.Object, E extends java.lang.Object, F extends java.lang.Object, G extends java.lang.Object, H extends java.lang.Object, I extends java.lang.Object, Res extends java.lang.Object> shapeless.ops.function$FnFromProduct<scala.Function1<shapeless.$colon$colon<A, shapeless.$colon$colon<B, shapeless.$colon$colon<C, shapeless.$colon$colon<D, shapeless.$colon$colon<E, shapeless.$colon$colon<F, shapeless.$colon$colon<G, shapeless.$colon$colon<H, shapeless.$colon$colon<I, shapeless.HNil>>>>>>>>>, Res>> fnFromProduct9();
    descriptor: ()Lshapeless/ops/function$FnFromProduct;
    flags: (0x0001) ACC_PUBLIC
    Code:
      stack=1, locals=1, args_size=1
         0: aload_0
         1: invokestatic  #81                 // InterfaceMethod shapeless/ops/FnFromProductInstances.fnFromProduct9$:(Lshapeless/ops/FnFromProductInstances;)Lshapeless/ops/function$FnFromProduct;
         4: areturn
      LineNumberTable:
        line 43: 0
      LocalVariableTable:
        Start  Length  Slot  Name   Signature
            0       5     0  this   Lshapeless/ops/function$FnFromProduct$;
    Signature: #78                          // <A:Ljava/lang/Object;B:Ljava/lang/Object;C:Ljava/lang/Object;D:Ljava/lang/Object;E:Ljava/lang/Object;F:Ljava/lang/Object;G:Ljava/lang/Object;H:Ljava/lang/Object;I:Ljava/lang/Object;Res:Ljava/lang/Object;>()Lshapeless/ops/function$FnFromProduct<Lscala/Function1<Lshapeless/$colon$colon<TA;Lshapeless/$colon$colon<TB;Lshapeless/$colon$colon<TC;Lshapeless/$colon$colon<TD;Lshapeless/$colon$colon<TE;Lshapeless/$colon$colon<TF;Lshapeless/$colon$colon<TG;Lshapeless/$colon$colon<TH;Lshapeless/$colon$colon<TI;Lshapeless/HNil;>;>;>;>;>;>;>;>;>;TRes;>;>;

  public <A extends java.lang.Object, B extends java.lang.Object, C extends java.lang.Object, D extends java.lang.Object, E extends java.lang.Object, F extends java.lang.Object, G extends java.lang.Object, H extends java.lang.Object, I extends java.lang.Object, J extends java.lang.Object, Res extends java.lang.Object> shapeless.ops.function$FnFromProduct<scala.Function1<shapeless.$colon$colon<A, shapeless.$colon$colon<B, shapeless.$colon$colon<C, shapeless.$colon$colon<D, shapeless.$colon$colon<E, shapeless.$colon$colon<F, shapeless.$colon$colon<G, shapeless.$colon$colon<H, shapeless.$colon$colon<I, shapeless.$colon$colon<J, shapeless.HNil>>>>>>>>>>, Res>> fnFromProduct10();
    descriptor: ()Lshapeless/ops/function$FnFromProduct;
    flags: (0x0001) ACC_PUBLIC
    Code:
      stack=1, locals=1, args_size=1
         0: aload_0
         1: invokestatic  #86                 // InterfaceMethod shapeless/ops/FnFromProductInstances.fnFromProduct10$:(Lshapeless/ops/FnFromProductInstances;)Lshapeless/ops/function$FnFromProduct;
         4: areturn
      LineNumberTable:
        line 43: 0
      LocalVariableTable:
        Start  Length  Slot  Name   Signature
            0       5     0  this   Lshapeless/ops/function$FnFromProduct$;
    Signature: #83                          // <A:Ljava/lang/Object;B:Ljava/lang/Object;C:Ljava/lang/Object;D:Ljava/lang/Object;E:Ljava/lang/Object;F:Ljava/lang/Object;G:Ljava/lang/Object;H:Ljava/lang/Object;I:Ljava/lang/Object;J:Ljava/lang/Object;Res:Ljava/lang/Object;>()Lshapeless/ops/function$FnFromProduct<Lscala/Function1<Lshapeless/$colon$colon<TA;Lshapeless/$colon$colon<TB;Lshapeless/$colon$colon<TC;Lshapeless/$colon$colon<TD;Lshapeless/$colon$colon<TE;Lshapeless/$colon$colon<TF;Lshapeless/$colon$colon<TG;Lshapeless/$colon$colon<TH;Lshapeless/$colon$colon<TI;Lshapeless/$colon$colon<TJ;Lshapeless/HNil;>;>;>;>;>;>;>;>;>;>;TRes;>;>;

  public <A extends java.lang.Object, B extends java.lang.Object, C extends java.lang.Object, D extends java.lang.Object, E extends java.lang.Object, F extends java.lang.Object, G extends java.lang.Object, H extends java.lang.Object, I extends java.lang.Object, J extends java.lang.Object, K extends java.lang.Object, Res extends java.lang.Object> shapeless.ops.function$FnFromProduct<scala.Function1<shapeless.$colon$colon<A, shapeless.$colon$colon<B, shapeless.$colon$colon<C, shapeless.$colon$colon<D, shapeless.$colon$colon<E, shapeless.$colon$colon<F, shapeless.$colon$colon<G, shapeless.$colon$colon<H, shapeless.$colon$colon<I, shapeless.$colon$colon<J, shapeless.$colon$colon<K, shapeless.HNil>>>>>>>>>>>, Res>> fnFromProduct11();
    descriptor: ()Lshapeless/ops/function$FnFromProduct;
    flags: (0x0001) ACC_PUBLIC
    Code:
      stack=1, locals=1, args_size=1
         0: aload_0
         1: invokestatic  #91                 // InterfaceMethod shapeless/ops/FnFromProductInstances.fnFromProduct11$:(Lshapeless/ops/FnFromProductInstances;)Lshapeless/ops/function$FnFromProduct;
         4: areturn
      LineNumberTable:
        line 43: 0
      LocalVariableTable:
        Start  Length  Slot  Name   Signature
            0       5     0  this   Lshapeless/ops/function$FnFromProduct$;
    Signature: #88                          // <A:Ljava/lang/Object;B:Ljava/lang/Object;C:Ljava/lang/Object;D:Ljava/lang/Object;E:Ljava/lang/Object;F:Ljava/lang/Object;G:Ljava/lang/Object;H:Ljava/lang/Object;I:Ljava/lang/Object;J:Ljava/lang/Object;K:Ljava/lang/Object;Res:Ljava/lang/Object;>()Lshapeless/ops/function$FnFromProduct<Lscala/Function1<Lshapeless/$colon$colon<TA;Lshapeless/$colon$colon<TB;Lshapeless/$colon$colon<TC;Lshapeless/$colon$colon<TD;Lshapeless/$colon$colon<TE;Lshapeless/$colon$colon<TF;Lshapeless/$colon$colon<TG;Lshapeless/$colon$colon<TH;Lshapeless/$colon$colon<TI;Lshapeless/$colon$colon<TJ;Lshapeless/$colon$colon<TK;Lshapeless/HNil;>;>;>;>;>;>;>;>;>;>;>;TRes;>;>;

  public <A extends java.lang.Object, B extends java.lang.Object, C extends java.lang.Object, D extends java.lang.Object, E extends java.lang.Object, F extends java.lang.Object, G extends java.lang.Object, H extends java.lang.Object, I extends java.lang.Object, J extends java.lang.Object, K extends java.lang.Object, L extends java.lang.Object, Res extends java.lang.Object> shapeless.ops.function$FnFromProduct<scala.Function1<shapeless.$colon$colon<A, shapeless.$colon$colon<B, shapeless.$colon$colon<C, shapeless.$colon$colon<D, shapeless.$colon$colon<E, shapeless.$colon$colon<F, shapeless.$colon$colon<G, shapeless.$colon$colon<H, shapeless.$colon$colon<I, shapeless.$colon$colon<J, shapeless.$colon$colon<K, shapeless.$colon$colon<L, shapeless.HNil>>>>>>>>>>>>, Res>> fnFromProduct12();
    descriptor: ()Lshapeless/ops/function$FnFromProduct;
    flags: (0x0001) ACC_PUBLIC
    Code:
      stack=1, locals=1, args_size=1
         0: aload_0
         1: invokestatic  #96                 // InterfaceMethod shapeless/ops/FnFromProductInstances.fnFromProduct12$:(Lshapeless/ops/FnFromProductInstances;)Lshapeless/ops/function$FnFromProduct;
         4: areturn
      LineNumberTable:
        line 43: 0
      LocalVariableTable:
        Start  Length  Slot  Name   Signature
            0       5     0  this   Lshapeless/ops/function$FnFromProduct$;
    Signature: #93                          // <A:Ljava/lang/Object;B:Ljava/lang/Object;C:Ljava/lang/Object;D:Ljava/lang/Object;E:Ljava/lang/Object;F:Ljava/lang/Object;G:Ljava/lang/Object;H:Ljava/lang/Object;I:Ljava/lang/Object;J:Ljava/lang/Object;K:Ljava/lang/Object;L:Ljava/lang/Object;Res:Ljava/lang/Object;>()Lshapeless/ops/function$FnFromProduct<Lscala/Function1<Lshapeless/$colon$colon<TA;Lshapeless/$colon$colon<TB;Lshapeless/$colon$colon<TC;Lshapeless/$colon$colon<TD;Lshapeless/$colon$colon<TE;Lshapeless/$colon$colon<TF;Lshapeless/$colon$colon<TG;Lshapeless/$colon$colon<TH;Lshapeless/$colon$colon<TI;Lshapeless/$colon$colon<TJ;Lshapeless/$colon$colon<TK;Lshapeless/$colon$colon<TL;Lshapeless/HNil;>;>;>;>;>;>;>;>;>;>;>;>;TRes;>;>;

  public <A extends java.lang.Object, B extends java.lang.Object, C extends java.lang.Object, D extends java.lang.Object, E extends java.lang.Object, F extends java.lang.Object, G extends java.lang.Object, H extends java.lang.Object, I extends java.lang.Object, J extends java.lang.Object, K extends java.lang.Object, L extends java.lang.Object, M extends java.lang.Object, Res extends java.lang.Object> shapeless.ops.function$FnFromProduct<scala.Function1<shapeless.$colon$colon<A, shapeless.$colon$colon<B, shapeless.$colon$colon<C, shapeless.$colon$colon<D, shapeless.$colon$colon<E, shapeless.$colon$colon<F, shapeless.$colon$colon<G, shapeless.$colon$colon<H, shapeless.$colon$colon<I, shapeless.$colon$colon<J, shapeless.$colon$colon<K, shapeless.$colon$colon<L, shapeless.$colon$colon<M, shapeless.HNil>>>>>>>>>>>>>, Res>> fnFromProduct13();
    descriptor: ()Lshapeless/ops/function$FnFromProduct;
    flags: (0x0001) ACC_PUBLIC
    Code:
      stack=1, locals=1, args_size=1
         0: aload_0
         1: invokestatic  #101                // InterfaceMethod shapeless/ops/FnFromProductInstances.fnFromProduct13$:(Lshapeless/ops/FnFromProductInstances;)Lshapeless/ops/function$FnFromProduct;
         4: areturn
      LineNumberTable:
        line 43: 0
      LocalVariableTable:
        Start  Length  Slot  Name   Signature
            0       5     0  this   Lshapeless/ops/function$FnFromProduct$;
    Signature: #98                          // <A:Ljava/lang/Object;B:Ljava/lang/Object;C:Ljava/lang/Object;D:Ljava/lang/Object;E:Ljava/lang/Object;F:Ljava/lang/Object;G:Ljava/lang/Object;H:Ljava/lang/Object;I:Ljava/lang/Object;J:Ljava/lang/Object;K:Ljava/lang/Object;L:Ljava/lang/Object;M:Ljava/lang/Object;Res:Ljava/lang/Object;>()Lshapeless/ops/function$FnFromProduct<Lscala/Function1<Lshapeless/$colon$colon<TA;Lshapeless/$colon$colon<TB;Lshapeless/$colon$colon<TC;Lshapeless/$colon$colon<TD;Lshapeless/$colon$colon<TE;Lshapeless/$colon$colon<TF;Lshapeless/$colon$colon<TG;Lshapeless/$colon$colon<TH;Lshapeless/$colon$colon<TI;Lshapeless/$colon$colon<TJ;Lshapeless/$colon$colon<TK;Lshapeless/$colon$colon<TL;Lshapeless/$colon$colon<TM;Lshapeless/HNil;>;>;>;>;>;>;>;>;>;>;>;>;>;TRes;>;>;

  public <A extends java.lang.Object, B extends java.lang.Object, C extends java.lang.Object, D extends java.lang.Object, E extends java.lang.Object, F extends java.lang.Object, G extends java.lang.Object, H extends java.lang.Object, I extends java.lang.Object, J extends java.lang.Object, K extends java.lang.Object, L extends java.lang.Object, M extends java.lang.Object, N extends java.lang.Object, Res extends java.lang.Object> shapeless.ops.function$FnFromProduct<scala.Function1<shapeless.$colon$colon<A, shapeless.$colon$colon<B, shapeless.$colon$colon<C, shapeless.$colon$colon<D, shapeless.$colon$colon<E, shapeless.$colon$colon<F, shapeless.$colon$colon<G, shapeless.$colon$colon<H, shapeless.$colon$colon<I, shapeless.$colon$colon<J, shapeless.$colon$colon<K, shapeless.$colon$colon<L, shapeless.$colon$colon<M, shapeless.$colon$colon<N, shapeless.HNil>>>>>>>>>>>>>>, Res>> fnFromProduct14();
    descriptor: ()Lshapeless/ops/function$FnFromProduct;
    flags: (0x0001) ACC_PUBLIC
    Code:
      stack=1, locals=1, args_size=1
         0: aload_0
         1: invokestatic  #106                // InterfaceMethod shapeless/ops/FnFromProductInstances.fnFromProduct14$:(Lshapeless/ops/FnFromProductInstances;)Lshapeless/ops/function$FnFromProduct;
         4: areturn
      LineNumberTable:
        line 43: 0
      LocalVariableTable:
        Start  Length  Slot  Name   Signature
            0       5     0  this   Lshapeless/ops/function$FnFromProduct$;
    Signature: #103                         // <A:Ljava/lang/Object;B:Ljava/lang/Object;C:Ljava/lang/Object;D:Ljava/lang/Object;E:Ljava/lang/Object;F:Ljava/lang/Object;G:Ljava/lang/Object;H:Ljava/lang/Object;I:Ljava/lang/Object;J:Ljava/lang/Object;K:Ljava/lang/Object;L:Ljava/lang/Object;M:Ljava/lang/Object;N:Ljava/lang/Object;Res:Ljava/lang/Object;>()Lshapeless/ops/function$FnFromProduct<Lscala/Function1<Lshapeless/$colon$colon<TA;Lshapeless/$colon$colon<TB;Lshapeless/$colon$colon<TC;Lshapeless/$colon$colon<TD;Lshapeless/$colon$colon<TE;Lshapeless/$colon$colon<TF;Lshapeless/$colon$colon<TG;Lshapeless/$colon$colon<TH;Lshapeless/$colon$colon<TI;Lshapeless/$colon$colon<TJ;Lshapeless/$colon$colon<TK;Lshapeless/$colon$colon<TL;Lshapeless/$colon$colon<TM;Lshapeless/$colon$colon<TN;Lshapeless/HNil;>;>;>;>;>;>;>;>;>;>;>;>;>;>;TRes;>;>;

  public <A extends java.lang.Object, B extends java.lang.Object, C extends java.lang.Object, D extends java.lang.Object, E extends java.lang.Object, F extends java.lang.Object, G extends java.lang.Object, H extends java.lang.Object, I extends java.lang.Object, J extends java.lang.Object, K extends java.lang.Object, L extends java.lang.Object, M extends java.lang.Object, N extends java.lang.Object, O extends java.lang.Object, Res extends java.lang.Object> shapeless.ops.function$FnFromProduct<scala.Function1<shapeless.$colon$colon<A, shapeless.$colon$colon<B, shapeless.$colon$colon<C, shapeless.$colon$colon<D, shapeless.$colon$colon<E, shapeless.$colon$colon<F, shapeless.$colon$colon<G, shapeless.$colon$colon<H, shapeless.$colon$colon<I, shapeless.$colon$colon<J, shapeless.$colon$colon<K, shapeless.$colon$colon<L, shapeless.$colon$colon<M, shapeless.$colon$colon<N, shapeless.$colon$colon<O, shapeless.HNil>>>>>>>>>>>>>>>, Res>> fnFromProduct15();
    descriptor: ()Lshapeless/ops/function$FnFromProduct;
    flags: (0x0001) ACC_PUBLIC
    Code:
      stack=1, locals=1, args_size=1
         0: aload_0
         1: invokestatic  #111                // InterfaceMethod shapeless/ops/FnFromProductInstances.fnFromProduct15$:(Lshapeless/ops/FnFromProductInstances;)Lshapeless/ops/function$FnFromProduct;
         4: areturn
      LineNumberTable:
        line 43: 0
      LocalVariableTable:
        Start  Length  Slot  Name   Signature
            0       5     0  this   Lshapeless/ops/function$FnFromProduct$;
    Signature: #108                         // <A:Ljava/lang/Object;B:Ljava/lang/Object;C:Ljava/lang/Object;D:Ljava/lang/Object;E:Ljava/lang/Object;F:Ljava/lang/Object;G:Ljava/lang/Object;H:Ljava/lang/Object;I:Ljava/lang/Object;J:Ljava/lang/Object;K:Ljava/lang/Object;L:Ljava/lang/Object;M:Ljava/lang/Object;N:Ljava/lang/Object;O:Ljava/lang/Object;Res:Ljava/lang/Object;>()Lshapeless/ops/function$FnFromProduct<Lscala/Function1<Lshapeless/$colon$colon<TA;Lshapeless/$colon$colon<TB;Lshapeless/$colon$colon<TC;Lshapeless/$colon$colon<TD;Lshapeless/$colon$colon<TE;Lshapeless/$colon$colon<TF;Lshapeless/$colon$colon<TG;Lshapeless/$colon$colon<TH;Lshapeless/$colon$colon<TI;Lshapeless/$colon$colon<TJ;Lshapeless/$colon$colon<TK;Lshapeless/$colon$colon<TL;Lshapeless/$colon$colon<TM;Lshapeless/$colon$colon<TN;Lshapeless/$colon$colon<TO;Lshapeless/HNil;>;>;>;>;>;>;>;>;>;>;>;>;>;>;>;TRes;>;>;

  public <A extends java.lang.Object, B extends java.lang.Object, C extends java.lang.Object, D extends java.lang.Object, E extends java.lang.Object, F extends java.lang.Object, G extends java.lang.Object, H extends java.lang.Object, I extends java.lang.Object, J extends java.lang.Object, K extends java.lang.Object, L extends java.lang.Object, M extends java.lang.Object, N extends java.lang.Object, O extends java.lang.Object, P extends java.lang.Object, Res extends java.lang.Object> shapeless.ops.function$FnFromProduct<scala.Function1<shapeless.$colon$colon<A, shapeless.$colon$colon<B, shapeless.$colon$colon<C, shapeless.$colon$colon<D, shapeless.$colon$colon<E, shapeless.$colon$colon<F, shapeless.$colon$colon<G, shapeless.$colon$colon<H, shapeless.$colon$colon<I, shapeless.$colon$colon<J, shapeless.$colon$colon<K, shapeless.$colon$colon<L, shapeless.$colon$colon<M, shapeless.$colon$colon<N, shapeless.$colon$colon<O, shapeless.$colon$colon<P, shapeless.HNil>>>>>>>>>>>>>>>>, Res>> fnFromProduct16();
    descriptor: ()Lshapeless/ops/function$FnFromProduct;
    flags: (0x0001) ACC_PUBLIC
    Code:
      stack=1, locals=1, args_size=1
         0: aload_0
         1: invokestatic  #116                // InterfaceMethod shapeless/ops/FnFromProductInstances.fnFromProduct16$:(Lshapeless/ops/FnFromProductInstances;)Lshapeless/ops/function$FnFromProduct;
         4: areturn
      LineNumberTable:
        line 43: 0
      LocalVariableTable:
        Start  Length  Slot  Name   Signature
            0       5     0  this   Lshapeless/ops/function$FnFromProduct$;
    Signature: #113                         // <A:Ljava/lang/Object;B:Ljava/lang/Object;C:Ljava/lang/Object;D:Ljava/lang/Object;E:Ljava/lang/Object;F:Ljava/lang/Object;G:Ljava/lang/Object;H:Ljava/lang/Object;I:Ljava/lang/Object;J:Ljava/lang/Object;K:Ljava/lang/Object;L:Ljava/lang/Object;M:Ljava/lang/Object;N:Ljava/lang/Object;O:Ljava/lang/Object;P:Ljava/lang/Object;Res:Ljava/lang/Object;>()Lshapeless/ops/function$FnFromProduct<Lscala/Function1<Lshapeless/$colon$colon<TA;Lshapeless/$colon$colon<TB;Lshapeless/$colon$colon<TC;Lshapeless/$colon$colon<TD;Lshapeless/$colon$colon<TE;Lshapeless/$colon$colon<TF;Lshapeless/$colon$colon<TG;Lshapeless/$colon$colon<TH;Lshapeless/$colon$colon<TI;Lshapeless/$colon$colon<TJ;Lshapeless/$colon$colon<TK;Lshapeless/$colon$colon<TL;Lshapeless/$colon$colon<TM;Lshapeless/$colon$colon<TN;Lshapeless/$colon$colon<TO;Lshapeless/$colon$colon<TP;Lshapeless/HNil;>;>;>;>;>;>;>;>;>;>;>;>;>;>;>;>;TRes;>;>;

  public <A extends java.lang.Object, B extends java.lang.Object, C extends java.lang.Object, D extends java.lang.Object, E extends java.lang.Object, F extends java.lang.Object, G extends java.lang.Object, H extends java.lang.Object, I extends java.lang.Object, J extends java.lang.Object, K extends java.lang.Object, L extends java.lang.Object, M extends java.lang.Object, N extends java.lang.Object, O extends java.lang.Object, P extends java.lang.Object, Q extends java.lang.Object, Res extends java.lang.Object> shapeless.ops.function$FnFromProduct<scala.Function1<shapeless.$colon$colon<A, shapeless.$colon$colon<B, shapeless.$colon$colon<C, shapeless.$colon$colon<D, shapeless.$colon$colon<E, shapeless.$colon$colon<F, shapeless.$colon$colon<G, shapeless.$colon$colon<H, shapeless.$colon$colon<I, shapeless.$colon$colon<J, shapeless.$colon$colon<K, shapeless.$colon$colon<L, shapeless.$colon$colon<M, shapeless.$colon$colon<N, shapeless.$colon$colon<O, shapeless.$colon$colon<P, shapeless.$colon$colon<Q, shapeless.HNil>>>>>>>>>>>>>>>>>, Res>> fnFromProduct17();
    descriptor: ()Lshapeless/ops/function$FnFromProduct;
    flags: (0x0001) ACC_PUBLIC
    Code:
      stack=1, locals=1, args_size=1
         0: aload_0
         1: invokestatic  #121                // InterfaceMethod shapeless/ops/FnFromProductInstances.fnFromProduct17$:(Lshapeless/ops/FnFromProductInstances;)Lshapeless/ops/function$FnFromProduct;
         4: areturn
      LineNumberTable:
        line 43: 0
      LocalVariableTable:
        Start  Length  Slot  Name   Signature
            0       5     0  this   Lshapeless/ops/function$FnFromProduct$;
    Signature: #118                         // <A:Ljava/lang/Object;B:Ljava/lang/Object;C:Ljava/lang/Object;D:Ljava/lang/Object;E:Ljava/lang/Object;F:Ljava/lang/Object;G:Ljava/lang/Object;H:Ljava/lang/Object;I:Ljava/lang/Object;J:Ljava/lang/Object;K:Ljava/lang/Object;L:Ljava/lang/Object;M:Ljava/lang/Object;N:Ljava/lang/Object;O:Ljava/lang/Object;P:Ljava/lang/Object;Q:Ljava/lang/Object;Res:Ljava/lang/Object;>()Lshapeless/ops/function$FnFromProduct<Lscala/Function1<Lshapeless/$colon$colon<TA;Lshapeless/$colon$colon<TB;Lshapeless/$colon$colon<TC;Lshapeless/$colon$colon<TD;Lshapeless/$colon$colon<TE;Lshapeless/$colon$colon<TF;Lshapeless/$colon$colon<TG;Lshapeless/$colon$colon<TH;Lshapeless/$colon$colon<TI;Lshapeless/$colon$colon<TJ;Lshapeless/$colon$colon<TK;Lshapeless/$colon$colon<TL;Lshapeless/$colon$colon<TM;Lshapeless/$colon$colon<TN;Lshapeless/$colon$colon<TO;Lshapeless/$colon$colon<TP;Lshapeless/$colon$colon<TQ;Lshapeless/HNil;>;>;>;>;>;>;>;>;>;>;>;>;>;>;>;>;>;TRes;>;>;

  public <A extends java.lang.Object, B extends java.lang.Object, C extends java.lang.Object, D extends java.lang.Object, E extends java.lang.Object, F extends java.lang.Object, G extends java.lang.Object, H extends java.lang.Object, I extends java.lang.Object, J extends java.lang.Object, K extends java.lang.Object, L extends java.lang.Object, M extends java.lang.Object, N extends java.lang.Object, O extends java.lang.Object, P extends java.lang.Object, Q extends java.lang.Object, R extends java.lang.Object, Res extends java.lang.Object> shapeless.ops.function$FnFromProduct<scala.Function1<shapeless.$colon$colon<A, shapeless.$colon$colon<B, shapeless.$colon$colon<C, shapeless.$colon$colon<D, shapeless.$colon$colon<E, shapeless.$colon$colon<F, shapeless.$colon$colon<G, shapeless.$colon$colon<H, shapeless.$colon$colon<I, shapeless.$colon$colon<J, shapeless.$colon$colon<K, shapeless.$colon$colon<L, shapeless.$colon$colon<M, shapeless.$colon$colon<N, shapeless.$colon$colon<O, shapeless.$colon$colon<P, shapeless.$colon$colon<Q, shapeless.$colon$colon<R, shapeless.HNil>>>>>>>>>>>>>>>>>>, Res>> fnFromProduct18();
    descriptor: ()Lshapeless/ops/function$FnFromProduct;
    flags: (0x0001) ACC_PUBLIC
    Code:
      stack=1, locals=1, args_size=1
         0: aload_0
         1: invokestatic  #126                // InterfaceMethod shapeless/ops/FnFromProductInstances.fnFromProduct18$:(Lshapeless/ops/FnFromProductInstances;)Lshapeless/ops/function$FnFromProduct;
         4: areturn
      LineNumberTable:
        line 43: 0
      LocalVariableTable:
        Start  Length  Slot  Name   Signature
            0       5     0  this   Lshapeless/ops/function$FnFromProduct$;
    Signature: #123                         // <A:Ljava/lang/Object;B:Ljava/lang/Object;C:Ljava/lang/Object;D:Ljava/lang/Object;E:Ljava/lang/Object;F:Ljava/lang/Object;G:Ljava/lang/Object;H:Ljava/lang/Object;I:Ljava/lang/Object;J:Ljava/lang/Object;K:Ljava/lang/Object;L:Ljava/lang/Object;M:Ljava/lang/Object;N:Ljava/lang/Object;O:Ljava/lang/Object;P:Ljava/lang/Object;Q:Ljava/lang/Object;R:Ljava/lang/Object;Res:Ljava/lang/Object;>()Lshapeless/ops/function$FnFromProduct<Lscala/Function1<Lshapeless/$colon$colon<TA;Lshapeless/$colon$colon<TB;Lshapeless/$colon$colon<TC;Lshapeless/$colon$colon<TD;Lshapeless/$colon$colon<TE;Lshapeless/$colon$colon<TF;Lshapeless/$colon$colon<TG;Lshapeless/$colon$colon<TH;Lshapeless/$colon$colon<TI;Lshapeless/$colon$colon<TJ;Lshapeless/$colon$colon<TK;Lshapeless/$colon$colon<TL;Lshapeless/$colon$colon<TM;Lshapeless/$colon$colon<TN;Lshapeless/$colon$colon<TO;Lshapeless/$colon$colon<TP;Lshapeless/$colon$colon<TQ;Lshapeless/$colon$colon<TR;Lshapeless/HNil;>;>;>;>;>;>;>;>;>;>;>;>;>;>;>;>;>;>;TRes;>;>;

  public <A extends java.lang.Object, B extends java.lang.Object, C extends java.lang.Object, D extends java.lang.Object, E extends java.lang.Object, F extends java.lang.Object, G extends java.lang.Object, H extends java.lang.Object, I extends java.lang.Object, J extends java.lang.Object, K extends java.lang.Object, L extends java.lang.Object, M extends java.lang.Object, N extends java.lang.Object, O extends java.lang.Object, P extends java.lang.Object, Q extends java.lang.Object, R extends java.lang.Object, S extends java.lang.Object, Res extends java.lang.Object> shapeless.ops.function$FnFromProduct<scala.Function1<shapeless.$colon$colon<A, shapeless.$colon$colon<B, shapeless.$colon$colon<C, shapeless.$colon$colon<D, shapeless.$colon$colon<E, shapeless.$colon$colon<F, shapeless.$colon$colon<G, shapeless.$colon$colon<H, shapeless.$colon$colon<I, shapeless.$colon$colon<J, shapeless.$colon$colon<K, shapeless.$colon$colon<L, shapeless.$colon$colon<M, shapeless.$colon$colon<N, shapeless.$colon$colon<O, shapeless.$colon$colon<P, shapeless.$colon$colon<Q, shapeless.$colon$colon<R, shapeless.$colon$colon<S, shapeless.HNil>>>>>>>>>>>>>>>>>>>, Res>> fnFromProduct19();
    descriptor: ()Lshapeless/ops/function$FnFromProduct;
    flags: (0x0001) ACC_PUBLIC
    Code:
      stack=1, locals=1, args_size=1
         0: aload_0
         1: invokestatic  #131                // InterfaceMethod shapeless/ops/FnFromProductInstances.fnFromProduct19$:(Lshapeless/ops/FnFromProductInstances;)Lshapeless/ops/function$FnFromProduct;
         4: areturn
      LineNumberTable:
        line 43: 0
      LocalVariableTable:
        Start  Length  Slot  Name   Signature
            0       5     0  this   Lshapeless/ops/function$FnFromProduct$;
    Signature: #128                         // <A:Ljava/lang/Object;B:Ljava/lang/Object;C:Ljava/lang/Object;D:Ljava/lang/Object;E:Ljava/lang/Object;F:Ljava/lang/Object;G:Ljava/lang/Object;H:Ljava/lang/Object;I:Ljava/lang/Object;J:Ljava/lang/Object;K:Ljava/lang/Object;L:Ljava/lang/Object;M:Ljava/lang/Object;N:Ljava/lang/Object;O:Ljava/lang/Object;P:Ljava/lang/Object;Q:Ljava/lang/Object;R:Ljava/lang/Object;S:Ljava/lang/Object;Res:Ljava/lang/Object;>()Lshapeless/ops/function$FnFromProduct<Lscala/Function1<Lshapeless/$colon$colon<TA;Lshapeless/$colon$colon<TB;Lshapeless/$colon$colon<TC;Lshapeless/$colon$colon<TD;Lshapeless/$colon$colon<TE;Lshapeless/$colon$colon<TF;Lshapeless/$colon$colon<TG;Lshapeless/$colon$colon<TH;Lshapeless/$colon$colon<TI;Lshapeless/$colon$colon<TJ;Lshapeless/$colon$colon<TK;Lshapeless/$colon$colon<TL;Lshapeless/$colon$colon<TM;Lshapeless/$colon$colon<TN;Lshapeless/$colon$colon<TO;Lshapeless/$colon$colon<TP;Lshapeless/$colon$colon<TQ;Lshapeless/$colon$colon<TR;Lshapeless/$colon$colon<TS;Lshapeless/HNil;>;>;>;>;>;>;>;>;>;>;>;>;>;>;>;>;>;>;>;TRes;>;>;

  public <A extends java.lang.Object, B extends java.lang.Object, C extends java.lang.Object, D extends java.lang.Object, E extends java.lang.Object, F extends java.lang.Object, G extends java.lang.Object, H extends java.lang.Object, I extends java.lang.Object, J extends java.lang.Object, K extends java.lang.Object, L extends java.lang.Object, M extends java.lang.Object, N extends java.lang.Object, O extends java.lang.Object, P extends java.lang.Object, Q extends java.lang.Object, R extends java.lang.Object, S extends java.lang.Object, T extends java.lang.Object, Res extends java.lang.Object> shapeless.ops.function$FnFromProduct<scala.Function1<shapeless.$colon$colon<A, shapeless.$colon$colon<B, shapeless.$colon$colon<C, shapeless.$colon$colon<D, shapeless.$colon$colon<E, shapeless.$colon$colon<F, shapeless.$colon$colon<G, shapeless.$colon$colon<H, shapeless.$colon$colon<I, shapeless.$colon$colon<J, shapeless.$colon$colon<K, shapeless.$colon$colon<L, shapeless.$colon$colon<M, shapeless.$colon$colon<N, shapeless.$colon$colon<O, shapeless.$colon$colon<P, shapeless.$colon$colon<Q, shapeless.$colon$colon<R, shapeless.$colon$colon<S, shapeless.$colon$colon<T, shapeless.HNil>>>>>>>>>>>>>>>>>>>>, Res>> fnFromProduct20();
    descriptor: ()Lshapeless/ops/function$FnFromProduct;
    flags: (0x0001) ACC_PUBLIC
    Code:
      stack=1, locals=1, args_size=1
         0: aload_0
         1: invokestatic  #136                // InterfaceMethod shapeless/ops/FnFromProductInstances.fnFromProduct20$:(Lshapeless/ops/FnFromProductInstances;)Lshapeless/ops/function$FnFromProduct;
         4: areturn
      LineNumberTable:
        line 43: 0
      LocalVariableTable:
        Start  Length  Slot  Name   Signature
            0       5     0  this   Lshapeless/ops/function$FnFromProduct$;
    Signature: #133                         // <A:Ljava/lang/Object;B:Ljava/lang/Object;C:Ljava/lang/Object;D:Ljava/lang/Object;E:Ljava/lang/Object;F:Ljava/lang/Object;G:Ljava/lang/Object;H:Ljava/lang/Object;I:Ljava/lang/Object;J:Ljava/lang/Object;K:Ljava/lang/Object;L:Ljava/lang/Object;M:Ljava/lang/Object;N:Ljava/lang/Object;O:Ljava/lang/Object;P:Ljava/lang/Object;Q:Ljava/lang/Object;R:Ljava/lang/Object;S:Ljava/lang/Object;T:Ljava/lang/Object;Res:Ljava/lang/Object;>()Lshapeless/ops/function$FnFromProduct<Lscala/Function1<Lshapeless/$colon$colon<TA;Lshapeless/$colon$colon<TB;Lshapeless/$colon$colon<TC;Lshapeless/$colon$colon<TD;Lshapeless/$colon$colon<TE;Lshapeless/$colon$colon<TF;Lshapeless/$colon$colon<TG;Lshapeless/$colon$colon<TH;Lshapeless/$colon$colon<TI;Lshapeless/$colon$colon<TJ;Lshapeless/$colon$colon<TK;Lshapeless/$colon$colon<TL;Lshapeless/$colon$colon<TM;Lshapeless/$colon$colon<TN;Lshapeless/$colon$colon<TO;Lshapeless/$colon$colon<TP;Lshapeless/$colon$colon<TQ;Lshapeless/$colon$colon<TR;Lshapeless/$colon$colon<TS;Lshapeless/$colon$colon<TT;Lshapeless/HNil;>;>;>;>;>;>;>;>;>;>;>;>;>;>;>;>;>;>;>;>;TRes;>;>;

  public <A extends java.lang.Object, B extends java.lang.Object, C extends java.lang.Object, D extends java.lang.Object, E extends java.lang.Object, F extends java.lang.Object, G extends java.lang.Object, H extends java.lang.Object, I extends java.lang.Object, J extends java.lang.Object, K extends java.lang.Object, L extends java.lang.Object, M extends java.lang.Object, N extends java.lang.Object, O extends java.lang.Object, P extends java.lang.Object, Q extends java.lang.Object, R extends java.lang.Object, S extends java.lang.Object, T extends java.lang.Object, U extends java.lang.Object, Res extends java.lang.Object> shapeless.ops.function$FnFromProduct<scala.Function1<shapeless.$colon$colon<A, shapeless.$colon$colon<B, shapeless.$colon$colon<C, shapeless.$colon$colon<D, shapeless.$colon$colon<E, shapeless.$colon$colon<F, shapeless.$colon$colon<G, shapeless.$colon$colon<H, shapeless.$colon$colon<I, shapeless.$colon$colon<J, shapeless.$colon$colon<K, shapeless.$colon$colon<L, shapeless.$colon$colon<M, shapeless.$colon$colon<N, shapeless.$colon$colon<O, shapeless.$colon$colon<P, shapeless.$colon$colon<Q, shapeless.$colon$colon<R, shapeless.$colon$colon<S, shapeless.$colon$colon<T, shapeless.$colon$colon<U, shapeless.HNil>>>>>>>>>>>>>>>>>>>>>, Res>> fnFromProduct21();
    descriptor: ()Lshapeless/ops/function$FnFromProduct;
    flags: (0x0001) ACC_PUBLIC
    Code:
      stack=1, locals=1, args_size=1
         0: aload_0
         1: invokestatic  #141                // InterfaceMethod shapeless/ops/FnFromProductInstances.fnFromProduct21$:(Lshapeless/ops/FnFromProductInstances;)Lshapeless/ops/function$FnFromProduct;
         4: areturn
      LineNumberTable:
        line 43: 0
      LocalVariableTable:
        Start  Length  Slot  Name   Signature
            0       5     0  this   Lshapeless/ops/function$FnFromProduct$;
    Signature: #138                         // <A:Ljava/lang/Object;B:Ljava/lang/Object;C:Ljava/lang/Object;D:Ljava/lang/Object;E:Ljava/lang/Object;F:Ljava/lang/Object;G:Ljava/lang/Object;H:Ljava/lang/Object;I:Ljava/lang/Object;J:Ljava/lang/Object;K:Ljava/lang/Object;L:Ljava/lang/Object;M:Ljava/lang/Object;N:Ljava/lang/Object;O:Ljava/lang/Object;P:Ljava/lang/Object;Q:Ljava/lang/Object;R:Ljava/lang/Object;S:Ljava/lang/Object;T:Ljava/lang/Object;U:Ljava/lang/Object;Res:Ljava/lang/Object;>()Lshapeless/ops/function$FnFromProduct<Lscala/Function1<Lshapeless/$colon$colon<TA;Lshapeless/$colon$colon<TB;Lshapeless/$colon$colon<TC;Lshapeless/$colon$colon<TD;Lshapeless/$colon$colon<TE;Lshapeless/$colon$colon<TF;Lshapeless/$colon$colon<TG;Lshapeless/$colon$colon<TH;Lshapeless/$colon$colon<TI;Lshapeless/$colon$colon<TJ;Lshapeless/$colon$colon<TK;Lshapeless/$colon$colon<TL;Lshapeless/$colon$colon<TM;Lshapeless/$colon$colon<TN;Lshapeless/$colon$colon<TO;Lshapeless/$colon$colon<TP;Lshapeless/$colon$colon<TQ;Lshapeless/$colon$colon<TR;Lshapeless/$colon$colon<TS;Lshapeless/$colon$colon<TT;Lshapeless/$colon$colon<TU;Lshapeless/HNil;>;>;>;>;>;>;>;>;>;>;>;>;>;>;>;>;>;>;>;>;>;TRes;>;>;

  public <A extends java.lang.Object, B extends java.lang.Object, C extends java.lang.Object, D extends java.lang.Object, E extends java.lang.Object, F extends java.lang.Object, G extends java.lang.Object, H extends java.lang.Object, I extends java.lang.Object, J extends java.lang.Object, K extends java.lang.Object, L extends java.lang.Object, M extends java.lang.Object, N extends java.lang.Object, O extends java.lang.Object, P extends java.lang.Object, Q extends java.lang.Object, R extends java.lang.Object, S extends java.lang.Object, T extends java.lang.Object, U extends java.lang.Object, V extends java.lang.Object, Res extends java.lang.Object> shapeless.ops.function$FnFromProduct<scala.Function1<shapeless.$colon$colon<A, shapeless.$colon$colon<B, shapeless.$colon$colon<C, shapeless.$colon$colon<D, shapeless.$colon$colon<E, shapeless.$colon$colon<F, shapeless.$colon$colon<G, shapeless.$colon$colon<H, shapeless.$colon$colon<I, shapeless.$colon$colon<J, shapeless.$colon$colon<K, shapeless.$colon$colon<L, shapeless.$colon$colon<M, shapeless.$colon$colon<N, shapeless.$colon$colon<O, shapeless.$colon$colon<P, shapeless.$colon$colon<Q, shapeless.$colon$colon<R, shapeless.$colon$colon<S, shapeless.$colon$colon<T, shapeless.$colon$colon<U, shapeless.$colon$colon<V, shapeless.HNil>>>>>>>>>>>>>>>>>>>>>>, Res>> fnFromProduct22();
    descriptor: ()Lshapeless/ops/function$FnFromProduct;
    flags: (0x0001) ACC_PUBLIC
    Code:
      stack=1, locals=1, args_size=1
         0: aload_0
         1: invokestatic  #146                // InterfaceMethod shapeless/ops/FnFromProductInstances.fnFromProduct22$:(Lshapeless/ops/FnFromProductInstances;)Lshapeless/ops/function$FnFromProduct;
         4: areturn
      LineNumberTable:
        line 43: 0
      LocalVariableTable:
        Start  Length  Slot  Name   Signature
            0       5     0  this   Lshapeless/ops/function$FnFromProduct$;
    Signature: #143                         // <A:Ljava/lang/Object;B:Ljava/lang/Object;C:Ljava/lang/Object;D:Ljava/lang/Object;E:Ljava/lang/Object;F:Ljava/lang/Object;G:Ljava/lang/Object;H:Ljava/lang/Object;I:Ljava/lang/Object;J:Ljava/lang/Object;K:Ljava/lang/Object;L:Ljava/lang/Object;M:Ljava/lang/Object;N:Ljava/lang/Object;O:Ljava/lang/Object;P:Ljava/lang/Object;Q:Ljava/lang/Object;R:Ljava/lang/Object;S:Ljava/lang/Object;T:Ljava/lang/Object;U:Ljava/lang/Object;V:Ljava/lang/Object;Res:Ljava/lang/Object;>()Lshapeless/ops/function$FnFromProduct<Lscala/Function1<Lshapeless/$colon$colon<TA;Lshapeless/$colon$colon<TB;Lshapeless/$colon$colon<TC;Lshapeless/$colon$colon<TD;Lshapeless/$colon$colon<TE;Lshapeless/$colon$colon<TF;Lshapeless/$colon$colon<TG;Lshapeless/$colon$colon<TH;Lshapeless/$colon$colon<TI;Lshapeless/$colon$colon<TJ;Lshapeless/$colon$colon<TK;Lshapeless/$colon$colon<TL;Lshapeless/$colon$colon<TM;Lshapeless/$colon$colon<TN;Lshapeless/$colon$colon<TO;Lshapeless/$colon$colon<TP;Lshapeless/$colon$colon<TQ;Lshapeless/$colon$colon<TR;Lshapeless/$colon$colon<TS;Lshapeless/$colon$colon<TT;Lshapeless/$colon$colon<TU;Lshapeless/$colon$colon<TV;Lshapeless/HNil;>;>;>;>;>;>;>;>;>;>;>;>;>;>;>;>;>;>;>;>;>;>;TRes;>;>;

  public <F extends java.lang.Object> shapeless.ops.function$FnFromProduct<F> apply(shapeless.ops.function$FnFromProduct<F>);
    descriptor: (Lshapeless/ops/function$FnFromProduct;)Lshapeless/ops/function$FnFromProduct;
    flags: (0x0001) ACC_PUBLIC
    Code:
      stack=1, locals=2, args_size=2
         0: aload_1
         1: areturn
      LineNumberTable:
        line 44: 0
      LocalVariableTable:
        Start  Length  Slot  Name   Signature
            0       2     0  this   Lshapeless/ops/function$FnFromProduct$;
            0       2     1 fnfromp   Lshapeless/ops/function$FnFromProduct;
    Signature: #149                         // <F:Ljava/lang/Object;>(Lshapeless/ops/function$FnFromProduct<TF;>;)Lshapeless/ops/function$FnFromProduct<TF;>;
    MethodParameters:
      Name                           Flags
      fnfromp                        final

  private java.lang.Object writeReplace();
    descriptor: ()Ljava/lang/Object;
    flags: (0x0002) ACC_PRIVATE
    Code:
      stack=3, locals=1, args_size=1
         0: new           #155                // class scala/runtime/ModuleSerializationProxy
         3: dup
         4: ldc           #2                  // class shapeless/ops/function$FnFromProduct$
         6: invokespecial #158                // Method scala/runtime/ModuleSerializationProxy."<init>":(Ljava/lang/Class;)V
         9: areturn
      LineNumberTable:
        line 43: 0
      LocalVariableTable:
        Start  Length  Slot  Name   Signature
            0      10     0  this   Lshapeless/ops/function$FnFromProduct$;

  public shapeless.ops.function$FnFromProduct$();
    descriptor: ()V
    flags: (0x0001) ACC_PUBLIC
    Code:
      stack=1, locals=1, args_size=1
         0: aload_0
         1: invokespecial #159                // Method java/lang/Object."<init>":()V
         4: return
      LineNumberTable:
        line 43: 0
      LocalVariableTable:
        Start  Length  Slot  Name   Signature
            0       5     0  this   Lshapeless/ops/function$FnFromProduct$;
}
InnerClasses:
  public static #14= #11 of #13;          // FnFromProduct=class shapeless/ops/function$FnFromProduct of class shapeless/ops/function
  public static #15= #2 of #13;           // FnFromProduct$=class shapeless/ops/function$FnFromProduct$ of class shapeless/ops/function
SourceFile: "functions.scala"
  ScalaInlineInfo: length = 0x86 (unknown attribute)
   01 01 00 1A 00 14 00 13 01 00 93 00 94 01 00 1D
   00 1E 01 00 25 00 1E 01 00 52 00 1E 01 00 57 00
   1E 01 00 5C 00 1E 01 00 61 00 1E 01 00 66 00 1E
   01 00 6B 00 1E 01 00 70 00 1E 01 00 75 00 1E 01
   00 7A 00 1E 01 00 7F 00 1E 01 00 2A 00 1E 01 00
   84 00 1E 01 00 89 00 1E 01 00 8E 00 1E 01 00 2F
   00 1E 01 00 34 00 1E 01 00 39 00 1E 01 00 3E 00
   1E 01 00 43 00 1E 01 00 48 00 1E 01 00 4D 00 1E
   01 00 98 00 99 01
  Scala: length = 0x0 (unknown attribute)

