Classfile /Users/mw/Projects/slang-braindump/.jar/jar8/assemble/slang-braindump/assemble/content/shapeless/ops/hlist$PaddedGrouper$.class
  Last modified May 29, 2022; size 4182 bytes
  SHA-256 checksum f16e170870af05aed16fa48e5ae3b1a0a78b10148a52d2d9bde1af16eb809e31
  Compiled from "hlists.scala"
public class shapeless.ops.hlist$PaddedGrouper$ implements shapeless.ops.hlist$LowPriorityPaddedGrouper,java.io.Serializable
  minor version: 0
  major version: 52
  flags: (0x0021) ACC_PUBLIC, ACC_SUPER
  this_class: #2                          // shapeless/ops/hlist$PaddedGrouper$
  super_class: #4                         // java/lang/Object
  interfaces: 2, fields: 1, methods: 6, attributes: 4
Constant pool:
    #1 = Utf8               shapeless/ops/hlist$PaddedGrouper$
    #2 = Class              #1            // shapeless/ops/hlist$PaddedGrouper$
    #3 = Utf8               java/lang/Object
    #4 = Class              #3            // java/lang/Object
    #5 = Utf8               shapeless/ops/hlist$LowPriorityPaddedGrouper
    #6 = Class              #5            // shapeless/ops/hlist$LowPriorityPaddedGrouper
    #7 = Utf8               java/io/Serializable
    #8 = Class              #7            // java/io/Serializable
    #9 = Utf8               hlists.scala
   #10 = Utf8               shapeless/ops/hlist$Grouper
   #11 = Class              #10           // shapeless/ops/hlist$Grouper
   #12 = Utf8               shapeless/ops/hlist
   #13 = Class              #12           // shapeless/ops/hlist
   #14 = Utf8               Grouper
   #15 = Utf8               shapeless/ops/hlist$Length
   #16 = Class              #15           // shapeless/ops/hlist$Length
   #17 = Utf8               Length
   #18 = Utf8               LowPriorityPaddedGrouper
   #19 = Utf8               shapeless/ops/hlist$PaddedGrouper
   #20 = Class              #19           // shapeless/ops/hlist$PaddedGrouper
   #21 = Utf8               PaddedGrouper
   #22 = Utf8               PaddedGrouper$
   #23 = Utf8               shapeless/ops/hlist$PaddedGrouper$$anon$77
   #24 = Class              #23           // shapeless/ops/hlist$PaddedGrouper$$anon$77
   #25 = Utf8               shapeless/ops/hlist$Prepend
   #26 = Class              #25           // shapeless/ops/hlist$Prepend
   #27 = Utf8               Prepend
   #28 = Utf8               shapeless/ops/hlist$Take
   #29 = Class              #28           // shapeless/ops/hlist$Take
   #30 = Utf8               Take
   #31 = Utf8               shapeless/ops/nat$Min
   #32 = Class              #31           // shapeless/ops/nat$Min
   #33 = Utf8               shapeless/ops/nat
   #34 = Class              #33           // shapeless/ops/nat
   #35 = Utf8               Min
   #36 = Utf8               shapeless/ops/nat$Mod
   #37 = Class              #36           // shapeless/ops/nat$Mod
   #38 = Utf8               Mod
   #39 = Utf8               shapeless/ops/nat$Sum
   #40 = Class              #39           // shapeless/ops/nat$Sum
   #41 = Utf8               Sum
   #42 = Utf8               MODULE$
   #43 = Utf8               Lshapeless/ops/hlist$PaddedGrouper$;
   #44 = Utf8               <clinit>
   #45 = Utf8               ()V
   #46 = Utf8               <init>
   #47 = NameAndType        #46:#45       // "<init>":()V
   #48 = Methodref          #2.#47        // shapeless/ops/hlist$PaddedGrouper$."<init>":()V
   #49 = NameAndType        #42:#43       // MODULE$:Lshapeless/ops/hlist$PaddedGrouper$;
   #50 = Fieldref           #2.#49        // shapeless/ops/hlist$PaddedGrouper$.MODULE$:Lshapeless/ops/hlist$PaddedGrouper$;
   #51 = Utf8               $init$
   #52 = Utf8               (Lshapeless/ops/hlist$LowPriorityPaddedGrouper;)V
   #53 = NameAndType        #51:#52       // $init$:(Lshapeless/ops/hlist$LowPriorityPaddedGrouper;)V
   #54 = InterfaceMethodref #6.#53        // shapeless/ops/hlist$LowPriorityPaddedGrouper.$init$:(Lshapeless/ops/hlist$LowPriorityPaddedGrouper;)V
   #55 = Utf8               incompletePaddedGrouper
   #56 = Utf8               (Lshapeless/ops/hlist$Length;Lshapeless/ops/hlist$Prepend;Lshapeless/ops/hlist$Length;Lshapeless/ops/nat$Mod;Lshapeless/ops/nat$Sum;Lshapeless/ops/nat$Min;Lshapeless/ops/hlist$Take;Lshapeless/ops/hlist$Grouper;)Lshapeless/ops/hlist$PaddedGrouper;
   #57 = Utf8               <L::Lshapeless/HList;N::Lshapeless/Nat;Step::Lshapeless/Nat;Pad::Lshapeless/HList;PL::Lshapeless/HList;LPL::Lshapeless/Nat;S::Lshapeless/Nat;MI::Lshapeless/Nat;T::Lshapeless/HList;M::Lshapeless/Nat;LL::Lshapeless/Nat;Out0::Lshapeless/HList;>(Lshapeless/ops/hlist$Length<TL;>;Lshapeless/ops/hlist$Prepend<TL;TPad;>;Lshapeless/ops/hlist$Length<TPL;>;Lshapeless/ops/nat$Mod<TLL;TStep;>;Lshapeless/ops/nat$Sum<TLL;TM;>;Lshapeless/ops/nat$Min<TLPL;TS;>;Lshapeless/ops/hlist$Take<TPL;TMI;>;Lshapeless/ops/hlist$Grouper<TT;TN;TStep;>;)Lshapeless/ops/hlist$PaddedGrouper<TL;TN;TStep;TPad;>;
   #58 = Utf8               len1
   #59 = Utf8               prep
   #60 = Utf8               len2
   #61 = Utf8               mod
   #62 = Utf8               sum
   #63 = Utf8               min
   #64 = Utf8               take
   #65 = Utf8               grouper
   #66 = Utf8               incompletePaddedGrouper$
   #67 = Utf8               (Lshapeless/ops/hlist$LowPriorityPaddedGrouper;Lshapeless/ops/hlist$Length;Lshapeless/ops/hlist$Prepend;Lshapeless/ops/hlist$Length;Lshapeless/ops/nat$Mod;Lshapeless/ops/nat$Sum;Lshapeless/ops/nat$Min;Lshapeless/ops/hlist$Take;Lshapeless/ops/hlist$Grouper;)Lshapeless/ops/hlist$PaddedGrouper;
   #68 = NameAndType        #66:#67       // incompletePaddedGrouper$:(Lshapeless/ops/hlist$LowPriorityPaddedGrouper;Lshapeless/ops/hlist$Length;Lshapeless/ops/hlist$Prepend;Lshapeless/ops/hlist$Length;Lshapeless/ops/nat$Mod;Lshapeless/ops/nat$Sum;Lshapeless/ops/nat$Min;Lshapeless/ops/hlist$Take;Lshapeless/ops/hlist$Grouper;)Lshapeless/ops/hlist$PaddedGrouper;
   #69 = InterfaceMethodref #6.#68        // shapeless/ops/hlist$LowPriorityPaddedGrouper.incompletePaddedGrouper$:(Lshapeless/ops/hlist$LowPriorityPaddedGrouper;Lshapeless/ops/hlist$Length;Lshapeless/ops/hlist$Prepend;Lshapeless/ops/hlist$Length;Lshapeless/ops/nat$Mod;Lshapeless/ops/nat$Sum;Lshapeless/ops/nat$Min;Lshapeless/ops/hlist$Take;Lshapeless/ops/hlist$Grouper;)Lshapeless/ops/hlist$PaddedGrouper;
   #70 = Utf8               this
   #71 = Utf8               Lshapeless/ops/hlist$Length;
   #72 = Utf8               Lshapeless/ops/hlist$Prepend;
   #73 = Utf8               Lshapeless/ops/nat$Mod;
   #74 = Utf8               Lshapeless/ops/nat$Sum;
   #75 = Utf8               Lshapeless/ops/nat$Min;
   #76 = Utf8               Lshapeless/ops/hlist$Take;
   #77 = Utf8               Lshapeless/ops/hlist$Grouper;
   #78 = Utf8               apply
   #79 = Utf8               (Lshapeless/ops/hlist$PaddedGrouper;)Lshapeless/ops/hlist$PaddedGrouper;
   #80 = Utf8               <L::Lshapeless/HList;N::Lshapeless/Nat;Step::Lshapeless/Nat;Pad::Lshapeless/HList;>(Lshapeless/ops/hlist$PaddedGrouper<TL;TN;TStep;TPad;>;)Lshapeless/ops/hlist$PaddedGrouper<TL;TN;TStep;TPad;>;
   #81 = Utf8               Lshapeless/ops/hlist$PaddedGrouper;
   #82 = Utf8               defaultPaddedGrouper
   #83 = Utf8               (Lshapeless/ops/hlist$Length;Lshapeless/ops/nat$Mod;Lscala/$eq$colon$eq;Lshapeless/ops/hlist$Grouper;)Lshapeless/ops/hlist$PaddedGrouper;
   #84 = Utf8               <L::Lshapeless/HList;N::Lshapeless/Nat;Step::Lshapeless/Nat;Pad::Lshapeless/HList;A::Lshapeless/Nat;B::Lshapeless/Nat;Out0::Lshapeless/HList;>(Lshapeless/ops/hlist$Length<TL;>;Lshapeless/ops/nat$Mod<TA;TStep;>;Lscala/$eq$colon$eq<TB;Lshapeless/_0;>;Lshapeless/ops/hlist$Grouper<TL;TN;TStep;>;)Lshapeless/ops/hlist$PaddedGrouper<TL;TN;TStep;TPad;>;
   #85 = Utf8               len
   #86 = Utf8               eq
   #87 = Utf8               (Lshapeless/ops/hlist$Grouper;)V
   #88 = NameAndType        #46:#87       // "<init>":(Lshapeless/ops/hlist$Grouper;)V
   #89 = Methodref          #24.#88       // shapeless/ops/hlist$PaddedGrouper$$anon$77."<init>":(Lshapeless/ops/hlist$Grouper;)V
   #90 = Utf8               Lscala/$eq$colon$eq;
   #91 = Utf8               writeReplace
   #92 = Utf8               ()Ljava/lang/Object;
   #93 = Utf8               scala/runtime/ModuleSerializationProxy
   #94 = Class              #93           // scala/runtime/ModuleSerializationProxy
   #95 = Utf8               (Ljava/lang/Class;)V
   #96 = NameAndType        #46:#95       // "<init>":(Ljava/lang/Class;)V
   #97 = Methodref          #94.#96       // scala/runtime/ModuleSerializationProxy."<init>":(Ljava/lang/Class;)V
   #98 = Methodref          #4.#47        // java/lang/Object."<init>":()V
   #99 = Utf8               Code
  #100 = Utf8               LineNumberTable
  #101 = Utf8               LocalVariableTable
  #102 = Utf8               Signature
  #103 = Utf8               MethodParameters
  #104 = Utf8               InnerClasses
  #105 = Utf8               SourceFile
  #106 = Utf8               ScalaInlineInfo
  #107 = Utf8               Scala
{
  public static final shapeless.ops.hlist$PaddedGrouper$ MODULE$;
    descriptor: Lshapeless/ops/hlist$PaddedGrouper$;
    flags: (0x0019) ACC_PUBLIC, ACC_STATIC, ACC_FINAL

  public static {};
    descriptor: ()V
    flags: (0x0009) ACC_PUBLIC, ACC_STATIC
    Code:
      stack=2, locals=0, args_size=0
         0: new           #2                  // class shapeless/ops/hlist$PaddedGrouper$
         3: dup
         4: invokespecial #48                 // Method "<init>":()V
         7: putstatic     #50                 // Field MODULE$:Lshapeless/ops/hlist$PaddedGrouper$;
        10: getstatic     #50                 // Field MODULE$:Lshapeless/ops/hlist$PaddedGrouper$;
        13: invokestatic  #54                 // InterfaceMethod shapeless/ops/hlist$LowPriorityPaddedGrouper.$init$:(Lshapeless/ops/hlist$LowPriorityPaddedGrouper;)V
        16: return
      LineNumberTable:
        line 1113: 0

  public <L extends shapeless.HList, N extends shapeless.Nat, Step extends shapeless.Nat, Pad extends shapeless.HList, PL extends shapeless.HList, LPL extends shapeless.Nat, S extends shapeless.Nat, MI extends shapeless.Nat, T extends shapeless.HList, M extends shapeless.Nat, LL extends shapeless.Nat, Out0 extends shapeless.HList> shapeless.ops.hlist$PaddedGrouper<L, N, Step, Pad> incompletePaddedGrouper(shapeless.ops.hlist$Length<L>, shapeless.ops.hlist$Prepend<L, Pad>, shapeless.ops.hlist$Length<PL>, shapeless.ops.nat$Mod<LL, Step>, shapeless.ops.nat$Sum<LL, M>, shapeless.ops.nat$Min<LPL, S>, shapeless.ops.hlist$Take<PL, MI>, shapeless.ops.hlist$Grouper<T, N, Step>);
    descriptor: (Lshapeless/ops/hlist$Length;Lshapeless/ops/hlist$Prepend;Lshapeless/ops/hlist$Length;Lshapeless/ops/nat$Mod;Lshapeless/ops/nat$Sum;Lshapeless/ops/nat$Min;Lshapeless/ops/hlist$Take;Lshapeless/ops/hlist$Grouper;)Lshapeless/ops/hlist$PaddedGrouper;
    flags: (0x0001) ACC_PUBLIC
    Code:
      stack=9, locals=9, args_size=9
         0: aload_0
         1: aload_1
         2: aload_2
         3: aload_3
         4: aload         4
         6: aload         5
         8: aload         6
        10: aload         7
        12: aload         8
        14: invokestatic  #69                 // InterfaceMethod shapeless/ops/hlist$LowPriorityPaddedGrouper.incompletePaddedGrouper$:(Lshapeless/ops/hlist$LowPriorityPaddedGrouper;Lshapeless/ops/hlist$Length;Lshapeless/ops/hlist$Prepend;Lshapeless/ops/hlist$Length;Lshapeless/ops/nat$Mod;Lshapeless/ops/nat$Sum;Lshapeless/ops/nat$Min;Lshapeless/ops/hlist$Take;Lshapeless/ops/hlist$Grouper;)Lshapeless/ops/hlist$PaddedGrouper;
        17: areturn
      LineNumberTable:
        line 1113: 0
      LocalVariableTable:
        Start  Length  Slot  Name   Signature
            0      18     0  this   Lshapeless/ops/hlist$PaddedGrouper$;
            0      18     1  len1   Lshapeless/ops/hlist$Length;
            0      18     2  prep   Lshapeless/ops/hlist$Prepend;
            0      18     3  len2   Lshapeless/ops/hlist$Length;
            0      18     4   mod   Lshapeless/ops/nat$Mod;
            0      18     5   sum   Lshapeless/ops/nat$Sum;
            0      18     6   min   Lshapeless/ops/nat$Min;
            0      18     7  take   Lshapeless/ops/hlist$Take;
            0      18     8 grouper   Lshapeless/ops/hlist$Grouper;
    Signature: #57                          // <L::Lshapeless/HList;N::Lshapeless/Nat;Step::Lshapeless/Nat;Pad::Lshapeless/HList;PL::Lshapeless/HList;LPL::Lshapeless/Nat;S::Lshapeless/Nat;MI::Lshapeless/Nat;T::Lshapeless/HList;M::Lshapeless/Nat;LL::Lshapeless/Nat;Out0::Lshapeless/HList;>(Lshapeless/ops/hlist$Length<TL;>;Lshapeless/ops/hlist$Prepend<TL;TPad;>;Lshapeless/ops/hlist$Length<TPL;>;Lshapeless/ops/nat$Mod<TLL;TStep;>;Lshapeless/ops/nat$Sum<TLL;TM;>;Lshapeless/ops/nat$Min<TLPL;TS;>;Lshapeless/ops/hlist$Take<TPL;TMI;>;Lshapeless/ops/hlist$Grouper<TT;TN;TStep;>;)Lshapeless/ops/hlist$PaddedGrouper<TL;TN;TStep;TPad;>;
    MethodParameters:
      Name                           Flags
      len1                           final
      prep                           final
      len2                           final
      mod                            final
      sum                            final
      min                            final
      take                           final
      grouper                        final

  public <L extends shapeless.HList, N extends shapeless.Nat, Step extends shapeless.Nat, Pad extends shapeless.HList> shapeless.ops.hlist$PaddedGrouper<L, N, Step, Pad> apply(shapeless.ops.hlist$PaddedGrouper<L, N, Step, Pad>);
    descriptor: (Lshapeless/ops/hlist$PaddedGrouper;)Lshapeless/ops/hlist$PaddedGrouper;
    flags: (0x0001) ACC_PUBLIC
    Code:
      stack=1, locals=2, args_size=2
         0: aload_1
         1: areturn
      LineNumberTable:
        line 1116: 0
      LocalVariableTable:
        Start  Length  Slot  Name   Signature
            0       2     0  this   Lshapeless/ops/hlist$PaddedGrouper$;
            0       2     1 grouper   Lshapeless/ops/hlist$PaddedGrouper;
    Signature: #80                          // <L::Lshapeless/HList;N::Lshapeless/Nat;Step::Lshapeless/Nat;Pad::Lshapeless/HList;>(Lshapeless/ops/hlist$PaddedGrouper<TL;TN;TStep;TPad;>;)Lshapeless/ops/hlist$PaddedGrouper<TL;TN;TStep;TPad;>;
    MethodParameters:
      Name                           Flags
      grouper                        final

  public <L extends shapeless.HList, N extends shapeless.Nat, Step extends shapeless.Nat, Pad extends shapeless.HList, A extends shapeless.Nat, B extends shapeless.Nat, Out0 extends shapeless.HList> shapeless.ops.hlist$PaddedGrouper<L, N, Step, Pad> defaultPaddedGrouper(shapeless.ops.hlist$Length<L>, shapeless.ops.nat$Mod<A, Step>, scala.$eq$colon$eq<B, shapeless._0>, shapeless.ops.hlist$Grouper<L, N, Step>);
    descriptor: (Lshapeless/ops/hlist$Length;Lshapeless/ops/nat$Mod;Lscala/$eq$colon$eq;Lshapeless/ops/hlist$Grouper;)Lshapeless/ops/hlist$PaddedGrouper;
    flags: (0x0001) ACC_PUBLIC
    Code:
      stack=3, locals=5, args_size=5
         0: new           #24                 // class shapeless/ops/hlist$PaddedGrouper$$anon$77
         3: dup
         4: aload         4
         6: invokespecial #89                 // Method shapeless/ops/hlist$PaddedGrouper$$anon$77."<init>":(Lshapeless/ops/hlist$Grouper;)V
         9: areturn
      LineNumberTable:
        line 1128: 0
      LocalVariableTable:
        Start  Length  Slot  Name   Signature
            0      10     0  this   Lshapeless/ops/hlist$PaddedGrouper$;
            0      10     1   len   Lshapeless/ops/hlist$Length;
            0      10     2   mod   Lshapeless/ops/nat$Mod;
            0      10     3    eq   Lscala/$eq$colon$eq;
            0      10     4 grouper   Lshapeless/ops/hlist$Grouper;
    Signature: #84                          // <L::Lshapeless/HList;N::Lshapeless/Nat;Step::Lshapeless/Nat;Pad::Lshapeless/HList;A::Lshapeless/Nat;B::Lshapeless/Nat;Out0::Lshapeless/HList;>(Lshapeless/ops/hlist$Length<TL;>;Lshapeless/ops/nat$Mod<TA;TStep;>;Lscala/$eq$colon$eq<TB;Lshapeless/_0;>;Lshapeless/ops/hlist$Grouper<TL;TN;TStep;>;)Lshapeless/ops/hlist$PaddedGrouper<TL;TN;TStep;TPad;>;
    MethodParameters:
      Name                           Flags
      len                            final
      mod                            final
      eq                             final
      grouper                        final

  private java.lang.Object writeReplace();
    descriptor: ()Ljava/lang/Object;
    flags: (0x0002) ACC_PRIVATE
    Code:
      stack=3, locals=1, args_size=1
         0: new           #94                 // class scala/runtime/ModuleSerializationProxy
         3: dup
         4: ldc           #2                  // class shapeless/ops/hlist$PaddedGrouper$
         6: invokespecial #97                 // Method scala/runtime/ModuleSerializationProxy."<init>":(Ljava/lang/Class;)V
         9: areturn
      LineNumberTable:
        line 1113: 0
      LocalVariableTable:
        Start  Length  Slot  Name   Signature
            0      10     0  this   Lshapeless/ops/hlist$PaddedGrouper$;

  public shapeless.ops.hlist$PaddedGrouper$();
    descriptor: ()V
    flags: (0x0001) ACC_PUBLIC
    Code:
      stack=1, locals=1, args_size=1
         0: aload_0
         1: invokespecial #98                 // Method java/lang/Object."<init>":()V
         4: return
      LineNumberTable:
        line 1113: 0
      LocalVariableTable:
        Start  Length  Slot  Name   Signature
            0       5     0  this   Lshapeless/ops/hlist$PaddedGrouper$;
}
InnerClasses:
  public static #14= #11 of #13;          // Grouper=class shapeless/ops/hlist$Grouper of class shapeless/ops/hlist
  public static #17= #16 of #13;          // Length=class shapeless/ops/hlist$Length of class shapeless/ops/hlist
  public static #18= #6 of #13;           // LowPriorityPaddedGrouper=class shapeless/ops/hlist$LowPriorityPaddedGrouper of class shapeless/ops/hlist
  public static #21= #20 of #13;          // PaddedGrouper=class shapeless/ops/hlist$PaddedGrouper of class shapeless/ops/hlist
  public static #22= #2 of #13;           // PaddedGrouper$=class shapeless/ops/hlist$PaddedGrouper$ of class shapeless/ops/hlist
  public final #24;                       // class shapeless/ops/hlist$PaddedGrouper$$anon$77
  public static #27= #26 of #13;          // Prepend=class shapeless/ops/hlist$Prepend of class shapeless/ops/hlist
  public static #30= #29 of #13;          // Take=class shapeless/ops/hlist$Take of class shapeless/ops/hlist
  public static #35= #32 of #34;          // Min=class shapeless/ops/nat$Min of class shapeless/ops/nat
  public static #38= #37 of #34;          // Mod=class shapeless/ops/nat$Mod of class shapeless/ops/nat
  public static #41= #40 of #34;          // Sum=class shapeless/ops/nat$Sum of class shapeless/ops/nat
SourceFile: "hlists.scala"
  ScalaInlineInfo: length = 0x1D (unknown attribute)
   01 01 00 05 00 2E 00 2D 01 00 4E 00 4F 01 00 52
   00 53 01 00 37 00 38 01 00 5B 00 5C 01
  Scala: length = 0x0 (unknown attribute)

