Classfile /Users/mw/Projects/slang-braindump/.jar/jar8/assemble/slang-braindump/assemble/content/shapeless/ops/hlist$ReverseSplitRight$ReverseSplitRight0$.class
  Last modified May 29, 2022; size 3152 bytes
  SHA-256 checksum 7a1fef24560e6d20475d06f929143b79409f12c13ff2ed521a9d57507d0f38b5
  Compiled from "hlists.scala"
public class shapeless.ops.hlist$ReverseSplitRight$ReverseSplitRight0$ implements shapeless.ops.hlist$ReverseSplitRight$LowPriorityReverseSplitRight0,java.io.Serializable
  minor version: 0
  major version: 52
  flags: (0x0021) ACC_PUBLIC, ACC_SUPER
  this_class: #2                          // shapeless/ops/hlist$ReverseSplitRight$ReverseSplitRight0$
  super_class: #4                         // java/lang/Object
  interfaces: 2, fields: 1, methods: 6, attributes: 4
Constant pool:
   #1 = Utf8               shapeless/ops/hlist$ReverseSplitRight$ReverseSplitRight0$
   #2 = Class              #1             // shapeless/ops/hlist$ReverseSplitRight$ReverseSplitRight0$
   #3 = Utf8               java/lang/Object
   #4 = Class              #3             // java/lang/Object
   #5 = Utf8               shapeless/ops/hlist$ReverseSplitRight$LowPriorityReverseSplitRight0
   #6 = Class              #5             // shapeless/ops/hlist$ReverseSplitRight$LowPriorityReverseSplitRight0
   #7 = Utf8               java/io/Serializable
   #8 = Class              #7             // java/io/Serializable
   #9 = Utf8               hlists.scala
  #10 = Utf8               shapeless/ops/hlist$ReverseSplitRight$
  #11 = Class              #10            // shapeless/ops/hlist$ReverseSplitRight$
  #12 = Utf8               shapeless/ops/hlist
  #13 = Class              #12            // shapeless/ops/hlist
  #14 = Utf8               ReverseSplitRight$
  #15 = Utf8               LowPriorityReverseSplitRight0
  #16 = Utf8               shapeless/ops/hlist$ReverseSplitRight$ReverseSplitRight0
  #17 = Class              #16            // shapeless/ops/hlist$ReverseSplitRight$ReverseSplitRight0
  #18 = Utf8               ReverseSplitRight0
  #19 = Utf8               ReverseSplitRight0$
  #20 = Utf8               shapeless/ops/hlist$ReverseSplitRight$ReverseSplitRight0$$anon$127
  #21 = Class              #20            // shapeless/ops/hlist$ReverseSplitRight$ReverseSplitRight0$$anon$127
  #22 = Utf8               MODULE$
  #23 = Utf8               Lshapeless/ops/hlist$ReverseSplitRight$ReverseSplitRight0$;
  #24 = Utf8               <clinit>
  #25 = Utf8               ()V
  #26 = Utf8               <init>
  #27 = NameAndType        #26:#25        // "<init>":()V
  #28 = Methodref          #2.#27         // shapeless/ops/hlist$ReverseSplitRight$ReverseSplitRight0$."<init>":()V
  #29 = NameAndType        #22:#23        // MODULE$:Lshapeless/ops/hlist$ReverseSplitRight$ReverseSplitRight0$;
  #30 = Fieldref           #2.#29         // shapeless/ops/hlist$ReverseSplitRight$ReverseSplitRight0$.MODULE$:Lshapeless/ops/hlist$ReverseSplitRight$ReverseSplitRight0$;
  #31 = Utf8               $init$
  #32 = Utf8               (Lshapeless/ops/hlist$ReverseSplitRight$LowPriorityReverseSplitRight0;)V
  #33 = NameAndType        #31:#32        // $init$:(Lshapeless/ops/hlist$ReverseSplitRight$LowPriorityReverseSplitRight0;)V
  #34 = InterfaceMethodref #6.#33         // shapeless/ops/hlist$ReverseSplitRight$LowPriorityReverseSplitRight0.$init$:(Lshapeless/ops/hlist$ReverseSplitRight$LowPriorityReverseSplitRight0;)V
  #35 = Utf8               hlistReverseSplitRight1
  #36 = Utf8               (Lshapeless/ops/hlist$ReverseSplitRight$ReverseSplitRight0;)Lshapeless/ops/hlist$ReverseSplitRight$ReverseSplitRight0;
  #37 = Utf8               <RevH:Ljava/lang/Object;RevT::Lshapeless/HList;AccP::Lshapeless/HList;U:Ljava/lang/Object;P::Lshapeless/HList;S::Lshapeless/HList;>(Lshapeless/ops/hlist$ReverseSplitRight$ReverseSplitRight0<TRevT;Lshapeless/$colon$colon<TRevH;TAccP;>;Lshapeless/HNil;TU;TP;TS;>;)Lshapeless/ops/hlist$ReverseSplitRight$ReverseSplitRight0<Lshapeless/$colon$colon<TRevH;TRevT;>;TAccP;Lshapeless/HNil;TU;TP;TS;>;
  #38 = Utf8               srt
  #39 = Utf8               hlistReverseSplitRight1$
  #40 = Utf8               (Lshapeless/ops/hlist$ReverseSplitRight$LowPriorityReverseSplitRight0;Lshapeless/ops/hlist$ReverseSplitRight$ReverseSplitRight0;)Lshapeless/ops/hlist$ReverseSplitRight$ReverseSplitRight0;
  #41 = NameAndType        #39:#40        // hlistReverseSplitRight1$:(Lshapeless/ops/hlist$ReverseSplitRight$LowPriorityReverseSplitRight0;Lshapeless/ops/hlist$ReverseSplitRight$ReverseSplitRight0;)Lshapeless/ops/hlist$ReverseSplitRight$ReverseSplitRight0;
  #42 = InterfaceMethodref #6.#41         // shapeless/ops/hlist$ReverseSplitRight$LowPriorityReverseSplitRight0.hlistReverseSplitRight1$:(Lshapeless/ops/hlist$ReverseSplitRight$LowPriorityReverseSplitRight0;Lshapeless/ops/hlist$ReverseSplitRight$ReverseSplitRight0;)Lshapeless/ops/hlist$ReverseSplitRight$ReverseSplitRight0;
  #43 = Utf8               this
  #44 = Utf8               Lshapeless/ops/hlist$ReverseSplitRight$ReverseSplitRight0;
  #45 = Utf8               hlistReverseSplitRight2
  #46 = Utf8               <AccPH:Ljava/lang/Object;AccPT::Lshapeless/HList;AccS::Lshapeless/HList;U:Ljava/lang/Object;P::Lshapeless/HList;S::Lshapeless/HList;>(Lshapeless/ops/hlist$ReverseSplitRight$ReverseSplitRight0<Lshapeless/HNil;TAccPT;Lshapeless/$colon$colon<TAccPH;TAccS;>;TU;TP;TS;>;)Lshapeless/ops/hlist$ReverseSplitRight$ReverseSplitRight0<Lshapeless/HNil;Lshapeless/$colon$colon<TAccPH;TAccPT;>;TAccS;TU;TP;TS;>;
  #47 = Utf8               hlistReverseSplitRight2$
  #48 = NameAndType        #47:#40        // hlistReverseSplitRight2$:(Lshapeless/ops/hlist$ReverseSplitRight$LowPriorityReverseSplitRight0;Lshapeless/ops/hlist$ReverseSplitRight$ReverseSplitRight0;)Lshapeless/ops/hlist$ReverseSplitRight$ReverseSplitRight0;
  #49 = InterfaceMethodref #6.#48         // shapeless/ops/hlist$ReverseSplitRight$LowPriorityReverseSplitRight0.hlistReverseSplitRight2$:(Lshapeless/ops/hlist$ReverseSplitRight$LowPriorityReverseSplitRight0;Lshapeless/ops/hlist$ReverseSplitRight$ReverseSplitRight0;)Lshapeless/ops/hlist$ReverseSplitRight$ReverseSplitRight0;
  #50 = Utf8               hlistReverseSplitRight3
  #51 = Utf8               ()Lshapeless/ops/hlist$ReverseSplitRight$ReverseSplitRight0;
  #52 = Utf8               <PH:Ljava/lang/Object;PT::Lshapeless/HList;S::Lshapeless/HList;>()Lshapeless/ops/hlist$ReverseSplitRight$ReverseSplitRight0<Lshapeless/HNil;Lshapeless/$colon$colon<TPH;TPT;>;TS;TPH;Lshapeless/$colon$colon<TPH;TPT;>;TS;>;
  #53 = Methodref          #21.#27        // shapeless/ops/hlist$ReverseSplitRight$ReverseSplitRight0$$anon$127."<init>":()V
  #54 = Utf8               writeReplace
  #55 = Utf8               ()Ljava/lang/Object;
  #56 = Utf8               scala/runtime/ModuleSerializationProxy
  #57 = Class              #56            // scala/runtime/ModuleSerializationProxy
  #58 = Utf8               (Ljava/lang/Class;)V
  #59 = NameAndType        #26:#58        // "<init>":(Ljava/lang/Class;)V
  #60 = Methodref          #57.#59        // scala/runtime/ModuleSerializationProxy."<init>":(Ljava/lang/Class;)V
  #61 = Methodref          #4.#27         // java/lang/Object."<init>":()V
  #62 = Utf8               Code
  #63 = Utf8               LineNumberTable
  #64 = Utf8               LocalVariableTable
  #65 = Utf8               Signature
  #66 = Utf8               MethodParameters
  #67 = Utf8               InnerClasses
  #68 = Utf8               SourceFile
  #69 = Utf8               ScalaInlineInfo
  #70 = Utf8               Scala
{
  public static final shapeless.ops.hlist$ReverseSplitRight$ReverseSplitRight0$ MODULE$;
    descriptor: Lshapeless/ops/hlist$ReverseSplitRight$ReverseSplitRight0$;
    flags: (0x0019) ACC_PUBLIC, ACC_STATIC, ACC_FINAL

  public static {};
    descriptor: ()V
    flags: (0x0009) ACC_PUBLIC, ACC_STATIC
    Code:
      stack=2, locals=0, args_size=0
         0: new           #2                  // class shapeless/ops/hlist$ReverseSplitRight$ReverseSplitRight0$
         3: dup
         4: invokespecial #28                 // Method "<init>":()V
         7: putstatic     #30                 // Field MODULE$:Lshapeless/ops/hlist$ReverseSplitRight$ReverseSplitRight0$;
        10: getstatic     #30                 // Field MODULE$:Lshapeless/ops/hlist$ReverseSplitRight$ReverseSplitRight0$;
        13: invokestatic  #34                 // InterfaceMethod shapeless/ops/hlist$ReverseSplitRight$LowPriorityReverseSplitRight0.$init$:(Lshapeless/ops/hlist$ReverseSplitRight$LowPriorityReverseSplitRight0;)V
        16: return
      LineNumberTable:
        line 1944: 0

  public <RevH extends java.lang.Object, RevT extends shapeless.HList, AccP extends shapeless.HList, U extends java.lang.Object, P extends shapeless.HList, S extends shapeless.HList> shapeless.ops.hlist$ReverseSplitRight$ReverseSplitRight0<shapeless.$colon$colon<RevH, RevT>, AccP, shapeless.HNil, U, P, S> hlistReverseSplitRight1(shapeless.ops.hlist$ReverseSplitRight$ReverseSplitRight0<RevT, shapeless.$colon$colon<RevH, AccP>, shapeless.HNil, U, P, S>);
    descriptor: (Lshapeless/ops/hlist$ReverseSplitRight$ReverseSplitRight0;)Lshapeless/ops/hlist$ReverseSplitRight$ReverseSplitRight0;
    flags: (0x0001) ACC_PUBLIC
    Code:
      stack=2, locals=2, args_size=2
         0: aload_0
         1: aload_1
         2: invokestatic  #42                 // InterfaceMethod shapeless/ops/hlist$ReverseSplitRight$LowPriorityReverseSplitRight0.hlistReverseSplitRight1$:(Lshapeless/ops/hlist$ReverseSplitRight$LowPriorityReverseSplitRight0;Lshapeless/ops/hlist$ReverseSplitRight$ReverseSplitRight0;)Lshapeless/ops/hlist$ReverseSplitRight$ReverseSplitRight0;
         5: areturn
      LineNumberTable:
        line 1944: 0
      LocalVariableTable:
        Start  Length  Slot  Name   Signature
            0       6     0  this   Lshapeless/ops/hlist$ReverseSplitRight$ReverseSplitRight0$;
            0       6     1   srt   Lshapeless/ops/hlist$ReverseSplitRight$ReverseSplitRight0;
    Signature: #37                          // <RevH:Ljava/lang/Object;RevT::Lshapeless/HList;AccP::Lshapeless/HList;U:Ljava/lang/Object;P::Lshapeless/HList;S::Lshapeless/HList;>(Lshapeless/ops/hlist$ReverseSplitRight$ReverseSplitRight0<TRevT;Lshapeless/$colon$colon<TRevH;TAccP;>;Lshapeless/HNil;TU;TP;TS;>;)Lshapeless/ops/hlist$ReverseSplitRight$ReverseSplitRight0<Lshapeless/$colon$colon<TRevH;TRevT;>;TAccP;Lshapeless/HNil;TU;TP;TS;>;
    MethodParameters:
      Name                           Flags
      srt                            final

  public <AccPH extends java.lang.Object, AccPT extends shapeless.HList, AccS extends shapeless.HList, U extends java.lang.Object, P extends shapeless.HList, S extends shapeless.HList> shapeless.ops.hlist$ReverseSplitRight$ReverseSplitRight0<shapeless.HNil, shapeless.$colon$colon<AccPH, AccPT>, AccS, U, P, S> hlistReverseSplitRight2(shapeless.ops.hlist$ReverseSplitRight$ReverseSplitRight0<shapeless.HNil, AccPT, shapeless.$colon$colon<AccPH, AccS>, U, P, S>);
    descriptor: (Lshapeless/ops/hlist$ReverseSplitRight$ReverseSplitRight0;)Lshapeless/ops/hlist$ReverseSplitRight$ReverseSplitRight0;
    flags: (0x0001) ACC_PUBLIC
    Code:
      stack=2, locals=2, args_size=2
         0: aload_0
         1: aload_1
         2: invokestatic  #49                 // InterfaceMethod shapeless/ops/hlist$ReverseSplitRight$LowPriorityReverseSplitRight0.hlistReverseSplitRight2$:(Lshapeless/ops/hlist$ReverseSplitRight$LowPriorityReverseSplitRight0;Lshapeless/ops/hlist$ReverseSplitRight$ReverseSplitRight0;)Lshapeless/ops/hlist$ReverseSplitRight$ReverseSplitRight0;
         5: areturn
      LineNumberTable:
        line 1944: 0
      LocalVariableTable:
        Start  Length  Slot  Name   Signature
            0       6     0  this   Lshapeless/ops/hlist$ReverseSplitRight$ReverseSplitRight0$;
            0       6     1   srt   Lshapeless/ops/hlist$ReverseSplitRight$ReverseSplitRight0;
    Signature: #46                          // <AccPH:Ljava/lang/Object;AccPT::Lshapeless/HList;AccS::Lshapeless/HList;U:Ljava/lang/Object;P::Lshapeless/HList;S::Lshapeless/HList;>(Lshapeless/ops/hlist$ReverseSplitRight$ReverseSplitRight0<Lshapeless/HNil;TAccPT;Lshapeless/$colon$colon<TAccPH;TAccS;>;TU;TP;TS;>;)Lshapeless/ops/hlist$ReverseSplitRight$ReverseSplitRight0<Lshapeless/HNil;Lshapeless/$colon$colon<TAccPH;TAccPT;>;TAccS;TU;TP;TS;>;
    MethodParameters:
      Name                           Flags
      srt                            final

  public <PH extends java.lang.Object, PT extends shapeless.HList, S extends shapeless.HList> shapeless.ops.hlist$ReverseSplitRight$ReverseSplitRight0<shapeless.HNil, shapeless.$colon$colon<PH, PT>, S, PH, shapeless.$colon$colon<PH, PT>, S> hlistReverseSplitRight3();
    descriptor: ()Lshapeless/ops/hlist$ReverseSplitRight$ReverseSplitRight0;
    flags: (0x0001) ACC_PUBLIC
    Code:
      stack=2, locals=1, args_size=1
         0: new           #21                 // class shapeless/ops/hlist$ReverseSplitRight$ReverseSplitRight0$$anon$127
         3: dup
         4: invokespecial #53                 // Method shapeless/ops/hlist$ReverseSplitRight$ReverseSplitRight0$$anon$127."<init>":()V
         7: areturn
      LineNumberTable:
        line 1946: 0
      LocalVariableTable:
        Start  Length  Slot  Name   Signature
            0       8     0  this   Lshapeless/ops/hlist$ReverseSplitRight$ReverseSplitRight0$;
    Signature: #52                          // <PH:Ljava/lang/Object;PT::Lshapeless/HList;S::Lshapeless/HList;>()Lshapeless/ops/hlist$ReverseSplitRight$ReverseSplitRight0<Lshapeless/HNil;Lshapeless/$colon$colon<TPH;TPT;>;TS;TPH;Lshapeless/$colon$colon<TPH;TPT;>;TS;>;

  private java.lang.Object writeReplace();
    descriptor: ()Ljava/lang/Object;
    flags: (0x0002) ACC_PRIVATE
    Code:
      stack=3, locals=1, args_size=1
         0: new           #57                 // class scala/runtime/ModuleSerializationProxy
         3: dup
         4: ldc           #2                  // class shapeless/ops/hlist$ReverseSplitRight$ReverseSplitRight0$
         6: invokespecial #60                 // Method scala/runtime/ModuleSerializationProxy."<init>":(Ljava/lang/Class;)V
         9: areturn
      LineNumberTable:
        line 1944: 0
      LocalVariableTable:
        Start  Length  Slot  Name   Signature
            0      10     0  this   Lshapeless/ops/hlist$ReverseSplitRight$ReverseSplitRight0$;

  public shapeless.ops.hlist$ReverseSplitRight$ReverseSplitRight0$();
    descriptor: ()V
    flags: (0x0001) ACC_PUBLIC
    Code:
      stack=1, locals=1, args_size=1
         0: aload_0
         1: invokespecial #61                 // Method java/lang/Object."<init>":()V
         4: return
      LineNumberTable:
        line 1944: 0
      LocalVariableTable:
        Start  Length  Slot  Name   Signature
            0       5     0  this   Lshapeless/ops/hlist$ReverseSplitRight$ReverseSplitRight0$;
}
InnerClasses:
  public static #14= #11 of #13;          // ReverseSplitRight$=class shapeless/ops/hlist$ReverseSplitRight$ of class shapeless/ops/hlist
  public static #15= #6 of #11;           // LowPriorityReverseSplitRight0=class shapeless/ops/hlist$ReverseSplitRight$LowPriorityReverseSplitRight0 of class shapeless/ops/hlist$ReverseSplitRight$
  public static #18= #17 of #11;          // ReverseSplitRight0=class shapeless/ops/hlist$ReverseSplitRight$ReverseSplitRight0 of class shapeless/ops/hlist$ReverseSplitRight$
  public static #19= #2 of #11;           // ReverseSplitRight0$=class shapeless/ops/hlist$ReverseSplitRight$ReverseSplitRight0$ of class shapeless/ops/hlist$ReverseSplitRight$
  public final #21;                       // class shapeless/ops/hlist$ReverseSplitRight$ReverseSplitRight0$$anon$127
SourceFile: "hlists.scala"
  ScalaInlineInfo: length = 0x1D (unknown attribute)
   01 01 00 05 00 1A 00 19 01 00 23 00 24 01 00 2D
   00 24 01 00 32 00 33 01 00 36 00 37 01
  Scala: length = 0x0 (unknown attribute)

