Classfile /Users/mw/Projects/slang-braindump/.jar/jar8/assemble/slang-braindump/assemble/content/shapeless/ops/hlist$MapCons$.class
  Last modified May 29, 2022; size 1791 bytes
  SHA-256 checksum c887bba63e47efef2223339501e6b39f8ef0f7388d621e2872b9342fb45c740a
  Compiled from "hlists.scala"
public class shapeless.ops.hlist$MapCons$ implements java.io.Serializable
  minor version: 0
  major version: 52
  flags: (0x0021) ACC_PUBLIC, ACC_SUPER
  this_class: #2                          // shapeless/ops/hlist$MapCons$
  super_class: #4                         // java/lang/Object
  interfaces: 1, fields: 1, methods: 6, attributes: 4
Constant pool:
   #1 = Utf8               shapeless/ops/hlist$MapCons$
   #2 = Class              #1             // shapeless/ops/hlist$MapCons$
   #3 = Utf8               java/lang/Object
   #4 = Class              #3             // java/lang/Object
   #5 = Utf8               java/io/Serializable
   #6 = Class              #5             // java/io/Serializable
   #7 = Utf8               hlists.scala
   #8 = Utf8               shapeless/ops/hlist$MapCons
   #9 = Class              #8             // shapeless/ops/hlist$MapCons
  #10 = Utf8               shapeless/ops/hlist
  #11 = Class              #10            // shapeless/ops/hlist
  #12 = Utf8               MapCons
  #13 = Utf8               MapCons$
  #14 = Utf8               shapeless/ops/hlist$MapCons$$anon$166
  #15 = Class              #14            // shapeless/ops/hlist$MapCons$$anon$166
  #16 = Utf8               shapeless/ops/hlist$MapCons$$anon$167
  #17 = Class              #16            // shapeless/ops/hlist$MapCons$$anon$167
  #18 = Utf8               MODULE$
  #19 = Utf8               Lshapeless/ops/hlist$MapCons$;
  #20 = Utf8               <clinit>
  #21 = Utf8               ()V
  #22 = Utf8               <init>
  #23 = NameAndType        #22:#21        // "<init>":()V
  #24 = Methodref          #2.#23         // shapeless/ops/hlist$MapCons$."<init>":()V
  #25 = NameAndType        #18:#19        // MODULE$:Lshapeless/ops/hlist$MapCons$;
  #26 = Fieldref           #2.#25         // shapeless/ops/hlist$MapCons$.MODULE$:Lshapeless/ops/hlist$MapCons$;
  #27 = Utf8               apply
  #28 = Utf8               (Lshapeless/ops/hlist$MapCons;)Lshapeless/ops/hlist$MapCons;
  #29 = Utf8               <A:Ljava/lang/Object;M::Lshapeless/HList;>(Lshapeless/ops/hlist$MapCons<TA;TM;>;)Lshapeless/ops/hlist$MapCons<TA;TM;>;
  #30 = Utf8               mapCons
  #31 = Utf8               this
  #32 = Utf8               Lshapeless/ops/hlist$MapCons;
  #33 = Utf8               hnilMapCons
  #34 = Utf8               ()Lshapeless/ops/hlist$MapCons;
  #35 = Utf8               <A:Ljava/lang/Object;>()Lshapeless/ops/hlist$MapCons<TA;Lshapeless/HNil;>;
  #36 = Methodref          #15.#23        // shapeless/ops/hlist$MapCons$$anon$166."<init>":()V
  #37 = Utf8               hlistMapCons
  #38 = Utf8               <A:Ljava/lang/Object;H::Lshapeless/HList;TM::Lshapeless/HList;MapConsOut::Lshapeless/HList;>(Lshapeless/ops/hlist$MapCons<TA;TTM;>;)Lshapeless/ops/hlist$MapCons<TA;Lshapeless/$colon$colon<TH;TTM;>;>;
  #39 = Utf8               (Lshapeless/ops/hlist$MapCons;)V
  #40 = NameAndType        #22:#39        // "<init>":(Lshapeless/ops/hlist$MapCons;)V
  #41 = Methodref          #17.#40        // shapeless/ops/hlist$MapCons$$anon$167."<init>":(Lshapeless/ops/hlist$MapCons;)V
  #42 = Utf8               writeReplace
  #43 = Utf8               ()Ljava/lang/Object;
  #44 = Utf8               scala/runtime/ModuleSerializationProxy
  #45 = Class              #44            // scala/runtime/ModuleSerializationProxy
  #46 = Utf8               (Ljava/lang/Class;)V
  #47 = NameAndType        #22:#46        // "<init>":(Ljava/lang/Class;)V
  #48 = Methodref          #45.#47        // scala/runtime/ModuleSerializationProxy."<init>":(Ljava/lang/Class;)V
  #49 = Methodref          #4.#23         // java/lang/Object."<init>":()V
  #50 = Utf8               Code
  #51 = Utf8               LineNumberTable
  #52 = Utf8               LocalVariableTable
  #53 = Utf8               Signature
  #54 = Utf8               MethodParameters
  #55 = Utf8               InnerClasses
  #56 = Utf8               SourceFile
  #57 = Utf8               ScalaInlineInfo
  #58 = Utf8               Scala
{
  public static final shapeless.ops.hlist$MapCons$ MODULE$;
    descriptor: Lshapeless/ops/hlist$MapCons$;
    flags: (0x0019) ACC_PUBLIC, ACC_STATIC, ACC_FINAL

  public static {};
    descriptor: ()V
    flags: (0x0009) ACC_PUBLIC, ACC_STATIC
    Code:
      stack=2, locals=0, args_size=0
         0: new           #2                  // class shapeless/ops/hlist$MapCons$
         3: dup
         4: invokespecial #24                 // Method "<init>":()V
         7: putstatic     #26                 // Field MODULE$:Lshapeless/ops/hlist$MapCons$;
        10: return
      LineNumberTable:
        line 2479: 0

  public <A extends java.lang.Object, M extends shapeless.HList> shapeless.ops.hlist$MapCons<A, M> apply(shapeless.ops.hlist$MapCons<A, M>);
    descriptor: (Lshapeless/ops/hlist$MapCons;)Lshapeless/ops/hlist$MapCons;
    flags: (0x0001) ACC_PUBLIC
    Code:
      stack=1, locals=2, args_size=2
         0: aload_1
         1: areturn
      LineNumberTable:
        line 2480: 0
      LocalVariableTable:
        Start  Length  Slot  Name   Signature
            0       2     0  this   Lshapeless/ops/hlist$MapCons$;
            0       2     1 mapCons   Lshapeless/ops/hlist$MapCons;
    Signature: #29                          // <A:Ljava/lang/Object;M::Lshapeless/HList;>(Lshapeless/ops/hlist$MapCons<TA;TM;>;)Lshapeless/ops/hlist$MapCons<TA;TM;>;
    MethodParameters:
      Name                           Flags
      mapCons                        final

  public <A extends java.lang.Object> shapeless.ops.hlist$MapCons<A, shapeless.HNil> hnilMapCons();
    descriptor: ()Lshapeless/ops/hlist$MapCons;
    flags: (0x0001) ACC_PUBLIC
    Code:
      stack=2, locals=1, args_size=1
         0: new           #15                 // class shapeless/ops/hlist$MapCons$$anon$166
         3: dup
         4: invokespecial #36                 // Method shapeless/ops/hlist$MapCons$$anon$166."<init>":()V
         7: areturn
      LineNumberTable:
        line 2485: 0
      LocalVariableTable:
        Start  Length  Slot  Name   Signature
            0       8     0  this   Lshapeless/ops/hlist$MapCons$;
    Signature: #35                          // <A:Ljava/lang/Object;>()Lshapeless/ops/hlist$MapCons<TA;Lshapeless/HNil;>;

  public <A extends java.lang.Object, H extends shapeless.HList, TM extends shapeless.HList, MapConsOut extends shapeless.HList> shapeless.ops.hlist$MapCons<A, shapeless.$colon$colon<H, TM>> hlistMapCons(shapeless.ops.hlist$MapCons<A, TM>);
    descriptor: (Lshapeless/ops/hlist$MapCons;)Lshapeless/ops/hlist$MapCons;
    flags: (0x0001) ACC_PUBLIC
    Code:
      stack=3, locals=2, args_size=2
         0: new           #17                 // class shapeless/ops/hlist$MapCons$$anon$167
         3: dup
         4: aload_1
         5: invokespecial #41                 // Method shapeless/ops/hlist$MapCons$$anon$167."<init>":(Lshapeless/ops/hlist$MapCons;)V
         8: areturn
      LineNumberTable:
        line 2493: 0
      LocalVariableTable:
        Start  Length  Slot  Name   Signature
            0       9     0  this   Lshapeless/ops/hlist$MapCons$;
            0       9     1 mapCons   Lshapeless/ops/hlist$MapCons;
    Signature: #38                          // <A:Ljava/lang/Object;H::Lshapeless/HList;TM::Lshapeless/HList;MapConsOut::Lshapeless/HList;>(Lshapeless/ops/hlist$MapCons<TA;TTM;>;)Lshapeless/ops/hlist$MapCons<TA;Lshapeless/$colon$colon<TH;TTM;>;>;
    MethodParameters:
      Name                           Flags
      mapCons                        final

  private java.lang.Object writeReplace();
    descriptor: ()Ljava/lang/Object;
    flags: (0x0002) ACC_PRIVATE
    Code:
      stack=3, locals=1, args_size=1
         0: new           #45                 // class scala/runtime/ModuleSerializationProxy
         3: dup
         4: ldc           #2                  // class shapeless/ops/hlist$MapCons$
         6: invokespecial #48                 // Method scala/runtime/ModuleSerializationProxy."<init>":(Ljava/lang/Class;)V
         9: areturn
      LineNumberTable:
        line 2479: 0
      LocalVariableTable:
        Start  Length  Slot  Name   Signature
            0      10     0  this   Lshapeless/ops/hlist$MapCons$;

  public shapeless.ops.hlist$MapCons$();
    descriptor: ()V
    flags: (0x0001) ACC_PUBLIC
    Code:
      stack=1, locals=1, args_size=1
         0: aload_0
         1: invokespecial #49                 // Method java/lang/Object."<init>":()V
         4: return
      LineNumberTable:
        line 2505: 0
        line 2479: 4
      LocalVariableTable:
        Start  Length  Slot  Name   Signature
            0       5     0  this   Lshapeless/ops/hlist$MapCons$;
}
InnerClasses:
  public static #12= #9 of #11;           // MapCons=class shapeless/ops/hlist$MapCons of class shapeless/ops/hlist
  public static #13= #2 of #11;           // MapCons$=class shapeless/ops/hlist$MapCons$ of class shapeless/ops/hlist
  public final #15;                       // class shapeless/ops/hlist$MapCons$$anon$166
  public final #17;                       // class shapeless/ops/hlist$MapCons$$anon$167
SourceFile: "hlists.scala"
  ScalaInlineInfo: length = 0x1D (unknown attribute)
   01 01 00 05 00 16 00 15 01 00 1B 00 1C 01 00 25
   00 1C 01 00 21 00 22 01 00 2A 00 2B 01
  Scala: length = 0x0 (unknown attribute)

