Classfile /Users/mw/Projects/slang-braindump/.jar/jar8/assemble/slang-braindump/assemble/content/shapeless/ops/hlist$LowPriorityToCoproductTraversable.class
  Last modified May 29, 2022; size 2575 bytes
  SHA-256 checksum 726141002130c3b8d32ae1058fc6dbfdb56a2f3a6f2c3806534dc9b79738be56
  Compiled from "hlists.scala"
public interface shapeless.ops.hlist$LowPriorityToCoproductTraversable
  minor version: 0
  major version: 52
  flags: (0x0601) ACC_PUBLIC, ACC_INTERFACE, ACC_ABSTRACT
  this_class: #2                          // shapeless/ops/hlist$LowPriorityToCoproductTraversable
  super_class: #4                         // java/lang/Object
  interfaces: 0, fields: 0, methods: 4, attributes: 4
Constant pool:
   #1 = Utf8               shapeless/ops/hlist$LowPriorityToCoproductTraversable
   #2 = Class              #1             // shapeless/ops/hlist$LowPriorityToCoproductTraversable
   #3 = Utf8               java/lang/Object
   #4 = Class              #3             // java/lang/Object
   #5 = Utf8               hlists.scala
   #6 = Utf8               shapeless/ops/coproduct$Inject
   #7 = Class              #6             // shapeless/ops/coproduct$Inject
   #8 = Utf8               shapeless/ops/coproduct
   #9 = Class              #8             // shapeless/ops/coproduct
  #10 = Utf8               Inject
  #11 = Utf8               shapeless/ops/hlist
  #12 = Class              #11            // shapeless/ops/hlist
  #13 = Utf8               LowPriorityToCoproductTraversable
  #14 = Utf8               shapeless/ops/hlist$LowPriorityToCoproductTraversable$$anon$52
  #15 = Class              #14            // shapeless/ops/hlist$LowPriorityToCoproductTraversable$$anon$52
  #16 = Utf8               shapeless/ops/hlist$LowPriorityToCoproductTraversable$NotIn
  #17 = Class              #16            // shapeless/ops/hlist$LowPriorityToCoproductTraversable$NotIn
  #18 = Utf8               NotIn
  #19 = Utf8               shapeless/ops/hlist$LowPriorityToCoproductTraversable$NotIn$
  #20 = Class              #19            // shapeless/ops/hlist$LowPriorityToCoproductTraversable$NotIn$
  #21 = Utf8               NotIn$
  #22 = Utf8               shapeless/ops/hlist$ToCoproductTraversable
  #23 = Class              #22            // shapeless/ops/hlist$ToCoproductTraversable
  #24 = Utf8               ToCoproductTraversable
  #25 = Utf8               ()Lshapeless/ops/hlist$LowPriorityToCoproductTraversable$NotIn$;
  #26 = Utf8               hconsToCoproductTraversable1$
  #27 = Utf8               (Lshapeless/ops/hlist$LowPriorityToCoproductTraversable;Lshapeless/ops/hlist$ToCoproductTraversable;Lscala/collection/Factory;Lscala/$less$colon$less;Lshapeless/ops/coproduct$Inject;)Lshapeless/ops/hlist$ToCoproductTraversable;
  #28 = Utf8               $this
  #29 = Utf8               coproductOfT
  #30 = Utf8               cbf
  #31 = Utf8               asTraversable
  #32 = Utf8               injectOut
  #33 = Utf8               hconsToCoproductTraversable1
  #34 = Utf8               (Lshapeless/ops/hlist$ToCoproductTraversable;Lscala/collection/Factory;Lscala/$less$colon$less;Lshapeless/ops/coproduct$Inject;)Lshapeless/ops/hlist$ToCoproductTraversable;
  #35 = NameAndType        #33:#34        // hconsToCoproductTraversable1:(Lshapeless/ops/hlist$ToCoproductTraversable;Lscala/collection/Factory;Lscala/$less$colon$less;Lshapeless/ops/coproduct$Inject;)Lshapeless/ops/hlist$ToCoproductTraversable;
  #36 = InterfaceMethodref #2.#35         // shapeless/ops/hlist$LowPriorityToCoproductTraversable.hconsToCoproductTraversable1:(Lshapeless/ops/hlist$ToCoproductTraversable;Lscala/collection/Factory;Lscala/$less$colon$less;Lshapeless/ops/coproduct$Inject;)Lshapeless/ops/hlist$ToCoproductTraversable;
  #37 = Utf8               Lshapeless/ops/hlist$LowPriorityToCoproductTraversable;
  #38 = Utf8               Lshapeless/ops/hlist$ToCoproductTraversable;
  #39 = Utf8               Lscala/collection/Factory;
  #40 = Utf8               Lscala/$less$colon$less;
  #41 = Utf8               Lshapeless/ops/coproduct$Inject;
  #42 = Utf8               <LH:Ljava/lang/Object;LT::Lshapeless/HList;M:Ljava/lang/Object;CT::Lshapeless/Coproduct;>(Lshapeless/ops/hlist$ToCoproductTraversable<TLT;TM;>;Lscala/collection/Factory<TCT;TM;>;Lscala/$less$colon$less<TM;Lscala/collection/Iterable<TCT;>;>;Lshapeless/ops/coproduct$Inject<TCT;TLH;>;)Lshapeless/ops/hlist$ToCoproductTraversable<Lshapeless/$colon$colon<TLH;TLT;>;TM;>;
  #43 = Utf8               <init>
  #44 = Utf8               (Lshapeless/ops/hlist$LowPriorityToCoproductTraversable;Lscala/collection/Factory;Lshapeless/ops/coproduct$Inject;Lscala/$less$colon$less;Lshapeless/ops/hlist$ToCoproductTraversable;)V
  #45 = NameAndType        #43:#44        // "<init>":(Lshapeless/ops/hlist$LowPriorityToCoproductTraversable;Lscala/collection/Factory;Lshapeless/ops/coproduct$Inject;Lscala/$less$colon$less;Lshapeless/ops/hlist$ToCoproductTraversable;)V
  #46 = Methodref          #15.#45        // shapeless/ops/hlist$LowPriorityToCoproductTraversable$$anon$52."<init>":(Lshapeless/ops/hlist$LowPriorityToCoproductTraversable;Lscala/collection/Factory;Lshapeless/ops/coproduct$Inject;Lscala/$less$colon$less;Lshapeless/ops/hlist$ToCoproductTraversable;)V
  #47 = Utf8               this
  #48 = Utf8               $init$
  #49 = Utf8               (Lshapeless/ops/hlist$LowPriorityToCoproductTraversable;)V
  #50 = Utf8               Code
  #51 = Utf8               LineNumberTable
  #52 = Utf8               LocalVariableTable
  #53 = Utf8               MethodParameters
  #54 = Utf8               Signature
  #55 = Utf8               InnerClasses
  #56 = Utf8               SourceFile
  #57 = Utf8               ScalaInlineInfo
  #58 = Utf8               Scala
{
  public abstract shapeless.ops.hlist$LowPriorityToCoproductTraversable$NotIn$ NotIn();
    descriptor: ()Lshapeless/ops/hlist$LowPriorityToCoproductTraversable$NotIn$;
    flags: (0x0401) ACC_PUBLIC, ACC_ABSTRACT

  public static shapeless.ops.hlist$ToCoproductTraversable hconsToCoproductTraversable1$(shapeless.ops.hlist$LowPriorityToCoproductTraversable, shapeless.ops.hlist$ToCoproductTraversable, scala.collection.Factory, scala.$less$colon$less, shapeless.ops.coproduct$Inject);
    descriptor: (Lshapeless/ops/hlist$LowPriorityToCoproductTraversable;Lshapeless/ops/hlist$ToCoproductTraversable;Lscala/collection/Factory;Lscala/$less$colon$less;Lshapeless/ops/coproduct$Inject;)Lshapeless/ops/hlist$ToCoproductTraversable;
    flags: (0x1009) ACC_PUBLIC, ACC_STATIC, ACC_SYNTHETIC
    Code:
      stack=5, locals=5, args_size=5
         0: aload_0
         1: aload_1
         2: aload_2
         3: aload_3
         4: aload         4
         6: invokespecial #36                 // InterfaceMethod hconsToCoproductTraversable1:(Lshapeless/ops/hlist$ToCoproductTraversable;Lscala/collection/Factory;Lscala/$less$colon$less;Lshapeless/ops/coproduct$Inject;)Lshapeless/ops/hlist$ToCoproductTraversable;
         9: areturn
      LineNumberTable:
        line 668: 0
      LocalVariableTable:
        Start  Length  Slot  Name   Signature
            0      10     0 $this   Lshapeless/ops/hlist$LowPriorityToCoproductTraversable;
            0      10     1 coproductOfT   Lshapeless/ops/hlist$ToCoproductTraversable;
            0      10     2   cbf   Lscala/collection/Factory;
            0      10     3 asTraversable   Lscala/$less$colon$less;
            0      10     4 injectOut   Lshapeless/ops/coproduct$Inject;
    MethodParameters:
      Name                           Flags
      $this                          final synthetic
      coproductOfT                   final
      cbf                            final
      asTraversable                  final
      injectOut                      final

  public default <LH extends java.lang.Object, LT extends shapeless.HList, M extends java.lang.Object, CT extends shapeless.Coproduct> shapeless.ops.hlist$ToCoproductTraversable<shapeless.$colon$colon<LH, LT>, M> hconsToCoproductTraversable1(shapeless.ops.hlist$ToCoproductTraversable<LT, M>, scala.collection.Factory<CT, M>, scala.$less$colon$less<M, scala.collection.Iterable<CT>>, shapeless.ops.coproduct$Inject<CT, LH>);
    descriptor: (Lshapeless/ops/hlist$ToCoproductTraversable;Lscala/collection/Factory;Lscala/$less$colon$less;Lshapeless/ops/coproduct$Inject;)Lshapeless/ops/hlist$ToCoproductTraversable;
    flags: (0x0001) ACC_PUBLIC
    Code:
      stack=7, locals=5, args_size=5
         0: new           #15                 // class shapeless/ops/hlist$LowPriorityToCoproductTraversable$$anon$52
         3: dup
         4: aconst_null
         5: aload_2
         6: aload         4
         8: aload_3
         9: aload_1
        10: invokespecial #46                 // Method shapeless/ops/hlist$LowPriorityToCoproductTraversable$$anon$52."<init>":(Lshapeless/ops/hlist$LowPriorityToCoproductTraversable;Lscala/collection/Factory;Lshapeless/ops/coproduct$Inject;Lscala/$less$colon$less;Lshapeless/ops/hlist$ToCoproductTraversable;)V
        13: areturn
      LineNumberTable:
        line 674: 0
      LocalVariableTable:
        Start  Length  Slot  Name   Signature
            0      14     0  this   Lshapeless/ops/hlist$LowPriorityToCoproductTraversable;
            0      14     1 coproductOfT   Lshapeless/ops/hlist$ToCoproductTraversable;
            0      14     2   cbf   Lscala/collection/Factory;
            0      14     3 asTraversable   Lscala/$less$colon$less;
            0      14     4 injectOut   Lshapeless/ops/coproduct$Inject;
    Signature: #42                          // <LH:Ljava/lang/Object;LT::Lshapeless/HList;M:Ljava/lang/Object;CT::Lshapeless/Coproduct;>(Lshapeless/ops/hlist$ToCoproductTraversable<TLT;TM;>;Lscala/collection/Factory<TCT;TM;>;Lscala/$less$colon$less<TM;Lscala/collection/Iterable<TCT;>;>;Lshapeless/ops/coproduct$Inject<TCT;TLH;>;)Lshapeless/ops/hlist$ToCoproductTraversable<Lshapeless/$colon$colon<TLH;TLT;>;TM;>;
    MethodParameters:
      Name                           Flags
      coproductOfT                   final
      cbf                            final
      asTraversable                  final
      injectOut                      final

  public static void $init$(shapeless.ops.hlist$LowPriorityToCoproductTraversable);
    descriptor: (Lshapeless/ops/hlist$LowPriorityToCoproductTraversable;)V
    flags: (0x0009) ACC_PUBLIC, ACC_STATIC
    Code:
      stack=0, locals=1, args_size=1
         0: return
      LineNumberTable:
        line 651: 0
      LocalVariableTable:
        Start  Length  Slot  Name   Signature
            0       1     0 $this   Lshapeless/ops/hlist$LowPriorityToCoproductTraversable;
    MethodParameters:
      Name                           Flags
      $this                          final synthetic
}
InnerClasses:
  public static #10= #7 of #9;            // Inject=class shapeless/ops/coproduct$Inject of class shapeless/ops/coproduct
  public static #13= #2 of #12;           // LowPriorityToCoproductTraversable=class shapeless/ops/hlist$LowPriorityToCoproductTraversable of class shapeless/ops/hlist
  public final #15;                       // class shapeless/ops/hlist$LowPriorityToCoproductTraversable$$anon$52
  public #18= #17 of #2;                  // NotIn=class shapeless/ops/hlist$LowPriorityToCoproductTraversable$NotIn of class shapeless/ops/hlist$LowPriorityToCoproductTraversable
  public #21= #20 of #2;                  // NotIn$=class shapeless/ops/hlist$LowPriorityToCoproductTraversable$NotIn$ of class shapeless/ops/hlist$LowPriorityToCoproductTraversable
  public static #24= #23 of #12;          // ToCoproductTraversable=class shapeless/ops/hlist$ToCoproductTraversable of class shapeless/ops/hlist
SourceFile: "hlists.scala"
  ScalaInlineInfo: length = 0x18 (unknown attribute)
   01 00 00 04 00 30 00 31 01 00 12 00 19 00 00 1A
   00 1B 01 00 21 00 22 00
  Scala: length = 0x0 (unknown attribute)

