Classfile /Users/mw/Projects/slang-braindump/.jar/jar8/assemble/slang-braindump/assemble/content/shapeless/ops/hlist$Grouper$.class
  Last modified May 29, 2022; size 3628 bytes
  SHA-256 checksum 0963948495e9fb8252a7c27ecd68dfe55c01cba2763dea299ac896516eaa60b6
  Compiled from "hlists.scala"
public class shapeless.ops.hlist$Grouper$ implements shapeless.ops.hlist$LowPriorityGrouper,java.io.Serializable
  minor version: 0
  major version: 52
  flags: (0x0021) ACC_PUBLIC, ACC_SUPER
  this_class: #2                          // shapeless/ops/hlist$Grouper$
  super_class: #4                         // java/lang/Object
  interfaces: 2, fields: 1, methods: 7, attributes: 4
Constant pool:
    #1 = Utf8               shapeless/ops/hlist$Grouper$
    #2 = Class              #1            // shapeless/ops/hlist$Grouper$
    #3 = Utf8               java/lang/Object
    #4 = Class              #3            // java/lang/Object
    #5 = Utf8               shapeless/ops/hlist$LowPriorityGrouper
    #6 = Class              #5            // shapeless/ops/hlist$LowPriorityGrouper
    #7 = Utf8               java/io/Serializable
    #8 = Class              #7            // java/io/Serializable
    #9 = Utf8               hlists.scala
   #10 = Utf8               shapeless/ops/hlist$Drop
   #11 = Class              #10           // shapeless/ops/hlist$Drop
   #12 = Utf8               shapeless/ops/hlist
   #13 = Class              #12           // shapeless/ops/hlist
   #14 = Utf8               Drop
   #15 = Utf8               shapeless/ops/hlist$Grouper
   #16 = Class              #15           // shapeless/ops/hlist$Grouper
   #17 = Utf8               Grouper
   #18 = Utf8               Grouper$
   #19 = Utf8               shapeless/ops/hlist$Grouper$$anon$74
   #20 = Class              #19           // shapeless/ops/hlist$Grouper$$anon$74
   #21 = Utf8               shapeless/ops/hlist$Grouper$$anon$75
   #22 = Class              #21           // shapeless/ops/hlist$Grouper$$anon$75
   #23 = Utf8               shapeless/ops/hlist$Length
   #24 = Class              #23           // shapeless/ops/hlist$Length
   #25 = Utf8               Length
   #26 = Utf8               LowPriorityGrouper
   #27 = Utf8               shapeless/ops/hlist$Take
   #28 = Class              #27           // shapeless/ops/hlist$Take
   #29 = Utf8               Take
   #30 = Utf8               shapeless/ops/hlist$Tupler
   #31 = Class              #30           // shapeless/ops/hlist$Tupler
   #32 = Utf8               Tupler
   #33 = Utf8               shapeless/ops/nat$LT
   #34 = Class              #33           // shapeless/ops/nat$LT
   #35 = Utf8               shapeless/ops/nat
   #36 = Class              #35           // shapeless/ops/nat
   #37 = Utf8               LT
   #38 = Utf8               shapeless/ops/nat$Min
   #39 = Class              #38           // shapeless/ops/nat$Min
   #40 = Utf8               Min
   #41 = Utf8               MODULE$
   #42 = Utf8               Lshapeless/ops/hlist$Grouper$;
   #43 = Utf8               <clinit>
   #44 = Utf8               ()V
   #45 = Utf8               <init>
   #46 = NameAndType        #45:#44       // "<init>":()V
   #47 = Methodref          #2.#46        // shapeless/ops/hlist$Grouper$."<init>":()V
   #48 = NameAndType        #41:#42       // MODULE$:Lshapeless/ops/hlist$Grouper$;
   #49 = Fieldref           #2.#48        // shapeless/ops/hlist$Grouper$.MODULE$:Lshapeless/ops/hlist$Grouper$;
   #50 = Utf8               $init$
   #51 = Utf8               (Lshapeless/ops/hlist$LowPriorityGrouper;)V
   #52 = NameAndType        #50:#51       // $init$:(Lshapeless/ops/hlist$LowPriorityGrouper;)V
   #53 = InterfaceMethodref #6.#52        // shapeless/ops/hlist$LowPriorityGrouper.$init$:(Lshapeless/ops/hlist$LowPriorityGrouper;)V
   #54 = Utf8               hlistGrouper
   #55 = Utf8               (Lshapeless/ops/hlist$Length;Lshapeless/ops/nat$Min;Lshapeless/ops/hlist$Take;Lshapeless/ops/hlist$Drop;Lshapeless/ops/hlist$Tupler;Lshapeless/ops/hlist$Grouper;)Lshapeless/ops/hlist$Grouper;
   #56 = Utf8               <L::Lshapeless/HList;N::Lshapeless/Nat;OutT::Lshapeless/HList;OutD::Lshapeless/HList;T:Ljava/lang/Object;Step::Lshapeless/Nat;LL::Lshapeless/Nat;M::Lshapeless/Nat;OutG::Lshapeless/HList;>(Lshapeless/ops/hlist$Length<TL;>;Lshapeless/ops/nat$Min<TLL;TStep;>;Lshapeless/ops/hlist$Take<TL;TN;>;Lshapeless/ops/hlist$Drop<TL;TM;>;Lshapeless/ops/hlist$Tupler<TOutT;>;Lshapeless/ops/hlist$Grouper<TOutD;TN;TStep;>;)Lshapeless/ops/hlist$Grouper<TL;TN;TStep;>;
   #57 = Utf8               len
   #58 = Utf8               min
   #59 = Utf8               take
   #60 = Utf8               drop
   #61 = Utf8               tup
   #62 = Utf8               grouper
   #63 = Utf8               hlistGrouper$
   #64 = Utf8               (Lshapeless/ops/hlist$LowPriorityGrouper;Lshapeless/ops/hlist$Length;Lshapeless/ops/nat$Min;Lshapeless/ops/hlist$Take;Lshapeless/ops/hlist$Drop;Lshapeless/ops/hlist$Tupler;Lshapeless/ops/hlist$Grouper;)Lshapeless/ops/hlist$Grouper;
   #65 = NameAndType        #63:#64       // hlistGrouper$:(Lshapeless/ops/hlist$LowPriorityGrouper;Lshapeless/ops/hlist$Length;Lshapeless/ops/nat$Min;Lshapeless/ops/hlist$Take;Lshapeless/ops/hlist$Drop;Lshapeless/ops/hlist$Tupler;Lshapeless/ops/hlist$Grouper;)Lshapeless/ops/hlist$Grouper;
   #66 = InterfaceMethodref #6.#65        // shapeless/ops/hlist$LowPriorityGrouper.hlistGrouper$:(Lshapeless/ops/hlist$LowPriorityGrouper;Lshapeless/ops/hlist$Length;Lshapeless/ops/nat$Min;Lshapeless/ops/hlist$Take;Lshapeless/ops/hlist$Drop;Lshapeless/ops/hlist$Tupler;Lshapeless/ops/hlist$Grouper;)Lshapeless/ops/hlist$Grouper;
   #67 = Utf8               this
   #68 = Utf8               Lshapeless/ops/hlist$Length;
   #69 = Utf8               Lshapeless/ops/nat$Min;
   #70 = Utf8               Lshapeless/ops/hlist$Take;
   #71 = Utf8               Lshapeless/ops/hlist$Drop;
   #72 = Utf8               Lshapeless/ops/hlist$Tupler;
   #73 = Utf8               Lshapeless/ops/hlist$Grouper;
   #74 = Utf8               apply
   #75 = Utf8               (Lshapeless/ops/hlist$Grouper;)Lshapeless/ops/hlist$Grouper;
   #76 = Utf8               <L::Lshapeless/HList;N::Lshapeless/Nat;Step::Lshapeless/Nat;>(Lshapeless/ops/hlist$Grouper<TL;TN;TStep;>;)Lshapeless/ops/hlist$Grouper<TL;TN;TStep;>;
   #77 = Utf8               hnilGrouper
   #78 = Utf8               ()Lshapeless/ops/hlist$Grouper;
   #79 = Utf8               <N::Lshapeless/Nat;Step::Lshapeless/Nat;>()Lshapeless/ops/hlist$Grouper<Lshapeless/HNil;TN;TStep;>;
   #80 = Methodref          #20.#46       // shapeless/ops/hlist$Grouper$$anon$74."<init>":()V
   #81 = Utf8               hlistGrouper1
   #82 = Utf8               (Lshapeless/ops/hlist$Length;Lshapeless/ops/nat$LT;)Lshapeless/ops/hlist$Grouper;
   #83 = Utf8               <L::Lshapeless/HList;A::Lshapeless/Nat;N::Lshapeless/Nat;Step::Lshapeless/Nat;>(Lshapeless/ops/hlist$Length<TL;>;Lshapeless/ops/nat$LT<TA;TN;>;)Lshapeless/ops/hlist$Grouper<TL;TN;TStep;>;
   #84 = Utf8               lt
   #85 = Methodref          #22.#46       // shapeless/ops/hlist$Grouper$$anon$75."<init>":()V
   #86 = Utf8               Lshapeless/ops/nat$LT;
   #87 = Utf8               writeReplace
   #88 = Utf8               ()Ljava/lang/Object;
   #89 = Utf8               scala/runtime/ModuleSerializationProxy
   #90 = Class              #89           // scala/runtime/ModuleSerializationProxy
   #91 = Utf8               (Ljava/lang/Class;)V
   #92 = NameAndType        #45:#91       // "<init>":(Ljava/lang/Class;)V
   #93 = Methodref          #90.#92       // scala/runtime/ModuleSerializationProxy."<init>":(Ljava/lang/Class;)V
   #94 = Methodref          #4.#46        // java/lang/Object."<init>":()V
   #95 = Utf8               Code
   #96 = Utf8               LineNumberTable
   #97 = Utf8               LocalVariableTable
   #98 = Utf8               Signature
   #99 = Utf8               MethodParameters
  #100 = Utf8               InnerClasses
  #101 = Utf8               SourceFile
  #102 = Utf8               ScalaInlineInfo
  #103 = Utf8               Scala
{
  public static final shapeless.ops.hlist$Grouper$ MODULE$;
    descriptor: Lshapeless/ops/hlist$Grouper$;
    flags: (0x0019) ACC_PUBLIC, ACC_STATIC, ACC_FINAL

  public static {};
    descriptor: ()V
    flags: (0x0009) ACC_PUBLIC, ACC_STATIC
    Code:
      stack=2, locals=0, args_size=0
         0: new           #2                  // class shapeless/ops/hlist$Grouper$
         3: dup
         4: invokespecial #47                 // Method "<init>":()V
         7: putstatic     #49                 // Field MODULE$:Lshapeless/ops/hlist$Grouper$;
        10: getstatic     #49                 // Field MODULE$:Lshapeless/ops/hlist$Grouper$;
        13: invokestatic  #53                 // InterfaceMethod shapeless/ops/hlist$LowPriorityGrouper.$init$:(Lshapeless/ops/hlist$LowPriorityGrouper;)V
        16: return
      LineNumberTable:
        line 1043: 0

  public <L extends shapeless.HList, N extends shapeless.Nat, OutT extends shapeless.HList, OutD extends shapeless.HList, T extends java.lang.Object, Step extends shapeless.Nat, LL extends shapeless.Nat, M extends shapeless.Nat, OutG extends shapeless.HList> shapeless.ops.hlist$Grouper<L, N, Step> hlistGrouper(shapeless.ops.hlist$Length<L>, shapeless.ops.nat$Min<LL, Step>, shapeless.ops.hlist$Take<L, N>, shapeless.ops.hlist$Drop<L, M>, shapeless.ops.hlist$Tupler<OutT>, shapeless.ops.hlist$Grouper<OutD, N, Step>);
    descriptor: (Lshapeless/ops/hlist$Length;Lshapeless/ops/nat$Min;Lshapeless/ops/hlist$Take;Lshapeless/ops/hlist$Drop;Lshapeless/ops/hlist$Tupler;Lshapeless/ops/hlist$Grouper;)Lshapeless/ops/hlist$Grouper;
    flags: (0x0001) ACC_PUBLIC
    Code:
      stack=7, locals=7, args_size=7
         0: aload_0
         1: aload_1
         2: aload_2
         3: aload_3
         4: aload         4
         6: aload         5
         8: aload         6
        10: invokestatic  #66                 // InterfaceMethod shapeless/ops/hlist$LowPriorityGrouper.hlistGrouper$:(Lshapeless/ops/hlist$LowPriorityGrouper;Lshapeless/ops/hlist$Length;Lshapeless/ops/nat$Min;Lshapeless/ops/hlist$Take;Lshapeless/ops/hlist$Drop;Lshapeless/ops/hlist$Tupler;Lshapeless/ops/hlist$Grouper;)Lshapeless/ops/hlist$Grouper;
        13: areturn
      LineNumberTable:
        line 1043: 0
      LocalVariableTable:
        Start  Length  Slot  Name   Signature
            0      14     0  this   Lshapeless/ops/hlist$Grouper$;
            0      14     1   len   Lshapeless/ops/hlist$Length;
            0      14     2   min   Lshapeless/ops/nat$Min;
            0      14     3  take   Lshapeless/ops/hlist$Take;
            0      14     4  drop   Lshapeless/ops/hlist$Drop;
            0      14     5   tup   Lshapeless/ops/hlist$Tupler;
            0      14     6 grouper   Lshapeless/ops/hlist$Grouper;
    Signature: #56                          // <L::Lshapeless/HList;N::Lshapeless/Nat;OutT::Lshapeless/HList;OutD::Lshapeless/HList;T:Ljava/lang/Object;Step::Lshapeless/Nat;LL::Lshapeless/Nat;M::Lshapeless/Nat;OutG::Lshapeless/HList;>(Lshapeless/ops/hlist$Length<TL;>;Lshapeless/ops/nat$Min<TLL;TStep;>;Lshapeless/ops/hlist$Take<TL;TN;>;Lshapeless/ops/hlist$Drop<TL;TM;>;Lshapeless/ops/hlist$Tupler<TOutT;>;Lshapeless/ops/hlist$Grouper<TOutD;TN;TStep;>;)Lshapeless/ops/hlist$Grouper<TL;TN;TStep;>;
    MethodParameters:
      Name                           Flags
      len                            final
      min                            final
      take                           final
      drop                           final
      tup                            final
      grouper                        final

  public <L extends shapeless.HList, N extends shapeless.Nat, Step extends shapeless.Nat> shapeless.ops.hlist$Grouper<L, N, Step> apply(shapeless.ops.hlist$Grouper<L, N, Step>);
    descriptor: (Lshapeless/ops/hlist$Grouper;)Lshapeless/ops/hlist$Grouper;
    flags: (0x0001) ACC_PUBLIC
    Code:
      stack=1, locals=2, args_size=2
         0: aload_1
         1: areturn
      LineNumberTable:
        line 1046: 0
      LocalVariableTable:
        Start  Length  Slot  Name   Signature
            0       2     0  this   Lshapeless/ops/hlist$Grouper$;
            0       2     1 grouper   Lshapeless/ops/hlist$Grouper;
    Signature: #76                          // <L::Lshapeless/HList;N::Lshapeless/Nat;Step::Lshapeless/Nat;>(Lshapeless/ops/hlist$Grouper<TL;TN;TStep;>;)Lshapeless/ops/hlist$Grouper<TL;TN;TStep;>;
    MethodParameters:
      Name                           Flags
      grouper                        final

  public <N extends shapeless.Nat, Step extends shapeless.Nat> shapeless.ops.hlist$Grouper<shapeless.HNil, N, Step> hnilGrouper();
    descriptor: ()Lshapeless/ops/hlist$Grouper;
    flags: (0x0001) ACC_PUBLIC
    Code:
      stack=2, locals=1, args_size=1
         0: new           #20                 // class shapeless/ops/hlist$Grouper$$anon$74
         3: dup
         4: invokespecial #80                 // Method shapeless/ops/hlist$Grouper$$anon$74."<init>":()V
         7: areturn
      LineNumberTable:
        line 1052: 0
      LocalVariableTable:
        Start  Length  Slot  Name   Signature
            0       8     0  this   Lshapeless/ops/hlist$Grouper$;
    Signature: #79                          // <N::Lshapeless/Nat;Step::Lshapeless/Nat;>()Lshapeless/ops/hlist$Grouper<Lshapeless/HNil;TN;TStep;>;

  public <L extends shapeless.HList, A extends shapeless.Nat, N extends shapeless.Nat, Step extends shapeless.Nat> shapeless.ops.hlist$Grouper<L, N, Step> hlistGrouper1(shapeless.ops.hlist$Length<L>, shapeless.ops.nat$LT<A, N>);
    descriptor: (Lshapeless/ops/hlist$Length;Lshapeless/ops/nat$LT;)Lshapeless/ops/hlist$Grouper;
    flags: (0x0001) ACC_PUBLIC
    Code:
      stack=2, locals=3, args_size=3
         0: new           #22                 // class shapeless/ops/hlist$Grouper$$anon$75
         3: dup
         4: invokespecial #85                 // Method shapeless/ops/hlist$Grouper$$anon$75."<init>":()V
         7: areturn
      LineNumberTable:
        line 1061: 0
      LocalVariableTable:
        Start  Length  Slot  Name   Signature
            0       8     0  this   Lshapeless/ops/hlist$Grouper$;
            0       8     1   len   Lshapeless/ops/hlist$Length;
            0       8     2    lt   Lshapeless/ops/nat$LT;
    Signature: #83                          // <L::Lshapeless/HList;A::Lshapeless/Nat;N::Lshapeless/Nat;Step::Lshapeless/Nat;>(Lshapeless/ops/hlist$Length<TL;>;Lshapeless/ops/nat$LT<TA;TN;>;)Lshapeless/ops/hlist$Grouper<TL;TN;TStep;>;
    MethodParameters:
      Name                           Flags
      len                            final
      lt                             final

  private java.lang.Object writeReplace();
    descriptor: ()Ljava/lang/Object;
    flags: (0x0002) ACC_PRIVATE
    Code:
      stack=3, locals=1, args_size=1
         0: new           #90                 // class scala/runtime/ModuleSerializationProxy
         3: dup
         4: ldc           #2                  // class shapeless/ops/hlist$Grouper$
         6: invokespecial #93                 // Method scala/runtime/ModuleSerializationProxy."<init>":(Ljava/lang/Class;)V
         9: areturn
      LineNumberTable:
        line 1043: 0
      LocalVariableTable:
        Start  Length  Slot  Name   Signature
            0      10     0  this   Lshapeless/ops/hlist$Grouper$;

  public shapeless.ops.hlist$Grouper$();
    descriptor: ()V
    flags: (0x0001) ACC_PUBLIC
    Code:
      stack=1, locals=1, args_size=1
         0: aload_0
         1: invokespecial #94                 // Method java/lang/Object."<init>":()V
         4: return
      LineNumberTable:
        line 1043: 0
      LocalVariableTable:
        Start  Length  Slot  Name   Signature
            0       5     0  this   Lshapeless/ops/hlist$Grouper$;
}
InnerClasses:
  public static #14= #11 of #13;          // Drop=class shapeless/ops/hlist$Drop of class shapeless/ops/hlist
  public static #17= #16 of #13;          // Grouper=class shapeless/ops/hlist$Grouper of class shapeless/ops/hlist
  public static #18= #2 of #13;           // Grouper$=class shapeless/ops/hlist$Grouper$ of class shapeless/ops/hlist
  public final #20;                       // class shapeless/ops/hlist$Grouper$$anon$74
  public final #22;                       // class shapeless/ops/hlist$Grouper$$anon$75
  public static #25= #24 of #13;          // Length=class shapeless/ops/hlist$Length of class shapeless/ops/hlist
  public static #26= #6 of #13;           // LowPriorityGrouper=class shapeless/ops/hlist$LowPriorityGrouper of class shapeless/ops/hlist
  public static #29= #28 of #13;          // Take=class shapeless/ops/hlist$Take of class shapeless/ops/hlist
  public static #32= #31 of #13;          // Tupler=class shapeless/ops/hlist$Tupler of class shapeless/ops/hlist
  public static #37= #34 of #36;          // LT=class shapeless/ops/nat$LT of class shapeless/ops/nat
  public static #40= #39 of #36;          // Min=class shapeless/ops/nat$Min of class shapeless/ops/nat
SourceFile: "hlists.scala"
  ScalaInlineInfo: length = 0x22 (unknown attribute)
   01 01 00 06 00 2D 00 2C 01 00 4A 00 4B 01 00 36
   00 37 01 00 51 00 52 01 00 4D 00 4E 01 00 57 00
   58 01
  Scala: length = 0x0 (unknown attribute)

