Classfile /Users/mw/Projects/slang-braindump/.jar/jar8/assemble/slang-braindump/assemble/content/shapeless/ops/hlist$Selector$.class
  Last modified May 29, 2022; size 1806 bytes
  SHA-256 checksum aff908e2bb468d6a5f319e6595607687bf1d30ce300f1ad732c6fee82fe29cd5
  Compiled from "hlists.scala"
public class shapeless.ops.hlist$Selector$ implements java.io.Serializable
  minor version: 0
  major version: 52
  flags: (0x0021) ACC_PUBLIC, ACC_SUPER
  this_class: #2                          // shapeless/ops/hlist$Selector$
  super_class: #4                         // java/lang/Object
  interfaces: 1, fields: 1, methods: 6, attributes: 4
Constant pool:
   #1 = Utf8               shapeless/ops/hlist$Selector$
   #2 = Class              #1             // shapeless/ops/hlist$Selector$
   #3 = Utf8               java/lang/Object
   #4 = Class              #3             // java/lang/Object
   #5 = Utf8               java/io/Serializable
   #6 = Class              #5             // java/io/Serializable
   #7 = Utf8               hlists.scala
   #8 = Utf8               shapeless/ops/hlist$Selector
   #9 = Class              #8             // shapeless/ops/hlist$Selector
  #10 = Utf8               shapeless/ops/hlist
  #11 = Class              #10            // shapeless/ops/hlist
  #12 = Utf8               Selector
  #13 = Utf8               Selector$
  #14 = Utf8               shapeless/ops/hlist$Selector$$anon$63
  #15 = Class              #14            // shapeless/ops/hlist$Selector$$anon$63
  #16 = Utf8               shapeless/ops/hlist$Selector$$anon$64
  #17 = Class              #16            // shapeless/ops/hlist$Selector$$anon$64
  #18 = Utf8               MODULE$
  #19 = Utf8               Lshapeless/ops/hlist$Selector$;
  #20 = Utf8               <clinit>
  #21 = Utf8               ()V
  #22 = Utf8               <init>
  #23 = NameAndType        #22:#21        // "<init>":()V
  #24 = Methodref          #2.#23         // shapeless/ops/hlist$Selector$."<init>":()V
  #25 = NameAndType        #18:#19        // MODULE$:Lshapeless/ops/hlist$Selector$;
  #26 = Fieldref           #2.#25         // shapeless/ops/hlist$Selector$.MODULE$:Lshapeless/ops/hlist$Selector$;
  #27 = Utf8               apply
  #28 = Utf8               (Lshapeless/ops/hlist$Selector;)Lshapeless/ops/hlist$Selector;
  #29 = Utf8               <L::Lshapeless/HList;U:Ljava/lang/Object;>(Lshapeless/ops/hlist$Selector<TL;TU;>;)Lshapeless/ops/hlist$Selector<TL;TU;>;
  #30 = Utf8               selector
  #31 = Utf8               this
  #32 = Utf8               Lshapeless/ops/hlist$Selector;
  #33 = Utf8               select
  #34 = Utf8               ()Lshapeless/ops/hlist$Selector;
  #35 = Utf8               <H:Ljava/lang/Object;T::Lshapeless/HList;>()Lshapeless/ops/hlist$Selector<Lshapeless/$colon$colon<TH;TT;>;TH;>;
  #36 = Methodref          #15.#23        // shapeless/ops/hlist$Selector$$anon$63."<init>":()V
  #37 = Utf8               recurse
  #38 = Utf8               <H:Ljava/lang/Object;T::Lshapeless/HList;U:Ljava/lang/Object;>(Lshapeless/ops/hlist$Selector<TT;TU;>;)Lshapeless/ops/hlist$Selector<Lshapeless/$colon$colon<TH;TT;>;TU;>;
  #39 = Utf8               st
  #40 = Utf8               (Lshapeless/ops/hlist$Selector;)V
  #41 = NameAndType        #22:#40        // "<init>":(Lshapeless/ops/hlist$Selector;)V
  #42 = Methodref          #17.#41        // shapeless/ops/hlist$Selector$$anon$64."<init>":(Lshapeless/ops/hlist$Selector;)V
  #43 = Utf8               writeReplace
  #44 = Utf8               ()Ljava/lang/Object;
  #45 = Utf8               scala/runtime/ModuleSerializationProxy
  #46 = Class              #45            // scala/runtime/ModuleSerializationProxy
  #47 = Utf8               (Ljava/lang/Class;)V
  #48 = NameAndType        #22:#47        // "<init>":(Ljava/lang/Class;)V
  #49 = Methodref          #46.#48        // scala/runtime/ModuleSerializationProxy."<init>":(Ljava/lang/Class;)V
  #50 = Methodref          #4.#23         // java/lang/Object."<init>":()V
  #51 = Utf8               Code
  #52 = Utf8               LineNumberTable
  #53 = Utf8               LocalVariableTable
  #54 = Utf8               Signature
  #55 = Utf8               MethodParameters
  #56 = Utf8               InnerClasses
  #57 = Utf8               SourceFile
  #58 = Utf8               ScalaInlineInfo
  #59 = Utf8               Scala
{
  public static final shapeless.ops.hlist$Selector$ MODULE$;
    descriptor: Lshapeless/ops/hlist$Selector$;
    flags: (0x0019) ACC_PUBLIC, ACC_STATIC, ACC_FINAL

  public static {};
    descriptor: ()V
    flags: (0x0009) ACC_PUBLIC, ACC_STATIC
    Code:
      stack=2, locals=0, args_size=0
         0: new           #2                  // class shapeless/ops/hlist$Selector$
         3: dup
         4: invokespecial #24                 // Method "<init>":()V
         7: putstatic     #26                 // Field MODULE$:Lshapeless/ops/hlist$Selector$;
        10: return
      LineNumberTable:
        line 865: 0

  public <L extends shapeless.HList, U extends java.lang.Object> shapeless.ops.hlist$Selector<L, U> apply(shapeless.ops.hlist$Selector<L, U>);
    descriptor: (Lshapeless/ops/hlist$Selector;)Lshapeless/ops/hlist$Selector;
    flags: (0x0001) ACC_PUBLIC
    Code:
      stack=1, locals=2, args_size=2
         0: aload_1
         1: areturn
      LineNumberTable:
        line 867: 0
      LocalVariableTable:
        Start  Length  Slot  Name   Signature
            0       2     0  this   Lshapeless/ops/hlist$Selector$;
            0       2     1 selector   Lshapeless/ops/hlist$Selector;
    Signature: #29                          // <L::Lshapeless/HList;U:Ljava/lang/Object;>(Lshapeless/ops/hlist$Selector<TL;TU;>;)Lshapeless/ops/hlist$Selector<TL;TU;>;
    MethodParameters:
      Name                           Flags
      selector                       final

  public <H extends java.lang.Object, T extends shapeless.HList> shapeless.ops.hlist$Selector<shapeless.$colon$colon<H, T>, H> select();
    descriptor: ()Lshapeless/ops/hlist$Selector;
    flags: (0x0001) ACC_PUBLIC
    Code:
      stack=2, locals=1, args_size=1
         0: new           #15                 // class shapeless/ops/hlist$Selector$$anon$63
         3: dup
         4: invokespecial #36                 // Method shapeless/ops/hlist$Selector$$anon$63."<init>":()V
         7: areturn
      LineNumberTable:
        line 870: 0
      LocalVariableTable:
        Start  Length  Slot  Name   Signature
            0       8     0  this   Lshapeless/ops/hlist$Selector$;
    Signature: #35                          // <H:Ljava/lang/Object;T::Lshapeless/HList;>()Lshapeless/ops/hlist$Selector<Lshapeless/$colon$colon<TH;TT;>;TH;>;

  public <H extends java.lang.Object, T extends shapeless.HList, U extends java.lang.Object> shapeless.ops.hlist$Selector<shapeless.$colon$colon<H, T>, U> recurse(shapeless.ops.hlist$Selector<T, U>);
    descriptor: (Lshapeless/ops/hlist$Selector;)Lshapeless/ops/hlist$Selector;
    flags: (0x0001) ACC_PUBLIC
    Code:
      stack=3, locals=2, args_size=2
         0: new           #17                 // class shapeless/ops/hlist$Selector$$anon$64
         3: dup
         4: aload_1
         5: invokespecial #42                 // Method shapeless/ops/hlist$Selector$$anon$64."<init>":(Lshapeless/ops/hlist$Selector;)V
         8: areturn
      LineNumberTable:
        line 876: 0
      LocalVariableTable:
        Start  Length  Slot  Name   Signature
            0       9     0  this   Lshapeless/ops/hlist$Selector$;
            0       9     1    st   Lshapeless/ops/hlist$Selector;
    Signature: #38                          // <H:Ljava/lang/Object;T::Lshapeless/HList;U:Ljava/lang/Object;>(Lshapeless/ops/hlist$Selector<TT;TU;>;)Lshapeless/ops/hlist$Selector<Lshapeless/$colon$colon<TH;TT;>;TU;>;
    MethodParameters:
      Name                           Flags
      st                             final

  private java.lang.Object writeReplace();
    descriptor: ()Ljava/lang/Object;
    flags: (0x0002) ACC_PRIVATE
    Code:
      stack=3, locals=1, args_size=1
         0: new           #46                 // class scala/runtime/ModuleSerializationProxy
         3: dup
         4: ldc           #2                  // class shapeless/ops/hlist$Selector$
         6: invokespecial #49                 // Method scala/runtime/ModuleSerializationProxy."<init>":(Ljava/lang/Class;)V
         9: areturn
      LineNumberTable:
        line 865: 0
      LocalVariableTable:
        Start  Length  Slot  Name   Signature
            0      10     0  this   Lshapeless/ops/hlist$Selector$;

  public shapeless.ops.hlist$Selector$();
    descriptor: ()V
    flags: (0x0001) ACC_PUBLIC
    Code:
      stack=1, locals=1, args_size=1
         0: aload_0
         1: invokespecial #50                 // Method java/lang/Object."<init>":()V
         4: return
      LineNumberTable:
        line 888: 0
        line 865: 4
      LocalVariableTable:
        Start  Length  Slot  Name   Signature
            0       5     0  this   Lshapeless/ops/hlist$Selector$;
}
InnerClasses:
  public static #12= #9 of #11;           // Selector=class shapeless/ops/hlist$Selector of class shapeless/ops/hlist
  public static #13= #2 of #11;           // Selector$=class shapeless/ops/hlist$Selector$ of class shapeless/ops/hlist
  public final #15;                       // class shapeless/ops/hlist$Selector$$anon$63
  public final #17;                       // class shapeless/ops/hlist$Selector$$anon$64
SourceFile: "hlists.scala"
  ScalaInlineInfo: length = 0x1D (unknown attribute)
   01 01 00 05 00 16 00 15 01 00 1B 00 1C 01 00 25
   00 1C 01 00 21 00 22 01 00 2B 00 2C 01
  Scala: length = 0x0 (unknown attribute)

