Classfile /Users/mw/Projects/slang-braindump/.jar/jar8/assemble/slang-braindump/assemble/content/shapeless/ops/hlist$MapFolder$$anon$32.class
  Last modified May 29, 2022; size 1303 bytes
  SHA-256 checksum 8d53e9abe84cf66ccd5529d7a1231f4e5d4973eb9d9bb2219856c5f99b8a9dcf
  Compiled from "hlists.scala"
public final class shapeless.ops.hlist$MapFolder$$anon$32 extends java.lang.Object implements shapeless.ops.hlist$MapFolder<shapeless.HNil, R, HF>
  minor version: 0
  major version: 52
  flags: (0x0031) ACC_PUBLIC, ACC_FINAL, ACC_SUPER
  this_class: #2                          // shapeless/ops/hlist$MapFolder$$anon$32
  super_class: #5                         // java/lang/Object
  interfaces: 1, fields: 0, methods: 3, attributes: 6
Constant pool:
   #1 = Utf8               shapeless/ops/hlist$MapFolder$$anon$32
   #2 = Class              #1             // shapeless/ops/hlist$MapFolder$$anon$32
   #3 = Utf8               Ljava/lang/Object;Lshapeless/ops/hlist$MapFolder<Lshapeless/HNil;TR;THF;>;
   #4 = Utf8               java/lang/Object
   #5 = Class              #4             // java/lang/Object
   #6 = Utf8               shapeless/ops/hlist$MapFolder
   #7 = Class              #6             // shapeless/ops/hlist$MapFolder
   #8 = Utf8               hlists.scala
   #9 = Utf8               shapeless/ops/hlist$MapFolder$
  #10 = Class              #9             // shapeless/ops/hlist$MapFolder$
  #11 = Utf8               hnilMapFolder
  #12 = Utf8               ()Lshapeless/ops/hlist$MapFolder;
  #13 = NameAndType        #11:#12        // hnilMapFolder:()Lshapeless/ops/hlist$MapFolder;
  #14 = Utf8               shapeless/ops/hlist
  #15 = Class              #14            // shapeless/ops/hlist
  #16 = Utf8               MapFolder
  #17 = Utf8               MapFolder$
  #18 = Utf8               apply
  #19 = Utf8               (Lshapeless/HNil;Ljava/lang/Object;Lscala/Function2;)Ljava/lang/Object;
  #20 = Utf8               (Lshapeless/HNil;TR;Lscala/Function2<TR;TR;TR;>;)TR;
  #21 = Utf8               l
  #22 = Utf8               in
  #23 = Utf8               op
  #24 = Utf8               this
  #25 = Utf8               Lshapeless/ops/hlist$MapFolder$$anon$32;
  #26 = Utf8               Lshapeless/HNil;
  #27 = Utf8               Ljava/lang/Object;
  #28 = Utf8               Lscala/Function2;
  #29 = Utf8               (Lshapeless/HList;Ljava/lang/Object;Lscala/Function2;)Ljava/lang/Object;
  #30 = Utf8               shapeless/HNil
  #31 = Class              #30            // shapeless/HNil
  #32 = NameAndType        #18:#19        // apply:(Lshapeless/HNil;Ljava/lang/Object;Lscala/Function2;)Ljava/lang/Object;
  #33 = Methodref          #2.#32         // shapeless/ops/hlist$MapFolder$$anon$32.apply:(Lshapeless/HNil;Ljava/lang/Object;Lscala/Function2;)Ljava/lang/Object;
  #34 = Utf8               Lshapeless/HList;
  #35 = Utf8               <init>
  #36 = Utf8               ()V
  #37 = NameAndType        #35:#36        // "<init>":()V
  #38 = Methodref          #5.#37         // java/lang/Object."<init>":()V
  #39 = Utf8               Code
  #40 = Utf8               LineNumberTable
  #41 = Utf8               LocalVariableTable
  #42 = Utf8               Signature
  #43 = Utf8               MethodParameters
  #44 = Utf8               InnerClasses
  #45 = Utf8               EnclosingMethod
  #46 = Utf8               SourceFile
  #47 = Utf8               ScalaInlineInfo
  #48 = Utf8               Scala
{
  public R apply(shapeless.HNil, R, scala.Function2<R, R, R>);
    descriptor: (Lshapeless/HNil;Ljava/lang/Object;Lscala/Function2;)Ljava/lang/Object;
    flags: (0x0001) ACC_PUBLIC
    Code:
      stack=1, locals=4, args_size=4
         0: aload_2
         1: areturn
      LineNumberTable:
        line 403: 0
      LocalVariableTable:
        Start  Length  Slot  Name   Signature
            0       2     0  this   Lshapeless/ops/hlist$MapFolder$$anon$32;
            0       2     1     l   Lshapeless/HNil;
            0       2     2    in   Ljava/lang/Object;
            0       2     3    op   Lscala/Function2;
    Signature: #20                          // (Lshapeless/HNil;TR;Lscala/Function2<TR;TR;TR;>;)TR;
    MethodParameters:
      Name                           Flags
      l                              final
      in                             final
      op                             final

  public java.lang.Object apply(shapeless.HList, java.lang.Object, scala.Function2);
    descriptor: (Lshapeless/HList;Ljava/lang/Object;Lscala/Function2;)Ljava/lang/Object;
    flags: (0x1041) ACC_PUBLIC, ACC_BRIDGE, ACC_SYNTHETIC
    Code:
      stack=4, locals=4, args_size=4
         0: aload_0
         1: aload_1
         2: checkcast     #31                 // class shapeless/HNil
         5: aload_2
         6: aload_3
         7: invokevirtual #33                 // Method apply:(Lshapeless/HNil;Ljava/lang/Object;Lscala/Function2;)Ljava/lang/Object;
        10: areturn
      LineNumberTable:
        line 402: 0
      LocalVariableTable:
        Start  Length  Slot  Name   Signature
            0      11     0  this   Lshapeless/ops/hlist$MapFolder$$anon$32;
            0      11     1     l   Lshapeless/HList;
            0      11     2    in   Ljava/lang/Object;
            0      11     3    op   Lscala/Function2;
    MethodParameters:
      Name                           Flags
      l                              final
      in                             final
      op                             final

  public shapeless.ops.hlist$MapFolder$$anon$32();
    descriptor: ()V
    flags: (0x0001) ACC_PUBLIC
    Code:
      stack=1, locals=1, args_size=1
         0: aload_0
         1: invokespecial #38                 // Method java/lang/Object."<init>":()V
         4: return
      LineNumberTable:
        line 402: 0
      LocalVariableTable:
        Start  Length  Slot  Name   Signature
            0       5     0  this   Lshapeless/ops/hlist$MapFolder$$anon$32;
}
InnerClasses:
  public static #16= #7 of #15;           // MapFolder=class shapeless/ops/hlist$MapFolder of class shapeless/ops/hlist
  public static #17= #10 of #15;          // MapFolder$=class shapeless/ops/hlist$MapFolder$ of class shapeless/ops/hlist
  public final #2;                        // class shapeless/ops/hlist$MapFolder$$anon$32
EnclosingMethod: #10.#13                // shapeless.ops.hlist$MapFolder$.hnilMapFolder
Signature: #3                           // Ljava/lang/Object;Lshapeless/ops/hlist$MapFolder<Lshapeless/HNil;TR;THF;>;
SourceFile: "hlists.scala"
  ScalaInlineInfo: length = 0x13 (unknown attribute)
   01 01 00 03 00 23 00 24 01 00 12 00 1D 01 00 12
   00 13 01
  Scala: length = 0x0 (unknown attribute)

