Classfile /Users/mw/Projects/slang-braindump/.jar/jar8/assemble/slang-braindump/assemble/content/shapeless/ops/hlist$LowPriorityDiff.class
  Last modified May 29, 2022; size 1284 bytes
  SHA-256 checksum 81093c688874b2c120e9acc0f25640bb4d4a66af22a03152b4f9c42276f9356f
  Compiled from "hlists.scala"
public interface shapeless.ops.hlist$LowPriorityDiff
  minor version: 0
  major version: 52
  flags: (0x0601) ACC_PUBLIC, ACC_INTERFACE, ACC_ABSTRACT
  this_class: #2                          // shapeless/ops/hlist$LowPriorityDiff
  super_class: #4                         // java/lang/Object
  interfaces: 0, fields: 0, methods: 3, attributes: 4
Constant pool:
   #1 = Utf8               shapeless/ops/hlist$LowPriorityDiff
   #2 = Class              #1             // shapeless/ops/hlist$LowPriorityDiff
   #3 = Utf8               java/lang/Object
   #4 = Class              #3             // java/lang/Object
   #5 = Utf8               hlists.scala
   #6 = Utf8               shapeless/ops/hlist$Diff
   #7 = Class              #6             // shapeless/ops/hlist$Diff
   #8 = Utf8               shapeless/ops/hlist
   #9 = Class              #8             // shapeless/ops/hlist
  #10 = Utf8               Diff
  #11 = Utf8               LowPriorityDiff
  #12 = Utf8               shapeless/ops/hlist$LowPriorityDiff$$anon$92
  #13 = Class              #12            // shapeless/ops/hlist$LowPriorityDiff$$anon$92
  #14 = Utf8               hconsDiff1$
  #15 = Utf8               (Lshapeless/ops/hlist$LowPriorityDiff;Lshapeless/ops/hlist$Diff;)Lshapeless/ops/hlist$Diff;
  #16 = Utf8               $this
  #17 = Utf8               d
  #18 = Utf8               hconsDiff1
  #19 = Utf8               (Lshapeless/ops/hlist$Diff;)Lshapeless/ops/hlist$Diff;
  #20 = NameAndType        #18:#19        // hconsDiff1:(Lshapeless/ops/hlist$Diff;)Lshapeless/ops/hlist$Diff;
  #21 = InterfaceMethodref #2.#20         // shapeless/ops/hlist$LowPriorityDiff.hconsDiff1:(Lshapeless/ops/hlist$Diff;)Lshapeless/ops/hlist$Diff;
  #22 = Utf8               Lshapeless/ops/hlist$LowPriorityDiff;
  #23 = Utf8               Lshapeless/ops/hlist$Diff;
  #24 = Utf8               <L::Lshapeless/HList;H:Ljava/lang/Object;T::Lshapeless/HList;D::Lshapeless/HList;>(Lshapeless/ops/hlist$Diff<TL;TT;>;)Lshapeless/ops/hlist$Diff<TL;Lshapeless/$colon$colon<TH;TT;>;>;
  #25 = Utf8               <init>
  #26 = Utf8               (Lshapeless/ops/hlist$LowPriorityDiff;Lshapeless/ops/hlist$Diff;)V
  #27 = NameAndType        #25:#26        // "<init>":(Lshapeless/ops/hlist$LowPriorityDiff;Lshapeless/ops/hlist$Diff;)V
  #28 = Methodref          #13.#27        // shapeless/ops/hlist$LowPriorityDiff$$anon$92."<init>":(Lshapeless/ops/hlist$LowPriorityDiff;Lshapeless/ops/hlist$Diff;)V
  #29 = Utf8               this
  #30 = Utf8               $init$
  #31 = Utf8               (Lshapeless/ops/hlist$LowPriorityDiff;)V
  #32 = Utf8               Code
  #33 = Utf8               LineNumberTable
  #34 = Utf8               LocalVariableTable
  #35 = Utf8               MethodParameters
  #36 = Utf8               Signature
  #37 = Utf8               InnerClasses
  #38 = Utf8               SourceFile
  #39 = Utf8               ScalaInlineInfo
  #40 = Utf8               Scala
{
  public static shapeless.ops.hlist$Diff hconsDiff1$(shapeless.ops.hlist$LowPriorityDiff, shapeless.ops.hlist$Diff);
    descriptor: (Lshapeless/ops/hlist$LowPriorityDiff;Lshapeless/ops/hlist$Diff;)Lshapeless/ops/hlist$Diff;
    flags: (0x1009) ACC_PUBLIC, ACC_STATIC, ACC_SYNTHETIC
    Code:
      stack=2, locals=2, args_size=2
         0: aload_0
         1: aload_1
         2: invokespecial #21                 // InterfaceMethod hconsDiff1:(Lshapeless/ops/hlist$Diff;)Lshapeless/ops/hlist$Diff;
         5: areturn
      LineNumberTable:
        line 1385: 0
      LocalVariableTable:
        Start  Length  Slot  Name   Signature
            0       6     0 $this   Lshapeless/ops/hlist$LowPriorityDiff;
            0       6     1     d   Lshapeless/ops/hlist$Diff;
    MethodParameters:
      Name                           Flags
      $this                          final synthetic
      d                              final

  public default <L extends shapeless.HList, H extends java.lang.Object, T extends shapeless.HList, D extends shapeless.HList> shapeless.ops.hlist$Diff<L, shapeless.$colon$colon<H, T>> hconsDiff1(shapeless.ops.hlist$Diff<L, T>);
    descriptor: (Lshapeless/ops/hlist$Diff;)Lshapeless/ops/hlist$Diff;
    flags: (0x0001) ACC_PUBLIC
    Code:
      stack=4, locals=2, args_size=2
         0: new           #13                 // class shapeless/ops/hlist$LowPriorityDiff$$anon$92
         3: dup
         4: aconst_null
         5: aload_1
         6: invokespecial #28                 // Method shapeless/ops/hlist$LowPriorityDiff$$anon$92."<init>":(Lshapeless/ops/hlist$LowPriorityDiff;Lshapeless/ops/hlist$Diff;)V
         9: areturn
      LineNumberTable:
        line 1387: 0
      LocalVariableTable:
        Start  Length  Slot  Name   Signature
            0      10     0  this   Lshapeless/ops/hlist$LowPriorityDiff;
            0      10     1     d   Lshapeless/ops/hlist$Diff;
    Signature: #24                          // <L::Lshapeless/HList;H:Ljava/lang/Object;T::Lshapeless/HList;D::Lshapeless/HList;>(Lshapeless/ops/hlist$Diff<TL;TT;>;)Lshapeless/ops/hlist$Diff<TL;Lshapeless/$colon$colon<TH;TT;>;>;
    MethodParameters:
      Name                           Flags
      d                              final

  public static void $init$(shapeless.ops.hlist$LowPriorityDiff);
    descriptor: (Lshapeless/ops/hlist$LowPriorityDiff;)V
    flags: (0x0009) ACC_PUBLIC, ACC_STATIC
    Code:
      stack=0, locals=1, args_size=1
         0: return
      LineNumberTable:
        line 1382: 0
      LocalVariableTable:
        Start  Length  Slot  Name   Signature
            0       1     0 $this   Lshapeless/ops/hlist$LowPriorityDiff;
    MethodParameters:
      Name                           Flags
      $this                          final synthetic
}
InnerClasses:
  public static #10= #7 of #9;            // Diff=class shapeless/ops/hlist$Diff of class shapeless/ops/hlist
  public static #11= #2 of #9;            // LowPriorityDiff=class shapeless/ops/hlist$LowPriorityDiff of class shapeless/ops/hlist
  public final #13;                       // class shapeless/ops/hlist$LowPriorityDiff$$anon$92
SourceFile: "hlists.scala"
  ScalaInlineInfo: length = 0x13 (unknown attribute)
   01 00 00 03 00 1E 00 1F 01 00 0E 00 0F 01 00 12
   00 13 00
  Scala: length = 0x0 (unknown attribute)

