Classfile /Users/mw/Projects/slang-braindump/.jar/jar8/assemble/slang-braindump/assemble/content/shapeless/ops/hlist$HKernel$.class
  Last modified May 29, 2022; size 1295 bytes
  SHA-256 checksum 5067c5e20a2d765cda9fccb82b37a0a6ec6c6e18b55b496ec4b1489af2125e4d
  Compiled from "hlists.scala"
public class shapeless.ops.hlist$HKernel$
  minor version: 0
  major version: 52
  flags: (0x0021) ACC_PUBLIC, ACC_SUPER
  this_class: #2                          // shapeless/ops/hlist$HKernel$
  super_class: #4                         // java/lang/Object
  interfaces: 0, fields: 1, methods: 4, attributes: 4
Constant pool:
   #1 = Utf8               shapeless/ops/hlist$HKernel$
   #2 = Class              #1             // shapeless/ops/hlist$HKernel$
   #3 = Utf8               java/lang/Object
   #4 = Class              #3             // java/lang/Object
   #5 = Utf8               hlists.scala
   #6 = Utf8               shapeless/ops/hlist$HKernel
   #7 = Class              #6             // shapeless/ops/hlist$HKernel
   #8 = Utf8               shapeless/ops/hlist
   #9 = Class              #8             // shapeless/ops/hlist
  #10 = Utf8               HKernel
  #11 = Utf8               HKernel$
  #12 = Utf8               shapeless/ops/hlist$HKernelAux
  #13 = Class              #12            // shapeless/ops/hlist$HKernelAux
  #14 = Utf8               HKernelAux
  #15 = Utf8               MODULE$
  #16 = Utf8               Lshapeless/ops/hlist$HKernel$;
  #17 = Utf8               <clinit>
  #18 = Utf8               ()V
  #19 = Utf8               <init>
  #20 = NameAndType        #19:#18        // "<init>":()V
  #21 = Methodref          #2.#20         // shapeless/ops/hlist$HKernel$."<init>":()V
  #22 = NameAndType        #15:#16        // MODULE$:Lshapeless/ops/hlist$HKernel$;
  #23 = Fieldref           #2.#22         // shapeless/ops/hlist$HKernel$.MODULE$:Lshapeless/ops/hlist$HKernel$;
  #24 = Utf8               apply
  #25 = Utf8               (Lshapeless/ops/hlist$HKernelAux;)Lshapeless/ops/hlist$HKernel;
  #26 = Utf8               <L::Lshapeless/HList;>(Lshapeless/ops/hlist$HKernelAux<TL;>;)Lshapeless/ops/hlist$HKernel;
  #27 = Utf8               mk
  #28 = Utf8               ()Ljava/lang/Object;
  #29 = NameAndType        #24:#28        // apply:()Ljava/lang/Object;
  #30 = InterfaceMethodref #13.#29        // shapeless/ops/hlist$HKernelAux.apply:()Ljava/lang/Object;
  #31 = Utf8               this
  #32 = Utf8               Lshapeless/ops/hlist$HKernelAux;
  #33 = Utf8               (Lshapeless/HList;Lshapeless/ops/hlist$HKernelAux;)Lshapeless/ops/hlist$HKernel;
  #34 = Utf8               <L::Lshapeless/HList;>(TL;Lshapeless/ops/hlist$HKernelAux<TL;>;)Lshapeless/ops/hlist$HKernel;
  #35 = Utf8               l
  #36 = Utf8               Lshapeless/HList;
  #37 = Methodref          #4.#20         // java/lang/Object."<init>":()V
  #38 = Utf8               Code
  #39 = Utf8               LineNumberTable
  #40 = Utf8               LocalVariableTable
  #41 = Utf8               Signature
  #42 = Utf8               MethodParameters
  #43 = Utf8               InnerClasses
  #44 = Utf8               SourceFile
  #45 = Utf8               ScalaInlineInfo
  #46 = Utf8               Scala
{
  public static final shapeless.ops.hlist$HKernel$ MODULE$;
    descriptor: Lshapeless/ops/hlist$HKernel$;
    flags: (0x0019) ACC_PUBLIC, ACC_STATIC, ACC_FINAL

  public static {};
    descriptor: ()V
    flags: (0x0009) ACC_PUBLIC, ACC_STATIC
    Code:
      stack=2, locals=0, args_size=0
         0: new           #2                  // class shapeless/ops/hlist$HKernel$
         3: dup
         4: invokespecial #21                 // Method "<init>":()V
         7: putstatic     #23                 // Field MODULE$:Lshapeless/ops/hlist$HKernel$;
        10: return
      LineNumberTable:
        line 206: 0

  public <L extends shapeless.HList> shapeless.ops.hlist$HKernel apply(shapeless.ops.hlist$HKernelAux<L>);
    descriptor: (Lshapeless/ops/hlist$HKernelAux;)Lshapeless/ops/hlist$HKernel;
    flags: (0x0001) ACC_PUBLIC
    Code:
      stack=1, locals=2, args_size=2
         0: aload_1
         1: invokeinterface #30,  1           // InterfaceMethod shapeless/ops/hlist$HKernelAux.apply:()Ljava/lang/Object;
         6: checkcast     #7                  // class shapeless/ops/hlist$HKernel
         9: areturn
      LineNumberTable:
        line 207: 0
      LocalVariableTable:
        Start  Length  Slot  Name   Signature
            0      10     0  this   Lshapeless/ops/hlist$HKernel$;
            0      10     1    mk   Lshapeless/ops/hlist$HKernelAux;
    Signature: #26                          // <L::Lshapeless/HList;>(Lshapeless/ops/hlist$HKernelAux<TL;>;)Lshapeless/ops/hlist$HKernel;
    MethodParameters:
      Name                           Flags
      mk                             final

  public <L extends shapeless.HList> shapeless.ops.hlist$HKernel apply(L, shapeless.ops.hlist$HKernelAux<L>);
    descriptor: (Lshapeless/HList;Lshapeless/ops/hlist$HKernelAux;)Lshapeless/ops/hlist$HKernel;
    flags: (0x0001) ACC_PUBLIC
    Code:
      stack=1, locals=3, args_size=3
         0: aload_2
         1: invokeinterface #30,  1           // InterfaceMethod shapeless/ops/hlist$HKernelAux.apply:()Ljava/lang/Object;
         6: checkcast     #7                  // class shapeless/ops/hlist$HKernel
         9: areturn
      LineNumberTable:
        line 208: 0
      LocalVariableTable:
        Start  Length  Slot  Name   Signature
            0      10     0  this   Lshapeless/ops/hlist$HKernel$;
            0      10     1     l   Lshapeless/HList;
            0      10     2    mk   Lshapeless/ops/hlist$HKernelAux;
    Signature: #34                          // <L::Lshapeless/HList;>(TL;Lshapeless/ops/hlist$HKernelAux<TL;>;)Lshapeless/ops/hlist$HKernel;
    MethodParameters:
      Name                           Flags
      l                              final
      mk                             final

  public shapeless.ops.hlist$HKernel$();
    descriptor: ()V
    flags: (0x0001) ACC_PUBLIC
    Code:
      stack=1, locals=1, args_size=1
         0: aload_0
         1: invokespecial #37                 // Method java/lang/Object."<init>":()V
         4: return
      LineNumberTable:
        line 211: 0
        line 206: 4
      LocalVariableTable:
        Start  Length  Slot  Name   Signature
            0       5     0  this   Lshapeless/ops/hlist$HKernel$;
}
InnerClasses:
  public static #10= #7 of #9;            // HKernel=class shapeless/ops/hlist$HKernel of class shapeless/ops/hlist
  public static #11= #2 of #9;            // HKernel$=class shapeless/ops/hlist$HKernel$ of class shapeless/ops/hlist
  public static #14= #13 of #9;           // HKernelAux=class shapeless/ops/hlist$HKernelAux of class shapeless/ops/hlist
SourceFile: "hlists.scala"
  ScalaInlineInfo: length = 0x13 (unknown attribute)
   01 01 00 03 00 13 00 12 01 00 18 00 21 01 00 18
   00 19 01
  Scala: length = 0x0 (unknown attribute)

