Classfile /Users/mw/Projects/slang-braindump/.jar/jar8/assemble/slang-braindump/assemble/content/shapeless/ops/hlist$LowPriorityRemove.class
  Last modified May 29, 2022; size 1315 bytes
  SHA-256 checksum 0004f80d0a2102cd2d7f37ce91d2d8aa10202f8cefeec4caa0ddae9dc9a13a28
  Compiled from "hlists.scala"
public interface shapeless.ops.hlist$LowPriorityRemove
  minor version: 0
  major version: 52
  flags: (0x0601) ACC_PUBLIC, ACC_INTERFACE, ACC_ABSTRACT
  this_class: #2                          // shapeless/ops/hlist$LowPriorityRemove
  super_class: #4                         // java/lang/Object
  interfaces: 0, fields: 0, methods: 3, attributes: 4
Constant pool:
   #1 = Utf8               shapeless/ops/hlist$LowPriorityRemove
   #2 = Class              #1             // shapeless/ops/hlist$LowPriorityRemove
   #3 = Utf8               java/lang/Object
   #4 = Class              #3             // java/lang/Object
   #5 = Utf8               hlists.scala
   #6 = Utf8               shapeless/ops/hlist
   #7 = Class              #6             // shapeless/ops/hlist
   #8 = Utf8               LowPriorityRemove
   #9 = Utf8               shapeless/ops/hlist$LowPriorityRemove$$anon$80
  #10 = Class              #9             // shapeless/ops/hlist$LowPriorityRemove$$anon$80
  #11 = Utf8               shapeless/ops/hlist$Remove
  #12 = Class              #11            // shapeless/ops/hlist$Remove
  #13 = Utf8               Remove
  #14 = Utf8               recurse$
  #15 = Utf8               (Lshapeless/ops/hlist$LowPriorityRemove;Lshapeless/ops/hlist$Remove;)Lshapeless/ops/hlist$Remove;
  #16 = Utf8               $this
  #17 = Utf8               r
  #18 = Utf8               recurse
  #19 = Utf8               (Lshapeless/ops/hlist$Remove;)Lshapeless/ops/hlist$Remove;
  #20 = NameAndType        #18:#19        // recurse:(Lshapeless/ops/hlist$Remove;)Lshapeless/ops/hlist$Remove;
  #21 = InterfaceMethodref #2.#20         // shapeless/ops/hlist$LowPriorityRemove.recurse:(Lshapeless/ops/hlist$Remove;)Lshapeless/ops/hlist$Remove;
  #22 = Utf8               Lshapeless/ops/hlist$LowPriorityRemove;
  #23 = Utf8               Lshapeless/ops/hlist$Remove;
  #24 = Utf8               <H:Ljava/lang/Object;T::Lshapeless/HList;E:Ljava/lang/Object;OutT::Lshapeless/HList;>(Lshapeless/ops/hlist$Remove<TT;TE;>;)Lshapeless/ops/hlist$Remove<Lshapeless/$colon$colon<TH;TT;>;TE;>;
  #25 = Utf8               <init>
  #26 = Utf8               (Lshapeless/ops/hlist$LowPriorityRemove;Lshapeless/ops/hlist$Remove;)V
  #27 = NameAndType        #25:#26        // "<init>":(Lshapeless/ops/hlist$LowPriorityRemove;Lshapeless/ops/hlist$Remove;)V
  #28 = Methodref          #10.#27        // shapeless/ops/hlist$LowPriorityRemove$$anon$80."<init>":(Lshapeless/ops/hlist$LowPriorityRemove;Lshapeless/ops/hlist$Remove;)V
  #29 = Utf8               this
  #30 = Utf8               $init$
  #31 = Utf8               (Lshapeless/ops/hlist$LowPriorityRemove;)V
  #32 = Utf8               Code
  #33 = Utf8               LineNumberTable
  #34 = Utf8               LocalVariableTable
  #35 = Utf8               MethodParameters
  #36 = Utf8               Signature
  #37 = Utf8               InnerClasses
  #38 = Utf8               SourceFile
  #39 = Utf8               ScalaInlineInfo
  #40 = Utf8               Scala
{
  public static shapeless.ops.hlist$Remove recurse$(shapeless.ops.hlist$LowPriorityRemove, shapeless.ops.hlist$Remove);
    descriptor: (Lshapeless/ops/hlist$LowPriorityRemove;Lshapeless/ops/hlist$Remove;)Lshapeless/ops/hlist$Remove;
    flags: (0x1009) ACC_PUBLIC, ACC_STATIC, ACC_SYNTHETIC
    Code:
      stack=2, locals=2, args_size=2
         0: aload_0
         1: aload_1
         2: invokespecial #21                 // InterfaceMethod recurse:(Lshapeless/ops/hlist$Remove;)Lshapeless/ops/hlist$Remove;
         5: areturn
      LineNumberTable:
        line 1194: 0
      LocalVariableTable:
        Start  Length  Slot  Name   Signature
            0       6     0 $this   Lshapeless/ops/hlist$LowPriorityRemove;
            0       6     1     r   Lshapeless/ops/hlist$Remove;
    MethodParameters:
      Name                           Flags
      $this                          final synthetic
      r                              final

  public default <H extends java.lang.Object, T extends shapeless.HList, E extends java.lang.Object, OutT extends shapeless.HList> shapeless.ops.hlist$Remove<shapeless.$colon$colon<H, T>, E> recurse(shapeless.ops.hlist$Remove<T, E>);
    descriptor: (Lshapeless/ops/hlist$Remove;)Lshapeless/ops/hlist$Remove;
    flags: (0x0001) ACC_PUBLIC
    Code:
      stack=4, locals=2, args_size=2
         0: new           #10                 // class shapeless/ops/hlist$LowPriorityRemove$$anon$80
         3: dup
         4: aconst_null
         5: aload_1
         6: invokespecial #28                 // Method shapeless/ops/hlist$LowPriorityRemove$$anon$80."<init>":(Lshapeless/ops/hlist$LowPriorityRemove;Lshapeless/ops/hlist$Remove;)V
         9: areturn
      LineNumberTable:
        line 1195: 0
      LocalVariableTable:
        Start  Length  Slot  Name   Signature
            0      10     0  this   Lshapeless/ops/hlist$LowPriorityRemove;
            0      10     1     r   Lshapeless/ops/hlist$Remove;
    Signature: #24                          // <H:Ljava/lang/Object;T::Lshapeless/HList;E:Ljava/lang/Object;OutT::Lshapeless/HList;>(Lshapeless/ops/hlist$Remove<TT;TE;>;)Lshapeless/ops/hlist$Remove<Lshapeless/$colon$colon<TH;TT;>;TE;>;
    MethodParameters:
      Name                           Flags
      r                              final

  public static void $init$(shapeless.ops.hlist$LowPriorityRemove);
    descriptor: (Lshapeless/ops/hlist$LowPriorityRemove;)V
    flags: (0x0009) ACC_PUBLIC, ACC_STATIC
    Code:
      stack=0, locals=1, args_size=1
         0: return
      LineNumberTable:
        line 1191: 0
      LocalVariableTable:
        Start  Length  Slot  Name   Signature
            0       1     0 $this   Lshapeless/ops/hlist$LowPriorityRemove;
    MethodParameters:
      Name                           Flags
      $this                          final synthetic
}
InnerClasses:
  public static #8= #2 of #7;             // LowPriorityRemove=class shapeless/ops/hlist$LowPriorityRemove of class shapeless/ops/hlist
  public final #10;                       // class shapeless/ops/hlist$LowPriorityRemove$$anon$80
  public static #13= #12 of #7;           // Remove=class shapeless/ops/hlist$Remove of class shapeless/ops/hlist
SourceFile: "hlists.scala"
  ScalaInlineInfo: length = 0x13 (unknown attribute)
   01 00 00 03 00 1E 00 1F 01 00 0E 00 0F 01 00 12
   00 13 00
  Scala: length = 0x0 (unknown attribute)

