Classfile /Users/mw/Projects/slang-braindump/.jar/jar8/assemble/slang-braindump/assemble/content/shapeless/ops/hlist$Partition$$anon$70.class
  Last modified May 29, 2022; size 2029 bytes
  SHA-256 checksum fa4c27db580e6c253af4bf0dee4a06b69738881d6c5eef13254f967af40779aa
  Compiled from "hlists.scala"
public final class shapeless.ops.hlist$Partition$$anon$70 extends java.lang.Object implements shapeless.ops.hlist$Partition<shapeless.HNil, U>
  minor version: 0
  major version: 52
  flags: (0x0031) ACC_PUBLIC, ACC_FINAL, ACC_SUPER
  this_class: #2                          // shapeless/ops/hlist$Partition$$anon$70
  super_class: #5                         // java/lang/Object
  interfaces: 1, fields: 0, methods: 8, attributes: 6
Constant pool:
   #1 = Utf8               shapeless/ops/hlist$Partition$$anon$70
   #2 = Class              #1             // shapeless/ops/hlist$Partition$$anon$70
   #3 = Utf8               Ljava/lang/Object;Lshapeless/ops/hlist$Partition<Lshapeless/HNil;TU;>;
   #4 = Utf8               java/lang/Object
   #5 = Class              #4             // java/lang/Object
   #6 = Utf8               shapeless/ops/hlist$Partition
   #7 = Class              #6             // shapeless/ops/hlist$Partition
   #8 = Utf8               hlists.scala
   #9 = Utf8               shapeless/ops/hlist$Partition$
  #10 = Class              #9             // shapeless/ops/hlist$Partition$
  #11 = Utf8               hlistPartitionNil
  #12 = Utf8               ()Lshapeless/ops/hlist$Partition;
  #13 = NameAndType        #11:#12        // hlistPartitionNil:()Lshapeless/ops/hlist$Partition;
  #14 = Utf8               shapeless/ops/hlist
  #15 = Class              #14            // shapeless/ops/hlist
  #16 = Utf8               Partition
  #17 = Utf8               Partition$
  #18 = Utf8               apply
  #19 = Utf8               (Lshapeless/HList;)Lscala/Tuple2;
  #20 = Utf8               l
  #21 = Utf8               apply$
  #22 = Utf8               (Lshapeless/ops/hlist$Partition;Lshapeless/HList;)Lscala/Tuple2;
  #23 = NameAndType        #21:#22        // apply$:(Lshapeless/ops/hlist$Partition;Lshapeless/HList;)Lscala/Tuple2;
  #24 = InterfaceMethodref #7.#23         // shapeless/ops/hlist$Partition.apply$:(Lshapeless/ops/hlist$Partition;Lshapeless/HList;)Lscala/Tuple2;
  #25 = Utf8               this
  #26 = Utf8               Lshapeless/ops/hlist$Partition$$anon$70;
  #27 = Utf8               Lshapeless/HList;
  #28 = Utf8               product
  #29 = Utf8               (Lshapeless/HList;)Lshapeless/$colon$colon;
  #30 = Utf8               product$
  #31 = Utf8               (Lshapeless/ops/hlist$Partition;Lshapeless/HList;)Lshapeless/$colon$colon;
  #32 = NameAndType        #30:#31        // product$:(Lshapeless/ops/hlist$Partition;Lshapeless/HList;)Lshapeless/$colon$colon;
  #33 = InterfaceMethodref #7.#32         // shapeless/ops/hlist$Partition.product$:(Lshapeless/ops/hlist$Partition;Lshapeless/HList;)Lshapeless/$colon$colon;
  #34 = Utf8               filter
  #35 = Utf8               (Lshapeless/HNil;)Lshapeless/HNil;
  #36 = Utf8               shapeless/HNil$
  #37 = Class              #36            // shapeless/HNil$
  #38 = Utf8               MODULE$
  #39 = Utf8               Lshapeless/HNil$;
  #40 = NameAndType        #38:#39        // MODULE$:Lshapeless/HNil$;
  #41 = Fieldref           #37.#40        // shapeless/HNil$.MODULE$:Lshapeless/HNil$;
  #42 = Utf8               Lshapeless/HNil;
  #43 = Utf8               filterNot
  #44 = Utf8               (Ljava/lang/Object;)Ljava/lang/Object;
  #45 = Utf8               t
  #46 = Utf8               shapeless/HList
  #47 = Class              #46            // shapeless/HList
  #48 = NameAndType        #18:#19        // apply:(Lshapeless/HList;)Lscala/Tuple2;
  #49 = Methodref          #2.#48         // shapeless/ops/hlist$Partition$$anon$70.apply:(Lshapeless/HList;)Lscala/Tuple2;
  #50 = Utf8               Ljava/lang/Object;
  #51 = Utf8               (Lshapeless/HList;)Lshapeless/HList;
  #52 = Utf8               shapeless/HNil
  #53 = Class              #52            // shapeless/HNil
  #54 = NameAndType        #43:#35        // filterNot:(Lshapeless/HNil;)Lshapeless/HNil;
  #55 = Methodref          #2.#54         // shapeless/ops/hlist$Partition$$anon$70.filterNot:(Lshapeless/HNil;)Lshapeless/HNil;
  #56 = NameAndType        #34:#35        // filter:(Lshapeless/HNil;)Lshapeless/HNil;
  #57 = Methodref          #2.#56         // shapeless/ops/hlist$Partition$$anon$70.filter:(Lshapeless/HNil;)Lshapeless/HNil;
  #58 = Utf8               <init>
  #59 = Utf8               ()V
  #60 = NameAndType        #58:#59        // "<init>":()V
  #61 = Methodref          #5.#60         // java/lang/Object."<init>":()V
  #62 = Utf8               $init$
  #63 = Utf8               (Lshapeless/ops/hlist$Partition;)V
  #64 = NameAndType        #62:#63        // $init$:(Lshapeless/ops/hlist$Partition;)V
  #65 = InterfaceMethodref #7.#64         // shapeless/ops/hlist$Partition.$init$:(Lshapeless/ops/hlist$Partition;)V
  #66 = Utf8               Code
  #67 = Utf8               LineNumberTable
  #68 = Utf8               LocalVariableTable
  #69 = Utf8               MethodParameters
  #70 = Utf8               InnerClasses
  #71 = Utf8               EnclosingMethod
  #72 = Utf8               Signature
  #73 = Utf8               SourceFile
  #74 = Utf8               ScalaInlineInfo
  #75 = Utf8               Scala
{
  public scala.Tuple2 apply(shapeless.HList);
    descriptor: (Lshapeless/HList;)Lscala/Tuple2;
    flags: (0x0001) ACC_PUBLIC
    Code:
      stack=2, locals=2, args_size=2
         0: aload_0
         1: aload_1
         2: invokestatic  #24                 // InterfaceMethod shapeless/ops/hlist$Partition.apply$:(Lshapeless/ops/hlist$Partition;Lshapeless/HList;)Lscala/Tuple2;
         5: areturn
      LineNumberTable:
        line 986: 0
      LocalVariableTable:
        Start  Length  Slot  Name   Signature
            0       6     0  this   Lshapeless/ops/hlist$Partition$$anon$70;
            0       6     1     l   Lshapeless/HList;
    MethodParameters:
      Name                           Flags
      l                              final

  public shapeless.$colon$colon product(shapeless.HList);
    descriptor: (Lshapeless/HList;)Lshapeless/$colon$colon;
    flags: (0x0001) ACC_PUBLIC
    Code:
      stack=2, locals=2, args_size=2
         0: aload_0
         1: aload_1
         2: invokestatic  #33                 // InterfaceMethod shapeless/ops/hlist$Partition.product$:(Lshapeless/ops/hlist$Partition;Lshapeless/HList;)Lshapeless/$colon$colon;
         5: areturn
      LineNumberTable:
        line 986: 0
      LocalVariableTable:
        Start  Length  Slot  Name   Signature
            0       6     0  this   Lshapeless/ops/hlist$Partition$$anon$70;
            0       6     1     l   Lshapeless/HList;
    MethodParameters:
      Name                           Flags
      l                              final

  public shapeless.HNil filter(shapeless.HNil);
    descriptor: (Lshapeless/HNil;)Lshapeless/HNil;
    flags: (0x0001) ACC_PUBLIC
    Code:
      stack=1, locals=2, args_size=2
         0: getstatic     #41                 // Field shapeless/HNil$.MODULE$:Lshapeless/HNil$;
         3: areturn
      LineNumberTable:
        line 990: 0
      LocalVariableTable:
        Start  Length  Slot  Name   Signature
            0       4     0  this   Lshapeless/ops/hlist$Partition$$anon$70;
            0       4     1     l   Lshapeless/HNil;
    MethodParameters:
      Name                           Flags
      l                              final

  public shapeless.HNil filterNot(shapeless.HNil);
    descriptor: (Lshapeless/HNil;)Lshapeless/HNil;
    flags: (0x0001) ACC_PUBLIC
    Code:
      stack=1, locals=2, args_size=2
         0: getstatic     #41                 // Field shapeless/HNil$.MODULE$:Lshapeless/HNil$;
         3: areturn
      LineNumberTable:
        line 991: 0
      LocalVariableTable:
        Start  Length  Slot  Name   Signature
            0       4     0  this   Lshapeless/ops/hlist$Partition$$anon$70;
            0       4     1     l   Lshapeless/HNil;
    MethodParameters:
      Name                           Flags
      l                              final

  public java.lang.Object apply(java.lang.Object);
    descriptor: (Ljava/lang/Object;)Ljava/lang/Object;
    flags: (0x1041) ACC_PUBLIC, ACC_BRIDGE, ACC_SYNTHETIC
    Code:
      stack=2, locals=2, args_size=2
         0: aload_0
         1: aload_1
         2: checkcast     #47                 // class shapeless/HList
         5: invokevirtual #49                 // Method apply:(Lshapeless/HList;)Lscala/Tuple2;
         8: areturn
      LineNumberTable:
        line 986: 0
      LocalVariableTable:
        Start  Length  Slot  Name   Signature
            0       9     0  this   Lshapeless/ops/hlist$Partition$$anon$70;
            0       9     1     t   Ljava/lang/Object;
    MethodParameters:
      Name                           Flags
      t                              final

  public shapeless.HList filterNot(shapeless.HList);
    descriptor: (Lshapeless/HList;)Lshapeless/HList;
    flags: (0x1041) ACC_PUBLIC, ACC_BRIDGE, ACC_SYNTHETIC
    Code:
      stack=2, locals=2, args_size=2
         0: aload_0
         1: aload_1
         2: checkcast     #53                 // class shapeless/HNil
         5: invokevirtual #55                 // Method filterNot:(Lshapeless/HNil;)Lshapeless/HNil;
         8: areturn
      LineNumberTable:
        line 986: 0
      LocalVariableTable:
        Start  Length  Slot  Name   Signature
            0       9     0  this   Lshapeless/ops/hlist$Partition$$anon$70;
            0       9     1     l   Lshapeless/HList;
    MethodParameters:
      Name                           Flags
      l                              final

  public shapeless.HList filter(shapeless.HList);
    descriptor: (Lshapeless/HList;)Lshapeless/HList;
    flags: (0x1041) ACC_PUBLIC, ACC_BRIDGE, ACC_SYNTHETIC
    Code:
      stack=2, locals=2, args_size=2
         0: aload_0
         1: aload_1
         2: checkcast     #53                 // class shapeless/HNil
         5: invokevirtual #57                 // Method filter:(Lshapeless/HNil;)Lshapeless/HNil;
         8: areturn
      LineNumberTable:
        line 986: 0
      LocalVariableTable:
        Start  Length  Slot  Name   Signature
            0       9     0  this   Lshapeless/ops/hlist$Partition$$anon$70;
            0       9     1     l   Lshapeless/HList;
    MethodParameters:
      Name                           Flags
      l                              final

  public shapeless.ops.hlist$Partition$$anon$70();
    descriptor: ()V
    flags: (0x0001) ACC_PUBLIC
    Code:
      stack=1, locals=1, args_size=1
         0: aload_0
         1: invokespecial #61                 // Method java/lang/Object."<init>":()V
         4: aload_0
         5: invokestatic  #65                 // InterfaceMethod shapeless/ops/hlist$Partition.$init$:(Lshapeless/ops/hlist$Partition;)V
         8: return
      LineNumberTable:
        line 986: 0
      LocalVariableTable:
        Start  Length  Slot  Name   Signature
            0       9     0  this   Lshapeless/ops/hlist$Partition$$anon$70;
}
InnerClasses:
  public static #16= #7 of #15;           // Partition=class shapeless/ops/hlist$Partition of class shapeless/ops/hlist
  public static #17= #10 of #15;          // Partition$=class shapeless/ops/hlist$Partition$ of class shapeless/ops/hlist
  public final #2;                        // class shapeless/ops/hlist$Partition$$anon$70
EnclosingMethod: #10.#13                // shapeless.ops.hlist$Partition$.hlistPartitionNil
Signature: #3                           // Ljava/lang/Object;Lshapeless/ops/hlist$Partition<Lshapeless/HNil;TU;>;
SourceFile: "hlists.scala"
  ScalaInlineInfo: length = 0x2C (unknown attribute)
   01 01 00 08 00 3A 00 3B 01 00 12 00 2C 01 00 12
   00 13 01 00 22 00 33 01 00 22 00 23 01 00 2B 00
   33 01 00 2B 00 23 01 00 1C 00 1D 01
  Scala: length = 0x0 (unknown attribute)

