Classfile /Users/mw/Projects/slang-braindump/.jar/jar8/assemble/slang-braindump/assemble/content/shapeless/ops/hlist$ReverseSplitLeft$ReverseSplitLeft0$.class
  Last modified May 29, 2022; size 2511 bytes
  SHA-256 checksum f2ebf143d7ba16b32434c8f8de2bbeab0ff05a561ee003b03f53c3454004ad1c
  Compiled from "hlists.scala"
public class shapeless.ops.hlist$ReverseSplitLeft$ReverseSplitLeft0$ implements shapeless.ops.hlist$ReverseSplitLeft$LowPriorityReverseSplitLeft0,java.io.Serializable
  minor version: 0
  major version: 52
  flags: (0x0021) ACC_PUBLIC, ACC_SUPER
  this_class: #2                          // shapeless/ops/hlist$ReverseSplitLeft$ReverseSplitLeft0$
  super_class: #4                         // java/lang/Object
  interfaces: 2, fields: 1, methods: 5, attributes: 4
Constant pool:
   #1 = Utf8               shapeless/ops/hlist$ReverseSplitLeft$ReverseSplitLeft0$
   #2 = Class              #1             // shapeless/ops/hlist$ReverseSplitLeft$ReverseSplitLeft0$
   #3 = Utf8               java/lang/Object
   #4 = Class              #3             // java/lang/Object
   #5 = Utf8               shapeless/ops/hlist$ReverseSplitLeft$LowPriorityReverseSplitLeft0
   #6 = Class              #5             // shapeless/ops/hlist$ReverseSplitLeft$LowPriorityReverseSplitLeft0
   #7 = Utf8               java/io/Serializable
   #8 = Class              #7             // java/io/Serializable
   #9 = Utf8               hlists.scala
  #10 = Utf8               shapeless/ops/hlist$ReverseSplitLeft$
  #11 = Class              #10            // shapeless/ops/hlist$ReverseSplitLeft$
  #12 = Utf8               shapeless/ops/hlist
  #13 = Class              #12            // shapeless/ops/hlist
  #14 = Utf8               ReverseSplitLeft$
  #15 = Utf8               LowPriorityReverseSplitLeft0
  #16 = Utf8               shapeless/ops/hlist$ReverseSplitLeft$ReverseSplitLeft0
  #17 = Class              #16            // shapeless/ops/hlist$ReverseSplitLeft$ReverseSplitLeft0
  #18 = Utf8               ReverseSplitLeft0
  #19 = Utf8               ReverseSplitLeft0$
  #20 = Utf8               shapeless/ops/hlist$ReverseSplitLeft$ReverseSplitLeft0$$anon$119
  #21 = Class              #20            // shapeless/ops/hlist$ReverseSplitLeft$ReverseSplitLeft0$$anon$119
  #22 = Utf8               MODULE$
  #23 = Utf8               Lshapeless/ops/hlist$ReverseSplitLeft$ReverseSplitLeft0$;
  #24 = Utf8               <clinit>
  #25 = Utf8               ()V
  #26 = Utf8               <init>
  #27 = NameAndType        #26:#25        // "<init>":()V
  #28 = Methodref          #2.#27         // shapeless/ops/hlist$ReverseSplitLeft$ReverseSplitLeft0$."<init>":()V
  #29 = NameAndType        #22:#23        // MODULE$:Lshapeless/ops/hlist$ReverseSplitLeft$ReverseSplitLeft0$;
  #30 = Fieldref           #2.#29         // shapeless/ops/hlist$ReverseSplitLeft$ReverseSplitLeft0$.MODULE$:Lshapeless/ops/hlist$ReverseSplitLeft$ReverseSplitLeft0$;
  #31 = Utf8               $init$
  #32 = Utf8               (Lshapeless/ops/hlist$ReverseSplitLeft$LowPriorityReverseSplitLeft0;)V
  #33 = NameAndType        #31:#32        // $init$:(Lshapeless/ops/hlist$ReverseSplitLeft$LowPriorityReverseSplitLeft0;)V
  #34 = InterfaceMethodref #6.#33         // shapeless/ops/hlist$ReverseSplitLeft$LowPriorityReverseSplitLeft0.$init$:(Lshapeless/ops/hlist$ReverseSplitLeft$LowPriorityReverseSplitLeft0;)V
  #35 = Utf8               hlistReverseSplitLeft1
  #36 = Utf8               (Lshapeless/ops/hlist$ReverseSplitLeft$ReverseSplitLeft0;)Lshapeless/ops/hlist$ReverseSplitLeft$ReverseSplitLeft0;
  #37 = Utf8               <AccP::Lshapeless/HList;AccSH:Ljava/lang/Object;AccST::Lshapeless/HList;U:Ljava/lang/Object;P:Ljava/lang/Object;S:Ljava/lang/Object;>(Lshapeless/ops/hlist$ReverseSplitLeft$ReverseSplitLeft0<Lshapeless/$colon$colon<TAccSH;TAccP;>;TAccST;TU;TP;TS;>;)Lshapeless/ops/hlist$ReverseSplitLeft$ReverseSplitLeft0<TAccP;Lshapeless/$colon$colon<TAccSH;TAccST;>;TU;TP;TS;>;
  #38 = Utf8               slt
  #39 = Utf8               hlistReverseSplitLeft1$
  #40 = Utf8               (Lshapeless/ops/hlist$ReverseSplitLeft$LowPriorityReverseSplitLeft0;Lshapeless/ops/hlist$ReverseSplitLeft$ReverseSplitLeft0;)Lshapeless/ops/hlist$ReverseSplitLeft$ReverseSplitLeft0;
  #41 = NameAndType        #39:#40        // hlistReverseSplitLeft1$:(Lshapeless/ops/hlist$ReverseSplitLeft$LowPriorityReverseSplitLeft0;Lshapeless/ops/hlist$ReverseSplitLeft$ReverseSplitLeft0;)Lshapeless/ops/hlist$ReverseSplitLeft$ReverseSplitLeft0;
  #42 = InterfaceMethodref #6.#41         // shapeless/ops/hlist$ReverseSplitLeft$LowPriorityReverseSplitLeft0.hlistReverseSplitLeft1$:(Lshapeless/ops/hlist$ReverseSplitLeft$LowPriorityReverseSplitLeft0;Lshapeless/ops/hlist$ReverseSplitLeft$ReverseSplitLeft0;)Lshapeless/ops/hlist$ReverseSplitLeft$ReverseSplitLeft0;
  #43 = Utf8               this
  #44 = Utf8               Lshapeless/ops/hlist$ReverseSplitLeft$ReverseSplitLeft0;
  #45 = Utf8               hlistReverseSplitLeft2
  #46 = Utf8               ()Lshapeless/ops/hlist$ReverseSplitLeft$ReverseSplitLeft0;
  #47 = Utf8               <P::Lshapeless/HList;SH:Ljava/lang/Object;ST::Lshapeless/HList;>()Lshapeless/ops/hlist$ReverseSplitLeft$ReverseSplitLeft0<TP;Lshapeless/$colon$colon<TSH;TST;>;TSH;TP;Lshapeless/$colon$colon<TSH;TST;>;>;
  #48 = Methodref          #21.#27        // shapeless/ops/hlist$ReverseSplitLeft$ReverseSplitLeft0$$anon$119."<init>":()V
  #49 = Utf8               writeReplace
  #50 = Utf8               ()Ljava/lang/Object;
  #51 = Utf8               scala/runtime/ModuleSerializationProxy
  #52 = Class              #51            // scala/runtime/ModuleSerializationProxy
  #53 = Utf8               (Ljava/lang/Class;)V
  #54 = NameAndType        #26:#53        // "<init>":(Ljava/lang/Class;)V
  #55 = Methodref          #52.#54        // scala/runtime/ModuleSerializationProxy."<init>":(Ljava/lang/Class;)V
  #56 = Methodref          #4.#27         // java/lang/Object."<init>":()V
  #57 = Utf8               Code
  #58 = Utf8               LineNumberTable
  #59 = Utf8               LocalVariableTable
  #60 = Utf8               Signature
  #61 = Utf8               MethodParameters
  #62 = Utf8               InnerClasses
  #63 = Utf8               SourceFile
  #64 = Utf8               ScalaInlineInfo
  #65 = Utf8               Scala
{
  public static final shapeless.ops.hlist$ReverseSplitLeft$ReverseSplitLeft0$ MODULE$;
    descriptor: Lshapeless/ops/hlist$ReverseSplitLeft$ReverseSplitLeft0$;
    flags: (0x0019) ACC_PUBLIC, ACC_STATIC, ACC_FINAL

  public static {};
    descriptor: ()V
    flags: (0x0009) ACC_PUBLIC, ACC_STATIC
    Code:
      stack=2, locals=0, args_size=0
         0: new           #2                  // class shapeless/ops/hlist$ReverseSplitLeft$ReverseSplitLeft0$
         3: dup
         4: invokespecial #28                 // Method "<init>":()V
         7: putstatic     #30                 // Field MODULE$:Lshapeless/ops/hlist$ReverseSplitLeft$ReverseSplitLeft0$;
        10: getstatic     #30                 // Field MODULE$:Lshapeless/ops/hlist$ReverseSplitLeft$ReverseSplitLeft0$;
        13: invokestatic  #34                 // InterfaceMethod shapeless/ops/hlist$ReverseSplitLeft$LowPriorityReverseSplitLeft0.$init$:(Lshapeless/ops/hlist$ReverseSplitLeft$LowPriorityReverseSplitLeft0;)V
        16: return
      LineNumberTable:
        line 1827: 0

  public <AccP extends shapeless.HList, AccSH extends java.lang.Object, AccST extends shapeless.HList, U extends java.lang.Object, P extends java.lang.Object, S extends java.lang.Object> shapeless.ops.hlist$ReverseSplitLeft$ReverseSplitLeft0<AccP, shapeless.$colon$colon<AccSH, AccST>, U, P, S> hlistReverseSplitLeft1(shapeless.ops.hlist$ReverseSplitLeft$ReverseSplitLeft0<shapeless.$colon$colon<AccSH, AccP>, AccST, U, P, S>);
    descriptor: (Lshapeless/ops/hlist$ReverseSplitLeft$ReverseSplitLeft0;)Lshapeless/ops/hlist$ReverseSplitLeft$ReverseSplitLeft0;
    flags: (0x0001) ACC_PUBLIC
    Code:
      stack=2, locals=2, args_size=2
         0: aload_0
         1: aload_1
         2: invokestatic  #42                 // InterfaceMethod shapeless/ops/hlist$ReverseSplitLeft$LowPriorityReverseSplitLeft0.hlistReverseSplitLeft1$:(Lshapeless/ops/hlist$ReverseSplitLeft$LowPriorityReverseSplitLeft0;Lshapeless/ops/hlist$ReverseSplitLeft$ReverseSplitLeft0;)Lshapeless/ops/hlist$ReverseSplitLeft$ReverseSplitLeft0;
         5: areturn
      LineNumberTable:
        line 1827: 0
      LocalVariableTable:
        Start  Length  Slot  Name   Signature
            0       6     0  this   Lshapeless/ops/hlist$ReverseSplitLeft$ReverseSplitLeft0$;
            0       6     1   slt   Lshapeless/ops/hlist$ReverseSplitLeft$ReverseSplitLeft0;
    Signature: #37                          // <AccP::Lshapeless/HList;AccSH:Ljava/lang/Object;AccST::Lshapeless/HList;U:Ljava/lang/Object;P:Ljava/lang/Object;S:Ljava/lang/Object;>(Lshapeless/ops/hlist$ReverseSplitLeft$ReverseSplitLeft0<Lshapeless/$colon$colon<TAccSH;TAccP;>;TAccST;TU;TP;TS;>;)Lshapeless/ops/hlist$ReverseSplitLeft$ReverseSplitLeft0<TAccP;Lshapeless/$colon$colon<TAccSH;TAccST;>;TU;TP;TS;>;
    MethodParameters:
      Name                           Flags
      slt                            final

  public <P extends shapeless.HList, SH extends java.lang.Object, ST extends shapeless.HList> shapeless.ops.hlist$ReverseSplitLeft$ReverseSplitLeft0<P, shapeless.$colon$colon<SH, ST>, SH, P, shapeless.$colon$colon<SH, ST>> hlistReverseSplitLeft2();
    descriptor: ()Lshapeless/ops/hlist$ReverseSplitLeft$ReverseSplitLeft0;
    flags: (0x0001) ACC_PUBLIC
    Code:
      stack=2, locals=1, args_size=1
         0: new           #21                 // class shapeless/ops/hlist$ReverseSplitLeft$ReverseSplitLeft0$$anon$119
         3: dup
         4: invokespecial #48                 // Method shapeless/ops/hlist$ReverseSplitLeft$ReverseSplitLeft0$$anon$119."<init>":()V
         7: areturn
      LineNumberTable:
        line 1829: 0
      LocalVariableTable:
        Start  Length  Slot  Name   Signature
            0       8     0  this   Lshapeless/ops/hlist$ReverseSplitLeft$ReverseSplitLeft0$;
    Signature: #47                          // <P::Lshapeless/HList;SH:Ljava/lang/Object;ST::Lshapeless/HList;>()Lshapeless/ops/hlist$ReverseSplitLeft$ReverseSplitLeft0<TP;Lshapeless/$colon$colon<TSH;TST;>;TSH;TP;Lshapeless/$colon$colon<TSH;TST;>;>;

  private java.lang.Object writeReplace();
    descriptor: ()Ljava/lang/Object;
    flags: (0x0002) ACC_PRIVATE
    Code:
      stack=3, locals=1, args_size=1
         0: new           #52                 // class scala/runtime/ModuleSerializationProxy
         3: dup
         4: ldc           #2                  // class shapeless/ops/hlist$ReverseSplitLeft$ReverseSplitLeft0$
         6: invokespecial #55                 // Method scala/runtime/ModuleSerializationProxy."<init>":(Ljava/lang/Class;)V
         9: areturn
      LineNumberTable:
        line 1827: 0
      LocalVariableTable:
        Start  Length  Slot  Name   Signature
            0      10     0  this   Lshapeless/ops/hlist$ReverseSplitLeft$ReverseSplitLeft0$;

  public shapeless.ops.hlist$ReverseSplitLeft$ReverseSplitLeft0$();
    descriptor: ()V
    flags: (0x0001) ACC_PUBLIC
    Code:
      stack=1, locals=1, args_size=1
         0: aload_0
         1: invokespecial #56                 // Method java/lang/Object."<init>":()V
         4: return
      LineNumberTable:
        line 1827: 0
      LocalVariableTable:
        Start  Length  Slot  Name   Signature
            0       5     0  this   Lshapeless/ops/hlist$ReverseSplitLeft$ReverseSplitLeft0$;
}
InnerClasses:
  public static #14= #11 of #13;          // ReverseSplitLeft$=class shapeless/ops/hlist$ReverseSplitLeft$ of class shapeless/ops/hlist
  public static #15= #6 of #11;           // LowPriorityReverseSplitLeft0=class shapeless/ops/hlist$ReverseSplitLeft$LowPriorityReverseSplitLeft0 of class shapeless/ops/hlist$ReverseSplitLeft$
  public static #18= #17 of #11;          // ReverseSplitLeft0=class shapeless/ops/hlist$ReverseSplitLeft$ReverseSplitLeft0 of class shapeless/ops/hlist$ReverseSplitLeft$
  public static #19= #2 of #11;           // ReverseSplitLeft0$=class shapeless/ops/hlist$ReverseSplitLeft$ReverseSplitLeft0$ of class shapeless/ops/hlist$ReverseSplitLeft$
  public final #21;                       // class shapeless/ops/hlist$ReverseSplitLeft$ReverseSplitLeft0$$anon$119
SourceFile: "hlists.scala"
  ScalaInlineInfo: length = 0x18 (unknown attribute)
   01 01 00 04 00 1A 00 19 01 00 23 00 24 01 00 2D
   00 2E 01 00 31 00 32 01
  Scala: length = 0x0 (unknown attribute)

