Classfile /Users/mw/Projects/slang-braindump/.jar/jar8/assemble/slang-braindump/assemble/content/shapeless/ops/hlist$HKernelAux$$anon$18.class
  Last modified May 29, 2022; size 1353 bytes
  SHA-256 checksum f070df43e32ef2adadb620d699b0889d1f5e7086895f292b626f940a8d71c72b
  Compiled from "hlists.scala"
public final class shapeless.ops.hlist$HKernelAux$$anon$18 extends java.lang.Object implements shapeless.ops.hlist$HKernelAux<shapeless.$colon$colon<H, T>>
  minor version: 0
  major version: 52
  flags: (0x0031) ACC_PUBLIC, ACC_FINAL, ACC_SUPER
  this_class: #2                          // shapeless/ops/hlist$HKernelAux$$anon$18
  super_class: #5                         // java/lang/Object
  interfaces: 1, fields: 1, methods: 3, attributes: 6
Constant pool:
   #1 = Utf8               shapeless/ops/hlist$HKernelAux$$anon$18
   #2 = Class              #1             // shapeless/ops/hlist$HKernelAux$$anon$18
   #3 = Utf8               Ljava/lang/Object;Lshapeless/ops/hlist$HKernelAux<Lshapeless/$colon$colon<TH;TT;>;>;
   #4 = Utf8               java/lang/Object
   #5 = Class              #4             // java/lang/Object
   #6 = Utf8               shapeless/ops/hlist$HKernelAux
   #7 = Class              #6             // shapeless/ops/hlist$HKernelAux
   #8 = Utf8               hlists.scala
   #9 = Utf8               shapeless/ops/hlist$HKernelAux$
  #10 = Class              #9             // shapeless/ops/hlist$HKernelAux$
  #11 = Utf8               mkHListHKernel
  #12 = Utf8               (Lshapeless/ops/hlist$HKernelAux;)Lshapeless/ops/hlist$HKernelAux;
  #13 = NameAndType        #11:#12        // mkHListHKernel:(Lshapeless/ops/hlist$HKernelAux;)Lshapeless/ops/hlist$HKernelAux;
  #14 = Utf8               shapeless/ops/hlist$HConsHKernel
  #15 = Class              #14            // shapeless/ops/hlist$HConsHKernel
  #16 = Utf8               shapeless/ops/hlist
  #17 = Class              #16            // shapeless/ops/hlist
  #18 = Utf8               HConsHKernel
  #19 = Utf8               shapeless/ops/hlist$HKernel
  #20 = Class              #19            // shapeless/ops/hlist$HKernel
  #21 = Utf8               HKernel
  #22 = Utf8               HKernelAux
  #23 = Utf8               HKernelAux$
  #24 = Utf8               ct$1
  #25 = Utf8               Lshapeless/ops/hlist$HKernelAux;
  #26 = Utf8               apply
  #27 = Utf8               ()Lshapeless/ops/hlist$HConsHKernel;
  #28 = Utf8               ()Lshapeless/ops/hlist$HConsHKernel<TH;TCtOut;>;
  #29 = NameAndType        #24:#25        // ct$1:Lshapeless/ops/hlist$HKernelAux;
  #30 = Fieldref           #2.#29         // shapeless/ops/hlist$HKernelAux$$anon$18.ct$1:Lshapeless/ops/hlist$HKernelAux;
  #31 = Utf8               ()Ljava/lang/Object;
  #32 = NameAndType        #26:#31        // apply:()Ljava/lang/Object;
  #33 = InterfaceMethodref #7.#32         // shapeless/ops/hlist$HKernelAux.apply:()Ljava/lang/Object;
  #34 = Utf8               <init>
  #35 = Utf8               (Lshapeless/ops/hlist$HKernel;)V
  #36 = NameAndType        #34:#35        // "<init>":(Lshapeless/ops/hlist$HKernel;)V
  #37 = Methodref          #15.#36        // shapeless/ops/hlist$HConsHKernel."<init>":(Lshapeless/ops/hlist$HKernel;)V
  #38 = Utf8               this
  #39 = Utf8               Lshapeless/ops/hlist$HKernelAux$$anon$18;
  #40 = NameAndType        #26:#27        // apply:()Lshapeless/ops/hlist$HConsHKernel;
  #41 = Methodref          #2.#40         // shapeless/ops/hlist$HKernelAux$$anon$18.apply:()Lshapeless/ops/hlist$HConsHKernel;
  #42 = Utf8               (Lshapeless/ops/hlist$HKernelAux;)V
  #43 = Utf8               ()V
  #44 = NameAndType        #34:#43        // "<init>":()V
  #45 = Methodref          #5.#44         // java/lang/Object."<init>":()V
  #46 = Utf8               Code
  #47 = Utf8               LineNumberTable
  #48 = Utf8               LocalVariableTable
  #49 = Utf8               Signature
  #50 = Utf8               MethodParameters
  #51 = Utf8               InnerClasses
  #52 = Utf8               EnclosingMethod
  #53 = Utf8               SourceFile
  #54 = Utf8               ScalaInlineInfo
  #55 = Utf8               Scala
{
  private final shapeless.ops.hlist$HKernelAux ct$1;
    descriptor: Lshapeless/ops/hlist$HKernelAux;
    flags: (0x0012) ACC_PRIVATE, ACC_FINAL

  public shapeless.ops.hlist$HConsHKernel<H, CtOut> apply();
    descriptor: ()Lshapeless/ops/hlist$HConsHKernel;
    flags: (0x0001) ACC_PUBLIC
    Code:
      stack=3, locals=1, args_size=1
         0: new           #15                 // class shapeless/ops/hlist$HConsHKernel
         3: dup
         4: aload_0
         5: getfield      #30                 // Field ct$1:Lshapeless/ops/hlist$HKernelAux;
         8: invokeinterface #33,  1           // InterfaceMethod shapeless/ops/hlist$HKernelAux.apply:()Ljava/lang/Object;
        13: checkcast     #20                 // class shapeless/ops/hlist$HKernel
        16: invokespecial #37                 // Method shapeless/ops/hlist$HConsHKernel."<init>":(Lshapeless/ops/hlist$HKernel;)V
        19: areturn
      LineNumberTable:
        line 224: 0
      LocalVariableTable:
        Start  Length  Slot  Name   Signature
            0      20     0  this   Lshapeless/ops/hlist$HKernelAux$$anon$18;
    Signature: #28                          // ()Lshapeless/ops/hlist$HConsHKernel<TH;TCtOut;>;

  public java.lang.Object apply();
    descriptor: ()Ljava/lang/Object;
    flags: (0x1041) ACC_PUBLIC, ACC_BRIDGE, ACC_SYNTHETIC
    Code:
      stack=1, locals=1, args_size=1
         0: aload_0
         1: invokevirtual #41                 // Method apply:()Lshapeless/ops/hlist$HConsHKernel;
         4: areturn
      LineNumberTable:
        line 222: 0
      LocalVariableTable:
        Start  Length  Slot  Name   Signature
            0       5     0  this   Lshapeless/ops/hlist$HKernelAux$$anon$18;

  public shapeless.ops.hlist$HKernelAux$$anon$18(shapeless.ops.hlist$HKernelAux);
    descriptor: (Lshapeless/ops/hlist$HKernelAux;)V
    flags: (0x0001) ACC_PUBLIC
    Code:
      stack=2, locals=2, args_size=2
         0: aload_0
         1: aload_1
         2: putfield      #30                 // Field ct$1:Lshapeless/ops/hlist$HKernelAux;
         5: aload_0
         6: invokespecial #45                 // Method java/lang/Object."<init>":()V
         9: return
      LineNumberTable:
        line 222: 0
      LocalVariableTable:
        Start  Length  Slot  Name   Signature
            0      10     0  this   Lshapeless/ops/hlist$HKernelAux$$anon$18;
            0      10     1  ct$1   Lshapeless/ops/hlist$HKernelAux;
    MethodParameters:
      Name                           Flags
      ct$1                           final
}
InnerClasses:
  public static final #18= #15 of #17;    // HConsHKernel=class shapeless/ops/hlist$HConsHKernel of class shapeless/ops/hlist
  public static #21= #20 of #17;          // HKernel=class shapeless/ops/hlist$HKernel of class shapeless/ops/hlist
  public static #22= #7 of #17;           // HKernelAux=class shapeless/ops/hlist$HKernelAux of class shapeless/ops/hlist
  public static #23= #10 of #17;          // HKernelAux$=class shapeless/ops/hlist$HKernelAux$ of class shapeless/ops/hlist
  public final #2;                        // class shapeless/ops/hlist$HKernelAux$$anon$18
EnclosingMethod: #10.#13                // shapeless.ops.hlist$HKernelAux$.mkHListHKernel
Signature: #3                           // Ljava/lang/Object;Lshapeless/ops/hlist$HKernelAux<Lshapeless/$colon$colon<TH;TT;>;>;
SourceFile: "hlists.scala"
  ScalaInlineInfo: length = 0x13 (unknown attribute)
   01 01 00 03 00 22 00 2A 01 00 1A 00 1F 01 00 1A
   00 1B 01
  Scala: length = 0x0 (unknown attribute)

