Classfile /Users/mw/Projects/slang-braindump/.jar/jar8/assemble/slang-braindump/assemble/content/shapeless/ops/hlist$ReverseSplitRight$LowPriorityReverseSplitRight0.class
  Last modified May 29, 2022; size 2791 bytes
  SHA-256 checksum a3f3884cda6fa72c5241466ab6e267adc08841f8a2604b0005ed2baa5a48a3af
  Compiled from "hlists.scala"
public interface shapeless.ops.hlist$ReverseSplitRight$LowPriorityReverseSplitRight0
  minor version: 0
  major version: 52
  flags: (0x0601) ACC_PUBLIC, ACC_INTERFACE, ACC_ABSTRACT
  this_class: #2                          // shapeless/ops/hlist$ReverseSplitRight$LowPriorityReverseSplitRight0
  super_class: #4                         // java/lang/Object
  interfaces: 0, fields: 0, methods: 5, attributes: 4
Constant pool:
   #1 = Utf8               shapeless/ops/hlist$ReverseSplitRight$LowPriorityReverseSplitRight0
   #2 = Class              #1             // shapeless/ops/hlist$ReverseSplitRight$LowPriorityReverseSplitRight0
   #3 = Utf8               java/lang/Object
   #4 = Class              #3             // java/lang/Object
   #5 = Utf8               hlists.scala
   #6 = Utf8               shapeless/ops/hlist$ReverseSplitRight$
   #7 = Class              #6             // shapeless/ops/hlist$ReverseSplitRight$
   #8 = Utf8               shapeless/ops/hlist
   #9 = Class              #8             // shapeless/ops/hlist
  #10 = Utf8               ReverseSplitRight$
  #11 = Utf8               LowPriorityReverseSplitRight0
  #12 = Utf8               shapeless/ops/hlist$ReverseSplitRight$LowPriorityReverseSplitRight0$$anon$125
  #13 = Class              #12            // shapeless/ops/hlist$ReverseSplitRight$LowPriorityReverseSplitRight0$$anon$125
  #14 = Utf8               shapeless/ops/hlist$ReverseSplitRight$LowPriorityReverseSplitRight0$$anon$126
  #15 = Class              #14            // shapeless/ops/hlist$ReverseSplitRight$LowPriorityReverseSplitRight0$$anon$126
  #16 = Utf8               shapeless/ops/hlist$ReverseSplitRight$ReverseSplitRight0
  #17 = Class              #16            // shapeless/ops/hlist$ReverseSplitRight$ReverseSplitRight0
  #18 = Utf8               ReverseSplitRight0
  #19 = Utf8               hlistReverseSplitRight1$
  #20 = Utf8               (Lshapeless/ops/hlist$ReverseSplitRight$LowPriorityReverseSplitRight0;Lshapeless/ops/hlist$ReverseSplitRight$ReverseSplitRight0;)Lshapeless/ops/hlist$ReverseSplitRight$ReverseSplitRight0;
  #21 = Utf8               $this
  #22 = Utf8               srt
  #23 = Utf8               hlistReverseSplitRight1
  #24 = Utf8               (Lshapeless/ops/hlist$ReverseSplitRight$ReverseSplitRight0;)Lshapeless/ops/hlist$ReverseSplitRight$ReverseSplitRight0;
  #25 = NameAndType        #23:#24        // hlistReverseSplitRight1:(Lshapeless/ops/hlist$ReverseSplitRight$ReverseSplitRight0;)Lshapeless/ops/hlist$ReverseSplitRight$ReverseSplitRight0;
  #26 = InterfaceMethodref #2.#25         // shapeless/ops/hlist$ReverseSplitRight$LowPriorityReverseSplitRight0.hlistReverseSplitRight1:(Lshapeless/ops/hlist$ReverseSplitRight$ReverseSplitRight0;)Lshapeless/ops/hlist$ReverseSplitRight$ReverseSplitRight0;
  #27 = Utf8               Lshapeless/ops/hlist$ReverseSplitRight$LowPriorityReverseSplitRight0;
  #28 = Utf8               Lshapeless/ops/hlist$ReverseSplitRight$ReverseSplitRight0;
  #29 = Utf8               <RevH:Ljava/lang/Object;RevT::Lshapeless/HList;AccP::Lshapeless/HList;U:Ljava/lang/Object;P::Lshapeless/HList;S::Lshapeless/HList;>(Lshapeless/ops/hlist$ReverseSplitRight$ReverseSplitRight0<TRevT;Lshapeless/$colon$colon<TRevH;TAccP;>;Lshapeless/HNil;TU;TP;TS;>;)Lshapeless/ops/hlist$ReverseSplitRight$ReverseSplitRight0<Lshapeless/$colon$colon<TRevH;TRevT;>;TAccP;Lshapeless/HNil;TU;TP;TS;>;
  #30 = Utf8               <init>
  #31 = Utf8               (Lshapeless/ops/hlist$ReverseSplitRight$LowPriorityReverseSplitRight0;Lshapeless/ops/hlist$ReverseSplitRight$ReverseSplitRight0;)V
  #32 = NameAndType        #30:#31        // "<init>":(Lshapeless/ops/hlist$ReverseSplitRight$LowPriorityReverseSplitRight0;Lshapeless/ops/hlist$ReverseSplitRight$ReverseSplitRight0;)V
  #33 = Methodref          #13.#32        // shapeless/ops/hlist$ReverseSplitRight$LowPriorityReverseSplitRight0$$anon$125."<init>":(Lshapeless/ops/hlist$ReverseSplitRight$LowPriorityReverseSplitRight0;Lshapeless/ops/hlist$ReverseSplitRight$ReverseSplitRight0;)V
  #34 = Utf8               this
  #35 = Utf8               hlistReverseSplitRight2$
  #36 = Utf8               hlistReverseSplitRight2
  #37 = NameAndType        #36:#24        // hlistReverseSplitRight2:(Lshapeless/ops/hlist$ReverseSplitRight$ReverseSplitRight0;)Lshapeless/ops/hlist$ReverseSplitRight$ReverseSplitRight0;
  #38 = InterfaceMethodref #2.#37         // shapeless/ops/hlist$ReverseSplitRight$LowPriorityReverseSplitRight0.hlistReverseSplitRight2:(Lshapeless/ops/hlist$ReverseSplitRight$ReverseSplitRight0;)Lshapeless/ops/hlist$ReverseSplitRight$ReverseSplitRight0;
  #39 = Utf8               <AccPH:Ljava/lang/Object;AccPT::Lshapeless/HList;AccS::Lshapeless/HList;U:Ljava/lang/Object;P::Lshapeless/HList;S::Lshapeless/HList;>(Lshapeless/ops/hlist$ReverseSplitRight$ReverseSplitRight0<Lshapeless/HNil;TAccPT;Lshapeless/$colon$colon<TAccPH;TAccS;>;TU;TP;TS;>;)Lshapeless/ops/hlist$ReverseSplitRight$ReverseSplitRight0<Lshapeless/HNil;Lshapeless/$colon$colon<TAccPH;TAccPT;>;TAccS;TU;TP;TS;>;
  #40 = Methodref          #15.#32        // shapeless/ops/hlist$ReverseSplitRight$LowPriorityReverseSplitRight0$$anon$126."<init>":(Lshapeless/ops/hlist$ReverseSplitRight$LowPriorityReverseSplitRight0;Lshapeless/ops/hlist$ReverseSplitRight$ReverseSplitRight0;)V
  #41 = Utf8               $init$
  #42 = Utf8               (Lshapeless/ops/hlist$ReverseSplitRight$LowPriorityReverseSplitRight0;)V
  #43 = Utf8               Code
  #44 = Utf8               LineNumberTable
  #45 = Utf8               LocalVariableTable
  #46 = Utf8               MethodParameters
  #47 = Utf8               Signature
  #48 = Utf8               InnerClasses
  #49 = Utf8               SourceFile
  #50 = Utf8               ScalaInlineInfo
  #51 = Utf8               Scala
{
  public static shapeless.ops.hlist$ReverseSplitRight$ReverseSplitRight0 hlistReverseSplitRight1$(shapeless.ops.hlist$ReverseSplitRight$LowPriorityReverseSplitRight0, shapeless.ops.hlist$ReverseSplitRight$ReverseSplitRight0);
    descriptor: (Lshapeless/ops/hlist$ReverseSplitRight$LowPriorityReverseSplitRight0;Lshapeless/ops/hlist$ReverseSplitRight$ReverseSplitRight0;)Lshapeless/ops/hlist$ReverseSplitRight$ReverseSplitRight0;
    flags: (0x1009) ACC_PUBLIC, ACC_STATIC, ACC_SYNTHETIC
    Code:
      stack=2, locals=2, args_size=2
         0: aload_0
         1: aload_1
         2: invokespecial #26                 // InterfaceMethod hlistReverseSplitRight1:(Lshapeless/ops/hlist$ReverseSplitRight$ReverseSplitRight0;)Lshapeless/ops/hlist$ReverseSplitRight$ReverseSplitRight0;
         5: areturn
      LineNumberTable:
        line 1931: 0
      LocalVariableTable:
        Start  Length  Slot  Name   Signature
            0       6     0 $this   Lshapeless/ops/hlist$ReverseSplitRight$LowPriorityReverseSplitRight0;
            0       6     1   srt   Lshapeless/ops/hlist$ReverseSplitRight$ReverseSplitRight0;
    MethodParameters:
      Name                           Flags
      $this                          final synthetic
      srt                            final

  public default <RevH extends java.lang.Object, RevT extends shapeless.HList, AccP extends shapeless.HList, U extends java.lang.Object, P extends shapeless.HList, S extends shapeless.HList> shapeless.ops.hlist$ReverseSplitRight$ReverseSplitRight0<shapeless.$colon$colon<RevH, RevT>, AccP, shapeless.HNil, U, P, S> hlistReverseSplitRight1(shapeless.ops.hlist$ReverseSplitRight$ReverseSplitRight0<RevT, shapeless.$colon$colon<RevH, AccP>, shapeless.HNil, U, P, S>);
    descriptor: (Lshapeless/ops/hlist$ReverseSplitRight$ReverseSplitRight0;)Lshapeless/ops/hlist$ReverseSplitRight$ReverseSplitRight0;
    flags: (0x0001) ACC_PUBLIC
    Code:
      stack=4, locals=2, args_size=2
         0: new           #13                 // class shapeless/ops/hlist$ReverseSplitRight$LowPriorityReverseSplitRight0$$anon$125
         3: dup
         4: aconst_null
         5: aload_1
         6: invokespecial #33                 // Method shapeless/ops/hlist$ReverseSplitRight$LowPriorityReverseSplitRight0$$anon$125."<init>":(Lshapeless/ops/hlist$ReverseSplitRight$LowPriorityReverseSplitRight0;Lshapeless/ops/hlist$ReverseSplitRight$ReverseSplitRight0;)V
         9: areturn
      LineNumberTable:
        line 1933: 0
      LocalVariableTable:
        Start  Length  Slot  Name   Signature
            0      10     0  this   Lshapeless/ops/hlist$ReverseSplitRight$LowPriorityReverseSplitRight0;
            0      10     1   srt   Lshapeless/ops/hlist$ReverseSplitRight$ReverseSplitRight0;
    Signature: #29                          // <RevH:Ljava/lang/Object;RevT::Lshapeless/HList;AccP::Lshapeless/HList;U:Ljava/lang/Object;P::Lshapeless/HList;S::Lshapeless/HList;>(Lshapeless/ops/hlist$ReverseSplitRight$ReverseSplitRight0<TRevT;Lshapeless/$colon$colon<TRevH;TAccP;>;Lshapeless/HNil;TU;TP;TS;>;)Lshapeless/ops/hlist$ReverseSplitRight$ReverseSplitRight0<Lshapeless/$colon$colon<TRevH;TRevT;>;TAccP;Lshapeless/HNil;TU;TP;TS;>;
    MethodParameters:
      Name                           Flags
      srt                            final

  public static shapeless.ops.hlist$ReverseSplitRight$ReverseSplitRight0 hlistReverseSplitRight2$(shapeless.ops.hlist$ReverseSplitRight$LowPriorityReverseSplitRight0, shapeless.ops.hlist$ReverseSplitRight$ReverseSplitRight0);
    descriptor: (Lshapeless/ops/hlist$ReverseSplitRight$LowPriorityReverseSplitRight0;Lshapeless/ops/hlist$ReverseSplitRight$ReverseSplitRight0;)Lshapeless/ops/hlist$ReverseSplitRight$ReverseSplitRight0;
    flags: (0x1009) ACC_PUBLIC, ACC_STATIC, ACC_SYNTHETIC
    Code:
      stack=2, locals=2, args_size=2
         0: aload_0
         1: aload_1
         2: invokespecial #38                 // InterfaceMethod hlistReverseSplitRight2:(Lshapeless/ops/hlist$ReverseSplitRight$ReverseSplitRight0;)Lshapeless/ops/hlist$ReverseSplitRight$ReverseSplitRight0;
         5: areturn
      LineNumberTable:
        line 1937: 0
      LocalVariableTable:
        Start  Length  Slot  Name   Signature
            0       6     0 $this   Lshapeless/ops/hlist$ReverseSplitRight$LowPriorityReverseSplitRight0;
            0       6     1   srt   Lshapeless/ops/hlist$ReverseSplitRight$ReverseSplitRight0;
    MethodParameters:
      Name                           Flags
      $this                          final synthetic
      srt                            final

  public default <AccPH extends java.lang.Object, AccPT extends shapeless.HList, AccS extends shapeless.HList, U extends java.lang.Object, P extends shapeless.HList, S extends shapeless.HList> shapeless.ops.hlist$ReverseSplitRight$ReverseSplitRight0<shapeless.HNil, shapeless.$colon$colon<AccPH, AccPT>, AccS, U, P, S> hlistReverseSplitRight2(shapeless.ops.hlist$ReverseSplitRight$ReverseSplitRight0<shapeless.HNil, AccPT, shapeless.$colon$colon<AccPH, AccS>, U, P, S>);
    descriptor: (Lshapeless/ops/hlist$ReverseSplitRight$ReverseSplitRight0;)Lshapeless/ops/hlist$ReverseSplitRight$ReverseSplitRight0;
    flags: (0x0001) ACC_PUBLIC
    Code:
      stack=4, locals=2, args_size=2
         0: new           #15                 // class shapeless/ops/hlist$ReverseSplitRight$LowPriorityReverseSplitRight0$$anon$126
         3: dup
         4: aconst_null
         5: aload_1
         6: invokespecial #40                 // Method shapeless/ops/hlist$ReverseSplitRight$LowPriorityReverseSplitRight0$$anon$126."<init>":(Lshapeless/ops/hlist$ReverseSplitRight$LowPriorityReverseSplitRight0;Lshapeless/ops/hlist$ReverseSplitRight$ReverseSplitRight0;)V
         9: areturn
      LineNumberTable:
        line 1939: 0
      LocalVariableTable:
        Start  Length  Slot  Name   Signature
            0      10     0  this   Lshapeless/ops/hlist$ReverseSplitRight$LowPriorityReverseSplitRight0;
            0      10     1   srt   Lshapeless/ops/hlist$ReverseSplitRight$ReverseSplitRight0;
    Signature: #39                          // <AccPH:Ljava/lang/Object;AccPT::Lshapeless/HList;AccS::Lshapeless/HList;U:Ljava/lang/Object;P::Lshapeless/HList;S::Lshapeless/HList;>(Lshapeless/ops/hlist$ReverseSplitRight$ReverseSplitRight0<Lshapeless/HNil;TAccPT;Lshapeless/$colon$colon<TAccPH;TAccS;>;TU;TP;TS;>;)Lshapeless/ops/hlist$ReverseSplitRight$ReverseSplitRight0<Lshapeless/HNil;Lshapeless/$colon$colon<TAccPH;TAccPT;>;TAccS;TU;TP;TS;>;
    MethodParameters:
      Name                           Flags
      srt                            final

  public static void $init$(shapeless.ops.hlist$ReverseSplitRight$LowPriorityReverseSplitRight0);
    descriptor: (Lshapeless/ops/hlist$ReverseSplitRight$LowPriorityReverseSplitRight0;)V
    flags: (0x0009) ACC_PUBLIC, ACC_STATIC
    Code:
      stack=0, locals=1, args_size=1
         0: return
      LineNumberTable:
        line 1930: 0
      LocalVariableTable:
        Start  Length  Slot  Name   Signature
            0       1     0 $this   Lshapeless/ops/hlist$ReverseSplitRight$LowPriorityReverseSplitRight0;
    MethodParameters:
      Name                           Flags
      $this                          final synthetic
}
InnerClasses:
  public static #10= #7 of #9;            // ReverseSplitRight$=class shapeless/ops/hlist$ReverseSplitRight$ of class shapeless/ops/hlist
  public static #11= #2 of #7;            // LowPriorityReverseSplitRight0=class shapeless/ops/hlist$ReverseSplitRight$LowPriorityReverseSplitRight0 of class shapeless/ops/hlist$ReverseSplitRight$
  public final #13;                       // class shapeless/ops/hlist$ReverseSplitRight$LowPriorityReverseSplitRight0$$anon$125
  public final #15;                       // class shapeless/ops/hlist$ReverseSplitRight$LowPriorityReverseSplitRight0$$anon$126
  public static #18= #17 of #7;           // ReverseSplitRight0=class shapeless/ops/hlist$ReverseSplitRight$ReverseSplitRight0 of class shapeless/ops/hlist$ReverseSplitRight$
SourceFile: "hlists.scala"
  ScalaInlineInfo: length = 0x1D (unknown attribute)
   01 00 00 05 00 29 00 2A 01 00 13 00 14 01 00 17
   00 18 00 00 23 00 14 01 00 24 00 18 00
  Scala: length = 0x0 (unknown attribute)

