Classfile /Users/mw/Projects/slang-braindump/.jar/jar8/assemble/slang-braindump/assemble/content/shapeless/ops/hlist$Repeat$$anon$140.class
  Last modified May 29, 2022; size 1506 bytes
  SHA-256 checksum b06310e05a14b60786d5d4fbb87da7a37840beef6c165bb5583946225c409685
  Compiled from "hlists.scala"
public final class shapeless.ops.hlist$Repeat$$anon$140 extends java.lang.Object implements shapeless.ops.hlist$Repeat<L, shapeless.Succ<Prev>>
  minor version: 0
  major version: 52
  flags: (0x0031) ACC_PUBLIC, ACC_FINAL, ACC_SUPER
  this_class: #2                          // shapeless/ops/hlist$Repeat$$anon$140
  super_class: #5                         // java/lang/Object
  interfaces: 1, fields: 2, methods: 3, attributes: 6
Constant pool:
   #1 = Utf8               shapeless/ops/hlist$Repeat$$anon$140
   #2 = Class              #1             // shapeless/ops/hlist$Repeat$$anon$140
   #3 = Utf8               Ljava/lang/Object;Lshapeless/ops/hlist$Repeat<TL;Lshapeless/Succ<TPrev;>;>;
   #4 = Utf8               java/lang/Object
   #5 = Class              #4             // java/lang/Object
   #6 = Utf8               shapeless/ops/hlist$Repeat
   #7 = Class              #6             // shapeless/ops/hlist$Repeat
   #8 = Utf8               hlists.scala
   #9 = Utf8               shapeless/ops/hlist$Repeat$
  #10 = Class              #9             // shapeless/ops/hlist$Repeat$
  #11 = Utf8               succ
  #12 = Utf8               (Lshapeless/ops/hlist$Repeat;Lshapeless/ops/hlist$Prepend;)Lshapeless/ops/hlist$Repeat;
  #13 = NameAndType        #11:#12        // succ:(Lshapeless/ops/hlist$Repeat;Lshapeless/ops/hlist$Prepend;)Lshapeless/ops/hlist$Repeat;
  #14 = Utf8               shapeless/ops/hlist$Prepend
  #15 = Class              #14            // shapeless/ops/hlist$Prepend
  #16 = Utf8               shapeless/ops/hlist
  #17 = Class              #16            // shapeless/ops/hlist
  #18 = Utf8               Prepend
  #19 = Utf8               Repeat
  #20 = Utf8               Repeat$
  #21 = Utf8               prepend$2
  #22 = Utf8               Lshapeless/ops/hlist$Prepend;
  #23 = Utf8               prev$1
  #24 = Utf8               Lshapeless/ops/hlist$Repeat;
  #25 = Utf8               apply
  #26 = Utf8               (Lshapeless/HList;)Lshapeless/HList;
  #27 = Utf8               (TL;)TP;
  #28 = Utf8               l
  #29 = NameAndType        #21:#22        // prepend$2:Lshapeless/ops/hlist$Prepend;
  #30 = Fieldref           #2.#29         // shapeless/ops/hlist$Repeat$$anon$140.prepend$2:Lshapeless/ops/hlist$Prepend;
  #31 = NameAndType        #23:#24        // prev$1:Lshapeless/ops/hlist$Repeat;
  #32 = Fieldref           #2.#31         // shapeless/ops/hlist$Repeat$$anon$140.prev$1:Lshapeless/ops/hlist$Repeat;
  #33 = Utf8               (Ljava/lang/Object;)Ljava/lang/Object;
  #34 = NameAndType        #25:#33        // apply:(Ljava/lang/Object;)Ljava/lang/Object;
  #35 = InterfaceMethodref #7.#34         // shapeless/ops/hlist$Repeat.apply:(Ljava/lang/Object;)Ljava/lang/Object;
  #36 = Utf8               (Ljava/lang/Object;Ljava/lang/Object;)Ljava/lang/Object;
  #37 = NameAndType        #25:#36        // apply:(Ljava/lang/Object;Ljava/lang/Object;)Ljava/lang/Object;
  #38 = InterfaceMethodref #15.#37        // shapeless/ops/hlist$Prepend.apply:(Ljava/lang/Object;Ljava/lang/Object;)Ljava/lang/Object;
  #39 = Utf8               shapeless/HList
  #40 = Class              #39            // shapeless/HList
  #41 = Utf8               this
  #42 = Utf8               Lshapeless/ops/hlist$Repeat$$anon$140;
  #43 = Utf8               Lshapeless/HList;
  #44 = Utf8               t
  #45 = NameAndType        #25:#26        // apply:(Lshapeless/HList;)Lshapeless/HList;
  #46 = Methodref          #2.#45         // shapeless/ops/hlist$Repeat$$anon$140.apply:(Lshapeless/HList;)Lshapeless/HList;
  #47 = Utf8               Ljava/lang/Object;
  #48 = Utf8               <init>
  #49 = Utf8               (Lshapeless/ops/hlist$Prepend;Lshapeless/ops/hlist$Repeat;)V
  #50 = Utf8               ()V
  #51 = NameAndType        #48:#50        // "<init>":()V
  #52 = Methodref          #5.#51         // java/lang/Object."<init>":()V
  #53 = Utf8               Code
  #54 = Utf8               LineNumberTable
  #55 = Utf8               LocalVariableTable
  #56 = Utf8               Signature
  #57 = Utf8               MethodParameters
  #58 = Utf8               InnerClasses
  #59 = Utf8               EnclosingMethod
  #60 = Utf8               SourceFile
  #61 = Utf8               ScalaInlineInfo
  #62 = Utf8               Scala
{
  private final shapeless.ops.hlist$Prepend prepend$2;
    descriptor: Lshapeless/ops/hlist$Prepend;
    flags: (0x0012) ACC_PRIVATE, ACC_FINAL

  private final shapeless.ops.hlist$Repeat prev$1;
    descriptor: Lshapeless/ops/hlist$Repeat;
    flags: (0x0012) ACC_PRIVATE, ACC_FINAL

  public P apply(L);
    descriptor: (Lshapeless/HList;)Lshapeless/HList;
    flags: (0x0001) ACC_PUBLIC
    Code:
      stack=4, locals=2, args_size=2
         0: aload_0
         1: getfield      #30                 // Field prepend$2:Lshapeless/ops/hlist$Prepend;
         4: aload_1
         5: aload_0
         6: getfield      #32                 // Field prev$1:Lshapeless/ops/hlist$Repeat;
         9: aload_1
        10: invokeinterface #35,  2           // InterfaceMethod shapeless/ops/hlist$Repeat.apply:(Ljava/lang/Object;)Ljava/lang/Object;
        15: invokeinterface #38,  3           // InterfaceMethod shapeless/ops/hlist$Prepend.apply:(Ljava/lang/Object;Ljava/lang/Object;)Ljava/lang/Object;
        20: checkcast     #40                 // class shapeless/HList
        23: areturn
      LineNumberTable:
        line 2118: 0
      LocalVariableTable:
        Start  Length  Slot  Name   Signature
            0      24     0  this   Lshapeless/ops/hlist$Repeat$$anon$140;
            0      24     1     l   Lshapeless/HList;
    Signature: #27                          // (TL;)TP;
    MethodParameters:
      Name                           Flags
      l                              final

  public java.lang.Object apply(java.lang.Object);
    descriptor: (Ljava/lang/Object;)Ljava/lang/Object;
    flags: (0x1041) ACC_PUBLIC, ACC_BRIDGE, ACC_SYNTHETIC
    Code:
      stack=2, locals=2, args_size=2
         0: aload_0
         1: aload_1
         2: checkcast     #40                 // class shapeless/HList
         5: invokevirtual #46                 // Method apply:(Lshapeless/HList;)Lshapeless/HList;
         8: areturn
      LineNumberTable:
        line 2116: 0
      LocalVariableTable:
        Start  Length  Slot  Name   Signature
            0       9     0  this   Lshapeless/ops/hlist$Repeat$$anon$140;
            0       9     1     t   Ljava/lang/Object;
    MethodParameters:
      Name                           Flags
      t                              final

  public shapeless.ops.hlist$Repeat$$anon$140(shapeless.ops.hlist$Prepend, shapeless.ops.hlist$Repeat);
    descriptor: (Lshapeless/ops/hlist$Prepend;Lshapeless/ops/hlist$Repeat;)V
    flags: (0x0001) ACC_PUBLIC
    Code:
      stack=2, locals=3, args_size=3
         0: aload_0
         1: aload_1
         2: putfield      #30                 // Field prepend$2:Lshapeless/ops/hlist$Prepend;
         5: aload_0
         6: aload_2
         7: putfield      #32                 // Field prev$1:Lshapeless/ops/hlist$Repeat;
        10: aload_0
        11: invokespecial #52                 // Method java/lang/Object."<init>":()V
        14: return
      LineNumberTable:
        line 2115: 0
        line 2114: 5
        line 2116: 10
      LocalVariableTable:
        Start  Length  Slot  Name   Signature
            0      15     0  this   Lshapeless/ops/hlist$Repeat$$anon$140;
            0      15     1 prepend$2   Lshapeless/ops/hlist$Prepend;
            0      15     2 prev$1   Lshapeless/ops/hlist$Repeat;
    MethodParameters:
      Name                           Flags
      prepend$2                      final
      prev$1                         final
}
InnerClasses:
  public static #18= #15 of #17;          // Prepend=class shapeless/ops/hlist$Prepend of class shapeless/ops/hlist
  public static #19= #7 of #17;           // Repeat=class shapeless/ops/hlist$Repeat of class shapeless/ops/hlist
  public static #20= #10 of #17;          // Repeat$=class shapeless/ops/hlist$Repeat$ of class shapeless/ops/hlist
  public final #2;                        // class shapeless/ops/hlist$Repeat$$anon$140
EnclosingMethod: #10.#13                // shapeless.ops.hlist$Repeat$.succ
Signature: #3                           // Ljava/lang/Object;Lshapeless/ops/hlist$Repeat<TL;Lshapeless/Succ<TPrev;>;>;
SourceFile: "hlists.scala"
  ScalaInlineInfo: length = 0x13 (unknown attribute)
   01 01 00 03 00 30 00 31 01 00 19 00 21 01 00 19
   00 1A 01
  Scala: length = 0x0 (unknown attribute)

