Classfile /Users/mw/Projects/slang-braindump/.jar/jar8/assemble/slang-braindump/assemble/content/shapeless/ops/hlist$ReverseSplitLeft$.class
  Last modified May 29, 2022; size 2136 bytes
  SHA-256 checksum 6393f8fa506cd3d1c7deedea2eff89963fce65ee5994cfb0769bce78b5ec835b
  Compiled from "hlists.scala"
public class shapeless.ops.hlist$ReverseSplitLeft$ implements java.io.Serializable
  minor version: 0
  major version: 52
  flags: (0x0021) ACC_PUBLIC, ACC_SUPER
  this_class: #2                          // shapeless/ops/hlist$ReverseSplitLeft$
  super_class: #4                         // java/lang/Object
  interfaces: 1, fields: 1, methods: 5, attributes: 4
Constant pool:
   #1 = Utf8               shapeless/ops/hlist$ReverseSplitLeft$
   #2 = Class              #1             // shapeless/ops/hlist$ReverseSplitLeft$
   #3 = Utf8               java/lang/Object
   #4 = Class              #3             // java/lang/Object
   #5 = Utf8               java/io/Serializable
   #6 = Class              #5             // java/io/Serializable
   #7 = Utf8               hlists.scala
   #8 = Utf8               shapeless/ops/hlist$ReverseSplitLeft
   #9 = Class              #8             // shapeless/ops/hlist$ReverseSplitLeft
  #10 = Utf8               shapeless/ops/hlist
  #11 = Class              #10            // shapeless/ops/hlist
  #12 = Utf8               ReverseSplitLeft
  #13 = Utf8               ReverseSplitLeft$
  #14 = Utf8               shapeless/ops/hlist$ReverseSplitLeft$$anon$117
  #15 = Class              #14            // shapeless/ops/hlist$ReverseSplitLeft$$anon$117
  #16 = Utf8               shapeless/ops/hlist$ReverseSplitLeft$LowPriorityReverseSplitLeft0
  #17 = Class              #16            // shapeless/ops/hlist$ReverseSplitLeft$LowPriorityReverseSplitLeft0
  #18 = Utf8               LowPriorityReverseSplitLeft0
  #19 = Utf8               shapeless/ops/hlist$ReverseSplitLeft$ReverseSplitLeft0
  #20 = Class              #19            // shapeless/ops/hlist$ReverseSplitLeft$ReverseSplitLeft0
  #21 = Utf8               ReverseSplitLeft0
  #22 = Utf8               shapeless/ops/hlist$ReverseSplitLeft$ReverseSplitLeft0$
  #23 = Class              #22            // shapeless/ops/hlist$ReverseSplitLeft$ReverseSplitLeft0$
  #24 = Utf8               ReverseSplitLeft0$
  #25 = Utf8               MODULE$
  #26 = Utf8               Lshapeless/ops/hlist$ReverseSplitLeft$;
  #27 = Utf8               <clinit>
  #28 = Utf8               ()V
  #29 = Utf8               <init>
  #30 = NameAndType        #29:#28        // "<init>":()V
  #31 = Methodref          #2.#30         // shapeless/ops/hlist$ReverseSplitLeft$."<init>":()V
  #32 = NameAndType        #25:#26        // MODULE$:Lshapeless/ops/hlist$ReverseSplitLeft$;
  #33 = Fieldref           #2.#32         // shapeless/ops/hlist$ReverseSplitLeft$.MODULE$:Lshapeless/ops/hlist$ReverseSplitLeft$;
  #34 = Utf8               apply
  #35 = Utf8               (Lshapeless/ops/hlist$ReverseSplitLeft;)Lshapeless/ops/hlist$ReverseSplitLeft;
  #36 = Utf8               <L::Lshapeless/HList;U:Ljava/lang/Object;>(Lshapeless/ops/hlist$ReverseSplitLeft<TL;TU;>;)Lshapeless/ops/hlist$ReverseSplitLeft<TL;TU;>;
  #37 = Utf8               split
  #38 = Utf8               this
  #39 = Utf8               Lshapeless/ops/hlist$ReverseSplitLeft;
  #40 = Utf8               reverseSplitLeft
  #41 = Utf8               (Lshapeless/ops/hlist$ReverseSplitLeft$ReverseSplitLeft0;)Lshapeless/ops/hlist$ReverseSplitLeft;
  #42 = Utf8               <L::Lshapeless/HList;U:Ljava/lang/Object;P::Lshapeless/HList;S::Lshapeless/HList;>(Lshapeless/ops/hlist$ReverseSplitLeft$ReverseSplitLeft0<Lshapeless/HNil;TL;TU;TP;TS;>;)Lshapeless/ops/hlist$ReverseSplitLeft<TL;TU;>;
  #43 = Utf8               splitLeft
  #44 = Utf8               (Lshapeless/ops/hlist$ReverseSplitLeft$ReverseSplitLeft0;)V
  #45 = NameAndType        #29:#44        // "<init>":(Lshapeless/ops/hlist$ReverseSplitLeft$ReverseSplitLeft0;)V
  #46 = Methodref          #15.#45        // shapeless/ops/hlist$ReverseSplitLeft$$anon$117."<init>":(Lshapeless/ops/hlist$ReverseSplitLeft$ReverseSplitLeft0;)V
  #47 = Utf8               Lshapeless/ops/hlist$ReverseSplitLeft$ReverseSplitLeft0;
  #48 = Utf8               writeReplace
  #49 = Utf8               ()Ljava/lang/Object;
  #50 = Utf8               scala/runtime/ModuleSerializationProxy
  #51 = Class              #50            // scala/runtime/ModuleSerializationProxy
  #52 = Utf8               (Ljava/lang/Class;)V
  #53 = NameAndType        #29:#52        // "<init>":(Ljava/lang/Class;)V
  #54 = Methodref          #51.#53        // scala/runtime/ModuleSerializationProxy."<init>":(Ljava/lang/Class;)V
  #55 = Methodref          #4.#30         // java/lang/Object."<init>":()V
  #56 = Utf8               Code
  #57 = Utf8               LineNumberTable
  #58 = Utf8               LocalVariableTable
  #59 = Utf8               Signature
  #60 = Utf8               MethodParameters
  #61 = Utf8               InnerClasses
  #62 = Utf8               SourceFile
  #63 = Utf8               ScalaInlineInfo
  #64 = Utf8               Scala
{
  public static final shapeless.ops.hlist$ReverseSplitLeft$ MODULE$;
    descriptor: Lshapeless/ops/hlist$ReverseSplitLeft$;
    flags: (0x0019) ACC_PUBLIC, ACC_STATIC, ACC_FINAL

  public static {};
    descriptor: ()V
    flags: (0x0009) ACC_PUBLIC, ACC_STATIC
    Code:
      stack=2, locals=0, args_size=0
         0: new           #2                  // class shapeless/ops/hlist$ReverseSplitLeft$
         3: dup
         4: invokespecial #31                 // Method "<init>":()V
         7: putstatic     #33                 // Field MODULE$:Lshapeless/ops/hlist$ReverseSplitLeft$;
        10: return
      LineNumberTable:
        line 1798: 0

  public <L extends shapeless.HList, U extends java.lang.Object> shapeless.ops.hlist$ReverseSplitLeft<L, U> apply(shapeless.ops.hlist$ReverseSplitLeft<L, U>);
    descriptor: (Lshapeless/ops/hlist$ReverseSplitLeft;)Lshapeless/ops/hlist$ReverseSplitLeft;
    flags: (0x0001) ACC_PUBLIC
    Code:
      stack=1, locals=2, args_size=2
         0: aload_1
         1: areturn
      LineNumberTable:
        line 1800: 0
      LocalVariableTable:
        Start  Length  Slot  Name   Signature
            0       2     0  this   Lshapeless/ops/hlist$ReverseSplitLeft$;
            0       2     1 split   Lshapeless/ops/hlist$ReverseSplitLeft;
    Signature: #36                          // <L::Lshapeless/HList;U:Ljava/lang/Object;>(Lshapeless/ops/hlist$ReverseSplitLeft<TL;TU;>;)Lshapeless/ops/hlist$ReverseSplitLeft<TL;TU;>;
    MethodParameters:
      Name                           Flags
      split                          final

  public <L extends shapeless.HList, U extends java.lang.Object, P extends shapeless.HList, S extends shapeless.HList> shapeless.ops.hlist$ReverseSplitLeft<L, U> reverseSplitLeft(shapeless.ops.hlist$ReverseSplitLeft$ReverseSplitLeft0<shapeless.HNil, L, U, P, S>);
    descriptor: (Lshapeless/ops/hlist$ReverseSplitLeft$ReverseSplitLeft0;)Lshapeless/ops/hlist$ReverseSplitLeft;
    flags: (0x0001) ACC_PUBLIC
    Code:
      stack=3, locals=2, args_size=2
         0: new           #15                 // class shapeless/ops/hlist$ReverseSplitLeft$$anon$117
         3: dup
         4: aload_1
         5: invokespecial #46                 // Method shapeless/ops/hlist$ReverseSplitLeft$$anon$117."<init>":(Lshapeless/ops/hlist$ReverseSplitLeft$ReverseSplitLeft0;)V
         8: areturn
      LineNumberTable:
        line 1809: 0
      LocalVariableTable:
        Start  Length  Slot  Name   Signature
            0       9     0  this   Lshapeless/ops/hlist$ReverseSplitLeft$;
            0       9     1 splitLeft   Lshapeless/ops/hlist$ReverseSplitLeft$ReverseSplitLeft0;
    Signature: #42                          // <L::Lshapeless/HList;U:Ljava/lang/Object;P::Lshapeless/HList;S::Lshapeless/HList;>(Lshapeless/ops/hlist$ReverseSplitLeft$ReverseSplitLeft0<Lshapeless/HNil;TL;TU;TP;TS;>;)Lshapeless/ops/hlist$ReverseSplitLeft<TL;TU;>;
    MethodParameters:
      Name                           Flags
      splitLeft                      final

  private java.lang.Object writeReplace();
    descriptor: ()Ljava/lang/Object;
    flags: (0x0002) ACC_PRIVATE
    Code:
      stack=3, locals=1, args_size=1
         0: new           #51                 // class scala/runtime/ModuleSerializationProxy
         3: dup
         4: ldc           #2                  // class shapeless/ops/hlist$ReverseSplitLeft$
         6: invokespecial #54                 // Method scala/runtime/ModuleSerializationProxy."<init>":(Ljava/lang/Class;)V
         9: areturn
      LineNumberTable:
        line 1798: 0
      LocalVariableTable:
        Start  Length  Slot  Name   Signature
            0      10     0  this   Lshapeless/ops/hlist$ReverseSplitLeft$;

  public shapeless.ops.hlist$ReverseSplitLeft$();
    descriptor: ()V
    flags: (0x0001) ACC_PUBLIC
    Code:
      stack=1, locals=1, args_size=1
         0: aload_0
         1: invokespecial #55                 // Method java/lang/Object."<init>":()V
         4: return
      LineNumberTable:
        line 1841: 0
        line 1798: 4
      LocalVariableTable:
        Start  Length  Slot  Name   Signature
            0       5     0  this   Lshapeless/ops/hlist$ReverseSplitLeft$;
}
InnerClasses:
  public static #12= #9 of #11;           // ReverseSplitLeft=class shapeless/ops/hlist$ReverseSplitLeft of class shapeless/ops/hlist
  public static #13= #2 of #11;           // ReverseSplitLeft$=class shapeless/ops/hlist$ReverseSplitLeft$ of class shapeless/ops/hlist
  public final #15;                       // class shapeless/ops/hlist$ReverseSplitLeft$$anon$117
  public static #18= #17 of #2;           // LowPriorityReverseSplitLeft0=class shapeless/ops/hlist$ReverseSplitLeft$LowPriorityReverseSplitLeft0 of class shapeless/ops/hlist$ReverseSplitLeft$
  public static #21= #20 of #2;           // ReverseSplitLeft0=class shapeless/ops/hlist$ReverseSplitLeft$ReverseSplitLeft0 of class shapeless/ops/hlist$ReverseSplitLeft$
  public static #24= #23 of #2;           // ReverseSplitLeft0$=class shapeless/ops/hlist$ReverseSplitLeft$ReverseSplitLeft0$ of class shapeless/ops/hlist$ReverseSplitLeft$
SourceFile: "hlists.scala"
  ScalaInlineInfo: length = 0x18 (unknown attribute)
   01 01 00 04 00 1D 00 1C 01 00 22 00 23 01 00 28
   00 29 01 00 30 00 31 01
  Scala: length = 0x0 (unknown attribute)

