Classfile /Users/mw/Projects/slang-braindump/.jar/jar8/assemble/slang-braindump/assemble/content/shapeless/ops/hlist$HNilHKernel$.class
  Last modified May 29, 2022; size 4346 bytes
  SHA-256 checksum e9e65011b0f08e8a0688ddb4e1d55968a13724976478e544c2e596a3162b32ed
  Compiled from "hlists.scala"
public class shapeless.ops.hlist$HNilHKernel$ implements shapeless.ops.hlist$HNilHKernel,scala.Product,java.io.Serializable
  minor version: 0
  major version: 52
  flags: (0x0021) ACC_PUBLIC, ACC_SUPER
  this_class: #2                          // shapeless/ops/hlist$HNilHKernel$
  super_class: #4                         // java/lang/Object
  interfaces: 3, fields: 1, methods: 19, attributes: 4
Constant pool:
    #1 = Utf8               shapeless/ops/hlist$HNilHKernel$
    #2 = Class              #1            // shapeless/ops/hlist$HNilHKernel$
    #3 = Utf8               java/lang/Object
    #4 = Class              #3            // java/lang/Object
    #5 = Utf8               shapeless/ops/hlist$HNilHKernel
    #6 = Class              #5            // shapeless/ops/hlist$HNilHKernel
    #7 = Utf8               scala/Product
    #8 = Class              #7            // scala/Product
    #9 = Utf8               java/io/Serializable
   #10 = Class              #9            // java/io/Serializable
   #11 = Utf8               hlists.scala
   #12 = Utf8               shapeless/PolyDefns$$tilde$greater
   #13 = Class              #12           // shapeless/PolyDefns$$tilde$greater
   #14 = Utf8               shapeless/PolyDefns
   #15 = Class              #14           // shapeless/PolyDefns
   #16 = Utf8               $tilde$greater
   #17 = Utf8               shapeless/ops/hlist
   #18 = Class              #17           // shapeless/ops/hlist
   #19 = Utf8               HNilHKernel
   #20 = Utf8               HNilHKernel$
   #21 = Utf8               MODULE$
   #22 = Utf8               Lshapeless/ops/hlist$HNilHKernel$;
   #23 = Utf8               <clinit>
   #24 = Utf8               ()V
   #25 = Utf8               <init>
   #26 = NameAndType        #25:#24       // "<init>":()V
   #27 = Methodref          #2.#26        // shapeless/ops/hlist$HNilHKernel$."<init>":()V
   #28 = NameAndType        #21:#22       // MODULE$:Lshapeless/ops/hlist$HNilHKernel$;
   #29 = Fieldref           #2.#28        // shapeless/ops/hlist$HNilHKernel$.MODULE$:Lshapeless/ops/hlist$HNilHKernel$;
   #30 = Utf8               $init$
   #31 = Utf8               (Lshapeless/ops/hlist$HNilHKernel;)V
   #32 = NameAndType        #30:#31       // $init$:(Lshapeless/ops/hlist$HNilHKernel;)V
   #33 = InterfaceMethodref #6.#32        // shapeless/ops/hlist$HNilHKernel.$init$:(Lshapeless/ops/hlist$HNilHKernel;)V
   #34 = Utf8               (Lscala/Product;)V
   #35 = NameAndType        #30:#34       // $init$:(Lscala/Product;)V
   #36 = InterfaceMethodref #8.#35        // scala/Product.$init$:(Lscala/Product;)V
   #37 = Utf8               productElementName
   #38 = Utf8               (I)Ljava/lang/String;
   #39 = Utf8               n
   #40 = Utf8               productElementName$
   #41 = Utf8               (Lscala/Product;I)Ljava/lang/String;
   #42 = NameAndType        #40:#41       // productElementName$:(Lscala/Product;I)Ljava/lang/String;
   #43 = InterfaceMethodref #8.#42        // scala/Product.productElementName$:(Lscala/Product;I)Ljava/lang/String;
   #44 = Utf8               this
   #45 = Utf8               I
   #46 = Utf8               productElementNames
   #47 = Utf8               ()Lscala/collection/Iterator;
   #48 = Utf8               ()Lscala/collection/Iterator<Ljava/lang/String;>;
   #49 = Utf8               productElementNames$
   #50 = Utf8               (Lscala/Product;)Lscala/collection/Iterator;
   #51 = NameAndType        #49:#50       // productElementNames$:(Lscala/Product;)Lscala/collection/Iterator;
   #52 = InterfaceMethodref #8.#51        // scala/Product.productElementNames$:(Lscala/Product;)Lscala/collection/Iterator;
   #53 = Utf8               map
   #54 = Utf8               (Lshapeless/PolyDefns$$tilde$greater;Lshapeless/HNil;)Lshapeless/HNil;
   #55 = Utf8               <F:Ljava/lang/Object;G:Ljava/lang/Object;>(Lshapeless/PolyDefns$$tilde$greater<TF;TG;>;Lshapeless/HNil;)Lshapeless/HNil;
   #56 = Utf8               f
   #57 = Utf8               l
   #58 = Utf8               map$
   #59 = Utf8               (Lshapeless/ops/hlist$HNilHKernel;Lshapeless/PolyDefns$$tilde$greater;Lshapeless/HNil;)Lshapeless/HNil;
   #60 = NameAndType        #58:#59       // map$:(Lshapeless/ops/hlist$HNilHKernel;Lshapeless/PolyDefns$$tilde$greater;Lshapeless/HNil;)Lshapeless/HNil;
   #61 = InterfaceMethodref #6.#60        // shapeless/ops/hlist$HNilHKernel.map$:(Lshapeless/ops/hlist$HNilHKernel;Lshapeless/PolyDefns$$tilde$greater;Lshapeless/HNil;)Lshapeless/HNil;
   #62 = Utf8               Lshapeless/PolyDefns$$tilde$greater;
   #63 = Utf8               Lshapeless/HNil;
   #64 = Utf8               tabulate
   #65 = Utf8               (ILscala/Function1;)Lshapeless/HNil;
   #66 = Utf8               <C:Ljava/lang/Object;>(ILscala/Function1<Ljava/lang/Object;TC;>;)Lshapeless/HNil;
   #67 = Utf8               from
   #68 = Utf8               tabulate$
   #69 = Utf8               (Lshapeless/ops/hlist$HNilHKernel;ILscala/Function1;)Lshapeless/HNil;
   #70 = NameAndType        #68:#69       // tabulate$:(Lshapeless/ops/hlist$HNilHKernel;ILscala/Function1;)Lshapeless/HNil;
   #71 = InterfaceMethodref #6.#70        // shapeless/ops/hlist$HNilHKernel.tabulate$:(Lshapeless/ops/hlist$HNilHKernel;ILscala/Function1;)Lshapeless/HNil;
   #72 = Utf8               Lscala/Function1;
   #73 = Utf8               toList
   #74 = Utf8               (Lshapeless/HNil;)Lscala/collection/immutable/List;
   #75 = Utf8               <C:Ljava/lang/Object;>(Lshapeless/HNil;)Lscala/collection/immutable/List<TC;>;
   #76 = Utf8               toList$
   #77 = Utf8               (Lshapeless/ops/hlist$HNilHKernel;Lshapeless/HNil;)Lscala/collection/immutable/List;
   #78 = NameAndType        #76:#77       // toList$:(Lshapeless/ops/hlist$HNilHKernel;Lshapeless/HNil;)Lscala/collection/immutable/List;
   #79 = InterfaceMethodref #6.#78        // shapeless/ops/hlist$HNilHKernel.toList$:(Lshapeless/ops/hlist$HNilHKernel;Lshapeless/HNil;)Lscala/collection/immutable/List;
   #80 = Utf8               length
   #81 = Utf8               ()I
   #82 = Utf8               length$
   #83 = Utf8               (Lshapeless/ops/hlist$HNilHKernel;)I
   #84 = NameAndType        #82:#83       // length$:(Lshapeless/ops/hlist$HNilHKernel;)I
   #85 = InterfaceMethodref #6.#84        // shapeless/ops/hlist$HNilHKernel.length$:(Lshapeless/ops/hlist$HNilHKernel;)I
   #86 = Utf8               productPrefix
   #87 = Utf8               ()Ljava/lang/String;
   #88 = String             #19           // HNilHKernel
   #89 = Utf8               productArity
   #90 = Utf8               productElement
   #91 = Utf8               (I)Ljava/lang/Object;
   #92 = Utf8               x$1
   #93 = Utf8               scala/runtime/Statics
   #94 = Class              #93           // scala/runtime/Statics
   #95 = Utf8               ioobe
   #96 = NameAndType        #95:#91       // ioobe:(I)Ljava/lang/Object;
   #97 = Methodref          #94.#96       // scala/runtime/Statics.ioobe:(I)Ljava/lang/Object;
   #98 = Utf8               productIterator
   #99 = Utf8               ()Lscala/collection/Iterator<Ljava/lang/Object;>;
  #100 = Utf8               scala/runtime/ScalaRunTime$
  #101 = Class              #100          // scala/runtime/ScalaRunTime$
  #102 = Utf8               Lscala/runtime/ScalaRunTime$;
  #103 = NameAndType        #21:#102      // MODULE$:Lscala/runtime/ScalaRunTime$;
  #104 = Fieldref           #101.#103     // scala/runtime/ScalaRunTime$.MODULE$:Lscala/runtime/ScalaRunTime$;
  #105 = Utf8               typedProductIterator
  #106 = NameAndType        #105:#50      // typedProductIterator:(Lscala/Product;)Lscala/collection/Iterator;
  #107 = Methodref          #101.#106     // scala/runtime/ScalaRunTime$.typedProductIterator:(Lscala/Product;)Lscala/collection/Iterator;
  #108 = Utf8               canEqual
  #109 = Utf8               (Ljava/lang/Object;)Z
  #110 = Utf8               Ljava/lang/Object;
  #111 = Utf8               hashCode
  #112 = Integer            1480857052
  #113 = Utf8               toString
  #114 = Utf8               writeReplace
  #115 = Utf8               ()Ljava/lang/Object;
  #116 = Utf8               scala/runtime/ModuleSerializationProxy
  #117 = Class              #116          // scala/runtime/ModuleSerializationProxy
  #118 = Utf8               (Ljava/lang/Class;)V
  #119 = NameAndType        #25:#118      // "<init>":(Ljava/lang/Class;)V
  #120 = Methodref          #117.#119     // scala/runtime/ModuleSerializationProxy."<init>":(Ljava/lang/Class;)V
  #121 = Utf8               (Lshapeless/HList;)Lscala/collection/immutable/List;
  #122 = Utf8               shapeless/HNil
  #123 = Class              #122          // shapeless/HNil
  #124 = NameAndType        #73:#74       // toList:(Lshapeless/HNil;)Lscala/collection/immutable/List;
  #125 = Methodref          #2.#124       // shapeless/ops/hlist$HNilHKernel$.toList:(Lshapeless/HNil;)Lscala/collection/immutable/List;
  #126 = Utf8               Lshapeless/HList;
  #127 = Utf8               (ILscala/Function1;)Lshapeless/HList;
  #128 = NameAndType        #64:#65       // tabulate:(ILscala/Function1;)Lshapeless/HNil;
  #129 = Methodref          #2.#128       // shapeless/ops/hlist$HNilHKernel$.tabulate:(ILscala/Function1;)Lshapeless/HNil;
  #130 = Utf8               (Lshapeless/PolyDefns$$tilde$greater;Lshapeless/HList;)Lshapeless/HList;
  #131 = NameAndType        #53:#54       // map:(Lshapeless/PolyDefns$$tilde$greater;Lshapeless/HNil;)Lshapeless/HNil;
  #132 = Methodref          #2.#131       // shapeless/ops/hlist$HNilHKernel$.map:(Lshapeless/PolyDefns$$tilde$greater;Lshapeless/HNil;)Lshapeless/HNil;
  #133 = Methodref          #4.#26        // java/lang/Object."<init>":()V
  #134 = Utf8               Code
  #135 = Utf8               LineNumberTable
  #136 = Utf8               LocalVariableTable
  #137 = Utf8               MethodParameters
  #138 = Utf8               Signature
  #139 = Utf8               StackMapTable
  #140 = Utf8               InnerClasses
  #141 = Utf8               SourceFile
  #142 = Utf8               ScalaInlineInfo
  #143 = Utf8               Scala
{
  public static final shapeless.ops.hlist$HNilHKernel$ MODULE$;
    descriptor: Lshapeless/ops/hlist$HNilHKernel$;
    flags: (0x0019) ACC_PUBLIC, ACC_STATIC, ACC_FINAL

  public static {};
    descriptor: ()V
    flags: (0x0009) ACC_PUBLIC, ACC_STATIC
    Code:
      stack=2, locals=0, args_size=0
         0: new           #2                  // class shapeless/ops/hlist$HNilHKernel$
         3: dup
         4: invokespecial #27                 // Method "<init>":()V
         7: putstatic     #29                 // Field MODULE$:Lshapeless/ops/hlist$HNilHKernel$;
        10: getstatic     #29                 // Field MODULE$:Lshapeless/ops/hlist$HNilHKernel$;
        13: invokestatic  #33                 // InterfaceMethod shapeless/ops/hlist$HNilHKernel.$init$:(Lshapeless/ops/hlist$HNilHKernel;)V
        16: getstatic     #29                 // Field MODULE$:Lshapeless/ops/hlist$HNilHKernel$;
        19: invokestatic  #36                 // InterfaceMethod scala/Product.$init$:(Lscala/Product;)V
        22: return
      LineNumberTable:
        line 190: 0

  public java.lang.String productElementName(int);
    descriptor: (I)Ljava/lang/String;
    flags: (0x0001) ACC_PUBLIC
    Code:
      stack=2, locals=2, args_size=2
         0: aload_0
         1: iload_1
         2: invokestatic  #43                 // InterfaceMethod scala/Product.productElementName$:(Lscala/Product;I)Ljava/lang/String;
         5: areturn
      LineNumberTable:
        line 190: 0
      LocalVariableTable:
        Start  Length  Slot  Name   Signature
            0       6     0  this   Lshapeless/ops/hlist$HNilHKernel$;
            0       6     1     n   I
    MethodParameters:
      Name                           Flags
      n                              final

  public scala.collection.Iterator<java.lang.String> productElementNames();
    descriptor: ()Lscala/collection/Iterator;
    flags: (0x0001) ACC_PUBLIC
    Code:
      stack=1, locals=1, args_size=1
         0: aload_0
         1: invokestatic  #52                 // InterfaceMethod scala/Product.productElementNames$:(Lscala/Product;)Lscala/collection/Iterator;
         4: areturn
      LineNumberTable:
        line 190: 0
      LocalVariableTable:
        Start  Length  Slot  Name   Signature
            0       5     0  this   Lshapeless/ops/hlist$HNilHKernel$;
    Signature: #48                          // ()Lscala/collection/Iterator<Ljava/lang/String;>;

  public <F extends java.lang.Object, G extends java.lang.Object> shapeless.HNil map(shapeless.PolyDefns$$tilde$greater<F, G>, shapeless.HNil);
    descriptor: (Lshapeless/PolyDefns$$tilde$greater;Lshapeless/HNil;)Lshapeless/HNil;
    flags: (0x0001) ACC_PUBLIC
    Code:
      stack=3, locals=3, args_size=3
         0: aload_0
         1: aload_1
         2: aload_2
         3: invokestatic  #61                 // InterfaceMethod shapeless/ops/hlist$HNilHKernel.map$:(Lshapeless/ops/hlist$HNilHKernel;Lshapeless/PolyDefns$$tilde$greater;Lshapeless/HNil;)Lshapeless/HNil;
         6: areturn
      LineNumberTable:
        line 190: 0
      LocalVariableTable:
        Start  Length  Slot  Name   Signature
            0       7     0  this   Lshapeless/ops/hlist$HNilHKernel$;
            0       7     1     f   Lshapeless/PolyDefns$$tilde$greater;
            0       7     2     l   Lshapeless/HNil;
    Signature: #55                          // <F:Ljava/lang/Object;G:Ljava/lang/Object;>(Lshapeless/PolyDefns$$tilde$greater<TF;TG;>;Lshapeless/HNil;)Lshapeless/HNil;
    MethodParameters:
      Name                           Flags
      f                              final
      l                              final

  public <C extends java.lang.Object> shapeless.HNil tabulate(int, scala.Function1<java.lang.Object, C>);
    descriptor: (ILscala/Function1;)Lshapeless/HNil;
    flags: (0x0001) ACC_PUBLIC
    Code:
      stack=3, locals=3, args_size=3
         0: aload_0
         1: iload_1
         2: aload_2
         3: invokestatic  #71                 // InterfaceMethod shapeless/ops/hlist$HNilHKernel.tabulate$:(Lshapeless/ops/hlist$HNilHKernel;ILscala/Function1;)Lshapeless/HNil;
         6: areturn
      LineNumberTable:
        line 190: 0
      LocalVariableTable:
        Start  Length  Slot  Name   Signature
            0       7     0  this   Lshapeless/ops/hlist$HNilHKernel$;
            0       7     1  from   I
            0       7     2     f   Lscala/Function1;
    Signature: #66                          // <C:Ljava/lang/Object;>(ILscala/Function1<Ljava/lang/Object;TC;>;)Lshapeless/HNil;
    MethodParameters:
      Name                           Flags
      from                           final
      f                              final

  public <C extends java.lang.Object> scala.collection.immutable.List<C> toList(shapeless.HNil);
    descriptor: (Lshapeless/HNil;)Lscala/collection/immutable/List;
    flags: (0x0001) ACC_PUBLIC
    Code:
      stack=2, locals=2, args_size=2
         0: aload_0
         1: aload_1
         2: invokestatic  #79                 // InterfaceMethod shapeless/ops/hlist$HNilHKernel.toList$:(Lshapeless/ops/hlist$HNilHKernel;Lshapeless/HNil;)Lscala/collection/immutable/List;
         5: areturn
      LineNumberTable:
        line 190: 0
      LocalVariableTable:
        Start  Length  Slot  Name   Signature
            0       6     0  this   Lshapeless/ops/hlist$HNilHKernel$;
            0       6     1     l   Lshapeless/HNil;
    Signature: #75                          // <C:Ljava/lang/Object;>(Lshapeless/HNil;)Lscala/collection/immutable/List<TC;>;
    MethodParameters:
      Name                           Flags
      l                              final

  public int length();
    descriptor: ()I
    flags: (0x0001) ACC_PUBLIC
    Code:
      stack=1, locals=1, args_size=1
         0: aload_0
         1: invokestatic  #85                 // InterfaceMethod shapeless/ops/hlist$HNilHKernel.length$:(Lshapeless/ops/hlist$HNilHKernel;)I
         4: ireturn
      LineNumberTable:
        line 190: 0
      LocalVariableTable:
        Start  Length  Slot  Name   Signature
            0       5     0  this   Lshapeless/ops/hlist$HNilHKernel$;

  public java.lang.String productPrefix();
    descriptor: ()Ljava/lang/String;
    flags: (0x0001) ACC_PUBLIC
    Code:
      stack=1, locals=1, args_size=1
         0: ldc           #88                 // String HNilHKernel
         2: areturn
      LineNumberTable:
        line 190: 0
      LocalVariableTable:
        Start  Length  Slot  Name   Signature
            0       3     0  this   Lshapeless/ops/hlist$HNilHKernel$;

  public int productArity();
    descriptor: ()I
    flags: (0x0001) ACC_PUBLIC
    Code:
      stack=1, locals=1, args_size=1
         0: iconst_0
         1: ireturn
      LineNumberTable:
        line 190: 0
      LocalVariableTable:
        Start  Length  Slot  Name   Signature
            0       2     0  this   Lshapeless/ops/hlist$HNilHKernel$;

  public java.lang.Object productElement(int);
    descriptor: (I)Ljava/lang/Object;
    flags: (0x0001) ACC_PUBLIC
    Code:
      stack=1, locals=4, args_size=2
         0: iload_1
         1: istore_3
         2: iload_1
         3: invokestatic  #97                 // Method scala/runtime/Statics.ioobe:(I)Ljava/lang/Object;
         6: astore_2
         7: goto          10
        10: aload_2
        11: areturn
      StackMapTable: number_of_entries = 1
        frame_type = 253 /* append */
          offset_delta = 10
          locals = [ class java/lang/Object, int ]
      LineNumberTable:
        line 190: 0
      LocalVariableTable:
        Start  Length  Slot  Name   Signature
            0      12     0  this   Lshapeless/ops/hlist$HNilHKernel$;
            0      12     1   x$1   I
    MethodParameters:
      Name                           Flags
      x$1                            final

  public scala.collection.Iterator<java.lang.Object> productIterator();
    descriptor: ()Lscala/collection/Iterator;
    flags: (0x0001) ACC_PUBLIC
    Code:
      stack=2, locals=1, args_size=1
         0: getstatic     #104                // Field scala/runtime/ScalaRunTime$.MODULE$:Lscala/runtime/ScalaRunTime$;
         3: aload_0
         4: invokevirtual #107                // Method scala/runtime/ScalaRunTime$.typedProductIterator:(Lscala/Product;)Lscala/collection/Iterator;
         7: areturn
      LineNumberTable:
        line 190: 0
      LocalVariableTable:
        Start  Length  Slot  Name   Signature
            0       8     0  this   Lshapeless/ops/hlist$HNilHKernel$;
    Signature: #99                          // ()Lscala/collection/Iterator<Ljava/lang/Object;>;

  public boolean canEqual(java.lang.Object);
    descriptor: (Ljava/lang/Object;)Z
    flags: (0x0001) ACC_PUBLIC
    Code:
      stack=1, locals=2, args_size=2
         0: aload_1
         1: instanceof    #2                  // class shapeless/ops/hlist$HNilHKernel$
         4: ireturn
      LineNumberTable:
        line 190: 0
      LocalVariableTable:
        Start  Length  Slot  Name   Signature
            0       5     0  this   Lshapeless/ops/hlist$HNilHKernel$;
            0       5     1   x$1   Ljava/lang/Object;
    MethodParameters:
      Name                           Flags
      x$1                            final

  public int hashCode();
    descriptor: ()I
    flags: (0x0001) ACC_PUBLIC
    Code:
      stack=1, locals=1, args_size=1
         0: ldc           #112                // int 1480857052
         2: ireturn
      LineNumberTable:
        line 190: 0
      LocalVariableTable:
        Start  Length  Slot  Name   Signature
            0       3     0  this   Lshapeless/ops/hlist$HNilHKernel$;

  public java.lang.String toString();
    descriptor: ()Ljava/lang/String;
    flags: (0x0001) ACC_PUBLIC
    Code:
      stack=1, locals=1, args_size=1
         0: ldc           #88                 // String HNilHKernel
         2: areturn
      LineNumberTable:
        line 190: 0
      LocalVariableTable:
        Start  Length  Slot  Name   Signature
            0       3     0  this   Lshapeless/ops/hlist$HNilHKernel$;

  private java.lang.Object writeReplace();
    descriptor: ()Ljava/lang/Object;
    flags: (0x0002) ACC_PRIVATE
    Code:
      stack=3, locals=1, args_size=1
         0: new           #117                // class scala/runtime/ModuleSerializationProxy
         3: dup
         4: ldc           #2                  // class shapeless/ops/hlist$HNilHKernel$
         6: invokespecial #120                // Method scala/runtime/ModuleSerializationProxy."<init>":(Ljava/lang/Class;)V
         9: areturn
      LineNumberTable:
        line 190: 0
      LocalVariableTable:
        Start  Length  Slot  Name   Signature
            0      10     0  this   Lshapeless/ops/hlist$HNilHKernel$;

  public scala.collection.immutable.List toList(shapeless.HList);
    descriptor: (Lshapeless/HList;)Lscala/collection/immutable/List;
    flags: (0x1041) ACC_PUBLIC, ACC_BRIDGE, ACC_SYNTHETIC
    Code:
      stack=2, locals=2, args_size=2
         0: aload_0
         1: aload_1
         2: checkcast     #123                // class shapeless/HNil
         5: invokevirtual #125                // Method toList:(Lshapeless/HNil;)Lscala/collection/immutable/List;
         8: areturn
      LineNumberTable:
        line 190: 0
      LocalVariableTable:
        Start  Length  Slot  Name   Signature
            0       9     0  this   Lshapeless/ops/hlist$HNilHKernel$;
            0       9     1     l   Lshapeless/HList;
    MethodParameters:
      Name                           Flags
      l                              final

  public shapeless.HList tabulate(int, scala.Function1);
    descriptor: (ILscala/Function1;)Lshapeless/HList;
    flags: (0x1041) ACC_PUBLIC, ACC_BRIDGE, ACC_SYNTHETIC
    Code:
      stack=3, locals=3, args_size=3
         0: aload_0
         1: iload_1
         2: aload_2
         3: invokevirtual #129                // Method tabulate:(ILscala/Function1;)Lshapeless/HNil;
         6: areturn
      LineNumberTable:
        line 190: 0
      LocalVariableTable:
        Start  Length  Slot  Name   Signature
            0       7     0  this   Lshapeless/ops/hlist$HNilHKernel$;
            0       7     1  from   I
            0       7     2     f   Lscala/Function1;
    MethodParameters:
      Name                           Flags
      from                           final
      f                              final

  public shapeless.HList map(shapeless.PolyDefns$$tilde$greater, shapeless.HList);
    descriptor: (Lshapeless/PolyDefns$$tilde$greater;Lshapeless/HList;)Lshapeless/HList;
    flags: (0x1041) ACC_PUBLIC, ACC_BRIDGE, ACC_SYNTHETIC
    Code:
      stack=3, locals=3, args_size=3
         0: aload_0
         1: aload_1
         2: aload_2
         3: checkcast     #123                // class shapeless/HNil
         6: invokevirtual #132                // Method map:(Lshapeless/PolyDefns$$tilde$greater;Lshapeless/HNil;)Lshapeless/HNil;
         9: areturn
      LineNumberTable:
        line 190: 0
      LocalVariableTable:
        Start  Length  Slot  Name   Signature
            0      10     0  this   Lshapeless/ops/hlist$HNilHKernel$;
            0      10     1     f   Lshapeless/PolyDefns$$tilde$greater;
            0      10     2     l   Lshapeless/HList;
    MethodParameters:
      Name                           Flags
      f                              final
      l                              final

  public shapeless.ops.hlist$HNilHKernel$();
    descriptor: ()V
    flags: (0x0001) ACC_PUBLIC
    Code:
      stack=1, locals=1, args_size=1
         0: aload_0
         1: invokespecial #133                // Method java/lang/Object."<init>":()V
         4: return
      LineNumberTable:
        line 190: 0
      LocalVariableTable:
        Start  Length  Slot  Name   Signature
            0       5     0  this   Lshapeless/ops/hlist$HNilHKernel$;
}
InnerClasses:
  public static #16= #13 of #15;          // $tilde$greater=class shapeless/PolyDefns$$tilde$greater of class shapeless/PolyDefns
  public static #19= #6 of #18;           // HNilHKernel=class shapeless/ops/hlist$HNilHKernel of class shapeless/ops/hlist
  public static #20= #2 of #18;           // HNilHKernel$=class shapeless/ops/hlist$HNilHKernel$ of class shapeless/ops/hlist
SourceFile: "hlists.scala"
  ScalaInlineInfo: length = 0x5E (unknown attribute)
   01 01 00 12 00 19 00 18 01 00 6C 00 6D 01 00 6F
   00 51 01 00 50 00 51 01 00 35 00 82 01 00 35 00
   36 01 00 59 00 51 01 00 5A 00 5B 01 00 25 00 26
   01 00 2E 00 2F 01 00 62 00 2F 01 00 56 00 57 01
   00 40 00 7F 01 00 40 00 41 01 00 49 00 79 01 00
   49 00 4A 01 00 71 00 57 01 00 72 00 73 01
  Scala: length = 0x0 (unknown attribute)

