Classfile /Users/mw/Projects/slang-braindump/.jar/jar8/assemble/slang-braindump/assemble/content/shapeless/ops/hlist$NatTRel$$anon$16.class
  Last modified May 29, 2022; size 2083 bytes
  SHA-256 checksum 3a53bf73c8072d7880aac727a048096f8565bc370896e1e0e1736f3c198e709e
  Compiled from "hlists.scala"
public final class shapeless.ops.hlist$NatTRel$$anon$16 extends java.lang.Object implements shapeless.ops.hlist$NatTRel<shapeless.$colon$colon<H1, T1>, java.lang.Object, shapeless.$colon$colon<H2, T2>, ?>
  minor version: 0
  major version: 52
  flags: (0x0031) ACC_PUBLIC, ACC_FINAL, ACC_SUPER
  this_class: #2                          // shapeless/ops/hlist$NatTRel$$anon$16
  super_class: #5                         // java/lang/Object
  interfaces: 1, fields: 1, methods: 3, attributes: 6
Constant pool:
   #1 = Utf8               shapeless/ops/hlist$NatTRel$$anon$16
   #2 = Class              #1             // shapeless/ops/hlist$NatTRel$$anon$16
   #3 = Utf8               Ljava/lang/Object;Lshapeless/ops/hlist$NatTRel<Lshapeless/$colon$colon<TH1;TT1;>;Ljava/lang/Object;Lshapeless/$colon$colon<TH2;TT2;>;*>;
   #4 = Utf8               java/lang/Object
   #5 = Class              #4             // java/lang/Object
   #6 = Utf8               shapeless/ops/hlist$NatTRel
   #7 = Class              #6             // shapeless/ops/hlist$NatTRel
   #8 = Utf8               hlists.scala
   #9 = Utf8               shapeless/ops/hlist$NatTRel$
  #10 = Class              #9             // shapeless/ops/hlist$NatTRel$
  #11 = Utf8               hlistNatTRel5
  #12 = Utf8               (Lshapeless/ops/hlist$NatTRel;)Lshapeless/ops/hlist$NatTRel;
  #13 = NameAndType        #11:#12        // hlistNatTRel5:(Lshapeless/ops/hlist$NatTRel;)Lshapeless/ops/hlist$NatTRel;
  #14 = Utf8               shapeless/PolyDefns$$tilde$greater
  #15 = Class              #14            // shapeless/PolyDefns$$tilde$greater
  #16 = Utf8               shapeless/PolyDefns
  #17 = Class              #16            // shapeless/PolyDefns
  #18 = Utf8               $tilde$greater
  #19 = Utf8               shapeless/ops/hlist
  #20 = Class              #19            // shapeless/ops/hlist
  #21 = Utf8               NatTRel
  #22 = Utf8               NatTRel$
  #23 = Utf8               nt$5
  #24 = Utf8               Lshapeless/ops/hlist$NatTRel;
  #25 = Utf8               map
  #26 = Utf8               (Lshapeless/PolyDefns$$tilde$greater;Lshapeless/$colon$colon;)Lshapeless/$colon$colon;
  #27 = Utf8               (Lshapeless/PolyDefns$$tilde$greater<Ljava/lang/Object;*>;Lshapeless/$colon$colon<TH1;TT1;>;)Lshapeless/$colon$colon<TH2;TT2;>;
  #28 = Utf8               f
  #29 = Utf8               fa
  #30 = Utf8               shapeless/$colon$colon
  #31 = Class              #30            // shapeless/$colon$colon
  #32 = Utf8               head
  #33 = Utf8               ()Ljava/lang/Object;
  #34 = NameAndType        #32:#33        // head:()Ljava/lang/Object;
  #35 = Methodref          #31.#34        // shapeless/$colon$colon.head:()Ljava/lang/Object;
  #36 = Utf8               apply
  #37 = Utf8               (Ljava/lang/Object;)Ljava/lang/Object;
  #38 = NameAndType        #36:#37        // apply:(Ljava/lang/Object;)Ljava/lang/Object;
  #39 = InterfaceMethodref #15.#38        // shapeless/PolyDefns$$tilde$greater.apply:(Ljava/lang/Object;)Ljava/lang/Object;
  #40 = Utf8               shapeless/HList$
  #41 = Class              #40            // shapeless/HList$
  #42 = Utf8               MODULE$
  #43 = Utf8               Lshapeless/HList$;
  #44 = NameAndType        #42:#43        // MODULE$:Lshapeless/HList$;
  #45 = Fieldref           #41.#44        // shapeless/HList$.MODULE$:Lshapeless/HList$;
  #46 = NameAndType        #23:#24        // nt$5:Lshapeless/ops/hlist$NatTRel;
  #47 = Fieldref           #2.#46         // shapeless/ops/hlist$NatTRel$$anon$16.nt$5:Lshapeless/ops/hlist$NatTRel;
  #48 = Utf8               tail
  #49 = Utf8               ()Lshapeless/HList;
  #50 = NameAndType        #48:#49        // tail:()Lshapeless/HList;
  #51 = Methodref          #31.#50        // shapeless/$colon$colon.tail:()Lshapeless/HList;
  #52 = Utf8               (Lshapeless/PolyDefns$$tilde$greater;Lshapeless/HList;)Lshapeless/HList;
  #53 = NameAndType        #25:#52        // map:(Lshapeless/PolyDefns$$tilde$greater;Lshapeless/HList;)Lshapeless/HList;
  #54 = InterfaceMethodref #7.#53         // shapeless/ops/hlist$NatTRel.map:(Lshapeless/PolyDefns$$tilde$greater;Lshapeless/HList;)Lshapeless/HList;
  #55 = Utf8               hlistOps
  #56 = Utf8               (Lshapeless/HList;)Lshapeless/syntax/HListOps;
  #57 = NameAndType        #55:#56        // hlistOps:(Lshapeless/HList;)Lshapeless/syntax/HListOps;
  #58 = Methodref          #41.#57        // shapeless/HList$.hlistOps:(Lshapeless/HList;)Lshapeless/syntax/HListOps;
  #59 = Utf8               shapeless/syntax/HListOps
  #60 = Class              #59            // shapeless/syntax/HListOps
  #61 = Utf8               $colon$colon
  #62 = Utf8               (Ljava/lang/Object;)Lshapeless/$colon$colon;
  #63 = NameAndType        #61:#62        // $colon$colon:(Ljava/lang/Object;)Lshapeless/$colon$colon;
  #64 = Methodref          #60.#63        // shapeless/syntax/HListOps.$colon$colon:(Ljava/lang/Object;)Lshapeless/$colon$colon;
  #65 = Utf8               this
  #66 = Utf8               Lshapeless/ops/hlist$NatTRel$$anon$16;
  #67 = Utf8               Lshapeless/PolyDefns$$tilde$greater;
  #68 = Utf8               Lshapeless/$colon$colon;
  #69 = Utf8               nt
  #70 = NameAndType        #25:#26        // map:(Lshapeless/PolyDefns$$tilde$greater;Lshapeless/$colon$colon;)Lshapeless/$colon$colon;
  #71 = Methodref          #2.#70         // shapeless/ops/hlist$NatTRel$$anon$16.map:(Lshapeless/PolyDefns$$tilde$greater;Lshapeless/$colon$colon;)Lshapeless/$colon$colon;
  #72 = Utf8               Lshapeless/HList;
  #73 = Utf8               <init>
  #74 = Utf8               (Lshapeless/ops/hlist$NatTRel;)V
  #75 = Utf8               ()V
  #76 = NameAndType        #73:#75        // "<init>":()V
  #77 = Methodref          #5.#76         // java/lang/Object."<init>":()V
  #78 = Utf8               Code
  #79 = Utf8               LineNumberTable
  #80 = Utf8               LocalVariableTable
  #81 = Utf8               Signature
  #82 = Utf8               MethodParameters
  #83 = Utf8               InnerClasses
  #84 = Utf8               EnclosingMethod
  #85 = Utf8               SourceFile
  #86 = Utf8               ScalaInlineInfo
  #87 = Utf8               Scala
{
  private final shapeless.ops.hlist$NatTRel nt$5;
    descriptor: Lshapeless/ops/hlist$NatTRel;
    flags: (0x0012) ACC_PRIVATE, ACC_FINAL

  public shapeless.$colon$colon<H2, T2> map(shapeless.PolyDefns$$tilde$greater<java.lang.Object, ?>, shapeless.$colon$colon<H1, T1>);
    descriptor: (Lshapeless/PolyDefns$$tilde$greater;Lshapeless/$colon$colon;)Lshapeless/$colon$colon;
    flags: (0x0001) ACC_PUBLIC
    Code:
      stack=4, locals=4, args_size=3
         0: aload_1
         1: aload_2
         2: invokevirtual #35                 // Method shapeless/$colon$colon.head:()Ljava/lang/Object;
         5: invokeinterface #39,  2           // InterfaceMethod shapeless/PolyDefns$$tilde$greater.apply:(Ljava/lang/Object;)Ljava/lang/Object;
        10: astore_3
        11: getstatic     #45                 // Field shapeless/HList$.MODULE$:Lshapeless/HList$;
        14: aload_0
        15: getfield      #47                 // Field nt$5:Lshapeless/ops/hlist$NatTRel;
        18: aload_1
        19: aload_2
        20: invokevirtual #51                 // Method shapeless/$colon$colon.tail:()Lshapeless/HList;
        23: invokeinterface #54,  3           // InterfaceMethod shapeless/ops/hlist$NatTRel.map:(Lshapeless/PolyDefns$$tilde$greater;Lshapeless/HList;)Lshapeless/HList;
        28: invokevirtual #58                 // Method shapeless/HList$.hlistOps:(Lshapeless/HList;)Lshapeless/syntax/HListOps;
        31: aload_3
        32: invokevirtual #64                 // Method shapeless/syntax/HListOps.$colon$colon:(Ljava/lang/Object;)Lshapeless/$colon$colon;
        35: areturn
      LineNumberTable:
        line 154: 0
      LocalVariableTable:
        Start  Length  Slot  Name   Signature
            0      36     0  this   Lshapeless/ops/hlist$NatTRel$$anon$16;
            0      36     1     f   Lshapeless/PolyDefns$$tilde$greater;
            0      36     2    fa   Lshapeless/$colon$colon;
    Signature: #27                          // (Lshapeless/PolyDefns$$tilde$greater<Ljava/lang/Object;*>;Lshapeless/$colon$colon<TH1;TT1;>;)Lshapeless/$colon$colon<TH2;TT2;>;
    MethodParameters:
      Name                           Flags
      f                              final
      fa                             final

  public shapeless.HList map(shapeless.PolyDefns$$tilde$greater, shapeless.HList);
    descriptor: (Lshapeless/PolyDefns$$tilde$greater;Lshapeless/HList;)Lshapeless/HList;
    flags: (0x1041) ACC_PUBLIC, ACC_BRIDGE, ACC_SYNTHETIC
    Code:
      stack=3, locals=3, args_size=3
         0: aload_0
         1: aload_1
         2: aload_2
         3: checkcast     #31                 // class shapeless/$colon$colon
         6: invokevirtual #71                 // Method map:(Lshapeless/PolyDefns$$tilde$greater;Lshapeless/$colon$colon;)Lshapeless/$colon$colon;
         9: areturn
      LineNumberTable:
        line 153: 0
      LocalVariableTable:
        Start  Length  Slot  Name   Signature
            0      10     0  this   Lshapeless/ops/hlist$NatTRel$$anon$16;
            0      10     1    nt   Lshapeless/PolyDefns$$tilde$greater;
            0      10     2    fa   Lshapeless/HList;
    MethodParameters:
      Name                           Flags
      nt                             final
      fa                             final

  public shapeless.ops.hlist$NatTRel$$anon$16(shapeless.ops.hlist$NatTRel);
    descriptor: (Lshapeless/ops/hlist$NatTRel;)V
    flags: (0x0001) ACC_PUBLIC
    Code:
      stack=2, locals=2, args_size=2
         0: aload_0
         1: aload_1
         2: putfield      #47                 // Field nt$5:Lshapeless/ops/hlist$NatTRel;
         5: aload_0
         6: invokespecial #77                 // Method java/lang/Object."<init>":()V
         9: return
      LineNumberTable:
        line 152: 0
        line 153: 5
      LocalVariableTable:
        Start  Length  Slot  Name   Signature
            0      10     0  this   Lshapeless/ops/hlist$NatTRel$$anon$16;
            0      10     1  nt$5   Lshapeless/ops/hlist$NatTRel;
    MethodParameters:
      Name                           Flags
      nt$5                           final
}
InnerClasses:
  public static #18= #15 of #17;          // $tilde$greater=class shapeless/PolyDefns$$tilde$greater of class shapeless/PolyDefns
  public static #21= #7 of #20;           // NatTRel=class shapeless/ops/hlist$NatTRel of class shapeless/ops/hlist
  public static #22= #10 of #20;          // NatTRel$=class shapeless/ops/hlist$NatTRel$ of class shapeless/ops/hlist
  public final #2;                        // class shapeless/ops/hlist$NatTRel$$anon$16
EnclosingMethod: #10.#13                // shapeless.ops.hlist$NatTRel$.hlistNatTRel5
Signature: #3                           // Ljava/lang/Object;Lshapeless/ops/hlist$NatTRel<Lshapeless/$colon$colon<TH1;TT1;>;Ljava/lang/Object;Lshapeless/$colon$colon<TH2;TT2;>;*>;
SourceFile: "hlists.scala"
  ScalaInlineInfo: length = 0x13 (unknown attribute)
   01 01 00 03 00 49 00 4A 01 00 19 00 1A 01 00 19
   00 34 01
  Scala: length = 0x0 (unknown attribute)

