Classfile /Users/mw/Projects/slang-braindump/.jar/jar8/assemble/slang-braindump/assemble/content/shapeless/ops/hlist$Combinations$.class
  Last modified May 29, 2022; size 3465 bytes
  SHA-256 checksum 4cb609babf633357e8753ec918c358f53e1f02f546234756da36f79231b8fca7
  Compiled from "hlists.scala"
public class shapeless.ops.hlist$Combinations$ implements shapeless.ops.hlist$LowPriorityCombinations,java.io.Serializable
  minor version: 0
  major version: 52
  flags: (0x0021) ACC_PUBLIC, ACC_SUPER
  this_class: #2                          // shapeless/ops/hlist$Combinations$
  super_class: #4                         // java/lang/Object
  interfaces: 2, fields: 1, methods: 8, attributes: 4
Constant pool:
   #1 = Utf8               shapeless/ops/hlist$Combinations$
   #2 = Class              #1             // shapeless/ops/hlist$Combinations$
   #3 = Utf8               java/lang/Object
   #4 = Class              #3             // java/lang/Object
   #5 = Utf8               shapeless/ops/hlist$LowPriorityCombinations
   #6 = Class              #5             // shapeless/ops/hlist$LowPriorityCombinations
   #7 = Utf8               java/io/Serializable
   #8 = Class              #7             // java/io/Serializable
   #9 = Utf8               hlists.scala
  #10 = Utf8               shapeless/ops/hlist$Combinations
  #11 = Class              #10            // shapeless/ops/hlist$Combinations
  #12 = Utf8               shapeless/ops/hlist
  #13 = Class              #12            // shapeless/ops/hlist
  #14 = Utf8               Combinations
  #15 = Utf8               Combinations$
  #16 = Utf8               shapeless/ops/hlist$Combinations$$anon$204
  #17 = Class              #16            // shapeless/ops/hlist$Combinations$$anon$204
  #18 = Utf8               shapeless/ops/hlist$Combinations$$anon$205
  #19 = Class              #18            // shapeless/ops/hlist$Combinations$$anon$205
  #20 = Utf8               LowPriorityCombinations
  #21 = Utf8               shapeless/ops/hlist$MapCons
  #22 = Class              #21            // shapeless/ops/hlist$MapCons
  #23 = Utf8               MapCons
  #24 = Utf8               shapeless/ops/hlist$Prepend
  #25 = Class              #24            // shapeless/ops/hlist$Prepend
  #26 = Utf8               Prepend
  #27 = Utf8               MODULE$
  #28 = Utf8               Lshapeless/ops/hlist$Combinations$;
  #29 = Utf8               <clinit>
  #30 = Utf8               ()V
  #31 = Utf8               <init>
  #32 = NameAndType        #31:#30        // "<init>":()V
  #33 = Methodref          #2.#32         // shapeless/ops/hlist$Combinations$."<init>":()V
  #34 = NameAndType        #27:#28        // MODULE$:Lshapeless/ops/hlist$Combinations$;
  #35 = Fieldref           #2.#34         // shapeless/ops/hlist$Combinations$.MODULE$:Lshapeless/ops/hlist$Combinations$;
  #36 = Utf8               $init$
  #37 = Utf8               (Lshapeless/ops/hlist$LowPriorityCombinations;)V
  #38 = NameAndType        #36:#37        // $init$:(Lshapeless/ops/hlist$LowPriorityCombinations;)V
  #39 = InterfaceMethodref #6.#38         // shapeless/ops/hlist$LowPriorityCombinations.$init$:(Lshapeless/ops/hlist$LowPriorityCombinations;)V
  #40 = Utf8               combinationHNil
  #41 = Utf8               ()Lshapeless/ops/hlist$Combinations;
  #42 = Utf8               <N::Lshapeless/Nat;>()Lshapeless/ops/hlist$Combinations<TN;Lshapeless/HNil;>;
  #43 = Utf8               combinationHNil$
  #44 = Utf8               (Lshapeless/ops/hlist$LowPriorityCombinations;)Lshapeless/ops/hlist$Combinations;
  #45 = NameAndType        #43:#44        // combinationHNil$:(Lshapeless/ops/hlist$LowPriorityCombinations;)Lshapeless/ops/hlist$Combinations;
  #46 = InterfaceMethodref #6.#45         // shapeless/ops/hlist$LowPriorityCombinations.combinationHNil$:(Lshapeless/ops/hlist$LowPriorityCombinations;)Lshapeless/ops/hlist$Combinations;
  #47 = Utf8               this
  #48 = Utf8               apply
  #49 = Utf8               (Lshapeless/ops/hlist$Combinations;)Lshapeless/ops/hlist$Combinations;
  #50 = Utf8               <N::Lshapeless/Nat;L::Lshapeless/HList;>(Lshapeless/ops/hlist$Combinations<TN;TL;>;)Lshapeless/ops/hlist$Combinations<TN;TL;>;
  #51 = Utf8               c
  #52 = Utf8               Lshapeless/ops/hlist$Combinations;
  #53 = Utf8               (Lshapeless/Nat;Lshapeless/HList;Lshapeless/ops/hlist$Combinations;)Lshapeless/HList;
  #54 = Utf8               <L::Lshapeless/HList;>(Lshapeless/Nat;TL;Lshapeless/ops/hlist$Combinations<Lshapeless/Nat;TL;>;)Lshapeless/HList;
  #55 = Utf8               n
  #56 = Utf8               l
  #57 = Utf8               (Ljava/lang/Object;)Ljava/lang/Object;
  #58 = NameAndType        #48:#57        // apply:(Ljava/lang/Object;)Ljava/lang/Object;
  #59 = InterfaceMethodref #11.#58        // shapeless/ops/hlist$Combinations.apply:(Ljava/lang/Object;)Ljava/lang/Object;
  #60 = Utf8               shapeless/HList
  #61 = Class              #60            // shapeless/HList
  #62 = Utf8               Lshapeless/Nat;
  #63 = Utf8               Lshapeless/HList;
  #64 = Utf8               combination0
  #65 = Utf8               <L::Lshapeless/HList;>()Lshapeless/ops/hlist$Combinations<Lshapeless/_0;TL;>;
  #66 = Methodref          #17.#32        // shapeless/ops/hlist$Combinations$$anon$204."<init>":()V
  #67 = Utf8               combination1
  #68 = Utf8               (Lshapeless/ops/hlist$Combinations;Lshapeless/ops/hlist$Combinations;Lshapeless/ops/hlist$MapCons;Lshapeless/ops/hlist$Prepend;)Lshapeless/ops/hlist$Combinations;
  #69 = Utf8               <N::Lshapeless/Nat;H:Ljava/lang/Object;T::Lshapeless/HList;C1::Lshapeless/HList;C2::Lshapeless/HList;CM::Lshapeless/HList;CpOut::Lshapeless/HList;>(Lshapeless/ops/hlist$Combinations<TN;TT;>;Lshapeless/ops/hlist$Combinations<Lshapeless/Succ<TN;>;TT;>;Lshapeless/ops/hlist$MapCons<TH;TC1;>;Lshapeless/ops/hlist$Prepend<TCM;TC2;>;)Lshapeless/ops/hlist$Combinations<Lshapeless/Succ<TN;>;Lshapeless/$colon$colon<TH;TT;>;>;
  #70 = Utf8               c1
  #71 = Utf8               c2
  #72 = Utf8               cm
  #73 = Utf8               cp
  #74 = Utf8               (Lshapeless/ops/hlist$Prepend;Lshapeless/ops/hlist$MapCons;Lshapeless/ops/hlist$Combinations;Lshapeless/ops/hlist$Combinations;)V
  #75 = NameAndType        #31:#74        // "<init>":(Lshapeless/ops/hlist$Prepend;Lshapeless/ops/hlist$MapCons;Lshapeless/ops/hlist$Combinations;Lshapeless/ops/hlist$Combinations;)V
  #76 = Methodref          #19.#75        // shapeless/ops/hlist$Combinations$$anon$205."<init>":(Lshapeless/ops/hlist$Prepend;Lshapeless/ops/hlist$MapCons;Lshapeless/ops/hlist$Combinations;Lshapeless/ops/hlist$Combinations;)V
  #77 = Utf8               Lshapeless/ops/hlist$MapCons;
  #78 = Utf8               Lshapeless/ops/hlist$Prepend;
  #79 = Utf8               writeReplace
  #80 = Utf8               ()Ljava/lang/Object;
  #81 = Utf8               scala/runtime/ModuleSerializationProxy
  #82 = Class              #81            // scala/runtime/ModuleSerializationProxy
  #83 = Utf8               (Ljava/lang/Class;)V
  #84 = NameAndType        #31:#83        // "<init>":(Ljava/lang/Class;)V
  #85 = Methodref          #82.#84        // scala/runtime/ModuleSerializationProxy."<init>":(Ljava/lang/Class;)V
  #86 = Methodref          #4.#32         // java/lang/Object."<init>":()V
  #87 = Utf8               Code
  #88 = Utf8               LineNumberTable
  #89 = Utf8               LocalVariableTable
  #90 = Utf8               Signature
  #91 = Utf8               MethodParameters
  #92 = Utf8               InnerClasses
  #93 = Utf8               SourceFile
  #94 = Utf8               ScalaInlineInfo
  #95 = Utf8               Scala
{
  public static final shapeless.ops.hlist$Combinations$ MODULE$;
    descriptor: Lshapeless/ops/hlist$Combinations$;
    flags: (0x0019) ACC_PUBLIC, ACC_STATIC, ACC_FINAL

  public static {};
    descriptor: ()V
    flags: (0x0009) ACC_PUBLIC, ACC_STATIC
    Code:
      stack=2, locals=0, args_size=0
         0: new           #2                  // class shapeless/ops/hlist$Combinations$
         3: dup
         4: invokespecial #33                 // Method "<init>":()V
         7: putstatic     #35                 // Field MODULE$:Lshapeless/ops/hlist$Combinations$;
        10: getstatic     #35                 // Field MODULE$:Lshapeless/ops/hlist$Combinations$;
        13: invokestatic  #39                 // InterfaceMethod shapeless/ops/hlist$LowPriorityCombinations.$init$:(Lshapeless/ops/hlist$LowPriorityCombinations;)V
        16: return
      LineNumberTable:
        line 3007: 0

  public <N extends shapeless.Nat> shapeless.ops.hlist$Combinations<N, shapeless.HNil> combinationHNil();
    descriptor: ()Lshapeless/ops/hlist$Combinations;
    flags: (0x0001) ACC_PUBLIC
    Code:
      stack=1, locals=1, args_size=1
         0: aload_0
         1: invokestatic  #46                 // InterfaceMethod shapeless/ops/hlist$LowPriorityCombinations.combinationHNil$:(Lshapeless/ops/hlist$LowPriorityCombinations;)Lshapeless/ops/hlist$Combinations;
         4: areturn
      LineNumberTable:
        line 3007: 0
      LocalVariableTable:
        Start  Length  Slot  Name   Signature
            0       5     0  this   Lshapeless/ops/hlist$Combinations$;
    Signature: #42                          // <N::Lshapeless/Nat;>()Lshapeless/ops/hlist$Combinations<TN;Lshapeless/HNil;>;

  public <N extends shapeless.Nat, L extends shapeless.HList> shapeless.ops.hlist$Combinations<N, L> apply(shapeless.ops.hlist$Combinations<N, L>);
    descriptor: (Lshapeless/ops/hlist$Combinations;)Lshapeless/ops/hlist$Combinations;
    flags: (0x0001) ACC_PUBLIC
    Code:
      stack=1, locals=2, args_size=2
         0: aload_1
         1: areturn
      LineNumberTable:
        line 3011: 0
      LocalVariableTable:
        Start  Length  Slot  Name   Signature
            0       2     0  this   Lshapeless/ops/hlist$Combinations$;
            0       2     1     c   Lshapeless/ops/hlist$Combinations;
    Signature: #50                          // <N::Lshapeless/Nat;L::Lshapeless/HList;>(Lshapeless/ops/hlist$Combinations<TN;TL;>;)Lshapeless/ops/hlist$Combinations<TN;TL;>;
    MethodParameters:
      Name                           Flags
      c                              final

  public <L extends shapeless.HList> shapeless.HList apply(shapeless.Nat, L, shapeless.ops.hlist$Combinations<shapeless.Nat, L>);
    descriptor: (Lshapeless/Nat;Lshapeless/HList;Lshapeless/ops/hlist$Combinations;)Lshapeless/HList;
    flags: (0x0001) ACC_PUBLIC
    Code:
      stack=2, locals=6, args_size=4
         0: aload_2
         1: astore        4
         3: aload_3
         4: astore        5
         6: aload         5
         8: aload         4
        10: invokeinterface #59,  2           // InterfaceMethod shapeless/ops/hlist$Combinations.apply:(Ljava/lang/Object;)Ljava/lang/Object;
        15: checkcast     #61                 // class shapeless/HList
        18: areturn
      LineNumberTable:
        line 3013: 0
      LocalVariableTable:
        Start  Length  Slot  Name   Signature
            0      19     0  this   Lshapeless/ops/hlist$Combinations$;
            0      19     1     n   Lshapeless/Nat;
            0      19     2     l   Lshapeless/HList;
            0      19     3     c   Lshapeless/ops/hlist$Combinations;
    Signature: #54                          // <L::Lshapeless/HList;>(Lshapeless/Nat;TL;Lshapeless/ops/hlist$Combinations<Lshapeless/Nat;TL;>;)Lshapeless/HList;
    MethodParameters:
      Name                           Flags
      n                              final
      l                              final
      c                              final

  public <L extends shapeless.HList> shapeless.ops.hlist$Combinations<shapeless._0, L> combination0();
    descriptor: ()Lshapeless/ops/hlist$Combinations;
    flags: (0x0001) ACC_PUBLIC
    Code:
      stack=2, locals=1, args_size=1
         0: new           #17                 // class shapeless/ops/hlist$Combinations$$anon$204
         3: dup
         4: invokespecial #66                 // Method shapeless/ops/hlist$Combinations$$anon$204."<init>":()V
         7: areturn
      LineNumberTable:
        line 3016: 0
      LocalVariableTable:
        Start  Length  Slot  Name   Signature
            0       8     0  this   Lshapeless/ops/hlist$Combinations$;
    Signature: #65                          // <L::Lshapeless/HList;>()Lshapeless/ops/hlist$Combinations<Lshapeless/_0;TL;>;

  public <N extends shapeless.Nat, H extends java.lang.Object, T extends shapeless.HList, C1 extends shapeless.HList, C2 extends shapeless.HList, CM extends shapeless.HList, CpOut extends shapeless.HList> shapeless.ops.hlist$Combinations<shapeless.Succ<N>, shapeless.$colon$colon<H, T>> combination1(shapeless.ops.hlist$Combinations<N, T>, shapeless.ops.hlist$Combinations<shapeless.Succ<N>, T>, shapeless.ops.hlist$MapCons<H, C1>, shapeless.ops.hlist$Prepend<CM, C2>);
    descriptor: (Lshapeless/ops/hlist$Combinations;Lshapeless/ops/hlist$Combinations;Lshapeless/ops/hlist$MapCons;Lshapeless/ops/hlist$Prepend;)Lshapeless/ops/hlist$Combinations;
    flags: (0x0001) ACC_PUBLIC
    Code:
      stack=6, locals=5, args_size=5
         0: new           #19                 // class shapeless/ops/hlist$Combinations$$anon$205
         3: dup
         4: aload         4
         6: aload_3
         7: aload_1
         8: aload_2
         9: invokespecial #76                 // Method shapeless/ops/hlist$Combinations$$anon$205."<init>":(Lshapeless/ops/hlist$Prepend;Lshapeless/ops/hlist$MapCons;Lshapeless/ops/hlist$Combinations;Lshapeless/ops/hlist$Combinations;)V
        12: areturn
      LineNumberTable:
        line 3027: 0
      LocalVariableTable:
        Start  Length  Slot  Name   Signature
            0      13     0  this   Lshapeless/ops/hlist$Combinations$;
            0      13     1    c1   Lshapeless/ops/hlist$Combinations;
            0      13     2    c2   Lshapeless/ops/hlist$Combinations;
            0      13     3    cm   Lshapeless/ops/hlist$MapCons;
            0      13     4    cp   Lshapeless/ops/hlist$Prepend;
    Signature: #69                          // <N::Lshapeless/Nat;H:Ljava/lang/Object;T::Lshapeless/HList;C1::Lshapeless/HList;C2::Lshapeless/HList;CM::Lshapeless/HList;CpOut::Lshapeless/HList;>(Lshapeless/ops/hlist$Combinations<TN;TT;>;Lshapeless/ops/hlist$Combinations<Lshapeless/Succ<TN;>;TT;>;Lshapeless/ops/hlist$MapCons<TH;TC1;>;Lshapeless/ops/hlist$Prepend<TCM;TC2;>;)Lshapeless/ops/hlist$Combinations<Lshapeless/Succ<TN;>;Lshapeless/$colon$colon<TH;TT;>;>;
    MethodParameters:
      Name                           Flags
      c1                             final
      c2                             final
      cm                             final
      cp                             final

  private java.lang.Object writeReplace();
    descriptor: ()Ljava/lang/Object;
    flags: (0x0002) ACC_PRIVATE
    Code:
      stack=3, locals=1, args_size=1
         0: new           #82                 // class scala/runtime/ModuleSerializationProxy
         3: dup
         4: ldc           #2                  // class shapeless/ops/hlist$Combinations$
         6: invokespecial #85                 // Method scala/runtime/ModuleSerializationProxy."<init>":(Ljava/lang/Class;)V
         9: areturn
      LineNumberTable:
        line 3007: 0
      LocalVariableTable:
        Start  Length  Slot  Name   Signature
            0      10     0  this   Lshapeless/ops/hlist$Combinations$;

  public shapeless.ops.hlist$Combinations$();
    descriptor: ()V
    flags: (0x0001) ACC_PUBLIC
    Code:
      stack=1, locals=1, args_size=1
         0: aload_0
         1: invokespecial #86                 // Method java/lang/Object."<init>":()V
         4: return
      LineNumberTable:
        line 3007: 0
      LocalVariableTable:
        Start  Length  Slot  Name   Signature
            0       5     0  this   Lshapeless/ops/hlist$Combinations$;
}
InnerClasses:
  public static #14= #11 of #13;          // Combinations=class shapeless/ops/hlist$Combinations of class shapeless/ops/hlist
  public static #15= #2 of #13;           // Combinations$=class shapeless/ops/hlist$Combinations$ of class shapeless/ops/hlist
  public final #17;                       // class shapeless/ops/hlist$Combinations$$anon$204
  public final #19;                       // class shapeless/ops/hlist$Combinations$$anon$205
  public static #20= #6 of #13;           // LowPriorityCombinations=class shapeless/ops/hlist$LowPriorityCombinations of class shapeless/ops/hlist
  public static #23= #22 of #13;          // MapCons=class shapeless/ops/hlist$MapCons of class shapeless/ops/hlist
  public static #26= #25 of #13;          // Prepend=class shapeless/ops/hlist$Prepend of class shapeless/ops/hlist
SourceFile: "hlists.scala"
  ScalaInlineInfo: length = 0x27 (unknown attribute)
   01 01 00 07 00 1F 00 1E 01 00 30 00 35 01 00 30
   00 31 01 00 40 00 29 01 00 43 00 44 01 00 28 00
   29 01 00 4F 00 50 01
  Scala: length = 0x0 (unknown attribute)

