Classfile /Users/mw/Projects/slang-braindump/.jar/jar8/assemble/slang-braindump/assemble/content/shapeless/ops/hlist$Unzip$.class
  Last modified May 29, 2022; size 2057 bytes
  SHA-256 checksum a0e5f330a1597eb55f049554eadcc65dd4962be328cdbc2e253efda2f51b9d7b
  Compiled from "hlists.scala"
public class shapeless.ops.hlist$Unzip$ implements java.io.Serializable
  minor version: 0
  major version: 52
  flags: (0x0021) ACC_PUBLIC, ACC_SUPER
  this_class: #2                          // shapeless/ops/hlist$Unzip$
  super_class: #4                         // java/lang/Object
  interfaces: 1, fields: 1, methods: 5, attributes: 4
Constant pool:
   #1 = Utf8               shapeless/ops/hlist$Unzip$
   #2 = Class              #1             // shapeless/ops/hlist$Unzip$
   #3 = Utf8               java/lang/Object
   #4 = Class              #3             // java/lang/Object
   #5 = Utf8               java/io/Serializable
   #6 = Class              #5             // java/io/Serializable
   #7 = Utf8               hlists.scala
   #8 = Utf8               shapeless/ops/hlist$Mapper
   #9 = Class              #8             // shapeless/ops/hlist$Mapper
  #10 = Utf8               shapeless/ops/hlist
  #11 = Class              #10            // shapeless/ops/hlist
  #12 = Utf8               Mapper
  #13 = Utf8               shapeless/ops/hlist$Transposer
  #14 = Class              #13            // shapeless/ops/hlist$Transposer
  #15 = Utf8               Transposer
  #16 = Utf8               shapeless/ops/hlist$Tupler
  #17 = Class              #16            // shapeless/ops/hlist$Tupler
  #18 = Utf8               Tupler
  #19 = Utf8               shapeless/ops/hlist$Unzip
  #20 = Class              #19            // shapeless/ops/hlist$Unzip
  #21 = Utf8               Unzip
  #22 = Utf8               Unzip$
  #23 = Utf8               shapeless/ops/hlist$Unzip$$anon$150
  #24 = Class              #23            // shapeless/ops/hlist$Unzip$$anon$150
  #25 = Utf8               MODULE$
  #26 = Utf8               Lshapeless/ops/hlist$Unzip$;
  #27 = Utf8               <clinit>
  #28 = Utf8               ()V
  #29 = Utf8               <init>
  #30 = NameAndType        #29:#28        // "<init>":()V
  #31 = Methodref          #2.#30         // shapeless/ops/hlist$Unzip$."<init>":()V
  #32 = NameAndType        #25:#26        // MODULE$:Lshapeless/ops/hlist$Unzip$;
  #33 = Fieldref           #2.#32         // shapeless/ops/hlist$Unzip$.MODULE$:Lshapeless/ops/hlist$Unzip$;
  #34 = Utf8               apply
  #35 = Utf8               (Lshapeless/ops/hlist$Unzip;)Lshapeless/ops/hlist$Unzip;
  #36 = Utf8               <L::Lshapeless/HList;>(Lshapeless/ops/hlist$Unzip<TL;>;)Lshapeless/ops/hlist$Unzip<TL;>;
  #37 = Utf8               unzip
  #38 = Utf8               this
  #39 = Utf8               Lshapeless/ops/hlist$Unzip;
  #40 = Utf8               unzipper
  #41 = Utf8               (Lshapeless/ops/hlist$Mapper;Lshapeless/ops/hlist$Transposer;Lshapeless/ops/hlist$Tupler;)Lshapeless/ops/hlist$Unzip;
  #42 = Utf8               <L::Lshapeless/HList;OutM::Lshapeless/HList;TransposerOut::Lshapeless/HList;TuplerOut:Ljava/lang/Object;>(Lshapeless/ops/hlist$Mapper<Lshapeless/productElements$;TL;>;Lshapeless/ops/hlist$Transposer<TOutM;>;Lshapeless/ops/hlist$Tupler<TTransposerOut;>;)Lshapeless/ops/hlist$Unzip<TL;>;
  #43 = Utf8               mapper
  #44 = Utf8               transposer
  #45 = Utf8               tupler
  #46 = Utf8               (Lshapeless/ops/hlist$Mapper;Lshapeless/ops/hlist$Transposer;Lshapeless/ops/hlist$Tupler;)V
  #47 = NameAndType        #29:#46        // "<init>":(Lshapeless/ops/hlist$Mapper;Lshapeless/ops/hlist$Transposer;Lshapeless/ops/hlist$Tupler;)V
  #48 = Methodref          #24.#47        // shapeless/ops/hlist$Unzip$$anon$150."<init>":(Lshapeless/ops/hlist$Mapper;Lshapeless/ops/hlist$Transposer;Lshapeless/ops/hlist$Tupler;)V
  #49 = Utf8               Lshapeless/ops/hlist$Mapper;
  #50 = Utf8               Lshapeless/ops/hlist$Transposer;
  #51 = Utf8               Lshapeless/ops/hlist$Tupler;
  #52 = Utf8               writeReplace
  #53 = Utf8               ()Ljava/lang/Object;
  #54 = Utf8               scala/runtime/ModuleSerializationProxy
  #55 = Class              #54            // scala/runtime/ModuleSerializationProxy
  #56 = Utf8               (Ljava/lang/Class;)V
  #57 = NameAndType        #29:#56        // "<init>":(Ljava/lang/Class;)V
  #58 = Methodref          #55.#57        // scala/runtime/ModuleSerializationProxy."<init>":(Ljava/lang/Class;)V
  #59 = Methodref          #4.#30         // java/lang/Object."<init>":()V
  #60 = Utf8               Code
  #61 = Utf8               LineNumberTable
  #62 = Utf8               LocalVariableTable
  #63 = Utf8               Signature
  #64 = Utf8               MethodParameters
  #65 = Utf8               InnerClasses
  #66 = Utf8               SourceFile
  #67 = Utf8               ScalaInlineInfo
  #68 = Utf8               Scala
{
  public static final shapeless.ops.hlist$Unzip$ MODULE$;
    descriptor: Lshapeless/ops/hlist$Unzip$;
    flags: (0x0019) ACC_PUBLIC, ACC_STATIC, ACC_FINAL

  public static {};
    descriptor: ()V
    flags: (0x0009) ACC_PUBLIC, ACC_STATIC
    Code:
      stack=2, locals=0, args_size=0
         0: new           #2                  // class shapeless/ops/hlist$Unzip$
         3: dup
         4: invokespecial #31                 // Method "<init>":()V
         7: putstatic     #33                 // Field MODULE$:Lshapeless/ops/hlist$Unzip$;
        10: return
      LineNumberTable:
        line 2232: 0

  public <L extends shapeless.HList> shapeless.ops.hlist$Unzip<L> apply(shapeless.ops.hlist$Unzip<L>);
    descriptor: (Lshapeless/ops/hlist$Unzip;)Lshapeless/ops/hlist$Unzip;
    flags: (0x0001) ACC_PUBLIC
    Code:
      stack=1, locals=2, args_size=2
         0: aload_1
         1: areturn
      LineNumberTable:
        line 2233: 0
      LocalVariableTable:
        Start  Length  Slot  Name   Signature
            0       2     0  this   Lshapeless/ops/hlist$Unzip$;
            0       2     1 unzip   Lshapeless/ops/hlist$Unzip;
    Signature: #36                          // <L::Lshapeless/HList;>(Lshapeless/ops/hlist$Unzip<TL;>;)Lshapeless/ops/hlist$Unzip<TL;>;
    MethodParameters:
      Name                           Flags
      unzip                          final

  public <L extends shapeless.HList, OutM extends shapeless.HList, TransposerOut extends shapeless.HList, TuplerOut extends java.lang.Object> shapeless.ops.hlist$Unzip<L> unzipper(shapeless.ops.hlist$Mapper<shapeless.productElements$, L>, shapeless.ops.hlist$Transposer<OutM>, shapeless.ops.hlist$Tupler<TransposerOut>);
    descriptor: (Lshapeless/ops/hlist$Mapper;Lshapeless/ops/hlist$Transposer;Lshapeless/ops/hlist$Tupler;)Lshapeless/ops/hlist$Unzip;
    flags: (0x0001) ACC_PUBLIC
    Code:
      stack=5, locals=4, args_size=4
         0: new           #24                 // class shapeless/ops/hlist$Unzip$$anon$150
         3: dup
         4: aload_1
         5: aload_2
         6: aload_3
         7: invokespecial #48                 // Method shapeless/ops/hlist$Unzip$$anon$150."<init>":(Lshapeless/ops/hlist$Mapper;Lshapeless/ops/hlist$Transposer;Lshapeless/ops/hlist$Tupler;)V
        10: areturn
      LineNumberTable:
        line 2242: 0
      LocalVariableTable:
        Start  Length  Slot  Name   Signature
            0      11     0  this   Lshapeless/ops/hlist$Unzip$;
            0      11     1 mapper   Lshapeless/ops/hlist$Mapper;
            0      11     2 transposer   Lshapeless/ops/hlist$Transposer;
            0      11     3 tupler   Lshapeless/ops/hlist$Tupler;
    Signature: #42                          // <L::Lshapeless/HList;OutM::Lshapeless/HList;TransposerOut::Lshapeless/HList;TuplerOut:Ljava/lang/Object;>(Lshapeless/ops/hlist$Mapper<Lshapeless/productElements$;TL;>;Lshapeless/ops/hlist$Transposer<TOutM;>;Lshapeless/ops/hlist$Tupler<TTransposerOut;>;)Lshapeless/ops/hlist$Unzip<TL;>;
    MethodParameters:
      Name                           Flags
      mapper                         final
      transposer                     final
      tupler                         final

  private java.lang.Object writeReplace();
    descriptor: ()Ljava/lang/Object;
    flags: (0x0002) ACC_PRIVATE
    Code:
      stack=3, locals=1, args_size=1
         0: new           #55                 // class scala/runtime/ModuleSerializationProxy
         3: dup
         4: ldc           #2                  // class shapeless/ops/hlist$Unzip$
         6: invokespecial #58                 // Method scala/runtime/ModuleSerializationProxy."<init>":(Ljava/lang/Class;)V
         9: areturn
      LineNumberTable:
        line 2232: 0
      LocalVariableTable:
        Start  Length  Slot  Name   Signature
            0      10     0  this   Lshapeless/ops/hlist$Unzip$;

  public shapeless.ops.hlist$Unzip$();
    descriptor: ()V
    flags: (0x0001) ACC_PUBLIC
    Code:
      stack=1, locals=1, args_size=1
         0: aload_0
         1: invokespecial #59                 // Method java/lang/Object."<init>":()V
         4: return
      LineNumberTable:
        line 2255: 0
        line 2232: 4
      LocalVariableTable:
        Start  Length  Slot  Name   Signature
            0       5     0  this   Lshapeless/ops/hlist$Unzip$;
}
InnerClasses:
  public static #12= #9 of #11;           // Mapper=class shapeless/ops/hlist$Mapper of class shapeless/ops/hlist
  public static #15= #14 of #11;          // Transposer=class shapeless/ops/hlist$Transposer of class shapeless/ops/hlist
  public static #18= #17 of #11;          // Tupler=class shapeless/ops/hlist$Tupler of class shapeless/ops/hlist
  public static #21= #20 of #11;          // Unzip=class shapeless/ops/hlist$Unzip of class shapeless/ops/hlist
  public static #22= #2 of #11;           // Unzip$=class shapeless/ops/hlist$Unzip$ of class shapeless/ops/hlist
  public final #24;                       // class shapeless/ops/hlist$Unzip$$anon$150
SourceFile: "hlists.scala"
  ScalaInlineInfo: length = 0x18 (unknown attribute)
   01 01 00 04 00 1D 00 1C 01 00 22 00 23 01 00 28
   00 29 01 00 34 00 35 01
  Scala: length = 0x0 (unknown attribute)

