Classfile /Users/mw/Projects/slang-braindump/.jar/jar8/assemble/slang-braindump/assemble/content/shapeless/ops/hlist$HConsHKernel$.class
  Last modified May 29, 2022; size 1853 bytes
  SHA-256 checksum 8a8eed97907b11dc136172e216b1580b2739edf0380b14db16c4c69d60031cb7
  Compiled from "hlists.scala"
public class shapeless.ops.hlist$HConsHKernel$ implements java.io.Serializable
  minor version: 0
  major version: 52
  flags: (0x0021) ACC_PUBLIC, ACC_SUPER
  this_class: #2                          // shapeless/ops/hlist$HConsHKernel$
  super_class: #4                         // java/lang/Object
  interfaces: 1, fields: 1, methods: 6, attributes: 4
Constant pool:
   #1 = Utf8               shapeless/ops/hlist$HConsHKernel$
   #2 = Class              #1             // shapeless/ops/hlist$HConsHKernel$
   #3 = Utf8               java/lang/Object
   #4 = Class              #3             // java/lang/Object
   #5 = Utf8               java/io/Serializable
   #6 = Class              #5             // java/io/Serializable
   #7 = Utf8               hlists.scala
   #8 = Utf8               shapeless/ops/hlist$HConsHKernel
   #9 = Class              #8             // shapeless/ops/hlist$HConsHKernel
  #10 = Utf8               shapeless/ops/hlist
  #11 = Class              #10            // shapeless/ops/hlist
  #12 = Utf8               HConsHKernel
  #13 = Utf8               HConsHKernel$
  #14 = Utf8               shapeless/ops/hlist$HKernel
  #15 = Class              #14            // shapeless/ops/hlist$HKernel
  #16 = Utf8               HKernel
  #17 = Utf8               MODULE$
  #18 = Utf8               Lshapeless/ops/hlist$HConsHKernel$;
  #19 = Utf8               <clinit>
  #20 = Utf8               ()V
  #21 = Utf8               <init>
  #22 = NameAndType        #21:#20        // "<init>":()V
  #23 = Methodref          #2.#22         // shapeless/ops/hlist$HConsHKernel$."<init>":()V
  #24 = NameAndType        #17:#18        // MODULE$:Lshapeless/ops/hlist$HConsHKernel$;
  #25 = Fieldref           #2.#24         // shapeless/ops/hlist$HConsHKernel$.MODULE$:Lshapeless/ops/hlist$HConsHKernel$;
  #26 = Utf8               toString
  #27 = Utf8               ()Ljava/lang/String;
  #28 = String             #12            // HConsHKernel
  #29 = Utf8               this
  #30 = Utf8               apply
  #31 = Utf8               (Lshapeless/ops/hlist$HKernel;)Lshapeless/ops/hlist$HConsHKernel;
  #32 = Utf8               <H:Ljava/lang/Object;T::Lshapeless/ops/hlist$HKernel;>(TT;)Lshapeless/ops/hlist$HConsHKernel<TH;TT;>;
  #33 = Utf8               tail
  #34 = Utf8               (Lshapeless/ops/hlist$HKernel;)V
  #35 = NameAndType        #21:#34        // "<init>":(Lshapeless/ops/hlist$HKernel;)V
  #36 = Methodref          #9.#35         // shapeless/ops/hlist$HConsHKernel."<init>":(Lshapeless/ops/hlist$HKernel;)V
  #37 = Utf8               Lshapeless/ops/hlist$HKernel;
  #38 = Utf8               unapply
  #39 = Utf8               (Lshapeless/ops/hlist$HConsHKernel;)Lscala/Option;
  #40 = Utf8               <H:Ljava/lang/Object;T::Lshapeless/ops/hlist$HKernel;>(Lshapeless/ops/hlist$HConsHKernel<TH;TT;>;)Lscala/Option<TT;>;
  #41 = Utf8               x$0
  #42 = Utf8               scala/None$
  #43 = Class              #42            // scala/None$
  #44 = Utf8               Lscala/None$;
  #45 = NameAndType        #17:#44        // MODULE$:Lscala/None$;
  #46 = Fieldref           #43.#45        // scala/None$.MODULE$:Lscala/None$;
  #47 = Utf8               scala/Some
  #48 = Class              #47            // scala/Some
  #49 = Utf8               ()Lshapeless/ops/hlist$HKernel;
  #50 = NameAndType        #33:#49        // tail:()Lshapeless/ops/hlist$HKernel;
  #51 = Methodref          #9.#50         // shapeless/ops/hlist$HConsHKernel.tail:()Lshapeless/ops/hlist$HKernel;
  #52 = Utf8               (Ljava/lang/Object;)V
  #53 = NameAndType        #21:#52        // "<init>":(Ljava/lang/Object;)V
  #54 = Methodref          #48.#53        // scala/Some."<init>":(Ljava/lang/Object;)V
  #55 = Utf8               Lshapeless/ops/hlist$HConsHKernel;
  #56 = Utf8               scala/Option
  #57 = Class              #56            // scala/Option
  #58 = Utf8               writeReplace
  #59 = Utf8               ()Ljava/lang/Object;
  #60 = Utf8               scala/runtime/ModuleSerializationProxy
  #61 = Class              #60            // scala/runtime/ModuleSerializationProxy
  #62 = Utf8               (Ljava/lang/Class;)V
  #63 = NameAndType        #21:#62        // "<init>":(Ljava/lang/Class;)V
  #64 = Methodref          #61.#63        // scala/runtime/ModuleSerializationProxy."<init>":(Ljava/lang/Class;)V
  #65 = Methodref          #4.#22         // java/lang/Object."<init>":()V
  #66 = Utf8               Code
  #67 = Utf8               LineNumberTable
  #68 = Utf8               LocalVariableTable
  #69 = Utf8               Signature
  #70 = Utf8               MethodParameters
  #71 = Utf8               StackMapTable
  #72 = Utf8               InnerClasses
  #73 = Utf8               SourceFile
  #74 = Utf8               ScalaInlineInfo
  #75 = Utf8               Scala
{
  public static final shapeless.ops.hlist$HConsHKernel$ MODULE$;
    descriptor: Lshapeless/ops/hlist$HConsHKernel$;
    flags: (0x0019) ACC_PUBLIC, ACC_STATIC, ACC_FINAL

  public static {};
    descriptor: ()V
    flags: (0x0009) ACC_PUBLIC, ACC_STATIC
    Code:
      stack=2, locals=0, args_size=0
         0: new           #2                  // class shapeless/ops/hlist$HConsHKernel$
         3: dup
         4: invokespecial #23                 // Method "<init>":()V
         7: putstatic     #25                 // Field MODULE$:Lshapeless/ops/hlist$HConsHKernel$;
        10: return
      LineNumberTable:
        line 192: 0

  public final java.lang.String toString();
    descriptor: ()Ljava/lang/String;
    flags: (0x0011) ACC_PUBLIC, ACC_FINAL
    Code:
      stack=1, locals=1, args_size=1
         0: ldc           #28                 // String HConsHKernel
         2: areturn
      LineNumberTable:
        line 192: 0
      LocalVariableTable:
        Start  Length  Slot  Name   Signature
            0       3     0  this   Lshapeless/ops/hlist$HConsHKernel$;

  public <H extends java.lang.Object, T extends shapeless.ops.hlist$HKernel> shapeless.ops.hlist$HConsHKernel<H, T> apply(T);
    descriptor: (Lshapeless/ops/hlist$HKernel;)Lshapeless/ops/hlist$HConsHKernel;
    flags: (0x0001) ACC_PUBLIC
    Code:
      stack=3, locals=2, args_size=2
         0: new           #9                  // class shapeless/ops/hlist$HConsHKernel
         3: dup
         4: aload_1
         5: invokespecial #36                 // Method shapeless/ops/hlist$HConsHKernel."<init>":(Lshapeless/ops/hlist$HKernel;)V
         8: areturn
      LineNumberTable:
        line 192: 0
      LocalVariableTable:
        Start  Length  Slot  Name   Signature
            0       9     0  this   Lshapeless/ops/hlist$HConsHKernel$;
            0       9     1  tail   Lshapeless/ops/hlist$HKernel;
    Signature: #32                          // <H:Ljava/lang/Object;T::Lshapeless/ops/hlist$HKernel;>(TT;)Lshapeless/ops/hlist$HConsHKernel<TH;TT;>;
    MethodParameters:
      Name                           Flags
      tail                           final

  public <H extends java.lang.Object, T extends shapeless.ops.hlist$HKernel> scala.Option<T> unapply(shapeless.ops.hlist$HConsHKernel<H, T>);
    descriptor: (Lshapeless/ops/hlist$HConsHKernel;)Lscala/Option;
    flags: (0x0001) ACC_PUBLIC
    Code:
      stack=3, locals=2, args_size=2
         0: aload_1
         1: ifnonnull     10
         4: getstatic     #46                 // Field scala/None$.MODULE$:Lscala/None$;
         7: goto          21
        10: new           #48                 // class scala/Some
        13: dup
        14: aload_1
        15: invokevirtual #51                 // Method shapeless/ops/hlist$HConsHKernel.tail:()Lshapeless/ops/hlist$HKernel;
        18: invokespecial #54                 // Method scala/Some."<init>":(Ljava/lang/Object;)V
        21: areturn
      StackMapTable: number_of_entries = 2
        frame_type = 10 /* same */
        frame_type = 74 /* same_locals_1_stack_item */
          stack = [ class scala/Option ]
      LineNumberTable:
        line 192: 0
      LocalVariableTable:
        Start  Length  Slot  Name   Signature
            0      22     0  this   Lshapeless/ops/hlist$HConsHKernel$;
            0      22     1   x$0   Lshapeless/ops/hlist$HConsHKernel;
    Signature: #40                          // <H:Ljava/lang/Object;T::Lshapeless/ops/hlist$HKernel;>(Lshapeless/ops/hlist$HConsHKernel<TH;TT;>;)Lscala/Option<TT;>;
    MethodParameters:
      Name                           Flags
      x$0                            final

  private java.lang.Object writeReplace();
    descriptor: ()Ljava/lang/Object;
    flags: (0x0002) ACC_PRIVATE
    Code:
      stack=3, locals=1, args_size=1
         0: new           #61                 // class scala/runtime/ModuleSerializationProxy
         3: dup
         4: ldc           #2                  // class shapeless/ops/hlist$HConsHKernel$
         6: invokespecial #64                 // Method scala/runtime/ModuleSerializationProxy."<init>":(Ljava/lang/Class;)V
         9: areturn
      LineNumberTable:
        line 192: 0
      LocalVariableTable:
        Start  Length  Slot  Name   Signature
            0      10     0  this   Lshapeless/ops/hlist$HConsHKernel$;

  public shapeless.ops.hlist$HConsHKernel$();
    descriptor: ()V
    flags: (0x0001) ACC_PUBLIC
    Code:
      stack=1, locals=1, args_size=1
         0: aload_0
         1: invokespecial #65                 // Method java/lang/Object."<init>":()V
         4: return
      LineNumberTable:
        line 192: 0
      LocalVariableTable:
        Start  Length  Slot  Name   Signature
            0       5     0  this   Lshapeless/ops/hlist$HConsHKernel$;
}
InnerClasses:
  public static final #12= #9 of #11;     // HConsHKernel=class shapeless/ops/hlist$HConsHKernel of class shapeless/ops/hlist
  public static #13= #2 of #11;           // HConsHKernel$=class shapeless/ops/hlist$HConsHKernel$ of class shapeless/ops/hlist
  public static #16= #15 of #11;          // HKernel=class shapeless/ops/hlist$HKernel of class shapeless/ops/hlist
SourceFile: "hlists.scala"
  ScalaInlineInfo: length = 0x1D (unknown attribute)
   01 01 00 05 00 15 00 14 01 00 1E 00 1F 01 00 1A
   00 1B 01 00 26 00 27 01 00 3A 00 3B 01
  Scala: length = 0x0 (unknown attribute)

