Classfile /Users/mw/Projects/slang-braindump/.jar/jar8/assemble/slang-braindump/assemble/content/shapeless/ops/hlist$.class
  Last modified May 29, 2022; size 2312 bytes
  SHA-256 checksum 3c460c077426c44a0f61b04686a5416df730180021250978440834acc55ce88a
  Compiled from "hlists.scala"
public final class shapeless.ops.hlist$
  minor version: 0
  major version: 52
  flags: (0x0031) ACC_PUBLIC, ACC_FINAL, ACC_SUPER
  this_class: #2                          // shapeless/ops/hlist$
  super_class: #4                         // java/lang/Object
  interfaces: 0, fields: 1, methods: 6, attributes: 4
Constant pool:
   #1 = Utf8               shapeless/ops/hlist$
   #2 = Class              #1             // shapeless/ops/hlist$
   #3 = Utf8               java/lang/Object
   #4 = Class              #3             // java/lang/Object
   #5 = Utf8               hlists.scala
   #6 = Utf8               shapeless/ops/hlist$$anon$165
   #7 = Class              #6             // shapeless/ops/hlist$$anon$165
   #8 = Utf8               shapeless/ops/hlist$ToTraversable
   #9 = Class              #8             // shapeless/ops/hlist$ToTraversable
  #10 = Utf8               shapeless/ops/hlist
  #11 = Class              #10            // shapeless/ops/hlist
  #12 = Utf8               ToTraversable
  #13 = Utf8               MODULE$
  #14 = Utf8               Lshapeless/ops/hlist$;
  #15 = Utf8               <clinit>
  #16 = Utf8               ()V
  #17 = Utf8               <init>
  #18 = NameAndType        #17:#16        // "<init>":()V
  #19 = Methodref          #2.#18         // shapeless/ops/hlist$."<init>":()V
  #20 = NameAndType        #13:#14        // MODULE$:Lshapeless/ops/hlist$;
  #21 = Fieldref           #2.#20         // shapeless/ops/hlist$.MODULE$:Lshapeless/ops/hlist$;
  #22 = Utf8               ToArray
  #23 = Utf8               (Lshapeless/ops/hlist$ToTraversable;)Lshapeless/ops/hlist$ToTraversable;
  #24 = Utf8               <L::Lshapeless/HList;Lub:Ljava/lang/Object;>(Lshapeless/ops/hlist$ToTraversable<TL;Lscala/Array;>;)Lshapeless/ops/hlist$ToTraversable<TL;Lscala/Array;>;
  #25 = Utf8               toArray
  #26 = Utf8               this
  #27 = Utf8               Lshapeless/ops/hlist$ToTraversable;
  #28 = Utf8               ToList
  #29 = Utf8               <L::Lshapeless/HList;Lub:Ljava/lang/Object;>(Lshapeless/ops/hlist$ToTraversable<TL;Lscala/collection/immutable/List;>;)Lshapeless/ops/hlist$ToTraversable<TL;Lscala/collection/immutable/List;>;
  #30 = Utf8               toList
  #31 = Utf8               hlistOrdering
  #32 = Utf8               (Lscala/math/Ordering;Lscala/math/Ordering;)Lscala/math/Ordering;
  #33 = Utf8               <H:Ljava/lang/Object;T::Lshapeless/HList;>(Lscala/math/Ordering<TH;>;Lscala/math/Ordering<TT;>;)Lscala/math/Ordering<Lshapeless/$colon$colon<TH;TT;>;>;
  #34 = Utf8               hOrdering
  #35 = Utf8               tOrdering
  #36 = Utf8               (Lscala/math/Ordering;Lscala/math/Ordering;)V
  #37 = NameAndType        #17:#36        // "<init>":(Lscala/math/Ordering;Lscala/math/Ordering;)V
  #38 = Methodref          #7.#37         // shapeless/ops/hlist$$anon$165."<init>":(Lscala/math/Ordering;Lscala/math/Ordering;)V
  #39 = Utf8               Lscala/math/Ordering;
  #40 = Utf8               shapeless$ops$hlist$$toTuple2
  #41 = Utf8               (Lshapeless/$colon$colon;)Lscala/Tuple2;
  #42 = Utf8               <Prefix:Ljava/lang/Object;Suffix:Ljava/lang/Object;>(Lshapeless/$colon$colon<TPrefix;Lshapeless/$colon$colon<TSuffix;Lshapeless/HNil;>;>;)Lscala/Tuple2<TPrefix;TSuffix;>;
  #43 = Utf8               l
  #44 = Utf8               scala/Tuple2
  #45 = Class              #44            // scala/Tuple2
  #46 = Utf8               shapeless/$colon$colon
  #47 = Class              #46            // shapeless/$colon$colon
  #48 = Utf8               head
  #49 = Utf8               ()Ljava/lang/Object;
  #50 = NameAndType        #48:#49        // head:()Ljava/lang/Object;
  #51 = Methodref          #47.#50        // shapeless/$colon$colon.head:()Ljava/lang/Object;
  #52 = Utf8               tail
  #53 = Utf8               ()Lshapeless/HList;
  #54 = NameAndType        #52:#53        // tail:()Lshapeless/HList;
  #55 = Methodref          #47.#54        // shapeless/$colon$colon.tail:()Lshapeless/HList;
  #56 = Utf8               (Ljava/lang/Object;Ljava/lang/Object;)V
  #57 = NameAndType        #17:#56        // "<init>":(Ljava/lang/Object;Ljava/lang/Object;)V
  #58 = Methodref          #45.#57        // scala/Tuple2."<init>":(Ljava/lang/Object;Ljava/lang/Object;)V
  #59 = Utf8               Lshapeless/$colon$colon;
  #60 = Methodref          #4.#18         // java/lang/Object."<init>":()V
  #61 = Utf8               Code
  #62 = Utf8               LineNumberTable
  #63 = Utf8               LocalVariableTable
  #64 = Utf8               Signature
  #65 = Utf8               MethodParameters
  #66 = Utf8               InnerClasses
  #67 = Utf8               SourceFile
  #68 = Utf8               ScalaInlineInfo
  #69 = Utf8               Scala
{
  public static final shapeless.ops.hlist$ MODULE$;
    descriptor: Lshapeless/ops/hlist$;
    flags: (0x0019) ACC_PUBLIC, ACC_STATIC, ACC_FINAL

  public static {};
    descriptor: ()V
    flags: (0x0009) ACC_PUBLIC, ACC_STATIC
    Code:
      stack=2, locals=0, args_size=0
         0: new           #2                  // class shapeless/ops/hlist$
         3: dup
         4: invokespecial #19                 // Method "<init>":()V
         7: putstatic     #21                 // Field MODULE$:Lshapeless/ops/hlist$;
        10: return
      LineNumberTable:
        line 26: 0

  public <L extends shapeless.HList, Lub extends java.lang.Object> shapeless.ops.hlist$ToTraversable<L, scala.Array> ToArray(shapeless.ops.hlist$ToTraversable<L, scala.Array>);
    descriptor: (Lshapeless/ops/hlist$ToTraversable;)Lshapeless/ops/hlist$ToTraversable;
    flags: (0x0001) ACC_PUBLIC
    Code:
      stack=1, locals=2, args_size=2
         0: aload_1
         1: areturn
      LineNumberTable:
        line 719: 0
      LocalVariableTable:
        Start  Length  Slot  Name   Signature
            0       2     0  this   Lshapeless/ops/hlist$;
            0       2     1 toArray   Lshapeless/ops/hlist$ToTraversable;
    Signature: #24                          // <L::Lshapeless/HList;Lub:Ljava/lang/Object;>(Lshapeless/ops/hlist$ToTraversable<TL;Lscala/Array;>;)Lshapeless/ops/hlist$ToTraversable<TL;Lscala/Array;>;
    MethodParameters:
      Name                           Flags
      toArray                        final

  public <L extends shapeless.HList, Lub extends java.lang.Object> shapeless.ops.hlist$ToTraversable<L, scala.collection.immutable.List> ToList(shapeless.ops.hlist$ToTraversable<L, scala.collection.immutable.List>);
    descriptor: (Lshapeless/ops/hlist$ToTraversable;)Lshapeless/ops/hlist$ToTraversable;
    flags: (0x0001) ACC_PUBLIC
    Code:
      stack=1, locals=2, args_size=2
         0: aload_1
         1: areturn
      LineNumberTable:
        line 722: 0
      LocalVariableTable:
        Start  Length  Slot  Name   Signature
            0       2     0  this   Lshapeless/ops/hlist$;
            0       2     1 toList   Lshapeless/ops/hlist$ToTraversable;
    Signature: #29                          // <L::Lshapeless/HList;Lub:Ljava/lang/Object;>(Lshapeless/ops/hlist$ToTraversable<TL;Lscala/collection/immutable/List;>;)Lshapeless/ops/hlist$ToTraversable<TL;Lscala/collection/immutable/List;>;
    MethodParameters:
      Name                           Flags
      toList                         final

  public <H extends java.lang.Object, T extends shapeless.HList> scala.math.Ordering<shapeless.$colon$colon<H, T>> hlistOrdering(scala.math.Ordering<H>, scala.math.Ordering<T>);
    descriptor: (Lscala/math/Ordering;Lscala/math/Ordering;)Lscala/math/Ordering;
    flags: (0x0001) ACC_PUBLIC
    Code:
      stack=4, locals=3, args_size=3
         0: new           #7                  // class shapeless/ops/hlist$$anon$165
         3: dup
         4: aload_1
         5: aload_2
         6: invokespecial #38                 // Method shapeless/ops/hlist$$anon$165."<init>":(Lscala/math/Ordering;Lscala/math/Ordering;)V
         9: areturn
      LineNumberTable:
        line 2464: 0
      LocalVariableTable:
        Start  Length  Slot  Name   Signature
            0      10     0  this   Lshapeless/ops/hlist$;
            0      10     1 hOrdering   Lscala/math/Ordering;
            0      10     2 tOrdering   Lscala/math/Ordering;
    Signature: #33                          // <H:Ljava/lang/Object;T::Lshapeless/HList;>(Lscala/math/Ordering<TH;>;Lscala/math/Ordering<TT;>;)Lscala/math/Ordering<Lshapeless/$colon$colon<TH;TT;>;>;
    MethodParameters:
      Name                           Flags
      hOrdering                      final
      tOrdering                      final

  public <Prefix extends java.lang.Object, Suffix extends java.lang.Object> scala.Tuple2<Prefix, Suffix> shapeless$ops$hlist$$toTuple2(shapeless.$colon$colon<Prefix, shapeless.$colon$colon<Suffix, shapeless.HNil>>);
    descriptor: (Lshapeless/$colon$colon;)Lscala/Tuple2;
    flags: (0x0001) ACC_PUBLIC
    Code:
      stack=4, locals=2, args_size=2
         0: new           #45                 // class scala/Tuple2
         3: dup
         4: aload_1
         5: invokevirtual #51                 // Method shapeless/$colon$colon.head:()Ljava/lang/Object;
         8: aload_1
         9: invokevirtual #55                 // Method shapeless/$colon$colon.tail:()Lshapeless/HList;
        12: checkcast     #47                 // class shapeless/$colon$colon
        15: invokevirtual #51                 // Method shapeless/$colon$colon.head:()Ljava/lang/Object;
        18: invokespecial #58                 // Method scala/Tuple2."<init>":(Ljava/lang/Object;Ljava/lang/Object;)V
        21: areturn
      LineNumberTable:
        line 2868: 0
      LocalVariableTable:
        Start  Length  Slot  Name   Signature
            0      22     0  this   Lshapeless/ops/hlist$;
            0      22     1     l   Lshapeless/$colon$colon;
    Signature: #42                          // <Prefix:Ljava/lang/Object;Suffix:Ljava/lang/Object;>(Lshapeless/$colon$colon<TPrefix;Lshapeless/$colon$colon<TSuffix;Lshapeless/HNil;>;>;)Lscala/Tuple2<TPrefix;TSuffix;>;
    MethodParameters:
      Name                           Flags
      l                              final

  private shapeless.ops.hlist$();
    descriptor: ()V
    flags: (0x0002) ACC_PRIVATE
    Code:
      stack=1, locals=1, args_size=1
         0: aload_0
         1: invokespecial #60                 // Method java/lang/Object."<init>":()V
         4: return
      LineNumberTable:
        line 3040: 0
        line 26: 4
      LocalVariableTable:
        Start  Length  Slot  Name   Signature
            0       5     0  this   Lshapeless/ops/hlist$;
}
InnerClasses:
  public final #7;                        // class shapeless/ops/hlist$$anon$165
  public static #12= #9 of #11;           // ToTraversable=class shapeless/ops/hlist$ToTraversable of class shapeless/ops/hlist
SourceFile: "hlists.scala"
  ScalaInlineInfo: length = 0x1D (unknown attribute)
   01 01 00 05 00 11 00 10 01 00 16 00 17 01 00 1C
   00 17 01 00 1F 00 20 01 00 28 00 29 01
  Scala: length = 0x0 (unknown attribute)

