Classfile /Users/mw/Projects/slang-braindump/.jar/jar8/assemble/slang-braindump/assemble/content/shapeless/ops/hlist$RightScanner$RightScanner0$.class
  Last modified May 29, 2022; size 820 bytes
  SHA-256 checksum 2c7a25e3f91604c5c16bd1d25aece696906708b8d33df42244f3a053eefe195d
  Compiled from "hlists.scala"
public class shapeless.ops.hlist$RightScanner$RightScanner0$ implements java.io.Serializable
  minor version: 0
  major version: 52
  flags: (0x0021) ACC_PUBLIC, ACC_SUPER
  this_class: #2                          // shapeless/ops/hlist$RightScanner$RightScanner0$
  super_class: #4                         // java/lang/Object
  interfaces: 1, fields: 1, methods: 3, attributes: 4
Constant pool:
   #1 = Utf8               shapeless/ops/hlist$RightScanner$RightScanner0$
   #2 = Class              #1             // shapeless/ops/hlist$RightScanner$RightScanner0$
   #3 = Utf8               java/lang/Object
   #4 = Class              #3             // java/lang/Object
   #5 = Utf8               java/io/Serializable
   #6 = Class              #5             // java/io/Serializable
   #7 = Utf8               hlists.scala
   #8 = Utf8               shapeless/ops/hlist$RightScanner$
   #9 = Class              #8             // shapeless/ops/hlist$RightScanner$
  #10 = Utf8               shapeless/ops/hlist
  #11 = Class              #10            // shapeless/ops/hlist
  #12 = Utf8               RightScanner$
  #13 = Utf8               RightScanner0$
  #14 = Utf8               MODULE$
  #15 = Utf8               Lshapeless/ops/hlist$RightScanner$RightScanner0$;
  #16 = Utf8               <clinit>
  #17 = Utf8               ()V
  #18 = Utf8               <init>
  #19 = NameAndType        #18:#17        // "<init>":()V
  #20 = Methodref          #2.#19         // shapeless/ops/hlist$RightScanner$RightScanner0$."<init>":()V
  #21 = NameAndType        #14:#15        // MODULE$:Lshapeless/ops/hlist$RightScanner$RightScanner0$;
  #22 = Fieldref           #2.#21         // shapeless/ops/hlist$RightScanner$RightScanner0$.MODULE$:Lshapeless/ops/hlist$RightScanner$RightScanner0$;
  #23 = Utf8               writeReplace
  #24 = Utf8               ()Ljava/lang/Object;
  #25 = Utf8               scala/runtime/ModuleSerializationProxy
  #26 = Class              #25            // scala/runtime/ModuleSerializationProxy
  #27 = Utf8               (Ljava/lang/Class;)V
  #28 = NameAndType        #18:#27        // "<init>":(Ljava/lang/Class;)V
  #29 = Methodref          #26.#28        // scala/runtime/ModuleSerializationProxy."<init>":(Ljava/lang/Class;)V
  #30 = Utf8               this
  #31 = Methodref          #4.#19         // java/lang/Object."<init>":()V
  #32 = Utf8               Code
  #33 = Utf8               LineNumberTable
  #34 = Utf8               LocalVariableTable
  #35 = Utf8               InnerClasses
  #36 = Utf8               SourceFile
  #37 = Utf8               ScalaInlineInfo
  #38 = Utf8               Scala
{
  public static final shapeless.ops.hlist$RightScanner$RightScanner0$ MODULE$;
    descriptor: Lshapeless/ops/hlist$RightScanner$RightScanner0$;
    flags: (0x0019) ACC_PUBLIC, ACC_STATIC, ACC_FINAL

  public static {};
    descriptor: ()V
    flags: (0x0009) ACC_PUBLIC, ACC_STATIC
    Code:
      stack=2, locals=0, args_size=0
         0: new           #2                  // class shapeless/ops/hlist$RightScanner$RightScanner0$
         3: dup
         4: invokespecial #20                 // Method "<init>":()V
         7: putstatic     #22                 // Field MODULE$:Lshapeless/ops/hlist$RightScanner$RightScanner0$;
        10: return
      LineNumberTable:
        line 2721: 0

  private java.lang.Object writeReplace();
    descriptor: ()Ljava/lang/Object;
    flags: (0x0002) ACC_PRIVATE
    Code:
      stack=3, locals=1, args_size=1
         0: new           #26                 // class scala/runtime/ModuleSerializationProxy
         3: dup
         4: ldc           #2                  // class shapeless/ops/hlist$RightScanner$RightScanner0$
         6: invokespecial #29                 // Method scala/runtime/ModuleSerializationProxy."<init>":(Ljava/lang/Class;)V
         9: areturn
      LineNumberTable:
        line 2721: 0
      LocalVariableTable:
        Start  Length  Slot  Name   Signature
            0      10     0  this   Lshapeless/ops/hlist$RightScanner$RightScanner0$;

  public shapeless.ops.hlist$RightScanner$RightScanner0$();
    descriptor: ()V
    flags: (0x0001) ACC_PUBLIC
    Code:
      stack=1, locals=1, args_size=1
         0: aload_0
         1: invokespecial #31                 // Method java/lang/Object."<init>":()V
         4: return
      LineNumberTable:
        line 2725: 0
        line 2721: 4
      LocalVariableTable:
        Start  Length  Slot  Name   Signature
            0       5     0  this   Lshapeless/ops/hlist$RightScanner$RightScanner0$;
}
InnerClasses:
  public static #12= #9 of #11;           // RightScanner$=class shapeless/ops/hlist$RightScanner$ of class shapeless/ops/hlist
  public static #13= #2 of #9;            // RightScanner0$=class shapeless/ops/hlist$RightScanner$RightScanner0$ of class shapeless/ops/hlist$RightScanner$
SourceFile: "hlists.scala"
  ScalaInlineInfo: length = 0xE (unknown attribute)
   01 01 00 02 00 12 00 11 01 00 17 00 18 01
  Scala: length = 0x0 (unknown attribute)

