Classfile /Users/mw/Projects/slang-braindump/.jar/jar8/assemble/slang-braindump/assemble/content/shapeless/ops/nat$LTEq$.class
  Last modified May 29, 2022; size 2160 bytes
  SHA-256 checksum 0a72852c8828bde45b6cc2528c58a9fffe7d241e2de3b7dd232d3eac25e81059
  Compiled from "nat.scala"
public class shapeless.ops.nat$LTEq$ implements shapeless.ops.nat$LTEq0,java.io.Serializable
  minor version: 0
  major version: 52
  flags: (0x0021) ACC_PUBLIC, ACC_SUPER
  this_class: #2                          // shapeless/ops/nat$LTEq$
  super_class: #4                         // java/lang/Object
  interfaces: 2, fields: 1, methods: 8, attributes: 4
Constant pool:
   #1 = Utf8               shapeless/ops/nat$LTEq$
   #2 = Class              #1             // shapeless/ops/nat$LTEq$
   #3 = Utf8               java/lang/Object
   #4 = Class              #3             // java/lang/Object
   #5 = Utf8               shapeless/ops/nat$LTEq0
   #6 = Class              #5             // shapeless/ops/nat$LTEq0
   #7 = Utf8               java/io/Serializable
   #8 = Class              #7             // java/io/Serializable
   #9 = Utf8               nat.scala
  #10 = Utf8               shapeless/ops/nat$LTEq
  #11 = Class              #10            // shapeless/ops/nat$LTEq
  #12 = Utf8               shapeless/ops/nat
  #13 = Class              #12            // shapeless/ops/nat
  #14 = Utf8               LTEq
  #15 = Utf8               LTEq$
  #16 = Utf8               shapeless/ops/nat$LTEq$$anon$15
  #17 = Class              #16            // shapeless/ops/nat$LTEq$$anon$15
  #18 = Utf8               shapeless/ops/nat$LTEq$$anon$16
  #19 = Class              #18            // shapeless/ops/nat$LTEq$$anon$16
  #20 = Utf8               LTEq0
  #21 = Utf8               MODULE$
  #22 = Utf8               Lshapeless/ops/nat$LTEq$;
  #23 = Utf8               <clinit>
  #24 = Utf8               ()V
  #25 = Utf8               <init>
  #26 = NameAndType        #25:#24        // "<init>":()V
  #27 = Methodref          #2.#26         // shapeless/ops/nat$LTEq$."<init>":()V
  #28 = NameAndType        #21:#22        // MODULE$:Lshapeless/ops/nat$LTEq$;
  #29 = Fieldref           #2.#28         // shapeless/ops/nat$LTEq$.MODULE$:Lshapeless/ops/nat$LTEq$;
  #30 = Utf8               $init$
  #31 = Utf8               (Lshapeless/ops/nat$LTEq0;)V
  #32 = NameAndType        #30:#31        // $init$:(Lshapeless/ops/nat$LTEq0;)V
  #33 = InterfaceMethodref #6.#32         // shapeless/ops/nat$LTEq0.$init$:(Lshapeless/ops/nat$LTEq0;)V
  #34 = Utf8               ltEq3
  #35 = Utf8               ()Lshapeless/ops/nat$LTEq;
  #36 = Utf8               <B::Lshapeless/Nat;>()Lshapeless/ops/nat$LTEq<Lshapeless/_0;TB;>;
  #37 = Utf8               ltEq3$
  #38 = Utf8               (Lshapeless/ops/nat$LTEq0;)Lshapeless/ops/nat$LTEq;
  #39 = NameAndType        #37:#38        // ltEq3$:(Lshapeless/ops/nat$LTEq0;)Lshapeless/ops/nat$LTEq;
  #40 = InterfaceMethodref #6.#39         // shapeless/ops/nat$LTEq0.ltEq3$:(Lshapeless/ops/nat$LTEq0;)Lshapeless/ops/nat$LTEq;
  #41 = Utf8               this
  #42 = Utf8               ltEq4
  #43 = Utf8               (Lshapeless/ops/nat$LTEq;)Lshapeless/ops/nat$LTEq;
  #44 = Utf8               <A::Lshapeless/Nat;B::Lshapeless/Nat;>(Lshapeless/ops/nat$LTEq<TA;TB;>;)Lshapeless/ops/nat$LTEq<Lshapeless/Succ<TA;>;Lshapeless/Succ<TB;>;>;
  #45 = Utf8               lteq
  #46 = Utf8               ltEq4$
  #47 = Utf8               (Lshapeless/ops/nat$LTEq0;Lshapeless/ops/nat$LTEq;)Lshapeless/ops/nat$LTEq;
  #48 = NameAndType        #46:#47        // ltEq4$:(Lshapeless/ops/nat$LTEq0;Lshapeless/ops/nat$LTEq;)Lshapeless/ops/nat$LTEq;
  #49 = InterfaceMethodref #6.#48         // shapeless/ops/nat$LTEq0.ltEq4$:(Lshapeless/ops/nat$LTEq0;Lshapeless/ops/nat$LTEq;)Lshapeless/ops/nat$LTEq;
  #50 = Utf8               Lshapeless/ops/nat$LTEq;
  #51 = Utf8               apply
  #52 = Utf8               <A::Lshapeless/Nat;B::Lshapeless/Nat;>(Lshapeless/ops/nat$LTEq<TA;TB;>;)Lshapeless/ops/nat$LTEq<TA;TB;>;
  #53 = Utf8               ltEq1
  #54 = Utf8               <A::Lshapeless/Nat;>()Lshapeless/ops/nat$LTEq<TA;TA;>;
  #55 = Methodref          #17.#26        // shapeless/ops/nat$LTEq$$anon$15."<init>":()V
  #56 = Utf8               ltEq2
  #57 = Utf8               <A::Lshapeless/Nat;>()Lshapeless/ops/nat$LTEq<TA;Lshapeless/Succ<TA;>;>;
  #58 = Methodref          #19.#26        // shapeless/ops/nat$LTEq$$anon$16."<init>":()V
  #59 = Utf8               writeReplace
  #60 = Utf8               ()Ljava/lang/Object;
  #61 = Utf8               scala/runtime/ModuleSerializationProxy
  #62 = Class              #61            // scala/runtime/ModuleSerializationProxy
  #63 = Utf8               (Ljava/lang/Class;)V
  #64 = NameAndType        #25:#63        // "<init>":(Ljava/lang/Class;)V
  #65 = Methodref          #62.#64        // scala/runtime/ModuleSerializationProxy."<init>":(Ljava/lang/Class;)V
  #66 = Methodref          #4.#26         // java/lang/Object."<init>":()V
  #67 = Utf8               Code
  #68 = Utf8               LineNumberTable
  #69 = Utf8               LocalVariableTable
  #70 = Utf8               Signature
  #71 = Utf8               MethodParameters
  #72 = Utf8               InnerClasses
  #73 = Utf8               SourceFile
  #74 = Utf8               ScalaInlineInfo
  #75 = Utf8               Scala
{
  public static final shapeless.ops.nat$LTEq$ MODULE$;
    descriptor: Lshapeless/ops/nat$LTEq$;
    flags: (0x0019) ACC_PUBLIC, ACC_STATIC, ACC_FINAL

  public static {};
    descriptor: ()V
    flags: (0x0009) ACC_PUBLIC, ACC_STATIC
    Code:
      stack=2, locals=0, args_size=0
         0: new           #2                  // class shapeless/ops/nat$LTEq$
         3: dup
         4: invokespecial #27                 // Method "<init>":()V
         7: putstatic     #29                 // Field MODULE$:Lshapeless/ops/nat$LTEq$;
        10: getstatic     #29                 // Field MODULE$:Lshapeless/ops/nat$LTEq$;
        13: invokestatic  #33                 // InterfaceMethod shapeless/ops/nat$LTEq0.$init$:(Lshapeless/ops/nat$LTEq0;)V
        16: return
      LineNumberTable:
        line 160: 0

  public <B extends shapeless.Nat> shapeless.ops.nat$LTEq<shapeless._0, B> ltEq3();
    descriptor: ()Lshapeless/ops/nat$LTEq;
    flags: (0x0001) ACC_PUBLIC
    Code:
      stack=1, locals=1, args_size=1
         0: aload_0
         1: invokestatic  #40                 // InterfaceMethod shapeless/ops/nat$LTEq0.ltEq3$:(Lshapeless/ops/nat$LTEq0;)Lshapeless/ops/nat$LTEq;
         4: areturn
      LineNumberTable:
        line 160: 0
      LocalVariableTable:
        Start  Length  Slot  Name   Signature
            0       5     0  this   Lshapeless/ops/nat$LTEq$;
    Signature: #36                          // <B::Lshapeless/Nat;>()Lshapeless/ops/nat$LTEq<Lshapeless/_0;TB;>;

  public <A extends shapeless.Nat, B extends shapeless.Nat> shapeless.ops.nat$LTEq<shapeless.Succ<A>, shapeless.Succ<B>> ltEq4(shapeless.ops.nat$LTEq<A, B>);
    descriptor: (Lshapeless/ops/nat$LTEq;)Lshapeless/ops/nat$LTEq;
    flags: (0x0001) ACC_PUBLIC
    Code:
      stack=2, locals=2, args_size=2
         0: aload_0
         1: aload_1
         2: invokestatic  #49                 // InterfaceMethod shapeless/ops/nat$LTEq0.ltEq4$:(Lshapeless/ops/nat$LTEq0;Lshapeless/ops/nat$LTEq;)Lshapeless/ops/nat$LTEq;
         5: areturn
      LineNumberTable:
        line 160: 0
      LocalVariableTable:
        Start  Length  Slot  Name   Signature
            0       6     0  this   Lshapeless/ops/nat$LTEq$;
            0       6     1  lteq   Lshapeless/ops/nat$LTEq;
    Signature: #44                          // <A::Lshapeless/Nat;B::Lshapeless/Nat;>(Lshapeless/ops/nat$LTEq<TA;TB;>;)Lshapeless/ops/nat$LTEq<Lshapeless/Succ<TA;>;Lshapeless/Succ<TB;>;>;
    MethodParameters:
      Name                           Flags
      lteq                           final

  public <A extends shapeless.Nat, B extends shapeless.Nat> shapeless.ops.nat$LTEq<A, B> apply(shapeless.ops.nat$LTEq<A, B>);
    descriptor: (Lshapeless/ops/nat$LTEq;)Lshapeless/ops/nat$LTEq;
    flags: (0x0001) ACC_PUBLIC
    Code:
      stack=1, locals=2, args_size=2
         0: aload_1
         1: areturn
      LineNumberTable:
        line 161: 0
      LocalVariableTable:
        Start  Length  Slot  Name   Signature
            0       2     0  this   Lshapeless/ops/nat$LTEq$;
            0       2     1  lteq   Lshapeless/ops/nat$LTEq;
    Signature: #52                          // <A::Lshapeless/Nat;B::Lshapeless/Nat;>(Lshapeless/ops/nat$LTEq<TA;TB;>;)Lshapeless/ops/nat$LTEq<TA;TB;>;
    MethodParameters:
      Name                           Flags
      lteq                           final

  public <A extends shapeless.Nat> shapeless.ops.nat$LTEq<A, A> ltEq1();
    descriptor: ()Lshapeless/ops/nat$LTEq;
    flags: (0x0001) ACC_PUBLIC
    Code:
      stack=2, locals=1, args_size=1
         0: new           #17                 // class shapeless/ops/nat$LTEq$$anon$15
         3: dup
         4: invokespecial #55                 // Method shapeless/ops/nat$LTEq$$anon$15."<init>":()V
         7: areturn
      LineNumberTable:
        line 163: 0
      LocalVariableTable:
        Start  Length  Slot  Name   Signature
            0       8     0  this   Lshapeless/ops/nat$LTEq$;
    Signature: #54                          // <A::Lshapeless/Nat;>()Lshapeless/ops/nat$LTEq<TA;TA;>;

  public <A extends shapeless.Nat> shapeless.ops.nat$LTEq<A, shapeless.Succ<A>> ltEq2();
    descriptor: ()Lshapeless/ops/nat$LTEq;
    flags: (0x0001) ACC_PUBLIC
    Code:
      stack=2, locals=1, args_size=1
         0: new           #19                 // class shapeless/ops/nat$LTEq$$anon$16
         3: dup
         4: invokespecial #58                 // Method shapeless/ops/nat$LTEq$$anon$16."<init>":()V
         7: areturn
      LineNumberTable:
        line 164: 0
      LocalVariableTable:
        Start  Length  Slot  Name   Signature
            0       8     0  this   Lshapeless/ops/nat$LTEq$;
    Signature: #57                          // <A::Lshapeless/Nat;>()Lshapeless/ops/nat$LTEq<TA;Lshapeless/Succ<TA;>;>;

  private java.lang.Object writeReplace();
    descriptor: ()Ljava/lang/Object;
    flags: (0x0002) ACC_PRIVATE
    Code:
      stack=3, locals=1, args_size=1
         0: new           #62                 // class scala/runtime/ModuleSerializationProxy
         3: dup
         4: ldc           #2                  // class shapeless/ops/nat$LTEq$
         6: invokespecial #65                 // Method scala/runtime/ModuleSerializationProxy."<init>":(Ljava/lang/Class;)V
         9: areturn
      LineNumberTable:
        line 160: 0
      LocalVariableTable:
        Start  Length  Slot  Name   Signature
            0      10     0  this   Lshapeless/ops/nat$LTEq$;

  public shapeless.ops.nat$LTEq$();
    descriptor: ()V
    flags: (0x0001) ACC_PUBLIC
    Code:
      stack=1, locals=1, args_size=1
         0: aload_0
         1: invokespecial #66                 // Method java/lang/Object."<init>":()V
         4: return
      LineNumberTable:
        line 160: 0
      LocalVariableTable:
        Start  Length  Slot  Name   Signature
            0       5     0  this   Lshapeless/ops/nat$LTEq$;
}
InnerClasses:
  public static #14= #11 of #13;          // LTEq=class shapeless/ops/nat$LTEq of class shapeless/ops/nat
  public static #15= #2 of #13;           // LTEq$=class shapeless/ops/nat$LTEq$ of class shapeless/ops/nat
  public final #17;                       // class shapeless/ops/nat$LTEq$$anon$15
  public final #19;                       // class shapeless/ops/nat$LTEq$$anon$16
  public static #20= #6 of #13;           // LTEq0=class shapeless/ops/nat$LTEq0 of class shapeless/ops/nat
SourceFile: "nat.scala"
  ScalaInlineInfo: length = 0x27 (unknown attribute)
   01 01 00 07 00 19 00 18 01 00 33 00 2B 01 00 35
   00 23 01 00 38 00 23 01 00 22 00 23 01 00 2A 00
   2B 01 00 3B 00 3C 01
  Scala: length = 0x0 (unknown attribute)

