Classfile /Users/mw/Projects/slang-braindump/.jar/jar8/assemble/slang-braindump/assemble/content/shapeless/ops/nat$ToInt$.class
  Last modified May 29, 2022; size 1691 bytes
  SHA-256 checksum adf8ba2686e9955208fa8aa3deabec6b937c12ed90dfcbffc8c9c6775a3a8d5d
  Compiled from "nat.scala"
public class shapeless.ops.nat$ToInt$ implements java.io.Serializable
  minor version: 0
  major version: 52
  flags: (0x0021) ACC_PUBLIC, ACC_SUPER
  this_class: #2                          // shapeless/ops/nat$ToInt$
  super_class: #4                         // java/lang/Object
  interfaces: 1, fields: 2, methods: 6, attributes: 4
Constant pool:
   #1 = Utf8               shapeless/ops/nat$ToInt$
   #2 = Class              #1             // shapeless/ops/nat$ToInt$
   #3 = Utf8               java/lang/Object
   #4 = Class              #3             // java/lang/Object
   #5 = Utf8               java/io/Serializable
   #6 = Class              #5             // java/io/Serializable
   #7 = Utf8               nat.scala
   #8 = Utf8               shapeless/ops/nat$ToInt
   #9 = Class              #8             // shapeless/ops/nat$ToInt
  #10 = Utf8               shapeless/ops/nat
  #11 = Class              #10            // shapeless/ops/nat
  #12 = Utf8               ToInt
  #13 = Utf8               ToInt$
  #14 = Utf8               shapeless/ops/nat$ToInt$$anon$49
  #15 = Class              #14            // shapeless/ops/nat$ToInt$$anon$49
  #16 = Utf8               shapeless/ops/nat$ToInt$Inst
  #17 = Class              #16            // shapeless/ops/nat$ToInt$Inst
  #18 = Utf8               Inst
  #19 = Utf8               MODULE$
  #20 = Utf8               Lshapeless/ops/nat$ToInt$;
  #21 = Utf8               toInt0
  #22 = Utf8               Lshapeless/ops/nat$ToInt;
  #23 = Utf8               Lshapeless/ops/nat$ToInt<Lshapeless/_0;>;
  #24 = Utf8               <clinit>
  #25 = Utf8               ()V
  #26 = Utf8               <init>
  #27 = NameAndType        #26:#25        // "<init>":()V
  #28 = Methodref          #2.#27         // shapeless/ops/nat$ToInt$."<init>":()V
  #29 = NameAndType        #19:#20        // MODULE$:Lshapeless/ops/nat$ToInt$;
  #30 = Fieldref           #2.#29         // shapeless/ops/nat$ToInt$.MODULE$:Lshapeless/ops/nat$ToInt$;
  #31 = Utf8               (I)V
  #32 = NameAndType        #26:#31        // "<init>":(I)V
  #33 = Methodref          #17.#32        // shapeless/ops/nat$ToInt$Inst."<init>":(I)V
  #34 = NameAndType        #21:#22        // toInt0:Lshapeless/ops/nat$ToInt;
  #35 = Fieldref           #2.#34         // shapeless/ops/nat$ToInt$.toInt0:Lshapeless/ops/nat$ToInt;
  #36 = Utf8               apply
  #37 = Utf8               (Lshapeless/ops/nat$ToInt;)Lshapeless/ops/nat$ToInt;
  #38 = Utf8               <N::Lshapeless/Nat;>(Lshapeless/ops/nat$ToInt<TN;>;)Lshapeless/ops/nat$ToInt<TN;>;
  #39 = Utf8               toInt
  #40 = Utf8               this
  #41 = Utf8               ()Lshapeless/ops/nat$ToInt;
  #42 = Utf8               ()Lshapeless/ops/nat$ToInt<Lshapeless/_0;>;
  #43 = Utf8               toIntSucc
  #44 = Utf8               <N::Lshapeless/Nat;>(Lshapeless/ops/nat$ToInt<TN;>;)Lshapeless/ops/nat$ToInt<Lshapeless/Succ<TN;>;>;
  #45 = Utf8               toIntN
  #46 = Utf8               (Lshapeless/ops/nat$ToInt;)V
  #47 = NameAndType        #26:#46        // "<init>":(Lshapeless/ops/nat$ToInt;)V
  #48 = Methodref          #15.#47        // shapeless/ops/nat$ToInt$$anon$49."<init>":(Lshapeless/ops/nat$ToInt;)V
  #49 = Utf8               writeReplace
  #50 = Utf8               ()Ljava/lang/Object;
  #51 = Utf8               scala/runtime/ModuleSerializationProxy
  #52 = Class              #51            // scala/runtime/ModuleSerializationProxy
  #53 = Utf8               (Ljava/lang/Class;)V
  #54 = NameAndType        #26:#53        // "<init>":(Ljava/lang/Class;)V
  #55 = Methodref          #52.#54        // scala/runtime/ModuleSerializationProxy."<init>":(Ljava/lang/Class;)V
  #56 = Methodref          #4.#27         // java/lang/Object."<init>":()V
  #57 = Utf8               Signature
  #58 = Utf8               Code
  #59 = Utf8               LineNumberTable
  #60 = Utf8               LocalVariableTable
  #61 = Utf8               MethodParameters
  #62 = Utf8               InnerClasses
  #63 = Utf8               SourceFile
  #64 = Utf8               ScalaInlineInfo
  #65 = Utf8               toIntSuccM
  #66 = Utf8               Scala
{
  public static final shapeless.ops.nat$ToInt$ MODULE$;
    descriptor: Lshapeless/ops/nat$ToInt$;
    flags: (0x0019) ACC_PUBLIC, ACC_STATIC, ACC_FINAL

  private static final shapeless.ops.nat$ToInt<shapeless._0> toInt0;
    descriptor: Lshapeless/ops/nat$ToInt;
    flags: (0x001a) ACC_PRIVATE, ACC_STATIC, ACC_FINAL
    Signature: #23                          // Lshapeless/ops/nat$ToInt<Lshapeless/_0;>;

  public static {};
    descriptor: ()V
    flags: (0x0009) ACC_PUBLIC, ACC_STATIC
    Code:
      stack=3, locals=0, args_size=0
         0: new           #2                  // class shapeless/ops/nat$ToInt$
         3: dup
         4: invokespecial #28                 // Method "<init>":()V
         7: putstatic     #30                 // Field MODULE$:Lshapeless/ops/nat$ToInt$;
        10: new           #17                 // class shapeless/ops/nat$ToInt$Inst
        13: dup
        14: iconst_0
        15: invokespecial #33                 // Method shapeless/ops/nat$ToInt$Inst."<init>":(I)V
        18: putstatic     #35                 // Field toInt0:Lshapeless/ops/nat$ToInt;
        21: return
      LineNumberTable:
        line 598: 0
        line 605: 10
        line 598: 21

  public <N extends shapeless.Nat> shapeless.ops.nat$ToInt<N> apply(shapeless.ops.nat$ToInt<N>);
    descriptor: (Lshapeless/ops/nat$ToInt;)Lshapeless/ops/nat$ToInt;
    flags: (0x0001) ACC_PUBLIC
    Code:
      stack=1, locals=2, args_size=2
         0: aload_1
         1: areturn
      LineNumberTable:
        line 599: 0
      LocalVariableTable:
        Start  Length  Slot  Name   Signature
            0       2     0  this   Lshapeless/ops/nat$ToInt$;
            0       2     1 toInt   Lshapeless/ops/nat$ToInt;
    Signature: #38                          // <N::Lshapeless/Nat;>(Lshapeless/ops/nat$ToInt<TN;>;)Lshapeless/ops/nat$ToInt<TN;>;
    MethodParameters:
      Name                           Flags
      toInt                          final

  public shapeless.ops.nat$ToInt<shapeless._0> toInt0();
    descriptor: ()Lshapeless/ops/nat$ToInt;
    flags: (0x0001) ACC_PUBLIC
    Code:
      stack=1, locals=1, args_size=1
         0: getstatic     #35                 // Field toInt0:Lshapeless/ops/nat$ToInt;
         3: areturn
      LineNumberTable:
        line 605: 0
      LocalVariableTable:
        Start  Length  Slot  Name   Signature
            0       4     0  this   Lshapeless/ops/nat$ToInt$;
    Signature: #42                          // ()Lshapeless/ops/nat$ToInt<Lshapeless/_0;>;

  public <N extends shapeless.Nat> shapeless.ops.nat$ToInt<shapeless.Succ<N>> toIntSucc(shapeless.ops.nat$ToInt<N>);
    descriptor: (Lshapeless/ops/nat$ToInt;)Lshapeless/ops/nat$ToInt;
    flags: (0x0001) ACC_PUBLIC
    Code:
      stack=3, locals=2, args_size=2
         0: new           #15                 // class shapeless/ops/nat$ToInt$$anon$49
         3: dup
         4: aload_1
         5: invokespecial #48                 // Method shapeless/ops/nat$ToInt$$anon$49."<init>":(Lshapeless/ops/nat$ToInt;)V
         8: areturn
      LineNumberTable:
        line 608: 0
      LocalVariableTable:
        Start  Length  Slot  Name   Signature
            0       9     0  this   Lshapeless/ops/nat$ToInt$;
            0       9     1 toIntN   Lshapeless/ops/nat$ToInt;
    Signature: #44                          // <N::Lshapeless/Nat;>(Lshapeless/ops/nat$ToInt<TN;>;)Lshapeless/ops/nat$ToInt<Lshapeless/Succ<TN;>;>;
    MethodParameters:
      Name                           Flags
      toIntN                         final

  private java.lang.Object writeReplace();
    descriptor: ()Ljava/lang/Object;
    flags: (0x0002) ACC_PRIVATE
    Code:
      stack=3, locals=1, args_size=1
         0: new           #52                 // class scala/runtime/ModuleSerializationProxy
         3: dup
         4: ldc           #2                  // class shapeless/ops/nat$ToInt$
         6: invokespecial #55                 // Method scala/runtime/ModuleSerializationProxy."<init>":(Ljava/lang/Class;)V
         9: areturn
      LineNumberTable:
        line 598: 0
      LocalVariableTable:
        Start  Length  Slot  Name   Signature
            0      10     0  this   Lshapeless/ops/nat$ToInt$;

  public shapeless.ops.nat$ToInt$();
    descriptor: ()V
    flags: (0x0001) ACC_PUBLIC
    Code:
      stack=1, locals=1, args_size=1
         0: aload_0
         1: invokespecial #56                 // Method java/lang/Object."<init>":()V
         4: return
      LineNumberTable:
        line 615: 0
        line 598: 4
      LocalVariableTable:
        Start  Length  Slot  Name   Signature
            0       5     0  this   Lshapeless/ops/nat$ToInt$;
}
InnerClasses:
  public static #12= #9 of #11;           // ToInt=class shapeless/ops/nat$ToInt of class shapeless/ops/nat
  public static #13= #2 of #11;           // ToInt$=class shapeless/ops/nat$ToInt$ of class shapeless/ops/nat
  public final #15;                       // class shapeless/ops/nat$ToInt$$anon$49
  public static #18= #17 of #2;           // Inst=class shapeless/ops/nat$ToInt$Inst of class shapeless/ops/nat$ToInt$
SourceFile: "nat.scala"
  ScalaInlineInfo: length = 0x22 (unknown attribute)
   01 01 00 06 00 1A 00 19 01 00 24 00 25 01 00 15
   00 29 01 00 2B 00 25 01 00 41 00 29 01 00 31 00
   32 01
  Scala: length = 0x0 (unknown attribute)

