Classfile /Users/mw/Projects/slang-braindump/.jar/jar8/assemble/slang-braindump/assemble/content/shapeless/ops/traversable$FromTraversable$.class
  Last modified May 29, 2022; size 2180 bytes
  SHA-256 checksum 9387e5e32d5058cd45f58da64dfe8ddf7ee8ab8a2a8b4d95e3219890735c5bdd
  Compiled from "traversables.scala"
public class shapeless.ops.traversable$FromTraversable$ implements java.io.Serializable
  minor version: 0
  major version: 52
  flags: (0x0021) ACC_PUBLIC, ACC_SUPER
  this_class: #2                          // shapeless/ops/traversable$FromTraversable$
  super_class: #4                         // java/lang/Object
  interfaces: 1, fields: 1, methods: 6, attributes: 4
Constant pool:
   #1 = Utf8               shapeless/ops/traversable$FromTraversable$
   #2 = Class              #1             // shapeless/ops/traversable$FromTraversable$
   #3 = Utf8               java/lang/Object
   #4 = Class              #3             // java/lang/Object
   #5 = Utf8               java/io/Serializable
   #6 = Class              #5             // java/io/Serializable
   #7 = Utf8               traversables.scala
   #8 = Utf8               shapeless/ops/traversable$FromTraversable
   #9 = Class              #8             // shapeless/ops/traversable$FromTraversable
  #10 = Utf8               shapeless/ops/traversable
  #11 = Class              #10            // shapeless/ops/traversable
  #12 = Utf8               FromTraversable
  #13 = Utf8               FromTraversable$
  #14 = Utf8               shapeless/ops/traversable$FromTraversable$$anon$1
  #15 = Class              #14            // shapeless/ops/traversable$FromTraversable$$anon$1
  #16 = Utf8               shapeless/ops/traversable$FromTraversable$$anon$2
  #17 = Class              #16            // shapeless/ops/traversable$FromTraversable$$anon$2
  #18 = Utf8               MODULE$
  #19 = Utf8               Lshapeless/ops/traversable$FromTraversable$;
  #20 = Utf8               <clinit>
  #21 = Utf8               ()V
  #22 = Utf8               <init>
  #23 = NameAndType        #22:#21        // "<init>":()V
  #24 = Methodref          #2.#23         // shapeless/ops/traversable$FromTraversable$."<init>":()V
  #25 = NameAndType        #18:#19        // MODULE$:Lshapeless/ops/traversable$FromTraversable$;
  #26 = Fieldref           #2.#25         // shapeless/ops/traversable$FromTraversable$.MODULE$:Lshapeless/ops/traversable$FromTraversable$;
  #27 = Utf8               apply
  #28 = Utf8               (Lshapeless/ops/traversable$FromTraversable;)Lshapeless/ops/traversable$FromTraversable;
  #29 = Utf8               <Out::Lshapeless/HList;>(Lshapeless/ops/traversable$FromTraversable<TOut;>;)Lshapeless/ops/traversable$FromTraversable<TOut;>;
  #30 = Utf8               from
  #31 = Utf8               this
  #32 = Utf8               Lshapeless/ops/traversable$FromTraversable;
  #33 = Utf8               hnilFromTraversable
  #34 = Utf8               ()Lshapeless/ops/traversable$FromTraversable;
  #35 = Utf8               <T:Ljava/lang/Object;>()Lshapeless/ops/traversable$FromTraversable<Lshapeless/HNil;>;
  #36 = Methodref          #15.#23        // shapeless/ops/traversable$FromTraversable$$anon$1."<init>":()V
  #37 = Utf8               hlistFromTraversable
  #38 = Utf8               (Lshapeless/ops/traversable$FromTraversable;Lshapeless/Typeable;)Lshapeless/ops/traversable$FromTraversable;
  #39 = Utf8               <OutH:Ljava/lang/Object;OutT::Lshapeless/HList;>(Lshapeless/ops/traversable$FromTraversable<TOutT;>;Lshapeless/Typeable<TOutH;>;)Lshapeless/ops/traversable$FromTraversable<Lshapeless/$colon$colon<TOutH;TOutT;>;>;
  #40 = Utf8               flt
  #41 = Utf8               oc
  #42 = Utf8               (Lshapeless/Typeable;Lshapeless/ops/traversable$FromTraversable;)V
  #43 = NameAndType        #22:#42        // "<init>":(Lshapeless/Typeable;Lshapeless/ops/traversable$FromTraversable;)V
  #44 = Methodref          #17.#43        // shapeless/ops/traversable$FromTraversable$$anon$2."<init>":(Lshapeless/Typeable;Lshapeless/ops/traversable$FromTraversable;)V
  #45 = Utf8               Lshapeless/Typeable;
  #46 = Utf8               writeReplace
  #47 = Utf8               ()Ljava/lang/Object;
  #48 = Utf8               scala/runtime/ModuleSerializationProxy
  #49 = Class              #48            // scala/runtime/ModuleSerializationProxy
  #50 = Utf8               (Ljava/lang/Class;)V
  #51 = NameAndType        #22:#50        // "<init>":(Ljava/lang/Class;)V
  #52 = Methodref          #49.#51        // scala/runtime/ModuleSerializationProxy."<init>":(Ljava/lang/Class;)V
  #53 = Methodref          #4.#23         // java/lang/Object."<init>":()V
  #54 = Utf8               Code
  #55 = Utf8               LineNumberTable
  #56 = Utf8               LocalVariableTable
  #57 = Utf8               Signature
  #58 = Utf8               MethodParameters
  #59 = Utf8               InnerClasses
  #60 = Utf8               SourceFile
  #61 = Utf8               ScalaInlineInfo
  #62 = Utf8               Scala
{
  public static final shapeless.ops.traversable$FromTraversable$ MODULE$;
    descriptor: Lshapeless/ops/traversable$FromTraversable$;
    flags: (0x0019) ACC_PUBLIC, ACC_STATIC, ACC_FINAL

  public static {};
    descriptor: ()V
    flags: (0x0009) ACC_PUBLIC, ACC_STATIC
    Code:
      stack=2, locals=0, args_size=0
         0: new           #2                  // class shapeless/ops/traversable$FromTraversable$
         3: dup
         4: invokespecial #24                 // Method "<init>":()V
         7: putstatic     #26                 // Field MODULE$:Lshapeless/ops/traversable$FromTraversable$;
        10: return
      LineNumberTable:
        line 35: 0

  public <Out extends shapeless.HList> shapeless.ops.traversable$FromTraversable<Out> apply(shapeless.ops.traversable$FromTraversable<Out>);
    descriptor: (Lshapeless/ops/traversable$FromTraversable;)Lshapeless/ops/traversable$FromTraversable;
    flags: (0x0001) ACC_PUBLIC
    Code:
      stack=1, locals=2, args_size=2
         0: aload_1
         1: areturn
      LineNumberTable:
        line 36: 0
      LocalVariableTable:
        Start  Length  Slot  Name   Signature
            0       2     0  this   Lshapeless/ops/traversable$FromTraversable$;
            0       2     1  from   Lshapeless/ops/traversable$FromTraversable;
    Signature: #29                          // <Out::Lshapeless/HList;>(Lshapeless/ops/traversable$FromTraversable<TOut;>;)Lshapeless/ops/traversable$FromTraversable<TOut;>;
    MethodParameters:
      Name                           Flags
      from                           final

  public <T extends java.lang.Object> shapeless.ops.traversable$FromTraversable<shapeless.HNil> hnilFromTraversable();
    descriptor: ()Lshapeless/ops/traversable$FromTraversable;
    flags: (0x0001) ACC_PUBLIC
    Code:
      stack=2, locals=1, args_size=1
         0: new           #15                 // class shapeless/ops/traversable$FromTraversable$$anon$1
         3: dup
         4: invokespecial #36                 // Method shapeless/ops/traversable$FromTraversable$$anon$1."<init>":()V
         7: areturn
      LineNumberTable:
        line 40: 0
      LocalVariableTable:
        Start  Length  Slot  Name   Signature
            0       8     0  this   Lshapeless/ops/traversable$FromTraversable$;
    Signature: #35                          // <T:Ljava/lang/Object;>()Lshapeless/ops/traversable$FromTraversable<Lshapeless/HNil;>;

  public <OutH extends java.lang.Object, OutT extends shapeless.HList> shapeless.ops.traversable$FromTraversable<shapeless.$colon$colon<OutH, OutT>> hlistFromTraversable(shapeless.ops.traversable$FromTraversable<OutT>, shapeless.Typeable<OutH>);
    descriptor: (Lshapeless/ops/traversable$FromTraversable;Lshapeless/Typeable;)Lshapeless/ops/traversable$FromTraversable;
    flags: (0x0001) ACC_PUBLIC
    Code:
      stack=4, locals=3, args_size=3
         0: new           #17                 // class shapeless/ops/traversable$FromTraversable$$anon$2
         3: dup
         4: aload_2
         5: aload_1
         6: invokespecial #44                 // Method shapeless/ops/traversable$FromTraversable$$anon$2."<init>":(Lshapeless/Typeable;Lshapeless/ops/traversable$FromTraversable;)V
         9: areturn
      LineNumberTable:
        line 46: 0
      LocalVariableTable:
        Start  Length  Slot  Name   Signature
            0      10     0  this   Lshapeless/ops/traversable$FromTraversable$;
            0      10     1   flt   Lshapeless/ops/traversable$FromTraversable;
            0      10     2    oc   Lshapeless/Typeable;
    Signature: #39                          // <OutH:Ljava/lang/Object;OutT::Lshapeless/HList;>(Lshapeless/ops/traversable$FromTraversable<TOutT;>;Lshapeless/Typeable<TOutH;>;)Lshapeless/ops/traversable$FromTraversable<Lshapeless/$colon$colon<TOutH;TOutT;>;>;
    MethodParameters:
      Name                           Flags
      flt                            final
      oc                             final

  private java.lang.Object writeReplace();
    descriptor: ()Ljava/lang/Object;
    flags: (0x0002) ACC_PRIVATE
    Code:
      stack=3, locals=1, args_size=1
         0: new           #49                 // class scala/runtime/ModuleSerializationProxy
         3: dup
         4: ldc           #2                  // class shapeless/ops/traversable$FromTraversable$
         6: invokespecial #52                 // Method scala/runtime/ModuleSerializationProxy."<init>":(Ljava/lang/Class;)V
         9: areturn
      LineNumberTable:
        line 35: 0
      LocalVariableTable:
        Start  Length  Slot  Name   Signature
            0      10     0  this   Lshapeless/ops/traversable$FromTraversable$;

  public shapeless.ops.traversable$FromTraversable$();
    descriptor: ()V
    flags: (0x0001) ACC_PUBLIC
    Code:
      stack=1, locals=1, args_size=1
         0: aload_0
         1: invokespecial #53                 // Method java/lang/Object."<init>":()V
         4: return
      LineNumberTable:
        line 58: 0
        line 35: 4
      LocalVariableTable:
        Start  Length  Slot  Name   Signature
            0       5     0  this   Lshapeless/ops/traversable$FromTraversable$;
}
InnerClasses:
  public static #12= #9 of #11;           // FromTraversable=class shapeless/ops/traversable$FromTraversable of class shapeless/ops/traversable
  public static #13= #2 of #11;           // FromTraversable$=class shapeless/ops/traversable$FromTraversable$ of class shapeless/ops/traversable
  public final #15;                       // class shapeless/ops/traversable$FromTraversable$$anon$1
  public final #17;                       // class shapeless/ops/traversable$FromTraversable$$anon$2
SourceFile: "traversables.scala"
  ScalaInlineInfo: length = 0x1D (unknown attribute)
   01 01 00 05 00 16 00 15 01 00 1B 00 1C 01 00 25
   00 26 01 00 21 00 22 01 00 2E 00 2F 01
  Scala: length = 0x0 (unknown attribute)

