Classfile /Users/mw/Projects/slang-braindump/.jar/jar8/assemble/slang-braindump/assemble/content/shapeless/ops/tuple$SplitRight$.class
  Last modified May 29, 2022; size 2137 bytes
  SHA-256 checksum 448aa328313016a14c8f9c2c5033878269c8d93fe57d4b513a239b35449c60fa
  Compiled from "tuples.scala"
public class shapeless.ops.tuple$SplitRight$ implements java.io.Serializable
  minor version: 0
  major version: 52
  flags: (0x0021) ACC_PUBLIC, ACC_SUPER
  this_class: #2                          // shapeless/ops/tuple$SplitRight$
  super_class: #4                         // java/lang/Object
  interfaces: 1, fields: 1, methods: 5, attributes: 4
Constant pool:
   #1 = Utf8               shapeless/ops/tuple$SplitRight$
   #2 = Class              #1             // shapeless/ops/tuple$SplitRight$
   #3 = Utf8               java/lang/Object
   #4 = Class              #3             // java/lang/Object
   #5 = Utf8               java/io/Serializable
   #6 = Class              #5             // java/io/Serializable
   #7 = Utf8               tuples.scala
   #8 = Utf8               shapeless/ops/hlist$SplitRight
   #9 = Class              #8             // shapeless/ops/hlist$SplitRight
  #10 = Utf8               shapeless/ops/hlist
  #11 = Class              #10            // shapeless/ops/hlist
  #12 = Utf8               SplitRight
  #13 = Utf8               shapeless/ops/hlist$Tupler
  #14 = Class              #13            // shapeless/ops/hlist$Tupler
  #15 = Utf8               Tupler
  #16 = Utf8               shapeless/ops/tuple$SplitRight
  #17 = Class              #16            // shapeless/ops/tuple$SplitRight
  #18 = Utf8               shapeless/ops/tuple
  #19 = Class              #18            // shapeless/ops/tuple
  #20 = Utf8               SplitRight$
  #21 = Utf8               shapeless/ops/tuple$SplitRight$$anon$22
  #22 = Class              #21            // shapeless/ops/tuple$SplitRight$$anon$22
  #23 = Utf8               MODULE$
  #24 = Utf8               Lshapeless/ops/tuple$SplitRight$;
  #25 = Utf8               <clinit>
  #26 = Utf8               ()V
  #27 = Utf8               <init>
  #28 = NameAndType        #27:#26        // "<init>":()V
  #29 = Methodref          #2.#28         // shapeless/ops/tuple$SplitRight$."<init>":()V
  #30 = NameAndType        #23:#24        // MODULE$:Lshapeless/ops/tuple$SplitRight$;
  #31 = Fieldref           #2.#30         // shapeless/ops/tuple$SplitRight$.MODULE$:Lshapeless/ops/tuple$SplitRight$;
  #32 = Utf8               apply
  #33 = Utf8               (Lshapeless/ops/tuple$SplitRight;)Lshapeless/ops/tuple$SplitRight;
  #34 = Utf8               <T:Ljava/lang/Object;U:Ljava/lang/Object;>(Lshapeless/ops/tuple$SplitRight<TT;TU;>;)Lshapeless/ops/tuple$SplitRight<TT;TU;>;
  #35 = Utf8               split
  #36 = Utf8               this
  #37 = Utf8               Lshapeless/ops/tuple$SplitRight;
  #38 = Utf8               tupleSplitRight
  #39 = Utf8               (Lshapeless/Generic;Lshapeless/ops/hlist$SplitRight;Lshapeless/ops/hlist$Tupler;Lshapeless/ops/hlist$Tupler;)Lshapeless/ops/tuple$SplitRight;
  #40 = Utf8               <T:Ljava/lang/Object;L::Lshapeless/HList;U:Ljava/lang/Object;LP::Lshapeless/HList;LS::Lshapeless/HList;>(Lshapeless/Generic<TT;>;Lshapeless/ops/hlist$SplitRight<TL;TU;>;Lshapeless/ops/hlist$Tupler<TLP;>;Lshapeless/ops/hlist$Tupler<TLS;>;)Lshapeless/ops/tuple$SplitRight<TT;TU;>;
  #41 = Utf8               gen
  #42 = Utf8               tpp
  #43 = Utf8               tps
  #44 = Utf8               (Lshapeless/ops/hlist$SplitRight;Lshapeless/Generic;Lshapeless/ops/hlist$Tupler;Lshapeless/ops/hlist$Tupler;)V
  #45 = NameAndType        #27:#44        // "<init>":(Lshapeless/ops/hlist$SplitRight;Lshapeless/Generic;Lshapeless/ops/hlist$Tupler;Lshapeless/ops/hlist$Tupler;)V
  #46 = Methodref          #22.#45        // shapeless/ops/tuple$SplitRight$$anon$22."<init>":(Lshapeless/ops/hlist$SplitRight;Lshapeless/Generic;Lshapeless/ops/hlist$Tupler;Lshapeless/ops/hlist$Tupler;)V
  #47 = Utf8               Lshapeless/Generic;
  #48 = Utf8               Lshapeless/ops/hlist$SplitRight;
  #49 = Utf8               Lshapeless/ops/hlist$Tupler;
  #50 = Utf8               writeReplace
  #51 = Utf8               ()Ljava/lang/Object;
  #52 = Utf8               scala/runtime/ModuleSerializationProxy
  #53 = Class              #52            // scala/runtime/ModuleSerializationProxy
  #54 = Utf8               (Ljava/lang/Class;)V
  #55 = NameAndType        #27:#54        // "<init>":(Ljava/lang/Class;)V
  #56 = Methodref          #53.#55        // scala/runtime/ModuleSerializationProxy."<init>":(Ljava/lang/Class;)V
  #57 = Methodref          #4.#28         // java/lang/Object."<init>":()V
  #58 = Utf8               Code
  #59 = Utf8               LineNumberTable
  #60 = Utf8               LocalVariableTable
  #61 = Utf8               Signature
  #62 = Utf8               MethodParameters
  #63 = Utf8               InnerClasses
  #64 = Utf8               SourceFile
  #65 = Utf8               ScalaInlineInfo
  #66 = Utf8               Scala
{
  public static final shapeless.ops.tuple$SplitRight$ MODULE$;
    descriptor: Lshapeless/ops/tuple$SplitRight$;
    flags: (0x0019) ACC_PUBLIC, ACC_STATIC, ACC_FINAL

  public static {};
    descriptor: ()V
    flags: (0x0009) ACC_PUBLIC, ACC_STATIC
    Code:
      stack=2, locals=0, args_size=0
         0: new           #2                  // class shapeless/ops/tuple$SplitRight$
         3: dup
         4: invokespecial #29                 // Method "<init>":()V
         7: putstatic     #31                 // Field MODULE$:Lshapeless/ops/tuple$SplitRight$;
        10: return
      LineNumberTable:
        line 501: 0

  public <T extends java.lang.Object, U extends java.lang.Object> shapeless.ops.tuple$SplitRight<T, U> apply(shapeless.ops.tuple$SplitRight<T, U>);
    descriptor: (Lshapeless/ops/tuple$SplitRight;)Lshapeless/ops/tuple$SplitRight;
    flags: (0x0001) ACC_PUBLIC
    Code:
      stack=1, locals=2, args_size=2
         0: aload_1
         1: areturn
      LineNumberTable:
        line 502: 0
      LocalVariableTable:
        Start  Length  Slot  Name   Signature
            0       2     0  this   Lshapeless/ops/tuple$SplitRight$;
            0       2     1 split   Lshapeless/ops/tuple$SplitRight;
    Signature: #34                          // <T:Ljava/lang/Object;U:Ljava/lang/Object;>(Lshapeless/ops/tuple$SplitRight<TT;TU;>;)Lshapeless/ops/tuple$SplitRight<TT;TU;>;
    MethodParameters:
      Name                           Flags
      split                          final

  public <T extends java.lang.Object, L extends shapeless.HList, U extends java.lang.Object, LP extends shapeless.HList, LS extends shapeless.HList> shapeless.ops.tuple$SplitRight<T, U> tupleSplitRight(shapeless.Generic<T>, shapeless.ops.hlist$SplitRight<L, U>, shapeless.ops.hlist$Tupler<LP>, shapeless.ops.hlist$Tupler<LS>);
    descriptor: (Lshapeless/Generic;Lshapeless/ops/hlist$SplitRight;Lshapeless/ops/hlist$Tupler;Lshapeless/ops/hlist$Tupler;)Lshapeless/ops/tuple$SplitRight;
    flags: (0x0001) ACC_PUBLIC
    Code:
      stack=6, locals=5, args_size=5
         0: new           #22                 // class shapeless/ops/tuple$SplitRight$$anon$22
         3: dup
         4: aload_2
         5: aload_1
         6: aload_3
         7: aload         4
         9: invokespecial #46                 // Method shapeless/ops/tuple$SplitRight$$anon$22."<init>":(Lshapeless/ops/hlist$SplitRight;Lshapeless/Generic;Lshapeless/ops/hlist$Tupler;Lshapeless/ops/hlist$Tupler;)V
        12: areturn
      LineNumberTable:
        line 513: 0
      LocalVariableTable:
        Start  Length  Slot  Name   Signature
            0      13     0  this   Lshapeless/ops/tuple$SplitRight$;
            0      13     1   gen   Lshapeless/Generic;
            0      13     2 split   Lshapeless/ops/hlist$SplitRight;
            0      13     3   tpp   Lshapeless/ops/hlist$Tupler;
            0      13     4   tps   Lshapeless/ops/hlist$Tupler;
    Signature: #40                          // <T:Ljava/lang/Object;L::Lshapeless/HList;U:Ljava/lang/Object;LP::Lshapeless/HList;LS::Lshapeless/HList;>(Lshapeless/Generic<TT;>;Lshapeless/ops/hlist$SplitRight<TL;TU;>;Lshapeless/ops/hlist$Tupler<TLP;>;Lshapeless/ops/hlist$Tupler<TLS;>;)Lshapeless/ops/tuple$SplitRight<TT;TU;>;
    MethodParameters:
      Name                           Flags
      gen                            final
      split                          final
      tpp                            final
      tps                            final

  private java.lang.Object writeReplace();
    descriptor: ()Ljava/lang/Object;
    flags: (0x0002) ACC_PRIVATE
    Code:
      stack=3, locals=1, args_size=1
         0: new           #53                 // class scala/runtime/ModuleSerializationProxy
         3: dup
         4: ldc           #2                  // class shapeless/ops/tuple$SplitRight$
         6: invokespecial #56                 // Method scala/runtime/ModuleSerializationProxy."<init>":(Ljava/lang/Class;)V
         9: areturn
      LineNumberTable:
        line 501: 0
      LocalVariableTable:
        Start  Length  Slot  Name   Signature
            0      10     0  this   Lshapeless/ops/tuple$SplitRight$;

  public shapeless.ops.tuple$SplitRight$();
    descriptor: ()V
    flags: (0x0001) ACC_PUBLIC
    Code:
      stack=1, locals=1, args_size=1
         0: aload_0
         1: invokespecial #57                 // Method java/lang/Object."<init>":()V
         4: return
      LineNumberTable:
        line 525: 0
        line 501: 4
      LocalVariableTable:
        Start  Length  Slot  Name   Signature
            0       5     0  this   Lshapeless/ops/tuple$SplitRight$;
}
InnerClasses:
  public static #12= #9 of #11;           // SplitRight=class shapeless/ops/hlist$SplitRight of class shapeless/ops/hlist
  public static #15= #14 of #11;          // Tupler=class shapeless/ops/hlist$Tupler of class shapeless/ops/hlist
  public static #12= #17 of #19;          // SplitRight=class shapeless/ops/tuple$SplitRight of class shapeless/ops/tuple
  public static #20= #2 of #19;           // SplitRight$=class shapeless/ops/tuple$SplitRight$ of class shapeless/ops/tuple
  public final #22;                       // class shapeless/ops/tuple$SplitRight$$anon$22
SourceFile: "tuples.scala"
  ScalaInlineInfo: length = 0x18 (unknown attribute)
   01 01 00 04 00 1B 00 1A 01 00 20 00 21 01 00 26
   00 27 01 00 32 00 33 01
  Scala: length = 0x0 (unknown attribute)

