Classfile /Users/mw/Projects/slang-braindump/.jar/jar8/assemble/slang-braindump/assemble/content/shapeless/ops/tuple$PaddedGrouper$.class
  Last modified May 29, 2022; size 2310 bytes
  SHA-256 checksum 61458acf37855849a90db2bd14e8d260f98e56036f29ab86a9f61fb5cade54a0
  Compiled from "tuples.scala"
public class shapeless.ops.tuple$PaddedGrouper$ implements java.io.Serializable
  minor version: 0
  major version: 52
  flags: (0x0021) ACC_PUBLIC, ACC_SUPER
  this_class: #2                          // shapeless/ops/tuple$PaddedGrouper$
  super_class: #4                         // java/lang/Object
  interfaces: 1, fields: 1, methods: 5, attributes: 4
Constant pool:
   #1 = Utf8               shapeless/ops/tuple$PaddedGrouper$
   #2 = Class              #1             // shapeless/ops/tuple$PaddedGrouper$
   #3 = Utf8               java/lang/Object
   #4 = Class              #3             // java/lang/Object
   #5 = Utf8               java/io/Serializable
   #6 = Class              #5             // java/io/Serializable
   #7 = Utf8               tuples.scala
   #8 = Utf8               shapeless/ops/hlist$PaddedGrouper
   #9 = Class              #8             // shapeless/ops/hlist$PaddedGrouper
  #10 = Utf8               shapeless/ops/hlist
  #11 = Class              #10            // shapeless/ops/hlist
  #12 = Utf8               PaddedGrouper
  #13 = Utf8               shapeless/ops/hlist$Tupler
  #14 = Class              #13            // shapeless/ops/hlist$Tupler
  #15 = Utf8               Tupler
  #16 = Utf8               shapeless/ops/tuple$PaddedGrouper
  #17 = Class              #16            // shapeless/ops/tuple$PaddedGrouper
  #18 = Utf8               shapeless/ops/tuple
  #19 = Class              #18            // shapeless/ops/tuple
  #20 = Utf8               PaddedGrouper$
  #21 = Utf8               shapeless/ops/tuple$PaddedGrouper$$anon$60
  #22 = Class              #21            // shapeless/ops/tuple$PaddedGrouper$$anon$60
  #23 = Utf8               MODULE$
  #24 = Utf8               Lshapeless/ops/tuple$PaddedGrouper$;
  #25 = Utf8               <clinit>
  #26 = Utf8               ()V
  #27 = Utf8               <init>
  #28 = NameAndType        #27:#26        // "<init>":()V
  #29 = Methodref          #2.#28         // shapeless/ops/tuple$PaddedGrouper$."<init>":()V
  #30 = NameAndType        #23:#24        // MODULE$:Lshapeless/ops/tuple$PaddedGrouper$;
  #31 = Fieldref           #2.#30         // shapeless/ops/tuple$PaddedGrouper$.MODULE$:Lshapeless/ops/tuple$PaddedGrouper$;
  #32 = Utf8               apply
  #33 = Utf8               (Lshapeless/ops/tuple$PaddedGrouper;)Lshapeless/ops/tuple$PaddedGrouper;
  #34 = Utf8               <T:Ljava/lang/Object;N::Lshapeless/Nat;Step::Lshapeless/Nat;Pad:Ljava/lang/Object;>(Lshapeless/ops/tuple$PaddedGrouper<TT;TN;TStep;TPad;>;)Lshapeless/ops/tuple$PaddedGrouper<TT;TN;TStep;TPad;>;
  #35 = Utf8               grouper
  #36 = Utf8               this
  #37 = Utf8               Lshapeless/ops/tuple$PaddedGrouper;
  #38 = Utf8               tuplePaddedGrouper
  #39 = Utf8               (Lshapeless/Generic;Lshapeless/Generic;Lshapeless/ops/hlist$PaddedGrouper;Lshapeless/ops/hlist$Tupler;)Lshapeless/ops/tuple$PaddedGrouper;
  #40 = Utf8               <Pad:Ljava/lang/Object;PadL::Lshapeless/HList;T:Ljava/lang/Object;N::Lshapeless/Nat;Step::Lshapeless/Nat;L::Lshapeless/HList;OutL::Lshapeless/HList;>(Lshapeless/Generic<TT;>;Lshapeless/Generic<TPad;>;Lshapeless/ops/hlist$PaddedGrouper<TL;TN;TStep;TPadL;>;Lshapeless/ops/hlist$Tupler<TOutL;>;)Lshapeless/ops/tuple$PaddedGrouper<TT;TN;TStep;TPad;>;
  #41 = Utf8               genL
  #42 = Utf8               genPad
  #43 = Utf8               tupler
  #44 = Utf8               (Lshapeless/ops/hlist$Tupler;Lshapeless/ops/hlist$PaddedGrouper;Lshapeless/Generic;Lshapeless/Generic;)V
  #45 = NameAndType        #27:#44        // "<init>":(Lshapeless/ops/hlist$Tupler;Lshapeless/ops/hlist$PaddedGrouper;Lshapeless/Generic;Lshapeless/Generic;)V
  #46 = Methodref          #22.#45        // shapeless/ops/tuple$PaddedGrouper$$anon$60."<init>":(Lshapeless/ops/hlist$Tupler;Lshapeless/ops/hlist$PaddedGrouper;Lshapeless/Generic;Lshapeless/Generic;)V
  #47 = Utf8               Lshapeless/Generic;
  #48 = Utf8               Lshapeless/ops/hlist$PaddedGrouper;
  #49 = Utf8               Lshapeless/ops/hlist$Tupler;
  #50 = Utf8               writeReplace
  #51 = Utf8               ()Ljava/lang/Object;
  #52 = Utf8               scala/runtime/ModuleSerializationProxy
  #53 = Class              #52            // scala/runtime/ModuleSerializationProxy
  #54 = Utf8               (Ljava/lang/Class;)V
  #55 = NameAndType        #27:#54        // "<init>":(Ljava/lang/Class;)V
  #56 = Methodref          #53.#55        // scala/runtime/ModuleSerializationProxy."<init>":(Ljava/lang/Class;)V
  #57 = Methodref          #4.#28         // java/lang/Object."<init>":()V
  #58 = Utf8               Code
  #59 = Utf8               LineNumberTable
  #60 = Utf8               LocalVariableTable
  #61 = Utf8               Signature
  #62 = Utf8               MethodParameters
  #63 = Utf8               InnerClasses
  #64 = Utf8               SourceFile
  #65 = Utf8               ScalaInlineInfo
  #66 = Utf8               Scala
{
  public static final shapeless.ops.tuple$PaddedGrouper$ MODULE$;
    descriptor: Lshapeless/ops/tuple$PaddedGrouper$;
    flags: (0x0019) ACC_PUBLIC, ACC_STATIC, ACC_FINAL

  public static {};
    descriptor: ()V
    flags: (0x0009) ACC_PUBLIC, ACC_STATIC
    Code:
      stack=2, locals=0, args_size=0
         0: new           #2                  // class shapeless/ops/tuple$PaddedGrouper$
         3: dup
         4: invokespecial #29                 // Method "<init>":()V
         7: putstatic     #31                 // Field MODULE$:Lshapeless/ops/tuple$PaddedGrouper$;
        10: return
      LineNumberTable:
        line 1292: 0

  public <T extends java.lang.Object, N extends shapeless.Nat, Step extends shapeless.Nat, Pad extends java.lang.Object> shapeless.ops.tuple$PaddedGrouper<T, N, Step, Pad> apply(shapeless.ops.tuple$PaddedGrouper<T, N, Step, Pad>);
    descriptor: (Lshapeless/ops/tuple$PaddedGrouper;)Lshapeless/ops/tuple$PaddedGrouper;
    flags: (0x0001) ACC_PUBLIC
    Code:
      stack=1, locals=2, args_size=2
         0: aload_1
         1: areturn
      LineNumberTable:
        line 1295: 0
      LocalVariableTable:
        Start  Length  Slot  Name   Signature
            0       2     0  this   Lshapeless/ops/tuple$PaddedGrouper$;
            0       2     1 grouper   Lshapeless/ops/tuple$PaddedGrouper;
    Signature: #34                          // <T:Ljava/lang/Object;N::Lshapeless/Nat;Step::Lshapeless/Nat;Pad:Ljava/lang/Object;>(Lshapeless/ops/tuple$PaddedGrouper<TT;TN;TStep;TPad;>;)Lshapeless/ops/tuple$PaddedGrouper<TT;TN;TStep;TPad;>;
    MethodParameters:
      Name                           Flags
      grouper                        final

  public <Pad extends java.lang.Object, PadL extends shapeless.HList, T extends java.lang.Object, N extends shapeless.Nat, Step extends shapeless.Nat, L extends shapeless.HList, OutL extends shapeless.HList> shapeless.ops.tuple$PaddedGrouper<T, N, Step, Pad> tuplePaddedGrouper(shapeless.Generic<T>, shapeless.Generic<Pad>, shapeless.ops.hlist$PaddedGrouper<L, N, Step, PadL>, shapeless.ops.hlist$Tupler<OutL>);
    descriptor: (Lshapeless/Generic;Lshapeless/Generic;Lshapeless/ops/hlist$PaddedGrouper;Lshapeless/ops/hlist$Tupler;)Lshapeless/ops/tuple$PaddedGrouper;
    flags: (0x0001) ACC_PUBLIC
    Code:
      stack=6, locals=5, args_size=5
         0: new           #22                 // class shapeless/ops/tuple$PaddedGrouper$$anon$60
         3: dup
         4: aload         4
         6: aload_3
         7: aload_1
         8: aload_2
         9: invokespecial #46                 // Method shapeless/ops/tuple$PaddedGrouper$$anon$60."<init>":(Lshapeless/ops/hlist$Tupler;Lshapeless/ops/hlist$PaddedGrouper;Lshapeless/Generic;Lshapeless/Generic;)V
        12: areturn
      LineNumberTable:
        line 1305: 0
      LocalVariableTable:
        Start  Length  Slot  Name   Signature
            0      13     0  this   Lshapeless/ops/tuple$PaddedGrouper$;
            0      13     1  genL   Lshapeless/Generic;
            0      13     2 genPad   Lshapeless/Generic;
            0      13     3 grouper   Lshapeless/ops/hlist$PaddedGrouper;
            0      13     4 tupler   Lshapeless/ops/hlist$Tupler;
    Signature: #40                          // <Pad:Ljava/lang/Object;PadL::Lshapeless/HList;T:Ljava/lang/Object;N::Lshapeless/Nat;Step::Lshapeless/Nat;L::Lshapeless/HList;OutL::Lshapeless/HList;>(Lshapeless/Generic<TT;>;Lshapeless/Generic<TPad;>;Lshapeless/ops/hlist$PaddedGrouper<TL;TN;TStep;TPadL;>;Lshapeless/ops/hlist$Tupler<TOutL;>;)Lshapeless/ops/tuple$PaddedGrouper<TT;TN;TStep;TPad;>;
    MethodParameters:
      Name                           Flags
      genL                           final
      genPad                         final
      grouper                        final
      tupler                         final

  private java.lang.Object writeReplace();
    descriptor: ()Ljava/lang/Object;
    flags: (0x0002) ACC_PRIVATE
    Code:
      stack=3, locals=1, args_size=1
         0: new           #53                 // class scala/runtime/ModuleSerializationProxy
         3: dup
         4: ldc           #2                  // class shapeless/ops/tuple$PaddedGrouper$
         6: invokespecial #56                 // Method scala/runtime/ModuleSerializationProxy."<init>":(Ljava/lang/Class;)V
         9: areturn
      LineNumberTable:
        line 1292: 0
      LocalVariableTable:
        Start  Length  Slot  Name   Signature
            0      10     0  this   Lshapeless/ops/tuple$PaddedGrouper$;

  public shapeless.ops.tuple$PaddedGrouper$();
    descriptor: ()V
    flags: (0x0001) ACC_PUBLIC
    Code:
      stack=1, locals=1, args_size=1
         0: aload_0
         1: invokespecial #57                 // Method java/lang/Object."<init>":()V
         4: return
      LineNumberTable:
        line 1319: 0
        line 1292: 4
      LocalVariableTable:
        Start  Length  Slot  Name   Signature
            0       5     0  this   Lshapeless/ops/tuple$PaddedGrouper$;
}
InnerClasses:
  public static #12= #9 of #11;           // PaddedGrouper=class shapeless/ops/hlist$PaddedGrouper of class shapeless/ops/hlist
  public static #15= #14 of #11;          // Tupler=class shapeless/ops/hlist$Tupler of class shapeless/ops/hlist
  public static #12= #17 of #19;          // PaddedGrouper=class shapeless/ops/tuple$PaddedGrouper of class shapeless/ops/tuple
  public static #20= #2 of #19;           // PaddedGrouper$=class shapeless/ops/tuple$PaddedGrouper$ of class shapeless/ops/tuple
  public final #22;                       // class shapeless/ops/tuple$PaddedGrouper$$anon$60
SourceFile: "tuples.scala"
  ScalaInlineInfo: length = 0x18 (unknown attribute)
   01 01 00 04 00 1B 00 1A 01 00 20 00 21 01 00 26
   00 27 01 00 32 00 33 01
  Scala: length = 0x0 (unknown attribute)

