Classfile /Users/mw/Projects/slang-braindump/.jar/jar8/assemble/slang-braindump/assemble/content/shapeless/ops/tuple$ReversePrepend$.class
  Last modified May 29, 2022; size 2168 bytes
  SHA-256 checksum 28ec1eac69242742f6de6731145565d87d65f5b47c70ea93569e1097590082c5
  Compiled from "tuples.scala"
public class shapeless.ops.tuple$ReversePrepend$ implements java.io.Serializable
  minor version: 0
  major version: 52
  flags: (0x0021) ACC_PUBLIC, ACC_SUPER
  this_class: #2                          // shapeless/ops/tuple$ReversePrepend$
  super_class: #4                         // java/lang/Object
  interfaces: 1, fields: 1, methods: 5, attributes: 4
Constant pool:
   #1 = Utf8               shapeless/ops/tuple$ReversePrepend$
   #2 = Class              #1             // shapeless/ops/tuple$ReversePrepend$
   #3 = Utf8               java/lang/Object
   #4 = Class              #3             // java/lang/Object
   #5 = Utf8               java/io/Serializable
   #6 = Class              #5             // java/io/Serializable
   #7 = Utf8               tuples.scala
   #8 = Utf8               shapeless/ops/hlist$ReversePrepend
   #9 = Class              #8             // shapeless/ops/hlist$ReversePrepend
  #10 = Utf8               shapeless/ops/hlist
  #11 = Class              #10            // shapeless/ops/hlist
  #12 = Utf8               ReversePrepend
  #13 = Utf8               shapeless/ops/hlist$Tupler
  #14 = Class              #13            // shapeless/ops/hlist$Tupler
  #15 = Utf8               Tupler
  #16 = Utf8               shapeless/ops/tuple$ReversePrepend
  #17 = Class              #16            // shapeless/ops/tuple$ReversePrepend
  #18 = Utf8               shapeless/ops/tuple
  #19 = Class              #18            // shapeless/ops/tuple
  #20 = Utf8               ReversePrepend$
  #21 = Utf8               shapeless/ops/tuple$ReversePrepend$$anon$3
  #22 = Class              #21            // shapeless/ops/tuple$ReversePrepend$$anon$3
  #23 = Utf8               MODULE$
  #24 = Utf8               Lshapeless/ops/tuple$ReversePrepend$;
  #25 = Utf8               <clinit>
  #26 = Utf8               ()V
  #27 = Utf8               <init>
  #28 = NameAndType        #27:#26        // "<init>":()V
  #29 = Methodref          #2.#28         // shapeless/ops/tuple$ReversePrepend$."<init>":()V
  #30 = NameAndType        #23:#24        // MODULE$:Lshapeless/ops/tuple$ReversePrepend$;
  #31 = Fieldref           #2.#30         // shapeless/ops/tuple$ReversePrepend$.MODULE$:Lshapeless/ops/tuple$ReversePrepend$;
  #32 = Utf8               apply
  #33 = Utf8               (Lshapeless/ops/tuple$ReversePrepend;)Lshapeless/ops/tuple$ReversePrepend;
  #34 = Utf8               <T:Ljava/lang/Object;U:Ljava/lang/Object;>(Lshapeless/ops/tuple$ReversePrepend<TT;TU;>;)Lshapeless/ops/tuple$ReversePrepend<TT;TU;>;
  #35 = Utf8               prepend
  #36 = Utf8               this
  #37 = Utf8               Lshapeless/ops/tuple$ReversePrepend;
  #38 = Utf8               (Lshapeless/Generic;Lshapeless/Generic;Lshapeless/ops/hlist$ReversePrepend;Lshapeless/ops/hlist$Tupler;)Lshapeless/ops/tuple$ReversePrepend;
  #39 = Utf8               <T:Ljava/lang/Object;L1::Lshapeless/HList;U:Ljava/lang/Object;L2::Lshapeless/HList;L3::Lshapeless/HList;>(Lshapeless/Generic<TT;>;Lshapeless/Generic<TU;>;Lshapeless/ops/hlist$ReversePrepend<TL1;TL2;>;Lshapeless/ops/hlist$Tupler<TL3;>;)Lshapeless/ops/tuple$ReversePrepend<TT;TU;>;
  #40 = Utf8               gent
  #41 = Utf8               genu
  #42 = Utf8               tp
  #43 = Utf8               (Lshapeless/ops/hlist$ReversePrepend;Lshapeless/Generic;Lshapeless/Generic;Lshapeless/ops/hlist$Tupler;)V
  #44 = NameAndType        #27:#43        // "<init>":(Lshapeless/ops/hlist$ReversePrepend;Lshapeless/Generic;Lshapeless/Generic;Lshapeless/ops/hlist$Tupler;)V
  #45 = Methodref          #22.#44        // shapeless/ops/tuple$ReversePrepend$$anon$3."<init>":(Lshapeless/ops/hlist$ReversePrepend;Lshapeless/Generic;Lshapeless/Generic;Lshapeless/ops/hlist$Tupler;)V
  #46 = Utf8               Lshapeless/Generic;
  #47 = Utf8               Lshapeless/ops/hlist$ReversePrepend;
  #48 = Utf8               Lshapeless/ops/hlist$Tupler;
  #49 = Utf8               writeReplace
  #50 = Utf8               ()Ljava/lang/Object;
  #51 = Utf8               scala/runtime/ModuleSerializationProxy
  #52 = Class              #51            // scala/runtime/ModuleSerializationProxy
  #53 = Utf8               (Ljava/lang/Class;)V
  #54 = NameAndType        #27:#53        // "<init>":(Ljava/lang/Class;)V
  #55 = Methodref          #52.#54        // scala/runtime/ModuleSerializationProxy."<init>":(Ljava/lang/Class;)V
  #56 = Methodref          #4.#28         // java/lang/Object."<init>":()V
  #57 = Utf8               Code
  #58 = Utf8               LineNumberTable
  #59 = Utf8               LocalVariableTable
  #60 = Utf8               Signature
  #61 = Utf8               MethodParameters
  #62 = Utf8               InnerClasses
  #63 = Utf8               SourceFile
  #64 = Utf8               ScalaInlineInfo
  #65 = Utf8               Scala
{
  public static final shapeless.ops.tuple$ReversePrepend$ MODULE$;
    descriptor: Lshapeless/ops/tuple$ReversePrepend$;
    flags: (0x0019) ACC_PUBLIC, ACC_STATIC, ACC_FINAL

  public static {};
    descriptor: ()V
    flags: (0x0009) ACC_PUBLIC, ACC_STATIC
    Code:
      stack=2, locals=0, args_size=0
         0: new           #2                  // class shapeless/ops/tuple$ReversePrepend$
         3: dup
         4: invokespecial #29                 // Method "<init>":()V
         7: putstatic     #31                 // Field MODULE$:Lshapeless/ops/tuple$ReversePrepend$;
        10: return
      LineNumberTable:
        line 80: 0

  public <T extends java.lang.Object, U extends java.lang.Object> shapeless.ops.tuple$ReversePrepend<T, U> apply(shapeless.ops.tuple$ReversePrepend<T, U>);
    descriptor: (Lshapeless/ops/tuple$ReversePrepend;)Lshapeless/ops/tuple$ReversePrepend;
    flags: (0x0001) ACC_PUBLIC
    Code:
      stack=1, locals=2, args_size=2
         0: aload_1
         1: areturn
      LineNumberTable:
        line 81: 0
      LocalVariableTable:
        Start  Length  Slot  Name   Signature
            0       2     0  this   Lshapeless/ops/tuple$ReversePrepend$;
            0       2     1 prepend   Lshapeless/ops/tuple$ReversePrepend;
    Signature: #34                          // <T:Ljava/lang/Object;U:Ljava/lang/Object;>(Lshapeless/ops/tuple$ReversePrepend<TT;TU;>;)Lshapeless/ops/tuple$ReversePrepend<TT;TU;>;
    MethodParameters:
      Name                           Flags
      prepend                        final

  public <T extends java.lang.Object, L1 extends shapeless.HList, U extends java.lang.Object, L2 extends shapeless.HList, L3 extends shapeless.HList> shapeless.ops.tuple$ReversePrepend<T, U> prepend(shapeless.Generic<T>, shapeless.Generic<U>, shapeless.ops.hlist$ReversePrepend<L1, L2>, shapeless.ops.hlist$Tupler<L3>);
    descriptor: (Lshapeless/Generic;Lshapeless/Generic;Lshapeless/ops/hlist$ReversePrepend;Lshapeless/ops/hlist$Tupler;)Lshapeless/ops/tuple$ReversePrepend;
    flags: (0x0001) ACC_PUBLIC
    Code:
      stack=6, locals=5, args_size=5
         0: new           #22                 // class shapeless/ops/tuple$ReversePrepend$$anon$3
         3: dup
         4: aload_3
         5: aload_1
         6: aload_2
         7: aload         4
         9: invokespecial #45                 // Method shapeless/ops/tuple$ReversePrepend$$anon$3."<init>":(Lshapeless/ops/hlist$ReversePrepend;Lshapeless/Generic;Lshapeless/Generic;Lshapeless/ops/hlist$Tupler;)V
        12: areturn
      LineNumberTable:
        line 87: 0
      LocalVariableTable:
        Start  Length  Slot  Name   Signature
            0      13     0  this   Lshapeless/ops/tuple$ReversePrepend$;
            0      13     1  gent   Lshapeless/Generic;
            0      13     2  genu   Lshapeless/Generic;
            0      13     3 prepend   Lshapeless/ops/hlist$ReversePrepend;
            0      13     4    tp   Lshapeless/ops/hlist$Tupler;
    Signature: #39                          // <T:Ljava/lang/Object;L1::Lshapeless/HList;U:Ljava/lang/Object;L2::Lshapeless/HList;L3::Lshapeless/HList;>(Lshapeless/Generic<TT;>;Lshapeless/Generic<TU;>;Lshapeless/ops/hlist$ReversePrepend<TL1;TL2;>;Lshapeless/ops/hlist$Tupler<TL3;>;)Lshapeless/ops/tuple$ReversePrepend<TT;TU;>;
    MethodParameters:
      Name                           Flags
      gent                           final
      genu                           final
      prepend                        final
      tp                             final

  private java.lang.Object writeReplace();
    descriptor: ()Ljava/lang/Object;
    flags: (0x0002) ACC_PRIVATE
    Code:
      stack=3, locals=1, args_size=1
         0: new           #52                 // class scala/runtime/ModuleSerializationProxy
         3: dup
         4: ldc           #2                  // class shapeless/ops/tuple$ReversePrepend$
         6: invokespecial #55                 // Method scala/runtime/ModuleSerializationProxy."<init>":(Ljava/lang/Class;)V
         9: areturn
      LineNumberTable:
        line 80: 0
      LocalVariableTable:
        Start  Length  Slot  Name   Signature
            0      10     0  this   Lshapeless/ops/tuple$ReversePrepend$;

  public shapeless.ops.tuple$ReversePrepend$();
    descriptor: ()V
    flags: (0x0001) ACC_PUBLIC
    Code:
      stack=1, locals=1, args_size=1
         0: aload_0
         1: invokespecial #56                 // Method java/lang/Object."<init>":()V
         4: return
      LineNumberTable:
        line 99: 0
        line 80: 4
      LocalVariableTable:
        Start  Length  Slot  Name   Signature
            0       5     0  this   Lshapeless/ops/tuple$ReversePrepend$;
}
InnerClasses:
  public static #12= #9 of #11;           // ReversePrepend=class shapeless/ops/hlist$ReversePrepend of class shapeless/ops/hlist
  public static #15= #14 of #11;          // Tupler=class shapeless/ops/hlist$Tupler of class shapeless/ops/hlist
  public static #12= #17 of #19;          // ReversePrepend=class shapeless/ops/tuple$ReversePrepend of class shapeless/ops/tuple
  public static #20= #2 of #19;           // ReversePrepend$=class shapeless/ops/tuple$ReversePrepend$ of class shapeless/ops/tuple
  public final #22;                       // class shapeless/ops/tuple$ReversePrepend$$anon$3
SourceFile: "tuples.scala"
  ScalaInlineInfo: length = 0x18 (unknown attribute)
   01 01 00 04 00 1B 00 1A 01 00 20 00 21 01 00 23
   00 26 01 00 31 00 32 01
  Scala: length = 0x0 (unknown attribute)

