Classfile /Users/mw/Projects/slang-braindump/.jar/jar8/assemble/slang-braindump/assemble/content/shapeless/ops/TuplerInstances.class
  Last modified May 29, 2022; size 28833 bytes
  SHA-256 checksum 56d8def1f40f17671e4c1431a1e91fc04ddf3de055804613304b9a4b29863480
  Compiled from "tupler.scala"
public interface shapeless.ops.TuplerInstances
  minor version: 0
  major version: 52
  flags: (0x0601) ACC_PUBLIC, ACC_INTERFACE, ACC_ABSTRACT
  this_class: #2                          // shapeless/ops/TuplerInstances
  super_class: #4                         // java/lang/Object
  interfaces: 0, fields: 0, methods: 45, attributes: 5
Constant pool:
    #1 = Utf8               shapeless/ops/TuplerInstances
    #2 = Class              #1            // shapeless/ops/TuplerInstances
    #3 = Utf8               java/lang/Object
    #4 = Class              #3            // java/lang/Object
    #5 = Utf8               tupler.scala
    #6 = Utf8               Lscala/reflect/ScalaSignature;
    #7 = Utf8               bytes
    #8 = Utf8               \u0006\u0005\u001dMhaB\r\u001b!\u0003\r\ta\b\u0005\u0006M\u0001!\taJ\u0003\u0005W\u0001\u0001A\u0006C\u0003N\u0001\u0011\ra\nC\u0003_\u0001\u0011\rq\fC\u0003m\u0001\u0011\rQ\u000eC\u0003~\u0001\u0011\ra\u0010C\u0004\u0002$\u0001!\u0019!!\n\t\u000f\u0005E\u0003\u0001b\u0001\u0002T!9\u0011Q\u0011\u0001\u0005\u0004\u0005\u001d\u0005bBA`\u0001\u0011\r\u0011\u0011\u0019\u0005\b\u0003\u007f\u0004A1\u0001B\u0001\u0011\u001d\u0011)\u0005\u0001C\u0002\u0005\u000fBqA!%\u0001\t\u0007\u0011\u0019\nC\u0004\u0003d\u0002!\u0019A!:\t\u000f\re\u0002\u0001b\u0001\u0004<!91q\u0013\u0001\u0005\u0004\re\u0005bBB~\u0001\u0011\r1Q \u0005\b\tK\u0002A1\u0001C4\u0011\u001d!)\u000e\u0001C\u0002\t/Dq!b\u0013\u0001\t\u0007)i\u0005C\u0004\u0006H\u0002!\u0019!\"3\t\u000f\u0019%\u0003\u0001b\u0001\u0007L!9a\u0011\u001b\u0001\u0005\u0004\u0019M\u0007bBD0\u0001\u0011\rq\u0011\r\u0002\u0010)V\u0004H.\u001a:J]N$\u0018M\\2fg*\u00111\u0004H\u0001\u0004_B\u001c(\"A\u000f\u0002\u0013MD\u0017\r]3mKN\u001c8\u0001A\n\u0003\u0001\u0001\u0002\"!\t\u0013\u000e\u0003\tR\u0011aI\u0001\u0006g\u000e\fG.Y\u0005\u0003K\t\u0012a!\u00118z%\u00164\u0017A\u0002\u0013j]&$H\u0005F\u0001)!\t\t\u0013&\u0003\u0002+E\t!QK\\5u\u0005\r\tU\u000f_\u000b\u0004[i:%C\u0001\u00181\r\u0011y\u0003\u0001A\u0017\u0003\u0019q\u0012XMZ5oK6,g\u000e\u001e \u0011\u0007E*\u0004H\u0004\u00023g5\t!$\u0003\u000255\u0005)\u0001\u000e\\5ti&\u0011ag\u000e\u0002\u0007)V\u0004H.\u001a:\u000b\u0005QR\u0002CA\u001d;\u0019\u0001!Qa\u000f\u0002C\u0002q\u0012\u0011\u0001T\t\u0003{\u0001\u0003\"!\t \n\u0005}\u0012#a\u0002(pi\"Lgn\u001a\t\u0003\u0003\nk\u0011\u0001H\u0005\u0003\u0007r\u0011Q\u0001\u0013\'jgR,A!\u0012\u0018!\r\n\u0019q*\u001e;\u0011\u0005e:E!\u0002%\u0003\u0005\u0004I%\u0001B(viB\n\"!\u0010&\u0011\u0005\u0005Z\u0015B\u0001\'#\u0005\r\te._\u0001\rQ2L7\u000f\u001e+va2,\'/M\u000b\u0003\u001fZ+\u0012\u0001\u0015\t\u0005#\n\u00116,D\u0001\u0001!\u0011\t5+\u0016-\n\u0005Qc\"\u0001\u0004\u0013d_2|g\u000eJ2pY>t\u0007CA\u001dW\t\u001596A1\u0001J\u0005\u0005\t\u0005CA!Z\u0013\tQFD\u0001\u0003I\u001d&d\u0007cA\u0011]+&\u0011QL\t\u0002\u0007)V\u0004H.Z\u0019\u0002\u0019!d\u0017n\u001d;UkBdWM\u001d\u001a\u0016\u0007\u0001$w-F\u0001b!\u0011\t&AY5\u0011\t\u0005\u001b6-\u001a\t\u0003s\u0011$Qa\u0016\u0003C\u0002%\u0003B!Q*g1B\u0011\u0011h\u001a\u0003\u0006Q\u0012\u0011\r!\u0013\u0002\u0002\u0005B!\u0011E[2g\u0013\tY\'E\u0001\u0004UkBdWMM\u0001\rQ2L7\u000f\u001e+va2,\'oM\u000b\u0005]J,\b0F\u0001p!\u0011\t&\u0001\u001d>\u0011\t\u0005\u001b\u0016o\u001d\t\u0003sI$QaV\u0003C\u0002%\u0003B!Q*umB\u0011\u0011(\u001e\u0003\u0006Q\u0016\u0011\r!\u0013\t\u0005\u0003N;\b\f\u0005\u0002:q\u0012)\u00110\u0002b\u0001\u0013\n\t1\tE\u0003\"wF$x/\u0003\u0002}E\t1A+\u001e9mKN\nA\u0002\u001b7jgR$V\u000f\u001d7feR*\u0012b`A\u0004\u0003\u001b\t\u0019\"!\u0007\u0016\u0005\u0005\u0005\u0001CB)\u0003\u0003\u0007\ti\u0002\u0005\u0004B\'\u0006\u0015\u0011\u0011\u0002\t\u0004s\u0005\u001dA!B,\u0007\u0005\u0004I\u0005CB!T\u0003\u0017\ty\u0001E\u0002:\u0003\u001b!Q\u0001\u001b\u0004C\u0002%\u0003b!Q*\u0002\u0012\u0005U\u0001cA\u001d\u0002\u0014\u0011)\u0011P\u0002b\u0001\u0013B)\u0011iUA\f1B\u0019\u0011(!\u0007\u0005\r\u0005maA1\u0001J\u0005\u0005!\u0005cC\u0011\u0002 \u0005\u0015\u00111BA\t\u0003/I1!!\t#\u0005\u0019!V\u000f\u001d7fi\u0005a\u0001\u000e\\5tiR+\b\u000f\\3skUa\u0011qEA\u0018\u0003k\tY$!\u0011\u0002HU\u0011\u0011\u0011\u0006\t\u0007#\n\tY#a\u0013\u0011\r\u0005\u001b\u0016QFA\u0019!\rI\u0014q\u0006\u0003\u0006/\u001e\u0011\r!\u0013\t\u0007\u0003N\u000b\u0019$a\u000e\u0011\u0007e\n)\u0004B\u0003i\u000f\t\u0007\u0011\n\u0005\u0004B\'\u0006e\u0012Q\b\t\u0004s\u0005mB!B=\b\u0005\u0004I\u0005CB!T\u0003\u007f\t\u0019\u0005E\u0002:\u0003\u0003\"a!a\u0007\b\u0005\u0004I\u0005#B!T\u0003\u000bB\u0006cA\u001d\u0002H\u00111\u0011\u0011J\u0004C\u0002%\u0013\u0011!\u0012\t\u000eC\u00055\u0013QFA\u001a\u0003s\ty$!\u0012\n\u0007\u0005=#E\u0001\u0004UkBdW-N\u0001\rQ2L7\u000f\u001e+va2,\'ON\u000b\u000f\u0003+\ni&a\u0019\u0002j\u0005=\u0014QOA>+\t\t9\u0006\u0005\u0004R\u0005\u0005e\u0013q\u0010\t\u0007\u0003N\u000bY&a\u0018\u0011\u0007e\ni\u0006B\u0003X\u0011\t\u0007\u0011\n\u0005\u0004B\'\u0006\u0005\u0014Q\r\t\u0004s\u0005\rD!\u00025\t\u0005\u0004I\u0005CB!T\u0003O\nY\u0007E\u0002:\u0003S\"Q!\u001f\u0005C\u0002%\u0003b!Q*\u0002n\u0005E\u0004cA\u001d\u0002p\u00111\u00111\u0004\u0005C\u0002%\u0003b!Q*\u0002t\u0005]\u0004cA\u001d\u0002v\u00111\u0011\u0011\n\u0005C\u0002%\u0003R!Q*\u0002za\u00032!OA>\t\u0019\ti\b\u0003b\u0001\u0013\n\ta\tE\b\"\u0003\u0003\u000bY&!\u0019\u0002h\u00055\u00141OA=\u0013\r\t\u0019I\t\u0002\u0007)V\u0004H.\u001a\u001c\u0002\u0019!d\u0017n\u001d;UkBdWM]\u001c\u0016!\u0005%\u0015\u0011SAL\u0003;\u000b\u0019+!+\u00020\u0006UVCAAF!\u0019\t&!!$\u0002:B1\u0011iUAH\u0003\'\u00032!OAI\t\u00159\u0016B1\u0001J!\u0019\t5+!&\u0002\u001aB\u0019\u0011(a&\u0005\u000b!L!\u0019A%\u0011\r\u0005\u001b\u00161TAP!\rI\u0014Q\u0014\u0003\u0006s&\u0011\r!\u0013\t\u0007\u0003N\u000b\t+!*\u0011\u0007e\n\u0019\u000b\u0002\u0004\u0002\u001c%\u0011\r!\u0013\t\u0007\u0003N\u000b9+a+\u0011\u0007e\nI\u000b\u0002\u0004\u0002J%\u0011\r!\u0013\t\u0007\u0003N\u000bi+!-\u0011\u0007e\ny\u000b\u0002\u0004\u0002~%\u0011\r!\u0013\t\u0006\u0003N\u000b\u0019\f\u0017\t\u0004s\u0005UFABA\\\u0013\t\u0007\u0011JA\u0001H!E\t\u00131XAH\u0003+\u000bY*!)\u0002(\u00065\u00161W\u0005\u0004\u0003{\u0013#A\u0002+va2,w\'\u0001\u0007iY&\u001cH\u000fV;qY\u0016\u0014\b(\u0006\n\u0002D\u0006-\u0017\u0011[Al\u0003;\f\u0019/!;\u0002p\u0006UXCAAc!\u0019\t&!a2\u0002zB1\u0011iUAe\u0003\u001b\u00042!OAf\t\u00159&B1\u0001J!\u0019\t5+a4\u0002TB\u0019\u0011(!5\u0005\u000b!T!\u0019A%\u0011\r\u0005\u001b\u0016Q[Am!\rI\u0014q\u001b\u0003\u0006s*\u0011\r!\u0013\t\u0007\u0003N\u000bY.a8\u0011\u0007e\ni\u000e\u0002\u0004\u0002\u001c)\u0011\r!\u0013\t\u0007\u0003N\u000b\t/!:\u0011\u0007e\n\u0019\u000f\u0002\u0004\u0002J)\u0011\r!\u0013\t\u0007\u0003N\u000b9/a;\u0011\u0007e\nI\u000f\u0002\u0004\u0002~)\u0011\r!\u0013\t\u0007\u0003N\u000bi/!=\u0011\u0007e\ny\u000f\u0002\u0004\u00028*\u0011\r!\u0013\t\u0006\u0003N\u000b\u0019\u0010\u0017\t\u0004s\u0005UHABA|\u0015\t\u0007\u0011JA\u0001I!M\t\u00131`Ae\u0003\u001f\f).a7\u0002b\u0006\u001d\u0018Q^Az\u0013\r\tiP\t\u0002\u0007)V\u0004H.\u001a\u001d\u0002\u0019!d\u0017n\u001d;UkBdWM]\u001d\u0016)\t\r!1\u0002B\t\u0005/\u0011iBa\t\u0003*\t=\"Q\u0007B\u001e+\t\u0011)\u0001\u0005\u0004R\u0005\t\u001d!q\b\t\u0007\u0003N\u0013IA!\u0004\u0011\u0007e\u0012Y\u0001B\u0003X\u0017\t\u0007\u0011\n\u0005\u0004B\'\n=!1\u0003\t\u0004s\tEA!\u00025\f\u0005\u0004I\u0005CB!T\u0005+\u0011I\u0002E\u0002:\u0005/!Q!_\u0006C\u0002%\u0003b!Q*\u0003\u001c\t}\u0001cA\u001d\u0003\u001e\u00111\u00111D\u0006C\u0002%\u0003b!Q*\u0003\"\t\u0015\u0002cA\u001d\u0003$\u00111\u0011\u0011J\u0006C\u0002%\u0003b!Q*\u0003(\t-\u0002cA\u001d\u0003*\u00111\u0011QP\u0006C\u0002%\u0003b!Q*\u0003.\tE\u0002cA\u001d\u00030\u00111\u0011qW\u0006C\u0002%\u0003b!Q*\u00034\t]\u0002cA\u001d\u00036\u00111\u0011q_\u0006C\u0002%\u0003R!Q*\u0003:a\u00032!\u000fB\u001e\t\u0019\u0011id\u0003b\u0001\u0013\n\t\u0011\nE\u000b\"\u0005\u0003\u0012IAa\u0004\u0003\u0016\tm!\u0011\u0005B\u0014\u0005[\u0011\u0019D!\u000f\n\u0007\t\r#E\u0001\u0004UkBdW-O\u0001\u000eQ2L7\u000f\u001e+va2,\'/\r\u0019\u0016-\t%#\u0011\u000bB,\u0005;\u0012\u0019G!\u001b\u0003p\tU$1\u0010BA\u0005\u000f+\"Aa\u0013\u0011\rE\u0013!Q\nBF!\u0019\t5Ka\u0014\u0003TA\u0019\u0011H!\u0015\u0005\u000b]c!\u0019A%\u0011\r\u0005\u001b&Q\u000bB-!\rI$q\u000b\u0003\u0006Q2\u0011\r!\u0013\t\u0007\u0003N\u0013YFa\u0018\u0011\u0007e\u0012i\u0006B\u0003z\u0019\t\u0007\u0011\n\u0005\u0004B\'\n\u0005$Q\r\t\u0004s\t\rDABA\u000e\u0019\t\u0007\u0011\n\u0005\u0004B\'\n\u001d$1\u000e\t\u0004s\t%DABA%\u0019\t\u0007\u0011\n\u0005\u0004B\'\n5$\u0011\u000f\t\u0004s\t=DABA?\u0019\t\u0007\u0011\n\u0005\u0004B\'\nM$q\u000f\t\u0004s\tUDABA\\\u0019\t\u0007\u0011\n\u0005\u0004B\'\ne$Q\u0010\t\u0004s\tmDABA|\u0019\t\u0007\u0011\n\u0005\u0004B\'\n}$1\u0011\t\u0004s\t\u0005EA\u0002B\u001f\u0019\t\u0007\u0011\nE\u0003B\'\n\u0015\u0005\fE\u0002:\u0005\u000f#aA!#\r\u0005\u0004I%!\u0001&\u0011/\u0005\u0012iIa\u0014\u0003V\tm#\u0011\rB4\u0005[\u0012\u0019H!\u001f\u0003\u0000\t\u0015\u0015b\u0001BHE\t9A+\u001e9mKF\u0002\u0014!\u00045mSN$H+\u001e9mKJ\f\u0014\'\u0006\r\u0003\u0016\nu%1\u0015BU\u0005_\u0013)La/\u0003B\n\u001d\'Q\u001aBj\u00053,\"Aa&\u0011\rE\u0013!\u0011\u0014Bo!\u0019\t5Ka\'\u0003 B\u0019\u0011H!(\u0005\u000b]k!\u0019A%\u0011\r\u0005\u001b&\u0011\u0015BS!\rI$1\u0015\u0003\u0006Q6\u0011\r!\u0013\t\u0007\u0003N\u00139Ka+\u0011\u0007e\u0012I\u000bB\u0003z\u001b\t\u0007\u0011\n\u0005\u0004B\'\n5&\u0011\u0017\t\u0004s\t=FABA\u000e\u001b\t\u0007\u0011\n\u0005\u0004B\'\nM&q\u0017\t\u0004s\tUFABA%\u001b\t\u0007\u0011\n\u0005\u0004B\'\ne&Q\u0018\t\u0004s\tmFABA?\u001b\t\u0007\u0011\n\u0005\u0004B\'\n}&1\u0019\t\u0004s\t\u0005GABA\\\u001b\t\u0007\u0011\n\u0005\u0004B\'\n\u0015\'\u0011\u001a\t\u0004s\t\u001dGABA|\u001b\t\u0007\u0011\n\u0005\u0004B\'\n-\'q\u001a\t\u0004s\t5GA\u0002B\u001f\u001b\t\u0007\u0011\n\u0005\u0004B\'\nE\'Q\u001b\t\u0004s\tMGA\u0002BE\u001b\t\u0007\u0011\nE\u0003B\'\n]\u0007\fE\u0002:\u00053$aAa7\u000e\u0005\u0004I%!A&\u00113\u0005\u0012yNa\'\u0003\"\n\u001d&Q\u0016BZ\u0005s\u0013yL!2\u0003L\nE\'q[\u0005\u0004\u0005C\u0014#a\u0002+va2,\u0017\'M\u0001\u000eQ2L7\u000f\u001e+va2,\'/\r\u001a\u00165\t\u001d(q\u001eB{\u0005w\u001c\taa\u0002\u0004\u000e\rM1\u0011DB\u0010\u0007K\u0019Yc!\r\u0016\u0005\t%\bCB)\u0003\u0005W\u001c\u0019\u0004\u0005\u0004B\'\n5(\u0011\u001f\t\u0004s\t=H!B,\u000f\u0005\u0004I\u0005CB!T\u0005g\u00149\u0010E\u0002:\u0005k$Q\u0001\u001b\bC\u0002%\u0003b!Q*\u0003z\nu\bcA\u001d\u0003|\u0012)\u0011P\u0004b\u0001\u0013B1\u0011i\u0015B\u0000\u0007\u0007\u00012!OB\u0001\t\u0019\tYB\u0004b\u0001\u0013B1\u0011iUB\u0003\u0007\u0013\u00012!OB\u0004\t\u0019\tIE\u0004b\u0001\u0013B1\u0011iUB\u0006\u0007\u001f\u00012!OB\u0007\t\u0019\tiH\u0004b\u0001\u0013B1\u0011iUB\t\u0007+\u00012!OB\n\t\u0019\t9L\u0004b\u0001\u0013B1\u0011iUB\f\u00077\u00012!OB\r\t\u0019\t9P\u0004b\u0001\u0013B1\u0011iUB\u000f\u0007C\u00012!OB\u0010\t\u0019\u0011iD\u0004b\u0001\u0013B1\u0011iUB\u0012\u0007O\u00012!OB\u0013\t\u0019\u0011II\u0004b\u0001\u0013B1\u0011iUB\u0015\u0007[\u00012!OB\u0016\t\u0019\u0011YN\u0004b\u0001\u0013B)\u0011iUB\u00181B\u0019\u0011h!\r\u0005\u000bmr!\u0019A%\u00117\u0005\u001a)D!<\u0003t\ne(q`B\u0003\u0007\u0017\u0019\tba\u0006\u0004\u001e\r\r2\u0011FB\u0018\u0013\r\u00199D\t\u0002\b)V\u0004H.Z\u00193\u00035AG.[:u)V\u0004H.\u001a:2gUa2QHB#\u0007\u0017\u001a\tfa\u0016\u0004^\r\r4\u0011NB8\u0007k\u001aYh!!\u0004\b\u000e5UCAB !\u0019\t&a!\u0011\u0004\u0012B1\u0011iUB\"\u0007\u000f\u00022!OB#\t\u00159vB1\u0001J!\u0019\t5k!\u0013\u0004NA\u0019\u0011ha\u0013\u0005\u000b!|!\u0019A%\u0011\r\u0005\u001b6qJB*!\rI4\u0011\u000b\u0003\u0006s>\u0011\r!\u0013\t\u0007\u0003N\u001b)f!\u0017\u0011\u0007e\u001a9\u0006\u0002\u0004\u0002\u001c=\u0011\r!\u0013\t\u0007\u0003N\u001bYfa\u0018\u0011\u0007e\u001ai\u0006\u0002\u0004\u0002J=\u0011\r!\u0013\t\u0007\u0003N\u001b\tg!\u001a\u0011\u0007e\u001a\u0019\u0007\u0002\u0004\u0002~=\u0011\r!\u0013\t\u0007\u0003N\u001b9ga\u001b\u0011\u0007e\u001aI\u0007\u0002\u0004\u00028>\u0011\r!\u0013\t\u0007\u0003N\u001big!\u001d\u0011\u0007e\u001ay\u0007\u0002\u0004\u0002x>\u0011\r!\u0013\t\u0007\u0003N\u001b\u0019ha\u001e\u0011\u0007e\u001a)\b\u0002\u0004\u0003>=\u0011\r!\u0013\t\u0007\u0003N\u001bIh! \u0011\u0007e\u001aY\b\u0002\u0004\u0003\n>\u0011\r!\u0013\t\u0007\u0003N\u001byha!\u0011\u0007e\u001a\t\t\u0002\u0004\u0003\\>\u0011\r!\u0013\t\u0007\u0003N\u001b)i!#\u0011\u0007e\u001a9\tB\u0003<\u001f\t\u0007\u0011\nE\u0003B\'\u000e-\u0005\fE\u0002:\u0007\u001b#aaa$\u0010\u0005\u0004I%!A\'\u0011;\u0005\u001a\u0019ja\u0011\u0004J\r=3QKB.\u0007C\u001a9g!\u001c\u0004t\re4qPBC\u0007\u0017K1a!&#\u0005\u001d!V\u000f\u001d7fcM\nQ\u0002\u001b7jgR$V\u000f\u001d7feF\"TCHBN\u0007G\u001bIka,\u00046\u000em6\u0011YBd\u0007\u001b\u001c\u0019n!7\u0004`\u000e\u001581^By+\t\u0019i\n\u0005\u0004R\u0005\r}5Q\u001f\t\u0007\u0003N\u001b\tk!*\u0011\u0007e\u001a\u0019\u000bB\u0003X!\t\u0007\u0011\n\u0005\u0004B\'\u000e\u001d61\u0016\t\u0004s\r%F!\u00025\u0011\u0005\u0004I\u0005CB!T\u0007[\u001b\t\fE\u0002:\u0007_#Q!\u001f\tC\u0002%\u0003b!Q*\u00044\u000e]\u0006cA\u001d\u00046\u00121\u00111\u0004\tC\u0002%\u0003b!Q*\u0004:\u000eu\u0006cA\u001d\u0004<\u00121\u0011\u0011\n\tC\u0002%\u0003b!Q*\u0004@\u000e\r\u0007cA\u001d\u0004B\u00121\u0011Q\u0010\tC\u0002%\u0003b!Q*\u0004F\u000e%\u0007cA\u001d\u0004H\u00121\u0011q\u0017\tC\u0002%\u0003b!Q*\u0004L\u000e=\u0007cA\u001d\u0004N\u00121\u0011q\u001f\tC\u0002%\u0003b!Q*\u0004R\u000eU\u0007cA\u001d\u0004T\u00121!Q\b\tC\u0002%\u0003b!Q*\u0004X\u000em\u0007cA\u001d\u0004Z\u00121!\u0011\u0012\tC\u0002%\u0003b!Q*\u0004^\u000e\u0005\bcA\u001d\u0004`\u00121!1\u001c\tC\u0002%\u0003b!Q*\u0004d\u000e\u001d\bcA\u001d\u0004f\u0012)1\b\u0005b\u0001\u0013B1\u0011iUBu\u0007[\u00042!OBv\t\u0019\u0019y\t\u0005b\u0001\u0013B)\u0011iUBx1B\u0019\u0011h!=\u0005\r\rM\bC1\u0001J\u0005\u0005q\u0005cH\u0011\u0004x\u000e\u00056qUBW\u0007g\u001bIla0\u0004F\u000e-7\u0011[Bl\u0007;\u001c\u0019o!;\u0004p&\u00191\u0011 \u0012\u0003\u000fQ+\b\u000f\\32i\u0005i\u0001\u000e\\5tiR+\b\u000f\\3scU*\u0002ea@\u0005\b\u00115A1\u0003C\r\t?!)\u0003b\u000b\u00052\u0011]BQ\bC\"\t\u0013\"y\u0005\"\u0016\u0005\\U\u0011A\u0011\u0001\t\u0007#\n!\u0019\u0001b\u0018\u0011\r\u0005\u001bFQ\u0001C\u0005!\rIDq\u0001\u0003\u0006/F\u0011\r!\u0013\t\u0007\u0003N#Y\u0001b\u0004\u0011\u0007e\"i\u0001B\u0003i#\t\u0007\u0011\n\u0005\u0004B\'\u0012EAQ\u0003\t\u0004s\u0011MA!B=\u0012\u0005\u0004I\u0005CB!T\t/!Y\u0002E\u0002:\t3!a!a\u0007\u0012\u0005\u0004I\u0005CB!T\t;!\t\u0003E\u0002:\t?!a!!\u0013\u0012\u0005\u0004I\u0005CB!T\tG!9\u0003E\u0002:\tK!a!! \u0012\u0005\u0004I\u0005CB!T\tS!i\u0003E\u0002:\tW!a!a.\u0012\u0005\u0004I\u0005CB!T\t_!\u0019\u0004E\u0002:\tc!a!a>\u0012\u0005\u0004I\u0005CB!T\tk!I\u0004E\u0002:\to!aA!\u0010\u0012\u0005\u0004I\u0005CB!T\tw!y\u0004E\u0002:\t{!aA!#\u0012\u0005\u0004I\u0005CB!T\t\u0003\")\u0005E\u0002:\t\u0007\"aAa7\u0012\u0005\u0004I\u0005CB!T\t\u000f\"Y\u0005E\u0002:\t\u0013\"QaO\tC\u0002%\u0003b!Q*\u0005N\u0011E\u0003cA\u001d\u0005P\u001111qR\tC\u0002%\u0003b!Q*\u0005T\u0011]\u0003cA\u001d\u0005V\u0011111_\tC\u0002%\u0003R!Q*\u0005Za\u00032!\u000fC.\t\u0019!i&\u0005b\u0001\u0013\n\tq\nE\u0011\"\tC\")\u0001b\u0003\u0005\u0012\u0011]AQ\u0004C\u0012\tS!y\u0003\"\u000e\u0005<\u0011\u0005Cq\tC\'\t\'\"I&C\u0002\u0005d\t\u0012q\u0001V;qY\u0016\fT\'A\u0007iY&\u001cH\u000fV;qY\u0016\u0014\u0018GN\u000b#\tS\"\t\bb\u001e\u0005~\u0011\rE\u0011\u0012CH\t+#Y\n\")\u0005(\u00125F1\u0017C]\t\u007f#)\rb3\u0016\u0005\u0011-\u0004CB)\u0003\t[\"y\r\u0005\u0004B\'\u0012=D1\u000f\t\u0004s\u0011ED!B,\u0013\u0005\u0004I\u0005CB!T\tk\"I\bE\u0002:\to\"Q\u0001\u001b\nC\u0002%\u0003b!Q*\u0005|\u0011}\u0004cA\u001d\u0005~\u0011)\u0011P\u0005b\u0001\u0013B1\u0011i\u0015CA\t\u000b\u00032!\u000fCB\t\u0019\tYB\u0005b\u0001\u0013B1\u0011i\u0015CD\t\u0017\u00032!\u000fCE\t\u0019\tIE\u0005b\u0001\u0013B1\u0011i\u0015CG\t#\u00032!\u000fCH\t\u0019\tiH\u0005b\u0001\u0013B1\u0011i\u0015CJ\t/\u00032!\u000fCK\t\u0019\t9L\u0005b\u0001\u0013B1\u0011i\u0015CM\t;\u00032!\u000fCN\t\u0019\t9P\u0005b\u0001\u0013B1\u0011i\u0015CP\tG\u00032!\u000fCQ\t\u0019\u0011iD\u0005b\u0001\u0013B1\u0011i\u0015CS\tS\u00032!\u000fCT\t\u0019\u0011II\u0005b\u0001\u0013B1\u0011i\u0015CV\t_\u00032!\u000fCW\t\u0019\u0011YN\u0005b\u0001\u0013B1\u0011i\u0015CY\tk\u00032!\u000fCZ\t\u0015Y$C1\u0001J!\u0019\t5\u000bb.\u0005<B\u0019\u0011\b\"/\u0005\r\r=%C1\u0001J!\u0019\t5\u000b\"0\u0005BB\u0019\u0011\bb0\u0005\r\rM(C1\u0001J!\u0019\t5\u000bb1\u0005HB\u0019\u0011\b\"2\u0005\r\u0011u#C1\u0001J!\u0015\t5\u000b\"3Y!\rID1\u001a\u0003\u0007\t\u001b\u0014\"\u0019A%\u0003\u0003A\u00032%\tCi\t_\")\bb\u001f\u0005\u0002\u0012\u001dEQ\u0012CJ\t3#y\n\"*\u0005,\u0012EFq\u0017C_\t\u0007$I-C\u0002\u0005T\n\u0012q\u0001V;qY\u0016\fd\'A\u0007iY&\u001cH\u000fV;qY\u0016\u0014\u0018gN\u000b%\t3$\t\u000fb:\u0005n\u0012MH\u0011 C\u0000\u000b\u000b)Y!\"\u0005\u0006\u0018\u0015uQ1EC\u0015\u000b_))$b\u000f\u0006BU\u0011A1\u001c\t\u0007#\n!i.\"\u0012\u0011\r\u0005\u001bFq\u001cCr!\rID\u0011\u001d\u0003\u0006/N\u0011\r!\u0013\t\u0007\u0003N#)\u000f\";\u0011\u0007e\"9\u000fB\u0003i\'\t\u0007\u0011\n\u0005\u0004B\'\u0012-Hq\u001e\t\u0004s\u00115H!B=\u0014\u0005\u0004I\u0005CB!T\tc$)\u0010E\u0002:\tg$a!a\u0007\u0014\u0005\u0004I\u0005CB!T\to$Y\u0010E\u0002:\ts$a!!\u0013\u0014\u0005\u0004I\u0005CB!T\t{,\t\u0001E\u0002:\t\u007f$a!! \u0014\u0005\u0004I\u0005CB!T\u000b\u0007)9\u0001E\u0002:\u000b\u000b!a!a.\u0014\u0005\u0004I\u0005CB!T\u000b\u0013)i\u0001E\u0002:\u000b\u0017!a!a>\u0014\u0005\u0004I\u0005CB!T\u000b\u001f)\u0019\u0002E\u0002:\u000b#!aA!\u0010\u0014\u0005\u0004I\u0005CB!T\u000b+)I\u0002E\u0002:\u000b/!aA!#\u0014\u0005\u0004I\u0005CB!T\u000b7)y\u0002E\u0002:\u000b;!aAa7\u0014\u0005\u0004I\u0005CB!T\u000bC))\u0003E\u0002:\u000bG!QaO\nC\u0002%\u0003b!Q*\u0006(\u0015-\u0002cA\u001d\u0006*\u001111qR\nC\u0002%\u0003b!Q*\u0006.\u0015E\u0002cA\u001d\u00060\u0011111_\nC\u0002%\u0003b!Q*\u00064\u0015]\u0002cA\u001d\u00066\u00111AQL\nC\u0002%\u0003b!Q*\u0006:\u0015u\u0002cA\u001d\u0006<\u00111AQZ\nC\u0002%\u0003R!Q*\u0006@a\u00032!OC!\t\u0019)\u0019e\u0005b\u0001\u0013\n\t\u0011\u000bE\u0013\"\u000b\u000f\"y\u000e\":\u0005l\u0012EHq\u001fC\u007f\u000b\u0007)I!b\u0004\u0006\u0016\u0015mQ\u0011EC\u0014\u000b[)\u0019$\"\u000f\u0006@%\u0019Q\u0011\n\u0012\u0003\u000fQ+\b\u000f\\32o\u0005i\u0001\u000e\\5tiR+\b\u000f\\3sca*b%b\u0014\u0006X\u0015uS1MC5\u000b_*)(b\u001f\u0006\u0002\u0016\u001dUQRCJ\u000b3+y*\"*\u0006,\u0016EVqWC_+\t)\t\u0006\u0005\u0004R\u0005\u0015MS\u0011\u0019\t\u0007\u0003N+)&\"\u0017\u0011\u0007e*9\u0006B\u0003X)\t\u0007\u0011\n\u0005\u0004B\'\u0016mSq\f\t\u0004s\u0015uC!\u00025\u0015\u0005\u0004I\u0005CB!T\u000bC*)\u0007E\u0002:\u000bG\"Q!\u001f\u000bC\u0002%\u0003b!Q*\u0006h\u0015-\u0004cA\u001d\u0006j\u00111\u00111\u0004\u000bC\u0002%\u0003b!Q*\u0006n\u0015E\u0004cA\u001d\u0006p\u00111\u0011\u0011\n\u000bC\u0002%\u0003b!Q*\u0006t\u0015]\u0004cA\u001d\u0006v\u00111\u0011Q\u0010\u000bC\u0002%\u0003b!Q*\u0006z\u0015u\u0004cA\u001d\u0006|\u00111\u0011q\u0017\u000bC\u0002%\u0003b!Q*\u0006\u0000\u0015\r\u0005cA\u001d\u0006\u0002\u00121\u0011q\u001f\u000bC\u0002%\u0003b!Q*\u0006\u0006\u0016%\u0005cA\u001d\u0006\b\u00121!Q\b\u000bC\u0002%\u0003b!Q*\u0006\f\u0016=\u0005cA\u001d\u0006\u000e\u00121!\u0011\u0012\u000bC\u0002%\u0003b!Q*\u0006\u0012\u0016U\u0005cA\u001d\u0006\u0014\u00121!1\u001c\u000bC\u0002%\u0003b!Q*\u0006\u0018\u0016m\u0005cA\u001d\u0006\u001a\u0012)1\b\u0006b\u0001\u0013B1\u0011iUCO\u000bC\u00032!OCP\t\u0019\u0019y\t\u0006b\u0001\u0013B1\u0011iUCR\u000bO\u00032!OCS\t\u0019\u0019\u0019\u0010\u0006b\u0001\u0013B1\u0011iUCU\u000b[\u00032!OCV\t\u0019!i\u0006\u0006b\u0001\u0013B1\u0011iUCX\u000bg\u00032!OCY\t\u0019!i\r\u0006b\u0001\u0013B1\u0011iUC[\u000bs\u00032!OC\\\t\u0019)\u0019\u0005\u0006b\u0001\u0013B)\u0011iUC^1B\u0019\u0011(\"0\u0005\r\u0015}FC1\u0001J\u0005\u0005\u0011\u0006cJ\u0011\u0006D\u0016US1LC1\u000bO*i\'b\u001d\u0006z\u0015}TQQCF\u000b#+9*\"(\u0006$\u0016%VqVC[\u000bwK1!\"2#\u0005\u001d!V\u000f\u001d7fca\nQ\u0002\u001b7jgR$V\u000f\u001d7feFJT\u0003KCf\u000b\',I.b8\u0006f\u0016-X\u0011_C|\u000b{4\u0019A\"\u0003\u0007\u0010\u0019Ua1\u0004D\u0011\rO1iCb\r\u0007:\u0019}RCACg!\u0019\t&!b4\u0007DA1\u0011iUCi\u000b+\u00042!OCj\t\u00159VC1\u0001J!\u0019\t5+b6\u0006\\B\u0019\u0011(\"7\u0005\u000b!,\"\u0019A%\u0011\r\u0005\u001bVQ\\Cq!\rITq\u001c\u0003\u0006sV\u0011\r!\u0013\t\u0007\u0003N+\u0019/b:\u0011\u0007e*)\u000f\u0002\u0004\u0002\u001cU\u0011\r!\u0013\t\u0007\u0003N+I/\"<\u0011\u0007e*Y\u000f\u0002\u0004\u0002JU\u0011\r!\u0013\t\u0007\u0003N+y/b=\u0011\u0007e*\t\u0010\u0002\u0004\u0002~U\u0011\r!\u0013\t\u0007\u0003N+)0\"?\u0011\u0007e*9\u0010\u0002\u0004\u00028V\u0011\r!\u0013\t\u0007\u0003N+Y0b@\u0011\u0007e*i\u0010\u0002\u0004\u0002xV\u0011\r!\u0013\t\u0007\u0003N3\tA\"\u0002\u0011\u0007e2\u0019\u0001\u0002\u0004\u0003>U\u0011\r!\u0013\t\u0007\u0003N39Ab\u0003\u0011\u0007e2I\u0001\u0002\u0004\u0003\nV\u0011\r!\u0013\t\u0007\u0003N3iA\"\u0005\u0011\u0007e2y\u0001\u0002\u0004\u0003\\V\u0011\r!\u0013\t\u0007\u0003N3\u0019Bb\u0006\u0011\u0007e2)\u0002B\u0003<+\t\u0007\u0011\n\u0005\u0004B\'\u001aeaQ\u0004\t\u0004s\u0019mAABBH+\t\u0007\u0011\n\u0005\u0004B\'\u001a}a1\u0005\t\u0004s\u0019\u0005BABBz+\t\u0007\u0011\n\u0005\u0004B\'\u001a\u0015b\u0011\u0006\t\u0004s\u0019\u001dBA\u0002C/+\t\u0007\u0011\n\u0005\u0004B\'\u001a-bq\u0006\t\u0004s\u00195BA\u0002Cg+\t\u0007\u0011\n\u0005\u0004B\'\u001aEbQ\u0007\t\u0004s\u0019MBABC\"+\t\u0007\u0011\n\u0005\u0004B\'\u001a]b1\b\t\u0004s\u0019eBABC`+\t\u0007\u0011\nE\u0003B\'\u001au\u0002\fE\u0002:\r\u007f!aA\"\u0011\u0016\u0005\u0004I%!A*\u0011S\u00052)%\"5\u0006X\u0016uW1]Cu\u000b_,)0b?\u0007\u0002\u0019\u001daQ\u0002D\n\r31yB\"\n\u0007,\u0019Ebq\u0007D\u001f\u0013\r19E\t\u0002\b)V\u0004H.Z\u0019:\u00035AG.[:u)V\u0004H.\u001a:3aUQcQ\nD+\r72\tGb\u001a\u0007n\u0019Md\u0011\u0010D@\r\u000b3YI\"%\u0007\u0018\u001aue1\u0015DU\r_3)Lb/\u0007B\u001a\u001dWC\u0001D(!\u0019\t&A\"\u0015\u0007LB1\u0011i\u0015D*\r/\u00022!\u000fD+\t\u00159fC1\u0001J!\u0019\t5K\"\u0017\u0007^A\u0019\u0011Hb\u0017\u0005\u000b!4\"\u0019A%\u0011\r\u0005\u001bfq\fD2!\rId\u0011\r\u0003\u0006sZ\u0011\r!\u0013\t\u0007\u0003N3)G\"\u001b\u0011\u0007e29\u0007\u0002\u0004\u0002\u001cY\u0011\r!\u0013\t\u0007\u0003N3YGb\u001c\u0011\u0007e2i\u0007\u0002\u0004\u0002JY\u0011\r!\u0013\t\u0007\u0003N3\tH\"\u001e\u0011\u0007e2\u0019\b\u0002\u0004\u0002~Y\u0011\r!\u0013\t\u0007\u0003N39Hb\u001f\u0011\u0007e2I\b\u0002\u0004\u00028Z\u0011\r!\u0013\t\u0007\u0003N3iH\"!\u0011\u0007e2y\b\u0002\u0004\u0002xZ\u0011\r!\u0013\t\u0007\u0003N3\u0019Ib\"\u0011\u0007e2)\t\u0002\u0004\u0003>Y\u0011\r!\u0013\t\u0007\u0003N3II\"$\u0011\u0007e2Y\t\u0002\u0004\u0003\nZ\u0011\r!\u0013\t\u0007\u0003N3yIb%\u0011\u0007e2\t\n\u0002\u0004\u0003\\Z\u0011\r!\u0013\t\u0007\u0003N3)J\"\'\u0011\u0007e29\nB\u0003<-\t\u0007\u0011\n\u0005\u0004B\'\u001ameq\u0014\t\u0004s\u0019uEABBH-\t\u0007\u0011\n\u0005\u0004B\'\u001a\u0005fQ\u0015\t\u0004s\u0019\rFABBz-\t\u0007\u0011\n\u0005\u0004B\'\u001a\u001df1\u0016\t\u0004s\u0019%FA\u0002C/-\t\u0007\u0011\n\u0005\u0004B\'\u001a5f\u0011\u0017\t\u0004s\u0019=FA\u0002Cg-\t\u0007\u0011\n\u0005\u0004B\'\u001aMfq\u0017\t\u0004s\u0019UFABC\"-\t\u0007\u0011\n\u0005\u0004B\'\u001aefQ\u0018\t\u0004s\u0019mFABC`-\t\u0007\u0011\n\u0005\u0004B\'\u001a}f1\u0019\t\u0004s\u0019\u0005GA\u0002D!-\t\u0007\u0011\nE\u0003B\'\u001a\u0015\u0007\fE\u0002:\r\u000f$aA\"3\u0017\u0005\u0004I%!\u0001+\u0011W\u00052iMb\u0015\u0007Z\u0019}cQ\rD6\rc29H\" \u0007\u0004\u001a%eq\u0012DK\r73\tKb*\u0007.\u001aMf\u0011\u0018D`\r\u000bL1Ab4#\u0005\u001d!V\u000f\u001d7feA\nQ\u0002\u001b7jgR$V\u000f\u001d7feJ\nT\u0003\fDk\r;4\u0019O\";\u0007p\u001aUh1`D\u0001\u000f\u000f9iab\u0005\b\u001a\u001d}qQED\u0016\u000fc99d\"\u0010\bD\u001d%sqJD++\t19\u000e\u0005\u0004R\u0005\u0019ew\u0011\f\t\u0007\u0003N3YNb8\u0011\u0007e2i\u000eB\u0003X/\t\u0007\u0011\n\u0005\u0004B\'\u001a\u0005hQ\u001d\t\u0004s\u0019\rH!\u00025\u0018\u0005\u0004I\u0005CB!T\rO4Y\u000fE\u0002:\rS$Q!_\fC\u0002%\u0003b!Q*\u0007n\u001aE\bcA\u001d\u0007p\u00121\u00111D\fC\u0002%\u0003b!Q*\u0007t\u001a]\bcA\u001d\u0007v\u00121\u0011\u0011J\fC\u0002%\u0003b!Q*\u0007z\u001au\bcA\u001d\u0007|\u00121\u0011QP\fC\u0002%\u0003b!Q*\u0007\u0000\u001e\r\u0001cA\u001d\b\u0002\u00111\u0011qW\fC\u0002%\u0003b!Q*\b\u0006\u001d%\u0001cA\u001d\b\b\u00111\u0011q_\fC\u0002%\u0003b!Q*\b\f\u001d=\u0001cA\u001d\b\u000e\u00111!QH\fC\u0002%\u0003b!Q*\b\u0012\u001dU\u0001cA\u001d\b\u0014\u00111!\u0011R\fC\u0002%\u0003b!Q*\b\u0018\u001dm\u0001cA\u001d\b\u001a\u00111!1\\\fC\u0002%\u0003b!Q*\b\u001e\u001d\u0005\u0002cA\u001d\b \u0011)1h\u0006b\u0001\u0013B1\u0011iUD\u0012\u000fO\u00012!OD\u0013\t\u0019\u0019yi\u0006b\u0001\u0013B1\u0011iUD\u0015\u000f[\u00012!OD\u0016\t\u0019\u0019\u0019p\u0006b\u0001\u0013B1\u0011iUD\u0018\u000fg\u00012!OD\u0019\t\u0019!if\u0006b\u0001\u0013B1\u0011iUD\u001b\u000fs\u00012!OD\u001c\t\u0019!im\u0006b\u0001\u0013B1\u0011iUD\u001e\u000f\u007f\u00012!OD\u001f\t\u0019)\u0019e\u0006b\u0001\u0013B1\u0011iUD!\u000f\u000b\u00022!OD\"\t\u0019)yl\u0006b\u0001\u0013B1\u0011iUD$\u000f\u0017\u00022!OD%\t\u00191\te\u0006b\u0001\u0013B1\u0011iUD\'\u000f#\u00022!OD(\t\u00191Im\u0006b\u0001\u0013B)\u0011iUD*1B\u0019\u0011h\"\u0016\u0005\r\u001d]sC1\u0001J\u0005\u0005)\u0006#L\u0011\b\\\u0019mg\u0011\u001dDt\r[4\u0019P\"?\u0007\u0000\u001e\u0015q1BD\t\u000f/9ibb\t\b*\u001d=rQGD\u001e\u000f\u0003:9e\"\u0014\bT%\u0019qQ\f\u0012\u0003\u000fQ+\b\u000f\\33c\u0005i\u0001\u000e\\5tiR+\b\u000f\\3seI*bfb\u0019\bl\u001dEtqOD?\u000f\u0007;Iib$\b\u0016\u001emu\u0011UDT\u000f[;\u0019l\"/\b@\u001e\u0015w1ZDi\u000f/<inb9\bjV\u0011qQ\r\t\u0007#\n99g\"<\u0011\r\u0005\u001bv\u0011ND7!\rIt1\u000e\u0003\u0006/b\u0011\r!\u0013\t\u0007\u0003N;ygb\u001d\u0011\u0007e:\t\bB\u0003i1\t\u0007\u0011\n\u0005\u0004B\'\u001eUt\u0011\u0010\t\u0004s\u001d]D!B=\u0019\u0005\u0004I\u0005CB!T\u000fw:y\bE\u0002:\u000f{\"a!a\u0007\u0019\u0005\u0004I\u0005CB!T\u000f\u0003;)\tE\u0002:\u000f\u0007#a!!\u0013\u0019\u0005\u0004I\u0005CB!T\u000f\u000f;Y\tE\u0002:\u000f\u0013#a!! \u0019\u0005\u0004I\u0005CB!T\u000f\u001b;\t\nE\u0002:\u000f\u001f#a!a.\u0019\u0005\u0004I\u0005CB!T\u000f\';9\nE\u0002:\u000f+#a!a>\u0019\u0005\u0004I\u0005CB!T\u000f3;i\nE\u0002:\u000f7#aA!\u0010\u0019\u0005\u0004I\u0005CB!T\u000f?;\u0019\u000bE\u0002:\u000fC#aA!#\u0019\u0005\u0004I\u0005CB!T\u000fK;I\u000bE\u0002:\u000fO#aAa7\u0019\u0005\u0004I\u0005CB!T\u000fW;y\u000bE\u0002:\u000f[#Qa\u000f\rC\u0002%\u0003b!Q*\b2\u001eU\u0006cA\u001d\b4\u001211q\u0012\rC\u0002%\u0003b!Q*\b8\u001em\u0006cA\u001d\b:\u0012111\u001f\rC\u0002%\u0003b!Q*\b>\u001e\u0005\u0007cA\u001d\b@\u00121AQ\f\rC\u0002%\u0003b!Q*\bD\u001e\u001d\u0007cA\u001d\bF\u00121AQ\u001a\rC\u0002%\u0003b!Q*\bJ\u001e5\u0007cA\u001d\bL\u00121Q1\t\rC\u0002%\u0003b!Q*\bP\u001eM\u0007cA\u001d\bR\u00121Qq\u0018\rC\u0002%\u0003b!Q*\bV\u001ee\u0007cA\u001d\bX\u00121a\u0011\t\rC\u0002%\u0003b!Q*\b\\\u001e}\u0007cA\u001d\b^\u00121a\u0011\u001a\rC\u0002%\u0003b!Q*\bb\u001e\u0015\bcA\u001d\bd\u00121qq\u000b\rC\u0002%\u0003R!Q*\bhb\u00032!ODu\t\u00199Y\u000f\u0007b\u0001\u0013\n\ta\u000bE\u0018\"\u000f_<Igb\u001c\bv\u001dmt\u0011QDD\u000f\u001b;\u0019j\"\'\b \u001e\u0015v1VDY\u000fo;ilb1\bJ\u001e=wQ[Dn\u000fC<9/C\u0002\br\n\u0012q\u0001V;qY\u0016\u0014$\u0007
    #9 = Utf8               shapeless/ops/TuplerInstances$$anon$1
   #10 = Class              #9            // shapeless/ops/TuplerInstances$$anon$1
   #11 = Utf8               shapeless/ops/TuplerInstances$$anon$10
   #12 = Class              #11           // shapeless/ops/TuplerInstances$$anon$10
   #13 = Utf8               shapeless/ops/TuplerInstances$$anon$11
   #14 = Class              #13           // shapeless/ops/TuplerInstances$$anon$11
   #15 = Utf8               shapeless/ops/TuplerInstances$$anon$12
   #16 = Class              #15           // shapeless/ops/TuplerInstances$$anon$12
   #17 = Utf8               shapeless/ops/TuplerInstances$$anon$13
   #18 = Class              #17           // shapeless/ops/TuplerInstances$$anon$13
   #19 = Utf8               shapeless/ops/TuplerInstances$$anon$14
   #20 = Class              #19           // shapeless/ops/TuplerInstances$$anon$14
   #21 = Utf8               shapeless/ops/TuplerInstances$$anon$15
   #22 = Class              #21           // shapeless/ops/TuplerInstances$$anon$15
   #23 = Utf8               shapeless/ops/TuplerInstances$$anon$16
   #24 = Class              #23           // shapeless/ops/TuplerInstances$$anon$16
   #25 = Utf8               shapeless/ops/TuplerInstances$$anon$17
   #26 = Class              #25           // shapeless/ops/TuplerInstances$$anon$17
   #27 = Utf8               shapeless/ops/TuplerInstances$$anon$18
   #28 = Class              #27           // shapeless/ops/TuplerInstances$$anon$18
   #29 = Utf8               shapeless/ops/TuplerInstances$$anon$19
   #30 = Class              #29           // shapeless/ops/TuplerInstances$$anon$19
   #31 = Utf8               shapeless/ops/TuplerInstances$$anon$2
   #32 = Class              #31           // shapeless/ops/TuplerInstances$$anon$2
   #33 = Utf8               shapeless/ops/TuplerInstances$$anon$20
   #34 = Class              #33           // shapeless/ops/TuplerInstances$$anon$20
   #35 = Utf8               shapeless/ops/TuplerInstances$$anon$21
   #36 = Class              #35           // shapeless/ops/TuplerInstances$$anon$21
   #37 = Utf8               shapeless/ops/TuplerInstances$$anon$22
   #38 = Class              #37           // shapeless/ops/TuplerInstances$$anon$22
   #39 = Utf8               shapeless/ops/TuplerInstances$$anon$3
   #40 = Class              #39           // shapeless/ops/TuplerInstances$$anon$3
   #41 = Utf8               shapeless/ops/TuplerInstances$$anon$4
   #42 = Class              #41           // shapeless/ops/TuplerInstances$$anon$4
   #43 = Utf8               shapeless/ops/TuplerInstances$$anon$5
   #44 = Class              #43           // shapeless/ops/TuplerInstances$$anon$5
   #45 = Utf8               shapeless/ops/TuplerInstances$$anon$6
   #46 = Class              #45           // shapeless/ops/TuplerInstances$$anon$6
   #47 = Utf8               shapeless/ops/TuplerInstances$$anon$7
   #48 = Class              #47           // shapeless/ops/TuplerInstances$$anon$7
   #49 = Utf8               shapeless/ops/TuplerInstances$$anon$8
   #50 = Class              #49           // shapeless/ops/TuplerInstances$$anon$8
   #51 = Utf8               shapeless/ops/TuplerInstances$$anon$9
   #52 = Class              #51           // shapeless/ops/TuplerInstances$$anon$9
   #53 = Utf8               shapeless/ops/hlist$Tupler
   #54 = Class              #53           // shapeless/ops/hlist$Tupler
   #55 = Utf8               shapeless/ops/hlist
   #56 = Class              #55           // shapeless/ops/hlist
   #57 = Utf8               Tupler
   #58 = Utf8               hlistTupler1$
   #59 = Utf8               (Lshapeless/ops/TuplerInstances;)Lshapeless/ops/hlist$Tupler;
   #60 = Utf8               $this
   #61 = Utf8               hlistTupler1
   #62 = Utf8               ()Lshapeless/ops/hlist$Tupler;
   #63 = NameAndType        #61:#62       // hlistTupler1:()Lshapeless/ops/hlist$Tupler;
   #64 = InterfaceMethodref #2.#63        // shapeless/ops/TuplerInstances.hlistTupler1:()Lshapeless/ops/hlist$Tupler;
   #65 = Utf8               Lshapeless/ops/TuplerInstances;
   #66 = Utf8               <A:Ljava/lang/Object;>()Lshapeless/ops/hlist$Tupler<Lshapeless/$colon$colon<TA;Lshapeless/HNil;>;>;
   #67 = Utf8               <init>
   #68 = Utf8               (Lshapeless/ops/TuplerInstances;)V
   #69 = NameAndType        #67:#68       // "<init>":(Lshapeless/ops/TuplerInstances;)V
   #70 = Methodref          #10.#69       // shapeless/ops/TuplerInstances$$anon$1."<init>":(Lshapeless/ops/TuplerInstances;)V
   #71 = Utf8               this
   #72 = Utf8               hlistTupler2$
   #73 = Utf8               hlistTupler2
   #74 = NameAndType        #73:#62       // hlistTupler2:()Lshapeless/ops/hlist$Tupler;
   #75 = InterfaceMethodref #2.#74        // shapeless/ops/TuplerInstances.hlistTupler2:()Lshapeless/ops/hlist$Tupler;
   #76 = Utf8               <A:Ljava/lang/Object;B:Ljava/lang/Object;>()Lshapeless/ops/hlist$Tupler<Lshapeless/$colon$colon<TA;Lshapeless/$colon$colon<TB;Lshapeless/HNil;>;>;>;
   #77 = Methodref          #32.#69       // shapeless/ops/TuplerInstances$$anon$2."<init>":(Lshapeless/ops/TuplerInstances;)V
   #78 = Utf8               hlistTupler3$
   #79 = Utf8               hlistTupler3
   #80 = NameAndType        #79:#62       // hlistTupler3:()Lshapeless/ops/hlist$Tupler;
   #81 = InterfaceMethodref #2.#80        // shapeless/ops/TuplerInstances.hlistTupler3:()Lshapeless/ops/hlist$Tupler;
   #82 = Utf8               <A:Ljava/lang/Object;B:Ljava/lang/Object;C:Ljava/lang/Object;>()Lshapeless/ops/hlist$Tupler<Lshapeless/$colon$colon<TA;Lshapeless/$colon$colon<TB;Lshapeless/$colon$colon<TC;Lshapeless/HNil;>;>;>;>;
   #83 = Methodref          #40.#69       // shapeless/ops/TuplerInstances$$anon$3."<init>":(Lshapeless/ops/TuplerInstances;)V
   #84 = Utf8               hlistTupler4$
   #85 = Utf8               hlistTupler4
   #86 = NameAndType        #85:#62       // hlistTupler4:()Lshapeless/ops/hlist$Tupler;
   #87 = InterfaceMethodref #2.#86        // shapeless/ops/TuplerInstances.hlistTupler4:()Lshapeless/ops/hlist$Tupler;
   #88 = Utf8               <A:Ljava/lang/Object;B:Ljava/lang/Object;C:Ljava/lang/Object;D:Ljava/lang/Object;>()Lshapeless/ops/hlist$Tupler<Lshapeless/$colon$colon<TA;Lshapeless/$colon$colon<TB;Lshapeless/$colon$colon<TC;Lshapeless/$colon$colon<TD;Lshapeless/HNil;>;>;>;>;>;
   #89 = Methodref          #42.#69       // shapeless/ops/TuplerInstances$$anon$4."<init>":(Lshapeless/ops/TuplerInstances;)V
   #90 = Utf8               hlistTupler5$
   #91 = Utf8               hlistTupler5
   #92 = NameAndType        #91:#62       // hlistTupler5:()Lshapeless/ops/hlist$Tupler;
   #93 = InterfaceMethodref #2.#92        // shapeless/ops/TuplerInstances.hlistTupler5:()Lshapeless/ops/hlist$Tupler;
   #94 = Utf8               <A:Ljava/lang/Object;B:Ljava/lang/Object;C:Ljava/lang/Object;D:Ljava/lang/Object;E:Ljava/lang/Object;>()Lshapeless/ops/hlist$Tupler<Lshapeless/$colon$colon<TA;Lshapeless/$colon$colon<TB;Lshapeless/$colon$colon<TC;Lshapeless/$colon$colon<TD;Lshapeless/$colon$colon<TE;Lshapeless/HNil;>;>;>;>;>;>;
   #95 = Methodref          #44.#69       // shapeless/ops/TuplerInstances$$anon$5."<init>":(Lshapeless/ops/TuplerInstances;)V
   #96 = Utf8               hlistTupler6$
   #97 = Utf8               hlistTupler6
   #98 = NameAndType        #97:#62       // hlistTupler6:()Lshapeless/ops/hlist$Tupler;
   #99 = InterfaceMethodref #2.#98        // shapeless/ops/TuplerInstances.hlistTupler6:()Lshapeless/ops/hlist$Tupler;
  #100 = Utf8               <A:Ljava/lang/Object;B:Ljava/lang/Object;C:Ljava/lang/Object;D:Ljava/lang/Object;E:Ljava/lang/Object;F:Ljava/lang/Object;>()Lshapeless/ops/hlist$Tupler<Lshapeless/$colon$colon<TA;Lshapeless/$colon$colon<TB;Lshapeless/$colon$colon<TC;Lshapeless/$colon$colon<TD;Lshapeless/$colon$colon<TE;Lshapeless/$colon$colon<TF;Lshapeless/HNil;>;>;>;>;>;>;>;
  #101 = Methodref          #46.#69       // shapeless/ops/TuplerInstances$$anon$6."<init>":(Lshapeless/ops/TuplerInstances;)V
  #102 = Utf8               hlistTupler7$
  #103 = Utf8               hlistTupler7
  #104 = NameAndType        #103:#62      // hlistTupler7:()Lshapeless/ops/hlist$Tupler;
  #105 = InterfaceMethodref #2.#104       // shapeless/ops/TuplerInstances.hlistTupler7:()Lshapeless/ops/hlist$Tupler;
  #106 = Utf8               <A:Ljava/lang/Object;B:Ljava/lang/Object;C:Ljava/lang/Object;D:Ljava/lang/Object;E:Ljava/lang/Object;F:Ljava/lang/Object;G:Ljava/lang/Object;>()Lshapeless/ops/hlist$Tupler<Lshapeless/$colon$colon<TA;Lshapeless/$colon$colon<TB;Lshapeless/$colon$colon<TC;Lshapeless/$colon$colon<TD;Lshapeless/$colon$colon<TE;Lshapeless/$colon$colon<TF;Lshapeless/$colon$colon<TG;Lshapeless/HNil;>;>;>;>;>;>;>;>;
  #107 = Methodref          #48.#69       // shapeless/ops/TuplerInstances$$anon$7."<init>":(Lshapeless/ops/TuplerInstances;)V
  #108 = Utf8               hlistTupler8$
  #109 = Utf8               hlistTupler8
  #110 = NameAndType        #109:#62      // hlistTupler8:()Lshapeless/ops/hlist$Tupler;
  #111 = InterfaceMethodref #2.#110       // shapeless/ops/TuplerInstances.hlistTupler8:()Lshapeless/ops/hlist$Tupler;
  #112 = Utf8               <A:Ljava/lang/Object;B:Ljava/lang/Object;C:Ljava/lang/Object;D:Ljava/lang/Object;E:Ljava/lang/Object;F:Ljava/lang/Object;G:Ljava/lang/Object;H:Ljava/lang/Object;>()Lshapeless/ops/hlist$Tupler<Lshapeless/$colon$colon<TA;Lshapeless/$colon$colon<TB;Lshapeless/$colon$colon<TC;Lshapeless/$colon$colon<TD;Lshapeless/$colon$colon<TE;Lshapeless/$colon$colon<TF;Lshapeless/$colon$colon<TG;Lshapeless/$colon$colon<TH;Lshapeless/HNil;>;>;>;>;>;>;>;>;>;
  #113 = Methodref          #50.#69       // shapeless/ops/TuplerInstances$$anon$8."<init>":(Lshapeless/ops/TuplerInstances;)V
  #114 = Utf8               hlistTupler9$
  #115 = Utf8               hlistTupler9
  #116 = NameAndType        #115:#62      // hlistTupler9:()Lshapeless/ops/hlist$Tupler;
  #117 = InterfaceMethodref #2.#116       // shapeless/ops/TuplerInstances.hlistTupler9:()Lshapeless/ops/hlist$Tupler;
  #118 = Utf8               <A:Ljava/lang/Object;B:Ljava/lang/Object;C:Ljava/lang/Object;D:Ljava/lang/Object;E:Ljava/lang/Object;F:Ljava/lang/Object;G:Ljava/lang/Object;H:Ljava/lang/Object;I:Ljava/lang/Object;>()Lshapeless/ops/hlist$Tupler<Lshapeless/$colon$colon<TA;Lshapeless/$colon$colon<TB;Lshapeless/$colon$colon<TC;Lshapeless/$colon$colon<TD;Lshapeless/$colon$colon<TE;Lshapeless/$colon$colon<TF;Lshapeless/$colon$colon<TG;Lshapeless/$colon$colon<TH;Lshapeless/$colon$colon<TI;Lshapeless/HNil;>;>;>;>;>;>;>;>;>;>;
  #119 = Methodref          #52.#69       // shapeless/ops/TuplerInstances$$anon$9."<init>":(Lshapeless/ops/TuplerInstances;)V
  #120 = Utf8               hlistTupler10$
  #121 = Utf8               hlistTupler10
  #122 = NameAndType        #121:#62      // hlistTupler10:()Lshapeless/ops/hlist$Tupler;
  #123 = InterfaceMethodref #2.#122       // shapeless/ops/TuplerInstances.hlistTupler10:()Lshapeless/ops/hlist$Tupler;
  #124 = Utf8               <A:Ljava/lang/Object;B:Ljava/lang/Object;C:Ljava/lang/Object;D:Ljava/lang/Object;E:Ljava/lang/Object;F:Ljava/lang/Object;G:Ljava/lang/Object;H:Ljava/lang/Object;I:Ljava/lang/Object;J:Ljava/lang/Object;>()Lshapeless/ops/hlist$Tupler<Lshapeless/$colon$colon<TA;Lshapeless/$colon$colon<TB;Lshapeless/$colon$colon<TC;Lshapeless/$colon$colon<TD;Lshapeless/$colon$colon<TE;Lshapeless/$colon$colon<TF;Lshapeless/$colon$colon<TG;Lshapeless/$colon$colon<TH;Lshapeless/$colon$colon<TI;Lshapeless/$colon$colon<TJ;Lshapeless/HNil;>;>;>;>;>;>;>;>;>;>;>;
  #125 = Methodref          #12.#69       // shapeless/ops/TuplerInstances$$anon$10."<init>":(Lshapeless/ops/TuplerInstances;)V
  #126 = Utf8               hlistTupler11$
  #127 = Utf8               hlistTupler11
  #128 = NameAndType        #127:#62      // hlistTupler11:()Lshapeless/ops/hlist$Tupler;
  #129 = InterfaceMethodref #2.#128       // shapeless/ops/TuplerInstances.hlistTupler11:()Lshapeless/ops/hlist$Tupler;
  #130 = Utf8               <A:Ljava/lang/Object;B:Ljava/lang/Object;C:Ljava/lang/Object;D:Ljava/lang/Object;E:Ljava/lang/Object;F:Ljava/lang/Object;G:Ljava/lang/Object;H:Ljava/lang/Object;I:Ljava/lang/Object;J:Ljava/lang/Object;K:Ljava/lang/Object;>()Lshapeless/ops/hlist$Tupler<Lshapeless/$colon$colon<TA;Lshapeless/$colon$colon<TB;Lshapeless/$colon$colon<TC;Lshapeless/$colon$colon<TD;Lshapeless/$colon$colon<TE;Lshapeless/$colon$colon<TF;Lshapeless/$colon$colon<TG;Lshapeless/$colon$colon<TH;Lshapeless/$colon$colon<TI;Lshapeless/$colon$colon<TJ;Lshapeless/$colon$colon<TK;Lshapeless/HNil;>;>;>;>;>;>;>;>;>;>;>;>;
  #131 = Methodref          #14.#69       // shapeless/ops/TuplerInstances$$anon$11."<init>":(Lshapeless/ops/TuplerInstances;)V
  #132 = Utf8               hlistTupler12$
  #133 = Utf8               hlistTupler12
  #134 = NameAndType        #133:#62      // hlistTupler12:()Lshapeless/ops/hlist$Tupler;
  #135 = InterfaceMethodref #2.#134       // shapeless/ops/TuplerInstances.hlistTupler12:()Lshapeless/ops/hlist$Tupler;
  #136 = Utf8               <A:Ljava/lang/Object;B:Ljava/lang/Object;C:Ljava/lang/Object;D:Ljava/lang/Object;E:Ljava/lang/Object;F:Ljava/lang/Object;G:Ljava/lang/Object;H:Ljava/lang/Object;I:Ljava/lang/Object;J:Ljava/lang/Object;K:Ljava/lang/Object;L:Ljava/lang/Object;>()Lshapeless/ops/hlist$Tupler<Lshapeless/$colon$colon<TA;Lshapeless/$colon$colon<TB;Lshapeless/$colon$colon<TC;Lshapeless/$colon$colon<TD;Lshapeless/$colon$colon<TE;Lshapeless/$colon$colon<TF;Lshapeless/$colon$colon<TG;Lshapeless/$colon$colon<TH;Lshapeless/$colon$colon<TI;Lshapeless/$colon$colon<TJ;Lshapeless/$colon$colon<TK;Lshapeless/$colon$colon<TL;Lshapeless/HNil;>;>;>;>;>;>;>;>;>;>;>;>;>;
  #137 = Methodref          #16.#69       // shapeless/ops/TuplerInstances$$anon$12."<init>":(Lshapeless/ops/TuplerInstances;)V
  #138 = Utf8               hlistTupler13$
  #139 = Utf8               hlistTupler13
  #140 = NameAndType        #139:#62      // hlistTupler13:()Lshapeless/ops/hlist$Tupler;
  #141 = InterfaceMethodref #2.#140       // shapeless/ops/TuplerInstances.hlistTupler13:()Lshapeless/ops/hlist$Tupler;
  #142 = Utf8               <A:Ljava/lang/Object;B:Ljava/lang/Object;C:Ljava/lang/Object;D:Ljava/lang/Object;E:Ljava/lang/Object;F:Ljava/lang/Object;G:Ljava/lang/Object;H:Ljava/lang/Object;I:Ljava/lang/Object;J:Ljava/lang/Object;K:Ljava/lang/Object;L:Ljava/lang/Object;M:Ljava/lang/Object;>()Lshapeless/ops/hlist$Tupler<Lshapeless/$colon$colon<TA;Lshapeless/$colon$colon<TB;Lshapeless/$colon$colon<TC;Lshapeless/$colon$colon<TD;Lshapeless/$colon$colon<TE;Lshapeless/$colon$colon<TF;Lshapeless/$colon$colon<TG;Lshapeless/$colon$colon<TH;Lshapeless/$colon$colon<TI;Lshapeless/$colon$colon<TJ;Lshapeless/$colon$colon<TK;Lshapeless/$colon$colon<TL;Lshapeless/$colon$colon<TM;Lshapeless/HNil;>;>;>;>;>;>;>;>;>;>;>;>;>;>;
  #143 = Methodref          #18.#69       // shapeless/ops/TuplerInstances$$anon$13."<init>":(Lshapeless/ops/TuplerInstances;)V
  #144 = Utf8               hlistTupler14$
  #145 = Utf8               hlistTupler14
  #146 = NameAndType        #145:#62      // hlistTupler14:()Lshapeless/ops/hlist$Tupler;
  #147 = InterfaceMethodref #2.#146       // shapeless/ops/TuplerInstances.hlistTupler14:()Lshapeless/ops/hlist$Tupler;
  #148 = Utf8               <A:Ljava/lang/Object;B:Ljava/lang/Object;C:Ljava/lang/Object;D:Ljava/lang/Object;E:Ljava/lang/Object;F:Ljava/lang/Object;G:Ljava/lang/Object;H:Ljava/lang/Object;I:Ljava/lang/Object;J:Ljava/lang/Object;K:Ljava/lang/Object;L:Ljava/lang/Object;M:Ljava/lang/Object;N:Ljava/lang/Object;>()Lshapeless/ops/hlist$Tupler<Lshapeless/$colon$colon<TA;Lshapeless/$colon$colon<TB;Lshapeless/$colon$colon<TC;Lshapeless/$colon$colon<TD;Lshapeless/$colon$colon<TE;Lshapeless/$colon$colon<TF;Lshapeless/$colon$colon<TG;Lshapeless/$colon$colon<TH;Lshapeless/$colon$colon<TI;Lshapeless/$colon$colon<TJ;Lshapeless/$colon$colon<TK;Lshapeless/$colon$colon<TL;Lshapeless/$colon$colon<TM;Lshapeless/$colon$colon<TN;Lshapeless/HNil;>;>;>;>;>;>;>;>;>;>;>;>;>;>;>;
  #149 = Methodref          #20.#69       // shapeless/ops/TuplerInstances$$anon$14."<init>":(Lshapeless/ops/TuplerInstances;)V
  #150 = Utf8               hlistTupler15$
  #151 = Utf8               hlistTupler15
  #152 = NameAndType        #151:#62      // hlistTupler15:()Lshapeless/ops/hlist$Tupler;
  #153 = InterfaceMethodref #2.#152       // shapeless/ops/TuplerInstances.hlistTupler15:()Lshapeless/ops/hlist$Tupler;
  #154 = Utf8               <A:Ljava/lang/Object;B:Ljava/lang/Object;C:Ljava/lang/Object;D:Ljava/lang/Object;E:Ljava/lang/Object;F:Ljava/lang/Object;G:Ljava/lang/Object;H:Ljava/lang/Object;I:Ljava/lang/Object;J:Ljava/lang/Object;K:Ljava/lang/Object;L:Ljava/lang/Object;M:Ljava/lang/Object;N:Ljava/lang/Object;O:Ljava/lang/Object;>()Lshapeless/ops/hlist$Tupler<Lshapeless/$colon$colon<TA;Lshapeless/$colon$colon<TB;Lshapeless/$colon$colon<TC;Lshapeless/$colon$colon<TD;Lshapeless/$colon$colon<TE;Lshapeless/$colon$colon<TF;Lshapeless/$colon$colon<TG;Lshapeless/$colon$colon<TH;Lshapeless/$colon$colon<TI;Lshapeless/$colon$colon<TJ;Lshapeless/$colon$colon<TK;Lshapeless/$colon$colon<TL;Lshapeless/$colon$colon<TM;Lshapeless/$colon$colon<TN;Lshapeless/$colon$colon<TO;Lshapeless/HNil;>;>;>;>;>;>;>;>;>;>;>;>;>;>;>;>;
  #155 = Methodref          #22.#69       // shapeless/ops/TuplerInstances$$anon$15."<init>":(Lshapeless/ops/TuplerInstances;)V
  #156 = Utf8               hlistTupler16$
  #157 = Utf8               hlistTupler16
  #158 = NameAndType        #157:#62      // hlistTupler16:()Lshapeless/ops/hlist$Tupler;
  #159 = InterfaceMethodref #2.#158       // shapeless/ops/TuplerInstances.hlistTupler16:()Lshapeless/ops/hlist$Tupler;
  #160 = Utf8               <A:Ljava/lang/Object;B:Ljava/lang/Object;C:Ljava/lang/Object;D:Ljava/lang/Object;E:Ljava/lang/Object;F:Ljava/lang/Object;G:Ljava/lang/Object;H:Ljava/lang/Object;I:Ljava/lang/Object;J:Ljava/lang/Object;K:Ljava/lang/Object;L:Ljava/lang/Object;M:Ljava/lang/Object;N:Ljava/lang/Object;O:Ljava/lang/Object;P:Ljava/lang/Object;>()Lshapeless/ops/hlist$Tupler<Lshapeless/$colon$colon<TA;Lshapeless/$colon$colon<TB;Lshapeless/$colon$colon<TC;Lshapeless/$colon$colon<TD;Lshapeless/$colon$colon<TE;Lshapeless/$colon$colon<TF;Lshapeless/$colon$colon<TG;Lshapeless/$colon$colon<TH;Lshapeless/$colon$colon<TI;Lshapeless/$colon$colon<TJ;Lshapeless/$colon$colon<TK;Lshapeless/$colon$colon<TL;Lshapeless/$colon$colon<TM;Lshapeless/$colon$colon<TN;Lshapeless/$colon$colon<TO;Lshapeless/$colon$colon<TP;Lshapeless/HNil;>;>;>;>;>;>;>;>;>;>;>;>;>;>;>;>;>;
  #161 = Methodref          #24.#69       // shapeless/ops/TuplerInstances$$anon$16."<init>":(Lshapeless/ops/TuplerInstances;)V
  #162 = Utf8               hlistTupler17$
  #163 = Utf8               hlistTupler17
  #164 = NameAndType        #163:#62      // hlistTupler17:()Lshapeless/ops/hlist$Tupler;
  #165 = InterfaceMethodref #2.#164       // shapeless/ops/TuplerInstances.hlistTupler17:()Lshapeless/ops/hlist$Tupler;
  #166 = Utf8               <A:Ljava/lang/Object;B:Ljava/lang/Object;C:Ljava/lang/Object;D:Ljava/lang/Object;E:Ljava/lang/Object;F:Ljava/lang/Object;G:Ljava/lang/Object;H:Ljava/lang/Object;I:Ljava/lang/Object;J:Ljava/lang/Object;K:Ljava/lang/Object;L:Ljava/lang/Object;M:Ljava/lang/Object;N:Ljava/lang/Object;O:Ljava/lang/Object;P:Ljava/lang/Object;Q:Ljava/lang/Object;>()Lshapeless/ops/hlist$Tupler<Lshapeless/$colon$colon<TA;Lshapeless/$colon$colon<TB;Lshapeless/$colon$colon<TC;Lshapeless/$colon$colon<TD;Lshapeless/$colon$colon<TE;Lshapeless/$colon$colon<TF;Lshapeless/$colon$colon<TG;Lshapeless/$colon$colon<TH;Lshapeless/$colon$colon<TI;Lshapeless/$colon$colon<TJ;Lshapeless/$colon$colon<TK;Lshapeless/$colon$colon<TL;Lshapeless/$colon$colon<TM;Lshapeless/$colon$colon<TN;Lshapeless/$colon$colon<TO;Lshapeless/$colon$colon<TP;Lshapeless/$colon$colon<TQ;Lshapeless/HNil;>;>;>;>;>;>;>;>;>;>;>;>;>;>;>;>;>;>;
  #167 = Methodref          #26.#69       // shapeless/ops/TuplerInstances$$anon$17."<init>":(Lshapeless/ops/TuplerInstances;)V
  #168 = Utf8               hlistTupler18$
  #169 = Utf8               hlistTupler18
  #170 = NameAndType        #169:#62      // hlistTupler18:()Lshapeless/ops/hlist$Tupler;
  #171 = InterfaceMethodref #2.#170       // shapeless/ops/TuplerInstances.hlistTupler18:()Lshapeless/ops/hlist$Tupler;
  #172 = Utf8               <A:Ljava/lang/Object;B:Ljava/lang/Object;C:Ljava/lang/Object;D:Ljava/lang/Object;E:Ljava/lang/Object;F:Ljava/lang/Object;G:Ljava/lang/Object;H:Ljava/lang/Object;I:Ljava/lang/Object;J:Ljava/lang/Object;K:Ljava/lang/Object;L:Ljava/lang/Object;M:Ljava/lang/Object;N:Ljava/lang/Object;O:Ljava/lang/Object;P:Ljava/lang/Object;Q:Ljava/lang/Object;R:Ljava/lang/Object;>()Lshapeless/ops/hlist$Tupler<Lshapeless/$colon$colon<TA;Lshapeless/$colon$colon<TB;Lshapeless/$colon$colon<TC;Lshapeless/$colon$colon<TD;Lshapeless/$colon$colon<TE;Lshapeless/$colon$colon<TF;Lshapeless/$colon$colon<TG;Lshapeless/$colon$colon<TH;Lshapeless/$colon$colon<TI;Lshapeless/$colon$colon<TJ;Lshapeless/$colon$colon<TK;Lshapeless/$colon$colon<TL;Lshapeless/$colon$colon<TM;Lshapeless/$colon$colon<TN;Lshapeless/$colon$colon<TO;Lshapeless/$colon$colon<TP;Lshapeless/$colon$colon<TQ;Lshapeless/$colon$colon<TR;Lshapeless/HNil;>;>;>;>;>;>;>;>;>;>;>;>;>;>;>;>;>;>;>;
  #173 = Methodref          #28.#69       // shapeless/ops/TuplerInstances$$anon$18."<init>":(Lshapeless/ops/TuplerInstances;)V
  #174 = Utf8               hlistTupler19$
  #175 = Utf8               hlistTupler19
  #176 = NameAndType        #175:#62      // hlistTupler19:()Lshapeless/ops/hlist$Tupler;
  #177 = InterfaceMethodref #2.#176       // shapeless/ops/TuplerInstances.hlistTupler19:()Lshapeless/ops/hlist$Tupler;
  #178 = Utf8               <A:Ljava/lang/Object;B:Ljava/lang/Object;C:Ljava/lang/Object;D:Ljava/lang/Object;E:Ljava/lang/Object;F:Ljava/lang/Object;G:Ljava/lang/Object;H:Ljava/lang/Object;I:Ljava/lang/Object;J:Ljava/lang/Object;K:Ljava/lang/Object;L:Ljava/lang/Object;M:Ljava/lang/Object;N:Ljava/lang/Object;O:Ljava/lang/Object;P:Ljava/lang/Object;Q:Ljava/lang/Object;R:Ljava/lang/Object;S:Ljava/lang/Object;>()Lshapeless/ops/hlist$Tupler<Lshapeless/$colon$colon<TA;Lshapeless/$colon$colon<TB;Lshapeless/$colon$colon<TC;Lshapeless/$colon$colon<TD;Lshapeless/$colon$colon<TE;Lshapeless/$colon$colon<TF;Lshapeless/$colon$colon<TG;Lshapeless/$colon$colon<TH;Lshapeless/$colon$colon<TI;Lshapeless/$colon$colon<TJ;Lshapeless/$colon$colon<TK;Lshapeless/$colon$colon<TL;Lshapeless/$colon$colon<TM;Lshapeless/$colon$colon<TN;Lshapeless/$colon$colon<TO;Lshapeless/$colon$colon<TP;Lshapeless/$colon$colon<TQ;Lshapeless/$colon$colon<TR;Lshapeless/$colon$colon<TS;Lshapeless/HNil;>;>;>;>;>;>;>;>;>;>;>;>;>;>;>;>;>;>;>;>;
  #179 = Methodref          #30.#69       // shapeless/ops/TuplerInstances$$anon$19."<init>":(Lshapeless/ops/TuplerInstances;)V
  #180 = Utf8               hlistTupler20$
  #181 = Utf8               hlistTupler20
  #182 = NameAndType        #181:#62      // hlistTupler20:()Lshapeless/ops/hlist$Tupler;
  #183 = InterfaceMethodref #2.#182       // shapeless/ops/TuplerInstances.hlistTupler20:()Lshapeless/ops/hlist$Tupler;
  #184 = Utf8               <A:Ljava/lang/Object;B:Ljava/lang/Object;C:Ljava/lang/Object;D:Ljava/lang/Object;E:Ljava/lang/Object;F:Ljava/lang/Object;G:Ljava/lang/Object;H:Ljava/lang/Object;I:Ljava/lang/Object;J:Ljava/lang/Object;K:Ljava/lang/Object;L:Ljava/lang/Object;M:Ljava/lang/Object;N:Ljava/lang/Object;O:Ljava/lang/Object;P:Ljava/lang/Object;Q:Ljava/lang/Object;R:Ljava/lang/Object;S:Ljava/lang/Object;T:Ljava/lang/Object;>()Lshapeless/ops/hlist$Tupler<Lshapeless/$colon$colon<TA;Lshapeless/$colon$colon<TB;Lshapeless/$colon$colon<TC;Lshapeless/$colon$colon<TD;Lshapeless/$colon$colon<TE;Lshapeless/$colon$colon<TF;Lshapeless/$colon$colon<TG;Lshapeless/$colon$colon<TH;Lshapeless/$colon$colon<TI;Lshapeless/$colon$colon<TJ;Lshapeless/$colon$colon<TK;Lshapeless/$colon$colon<TL;Lshapeless/$colon$colon<TM;Lshapeless/$colon$colon<TN;Lshapeless/$colon$colon<TO;Lshapeless/$colon$colon<TP;Lshapeless/$colon$colon<TQ;Lshapeless/$colon$colon<TR;Lshapeless/$colon$colon<TS;Lshapeless/$colon$colon<TT;Lshapeless/HNil;>;>;>;>;>;>;>;>;>;>;>;>;>;>;>;>;>;>;>;>;>;
  #185 = Methodref          #34.#69       // shapeless/ops/TuplerInstances$$anon$20."<init>":(Lshapeless/ops/TuplerInstances;)V
  #186 = Utf8               hlistTupler21$
  #187 = Utf8               hlistTupler21
  #188 = NameAndType        #187:#62      // hlistTupler21:()Lshapeless/ops/hlist$Tupler;
  #189 = InterfaceMethodref #2.#188       // shapeless/ops/TuplerInstances.hlistTupler21:()Lshapeless/ops/hlist$Tupler;
  #190 = Utf8               <A:Ljava/lang/Object;B:Ljava/lang/Object;C:Ljava/lang/Object;D:Ljava/lang/Object;E:Ljava/lang/Object;F:Ljava/lang/Object;G:Ljava/lang/Object;H:Ljava/lang/Object;I:Ljava/lang/Object;J:Ljava/lang/Object;K:Ljava/lang/Object;L:Ljava/lang/Object;M:Ljava/lang/Object;N:Ljava/lang/Object;O:Ljava/lang/Object;P:Ljava/lang/Object;Q:Ljava/lang/Object;R:Ljava/lang/Object;S:Ljava/lang/Object;T:Ljava/lang/Object;U:Ljava/lang/Object;>()Lshapeless/ops/hlist$Tupler<Lshapeless/$colon$colon<TA;Lshapeless/$colon$colon<TB;Lshapeless/$colon$colon<TC;Lshapeless/$colon$colon<TD;Lshapeless/$colon$colon<TE;Lshapeless/$colon$colon<TF;Lshapeless/$colon$colon<TG;Lshapeless/$colon$colon<TH;Lshapeless/$colon$colon<TI;Lshapeless/$colon$colon<TJ;Lshapeless/$colon$colon<TK;Lshapeless/$colon$colon<TL;Lshapeless/$colon$colon<TM;Lshapeless/$colon$colon<TN;Lshapeless/$colon$colon<TO;Lshapeless/$colon$colon<TP;Lshapeless/$colon$colon<TQ;Lshapeless/$colon$colon<TR;Lshapeless/$colon$colon<TS;Lshapeless/$colon$colon<TT;Lshapeless/$colon$colon<TU;Lshapeless/HNil;>;>;>;>;>;>;>;>;>;>;>;>;>;>;>;>;>;>;>;>;>;>;
  #191 = Methodref          #36.#69       // shapeless/ops/TuplerInstances$$anon$21."<init>":(Lshapeless/ops/TuplerInstances;)V
  #192 = Utf8               hlistTupler22$
  #193 = Utf8               hlistTupler22
  #194 = NameAndType        #193:#62      // hlistTupler22:()Lshapeless/ops/hlist$Tupler;
  #195 = InterfaceMethodref #2.#194       // shapeless/ops/TuplerInstances.hlistTupler22:()Lshapeless/ops/hlist$Tupler;
  #196 = Utf8               <A:Ljava/lang/Object;B:Ljava/lang/Object;C:Ljava/lang/Object;D:Ljava/lang/Object;E:Ljava/lang/Object;F:Ljava/lang/Object;G:Ljava/lang/Object;H:Ljava/lang/Object;I:Ljava/lang/Object;J:Ljava/lang/Object;K:Ljava/lang/Object;L:Ljava/lang/Object;M:Ljava/lang/Object;N:Ljava/lang/Object;O:Ljava/lang/Object;P:Ljava/lang/Object;Q:Ljava/lang/Object;R:Ljava/lang/Object;S:Ljava/lang/Object;T:Ljava/lang/Object;U:Ljava/lang/Object;V:Ljava/lang/Object;>()Lshapeless/ops/hlist$Tupler<Lshapeless/$colon$colon<TA;Lshapeless/$colon$colon<TB;Lshapeless/$colon$colon<TC;Lshapeless/$colon$colon<TD;Lshapeless/$colon$colon<TE;Lshapeless/$colon$colon<TF;Lshapeless/$colon$colon<TG;Lshapeless/$colon$colon<TH;Lshapeless/$colon$colon<TI;Lshapeless/$colon$colon<TJ;Lshapeless/$colon$colon<TK;Lshapeless/$colon$colon<TL;Lshapeless/$colon$colon<TM;Lshapeless/$colon$colon<TN;Lshapeless/$colon$colon<TO;Lshapeless/$colon$colon<TP;Lshapeless/$colon$colon<TQ;Lshapeless/$colon$colon<TR;Lshapeless/$colon$colon<TS;Lshapeless/$colon$colon<TT;Lshapeless/$colon$colon<TU;Lshapeless/$colon$colon<TV;Lshapeless/HNil;>;>;>;>;>;>;>;>;>;>;>;>;>;>;>;>;>;>;>;>;>;>;>;
  #197 = Methodref          #38.#69       // shapeless/ops/TuplerInstances$$anon$22."<init>":(Lshapeless/ops/TuplerInstances;)V
  #198 = Utf8               $init$
  #199 = Utf8               Code
  #200 = Utf8               LineNumberTable
  #201 = Utf8               LocalVariableTable
  #202 = Utf8               MethodParameters
  #203 = Utf8               Signature
  #204 = Utf8               InnerClasses
  #205 = Utf8               SourceFile
  #206 = Utf8               RuntimeVisibleAnnotations
  #207 = Utf8               ScalaInlineInfo
  #208 = Utf8               ScalaSig
{
  public static shapeless.ops.hlist$Tupler hlistTupler1$(shapeless.ops.TuplerInstances);
    descriptor: (Lshapeless/ops/TuplerInstances;)Lshapeless/ops/hlist$Tupler;
    flags: (0x1009) ACC_PUBLIC, ACC_STATIC, ACC_SYNTHETIC
    Code:
      stack=1, locals=1, args_size=1
         0: aload_0
         1: invokespecial #64                 // InterfaceMethod hlistTupler1:()Lshapeless/ops/hlist$Tupler;
         4: areturn
      LineNumberTable:
        line 27: 0
      LocalVariableTable:
        Start  Length  Slot  Name   Signature
            0       5     0 $this   Lshapeless/ops/TuplerInstances;
    MethodParameters:
      Name                           Flags
      $this                          final synthetic

  public default <A extends java.lang.Object> shapeless.ops.hlist$Tupler<shapeless.$colon$colon<A, shapeless.HNil>> hlistTupler1();
    descriptor: ()Lshapeless/ops/hlist$Tupler;
    flags: (0x0001) ACC_PUBLIC
    Code:
      stack=3, locals=1, args_size=1
         0: new           #10                 // class shapeless/ops/TuplerInstances$$anon$1
         3: dup
         4: aconst_null
         5: invokespecial #70                 // Method shapeless/ops/TuplerInstances$$anon$1."<init>":(Lshapeless/ops/TuplerInstances;)V
         8: areturn
      LineNumberTable:
        line 33: 0
      LocalVariableTable:
        Start  Length  Slot  Name   Signature
            0       9     0  this   Lshapeless/ops/TuplerInstances;
    Signature: #66                          // <A:Ljava/lang/Object;>()Lshapeless/ops/hlist$Tupler<Lshapeless/$colon$colon<TA;Lshapeless/HNil;>;>;

  public static shapeless.ops.hlist$Tupler hlistTupler2$(shapeless.ops.TuplerInstances);
    descriptor: (Lshapeless/ops/TuplerInstances;)Lshapeless/ops/hlist$Tupler;
    flags: (0x1009) ACC_PUBLIC, ACC_STATIC, ACC_SYNTHETIC
    Code:
      stack=1, locals=1, args_size=1
         0: aload_0
         1: invokespecial #75                 // InterfaceMethod hlistTupler2:()Lshapeless/ops/hlist$Tupler;
         4: areturn
      LineNumberTable:
        line 38: 0
      LocalVariableTable:
        Start  Length  Slot  Name   Signature
            0       5     0 $this   Lshapeless/ops/TuplerInstances;
    MethodParameters:
      Name                           Flags
      $this                          final synthetic

  public default <A extends java.lang.Object, B extends java.lang.Object> shapeless.ops.hlist$Tupler<shapeless.$colon$colon<A, shapeless.$colon$colon<B, shapeless.HNil>>> hlistTupler2();
    descriptor: ()Lshapeless/ops/hlist$Tupler;
    flags: (0x0001) ACC_PUBLIC
    Code:
      stack=3, locals=1, args_size=1
         0: new           #32                 // class shapeless/ops/TuplerInstances$$anon$2
         3: dup
         4: aconst_null
         5: invokespecial #77                 // Method shapeless/ops/TuplerInstances$$anon$2."<init>":(Lshapeless/ops/TuplerInstances;)V
         8: areturn
      LineNumberTable:
        line 44: 0
      LocalVariableTable:
        Start  Length  Slot  Name   Signature
            0       9     0  this   Lshapeless/ops/TuplerInstances;
    Signature: #76                          // <A:Ljava/lang/Object;B:Ljava/lang/Object;>()Lshapeless/ops/hlist$Tupler<Lshapeless/$colon$colon<TA;Lshapeless/$colon$colon<TB;Lshapeless/HNil;>;>;>;

  public static shapeless.ops.hlist$Tupler hlistTupler3$(shapeless.ops.TuplerInstances);
    descriptor: (Lshapeless/ops/TuplerInstances;)Lshapeless/ops/hlist$Tupler;
    flags: (0x1009) ACC_PUBLIC, ACC_STATIC, ACC_SYNTHETIC
    Code:
      stack=1, locals=1, args_size=1
         0: aload_0
         1: invokespecial #81                 // InterfaceMethod hlistTupler3:()Lshapeless/ops/hlist$Tupler;
         4: areturn
      LineNumberTable:
        line 49: 0
      LocalVariableTable:
        Start  Length  Slot  Name   Signature
            0       5     0 $this   Lshapeless/ops/TuplerInstances;
    MethodParameters:
      Name                           Flags
      $this                          final synthetic

  public default <A extends java.lang.Object, B extends java.lang.Object, C extends java.lang.Object> shapeless.ops.hlist$Tupler<shapeless.$colon$colon<A, shapeless.$colon$colon<B, shapeless.$colon$colon<C, shapeless.HNil>>>> hlistTupler3();
    descriptor: ()Lshapeless/ops/hlist$Tupler;
    flags: (0x0001) ACC_PUBLIC
    Code:
      stack=3, locals=1, args_size=1
         0: new           #40                 // class shapeless/ops/TuplerInstances$$anon$3
         3: dup
         4: aconst_null
         5: invokespecial #83                 // Method shapeless/ops/TuplerInstances$$anon$3."<init>":(Lshapeless/ops/TuplerInstances;)V
         8: areturn
      LineNumberTable:
        line 55: 0
      LocalVariableTable:
        Start  Length  Slot  Name   Signature
            0       9     0  this   Lshapeless/ops/TuplerInstances;
    Signature: #82                          // <A:Ljava/lang/Object;B:Ljava/lang/Object;C:Ljava/lang/Object;>()Lshapeless/ops/hlist$Tupler<Lshapeless/$colon$colon<TA;Lshapeless/$colon$colon<TB;Lshapeless/$colon$colon<TC;Lshapeless/HNil;>;>;>;>;

  public static shapeless.ops.hlist$Tupler hlistTupler4$(shapeless.ops.TuplerInstances);
    descriptor: (Lshapeless/ops/TuplerInstances;)Lshapeless/ops/hlist$Tupler;
    flags: (0x1009) ACC_PUBLIC, ACC_STATIC, ACC_SYNTHETIC
    Code:
      stack=1, locals=1, args_size=1
         0: aload_0
         1: invokespecial #87                 // InterfaceMethod hlistTupler4:()Lshapeless/ops/hlist$Tupler;
         4: areturn
      LineNumberTable:
        line 60: 0
      LocalVariableTable:
        Start  Length  Slot  Name   Signature
            0       5     0 $this   Lshapeless/ops/TuplerInstances;
    MethodParameters:
      Name                           Flags
      $this                          final synthetic

  public default <A extends java.lang.Object, B extends java.lang.Object, C extends java.lang.Object, D extends java.lang.Object> shapeless.ops.hlist$Tupler<shapeless.$colon$colon<A, shapeless.$colon$colon<B, shapeless.$colon$colon<C, shapeless.$colon$colon<D, shapeless.HNil>>>>> hlistTupler4();
    descriptor: ()Lshapeless/ops/hlist$Tupler;
    flags: (0x0001) ACC_PUBLIC
    Code:
      stack=3, locals=1, args_size=1
         0: new           #42                 // class shapeless/ops/TuplerInstances$$anon$4
         3: dup
         4: aconst_null
         5: invokespecial #89                 // Method shapeless/ops/TuplerInstances$$anon$4."<init>":(Lshapeless/ops/TuplerInstances;)V
         8: areturn
      LineNumberTable:
        line 66: 0
      LocalVariableTable:
        Start  Length  Slot  Name   Signature
            0       9     0  this   Lshapeless/ops/TuplerInstances;
    Signature: #88                          // <A:Ljava/lang/Object;B:Ljava/lang/Object;C:Ljava/lang/Object;D:Ljava/lang/Object;>()Lshapeless/ops/hlist$Tupler<Lshapeless/$colon$colon<TA;Lshapeless/$colon$colon<TB;Lshapeless/$colon$colon<TC;Lshapeless/$colon$colon<TD;Lshapeless/HNil;>;>;>;>;>;

  public static shapeless.ops.hlist$Tupler hlistTupler5$(shapeless.ops.TuplerInstances);
    descriptor: (Lshapeless/ops/TuplerInstances;)Lshapeless/ops/hlist$Tupler;
    flags: (0x1009) ACC_PUBLIC, ACC_STATIC, ACC_SYNTHETIC
    Code:
      stack=1, locals=1, args_size=1
         0: aload_0
         1: invokespecial #93                 // InterfaceMethod hlistTupler5:()Lshapeless/ops/hlist$Tupler;
         4: areturn
      LineNumberTable:
        line 71: 0
      LocalVariableTable:
        Start  Length  Slot  Name   Signature
            0       5     0 $this   Lshapeless/ops/TuplerInstances;
    MethodParameters:
      Name                           Flags
      $this                          final synthetic

  public default <A extends java.lang.Object, B extends java.lang.Object, C extends java.lang.Object, D extends java.lang.Object, E extends java.lang.Object> shapeless.ops.hlist$Tupler<shapeless.$colon$colon<A, shapeless.$colon$colon<B, shapeless.$colon$colon<C, shapeless.$colon$colon<D, shapeless.$colon$colon<E, shapeless.HNil>>>>>> hlistTupler5();
    descriptor: ()Lshapeless/ops/hlist$Tupler;
    flags: (0x0001) ACC_PUBLIC
    Code:
      stack=3, locals=1, args_size=1
         0: new           #44                 // class shapeless/ops/TuplerInstances$$anon$5
         3: dup
         4: aconst_null
         5: invokespecial #95                 // Method shapeless/ops/TuplerInstances$$anon$5."<init>":(Lshapeless/ops/TuplerInstances;)V
         8: areturn
      LineNumberTable:
        line 77: 0
      LocalVariableTable:
        Start  Length  Slot  Name   Signature
            0       9     0  this   Lshapeless/ops/TuplerInstances;
    Signature: #94                          // <A:Ljava/lang/Object;B:Ljava/lang/Object;C:Ljava/lang/Object;D:Ljava/lang/Object;E:Ljava/lang/Object;>()Lshapeless/ops/hlist$Tupler<Lshapeless/$colon$colon<TA;Lshapeless/$colon$colon<TB;Lshapeless/$colon$colon<TC;Lshapeless/$colon$colon<TD;Lshapeless/$colon$colon<TE;Lshapeless/HNil;>;>;>;>;>;>;

  public static shapeless.ops.hlist$Tupler hlistTupler6$(shapeless.ops.TuplerInstances);
    descriptor: (Lshapeless/ops/TuplerInstances;)Lshapeless/ops/hlist$Tupler;
    flags: (0x1009) ACC_PUBLIC, ACC_STATIC, ACC_SYNTHETIC
    Code:
      stack=1, locals=1, args_size=1
         0: aload_0
         1: invokespecial #99                 // InterfaceMethod hlistTupler6:()Lshapeless/ops/hlist$Tupler;
         4: areturn
      LineNumberTable:
        line 82: 0
      LocalVariableTable:
        Start  Length  Slot  Name   Signature
            0       5     0 $this   Lshapeless/ops/TuplerInstances;
    MethodParameters:
      Name                           Flags
      $this                          final synthetic

  public default <A extends java.lang.Object, B extends java.lang.Object, C extends java.lang.Object, D extends java.lang.Object, E extends java.lang.Object, F extends java.lang.Object> shapeless.ops.hlist$Tupler<shapeless.$colon$colon<A, shapeless.$colon$colon<B, shapeless.$colon$colon<C, shapeless.$colon$colon<D, shapeless.$colon$colon<E, shapeless.$colon$colon<F, shapeless.HNil>>>>>>> hlistTupler6();
    descriptor: ()Lshapeless/ops/hlist$Tupler;
    flags: (0x0001) ACC_PUBLIC
    Code:
      stack=3, locals=1, args_size=1
         0: new           #46                 // class shapeless/ops/TuplerInstances$$anon$6
         3: dup
         4: aconst_null
         5: invokespecial #101                // Method shapeless/ops/TuplerInstances$$anon$6."<init>":(Lshapeless/ops/TuplerInstances;)V
         8: areturn
      LineNumberTable:
        line 88: 0
      LocalVariableTable:
        Start  Length  Slot  Name   Signature
            0       9     0  this   Lshapeless/ops/TuplerInstances;
    Signature: #100                         // <A:Ljava/lang/Object;B:Ljava/lang/Object;C:Ljava/lang/Object;D:Ljava/lang/Object;E:Ljava/lang/Object;F:Ljava/lang/Object;>()Lshapeless/ops/hlist$Tupler<Lshapeless/$colon$colon<TA;Lshapeless/$colon$colon<TB;Lshapeless/$colon$colon<TC;Lshapeless/$colon$colon<TD;Lshapeless/$colon$colon<TE;Lshapeless/$colon$colon<TF;Lshapeless/HNil;>;>;>;>;>;>;>;

  public static shapeless.ops.hlist$Tupler hlistTupler7$(shapeless.ops.TuplerInstances);
    descriptor: (Lshapeless/ops/TuplerInstances;)Lshapeless/ops/hlist$Tupler;
    flags: (0x1009) ACC_PUBLIC, ACC_STATIC, ACC_SYNTHETIC
    Code:
      stack=1, locals=1, args_size=1
         0: aload_0
         1: invokespecial #105                // InterfaceMethod hlistTupler7:()Lshapeless/ops/hlist$Tupler;
         4: areturn
      LineNumberTable:
        line 93: 0
      LocalVariableTable:
        Start  Length  Slot  Name   Signature
            0       5     0 $this   Lshapeless/ops/TuplerInstances;
    MethodParameters:
      Name                           Flags
      $this                          final synthetic

  public default <A extends java.lang.Object, B extends java.lang.Object, C extends java.lang.Object, D extends java.lang.Object, E extends java.lang.Object, F extends java.lang.Object, G extends java.lang.Object> shapeless.ops.hlist$Tupler<shapeless.$colon$colon<A, shapeless.$colon$colon<B, shapeless.$colon$colon<C, shapeless.$colon$colon<D, shapeless.$colon$colon<E, shapeless.$colon$colon<F, shapeless.$colon$colon<G, shapeless.HNil>>>>>>>> hlistTupler7();
    descriptor: ()Lshapeless/ops/hlist$Tupler;
    flags: (0x0001) ACC_PUBLIC
    Code:
      stack=3, locals=1, args_size=1
         0: new           #48                 // class shapeless/ops/TuplerInstances$$anon$7
         3: dup
         4: aconst_null
         5: invokespecial #107                // Method shapeless/ops/TuplerInstances$$anon$7."<init>":(Lshapeless/ops/TuplerInstances;)V
         8: areturn
      LineNumberTable:
        line 99: 0
      LocalVariableTable:
        Start  Length  Slot  Name   Signature
            0       9     0  this   Lshapeless/ops/TuplerInstances;
    Signature: #106                         // <A:Ljava/lang/Object;B:Ljava/lang/Object;C:Ljava/lang/Object;D:Ljava/lang/Object;E:Ljava/lang/Object;F:Ljava/lang/Object;G:Ljava/lang/Object;>()Lshapeless/ops/hlist$Tupler<Lshapeless/$colon$colon<TA;Lshapeless/$colon$colon<TB;Lshapeless/$colon$colon<TC;Lshapeless/$colon$colon<TD;Lshapeless/$colon$colon<TE;Lshapeless/$colon$colon<TF;Lshapeless/$colon$colon<TG;Lshapeless/HNil;>;>;>;>;>;>;>;>;

  public static shapeless.ops.hlist$Tupler hlistTupler8$(shapeless.ops.TuplerInstances);
    descriptor: (Lshapeless/ops/TuplerInstances;)Lshapeless/ops/hlist$Tupler;
    flags: (0x1009) ACC_PUBLIC, ACC_STATIC, ACC_SYNTHETIC
    Code:
      stack=1, locals=1, args_size=1
         0: aload_0
         1: invokespecial #111                // InterfaceMethod hlistTupler8:()Lshapeless/ops/hlist$Tupler;
         4: areturn
      LineNumberTable:
        line 104: 0
      LocalVariableTable:
        Start  Length  Slot  Name   Signature
            0       5     0 $this   Lshapeless/ops/TuplerInstances;
    MethodParameters:
      Name                           Flags
      $this                          final synthetic

  public default <A extends java.lang.Object, B extends java.lang.Object, C extends java.lang.Object, D extends java.lang.Object, E extends java.lang.Object, F extends java.lang.Object, G extends java.lang.Object, H extends java.lang.Object> shapeless.ops.hlist$Tupler<shapeless.$colon$colon<A, shapeless.$colon$colon<B, shapeless.$colon$colon<C, shapeless.$colon$colon<D, shapeless.$colon$colon<E, shapeless.$colon$colon<F, shapeless.$colon$colon<G, shapeless.$colon$colon<H, shapeless.HNil>>>>>>>>> hlistTupler8();
    descriptor: ()Lshapeless/ops/hlist$Tupler;
    flags: (0x0001) ACC_PUBLIC
    Code:
      stack=3, locals=1, args_size=1
         0: new           #50                 // class shapeless/ops/TuplerInstances$$anon$8
         3: dup
         4: aconst_null
         5: invokespecial #113                // Method shapeless/ops/TuplerInstances$$anon$8."<init>":(Lshapeless/ops/TuplerInstances;)V
         8: areturn
      LineNumberTable:
        line 110: 0
      LocalVariableTable:
        Start  Length  Slot  Name   Signature
            0       9     0  this   Lshapeless/ops/TuplerInstances;
    Signature: #112                         // <A:Ljava/lang/Object;B:Ljava/lang/Object;C:Ljava/lang/Object;D:Ljava/lang/Object;E:Ljava/lang/Object;F:Ljava/lang/Object;G:Ljava/lang/Object;H:Ljava/lang/Object;>()Lshapeless/ops/hlist$Tupler<Lshapeless/$colon$colon<TA;Lshapeless/$colon$colon<TB;Lshapeless/$colon$colon<TC;Lshapeless/$colon$colon<TD;Lshapeless/$colon$colon<TE;Lshapeless/$colon$colon<TF;Lshapeless/$colon$colon<TG;Lshapeless/$colon$colon<TH;Lshapeless/HNil;>;>;>;>;>;>;>;>;>;

  public static shapeless.ops.hlist$Tupler hlistTupler9$(shapeless.ops.TuplerInstances);
    descriptor: (Lshapeless/ops/TuplerInstances;)Lshapeless/ops/hlist$Tupler;
    flags: (0x1009) ACC_PUBLIC, ACC_STATIC, ACC_SYNTHETIC
    Code:
      stack=1, locals=1, args_size=1
         0: aload_0
         1: invokespecial #117                // InterfaceMethod hlistTupler9:()Lshapeless/ops/hlist$Tupler;
         4: areturn
      LineNumberTable:
        line 115: 0
      LocalVariableTable:
        Start  Length  Slot  Name   Signature
            0       5     0 $this   Lshapeless/ops/TuplerInstances;
    MethodParameters:
      Name                           Flags
      $this                          final synthetic

  public default <A extends java.lang.Object, B extends java.lang.Object, C extends java.lang.Object, D extends java.lang.Object, E extends java.lang.Object, F extends java.lang.Object, G extends java.lang.Object, H extends java.lang.Object, I extends java.lang.Object> shapeless.ops.hlist$Tupler<shapeless.$colon$colon<A, shapeless.$colon$colon<B, shapeless.$colon$colon<C, shapeless.$colon$colon<D, shapeless.$colon$colon<E, shapeless.$colon$colon<F, shapeless.$colon$colon<G, shapeless.$colon$colon<H, shapeless.$colon$colon<I, shapeless.HNil>>>>>>>>>> hlistTupler9();
    descriptor: ()Lshapeless/ops/hlist$Tupler;
    flags: (0x0001) ACC_PUBLIC
    Code:
      stack=3, locals=1, args_size=1
         0: new           #52                 // class shapeless/ops/TuplerInstances$$anon$9
         3: dup
         4: aconst_null
         5: invokespecial #119                // Method shapeless/ops/TuplerInstances$$anon$9."<init>":(Lshapeless/ops/TuplerInstances;)V
         8: areturn
      LineNumberTable:
        line 121: 0
      LocalVariableTable:
        Start  Length  Slot  Name   Signature
            0       9     0  this   Lshapeless/ops/TuplerInstances;
    Signature: #118                         // <A:Ljava/lang/Object;B:Ljava/lang/Object;C:Ljava/lang/Object;D:Ljava/lang/Object;E:Ljava/lang/Object;F:Ljava/lang/Object;G:Ljava/lang/Object;H:Ljava/lang/Object;I:Ljava/lang/Object;>()Lshapeless/ops/hlist$Tupler<Lshapeless/$colon$colon<TA;Lshapeless/$colon$colon<TB;Lshapeless/$colon$colon<TC;Lshapeless/$colon$colon<TD;Lshapeless/$colon$colon<TE;Lshapeless/$colon$colon<TF;Lshapeless/$colon$colon<TG;Lshapeless/$colon$colon<TH;Lshapeless/$colon$colon<TI;Lshapeless/HNil;>;>;>;>;>;>;>;>;>;>;

  public static shapeless.ops.hlist$Tupler hlistTupler10$(shapeless.ops.TuplerInstances);
    descriptor: (Lshapeless/ops/TuplerInstances;)Lshapeless/ops/hlist$Tupler;
    flags: (0x1009) ACC_PUBLIC, ACC_STATIC, ACC_SYNTHETIC
    Code:
      stack=1, locals=1, args_size=1
         0: aload_0
         1: invokespecial #123                // InterfaceMethod hlistTupler10:()Lshapeless/ops/hlist$Tupler;
         4: areturn
      LineNumberTable:
        line 126: 0
      LocalVariableTable:
        Start  Length  Slot  Name   Signature
            0       5     0 $this   Lshapeless/ops/TuplerInstances;
    MethodParameters:
      Name                           Flags
      $this                          final synthetic

  public default <A extends java.lang.Object, B extends java.lang.Object, C extends java.lang.Object, D extends java.lang.Object, E extends java.lang.Object, F extends java.lang.Object, G extends java.lang.Object, H extends java.lang.Object, I extends java.lang.Object, J extends java.lang.Object> shapeless.ops.hlist$Tupler<shapeless.$colon$colon<A, shapeless.$colon$colon<B, shapeless.$colon$colon<C, shapeless.$colon$colon<D, shapeless.$colon$colon<E, shapeless.$colon$colon<F, shapeless.$colon$colon<G, shapeless.$colon$colon<H, shapeless.$colon$colon<I, shapeless.$colon$colon<J, shapeless.HNil>>>>>>>>>>> hlistTupler10();
    descriptor: ()Lshapeless/ops/hlist$Tupler;
    flags: (0x0001) ACC_PUBLIC
    Code:
      stack=3, locals=1, args_size=1
         0: new           #12                 // class shapeless/ops/TuplerInstances$$anon$10
         3: dup
         4: aconst_null
         5: invokespecial #125                // Method shapeless/ops/TuplerInstances$$anon$10."<init>":(Lshapeless/ops/TuplerInstances;)V
         8: areturn
      LineNumberTable:
        line 132: 0
      LocalVariableTable:
        Start  Length  Slot  Name   Signature
            0       9     0  this   Lshapeless/ops/TuplerInstances;
    Signature: #124                         // <A:Ljava/lang/Object;B:Ljava/lang/Object;C:Ljava/lang/Object;D:Ljava/lang/Object;E:Ljava/lang/Object;F:Ljava/lang/Object;G:Ljava/lang/Object;H:Ljava/lang/Object;I:Ljava/lang/Object;J:Ljava/lang/Object;>()Lshapeless/ops/hlist$Tupler<Lshapeless/$colon$colon<TA;Lshapeless/$colon$colon<TB;Lshapeless/$colon$colon<TC;Lshapeless/$colon$colon<TD;Lshapeless/$colon$colon<TE;Lshapeless/$colon$colon<TF;Lshapeless/$colon$colon<TG;Lshapeless/$colon$colon<TH;Lshapeless/$colon$colon<TI;Lshapeless/$colon$colon<TJ;Lshapeless/HNil;>;>;>;>;>;>;>;>;>;>;>;

  public static shapeless.ops.hlist$Tupler hlistTupler11$(shapeless.ops.TuplerInstances);
    descriptor: (Lshapeless/ops/TuplerInstances;)Lshapeless/ops/hlist$Tupler;
    flags: (0x1009) ACC_PUBLIC, ACC_STATIC, ACC_SYNTHETIC
    Code:
      stack=1, locals=1, args_size=1
         0: aload_0
         1: invokespecial #129                // InterfaceMethod hlistTupler11:()Lshapeless/ops/hlist$Tupler;
         4: areturn
      LineNumberTable:
        line 137: 0
      LocalVariableTable:
        Start  Length  Slot  Name   Signature
            0       5     0 $this   Lshapeless/ops/TuplerInstances;
    MethodParameters:
      Name                           Flags
      $this                          final synthetic

  public default <A extends java.lang.Object, B extends java.lang.Object, C extends java.lang.Object, D extends java.lang.Object, E extends java.lang.Object, F extends java.lang.Object, G extends java.lang.Object, H extends java.lang.Object, I extends java.lang.Object, J extends java.lang.Object, K extends java.lang.Object> shapeless.ops.hlist$Tupler<shapeless.$colon$colon<A, shapeless.$colon$colon<B, shapeless.$colon$colon<C, shapeless.$colon$colon<D, shapeless.$colon$colon<E, shapeless.$colon$colon<F, shapeless.$colon$colon<G, shapeless.$colon$colon<H, shapeless.$colon$colon<I, shapeless.$colon$colon<J, shapeless.$colon$colon<K, shapeless.HNil>>>>>>>>>>>> hlistTupler11();
    descriptor: ()Lshapeless/ops/hlist$Tupler;
    flags: (0x0001) ACC_PUBLIC
    Code:
      stack=3, locals=1, args_size=1
         0: new           #14                 // class shapeless/ops/TuplerInstances$$anon$11
         3: dup
         4: aconst_null
         5: invokespecial #131                // Method shapeless/ops/TuplerInstances$$anon$11."<init>":(Lshapeless/ops/TuplerInstances;)V
         8: areturn
      LineNumberTable:
        line 143: 0
      LocalVariableTable:
        Start  Length  Slot  Name   Signature
            0       9     0  this   Lshapeless/ops/TuplerInstances;
    Signature: #130                         // <A:Ljava/lang/Object;B:Ljava/lang/Object;C:Ljava/lang/Object;D:Ljava/lang/Object;E:Ljava/lang/Object;F:Ljava/lang/Object;G:Ljava/lang/Object;H:Ljava/lang/Object;I:Ljava/lang/Object;J:Ljava/lang/Object;K:Ljava/lang/Object;>()Lshapeless/ops/hlist$Tupler<Lshapeless/$colon$colon<TA;Lshapeless/$colon$colon<TB;Lshapeless/$colon$colon<TC;Lshapeless/$colon$colon<TD;Lshapeless/$colon$colon<TE;Lshapeless/$colon$colon<TF;Lshapeless/$colon$colon<TG;Lshapeless/$colon$colon<TH;Lshapeless/$colon$colon<TI;Lshapeless/$colon$colon<TJ;Lshapeless/$colon$colon<TK;Lshapeless/HNil;>;>;>;>;>;>;>;>;>;>;>;>;

  public static shapeless.ops.hlist$Tupler hlistTupler12$(shapeless.ops.TuplerInstances);
    descriptor: (Lshapeless/ops/TuplerInstances;)Lshapeless/ops/hlist$Tupler;
    flags: (0x1009) ACC_PUBLIC, ACC_STATIC, ACC_SYNTHETIC
    Code:
      stack=1, locals=1, args_size=1
         0: aload_0
         1: invokespecial #135                // InterfaceMethod hlistTupler12:()Lshapeless/ops/hlist$Tupler;
         4: areturn
      LineNumberTable:
        line 148: 0
      LocalVariableTable:
        Start  Length  Slot  Name   Signature
            0       5     0 $this   Lshapeless/ops/TuplerInstances;
    MethodParameters:
      Name                           Flags
      $this                          final synthetic

  public default <A extends java.lang.Object, B extends java.lang.Object, C extends java.lang.Object, D extends java.lang.Object, E extends java.lang.Object, F extends java.lang.Object, G extends java.lang.Object, H extends java.lang.Object, I extends java.lang.Object, J extends java.lang.Object, K extends java.lang.Object, L extends java.lang.Object> shapeless.ops.hlist$Tupler<shapeless.$colon$colon<A, shapeless.$colon$colon<B, shapeless.$colon$colon<C, shapeless.$colon$colon<D, shapeless.$colon$colon<E, shapeless.$colon$colon<F, shapeless.$colon$colon<G, shapeless.$colon$colon<H, shapeless.$colon$colon<I, shapeless.$colon$colon<J, shapeless.$colon$colon<K, shapeless.$colon$colon<L, shapeless.HNil>>>>>>>>>>>>> hlistTupler12();
    descriptor: ()Lshapeless/ops/hlist$Tupler;
    flags: (0x0001) ACC_PUBLIC
    Code:
      stack=3, locals=1, args_size=1
         0: new           #16                 // class shapeless/ops/TuplerInstances$$anon$12
         3: dup
         4: aconst_null
         5: invokespecial #137                // Method shapeless/ops/TuplerInstances$$anon$12."<init>":(Lshapeless/ops/TuplerInstances;)V
         8: areturn
      LineNumberTable:
        line 154: 0
      LocalVariableTable:
        Start  Length  Slot  Name   Signature
            0       9     0  this   Lshapeless/ops/TuplerInstances;
    Signature: #136                         // <A:Ljava/lang/Object;B:Ljava/lang/Object;C:Ljava/lang/Object;D:Ljava/lang/Object;E:Ljava/lang/Object;F:Ljava/lang/Object;G:Ljava/lang/Object;H:Ljava/lang/Object;I:Ljava/lang/Object;J:Ljava/lang/Object;K:Ljava/lang/Object;L:Ljava/lang/Object;>()Lshapeless/ops/hlist$Tupler<Lshapeless/$colon$colon<TA;Lshapeless/$colon$colon<TB;Lshapeless/$colon$colon<TC;Lshapeless/$colon$colon<TD;Lshapeless/$colon$colon<TE;Lshapeless/$colon$colon<TF;Lshapeless/$colon$colon<TG;Lshapeless/$colon$colon<TH;Lshapeless/$colon$colon<TI;Lshapeless/$colon$colon<TJ;Lshapeless/$colon$colon<TK;Lshapeless/$colon$colon<TL;Lshapeless/HNil;>;>;>;>;>;>;>;>;>;>;>;>;>;

  public static shapeless.ops.hlist$Tupler hlistTupler13$(shapeless.ops.TuplerInstances);
    descriptor: (Lshapeless/ops/TuplerInstances;)Lshapeless/ops/hlist$Tupler;
    flags: (0x1009) ACC_PUBLIC, ACC_STATIC, ACC_SYNTHETIC
    Code:
      stack=1, locals=1, args_size=1
         0: aload_0
         1: invokespecial #141                // InterfaceMethod hlistTupler13:()Lshapeless/ops/hlist$Tupler;
         4: areturn
      LineNumberTable:
        line 159: 0
      LocalVariableTable:
        Start  Length  Slot  Name   Signature
            0       5     0 $this   Lshapeless/ops/TuplerInstances;
    MethodParameters:
      Name                           Flags
      $this                          final synthetic

  public default <A extends java.lang.Object, B extends java.lang.Object, C extends java.lang.Object, D extends java.lang.Object, E extends java.lang.Object, F extends java.lang.Object, G extends java.lang.Object, H extends java.lang.Object, I extends java.lang.Object, J extends java.lang.Object, K extends java.lang.Object, L extends java.lang.Object, M extends java.lang.Object> shapeless.ops.hlist$Tupler<shapeless.$colon$colon<A, shapeless.$colon$colon<B, shapeless.$colon$colon<C, shapeless.$colon$colon<D, shapeless.$colon$colon<E, shapeless.$colon$colon<F, shapeless.$colon$colon<G, shapeless.$colon$colon<H, shapeless.$colon$colon<I, shapeless.$colon$colon<J, shapeless.$colon$colon<K, shapeless.$colon$colon<L, shapeless.$colon$colon<M, shapeless.HNil>>>>>>>>>>>>>> hlistTupler13();
    descriptor: ()Lshapeless/ops/hlist$Tupler;
    flags: (0x0001) ACC_PUBLIC
    Code:
      stack=3, locals=1, args_size=1
         0: new           #18                 // class shapeless/ops/TuplerInstances$$anon$13
         3: dup
         4: aconst_null
         5: invokespecial #143                // Method shapeless/ops/TuplerInstances$$anon$13."<init>":(Lshapeless/ops/TuplerInstances;)V
         8: areturn
      LineNumberTable:
        line 165: 0
      LocalVariableTable:
        Start  Length  Slot  Name   Signature
            0       9     0  this   Lshapeless/ops/TuplerInstances;
    Signature: #142                         // <A:Ljava/lang/Object;B:Ljava/lang/Object;C:Ljava/lang/Object;D:Ljava/lang/Object;E:Ljava/lang/Object;F:Ljava/lang/Object;G:Ljava/lang/Object;H:Ljava/lang/Object;I:Ljava/lang/Object;J:Ljava/lang/Object;K:Ljava/lang/Object;L:Ljava/lang/Object;M:Ljava/lang/Object;>()Lshapeless/ops/hlist$Tupler<Lshapeless/$colon$colon<TA;Lshapeless/$colon$colon<TB;Lshapeless/$colon$colon<TC;Lshapeless/$colon$colon<TD;Lshapeless/$colon$colon<TE;Lshapeless/$colon$colon<TF;Lshapeless/$colon$colon<TG;Lshapeless/$colon$colon<TH;Lshapeless/$colon$colon<TI;Lshapeless/$colon$colon<TJ;Lshapeless/$colon$colon<TK;Lshapeless/$colon$colon<TL;Lshapeless/$colon$colon<TM;Lshapeless/HNil;>;>;>;>;>;>;>;>;>;>;>;>;>;>;

  public static shapeless.ops.hlist$Tupler hlistTupler14$(shapeless.ops.TuplerInstances);
    descriptor: (Lshapeless/ops/TuplerInstances;)Lshapeless/ops/hlist$Tupler;
    flags: (0x1009) ACC_PUBLIC, ACC_STATIC, ACC_SYNTHETIC
    Code:
      stack=1, locals=1, args_size=1
         0: aload_0
         1: invokespecial #147                // InterfaceMethod hlistTupler14:()Lshapeless/ops/hlist$Tupler;
         4: areturn
      LineNumberTable:
        line 170: 0
      LocalVariableTable:
        Start  Length  Slot  Name   Signature
            0       5     0 $this   Lshapeless/ops/TuplerInstances;
    MethodParameters:
      Name                           Flags
      $this                          final synthetic

  public default <A extends java.lang.Object, B extends java.lang.Object, C extends java.lang.Object, D extends java.lang.Object, E extends java.lang.Object, F extends java.lang.Object, G extends java.lang.Object, H extends java.lang.Object, I extends java.lang.Object, J extends java.lang.Object, K extends java.lang.Object, L extends java.lang.Object, M extends java.lang.Object, N extends java.lang.Object> shapeless.ops.hlist$Tupler<shapeless.$colon$colon<A, shapeless.$colon$colon<B, shapeless.$colon$colon<C, shapeless.$colon$colon<D, shapeless.$colon$colon<E, shapeless.$colon$colon<F, shapeless.$colon$colon<G, shapeless.$colon$colon<H, shapeless.$colon$colon<I, shapeless.$colon$colon<J, shapeless.$colon$colon<K, shapeless.$colon$colon<L, shapeless.$colon$colon<M, shapeless.$colon$colon<N, shapeless.HNil>>>>>>>>>>>>>>> hlistTupler14();
    descriptor: ()Lshapeless/ops/hlist$Tupler;
    flags: (0x0001) ACC_PUBLIC
    Code:
      stack=3, locals=1, args_size=1
         0: new           #20                 // class shapeless/ops/TuplerInstances$$anon$14
         3: dup
         4: aconst_null
         5: invokespecial #149                // Method shapeless/ops/TuplerInstances$$anon$14."<init>":(Lshapeless/ops/TuplerInstances;)V
         8: areturn
      LineNumberTable:
        line 176: 0
      LocalVariableTable:
        Start  Length  Slot  Name   Signature
            0       9     0  this   Lshapeless/ops/TuplerInstances;
    Signature: #148                         // <A:Ljava/lang/Object;B:Ljava/lang/Object;C:Ljava/lang/Object;D:Ljava/lang/Object;E:Ljava/lang/Object;F:Ljava/lang/Object;G:Ljava/lang/Object;H:Ljava/lang/Object;I:Ljava/lang/Object;J:Ljava/lang/Object;K:Ljava/lang/Object;L:Ljava/lang/Object;M:Ljava/lang/Object;N:Ljava/lang/Object;>()Lshapeless/ops/hlist$Tupler<Lshapeless/$colon$colon<TA;Lshapeless/$colon$colon<TB;Lshapeless/$colon$colon<TC;Lshapeless/$colon$colon<TD;Lshapeless/$colon$colon<TE;Lshapeless/$colon$colon<TF;Lshapeless/$colon$colon<TG;Lshapeless/$colon$colon<TH;Lshapeless/$colon$colon<TI;Lshapeless/$colon$colon<TJ;Lshapeless/$colon$colon<TK;Lshapeless/$colon$colon<TL;Lshapeless/$colon$colon<TM;Lshapeless/$colon$colon<TN;Lshapeless/HNil;>;>;>;>;>;>;>;>;>;>;>;>;>;>;>;

  public static shapeless.ops.hlist$Tupler hlistTupler15$(shapeless.ops.TuplerInstances);
    descriptor: (Lshapeless/ops/TuplerInstances;)Lshapeless/ops/hlist$Tupler;
    flags: (0x1009) ACC_PUBLIC, ACC_STATIC, ACC_SYNTHETIC
    Code:
      stack=1, locals=1, args_size=1
         0: aload_0
         1: invokespecial #153                // InterfaceMethod hlistTupler15:()Lshapeless/ops/hlist$Tupler;
         4: areturn
      LineNumberTable:
        line 181: 0
      LocalVariableTable:
        Start  Length  Slot  Name   Signature
            0       5     0 $this   Lshapeless/ops/TuplerInstances;
    MethodParameters:
      Name                           Flags
      $this                          final synthetic

  public default <A extends java.lang.Object, B extends java.lang.Object, C extends java.lang.Object, D extends java.lang.Object, E extends java.lang.Object, F extends java.lang.Object, G extends java.lang.Object, H extends java.lang.Object, I extends java.lang.Object, J extends java.lang.Object, K extends java.lang.Object, L extends java.lang.Object, M extends java.lang.Object, N extends java.lang.Object, O extends java.lang.Object> shapeless.ops.hlist$Tupler<shapeless.$colon$colon<A, shapeless.$colon$colon<B, shapeless.$colon$colon<C, shapeless.$colon$colon<D, shapeless.$colon$colon<E, shapeless.$colon$colon<F, shapeless.$colon$colon<G, shapeless.$colon$colon<H, shapeless.$colon$colon<I, shapeless.$colon$colon<J, shapeless.$colon$colon<K, shapeless.$colon$colon<L, shapeless.$colon$colon<M, shapeless.$colon$colon<N, shapeless.$colon$colon<O, shapeless.HNil>>>>>>>>>>>>>>>> hlistTupler15();
    descriptor: ()Lshapeless/ops/hlist$Tupler;
    flags: (0x0001) ACC_PUBLIC
    Code:
      stack=3, locals=1, args_size=1
         0: new           #22                 // class shapeless/ops/TuplerInstances$$anon$15
         3: dup
         4: aconst_null
         5: invokespecial #155                // Method shapeless/ops/TuplerInstances$$anon$15."<init>":(Lshapeless/ops/TuplerInstances;)V
         8: areturn
      LineNumberTable:
        line 187: 0
      LocalVariableTable:
        Start  Length  Slot  Name   Signature
            0       9     0  this   Lshapeless/ops/TuplerInstances;
    Signature: #154                         // <A:Ljava/lang/Object;B:Ljava/lang/Object;C:Ljava/lang/Object;D:Ljava/lang/Object;E:Ljava/lang/Object;F:Ljava/lang/Object;G:Ljava/lang/Object;H:Ljava/lang/Object;I:Ljava/lang/Object;J:Ljava/lang/Object;K:Ljava/lang/Object;L:Ljava/lang/Object;M:Ljava/lang/Object;N:Ljava/lang/Object;O:Ljava/lang/Object;>()Lshapeless/ops/hlist$Tupler<Lshapeless/$colon$colon<TA;Lshapeless/$colon$colon<TB;Lshapeless/$colon$colon<TC;Lshapeless/$colon$colon<TD;Lshapeless/$colon$colon<TE;Lshapeless/$colon$colon<TF;Lshapeless/$colon$colon<TG;Lshapeless/$colon$colon<TH;Lshapeless/$colon$colon<TI;Lshapeless/$colon$colon<TJ;Lshapeless/$colon$colon<TK;Lshapeless/$colon$colon<TL;Lshapeless/$colon$colon<TM;Lshapeless/$colon$colon<TN;Lshapeless/$colon$colon<TO;Lshapeless/HNil;>;>;>;>;>;>;>;>;>;>;>;>;>;>;>;>;

  public static shapeless.ops.hlist$Tupler hlistTupler16$(shapeless.ops.TuplerInstances);
    descriptor: (Lshapeless/ops/TuplerInstances;)Lshapeless/ops/hlist$Tupler;
    flags: (0x1009) ACC_PUBLIC, ACC_STATIC, ACC_SYNTHETIC
    Code:
      stack=1, locals=1, args_size=1
         0: aload_0
         1: invokespecial #159                // InterfaceMethod hlistTupler16:()Lshapeless/ops/hlist$Tupler;
         4: areturn
      LineNumberTable:
        line 192: 0
      LocalVariableTable:
        Start  Length  Slot  Name   Signature
            0       5     0 $this   Lshapeless/ops/TuplerInstances;
    MethodParameters:
      Name                           Flags
      $this                          final synthetic

  public default <A extends java.lang.Object, B extends java.lang.Object, C extends java.lang.Object, D extends java.lang.Object, E extends java.lang.Object, F extends java.lang.Object, G extends java.lang.Object, H extends java.lang.Object, I extends java.lang.Object, J extends java.lang.Object, K extends java.lang.Object, L extends java.lang.Object, M extends java.lang.Object, N extends java.lang.Object, O extends java.lang.Object, P extends java.lang.Object> shapeless.ops.hlist$Tupler<shapeless.$colon$colon<A, shapeless.$colon$colon<B, shapeless.$colon$colon<C, shapeless.$colon$colon<D, shapeless.$colon$colon<E, shapeless.$colon$colon<F, shapeless.$colon$colon<G, shapeless.$colon$colon<H, shapeless.$colon$colon<I, shapeless.$colon$colon<J, shapeless.$colon$colon<K, shapeless.$colon$colon<L, shapeless.$colon$colon<M, shapeless.$colon$colon<N, shapeless.$colon$colon<O, shapeless.$colon$colon<P, shapeless.HNil>>>>>>>>>>>>>>>>> hlistTupler16();
    descriptor: ()Lshapeless/ops/hlist$Tupler;
    flags: (0x0001) ACC_PUBLIC
    Code:
      stack=3, locals=1, args_size=1
         0: new           #24                 // class shapeless/ops/TuplerInstances$$anon$16
         3: dup
         4: aconst_null
         5: invokespecial #161                // Method shapeless/ops/TuplerInstances$$anon$16."<init>":(Lshapeless/ops/TuplerInstances;)V
         8: areturn
      LineNumberTable:
        line 198: 0
      LocalVariableTable:
        Start  Length  Slot  Name   Signature
            0       9     0  this   Lshapeless/ops/TuplerInstances;
    Signature: #160                         // <A:Ljava/lang/Object;B:Ljava/lang/Object;C:Ljava/lang/Object;D:Ljava/lang/Object;E:Ljava/lang/Object;F:Ljava/lang/Object;G:Ljava/lang/Object;H:Ljava/lang/Object;I:Ljava/lang/Object;J:Ljava/lang/Object;K:Ljava/lang/Object;L:Ljava/lang/Object;M:Ljava/lang/Object;N:Ljava/lang/Object;O:Ljava/lang/Object;P:Ljava/lang/Object;>()Lshapeless/ops/hlist$Tupler<Lshapeless/$colon$colon<TA;Lshapeless/$colon$colon<TB;Lshapeless/$colon$colon<TC;Lshapeless/$colon$colon<TD;Lshapeless/$colon$colon<TE;Lshapeless/$colon$colon<TF;Lshapeless/$colon$colon<TG;Lshapeless/$colon$colon<TH;Lshapeless/$colon$colon<TI;Lshapeless/$colon$colon<TJ;Lshapeless/$colon$colon<TK;Lshapeless/$colon$colon<TL;Lshapeless/$colon$colon<TM;Lshapeless/$colon$colon<TN;Lshapeless/$colon$colon<TO;Lshapeless/$colon$colon<TP;Lshapeless/HNil;>;>;>;>;>;>;>;>;>;>;>;>;>;>;>;>;>;

  public static shapeless.ops.hlist$Tupler hlistTupler17$(shapeless.ops.TuplerInstances);
    descriptor: (Lshapeless/ops/TuplerInstances;)Lshapeless/ops/hlist$Tupler;
    flags: (0x1009) ACC_PUBLIC, ACC_STATIC, ACC_SYNTHETIC
    Code:
      stack=1, locals=1, args_size=1
         0: aload_0
         1: invokespecial #165                // InterfaceMethod hlistTupler17:()Lshapeless/ops/hlist$Tupler;
         4: areturn
      LineNumberTable:
        line 203: 0
      LocalVariableTable:
        Start  Length  Slot  Name   Signature
            0       5     0 $this   Lshapeless/ops/TuplerInstances;
    MethodParameters:
      Name                           Flags
      $this                          final synthetic

  public default <A extends java.lang.Object, B extends java.lang.Object, C extends java.lang.Object, D extends java.lang.Object, E extends java.lang.Object, F extends java.lang.Object, G extends java.lang.Object, H extends java.lang.Object, I extends java.lang.Object, J extends java.lang.Object, K extends java.lang.Object, L extends java.lang.Object, M extends java.lang.Object, N extends java.lang.Object, O extends java.lang.Object, P extends java.lang.Object, Q extends java.lang.Object> shapeless.ops.hlist$Tupler<shapeless.$colon$colon<A, shapeless.$colon$colon<B, shapeless.$colon$colon<C, shapeless.$colon$colon<D, shapeless.$colon$colon<E, shapeless.$colon$colon<F, shapeless.$colon$colon<G, shapeless.$colon$colon<H, shapeless.$colon$colon<I, shapeless.$colon$colon<J, shapeless.$colon$colon<K, shapeless.$colon$colon<L, shapeless.$colon$colon<M, shapeless.$colon$colon<N, shapeless.$colon$colon<O, shapeless.$colon$colon<P, shapeless.$colon$colon<Q, shapeless.HNil>>>>>>>>>>>>>>>>>> hlistTupler17();
    descriptor: ()Lshapeless/ops/hlist$Tupler;
    flags: (0x0001) ACC_PUBLIC
    Code:
      stack=3, locals=1, args_size=1
         0: new           #26                 // class shapeless/ops/TuplerInstances$$anon$17
         3: dup
         4: aconst_null
         5: invokespecial #167                // Method shapeless/ops/TuplerInstances$$anon$17."<init>":(Lshapeless/ops/TuplerInstances;)V
         8: areturn
      LineNumberTable:
        line 209: 0
      LocalVariableTable:
        Start  Length  Slot  Name   Signature
            0       9     0  this   Lshapeless/ops/TuplerInstances;
    Signature: #166                         // <A:Ljava/lang/Object;B:Ljava/lang/Object;C:Ljava/lang/Object;D:Ljava/lang/Object;E:Ljava/lang/Object;F:Ljava/lang/Object;G:Ljava/lang/Object;H:Ljava/lang/Object;I:Ljava/lang/Object;J:Ljava/lang/Object;K:Ljava/lang/Object;L:Ljava/lang/Object;M:Ljava/lang/Object;N:Ljava/lang/Object;O:Ljava/lang/Object;P:Ljava/lang/Object;Q:Ljava/lang/Object;>()Lshapeless/ops/hlist$Tupler<Lshapeless/$colon$colon<TA;Lshapeless/$colon$colon<TB;Lshapeless/$colon$colon<TC;Lshapeless/$colon$colon<TD;Lshapeless/$colon$colon<TE;Lshapeless/$colon$colon<TF;Lshapeless/$colon$colon<TG;Lshapeless/$colon$colon<TH;Lshapeless/$colon$colon<TI;Lshapeless/$colon$colon<TJ;Lshapeless/$colon$colon<TK;Lshapeless/$colon$colon<TL;Lshapeless/$colon$colon<TM;Lshapeless/$colon$colon<TN;Lshapeless/$colon$colon<TO;Lshapeless/$colon$colon<TP;Lshapeless/$colon$colon<TQ;Lshapeless/HNil;>;>;>;>;>;>;>;>;>;>;>;>;>;>;>;>;>;>;

  public static shapeless.ops.hlist$Tupler hlistTupler18$(shapeless.ops.TuplerInstances);
    descriptor: (Lshapeless/ops/TuplerInstances;)Lshapeless/ops/hlist$Tupler;
    flags: (0x1009) ACC_PUBLIC, ACC_STATIC, ACC_SYNTHETIC
    Code:
      stack=1, locals=1, args_size=1
         0: aload_0
         1: invokespecial #171                // InterfaceMethod hlistTupler18:()Lshapeless/ops/hlist$Tupler;
         4: areturn
      LineNumberTable:
        line 214: 0
      LocalVariableTable:
        Start  Length  Slot  Name   Signature
            0       5     0 $this   Lshapeless/ops/TuplerInstances;
    MethodParameters:
      Name                           Flags
      $this                          final synthetic

  public default <A extends java.lang.Object, B extends java.lang.Object, C extends java.lang.Object, D extends java.lang.Object, E extends java.lang.Object, F extends java.lang.Object, G extends java.lang.Object, H extends java.lang.Object, I extends java.lang.Object, J extends java.lang.Object, K extends java.lang.Object, L extends java.lang.Object, M extends java.lang.Object, N extends java.lang.Object, O extends java.lang.Object, P extends java.lang.Object, Q extends java.lang.Object, R extends java.lang.Object> shapeless.ops.hlist$Tupler<shapeless.$colon$colon<A, shapeless.$colon$colon<B, shapeless.$colon$colon<C, shapeless.$colon$colon<D, shapeless.$colon$colon<E, shapeless.$colon$colon<F, shapeless.$colon$colon<G, shapeless.$colon$colon<H, shapeless.$colon$colon<I, shapeless.$colon$colon<J, shapeless.$colon$colon<K, shapeless.$colon$colon<L, shapeless.$colon$colon<M, shapeless.$colon$colon<N, shapeless.$colon$colon<O, shapeless.$colon$colon<P, shapeless.$colon$colon<Q, shapeless.$colon$colon<R, shapeless.HNil>>>>>>>>>>>>>>>>>>> hlistTupler18();
    descriptor: ()Lshapeless/ops/hlist$Tupler;
    flags: (0x0001) ACC_PUBLIC
    Code:
      stack=3, locals=1, args_size=1
         0: new           #28                 // class shapeless/ops/TuplerInstances$$anon$18
         3: dup
         4: aconst_null
         5: invokespecial #173                // Method shapeless/ops/TuplerInstances$$anon$18."<init>":(Lshapeless/ops/TuplerInstances;)V
         8: areturn
      LineNumberTable:
        line 220: 0
      LocalVariableTable:
        Start  Length  Slot  Name   Signature
            0       9     0  this   Lshapeless/ops/TuplerInstances;
    Signature: #172                         // <A:Ljava/lang/Object;B:Ljava/lang/Object;C:Ljava/lang/Object;D:Ljava/lang/Object;E:Ljava/lang/Object;F:Ljava/lang/Object;G:Ljava/lang/Object;H:Ljava/lang/Object;I:Ljava/lang/Object;J:Ljava/lang/Object;K:Ljava/lang/Object;L:Ljava/lang/Object;M:Ljava/lang/Object;N:Ljava/lang/Object;O:Ljava/lang/Object;P:Ljava/lang/Object;Q:Ljava/lang/Object;R:Ljava/lang/Object;>()Lshapeless/ops/hlist$Tupler<Lshapeless/$colon$colon<TA;Lshapeless/$colon$colon<TB;Lshapeless/$colon$colon<TC;Lshapeless/$colon$colon<TD;Lshapeless/$colon$colon<TE;Lshapeless/$colon$colon<TF;Lshapeless/$colon$colon<TG;Lshapeless/$colon$colon<TH;Lshapeless/$colon$colon<TI;Lshapeless/$colon$colon<TJ;Lshapeless/$colon$colon<TK;Lshapeless/$colon$colon<TL;Lshapeless/$colon$colon<TM;Lshapeless/$colon$colon<TN;Lshapeless/$colon$colon<TO;Lshapeless/$colon$colon<TP;Lshapeless/$colon$colon<TQ;Lshapeless/$colon$colon<TR;Lshapeless/HNil;>;>;>;>;>;>;>;>;>;>;>;>;>;>;>;>;>;>;>;

  public static shapeless.ops.hlist$Tupler hlistTupler19$(shapeless.ops.TuplerInstances);
    descriptor: (Lshapeless/ops/TuplerInstances;)Lshapeless/ops/hlist$Tupler;
    flags: (0x1009) ACC_PUBLIC, ACC_STATIC, ACC_SYNTHETIC
    Code:
      stack=1, locals=1, args_size=1
         0: aload_0
         1: invokespecial #177                // InterfaceMethod hlistTupler19:()Lshapeless/ops/hlist$Tupler;
         4: areturn
      LineNumberTable:
        line 225: 0
      LocalVariableTable:
        Start  Length  Slot  Name   Signature
            0       5     0 $this   Lshapeless/ops/TuplerInstances;
    MethodParameters:
      Name                           Flags
      $this                          final synthetic

  public default <A extends java.lang.Object, B extends java.lang.Object, C extends java.lang.Object, D extends java.lang.Object, E extends java.lang.Object, F extends java.lang.Object, G extends java.lang.Object, H extends java.lang.Object, I extends java.lang.Object, J extends java.lang.Object, K extends java.lang.Object, L extends java.lang.Object, M extends java.lang.Object, N extends java.lang.Object, O extends java.lang.Object, P extends java.lang.Object, Q extends java.lang.Object, R extends java.lang.Object, S extends java.lang.Object> shapeless.ops.hlist$Tupler<shapeless.$colon$colon<A, shapeless.$colon$colon<B, shapeless.$colon$colon<C, shapeless.$colon$colon<D, shapeless.$colon$colon<E, shapeless.$colon$colon<F, shapeless.$colon$colon<G, shapeless.$colon$colon<H, shapeless.$colon$colon<I, shapeless.$colon$colon<J, shapeless.$colon$colon<K, shapeless.$colon$colon<L, shapeless.$colon$colon<M, shapeless.$colon$colon<N, shapeless.$colon$colon<O, shapeless.$colon$colon<P, shapeless.$colon$colon<Q, shapeless.$colon$colon<R, shapeless.$colon$colon<S, shapeless.HNil>>>>>>>>>>>>>>>>>>>> hlistTupler19();
    descriptor: ()Lshapeless/ops/hlist$Tupler;
    flags: (0x0001) ACC_PUBLIC
    Code:
      stack=3, locals=1, args_size=1
         0: new           #30                 // class shapeless/ops/TuplerInstances$$anon$19
         3: dup
         4: aconst_null
         5: invokespecial #179                // Method shapeless/ops/TuplerInstances$$anon$19."<init>":(Lshapeless/ops/TuplerInstances;)V
         8: areturn
      LineNumberTable:
        line 231: 0
      LocalVariableTable:
        Start  Length  Slot  Name   Signature
            0       9     0  this   Lshapeless/ops/TuplerInstances;
    Signature: #178                         // <A:Ljava/lang/Object;B:Ljava/lang/Object;C:Ljava/lang/Object;D:Ljava/lang/Object;E:Ljava/lang/Object;F:Ljava/lang/Object;G:Ljava/lang/Object;H:Ljava/lang/Object;I:Ljava/lang/Object;J:Ljava/lang/Object;K:Ljava/lang/Object;L:Ljava/lang/Object;M:Ljava/lang/Object;N:Ljava/lang/Object;O:Ljava/lang/Object;P:Ljava/lang/Object;Q:Ljava/lang/Object;R:Ljava/lang/Object;S:Ljava/lang/Object;>()Lshapeless/ops/hlist$Tupler<Lshapeless/$colon$colon<TA;Lshapeless/$colon$colon<TB;Lshapeless/$colon$colon<TC;Lshapeless/$colon$colon<TD;Lshapeless/$colon$colon<TE;Lshapeless/$colon$colon<TF;Lshapeless/$colon$colon<TG;Lshapeless/$colon$colon<TH;Lshapeless/$colon$colon<TI;Lshapeless/$colon$colon<TJ;Lshapeless/$colon$colon<TK;Lshapeless/$colon$colon<TL;Lshapeless/$colon$colon<TM;Lshapeless/$colon$colon<TN;Lshapeless/$colon$colon<TO;Lshapeless/$colon$colon<TP;Lshapeless/$colon$colon<TQ;Lshapeless/$colon$colon<TR;Lshapeless/$colon$colon<TS;Lshapeless/HNil;>;>;>;>;>;>;>;>;>;>;>;>;>;>;>;>;>;>;>;>;

  public static shapeless.ops.hlist$Tupler hlistTupler20$(shapeless.ops.TuplerInstances);
    descriptor: (Lshapeless/ops/TuplerInstances;)Lshapeless/ops/hlist$Tupler;
    flags: (0x1009) ACC_PUBLIC, ACC_STATIC, ACC_SYNTHETIC
    Code:
      stack=1, locals=1, args_size=1
         0: aload_0
         1: invokespecial #183                // InterfaceMethod hlistTupler20:()Lshapeless/ops/hlist$Tupler;
         4: areturn
      LineNumberTable:
        line 236: 0
      LocalVariableTable:
        Start  Length  Slot  Name   Signature
            0       5     0 $this   Lshapeless/ops/TuplerInstances;
    MethodParameters:
      Name                           Flags
      $this                          final synthetic

  public default <A extends java.lang.Object, B extends java.lang.Object, C extends java.lang.Object, D extends java.lang.Object, E extends java.lang.Object, F extends java.lang.Object, G extends java.lang.Object, H extends java.lang.Object, I extends java.lang.Object, J extends java.lang.Object, K extends java.lang.Object, L extends java.lang.Object, M extends java.lang.Object, N extends java.lang.Object, O extends java.lang.Object, P extends java.lang.Object, Q extends java.lang.Object, R extends java.lang.Object, S extends java.lang.Object, T extends java.lang.Object> shapeless.ops.hlist$Tupler<shapeless.$colon$colon<A, shapeless.$colon$colon<B, shapeless.$colon$colon<C, shapeless.$colon$colon<D, shapeless.$colon$colon<E, shapeless.$colon$colon<F, shapeless.$colon$colon<G, shapeless.$colon$colon<H, shapeless.$colon$colon<I, shapeless.$colon$colon<J, shapeless.$colon$colon<K, shapeless.$colon$colon<L, shapeless.$colon$colon<M, shapeless.$colon$colon<N, shapeless.$colon$colon<O, shapeless.$colon$colon<P, shapeless.$colon$colon<Q, shapeless.$colon$colon<R, shapeless.$colon$colon<S, shapeless.$colon$colon<T, shapeless.HNil>>>>>>>>>>>>>>>>>>>>> hlistTupler20();
    descriptor: ()Lshapeless/ops/hlist$Tupler;
    flags: (0x0001) ACC_PUBLIC
    Code:
      stack=3, locals=1, args_size=1
         0: new           #34                 // class shapeless/ops/TuplerInstances$$anon$20
         3: dup
         4: aconst_null
         5: invokespecial #185                // Method shapeless/ops/TuplerInstances$$anon$20."<init>":(Lshapeless/ops/TuplerInstances;)V
         8: areturn
      LineNumberTable:
        line 242: 0
      LocalVariableTable:
        Start  Length  Slot  Name   Signature
            0       9     0  this   Lshapeless/ops/TuplerInstances;
    Signature: #184                         // <A:Ljava/lang/Object;B:Ljava/lang/Object;C:Ljava/lang/Object;D:Ljava/lang/Object;E:Ljava/lang/Object;F:Ljava/lang/Object;G:Ljava/lang/Object;H:Ljava/lang/Object;I:Ljava/lang/Object;J:Ljava/lang/Object;K:Ljava/lang/Object;L:Ljava/lang/Object;M:Ljava/lang/Object;N:Ljava/lang/Object;O:Ljava/lang/Object;P:Ljava/lang/Object;Q:Ljava/lang/Object;R:Ljava/lang/Object;S:Ljava/lang/Object;T:Ljava/lang/Object;>()Lshapeless/ops/hlist$Tupler<Lshapeless/$colon$colon<TA;Lshapeless/$colon$colon<TB;Lshapeless/$colon$colon<TC;Lshapeless/$colon$colon<TD;Lshapeless/$colon$colon<TE;Lshapeless/$colon$colon<TF;Lshapeless/$colon$colon<TG;Lshapeless/$colon$colon<TH;Lshapeless/$colon$colon<TI;Lshapeless/$colon$colon<TJ;Lshapeless/$colon$colon<TK;Lshapeless/$colon$colon<TL;Lshapeless/$colon$colon<TM;Lshapeless/$colon$colon<TN;Lshapeless/$colon$colon<TO;Lshapeless/$colon$colon<TP;Lshapeless/$colon$colon<TQ;Lshapeless/$colon$colon<TR;Lshapeless/$colon$colon<TS;Lshapeless/$colon$colon<TT;Lshapeless/HNil;>;>;>;>;>;>;>;>;>;>;>;>;>;>;>;>;>;>;>;>;>;

  public static shapeless.ops.hlist$Tupler hlistTupler21$(shapeless.ops.TuplerInstances);
    descriptor: (Lshapeless/ops/TuplerInstances;)Lshapeless/ops/hlist$Tupler;
    flags: (0x1009) ACC_PUBLIC, ACC_STATIC, ACC_SYNTHETIC
    Code:
      stack=1, locals=1, args_size=1
         0: aload_0
         1: invokespecial #189                // InterfaceMethod hlistTupler21:()Lshapeless/ops/hlist$Tupler;
         4: areturn
      LineNumberTable:
        line 247: 0
      LocalVariableTable:
        Start  Length  Slot  Name   Signature
            0       5     0 $this   Lshapeless/ops/TuplerInstances;
    MethodParameters:
      Name                           Flags
      $this                          final synthetic

  public default <A extends java.lang.Object, B extends java.lang.Object, C extends java.lang.Object, D extends java.lang.Object, E extends java.lang.Object, F extends java.lang.Object, G extends java.lang.Object, H extends java.lang.Object, I extends java.lang.Object, J extends java.lang.Object, K extends java.lang.Object, L extends java.lang.Object, M extends java.lang.Object, N extends java.lang.Object, O extends java.lang.Object, P extends java.lang.Object, Q extends java.lang.Object, R extends java.lang.Object, S extends java.lang.Object, T extends java.lang.Object, U extends java.lang.Object> shapeless.ops.hlist$Tupler<shapeless.$colon$colon<A, shapeless.$colon$colon<B, shapeless.$colon$colon<C, shapeless.$colon$colon<D, shapeless.$colon$colon<E, shapeless.$colon$colon<F, shapeless.$colon$colon<G, shapeless.$colon$colon<H, shapeless.$colon$colon<I, shapeless.$colon$colon<J, shapeless.$colon$colon<K, shapeless.$colon$colon<L, shapeless.$colon$colon<M, shapeless.$colon$colon<N, shapeless.$colon$colon<O, shapeless.$colon$colon<P, shapeless.$colon$colon<Q, shapeless.$colon$colon<R, shapeless.$colon$colon<S, shapeless.$colon$colon<T, shapeless.$colon$colon<U, shapeless.HNil>>>>>>>>>>>>>>>>>>>>>> hlistTupler21();
    descriptor: ()Lshapeless/ops/hlist$Tupler;
    flags: (0x0001) ACC_PUBLIC
    Code:
      stack=3, locals=1, args_size=1
         0: new           #36                 // class shapeless/ops/TuplerInstances$$anon$21
         3: dup
         4: aconst_null
         5: invokespecial #191                // Method shapeless/ops/TuplerInstances$$anon$21."<init>":(Lshapeless/ops/TuplerInstances;)V
         8: areturn
      LineNumberTable:
        line 253: 0
      LocalVariableTable:
        Start  Length  Slot  Name   Signature
            0       9     0  this   Lshapeless/ops/TuplerInstances;
    Signature: #190                         // <A:Ljava/lang/Object;B:Ljava/lang/Object;C:Ljava/lang/Object;D:Ljava/lang/Object;E:Ljava/lang/Object;F:Ljava/lang/Object;G:Ljava/lang/Object;H:Ljava/lang/Object;I:Ljava/lang/Object;J:Ljava/lang/Object;K:Ljava/lang/Object;L:Ljava/lang/Object;M:Ljava/lang/Object;N:Ljava/lang/Object;O:Ljava/lang/Object;P:Ljava/lang/Object;Q:Ljava/lang/Object;R:Ljava/lang/Object;S:Ljava/lang/Object;T:Ljava/lang/Object;U:Ljava/lang/Object;>()Lshapeless/ops/hlist$Tupler<Lshapeless/$colon$colon<TA;Lshapeless/$colon$colon<TB;Lshapeless/$colon$colon<TC;Lshapeless/$colon$colon<TD;Lshapeless/$colon$colon<TE;Lshapeless/$colon$colon<TF;Lshapeless/$colon$colon<TG;Lshapeless/$colon$colon<TH;Lshapeless/$colon$colon<TI;Lshapeless/$colon$colon<TJ;Lshapeless/$colon$colon<TK;Lshapeless/$colon$colon<TL;Lshapeless/$colon$colon<TM;Lshapeless/$colon$colon<TN;Lshapeless/$colon$colon<TO;Lshapeless/$colon$colon<TP;Lshapeless/$colon$colon<TQ;Lshapeless/$colon$colon<TR;Lshapeless/$colon$colon<TS;Lshapeless/$colon$colon<TT;Lshapeless/$colon$colon<TU;Lshapeless/HNil;>;>;>;>;>;>;>;>;>;>;>;>;>;>;>;>;>;>;>;>;>;>;

  public static shapeless.ops.hlist$Tupler hlistTupler22$(shapeless.ops.TuplerInstances);
    descriptor: (Lshapeless/ops/TuplerInstances;)Lshapeless/ops/hlist$Tupler;
    flags: (0x1009) ACC_PUBLIC, ACC_STATIC, ACC_SYNTHETIC
    Code:
      stack=1, locals=1, args_size=1
         0: aload_0
         1: invokespecial #195                // InterfaceMethod hlistTupler22:()Lshapeless/ops/hlist$Tupler;
         4: areturn
      LineNumberTable:
        line 258: 0
      LocalVariableTable:
        Start  Length  Slot  Name   Signature
            0       5     0 $this   Lshapeless/ops/TuplerInstances;
    MethodParameters:
      Name                           Flags
      $this                          final synthetic

  public default <A extends java.lang.Object, B extends java.lang.Object, C extends java.lang.Object, D extends java.lang.Object, E extends java.lang.Object, F extends java.lang.Object, G extends java.lang.Object, H extends java.lang.Object, I extends java.lang.Object, J extends java.lang.Object, K extends java.lang.Object, L extends java.lang.Object, M extends java.lang.Object, N extends java.lang.Object, O extends java.lang.Object, P extends java.lang.Object, Q extends java.lang.Object, R extends java.lang.Object, S extends java.lang.Object, T extends java.lang.Object, U extends java.lang.Object, V extends java.lang.Object> shapeless.ops.hlist$Tupler<shapeless.$colon$colon<A, shapeless.$colon$colon<B, shapeless.$colon$colon<C, shapeless.$colon$colon<D, shapeless.$colon$colon<E, shapeless.$colon$colon<F, shapeless.$colon$colon<G, shapeless.$colon$colon<H, shapeless.$colon$colon<I, shapeless.$colon$colon<J, shapeless.$colon$colon<K, shapeless.$colon$colon<L, shapeless.$colon$colon<M, shapeless.$colon$colon<N, shapeless.$colon$colon<O, shapeless.$colon$colon<P, shapeless.$colon$colon<Q, shapeless.$colon$colon<R, shapeless.$colon$colon<S, shapeless.$colon$colon<T, shapeless.$colon$colon<U, shapeless.$colon$colon<V, shapeless.HNil>>>>>>>>>>>>>>>>>>>>>>> hlistTupler22();
    descriptor: ()Lshapeless/ops/hlist$Tupler;
    flags: (0x0001) ACC_PUBLIC
    Code:
      stack=3, locals=1, args_size=1
         0: new           #38                 // class shapeless/ops/TuplerInstances$$anon$22
         3: dup
         4: aconst_null
         5: invokespecial #197                // Method shapeless/ops/TuplerInstances$$anon$22."<init>":(Lshapeless/ops/TuplerInstances;)V
         8: areturn
      LineNumberTable:
        line 264: 0
      LocalVariableTable:
        Start  Length  Slot  Name   Signature
            0       9     0  this   Lshapeless/ops/TuplerInstances;
    Signature: #196                         // <A:Ljava/lang/Object;B:Ljava/lang/Object;C:Ljava/lang/Object;D:Ljava/lang/Object;E:Ljava/lang/Object;F:Ljava/lang/Object;G:Ljava/lang/Object;H:Ljava/lang/Object;I:Ljava/lang/Object;J:Ljava/lang/Object;K:Ljava/lang/Object;L:Ljava/lang/Object;M:Ljava/lang/Object;N:Ljava/lang/Object;O:Ljava/lang/Object;P:Ljava/lang/Object;Q:Ljava/lang/Object;R:Ljava/lang/Object;S:Ljava/lang/Object;T:Ljava/lang/Object;U:Ljava/lang/Object;V:Ljava/lang/Object;>()Lshapeless/ops/hlist$Tupler<Lshapeless/$colon$colon<TA;Lshapeless/$colon$colon<TB;Lshapeless/$colon$colon<TC;Lshapeless/$colon$colon<TD;Lshapeless/$colon$colon<TE;Lshapeless/$colon$colon<TF;Lshapeless/$colon$colon<TG;Lshapeless/$colon$colon<TH;Lshapeless/$colon$colon<TI;Lshapeless/$colon$colon<TJ;Lshapeless/$colon$colon<TK;Lshapeless/$colon$colon<TL;Lshapeless/$colon$colon<TM;Lshapeless/$colon$colon<TN;Lshapeless/$colon$colon<TO;Lshapeless/$colon$colon<TP;Lshapeless/$colon$colon<TQ;Lshapeless/$colon$colon<TR;Lshapeless/$colon$colon<TS;Lshapeless/$colon$colon<TT;Lshapeless/$colon$colon<TU;Lshapeless/$colon$colon<TV;Lshapeless/HNil;>;>;>;>;>;>;>;>;>;>;>;>;>;>;>;>;>;>;>;>;>;>;>;

  public static void $init$(shapeless.ops.TuplerInstances);
    descriptor: (Lshapeless/ops/TuplerInstances;)V
    flags: (0x0009) ACC_PUBLIC, ACC_STATIC
    Code:
      stack=0, locals=1, args_size=1
         0: return
      LineNumberTable:
        line 24: 0
      LocalVariableTable:
        Start  Length  Slot  Name   Signature
            0       1     0 $this   Lshapeless/ops/TuplerInstances;
    MethodParameters:
      Name                           Flags
      $this                          final synthetic
}
InnerClasses:
  public final #10;                       // class shapeless/ops/TuplerInstances$$anon$1
  public final #12;                       // class shapeless/ops/TuplerInstances$$anon$10
  public final #14;                       // class shapeless/ops/TuplerInstances$$anon$11
  public final #16;                       // class shapeless/ops/TuplerInstances$$anon$12
  public final #18;                       // class shapeless/ops/TuplerInstances$$anon$13
  public final #20;                       // class shapeless/ops/TuplerInstances$$anon$14
  public final #22;                       // class shapeless/ops/TuplerInstances$$anon$15
  public final #24;                       // class shapeless/ops/TuplerInstances$$anon$16
  public final #26;                       // class shapeless/ops/TuplerInstances$$anon$17
  public final #28;                       // class shapeless/ops/TuplerInstances$$anon$18
  public final #30;                       // class shapeless/ops/TuplerInstances$$anon$19
  public final #32;                       // class shapeless/ops/TuplerInstances$$anon$2
  public final #34;                       // class shapeless/ops/TuplerInstances$$anon$20
  public final #36;                       // class shapeless/ops/TuplerInstances$$anon$21
  public final #38;                       // class shapeless/ops/TuplerInstances$$anon$22
  public final #40;                       // class shapeless/ops/TuplerInstances$$anon$3
  public final #42;                       // class shapeless/ops/TuplerInstances$$anon$4
  public final #44;                       // class shapeless/ops/TuplerInstances$$anon$5
  public final #46;                       // class shapeless/ops/TuplerInstances$$anon$6
  public final #48;                       // class shapeless/ops/TuplerInstances$$anon$7
  public final #50;                       // class shapeless/ops/TuplerInstances$$anon$8
  public final #52;                       // class shapeless/ops/TuplerInstances$$anon$9
  public static #57= #54 of #56;          // Tupler=class shapeless/ops/hlist$Tupler of class shapeless/ops/hlist
SourceFile: "tupler.scala"
RuntimeVisibleAnnotations:
  0: #6(#7=s#8)
    scala.reflect.ScalaSignature(
      bytes="\u0006\u0005\u001dMhaB\r\u001b!\u0003\r\ta\b\u0005\u0006M\u0001!\taJ\u0003\u0005W\u0001\u0001A\u0006C\u0003N\u0001\u0011\ra\nC\u0003_\u0001\u0011\rq\fC\u0003m\u0001\u0011\rQ\u000eC\u0003~\u0001\u0011\ra\u0010C\u0004\u0002$\u0001!\u0019!!\n\t\u000f\u0005E\u0003\u0001b\u0001\u0002T!9\u0011Q\u0011\u0001\u0005\u0004\u0005\u001d\u0005bBA`\u0001\u0011\r\u0011\u0011\u0019\u0005\b\u0003\u007f\u0004A1\u0001B\u0001\u0011\u001d\u0011)\u0005\u0001C\u0002\u0005\u000fBqA!%\u0001\t\u0007\u0011\u0019\nC\u0004\u0003d\u0002!\u0019A!:\t\u000f\re\u0002\u0001b\u0001\u0004<!91q\u0013\u0001\u0005\u0004\re\u0005bBB~\u0001\u0011\r1Q \u0005\b\tK\u0002A1\u0001C4\u0011\u001d!)\u000e\u0001C\u0002\t/Dq!b\u0013\u0001\t\u0007)i\u0005C\u0004\u0006H\u0002!\u0019!\"3\t\u000f\u0019%\u0003\u0001b\u0001\u0007L!9a\u0011\u001b\u0001\u0005\u0004\u0019M\u0007bBD0\u0001\u0011\rq\u0011\r\u0002\u0010)V\u0004H.\u001a:J]N$\u0018M\\2fg*\u00111\u0004H\u0001\u0004_B\u001c(\"A\u000f\u0002\u0013MD\u0017\r]3mKN\u001c8\u0001A\n\u0003\u0001\u0001\u0002\"!\t\u0013\u000e\u0003\tR\u0011aI\u0001\u0006g\u000e\fG.Y\u0005\u0003K\t\u0012a!\u00118z%\u00164\u0017A\u0002\u0013j]&$H\u0005F\u0001)!\t\t\u0013&\u0003\u0002+E\t!QK\\5u\u0005\r\tU\u000f_\u000b\u0004[i:%C\u0001\u00181\r\u0011y\u0003\u0001A\u0017\u0003\u0019q\u0012XMZ5oK6,g\u000e\u001e \u0011\u0007E*\u0004H\u0004\u00023g5\t!$\u0003\u000255\u0005)\u0001\u000e\\5ti&\u0011ag\u000e\u0002\u0007)V\u0004H.\u001a:\u000b\u0005QR\u0002CA\u001d;\u0019\u0001!Qa\u000f\u0002C\u0002q\u0012\u0011\u0001T\t\u0003{\u0001\u0003\"!\t \n\u0005}\u0012#a\u0002(pi\"Lgn\u001a\t\u0003\u0003\nk\u0011\u0001H\u0005\u0003\u0007r\u0011Q\u0001\u0013\'jgR,A!\u0012\u0018!\r\n\u0019q*\u001e;\u0011\u0005e:E!\u0002%\u0003\u0005\u0004I%\u0001B(viB\n\"!\u0010&\u0011\u0005\u0005Z\u0015B\u0001\'#\u0005\r\te._\u0001\rQ2L7\u000f\u001e+va2,\'/M\u000b\u0003\u001fZ+\u0012\u0001\u0015\t\u0005#\n\u00116,D\u0001\u0001!\u0011\t5+\u0016-\n\u0005Qc\"\u0001\u0004\u0013d_2|g\u000eJ2pY>t\u0007CA\u001dW\t\u001596A1\u0001J\u0005\u0005\t\u0005CA!Z\u0013\tQFD\u0001\u0003I\u001d&d\u0007cA\u0011]+&\u0011QL\t\u0002\u0007)V\u0004H.Z\u0019\u0002\u0019!d\u0017n\u001d;UkBdWM\u001d\u001a\u0016\u0007\u0001$w-F\u0001b!\u0011\t&AY5\u0011\t\u0005\u001b6-\u001a\t\u0003s\u0011$Qa\u0016\u0003C\u0002%\u0003B!Q*g1B\u0011\u0011h\u001a\u0003\u0006Q\u0012\u0011\r!\u0013\u0002\u0002\u0005B!\u0011E[2g\u0013\tY\'E\u0001\u0004UkBdWMM\u0001\rQ2L7\u000f\u001e+va2,\'oM\u000b\u0005]J,\b0F\u0001p!\u0011\t&\u0001\u001d>\u0011\t\u0005\u001b\u0016o\u001d\t\u0003sI$QaV\u0003C\u0002%\u0003B!Q*umB\u0011\u0011(\u001e\u0003\u0006Q\u0016\u0011\r!\u0013\t\u0005\u0003N;\b\f\u0005\u0002:q\u0012)\u00110\u0002b\u0001\u0013\n\t1\tE\u0003\"wF$x/\u0003\u0002}E\t1A+\u001e9mKN\nA\u0002\u001b7jgR$V\u000f\u001d7feR*\u0012b`A\u0004\u0003\u001b\t\u0019\"!\u0007\u0016\u0005\u0005\u0005\u0001CB)\u0003\u0003\u0007\ti\u0002\u0005\u0004B\'\u0006\u0015\u0011\u0011\u0002\t\u0004s\u0005\u001dA!B,\u0007\u0005\u0004I\u0005CB!T\u0003\u0017\ty\u0001E\u0002:\u0003\u001b!Q\u0001\u001b\u0004C\u0002%\u0003b!Q*\u0002\u0012\u0005U\u0001cA\u001d\u0002\u0014\u0011)\u0011P\u0002b\u0001\u0013B)\u0011iUA\f1B\u0019\u0011(!\u0007\u0005\r\u0005maA1\u0001J\u0005\u0005!\u0005cC\u0011\u0002 \u0005\u0015\u00111BA\t\u0003/I1!!\t#\u0005\u0019!V\u000f\u001d7fi\u0005a\u0001\u000e\\5tiR+\b\u000f\\3skUa\u0011qEA\u0018\u0003k\tY$!\u0011\u0002HU\u0011\u0011\u0011\u0006\t\u0007#\n\tY#a\u0013\u0011\r\u0005\u001b\u0016QFA\u0019!\rI\u0014q\u0006\u0003\u0006/\u001e\u0011\r!\u0013\t\u0007\u0003N\u000b\u0019$a\u000e\u0011\u0007e\n)\u0004B\u0003i\u000f\t\u0007\u0011\n\u0005\u0004B\'\u0006e\u0012Q\b\t\u0004s\u0005mB!B=\b\u0005\u0004I\u0005CB!T\u0003\u007f\t\u0019\u0005E\u0002:\u0003\u0003\"a!a\u0007\b\u0005\u0004I\u0005#B!T\u0003\u000bB\u0006cA\u001d\u0002H\u00111\u0011\u0011J\u0004C\u0002%\u0013\u0011!\u0012\t\u000eC\u00055\u0013QFA\u001a\u0003s\ty$!\u0012\n\u0007\u0005=#E\u0001\u0004UkBdW-N\u0001\rQ2L7\u000f\u001e+va2,\'ON\u000b\u000f\u0003+\ni&a\u0019\u0002j\u0005=\u0014QOA>+\t\t9\u0006\u0005\u0004R\u0005\u0005e\u0013q\u0010\t\u0007\u0003N\u000bY&a\u0018\u0011\u0007e\ni\u0006B\u0003X\u0011\t\u0007\u0011\n\u0005\u0004B\'\u0006\u0005\u0014Q\r\t\u0004s\u0005\rD!\u00025\t\u0005\u0004I\u0005CB!T\u0003O\nY\u0007E\u0002:\u0003S\"Q!\u001f\u0005C\u0002%\u0003b!Q*\u0002n\u0005E\u0004cA\u001d\u0002p\u00111\u00111\u0004\u0005C\u0002%\u0003b!Q*\u0002t\u0005]\u0004cA\u001d\u0002v\u00111\u0011\u0011\n\u0005C\u0002%\u0003R!Q*\u0002za\u00032!OA>\t\u0019\ti\b\u0003b\u0001\u0013\n\ta\tE\b\"\u0003\u0003\u000bY&!\u0019\u0002h\u00055\u00141OA=\u0013\r\t\u0019I\t\u0002\u0007)V\u0004H.\u001a\u001c\u0002\u0019!d\u0017n\u001d;UkBdWM]\u001c\u0016!\u0005%\u0015\u0011SAL\u0003;\u000b\u0019+!+\u00020\u0006UVCAAF!\u0019\t&!!$\u0002:B1\u0011iUAH\u0003\'\u00032!OAI\t\u00159\u0016B1\u0001J!\u0019\t5+!&\u0002\u001aB\u0019\u0011(a&\u0005\u000b!L!\u0019A%\u0011\r\u0005\u001b\u00161TAP!\rI\u0014Q\u0014\u0003\u0006s&\u0011\r!\u0013\t\u0007\u0003N\u000b\t+!*\u0011\u0007e\n\u0019\u000b\u0002\u0004\u0002\u001c%\u0011\r!\u0013\t\u0007\u0003N\u000b9+a+\u0011\u0007e\nI\u000b\u0002\u0004\u0002J%\u0011\r!\u0013\t\u0007\u0003N\u000bi+!-\u0011\u0007e\ny\u000b\u0002\u0004\u0002~%\u0011\r!\u0013\t\u0006\u0003N\u000b\u0019\f\u0017\t\u0004s\u0005UFABA\\\u0013\t\u0007\u0011JA\u0001H!E\t\u00131XAH\u0003+\u000bY*!)\u0002(\u00065\u00161W\u0005\u0004\u0003{\u0013#A\u0002+va2,w\'\u0001\u0007iY&\u001cH\u000fV;qY\u0016\u0014\b(\u0006\n\u0002D\u0006-\u0017\u0011[Al\u0003;\f\u0019/!;\u0002p\u0006UXCAAc!\u0019\t&!a2\u0002zB1\u0011iUAe\u0003\u001b\u00042!OAf\t\u00159&B1\u0001J!\u0019\t5+a4\u0002TB\u0019\u0011(!5\u0005\u000b!T!\u0019A%\u0011\r\u0005\u001b\u0016Q[Am!\rI\u0014q\u001b\u0003\u0006s*\u0011\r!\u0013\t\u0007\u0003N\u000bY.a8\u0011\u0007e\ni\u000e\u0002\u0004\u0002\u001c)\u0011\r!\u0013\t\u0007\u0003N\u000b\t/!:\u0011\u0007e\n\u0019\u000f\u0002\u0004\u0002J)\u0011\r!\u0013\t\u0007\u0003N\u000b9/a;\u0011\u0007e\nI\u000f\u0002\u0004\u0002~)\u0011\r!\u0013\t\u0007\u0003N\u000bi/!=\u0011\u0007e\ny\u000f\u0002\u0004\u00028*\u0011\r!\u0013\t\u0006\u0003N\u000b\u0019\u0010\u0017\t\u0004s\u0005UHABA|\u0015\t\u0007\u0011JA\u0001I!M\t\u00131`Ae\u0003\u001f\f).a7\u0002b\u0006\u001d\u0018Q^Az\u0013\r\tiP\t\u0002\u0007)V\u0004H.\u001a\u001d\u0002\u0019!d\u0017n\u001d;UkBdWM]\u001d\u0016)\t\r!1\u0002B\t\u0005/\u0011iBa\t\u0003*\t=\"Q\u0007B\u001e+\t\u0011)\u0001\u0005\u0004R\u0005\t\u001d!q\b\t\u0007\u0003N\u0013IA!\u0004\u0011\u0007e\u0012Y\u0001B\u0003X\u0017\t\u0007\u0011\n\u0005\u0004B\'\n=!1\u0003\t\u0004s\tEA!\u00025\f\u0005\u0004I\u0005CB!T\u0005+\u0011I\u0002E\u0002:\u0005/!Q!_\u0006C\u0002%\u0003b!Q*\u0003\u001c\t}\u0001cA\u001d\u0003\u001e\u00111\u00111D\u0006C\u0002%\u0003b!Q*\u0003\"\t\u0015\u0002cA\u001d\u0003$\u00111\u0011\u0011J\u0006C\u0002%\u0003b!Q*\u0003(\t-\u0002cA\u001d\u0003*\u00111\u0011QP\u0006C\u0002%\u0003b!Q*\u0003.\tE\u0002cA\u001d\u00030\u00111\u0011qW\u0006C\u0002%\u0003b!Q*\u00034\t]\u0002cA\u001d\u00036\u00111\u0011q_\u0006C\u0002%\u0003R!Q*\u0003:a\u00032!\u000fB\u001e\t\u0019\u0011id\u0003b\u0001\u0013\n\t\u0011\nE\u000b\"\u0005\u0003\u0012IAa\u0004\u0003\u0016\tm!\u0011\u0005B\u0014\u0005[\u0011\u0019D!\u000f\n\u0007\t\r#E\u0001\u0004UkBdW-O\u0001\u000eQ2L7\u000f\u001e+va2,\'/\r\u0019\u0016-\t%#\u0011\u000bB,\u0005;\u0012\u0019G!\u001b\u0003p\tU$1\u0010BA\u0005\u000f+\"Aa\u0013\u0011\rE\u0013!Q\nBF!\u0019\t5Ka\u0014\u0003TA\u0019\u0011H!\u0015\u0005\u000b]c!\u0019A%\u0011\r\u0005\u001b&Q\u000bB-!\rI$q\u000b\u0003\u0006Q2\u0011\r!\u0013\t\u0007\u0003N\u0013YFa\u0018\u0011\u0007e\u0012i\u0006B\u0003z\u0019\t\u0007\u0011\n\u0005\u0004B\'\n\u0005$Q\r\t\u0004s\t\rDABA\u000e\u0019\t\u0007\u0011\n\u0005\u0004B\'\n\u001d$1\u000e\t\u0004s\t%DABA%\u0019\t\u0007\u0011\n\u0005\u0004B\'\n5$\u0011\u000f\t\u0004s\t=DABA?\u0019\t\u0007\u0011\n\u0005\u0004B\'\nM$q\u000f\t\u0004s\tUDABA\\\u0019\t\u0007\u0011\n\u0005\u0004B\'\ne$Q\u0010\t\u0004s\tmDABA|\u0019\t\u0007\u0011\n\u0005\u0004B\'\n}$1\u0011\t\u0004s\t\u0005EA\u0002B\u001f\u0019\t\u0007\u0011\nE\u0003B\'\n\u0015\u0005\fE\u0002:\u0005\u000f#aA!#\r\u0005\u0004I%!\u0001&\u0011/\u0005\u0012iIa\u0014\u0003V\tm#\u0011\rB4\u0005[\u0012\u0019H!\u001f\u0003\u0000\t\u0015\u0015b\u0001BHE\t9A+\u001e9mKF\u0002\u0014!\u00045mSN$H+\u001e9mKJ\f\u0014\'\u0006\r\u0003\u0016\nu%1\u0015BU\u0005_\u0013)La/\u0003B\n\u001d\'Q\u001aBj\u00053,\"Aa&\u0011\rE\u0013!\u0011\u0014Bo!\u0019\t5Ka\'\u0003 B\u0019\u0011H!(\u0005\u000b]k!\u0019A%\u0011\r\u0005\u001b&\u0011\u0015BS!\rI$1\u0015\u0003\u0006Q6\u0011\r!\u0013\t\u0007\u0003N\u00139Ka+\u0011\u0007e\u0012I\u000bB\u0003z\u001b\t\u0007\u0011\n\u0005\u0004B\'\n5&\u0011\u0017\t\u0004s\t=FABA\u000e\u001b\t\u0007\u0011\n\u0005\u0004B\'\nM&q\u0017\t\u0004s\tUFABA%\u001b\t\u0007\u0011\n\u0005\u0004B\'\ne&Q\u0018\t\u0004s\tmFABA?\u001b\t\u0007\u0011\n\u0005\u0004B\'\n}&1\u0019\t\u0004s\t\u0005GABA\\\u001b\t\u0007\u0011\n\u0005\u0004B\'\n\u0015\'\u0011\u001a\t\u0004s\t\u001dGABA|\u001b\t\u0007\u0011\n\u0005\u0004B\'\n-\'q\u001a\t\u0004s\t5GA\u0002B\u001f\u001b\t\u0007\u0011\n\u0005\u0004B\'\nE\'Q\u001b\t\u0004s\tMGA\u0002BE\u001b\t\u0007\u0011\nE\u0003B\'\n]\u0007\fE\u0002:\u00053$aAa7\u000e\u0005\u0004I%!A&\u00113\u0005\u0012yNa\'\u0003\"\n\u001d&Q\u0016BZ\u0005s\u0013yL!2\u0003L\nE\'q[\u0005\u0004\u0005C\u0014#a\u0002+va2,\u0017\'M\u0001\u000eQ2L7\u000f\u001e+va2,\'/\r\u001a\u00165\t\u001d(q\u001eB{\u0005w\u001c\taa\u0002\u0004\u000e\rM1\u0011DB\u0010\u0007K\u0019Yc!\r\u0016\u0005\t%\bCB)\u0003\u0005W\u001c\u0019\u0004\u0005\u0004B\'\n5(\u0011\u001f\t\u0004s\t=H!B,\u000f\u0005\u0004I\u0005CB!T\u0005g\u00149\u0010E\u0002:\u0005k$Q\u0001\u001b\bC\u0002%\u0003b!Q*\u0003z\nu\bcA\u001d\u0003|\u0012)\u0011P\u0004b\u0001\u0013B1\u0011i\u0015B\u0000\u0007\u0007\u00012!OB\u0001\t\u0019\tYB\u0004b\u0001\u0013B1\u0011iUB\u0003\u0007\u0013\u00012!OB\u0004\t\u0019\tIE\u0004b\u0001\u0013B1\u0011iUB\u0006\u0007\u001f\u00012!OB\u0007\t\u0019\tiH\u0004b\u0001\u0013B1\u0011iUB\t\u0007+\u00012!OB\n\t\u0019\t9L\u0004b\u0001\u0013B1\u0011iUB\f\u00077\u00012!OB\r\t\u0019\t9P\u0004b\u0001\u0013B1\u0011iUB\u000f\u0007C\u00012!OB\u0010\t\u0019\u0011iD\u0004b\u0001\u0013B1\u0011iUB\u0012\u0007O\u00012!OB\u0013\t\u0019\u0011II\u0004b\u0001\u0013B1\u0011iUB\u0015\u0007[\u00012!OB\u0016\t\u0019\u0011YN\u0004b\u0001\u0013B)\u0011iUB\u00181B\u0019\u0011h!\r\u0005\u000bmr!\u0019A%\u00117\u0005\u001a)D!<\u0003t\ne(q`B\u0003\u0007\u0017\u0019\tba\u0006\u0004\u001e\r\r2\u0011FB\u0018\u0013\r\u00199D\t\u0002\b)V\u0004H.Z\u00193\u00035AG.[:u)V\u0004H.\u001a:2gUa2QHB#\u0007\u0017\u001a\tfa\u0016\u0004^\r\r4\u0011NB8\u0007k\u001aYh!!\u0004\b\u000e5UCAB !\u0019\t&a!\u0011\u0004\u0012B1\u0011iUB\"\u0007\u000f\u00022!OB#\t\u00159vB1\u0001J!\u0019\t5k!\u0013\u0004NA\u0019\u0011ha\u0013\u0005\u000b!|!\u0019A%\u0011\r\u0005\u001b6qJB*!\rI4\u0011\u000b\u0003\u0006s>\u0011\r!\u0013\t\u0007\u0003N\u001b)f!\u0017\u0011\u0007e\u001a9\u0006\u0002\u0004\u0002\u001c=\u0011\r!\u0013\t\u0007\u0003N\u001bYfa\u0018\u0011\u0007e\u001ai\u0006\u0002\u0004\u0002J=\u0011\r!\u0013\t\u0007\u0003N\u001b\tg!\u001a\u0011\u0007e\u001a\u0019\u0007\u0002\u0004\u0002~=\u0011\r!\u0013\t\u0007\u0003N\u001b9ga\u001b\u0011\u0007e\u001aI\u0007\u0002\u0004\u00028>\u0011\r!\u0013\t\u0007\u0003N\u001big!\u001d\u0011\u0007e\u001ay\u0007\u0002\u0004\u0002x>\u0011\r!\u0013\t\u0007\u0003N\u001b\u0019ha\u001e\u0011\u0007e\u001a)\b\u0002\u0004\u0003>=\u0011\r!\u0013\t\u0007\u0003N\u001bIh! \u0011\u0007e\u001aY\b\u0002\u0004\u0003\n>\u0011\r!\u0013\t\u0007\u0003N\u001byha!\u0011\u0007e\u001a\t\t\u0002\u0004\u0003\\>\u0011\r!\u0013\t\u0007\u0003N\u001b)i!#\u0011\u0007e\u001a9\tB\u0003<\u001f\t\u0007\u0011\nE\u0003B\'\u000e-\u0005\fE\u0002:\u0007\u001b#aaa$\u0010\u0005\u0004I%!A\'\u0011;\u0005\u001a\u0019ja\u0011\u0004J\r=3QKB.\u0007C\u001a9g!\u001c\u0004t\re4qPBC\u0007\u0017K1a!&#\u0005\u001d!V\u000f\u001d7fcM\nQ\u0002\u001b7jgR$V\u000f\u001d7feF\"TCHBN\u0007G\u001bIka,\u00046\u000em6\u0011YBd\u0007\u001b\u001c\u0019n!7\u0004`\u000e\u001581^By+\t\u0019i\n\u0005\u0004R\u0005\r}5Q\u001f\t\u0007\u0003N\u001b\tk!*\u0011\u0007e\u001a\u0019\u000bB\u0003X!\t\u0007\u0011\n\u0005\u0004B\'\u000e\u001d61\u0016\t\u0004s\r%F!\u00025\u0011\u0005\u0004I\u0005CB!T\u0007[\u001b\t\fE\u0002:\u0007_#Q!\u001f\tC\u0002%\u0003b!Q*\u00044\u000e]\u0006cA\u001d\u00046\u00121\u00111\u0004\tC\u0002%\u0003b!Q*\u0004:\u000eu\u0006cA\u001d\u0004<\u00121\u0011\u0011\n\tC\u0002%\u0003b!Q*\u0004@\u000e\r\u0007cA\u001d\u0004B\u00121\u0011Q\u0010\tC\u0002%\u0003b!Q*\u0004F\u000e%\u0007cA\u001d\u0004H\u00121\u0011q\u0017\tC\u0002%\u0003b!Q*\u0004L\u000e=\u0007cA\u001d\u0004N\u00121\u0011q\u001f\tC\u0002%\u0003b!Q*\u0004R\u000eU\u0007cA\u001d\u0004T\u00121!Q\b\tC\u0002%\u0003b!Q*\u0004X\u000em\u0007cA\u001d\u0004Z\u00121!\u0011\u0012\tC\u0002%\u0003b!Q*\u0004^\u000e\u0005\bcA\u001d\u0004`\u00121!1\u001c\tC\u0002%\u0003b!Q*\u0004d\u000e\u001d\bcA\u001d\u0004f\u0012)1\b\u0005b\u0001\u0013B1\u0011iUBu\u0007[\u00042!OBv\t\u0019\u0019y\t\u0005b\u0001\u0013B)\u0011iUBx1B\u0019\u0011h!=\u0005\r\rM\bC1\u0001J\u0005\u0005q\u0005cH\u0011\u0004x\u000e\u00056qUBW\u0007g\u001bIla0\u0004F\u000e-7\u0011[Bl\u0007;\u001c\u0019o!;\u0004p&\u00191\u0011 \u0012\u0003\u000fQ+\b\u000f\\32i\u0005i\u0001\u000e\\5tiR+\b\u000f\\3scU*\u0002ea@\u0005\b\u00115A1\u0003C\r\t?!)\u0003b\u000b\u00052\u0011]BQ\bC\"\t\u0013\"y\u0005\"\u0016\u0005\\U\u0011A\u0011\u0001\t\u0007#\n!\u0019\u0001b\u0018\u0011\r\u0005\u001bFQ\u0001C\u0005!\rIDq\u0001\u0003\u0006/F\u0011\r!\u0013\t\u0007\u0003N#Y\u0001b\u0004\u0011\u0007e\"i\u0001B\u0003i#\t\u0007\u0011\n\u0005\u0004B\'\u0012EAQ\u0003\t\u0004s\u0011MA!B=\u0012\u0005\u0004I\u0005CB!T\t/!Y\u0002E\u0002:\t3!a!a\u0007\u0012\u0005\u0004I\u0005CB!T\t;!\t\u0003E\u0002:\t?!a!!\u0013\u0012\u0005\u0004I\u0005CB!T\tG!9\u0003E\u0002:\tK!a!! \u0012\u0005\u0004I\u0005CB!T\tS!i\u0003E\u0002:\tW!a!a.\u0012\u0005\u0004I\u0005CB!T\t_!\u0019\u0004E\u0002:\tc!a!a>\u0012\u0005\u0004I\u0005CB!T\tk!I\u0004E\u0002:\to!aA!\u0010\u0012\u0005\u0004I\u0005CB!T\tw!y\u0004E\u0002:\t{!aA!#\u0012\u0005\u0004I\u0005CB!T\t\u0003\")\u0005E\u0002:\t\u0007\"aAa7\u0012\u0005\u0004I\u0005CB!T\t\u000f\"Y\u0005E\u0002:\t\u0013\"QaO\tC\u0002%\u0003b!Q*\u0005N\u0011E\u0003cA\u001d\u0005P\u001111qR\tC\u0002%\u0003b!Q*\u0005T\u0011]\u0003cA\u001d\u0005V\u0011111_\tC\u0002%\u0003R!Q*\u0005Za\u00032!\u000fC.\t\u0019!i&\u0005b\u0001\u0013\n\tq\nE\u0011\"\tC\")\u0001b\u0003\u0005\u0012\u0011]AQ\u0004C\u0012\tS!y\u0003\"\u000e\u0005<\u0011\u0005Cq\tC\'\t\'\"I&C\u0002\u0005d\t\u0012q\u0001V;qY\u0016\fT\'A\u0007iY&\u001cH\u000fV;qY\u0016\u0014\u0018GN\u000b#\tS\"\t\bb\u001e\u0005~\u0011\rE\u0011\u0012CH\t+#Y\n\")\u0005(\u00125F1\u0017C]\t\u007f#)\rb3\u0016\u0005\u0011-\u0004CB)\u0003\t[\"y\r\u0005\u0004B\'\u0012=D1\u000f\t\u0004s\u0011ED!B,\u0013\u0005\u0004I\u0005CB!T\tk\"I\bE\u0002:\to\"Q\u0001\u001b\nC\u0002%\u0003b!Q*\u0005|\u0011}\u0004cA\u001d\u0005~\u0011)\u0011P\u0005b\u0001\u0013B1\u0011i\u0015CA\t\u000b\u00032!\u000fCB\t\u0019\tYB\u0005b\u0001\u0013B1\u0011i\u0015CD\t\u0017\u00032!\u000fCE\t\u0019\tIE\u0005b\u0001\u0013B1\u0011i\u0015CG\t#\u00032!\u000fCH\t\u0019\tiH\u0005b\u0001\u0013B1\u0011i\u0015CJ\t/\u00032!\u000fCK\t\u0019\t9L\u0005b\u0001\u0013B1\u0011i\u0015CM\t;\u00032!\u000fCN\t\u0019\t9P\u0005b\u0001\u0013B1\u0011i\u0015CP\tG\u00032!\u000fCQ\t\u0019\u0011iD\u0005b\u0001\u0013B1\u0011i\u0015CS\tS\u00032!\u000fCT\t\u0019\u0011II\u0005b\u0001\u0013B1\u0011i\u0015CV\t_\u00032!\u000fCW\t\u0019\u0011YN\u0005b\u0001\u0013B1\u0011i\u0015CY\tk\u00032!\u000fCZ\t\u0015Y$C1\u0001J!\u0019\t5\u000bb.\u0005<B\u0019\u0011\b\"/\u0005\r\r=%C1\u0001J!\u0019\t5\u000b\"0\u0005BB\u0019\u0011\bb0\u0005\r\rM(C1\u0001J!\u0019\t5\u000bb1\u0005HB\u0019\u0011\b\"2\u0005\r\u0011u#C1\u0001J!\u0015\t5\u000b\"3Y!\rID1\u001a\u0003\u0007\t\u001b\u0014\"\u0019A%\u0003\u0003A\u00032%\tCi\t_\")\bb\u001f\u0005\u0002\u0012\u001dEQ\u0012CJ\t3#y\n\"*\u0005,\u0012EFq\u0017C_\t\u0007$I-C\u0002\u0005T\n\u0012q\u0001V;qY\u0016\fd\'A\u0007iY&\u001cH\u000fV;qY\u0016\u0014\u0018gN\u000b%\t3$\t\u000fb:\u0005n\u0012MH\u0011 C\u0000\u000b\u000b)Y!\"\u0005\u0006\u0018\u0015uQ1EC\u0015\u000b_))$b\u000f\u0006BU\u0011A1\u001c\t\u0007#\n!i.\"\u0012\u0011\r\u0005\u001bFq\u001cCr!\rID\u0011\u001d\u0003\u0006/N\u0011\r!\u0013\t\u0007\u0003N#)\u000f\";\u0011\u0007e\"9\u000fB\u0003i\'\t\u0007\u0011\n\u0005\u0004B\'\u0012-Hq\u001e\t\u0004s\u00115H!B=\u0014\u0005\u0004I\u0005CB!T\tc$)\u0010E\u0002:\tg$a!a\u0007\u0014\u0005\u0004I\u0005CB!T\to$Y\u0010E\u0002:\ts$a!!\u0013\u0014\u0005\u0004I\u0005CB!T\t{,\t\u0001E\u0002:\t\u007f$a!! \u0014\u0005\u0004I\u0005CB!T\u000b\u0007)9\u0001E\u0002:\u000b\u000b!a!a.\u0014\u0005\u0004I\u0005CB!T\u000b\u0013)i\u0001E\u0002:\u000b\u0017!a!a>\u0014\u0005\u0004I\u0005CB!T\u000b\u001f)\u0019\u0002E\u0002:\u000b#!aA!\u0010\u0014\u0005\u0004I\u0005CB!T\u000b+)I\u0002E\u0002:\u000b/!aA!#\u0014\u0005\u0004I\u0005CB!T\u000b7)y\u0002E\u0002:\u000b;!aAa7\u0014\u0005\u0004I\u0005CB!T\u000bC))\u0003E\u0002:\u000bG!QaO\nC\u0002%\u0003b!Q*\u0006(\u0015-\u0002cA\u001d\u0006*\u001111qR\nC\u0002%\u0003b!Q*\u0006.\u0015E\u0002cA\u001d\u00060\u0011111_\nC\u0002%\u0003b!Q*\u00064\u0015]\u0002cA\u001d\u00066\u00111AQL\nC\u0002%\u0003b!Q*\u0006:\u0015u\u0002cA\u001d\u0006<\u00111AQZ\nC\u0002%\u0003R!Q*\u0006@a\u00032!OC!\t\u0019)\u0019e\u0005b\u0001\u0013\n\t\u0011\u000bE\u0013\"\u000b\u000f\"y\u000e\":\u0005l\u0012EHq\u001fC\u007f\u000b\u0007)I!b\u0004\u0006\u0016\u0015mQ\u0011EC\u0014\u000b[)\u0019$\"\u000f\u0006@%\u0019Q\u0011\n\u0012\u0003\u000fQ+\b\u000f\\32o\u0005i\u0001\u000e\\5tiR+\b\u000f\\3sca*b%b\u0014\u0006X\u0015uS1MC5\u000b_*)(b\u001f\u0006\u0002\u0016\u001dUQRCJ\u000b3+y*\"*\u0006,\u0016EVqWC_+\t)\t\u0006\u0005\u0004R\u0005\u0015MS\u0011\u0019\t\u0007\u0003N+)&\"\u0017\u0011\u0007e*9\u0006B\u0003X)\t\u0007\u0011\n\u0005\u0004B\'\u0016mSq\f\t\u0004s\u0015uC!\u00025\u0015\u0005\u0004I\u0005CB!T\u000bC*)\u0007E\u0002:\u000bG\"Q!\u001f\u000bC\u0002%\u0003b!Q*\u0006h\u0015-\u0004cA\u001d\u0006j\u00111\u00111\u0004\u000bC\u0002%\u0003b!Q*\u0006n\u0015E\u0004cA\u001d\u0006p\u00111\u0011\u0011\n\u000bC\u0002%\u0003b!Q*\u0006t\u0015]\u0004cA\u001d\u0006v\u00111\u0011Q\u0010\u000bC\u0002%\u0003b!Q*\u0006z\u0015u\u0004cA\u001d\u0006|\u00111\u0011q\u0017\u000bC\u0002%\u0003b!Q*\u0006\u0000\u0015\r\u0005cA\u001d\u0006\u0002\u00121\u0011q\u001f\u000bC\u0002%\u0003b!Q*\u0006\u0006\u0016%\u0005cA\u001d\u0006\b\u00121!Q\b\u000bC\u0002%\u0003b!Q*\u0006\f\u0016=\u0005cA\u001d\u0006\u000e\u00121!\u0011\u0012\u000bC\u0002%\u0003b!Q*\u0006\u0012\u0016U\u0005cA\u001d\u0006\u0014\u00121!1\u001c\u000bC\u0002%\u0003b!Q*\u0006\u0018\u0016m\u0005cA\u001d\u0006\u001a\u0012)1\b\u0006b\u0001\u0013B1\u0011iUCO\u000bC\u00032!OCP\t\u0019\u0019y\t\u0006b\u0001\u0013B1\u0011iUCR\u000bO\u00032!OCS\t\u0019\u0019\u0019\u0010\u0006b\u0001\u0013B1\u0011iUCU\u000b[\u00032!OCV\t\u0019!i\u0006\u0006b\u0001\u0013B1\u0011iUCX\u000bg\u00032!OCY\t\u0019!i\r\u0006b\u0001\u0013B1\u0011iUC[\u000bs\u00032!OC\\\t\u0019)\u0019\u0005\u0006b\u0001\u0013B)\u0011iUC^1B\u0019\u0011(\"0\u0005\r\u0015}FC1\u0001J\u0005\u0005\u0011\u0006cJ\u0011\u0006D\u0016US1LC1\u000bO*i\'b\u001d\u0006z\u0015}TQQCF\u000b#+9*\"(\u0006$\u0016%VqVC[\u000bwK1!\"2#\u0005\u001d!V\u000f\u001d7fca\nQ\u0002\u001b7jgR$V\u000f\u001d7feFJT\u0003KCf\u000b\',I.b8\u0006f\u0016-X\u0011_C|\u000b{4\u0019A\"\u0003\u0007\u0010\u0019Ua1\u0004D\u0011\rO1iCb\r\u0007:\u0019}RCACg!\u0019\t&!b4\u0007DA1\u0011iUCi\u000b+\u00042!OCj\t\u00159VC1\u0001J!\u0019\t5+b6\u0006\\B\u0019\u0011(\"7\u0005\u000b!,\"\u0019A%\u0011\r\u0005\u001bVQ\\Cq!\rITq\u001c\u0003\u0006sV\u0011\r!\u0013\t\u0007\u0003N+\u0019/b:\u0011\u0007e*)\u000f\u0002\u0004\u0002\u001cU\u0011\r!\u0013\t\u0007\u0003N+I/\"<\u0011\u0007e*Y\u000f\u0002\u0004\u0002JU\u0011\r!\u0013\t\u0007\u0003N+y/b=\u0011\u0007e*\t\u0010\u0002\u0004\u0002~U\u0011\r!\u0013\t\u0007\u0003N+)0\"?\u0011\u0007e*9\u0010\u0002\u0004\u00028V\u0011\r!\u0013\t\u0007\u0003N+Y0b@\u0011\u0007e*i\u0010\u0002\u0004\u0002xV\u0011\r!\u0013\t\u0007\u0003N3\tA\"\u0002\u0011\u0007e2\u0019\u0001\u0002\u0004\u0003>U\u0011\r!\u0013\t\u0007\u0003N39Ab\u0003\u0011\u0007e2I\u0001\u0002\u0004\u0003\nV\u0011\r!\u0013\t\u0007\u0003N3iA\"\u0005\u0011\u0007e2y\u0001\u0002\u0004\u0003\\V\u0011\r!\u0013\t\u0007\u0003N3\u0019Bb\u0006\u0011\u0007e2)\u0002B\u0003<+\t\u0007\u0011\n\u0005\u0004B\'\u001aeaQ\u0004\t\u0004s\u0019mAABBH+\t\u0007\u0011\n\u0005\u0004B\'\u001a}a1\u0005\t\u0004s\u0019\u0005BABBz+\t\u0007\u0011\n\u0005\u0004B\'\u001a\u0015b\u0011\u0006\t\u0004s\u0019\u001dBA\u0002C/+\t\u0007\u0011\n\u0005\u0004B\'\u001a-bq\u0006\t\u0004s\u00195BA\u0002Cg+\t\u0007\u0011\n\u0005\u0004B\'\u001aEbQ\u0007\t\u0004s\u0019MBABC\"+\t\u0007\u0011\n\u0005\u0004B\'\u001a]b1\b\t\u0004s\u0019eBABC`+\t\u0007\u0011\nE\u0003B\'\u001au\u0002\fE\u0002:\r\u007f!aA\"\u0011\u0016\u0005\u0004I%!A*\u0011S\u00052)%\"5\u0006X\u0016uW1]Cu\u000b_,)0b?\u0007\u0002\u0019\u001daQ\u0002D\n\r31yB\"\n\u0007,\u0019Ebq\u0007D\u001f\u0013\r19E\t\u0002\b)V\u0004H.Z\u0019:\u00035AG.[:u)V\u0004H.\u001a:3aUQcQ\nD+\r72\tGb\u001a\u0007n\u0019Md\u0011\u0010D@\r\u000b3YI\"%\u0007\u0018\u001aue1\u0015DU\r_3)Lb/\u0007B\u001a\u001dWC\u0001D(!\u0019\t&A\"\u0015\u0007LB1\u0011i\u0015D*\r/\u00022!\u000fD+\t\u00159fC1\u0001J!\u0019\t5K\"\u0017\u0007^A\u0019\u0011Hb\u0017\u0005\u000b!4\"\u0019A%\u0011\r\u0005\u001bfq\fD2!\rId\u0011\r\u0003\u0006sZ\u0011\r!\u0013\t\u0007\u0003N3)G\"\u001b\u0011\u0007e29\u0007\u0002\u0004\u0002\u001cY\u0011\r!\u0013\t\u0007\u0003N3YGb\u001c\u0011\u0007e2i\u0007\u0002\u0004\u0002JY\u0011\r!\u0013\t\u0007\u0003N3\tH\"\u001e\u0011\u0007e2\u0019\b\u0002\u0004\u0002~Y\u0011\r!\u0013\t\u0007\u0003N39Hb\u001f\u0011\u0007e2I\b\u0002\u0004\u00028Z\u0011\r!\u0013\t\u0007\u0003N3iH\"!\u0011\u0007e2y\b\u0002\u0004\u0002xZ\u0011\r!\u0013\t\u0007\u0003N3\u0019Ib\"\u0011\u0007e2)\t\u0002\u0004\u0003>Y\u0011\r!\u0013\t\u0007\u0003N3II\"$\u0011\u0007e2Y\t\u0002\u0004\u0003\nZ\u0011\r!\u0013\t\u0007\u0003N3yIb%\u0011\u0007e2\t\n\u0002\u0004\u0003\\Z\u0011\r!\u0013\t\u0007\u0003N3)J\"\'\u0011\u0007e29\nB\u0003<-\t\u0007\u0011\n\u0005\u0004B\'\u001ameq\u0014\t\u0004s\u0019uEABBH-\t\u0007\u0011\n\u0005\u0004B\'\u001a\u0005fQ\u0015\t\u0004s\u0019\rFABBz-\t\u0007\u0011\n\u0005\u0004B\'\u001a\u001df1\u0016\t\u0004s\u0019%FA\u0002C/-\t\u0007\u0011\n\u0005\u0004B\'\u001a5f\u0011\u0017\t\u0004s\u0019=FA\u0002Cg-\t\u0007\u0011\n\u0005\u0004B\'\u001aMfq\u0017\t\u0004s\u0019UFABC\"-\t\u0007\u0011\n\u0005\u0004B\'\u001aefQ\u0018\t\u0004s\u0019mFABC`-\t\u0007\u0011\n\u0005\u0004B\'\u001a}f1\u0019\t\u0004s\u0019\u0005GA\u0002D!-\t\u0007\u0011\nE\u0003B\'\u001a\u0015\u0007\fE\u0002:\r\u000f$aA\"3\u0017\u0005\u0004I%!\u0001+\u0011W\u00052iMb\u0015\u0007Z\u0019}cQ\rD6\rc29H\" \u0007\u0004\u001a%eq\u0012DK\r73\tKb*\u0007.\u001aMf\u0011\u0018D`\r\u000bL1Ab4#\u0005\u001d!V\u000f\u001d7feA\nQ\u0002\u001b7jgR$V\u000f\u001d7feJ\nT\u0003\fDk\r;4\u0019O\";\u0007p\u001aUh1`D\u0001\u000f\u000f9iab\u0005\b\u001a\u001d}qQED\u0016\u000fc99d\"\u0010\bD\u001d%sqJD++\t19\u000e\u0005\u0004R\u0005\u0019ew\u0011\f\t\u0007\u0003N3YNb8\u0011\u0007e2i\u000eB\u0003X/\t\u0007\u0011\n\u0005\u0004B\'\u001a\u0005hQ\u001d\t\u0004s\u0019\rH!\u00025\u0018\u0005\u0004I\u0005CB!T\rO4Y\u000fE\u0002:\rS$Q!_\fC\u0002%\u0003b!Q*\u0007n\u001aE\bcA\u001d\u0007p\u00121\u00111D\fC\u0002%\u0003b!Q*\u0007t\u001a]\bcA\u001d\u0007v\u00121\u0011\u0011J\fC\u0002%\u0003b!Q*\u0007z\u001au\bcA\u001d\u0007|\u00121\u0011QP\fC\u0002%\u0003b!Q*\u0007\u0000\u001e\r\u0001cA\u001d\b\u0002\u00111\u0011qW\fC\u0002%\u0003b!Q*\b\u0006\u001d%\u0001cA\u001d\b\b\u00111\u0011q_\fC\u0002%\u0003b!Q*\b\f\u001d=\u0001cA\u001d\b\u000e\u00111!QH\fC\u0002%\u0003b!Q*\b\u0012\u001dU\u0001cA\u001d\b\u0014\u00111!\u0011R\fC\u0002%\u0003b!Q*\b\u0018\u001dm\u0001cA\u001d\b\u001a\u00111!1\\\fC\u0002%\u0003b!Q*\b\u001e\u001d\u0005\u0002cA\u001d\b \u0011)1h\u0006b\u0001\u0013B1\u0011iUD\u0012\u000fO\u00012!OD\u0013\t\u0019\u0019yi\u0006b\u0001\u0013B1\u0011iUD\u0015\u000f[\u00012!OD\u0016\t\u0019\u0019\u0019p\u0006b\u0001\u0013B1\u0011iUD\u0018\u000fg\u00012!OD\u0019\t\u0019!if\u0006b\u0001\u0013B1\u0011iUD\u001b\u000fs\u00012!OD\u001c\t\u0019!im\u0006b\u0001\u0013B1\u0011iUD\u001e\u000f\u007f\u00012!OD\u001f\t\u0019)\u0019e\u0006b\u0001\u0013B1\u0011iUD!\u000f\u000b\u00022!OD\"\t\u0019)yl\u0006b\u0001\u0013B1\u0011iUD$\u000f\u0017\u00022!OD%\t\u00191\te\u0006b\u0001\u0013B1\u0011iUD\'\u000f#\u00022!OD(\t\u00191Im\u0006b\u0001\u0013B)\u0011iUD*1B\u0019\u0011h\"\u0016\u0005\r\u001d]sC1\u0001J\u0005\u0005)\u0006#L\u0011\b\\\u0019mg\u0011\u001dDt\r[4\u0019P\"?\u0007\u0000\u001e\u0015q1BD\t\u000f/9ibb\t\b*\u001d=rQGD\u001e\u000f\u0003:9e\"\u0014\bT%\u0019qQ\f\u0012\u0003\u000fQ+\b\u000f\\33c\u0005i\u0001\u000e\\5tiR+\b\u000f\\3seI*bfb\u0019\bl\u001dEtqOD?\u000f\u0007;Iib$\b\u0016\u001emu\u0011UDT\u000f[;\u0019l\"/\b@\u001e\u0015w1ZDi\u000f/<inb9\bjV\u0011qQ\r\t\u0007#\n99g\"<\u0011\r\u0005\u001bv\u0011ND7!\rIt1\u000e\u0003\u0006/b\u0011\r!\u0013\t\u0007\u0003N;ygb\u001d\u0011\u0007e:\t\bB\u0003i1\t\u0007\u0011\n\u0005\u0004B\'\u001eUt\u0011\u0010\t\u0004s\u001d]D!B=\u0019\u0005\u0004I\u0005CB!T\u000fw:y\bE\u0002:\u000f{\"a!a\u0007\u0019\u0005\u0004I\u0005CB!T\u000f\u0003;)\tE\u0002:\u000f\u0007#a!!\u0013\u0019\u0005\u0004I\u0005CB!T\u000f\u000f;Y\tE\u0002:\u000f\u0013#a!! \u0019\u0005\u0004I\u0005CB!T\u000f\u001b;\t\nE\u0002:\u000f\u001f#a!a.\u0019\u0005\u0004I\u0005CB!T\u000f\';9\nE\u0002:\u000f+#a!a>\u0019\u0005\u0004I\u0005CB!T\u000f3;i\nE\u0002:\u000f7#aA!\u0010\u0019\u0005\u0004I\u0005CB!T\u000f?;\u0019\u000bE\u0002:\u000fC#aA!#\u0019\u0005\u0004I\u0005CB!T\u000fK;I\u000bE\u0002:\u000fO#aAa7\u0019\u0005\u0004I\u0005CB!T\u000fW;y\u000bE\u0002:\u000f[#Qa\u000f\rC\u0002%\u0003b!Q*\b2\u001eU\u0006cA\u001d\b4\u001211q\u0012\rC\u0002%\u0003b!Q*\b8\u001em\u0006cA\u001d\b:\u0012111\u001f\rC\u0002%\u0003b!Q*\b>\u001e\u0005\u0007cA\u001d\b@\u00121AQ\f\rC\u0002%\u0003b!Q*\bD\u001e\u001d\u0007cA\u001d\bF\u00121AQ\u001a\rC\u0002%\u0003b!Q*\bJ\u001e5\u0007cA\u001d\bL\u00121Q1\t\rC\u0002%\u0003b!Q*\bP\u001eM\u0007cA\u001d\bR\u00121Qq\u0018\rC\u0002%\u0003b!Q*\bV\u001ee\u0007cA\u001d\bX\u00121a\u0011\t\rC\u0002%\u0003b!Q*\b\\\u001e}\u0007cA\u001d\b^\u00121a\u0011\u001a\rC\u0002%\u0003b!Q*\bb\u001e\u0015\bcA\u001d\bd\u00121qq\u000b\rC\u0002%\u0003R!Q*\bhb\u00032!ODu\t\u00199Y\u000f\u0007b\u0001\u0013\n\ta\u000bE\u0018\"\u000f_<Igb\u001c\bv\u001dmt\u0011QDD\u000f\u001b;\u0019j\"\'\b \u001e\u0015v1VDY\u000fo;ilb1\bJ\u001e=wQ[Dn\u000fC<9/C\u0002\br\n\u0012q\u0001V;qY\u0016\u0014$\u0007"
    )
  ScalaInlineInfo: length = 0xE5 (unknown attribute)
   01 00 00 2D 00 C6 00 44 01 00 3A 00 3B 01 00 3D
   00 3E 00 00 78 00 3B 01 00 79 00 3E 00 00 7E 00
   3B 01 00 7F 00 3E 00 00 84 00 3B 01 00 85 00 3E
   00 00 8A 00 3B 01 00 8B 00 3E 00 00 90 00 3B 01
   00 91 00 3E 00 00 96 00 3B 01 00 97 00 3E 00 00
   9C 00 3B 01 00 9D 00 3E 00 00 A2 00 3B 01 00 A3
   00 3E 00 00 A8 00 3B 01 00 A9 00 3E 00 00 AE 00
   3B 01 00 AF 00 3E 00 00 48 00 3B 01 00 49 00 3E
   00 00 B4 00 3B 01 00 B5 00 3E 00 00 BA 00 3B 01
   00 BB 00 3E 00 00 C0 00 3B 01 00 C1 00 3E 00 00
   4E 00 3B 01 00 4F 00 3E 00 00 54 00 3B 01 00 55
   00 3E 00 00 5A 00 3B 01 00 5B 00 3E 00 00 60 00
   3B 01 00 61 00 3E 00 00 66 00 3B 01 00 67 00 3E
   00 00 6C 00 3B 01 00 6D 00 3E 00 00 72 00 3B 01
   00 73 00 3E 00
  ScalaSig: length = 0x3 (unknown attribute)
   05 02 00
