Classfile /Users/mw/Projects/slang-braindump/.jar/jar8/assemble/slang-braindump/assemble/content/shapeless/ops/tuple$ToSized$.class
  Last modified May 29, 2022; size 1722 bytes
  SHA-256 checksum a5076ee20d17d84f52912112672c154141e74c80cad515933b0a712c820cec2c
  Compiled from "tuples.scala"
public class shapeless.ops.tuple$ToSized$ implements java.io.Serializable
  minor version: 0
  major version: 52
  flags: (0x0021) ACC_PUBLIC, ACC_SUPER
  this_class: #2                          // shapeless/ops/tuple$ToSized$
  super_class: #4                         // java/lang/Object
  interfaces: 1, fields: 1, methods: 5, attributes: 4
Constant pool:
   #1 = Utf8               shapeless/ops/tuple$ToSized$
   #2 = Class              #1             // shapeless/ops/tuple$ToSized$
   #3 = Utf8               java/lang/Object
   #4 = Class              #3             // java/lang/Object
   #5 = Utf8               java/io/Serializable
   #6 = Class              #5             // java/io/Serializable
   #7 = Utf8               tuples.scala
   #8 = Utf8               shapeless/ops/hlist$ToSized
   #9 = Class              #8             // shapeless/ops/hlist$ToSized
  #10 = Utf8               shapeless/ops/hlist
  #11 = Class              #10            // shapeless/ops/hlist
  #12 = Utf8               ToSized
  #13 = Utf8               shapeless/ops/tuple$ToSized
  #14 = Class              #13            // shapeless/ops/tuple$ToSized
  #15 = Utf8               shapeless/ops/tuple
  #16 = Class              #15            // shapeless/ops/tuple
  #17 = Utf8               ToSized$
  #18 = Utf8               shapeless/ops/tuple$ToSized$$anon$45
  #19 = Class              #18            // shapeless/ops/tuple$ToSized$$anon$45
  #20 = Utf8               MODULE$
  #21 = Utf8               Lshapeless/ops/tuple$ToSized$;
  #22 = Utf8               <clinit>
  #23 = Utf8               ()V
  #24 = Utf8               <init>
  #25 = NameAndType        #24:#23        // "<init>":()V
  #26 = Methodref          #2.#25         // shapeless/ops/tuple$ToSized$."<init>":()V
  #27 = NameAndType        #20:#21        // MODULE$:Lshapeless/ops/tuple$ToSized$;
  #28 = Fieldref           #2.#27         // shapeless/ops/tuple$ToSized$.MODULE$:Lshapeless/ops/tuple$ToSized$;
  #29 = Utf8               apply
  #30 = Utf8               (Lshapeless/ops/tuple$ToSized;)Lshapeless/ops/tuple$ToSized;
  #31 = Utf8               <T:Ljava/lang/Object;M:Ljava/lang/Object;>(Lshapeless/ops/tuple$ToSized<TT;TM;>;)Lshapeless/ops/tuple$ToSized<TT;TM;>;
  #32 = Utf8               toSized
  #33 = Utf8               this
  #34 = Utf8               Lshapeless/ops/tuple$ToSized;
  #35 = Utf8               (Lshapeless/Generic;Lshapeless/ops/hlist$ToSized;)Lshapeless/ops/tuple$ToSized;
  #36 = Utf8               <T:Ljava/lang/Object;L::Lshapeless/HList;M:Ljava/lang/Object;>(Lshapeless/Generic<TT;>;Lshapeless/ops/hlist$ToSized<TL;TM;>;)Lshapeless/ops/tuple$ToSized<TT;TM;>;
  #37 = Utf8               gen
  #38 = Utf8               (Lshapeless/Generic;Lshapeless/ops/hlist$ToSized;)V
  #39 = NameAndType        #24:#38        // "<init>":(Lshapeless/Generic;Lshapeless/ops/hlist$ToSized;)V
  #40 = Methodref          #19.#39        // shapeless/ops/tuple$ToSized$$anon$45."<init>":(Lshapeless/Generic;Lshapeless/ops/hlist$ToSized;)V
  #41 = Utf8               Lshapeless/Generic;
  #42 = Utf8               Lshapeless/ops/hlist$ToSized;
  #43 = Utf8               writeReplace
  #44 = Utf8               ()Ljava/lang/Object;
  #45 = Utf8               scala/runtime/ModuleSerializationProxy
  #46 = Class              #45            // scala/runtime/ModuleSerializationProxy
  #47 = Utf8               (Ljava/lang/Class;)V
  #48 = NameAndType        #24:#47        // "<init>":(Ljava/lang/Class;)V
  #49 = Methodref          #46.#48        // scala/runtime/ModuleSerializationProxy."<init>":(Ljava/lang/Class;)V
  #50 = Methodref          #4.#25         // java/lang/Object."<init>":()V
  #51 = Utf8               Code
  #52 = Utf8               LineNumberTable
  #53 = Utf8               LocalVariableTable
  #54 = Utf8               Signature
  #55 = Utf8               MethodParameters
  #56 = Utf8               InnerClasses
  #57 = Utf8               SourceFile
  #58 = Utf8               ScalaInlineInfo
  #59 = Utf8               Scala
{
  public static final shapeless.ops.tuple$ToSized$ MODULE$;
    descriptor: Lshapeless/ops/tuple$ToSized$;
    flags: (0x0019) ACC_PUBLIC, ACC_STATIC, ACC_FINAL

  public static {};
    descriptor: ()V
    flags: (0x0009) ACC_PUBLIC, ACC_STATIC
    Code:
      stack=2, locals=0, args_size=0
         0: new           #2                  // class shapeless/ops/tuple$ToSized$
         3: dup
         4: invokespecial #26                 // Method "<init>":()V
         7: putstatic     #28                 // Field MODULE$:Lshapeless/ops/tuple$ToSized$;
        10: return
      LineNumberTable:
        line 1005: 0

  public <T extends java.lang.Object, M extends java.lang.Object> shapeless.ops.tuple$ToSized<T, M> apply(shapeless.ops.tuple$ToSized<T, M>);
    descriptor: (Lshapeless/ops/tuple$ToSized;)Lshapeless/ops/tuple$ToSized;
    flags: (0x0001) ACC_PUBLIC
    Code:
      stack=1, locals=2, args_size=2
         0: aload_1
         1: areturn
      LineNumberTable:
        line 1006: 0
      LocalVariableTable:
        Start  Length  Slot  Name   Signature
            0       2     0  this   Lshapeless/ops/tuple$ToSized$;
            0       2     1 toSized   Lshapeless/ops/tuple$ToSized;
    Signature: #31                          // <T:Ljava/lang/Object;M:Ljava/lang/Object;>(Lshapeless/ops/tuple$ToSized<TT;TM;>;)Lshapeless/ops/tuple$ToSized<TT;TM;>;
    MethodParameters:
      Name                           Flags
      toSized                        final

  public <T extends java.lang.Object, L extends shapeless.HList, M extends java.lang.Object> shapeless.ops.tuple$ToSized<T, M> toSized(shapeless.Generic<T>, shapeless.ops.hlist$ToSized<L, M>);
    descriptor: (Lshapeless/Generic;Lshapeless/ops/hlist$ToSized;)Lshapeless/ops/tuple$ToSized;
    flags: (0x0001) ACC_PUBLIC
    Code:
      stack=4, locals=3, args_size=3
         0: new           #19                 // class shapeless/ops/tuple$ToSized$$anon$45
         3: dup
         4: aload_1
         5: aload_2
         6: invokespecial #40                 // Method shapeless/ops/tuple$ToSized$$anon$45."<init>":(Lshapeless/Generic;Lshapeless/ops/hlist$ToSized;)V
         9: areturn
      LineNumberTable:
        line 1012: 0
      LocalVariableTable:
        Start  Length  Slot  Name   Signature
            0      10     0  this   Lshapeless/ops/tuple$ToSized$;
            0      10     1   gen   Lshapeless/Generic;
            0      10     2 toSized   Lshapeless/ops/hlist$ToSized;
    Signature: #36                          // <T:Ljava/lang/Object;L::Lshapeless/HList;M:Ljava/lang/Object;>(Lshapeless/Generic<TT;>;Lshapeless/ops/hlist$ToSized<TL;TM;>;)Lshapeless/ops/tuple$ToSized<TT;TM;>;
    MethodParameters:
      Name                           Flags
      gen                            final
      toSized                        final

  private java.lang.Object writeReplace();
    descriptor: ()Ljava/lang/Object;
    flags: (0x0002) ACC_PRIVATE
    Code:
      stack=3, locals=1, args_size=1
         0: new           #46                 // class scala/runtime/ModuleSerializationProxy
         3: dup
         4: ldc           #2                  // class shapeless/ops/tuple$ToSized$
         6: invokespecial #49                 // Method scala/runtime/ModuleSerializationProxy."<init>":(Ljava/lang/Class;)V
         9: areturn
      LineNumberTable:
        line 1005: 0
      LocalVariableTable:
        Start  Length  Slot  Name   Signature
            0      10     0  this   Lshapeless/ops/tuple$ToSized$;

  public shapeless.ops.tuple$ToSized$();
    descriptor: ()V
    flags: (0x0001) ACC_PUBLIC
    Code:
      stack=1, locals=1, args_size=1
         0: aload_0
         1: invokespecial #50                 // Method java/lang/Object."<init>":()V
         4: return
      LineNumberTable:
        line 1023: 0
        line 1005: 4
      LocalVariableTable:
        Start  Length  Slot  Name   Signature
            0       5     0  this   Lshapeless/ops/tuple$ToSized$;
}
InnerClasses:
  public static #12= #9 of #11;           // ToSized=class shapeless/ops/hlist$ToSized of class shapeless/ops/hlist
  public static #12= #14 of #16;          // ToSized=class shapeless/ops/tuple$ToSized of class shapeless/ops/tuple
  public static #17= #2 of #16;           // ToSized$=class shapeless/ops/tuple$ToSized$ of class shapeless/ops/tuple
  public final #19;                       // class shapeless/ops/tuple$ToSized$$anon$45
SourceFile: "tuples.scala"
  ScalaInlineInfo: length = 0x18 (unknown attribute)
   01 01 00 04 00 18 00 17 01 00 1D 00 1E 01 00 20
   00 23 01 00 2B 00 2C 01
  Scala: length = 0x0 (unknown attribute)

