Classfile /Users/mw/Projects/slang-braindump/.jar/jar8/assemble/slang-braindump/assemble/content/shapeless/ops/tuple$RightScanner$.class
  Last modified May 29, 2022; size 2085 bytes
  SHA-256 checksum fdd9aa1e7fe3cd2174112894cb66c7fa1656ed042607465d32401f2c5d388fbd
  Compiled from "tuples.scala"
public class shapeless.ops.tuple$RightScanner$ implements java.io.Serializable
  minor version: 0
  major version: 52
  flags: (0x0021) ACC_PUBLIC, ACC_SUPER
  this_class: #2                          // shapeless/ops/tuple$RightScanner$
  super_class: #4                         // java/lang/Object
  interfaces: 1, fields: 1, methods: 5, attributes: 4
Constant pool:
   #1 = Utf8               shapeless/ops/tuple$RightScanner$
   #2 = Class              #1             // shapeless/ops/tuple$RightScanner$
   #3 = Utf8               java/lang/Object
   #4 = Class              #3             // java/lang/Object
   #5 = Utf8               java/io/Serializable
   #6 = Class              #5             // java/io/Serializable
   #7 = Utf8               tuples.scala
   #8 = Utf8               shapeless/ops/hlist$RightScanner
   #9 = Class              #8             // shapeless/ops/hlist$RightScanner
  #10 = Utf8               shapeless/ops/hlist
  #11 = Class              #10            // shapeless/ops/hlist
  #12 = Utf8               RightScanner
  #13 = Utf8               shapeless/ops/hlist$Tupler
  #14 = Class              #13            // shapeless/ops/hlist$Tupler
  #15 = Utf8               Tupler
  #16 = Utf8               shapeless/ops/tuple$RightScanner
  #17 = Class              #16            // shapeless/ops/tuple$RightScanner
  #18 = Utf8               shapeless/ops/tuple
  #19 = Class              #18            // shapeless/ops/tuple
  #20 = Utf8               RightScanner$
  #21 = Utf8               shapeless/ops/tuple$RightScanner$$anon$55
  #22 = Class              #21            // shapeless/ops/tuple$RightScanner$$anon$55
  #23 = Utf8               MODULE$
  #24 = Utf8               Lshapeless/ops/tuple$RightScanner$;
  #25 = Utf8               <clinit>
  #26 = Utf8               ()V
  #27 = Utf8               <init>
  #28 = NameAndType        #27:#26        // "<init>":()V
  #29 = Methodref          #2.#28         // shapeless/ops/tuple$RightScanner$."<init>":()V
  #30 = NameAndType        #23:#24        // MODULE$:Lshapeless/ops/tuple$RightScanner$;
  #31 = Fieldref           #2.#30         // shapeless/ops/tuple$RightScanner$.MODULE$:Lshapeless/ops/tuple$RightScanner$;
  #32 = Utf8               apply
  #33 = Utf8               (Lshapeless/ops/tuple$RightScanner;)Lshapeless/ops/tuple$RightScanner;
  #34 = Utf8               <T:Ljava/lang/Object;In:Ljava/lang/Object;P::Lshapeless/Poly;>(Lshapeless/ops/tuple$RightScanner<TT;TIn;TP;>;)Lshapeless/ops/tuple$RightScanner<TT;TIn;TP;>;
  #35 = Utf8               scanR
  #36 = Utf8               this
  #37 = Utf8               Lshapeless/ops/tuple$RightScanner;
  #38 = Utf8               scanner
  #39 = Utf8               (Lshapeless/Generic;Lshapeless/ops/hlist$RightScanner;Lshapeless/ops/hlist$Tupler;)Lshapeless/ops/tuple$RightScanner;
  #40 = Utf8               <T:Ljava/lang/Object;L::Lshapeless/HList;In:Ljava/lang/Object;P::Lshapeless/Poly;R::Lshapeless/HList;>(Lshapeless/Generic<TT;>;Lshapeless/ops/hlist$RightScanner<TL;TIn;TP;>;Lshapeless/ops/hlist$Tupler<TR;>;)Lshapeless/ops/tuple$RightScanner<TT;TIn;TP;>;
  #41 = Utf8               gen
  #42 = Utf8               tp
  #43 = Utf8               (Lshapeless/ops/hlist$Tupler;Lshapeless/ops/hlist$RightScanner;Lshapeless/Generic;)V
  #44 = NameAndType        #27:#43        // "<init>":(Lshapeless/ops/hlist$Tupler;Lshapeless/ops/hlist$RightScanner;Lshapeless/Generic;)V
  #45 = Methodref          #22.#44        // shapeless/ops/tuple$RightScanner$$anon$55."<init>":(Lshapeless/ops/hlist$Tupler;Lshapeless/ops/hlist$RightScanner;Lshapeless/Generic;)V
  #46 = Utf8               Lshapeless/Generic;
  #47 = Utf8               Lshapeless/ops/hlist$RightScanner;
  #48 = Utf8               Lshapeless/ops/hlist$Tupler;
  #49 = Utf8               writeReplace
  #50 = Utf8               ()Ljava/lang/Object;
  #51 = Utf8               scala/runtime/ModuleSerializationProxy
  #52 = Class              #51            // scala/runtime/ModuleSerializationProxy
  #53 = Utf8               (Ljava/lang/Class;)V
  #54 = NameAndType        #27:#53        // "<init>":(Ljava/lang/Class;)V
  #55 = Methodref          #52.#54        // scala/runtime/ModuleSerializationProxy."<init>":(Ljava/lang/Class;)V
  #56 = Methodref          #4.#28         // java/lang/Object."<init>":()V
  #57 = Utf8               Code
  #58 = Utf8               LineNumberTable
  #59 = Utf8               LocalVariableTable
  #60 = Utf8               Signature
  #61 = Utf8               MethodParameters
  #62 = Utf8               InnerClasses
  #63 = Utf8               SourceFile
  #64 = Utf8               ScalaInlineInfo
  #65 = Utf8               Scala
{
  public static final shapeless.ops.tuple$RightScanner$ MODULE$;
    descriptor: Lshapeless/ops/tuple$RightScanner$;
    flags: (0x0019) ACC_PUBLIC, ACC_STATIC, ACC_FINAL

  public static {};
    descriptor: ()V
    flags: (0x0009) ACC_PUBLIC, ACC_STATIC
    Code:
      stack=2, locals=0, args_size=0
         0: new           #2                  // class shapeless/ops/tuple$RightScanner$
         3: dup
         4: invokespecial #29                 // Method "<init>":()V
         7: putstatic     #31                 // Field MODULE$:Lshapeless/ops/tuple$RightScanner$;
        10: return
      LineNumberTable:
        line 1187: 0

  public <T extends java.lang.Object, In extends java.lang.Object, P extends shapeless.Poly> shapeless.ops.tuple$RightScanner<T, In, P> apply(shapeless.ops.tuple$RightScanner<T, In, P>);
    descriptor: (Lshapeless/ops/tuple$RightScanner;)Lshapeless/ops/tuple$RightScanner;
    flags: (0x0001) ACC_PUBLIC
    Code:
      stack=1, locals=2, args_size=2
         0: aload_1
         1: areturn
      LineNumberTable:
        line 1188: 0
      LocalVariableTable:
        Start  Length  Slot  Name   Signature
            0       2     0  this   Lshapeless/ops/tuple$RightScanner$;
            0       2     1 scanR   Lshapeless/ops/tuple$RightScanner;
    Signature: #34                          // <T:Ljava/lang/Object;In:Ljava/lang/Object;P::Lshapeless/Poly;>(Lshapeless/ops/tuple$RightScanner<TT;TIn;TP;>;)Lshapeless/ops/tuple$RightScanner<TT;TIn;TP;>;
    MethodParameters:
      Name                           Flags
      scanR                          final

  public <T extends java.lang.Object, L extends shapeless.HList, In extends java.lang.Object, P extends shapeless.Poly, R extends shapeless.HList> shapeless.ops.tuple$RightScanner<T, In, P> scanner(shapeless.Generic<T>, shapeless.ops.hlist$RightScanner<L, In, P>, shapeless.ops.hlist$Tupler<R>);
    descriptor: (Lshapeless/Generic;Lshapeless/ops/hlist$RightScanner;Lshapeless/ops/hlist$Tupler;)Lshapeless/ops/tuple$RightScanner;
    flags: (0x0001) ACC_PUBLIC
    Code:
      stack=5, locals=4, args_size=4
         0: new           #22                 // class shapeless/ops/tuple$RightScanner$$anon$55
         3: dup
         4: aload_3
         5: aload_2
         6: aload_1
         7: invokespecial #45                 // Method shapeless/ops/tuple$RightScanner$$anon$55."<init>":(Lshapeless/ops/hlist$Tupler;Lshapeless/ops/hlist$RightScanner;Lshapeless/Generic;)V
        10: areturn
      LineNumberTable:
        line 1197: 0
      LocalVariableTable:
        Start  Length  Slot  Name   Signature
            0      11     0  this   Lshapeless/ops/tuple$RightScanner$;
            0      11     1   gen   Lshapeless/Generic;
            0      11     2 scanR   Lshapeless/ops/hlist$RightScanner;
            0      11     3    tp   Lshapeless/ops/hlist$Tupler;
    Signature: #40                          // <T:Ljava/lang/Object;L::Lshapeless/HList;In:Ljava/lang/Object;P::Lshapeless/Poly;R::Lshapeless/HList;>(Lshapeless/Generic<TT;>;Lshapeless/ops/hlist$RightScanner<TL;TIn;TP;>;Lshapeless/ops/hlist$Tupler<TR;>;)Lshapeless/ops/tuple$RightScanner<TT;TIn;TP;>;
    MethodParameters:
      Name                           Flags
      gen                            final
      scanR                          final
      tp                             final

  private java.lang.Object writeReplace();
    descriptor: ()Ljava/lang/Object;
    flags: (0x0002) ACC_PRIVATE
    Code:
      stack=3, locals=1, args_size=1
         0: new           #52                 // class scala/runtime/ModuleSerializationProxy
         3: dup
         4: ldc           #2                  // class shapeless/ops/tuple$RightScanner$
         6: invokespecial #55                 // Method scala/runtime/ModuleSerializationProxy."<init>":(Ljava/lang/Class;)V
         9: areturn
      LineNumberTable:
        line 1187: 0
      LocalVariableTable:
        Start  Length  Slot  Name   Signature
            0      10     0  this   Lshapeless/ops/tuple$RightScanner$;

  public shapeless.ops.tuple$RightScanner$();
    descriptor: ()V
    flags: (0x0001) ACC_PUBLIC
    Code:
      stack=1, locals=1, args_size=1
         0: aload_0
         1: invokespecial #56                 // Method java/lang/Object."<init>":()V
         4: return
      LineNumberTable:
        line 1209: 0
        line 1187: 4
      LocalVariableTable:
        Start  Length  Slot  Name   Signature
            0       5     0  this   Lshapeless/ops/tuple$RightScanner$;
}
InnerClasses:
  public static #12= #9 of #11;           // RightScanner=class shapeless/ops/hlist$RightScanner of class shapeless/ops/hlist
  public static #15= #14 of #11;          // Tupler=class shapeless/ops/hlist$Tupler of class shapeless/ops/hlist
  public static #12= #17 of #19;          // RightScanner=class shapeless/ops/tuple$RightScanner of class shapeless/ops/tuple
  public static #20= #2 of #19;           // RightScanner$=class shapeless/ops/tuple$RightScanner$ of class shapeless/ops/tuple
  public final #22;                       // class shapeless/ops/tuple$RightScanner$$anon$55
SourceFile: "tuples.scala"
  ScalaInlineInfo: length = 0x18 (unknown attribute)
   01 01 00 04 00 1B 00 1A 01 00 20 00 21 01 00 26
   00 27 01 00 31 00 32 01
  Scala: length = 0x0 (unknown attribute)

