Classfile /Users/mw/Projects/slang-braindump/.jar/jar8/assemble/slang-braindump/assemble/content/shapeless/ops/tuple$ZipWithIndex$.class
  Last modified May 29, 2022; size 1989 bytes
  SHA-256 checksum d19e4f27f5c085d06c4dd4469e0f0541f35632ebf9bc3b0a1975834e76194a74
  Compiled from "tuples.scala"
public class shapeless.ops.tuple$ZipWithIndex$ implements java.io.Serializable
  minor version: 0
  major version: 52
  flags: (0x0021) ACC_PUBLIC, ACC_SUPER
  this_class: #2                          // shapeless/ops/tuple$ZipWithIndex$
  super_class: #4                         // java/lang/Object
  interfaces: 1, fields: 1, methods: 5, attributes: 4
Constant pool:
   #1 = Utf8               shapeless/ops/tuple$ZipWithIndex$
   #2 = Class              #1             // shapeless/ops/tuple$ZipWithIndex$
   #3 = Utf8               java/lang/Object
   #4 = Class              #3             // java/lang/Object
   #5 = Utf8               java/io/Serializable
   #6 = Class              #5             // java/io/Serializable
   #7 = Utf8               tuples.scala
   #8 = Utf8               shapeless/ops/hlist$Tupler
   #9 = Class              #8             // shapeless/ops/hlist$Tupler
  #10 = Utf8               shapeless/ops/hlist
  #11 = Class              #10            // shapeless/ops/hlist
  #12 = Utf8               Tupler
  #13 = Utf8               shapeless/ops/hlist$ZipWithIndex
  #14 = Class              #13            // shapeless/ops/hlist$ZipWithIndex
  #15 = Utf8               ZipWithIndex
  #16 = Utf8               shapeless/ops/tuple$ZipWithIndex
  #17 = Class              #16            // shapeless/ops/tuple$ZipWithIndex
  #18 = Utf8               shapeless/ops/tuple
  #19 = Class              #18            // shapeless/ops/tuple
  #20 = Utf8               ZipWithIndex$
  #21 = Utf8               shapeless/ops/tuple$ZipWithIndex$$anon$37
  #22 = Class              #21            // shapeless/ops/tuple$ZipWithIndex$$anon$37
  #23 = Utf8               MODULE$
  #24 = Utf8               Lshapeless/ops/tuple$ZipWithIndex$;
  #25 = Utf8               <clinit>
  #26 = Utf8               ()V
  #27 = Utf8               <init>
  #28 = NameAndType        #27:#26        // "<init>":()V
  #29 = Methodref          #2.#28         // shapeless/ops/tuple$ZipWithIndex$."<init>":()V
  #30 = NameAndType        #23:#24        // MODULE$:Lshapeless/ops/tuple$ZipWithIndex$;
  #31 = Fieldref           #2.#30         // shapeless/ops/tuple$ZipWithIndex$.MODULE$:Lshapeless/ops/tuple$ZipWithIndex$;
  #32 = Utf8               apply
  #33 = Utf8               (Lshapeless/ops/tuple$ZipWithIndex;)Lshapeless/ops/tuple$ZipWithIndex;
  #34 = Utf8               <T:Ljava/lang/Object;>(Lshapeless/ops/tuple$ZipWithIndex<TT;>;)Lshapeless/ops/tuple$ZipWithIndex<TT;>;
  #35 = Utf8               zip
  #36 = Utf8               this
  #37 = Utf8               Lshapeless/ops/tuple$ZipWithIndex;
  #38 = Utf8               zipConst
  #39 = Utf8               (Lshapeless/Generic;Lshapeless/ops/hlist$ZipWithIndex;Lshapeless/ops/hlist$Tupler;)Lshapeless/ops/tuple$ZipWithIndex;
  #40 = Utf8               <T:Ljava/lang/Object;L1::Lshapeless/HList;L2::Lshapeless/HList;>(Lshapeless/Generic<TT;>;Lshapeless/ops/hlist$ZipWithIndex<TL1;>;Lshapeless/ops/hlist$Tupler<TL2;>;)Lshapeless/ops/tuple$ZipWithIndex<TT;>;
  #41 = Utf8               gen
  #42 = Utf8               zipper
  #43 = Utf8               tp
  #44 = Utf8               (Lshapeless/ops/hlist$Tupler;Lshapeless/ops/hlist$ZipWithIndex;Lshapeless/Generic;)V
  #45 = NameAndType        #27:#44        // "<init>":(Lshapeless/ops/hlist$Tupler;Lshapeless/ops/hlist$ZipWithIndex;Lshapeless/Generic;)V
  #46 = Methodref          #22.#45        // shapeless/ops/tuple$ZipWithIndex$$anon$37."<init>":(Lshapeless/ops/hlist$Tupler;Lshapeless/ops/hlist$ZipWithIndex;Lshapeless/Generic;)V
  #47 = Utf8               Lshapeless/Generic;
  #48 = Utf8               Lshapeless/ops/hlist$ZipWithIndex;
  #49 = Utf8               Lshapeless/ops/hlist$Tupler;
  #50 = Utf8               writeReplace
  #51 = Utf8               ()Ljava/lang/Object;
  #52 = Utf8               scala/runtime/ModuleSerializationProxy
  #53 = Class              #52            // scala/runtime/ModuleSerializationProxy
  #54 = Utf8               (Ljava/lang/Class;)V
  #55 = NameAndType        #27:#54        // "<init>":(Ljava/lang/Class;)V
  #56 = Methodref          #53.#55        // scala/runtime/ModuleSerializationProxy."<init>":(Ljava/lang/Class;)V
  #57 = Methodref          #4.#28         // java/lang/Object."<init>":()V
  #58 = Utf8               Code
  #59 = Utf8               LineNumberTable
  #60 = Utf8               LocalVariableTable
  #61 = Utf8               Signature
  #62 = Utf8               MethodParameters
  #63 = Utf8               InnerClasses
  #64 = Utf8               SourceFile
  #65 = Utf8               ScalaInlineInfo
  #66 = Utf8               Scala
{
  public static final shapeless.ops.tuple$ZipWithIndex$ MODULE$;
    descriptor: Lshapeless/ops/tuple$ZipWithIndex$;
    flags: (0x0019) ACC_PUBLIC, ACC_STATIC, ACC_FINAL

  public static {};
    descriptor: ()V
    flags: (0x0009) ACC_PUBLIC, ACC_STATIC
    Code:
      stack=2, locals=0, args_size=0
         0: new           #2                  // class shapeless/ops/tuple$ZipWithIndex$
         3: dup
         4: invokespecial #29                 // Method "<init>":()V
         7: putstatic     #31                 // Field MODULE$:Lshapeless/ops/tuple$ZipWithIndex$;
        10: return
      LineNumberTable:
        line 837: 0

  public <T extends java.lang.Object> shapeless.ops.tuple$ZipWithIndex<T> apply(shapeless.ops.tuple$ZipWithIndex<T>);
    descriptor: (Lshapeless/ops/tuple$ZipWithIndex;)Lshapeless/ops/tuple$ZipWithIndex;
    flags: (0x0001) ACC_PUBLIC
    Code:
      stack=1, locals=2, args_size=2
         0: aload_1
         1: areturn
      LineNumberTable:
        line 838: 0
      LocalVariableTable:
        Start  Length  Slot  Name   Signature
            0       2     0  this   Lshapeless/ops/tuple$ZipWithIndex$;
            0       2     1   zip   Lshapeless/ops/tuple$ZipWithIndex;
    Signature: #34                          // <T:Ljava/lang/Object;>(Lshapeless/ops/tuple$ZipWithIndex<TT;>;)Lshapeless/ops/tuple$ZipWithIndex<TT;>;
    MethodParameters:
      Name                           Flags
      zip                            final

  public <T extends java.lang.Object, L1 extends shapeless.HList, L2 extends shapeless.HList> shapeless.ops.tuple$ZipWithIndex<T> zipConst(shapeless.Generic<T>, shapeless.ops.hlist$ZipWithIndex<L1>, shapeless.ops.hlist$Tupler<L2>);
    descriptor: (Lshapeless/Generic;Lshapeless/ops/hlist$ZipWithIndex;Lshapeless/ops/hlist$Tupler;)Lshapeless/ops/tuple$ZipWithIndex;
    flags: (0x0001) ACC_PUBLIC
    Code:
      stack=5, locals=4, args_size=4
         0: new           #22                 // class shapeless/ops/tuple$ZipWithIndex$$anon$37
         3: dup
         4: aload_3
         5: aload_2
         6: aload_1
         7: invokespecial #46                 // Method shapeless/ops/tuple$ZipWithIndex$$anon$37."<init>":(Lshapeless/ops/hlist$Tupler;Lshapeless/ops/hlist$ZipWithIndex;Lshapeless/Generic;)V
        10: areturn
      LineNumberTable:
        line 844: 0
      LocalVariableTable:
        Start  Length  Slot  Name   Signature
            0      11     0  this   Lshapeless/ops/tuple$ZipWithIndex$;
            0      11     1   gen   Lshapeless/Generic;
            0      11     2 zipper   Lshapeless/ops/hlist$ZipWithIndex;
            0      11     3    tp   Lshapeless/ops/hlist$Tupler;
    Signature: #40                          // <T:Ljava/lang/Object;L1::Lshapeless/HList;L2::Lshapeless/HList;>(Lshapeless/Generic<TT;>;Lshapeless/ops/hlist$ZipWithIndex<TL1;>;Lshapeless/ops/hlist$Tupler<TL2;>;)Lshapeless/ops/tuple$ZipWithIndex<TT;>;
    MethodParameters:
      Name                           Flags
      gen                            final
      zipper                         final
      tp                             final

  private java.lang.Object writeReplace();
    descriptor: ()Ljava/lang/Object;
    flags: (0x0002) ACC_PRIVATE
    Code:
      stack=3, locals=1, args_size=1
         0: new           #53                 // class scala/runtime/ModuleSerializationProxy
         3: dup
         4: ldc           #2                  // class shapeless/ops/tuple$ZipWithIndex$
         6: invokespecial #56                 // Method scala/runtime/ModuleSerializationProxy."<init>":(Ljava/lang/Class;)V
         9: areturn
      LineNumberTable:
        line 837: 0
      LocalVariableTable:
        Start  Length  Slot  Name   Signature
            0      10     0  this   Lshapeless/ops/tuple$ZipWithIndex$;

  public shapeless.ops.tuple$ZipWithIndex$();
    descriptor: ()V
    flags: (0x0001) ACC_PUBLIC
    Code:
      stack=1, locals=1, args_size=1
         0: aload_0
         1: invokespecial #57                 // Method java/lang/Object."<init>":()V
         4: return
      LineNumberTable:
        line 856: 0
        line 837: 4
      LocalVariableTable:
        Start  Length  Slot  Name   Signature
            0       5     0  this   Lshapeless/ops/tuple$ZipWithIndex$;
}
InnerClasses:
  public static #12= #9 of #11;           // Tupler=class shapeless/ops/hlist$Tupler of class shapeless/ops/hlist
  public static #15= #14 of #11;          // ZipWithIndex=class shapeless/ops/hlist$ZipWithIndex of class shapeless/ops/hlist
  public static #15= #17 of #19;          // ZipWithIndex=class shapeless/ops/tuple$ZipWithIndex of class shapeless/ops/tuple
  public static #20= #2 of #19;           // ZipWithIndex$=class shapeless/ops/tuple$ZipWithIndex$ of class shapeless/ops/tuple
  public final #22;                       // class shapeless/ops/tuple$ZipWithIndex$$anon$37
SourceFile: "tuples.scala"
  ScalaInlineInfo: length = 0x18 (unknown attribute)
   01 01 00 04 00 1B 00 1A 01 00 20 00 21 01 00 32
   00 33 01 00 26 00 27 01
  Scala: length = 0x0 (unknown attribute)

