Classfile /Users/mw/Projects/slang-braindump/.jar/jar8/assemble/slang-braindump/assemble/content/shapeless/ops/union$Fields$.class
  Last modified May 29, 2022; size 1958 bytes
  SHA-256 checksum 9eed162f59c06a2ae321873c964bb60eb43d1ecdb320f7cf79cdab668031d1f5
  Compiled from "unions.scala"
public class shapeless.ops.union$Fields$ implements java.io.Serializable
  minor version: 0
  major version: 52
  flags: (0x0021) ACC_PUBLIC, ACC_SUPER
  this_class: #2                          // shapeless/ops/union$Fields$
  super_class: #4                         // java/lang/Object
  interfaces: 1, fields: 2, methods: 6, attributes: 4
Constant pool:
   #1 = Utf8               shapeless/ops/union$Fields$
   #2 = Class              #1             // shapeless/ops/union$Fields$
   #3 = Utf8               java/lang/Object
   #4 = Class              #3             // java/lang/Object
   #5 = Utf8               java/io/Serializable
   #6 = Class              #5             // java/io/Serializable
   #7 = Utf8               unions.scala
   #8 = Utf8               shapeless/ops/union$Fields
   #9 = Class              #8             // shapeless/ops/union$Fields
  #10 = Utf8               shapeless/ops/union
  #11 = Class              #10            // shapeless/ops/union
  #12 = Utf8               Fields
  #13 = Utf8               Fields$
  #14 = Utf8               shapeless/ops/union$Fields$$anon$7
  #15 = Class              #14            // shapeless/ops/union$Fields$$anon$7
  #16 = Utf8               shapeless/ops/union$Fields$$anon$8
  #17 = Class              #16            // shapeless/ops/union$Fields$$anon$8
  #18 = Utf8               MODULE$
  #19 = Utf8               Lshapeless/ops/union$Fields$;
  #20 = Utf8               cnilFields
  #21 = Utf8               Lshapeless/ops/union$Fields;
  #22 = Utf8               Lshapeless/ops/union$Fields<Lshapeless/CNil;>;
  #23 = Utf8               <clinit>
  #24 = Utf8               ()V
  #25 = Utf8               <init>
  #26 = NameAndType        #25:#24        // "<init>":()V
  #27 = Methodref          #2.#26         // shapeless/ops/union$Fields$."<init>":()V
  #28 = NameAndType        #18:#19        // MODULE$:Lshapeless/ops/union$Fields$;
  #29 = Fieldref           #2.#28         // shapeless/ops/union$Fields$.MODULE$:Lshapeless/ops/union$Fields$;
  #30 = Methodref          #15.#26        // shapeless/ops/union$Fields$$anon$7."<init>":()V
  #31 = NameAndType        #20:#21        // cnilFields:Lshapeless/ops/union$Fields;
  #32 = Fieldref           #2.#31         // shapeless/ops/union$Fields$.cnilFields:Lshapeless/ops/union$Fields;
  #33 = Utf8               apply
  #34 = Utf8               (Lshapeless/ops/union$Fields;)Lshapeless/ops/union$Fields;
  #35 = Utf8               <U::Lshapeless/Coproduct;>(Lshapeless/ops/union$Fields<TU;>;)Lshapeless/ops/union$Fields<TU;>;
  #36 = Utf8               fields
  #37 = Utf8               this
  #38 = Utf8               ()Lshapeless/ops/union$Fields;
  #39 = Utf8               ()Lshapeless/ops/union$Fields<Lshapeless/CNil;>;
  #40 = Utf8               cconsFields
  #41 = Utf8               (Lshapeless/Witness;Lshapeless/ops/union$Fields;)Lshapeless/ops/union$Fields;
  #42 = Utf8               <K:Ljava/lang/Object;V:Ljava/lang/Object;T::Lshapeless/Coproduct;>(Lshapeless/Witness;Lshapeless/ops/union$Fields<TT;>;)Lshapeless/ops/union$Fields<Lshapeless/$colon$plus$colon<TV;TT;>;>;
  #43 = Utf8               key
  #44 = Utf8               tailFields
  #45 = Utf8               (Lshapeless/Witness;Lshapeless/ops/union$Fields;)V
  #46 = NameAndType        #25:#45        // "<init>":(Lshapeless/Witness;Lshapeless/ops/union$Fields;)V
  #47 = Methodref          #17.#46        // shapeless/ops/union$Fields$$anon$8."<init>":(Lshapeless/Witness;Lshapeless/ops/union$Fields;)V
  #48 = Utf8               Lshapeless/Witness;
  #49 = Utf8               writeReplace
  #50 = Utf8               ()Ljava/lang/Object;
  #51 = Utf8               scala/runtime/ModuleSerializationProxy
  #52 = Class              #51            // scala/runtime/ModuleSerializationProxy
  #53 = Utf8               (Ljava/lang/Class;)V
  #54 = NameAndType        #25:#53        // "<init>":(Ljava/lang/Class;)V
  #55 = Methodref          #52.#54        // scala/runtime/ModuleSerializationProxy."<init>":(Ljava/lang/Class;)V
  #56 = Methodref          #4.#26         // java/lang/Object."<init>":()V
  #57 = Utf8               Signature
  #58 = Utf8               Code
  #59 = Utf8               LineNumberTable
  #60 = Utf8               LocalVariableTable
  #61 = Utf8               MethodParameters
  #62 = Utf8               InnerClasses
  #63 = Utf8               SourceFile
  #64 = Utf8               ScalaInlineInfo
  #65 = Utf8               Scala
{
  public static final shapeless.ops.union$Fields$ MODULE$;
    descriptor: Lshapeless/ops/union$Fields$;
    flags: (0x0019) ACC_PUBLIC, ACC_STATIC, ACC_FINAL

  private static final shapeless.ops.union$Fields<shapeless.CNil> cnilFields;
    descriptor: Lshapeless/ops/union$Fields;
    flags: (0x001a) ACC_PRIVATE, ACC_STATIC, ACC_FINAL
    Signature: #22                          // Lshapeless/ops/union$Fields<Lshapeless/CNil;>;

  public static {};
    descriptor: ()V
    flags: (0x0009) ACC_PUBLIC, ACC_STATIC
    Code:
      stack=2, locals=0, args_size=0
         0: new           #2                  // class shapeless/ops/union$Fields$
         3: dup
         4: invokespecial #27                 // Method "<init>":()V
         7: putstatic     #29                 // Field MODULE$:Lshapeless/ops/union$Fields$;
        10: new           #15                 // class shapeless/ops/union$Fields$$anon$7
        13: dup
        14: invokespecial #30                 // Method shapeless/ops/union$Fields$$anon$7."<init>":()V
        17: putstatic     #32                 // Field cnilFields:Lshapeless/ops/union$Fields;
        20: return
      LineNumberTable:
        line 127: 0
        line 133: 10
        line 132: 17
        line 127: 20

  public <U extends shapeless.Coproduct> shapeless.ops.union$Fields<U> apply(shapeless.ops.union$Fields<U>);
    descriptor: (Lshapeless/ops/union$Fields;)Lshapeless/ops/union$Fields;
    flags: (0x0001) ACC_PUBLIC
    Code:
      stack=1, locals=2, args_size=2
         0: aload_1
         1: areturn
      LineNumberTable:
        line 128: 0
      LocalVariableTable:
        Start  Length  Slot  Name   Signature
            0       2     0  this   Lshapeless/ops/union$Fields$;
            0       2     1 fields   Lshapeless/ops/union$Fields;
    Signature: #35                          // <U::Lshapeless/Coproduct;>(Lshapeless/ops/union$Fields<TU;>;)Lshapeless/ops/union$Fields<TU;>;
    MethodParameters:
      Name                           Flags
      fields                         final

  public shapeless.ops.union$Fields<shapeless.CNil> cnilFields();
    descriptor: ()Lshapeless/ops/union$Fields;
    flags: (0x0001) ACC_PUBLIC
    Code:
      stack=1, locals=1, args_size=1
         0: getstatic     #32                 // Field cnilFields:Lshapeless/ops/union$Fields;
         3: areturn
      LineNumberTable:
        line 132: 0
      LocalVariableTable:
        Start  Length  Slot  Name   Signature
            0       4     0  this   Lshapeless/ops/union$Fields$;
    Signature: #39                          // ()Lshapeless/ops/union$Fields<Lshapeless/CNil;>;

  public <K extends java.lang.Object, V extends java.lang.Object, T extends shapeless.Coproduct> shapeless.ops.union$Fields<shapeless.$colon$plus$colon<V, T>> cconsFields(shapeless.Witness, shapeless.ops.union$Fields<T>);
    descriptor: (Lshapeless/Witness;Lshapeless/ops/union$Fields;)Lshapeless/ops/union$Fields;
    flags: (0x0001) ACC_PUBLIC
    Code:
      stack=4, locals=3, args_size=3
         0: new           #17                 // class shapeless/ops/union$Fields$$anon$8
         3: dup
         4: aload_1
         5: aload_2
         6: invokespecial #47                 // Method shapeless/ops/union$Fields$$anon$8."<init>":(Lshapeless/Witness;Lshapeless/ops/union$Fields;)V
         9: areturn
      LineNumberTable:
        line 142: 0
      LocalVariableTable:
        Start  Length  Slot  Name   Signature
            0      10     0  this   Lshapeless/ops/union$Fields$;
            0      10     1   key   Lshapeless/Witness;
            0      10     2 tailFields   Lshapeless/ops/union$Fields;
    Signature: #42                          // <K:Ljava/lang/Object;V:Ljava/lang/Object;T::Lshapeless/Coproduct;>(Lshapeless/Witness;Lshapeless/ops/union$Fields<TT;>;)Lshapeless/ops/union$Fields<Lshapeless/$colon$plus$colon<TV;TT;>;>;
    MethodParameters:
      Name                           Flags
      key                            final
      tailFields                     final

  private java.lang.Object writeReplace();
    descriptor: ()Ljava/lang/Object;
    flags: (0x0002) ACC_PRIVATE
    Code:
      stack=3, locals=1, args_size=1
         0: new           #52                 // class scala/runtime/ModuleSerializationProxy
         3: dup
         4: ldc           #2                  // class shapeless/ops/union$Fields$
         6: invokespecial #55                 // Method scala/runtime/ModuleSerializationProxy."<init>":(Ljava/lang/Class;)V
         9: areturn
      LineNumberTable:
        line 127: 0
      LocalVariableTable:
        Start  Length  Slot  Name   Signature
            0      10     0  this   Lshapeless/ops/union$Fields$;

  public shapeless.ops.union$Fields$();
    descriptor: ()V
    flags: (0x0001) ACC_PUBLIC
    Code:
      stack=1, locals=1, args_size=1
         0: aload_0
         1: invokespecial #56                 // Method java/lang/Object."<init>":()V
         4: return
      LineNumberTable:
        line 159: 0
        line 127: 4
      LocalVariableTable:
        Start  Length  Slot  Name   Signature
            0       5     0  this   Lshapeless/ops/union$Fields$;
}
InnerClasses:
  public static #12= #9 of #11;           // Fields=class shapeless/ops/union$Fields of class shapeless/ops/union
  public static #13= #2 of #11;           // Fields$=class shapeless/ops/union$Fields$ of class shapeless/ops/union
  public final #15;                       // class shapeless/ops/union$Fields$$anon$7
  public final #17;                       // class shapeless/ops/union$Fields$$anon$8
SourceFile: "unions.scala"
  ScalaInlineInfo: length = 0x1D (unknown attribute)
   01 01 00 05 00 19 00 18 01 00 21 00 22 01 00 28
   00 29 01 00 14 00 26 01 00 31 00 32 01
  Scala: length = 0x0 (unknown attribute)

