Classfile /Users/mw/Projects/slang-braindump/.jar/jar8/assemble/slang-braindump/assemble/content/shapeless/ops/union$UnzipFields$.class
  Last modified May 29, 2022; size 1971 bytes
  SHA-256 checksum 7024f4187dcb6924c9dc8dd506e4e9047ef8d3e8762692d44f8499a241a411b5
  Compiled from "unions.scala"
public class shapeless.ops.union$UnzipFields$ implements java.io.Serializable
  minor version: 0
  major version: 52
  flags: (0x0021) ACC_PUBLIC, ACC_SUPER
  this_class: #2                          // shapeless/ops/union$UnzipFields$
  super_class: #4                         // java/lang/Object
  interfaces: 1, fields: 1, methods: 6, attributes: 4
Constant pool:
   #1 = Utf8               shapeless/ops/union$UnzipFields$
   #2 = Class              #1             // shapeless/ops/union$UnzipFields$
   #3 = Utf8               java/lang/Object
   #4 = Class              #3             // java/lang/Object
   #5 = Utf8               java/io/Serializable
   #6 = Class              #5             // java/io/Serializable
   #7 = Utf8               unions.scala
   #8 = Utf8               shapeless/ops/union$UnzipFields
   #9 = Class              #8             // shapeless/ops/union$UnzipFields
  #10 = Utf8               shapeless/ops/union
  #11 = Class              #10            // shapeless/ops/union
  #12 = Utf8               UnzipFields
  #13 = Utf8               UnzipFields$
  #14 = Utf8               shapeless/ops/union$UnzipFields$$anon$10
  #15 = Class              #14            // shapeless/ops/union$UnzipFields$$anon$10
  #16 = Utf8               shapeless/ops/union$UnzipFields$$anon$9
  #17 = Class              #16            // shapeless/ops/union$UnzipFields$$anon$9
  #18 = Utf8               MODULE$
  #19 = Utf8               Lshapeless/ops/union$UnzipFields$;
  #20 = Utf8               <clinit>
  #21 = Utf8               ()V
  #22 = Utf8               <init>
  #23 = NameAndType        #22:#21        // "<init>":()V
  #24 = Methodref          #2.#23         // shapeless/ops/union$UnzipFields$."<init>":()V
  #25 = NameAndType        #18:#19        // MODULE$:Lshapeless/ops/union$UnzipFields$;
  #26 = Fieldref           #2.#25         // shapeless/ops/union$UnzipFields$.MODULE$:Lshapeless/ops/union$UnzipFields$;
  #27 = Utf8               apply
  #28 = Utf8               (Lshapeless/ops/union$UnzipFields;)Lshapeless/ops/union$UnzipFields;
  #29 = Utf8               <L::Lshapeless/Coproduct;>(Lshapeless/ops/union$UnzipFields<TL;>;)Lshapeless/ops/union$UnzipFields<TL;>;
  #30 = Utf8               uf
  #31 = Utf8               this
  #32 = Utf8               Lshapeless/ops/union$UnzipFields;
  #33 = Utf8               cnilUnzipFields
  #34 = Utf8               ()Lshapeless/ops/union$UnzipFields;
  #35 = Utf8               <L::Lshapeless/CNil;>()Lshapeless/ops/union$UnzipFields<TL;>;
  #36 = Methodref          #17.#23        // shapeless/ops/union$UnzipFields$$anon$9."<init>":()V
  #37 = Utf8               cconsUnzipFields
  #38 = Utf8               (Lshapeless/Witness;Lshapeless/ops/union$UnzipFields;)Lshapeless/ops/union$UnzipFields;
  #39 = Utf8               <K:Ljava/lang/Object;V:Ljava/lang/Object;T::Lshapeless/Coproduct;>(Lshapeless/Witness;Lshapeless/ops/union$UnzipFields<TT;>;)Lshapeless/ops/union$UnzipFields<Lshapeless/$colon$plus$colon<TV;TT;>;>;
  #40 = Utf8               key
  #41 = Utf8               tailUF
  #42 = Utf8               (Lshapeless/Witness;Lshapeless/ops/union$UnzipFields;)V
  #43 = NameAndType        #22:#42        // "<init>":(Lshapeless/Witness;Lshapeless/ops/union$UnzipFields;)V
  #44 = Methodref          #15.#43        // shapeless/ops/union$UnzipFields$$anon$10."<init>":(Lshapeless/Witness;Lshapeless/ops/union$UnzipFields;)V
  #45 = Utf8               Lshapeless/Witness;
  #46 = Utf8               writeReplace
  #47 = Utf8               ()Ljava/lang/Object;
  #48 = Utf8               scala/runtime/ModuleSerializationProxy
  #49 = Class              #48            // scala/runtime/ModuleSerializationProxy
  #50 = Utf8               (Ljava/lang/Class;)V
  #51 = NameAndType        #22:#50        // "<init>":(Ljava/lang/Class;)V
  #52 = Methodref          #49.#51        // scala/runtime/ModuleSerializationProxy."<init>":(Ljava/lang/Class;)V
  #53 = Methodref          #4.#23         // java/lang/Object."<init>":()V
  #54 = Utf8               Code
  #55 = Utf8               LineNumberTable
  #56 = Utf8               LocalVariableTable
  #57 = Utf8               Signature
  #58 = Utf8               MethodParameters
  #59 = Utf8               InnerClasses
  #60 = Utf8               SourceFile
  #61 = Utf8               ScalaInlineInfo
  #62 = Utf8               Scala
{
  public static final shapeless.ops.union$UnzipFields$ MODULE$;
    descriptor: Lshapeless/ops/union$UnzipFields$;
    flags: (0x0019) ACC_PUBLIC, ACC_STATIC, ACC_FINAL

  public static {};
    descriptor: ()V
    flags: (0x0009) ACC_PUBLIC, ACC_STATIC
    Code:
      stack=2, locals=0, args_size=0
         0: new           #2                  // class shapeless/ops/union$UnzipFields$
         3: dup
         4: invokespecial #24                 // Method "<init>":()V
         7: putstatic     #26                 // Field MODULE$:Lshapeless/ops/union$UnzipFields$;
        10: return
      LineNumberTable:
        line 167: 0

  public <L extends shapeless.Coproduct> shapeless.ops.union$UnzipFields<L> apply(shapeless.ops.union$UnzipFields<L>);
    descriptor: (Lshapeless/ops/union$UnzipFields;)Lshapeless/ops/union$UnzipFields;
    flags: (0x0001) ACC_PUBLIC
    Code:
      stack=1, locals=2, args_size=2
         0: aload_1
         1: areturn
      LineNumberTable:
        line 168: 0
      LocalVariableTable:
        Start  Length  Slot  Name   Signature
            0       2     0  this   Lshapeless/ops/union$UnzipFields$;
            0       2     1    uf   Lshapeless/ops/union$UnzipFields;
    Signature: #29                          // <L::Lshapeless/Coproduct;>(Lshapeless/ops/union$UnzipFields<TL;>;)Lshapeless/ops/union$UnzipFields<TL;>;
    MethodParameters:
      Name                           Flags
      uf                             final

  public <L extends shapeless.CNil> shapeless.ops.union$UnzipFields<L> cnilUnzipFields();
    descriptor: ()Lshapeless/ops/union$UnzipFields;
    flags: (0x0001) ACC_PUBLIC
    Code:
      stack=2, locals=1, args_size=1
         0: new           #17                 // class shapeless/ops/union$UnzipFields$$anon$9
         3: dup
         4: invokespecial #36                 // Method shapeless/ops/union$UnzipFields$$anon$9."<init>":()V
         7: areturn
      LineNumberTable:
        line 173: 0
      LocalVariableTable:
        Start  Length  Slot  Name   Signature
            0       8     0  this   Lshapeless/ops/union$UnzipFields$;
    Signature: #35                          // <L::Lshapeless/CNil;>()Lshapeless/ops/union$UnzipFields<TL;>;

  public <K extends java.lang.Object, V extends java.lang.Object, T extends shapeless.Coproduct> shapeless.ops.union$UnzipFields<shapeless.$colon$plus$colon<V, T>> cconsUnzipFields(shapeless.Witness, shapeless.ops.union$UnzipFields<T>);
    descriptor: (Lshapeless/Witness;Lshapeless/ops/union$UnzipFields;)Lshapeless/ops/union$UnzipFields;
    flags: (0x0001) ACC_PUBLIC
    Code:
      stack=4, locals=3, args_size=3
         0: new           #15                 // class shapeless/ops/union$UnzipFields$$anon$10
         3: dup
         4: aload_1
         5: aload_2
         6: invokespecial #44                 // Method shapeless/ops/union$UnzipFields$$anon$10."<init>":(Lshapeless/Witness;Lshapeless/ops/union$UnzipFields;)V
         9: areturn
      LineNumberTable:
        line 184: 0
      LocalVariableTable:
        Start  Length  Slot  Name   Signature
            0      10     0  this   Lshapeless/ops/union$UnzipFields$;
            0      10     1   key   Lshapeless/Witness;
            0      10     2 tailUF   Lshapeless/ops/union$UnzipFields;
    Signature: #39                          // <K:Ljava/lang/Object;V:Ljava/lang/Object;T::Lshapeless/Coproduct;>(Lshapeless/Witness;Lshapeless/ops/union$UnzipFields<TT;>;)Lshapeless/ops/union$UnzipFields<Lshapeless/$colon$plus$colon<TV;TT;>;>;
    MethodParameters:
      Name                           Flags
      key                            final
      tailUF                         final

  private java.lang.Object writeReplace();
    descriptor: ()Ljava/lang/Object;
    flags: (0x0002) ACC_PRIVATE
    Code:
      stack=3, locals=1, args_size=1
         0: new           #49                 // class scala/runtime/ModuleSerializationProxy
         3: dup
         4: ldc           #2                  // class shapeless/ops/union$UnzipFields$
         6: invokespecial #52                 // Method scala/runtime/ModuleSerializationProxy."<init>":(Ljava/lang/Class;)V
         9: areturn
      LineNumberTable:
        line 167: 0
      LocalVariableTable:
        Start  Length  Slot  Name   Signature
            0      10     0  this   Lshapeless/ops/union$UnzipFields$;

  public shapeless.ops.union$UnzipFields$();
    descriptor: ()V
    flags: (0x0001) ACC_PUBLIC
    Code:
      stack=1, locals=1, args_size=1
         0: aload_0
         1: invokespecial #53                 // Method java/lang/Object."<init>":()V
         4: return
      LineNumberTable:
        line 203: 0
        line 167: 4
      LocalVariableTable:
        Start  Length  Slot  Name   Signature
            0       5     0  this   Lshapeless/ops/union$UnzipFields$;
}
InnerClasses:
  public static #12= #9 of #11;           // UnzipFields=class shapeless/ops/union$UnzipFields of class shapeless/ops/union
  public static #13= #2 of #11;           // UnzipFields$=class shapeless/ops/union$UnzipFields$ of class shapeless/ops/union
  public final #15;                       // class shapeless/ops/union$UnzipFields$$anon$10
  public final #17;                       // class shapeless/ops/union$UnzipFields$$anon$9
SourceFile: "unions.scala"
  ScalaInlineInfo: length = 0x1D (unknown attribute)
   01 01 00 05 00 16 00 15 01 00 1B 00 1C 01 00 25
   00 26 01 00 21 00 22 01 00 2E 00 2F 01
  Scala: length = 0x0 (unknown attribute)

