Classfile /Users/mw/Projects/slang-braindump/.jar/jar8/assemble/slang-braindump/assemble/content/shapeless/ops/union$UnzipFields$$anon$9.class
  Last modified May 29, 2022; size 1339 bytes
  SHA-256 checksum 82c7a24630d1c13d6386d9de282a047e0d40216756a6918ab6b93413c2c4618f
  Compiled from "unions.scala"
public final class shapeless.ops.union$UnzipFields$$anon$9 extends java.lang.Object implements shapeless.ops.union$UnzipFields<L>
  minor version: 0
  major version: 52
  flags: (0x0031) ACC_PUBLIC, ACC_FINAL, ACC_SUPER
  this_class: #2                          // shapeless/ops/union$UnzipFields$$anon$9
  super_class: #5                         // java/lang/Object
  interfaces: 1, fields: 0, methods: 5, attributes: 6
Constant pool:
   #1 = Utf8               shapeless/ops/union$UnzipFields$$anon$9
   #2 = Class              #1             // shapeless/ops/union$UnzipFields$$anon$9
   #3 = Utf8               Ljava/lang/Object;Lshapeless/ops/union$UnzipFields<TL;>;
   #4 = Utf8               java/lang/Object
   #5 = Class              #4             // java/lang/Object
   #6 = Utf8               shapeless/ops/union$UnzipFields
   #7 = Class              #6             // shapeless/ops/union$UnzipFields
   #8 = Utf8               unions.scala
   #9 = Utf8               shapeless/ops/union$UnzipFields$
  #10 = Class              #9             // shapeless/ops/union$UnzipFields$
  #11 = Utf8               cnilUnzipFields
  #12 = Utf8               ()Lshapeless/ops/union$UnzipFields;
  #13 = NameAndType        #11:#12        // cnilUnzipFields:()Lshapeless/ops/union$UnzipFields;
  #14 = Utf8               shapeless/ops/union
  #15 = Class              #14            // shapeless/ops/union
  #16 = Utf8               UnzipFields
  #17 = Utf8               UnzipFields$
  #18 = Utf8               keys
  #19 = Utf8               ()Lshapeless/HNil$;
  #20 = Utf8               shapeless/HNil$
  #21 = Class              #20            // shapeless/HNil$
  #22 = Utf8               MODULE$
  #23 = Utf8               Lshapeless/HNil$;
  #24 = NameAndType        #22:#23        // MODULE$:Lshapeless/HNil$;
  #25 = Fieldref           #21.#24        // shapeless/HNil$.MODULE$:Lshapeless/HNil$;
  #26 = Utf8               this
  #27 = Utf8               Lshapeless/ops/union$UnzipFields$$anon$9;
  #28 = Utf8               values
  #29 = Utf8               (Lshapeless/CNil;)Lshapeless/CNil;
  #30 = Utf8               (TL;)TL;
  #31 = Utf8               u
  #32 = Utf8               Lshapeless/CNil;
  #33 = Utf8               (Lshapeless/Coproduct;)Lshapeless/Coproduct;
  #34 = Utf8               shapeless/CNil
  #35 = Class              #34            // shapeless/CNil
  #36 = NameAndType        #28:#29        // values:(Lshapeless/CNil;)Lshapeless/CNil;
  #37 = Methodref          #2.#36         // shapeless/ops/union$UnzipFields$$anon$9.values:(Lshapeless/CNil;)Lshapeless/CNil;
  #38 = Utf8               Lshapeless/Coproduct;
  #39 = Utf8               ()Lshapeless/HList;
  #40 = NameAndType        #18:#19        // keys:()Lshapeless/HNil$;
  #41 = Methodref          #2.#40         // shapeless/ops/union$UnzipFields$$anon$9.keys:()Lshapeless/HNil$;
  #42 = Utf8               <init>
  #43 = Utf8               ()V
  #44 = NameAndType        #42:#43        // "<init>":()V
  #45 = Methodref          #5.#44         // java/lang/Object."<init>":()V
  #46 = Utf8               Code
  #47 = Utf8               LineNumberTable
  #48 = Utf8               LocalVariableTable
  #49 = Utf8               Signature
  #50 = Utf8               MethodParameters
  #51 = Utf8               InnerClasses
  #52 = Utf8               EnclosingMethod
  #53 = Utf8               SourceFile
  #54 = Utf8               ScalaInlineInfo
  #55 = Utf8               Scala
{
  public shapeless.HNil$ keys();
    descriptor: ()Lshapeless/HNil$;
    flags: (0x0001) ACC_PUBLIC
    Code:
      stack=1, locals=1, args_size=1
         0: getstatic     #25                 // Field shapeless/HNil$.MODULE$:Lshapeless/HNil$;
         3: areturn
      LineNumberTable:
        line 176: 0
      LocalVariableTable:
        Start  Length  Slot  Name   Signature
            0       4     0  this   Lshapeless/ops/union$UnzipFields$$anon$9;

  public L values(L);
    descriptor: (Lshapeless/CNil;)Lshapeless/CNil;
    flags: (0x0001) ACC_PUBLIC
    Code:
      stack=1, locals=2, args_size=2
         0: aload_1
         1: areturn
      LineNumberTable:
        line 177: 0
      LocalVariableTable:
        Start  Length  Slot  Name   Signature
            0       2     0  this   Lshapeless/ops/union$UnzipFields$$anon$9;
            0       2     1     u   Lshapeless/CNil;
    Signature: #30                          // (TL;)TL;
    MethodParameters:
      Name                           Flags
      u                              final

  public shapeless.Coproduct values(shapeless.Coproduct);
    descriptor: (Lshapeless/Coproduct;)Lshapeless/Coproduct;
    flags: (0x1041) ACC_PUBLIC, ACC_BRIDGE, ACC_SYNTHETIC
    Code:
      stack=2, locals=2, args_size=2
         0: aload_0
         1: aload_1
         2: checkcast     #35                 // class shapeless/CNil
         5: invokevirtual #37                 // Method values:(Lshapeless/CNil;)Lshapeless/CNil;
         8: areturn
      LineNumberTable:
        line 173: 0
      LocalVariableTable:
        Start  Length  Slot  Name   Signature
            0       9     0  this   Lshapeless/ops/union$UnzipFields$$anon$9;
            0       9     1     u   Lshapeless/Coproduct;
    MethodParameters:
      Name                           Flags
      u                              final

  public shapeless.HList keys();
    descriptor: ()Lshapeless/HList;
    flags: (0x1041) ACC_PUBLIC, ACC_BRIDGE, ACC_SYNTHETIC
    Code:
      stack=1, locals=1, args_size=1
         0: aload_0
         1: invokevirtual #41                 // Method keys:()Lshapeless/HNil$;
         4: areturn
      LineNumberTable:
        line 173: 0
      LocalVariableTable:
        Start  Length  Slot  Name   Signature
            0       5     0  this   Lshapeless/ops/union$UnzipFields$$anon$9;

  public shapeless.ops.union$UnzipFields$$anon$9();
    descriptor: ()V
    flags: (0x0001) ACC_PUBLIC
    Code:
      stack=1, locals=1, args_size=1
         0: aload_0
         1: invokespecial #45                 // Method java/lang/Object."<init>":()V
         4: return
      LineNumberTable:
        line 173: 0
      LocalVariableTable:
        Start  Length  Slot  Name   Signature
            0       5     0  this   Lshapeless/ops/union$UnzipFields$$anon$9;
}
InnerClasses:
  public static #16= #7 of #15;           // UnzipFields=class shapeless/ops/union$UnzipFields of class shapeless/ops/union
  public static #17= #10 of #15;          // UnzipFields$=class shapeless/ops/union$UnzipFields$ of class shapeless/ops/union
  public final #2;                        // class shapeless/ops/union$UnzipFields$$anon$9
EnclosingMethod: #10.#13                // shapeless.ops.union$UnzipFields$.cnilUnzipFields
Signature: #3                           // Ljava/lang/Object;Lshapeless/ops/union$UnzipFields<TL;>;
SourceFile: "unions.scala"
  ScalaInlineInfo: length = 0x1D (unknown attribute)
   01 01 00 05 00 2A 00 2B 01 00 12 00 27 01 00 12
   00 13 01 00 1C 00 1D 01 00 1C 00 21 01
  Scala: length = 0x0 (unknown attribute)

