Classfile /Users/mw/Projects/slang-braindump/.jar/jar8/assemble/slang-braindump/assemble/content/shapeless/ops/union$Keys$.class
  Last modified May 29, 2022; size 1824 bytes
  SHA-256 checksum 4736dee0c34f6b07fbc21f81d376ded55d97c6b5377ae9db609610250606b250
  Compiled from "unions.scala"
public class shapeless.ops.union$Keys$ implements java.io.Serializable
  minor version: 0
  major version: 52
  flags: (0x0021) ACC_PUBLIC, ACC_SUPER
  this_class: #2                          // shapeless/ops/union$Keys$
  super_class: #4                         // java/lang/Object
  interfaces: 1, fields: 1, methods: 6, attributes: 4
Constant pool:
   #1 = Utf8               shapeless/ops/union$Keys$
   #2 = Class              #1             // shapeless/ops/union$Keys$
   #3 = Utf8               java/lang/Object
   #4 = Class              #3             // java/lang/Object
   #5 = Utf8               java/io/Serializable
   #6 = Class              #5             // java/io/Serializable
   #7 = Utf8               unions.scala
   #8 = Utf8               shapeless/ops/union$Keys
   #9 = Class              #8             // shapeless/ops/union$Keys
  #10 = Utf8               shapeless/ops/union
  #11 = Class              #10            // shapeless/ops/union
  #12 = Utf8               Keys
  #13 = Utf8               Keys$
  #14 = Utf8               shapeless/ops/union$Keys$$anon$3
  #15 = Class              #14            // shapeless/ops/union$Keys$$anon$3
  #16 = Utf8               shapeless/ops/union$Keys$$anon$4
  #17 = Class              #16            // shapeless/ops/union$Keys$$anon$4
  #18 = Utf8               MODULE$
  #19 = Utf8               Lshapeless/ops/union$Keys$;
  #20 = Utf8               <clinit>
  #21 = Utf8               ()V
  #22 = Utf8               <init>
  #23 = NameAndType        #22:#21        // "<init>":()V
  #24 = Methodref          #2.#23         // shapeless/ops/union$Keys$."<init>":()V
  #25 = NameAndType        #18:#19        // MODULE$:Lshapeless/ops/union$Keys$;
  #26 = Fieldref           #2.#25         // shapeless/ops/union$Keys$.MODULE$:Lshapeless/ops/union$Keys$;
  #27 = Utf8               apply
  #28 = Utf8               (Lshapeless/ops/union$Keys;)Lshapeless/ops/union$Keys;
  #29 = Utf8               <U::Lshapeless/Coproduct;>(Lshapeless/ops/union$Keys<TU;>;)Lshapeless/ops/union$Keys<TU;>;
  #30 = Utf8               keys
  #31 = Utf8               this
  #32 = Utf8               Lshapeless/ops/union$Keys;
  #33 = Utf8               cnilKeys
  #34 = Utf8               ()Lshapeless/ops/union$Keys;
  #35 = Utf8               <U::Lshapeless/CNil;>()Lshapeless/ops/union$Keys<TU;>;
  #36 = Methodref          #15.#23        // shapeless/ops/union$Keys$$anon$3."<init>":()V
  #37 = Utf8               coproductKeys
  #38 = Utf8               (Lshapeless/Witness;Lshapeless/ops/union$Keys;)Lshapeless/ops/union$Keys;
  #39 = Utf8               <K:Ljava/lang/Object;V:Ljava/lang/Object;T::Lshapeless/Coproduct;>(Lshapeless/Witness;Lshapeless/ops/union$Keys<TT;>;)Lshapeless/ops/union$Keys<Lshapeless/$colon$plus$colon<TV;TT;>;>;
  #40 = Utf8               wk
  #41 = Utf8               kt
  #42 = Utf8               (Lshapeless/Witness;Lshapeless/ops/union$Keys;)V
  #43 = NameAndType        #22:#42        // "<init>":(Lshapeless/Witness;Lshapeless/ops/union$Keys;)V
  #44 = Methodref          #17.#43        // shapeless/ops/union$Keys$$anon$4."<init>":(Lshapeless/Witness;Lshapeless/ops/union$Keys;)V
  #45 = Utf8               Lshapeless/Witness;
  #46 = Utf8               writeReplace
  #47 = Utf8               ()Ljava/lang/Object;
  #48 = Utf8               scala/runtime/ModuleSerializationProxy
  #49 = Class              #48            // scala/runtime/ModuleSerializationProxy
  #50 = Utf8               (Ljava/lang/Class;)V
  #51 = NameAndType        #22:#50        // "<init>":(Ljava/lang/Class;)V
  #52 = Methodref          #49.#51        // scala/runtime/ModuleSerializationProxy."<init>":(Ljava/lang/Class;)V
  #53 = Methodref          #4.#23         // java/lang/Object."<init>":()V
  #54 = Utf8               Code
  #55 = Utf8               LineNumberTable
  #56 = Utf8               LocalVariableTable
  #57 = Utf8               Signature
  #58 = Utf8               MethodParameters
  #59 = Utf8               InnerClasses
  #60 = Utf8               SourceFile
  #61 = Utf8               ScalaInlineInfo
  #62 = Utf8               Scala
{
  public static final shapeless.ops.union$Keys$ MODULE$;
    descriptor: Lshapeless/ops/union$Keys$;
    flags: (0x0019) ACC_PUBLIC, ACC_STATIC, ACC_FINAL

  public static {};
    descriptor: ()V
    flags: (0x0009) ACC_PUBLIC, ACC_STATIC
    Code:
      stack=2, locals=0, args_size=0
         0: new           #2                  // class shapeless/ops/union$Keys$
         3: dup
         4: invokespecial #24                 // Method "<init>":()V
         7: putstatic     #26                 // Field MODULE$:Lshapeless/ops/union$Keys$;
        10: return
      LineNumberTable:
        line 72: 0

  public <U extends shapeless.Coproduct> shapeless.ops.union$Keys<U> apply(shapeless.ops.union$Keys<U>);
    descriptor: (Lshapeless/ops/union$Keys;)Lshapeless/ops/union$Keys;
    flags: (0x0001) ACC_PUBLIC
    Code:
      stack=1, locals=2, args_size=2
         0: aload_1
         1: areturn
      LineNumberTable:
        line 73: 0
      LocalVariableTable:
        Start  Length  Slot  Name   Signature
            0       2     0  this   Lshapeless/ops/union$Keys$;
            0       2     1  keys   Lshapeless/ops/union$Keys;
    Signature: #29                          // <U::Lshapeless/Coproduct;>(Lshapeless/ops/union$Keys<TU;>;)Lshapeless/ops/union$Keys<TU;>;
    MethodParameters:
      Name                           Flags
      keys                           final

  public <U extends shapeless.CNil> shapeless.ops.union$Keys<U> cnilKeys();
    descriptor: ()Lshapeless/ops/union$Keys;
    flags: (0x0001) ACC_PUBLIC
    Code:
      stack=2, locals=1, args_size=1
         0: new           #15                 // class shapeless/ops/union$Keys$$anon$3
         3: dup
         4: invokespecial #36                 // Method shapeless/ops/union$Keys$$anon$3."<init>":()V
         7: areturn
      LineNumberTable:
        line 78: 0
      LocalVariableTable:
        Start  Length  Slot  Name   Signature
            0       8     0  this   Lshapeless/ops/union$Keys$;
    Signature: #35                          // <U::Lshapeless/CNil;>()Lshapeless/ops/union$Keys<TU;>;

  public <K extends java.lang.Object, V extends java.lang.Object, T extends shapeless.Coproduct> shapeless.ops.union$Keys<shapeless.$colon$plus$colon<V, T>> coproductKeys(shapeless.Witness, shapeless.ops.union$Keys<T>);
    descriptor: (Lshapeless/Witness;Lshapeless/ops/union$Keys;)Lshapeless/ops/union$Keys;
    flags: (0x0001) ACC_PUBLIC
    Code:
      stack=4, locals=3, args_size=3
         0: new           #17                 // class shapeless/ops/union$Keys$$anon$4
         3: dup
         4: aload_1
         5: aload_2
         6: invokespecial #44                 // Method shapeless/ops/union$Keys$$anon$4."<init>":(Lshapeless/Witness;Lshapeless/ops/union$Keys;)V
         9: areturn
      LineNumberTable:
        line 84: 0
      LocalVariableTable:
        Start  Length  Slot  Name   Signature
            0      10     0  this   Lshapeless/ops/union$Keys$;
            0      10     1    wk   Lshapeless/Witness;
            0      10     2    kt   Lshapeless/ops/union$Keys;
    Signature: #39                          // <K:Ljava/lang/Object;V:Ljava/lang/Object;T::Lshapeless/Coproduct;>(Lshapeless/Witness;Lshapeless/ops/union$Keys<TT;>;)Lshapeless/ops/union$Keys<Lshapeless/$colon$plus$colon<TV;TT;>;>;
    MethodParameters:
      Name                           Flags
      wk                             final
      kt                             final

  private java.lang.Object writeReplace();
    descriptor: ()Ljava/lang/Object;
    flags: (0x0002) ACC_PRIVATE
    Code:
      stack=3, locals=1, args_size=1
         0: new           #49                 // class scala/runtime/ModuleSerializationProxy
         3: dup
         4: ldc           #2                  // class shapeless/ops/union$Keys$
         6: invokespecial #52                 // Method scala/runtime/ModuleSerializationProxy."<init>":(Ljava/lang/Class;)V
         9: areturn
      LineNumberTable:
        line 72: 0
      LocalVariableTable:
        Start  Length  Slot  Name   Signature
            0      10     0  this   Lshapeless/ops/union$Keys$;

  public shapeless.ops.union$Keys$();
    descriptor: ()V
    flags: (0x0001) ACC_PUBLIC
    Code:
      stack=1, locals=1, args_size=1
         0: aload_0
         1: invokespecial #53                 // Method java/lang/Object."<init>":()V
         4: return
      LineNumberTable:
        line 95: 0
        line 72: 4
      LocalVariableTable:
        Start  Length  Slot  Name   Signature
            0       5     0  this   Lshapeless/ops/union$Keys$;
}
InnerClasses:
  public static #12= #9 of #11;           // Keys=class shapeless/ops/union$Keys of class shapeless/ops/union
  public static #13= #2 of #11;           // Keys$=class shapeless/ops/union$Keys$ of class shapeless/ops/union
  public final #15;                       // class shapeless/ops/union$Keys$$anon$3
  public final #17;                       // class shapeless/ops/union$Keys$$anon$4
SourceFile: "unions.scala"
  ScalaInlineInfo: length = 0x1D (unknown attribute)
   01 01 00 05 00 16 00 15 01 00 1B 00 1C 01 00 21
   00 22 01 00 25 00 26 01 00 2E 00 2F 01
  Scala: length = 0x0 (unknown attribute)

