Classfile /Users/mw/Projects/slang-braindump/.jar/jar8/assemble/slang-braindump/assemble/content/shapeless/ops/zipper$LeftTo$$anon$8.class
  Last modified May 29, 2022; size 3322 bytes
  SHA-256 checksum b0806ab83e487f47e1529a6fffaf0c3f39a45575240b07cdb46d3ad3ae138101
  Compiled from "zipper.scala"
public final class shapeless.ops.zipper$LeftTo$$anon$8 extends java.lang.Object implements shapeless.ops.zipper$LeftTo<shapeless.Zipper<C, L, R, P>, T>
  minor version: 0
  major version: 52
  flags: (0x0031) ACC_PUBLIC, ACC_FINAL, ACC_SUPER
  this_class: #2                          // shapeless/ops/zipper$LeftTo$$anon$8
  super_class: #5                         // java/lang/Object
  interfaces: 1, fields: 3, methods: 3, attributes: 6
Constant pool:
    #1 = Utf8               shapeless/ops/zipper$LeftTo$$anon$8
    #2 = Class              #1            // shapeless/ops/zipper$LeftTo$$anon$8
    #3 = Utf8               Ljava/lang/Object;Lshapeless/ops/zipper$LeftTo<Lshapeless/Zipper<TC;TL;TR;TP;>;TT;>;
    #4 = Utf8               java/lang/Object
    #5 = Class              #4            // java/lang/Object
    #6 = Utf8               shapeless/ops/zipper$LeftTo
    #7 = Class              #6            // shapeless/ops/zipper$LeftTo
    #8 = Utf8               zipper.scala
    #9 = Utf8               shapeless/ops/zipper$LeftTo$
   #10 = Class              #9            // shapeless/ops/zipper$LeftTo$
   #11 = Utf8               leftTo
   #12 = Utf8               (Lshapeless/ops/hlist$SplitLeft;Lshapeless/ops/hlist$ReversePrepend;Lshapeless/ops/hlist$IsHCons;)Lshapeless/ops/zipper$LeftTo;
   #13 = NameAndType        #11:#12       // leftTo:(Lshapeless/ops/hlist$SplitLeft;Lshapeless/ops/hlist$ReversePrepend;Lshapeless/ops/hlist$IsHCons;)Lshapeless/ops/zipper$LeftTo;
   #14 = Utf8               shapeless/ops/hlist$IsHCons
   #15 = Class              #14           // shapeless/ops/hlist$IsHCons
   #16 = Utf8               shapeless/ops/hlist
   #17 = Class              #16           // shapeless/ops/hlist
   #18 = Utf8               IsHCons
   #19 = Utf8               shapeless/ops/hlist$ReversePrepend
   #20 = Class              #19           // shapeless/ops/hlist$ReversePrepend
   #21 = Utf8               ReversePrepend
   #22 = Utf8               shapeless/ops/hlist$SplitLeft
   #23 = Class              #22           // shapeless/ops/hlist$SplitLeft
   #24 = Utf8               SplitLeft
   #25 = Utf8               shapeless/ops/zipper
   #26 = Class              #25           // shapeless/ops/zipper
   #27 = Utf8               LeftTo
   #28 = Utf8               LeftTo$
   #29 = Utf8               split$4
   #30 = Utf8               Lshapeless/ops/hlist$SplitLeft;
   #31 = Utf8               cons$1
   #32 = Utf8               Lshapeless/ops/hlist$IsHCons;
   #33 = Utf8               reverse$4
   #34 = Utf8               Lshapeless/ops/hlist$ReversePrepend;
   #35 = Utf8               apply
   #36 = Utf8               (Lshapeless/Zipper;)Lshapeless/Zipper;
   #37 = Utf8               (Lshapeless/Zipper<TC;TL;TR;TP;>;)Lshapeless/Zipper<TC;Lshapeless/HList;Lshapeless/$colon$colon<Ljava/lang/Object;Lshapeless/HList;>;TP;>;
   #38 = Utf8               z
   #39 = Utf8               shapeless/HList$
   #40 = Class              #39           // shapeless/HList$
   #41 = Utf8               MODULE$
   #42 = Utf8               Lshapeless/HList$;
   #43 = NameAndType        #41:#42       // MODULE$:Lshapeless/HList$;
   #44 = Fieldref           #40.#43       // shapeless/HList$.MODULE$:Lshapeless/HList$;
   #45 = Utf8               shapeless/Zipper
   #46 = Class              #45           // shapeless/Zipper
   #47 = Utf8               prefix
   #48 = Utf8               ()Lshapeless/HList;
   #49 = NameAndType        #47:#48       // prefix:()Lshapeless/HList;
   #50 = Methodref          #46.#49       // shapeless/Zipper.prefix:()Lshapeless/HList;
   #51 = Utf8               hlistOps
   #52 = Utf8               (Lshapeless/HList;)Lshapeless/syntax/HListOps;
   #53 = NameAndType        #51:#52       // hlistOps:(Lshapeless/HList;)Lshapeless/syntax/HListOps;
   #54 = Methodref          #40.#53       // shapeless/HList$.hlistOps:(Lshapeless/HList;)Lshapeless/syntax/HListOps;
   #55 = NameAndType        #29:#30       // split$4:Lshapeless/ops/hlist$SplitLeft;
   #56 = Fieldref           #2.#55        // shapeless/ops/zipper$LeftTo$$anon$8.split$4:Lshapeless/ops/hlist$SplitLeft;
   #57 = Utf8               shapeless/syntax/HListOps
   #58 = Class              #57           // shapeless/syntax/HListOps
   #59 = Utf8               splitLeftP
   #60 = Utf8               (Lshapeless/ops/hlist$SplitLeft;)Lshapeless/$colon$colon;
   #61 = NameAndType        #59:#60       // splitLeftP:(Lshapeless/ops/hlist$SplitLeft;)Lshapeless/$colon$colon;
   #62 = Methodref          #58.#61       // shapeless/syntax/HListOps.splitLeftP:(Lshapeless/ops/hlist$SplitLeft;)Lshapeless/$colon$colon;
   #63 = Utf8               shapeless/$colon$colon
   #64 = Class              #63           // shapeless/$colon$colon
   #65 = Utf8               head
   #66 = Utf8               ()Ljava/lang/Object;
   #67 = NameAndType        #65:#66       // head:()Ljava/lang/Object;
   #68 = Methodref          #64.#67       // shapeless/$colon$colon.head:()Ljava/lang/Object;
   #69 = Utf8               shapeless/HList
   #70 = Class              #69           // shapeless/HList
   #71 = Utf8               tail
   #72 = NameAndType        #71:#48       // tail:()Lshapeless/HList;
   #73 = Methodref          #64.#72       // shapeless/$colon$colon.tail:()Lshapeless/HList;
   #74 = Utf8               shapeless/HNil
   #75 = Class              #74           // shapeless/HNil
   #76 = Utf8               shapeless/HNil$
   #77 = Class              #76           // shapeless/HNil$
   #78 = Utf8               Lshapeless/HNil$;
   #79 = NameAndType        #41:#78       // MODULE$:Lshapeless/HNil$;
   #80 = Fieldref           #77.#79       // shapeless/HNil$.MODULE$:Lshapeless/HNil$;
   #81 = Utf8               equals
   #82 = Utf8               (Ljava/lang/Object;)Z
   #83 = NameAndType        #81:#82       // equals:(Ljava/lang/Object;)Z
   #84 = Methodref          #5.#83        // java/lang/Object.equals:(Ljava/lang/Object;)Z
   #85 = Utf8               scala/Tuple2
   #86 = Class              #85           // scala/Tuple2
   #87 = Utf8               <init>
   #88 = Utf8               (Ljava/lang/Object;Ljava/lang/Object;)V
   #89 = NameAndType        #87:#88       // "<init>":(Ljava/lang/Object;Ljava/lang/Object;)V
   #90 = Methodref          #86.#89       // scala/Tuple2."<init>":(Ljava/lang/Object;Ljava/lang/Object;)V
   #91 = Utf8               scala/MatchError
   #92 = Class              #91           // scala/MatchError
   #93 = Utf8               (Ljava/lang/Object;)V
   #94 = NameAndType        #87:#93       // "<init>":(Ljava/lang/Object;)V
   #95 = Methodref          #92.#94       // scala/MatchError."<init>":(Ljava/lang/Object;)V
   #96 = Utf8               _1
   #97 = NameAndType        #96:#66       // _1:()Ljava/lang/Object;
   #98 = Methodref          #86.#97       // scala/Tuple2._1:()Ljava/lang/Object;
   #99 = Utf8               _2
  #100 = NameAndType        #99:#66       // _2:()Ljava/lang/Object;
  #101 = Methodref          #86.#100      // scala/Tuple2._2:()Ljava/lang/Object;
  #102 = NameAndType        #31:#32       // cons$1:Lshapeless/ops/hlist$IsHCons;
  #103 = Fieldref           #2.#102       // shapeless/ops/zipper$LeftTo$$anon$8.cons$1:Lshapeless/ops/hlist$IsHCons;
  #104 = Utf8               (Lshapeless/ops/hlist$IsHCons;)Lshapeless/HList;
  #105 = NameAndType        #71:#104      // tail:(Lshapeless/ops/hlist$IsHCons;)Lshapeless/HList;
  #106 = Methodref          #58.#105      // shapeless/syntax/HListOps.tail:(Lshapeless/ops/hlist$IsHCons;)Lshapeless/HList;
  #107 = Utf8               (Lshapeless/ops/hlist$IsHCons;)Ljava/lang/Object;
  #108 = NameAndType        #65:#107      // head:(Lshapeless/ops/hlist$IsHCons;)Ljava/lang/Object;
  #109 = Methodref          #58.#108      // shapeless/syntax/HListOps.head:(Lshapeless/ops/hlist$IsHCons;)Ljava/lang/Object;
  #110 = Utf8               suffix
  #111 = NameAndType        #110:#48      // suffix:()Lshapeless/HList;
  #112 = Methodref          #46.#111      // shapeless/Zipper.suffix:()Lshapeless/HList;
  #113 = NameAndType        #33:#34       // reverse$4:Lshapeless/ops/hlist$ReversePrepend;
  #114 = Fieldref           #2.#113       // shapeless/ops/zipper$LeftTo$$anon$8.reverse$4:Lshapeless/ops/hlist$ReversePrepend;
  #115 = Utf8               reverse_$colon$colon$colon
  #116 = Utf8               (Lshapeless/HList;Lshapeless/ops/hlist$ReversePrepend;)Lshapeless/HList;
  #117 = NameAndType        #115:#116     // reverse_$colon$colon$colon:(Lshapeless/HList;Lshapeless/ops/hlist$ReversePrepend;)Lshapeless/HList;
  #118 = Methodref          #58.#117      // shapeless/syntax/HListOps.reverse_$colon$colon$colon:(Lshapeless/HList;Lshapeless/ops/hlist$ReversePrepend;)Lshapeless/HList;
  #119 = Utf8               $colon$colon
  #120 = Utf8               (Ljava/lang/Object;)Lshapeless/$colon$colon;
  #121 = NameAndType        #119:#120     // $colon$colon:(Ljava/lang/Object;)Lshapeless/$colon$colon;
  #122 = Methodref          #58.#121      // shapeless/syntax/HListOps.$colon$colon:(Ljava/lang/Object;)Lshapeless/$colon$colon;
  #123 = Utf8               parent
  #124 = NameAndType        #123:#66      // parent:()Ljava/lang/Object;
  #125 = Methodref          #46.#124      // shapeless/Zipper.parent:()Ljava/lang/Object;
  #126 = Utf8               (Lshapeless/HList;Lshapeless/HList;Ljava/lang/Object;)V
  #127 = NameAndType        #87:#126      // "<init>":(Lshapeless/HList;Lshapeless/HList;Ljava/lang/Object;)V
  #128 = Methodref          #46.#127      // shapeless/Zipper."<init>":(Lshapeless/HList;Lshapeless/HList;Ljava/lang/Object;)V
  #129 = Utf8               s
  #130 = Utf8               Lshapeless/HList;
  #131 = Utf8               p
  #132 = Utf8               this
  #133 = Utf8               Lshapeless/ops/zipper$LeftTo$$anon$8;
  #134 = Utf8               Lshapeless/Zipper;
  #135 = Utf8               (Ljava/lang/Object;)Ljava/lang/Object;
  #136 = Utf8               t
  #137 = NameAndType        #35:#36       // apply:(Lshapeless/Zipper;)Lshapeless/Zipper;
  #138 = Methodref          #2.#137       // shapeless/ops/zipper$LeftTo$$anon$8.apply:(Lshapeless/Zipper;)Lshapeless/Zipper;
  #139 = Utf8               Ljava/lang/Object;
  #140 = Utf8               (Lshapeless/ops/hlist$SplitLeft;Lshapeless/ops/hlist$IsHCons;Lshapeless/ops/hlist$ReversePrepend;)V
  #141 = Utf8               ()V
  #142 = NameAndType        #87:#141      // "<init>":()V
  #143 = Methodref          #5.#142       // java/lang/Object."<init>":()V
  #144 = Utf8               Code
  #145 = Utf8               StackMapTable
  #146 = Utf8               LineNumberTable
  #147 = Utf8               LocalVariableTable
  #148 = Utf8               Signature
  #149 = Utf8               MethodParameters
  #150 = Utf8               InnerClasses
  #151 = Utf8               EnclosingMethod
  #152 = Utf8               SourceFile
  #153 = Utf8               ScalaInlineInfo
  #154 = Utf8               Scala
{
  private final shapeless.ops.hlist$SplitLeft split$4;
    descriptor: Lshapeless/ops/hlist$SplitLeft;
    flags: (0x0012) ACC_PRIVATE, ACC_FINAL

  private final shapeless.ops.hlist$IsHCons cons$1;
    descriptor: Lshapeless/ops/hlist$IsHCons;
    flags: (0x0012) ACC_PRIVATE, ACC_FINAL

  private final shapeless.ops.hlist$ReversePrepend reverse$4;
    descriptor: Lshapeless/ops/hlist$ReversePrepend;
    flags: (0x0012) ACC_PRIVATE, ACC_FINAL

  public shapeless.Zipper<C, shapeless.HList, shapeless.$colon$colon<java.lang.Object, shapeless.HList>, P> apply(shapeless.Zipper<C, L, R, P>);
    descriptor: (Lshapeless/Zipper;)Lshapeless/Zipper;
    flags: (0x0001) ACC_PUBLIC
    Code:
      stack=7, locals=13, args_size=2
         0: getstatic     #44                 // Field shapeless/HList$.MODULE$:Lshapeless/HList$;
         3: aload_1
         4: invokevirtual #50                 // Method shapeless/Zipper.prefix:()Lshapeless/HList;
         7: invokevirtual #54                 // Method shapeless/HList$.hlistOps:(Lshapeless/HList;)Lshapeless/syntax/HListOps;
        10: aload_0
        11: getfield      #56                 // Field split$4:Lshapeless/ops/hlist$SplitLeft;
        14: invokevirtual #62                 // Method shapeless/syntax/HListOps.splitLeftP:(Lshapeless/ops/hlist$SplitLeft;)Lshapeless/$colon$colon;
        17: astore        4
        19: aload         4
        21: ifnull        101
        24: aload         4
        26: invokevirtual #68                 // Method shapeless/$colon$colon.head:()Ljava/lang/Object;
        29: checkcast     #70                 // class shapeless/HList
        32: astore        5
        34: aload         4
        36: invokevirtual #73                 // Method shapeless/$colon$colon.tail:()Lshapeless/HList;
        39: checkcast     #64                 // class shapeless/$colon$colon
        42: astore        6
        44: aload         6
        46: ifnull        98
        49: aload         6
        51: invokevirtual #68                 // Method shapeless/$colon$colon.head:()Ljava/lang/Object;
        54: checkcast     #70                 // class shapeless/HList
        57: astore        7
        59: aload         6
        61: invokevirtual #73                 // Method shapeless/$colon$colon.tail:()Lshapeless/HList;
        64: checkcast     #75                 // class shapeless/HNil
        67: astore        8
        69: getstatic     #80                 // Field shapeless/HNil$.MODULE$:Lshapeless/HNil$;
        72: aload         8
        74: invokevirtual #84                 // Method java/lang/Object.equals:(Ljava/lang/Object;)Z
        77: ifeq          95
        80: new           #86                 // class scala/Tuple2
        83: dup
        84: aload         5
        86: aload         7
        88: invokespecial #90                 // Method scala/Tuple2."<init>":(Ljava/lang/Object;Ljava/lang/Object;)V
        91: astore_2
        92: goto          114
        95: goto          104
        98: goto          104
       101: goto          104
       104: new           #92                 // class scala/MatchError
       107: dup
       108: aload         4
       110: invokespecial #95                 // Method scala/MatchError."<init>":(Ljava/lang/Object;)V
       113: athrow
       114: aload_2
       115: astore_3
       116: aload_3
       117: invokevirtual #98                 // Method scala/Tuple2._1:()Ljava/lang/Object;
       120: checkcast     #70                 // class shapeless/HList
       123: astore        9
       125: aload_3
       126: invokevirtual #101                // Method scala/Tuple2._2:()Ljava/lang/Object;
       129: checkcast     #70                 // class shapeless/HList
       132: astore        10
       134: new           #46                 // class shapeless/Zipper
       137: dup
       138: getstatic     #44                 // Field shapeless/HList$.MODULE$:Lshapeless/HList$;
       141: aload         10
       143: invokevirtual #54                 // Method shapeless/HList$.hlistOps:(Lshapeless/HList;)Lshapeless/syntax/HListOps;
       146: aload_0
       147: getfield      #103                // Field cons$1:Lshapeless/ops/hlist$IsHCons;
       150: invokevirtual #106                // Method shapeless/syntax/HListOps.tail:(Lshapeless/ops/hlist$IsHCons;)Lshapeless/HList;
       153: getstatic     #44                 // Field shapeless/HList$.MODULE$:Lshapeless/HList$;
       156: aload         10
       158: invokevirtual #54                 // Method shapeless/HList$.hlistOps:(Lshapeless/HList;)Lshapeless/syntax/HListOps;
       161: aload_0
       162: getfield      #103                // Field cons$1:Lshapeless/ops/hlist$IsHCons;
       165: invokevirtual #109                // Method shapeless/syntax/HListOps.head:(Lshapeless/ops/hlist$IsHCons;)Ljava/lang/Object;
       168: astore        11
       170: getstatic     #44                 // Field shapeless/HList$.MODULE$:Lshapeless/HList$;
       173: aload         9
       175: astore        12
       177: getstatic     #44                 // Field shapeless/HList$.MODULE$:Lshapeless/HList$;
       180: aload_1
       181: invokevirtual #112                // Method shapeless/Zipper.suffix:()Lshapeless/HList;
       184: invokevirtual #54                 // Method shapeless/HList$.hlistOps:(Lshapeless/HList;)Lshapeless/syntax/HListOps;
       187: aload         12
       189: aload_0
       190: getfield      #114                // Field reverse$4:Lshapeless/ops/hlist$ReversePrepend;
       193: invokevirtual #118                // Method shapeless/syntax/HListOps.reverse_$colon$colon$colon:(Lshapeless/HList;Lshapeless/ops/hlist$ReversePrepend;)Lshapeless/HList;
       196: invokevirtual #54                 // Method shapeless/HList$.hlistOps:(Lshapeless/HList;)Lshapeless/syntax/HListOps;
       199: aload         11
       201: invokevirtual #122                // Method shapeless/syntax/HListOps.$colon$colon:(Ljava/lang/Object;)Lshapeless/$colon$colon;
       204: aload_1
       205: invokevirtual #125                // Method shapeless/Zipper.parent:()Ljava/lang/Object;
       208: invokespecial #128                // Method shapeless/Zipper."<init>":(Lshapeless/HList;Lshapeless/HList;Ljava/lang/Object;)V
       211: areturn
      StackMapTable: number_of_entries = 5
        frame_type = 255 /* full_frame */
          offset_delta = 95
          locals = [ class shapeless/ops/zipper$LeftTo$$anon$8, class shapeless/Zipper, top, top, class shapeless/$colon$colon, class shapeless/HList, class shapeless/$colon$colon, class shapeless/HList, class shapeless/HNil ]
          stack = []
        frame_type = 249 /* chop */
          offset_delta = 2
        frame_type = 249 /* chop */
          offset_delta = 2
        frame_type = 2 /* same */
        frame_type = 255 /* full_frame */
          offset_delta = 9
          locals = [ class shapeless/ops/zipper$LeftTo$$anon$8, class shapeless/Zipper, class scala/Tuple2, top, class shapeless/$colon$colon, class shapeless/HList, class shapeless/$colon$colon, class shapeless/HList, class shapeless/HNil ]
          stack = []
      LineNumberTable:
        line 156: 0
        line 157: 134
      LocalVariableTable:
        Start  Length  Slot  Name   Signature
           57      41     7     s   Lshapeless/HList;
           32      69     5     p   Lshapeless/HList;
          123      88     9     p   Lshapeless/HList;
          132      79    10     s   Lshapeless/HList;
            0     212     0  this   Lshapeless/ops/zipper$LeftTo$$anon$8;
            0     212     1     z   Lshapeless/Zipper;
    Signature: #37                          // (Lshapeless/Zipper<TC;TL;TR;TP;>;)Lshapeless/Zipper<TC;Lshapeless/HList;Lshapeless/$colon$colon<Ljava/lang/Object;Lshapeless/HList;>;TP;>;
    MethodParameters:
      Name                           Flags
      z                              final

  public java.lang.Object apply(java.lang.Object);
    descriptor: (Ljava/lang/Object;)Ljava/lang/Object;
    flags: (0x1041) ACC_PUBLIC, ACC_BRIDGE, ACC_SYNTHETIC
    Code:
      stack=2, locals=2, args_size=2
         0: aload_0
         1: aload_1
         2: checkcast     #46                 // class shapeless/Zipper
         5: invokevirtual #138                // Method apply:(Lshapeless/Zipper;)Lshapeless/Zipper;
         8: areturn
      LineNumberTable:
        line 153: 0
      LocalVariableTable:
        Start  Length  Slot  Name   Signature
            0       9     0  this   Lshapeless/ops/zipper$LeftTo$$anon$8;
            0       9     1     t   Ljava/lang/Object;
    MethodParameters:
      Name                           Flags
      t                              final

  public shapeless.ops.zipper$LeftTo$$anon$8(shapeless.ops.hlist$SplitLeft, shapeless.ops.hlist$IsHCons, shapeless.ops.hlist$ReversePrepend);
    descriptor: (Lshapeless/ops/hlist$SplitLeft;Lshapeless/ops/hlist$IsHCons;Lshapeless/ops/hlist$ReversePrepend;)V
    flags: (0x0001) ACC_PUBLIC
    Code:
      stack=2, locals=4, args_size=4
         0: aload_0
         1: aload_1
         2: putfield      #56                 // Field split$4:Lshapeless/ops/hlist$SplitLeft;
         5: aload_0
         6: aload_2
         7: putfield      #103                // Field cons$1:Lshapeless/ops/hlist$IsHCons;
        10: aload_0
        11: aload_3
        12: putfield      #114                // Field reverse$4:Lshapeless/ops/hlist$ReversePrepend;
        15: aload_0
        16: invokespecial #143                // Method java/lang/Object."<init>":()V
        19: return
      LineNumberTable:
        line 150: 0
        line 152: 5
        line 151: 10
        line 153: 15
      LocalVariableTable:
        Start  Length  Slot  Name   Signature
            0      20     0  this   Lshapeless/ops/zipper$LeftTo$$anon$8;
            0      20     1 split$4   Lshapeless/ops/hlist$SplitLeft;
            0      20     2 cons$1   Lshapeless/ops/hlist$IsHCons;
            0      20     3 reverse$4   Lshapeless/ops/hlist$ReversePrepend;
    MethodParameters:
      Name                           Flags
      split$4                        final
      cons$1                         final
      reverse$4                      final
}
InnerClasses:
  public static #18= #15 of #17;          // IsHCons=class shapeless/ops/hlist$IsHCons of class shapeless/ops/hlist
  public static #21= #20 of #17;          // ReversePrepend=class shapeless/ops/hlist$ReversePrepend of class shapeless/ops/hlist
  public static #24= #23 of #17;          // SplitLeft=class shapeless/ops/hlist$SplitLeft of class shapeless/ops/hlist
  public static #27= #7 of #26;           // LeftTo=class shapeless/ops/zipper$LeftTo of class shapeless/ops/zipper
  public static #28= #10 of #26;          // LeftTo$=class shapeless/ops/zipper$LeftTo$ of class shapeless/ops/zipper
  public final #2;                        // class shapeless/ops/zipper$LeftTo$$anon$8
EnclosingMethod: #10.#13                // shapeless.ops.zipper$LeftTo$.leftTo
Signature: #3                           // Ljava/lang/Object;Lshapeless/ops/zipper$LeftTo<Lshapeless/Zipper<TC;TL;TR;TP;>;TT;>;
SourceFile: "zipper.scala"
  ScalaInlineInfo: length = 0x13 (unknown attribute)
   01 01 00 03 00 57 00 8C 01 00 23 00 87 01 00 23
   00 24 01
  Scala: length = 0x0 (unknown attribute)

