Classfile /Users/mw/Projects/slang-braindump/.jar/jar8/assemble/slang-braindump/assemble/content/shapeless/ops/zipper$Put$$anon$16.class
  Last modified May 29, 2022; size 1808 bytes
  SHA-256 checksum 3c642569d2ec48df62b995e67c4651fb2f841ca33ee6ebe4e0def15a2be81b59
  Compiled from "zipper.scala"
public final class shapeless.ops.zipper$Put$$anon$16 extends java.lang.Object implements shapeless.ops.zipper$Put<shapeless.Zipper<C, L, shapeless.$colon$colon<RH, RT>, P>, E>
  minor version: 0
  major version: 52
  flags: (0x0031) ACC_PUBLIC, ACC_FINAL, ACC_SUPER
  this_class: #2                          // shapeless/ops/zipper$Put$$anon$16
  super_class: #5                         // java/lang/Object
  interfaces: 1, fields: 0, methods: 3, attributes: 6
Constant pool:
   #1 = Utf8               shapeless/ops/zipper$Put$$anon$16
   #2 = Class              #1             // shapeless/ops/zipper$Put$$anon$16
   #3 = Utf8               Ljava/lang/Object;Lshapeless/ops/zipper$Put<Lshapeless/Zipper<TC;TL;Lshapeless/$colon$colon<TRH;TRT;>;TP;>;TE;>;
   #4 = Utf8               java/lang/Object
   #5 = Class              #4             // java/lang/Object
   #6 = Utf8               shapeless/ops/zipper$Put
   #7 = Class              #6             // shapeless/ops/zipper$Put
   #8 = Utf8               zipper.scala
   #9 = Utf8               shapeless/ops/zipper$Put$
  #10 = Class              #9             // shapeless/ops/zipper$Put$
  #11 = Utf8               hlistPut
  #12 = Utf8               (Lshapeless/ops/hlist$ReversePrepend;)Lshapeless/ops/zipper$Put;
  #13 = NameAndType        #11:#12        // hlistPut:(Lshapeless/ops/hlist$ReversePrepend;)Lshapeless/ops/zipper$Put;
  #14 = Utf8               shapeless/ops/zipper
  #15 = Class              #14            // shapeless/ops/zipper
  #16 = Utf8               Put
  #17 = Utf8               Put$
  #18 = Utf8               apply
  #19 = Utf8               (Lshapeless/Zipper;Ljava/lang/Object;)Lshapeless/Zipper;
  #20 = Utf8               (Lshapeless/Zipper<TC;TL;Lshapeless/$colon$colon<TRH;TRT;>;TP;>;TE;)Lshapeless/Zipper<TCL;TL;Lshapeless/$colon$colon<TE;TRT;>;TP;>;
  #21 = Utf8               z
  #22 = Utf8               e
  #23 = Utf8               shapeless/Zipper
  #24 = Class              #23            // shapeless/Zipper
  #25 = Utf8               prefix
  #26 = Utf8               ()Lshapeless/HList;
  #27 = NameAndType        #25:#26        // prefix:()Lshapeless/HList;
  #28 = Methodref          #24.#27        // shapeless/Zipper.prefix:()Lshapeless/HList;
  #29 = Utf8               shapeless/HList$
  #30 = Class              #29            // shapeless/HList$
  #31 = Utf8               MODULE$
  #32 = Utf8               Lshapeless/HList$;
  #33 = NameAndType        #31:#32        // MODULE$:Lshapeless/HList$;
  #34 = Fieldref           #30.#33        // shapeless/HList$.MODULE$:Lshapeless/HList$;
  #35 = Utf8               suffix
  #36 = NameAndType        #35:#26        // suffix:()Lshapeless/HList;
  #37 = Methodref          #24.#36        // shapeless/Zipper.suffix:()Lshapeless/HList;
  #38 = Utf8               shapeless/$colon$colon
  #39 = Class              #38            // shapeless/$colon$colon
  #40 = Utf8               tail
  #41 = NameAndType        #40:#26        // tail:()Lshapeless/HList;
  #42 = Methodref          #39.#41        // shapeless/$colon$colon.tail:()Lshapeless/HList;
  #43 = Utf8               hlistOps
  #44 = Utf8               (Lshapeless/HList;)Lshapeless/syntax/HListOps;
  #45 = NameAndType        #43:#44        // hlistOps:(Lshapeless/HList;)Lshapeless/syntax/HListOps;
  #46 = Methodref          #30.#45        // shapeless/HList$.hlistOps:(Lshapeless/HList;)Lshapeless/syntax/HListOps;
  #47 = Utf8               shapeless/syntax/HListOps
  #48 = Class              #47            // shapeless/syntax/HListOps
  #49 = Utf8               $colon$colon
  #50 = Utf8               (Ljava/lang/Object;)Lshapeless/$colon$colon;
  #51 = NameAndType        #49:#50        // $colon$colon:(Ljava/lang/Object;)Lshapeless/$colon$colon;
  #52 = Methodref          #48.#51        // shapeless/syntax/HListOps.$colon$colon:(Ljava/lang/Object;)Lshapeless/$colon$colon;
  #53 = Utf8               parent
  #54 = Utf8               ()Ljava/lang/Object;
  #55 = NameAndType        #53:#54        // parent:()Ljava/lang/Object;
  #56 = Methodref          #24.#55        // shapeless/Zipper.parent:()Ljava/lang/Object;
  #57 = Utf8               <init>
  #58 = Utf8               (Lshapeless/HList;Lshapeless/HList;Ljava/lang/Object;)V
  #59 = NameAndType        #57:#58        // "<init>":(Lshapeless/HList;Lshapeless/HList;Ljava/lang/Object;)V
  #60 = Methodref          #24.#59        // shapeless/Zipper."<init>":(Lshapeless/HList;Lshapeless/HList;Ljava/lang/Object;)V
  #61 = Utf8               this
  #62 = Utf8               Lshapeless/ops/zipper$Put$$anon$16;
  #63 = Utf8               Lshapeless/Zipper;
  #64 = Utf8               Ljava/lang/Object;
  #65 = Utf8               (Ljava/lang/Object;Ljava/lang/Object;)Ljava/lang/Object;
  #66 = Utf8               t
  #67 = Utf8               u
  #68 = NameAndType        #18:#19        // apply:(Lshapeless/Zipper;Ljava/lang/Object;)Lshapeless/Zipper;
  #69 = Methodref          #2.#68         // shapeless/ops/zipper$Put$$anon$16.apply:(Lshapeless/Zipper;Ljava/lang/Object;)Lshapeless/Zipper;
  #70 = Utf8               ()V
  #71 = NameAndType        #57:#70        // "<init>":()V
  #72 = Methodref          #5.#71         // java/lang/Object."<init>":()V
  #73 = Utf8               Code
  #74 = Utf8               LineNumberTable
  #75 = Utf8               LocalVariableTable
  #76 = Utf8               Signature
  #77 = Utf8               MethodParameters
  #78 = Utf8               InnerClasses
  #79 = Utf8               EnclosingMethod
  #80 = Utf8               SourceFile
  #81 = Utf8               ScalaInlineInfo
  #82 = Utf8               Scala
{
  public shapeless.Zipper<CL, L, shapeless.$colon$colon<E, RT>, P> apply(shapeless.Zipper<C, L, shapeless.$colon$colon<RH, RT>, P>, E);
    descriptor: (Lshapeless/Zipper;Ljava/lang/Object;)Lshapeless/Zipper;
    flags: (0x0001) ACC_PUBLIC
    Code:
      stack=5, locals=4, args_size=3
         0: new           #24                 // class shapeless/Zipper
         3: dup
         4: aload_1
         5: invokevirtual #28                 // Method shapeless/Zipper.prefix:()Lshapeless/HList;
         8: aload_2
         9: astore_3
        10: getstatic     #34                 // Field shapeless/HList$.MODULE$:Lshapeless/HList$;
        13: aload_1
        14: invokevirtual #37                 // Method shapeless/Zipper.suffix:()Lshapeless/HList;
        17: checkcast     #39                 // class shapeless/$colon$colon
        20: invokevirtual #42                 // Method shapeless/$colon$colon.tail:()Lshapeless/HList;
        23: invokevirtual #46                 // Method shapeless/HList$.hlistOps:(Lshapeless/HList;)Lshapeless/syntax/HListOps;
        26: aload_3
        27: invokevirtual #52                 // Method shapeless/syntax/HListOps.$colon$colon:(Ljava/lang/Object;)Lshapeless/$colon$colon;
        30: aload_1
        31: invokevirtual #56                 // Method shapeless/Zipper.parent:()Ljava/lang/Object;
        34: invokespecial #60                 // Method shapeless/Zipper."<init>":(Lshapeless/HList;Lshapeless/HList;Ljava/lang/Object;)V
        37: areturn
      LineNumberTable:
        line 258: 0
      LocalVariableTable:
        Start  Length  Slot  Name   Signature
            0      38     0  this   Lshapeless/ops/zipper$Put$$anon$16;
            0      38     1     z   Lshapeless/Zipper;
            0      38     2     e   Ljava/lang/Object;
    Signature: #20                          // (Lshapeless/Zipper<TC;TL;Lshapeless/$colon$colon<TRH;TRT;>;TP;>;TE;)Lshapeless/Zipper<TCL;TL;Lshapeless/$colon$colon<TE;TRT;>;TP;>;
    MethodParameters:
      Name                           Flags
      z                              final
      e                              final

  public java.lang.Object apply(java.lang.Object, java.lang.Object);
    descriptor: (Ljava/lang/Object;Ljava/lang/Object;)Ljava/lang/Object;
    flags: (0x1041) ACC_PUBLIC, ACC_BRIDGE, ACC_SYNTHETIC
    Code:
      stack=3, locals=3, args_size=3
         0: aload_0
         1: aload_1
         2: checkcast     #24                 // class shapeless/Zipper
         5: aload_2
         6: invokevirtual #69                 // Method apply:(Lshapeless/Zipper;Ljava/lang/Object;)Lshapeless/Zipper;
         9: areturn
      LineNumberTable:
        line 256: 0
      LocalVariableTable:
        Start  Length  Slot  Name   Signature
            0      10     0  this   Lshapeless/ops/zipper$Put$$anon$16;
            0      10     1     t   Ljava/lang/Object;
            0      10     2     u   Ljava/lang/Object;
    MethodParameters:
      Name                           Flags
      t                              final
      u                              final

  public shapeless.ops.zipper$Put$$anon$16();
    descriptor: ()V
    flags: (0x0001) ACC_PUBLIC
    Code:
      stack=1, locals=1, args_size=1
         0: aload_0
         1: invokespecial #72                 // Method java/lang/Object."<init>":()V
         4: return
      LineNumberTable:
        line 256: 0
      LocalVariableTable:
        Start  Length  Slot  Name   Signature
            0       5     0  this   Lshapeless/ops/zipper$Put$$anon$16;
}
InnerClasses:
  public static #16= #7 of #15;           // Put=class shapeless/ops/zipper$Put of class shapeless/ops/zipper
  public static #17= #10 of #15;          // Put$=class shapeless/ops/zipper$Put$ of class shapeless/ops/zipper
  public final #2;                        // class shapeless/ops/zipper$Put$$anon$16
EnclosingMethod: #10.#13                // shapeless.ops.zipper$Put$.hlistPut
Signature: #3                           // Ljava/lang/Object;Lshapeless/ops/zipper$Put<Lshapeless/Zipper<TC;TL;Lshapeless/$colon$colon<TRH;TRT;>;TP;>;TE;>;
SourceFile: "zipper.scala"
  ScalaInlineInfo: length = 0x13 (unknown attribute)
   01 01 00 03 00 39 00 46 01 00 12 00 41 01 00 12
   00 13 01
  Scala: length = 0x0 (unknown attribute)

