Classfile /Users/mw/Projects/slang-braindump/.jar/jar8/assemble/slang-braindump/assemble/content/shapeless/ops/zipper$Put$.class
  Last modified May 29, 2022; size 2399 bytes
  SHA-256 checksum fe37cb11bb91eb38f5ef684fb8ed05c3196422be59f2400d924dcef1babf219d
  Compiled from "zipper.scala"
public class shapeless.ops.zipper$Put$ implements java.io.Serializable
  minor version: 0
  major version: 52
  flags: (0x0021) ACC_PUBLIC, ACC_SUPER
  this_class: #2                          // shapeless/ops/zipper$Put$
  super_class: #4                         // java/lang/Object
  interfaces: 1, fields: 1, methods: 6, attributes: 4
Constant pool:
   #1 = Utf8               shapeless/ops/zipper$Put$
   #2 = Class              #1             // shapeless/ops/zipper$Put$
   #3 = Utf8               java/lang/Object
   #4 = Class              #3             // java/lang/Object
   #5 = Utf8               java/io/Serializable
   #6 = Class              #5             // java/io/Serializable
   #7 = Utf8               zipper.scala
   #8 = Utf8               shapeless/ops/hlist$ReversePrepend
   #9 = Class              #8             // shapeless/ops/hlist$ReversePrepend
  #10 = Utf8               shapeless/ops/hlist
  #11 = Class              #10            // shapeless/ops/hlist
  #12 = Utf8               ReversePrepend
  #13 = Utf8               shapeless/ops/zipper$Put
  #14 = Class              #13            // shapeless/ops/zipper$Put
  #15 = Utf8               shapeless/ops/zipper
  #16 = Class              #15            // shapeless/ops/zipper
  #17 = Utf8               Put
  #18 = Utf8               Put$
  #19 = Utf8               shapeless/ops/zipper$Put$$anon$15
  #20 = Class              #19            // shapeless/ops/zipper$Put$$anon$15
  #21 = Utf8               shapeless/ops/zipper$Put$$anon$16
  #22 = Class              #21            // shapeless/ops/zipper$Put$$anon$16
  #23 = Utf8               MODULE$
  #24 = Utf8               Lshapeless/ops/zipper$Put$;
  #25 = Utf8               <clinit>
  #26 = Utf8               ()V
  #27 = Utf8               <init>
  #28 = NameAndType        #27:#26        // "<init>":()V
  #29 = Methodref          #2.#28         // shapeless/ops/zipper$Put$."<init>":()V
  #30 = NameAndType        #23:#24        // MODULE$:Lshapeless/ops/zipper$Put$;
  #31 = Fieldref           #2.#30         // shapeless/ops/zipper$Put$.MODULE$:Lshapeless/ops/zipper$Put$;
  #32 = Utf8               apply
  #33 = Utf8               (Lshapeless/ops/zipper$Put;)Lshapeless/ops/zipper$Put;
  #34 = Utf8               <Z:Ljava/lang/Object;E:Ljava/lang/Object;>(Lshapeless/ops/zipper$Put<TZ;TE;>;)Lshapeless/ops/zipper$Put<TZ;TE;>;
  #35 = Utf8               put
  #36 = Utf8               this
  #37 = Utf8               Lshapeless/ops/zipper$Put;
  #38 = Utf8               genericPut
  #39 = Utf8               (Lshapeless/Generic;Lshapeless/ops/hlist$ReversePrepend;)Lshapeless/ops/zipper$Put;
  #40 = Utf8               <C:Ljava/lang/Object;L::Lshapeless/HList;RH:Ljava/lang/Object;RT::Lshapeless/HList;P:Ljava/lang/Object;E:Ljava/lang/Object;CL::Lshapeless/HList;>(Lshapeless/Generic<TC;>;Lshapeless/ops/hlist$ReversePrepend<TL;Lshapeless/$colon$colon<TE;TRT;>;>;)Lshapeless/ops/zipper$Put<Lshapeless/Zipper<TC;TL;Lshapeless/$colon$colon<TRH;TRT;>;TP;>;TE;>;
  #41 = Utf8               gen
  #42 = Utf8               rp
  #43 = Methodref          #20.#28        // shapeless/ops/zipper$Put$$anon$15."<init>":()V
  #44 = Utf8               Lshapeless/Generic;
  #45 = Utf8               Lshapeless/ops/hlist$ReversePrepend;
  #46 = Utf8               hlistPut
  #47 = Utf8               (Lshapeless/ops/hlist$ReversePrepend;)Lshapeless/ops/zipper$Put;
  #48 = Utf8               <C::Lshapeless/HList;L::Lshapeless/HList;RH:Ljava/lang/Object;RT::Lshapeless/HList;P:Ljava/lang/Object;E:Ljava/lang/Object;CL::Lshapeless/HList;>(Lshapeless/ops/hlist$ReversePrepend<TL;Lshapeless/$colon$colon<TE;TRT;>;>;)Lshapeless/ops/zipper$Put<Lshapeless/Zipper<TC;TL;Lshapeless/$colon$colon<TRH;TRT;>;TP;>;TE;>;
  #49 = Methodref          #22.#28        // shapeless/ops/zipper$Put$$anon$16."<init>":()V
  #50 = Utf8               writeReplace
  #51 = Utf8               ()Ljava/lang/Object;
  #52 = Utf8               scala/runtime/ModuleSerializationProxy
  #53 = Class              #52            // scala/runtime/ModuleSerializationProxy
  #54 = Utf8               (Ljava/lang/Class;)V
  #55 = NameAndType        #27:#54        // "<init>":(Ljava/lang/Class;)V
  #56 = Methodref          #53.#55        // scala/runtime/ModuleSerializationProxy."<init>":(Ljava/lang/Class;)V
  #57 = Methodref          #4.#28         // java/lang/Object."<init>":()V
  #58 = Utf8               Code
  #59 = Utf8               LineNumberTable
  #60 = Utf8               LocalVariableTable
  #61 = Utf8               Signature
  #62 = Utf8               MethodParameters
  #63 = Utf8               InnerClasses
  #64 = Utf8               SourceFile
  #65 = Utf8               ScalaInlineInfo
  #66 = Utf8               Scala
{
  public static final shapeless.ops.zipper$Put$ MODULE$;
    descriptor: Lshapeless/ops/zipper$Put$;
    flags: (0x0019) ACC_PUBLIC, ACC_STATIC, ACC_FINAL

  public static {};
    descriptor: ()V
    flags: (0x0009) ACC_PUBLIC, ACC_STATIC
    Code:
      stack=2, locals=0, args_size=0
         0: new           #2                  // class shapeless/ops/zipper$Put$
         3: dup
         4: invokespecial #29                 // Method "<init>":()V
         7: putstatic     #31                 // Field MODULE$:Lshapeless/ops/zipper$Put$;
        10: return
      LineNumberTable:
        line 240: 0

  public <Z extends java.lang.Object, E extends java.lang.Object> shapeless.ops.zipper$Put<Z, E> apply(shapeless.ops.zipper$Put<Z, E>);
    descriptor: (Lshapeless/ops/zipper$Put;)Lshapeless/ops/zipper$Put;
    flags: (0x0001) ACC_PUBLIC
    Code:
      stack=1, locals=2, args_size=2
         0: aload_1
         1: areturn
      LineNumberTable:
        line 241: 0
      LocalVariableTable:
        Start  Length  Slot  Name   Signature
            0       2     0  this   Lshapeless/ops/zipper$Put$;
            0       2     1   put   Lshapeless/ops/zipper$Put;
    Signature: #34                          // <Z:Ljava/lang/Object;E:Ljava/lang/Object;>(Lshapeless/ops/zipper$Put<TZ;TE;>;)Lshapeless/ops/zipper$Put<TZ;TE;>;
    MethodParameters:
      Name                           Flags
      put                            final

  public <C extends java.lang.Object, L extends shapeless.HList, RH extends java.lang.Object, RT extends shapeless.HList, P extends java.lang.Object, E extends java.lang.Object, CL extends shapeless.HList> shapeless.ops.zipper$Put<shapeless.Zipper<C, L, shapeless.$colon$colon<RH, RT>, P>, E> genericPut(shapeless.Generic<C>, shapeless.ops.hlist$ReversePrepend<L, shapeless.$colon$colon<E, RT>>);
    descriptor: (Lshapeless/Generic;Lshapeless/ops/hlist$ReversePrepend;)Lshapeless/ops/zipper$Put;
    flags: (0x0001) ACC_PUBLIC
    Code:
      stack=2, locals=3, args_size=3
         0: new           #20                 // class shapeless/ops/zipper$Put$$anon$15
         3: dup
         4: invokespecial #43                 // Method shapeless/ops/zipper$Put$$anon$15."<init>":()V
         7: areturn
      LineNumberTable:
        line 249: 0
      LocalVariableTable:
        Start  Length  Slot  Name   Signature
            0       8     0  this   Lshapeless/ops/zipper$Put$;
            0       8     1   gen   Lshapeless/Generic;
            0       8     2    rp   Lshapeless/ops/hlist$ReversePrepend;
    Signature: #40                          // <C:Ljava/lang/Object;L::Lshapeless/HList;RH:Ljava/lang/Object;RT::Lshapeless/HList;P:Ljava/lang/Object;E:Ljava/lang/Object;CL::Lshapeless/HList;>(Lshapeless/Generic<TC;>;Lshapeless/ops/hlist$ReversePrepend<TL;Lshapeless/$colon$colon<TE;TRT;>;>;)Lshapeless/ops/zipper$Put<Lshapeless/Zipper<TC;TL;Lshapeless/$colon$colon<TRH;TRT;>;TP;>;TE;>;
    MethodParameters:
      Name                           Flags
      gen                            final
      rp                             final

  public <C extends shapeless.HList, L extends shapeless.HList, RH extends java.lang.Object, RT extends shapeless.HList, P extends java.lang.Object, E extends java.lang.Object, CL extends shapeless.HList> shapeless.ops.zipper$Put<shapeless.Zipper<C, L, shapeless.$colon$colon<RH, RT>, P>, E> hlistPut(shapeless.ops.hlist$ReversePrepend<L, shapeless.$colon$colon<E, RT>>);
    descriptor: (Lshapeless/ops/hlist$ReversePrepend;)Lshapeless/ops/zipper$Put;
    flags: (0x0001) ACC_PUBLIC
    Code:
      stack=2, locals=2, args_size=2
         0: new           #22                 // class shapeless/ops/zipper$Put$$anon$16
         3: dup
         4: invokespecial #49                 // Method shapeless/ops/zipper$Put$$anon$16."<init>":()V
         7: areturn
      LineNumberTable:
        line 256: 0
      LocalVariableTable:
        Start  Length  Slot  Name   Signature
            0       8     0  this   Lshapeless/ops/zipper$Put$;
            0       8     1    rp   Lshapeless/ops/hlist$ReversePrepend;
    Signature: #48                          // <C::Lshapeless/HList;L::Lshapeless/HList;RH:Ljava/lang/Object;RT::Lshapeless/HList;P:Ljava/lang/Object;E:Ljava/lang/Object;CL::Lshapeless/HList;>(Lshapeless/ops/hlist$ReversePrepend<TL;Lshapeless/$colon$colon<TE;TRT;>;>;)Lshapeless/ops/zipper$Put<Lshapeless/Zipper<TC;TL;Lshapeless/$colon$colon<TRH;TRT;>;TP;>;TE;>;
    MethodParameters:
      Name                           Flags
      rp                             final

  private java.lang.Object writeReplace();
    descriptor: ()Ljava/lang/Object;
    flags: (0x0002) ACC_PRIVATE
    Code:
      stack=3, locals=1, args_size=1
         0: new           #53                 // class scala/runtime/ModuleSerializationProxy
         3: dup
         4: ldc           #2                  // class shapeless/ops/zipper$Put$
         6: invokespecial #56                 // Method scala/runtime/ModuleSerializationProxy."<init>":(Ljava/lang/Class;)V
         9: areturn
      LineNumberTable:
        line 240: 0
      LocalVariableTable:
        Start  Length  Slot  Name   Signature
            0      10     0  this   Lshapeless/ops/zipper$Put$;

  public shapeless.ops.zipper$Put$();
    descriptor: ()V
    flags: (0x0001) ACC_PUBLIC
    Code:
      stack=1, locals=1, args_size=1
         0: aload_0
         1: invokespecial #57                 // Method java/lang/Object."<init>":()V
         4: return
      LineNumberTable:
        line 262: 0
        line 240: 4
      LocalVariableTable:
        Start  Length  Slot  Name   Signature
            0       5     0  this   Lshapeless/ops/zipper$Put$;
}
InnerClasses:
  public static #12= #9 of #11;           // ReversePrepend=class shapeless/ops/hlist$ReversePrepend of class shapeless/ops/hlist
  public static #17= #14 of #16;          // Put=class shapeless/ops/zipper$Put of class shapeless/ops/zipper
  public static #18= #2 of #16;           // Put$=class shapeless/ops/zipper$Put$ of class shapeless/ops/zipper
  public final #20;                       // class shapeless/ops/zipper$Put$$anon$15
  public final #22;                       // class shapeless/ops/zipper$Put$$anon$16
SourceFile: "zipper.scala"
  ScalaInlineInfo: length = 0x1D (unknown attribute)
   01 01 00 05 00 1B 00 1A 01 00 20 00 21 01 00 26
   00 27 01 00 2E 00 2F 01 00 32 00 33 01
  Scala: length = 0x0 (unknown attribute)

