Classfile /Users/mw/Projects/slang-braindump/.jar/jar8/assemble/slang-braindump/assemble/content/shapeless/ops/zipper$Modify$$anon$17.class
  Last modified May 29, 2022; size 1841 bytes
  SHA-256 checksum c6ffa4a729805e9da46f1acbc2ff15cc6917ee1ea51991ac95f6d8e86f64dd6c
  Compiled from "zipper.scala"
public final class shapeless.ops.zipper$Modify$$anon$17 extends java.lang.Object implements shapeless.ops.zipper$Modify<shapeless.Zipper<C, L, shapeless.$colon$colon<RH1, RT>, P>, RH1, RH2>
  minor version: 0
  major version: 52
  flags: (0x0031) ACC_PUBLIC, ACC_FINAL, ACC_SUPER
  this_class: #2                          // shapeless/ops/zipper$Modify$$anon$17
  super_class: #5                         // java/lang/Object
  interfaces: 1, fields: 2, methods: 3, attributes: 6
Constant pool:
   #1 = Utf8               shapeless/ops/zipper$Modify$$anon$17
   #2 = Class              #1             // shapeless/ops/zipper$Modify$$anon$17
   #3 = Utf8               Ljava/lang/Object;Lshapeless/ops/zipper$Modify<Lshapeless/Zipper<TC;TL;Lshapeless/$colon$colon<TRH1;TRT;>;TP;>;TRH1;TRH2;>;
   #4 = Utf8               java/lang/Object
   #5 = Class              #4             // java/lang/Object
   #6 = Utf8               shapeless/ops/zipper$Modify
   #7 = Class              #6             // shapeless/ops/zipper$Modify
   #8 = Utf8               zipper.scala
   #9 = Utf8               shapeless/ops/zipper$Modify$
  #10 = Class              #9             // shapeless/ops/zipper$Modify$
  #11 = Utf8               modify
  #12 = Utf8               (Lshapeless/ops/zipper$Get;Lshapeless/ops/zipper$Put;)Lshapeless/ops/zipper$Modify;
  #13 = NameAndType        #11:#12        // modify:(Lshapeless/ops/zipper$Get;Lshapeless/ops/zipper$Put;)Lshapeless/ops/zipper$Modify;
  #14 = Utf8               shapeless/ops/zipper$Get
  #15 = Class              #14            // shapeless/ops/zipper$Get
  #16 = Utf8               shapeless/ops/zipper
  #17 = Class              #16            // shapeless/ops/zipper
  #18 = Utf8               Get
  #19 = Utf8               Modify
  #20 = Utf8               Modify$
  #21 = Utf8               shapeless/ops/zipper$Put
  #22 = Class              #21            // shapeless/ops/zipper$Put
  #23 = Utf8               Put
  #24 = Utf8               put$1
  #25 = Utf8               Lshapeless/ops/zipper$Put;
  #26 = Utf8               get$1
  #27 = Utf8               Lshapeless/ops/zipper$Get;
  #28 = Utf8               apply
  #29 = Utf8               (Lshapeless/Zipper;Lscala/Function1;)Lshapeless/Zipper;
  #30 = Utf8               (Lshapeless/Zipper<TC;TL;Lshapeless/$colon$colon<TRH1;TRT;>;TP;>;Lscala/Function1<TRH1;TRH2;>;)Lshapeless/Zipper<TC;TL;Lshapeless/$colon$colon<TRH2;TRT;>;TP;>;
  #31 = Utf8               z
  #32 = Utf8               f
  #33 = NameAndType        #24:#25        // put$1:Lshapeless/ops/zipper$Put;
  #34 = Fieldref           #2.#33         // shapeless/ops/zipper$Modify$$anon$17.put$1:Lshapeless/ops/zipper$Put;
  #35 = NameAndType        #26:#27        // get$1:Lshapeless/ops/zipper$Get;
  #36 = Fieldref           #2.#35         // shapeless/ops/zipper$Modify$$anon$17.get$1:Lshapeless/ops/zipper$Get;
  #37 = Utf8               (Ljava/lang/Object;)Ljava/lang/Object;
  #38 = NameAndType        #28:#37        // apply:(Ljava/lang/Object;)Ljava/lang/Object;
  #39 = InterfaceMethodref #15.#38        // shapeless/ops/zipper$Get.apply:(Ljava/lang/Object;)Ljava/lang/Object;
  #40 = Utf8               scala/Function1
  #41 = Class              #40            // scala/Function1
  #42 = InterfaceMethodref #41.#38        // scala/Function1.apply:(Ljava/lang/Object;)Ljava/lang/Object;
  #43 = Utf8               (Ljava/lang/Object;Ljava/lang/Object;)Ljava/lang/Object;
  #44 = NameAndType        #28:#43        // apply:(Ljava/lang/Object;Ljava/lang/Object;)Ljava/lang/Object;
  #45 = InterfaceMethodref #22.#44        // shapeless/ops/zipper$Put.apply:(Ljava/lang/Object;Ljava/lang/Object;)Ljava/lang/Object;
  #46 = Utf8               shapeless/Zipper
  #47 = Class              #46            // shapeless/Zipper
  #48 = Utf8               this
  #49 = Utf8               Lshapeless/ops/zipper$Modify$$anon$17;
  #50 = Utf8               Lshapeless/Zipper;
  #51 = Utf8               Lscala/Function1;
  #52 = Utf8               t
  #53 = Utf8               u
  #54 = NameAndType        #28:#29        // apply:(Lshapeless/Zipper;Lscala/Function1;)Lshapeless/Zipper;
  #55 = Methodref          #2.#54         // shapeless/ops/zipper$Modify$$anon$17.apply:(Lshapeless/Zipper;Lscala/Function1;)Lshapeless/Zipper;
  #56 = Utf8               Ljava/lang/Object;
  #57 = Utf8               <init>
  #58 = Utf8               (Lshapeless/ops/zipper$Put;Lshapeless/ops/zipper$Get;)V
  #59 = Utf8               ()V
  #60 = NameAndType        #57:#59        // "<init>":()V
  #61 = Methodref          #5.#60         // java/lang/Object."<init>":()V
  #62 = Utf8               Code
  #63 = Utf8               LineNumberTable
  #64 = Utf8               LocalVariableTable
  #65 = Utf8               Signature
  #66 = Utf8               MethodParameters
  #67 = Utf8               InnerClasses
  #68 = Utf8               EnclosingMethod
  #69 = Utf8               SourceFile
  #70 = Utf8               ScalaInlineInfo
  #71 = Utf8               Scala
{
  private final shapeless.ops.zipper$Put put$1;
    descriptor: Lshapeless/ops/zipper$Put;
    flags: (0x0012) ACC_PRIVATE, ACC_FINAL

  private final shapeless.ops.zipper$Get get$1;
    descriptor: Lshapeless/ops/zipper$Get;
    flags: (0x0012) ACC_PRIVATE, ACC_FINAL

  public shapeless.Zipper<C, L, shapeless.$colon$colon<RH2, RT>, P> apply(shapeless.Zipper<C, L, shapeless.$colon$colon<RH1, RT>, P>, scala.Function1<RH1, RH2>);
    descriptor: (Lshapeless/Zipper;Lscala/Function1;)Lshapeless/Zipper;
    flags: (0x0001) ACC_PUBLIC
    Code:
      stack=5, locals=3, args_size=3
         0: aload_0
         1: getfield      #34                 // Field put$1:Lshapeless/ops/zipper$Put;
         4: aload_1
         5: aload_2
         6: aload_0
         7: getfield      #36                 // Field get$1:Lshapeless/ops/zipper$Get;
        10: aload_1
        11: invokeinterface #39,  2           // InterfaceMethod shapeless/ops/zipper$Get.apply:(Ljava/lang/Object;)Ljava/lang/Object;
        16: invokeinterface #42,  2           // InterfaceMethod scala/Function1.apply:(Ljava/lang/Object;)Ljava/lang/Object;
        21: invokeinterface #45,  3           // InterfaceMethod shapeless/ops/zipper$Put.apply:(Ljava/lang/Object;Ljava/lang/Object;)Ljava/lang/Object;
        26: checkcast     #47                 // class shapeless/Zipper
        29: areturn
      LineNumberTable:
        line 276: 0
      LocalVariableTable:
        Start  Length  Slot  Name   Signature
            0      30     0  this   Lshapeless/ops/zipper$Modify$$anon$17;
            0      30     1     z   Lshapeless/Zipper;
            0      30     2     f   Lscala/Function1;
    Signature: #30                          // (Lshapeless/Zipper<TC;TL;Lshapeless/$colon$colon<TRH1;TRT;>;TP;>;Lscala/Function1<TRH1;TRH2;>;)Lshapeless/Zipper<TC;TL;Lshapeless/$colon$colon<TRH2;TRT;>;TP;>;
    MethodParameters:
      Name                           Flags
      z                              final
      f                              final

  public java.lang.Object apply(java.lang.Object, java.lang.Object);
    descriptor: (Ljava/lang/Object;Ljava/lang/Object;)Ljava/lang/Object;
    flags: (0x1041) ACC_PUBLIC, ACC_BRIDGE, ACC_SYNTHETIC
    Code:
      stack=3, locals=3, args_size=3
         0: aload_0
         1: aload_1
         2: checkcast     #47                 // class shapeless/Zipper
         5: aload_2
         6: checkcast     #41                 // class scala/Function1
         9: invokevirtual #55                 // Method apply:(Lshapeless/Zipper;Lscala/Function1;)Lshapeless/Zipper;
        12: areturn
      LineNumberTable:
        line 274: 0
      LocalVariableTable:
        Start  Length  Slot  Name   Signature
            0      13     0  this   Lshapeless/ops/zipper$Modify$$anon$17;
            0      13     1     t   Ljava/lang/Object;
            0      13     2     u   Ljava/lang/Object;
    MethodParameters:
      Name                           Flags
      t                              final
      u                              final

  public shapeless.ops.zipper$Modify$$anon$17(shapeless.ops.zipper$Put, shapeless.ops.zipper$Get);
    descriptor: (Lshapeless/ops/zipper$Put;Lshapeless/ops/zipper$Get;)V
    flags: (0x0001) ACC_PUBLIC
    Code:
      stack=2, locals=3, args_size=3
         0: aload_0
         1: aload_1
         2: putfield      #34                 // Field put$1:Lshapeless/ops/zipper$Put;
         5: aload_0
         6: aload_2
         7: putfield      #36                 // Field get$1:Lshapeless/ops/zipper$Get;
        10: aload_0
        11: invokespecial #61                 // Method java/lang/Object."<init>":()V
        14: return
      LineNumberTable:
        line 272: 0
        line 271: 5
        line 274: 10
      LocalVariableTable:
        Start  Length  Slot  Name   Signature
            0      15     0  this   Lshapeless/ops/zipper$Modify$$anon$17;
            0      15     1 put$1   Lshapeless/ops/zipper$Put;
            0      15     2 get$1   Lshapeless/ops/zipper$Get;
    MethodParameters:
      Name                           Flags
      put$1                          final
      get$1                          final
}
InnerClasses:
  public static #18= #15 of #17;          // Get=class shapeless/ops/zipper$Get of class shapeless/ops/zipper
  public static #19= #7 of #17;           // Modify=class shapeless/ops/zipper$Modify of class shapeless/ops/zipper
  public static #20= #10 of #17;          // Modify$=class shapeless/ops/zipper$Modify$ of class shapeless/ops/zipper
  public final #2;                        // class shapeless/ops/zipper$Modify$$anon$17
  public static #23= #22 of #17;          // Put=class shapeless/ops/zipper$Put of class shapeless/ops/zipper
EnclosingMethod: #10.#13                // shapeless.ops.zipper$Modify$.modify
Signature: #3                           // Ljava/lang/Object;Lshapeless/ops/zipper$Modify<Lshapeless/Zipper<TC;TL;Lshapeless/$colon$colon<TRH1;TRT;>;TP;>;TRH1;TRH2;>;
SourceFile: "zipper.scala"
  ScalaInlineInfo: length = 0x13 (unknown attribute)
   01 01 00 03 00 39 00 3A 01 00 1C 00 2B 01 00 1C
   00 1D 01
  Scala: length = 0x0 (unknown attribute)

