Classfile /Users/mw/Projects/slang-braindump/.jar/jar11/assemble/slang-braindump/assemble/content/coursier/params/MirrorConfFile.class
  Last modified May 29, 2022; size 5337 bytes
  SHA-256 checksum ed03a2aa081e475672766e24a6c06f8b7ad5d3f7fa050a90e8c28721a28440d1
  Compiled from "MirrorConfFile.scala"
public final class coursier.params.MirrorConfFile extends coursier.internal.PlatformMirrorConfFile implements scala.Product,java.io.Serializable
  minor version: 0
  major version: 52
  flags: (0x0031) ACC_PUBLIC, ACC_FINAL, ACC_SUPER
  this_class: #2                          // coursier/params/MirrorConfFile
  super_class: #4                         // coursier/internal/PlatformMirrorConfFile
  interfaces: 2, fields: 2, methods: 19, attributes: 4
Constant pool:
    #1 = Utf8               coursier/params/MirrorConfFile
    #2 = Class              #1            // coursier/params/MirrorConfFile
    #3 = Utf8               coursier/internal/PlatformMirrorConfFile
    #4 = Class              #3            // coursier/internal/PlatformMirrorConfFile
    #5 = Utf8               scala/Product
    #6 = Class              #5            // scala/Product
    #7 = Utf8               java/io/Serializable
    #8 = Class              #7            // java/io/Serializable
    #9 = Utf8               MirrorConfFile.scala
   #10 = Utf8               Lscala/reflect/ScalaSignature;
   #11 = Utf8               bytes
   #12 = Utf8               \u0006\u0005\u0005-b\u0001\u0002\r\u001a\u0005yA\u0001b\u000e\u0001\u0003\u0006\u0004%\t\u0001\u000f\u0005\t\u0003\u0002\u0011\t\u0011)A\u0005s!A!\t\u0001BC\u0002\u0013\u00051\t\u0003\u0005H\u0001\t\u0005\t\u0015!\u0003E\u0011\u0015A\u0005\u0001\"\u0001J\u0011\u0015A\u0005\u0001\"\u0001O\u0011\u0015\u0001\u0006\u0001\"\u0001R\u0011\u0015\u0019\u0006\u0001\"\u0001U\u0011\u00151\u0006\u0001\"\u0011X\u0011\u0015y\u0006\u0001\"\u0011a\u0011\u00151\u0007\u0001\"\u0011h\u0011\u0015I\u0007\u0001\"\u0011k\u0011\u0015q\u0007\u0001\"\u0003p\u0011\u0015\u0019\b\u0001\"\u0011u\u0011\u0015)\b\u0001\"\u0011w\u0011\u00159\b\u0001\"\u0011y\u0011\u0015Y\b\u0001\"\u0011}\u000f\u0015q\u0018\u0004#\u0001\u0000\r\u0019A\u0012\u0004#\u0001\u0002\u0002!1\u0001j\u0005C\u0001\u0003\'Aq!!\u0006\u0014\t\u0003\t9\u0002C\u0004\u0002\u0016M!\t!a\u0007\t\u0013\u0005\u00052#!A\u0005\n\u0005\r\"AD\'jeJ|\'oQ8oM\u001aKG.\u001a\u0006\u00035m\ta\u0001]1sC6\u001c(\"\u0001\u000f\u0002\u0011\r|WO]:jKJ\u001c\u0001a\u0005\u0003\u0001?\u0015Z\u0003C\u0001\u0011$\u001b\u0005\t#B\u0001\u0012\u001c\u0003!Ig\u000e^3s]\u0006d\u0017B\u0001\u0013\"\u0005Y\u0001F.\u0019;g_JlW*\u001b:s_J\u001cuN\u001c4GS2,\u0007C\u0001\u0014*\u001b\u00059#\"\u0001\u0015\u0002\u000bM\u001c\u0017\r\\1\n\u0005):#a\u0002)s_\u0012,8\r\u001e\t\u0003YQr!!\f\u001a\u000f\u00059\nT\"A\u0018\u000b\u0005Aj\u0012A\u0002\u001fs_>$h(C\u0001)\u0013\t\u0019t%A\u0004qC\u000e\\\u0017mZ3\n\u0005U2$\u0001D*fe&\fG.\u001b>bE2,\'BA\u001a(\u0003\u0011\u0001\u0018\r\u001e5\u0016\u0003e\u0002\"A\u000f \u000f\u0005mb\u0004C\u0001\u0018(\u0013\tit%\u0001\u0004Qe\u0016$WMZ\u0005\u0003\u007f\u0001\u0013aa\u0015;sS:<\'BA\u001f(\u0003\u0015\u0001\u0018\r\u001e5!\u0003!y\u0007\u000f^5p]\u0006dW#\u0001#\u0011\u0005\u0019*\u0015B\u0001$(\u0005\u001d\u0011un\u001c7fC:\f\u0011b\u001c9uS>t\u0017\r\u001c\u0011\u0002\rqJg.\u001b;?)\rQE*\u0014\t\u0003\u0017\u0002i\u0011!\u0007\u0005\u0006o\u0015\u0001\r!\u000f\u0005\u0006\u0005\u0016\u0001\r\u0001\u0012\u000b\u0003\u0015>CQa\u000e\u0004A\u0002e\n\u0001b^5uQB\u000bG\u000f\u001b\u000b\u0003\u0015JCQaN\u0004A\u0002e\nAb^5uQ>\u0003H/[8oC2$\"AS+\t\u000b\tC\u0001\u0019\u0001#\u0002\u0011Q|7\u000b\u001e:j]\u001e$\u0012\u0001\u0017\t\u00033zk\u0011A\u0017\u0006\u00037r\u000bA\u0001\\1oO*\tQ,\u0001\u0003kCZ\f\u0017BA [\u0003!\u0019\u0017M\\#rk\u0006dGC\u0001#b\u0011\u0015\u0011\'\u00021\u0001d\u0003\ry\'M\u001b\t\u0003M\u0011L!!Z\u0014\u0003\u0007\u0005s\u00170\u0001\u0004fcV\fGn\u001d\u000b\u0003\t\"DQAY\u0006A\u0002\r\f\u0001\u0002[1tQ\u000e{G-\u001a\u000b\u0002WB\u0011a\u0005\\\u0005\u0003[\u001e\u00121!\u00138u\u0003\u0015!X\u000f\u001d7f+\u0005\u0001\b\u0003\u0002\u0014rs\u0011K!A]\u0014\u0003\rQ+\b\u000f\\33\u00035\u0001(o\u001c3vGR\u0004&/\u001a4jqV\t\u0001,\u0001\u0007qe>$Wo\u0019;Be&$\u00180F\u0001l\u00039\u0001(o\u001c3vGR,E.Z7f]R$\"aY=\t\u000bi\u0004\u0002\u0019A6\u0002\u00039\f!\u0003\u001d:pIV\u001cG/\u00127f[\u0016tGOT1nKR\u0011\u0001, \u0005\u0006uF\u0001\ra[\u0001\u000f\u001b&\u0014(o\u001c:D_:4g)\u001b7f!\tY5cE\u0003\u0014\u0003\u0007\tI\u0001E\u0002\'\u0003\u000bI1!a\u0002(\u0005\u0019\te.\u001f*fMB!\u00111BA\t\u001b\t\tiAC\u0002\u0002\u0010q\u000b!![8\n\u0007U\ni\u0001F\u0001\u0000\u0003\u0015\t\u0007\u000f\u001d7z)\rQ\u0015\u0011\u0004\u0005\u0006oU\u0001\r!\u000f\u000b\u0006\u0015\u0006u\u0011q\u0004\u0005\u0006oY\u0001\r!\u000f\u0005\u0006\u0005Z\u0001\r\u0001R\u0001\roJLG/\u001a*fa2\f7-\u001a\u000b\u0003\u0003K\u00012!WA\u0014\u0013\r\tIC\u0017\u0002\u0007\u001f\nTWm\u0019;
   #13 = Utf8               path
   #14 = Utf8               Ljava/lang/String;
   #15 = Utf8               optional
   #16 = Utf8               Z
   #17 = Utf8               apply
   #18 = Utf8               (Ljava/lang/String;Z)Lcoursier/params/MirrorConfFile;
   #19 = Utf8               coursier/params/MirrorConfFile$
   #20 = Class              #19           // coursier/params/MirrorConfFile$
   #21 = Utf8               MODULE$
   #22 = Utf8               Lcoursier/params/MirrorConfFile$;
   #23 = NameAndType        #21:#22       // MODULE$:Lcoursier/params/MirrorConfFile$;
   #24 = Fieldref           #20.#23       // coursier/params/MirrorConfFile$.MODULE$:Lcoursier/params/MirrorConfFile$;
   #25 = NameAndType        #17:#18       // apply:(Ljava/lang/String;Z)Lcoursier/params/MirrorConfFile;
   #26 = Methodref          #20.#25       // coursier/params/MirrorConfFile$.apply:(Ljava/lang/String;Z)Lcoursier/params/MirrorConfFile;
   #27 = Utf8               (Ljava/lang/String;)Lcoursier/params/MirrorConfFile;
   #28 = NameAndType        #17:#27       // apply:(Ljava/lang/String;)Lcoursier/params/MirrorConfFile;
   #29 = Methodref          #20.#28       // coursier/params/MirrorConfFile$.apply:(Ljava/lang/String;)Lcoursier/params/MirrorConfFile;
   #30 = Utf8               productIterator
   #31 = Utf8               ()Lscala/collection/Iterator;
   #32 = Utf8               ()Lscala/collection/Iterator<Ljava/lang/Object;>;
   #33 = Utf8               productIterator$
   #34 = Utf8               (Lscala/Product;)Lscala/collection/Iterator;
   #35 = NameAndType        #33:#34       // productIterator$:(Lscala/Product;)Lscala/collection/Iterator;
   #36 = InterfaceMethodref #6.#35        // scala/Product.productIterator$:(Lscala/Product;)Lscala/collection/Iterator;
   #37 = Utf8               this
   #38 = Utf8               Lcoursier/params/MirrorConfFile;
   #39 = Utf8               productElementNames
   #40 = Utf8               ()Lscala/collection/Iterator<Ljava/lang/String;>;
   #41 = Utf8               productElementNames$
   #42 = NameAndType        #41:#34       // productElementNames$:(Lscala/Product;)Lscala/collection/Iterator;
   #43 = InterfaceMethodref #6.#42        // scala/Product.productElementNames$:(Lscala/Product;)Lscala/collection/Iterator;
   #44 = Utf8               ()Ljava/lang/String;
   #45 = NameAndType        #13:#14       // path:Ljava/lang/String;
   #46 = Fieldref           #2.#45        // coursier/params/MirrorConfFile.path:Ljava/lang/String;
   #47 = Utf8               ()Z
   #48 = NameAndType        #15:#16       // optional:Z
   #49 = Fieldref           #2.#48        // coursier/params/MirrorConfFile.optional:Z
   #50 = Utf8               withPath
   #51 = NameAndType        #15:#47       // optional:()Z
   #52 = Methodref          #2.#51        // coursier/params/MirrorConfFile.optional:()Z
   #53 = Utf8               <init>
   #54 = Utf8               (Ljava/lang/String;Z)V
   #55 = NameAndType        #53:#54       // "<init>":(Ljava/lang/String;Z)V
   #56 = Methodref          #2.#55        // coursier/params/MirrorConfFile."<init>":(Ljava/lang/String;Z)V
   #57 = Utf8               withOptional
   #58 = Utf8               (Z)Lcoursier/params/MirrorConfFile;
   #59 = NameAndType        #13:#44       // path:()Ljava/lang/String;
   #60 = Methodref          #2.#59        // coursier/params/MirrorConfFile.path:()Ljava/lang/String;
   #61 = Utf8               toString
   #62 = Utf8               java/lang/StringBuilder
   #63 = Class              #62           // java/lang/StringBuilder
   #64 = Utf8               MirrorConfFile(
   #65 = String             #64           // MirrorConfFile(
   #66 = Utf8               (Ljava/lang/String;)V
   #67 = NameAndType        #53:#66       // "<init>":(Ljava/lang/String;)V
   #68 = Methodref          #63.#67       // java/lang/StringBuilder."<init>":(Ljava/lang/String;)V
   #69 = Utf8               java/lang/String
   #70 = Class              #69           // java/lang/String
   #71 = Utf8               valueOf
   #72 = Utf8               (Ljava/lang/Object;)Ljava/lang/String;
   #73 = NameAndType        #71:#72       // valueOf:(Ljava/lang/Object;)Ljava/lang/String;
   #74 = Methodref          #70.#73       // java/lang/String.valueOf:(Ljava/lang/Object;)Ljava/lang/String;
   #75 = Utf8               append
   #76 = Utf8               (Ljava/lang/String;)Ljava/lang/StringBuilder;
   #77 = NameAndType        #75:#76       // append:(Ljava/lang/String;)Ljava/lang/StringBuilder;
   #78 = Methodref          #63.#77       // java/lang/StringBuilder.append:(Ljava/lang/String;)Ljava/lang/StringBuilder;
   #79 = Utf8               ,
   #80 = String             #79           // ,
   #81 = Utf8               (Z)Ljava/lang/String;
   #82 = NameAndType        #71:#81       // valueOf:(Z)Ljava/lang/String;
   #83 = Methodref          #70.#82       // java/lang/String.valueOf:(Z)Ljava/lang/String;
   #84 = Utf8               )
   #85 = String             #84           // )
   #86 = NameAndType        #61:#44       // toString:()Ljava/lang/String;
   #87 = Methodref          #63.#86       // java/lang/StringBuilder.toString:()Ljava/lang/String;
   #88 = Utf8               b
   #89 = Utf8               Ljava/lang/StringBuilder;
   #90 = Utf8               canEqual
   #91 = Utf8               (Ljava/lang/Object;)Z
   #92 = Utf8               obj
   #93 = Utf8               Ljava/lang/Object;
   #94 = Utf8               equals
   #95 = NameAndType        #90:#91       // canEqual:(Ljava/lang/Object;)Z
   #96 = Methodref          #2.#95        // coursier/params/MirrorConfFile.canEqual:(Ljava/lang/Object;)Z
   #97 = Utf8               java/lang/Object
   #98 = Class              #97           // java/lang/Object
   #99 = NameAndType        #94:#91       // equals:(Ljava/lang/Object;)Z
  #100 = Methodref          #98.#99       // java/lang/Object.equals:(Ljava/lang/Object;)Z
  #101 = Utf8               other
  #102 = Utf8               hashCode
  #103 = Utf8               ()I
  #104 = Utf8               MirrorConfFile
  #105 = String             #104          // MirrorConfFile
  #106 = Utf8               scala/runtime/Statics
  #107 = Class              #106          // scala/runtime/Statics
  #108 = Utf8               anyHash
  #109 = Utf8               (Ljava/lang/Object;)I
  #110 = NameAndType        #108:#109     // anyHash:(Ljava/lang/Object;)I
  #111 = Methodref          #107.#110     // scala/runtime/Statics.anyHash:(Ljava/lang/Object;)I
  #112 = Utf8               code
  #113 = Utf8               I
  #114 = Utf8               tuple
  #115 = Utf8               ()Lscala/Tuple2;
  #116 = Utf8               ()Lscala/Tuple2<Ljava/lang/String;Ljava/lang/Object;>;
  #117 = Utf8               scala/Tuple2
  #118 = Class              #117          // scala/Tuple2
  #119 = Utf8               scala/runtime/BoxesRunTime
  #120 = Class              #119          // scala/runtime/BoxesRunTime
  #121 = Utf8               boxToBoolean
  #122 = Utf8               (Z)Ljava/lang/Boolean;
  #123 = NameAndType        #121:#122     // boxToBoolean:(Z)Ljava/lang/Boolean;
  #124 = Methodref          #120.#123     // scala/runtime/BoxesRunTime.boxToBoolean:(Z)Ljava/lang/Boolean;
  #125 = Utf8               (Ljava/lang/Object;Ljava/lang/Object;)V
  #126 = NameAndType        #53:#125      // "<init>":(Ljava/lang/Object;Ljava/lang/Object;)V
  #127 = Methodref          #118.#126     // scala/Tuple2."<init>":(Ljava/lang/Object;Ljava/lang/Object;)V
  #128 = Utf8               productPrefix
  #129 = Utf8               productArity
  #130 = Utf8               productElement
  #131 = Utf8               (I)Ljava/lang/Object;
  #132 = Utf8               n
  #133 = Utf8               java/lang/IndexOutOfBoundsException
  #134 = Class              #133          // java/lang/IndexOutOfBoundsException
  #135 = Utf8               boxToInteger
  #136 = Utf8               (I)Ljava/lang/Integer;
  #137 = NameAndType        #135:#136     // boxToInteger:(I)Ljava/lang/Integer;
  #138 = Methodref          #120.#137     // scala/runtime/BoxesRunTime.boxToInteger:(I)Ljava/lang/Integer;
  #139 = Methodref          #98.#86       // java/lang/Object.toString:()Ljava/lang/String;
  #140 = Methodref          #134.#67      // java/lang/IndexOutOfBoundsException."<init>":(Ljava/lang/String;)V
  #141 = Utf8               productElementName
  #142 = Utf8               (I)Ljava/lang/String;
  #143 = String             #13           // path
  #144 = String             #15           // optional
  #145 = Utf8               ()V
  #146 = NameAndType        #53:#145      // "<init>":()V
  #147 = Methodref          #4.#146       // coursier/internal/PlatformMirrorConfFile."<init>":()V
  #148 = Utf8               $init$
  #149 = Utf8               (Lscala/Product;)V
  #150 = NameAndType        #148:#149     // $init$:(Lscala/Product;)V
  #151 = InterfaceMethodref #6.#150       // scala/Product.$init$:(Lscala/Product;)V
  #152 = Utf8               Code
  #153 = Utf8               MethodParameters
  #154 = Utf8               LineNumberTable
  #155 = Utf8               LocalVariableTable
  #156 = Utf8               Signature
  #157 = Utf8               StackMapTable
  #158 = Utf8               SourceFile
  #159 = Utf8               RuntimeVisibleAnnotations
  #160 = Utf8               ScalaInlineInfo
  #161 = Utf8               ScalaSig
{
  private final java.lang.String path;
    descriptor: Ljava/lang/String;
    flags: (0x0012) ACC_PRIVATE, ACC_FINAL

  private final boolean optional;
    descriptor: Z
    flags: (0x0012) ACC_PRIVATE, ACC_FINAL

  public static coursier.params.MirrorConfFile apply(java.lang.String, boolean);
    descriptor: (Ljava/lang/String;Z)Lcoursier/params/MirrorConfFile;
    flags: (0x0009) ACC_PUBLIC, ACC_STATIC
    Code:
      stack=3, locals=2, args_size=2
         0: getstatic     #24                 // Field coursier/params/MirrorConfFile$.MODULE$:Lcoursier/params/MirrorConfFile$;
         3: aload_0
         4: iload_1
         5: invokevirtual #26                 // Method coursier/params/MirrorConfFile$.apply:(Ljava/lang/String;Z)Lcoursier/params/MirrorConfFile;
         8: areturn
    MethodParameters:
      Name                           Flags
      path                           final
      optional                       final

  public static coursier.params.MirrorConfFile apply(java.lang.String);
    descriptor: (Ljava/lang/String;)Lcoursier/params/MirrorConfFile;
    flags: (0x0009) ACC_PUBLIC, ACC_STATIC
    Code:
      stack=2, locals=1, args_size=1
         0: getstatic     #24                 // Field coursier/params/MirrorConfFile$.MODULE$:Lcoursier/params/MirrorConfFile$;
         3: aload_0
         4: invokevirtual #29                 // Method coursier/params/MirrorConfFile$.apply:(Ljava/lang/String;)Lcoursier/params/MirrorConfFile;
         7: areturn
    MethodParameters:
      Name                           Flags
      path                           final

  public scala.collection.Iterator<java.lang.Object> productIterator();
    descriptor: ()Lscala/collection/Iterator;
    flags: (0x0001) ACC_PUBLIC
    Code:
      stack=1, locals=1, args_size=1
         0: aload_0
         1: invokestatic  #36                 // InterfaceMethod scala/Product.productIterator$:(Lscala/Product;)Lscala/collection/Iterator;
         4: areturn
      LineNumberTable:
        line 4: 0
      LocalVariableTable:
        Start  Length  Slot  Name   Signature
            0       5     0  this   Lcoursier/params/MirrorConfFile;
    Signature: #32                          // ()Lscala/collection/Iterator<Ljava/lang/Object;>;

  public scala.collection.Iterator<java.lang.String> productElementNames();
    descriptor: ()Lscala/collection/Iterator;
    flags: (0x0001) ACC_PUBLIC
    Code:
      stack=1, locals=1, args_size=1
         0: aload_0
         1: invokestatic  #43                 // InterfaceMethod scala/Product.productElementNames$:(Lscala/Product;)Lscala/collection/Iterator;
         4: areturn
      LineNumberTable:
        line 4: 0
      LocalVariableTable:
        Start  Length  Slot  Name   Signature
            0       5     0  this   Lcoursier/params/MirrorConfFile;
    Signature: #40                          // ()Lscala/collection/Iterator<Ljava/lang/String;>;

  public java.lang.String path();
    descriptor: ()Ljava/lang/String;
    flags: (0x0001) ACC_PUBLIC
    Code:
      stack=1, locals=1, args_size=1
         0: aload_0
         1: getfield      #46                 // Field path:Ljava/lang/String;
         4: areturn
      LineNumberTable:
        line 4: 0
      LocalVariableTable:
        Start  Length  Slot  Name   Signature
            0       5     0  this   Lcoursier/params/MirrorConfFile;

  public boolean optional();
    descriptor: ()Z
    flags: (0x0001) ACC_PUBLIC
    Code:
      stack=1, locals=1, args_size=1
         0: aload_0
         1: getfield      #49                 // Field optional:Z
         4: ireturn
      LineNumberTable:
        line 4: 0
      LocalVariableTable:
        Start  Length  Slot  Name   Signature
            0       5     0  this   Lcoursier/params/MirrorConfFile;

  public coursier.params.MirrorConfFile withPath(java.lang.String);
    descriptor: (Ljava/lang/String;)Lcoursier/params/MirrorConfFile;
    flags: (0x0001) ACC_PUBLIC
    Code:
      stack=4, locals=2, args_size=2
         0: new           #2                  // class coursier/params/MirrorConfFile
         3: dup
         4: aload_1
         5: aload_0
         6: invokevirtual #52                 // Method optional:()Z
         9: invokespecial #56                 // Method "<init>":(Ljava/lang/String;Z)V
        12: areturn
      LineNumberTable:
        line 4: 0
      LocalVariableTable:
        Start  Length  Slot  Name   Signature
            0      13     0  this   Lcoursier/params/MirrorConfFile;
            0      13     1  path   Ljava/lang/String;
    MethodParameters:
      Name                           Flags
      path                           final

  public coursier.params.MirrorConfFile withOptional(boolean);
    descriptor: (Z)Lcoursier/params/MirrorConfFile;
    flags: (0x0001) ACC_PUBLIC
    Code:
      stack=4, locals=2, args_size=2
         0: new           #2                  // class coursier/params/MirrorConfFile
         3: dup
         4: aload_0
         5: invokevirtual #60                 // Method path:()Ljava/lang/String;
         8: iload_1
         9: invokespecial #56                 // Method "<init>":(Ljava/lang/String;Z)V
        12: areturn
      LineNumberTable:
        line 4: 0
      LocalVariableTable:
        Start  Length  Slot  Name   Signature
            0      13     0  this   Lcoursier/params/MirrorConfFile;
            0      13     1 optional   Z
    MethodParameters:
      Name                           Flags
      optional                       final

  public java.lang.String toString();
    descriptor: ()Ljava/lang/String;
    flags: (0x0001) ACC_PUBLIC
    Code:
      stack=3, locals=2, args_size=1
         0: new           #63                 // class java/lang/StringBuilder
         3: dup
         4: ldc           #65                 // String MirrorConfFile(
         6: invokespecial #68                 // Method java/lang/StringBuilder."<init>":(Ljava/lang/String;)V
         9: astore_1
        10: aload_1
        11: aload_0
        12: invokevirtual #60                 // Method path:()Ljava/lang/String;
        15: invokestatic  #74                 // Method java/lang/String.valueOf:(Ljava/lang/Object;)Ljava/lang/String;
        18: invokevirtual #78                 // Method java/lang/StringBuilder.append:(Ljava/lang/String;)Ljava/lang/StringBuilder;
        21: pop
        22: aload_1
        23: ldc           #80                 // String ,
        25: invokevirtual #78                 // Method java/lang/StringBuilder.append:(Ljava/lang/String;)Ljava/lang/StringBuilder;
        28: pop
        29: aload_1
        30: aload_0
        31: invokevirtual #52                 // Method optional:()Z
        34: invokestatic  #83                 // Method java/lang/String.valueOf:(Z)Ljava/lang/String;
        37: invokevirtual #78                 // Method java/lang/StringBuilder.append:(Ljava/lang/String;)Ljava/lang/StringBuilder;
        40: pop
        41: aload_1
        42: ldc           #85                 // String )
        44: invokevirtual #78                 // Method java/lang/StringBuilder.append:(Ljava/lang/String;)Ljava/lang/StringBuilder;
        47: pop
        48: aload_1
        49: invokevirtual #87                 // Method java/lang/StringBuilder.toString:()Ljava/lang/String;
        52: areturn
      LineNumberTable:
        line 4: 0
      LocalVariableTable:
        Start  Length  Slot  Name   Signature
           10      42     1     b   Ljava/lang/StringBuilder;
            0      53     0  this   Lcoursier/params/MirrorConfFile;

  public boolean canEqual(java.lang.Object);
    descriptor: (Ljava/lang/Object;)Z
    flags: (0x0001) ACC_PUBLIC
    Code:
      stack=1, locals=2, args_size=2
         0: aload_1
         1: ifnull        15
         4: aload_1
         5: instanceof    #2                  // class coursier/params/MirrorConfFile
         8: ifeq          15
        11: iconst_1
        12: goto          16
        15: iconst_0
        16: ireturn
      StackMapTable: number_of_entries = 2
        frame_type = 15 /* same */
        frame_type = 64 /* same_locals_1_stack_item */
          stack = [ int ]
      LineNumberTable:
        line 4: 0
      LocalVariableTable:
        Start  Length  Slot  Name   Signature
            0      17     0  this   Lcoursier/params/MirrorConfFile;
            0      17     1   obj   Ljava/lang/Object;
    MethodParameters:
      Name                           Flags
      obj                            final

  public boolean equals(java.lang.Object);
    descriptor: (Ljava/lang/Object;)Z
    flags: (0x0001) ACC_PUBLIC
    Code:
      stack=2, locals=4, args_size=2
         0: aload_0
         1: aload_1
         2: if_acmpeq     69
         5: aload_0
         6: aload_1
         7: invokevirtual #96                 // Method canEqual:(Ljava/lang/Object;)Z
        10: ifeq          73
        13: aload_1
        14: checkcast     #2                  // class coursier/params/MirrorConfFile
        17: astore_2
        18: iconst_1
        19: ifeq          65
        22: aload_0
        23: invokevirtual #60                 // Method path:()Ljava/lang/String;
        26: aload_2
        27: invokevirtual #60                 // Method path:()Ljava/lang/String;
        30: astore_3
        31: dup
        32: ifnonnull     43
        35: pop
        36: aload_3
        37: ifnull        50
        40: goto          65
        43: aload_3
        44: invokevirtual #100                // Method java/lang/Object.equals:(Ljava/lang/Object;)Z
        47: ifeq          65
        50: aload_0
        51: invokevirtual #52                 // Method optional:()Z
        54: aload_2
        55: invokevirtual #52                 // Method optional:()Z
        58: if_icmpne     65
        61: iconst_1
        62: goto          66
        65: iconst_0
        66: ifeq          73
        69: iconst_1
        70: goto          74
        73: iconst_0
        74: ireturn
      StackMapTable: number_of_entries = 7
        frame_type = 255 /* full_frame */
          offset_delta = 43
          locals = [ class coursier/params/MirrorConfFile, class java/lang/Object, class coursier/params/MirrorConfFile, class java/lang/String ]
          stack = [ class java/lang/String ]
        frame_type = 6 /* same */
        frame_type = 250 /* chop */
          offset_delta = 14
        frame_type = 64 /* same_locals_1_stack_item */
          stack = [ int ]
        frame_type = 250 /* chop */
          offset_delta = 2
        frame_type = 3 /* same */
        frame_type = 64 /* same_locals_1_stack_item */
          stack = [ int ]
      LineNumberTable:
        line 4: 0
      LocalVariableTable:
        Start  Length  Slot  Name   Signature
           18      48     2 other   Lcoursier/params/MirrorConfFile;
            0      75     0  this   Lcoursier/params/MirrorConfFile;
            0      75     1   obj   Ljava/lang/Object;
    MethodParameters:
      Name                           Flags
      obj                            final

  public int hashCode();
    descriptor: ()I
    flags: (0x0001) ACC_PUBLIC
    Code:
      stack=2, locals=2, args_size=1
         0: bipush        17
         2: ldc           #105                // String MirrorConfFile
         4: invokestatic  #111                // Method scala/runtime/Statics.anyHash:(Ljava/lang/Object;)I
         7: iadd
         8: istore_1
         9: bipush        37
        11: iload_1
        12: imul
        13: aload_0
        14: invokevirtual #60                 // Method path:()Ljava/lang/String;
        17: invokestatic  #111                // Method scala/runtime/Statics.anyHash:(Ljava/lang/Object;)I
        20: iadd
        21: istore_1
        22: bipush        37
        24: iload_1
        25: imul
        26: aload_0
        27: invokevirtual #52                 // Method optional:()Z
        30: ifeq          39
        33: sipush        1231
        36: goto          42
        39: sipush        1237
        42: iadd
        43: istore_1
        44: bipush        37
        46: iload_1
        47: imul
        48: ireturn
      StackMapTable: number_of_entries = 2
        frame_type = 255 /* full_frame */
          offset_delta = 39
          locals = [ class coursier/params/MirrorConfFile, int ]
          stack = [ int ]
        frame_type = 255 /* full_frame */
          offset_delta = 2
          locals = [ class coursier/params/MirrorConfFile, int ]
          stack = [ int, int ]
      LineNumberTable:
        line 4: 0
      LocalVariableTable:
        Start  Length  Slot  Name   Signature
            9      39     1  code   I
            0      49     0  this   Lcoursier/params/MirrorConfFile;

  private scala.Tuple2<java.lang.String, java.lang.Object> tuple();
    descriptor: ()Lscala/Tuple2;
    flags: (0x0002) ACC_PRIVATE
    Code:
      stack=4, locals=1, args_size=1
         0: new           #118                // class scala/Tuple2
         3: dup
         4: aload_0
         5: invokevirtual #60                 // Method path:()Ljava/lang/String;
         8: aload_0
         9: invokevirtual #52                 // Method optional:()Z
        12: invokestatic  #124                // Method scala/runtime/BoxesRunTime.boxToBoolean:(Z)Ljava/lang/Boolean;
        15: invokespecial #127                // Method scala/Tuple2."<init>":(Ljava/lang/Object;Ljava/lang/Object;)V
        18: areturn
      LineNumberTable:
        line 4: 0
      LocalVariableTable:
        Start  Length  Slot  Name   Signature
            0      19     0  this   Lcoursier/params/MirrorConfFile;
    Signature: #116                         // ()Lscala/Tuple2<Ljava/lang/String;Ljava/lang/Object;>;

  public java.lang.String productPrefix();
    descriptor: ()Ljava/lang/String;
    flags: (0x0001) ACC_PUBLIC
    Code:
      stack=1, locals=1, args_size=1
         0: ldc           #105                // String MirrorConfFile
         2: areturn
      LineNumberTable:
        line 4: 0
      LocalVariableTable:
        Start  Length  Slot  Name   Signature
            0       3     0  this   Lcoursier/params/MirrorConfFile;

  public int productArity();
    descriptor: ()I
    flags: (0x0001) ACC_PUBLIC
    Code:
      stack=1, locals=1, args_size=1
         0: iconst_2
         1: ireturn
      LineNumberTable:
        line 4: 0
      LocalVariableTable:
        Start  Length  Slot  Name   Signature
            0       2     0  this   Lcoursier/params/MirrorConfFile;

  public java.lang.Object productElement(int);
    descriptor: (I)Ljava/lang/Object;
    flags: (0x0001) ACC_PUBLIC
    Code:
      stack=3, locals=3, args_size=2
         0: iload_1
         1: istore_2
         2: iload_2
         3: tableswitch   { // 0 to 1
                       0: 24
                       1: 31
                 default: 41
            }
        24: aload_0
        25: invokevirtual #60                 // Method path:()Ljava/lang/String;
        28: goto          56
        31: aload_0
        32: invokevirtual #52                 // Method optional:()Z
        35: invokestatic  #124                // Method scala/runtime/BoxesRunTime.boxToBoolean:(Z)Ljava/lang/Boolean;
        38: goto          56
        41: new           #134                // class java/lang/IndexOutOfBoundsException
        44: dup
        45: iload_2
        46: invokestatic  #138                // Method scala/runtime/BoxesRunTime.boxToInteger:(I)Ljava/lang/Integer;
        49: invokevirtual #139                // Method java/lang/Object.toString:()Ljava/lang/String;
        52: invokespecial #140                // Method java/lang/IndexOutOfBoundsException."<init>":(Ljava/lang/String;)V
        55: athrow
        56: areturn
      StackMapTable: number_of_entries = 4
        frame_type = 252 /* append */
          offset_delta = 24
          locals = [ int ]
        frame_type = 6 /* same */
        frame_type = 9 /* same */
        frame_type = 78 /* same_locals_1_stack_item */
          stack = [ class java/lang/Object ]
      LineNumberTable:
        line 4: 0
      LocalVariableTable:
        Start  Length  Slot  Name   Signature
            0      57     0  this   Lcoursier/params/MirrorConfFile;
            0      57     1     n   I
    MethodParameters:
      Name                           Flags
      n                              final

  public java.lang.String productElementName(int);
    descriptor: (I)Ljava/lang/String;
    flags: (0x0001) ACC_PUBLIC
    Code:
      stack=3, locals=3, args_size=2
         0: iload_1
         1: istore_2
         2: iload_2
         3: tableswitch   { // 0 to 1
                       0: 24
                       1: 29
                 default: 34
            }
        24: ldc           #143                // String path
        26: goto          49
        29: ldc           #144                // String optional
        31: goto          49
        34: new           #134                // class java/lang/IndexOutOfBoundsException
        37: dup
        38: iload_2
        39: invokestatic  #138                // Method scala/runtime/BoxesRunTime.boxToInteger:(I)Ljava/lang/Integer;
        42: invokevirtual #139                // Method java/lang/Object.toString:()Ljava/lang/String;
        45: invokespecial #140                // Method java/lang/IndexOutOfBoundsException."<init>":(Ljava/lang/String;)V
        48: athrow
        49: areturn
      StackMapTable: number_of_entries = 4
        frame_type = 252 /* append */
          offset_delta = 24
          locals = [ int ]
        frame_type = 4 /* same */
        frame_type = 4 /* same */
        frame_type = 78 /* same_locals_1_stack_item */
          stack = [ class java/lang/String ]
      LineNumberTable:
        line 4: 0
      LocalVariableTable:
        Start  Length  Slot  Name   Signature
            0      50     0  this   Lcoursier/params/MirrorConfFile;
            0      50     1     n   I
    MethodParameters:
      Name                           Flags
      n                              final

  public coursier.params.MirrorConfFile(java.lang.String, boolean);
    descriptor: (Ljava/lang/String;Z)V
    flags: (0x0001) ACC_PUBLIC
    Code:
      stack=2, locals=3, args_size=3
         0: aload_0
         1: aload_1
         2: putfield      #46                 // Field path:Ljava/lang/String;
         5: aload_0
         6: iload_2
         7: putfield      #49                 // Field optional:Z
        10: aload_0
        11: invokespecial #147                // Method coursier/internal/PlatformMirrorConfFile."<init>":()V
        14: aload_0
        15: invokestatic  #151                // InterfaceMethod scala/Product.$init$:(Lscala/Product;)V
        18: return
      LineNumberTable:
        line 4: 0
        line 7: 10
        line 4: 18
      LocalVariableTable:
        Start  Length  Slot  Name   Signature
            0      19     0  this   Lcoursier/params/MirrorConfFile;
            0      19     1  path   Ljava/lang/String;
            0      19     2 optional   Z
    MethodParameters:
      Name                           Flags
      path                           final
      optional                       final

  public coursier.params.MirrorConfFile(java.lang.String);
    descriptor: (Ljava/lang/String;)V
    flags: (0x0001) ACC_PUBLIC
    Code:
      stack=3, locals=2, args_size=2
         0: aload_0
         1: aload_1
         2: iconst_1
         3: invokespecial #56                 // Method "<init>":(Ljava/lang/String;Z)V
         6: return
      LineNumberTable:
        line 4: 0
        line 6: 2
        line 4: 6
      LocalVariableTable:
        Start  Length  Slot  Name   Signature
            0       7     0  this   Lcoursier/params/MirrorConfFile;
            0       7     1  path   Ljava/lang/String;
    MethodParameters:
      Name                           Flags
      path                           final
}
SourceFile: "MirrorConfFile.scala"
RuntimeVisibleAnnotations:
  0: #10(#11=s#12)
    scala.reflect.ScalaSignature(
      bytes="\u0006\u0005\u0005-b\u0001\u0002\r\u001a\u0005yA\u0001b\u000e\u0001\u0003\u0006\u0004%\t\u0001\u000f\u0005\t\u0003\u0002\u0011\t\u0011)A\u0005s!A!\t\u0001BC\u0002\u0013\u00051\t\u0003\u0005H\u0001\t\u0005\t\u0015!\u0003E\u0011\u0015A\u0005\u0001\"\u0001J\u0011\u0015A\u0005\u0001\"\u0001O\u0011\u0015\u0001\u0006\u0001\"\u0001R\u0011\u0015\u0019\u0006\u0001\"\u0001U\u0011\u00151\u0006\u0001\"\u0011X\u0011\u0015y\u0006\u0001\"\u0011a\u0011\u00151\u0007\u0001\"\u0011h\u0011\u0015I\u0007\u0001\"\u0011k\u0011\u0015q\u0007\u0001\"\u0003p\u0011\u0015\u0019\b\u0001\"\u0011u\u0011\u0015)\b\u0001\"\u0011w\u0011\u00159\b\u0001\"\u0011y\u0011\u0015Y\b\u0001\"\u0011}\u000f\u0015q\u0018\u0004#\u0001\u0000\r\u0019A\u0012\u0004#\u0001\u0002\u0002!1\u0001j\u0005C\u0001\u0003\'Aq!!\u0006\u0014\t\u0003\t9\u0002C\u0004\u0002\u0016M!\t!a\u0007\t\u0013\u0005\u00052#!A\u0005\n\u0005\r\"AD\'jeJ|\'oQ8oM\u001aKG.\u001a\u0006\u00035m\ta\u0001]1sC6\u001c(\"\u0001\u000f\u0002\u0011\r|WO]:jKJ\u001c\u0001a\u0005\u0003\u0001?\u0015Z\u0003C\u0001\u0011$\u001b\u0005\t#B\u0001\u0012\u001c\u0003!Ig\u000e^3s]\u0006d\u0017B\u0001\u0013\"\u0005Y\u0001F.\u0019;g_JlW*\u001b:s_J\u001cuN\u001c4GS2,\u0007C\u0001\u0014*\u001b\u00059#\"\u0001\u0015\u0002\u000bM\u001c\u0017\r\\1\n\u0005):#a\u0002)s_\u0012,8\r\u001e\t\u0003YQr!!\f\u001a\u000f\u00059\nT\"A\u0018\u000b\u0005Aj\u0012A\u0002\u001fs_>$h(C\u0001)\u0013\t\u0019t%A\u0004qC\u000e\\\u0017mZ3\n\u0005U2$\u0001D*fe&\fG.\u001b>bE2,\'BA\u001a(\u0003\u0011\u0001\u0018\r\u001e5\u0016\u0003e\u0002\"A\u000f \u000f\u0005mb\u0004C\u0001\u0018(\u0013\tit%\u0001\u0004Qe\u0016$WMZ\u0005\u0003\u007f\u0001\u0013aa\u0015;sS:<\'BA\u001f(\u0003\u0015\u0001\u0018\r\u001e5!\u0003!y\u0007\u000f^5p]\u0006dW#\u0001#\u0011\u0005\u0019*\u0015B\u0001$(\u0005\u001d\u0011un\u001c7fC:\f\u0011b\u001c9uS>t\u0017\r\u001c\u0011\u0002\rqJg.\u001b;?)\rQE*\u0014\t\u0003\u0017\u0002i\u0011!\u0007\u0005\u0006o\u0015\u0001\r!\u000f\u0005\u0006\u0005\u0016\u0001\r\u0001\u0012\u000b\u0003\u0015>CQa\u000e\u0004A\u0002e\n\u0001b^5uQB\u000bG\u000f\u001b\u000b\u0003\u0015JCQaN\u0004A\u0002e\nAb^5uQ>\u0003H/[8oC2$\"AS+\t\u000b\tC\u0001\u0019\u0001#\u0002\u0011Q|7\u000b\u001e:j]\u001e$\u0012\u0001\u0017\t\u00033zk\u0011A\u0017\u0006\u00037r\u000bA\u0001\\1oO*\tQ,\u0001\u0003kCZ\f\u0017BA [\u0003!\u0019\u0017M\\#rk\u0006dGC\u0001#b\u0011\u0015\u0011\'\u00021\u0001d\u0003\ry\'M\u001b\t\u0003M\u0011L!!Z\u0014\u0003\u0007\u0005s\u00170\u0001\u0004fcV\fGn\u001d\u000b\u0003\t\"DQAY\u0006A\u0002\r\f\u0001\u0002[1tQ\u000e{G-\u001a\u000b\u0002WB\u0011a\u0005\\\u0005\u0003[\u001e\u00121!\u00138u\u0003\u0015!X\u000f\u001d7f+\u0005\u0001\b\u0003\u0002\u0014rs\u0011K!A]\u0014\u0003\rQ+\b\u000f\\33\u00035\u0001(o\u001c3vGR\u0004&/\u001a4jqV\t\u0001,\u0001\u0007qe>$Wo\u0019;Be&$\u00180F\u0001l\u00039\u0001(o\u001c3vGR,E.Z7f]R$\"aY=\t\u000bi\u0004\u0002\u0019A6\u0002\u00039\f!\u0003\u001d:pIV\u001cG/\u00127f[\u0016tGOT1nKR\u0011\u0001, \u0005\u0006uF\u0001\ra[\u0001\u000f\u001b&\u0014(o\u001c:D_:4g)\u001b7f!\tY5cE\u0003\u0014\u0003\u0007\tI\u0001E\u0002\'\u0003\u000bI1!a\u0002(\u0005\u0019\te.\u001f*fMB!\u00111BA\t\u001b\t\tiAC\u0002\u0002\u0010q\u000b!![8\n\u0007U\ni\u0001F\u0001\u0000\u0003\u0015\t\u0007\u000f\u001d7z)\rQ\u0015\u0011\u0004\u0005\u0006oU\u0001\r!\u000f\u000b\u0006\u0015\u0006u\u0011q\u0004\u0005\u0006oY\u0001\r!\u000f\u0005\u0006\u0005Z\u0001\r\u0001R\u0001\roJLG/\u001a*fa2\f7-\u001a\u000b\u0003\u0003K\u00012!WA\u0014\u0013\r\tIC\u0017\u0002\u0007\u001f\nTWm\u0019;"
    )
  ScalaInlineInfo: length = 0x59 (unknown attribute)
   01 01 00 11 00 35 00 42 01 00 35 00 36 01 00 5A
   00 5B 01 00 5E 00 5B 01 00 66 00 67 01 00 0F 00
   2F 01 00 0D 00 2C 01 00 81 00 67 01 00 82 00 83
   01 00 8D 00 8E 01 00 27 00 1F 01 00 1E 00 1F 01
   00 80 00 2C 01 00 3D 00 2C 01 00 72 00 73 01 00
   39 00 3A 01 00 32 00 1B 01
  ScalaSig: length = 0x3 (unknown attribute)
   05 02 00
