Classfile /Users/mw/Projects/slang-braindump/.jar/jar8/assemble/slang-braindump/assemble/content/shapeless/syntax/std/LowPriorityTuple.class
  Last modified May 29, 2022; size 1352 bytes
  SHA-256 checksum 08263284daa71ea8362190ba37980cfb136dce559d365c272fead4f9b1798e4c
  Compiled from "tuples.scala"
public interface shapeless.syntax.std.LowPriorityTuple
  minor version: 0
  major version: 52
  flags: (0x0601) ACC_PUBLIC, ACC_INTERFACE, ACC_ABSTRACT
  this_class: #2                          // shapeless/syntax/std/LowPriorityTuple
  super_class: #4                         // java/lang/Object
  interfaces: 0, fields: 0, methods: 3, attributes: 4
Constant pool:
   #1 = Utf8               shapeless/syntax/std/LowPriorityTuple
   #2 = Class              #1             // shapeless/syntax/std/LowPriorityTuple
   #3 = Utf8               java/lang/Object
   #4 = Class              #3             // java/lang/Object
   #5 = Utf8               tuples.scala
   #6 = Utf8               Lscala/reflect/ScalaSignature;
   #7 = Utf8               bytes
   #8 = Utf8               \u0006\u0005-2qa\u0001\u0003\u0011\u0002\u0007\u00051\u0002C\u0003\u0013\u0001\u0011\u00051\u0003C\u0003\u0018\u0001\u0011\r\u0001D\u0001\tM_^\u0004&/[8sSRLH+\u001e9mK*\u0011QAB\u0001\u0004gR$\'BA\u0004\t\u0003\u0019\u0019\u0018P\u001c;bq*\t\u0011\"A\u0005tQ\u0006\u0004X\r\\3tg\u000e\u00011C\u0001\u0001\r!\ti\u0001#D\u0001\u000f\u0015\u0005y\u0011!B:dC2\f\u0017BA\t\u000f\u0005\u0019\te.\u001f*fM\u00061A%\u001b8ji\u0012\"\u0012\u0001\u0006\t\u0003\u001bUI!A\u0006\b\u0003\tUs\u0017\u000e^\u0001\u0010aJ|G-^2u)V\u0004H.Z(qgV\u0011\u0011\u0004\t\u000b\u00035%\u00022a\u0007\u000f\u001f\u001b\u0005!\u0011BA\u000f\u0005\u0005!!V\u000f\u001d7f\u001fB\u001c\bCA\u0010!\u0019\u0001!Q!\t\u0002C\u0002\t\u0012\u0011\u0001U\t\u0003G\u0019\u0002\"!\u0004\u0013\n\u0005\u0015r!a\u0002(pi\"Lgn\u001a\t\u0003\u001b\u001dJ!\u0001\u000b\b\u0003\u000fA\u0013x\u000eZ;di\")!F\u0001a\u0001=\u0005\t\u0001\u000f
   #9 = Utf8               productTupleOps$
  #10 = Utf8               (Lshapeless/syntax/std/LowPriorityTuple;Lscala/Product;)Lshapeless/syntax/std/TupleOps;
  #11 = Utf8               $this
  #12 = Utf8               p
  #13 = Utf8               productTupleOps
  #14 = Utf8               (Lscala/Product;)Lshapeless/syntax/std/TupleOps;
  #15 = NameAndType        #13:#14        // productTupleOps:(Lscala/Product;)Lshapeless/syntax/std/TupleOps;
  #16 = InterfaceMethodref #2.#15         // shapeless/syntax/std/LowPriorityTuple.productTupleOps:(Lscala/Product;)Lshapeless/syntax/std/TupleOps;
  #17 = Utf8               Lshapeless/syntax/std/LowPriorityTuple;
  #18 = Utf8               Lscala/Product;
  #19 = Utf8               <P::Lscala/Product;>(TP;)Lshapeless/syntax/std/TupleOps<TP;>;
  #20 = Utf8               shapeless/syntax/std/TupleOps
  #21 = Class              #20            // shapeless/syntax/std/TupleOps
  #22 = Utf8               <init>
  #23 = Utf8               (Ljava/lang/Object;)V
  #24 = NameAndType        #22:#23        // "<init>":(Ljava/lang/Object;)V
  #25 = Methodref          #21.#24        // shapeless/syntax/std/TupleOps."<init>":(Ljava/lang/Object;)V
  #26 = Utf8               this
  #27 = Utf8               $init$
  #28 = Utf8               (Lshapeless/syntax/std/LowPriorityTuple;)V
  #29 = Utf8               Code
  #30 = Utf8               LineNumberTable
  #31 = Utf8               LocalVariableTable
  #32 = Utf8               MethodParameters
  #33 = Utf8               Signature
  #34 = Utf8               SourceFile
  #35 = Utf8               RuntimeVisibleAnnotations
  #36 = Utf8               ScalaInlineInfo
  #37 = Utf8               ScalaSig
{
  public static shapeless.syntax.std.TupleOps productTupleOps$(shapeless.syntax.std.LowPriorityTuple, scala.Product);
    descriptor: (Lshapeless/syntax/std/LowPriorityTuple;Lscala/Product;)Lshapeless/syntax/std/TupleOps;
    flags: (0x1009) ACC_PUBLIC, ACC_STATIC, ACC_SYNTHETIC
    Code:
      stack=2, locals=2, args_size=2
         0: aload_0
         1: aload_1
         2: invokespecial #16                 // InterfaceMethod productTupleOps:(Lscala/Product;)Lshapeless/syntax/std/TupleOps;
         5: areturn
      LineNumberTable:
        line 22: 0
      LocalVariableTable:
        Start  Length  Slot  Name   Signature
            0       6     0 $this   Lshapeless/syntax/std/LowPriorityTuple;
            0       6     1     p   Lscala/Product;
    MethodParameters:
      Name                           Flags
      $this                          final synthetic
      p                              final

  public default <P extends scala.Product> shapeless.syntax.std.TupleOps<P> productTupleOps(P);
    descriptor: (Lscala/Product;)Lshapeless/syntax/std/TupleOps;
    flags: (0x0001) ACC_PUBLIC
    Code:
      stack=3, locals=2, args_size=2
         0: new           #21                 // class shapeless/syntax/std/TupleOps
         3: dup
         4: aload_1
         5: invokespecial #25                 // Method shapeless/syntax/std/TupleOps."<init>":(Ljava/lang/Object;)V
         8: areturn
      LineNumberTable:
        line 22: 0
      LocalVariableTable:
        Start  Length  Slot  Name   Signature
            0       9     0  this   Lshapeless/syntax/std/LowPriorityTuple;
            0       9     1     p   Lscala/Product;
    Signature: #19                          // <P::Lscala/Product;>(TP;)Lshapeless/syntax/std/TupleOps<TP;>;
    MethodParameters:
      Name                           Flags
      p                              final

  public static void $init$(shapeless.syntax.std.LowPriorityTuple);
    descriptor: (Lshapeless/syntax/std/LowPriorityTuple;)V
    flags: (0x0009) ACC_PUBLIC, ACC_STATIC
    Code:
      stack=0, locals=1, args_size=1
         0: return
      LineNumberTable:
        line 21: 0
      LocalVariableTable:
        Start  Length  Slot  Name   Signature
            0       1     0 $this   Lshapeless/syntax/std/LowPriorityTuple;
    MethodParameters:
      Name                           Flags
      $this                          final synthetic
}
SourceFile: "tuples.scala"
RuntimeVisibleAnnotations:
  0: #6(#7=s#8)
    scala.reflect.ScalaSignature(
      bytes="\u0006\u0005-2qa\u0001\u0003\u0011\u0002\u0007\u00051\u0002C\u0003\u0013\u0001\u0011\u00051\u0003C\u0003\u0018\u0001\u0011\r\u0001D\u0001\tM_^\u0004&/[8sSRLH+\u001e9mK*\u0011QAB\u0001\u0004gR$\'BA\u0004\t\u0003\u0019\u0019\u0018P\u001c;bq*\t\u0011\"A\u0005tQ\u0006\u0004X\r\\3tg\u000e\u00011C\u0001\u0001\r!\ti\u0001#D\u0001\u000f\u0015\u0005y\u0011!B:dC2\f\u0017BA\t\u000f\u0005\u0019\te.\u001f*fM\u00061A%\u001b8ji\u0012\"\u0012\u0001\u0006\t\u0003\u001bUI!A\u0006\b\u0003\tUs\u0017\u000e^\u0001\u0010aJ|G-^2u)V\u0004H.Z(qgV\u0011\u0011\u0004\t\u000b\u00035%\u00022a\u0007\u000f\u001f\u001b\u0005!\u0011BA\u000f\u0005\u0005!!V\u000f\u001d7f\u001fB\u001c\bCA\u0010!\u0019\u0001!Q!\t\u0002C\u0002\t\u0012\u0011\u0001U\t\u0003G\u0019\u0002\"!\u0004\u0013\n\u0005\u0015r!a\u0002(pi\"Lgn\u001a\t\u0003\u001b\u001dJ!\u0001\u000b\b\u0003\u000fA\u0013x\u000eZ;di\")!F\u0001a\u0001=\u0005\t\u0001\u000f"
    )
  ScalaInlineInfo: length = 0x13 (unknown attribute)
   01 00 00 03 00 1B 00 1C 01 00 09 00 0A 01 00 0D
   00 0E 00
  ScalaSig: length = 0x3 (unknown attribute)
   05 02 00
