Classfile /Users/mw/Projects/slang-braindump/.jar/jar8/assemble/slang-braindump/assemble/content/shapeless/syntax/std/tuple$.class
  Last modified May 29, 2022; size 1615 bytes
  SHA-256 checksum b7d141f688d2baa2d8833ab946f01d01e48235fe9d8a949b48e3c29354d10f97
  Compiled from "tuples.scala"
public final class shapeless.syntax.std.tuple$ implements shapeless.syntax.std.LowPriorityTuple
  minor version: 0
  major version: 52
  flags: (0x0031) ACC_PUBLIC, ACC_FINAL, ACC_SUPER
  this_class: #2                          // shapeless/syntax/std/tuple$
  super_class: #4                         // java/lang/Object
  interfaces: 1, fields: 1, methods: 5, attributes: 3
Constant pool:
   #1 = Utf8               shapeless/syntax/std/tuple$
   #2 = Class              #1             // shapeless/syntax/std/tuple$
   #3 = Utf8               java/lang/Object
   #4 = Class              #3             // java/lang/Object
   #5 = Utf8               shapeless/syntax/std/LowPriorityTuple
   #6 = Class              #5             // shapeless/syntax/std/LowPriorityTuple
   #7 = Utf8               tuples.scala
   #8 = Utf8               MODULE$
   #9 = Utf8               Lshapeless/syntax/std/tuple$;
  #10 = Utf8               <clinit>
  #11 = Utf8               ()V
  #12 = Utf8               <init>
  #13 = NameAndType        #12:#11        // "<init>":()V
  #14 = Methodref          #2.#13         // shapeless/syntax/std/tuple$."<init>":()V
  #15 = NameAndType        #8:#9          // MODULE$:Lshapeless/syntax/std/tuple$;
  #16 = Fieldref           #2.#15         // shapeless/syntax/std/tuple$.MODULE$:Lshapeless/syntax/std/tuple$;
  #17 = Utf8               $init$
  #18 = Utf8               (Lshapeless/syntax/std/LowPriorityTuple;)V
  #19 = NameAndType        #17:#18        // $init$:(Lshapeless/syntax/std/LowPriorityTuple;)V
  #20 = InterfaceMethodref #6.#19         // shapeless/syntax/std/LowPriorityTuple.$init$:(Lshapeless/syntax/std/LowPriorityTuple;)V
  #21 = Utf8               productTupleOps
  #22 = Utf8               (Lscala/Product;)Lshapeless/syntax/std/TupleOps;
  #23 = Utf8               <P::Lscala/Product;>(TP;)Lshapeless/syntax/std/TupleOps<TP;>;
  #24 = Utf8               p
  #25 = Utf8               productTupleOps$
  #26 = Utf8               (Lshapeless/syntax/std/LowPriorityTuple;Lscala/Product;)Lshapeless/syntax/std/TupleOps;
  #27 = NameAndType        #25:#26        // productTupleOps$:(Lshapeless/syntax/std/LowPriorityTuple;Lscala/Product;)Lshapeless/syntax/std/TupleOps;
  #28 = InterfaceMethodref #6.#27         // shapeless/syntax/std/LowPriorityTuple.productTupleOps$:(Lshapeless/syntax/std/LowPriorityTuple;Lscala/Product;)Lshapeless/syntax/std/TupleOps;
  #29 = Utf8               this
  #30 = Utf8               Lscala/Product;
  #31 = Utf8               unitTupleOps
  #32 = Utf8               (Lscala/runtime/BoxedUnit;)Lshapeless/syntax/std/TupleOps;
  #33 = Utf8               (Lscala/runtime/BoxedUnit;)Lshapeless/syntax/std/TupleOps<Lscala/runtime/BoxedUnit;>;
  #34 = Utf8               u
  #35 = Utf8               shapeless/syntax/std/TupleOps
  #36 = Class              #35            // shapeless/syntax/std/TupleOps
  #37 = Utf8               (Ljava/lang/Object;)V
  #38 = NameAndType        #12:#37        // "<init>":(Ljava/lang/Object;)V
  #39 = Methodref          #36.#38        // shapeless/syntax/std/TupleOps."<init>":(Ljava/lang/Object;)V
  #40 = Utf8               Lscala/runtime/BoxedUnit;
  #41 = Utf8               hlistOps
  #42 = Utf8               (Lshapeless/HList;)Lshapeless/syntax/HListOps;
  #43 = Utf8               <L::Lshapeless/HList;>(TL;)Lshapeless/syntax/HListOps<TL;>;
  #44 = Utf8               l
  #45 = Utf8               shapeless/syntax/HListOps
  #46 = Class              #45            // shapeless/syntax/HListOps
  #47 = Utf8               (Lshapeless/HList;)V
  #48 = NameAndType        #12:#47        // "<init>":(Lshapeless/HList;)V
  #49 = Methodref          #46.#48        // shapeless/syntax/HListOps."<init>":(Lshapeless/HList;)V
  #50 = Utf8               Lshapeless/HList;
  #51 = Methodref          #4.#13         // java/lang/Object."<init>":()V
  #52 = Utf8               Code
  #53 = Utf8               LineNumberTable
  #54 = Utf8               LocalVariableTable
  #55 = Utf8               Signature
  #56 = Utf8               MethodParameters
  #57 = Utf8               SourceFile
  #58 = Utf8               ScalaInlineInfo
  #59 = Utf8               Scala
{
  public static final shapeless.syntax.std.tuple$ MODULE$;
    descriptor: Lshapeless/syntax/std/tuple$;
    flags: (0x0019) ACC_PUBLIC, ACC_STATIC, ACC_FINAL

  public static {};
    descriptor: ()V
    flags: (0x0009) ACC_PUBLIC, ACC_STATIC
    Code:
      stack=2, locals=0, args_size=0
         0: new           #2                  // class shapeless/syntax/std/tuple$
         3: dup
         4: invokespecial #14                 // Method "<init>":()V
         7: putstatic     #16                 // Field MODULE$:Lshapeless/syntax/std/tuple$;
        10: getstatic     #16                 // Field MODULE$:Lshapeless/syntax/std/tuple$;
        13: invokestatic  #20                 // InterfaceMethod shapeless/syntax/std/LowPriorityTuple.$init$:(Lshapeless/syntax/std/LowPriorityTuple;)V
        16: return
      LineNumberTable:
        line 25: 0

  public <P extends scala.Product> shapeless.syntax.std.TupleOps<P> productTupleOps(P);
    descriptor: (Lscala/Product;)Lshapeless/syntax/std/TupleOps;
    flags: (0x0001) ACC_PUBLIC
    Code:
      stack=2, locals=2, args_size=2
         0: aload_0
         1: aload_1
         2: invokestatic  #28                 // InterfaceMethod shapeless/syntax/std/LowPriorityTuple.productTupleOps$:(Lshapeless/syntax/std/LowPriorityTuple;Lscala/Product;)Lshapeless/syntax/std/TupleOps;
         5: areturn
      LineNumberTable:
        line 25: 0
      LocalVariableTable:
        Start  Length  Slot  Name   Signature
            0       6     0  this   Lshapeless/syntax/std/tuple$;
            0       6     1     p   Lscala/Product;
    Signature: #23                          // <P::Lscala/Product;>(TP;)Lshapeless/syntax/std/TupleOps<TP;>;
    MethodParameters:
      Name                           Flags
      p                              final

  public shapeless.syntax.std.TupleOps<scala.runtime.BoxedUnit> unitTupleOps(scala.runtime.BoxedUnit);
    descriptor: (Lscala/runtime/BoxedUnit;)Lshapeless/syntax/std/TupleOps;
    flags: (0x0001) ACC_PUBLIC
    Code:
      stack=3, locals=2, args_size=2
         0: new           #36                 // class shapeless/syntax/std/TupleOps
         3: dup
         4: aload_1
         5: invokespecial #39                 // Method shapeless/syntax/std/TupleOps."<init>":(Ljava/lang/Object;)V
         8: areturn
      LineNumberTable:
        line 26: 0
      LocalVariableTable:
        Start  Length  Slot  Name   Signature
            0       9     0  this   Lshapeless/syntax/std/tuple$;
            0       9     1     u   Lscala/runtime/BoxedUnit;
    Signature: #33                          // (Lscala/runtime/BoxedUnit;)Lshapeless/syntax/std/TupleOps<Lscala/runtime/BoxedUnit;>;
    MethodParameters:
      Name                           Flags
      u                              final

  public <L extends shapeless.HList> shapeless.syntax.HListOps<L> hlistOps(L);
    descriptor: (Lshapeless/HList;)Lshapeless/syntax/HListOps;
    flags: (0x0001) ACC_PUBLIC
    Code:
      stack=3, locals=2, args_size=2
         0: new           #46                 // class shapeless/syntax/HListOps
         3: dup
         4: aload_1
         5: invokespecial #49                 // Method shapeless/syntax/HListOps."<init>":(Lshapeless/HList;)V
         8: areturn
      LineNumberTable:
        line 30: 0
      LocalVariableTable:
        Start  Length  Slot  Name   Signature
            0       9     0  this   Lshapeless/syntax/std/tuple$;
            0       9     1     l   Lshapeless/HList;
    Signature: #43                          // <L::Lshapeless/HList;>(TL;)Lshapeless/syntax/HListOps<TL;>;
    MethodParameters:
      Name                           Flags
      l                              final

  private shapeless.syntax.std.tuple$();
    descriptor: ()V
    flags: (0x0002) ACC_PRIVATE
    Code:
      stack=1, locals=1, args_size=1
         0: aload_0
         1: invokespecial #51                 // Method java/lang/Object."<init>":()V
         4: return
      LineNumberTable:
        line 25: 0
      LocalVariableTable:
        Start  Length  Slot  Name   Signature
            0       5     0  this   Lshapeless/syntax/std/tuple$;
}
SourceFile: "tuples.scala"
  ScalaInlineInfo: length = 0x18 (unknown attribute)
   01 01 00 04 00 0C 00 0B 01 00 29 00 2A 01 00 15
   00 16 01 00 1F 00 20 01
  Scala: length = 0x0 (unknown attribute)

