Classfile /Users/mw/Projects/slang-braindump/.jar/jar8/assemble/slang-braindump/assemble/content/org/scalatest/tagobjects/FirefoxBrowser$.class
  Last modified May 29, 2022; size 531 bytes
  SHA-256 checksum bec60840c7e00f3b072f5745ea8abf00a8ec235aecd385b115dd2946d820740e
  Compiled from "FirefoxBrowser.scala"
public final class org.scalatest.tagobjects.FirefoxBrowser$ extends org.scalatest.Tag
  minor version: 0
  major version: 52
  flags: (0x0031) ACC_PUBLIC, ACC_FINAL, ACC_SUPER
  this_class: #2                          // org/scalatest/tagobjects/FirefoxBrowser$
  super_class: #4                         // org/scalatest/Tag
  interfaces: 0, fields: 1, methods: 2, attributes: 3
Constant pool:
   #1 = Utf8               org/scalatest/tagobjects/FirefoxBrowser$
   #2 = Class              #1             // org/scalatest/tagobjects/FirefoxBrowser$
   #3 = Utf8               org/scalatest/Tag
   #4 = Class              #3             // org/scalatest/Tag
   #5 = Utf8               FirefoxBrowser.scala
   #6 = Utf8               MODULE$
   #7 = Utf8               Lorg/scalatest/tagobjects/FirefoxBrowser$;
   #8 = Utf8               <clinit>
   #9 = Utf8               ()V
  #10 = Utf8               <init>
  #11 = NameAndType        #10:#9         // "<init>":()V
  #12 = Methodref          #2.#11         // org/scalatest/tagobjects/FirefoxBrowser$."<init>":()V
  #13 = NameAndType        #6:#7          // MODULE$:Lorg/scalatest/tagobjects/FirefoxBrowser$;
  #14 = Fieldref           #2.#13         // org/scalatest/tagobjects/FirefoxBrowser$.MODULE$:Lorg/scalatest/tagobjects/FirefoxBrowser$;
  #15 = Utf8               org.scalatest.tags.FirefoxBrowser
  #16 = String             #15            // org.scalatest.tags.FirefoxBrowser
  #17 = Utf8               (Ljava/lang/String;)V
  #18 = NameAndType        #10:#17        // "<init>":(Ljava/lang/String;)V
  #19 = Methodref          #4.#18         // org/scalatest/Tag."<init>":(Ljava/lang/String;)V
  #20 = Utf8               this
  #21 = Utf8               Code
  #22 = Utf8               LineNumberTable
  #23 = Utf8               LocalVariableTable
  #24 = Utf8               SourceFile
  #25 = Utf8               ScalaInlineInfo
  #26 = Utf8               Scala
{
  public static final org.scalatest.tagobjects.FirefoxBrowser$ MODULE$;
    descriptor: Lorg/scalatest/tagobjects/FirefoxBrowser$;
    flags: (0x0019) ACC_PUBLIC, ACC_STATIC, ACC_FINAL

  public static {};
    descriptor: ()V
    flags: (0x0009) ACC_PUBLIC, ACC_STATIC
    Code:
      stack=2, locals=0, args_size=0
         0: new           #2                  // class org/scalatest/tagobjects/FirefoxBrowser$
         3: dup
         4: invokespecial #12                 // Method "<init>":()V
         7: putstatic     #14                 // Field MODULE$:Lorg/scalatest/tagobjects/FirefoxBrowser$;
        10: return
      LineNumberTable:
        line 23: 0

  private org.scalatest.tagobjects.FirefoxBrowser$();
    descriptor: ()V
    flags: (0x0002) ACC_PRIVATE
    Code:
      stack=2, locals=1, args_size=1
         0: aload_0
         1: ldc           #16                 // String org.scalatest.tags.FirefoxBrowser
         3: invokespecial #19                 // Method org/scalatest/Tag."<init>":(Ljava/lang/String;)V
         6: return
      LineNumberTable:
        line 23: 0
      LocalVariableTable:
        Start  Length  Slot  Name   Signature
            0       7     0  this   Lorg/scalatest/tagobjects/FirefoxBrowser$;
}
SourceFile: "FirefoxBrowser.scala"
  ScalaInlineInfo: length = 0x9 (unknown attribute)
   01 01 00 01 00 0A 00 09 01
  Scala: length = 0x0 (unknown attribute)

