Classfile /Users/mw/Projects/slang-braindump/.jar/jar8/assemble/slang-braindump/assemble/content/org/scalatest/tagobjects/InternetExplorerBrowser.class
  Last modified May 29, 2022; size 646 bytes
  SHA-256 checksum 7e2e9684c9ff62fecf6b80bedc62055890ea6704a6a618758d177225804c2477
  Compiled from "InternetExplorerBrowser.scala"
public final class org.scalatest.tagobjects.InternetExplorerBrowser
  minor version: 0
  major version: 52
  flags: (0x0031) ACC_PUBLIC, ACC_FINAL, ACC_SUPER
  this_class: #2                          // org/scalatest/tagobjects/InternetExplorerBrowser
  super_class: #4                         // java/lang/Object
  interfaces: 0, fields: 0, methods: 1, attributes: 3
Constant pool:
   #1 = Utf8               org/scalatest/tagobjects/InternetExplorerBrowser
   #2 = Class              #1             // org/scalatest/tagobjects/InternetExplorerBrowser
   #3 = Utf8               java/lang/Object
   #4 = Class              #3             // java/lang/Object
   #5 = Utf8               InternetExplorerBrowser.scala
   #6 = Utf8               Lscala/reflect/ScalaSignature;
   #7 = Utf8               bytes
   #8 = Utf8               \u0006\u0005U9Qa\u0001\u0003\t\u0002-1Q!\u0004\u0003\t\u00029AQaE\u0001\u0005\u0002Q\tq#\u00138uKJtW\r^#ya2|\'/\u001a:Ce><8/\u001a:\u000b\u0005\u00151\u0011A\u0003;bO>\u0014\'.Z2ug*\u0011q\u0001C\u0001\ng\u000e\fG.\u0019;fgRT\u0011!C\u0001\u0004_J<7\u0001\u0001\t\u0003\u0019\u0005i\u0011\u0001\u0002\u0002\u0018\u0013:$XM\u001d8fi\u0016C\b\u000f\\8sKJ\u0014%o\\<tKJ\u001c\"!A\b\u0011\u0005A\tR\"\u0001\u0004\n\u0005I1!a\u0001+bO\u00061A(\u001b8jiz\"\u0012a\u0003
   #9 = Utf8               name
  #10 = Utf8               ()Ljava/lang/String;
  #11 = Utf8               org/scalatest/tagobjects/InternetExplorerBrowser$
  #12 = Class              #11            // org/scalatest/tagobjects/InternetExplorerBrowser$
  #13 = Utf8               MODULE$
  #14 = Utf8               Lorg/scalatest/tagobjects/InternetExplorerBrowser$;
  #15 = NameAndType        #13:#14        // MODULE$:Lorg/scalatest/tagobjects/InternetExplorerBrowser$;
  #16 = Fieldref           #12.#15        // org/scalatest/tagobjects/InternetExplorerBrowser$.MODULE$:Lorg/scalatest/tagobjects/InternetExplorerBrowser$;
  #17 = NameAndType        #9:#10         // name:()Ljava/lang/String;
  #18 = Methodref          #12.#17        // org/scalatest/tagobjects/InternetExplorerBrowser$.name:()Ljava/lang/String;
  #19 = Utf8               Code
  #20 = Utf8               SourceFile
  #21 = Utf8               RuntimeVisibleAnnotations
  #22 = Utf8               ScalaSig
{
  public static java.lang.String name();
    descriptor: ()Ljava/lang/String;
    flags: (0x0009) ACC_PUBLIC, ACC_STATIC
    Code:
      stack=1, locals=0, args_size=0
         0: getstatic     #16                 // Field org/scalatest/tagobjects/InternetExplorerBrowser$.MODULE$:Lorg/scalatest/tagobjects/InternetExplorerBrowser$;
         3: invokevirtual #18                 // Method org/scalatest/tagobjects/InternetExplorerBrowser$.name:()Ljava/lang/String;
         6: areturn
}
SourceFile: "InternetExplorerBrowser.scala"
RuntimeVisibleAnnotations:
  0: #6(#7=s#8)
    scala.reflect.ScalaSignature(
      bytes="\u0006\u0005U9Qa\u0001\u0003\t\u0002-1Q!\u0004\u0003\t\u00029AQaE\u0001\u0005\u0002Q\tq#\u00138uKJtW\r^#ya2|\'/\u001a:Ce><8/\u001a:\u000b\u0005\u00151\u0011A\u0003;bO>\u0014\'.Z2ug*\u0011q\u0001C\u0001\ng\u000e\fG.\u0019;fgRT\u0011!C\u0001\u0004_J<7\u0001\u0001\t\u0003\u0019\u0005i\u0011\u0001\u0002\u0002\u0018\u0013:$XM\u001d8fi\u0016C\b\u000f\\8sKJ\u0014%o\\<tKJ\u001c\"!A\b\u0011\u0005A\tR\"\u0001\u0004\n\u0005I1!a\u0001+bO\u00061A(\u001b8jiz\"\u0012a\u0003"
    )
  ScalaSig: length = 0x3 (unknown attribute)
   05 02 00
