Classfile /Users/mw/Projects/slang-braindump/.jar/jar11/assemble/slang-braindump/assemble/content/scala/collection/convert/AsScalaExtensions$PropertiesHasAsScala.class
  Last modified May 29, 2022; size 1484 bytes
  SHA-256 checksum 5c2c4a420cf1070f541c5fab027b69eec8be7149f093cfbdae554bff2f4719ef
  Compiled from "AsScalaExtensions.scala"
public class scala.collection.convert.AsScalaExtensions$PropertiesHasAsScala
  minor version: 0
  major version: 52
  flags: (0x0021) ACC_PUBLIC, ACC_SUPER
  this_class: #2                          // scala/collection/convert/AsScalaExtensions$PropertiesHasAsScala
  super_class: #4                         // java/lang/Object
  interfaces: 0, fields: 2, methods: 3, attributes: 4
Constant pool:
   #1 = Utf8               scala/collection/convert/AsScalaExtensions$PropertiesHasAsScala
   #2 = Class              #1             // scala/collection/convert/AsScalaExtensions$PropertiesHasAsScala
   #3 = Utf8               java/lang/Object
   #4 = Class              #3             // java/lang/Object
   #5 = Utf8               AsScalaExtensions.scala
   #6 = Utf8               scala/collection/convert/AsScalaExtensions
   #7 = Class              #6             // scala/collection/convert/AsScalaExtensions
   #8 = Utf8               PropertiesHasAsScala
   #9 = Utf8               i
  #10 = Utf8               Ljava/util/Properties;
  #11 = Utf8               $outer
  #12 = Utf8               Lscala/collection/convert/AsScalaExtensions;
  #13 = Utf8               asScala
  #14 = Utf8               ()Lscala/collection/mutable/Map;
  #15 = Utf8               ()Lscala/collection/mutable/Map<Ljava/lang/String;Ljava/lang/String;>;
  #16 = Utf8               scala/jdk/javaapi/CollectionConverters$
  #17 = Class              #16            // scala/jdk/javaapi/CollectionConverters$
  #18 = Utf8               MODULE$
  #19 = Utf8               Lscala/jdk/javaapi/CollectionConverters$;
  #20 = NameAndType        #18:#19        // MODULE$:Lscala/jdk/javaapi/CollectionConverters$;
  #21 = Fieldref           #17.#20        // scala/jdk/javaapi/CollectionConverters$.MODULE$:Lscala/jdk/javaapi/CollectionConverters$;
  #22 = NameAndType        #9:#10         // i:Ljava/util/Properties;
  #23 = Fieldref           #2.#22         // scala/collection/convert/AsScalaExtensions$PropertiesHasAsScala.i:Ljava/util/Properties;
  #24 = Utf8               scala/collection/convert/AsScalaConverters
  #25 = Class              #24            // scala/collection/convert/AsScalaConverters
  #26 = Utf8               asScala$
  #27 = Utf8               (Lscala/collection/convert/AsScalaConverters;Ljava/util/Properties;)Lscala/collection/mutable/Map;
  #28 = NameAndType        #26:#27        // asScala$:(Lscala/collection/convert/AsScalaConverters;Ljava/util/Properties;)Lscala/collection/mutable/Map;
  #29 = InterfaceMethodref #25.#28        // scala/collection/convert/AsScalaConverters.asScala$:(Lscala/collection/convert/AsScalaConverters;Ljava/util/Properties;)Lscala/collection/mutable/Map;
  #30 = Utf8               this
  #31 = Utf8               Lscala/collection/convert/AsScalaExtensions$PropertiesHasAsScala;
  #32 = Utf8               scala$collection$convert$AsScalaExtensions$PropertiesHasAsScala$$$outer
  #33 = Utf8               ()Lscala/collection/convert/AsScalaExtensions;
  #34 = NameAndType        #11:#12        // $outer:Lscala/collection/convert/AsScalaExtensions;
  #35 = Fieldref           #2.#34         // scala/collection/convert/AsScalaExtensions$PropertiesHasAsScala.$outer:Lscala/collection/convert/AsScalaExtensions;
  #36 = Utf8               <init>
  #37 = Utf8               (Lscala/collection/convert/AsScalaExtensions;Ljava/util/Properties;)V
  #38 = Utf8               ()V
  #39 = NameAndType        #36:#38        // "<init>":()V
  #40 = Methodref          #4.#39         // java/lang/Object."<init>":()V
  #41 = Utf8               Code
  #42 = Utf8               LineNumberTable
  #43 = Utf8               LocalVariableTable
  #44 = Utf8               Signature
  #45 = Utf8               StackMapTable
  #46 = Utf8               MethodParameters
  #47 = Utf8               InnerClasses
  #48 = Utf8               SourceFile
  #49 = Utf8               ScalaInlineInfo
  #50 = Utf8               Scala
{
  private final java.util.Properties i;
    descriptor: Ljava/util/Properties;
    flags: (0x0012) ACC_PRIVATE, ACC_FINAL

  public final scala.collection.convert.AsScalaExtensions $outer;
    descriptor: Lscala/collection/convert/AsScalaExtensions;
    flags: (0x1011) ACC_PUBLIC, ACC_FINAL, ACC_SYNTHETIC

  public scala.collection.mutable.Map<java.lang.String, java.lang.String> asScala();
    descriptor: ()Lscala/collection/mutable/Map;
    flags: (0x0001) ACC_PUBLIC
    Code:
      stack=2, locals=1, args_size=1
         0: getstatic     #21                 // Field scala/jdk/javaapi/CollectionConverters$.MODULE$:Lscala/jdk/javaapi/CollectionConverters$;
         3: aload_0
         4: getfield      #23                 // Field i:Ljava/util/Properties;
         7: invokestatic  #29                 // InterfaceMethod scala/collection/convert/AsScalaConverters.asScala$:(Lscala/collection/convert/AsScalaConverters;Ljava/util/Properties;)Lscala/collection/mutable/Map;
        10: areturn
      LineNumberTable:
        line 91: 0
      LocalVariableTable:
        Start  Length  Slot  Name   Signature
            0      11     0  this   Lscala/collection/convert/AsScalaExtensions$PropertiesHasAsScala;
    Signature: #15                          // ()Lscala/collection/mutable/Map<Ljava/lang/String;Ljava/lang/String;>;

  public scala.collection.convert.AsScalaExtensions scala$collection$convert$AsScalaExtensions$PropertiesHasAsScala$$$outer();
    descriptor: ()Lscala/collection/convert/AsScalaExtensions;
    flags: (0x1001) ACC_PUBLIC, ACC_SYNTHETIC
    Code:
      stack=1, locals=1, args_size=1
         0: aload_0
         1: getfield      #35                 // Field $outer:Lscala/collection/convert/AsScalaExtensions;
         4: areturn
      LineNumberTable:
        line 87: 0
      LocalVariableTable:
        Start  Length  Slot  Name   Signature
            0       5     0  this   Lscala/collection/convert/AsScalaExtensions$PropertiesHasAsScala;

  public scala.collection.convert.AsScalaExtensions$PropertiesHasAsScala(scala.collection.convert.AsScalaExtensions, java.util.Properties);
    descriptor: (Lscala/collection/convert/AsScalaExtensions;Ljava/util/Properties;)V
    flags: (0x0001) ACC_PUBLIC
    Code:
      stack=2, locals=3, args_size=3
         0: aload_0
         1: aload_2
         2: putfield      #23                 // Field i:Ljava/util/Properties;
         5: aload_1
         6: ifnonnull     11
         9: aconst_null
        10: athrow
        11: aload_0
        12: aload_1
        13: putfield      #35                 // Field $outer:Lscala/collection/convert/AsScalaExtensions;
        16: aload_0
        17: invokespecial #40                 // Method java/lang/Object."<init>":()V
        20: return
      StackMapTable: number_of_entries = 1
        frame_type = 11 /* same */
      LineNumberTable:
        line 87: 0
      LocalVariableTable:
        Start  Length  Slot  Name   Signature
            0      21     0  this   Lscala/collection/convert/AsScalaExtensions$PropertiesHasAsScala;
            0      21     1 $outer   Lscala/collection/convert/AsScalaExtensions;
            0      21     2     i   Ljava/util/Properties;
    MethodParameters:
      Name                           Flags
      $outer                         final synthetic
      i                              final
}
InnerClasses:
  public #8= #2 of #7;                    // PropertiesHasAsScala=class scala/collection/convert/AsScalaExtensions$PropertiesHasAsScala of class scala/collection/convert/AsScalaExtensions
SourceFile: "AsScalaExtensions.scala"
  ScalaInlineInfo: length = 0x13 (unknown attribute)
   01 00 00 03 00 24 00 25 00 00 0D 00 0E 00 00 20
   00 21 00
  Scala: length = 0x0 (unknown attribute)

