Classfile /Users/mw/Projects/slang-braindump/.jar/jar11/assemble/slang-braindump/assemble/content/scala/collection/convert/JavaCollectionWrappers$JMapWrapperLike$$anon$5.class
  Last modified May 29, 2022; size 1986 bytes
  SHA-256 checksum 1cdf3e799bddf37b626a2881689f3493ff5a2392c5f6ef6a060e7afe40672d8f
  Compiled from "JavaCollectionWrappers.scala"
public final class scala.collection.convert.JavaCollectionWrappers$JMapWrapperLike$$anon$5 extends scala.collection.AbstractIterator<scala.Tuple2<K, V>>
  minor version: 0
  major version: 52
  flags: (0x0031) ACC_PUBLIC, ACC_FINAL, ACC_SUPER
  this_class: #2                          // scala/collection/convert/JavaCollectionWrappers$JMapWrapperLike$$anon$5
  super_class: #5                         // scala/collection/AbstractIterator
  interfaces: 0, fields: 1, methods: 5, attributes: 6
Constant pool:
   #1 = Utf8               scala/collection/convert/JavaCollectionWrappers$JMapWrapperLike$$anon$5
   #2 = Class              #1             // scala/collection/convert/JavaCollectionWrappers$JMapWrapperLike$$anon$5
   #3 = Utf8               Lscala/collection/AbstractIterator<Lscala/Tuple2<TK;TV;>;>;
   #4 = Utf8               scala/collection/AbstractIterator
   #5 = Class              #4             // scala/collection/AbstractIterator
   #6 = Utf8               JavaCollectionWrappers.scala
   #7 = Utf8               scala/collection/convert/JavaCollectionWrappers$JMapWrapperLike
   #8 = Class              #7             // scala/collection/convert/JavaCollectionWrappers$JMapWrapperLike
   #9 = Utf8               iterator
  #10 = Utf8               ()Lscala/collection/Iterator;
  #11 = NameAndType        #9:#10         // iterator:()Lscala/collection/Iterator;
  #12 = Utf8               java/util/Map$Entry
  #13 = Class              #12            // java/util/Map$Entry
  #14 = Utf8               java/util/Map
  #15 = Class              #14            // java/util/Map
  #16 = Utf8               Entry
  #17 = Utf8               scala/collection/convert/JavaCollectionWrappers
  #18 = Class              #17            // scala/collection/convert/JavaCollectionWrappers
  #19 = Utf8               JMapWrapperLike
  #20 = Utf8               ui
  #21 = Utf8               Ljava/util/Iterator;
  #22 = Utf8               Ljava/util/Iterator<Ljava/util/Map$Entry<TK;TV;>;>;
  #23 = Utf8               ()Ljava/util/Iterator;
  #24 = Utf8               ()Ljava/util/Iterator<Ljava/util/Map$Entry<TK;TV;>;>;
  #25 = NameAndType        #20:#21        // ui:Ljava/util/Iterator;
  #26 = Fieldref           #2.#25         // scala/collection/convert/JavaCollectionWrappers$JMapWrapperLike$$anon$5.ui:Ljava/util/Iterator;
  #27 = Utf8               this
  #28 = Utf8               Lscala/collection/convert/JavaCollectionWrappers$JMapWrapperLike$$anon$5;
  #29 = Utf8               hasNext
  #30 = Utf8               ()Z
  #31 = NameAndType        #20:#23        // ui:()Ljava/util/Iterator;
  #32 = Methodref          #2.#31         // scala/collection/convert/JavaCollectionWrappers$JMapWrapperLike$$anon$5.ui:()Ljava/util/Iterator;
  #33 = Utf8               java/util/Iterator
  #34 = Class              #33            // java/util/Iterator
  #35 = NameAndType        #29:#30        // hasNext:()Z
  #36 = InterfaceMethodref #34.#35        // java/util/Iterator.hasNext:()Z
  #37 = Utf8               next
  #38 = Utf8               ()Lscala/Tuple2;
  #39 = Utf8               ()Lscala/Tuple2<TK;TV;>;
  #40 = Utf8               ()Ljava/lang/Object;
  #41 = NameAndType        #37:#40        // next:()Ljava/lang/Object;
  #42 = InterfaceMethodref #34.#41        // java/util/Iterator.next:()Ljava/lang/Object;
  #43 = Utf8               scala/Tuple2
  #44 = Class              #43            // scala/Tuple2
  #45 = Utf8               getKey
  #46 = NameAndType        #45:#40        // getKey:()Ljava/lang/Object;
  #47 = InterfaceMethodref #13.#46        // java/util/Map$Entry.getKey:()Ljava/lang/Object;
  #48 = Utf8               getValue
  #49 = NameAndType        #48:#40        // getValue:()Ljava/lang/Object;
  #50 = InterfaceMethodref #13.#49        // java/util/Map$Entry.getValue:()Ljava/lang/Object;
  #51 = Utf8               <init>
  #52 = Utf8               (Ljava/lang/Object;Ljava/lang/Object;)V
  #53 = NameAndType        #51:#52        // "<init>":(Ljava/lang/Object;Ljava/lang/Object;)V
  #54 = Methodref          #44.#53        // scala/Tuple2."<init>":(Ljava/lang/Object;Ljava/lang/Object;)V
  #55 = Utf8               e
  #56 = Utf8               Ljava/util/Map$Entry;
  #57 = NameAndType        #37:#38        // next:()Lscala/Tuple2;
  #58 = Methodref          #2.#57         // scala/collection/convert/JavaCollectionWrappers$JMapWrapperLike$$anon$5.next:()Lscala/Tuple2;
  #59 = Utf8               (Lscala/collection/convert/JavaCollectionWrappers$JMapWrapperLike;)V
  #60 = Utf8               $outer
  #61 = Utf8               ()V
  #62 = NameAndType        #51:#61        // "<init>":()V
  #63 = Methodref          #5.#62         // scala/collection/AbstractIterator."<init>":()V
  #64 = Utf8               underlying
  #65 = Utf8               ()Ljava/util/Map;
  #66 = NameAndType        #64:#65        // underlying:()Ljava/util/Map;
  #67 = InterfaceMethodref #8.#66         // scala/collection/convert/JavaCollectionWrappers$JMapWrapperLike.underlying:()Ljava/util/Map;
  #68 = Utf8               entrySet
  #69 = Utf8               ()Ljava/util/Set;
  #70 = NameAndType        #68:#69        // entrySet:()Ljava/util/Set;
  #71 = InterfaceMethodref #15.#70        // java/util/Map.entrySet:()Ljava/util/Set;
  #72 = Utf8               java/util/Set
  #73 = Class              #72            // java/util/Set
  #74 = NameAndType        #9:#23         // iterator:()Ljava/util/Iterator;
  #75 = InterfaceMethodref #73.#74        // java/util/Set.iterator:()Ljava/util/Iterator;
  #76 = Utf8               Lscala/collection/convert/JavaCollectionWrappers$JMapWrapperLike;
  #77 = Utf8               Signature
  #78 = Utf8               Code
  #79 = Utf8               LineNumberTable
  #80 = Utf8               LocalVariableTable
  #81 = Utf8               MethodParameters
  #82 = Utf8               InnerClasses
  #83 = Utf8               EnclosingMethod
  #84 = Utf8               SourceFile
  #85 = Utf8               ScalaInlineInfo
  #86 = Utf8               Scala
{
  private final java.util.Iterator<java.util.Map$Entry<K, V>> ui;
    descriptor: Ljava/util/Iterator;
    flags: (0x0012) ACC_PRIVATE, ACC_FINAL
    Signature: #22                          // Ljava/util/Iterator<Ljava/util/Map$Entry<TK;TV;>;>;

  private java.util.Iterator<java.util.Map$Entry<K, V>> ui();
    descriptor: ()Ljava/util/Iterator;
    flags: (0x0002) ACC_PRIVATE
    Code:
      stack=1, locals=1, args_size=1
         0: aload_0
         1: getfield      #26                 // Field ui:Ljava/util/Iterator;
         4: areturn
      LineNumberTable:
        line 350: 0
      LocalVariableTable:
        Start  Length  Slot  Name   Signature
            0       5     0  this   Lscala/collection/convert/JavaCollectionWrappers$JMapWrapperLike$$anon$5;
    Signature: #24                          // ()Ljava/util/Iterator<Ljava/util/Map$Entry<TK;TV;>;>;

  public boolean hasNext();
    descriptor: ()Z
    flags: (0x0001) ACC_PUBLIC
    Code:
      stack=1, locals=1, args_size=1
         0: aload_0
         1: invokespecial #32                 // Method ui:()Ljava/util/Iterator;
         4: invokeinterface #36,  1           // InterfaceMethod java/util/Iterator.hasNext:()Z
         9: ireturn
      LineNumberTable:
        line 351: 0
      LocalVariableTable:
        Start  Length  Slot  Name   Signature
            0      10     0  this   Lscala/collection/convert/JavaCollectionWrappers$JMapWrapperLike$$anon$5;

  public scala.Tuple2<K, V> next();
    descriptor: ()Lscala/Tuple2;
    flags: (0x0001) ACC_PUBLIC
    Code:
      stack=4, locals=2, args_size=1
         0: aload_0
         1: invokespecial #32                 // Method ui:()Ljava/util/Iterator;
         4: invokeinterface #42,  1           // InterfaceMethod java/util/Iterator.next:()Ljava/lang/Object;
         9: checkcast     #13                 // class java/util/Map$Entry
        12: astore_1
        13: new           #44                 // class scala/Tuple2
        16: dup
        17: aload_1
        18: invokeinterface #47,  1           // InterfaceMethod java/util/Map$Entry.getKey:()Ljava/lang/Object;
        23: aload_1
        24: invokeinterface #50,  1           // InterfaceMethod java/util/Map$Entry.getValue:()Ljava/lang/Object;
        29: invokespecial #54                 // Method scala/Tuple2."<init>":(Ljava/lang/Object;Ljava/lang/Object;)V
        32: areturn
      LineNumberTable:
        line 352: 0
      LocalVariableTable:
        Start  Length  Slot  Name   Signature
           13      19     1     e   Ljava/util/Map$Entry;
            0      33     0  this   Lscala/collection/convert/JavaCollectionWrappers$JMapWrapperLike$$anon$5;
    Signature: #39                          // ()Lscala/Tuple2<TK;TV;>;

  public java.lang.Object next();
    descriptor: ()Ljava/lang/Object;
    flags: (0x1041) ACC_PUBLIC, ACC_BRIDGE, ACC_SYNTHETIC
    Code:
      stack=1, locals=1, args_size=1
         0: aload_0
         1: invokevirtual #58                 // Method next:()Lscala/Tuple2;
         4: areturn
      LineNumberTable:
        line 349: 0
      LocalVariableTable:
        Start  Length  Slot  Name   Signature
            0       5     0  this   Lscala/collection/convert/JavaCollectionWrappers$JMapWrapperLike$$anon$5;

  public scala.collection.convert.JavaCollectionWrappers$JMapWrapperLike$$anon$5(scala.collection.convert.JavaCollectionWrappers$JMapWrapperLike);
    descriptor: (Lscala/collection/convert/JavaCollectionWrappers$JMapWrapperLike;)V
    flags: (0x0001) ACC_PUBLIC
    Code:
      stack=2, locals=2, args_size=2
         0: aload_0
         1: invokespecial #63                 // Method scala/collection/AbstractIterator."<init>":()V
         4: aload_0
         5: aload_1
         6: invokeinterface #67,  1           // InterfaceMethod scala/collection/convert/JavaCollectionWrappers$JMapWrapperLike.underlying:()Ljava/util/Map;
        11: invokeinterface #71,  1           // InterfaceMethod java/util/Map.entrySet:()Ljava/util/Set;
        16: invokeinterface #75,  1           // InterfaceMethod java/util/Set.iterator:()Ljava/util/Iterator;
        21: putfield      #26                 // Field ui:Ljava/util/Iterator;
        24: return
      LineNumberTable:
        line 349: 0
        line 350: 4
        line 349: 24
      LocalVariableTable:
        Start  Length  Slot  Name   Signature
            0      25     0  this   Lscala/collection/convert/JavaCollectionWrappers$JMapWrapperLike$$anon$5;
            0      25     1 $outer   Lscala/collection/convert/JavaCollectionWrappers$JMapWrapperLike;
    MethodParameters:
      Name                           Flags
      $outer                         final synthetic
}
InnerClasses:
  public static #16= #13 of #15;          // Entry=class java/util/Map$Entry of class java/util/Map
  public static #19= #8 of #18;           // JMapWrapperLike=class scala/collection/convert/JavaCollectionWrappers$JMapWrapperLike of class scala/collection/convert/JavaCollectionWrappers
  public final #2;                        // class scala/collection/convert/JavaCollectionWrappers$JMapWrapperLike$$anon$5
EnclosingMethod: #8.#11                 // scala.collection.convert.JavaCollectionWrappers$JMapWrapperLike.iterator
Signature: #3                           // Lscala/collection/AbstractIterator<Lscala/Tuple2<TK;TV;>;>;
SourceFile: "JavaCollectionWrappers.scala"
  ScalaInlineInfo: length = 0x1D (unknown attribute)
   01 01 00 05 00 33 00 3B 01 00 1D 00 1E 01 00 25
   00 28 01 00 25 00 26 01 00 14 00 17 01
  Scala: length = 0x0 (unknown attribute)

