Classfile /Users/mw/Projects/slang-braindump/.jar/jar11/assemble/slang-braindump/assemble/content/scala/collection/convert/JavaCollectionWrappers$IterableWrapperTrait.class
  Last modified May 29, 2022; size 2041 bytes
  SHA-256 checksum 779bc977861fe33b9c0fbb6ff62b0dbbffd1d500cdf9b2d39655a6a91135a1aa
  Compiled from "JavaCollectionWrappers.scala"
public interface scala.collection.convert.JavaCollectionWrappers$IterableWrapperTrait<A extends java.lang.Object>
  minor version: 0
  major version: 52
  flags: (0x0601) ACC_PUBLIC, ACC_INTERFACE, ACC_ABSTRACT
  this_class: #2                          // scala/collection/convert/JavaCollectionWrappers$IterableWrapperTrait
  super_class: #5                         // java/lang/Object
  interfaces: 0, fields: 0, methods: 8, attributes: 5
Constant pool:
   #1 = Utf8               scala/collection/convert/JavaCollectionWrappers$IterableWrapperTrait
   #2 = Class              #1             // scala/collection/convert/JavaCollectionWrappers$IterableWrapperTrait
   #3 = Utf8               <A:Ljava/lang/Object;>Ljava/lang/Object;
   #4 = Utf8               java/lang/Object
   #5 = Class              #4             // java/lang/Object
   #6 = Utf8               JavaCollectionWrappers.scala
   #7 = Utf8               scala/collection/convert/JavaCollectionWrappers
   #8 = Class              #7             // scala/collection/convert/JavaCollectionWrappers
   #9 = Utf8               IterableWrapperTrait
  #10 = Utf8               scala/collection/convert/JavaCollectionWrappers$IteratorWrapper
  #11 = Class              #10            // scala/collection/convert/JavaCollectionWrappers$IteratorWrapper
  #12 = Utf8               IteratorWrapper
  #13 = Utf8               underlying
  #14 = Utf8               ()Lscala/collection/Iterable;
  #15 = Utf8               ()Lscala/collection/Iterable<TA;>;
  #16 = Utf8               size$
  #17 = Utf8               (Lscala/collection/convert/JavaCollectionWrappers$IterableWrapperTrait;)I
  #18 = Utf8               $this
  #19 = Utf8               size
  #20 = Utf8               ()I
  #21 = NameAndType        #19:#20        // size:()I
  #22 = InterfaceMethodref #2.#21         // scala/collection/convert/JavaCollectionWrappers$IterableWrapperTrait.size:()I
  #23 = Utf8               Lscala/collection/convert/JavaCollectionWrappers$IterableWrapperTrait;
  #24 = NameAndType        #13:#14        // underlying:()Lscala/collection/Iterable;
  #25 = InterfaceMethodref #2.#24         // scala/collection/convert/JavaCollectionWrappers$IterableWrapperTrait.underlying:()Lscala/collection/Iterable;
  #26 = Utf8               scala/collection/Iterable
  #27 = Class              #26            // scala/collection/Iterable
  #28 = InterfaceMethodref #27.#21        // scala/collection/Iterable.size:()I
  #29 = Utf8               this
  #30 = Utf8               iterator$
  #31 = Utf8               (Lscala/collection/convert/JavaCollectionWrappers$IterableWrapperTrait;)Lscala/collection/convert/JavaCollectionWrappers$IteratorWrapper;
  #32 = Utf8               iterator
  #33 = Utf8               ()Lscala/collection/convert/JavaCollectionWrappers$IteratorWrapper;
  #34 = NameAndType        #32:#33        // iterator:()Lscala/collection/convert/JavaCollectionWrappers$IteratorWrapper;
  #35 = InterfaceMethodref #2.#34         // scala/collection/convert/JavaCollectionWrappers$IterableWrapperTrait.iterator:()Lscala/collection/convert/JavaCollectionWrappers$IteratorWrapper;
  #36 = Utf8               ()Lscala/collection/convert/JavaCollectionWrappers$IteratorWrapper<TA;>;
  #37 = Utf8               ()Lscala/collection/Iterator;
  #38 = NameAndType        #32:#37        // iterator:()Lscala/collection/Iterator;
  #39 = InterfaceMethodref #27.#38        // scala/collection/Iterable.iterator:()Lscala/collection/Iterator;
  #40 = Utf8               <init>
  #41 = Utf8               (Lscala/collection/Iterator;)V
  #42 = NameAndType        #40:#41        // "<init>":(Lscala/collection/Iterator;)V
  #43 = Methodref          #11.#42        // scala/collection/convert/JavaCollectionWrappers$IteratorWrapper."<init>":(Lscala/collection/Iterator;)V
  #44 = Utf8               isEmpty$
  #45 = Utf8               (Lscala/collection/convert/JavaCollectionWrappers$IterableWrapperTrait;)Z
  #46 = Utf8               isEmpty
  #47 = Utf8               ()Z
  #48 = NameAndType        #46:#47        // isEmpty:()Z
  #49 = InterfaceMethodref #2.#48         // scala/collection/convert/JavaCollectionWrappers$IterableWrapperTrait.isEmpty:()Z
  #50 = InterfaceMethodref #27.#48        // scala/collection/Iterable.isEmpty:()Z
  #51 = Utf8               $init$
  #52 = Utf8               (Lscala/collection/convert/JavaCollectionWrappers$IterableWrapperTrait;)V
  #53 = Utf8               Signature
  #54 = Utf8               Code
  #55 = Utf8               LineNumberTable
  #56 = Utf8               LocalVariableTable
  #57 = Utf8               MethodParameters
  #58 = Utf8               InnerClasses
  #59 = Utf8               SourceFile
  #60 = Utf8               ScalaInlineInfo
  #61 = Utf8               Scala
{
  public abstract scala.collection.Iterable<A> underlying();
    descriptor: ()Lscala/collection/Iterable;
    flags: (0x0401) ACC_PUBLIC, ACC_ABSTRACT
    Signature: #15                          // ()Lscala/collection/Iterable<TA;>;

  public static int size$(scala.collection.convert.JavaCollectionWrappers$IterableWrapperTrait);
    descriptor: (Lscala/collection/convert/JavaCollectionWrappers$IterableWrapperTrait;)I
    flags: (0x1009) ACC_PUBLIC, ACC_STATIC, ACC_SYNTHETIC
    Code:
      stack=1, locals=1, args_size=1
         0: aload_0
         1: invokespecial #22                 // InterfaceMethod size:()I
         4: ireturn
      LineNumberTable:
        line 49: 0
      LocalVariableTable:
        Start  Length  Slot  Name   Signature
            0       5     0 $this   Lscala/collection/convert/JavaCollectionWrappers$IterableWrapperTrait;
    MethodParameters:
      Name                           Flags
      $this                          final synthetic

  public default int size();
    descriptor: ()I
    flags: (0x0001) ACC_PUBLIC
    Code:
      stack=1, locals=1, args_size=1
         0: aload_0
         1: invokeinterface #25,  1           // InterfaceMethod underlying:()Lscala/collection/Iterable;
         6: invokeinterface #28,  1           // InterfaceMethod scala/collection/Iterable.size:()I
        11: ireturn
      LineNumberTable:
        line 49: 0
      LocalVariableTable:
        Start  Length  Slot  Name   Signature
            0      12     0  this   Lscala/collection/convert/JavaCollectionWrappers$IterableWrapperTrait;

  public static scala.collection.convert.JavaCollectionWrappers$IteratorWrapper iterator$(scala.collection.convert.JavaCollectionWrappers$IterableWrapperTrait);
    descriptor: (Lscala/collection/convert/JavaCollectionWrappers$IterableWrapperTrait;)Lscala/collection/convert/JavaCollectionWrappers$IteratorWrapper;
    flags: (0x1009) ACC_PUBLIC, ACC_STATIC, ACC_SYNTHETIC
    Code:
      stack=1, locals=1, args_size=1
         0: aload_0
         1: invokespecial #35                 // InterfaceMethod iterator:()Lscala/collection/convert/JavaCollectionWrappers$IteratorWrapper;
         4: areturn
      LineNumberTable:
        line 50: 0
      LocalVariableTable:
        Start  Length  Slot  Name   Signature
            0       5     0 $this   Lscala/collection/convert/JavaCollectionWrappers$IterableWrapperTrait;
    MethodParameters:
      Name                           Flags
      $this                          final synthetic

  public default scala.collection.convert.JavaCollectionWrappers$IteratorWrapper<A> iterator();
    descriptor: ()Lscala/collection/convert/JavaCollectionWrappers$IteratorWrapper;
    flags: (0x0001) ACC_PUBLIC
    Code:
      stack=3, locals=1, args_size=1
         0: new           #11                 // class scala/collection/convert/JavaCollectionWrappers$IteratorWrapper
         3: dup
         4: aload_0
         5: invokeinterface #25,  1           // InterfaceMethod underlying:()Lscala/collection/Iterable;
        10: invokeinterface #39,  1           // InterfaceMethod scala/collection/Iterable.iterator:()Lscala/collection/Iterator;
        15: invokespecial #43                 // Method scala/collection/convert/JavaCollectionWrappers$IteratorWrapper."<init>":(Lscala/collection/Iterator;)V
        18: areturn
      LineNumberTable:
        line 50: 0
      LocalVariableTable:
        Start  Length  Slot  Name   Signature
            0      19     0  this   Lscala/collection/convert/JavaCollectionWrappers$IterableWrapperTrait;
    Signature: #36                          // ()Lscala/collection/convert/JavaCollectionWrappers$IteratorWrapper<TA;>;

  public static boolean isEmpty$(scala.collection.convert.JavaCollectionWrappers$IterableWrapperTrait);
    descriptor: (Lscala/collection/convert/JavaCollectionWrappers$IterableWrapperTrait;)Z
    flags: (0x1009) ACC_PUBLIC, ACC_STATIC, ACC_SYNTHETIC
    Code:
      stack=1, locals=1, args_size=1
         0: aload_0
         1: invokespecial #49                 // InterfaceMethod isEmpty:()Z
         4: ireturn
      LineNumberTable:
        line 51: 0
      LocalVariableTable:
        Start  Length  Slot  Name   Signature
            0       5     0 $this   Lscala/collection/convert/JavaCollectionWrappers$IterableWrapperTrait;
    MethodParameters:
      Name                           Flags
      $this                          final synthetic

  public default boolean isEmpty();
    descriptor: ()Z
    flags: (0x0001) ACC_PUBLIC
    Code:
      stack=1, locals=1, args_size=1
         0: aload_0
         1: invokeinterface #25,  1           // InterfaceMethod underlying:()Lscala/collection/Iterable;
         6: invokeinterface #50,  1           // InterfaceMethod scala/collection/Iterable.isEmpty:()Z
        11: ireturn
      LineNumberTable:
        line 51: 0
      LocalVariableTable:
        Start  Length  Slot  Name   Signature
            0      12     0  this   Lscala/collection/convert/JavaCollectionWrappers$IterableWrapperTrait;

  public static void $init$(scala.collection.convert.JavaCollectionWrappers$IterableWrapperTrait);
    descriptor: (Lscala/collection/convert/JavaCollectionWrappers$IterableWrapperTrait;)V
    flags: (0x0009) ACC_PUBLIC, ACC_STATIC
    Code:
      stack=0, locals=1, args_size=1
         0: return
      LineNumberTable:
        line 47: 0
      LocalVariableTable:
        Start  Length  Slot  Name   Signature
            0       1     0 $this   Lscala/collection/convert/JavaCollectionWrappers$IterableWrapperTrait;
    MethodParameters:
      Name                           Flags
      $this                          final synthetic
}
InnerClasses:
  public static #9= #2 of #8;             // IterableWrapperTrait=class scala/collection/convert/JavaCollectionWrappers$IterableWrapperTrait of class scala/collection/convert/JavaCollectionWrappers
  public static #12= #11 of #8;           // IteratorWrapper=class scala/collection/convert/JavaCollectionWrappers$IteratorWrapper of class scala/collection/convert/JavaCollectionWrappers
Signature: #3                           // <A:Ljava/lang/Object;>Ljava/lang/Object;
SourceFile: "JavaCollectionWrappers.scala"
  ScalaInlineInfo: length = 0x2C (unknown attribute)
   01 00 00 08 00 33 00 34 01 00 2E 00 2F 00 00 2C
   00 2D 01 00 20 00 21 00 00 1E 00 1F 01 00 13 00
   14 00 00 10 00 11 01 00 0D 00 0E 00
  Scala: length = 0x0 (unknown attribute)

