Classfile /Users/mw/Projects/slang-braindump/.jar/jar11/assemble/slang-braindump/assemble/content/scala/collection/convert/JavaCollectionWrappers$JListWrapper.class
  Last modified May 29, 2022; size 17140 bytes
  SHA-256 checksum a5441b6374e564f234b0033e05315865e82dabfbeaf28a7776241f87553be6fd
  Compiled from "JavaCollectionWrappers.scala"
public class scala.collection.convert.JavaCollectionWrappers$JListWrapper<A extends java.lang.Object> extends scala.collection.mutable.AbstractBuffer<A> implements scala.collection.StrictOptimizedSeqOps<A, scala.collection.mutable.Buffer, scala.collection.mutable.Buffer<A>>, java.io.Serializable, scala.Product
  minor version: 0
  major version: 52
  flags: (0x0021) ACC_PUBLIC, ACC_SUPER
  this_class: #2                          // scala/collection/convert/JavaCollectionWrappers$JListWrapper
  super_class: #5                         // scala/collection/mutable/AbstractBuffer
  interfaces: 3, fields: 2, methods: 71, attributes: 6
Constant pool:
    #1 = Utf8               scala/collection/convert/JavaCollectionWrappers$JListWrapper
    #2 = Class              #1            // scala/collection/convert/JavaCollectionWrappers$JListWrapper
    #3 = Utf8               <A:Ljava/lang/Object;>Lscala/collection/mutable/AbstractBuffer<TA;>;Lscala/collection/StrictOptimizedSeqOps<TA;Lscala/collection/mutable/Buffer;Lscala/collection/mutable/Buffer<TA;>;>;Ljava/io/Serializable;Lscala/Product;
    #4 = Utf8               scala/collection/mutable/AbstractBuffer
    #5 = Class              #4            // scala/collection/mutable/AbstractBuffer
    #6 = Utf8               scala/collection/StrictOptimizedSeqOps
    #7 = Class              #6            // scala/collection/StrictOptimizedSeqOps
    #8 = Utf8               java/io/Serializable
    #9 = Class              #8            // java/io/Serializable
   #10 = Utf8               scala/Product
   #11 = Class              #10           // scala/Product
   #12 = Utf8               JavaCollectionWrappers.scala
   #13 = Utf8               java/lang/invoke/MethodHandles$Lookup
   #14 = Class              #13           // java/lang/invoke/MethodHandles$Lookup
   #15 = Utf8               java/lang/invoke/MethodHandles
   #16 = Class              #15           // java/lang/invoke/MethodHandles
   #17 = Utf8               Lookup
   #18 = Utf8               scala/collection/convert/AsScalaExtensions$IteratorHasAsScala
   #19 = Class              #18           // scala/collection/convert/AsScalaExtensions$IteratorHasAsScala
   #20 = Utf8               scala/collection/convert/AsScalaExtensions
   #21 = Class              #20           // scala/collection/convert/AsScalaExtensions
   #22 = Utf8               IteratorHasAsScala
   #23 = Utf8               scala/collection/convert/JavaCollectionWrappers
   #24 = Class              #23           // scala/collection/convert/JavaCollectionWrappers
   #25 = Utf8               JListWrapper
   #26 = Utf8               scala/runtime/ScalaRunTime$$anon$1
   #27 = Class              #26           // scala/runtime/ScalaRunTime$$anon$1
   #28 = Utf8               serialVersionUID
   #29 = Utf8               J
   #30 = Long               3l
   #32 = Utf8               underlying
   #33 = Utf8               Ljava/util/List;
   #34 = Utf8               Ljava/util/List<TA;>;
   #35 = Utf8               productElementNames
   #36 = Utf8               ()Lscala/collection/Iterator;
   #37 = Utf8               ()Lscala/collection/Iterator<Ljava/lang/String;>;
   #38 = Utf8               productElementNames$
   #39 = Utf8               (Lscala/Product;)Lscala/collection/Iterator;
   #40 = NameAndType        #38:#39       // productElementNames$:(Lscala/Product;)Lscala/collection/Iterator;
   #41 = InterfaceMethodref #11.#40       // scala/Product.productElementNames$:(Lscala/Product;)Lscala/collection/Iterator;
   #42 = Utf8               this
   #43 = Utf8               Lscala/collection/convert/JavaCollectionWrappers$JListWrapper;
   #44 = Utf8               distinctBy
   #45 = Utf8               (Lscala/Function1;)Ljava/lang/Object;
   #46 = Utf8               f
   #47 = Utf8               distinctBy$
   #48 = Utf8               (Lscala/collection/StrictOptimizedSeqOps;Lscala/Function1;)Ljava/lang/Object;
   #49 = NameAndType        #47:#48       // distinctBy$:(Lscala/collection/StrictOptimizedSeqOps;Lscala/Function1;)Ljava/lang/Object;
   #50 = InterfaceMethodref #7.#49        // scala/collection/StrictOptimizedSeqOps.distinctBy$:(Lscala/collection/StrictOptimizedSeqOps;Lscala/Function1;)Ljava/lang/Object;
   #51 = Utf8               Lscala/Function1;
   #52 = Utf8               prepended
   #53 = Utf8               (Ljava/lang/Object;)Ljava/lang/Object;
   #54 = Utf8               elem
   #55 = Utf8               prepended$
   #56 = Utf8               (Lscala/collection/StrictOptimizedSeqOps;Ljava/lang/Object;)Ljava/lang/Object;
   #57 = NameAndType        #55:#56       // prepended$:(Lscala/collection/StrictOptimizedSeqOps;Ljava/lang/Object;)Ljava/lang/Object;
   #58 = InterfaceMethodref #7.#57        // scala/collection/StrictOptimizedSeqOps.prepended$:(Lscala/collection/StrictOptimizedSeqOps;Ljava/lang/Object;)Ljava/lang/Object;
   #59 = Utf8               Ljava/lang/Object;
   #60 = Utf8               appended
   #61 = Utf8               appended$
   #62 = NameAndType        #61:#56       // appended$:(Lscala/collection/StrictOptimizedSeqOps;Ljava/lang/Object;)Ljava/lang/Object;
   #63 = InterfaceMethodref #7.#62        // scala/collection/StrictOptimizedSeqOps.appended$:(Lscala/collection/StrictOptimizedSeqOps;Ljava/lang/Object;)Ljava/lang/Object;
   #64 = Utf8               appendedAll
   #65 = Utf8               (Lscala/collection/IterableOnce;)Ljava/lang/Object;
   #66 = Utf8               suffix
   #67 = Utf8               appendedAll$
   #68 = Utf8               (Lscala/collection/StrictOptimizedSeqOps;Lscala/collection/IterableOnce;)Ljava/lang/Object;
   #69 = NameAndType        #67:#68       // appendedAll$:(Lscala/collection/StrictOptimizedSeqOps;Lscala/collection/IterableOnce;)Ljava/lang/Object;
   #70 = InterfaceMethodref #7.#69        // scala/collection/StrictOptimizedSeqOps.appendedAll$:(Lscala/collection/StrictOptimizedSeqOps;Lscala/collection/IterableOnce;)Ljava/lang/Object;
   #71 = Utf8               Lscala/collection/IterableOnce;
   #72 = Utf8               prependedAll
   #73 = Utf8               prefix
   #74 = Utf8               prependedAll$
   #75 = NameAndType        #74:#68       // prependedAll$:(Lscala/collection/StrictOptimizedSeqOps;Lscala/collection/IterableOnce;)Ljava/lang/Object;
   #76 = InterfaceMethodref #7.#75        // scala/collection/StrictOptimizedSeqOps.prependedAll$:(Lscala/collection/StrictOptimizedSeqOps;Lscala/collection/IterableOnce;)Ljava/lang/Object;
   #77 = Utf8               padTo
   #78 = Utf8               (ILjava/lang/Object;)Ljava/lang/Object;
   #79 = Utf8               len
   #80 = Utf8               padTo$
   #81 = Utf8               (Lscala/collection/StrictOptimizedSeqOps;ILjava/lang/Object;)Ljava/lang/Object;
   #82 = NameAndType        #80:#81       // padTo$:(Lscala/collection/StrictOptimizedSeqOps;ILjava/lang/Object;)Ljava/lang/Object;
   #83 = InterfaceMethodref #7.#82        // scala/collection/StrictOptimizedSeqOps.padTo$:(Lscala/collection/StrictOptimizedSeqOps;ILjava/lang/Object;)Ljava/lang/Object;
   #84 = Utf8               I
   #85 = Utf8               diff
   #86 = Utf8               (Lscala/collection/Seq;)Ljava/lang/Object;
   #87 = Utf8               that
   #88 = Utf8               diff$
   #89 = Utf8               (Lscala/collection/StrictOptimizedSeqOps;Lscala/collection/Seq;)Ljava/lang/Object;
   #90 = NameAndType        #88:#89       // diff$:(Lscala/collection/StrictOptimizedSeqOps;Lscala/collection/Seq;)Ljava/lang/Object;
   #91 = InterfaceMethodref #7.#90        // scala/collection/StrictOptimizedSeqOps.diff$:(Lscala/collection/StrictOptimizedSeqOps;Lscala/collection/Seq;)Ljava/lang/Object;
   #92 = Utf8               Lscala/collection/Seq;
   #93 = Utf8               intersect
   #94 = Utf8               intersect$
   #95 = NameAndType        #94:#89       // intersect$:(Lscala/collection/StrictOptimizedSeqOps;Lscala/collection/Seq;)Ljava/lang/Object;
   #96 = InterfaceMethodref #7.#95        // scala/collection/StrictOptimizedSeqOps.intersect$:(Lscala/collection/StrictOptimizedSeqOps;Lscala/collection/Seq;)Ljava/lang/Object;
   #97 = Utf8               partition
   #98 = Utf8               (Lscala/Function1;)Lscala/Tuple2;
   #99 = Utf8               (Lscala/Function1<TA;Ljava/lang/Object;>;)Lscala/Tuple2<Lscala/collection/mutable/Buffer<TA;>;Lscala/collection/mutable/Buffer<TA;>;>;
  #100 = Utf8               p
  #101 = Utf8               scala/collection/StrictOptimizedIterableOps
  #102 = Class              #101          // scala/collection/StrictOptimizedIterableOps
  #103 = Utf8               partition$
  #104 = Utf8               (Lscala/collection/StrictOptimizedIterableOps;Lscala/Function1;)Lscala/Tuple2;
  #105 = NameAndType        #103:#104     // partition$:(Lscala/collection/StrictOptimizedIterableOps;Lscala/Function1;)Lscala/Tuple2;
  #106 = InterfaceMethodref #102.#105     // scala/collection/StrictOptimizedIterableOps.partition$:(Lscala/collection/StrictOptimizedIterableOps;Lscala/Function1;)Lscala/Tuple2;
  #107 = Utf8               span
  #108 = Utf8               span$
  #109 = NameAndType        #108:#104     // span$:(Lscala/collection/StrictOptimizedIterableOps;Lscala/Function1;)Lscala/Tuple2;
  #110 = InterfaceMethodref #102.#109     // scala/collection/StrictOptimizedIterableOps.span$:(Lscala/collection/StrictOptimizedIterableOps;Lscala/Function1;)Lscala/Tuple2;
  #111 = Utf8               unzip
  #112 = Utf8               <A1:Ljava/lang/Object;A2:Ljava/lang/Object;>(Lscala/Function1<TA;Lscala/Tuple2<TA1;TA2;>;>;)Lscala/Tuple2<Lscala/collection/mutable/Buffer<TA1;>;Lscala/collection/mutable/Buffer<TA2;>;>;
  #113 = Utf8               asPair
  #114 = Utf8               unzip$
  #115 = NameAndType        #114:#104     // unzip$:(Lscala/collection/StrictOptimizedIterableOps;Lscala/Function1;)Lscala/Tuple2;
  #116 = InterfaceMethodref #102.#115     // scala/collection/StrictOptimizedIterableOps.unzip$:(Lscala/collection/StrictOptimizedIterableOps;Lscala/Function1;)Lscala/Tuple2;
  #117 = Utf8               unzip3
  #118 = Utf8               (Lscala/Function1;)Lscala/Tuple3;
  #119 = Utf8               <A1:Ljava/lang/Object;A2:Ljava/lang/Object;A3:Ljava/lang/Object;>(Lscala/Function1<TA;Lscala/Tuple3<TA1;TA2;TA3;>;>;)Lscala/Tuple3<Lscala/collection/mutable/Buffer<TA1;>;Lscala/collection/mutable/Buffer<TA2;>;Lscala/collection/mutable/Buffer<TA3;>;>;
  #120 = Utf8               asTriple
  #121 = Utf8               unzip3$
  #122 = Utf8               (Lscala/collection/StrictOptimizedIterableOps;Lscala/Function1;)Lscala/Tuple3;
  #123 = NameAndType        #121:#122     // unzip3$:(Lscala/collection/StrictOptimizedIterableOps;Lscala/Function1;)Lscala/Tuple3;
  #124 = InterfaceMethodref #102.#123     // scala/collection/StrictOptimizedIterableOps.unzip3$:(Lscala/collection/StrictOptimizedIterableOps;Lscala/Function1;)Lscala/Tuple3;
  #125 = Utf8               map
  #126 = Utf8               map$
  #127 = Utf8               (Lscala/collection/StrictOptimizedIterableOps;Lscala/Function1;)Ljava/lang/Object;
  #128 = NameAndType        #126:#127     // map$:(Lscala/collection/StrictOptimizedIterableOps;Lscala/Function1;)Ljava/lang/Object;
  #129 = InterfaceMethodref #102.#128     // scala/collection/StrictOptimizedIterableOps.map$:(Lscala/collection/StrictOptimizedIterableOps;Lscala/Function1;)Ljava/lang/Object;
  #130 = Utf8               strictOptimizedMap
  #131 = Utf8               (Lscala/collection/mutable/Builder;Lscala/Function1;)Ljava/lang/Object;
  #132 = Utf8               <B:Ljava/lang/Object;C2:Ljava/lang/Object;>(Lscala/collection/mutable/Builder<TB;TC2;>;Lscala/Function1<TA;TB;>;)TC2;
  #133 = Utf8               b
  #134 = Utf8               strictOptimizedMap$
  #135 = Utf8               (Lscala/collection/StrictOptimizedIterableOps;Lscala/collection/mutable/Builder;Lscala/Function1;)Ljava/lang/Object;
  #136 = NameAndType        #134:#135     // strictOptimizedMap$:(Lscala/collection/StrictOptimizedIterableOps;Lscala/collection/mutable/Builder;Lscala/Function1;)Ljava/lang/Object;
  #137 = InterfaceMethodref #102.#136     // scala/collection/StrictOptimizedIterableOps.strictOptimizedMap$:(Lscala/collection/StrictOptimizedIterableOps;Lscala/collection/mutable/Builder;Lscala/Function1;)Ljava/lang/Object;
  #138 = Utf8               Lscala/collection/mutable/Builder;
  #139 = Utf8               flatMap
  #140 = Utf8               flatMap$
  #141 = NameAndType        #140:#127     // flatMap$:(Lscala/collection/StrictOptimizedIterableOps;Lscala/Function1;)Ljava/lang/Object;
  #142 = InterfaceMethodref #102.#141     // scala/collection/StrictOptimizedIterableOps.flatMap$:(Lscala/collection/StrictOptimizedIterableOps;Lscala/Function1;)Ljava/lang/Object;
  #143 = Utf8               strictOptimizedFlatMap
  #144 = Utf8               <B:Ljava/lang/Object;C2:Ljava/lang/Object;>(Lscala/collection/mutable/Builder<TB;TC2;>;Lscala/Function1<TA;Lscala/collection/IterableOnce<TB;>;>;)TC2;
  #145 = Utf8               strictOptimizedFlatMap$
  #146 = NameAndType        #145:#135     // strictOptimizedFlatMap$:(Lscala/collection/StrictOptimizedIterableOps;Lscala/collection/mutable/Builder;Lscala/Function1;)Ljava/lang/Object;
  #147 = InterfaceMethodref #102.#146     // scala/collection/StrictOptimizedIterableOps.strictOptimizedFlatMap$:(Lscala/collection/StrictOptimizedIterableOps;Lscala/collection/mutable/Builder;Lscala/Function1;)Ljava/lang/Object;
  #148 = Utf8               strictOptimizedConcat
  #149 = Utf8               (Lscala/collection/IterableOnce;Lscala/collection/mutable/Builder;)Ljava/lang/Object;
  #150 = Utf8               <B:Ljava/lang/Object;C2:Ljava/lang/Object;>(Lscala/collection/IterableOnce<TB;>;Lscala/collection/mutable/Builder<TB;TC2;>;)TC2;
  #151 = Utf8               strictOptimizedConcat$
  #152 = Utf8               (Lscala/collection/StrictOptimizedIterableOps;Lscala/collection/IterableOnce;Lscala/collection/mutable/Builder;)Ljava/lang/Object;
  #153 = NameAndType        #151:#152     // strictOptimizedConcat$:(Lscala/collection/StrictOptimizedIterableOps;Lscala/collection/IterableOnce;Lscala/collection/mutable/Builder;)Ljava/lang/Object;
  #154 = InterfaceMethodref #102.#153     // scala/collection/StrictOptimizedIterableOps.strictOptimizedConcat$:(Lscala/collection/StrictOptimizedIterableOps;Lscala/collection/IterableOnce;Lscala/collection/mutable/Builder;)Ljava/lang/Object;
  #155 = Utf8               collect
  #156 = Utf8               (Lscala/PartialFunction;)Ljava/lang/Object;
  #157 = Utf8               pf
  #158 = Utf8               collect$
  #159 = Utf8               (Lscala/collection/StrictOptimizedIterableOps;Lscala/PartialFunction;)Ljava/lang/Object;
  #160 = NameAndType        #158:#159     // collect$:(Lscala/collection/StrictOptimizedIterableOps;Lscala/PartialFunction;)Ljava/lang/Object;
  #161 = InterfaceMethodref #102.#160     // scala/collection/StrictOptimizedIterableOps.collect$:(Lscala/collection/StrictOptimizedIterableOps;Lscala/PartialFunction;)Ljava/lang/Object;
  #162 = Utf8               Lscala/PartialFunction;
  #163 = Utf8               strictOptimizedCollect
  #164 = Utf8               (Lscala/collection/mutable/Builder;Lscala/PartialFunction;)Ljava/lang/Object;
  #165 = Utf8               <B:Ljava/lang/Object;C2:Ljava/lang/Object;>(Lscala/collection/mutable/Builder<TB;TC2;>;Lscala/PartialFunction<TA;TB;>;)TC2;
  #166 = Utf8               strictOptimizedCollect$
  #167 = Utf8               (Lscala/collection/StrictOptimizedIterableOps;Lscala/collection/mutable/Builder;Lscala/PartialFunction;)Ljava/lang/Object;
  #168 = NameAndType        #166:#167     // strictOptimizedCollect$:(Lscala/collection/StrictOptimizedIterableOps;Lscala/collection/mutable/Builder;Lscala/PartialFunction;)Ljava/lang/Object;
  #169 = InterfaceMethodref #102.#168     // scala/collection/StrictOptimizedIterableOps.strictOptimizedCollect$:(Lscala/collection/StrictOptimizedIterableOps;Lscala/collection/mutable/Builder;Lscala/PartialFunction;)Ljava/lang/Object;
  #170 = Utf8               flatten
  #171 = Utf8               toIterableOnce
  #172 = Utf8               flatten$
  #173 = NameAndType        #172:#127     // flatten$:(Lscala/collection/StrictOptimizedIterableOps;Lscala/Function1;)Ljava/lang/Object;
  #174 = InterfaceMethodref #102.#173     // scala/collection/StrictOptimizedIterableOps.flatten$:(Lscala/collection/StrictOptimizedIterableOps;Lscala/Function1;)Ljava/lang/Object;
  #175 = Utf8               strictOptimizedFlatten
  #176 = Utf8               strictOptimizedFlatten$
  #177 = NameAndType        #176:#135     // strictOptimizedFlatten$:(Lscala/collection/StrictOptimizedIterableOps;Lscala/collection/mutable/Builder;Lscala/Function1;)Ljava/lang/Object;
  #178 = InterfaceMethodref #102.#177     // scala/collection/StrictOptimizedIterableOps.strictOptimizedFlatten$:(Lscala/collection/StrictOptimizedIterableOps;Lscala/collection/mutable/Builder;Lscala/Function1;)Ljava/lang/Object;
  #179 = Utf8               zip
  #180 = Utf8               zip$
  #181 = Utf8               (Lscala/collection/StrictOptimizedIterableOps;Lscala/collection/IterableOnce;)Ljava/lang/Object;
  #182 = NameAndType        #180:#181     // zip$:(Lscala/collection/StrictOptimizedIterableOps;Lscala/collection/IterableOnce;)Ljava/lang/Object;
  #183 = InterfaceMethodref #102.#182     // scala/collection/StrictOptimizedIterableOps.zip$:(Lscala/collection/StrictOptimizedIterableOps;Lscala/collection/IterableOnce;)Ljava/lang/Object;
  #184 = Utf8               strictOptimizedZip
  #185 = Utf8               <B:Ljava/lang/Object;C2:Ljava/lang/Object;>(Lscala/collection/IterableOnce<TB;>;Lscala/collection/mutable/Builder<Lscala/Tuple2<TA;TB;>;TC2;>;)TC2;
  #186 = Utf8               strictOptimizedZip$
  #187 = NameAndType        #186:#152     // strictOptimizedZip$:(Lscala/collection/StrictOptimizedIterableOps;Lscala/collection/IterableOnce;Lscala/collection/mutable/Builder;)Ljava/lang/Object;
  #188 = InterfaceMethodref #102.#187     // scala/collection/StrictOptimizedIterableOps.strictOptimizedZip$:(Lscala/collection/StrictOptimizedIterableOps;Lscala/collection/IterableOnce;Lscala/collection/mutable/Builder;)Ljava/lang/Object;
  #189 = Utf8               zipWithIndex
  #190 = Utf8               ()Ljava/lang/Object;
  #191 = Utf8               zipWithIndex$
  #192 = Utf8               (Lscala/collection/StrictOptimizedIterableOps;)Ljava/lang/Object;
  #193 = NameAndType        #191:#192     // zipWithIndex$:(Lscala/collection/StrictOptimizedIterableOps;)Ljava/lang/Object;
  #194 = InterfaceMethodref #102.#193     // scala/collection/StrictOptimizedIterableOps.zipWithIndex$:(Lscala/collection/StrictOptimizedIterableOps;)Ljava/lang/Object;
  #195 = Utf8               scanLeft
  #196 = Utf8               (Ljava/lang/Object;Lscala/Function2;)Ljava/lang/Object;
  #197 = Utf8               z
  #198 = Utf8               op
  #199 = Utf8               scanLeft$
  #200 = Utf8               (Lscala/collection/StrictOptimizedIterableOps;Ljava/lang/Object;Lscala/Function2;)Ljava/lang/Object;
  #201 = NameAndType        #199:#200     // scanLeft$:(Lscala/collection/StrictOptimizedIterableOps;Ljava/lang/Object;Lscala/Function2;)Ljava/lang/Object;
  #202 = InterfaceMethodref #102.#201     // scala/collection/StrictOptimizedIterableOps.scanLeft$:(Lscala/collection/StrictOptimizedIterableOps;Ljava/lang/Object;Lscala/Function2;)Ljava/lang/Object;
  #203 = Utf8               Lscala/Function2;
  #204 = Utf8               filter
  #205 = Utf8               pred
  #206 = Utf8               filter$
  #207 = NameAndType        #206:#127     // filter$:(Lscala/collection/StrictOptimizedIterableOps;Lscala/Function1;)Ljava/lang/Object;
  #208 = InterfaceMethodref #102.#207     // scala/collection/StrictOptimizedIterableOps.filter$:(Lscala/collection/StrictOptimizedIterableOps;Lscala/Function1;)Ljava/lang/Object;
  #209 = Utf8               filterNot
  #210 = Utf8               filterNot$
  #211 = NameAndType        #210:#127     // filterNot$:(Lscala/collection/StrictOptimizedIterableOps;Lscala/Function1;)Ljava/lang/Object;
  #212 = InterfaceMethodref #102.#211     // scala/collection/StrictOptimizedIterableOps.filterNot$:(Lscala/collection/StrictOptimizedIterableOps;Lscala/Function1;)Ljava/lang/Object;
  #213 = Utf8               filterImpl
  #214 = Utf8               (Lscala/Function1;Z)Ljava/lang/Object;
  #215 = Utf8               isFlipped
  #216 = Utf8               filterImpl$
  #217 = Utf8               (Lscala/collection/StrictOptimizedIterableOps;Lscala/Function1;Z)Ljava/lang/Object;
  #218 = NameAndType        #216:#217     // filterImpl$:(Lscala/collection/StrictOptimizedIterableOps;Lscala/Function1;Z)Ljava/lang/Object;
  #219 = InterfaceMethodref #102.#218     // scala/collection/StrictOptimizedIterableOps.filterImpl$:(Lscala/collection/StrictOptimizedIterableOps;Lscala/Function1;Z)Ljava/lang/Object;
  #220 = Utf8               Z
  #221 = Utf8               partitionMap
  #222 = Utf8               <A1:Ljava/lang/Object;A2:Ljava/lang/Object;>(Lscala/Function1<TA;Lscala/util/Either<TA1;TA2;>;>;)Lscala/Tuple2<Lscala/collection/mutable/Buffer<TA1;>;Lscala/collection/mutable/Buffer<TA2;>;>;
  #223 = Utf8               partitionMap$
  #224 = NameAndType        #223:#104     // partitionMap$:(Lscala/collection/StrictOptimizedIterableOps;Lscala/Function1;)Lscala/Tuple2;
  #225 = InterfaceMethodref #102.#224     // scala/collection/StrictOptimizedIterableOps.partitionMap$:(Lscala/collection/StrictOptimizedIterableOps;Lscala/Function1;)Lscala/Tuple2;
  #226 = Utf8               tapEach
  #227 = Utf8               tapEach$
  #228 = NameAndType        #227:#127     // tapEach$:(Lscala/collection/StrictOptimizedIterableOps;Lscala/Function1;)Ljava/lang/Object;
  #229 = InterfaceMethodref #102.#228     // scala/collection/StrictOptimizedIterableOps.tapEach$:(Lscala/collection/StrictOptimizedIterableOps;Lscala/Function1;)Ljava/lang/Object;
  #230 = Utf8               takeRight
  #231 = Utf8               (I)Ljava/lang/Object;
  #232 = Utf8               n
  #233 = Utf8               takeRight$
  #234 = Utf8               (Lscala/collection/StrictOptimizedIterableOps;I)Ljava/lang/Object;
  #235 = NameAndType        #233:#234     // takeRight$:(Lscala/collection/StrictOptimizedIterableOps;I)Ljava/lang/Object;
  #236 = InterfaceMethodref #102.#235     // scala/collection/StrictOptimizedIterableOps.takeRight$:(Lscala/collection/StrictOptimizedIterableOps;I)Ljava/lang/Object;
  #237 = Utf8               dropRight
  #238 = Utf8               dropRight$
  #239 = NameAndType        #238:#234     // dropRight$:(Lscala/collection/StrictOptimizedIterableOps;I)Ljava/lang/Object;
  #240 = InterfaceMethodref #102.#239     // scala/collection/StrictOptimizedIterableOps.dropRight$:(Lscala/collection/StrictOptimizedIterableOps;I)Ljava/lang/Object;
  #241 = Utf8               ()Ljava/util/List;
  #242 = Utf8               ()Ljava/util/List<TA;>;
  #243 = NameAndType        #32:#33       // underlying:Ljava/util/List;
  #244 = Fieldref           #2.#243       // scala/collection/convert/JavaCollectionWrappers$JListWrapper.underlying:Ljava/util/List;
  #245 = Utf8               length
  #246 = Utf8               ()I
  #247 = NameAndType        #32:#241      // underlying:()Ljava/util/List;
  #248 = Methodref          #2.#247       // scala/collection/convert/JavaCollectionWrappers$JListWrapper.underlying:()Ljava/util/List;
  #249 = Utf8               java/util/List
  #250 = Class              #249          // java/util/List
  #251 = Utf8               size
  #252 = NameAndType        #251:#246     // size:()I
  #253 = InterfaceMethodref #250.#252     // java/util/List.size:()I
  #254 = Utf8               knownSize
  #255 = Utf8               isEmpty
  #256 = Utf8               ()Z
  #257 = NameAndType        #255:#256     // isEmpty:()Z
  #258 = InterfaceMethodref #250.#257     // java/util/List.isEmpty:()Z
  #259 = Utf8               iterator
  #260 = Utf8               ()Lscala/collection/Iterator<TA;>;
  #261 = Utf8               scala/jdk/CollectionConverters$
  #262 = Class              #261          // scala/jdk/CollectionConverters$
  #263 = Utf8               MODULE$
  #264 = Utf8               Lscala/jdk/CollectionConverters$;
  #265 = NameAndType        #263:#264     // MODULE$:Lscala/jdk/CollectionConverters$;
  #266 = Fieldref           #262.#265     // scala/jdk/CollectionConverters$.MODULE$:Lscala/jdk/CollectionConverters$;
  #267 = Utf8               ()Ljava/util/Iterator;
  #268 = NameAndType        #259:#267     // iterator:()Ljava/util/Iterator;
  #269 = InterfaceMethodref #250.#268     // java/util/List.iterator:()Ljava/util/Iterator;
  #270 = Utf8               <init>
  #271 = Utf8               (Lscala/collection/convert/AsScalaExtensions;Ljava/util/Iterator;)V
  #272 = NameAndType        #270:#271     // "<init>":(Lscala/collection/convert/AsScalaExtensions;Ljava/util/Iterator;)V
  #273 = Methodref          #19.#272      // scala/collection/convert/AsScalaExtensions$IteratorHasAsScala."<init>":(Lscala/collection/convert/AsScalaExtensions;Ljava/util/Iterator;)V
  #274 = Utf8               asScala
  #275 = NameAndType        #274:#36      // asScala:()Lscala/collection/Iterator;
  #276 = Methodref          #19.#275      // scala/collection/convert/AsScalaExtensions$IteratorHasAsScala.asScala:()Lscala/collection/Iterator;
  #277 = Utf8               IteratorHasAsScala_this
  #278 = Utf8               IteratorHasAsScala_i
  #279 = Utf8               Ljava/util/Iterator;
  #280 = Utf8               apply
  #281 = Utf8               (I)TA;
  #282 = Utf8               i
  #283 = Utf8               get
  #284 = NameAndType        #283:#231     // get:(I)Ljava/lang/Object;
  #285 = InterfaceMethodref #250.#284     // java/util/List.get:(I)Ljava/lang/Object;
  #286 = Utf8               update
  #287 = Utf8               (ILjava/lang/Object;)V
  #288 = Utf8               (ITA;)V
  #289 = Utf8               set
  #290 = NameAndType        #289:#78      // set:(ILjava/lang/Object;)Ljava/lang/Object;
  #291 = InterfaceMethodref #250.#290     // java/util/List.set:(ILjava/lang/Object;)Ljava/lang/Object;
  #292 = Utf8               prepend
  #293 = Utf8               (Ljava/lang/Object;)Lscala/collection/convert/JavaCollectionWrappers$JListWrapper;
  #294 = Utf8               (TA;)Lscala/collection/convert/JavaCollectionWrappers$JListWrapper<TA;>;
  #295 = Utf8               subList
  #296 = Utf8               (II)Ljava/util/List;
  #297 = NameAndType        #295:#296     // subList:(II)Ljava/util/List;
  #298 = InterfaceMethodref #250.#297     // java/util/List.subList:(II)Ljava/util/List;
  #299 = Utf8               add
  #300 = Utf8               (Ljava/lang/Object;)Z
  #301 = NameAndType        #299:#300     // add:(Ljava/lang/Object;)Z
  #302 = InterfaceMethodref #250.#301     // java/util/List.add:(Ljava/lang/Object;)Z
  #303 = Utf8               addOne
  #304 = Utf8               insert
  #305 = Utf8               idx
  #306 = Utf8               insertAll
  #307 = Utf8               (ILscala/collection/IterableOnce;)V
  #308 = Utf8               (ILscala/collection/IterableOnce<TA;>;)V
  #309 = Utf8               elems
  #310 = Utf8               scala/collection/IterableOnce
  #311 = Class              #310          // scala/collection/IterableOnce
  #312 = NameAndType        #259:#36      // iterator:()Lscala/collection/Iterator;
  #313 = InterfaceMethodref #311.#312     // scala/collection/IterableOnce.iterator:()Lscala/collection/Iterator;
  #314 = MethodType         #53           //  (Ljava/lang/Object;)Ljava/lang/Object;
  #315 = Utf8               $anonfun$insertAll$1$adapted
  #316 = Utf8               (Ljava/util/List;Ljava/lang/Object;)Ljava/lang/Object;
  #317 = NameAndType        #315:#316     // $anonfun$insertAll$1$adapted:(Ljava/util/List;Ljava/lang/Object;)Ljava/lang/Object;
  #318 = Methodref          #2.#317       // scala/collection/convert/JavaCollectionWrappers$JListWrapper.$anonfun$insertAll$1$adapted:(Ljava/util/List;Ljava/lang/Object;)Ljava/lang/Object;
  #319 = MethodHandle       6:#318        // REF_invokeStatic scala/collection/convert/JavaCollectionWrappers$JListWrapper.$anonfun$insertAll$1$adapted:(Ljava/util/List;Ljava/lang/Object;)Ljava/lang/Object;
  #320 = Integer            1
  #321 = Utf8               java/lang/invoke/LambdaMetafactory
  #322 = Class              #321          // java/lang/invoke/LambdaMetafactory
  #323 = Utf8               altMetafactory
  #324 = Utf8               (Ljava/lang/invoke/MethodHandles$Lookup;Ljava/lang/String;Ljava/lang/invoke/MethodType;[Ljava/lang/Object;)Ljava/lang/invoke/CallSite;
  #325 = NameAndType        #323:#324     // altMetafactory:(Ljava/lang/invoke/MethodHandles$Lookup;Ljava/lang/String;Ljava/lang/invoke/MethodType;[Ljava/lang/Object;)Ljava/lang/invoke/CallSite;
  #326 = Methodref          #322.#325     // java/lang/invoke/LambdaMetafactory.altMetafactory:(Ljava/lang/invoke/MethodHandles$Lookup;Ljava/lang/String;Ljava/lang/invoke/MethodType;[Ljava/lang/Object;)Ljava/lang/invoke/CallSite;
  #327 = MethodHandle       6:#326        // REF_invokeStatic java/lang/invoke/LambdaMetafactory.altMetafactory:(Ljava/lang/invoke/MethodHandles$Lookup;Ljava/lang/String;Ljava/lang/invoke/MethodType;[Ljava/lang/Object;)Ljava/lang/invoke/CallSite;
  #328 = Utf8               (Ljava/util/List;)Lscala/Function1;
  #329 = NameAndType        #280:#328     // apply:(Ljava/util/List;)Lscala/Function1;
  #330 = InvokeDynamic      #0:#329       // #0:apply:(Ljava/util/List;)Lscala/Function1;
  #331 = Utf8               scala/collection/Iterator
  #332 = Class              #331          // scala/collection/Iterator
  #333 = Utf8               foreach
  #334 = Utf8               (Lscala/Function1;)V
  #335 = NameAndType        #333:#334     // foreach:(Lscala/Function1;)V
  #336 = InterfaceMethodref #332.#335     // scala/collection/Iterator.foreach:(Lscala/Function1;)V
  #337 = Utf8               ins
  #338 = Utf8               remove
  #339 = NameAndType        #338:#231     // remove:(I)Ljava/lang/Object;
  #340 = InterfaceMethodref #250.#339     // java/util/List.remove:(I)Ljava/lang/Object;
  #341 = Utf8               clear
  #342 = Utf8               ()V
  #343 = NameAndType        #341:#342     // clear:()V
  #344 = InterfaceMethodref #250.#343     // java/util/List.clear:()V
  #345 = Utf8               clone
  #346 = Utf8               ()Lscala/collection/convert/JavaCollectionWrappers$JListWrapper;
  #347 = Utf8               ()Lscala/collection/convert/JavaCollectionWrappers$JListWrapper<TA;>;
  #348 = Utf8               java/util/ArrayList
  #349 = Class              #348          // java/util/ArrayList
  #350 = Utf8               (Ljava/util/Collection;)V
  #351 = NameAndType        #270:#350     // "<init>":(Ljava/util/Collection;)V
  #352 = Methodref          #349.#351     // java/util/ArrayList."<init>":(Ljava/util/Collection;)V
  #353 = Utf8               (Ljava/util/List;)V
  #354 = NameAndType        #270:#353     // "<init>":(Ljava/util/List;)V
  #355 = Methodref          #2.#354       // scala/collection/convert/JavaCollectionWrappers$JListWrapper."<init>":(Ljava/util/List;)V
  #356 = Utf8               patchInPlace
  #357 = Utf8               (ILscala/collection/IterableOnce;I)Lscala/collection/convert/JavaCollectionWrappers$JListWrapper;
  #358 = Utf8               (ILscala/collection/IterableOnce<TA;>;I)Lscala/collection/convert/JavaCollectionWrappers$JListWrapper<TA;>;
  #359 = Utf8               from
  #360 = Utf8               patch
  #361 = Utf8               replaced
  #362 = Utf8               (II)V
  #363 = NameAndType        #338:#362     // remove:(II)V
  #364 = Methodref          #2.#363       // scala/collection/convert/JavaCollectionWrappers$JListWrapper.remove:(II)V
  #365 = NameAndType        #306:#307     // insertAll:(ILscala/collection/IterableOnce;)V
  #366 = Methodref          #2.#365       // scala/collection/convert/JavaCollectionWrappers$JListWrapper.insertAll:(ILscala/collection/IterableOnce;)V
  #367 = Utf8               iterableFactory
  #368 = Utf8               ()Lscala/collection/mutable/ArrayBuffer$;
  #369 = Utf8               scala/collection/mutable/ArrayBuffer$
  #370 = Class              #369          // scala/collection/mutable/ArrayBuffer$
  #371 = Utf8               Lscala/collection/mutable/ArrayBuffer$;
  #372 = NameAndType        #263:#371     // MODULE$:Lscala/collection/mutable/ArrayBuffer$;
  #373 = Fieldref           #370.#372     // scala/collection/mutable/ArrayBuffer$.MODULE$:Lscala/collection/mutable/ArrayBuffer$;
  #374 = Utf8               subtractOne
  #375 = NameAndType        #338:#300     // remove:(Ljava/lang/Object;)Z
  #376 = InterfaceMethodref #250.#375     // java/util/List.remove:(Ljava/lang/Object;)Z
  #377 = Utf8               copy
  #378 = Utf8               (Ljava/util/List;)Lscala/collection/convert/JavaCollectionWrappers$JListWrapper;
  #379 = Utf8               <A:Ljava/lang/Object;>(Ljava/util/List<TA;>;)Lscala/collection/convert/JavaCollectionWrappers$JListWrapper<TA;>;
  #380 = Utf8               copy$default$1
  #381 = Utf8               <A:Ljava/lang/Object;>()Ljava/util/List<TA;>;
  #382 = Utf8               productPrefix
  #383 = Utf8               ()Ljava/lang/String;
  #384 = String             #25           // JListWrapper
  #385 = Utf8               productArity
  #386 = Utf8               productElement
  #387 = Utf8               x$1
  #388 = Utf8               scala/runtime/Statics
  #389 = Class              #388          // scala/runtime/Statics
  #390 = Utf8               ioobe
  #391 = NameAndType        #390:#231     // ioobe:(I)Ljava/lang/Object;
  #392 = Methodref          #389.#391     // scala/runtime/Statics.ioobe:(I)Ljava/lang/Object;
  #393 = Utf8               productIterator
  #394 = Utf8               ()Lscala/collection/Iterator<Ljava/lang/Object;>;
  #395 = Utf8               (Lscala/Product;)V
  #396 = NameAndType        #270:#395     // "<init>":(Lscala/Product;)V
  #397 = Methodref          #27.#396      // scala/runtime/ScalaRunTime$$anon$1."<init>":(Lscala/Product;)V
  #398 = Utf8               productElementName
  #399 = Utf8               (I)Ljava/lang/String;
  #400 = String             #32           // underlying
  #401 = Utf8               java/lang/String
  #402 = Class              #401          // java/lang/String
  #403 = Utf8               (Ljava/lang/Object;)Lscala/collection/mutable/Shrinkable;
  #404 = NameAndType        #374:#293     // subtractOne:(Ljava/lang/Object;)Lscala/collection/convert/JavaCollectionWrappers$JListWrapper;
  #405 = Methodref          #2.#404       // scala/collection/convert/JavaCollectionWrappers$JListWrapper.subtractOne:(Ljava/lang/Object;)Lscala/collection/convert/JavaCollectionWrappers$JListWrapper;
  #406 = Utf8               (Ljava/lang/Object;)Lscala/collection/mutable/Buffer;
  #407 = Utf8               x
  #408 = Utf8               ()Lscala/collection/IterableFactory;
  #409 = NameAndType        #367:#368     // iterableFactory:()Lscala/collection/mutable/ArrayBuffer$;
  #410 = Methodref          #2.#409       // scala/collection/convert/JavaCollectionWrappers$JListWrapper.iterableFactory:()Lscala/collection/mutable/ArrayBuffer$;
  #411 = Utf8               ()Lscala/collection/SeqFactory;
  #412 = Utf8               (ILscala/collection/IterableOnce;I)Lscala/collection/mutable/Buffer;
  #413 = NameAndType        #356:#357     // patchInPlace:(ILscala/collection/IterableOnce;I)Lscala/collection/convert/JavaCollectionWrappers$JListWrapper;
  #414 = Methodref          #2.#413       // scala/collection/convert/JavaCollectionWrappers$JListWrapper.patchInPlace:(ILscala/collection/IterableOnce;I)Lscala/collection/convert/JavaCollectionWrappers$JListWrapper;
  #415 = NameAndType        #345:#346     // clone:()Lscala/collection/convert/JavaCollectionWrappers$JListWrapper;
  #416 = Methodref          #2.#415       // scala/collection/convert/JavaCollectionWrappers$JListWrapper.clone:()Lscala/collection/convert/JavaCollectionWrappers$JListWrapper;
  #417 = Utf8               (Ljava/lang/Object;)Lscala/collection/mutable/Growable;
  #418 = NameAndType        #303:#293     // addOne:(Ljava/lang/Object;)Lscala/collection/convert/JavaCollectionWrappers$JListWrapper;
  #419 = Methodref          #2.#418       // scala/collection/convert/JavaCollectionWrappers$JListWrapper.addOne:(Ljava/lang/Object;)Lscala/collection/convert/JavaCollectionWrappers$JListWrapper;
  #420 = NameAndType        #292:#293     // prepend:(Ljava/lang/Object;)Lscala/collection/convert/JavaCollectionWrappers$JListWrapper;
  #421 = Methodref          #2.#420       // scala/collection/convert/JavaCollectionWrappers$JListWrapper.prepend:(Ljava/lang/Object;)Lscala/collection/convert/JavaCollectionWrappers$JListWrapper;
  #422 = Utf8               v1
  #423 = Utf8               scala/runtime/BoxesRunTime
  #424 = Class              #423          // scala/runtime/BoxesRunTime
  #425 = Utf8               unboxToInt
  #426 = Utf8               (Ljava/lang/Object;)I
  #427 = NameAndType        #425:#426     // unboxToInt:(Ljava/lang/Object;)I
  #428 = Methodref          #424.#427     // scala/runtime/BoxesRunTime.unboxToInt:(Ljava/lang/Object;)I
  #429 = NameAndType        #280:#231     // apply:(I)Ljava/lang/Object;
  #430 = Methodref          #2.#429       // scala/collection/convert/JavaCollectionWrappers$JListWrapper.apply:(I)Ljava/lang/Object;
  #431 = Utf8               $anonfun$insertAll$1
  #432 = Utf8               (Ljava/util/List;Ljava/lang/Object;)Z
  #433 = Utf8               ins$1
  #434 = Utf8               (Ljava/util/List<TA;>;)V
  #435 = NameAndType        #270:#342     // "<init>":()V
  #436 = Methodref          #5.#435       // scala/collection/mutable/AbstractBuffer."<init>":()V
  #437 = NameAndType        #431:#432     // $anonfun$insertAll$1:(Ljava/util/List;Ljava/lang/Object;)Z
  #438 = Methodref          #2.#437       // scala/collection/convert/JavaCollectionWrappers$JListWrapper.$anonfun$insertAll$1:(Ljava/util/List;Ljava/lang/Object;)Z
  #439 = Utf8               boxToBoolean
  #440 = Utf8               (Z)Ljava/lang/Boolean;
  #441 = NameAndType        #439:#440     // boxToBoolean:(Z)Ljava/lang/Boolean;
  #442 = Methodref          #424.#441     // scala/runtime/BoxesRunTime.boxToBoolean:(Z)Ljava/lang/Boolean;
  #443 = Utf8               $deserializeLambda$
  #444 = Utf8               (Ljava/lang/invoke/SerializedLambda;)Ljava/lang/Object;
  #445 = Utf8               scala/runtime/LambdaDeserialize
  #446 = Class              #445          // scala/runtime/LambdaDeserialize
  #447 = Utf8               bootstrap
  #448 = Utf8               (Ljava/lang/invoke/MethodHandles$Lookup;Ljava/lang/String;Ljava/lang/invoke/MethodType;[Ljava/lang/invoke/MethodHandle;)Ljava/lang/invoke/CallSite;
  #449 = NameAndType        #447:#448     // bootstrap:(Ljava/lang/invoke/MethodHandles$Lookup;Ljava/lang/String;Ljava/lang/invoke/MethodType;[Ljava/lang/invoke/MethodHandle;)Ljava/lang/invoke/CallSite;
  #450 = Methodref          #446.#449     // scala/runtime/LambdaDeserialize.bootstrap:(Ljava/lang/invoke/MethodHandles$Lookup;Ljava/lang/String;Ljava/lang/invoke/MethodType;[Ljava/lang/invoke/MethodHandle;)Ljava/lang/invoke/CallSite;
  #451 = MethodHandle       6:#450        // REF_invokeStatic scala/runtime/LambdaDeserialize.bootstrap:(Ljava/lang/invoke/MethodHandles$Lookup;Ljava/lang/String;Ljava/lang/invoke/MethodType;[Ljava/lang/invoke/MethodHandle;)Ljava/lang/invoke/CallSite;
  #452 = Utf8               lambdaDeserialize
  #453 = NameAndType        #452:#444     // lambdaDeserialize:(Ljava/lang/invoke/SerializedLambda;)Ljava/lang/Object;
  #454 = InvokeDynamic      #1:#453       // #1:lambdaDeserialize:(Ljava/lang/invoke/SerializedLambda;)Ljava/lang/Object;
  #455 = Utf8               ConstantValue
  #456 = Utf8               Signature
  #457 = Utf8               Code
  #458 = Utf8               LineNumberTable
  #459 = Utf8               LocalVariableTable
  #460 = Utf8               MethodParameters
  #461 = Utf8               StackMapTable
  #462 = Utf8               InnerClasses
  #463 = Utf8               SourceFile
  #464 = Utf8               BootstrapMethods
  #465 = Utf8               ScalaInlineInfo
  #466 = Utf8               Scala
{
  private static final long serialVersionUID;
    descriptor: J
    flags: (0x001a) ACC_PRIVATE, ACC_STATIC, ACC_FINAL
    ConstantValue: long 3l

  private final java.util.List<A> underlying;
    descriptor: Ljava/util/List;
    flags: (0x0012) ACC_PRIVATE, ACC_FINAL
    Signature: #34                          // Ljava/util/List<TA;>;

  public scala.collection.Iterator<java.lang.String> productElementNames();
    descriptor: ()Lscala/collection/Iterator;
    flags: (0x0001) ACC_PUBLIC
    Code:
      stack=1, locals=1, args_size=1
         0: aload_0
         1: invokestatic  #41                 // InterfaceMethod scala/Product.productElementNames$:(Lscala/Product;)Lscala/collection/Iterator;
         4: areturn
      LineNumberTable:
        line 103: 0
      LocalVariableTable:
        Start  Length  Slot  Name   Signature
            0       5     0  this   Lscala/collection/convert/JavaCollectionWrappers$JListWrapper;
    Signature: #37                          // ()Lscala/collection/Iterator<Ljava/lang/String;>;

  public java.lang.Object distinctBy(scala.Function1);
    descriptor: (Lscala/Function1;)Ljava/lang/Object;
    flags: (0x0001) ACC_PUBLIC
    Code:
      stack=2, locals=2, args_size=2
         0: aload_0
         1: aload_1
         2: invokestatic  #50                 // InterfaceMethod scala/collection/StrictOptimizedSeqOps.distinctBy$:(Lscala/collection/StrictOptimizedSeqOps;Lscala/Function1;)Ljava/lang/Object;
         5: areturn
      LineNumberTable:
        line 103: 0
      LocalVariableTable:
        Start  Length  Slot  Name   Signature
            0       6     0  this   Lscala/collection/convert/JavaCollectionWrappers$JListWrapper;
            0       6     1     f   Lscala/Function1;
    MethodParameters:
      Name                           Flags
      f                              final

  public java.lang.Object prepended(java.lang.Object);
    descriptor: (Ljava/lang/Object;)Ljava/lang/Object;
    flags: (0x0001) ACC_PUBLIC
    Code:
      stack=2, locals=2, args_size=2
         0: aload_0
         1: aload_1
         2: invokestatic  #58                 // InterfaceMethod scala/collection/StrictOptimizedSeqOps.prepended$:(Lscala/collection/StrictOptimizedSeqOps;Ljava/lang/Object;)Ljava/lang/Object;
         5: areturn
      LineNumberTable:
        line 103: 0
      LocalVariableTable:
        Start  Length  Slot  Name   Signature
            0       6     0  this   Lscala/collection/convert/JavaCollectionWrappers$JListWrapper;
            0       6     1  elem   Ljava/lang/Object;
    MethodParameters:
      Name                           Flags
      elem                           final

  public java.lang.Object appended(java.lang.Object);
    descriptor: (Ljava/lang/Object;)Ljava/lang/Object;
    flags: (0x0001) ACC_PUBLIC
    Code:
      stack=2, locals=2, args_size=2
         0: aload_0
         1: aload_1
         2: invokestatic  #63                 // InterfaceMethod scala/collection/StrictOptimizedSeqOps.appended$:(Lscala/collection/StrictOptimizedSeqOps;Ljava/lang/Object;)Ljava/lang/Object;
         5: areturn
      LineNumberTable:
        line 103: 0
      LocalVariableTable:
        Start  Length  Slot  Name   Signature
            0       6     0  this   Lscala/collection/convert/JavaCollectionWrappers$JListWrapper;
            0       6     1  elem   Ljava/lang/Object;
    MethodParameters:
      Name                           Flags
      elem                           final

  public java.lang.Object appendedAll(scala.collection.IterableOnce);
    descriptor: (Lscala/collection/IterableOnce;)Ljava/lang/Object;
    flags: (0x0001) ACC_PUBLIC
    Code:
      stack=2, locals=2, args_size=2
         0: aload_0
         1: aload_1
         2: invokestatic  #70                 // InterfaceMethod scala/collection/StrictOptimizedSeqOps.appendedAll$:(Lscala/collection/StrictOptimizedSeqOps;Lscala/collection/IterableOnce;)Ljava/lang/Object;
         5: areturn
      LineNumberTable:
        line 103: 0
      LocalVariableTable:
        Start  Length  Slot  Name   Signature
            0       6     0  this   Lscala/collection/convert/JavaCollectionWrappers$JListWrapper;
            0       6     1 suffix   Lscala/collection/IterableOnce;
    MethodParameters:
      Name                           Flags
      suffix                         final

  public java.lang.Object prependedAll(scala.collection.IterableOnce);
    descriptor: (Lscala/collection/IterableOnce;)Ljava/lang/Object;
    flags: (0x0001) ACC_PUBLIC
    Code:
      stack=2, locals=2, args_size=2
         0: aload_0
         1: aload_1
         2: invokestatic  #76                 // InterfaceMethod scala/collection/StrictOptimizedSeqOps.prependedAll$:(Lscala/collection/StrictOptimizedSeqOps;Lscala/collection/IterableOnce;)Ljava/lang/Object;
         5: areturn
      LineNumberTable:
        line 103: 0
      LocalVariableTable:
        Start  Length  Slot  Name   Signature
            0       6     0  this   Lscala/collection/convert/JavaCollectionWrappers$JListWrapper;
            0       6     1 prefix   Lscala/collection/IterableOnce;
    MethodParameters:
      Name                           Flags
      prefix                         final

  public java.lang.Object padTo(int, java.lang.Object);
    descriptor: (ILjava/lang/Object;)Ljava/lang/Object;
    flags: (0x0001) ACC_PUBLIC
    Code:
      stack=3, locals=3, args_size=3
         0: aload_0
         1: iload_1
         2: aload_2
         3: invokestatic  #83                 // InterfaceMethod scala/collection/StrictOptimizedSeqOps.padTo$:(Lscala/collection/StrictOptimizedSeqOps;ILjava/lang/Object;)Ljava/lang/Object;
         6: areturn
      LineNumberTable:
        line 103: 0
      LocalVariableTable:
        Start  Length  Slot  Name   Signature
            0       7     0  this   Lscala/collection/convert/JavaCollectionWrappers$JListWrapper;
            0       7     1   len   I
            0       7     2  elem   Ljava/lang/Object;
    MethodParameters:
      Name                           Flags
      len                            final
      elem                           final

  public java.lang.Object diff(scala.collection.Seq);
    descriptor: (Lscala/collection/Seq;)Ljava/lang/Object;
    flags: (0x0001) ACC_PUBLIC
    Code:
      stack=2, locals=2, args_size=2
         0: aload_0
         1: aload_1
         2: invokestatic  #91                 // InterfaceMethod scala/collection/StrictOptimizedSeqOps.diff$:(Lscala/collection/StrictOptimizedSeqOps;Lscala/collection/Seq;)Ljava/lang/Object;
         5: areturn
      LineNumberTable:
        line 103: 0
      LocalVariableTable:
        Start  Length  Slot  Name   Signature
            0       6     0  this   Lscala/collection/convert/JavaCollectionWrappers$JListWrapper;
            0       6     1  that   Lscala/collection/Seq;
    MethodParameters:
      Name                           Flags
      that                           final

  public java.lang.Object intersect(scala.collection.Seq);
    descriptor: (Lscala/collection/Seq;)Ljava/lang/Object;
    flags: (0x0001) ACC_PUBLIC
    Code:
      stack=2, locals=2, args_size=2
         0: aload_0
         1: aload_1
         2: invokestatic  #96                 // InterfaceMethod scala/collection/StrictOptimizedSeqOps.intersect$:(Lscala/collection/StrictOptimizedSeqOps;Lscala/collection/Seq;)Ljava/lang/Object;
         5: areturn
      LineNumberTable:
        line 103: 0
      LocalVariableTable:
        Start  Length  Slot  Name   Signature
            0       6     0  this   Lscala/collection/convert/JavaCollectionWrappers$JListWrapper;
            0       6     1  that   Lscala/collection/Seq;
    MethodParameters:
      Name                           Flags
      that                           final

  public scala.Tuple2<scala.collection.mutable.Buffer<A>, scala.collection.mutable.Buffer<A>> partition(scala.Function1<A, java.lang.Object>);
    descriptor: (Lscala/Function1;)Lscala/Tuple2;
    flags: (0x0001) ACC_PUBLIC
    Code:
      stack=2, locals=2, args_size=2
         0: aload_0
         1: aload_1
         2: invokestatic  #106                // InterfaceMethod scala/collection/StrictOptimizedIterableOps.partition$:(Lscala/collection/StrictOptimizedIterableOps;Lscala/Function1;)Lscala/Tuple2;
         5: areturn
      LineNumberTable:
        line 103: 0
      LocalVariableTable:
        Start  Length  Slot  Name   Signature
            0       6     0  this   Lscala/collection/convert/JavaCollectionWrappers$JListWrapper;
            0       6     1     p   Lscala/Function1;
    Signature: #99                          // (Lscala/Function1<TA;Ljava/lang/Object;>;)Lscala/Tuple2<Lscala/collection/mutable/Buffer<TA;>;Lscala/collection/mutable/Buffer<TA;>;>;
    MethodParameters:
      Name                           Flags
      p                              final

  public scala.Tuple2<scala.collection.mutable.Buffer<A>, scala.collection.mutable.Buffer<A>> span(scala.Function1<A, java.lang.Object>);
    descriptor: (Lscala/Function1;)Lscala/Tuple2;
    flags: (0x0001) ACC_PUBLIC
    Code:
      stack=2, locals=2, args_size=2
         0: aload_0
         1: aload_1
         2: invokestatic  #110                // InterfaceMethod scala/collection/StrictOptimizedIterableOps.span$:(Lscala/collection/StrictOptimizedIterableOps;Lscala/Function1;)Lscala/Tuple2;
         5: areturn
      LineNumberTable:
        line 103: 0
      LocalVariableTable:
        Start  Length  Slot  Name   Signature
            0       6     0  this   Lscala/collection/convert/JavaCollectionWrappers$JListWrapper;
            0       6     1     p   Lscala/Function1;
    Signature: #99                          // (Lscala/Function1<TA;Ljava/lang/Object;>;)Lscala/Tuple2<Lscala/collection/mutable/Buffer<TA;>;Lscala/collection/mutable/Buffer<TA;>;>;
    MethodParameters:
      Name                           Flags
      p                              final

  public <A1 extends java.lang.Object, A2 extends java.lang.Object> scala.Tuple2<scala.collection.mutable.Buffer<A1>, scala.collection.mutable.Buffer<A2>> unzip(scala.Function1<A, scala.Tuple2<A1, A2>>);
    descriptor: (Lscala/Function1;)Lscala/Tuple2;
    flags: (0x0001) ACC_PUBLIC
    Code:
      stack=2, locals=2, args_size=2
         0: aload_0
         1: aload_1
         2: invokestatic  #116                // InterfaceMethod scala/collection/StrictOptimizedIterableOps.unzip$:(Lscala/collection/StrictOptimizedIterableOps;Lscala/Function1;)Lscala/Tuple2;
         5: areturn
      LineNumberTable:
        line 103: 0
      LocalVariableTable:
        Start  Length  Slot  Name   Signature
            0       6     0  this   Lscala/collection/convert/JavaCollectionWrappers$JListWrapper;
            0       6     1 asPair   Lscala/Function1;
    Signature: #112                         // <A1:Ljava/lang/Object;A2:Ljava/lang/Object;>(Lscala/Function1<TA;Lscala/Tuple2<TA1;TA2;>;>;)Lscala/Tuple2<Lscala/collection/mutable/Buffer<TA1;>;Lscala/collection/mutable/Buffer<TA2;>;>;
    MethodParameters:
      Name                           Flags
      asPair                         final

  public <A1 extends java.lang.Object, A2 extends java.lang.Object, A3 extends java.lang.Object> scala.Tuple3<scala.collection.mutable.Buffer<A1>, scala.collection.mutable.Buffer<A2>, scala.collection.mutable.Buffer<A3>> unzip3(scala.Function1<A, scala.Tuple3<A1, A2, A3>>);
    descriptor: (Lscala/Function1;)Lscala/Tuple3;
    flags: (0x0001) ACC_PUBLIC
    Code:
      stack=2, locals=2, args_size=2
         0: aload_0
         1: aload_1
         2: invokestatic  #124                // InterfaceMethod scala/collection/StrictOptimizedIterableOps.unzip3$:(Lscala/collection/StrictOptimizedIterableOps;Lscala/Function1;)Lscala/Tuple3;
         5: areturn
      LineNumberTable:
        line 103: 0
      LocalVariableTable:
        Start  Length  Slot  Name   Signature
            0       6     0  this   Lscala/collection/convert/JavaCollectionWrappers$JListWrapper;
            0       6     1 asTriple   Lscala/Function1;
    Signature: #119                         // <A1:Ljava/lang/Object;A2:Ljava/lang/Object;A3:Ljava/lang/Object;>(Lscala/Function1<TA;Lscala/Tuple3<TA1;TA2;TA3;>;>;)Lscala/Tuple3<Lscala/collection/mutable/Buffer<TA1;>;Lscala/collection/mutable/Buffer<TA2;>;Lscala/collection/mutable/Buffer<TA3;>;>;
    MethodParameters:
      Name                           Flags
      asTriple                       final

  public java.lang.Object map(scala.Function1);
    descriptor: (Lscala/Function1;)Ljava/lang/Object;
    flags: (0x0001) ACC_PUBLIC
    Code:
      stack=2, locals=2, args_size=2
         0: aload_0
         1: aload_1
         2: invokestatic  #129                // InterfaceMethod scala/collection/StrictOptimizedIterableOps.map$:(Lscala/collection/StrictOptimizedIterableOps;Lscala/Function1;)Ljava/lang/Object;
         5: areturn
      LineNumberTable:
        line 103: 0
      LocalVariableTable:
        Start  Length  Slot  Name   Signature
            0       6     0  this   Lscala/collection/convert/JavaCollectionWrappers$JListWrapper;
            0       6     1     f   Lscala/Function1;
    MethodParameters:
      Name                           Flags
      f                              final

  public final <B extends java.lang.Object, C2 extends java.lang.Object> C2 strictOptimizedMap(scala.collection.mutable.Builder<B, C2>, scala.Function1<A, B>);
    descriptor: (Lscala/collection/mutable/Builder;Lscala/Function1;)Ljava/lang/Object;
    flags: (0x0011) ACC_PUBLIC, ACC_FINAL
    Code:
      stack=3, locals=3, args_size=3
         0: aload_0
         1: aload_1
         2: aload_2
         3: invokestatic  #137                // InterfaceMethod scala/collection/StrictOptimizedIterableOps.strictOptimizedMap$:(Lscala/collection/StrictOptimizedIterableOps;Lscala/collection/mutable/Builder;Lscala/Function1;)Ljava/lang/Object;
         6: areturn
      LineNumberTable:
        line 103: 0
      LocalVariableTable:
        Start  Length  Slot  Name   Signature
            0       7     0  this   Lscala/collection/convert/JavaCollectionWrappers$JListWrapper;
            0       7     1     b   Lscala/collection/mutable/Builder;
            0       7     2     f   Lscala/Function1;
    Signature: #132                         // <B:Ljava/lang/Object;C2:Ljava/lang/Object;>(Lscala/collection/mutable/Builder<TB;TC2;>;Lscala/Function1<TA;TB;>;)TC2;
    MethodParameters:
      Name                           Flags
      b                              final
      f                              final

  public java.lang.Object flatMap(scala.Function1);
    descriptor: (Lscala/Function1;)Ljava/lang/Object;
    flags: (0x0001) ACC_PUBLIC
    Code:
      stack=2, locals=2, args_size=2
         0: aload_0
         1: aload_1
         2: invokestatic  #142                // InterfaceMethod scala/collection/StrictOptimizedIterableOps.flatMap$:(Lscala/collection/StrictOptimizedIterableOps;Lscala/Function1;)Ljava/lang/Object;
         5: areturn
      LineNumberTable:
        line 103: 0
      LocalVariableTable:
        Start  Length  Slot  Name   Signature
            0       6     0  this   Lscala/collection/convert/JavaCollectionWrappers$JListWrapper;
            0       6     1     f   Lscala/Function1;
    MethodParameters:
      Name                           Flags
      f                              final

  public final <B extends java.lang.Object, C2 extends java.lang.Object> C2 strictOptimizedFlatMap(scala.collection.mutable.Builder<B, C2>, scala.Function1<A, scala.collection.IterableOnce<B>>);
    descriptor: (Lscala/collection/mutable/Builder;Lscala/Function1;)Ljava/lang/Object;
    flags: (0x0011) ACC_PUBLIC, ACC_FINAL
    Code:
      stack=3, locals=3, args_size=3
         0: aload_0
         1: aload_1
         2: aload_2
         3: invokestatic  #147                // InterfaceMethod scala/collection/StrictOptimizedIterableOps.strictOptimizedFlatMap$:(Lscala/collection/StrictOptimizedIterableOps;Lscala/collection/mutable/Builder;Lscala/Function1;)Ljava/lang/Object;
         6: areturn
      LineNumberTable:
        line 103: 0
      LocalVariableTable:
        Start  Length  Slot  Name   Signature
            0       7     0  this   Lscala/collection/convert/JavaCollectionWrappers$JListWrapper;
            0       7     1     b   Lscala/collection/mutable/Builder;
            0       7     2     f   Lscala/Function1;
    Signature: #144                         // <B:Ljava/lang/Object;C2:Ljava/lang/Object;>(Lscala/collection/mutable/Builder<TB;TC2;>;Lscala/Function1<TA;Lscala/collection/IterableOnce<TB;>;>;)TC2;
    MethodParameters:
      Name                           Flags
      b                              final
      f                              final

  public final <B extends java.lang.Object, C2 extends java.lang.Object> C2 strictOptimizedConcat(scala.collection.IterableOnce<B>, scala.collection.mutable.Builder<B, C2>);
    descriptor: (Lscala/collection/IterableOnce;Lscala/collection/mutable/Builder;)Ljava/lang/Object;
    flags: (0x0011) ACC_PUBLIC, ACC_FINAL
    Code:
      stack=3, locals=3, args_size=3
         0: aload_0
         1: aload_1
         2: aload_2
         3: invokestatic  #154                // InterfaceMethod scala/collection/StrictOptimizedIterableOps.strictOptimizedConcat$:(Lscala/collection/StrictOptimizedIterableOps;Lscala/collection/IterableOnce;Lscala/collection/mutable/Builder;)Ljava/lang/Object;
         6: areturn
      LineNumberTable:
        line 103: 0
      LocalVariableTable:
        Start  Length  Slot  Name   Signature
            0       7     0  this   Lscala/collection/convert/JavaCollectionWrappers$JListWrapper;
            0       7     1  that   Lscala/collection/IterableOnce;
            0       7     2     b   Lscala/collection/mutable/Builder;
    Signature: #150                         // <B:Ljava/lang/Object;C2:Ljava/lang/Object;>(Lscala/collection/IterableOnce<TB;>;Lscala/collection/mutable/Builder<TB;TC2;>;)TC2;
    MethodParameters:
      Name                           Flags
      that                           final
      b                              final

  public java.lang.Object collect(scala.PartialFunction);
    descriptor: (Lscala/PartialFunction;)Ljava/lang/Object;
    flags: (0x0001) ACC_PUBLIC
    Code:
      stack=2, locals=2, args_size=2
         0: aload_0
         1: aload_1
         2: invokestatic  #161                // InterfaceMethod scala/collection/StrictOptimizedIterableOps.collect$:(Lscala/collection/StrictOptimizedIterableOps;Lscala/PartialFunction;)Ljava/lang/Object;
         5: areturn
      LineNumberTable:
        line 103: 0
      LocalVariableTable:
        Start  Length  Slot  Name   Signature
            0       6     0  this   Lscala/collection/convert/JavaCollectionWrappers$JListWrapper;
            0       6     1    pf   Lscala/PartialFunction;
    MethodParameters:
      Name                           Flags
      pf                             final

  public final <B extends java.lang.Object, C2 extends java.lang.Object> C2 strictOptimizedCollect(scala.collection.mutable.Builder<B, C2>, scala.PartialFunction<A, B>);
    descriptor: (Lscala/collection/mutable/Builder;Lscala/PartialFunction;)Ljava/lang/Object;
    flags: (0x0011) ACC_PUBLIC, ACC_FINAL
    Code:
      stack=3, locals=3, args_size=3
         0: aload_0
         1: aload_1
         2: aload_2
         3: invokestatic  #169                // InterfaceMethod scala/collection/StrictOptimizedIterableOps.strictOptimizedCollect$:(Lscala/collection/StrictOptimizedIterableOps;Lscala/collection/mutable/Builder;Lscala/PartialFunction;)Ljava/lang/Object;
         6: areturn
      LineNumberTable:
        line 103: 0
      LocalVariableTable:
        Start  Length  Slot  Name   Signature
            0       7     0  this   Lscala/collection/convert/JavaCollectionWrappers$JListWrapper;
            0       7     1     b   Lscala/collection/mutable/Builder;
            0       7     2    pf   Lscala/PartialFunction;
    Signature: #165                         // <B:Ljava/lang/Object;C2:Ljava/lang/Object;>(Lscala/collection/mutable/Builder<TB;TC2;>;Lscala/PartialFunction<TA;TB;>;)TC2;
    MethodParameters:
      Name                           Flags
      b                              final
      pf                             final

  public java.lang.Object flatten(scala.Function1);
    descriptor: (Lscala/Function1;)Ljava/lang/Object;
    flags: (0x0001) ACC_PUBLIC
    Code:
      stack=2, locals=2, args_size=2
         0: aload_0
         1: aload_1
         2: invokestatic  #174                // InterfaceMethod scala/collection/StrictOptimizedIterableOps.flatten$:(Lscala/collection/StrictOptimizedIterableOps;Lscala/Function1;)Ljava/lang/Object;
         5: areturn
      LineNumberTable:
        line 103: 0
      LocalVariableTable:
        Start  Length  Slot  Name   Signature
            0       6     0  this   Lscala/collection/convert/JavaCollectionWrappers$JListWrapper;
            0       6     1 toIterableOnce   Lscala/Function1;
    MethodParameters:
      Name                           Flags
      toIterableOnce                 final

  public final <B extends java.lang.Object, C2 extends java.lang.Object> C2 strictOptimizedFlatten(scala.collection.mutable.Builder<B, C2>, scala.Function1<A, scala.collection.IterableOnce<B>>);
    descriptor: (Lscala/collection/mutable/Builder;Lscala/Function1;)Ljava/lang/Object;
    flags: (0x0011) ACC_PUBLIC, ACC_FINAL
    Code:
      stack=3, locals=3, args_size=3
         0: aload_0
         1: aload_1
         2: aload_2
         3: invokestatic  #178                // InterfaceMethod scala/collection/StrictOptimizedIterableOps.strictOptimizedFlatten$:(Lscala/collection/StrictOptimizedIterableOps;Lscala/collection/mutable/Builder;Lscala/Function1;)Ljava/lang/Object;
         6: areturn
      LineNumberTable:
        line 103: 0
      LocalVariableTable:
        Start  Length  Slot  Name   Signature
            0       7     0  this   Lscala/collection/convert/JavaCollectionWrappers$JListWrapper;
            0       7     1     b   Lscala/collection/mutable/Builder;
            0       7     2 toIterableOnce   Lscala/Function1;
    Signature: #144                         // <B:Ljava/lang/Object;C2:Ljava/lang/Object;>(Lscala/collection/mutable/Builder<TB;TC2;>;Lscala/Function1<TA;Lscala/collection/IterableOnce<TB;>;>;)TC2;
    MethodParameters:
      Name                           Flags
      b                              final
      toIterableOnce                 final

  public java.lang.Object zip(scala.collection.IterableOnce);
    descriptor: (Lscala/collection/IterableOnce;)Ljava/lang/Object;
    flags: (0x0001) ACC_PUBLIC
    Code:
      stack=2, locals=2, args_size=2
         0: aload_0
         1: aload_1
         2: invokestatic  #183                // InterfaceMethod scala/collection/StrictOptimizedIterableOps.zip$:(Lscala/collection/StrictOptimizedIterableOps;Lscala/collection/IterableOnce;)Ljava/lang/Object;
         5: areturn
      LineNumberTable:
        line 103: 0
      LocalVariableTable:
        Start  Length  Slot  Name   Signature
            0       6     0  this   Lscala/collection/convert/JavaCollectionWrappers$JListWrapper;
            0       6     1  that   Lscala/collection/IterableOnce;
    MethodParameters:
      Name                           Flags
      that                           final

  public final <B extends java.lang.Object, C2 extends java.lang.Object> C2 strictOptimizedZip(scala.collection.IterableOnce<B>, scala.collection.mutable.Builder<scala.Tuple2<A, B>, C2>);
    descriptor: (Lscala/collection/IterableOnce;Lscala/collection/mutable/Builder;)Ljava/lang/Object;
    flags: (0x0011) ACC_PUBLIC, ACC_FINAL
    Code:
      stack=3, locals=3, args_size=3
         0: aload_0
         1: aload_1
         2: aload_2
         3: invokestatic  #188                // InterfaceMethod scala/collection/StrictOptimizedIterableOps.strictOptimizedZip$:(Lscala/collection/StrictOptimizedIterableOps;Lscala/collection/IterableOnce;Lscala/collection/mutable/Builder;)Ljava/lang/Object;
         6: areturn
      LineNumberTable:
        line 103: 0
      LocalVariableTable:
        Start  Length  Slot  Name   Signature
            0       7     0  this   Lscala/collection/convert/JavaCollectionWrappers$JListWrapper;
            0       7     1  that   Lscala/collection/IterableOnce;
            0       7     2     b   Lscala/collection/mutable/Builder;
    Signature: #185                         // <B:Ljava/lang/Object;C2:Ljava/lang/Object;>(Lscala/collection/IterableOnce<TB;>;Lscala/collection/mutable/Builder<Lscala/Tuple2<TA;TB;>;TC2;>;)TC2;
    MethodParameters:
      Name                           Flags
      that                           final
      b                              final

  public java.lang.Object zipWithIndex();
    descriptor: ()Ljava/lang/Object;
    flags: (0x0001) ACC_PUBLIC
    Code:
      stack=1, locals=1, args_size=1
         0: aload_0
         1: invokestatic  #194                // InterfaceMethod scala/collection/StrictOptimizedIterableOps.zipWithIndex$:(Lscala/collection/StrictOptimizedIterableOps;)Ljava/lang/Object;
         4: areturn
      LineNumberTable:
        line 103: 0
      LocalVariableTable:
        Start  Length  Slot  Name   Signature
            0       5     0  this   Lscala/collection/convert/JavaCollectionWrappers$JListWrapper;

  public java.lang.Object scanLeft(java.lang.Object, scala.Function2);
    descriptor: (Ljava/lang/Object;Lscala/Function2;)Ljava/lang/Object;
    flags: (0x0001) ACC_PUBLIC
    Code:
      stack=3, locals=3, args_size=3
         0: aload_0
         1: aload_1
         2: aload_2
         3: invokestatic  #202                // InterfaceMethod scala/collection/StrictOptimizedIterableOps.scanLeft$:(Lscala/collection/StrictOptimizedIterableOps;Ljava/lang/Object;Lscala/Function2;)Ljava/lang/Object;
         6: areturn
      LineNumberTable:
        line 103: 0
      LocalVariableTable:
        Start  Length  Slot  Name   Signature
            0       7     0  this   Lscala/collection/convert/JavaCollectionWrappers$JListWrapper;
            0       7     1     z   Ljava/lang/Object;
            0       7     2    op   Lscala/Function2;
    MethodParameters:
      Name                           Flags
      z                              final
      op                             final

  public java.lang.Object filter(scala.Function1);
    descriptor: (Lscala/Function1;)Ljava/lang/Object;
    flags: (0x0001) ACC_PUBLIC
    Code:
      stack=2, locals=2, args_size=2
         0: aload_0
         1: aload_1
         2: invokestatic  #208                // InterfaceMethod scala/collection/StrictOptimizedIterableOps.filter$:(Lscala/collection/StrictOptimizedIterableOps;Lscala/Function1;)Ljava/lang/Object;
         5: areturn
      LineNumberTable:
        line 103: 0
      LocalVariableTable:
        Start  Length  Slot  Name   Signature
            0       6     0  this   Lscala/collection/convert/JavaCollectionWrappers$JListWrapper;
            0       6     1  pred   Lscala/Function1;
    MethodParameters:
      Name                           Flags
      pred                           final

  public java.lang.Object filterNot(scala.Function1);
    descriptor: (Lscala/Function1;)Ljava/lang/Object;
    flags: (0x0001) ACC_PUBLIC
    Code:
      stack=2, locals=2, args_size=2
         0: aload_0
         1: aload_1
         2: invokestatic  #212                // InterfaceMethod scala/collection/StrictOptimizedIterableOps.filterNot$:(Lscala/collection/StrictOptimizedIterableOps;Lscala/Function1;)Ljava/lang/Object;
         5: areturn
      LineNumberTable:
        line 103: 0
      LocalVariableTable:
        Start  Length  Slot  Name   Signature
            0       6     0  this   Lscala/collection/convert/JavaCollectionWrappers$JListWrapper;
            0       6     1  pred   Lscala/Function1;
    MethodParameters:
      Name                           Flags
      pred                           final

  public java.lang.Object filterImpl(scala.Function1, boolean);
    descriptor: (Lscala/Function1;Z)Ljava/lang/Object;
    flags: (0x0001) ACC_PUBLIC
    Code:
      stack=3, locals=3, args_size=3
         0: aload_0
         1: aload_1
         2: iload_2
         3: invokestatic  #219                // InterfaceMethod scala/collection/StrictOptimizedIterableOps.filterImpl$:(Lscala/collection/StrictOptimizedIterableOps;Lscala/Function1;Z)Ljava/lang/Object;
         6: areturn
      LineNumberTable:
        line 103: 0
      LocalVariableTable:
        Start  Length  Slot  Name   Signature
            0       7     0  this   Lscala/collection/convert/JavaCollectionWrappers$JListWrapper;
            0       7     1  pred   Lscala/Function1;
            0       7     2 isFlipped   Z
    MethodParameters:
      Name                           Flags
      pred                           final
      isFlipped                      final

  public <A1 extends java.lang.Object, A2 extends java.lang.Object> scala.Tuple2<scala.collection.mutable.Buffer<A1>, scala.collection.mutable.Buffer<A2>> partitionMap(scala.Function1<A, scala.util.Either<A1, A2>>);
    descriptor: (Lscala/Function1;)Lscala/Tuple2;
    flags: (0x0001) ACC_PUBLIC
    Code:
      stack=2, locals=2, args_size=2
         0: aload_0
         1: aload_1
         2: invokestatic  #225                // InterfaceMethod scala/collection/StrictOptimizedIterableOps.partitionMap$:(Lscala/collection/StrictOptimizedIterableOps;Lscala/Function1;)Lscala/Tuple2;
         5: areturn
      LineNumberTable:
        line 103: 0
      LocalVariableTable:
        Start  Length  Slot  Name   Signature
            0       6     0  this   Lscala/collection/convert/JavaCollectionWrappers$JListWrapper;
            0       6     1     f   Lscala/Function1;
    Signature: #222                         // <A1:Ljava/lang/Object;A2:Ljava/lang/Object;>(Lscala/Function1<TA;Lscala/util/Either<TA1;TA2;>;>;)Lscala/Tuple2<Lscala/collection/mutable/Buffer<TA1;>;Lscala/collection/mutable/Buffer<TA2;>;>;
    MethodParameters:
      Name                           Flags
      f                              final

  public java.lang.Object tapEach(scala.Function1);
    descriptor: (Lscala/Function1;)Ljava/lang/Object;
    flags: (0x0001) ACC_PUBLIC
    Code:
      stack=2, locals=2, args_size=2
         0: aload_0
         1: aload_1
         2: invokestatic  #229                // InterfaceMethod scala/collection/StrictOptimizedIterableOps.tapEach$:(Lscala/collection/StrictOptimizedIterableOps;Lscala/Function1;)Ljava/lang/Object;
         5: areturn
      LineNumberTable:
        line 103: 0
      LocalVariableTable:
        Start  Length  Slot  Name   Signature
            0       6     0  this   Lscala/collection/convert/JavaCollectionWrappers$JListWrapper;
            0       6     1     f   Lscala/Function1;
    MethodParameters:
      Name                           Flags
      f                              final

  public java.lang.Object takeRight(int);
    descriptor: (I)Ljava/lang/Object;
    flags: (0x0001) ACC_PUBLIC
    Code:
      stack=2, locals=2, args_size=2
         0: aload_0
         1: iload_1
         2: invokestatic  #236                // InterfaceMethod scala/collection/StrictOptimizedIterableOps.takeRight$:(Lscala/collection/StrictOptimizedIterableOps;I)Ljava/lang/Object;
         5: areturn
      LineNumberTable:
        line 103: 0
      LocalVariableTable:
        Start  Length  Slot  Name   Signature
            0       6     0  this   Lscala/collection/convert/JavaCollectionWrappers$JListWrapper;
            0       6     1     n   I
    MethodParameters:
      Name                           Flags
      n                              final

  public java.lang.Object dropRight(int);
    descriptor: (I)Ljava/lang/Object;
    flags: (0x0001) ACC_PUBLIC
    Code:
      stack=2, locals=2, args_size=2
         0: aload_0
         1: iload_1
         2: invokestatic  #240                // InterfaceMethod scala/collection/StrictOptimizedIterableOps.dropRight$:(Lscala/collection/StrictOptimizedIterableOps;I)Ljava/lang/Object;
         5: areturn
      LineNumberTable:
        line 103: 0
      LocalVariableTable:
        Start  Length  Slot  Name   Signature
            0       6     0  this   Lscala/collection/convert/JavaCollectionWrappers$JListWrapper;
            0       6     1     n   I
    MethodParameters:
      Name                           Flags
      n                              final

  public java.util.List<A> underlying();
    descriptor: ()Ljava/util/List;
    flags: (0x0001) ACC_PUBLIC
    Code:
      stack=1, locals=1, args_size=1
         0: aload_0
         1: getfield      #244                // Field underlying:Ljava/util/List;
         4: areturn
      LineNumberTable:
        line 103: 0
      LocalVariableTable:
        Start  Length  Slot  Name   Signature
            0       5     0  this   Lscala/collection/convert/JavaCollectionWrappers$JListWrapper;
    Signature: #242                         // ()Ljava/util/List<TA;>;

  public int length();
    descriptor: ()I
    flags: (0x0001) ACC_PUBLIC
    Code:
      stack=1, locals=1, args_size=1
         0: aload_0
         1: invokevirtual #248                // Method underlying:()Ljava/util/List;
         4: invokeinterface #253,  1          // InterfaceMethod java/util/List.size:()I
         9: ireturn
      LineNumberTable:
        line 109: 0
      LocalVariableTable:
        Start  Length  Slot  Name   Signature
            0      10     0  this   Lscala/collection/convert/JavaCollectionWrappers$JListWrapper;

  public int knownSize();
    descriptor: ()I
    flags: (0x0001) ACC_PUBLIC
    Code:
      stack=1, locals=1, args_size=1
         0: aload_0
         1: invokevirtual #248                // Method underlying:()Ljava/util/List;
         4: invokeinterface #258,  1          // InterfaceMethod java/util/List.isEmpty:()Z
         9: ifeq          14
        12: iconst_0
        13: ireturn
        14: iconst_m1
        15: ireturn
      StackMapTable: number_of_entries = 1
        frame_type = 14 /* same */
      LineNumberTable:
        line 110: 0
      LocalVariableTable:
        Start  Length  Slot  Name   Signature
            0      16     0  this   Lscala/collection/convert/JavaCollectionWrappers$JListWrapper;

  public boolean isEmpty();
    descriptor: ()Z
    flags: (0x0001) ACC_PUBLIC
    Code:
      stack=1, locals=1, args_size=1
         0: aload_0
         1: invokevirtual #248                // Method underlying:()Ljava/util/List;
         4: invokeinterface #258,  1          // InterfaceMethod java/util/List.isEmpty:()Z
         9: ireturn
      LineNumberTable:
        line 111: 0
      LocalVariableTable:
        Start  Length  Slot  Name   Signature
            0      10     0  this   Lscala/collection/convert/JavaCollectionWrappers$JListWrapper;

  public scala.collection.Iterator<A> iterator();
    descriptor: ()Lscala/collection/Iterator;
    flags: (0x0001) ACC_PUBLIC
    Code:
      stack=4, locals=3, args_size=1
         0: getstatic     #266                // Field scala/jdk/CollectionConverters$.MODULE$:Lscala/jdk/CollectionConverters$;
         3: aload_0
         4: invokevirtual #248                // Method underlying:()Ljava/util/List;
         7: invokeinterface #269,  1          // InterfaceMethod java/util/List.iterator:()Ljava/util/Iterator;
        12: astore_2
        13: astore_1
        14: new           #19                 // class scala/collection/convert/AsScalaExtensions$IteratorHasAsScala
        17: dup
        18: aload_1
        19: aload_2
        20: invokespecial #273                // Method scala/collection/convert/AsScalaExtensions$IteratorHasAsScala."<init>":(Lscala/collection/convert/AsScalaExtensions;Ljava/util/Iterator;)V
        23: aconst_null
        24: astore_1
        25: aconst_null
        26: astore_2
        27: invokevirtual #276                // Method scala/collection/convert/AsScalaExtensions$IteratorHasAsScala.asScala:()Lscala/collection/Iterator;
        30: areturn
      LineNumberTable:
        line 112: 0
      LocalVariableTable:
        Start  Length  Slot  Name   Signature
            0      31     0  this   Lscala/collection/convert/JavaCollectionWrappers$JListWrapper;
           14       9     1 IteratorHasAsScala_this   Lscala/jdk/CollectionConverters$;
           14       9     2 IteratorHasAsScala_i   Ljava/util/Iterator;
    Signature: #260                         // ()Lscala/collection/Iterator<TA;>;

  public A apply(int);
    descriptor: (I)Ljava/lang/Object;
    flags: (0x0001) ACC_PUBLIC
    Code:
      stack=2, locals=2, args_size=2
         0: aload_0
         1: invokevirtual #248                // Method underlying:()Ljava/util/List;
         4: iload_1
         5: invokeinterface #285,  2          // InterfaceMethod java/util/List.get:(I)Ljava/lang/Object;
        10: areturn
      LineNumberTable:
        line 113: 0
      LocalVariableTable:
        Start  Length  Slot  Name   Signature
            0      11     0  this   Lscala/collection/convert/JavaCollectionWrappers$JListWrapper;
            0      11     1     i   I
    Signature: #281                         // (I)TA;
    MethodParameters:
      Name                           Flags
      i                              final

  public void update(int, A);
    descriptor: (ILjava/lang/Object;)V
    flags: (0x0001) ACC_PUBLIC
    Code:
      stack=3, locals=3, args_size=3
         0: aload_0
         1: invokevirtual #248                // Method underlying:()Ljava/util/List;
         4: iload_1
         5: aload_2
         6: invokeinterface #291,  3          // InterfaceMethod java/util/List.set:(ILjava/lang/Object;)Ljava/lang/Object;
        11: pop
        12: return
      LineNumberTable:
        line 114: 0
      LocalVariableTable:
        Start  Length  Slot  Name   Signature
            0      13     0  this   Lscala/collection/convert/JavaCollectionWrappers$JListWrapper;
            0      13     1     i   I
            0      13     2  elem   Ljava/lang/Object;
    Signature: #288                         // (ITA;)V
    MethodParameters:
      Name                           Flags
      i                              final
      elem                           final

  public scala.collection.convert.JavaCollectionWrappers$JListWrapper<A> prepend(A);
    descriptor: (Ljava/lang/Object;)Lscala/collection/convert/JavaCollectionWrappers$JListWrapper;
    flags: (0x0001) ACC_PUBLIC
    Code:
      stack=3, locals=2, args_size=2
         0: aload_0
         1: invokevirtual #248                // Method underlying:()Ljava/util/List;
         4: iconst_0
         5: iconst_0
         6: invokeinterface #298,  3          // InterfaceMethod java/util/List.subList:(II)Ljava/util/List;
        11: aload_1
        12: invokeinterface #302,  2          // InterfaceMethod java/util/List.add:(Ljava/lang/Object;)Z
        17: pop
        18: aload_0
        19: areturn
      LineNumberTable:
        line 115: 0
      LocalVariableTable:
        Start  Length  Slot  Name   Signature
            0      20     0  this   Lscala/collection/convert/JavaCollectionWrappers$JListWrapper;
            0      20     1  elem   Ljava/lang/Object;
    Signature: #294                         // (TA;)Lscala/collection/convert/JavaCollectionWrappers$JListWrapper<TA;>;
    MethodParameters:
      Name                           Flags
      elem                           final

  public scala.collection.convert.JavaCollectionWrappers$JListWrapper<A> addOne(A);
    descriptor: (Ljava/lang/Object;)Lscala/collection/convert/JavaCollectionWrappers$JListWrapper;
    flags: (0x0001) ACC_PUBLIC
    Code:
      stack=2, locals=2, args_size=2
         0: aload_0
         1: invokevirtual #248                // Method underlying:()Ljava/util/List;
         4: aload_1
         5: invokeinterface #302,  2          // InterfaceMethod java/util/List.add:(Ljava/lang/Object;)Z
        10: pop
        11: aload_0
        12: areturn
      LineNumberTable:
        line 116: 0
      LocalVariableTable:
        Start  Length  Slot  Name   Signature
            0      13     0  this   Lscala/collection/convert/JavaCollectionWrappers$JListWrapper;
            0      13     1  elem   Ljava/lang/Object;
    Signature: #294                         // (TA;)Lscala/collection/convert/JavaCollectionWrappers$JListWrapper<TA;>;
    MethodParameters:
      Name                           Flags
      elem                           final

  public void insert(int, A);
    descriptor: (ILjava/lang/Object;)V
    flags: (0x0001) ACC_PUBLIC
    Code:
      stack=3, locals=3, args_size=3
         0: aload_0
         1: invokevirtual #248                // Method underlying:()Ljava/util/List;
         4: iconst_0
         5: iload_1
         6: invokeinterface #298,  3          // InterfaceMethod java/util/List.subList:(II)Ljava/util/List;
        11: aload_2
        12: invokeinterface #302,  2          // InterfaceMethod java/util/List.add:(Ljava/lang/Object;)Z
        17: pop
        18: return
      LineNumberTable:
        line 117: 0
      LocalVariableTable:
        Start  Length  Slot  Name   Signature
            0      19     0  this   Lscala/collection/convert/JavaCollectionWrappers$JListWrapper;
            0      19     1   idx   I
            0      19     2  elem   Ljava/lang/Object;
    Signature: #288                         // (ITA;)V
    MethodParameters:
      Name                           Flags
      idx                            final
      elem                           final

  public void insertAll(int, scala.collection.IterableOnce<A>);
    descriptor: (ILscala/collection/IterableOnce;)V
    flags: (0x0001) ACC_PUBLIC
    Code:
      stack=3, locals=4, args_size=3
         0: aload_0
         1: invokevirtual #248                // Method underlying:()Ljava/util/List;
         4: iconst_0
         5: iload_1
         6: invokeinterface #298,  3          // InterfaceMethod java/util/List.subList:(II)Ljava/util/List;
        11: astore_3
        12: aload_2
        13: invokeinterface #313,  1          // InterfaceMethod scala/collection/IterableOnce.iterator:()Lscala/collection/Iterator;
        18: aload_3
        19: invokedynamic #330,  0            // InvokeDynamic #0:apply:(Ljava/util/List;)Lscala/Function1;
        24: invokeinterface #336,  2          // InterfaceMethod scala/collection/Iterator.foreach:(Lscala/Function1;)V
        29: return
      LineNumberTable:
        line 119: 0
        line 120: 12
      LocalVariableTable:
        Start  Length  Slot  Name   Signature
           12      17     3   ins   Ljava/util/List;
            0      30     0  this   Lscala/collection/convert/JavaCollectionWrappers$JListWrapper;
            0      30     1     i   I
            0      30     2 elems   Lscala/collection/IterableOnce;
    Signature: #308                         // (ILscala/collection/IterableOnce<TA;>;)V
    MethodParameters:
      Name                           Flags
      i                              final
      elems                          final

  public A remove(int);
    descriptor: (I)Ljava/lang/Object;
    flags: (0x0001) ACC_PUBLIC
    Code:
      stack=2, locals=2, args_size=2
         0: aload_0
         1: invokevirtual #248                // Method underlying:()Ljava/util/List;
         4: iload_1
         5: invokeinterface #340,  2          // InterfaceMethod java/util/List.remove:(I)Ljava/lang/Object;
        10: areturn
      LineNumberTable:
        line 122: 0
      LocalVariableTable:
        Start  Length  Slot  Name   Signature
            0      11     0  this   Lscala/collection/convert/JavaCollectionWrappers$JListWrapper;
            0      11     1     i   I
    Signature: #281                         // (I)TA;
    MethodParameters:
      Name                           Flags
      i                              final

  public void clear();
    descriptor: ()V
    flags: (0x0001) ACC_PUBLIC
    Code:
      stack=1, locals=1, args_size=1
         0: aload_0
         1: invokevirtual #248                // Method underlying:()Ljava/util/List;
         4: invokeinterface #344,  1          // InterfaceMethod java/util/List.clear:()V
         9: return
      LineNumberTable:
        line 123: 0
      LocalVariableTable:
        Start  Length  Slot  Name   Signature
            0      10     0  this   Lscala/collection/convert/JavaCollectionWrappers$JListWrapper;

  public scala.collection.convert.JavaCollectionWrappers$JListWrapper<A> clone();
    descriptor: ()Lscala/collection/convert/JavaCollectionWrappers$JListWrapper;
    flags: (0x0001) ACC_PUBLIC
    Code:
      stack=5, locals=1, args_size=1
         0: new           #2                  // class scala/collection/convert/JavaCollectionWrappers$JListWrapper
         3: dup
         4: new           #349                // class java/util/ArrayList
         7: dup
         8: aload_0
         9: invokevirtual #248                // Method underlying:()Ljava/util/List;
        12: invokespecial #352                // Method java/util/ArrayList."<init>":(Ljava/util/Collection;)V
        15: invokespecial #355                // Method "<init>":(Ljava/util/List;)V
        18: areturn
      LineNumberTable:
        line 126: 0
      LocalVariableTable:
        Start  Length  Slot  Name   Signature
            0      19     0  this   Lscala/collection/convert/JavaCollectionWrappers$JListWrapper;
    Signature: #347                         // ()Lscala/collection/convert/JavaCollectionWrappers$JListWrapper<TA;>;

  public scala.collection.convert.JavaCollectionWrappers$JListWrapper<A> patchInPlace(int, scala.collection.IterableOnce<A>, int);
    descriptor: (ILscala/collection/IterableOnce;I)Lscala/collection/convert/JavaCollectionWrappers$JListWrapper;
    flags: (0x0001) ACC_PUBLIC
    Code:
      stack=3, locals=4, args_size=4
         0: aload_0
         1: iload_1
         2: iload_3
         3: invokevirtual #364                // Method remove:(II)V
         6: aload_0
         7: iload_1
         8: aload_2
         9: invokevirtual #366                // Method insertAll:(ILscala/collection/IterableOnce;)V
        12: aload_0
        13: areturn
      LineNumberTable:
        line 128: 0
        line 129: 6
        line 130: 12
      LocalVariableTable:
        Start  Length  Slot  Name   Signature
            0      14     0  this   Lscala/collection/convert/JavaCollectionWrappers$JListWrapper;
            0      14     1  from   I
            0      14     2 patch   Lscala/collection/IterableOnce;
            0      14     3 replaced   I
    Signature: #358                         // (ILscala/collection/IterableOnce<TA;>;I)Lscala/collection/convert/JavaCollectionWrappers$JListWrapper<TA;>;
    MethodParameters:
      Name                           Flags
      from                           final
      patch                          final
      replaced                       final

  public void remove(int, int);
    descriptor: (II)V
    flags: (0x0001) ACC_PUBLIC
    Code:
      stack=4, locals=3, args_size=3
         0: aload_0
         1: invokevirtual #248                // Method underlying:()Ljava/util/List;
         4: iload_1
         5: iload_1
         6: iload_2
         7: iadd
         8: invokeinterface #298,  3          // InterfaceMethod java/util/List.subList:(II)Ljava/util/List;
        13: invokeinterface #344,  1          // InterfaceMethod java/util/List.clear:()V
        18: return
      LineNumberTable:
        line 132: 0
      LocalVariableTable:
        Start  Length  Slot  Name   Signature
            0      19     0  this   Lscala/collection/convert/JavaCollectionWrappers$JListWrapper;
            0      19     1  from   I
            0      19     2     n   I
    MethodParameters:
      Name                           Flags
      from                           final
      n                              final

  public scala.collection.mutable.ArrayBuffer$ iterableFactory();
    descriptor: ()Lscala/collection/mutable/ArrayBuffer$;
    flags: (0x0001) ACC_PUBLIC
    Code:
      stack=1, locals=1, args_size=1
         0: getstatic     #373                // Field scala/collection/mutable/ArrayBuffer$.MODULE$:Lscala/collection/mutable/ArrayBuffer$;
         3: areturn
      LineNumberTable:
        line 133: 0
      LocalVariableTable:
        Start  Length  Slot  Name   Signature
            0       4     0  this   Lscala/collection/convert/JavaCollectionWrappers$JListWrapper;

  public scala.collection.convert.JavaCollectionWrappers$JListWrapper<A> subtractOne(A);
    descriptor: (Ljava/lang/Object;)Lscala/collection/convert/JavaCollectionWrappers$JListWrapper;
    flags: (0x0001) ACC_PUBLIC
    Code:
      stack=2, locals=2, args_size=2
         0: aload_0
         1: invokevirtual #248                // Method underlying:()Ljava/util/List;
         4: aload_1
         5: invokeinterface #376,  2          // InterfaceMethod java/util/List.remove:(Ljava/lang/Object;)Z
        10: pop
        11: aload_0
        12: areturn
      LineNumberTable:
        line 134: 0
      LocalVariableTable:
        Start  Length  Slot  Name   Signature
            0      13     0  this   Lscala/collection/convert/JavaCollectionWrappers$JListWrapper;
            0      13     1  elem   Ljava/lang/Object;
    Signature: #294                         // (TA;)Lscala/collection/convert/JavaCollectionWrappers$JListWrapper<TA;>;
    MethodParameters:
      Name                           Flags
      elem                           final

  public <A extends java.lang.Object> scala.collection.convert.JavaCollectionWrappers$JListWrapper<A> copy(java.util.List<A>);
    descriptor: (Ljava/util/List;)Lscala/collection/convert/JavaCollectionWrappers$JListWrapper;
    flags: (0x0001) ACC_PUBLIC
    Code:
      stack=3, locals=2, args_size=2
         0: new           #2                  // class scala/collection/convert/JavaCollectionWrappers$JListWrapper
         3: dup
         4: aload_1
         5: invokespecial #355                // Method "<init>":(Ljava/util/List;)V
         8: areturn
      LineNumberTable:
        line 103: 0
      LocalVariableTable:
        Start  Length  Slot  Name   Signature
            0       9     0  this   Lscala/collection/convert/JavaCollectionWrappers$JListWrapper;
            0       9     1 underlying   Ljava/util/List;
    Signature: #379                         // <A:Ljava/lang/Object;>(Ljava/util/List<TA;>;)Lscala/collection/convert/JavaCollectionWrappers$JListWrapper<TA;>;
    MethodParameters:
      Name                           Flags
      underlying                     final

  public <A extends java.lang.Object> java.util.List<A> copy$default$1();
    descriptor: ()Ljava/util/List;
    flags: (0x0001) ACC_PUBLIC
    Code:
      stack=1, locals=1, args_size=1
         0: aload_0
         1: invokevirtual #248                // Method underlying:()Ljava/util/List;
         4: areturn
      LineNumberTable:
        line 103: 0
      LocalVariableTable:
        Start  Length  Slot  Name   Signature
            0       5     0  this   Lscala/collection/convert/JavaCollectionWrappers$JListWrapper;
    Signature: #381                         // <A:Ljava/lang/Object;>()Ljava/util/List<TA;>;

  public java.lang.String productPrefix();
    descriptor: ()Ljava/lang/String;
    flags: (0x0001) ACC_PUBLIC
    Code:
      stack=1, locals=1, args_size=1
         0: ldc_w         #384                // String JListWrapper
         3: areturn
      LineNumberTable:
        line 103: 0
      LocalVariableTable:
        Start  Length  Slot  Name   Signature
            0       4     0  this   Lscala/collection/convert/JavaCollectionWrappers$JListWrapper;

  public int productArity();
    descriptor: ()I
    flags: (0x0001) ACC_PUBLIC
    Code:
      stack=1, locals=1, args_size=1
         0: iconst_1
         1: ireturn
      LineNumberTable:
        line 103: 0
      LocalVariableTable:
        Start  Length  Slot  Name   Signature
            0       2     0  this   Lscala/collection/convert/JavaCollectionWrappers$JListWrapper;

  public java.lang.Object productElement(int);
    descriptor: (I)Ljava/lang/Object;
    flags: (0x0001) ACC_PUBLIC
    Code:
      stack=1, locals=2, args_size=2
         0: iload_1
         1: tableswitch   { // 0 to 0
                       0: 20
                 default: 25
            }
        20: aload_0
        21: invokevirtual #248                // Method underlying:()Ljava/util/List;
        24: areturn
        25: iload_1
        26: invokestatic  #392                // Method scala/runtime/Statics.ioobe:(I)Ljava/lang/Object;
        29: areturn
      StackMapTable: number_of_entries = 2
        frame_type = 20 /* same */
        frame_type = 4 /* same */
      LineNumberTable:
        line 103: 0
      LocalVariableTable:
        Start  Length  Slot  Name   Signature
            0      30     0  this   Lscala/collection/convert/JavaCollectionWrappers$JListWrapper;
            0      30     1   x$1   I
    MethodParameters:
      Name                           Flags
      x$1                            final

  public scala.collection.Iterator<java.lang.Object> productIterator();
    descriptor: ()Lscala/collection/Iterator;
    flags: (0x0001) ACC_PUBLIC
    Code:
      stack=3, locals=1, args_size=1
         0: new           #27                 // class scala/runtime/ScalaRunTime$$anon$1
         3: dup
         4: aload_0
         5: invokespecial #397                // Method scala/runtime/ScalaRunTime$$anon$1."<init>":(Lscala/Product;)V
         8: areturn
      LineNumberTable:
        line 103: 0
      LocalVariableTable:
        Start  Length  Slot  Name   Signature
            0       9     0  this   Lscala/collection/convert/JavaCollectionWrappers$JListWrapper;
    Signature: #394                         // ()Lscala/collection/Iterator<Ljava/lang/Object;>;

  public java.lang.String productElementName(int);
    descriptor: (I)Ljava/lang/String;
    flags: (0x0001) ACC_PUBLIC
    Code:
      stack=1, locals=2, args_size=2
         0: iload_1
         1: tableswitch   { // 0 to 0
                       0: 20
                 default: 24
            }
        20: ldc_w         #400                // String underlying
        23: areturn
        24: iload_1
        25: invokestatic  #392                // Method scala/runtime/Statics.ioobe:(I)Ljava/lang/Object;
        28: checkcast     #402                // class java/lang/String
        31: areturn
      StackMapTable: number_of_entries = 2
        frame_type = 20 /* same */
        frame_type = 3 /* same */
      LineNumberTable:
        line 103: 0
      LocalVariableTable:
        Start  Length  Slot  Name   Signature
            0      32     0  this   Lscala/collection/convert/JavaCollectionWrappers$JListWrapper;
            0      32     1   x$1   I
    MethodParameters:
      Name                           Flags
      x$1                            final

  public scala.collection.mutable.Shrinkable subtractOne(java.lang.Object);
    descriptor: (Ljava/lang/Object;)Lscala/collection/mutable/Shrinkable;
    flags: (0x1041) ACC_PUBLIC, ACC_BRIDGE, ACC_SYNTHETIC
    Code:
      stack=2, locals=2, args_size=2
         0: aload_0
         1: aload_1
         2: invokevirtual #405                // Method subtractOne:(Ljava/lang/Object;)Lscala/collection/convert/JavaCollectionWrappers$JListWrapper;
         5: areturn
      LineNumberTable:
        line 103: 0
      LocalVariableTable:
        Start  Length  Slot  Name   Signature
            0       6     0  this   Lscala/collection/convert/JavaCollectionWrappers$JListWrapper;
            0       6     1  elem   Ljava/lang/Object;
    MethodParameters:
      Name                           Flags
      elem                           final

  public scala.collection.mutable.Buffer subtractOne(java.lang.Object);
    descriptor: (Ljava/lang/Object;)Lscala/collection/mutable/Buffer;
    flags: (0x1041) ACC_PUBLIC, ACC_BRIDGE, ACC_SYNTHETIC
    Code:
      stack=2, locals=2, args_size=2
         0: aload_0
         1: aload_1
         2: invokevirtual #405                // Method subtractOne:(Ljava/lang/Object;)Lscala/collection/convert/JavaCollectionWrappers$JListWrapper;
         5: areturn
      LineNumberTable:
        line 103: 0
      LocalVariableTable:
        Start  Length  Slot  Name   Signature
            0       6     0  this   Lscala/collection/convert/JavaCollectionWrappers$JListWrapper;
            0       6     1     x   Ljava/lang/Object;
    MethodParameters:
      Name                           Flags
      x                              final

  public scala.collection.IterableFactory iterableFactory();
    descriptor: ()Lscala/collection/IterableFactory;
    flags: (0x1041) ACC_PUBLIC, ACC_BRIDGE, ACC_SYNTHETIC
    Code:
      stack=1, locals=1, args_size=1
         0: aload_0
         1: invokevirtual #410                // Method iterableFactory:()Lscala/collection/mutable/ArrayBuffer$;
         4: areturn
      LineNumberTable:
        line 103: 0
      LocalVariableTable:
        Start  Length  Slot  Name   Signature
            0       5     0  this   Lscala/collection/convert/JavaCollectionWrappers$JListWrapper;

  public scala.collection.SeqFactory iterableFactory();
    descriptor: ()Lscala/collection/SeqFactory;
    flags: (0x1041) ACC_PUBLIC, ACC_BRIDGE, ACC_SYNTHETIC
    Code:
      stack=1, locals=1, args_size=1
         0: aload_0
         1: invokevirtual #410                // Method iterableFactory:()Lscala/collection/mutable/ArrayBuffer$;
         4: areturn
      LineNumberTable:
        line 103: 0
      LocalVariableTable:
        Start  Length  Slot  Name   Signature
            0       5     0  this   Lscala/collection/convert/JavaCollectionWrappers$JListWrapper;

  public scala.collection.mutable.Buffer patchInPlace(int, scala.collection.IterableOnce, int);
    descriptor: (ILscala/collection/IterableOnce;I)Lscala/collection/mutable/Buffer;
    flags: (0x1041) ACC_PUBLIC, ACC_BRIDGE, ACC_SYNTHETIC
    Code:
      stack=4, locals=4, args_size=4
         0: aload_0
         1: iload_1
         2: aload_2
         3: iload_3
         4: invokevirtual #414                // Method patchInPlace:(ILscala/collection/IterableOnce;I)Lscala/collection/convert/JavaCollectionWrappers$JListWrapper;
         7: areturn
      LineNumberTable:
        line 103: 0
      LocalVariableTable:
        Start  Length  Slot  Name   Signature
            0       8     0  this   Lscala/collection/convert/JavaCollectionWrappers$JListWrapper;
            0       8     1  from   I
            0       8     2 patch   Lscala/collection/IterableOnce;
            0       8     3 replaced   I
    MethodParameters:
      Name                           Flags
      from                           final
      patch                          final
      replaced                       final

  public java.lang.Object clone();
    descriptor: ()Ljava/lang/Object;
    flags: (0x1041) ACC_PUBLIC, ACC_BRIDGE, ACC_SYNTHETIC
    Code:
      stack=1, locals=1, args_size=1
         0: aload_0
         1: invokevirtual #416                // Method clone:()Lscala/collection/convert/JavaCollectionWrappers$JListWrapper;
         4: areturn
      LineNumberTable:
        line 103: 0
      LocalVariableTable:
        Start  Length  Slot  Name   Signature
            0       5     0  this   Lscala/collection/convert/JavaCollectionWrappers$JListWrapper;

  public scala.collection.mutable.Growable addOne(java.lang.Object);
    descriptor: (Ljava/lang/Object;)Lscala/collection/mutable/Growable;
    flags: (0x1041) ACC_PUBLIC, ACC_BRIDGE, ACC_SYNTHETIC
    Code:
      stack=2, locals=2, args_size=2
         0: aload_0
         1: aload_1
         2: invokevirtual #419                // Method addOne:(Ljava/lang/Object;)Lscala/collection/convert/JavaCollectionWrappers$JListWrapper;
         5: areturn
      LineNumberTable:
        line 103: 0
      LocalVariableTable:
        Start  Length  Slot  Name   Signature
            0       6     0  this   Lscala/collection/convert/JavaCollectionWrappers$JListWrapper;
            0       6     1  elem   Ljava/lang/Object;
    MethodParameters:
      Name                           Flags
      elem                           final

  public scala.collection.mutable.Buffer prepend(java.lang.Object);
    descriptor: (Ljava/lang/Object;)Lscala/collection/mutable/Buffer;
    flags: (0x1041) ACC_PUBLIC, ACC_BRIDGE, ACC_SYNTHETIC
    Code:
      stack=2, locals=2, args_size=2
         0: aload_0
         1: aload_1
         2: invokevirtual #421                // Method prepend:(Ljava/lang/Object;)Lscala/collection/convert/JavaCollectionWrappers$JListWrapper;
         5: areturn
      LineNumberTable:
        line 103: 0
      LocalVariableTable:
        Start  Length  Slot  Name   Signature
            0       6     0  this   Lscala/collection/convert/JavaCollectionWrappers$JListWrapper;
            0       6     1  elem   Ljava/lang/Object;
    MethodParameters:
      Name                           Flags
      elem                           final

  public java.lang.Object apply(java.lang.Object);
    descriptor: (Ljava/lang/Object;)Ljava/lang/Object;
    flags: (0x1041) ACC_PUBLIC, ACC_BRIDGE, ACC_SYNTHETIC
    Code:
      stack=2, locals=2, args_size=2
         0: aload_0
         1: aload_1
         2: invokestatic  #428                // Method scala/runtime/BoxesRunTime.unboxToInt:(Ljava/lang/Object;)I
         5: invokevirtual #430                // Method apply:(I)Ljava/lang/Object;
         8: areturn
      LineNumberTable:
        line 103: 0
      LocalVariableTable:
        Start  Length  Slot  Name   Signature
            0       9     0  this   Lscala/collection/convert/JavaCollectionWrappers$JListWrapper;
            0       9     1    v1   Ljava/lang/Object;
    MethodParameters:
      Name                           Flags
      v1                             final

  public static final boolean $anonfun$insertAll$1(java.util.List, java.lang.Object);
    descriptor: (Ljava/util/List;Ljava/lang/Object;)Z
    flags: (0x1019) ACC_PUBLIC, ACC_STATIC, ACC_FINAL, ACC_SYNTHETIC
    Code:
      stack=2, locals=2, args_size=2
         0: aload_0
         1: aload_1
         2: invokeinterface #302,  2          // InterfaceMethod java/util/List.add:(Ljava/lang/Object;)Z
         7: ireturn
      LineNumberTable:
        line 120: 0
      LocalVariableTable:
        Start  Length  Slot  Name   Signature
            0       8     0 ins$1   Ljava/util/List;
            0       8     1   x$1   Ljava/lang/Object;
    MethodParameters:
      Name                           Flags
      ins$1                          final
      x$1                            final

  public scala.collection.convert.JavaCollectionWrappers$JListWrapper(java.util.List<A>);
    descriptor: (Ljava/util/List;)V
    flags: (0x0001) ACC_PUBLIC
    Code:
      stack=2, locals=2, args_size=2
         0: aload_0
         1: aload_1
         2: putfield      #244                // Field underlying:Ljava/util/List;
         5: aload_0
         6: invokespecial #436                // Method scala/collection/mutable/AbstractBuffer."<init>":()V
         9: return
      LineNumberTable:
        line 103: 0
        line 104: 5
      LocalVariableTable:
        Start  Length  Slot  Name   Signature
            0      10     0  this   Lscala/collection/convert/JavaCollectionWrappers$JListWrapper;
            0      10     1 underlying   Ljava/util/List;
    Signature: #434                         // (Ljava/util/List<TA;>;)V
    MethodParameters:
      Name                           Flags
      underlying                     final

  public static final java.lang.Object $anonfun$insertAll$1$adapted(java.util.List, java.lang.Object);
    descriptor: (Ljava/util/List;Ljava/lang/Object;)Ljava/lang/Object;
    flags: (0x1019) ACC_PUBLIC, ACC_STATIC, ACC_FINAL, ACC_SYNTHETIC
    Code:
      stack=2, locals=2, args_size=2
         0: aload_0
         1: aload_1
         2: invokestatic  #438                // Method $anonfun$insertAll$1:(Ljava/util/List;Ljava/lang/Object;)Z
         5: invokestatic  #442                // Method scala/runtime/BoxesRunTime.boxToBoolean:(Z)Ljava/lang/Boolean;
         8: areturn
      LineNumberTable:
        line 120: 0
      LocalVariableTable:
        Start  Length  Slot  Name   Signature
            0       9     0 ins$1   Ljava/util/List;
            0       9     1   x$1   Ljava/lang/Object;
    MethodParameters:
      Name                           Flags
      ins$1                          final
      x$1                            final

  private static java.lang.Object $deserializeLambda$(java.lang.invoke.SerializedLambda);
    descriptor: (Ljava/lang/invoke/SerializedLambda;)Ljava/lang/Object;
    flags: (0x100a) ACC_PRIVATE, ACC_STATIC, ACC_SYNTHETIC
    Code:
      stack=1, locals=1, args_size=1
         0: aload_0
         1: invokedynamic #454,  0            // InvokeDynamic #1:lambdaDeserialize:(Ljava/lang/invoke/SerializedLambda;)Ljava/lang/Object;
         6: areturn
}
InnerClasses:
  public static final #17= #14 of #16;    // Lookup=class java/lang/invoke/MethodHandles$Lookup of class java/lang/invoke/MethodHandles
  public #22= #19 of #21;                 // IteratorHasAsScala=class scala/collection/convert/AsScalaExtensions$IteratorHasAsScala of class scala/collection/convert/AsScalaExtensions
  public static #25= #2 of #24;           // JListWrapper=class scala/collection/convert/JavaCollectionWrappers$JListWrapper of class scala/collection/convert/JavaCollectionWrappers
  public final #27;                       // class scala/runtime/ScalaRunTime$$anon$1
Signature: #3                           // <A:Ljava/lang/Object;>Lscala/collection/mutable/AbstractBuffer<TA;>;Lscala/collection/StrictOptimizedSeqOps<TA;Lscala/collection/mutable/Buffer;Lscala/collection/mutable/Buffer<TA;>;>;Ljava/io/Serializable;Lscala/Product;
SourceFile: "JavaCollectionWrappers.scala"
BootstrapMethods:
  0: #327 REF_invokeStatic java/lang/invoke/LambdaMetafactory.altMetafactory:(Ljava/lang/invoke/MethodHandles$Lookup;Ljava/lang/String;Ljava/lang/invoke/MethodType;[Ljava/lang/Object;)Ljava/lang/invoke/CallSite;
    Method arguments:
      #314 (Ljava/lang/Object;)Ljava/lang/Object;
      #319 REF_invokeStatic scala/collection/convert/JavaCollectionWrappers$JListWrapper.$anonfun$insertAll$1$adapted:(Ljava/util/List;Ljava/lang/Object;)Ljava/lang/Object;
      #314 (Ljava/lang/Object;)Ljava/lang/Object;
      #320 1
  1: #451 REF_invokeStatic scala/runtime/LambdaDeserialize.bootstrap:(Ljava/lang/invoke/MethodHandles$Lookup;Ljava/lang/String;Ljava/lang/invoke/MethodType;[Ljava/lang/invoke/MethodHandle;)Ljava/lang/invoke/CallSite;
    Method arguments:
      #319 REF_invokeStatic scala/collection/convert/JavaCollectionWrappers$JListWrapper.$anonfun$insertAll$1$adapted:(Ljava/util/List;Ljava/lang/Object;)Ljava/lang/Object;
  ScalaInlineInfo: length = 0x162 (unknown attribute)
   01 00 00 46 01 AF 01 B0 01 01 3B 01 3C 01 01 0E
   01 61 00 01 2F 01 25 00 01 2F 01 A1 00 00 3C 00
   35 00 00 40 00 41 00 01 18 00 E7 00 01 18 00 35
   00 01 55 01 56 00 01 59 00 BE 00 01 59 01 5A 00
   00 9B 00 9C 00 01 79 01 7A 00 01 7C 00 F1 00 00
   55 00 56 00 00 2C 00 2D 00 00 ED 00 E7 00 00 CC
   00 2D 00 00 D5 00 D6 00 00 D1 00 2D 00 00 8B 00
   2D 00 00 AA 00 2D 00 01 30 01 1F 00 01 32 01 33
   00 00 5D 00 56 00 00 FF 01 00 00 01 6F 01 98 00
   01 6F 01 9B 00 01 6F 01 70 00 01 03 00 24 00 00
   FE 00 F6 00 00 F5 00 F6 00 00 7D 00 2D 00 00 4D
   00 4E 00 00 61 00 62 00 00 DD 00 62 00 01 64 01
   65 00 01 64 01 9C 00 01 24 01 25 00 01 24 01 96
   00 00 34 00 35 00 00 48 00 41 00 01 81 00 F6 00
   01 82 00 E7 00 01 8E 01 8F 00 00 23 00 24 00 01
   89 00 24 00 01 7E 01 7F 00 01 52 00 E7 00 01 52
   01 6A 00 00 C3 00 C4 00 00 6B 00 62 00 00 A3 00
   A4 05 00 94 00 95 05 00 8F 00 83 05 00 AF 00 83
   05 00 82 00 83 05 00 B8 00 95 05 01 76 01 25 00
   01 76 01 96 00 01 76 01 93 00 00 E6 00 E7 00 00
   E2 00 2D 00 00 20 00 F1 00 00 6F 00 62 00 00 75
   00 76 00 01 1E 01 1F 00 00 B3 00 41 00 00 BD 00
   BE 00
  Scala: length = 0x0 (unknown attribute)

