Classfile /Users/mw/Projects/slang-braindump/.jar/jar11/assemble/slang-braindump/assemble/content/scala/collection/convert/ToJavaImplicits.class
  Last modified May 29, 2022; size 10680 bytes
  SHA-256 checksum 7cef2c679e16a8053f92438c793c4a64a162f316f699020a82f4724c27ba87b2
  Compiled from "ImplicitConversions.scala"
public interface scala.collection.convert.ToJavaImplicits
  minor version: 0
  major version: 52
  flags: (0x0601) ACC_PUBLIC, ACC_INTERFACE, ACC_ABSTRACT
  this_class: #2                          // scala/collection/convert/ToJavaImplicits
  super_class: #4                         // java/lang/Object
  interfaces: 0, fields: 0, methods: 27, attributes: 5
Constant pool:
    #1 = Utf8               scala/collection/convert/ToJavaImplicits
    #2 = Class              #1            // scala/collection/convert/ToJavaImplicits
    #3 = Utf8               java/lang/Object
    #4 = Class              #3            // java/lang/Object
    #5 = Utf8               ImplicitConversions.scala
    #6 = Utf8               Lscala/reflect/ScalaSignature;
    #7 = Utf8               bytes
    #8 = Utf8               \u0006\u0005\u0005]faB\b\u0011!\u0003\r\ta\u0006\u0005\u00069\u0001!\t!\b\u0005\u0006C\u0001!\u0019A\t\u0005\u0006y\u0001!\u0019!\u0010\u0005\u0006\r\u0002!\u0019a\u0012\u0005\u0006+\u0002!\u0019A\u0016\u0005\u0006?\u0002!\u0019\u0001\u0019\u0005\u0006_\u0002!\u0019\u0001\u001d\u0005\u0006u\u0002!\u0019a\u001f\u0005\b\u0003\u000f\u0001A1AA\u0005\u0011\u001d\ty\u0002\u0001C\u0002\u0003CAq!!\r\u0001\t\u0007\t\u0019\u0004C\u0004\u0002R\u0001!\u0019!a\u0015\t\u000f\u0005%\u0004\u0001b\u0001\u0002l!9\u0011q\u0010\u0001\u0005\u0004\u0005\u0005%a\u0004+p\u0015\u00064\u0018-S7qY&\u001c\u0017\u000e^:\u000b\u0005E\u0011\u0012aB2p]Z,\'\u000f\u001e\u0006\u0003\'Q\t!bY8mY\u0016\u001cG/[8o\u0015\u0005)\u0012!B:dC2\f7\u0001A\n\u0003\u0001a\u0001\"!\u0007\u000e\u000e\u0003QI!a\u0007\u000b\u0003\r\u0005s\u0017PU3g\u0003\u0019!\u0013N\\5uIQ\ta\u0004\u0005\u0002\u001a?%\u0011\u0001\u0005\u0006\u0002\u0005+:LG/\u0001\u000bji\u0016\u0014\u0018\r^8sIU\u0004\u0004G\r\u0019bg*\u000bg/Y\u000b\u0003G9\"\"\u0001J\u001c\u0011\u0007\u0015RC&D\u0001\'\u0015\t9\u0003&\u0001\u0003vi&d\'\"A\u0015\u0002\t)\fg/Y\u0005\u0003W\u0019\u0012\u0001\"\u0013;fe\u0006$xN\u001d\t\u0003[9b\u0001\u0001B\u00030\u0005\t\u0007\u0001GA\u0001B#\t\tD\u0007\u0005\u0002\u001ae%\u00111\u0007\u0006\u0002\b\u001d>$\b.\u001b8h!\tIR\'\u0003\u00027)\t\u0019\u0011I\\=\t\u000ba\u0012\u0001\u0019A\u001d\u0002\u0005%$\bc\u0001\u001e<Y5\t!#\u0003\u0002,%\u00059RM\\;nKJ\fG/[8oIU\u0004\u0004G\r\u0019bg*\u000bg/Y\u000b\u0003}\r#\"a\u0010#\u0011\u0007\u0015\u0002%)\u0003\u0002BM\tYQI\\;nKJ\fG/[8o!\ti3\tB\u00030\u0007\t\u0007\u0001\u0007C\u00039\u0007\u0001\u0007Q\tE\u0002;w\t\u000bA#\u001b;fe\u0006\u0014G.\u001a\u0013vaA\u0012\u0004\'Y:KCZ\fWC\u0001%Q)\tI\u0015\u000bE\u0002K\u001b>k\u0011a\u0013\u0006\u0003\u0019\"\nA\u0001\\1oO&\u0011aj\u0013\u0002\t\u0013R,\'/\u00192mKB\u0011Q\u0006\u0015\u0003\u0006_\u0011\u0011\r\u0001\r\u0005\u0006%\u0012\u0001\raU\u0001\u0002SB\u0019!\bV(\n\u00059\u0013\u0012AF2pY2,7\r^5p]\u0012*\b\u0007\r\u001a1CNT\u0015M^1\u0016\u0005]cFC\u0001-^!\r)\u0013lW\u0005\u00035\u001a\u0012!bQ8mY\u0016\u001cG/[8o!\tiC\fB\u00030\u000b\t\u0007\u0001\u0007C\u00039\u000b\u0001\u0007a\fE\u0002;)n\u000baCY;gM\u0016\u0014H%\u001e\u00191eA\n5OS1wC2K7\u000f^\u000b\u0003C\u001a$\"AY4\u0011\u0007\u0015\u001aW-\u0003\u0002eM\t!A*[:u!\tic\rB\u00030\r\t\u0007\u0001\u0007C\u0003i\r\u0001\u0007\u0011.A\u0001c!\rQW.Z\u0007\u0002W*\u0011ANE\u0001\b[V$\u0018M\u00197f\u0013\tq7N\u0001\u0004Ck\u001a4WM]\u0001\u001b[V$\u0018M\u00197f\'\u0016\fH%\u001e\u00191eA\n5OS1wC2K7\u000f^\u000b\u0003cR$\"A];\u0011\u0007\u0015\u001a7\u000f\u0005\u0002.i\u0012)qf\u0002b\u0001a!)ao\u0002a\u0001o\u0006\u00191/Z9\u0011\u0007)D8/\u0003\u0002zW\n\u00191+Z9\u0002\'M,\u0017\u000fJ;1aI\u0002\u0014i\u001d&bm\u0006d\u0015n\u001d;\u0016\u0005q|HcA?\u0002\u0002A\u0019Qe\u0019@\u0011\u00055zH!B\u0018\t\u0005\u0004\u0001\u0004B\u0002<\t\u0001\u0004\t\u0019\u0001\u0005\u0003;\u0003\u000bq\u0018BA=\u0013\u0003eiW\u000f^1cY\u0016\u001cV\r\u001e\u0013vaA\u0012\u0004\'Q:KCZ\f7+\u001a;\u0016\t\u0005-\u0011Q\u0003\u000b\u0005\u0003\u001b\t9\u0002E\u0003&\u0003\u001f\t\u0019\"C\u0002\u0002\u0012\u0019\u00121aU3u!\ri\u0013Q\u0003\u0003\u0006_%\u0011\r\u0001\r\u0005\b\u00033I\u0001\u0019AA\u000e\u0003\u0005\u0019\b#\u00026\u0002\u001e\u0005M\u0011bAA\tW\u0006\u00112/\u001a;%kB\u0002$\u0007M!t\u0015\u00064\u0018mU3u+\u0011\t\u0019#!\u000b\u0015\t\u0005\u0015\u00121\u0006\t\u0006K\u0005=\u0011q\u0005\t\u0004[\u0005%B!B\u0018\u000b\u0005\u0004\u0001\u0004bBA\r\u0015\u0001\u0007\u0011Q\u0006\t\u0006u\u0005=\u0012qE\u0005\u0004\u0003#\u0011\u0012!G7vi\u0006\u0014G.Z\'ba\u0012*\b\u0007\r\u001a1\u0003NT\u0015M^1NCB,b!!\u000e\u0002@\u0005\u0015C\u0003BA\u001c\u0003\u0013\u0002r!JA\u001d\u0003{\t\u0019%C\u0002\u0002<\u0019\u00121!T1q!\ri\u0013q\b\u0003\u0007\u0003\u0003Z!\u0019\u0001\u0019\u0003\u0003-\u00032!LA#\t\u0019\t9e\u0003b\u0001a\t\ta\u000bC\u0004\u0002L-\u0001\r!!\u0014\u0002\u00035\u0004rA[A(\u0003{\t\u0019%C\u0002\u0002<-\fa\u0003Z5di&|g.\u0019:zIU\u0004\u0004G\r\u0019bg*\u000bg/Y\u000b\u0007\u0003+\ny&a\u0019\u0015\t\u0005]\u0013Q\r\t\bK\u0005e\u0013QLA1\u0013\r\tYF\n\u0002\u000b\t&\u001cG/[8oCJL\bcA\u0017\u0002`\u00111\u0011\u0011\t\u0007C\u0002A\u00022!LA2\t\u0019\t9\u0005\u0004b\u0001a!9\u00111\n\u0007A\u0002\u0005\u001d\u0004c\u00026\u0002P\u0005u\u0013\u0011M\u0001\u0013[\u0006\u0004H%\u001e\u00191eA\n5OS1wC6\u000b\u0007/\u0006\u0004\u0002n\u0005M\u0014q\u000f\u000b\u0005\u0003_\nI\bE\u0004&\u0003s\t\t(!\u001e\u0011\u00075\n\u0019\b\u0002\u0004\u0002B5\u0011\r\u0001\r\t\u0004[\u0005]DABA$\u001b\t\u0007\u0001\u0007C\u0004\u0002L5\u0001\r!a\u001f\u0011\u000fi\ni(!\u001d\u0002v%\u0019\u00111\b\n\u000295\f\u0007\u000fJ;1aI\u0002\u0014i\u001d&bm\u0006\u001cuN\\2veJ,g\u000e^\'baV1\u00111QAJ\u0003/#B!!\"\u0002\u001aBA\u0011qQAG\u0003#\u000b)*\u0004\u0002\u0002\n*\u0019\u00111\u0012\u0014\u0002\u0015\r|gnY;se\u0016tG/\u0003\u0003\u0002\u0010\u0006%%!D\"p]\u000e,(O]3oi6\u000b\u0007\u000fE\u0002.\u0003\'#a!!\u0011\u000f\u0005\u0004\u0001\u0004cA\u0017\u0002\u0018\u00121\u0011q\t\bC\u0002ABq!a\u0013\u000f\u0001\u0004\tY\n\u0005\u0005\u0002\u001e\u0006\u0005\u0016\u0011SAK\u001b\t\tyJC\u0002\u0002\fJIA!a\u000f\u0002 \"Z\u0001!!*\u0002,\u00065\u0016\u0011WAZ!\rI\u0012qU\u0005\u0004\u0003S#\"A\u00033faJ,7-\u0019;fI\u00069Q.Z:tC\u001e,\u0017EAAX\u00031*6/\u001a\u0011ag\u000e\fG.\u0019\u0018kI.t3i\u001c7mK\u000e$\u0018n\u001c8D_:4XM\u001d;feN\u0004\u0007%\u001b8ti\u0016\fG-A\u0003tS:\u001cW-\t\u0002\u00026\u00061!GL\u00194]A\u0002
    #9 = Utf8               iterator$u0020asJava$
   #10 = Utf8               (Lscala/collection/convert/ToJavaImplicits;Lscala/collection/Iterator;)Ljava/util/Iterator;
   #11 = Utf8               $this
   #12 = Utf8               it
   #13 = Utf8               iterator$u0020asJava
   #14 = Utf8               (Lscala/collection/Iterator;)Ljava/util/Iterator;
   #15 = NameAndType        #13:#14       // iterator$u0020asJava:(Lscala/collection/Iterator;)Ljava/util/Iterator;
   #16 = InterfaceMethodref #2.#15        // scala/collection/convert/ToJavaImplicits.iterator$u0020asJava:(Lscala/collection/Iterator;)Ljava/util/Iterator;
   #17 = Utf8               Lscala/collection/convert/ToJavaImplicits;
   #18 = Utf8               Lscala/collection/Iterator;
   #19 = Utf8               <A:Ljava/lang/Object;>(Lscala/collection/Iterator<TA;>;)Ljava/util/Iterator<TA;>;
   #20 = Utf8               scala/collection/JavaConverters$
   #21 = Class              #20           // scala/collection/JavaConverters$
   #22 = Utf8               MODULE$
   #23 = Utf8               Lscala/collection/JavaConverters$;
   #24 = NameAndType        #22:#23       // MODULE$:Lscala/collection/JavaConverters$;
   #25 = Fieldref           #21.#24       // scala/collection/JavaConverters$.MODULE$:Lscala/collection/JavaConverters$;
   #26 = Utf8               scala/collection/convert/AsJavaConverters
   #27 = Class              #26           // scala/collection/convert/AsJavaConverters
   #28 = Utf8               asJava$
   #29 = Utf8               (Lscala/collection/convert/AsJavaConverters;Lscala/collection/Iterator;)Ljava/util/Iterator;
   #30 = NameAndType        #28:#29       // asJava$:(Lscala/collection/convert/AsJavaConverters;Lscala/collection/Iterator;)Ljava/util/Iterator;
   #31 = InterfaceMethodref #27.#30       // scala/collection/convert/AsJavaConverters.asJava$:(Lscala/collection/convert/AsJavaConverters;Lscala/collection/Iterator;)Ljava/util/Iterator;
   #32 = Utf8               this
   #33 = Utf8               enumeration$u0020asJava$
   #34 = Utf8               (Lscala/collection/convert/ToJavaImplicits;Lscala/collection/Iterator;)Ljava/util/Enumeration;
   #35 = Utf8               enumeration$u0020asJava
   #36 = Utf8               (Lscala/collection/Iterator;)Ljava/util/Enumeration;
   #37 = NameAndType        #35:#36       // enumeration$u0020asJava:(Lscala/collection/Iterator;)Ljava/util/Enumeration;
   #38 = InterfaceMethodref #2.#37        // scala/collection/convert/ToJavaImplicits.enumeration$u0020asJava:(Lscala/collection/Iterator;)Ljava/util/Enumeration;
   #39 = Utf8               <A:Ljava/lang/Object;>(Lscala/collection/Iterator<TA;>;)Ljava/util/Enumeration<TA;>;
   #40 = Utf8               asJavaEnumeration$
   #41 = Utf8               (Lscala/collection/convert/AsJavaConverters;Lscala/collection/Iterator;)Ljava/util/Enumeration;
   #42 = NameAndType        #40:#41       // asJavaEnumeration$:(Lscala/collection/convert/AsJavaConverters;Lscala/collection/Iterator;)Ljava/util/Enumeration;
   #43 = InterfaceMethodref #27.#42       // scala/collection/convert/AsJavaConverters.asJavaEnumeration$:(Lscala/collection/convert/AsJavaConverters;Lscala/collection/Iterator;)Ljava/util/Enumeration;
   #44 = Utf8               iterable$u0020asJava$
   #45 = Utf8               (Lscala/collection/convert/ToJavaImplicits;Lscala/collection/Iterable;)Ljava/lang/Iterable;
   #46 = Utf8               i
   #47 = Utf8               iterable$u0020asJava
   #48 = Utf8               (Lscala/collection/Iterable;)Ljava/lang/Iterable;
   #49 = NameAndType        #47:#48       // iterable$u0020asJava:(Lscala/collection/Iterable;)Ljava/lang/Iterable;
   #50 = InterfaceMethodref #2.#49        // scala/collection/convert/ToJavaImplicits.iterable$u0020asJava:(Lscala/collection/Iterable;)Ljava/lang/Iterable;
   #51 = Utf8               Lscala/collection/Iterable;
   #52 = Utf8               <A:Ljava/lang/Object;>(Lscala/collection/Iterable<TA;>;)Ljava/lang/Iterable<TA;>;
   #53 = Utf8               (Lscala/collection/convert/AsJavaConverters;Lscala/collection/Iterable;)Ljava/lang/Iterable;
   #54 = NameAndType        #28:#53       // asJava$:(Lscala/collection/convert/AsJavaConverters;Lscala/collection/Iterable;)Ljava/lang/Iterable;
   #55 = InterfaceMethodref #27.#54       // scala/collection/convert/AsJavaConverters.asJava$:(Lscala/collection/convert/AsJavaConverters;Lscala/collection/Iterable;)Ljava/lang/Iterable;
   #56 = Utf8               collection$u0020asJava$
   #57 = Utf8               (Lscala/collection/convert/ToJavaImplicits;Lscala/collection/Iterable;)Ljava/util/Collection;
   #58 = Utf8               collection$u0020asJava
   #59 = Utf8               (Lscala/collection/Iterable;)Ljava/util/Collection;
   #60 = NameAndType        #58:#59       // collection$u0020asJava:(Lscala/collection/Iterable;)Ljava/util/Collection;
   #61 = InterfaceMethodref #2.#60        // scala/collection/convert/ToJavaImplicits.collection$u0020asJava:(Lscala/collection/Iterable;)Ljava/util/Collection;
   #62 = Utf8               <A:Ljava/lang/Object;>(Lscala/collection/Iterable<TA;>;)Ljava/util/Collection<TA;>;
   #63 = Utf8               asJavaCollection$
   #64 = Utf8               (Lscala/collection/convert/AsJavaConverters;Lscala/collection/Iterable;)Ljava/util/Collection;
   #65 = NameAndType        #63:#64       // asJavaCollection$:(Lscala/collection/convert/AsJavaConverters;Lscala/collection/Iterable;)Ljava/util/Collection;
   #66 = InterfaceMethodref #27.#65       // scala/collection/convert/AsJavaConverters.asJavaCollection$:(Lscala/collection/convert/AsJavaConverters;Lscala/collection/Iterable;)Ljava/util/Collection;
   #67 = Utf8               buffer$u0020AsJavaList$
   #68 = Utf8               (Lscala/collection/convert/ToJavaImplicits;Lscala/collection/mutable/Buffer;)Ljava/util/List;
   #69 = Utf8               b
   #70 = Utf8               buffer$u0020AsJavaList
   #71 = Utf8               (Lscala/collection/mutable/Buffer;)Ljava/util/List;
   #72 = NameAndType        #70:#71       // buffer$u0020AsJavaList:(Lscala/collection/mutable/Buffer;)Ljava/util/List;
   #73 = InterfaceMethodref #2.#72        // scala/collection/convert/ToJavaImplicits.buffer$u0020AsJavaList:(Lscala/collection/mutable/Buffer;)Ljava/util/List;
   #74 = Utf8               Lscala/collection/mutable/Buffer;
   #75 = Utf8               <A:Ljava/lang/Object;>(Lscala/collection/mutable/Buffer<TA;>;)Ljava/util/List<TA;>;
   #76 = Utf8               (Lscala/collection/convert/AsJavaConverters;Lscala/collection/mutable/Buffer;)Ljava/util/List;
   #77 = NameAndType        #28:#76       // asJava$:(Lscala/collection/convert/AsJavaConverters;Lscala/collection/mutable/Buffer;)Ljava/util/List;
   #78 = InterfaceMethodref #27.#77       // scala/collection/convert/AsJavaConverters.asJava$:(Lscala/collection/convert/AsJavaConverters;Lscala/collection/mutable/Buffer;)Ljava/util/List;
   #79 = Utf8               mutableSeq$u0020AsJavaList$
   #80 = Utf8               (Lscala/collection/convert/ToJavaImplicits;Lscala/collection/mutable/Seq;)Ljava/util/List;
   #81 = Utf8               seq
   #82 = Utf8               mutableSeq$u0020AsJavaList
   #83 = Utf8               (Lscala/collection/mutable/Seq;)Ljava/util/List;
   #84 = NameAndType        #82:#83       // mutableSeq$u0020AsJavaList:(Lscala/collection/mutable/Seq;)Ljava/util/List;
   #85 = InterfaceMethodref #2.#84        // scala/collection/convert/ToJavaImplicits.mutableSeq$u0020AsJavaList:(Lscala/collection/mutable/Seq;)Ljava/util/List;
   #86 = Utf8               Lscala/collection/mutable/Seq;
   #87 = Utf8               <A:Ljava/lang/Object;>(Lscala/collection/mutable/Seq<TA;>;)Ljava/util/List<TA;>;
   #88 = Utf8               (Lscala/collection/convert/AsJavaConverters;Lscala/collection/mutable/Seq;)Ljava/util/List;
   #89 = NameAndType        #28:#88       // asJava$:(Lscala/collection/convert/AsJavaConverters;Lscala/collection/mutable/Seq;)Ljava/util/List;
   #90 = InterfaceMethodref #27.#89       // scala/collection/convert/AsJavaConverters.asJava$:(Lscala/collection/convert/AsJavaConverters;Lscala/collection/mutable/Seq;)Ljava/util/List;
   #91 = Utf8               seq$u0020AsJavaList$
   #92 = Utf8               (Lscala/collection/convert/ToJavaImplicits;Lscala/collection/Seq;)Ljava/util/List;
   #93 = Utf8               seq$u0020AsJavaList
   #94 = Utf8               (Lscala/collection/Seq;)Ljava/util/List;
   #95 = NameAndType        #93:#94       // seq$u0020AsJavaList:(Lscala/collection/Seq;)Ljava/util/List;
   #96 = InterfaceMethodref #2.#95        // scala/collection/convert/ToJavaImplicits.seq$u0020AsJavaList:(Lscala/collection/Seq;)Ljava/util/List;
   #97 = Utf8               Lscala/collection/Seq;
   #98 = Utf8               <A:Ljava/lang/Object;>(Lscala/collection/Seq<TA;>;)Ljava/util/List<TA;>;
   #99 = Utf8               (Lscala/collection/convert/AsJavaConverters;Lscala/collection/Seq;)Ljava/util/List;
  #100 = NameAndType        #28:#99       // asJava$:(Lscala/collection/convert/AsJavaConverters;Lscala/collection/Seq;)Ljava/util/List;
  #101 = InterfaceMethodref #27.#100      // scala/collection/convert/AsJavaConverters.asJava$:(Lscala/collection/convert/AsJavaConverters;Lscala/collection/Seq;)Ljava/util/List;
  #102 = Utf8               mutableSet$u0020AsJavaSet$
  #103 = Utf8               (Lscala/collection/convert/ToJavaImplicits;Lscala/collection/mutable/Set;)Ljava/util/Set;
  #104 = Utf8               s
  #105 = Utf8               mutableSet$u0020AsJavaSet
  #106 = Utf8               (Lscala/collection/mutable/Set;)Ljava/util/Set;
  #107 = NameAndType        #105:#106     // mutableSet$u0020AsJavaSet:(Lscala/collection/mutable/Set;)Ljava/util/Set;
  #108 = InterfaceMethodref #2.#107       // scala/collection/convert/ToJavaImplicits.mutableSet$u0020AsJavaSet:(Lscala/collection/mutable/Set;)Ljava/util/Set;
  #109 = Utf8               Lscala/collection/mutable/Set;
  #110 = Utf8               <A:Ljava/lang/Object;>(Lscala/collection/mutable/Set<TA;>;)Ljava/util/Set<TA;>;
  #111 = Utf8               (Lscala/collection/convert/AsJavaConverters;Lscala/collection/mutable/Set;)Ljava/util/Set;
  #112 = NameAndType        #28:#111      // asJava$:(Lscala/collection/convert/AsJavaConverters;Lscala/collection/mutable/Set;)Ljava/util/Set;
  #113 = InterfaceMethodref #27.#112      // scala/collection/convert/AsJavaConverters.asJava$:(Lscala/collection/convert/AsJavaConverters;Lscala/collection/mutable/Set;)Ljava/util/Set;
  #114 = Utf8               set$u0020AsJavaSet$
  #115 = Utf8               (Lscala/collection/convert/ToJavaImplicits;Lscala/collection/Set;)Ljava/util/Set;
  #116 = Utf8               set$u0020AsJavaSet
  #117 = Utf8               (Lscala/collection/Set;)Ljava/util/Set;
  #118 = NameAndType        #116:#117     // set$u0020AsJavaSet:(Lscala/collection/Set;)Ljava/util/Set;
  #119 = InterfaceMethodref #2.#118       // scala/collection/convert/ToJavaImplicits.set$u0020AsJavaSet:(Lscala/collection/Set;)Ljava/util/Set;
  #120 = Utf8               Lscala/collection/Set;
  #121 = Utf8               <A:Ljava/lang/Object;>(Lscala/collection/Set<TA;>;)Ljava/util/Set<TA;>;
  #122 = Utf8               (Lscala/collection/convert/AsJavaConverters;Lscala/collection/Set;)Ljava/util/Set;
  #123 = NameAndType        #28:#122      // asJava$:(Lscala/collection/convert/AsJavaConverters;Lscala/collection/Set;)Ljava/util/Set;
  #124 = InterfaceMethodref #27.#123      // scala/collection/convert/AsJavaConverters.asJava$:(Lscala/collection/convert/AsJavaConverters;Lscala/collection/Set;)Ljava/util/Set;
  #125 = Utf8               mutableMap$u0020AsJavaMap$
  #126 = Utf8               (Lscala/collection/convert/ToJavaImplicits;Lscala/collection/mutable/Map;)Ljava/util/Map;
  #127 = Utf8               m
  #128 = Utf8               mutableMap$u0020AsJavaMap
  #129 = Utf8               (Lscala/collection/mutable/Map;)Ljava/util/Map;
  #130 = NameAndType        #128:#129     // mutableMap$u0020AsJavaMap:(Lscala/collection/mutable/Map;)Ljava/util/Map;
  #131 = InterfaceMethodref #2.#130       // scala/collection/convert/ToJavaImplicits.mutableMap$u0020AsJavaMap:(Lscala/collection/mutable/Map;)Ljava/util/Map;
  #132 = Utf8               Lscala/collection/mutable/Map;
  #133 = Utf8               <K:Ljava/lang/Object;V:Ljava/lang/Object;>(Lscala/collection/mutable/Map<TK;TV;>;)Ljava/util/Map<TK;TV;>;
  #134 = Utf8               (Lscala/collection/convert/AsJavaConverters;Lscala/collection/mutable/Map;)Ljava/util/Map;
  #135 = NameAndType        #28:#134      // asJava$:(Lscala/collection/convert/AsJavaConverters;Lscala/collection/mutable/Map;)Ljava/util/Map;
  #136 = InterfaceMethodref #27.#135      // scala/collection/convert/AsJavaConverters.asJava$:(Lscala/collection/convert/AsJavaConverters;Lscala/collection/mutable/Map;)Ljava/util/Map;
  #137 = Utf8               dictionary$u0020asJava$
  #138 = Utf8               (Lscala/collection/convert/ToJavaImplicits;Lscala/collection/mutable/Map;)Ljava/util/Dictionary;
  #139 = Utf8               dictionary$u0020asJava
  #140 = Utf8               (Lscala/collection/mutable/Map;)Ljava/util/Dictionary;
  #141 = NameAndType        #139:#140     // dictionary$u0020asJava:(Lscala/collection/mutable/Map;)Ljava/util/Dictionary;
  #142 = InterfaceMethodref #2.#141       // scala/collection/convert/ToJavaImplicits.dictionary$u0020asJava:(Lscala/collection/mutable/Map;)Ljava/util/Dictionary;
  #143 = Utf8               <K:Ljava/lang/Object;V:Ljava/lang/Object;>(Lscala/collection/mutable/Map<TK;TV;>;)Ljava/util/Dictionary<TK;TV;>;
  #144 = Utf8               asJavaDictionary$
  #145 = Utf8               (Lscala/collection/convert/AsJavaConverters;Lscala/collection/mutable/Map;)Ljava/util/Dictionary;
  #146 = NameAndType        #144:#145     // asJavaDictionary$:(Lscala/collection/convert/AsJavaConverters;Lscala/collection/mutable/Map;)Ljava/util/Dictionary;
  #147 = InterfaceMethodref #27.#146      // scala/collection/convert/AsJavaConverters.asJavaDictionary$:(Lscala/collection/convert/AsJavaConverters;Lscala/collection/mutable/Map;)Ljava/util/Dictionary;
  #148 = Utf8               map$u0020AsJavaMap$
  #149 = Utf8               (Lscala/collection/convert/ToJavaImplicits;Lscala/collection/Map;)Ljava/util/Map;
  #150 = Utf8               map$u0020AsJavaMap
  #151 = Utf8               (Lscala/collection/Map;)Ljava/util/Map;
  #152 = NameAndType        #150:#151     // map$u0020AsJavaMap:(Lscala/collection/Map;)Ljava/util/Map;
  #153 = InterfaceMethodref #2.#152       // scala/collection/convert/ToJavaImplicits.map$u0020AsJavaMap:(Lscala/collection/Map;)Ljava/util/Map;
  #154 = Utf8               Lscala/collection/Map;
  #155 = Utf8               <K:Ljava/lang/Object;V:Ljava/lang/Object;>(Lscala/collection/Map<TK;TV;>;)Ljava/util/Map<TK;TV;>;
  #156 = Utf8               (Lscala/collection/convert/AsJavaConverters;Lscala/collection/Map;)Ljava/util/Map;
  #157 = NameAndType        #28:#156      // asJava$:(Lscala/collection/convert/AsJavaConverters;Lscala/collection/Map;)Ljava/util/Map;
  #158 = InterfaceMethodref #27.#157      // scala/collection/convert/AsJavaConverters.asJava$:(Lscala/collection/convert/AsJavaConverters;Lscala/collection/Map;)Ljava/util/Map;
  #159 = Utf8               map$u0020AsJavaConcurrentMap$
  #160 = Utf8               (Lscala/collection/convert/ToJavaImplicits;Lscala/collection/concurrent/Map;)Ljava/util/concurrent/ConcurrentMap;
  #161 = Utf8               map$u0020AsJavaConcurrentMap
  #162 = Utf8               (Lscala/collection/concurrent/Map;)Ljava/util/concurrent/ConcurrentMap;
  #163 = NameAndType        #161:#162     // map$u0020AsJavaConcurrentMap:(Lscala/collection/concurrent/Map;)Ljava/util/concurrent/ConcurrentMap;
  #164 = InterfaceMethodref #2.#163       // scala/collection/convert/ToJavaImplicits.map$u0020AsJavaConcurrentMap:(Lscala/collection/concurrent/Map;)Ljava/util/concurrent/ConcurrentMap;
  #165 = Utf8               Lscala/collection/concurrent/Map;
  #166 = Utf8               <K:Ljava/lang/Object;V:Ljava/lang/Object;>(Lscala/collection/concurrent/Map<TK;TV;>;)Ljava/util/concurrent/ConcurrentMap<TK;TV;>;
  #167 = Utf8               (Lscala/collection/convert/AsJavaConverters;Lscala/collection/concurrent/Map;)Ljava/util/concurrent/ConcurrentMap;
  #168 = NameAndType        #28:#167      // asJava$:(Lscala/collection/convert/AsJavaConverters;Lscala/collection/concurrent/Map;)Ljava/util/concurrent/ConcurrentMap;
  #169 = InterfaceMethodref #27.#168      // scala/collection/convert/AsJavaConverters.asJava$:(Lscala/collection/convert/AsJavaConverters;Lscala/collection/concurrent/Map;)Ljava/util/concurrent/ConcurrentMap;
  #170 = Utf8               $init$
  #171 = Utf8               (Lscala/collection/convert/ToJavaImplicits;)V
  #172 = Utf8               Code
  #173 = Utf8               LineNumberTable
  #174 = Utf8               LocalVariableTable
  #175 = Utf8               MethodParameters
  #176 = Utf8               Signature
  #177 = Utf8               SourceFile
  #178 = Utf8               Deprecated
  #179 = Utf8               RuntimeVisibleAnnotations
  #180 = Utf8               ScalaInlineInfo
  #181 = Utf8               ScalaSig
{
  public static java.util.Iterator iterator$u0020asJava$(scala.collection.convert.ToJavaImplicits, scala.collection.Iterator);
    descriptor: (Lscala/collection/convert/ToJavaImplicits;Lscala/collection/Iterator;)Ljava/util/Iterator;
    flags: (0x1009) ACC_PUBLIC, ACC_STATIC, ACC_SYNTHETIC
    Code:
      stack=2, locals=2, args_size=2
         0: aload_0
         1: aload_1
         2: invokespecial #16                 // InterfaceMethod iterator$u0020asJava:(Lscala/collection/Iterator;)Ljava/util/Iterator;
         5: areturn
      LineNumberTable:
        line 83: 0
      LocalVariableTable:
        Start  Length  Slot  Name   Signature
            0       6     0 $this   Lscala/collection/convert/ToJavaImplicits;
            0       6     1    it   Lscala/collection/Iterator;
    MethodParameters:
      Name                           Flags
      $this                          final synthetic
      it                             final

  public default <A extends java.lang.Object> java.util.Iterator<A> iterator$u0020asJava(scala.collection.Iterator<A>);
    descriptor: (Lscala/collection/Iterator;)Ljava/util/Iterator;
    flags: (0x0001) ACC_PUBLIC
    Code:
      stack=2, locals=2, args_size=2
         0: getstatic     #25                 // Field scala/collection/JavaConverters$.MODULE$:Lscala/collection/JavaConverters$;
         3: aload_1
         4: invokestatic  #31                 // InterfaceMethod scala/collection/convert/AsJavaConverters.asJava$:(Lscala/collection/convert/AsJavaConverters;Lscala/collection/Iterator;)Ljava/util/Iterator;
         7: areturn
      LineNumberTable:
        line 83: 0
      LocalVariableTable:
        Start  Length  Slot  Name   Signature
            0       8     0  this   Lscala/collection/convert/ToJavaImplicits;
            0       8     1    it   Lscala/collection/Iterator;
    Signature: #19                          // <A:Ljava/lang/Object;>(Lscala/collection/Iterator<TA;>;)Ljava/util/Iterator<TA;>;
    MethodParameters:
      Name                           Flags
      it                             final

  public static java.util.Enumeration enumeration$u0020asJava$(scala.collection.convert.ToJavaImplicits, scala.collection.Iterator);
    descriptor: (Lscala/collection/convert/ToJavaImplicits;Lscala/collection/Iterator;)Ljava/util/Enumeration;
    flags: (0x1009) ACC_PUBLIC, ACC_STATIC, ACC_SYNTHETIC
    Code:
      stack=2, locals=2, args_size=2
         0: aload_0
         1: aload_1
         2: invokespecial #38                 // InterfaceMethod enumeration$u0020asJava:(Lscala/collection/Iterator;)Ljava/util/Enumeration;
         5: areturn
      LineNumberTable:
        line 88: 0
      LocalVariableTable:
        Start  Length  Slot  Name   Signature
            0       6     0 $this   Lscala/collection/convert/ToJavaImplicits;
            0       6     1    it   Lscala/collection/Iterator;
    MethodParameters:
      Name                           Flags
      $this                          final synthetic
      it                             final

  public default <A extends java.lang.Object> java.util.Enumeration<A> enumeration$u0020asJava(scala.collection.Iterator<A>);
    descriptor: (Lscala/collection/Iterator;)Ljava/util/Enumeration;
    flags: (0x0001) ACC_PUBLIC
    Code:
      stack=2, locals=2, args_size=2
         0: getstatic     #25                 // Field scala/collection/JavaConverters$.MODULE$:Lscala/collection/JavaConverters$;
         3: aload_1
         4: invokestatic  #43                 // InterfaceMethod scala/collection/convert/AsJavaConverters.asJavaEnumeration$:(Lscala/collection/convert/AsJavaConverters;Lscala/collection/Iterator;)Ljava/util/Enumeration;
         7: areturn
      LineNumberTable:
        line 88: 0
      LocalVariableTable:
        Start  Length  Slot  Name   Signature
            0       8     0  this   Lscala/collection/convert/ToJavaImplicits;
            0       8     1    it   Lscala/collection/Iterator;
    Signature: #39                          // <A:Ljava/lang/Object;>(Lscala/collection/Iterator<TA;>;)Ljava/util/Enumeration<TA;>;
    MethodParameters:
      Name                           Flags
      it                             final

  public static java.lang.Iterable iterable$u0020asJava$(scala.collection.convert.ToJavaImplicits, scala.collection.Iterable);
    descriptor: (Lscala/collection/convert/ToJavaImplicits;Lscala/collection/Iterable;)Ljava/lang/Iterable;
    flags: (0x1009) ACC_PUBLIC, ACC_STATIC, ACC_SYNTHETIC
    Code:
      stack=2, locals=2, args_size=2
         0: aload_0
         1: aload_1
         2: invokespecial #50                 // InterfaceMethod iterable$u0020asJava:(Lscala/collection/Iterable;)Ljava/lang/Iterable;
         5: areturn
      LineNumberTable:
        line 93: 0
      LocalVariableTable:
        Start  Length  Slot  Name   Signature
            0       6     0 $this   Lscala/collection/convert/ToJavaImplicits;
            0       6     1     i   Lscala/collection/Iterable;
    MethodParameters:
      Name                           Flags
      $this                          final synthetic
      i                              final

  public default <A extends java.lang.Object> java.lang.Iterable<A> iterable$u0020asJava(scala.collection.Iterable<A>);
    descriptor: (Lscala/collection/Iterable;)Ljava/lang/Iterable;
    flags: (0x0001) ACC_PUBLIC
    Code:
      stack=2, locals=2, args_size=2
         0: getstatic     #25                 // Field scala/collection/JavaConverters$.MODULE$:Lscala/collection/JavaConverters$;
         3: aload_1
         4: invokestatic  #55                 // InterfaceMethod scala/collection/convert/AsJavaConverters.asJava$:(Lscala/collection/convert/AsJavaConverters;Lscala/collection/Iterable;)Ljava/lang/Iterable;
         7: areturn
      LineNumberTable:
        line 93: 0
      LocalVariableTable:
        Start  Length  Slot  Name   Signature
            0       8     0  this   Lscala/collection/convert/ToJavaImplicits;
            0       8     1     i   Lscala/collection/Iterable;
    Signature: #52                          // <A:Ljava/lang/Object;>(Lscala/collection/Iterable<TA;>;)Ljava/lang/Iterable<TA;>;
    MethodParameters:
      Name                           Flags
      i                              final

  public static java.util.Collection collection$u0020asJava$(scala.collection.convert.ToJavaImplicits, scala.collection.Iterable);
    descriptor: (Lscala/collection/convert/ToJavaImplicits;Lscala/collection/Iterable;)Ljava/util/Collection;
    flags: (0x1009) ACC_PUBLIC, ACC_STATIC, ACC_SYNTHETIC
    Code:
      stack=2, locals=2, args_size=2
         0: aload_0
         1: aload_1
         2: invokespecial #61                 // InterfaceMethod collection$u0020asJava:(Lscala/collection/Iterable;)Ljava/util/Collection;
         5: areturn
      LineNumberTable:
        line 98: 0
      LocalVariableTable:
        Start  Length  Slot  Name   Signature
            0       6     0 $this   Lscala/collection/convert/ToJavaImplicits;
            0       6     1    it   Lscala/collection/Iterable;
    MethodParameters:
      Name                           Flags
      $this                          final synthetic
      it                             final

  public default <A extends java.lang.Object> java.util.Collection<A> collection$u0020asJava(scala.collection.Iterable<A>);
    descriptor: (Lscala/collection/Iterable;)Ljava/util/Collection;
    flags: (0x0001) ACC_PUBLIC
    Code:
      stack=2, locals=2, args_size=2
         0: getstatic     #25                 // Field scala/collection/JavaConverters$.MODULE$:Lscala/collection/JavaConverters$;
         3: aload_1
         4: invokestatic  #66                 // InterfaceMethod scala/collection/convert/AsJavaConverters.asJavaCollection$:(Lscala/collection/convert/AsJavaConverters;Lscala/collection/Iterable;)Ljava/util/Collection;
         7: areturn
      LineNumberTable:
        line 98: 0
      LocalVariableTable:
        Start  Length  Slot  Name   Signature
            0       8     0  this   Lscala/collection/convert/ToJavaImplicits;
            0       8     1    it   Lscala/collection/Iterable;
    Signature: #62                          // <A:Ljava/lang/Object;>(Lscala/collection/Iterable<TA;>;)Ljava/util/Collection<TA;>;
    MethodParameters:
      Name                           Flags
      it                             final

  public static java.util.List buffer$u0020AsJavaList$(scala.collection.convert.ToJavaImplicits, scala.collection.mutable.Buffer);
    descriptor: (Lscala/collection/convert/ToJavaImplicits;Lscala/collection/mutable/Buffer;)Ljava/util/List;
    flags: (0x1009) ACC_PUBLIC, ACC_STATIC, ACC_SYNTHETIC
    Code:
      stack=2, locals=2, args_size=2
         0: aload_0
         1: aload_1
         2: invokespecial #73                 // InterfaceMethod buffer$u0020AsJavaList:(Lscala/collection/mutable/Buffer;)Ljava/util/List;
         5: areturn
      LineNumberTable:
        line 103: 0
      LocalVariableTable:
        Start  Length  Slot  Name   Signature
            0       6     0 $this   Lscala/collection/convert/ToJavaImplicits;
            0       6     1     b   Lscala/collection/mutable/Buffer;
    MethodParameters:
      Name                           Flags
      $this                          final synthetic
      b                              final

  public default <A extends java.lang.Object> java.util.List<A> buffer$u0020AsJavaList(scala.collection.mutable.Buffer<A>);
    descriptor: (Lscala/collection/mutable/Buffer;)Ljava/util/List;
    flags: (0x0001) ACC_PUBLIC
    Code:
      stack=2, locals=2, args_size=2
         0: getstatic     #25                 // Field scala/collection/JavaConverters$.MODULE$:Lscala/collection/JavaConverters$;
         3: aload_1
         4: invokestatic  #78                 // InterfaceMethod scala/collection/convert/AsJavaConverters.asJava$:(Lscala/collection/convert/AsJavaConverters;Lscala/collection/mutable/Buffer;)Ljava/util/List;
         7: areturn
      LineNumberTable:
        line 103: 0
      LocalVariableTable:
        Start  Length  Slot  Name   Signature
            0       8     0  this   Lscala/collection/convert/ToJavaImplicits;
            0       8     1     b   Lscala/collection/mutable/Buffer;
    Signature: #75                          // <A:Ljava/lang/Object;>(Lscala/collection/mutable/Buffer<TA;>;)Ljava/util/List<TA;>;
    MethodParameters:
      Name                           Flags
      b                              final

  public static java.util.List mutableSeq$u0020AsJavaList$(scala.collection.convert.ToJavaImplicits, scala.collection.mutable.Seq);
    descriptor: (Lscala/collection/convert/ToJavaImplicits;Lscala/collection/mutable/Seq;)Ljava/util/List;
    flags: (0x1009) ACC_PUBLIC, ACC_STATIC, ACC_SYNTHETIC
    Code:
      stack=2, locals=2, args_size=2
         0: aload_0
         1: aload_1
         2: invokespecial #85                 // InterfaceMethod mutableSeq$u0020AsJavaList:(Lscala/collection/mutable/Seq;)Ljava/util/List;
         5: areturn
      LineNumberTable:
        line 108: 0
      LocalVariableTable:
        Start  Length  Slot  Name   Signature
            0       6     0 $this   Lscala/collection/convert/ToJavaImplicits;
            0       6     1   seq   Lscala/collection/mutable/Seq;
    MethodParameters:
      Name                           Flags
      $this                          final synthetic
      seq                            final

  public default <A extends java.lang.Object> java.util.List<A> mutableSeq$u0020AsJavaList(scala.collection.mutable.Seq<A>);
    descriptor: (Lscala/collection/mutable/Seq;)Ljava/util/List;
    flags: (0x0001) ACC_PUBLIC
    Code:
      stack=2, locals=2, args_size=2
         0: getstatic     #25                 // Field scala/collection/JavaConverters$.MODULE$:Lscala/collection/JavaConverters$;
         3: aload_1
         4: invokestatic  #90                 // InterfaceMethod scala/collection/convert/AsJavaConverters.asJava$:(Lscala/collection/convert/AsJavaConverters;Lscala/collection/mutable/Seq;)Ljava/util/List;
         7: areturn
      LineNumberTable:
        line 108: 0
      LocalVariableTable:
        Start  Length  Slot  Name   Signature
            0       8     0  this   Lscala/collection/convert/ToJavaImplicits;
            0       8     1   seq   Lscala/collection/mutable/Seq;
    Signature: #87                          // <A:Ljava/lang/Object;>(Lscala/collection/mutable/Seq<TA;>;)Ljava/util/List<TA;>;
    MethodParameters:
      Name                           Flags
      seq                            final

  public static java.util.List seq$u0020AsJavaList$(scala.collection.convert.ToJavaImplicits, scala.collection.Seq);
    descriptor: (Lscala/collection/convert/ToJavaImplicits;Lscala/collection/Seq;)Ljava/util/List;
    flags: (0x1009) ACC_PUBLIC, ACC_STATIC, ACC_SYNTHETIC
    Code:
      stack=2, locals=2, args_size=2
         0: aload_0
         1: aload_1
         2: invokespecial #96                 // InterfaceMethod seq$u0020AsJavaList:(Lscala/collection/Seq;)Ljava/util/List;
         5: areturn
      LineNumberTable:
        line 113: 0
      LocalVariableTable:
        Start  Length  Slot  Name   Signature
            0       6     0 $this   Lscala/collection/convert/ToJavaImplicits;
            0       6     1   seq   Lscala/collection/Seq;
    MethodParameters:
      Name                           Flags
      $this                          final synthetic
      seq                            final

  public default <A extends java.lang.Object> java.util.List<A> seq$u0020AsJavaList(scala.collection.Seq<A>);
    descriptor: (Lscala/collection/Seq;)Ljava/util/List;
    flags: (0x0001) ACC_PUBLIC
    Code:
      stack=2, locals=2, args_size=2
         0: getstatic     #25                 // Field scala/collection/JavaConverters$.MODULE$:Lscala/collection/JavaConverters$;
         3: aload_1
         4: invokestatic  #101                // InterfaceMethod scala/collection/convert/AsJavaConverters.asJava$:(Lscala/collection/convert/AsJavaConverters;Lscala/collection/Seq;)Ljava/util/List;
         7: areturn
      LineNumberTable:
        line 113: 0
      LocalVariableTable:
        Start  Length  Slot  Name   Signature
            0       8     0  this   Lscala/collection/convert/ToJavaImplicits;
            0       8     1   seq   Lscala/collection/Seq;
    Signature: #98                          // <A:Ljava/lang/Object;>(Lscala/collection/Seq<TA;>;)Ljava/util/List<TA;>;
    MethodParameters:
      Name                           Flags
      seq                            final

  public static java.util.Set mutableSet$u0020AsJavaSet$(scala.collection.convert.ToJavaImplicits, scala.collection.mutable.Set);
    descriptor: (Lscala/collection/convert/ToJavaImplicits;Lscala/collection/mutable/Set;)Ljava/util/Set;
    flags: (0x1009) ACC_PUBLIC, ACC_STATIC, ACC_SYNTHETIC
    Code:
      stack=2, locals=2, args_size=2
         0: aload_0
         1: aload_1
         2: invokespecial #108                // InterfaceMethod mutableSet$u0020AsJavaSet:(Lscala/collection/mutable/Set;)Ljava/util/Set;
         5: areturn
      LineNumberTable:
        line 118: 0
      LocalVariableTable:
        Start  Length  Slot  Name   Signature
            0       6     0 $this   Lscala/collection/convert/ToJavaImplicits;
            0       6     1     s   Lscala/collection/mutable/Set;
    MethodParameters:
      Name                           Flags
      $this                          final synthetic
      s                              final

  public default <A extends java.lang.Object> java.util.Set<A> mutableSet$u0020AsJavaSet(scala.collection.mutable.Set<A>);
    descriptor: (Lscala/collection/mutable/Set;)Ljava/util/Set;
    flags: (0x0001) ACC_PUBLIC
    Code:
      stack=2, locals=2, args_size=2
         0: getstatic     #25                 // Field scala/collection/JavaConverters$.MODULE$:Lscala/collection/JavaConverters$;
         3: aload_1
         4: invokestatic  #113                // InterfaceMethod scala/collection/convert/AsJavaConverters.asJava$:(Lscala/collection/convert/AsJavaConverters;Lscala/collection/mutable/Set;)Ljava/util/Set;
         7: areturn
      LineNumberTable:
        line 118: 0
      LocalVariableTable:
        Start  Length  Slot  Name   Signature
            0       8     0  this   Lscala/collection/convert/ToJavaImplicits;
            0       8     1     s   Lscala/collection/mutable/Set;
    Signature: #110                         // <A:Ljava/lang/Object;>(Lscala/collection/mutable/Set<TA;>;)Ljava/util/Set<TA;>;
    MethodParameters:
      Name                           Flags
      s                              final

  public static java.util.Set set$u0020AsJavaSet$(scala.collection.convert.ToJavaImplicits, scala.collection.Set);
    descriptor: (Lscala/collection/convert/ToJavaImplicits;Lscala/collection/Set;)Ljava/util/Set;
    flags: (0x1009) ACC_PUBLIC, ACC_STATIC, ACC_SYNTHETIC
    Code:
      stack=2, locals=2, args_size=2
         0: aload_0
         1: aload_1
         2: invokespecial #119                // InterfaceMethod set$u0020AsJavaSet:(Lscala/collection/Set;)Ljava/util/Set;
         5: areturn
      LineNumberTable:
        line 123: 0
      LocalVariableTable:
        Start  Length  Slot  Name   Signature
            0       6     0 $this   Lscala/collection/convert/ToJavaImplicits;
            0       6     1     s   Lscala/collection/Set;
    MethodParameters:
      Name                           Flags
      $this                          final synthetic
      s                              final

  public default <A extends java.lang.Object> java.util.Set<A> set$u0020AsJavaSet(scala.collection.Set<A>);
    descriptor: (Lscala/collection/Set;)Ljava/util/Set;
    flags: (0x0001) ACC_PUBLIC
    Code:
      stack=2, locals=2, args_size=2
         0: getstatic     #25                 // Field scala/collection/JavaConverters$.MODULE$:Lscala/collection/JavaConverters$;
         3: aload_1
         4: invokestatic  #124                // InterfaceMethod scala/collection/convert/AsJavaConverters.asJava$:(Lscala/collection/convert/AsJavaConverters;Lscala/collection/Set;)Ljava/util/Set;
         7: areturn
      LineNumberTable:
        line 123: 0
      LocalVariableTable:
        Start  Length  Slot  Name   Signature
            0       8     0  this   Lscala/collection/convert/ToJavaImplicits;
            0       8     1     s   Lscala/collection/Set;
    Signature: #121                         // <A:Ljava/lang/Object;>(Lscala/collection/Set<TA;>;)Ljava/util/Set<TA;>;
    MethodParameters:
      Name                           Flags
      s                              final

  public static java.util.Map mutableMap$u0020AsJavaMap$(scala.collection.convert.ToJavaImplicits, scala.collection.mutable.Map);
    descriptor: (Lscala/collection/convert/ToJavaImplicits;Lscala/collection/mutable/Map;)Ljava/util/Map;
    flags: (0x1009) ACC_PUBLIC, ACC_STATIC, ACC_SYNTHETIC
    Code:
      stack=2, locals=2, args_size=2
         0: aload_0
         1: aload_1
         2: invokespecial #131                // InterfaceMethod mutableMap$u0020AsJavaMap:(Lscala/collection/mutable/Map;)Ljava/util/Map;
         5: areturn
      LineNumberTable:
        line 128: 0
      LocalVariableTable:
        Start  Length  Slot  Name   Signature
            0       6     0 $this   Lscala/collection/convert/ToJavaImplicits;
            0       6     1     m   Lscala/collection/mutable/Map;
    MethodParameters:
      Name                           Flags
      $this                          final synthetic
      m                              final

  public default <K extends java.lang.Object, V extends java.lang.Object> java.util.Map<K, V> mutableMap$u0020AsJavaMap(scala.collection.mutable.Map<K, V>);
    descriptor: (Lscala/collection/mutable/Map;)Ljava/util/Map;
    flags: (0x0001) ACC_PUBLIC
    Code:
      stack=2, locals=2, args_size=2
         0: getstatic     #25                 // Field scala/collection/JavaConverters$.MODULE$:Lscala/collection/JavaConverters$;
         3: aload_1
         4: invokestatic  #136                // InterfaceMethod scala/collection/convert/AsJavaConverters.asJava$:(Lscala/collection/convert/AsJavaConverters;Lscala/collection/mutable/Map;)Ljava/util/Map;
         7: areturn
      LineNumberTable:
        line 128: 0
      LocalVariableTable:
        Start  Length  Slot  Name   Signature
            0       8     0  this   Lscala/collection/convert/ToJavaImplicits;
            0       8     1     m   Lscala/collection/mutable/Map;
    Signature: #133                         // <K:Ljava/lang/Object;V:Ljava/lang/Object;>(Lscala/collection/mutable/Map<TK;TV;>;)Ljava/util/Map<TK;TV;>;
    MethodParameters:
      Name                           Flags
      m                              final

  public static java.util.Dictionary dictionary$u0020asJava$(scala.collection.convert.ToJavaImplicits, scala.collection.mutable.Map);
    descriptor: (Lscala/collection/convert/ToJavaImplicits;Lscala/collection/mutable/Map;)Ljava/util/Dictionary;
    flags: (0x1009) ACC_PUBLIC, ACC_STATIC, ACC_SYNTHETIC
    Code:
      stack=2, locals=2, args_size=2
         0: aload_0
         1: aload_1
         2: invokespecial #142                // InterfaceMethod dictionary$u0020asJava:(Lscala/collection/mutable/Map;)Ljava/util/Dictionary;
         5: areturn
      LineNumberTable:
        line 133: 0
      LocalVariableTable:
        Start  Length  Slot  Name   Signature
            0       6     0 $this   Lscala/collection/convert/ToJavaImplicits;
            0       6     1     m   Lscala/collection/mutable/Map;
    MethodParameters:
      Name                           Flags
      $this                          final synthetic
      m                              final

  public default <K extends java.lang.Object, V extends java.lang.Object> java.util.Dictionary<K, V> dictionary$u0020asJava(scala.collection.mutable.Map<K, V>);
    descriptor: (Lscala/collection/mutable/Map;)Ljava/util/Dictionary;
    flags: (0x0001) ACC_PUBLIC
    Code:
      stack=2, locals=2, args_size=2
         0: getstatic     #25                 // Field scala/collection/JavaConverters$.MODULE$:Lscala/collection/JavaConverters$;
         3: aload_1
         4: invokestatic  #147                // InterfaceMethod scala/collection/convert/AsJavaConverters.asJavaDictionary$:(Lscala/collection/convert/AsJavaConverters;Lscala/collection/mutable/Map;)Ljava/util/Dictionary;
         7: areturn
      LineNumberTable:
        line 133: 0
      LocalVariableTable:
        Start  Length  Slot  Name   Signature
            0       8     0  this   Lscala/collection/convert/ToJavaImplicits;
            0       8     1     m   Lscala/collection/mutable/Map;
    Signature: #143                         // <K:Ljava/lang/Object;V:Ljava/lang/Object;>(Lscala/collection/mutable/Map<TK;TV;>;)Ljava/util/Dictionary<TK;TV;>;
    MethodParameters:
      Name                           Flags
      m                              final

  public static java.util.Map map$u0020AsJavaMap$(scala.collection.convert.ToJavaImplicits, scala.collection.Map);
    descriptor: (Lscala/collection/convert/ToJavaImplicits;Lscala/collection/Map;)Ljava/util/Map;
    flags: (0x1009) ACC_PUBLIC, ACC_STATIC, ACC_SYNTHETIC
    Code:
      stack=2, locals=2, args_size=2
         0: aload_0
         1: aload_1
         2: invokespecial #153                // InterfaceMethod map$u0020AsJavaMap:(Lscala/collection/Map;)Ljava/util/Map;
         5: areturn
      LineNumberTable:
        line 138: 0
      LocalVariableTable:
        Start  Length  Slot  Name   Signature
            0       6     0 $this   Lscala/collection/convert/ToJavaImplicits;
            0       6     1     m   Lscala/collection/Map;
    MethodParameters:
      Name                           Flags
      $this                          final synthetic
      m                              final

  public default <K extends java.lang.Object, V extends java.lang.Object> java.util.Map<K, V> map$u0020AsJavaMap(scala.collection.Map<K, V>);
    descriptor: (Lscala/collection/Map;)Ljava/util/Map;
    flags: (0x0001) ACC_PUBLIC
    Code:
      stack=2, locals=2, args_size=2
         0: getstatic     #25                 // Field scala/collection/JavaConverters$.MODULE$:Lscala/collection/JavaConverters$;
         3: aload_1
         4: invokestatic  #158                // InterfaceMethod scala/collection/convert/AsJavaConverters.asJava$:(Lscala/collection/convert/AsJavaConverters;Lscala/collection/Map;)Ljava/util/Map;
         7: areturn
      LineNumberTable:
        line 138: 0
      LocalVariableTable:
        Start  Length  Slot  Name   Signature
            0       8     0  this   Lscala/collection/convert/ToJavaImplicits;
            0       8     1     m   Lscala/collection/Map;
    Signature: #155                         // <K:Ljava/lang/Object;V:Ljava/lang/Object;>(Lscala/collection/Map<TK;TV;>;)Ljava/util/Map<TK;TV;>;
    MethodParameters:
      Name                           Flags
      m                              final

  public static java.util.concurrent.ConcurrentMap map$u0020AsJavaConcurrentMap$(scala.collection.convert.ToJavaImplicits, scala.collection.concurrent.Map);
    descriptor: (Lscala/collection/convert/ToJavaImplicits;Lscala/collection/concurrent/Map;)Ljava/util/concurrent/ConcurrentMap;
    flags: (0x1009) ACC_PUBLIC, ACC_STATIC, ACC_SYNTHETIC
    Code:
      stack=2, locals=2, args_size=2
         0: aload_0
         1: aload_1
         2: invokespecial #164                // InterfaceMethod map$u0020AsJavaConcurrentMap:(Lscala/collection/concurrent/Map;)Ljava/util/concurrent/ConcurrentMap;
         5: areturn
      LineNumberTable:
        line 143: 0
      LocalVariableTable:
        Start  Length  Slot  Name   Signature
            0       6     0 $this   Lscala/collection/convert/ToJavaImplicits;
            0       6     1     m   Lscala/collection/concurrent/Map;
    MethodParameters:
      Name                           Flags
      $this                          final synthetic
      m                              final

  public default <K extends java.lang.Object, V extends java.lang.Object> java.util.concurrent.ConcurrentMap<K, V> map$u0020AsJavaConcurrentMap(scala.collection.concurrent.Map<K, V>);
    descriptor: (Lscala/collection/concurrent/Map;)Ljava/util/concurrent/ConcurrentMap;
    flags: (0x0001) ACC_PUBLIC
    Code:
      stack=2, locals=2, args_size=2
         0: getstatic     #25                 // Field scala/collection/JavaConverters$.MODULE$:Lscala/collection/JavaConverters$;
         3: aload_1
         4: invokestatic  #169                // InterfaceMethod scala/collection/convert/AsJavaConverters.asJava$:(Lscala/collection/convert/AsJavaConverters;Lscala/collection/concurrent/Map;)Ljava/util/concurrent/ConcurrentMap;
         7: areturn
      LineNumberTable:
        line 143: 0
      LocalVariableTable:
        Start  Length  Slot  Name   Signature
            0       8     0  this   Lscala/collection/convert/ToJavaImplicits;
            0       8     1     m   Lscala/collection/concurrent/Map;
    Signature: #166                         // <K:Ljava/lang/Object;V:Ljava/lang/Object;>(Lscala/collection/concurrent/Map<TK;TV;>;)Ljava/util/concurrent/ConcurrentMap<TK;TV;>;
    MethodParameters:
      Name                           Flags
      m                              final

  public static void $init$(scala.collection.convert.ToJavaImplicits);
    descriptor: (Lscala/collection/convert/ToJavaImplicits;)V
    flags: (0x0009) ACC_PUBLIC, ACC_STATIC
    Code:
      stack=0, locals=1, args_size=1
         0: return
      LineNumberTable:
        line 79: 0
      LocalVariableTable:
        Start  Length  Slot  Name   Signature
            0       1     0 $this   Lscala/collection/convert/ToJavaImplicits;
    MethodParameters:
      Name                           Flags
      $this                          final synthetic
}
SourceFile: "ImplicitConversions.scala"
Deprecated: true
RuntimeVisibleAnnotations:
  0: #6(#7=s#8)
    scala.reflect.ScalaSignature(
      bytes="\u0006\u0005\u0005]faB\b\u0011!\u0003\r\ta\u0006\u0005\u00069\u0001!\t!\b\u0005\u0006C\u0001!\u0019A\t\u0005\u0006y\u0001!\u0019!\u0010\u0005\u0006\r\u0002!\u0019a\u0012\u0005\u0006+\u0002!\u0019A\u0016\u0005\u0006?\u0002!\u0019\u0001\u0019\u0005\u0006_\u0002!\u0019\u0001\u001d\u0005\u0006u\u0002!\u0019a\u001f\u0005\b\u0003\u000f\u0001A1AA\u0005\u0011\u001d\ty\u0002\u0001C\u0002\u0003CAq!!\r\u0001\t\u0007\t\u0019\u0004C\u0004\u0002R\u0001!\u0019!a\u0015\t\u000f\u0005%\u0004\u0001b\u0001\u0002l!9\u0011q\u0010\u0001\u0005\u0004\u0005\u0005%a\u0004+p\u0015\u00064\u0018-S7qY&\u001c\u0017\u000e^:\u000b\u0005E\u0011\u0012aB2p]Z,\'\u000f\u001e\u0006\u0003\'Q\t!bY8mY\u0016\u001cG/[8o\u0015\u0005)\u0012!B:dC2\f7\u0001A\n\u0003\u0001a\u0001\"!\u0007\u000e\u000e\u0003QI!a\u0007\u000b\u0003\r\u0005s\u0017PU3g\u0003\u0019!\u0013N\\5uIQ\ta\u0004\u0005\u0002\u001a?%\u0011\u0001\u0005\u0006\u0002\u0005+:LG/\u0001\u000bji\u0016\u0014\u0018\r^8sIU\u0004\u0004G\r\u0019bg*\u000bg/Y\u000b\u0003G9\"\"\u0001J\u001c\u0011\u0007\u0015RC&D\u0001\'\u0015\t9\u0003&\u0001\u0003vi&d\'\"A\u0015\u0002\t)\fg/Y\u0005\u0003W\u0019\u0012\u0001\"\u0013;fe\u0006$xN\u001d\t\u0003[9b\u0001\u0001B\u00030\u0005\t\u0007\u0001GA\u0001B#\t\tD\u0007\u0005\u0002\u001ae%\u00111\u0007\u0006\u0002\b\u001d>$\b.\u001b8h!\tIR\'\u0003\u00027)\t\u0019\u0011I\\=\t\u000ba\u0012\u0001\u0019A\u001d\u0002\u0005%$\bc\u0001\u001e<Y5\t!#\u0003\u0002,%\u00059RM\\;nKJ\fG/[8oIU\u0004\u0004G\r\u0019bg*\u000bg/Y\u000b\u0003}\r#\"a\u0010#\u0011\u0007\u0015\u0002%)\u0003\u0002BM\tYQI\\;nKJ\fG/[8o!\ti3\tB\u00030\u0007\t\u0007\u0001\u0007C\u00039\u0007\u0001\u0007Q\tE\u0002;w\t\u000bA#\u001b;fe\u0006\u0014G.\u001a\u0013vaA\u0012\u0004\'Y:KCZ\fWC\u0001%Q)\tI\u0015\u000bE\u0002K\u001b>k\u0011a\u0013\u0006\u0003\u0019\"\nA\u0001\\1oO&\u0011aj\u0013\u0002\t\u0013R,\'/\u00192mKB\u0011Q\u0006\u0015\u0003\u0006_\u0011\u0011\r\u0001\r\u0005\u0006%\u0012\u0001\raU\u0001\u0002SB\u0019!\bV(\n\u00059\u0013\u0012AF2pY2,7\r^5p]\u0012*\b\u0007\r\u001a1CNT\u0015M^1\u0016\u0005]cFC\u0001-^!\r)\u0013lW\u0005\u00035\u001a\u0012!bQ8mY\u0016\u001cG/[8o!\tiC\fB\u00030\u000b\t\u0007\u0001\u0007C\u00039\u000b\u0001\u0007a\fE\u0002;)n\u000baCY;gM\u0016\u0014H%\u001e\u00191eA\n5OS1wC2K7\u000f^\u000b\u0003C\u001a$\"AY4\u0011\u0007\u0015\u001aW-\u0003\u0002eM\t!A*[:u!\tic\rB\u00030\r\t\u0007\u0001\u0007C\u0003i\r\u0001\u0007\u0011.A\u0001c!\rQW.Z\u0007\u0002W*\u0011ANE\u0001\b[V$\u0018M\u00197f\u0013\tq7N\u0001\u0004Ck\u001a4WM]\u0001\u001b[V$\u0018M\u00197f\'\u0016\fH%\u001e\u00191eA\n5OS1wC2K7\u000f^\u000b\u0003cR$\"A];\u0011\u0007\u0015\u001a7\u000f\u0005\u0002.i\u0012)qf\u0002b\u0001a!)ao\u0002a\u0001o\u0006\u00191/Z9\u0011\u0007)D8/\u0003\u0002zW\n\u00191+Z9\u0002\'M,\u0017\u000fJ;1aI\u0002\u0014i\u001d&bm\u0006d\u0015n\u001d;\u0016\u0005q|HcA?\u0002\u0002A\u0019Qe\u0019@\u0011\u00055zH!B\u0018\t\u0005\u0004\u0001\u0004B\u0002<\t\u0001\u0004\t\u0019\u0001\u0005\u0003;\u0003\u000bq\u0018BA=\u0013\u0003eiW\u000f^1cY\u0016\u001cV\r\u001e\u0013vaA\u0012\u0004\'Q:KCZ\f7+\u001a;\u0016\t\u0005-\u0011Q\u0003\u000b\u0005\u0003\u001b\t9\u0002E\u0003&\u0003\u001f\t\u0019\"C\u0002\u0002\u0012\u0019\u00121aU3u!\ri\u0013Q\u0003\u0003\u0006_%\u0011\r\u0001\r\u0005\b\u00033I\u0001\u0019AA\u000e\u0003\u0005\u0019\b#\u00026\u0002\u001e\u0005M\u0011bAA\tW\u0006\u00112/\u001a;%kB\u0002$\u0007M!t\u0015\u00064\u0018mU3u+\u0011\t\u0019#!\u000b\u0015\t\u0005\u0015\u00121\u0006\t\u0006K\u0005=\u0011q\u0005\t\u0004[\u0005%B!B\u0018\u000b\u0005\u0004\u0001\u0004bBA\r\u0015\u0001\u0007\u0011Q\u0006\t\u0006u\u0005=\u0012qE\u0005\u0004\u0003#\u0011\u0012!G7vi\u0006\u0014G.Z\'ba\u0012*\b\u0007\r\u001a1\u0003NT\u0015M^1NCB,b!!\u000e\u0002@\u0005\u0015C\u0003BA\u001c\u0003\u0013\u0002r!JA\u001d\u0003{\t\u0019%C\u0002\u0002<\u0019\u00121!T1q!\ri\u0013q\b\u0003\u0007\u0003\u0003Z!\u0019\u0001\u0019\u0003\u0003-\u00032!LA#\t\u0019\t9e\u0003b\u0001a\t\ta\u000bC\u0004\u0002L-\u0001\r!!\u0014\u0002\u00035\u0004rA[A(\u0003{\t\u0019%C\u0002\u0002<-\fa\u0003Z5di&|g.\u0019:zIU\u0004\u0004G\r\u0019bg*\u000bg/Y\u000b\u0007\u0003+\ny&a\u0019\u0015\t\u0005]\u0013Q\r\t\bK\u0005e\u0013QLA1\u0013\r\tYF\n\u0002\u000b\t&\u001cG/[8oCJL\bcA\u0017\u0002`\u00111\u0011\u0011\t\u0007C\u0002A\u00022!LA2\t\u0019\t9\u0005\u0004b\u0001a!9\u00111\n\u0007A\u0002\u0005\u001d\u0004c\u00026\u0002P\u0005u\u0013\u0011M\u0001\u0013[\u0006\u0004H%\u001e\u00191eA\n5OS1wC6\u000b\u0007/\u0006\u0004\u0002n\u0005M\u0014q\u000f\u000b\u0005\u0003_\nI\bE\u0004&\u0003s\t\t(!\u001e\u0011\u00075\n\u0019\b\u0002\u0004\u0002B5\u0011\r\u0001\r\t\u0004[\u0005]DABA$\u001b\t\u0007\u0001\u0007C\u0004\u0002L5\u0001\r!a\u001f\u0011\u000fi\ni(!\u001d\u0002v%\u0019\u00111\b\n\u000295\f\u0007\u000fJ;1aI\u0002\u0014i\u001d&bm\u0006\u001cuN\\2veJ,g\u000e^\'baV1\u00111QAJ\u0003/#B!!\"\u0002\u001aBA\u0011qQAG\u0003#\u000b)*\u0004\u0002\u0002\n*\u0019\u00111\u0012\u0014\u0002\u0015\r|gnY;se\u0016tG/\u0003\u0003\u0002\u0010\u0006%%!D\"p]\u000e,(O]3oi6\u000b\u0007\u000fE\u0002.\u0003\'#a!!\u0011\u000f\u0005\u0004\u0001\u0004cA\u0017\u0002\u0018\u00121\u0011q\t\bC\u0002ABq!a\u0013\u000f\u0001\u0004\tY\n\u0005\u0005\u0002\u001e\u0006\u0005\u0016\u0011SAK\u001b\t\tyJC\u0002\u0002\fJIA!a\u000f\u0002 \"Z\u0001!!*\u0002,\u00065\u0016\u0011WAZ!\rI\u0012qU\u0005\u0004\u0003S#\"A\u00033faJ,7-\u0019;fI\u00069Q.Z:tC\u001e,\u0017EAAX\u00031*6/\u001a\u0011ag\u000e\fG.\u0019\u0018kI.t3i\u001c7mK\u000e$\u0018n\u001c8D_:4XM\u001d;feN\u0004\u0007%\u001b8ti\u0016\fG-A\u0003tS:\u001cW-\t\u0002\u00026\u00061!GL\u00194]A\u0002"
    )
  ScalaInlineInfo: length = 0x8B (unknown attribute)
   01 00 00 1B 00 AA 00 AB 01 00 46 00 47 00 00 43
   00 44 01 00 3A 00 3B 00 00 38 00 39 01 00 8B 00
   8C 00 00 89 00 8A 01 00 23 00 24 00 00 21 00 22
   01 00 2F 00 30 00 00 2C 00 2D 01 00 0D 00 0E 00
   00 09 00 0A 01 00 A1 00 A2 00 00 9F 00 A0 01 00
   96 00 97 00 00 94 00 95 01 00 80 00 81 00 00 7D
   00 7E 01 00 52 00 53 00 00 4F 00 50 01 00 69 00
   6A 00 00 66 00 67 01 00 5D 00 5E 00 00 5B 00 5C
   01 00 74 00 75 00 00 72 00 73 01
  ScalaSig: length = 0x3 (unknown attribute)
   05 02 00
