Classfile /Users/mw/Projects/slang-braindump/.jar/jar8/assemble/slang-braindump/assemble/content/org/antlr/runtime/debug/DebugTokenStream.class
  Last modified May 29, 2022; size 3428 bytes
  SHA-256 checksum bf4e7d291da26d7243fd3092f6bf67809a6cec5aa95d71f0c56ecd35ab1f3190
  Compiled from "DebugTokenStream.java"
public class org.antlr.runtime.debug.DebugTokenStream implements org.antlr.runtime.TokenStream
  minor version: 0
  major version: 49
  flags: (0x0021) ACC_PUBLIC, ACC_SUPER
  this_class: #30                         // org/antlr/runtime/debug/DebugTokenStream
  super_class: #31                        // java/lang/Object
  interfaces: 1, fields: 4, methods: 20, attributes: 1
Constant pool:
    #1 = Methodref          #31.#85       // java/lang/Object."<init>":()V
    #2 = Fieldref           #30.#86       // org/antlr/runtime/debug/DebugTokenStream.initialStreamState:Z
    #3 = Fieldref           #30.#87       // org/antlr/runtime/debug/DebugTokenStream.input:Lorg/antlr/runtime/TokenStream;
    #4 = Methodref          #30.#88       // org/antlr/runtime/debug/DebugTokenStream.setDebugListener:(Lorg/antlr/runtime/debug/DebugEventListener;)V
    #5 = InterfaceMethodref #32.#89       // org/antlr/runtime/TokenStream.LT:(I)Lorg/antlr/runtime/Token;
    #6 = Fieldref           #30.#90       // org/antlr/runtime/debug/DebugTokenStream.dbg:Lorg/antlr/runtime/debug/DebugEventListener;
    #7 = Methodref          #30.#91       // org/antlr/runtime/debug/DebugTokenStream.consumeInitialHiddenTokens:()V
    #8 = InterfaceMethodref #32.#92       // org/antlr/runtime/TokenStream.index:()I
    #9 = InterfaceMethodref #32.#93       // org/antlr/runtime/TokenStream.consume:()V
   #10 = InterfaceMethodref #94.#95       // org/antlr/runtime/debug/DebugEventListener.consumeToken:(Lorg/antlr/runtime/Token;)V
   #11 = InterfaceMethodref #32.#96       // org/antlr/runtime/TokenStream.get:(I)Lorg/antlr/runtime/Token;
   #12 = InterfaceMethodref #94.#97       // org/antlr/runtime/debug/DebugEventListener.consumeHiddenToken:(Lorg/antlr/runtime/Token;)V
   #13 = InterfaceMethodref #94.#98       // org/antlr/runtime/debug/DebugEventListener.LT:(ILorg/antlr/runtime/Token;)V
   #14 = InterfaceMethodref #32.#99       // org/antlr/runtime/TokenStream.LA:(I)I
   #15 = InterfaceMethodref #32.#100      // org/antlr/runtime/TokenStream.mark:()I
   #16 = Fieldref           #30.#101      // org/antlr/runtime/debug/DebugTokenStream.lastMarker:I
   #17 = InterfaceMethodref #94.#102      // org/antlr/runtime/debug/DebugEventListener.mark:(I)V
   #18 = InterfaceMethodref #32.#103      // org/antlr/runtime/TokenStream.range:()I
   #19 = InterfaceMethodref #94.#104      // org/antlr/runtime/debug/DebugEventListener.rewind:(I)V
   #20 = InterfaceMethodref #32.#104      // org/antlr/runtime/TokenStream.rewind:(I)V
   #21 = InterfaceMethodref #94.#105      // org/antlr/runtime/debug/DebugEventListener.rewind:()V
   #22 = InterfaceMethodref #32.#106      // org/antlr/runtime/TokenStream.seek:(I)V
   #23 = InterfaceMethodref #32.#107      // org/antlr/runtime/TokenStream.size:()I
   #24 = InterfaceMethodref #32.#108      // org/antlr/runtime/TokenStream.getTokenSource:()Lorg/antlr/runtime/TokenSource;
   #25 = Methodref          #30.#108      // org/antlr/runtime/debug/DebugTokenStream.getTokenSource:()Lorg/antlr/runtime/TokenSource;
   #26 = InterfaceMethodref #109.#110     // org/antlr/runtime/TokenSource.getSourceName:()Ljava/lang/String;
   #27 = Methodref          #31.#111      // java/lang/Object.toString:()Ljava/lang/String;
   #28 = InterfaceMethodref #32.#112      // org/antlr/runtime/TokenStream.toString:(II)Ljava/lang/String;
   #29 = InterfaceMethodref #32.#113      // org/antlr/runtime/TokenStream.toString:(Lorg/antlr/runtime/Token;Lorg/antlr/runtime/Token;)Ljava/lang/String;
   #30 = Class              #114          // org/antlr/runtime/debug/DebugTokenStream
   #31 = Class              #115          // java/lang/Object
   #32 = Class              #116          // org/antlr/runtime/TokenStream
   #33 = Utf8               dbg
   #34 = Utf8               Lorg/antlr/runtime/debug/DebugEventListener;
   #35 = Utf8               input
   #36 = Utf8               Lorg/antlr/runtime/TokenStream;
   #37 = Utf8               initialStreamState
   #38 = Utf8               Z
   #39 = Utf8               lastMarker
   #40 = Utf8               I
   #41 = Utf8               <init>
   #42 = Utf8               (Lorg/antlr/runtime/TokenStream;Lorg/antlr/runtime/debug/DebugEventListener;)V
   #43 = Utf8               Code
   #44 = Utf8               LineNumberTable
   #45 = Utf8               LocalVariableTable
   #46 = Utf8               this
   #47 = Utf8               Lorg/antlr/runtime/debug/DebugTokenStream;
   #48 = Utf8               setDebugListener
   #49 = Utf8               (Lorg/antlr/runtime/debug/DebugEventListener;)V
   #50 = Utf8               consume
   #51 = Utf8               ()V
   #52 = Utf8               i
   #53 = Utf8               a
   #54 = Utf8               t
   #55 = Utf8               Lorg/antlr/runtime/Token;
   #56 = Utf8               b
   #57 = Utf8               consumeInitialHiddenTokens
   #58 = Utf8               firstOnChannelTokenIndex
   #59 = Utf8               LT
   #60 = Utf8               (I)Lorg/antlr/runtime/Token;
   #61 = Utf8               LA
   #62 = Utf8               (I)I
   #63 = Utf8               get
   #64 = Utf8               mark
   #65 = Utf8               ()I
   #66 = Utf8               index
   #67 = Utf8               range
   #68 = Utf8               rewind
   #69 = Utf8               (I)V
   #70 = Utf8               marker
   #71 = Utf8               release
   #72 = Utf8               seek
   #73 = Utf8               size
   #74 = Utf8               getTokenSource
   #75 = Utf8               ()Lorg/antlr/runtime/TokenSource;
   #76 = Utf8               getSourceName
   #77 = Utf8               ()Ljava/lang/String;
   #78 = Utf8               toString
   #79 = Utf8               (II)Ljava/lang/String;
   #80 = Utf8               start
   #81 = Utf8               stop
   #82 = Utf8               (Lorg/antlr/runtime/Token;Lorg/antlr/runtime/Token;)Ljava/lang/String;
   #83 = Utf8               SourceFile
   #84 = Utf8               DebugTokenStream.java
   #85 = NameAndType        #41:#51       // "<init>":()V
   #86 = NameAndType        #37:#38       // initialStreamState:Z
   #87 = NameAndType        #35:#36       // input:Lorg/antlr/runtime/TokenStream;
   #88 = NameAndType        #48:#49       // setDebugListener:(Lorg/antlr/runtime/debug/DebugEventListener;)V
   #89 = NameAndType        #59:#60       // LT:(I)Lorg/antlr/runtime/Token;
   #90 = NameAndType        #33:#34       // dbg:Lorg/antlr/runtime/debug/DebugEventListener;
   #91 = NameAndType        #57:#51       // consumeInitialHiddenTokens:()V
   #92 = NameAndType        #66:#65       // index:()I
   #93 = NameAndType        #50:#51       // consume:()V
   #94 = Class              #117          // org/antlr/runtime/debug/DebugEventListener
   #95 = NameAndType        #118:#119     // consumeToken:(Lorg/antlr/runtime/Token;)V
   #96 = NameAndType        #63:#60       // get:(I)Lorg/antlr/runtime/Token;
   #97 = NameAndType        #120:#119     // consumeHiddenToken:(Lorg/antlr/runtime/Token;)V
   #98 = NameAndType        #59:#121      // LT:(ILorg/antlr/runtime/Token;)V
   #99 = NameAndType        #61:#62       // LA:(I)I
  #100 = NameAndType        #64:#65       // mark:()I
  #101 = NameAndType        #39:#40       // lastMarker:I
  #102 = NameAndType        #64:#69       // mark:(I)V
  #103 = NameAndType        #67:#65       // range:()I
  #104 = NameAndType        #68:#69       // rewind:(I)V
  #105 = NameAndType        #68:#51       // rewind:()V
  #106 = NameAndType        #72:#69       // seek:(I)V
  #107 = NameAndType        #73:#65       // size:()I
  #108 = NameAndType        #74:#75       // getTokenSource:()Lorg/antlr/runtime/TokenSource;
  #109 = Class              #122          // org/antlr/runtime/TokenSource
  #110 = NameAndType        #76:#77       // getSourceName:()Ljava/lang/String;
  #111 = NameAndType        #78:#77       // toString:()Ljava/lang/String;
  #112 = NameAndType        #78:#79       // toString:(II)Ljava/lang/String;
  #113 = NameAndType        #78:#82       // toString:(Lorg/antlr/runtime/Token;Lorg/antlr/runtime/Token;)Ljava/lang/String;
  #114 = Utf8               org/antlr/runtime/debug/DebugTokenStream
  #115 = Utf8               java/lang/Object
  #116 = Utf8               org/antlr/runtime/TokenStream
  #117 = Utf8               org/antlr/runtime/debug/DebugEventListener
  #118 = Utf8               consumeToken
  #119 = Utf8               (Lorg/antlr/runtime/Token;)V
  #120 = Utf8               consumeHiddenToken
  #121 = Utf8               (ILorg/antlr/runtime/Token;)V
  #122 = Utf8               org/antlr/runtime/TokenSource
{
  protected org.antlr.runtime.debug.DebugEventListener dbg;
    descriptor: Lorg/antlr/runtime/debug/DebugEventListener;
    flags: (0x0004) ACC_PROTECTED

  public org.antlr.runtime.TokenStream input;
    descriptor: Lorg/antlr/runtime/TokenStream;
    flags: (0x0001) ACC_PUBLIC

  protected boolean initialStreamState;
    descriptor: Z
    flags: (0x0004) ACC_PROTECTED

  protected int lastMarker;
    descriptor: I
    flags: (0x0004) ACC_PROTECTED

  public org.antlr.runtime.debug.DebugTokenStream(org.antlr.runtime.TokenStream, org.antlr.runtime.debug.DebugEventListener);
    descriptor: (Lorg/antlr/runtime/TokenStream;Lorg/antlr/runtime/debug/DebugEventListener;)V
    flags: (0x0001) ACC_PUBLIC
    Code:
      stack=2, locals=3, args_size=3
         0: aload_0
         1: invokespecial #1                  // Method java/lang/Object."<init>":()V
         4: aload_0
         5: iconst_1
         6: putfield      #2                  // Field initialStreamState:Z
         9: aload_0
        10: aload_1
        11: putfield      #3                  // Field input:Lorg/antlr/runtime/TokenStream;
        14: aload_0
        15: aload_2
        16: invokevirtual #4                  // Method setDebugListener:(Lorg/antlr/runtime/debug/DebugEventListener;)V
        19: aload_1
        20: iconst_1
        21: invokeinterface #5,  2            // InterfaceMethod org/antlr/runtime/TokenStream.LT:(I)Lorg/antlr/runtime/Token;
        26: pop
        27: return
      LineNumberTable:
        line 40: 0
        line 35: 4
        line 41: 9
        line 42: 14
        line 45: 19
        line 46: 27
      LocalVariableTable:
        Start  Length  Slot  Name   Signature
            0      28     0  this   Lorg/antlr/runtime/debug/DebugTokenStream;
            0      28     1 input   Lorg/antlr/runtime/TokenStream;
            0      28     2   dbg   Lorg/antlr/runtime/debug/DebugEventListener;

  public void setDebugListener(org.antlr.runtime.debug.DebugEventListener);
    descriptor: (Lorg/antlr/runtime/debug/DebugEventListener;)V
    flags: (0x0001) ACC_PUBLIC
    Code:
      stack=2, locals=2, args_size=2
         0: aload_0
         1: aload_1
         2: putfield      #6                  // Field dbg:Lorg/antlr/runtime/debug/DebugEventListener;
         5: return
      LineNumberTable:
        line 49: 0
        line 50: 5
      LocalVariableTable:
        Start  Length  Slot  Name   Signature
            0       6     0  this   Lorg/antlr/runtime/debug/DebugTokenStream;
            0       6     1   dbg   Lorg/antlr/runtime/debug/DebugEventListener;

  public void consume();
    descriptor: ()V
    flags: (0x0001) ACC_PUBLIC
    Code:
      stack=3, locals=5, args_size=1
         0: aload_0
         1: getfield      #2                  // Field initialStreamState:Z
         4: ifeq          11
         7: aload_0
         8: invokevirtual #7                  // Method consumeInitialHiddenTokens:()V
        11: aload_0
        12: getfield      #3                  // Field input:Lorg/antlr/runtime/TokenStream;
        15: invokeinterface #8,  1            // InterfaceMethod org/antlr/runtime/TokenStream.index:()I
        20: istore_1
        21: aload_0
        22: getfield      #3                  // Field input:Lorg/antlr/runtime/TokenStream;
        25: iconst_1
        26: invokeinterface #5,  2            // InterfaceMethod org/antlr/runtime/TokenStream.LT:(I)Lorg/antlr/runtime/Token;
        31: astore_2
        32: aload_0
        33: getfield      #3                  // Field input:Lorg/antlr/runtime/TokenStream;
        36: invokeinterface #9,  1            // InterfaceMethod org/antlr/runtime/TokenStream.consume:()V
        41: aload_0
        42: getfield      #3                  // Field input:Lorg/antlr/runtime/TokenStream;
        45: invokeinterface #8,  1            // InterfaceMethod org/antlr/runtime/TokenStream.index:()I
        50: istore_3
        51: aload_0
        52: getfield      #6                  // Field dbg:Lorg/antlr/runtime/debug/DebugEventListener;
        55: aload_2
        56: invokeinterface #10,  2           // InterfaceMethod org/antlr/runtime/debug/DebugEventListener.consumeToken:(Lorg/antlr/runtime/Token;)V
        61: iload_3
        62: iload_1
        63: iconst_1
        64: iadd
        65: if_icmple     105
        68: iload_1
        69: iconst_1
        70: iadd
        71: istore        4
        73: iload         4
        75: iload_3
        76: if_icmpge     105
        79: aload_0
        80: getfield      #6                  // Field dbg:Lorg/antlr/runtime/debug/DebugEventListener;
        83: aload_0
        84: getfield      #3                  // Field input:Lorg/antlr/runtime/TokenStream;
        87: iload         4
        89: invokeinterface #11,  2           // InterfaceMethod org/antlr/runtime/TokenStream.get:(I)Lorg/antlr/runtime/Token;
        94: invokeinterface #12,  2           // InterfaceMethod org/antlr/runtime/debug/DebugEventListener.consumeHiddenToken:(Lorg/antlr/runtime/Token;)V
        99: iinc          4, 1
       102: goto          73
       105: return
      LineNumberTable:
        line 54: 0
        line 55: 7
        line 57: 11
        line 58: 21
        line 59: 32
        line 60: 41
        line 61: 51
        line 62: 61
        line 64: 68
        line 65: 79
        line 64: 99
        line 68: 105
      LocalVariableTable:
        Start  Length  Slot  Name   Signature
           73      32     4     i   I
            0     106     0  this   Lorg/antlr/runtime/debug/DebugTokenStream;
           21      85     1     a   I
           32      74     2     t   Lorg/antlr/runtime/Token;
           51      55     3     b   I

  protected void consumeInitialHiddenTokens();
    descriptor: ()V
    flags: (0x0004) ACC_PROTECTED
    Code:
      stack=3, locals=3, args_size=1
         0: aload_0
         1: getfield      #3                  // Field input:Lorg/antlr/runtime/TokenStream;
         4: invokeinterface #8,  1            // InterfaceMethod org/antlr/runtime/TokenStream.index:()I
         9: istore_1
        10: iconst_0
        11: istore_2
        12: iload_2
        13: iload_1
        14: if_icmpge     42
        17: aload_0
        18: getfield      #6                  // Field dbg:Lorg/antlr/runtime/debug/DebugEventListener;
        21: aload_0
        22: getfield      #3                  // Field input:Lorg/antlr/runtime/TokenStream;
        25: iload_2
        26: invokeinterface #11,  2           // InterfaceMethod org/antlr/runtime/TokenStream.get:(I)Lorg/antlr/runtime/Token;
        31: invokeinterface #12,  2           // InterfaceMethod org/antlr/runtime/debug/DebugEventListener.consumeHiddenToken:(Lorg/antlr/runtime/Token;)V
        36: iinc          2, 1
        39: goto          12
        42: aload_0
        43: iconst_0
        44: putfield      #2                  // Field initialStreamState:Z
        47: return
      LineNumberTable:
        line 72: 0
        line 73: 10
        line 74: 17
        line 73: 36
        line 76: 42
        line 77: 47
      LocalVariableTable:
        Start  Length  Slot  Name   Signature
           12      30     2     i   I
            0      48     0  this   Lorg/antlr/runtime/debug/DebugTokenStream;
           10      38     1 firstOnChannelTokenIndex   I

  public org.antlr.runtime.Token LT(int);
    descriptor: (I)Lorg/antlr/runtime/Token;
    flags: (0x0001) ACC_PUBLIC
    Code:
      stack=4, locals=2, args_size=2
         0: aload_0
         1: getfield      #2                  // Field initialStreamState:Z
         4: ifeq          11
         7: aload_0
         8: invokevirtual #7                  // Method consumeInitialHiddenTokens:()V
        11: aload_0
        12: getfield      #6                  // Field dbg:Lorg/antlr/runtime/debug/DebugEventListener;
        15: iload_1
        16: aload_0
        17: getfield      #3                  // Field input:Lorg/antlr/runtime/TokenStream;
        20: iload_1
        21: invokeinterface #5,  2            // InterfaceMethod org/antlr/runtime/TokenStream.LT:(I)Lorg/antlr/runtime/Token;
        26: invokeinterface #13,  3           // InterfaceMethod org/antlr/runtime/debug/DebugEventListener.LT:(ILorg/antlr/runtime/Token;)V
        31: aload_0
        32: getfield      #3                  // Field input:Lorg/antlr/runtime/TokenStream;
        35: iload_1
        36: invokeinterface #5,  2            // InterfaceMethod org/antlr/runtime/TokenStream.LT:(I)Lorg/antlr/runtime/Token;
        41: areturn
      LineNumberTable:
        line 81: 0
        line 82: 7
        line 84: 11
        line 85: 31
      LocalVariableTable:
        Start  Length  Slot  Name   Signature
            0      42     0  this   Lorg/antlr/runtime/debug/DebugTokenStream;
            0      42     1     i   I

  public int LA(int);
    descriptor: (I)I
    flags: (0x0001) ACC_PUBLIC
    Code:
      stack=4, locals=2, args_size=2
         0: aload_0
         1: getfield      #2                  // Field initialStreamState:Z
         4: ifeq          11
         7: aload_0
         8: invokevirtual #7                  // Method consumeInitialHiddenTokens:()V
        11: aload_0
        12: getfield      #6                  // Field dbg:Lorg/antlr/runtime/debug/DebugEventListener;
        15: iload_1
        16: aload_0
        17: getfield      #3                  // Field input:Lorg/antlr/runtime/TokenStream;
        20: iload_1
        21: invokeinterface #5,  2            // InterfaceMethod org/antlr/runtime/TokenStream.LT:(I)Lorg/antlr/runtime/Token;
        26: invokeinterface #13,  3           // InterfaceMethod org/antlr/runtime/debug/DebugEventListener.LT:(ILorg/antlr/runtime/Token;)V
        31: aload_0
        32: getfield      #3                  // Field input:Lorg/antlr/runtime/TokenStream;
        35: iload_1
        36: invokeinterface #14,  2           // InterfaceMethod org/antlr/runtime/TokenStream.LA:(I)I
        41: ireturn
      LineNumberTable:
        line 90: 0
        line 91: 7
        line 93: 11
        line 94: 31
      LocalVariableTable:
        Start  Length  Slot  Name   Signature
            0      42     0  this   Lorg/antlr/runtime/debug/DebugTokenStream;
            0      42     1     i   I

  public org.antlr.runtime.Token get(int);
    descriptor: (I)Lorg/antlr/runtime/Token;
    flags: (0x0001) ACC_PUBLIC
    Code:
      stack=2, locals=2, args_size=2
         0: aload_0
         1: getfield      #3                  // Field input:Lorg/antlr/runtime/TokenStream;
         4: iload_1
         5: invokeinterface #11,  2           // InterfaceMethod org/antlr/runtime/TokenStream.get:(I)Lorg/antlr/runtime/Token;
        10: areturn
      LineNumberTable:
        line 99: 0
      LocalVariableTable:
        Start  Length  Slot  Name   Signature
            0      11     0  this   Lorg/antlr/runtime/debug/DebugTokenStream;
            0      11     1     i   I

  public int mark();
    descriptor: ()I
    flags: (0x0001) ACC_PUBLIC
    Code:
      stack=2, locals=1, args_size=1
         0: aload_0
         1: aload_0
         2: getfield      #3                  // Field input:Lorg/antlr/runtime/TokenStream;
         5: invokeinterface #15,  1           // InterfaceMethod org/antlr/runtime/TokenStream.mark:()I
        10: putfield      #16                 // Field lastMarker:I
        13: aload_0
        14: getfield      #6                  // Field dbg:Lorg/antlr/runtime/debug/DebugEventListener;
        17: aload_0
        18: getfield      #16                 // Field lastMarker:I
        21: invokeinterface #17,  2           // InterfaceMethod org/antlr/runtime/debug/DebugEventListener.mark:(I)V
        26: aload_0
        27: getfield      #16                 // Field lastMarker:I
        30: ireturn
      LineNumberTable:
        line 104: 0
        line 105: 13
        line 106: 26
      LocalVariableTable:
        Start  Length  Slot  Name   Signature
            0      31     0  this   Lorg/antlr/runtime/debug/DebugTokenStream;

  public int index();
    descriptor: ()I
    flags: (0x0001) ACC_PUBLIC
    Code:
      stack=1, locals=1, args_size=1
         0: aload_0
         1: getfield      #3                  // Field input:Lorg/antlr/runtime/TokenStream;
         4: invokeinterface #8,  1            // InterfaceMethod org/antlr/runtime/TokenStream.index:()I
         9: ireturn
      LineNumberTable:
        line 111: 0
      LocalVariableTable:
        Start  Length  Slot  Name   Signature
            0      10     0  this   Lorg/antlr/runtime/debug/DebugTokenStream;

  public int range();
    descriptor: ()I
    flags: (0x0001) ACC_PUBLIC
    Code:
      stack=1, locals=1, args_size=1
         0: aload_0
         1: getfield      #3                  // Field input:Lorg/antlr/runtime/TokenStream;
         4: invokeinterface #18,  1           // InterfaceMethod org/antlr/runtime/TokenStream.range:()I
         9: ireturn
      LineNumberTable:
        line 116: 0
      LocalVariableTable:
        Start  Length  Slot  Name   Signature
            0      10     0  this   Lorg/antlr/runtime/debug/DebugTokenStream;

  public void rewind(int);
    descriptor: (I)V
    flags: (0x0001) ACC_PUBLIC
    Code:
      stack=2, locals=2, args_size=2
         0: aload_0
         1: getfield      #6                  // Field dbg:Lorg/antlr/runtime/debug/DebugEventListener;
         4: iload_1
         5: invokeinterface #19,  2           // InterfaceMethod org/antlr/runtime/debug/DebugEventListener.rewind:(I)V
        10: aload_0
        11: getfield      #3                  // Field input:Lorg/antlr/runtime/TokenStream;
        14: iload_1
        15: invokeinterface #20,  2           // InterfaceMethod org/antlr/runtime/TokenStream.rewind:(I)V
        20: return
      LineNumberTable:
        line 121: 0
        line 122: 10
        line 123: 20
      LocalVariableTable:
        Start  Length  Slot  Name   Signature
            0      21     0  this   Lorg/antlr/runtime/debug/DebugTokenStream;
            0      21     1 marker   I

  public void rewind();
    descriptor: ()V
    flags: (0x0001) ACC_PUBLIC
    Code:
      stack=2, locals=1, args_size=1
         0: aload_0
         1: getfield      #6                  // Field dbg:Lorg/antlr/runtime/debug/DebugEventListener;
         4: invokeinterface #21,  1           // InterfaceMethod org/antlr/runtime/debug/DebugEventListener.rewind:()V
         9: aload_0
        10: getfield      #3                  // Field input:Lorg/antlr/runtime/TokenStream;
        13: aload_0
        14: getfield      #16                 // Field lastMarker:I
        17: invokeinterface #20,  2           // InterfaceMethod org/antlr/runtime/TokenStream.rewind:(I)V
        22: return
      LineNumberTable:
        line 127: 0
        line 128: 9
        line 129: 22
      LocalVariableTable:
        Start  Length  Slot  Name   Signature
            0      23     0  this   Lorg/antlr/runtime/debug/DebugTokenStream;

  public void release(int);
    descriptor: (I)V
    flags: (0x0001) ACC_PUBLIC
    Code:
      stack=0, locals=2, args_size=2
         0: return
      LineNumberTable:
        line 133: 0
      LocalVariableTable:
        Start  Length  Slot  Name   Signature
            0       1     0  this   Lorg/antlr/runtime/debug/DebugTokenStream;
            0       1     1 marker   I

  public void seek(int);
    descriptor: (I)V
    flags: (0x0001) ACC_PUBLIC
    Code:
      stack=2, locals=2, args_size=2
         0: aload_0
         1: getfield      #3                  // Field input:Lorg/antlr/runtime/TokenStream;
         4: iload_1
         5: invokeinterface #22,  2           // InterfaceMethod org/antlr/runtime/TokenStream.seek:(I)V
        10: return
      LineNumberTable:
        line 139: 0
        line 140: 10
      LocalVariableTable:
        Start  Length  Slot  Name   Signature
            0      11     0  this   Lorg/antlr/runtime/debug/DebugTokenStream;
            0      11     1 index   I

  public int size();
    descriptor: ()I
    flags: (0x0001) ACC_PUBLIC
    Code:
      stack=1, locals=1, args_size=1
         0: aload_0
         1: getfield      #3                  // Field input:Lorg/antlr/runtime/TokenStream;
         4: invokeinterface #23,  1           // InterfaceMethod org/antlr/runtime/TokenStream.size:()I
         9: ireturn
      LineNumberTable:
        line 144: 0
      LocalVariableTable:
        Start  Length  Slot  Name   Signature
            0      10     0  this   Lorg/antlr/runtime/debug/DebugTokenStream;

  public org.antlr.runtime.TokenSource getTokenSource();
    descriptor: ()Lorg/antlr/runtime/TokenSource;
    flags: (0x0001) ACC_PUBLIC
    Code:
      stack=1, locals=1, args_size=1
         0: aload_0
         1: getfield      #3                  // Field input:Lorg/antlr/runtime/TokenStream;
         4: invokeinterface #24,  1           // InterfaceMethod org/antlr/runtime/TokenStream.getTokenSource:()Lorg/antlr/runtime/TokenSource;
         9: areturn
      LineNumberTable:
        line 149: 0
      LocalVariableTable:
        Start  Length  Slot  Name   Signature
            0      10     0  this   Lorg/antlr/runtime/debug/DebugTokenStream;

  public java.lang.String getSourceName();
    descriptor: ()Ljava/lang/String;
    flags: (0x0001) ACC_PUBLIC
    Code:
      stack=1, locals=1, args_size=1
         0: aload_0
         1: invokevirtual #25                 // Method getTokenSource:()Lorg/antlr/runtime/TokenSource;
         4: invokeinterface #26,  1           // InterfaceMethod org/antlr/runtime/TokenSource.getSourceName:()Ljava/lang/String;
         9: areturn
      LineNumberTable:
        line 154: 0
      LocalVariableTable:
        Start  Length  Slot  Name   Signature
            0      10     0  this   Lorg/antlr/runtime/debug/DebugTokenStream;

  public java.lang.String toString();
    descriptor: ()Ljava/lang/String;
    flags: (0x0001) ACC_PUBLIC
    Code:
      stack=1, locals=1, args_size=1
         0: aload_0
         1: getfield      #3                  // Field input:Lorg/antlr/runtime/TokenStream;
         4: invokevirtual #27                 // Method java/lang/Object.toString:()Ljava/lang/String;
         7: areturn
      LineNumberTable:
        line 159: 0
      LocalVariableTable:
        Start  Length  Slot  Name   Signature
            0       8     0  this   Lorg/antlr/runtime/debug/DebugTokenStream;

  public java.lang.String toString(int, int);
    descriptor: (II)Ljava/lang/String;
    flags: (0x0001) ACC_PUBLIC
    Code:
      stack=3, locals=3, args_size=3
         0: aload_0
         1: getfield      #3                  // Field input:Lorg/antlr/runtime/TokenStream;
         4: iload_1
         5: iload_2
         6: invokeinterface #28,  3           // InterfaceMethod org/antlr/runtime/TokenStream.toString:(II)Ljava/lang/String;
        11: areturn
      LineNumberTable:
        line 164: 0
      LocalVariableTable:
        Start  Length  Slot  Name   Signature
            0      12     0  this   Lorg/antlr/runtime/debug/DebugTokenStream;
            0      12     1 start   I
            0      12     2  stop   I

  public java.lang.String toString(org.antlr.runtime.Token, org.antlr.runtime.Token);
    descriptor: (Lorg/antlr/runtime/Token;Lorg/antlr/runtime/Token;)Ljava/lang/String;
    flags: (0x0001) ACC_PUBLIC
    Code:
      stack=3, locals=3, args_size=3
         0: aload_0
         1: getfield      #3                  // Field input:Lorg/antlr/runtime/TokenStream;
         4: aload_1
         5: aload_2
         6: invokeinterface #29,  3           // InterfaceMethod org/antlr/runtime/TokenStream.toString:(Lorg/antlr/runtime/Token;Lorg/antlr/runtime/Token;)Ljava/lang/String;
        11: areturn
      LineNumberTable:
        line 169: 0
      LocalVariableTable:
        Start  Length  Slot  Name   Signature
            0      12     0  this   Lorg/antlr/runtime/debug/DebugTokenStream;
            0      12     1 start   Lorg/antlr/runtime/Token;
            0      12     2  stop   Lorg/antlr/runtime/Token;
}
SourceFile: "DebugTokenStream.java"
