Classfile /Users/mw/Projects/slang-braindump/.jar/jar8/assemble/slang-braindump/assemble/content/org/antlr/runtime/debug/RemoteDebugEventSocketListener$ProxyTree.class
  Last modified May 29, 2022; size 1674 bytes
  SHA-256 checksum 35c42afbc1b0b38c10409b08615935e76b06887991be520fcff266ada74791f9
  Compiled from "RemoteDebugEventSocketListener.java"
public class org.antlr.runtime.debug.RemoteDebugEventSocketListener$ProxyTree extends org.antlr.runtime.tree.BaseTree
  minor version: 0
  major version: 49
  flags: (0x0021) ACC_PUBLIC, ACC_SUPER
  this_class: #9                          // org/antlr/runtime/debug/RemoteDebugEventSocketListener$ProxyTree
  super_class: #10                        // org/antlr/runtime/tree/BaseTree
  interfaces: 0, fields: 6, methods: 10, attributes: 2
Constant pool:
   #1 = Methodref          #10.#43        // org/antlr/runtime/tree/BaseTree."<init>":()V
   #2 = Fieldref           #9.#44         // org/antlr/runtime/debug/RemoteDebugEventSocketListener$ProxyTree.line:I
   #3 = Fieldref           #9.#45         // org/antlr/runtime/debug/RemoteDebugEventSocketListener$ProxyTree.charPos:I
   #4 = Fieldref           #9.#46         // org/antlr/runtime/debug/RemoteDebugEventSocketListener$ProxyTree.tokenIndex:I
   #5 = Fieldref           #9.#47         // org/antlr/runtime/debug/RemoteDebugEventSocketListener$ProxyTree.ID:I
   #6 = Fieldref           #9.#48         // org/antlr/runtime/debug/RemoteDebugEventSocketListener$ProxyTree.type:I
   #7 = Fieldref           #9.#49         // org/antlr/runtime/debug/RemoteDebugEventSocketListener$ProxyTree.text:Ljava/lang/String;
   #8 = String             #50            // fix this
   #9 = Class              #52            // org/antlr/runtime/debug/RemoteDebugEventSocketListener$ProxyTree
  #10 = Class              #53            // org/antlr/runtime/tree/BaseTree
  #11 = Utf8               ID
  #12 = Utf8               I
  #13 = Utf8               type
  #14 = Utf8               line
  #15 = Utf8               charPos
  #16 = Utf8               tokenIndex
  #17 = Utf8               text
  #18 = Utf8               Ljava/lang/String;
  #19 = Utf8               <init>
  #20 = Utf8               (IIIIILjava/lang/String;)V
  #21 = Utf8               Code
  #22 = Utf8               LineNumberTable
  #23 = Utf8               LocalVariableTable
  #24 = Utf8               this
  #25 = Utf8               ProxyTree
  #26 = Utf8               InnerClasses
  #27 = Utf8               Lorg/antlr/runtime/debug/RemoteDebugEventSocketListener$ProxyTree;
  #28 = Utf8               (I)V
  #29 = Utf8               getTokenStartIndex
  #30 = Utf8               ()I
  #31 = Utf8               setTokenStartIndex
  #32 = Utf8               index
  #33 = Utf8               getTokenStopIndex
  #34 = Utf8               setTokenStopIndex
  #35 = Utf8               dupNode
  #36 = Utf8               ()Lorg/antlr/runtime/tree/Tree;
  #37 = Utf8               getType
  #38 = Utf8               getText
  #39 = Utf8               ()Ljava/lang/String;
  #40 = Utf8               toString
  #41 = Utf8               SourceFile
  #42 = Utf8               RemoteDebugEventSocketListener.java
  #43 = NameAndType        #19:#54        // "<init>":()V
  #44 = NameAndType        #14:#12        // line:I
  #45 = NameAndType        #15:#12        // charPos:I
  #46 = NameAndType        #16:#12        // tokenIndex:I
  #47 = NameAndType        #11:#12        // ID:I
  #48 = NameAndType        #13:#12        // type:I
  #49 = NameAndType        #17:#18        // text:Ljava/lang/String;
  #50 = Utf8               fix this
  #51 = Class              #55            // org/antlr/runtime/debug/RemoteDebugEventSocketListener
  #52 = Utf8               org/antlr/runtime/debug/RemoteDebugEventSocketListener$ProxyTree
  #53 = Utf8               org/antlr/runtime/tree/BaseTree
  #54 = Utf8               ()V
  #55 = Utf8               org/antlr/runtime/debug/RemoteDebugEventSocketListener
{
  public int ID;
    descriptor: I
    flags: (0x0001) ACC_PUBLIC

  public int type;
    descriptor: I
    flags: (0x0001) ACC_PUBLIC

  public int line;
    descriptor: I
    flags: (0x0001) ACC_PUBLIC

  public int charPos;
    descriptor: I
    flags: (0x0001) ACC_PUBLIC

  public int tokenIndex;
    descriptor: I
    flags: (0x0001) ACC_PUBLIC

  public java.lang.String text;
    descriptor: Ljava/lang/String;
    flags: (0x0001) ACC_PUBLIC

  public org.antlr.runtime.debug.RemoteDebugEventSocketListener$ProxyTree(int, int, int, int, int, java.lang.String);
    descriptor: (IIIIILjava/lang/String;)V
    flags: (0x0001) ACC_PUBLIC
    Code:
      stack=2, locals=7, args_size=7
         0: aload_0
         1: invokespecial #1                  // Method org/antlr/runtime/tree/BaseTree."<init>":()V
         4: aload_0
         5: iconst_0
         6: putfield      #2                  // Field line:I
         9: aload_0
        10: iconst_m1
        11: putfield      #3                  // Field charPos:I
        14: aload_0
        15: iconst_m1
        16: putfield      #4                  // Field tokenIndex:I
        19: aload_0
        20: iload_1
        21: putfield      #5                  // Field ID:I
        24: aload_0
        25: iload_2
        26: putfield      #6                  // Field type:I
        29: aload_0
        30: iload_3
        31: putfield      #2                  // Field line:I
        34: aload_0
        35: iload         4
        37: putfield      #3                  // Field charPos:I
        40: aload_0
        41: iload         5
        43: putfield      #4                  // Field tokenIndex:I
        46: aload_0
        47: aload         6
        49: putfield      #7                  // Field text:Ljava/lang/String;
        52: return
      LineNumberTable:
        line 165: 0
        line 160: 4
        line 161: 9
        line 162: 14
        line 166: 19
        line 167: 24
        line 168: 29
        line 169: 34
        line 170: 40
        line 171: 46
        line 172: 52
      LocalVariableTable:
        Start  Length  Slot  Name   Signature
            0      53     0  this   Lorg/antlr/runtime/debug/RemoteDebugEventSocketListener$ProxyTree;
            0      53     1    ID   I
            0      53     2  type   I
            0      53     3  line   I
            0      53     4 charPos   I
            0      53     5 tokenIndex   I
            0      53     6  text   Ljava/lang/String;

  public org.antlr.runtime.debug.RemoteDebugEventSocketListener$ProxyTree(int);
    descriptor: (I)V
    flags: (0x0001) ACC_PUBLIC
    Code:
      stack=2, locals=2, args_size=2
         0: aload_0
         1: invokespecial #1                  // Method org/antlr/runtime/tree/BaseTree."<init>":()V
         4: aload_0
         5: iconst_0
         6: putfield      #2                  // Field line:I
         9: aload_0
        10: iconst_m1
        11: putfield      #3                  // Field charPos:I
        14: aload_0
        15: iconst_m1
        16: putfield      #4                  // Field tokenIndex:I
        19: aload_0
        20: iload_1
        21: putfield      #5                  // Field ID:I
        24: return
      LineNumberTable:
        line 174: 0
        line 160: 4
        line 161: 9
        line 162: 14
        line 174: 19
      LocalVariableTable:
        Start  Length  Slot  Name   Signature
            0      25     0  this   Lorg/antlr/runtime/debug/RemoteDebugEventSocketListener$ProxyTree;
            0      25     1    ID   I

  public int getTokenStartIndex();
    descriptor: ()I
    flags: (0x0001) ACC_PUBLIC
    Code:
      stack=1, locals=1, args_size=1
         0: aload_0
         1: getfield      #4                  // Field tokenIndex:I
         4: ireturn
      LineNumberTable:
        line 176: 0
      LocalVariableTable:
        Start  Length  Slot  Name   Signature
            0       5     0  this   Lorg/antlr/runtime/debug/RemoteDebugEventSocketListener$ProxyTree;

  public void setTokenStartIndex(int);
    descriptor: (I)V
    flags: (0x0001) ACC_PUBLIC
    Code:
      stack=0, locals=2, args_size=2
         0: return
      LineNumberTable:
        line 177: 0
      LocalVariableTable:
        Start  Length  Slot  Name   Signature
            0       1     0  this   Lorg/antlr/runtime/debug/RemoteDebugEventSocketListener$ProxyTree;
            0       1     1 index   I

  public int getTokenStopIndex();
    descriptor: ()I
    flags: (0x0001) ACC_PUBLIC
    Code:
      stack=1, locals=1, args_size=1
         0: iconst_0
         1: ireturn
      LineNumberTable:
        line 178: 0
      LocalVariableTable:
        Start  Length  Slot  Name   Signature
            0       2     0  this   Lorg/antlr/runtime/debug/RemoteDebugEventSocketListener$ProxyTree;

  public void setTokenStopIndex(int);
    descriptor: (I)V
    flags: (0x0001) ACC_PUBLIC
    Code:
      stack=0, locals=2, args_size=2
         0: return
      LineNumberTable:
        line 179: 0
      LocalVariableTable:
        Start  Length  Slot  Name   Signature
            0       1     0  this   Lorg/antlr/runtime/debug/RemoteDebugEventSocketListener$ProxyTree;
            0       1     1 index   I

  public org.antlr.runtime.tree.Tree dupNode();
    descriptor: ()Lorg/antlr/runtime/tree/Tree;
    flags: (0x0001) ACC_PUBLIC
    Code:
      stack=1, locals=1, args_size=1
         0: aconst_null
         1: areturn
      LineNumberTable:
        line 180: 0
      LocalVariableTable:
        Start  Length  Slot  Name   Signature
            0       2     0  this   Lorg/antlr/runtime/debug/RemoteDebugEventSocketListener$ProxyTree;

  public int getType();
    descriptor: ()I
    flags: (0x0001) ACC_PUBLIC
    Code:
      stack=1, locals=1, args_size=1
         0: aload_0
         1: getfield      #6                  // Field type:I
         4: ireturn
      LineNumberTable:
        line 181: 0
      LocalVariableTable:
        Start  Length  Slot  Name   Signature
            0       5     0  this   Lorg/antlr/runtime/debug/RemoteDebugEventSocketListener$ProxyTree;

  public java.lang.String getText();
    descriptor: ()Ljava/lang/String;
    flags: (0x0001) ACC_PUBLIC
    Code:
      stack=1, locals=1, args_size=1
         0: aload_0
         1: getfield      #7                  // Field text:Ljava/lang/String;
         4: areturn
      LineNumberTable:
        line 182: 0
      LocalVariableTable:
        Start  Length  Slot  Name   Signature
            0       5     0  this   Lorg/antlr/runtime/debug/RemoteDebugEventSocketListener$ProxyTree;

  public java.lang.String toString();
    descriptor: ()Ljava/lang/String;
    flags: (0x0001) ACC_PUBLIC
    Code:
      stack=1, locals=1, args_size=1
         0: ldc           #8                  // String fix this
         2: areturn
      LineNumberTable:
        line 184: 0
      LocalVariableTable:
        Start  Length  Slot  Name   Signature
            0       3     0  this   Lorg/antlr/runtime/debug/RemoteDebugEventSocketListener$ProxyTree;
}
SourceFile: "RemoteDebugEventSocketListener.java"
InnerClasses:
  public static #25= #9 of #51;           // ProxyTree=class org/antlr/runtime/debug/RemoteDebugEventSocketListener$ProxyTree of class org/antlr/runtime/debug/RemoteDebugEventSocketListener
