Classfile /Users/mw/Projects/slang-braindump/.jar/jar8/assemble/slang-braindump/assemble/content/coursier/paths/Mirror$Types.class
  Last modified May 29, 2022; size 378 bytes
  SHA-256 checksum 69ee6868ce7fa6b31bed53032e27875ec210209f32b8b9dafe29e8bfe6266715
  Compiled from "Mirror.java"
public final class coursier.paths.Mirror$Types
  minor version: 0
  major version: 52
  flags: (0x0031) ACC_PUBLIC, ACC_FINAL, ACC_SUPER
  this_class: #2                          // coursier/paths/Mirror$Types
  super_class: #4                         // java/lang/Object
  interfaces: 0, fields: 2, methods: 1, attributes: 2
Constant pool:
   #1 = Utf8               coursier/paths/Mirror$Types
   #2 = Class              #1             // coursier/paths/Mirror$Types
   #3 = Utf8               java/lang/Object
   #4 = Class              #3             // java/lang/Object
   #5 = Utf8               Mirror.java
   #6 = Utf8               coursier/paths/Mirror
   #7 = Class              #6             // coursier/paths/Mirror
   #8 = Utf8               Types
   #9 = Utf8               MAVEN
  #10 = Utf8               Ljava/lang/String;
  #11 = Utf8               maven
  #12 = String             #11            // maven
  #13 = Utf8               TREE
  #14 = Utf8               tree
  #15 = String             #14            // tree
  #16 = Utf8               <init>
  #17 = Utf8               ()V
  #18 = NameAndType        #16:#17        // "<init>":()V
  #19 = Methodref          #4.#18         // java/lang/Object."<init>":()V
  #20 = Utf8               ConstantValue
  #21 = Utf8               Code
  #22 = Utf8               LineNumberTable
  #23 = Utf8               InnerClasses
  #24 = Utf8               SourceFile
{
  public static final java.lang.String MAVEN;
    descriptor: Ljava/lang/String;
    flags: (0x0019) ACC_PUBLIC, ACC_STATIC, ACC_FINAL
    ConstantValue: String maven

  public static final java.lang.String TREE;
    descriptor: Ljava/lang/String;
    flags: (0x0019) ACC_PUBLIC, ACC_STATIC, ACC_FINAL
    ConstantValue: String tree

  public coursier.paths.Mirror$Types();
    descriptor: ()V
    flags: (0x0001) ACC_PUBLIC
    Code:
      stack=1, locals=1, args_size=1
         0: aload_0
         1: invokespecial #19                 // Method java/lang/Object."<init>":()V
         4: return
      LineNumberTable:
        line 15: 0
}
InnerClasses:
  public static final #8= #2 of #7;       // Types=class coursier/paths/Mirror$Types of class coursier/paths/Mirror
SourceFile: "Mirror.java"
