Classfile /Users/mw/Projects/slang-braindump/.jar/jar8/assemble/slang-braindump/assemble/content/coursier/graph/ReverseModuleTree.class
  Last modified May 29, 2022; size 5607 bytes
  SHA-256 checksum 26e388d8ef07b84e6f96dabef6d0c5dca935361266acc36b693b90879f126bdf
  Compiled from "ReverseModuleTree.scala"
public abstract class coursier.graph.ReverseModuleTree
  minor version: 0
  major version: 52
  flags: (0x0421) ACC_PUBLIC, ACC_SUPER, ACC_ABSTRACT
  this_class: #2                          // coursier/graph/ReverseModuleTree
  super_class: #4                         // java/lang/Object
  interfaces: 0, fields: 0, methods: 13, attributes: 5
Constant pool:
   #1 = Utf8               coursier/graph/ReverseModuleTree
   #2 = Class              #1             // coursier/graph/ReverseModuleTree
   #3 = Utf8               java/lang/Object
   #4 = Class              #3             // java/lang/Object
   #5 = Utf8               ReverseModuleTree.scala
   #6 = Utf8               Lscala/reflect/ScalaSignature;
   #7 = Utf8               bytes
   #8 = Utf8               \u0006\u0005\tEe!\u0002!B\u0003C1\u0005\"B\'\u0001\t\u0003q\u0005\"B)\u0001\r\u0003\u0011\u0006\"B-\u0001\r\u0003Q\u0006\"\u00024\u0001\r\u0003\u0011\u0006\"B4\u0001\r\u0003Q\u0006\"\u00025\u0001\r\u0003Q\u0006\"B5\u0001\r\u0003Q\u0007\"\u00028\u0001\r\u0003ywA\u0002BH\u0003\"\u0005QPB\u0003A\u0003\"\u00051\u0010C\u0003N\u0015\u0011\u0005A\u0010C\u0003\u007f\u0015\u0011\u0005q\u0010C\u0004\u0002\u0014)!\t!!\u0006\t\u000f\u0005\u0015\"\u0002\"\u0001\u0002(!I\u0011\u0011\b\u0006\u0012\u0002\u0013\u0005\u00111\b\u0005\n\u0003#R\u0011\u0013!C\u0001\u0003\'2aA\u001f\u0006C\u0003\u0006m\u0007\u0002C)\u0012\u0005+\u0007I\u0011\u0001*\t\u0013\u0005\u001d\u0018C!E!\u0002\u0013\u0019\u0006\u0002C-\u0012\u0005+\u0007I\u0011\u0001.\t\u0013\u0005%\u0018C!E!\u0002\u0013Y\u0006\"CAV#\tU\r\u0011\"\u0001[\u0011%\tY/\u0005B\tB\u0003%1\f\u0003\u0005g#\tU\r\u0011\"\u0001S\u0011%\ti/\u0005B\tB\u0003%1\u000b\u0003\u0005h#\tU\r\u0011\"\u0001[\u0011%\ty/\u0005B\tB\u0003%1\f\u0003\u0005i#\tU\r\u0011\"\u0001[\u0011%\t\t0\u0005B\tB\u0003%1\f\u0003\u0005j#\tU\r\u0011\"\u0001k\u0011%\t\u00190\u0005B\tB\u0003%1\u000e\u0003\u0006\u00028F\u0011)\u001a!C\u0001\u0003kD!\"a>\u0012\u0005#\u0005\u000b\u0011BA6\u0011)\tY,\u0005BK\u0002\u0013\u0005\u0011\u0011 \u0005\u000b\u0003w\f\"\u0011#Q\u0001\n\u0005e\u0004BB\'\u0012\t\u0003\ti\u0010\u0003\u0004o#\u0011\u0005!\u0011\u0003\u0005\n\u0005+\t\u0012\u0011!C\u0001\u0005/A\u0011Ba\u000b\u0012#\u0003%\tA!\f\t\u0013\tE\u0012#%A\u0005\u0002\tM\u0002\"\u0003B\u001c#E\u0005I\u0011\u0001B\u001a\u0011%\u0011I$EI\u0001\n\u0003\u0011i\u0003C\u0005\u0003<E\t\n\u0011\"\u0001\u00034!I!QH\t\u0012\u0002\u0013\u0005!1\u0007\u0005\n\u0005\u007f\t\u0012\u0013!C\u0001\u0003\'B\u0011B!\u0011\u0012#\u0003%\tAa\u0011\t\u0013\t\u001d\u0013#%A\u0005\u0002\t%\u0003\"\u0003B\'#\u0005\u0005I\u0011\tB(\u0011%\u0011\t&EA\u0001\n\u0003\u0011\u0019\u0006C\u0005\u0003\\E\t\t\u0011\"\u0001\u0003^!I!\u0011N\t\u0002\u0002\u0013\u0005#1\u000e\u0005\n\u0005s\n\u0012\u0011!C\u0001\u0005wB\u0011Ba \u0012\u0003\u0003%\tE!!\t\u0013\t\u0015\u0015#!A\u0005B\t\u001d\u0005\"CAK#\u0005\u0005I\u0011IAL\u0011%\u0011I)EA\u0001\n\u0003\u0012Yi\u0002\u0006\u0002X)\t\t\u0011#\u0001B\u000332\u0011B\u001f\u0006\u0002\u0002#\u0005\u0011)!\u0018\t\r5SD\u0011AAJ\u0011%\t)JOA\u0001\n\u000b\n9\nC\u0005\u0002&i\n\t\u0011\"!\u0002$\"I\u0011Q\u0018\u001e\u0002\u0002\u0013\u0005\u0015q\u0018\u0005\n\u0003#T\u0014\u0011!C\u0005\u0003\'\u0014\u0011CU3wKJ\u001cX-T8ek2,GK]3f\u0015\t\u00115)A\u0003he\u0006\u0004\bNC\u0001E\u0003!\u0019w.\u001e:tS\u0016\u00148\u0001A\n\u0003\u0001\u001d\u0003\"\u0001S&\u000e\u0003%S\u0011AS\u0001\u0006g\u000e\fG.Y\u0005\u0003\u0019&\u0013a!\u00118z%\u00164\u0017A\u0002\u001fj]&$h\bF\u0001P!\t\u0001\u0006!D\u0001B\u0003\u0019iw\u000eZ;mKV\t1\u000b\u0005\u0002U/6\tQK\u0003\u0002W\u0007\u0006!1m\u001c:f\u0013\tAVK\u0001\u0004N_\u0012,H.Z\u0001\u0012e\u0016\u001cwN\\2jY\u0016$g+\u001a:tS>tW#A.\u0011\u0005q\u001bgBA/b!\tq\u0016*D\u0001`\u0015\t\u0001W)\u0001\u0004=e>|GOP\u0005\u0003E&\u000ba\u0001\u0015:fI\u00164\u0017B\u00013f\u0005\u0019\u0019FO]5oO*\u0011!-S\u0001\u0010I\u0016\u0004XM\u001c3t\u001f:lu\u000eZ;mK\u0006\u0001B-\u001a9f]\u0012\u001cxJ\u001c,feNLwN\\\u0001\u001bI\u0016\u0004XM\u001c3t\u001f:\u0014VmY8oG&dW\r\u001a,feNLwN\\\u0001\u0012Kb\u001cG.\u001e3fI\u0012+\u0007/\u001a8eg>sW#A6\u0011\u0005!c\u0017BA7J\u0005\u001d\u0011un\u001c7fC:\f\u0011\u0002Z3qK:$W-Z:\u0016\u0003A\u00042!\u001d<P\u001d\t\u0011HO\u0004\u0002_g&\t!*\u0003\u0002v\u0013\u00069\u0001/Y2lC\u001e,\u0017BA<y\u0005\r\u0019V-\u001d\u0006\u0003k&K#\u0001A\t\u0003\t9{G-Z\n\u0003\u0015\u001d#\u0012! \t\u0003!*\taB\u001a:p[6{G-\u001e7f)J,W\rF\u0003q\u0003\u0003\t9\u0001C\u0004\u0002\u00041\u0001\r!!\u0002\u0002\u000bI|w\u000e^:\u0011\u0007E48\u000bC\u0004\u0002\n1\u0001\r!a\u0003\u0002\u00175|G-\u001e7f)J,Wm\u001d\t\u0005cZ\fi\u0001E\u0002Q\u0003\u001fI1!!\u0005B\u0005)iu\u000eZ;mKR\u0013X-Z\u0001\u0013MJ|W\u000eR3qK:$WM\\2z)J,W\rF\u0003q\u0003/\tI\u0002C\u0004\u0002\u00045\u0001\r!!\u0002\t\u000f\u0005mQ\u00021\u0001\u0002\u001e\u0005yA-\u001a9f]\u0012,gnY=Ue\u0016,7\u000f\u0005\u0003rm\u0006}\u0001c\u0001)\u0002\"%\u0019\u00111E!\u0003\u001d\u0011+\u0007/\u001a8eK:\u001c\u0017\u0010\u0016:fK\u0006)\u0011\r\u001d9msR9\u0001/!\u000b\u00024\u0005U\u0002bBA\u0016\u001d\u0001\u0007\u0011QF\u0001\u000be\u0016\u001cx\u000e\\;uS>t\u0007c\u0001+\u00020%\u0019\u0011\u0011G+\u0003\u0015I+7o\u001c7vi&|g\u000eC\u0005\u0002\u00049\u0001\n\u00111\u0001\u0002\u0006!A\u0011q\u0007\b\u0011\u0002\u0003\u00071.\u0001\bxSRDW\t_2mkNLwN\\:\u0002\u001f\u0005\u0004\b\u000f\\=%I\u00164\u0017-\u001e7uII*\"!!\u0010+\t\u0005\u0015\u0011qH\u0016\u0003\u0003\u0003\u0002B!a\u0011\u0002N5\u0011\u0011Q\t\u0006\u0005\u0003\u000f\nI%A\u0005v]\u000eDWmY6fI*\u0019\u00111J%\u0002\u0015\u0005tgn\u001c;bi&|g.\u0003\u0003\u0002P\u0005\u0015#!E;oG\",7m[3e-\u0006\u0014\u0018.\u00198dK\u0006y\u0011\r\u001d9ms\u0012\"WMZ1vYR$3\'\u0006\u0002\u0002V)\u001a1.a\u0010\u0002\t9{G-\u001a\t\u0004\u00037RT\"\u0001\u0006\u0014\u000bi\ny&a!\u0011#\u0005\u0005\u0014qM*\\7N[6l[A6\u0003s\n\t)\u0004\u0002\u0002d)\u0019\u0011QM%\u0002\u000fI,h\u000e^5nK&!\u0011\u0011NA2\u0005E\t%m\u001d;sC\u000e$h)\u001e8di&|g.\u000f\t\u00079\u000654+!\u001d\n\u0007\u0005=TMA\u0002NCB\u0004B!\u001d<\u0002tA1\u0001*!\u001eT7.L1!a\u001eJ\u0005\u0019!V\u000f\u001d7fgA1A,!\u001cT\u0003w\u0002R\u0001SA?7nK1!a J\u0005\u0019!V\u000f\u001d7feA\u0019\u00111L\t\u0011\t\u0005\u0015\u0015qR\u0007\u0003\u0003\u000fSA!!#\u0002\f\u0006\u0011\u0011n\u001c\u0006\u0003\u0003\u001b\u000bAA[1wC&!\u0011\u0011SAD\u00051\u0019VM]5bY&T\u0018M\u00197f)\t\tI&\u0001\u0005u_N#(/\u001b8h)\t\tI\n\u0005\u0003\u0002\u001c\u0006\u0005VBAAO\u0015\u0011\ty*a#\u0002\t1\fgnZ\u0005\u0004I\u0006uE\u0003FAA\u0003K\u000b9+!+\u0002.\u0006=\u0016\u0011WAZ\u0003k\u000bI\fC\u0003R{\u0001\u00071\u000bC\u0003Z{\u0001\u00071\f\u0003\u0004\u0002,v\u0002\raW\u0001\u0010e\u0016$\u0018-\u001b8fIZ+\'o]5p]\")a-\u0010a\u0001\'\")q-\u0010a\u00017\")\u0001.\u0010a\u00017\")\u0011.\u0010a\u0001W\"9\u0011qW\u001fA\u0002\u0005-\u0014\u0001D1mY\u0012+\u0007/\u001a8eK\u0016\u001c\bbBA^{\u0001\u0007\u0011\u0011P\u0001\tm\u0016\u00148/[8og\u00069QO\\1qa2LH\u0003BAa\u0003\u001b\u0004R\u0001SAb\u0003\u000fL1!!2J\u0005\u0019y\u0005\u000f^5p]Bq\u0001*!3T7n\u001b6lW6\u0002l\u0005e\u0014bAAf\u0013\n1A+\u001e9mKfB\u0011\"a4?\u0003\u0003\u0005\r!!!\u0002\u0007a$\u0003\'\u0001\u0007xe&$XMU3qY\u0006\u001cW\r\u0006\u0002\u0002VB!\u00111TAl\u0013\u0011\tI.!(\u0003\r=\u0013\'.Z2u\'\u0019\tr*!8\u0002dB\u0019\u0001*a8\n\u0007\u0005\u0005\u0018JA\u0004Qe>$Wo\u0019;\u0011\u0007E\f)/C\u0002\u0002\u0012b\fq!\\8ek2,\u0007%\u0001\nsK\u000e|gnY5mK\u00124VM]:j_:\u0004\u0013\u0001\u0005:fi\u0006Lg.\u001a3WKJ\u001c\u0018n\u001c8!\u0003A!W\r]3oIN|e.T8ek2,\u0007%A\teKB,g\u000eZ:P]Z+\'o]5p]\u0002\n1\u0004Z3qK:$7o\u00148SK\u000e|gnY5mK\u00124VM]:j_:\u0004\u0013AE3yG2,H-\u001a3EKB,g\u000eZ:P]\u0002*\"!a\u001b\u0002\u001b\u0005dG\u000eR3qK:$W-Z:!+\t\tI(A\u0005wKJ\u001c\u0018n\u001c8tAQ!\u0012\u0011QA\u0000\u0005\u0003\u0011\u0019A!\u0002\u0003\b\t%!1\u0002B\u0007\u0005\u001fAQ!\u0015\u0013A\u0002MCQ!\u0017\u0013A\u0002mCa!a+%\u0001\u0004Y\u0006\"\u00024%\u0001\u0004\u0019\u0006\"B4%\u0001\u0004Y\u0006\"\u00025%\u0001\u0004Y\u0006\"B5%\u0001\u0004Y\u0007bBA\\I\u0001\u0007\u00111\u000e\u0005\b\u0003w#\u0003\u0019AA=+\t\u0011\u0019\u0002\u0005\u0003rm\u0006\u0005\u0015\u0001B2paf$B#!!\u0003\u001a\tm!Q\u0004B\u0010\u0005C\u0011\u0019C!\n\u0003(\t%\u0002bB)\'!\u0003\u0005\ra\u0015\u0005\b3\u001a\u0002\n\u00111\u0001\\\u0011!\tYK\nI\u0001\u0002\u0004Y\u0006b\u00024\'!\u0003\u0005\ra\u0015\u0005\bO\u001a\u0002\n\u00111\u0001\\\u0011\u001dAg\u0005%AA\u0002mCq!\u001b\u0014\u0011\u0002\u0003\u00071\u000eC\u0005\u00028\u001a\u0002\n\u00111\u0001\u0002l!I\u00111\u0018\u0014\u0011\u0002\u0003\u0007\u0011\u0011P\u0001\u000fG>\u0004\u0018\u0010\n3fM\u0006,H\u000e\u001e\u00132+\t\u0011yCK\u0002T\u0003\u007f\tabY8qs\u0012\"WMZ1vYR$#\'\u0006\u0002\u00036)\u001a1,a\u0010\u0002\u001d\r|\u0007/\u001f\u0013eK\u001a\fW\u000f\u001c;%g\u0005q1m\u001c9zI\u0011,g-Y;mi\u0012\"\u0014AD2paf$C-\u001a4bk2$H%N\u0001\u000fG>\u0004\u0018\u0010\n3fM\u0006,H\u000e\u001e\u00137\u00039\u0019w\u000e]=%I\u00164\u0017-\u001e7uI]\nabY8qs\u0012\"WMZ1vYR$\u0003(\u0006\u0002\u0003F)\"\u00111NA \u00039\u0019w\u000e]=%I\u00164\u0017-\u001e7uIe*\"Aa\u0013+\t\u0005e\u0014qH\u0001\u000eaJ|G-^2u!J,g-\u001b=\u0016\u0005\u0005e\u0015\u0001\u00049s_\u0012,8\r^!sSRLXC\u0001B+!\rA%qK\u0005\u0004\u00053J%aA%oi\u0006q\u0001O]8ek\u000e$X\t\\3nK:$H\u0003\u0002B0\u0005K\u00022\u0001\u0013B1\u0013\r\u0011\u0019\'\u0013\u0002\u0004\u0003:L\b\"\u0003B4e\u0005\u0005\t\u0019\u0001B+\u0003\rAH%M\u0001\u0010aJ|G-^2u\u0013R,\'/\u0019;peV\u0011!Q\u000e\t\u0007\u0005_\u0012)Ha\u0018\u000e\u0005\tE$b\u0001B:\u0013\u0006Q1m\u001c7mK\u000e$\u0018n\u001c8\n\t\t]$\u0011\u000f\u0002\t\u0013R,\'/\u0019;pe\u0006A1-\u00198FcV\fG\u000eF\u0002l\u0005{B\u0011Ba\u001a5\u0003\u0003\u0005\rAa\u0018\u0002%A\u0014x\u000eZ;di\u0016cW-\\3oi:\u000bW.\u001a\u000b\u0005\u00033\u0013\u0019\tC\u0005\u0003hU\n\t\u00111\u0001\u0003V\u0005A\u0001.Y:i\u0007>$W\r\u0006\u0002\u0003V\u00051Q-];bYN$2a\u001bBG\u0011%\u00119\u0007OA\u0001\u0002\u0004\u0011y&A\tSKZ,\'o]3N_\u0012,H.\u001a+sK\u0016\u0004
   #9 = Utf8               coursier/graph/ReverseModuleTree$Node
  #10 = Class              #9             // coursier/graph/ReverseModuleTree$Node
  #11 = Utf8               Node
  #12 = Utf8               coursier/graph/ReverseModuleTree$Node$
  #13 = Class              #12            // coursier/graph/ReverseModuleTree$Node$
  #14 = Utf8
  #15 = Utf8               apply$default$3
  #16 = Utf8               ()Z
  #17 = Utf8               coursier/graph/ReverseModuleTree$
  #18 = Class              #17            // coursier/graph/ReverseModuleTree$
  #19 = Utf8               MODULE$
  #20 = Utf8               Lcoursier/graph/ReverseModuleTree$;
  #21 = NameAndType        #19:#20        // MODULE$:Lcoursier/graph/ReverseModuleTree$;
  #22 = Fieldref           #18.#21        // coursier/graph/ReverseModuleTree$.MODULE$:Lcoursier/graph/ReverseModuleTree$;
  #23 = NameAndType        #15:#16        // apply$default$3:()Z
  #24 = Methodref          #18.#23        // coursier/graph/ReverseModuleTree$.apply$default$3:()Z
  #25 = Utf8               apply$default$2
  #26 = Utf8               ()Lscala/collection/immutable/Seq;
  #27 = Utf8               ()Lscala/collection/immutable/Seq<Lcoursier/core/Module;>;
  #28 = NameAndType        #25:#26        // apply$default$2:()Lscala/collection/immutable/Seq;
  #29 = Methodref          #18.#28        // coursier/graph/ReverseModuleTree$.apply$default$2:()Lscala/collection/immutable/Seq;
  #30 = Utf8               apply
  #31 = Utf8               (Lcoursier/core/Resolution;Lscala/collection/immutable/Seq;Z)Lscala/collection/immutable/Seq;
  #32 = Utf8               (Lcoursier/core/Resolution;Lscala/collection/immutable/Seq<Lcoursier/core/Module;>;Z)Lscala/collection/immutable/Seq<Lcoursier/graph/ReverseModuleTree;>;
  #33 = Utf8               resolution
  #34 = Utf8               roots
  #35 = Utf8               withExclusions
  #36 = NameAndType        #30:#31        // apply:(Lcoursier/core/Resolution;Lscala/collection/immutable/Seq;Z)Lscala/collection/immutable/Seq;
  #37 = Methodref          #18.#36        // coursier/graph/ReverseModuleTree$.apply:(Lcoursier/core/Resolution;Lscala/collection/immutable/Seq;Z)Lscala/collection/immutable/Seq;
  #38 = Utf8               fromDependencyTree
  #39 = Utf8               (Lscala/collection/immutable/Seq;Lscala/collection/immutable/Seq;)Lscala/collection/immutable/Seq;
  #40 = Utf8               (Lscala/collection/immutable/Seq<Lcoursier/core/Module;>;Lscala/collection/immutable/Seq<Lcoursier/graph/DependencyTree;>;)Lscala/collection/immutable/Seq<Lcoursier/graph/ReverseModuleTree;>;
  #41 = Utf8               dependencyTrees
  #42 = NameAndType        #38:#39        // fromDependencyTree:(Lscala/collection/immutable/Seq;Lscala/collection/immutable/Seq;)Lscala/collection/immutable/Seq;
  #43 = Methodref          #18.#42        // coursier/graph/ReverseModuleTree$.fromDependencyTree:(Lscala/collection/immutable/Seq;Lscala/collection/immutable/Seq;)Lscala/collection/immutable/Seq;
  #44 = Utf8               fromModuleTree
  #45 = Utf8               (Lscala/collection/immutable/Seq<Lcoursier/core/Module;>;Lscala/collection/immutable/Seq<Lcoursier/graph/ModuleTree;>;)Lscala/collection/immutable/Seq<Lcoursier/graph/ReverseModuleTree;>;
  #46 = Utf8               moduleTrees
  #47 = NameAndType        #44:#39        // fromModuleTree:(Lscala/collection/immutable/Seq;Lscala/collection/immutable/Seq;)Lscala/collection/immutable/Seq;
  #48 = Methodref          #18.#47        // coursier/graph/ReverseModuleTree$.fromModuleTree:(Lscala/collection/immutable/Seq;Lscala/collection/immutable/Seq;)Lscala/collection/immutable/Seq;
  #49 = Utf8               module
  #50 = Utf8               ()Lcoursier/core/Module;
  #51 = Utf8               reconciledVersion
  #52 = Utf8               ()Ljava/lang/String;
  #53 = Utf8               dependsOnModule
  #54 = Utf8               dependsOnVersion
  #55 = Utf8               dependsOnReconciledVersion
  #56 = Utf8               excludedDependsOn
  #57 = Utf8               dependees
  #58 = Utf8               ()Lscala/collection/immutable/Seq<Lcoursier/graph/ReverseModuleTree;>;
  #59 = Utf8               <init>
  #60 = Utf8               ()V
  #61 = NameAndType        #59:#60        // "<init>":()V
  #62 = Methodref          #4.#61         // java/lang/Object."<init>":()V
  #63 = Utf8               this
  #64 = Utf8               Lcoursier/graph/ReverseModuleTree;
  #65 = Utf8               Code
  #66 = Utf8               Signature
  #67 = Utf8               MethodParameters
  #68 = Utf8               LineNumberTable
  #69 = Utf8               LocalVariableTable
  #70 = Utf8               InnerClasses
  #71 = Utf8               SourceFile
  #72 = Utf8               RuntimeVisibleAnnotations
  #73 = Utf8               ScalaInlineInfo
  #74 = Utf8               ScalaSig
{
  public static boolean apply$default$3();
    descriptor: ()Z
    flags: (0x0009) ACC_PUBLIC, ACC_STATIC
    Code:
      stack=1, locals=0, args_size=0
         0: getstatic     #22                 // Field coursier/graph/ReverseModuleTree$.MODULE$:Lcoursier/graph/ReverseModuleTree$;
         3: invokevirtual #24                 // Method coursier/graph/ReverseModuleTree$.apply$default$3:()Z
         6: ireturn

  public static scala.collection.immutable.Seq<coursier.core.Module> apply$default$2();
    descriptor: ()Lscala/collection/immutable/Seq;
    flags: (0x0009) ACC_PUBLIC, ACC_STATIC
    Code:
      stack=1, locals=0, args_size=0
         0: getstatic     #22                 // Field coursier/graph/ReverseModuleTree$.MODULE$:Lcoursier/graph/ReverseModuleTree$;
         3: invokevirtual #29                 // Method coursier/graph/ReverseModuleTree$.apply$default$2:()Lscala/collection/immutable/Seq;
         6: areturn
    Signature: #27                          // ()Lscala/collection/immutable/Seq<Lcoursier/core/Module;>;

  public static scala.collection.immutable.Seq<coursier.graph.ReverseModuleTree> apply(coursier.core.Resolution, scala.collection.immutable.Seq<coursier.core.Module>, boolean);
    descriptor: (Lcoursier/core/Resolution;Lscala/collection/immutable/Seq;Z)Lscala/collection/immutable/Seq;
    flags: (0x0009) ACC_PUBLIC, ACC_STATIC
    Code:
      stack=4, locals=3, args_size=3
         0: getstatic     #22                 // Field coursier/graph/ReverseModuleTree$.MODULE$:Lcoursier/graph/ReverseModuleTree$;
         3: aload_0
         4: aload_1
         5: iload_2
         6: invokevirtual #37                 // Method coursier/graph/ReverseModuleTree$.apply:(Lcoursier/core/Resolution;Lscala/collection/immutable/Seq;Z)Lscala/collection/immutable/Seq;
         9: areturn
    Signature: #32                          // (Lcoursier/core/Resolution;Lscala/collection/immutable/Seq<Lcoursier/core/Module;>;Z)Lscala/collection/immutable/Seq<Lcoursier/graph/ReverseModuleTree;>;
    MethodParameters:
      Name                           Flags
      resolution                     final
      roots                          final
      withExclusions                 final

  public static scala.collection.immutable.Seq<coursier.graph.ReverseModuleTree> fromDependencyTree(scala.collection.immutable.Seq<coursier.core.Module>, scala.collection.immutable.Seq<coursier.graph.DependencyTree>);
    descriptor: (Lscala/collection/immutable/Seq;Lscala/collection/immutable/Seq;)Lscala/collection/immutable/Seq;
    flags: (0x0009) ACC_PUBLIC, ACC_STATIC
    Code:
      stack=3, locals=2, args_size=2
         0: getstatic     #22                 // Field coursier/graph/ReverseModuleTree$.MODULE$:Lcoursier/graph/ReverseModuleTree$;
         3: aload_0
         4: aload_1
         5: invokevirtual #43                 // Method coursier/graph/ReverseModuleTree$.fromDependencyTree:(Lscala/collection/immutable/Seq;Lscala/collection/immutable/Seq;)Lscala/collection/immutable/Seq;
         8: areturn
    Signature: #40                          // (Lscala/collection/immutable/Seq<Lcoursier/core/Module;>;Lscala/collection/immutable/Seq<Lcoursier/graph/DependencyTree;>;)Lscala/collection/immutable/Seq<Lcoursier/graph/ReverseModuleTree;>;
    MethodParameters:
      Name                           Flags
      roots                          final
      dependencyTrees                final

  public static scala.collection.immutable.Seq<coursier.graph.ReverseModuleTree> fromModuleTree(scala.collection.immutable.Seq<coursier.core.Module>, scala.collection.immutable.Seq<coursier.graph.ModuleTree>);
    descriptor: (Lscala/collection/immutable/Seq;Lscala/collection/immutable/Seq;)Lscala/collection/immutable/Seq;
    flags: (0x0009) ACC_PUBLIC, ACC_STATIC
    Code:
      stack=3, locals=2, args_size=2
         0: getstatic     #22                 // Field coursier/graph/ReverseModuleTree$.MODULE$:Lcoursier/graph/ReverseModuleTree$;
         3: aload_0
         4: aload_1
         5: invokevirtual #48                 // Method coursier/graph/ReverseModuleTree$.fromModuleTree:(Lscala/collection/immutable/Seq;Lscala/collection/immutable/Seq;)Lscala/collection/immutable/Seq;
         8: areturn
    Signature: #45                          // (Lscala/collection/immutable/Seq<Lcoursier/core/Module;>;Lscala/collection/immutable/Seq<Lcoursier/graph/ModuleTree;>;)Lscala/collection/immutable/Seq<Lcoursier/graph/ReverseModuleTree;>;
    MethodParameters:
      Name                           Flags
      roots                          final
      moduleTrees                    final

  public abstract coursier.core.Module module();
    descriptor: ()Lcoursier/core/Module;
    flags: (0x0401) ACC_PUBLIC, ACC_ABSTRACT

  public abstract java.lang.String reconciledVersion();
    descriptor: ()Ljava/lang/String;
    flags: (0x0401) ACC_PUBLIC, ACC_ABSTRACT

  public abstract coursier.core.Module dependsOnModule();
    descriptor: ()Lcoursier/core/Module;
    flags: (0x0401) ACC_PUBLIC, ACC_ABSTRACT

  public abstract java.lang.String dependsOnVersion();
    descriptor: ()Ljava/lang/String;
    flags: (0x0401) ACC_PUBLIC, ACC_ABSTRACT

  public abstract java.lang.String dependsOnReconciledVersion();
    descriptor: ()Ljava/lang/String;
    flags: (0x0401) ACC_PUBLIC, ACC_ABSTRACT

  public abstract boolean excludedDependsOn();
    descriptor: ()Z
    flags: (0x0401) ACC_PUBLIC, ACC_ABSTRACT

  public abstract scala.collection.immutable.Seq<coursier.graph.ReverseModuleTree> dependees();
    descriptor: ()Lscala/collection/immutable/Seq;
    flags: (0x0401) ACC_PUBLIC, ACC_ABSTRACT
    Signature: #58                          // ()Lscala/collection/immutable/Seq<Lcoursier/graph/ReverseModuleTree;>;

  public coursier.graph.ReverseModuleTree();
    descriptor: ()V
    flags: (0x0001) ACC_PUBLIC
    Code:
      stack=1, locals=1, args_size=1
         0: aload_0
         1: invokespecial #62                 // Method java/lang/Object."<init>":()V
         4: return
      LineNumberTable:
        line 55: 0
        line 9: 4
      LocalVariableTable:
        Start  Length  Slot  Name   Signature
            0       5     0  this   Lcoursier/graph/ReverseModuleTree;
}
InnerClasses:
  public static final #11= #10 of #2;     // Node=class coursier/graph/ReverseModuleTree$Node of class coursier/graph/ReverseModuleTree
  public static #14= #13 of #2;           // =class coursier/graph/ReverseModuleTree$Node$ of class coursier/graph/ReverseModuleTree
SourceFile: "ReverseModuleTree.scala"
RuntimeVisibleAnnotations:
  0: #6(#7=s#8)
    scala.reflect.ScalaSignature(
      bytes="\u0006\u0005\tEe!\u0002!B\u0003C1\u0005\"B\'\u0001\t\u0003q\u0005\"B)\u0001\r\u0003\u0011\u0006\"B-\u0001\r\u0003Q\u0006\"\u00024\u0001\r\u0003\u0011\u0006\"B4\u0001\r\u0003Q\u0006\"\u00025\u0001\r\u0003Q\u0006\"B5\u0001\r\u0003Q\u0007\"\u00028\u0001\r\u0003ywA\u0002BH\u0003\"\u0005QPB\u0003A\u0003\"\u00051\u0010C\u0003N\u0015\u0011\u0005A\u0010C\u0003\u007f\u0015\u0011\u0005q\u0010C\u0004\u0002\u0014)!\t!!\u0006\t\u000f\u0005\u0015\"\u0002\"\u0001\u0002(!I\u0011\u0011\b\u0006\u0012\u0002\u0013\u0005\u00111\b\u0005\n\u0003#R\u0011\u0013!C\u0001\u0003\'2aA\u001f\u0006C\u0003\u0006m\u0007\u0002C)\u0012\u0005+\u0007I\u0011\u0001*\t\u0013\u0005\u001d\u0018C!E!\u0002\u0013\u0019\u0006\u0002C-\u0012\u0005+\u0007I\u0011\u0001.\t\u0013\u0005%\u0018C!E!\u0002\u0013Y\u0006\"CAV#\tU\r\u0011\"\u0001[\u0011%\tY/\u0005B\tB\u0003%1\f\u0003\u0005g#\tU\r\u0011\"\u0001S\u0011%\ti/\u0005B\tB\u0003%1\u000b\u0003\u0005h#\tU\r\u0011\"\u0001[\u0011%\ty/\u0005B\tB\u0003%1\f\u0003\u0005i#\tU\r\u0011\"\u0001[\u0011%\t\t0\u0005B\tB\u0003%1\f\u0003\u0005j#\tU\r\u0011\"\u0001k\u0011%\t\u00190\u0005B\tB\u0003%1\u000e\u0003\u0006\u00028F\u0011)\u001a!C\u0001\u0003kD!\"a>\u0012\u0005#\u0005\u000b\u0011BA6\u0011)\tY,\u0005BK\u0002\u0013\u0005\u0011\u0011 \u0005\u000b\u0003w\f\"\u0011#Q\u0001\n\u0005e\u0004BB\'\u0012\t\u0003\ti\u0010\u0003\u0004o#\u0011\u0005!\u0011\u0003\u0005\n\u0005+\t\u0012\u0011!C\u0001\u0005/A\u0011Ba\u000b\u0012#\u0003%\tA!\f\t\u0013\tE\u0012#%A\u0005\u0002\tM\u0002\"\u0003B\u001c#E\u0005I\u0011\u0001B\u001a\u0011%\u0011I$EI\u0001\n\u0003\u0011i\u0003C\u0005\u0003<E\t\n\u0011\"\u0001\u00034!I!QH\t\u0012\u0002\u0013\u0005!1\u0007\u0005\n\u0005\u007f\t\u0012\u0013!C\u0001\u0003\'B\u0011B!\u0011\u0012#\u0003%\tAa\u0011\t\u0013\t\u001d\u0013#%A\u0005\u0002\t%\u0003\"\u0003B\'#\u0005\u0005I\u0011\tB(\u0011%\u0011\t&EA\u0001\n\u0003\u0011\u0019\u0006C\u0005\u0003\\E\t\t\u0011\"\u0001\u0003^!I!\u0011N\t\u0002\u0002\u0013\u0005#1\u000e\u0005\n\u0005s\n\u0012\u0011!C\u0001\u0005wB\u0011Ba \u0012\u0003\u0003%\tE!!\t\u0013\t\u0015\u0015#!A\u0005B\t\u001d\u0005\"CAK#\u0005\u0005I\u0011IAL\u0011%\u0011I)EA\u0001\n\u0003\u0012Yi\u0002\u0006\u0002X)\t\t\u0011#\u0001B\u000332\u0011B\u001f\u0006\u0002\u0002#\u0005\u0011)!\u0018\t\r5SD\u0011AAJ\u0011%\t)JOA\u0001\n\u000b\n9\nC\u0005\u0002&i\n\t\u0011\"!\u0002$\"I\u0011Q\u0018\u001e\u0002\u0002\u0013\u0005\u0015q\u0018\u0005\n\u0003#T\u0014\u0011!C\u0005\u0003\'\u0014\u0011CU3wKJ\u001cX-T8ek2,GK]3f\u0015\t\u00115)A\u0003he\u0006\u0004\bNC\u0001E\u0003!\u0019w.\u001e:tS\u0016\u00148\u0001A\n\u0003\u0001\u001d\u0003\"\u0001S&\u000e\u0003%S\u0011AS\u0001\u0006g\u000e\fG.Y\u0005\u0003\u0019&\u0013a!\u00118z%\u00164\u0017A\u0002\u001fj]&$h\bF\u0001P!\t\u0001\u0006!D\u0001B\u0003\u0019iw\u000eZ;mKV\t1\u000b\u0005\u0002U/6\tQK\u0003\u0002W\u0007\u0006!1m\u001c:f\u0013\tAVK\u0001\u0004N_\u0012,H.Z\u0001\u0012e\u0016\u001cwN\\2jY\u0016$g+\u001a:tS>tW#A.\u0011\u0005q\u001bgBA/b!\tq\u0016*D\u0001`\u0015\t\u0001W)\u0001\u0004=e>|GOP\u0005\u0003E&\u000ba\u0001\u0015:fI\u00164\u0017B\u00013f\u0005\u0019\u0019FO]5oO*\u0011!-S\u0001\u0010I\u0016\u0004XM\u001c3t\u001f:lu\u000eZ;mK\u0006\u0001B-\u001a9f]\u0012\u001cxJ\u001c,feNLwN\\\u0001\u001bI\u0016\u0004XM\u001c3t\u001f:\u0014VmY8oG&dW\r\u001a,feNLwN\\\u0001\u0012Kb\u001cG.\u001e3fI\u0012+\u0007/\u001a8eg>sW#A6\u0011\u0005!c\u0017BA7J\u0005\u001d\u0011un\u001c7fC:\f\u0011\u0002Z3qK:$W-Z:\u0016\u0003A\u00042!\u001d<P\u001d\t\u0011HO\u0004\u0002_g&\t!*\u0003\u0002v\u0013\u00069\u0001/Y2lC\u001e,\u0017BA<y\u0005\r\u0019V-\u001d\u0006\u0003k&K#\u0001A\t\u0003\t9{G-Z\n\u0003\u0015\u001d#\u0012! \t\u0003!*\taB\u001a:p[6{G-\u001e7f)J,W\rF\u0003q\u0003\u0003\t9\u0001C\u0004\u0002\u00041\u0001\r!!\u0002\u0002\u000bI|w\u000e^:\u0011\u0007E48\u000bC\u0004\u0002\n1\u0001\r!a\u0003\u0002\u00175|G-\u001e7f)J,Wm\u001d\t\u0005cZ\fi\u0001E\u0002Q\u0003\u001fI1!!\u0005B\u0005)iu\u000eZ;mKR\u0013X-Z\u0001\u0013MJ|W\u000eR3qK:$WM\\2z)J,W\rF\u0003q\u0003/\tI\u0002C\u0004\u0002\u00045\u0001\r!!\u0002\t\u000f\u0005mQ\u00021\u0001\u0002\u001e\u0005yA-\u001a9f]\u0012,gnY=Ue\u0016,7\u000f\u0005\u0003rm\u0006}\u0001c\u0001)\u0002\"%\u0019\u00111E!\u0003\u001d\u0011+\u0007/\u001a8eK:\u001c\u0017\u0010\u0016:fK\u0006)\u0011\r\u001d9msR9\u0001/!\u000b\u00024\u0005U\u0002bBA\u0016\u001d\u0001\u0007\u0011QF\u0001\u000be\u0016\u001cx\u000e\\;uS>t\u0007c\u0001+\u00020%\u0019\u0011\u0011G+\u0003\u0015I+7o\u001c7vi&|g\u000eC\u0005\u0002\u00049\u0001\n\u00111\u0001\u0002\u0006!A\u0011q\u0007\b\u0011\u0002\u0003\u00071.\u0001\bxSRDW\t_2mkNLwN\\:\u0002\u001f\u0005\u0004\b\u000f\\=%I\u00164\u0017-\u001e7uII*\"!!\u0010+\t\u0005\u0015\u0011qH\u0016\u0003\u0003\u0003\u0002B!a\u0011\u0002N5\u0011\u0011Q\t\u0006\u0005\u0003\u000f\nI%A\u0005v]\u000eDWmY6fI*\u0019\u00111J%\u0002\u0015\u0005tgn\u001c;bi&|g.\u0003\u0003\u0002P\u0005\u0015#!E;oG\",7m[3e-\u0006\u0014\u0018.\u00198dK\u0006y\u0011\r\u001d9ms\u0012\"WMZ1vYR$3\'\u0006\u0002\u0002V)\u001a1.a\u0010\u0002\t9{G-\u001a\t\u0004\u00037RT\"\u0001\u0006\u0014\u000bi\ny&a!\u0011#\u0005\u0005\u0014qM*\\7N[6l[A6\u0003s\n\t)\u0004\u0002\u0002d)\u0019\u0011QM%\u0002\u000fI,h\u000e^5nK&!\u0011\u0011NA2\u0005E\t%m\u001d;sC\u000e$h)\u001e8di&|g.\u000f\t\u00079\u000654+!\u001d\n\u0007\u0005=TMA\u0002NCB\u0004B!\u001d<\u0002tA1\u0001*!\u001eT7.L1!a\u001eJ\u0005\u0019!V\u000f\u001d7fgA1A,!\u001cT\u0003w\u0002R\u0001SA?7nK1!a J\u0005\u0019!V\u000f\u001d7feA\u0019\u00111L\t\u0011\t\u0005\u0015\u0015qR\u0007\u0003\u0003\u000fSA!!#\u0002\f\u0006\u0011\u0011n\u001c\u0006\u0003\u0003\u001b\u000bAA[1wC&!\u0011\u0011SAD\u00051\u0019VM]5bY&T\u0018M\u00197f)\t\tI&\u0001\u0005u_N#(/\u001b8h)\t\tI\n\u0005\u0003\u0002\u001c\u0006\u0005VBAAO\u0015\u0011\ty*a#\u0002\t1\fgnZ\u0005\u0004I\u0006uE\u0003FAA\u0003K\u000b9+!+\u0002.\u0006=\u0016\u0011WAZ\u0003k\u000bI\fC\u0003R{\u0001\u00071\u000bC\u0003Z{\u0001\u00071\f\u0003\u0004\u0002,v\u0002\raW\u0001\u0010e\u0016$\u0018-\u001b8fIZ+\'o]5p]\")a-\u0010a\u0001\'\")q-\u0010a\u00017\")\u0001.\u0010a\u00017\")\u0011.\u0010a\u0001W\"9\u0011qW\u001fA\u0002\u0005-\u0014\u0001D1mY\u0012+\u0007/\u001a8eK\u0016\u001c\bbBA^{\u0001\u0007\u0011\u0011P\u0001\tm\u0016\u00148/[8og\u00069QO\\1qa2LH\u0003BAa\u0003\u001b\u0004R\u0001SAb\u0003\u000fL1!!2J\u0005\u0019y\u0005\u000f^5p]Bq\u0001*!3T7n\u001b6lW6\u0002l\u0005e\u0014bAAf\u0013\n1A+\u001e9mKfB\u0011\"a4?\u0003\u0003\u0005\r!!!\u0002\u0007a$\u0003\'\u0001\u0007xe&$XMU3qY\u0006\u001cW\r\u0006\u0002\u0002VB!\u00111TAl\u0013\u0011\tI.!(\u0003\r=\u0013\'.Z2u\'\u0019\tr*!8\u0002dB\u0019\u0001*a8\n\u0007\u0005\u0005\u0018JA\u0004Qe>$Wo\u0019;\u0011\u0007E\f)/C\u0002\u0002\u0012b\fq!\\8ek2,\u0007%\u0001\nsK\u000e|gnY5mK\u00124VM]:j_:\u0004\u0013\u0001\u0005:fi\u0006Lg.\u001a3WKJ\u001c\u0018n\u001c8!\u0003A!W\r]3oIN|e.T8ek2,\u0007%A\teKB,g\u000eZ:P]Z+\'o]5p]\u0002\n1\u0004Z3qK:$7o\u00148SK\u000e|gnY5mK\u00124VM]:j_:\u0004\u0013AE3yG2,H-\u001a3EKB,g\u000eZ:P]\u0002*\"!a\u001b\u0002\u001b\u0005dG\u000eR3qK:$W-Z:!+\t\tI(A\u0005wKJ\u001c\u0018n\u001c8tAQ!\u0012\u0011QA\u0000\u0005\u0003\u0011\u0019A!\u0002\u0003\b\t%!1\u0002B\u0007\u0005\u001fAQ!\u0015\u0013A\u0002MCQ!\u0017\u0013A\u0002mCa!a+%\u0001\u0004Y\u0006\"\u00024%\u0001\u0004\u0019\u0006\"B4%\u0001\u0004Y\u0006\"\u00025%\u0001\u0004Y\u0006\"B5%\u0001\u0004Y\u0007bBA\\I\u0001\u0007\u00111\u000e\u0005\b\u0003w#\u0003\u0019AA=+\t\u0011\u0019\u0002\u0005\u0003rm\u0006\u0005\u0015\u0001B2paf$B#!!\u0003\u001a\tm!Q\u0004B\u0010\u0005C\u0011\u0019C!\n\u0003(\t%\u0002bB)\'!\u0003\u0005\ra\u0015\u0005\b3\u001a\u0002\n\u00111\u0001\\\u0011!\tYK\nI\u0001\u0002\u0004Y\u0006b\u00024\'!\u0003\u0005\ra\u0015\u0005\bO\u001a\u0002\n\u00111\u0001\\\u0011\u001dAg\u0005%AA\u0002mCq!\u001b\u0014\u0011\u0002\u0003\u00071\u000eC\u0005\u00028\u001a\u0002\n\u00111\u0001\u0002l!I\u00111\u0018\u0014\u0011\u0002\u0003\u0007\u0011\u0011P\u0001\u000fG>\u0004\u0018\u0010\n3fM\u0006,H\u000e\u001e\u00132+\t\u0011yCK\u0002T\u0003\u007f\tabY8qs\u0012\"WMZ1vYR$#\'\u0006\u0002\u00036)\u001a1,a\u0010\u0002\u001d\r|\u0007/\u001f\u0013eK\u001a\fW\u000f\u001c;%g\u0005q1m\u001c9zI\u0011,g-Y;mi\u0012\"\u0014AD2paf$C-\u001a4bk2$H%N\u0001\u000fG>\u0004\u0018\u0010\n3fM\u0006,H\u000e\u001e\u00137\u00039\u0019w\u000e]=%I\u00164\u0017-\u001e7uI]\nabY8qs\u0012\"WMZ1vYR$\u0003(\u0006\u0002\u0003F)\"\u00111NA \u00039\u0019w\u000e]=%I\u00164\u0017-\u001e7uIe*\"Aa\u0013+\t\u0005e\u0014qH\u0001\u000eaJ|G-^2u!J,g-\u001b=\u0016\u0005\u0005e\u0015\u0001\u00049s_\u0012,8\r^!sSRLXC\u0001B+!\rA%qK\u0005\u0004\u00053J%aA%oi\u0006q\u0001O]8ek\u000e$X\t\\3nK:$H\u0003\u0002B0\u0005K\u00022\u0001\u0013B1\u0013\r\u0011\u0019\'\u0013\u0002\u0004\u0003:L\b\"\u0003B4e\u0005\u0005\t\u0019\u0001B+\u0003\rAH%M\u0001\u0010aJ|G-^2u\u0013R,\'/\u0019;peV\u0011!Q\u000e\t\u0007\u0005_\u0012)Ha\u0018\u000e\u0005\tE$b\u0001B:\u0013\u0006Q1m\u001c7mK\u000e$\u0018n\u001c8\n\t\t]$\u0011\u000f\u0002\t\u0013R,\'/\u0019;pe\u0006A1-\u00198FcV\fG\u000eF\u0002l\u0005{B\u0011Ba\u001a5\u0003\u0003\u0005\rAa\u0018\u0002%A\u0014x\u000eZ;di\u0016cW-\\3oi:\u000bW.\u001a\u000b\u0005\u00033\u0013\u0019\tC\u0005\u0003hU\n\t\u00111\u0001\u0003V\u0005A\u0001.Y:i\u0007>$W\r\u0006\u0002\u0003V\u00051Q-];bYN$2a\u001bBG\u0011%\u00119\u0007OA\u0001\u0002\u0004\u0011y&A\tSKZ,\'o]3N_\u0012,H.\u001a+sK\u0016\u0004"
    )
  ScalaInlineInfo: length = 0x2C (unknown attribute)
   01 00 00 08 00 3B 00 3C 01 00 39 00 1A 00 00 35
   00 32 00 00 37 00 34 00 00 36 00 34 00 00 38 00
   10 00 00 31 00 32 00 00 33 00 34 00
  ScalaSig: length = 0x3 (unknown attribute)
   05 02 00
