Classfile /Users/mw/Projects/slang-braindump/.jar/jar11/assemble/slang-braindump/assemble/content/scala/math/BigInt$.class
  Last modified May 29, 2022; size 4667 bytes
  SHA-256 checksum 1f100fe6bac4712f27aa4654e40a3dd517f17cc4ce8cc1a387a48257fa536f13
  Compiled from "BigInt.scala"
public final class scala.math.BigInt$ implements java.io.Serializable
  minor version: 0
  major version: 52
  flags: (0x0031) ACC_PUBLIC, ACC_FINAL, ACC_SUPER
  this_class: #2                          // scala/math/BigInt$
  super_class: #4                         // java/lang/Object
  interfaces: 1, fields: 7, methods: 21, attributes: 3
Constant pool:
    #1 = Utf8               scala/math/BigInt$
    #2 = Class              #1            // scala/math/BigInt$
    #3 = Utf8               java/lang/Object
    #4 = Class              #3            // java/lang/Object
    #5 = Utf8               java/io/Serializable
    #6 = Class              #5            // java/io/Serializable
    #7 = Utf8               BigInt.scala
    #8 = Utf8               MODULE$
    #9 = Utf8               Lscala/math/BigInt$;
   #10 = Utf8               scala$math$BigInt$$longMinValueBigInteger
   #11 = Utf8               Ljava/math/BigInteger;
   #12 = Utf8               longMinValue
   #13 = Utf8               Lscala/math/BigInt;
   #14 = Utf8               minCached
   #15 = Utf8               I
   #16 = Utf8               maxCached
   #17 = Utf8               cache
   #18 = Utf8               [Lscala/math/BigInt;
   #19 = Utf8               scala$math$BigInt$$minusOne
   #20 = Utf8               <clinit>
   #21 = Utf8               ()V
   #22 = Utf8               <init>
   #23 = NameAndType        #22:#21       // "<init>":()V
   #24 = Methodref          #2.#23        // scala/math/BigInt$."<init>":()V
   #25 = NameAndType        #8:#9         // MODULE$:Lscala/math/BigInt$;
   #26 = Fieldref           #2.#25        // scala/math/BigInt$.MODULE$:Lscala/math/BigInt$;
   #27 = Long               -9223372036854775808l
   #29 = Utf8               java/math/BigInteger
   #30 = Class              #29           // java/math/BigInteger
   #31 = Utf8               valueOf
   #32 = Utf8               (J)Ljava/math/BigInteger;
   #33 = NameAndType        #31:#32       // valueOf:(J)Ljava/math/BigInteger;
   #34 = Methodref          #30.#33       // java/math/BigInteger.valueOf:(J)Ljava/math/BigInteger;
   #35 = NameAndType        #10:#11       // scala$math$BigInt$$longMinValueBigInteger:Ljava/math/BigInteger;
   #36 = Fieldref           #2.#35        // scala/math/BigInt$.scala$math$BigInt$$longMinValueBigInteger:Ljava/math/BigInteger;
   #37 = Utf8               scala/math/BigInt
   #38 = Class              #37           // scala/math/BigInt
   #39 = Utf8               ()Ljava/math/BigInteger;
   #40 = NameAndType        #10:#39       // scala$math$BigInt$$longMinValueBigInteger:()Ljava/math/BigInteger;
   #41 = Methodref          #2.#40        // scala/math/BigInt$.scala$math$BigInt$$longMinValueBigInteger:()Ljava/math/BigInteger;
   #42 = Utf8               (Ljava/math/BigInteger;J)V
   #43 = NameAndType        #22:#42       // "<init>":(Ljava/math/BigInteger;J)V
   #44 = Methodref          #38.#43       // scala/math/BigInt."<init>":(Ljava/math/BigInteger;J)V
   #45 = NameAndType        #12:#13       // longMinValue:Lscala/math/BigInt;
   #46 = Fieldref           #2.#45        // scala/math/BigInt$.longMinValue:Lscala/math/BigInt;
   #47 = NameAndType        #14:#15       // minCached:I
   #48 = Fieldref           #2.#47        // scala/math/BigInt$.minCached:I
   #49 = NameAndType        #16:#15       // maxCached:I
   #50 = Fieldref           #2.#49        // scala/math/BigInt$.maxCached:I
   #51 = NameAndType        #17:#18       // cache:[Lscala/math/BigInt;
   #52 = Fieldref           #2.#51        // scala/math/BigInt$.cache:[Lscala/math/BigInt;
   #53 = Long               -1l
   #55 = NameAndType        #19:#11       // scala$math$BigInt$$minusOne:Ljava/math/BigInteger;
   #56 = Fieldref           #2.#55        // scala/math/BigInt$.scala$math$BigInt$$minusOne:Ljava/math/BigInteger;
   #57 = Utf8               this
   #58 = Utf8               ()Lscala/math/BigInt;
   #59 = Utf8               getCached
   #60 = Utf8               (I)Lscala/math/BigInt;
   #61 = Utf8               i
   #62 = Utf8               offset
   #63 = Utf8               n
   #64 = Utf8               apply
   #65 = NameAndType        #59:#60       // getCached:(I)Lscala/math/BigInt;
   #66 = Methodref          #2.#65        // scala/math/BigInt$.getCached:(I)Lscala/math/BigInt;
   #67 = Utf8               (J)Lscala/math/BigInt;
   #68 = NameAndType        #64:#67       // apply:(J)Lscala/math/BigInt;
   #69 = Methodref          #2.#68        // scala/math/BigInt$.apply:(J)Lscala/math/BigInt;
   #70 = Utf8               l
   #71 = NameAndType        #12:#58       // longMinValue:()Lscala/math/BigInt;
   #72 = Methodref          #2.#71        // scala/math/BigInt$.longMinValue:()Lscala/math/BigInt;
   #73 = Utf8               J
   #74 = Utf8               ([B)Lscala/math/BigInt;
   #75 = Utf8               x
   #76 = Utf8               ([B)V
   #77 = NameAndType        #22:#76       // "<init>":([B)V
   #78 = Methodref          #30.#77       // java/math/BigInteger."<init>":([B)V
   #79 = Utf8               (Ljava/math/BigInteger;)Lscala/math/BigInt;
   #80 = NameAndType        #64:#79       // apply:(Ljava/math/BigInteger;)Lscala/math/BigInt;
   #81 = Methodref          #2.#80        // scala/math/BigInt$.apply:(Ljava/math/BigInteger;)Lscala/math/BigInt;
   #82 = Utf8               [B
   #83 = Utf8               (I[B)Lscala/math/BigInt;
   #84 = Utf8               signum
   #85 = Utf8               magnitude
   #86 = Utf8               (I[B)V
   #87 = NameAndType        #22:#86       // "<init>":(I[B)V
   #88 = Methodref          #30.#87       // java/math/BigInteger."<init>":(I[B)V
   #89 = Utf8               (IILscala/util/Random;)Lscala/math/BigInt;
   #90 = Utf8               bitlength
   #91 = Utf8               certainty
   #92 = Utf8               rnd
   #93 = Utf8               scala/util/Random
   #94 = Class              #93           // scala/util/Random
   #95 = Utf8               self
   #96 = Utf8               ()Ljava/util/Random;
   #97 = NameAndType        #95:#96       // self:()Ljava/util/Random;
   #98 = Methodref          #94.#97       // scala/util/Random.self:()Ljava/util/Random;
   #99 = Utf8               (IILjava/util/Random;)V
  #100 = NameAndType        #22:#99       // "<init>":(IILjava/util/Random;)V
  #101 = Methodref          #30.#100      // java/math/BigInteger."<init>":(IILjava/util/Random;)V
  #102 = Utf8               Lscala/util/Random;
  #103 = Utf8               (ILscala/util/Random;)Lscala/math/BigInt;
  #104 = Utf8               numbits
  #105 = Utf8               (ILjava/util/Random;)V
  #106 = NameAndType        #22:#105      // "<init>":(ILjava/util/Random;)V
  #107 = Methodref          #30.#106      // java/math/BigInteger."<init>":(ILjava/util/Random;)V
  #108 = Utf8               (Ljava/lang/String;)Lscala/math/BigInt;
  #109 = Utf8               (Ljava/lang/String;)V
  #110 = NameAndType        #22:#109      // "<init>":(Ljava/lang/String;)V
  #111 = Methodref          #30.#110      // java/math/BigInteger."<init>":(Ljava/lang/String;)V
  #112 = Utf8               Ljava/lang/String;
  #113 = Utf8               (Ljava/lang/String;I)Lscala/math/BigInt;
  #114 = Utf8               radix
  #115 = Utf8               (Ljava/lang/String;I)V
  #116 = NameAndType        #22:#115      // "<init>":(Ljava/lang/String;I)V
  #117 = Methodref          #30.#116      // java/math/BigInteger."<init>":(Ljava/lang/String;I)V
  #118 = Utf8               bitLength
  #119 = Utf8               ()I
  #120 = NameAndType        #118:#119     // bitLength:()I
  #121 = Methodref          #30.#120      // java/math/BigInteger.bitLength:()I
  #122 = Utf8               longValue
  #123 = Utf8               ()J
  #124 = NameAndType        #122:#123     // longValue:()J
  #125 = Methodref          #30.#124      // java/math/BigInteger.longValue:()J
  #126 = Utf8               probablePrime
  #127 = Utf8               (ILjava/util/Random;)Ljava/math/BigInteger;
  #128 = NameAndType        #126:#127     // probablePrime:(ILjava/util/Random;)Ljava/math/BigInteger;
  #129 = Methodref          #30.#128      // java/math/BigInteger.probablePrime:(ILjava/util/Random;)Ljava/math/BigInteger;
  #130 = Utf8               int2bigInt
  #131 = NameAndType        #64:#60       // apply:(I)Lscala/math/BigInt;
  #132 = Methodref          #2.#131       // scala/math/BigInt$.apply:(I)Lscala/math/BigInt;
  #133 = Utf8               long2bigInt
  #134 = Utf8               javaBigInteger2bigInt
  #135 = Utf8               scala$math$BigInt$$longGcd
  #136 = Utf8               (JJ)J
  #137 = Utf8               a
  #138 = Utf8               b
  #139 = Utf8               java/lang/Long
  #140 = Class              #139          // java/lang/Long
  #141 = Utf8               numberOfTrailingZeros
  #142 = Utf8               (J)I
  #143 = NameAndType        #141:#142     // numberOfTrailingZeros:(J)I
  #144 = Methodref          #140.#143     // java/lang/Long.numberOfTrailingZeros:(J)I
  #145 = Utf8               scala/math/package$
  #146 = Class              #145          // scala/math/package$
  #147 = Utf8               Lscala/math/package$;
  #148 = NameAndType        #8:#147       // MODULE$:Lscala/math/package$;
  #149 = Fieldref           #146.#148     // scala/math/package$.MODULE$:Lscala/math/package$;
  #150 = Utf8               java/lang/Math
  #151 = Class              #150          // java/lang/Math
  #152 = Utf8               min
  #153 = Utf8               (II)I
  #154 = NameAndType        #152:#153     // min:(II)I
  #155 = Methodref          #151.#154     // java/lang/Math.min:(II)I
  #156 = Utf8               delta
  #157 = Utf8               minDeltaOrZero
  #158 = Utf8               aTwos
  #159 = Utf8               a1
  #160 = Utf8               bTwos
  #161 = Utf8               b1
  #162 = Utf8               writeReplace
  #163 = Utf8               ()Ljava/lang/Object;
  #164 = Utf8               scala/runtime/ModuleSerializationProxy
  #165 = Class              #164          // scala/runtime/ModuleSerializationProxy
  #166 = Utf8               (Ljava/lang/Class;)V
  #167 = NameAndType        #22:#166      // "<init>":(Ljava/lang/Class;)V
  #168 = Methodref          #165.#167     // scala/runtime/ModuleSerializationProxy."<init>":(Ljava/lang/Class;)V
  #169 = Methodref          #4.#23        // java/lang/Object."<init>":()V
  #170 = Utf8               Code
  #171 = Utf8               LineNumberTable
  #172 = Utf8               LocalVariableTable
  #173 = Utf8               StackMapTable
  #174 = Utf8               MethodParameters
  #175 = Utf8               SourceFile
  #176 = Utf8               ScalaInlineInfo
  #177 = Utf8               Scala
{
  public static final scala.math.BigInt$ MODULE$;
    descriptor: Lscala/math/BigInt$;
    flags: (0x0019) ACC_PUBLIC, ACC_STATIC, ACC_FINAL

  private static final java.math.BigInteger scala$math$BigInt$$longMinValueBigInteger;
    descriptor: Ljava/math/BigInteger;
    flags: (0x001a) ACC_PRIVATE, ACC_STATIC, ACC_FINAL

  private static final scala.math.BigInt longMinValue;
    descriptor: Lscala/math/BigInt;
    flags: (0x001a) ACC_PRIVATE, ACC_STATIC, ACC_FINAL

  private static final int minCached;
    descriptor: I
    flags: (0x001a) ACC_PRIVATE, ACC_STATIC, ACC_FINAL

  private static final int maxCached;
    descriptor: I
    flags: (0x001a) ACC_PRIVATE, ACC_STATIC, ACC_FINAL

  private static final scala.math.BigInt[] cache;
    descriptor: [Lscala/math/BigInt;
    flags: (0x001a) ACC_PRIVATE, ACC_STATIC, ACC_FINAL

  private static final java.math.BigInteger scala$math$BigInt$$minusOne;
    descriptor: Ljava/math/BigInteger;
    flags: (0x001a) ACC_PRIVATE, ACC_STATIC, ACC_FINAL

  public static {};
    descriptor: ()V
    flags: (0x0009) ACC_PUBLIC, ACC_STATIC
    Code:
      stack=5, locals=0, args_size=0
         0: new           #2                  // class scala/math/BigInt$
         3: dup
         4: invokespecial #24                 // Method "<init>":()V
         7: putstatic     #26                 // Field MODULE$:Lscala/math/BigInt$;
        10: ldc2_w        #27                 // long -9223372036854775808l
        13: invokestatic  #34                 // Method java/math/BigInteger.valueOf:(J)Ljava/math/BigInteger;
        16: putstatic     #36                 // Field scala$math$BigInt$$longMinValueBigInteger:Ljava/math/BigInteger;
        19: new           #38                 // class scala/math/BigInt
        22: dup
        23: getstatic     #26                 // Field MODULE$:Lscala/math/BigInt$;
        26: invokevirtual #41                 // Method scala$math$BigInt$$longMinValueBigInteger:()Ljava/math/BigInteger;
        29: ldc2_w        #27                 // long -9223372036854775808l
        32: invokespecial #44                 // Method scala/math/BigInt."<init>":(Ljava/math/BigInteger;J)V
        35: putstatic     #46                 // Field longMinValue:Lscala/math/BigInt;
        38: sipush        -1024
        41: putstatic     #48                 // Field minCached:I
        44: sipush        1024
        47: putstatic     #50                 // Field maxCached:I
        50: getstatic     #50                 // Field maxCached:I
        53: getstatic     #48                 // Field minCached:I
        56: isub
        57: iconst_1
        58: iadd
        59: anewarray     #38                 // class scala/math/BigInt
        62: putstatic     #52                 // Field cache:[Lscala/math/BigInt;
        65: ldc2_w        #53                 // long -1l
        68: invokestatic  #34                 // Method java/math/BigInteger.valueOf:(J)Ljava/math/BigInteger;
        71: putstatic     #56                 // Field scala$math$BigInt$$minusOne:Ljava/math/BigInteger;
        74: return
      LineNumberTable:
        line 22: 0
        line 24: 10
        line 25: 19
        line 27: 38
        line 28: 44
        line 29: 50
        line 41: 65
        line 22: 74

  public java.math.BigInteger scala$math$BigInt$$longMinValueBigInteger();
    descriptor: ()Ljava/math/BigInteger;
    flags: (0x0001) ACC_PUBLIC
    Code:
      stack=1, locals=1, args_size=1
         0: getstatic     #36                 // Field scala$math$BigInt$$longMinValueBigInteger:Ljava/math/BigInteger;
         3: areturn
      LineNumberTable:
        line 24: 0
      LocalVariableTable:
        Start  Length  Slot  Name   Signature
            0       4     0  this   Lscala/math/BigInt$;

  private scala.math.BigInt longMinValue();
    descriptor: ()Lscala/math/BigInt;
    flags: (0x0002) ACC_PRIVATE
    Code:
      stack=1, locals=1, args_size=1
         0: getstatic     #46                 // Field longMinValue:Lscala/math/BigInt;
         3: areturn
      LineNumberTable:
        line 25: 0
      LocalVariableTable:
        Start  Length  Slot  Name   Signature
            0       4     0  this   Lscala/math/BigInt$;

  private scala.math.BigInt getCached(int);
    descriptor: (I)Lscala/math/BigInt;
    flags: (0x0002) ACC_PRIVATE
    Code:
      stack=5, locals=4, args_size=2
         0: iload_1
         1: getstatic     #48                 // Field minCached:I
         4: isub
         5: istore_2
         6: getstatic     #52                 // Field cache:[Lscala/math/BigInt;
         9: iload_2
        10: aaload
        11: astore_3
        12: aload_3
        13: ifnonnull     33
        16: new           #38                 // class scala/math/BigInt
        19: dup
        20: aconst_null
        21: iload_1
        22: i2l
        23: invokespecial #44                 // Method scala/math/BigInt."<init>":(Ljava/math/BigInteger;J)V
        26: astore_3
        27: getstatic     #52                 // Field cache:[Lscala/math/BigInt;
        30: iload_2
        31: aload_3
        32: aastore
        33: aload_3
        34: areturn
      StackMapTable: number_of_entries = 1
        frame_type = 253 /* append */
          offset_delta = 33
          locals = [ int, class scala/math/BigInt ]
      LineNumberTable:
        line 32: 0
        line 33: 6
        line 34: 12
        line 35: 16
        line 36: 27
        line 38: 33
      LocalVariableTable:
        Start  Length  Slot  Name   Signature
            6      28     2 offset   I
           12      22     3     n   Lscala/math/BigInt;
            0      35     0  this   Lscala/math/BigInt$;
            0      35     1     i   I
    MethodParameters:
      Name                           Flags
      i                              final

  public java.math.BigInteger scala$math$BigInt$$minusOne();
    descriptor: ()Ljava/math/BigInteger;
    flags: (0x0001) ACC_PUBLIC
    Code:
      stack=1, locals=1, args_size=1
         0: getstatic     #56                 // Field scala$math$BigInt$$minusOne:Ljava/math/BigInteger;
         3: areturn
      LineNumberTable:
        line 41: 0
      LocalVariableTable:
        Start  Length  Slot  Name   Signature
            0       4     0  this   Lscala/math/BigInt$;

  public scala.math.BigInt apply(int);
    descriptor: (I)Lscala/math/BigInt;
    flags: (0x0001) ACC_PUBLIC
    Code:
      stack=3, locals=2, args_size=2
         0: getstatic     #48                 // Field minCached:I
         3: iload_1
         4: if_icmpgt     20
         7: iload_1
         8: getstatic     #50                 // Field maxCached:I
        11: if_icmpgt     20
        14: aload_0
        15: iload_1
        16: invokespecial #66                 // Method getCached:(I)Lscala/math/BigInt;
        19: areturn
        20: aload_0
        21: iload_1
        22: i2l
        23: invokevirtual #69                 // Method apply:(J)Lscala/math/BigInt;
        26: areturn
      StackMapTable: number_of_entries = 1
        frame_type = 20 /* same */
      LineNumberTable:
        line 50: 0
      LocalVariableTable:
        Start  Length  Slot  Name   Signature
            0      27     0  this   Lscala/math/BigInt$;
            0      27     1     i   I
    MethodParameters:
      Name                           Flags
      i                              final

  public scala.math.BigInt apply(long);
    descriptor: (J)Lscala/math/BigInt;
    flags: (0x0001) ACC_PUBLIC
    Code:
      stack=5, locals=3, args_size=2
         0: getstatic     #48                 // Field minCached:I
         3: i2l
         4: lload_1
         5: lcmp
         6: ifgt          25
         9: lload_1
        10: getstatic     #50                 // Field maxCached:I
        13: i2l
        14: lcmp
        15: ifgt          25
        18: aload_0
        19: lload_1
        20: l2i
        21: invokespecial #66                 // Method getCached:(I)Lscala/math/BigInt;
        24: areturn
        25: lload_1
        26: ldc2_w        #27                 // long -9223372036854775808l
        29: lcmp
        30: ifne          38
        33: aload_0
        34: invokespecial #72                 // Method longMinValue:()Lscala/math/BigInt;
        37: areturn
        38: new           #38                 // class scala/math/BigInt
        41: dup
        42: aconst_null
        43: lload_1
        44: invokespecial #44                 // Method scala/math/BigInt."<init>":(Ljava/math/BigInteger;J)V
        47: areturn
      StackMapTable: number_of_entries = 2
        frame_type = 25 /* same */
        frame_type = 12 /* same */
      LineNumberTable:
        line 59: 0
        line 60: 25
      LocalVariableTable:
        Start  Length  Slot  Name   Signature
            0      48     0  this   Lscala/math/BigInt$;
            0      48     1     l   J
    MethodParameters:
      Name                           Flags
      l                              final

  public scala.math.BigInt apply(byte[]);
    descriptor: ([B)Lscala/math/BigInt;
    flags: (0x0001) ACC_PUBLIC
    Code:
      stack=4, locals=2, args_size=2
         0: aload_0
         1: new           #30                 // class java/math/BigInteger
         4: dup
         5: aload_1
         6: invokespecial #78                 // Method java/math/BigInteger."<init>":([B)V
         9: invokevirtual #81                 // Method apply:(Ljava/math/BigInteger;)Lscala/math/BigInt;
        12: areturn
      LineNumberTable:
        line 67: 0
      LocalVariableTable:
        Start  Length  Slot  Name   Signature
            0      13     0  this   Lscala/math/BigInt$;
            0      13     1     x   [B
    MethodParameters:
      Name                           Flags
      x                              final

  public scala.math.BigInt apply(int, byte[]);
    descriptor: (I[B)Lscala/math/BigInt;
    flags: (0x0001) ACC_PUBLIC
    Code:
      stack=5, locals=3, args_size=3
         0: aload_0
         1: new           #30                 // class java/math/BigInteger
         4: dup
         5: iload_1
         6: aload_2
         7: invokespecial #88                 // Method java/math/BigInteger."<init>":(I[B)V
        10: invokevirtual #81                 // Method apply:(Ljava/math/BigInteger;)Lscala/math/BigInt;
        13: areturn
      LineNumberTable:
        line 77: 0
      LocalVariableTable:
        Start  Length  Slot  Name   Signature
            0      14     0  this   Lscala/math/BigInt$;
            0      14     1 signum   I
            0      14     2 magnitude   [B
    MethodParameters:
      Name                           Flags
      signum                         final
      magnitude                      final

  public scala.math.BigInt apply(int, int, scala.util.Random);
    descriptor: (IILscala/util/Random;)Lscala/math/BigInt;
    flags: (0x0001) ACC_PUBLIC
    Code:
      stack=6, locals=4, args_size=4
         0: aload_0
         1: new           #30                 // class java/math/BigInteger
         4: dup
         5: iload_1
         6: iload_2
         7: aload_3
         8: invokevirtual #98                 // Method scala/util/Random.self:()Ljava/util/Random;
        11: invokespecial #101                // Method java/math/BigInteger."<init>":(IILjava/util/Random;)V
        14: invokevirtual #81                 // Method apply:(Ljava/math/BigInteger;)Lscala/math/BigInt;
        17: areturn
      LineNumberTable:
        line 83: 0
      LocalVariableTable:
        Start  Length  Slot  Name   Signature
            0      18     0  this   Lscala/math/BigInt$;
            0      18     1 bitlength   I
            0      18     2 certainty   I
            0      18     3   rnd   Lscala/util/Random;
    MethodParameters:
      Name                           Flags
      bitlength                      final
      certainty                      final
      rnd                            final

  public scala.math.BigInt apply(int, scala.util.Random);
    descriptor: (ILscala/util/Random;)Lscala/math/BigInt;
    flags: (0x0001) ACC_PUBLIC
    Code:
      stack=5, locals=3, args_size=3
         0: aload_0
         1: new           #30                 // class java/math/BigInteger
         4: dup
         5: iload_1
         6: aload_2
         7: invokevirtual #98                 // Method scala/util/Random.self:()Ljava/util/Random;
        10: invokespecial #107                // Method java/math/BigInteger."<init>":(ILjava/util/Random;)V
        13: invokevirtual #81                 // Method apply:(Ljava/math/BigInteger;)Lscala/math/BigInt;
        16: areturn
      LineNumberTable:
        line 89: 0
      LocalVariableTable:
        Start  Length  Slot  Name   Signature
            0      17     0  this   Lscala/math/BigInt$;
            0      17     1 numbits   I
            0      17     2   rnd   Lscala/util/Random;
    MethodParameters:
      Name                           Flags
      numbits                        final
      rnd                            final

  public scala.math.BigInt apply(java.lang.String);
    descriptor: (Ljava/lang/String;)Lscala/math/BigInt;
    flags: (0x0001) ACC_PUBLIC
    Code:
      stack=4, locals=2, args_size=2
         0: aload_0
         1: new           #30                 // class java/math/BigInteger
         4: dup
         5: aload_1
         6: invokespecial #111                // Method java/math/BigInteger."<init>":(Ljava/lang/String;)V
         9: invokevirtual #81                 // Method apply:(Ljava/math/BigInteger;)Lscala/math/BigInt;
        12: areturn
      LineNumberTable:
        line 94: 0
      LocalVariableTable:
        Start  Length  Slot  Name   Signature
            0      13     0  this   Lscala/math/BigInt$;
            0      13     1     x   Ljava/lang/String;
    MethodParameters:
      Name                           Flags
      x                              final

  public scala.math.BigInt apply(java.lang.String, int);
    descriptor: (Ljava/lang/String;I)Lscala/math/BigInt;
    flags: (0x0001) ACC_PUBLIC
    Code:
      stack=5, locals=3, args_size=3
         0: aload_0
         1: new           #30                 // class java/math/BigInteger
         4: dup
         5: aload_1
         6: iload_2
         7: invokespecial #117                // Method java/math/BigInteger."<init>":(Ljava/lang/String;I)V
        10: invokevirtual #81                 // Method apply:(Ljava/math/BigInteger;)Lscala/math/BigInt;
        13: areturn
      LineNumberTable:
        line 100: 0
      LocalVariableTable:
        Start  Length  Slot  Name   Signature
            0      14     0  this   Lscala/math/BigInt$;
            0      14     1     x   Ljava/lang/String;
            0      14     2 radix   I
    MethodParameters:
      Name                           Flags
      x                              final
      radix                          final

  public scala.math.BigInt apply(java.math.BigInteger);
    descriptor: (Ljava/math/BigInteger;)Lscala/math/BigInt;
    flags: (0x0001) ACC_PUBLIC
    Code:
      stack=5, locals=4, args_size=2
         0: aload_1
         1: invokevirtual #121                // Method java/math/BigInteger.bitLength:()I
         4: bipush        63
         6: if_icmpgt     49
         9: aload_1
        10: invokevirtual #125                // Method java/math/BigInteger.longValue:()J
        13: lstore_2
        14: getstatic     #48                 // Field minCached:I
        17: i2l
        18: lload_2
        19: lcmp
        20: ifgt          39
        23: lload_2
        24: getstatic     #50                 // Field maxCached:I
        27: i2l
        28: lcmp
        29: ifgt          39
        32: aload_0
        33: lload_2
        34: l2i
        35: invokespecial #66                 // Method getCached:(I)Lscala/math/BigInt;
        38: areturn
        39: new           #38                 // class scala/math/BigInt
        42: dup
        43: aload_1
        44: lload_2
        45: invokespecial #44                 // Method scala/math/BigInt."<init>":(Ljava/math/BigInteger;J)V
        48: areturn
        49: new           #38                 // class scala/math/BigInt
        52: dup
        53: aload_1
        54: ldc2_w        #27                 // long -9223372036854775808l
        57: invokespecial #44                 // Method scala/math/BigInt."<init>":(Ljava/math/BigInteger;J)V
        60: areturn
      StackMapTable: number_of_entries = 2
        frame_type = 252 /* append */
          offset_delta = 39
          locals = [ long ]
        frame_type = 250 /* chop */
          offset_delta = 9
      LineNumberTable:
        line 105: 0
        line 106: 9
        line 107: 14
        line 108: 49
      LocalVariableTable:
        Start  Length  Slot  Name   Signature
           14      34     2     l   J
            0      61     0  this   Lscala/math/BigInt$;
            0      61     1     x   Ljava/math/BigInteger;
    MethodParameters:
      Name                           Flags
      x                              final

  public scala.math.BigInt probablePrime(int, scala.util.Random);
    descriptor: (ILscala/util/Random;)Lscala/math/BigInt;
    flags: (0x0001) ACC_PUBLIC
    Code:
      stack=3, locals=3, args_size=3
         0: aload_0
         1: iload_1
         2: aload_2
         3: invokevirtual #98                 // Method scala/util/Random.self:()Ljava/util/Random;
         6: invokestatic  #129                // Method java/math/BigInteger.probablePrime:(ILjava/util/Random;)Ljava/math/BigInteger;
         9: invokevirtual #81                 // Method apply:(Ljava/math/BigInteger;)Lscala/math/BigInt;
        12: areturn
      LineNumberTable:
        line 114: 0
      LocalVariableTable:
        Start  Length  Slot  Name   Signature
            0      13     0  this   Lscala/math/BigInt$;
            0      13     1 bitLength   I
            0      13     2   rnd   Lscala/util/Random;
    MethodParameters:
      Name                           Flags
      bitLength                      final
      rnd                            final

  public scala.math.BigInt int2bigInt(int);
    descriptor: (I)Lscala/math/BigInt;
    flags: (0x0001) ACC_PUBLIC
    Code:
      stack=2, locals=2, args_size=2
         0: aload_0
         1: iload_1
         2: invokevirtual #132                // Method apply:(I)Lscala/math/BigInt;
         5: areturn
      LineNumberTable:
        line 118: 0
      LocalVariableTable:
        Start  Length  Slot  Name   Signature
            0       6     0  this   Lscala/math/BigInt$;
            0       6     1     i   I
    MethodParameters:
      Name                           Flags
      i                              final

  public scala.math.BigInt long2bigInt(long);
    descriptor: (J)Lscala/math/BigInt;
    flags: (0x0001) ACC_PUBLIC
    Code:
      stack=3, locals=3, args_size=2
         0: aload_0
         1: lload_1
         2: invokevirtual #69                 // Method apply:(J)Lscala/math/BigInt;
         5: areturn
      LineNumberTable:
        line 122: 0
      LocalVariableTable:
        Start  Length  Slot  Name   Signature
            0       6     0  this   Lscala/math/BigInt$;
            0       6     1     l   J
    MethodParameters:
      Name                           Flags
      l                              final

  public scala.math.BigInt javaBigInteger2bigInt(java.math.BigInteger);
    descriptor: (Ljava/math/BigInteger;)Lscala/math/BigInt;
    flags: (0x0001) ACC_PUBLIC
    Code:
      stack=2, locals=2, args_size=2
         0: aload_0
         1: aload_1
         2: invokevirtual #81                 // Method apply:(Ljava/math/BigInteger;)Lscala/math/BigInt;
         5: areturn
      LineNumberTable:
        line 126: 0
      LocalVariableTable:
        Start  Length  Slot  Name   Signature
            0       6     0  this   Lscala/math/BigInt$;
            0       6     1     x   Ljava/math/BigInteger;
    MethodParameters:
      Name                           Flags
      x                              final

  public long scala$math$BigInt$$longGcd(long, long);
    descriptor: (JJ)J
    flags: (0x0001) ACC_PUBLIC
    Code:
      stack=5, locals=15, args_size=3
         0: lload_1
         1: lconst_0
         2: lcmp
         3: ifne          8
         6: lload_3
         7: lreturn
         8: lload_3
         9: lconst_0
        10: lcmp
        11: ifne          16
        14: lload_1
        15: lreturn
        16: lload_1
        17: invokestatic  #144                // Method java/lang/Long.numberOfTrailingZeros:(J)I
        20: istore        5
        22: lload_1
        23: iload         5
        25: lshr
        26: lstore        6
        28: lload_3
        29: invokestatic  #144                // Method java/lang/Long.numberOfTrailingZeros:(J)I
        32: istore        8
        34: lload_3
        35: iload         8
        37: lshr
        38: lstore        9
        40: lload         6
        42: lload         9
        44: lcmp
        45: ifeq          95
        48: lload         6
        50: lload         9
        52: lsub
        53: lstore        11
        55: lload         11
        57: lload         11
        59: bipush        63
        61: lshr
        62: land
        63: lstore        13
        65: lload         11
        67: lload         13
        69: lsub
        70: lload         13
        72: lsub
        73: lstore        6
        75: lload         9
        77: lload         13
        79: ladd
        80: lstore        9
        82: lload         6
        84: lload         6
        86: invokestatic  #144                // Method java/lang/Long.numberOfTrailingZeros:(J)I
        89: lshr
        90: lstore        6
        92: goto          40
        95: lload         6
        97: getstatic     #149                // Field scala/math/package$.MODULE$:Lscala/math/package$;
       100: pop
       101: iload         5
       103: iload         8
       105: invokestatic  #155                // Method java/lang/Math.min:(II)I
       108: lshl
       109: lreturn
      StackMapTable: number_of_entries = 4
        frame_type = 8 /* same */
        frame_type = 7 /* same */
        frame_type = 255 /* full_frame */
          offset_delta = 23
          locals = [ class scala/math/BigInt$, long, long, int, long, int, long ]
          stack = []
        frame_type = 54 /* same */
      LineNumberTable:
        line 139: 0
        line 141: 6
        line 143: 8
        line 148: 16
        line 149: 22
        line 151: 28
        line 152: 34
        line 153: 40
        line 159: 48
        line 160: 55
        line 162: 65
        line 165: 75
        line 167: 82
        line 153: 92
        line 170: 95
      LocalVariableTable:
        Start  Length  Slot  Name   Signature
           55      37    11 delta   J
           65      27    13 minDeltaOrZero   J
           22      87     5 aTwos   I
           28      81     6    a1   J
           34      75     8 bTwos   I
           40      69     9    b1   J
            0     110     0  this   Lscala/math/BigInt$;
            0     110     1     a   J
            0     110     3     b   J
    MethodParameters:
      Name                           Flags
      a                              final
      b                              final

  private java.lang.Object writeReplace();
    descriptor: ()Ljava/lang/Object;
    flags: (0x0002) ACC_PRIVATE
    Code:
      stack=3, locals=1, args_size=1
         0: new           #165                // class scala/runtime/ModuleSerializationProxy
         3: dup
         4: ldc           #2                  // class scala/math/BigInt$
         6: invokespecial #168                // Method scala/runtime/ModuleSerializationProxy."<init>":(Ljava/lang/Class;)V
         9: areturn
      LineNumberTable:
        line 22: 0
      LocalVariableTable:
        Start  Length  Slot  Name   Signature
            0      10     0  this   Lscala/math/BigInt$;

  private scala.math.BigInt$();
    descriptor: ()V
    flags: (0x0002) ACC_PRIVATE
    Code:
      stack=1, locals=1, args_size=1
         0: aload_0
         1: invokespecial #169                // Method java/lang/Object."<init>":()V
         4: return
      LineNumberTable:
        line 22: 0
      LocalVariableTable:
        Start  Length  Slot  Name   Signature
            0       5     0  this   Lscala/math/BigInt$;
}
SourceFile: "BigInt.scala"
  ScalaInlineInfo: length = 0x68 (unknown attribute)
   01 01 00 14 00 16 00 15 01 00 40 00 3C 01 00 40
   00 59 01 00 40 00 67 01 00 40 00 53 01 00 40 00
   43 01 00 40 00 6C 01 00 40 00 71 01 00 40 00 4F
   01 00 40 00 4A 01 00 3B 00 3C 01 00 82 00 3C 01
   00 86 00 4F 01 00 85 00 43 01 00 0C 00 3A 01 00
   7E 00 67 01 00 87 00 88 01 00 0A 00 27 01 00 13
   00 27 01 00 A2 00 A3 01
  Scala: length = 0x0 (unknown attribute)

