Classfile /Users/mw/Projects/slang-braindump/.jar/jar11/assemble/slang-braindump/assemble/content/scala/math/Fractional$.class
  Last modified May 29, 2022; size 932 bytes
  SHA-256 checksum 837f969cad9d598864e1b2a093b00ae46c2399f3600bbe64be9f8b1e46c0d270
  Compiled from "Fractional.scala"
public final class scala.math.Fractional$ implements java.io.Serializable
  minor version: 0
  major version: 52
  flags: (0x0031) ACC_PUBLIC, ACC_FINAL, ACC_SUPER
  this_class: #2                          // scala/math/Fractional$
  super_class: #4                         // java/lang/Object
  interfaces: 1, fields: 1, methods: 4, attributes: 3
Constant pool:
   #1 = Utf8               scala/math/Fractional$
   #2 = Class              #1             // scala/math/Fractional$
   #3 = Utf8               java/lang/Object
   #4 = Class              #3             // java/lang/Object
   #5 = Utf8               java/io/Serializable
   #6 = Class              #5             // java/io/Serializable
   #7 = Utf8               Fractional.scala
   #8 = Utf8               MODULE$
   #9 = Utf8               Lscala/math/Fractional$;
  #10 = Utf8               <clinit>
  #11 = Utf8               ()V
  #12 = Utf8               <init>
  #13 = NameAndType        #12:#11        // "<init>":()V
  #14 = Methodref          #2.#13         // scala/math/Fractional$."<init>":()V
  #15 = NameAndType        #8:#9          // MODULE$:Lscala/math/Fractional$;
  #16 = Fieldref           #2.#15         // scala/math/Fractional$.MODULE$:Lscala/math/Fractional$;
  #17 = Utf8               apply
  #18 = Utf8               (Lscala/math/Fractional;)Lscala/math/Fractional;
  #19 = Utf8               <T:Ljava/lang/Object;>(Lscala/math/Fractional<TT;>;)Lscala/math/Fractional<TT;>;
  #20 = Utf8               frac
  #21 = Utf8               this
  #22 = Utf8               Lscala/math/Fractional;
  #23 = Utf8               writeReplace
  #24 = Utf8               ()Ljava/lang/Object;
  #25 = Utf8               scala/runtime/ModuleSerializationProxy
  #26 = Class              #25            // scala/runtime/ModuleSerializationProxy
  #27 = Utf8               (Ljava/lang/Class;)V
  #28 = NameAndType        #12:#27        // "<init>":(Ljava/lang/Class;)V
  #29 = Methodref          #26.#28        // scala/runtime/ModuleSerializationProxy."<init>":(Ljava/lang/Class;)V
  #30 = Methodref          #4.#13         // java/lang/Object."<init>":()V
  #31 = Utf8               Code
  #32 = Utf8               LineNumberTable
  #33 = Utf8               LocalVariableTable
  #34 = Utf8               Signature
  #35 = Utf8               MethodParameters
  #36 = Utf8               SourceFile
  #37 = Utf8               ScalaInlineInfo
  #38 = Utf8               Scala
{
  public static final scala.math.Fractional$ MODULE$;
    descriptor: Lscala/math/Fractional$;
    flags: (0x0019) ACC_PUBLIC, ACC_STATIC, ACC_FINAL

  public static {};
    descriptor: ()V
    flags: (0x0009) ACC_PUBLIC, ACC_STATIC
    Code:
      stack=2, locals=0, args_size=0
         0: new           #2                  // class scala/math/Fractional$
         3: dup
         4: invokespecial #14                 // Method "<init>":()V
         7: putstatic     #16                 // Field MODULE$:Lscala/math/Fractional$;
        10: return
      LineNumberTable:
        line 28: 0

  public <T extends java.lang.Object> scala.math.Fractional<T> apply(scala.math.Fractional<T>);
    descriptor: (Lscala/math/Fractional;)Lscala/math/Fractional;
    flags: (0x0001) ACC_PUBLIC
    Code:
      stack=1, locals=2, args_size=2
         0: aload_1
         1: areturn
      LineNumberTable:
        line 29: 0
      LocalVariableTable:
        Start  Length  Slot  Name   Signature
            0       2     0  this   Lscala/math/Fractional$;
            0       2     1  frac   Lscala/math/Fractional;
    Signature: #19                          // <T:Ljava/lang/Object;>(Lscala/math/Fractional<TT;>;)Lscala/math/Fractional<TT;>;
    MethodParameters:
      Name                           Flags
      frac                           final

  private java.lang.Object writeReplace();
    descriptor: ()Ljava/lang/Object;
    flags: (0x0002) ACC_PRIVATE
    Code:
      stack=3, locals=1, args_size=1
         0: new           #26                 // class scala/runtime/ModuleSerializationProxy
         3: dup
         4: ldc           #2                  // class scala/math/Fractional$
         6: invokespecial #29                 // Method scala/runtime/ModuleSerializationProxy."<init>":(Ljava/lang/Class;)V
         9: areturn
      LineNumberTable:
        line 28: 0
      LocalVariableTable:
        Start  Length  Slot  Name   Signature
            0      10     0  this   Lscala/math/Fractional$;

  private scala.math.Fractional$();
    descriptor: ()V
    flags: (0x0002) ACC_PRIVATE
    Code:
      stack=1, locals=1, args_size=1
         0: aload_0
         1: invokespecial #30                 // Method java/lang/Object."<init>":()V
         4: return
      LineNumberTable:
        line 28: 0
      LocalVariableTable:
        Start  Length  Slot  Name   Signature
            0       5     0  this   Lscala/math/Fractional$;
}
SourceFile: "Fractional.scala"
  ScalaInlineInfo: length = 0x13 (unknown attribute)
   01 01 00 03 00 0C 00 0B 01 00 11 00 12 05 00 17
   00 18 01
  Scala: length = 0x0 (unknown attribute)

