Classfile /Users/mw/Projects/slang-braindump/.jar/jar11/assemble/slang-braindump/assemble/content/scala/math/Fractional$FractionalOps.class
  Last modified May 29, 2022; size 1232 bytes
  SHA-256 checksum a8922324e1c5d707a345c469c44b3e39b7016a9efbf9f52a909ca81c15fa6e07
  Compiled from "Fractional.scala"
public class scala.math.Fractional$FractionalOps extends scala.math.Numeric<T>.NumericOps
  minor version: 0
  major version: 52
  flags: (0x0021) ACC_PUBLIC, ACC_SUPER
  this_class: #2                          // scala/math/Fractional$FractionalOps
  super_class: #5                         // scala/math/Numeric$NumericOps
  interfaces: 0, fields: 1, methods: 3, attributes: 5
Constant pool:
   #1 = Utf8               scala/math/Fractional$FractionalOps
   #2 = Class              #1             // scala/math/Fractional$FractionalOps
   #3 = Utf8               Lscala/math/Numeric<TT;>.NumericOps;
   #4 = Utf8               scala/math/Numeric$NumericOps
   #5 = Class              #4             // scala/math/Numeric$NumericOps
   #6 = Utf8               Fractional.scala
   #7 = Utf8               scala/math/Fractional
   #8 = Class              #7             // scala/math/Fractional
   #9 = Utf8               FractionalOps
  #10 = Utf8               scala/math/Numeric
  #11 = Class              #10            // scala/math/Numeric
  #12 = Utf8               NumericOps
  #13 = Utf8               lhs
  #14 = Utf8               Ljava/lang/Object;
  #15 = Utf8               TT;
  #16 = Utf8               $div
  #17 = Utf8               (Ljava/lang/Object;)Ljava/lang/Object;
  #18 = Utf8               (TT;)TT;
  #19 = Utf8               rhs
  #20 = Utf8               scala$math$Fractional$FractionalOps$$$outer
  #21 = Utf8               ()Lscala/math/Fractional;
  #22 = NameAndType        #20:#21        // scala$math$Fractional$FractionalOps$$$outer:()Lscala/math/Fractional;
  #23 = Methodref          #2.#22         // scala/math/Fractional$FractionalOps.scala$math$Fractional$FractionalOps$$$outer:()Lscala/math/Fractional;
  #24 = NameAndType        #13:#14        // lhs:Ljava/lang/Object;
  #25 = Fieldref           #2.#24         // scala/math/Fractional$FractionalOps.lhs:Ljava/lang/Object;
  #26 = Utf8               div
  #27 = Utf8               (Ljava/lang/Object;Ljava/lang/Object;)Ljava/lang/Object;
  #28 = NameAndType        #26:#27        // div:(Ljava/lang/Object;Ljava/lang/Object;)Ljava/lang/Object;
  #29 = InterfaceMethodref #8.#28         // scala/math/Fractional.div:(Ljava/lang/Object;Ljava/lang/Object;)Ljava/lang/Object;
  #30 = Utf8               this
  #31 = Utf8               Lscala/math/Fractional$FractionalOps;
  #32 = Utf8               $outer
  #33 = Utf8               Lscala/math/Numeric;
  #34 = NameAndType        #32:#33        // $outer:Lscala/math/Numeric;
  #35 = Fieldref           #2.#34         // scala/math/Fractional$FractionalOps.$outer:Lscala/math/Numeric;
  #36 = Utf8               <init>
  #37 = Utf8               (Lscala/math/Fractional;Ljava/lang/Object;)V
  #38 = Utf8               (TT;)V
  #39 = Utf8               (Lscala/math/Numeric;Ljava/lang/Object;)V
  #40 = NameAndType        #36:#39        // "<init>":(Lscala/math/Numeric;Ljava/lang/Object;)V
  #41 = Methodref          #5.#40         // scala/math/Numeric$NumericOps."<init>":(Lscala/math/Numeric;Ljava/lang/Object;)V
  #42 = Utf8               Lscala/math/Fractional;
  #43 = Utf8               Signature
  #44 = Utf8               Code
  #45 = Utf8               LineNumberTable
  #46 = Utf8               LocalVariableTable
  #47 = Utf8               MethodParameters
  #48 = Utf8               InnerClasses
  #49 = Utf8               SourceFile
  #50 = Utf8               ScalaInlineInfo
  #51 = Utf8               Scala
{
  private final T lhs;
    descriptor: Ljava/lang/Object;
    flags: (0x0012) ACC_PRIVATE, ACC_FINAL
    Signature: #15                          // TT;

  public T $div(T);
    descriptor: (Ljava/lang/Object;)Ljava/lang/Object;
    flags: (0x0001) ACC_PUBLIC
    Code:
      stack=3, locals=2, args_size=2
         0: aload_0
         1: invokevirtual #23                 // Method scala$math$Fractional$FractionalOps$$$outer:()Lscala/math/Fractional;
         4: aload_0
         5: getfield      #25                 // Field lhs:Ljava/lang/Object;
         8: aload_1
         9: invokeinterface #29,  3           // InterfaceMethod scala/math/Fractional.div:(Ljava/lang/Object;Ljava/lang/Object;)Ljava/lang/Object;
        14: areturn
      LineNumberTable:
        line 22: 0
      LocalVariableTable:
        Start  Length  Slot  Name   Signature
            0      15     0  this   Lscala/math/Fractional$FractionalOps;
            0      15     1   rhs   Ljava/lang/Object;
    Signature: #18                          // (TT;)TT;
    MethodParameters:
      Name                           Flags
      rhs                            final

  public scala.math.Fractional scala$math$Fractional$FractionalOps$$$outer();
    descriptor: ()Lscala/math/Fractional;
    flags: (0x1001) ACC_PUBLIC, ACC_SYNTHETIC
    Code:
      stack=1, locals=1, args_size=1
         0: aload_0
         1: getfield      #35                 // Field $outer:Lscala/math/Numeric;
         4: checkcast     #8                  // class scala/math/Fractional
         7: areturn
      LineNumberTable:
        line 21: 0
      LocalVariableTable:
        Start  Length  Slot  Name   Signature
            0       8     0  this   Lscala/math/Fractional$FractionalOps;

  public scala.math.Fractional$FractionalOps(T);
    descriptor: (Lscala/math/Fractional;Ljava/lang/Object;)V
    flags: (0x0001) ACC_PUBLIC
    Code:
      stack=3, locals=3, args_size=3
         0: aload_0
         1: aload_2
         2: putfield      #25                 // Field lhs:Ljava/lang/Object;
         5: aload_0
         6: aload_1
         7: aload_2
         8: invokespecial #41                 // Method scala/math/Numeric$NumericOps."<init>":(Lscala/math/Numeric;Ljava/lang/Object;)V
        11: return
      LineNumberTable:
        line 21: 0
      LocalVariableTable:
        Start  Length  Slot  Name   Signature
            0      12     0  this   Lscala/math/Fractional$FractionalOps;
            0      12     1 $outer   Lscala/math/Fractional;
            0      12     2   lhs   Ljava/lang/Object;
    Signature: #38                          // (TT;)V
    MethodParameters:
      Name                           Flags
      $outer                         final synthetic
      lhs                            final
}
InnerClasses:
  public #9= #2 of #8;                    // FractionalOps=class scala/math/Fractional$FractionalOps of class scala/math/Fractional
  public #12= #5 of #11;                  // NumericOps=class scala/math/Numeric$NumericOps of class scala/math/Numeric
Signature: #3                           // Lscala/math/Numeric<TT;>.NumericOps;
SourceFile: "Fractional.scala"
  ScalaInlineInfo: length = 0x13 (unknown attribute)
   01 00 00 03 00 10 00 11 00 00 24 00 25 00 00 14
   00 15 00
  Scala: length = 0x0 (unknown attribute)

