Classfile /Users/mw/Projects/slang-braindump/.jar/jar11/assemble/slang-braindump/assemble/content/scala/math/Numeric$NumericOps.class
  Last modified May 29, 2022; size 2293 bytes
  SHA-256 checksum 86ebf37cfd6108edd26406d014ce2a4f5ea6b3a1b166643d579573f879b74504
  Compiled from "Numeric.scala"
public class scala.math.Numeric$NumericOps
  minor version: 0
  major version: 52
  flags: (0x0021) ACC_PUBLIC, ACC_SUPER
  this_class: #2                          // scala/math/Numeric$NumericOps
  super_class: #4                         // java/lang/Object
  interfaces: 0, fields: 2, methods: 13, attributes: 4
Constant pool:
   #1 = Utf8               scala/math/Numeric$NumericOps
   #2 = Class              #1             // scala/math/Numeric$NumericOps
   #3 = Utf8               java/lang/Object
   #4 = Class              #3             // java/lang/Object
   #5 = Utf8               Numeric.scala
   #6 = Utf8               scala/math/Numeric
   #7 = Class              #6             // scala/math/Numeric
   #8 = Utf8               NumericOps
   #9 = Utf8               lhs
  #10 = Utf8               Ljava/lang/Object;
  #11 = Utf8               TT;
  #12 = Utf8               $outer
  #13 = Utf8               Lscala/math/Numeric;
  #14 = Utf8               $plus
  #15 = Utf8               (Ljava/lang/Object;)Ljava/lang/Object;
  #16 = Utf8               (TT;)TT;
  #17 = Utf8               rhs
  #18 = Utf8               scala$math$Numeric$NumericOps$$$outer
  #19 = Utf8               ()Lscala/math/Numeric;
  #20 = NameAndType        #18:#19        // scala$math$Numeric$NumericOps$$$outer:()Lscala/math/Numeric;
  #21 = Methodref          #2.#20         // scala/math/Numeric$NumericOps.scala$math$Numeric$NumericOps$$$outer:()Lscala/math/Numeric;
  #22 = NameAndType        #9:#10         // lhs:Ljava/lang/Object;
  #23 = Fieldref           #2.#22         // scala/math/Numeric$NumericOps.lhs:Ljava/lang/Object;
  #24 = Utf8               plus
  #25 = Utf8               (Ljava/lang/Object;Ljava/lang/Object;)Ljava/lang/Object;
  #26 = NameAndType        #24:#25        // plus:(Ljava/lang/Object;Ljava/lang/Object;)Ljava/lang/Object;
  #27 = InterfaceMethodref #7.#26         // scala/math/Numeric.plus:(Ljava/lang/Object;Ljava/lang/Object;)Ljava/lang/Object;
  #28 = Utf8               this
  #29 = Utf8               Lscala/math/Numeric$NumericOps;
  #30 = Utf8               $minus
  #31 = Utf8               minus
  #32 = NameAndType        #31:#25        // minus:(Ljava/lang/Object;Ljava/lang/Object;)Ljava/lang/Object;
  #33 = InterfaceMethodref #7.#32         // scala/math/Numeric.minus:(Ljava/lang/Object;Ljava/lang/Object;)Ljava/lang/Object;
  #34 = Utf8               $times
  #35 = Utf8               times
  #36 = NameAndType        #35:#25        // times:(Ljava/lang/Object;Ljava/lang/Object;)Ljava/lang/Object;
  #37 = InterfaceMethodref #7.#36         // scala/math/Numeric.times:(Ljava/lang/Object;Ljava/lang/Object;)Ljava/lang/Object;
  #38 = Utf8               unary_$minus
  #39 = Utf8               ()Ljava/lang/Object;
  #40 = Utf8               ()TT;
  #41 = Utf8               negate
  #42 = NameAndType        #41:#15        // negate:(Ljava/lang/Object;)Ljava/lang/Object;
  #43 = InterfaceMethodref #7.#42         // scala/math/Numeric.negate:(Ljava/lang/Object;)Ljava/lang/Object;
  #44 = Utf8               abs
  #45 = NameAndType        #44:#15        // abs:(Ljava/lang/Object;)Ljava/lang/Object;
  #46 = InterfaceMethodref #7.#45         // scala/math/Numeric.abs:(Ljava/lang/Object;)Ljava/lang/Object;
  #47 = Utf8               signum
  #48 = Utf8               ()I
  #49 = Utf8               (Ljava/lang/Object;)I
  #50 = NameAndType        #47:#49        // signum:(Ljava/lang/Object;)I
  #51 = InterfaceMethodref #7.#50         // scala/math/Numeric.signum:(Ljava/lang/Object;)I
  #52 = Utf8               sign
  #53 = NameAndType        #52:#15        // sign:(Ljava/lang/Object;)Ljava/lang/Object;
  #54 = InterfaceMethodref #7.#53         // scala/math/Numeric.sign:(Ljava/lang/Object;)Ljava/lang/Object;
  #55 = Utf8               toInt
  #56 = NameAndType        #55:#49        // toInt:(Ljava/lang/Object;)I
  #57 = InterfaceMethodref #7.#56         // scala/math/Numeric.toInt:(Ljava/lang/Object;)I
  #58 = Utf8               toLong
  #59 = Utf8               ()J
  #60 = Utf8               (Ljava/lang/Object;)J
  #61 = NameAndType        #58:#60        // toLong:(Ljava/lang/Object;)J
  #62 = InterfaceMethodref #7.#61         // scala/math/Numeric.toLong:(Ljava/lang/Object;)J
  #63 = Utf8               toFloat
  #64 = Utf8               ()F
  #65 = Utf8               (Ljava/lang/Object;)F
  #66 = NameAndType        #63:#65        // toFloat:(Ljava/lang/Object;)F
  #67 = InterfaceMethodref #7.#66         // scala/math/Numeric.toFloat:(Ljava/lang/Object;)F
  #68 = Utf8               toDouble
  #69 = Utf8               ()D
  #70 = Utf8               (Ljava/lang/Object;)D
  #71 = NameAndType        #68:#70        // toDouble:(Ljava/lang/Object;)D
  #72 = InterfaceMethodref #7.#71         // scala/math/Numeric.toDouble:(Ljava/lang/Object;)D
  #73 = NameAndType        #12:#13        // $outer:Lscala/math/Numeric;
  #74 = Fieldref           #2.#73         // scala/math/Numeric$NumericOps.$outer:Lscala/math/Numeric;
  #75 = Utf8               <init>
  #76 = Utf8               (Lscala/math/Numeric;Ljava/lang/Object;)V
  #77 = Utf8               (TT;)V
  #78 = Utf8               ()V
  #79 = NameAndType        #75:#78        // "<init>":()V
  #80 = Methodref          #4.#79         // java/lang/Object."<init>":()V
  #81 = Utf8               Signature
  #82 = Utf8               Code
  #83 = Utf8               LineNumberTable
  #84 = Utf8               LocalVariableTable
  #85 = Utf8               MethodParameters
  #86 = Utf8               Deprecated
  #87 = Utf8               StackMapTable
  #88 = Utf8               InnerClasses
  #89 = Utf8               SourceFile
  #90 = Utf8               ScalaInlineInfo
  #91 = Utf8               Scala
{
  private final T lhs;
    descriptor: Ljava/lang/Object;
    flags: (0x0012) ACC_PRIVATE, ACC_FINAL
    Signature: #11                          // TT;

  public final scala.math.Numeric $outer;
    descriptor: Lscala/math/Numeric;
    flags: (0x1011) ACC_PUBLIC, ACC_FINAL, ACC_SYNTHETIC

  public T $plus(T);
    descriptor: (Ljava/lang/Object;)Ljava/lang/Object;
    flags: (0x0001) ACC_PUBLIC
    Code:
      stack=3, locals=2, args_size=2
         0: aload_0
         1: invokevirtual #21                 // Method scala$math$Numeric$NumericOps$$$outer:()Lscala/math/Numeric;
         4: aload_0
         5: getfield      #23                 // Field lhs:Ljava/lang/Object;
         8: aload_1
         9: invokeinterface #27,  3           // InterfaceMethod scala/math/Numeric.plus:(Ljava/lang/Object;Ljava/lang/Object;)Ljava/lang/Object;
        14: areturn
      LineNumberTable:
        line 233: 0
      LocalVariableTable:
        Start  Length  Slot  Name   Signature
            0      15     0  this   Lscala/math/Numeric$NumericOps;
            0      15     1   rhs   Ljava/lang/Object;
    Signature: #16                          // (TT;)TT;
    MethodParameters:
      Name                           Flags
      rhs                            final

  public T $minus(T);
    descriptor: (Ljava/lang/Object;)Ljava/lang/Object;
    flags: (0x0001) ACC_PUBLIC
    Code:
      stack=3, locals=2, args_size=2
         0: aload_0
         1: invokevirtual #21                 // Method scala$math$Numeric$NumericOps$$$outer:()Lscala/math/Numeric;
         4: aload_0
         5: getfield      #23                 // Field lhs:Ljava/lang/Object;
         8: aload_1
         9: invokeinterface #33,  3           // InterfaceMethod scala/math/Numeric.minus:(Ljava/lang/Object;Ljava/lang/Object;)Ljava/lang/Object;
        14: areturn
      LineNumberTable:
        line 234: 0
      LocalVariableTable:
        Start  Length  Slot  Name   Signature
            0      15     0  this   Lscala/math/Numeric$NumericOps;
            0      15     1   rhs   Ljava/lang/Object;
    Signature: #16                          // (TT;)TT;
    MethodParameters:
      Name                           Flags
      rhs                            final

  public T $times(T);
    descriptor: (Ljava/lang/Object;)Ljava/lang/Object;
    flags: (0x0001) ACC_PUBLIC
    Code:
      stack=3, locals=2, args_size=2
         0: aload_0
         1: invokevirtual #21                 // Method scala$math$Numeric$NumericOps$$$outer:()Lscala/math/Numeric;
         4: aload_0
         5: getfield      #23                 // Field lhs:Ljava/lang/Object;
         8: aload_1
         9: invokeinterface #37,  3           // InterfaceMethod scala/math/Numeric.times:(Ljava/lang/Object;Ljava/lang/Object;)Ljava/lang/Object;
        14: areturn
      LineNumberTable:
        line 235: 0
      LocalVariableTable:
        Start  Length  Slot  Name   Signature
            0      15     0  this   Lscala/math/Numeric$NumericOps;
            0      15     1   rhs   Ljava/lang/Object;
    Signature: #16                          // (TT;)TT;
    MethodParameters:
      Name                           Flags
      rhs                            final

  public T unary_$minus();
    descriptor: ()Ljava/lang/Object;
    flags: (0x0001) ACC_PUBLIC
    Code:
      stack=2, locals=1, args_size=1
         0: aload_0
         1: invokevirtual #21                 // Method scala$math$Numeric$NumericOps$$$outer:()Lscala/math/Numeric;
         4: aload_0
         5: getfield      #23                 // Field lhs:Ljava/lang/Object;
         8: invokeinterface #43,  2           // InterfaceMethod scala/math/Numeric.negate:(Ljava/lang/Object;)Ljava/lang/Object;
        13: areturn
      LineNumberTable:
        line 236: 0
      LocalVariableTable:
        Start  Length  Slot  Name   Signature
            0      14     0  this   Lscala/math/Numeric$NumericOps;
    Signature: #40                          // ()TT;

  public T abs();
    descriptor: ()Ljava/lang/Object;
    flags: (0x0001) ACC_PUBLIC
    Code:
      stack=2, locals=1, args_size=1
         0: aload_0
         1: invokevirtual #21                 // Method scala$math$Numeric$NumericOps$$$outer:()Lscala/math/Numeric;
         4: aload_0
         5: getfield      #23                 // Field lhs:Ljava/lang/Object;
         8: invokeinterface #46,  2           // InterfaceMethod scala/math/Numeric.abs:(Ljava/lang/Object;)Ljava/lang/Object;
        13: areturn
      LineNumberTable:
        line 237: 0
      LocalVariableTable:
        Start  Length  Slot  Name   Signature
            0      14     0  this   Lscala/math/Numeric$NumericOps;
    Signature: #40                          // ()TT;

  public int signum();
    descriptor: ()I
    flags: (0x0001) ACC_PUBLIC
    Code:
      stack=2, locals=1, args_size=1
         0: aload_0
         1: invokevirtual #21                 // Method scala$math$Numeric$NumericOps$$$outer:()Lscala/math/Numeric;
         4: aload_0
         5: getfield      #23                 // Field lhs:Ljava/lang/Object;
         8: invokeinterface #51,  2           // InterfaceMethod scala/math/Numeric.signum:(Ljava/lang/Object;)I
        13: ireturn
      LineNumberTable:
        line 238: 0
      LocalVariableTable:
        Start  Length  Slot  Name   Signature
            0      14     0  this   Lscala/math/Numeric$NumericOps;
    Deprecated: true

  public T sign();
    descriptor: ()Ljava/lang/Object;
    flags: (0x0001) ACC_PUBLIC
    Code:
      stack=2, locals=1, args_size=1
         0: aload_0
         1: invokevirtual #21                 // Method scala$math$Numeric$NumericOps$$$outer:()Lscala/math/Numeric;
         4: aload_0
         5: getfield      #23                 // Field lhs:Ljava/lang/Object;
         8: invokeinterface #54,  2           // InterfaceMethod scala/math/Numeric.sign:(Ljava/lang/Object;)Ljava/lang/Object;
        13: areturn
      LineNumberTable:
        line 239: 0
      LocalVariableTable:
        Start  Length  Slot  Name   Signature
            0      14     0  this   Lscala/math/Numeric$NumericOps;
    Signature: #40                          // ()TT;

  public int toInt();
    descriptor: ()I
    flags: (0x0001) ACC_PUBLIC
    Code:
      stack=2, locals=1, args_size=1
         0: aload_0
         1: invokevirtual #21                 // Method scala$math$Numeric$NumericOps$$$outer:()Lscala/math/Numeric;
         4: aload_0
         5: getfield      #23                 // Field lhs:Ljava/lang/Object;
         8: invokeinterface #57,  2           // InterfaceMethod scala/math/Numeric.toInt:(Ljava/lang/Object;)I
        13: ireturn
      LineNumberTable:
        line 240: 0
      LocalVariableTable:
        Start  Length  Slot  Name   Signature
            0      14     0  this   Lscala/math/Numeric$NumericOps;

  public long toLong();
    descriptor: ()J
    flags: (0x0001) ACC_PUBLIC
    Code:
      stack=2, locals=1, args_size=1
         0: aload_0
         1: invokevirtual #21                 // Method scala$math$Numeric$NumericOps$$$outer:()Lscala/math/Numeric;
         4: aload_0
         5: getfield      #23                 // Field lhs:Ljava/lang/Object;
         8: invokeinterface #62,  2           // InterfaceMethod scala/math/Numeric.toLong:(Ljava/lang/Object;)J
        13: lreturn
      LineNumberTable:
        line 241: 0
      LocalVariableTable:
        Start  Length  Slot  Name   Signature
            0      14     0  this   Lscala/math/Numeric$NumericOps;

  public float toFloat();
    descriptor: ()F
    flags: (0x0001) ACC_PUBLIC
    Code:
      stack=2, locals=1, args_size=1
         0: aload_0
         1: invokevirtual #21                 // Method scala$math$Numeric$NumericOps$$$outer:()Lscala/math/Numeric;
         4: aload_0
         5: getfield      #23                 // Field lhs:Ljava/lang/Object;
         8: invokeinterface #67,  2           // InterfaceMethod scala/math/Numeric.toFloat:(Ljava/lang/Object;)F
        13: freturn
      LineNumberTable:
        line 242: 0
      LocalVariableTable:
        Start  Length  Slot  Name   Signature
            0      14     0  this   Lscala/math/Numeric$NumericOps;

  public double toDouble();
    descriptor: ()D
    flags: (0x0001) ACC_PUBLIC
    Code:
      stack=2, locals=1, args_size=1
         0: aload_0
         1: invokevirtual #21                 // Method scala$math$Numeric$NumericOps$$$outer:()Lscala/math/Numeric;
         4: aload_0
         5: getfield      #23                 // Field lhs:Ljava/lang/Object;
         8: invokeinterface #72,  2           // InterfaceMethod scala/math/Numeric.toDouble:(Ljava/lang/Object;)D
        13: dreturn
      LineNumberTable:
        line 243: 0
      LocalVariableTable:
        Start  Length  Slot  Name   Signature
            0      14     0  this   Lscala/math/Numeric$NumericOps;

  public scala.math.Numeric scala$math$Numeric$NumericOps$$$outer();
    descriptor: ()Lscala/math/Numeric;
    flags: (0x1001) ACC_PUBLIC, ACC_SYNTHETIC
    Code:
      stack=1, locals=1, args_size=1
         0: aload_0
         1: getfield      #74                 // Field $outer:Lscala/math/Numeric;
         4: areturn
      LineNumberTable:
        line 232: 0
      LocalVariableTable:
        Start  Length  Slot  Name   Signature
            0       5     0  this   Lscala/math/Numeric$NumericOps;

  public scala.math.Numeric$NumericOps(T);
    descriptor: (Lscala/math/Numeric;Ljava/lang/Object;)V
    flags: (0x0001) ACC_PUBLIC
    Code:
      stack=2, locals=3, args_size=3
         0: aload_0
         1: aload_2
         2: putfield      #23                 // Field lhs:Ljava/lang/Object;
         5: aload_1
         6: ifnonnull     11
         9: aconst_null
        10: athrow
        11: aload_0
        12: aload_1
        13: putfield      #74                 // Field $outer:Lscala/math/Numeric;
        16: aload_0
        17: invokespecial #80                 // Method java/lang/Object."<init>":()V
        20: return
      StackMapTable: number_of_entries = 1
        frame_type = 11 /* same */
      LineNumberTable:
        line 232: 0
      LocalVariableTable:
        Start  Length  Slot  Name   Signature
            0      21     0  this   Lscala/math/Numeric$NumericOps;
            0      21     1 $outer   Lscala/math/Numeric;
            0      21     2   lhs   Ljava/lang/Object;
    Signature: #77                          // (TT;)V
    MethodParameters:
      Name                           Flags
      $outer                         final synthetic
      lhs                            final
}
InnerClasses:
  public #8= #2 of #7;                    // NumericOps=class scala/math/Numeric$NumericOps of class scala/math/Numeric
SourceFile: "Numeric.scala"
  ScalaInlineInfo: length = 0x45 (unknown attribute)
   01 00 00 0D 00 1E 00 0F 00 00 0E 00 0F 00 00 22
   00 0F 00 00 4B 00 4C 00 00 2C 00 27 00 00 12 00
   13 00 00 34 00 27 00 00 2F 00 30 00 00 44 00 45
   00 00 3F 00 40 00 00 37 00 30 00 00 3A 00 3B 00
   00 26 00 27 00
  Scala: length = 0x0 (unknown attribute)

