Classfile /Users/mw/Projects/slang-braindump/.jar/jar11/assemble/slang-braindump/assemble/content/scala/math/Numeric$ExtraImplicits.class
  Last modified May 29, 2022; size 1204 bytes
  SHA-256 checksum 4bd7168503f49351e8e888b3c34ba72371ad34c980404b97c05332aa2b600d36
  Compiled from "Numeric.scala"
public interface scala.math.Numeric$ExtraImplicits
  minor version: 0
  major version: 52
  flags: (0x0601) ACC_PUBLIC, ACC_INTERFACE, ACC_ABSTRACT
  this_class: #2                          // scala/math/Numeric$ExtraImplicits
  super_class: #4                         // java/lang/Object
  interfaces: 0, fields: 0, methods: 3, attributes: 4
Constant pool:
   #1 = Utf8               scala/math/Numeric$ExtraImplicits
   #2 = Class              #1             // scala/math/Numeric$ExtraImplicits
   #3 = Utf8               java/lang/Object
   #4 = Class              #3             // java/lang/Object
   #5 = Utf8               Numeric.scala
   #6 = Utf8               scala/math/Numeric
   #7 = Class              #6             // scala/math/Numeric
   #8 = Utf8               ExtraImplicits
   #9 = Utf8               scala/math/Numeric$NumericOps
  #10 = Class              #9             // scala/math/Numeric$NumericOps
  #11 = Utf8               NumericOps
  #12 = Utf8               infixNumericOps$
  #13 = Utf8               (Lscala/math/Numeric$ExtraImplicits;Ljava/lang/Object;Lscala/math/Numeric;)Lscala/math/Numeric$NumericOps;
  #14 = Utf8               $this
  #15 = Utf8               x
  #16 = Utf8               num
  #17 = Utf8               infixNumericOps
  #18 = Utf8               (Ljava/lang/Object;Lscala/math/Numeric;)Lscala/math/Numeric$NumericOps;
  #19 = NameAndType        #17:#18        // infixNumericOps:(Ljava/lang/Object;Lscala/math/Numeric;)Lscala/math/Numeric$NumericOps;
  #20 = InterfaceMethodref #2.#19         // scala/math/Numeric$ExtraImplicits.infixNumericOps:(Ljava/lang/Object;Lscala/math/Numeric;)Lscala/math/Numeric$NumericOps;
  #21 = Utf8               Lscala/math/Numeric$ExtraImplicits;
  #22 = Utf8               Ljava/lang/Object;
  #23 = Utf8               Lscala/math/Numeric;
  #24 = Utf8               <T:Ljava/lang/Object;>(TT;Lscala/math/Numeric<TT;>;)Lscala/math/Numeric<TT;>.NumericOps;
  #25 = Utf8               <init>
  #26 = Utf8               (Lscala/math/Numeric;Ljava/lang/Object;)V
  #27 = NameAndType        #25:#26        // "<init>":(Lscala/math/Numeric;Ljava/lang/Object;)V
  #28 = Methodref          #10.#27        // scala/math/Numeric$NumericOps."<init>":(Lscala/math/Numeric;Ljava/lang/Object;)V
  #29 = Utf8               this
  #30 = Utf8               $init$
  #31 = Utf8               (Lscala/math/Numeric$ExtraImplicits;)V
  #32 = Utf8               Code
  #33 = Utf8               LineNumberTable
  #34 = Utf8               LocalVariableTable
  #35 = Utf8               MethodParameters
  #36 = Utf8               Signature
  #37 = Utf8               InnerClasses
  #38 = Utf8               SourceFile
  #39 = Utf8               ScalaInlineInfo
  #40 = Utf8               Scala
{
  public static scala.math.Numeric$NumericOps infixNumericOps$(scala.math.Numeric$ExtraImplicits, java.lang.Object, scala.math.Numeric);
    descriptor: (Lscala/math/Numeric$ExtraImplicits;Ljava/lang/Object;Lscala/math/Numeric;)Lscala/math/Numeric$NumericOps;
    flags: (0x1009) ACC_PUBLIC, ACC_STATIC, ACC_SYNTHETIC
    Code:
      stack=3, locals=3, args_size=3
         0: aload_0
         1: aload_1
         2: aload_2
         3: invokespecial #20                 // InterfaceMethod infixNumericOps:(Ljava/lang/Object;Lscala/math/Numeric;)Lscala/math/Numeric$NumericOps;
         6: areturn
      LineNumberTable:
        line 31: 0
      LocalVariableTable:
        Start  Length  Slot  Name   Signature
            0       7     0 $this   Lscala/math/Numeric$ExtraImplicits;
            0       7     1     x   Ljava/lang/Object;
            0       7     2   num   Lscala/math/Numeric;
    MethodParameters:
      Name                           Flags
      $this                          final synthetic
      x                              final
      num                            final

  public default <T extends java.lang.Object> scala.math.Numeric<T>.NumericOps infixNumericOps(T, scala.math.Numeric<T>);
    descriptor: (Ljava/lang/Object;Lscala/math/Numeric;)Lscala/math/Numeric$NumericOps;
    flags: (0x0001) ACC_PUBLIC
    Code:
      stack=4, locals=3, args_size=3
         0: new           #10                 // class scala/math/Numeric$NumericOps
         3: dup
         4: aload_2
         5: aload_1
         6: invokespecial #28                 // Method scala/math/Numeric$NumericOps."<init>":(Lscala/math/Numeric;Ljava/lang/Object;)V
         9: areturn
      LineNumberTable:
        line 31: 0
      LocalVariableTable:
        Start  Length  Slot  Name   Signature
            0      10     0  this   Lscala/math/Numeric$ExtraImplicits;
            0      10     1     x   Ljava/lang/Object;
            0      10     2   num   Lscala/math/Numeric;
    Signature: #24                          // <T:Ljava/lang/Object;>(TT;Lscala/math/Numeric<TT;>;)Lscala/math/Numeric<TT;>.NumericOps;
    MethodParameters:
      Name                           Flags
      x                              final
      num                            final

  public static void $init$(scala.math.Numeric$ExtraImplicits);
    descriptor: (Lscala/math/Numeric$ExtraImplicits;)V
    flags: (0x0009) ACC_PUBLIC, ACC_STATIC
    Code:
      stack=0, locals=1, args_size=1
         0: return
      LineNumberTable:
        line 23: 0
      LocalVariableTable:
        Start  Length  Slot  Name   Signature
            0       1     0 $this   Lscala/math/Numeric$ExtraImplicits;
    MethodParameters:
      Name                           Flags
      $this                          final synthetic
}
InnerClasses:
  public static #8= #2 of #7;             // ExtraImplicits=class scala/math/Numeric$ExtraImplicits of class scala/math/Numeric
  public #11= #10 of #7;                  // NumericOps=class scala/math/Numeric$NumericOps of class scala/math/Numeric
SourceFile: "Numeric.scala"
  ScalaInlineInfo: length = 0x13 (unknown attribute)
   01 00 00 03 00 1E 00 1F 01 00 11 00 12 00 00 0C
   00 0D 01
  Scala: length = 0x0 (unknown attribute)

