Classfile /Users/mw/Projects/slang-braindump/.jar/jar11/assemble/slang-braindump/assemble/content/scala/math/Numeric$LongIsIntegral.class
  Last modified May 29, 2022; size 4345 bytes
  SHA-256 checksum d1d1f16b0c97f652513acaa357e558037658259d83bd278d3ffe4827bde29601
  Compiled from "Numeric.scala"
public interface scala.math.Numeric$LongIsIntegral extends scala.math.Integral<java.lang.Object>
  minor version: 0
  major version: 52
  flags: (0x0601) ACC_PUBLIC, ACC_INTERFACE, ACC_ABSTRACT
  this_class: #2                          // scala/math/Numeric$LongIsIntegral
  super_class: #5                         // java/lang/Object
  interfaces: 1, fields: 0, methods: 29, attributes: 5
Constant pool:
    #1 = Utf8               scala/math/Numeric$LongIsIntegral
    #2 = Class              #1            // scala/math/Numeric$LongIsIntegral
    #3 = Utf8               Ljava/lang/Object;Lscala/math/Integral<Ljava/lang/Object;>;
    #4 = Utf8               java/lang/Object
    #5 = Class              #4            // java/lang/Object
    #6 = Utf8               scala/math/Integral
    #7 = Class              #6            // scala/math/Integral
    #8 = Utf8               Numeric.scala
    #9 = Utf8               scala/math/Numeric
   #10 = Class              #9            // scala/math/Numeric
   #11 = Utf8               LongIsIntegral
   #12 = Utf8               plus$
   #13 = Utf8               (Lscala/math/Numeric$LongIsIntegral;JJ)J
   #14 = Utf8               $this
   #15 = Utf8               x
   #16 = Utf8               y
   #17 = Utf8               plus
   #18 = Utf8               (JJ)J
   #19 = NameAndType        #17:#18       // plus:(JJ)J
   #20 = InterfaceMethodref #2.#19        // scala/math/Numeric$LongIsIntegral.plus:(JJ)J
   #21 = Utf8               Lscala/math/Numeric$LongIsIntegral;
   #22 = Utf8               J
   #23 = Utf8               this
   #24 = Utf8               minus$
   #25 = Utf8               minus
   #26 = NameAndType        #25:#18       // minus:(JJ)J
   #27 = InterfaceMethodref #2.#26        // scala/math/Numeric$LongIsIntegral.minus:(JJ)J
   #28 = Utf8               times$
   #29 = Utf8               times
   #30 = NameAndType        #29:#18       // times:(JJ)J
   #31 = InterfaceMethodref #2.#30        // scala/math/Numeric$LongIsIntegral.times:(JJ)J
   #32 = Utf8               quot$
   #33 = Utf8               quot
   #34 = NameAndType        #33:#18       // quot:(JJ)J
   #35 = InterfaceMethodref #2.#34        // scala/math/Numeric$LongIsIntegral.quot:(JJ)J
   #36 = Utf8               rem$
   #37 = Utf8               rem
   #38 = NameAndType        #37:#18       // rem:(JJ)J
   #39 = InterfaceMethodref #2.#38        // scala/math/Numeric$LongIsIntegral.rem:(JJ)J
   #40 = Utf8               negate$
   #41 = Utf8               (Lscala/math/Numeric$LongIsIntegral;J)J
   #42 = Utf8               negate
   #43 = Utf8               (J)J
   #44 = NameAndType        #42:#43       // negate:(J)J
   #45 = InterfaceMethodref #2.#44        // scala/math/Numeric$LongIsIntegral.negate:(J)J
   #46 = Utf8               fromInt$
   #47 = Utf8               (Lscala/math/Numeric$LongIsIntegral;I)J
   #48 = Utf8               fromInt
   #49 = Utf8               (I)J
   #50 = NameAndType        #48:#49       // fromInt:(I)J
   #51 = InterfaceMethodref #2.#50        // scala/math/Numeric$LongIsIntegral.fromInt:(I)J
   #52 = Utf8               I
   #53 = Utf8               parseString$
   #54 = Utf8               (Lscala/math/Numeric$LongIsIntegral;Ljava/lang/String;)Lscala/Option;
   #55 = Utf8               str
   #56 = Utf8               parseString
   #57 = Utf8               (Ljava/lang/String;)Lscala/Option;
   #58 = NameAndType        #56:#57       // parseString:(Ljava/lang/String;)Lscala/Option;
   #59 = InterfaceMethodref #2.#58        // scala/math/Numeric$LongIsIntegral.parseString:(Ljava/lang/String;)Lscala/Option;
   #60 = Utf8               Ljava/lang/String;
   #61 = Utf8               (Ljava/lang/String;)Lscala/Option<Ljava/lang/Object;>;
   #62 = Utf8               scala/collection/StringParsers$
   #63 = Class              #62           // scala/collection/StringParsers$
   #64 = Utf8               MODULE$
   #65 = Utf8               Lscala/collection/StringParsers$;
   #66 = NameAndType        #64:#65       // MODULE$:Lscala/collection/StringParsers$;
   #67 = Fieldref           #63.#66       // scala/collection/StringParsers$.MODULE$:Lscala/collection/StringParsers$;
   #68 = Utf8               parseLong
   #69 = NameAndType        #68:#57       // parseLong:(Ljava/lang/String;)Lscala/Option;
   #70 = Methodref          #63.#69       // scala/collection/StringParsers$.parseLong:(Ljava/lang/String;)Lscala/Option;
   #71 = Utf8               toInt$
   #72 = Utf8               (Lscala/math/Numeric$LongIsIntegral;J)I
   #73 = Utf8               toInt
   #74 = Utf8               (J)I
   #75 = NameAndType        #73:#74       // toInt:(J)I
   #76 = InterfaceMethodref #2.#75        // scala/math/Numeric$LongIsIntegral.toInt:(J)I
   #77 = Utf8               toLong$
   #78 = Utf8               toLong
   #79 = NameAndType        #78:#43       // toLong:(J)J
   #80 = InterfaceMethodref #2.#79        // scala/math/Numeric$LongIsIntegral.toLong:(J)J
   #81 = Utf8               toFloat$
   #82 = Utf8               (Lscala/math/Numeric$LongIsIntegral;J)F
   #83 = Utf8               toFloat
   #84 = Utf8               (J)F
   #85 = NameAndType        #83:#84       // toFloat:(J)F
   #86 = InterfaceMethodref #2.#85        // scala/math/Numeric$LongIsIntegral.toFloat:(J)F
   #87 = Utf8               toDouble$
   #88 = Utf8               (Lscala/math/Numeric$LongIsIntegral;J)D
   #89 = Utf8               toDouble
   #90 = Utf8               (J)D
   #91 = NameAndType        #89:#90       // toDouble:(J)D
   #92 = InterfaceMethodref #2.#91        // scala/math/Numeric$LongIsIntegral.toDouble:(J)D
   #93 = Utf8               signum$
   #94 = Utf8               signum
   #95 = NameAndType        #94:#74       // signum:(J)I
   #96 = InterfaceMethodref #2.#95        // scala/math/Numeric$LongIsIntegral.signum:(J)I
   #97 = Utf8               scala/math/package$
   #98 = Class              #97           // scala/math/package$
   #99 = Utf8               Lscala/math/package$;
  #100 = NameAndType        #64:#99       // MODULE$:Lscala/math/package$;
  #101 = Fieldref           #98.#100      // scala/math/package$.MODULE$:Lscala/math/package$;
  #102 = Utf8               java/lang/Long
  #103 = Class              #102          // java/lang/Long
  #104 = Methodref          #103.#95      // java/lang/Long.signum:(J)I
  #105 = Utf8               sign$
  #106 = Utf8               sign
  #107 = NameAndType        #106:#43      // sign:(J)J
  #108 = InterfaceMethodref #2.#107       // scala/math/Numeric$LongIsIntegral.sign:(J)J
  #109 = Utf8               $init$
  #110 = Utf8               (Lscala/math/Numeric$LongIsIntegral;)V
  #111 = Utf8               Code
  #112 = Utf8               LineNumberTable
  #113 = Utf8               LocalVariableTable
  #114 = Utf8               MethodParameters
  #115 = Utf8               Signature
  #116 = Utf8               InnerClasses
  #117 = Utf8               SourceFile
  #118 = Utf8               ScalaInlineInfo
  #119 = Utf8               Scala
{
  public static long plus$(scala.math.Numeric$LongIsIntegral, long, long);
    descriptor: (Lscala/math/Numeric$LongIsIntegral;JJ)J
    flags: (0x1009) ACC_PUBLIC, ACC_STATIC, ACC_SYNTHETIC
    Code:
      stack=5, locals=5, args_size=3
         0: aload_0
         1: lload_1
         2: lload_3
         3: invokespecial #20                 // InterfaceMethod plus:(JJ)J
         6: lreturn
      LineNumberTable:
        line 124: 0
      LocalVariableTable:
        Start  Length  Slot  Name   Signature
            0       7     0 $this   Lscala/math/Numeric$LongIsIntegral;
            0       7     1     x   J
            0       7     3     y   J
    MethodParameters:
      Name                           Flags
      $this                          final synthetic
      x                              final
      y                              final

  public default long plus(long, long);
    descriptor: (JJ)J
    flags: (0x0001) ACC_PUBLIC
    Code:
      stack=4, locals=5, args_size=3
         0: lload_1
         1: lload_3
         2: ladd
         3: lreturn
      LineNumberTable:
        line 124: 0
      LocalVariableTable:
        Start  Length  Slot  Name   Signature
            0       4     0  this   Lscala/math/Numeric$LongIsIntegral;
            0       4     1     x   J
            0       4     3     y   J
    MethodParameters:
      Name                           Flags
      x                              final
      y                              final

  public static long minus$(scala.math.Numeric$LongIsIntegral, long, long);
    descriptor: (Lscala/math/Numeric$LongIsIntegral;JJ)J
    flags: (0x1009) ACC_PUBLIC, ACC_STATIC, ACC_SYNTHETIC
    Code:
      stack=5, locals=5, args_size=3
         0: aload_0
         1: lload_1
         2: lload_3
         3: invokespecial #27                 // InterfaceMethod minus:(JJ)J
         6: lreturn
      LineNumberTable:
        line 125: 0
      LocalVariableTable:
        Start  Length  Slot  Name   Signature
            0       7     0 $this   Lscala/math/Numeric$LongIsIntegral;
            0       7     1     x   J
            0       7     3     y   J
    MethodParameters:
      Name                           Flags
      $this                          final synthetic
      x                              final
      y                              final

  public default long minus(long, long);
    descriptor: (JJ)J
    flags: (0x0001) ACC_PUBLIC
    Code:
      stack=4, locals=5, args_size=3
         0: lload_1
         1: lload_3
         2: lsub
         3: lreturn
      LineNumberTable:
        line 125: 0
      LocalVariableTable:
        Start  Length  Slot  Name   Signature
            0       4     0  this   Lscala/math/Numeric$LongIsIntegral;
            0       4     1     x   J
            0       4     3     y   J
    MethodParameters:
      Name                           Flags
      x                              final
      y                              final

  public static long times$(scala.math.Numeric$LongIsIntegral, long, long);
    descriptor: (Lscala/math/Numeric$LongIsIntegral;JJ)J
    flags: (0x1009) ACC_PUBLIC, ACC_STATIC, ACC_SYNTHETIC
    Code:
      stack=5, locals=5, args_size=3
         0: aload_0
         1: lload_1
         2: lload_3
         3: invokespecial #31                 // InterfaceMethod times:(JJ)J
         6: lreturn
      LineNumberTable:
        line 126: 0
      LocalVariableTable:
        Start  Length  Slot  Name   Signature
            0       7     0 $this   Lscala/math/Numeric$LongIsIntegral;
            0       7     1     x   J
            0       7     3     y   J
    MethodParameters:
      Name                           Flags
      $this                          final synthetic
      x                              final
      y                              final

  public default long times(long, long);
    descriptor: (JJ)J
    flags: (0x0001) ACC_PUBLIC
    Code:
      stack=4, locals=5, args_size=3
         0: lload_1
         1: lload_3
         2: lmul
         3: lreturn
      LineNumberTable:
        line 126: 0
      LocalVariableTable:
        Start  Length  Slot  Name   Signature
            0       4     0  this   Lscala/math/Numeric$LongIsIntegral;
            0       4     1     x   J
            0       4     3     y   J
    MethodParameters:
      Name                           Flags
      x                              final
      y                              final

  public static long quot$(scala.math.Numeric$LongIsIntegral, long, long);
    descriptor: (Lscala/math/Numeric$LongIsIntegral;JJ)J
    flags: (0x1009) ACC_PUBLIC, ACC_STATIC, ACC_SYNTHETIC
    Code:
      stack=5, locals=5, args_size=3
         0: aload_0
         1: lload_1
         2: lload_3
         3: invokespecial #35                 // InterfaceMethod quot:(JJ)J
         6: lreturn
      LineNumberTable:
        line 127: 0
      LocalVariableTable:
        Start  Length  Slot  Name   Signature
            0       7     0 $this   Lscala/math/Numeric$LongIsIntegral;
            0       7     1     x   J
            0       7     3     y   J
    MethodParameters:
      Name                           Flags
      $this                          final synthetic
      x                              final
      y                              final

  public default long quot(long, long);
    descriptor: (JJ)J
    flags: (0x0001) ACC_PUBLIC
    Code:
      stack=4, locals=5, args_size=3
         0: lload_1
         1: lload_3
         2: ldiv
         3: lreturn
      LineNumberTable:
        line 127: 0
      LocalVariableTable:
        Start  Length  Slot  Name   Signature
            0       4     0  this   Lscala/math/Numeric$LongIsIntegral;
            0       4     1     x   J
            0       4     3     y   J
    MethodParameters:
      Name                           Flags
      x                              final
      y                              final

  public static long rem$(scala.math.Numeric$LongIsIntegral, long, long);
    descriptor: (Lscala/math/Numeric$LongIsIntegral;JJ)J
    flags: (0x1009) ACC_PUBLIC, ACC_STATIC, ACC_SYNTHETIC
    Code:
      stack=5, locals=5, args_size=3
         0: aload_0
         1: lload_1
         2: lload_3
         3: invokespecial #39                 // InterfaceMethod rem:(JJ)J
         6: lreturn
      LineNumberTable:
        line 128: 0
      LocalVariableTable:
        Start  Length  Slot  Name   Signature
            0       7     0 $this   Lscala/math/Numeric$LongIsIntegral;
            0       7     1     x   J
            0       7     3     y   J
    MethodParameters:
      Name                           Flags
      $this                          final synthetic
      x                              final
      y                              final

  public default long rem(long, long);
    descriptor: (JJ)J
    flags: (0x0001) ACC_PUBLIC
    Code:
      stack=4, locals=5, args_size=3
         0: lload_1
         1: lload_3
         2: lrem
         3: lreturn
      LineNumberTable:
        line 128: 0
      LocalVariableTable:
        Start  Length  Slot  Name   Signature
            0       4     0  this   Lscala/math/Numeric$LongIsIntegral;
            0       4     1     x   J
            0       4     3     y   J
    MethodParameters:
      Name                           Flags
      x                              final
      y                              final

  public static long negate$(scala.math.Numeric$LongIsIntegral, long);
    descriptor: (Lscala/math/Numeric$LongIsIntegral;J)J
    flags: (0x1009) ACC_PUBLIC, ACC_STATIC, ACC_SYNTHETIC
    Code:
      stack=3, locals=3, args_size=2
         0: aload_0
         1: lload_1
         2: invokespecial #45                 // InterfaceMethod negate:(J)J
         5: lreturn
      LineNumberTable:
        line 129: 0
      LocalVariableTable:
        Start  Length  Slot  Name   Signature
            0       6     0 $this   Lscala/math/Numeric$LongIsIntegral;
            0       6     1     x   J
    MethodParameters:
      Name                           Flags
      $this                          final synthetic
      x                              final

  public default long negate(long);
    descriptor: (J)J
    flags: (0x0001) ACC_PUBLIC
    Code:
      stack=2, locals=3, args_size=2
         0: lload_1
         1: lneg
         2: lreturn
      LineNumberTable:
        line 129: 0
      LocalVariableTable:
        Start  Length  Slot  Name   Signature
            0       3     0  this   Lscala/math/Numeric$LongIsIntegral;
            0       3     1     x   J
    MethodParameters:
      Name                           Flags
      x                              final

  public static long fromInt$(scala.math.Numeric$LongIsIntegral, int);
    descriptor: (Lscala/math/Numeric$LongIsIntegral;I)J
    flags: (0x1009) ACC_PUBLIC, ACC_STATIC, ACC_SYNTHETIC
    Code:
      stack=2, locals=2, args_size=2
         0: aload_0
         1: iload_1
         2: invokespecial #51                 // InterfaceMethod fromInt:(I)J
         5: lreturn
      LineNumberTable:
        line 130: 0
      LocalVariableTable:
        Start  Length  Slot  Name   Signature
            0       6     0 $this   Lscala/math/Numeric$LongIsIntegral;
            0       6     1     x   I
    MethodParameters:
      Name                           Flags
      $this                          final synthetic
      x                              final

  public default long fromInt(int);
    descriptor: (I)J
    flags: (0x0001) ACC_PUBLIC
    Code:
      stack=2, locals=2, args_size=2
         0: iload_1
         1: i2l
         2: lreturn
      LineNumberTable:
        line 130: 0
      LocalVariableTable:
        Start  Length  Slot  Name   Signature
            0       3     0  this   Lscala/math/Numeric$LongIsIntegral;
            0       3     1     x   I
    MethodParameters:
      Name                           Flags
      x                              final

  public static scala.Option parseString$(scala.math.Numeric$LongIsIntegral, java.lang.String);
    descriptor: (Lscala/math/Numeric$LongIsIntegral;Ljava/lang/String;)Lscala/Option;
    flags: (0x1009) ACC_PUBLIC, ACC_STATIC, ACC_SYNTHETIC
    Code:
      stack=2, locals=2, args_size=2
         0: aload_0
         1: aload_1
         2: invokespecial #59                 // InterfaceMethod parseString:(Ljava/lang/String;)Lscala/Option;
         5: areturn
      LineNumberTable:
        line 131: 0
      LocalVariableTable:
        Start  Length  Slot  Name   Signature
            0       6     0 $this   Lscala/math/Numeric$LongIsIntegral;
            0       6     1   str   Ljava/lang/String;
    MethodParameters:
      Name                           Flags
      $this                          final synthetic
      str                            final

  public default scala.Option<java.lang.Object> parseString(java.lang.String);
    descriptor: (Ljava/lang/String;)Lscala/Option;
    flags: (0x0001) ACC_PUBLIC
    Code:
      stack=2, locals=2, args_size=2
         0: getstatic     #67                 // Field scala/collection/StringParsers$.MODULE$:Lscala/collection/StringParsers$;
         3: aload_1
         4: invokevirtual #70                 // Method scala/collection/StringParsers$.parseLong:(Ljava/lang/String;)Lscala/Option;
         7: areturn
      LineNumberTable:
        line 131: 0
      LocalVariableTable:
        Start  Length  Slot  Name   Signature
            0       8     0  this   Lscala/math/Numeric$LongIsIntegral;
            0       8     1   str   Ljava/lang/String;
    Signature: #61                          // (Ljava/lang/String;)Lscala/Option<Ljava/lang/Object;>;
    MethodParameters:
      Name                           Flags
      str                            final

  public static int toInt$(scala.math.Numeric$LongIsIntegral, long);
    descriptor: (Lscala/math/Numeric$LongIsIntegral;J)I
    flags: (0x1009) ACC_PUBLIC, ACC_STATIC, ACC_SYNTHETIC
    Code:
      stack=3, locals=3, args_size=2
         0: aload_0
         1: lload_1
         2: invokespecial #76                 // InterfaceMethod toInt:(J)I
         5: ireturn
      LineNumberTable:
        line 132: 0
      LocalVariableTable:
        Start  Length  Slot  Name   Signature
            0       6     0 $this   Lscala/math/Numeric$LongIsIntegral;
            0       6     1     x   J
    MethodParameters:
      Name                           Flags
      $this                          final synthetic
      x                              final

  public default int toInt(long);
    descriptor: (J)I
    flags: (0x0001) ACC_PUBLIC
    Code:
      stack=2, locals=3, args_size=2
         0: lload_1
         1: l2i
         2: ireturn
      LineNumberTable:
        line 132: 0
      LocalVariableTable:
        Start  Length  Slot  Name   Signature
            0       3     0  this   Lscala/math/Numeric$LongIsIntegral;
            0       3     1     x   J
    MethodParameters:
      Name                           Flags
      x                              final

  public static long toLong$(scala.math.Numeric$LongIsIntegral, long);
    descriptor: (Lscala/math/Numeric$LongIsIntegral;J)J
    flags: (0x1009) ACC_PUBLIC, ACC_STATIC, ACC_SYNTHETIC
    Code:
      stack=3, locals=3, args_size=2
         0: aload_0
         1: lload_1
         2: invokespecial #80                 // InterfaceMethod toLong:(J)J
         5: lreturn
      LineNumberTable:
        line 133: 0
      LocalVariableTable:
        Start  Length  Slot  Name   Signature
            0       6     0 $this   Lscala/math/Numeric$LongIsIntegral;
            0       6     1     x   J
    MethodParameters:
      Name                           Flags
      $this                          final synthetic
      x                              final

  public default long toLong(long);
    descriptor: (J)J
    flags: (0x0001) ACC_PUBLIC
    Code:
      stack=2, locals=3, args_size=2
         0: lload_1
         1: lreturn
      LineNumberTable:
        line 133: 0
      LocalVariableTable:
        Start  Length  Slot  Name   Signature
            0       2     0  this   Lscala/math/Numeric$LongIsIntegral;
            0       2     1     x   J
    MethodParameters:
      Name                           Flags
      x                              final

  public static float toFloat$(scala.math.Numeric$LongIsIntegral, long);
    descriptor: (Lscala/math/Numeric$LongIsIntegral;J)F
    flags: (0x1009) ACC_PUBLIC, ACC_STATIC, ACC_SYNTHETIC
    Code:
      stack=3, locals=3, args_size=2
         0: aload_0
         1: lload_1
         2: invokespecial #86                 // InterfaceMethod toFloat:(J)F
         5: freturn
      LineNumberTable:
        line 134: 0
      LocalVariableTable:
        Start  Length  Slot  Name   Signature
            0       6     0 $this   Lscala/math/Numeric$LongIsIntegral;
            0       6     1     x   J
    MethodParameters:
      Name                           Flags
      $this                          final synthetic
      x                              final

  public default float toFloat(long);
    descriptor: (J)F
    flags: (0x0001) ACC_PUBLIC
    Code:
      stack=2, locals=3, args_size=2
         0: lload_1
         1: l2f
         2: freturn
      LineNumberTable:
        line 134: 0
      LocalVariableTable:
        Start  Length  Slot  Name   Signature
            0       3     0  this   Lscala/math/Numeric$LongIsIntegral;
            0       3     1     x   J
    MethodParameters:
      Name                           Flags
      x                              final

  public static double toDouble$(scala.math.Numeric$LongIsIntegral, long);
    descriptor: (Lscala/math/Numeric$LongIsIntegral;J)D
    flags: (0x1009) ACC_PUBLIC, ACC_STATIC, ACC_SYNTHETIC
    Code:
      stack=3, locals=3, args_size=2
         0: aload_0
         1: lload_1
         2: invokespecial #92                 // InterfaceMethod toDouble:(J)D
         5: dreturn
      LineNumberTable:
        line 135: 0
      LocalVariableTable:
        Start  Length  Slot  Name   Signature
            0       6     0 $this   Lscala/math/Numeric$LongIsIntegral;
            0       6     1     x   J
    MethodParameters:
      Name                           Flags
      $this                          final synthetic
      x                              final

  public default double toDouble(long);
    descriptor: (J)D
    flags: (0x0001) ACC_PUBLIC
    Code:
      stack=2, locals=3, args_size=2
         0: lload_1
         1: l2d
         2: dreturn
      LineNumberTable:
        line 135: 0
      LocalVariableTable:
        Start  Length  Slot  Name   Signature
            0       3     0  this   Lscala/math/Numeric$LongIsIntegral;
            0       3     1     x   J
    MethodParameters:
      Name                           Flags
      x                              final

  public static int signum$(scala.math.Numeric$LongIsIntegral, long);
    descriptor: (Lscala/math/Numeric$LongIsIntegral;J)I
    flags: (0x1009) ACC_PUBLIC, ACC_STATIC, ACC_SYNTHETIC
    Code:
      stack=3, locals=3, args_size=2
         0: aload_0
         1: lload_1
         2: invokespecial #96                 // InterfaceMethod signum:(J)I
         5: ireturn
      LineNumberTable:
        line 136: 0
      LocalVariableTable:
        Start  Length  Slot  Name   Signature
            0       6     0 $this   Lscala/math/Numeric$LongIsIntegral;
            0       6     1     x   J
    MethodParameters:
      Name                           Flags
      $this                          final synthetic
      x                              final

  public default int signum(long);
    descriptor: (J)I
    flags: (0x0001) ACC_PUBLIC
    Code:
      stack=2, locals=3, args_size=2
         0: getstatic     #101                // Field scala/math/package$.MODULE$:Lscala/math/package$;
         3: pop
         4: lload_1
         5: invokestatic  #104                // Method java/lang/Long.signum:(J)I
         8: i2l
         9: l2i
        10: ireturn
      LineNumberTable:
        line 136: 0
      LocalVariableTable:
        Start  Length  Slot  Name   Signature
            0      11     0  this   Lscala/math/Numeric$LongIsIntegral;
            0      11     1     x   J
    MethodParameters:
      Name                           Flags
      x                              final

  public static long sign$(scala.math.Numeric$LongIsIntegral, long);
    descriptor: (Lscala/math/Numeric$LongIsIntegral;J)J
    flags: (0x1009) ACC_PUBLIC, ACC_STATIC, ACC_SYNTHETIC
    Code:
      stack=3, locals=3, args_size=2
         0: aload_0
         1: lload_1
         2: invokespecial #108                // InterfaceMethod sign:(J)J
         5: lreturn
      LineNumberTable:
        line 137: 0
      LocalVariableTable:
        Start  Length  Slot  Name   Signature
            0       6     0 $this   Lscala/math/Numeric$LongIsIntegral;
            0       6     1     x   J
    MethodParameters:
      Name                           Flags
      $this                          final synthetic
      x                              final

  public default long sign(long);
    descriptor: (J)J
    flags: (0x0001) ACC_PUBLIC
    Code:
      stack=2, locals=3, args_size=2
         0: getstatic     #101                // Field scala/math/package$.MODULE$:Lscala/math/package$;
         3: pop
         4: lload_1
         5: invokestatic  #104                // Method java/lang/Long.signum:(J)I
         8: i2l
         9: lreturn
      LineNumberTable:
        line 137: 0
      LocalVariableTable:
        Start  Length  Slot  Name   Signature
            0      10     0  this   Lscala/math/Numeric$LongIsIntegral;
            0      10     1     x   J
    MethodParameters:
      Name                           Flags
      x                              final

  public static void $init$(scala.math.Numeric$LongIsIntegral);
    descriptor: (Lscala/math/Numeric$LongIsIntegral;)V
    flags: (0x0009) ACC_PUBLIC, ACC_STATIC
    Code:
      stack=0, locals=1, args_size=1
         0: return
      LineNumberTable:
        line 123: 0
      LocalVariableTable:
        Start  Length  Slot  Name   Signature
            0       1     0 $this   Lscala/math/Numeric$LongIsIntegral;
    MethodParameters:
      Name                           Flags
      $this                          final synthetic
}
InnerClasses:
  public static #11= #2 of #10;           // LongIsIntegral=class scala/math/Numeric$LongIsIntegral of class scala/math/Numeric
Signature: #3                           // Ljava/lang/Object;Lscala/math/Integral<Ljava/lang/Object;>;
SourceFile: "Numeric.scala"
  ScalaInlineInfo: length = 0x95 (unknown attribute)
   01 00 00 1D 00 6D 00 6E 01 00 30 00 31 00 00 2E
   00 2F 01 00 19 00 12 00 00 18 00 0D 01 00 2A 00
   2B 00 00 28 00 29 01 00 38 00 39 00 00 35 00 36
   01 00 11 00 12 00 00 0C 00 0D 01 00 21 00 12 00
   00 20 00 0D 01 00 25 00 12 00 00 24 00 0D 01 00
   6A 00 2B 00 00 69 00 29 01 00 5E 00 4A 00 00 5D
   00 48 01 00 1D 00 12 00 00 1C 00 0D 01 00 59 00
   5A 00 00 57 00 58 01 00 53 00 54 00 00 51 00 52
   01 00 49 00 4A 00 00 47 00 48 01 00 4E 00 2B 00
   00 4D 00 29 01
  Scala: length = 0x0 (unknown attribute)

