Classfile /Users/mw/Projects/slang-braindump/.jar/jar11/assemble/slang-braindump/assemble/content/scala/math/Numeric$ShortIsIntegral.class
  Last modified May 29, 2022; size 4426 bytes
  SHA-256 checksum d2850175800b71a279391d95317bac4101fddef506c5dcccf3105446af2b0ba8
  Compiled from "Numeric.scala"
public interface scala.math.Numeric$ShortIsIntegral extends scala.math.Integral<java.lang.Object>
  minor version: 0
  major version: 52
  flags: (0x0601) ACC_PUBLIC, ACC_INTERFACE, ACC_ABSTRACT
  this_class: #2                          // scala/math/Numeric$ShortIsIntegral
  super_class: #5                         // java/lang/Object
  interfaces: 1, fields: 0, methods: 29, attributes: 5
Constant pool:
    #1 = Utf8               scala/math/Numeric$ShortIsIntegral
    #2 = Class              #1            // scala/math/Numeric$ShortIsIntegral
    #3 = Utf8               Ljava/lang/Object;Lscala/math/Integral<Ljava/lang/Object;>;
    #4 = Utf8               java/lang/Object
    #5 = Class              #4            // java/lang/Object
    #6 = Utf8               scala/math/Integral
    #7 = Class              #6            // scala/math/Integral
    #8 = Utf8               Numeric.scala
    #9 = Utf8               scala/math/Numeric
   #10 = Class              #9            // scala/math/Numeric
   #11 = Utf8               ShortIsIntegral
   #12 = Utf8               plus$
   #13 = Utf8               (Lscala/math/Numeric$ShortIsIntegral;SS)S
   #14 = Utf8               $this
   #15 = Utf8               x
   #16 = Utf8               y
   #17 = Utf8               plus
   #18 = Utf8               (SS)S
   #19 = NameAndType        #17:#18       // plus:(SS)S
   #20 = InterfaceMethodref #2.#19        // scala/math/Numeric$ShortIsIntegral.plus:(SS)S
   #21 = Utf8               Lscala/math/Numeric$ShortIsIntegral;
   #22 = Utf8               S
   #23 = Utf8               this
   #24 = Utf8               minus$
   #25 = Utf8               minus
   #26 = NameAndType        #25:#18       // minus:(SS)S
   #27 = InterfaceMethodref #2.#26        // scala/math/Numeric$ShortIsIntegral.minus:(SS)S
   #28 = Utf8               times$
   #29 = Utf8               times
   #30 = NameAndType        #29:#18       // times:(SS)S
   #31 = InterfaceMethodref #2.#30        // scala/math/Numeric$ShortIsIntegral.times:(SS)S
   #32 = Utf8               quot$
   #33 = Utf8               quot
   #34 = NameAndType        #33:#18       // quot:(SS)S
   #35 = InterfaceMethodref #2.#34        // scala/math/Numeric$ShortIsIntegral.quot:(SS)S
   #36 = Utf8               rem$
   #37 = Utf8               rem
   #38 = NameAndType        #37:#18       // rem:(SS)S
   #39 = InterfaceMethodref #2.#38        // scala/math/Numeric$ShortIsIntegral.rem:(SS)S
   #40 = Utf8               negate$
   #41 = Utf8               (Lscala/math/Numeric$ShortIsIntegral;S)S
   #42 = Utf8               negate
   #43 = Utf8               (S)S
   #44 = NameAndType        #42:#43       // negate:(S)S
   #45 = InterfaceMethodref #2.#44        // scala/math/Numeric$ShortIsIntegral.negate:(S)S
   #46 = Utf8               fromInt$
   #47 = Utf8               (Lscala/math/Numeric$ShortIsIntegral;I)S
   #48 = Utf8               fromInt
   #49 = Utf8               (I)S
   #50 = NameAndType        #48:#49       // fromInt:(I)S
   #51 = InterfaceMethodref #2.#50        // scala/math/Numeric$ShortIsIntegral.fromInt:(I)S
   #52 = Utf8               I
   #53 = Utf8               parseString$
   #54 = Utf8               (Lscala/math/Numeric$ShortIsIntegral;Ljava/lang/String;)Lscala/Option;
   #55 = Utf8               str
   #56 = Utf8               parseString
   #57 = Utf8               (Ljava/lang/String;)Lscala/Option;
   #58 = NameAndType        #56:#57       // parseString:(Ljava/lang/String;)Lscala/Option;
   #59 = InterfaceMethodref #2.#58        // scala/math/Numeric$ShortIsIntegral.parseString:(Ljava/lang/String;)Lscala/Option;
   #60 = Utf8               Ljava/lang/String;
   #61 = Utf8               (Ljava/lang/String;)Lscala/Option<Ljava/lang/Object;>;
   #62 = Utf8               scala/collection/StringParsers$
   #63 = Class              #62           // scala/collection/StringParsers$
   #64 = Utf8               MODULE$
   #65 = Utf8               Lscala/collection/StringParsers$;
   #66 = NameAndType        #64:#65       // MODULE$:Lscala/collection/StringParsers$;
   #67 = Fieldref           #63.#66       // scala/collection/StringParsers$.MODULE$:Lscala/collection/StringParsers$;
   #68 = Utf8               parseShort
   #69 = NameAndType        #68:#57       // parseShort:(Ljava/lang/String;)Lscala/Option;
   #70 = Methodref          #63.#69       // scala/collection/StringParsers$.parseShort:(Ljava/lang/String;)Lscala/Option;
   #71 = Utf8               toInt$
   #72 = Utf8               (Lscala/math/Numeric$ShortIsIntegral;S)I
   #73 = Utf8               toInt
   #74 = Utf8               (S)I
   #75 = NameAndType        #73:#74       // toInt:(S)I
   #76 = InterfaceMethodref #2.#75        // scala/math/Numeric$ShortIsIntegral.toInt:(S)I
   #77 = Utf8               toLong$
   #78 = Utf8               (Lscala/math/Numeric$ShortIsIntegral;S)J
   #79 = Utf8               toLong
   #80 = Utf8               (S)J
   #81 = NameAndType        #79:#80       // toLong:(S)J
   #82 = InterfaceMethodref #2.#81        // scala/math/Numeric$ShortIsIntegral.toLong:(S)J
   #83 = Utf8               toFloat$
   #84 = Utf8               (Lscala/math/Numeric$ShortIsIntegral;S)F
   #85 = Utf8               toFloat
   #86 = Utf8               (S)F
   #87 = NameAndType        #85:#86       // toFloat:(S)F
   #88 = InterfaceMethodref #2.#87        // scala/math/Numeric$ShortIsIntegral.toFloat:(S)F
   #89 = Utf8               toDouble$
   #90 = Utf8               (Lscala/math/Numeric$ShortIsIntegral;S)D
   #91 = Utf8               toDouble
   #92 = Utf8               (S)D
   #93 = NameAndType        #91:#92       // toDouble:(S)D
   #94 = InterfaceMethodref #2.#93        // scala/math/Numeric$ShortIsIntegral.toDouble:(S)D
   #95 = Utf8               signum$
   #96 = Utf8               signum
   #97 = NameAndType        #96:#74       // signum:(S)I
   #98 = InterfaceMethodref #2.#97        // scala/math/Numeric$ShortIsIntegral.signum:(S)I
   #99 = Utf8               scala/math/package$
  #100 = Class              #99           // scala/math/package$
  #101 = Utf8               Lscala/math/package$;
  #102 = NameAndType        #64:#101      // MODULE$:Lscala/math/package$;
  #103 = Fieldref           #100.#102     // scala/math/package$.MODULE$:Lscala/math/package$;
  #104 = Utf8               java/lang/Integer
  #105 = Class              #104          // java/lang/Integer
  #106 = Utf8               (I)I
  #107 = NameAndType        #96:#106      // signum:(I)I
  #108 = Methodref          #105.#107     // java/lang/Integer.signum:(I)I
  #109 = Utf8               sign$
  #110 = Utf8               sign
  #111 = NameAndType        #110:#43      // sign:(S)S
  #112 = InterfaceMethodref #2.#111       // scala/math/Numeric$ShortIsIntegral.sign:(S)S
  #113 = Utf8               $init$
  #114 = Utf8               (Lscala/math/Numeric$ShortIsIntegral;)V
  #115 = Utf8               Code
  #116 = Utf8               LineNumberTable
  #117 = Utf8               LocalVariableTable
  #118 = Utf8               MethodParameters
  #119 = Utf8               Signature
  #120 = Utf8               InnerClasses
  #121 = Utf8               SourceFile
  #122 = Utf8               ScalaInlineInfo
  #123 = Utf8               Scala
{
  public static short plus$(scala.math.Numeric$ShortIsIntegral, short, short);
    descriptor: (Lscala/math/Numeric$ShortIsIntegral;SS)S
    flags: (0x1009) ACC_PUBLIC, ACC_STATIC, ACC_SYNTHETIC
    Code:
      stack=3, locals=3, args_size=3
         0: aload_0
         1: iload_1
         2: iload_2
         3: invokespecial #20                 // InterfaceMethod plus:(SS)S
         6: ireturn
      LineNumberTable:
        line 70: 0
      LocalVariableTable:
        Start  Length  Slot  Name   Signature
            0       7     0 $this   Lscala/math/Numeric$ShortIsIntegral;
            0       7     1     x   S
            0       7     2     y   S
    MethodParameters:
      Name                           Flags
      $this                          final synthetic
      x                              final
      y                              final

  public default short plus(short, short);
    descriptor: (SS)S
    flags: (0x0001) ACC_PUBLIC
    Code:
      stack=2, locals=3, args_size=3
         0: iload_1
         1: iload_2
         2: iadd
         3: i2s
         4: ireturn
      LineNumberTable:
        line 70: 0
      LocalVariableTable:
        Start  Length  Slot  Name   Signature
            0       5     0  this   Lscala/math/Numeric$ShortIsIntegral;
            0       5     1     x   S
            0       5     2     y   S
    MethodParameters:
      Name                           Flags
      x                              final
      y                              final

  public static short minus$(scala.math.Numeric$ShortIsIntegral, short, short);
    descriptor: (Lscala/math/Numeric$ShortIsIntegral;SS)S
    flags: (0x1009) ACC_PUBLIC, ACC_STATIC, ACC_SYNTHETIC
    Code:
      stack=3, locals=3, args_size=3
         0: aload_0
         1: iload_1
         2: iload_2
         3: invokespecial #27                 // InterfaceMethod minus:(SS)S
         6: ireturn
      LineNumberTable:
        line 71: 0
      LocalVariableTable:
        Start  Length  Slot  Name   Signature
            0       7     0 $this   Lscala/math/Numeric$ShortIsIntegral;
            0       7     1     x   S
            0       7     2     y   S
    MethodParameters:
      Name                           Flags
      $this                          final synthetic
      x                              final
      y                              final

  public default short minus(short, short);
    descriptor: (SS)S
    flags: (0x0001) ACC_PUBLIC
    Code:
      stack=2, locals=3, args_size=3
         0: iload_1
         1: iload_2
         2: isub
         3: i2s
         4: ireturn
      LineNumberTable:
        line 71: 0
      LocalVariableTable:
        Start  Length  Slot  Name   Signature
            0       5     0  this   Lscala/math/Numeric$ShortIsIntegral;
            0       5     1     x   S
            0       5     2     y   S
    MethodParameters:
      Name                           Flags
      x                              final
      y                              final

  public static short times$(scala.math.Numeric$ShortIsIntegral, short, short);
    descriptor: (Lscala/math/Numeric$ShortIsIntegral;SS)S
    flags: (0x1009) ACC_PUBLIC, ACC_STATIC, ACC_SYNTHETIC
    Code:
      stack=3, locals=3, args_size=3
         0: aload_0
         1: iload_1
         2: iload_2
         3: invokespecial #31                 // InterfaceMethod times:(SS)S
         6: ireturn
      LineNumberTable:
        line 72: 0
      LocalVariableTable:
        Start  Length  Slot  Name   Signature
            0       7     0 $this   Lscala/math/Numeric$ShortIsIntegral;
            0       7     1     x   S
            0       7     2     y   S
    MethodParameters:
      Name                           Flags
      $this                          final synthetic
      x                              final
      y                              final

  public default short times(short, short);
    descriptor: (SS)S
    flags: (0x0001) ACC_PUBLIC
    Code:
      stack=2, locals=3, args_size=3
         0: iload_1
         1: iload_2
         2: imul
         3: i2s
         4: ireturn
      LineNumberTable:
        line 72: 0
      LocalVariableTable:
        Start  Length  Slot  Name   Signature
            0       5     0  this   Lscala/math/Numeric$ShortIsIntegral;
            0       5     1     x   S
            0       5     2     y   S
    MethodParameters:
      Name                           Flags
      x                              final
      y                              final

  public static short quot$(scala.math.Numeric$ShortIsIntegral, short, short);
    descriptor: (Lscala/math/Numeric$ShortIsIntegral;SS)S
    flags: (0x1009) ACC_PUBLIC, ACC_STATIC, ACC_SYNTHETIC
    Code:
      stack=3, locals=3, args_size=3
         0: aload_0
         1: iload_1
         2: iload_2
         3: invokespecial #35                 // InterfaceMethod quot:(SS)S
         6: ireturn
      LineNumberTable:
        line 73: 0
      LocalVariableTable:
        Start  Length  Slot  Name   Signature
            0       7     0 $this   Lscala/math/Numeric$ShortIsIntegral;
            0       7     1     x   S
            0       7     2     y   S
    MethodParameters:
      Name                           Flags
      $this                          final synthetic
      x                              final
      y                              final

  public default short quot(short, short);
    descriptor: (SS)S
    flags: (0x0001) ACC_PUBLIC
    Code:
      stack=2, locals=3, args_size=3
         0: iload_1
         1: iload_2
         2: idiv
         3: i2s
         4: ireturn
      LineNumberTable:
        line 73: 0
      LocalVariableTable:
        Start  Length  Slot  Name   Signature
            0       5     0  this   Lscala/math/Numeric$ShortIsIntegral;
            0       5     1     x   S
            0       5     2     y   S
    MethodParameters:
      Name                           Flags
      x                              final
      y                              final

  public static short rem$(scala.math.Numeric$ShortIsIntegral, short, short);
    descriptor: (Lscala/math/Numeric$ShortIsIntegral;SS)S
    flags: (0x1009) ACC_PUBLIC, ACC_STATIC, ACC_SYNTHETIC
    Code:
      stack=3, locals=3, args_size=3
         0: aload_0
         1: iload_1
         2: iload_2
         3: invokespecial #39                 // InterfaceMethod rem:(SS)S
         6: ireturn
      LineNumberTable:
        line 74: 0
      LocalVariableTable:
        Start  Length  Slot  Name   Signature
            0       7     0 $this   Lscala/math/Numeric$ShortIsIntegral;
            0       7     1     x   S
            0       7     2     y   S
    MethodParameters:
      Name                           Flags
      $this                          final synthetic
      x                              final
      y                              final

  public default short rem(short, short);
    descriptor: (SS)S
    flags: (0x0001) ACC_PUBLIC
    Code:
      stack=2, locals=3, args_size=3
         0: iload_1
         1: iload_2
         2: irem
         3: i2s
         4: ireturn
      LineNumberTable:
        line 74: 0
      LocalVariableTable:
        Start  Length  Slot  Name   Signature
            0       5     0  this   Lscala/math/Numeric$ShortIsIntegral;
            0       5     1     x   S
            0       5     2     y   S
    MethodParameters:
      Name                           Flags
      x                              final
      y                              final

  public static short negate$(scala.math.Numeric$ShortIsIntegral, short);
    descriptor: (Lscala/math/Numeric$ShortIsIntegral;S)S
    flags: (0x1009) ACC_PUBLIC, ACC_STATIC, ACC_SYNTHETIC
    Code:
      stack=2, locals=2, args_size=2
         0: aload_0
         1: iload_1
         2: invokespecial #45                 // InterfaceMethod negate:(S)S
         5: ireturn
      LineNumberTable:
        line 75: 0
      LocalVariableTable:
        Start  Length  Slot  Name   Signature
            0       6     0 $this   Lscala/math/Numeric$ShortIsIntegral;
            0       6     1     x   S
    MethodParameters:
      Name                           Flags
      $this                          final synthetic
      x                              final

  public default short negate(short);
    descriptor: (S)S
    flags: (0x0001) ACC_PUBLIC
    Code:
      stack=1, locals=2, args_size=2
         0: iload_1
         1: ineg
         2: i2s
         3: ireturn
      LineNumberTable:
        line 75: 0
      LocalVariableTable:
        Start  Length  Slot  Name   Signature
            0       4     0  this   Lscala/math/Numeric$ShortIsIntegral;
            0       4     1     x   S
    MethodParameters:
      Name                           Flags
      x                              final

  public static short fromInt$(scala.math.Numeric$ShortIsIntegral, int);
    descriptor: (Lscala/math/Numeric$ShortIsIntegral;I)S
    flags: (0x1009) ACC_PUBLIC, ACC_STATIC, ACC_SYNTHETIC
    Code:
      stack=2, locals=2, args_size=2
         0: aload_0
         1: iload_1
         2: invokespecial #51                 // InterfaceMethod fromInt:(I)S
         5: ireturn
      LineNumberTable:
        line 76: 0
      LocalVariableTable:
        Start  Length  Slot  Name   Signature
            0       6     0 $this   Lscala/math/Numeric$ShortIsIntegral;
            0       6     1     x   I
    MethodParameters:
      Name                           Flags
      $this                          final synthetic
      x                              final

  public default short fromInt(int);
    descriptor: (I)S
    flags: (0x0001) ACC_PUBLIC
    Code:
      stack=1, locals=2, args_size=2
         0: iload_1
         1: i2s
         2: ireturn
      LineNumberTable:
        line 76: 0
      LocalVariableTable:
        Start  Length  Slot  Name   Signature
            0       3     0  this   Lscala/math/Numeric$ShortIsIntegral;
            0       3     1     x   I
    MethodParameters:
      Name                           Flags
      x                              final

  public static scala.Option parseString$(scala.math.Numeric$ShortIsIntegral, java.lang.String);
    descriptor: (Lscala/math/Numeric$ShortIsIntegral;Ljava/lang/String;)Lscala/Option;
    flags: (0x1009) ACC_PUBLIC, ACC_STATIC, ACC_SYNTHETIC
    Code:
      stack=2, locals=2, args_size=2
         0: aload_0
         1: aload_1
         2: invokespecial #59                 // InterfaceMethod parseString:(Ljava/lang/String;)Lscala/Option;
         5: areturn
      LineNumberTable:
        line 77: 0
      LocalVariableTable:
        Start  Length  Slot  Name   Signature
            0       6     0 $this   Lscala/math/Numeric$ShortIsIntegral;
            0       6     1   str   Ljava/lang/String;
    MethodParameters:
      Name                           Flags
      $this                          final synthetic
      str                            final

  public default scala.Option<java.lang.Object> parseString(java.lang.String);
    descriptor: (Ljava/lang/String;)Lscala/Option;
    flags: (0x0001) ACC_PUBLIC
    Code:
      stack=2, locals=2, args_size=2
         0: getstatic     #67                 // Field scala/collection/StringParsers$.MODULE$:Lscala/collection/StringParsers$;
         3: aload_1
         4: invokevirtual #70                 // Method scala/collection/StringParsers$.parseShort:(Ljava/lang/String;)Lscala/Option;
         7: areturn
      LineNumberTable:
        line 77: 0
      LocalVariableTable:
        Start  Length  Slot  Name   Signature
            0       8     0  this   Lscala/math/Numeric$ShortIsIntegral;
            0       8     1   str   Ljava/lang/String;
    Signature: #61                          // (Ljava/lang/String;)Lscala/Option<Ljava/lang/Object;>;
    MethodParameters:
      Name                           Flags
      str                            final

  public static int toInt$(scala.math.Numeric$ShortIsIntegral, short);
    descriptor: (Lscala/math/Numeric$ShortIsIntegral;S)I
    flags: (0x1009) ACC_PUBLIC, ACC_STATIC, ACC_SYNTHETIC
    Code:
      stack=2, locals=2, args_size=2
         0: aload_0
         1: iload_1
         2: invokespecial #76                 // InterfaceMethod toInt:(S)I
         5: ireturn
      LineNumberTable:
        line 78: 0
      LocalVariableTable:
        Start  Length  Slot  Name   Signature
            0       6     0 $this   Lscala/math/Numeric$ShortIsIntegral;
            0       6     1     x   S
    MethodParameters:
      Name                           Flags
      $this                          final synthetic
      x                              final

  public default int toInt(short);
    descriptor: (S)I
    flags: (0x0001) ACC_PUBLIC
    Code:
      stack=1, locals=2, args_size=2
         0: iload_1
         1: ireturn
      LineNumberTable:
        line 78: 0
      LocalVariableTable:
        Start  Length  Slot  Name   Signature
            0       2     0  this   Lscala/math/Numeric$ShortIsIntegral;
            0       2     1     x   S
    MethodParameters:
      Name                           Flags
      x                              final

  public static long toLong$(scala.math.Numeric$ShortIsIntegral, short);
    descriptor: (Lscala/math/Numeric$ShortIsIntegral;S)J
    flags: (0x1009) ACC_PUBLIC, ACC_STATIC, ACC_SYNTHETIC
    Code:
      stack=2, locals=2, args_size=2
         0: aload_0
         1: iload_1
         2: invokespecial #82                 // InterfaceMethod toLong:(S)J
         5: lreturn
      LineNumberTable:
        line 79: 0
      LocalVariableTable:
        Start  Length  Slot  Name   Signature
            0       6     0 $this   Lscala/math/Numeric$ShortIsIntegral;
            0       6     1     x   S
    MethodParameters:
      Name                           Flags
      $this                          final synthetic
      x                              final

  public default long toLong(short);
    descriptor: (S)J
    flags: (0x0001) ACC_PUBLIC
    Code:
      stack=2, locals=2, args_size=2
         0: iload_1
         1: i2l
         2: lreturn
      LineNumberTable:
        line 79: 0
      LocalVariableTable:
        Start  Length  Slot  Name   Signature
            0       3     0  this   Lscala/math/Numeric$ShortIsIntegral;
            0       3     1     x   S
    MethodParameters:
      Name                           Flags
      x                              final

  public static float toFloat$(scala.math.Numeric$ShortIsIntegral, short);
    descriptor: (Lscala/math/Numeric$ShortIsIntegral;S)F
    flags: (0x1009) ACC_PUBLIC, ACC_STATIC, ACC_SYNTHETIC
    Code:
      stack=2, locals=2, args_size=2
         0: aload_0
         1: iload_1
         2: invokespecial #88                 // InterfaceMethod toFloat:(S)F
         5: freturn
      LineNumberTable:
        line 80: 0
      LocalVariableTable:
        Start  Length  Slot  Name   Signature
            0       6     0 $this   Lscala/math/Numeric$ShortIsIntegral;
            0       6     1     x   S
    MethodParameters:
      Name                           Flags
      $this                          final synthetic
      x                              final

  public default float toFloat(short);
    descriptor: (S)F
    flags: (0x0001) ACC_PUBLIC
    Code:
      stack=1, locals=2, args_size=2
         0: iload_1
         1: i2f
         2: freturn
      LineNumberTable:
        line 80: 0
      LocalVariableTable:
        Start  Length  Slot  Name   Signature
            0       3     0  this   Lscala/math/Numeric$ShortIsIntegral;
            0       3     1     x   S
    MethodParameters:
      Name                           Flags
      x                              final

  public static double toDouble$(scala.math.Numeric$ShortIsIntegral, short);
    descriptor: (Lscala/math/Numeric$ShortIsIntegral;S)D
    flags: (0x1009) ACC_PUBLIC, ACC_STATIC, ACC_SYNTHETIC
    Code:
      stack=2, locals=2, args_size=2
         0: aload_0
         1: iload_1
         2: invokespecial #94                 // InterfaceMethod toDouble:(S)D
         5: dreturn
      LineNumberTable:
        line 81: 0
      LocalVariableTable:
        Start  Length  Slot  Name   Signature
            0       6     0 $this   Lscala/math/Numeric$ShortIsIntegral;
            0       6     1     x   S
    MethodParameters:
      Name                           Flags
      $this                          final synthetic
      x                              final

  public default double toDouble(short);
    descriptor: (S)D
    flags: (0x0001) ACC_PUBLIC
    Code:
      stack=2, locals=2, args_size=2
         0: iload_1
         1: i2d
         2: dreturn
      LineNumberTable:
        line 81: 0
      LocalVariableTable:
        Start  Length  Slot  Name   Signature
            0       3     0  this   Lscala/math/Numeric$ShortIsIntegral;
            0       3     1     x   S
    MethodParameters:
      Name                           Flags
      x                              final

  public static int signum$(scala.math.Numeric$ShortIsIntegral, short);
    descriptor: (Lscala/math/Numeric$ShortIsIntegral;S)I
    flags: (0x1009) ACC_PUBLIC, ACC_STATIC, ACC_SYNTHETIC
    Code:
      stack=2, locals=2, args_size=2
         0: aload_0
         1: iload_1
         2: invokespecial #98                 // InterfaceMethod signum:(S)I
         5: ireturn
      LineNumberTable:
        line 82: 0
      LocalVariableTable:
        Start  Length  Slot  Name   Signature
            0       6     0 $this   Lscala/math/Numeric$ShortIsIntegral;
            0       6     1     x   S
    MethodParameters:
      Name                           Flags
      $this                          final synthetic
      x                              final

  public default int signum(short);
    descriptor: (S)I
    flags: (0x0001) ACC_PUBLIC
    Code:
      stack=1, locals=2, args_size=2
         0: getstatic     #103                // Field scala/math/package$.MODULE$:Lscala/math/package$;
         3: pop
         4: iload_1
         5: invokestatic  #108                // Method java/lang/Integer.signum:(I)I
         8: ireturn
      LineNumberTable:
        line 82: 0
      LocalVariableTable:
        Start  Length  Slot  Name   Signature
            0       9     0  this   Lscala/math/Numeric$ShortIsIntegral;
            0       9     1     x   S
    MethodParameters:
      Name                           Flags
      x                              final

  public static short sign$(scala.math.Numeric$ShortIsIntegral, short);
    descriptor: (Lscala/math/Numeric$ShortIsIntegral;S)S
    flags: (0x1009) ACC_PUBLIC, ACC_STATIC, ACC_SYNTHETIC
    Code:
      stack=2, locals=2, args_size=2
         0: aload_0
         1: iload_1
         2: invokespecial #112                // InterfaceMethod sign:(S)S
         5: ireturn
      LineNumberTable:
        line 83: 0
      LocalVariableTable:
        Start  Length  Slot  Name   Signature
            0       6     0 $this   Lscala/math/Numeric$ShortIsIntegral;
            0       6     1     x   S
    MethodParameters:
      Name                           Flags
      $this                          final synthetic
      x                              final

  public default short sign(short);
    descriptor: (S)S
    flags: (0x0001) ACC_PUBLIC
    Code:
      stack=1, locals=2, args_size=2
         0: getstatic     #103                // Field scala/math/package$.MODULE$:Lscala/math/package$;
         3: pop
         4: iload_1
         5: invokestatic  #108                // Method java/lang/Integer.signum:(I)I
         8: i2s
         9: ireturn
      LineNumberTable:
        line 83: 0
      LocalVariableTable:
        Start  Length  Slot  Name   Signature
            0      10     0  this   Lscala/math/Numeric$ShortIsIntegral;
            0      10     1     x   S
    MethodParameters:
      Name                           Flags
      x                              final

  public static void $init$(scala.math.Numeric$ShortIsIntegral);
    descriptor: (Lscala/math/Numeric$ShortIsIntegral;)V
    flags: (0x0009) ACC_PUBLIC, ACC_STATIC
    Code:
      stack=0, locals=1, args_size=1
         0: return
      LineNumberTable:
        line 69: 0
      LocalVariableTable:
        Start  Length  Slot  Name   Signature
            0       1     0 $this   Lscala/math/Numeric$ShortIsIntegral;
    MethodParameters:
      Name                           Flags
      $this                          final synthetic
}
InnerClasses:
  public static #11= #2 of #10;           // ShortIsIntegral=class scala/math/Numeric$ShortIsIntegral of class scala/math/Numeric
Signature: #3                           // Ljava/lang/Object;Lscala/math/Integral<Ljava/lang/Object;>;
SourceFile: "Numeric.scala"
  ScalaInlineInfo: length = 0x95 (unknown attribute)
   01 00 00 1D 00 71 00 72 01 00 30 00 31 00 00 2E
   00 2F 01 00 19 00 12 00 00 18 00 0D 01 00 2A 00
   2B 00 00 28 00 29 01 00 38 00 39 00 00 35 00 36
   01 00 11 00 12 00 00 0C 00 0D 01 00 21 00 12 00
   00 20 00 0D 01 00 25 00 12 00 00 24 00 0D 01 00
   6E 00 2B 00 00 6D 00 29 01 00 60 00 4A 00 00 5F
   00 48 01 00 1D 00 12 00 00 1C 00 0D 01 00 5B 00
   5C 00 00 59 00 5A 01 00 55 00 56 00 00 53 00 54
   01 00 49 00 4A 00 00 47 00 48 01 00 4F 00 50 00
   00 4D 00 4E 01
  Scala: length = 0x0 (unknown attribute)

