Classfile /Users/mw/Projects/slang-braindump/.jar/jar11/assemble/slang-braindump/assemble/content/scala/math/Ordering$BigDecimalOrdering.class
  Last modified May 29, 2022; size 1071 bytes
  SHA-256 checksum 5aaa72a7f6edd33edd3ce1a7ac74997eb99e0f80236ff59addb7780e3b618141
  Compiled from "Ordering.scala"
public interface scala.math.Ordering$BigDecimalOrdering extends scala.math.Ordering<scala.math.BigDecimal>
  minor version: 0
  major version: 52
  flags: (0x0601) ACC_PUBLIC, ACC_INTERFACE, ACC_ABSTRACT
  this_class: #2                          // scala/math/Ordering$BigDecimalOrdering
  super_class: #5                         // java/lang/Object
  interfaces: 1, fields: 0, methods: 3, attributes: 5
Constant pool:
   #1 = Utf8               scala/math/Ordering$BigDecimalOrdering
   #2 = Class              #1             // scala/math/Ordering$BigDecimalOrdering
   #3 = Utf8               Ljava/lang/Object;Lscala/math/Ordering<Lscala/math/BigDecimal;>;
   #4 = Utf8               java/lang/Object
   #5 = Class              #4             // java/lang/Object
   #6 = Utf8               scala/math/Ordering
   #7 = Class              #6             // scala/math/Ordering
   #8 = Utf8               Ordering.scala
   #9 = Utf8               BigDecimalOrdering
  #10 = Utf8               compare$
  #11 = Utf8               (Lscala/math/Ordering$BigDecimalOrdering;Lscala/math/BigDecimal;Lscala/math/BigDecimal;)I
  #12 = Utf8               $this
  #13 = Utf8               x
  #14 = Utf8               y
  #15 = Utf8               compare
  #16 = Utf8               (Lscala/math/BigDecimal;Lscala/math/BigDecimal;)I
  #17 = NameAndType        #15:#16        // compare:(Lscala/math/BigDecimal;Lscala/math/BigDecimal;)I
  #18 = InterfaceMethodref #2.#17         // scala/math/Ordering$BigDecimalOrdering.compare:(Lscala/math/BigDecimal;Lscala/math/BigDecimal;)I
  #19 = Utf8               Lscala/math/Ordering$BigDecimalOrdering;
  #20 = Utf8               Lscala/math/BigDecimal;
  #21 = Utf8               scala/math/BigDecimal
  #22 = Class              #21            // scala/math/BigDecimal
  #23 = Utf8               (Lscala/math/BigDecimal;)I
  #24 = NameAndType        #15:#23        // compare:(Lscala/math/BigDecimal;)I
  #25 = Methodref          #22.#24        // scala/math/BigDecimal.compare:(Lscala/math/BigDecimal;)I
  #26 = Utf8               this
  #27 = Utf8               $init$
  #28 = Utf8               (Lscala/math/Ordering$BigDecimalOrdering;)V
  #29 = Utf8               Code
  #30 = Utf8               LineNumberTable
  #31 = Utf8               LocalVariableTable
  #32 = Utf8               MethodParameters
  #33 = Utf8               InnerClasses
  #34 = Utf8               Signature
  #35 = Utf8               SourceFile
  #36 = Utf8               ScalaInlineInfo
  #37 = Utf8               Scala
{
  public static int compare$(scala.math.Ordering$BigDecimalOrdering, scala.math.BigDecimal, scala.math.BigDecimal);
    descriptor: (Lscala/math/Ordering$BigDecimalOrdering;Lscala/math/BigDecimal;Lscala/math/BigDecimal;)I
    flags: (0x1009) ACC_PUBLIC, ACC_STATIC, ACC_SYNTHETIC
    Code:
      stack=3, locals=3, args_size=3
         0: aload_0
         1: aload_1
         2: aload_2
         3: invokespecial #18                 // InterfaceMethod compare:(Lscala/math/BigDecimal;Lscala/math/BigDecimal;)I
         6: ireturn
      LineNumberTable:
        line 570: 0
      LocalVariableTable:
        Start  Length  Slot  Name   Signature
            0       7     0 $this   Lscala/math/Ordering$BigDecimalOrdering;
            0       7     1     x   Lscala/math/BigDecimal;
            0       7     2     y   Lscala/math/BigDecimal;
    MethodParameters:
      Name                           Flags
      $this                          final synthetic
      x                              final
      y                              final

  public default int compare(scala.math.BigDecimal, scala.math.BigDecimal);
    descriptor: (Lscala/math/BigDecimal;Lscala/math/BigDecimal;)I
    flags: (0x0001) ACC_PUBLIC
    Code:
      stack=2, locals=3, args_size=3
         0: aload_1
         1: aload_2
         2: invokevirtual #25                 // Method scala/math/BigDecimal.compare:(Lscala/math/BigDecimal;)I
         5: ireturn
      LineNumberTable:
        line 570: 0
      LocalVariableTable:
        Start  Length  Slot  Name   Signature
            0       6     0  this   Lscala/math/Ordering$BigDecimalOrdering;
            0       6     1     x   Lscala/math/BigDecimal;
            0       6     2     y   Lscala/math/BigDecimal;
    MethodParameters:
      Name                           Flags
      x                              final
      y                              final

  public static void $init$(scala.math.Ordering$BigDecimalOrdering);
    descriptor: (Lscala/math/Ordering$BigDecimalOrdering;)V
    flags: (0x0009) ACC_PUBLIC, ACC_STATIC
    Code:
      stack=0, locals=1, args_size=1
         0: return
      LineNumberTable:
        line 569: 0
      LocalVariableTable:
        Start  Length  Slot  Name   Signature
            0       1     0 $this   Lscala/math/Ordering$BigDecimalOrdering;
    MethodParameters:
      Name                           Flags
      $this                          final synthetic
}
InnerClasses:
  public static #9= #2 of #7;             // BigDecimalOrdering=class scala/math/Ordering$BigDecimalOrdering of class scala/math/Ordering
Signature: #3                           // Ljava/lang/Object;Lscala/math/Ordering<Lscala/math/BigDecimal;>;
SourceFile: "Ordering.scala"
  ScalaInlineInfo: length = 0x13 (unknown attribute)
   01 00 00 03 00 1B 00 1C 01 00 0F 00 10 00 00 0A
   00 0B 01
  Scala: length = 0x0 (unknown attribute)

