Classfile /Users/mw/Projects/slang-braindump/.jar/jar11/assemble/slang-braindump/assemble/content/scala/math/PartialOrdering.class
  Last modified May 29, 2022; size 3473 bytes
  SHA-256 checksum b31a2fb39b84f81ad1b112f63157722f4fdd97a72ec09205e641f49ab16bc3ca
  Compiled from "PartialOrdering.scala"
public interface scala.math.PartialOrdering<T extends java.lang.Object> extends scala.math.Equiv<T>
  minor version: 0
  major version: 52
  flags: (0x0601) ACC_PUBLIC, ACC_INTERFACE, ACC_ABSTRACT
  this_class: #2                          // scala/math/PartialOrdering
  super_class: #5                         // java/lang/Object
  interfaces: 1, fields: 0, methods: 14, attributes: 6
Constant pool:
   #1 = Utf8               scala/math/PartialOrdering
   #2 = Class              #1             // scala/math/PartialOrdering
   #3 = Utf8               <T:Ljava/lang/Object;>Ljava/lang/Object;Lscala/math/Equiv<TT;>;
   #4 = Utf8               java/lang/Object
   #5 = Class              #4             // java/lang/Object
   #6 = Utf8               scala/math/Equiv
   #7 = Class              #6             // scala/math/Equiv
   #8 = Utf8               PartialOrdering.scala
   #9 = Utf8               Lscala/reflect/ScalaSignature;
  #10 = Utf8               bytes
  #11 = Utf8               \u0006\u0005U4qAD\b\u0011\u0002\u0007\u0005A\u0003C\u0003*\u0001\u0011\u0005!\u0006C\u0003/\u0001\u0019\u0005q\u0006C\u0003;\u0001\u0019\u00051\bC\u0003B\u0001\u0011\u0005!\tC\u0003F\u0001\u0011\u0005a\tC\u0003J\u0001\u0011\u0005!\nC\u0003N\u0001\u0011\u0005a\nC\u0003R\u0001\u0011\u0005!kB\u0003U\u001f!\u0005QKB\u0003\u000f\u001f!\u0005a\u000bC\u0003`\u0015\u0011\u0005\u0001\rC\u0003b\u0015\u0011\u0005!\rC\u0004n\u0015\u0005\u0005I\u0011\u00028\u0003\u001fA\u000b\'\u000f^5bY>\u0013H-\u001a:j]\u001eT!\u0001E\t\u0002\t5\fG\u000f\u001b\u0006\u0002%\u0005)1oY1mC\u000e\u0001QCA\u000b!\'\r\u0001aC\u0007\t\u0003/ai\u0011!E\u0005\u00033E\u0011a!\u00118z%\u00164\u0007cA\u000e\u001d=5\tq\"\u0003\u0002\u001e\u001f\t)Q)];jmB\u0011q\u0004\t\u0007\u0001\t\u0015\t\u0003A1\u0001#\u0005\u0005!\u0016CA\u0012\'!\t9B%\u0003\u0002&#\t9aj\u001c;iS:<\u0007CA\f(\u0013\tA\u0013CA\u0002B]f\fa\u0001J5oSR$C#A\u0016\u0011\u0005]a\u0013BA\u0017\u0012\u0005\u0011)f.\u001b;\u0002\u0015Q\u0014\u0018pQ8na\u0006\u0014X\rF\u00021ma\u00022aF\u00194\u0013\t\u0011\u0014C\u0001\u0004PaRLwN\u001c\t\u0003/QJ!!N\t\u0003\u0007%sG\u000fC\u00038\u0005\u0001\u0007a$A\u0001y\u0011\u0015I$\u00011\u0001\u001f\u0003\u0005I\u0018\u0001\u00027uKF$2\u0001P A!\t9R(\u0003\u0002?#\t9!i\\8mK\u0006t\u0007\"B\u001c\u0004\u0001\u0004q\u0002\"B\u001d\u0004\u0001\u0004q\u0012\u0001B4uKF$2\u0001P\"E\u0011\u00159D\u00011\u0001\u001f\u0011\u0015ID\u00011\u0001\u001f\u0003\taG\u000fF\u0002=\u000f\"CQaN\u0003A\u0002yAQ!O\u0003A\u0002y\t!a\u001a;\u0015\u0007qZE\nC\u00038\r\u0001\u0007a\u0004C\u0003:\r\u0001\u0007a$A\u0003fcVLg\u000fF\u0002=\u001fBCQaN\u0004A\u0002yAQ!O\u0004A\u0002y\tqA]3wKJ\u001cX-F\u0001T!\rY\u0002AH\u0001\u0010!\u0006\u0014H/[1m\u001fJ$WM]5oOB\u00111DC\n\u0004\u0015Y9\u0006C\u0001-^\u001b\u0005I&B\u0001.\\\u0003\tIwNC\u0001]\u0003\u0011Q\u0017M^1\n\u0005yK&\u0001D*fe&\fG.\u001b>bE2,\u0017A\u0002\u001fj]&$h\bF\u0001V\u0003\u0015\t\u0007\u000f\u001d7z+\t\u0019g\r\u0006\u0002eOB\u00191\u0004A3\u0011\u0005}1G!B\u0011\r\u0005\u0004\u0011\u0003\"\u00025\r\u0001\b!\u0017AA3wQ\ta!\u000e\u0005\u0002\u0018W&\u0011A.\u0005\u0002\u0007S:d\u0017N\\3\u0002\u0019]\u0014\u0018\u000e^3SKBd\u0017mY3\u0015\u0003=\u0004\"\u0001]:\u000e\u0003ET!A].\u0002\t1\fgnZ\u0005\u0003iF\u0014aa\u00142kK\u000e$\b
  #12 = Utf8               scala/math/PartialOrdering$$anon$1
  #13 = Class              #12            // scala/math/PartialOrdering$$anon$1
  #14 = Utf8               apply
  #15 = Utf8               (Lscala/math/PartialOrdering;)Lscala/math/PartialOrdering;
  #16 = Utf8               <T:Ljava/lang/Object;>(Lscala/math/PartialOrdering<TT;>;)Lscala/math/PartialOrdering<TT;>;
  #17 = Utf8               ev
  #18 = Utf8               scala/math/PartialOrdering$
  #19 = Class              #18            // scala/math/PartialOrdering$
  #20 = Utf8               MODULE$
  #21 = Utf8               Lscala/math/PartialOrdering$;
  #22 = NameAndType        #20:#21        // MODULE$:Lscala/math/PartialOrdering$;
  #23 = Fieldref           #19.#22        // scala/math/PartialOrdering$.MODULE$:Lscala/math/PartialOrdering$;
  #24 = Utf8               Lscala/math/PartialOrdering;
  #25 = Utf8               tryCompare
  #26 = Utf8               (Ljava/lang/Object;Ljava/lang/Object;)Lscala/Option;
  #27 = Utf8               (TT;TT;)Lscala/Option<Ljava/lang/Object;>;
  #28 = Utf8               x
  #29 = Utf8               y
  #30 = Utf8               lteq
  #31 = Utf8               (Ljava/lang/Object;Ljava/lang/Object;)Z
  #32 = Utf8               (TT;TT;)Z
  #33 = Utf8               gteq$
  #34 = Utf8               (Lscala/math/PartialOrdering;Ljava/lang/Object;Ljava/lang/Object;)Z
  #35 = Utf8               $this
  #36 = Utf8               gteq
  #37 = NameAndType        #36:#31        // gteq:(Ljava/lang/Object;Ljava/lang/Object;)Z
  #38 = InterfaceMethodref #2.#37         // scala/math/PartialOrdering.gteq:(Ljava/lang/Object;Ljava/lang/Object;)Z
  #39 = Utf8               Ljava/lang/Object;
  #40 = NameAndType        #30:#31        // lteq:(Ljava/lang/Object;Ljava/lang/Object;)Z
  #41 = InterfaceMethodref #2.#40         // scala/math/PartialOrdering.lteq:(Ljava/lang/Object;Ljava/lang/Object;)Z
  #42 = Utf8               this
  #43 = Utf8               lt$
  #44 = Utf8               lt
  #45 = NameAndType        #44:#31        // lt:(Ljava/lang/Object;Ljava/lang/Object;)Z
  #46 = InterfaceMethodref #2.#45         // scala/math/PartialOrdering.lt:(Ljava/lang/Object;Ljava/lang/Object;)Z
  #47 = Utf8               equiv
  #48 = NameAndType        #47:#31        // equiv:(Ljava/lang/Object;Ljava/lang/Object;)Z
  #49 = InterfaceMethodref #2.#48         // scala/math/PartialOrdering.equiv:(Ljava/lang/Object;Ljava/lang/Object;)Z
  #50 = Utf8               gt$
  #51 = Utf8               gt
  #52 = NameAndType        #51:#31        // gt:(Ljava/lang/Object;Ljava/lang/Object;)Z
  #53 = InterfaceMethodref #2.#52         // scala/math/PartialOrdering.gt:(Ljava/lang/Object;Ljava/lang/Object;)Z
  #54 = Utf8               equiv$
  #55 = Utf8               reverse$
  #56 = Utf8               reverse
  #57 = Utf8               ()Lscala/math/PartialOrdering;
  #58 = NameAndType        #56:#57        // reverse:()Lscala/math/PartialOrdering;
  #59 = InterfaceMethodref #2.#58         // scala/math/PartialOrdering.reverse:()Lscala/math/PartialOrdering;
  #60 = Utf8               ()Lscala/math/PartialOrdering<TT;>;
  #61 = Utf8               <init>
  #62 = Utf8               (Lscala/math/PartialOrdering;)V
  #63 = NameAndType        #61:#62        // "<init>":(Lscala/math/PartialOrdering;)V
  #64 = Methodref          #13.#63        // scala/math/PartialOrdering$$anon$1."<init>":(Lscala/math/PartialOrdering;)V
  #65 = Utf8               $init$
  #66 = Utf8               Code
  #67 = Utf8               LineNumberTable
  #68 = Utf8               LocalVariableTable
  #69 = Utf8               Signature
  #70 = Utf8               MethodParameters
  #71 = Utf8               StackMapTable
  #72 = Utf8               InnerClasses
  #73 = Utf8               SourceFile
  #74 = Utf8               RuntimeVisibleAnnotations
  #75 = Utf8               ScalaInlineInfo
  #76 = Utf8               ScalaSig
{
  public static <T extends java.lang.Object> scala.math.PartialOrdering<T> apply(scala.math.PartialOrdering<T>);
    descriptor: (Lscala/math/PartialOrdering;)Lscala/math/PartialOrdering;
    flags: (0x0009) ACC_PUBLIC, ACC_STATIC
    Code:
      stack=1, locals=1, args_size=1
         0: getstatic     #23                 // Field scala/math/PartialOrdering$.MODULE$:Lscala/math/PartialOrdering$;
         3: pop
         4: aload_0
         5: areturn
      LineNumberTable:
        line 87: 4
      LocalVariableTable:
        Start  Length  Slot  Name   Signature
            0       6     0    ev   Lscala/math/PartialOrdering;
    Signature: #16                          // <T:Ljava/lang/Object;>(Lscala/math/PartialOrdering<TT;>;)Lscala/math/PartialOrdering<TT;>;
    MethodParameters:
      Name                           Flags
      ev                             final

  public abstract scala.Option<java.lang.Object> tryCompare(T, T);
    descriptor: (Ljava/lang/Object;Ljava/lang/Object;)Lscala/Option;
    flags: (0x0401) ACC_PUBLIC, ACC_ABSTRACT
    Signature: #27                          // (TT;TT;)Lscala/Option<Ljava/lang/Object;>;
    MethodParameters:
      Name                           Flags
      x                              final
      y                              final

  public abstract boolean lteq(T, T);
    descriptor: (Ljava/lang/Object;Ljava/lang/Object;)Z
    flags: (0x0401) ACC_PUBLIC, ACC_ABSTRACT
    Signature: #32                          // (TT;TT;)Z
    MethodParameters:
      Name                           Flags
      x                              final
      y                              final

  public static boolean gteq$(scala.math.PartialOrdering, java.lang.Object, java.lang.Object);
    descriptor: (Lscala/math/PartialOrdering;Ljava/lang/Object;Ljava/lang/Object;)Z
    flags: (0x1009) ACC_PUBLIC, ACC_STATIC, ACC_SYNTHETIC
    Code:
      stack=3, locals=3, args_size=3
         0: aload_0
         1: aload_1
         2: aload_2
         3: invokespecial #38                 // InterfaceMethod gteq:(Ljava/lang/Object;Ljava/lang/Object;)Z
         6: ireturn
      LineNumberTable:
        line 59: 0
      LocalVariableTable:
        Start  Length  Slot  Name   Signature
            0       7     0 $this   Lscala/math/PartialOrdering;
            0       7     1     x   Ljava/lang/Object;
            0       7     2     y   Ljava/lang/Object;
    MethodParameters:
      Name                           Flags
      $this                          final synthetic
      x                              final
      y                              final

  public default boolean gteq(T, T);
    descriptor: (Ljava/lang/Object;Ljava/lang/Object;)Z
    flags: (0x0001) ACC_PUBLIC
    Code:
      stack=3, locals=3, args_size=3
         0: aload_0
         1: aload_2
         2: aload_1
         3: invokeinterface #41,  3           // InterfaceMethod lteq:(Ljava/lang/Object;Ljava/lang/Object;)Z
         8: ireturn
      LineNumberTable:
        line 59: 0
      LocalVariableTable:
        Start  Length  Slot  Name   Signature
            0       9     0  this   Lscala/math/PartialOrdering;
            0       9     1     x   Ljava/lang/Object;
            0       9     2     y   Ljava/lang/Object;
    Signature: #32                          // (TT;TT;)Z
    MethodParameters:
      Name                           Flags
      x                              final
      y                              final

  public static boolean lt$(scala.math.PartialOrdering, java.lang.Object, java.lang.Object);
    descriptor: (Lscala/math/PartialOrdering;Ljava/lang/Object;Ljava/lang/Object;)Z
    flags: (0x1009) ACC_PUBLIC, ACC_STATIC, ACC_SYNTHETIC
    Code:
      stack=3, locals=3, args_size=3
         0: aload_0
         1: aload_1
         2: aload_2
         3: invokespecial #46                 // InterfaceMethod lt:(Ljava/lang/Object;Ljava/lang/Object;)Z
         6: ireturn
      LineNumberTable:
        line 64: 0
      LocalVariableTable:
        Start  Length  Slot  Name   Signature
            0       7     0 $this   Lscala/math/PartialOrdering;
            0       7     1     x   Ljava/lang/Object;
            0       7     2     y   Ljava/lang/Object;
    MethodParameters:
      Name                           Flags
      $this                          final synthetic
      x                              final
      y                              final

  public default boolean lt(T, T);
    descriptor: (Ljava/lang/Object;Ljava/lang/Object;)Z
    flags: (0x0001) ACC_PUBLIC
    Code:
      stack=3, locals=3, args_size=3
         0: aload_0
         1: aload_1
         2: aload_2
         3: invokeinterface #41,  3           // InterfaceMethod lteq:(Ljava/lang/Object;Ljava/lang/Object;)Z
         8: ifeq          24
        11: aload_0
        12: aload_1
        13: aload_2
        14: invokeinterface #49,  3           // InterfaceMethod equiv:(Ljava/lang/Object;Ljava/lang/Object;)Z
        19: ifne          24
        22: iconst_1
        23: ireturn
        24: iconst_0
        25: ireturn
      StackMapTable: number_of_entries = 1
        frame_type = 24 /* same */
      LineNumberTable:
        line 64: 0
      LocalVariableTable:
        Start  Length  Slot  Name   Signature
            0      26     0  this   Lscala/math/PartialOrdering;
            0      26     1     x   Ljava/lang/Object;
            0      26     2     y   Ljava/lang/Object;
    Signature: #32                          // (TT;TT;)Z
    MethodParameters:
      Name                           Flags
      x                              final
      y                              final

  public static boolean gt$(scala.math.PartialOrdering, java.lang.Object, java.lang.Object);
    descriptor: (Lscala/math/PartialOrdering;Ljava/lang/Object;Ljava/lang/Object;)Z
    flags: (0x1009) ACC_PUBLIC, ACC_STATIC, ACC_SYNTHETIC
    Code:
      stack=3, locals=3, args_size=3
         0: aload_0
         1: aload_1
         2: aload_2
         3: invokespecial #53                 // InterfaceMethod gt:(Ljava/lang/Object;Ljava/lang/Object;)Z
         6: ireturn
      LineNumberTable:
        line 69: 0
      LocalVariableTable:
        Start  Length  Slot  Name   Signature
            0       7     0 $this   Lscala/math/PartialOrdering;
            0       7     1     x   Ljava/lang/Object;
            0       7     2     y   Ljava/lang/Object;
    MethodParameters:
      Name                           Flags
      $this                          final synthetic
      x                              final
      y                              final

  public default boolean gt(T, T);
    descriptor: (Ljava/lang/Object;Ljava/lang/Object;)Z
    flags: (0x0001) ACC_PUBLIC
    Code:
      stack=3, locals=3, args_size=3
         0: aload_0
         1: aload_1
         2: aload_2
         3: invokeinterface #38,  3           // InterfaceMethod gteq:(Ljava/lang/Object;Ljava/lang/Object;)Z
         8: ifeq          24
        11: aload_0
        12: aload_1
        13: aload_2
        14: invokeinterface #49,  3           // InterfaceMethod equiv:(Ljava/lang/Object;Ljava/lang/Object;)Z
        19: ifne          24
        22: iconst_1
        23: ireturn
        24: iconst_0
        25: ireturn
      StackMapTable: number_of_entries = 1
        frame_type = 24 /* same */
      LineNumberTable:
        line 69: 0
      LocalVariableTable:
        Start  Length  Slot  Name   Signature
            0      26     0  this   Lscala/math/PartialOrdering;
            0      26     1     x   Ljava/lang/Object;
            0      26     2     y   Ljava/lang/Object;
    Signature: #32                          // (TT;TT;)Z
    MethodParameters:
      Name                           Flags
      x                              final
      y                              final

  public static boolean equiv$(scala.math.PartialOrdering, java.lang.Object, java.lang.Object);
    descriptor: (Lscala/math/PartialOrdering;Ljava/lang/Object;Ljava/lang/Object;)Z
    flags: (0x1009) ACC_PUBLIC, ACC_STATIC, ACC_SYNTHETIC
    Code:
      stack=3, locals=3, args_size=3
         0: aload_0
         1: aload_1
         2: aload_2
         3: invokespecial #49                 // InterfaceMethod equiv:(Ljava/lang/Object;Ljava/lang/Object;)Z
         6: ireturn
      LineNumberTable:
        line 73: 0
      LocalVariableTable:
        Start  Length  Slot  Name   Signature
            0       7     0 $this   Lscala/math/PartialOrdering;
            0       7     1     x   Ljava/lang/Object;
            0       7     2     y   Ljava/lang/Object;
    MethodParameters:
      Name                           Flags
      $this                          final synthetic
      x                              final
      y                              final

  public default boolean equiv(T, T);
    descriptor: (Ljava/lang/Object;Ljava/lang/Object;)Z
    flags: (0x0001) ACC_PUBLIC
    Code:
      stack=3, locals=3, args_size=3
         0: aload_0
         1: aload_1
         2: aload_2
         3: invokeinterface #41,  3           // InterfaceMethod lteq:(Ljava/lang/Object;Ljava/lang/Object;)Z
         8: ifeq          24
        11: aload_0
        12: aload_2
        13: aload_1
        14: invokeinterface #41,  3           // InterfaceMethod lteq:(Ljava/lang/Object;Ljava/lang/Object;)Z
        19: ifeq          24
        22: iconst_1
        23: ireturn
        24: iconst_0
        25: ireturn
      StackMapTable: number_of_entries = 1
        frame_type = 24 /* same */
      LineNumberTable:
        line 73: 0
      LocalVariableTable:
        Start  Length  Slot  Name   Signature
            0      26     0  this   Lscala/math/PartialOrdering;
            0      26     1     x   Ljava/lang/Object;
            0      26     2     y   Ljava/lang/Object;
    Signature: #32                          // (TT;TT;)Z
    MethodParameters:
      Name                           Flags
      x                              final
      y                              final

  public static scala.math.PartialOrdering reverse$(scala.math.PartialOrdering);
    descriptor: (Lscala/math/PartialOrdering;)Lscala/math/PartialOrdering;
    flags: (0x1009) ACC_PUBLIC, ACC_STATIC, ACC_SYNTHETIC
    Code:
      stack=1, locals=1, args_size=1
         0: aload_0
         1: invokespecial #59                 // InterfaceMethod reverse:()Lscala/math/PartialOrdering;
         4: areturn
      LineNumberTable:
        line 75: 0
      LocalVariableTable:
        Start  Length  Slot  Name   Signature
            0       5     0 $this   Lscala/math/PartialOrdering;
    MethodParameters:
      Name                           Flags
      $this                          final synthetic

  public default scala.math.PartialOrdering<T> reverse();
    descriptor: ()Lscala/math/PartialOrdering;
    flags: (0x0001) ACC_PUBLIC
    Code:
      stack=3, locals=1, args_size=1
         0: new           #13                 // class scala/math/PartialOrdering$$anon$1
         3: dup
         4: aload_0
         5: invokespecial #64                 // Method scala/math/PartialOrdering$$anon$1."<init>":(Lscala/math/PartialOrdering;)V
         8: areturn
      LineNumberTable:
        line 75: 0
      LocalVariableTable:
        Start  Length  Slot  Name   Signature
            0       9     0  this   Lscala/math/PartialOrdering;
    Signature: #60                          // ()Lscala/math/PartialOrdering<TT;>;

  public static void $init$(scala.math.PartialOrdering);
    descriptor: (Lscala/math/PartialOrdering;)V
    flags: (0x0009) ACC_PUBLIC, ACC_STATIC
    Code:
      stack=0, locals=1, args_size=1
         0: return
      LineNumberTable:
        line 41: 0
      LocalVariableTable:
        Start  Length  Slot  Name   Signature
            0       1     0 $this   Lscala/math/PartialOrdering;
    MethodParameters:
      Name                           Flags
      $this                          final synthetic
}
InnerClasses:
  public final #13;                       // class scala/math/PartialOrdering$$anon$1
Signature: #3                           // <T:Ljava/lang/Object;>Ljava/lang/Object;Lscala/math/Equiv<TT;>;
SourceFile: "PartialOrdering.scala"
RuntimeVisibleAnnotations:
  0: #9(#10=s#11)
    scala.reflect.ScalaSignature(
      bytes="\u0006\u0005U4qAD\b\u0011\u0002\u0007\u0005A\u0003C\u0003*\u0001\u0011\u0005!\u0006C\u0003/\u0001\u0019\u0005q\u0006C\u0003;\u0001\u0019\u00051\bC\u0003B\u0001\u0011\u0005!\tC\u0003F\u0001\u0011\u0005a\tC\u0003J\u0001\u0011\u0005!\nC\u0003N\u0001\u0011\u0005a\nC\u0003R\u0001\u0011\u0005!kB\u0003U\u001f!\u0005QKB\u0003\u000f\u001f!\u0005a\u000bC\u0003`\u0015\u0011\u0005\u0001\rC\u0003b\u0015\u0011\u0005!\rC\u0004n\u0015\u0005\u0005I\u0011\u00028\u0003\u001fA\u000b\'\u000f^5bY>\u0013H-\u001a:j]\u001eT!\u0001E\t\u0002\t5\fG\u000f\u001b\u0006\u0002%\u0005)1oY1mC\u000e\u0001QCA\u000b!\'\r\u0001aC\u0007\t\u0003/ai\u0011!E\u0005\u00033E\u0011a!\u00118z%\u00164\u0007cA\u000e\u001d=5\tq\"\u0003\u0002\u001e\u001f\t)Q)];jmB\u0011q\u0004\t\u0007\u0001\t\u0015\t\u0003A1\u0001#\u0005\u0005!\u0016CA\u0012\'!\t9B%\u0003\u0002&#\t9aj\u001c;iS:<\u0007CA\f(\u0013\tA\u0013CA\u0002B]f\fa\u0001J5oSR$C#A\u0016\u0011\u0005]a\u0013BA\u0017\u0012\u0005\u0011)f.\u001b;\u0002\u0015Q\u0014\u0018pQ8na\u0006\u0014X\rF\u00021ma\u00022aF\u00194\u0013\t\u0011\u0014C\u0001\u0004PaRLwN\u001c\t\u0003/QJ!!N\t\u0003\u0007%sG\u000fC\u00038\u0005\u0001\u0007a$A\u0001y\u0011\u0015I$\u00011\u0001\u001f\u0003\u0005I\u0018\u0001\u00027uKF$2\u0001P A!\t9R(\u0003\u0002?#\t9!i\\8mK\u0006t\u0007\"B\u001c\u0004\u0001\u0004q\u0002\"B\u001d\u0004\u0001\u0004q\u0012\u0001B4uKF$2\u0001P\"E\u0011\u00159D\u00011\u0001\u001f\u0011\u0015ID\u00011\u0001\u001f\u0003\taG\u000fF\u0002=\u000f\"CQaN\u0003A\u0002yAQ!O\u0003A\u0002y\t!a\u001a;\u0015\u0007qZE\nC\u00038\r\u0001\u0007a\u0004C\u0003:\r\u0001\u0007a$A\u0003fcVLg\u000fF\u0002=\u001fBCQaN\u0004A\u0002yAQ!O\u0004A\u0002y\tqA]3wKJ\u001cX-F\u0001T!\rY\u0002AH\u0001\u0010!\u0006\u0014H/[1m\u001fJ$WM]5oOB\u00111DC\n\u0004\u0015Y9\u0006C\u0001-^\u001b\u0005I&B\u0001.\\\u0003\tIwNC\u0001]\u0003\u0011Q\u0017M^1\n\u0005yK&\u0001D*fe&\fG.\u001b>bE2,\u0017A\u0002\u001fj]&$h\bF\u0001V\u0003\u0015\t\u0007\u000f\u001d7z+\t\u0019g\r\u0006\u0002eOB\u00191\u0004A3\u0011\u0005}1G!B\u0011\r\u0005\u0004\u0011\u0003\"\u00025\r\u0001\b!\u0017AA3wQ\ta!\u000e\u0005\u0002\u0018W&\u0011A.\u0005\u0002\u0007S:d\u0017N\\3\u0002\u0019]\u0014\u0018\u000e^3SKBd\u0017mY3\u0015\u0003=\u0004\"\u0001]:\u000e\u0003ET!A].\u0002\t1\fgnZ\u0005\u0003iF\u0014aa\u00142kK\u000e$\b"
    )
  ScalaInlineInfo: length = 0x45 (unknown attribute)
   01 00 00 0D 00 41 00 3E 01 00 2F 00 1F 00 00 36
   00 22 01 00 33 00 1F 00 00 32 00 22 01 00 24 00
   1F 00 00 21 00 22 01 00 2C 00 1F 00 00 2B 00 22
   01 00 1E 00 1F 00 00 38 00 39 00 00 37 00 0F 01
   00 19 00 1A 00
  ScalaSig: length = 0x3 (unknown attribute)
   05 02 00
