Classfile /Users/mw/Projects/slang-braindump/.jar/jar8/assemble/slang-braindump/assemble/content/org/scalatest/tools/AboutJDialog.class
  Last modified May 29, 2022; size 6956 bytes
  SHA-256 checksum 80f3c7a4c6c27e2e9a79a9f4d28bbc560891ba84bb64b4261dfe8f4580f1732b
  Compiled from "AboutJDialog.scala"
public class org.scalatest.tools.AboutJDialog extends javax.swing.JDialog
  minor version: 0
  major version: 52
  flags: (0x0021) ACC_PUBLIC, ACC_SUPER
  this_class: #2                          // org/scalatest/tools/AboutJDialog
  super_class: #4                         // javax/swing/JDialog
  interfaces: 0, fields: 22, methods: 23, attributes: 4
Constant pool:
    #1 = Utf8               org/scalatest/tools/AboutJDialog
    #2 = Class              #1            // org/scalatest/tools/AboutJDialog
    #3 = Utf8               javax/swing/JDialog
    #4 = Class              #3            // javax/swing/JDialog
    #5 = Utf8               AboutJDialog.scala
    #6 = Utf8               Lscala/reflect/ScalaSignature;
    #7 = Utf8               bytes
    #8 = Utf8               \u0006\u0005\u0005ua!\u0002\u00192\u0001M:\u0004\u0002\u0003!\u0001\u0005\u0003\u0005\u000b\u0011\u0002\"\t\u0011\u0015\u0003!\u0011!Q\u0001\n\u0019CQa\u0015\u0001\u0005\u0002QCq!\u0017\u0001C\u0002\u0013\u0005!\f\u0003\u0004\\\u0001\u0001\u0006IA\u0012\u0005\b9\u0002\u0011\r\u0011\"\u0001[\u0011\u0019i\u0006\u0001)A\u0005\r\"9a\f\u0001b\u0001\n\u0003Q\u0006BB0\u0001A\u0003%a\tC\u0004a\u0001\t\u0007I\u0011\u0001.\t\r\u0005\u0004\u0001\u0015!\u0003G\u0011\u001d\u0011\u0007A1A\u0005\u0002iCaa\u0019\u0001!\u0002\u00131\u0005b\u00023\u0001\u0005\u0004%\tA\u0017\u0005\u0007K\u0002\u0001\u000b\u0011\u0002$\t\u000f\u0019\u0004!\u0019!C\u00015\"1q\r\u0001Q\u0001\n\u0019Cq\u0001\u001b\u0001C\u0002\u0013\u0005!\f\u0003\u0004j\u0001\u0001\u0006IA\u0012\u0005\bU\u0002\u0011\r\u0011\"\u0001[\u0011\u0019Y\u0007\u0001)A\u0005\r\"9A\u000e\u0001b\u0001\n\u0003i\u0007BB9\u0001A\u0003%a\u000eC\u0004s\u0001\t\u0007I\u0011A7\t\rM\u0004\u0001\u0015!\u0003o\u0011\u001d!\bA1A\u0005\u00025Da!\u001e\u0001!\u0002\u0013q\u0007b\u0002<\u0001\u0005\u0004%\t!\u001c\u0005\u0007o\u0002\u0001\u000b\u0011\u00028\t\u000fa\u0004!\u0019!C\u0001[\"1\u0011\u0010\u0001Q\u0001\n9DqA\u001f\u0001C\u0002\u0013\u0005Q\u000e\u0003\u0004|\u0001\u0001\u0006IA\u001c\u0005\by\u0002\u0011\r\u0011\"\u0001n\u0011\u0019i\b\u0001)A\u0005]\"9a\u0010\u0001b\u0001\n\u0003i\u0007BB@\u0001A\u0003%a\u000eC\u0005\u0002\u0002\u0001\u0011\r\u0011\"\u0001\u0002\u0004!A\u00111\u0002\u0001!\u0002\u0013\t)\u0001C\u0005\u0002\u000e\u0001\u0011\r\u0011\"\u0001\u0002\u0004!A\u0011q\u0002\u0001!\u0002\u0013\t)\u0001C\u0005\u0002\u0012\u0001\u0011\r\u0011\"\u0001\u0002\u0004!A\u00111\u0003\u0001!\u0002\u0013\t)\u0001C\u0005\u0002\u0016\u0001\u0011\r\u0011\"\u0001\u0002\u0004!A\u0011q\u0003\u0001!\u0002\u0013\t)\u0001C\u0005\u0002\u001a\u0001\u0011\r\u0011\"\u0001\u0002\u0004!A\u00111\u0004\u0001!\u0002\u0013\t)A\u0001\u0007BE>,HO\u0013#jC2|wM\u0003\u00023g\u0005)Ao\\8mg*\u0011A\'N\u0001\ng\u000e\fG.\u0019;fgRT\u0011AN\u0001\u0004_J<7C\u0001\u00019!\tId(D\u0001;\u0015\tYD(A\u0003to&twMC\u0001>\u0003\u0015Q\u0017M^1y\u0013\ty$HA\u0004K\t&\fGn\\4\u0002\u000b=<h.\u001a:\u0004\u0001A\u0011\u0011hQ\u0005\u0003\tj\u0012aA\u0013$sC6,\u0017!\u0002;ji2,\u0007CA$Q\u001d\tAe\n\u0005\u0002J\u00196\t!J\u0003\u0002L\u0003\u00061AH]8pizR\u0011!T\u0001\u0006g\u000e\fG.Y\u0005\u0003\u001f2\u000ba\u0001\u0015:fI\u00164\u0017BA)S\u0005\u0019\u0019FO]5oO*\u0011q\nT\u0001\u0007y%t\u0017\u000e\u001e \u0015\u0007U;\u0006\f\u0005\u0002W\u00015\t\u0011\u0007C\u0003A\u0007\u0001\u0007!\tC\u0003F\u0007\u0001\u0007a)\u0001\u0003oC6,W#\u0001$\u0002\u000b9\fW.\u001a\u0011\u0002\u0013\r|\u0007/\u001f:jO\"$\u0018AC2paf\u0014\u0018n\u001a5uA\u0005AQn\u001c:f\u0013:4w.A\u0005n_J,\u0017J\u001c4pA\u0005\u0019QO\u001d7\u0002\tU\u0014H\u000eI\u0001\bm\u0016\u00148/[8o\u0003!1XM]:j_:\u0004\u0013\u0001D:dC2\fg+\u001a:tS>t\u0017!D:dC2\fg+\u001a:tS>t\u0007%\u0001\u0004sK\u0006\u001cxN\\\u0001\be\u0016\f7o\u001c8!\u0003)!(/\u00193f[\u0006\u00148n]\u0001\fiJ\fG-Z7be.\u001c\b%A\u0004d_6\u0004\u0018M\\=\u0002\u0011\r|W\u000e]1os\u0002\n\u0011B\\1nK2\u000b\'-\u001a7\u0016\u00039\u0004\"!O8\n\u0005AT$A\u0002&MC\n,G.\u0001\u0006oC6,G*\u00192fY\u0002\nabY8qsJLw\r\u001b;MC\n,G.A\bd_BL(/[4ii2\u000b\'-\u001a7!\u0003!)(\u000f\u001c\'bE\u0016d\u0017!C;sY2\u000b\'-\u001a7!\u00035iwN]3J]\u001a|G*\u00192fY\u0006qQn\u001c:f\u0013:4w\u000eT1cK2\u0004\u0013\u0001\u0004<feNLwN\u001c\'bE\u0016d\u0017!\u0004<feNLwN\u001c\'bE\u0016d\u0007%A\u0006sK\u0006\u001cxN\u001c\'bE\u0016d\u0017\u0001\u0004:fCN|g\u000eT1cK2\u0004\u0013a\u0004;sC\u0012,W.\u0019:lg2\u000b\'-\u001a7\u0002!Q\u0014\u0018\rZ3nCJ\\7\u000fT1cK2\u0004\u0013\u0001D2p[B\fg.\u001f\'bE\u0016d\u0017!D2p[B\fg.\u001f\'bE\u0016d\u0007%A\u0006o_J$\bN\u0013)b]\u0016dWCAA\u0003!\rI\u0014qA\u0005\u0004\u0003\u0013Q$A\u0002&QC:,G.\u0001\u0007o_J$\bN\u0013)b]\u0016d\u0007%\u0001\ndK:$XM\u001d\"piR|WN\u0013)b]\u0016d\u0017aE2f]R,\'OQ8ui>l\'\nU1oK2\u0004\u0013\u0001D2f]R,\'O\u0013)b]\u0016d\u0017!D2f]R,\'O\u0013)b]\u0016d\u0007%\u0001\rd_BL(/[4iiR\u0013\u0018\rZ3nCJ\\\'\nU1oK2\f\u0011dY8qsJLw\r\u001b;Ue\u0006$W-\\1sW*\u0003\u0016M\\3mA\u0005Y\u0011MY8vi*\u0003\u0016M\\3m\u00031\t\'m\\;u\u0015B\u000bg.\u001a7!\u0001
    #9 = Utf8               name
   #10 = Utf8               Ljava/lang/String;
   #11 = Utf8               copyright
   #12 = Utf8               moreInfo
   #13 = Utf8               url
   #14 = Utf8               version
   #15 = Utf8               scalaVersion
   #16 = Utf8               reason
   #17 = Utf8               trademarks
   #18 = Utf8               company
   #19 = Utf8               nameLabel
   #20 = Utf8               Ljavax/swing/JLabel;
   #21 = Utf8               copyrightLabel
   #22 = Utf8               urlLabel
   #23 = Utf8               moreInfoLabel
   #24 = Utf8               versionLabel
   #25 = Utf8               reasonLabel
   #26 = Utf8               trademarksLabel
   #27 = Utf8               companyLabel
   #28 = Utf8               northJPanel
   #29 = Utf8               Ljavax/swing/JPanel;
   #30 = Utf8               centerBottomJPanel
   #31 = Utf8               centerJPanel
   #32 = Utf8               copyrightTrademarkJPanel
   #33 = Utf8               aboutJPanel
   #34 = Utf8               ()Ljava/lang/String;
   #35 = NameAndType        #9:#10        // name:Ljava/lang/String;
   #36 = Fieldref           #2.#35        // org/scalatest/tools/AboutJDialog.name:Ljava/lang/String;
   #37 = Utf8               this
   #38 = Utf8               Lorg/scalatest/tools/AboutJDialog;
   #39 = NameAndType        #11:#10       // copyright:Ljava/lang/String;
   #40 = Fieldref           #2.#39        // org/scalatest/tools/AboutJDialog.copyright:Ljava/lang/String;
   #41 = NameAndType        #12:#10       // moreInfo:Ljava/lang/String;
   #42 = Fieldref           #2.#41        // org/scalatest/tools/AboutJDialog.moreInfo:Ljava/lang/String;
   #43 = NameAndType        #13:#10       // url:Ljava/lang/String;
   #44 = Fieldref           #2.#43        // org/scalatest/tools/AboutJDialog.url:Ljava/lang/String;
   #45 = NameAndType        #14:#10       // version:Ljava/lang/String;
   #46 = Fieldref           #2.#45        // org/scalatest/tools/AboutJDialog.version:Ljava/lang/String;
   #47 = NameAndType        #15:#10       // scalaVersion:Ljava/lang/String;
   #48 = Fieldref           #2.#47        // org/scalatest/tools/AboutJDialog.scalaVersion:Ljava/lang/String;
   #49 = NameAndType        #16:#10       // reason:Ljava/lang/String;
   #50 = Fieldref           #2.#49        // org/scalatest/tools/AboutJDialog.reason:Ljava/lang/String;
   #51 = NameAndType        #17:#10       // trademarks:Ljava/lang/String;
   #52 = Fieldref           #2.#51        // org/scalatest/tools/AboutJDialog.trademarks:Ljava/lang/String;
   #53 = NameAndType        #18:#10       // company:Ljava/lang/String;
   #54 = Fieldref           #2.#53        // org/scalatest/tools/AboutJDialog.company:Ljava/lang/String;
   #55 = Utf8               ()Ljavax/swing/JLabel;
   #56 = NameAndType        #19:#20       // nameLabel:Ljavax/swing/JLabel;
   #57 = Fieldref           #2.#56        // org/scalatest/tools/AboutJDialog.nameLabel:Ljavax/swing/JLabel;
   #58 = NameAndType        #21:#20       // copyrightLabel:Ljavax/swing/JLabel;
   #59 = Fieldref           #2.#58        // org/scalatest/tools/AboutJDialog.copyrightLabel:Ljavax/swing/JLabel;
   #60 = NameAndType        #22:#20       // urlLabel:Ljavax/swing/JLabel;
   #61 = Fieldref           #2.#60        // org/scalatest/tools/AboutJDialog.urlLabel:Ljavax/swing/JLabel;
   #62 = NameAndType        #23:#20       // moreInfoLabel:Ljavax/swing/JLabel;
   #63 = Fieldref           #2.#62        // org/scalatest/tools/AboutJDialog.moreInfoLabel:Ljavax/swing/JLabel;
   #64 = NameAndType        #24:#20       // versionLabel:Ljavax/swing/JLabel;
   #65 = Fieldref           #2.#64        // org/scalatest/tools/AboutJDialog.versionLabel:Ljavax/swing/JLabel;
   #66 = NameAndType        #25:#20       // reasonLabel:Ljavax/swing/JLabel;
   #67 = Fieldref           #2.#66        // org/scalatest/tools/AboutJDialog.reasonLabel:Ljavax/swing/JLabel;
   #68 = NameAndType        #26:#20       // trademarksLabel:Ljavax/swing/JLabel;
   #69 = Fieldref           #2.#68        // org/scalatest/tools/AboutJDialog.trademarksLabel:Ljavax/swing/JLabel;
   #70 = NameAndType        #27:#20       // companyLabel:Ljavax/swing/JLabel;
   #71 = Fieldref           #2.#70        // org/scalatest/tools/AboutJDialog.companyLabel:Ljavax/swing/JLabel;
   #72 = Utf8               ()Ljavax/swing/JPanel;
   #73 = NameAndType        #28:#29       // northJPanel:Ljavax/swing/JPanel;
   #74 = Fieldref           #2.#73        // org/scalatest/tools/AboutJDialog.northJPanel:Ljavax/swing/JPanel;
   #75 = NameAndType        #30:#29       // centerBottomJPanel:Ljavax/swing/JPanel;
   #76 = Fieldref           #2.#75        // org/scalatest/tools/AboutJDialog.centerBottomJPanel:Ljavax/swing/JPanel;
   #77 = NameAndType        #31:#29       // centerJPanel:Ljavax/swing/JPanel;
   #78 = Fieldref           #2.#77        // org/scalatest/tools/AboutJDialog.centerJPanel:Ljavax/swing/JPanel;
   #79 = NameAndType        #32:#29       // copyrightTrademarkJPanel:Ljavax/swing/JPanel;
   #80 = Fieldref           #2.#79        // org/scalatest/tools/AboutJDialog.copyrightTrademarkJPanel:Ljavax/swing/JPanel;
   #81 = NameAndType        #33:#29       // aboutJPanel:Ljavax/swing/JPanel;
   #82 = Fieldref           #2.#81        // org/scalatest/tools/AboutJDialog.aboutJPanel:Ljavax/swing/JPanel;
   #83 = Utf8               <init>
   #84 = Utf8               (Ljavax/swing/JFrame;Ljava/lang/String;)V
   #85 = Utf8               owner
   #86 = Utf8               title
   #87 = Utf8               (Ljava/awt/Frame;Ljava/lang/String;)V
   #88 = NameAndType        #83:#87       // "<init>":(Ljava/awt/Frame;Ljava/lang/String;)V
   #89 = Methodref          #4.#88        // javax/swing/JDialog."<init>":(Ljava/awt/Frame;Ljava/lang/String;)V
   #90 = Utf8               org/scalatest/Resources$
   #91 = Class              #90           // org/scalatest/Resources$
   #92 = Utf8               MODULE$
   #93 = Utf8               Lorg/scalatest/Resources$;
   #94 = NameAndType        #92:#93       // MODULE$:Lorg/scalatest/Resources$;
   #95 = Fieldref           #91.#94       // org/scalatest/Resources$.MODULE$:Lorg/scalatest/Resources$;
   #96 = Utf8               AppName
   #97 = NameAndType        #96:#34       // AppName:()Ljava/lang/String;
   #98 = Methodref          #91.#97       // org/scalatest/Resources$.AppName:()Ljava/lang/String;
   #99 = Utf8               AppCopyright
  #100 = NameAndType        #99:#34       // AppCopyright:()Ljava/lang/String;
  #101 = Methodref          #91.#100      // org/scalatest/Resources$.AppCopyright:()Ljava/lang/String;
  #102 = Utf8               MoreInfo
  #103 = NameAndType        #102:#34      // MoreInfo:()Ljava/lang/String;
  #104 = Methodref          #91.#103      // org/scalatest/Resources$.MoreInfo:()Ljava/lang/String;
  #105 = Utf8               AppURL
  #106 = NameAndType        #105:#34      // AppURL:()Ljava/lang/String;
  #107 = Methodref          #91.#106      // org/scalatest/Resources$.AppURL:()Ljava/lang/String;
  #108 = Utf8               org/scalatest/ScalaTestVersions$
  #109 = Class              #108          // org/scalatest/ScalaTestVersions$
  #110 = Utf8               Lorg/scalatest/ScalaTestVersions$;
  #111 = NameAndType        #92:#110      // MODULE$:Lorg/scalatest/ScalaTestVersions$;
  #112 = Fieldref           #109.#111     // org/scalatest/ScalaTestVersions$.MODULE$:Lorg/scalatest/ScalaTestVersions$;
  #113 = Utf8               ScalaTestVersion
  #114 = NameAndType        #113:#34      // ScalaTestVersion:()Ljava/lang/String;
  #115 = Methodref          #109.#114     // org/scalatest/ScalaTestVersions$.ScalaTestVersion:()Ljava/lang/String;
  #116 = Utf8               BuiltForScalaVersion
  #117 = NameAndType        #116:#34      // BuiltForScalaVersion:()Ljava/lang/String;
  #118 = Methodref          #109.#117     // org/scalatest/ScalaTestVersions$.BuiltForScalaVersion:()Ljava/lang/String;
  #119 = Utf8               Reason
  #120 = NameAndType        #119:#34      // Reason:()Ljava/lang/String;
  #121 = Methodref          #91.#120      // org/scalatest/Resources$.Reason:()Ljava/lang/String;
  #122 = Utf8               Trademarks
  #123 = NameAndType        #122:#34      // Trademarks:()Ljava/lang/String;
  #124 = Methodref          #91.#123      // org/scalatest/Resources$.Trademarks:()Ljava/lang/String;
  #125 = Utf8               ArtimaInc
  #126 = NameAndType        #125:#34      // ArtimaInc:()Ljava/lang/String;
  #127 = Methodref          #91.#126      // org/scalatest/Resources$.ArtimaInc:()Ljava/lang/String;
  #128 = Utf8               javax/swing/JLabel
  #129 = Class              #128          // javax/swing/JLabel
  #130 = NameAndType        #9:#34        // name:()Ljava/lang/String;
  #131 = Methodref          #2.#130       // org/scalatest/tools/AboutJDialog.name:()Ljava/lang/String;
  #132 = Utf8               (Ljava/lang/String;I)V
  #133 = NameAndType        #83:#132      // "<init>":(Ljava/lang/String;I)V
  #134 = Methodref          #129.#133     // javax/swing/JLabel."<init>":(Ljava/lang/String;I)V
  #135 = NameAndType        #11:#34       // copyright:()Ljava/lang/String;
  #136 = Methodref          #2.#135       // org/scalatest/tools/AboutJDialog.copyright:()Ljava/lang/String;
  #137 = NameAndType        #13:#34       // url:()Ljava/lang/String;
  #138 = Methodref          #2.#137       // org/scalatest/tools/AboutJDialog.url:()Ljava/lang/String;
  #139 = NameAndType        #12:#34       // moreInfo:()Ljava/lang/String;
  #140 = Methodref          #2.#139       // org/scalatest/tools/AboutJDialog.moreInfo:()Ljava/lang/String;
  #141 = Utf8               java/lang/StringBuilder
  #142 = Class              #141          // java/lang/StringBuilder
  #143 = Integer            19
  #144 = Utf8               (I)V
  #145 = NameAndType        #83:#144      // "<init>":(I)V
  #146 = Methodref          #142.#145     // java/lang/StringBuilder."<init>":(I)V
  #147 = NameAndType        #14:#34       // version:()Ljava/lang/String;
  #148 = Methodref          #2.#147       // org/scalatest/tools/AboutJDialog.version:()Ljava/lang/String;
  #149 = Utf8               append
  #150 = Utf8               (Ljava/lang/String;)Ljava/lang/StringBuilder;
  #151 = NameAndType        #149:#150     // append:(Ljava/lang/String;)Ljava/lang/StringBuilder;
  #152 = Methodref          #142.#151     // java/lang/StringBuilder.append:(Ljava/lang/String;)Ljava/lang/StringBuilder;
  #153 = Utf8                (Built for Scala
  #154 = String             #153          //  (Built for Scala
  #155 = NameAndType        #15:#34       // scalaVersion:()Ljava/lang/String;
  #156 = Methodref          #2.#155       // org/scalatest/tools/AboutJDialog.scalaVersion:()Ljava/lang/String;
  #157 = Utf8               )
  #158 = String             #157          // )
  #159 = Utf8               toString
  #160 = NameAndType        #159:#34      // toString:()Ljava/lang/String;
  #161 = Methodref          #142.#160     // java/lang/StringBuilder.toString:()Ljava/lang/String;
  #162 = NameAndType        #16:#34       // reason:()Ljava/lang/String;
  #163 = Methodref          #2.#162       // org/scalatest/tools/AboutJDialog.reason:()Ljava/lang/String;
  #164 = NameAndType        #17:#34       // trademarks:()Ljava/lang/String;
  #165 = Methodref          #2.#164       // org/scalatest/tools/AboutJDialog.trademarks:()Ljava/lang/String;
  #166 = NameAndType        #18:#34       // company:()Ljava/lang/String;
  #167 = Methodref          #2.#166       // org/scalatest/tools/AboutJDialog.company:()Ljava/lang/String;
  #168 = NameAndType        #19:#55       // nameLabel:()Ljavax/swing/JLabel;
  #169 = Methodref          #2.#168       // org/scalatest/tools/AboutJDialog.nameLabel:()Ljavax/swing/JLabel;
  #170 = Utf8               java/awt/Font
  #171 = Class              #170          // java/awt/Font
  #172 = Utf8               SansSerif
  #173 = String             #172          // SansSerif
  #174 = Utf8               (Ljava/lang/String;II)V
  #175 = NameAndType        #83:#174      // "<init>":(Ljava/lang/String;II)V
  #176 = Methodref          #171.#175     // java/awt/Font."<init>":(Ljava/lang/String;II)V
  #177 = Utf8               setFont
  #178 = Utf8               (Ljava/awt/Font;)V
  #179 = NameAndType        #177:#178     // setFont:(Ljava/awt/Font;)V
  #180 = Methodref          #129.#179     // javax/swing/JLabel.setFont:(Ljava/awt/Font;)V
  #181 = NameAndType        #22:#55       // urlLabel:()Ljavax/swing/JLabel;
  #182 = Methodref          #2.#181       // org/scalatest/tools/AboutJDialog.urlLabel:()Ljavax/swing/JLabel;
  #183 = NameAndType        #25:#55       // reasonLabel:()Ljavax/swing/JLabel;
  #184 = Methodref          #2.#183       // org/scalatest/tools/AboutJDialog.reasonLabel:()Ljavax/swing/JLabel;
  #185 = NameAndType        #27:#55       // companyLabel:()Ljavax/swing/JLabel;
  #186 = Methodref          #2.#185       // org/scalatest/tools/AboutJDialog.companyLabel:()Ljavax/swing/JLabel;
  #187 = NameAndType        #26:#55       // trademarksLabel:()Ljavax/swing/JLabel;
  #188 = Methodref          #2.#187       // org/scalatest/tools/AboutJDialog.trademarksLabel:()Ljavax/swing/JLabel;
  #189 = NameAndType        #21:#55       // copyrightLabel:()Ljavax/swing/JLabel;
  #190 = Methodref          #2.#189       // org/scalatest/tools/AboutJDialog.copyrightLabel:()Ljavax/swing/JLabel;
  #191 = Utf8               java/awt/Color
  #192 = Class              #191          // java/awt/Color
  #193 = Utf8               (III)V
  #194 = NameAndType        #83:#193      // "<init>":(III)V
  #195 = Methodref          #192.#194     // java/awt/Color."<init>":(III)V
  #196 = Utf8               setForeground
  #197 = Utf8               (Ljava/awt/Color;)V
  #198 = NameAndType        #196:#197     // setForeground:(Ljava/awt/Color;)V
  #199 = Methodref          #129.#198     // javax/swing/JLabel.setForeground:(Ljava/awt/Color;)V
  #200 = NameAndType        #24:#55       // versionLabel:()Ljavax/swing/JLabel;
  #201 = Methodref          #2.#200       // org/scalatest/tools/AboutJDialog.versionLabel:()Ljavax/swing/JLabel;
  #202 = Utf8               javax/swing/JPanel
  #203 = Class              #202          // javax/swing/JPanel
  #204 = Utf8               ()V
  #205 = NameAndType        #83:#204      // "<init>":()V
  #206 = Methodref          #203.#205     // javax/swing/JPanel."<init>":()V
  #207 = NameAndType        #28:#72       // northJPanel:()Ljavax/swing/JPanel;
  #208 = Methodref          #2.#207       // org/scalatest/tools/AboutJDialog.northJPanel:()Ljavax/swing/JPanel;
  #209 = Utf8               java/awt/BorderLayout
  #210 = Class              #209          // java/awt/BorderLayout
  #211 = Methodref          #210.#205     // java/awt/BorderLayout."<init>":()V
  #212 = Utf8               setLayout
  #213 = Utf8               (Ljava/awt/LayoutManager;)V
  #214 = NameAndType        #212:#213     // setLayout:(Ljava/awt/LayoutManager;)V
  #215 = Methodref          #203.#214     // javax/swing/JPanel.setLayout:(Ljava/awt/LayoutManager;)V
  #216 = Utf8               North
  #217 = String             #216          // North
  #218 = Utf8               add
  #219 = Utf8               (Ljava/awt/Component;Ljava/lang/Object;)V
  #220 = NameAndType        #218:#219     // add:(Ljava/awt/Component;Ljava/lang/Object;)V
  #221 = Methodref          #203.#220     // javax/swing/JPanel.add:(Ljava/awt/Component;Ljava/lang/Object;)V
  #222 = Utf8               South
  #223 = String             #222          // South
  #224 = NameAndType        #30:#72       // centerBottomJPanel:()Ljavax/swing/JPanel;
  #225 = Methodref          #2.#224       // org/scalatest/tools/AboutJDialog.centerBottomJPanel:()Ljavax/swing/JPanel;
  #226 = Utf8               java/awt/GridLayout
  #227 = Class              #226          // java/awt/GridLayout
  #228 = Utf8               (II)V
  #229 = NameAndType        #83:#228      // "<init>":(II)V
  #230 = Methodref          #227.#229     // java/awt/GridLayout."<init>":(II)V
  #231 = NameAndType        #23:#55       // moreInfoLabel:()Ljavax/swing/JLabel;
  #232 = Methodref          #2.#231       // org/scalatest/tools/AboutJDialog.moreInfoLabel:()Ljavax/swing/JLabel;
  #233 = Utf8               (Ljava/awt/Component;)Ljava/awt/Component;
  #234 = NameAndType        #218:#233     // add:(Ljava/awt/Component;)Ljava/awt/Component;
  #235 = Methodref          #203.#234     // javax/swing/JPanel.add:(Ljava/awt/Component;)Ljava/awt/Component;
  #236 = NameAndType        #31:#72       // centerJPanel:()Ljavax/swing/JPanel;
  #237 = Methodref          #2.#236       // org/scalatest/tools/AboutJDialog.centerJPanel:()Ljavax/swing/JPanel;
  #238 = Utf8               (IIII)V
  #239 = NameAndType        #83:#238      // "<init>":(IIII)V
  #240 = Methodref          #227.#239     // java/awt/GridLayout."<init>":(IIII)V
  #241 = NameAndType        #32:#72       // copyrightTrademarkJPanel:()Ljavax/swing/JPanel;
  #242 = Methodref          #2.#241       // org/scalatest/tools/AboutJDialog.copyrightTrademarkJPanel:()Ljavax/swing/JPanel;
  #243 = NameAndType        #33:#72       // aboutJPanel:()Ljavax/swing/JPanel;
  #244 = Methodref          #2.#243       // org/scalatest/tools/AboutJDialog.aboutJPanel:()Ljavax/swing/JPanel;
  #245 = Methodref          #210.#229     // java/awt/BorderLayout."<init>":(II)V
  #246 = Utf8               Center
  #247 = String             #246          // Center
  #248 = Utf8               javax/swing/border/EmptyBorder
  #249 = Class              #248          // javax/swing/border/EmptyBorder
  #250 = Methodref          #249.#239     // javax/swing/border/EmptyBorder."<init>":(IIII)V
  #251 = Utf8               setBorder
  #252 = Utf8               (Ljavax/swing/border/Border;)V
  #253 = NameAndType        #251:#252     // setBorder:(Ljavax/swing/border/Border;)V
  #254 = Methodref          #203.#253     // javax/swing/JPanel.setBorder:(Ljavax/swing/border/Border;)V
  #255 = Utf8               getContentPane
  #256 = Utf8               ()Ljava/awt/Container;
  #257 = NameAndType        #255:#256     // getContentPane:()Ljava/awt/Container;
  #258 = Methodref          #2.#257       // org/scalatest/tools/AboutJDialog.getContentPane:()Ljava/awt/Container;
  #259 = Utf8               java/awt/Container
  #260 = Class              #259          // java/awt/Container
  #261 = Methodref          #260.#214     // java/awt/Container.setLayout:(Ljava/awt/LayoutManager;)V
  #262 = Utf8               (Ljava/lang/String;Ljava/awt/Component;)Ljava/awt/Component;
  #263 = NameAndType        #218:#262     // add:(Ljava/lang/String;Ljava/awt/Component;)Ljava/awt/Component;
  #264 = Methodref          #260.#263     // java/awt/Container.add:(Ljava/lang/String;Ljava/awt/Component;)Ljava/awt/Component;
  #265 = Utf8               pack
  #266 = NameAndType        #265:#204     // pack:()V
  #267 = Methodref          #2.#266       // org/scalatest/tools/AboutJDialog.pack:()V
  #268 = Utf8               Ljavax/swing/JFrame;
  #269 = Utf8               Code
  #270 = Utf8               LineNumberTable
  #271 = Utf8               LocalVariableTable
  #272 = Utf8               MethodParameters
  #273 = Utf8               SourceFile
  #274 = Utf8               RuntimeVisibleAnnotations
  #275 = Utf8               ScalaInlineInfo
  #276 = Utf8               ScalaSig
{
  private final java.lang.String name;
    descriptor: Ljava/lang/String;
    flags: (0x0012) ACC_PRIVATE, ACC_FINAL

  private final java.lang.String copyright;
    descriptor: Ljava/lang/String;
    flags: (0x0012) ACC_PRIVATE, ACC_FINAL

  private final java.lang.String moreInfo;
    descriptor: Ljava/lang/String;
    flags: (0x0012) ACC_PRIVATE, ACC_FINAL

  private final java.lang.String url;
    descriptor: Ljava/lang/String;
    flags: (0x0012) ACC_PRIVATE, ACC_FINAL

  private final java.lang.String version;
    descriptor: Ljava/lang/String;
    flags: (0x0012) ACC_PRIVATE, ACC_FINAL

  private final java.lang.String scalaVersion;
    descriptor: Ljava/lang/String;
    flags: (0x0012) ACC_PRIVATE, ACC_FINAL

  private final java.lang.String reason;
    descriptor: Ljava/lang/String;
    flags: (0x0012) ACC_PRIVATE, ACC_FINAL

  private final java.lang.String trademarks;
    descriptor: Ljava/lang/String;
    flags: (0x0012) ACC_PRIVATE, ACC_FINAL

  private final java.lang.String company;
    descriptor: Ljava/lang/String;
    flags: (0x0012) ACC_PRIVATE, ACC_FINAL

  private final javax.swing.JLabel nameLabel;
    descriptor: Ljavax/swing/JLabel;
    flags: (0x0012) ACC_PRIVATE, ACC_FINAL

  private final javax.swing.JLabel copyrightLabel;
    descriptor: Ljavax/swing/JLabel;
    flags: (0x0012) ACC_PRIVATE, ACC_FINAL

  private final javax.swing.JLabel urlLabel;
    descriptor: Ljavax/swing/JLabel;
    flags: (0x0012) ACC_PRIVATE, ACC_FINAL

  private final javax.swing.JLabel moreInfoLabel;
    descriptor: Ljavax/swing/JLabel;
    flags: (0x0012) ACC_PRIVATE, ACC_FINAL

  private final javax.swing.JLabel versionLabel;
    descriptor: Ljavax/swing/JLabel;
    flags: (0x0012) ACC_PRIVATE, ACC_FINAL

  private final javax.swing.JLabel reasonLabel;
    descriptor: Ljavax/swing/JLabel;
    flags: (0x0012) ACC_PRIVATE, ACC_FINAL

  private final javax.swing.JLabel trademarksLabel;
    descriptor: Ljavax/swing/JLabel;
    flags: (0x0012) ACC_PRIVATE, ACC_FINAL

  private final javax.swing.JLabel companyLabel;
    descriptor: Ljavax/swing/JLabel;
    flags: (0x0012) ACC_PRIVATE, ACC_FINAL

  private final javax.swing.JPanel northJPanel;
    descriptor: Ljavax/swing/JPanel;
    flags: (0x0012) ACC_PRIVATE, ACC_FINAL

  private final javax.swing.JPanel centerBottomJPanel;
    descriptor: Ljavax/swing/JPanel;
    flags: (0x0012) ACC_PRIVATE, ACC_FINAL

  private final javax.swing.JPanel centerJPanel;
    descriptor: Ljavax/swing/JPanel;
    flags: (0x0012) ACC_PRIVATE, ACC_FINAL

  private final javax.swing.JPanel copyrightTrademarkJPanel;
    descriptor: Ljavax/swing/JPanel;
    flags: (0x0012) ACC_PRIVATE, ACC_FINAL

  private final javax.swing.JPanel aboutJPanel;
    descriptor: Ljavax/swing/JPanel;
    flags: (0x0012) ACC_PRIVATE, ACC_FINAL

  public java.lang.String name();
    descriptor: ()Ljava/lang/String;
    flags: (0x0001) ACC_PUBLIC
    Code:
      stack=1, locals=1, args_size=1
         0: aload_0
         1: getfield      #36                 // Field name:Ljava/lang/String;
         4: areturn
      LineNumberTable:
        line 39: 0
      LocalVariableTable:
        Start  Length  Slot  Name   Signature
            0       5     0  this   Lorg/scalatest/tools/AboutJDialog;

  public java.lang.String copyright();
    descriptor: ()Ljava/lang/String;
    flags: (0x0001) ACC_PUBLIC
    Code:
      stack=1, locals=1, args_size=1
         0: aload_0
         1: getfield      #40                 // Field copyright:Ljava/lang/String;
         4: areturn
      LineNumberTable:
        line 40: 0
      LocalVariableTable:
        Start  Length  Slot  Name   Signature
            0       5     0  this   Lorg/scalatest/tools/AboutJDialog;

  public java.lang.String moreInfo();
    descriptor: ()Ljava/lang/String;
    flags: (0x0001) ACC_PUBLIC
    Code:
      stack=1, locals=1, args_size=1
         0: aload_0
         1: getfield      #42                 // Field moreInfo:Ljava/lang/String;
         4: areturn
      LineNumberTable:
        line 41: 0
      LocalVariableTable:
        Start  Length  Slot  Name   Signature
            0       5     0  this   Lorg/scalatest/tools/AboutJDialog;

  public java.lang.String url();
    descriptor: ()Ljava/lang/String;
    flags: (0x0001) ACC_PUBLIC
    Code:
      stack=1, locals=1, args_size=1
         0: aload_0
         1: getfield      #44                 // Field url:Ljava/lang/String;
         4: areturn
      LineNumberTable:
        line 42: 0
      LocalVariableTable:
        Start  Length  Slot  Name   Signature
            0       5     0  this   Lorg/scalatest/tools/AboutJDialog;

  public java.lang.String version();
    descriptor: ()Ljava/lang/String;
    flags: (0x0001) ACC_PUBLIC
    Code:
      stack=1, locals=1, args_size=1
         0: aload_0
         1: getfield      #46                 // Field version:Ljava/lang/String;
         4: areturn
      LineNumberTable:
        line 43: 0
      LocalVariableTable:
        Start  Length  Slot  Name   Signature
            0       5     0  this   Lorg/scalatest/tools/AboutJDialog;

  public java.lang.String scalaVersion();
    descriptor: ()Ljava/lang/String;
    flags: (0x0001) ACC_PUBLIC
    Code:
      stack=1, locals=1, args_size=1
         0: aload_0
         1: getfield      #48                 // Field scalaVersion:Ljava/lang/String;
         4: areturn
      LineNumberTable:
        line 44: 0
      LocalVariableTable:
        Start  Length  Slot  Name   Signature
            0       5     0  this   Lorg/scalatest/tools/AboutJDialog;

  public java.lang.String reason();
    descriptor: ()Ljava/lang/String;
    flags: (0x0001) ACC_PUBLIC
    Code:
      stack=1, locals=1, args_size=1
         0: aload_0
         1: getfield      #50                 // Field reason:Ljava/lang/String;
         4: areturn
      LineNumberTable:
        line 45: 0
      LocalVariableTable:
        Start  Length  Slot  Name   Signature
            0       5     0  this   Lorg/scalatest/tools/AboutJDialog;

  public java.lang.String trademarks();
    descriptor: ()Ljava/lang/String;
    flags: (0x0001) ACC_PUBLIC
    Code:
      stack=1, locals=1, args_size=1
         0: aload_0
         1: getfield      #52                 // Field trademarks:Ljava/lang/String;
         4: areturn
      LineNumberTable:
        line 46: 0
      LocalVariableTable:
        Start  Length  Slot  Name   Signature
            0       5     0  this   Lorg/scalatest/tools/AboutJDialog;

  public java.lang.String company();
    descriptor: ()Ljava/lang/String;
    flags: (0x0001) ACC_PUBLIC
    Code:
      stack=1, locals=1, args_size=1
         0: aload_0
         1: getfield      #54                 // Field company:Ljava/lang/String;
         4: areturn
      LineNumberTable:
        line 47: 0
      LocalVariableTable:
        Start  Length  Slot  Name   Signature
            0       5     0  this   Lorg/scalatest/tools/AboutJDialog;

  public javax.swing.JLabel nameLabel();
    descriptor: ()Ljavax/swing/JLabel;
    flags: (0x0001) ACC_PUBLIC
    Code:
      stack=1, locals=1, args_size=1
         0: aload_0
         1: getfield      #57                 // Field nameLabel:Ljavax/swing/JLabel;
         4: areturn
      LineNumberTable:
        line 48: 0
      LocalVariableTable:
        Start  Length  Slot  Name   Signature
            0       5     0  this   Lorg/scalatest/tools/AboutJDialog;

  public javax.swing.JLabel copyrightLabel();
    descriptor: ()Ljavax/swing/JLabel;
    flags: (0x0001) ACC_PUBLIC
    Code:
      stack=1, locals=1, args_size=1
         0: aload_0
         1: getfield      #59                 // Field copyrightLabel:Ljavax/swing/JLabel;
         4: areturn
      LineNumberTable:
        line 49: 0
      LocalVariableTable:
        Start  Length  Slot  Name   Signature
            0       5     0  this   Lorg/scalatest/tools/AboutJDialog;

  public javax.swing.JLabel urlLabel();
    descriptor: ()Ljavax/swing/JLabel;
    flags: (0x0001) ACC_PUBLIC
    Code:
      stack=1, locals=1, args_size=1
         0: aload_0
         1: getfield      #61                 // Field urlLabel:Ljavax/swing/JLabel;
         4: areturn
      LineNumberTable:
        line 50: 0
      LocalVariableTable:
        Start  Length  Slot  Name   Signature
            0       5     0  this   Lorg/scalatest/tools/AboutJDialog;

  public javax.swing.JLabel moreInfoLabel();
    descriptor: ()Ljavax/swing/JLabel;
    flags: (0x0001) ACC_PUBLIC
    Code:
      stack=1, locals=1, args_size=1
         0: aload_0
         1: getfield      #63                 // Field moreInfoLabel:Ljavax/swing/JLabel;
         4: areturn
      LineNumberTable:
        line 51: 0
      LocalVariableTable:
        Start  Length  Slot  Name   Signature
            0       5     0  this   Lorg/scalatest/tools/AboutJDialog;

  public javax.swing.JLabel versionLabel();
    descriptor: ()Ljavax/swing/JLabel;
    flags: (0x0001) ACC_PUBLIC
    Code:
      stack=1, locals=1, args_size=1
         0: aload_0
         1: getfield      #65                 // Field versionLabel:Ljavax/swing/JLabel;
         4: areturn
      LineNumberTable:
        line 52: 0
      LocalVariableTable:
        Start  Length  Slot  Name   Signature
            0       5     0  this   Lorg/scalatest/tools/AboutJDialog;

  public javax.swing.JLabel reasonLabel();
    descriptor: ()Ljavax/swing/JLabel;
    flags: (0x0001) ACC_PUBLIC
    Code:
      stack=1, locals=1, args_size=1
         0: aload_0
         1: getfield      #67                 // Field reasonLabel:Ljavax/swing/JLabel;
         4: areturn
      LineNumberTable:
        line 53: 0
      LocalVariableTable:
        Start  Length  Slot  Name   Signature
            0       5     0  this   Lorg/scalatest/tools/AboutJDialog;

  public javax.swing.JLabel trademarksLabel();
    descriptor: ()Ljavax/swing/JLabel;
    flags: (0x0001) ACC_PUBLIC
    Code:
      stack=1, locals=1, args_size=1
         0: aload_0
         1: getfield      #69                 // Field trademarksLabel:Ljavax/swing/JLabel;
         4: areturn
      LineNumberTable:
        line 54: 0
      LocalVariableTable:
        Start  Length  Slot  Name   Signature
            0       5     0  this   Lorg/scalatest/tools/AboutJDialog;

  public javax.swing.JLabel companyLabel();
    descriptor: ()Ljavax/swing/JLabel;
    flags: (0x0001) ACC_PUBLIC
    Code:
      stack=1, locals=1, args_size=1
         0: aload_0
         1: getfield      #71                 // Field companyLabel:Ljavax/swing/JLabel;
         4: areturn
      LineNumberTable:
        line 55: 0
      LocalVariableTable:
        Start  Length  Slot  Name   Signature
            0       5     0  this   Lorg/scalatest/tools/AboutJDialog;

  public javax.swing.JPanel northJPanel();
    descriptor: ()Ljavax/swing/JPanel;
    flags: (0x0001) ACC_PUBLIC
    Code:
      stack=1, locals=1, args_size=1
         0: aload_0
         1: getfield      #74                 // Field northJPanel:Ljavax/swing/JPanel;
         4: areturn
      LineNumberTable:
        line 67: 0
      LocalVariableTable:
        Start  Length  Slot  Name   Signature
            0       5     0  this   Lorg/scalatest/tools/AboutJDialog;

  public javax.swing.JPanel centerBottomJPanel();
    descriptor: ()Ljavax/swing/JPanel;
    flags: (0x0001) ACC_PUBLIC
    Code:
      stack=1, locals=1, args_size=1
         0: aload_0
         1: getfield      #76                 // Field centerBottomJPanel:Ljavax/swing/JPanel;
         4: areturn
      LineNumberTable:
        line 72: 0
      LocalVariableTable:
        Start  Length  Slot  Name   Signature
            0       5     0  this   Lorg/scalatest/tools/AboutJDialog;

  public javax.swing.JPanel centerJPanel();
    descriptor: ()Ljavax/swing/JPanel;
    flags: (0x0001) ACC_PUBLIC
    Code:
      stack=1, locals=1, args_size=1
         0: aload_0
         1: getfield      #78                 // Field centerJPanel:Ljavax/swing/JPanel;
         4: areturn
      LineNumberTable:
        line 77: 0
      LocalVariableTable:
        Start  Length  Slot  Name   Signature
            0       5     0  this   Lorg/scalatest/tools/AboutJDialog;

  public javax.swing.JPanel copyrightTrademarkJPanel();
    descriptor: ()Ljavax/swing/JPanel;
    flags: (0x0001) ACC_PUBLIC
    Code:
      stack=1, locals=1, args_size=1
         0: aload_0
         1: getfield      #80                 // Field copyrightTrademarkJPanel:Ljavax/swing/JPanel;
         4: areturn
      LineNumberTable:
        line 82: 0
      LocalVariableTable:
        Start  Length  Slot  Name   Signature
            0       5     0  this   Lorg/scalatest/tools/AboutJDialog;

  public javax.swing.JPanel aboutJPanel();
    descriptor: ()Ljavax/swing/JPanel;
    flags: (0x0001) ACC_PUBLIC
    Code:
      stack=1, locals=1, args_size=1
         0: aload_0
         1: getfield      #82                 // Field aboutJPanel:Ljavax/swing/JPanel;
         4: areturn
      LineNumberTable:
        line 87: 0
      LocalVariableTable:
        Start  Length  Slot  Name   Signature
            0       5     0  this   Lorg/scalatest/tools/AboutJDialog;

  public org.scalatest.tools.AboutJDialog(javax.swing.JFrame, java.lang.String);
    descriptor: (Ljavax/swing/JFrame;Ljava/lang/String;)V
    flags: (0x0001) ACC_PUBLIC
    Code:
      stack=7, locals=3, args_size=3
         0: aload_0
         1: aload_1
         2: aload_2
         3: invokespecial #89                 // Method javax/swing/JDialog."<init>":(Ljava/awt/Frame;Ljava/lang/String;)V
         6: aload_0
         7: getstatic     #95                 // Field org/scalatest/Resources$.MODULE$:Lorg/scalatest/Resources$;
        10: invokevirtual #98                 // Method org/scalatest/Resources$.AppName:()Ljava/lang/String;
        13: putfield      #36                 // Field name:Ljava/lang/String;
        16: aload_0
        17: getstatic     #95                 // Field org/scalatest/Resources$.MODULE$:Lorg/scalatest/Resources$;
        20: invokevirtual #101                // Method org/scalatest/Resources$.AppCopyright:()Ljava/lang/String;
        23: putfield      #40                 // Field copyright:Ljava/lang/String;
        26: aload_0
        27: getstatic     #95                 // Field org/scalatest/Resources$.MODULE$:Lorg/scalatest/Resources$;
        30: invokevirtual #104                // Method org/scalatest/Resources$.MoreInfo:()Ljava/lang/String;
        33: putfield      #42                 // Field moreInfo:Ljava/lang/String;
        36: aload_0
        37: getstatic     #95                 // Field org/scalatest/Resources$.MODULE$:Lorg/scalatest/Resources$;
        40: invokevirtual #107                // Method org/scalatest/Resources$.AppURL:()Ljava/lang/String;
        43: putfield      #44                 // Field url:Ljava/lang/String;
        46: aload_0
        47: getstatic     #112                // Field org/scalatest/ScalaTestVersions$.MODULE$:Lorg/scalatest/ScalaTestVersions$;
        50: invokevirtual #115                // Method org/scalatest/ScalaTestVersions$.ScalaTestVersion:()Ljava/lang/String;
        53: putfield      #46                 // Field version:Ljava/lang/String;
        56: aload_0
        57: getstatic     #112                // Field org/scalatest/ScalaTestVersions$.MODULE$:Lorg/scalatest/ScalaTestVersions$;
        60: invokevirtual #118                // Method org/scalatest/ScalaTestVersions$.BuiltForScalaVersion:()Ljava/lang/String;
        63: putfield      #48                 // Field scalaVersion:Ljava/lang/String;
        66: aload_0
        67: getstatic     #95                 // Field org/scalatest/Resources$.MODULE$:Lorg/scalatest/Resources$;
        70: invokevirtual #121                // Method org/scalatest/Resources$.Reason:()Ljava/lang/String;
        73: putfield      #50                 // Field reason:Ljava/lang/String;
        76: aload_0
        77: getstatic     #95                 // Field org/scalatest/Resources$.MODULE$:Lorg/scalatest/Resources$;
        80: invokevirtual #124                // Method org/scalatest/Resources$.Trademarks:()Ljava/lang/String;
        83: putfield      #52                 // Field trademarks:Ljava/lang/String;
        86: aload_0
        87: getstatic     #95                 // Field org/scalatest/Resources$.MODULE$:Lorg/scalatest/Resources$;
        90: invokevirtual #127                // Method org/scalatest/Resources$.ArtimaInc:()Ljava/lang/String;
        93: putfield      #54                 // Field company:Ljava/lang/String;
        96: aload_0
        97: new           #129                // class javax/swing/JLabel
       100: dup
       101: aload_0
       102: invokevirtual #131                // Method name:()Ljava/lang/String;
       105: iconst_0
       106: invokespecial #134                // Method javax/swing/JLabel."<init>":(Ljava/lang/String;I)V
       109: putfield      #57                 // Field nameLabel:Ljavax/swing/JLabel;
       112: aload_0
       113: new           #129                // class javax/swing/JLabel
       116: dup
       117: aload_0
       118: invokevirtual #136                // Method copyright:()Ljava/lang/String;
       121: iconst_0
       122: invokespecial #134                // Method javax/swing/JLabel."<init>":(Ljava/lang/String;I)V
       125: putfield      #59                 // Field copyrightLabel:Ljavax/swing/JLabel;
       128: aload_0
       129: new           #129                // class javax/swing/JLabel
       132: dup
       133: aload_0
       134: invokevirtual #138                // Method url:()Ljava/lang/String;
       137: iconst_0
       138: invokespecial #134                // Method javax/swing/JLabel."<init>":(Ljava/lang/String;I)V
       141: putfield      #61                 // Field urlLabel:Ljavax/swing/JLabel;
       144: aload_0
       145: new           #129                // class javax/swing/JLabel
       148: dup
       149: aload_0
       150: invokevirtual #140                // Method moreInfo:()Ljava/lang/String;
       153: iconst_0
       154: invokespecial #134                // Method javax/swing/JLabel."<init>":(Ljava/lang/String;I)V
       157: putfield      #63                 // Field moreInfoLabel:Ljavax/swing/JLabel;
       160: aload_0
       161: new           #129                // class javax/swing/JLabel
       164: dup
       165: new           #142                // class java/lang/StringBuilder
       168: dup
       169: ldc           #143                // int 19
       171: invokespecial #146                // Method java/lang/StringBuilder."<init>":(I)V
       174: aload_0
       175: invokevirtual #148                // Method version:()Ljava/lang/String;
       178: invokevirtual #152                // Method java/lang/StringBuilder.append:(Ljava/lang/String;)Ljava/lang/StringBuilder;
       181: ldc           #154                // String  (Built for Scala
       183: invokevirtual #152                // Method java/lang/StringBuilder.append:(Ljava/lang/String;)Ljava/lang/StringBuilder;
       186: aload_0
       187: invokevirtual #156                // Method scalaVersion:()Ljava/lang/String;
       190: invokevirtual #152                // Method java/lang/StringBuilder.append:(Ljava/lang/String;)Ljava/lang/StringBuilder;
       193: ldc           #158                // String )
       195: invokevirtual #152                // Method java/lang/StringBuilder.append:(Ljava/lang/String;)Ljava/lang/StringBuilder;
       198: invokevirtual #161                // Method java/lang/StringBuilder.toString:()Ljava/lang/String;
       201: iconst_0
       202: invokespecial #134                // Method javax/swing/JLabel."<init>":(Ljava/lang/String;I)V
       205: putfield      #65                 // Field versionLabel:Ljavax/swing/JLabel;
       208: aload_0
       209: new           #129                // class javax/swing/JLabel
       212: dup
       213: aload_0
       214: invokevirtual #163                // Method reason:()Ljava/lang/String;
       217: iconst_0
       218: invokespecial #134                // Method javax/swing/JLabel."<init>":(Ljava/lang/String;I)V
       221: putfield      #67                 // Field reasonLabel:Ljavax/swing/JLabel;
       224: aload_0
       225: new           #129                // class javax/swing/JLabel
       228: dup
       229: aload_0
       230: invokevirtual #165                // Method trademarks:()Ljava/lang/String;
       233: iconst_0
       234: invokespecial #134                // Method javax/swing/JLabel."<init>":(Ljava/lang/String;I)V
       237: putfield      #69                 // Field trademarksLabel:Ljavax/swing/JLabel;
       240: aload_0
       241: new           #129                // class javax/swing/JLabel
       244: dup
       245: aload_0
       246: invokevirtual #167                // Method company:()Ljava/lang/String;
       249: iconst_0
       250: invokespecial #134                // Method javax/swing/JLabel."<init>":(Ljava/lang/String;I)V
       253: putfield      #71                 // Field companyLabel:Ljavax/swing/JLabel;
       256: aload_0
       257: invokevirtual #169                // Method nameLabel:()Ljavax/swing/JLabel;
       260: new           #171                // class java/awt/Font
       263: dup
       264: ldc           #173                // String SansSerif
       266: iconst_1
       267: bipush        20
       269: invokespecial #176                // Method java/awt/Font."<init>":(Ljava/lang/String;II)V
       272: invokevirtual #180                // Method javax/swing/JLabel.setFont:(Ljava/awt/Font;)V
       275: aload_0
       276: invokevirtual #182                // Method urlLabel:()Ljavax/swing/JLabel;
       279: new           #171                // class java/awt/Font
       282: dup
       283: ldc           #173                // String SansSerif
       285: iconst_0
       286: bipush        13
       288: invokespecial #176                // Method java/awt/Font."<init>":(Ljava/lang/String;II)V
       291: invokevirtual #180                // Method javax/swing/JLabel.setFont:(Ljava/awt/Font;)V
       294: aload_0
       295: invokevirtual #184                // Method reasonLabel:()Ljavax/swing/JLabel;
       298: new           #171                // class java/awt/Font
       301: dup
       302: ldc           #173                // String SansSerif
       304: iconst_2
       305: bipush        13
       307: invokespecial #176                // Method java/awt/Font."<init>":(Ljava/lang/String;II)V
       310: invokevirtual #180                // Method javax/swing/JLabel.setFont:(Ljava/awt/Font;)V
       313: aload_0
       314: invokevirtual #186                // Method companyLabel:()Ljavax/swing/JLabel;
       317: new           #171                // class java/awt/Font
       320: dup
       321: ldc           #173                // String SansSerif
       323: iconst_1
       324: bipush        14
       326: invokespecial #176                // Method java/awt/Font."<init>":(Ljava/lang/String;II)V
       329: invokevirtual #180                // Method javax/swing/JLabel.setFont:(Ljava/awt/Font;)V
       332: aload_0
       333: invokevirtual #188                // Method trademarksLabel:()Ljavax/swing/JLabel;
       336: new           #171                // class java/awt/Font
       339: dup
       340: ldc           #173                // String SansSerif
       342: iconst_0
       343: bipush        11
       345: invokespecial #176                // Method java/awt/Font."<init>":(Ljava/lang/String;II)V
       348: invokevirtual #180                // Method javax/swing/JLabel.setFont:(Ljava/awt/Font;)V
       351: aload_0
       352: invokevirtual #190                // Method copyrightLabel:()Ljavax/swing/JLabel;
       355: new           #171                // class java/awt/Font
       358: dup
       359: ldc           #173                // String SansSerif
       361: iconst_0
       362: bipush        11
       364: invokespecial #176                // Method java/awt/Font."<init>":(Ljava/lang/String;II)V
       367: invokevirtual #180                // Method javax/swing/JLabel.setFont:(Ljava/awt/Font;)V
       370: aload_0
       371: invokevirtual #169                // Method nameLabel:()Ljavax/swing/JLabel;
       374: new           #192                // class java/awt/Color
       377: dup
       378: iconst_0
       379: iconst_0
       380: bipush        102
       382: invokespecial #195                // Method java/awt/Color."<init>":(III)V
       385: invokevirtual #199                // Method javax/swing/JLabel.setForeground:(Ljava/awt/Color;)V
       388: aload_0
       389: invokevirtual #201                // Method versionLabel:()Ljavax/swing/JLabel;
       392: new           #192                // class java/awt/Color
       395: dup
       396: iconst_0
       397: iconst_0
       398: bipush        102
       400: invokespecial #195                // Method java/awt/Color."<init>":(III)V
       403: invokevirtual #199                // Method javax/swing/JLabel.setForeground:(Ljava/awt/Color;)V
       406: aload_0
       407: invokevirtual #186                // Method companyLabel:()Ljavax/swing/JLabel;
       410: new           #192                // class java/awt/Color
       413: dup
       414: iconst_0
       415: iconst_0
       416: bipush        102
       418: invokespecial #195                // Method java/awt/Color."<init>":(III)V
       421: invokevirtual #199                // Method javax/swing/JLabel.setForeground:(Ljava/awt/Color;)V
       424: aload_0
       425: new           #203                // class javax/swing/JPanel
       428: dup
       429: invokespecial #206                // Method javax/swing/JPanel."<init>":()V
       432: putfield      #74                 // Field northJPanel:Ljavax/swing/JPanel;
       435: aload_0
       436: invokevirtual #208                // Method northJPanel:()Ljavax/swing/JPanel;
       439: new           #210                // class java/awt/BorderLayout
       442: dup
       443: invokespecial #211                // Method java/awt/BorderLayout."<init>":()V
       446: invokevirtual #215                // Method javax/swing/JPanel.setLayout:(Ljava/awt/LayoutManager;)V
       449: aload_0
       450: invokevirtual #208                // Method northJPanel:()Ljavax/swing/JPanel;
       453: aload_0
       454: invokevirtual #169                // Method nameLabel:()Ljavax/swing/JLabel;
       457: ldc           #217                // String North
       459: invokevirtual #221                // Method javax/swing/JPanel.add:(Ljava/awt/Component;Ljava/lang/Object;)V
       462: aload_0
       463: invokevirtual #208                // Method northJPanel:()Ljavax/swing/JPanel;
       466: aload_0
       467: invokevirtual #201                // Method versionLabel:()Ljavax/swing/JLabel;
       470: ldc           #223                // String South
       472: invokevirtual #221                // Method javax/swing/JPanel.add:(Ljava/awt/Component;Ljava/lang/Object;)V
       475: aload_0
       476: new           #203                // class javax/swing/JPanel
       479: dup
       480: invokespecial #206                // Method javax/swing/JPanel."<init>":()V
       483: putfield      #76                 // Field centerBottomJPanel:Ljavax/swing/JPanel;
       486: aload_0
       487: invokevirtual #225                // Method centerBottomJPanel:()Ljavax/swing/JPanel;
       490: new           #227                // class java/awt/GridLayout
       493: dup
       494: iconst_2
       495: iconst_1
       496: invokespecial #230                // Method java/awt/GridLayout."<init>":(II)V
       499: invokevirtual #215                // Method javax/swing/JPanel.setLayout:(Ljava/awt/LayoutManager;)V
       502: aload_0
       503: invokevirtual #225                // Method centerBottomJPanel:()Ljavax/swing/JPanel;
       506: aload_0
       507: invokevirtual #232                // Method moreInfoLabel:()Ljavax/swing/JLabel;
       510: invokevirtual #235                // Method javax/swing/JPanel.add:(Ljava/awt/Component;)Ljava/awt/Component;
       513: pop
       514: aload_0
       515: invokevirtual #225                // Method centerBottomJPanel:()Ljavax/swing/JPanel;
       518: aload_0
       519: invokevirtual #182                // Method urlLabel:()Ljavax/swing/JLabel;
       522: invokevirtual #235                // Method javax/swing/JPanel.add:(Ljava/awt/Component;)Ljava/awt/Component;
       525: pop
       526: aload_0
       527: new           #203                // class javax/swing/JPanel
       530: dup
       531: invokespecial #206                // Method javax/swing/JPanel."<init>":()V
       534: putfield      #78                 // Field centerJPanel:Ljavax/swing/JPanel;
       537: aload_0
       538: invokevirtual #237                // Method centerJPanel:()Ljavax/swing/JPanel;
       541: new           #227                // class java/awt/GridLayout
       544: dup
       545: iconst_2
       546: iconst_1
       547: iconst_5
       548: iconst_5
       549: invokespecial #240                // Method java/awt/GridLayout."<init>":(IIII)V
       552: invokevirtual #215                // Method javax/swing/JPanel.setLayout:(Ljava/awt/LayoutManager;)V
       555: aload_0
       556: invokevirtual #237                // Method centerJPanel:()Ljavax/swing/JPanel;
       559: aload_0
       560: invokevirtual #184                // Method reasonLabel:()Ljavax/swing/JLabel;
       563: invokevirtual #235                // Method javax/swing/JPanel.add:(Ljava/awt/Component;)Ljava/awt/Component;
       566: pop
       567: aload_0
       568: invokevirtual #237                // Method centerJPanel:()Ljavax/swing/JPanel;
       571: aload_0
       572: invokevirtual #225                // Method centerBottomJPanel:()Ljavax/swing/JPanel;
       575: invokevirtual #235                // Method javax/swing/JPanel.add:(Ljava/awt/Component;)Ljava/awt/Component;
       578: pop
       579: aload_0
       580: new           #203                // class javax/swing/JPanel
       583: dup
       584: invokespecial #206                // Method javax/swing/JPanel."<init>":()V
       587: putfield      #80                 // Field copyrightTrademarkJPanel:Ljavax/swing/JPanel;
       590: aload_0
       591: invokevirtual #242                // Method copyrightTrademarkJPanel:()Ljavax/swing/JPanel;
       594: new           #227                // class java/awt/GridLayout
       597: dup
       598: iconst_2
       599: iconst_1
       600: invokespecial #230                // Method java/awt/GridLayout."<init>":(II)V
       603: invokevirtual #215                // Method javax/swing/JPanel.setLayout:(Ljava/awt/LayoutManager;)V
       606: aload_0
       607: invokevirtual #242                // Method copyrightTrademarkJPanel:()Ljavax/swing/JPanel;
       610: aload_0
       611: invokevirtual #190                // Method copyrightLabel:()Ljavax/swing/JLabel;
       614: invokevirtual #235                // Method javax/swing/JPanel.add:(Ljava/awt/Component;)Ljava/awt/Component;
       617: pop
       618: aload_0
       619: invokevirtual #242                // Method copyrightTrademarkJPanel:()Ljavax/swing/JPanel;
       622: aload_0
       623: invokevirtual #188                // Method trademarksLabel:()Ljavax/swing/JLabel;
       626: invokevirtual #235                // Method javax/swing/JPanel.add:(Ljava/awt/Component;)Ljava/awt/Component;
       629: pop
       630: aload_0
       631: new           #203                // class javax/swing/JPanel
       634: dup
       635: invokespecial #206                // Method javax/swing/JPanel."<init>":()V
       638: putfield      #82                 // Field aboutJPanel:Ljavax/swing/JPanel;
       641: aload_0
       642: invokevirtual #244                // Method aboutJPanel:()Ljavax/swing/JPanel;
       645: new           #210                // class java/awt/BorderLayout
       648: dup
       649: bipush        15
       651: bipush        15
       653: invokespecial #245                // Method java/awt/BorderLayout."<init>":(II)V
       656: invokevirtual #215                // Method javax/swing/JPanel.setLayout:(Ljava/awt/LayoutManager;)V
       659: aload_0
       660: invokevirtual #244                // Method aboutJPanel:()Ljavax/swing/JPanel;
       663: aload_0
       664: invokevirtual #208                // Method northJPanel:()Ljavax/swing/JPanel;
       667: ldc           #217                // String North
       669: invokevirtual #221                // Method javax/swing/JPanel.add:(Ljava/awt/Component;Ljava/lang/Object;)V
       672: aload_0
       673: invokevirtual #244                // Method aboutJPanel:()Ljavax/swing/JPanel;
       676: aload_0
       677: invokevirtual #237                // Method centerJPanel:()Ljavax/swing/JPanel;
       680: ldc           #247                // String Center
       682: invokevirtual #221                // Method javax/swing/JPanel.add:(Ljava/awt/Component;Ljava/lang/Object;)V
       685: aload_0
       686: invokevirtual #244                // Method aboutJPanel:()Ljavax/swing/JPanel;
       689: aload_0
       690: invokevirtual #242                // Method copyrightTrademarkJPanel:()Ljavax/swing/JPanel;
       693: ldc           #223                // String South
       695: invokevirtual #221                // Method javax/swing/JPanel.add:(Ljava/awt/Component;Ljava/lang/Object;)V
       698: aload_0
       699: invokevirtual #244                // Method aboutJPanel:()Ljavax/swing/JPanel;
       702: new           #249                // class javax/swing/border/EmptyBorder
       705: dup
       706: iconst_5
       707: iconst_5
       708: iconst_5
       709: iconst_5
       710: invokespecial #250                // Method javax/swing/border/EmptyBorder."<init>":(IIII)V
       713: invokevirtual #254                // Method javax/swing/JPanel.setBorder:(Ljavax/swing/border/Border;)V
       716: aload_0
       717: invokevirtual #258                // Method getContentPane:()Ljava/awt/Container;
       720: new           #210                // class java/awt/BorderLayout
       723: dup
       724: invokespecial #211                // Method java/awt/BorderLayout."<init>":()V
       727: invokevirtual #261                // Method java/awt/Container.setLayout:(Ljava/awt/LayoutManager;)V
       730: aload_0
       731: invokevirtual #258                // Method getContentPane:()Ljava/awt/Container;
       734: ldc           #247                // String Center
       736: aload_0
       737: invokevirtual #244                // Method aboutJPanel:()Ljavax/swing/JPanel;
       740: invokevirtual #264                // Method java/awt/Container.add:(Ljava/lang/String;Ljava/awt/Component;)Ljava/awt/Component;
       743: pop
       744: aload_0
       745: invokevirtual #267                // Method pack:()V
       748: return
      LineNumberTable:
        line 37: 0
        line 39: 6
        line 40: 16
        line 41: 26
        line 42: 36
        line 43: 46
        line 44: 56
        line 45: 66
        line 46: 76
        line 47: 86
        line 48: 96
        line 49: 112
        line 50: 128
        line 51: 144
        line 52: 160
        line 53: 208
        line 54: 224
        line 55: 240
        line 57: 256
        line 58: 275
        line 59: 294
        line 60: 313
        line 61: 332
        line 62: 351
        line 63: 370
        line 64: 388
        line 65: 406
        line 67: 424
        line 68: 435
        line 69: 449
        line 70: 462
        line 72: 475
        line 73: 486
        line 74: 502
        line 75: 514
        line 77: 526
        line 78: 537
        line 79: 555
        line 80: 567
        line 82: 579
        line 83: 590
        line 84: 606
        line 85: 618
        line 87: 630
        line 88: 641
        line 89: 659
        line 90: 672
        line 91: 685
        line 92: 698
        line 93: 716
        line 94: 730
        line 95: 744
        line 37: 748
      LocalVariableTable:
        Start  Length  Slot  Name   Signature
            0     749     0  this   Lorg/scalatest/tools/AboutJDialog;
            0     749     1 owner   Ljavax/swing/JFrame;
            0     749     2 title   Ljava/lang/String;
    MethodParameters:
      Name                           Flags
      owner                          final
      title                          final
}
SourceFile: "AboutJDialog.scala"
RuntimeVisibleAnnotations:
  0: #6(#7=s#8)
    scala.reflect.ScalaSignature(
      bytes="\u0006\u0005\u0005ua!\u0002\u00192\u0001M:\u0004\u0002\u0003!\u0001\u0005\u0003\u0005\u000b\u0011\u0002\"\t\u0011\u0015\u0003!\u0011!Q\u0001\n\u0019CQa\u0015\u0001\u0005\u0002QCq!\u0017\u0001C\u0002\u0013\u0005!\f\u0003\u0004\\\u0001\u0001\u0006IA\u0012\u0005\b9\u0002\u0011\r\u0011\"\u0001[\u0011\u0019i\u0006\u0001)A\u0005\r\"9a\f\u0001b\u0001\n\u0003Q\u0006BB0\u0001A\u0003%a\tC\u0004a\u0001\t\u0007I\u0011\u0001.\t\r\u0005\u0004\u0001\u0015!\u0003G\u0011\u001d\u0011\u0007A1A\u0005\u0002iCaa\u0019\u0001!\u0002\u00131\u0005b\u00023\u0001\u0005\u0004%\tA\u0017\u0005\u0007K\u0002\u0001\u000b\u0011\u0002$\t\u000f\u0019\u0004!\u0019!C\u00015\"1q\r\u0001Q\u0001\n\u0019Cq\u0001\u001b\u0001C\u0002\u0013\u0005!\f\u0003\u0004j\u0001\u0001\u0006IA\u0012\u0005\bU\u0002\u0011\r\u0011\"\u0001[\u0011\u0019Y\u0007\u0001)A\u0005\r\"9A\u000e\u0001b\u0001\n\u0003i\u0007BB9\u0001A\u0003%a\u000eC\u0004s\u0001\t\u0007I\u0011A7\t\rM\u0004\u0001\u0015!\u0003o\u0011\u001d!\bA1A\u0005\u00025Da!\u001e\u0001!\u0002\u0013q\u0007b\u0002<\u0001\u0005\u0004%\t!\u001c\u0005\u0007o\u0002\u0001\u000b\u0011\u00028\t\u000fa\u0004!\u0019!C\u0001[\"1\u0011\u0010\u0001Q\u0001\n9DqA\u001f\u0001C\u0002\u0013\u0005Q\u000e\u0003\u0004|\u0001\u0001\u0006IA\u001c\u0005\by\u0002\u0011\r\u0011\"\u0001n\u0011\u0019i\b\u0001)A\u0005]\"9a\u0010\u0001b\u0001\n\u0003i\u0007BB@\u0001A\u0003%a\u000eC\u0005\u0002\u0002\u0001\u0011\r\u0011\"\u0001\u0002\u0004!A\u00111\u0002\u0001!\u0002\u0013\t)\u0001C\u0005\u0002\u000e\u0001\u0011\r\u0011\"\u0001\u0002\u0004!A\u0011q\u0002\u0001!\u0002\u0013\t)\u0001C\u0005\u0002\u0012\u0001\u0011\r\u0011\"\u0001\u0002\u0004!A\u00111\u0003\u0001!\u0002\u0013\t)\u0001C\u0005\u0002\u0016\u0001\u0011\r\u0011\"\u0001\u0002\u0004!A\u0011q\u0003\u0001!\u0002\u0013\t)\u0001C\u0005\u0002\u001a\u0001\u0011\r\u0011\"\u0001\u0002\u0004!A\u00111\u0004\u0001!\u0002\u0013\t)A\u0001\u0007BE>,HO\u0013#jC2|wM\u0003\u00023g\u0005)Ao\\8mg*\u0011A\'N\u0001\ng\u000e\fG.\u0019;fgRT\u0011AN\u0001\u0004_J<7C\u0001\u00019!\tId(D\u0001;\u0015\tYD(A\u0003to&twMC\u0001>\u0003\u0015Q\u0017M^1y\u0013\ty$HA\u0004K\t&\fGn\\4\u0002\u000b=<h.\u001a:\u0004\u0001A\u0011\u0011hQ\u0005\u0003\tj\u0012aA\u0013$sC6,\u0017!\u0002;ji2,\u0007CA$Q\u001d\tAe\n\u0005\u0002J\u00196\t!J\u0003\u0002L\u0003\u00061AH]8pizR\u0011!T\u0001\u0006g\u000e\fG.Y\u0005\u0003\u001f2\u000ba\u0001\u0015:fI\u00164\u0017BA)S\u0005\u0019\u0019FO]5oO*\u0011q\nT\u0001\u0007y%t\u0017\u000e\u001e \u0015\u0007U;\u0006\f\u0005\u0002W\u00015\t\u0011\u0007C\u0003A\u0007\u0001\u0007!\tC\u0003F\u0007\u0001\u0007a)\u0001\u0003oC6,W#\u0001$\u0002\u000b9\fW.\u001a\u0011\u0002\u0013\r|\u0007/\u001f:jO\"$\u0018AC2paf\u0014\u0018n\u001a5uA\u0005AQn\u001c:f\u0013:4w.A\u0005n_J,\u0017J\u001c4pA\u0005\u0019QO\u001d7\u0002\tU\u0014H\u000eI\u0001\bm\u0016\u00148/[8o\u0003!1XM]:j_:\u0004\u0013\u0001D:dC2\fg+\u001a:tS>t\u0017!D:dC2\fg+\u001a:tS>t\u0007%\u0001\u0004sK\u0006\u001cxN\\\u0001\be\u0016\f7o\u001c8!\u0003)!(/\u00193f[\u0006\u00148n]\u0001\fiJ\fG-Z7be.\u001c\b%A\u0004d_6\u0004\u0018M\\=\u0002\u0011\r|W\u000e]1os\u0002\n\u0011B\\1nK2\u000b\'-\u001a7\u0016\u00039\u0004\"!O8\n\u0005AT$A\u0002&MC\n,G.\u0001\u0006oC6,G*\u00192fY\u0002\nabY8qsJLw\r\u001b;MC\n,G.A\bd_BL(/[4ii2\u000b\'-\u001a7!\u0003!)(\u000f\u001c\'bE\u0016d\u0017!C;sY2\u000b\'-\u001a7!\u00035iwN]3J]\u001a|G*\u00192fY\u0006qQn\u001c:f\u0013:4w\u000eT1cK2\u0004\u0013\u0001\u0004<feNLwN\u001c\'bE\u0016d\u0017!\u0004<feNLwN\u001c\'bE\u0016d\u0007%A\u0006sK\u0006\u001cxN\u001c\'bE\u0016d\u0017\u0001\u0004:fCN|g\u000eT1cK2\u0004\u0013a\u0004;sC\u0012,W.\u0019:lg2\u000b\'-\u001a7\u0002!Q\u0014\u0018\rZ3nCJ\\7\u000fT1cK2\u0004\u0013\u0001D2p[B\fg.\u001f\'bE\u0016d\u0017!D2p[B\fg.\u001f\'bE\u0016d\u0007%A\u0006o_J$\bN\u0013)b]\u0016dWCAA\u0003!\rI\u0014qA\u0005\u0004\u0003\u0013Q$A\u0002&QC:,G.\u0001\u0007o_J$\bN\u0013)b]\u0016d\u0007%\u0001\ndK:$XM\u001d\"piR|WN\u0013)b]\u0016d\u0017aE2f]R,\'OQ8ui>l\'\nU1oK2\u0004\u0013\u0001D2f]R,\'O\u0013)b]\u0016d\u0017!D2f]R,\'O\u0013)b]\u0016d\u0007%\u0001\rd_BL(/[4iiR\u0013\u0018\rZ3nCJ\\\'\nU1oK2\f\u0011dY8qsJLw\r\u001b;Ue\u0006$W-\\1sW*\u0003\u0016M\\3mA\u0005Y\u0011MY8vi*\u0003\u0016M\\3m\u00031\t\'m\\;u\u0015B\u000bg.\u001a7!\u0001"
    )
  ScalaInlineInfo: length = 0x77 (unknown attribute)
   01 00 00 17 00 53 00 54 00 00 21 00 48 00 00 1E
   00 48 00 00 1F 00 48 00 00 12 00 22 00 00 1B 00
   37 00 00 0B 00 22 00 00 15 00 37 00 00 20 00 48
   00 00 0C 00 22 00 00 17 00 37 00 00 09 00 22 00
   00 13 00 37 00 00 1C 00 48 00 00 10 00 22 00 00
   19 00 37 00 00 0F 00 22 00 00 11 00 22 00 00 1A
   00 37 00 00 0D 00 22 00 00 16 00 37 00 00 0E 00
   22 00 00 18 00 37 00
  ScalaSig: length = 0x3 (unknown attribute)
   05 02 00
