Classfile /Users/mw/Projects/slang-braindump/.jar/jar8/assemble/slang-braindump/assemble/content/org/scalatest/tools/AnsiReset$.class
  Last modified May 29, 2022; size 596 bytes
  SHA-256 checksum 08e33a9e8db90fe2f3ef34b753a37c72476a1522155e06ae5eafcdc3f6449bc8
  Compiled from "AnsiReset.scala"
public final class org.scalatest.tools.AnsiReset$
  minor version: 0
  major version: 52
  flags: (0x0031) ACC_PUBLIC, ACC_FINAL, ACC_SUPER
  this_class: #2                          // org/scalatest/tools/AnsiReset$
  super_class: #4                         // java/lang/Object
  interfaces: 0, fields: 2, methods: 3, attributes: 3
Constant pool:
   #1 = Utf8               org/scalatest/tools/AnsiReset$
   #2 = Class              #1             // org/scalatest/tools/AnsiReset$
   #3 = Utf8               java/lang/Object
   #4 = Class              #3             // java/lang/Object
   #5 = Utf8               AnsiReset.scala
   #6 = Utf8               MODULE$
   #7 = Utf8               Lorg/scalatest/tools/AnsiReset$;
   #8 = Utf8               code
   #9 = Utf8               Ljava/lang/String;
  #10 = Utf8               <clinit>
  #11 = Utf8               ()V
  #12 = Utf8               <init>
  #13 = NameAndType        #12:#11        // "<init>":()V
  #14 = Methodref          #2.#13         // org/scalatest/tools/AnsiReset$."<init>":()V
  #15 = NameAndType        #6:#7          // MODULE$:Lorg/scalatest/tools/AnsiReset$;
  #16 = Fieldref           #2.#15         // org/scalatest/tools/AnsiReset$.MODULE$:Lorg/scalatest/tools/AnsiReset$;
  #17 = Utf8               \u001b[0m
  #18 = String             #17            // \u001b[0m
  #19 = NameAndType        #8:#9          // code:Ljava/lang/String;
  #20 = Fieldref           #2.#19         // org/scalatest/tools/AnsiReset$.code:Ljava/lang/String;
  #21 = Utf8               ()Ljava/lang/String;
  #22 = Utf8               this
  #23 = Methodref          #4.#13         // java/lang/Object."<init>":()V
  #24 = Utf8               Code
  #25 = Utf8               LineNumberTable
  #26 = Utf8               LocalVariableTable
  #27 = Utf8               SourceFile
  #28 = Utf8               ScalaInlineInfo
  #29 = Utf8               Scala
{
  public static final org.scalatest.tools.AnsiReset$ MODULE$;
    descriptor: Lorg/scalatest/tools/AnsiReset$;
    flags: (0x0019) ACC_PUBLIC, ACC_STATIC, ACC_FINAL

  private static final java.lang.String code;
    descriptor: Ljava/lang/String;
    flags: (0x001a) ACC_PRIVATE, ACC_STATIC, ACC_FINAL

  public static {};
    descriptor: ()V
    flags: (0x0009) ACC_PUBLIC, ACC_STATIC
    Code:
      stack=2, locals=0, args_size=0
         0: new           #2                  // class org/scalatest/tools/AnsiReset$
         3: dup
         4: invokespecial #14                 // Method "<init>":()V
         7: putstatic     #16                 // Field MODULE$:Lorg/scalatest/tools/AnsiReset$;
        10: ldc           #18                 // String \u001b[0m
        12: putstatic     #20                 // Field code:Ljava/lang/String;
        15: return
      LineNumberTable:
        line 18: 0
        line 19: 10
        line 18: 15

  public java.lang.String code();
    descriptor: ()Ljava/lang/String;
    flags: (0x0001) ACC_PUBLIC
    Code:
      stack=1, locals=1, args_size=1
         0: getstatic     #20                 // Field code:Ljava/lang/String;
         3: areturn
      LineNumberTable:
        line 19: 0
      LocalVariableTable:
        Start  Length  Slot  Name   Signature
            0       4     0  this   Lorg/scalatest/tools/AnsiReset$;

  private org.scalatest.tools.AnsiReset$();
    descriptor: ()V
    flags: (0x0002) ACC_PRIVATE
    Code:
      stack=1, locals=1, args_size=1
         0: aload_0
         1: invokespecial #23                 // Method java/lang/Object."<init>":()V
         4: return
      LineNumberTable:
        line 21: 0
        line 18: 4
      LocalVariableTable:
        Start  Length  Slot  Name   Signature
            0       5     0  this   Lorg/scalatest/tools/AnsiReset$;
}
SourceFile: "AnsiReset.scala"
  ScalaInlineInfo: length = 0xE (unknown attribute)
   01 01 00 02 00 0C 00 0B 01 00 08 00 15 01
  Scala: length = 0x0 (unknown attribute)

