Classfile /Users/mw/Projects/slang-braindump/.jar/jar8/assemble/slang-braindump/assemble/content/org/scalatest/tools/AnsiReset.class
  Last modified May 29, 2022; size 655 bytes
  SHA-256 checksum 6914271d11a8e2a8e457455d99b213b6c67b840762551ef5c1a5dc9c4aa22fe1
  Compiled from "AnsiReset.scala"
public final class org.scalatest.tools.AnsiReset
  minor version: 0
  major version: 52
  flags: (0x0031) ACC_PUBLIC, ACC_FINAL, ACC_SUPER
  this_class: #2                          // org/scalatest/tools/AnsiReset
  super_class: #4                         // java/lang/Object
  interfaces: 0, fields: 0, methods: 1, attributes: 3
Constant pool:
   #1 = Utf8               org/scalatest/tools/AnsiReset
   #2 = Class              #1             // org/scalatest/tools/AnsiReset
   #3 = Utf8               java/lang/Object
   #4 = Class              #3             // java/lang/Object
   #5 = Utf8               AnsiReset.scala
   #6 = Utf8               Lscala/reflect/ScalaSignature;
   #7 = Utf8               bytes
   #8 = Utf8               \u0006\u0005\u001d:a!\u0002\u0004\t\u0002!aaA\u0002\b\u0007\u0011\u0003Aq\u0002C\u0003\u0017\u0003\u0011\u0005\u0001\u0004C\u0004\u001a\u0003\t\u0007I\u0011\u0001\u000e\t\r\u0019\n\u0001\u0015!\u0003\u001c\u0003%\ten]5SKN,GO\u0003\u0002\b\u0011\u0005)Ao\\8mg*\u0011\u0011BC\u0001\ng\u000e\fG.\u0019;fgRT\u0011aC\u0001\u0004_J<\u0007CA\u0007\u0002\u001b\u00051!!C!og&\u0014Vm]3u\'\t\t\u0001\u0003\u0005\u0002\u0012)5\t!CC\u0001\u0014\u0003\u0015\u00198-\u00197b\u0013\t)\"C\u0001\u0004B]f\u0014VMZ\u0001\u0007y%t\u0017\u000e\u001e \u0004\u0001Q\tA\"\u0001\u0003d_\u0012,W#A\u000e\u0011\u0005q\u0019cBA\u000f\"!\tq\"#D\u0001 \u0015\t\u0001s#\u0001\u0004=e>|GOP\u0005\u0003EI\ta\u0001\u0015:fI\u00164\u0017B\u0001\u0013&\u0005\u0019\u0019FO]5oO*\u0011!EE\u0001\u0006G>$W\r\t
   #9 = Utf8               code
  #10 = Utf8               ()Ljava/lang/String;
  #11 = Utf8               org/scalatest/tools/AnsiReset$
  #12 = Class              #11            // org/scalatest/tools/AnsiReset$
  #13 = Utf8               MODULE$
  #14 = Utf8               Lorg/scalatest/tools/AnsiReset$;
  #15 = NameAndType        #13:#14        // MODULE$:Lorg/scalatest/tools/AnsiReset$;
  #16 = Fieldref           #12.#15        // org/scalatest/tools/AnsiReset$.MODULE$:Lorg/scalatest/tools/AnsiReset$;
  #17 = NameAndType        #9:#10         // code:()Ljava/lang/String;
  #18 = Methodref          #12.#17        // org/scalatest/tools/AnsiReset$.code:()Ljava/lang/String;
  #19 = Utf8               Code
  #20 = Utf8               SourceFile
  #21 = Utf8               RuntimeVisibleAnnotations
  #22 = Utf8               ScalaSig
{
  public static java.lang.String code();
    descriptor: ()Ljava/lang/String;
    flags: (0x0009) ACC_PUBLIC, ACC_STATIC
    Code:
      stack=1, locals=0, args_size=0
         0: getstatic     #16                 // Field org/scalatest/tools/AnsiReset$.MODULE$:Lorg/scalatest/tools/AnsiReset$;
         3: invokevirtual #18                 // Method org/scalatest/tools/AnsiReset$.code:()Ljava/lang/String;
         6: areturn
}
SourceFile: "AnsiReset.scala"
RuntimeVisibleAnnotations:
  0: #6(#7=s#8)
    scala.reflect.ScalaSignature(
      bytes="\u0006\u0005\u001d:a!\u0002\u0004\t\u0002!aaA\u0002\b\u0007\u0011\u0003Aq\u0002C\u0003\u0017\u0003\u0011\u0005\u0001\u0004C\u0004\u001a\u0003\t\u0007I\u0011\u0001\u000e\t\r\u0019\n\u0001\u0015!\u0003\u001c\u0003%\ten]5SKN,GO\u0003\u0002\b\u0011\u0005)Ao\\8mg*\u0011\u0011BC\u0001\ng\u000e\fG.\u0019;fgRT\u0011aC\u0001\u0004_J<\u0007CA\u0007\u0002\u001b\u00051!!C!og&\u0014Vm]3u\'\t\t\u0001\u0003\u0005\u0002\u0012)5\t!CC\u0001\u0014\u0003\u0015\u00198-\u00197b\u0013\t)\"C\u0001\u0004B]f\u0014VMZ\u0001\u0007y%t\u0017\u000e\u001e \u0004\u0001Q\tA\"\u0001\u0003d_\u0012,W#A\u000e\u0011\u0005q\u0019cBA\u000f\"!\tq\"#D\u0001 \u0015\t\u0001s#\u0001\u0004=e>|GOP\u0005\u0003EI\ta\u0001\u0015:fI\u00164\u0017B\u0001\u0013&\u0005\u0019\u0019FO]5oO*\u0011!EE\u0001\u0006G>$W\r\t"
    )
  ScalaSig: length = 0x3 (unknown attribute)
   05 02 00
