Classfile /Users/mw/Projects/slang-braindump/.jar/jar8/assemble/slang-braindump/assemble/content/org/scalatest/tools/AnsiYellow.class
  Last modified May 29, 2022; size 2103 bytes
  SHA-256 checksum 172d7ff52ea08c787091673e2617202ed4f1ecbe47e75283bf60474a5eb5234c
  Compiled from "AnsiColor.scala"
public final class org.scalatest.tools.AnsiYellow
  minor version: 0
  major version: 52
  flags: (0x0031) ACC_PUBLIC, ACC_FINAL, ACC_SUPER
  this_class: #2                          // org/scalatest/tools/AnsiYellow
  super_class: #4                         // java/lang/Object
  interfaces: 0, fields: 0, methods: 10, attributes: 3
Constant pool:
   #1 = Utf8               org/scalatest/tools/AnsiYellow
   #2 = Class              #1             // org/scalatest/tools/AnsiYellow
   #3 = Utf8               java/lang/Object
   #4 = Class              #3             // java/lang/Object
   #5 = Utf8               AnsiColor.scala
   #6 = Utf8               Lscala/reflect/ScalaSignature;
   #7 = Utf8               bytes
   #8 = Utf8               \u0006\u0005)<a!\u0004\b\t\u0002B!bA\u0002\f\u000f\u0011\u0003\u0003r\u0003C\u00032\u0003\u0011\u0005!\u0007C\u00044\u0003\t\u0007I\u0011\u0001\u001b\t\ru\n\u0001\u0015!\u00036\u0011\u001dq\u0014!!A\u0005B}BqaR\u0001\u0002\u0002\u0013\u0005\u0001\nC\u0004M\u0003\u0005\u0005I\u0011A\'\t\u000fM\u000b\u0011\u0011!C!)\"91,AA\u0001\n\u0003a\u0006bB1\u0002\u0003\u0003%\tE\u0019\u0005\bG\u0006\t\t\u0011\"\u0011e\u0011\u001d)\u0017!!A\u0005\n\u0019\f!\"\u00118tSf+G\u000e\\8x\u0015\ty\u0001#A\u0003u_>d7O\u0003\u0002\u0012%\u0005I1oY1mCR,7\u000f\u001e\u0006\u0002\'\u0005\u0019qN]4\u0011\u0005U\tQ\"\u0001\b\u0003\u0015\u0005s7/[-fY2|woE\u0003\u00021y\tC\u0005\u0005\u0002\u001a95\t!DC\u0001\u001c\u0003\u0015\u00198-\u00197b\u0013\ti\"D\u0001\u0004B]f\u0014VM\u001a\t\u0003+}I!\u0001\t\b\u0003\u0013\u0005s7/[\"pY>\u0014\bCA\r#\u0013\t\u0019#DA\u0004Qe>$Wo\u0019;\u0011\u0005\u0015rcB\u0001\u0014-\u001d\t93&D\u0001)\u0015\tI#&\u0001\u0004=e>|GOP\u0002\u0001\u0013\u0005Y\u0012BA\u0017\u001b\u0003\u001d\u0001\u0018mY6bO\u0016L!a\f\u0019\u0003\u0019M+\'/[1mSj\f\'\r\\3\u000b\u00055R\u0012A\u0002\u001fj]&$h\bF\u0001\u0015\u0003\u0011\u0019w\u000eZ3\u0016\u0003U\u0002\"A\u000e\u001e\u000f\u0005]B\u0004CA\u0014\u001b\u0013\tI$$\u0001\u0004Qe\u0016$WMZ\u0005\u0003wq\u0012aa\u0015;sS:<\'BA\u001d\u001b\u0003\u0015\u0019w\u000eZ3!\u00035\u0001(o\u001c3vGR\u0004&/\u001a4jqV\t\u0001\t\u0005\u0002B\r6\t!I\u0003\u0002D\t\u0006!A.\u00198h\u0015\u0005)\u0015\u0001\u00026bm\u0006L!a\u000f\"\u0002\u0019A\u0014x\u000eZ;di\u0006\u0013\u0018\u000e^=\u0016\u0003%\u0003\"!\u0007&\n\u0005-S\"aA%oi\u0006q\u0001O]8ek\u000e$X\t\\3nK:$HC\u0001(R!\tIr*\u0003\u0002Q5\t\u0019\u0011I\\=\t\u000fI;\u0011\u0011!a\u0001\u0013\u0006\u0019\u0001\u0010J\u0019\u0002\u001fA\u0014x\u000eZ;di&#XM]1u_J,\u0012!\u0016\t\u0004-fsU\"A,\u000b\u0005aS\u0012AC2pY2,7\r^5p]&\u0011!l\u0016\u0002\t\u0013R,\'/\u0019;pe\u0006A1-\u00198FcV\fG\u000e\u0006\u0002^AB\u0011\u0011DX\u0005\u0003?j\u0011qAQ8pY\u0016\fg\u000eC\u0004S\u0013\u0005\u0005\t\u0019\u0001(\u0002\u0011!\f7\u000f[\"pI\u0016$\u0012!S\u0001\ti>\u001cFO]5oOR\t\u0001)\u0001\u0007xe&$XMU3qY\u0006\u001cW\rF\u0001h!\t\t\u0005.\u0003\u0002j\u0005\n1qJ\u00196fGR\u0004
   #9 = Utf8               toString
  #10 = Utf8               ()Ljava/lang/String;
  #11 = Utf8               org/scalatest/tools/AnsiYellow$
  #12 = Class              #11            // org/scalatest/tools/AnsiYellow$
  #13 = Utf8               MODULE$
  #14 = Utf8               Lorg/scalatest/tools/AnsiYellow$;
  #15 = NameAndType        #13:#14        // MODULE$:Lorg/scalatest/tools/AnsiYellow$;
  #16 = Fieldref           #12.#15        // org/scalatest/tools/AnsiYellow$.MODULE$:Lorg/scalatest/tools/AnsiYellow$;
  #17 = NameAndType        #9:#10         // toString:()Ljava/lang/String;
  #18 = Methodref          #12.#17        // org/scalatest/tools/AnsiYellow$.toString:()Ljava/lang/String;
  #19 = Utf8               hashCode
  #20 = Utf8               ()I
  #21 = NameAndType        #19:#20        // hashCode:()I
  #22 = Methodref          #12.#21        // org/scalatest/tools/AnsiYellow$.hashCode:()I
  #23 = Utf8               canEqual
  #24 = Utf8               (Ljava/lang/Object;)Z
  #25 = Utf8               x$1
  #26 = NameAndType        #23:#24        // canEqual:(Ljava/lang/Object;)Z
  #27 = Methodref          #12.#26        // org/scalatest/tools/AnsiYellow$.canEqual:(Ljava/lang/Object;)Z
  #28 = Utf8               Ljava/lang/Object;
  #29 = Utf8               productIterator
  #30 = Utf8               ()Lscala/collection/Iterator;
  #31 = Utf8               ()Lscala/collection/Iterator<Ljava/lang/Object;>;
  #32 = NameAndType        #29:#30        // productIterator:()Lscala/collection/Iterator;
  #33 = Methodref          #12.#32        // org/scalatest/tools/AnsiYellow$.productIterator:()Lscala/collection/Iterator;
  #34 = Utf8               productElement
  #35 = Utf8               (I)Ljava/lang/Object;
  #36 = NameAndType        #34:#35        // productElement:(I)Ljava/lang/Object;
  #37 = Methodref          #12.#36        // org/scalatest/tools/AnsiYellow$.productElement:(I)Ljava/lang/Object;
  #38 = Utf8               I
  #39 = Utf8               productArity
  #40 = NameAndType        #39:#20        // productArity:()I
  #41 = Methodref          #12.#40        // org/scalatest/tools/AnsiYellow$.productArity:()I
  #42 = Utf8               productPrefix
  #43 = NameAndType        #42:#10        // productPrefix:()Ljava/lang/String;
  #44 = Methodref          #12.#43        // org/scalatest/tools/AnsiYellow$.productPrefix:()Ljava/lang/String;
  #45 = Utf8               code
  #46 = NameAndType        #45:#10        // code:()Ljava/lang/String;
  #47 = Methodref          #12.#46        // org/scalatest/tools/AnsiYellow$.code:()Ljava/lang/String;
  #48 = Utf8               productElementNames
  #49 = Utf8               ()Lscala/collection/Iterator<Ljava/lang/String;>;
  #50 = NameAndType        #48:#30        // productElementNames:()Lscala/collection/Iterator;
  #51 = Methodref          #12.#50        // org/scalatest/tools/AnsiYellow$.productElementNames:()Lscala/collection/Iterator;
  #52 = Utf8               productElementName
  #53 = Utf8               (I)Ljava/lang/String;
  #54 = Utf8               n
  #55 = NameAndType        #52:#53        // productElementName:(I)Ljava/lang/String;
  #56 = Methodref          #12.#55        // org/scalatest/tools/AnsiYellow$.productElementName:(I)Ljava/lang/String;
  #57 = Utf8               Code
  #58 = Utf8               LocalVariableTable
  #59 = Utf8               MethodParameters
  #60 = Utf8               Signature
  #61 = Utf8               SourceFile
  #62 = Utf8               RuntimeVisibleAnnotations
  #63 = Utf8               ScalaSig
{
  public static java.lang.String toString();
    descriptor: ()Ljava/lang/String;
    flags: (0x0009) ACC_PUBLIC, ACC_STATIC
    Code:
      stack=1, locals=0, args_size=0
         0: getstatic     #16                 // Field org/scalatest/tools/AnsiYellow$.MODULE$:Lorg/scalatest/tools/AnsiYellow$;
         3: invokevirtual #18                 // Method org/scalatest/tools/AnsiYellow$.toString:()Ljava/lang/String;
         6: areturn

  public static int hashCode();
    descriptor: ()I
    flags: (0x0009) ACC_PUBLIC, ACC_STATIC
    Code:
      stack=1, locals=0, args_size=0
         0: getstatic     #16                 // Field org/scalatest/tools/AnsiYellow$.MODULE$:Lorg/scalatest/tools/AnsiYellow$;
         3: invokevirtual #22                 // Method org/scalatest/tools/AnsiYellow$.hashCode:()I
         6: ireturn

  public static boolean canEqual(java.lang.Object);
    descriptor: (Ljava/lang/Object;)Z
    flags: (0x0009) ACC_PUBLIC, ACC_STATIC
    Code:
      stack=2, locals=1, args_size=1
         0: getstatic     #16                 // Field org/scalatest/tools/AnsiYellow$.MODULE$:Lorg/scalatest/tools/AnsiYellow$;
         3: aload_0
         4: invokevirtual #27                 // Method org/scalatest/tools/AnsiYellow$.canEqual:(Ljava/lang/Object;)Z
         7: ireturn
      LocalVariableTable:
        Start  Length  Slot  Name   Signature
            0       8     0   x$1   Ljava/lang/Object;
    MethodParameters:
      Name                           Flags
      x$1                            final

  public static scala.collection.Iterator<java.lang.Object> productIterator();
    descriptor: ()Lscala/collection/Iterator;
    flags: (0x0009) ACC_PUBLIC, ACC_STATIC
    Code:
      stack=1, locals=0, args_size=0
         0: getstatic     #16                 // Field org/scalatest/tools/AnsiYellow$.MODULE$:Lorg/scalatest/tools/AnsiYellow$;
         3: invokevirtual #33                 // Method org/scalatest/tools/AnsiYellow$.productIterator:()Lscala/collection/Iterator;
         6: areturn
    Signature: #31                          // ()Lscala/collection/Iterator<Ljava/lang/Object;>;

  public static java.lang.Object productElement(int);
    descriptor: (I)Ljava/lang/Object;
    flags: (0x0009) ACC_PUBLIC, ACC_STATIC
    Code:
      stack=2, locals=1, args_size=1
         0: getstatic     #16                 // Field org/scalatest/tools/AnsiYellow$.MODULE$:Lorg/scalatest/tools/AnsiYellow$;
         3: iload_0
         4: invokevirtual #37                 // Method org/scalatest/tools/AnsiYellow$.productElement:(I)Ljava/lang/Object;
         7: areturn
      LocalVariableTable:
        Start  Length  Slot  Name   Signature
            0       8     0   x$1   I
    MethodParameters:
      Name                           Flags
      x$1                            final

  public static int productArity();
    descriptor: ()I
    flags: (0x0009) ACC_PUBLIC, ACC_STATIC
    Code:
      stack=1, locals=0, args_size=0
         0: getstatic     #16                 // Field org/scalatest/tools/AnsiYellow$.MODULE$:Lorg/scalatest/tools/AnsiYellow$;
         3: invokevirtual #41                 // Method org/scalatest/tools/AnsiYellow$.productArity:()I
         6: ireturn

  public static java.lang.String productPrefix();
    descriptor: ()Ljava/lang/String;
    flags: (0x0009) ACC_PUBLIC, ACC_STATIC
    Code:
      stack=1, locals=0, args_size=0
         0: getstatic     #16                 // Field org/scalatest/tools/AnsiYellow$.MODULE$:Lorg/scalatest/tools/AnsiYellow$;
         3: invokevirtual #44                 // Method org/scalatest/tools/AnsiYellow$.productPrefix:()Ljava/lang/String;
         6: areturn

  public static java.lang.String code();
    descriptor: ()Ljava/lang/String;
    flags: (0x0009) ACC_PUBLIC, ACC_STATIC
    Code:
      stack=1, locals=0, args_size=0
         0: getstatic     #16                 // Field org/scalatest/tools/AnsiYellow$.MODULE$:Lorg/scalatest/tools/AnsiYellow$;
         3: invokevirtual #47                 // Method org/scalatest/tools/AnsiYellow$.code:()Ljava/lang/String;
         6: areturn

  public static scala.collection.Iterator<java.lang.String> productElementNames();
    descriptor: ()Lscala/collection/Iterator;
    flags: (0x0009) ACC_PUBLIC, ACC_STATIC
    Code:
      stack=1, locals=0, args_size=0
         0: getstatic     #16                 // Field org/scalatest/tools/AnsiYellow$.MODULE$:Lorg/scalatest/tools/AnsiYellow$;
         3: invokevirtual #51                 // Method org/scalatest/tools/AnsiYellow$.productElementNames:()Lscala/collection/Iterator;
         6: areturn
    Signature: #49                          // ()Lscala/collection/Iterator<Ljava/lang/String;>;

  public static java.lang.String productElementName(int);
    descriptor: (I)Ljava/lang/String;
    flags: (0x0009) ACC_PUBLIC, ACC_STATIC
    Code:
      stack=2, locals=1, args_size=1
         0: getstatic     #16                 // Field org/scalatest/tools/AnsiYellow$.MODULE$:Lorg/scalatest/tools/AnsiYellow$;
         3: iload_0
         4: invokevirtual #56                 // Method org/scalatest/tools/AnsiYellow$.productElementName:(I)Ljava/lang/String;
         7: areturn
      LocalVariableTable:
        Start  Length  Slot  Name   Signature
            0       8     0     n   I
    MethodParameters:
      Name                           Flags
      n                              final
}
SourceFile: "AnsiColor.scala"
RuntimeVisibleAnnotations:
  0: #6(#7=s#8)
    scala.reflect.ScalaSignature(
      bytes="\u0006\u0005)<a!\u0004\b\t\u0002B!bA\u0002\f\u000f\u0011\u0003\u0003r\u0003C\u00032\u0003\u0011\u0005!\u0007C\u00044\u0003\t\u0007I\u0011\u0001\u001b\t\ru\n\u0001\u0015!\u00036\u0011\u001dq\u0014!!A\u0005B}BqaR\u0001\u0002\u0002\u0013\u0005\u0001\nC\u0004M\u0003\u0005\u0005I\u0011A\'\t\u000fM\u000b\u0011\u0011!C!)\"91,AA\u0001\n\u0003a\u0006bB1\u0002\u0003\u0003%\tE\u0019\u0005\bG\u0006\t\t\u0011\"\u0011e\u0011\u001d)\u0017!!A\u0005\n\u0019\f!\"\u00118tSf+G\u000e\\8x\u0015\ty\u0001#A\u0003u_>d7O\u0003\u0002\u0012%\u0005I1oY1mCR,7\u000f\u001e\u0006\u0002\'\u0005\u0019qN]4\u0011\u0005U\tQ\"\u0001\b\u0003\u0015\u0005s7/[-fY2|woE\u0003\u00021y\tC\u0005\u0005\u0002\u001a95\t!DC\u0001\u001c\u0003\u0015\u00198-\u00197b\u0013\ti\"D\u0001\u0004B]f\u0014VM\u001a\t\u0003+}I!\u0001\t\b\u0003\u0013\u0005s7/[\"pY>\u0014\bCA\r#\u0013\t\u0019#DA\u0004Qe>$Wo\u0019;\u0011\u0005\u0015rcB\u0001\u0014-\u001d\t93&D\u0001)\u0015\tI#&\u0001\u0004=e>|GOP\u0002\u0001\u0013\u0005Y\u0012BA\u0017\u001b\u0003\u001d\u0001\u0018mY6bO\u0016L!a\f\u0019\u0003\u0019M+\'/[1mSj\f\'\r\\3\u000b\u00055R\u0012A\u0002\u001fj]&$h\bF\u0001\u0015\u0003\u0011\u0019w\u000eZ3\u0016\u0003U\u0002\"A\u000e\u001e\u000f\u0005]B\u0004CA\u0014\u001b\u0013\tI$$\u0001\u0004Qe\u0016$WMZ\u0005\u0003wq\u0012aa\u0015;sS:<\'BA\u001d\u001b\u0003\u0015\u0019w\u000eZ3!\u00035\u0001(o\u001c3vGR\u0004&/\u001a4jqV\t\u0001\t\u0005\u0002B\r6\t!I\u0003\u0002D\t\u0006!A.\u00198h\u0015\u0005)\u0015\u0001\u00026bm\u0006L!a\u000f\"\u0002\u0019A\u0014x\u000eZ;di\u0006\u0013\u0018\u000e^=\u0016\u0003%\u0003\"!\u0007&\n\u0005-S\"aA%oi\u0006q\u0001O]8ek\u000e$X\t\\3nK:$HC\u0001(R!\tIr*\u0003\u0002Q5\t\u0019\u0011I\\=\t\u000fI;\u0011\u0011!a\u0001\u0013\u0006\u0019\u0001\u0010J\u0019\u0002\u001fA\u0014x\u000eZ;di&#XM]1u_J,\u0012!\u0016\t\u0004-fsU\"A,\u000b\u0005aS\u0012AC2pY2,7\r^5p]&\u0011!l\u0016\u0002\t\u0013R,\'/\u0019;pe\u0006A1-\u00198FcV\fG\u000e\u0006\u0002^AB\u0011\u0011DX\u0005\u0003?j\u0011qAQ8pY\u0016\fg\u000eC\u0004S\u0013\u0005\u0005\t\u0019\u0001(\u0002\u0011!\f7\u000f[\"pI\u0016$\u0012!S\u0001\ti>\u001cFO]5oOR\t\u0001)\u0001\u0007xe&$XMU3qY\u0006\u001cW\rF\u0001h!\t\t\u0005.\u0003\u0002j\u0005\n1qJ\u00196fGR\u0004"
    )
  ScalaSig: length = 0x3 (unknown attribute)
   05 02 00
