Classfile /Users/mw/Projects/slang-braindump/.jar/jar8/assemble/slang-braindump/assemble/content/org/scalatest/tools/DashboardReporter$SlowRecord$1.class
  Last modified May 29, 2022; size 6023 bytes
  SHA-256 checksum a10c5ff878984084cb9aeba1e106f1f79a7bce7a6ca9f73595751e6cde364626
  Compiled from "DashboardReporter.scala"
public class org.scalatest.tools.DashboardReporter$SlowRecord$1 implements scala.Product,java.io.Serializable
  minor version: 0
  major version: 52
  flags: (0x0021) ACC_PUBLIC, ACC_SUPER
  this_class: #2                          // org/scalatest/tools/DashboardReporter$SlowRecord$1
  super_class: #4                         // java/lang/Object
  interfaces: 2, fields: 6, methods: 23, attributes: 5
Constant pool:
    #1 = Utf8               org/scalatest/tools/DashboardReporter$SlowRecord$1
    #2 = Class              #1            // org/scalatest/tools/DashboardReporter$SlowRecord$1
    #3 = Utf8               java/lang/Object
    #4 = Class              #3            // java/lang/Object
    #5 = Utf8               scala/Product
    #6 = Class              #5            // scala/Product
    #7 = Utf8               java/io/Serializable
    #8 = Class              #7            // java/io/Serializable
    #9 = Utf8               DashboardReporter.scala
   #10 = Utf8               org/scalatest/tools/DashboardReporter
   #11 = Class              #10           // org/scalatest/tools/DashboardReporter
   #12 = Utf8               genRecentlySlower$1
   #13 = Utf8               (Lorg/scalatest/tools/Durations;)Ljava/lang/String;
   #14 = NameAndType        #12:#13       // genRecentlySlower$1:(Lorg/scalatest/tools/Durations;)Ljava/lang/String;
   #15 = Utf8               SlowRecord$1
   #16 = Utf8               org/scalatest/tools/Durations$Suite
   #17 = Class              #16           // org/scalatest/tools/Durations$Suite
   #18 = Utf8               org/scalatest/tools/Durations
   #19 = Class              #18           // org/scalatest/tools/Durations
   #20 = Utf8               Suite
   #21 = Utf8               org/scalatest/tools/Durations$Test
   #22 = Class              #21           // org/scalatest/tools/Durations$Test
   #23 = Utf8               Test
   #24 = Utf8               suite
   #25 = Utf8               Lorg/scalatest/tools/Durations$Suite;
   #26 = Utf8               test
   #27 = Utf8               Lorg/scalatest/tools/Durations$Test;
   #28 = Utf8               oldAvg
   #29 = Utf8               I
   #30 = Utf8               newAvg
   #31 = Utf8               percentSlower
   #32 = Utf8               $outer
   #33 = Utf8               Lorg/scalatest/tools/DashboardReporter;
   #34 = Utf8               productElementNames
   #35 = Utf8               ()Lscala/collection/Iterator;
   #36 = Utf8               ()Lscala/collection/Iterator<Ljava/lang/String;>;
   #37 = Utf8               productElementNames$
   #38 = Utf8               (Lscala/Product;)Lscala/collection/Iterator;
   #39 = NameAndType        #37:#38       // productElementNames$:(Lscala/Product;)Lscala/collection/Iterator;
   #40 = InterfaceMethodref #6.#39        // scala/Product.productElementNames$:(Lscala/Product;)Lscala/collection/Iterator;
   #41 = Utf8               this
   #42 = Utf8               Lorg/scalatest/tools/DashboardReporter$SlowRecord$1;
   #43 = Utf8               ()Lorg/scalatest/tools/Durations$Suite;
   #44 = NameAndType        #24:#25       // suite:Lorg/scalatest/tools/Durations$Suite;
   #45 = Fieldref           #2.#44        // org/scalatest/tools/DashboardReporter$SlowRecord$1.suite:Lorg/scalatest/tools/Durations$Suite;
   #46 = Utf8               ()Lorg/scalatest/tools/Durations$Test;
   #47 = NameAndType        #26:#27       // test:Lorg/scalatest/tools/Durations$Test;
   #48 = Fieldref           #2.#47        // org/scalatest/tools/DashboardReporter$SlowRecord$1.test:Lorg/scalatest/tools/Durations$Test;
   #49 = Utf8               ()I
   #50 = NameAndType        #28:#29       // oldAvg:I
   #51 = Fieldref           #2.#50        // org/scalatest/tools/DashboardReporter$SlowRecord$1.oldAvg:I
   #52 = NameAndType        #30:#29       // newAvg:I
   #53 = Fieldref           #2.#52        // org/scalatest/tools/DashboardReporter$SlowRecord$1.newAvg:I
   #54 = NameAndType        #31:#29       // percentSlower:I
   #55 = Fieldref           #2.#54        // org/scalatest/tools/DashboardReporter$SlowRecord$1.percentSlower:I
   #56 = Utf8               toXml
   #57 = Utf8               ()Ljava/lang/String;
   #58 = Utf8               java/lang/StringBuilder
   #59 = Class              #58           // java/lang/StringBuilder
   #60 = Integer            84
   #61 = Utf8               <init>
   #62 = Utf8               (I)V
   #63 = NameAndType        #61:#62       // "<init>":(I)V
   #64 = Methodref          #59.#63       // java/lang/StringBuilder."<init>":(I)V
   #65 = Utf8                     <slowerTest suiteId=\"$suiteId$\" suiteName=\"$suiteName$\" testName=\"$testName$\"
   #66 = String             #65           //       <slowerTest suiteId=\"$suiteId$\" suiteName=\"$suiteName$\" testName=\"$testName$\"
   #67 = Utf8               append
   #68 = Utf8               (Ljava/lang/String;)Ljava/lang/StringBuilder;
   #69 = NameAndType        #67:#68       // append:(Ljava/lang/String;)Ljava/lang/StringBuilder;
   #70 = Methodref          #59.#69       // java/lang/StringBuilder.append:(Ljava/lang/String;)Ljava/lang/StringBuilder;
   #71 = Utf8               scala/collection/StringOps$
   #72 = Class              #71           // scala/collection/StringOps$
   #73 = Utf8               MODULE$
   #74 = Utf8               Lscala/collection/StringOps$;
   #75 = NameAndType        #73:#74       // MODULE$:Lscala/collection/StringOps$;
   #76 = Fieldref           #72.#75       // scala/collection/StringOps$.MODULE$:Lscala/collection/StringOps$;
   #77 = Utf8               scala/Predef$
   #78 = Class              #77           // scala/Predef$
   #79 = Utf8               Lscala/Predef$;
   #80 = NameAndType        #73:#79       // MODULE$:Lscala/Predef$;
   #81 = Fieldref           #78.#80       // scala/Predef$.MODULE$:Lscala/Predef$;
   #82 = Utf8               |oldAvg=\"$oldAvg$\" newAvg=\"$newAvg$\"/>\n               |
   #83 = String             #82           // |oldAvg=\"$oldAvg$\" newAvg=\"$newAvg$\"/>\n               |
   #84 = Utf8               augmentString
   #85 = Utf8               (Ljava/lang/String;)Ljava/lang/String;
   #86 = NameAndType        #84:#85       // augmentString:(Ljava/lang/String;)Ljava/lang/String;
   #87 = Methodref          #78.#86       // scala/Predef$.augmentString:(Ljava/lang/String;)Ljava/lang/String;
   #88 = Utf8               stripMargin$extension
   #89 = NameAndType        #88:#85       // stripMargin$extension:(Ljava/lang/String;)Ljava/lang/String;
   #90 = Methodref          #72.#89       // scala/collection/StringOps$.stripMargin$extension:(Ljava/lang/String;)Ljava/lang/String;
   #91 = Utf8               toString
   #92 = NameAndType        #91:#57       // toString:()Ljava/lang/String;
   #93 = Methodref          #59.#92       // java/lang/StringBuilder.toString:()Ljava/lang/String;
   #94 = Utf8               \\$suiteId\\$
   #95 = String             #94           // \\$suiteId\\$
   #96 = NameAndType        #24:#43       // suite:()Lorg/scalatest/tools/Durations$Suite;
   #97 = Methodref          #2.#96        // org/scalatest/tools/DashboardReporter$SlowRecord$1.suite:()Lorg/scalatest/tools/Durations$Suite;
   #98 = Utf8               suiteId
   #99 = NameAndType        #98:#57       // suiteId:()Ljava/lang/String;
  #100 = Methodref          #17.#99       // org/scalatest/tools/Durations$Suite.suiteId:()Ljava/lang/String;
  #101 = Utf8               java/util/regex/Matcher
  #102 = Class              #101          // java/util/regex/Matcher
  #103 = Utf8               quoteReplacement
  #104 = NameAndType        #103:#85      // quoteReplacement:(Ljava/lang/String;)Ljava/lang/String;
  #105 = Methodref          #102.#104     // java/util/regex/Matcher.quoteReplacement:(Ljava/lang/String;)Ljava/lang/String;
  #106 = Utf8               java/lang/String
  #107 = Class              #106          // java/lang/String
  #108 = Utf8               replaceFirst
  #109 = Utf8               (Ljava/lang/String;Ljava/lang/String;)Ljava/lang/String;
  #110 = NameAndType        #108:#109     // replaceFirst:(Ljava/lang/String;Ljava/lang/String;)Ljava/lang/String;
  #111 = Methodref          #107.#110     // java/lang/String.replaceFirst:(Ljava/lang/String;Ljava/lang/String;)Ljava/lang/String;
  #112 = Utf8               \\$suiteName\\$
  #113 = String             #112          // \\$suiteName\\$
  #114 = Utf8               suiteName
  #115 = NameAndType        #114:#57      // suiteName:()Ljava/lang/String;
  #116 = Methodref          #17.#115      // org/scalatest/tools/Durations$Suite.suiteName:()Ljava/lang/String;
  #117 = Utf8               \\$testName\\$
  #118 = String             #117          // \\$testName\\$
  #119 = NameAndType        #26:#46       // test:()Lorg/scalatest/tools/Durations$Test;
  #120 = Methodref          #2.#119       // org/scalatest/tools/DashboardReporter$SlowRecord$1.test:()Lorg/scalatest/tools/Durations$Test;
  #121 = Utf8               name
  #122 = NameAndType        #121:#57      // name:()Ljava/lang/String;
  #123 = Methodref          #22.#122      // org/scalatest/tools/Durations$Test.name:()Ljava/lang/String;
  #124 = Utf8               \\$oldAvg\\$
  #125 = String             #124          // \\$oldAvg\\$
  #126 = NameAndType        #28:#49       // oldAvg:()I
  #127 = Methodref          #2.#126       // org/scalatest/tools/DashboardReporter$SlowRecord$1.oldAvg:()I
  #128 = Utf8               scala/runtime/BoxesRunTime
  #129 = Class              #128          // scala/runtime/BoxesRunTime
  #130 = Utf8               boxToInteger
  #131 = Utf8               (I)Ljava/lang/Integer;
  #132 = NameAndType        #130:#131     // boxToInteger:(I)Ljava/lang/Integer;
  #133 = Methodref          #129.#132     // scala/runtime/BoxesRunTime.boxToInteger:(I)Ljava/lang/Integer;
  #134 = Utf8               valueOf
  #135 = Utf8               (Ljava/lang/Object;)Ljava/lang/String;
  #136 = NameAndType        #134:#135     // valueOf:(Ljava/lang/Object;)Ljava/lang/String;
  #137 = Methodref          #107.#136     // java/lang/String.valueOf:(Ljava/lang/Object;)Ljava/lang/String;
  #138 = Utf8               \\$newAvg\\$
  #139 = String             #138          // \\$newAvg\\$
  #140 = NameAndType        #30:#49       // newAvg:()I
  #141 = Methodref          #2.#140       // org/scalatest/tools/DashboardReporter$SlowRecord$1.newAvg:()I
  #142 = Utf8               SlowerTestTemplate
  #143 = Utf8               Ljava/lang/String;
  #144 = Utf8               copy
  #145 = Utf8               (Lorg/scalatest/tools/Durations$Suite;Lorg/scalatest/tools/Durations$Test;III)Lorg/scalatest/tools/DashboardReporter$SlowRecord$1;
  #146 = NameAndType        #32:#33       // $outer:Lorg/scalatest/tools/DashboardReporter;
  #147 = Fieldref           #2.#146       // org/scalatest/tools/DashboardReporter$SlowRecord$1.$outer:Lorg/scalatest/tools/DashboardReporter;
  #148 = Utf8               (Lorg/scalatest/tools/DashboardReporter;Lorg/scalatest/tools/Durations$Suite;Lorg/scalatest/tools/Durations$Test;III)V
  #149 = NameAndType        #61:#148      // "<init>":(Lorg/scalatest/tools/DashboardReporter;Lorg/scalatest/tools/Durations$Suite;Lorg/scalatest/tools/Durations$Test;III)V
  #150 = Methodref          #2.#149       // org/scalatest/tools/DashboardReporter$SlowRecord$1."<init>":(Lorg/scalatest/tools/DashboardReporter;Lorg/scalatest/tools/Durations$Suite;Lorg/scalatest/tools/Durations$Test;III)V
  #151 = Utf8               copy$default$1
  #152 = Utf8               copy$default$2
  #153 = Utf8               copy$default$3
  #154 = Utf8               copy$default$4
  #155 = Utf8               copy$default$5
  #156 = NameAndType        #31:#49       // percentSlower:()I
  #157 = Methodref          #2.#156       // org/scalatest/tools/DashboardReporter$SlowRecord$1.percentSlower:()I
  #158 = Utf8               productPrefix
  #159 = Utf8               SlowRecord
  #160 = String             #159          // SlowRecord
  #161 = Utf8               productArity
  #162 = Utf8               productElement
  #163 = Utf8               (I)Ljava/lang/Object;
  #164 = Utf8               x$1
  #165 = Utf8               scala/runtime/Statics
  #166 = Class              #165          // scala/runtime/Statics
  #167 = Utf8               ioobe
  #168 = NameAndType        #167:#163     // ioobe:(I)Ljava/lang/Object;
  #169 = Methodref          #166.#168     // scala/runtime/Statics.ioobe:(I)Ljava/lang/Object;
  #170 = Utf8               productIterator
  #171 = Utf8               ()Lscala/collection/Iterator<Ljava/lang/Object;>;
  #172 = Utf8               scala/runtime/ScalaRunTime$
  #173 = Class              #172          // scala/runtime/ScalaRunTime$
  #174 = Utf8               Lscala/runtime/ScalaRunTime$;
  #175 = NameAndType        #73:#174      // MODULE$:Lscala/runtime/ScalaRunTime$;
  #176 = Fieldref           #173.#175     // scala/runtime/ScalaRunTime$.MODULE$:Lscala/runtime/ScalaRunTime$;
  #177 = Utf8               typedProductIterator
  #178 = NameAndType        #177:#38      // typedProductIterator:(Lscala/Product;)Lscala/collection/Iterator;
  #179 = Methodref          #173.#178     // scala/runtime/ScalaRunTime$.typedProductIterator:(Lscala/Product;)Lscala/collection/Iterator;
  #180 = Utf8               canEqual
  #181 = Utf8               (Ljava/lang/Object;)Z
  #182 = Utf8               Ljava/lang/Object;
  #183 = Utf8               productElementName
  #184 = Utf8               (I)Ljava/lang/String;
  #185 = String             #24           // suite
  #186 = String             #26           // test
  #187 = String             #28           // oldAvg
  #188 = String             #30           // newAvg
  #189 = String             #31           // percentSlower
  #190 = Utf8               hashCode
  #191 = Integer            -889275714
  #192 = NameAndType        #158:#57      // productPrefix:()Ljava/lang/String;
  #193 = Methodref          #2.#192       // org/scalatest/tools/DashboardReporter$SlowRecord$1.productPrefix:()Ljava/lang/String;
  #194 = NameAndType        #190:#49      // hashCode:()I
  #195 = Methodref          #107.#194     // java/lang/String.hashCode:()I
  #196 = Utf8               mix
  #197 = Utf8               (II)I
  #198 = NameAndType        #196:#197     // mix:(II)I
  #199 = Methodref          #166.#198     // scala/runtime/Statics.mix:(II)I
  #200 = Utf8               anyHash
  #201 = Utf8               (Ljava/lang/Object;)I
  #202 = NameAndType        #200:#201     // anyHash:(Ljava/lang/Object;)I
  #203 = Methodref          #166.#202     // scala/runtime/Statics.anyHash:(Ljava/lang/Object;)I
  #204 = Utf8               finalizeHash
  #205 = NameAndType        #204:#197     // finalizeHash:(II)I
  #206 = Methodref          #166.#205     // scala/runtime/Statics.finalizeHash:(II)I
  #207 = Utf8               _toString
  #208 = Utf8               (Lscala/Product;)Ljava/lang/String;
  #209 = NameAndType        #207:#208     // _toString:(Lscala/Product;)Ljava/lang/String;
  #210 = Methodref          #173.#209     // scala/runtime/ScalaRunTime$._toString:(Lscala/Product;)Ljava/lang/String;
  #211 = Utf8               equals
  #212 = NameAndType        #211:#181     // equals:(Ljava/lang/Object;)Z
  #213 = Methodref          #4.#212       // java/lang/Object.equals:(Ljava/lang/Object;)Z
  #214 = NameAndType        #180:#181     // canEqual:(Ljava/lang/Object;)Z
  #215 = Methodref          #2.#214       // org/scalatest/tools/DashboardReporter$SlowRecord$1.canEqual:(Ljava/lang/Object;)Z
  #216 = Utf8               ()V
  #217 = NameAndType        #61:#216      // "<init>":()V
  #218 = Methodref          #4.#217       // java/lang/Object."<init>":()V
  #219 = Utf8               $init$
  #220 = Utf8               (Lscala/Product;)V
  #221 = NameAndType        #219:#220     // $init$:(Lscala/Product;)V
  #222 = InterfaceMethodref #6.#221       // scala/Product.$init$:(Lscala/Product;)V
  #223 = Utf8               Code
  #224 = Utf8               LineNumberTable
  #225 = Utf8               LocalVariableTable
  #226 = Utf8               Signature
  #227 = Utf8               MethodParameters
  #228 = Utf8               StackMapTable
  #229 = Utf8               InnerClasses
  #230 = Utf8               EnclosingMethod
  #231 = Utf8               SourceFile
  #232 = Utf8               ScalaInlineInfo
  #233 = Utf8               Scala
{
  private final org.scalatest.tools.Durations$Suite suite;
    descriptor: Lorg/scalatest/tools/Durations$Suite;
    flags: (0x0012) ACC_PRIVATE, ACC_FINAL

  private final org.scalatest.tools.Durations$Test test;
    descriptor: Lorg/scalatest/tools/Durations$Test;
    flags: (0x0012) ACC_PRIVATE, ACC_FINAL

  private final int oldAvg;
    descriptor: I
    flags: (0x0012) ACC_PRIVATE, ACC_FINAL

  private final int newAvg;
    descriptor: I
    flags: (0x0012) ACC_PRIVATE, ACC_FINAL

  private final int percentSlower;
    descriptor: I
    flags: (0x0012) ACC_PRIVATE, ACC_FINAL

  private final org.scalatest.tools.DashboardReporter $outer;
    descriptor: Lorg/scalatest/tools/DashboardReporter;
    flags: (0x1012) ACC_PRIVATE, ACC_FINAL, ACC_SYNTHETIC

  public scala.collection.Iterator<java.lang.String> productElementNames();
    descriptor: ()Lscala/collection/Iterator;
    flags: (0x0001) ACC_PUBLIC
    Code:
      stack=1, locals=1, args_size=1
         0: aload_0
         1: invokestatic  #40                 // InterfaceMethod scala/Product.productElementNames$:(Lscala/Product;)Lscala/collection/Iterator;
         4: areturn
      LineNumberTable:
        line 429: 0
      LocalVariableTable:
        Start  Length  Slot  Name   Signature
            0       5     0  this   Lorg/scalatest/tools/DashboardReporter$SlowRecord$1;
    Signature: #36                          // ()Lscala/collection/Iterator<Ljava/lang/String;>;

  public org.scalatest.tools.Durations$Suite suite();
    descriptor: ()Lorg/scalatest/tools/Durations$Suite;
    flags: (0x0001) ACC_PUBLIC
    Code:
      stack=1, locals=1, args_size=1
         0: aload_0
         1: getfield      #45                 // Field suite:Lorg/scalatest/tools/Durations$Suite;
         4: areturn
      LineNumberTable:
        line 429: 0
      LocalVariableTable:
        Start  Length  Slot  Name   Signature
            0       5     0  this   Lorg/scalatest/tools/DashboardReporter$SlowRecord$1;

  public org.scalatest.tools.Durations$Test test();
    descriptor: ()Lorg/scalatest/tools/Durations$Test;
    flags: (0x0001) ACC_PUBLIC
    Code:
      stack=1, locals=1, args_size=1
         0: aload_0
         1: getfield      #48                 // Field test:Lorg/scalatest/tools/Durations$Test;
         4: areturn
      LineNumberTable:
        line 429: 0
      LocalVariableTable:
        Start  Length  Slot  Name   Signature
            0       5     0  this   Lorg/scalatest/tools/DashboardReporter$SlowRecord$1;

  public int oldAvg();
    descriptor: ()I
    flags: (0x0001) ACC_PUBLIC
    Code:
      stack=1, locals=1, args_size=1
         0: aload_0
         1: getfield      #51                 // Field oldAvg:I
         4: ireturn
      LineNumberTable:
        line 430: 0
      LocalVariableTable:
        Start  Length  Slot  Name   Signature
            0       5     0  this   Lorg/scalatest/tools/DashboardReporter$SlowRecord$1;

  public int newAvg();
    descriptor: ()I
    flags: (0x0001) ACC_PUBLIC
    Code:
      stack=1, locals=1, args_size=1
         0: aload_0
         1: getfield      #53                 // Field newAvg:I
         4: ireturn
      LineNumberTable:
        line 430: 0
      LocalVariableTable:
        Start  Length  Slot  Name   Signature
            0       5     0  this   Lorg/scalatest/tools/DashboardReporter$SlowRecord$1;

  public int percentSlower();
    descriptor: ()I
    flags: (0x0001) ACC_PUBLIC
    Code:
      stack=1, locals=1, args_size=1
         0: aload_0
         1: getfield      #55                 // Field percentSlower:I
         4: ireturn
      LineNumberTable:
        line 430: 0
      LocalVariableTable:
        Start  Length  Slot  Name   Signature
            0       5     0  this   Lorg/scalatest/tools/DashboardReporter$SlowRecord$1;

  public java.lang.String toXml();
    descriptor: ()Ljava/lang/String;
    flags: (0x0001) ACC_PUBLIC
    Code:
      stack=4, locals=2, args_size=1
         0: new           #59                 // class java/lang/StringBuilder
         3: dup
         4: ldc           #60                 // int 84
         6: invokespecial #64                 // Method java/lang/StringBuilder."<init>":(I)V
         9: ldc           #66                 // String       <slowerTest suiteId=\"$suiteId$\" suiteName=\"$suiteName$\" testName=\"$testName$\"
        11: invokevirtual #70                 // Method java/lang/StringBuilder.append:(Ljava/lang/String;)Ljava/lang/StringBuilder;
        14: getstatic     #76                 // Field scala/collection/StringOps$.MODULE$:Lscala/collection/StringOps$;
        17: getstatic     #81                 // Field scala/Predef$.MODULE$:Lscala/Predef$;
        20: ldc           #83                 // String |oldAvg=\"$oldAvg$\" newAvg=\"$newAvg$\"/>\n               |
        22: invokevirtual #87                 // Method scala/Predef$.augmentString:(Ljava/lang/String;)Ljava/lang/String;
        25: invokevirtual #90                 // Method scala/collection/StringOps$.stripMargin$extension:(Ljava/lang/String;)Ljava/lang/String;
        28: invokevirtual #70                 // Method java/lang/StringBuilder.append:(Ljava/lang/String;)Ljava/lang/StringBuilder;
        31: invokevirtual #93                 // Method java/lang/StringBuilder.toString:()Ljava/lang/String;
        34: astore_1
        35: aload_1
        36: ldc           #95                 // String \\$suiteId\\$
        38: aload_0
        39: invokevirtual #97                 // Method suite:()Lorg/scalatest/tools/Durations$Suite;
        42: invokevirtual #100                // Method org/scalatest/tools/Durations$Suite.suiteId:()Ljava/lang/String;
        45: invokestatic  #105                // Method java/util/regex/Matcher.quoteReplacement:(Ljava/lang/String;)Ljava/lang/String;
        48: invokevirtual #111                // Method java/lang/String.replaceFirst:(Ljava/lang/String;Ljava/lang/String;)Ljava/lang/String;
        51: ldc           #113                // String \\$suiteName\\$
        53: aload_0
        54: invokevirtual #97                 // Method suite:()Lorg/scalatest/tools/Durations$Suite;
        57: invokevirtual #116                // Method org/scalatest/tools/Durations$Suite.suiteName:()Ljava/lang/String;
        60: invokestatic  #105                // Method java/util/regex/Matcher.quoteReplacement:(Ljava/lang/String;)Ljava/lang/String;
        63: invokevirtual #111                // Method java/lang/String.replaceFirst:(Ljava/lang/String;Ljava/lang/String;)Ljava/lang/String;
        66: ldc           #118                // String \\$testName\\$
        68: aload_0
        69: invokevirtual #120                // Method test:()Lorg/scalatest/tools/Durations$Test;
        72: invokevirtual #123                // Method org/scalatest/tools/Durations$Test.name:()Ljava/lang/String;
        75: invokestatic  #105                // Method java/util/regex/Matcher.quoteReplacement:(Ljava/lang/String;)Ljava/lang/String;
        78: invokevirtual #111                // Method java/lang/String.replaceFirst:(Ljava/lang/String;Ljava/lang/String;)Ljava/lang/String;
        81: ldc           #125                // String \\$oldAvg\\$
        83: aload_0
        84: invokevirtual #127                // Method oldAvg:()I
        87: invokestatic  #133                // Method scala/runtime/BoxesRunTime.boxToInteger:(I)Ljava/lang/Integer;
        90: invokestatic  #137                // Method java/lang/String.valueOf:(Ljava/lang/Object;)Ljava/lang/String;
        93: invokevirtual #111                // Method java/lang/String.replaceFirst:(Ljava/lang/String;Ljava/lang/String;)Ljava/lang/String;
        96: ldc           #139                // String \\$newAvg\\$
        98: aload_0
        99: invokevirtual #141                // Method newAvg:()I
       102: invokestatic  #133                // Method scala/runtime/BoxesRunTime.boxToInteger:(I)Ljava/lang/Integer;
       105: invokestatic  #137                // Method java/lang/String.valueOf:(Ljava/lang/Object;)Ljava/lang/String;
       108: invokevirtual #111                // Method java/lang/String.replaceFirst:(Ljava/lang/String;Ljava/lang/String;)Ljava/lang/String;
       111: areturn
      LineNumberTable:
        line 435: 0
        line 434: 9
        line 436: 17
        line 439: 35
        line 440: 36
        line 441: 51
        line 442: 66
        line 443: 81
        line 444: 96
      LocalVariableTable:
        Start  Length  Slot  Name   Signature
           35      76     1 SlowerTestTemplate   Ljava/lang/String;
            0     112     0  this   Lorg/scalatest/tools/DashboardReporter$SlowRecord$1;

  public org.scalatest.tools.DashboardReporter$SlowRecord$1 copy(org.scalatest.tools.Durations$Suite, org.scalatest.tools.Durations$Test, int, int, int);
    descriptor: (Lorg/scalatest/tools/Durations$Suite;Lorg/scalatest/tools/Durations$Test;III)Lorg/scalatest/tools/DashboardReporter$SlowRecord$1;
    flags: (0x0001) ACC_PUBLIC
    Code:
      stack=8, locals=6, args_size=6
         0: new           #2                  // class org/scalatest/tools/DashboardReporter$SlowRecord$1
         3: dup
         4: aload_0
         5: getfield      #147                // Field $outer:Lorg/scalatest/tools/DashboardReporter;
         8: aload_1
         9: aload_2
        10: iload_3
        11: iload         4
        13: iload         5
        15: invokespecial #150                // Method "<init>":(Lorg/scalatest/tools/DashboardReporter;Lorg/scalatest/tools/Durations$Suite;Lorg/scalatest/tools/Durations$Test;III)V
        18: areturn
      LineNumberTable:
        line 429: 0
        line 430: 10
      LocalVariableTable:
        Start  Length  Slot  Name   Signature
            0      19     0  this   Lorg/scalatest/tools/DashboardReporter$SlowRecord$1;
            0      19     1 suite   Lorg/scalatest/tools/Durations$Suite;
            0      19     2  test   Lorg/scalatest/tools/Durations$Test;
            0      19     3 oldAvg   I
            0      19     4 newAvg   I
            0      19     5 percentSlower   I
    MethodParameters:
      Name                           Flags
      suite                          final
      test                           final
      oldAvg                         final
      newAvg                         final
      percentSlower                  final

  public org.scalatest.tools.Durations$Suite copy$default$1();
    descriptor: ()Lorg/scalatest/tools/Durations$Suite;
    flags: (0x0001) ACC_PUBLIC
    Code:
      stack=1, locals=1, args_size=1
         0: aload_0
         1: invokevirtual #97                 // Method suite:()Lorg/scalatest/tools/Durations$Suite;
         4: areturn
      LineNumberTable:
        line 429: 0
      LocalVariableTable:
        Start  Length  Slot  Name   Signature
            0       5     0  this   Lorg/scalatest/tools/DashboardReporter$SlowRecord$1;

  public org.scalatest.tools.Durations$Test copy$default$2();
    descriptor: ()Lorg/scalatest/tools/Durations$Test;
    flags: (0x0001) ACC_PUBLIC
    Code:
      stack=1, locals=1, args_size=1
         0: aload_0
         1: invokevirtual #120                // Method test:()Lorg/scalatest/tools/Durations$Test;
         4: areturn
      LineNumberTable:
        line 429: 0
      LocalVariableTable:
        Start  Length  Slot  Name   Signature
            0       5     0  this   Lorg/scalatest/tools/DashboardReporter$SlowRecord$1;

  public int copy$default$3();
    descriptor: ()I
    flags: (0x0001) ACC_PUBLIC
    Code:
      stack=1, locals=1, args_size=1
         0: aload_0
         1: invokevirtual #127                // Method oldAvg:()I
         4: ireturn
      LineNumberTable:
        line 430: 0
      LocalVariableTable:
        Start  Length  Slot  Name   Signature
            0       5     0  this   Lorg/scalatest/tools/DashboardReporter$SlowRecord$1;

  public int copy$default$4();
    descriptor: ()I
    flags: (0x0001) ACC_PUBLIC
    Code:
      stack=1, locals=1, args_size=1
         0: aload_0
         1: invokevirtual #141                // Method newAvg:()I
         4: ireturn
      LineNumberTable:
        line 430: 0
      LocalVariableTable:
        Start  Length  Slot  Name   Signature
            0       5     0  this   Lorg/scalatest/tools/DashboardReporter$SlowRecord$1;

  public int copy$default$5();
    descriptor: ()I
    flags: (0x0001) ACC_PUBLIC
    Code:
      stack=1, locals=1, args_size=1
         0: aload_0
         1: invokevirtual #157                // Method percentSlower:()I
         4: ireturn
      LineNumberTable:
        line 430: 0
      LocalVariableTable:
        Start  Length  Slot  Name   Signature
            0       5     0  this   Lorg/scalatest/tools/DashboardReporter$SlowRecord$1;

  public java.lang.String productPrefix();
    descriptor: ()Ljava/lang/String;
    flags: (0x0001) ACC_PUBLIC
    Code:
      stack=1, locals=1, args_size=1
         0: ldc           #160                // String SlowRecord
         2: areturn
      LineNumberTable:
        line 429: 0
      LocalVariableTable:
        Start  Length  Slot  Name   Signature
            0       3     0  this   Lorg/scalatest/tools/DashboardReporter$SlowRecord$1;

  public int productArity();
    descriptor: ()I
    flags: (0x0001) ACC_PUBLIC
    Code:
      stack=1, locals=1, args_size=1
         0: iconst_5
         1: ireturn
      LineNumberTable:
        line 429: 0
      LocalVariableTable:
        Start  Length  Slot  Name   Signature
            0       2     0  this   Lorg/scalatest/tools/DashboardReporter$SlowRecord$1;

  public java.lang.Object productElement(int);
    descriptor: (I)Ljava/lang/Object;
    flags: (0x0001) ACC_PUBLIC
    Code:
      stack=1, locals=3, args_size=2
         0: iload_1
         1: istore_2
         2: iload_2
         3: tableswitch   { // 0 to 4
                       0: 36
                       1: 43
                       2: 50
                       3: 60
                       4: 70
                 default: 80
            }
        36: aload_0
        37: invokevirtual #97                 // Method suite:()Lorg/scalatest/tools/Durations$Suite;
        40: goto          87
        43: aload_0
        44: invokevirtual #120                // Method test:()Lorg/scalatest/tools/Durations$Test;
        47: goto          87
        50: aload_0
        51: invokevirtual #127                // Method oldAvg:()I
        54: invokestatic  #133                // Method scala/runtime/BoxesRunTime.boxToInteger:(I)Ljava/lang/Integer;
        57: goto          87
        60: aload_0
        61: invokevirtual #141                // Method newAvg:()I
        64: invokestatic  #133                // Method scala/runtime/BoxesRunTime.boxToInteger:(I)Ljava/lang/Integer;
        67: goto          87
        70: aload_0
        71: invokevirtual #157                // Method percentSlower:()I
        74: invokestatic  #133                // Method scala/runtime/BoxesRunTime.boxToInteger:(I)Ljava/lang/Integer;
        77: goto          87
        80: iload_1
        81: invokestatic  #169                // Method scala/runtime/Statics.ioobe:(I)Ljava/lang/Object;
        84: goto          87
        87: areturn
      StackMapTable: number_of_entries = 7
        frame_type = 252 /* append */
          offset_delta = 36
          locals = [ int ]
        frame_type = 6 /* same */
        frame_type = 6 /* same */
        frame_type = 9 /* same */
        frame_type = 9 /* same */
        frame_type = 9 /* same */
        frame_type = 70 /* same_locals_1_stack_item */
          stack = [ class java/lang/Object ]
      LineNumberTable:
        line 429: 0
      LocalVariableTable:
        Start  Length  Slot  Name   Signature
            0      88     0  this   Lorg/scalatest/tools/DashboardReporter$SlowRecord$1;
            0      88     1   x$1   I
    MethodParameters:
      Name                           Flags
      x$1                            final

  public scala.collection.Iterator<java.lang.Object> productIterator();
    descriptor: ()Lscala/collection/Iterator;
    flags: (0x0001) ACC_PUBLIC
    Code:
      stack=2, locals=1, args_size=1
         0: getstatic     #176                // Field scala/runtime/ScalaRunTime$.MODULE$:Lscala/runtime/ScalaRunTime$;
         3: aload_0
         4: invokevirtual #179                // Method scala/runtime/ScalaRunTime$.typedProductIterator:(Lscala/Product;)Lscala/collection/Iterator;
         7: areturn
      LineNumberTable:
        line 429: 0
      LocalVariableTable:
        Start  Length  Slot  Name   Signature
            0       8     0  this   Lorg/scalatest/tools/DashboardReporter$SlowRecord$1;
    Signature: #171                         // ()Lscala/collection/Iterator<Ljava/lang/Object;>;

  public boolean canEqual(java.lang.Object);
    descriptor: (Ljava/lang/Object;)Z
    flags: (0x0001) ACC_PUBLIC
    Code:
      stack=1, locals=2, args_size=2
         0: aload_1
         1: instanceof    #2                  // class org/scalatest/tools/DashboardReporter$SlowRecord$1
         4: ireturn
      LineNumberTable:
        line 429: 0
      LocalVariableTable:
        Start  Length  Slot  Name   Signature
            0       5     0  this   Lorg/scalatest/tools/DashboardReporter$SlowRecord$1;
            0       5     1   x$1   Ljava/lang/Object;
    MethodParameters:
      Name                           Flags
      x$1                            final

  public java.lang.String productElementName(int);
    descriptor: (I)Ljava/lang/String;
    flags: (0x0001) ACC_PUBLIC
    Code:
      stack=1, locals=3, args_size=2
         0: iload_1
         1: istore_2
         2: iload_2
         3: tableswitch   { // 0 to 4
                       0: 36
                       1: 41
                       2: 46
                       3: 51
                       4: 56
                 default: 61
            }
        36: ldc           #185                // String suite
        38: goto          71
        41: ldc           #186                // String test
        43: goto          71
        46: ldc           #187                // String oldAvg
        48: goto          71
        51: ldc           #188                // String newAvg
        53: goto          71
        56: ldc           #189                // String percentSlower
        58: goto          71
        61: iload_1
        62: invokestatic  #169                // Method scala/runtime/Statics.ioobe:(I)Ljava/lang/Object;
        65: checkcast     #107                // class java/lang/String
        68: goto          71
        71: areturn
      StackMapTable: number_of_entries = 7
        frame_type = 252 /* append */
          offset_delta = 36
          locals = [ int ]
        frame_type = 4 /* same */
        frame_type = 4 /* same */
        frame_type = 4 /* same */
        frame_type = 4 /* same */
        frame_type = 4 /* same */
        frame_type = 73 /* same_locals_1_stack_item */
          stack = [ class java/lang/String ]
      LineNumberTable:
        line 429: 0
      LocalVariableTable:
        Start  Length  Slot  Name   Signature
            0      72     0  this   Lorg/scalatest/tools/DashboardReporter$SlowRecord$1;
            0      72     1   x$1   I
    MethodParameters:
      Name                           Flags
      x$1                            final

  public int hashCode();
    descriptor: ()I
    flags: (0x0001) ACC_PUBLIC
    Code:
      stack=2, locals=2, args_size=1
         0: ldc           #191                // int -889275714
         2: istore_1
         3: iload_1
         4: aload_0
         5: invokevirtual #193                // Method productPrefix:()Ljava/lang/String;
         8: invokevirtual #195                // Method java/lang/String.hashCode:()I
        11: invokestatic  #199                // Method scala/runtime/Statics.mix:(II)I
        14: istore_1
        15: iload_1
        16: aload_0
        17: invokevirtual #97                 // Method suite:()Lorg/scalatest/tools/Durations$Suite;
        20: invokestatic  #203                // Method scala/runtime/Statics.anyHash:(Ljava/lang/Object;)I
        23: invokestatic  #199                // Method scala/runtime/Statics.mix:(II)I
        26: istore_1
        27: iload_1
        28: aload_0
        29: invokevirtual #120                // Method test:()Lorg/scalatest/tools/Durations$Test;
        32: invokestatic  #203                // Method scala/runtime/Statics.anyHash:(Ljava/lang/Object;)I
        35: invokestatic  #199                // Method scala/runtime/Statics.mix:(II)I
        38: istore_1
        39: iload_1
        40: aload_0
        41: invokevirtual #127                // Method oldAvg:()I
        44: invokestatic  #199                // Method scala/runtime/Statics.mix:(II)I
        47: istore_1
        48: iload_1
        49: aload_0
        50: invokevirtual #141                // Method newAvg:()I
        53: invokestatic  #199                // Method scala/runtime/Statics.mix:(II)I
        56: istore_1
        57: iload_1
        58: aload_0
        59: invokevirtual #157                // Method percentSlower:()I
        62: invokestatic  #199                // Method scala/runtime/Statics.mix:(II)I
        65: istore_1
        66: iload_1
        67: iconst_5
        68: invokestatic  #206                // Method scala/runtime/Statics.finalizeHash:(II)I
        71: ireturn
      LineNumberTable:
        line 429: 0
      LocalVariableTable:
        Start  Length  Slot  Name   Signature
            0      72     0  this   Lorg/scalatest/tools/DashboardReporter$SlowRecord$1;

  public java.lang.String toString();
    descriptor: ()Ljava/lang/String;
    flags: (0x0001) ACC_PUBLIC
    Code:
      stack=2, locals=1, args_size=1
         0: getstatic     #176                // Field scala/runtime/ScalaRunTime$.MODULE$:Lscala/runtime/ScalaRunTime$;
         3: aload_0
         4: invokevirtual #210                // Method scala/runtime/ScalaRunTime$._toString:(Lscala/Product;)Ljava/lang/String;
         7: areturn
      LineNumberTable:
        line 429: 0
      LocalVariableTable:
        Start  Length  Slot  Name   Signature
            0       8     0  this   Lorg/scalatest/tools/DashboardReporter$SlowRecord$1;

  public boolean equals(java.lang.Object);
    descriptor: (Ljava/lang/Object;)Z
    flags: (0x0001) ACC_PUBLIC
    Code:
      stack=2, locals=7, args_size=2
         0: aload_0
         1: aload_1
         2: if_acmpeq     154
         5: aload_1
         6: astore_3
         7: aload_3
         8: instanceof    #2                  // class org/scalatest/tools/DashboardReporter$SlowRecord$1
        11: ifeq          19
        14: iconst_1
        15: istore_2
        16: goto          27
        19: goto          22
        22: iconst_0
        23: istore_2
        24: goto          27
        27: iload_2
        28: ifeq          158
        31: aload_1
        32: checkcast     #2                  // class org/scalatest/tools/DashboardReporter$SlowRecord$1
        35: astore        4
        37: aload_0
        38: invokevirtual #127                // Method oldAvg:()I
        41: aload         4
        43: invokevirtual #127                // Method oldAvg:()I
        46: if_icmpne     150
        49: aload_0
        50: invokevirtual #141                // Method newAvg:()I
        53: aload         4
        55: invokevirtual #141                // Method newAvg:()I
        58: if_icmpne     150
        61: aload_0
        62: invokevirtual #157                // Method percentSlower:()I
        65: aload         4
        67: invokevirtual #157                // Method percentSlower:()I
        70: if_icmpne     150
        73: aload_0
        74: invokevirtual #97                 // Method suite:()Lorg/scalatest/tools/Durations$Suite;
        77: aload         4
        79: invokevirtual #97                 // Method suite:()Lorg/scalatest/tools/Durations$Suite;
        82: astore        5
        84: dup
        85: ifnonnull     97
        88: pop
        89: aload         5
        91: ifnull        105
        94: goto          150
        97: aload         5
        99: invokevirtual #213                // Method java/lang/Object.equals:(Ljava/lang/Object;)Z
       102: ifeq          150
       105: aload_0
       106: invokevirtual #120                // Method test:()Lorg/scalatest/tools/Durations$Test;
       109: aload         4
       111: invokevirtual #120                // Method test:()Lorg/scalatest/tools/Durations$Test;
       114: astore        6
       116: dup
       117: ifnonnull     129
       120: pop
       121: aload         6
       123: ifnull        137
       126: goto          150
       129: aload         6
       131: invokevirtual #213                // Method java/lang/Object.equals:(Ljava/lang/Object;)Z
       134: ifeq          150
       137: aload         4
       139: aload_0
       140: invokevirtual #215                // Method canEqual:(Ljava/lang/Object;)Z
       143: ifeq          150
       146: iconst_1
       147: goto          151
       150: iconst_0
       151: ifeq          158
       154: iconst_1
       155: goto          159
       158: iconst_0
       159: ireturn
      StackMapTable: number_of_entries = 12
        frame_type = 253 /* append */
          offset_delta = 19
          locals = [ top, class java/lang/Object ]
        frame_type = 2 /* same */
        frame_type = 255 /* full_frame */
          offset_delta = 4
          locals = [ class org/scalatest/tools/DashboardReporter$SlowRecord$1, class java/lang/Object, int, class java/lang/Object ]
          stack = []
        frame_type = 255 /* full_frame */
          offset_delta = 69
          locals = [ class org/scalatest/tools/DashboardReporter$SlowRecord$1, class java/lang/Object, int, class java/lang/Object, class org/scalatest/tools/DashboardReporter$SlowRecord$1, class org/scalatest/tools/Durations$Suite ]
          stack = [ class org/scalatest/tools/Durations$Suite ]
        frame_type = 7 /* same */
        frame_type = 255 /* full_frame */
          offset_delta = 23
          locals = [ class org/scalatest/tools/DashboardReporter$SlowRecord$1, class java/lang/Object, int, class java/lang/Object, class org/scalatest/tools/DashboardReporter$SlowRecord$1, class org/scalatest/tools/Durations$Suite, class org/scalatest/tools/Durations$Test ]
          stack = [ class org/scalatest/tools/Durations$Test ]
        frame_type = 7 /* same */
        frame_type = 249 /* chop */
          offset_delta = 12
        frame_type = 64 /* same_locals_1_stack_item */
          stack = [ int ]
        frame_type = 248 /* chop */
          offset_delta = 2
        frame_type = 253 /* append */
          offset_delta = 3
          locals = [ int, class java/lang/Object ]
        frame_type = 255 /* full_frame */
          offset_delta = 0
          locals = [ class org/scalatest/tools/DashboardReporter$SlowRecord$1, class java/lang/Object ]
          stack = [ int ]
      LineNumberTable:
        line 429: 0
      LocalVariableTable:
        Start  Length  Slot  Name   Signature
            0     160     0  this   Lorg/scalatest/tools/DashboardReporter$SlowRecord$1;
            0     160     1   x$1   Ljava/lang/Object;
    MethodParameters:
      Name                           Flags
      x$1                            final

  public org.scalatest.tools.DashboardReporter$SlowRecord$1(org.scalatest.tools.DashboardReporter, org.scalatest.tools.Durations$Suite, org.scalatest.tools.Durations$Test, int, int, int);
    descriptor: (Lorg/scalatest/tools/DashboardReporter;Lorg/scalatest/tools/Durations$Suite;Lorg/scalatest/tools/Durations$Test;III)V
    flags: (0x0001) ACC_PUBLIC
    Code:
      stack=2, locals=7, args_size=7
         0: aload_0
         1: aload_2
         2: putfield      #45                 // Field suite:Lorg/scalatest/tools/Durations$Suite;
         5: aload_0
         6: aload_3
         7: putfield      #48                 // Field test:Lorg/scalatest/tools/Durations$Test;
        10: aload_0
        11: iload         4
        13: putfield      #51                 // Field oldAvg:I
        16: aload_0
        17: iload         5
        19: putfield      #53                 // Field newAvg:I
        22: aload_0
        23: iload         6
        25: putfield      #55                 // Field percentSlower:I
        28: aload_1
        29: ifnonnull     34
        32: aconst_null
        33: athrow
        34: aload_0
        35: aload_1
        36: putfield      #147                // Field $outer:Lorg/scalatest/tools/DashboardReporter;
        39: aload_0
        40: invokespecial #218                // Method java/lang/Object."<init>":()V
        43: aload_0
        44: invokestatic  #222                // InterfaceMethod scala/Product.$init$:(Lscala/Product;)V
        47: return
      StackMapTable: number_of_entries = 1
        frame_type = 34 /* same */
      LineNumberTable:
        line 429: 0
        line 430: 10
        line 429: 28
      LocalVariableTable:
        Start  Length  Slot  Name   Signature
            0      48     0  this   Lorg/scalatest/tools/DashboardReporter$SlowRecord$1;
            0      48     1 $outer   Lorg/scalatest/tools/DashboardReporter;
            0      48     2 suite   Lorg/scalatest/tools/Durations$Suite;
            0      48     3  test   Lorg/scalatest/tools/Durations$Test;
            0      48     4 oldAvg   I
            0      48     5 newAvg   I
            0      48     6 percentSlower   I
    MethodParameters:
      Name                           Flags
      $outer                         final synthetic
      suite                          final
      test                           final
      oldAvg                         final
      newAvg                         final
      percentSlower                  final
}
InnerClasses:
  public #15= #2;                         // SlowRecord$1=class org/scalatest/tools/DashboardReporter$SlowRecord$1
  public #20= #17 of #19;                 // Suite=class org/scalatest/tools/Durations$Suite of class org/scalatest/tools/Durations
  public #23= #22 of #19;                 // Test=class org/scalatest/tools/Durations$Test of class org/scalatest/tools/Durations
EnclosingMethod: #11.#14                // org.scalatest.tools.DashboardReporter.genRecentlySlower$1
SourceFile: "DashboardReporter.scala"
  ScalaInlineInfo: length = 0x77 (unknown attribute)
   01 01 00 17 00 3D 00 94 01 00 B4 00 B5 01 00 90
   00 91 01 00 97 00 2B 01 00 98 00 2E 01 00 99 00
   31 01 00 9A 00 31 01 00 9B 00 31 01 00 D3 00 B5
   01 00 BE 00 31 01 00 1E 00 31 01 00 1C 00 31 01
   00 1F 00 31 01 00 A1 00 31 01 00 A2 00 A3 01 00
   B7 00 B8 01 00 22 00 23 01 00 AA 00 23 01 00 9E
   00 39 01 00 18 00 2B 01 00 1A 00 2E 01 00 5B 00
   39 01 00 38 00 39 01
  Scala: length = 0x0 (unknown attribute)

