Classfile /Users/mw/Projects/slang-braindump/.jar/jar8/assemble/slang-braindump/assemble/content/org/scalatest/tools/DashboardReporterConfiguration.class
  Last modified May 29, 2022; size 6981 bytes
  SHA-256 checksum 116b2f8dd2302d6c2307a639ed03eea3948e92719323f95e16688e475bc09837
  Compiled from "ReporterConfiguration.scala"
public class org.scalatest.tools.DashboardReporterConfiguration extends org.scalatest.tools.ReporterConfiguration
  minor version: 0
  major version: 52
  flags: (0x0021) ACC_PUBLIC, ACC_SUPER
  this_class: #2                          // org/scalatest/tools/DashboardReporterConfiguration
  super_class: #4                         // org/scalatest/tools/ReporterConfiguration
  interfaces: 0, fields: 3, methods: 21, attributes: 4
Constant pool:
    #1 = Utf8               org/scalatest/tools/DashboardReporterConfiguration
    #2 = Class              #1            // org/scalatest/tools/DashboardReporterConfiguration
    #3 = Utf8               org/scalatest/tools/ReporterConfiguration
    #4 = Class              #3            // org/scalatest/tools/ReporterConfiguration
    #5 = Utf8               ReporterConfiguration.scala
    #6 = Utf8               Lscala/reflect/ScalaSignature;
    #7 = Utf8               bytes
    #8 = Utf8               \u0006\u0005\u0005ud!\u0002\u000f\u001e\u0001v\u0019\u0003\u0002C\u001e\u0001\u0005+\u0007I\u0011\u0001\u001f\t\u0011!\u0003!\u0011#Q\u0001\nuB\u0001\"\u0013\u0001\u0003\u0016\u0004%\tA\u0013\u0005\t\u001d\u0002\u0011\t\u0012)A\u0005\u0017\"Aq\n\u0001BK\u0002\u0013\u0005\u0001\u000b\u0003\u0005U\u0001\tE\t\u0015!\u0003R\u0011\u0015)\u0006\u0001\"\u0001W\u0011\u001dY\u0006!!A\u0005\u0002qCq\u0001\u0019\u0001\u0012\u0002\u0013\u0005\u0011\rC\u0004m\u0001E\u0005I\u0011A7\t\u000f=\u0004\u0011\u0013!C\u0001a\"9!\u000fAA\u0001\n\u0003\u001a\bbB>\u0001\u0003\u0003%\t\u0001\u0015\u0005\by\u0002\t\t\u0011\"\u0001~\u0011%\t9\u0001AA\u0001\n\u0003\nI\u0001C\u0005\u0002\u0018\u0001\t\t\u0011\"\u0001\u0002\u001a!I\u00111\u0005\u0001\u0002\u0002\u0013\u0005\u0013Q\u0005\u0005\n\u0003S\u0001\u0011\u0011!C!\u0003WA\u0011\"!\f\u0001\u0003\u0003%\t%a\f\t\u0013\u0005E\u0002!!A\u0005B\u0005MrACA\u001c;\u0005\u0005\t\u0012A\u000f\u0002:\u0019IA$HA\u0001\u0012\u0003i\u00121\b\u0005\u0007+Z!\t!a\u0015\t\u0013\u00055b#!A\u0005F\u0005=\u0002\"CA+-\u0005\u0005I\u0011QA,\u0011%\tyFFA\u0001\n\u0003\u000b\t\u0007C\u0005\u0002tY\t\t\u0011\"\u0003\u0002v\tqB)Y:iE>\f\'\u000f\u001a*fa>\u0014H/\u001a:D_:4\u0017nZ;sCRLwN\u001c\u0006\u0003=}\tQ\u0001^8pYNT!\u0001I\u0011\u0002\u0013M\u001c\u0017\r\\1uKN$(\"\u0001\u0012\u0002\u0007=\u0014xm\u0005\u0003\u0001I!r\u0003CA\u0013\'\u001b\u0005i\u0012BA\u0014\u001e\u0005U\u0011V\r]8si\u0016\u00148i\u001c8gS\u001e,(/\u0019;j_:\u0004\"!\u000b\u0017\u000e\u0003)R\u0011aK\u0001\u0006g\u000e\fG.Y\u0005\u0003[)\u0012q\u0001\u0015:pIV\u001cG\u000f\u0005\u00020q9\u0011\u0001G\u000e\b\u0003cUj\u0011A\r\u0006\u0003gQ\na\u0001\u0010:p_Rt4\u0001A\u0005\u0002W%\u0011qGK\u0001\ba\u0006\u001c7.Y4f\u0013\tI$H\u0001\u0007TKJL\u0017\r\\5{C\ndWM\u0003\u00028U\u0005I1m\u001c8gS\u001e\u001cV\r^\u000b\u0002{A\u0019aHQ#\u000f\u0005}\u0002\u0005CA\u0019+\u0013\t\t%&\u0001\u0004Qe\u0016$WMZ\u0005\u0003\u0007\u0012\u00131aU3u\u0015\t\t%\u0006\u0005\u0002&\r&\u0011q)\b\u0002\u0014%\u0016\u0004xN\u001d;fe\u000e{gNZ5h!\u0006\u0014\u0018-\\\u0001\u000bG>tg-[4TKR\u0004\u0013\u0001\u00034jY\u0016t\u0015-\\3\u0016\u0003-\u0003\"A\u0010\'\n\u00055#%AB*ue&tw-A\u0005gS2,g*Y7fA\u0005\tb.^7PY\u00124\u0015\u000e\\3t)>\\U-\u001a9\u0016\u0003E\u0003\"!\u000b*\n\u0005MS#aA%oi\u0006\u0011b.^7PY\u00124\u0015\u000e\\3t)>\\U-\u001a9!\u0003\u0019a\u0014N\\5u}Q!q\u000bW-[!\t)\u0003\u0001C\u0003<\u000f\u0001\u0007Q\bC\u0003J\u000f\u0001\u00071\nC\u0003P\u000f\u0001\u0007\u0011+\u0001\u0003d_BLH\u0003B,^=~Cqa\u000f\u0005\u0011\u0002\u0003\u0007Q\bC\u0004J\u0011A\u0005\t\u0019A&\t\u000f=C\u0001\u0013!a\u0001#\u0006q1m\u001c9zI\u0011,g-Y;mi\u0012\nT#\u00012+\u0005u\u001a7&\u00013\u0011\u0005\u0015TW\"\u00014\u000b\u0005\u001dD\u0017!C;oG\",7m[3e\u0015\tI\'&\u0001\u0006b]:|G/\u0019;j_:L!a\u001b4\u0003#Ut7\r[3dW\u0016$g+\u0019:jC:\u001cW-\u0001\bd_BLH\u0005Z3gCVdG\u000f\n\u001a\u0016\u00039T#aS2\u0002\u001d\r|\u0007/\u001f\u0013eK\u001a\fW\u000f\u001c;%gU\t\u0011O\u000b\u0002RG\u0006i\u0001O]8ek\u000e$\bK]3gSb,\u0012\u0001\u001e\t\u0003kjl\u0011A\u001e\u0006\u0003ob\fA\u0001\\1oO*\t\u00110\u0001\u0003kCZ\f\u0017BA\'w\u00031\u0001(o\u001c3vGR\f%/\u001b;z\u00039\u0001(o\u001c3vGR,E.Z7f]R$2A`A\u0002!\tIs0C\u0002\u0002\u0002)\u00121!\u00118z\u0011!\t)ADA\u0001\u0002\u0004\t\u0016a\u0001=%c\u0005y\u0001O]8ek\u000e$\u0018\n^3sCR|\'/\u0006\u0002\u0002\fA)\u0011QBA\n}6\u0011\u0011q\u0002\u0006\u0004\u0003#Q\u0013AC2pY2,7\r^5p]&!\u0011QCA\b\u0005!IE/\u001a:bi>\u0014\u0018\u0001C2b]\u0016\u000bX/\u00197\u0015\t\u0005m\u0011\u0011\u0005\t\u0004S\u0005u\u0011bAA\u0010U\t9!i\\8mK\u0006t\u0007\u0002CA\u0003!\u0005\u0005\t\u0019\u0001@\u0002%A\u0014x\u000eZ;di\u0016cW-\\3oi:\u000bW.\u001a\u000b\u0004i\u0006\u001d\u0002\u0002CA\u0003#\u0005\u0005\t\u0019A)\u0002\u0011!\f7\u000f[\"pI\u0016$\u0012!U\u0001\ti>\u001cFO]5oOR\tA/\u0001\u0004fcV\fGn\u001d\u000b\u0005\u00037\t)\u0004\u0003\u0005\u0002\u0006Q\t\t\u00111\u0001\u007f\u0003y!\u0015m\u001d5c_\u0006\u0014HMU3q_J$XM]\"p]\u001aLw-\u001e:bi&|g\u000e\u0005\u0002&-M)a#!\u0010\u0002JAA\u0011qHA#{-\u000bv+\u0004\u0002\u0002B)\u0019\u00111\t\u0016\u0002\u000fI,h\u000e^5nK&!\u0011qIA!\u0005E\t%m\u001d;sC\u000e$h)\u001e8di&|gn\r\t\u0005\u0003\u0017\n\t&\u0004\u0002\u0002N)\u0019\u0011q\n=\u0002\u0005%|\u0017bA\u001d\u0002NQ\u0011\u0011\u0011H\u0001\u0006CB\u0004H.\u001f\u000b\b/\u0006e\u00131LA/\u0011\u0015Y\u0014\u00041\u0001>\u0011\u0015I\u0015\u00041\u0001L\u0011\u0015y\u0015\u00041\u0001R\u0003\u001d)h.\u00199qYf$B!a\u0019\u0002pA)\u0011&!\u001a\u0002j%\u0019\u0011q\r\u0016\u0003\r=\u0003H/[8o!\u0019I\u00131N\u001fL#&\u0019\u0011Q\u000e\u0016\u0003\rQ+\b\u000f\\34\u0011!\t\tHGA\u0001\u0002\u00049\u0016a\u0001=%a\u0005aqO]5uKJ+\u0007\u000f\\1dKR\u0011\u0011q\u000f\t\u0004k\u0006e\u0014bAA>m\n1qJ\u00196fGR\u0004
    #9 = Utf8               configSet
   #10 = Utf8               Lscala/collection/immutable/Set;
   #11 = Utf8               Lscala/collection/immutable/Set<Lorg/scalatest/tools/ReporterConfigParam;>;
   #12 = Utf8               fileName
   #13 = Utf8               Ljava/lang/String;
   #14 = Utf8               numOldFilesToKeep
   #15 = Utf8               I
   #16 = Utf8               unapply
   #17 = Utf8               (Lorg/scalatest/tools/DashboardReporterConfiguration;)Lscala/Option;
   #18 = Utf8               (Lorg/scalatest/tools/DashboardReporterConfiguration;)Lscala/Option<Lscala/Tuple3<Lscala/collection/immutable/Set<Lorg/scalatest/tools/ReporterConfigParam;>;Ljava/lang/String;Ljava/lang/Object;>;>;
   #19 = Utf8               x$0
   #20 = Utf8               org/scalatest/tools/DashboardReporterConfiguration$
   #21 = Class              #20           // org/scalatest/tools/DashboardReporterConfiguration$
   #22 = Utf8               MODULE$
   #23 = Utf8               Lorg/scalatest/tools/DashboardReporterConfiguration$;
   #24 = NameAndType        #22:#23       // MODULE$:Lorg/scalatest/tools/DashboardReporterConfiguration$;
   #25 = Fieldref           #21.#24       // org/scalatest/tools/DashboardReporterConfiguration$.MODULE$:Lorg/scalatest/tools/DashboardReporterConfiguration$;
   #26 = NameAndType        #16:#17       // unapply:(Lorg/scalatest/tools/DashboardReporterConfiguration;)Lscala/Option;
   #27 = Methodref          #21.#26       // org/scalatest/tools/DashboardReporterConfiguration$.unapply:(Lorg/scalatest/tools/DashboardReporterConfiguration;)Lscala/Option;
   #28 = Utf8               Lorg/scalatest/tools/DashboardReporterConfiguration;
   #29 = Utf8               apply
   #30 = Utf8               (Lscala/collection/immutable/Set;Ljava/lang/String;I)Lorg/scalatest/tools/DashboardReporterConfiguration;
   #31 = Utf8               (Lscala/collection/immutable/Set<Lorg/scalatest/tools/ReporterConfigParam;>;Ljava/lang/String;I)Lorg/scalatest/tools/DashboardReporterConfiguration;
   #32 = NameAndType        #29:#30       // apply:(Lscala/collection/immutable/Set;Ljava/lang/String;I)Lorg/scalatest/tools/DashboardReporterConfiguration;
   #33 = Methodref          #21.#32       // org/scalatest/tools/DashboardReporterConfiguration$.apply:(Lscala/collection/immutable/Set;Ljava/lang/String;I)Lorg/scalatest/tools/DashboardReporterConfiguration;
   #34 = Utf8               tupled
   #35 = Utf8               ()Lscala/Function1;
   #36 = Utf8               ()Lscala/Function1<Lscala/Tuple3<Lscala/collection/immutable/Set<Lorg/scalatest/tools/ReporterConfigParam;>;Ljava/lang/String;Ljava/lang/Object;>;Lorg/scalatest/tools/DashboardReporterConfiguration;>;
   #37 = NameAndType        #34:#35       // tupled:()Lscala/Function1;
   #38 = Methodref          #21.#37       // org/scalatest/tools/DashboardReporterConfiguration$.tupled:()Lscala/Function1;
   #39 = Utf8               curried
   #40 = Utf8               ()Lscala/Function1<Lscala/collection/immutable/Set<Lorg/scalatest/tools/ReporterConfigParam;>;Lscala/Function1<Ljava/lang/String;Lscala/Function1<Ljava/lang/Object;Lorg/scalatest/tools/DashboardReporterConfiguration;>;>;>;
   #41 = NameAndType        #39:#35       // curried:()Lscala/Function1;
   #42 = Methodref          #21.#41       // org/scalatest/tools/DashboardReporterConfiguration$.curried:()Lscala/Function1;
   #43 = Utf8               ()Lscala/collection/immutable/Set;
   #44 = Utf8               ()Lscala/collection/immutable/Set<Lorg/scalatest/tools/ReporterConfigParam;>;
   #45 = NameAndType        #9:#10        // configSet:Lscala/collection/immutable/Set;
   #46 = Fieldref           #2.#45        // org/scalatest/tools/DashboardReporterConfiguration.configSet:Lscala/collection/immutable/Set;
   #47 = Utf8               this
   #48 = Utf8               ()Ljava/lang/String;
   #49 = NameAndType        #12:#13       // fileName:Ljava/lang/String;
   #50 = Fieldref           #2.#49        // org/scalatest/tools/DashboardReporterConfiguration.fileName:Ljava/lang/String;
   #51 = Utf8               ()I
   #52 = NameAndType        #14:#15       // numOldFilesToKeep:I
   #53 = Fieldref           #2.#52        // org/scalatest/tools/DashboardReporterConfiguration.numOldFilesToKeep:I
   #54 = Utf8               copy
   #55 = Utf8               <init>
   #56 = Utf8               (Lscala/collection/immutable/Set;Ljava/lang/String;I)V
   #57 = NameAndType        #55:#56       // "<init>":(Lscala/collection/immutable/Set;Ljava/lang/String;I)V
   #58 = Methodref          #2.#57        // org/scalatest/tools/DashboardReporterConfiguration."<init>":(Lscala/collection/immutable/Set;Ljava/lang/String;I)V
   #59 = Utf8               copy$default$1
   #60 = NameAndType        #9:#43        // configSet:()Lscala/collection/immutable/Set;
   #61 = Methodref          #2.#60        // org/scalatest/tools/DashboardReporterConfiguration.configSet:()Lscala/collection/immutable/Set;
   #62 = Utf8               copy$default$2
   #63 = NameAndType        #12:#48       // fileName:()Ljava/lang/String;
   #64 = Methodref          #2.#63        // org/scalatest/tools/DashboardReporterConfiguration.fileName:()Ljava/lang/String;
   #65 = Utf8               copy$default$3
   #66 = NameAndType        #14:#51       // numOldFilesToKeep:()I
   #67 = Methodref          #2.#66        // org/scalatest/tools/DashboardReporterConfiguration.numOldFilesToKeep:()I
   #68 = Utf8               productPrefix
   #69 = Utf8               DashboardReporterConfiguration
   #70 = String             #69           // DashboardReporterConfiguration
   #71 = Utf8               productArity
   #72 = Utf8               productElement
   #73 = Utf8               (I)Ljava/lang/Object;
   #74 = Utf8               x$1
   #75 = Utf8               scala/runtime/BoxesRunTime
   #76 = Class              #75           // scala/runtime/BoxesRunTime
   #77 = Utf8               boxToInteger
   #78 = Utf8               (I)Ljava/lang/Integer;
   #79 = NameAndType        #77:#78       // boxToInteger:(I)Ljava/lang/Integer;
   #80 = Methodref          #76.#79       // scala/runtime/BoxesRunTime.boxToInteger:(I)Ljava/lang/Integer;
   #81 = Utf8               scala/runtime/Statics
   #82 = Class              #81           // scala/runtime/Statics
   #83 = Utf8               ioobe
   #84 = NameAndType        #83:#73       // ioobe:(I)Ljava/lang/Object;
   #85 = Methodref          #82.#84       // scala/runtime/Statics.ioobe:(I)Ljava/lang/Object;
   #86 = Utf8               java/lang/Object
   #87 = Class              #86           // java/lang/Object
   #88 = Utf8               productIterator
   #89 = Utf8               ()Lscala/collection/Iterator;
   #90 = Utf8               ()Lscala/collection/Iterator<Ljava/lang/Object;>;
   #91 = Utf8               scala/runtime/ScalaRunTime$
   #92 = Class              #91           // scala/runtime/ScalaRunTime$
   #93 = Utf8               Lscala/runtime/ScalaRunTime$;
   #94 = NameAndType        #22:#93       // MODULE$:Lscala/runtime/ScalaRunTime$;
   #95 = Fieldref           #92.#94       // scala/runtime/ScalaRunTime$.MODULE$:Lscala/runtime/ScalaRunTime$;
   #96 = Utf8               typedProductIterator
   #97 = Utf8               (Lscala/Product;)Lscala/collection/Iterator;
   #98 = NameAndType        #96:#97       // typedProductIterator:(Lscala/Product;)Lscala/collection/Iterator;
   #99 = Methodref          #92.#98       // scala/runtime/ScalaRunTime$.typedProductIterator:(Lscala/Product;)Lscala/collection/Iterator;
  #100 = Utf8               canEqual
  #101 = Utf8               (Ljava/lang/Object;)Z
  #102 = Utf8               Ljava/lang/Object;
  #103 = Utf8               productElementName
  #104 = Utf8               (I)Ljava/lang/String;
  #105 = String             #9            // configSet
  #106 = String             #12           // fileName
  #107 = String             #14           // numOldFilesToKeep
  #108 = Utf8               java/lang/String
  #109 = Class              #108          // java/lang/String
  #110 = Utf8               hashCode
  #111 = Integer            -889275714
  #112 = NameAndType        #68:#48       // productPrefix:()Ljava/lang/String;
  #113 = Methodref          #2.#112       // org/scalatest/tools/DashboardReporterConfiguration.productPrefix:()Ljava/lang/String;
  #114 = NameAndType        #110:#51      // hashCode:()I
  #115 = Methodref          #109.#114     // java/lang/String.hashCode:()I
  #116 = Utf8               mix
  #117 = Utf8               (II)I
  #118 = NameAndType        #116:#117     // mix:(II)I
  #119 = Methodref          #82.#118      // scala/runtime/Statics.mix:(II)I
  #120 = Utf8               anyHash
  #121 = Utf8               (Ljava/lang/Object;)I
  #122 = NameAndType        #120:#121     // anyHash:(Ljava/lang/Object;)I
  #123 = Methodref          #82.#122      // scala/runtime/Statics.anyHash:(Ljava/lang/Object;)I
  #124 = Utf8               finalizeHash
  #125 = NameAndType        #124:#117     // finalizeHash:(II)I
  #126 = Methodref          #82.#125      // scala/runtime/Statics.finalizeHash:(II)I
  #127 = Utf8               toString
  #128 = Utf8               _toString
  #129 = Utf8               (Lscala/Product;)Ljava/lang/String;
  #130 = NameAndType        #128:#129     // _toString:(Lscala/Product;)Ljava/lang/String;
  #131 = Methodref          #92.#130      // scala/runtime/ScalaRunTime$._toString:(Lscala/Product;)Ljava/lang/String;
  #132 = Utf8               equals
  #133 = NameAndType        #132:#101     // equals:(Ljava/lang/Object;)Z
  #134 = Methodref          #87.#133      // java/lang/Object.equals:(Ljava/lang/Object;)Z
  #135 = NameAndType        #100:#101     // canEqual:(Ljava/lang/Object;)Z
  #136 = Methodref          #2.#135       // org/scalatest/tools/DashboardReporterConfiguration.canEqual:(Ljava/lang/Object;)Z
  #137 = Utf8               scala/collection/immutable/Set
  #138 = Class              #137          // scala/collection/immutable/Set
  #139 = Utf8               (Lscala/collection/immutable/Set<Lorg/scalatest/tools/ReporterConfigParam;>;Ljava/lang/String;I)V
  #140 = Utf8               ()V
  #141 = NameAndType        #55:#140      // "<init>":()V
  #142 = Methodref          #4.#141       // org/scalatest/tools/ReporterConfiguration."<init>":()V
  #143 = Utf8               Signature
  #144 = Utf8               Code
  #145 = Utf8               LocalVariableTable
  #146 = Utf8               MethodParameters
  #147 = Utf8               LineNumberTable
  #148 = Utf8               StackMapTable
  #149 = Utf8               SourceFile
  #150 = Utf8               RuntimeVisibleAnnotations
  #151 = Utf8               ScalaInlineInfo
  #152 = Utf8               ScalaSig
{
  private final scala.collection.immutable.Set<org.scalatest.tools.ReporterConfigParam> configSet;
    descriptor: Lscala/collection/immutable/Set;
    flags: (0x0012) ACC_PRIVATE, ACC_FINAL
    Signature: #11                          // Lscala/collection/immutable/Set<Lorg/scalatest/tools/ReporterConfigParam;>;

  private final java.lang.String fileName;
    descriptor: Ljava/lang/String;
    flags: (0x0012) ACC_PRIVATE, ACC_FINAL

  private final int numOldFilesToKeep;
    descriptor: I
    flags: (0x0012) ACC_PRIVATE, ACC_FINAL

  public static scala.Option<scala.Tuple3<scala.collection.immutable.Set<org.scalatest.tools.ReporterConfigParam>, java.lang.String, java.lang.Object>> unapply(org.scalatest.tools.DashboardReporterConfiguration);
    descriptor: (Lorg/scalatest/tools/DashboardReporterConfiguration;)Lscala/Option;
    flags: (0x0009) ACC_PUBLIC, ACC_STATIC
    Code:
      stack=2, locals=1, args_size=1
         0: getstatic     #25                 // Field org/scalatest/tools/DashboardReporterConfiguration$.MODULE$:Lorg/scalatest/tools/DashboardReporterConfiguration$;
         3: aload_0
         4: invokevirtual #27                 // Method org/scalatest/tools/DashboardReporterConfiguration$.unapply:(Lorg/scalatest/tools/DashboardReporterConfiguration;)Lscala/Option;
         7: areturn
      LocalVariableTable:
        Start  Length  Slot  Name   Signature
            0       8     0   x$0   Lorg/scalatest/tools/DashboardReporterConfiguration;
    Signature: #18                          // (Lorg/scalatest/tools/DashboardReporterConfiguration;)Lscala/Option<Lscala/Tuple3<Lscala/collection/immutable/Set<Lorg/scalatest/tools/ReporterConfigParam;>;Ljava/lang/String;Ljava/lang/Object;>;>;
    MethodParameters:
      Name                           Flags
      x$0                            final

  public static org.scalatest.tools.DashboardReporterConfiguration apply(scala.collection.immutable.Set<org.scalatest.tools.ReporterConfigParam>, java.lang.String, int);
    descriptor: (Lscala/collection/immutable/Set;Ljava/lang/String;I)Lorg/scalatest/tools/DashboardReporterConfiguration;
    flags: (0x0009) ACC_PUBLIC, ACC_STATIC
    Code:
      stack=4, locals=3, args_size=3
         0: getstatic     #25                 // Field org/scalatest/tools/DashboardReporterConfiguration$.MODULE$:Lorg/scalatest/tools/DashboardReporterConfiguration$;
         3: aload_0
         4: aload_1
         5: iload_2
         6: invokevirtual #33                 // Method org/scalatest/tools/DashboardReporterConfiguration$.apply:(Lscala/collection/immutable/Set;Ljava/lang/String;I)Lorg/scalatest/tools/DashboardReporterConfiguration;
         9: areturn
      LocalVariableTable:
        Start  Length  Slot  Name   Signature
            0      10     0 configSet   Lscala/collection/immutable/Set;
            0      10     1 fileName   Ljava/lang/String;
            0      10     2 numOldFilesToKeep   I
    Signature: #31                          // (Lscala/collection/immutable/Set<Lorg/scalatest/tools/ReporterConfigParam;>;Ljava/lang/String;I)Lorg/scalatest/tools/DashboardReporterConfiguration;
    MethodParameters:
      Name                           Flags
      configSet                      final
      fileName                       final
      numOldFilesToKeep              final

  public static scala.Function1<scala.Tuple3<scala.collection.immutable.Set<org.scalatest.tools.ReporterConfigParam>, java.lang.String, java.lang.Object>, org.scalatest.tools.DashboardReporterConfiguration> tupled();
    descriptor: ()Lscala/Function1;
    flags: (0x0009) ACC_PUBLIC, ACC_STATIC
    Code:
      stack=1, locals=0, args_size=0
         0: getstatic     #25                 // Field org/scalatest/tools/DashboardReporterConfiguration$.MODULE$:Lorg/scalatest/tools/DashboardReporterConfiguration$;
         3: invokevirtual #38                 // Method org/scalatest/tools/DashboardReporterConfiguration$.tupled:()Lscala/Function1;
         6: areturn
    Signature: #36                          // ()Lscala/Function1<Lscala/Tuple3<Lscala/collection/immutable/Set<Lorg/scalatest/tools/ReporterConfigParam;>;Ljava/lang/String;Ljava/lang/Object;>;Lorg/scalatest/tools/DashboardReporterConfiguration;>;

  public static scala.Function1<scala.collection.immutable.Set<org.scalatest.tools.ReporterConfigParam>, scala.Function1<java.lang.String, scala.Function1<java.lang.Object, org.scalatest.tools.DashboardReporterConfiguration>>> curried();
    descriptor: ()Lscala/Function1;
    flags: (0x0009) ACC_PUBLIC, ACC_STATIC
    Code:
      stack=1, locals=0, args_size=0
         0: getstatic     #25                 // Field org/scalatest/tools/DashboardReporterConfiguration$.MODULE$:Lorg/scalatest/tools/DashboardReporterConfiguration$;
         3: invokevirtual #42                 // Method org/scalatest/tools/DashboardReporterConfiguration$.curried:()Lscala/Function1;
         6: areturn
    Signature: #40                          // ()Lscala/Function1<Lscala/collection/immutable/Set<Lorg/scalatest/tools/ReporterConfigParam;>;Lscala/Function1<Ljava/lang/String;Lscala/Function1<Ljava/lang/Object;Lorg/scalatest/tools/DashboardReporterConfiguration;>;>;>;

  public scala.collection.immutable.Set<org.scalatest.tools.ReporterConfigParam> configSet();
    descriptor: ()Lscala/collection/immutable/Set;
    flags: (0x0001) ACC_PUBLIC
    Code:
      stack=1, locals=1, args_size=1
         0: aload_0
         1: getfield      #46                 // Field configSet:Lscala/collection/immutable/Set;
         4: areturn
      LineNumberTable:
        line 33: 0
      LocalVariableTable:
        Start  Length  Slot  Name   Signature
            0       5     0  this   Lorg/scalatest/tools/DashboardReporterConfiguration;
    Signature: #44                          // ()Lscala/collection/immutable/Set<Lorg/scalatest/tools/ReporterConfigParam;>;

  public java.lang.String fileName();
    descriptor: ()Ljava/lang/String;
    flags: (0x0001) ACC_PUBLIC
    Code:
      stack=1, locals=1, args_size=1
         0: aload_0
         1: getfield      #50                 // Field fileName:Ljava/lang/String;
         4: areturn
      LineNumberTable:
        line 33: 0
      LocalVariableTable:
        Start  Length  Slot  Name   Signature
            0       5     0  this   Lorg/scalatest/tools/DashboardReporterConfiguration;

  public int numOldFilesToKeep();
    descriptor: ()I
    flags: (0x0001) ACC_PUBLIC
    Code:
      stack=1, locals=1, args_size=1
         0: aload_0
         1: getfield      #53                 // Field numOldFilesToKeep:I
         4: ireturn
      LineNumberTable:
        line 33: 0
      LocalVariableTable:
        Start  Length  Slot  Name   Signature
            0       5     0  this   Lorg/scalatest/tools/DashboardReporterConfiguration;

  public org.scalatest.tools.DashboardReporterConfiguration copy(scala.collection.immutable.Set<org.scalatest.tools.ReporterConfigParam>, java.lang.String, int);
    descriptor: (Lscala/collection/immutable/Set;Ljava/lang/String;I)Lorg/scalatest/tools/DashboardReporterConfiguration;
    flags: (0x0001) ACC_PUBLIC
    Code:
      stack=5, locals=4, args_size=4
         0: new           #2                  // class org/scalatest/tools/DashboardReporterConfiguration
         3: dup
         4: aload_1
         5: aload_2
         6: iload_3
         7: invokespecial #58                 // Method "<init>":(Lscala/collection/immutable/Set;Ljava/lang/String;I)V
        10: areturn
      LineNumberTable:
        line 33: 0
      LocalVariableTable:
        Start  Length  Slot  Name   Signature
            0      11     0  this   Lorg/scalatest/tools/DashboardReporterConfiguration;
            0      11     1 configSet   Lscala/collection/immutable/Set;
            0      11     2 fileName   Ljava/lang/String;
            0      11     3 numOldFilesToKeep   I
    Signature: #31                          // (Lscala/collection/immutable/Set<Lorg/scalatest/tools/ReporterConfigParam;>;Ljava/lang/String;I)Lorg/scalatest/tools/DashboardReporterConfiguration;
    MethodParameters:
      Name                           Flags
      configSet                      final
      fileName                       final
      numOldFilesToKeep              final

  public scala.collection.immutable.Set<org.scalatest.tools.ReporterConfigParam> copy$default$1();
    descriptor: ()Lscala/collection/immutable/Set;
    flags: (0x0001) ACC_PUBLIC
    Code:
      stack=1, locals=1, args_size=1
         0: aload_0
         1: invokevirtual #61                 // Method configSet:()Lscala/collection/immutable/Set;
         4: areturn
      LineNumberTable:
        line 33: 0
      LocalVariableTable:
        Start  Length  Slot  Name   Signature
            0       5     0  this   Lorg/scalatest/tools/DashboardReporterConfiguration;
    Signature: #44                          // ()Lscala/collection/immutable/Set<Lorg/scalatest/tools/ReporterConfigParam;>;

  public java.lang.String copy$default$2();
    descriptor: ()Ljava/lang/String;
    flags: (0x0001) ACC_PUBLIC
    Code:
      stack=1, locals=1, args_size=1
         0: aload_0
         1: invokevirtual #64                 // Method fileName:()Ljava/lang/String;
         4: areturn
      LineNumberTable:
        line 33: 0
      LocalVariableTable:
        Start  Length  Slot  Name   Signature
            0       5     0  this   Lorg/scalatest/tools/DashboardReporterConfiguration;

  public int copy$default$3();
    descriptor: ()I
    flags: (0x0001) ACC_PUBLIC
    Code:
      stack=1, locals=1, args_size=1
         0: aload_0
         1: invokevirtual #67                 // Method numOldFilesToKeep:()I
         4: ireturn
      LineNumberTable:
        line 33: 0
      LocalVariableTable:
        Start  Length  Slot  Name   Signature
            0       5     0  this   Lorg/scalatest/tools/DashboardReporterConfiguration;

  public java.lang.String productPrefix();
    descriptor: ()Ljava/lang/String;
    flags: (0x0001) ACC_PUBLIC
    Code:
      stack=1, locals=1, args_size=1
         0: ldc           #70                 // String DashboardReporterConfiguration
         2: areturn
      LineNumberTable:
        line 33: 0
      LocalVariableTable:
        Start  Length  Slot  Name   Signature
            0       3     0  this   Lorg/scalatest/tools/DashboardReporterConfiguration;

  public int productArity();
    descriptor: ()I
    flags: (0x0001) ACC_PUBLIC
    Code:
      stack=1, locals=1, args_size=1
         0: iconst_3
         1: ireturn
      LineNumberTable:
        line 33: 0
      LocalVariableTable:
        Start  Length  Slot  Name   Signature
            0       2     0  this   Lorg/scalatest/tools/DashboardReporterConfiguration;

  public java.lang.Object productElement(int);
    descriptor: (I)Ljava/lang/Object;
    flags: (0x0001) ACC_PUBLIC
    Code:
      stack=1, locals=3, args_size=2
         0: iload_1
         1: istore_2
         2: iload_2
         3: tableswitch   { // 0 to 2
                       0: 28
                       1: 35
                       2: 42
                 default: 52
            }
        28: aload_0
        29: invokevirtual #61                 // Method configSet:()Lscala/collection/immutable/Set;
        32: goto          59
        35: aload_0
        36: invokevirtual #64                 // Method fileName:()Ljava/lang/String;
        39: goto          59
        42: aload_0
        43: invokevirtual #67                 // Method numOldFilesToKeep:()I
        46: invokestatic  #80                 // Method scala/runtime/BoxesRunTime.boxToInteger:(I)Ljava/lang/Integer;
        49: goto          59
        52: iload_1
        53: invokestatic  #85                 // Method scala/runtime/Statics.ioobe:(I)Ljava/lang/Object;
        56: goto          59
        59: areturn
      StackMapTable: number_of_entries = 5
        frame_type = 252 /* append */
          offset_delta = 28
          locals = [ int ]
        frame_type = 6 /* same */
        frame_type = 6 /* same */
        frame_type = 9 /* same */
        frame_type = 70 /* same_locals_1_stack_item */
          stack = [ class java/lang/Object ]
      LineNumberTable:
        line 33: 0
      LocalVariableTable:
        Start  Length  Slot  Name   Signature
            0      60     0  this   Lorg/scalatest/tools/DashboardReporterConfiguration;
            0      60     1   x$1   I
    MethodParameters:
      Name                           Flags
      x$1                            final

  public scala.collection.Iterator<java.lang.Object> productIterator();
    descriptor: ()Lscala/collection/Iterator;
    flags: (0x0001) ACC_PUBLIC
    Code:
      stack=2, locals=1, args_size=1
         0: getstatic     #95                 // Field scala/runtime/ScalaRunTime$.MODULE$:Lscala/runtime/ScalaRunTime$;
         3: aload_0
         4: invokevirtual #99                 // Method scala/runtime/ScalaRunTime$.typedProductIterator:(Lscala/Product;)Lscala/collection/Iterator;
         7: areturn
      LineNumberTable:
        line 33: 0
      LocalVariableTable:
        Start  Length  Slot  Name   Signature
            0       8     0  this   Lorg/scalatest/tools/DashboardReporterConfiguration;
    Signature: #90                          // ()Lscala/collection/Iterator<Ljava/lang/Object;>;

  public boolean canEqual(java.lang.Object);
    descriptor: (Ljava/lang/Object;)Z
    flags: (0x0001) ACC_PUBLIC
    Code:
      stack=1, locals=2, args_size=2
         0: aload_1
         1: instanceof    #2                  // class org/scalatest/tools/DashboardReporterConfiguration
         4: ireturn
      LineNumberTable:
        line 33: 0
      LocalVariableTable:
        Start  Length  Slot  Name   Signature
            0       5     0  this   Lorg/scalatest/tools/DashboardReporterConfiguration;
            0       5     1   x$1   Ljava/lang/Object;
    MethodParameters:
      Name                           Flags
      x$1                            final

  public java.lang.String productElementName(int);
    descriptor: (I)Ljava/lang/String;
    flags: (0x0001) ACC_PUBLIC
    Code:
      stack=1, locals=3, args_size=2
         0: iload_1
         1: istore_2
         2: iload_2
         3: tableswitch   { // 0 to 2
                       0: 28
                       1: 33
                       2: 38
                 default: 43
            }
        28: ldc           #105                // String configSet
        30: goto          53
        33: ldc           #106                // String fileName
        35: goto          53
        38: ldc           #107                // String numOldFilesToKeep
        40: goto          53
        43: iload_1
        44: invokestatic  #85                 // Method scala/runtime/Statics.ioobe:(I)Ljava/lang/Object;
        47: checkcast     #109                // class java/lang/String
        50: goto          53
        53: areturn
      StackMapTable: number_of_entries = 5
        frame_type = 252 /* append */
          offset_delta = 28
          locals = [ int ]
        frame_type = 4 /* same */
        frame_type = 4 /* same */
        frame_type = 4 /* same */
        frame_type = 73 /* same_locals_1_stack_item */
          stack = [ class java/lang/String ]
      LineNumberTable:
        line 33: 0
      LocalVariableTable:
        Start  Length  Slot  Name   Signature
            0      54     0  this   Lorg/scalatest/tools/DashboardReporterConfiguration;
            0      54     1   x$1   I
    MethodParameters:
      Name                           Flags
      x$1                            final

  public int hashCode();
    descriptor: ()I
    flags: (0x0001) ACC_PUBLIC
    Code:
      stack=2, locals=2, args_size=1
         0: ldc           #111                // int -889275714
         2: istore_1
         3: iload_1
         4: aload_0
         5: invokevirtual #113                // Method productPrefix:()Ljava/lang/String;
         8: invokevirtual #115                // Method java/lang/String.hashCode:()I
        11: invokestatic  #119                // Method scala/runtime/Statics.mix:(II)I
        14: istore_1
        15: iload_1
        16: aload_0
        17: invokevirtual #61                 // Method configSet:()Lscala/collection/immutable/Set;
        20: invokestatic  #123                // Method scala/runtime/Statics.anyHash:(Ljava/lang/Object;)I
        23: invokestatic  #119                // Method scala/runtime/Statics.mix:(II)I
        26: istore_1
        27: iload_1
        28: aload_0
        29: invokevirtual #64                 // Method fileName:()Ljava/lang/String;
        32: invokestatic  #123                // Method scala/runtime/Statics.anyHash:(Ljava/lang/Object;)I
        35: invokestatic  #119                // Method scala/runtime/Statics.mix:(II)I
        38: istore_1
        39: iload_1
        40: aload_0
        41: invokevirtual #67                 // Method numOldFilesToKeep:()I
        44: invokestatic  #119                // Method scala/runtime/Statics.mix:(II)I
        47: istore_1
        48: iload_1
        49: iconst_3
        50: invokestatic  #126                // Method scala/runtime/Statics.finalizeHash:(II)I
        53: ireturn
      LineNumberTable:
        line 33: 0
      LocalVariableTable:
        Start  Length  Slot  Name   Signature
            0      54     0  this   Lorg/scalatest/tools/DashboardReporterConfiguration;

  public java.lang.String toString();
    descriptor: ()Ljava/lang/String;
    flags: (0x0001) ACC_PUBLIC
    Code:
      stack=2, locals=1, args_size=1
         0: getstatic     #95                 // Field scala/runtime/ScalaRunTime$.MODULE$:Lscala/runtime/ScalaRunTime$;
         3: aload_0
         4: invokevirtual #131                // Method scala/runtime/ScalaRunTime$._toString:(Lscala/Product;)Ljava/lang/String;
         7: areturn
      LineNumberTable:
        line 33: 0
      LocalVariableTable:
        Start  Length  Slot  Name   Signature
            0       8     0  this   Lorg/scalatest/tools/DashboardReporterConfiguration;

  public boolean equals(java.lang.Object);
    descriptor: (Ljava/lang/Object;)Z
    flags: (0x0001) ACC_PUBLIC
    Code:
      stack=2, locals=7, args_size=2
         0: aload_0
         1: aload_1
         2: if_acmpeq     130
         5: aload_1
         6: astore_3
         7: aload_3
         8: instanceof    #2                  // class org/scalatest/tools/DashboardReporterConfiguration
        11: ifeq          19
        14: iconst_1
        15: istore_2
        16: goto          27
        19: goto          22
        22: iconst_0
        23: istore_2
        24: goto          27
        27: iload_2
        28: ifeq          134
        31: aload_1
        32: checkcast     #2                  // class org/scalatest/tools/DashboardReporterConfiguration
        35: astore        4
        37: aload_0
        38: invokevirtual #67                 // Method numOldFilesToKeep:()I
        41: aload         4
        43: invokevirtual #67                 // Method numOldFilesToKeep:()I
        46: if_icmpne     126
        49: aload_0
        50: invokevirtual #61                 // Method configSet:()Lscala/collection/immutable/Set;
        53: aload         4
        55: invokevirtual #61                 // Method configSet:()Lscala/collection/immutable/Set;
        58: astore        5
        60: dup
        61: ifnonnull     73
        64: pop
        65: aload         5
        67: ifnull        81
        70: goto          126
        73: aload         5
        75: invokevirtual #134                // Method java/lang/Object.equals:(Ljava/lang/Object;)Z
        78: ifeq          126
        81: aload_0
        82: invokevirtual #64                 // Method fileName:()Ljava/lang/String;
        85: aload         4
        87: invokevirtual #64                 // Method fileName:()Ljava/lang/String;
        90: astore        6
        92: dup
        93: ifnonnull     105
        96: pop
        97: aload         6
        99: ifnull        113
       102: goto          126
       105: aload         6
       107: invokevirtual #134                // Method java/lang/Object.equals:(Ljava/lang/Object;)Z
       110: ifeq          126
       113: aload         4
       115: aload_0
       116: invokevirtual #136                // Method canEqual:(Ljava/lang/Object;)Z
       119: ifeq          126
       122: iconst_1
       123: goto          127
       126: iconst_0
       127: ifeq          134
       130: iconst_1
       131: goto          135
       134: iconst_0
       135: ireturn
      StackMapTable: number_of_entries = 12
        frame_type = 253 /* append */
          offset_delta = 19
          locals = [ top, class java/lang/Object ]
        frame_type = 2 /* same */
        frame_type = 255 /* full_frame */
          offset_delta = 4
          locals = [ class org/scalatest/tools/DashboardReporterConfiguration, class java/lang/Object, int, class java/lang/Object ]
          stack = []
        frame_type = 255 /* full_frame */
          offset_delta = 45
          locals = [ class org/scalatest/tools/DashboardReporterConfiguration, class java/lang/Object, int, class java/lang/Object, class org/scalatest/tools/DashboardReporterConfiguration, class scala/collection/immutable/Set ]
          stack = [ class scala/collection/immutable/Set ]
        frame_type = 7 /* same */
        frame_type = 255 /* full_frame */
          offset_delta = 23
          locals = [ class org/scalatest/tools/DashboardReporterConfiguration, class java/lang/Object, int, class java/lang/Object, class org/scalatest/tools/DashboardReporterConfiguration, class scala/collection/immutable/Set, class java/lang/String ]
          stack = [ class java/lang/String ]
        frame_type = 7 /* same */
        frame_type = 249 /* chop */
          offset_delta = 12
        frame_type = 64 /* same_locals_1_stack_item */
          stack = [ int ]
        frame_type = 248 /* chop */
          offset_delta = 2
        frame_type = 253 /* append */
          offset_delta = 3
          locals = [ int, class java/lang/Object ]
        frame_type = 255 /* full_frame */
          offset_delta = 0
          locals = [ class org/scalatest/tools/DashboardReporterConfiguration, class java/lang/Object ]
          stack = [ int ]
      LineNumberTable:
        line 33: 0
      LocalVariableTable:
        Start  Length  Slot  Name   Signature
            0     136     0  this   Lorg/scalatest/tools/DashboardReporterConfiguration;
            0     136     1   x$1   Ljava/lang/Object;
    MethodParameters:
      Name                           Flags
      x$1                            final

  public org.scalatest.tools.DashboardReporterConfiguration(scala.collection.immutable.Set<org.scalatest.tools.ReporterConfigParam>, java.lang.String, int);
    descriptor: (Lscala/collection/immutable/Set;Ljava/lang/String;I)V
    flags: (0x0001) ACC_PUBLIC
    Code:
      stack=2, locals=4, args_size=4
         0: aload_0
         1: aload_1
         2: putfield      #46                 // Field configSet:Lscala/collection/immutable/Set;
         5: aload_0
         6: aload_2
         7: putfield      #50                 // Field fileName:Ljava/lang/String;
        10: aload_0
        11: iload_3
        12: putfield      #53                 // Field numOldFilesToKeep:I
        15: aload_0
        16: invokespecial #142                // Method org/scalatest/tools/ReporterConfiguration."<init>":()V
        19: return
      LineNumberTable:
        line 33: 0
      LocalVariableTable:
        Start  Length  Slot  Name   Signature
            0      20     0  this   Lorg/scalatest/tools/DashboardReporterConfiguration;
            0      20     1 configSet   Lscala/collection/immutable/Set;
            0      20     2 fileName   Ljava/lang/String;
            0      20     3 numOldFilesToKeep   I
    Signature: #139                         // (Lscala/collection/immutable/Set<Lorg/scalatest/tools/ReporterConfigParam;>;Ljava/lang/String;I)V
    MethodParameters:
      Name                           Flags
      configSet                      final
      fileName                       final
      numOldFilesToKeep              final
}
SourceFile: "ReporterConfiguration.scala"
RuntimeVisibleAnnotations:
  0: #6(#7=s#8)
    scala.reflect.ScalaSignature(
      bytes="\u0006\u0005\u0005ud!\u0002\u000f\u001e\u0001v\u0019\u0003\u0002C\u001e\u0001\u0005+\u0007I\u0011\u0001\u001f\t\u0011!\u0003!\u0011#Q\u0001\nuB\u0001\"\u0013\u0001\u0003\u0016\u0004%\tA\u0013\u0005\t\u001d\u0002\u0011\t\u0012)A\u0005\u0017\"Aq\n\u0001BK\u0002\u0013\u0005\u0001\u000b\u0003\u0005U\u0001\tE\t\u0015!\u0003R\u0011\u0015)\u0006\u0001\"\u0001W\u0011\u001dY\u0006!!A\u0005\u0002qCq\u0001\u0019\u0001\u0012\u0002\u0013\u0005\u0011\rC\u0004m\u0001E\u0005I\u0011A7\t\u000f=\u0004\u0011\u0013!C\u0001a\"9!\u000fAA\u0001\n\u0003\u001a\bbB>\u0001\u0003\u0003%\t\u0001\u0015\u0005\by\u0002\t\t\u0011\"\u0001~\u0011%\t9\u0001AA\u0001\n\u0003\nI\u0001C\u0005\u0002\u0018\u0001\t\t\u0011\"\u0001\u0002\u001a!I\u00111\u0005\u0001\u0002\u0002\u0013\u0005\u0013Q\u0005\u0005\n\u0003S\u0001\u0011\u0011!C!\u0003WA\u0011\"!\f\u0001\u0003\u0003%\t%a\f\t\u0013\u0005E\u0002!!A\u0005B\u0005MrACA\u001c;\u0005\u0005\t\u0012A\u000f\u0002:\u0019IA$HA\u0001\u0012\u0003i\u00121\b\u0005\u0007+Z!\t!a\u0015\t\u0013\u00055b#!A\u0005F\u0005=\u0002\"CA+-\u0005\u0005I\u0011QA,\u0011%\tyFFA\u0001\n\u0003\u000b\t\u0007C\u0005\u0002tY\t\t\u0011\"\u0003\u0002v\tqB)Y:iE>\f\'\u000f\u001a*fa>\u0014H/\u001a:D_:4\u0017nZ;sCRLwN\u001c\u0006\u0003=}\tQ\u0001^8pYNT!\u0001I\u0011\u0002\u0013M\u001c\u0017\r\\1uKN$(\"\u0001\u0012\u0002\u0007=\u0014xm\u0005\u0003\u0001I!r\u0003CA\u0013\'\u001b\u0005i\u0012BA\u0014\u001e\u0005U\u0011V\r]8si\u0016\u00148i\u001c8gS\u001e,(/\u0019;j_:\u0004\"!\u000b\u0017\u000e\u0003)R\u0011aK\u0001\u0006g\u000e\fG.Y\u0005\u0003[)\u0012q\u0001\u0015:pIV\u001cG\u000f\u0005\u00020q9\u0011\u0001G\u000e\b\u0003cUj\u0011A\r\u0006\u0003gQ\na\u0001\u0010:p_Rt4\u0001A\u0005\u0002W%\u0011qGK\u0001\ba\u0006\u001c7.Y4f\u0013\tI$H\u0001\u0007TKJL\u0017\r\\5{C\ndWM\u0003\u00028U\u0005I1m\u001c8gS\u001e\u001cV\r^\u000b\u0002{A\u0019aHQ#\u000f\u0005}\u0002\u0005CA\u0019+\u0013\t\t%&\u0001\u0004Qe\u0016$WMZ\u0005\u0003\u0007\u0012\u00131aU3u\u0015\t\t%\u0006\u0005\u0002&\r&\u0011q)\b\u0002\u0014%\u0016\u0004xN\u001d;fe\u000e{gNZ5h!\u0006\u0014\u0018-\\\u0001\u000bG>tg-[4TKR\u0004\u0013\u0001\u00034jY\u0016t\u0015-\\3\u0016\u0003-\u0003\"A\u0010\'\n\u00055#%AB*ue&tw-A\u0005gS2,g*Y7fA\u0005\tb.^7PY\u00124\u0015\u000e\\3t)>\\U-\u001a9\u0016\u0003E\u0003\"!\u000b*\n\u0005MS#aA%oi\u0006\u0011b.^7PY\u00124\u0015\u000e\\3t)>\\U-\u001a9!\u0003\u0019a\u0014N\\5u}Q!q\u000bW-[!\t)\u0003\u0001C\u0003<\u000f\u0001\u0007Q\bC\u0003J\u000f\u0001\u00071\nC\u0003P\u000f\u0001\u0007\u0011+\u0001\u0003d_BLH\u0003B,^=~Cqa\u000f\u0005\u0011\u0002\u0003\u0007Q\bC\u0004J\u0011A\u0005\t\u0019A&\t\u000f=C\u0001\u0013!a\u0001#\u0006q1m\u001c9zI\u0011,g-Y;mi\u0012\nT#\u00012+\u0005u\u001a7&\u00013\u0011\u0005\u0015TW\"\u00014\u000b\u0005\u001dD\u0017!C;oG\",7m[3e\u0015\tI\'&\u0001\u0006b]:|G/\u0019;j_:L!a\u001b4\u0003#Ut7\r[3dW\u0016$g+\u0019:jC:\u001cW-\u0001\bd_BLH\u0005Z3gCVdG\u000f\n\u001a\u0016\u00039T#aS2\u0002\u001d\r|\u0007/\u001f\u0013eK\u001a\fW\u000f\u001c;%gU\t\u0011O\u000b\u0002RG\u0006i\u0001O]8ek\u000e$\bK]3gSb,\u0012\u0001\u001e\t\u0003kjl\u0011A\u001e\u0006\u0003ob\fA\u0001\\1oO*\t\u00110\u0001\u0003kCZ\f\u0017BA\'w\u00031\u0001(o\u001c3vGR\f%/\u001b;z\u00039\u0001(o\u001c3vGR,E.Z7f]R$2A`A\u0002!\tIs0C\u0002\u0002\u0002)\u00121!\u00118z\u0011!\t)ADA\u0001\u0002\u0004\t\u0016a\u0001=%c\u0005y\u0001O]8ek\u000e$\u0018\n^3sCR|\'/\u0006\u0002\u0002\fA)\u0011QBA\n}6\u0011\u0011q\u0002\u0006\u0004\u0003#Q\u0013AC2pY2,7\r^5p]&!\u0011QCA\b\u0005!IE/\u001a:bi>\u0014\u0018\u0001C2b]\u0016\u000bX/\u00197\u0015\t\u0005m\u0011\u0011\u0005\t\u0004S\u0005u\u0011bAA\u0010U\t9!i\\8mK\u0006t\u0007\u0002CA\u0003!\u0005\u0005\t\u0019\u0001@\u0002%A\u0014x\u000eZ;di\u0016cW-\\3oi:\u000bW.\u001a\u000b\u0004i\u0006\u001d\u0002\u0002CA\u0003#\u0005\u0005\t\u0019A)\u0002\u0011!\f7\u000f[\"pI\u0016$\u0012!U\u0001\ti>\u001cFO]5oOR\tA/\u0001\u0004fcV\fGn\u001d\u000b\u0005\u00037\t)\u0004\u0003\u0005\u0002\u0006Q\t\t\u00111\u0001\u007f\u0003y!\u0015m\u001d5c_\u0006\u0014HMU3q_J$XM]\"p]\u001aLw-\u001e:bi&|g\u000e\u0005\u0002&-M)a#!\u0010\u0002JAA\u0011qHA#{-\u000bv+\u0004\u0002\u0002B)\u0019\u00111\t\u0016\u0002\u000fI,h\u000e^5nK&!\u0011qIA!\u0005E\t%m\u001d;sC\u000e$h)\u001e8di&|gn\r\t\u0005\u0003\u0017\n\t&\u0004\u0002\u0002N)\u0019\u0011q\n=\u0002\u0005%|\u0017bA\u001d\u0002NQ\u0011\u0011\u0011H\u0001\u0006CB\u0004H.\u001f\u000b\b/\u0006e\u00131LA/\u0011\u0015Y\u0014\u00041\u0001>\u0011\u0015I\u0015\u00041\u0001L\u0011\u0015y\u0015\u00041\u0001R\u0003\u001d)h.\u00199qYf$B!a\u0019\u0002pA)\u0011&!\u001a\u0002j%\u0019\u0011q\r\u0016\u0003\r=\u0003H/[8o!\u0019I\u00131N\u001fL#&\u0019\u0011Q\u000e\u0016\u0003\rQ+\b\u000f\\34\u0011!\t\tHGA\u0001\u0002\u00049\u0016a\u0001=%a\u0005aqO]5uKJ+\u0007\u000f\\1dKR\u0011\u0011q\u000f\t\u0004k\u0006e\u0014bAA>m\n1qJ\u00196fGR\u0004"
    )
  ScalaInlineInfo: length = 0x59 (unknown attribute)
   01 00 00 11 00 37 00 38 00 00 64 00 65 00 00 09
   00 2B 00 00 36 00 1E 00 00 3B 00 2B 00 00 3E 00
   30 00 00 41 00 33 00 00 84 00 65 00 00 0C 00 30
   00 00 6E 00 33 00 00 0E 00 33 00 00 47 00 33 00
   00 48 00 49 00 00 67 00 68 00 00 58 00 59 00 00
   44 00 30 00 00 7F 00 30 00
  ScalaSig: length = 0x3 (unknown attribute)
   05 02 00
