Classfile /Users/mw/Projects/slang-braindump/.jar/jar8/assemble/slang-braindump/assemble/content/org/scalatest/tools/Fragment$.class
  Last modified May 29, 2022; size 4156 bytes
  SHA-256 checksum 65dffc689b525fd544884e6f21079a365c0004b9ac6e1ff48db34801cc98c412
  Compiled from "Fragment.scala"
public final class org.scalatest.tools.Fragment$ implements java.io.Serializable
  minor version: 0
  major version: 52
  flags: (0x0031) ACC_PUBLIC, ACC_FINAL, ACC_SUPER
  this_class: #2                          // org/scalatest/tools/Fragment$
  super_class: #4                         // java/lang/Object
  interfaces: 1, fields: 1, methods: 12, attributes: 5
Constant pool:
    #1 = Utf8               org/scalatest/tools/Fragment$
    #2 = Class              #1            // org/scalatest/tools/Fragment$
    #3 = Utf8               java/lang/Object
    #4 = Class              #3            // java/lang/Object
    #5 = Utf8               java/io/Serializable
    #6 = Class              #5            // java/io/Serializable
    #7 = Utf8               Fragment.scala
    #8 = Utf8               java/lang/invoke/MethodHandles$Lookup
    #9 = Class              #8            // java/lang/invoke/MethodHandles$Lookup
   #10 = Utf8               java/lang/invoke/MethodHandles
   #11 = Class              #10           // java/lang/invoke/MethodHandles
   #12 = Utf8               Lookup
   #13 = Utf8               MODULE$
   #14 = Utf8               Lorg/scalatest/tools/Fragment$;
   #15 = Utf8               <clinit>
   #16 = Utf8               ()V
   #17 = Utf8               <init>
   #18 = NameAndType        #17:#16       // "<init>":()V
   #19 = Methodref          #2.#18        // org/scalatest/tools/Fragment$."<init>":()V
   #20 = NameAndType        #13:#14       // MODULE$:Lorg/scalatest/tools/Fragment$;
   #21 = Fieldref           #2.#20        // org/scalatest/tools/Fragment$.MODULE$:Lorg/scalatest/tools/Fragment$;
   #22 = Utf8               countTrailingEOLs
   #23 = Utf8               (Ljava/lang/String;)I
   #24 = Utf8               s
   #25 = Utf8               java/lang/String
   #26 = Class              #25           // java/lang/String
   #27 = Utf8               length
   #28 = Utf8               ()I
   #29 = NameAndType        #27:#28       // length:()I
   #30 = Methodref          #26.#29       // java/lang/String.length:()I
   #31 = Utf8               scala/Predef$
   #32 = Class              #31           // scala/Predef$
   #33 = Utf8               Lscala/Predef$;
   #34 = NameAndType        #13:#33       // MODULE$:Lscala/Predef$;
   #35 = Fieldref           #32.#34       // scala/Predef$.MODULE$:Lscala/Predef$;
   #36 = Utf8               augmentString
   #37 = Utf8               (Ljava/lang/String;)Ljava/lang/String;
   #38 = NameAndType        #36:#37       // augmentString:(Ljava/lang/String;)Ljava/lang/String;
   #39 = Methodref          #32.#38       // scala/Predef$.augmentString:(Ljava/lang/String;)Ljava/lang/String;
   #40 = Utf8               (Ljava/lang/Object;)Ljava/lang/Object;
   #41 = MethodType         #40           //  (Ljava/lang/Object;)Ljava/lang/Object;
   #42 = Utf8               $anonfun$countTrailingEOLs$1$adapted
   #43 = NameAndType        #42:#40       // $anonfun$countTrailingEOLs$1$adapted:(Ljava/lang/Object;)Ljava/lang/Object;
   #44 = Methodref          #2.#43        // org/scalatest/tools/Fragment$.$anonfun$countTrailingEOLs$1$adapted:(Ljava/lang/Object;)Ljava/lang/Object;
   #45 = MethodHandle       6:#44         // REF_invokeStatic org/scalatest/tools/Fragment$.$anonfun$countTrailingEOLs$1$adapted:(Ljava/lang/Object;)Ljava/lang/Object;
   #46 = Integer            1
   #47 = Utf8               java/lang/invoke/LambdaMetafactory
   #48 = Class              #47           // java/lang/invoke/LambdaMetafactory
   #49 = Utf8               altMetafactory
   #50 = Utf8               (Ljava/lang/invoke/MethodHandles$Lookup;Ljava/lang/String;Ljava/lang/invoke/MethodType;[Ljava/lang/Object;)Ljava/lang/invoke/CallSite;
   #51 = NameAndType        #49:#50       // altMetafactory:(Ljava/lang/invoke/MethodHandles$Lookup;Ljava/lang/String;Ljava/lang/invoke/MethodType;[Ljava/lang/Object;)Ljava/lang/invoke/CallSite;
   #52 = Methodref          #48.#51       // java/lang/invoke/LambdaMetafactory.altMetafactory:(Ljava/lang/invoke/MethodHandles$Lookup;Ljava/lang/String;Ljava/lang/invoke/MethodType;[Ljava/lang/Object;)Ljava/lang/invoke/CallSite;
   #53 = MethodHandle       6:#52         // REF_invokeStatic java/lang/invoke/LambdaMetafactory.altMetafactory:(Ljava/lang/invoke/MethodHandles$Lookup;Ljava/lang/String;Ljava/lang/invoke/MethodType;[Ljava/lang/Object;)Ljava/lang/invoke/CallSite;
   #54 = Utf8               apply
   #55 = Utf8               ()Lscala/Function1;
   #56 = NameAndType        #54:#55       // apply:()Lscala/Function1;
   #57 = InvokeDynamic      #0:#56        // #0:apply:()Lscala/Function1;
   #58 = Utf8               scala/collection/StringOps$
   #59 = Class              #58           // scala/collection/StringOps$
   #60 = Utf8               Lscala/collection/StringOps$;
   #61 = NameAndType        #13:#60       // MODULE$:Lscala/collection/StringOps$;
   #62 = Fieldref           #59.#61       // scala/collection/StringOps$.MODULE$:Lscala/collection/StringOps$;
   #63 = Utf8               lastIndexWhere$default$2$extension
   #64 = NameAndType        #63:#23       // lastIndexWhere$default$2$extension:(Ljava/lang/String;)I
   #65 = Methodref          #59.#64       // scala/collection/StringOps$.lastIndexWhere$default$2$extension:(Ljava/lang/String;)I
   #66 = Utf8               lastIndexWhere$extension
   #67 = Utf8               (Ljava/lang/String;Lscala/Function1;I)I
   #68 = NameAndType        #66:#67       // lastIndexWhere$extension:(Ljava/lang/String;Lscala/Function1;I)I
   #69 = Methodref          #59.#68       // scala/collection/StringOps$.lastIndexWhere$extension:(Ljava/lang/String;Lscala/Function1;I)I
   #70 = Utf8               qual$1
   #71 = Utf8               Ljava/lang/String;
   #72 = Utf8               x$1
   #73 = Utf8               Lscala/Function1;
   #74 = Utf8               x$2
   #75 = Utf8               I
   #76 = Utf8               this
   #77 = Utf8               countLeadingEOLs
   #78 = Utf8               $anonfun$countLeadingEOLs$1$adapted
   #79 = NameAndType        #78:#40       // $anonfun$countLeadingEOLs$1$adapted:(Ljava/lang/Object;)Ljava/lang/Object;
   #80 = Methodref          #2.#79        // org/scalatest/tools/Fragment$.$anonfun$countLeadingEOLs$1$adapted:(Ljava/lang/Object;)Ljava/lang/Object;
   #81 = MethodHandle       6:#80         // REF_invokeStatic org/scalatest/tools/Fragment$.$anonfun$countLeadingEOLs$1$adapted:(Ljava/lang/Object;)Ljava/lang/Object;
   #82 = InvokeDynamic      #1:#56        // #1:apply:()Lscala/Function1;
   #83 = Utf8               indexWhere$default$2$extension
   #84 = NameAndType        #83:#23       // indexWhere$default$2$extension:(Ljava/lang/String;)I
   #85 = Methodref          #59.#84       // scala/collection/StringOps$.indexWhere$default$2$extension:(Ljava/lang/String;)I
   #86 = Utf8               indexWhere$extension
   #87 = NameAndType        #86:#67       // indexWhere$extension:(Ljava/lang/String;Lscala/Function1;I)I
   #88 = Methodref          #59.#87       // scala/collection/StringOps$.indexWhere$extension:(Ljava/lang/String;Lscala/Function1;I)I
   #89 = Utf8               idx
   #90 = Utf8               scala/Function1
   #91 = Class              #90           // scala/Function1
   #92 = Utf8               (Ljava/lang/String;Lorg/scalatest/tools/AnsiColor;)Lorg/scalatest/tools/Fragment;
   #93 = Utf8               text
   #94 = Utf8               ansiColor
   #95 = Utf8               org/scalatest/tools/Fragment
   #96 = Class              #95           // org/scalatest/tools/Fragment
   #97 = Utf8               (Ljava/lang/String;Lorg/scalatest/tools/AnsiColor;)V
   #98 = NameAndType        #17:#97       // "<init>":(Ljava/lang/String;Lorg/scalatest/tools/AnsiColor;)V
   #99 = Methodref          #96.#98       // org/scalatest/tools/Fragment."<init>":(Ljava/lang/String;Lorg/scalatest/tools/AnsiColor;)V
  #100 = Utf8               Lorg/scalatest/tools/AnsiColor;
  #101 = Utf8               unapply
  #102 = Utf8               (Lorg/scalatest/tools/Fragment;)Lscala/Option;
  #103 = Utf8               (Lorg/scalatest/tools/Fragment;)Lscala/Option<Lscala/Tuple2<Ljava/lang/String;Lorg/scalatest/tools/AnsiColor;>;>;
  #104 = Utf8               x$0
  #105 = Utf8               scala/None$
  #106 = Class              #105          // scala/None$
  #107 = Utf8               Lscala/None$;
  #108 = NameAndType        #13:#107      // MODULE$:Lscala/None$;
  #109 = Fieldref           #106.#108     // scala/None$.MODULE$:Lscala/None$;
  #110 = Utf8               scala/Some
  #111 = Class              #110          // scala/Some
  #112 = Utf8               scala/Tuple2
  #113 = Class              #112          // scala/Tuple2
  #114 = Utf8               ()Ljava/lang/String;
  #115 = NameAndType        #93:#114      // text:()Ljava/lang/String;
  #116 = Methodref          #96.#115      // org/scalatest/tools/Fragment.text:()Ljava/lang/String;
  #117 = Utf8               ()Lorg/scalatest/tools/AnsiColor;
  #118 = NameAndType        #94:#117      // ansiColor:()Lorg/scalatest/tools/AnsiColor;
  #119 = Methodref          #96.#118      // org/scalatest/tools/Fragment.ansiColor:()Lorg/scalatest/tools/AnsiColor;
  #120 = Utf8               (Ljava/lang/Object;Ljava/lang/Object;)V
  #121 = NameAndType        #17:#120      // "<init>":(Ljava/lang/Object;Ljava/lang/Object;)V
  #122 = Methodref          #113.#121     // scala/Tuple2."<init>":(Ljava/lang/Object;Ljava/lang/Object;)V
  #123 = Utf8               (Ljava/lang/Object;)V
  #124 = NameAndType        #17:#123      // "<init>":(Ljava/lang/Object;)V
  #125 = Methodref          #111.#124     // scala/Some."<init>":(Ljava/lang/Object;)V
  #126 = Utf8               Lorg/scalatest/tools/Fragment;
  #127 = Utf8               scala/Option
  #128 = Class              #127          // scala/Option
  #129 = Utf8               writeReplace
  #130 = Utf8               ()Ljava/lang/Object;
  #131 = Utf8               scala/runtime/ModuleSerializationProxy
  #132 = Class              #131          // scala/runtime/ModuleSerializationProxy
  #133 = Utf8               (Ljava/lang/Class;)V
  #134 = NameAndType        #17:#133      // "<init>":(Ljava/lang/Class;)V
  #135 = Methodref          #132.#134     // scala/runtime/ModuleSerializationProxy."<init>":(Ljava/lang/Class;)V
  #136 = Utf8               $anonfun$countTrailingEOLs$1
  #137 = Utf8               (C)Z
  #138 = Utf8               x$3
  #139 = Utf8               C
  #140 = Utf8               $anonfun$countLeadingEOLs$1
  #141 = Utf8               x$4
  #142 = Methodref          #4.#18        // java/lang/Object."<init>":()V
  #143 = Utf8               scala/runtime/BoxesRunTime
  #144 = Class              #143          // scala/runtime/BoxesRunTime
  #145 = Utf8               unboxToChar
  #146 = Utf8               (Ljava/lang/Object;)C
  #147 = NameAndType        #145:#146     // unboxToChar:(Ljava/lang/Object;)C
  #148 = Methodref          #144.#147     // scala/runtime/BoxesRunTime.unboxToChar:(Ljava/lang/Object;)C
  #149 = NameAndType        #136:#137     // $anonfun$countTrailingEOLs$1:(C)Z
  #150 = Methodref          #2.#149       // org/scalatest/tools/Fragment$.$anonfun$countTrailingEOLs$1:(C)Z
  #151 = Utf8               boxToBoolean
  #152 = Utf8               (Z)Ljava/lang/Boolean;
  #153 = NameAndType        #151:#152     // boxToBoolean:(Z)Ljava/lang/Boolean;
  #154 = Methodref          #144.#153     // scala/runtime/BoxesRunTime.boxToBoolean:(Z)Ljava/lang/Boolean;
  #155 = Utf8               Ljava/lang/Object;
  #156 = NameAndType        #140:#137     // $anonfun$countLeadingEOLs$1:(C)Z
  #157 = Methodref          #2.#156       // org/scalatest/tools/Fragment$.$anonfun$countLeadingEOLs$1:(C)Z
  #158 = Utf8               $deserializeLambda$
  #159 = Utf8               (Ljava/lang/invoke/SerializedLambda;)Ljava/lang/Object;
  #160 = Utf8               scala/runtime/LambdaDeserialize
  #161 = Class              #160          // scala/runtime/LambdaDeserialize
  #162 = Utf8               bootstrap
  #163 = Utf8               (Ljava/lang/invoke/MethodHandles$Lookup;Ljava/lang/String;Ljava/lang/invoke/MethodType;[Ljava/lang/invoke/MethodHandle;)Ljava/lang/invoke/CallSite;
  #164 = NameAndType        #162:#163     // bootstrap:(Ljava/lang/invoke/MethodHandles$Lookup;Ljava/lang/String;Ljava/lang/invoke/MethodType;[Ljava/lang/invoke/MethodHandle;)Ljava/lang/invoke/CallSite;
  #165 = Methodref          #161.#164     // scala/runtime/LambdaDeserialize.bootstrap:(Ljava/lang/invoke/MethodHandles$Lookup;Ljava/lang/String;Ljava/lang/invoke/MethodType;[Ljava/lang/invoke/MethodHandle;)Ljava/lang/invoke/CallSite;
  #166 = MethodHandle       6:#165        // REF_invokeStatic scala/runtime/LambdaDeserialize.bootstrap:(Ljava/lang/invoke/MethodHandles$Lookup;Ljava/lang/String;Ljava/lang/invoke/MethodType;[Ljava/lang/invoke/MethodHandle;)Ljava/lang/invoke/CallSite;
  #167 = Utf8               lambdaDeserialize
  #168 = NameAndType        #167:#159     // lambdaDeserialize:(Ljava/lang/invoke/SerializedLambda;)Ljava/lang/Object;
  #169 = InvokeDynamic      #2:#168       // #2:lambdaDeserialize:(Ljava/lang/invoke/SerializedLambda;)Ljava/lang/Object;
  #170 = Utf8               Code
  #171 = Utf8               LineNumberTable
  #172 = Utf8               LocalVariableTable
  #173 = Utf8               MethodParameters
  #174 = Utf8               StackMapTable
  #175 = Utf8               Signature
  #176 = Utf8               InnerClasses
  #177 = Utf8               SourceFile
  #178 = Utf8               BootstrapMethods
  #179 = Utf8               ScalaInlineInfo
  #180 = Utf8               Scala
{
  public static final org.scalatest.tools.Fragment$ MODULE$;
    descriptor: Lorg/scalatest/tools/Fragment$;
    flags: (0x0019) ACC_PUBLIC, ACC_STATIC, ACC_FINAL

  public static {};
    descriptor: ()V
    flags: (0x0009) ACC_PUBLIC, ACC_STATIC
    Code:
      stack=2, locals=0, args_size=0
         0: new           #2                  // class org/scalatest/tools/Fragment$
         3: dup
         4: invokespecial #19                 // Method "<init>":()V
         7: putstatic     #21                 // Field MODULE$:Lorg/scalatest/tools/Fragment$;
        10: return
      LineNumberTable:
        line 33: 0

  public int countTrailingEOLs(java.lang.String);
    descriptor: (Ljava/lang/String;)I
    flags: (0x0001) ACC_PUBLIC
    Code:
      stack=5, locals=5, args_size=2
         0: aload_1
         1: invokevirtual #30                 // Method java/lang/String.length:()I
         4: getstatic     #35                 // Field scala/Predef$.MODULE$:Lscala/Predef$;
         7: aload_1
         8: invokevirtual #39                 // Method scala/Predef$.augmentString:(Ljava/lang/String;)Ljava/lang/String;
        11: astore_2
        12: invokedynamic #57,  0             // InvokeDynamic #0:apply:()Lscala/Function1;
        17: astore_3
        18: getstatic     #62                 // Field scala/collection/StringOps$.MODULE$:Lscala/collection/StringOps$;
        21: aload_2
        22: invokevirtual #65                 // Method scala/collection/StringOps$.lastIndexWhere$default$2$extension:(Ljava/lang/String;)I
        25: istore        4
        27: getstatic     #62                 // Field scala/collection/StringOps$.MODULE$:Lscala/collection/StringOps$;
        30: aload_2
        31: aload_3
        32: iload         4
        34: invokevirtual #69                 // Method scala/collection/StringOps$.lastIndexWhere$extension:(Ljava/lang/String;Lscala/Function1;I)I
        37: isub
        38: iconst_1
        39: isub
        40: ireturn
      LineNumberTable:
        line 35: 0
      LocalVariableTable:
        Start  Length  Slot  Name   Signature
           12      25     2 qual$1   Ljava/lang/String;
           18      19     3   x$1   Lscala/Function1;
           27      10     4   x$2   I
            0      41     0  this   Lorg/scalatest/tools/Fragment$;
            0      41     1     s   Ljava/lang/String;
    MethodParameters:
      Name                           Flags
      s                              final

  public int countLeadingEOLs(java.lang.String);
    descriptor: (Ljava/lang/String;)I
    flags: (0x0001) ACC_PUBLIC
    Code:
      stack=4, locals=6, args_size=2
         0: getstatic     #35                 // Field scala/Predef$.MODULE$:Lscala/Predef$;
         3: aload_1
         4: invokevirtual #39                 // Method scala/Predef$.augmentString:(Ljava/lang/String;)Ljava/lang/String;
         7: astore_3
         8: invokedynamic #82,  0             // InvokeDynamic #1:apply:()Lscala/Function1;
        13: astore        4
        15: getstatic     #62                 // Field scala/collection/StringOps$.MODULE$:Lscala/collection/StringOps$;
        18: aload_3
        19: invokevirtual #85                 // Method scala/collection/StringOps$.indexWhere$default$2$extension:(Ljava/lang/String;)I
        22: istore        5
        24: getstatic     #62                 // Field scala/collection/StringOps$.MODULE$:Lscala/collection/StringOps$;
        27: aload_3
        28: aload         4
        30: iload         5
        32: invokevirtual #88                 // Method scala/collection/StringOps$.indexWhere$extension:(Ljava/lang/String;Lscala/Function1;I)I
        35: istore_2
        36: iload_2
        37: iconst_m1
        38: if_icmpeq     45
        41: iload_2
        42: goto          46
        45: iconst_0
        46: ireturn
      StackMapTable: number_of_entries = 2
        frame_type = 255 /* full_frame */
          offset_delta = 45
          locals = [ class org/scalatest/tools/Fragment$, class java/lang/String, int, class java/lang/String, class scala/Function1, int ]
          stack = []
        frame_type = 64 /* same_locals_1_stack_item */
          stack = [ int ]
      LineNumberTable:
        line 38: 0
        line 39: 36
      LocalVariableTable:
        Start  Length  Slot  Name   Signature
            8      27     3 qual$1   Ljava/lang/String;
           15      20     4   x$1   Lscala/Function1;
           24      11     5   x$2   I
           36      10     2   idx   I
            0      47     0  this   Lorg/scalatest/tools/Fragment$;
            0      47     1     s   Ljava/lang/String;
    MethodParameters:
      Name                           Flags
      s                              final

  public org.scalatest.tools.Fragment apply(java.lang.String, org.scalatest.tools.AnsiColor);
    descriptor: (Ljava/lang/String;Lorg/scalatest/tools/AnsiColor;)Lorg/scalatest/tools/Fragment;
    flags: (0x0001) ACC_PUBLIC
    Code:
      stack=4, locals=3, args_size=3
         0: new           #96                 // class org/scalatest/tools/Fragment
         3: dup
         4: aload_1
         5: aload_2
         6: invokespecial #99                 // Method org/scalatest/tools/Fragment."<init>":(Ljava/lang/String;Lorg/scalatest/tools/AnsiColor;)V
         9: areturn
      LineNumberTable:
        line 22: 0
      LocalVariableTable:
        Start  Length  Slot  Name   Signature
            0      10     0  this   Lorg/scalatest/tools/Fragment$;
            0      10     1  text   Ljava/lang/String;
            0      10     2 ansiColor   Lorg/scalatest/tools/AnsiColor;
    MethodParameters:
      Name                           Flags
      text                           final
      ansiColor                      final

  public scala.Option<scala.Tuple2<java.lang.String, org.scalatest.tools.AnsiColor>> unapply(org.scalatest.tools.Fragment);
    descriptor: (Lorg/scalatest/tools/Fragment;)Lscala/Option;
    flags: (0x0001) ACC_PUBLIC
    Code:
      stack=6, locals=2, args_size=2
         0: aload_1
         1: ifnonnull     10
         4: getstatic     #109                // Field scala/None$.MODULE$:Lscala/None$;
         7: goto          32
        10: new           #111                // class scala/Some
        13: dup
        14: new           #113                // class scala/Tuple2
        17: dup
        18: aload_1
        19: invokevirtual #116                // Method org/scalatest/tools/Fragment.text:()Ljava/lang/String;
        22: aload_1
        23: invokevirtual #119                // Method org/scalatest/tools/Fragment.ansiColor:()Lorg/scalatest/tools/AnsiColor;
        26: invokespecial #122                // Method scala/Tuple2."<init>":(Ljava/lang/Object;Ljava/lang/Object;)V
        29: invokespecial #125                // Method scala/Some."<init>":(Ljava/lang/Object;)V
        32: areturn
      StackMapTable: number_of_entries = 2
        frame_type = 10 /* same */
        frame_type = 85 /* same_locals_1_stack_item */
          stack = [ class scala/Option ]
      LineNumberTable:
        line 22: 0
      LocalVariableTable:
        Start  Length  Slot  Name   Signature
            0      33     0  this   Lorg/scalatest/tools/Fragment$;
            0      33     1   x$0   Lorg/scalatest/tools/Fragment;
    Signature: #103                         // (Lorg/scalatest/tools/Fragment;)Lscala/Option<Lscala/Tuple2<Ljava/lang/String;Lorg/scalatest/tools/AnsiColor;>;>;
    MethodParameters:
      Name                           Flags
      x$0                            final

  private java.lang.Object writeReplace();
    descriptor: ()Ljava/lang/Object;
    flags: (0x0002) ACC_PRIVATE
    Code:
      stack=3, locals=1, args_size=1
         0: new           #132                // class scala/runtime/ModuleSerializationProxy
         3: dup
         4: ldc           #2                  // class org/scalatest/tools/Fragment$
         6: invokespecial #135                // Method scala/runtime/ModuleSerializationProxy."<init>":(Ljava/lang/Class;)V
         9: areturn
      LineNumberTable:
        line 33: 0
      LocalVariableTable:
        Start  Length  Slot  Name   Signature
            0      10     0  this   Lorg/scalatest/tools/Fragment$;

  public static final boolean $anonfun$countTrailingEOLs$1(char);
    descriptor: (C)Z
    flags: (0x1019) ACC_PUBLIC, ACC_STATIC, ACC_FINAL, ACC_SYNTHETIC
    Code:
      stack=2, locals=1, args_size=1
         0: iload_0
         1: bipush        10
         3: if_icmpeq     10
         6: iconst_1
         7: goto          11
        10: iconst_0
        11: ireturn
      StackMapTable: number_of_entries = 2
        frame_type = 10 /* same */
        frame_type = 64 /* same_locals_1_stack_item */
          stack = [ int ]
      LineNumberTable:
        line 35: 0
      LocalVariableTable:
        Start  Length  Slot  Name   Signature
            0      12     0   x$3   C
    MethodParameters:
      Name                           Flags
      x$3                            final

  public static final boolean $anonfun$countLeadingEOLs$1(char);
    descriptor: (C)Z
    flags: (0x1019) ACC_PUBLIC, ACC_STATIC, ACC_FINAL, ACC_SYNTHETIC
    Code:
      stack=2, locals=1, args_size=1
         0: iload_0
         1: bipush        10
         3: if_icmpeq     10
         6: iconst_1
         7: goto          11
        10: iconst_0
        11: ireturn
      StackMapTable: number_of_entries = 2
        frame_type = 10 /* same */
        frame_type = 64 /* same_locals_1_stack_item */
          stack = [ int ]
      LineNumberTable:
        line 38: 0
      LocalVariableTable:
        Start  Length  Slot  Name   Signature
            0      12     0   x$4   C
    MethodParameters:
      Name                           Flags
      x$4                            final

  private org.scalatest.tools.Fragment$();
    descriptor: ()V
    flags: (0x0002) ACC_PRIVATE
    Code:
      stack=1, locals=1, args_size=1
         0: aload_0
         1: invokespecial #142                // Method java/lang/Object."<init>":()V
         4: return
      LineNumberTable:
        line 42: 0
        line 33: 4
      LocalVariableTable:
        Start  Length  Slot  Name   Signature
            0       5     0  this   Lorg/scalatest/tools/Fragment$;

  public static final java.lang.Object $anonfun$countTrailingEOLs$1$adapted(java.lang.Object);
    descriptor: (Ljava/lang/Object;)Ljava/lang/Object;
    flags: (0x1019) ACC_PUBLIC, ACC_STATIC, ACC_FINAL, ACC_SYNTHETIC
    Code:
      stack=1, locals=1, args_size=1
         0: aload_0
         1: invokestatic  #148                // Method scala/runtime/BoxesRunTime.unboxToChar:(Ljava/lang/Object;)C
         4: invokestatic  #150                // Method $anonfun$countTrailingEOLs$1:(C)Z
         7: invokestatic  #154                // Method scala/runtime/BoxesRunTime.boxToBoolean:(Z)Ljava/lang/Boolean;
        10: areturn
      LineNumberTable:
        line 35: 0
      LocalVariableTable:
        Start  Length  Slot  Name   Signature
            0      11     0   x$3   Ljava/lang/Object;
    MethodParameters:
      Name                           Flags
      x$3                            final

  public static final java.lang.Object $anonfun$countLeadingEOLs$1$adapted(java.lang.Object);
    descriptor: (Ljava/lang/Object;)Ljava/lang/Object;
    flags: (0x1019) ACC_PUBLIC, ACC_STATIC, ACC_FINAL, ACC_SYNTHETIC
    Code:
      stack=1, locals=1, args_size=1
         0: aload_0
         1: invokestatic  #148                // Method scala/runtime/BoxesRunTime.unboxToChar:(Ljava/lang/Object;)C
         4: invokestatic  #157                // Method $anonfun$countLeadingEOLs$1:(C)Z
         7: invokestatic  #154                // Method scala/runtime/BoxesRunTime.boxToBoolean:(Z)Ljava/lang/Boolean;
        10: areturn
      LineNumberTable:
        line 38: 0
      LocalVariableTable:
        Start  Length  Slot  Name   Signature
            0      11     0   x$4   Ljava/lang/Object;
    MethodParameters:
      Name                           Flags
      x$4                            final

  private static java.lang.Object $deserializeLambda$(java.lang.invoke.SerializedLambda);
    descriptor: (Ljava/lang/invoke/SerializedLambda;)Ljava/lang/Object;
    flags: (0x100a) ACC_PRIVATE, ACC_STATIC, ACC_SYNTHETIC
    Code:
      stack=1, locals=1, args_size=1
         0: aload_0
         1: invokedynamic #169,  0            // InvokeDynamic #2:lambdaDeserialize:(Ljava/lang/invoke/SerializedLambda;)Ljava/lang/Object;
         6: areturn
}
InnerClasses:
  public static final #12= #9 of #11;     // Lookup=class java/lang/invoke/MethodHandles$Lookup of class java/lang/invoke/MethodHandles
SourceFile: "Fragment.scala"
BootstrapMethods:
  0: #53 REF_invokeStatic java/lang/invoke/LambdaMetafactory.altMetafactory:(Ljava/lang/invoke/MethodHandles$Lookup;Ljava/lang/String;Ljava/lang/invoke/MethodType;[Ljava/lang/Object;)Ljava/lang/invoke/CallSite;
    Method arguments:
      #41 (Ljava/lang/Object;)Ljava/lang/Object;
      #45 REF_invokeStatic org/scalatest/tools/Fragment$.$anonfun$countTrailingEOLs$1$adapted:(Ljava/lang/Object;)Ljava/lang/Object;
      #41 (Ljava/lang/Object;)Ljava/lang/Object;
      #46 1
  1: #53 REF_invokeStatic java/lang/invoke/LambdaMetafactory.altMetafactory:(Ljava/lang/invoke/MethodHandles$Lookup;Ljava/lang/String;Ljava/lang/invoke/MethodType;[Ljava/lang/Object;)Ljava/lang/invoke/CallSite;
    Method arguments:
      #41 (Ljava/lang/Object;)Ljava/lang/Object;
      #81 REF_invokeStatic org/scalatest/tools/Fragment$.$anonfun$countLeadingEOLs$1$adapted:(Ljava/lang/Object;)Ljava/lang/Object;
      #41 (Ljava/lang/Object;)Ljava/lang/Object;
      #46 1
  2: #166 REF_invokeStatic scala/runtime/LambdaDeserialize.bootstrap:(Ljava/lang/invoke/MethodHandles$Lookup;Ljava/lang/String;Ljava/lang/invoke/MethodType;[Ljava/lang/invoke/MethodHandle;)Ljava/lang/invoke/CallSite;
    Method arguments:
      #81 REF_invokeStatic org/scalatest/tools/Fragment$.$anonfun$countLeadingEOLs$1$adapted:(Ljava/lang/Object;)Ljava/lang/Object;
      #45 REF_invokeStatic org/scalatest/tools/Fragment$.$anonfun$countTrailingEOLs$1$adapted:(Ljava/lang/Object;)Ljava/lang/Object;
  ScalaInlineInfo: length = 0x36 (unknown attribute)
   01 01 00 0A 00 8C 00 89 01 00 4E 00 28 01 00 88
   00 89 01 00 2A 00 28 01 00 11 00 10 01 00 36 00
   5C 01 00 4D 00 17 01 00 16 00 17 01 00 65 00 66
   01 00 81 00 82 01
  Scala: length = 0x0 (unknown attribute)

