Classfile /Users/mw/Projects/slang-braindump/.jar/jar8/assemble/slang-braindump/assemble/content/org/scalatest/tools/Framework$SbtReporter.class
  Last modified May 29, 2022; size 6906 bytes
  SHA-256 checksum 47b7178795fabb08f1a857028ea50f7df612b5d132195e1623a408bbb4318b5f
  Compiled from "Framework.scala"
public class org.scalatest.tools.Framework$SbtReporter implements org.scalatest.Reporter
  minor version: 0
  major version: 52
  flags: (0x0021) ACC_PUBLIC, ACC_SUPER
  this_class: #2                          // org/scalatest/tools/Framework$SbtReporter
  super_class: #4                         // java/lang/Object
  interfaces: 1, fields: 7, methods: 12, attributes: 5
Constant pool:
    #1 = Utf8               org/scalatest/tools/Framework$SbtReporter
    #2 = Class              #1            // org/scalatest/tools/Framework$SbtReporter
    #3 = Utf8               java/lang/Object
    #4 = Class              #3            // java/lang/Object
    #5 = Utf8               org/scalatest/Reporter
    #6 = Class              #5            // org/scalatest/Reporter
    #7 = Utf8               Framework.scala
    #8 = Utf8               java/lang/invoke/MethodHandles$Lookup
    #9 = Class              #8            // java/lang/invoke/MethodHandles$Lookup
   #10 = Utf8               java/lang/invoke/MethodHandles
   #11 = Class              #10           // java/lang/invoke/MethodHandles
   #12 = Utf8               Lookup
   #13 = Utf8               org/scalatest/tools/Framework
   #14 = Class              #13           // org/scalatest/tools/Framework
   #15 = Utf8               SbtReporter
   #16 = Utf8               org/scalatest/tools/Framework$ScalaTestSbtEvent
   #17 = Class              #16           // org/scalatest/tools/Framework$ScalaTestSbtEvent
   #18 = Utf8               ScalaTestSbtEvent
   #19 = Utf8               org/scalatest/tools/Framework$SummaryCounter
   #20 = Class              #19           // org/scalatest/tools/Framework$SummaryCounter
   #21 = Utf8               SummaryCounter
   #22 = Utf8               suiteId
   #23 = Utf8               Ljava/lang/String;
   #24 = Utf8               fullyQualifiedName
   #25 = Utf8               fingerprint
   #26 = Utf8               Lsbt/testing/Fingerprint;
   #27 = Utf8               eventHandler
   #28 = Utf8               Lsbt/testing/EventHandler;
   #29 = Utf8               report
   #30 = Utf8               Lorg/scalatest/Reporter;
   #31 = Utf8               summaryCounter
   #32 = Utf8               Lorg/scalatest/tools/Framework$SummaryCounter;
   #33 = Utf8               $outer
   #34 = Utf8               Lorg/scalatest/tools/Framework;
   #35 = Utf8               getTestSelector
   #36 = Utf8               (Ljava/lang/String;Ljava/lang/String;)Lsbt/testing/Selector;
   #37 = Utf8               eventSuiteId
   #38 = Utf8               testName
   #39 = NameAndType        #22:#23       // suiteId:Ljava/lang/String;
   #40 = Fieldref           #2.#39        // org/scalatest/tools/Framework$SbtReporter.suiteId:Ljava/lang/String;
   #41 = Utf8               equals
   #42 = Utf8               (Ljava/lang/Object;)Z
   #43 = NameAndType        #41:#42       // equals:(Ljava/lang/Object;)Z
   #44 = Methodref          #4.#43        // java/lang/Object.equals:(Ljava/lang/Object;)Z
   #45 = Utf8               sbt/testing/TestSelector
   #46 = Class              #45           // sbt/testing/TestSelector
   #47 = Utf8               <init>
   #48 = Utf8               (Ljava/lang/String;)V
   #49 = NameAndType        #47:#48       // "<init>":(Ljava/lang/String;)V
   #50 = Methodref          #46.#49       // sbt/testing/TestSelector."<init>":(Ljava/lang/String;)V
   #51 = Utf8               sbt/testing/NestedTestSelector
   #52 = Class              #51           // sbt/testing/NestedTestSelector
   #53 = Utf8               (Ljava/lang/String;Ljava/lang/String;)V
   #54 = NameAndType        #47:#53       // "<init>":(Ljava/lang/String;Ljava/lang/String;)V
   #55 = Methodref          #52.#54       // sbt/testing/NestedTestSelector."<init>":(Ljava/lang/String;Ljava/lang/String;)V
   #56 = Utf8               this
   #57 = Utf8               Lorg/scalatest/tools/Framework$SbtReporter;
   #58 = Utf8               java/lang/String
   #59 = Class              #58           // java/lang/String
   #60 = Utf8               sbt/testing/Selector
   #61 = Class              #60           // sbt/testing/Selector
   #62 = Utf8               getSuiteSelector
   #63 = Utf8               (Ljava/lang/String;)Lsbt/testing/Selector;
   #64 = Utf8               sbt/testing/SuiteSelector
   #65 = Class              #64           // sbt/testing/SuiteSelector
   #66 = Utf8               ()V
   #67 = NameAndType        #47:#66       // "<init>":()V
   #68 = Methodref          #65.#67       // sbt/testing/SuiteSelector."<init>":()V
   #69 = Utf8               sbt/testing/NestedSuiteSelector
   #70 = Class              #69           // sbt/testing/NestedSuiteSelector
   #71 = Methodref          #70.#49       // sbt/testing/NestedSuiteSelector."<init>":(Ljava/lang/String;)V
   #72 = Utf8               getOptionalThrowable
   #73 = Utf8               (Lscala/Option;)Lsbt/testing/OptionalThrowable;
   #74 = Utf8               (Lscala/Option<Ljava/lang/Throwable;>;)Lsbt/testing/OptionalThrowable;
   #75 = Utf8               throwable
   #76 = Utf8               scala/Some
   #77 = Class              #76           // scala/Some
   #78 = Utf8               value
   #79 = Utf8               ()Ljava/lang/Object;
   #80 = NameAndType        #78:#79       // value:()Ljava/lang/Object;
   #81 = Methodref          #77.#80       // scala/Some.value:()Ljava/lang/Object;
   #82 = Utf8               java/lang/Throwable
   #83 = Class              #82           // java/lang/Throwable
   #84 = Utf8               sbt/testing/OptionalThrowable
   #85 = Class              #84           // sbt/testing/OptionalThrowable
   #86 = Utf8               (Ljava/lang/Throwable;)V
   #87 = NameAndType        #47:#86       // "<init>":(Ljava/lang/Throwable;)V
   #88 = Methodref          #85.#87       // sbt/testing/OptionalThrowable."<init>":(Ljava/lang/Throwable;)V
   #89 = Utf8               scala/None$
   #90 = Class              #89           // scala/None$
   #91 = Utf8               MODULE$
   #92 = Utf8               Lscala/None$;
   #93 = NameAndType        #91:#92       // MODULE$:Lscala/None$;
   #94 = Fieldref           #90.#93       // scala/None$.MODULE$:Lscala/None$;
   #95 = Methodref          #85.#67       // sbt/testing/OptionalThrowable."<init>":()V
   #96 = Utf8               scala/MatchError
   #97 = Class              #96           // scala/MatchError
   #98 = Utf8               (Ljava/lang/Object;)V
   #99 = NameAndType        #47:#98       // "<init>":(Ljava/lang/Object;)V
  #100 = Methodref          #97.#99       // scala/MatchError."<init>":(Ljava/lang/Object;)V
  #101 = Utf8               t
  #102 = Utf8               Ljava/lang/Throwable;
  #103 = Utf8               Lscala/Option;
  #104 = Utf8               scala/Option
  #105 = Class              #104          // scala/Option
  #106 = Utf8               apply
  #107 = Utf8               (Lorg/scalatest/events/Event;)V
  #108 = Utf8               event
  #109 = NameAndType        #29:#30       // report:Lorg/scalatest/Reporter;
  #110 = Fieldref           #2.#109       // org/scalatest/tools/Framework$SbtReporter.report:Lorg/scalatest/Reporter;
  #111 = NameAndType        #106:#107     // apply:(Lorg/scalatest/events/Event;)V
  #112 = InterfaceMethodref #6.#111       // org/scalatest/Reporter.apply:(Lorg/scalatest/events/Event;)V
  #113 = Utf8               org/scalatest/events/TestPending
  #114 = Class              #113          // org/scalatest/events/TestPending
  #115 = NameAndType        #31:#32       // summaryCounter:Lorg/scalatest/tools/Framework$SummaryCounter;
  #116 = Fieldref           #2.#115       // org/scalatest/tools/Framework$SbtReporter.summaryCounter:Lorg/scalatest/tools/Framework$SummaryCounter;
  #117 = Utf8               incrementTestsPendingCount
  #118 = NameAndType        #117:#66      // incrementTestsPendingCount:()V
  #119 = Methodref          #20.#118      // org/scalatest/tools/Framework$SummaryCounter.incrementTestsPendingCount:()V
  #120 = NameAndType        #27:#28       // eventHandler:Lsbt/testing/EventHandler;
  #121 = Fieldref           #2.#120       // org/scalatest/tools/Framework$SbtReporter.eventHandler:Lsbt/testing/EventHandler;
  #122 = Utf8               org$scalatest$tools$Framework$SbtReporter$$$outer
  #123 = Utf8               ()Lorg/scalatest/tools/Framework;
  #124 = NameAndType        #122:#123     // org$scalatest$tools$Framework$SbtReporter$$$outer:()Lorg/scalatest/tools/Framework;
  #125 = Methodref          #2.#124       // org/scalatest/tools/Framework$SbtReporter.org$scalatest$tools$Framework$SbtReporter$$$outer:()Lorg/scalatest/tools/Framework;
  #126 = NameAndType        #24:#23       // fullyQualifiedName:Ljava/lang/String;
  #127 = Fieldref           #2.#126       // org/scalatest/tools/Framework$SbtReporter.fullyQualifiedName:Ljava/lang/String;
  #128 = NameAndType        #25:#26       // fingerprint:Lsbt/testing/Fingerprint;
  #129 = Fieldref           #2.#128       // org/scalatest/tools/Framework$SbtReporter.fingerprint:Lsbt/testing/Fingerprint;
  #130 = Utf8               ()Ljava/lang/String;
  #131 = NameAndType        #22:#130      // suiteId:()Ljava/lang/String;
  #132 = Methodref          #114.#131     // org/scalatest/events/TestPending.suiteId:()Ljava/lang/String;
  #133 = NameAndType        #38:#130      // testName:()Ljava/lang/String;
  #134 = Methodref          #114.#133     // org/scalatest/events/TestPending.testName:()Ljava/lang/String;
  #135 = NameAndType        #35:#36       // getTestSelector:(Ljava/lang/String;Ljava/lang/String;)Lsbt/testing/Selector;
  #136 = Methodref          #2.#135       // org/scalatest/tools/Framework$SbtReporter.getTestSelector:(Ljava/lang/String;Ljava/lang/String;)Lsbt/testing/Selector;
  #137 = Utf8               sbt/testing/Status
  #138 = Class              #137          // sbt/testing/Status
  #139 = Utf8               Pending
  #140 = Utf8               Lsbt/testing/Status;
  #141 = NameAndType        #139:#140     // Pending:Lsbt/testing/Status;
  #142 = Fieldref           #138.#141     // sbt/testing/Status.Pending:Lsbt/testing/Status;
  #143 = Utf8               duration
  #144 = Utf8               ()Lscala/Option;
  #145 = NameAndType        #143:#144     // duration:()Lscala/Option;
  #146 = Methodref          #114.#145     // org/scalatest/events/TestPending.duration:()Lscala/Option;
  #147 = Utf8               ()J
  #148 = MethodType         #147          //  ()J
  #149 = Utf8               $anonfun$apply$2
  #150 = NameAndType        #149:#147     // $anonfun$apply$2:()J
  #151 = Methodref          #2.#150       // org/scalatest/tools/Framework$SbtReporter.$anonfun$apply$2:()J
  #152 = MethodHandle       6:#151        // REF_invokeStatic org/scalatest/tools/Framework$SbtReporter.$anonfun$apply$2:()J
  #153 = Integer            1
  #154 = Utf8               java/lang/invoke/LambdaMetafactory
  #155 = Class              #154          // java/lang/invoke/LambdaMetafactory
  #156 = Utf8               altMetafactory
  #157 = Utf8               (Ljava/lang/invoke/MethodHandles$Lookup;Ljava/lang/String;Ljava/lang/invoke/MethodType;[Ljava/lang/Object;)Ljava/lang/invoke/CallSite;
  #158 = NameAndType        #156:#157     // altMetafactory:(Ljava/lang/invoke/MethodHandles$Lookup;Ljava/lang/String;Ljava/lang/invoke/MethodType;[Ljava/lang/Object;)Ljava/lang/invoke/CallSite;
  #159 = Methodref          #155.#158     // java/lang/invoke/LambdaMetafactory.altMetafactory:(Ljava/lang/invoke/MethodHandles$Lookup;Ljava/lang/String;Ljava/lang/invoke/MethodType;[Ljava/lang/Object;)Ljava/lang/invoke/CallSite;
  #160 = MethodHandle       6:#159        // REF_invokeStatic java/lang/invoke/LambdaMetafactory.altMetafactory:(Ljava/lang/invoke/MethodHandles$Lookup;Ljava/lang/String;Ljava/lang/invoke/MethodType;[Ljava/lang/Object;)Ljava/lang/invoke/CallSite;
  #161 = Utf8               apply$mcJ$sp
  #162 = Utf8               ()Lscala/runtime/java8/JFunction0$mcJ$sp;
  #163 = NameAndType        #161:#162     // apply$mcJ$sp:()Lscala/runtime/java8/JFunction0$mcJ$sp;
  #164 = InvokeDynamic      #0:#163       // #0:apply$mcJ$sp:()Lscala/runtime/java8/JFunction0$mcJ$sp;
  #165 = Utf8               getOrElse
  #166 = Utf8               (Lscala/Function0;)Ljava/lang/Object;
  #167 = NameAndType        #165:#166     // getOrElse:(Lscala/Function0;)Ljava/lang/Object;
  #168 = Methodref          #105.#167     // scala/Option.getOrElse:(Lscala/Function0;)Ljava/lang/Object;
  #169 = Utf8               scala/runtime/BoxesRunTime
  #170 = Class              #169          // scala/runtime/BoxesRunTime
  #171 = Utf8               unboxToLong
  #172 = Utf8               (Ljava/lang/Object;)J
  #173 = NameAndType        #171:#172     // unboxToLong:(Ljava/lang/Object;)J
  #174 = Methodref          #170.#173     // scala/runtime/BoxesRunTime.unboxToLong:(Ljava/lang/Object;)J
  #175 = Utf8               (Lorg/scalatest/tools/Framework;Ljava/lang/String;Lsbt/testing/Fingerprint;Lsbt/testing/Selector;Lsbt/testing/Status;Lsbt/testing/OptionalThrowable;J)V
  #176 = NameAndType        #47:#175      // "<init>":(Lorg/scalatest/tools/Framework;Ljava/lang/String;Lsbt/testing/Fingerprint;Lsbt/testing/Selector;Lsbt/testing/Status;Lsbt/testing/OptionalThrowable;J)V
  #177 = Methodref          #17.#176      // org/scalatest/tools/Framework$ScalaTestSbtEvent."<init>":(Lorg/scalatest/tools/Framework;Ljava/lang/String;Lsbt/testing/Fingerprint;Lsbt/testing/Selector;Lsbt/testing/Status;Lsbt/testing/OptionalThrowable;J)V
  #178 = Utf8               sbt/testing/EventHandler
  #179 = Class              #178          // sbt/testing/EventHandler
  #180 = Utf8               handle
  #181 = Utf8               (Lsbt/testing/Event;)V
  #182 = NameAndType        #180:#181     // handle:(Lsbt/testing/Event;)V
  #183 = InterfaceMethodref #179.#182     // sbt/testing/EventHandler.handle:(Lsbt/testing/Event;)V
  #184 = Utf8               scala/runtime/BoxedUnit
  #185 = Class              #184          // scala/runtime/BoxedUnit
  #186 = Utf8               UNIT
  #187 = Utf8               Lscala/runtime/BoxedUnit;
  #188 = NameAndType        #186:#187     // UNIT:Lscala/runtime/BoxedUnit;
  #189 = Fieldref           #185.#188     // scala/runtime/BoxedUnit.UNIT:Lscala/runtime/BoxedUnit;
  #190 = Utf8               org/scalatest/events/TestFailed
  #191 = Class              #190          // org/scalatest/events/TestFailed
  #192 = Utf8               incrementTestsFailedCount
  #193 = NameAndType        #192:#66      // incrementTestsFailedCount:()V
  #194 = Methodref          #20.#193      // org/scalatest/tools/Framework$SummaryCounter.incrementTestsFailedCount:()V
  #195 = Methodref          #191.#131     // org/scalatest/events/TestFailed.suiteId:()Ljava/lang/String;
  #196 = Methodref          #191.#133     // org/scalatest/events/TestFailed.testName:()Ljava/lang/String;
  #197 = Utf8               Failure
  #198 = NameAndType        #197:#140     // Failure:Lsbt/testing/Status;
  #199 = Fieldref           #138.#198     // sbt/testing/Status.Failure:Lsbt/testing/Status;
  #200 = NameAndType        #75:#144      // throwable:()Lscala/Option;
  #201 = Methodref          #191.#200     // org/scalatest/events/TestFailed.throwable:()Lscala/Option;
  #202 = NameAndType        #72:#73       // getOptionalThrowable:(Lscala/Option;)Lsbt/testing/OptionalThrowable;
  #203 = Methodref          #2.#202       // org/scalatest/tools/Framework$SbtReporter.getOptionalThrowable:(Lscala/Option;)Lsbt/testing/OptionalThrowable;
  #204 = Methodref          #191.#145     // org/scalatest/events/TestFailed.duration:()Lscala/Option;
  #205 = Utf8               $anonfun$apply$3
  #206 = NameAndType        #205:#147     // $anonfun$apply$3:()J
  #207 = Methodref          #2.#206       // org/scalatest/tools/Framework$SbtReporter.$anonfun$apply$3:()J
  #208 = MethodHandle       6:#207        // REF_invokeStatic org/scalatest/tools/Framework$SbtReporter.$anonfun$apply$3:()J
  #209 = InvokeDynamic      #1:#163       // #1:apply$mcJ$sp:()Lscala/runtime/java8/JFunction0$mcJ$sp;
  #210 = Utf8               org/scalatest/events/TestSucceeded
  #211 = Class              #210          // org/scalatest/events/TestSucceeded
  #212 = Utf8               incrementTestsSucceededCount
  #213 = NameAndType        #212:#66      // incrementTestsSucceededCount:()V
  #214 = Methodref          #20.#213      // org/scalatest/tools/Framework$SummaryCounter.incrementTestsSucceededCount:()V
  #215 = Methodref          #211.#131     // org/scalatest/events/TestSucceeded.suiteId:()Ljava/lang/String;
  #216 = Methodref          #211.#133     // org/scalatest/events/TestSucceeded.testName:()Ljava/lang/String;
  #217 = Utf8               Success
  #218 = NameAndType        #217:#140     // Success:Lsbt/testing/Status;
  #219 = Fieldref           #138.#218     // sbt/testing/Status.Success:Lsbt/testing/Status;
  #220 = Methodref          #211.#145     // org/scalatest/events/TestSucceeded.duration:()Lscala/Option;
  #221 = Utf8               $anonfun$apply$4
  #222 = NameAndType        #221:#147     // $anonfun$apply$4:()J
  #223 = Methodref          #2.#222       // org/scalatest/tools/Framework$SbtReporter.$anonfun$apply$4:()J
  #224 = MethodHandle       6:#223        // REF_invokeStatic org/scalatest/tools/Framework$SbtReporter.$anonfun$apply$4:()J
  #225 = InvokeDynamic      #2:#163       // #2:apply$mcJ$sp:()Lscala/runtime/java8/JFunction0$mcJ$sp;
  #226 = Utf8               org/scalatest/events/TestIgnored
  #227 = Class              #226          // org/scalatest/events/TestIgnored
  #228 = Utf8               incrementTestsIgnoredCount
  #229 = NameAndType        #228:#66      // incrementTestsIgnoredCount:()V
  #230 = Methodref          #20.#229      // org/scalatest/tools/Framework$SummaryCounter.incrementTestsIgnoredCount:()V
  #231 = Methodref          #227.#131     // org/scalatest/events/TestIgnored.suiteId:()Ljava/lang/String;
  #232 = Methodref          #227.#133     // org/scalatest/events/TestIgnored.testName:()Ljava/lang/String;
  #233 = Utf8               Ignored
  #234 = NameAndType        #233:#140     // Ignored:Lsbt/testing/Status;
  #235 = Fieldref           #138.#234     // sbt/testing/Status.Ignored:Lsbt/testing/Status;
  #236 = Long               -1l
  #238 = Utf8               org/scalatest/events/TestCanceled
  #239 = Class              #238          // org/scalatest/events/TestCanceled
  #240 = Utf8               incrementTestsCanceledCount
  #241 = NameAndType        #240:#66      // incrementTestsCanceledCount:()V
  #242 = Methodref          #20.#241      // org/scalatest/tools/Framework$SummaryCounter.incrementTestsCanceledCount:()V
  #243 = Methodref          #239.#131     // org/scalatest/events/TestCanceled.suiteId:()Ljava/lang/String;
  #244 = Methodref          #239.#133     // org/scalatest/events/TestCanceled.testName:()Ljava/lang/String;
  #245 = Utf8               Canceled
  #246 = NameAndType        #245:#140     // Canceled:Lsbt/testing/Status;
  #247 = Fieldref           #138.#246     // sbt/testing/Status.Canceled:Lsbt/testing/Status;
  #248 = Methodref          #239.#145     // org/scalatest/events/TestCanceled.duration:()Lscala/Option;
  #249 = Utf8               $anonfun$apply$5
  #250 = NameAndType        #249:#147     // $anonfun$apply$5:()J
  #251 = Methodref          #2.#250       // org/scalatest/tools/Framework$SbtReporter.$anonfun$apply$5:()J
  #252 = MethodHandle       6:#251        // REF_invokeStatic org/scalatest/tools/Framework$SbtReporter.$anonfun$apply$5:()J
  #253 = InvokeDynamic      #3:#163       // #3:apply$mcJ$sp:()Lscala/runtime/java8/JFunction0$mcJ$sp;
  #254 = Utf8               org/scalatest/events/SuiteCompleted
  #255 = Class              #254          // org/scalatest/events/SuiteCompleted
  #256 = Utf8               incrementSuitesCompletedCount
  #257 = NameAndType        #256:#66      // incrementSuitesCompletedCount:()V
  #258 = Methodref          #20.#257      // org/scalatest/tools/Framework$SummaryCounter.incrementSuitesCompletedCount:()V
  #259 = Utf8               org/scalatest/events/SuiteAborted
  #260 = Class              #259          // org/scalatest/events/SuiteAborted
  #261 = Utf8               incrementSuitesAbortedCount
  #262 = NameAndType        #261:#66      // incrementSuitesAbortedCount:()V
  #263 = Methodref          #20.#262      // org/scalatest/tools/Framework$SummaryCounter.incrementSuitesAbortedCount:()V
  #264 = Methodref          #260.#131     // org/scalatest/events/SuiteAborted.suiteId:()Ljava/lang/String;
  #265 = NameAndType        #62:#63       // getSuiteSelector:(Ljava/lang/String;)Lsbt/testing/Selector;
  #266 = Methodref          #2.#265       // org/scalatest/tools/Framework$SbtReporter.getSuiteSelector:(Ljava/lang/String;)Lsbt/testing/Selector;
  #267 = Utf8               Error
  #268 = NameAndType        #267:#140     // Error:Lsbt/testing/Status;
  #269 = Fieldref           #138.#268     // sbt/testing/Status.Error:Lsbt/testing/Status;
  #270 = Methodref          #260.#200     // org/scalatest/events/SuiteAborted.throwable:()Lscala/Option;
  #271 = Methodref          #260.#145     // org/scalatest/events/SuiteAborted.duration:()Lscala/Option;
  #272 = Utf8               $anonfun$apply$6
  #273 = NameAndType        #272:#147     // $anonfun$apply$6:()J
  #274 = Methodref          #2.#273       // org/scalatest/tools/Framework$SbtReporter.$anonfun$apply$6:()J
  #275 = MethodHandle       6:#274        // REF_invokeStatic org/scalatest/tools/Framework$SbtReporter.$anonfun$apply$6:()J
  #276 = InvokeDynamic      #4:#163       // #4:apply$mcJ$sp:()Lscala/runtime/java8/JFunction0$mcJ$sp;
  #277 = Utf8               org/scalatest/events/ScopePending
  #278 = Class              #277          // org/scalatest/events/ScopePending
  #279 = Utf8               incrementScopesPendingCount
  #280 = NameAndType        #279:#66      // incrementScopesPendingCount:()V
  #281 = Methodref          #20.#280      // org/scalatest/tools/Framework$SummaryCounter.incrementScopesPendingCount:()V
  #282 = Utf8               Lorg/scalatest/events/Event;
  #283 = Utf8               org/scalatest/events/Event
  #284 = Class              #283          // org/scalatest/events/Event
  #285 = NameAndType        #33:#34       // $outer:Lorg/scalatest/tools/Framework;
  #286 = Fieldref           #2.#285       // org/scalatest/tools/Framework$SbtReporter.$outer:Lorg/scalatest/tools/Framework;
  #287 = Utf8               (Lorg/scalatest/tools/Framework;Ljava/lang/String;Ljava/lang/String;Lsbt/testing/Fingerprint;Lsbt/testing/EventHandler;Lorg/scalatest/Reporter;Lorg/scalatest/tools/Framework$SummaryCounter;)V
  #288 = Methodref          #4.#67        // java/lang/Object."<init>":()V
  #289 = Utf8               $deserializeLambda$
  #290 = Utf8               (Ljava/lang/invoke/SerializedLambda;)Ljava/lang/Object;
  #291 = Utf8               scala/runtime/LambdaDeserialize
  #292 = Class              #291          // scala/runtime/LambdaDeserialize
  #293 = Utf8               bootstrap
  #294 = Utf8               (Ljava/lang/invoke/MethodHandles$Lookup;Ljava/lang/String;Ljava/lang/invoke/MethodType;[Ljava/lang/invoke/MethodHandle;)Ljava/lang/invoke/CallSite;
  #295 = NameAndType        #293:#294     // bootstrap:(Ljava/lang/invoke/MethodHandles$Lookup;Ljava/lang/String;Ljava/lang/invoke/MethodType;[Ljava/lang/invoke/MethodHandle;)Ljava/lang/invoke/CallSite;
  #296 = Methodref          #292.#295     // scala/runtime/LambdaDeserialize.bootstrap:(Ljava/lang/invoke/MethodHandles$Lookup;Ljava/lang/String;Ljava/lang/invoke/MethodType;[Ljava/lang/invoke/MethodHandle;)Ljava/lang/invoke/CallSite;
  #297 = MethodHandle       6:#296        // REF_invokeStatic scala/runtime/LambdaDeserialize.bootstrap:(Ljava/lang/invoke/MethodHandles$Lookup;Ljava/lang/String;Ljava/lang/invoke/MethodType;[Ljava/lang/invoke/MethodHandle;)Ljava/lang/invoke/CallSite;
  #298 = Utf8               lambdaDeserialize
  #299 = NameAndType        #298:#290     // lambdaDeserialize:(Ljava/lang/invoke/SerializedLambda;)Ljava/lang/Object;
  #300 = InvokeDynamic      #5:#299       // #5:lambdaDeserialize:(Ljava/lang/invoke/SerializedLambda;)Ljava/lang/Object;
  #301 = Utf8               Code
  #302 = Utf8               StackMapTable
  #303 = Utf8               LineNumberTable
  #304 = Utf8               LocalVariableTable
  #305 = Utf8               MethodParameters
  #306 = Utf8               Signature
  #307 = Utf8               InnerClasses
  #308 = Utf8               SourceFile
  #309 = Utf8               BootstrapMethods
  #310 = Utf8               ScalaInlineInfo
  #311 = Utf8               Scala
{
  private final java.lang.String suiteId;
    descriptor: Ljava/lang/String;
    flags: (0x0012) ACC_PRIVATE, ACC_FINAL

  private final java.lang.String fullyQualifiedName;
    descriptor: Ljava/lang/String;
    flags: (0x0012) ACC_PRIVATE, ACC_FINAL

  private final sbt.testing.Fingerprint fingerprint;
    descriptor: Lsbt/testing/Fingerprint;
    flags: (0x0012) ACC_PRIVATE, ACC_FINAL

  private final sbt.testing.EventHandler eventHandler;
    descriptor: Lsbt/testing/EventHandler;
    flags: (0x0012) ACC_PRIVATE, ACC_FINAL

  private final org.scalatest.Reporter report;
    descriptor: Lorg/scalatest/Reporter;
    flags: (0x0012) ACC_PRIVATE, ACC_FINAL

  private final org.scalatest.tools.Framework$SummaryCounter summaryCounter;
    descriptor: Lorg/scalatest/tools/Framework$SummaryCounter;
    flags: (0x0012) ACC_PRIVATE, ACC_FINAL

  public final org.scalatest.tools.Framework $outer;
    descriptor: Lorg/scalatest/tools/Framework;
    flags: (0x1011) ACC_PUBLIC, ACC_FINAL, ACC_SYNTHETIC

  private sbt.testing.Selector getTestSelector(java.lang.String, java.lang.String);
    descriptor: (Ljava/lang/String;Ljava/lang/String;)Lsbt/testing/Selector;
    flags: (0x0002) ACC_PRIVATE
    Code:
      stack=4, locals=4, args_size=3
         0: aload_0
         1: getfield      #40                 // Field suiteId:Ljava/lang/String;
         4: aload_1
         5: astore_3
         6: dup
         7: ifnonnull     18
        10: pop
        11: aload_3
        12: ifnull        25
        15: goto          36
        18: aload_3
        19: invokevirtual #44                 // Method java/lang/Object.equals:(Ljava/lang/Object;)Z
        22: ifeq          36
        25: new           #46                 // class sbt/testing/TestSelector
        28: dup
        29: aload_2
        30: invokespecial #50                 // Method sbt/testing/TestSelector."<init>":(Ljava/lang/String;)V
        33: goto          45
        36: new           #52                 // class sbt/testing/NestedTestSelector
        39: dup
        40: aload_1
        41: aload_2
        42: invokespecial #55                 // Method sbt/testing/NestedTestSelector."<init>":(Ljava/lang/String;Ljava/lang/String;)V
        45: areturn
      StackMapTable: number_of_entries = 4
        frame_type = 255 /* full_frame */
          offset_delta = 18
          locals = [ class org/scalatest/tools/Framework$SbtReporter, class java/lang/String, class java/lang/String, class java/lang/String ]
          stack = [ class java/lang/String ]
        frame_type = 6 /* same */
        frame_type = 10 /* same */
        frame_type = 72 /* same_locals_1_stack_item */
          stack = [ class sbt/testing/Selector ]
      LineNumberTable:
        line 1164: 0
        line 1165: 25
        line 1167: 36
      LocalVariableTable:
        Start  Length  Slot  Name   Signature
            0      46     0  this   Lorg/scalatest/tools/Framework$SbtReporter;
            0      46     1 eventSuiteId   Ljava/lang/String;
            0      46     2 testName   Ljava/lang/String;
    MethodParameters:
      Name                           Flags
      eventSuiteId                   final
      testName                       final

  private sbt.testing.Selector getSuiteSelector(java.lang.String);
    descriptor: (Ljava/lang/String;)Lsbt/testing/Selector;
    flags: (0x0002) ACC_PRIVATE
    Code:
      stack=3, locals=3, args_size=2
         0: aload_0
         1: getfield      #40                 // Field suiteId:Ljava/lang/String;
         4: aload_1
         5: astore_2
         6: dup
         7: ifnonnull     18
        10: pop
        11: aload_2
        12: ifnull        25
        15: goto          35
        18: aload_2
        19: invokevirtual #44                 // Method java/lang/Object.equals:(Ljava/lang/Object;)Z
        22: ifeq          35
        25: new           #65                 // class sbt/testing/SuiteSelector
        28: dup
        29: invokespecial #68                 // Method sbt/testing/SuiteSelector."<init>":()V
        32: goto          43
        35: new           #70                 // class sbt/testing/NestedSuiteSelector
        38: dup
        39: aload_1
        40: invokespecial #71                 // Method sbt/testing/NestedSuiteSelector."<init>":(Ljava/lang/String;)V
        43: areturn
      StackMapTable: number_of_entries = 4
        frame_type = 255 /* full_frame */
          offset_delta = 18
          locals = [ class org/scalatest/tools/Framework$SbtReporter, class java/lang/String, class java/lang/String ]
          stack = [ class java/lang/String ]
        frame_type = 6 /* same */
        frame_type = 9 /* same */
        frame_type = 71 /* same_locals_1_stack_item */
          stack = [ class sbt/testing/Selector ]
      LineNumberTable:
        line 1171: 0
        line 1172: 25
        line 1174: 35
      LocalVariableTable:
        Start  Length  Slot  Name   Signature
            0      44     0  this   Lorg/scalatest/tools/Framework$SbtReporter;
            0      44     1 eventSuiteId   Ljava/lang/String;
    MethodParameters:
      Name                           Flags
      eventSuiteId                   final

  private sbt.testing.OptionalThrowable getOptionalThrowable(scala.Option<java.lang.Throwable>);
    descriptor: (Lscala/Option;)Lsbt/testing/OptionalThrowable;
    flags: (0x0002) ACC_PRIVATE
    Code:
      stack=3, locals=6, args_size=2
         0: aload_1
         1: astore_3
         2: aload_3
         3: instanceof    #77                 // class scala/Some
         6: ifeq          38
         9: aload_3
        10: checkcast     #77                 // class scala/Some
        13: astore        4
        15: aload         4
        17: invokevirtual #81                 // Method scala/Some.value:()Ljava/lang/Object;
        20: checkcast     #83                 // class java/lang/Throwable
        23: astore        5
        25: new           #85                 // class sbt/testing/OptionalThrowable
        28: dup
        29: aload         5
        31: invokespecial #88                 // Method sbt/testing/OptionalThrowable."<init>":(Ljava/lang/Throwable;)V
        34: astore_2
        35: goto          74
        38: goto          41
        41: getstatic     #94                 // Field scala/None$.MODULE$:Lscala/None$;
        44: aload_3
        45: invokevirtual #44                 // Method java/lang/Object.equals:(Ljava/lang/Object;)Z
        48: ifeq          62
        51: new           #85                 // class sbt/testing/OptionalThrowable
        54: dup
        55: invokespecial #95                 // Method sbt/testing/OptionalThrowable."<init>":()V
        58: astore_2
        59: goto          74
        62: goto          65
        65: new           #97                 // class scala/MatchError
        68: dup
        69: aload_3
        70: invokespecial #100                // Method scala/MatchError."<init>":(Ljava/lang/Object;)V
        73: athrow
        74: aload_2
        75: areturn
      StackMapTable: number_of_entries = 5
        frame_type = 253 /* append */
          offset_delta = 38
          locals = [ top, class scala/Option ]
        frame_type = 2 /* same */
        frame_type = 20 /* same */
        frame_type = 2 /* same */
        frame_type = 255 /* full_frame */
          offset_delta = 8
          locals = [ class org/scalatest/tools/Framework$SbtReporter, class scala/Option, class sbt/testing/OptionalThrowable, class scala/Option ]
          stack = []
      LineNumberTable:
        line 1178: 0
        line 1179: 2
        line 1180: 41
        line 1178: 65
      LocalVariableTable:
        Start  Length  Slot  Name   Signature
           25      13     5     t   Ljava/lang/Throwable;
            0      76     0  this   Lorg/scalatest/tools/Framework$SbtReporter;
            0      76     1 throwable   Lscala/Option;
    Signature: #74                          // (Lscala/Option<Ljava/lang/Throwable;>;)Lsbt/testing/OptionalThrowable;
    MethodParameters:
      Name                           Flags
      throwable                      final

  public void apply(org.scalatest.events.Event);
    descriptor: (Lorg/scalatest/events/Event;)V
    flags: (0x0001) ACC_PUBLIC
    Code:
      stack=11, locals=10, args_size=2
         0: aload_0
         1: getfield      #110                // Field report:Lorg/scalatest/Reporter;
         4: aload_1
         5: invokeinterface #112,  2          // InterfaceMethod org/scalatest/Reporter.apply:(Lorg/scalatest/events/Event;)V
        10: aload_1
        11: astore_3
        12: aload_3
        13: instanceof    #114                // class org/scalatest/events/TestPending
        16: ifeq          107
        19: aload_3
        20: checkcast     #114                // class org/scalatest/events/TestPending
        23: astore        4
        25: aload_0
        26: getfield      #116                // Field summaryCounter:Lorg/scalatest/tools/Framework$SummaryCounter;
        29: invokevirtual #119                // Method org/scalatest/tools/Framework$SummaryCounter.incrementTestsPendingCount:()V
        32: aload_0
        33: getfield      #121                // Field eventHandler:Lsbt/testing/EventHandler;
        36: new           #17                 // class org/scalatest/tools/Framework$ScalaTestSbtEvent
        39: dup
        40: aload_0
        41: invokevirtual #125                // Method org$scalatest$tools$Framework$SbtReporter$$$outer:()Lorg/scalatest/tools/Framework;
        44: aload_0
        45: getfield      #127                // Field fullyQualifiedName:Ljava/lang/String;
        48: aload_0
        49: getfield      #129                // Field fingerprint:Lsbt/testing/Fingerprint;
        52: aload_0
        53: aload         4
        55: invokevirtual #132                // Method org/scalatest/events/TestPending.suiteId:()Ljava/lang/String;
        58: aload         4
        60: invokevirtual #134                // Method org/scalatest/events/TestPending.testName:()Ljava/lang/String;
        63: invokespecial #136                // Method getTestSelector:(Ljava/lang/String;Ljava/lang/String;)Lsbt/testing/Selector;
        66: getstatic     #142                // Field sbt/testing/Status.Pending:Lsbt/testing/Status;
        69: new           #85                 // class sbt/testing/OptionalThrowable
        72: dup
        73: invokespecial #95                 // Method sbt/testing/OptionalThrowable."<init>":()V
        76: aload         4
        78: invokevirtual #146                // Method org/scalatest/events/TestPending.duration:()Lscala/Option;
        81: invokedynamic #164,  0            // InvokeDynamic #0:apply$mcJ$sp:()Lscala/runtime/java8/JFunction0$mcJ$sp;
        86: invokevirtual #168                // Method scala/Option.getOrElse:(Lscala/Function0;)Ljava/lang/Object;
        89: invokestatic  #174                // Method scala/runtime/BoxesRunTime.unboxToLong:(Ljava/lang/Object;)J
        92: invokespecial #177                // Method org/scalatest/tools/Framework$ScalaTestSbtEvent."<init>":(Lorg/scalatest/tools/Framework;Ljava/lang/String;Lsbt/testing/Fingerprint;Lsbt/testing/Selector;Lsbt/testing/Status;Lsbt/testing/OptionalThrowable;J)V
        95: invokeinterface #183,  2          // InterfaceMethod sbt/testing/EventHandler.handle:(Lsbt/testing/Event;)V
       100: getstatic     #189                // Field scala/runtime/BoxedUnit.UNIT:Lscala/runtime/BoxedUnit;
       103: astore_2
       104: goto          641
       107: goto          110
       110: aload_3
       111: instanceof    #191                // class org/scalatest/events/TestFailed
       114: ifeq          207
       117: aload_3
       118: checkcast     #191                // class org/scalatest/events/TestFailed
       121: astore        5
       123: aload_0
       124: getfield      #116                // Field summaryCounter:Lorg/scalatest/tools/Framework$SummaryCounter;
       127: invokevirtual #194                // Method org/scalatest/tools/Framework$SummaryCounter.incrementTestsFailedCount:()V
       130: aload_0
       131: getfield      #121                // Field eventHandler:Lsbt/testing/EventHandler;
       134: new           #17                 // class org/scalatest/tools/Framework$ScalaTestSbtEvent
       137: dup
       138: aload_0
       139: invokevirtual #125                // Method org$scalatest$tools$Framework$SbtReporter$$$outer:()Lorg/scalatest/tools/Framework;
       142: aload_0
       143: getfield      #127                // Field fullyQualifiedName:Ljava/lang/String;
       146: aload_0
       147: getfield      #129                // Field fingerprint:Lsbt/testing/Fingerprint;
       150: aload_0
       151: aload         5
       153: invokevirtual #195                // Method org/scalatest/events/TestFailed.suiteId:()Ljava/lang/String;
       156: aload         5
       158: invokevirtual #196                // Method org/scalatest/events/TestFailed.testName:()Ljava/lang/String;
       161: invokespecial #136                // Method getTestSelector:(Ljava/lang/String;Ljava/lang/String;)Lsbt/testing/Selector;
       164: getstatic     #199                // Field sbt/testing/Status.Failure:Lsbt/testing/Status;
       167: aload_0
       168: aload         5
       170: invokevirtual #201                // Method org/scalatest/events/TestFailed.throwable:()Lscala/Option;
       173: invokespecial #203                // Method getOptionalThrowable:(Lscala/Option;)Lsbt/testing/OptionalThrowable;
       176: aload         5
       178: invokevirtual #204                // Method org/scalatest/events/TestFailed.duration:()Lscala/Option;
       181: invokedynamic #209,  0            // InvokeDynamic #1:apply$mcJ$sp:()Lscala/runtime/java8/JFunction0$mcJ$sp;
       186: invokevirtual #168                // Method scala/Option.getOrElse:(Lscala/Function0;)Ljava/lang/Object;
       189: invokestatic  #174                // Method scala/runtime/BoxesRunTime.unboxToLong:(Ljava/lang/Object;)J
       192: invokespecial #177                // Method org/scalatest/tools/Framework$ScalaTestSbtEvent."<init>":(Lorg/scalatest/tools/Framework;Ljava/lang/String;Lsbt/testing/Fingerprint;Lsbt/testing/Selector;Lsbt/testing/Status;Lsbt/testing/OptionalThrowable;J)V
       195: invokeinterface #183,  2          // InterfaceMethod sbt/testing/EventHandler.handle:(Lsbt/testing/Event;)V
       200: getstatic     #189                // Field scala/runtime/BoxedUnit.UNIT:Lscala/runtime/BoxedUnit;
       203: astore_2
       204: goto          641
       207: goto          210
       210: aload_3
       211: instanceof    #211                // class org/scalatest/events/TestSucceeded
       214: ifeq          305
       217: aload_3
       218: checkcast     #211                // class org/scalatest/events/TestSucceeded
       221: astore        6
       223: aload_0
       224: getfield      #116                // Field summaryCounter:Lorg/scalatest/tools/Framework$SummaryCounter;
       227: invokevirtual #214                // Method org/scalatest/tools/Framework$SummaryCounter.incrementTestsSucceededCount:()V
       230: aload_0
       231: getfield      #121                // Field eventHandler:Lsbt/testing/EventHandler;
       234: new           #17                 // class org/scalatest/tools/Framework$ScalaTestSbtEvent
       237: dup
       238: aload_0
       239: invokevirtual #125                // Method org$scalatest$tools$Framework$SbtReporter$$$outer:()Lorg/scalatest/tools/Framework;
       242: aload_0
       243: getfield      #127                // Field fullyQualifiedName:Ljava/lang/String;
       246: aload_0
       247: getfield      #129                // Field fingerprint:Lsbt/testing/Fingerprint;
       250: aload_0
       251: aload         6
       253: invokevirtual #215                // Method org/scalatest/events/TestSucceeded.suiteId:()Ljava/lang/String;
       256: aload         6
       258: invokevirtual #216                // Method org/scalatest/events/TestSucceeded.testName:()Ljava/lang/String;
       261: invokespecial #136                // Method getTestSelector:(Ljava/lang/String;Ljava/lang/String;)Lsbt/testing/Selector;
       264: getstatic     #219                // Field sbt/testing/Status.Success:Lsbt/testing/Status;
       267: new           #85                 // class sbt/testing/OptionalThrowable
       270: dup
       271: invokespecial #95                 // Method sbt/testing/OptionalThrowable."<init>":()V
       274: aload         6
       276: invokevirtual #220                // Method org/scalatest/events/TestSucceeded.duration:()Lscala/Option;
       279: invokedynamic #225,  0            // InvokeDynamic #2:apply$mcJ$sp:()Lscala/runtime/java8/JFunction0$mcJ$sp;
       284: invokevirtual #168                // Method scala/Option.getOrElse:(Lscala/Function0;)Ljava/lang/Object;
       287: invokestatic  #174                // Method scala/runtime/BoxesRunTime.unboxToLong:(Ljava/lang/Object;)J
       290: invokespecial #177                // Method org/scalatest/tools/Framework$ScalaTestSbtEvent."<init>":(Lorg/scalatest/tools/Framework;Ljava/lang/String;Lsbt/testing/Fingerprint;Lsbt/testing/Selector;Lsbt/testing/Status;Lsbt/testing/OptionalThrowable;J)V
       293: invokeinterface #183,  2          // InterfaceMethod sbt/testing/EventHandler.handle:(Lsbt/testing/Event;)V
       298: getstatic     #189                // Field scala/runtime/BoxedUnit.UNIT:Lscala/runtime/BoxedUnit;
       301: astore_2
       302: goto          641
       305: goto          308
       308: aload_3
       309: instanceof    #227                // class org/scalatest/events/TestIgnored
       312: ifeq          390
       315: aload_3
       316: checkcast     #227                // class org/scalatest/events/TestIgnored
       319: astore        7
       321: aload_0
       322: getfield      #116                // Field summaryCounter:Lorg/scalatest/tools/Framework$SummaryCounter;
       325: invokevirtual #230                // Method org/scalatest/tools/Framework$SummaryCounter.incrementTestsIgnoredCount:()V
       328: aload_0
       329: getfield      #121                // Field eventHandler:Lsbt/testing/EventHandler;
       332: new           #17                 // class org/scalatest/tools/Framework$ScalaTestSbtEvent
       335: dup
       336: aload_0
       337: invokevirtual #125                // Method org$scalatest$tools$Framework$SbtReporter$$$outer:()Lorg/scalatest/tools/Framework;
       340: aload_0
       341: getfield      #127                // Field fullyQualifiedName:Ljava/lang/String;
       344: aload_0
       345: getfield      #129                // Field fingerprint:Lsbt/testing/Fingerprint;
       348: aload_0
       349: aload         7
       351: invokevirtual #231                // Method org/scalatest/events/TestIgnored.suiteId:()Ljava/lang/String;
       354: aload         7
       356: invokevirtual #232                // Method org/scalatest/events/TestIgnored.testName:()Ljava/lang/String;
       359: invokespecial #136                // Method getTestSelector:(Ljava/lang/String;Ljava/lang/String;)Lsbt/testing/Selector;
       362: getstatic     #235                // Field sbt/testing/Status.Ignored:Lsbt/testing/Status;
       365: new           #85                 // class sbt/testing/OptionalThrowable
       368: dup
       369: invokespecial #95                 // Method sbt/testing/OptionalThrowable."<init>":()V
       372: ldc2_w        #236                // long -1l
       375: invokespecial #177                // Method org/scalatest/tools/Framework$ScalaTestSbtEvent."<init>":(Lorg/scalatest/tools/Framework;Ljava/lang/String;Lsbt/testing/Fingerprint;Lsbt/testing/Selector;Lsbt/testing/Status;Lsbt/testing/OptionalThrowable;J)V
       378: invokeinterface #183,  2          // InterfaceMethod sbt/testing/EventHandler.handle:(Lsbt/testing/Event;)V
       383: getstatic     #189                // Field scala/runtime/BoxedUnit.UNIT:Lscala/runtime/BoxedUnit;
       386: astore_2
       387: goto          641
       390: goto          393
       393: aload_3
       394: instanceof    #239                // class org/scalatest/events/TestCanceled
       397: ifeq          488
       400: aload_3
       401: checkcast     #239                // class org/scalatest/events/TestCanceled
       404: astore        8
       406: aload_0
       407: getfield      #116                // Field summaryCounter:Lorg/scalatest/tools/Framework$SummaryCounter;
       410: invokevirtual #242                // Method org/scalatest/tools/Framework$SummaryCounter.incrementTestsCanceledCount:()V
       413: aload_0
       414: getfield      #121                // Field eventHandler:Lsbt/testing/EventHandler;
       417: new           #17                 // class org/scalatest/tools/Framework$ScalaTestSbtEvent
       420: dup
       421: aload_0
       422: invokevirtual #125                // Method org$scalatest$tools$Framework$SbtReporter$$$outer:()Lorg/scalatest/tools/Framework;
       425: aload_0
       426: getfield      #127                // Field fullyQualifiedName:Ljava/lang/String;
       429: aload_0
       430: getfield      #129                // Field fingerprint:Lsbt/testing/Fingerprint;
       433: aload_0
       434: aload         8
       436: invokevirtual #243                // Method org/scalatest/events/TestCanceled.suiteId:()Ljava/lang/String;
       439: aload         8
       441: invokevirtual #244                // Method org/scalatest/events/TestCanceled.testName:()Ljava/lang/String;
       444: invokespecial #136                // Method getTestSelector:(Ljava/lang/String;Ljava/lang/String;)Lsbt/testing/Selector;
       447: getstatic     #247                // Field sbt/testing/Status.Canceled:Lsbt/testing/Status;
       450: new           #85                 // class sbt/testing/OptionalThrowable
       453: dup
       454: invokespecial #95                 // Method sbt/testing/OptionalThrowable."<init>":()V
       457: aload         8
       459: invokevirtual #248                // Method org/scalatest/events/TestCanceled.duration:()Lscala/Option;
       462: invokedynamic #253,  0            // InvokeDynamic #3:apply$mcJ$sp:()Lscala/runtime/java8/JFunction0$mcJ$sp;
       467: invokevirtual #168                // Method scala/Option.getOrElse:(Lscala/Function0;)Ljava/lang/Object;
       470: invokestatic  #174                // Method scala/runtime/BoxesRunTime.unboxToLong:(Ljava/lang/Object;)J
       473: invokespecial #177                // Method org/scalatest/tools/Framework$ScalaTestSbtEvent."<init>":(Lorg/scalatest/tools/Framework;Ljava/lang/String;Lsbt/testing/Fingerprint;Lsbt/testing/Selector;Lsbt/testing/Status;Lsbt/testing/OptionalThrowable;J)V
       476: invokeinterface #183,  2          // InterfaceMethod sbt/testing/EventHandler.handle:(Lsbt/testing/Event;)V
       481: getstatic     #189                // Field scala/runtime/BoxedUnit.UNIT:Lscala/runtime/BoxedUnit;
       484: astore_2
       485: goto          641
       488: goto          491
       491: aload_3
       492: instanceof    #255                // class org/scalatest/events/SuiteCompleted
       495: ifeq          512
       498: aload_0
       499: getfield      #116                // Field summaryCounter:Lorg/scalatest/tools/Framework$SummaryCounter;
       502: invokevirtual #258                // Method org/scalatest/tools/Framework$SummaryCounter.incrementSuitesCompletedCount:()V
       505: getstatic     #189                // Field scala/runtime/BoxedUnit.UNIT:Lscala/runtime/BoxedUnit;
       508: astore_2
       509: goto          641
       512: goto          515
       515: aload_3
       516: instanceof    #260                // class org/scalatest/events/SuiteAborted
       519: ifeq          607
       522: aload_3
       523: checkcast     #260                // class org/scalatest/events/SuiteAborted
       526: astore        9
       528: aload_0
       529: getfield      #116                // Field summaryCounter:Lorg/scalatest/tools/Framework$SummaryCounter;
       532: invokevirtual #263                // Method org/scalatest/tools/Framework$SummaryCounter.incrementSuitesAbortedCount:()V
       535: aload_0
       536: getfield      #121                // Field eventHandler:Lsbt/testing/EventHandler;
       539: new           #17                 // class org/scalatest/tools/Framework$ScalaTestSbtEvent
       542: dup
       543: aload_0
       544: invokevirtual #125                // Method org$scalatest$tools$Framework$SbtReporter$$$outer:()Lorg/scalatest/tools/Framework;
       547: aload_0
       548: getfield      #127                // Field fullyQualifiedName:Ljava/lang/String;
       551: aload_0
       552: getfield      #129                // Field fingerprint:Lsbt/testing/Fingerprint;
       555: aload_0
       556: aload         9
       558: invokevirtual #264                // Method org/scalatest/events/SuiteAborted.suiteId:()Ljava/lang/String;
       561: invokespecial #266                // Method getSuiteSelector:(Ljava/lang/String;)Lsbt/testing/Selector;
       564: getstatic     #269                // Field sbt/testing/Status.Error:Lsbt/testing/Status;
       567: aload_0
       568: aload         9
       570: invokevirtual #270                // Method org/scalatest/events/SuiteAborted.throwable:()Lscala/Option;
       573: invokespecial #203                // Method getOptionalThrowable:(Lscala/Option;)Lsbt/testing/OptionalThrowable;
       576: aload         9
       578: invokevirtual #271                // Method org/scalatest/events/SuiteAborted.duration:()Lscala/Option;
       581: invokedynamic #276,  0            // InvokeDynamic #4:apply$mcJ$sp:()Lscala/runtime/java8/JFunction0$mcJ$sp;
       586: invokevirtual #168                // Method scala/Option.getOrElse:(Lscala/Function0;)Ljava/lang/Object;
       589: invokestatic  #174                // Method scala/runtime/BoxesRunTime.unboxToLong:(Ljava/lang/Object;)J
       592: invokespecial #177                // Method org/scalatest/tools/Framework$ScalaTestSbtEvent."<init>":(Lorg/scalatest/tools/Framework;Ljava/lang/String;Lsbt/testing/Fingerprint;Lsbt/testing/Selector;Lsbt/testing/Status;Lsbt/testing/OptionalThrowable;J)V
       595: invokeinterface #183,  2          // InterfaceMethod sbt/testing/EventHandler.handle:(Lsbt/testing/Event;)V
       600: getstatic     #189                // Field scala/runtime/BoxedUnit.UNIT:Lscala/runtime/BoxedUnit;
       603: astore_2
       604: goto          641
       607: goto          610
       610: aload_3
       611: instanceof    #278                // class org/scalatest/events/ScopePending
       614: ifeq          631
       617: aload_0
       618: getfield      #116                // Field summaryCounter:Lorg/scalatest/tools/Framework$SummaryCounter;
       621: invokevirtual #281                // Method org/scalatest/tools/Framework$SummaryCounter.incrementScopesPendingCount:()V
       624: getstatic     #189                // Field scala/runtime/BoxedUnit.UNIT:Lscala/runtime/BoxedUnit;
       627: astore_2
       628: goto          641
       631: goto          634
       634: getstatic     #189                // Field scala/runtime/BoxedUnit.UNIT:Lscala/runtime/BoxedUnit;
       637: astore_2
       638: goto          641
       641: return
      StackMapTable: number_of_entries = 17
        frame_type = 253 /* append */
          offset_delta = 107
          locals = [ top, class org/scalatest/events/Event ]
        frame_type = 2 /* same */
        frame_type = 251 /* same_frame_extended */
          offset_delta = 96
        frame_type = 2 /* same */
        frame_type = 251 /* same_frame_extended */
          offset_delta = 94
        frame_type = 2 /* same */
        frame_type = 251 /* same_frame_extended */
          offset_delta = 81
        frame_type = 2 /* same */
        frame_type = 251 /* same_frame_extended */
          offset_delta = 94
        frame_type = 2 /* same */
        frame_type = 20 /* same */
        frame_type = 2 /* same */
        frame_type = 251 /* same_frame_extended */
          offset_delta = 91
        frame_type = 2 /* same */
        frame_type = 20 /* same */
        frame_type = 2 /* same */
        frame_type = 255 /* full_frame */
          offset_delta = 6
          locals = [ class org/scalatest/tools/Framework$SbtReporter, class org/scalatest/events/Event, class scala/runtime/BoxedUnit, class org/scalatest/events/Event ]
          stack = []
      LineNumberTable:
        line 1184: 0
        line 1185: 10
        line 1187: 12
        line 1188: 25
        line 1189: 32
        line 1187: 107
        line 1190: 110
        line 1191: 123
        line 1192: 130
        line 1190: 207
        line 1193: 210
        line 1194: 223
        line 1195: 230
        line 1193: 305
        line 1196: 308
        line 1197: 321
        line 1198: 328
        line 1196: 390
        line 1199: 393
        line 1200: 406
        line 1201: 413
        line 1199: 488
        line 1202: 491
        line 1203: 498
        line 1202: 512
        line 1204: 515
        line 1205: 528
        line 1206: 535
        line 1204: 607
        line 1207: 610
        line 1208: 617
        line 1207: 631
        line 1209: 634
        line 1185: 641
      LocalVariableTable:
        Start  Length  Slot  Name   Signature
            0     642     0  this   Lorg/scalatest/tools/Framework$SbtReporter;
            0     642     1 event   Lorg/scalatest/events/Event;
    MethodParameters:
      Name                           Flags
      event                          final

  public org.scalatest.tools.Framework org$scalatest$tools$Framework$SbtReporter$$$outer();
    descriptor: ()Lorg/scalatest/tools/Framework;
    flags: (0x1001) ACC_PUBLIC, ACC_SYNTHETIC
    Code:
      stack=1, locals=1, args_size=1
         0: aload_0
         1: getfield      #286                // Field $outer:Lorg/scalatest/tools/Framework;
         4: areturn
      LineNumberTable:
        line 1159: 0
      LocalVariableTable:
        Start  Length  Slot  Name   Signature
            0       5     0  this   Lorg/scalatest/tools/Framework$SbtReporter;

  public static final long $anonfun$apply$2();
    descriptor: ()J
    flags: (0x1019) ACC_PUBLIC, ACC_STATIC, ACC_FINAL, ACC_SYNTHETIC
    Code:
      stack=2, locals=0, args_size=0
         0: lconst_0
         1: lreturn
      LineNumberTable:
        line 1189: 0

  public static final long $anonfun$apply$3();
    descriptor: ()J
    flags: (0x1019) ACC_PUBLIC, ACC_STATIC, ACC_FINAL, ACC_SYNTHETIC
    Code:
      stack=2, locals=0, args_size=0
         0: lconst_0
         1: lreturn
      LineNumberTable:
        line 1192: 0

  public static final long $anonfun$apply$4();
    descriptor: ()J
    flags: (0x1019) ACC_PUBLIC, ACC_STATIC, ACC_FINAL, ACC_SYNTHETIC
    Code:
      stack=2, locals=0, args_size=0
         0: lconst_0
         1: lreturn
      LineNumberTable:
        line 1195: 0

  public static final long $anonfun$apply$5();
    descriptor: ()J
    flags: (0x1019) ACC_PUBLIC, ACC_STATIC, ACC_FINAL, ACC_SYNTHETIC
    Code:
      stack=2, locals=0, args_size=0
         0: lconst_0
         1: lreturn
      LineNumberTable:
        line 1201: 0

  public static final long $anonfun$apply$6();
    descriptor: ()J
    flags: (0x1019) ACC_PUBLIC, ACC_STATIC, ACC_FINAL, ACC_SYNTHETIC
    Code:
      stack=2, locals=0, args_size=0
         0: lconst_0
         1: lreturn
      LineNumberTable:
        line 1206: 0

  public org.scalatest.tools.Framework$SbtReporter(org.scalatest.tools.Framework, java.lang.String, java.lang.String, sbt.testing.Fingerprint, sbt.testing.EventHandler, org.scalatest.Reporter, org.scalatest.tools.Framework$SummaryCounter);
    descriptor: (Lorg/scalatest/tools/Framework;Ljava/lang/String;Ljava/lang/String;Lsbt/testing/Fingerprint;Lsbt/testing/EventHandler;Lorg/scalatest/Reporter;Lorg/scalatest/tools/Framework$SummaryCounter;)V
    flags: (0x0001) ACC_PUBLIC
    Code:
      stack=2, locals=8, args_size=8
         0: aload_0
         1: aload_2
         2: putfield      #40                 // Field suiteId:Ljava/lang/String;
         5: aload_0
         6: aload_3
         7: putfield      #127                // Field fullyQualifiedName:Ljava/lang/String;
        10: aload_0
        11: aload         4
        13: putfield      #129                // Field fingerprint:Lsbt/testing/Fingerprint;
        16: aload_0
        17: aload         5
        19: putfield      #121                // Field eventHandler:Lsbt/testing/EventHandler;
        22: aload_0
        23: aload         6
        25: putfield      #110                // Field report:Lorg/scalatest/Reporter;
        28: aload_0
        29: aload         7
        31: putfield      #116                // Field summaryCounter:Lorg/scalatest/tools/Framework$SummaryCounter;
        34: aload_1
        35: ifnonnull     40
        38: aconst_null
        39: athrow
        40: aload_0
        41: aload_1
        42: putfield      #286                // Field $outer:Lorg/scalatest/tools/Framework;
        45: aload_0
        46: invokespecial #288                // Method java/lang/Object."<init>":()V
        49: return
      StackMapTable: number_of_entries = 1
        frame_type = 40 /* same */
      LineNumberTable:
        line 1159: 0
      LocalVariableTable:
        Start  Length  Slot  Name   Signature
            0      50     0  this   Lorg/scalatest/tools/Framework$SbtReporter;
            0      50     1 $outer   Lorg/scalatest/tools/Framework;
            0      50     2 suiteId   Ljava/lang/String;
            0      50     3 fullyQualifiedName   Ljava/lang/String;
            0      50     4 fingerprint   Lsbt/testing/Fingerprint;
            0      50     5 eventHandler   Lsbt/testing/EventHandler;
            0      50     6 report   Lorg/scalatest/Reporter;
            0      50     7 summaryCounter   Lorg/scalatest/tools/Framework$SummaryCounter;
    MethodParameters:
      Name                           Flags
      $outer                         final synthetic
      suiteId                        final
      fullyQualifiedName             final
      fingerprint                    final
      eventHandler                   final
      report                         final
      summaryCounter                 final

  private static java.lang.Object $deserializeLambda$(java.lang.invoke.SerializedLambda);
    descriptor: (Ljava/lang/invoke/SerializedLambda;)Ljava/lang/Object;
    flags: (0x100a) ACC_PRIVATE, ACC_STATIC, ACC_SYNTHETIC
    Code:
      stack=1, locals=1, args_size=1
         0: aload_0
         1: invokedynamic #300,  0            // InvokeDynamic #5:lambdaDeserialize:(Ljava/lang/invoke/SerializedLambda;)Ljava/lang/Object;
         6: areturn
}
InnerClasses:
  public static final #12= #9 of #11;     // Lookup=class java/lang/invoke/MethodHandles$Lookup of class java/lang/invoke/MethodHandles
  private #15= #2 of #14;                 // SbtReporter=class org/scalatest/tools/Framework$SbtReporter of class org/scalatest/tools/Framework
  private #18= #17 of #14;                // ScalaTestSbtEvent=class org/scalatest/tools/Framework$ScalaTestSbtEvent of class org/scalatest/tools/Framework
  public #21= #20 of #14;                 // SummaryCounter=class org/scalatest/tools/Framework$SummaryCounter of class org/scalatest/tools/Framework
SourceFile: "Framework.scala"
BootstrapMethods:
  0: #160 REF_invokeStatic java/lang/invoke/LambdaMetafactory.altMetafactory:(Ljava/lang/invoke/MethodHandles$Lookup;Ljava/lang/String;Ljava/lang/invoke/MethodType;[Ljava/lang/Object;)Ljava/lang/invoke/CallSite;
    Method arguments:
      #148 ()J
      #152 REF_invokeStatic org/scalatest/tools/Framework$SbtReporter.$anonfun$apply$2:()J
      #148 ()J
      #153 1
  1: #160 REF_invokeStatic java/lang/invoke/LambdaMetafactory.altMetafactory:(Ljava/lang/invoke/MethodHandles$Lookup;Ljava/lang/String;Ljava/lang/invoke/MethodType;[Ljava/lang/Object;)Ljava/lang/invoke/CallSite;
    Method arguments:
      #148 ()J
      #208 REF_invokeStatic org/scalatest/tools/Framework$SbtReporter.$anonfun$apply$3:()J
      #148 ()J
      #153 1
  2: #160 REF_invokeStatic java/lang/invoke/LambdaMetafactory.altMetafactory:(Ljava/lang/invoke/MethodHandles$Lookup;Ljava/lang/String;Ljava/lang/invoke/MethodType;[Ljava/lang/Object;)Ljava/lang/invoke/CallSite;
    Method arguments:
      #148 ()J
      #224 REF_invokeStatic org/scalatest/tools/Framework$SbtReporter.$anonfun$apply$4:()J
      #148 ()J
      #153 1
  3: #160 REF_invokeStatic java/lang/invoke/LambdaMetafactory.altMetafactory:(Ljava/lang/invoke/MethodHandles$Lookup;Ljava/lang/String;Ljava/lang/invoke/MethodType;[Ljava/lang/Object;)Ljava/lang/invoke/CallSite;
    Method arguments:
      #148 ()J
      #252 REF_invokeStatic org/scalatest/tools/Framework$SbtReporter.$anonfun$apply$5:()J
      #148 ()J
      #153 1
  4: #160 REF_invokeStatic java/lang/invoke/LambdaMetafactory.altMetafactory:(Ljava/lang/invoke/MethodHandles$Lookup;Ljava/lang/String;Ljava/lang/invoke/MethodType;[Ljava/lang/Object;)Ljava/lang/invoke/CallSite;
    Method arguments:
      #148 ()J
      #275 REF_invokeStatic org/scalatest/tools/Framework$SbtReporter.$anonfun$apply$6:()J
      #148 ()J
      #153 1
  5: #297 REF_invokeStatic scala/runtime/LambdaDeserialize.bootstrap:(Ljava/lang/invoke/MethodHandles$Lookup;Ljava/lang/String;Ljava/lang/invoke/MethodType;[Ljava/lang/invoke/MethodHandle;)Ljava/lang/invoke/CallSite;
    Method arguments:
      #152 REF_invokeStatic org/scalatest/tools/Framework$SbtReporter.$anonfun$apply$2:()J
      #208 REF_invokeStatic org/scalatest/tools/Framework$SbtReporter.$anonfun$apply$3:()J
      #224 REF_invokeStatic org/scalatest/tools/Framework$SbtReporter.$anonfun$apply$4:()J
      #252 REF_invokeStatic org/scalatest/tools/Framework$SbtReporter.$anonfun$apply$5:()J
      #275 REF_invokeStatic org/scalatest/tools/Framework$SbtReporter.$anonfun$apply$6:()J
  ScalaInlineInfo: length = 0x3B (unknown attribute)
   01 00 00 0B 00 95 00 93 01 00 CD 00 93 01 00 DD
   00 93 01 00 F9 00 93 01 01 10 00 93 01 00 2F 01
   1F 00 00 6A 00 6B 00 00 48 00 49 01 00 3E 00 3F
   01 00 23 00 24 01 00 7A 00 7B 00
  Scala: length = 0x0 (unknown attribute)

