Classfile /Users/mw/Projects/slang-braindump/.jar/jar8/assemble/slang-braindump/assemble/content/org/scalatest/tools/Framework$ScalaTestRunner.class
  Last modified May 29, 2022; size 23224 bytes
  SHA-256 checksum 5049b5586d04cbbaf7e60fc5d838c9cac2e0d27b25a96b17d05560d97f385471
  Compiled from "Framework.scala"
public class org.scalatest.tools.Framework$ScalaTestRunner implements sbt.testing.Runner
  minor version: 0
  major version: 52
  flags: (0x0021) ACC_PUBLIC, ACC_SUPER
  this_class: #2                          // org/scalatest/tools/Framework$ScalaTestRunner
  super_class: #4                         // java/lang/Object
  interfaces: 1, fields: 35, methods: 51, attributes: 5
Constant pool:
    #1 = Utf8               org/scalatest/tools/Framework$ScalaTestRunner
    #2 = Class              #1            // org/scalatest/tools/Framework$ScalaTestRunner
    #3 = Utf8               java/lang/Object
    #4 = Class              #3            // java/lang/Object
    #5 = Utf8               sbt/testing/Runner
    #6 = Class              #5            // sbt/testing/Runner
    #7 = Utf8               Framework.scala
    #8 = Utf8               java/lang/invoke/MethodHandles$Lookup
    #9 = Class              #8            // java/lang/invoke/MethodHandles$Lookup
   #10 = Utf8               java/lang/invoke/MethodHandles
   #11 = Class              #10           // java/lang/invoke/MethodHandles
   #12 = Utf8               Lookup
   #13 = Utf8               org/scalatest/tools/Framework
   #14 = Class              #13           // org/scalatest/tools/Framework
   #15 = Utf8               ScalaTestRunner
   #16 = Utf8               org/scalatest/tools/Framework$ScalaTestRunner$$anon$3
   #17 = Class              #16           // org/scalatest/tools/Framework$ScalaTestRunner$$anon$3
   #18 = Utf8               org/scalatest/tools/Framework$ScalaTestRunner$Skeleton$1
   #19 = Class              #18           // org/scalatest/tools/Framework$ScalaTestRunner$Skeleton$1
   #20 = Utf8               Skeleton$1
   #21 = Utf8               org/scalatest/tools/Framework$ScalaTestRunner$SkeletonObjectInputStream$1
   #22 = Class              #21           // org/scalatest/tools/Framework$ScalaTestRunner$SkeletonObjectInputStream$1
   #23 = Utf8               SkeletonObjectInputStream$1
   #24 = Utf8               org/scalatest/tools/Framework$ScalaTestTask
   #25 = Class              #24           // org/scalatest/tools/Framework$ScalaTestTask
   #26 = Utf8               ScalaTestTask
   #27 = Utf8               org/scalatest/tools/Framework$SummaryCounter
   #28 = Class              #27           // org/scalatest/tools/Framework$SummaryCounter
   #29 = Utf8               SummaryCounter
   #30 = Utf8               scala/collection/ArrayOps$WithFilter
   #31 = Class              #30           // scala/collection/ArrayOps$WithFilter
   #32 = Utf8               scala/collection/ArrayOps
   #33 = Class              #32           // scala/collection/ArrayOps
   #34 = Utf8               WithFilter
   #35 = Utf8               scala/collection/JavaConverters$AsScala
   #36 = Class              #35           // scala/collection/JavaConverters$AsScala
   #37 = Utf8               scala/collection/JavaConverters
   #38 = Class              #37           // scala/collection/JavaConverters
   #39 = Utf8               AsScala
   #40 = Utf8               runArgs
   #41 = Utf8               [Ljava/lang/String;
   #42 = Utf8               loader
   #43 = Utf8               Ljava/lang/ClassLoader;
   #44 = Utf8               tagsToInclude
   #45 = Utf8               Lscala/collection/immutable/Set;
   #46 = Utf8               Lscala/collection/immutable/Set<Ljava/lang/String;>;
   #47 = Utf8               tagsToExclude
   #48 = Utf8               membersOnly
   #49 = Utf8               Lscala/collection/immutable/List;
   #50 = Utf8               Lscala/collection/immutable/List<Ljava/lang/String;>;
   #51 = Utf8               wildcard
   #52 = Utf8               autoSelectors
   #53 = Utf8               Lscala/collection/immutable/List<Lsbt/testing/Selector;>;
   #54 = Utf8               configMap
   #55 = Utf8               Lorg/scalatest/ConfigMap;
   #56 = Utf8               repConfig
   #57 = Utf8               Lorg/scalatest/tools/ReporterConfigurations;
   #58 = Utf8               useSbtLogInfoReporter
   #59 = Utf8               Z
   #60 = Utf8               presentAllDurations
   #61 = Utf8               presentInColor
   #62 = Utf8               presentShortStackTraces
   #63 = Utf8               presentFullStackTraces
   #64 = Utf8               presentUnformatted
   #65 = Utf8               presentReminder
   #66 = Utf8               presentReminderWithShortStackTraces
   #67 = Utf8               presentReminderWithFullStackTraces
   #68 = Utf8               presentReminderWithoutCanceledTests
   #69 = Utf8               presentFilePathname
   #70 = Utf8               presentJson
   #71 = Utf8               configSet
   #72 = Utf8               Lscala/collection/immutable/Set<Lorg/scalatest/tools/ReporterConfigParam;>;
   #73 = Utf8               isDone
   #74 = Utf8               Ljava/util/concurrent/atomic/AtomicBoolean;
   #75 = Utf8               serverThread
   #76 = Utf8               Ljava/util/concurrent/atomic/AtomicReference;
   #77 = Utf8               Ljava/util/concurrent/atomic/AtomicReference<Lscala/Option<Ljava/lang/Thread;>;>;
   #78 = Utf8               statusList
   #79 = Utf8               Ljava/util/concurrent/LinkedBlockingQueue;
   #80 = Utf8               Ljava/util/concurrent/LinkedBlockingQueue<Lorg/scalatest/Status;>;
   #81 = Utf8               tracker
   #82 = Utf8               Lorg/scalatest/Tracker;
   #83 = Utf8               summaryCounter
   #84 = Utf8               Lorg/scalatest/tools/Framework$SummaryCounter;
   #85 = Utf8               runStartTime
   #86 = Utf8               J
   #87 = Utf8               dispatchReporter
   #88 = Utf8               Lorg/scalatest/DispatchReporter;
   #89 = Utf8               suiteSortingReporter
   #90 = Utf8               Lorg/scalatest/tools/SuiteSortingReporter;
   #91 = Utf8               org$scalatest$tools$Framework$ScalaTestRunner$$atomicThreadCounter
   #92 = Utf8               Ljava/util/concurrent/atomic/AtomicInteger;
   #93 = Utf8               threadFactory
   #94 = Utf8               Ljava/util/concurrent/ThreadFactory;
   #95 = Utf8               poolSize
   #96 = Utf8               I
   #97 = Utf8               execSvc
   #98 = Utf8               Ljava/util/concurrent/ExecutorService;
   #99 = Utf8               $outer
  #100 = Utf8               Lorg/scalatest/tools/Framework;
  #101 = Utf8               ()Lorg/scalatest/tools/ReporterConfigurations;
  #102 = NameAndType        #56:#57       // repConfig:Lorg/scalatest/tools/ReporterConfigurations;
  #103 = Fieldref           #2.#102       // org/scalatest/tools/Framework$ScalaTestRunner.repConfig:Lorg/scalatest/tools/ReporterConfigurations;
  #104 = Utf8               this
  #105 = Utf8               Lorg/scalatest/tools/Framework$ScalaTestRunner;
  #106 = Utf8               ()Z
  #107 = NameAndType        #58:#59       // useSbtLogInfoReporter:Z
  #108 = Fieldref           #2.#107       // org/scalatest/tools/Framework$ScalaTestRunner.useSbtLogInfoReporter:Z
  #109 = NameAndType        #60:#59       // presentAllDurations:Z
  #110 = Fieldref           #2.#109       // org/scalatest/tools/Framework$ScalaTestRunner.presentAllDurations:Z
  #111 = NameAndType        #61:#59       // presentInColor:Z
  #112 = Fieldref           #2.#111       // org/scalatest/tools/Framework$ScalaTestRunner.presentInColor:Z
  #113 = NameAndType        #62:#59       // presentShortStackTraces:Z
  #114 = Fieldref           #2.#113       // org/scalatest/tools/Framework$ScalaTestRunner.presentShortStackTraces:Z
  #115 = NameAndType        #63:#59       // presentFullStackTraces:Z
  #116 = Fieldref           #2.#115       // org/scalatest/tools/Framework$ScalaTestRunner.presentFullStackTraces:Z
  #117 = NameAndType        #64:#59       // presentUnformatted:Z
  #118 = Fieldref           #2.#117       // org/scalatest/tools/Framework$ScalaTestRunner.presentUnformatted:Z
  #119 = NameAndType        #65:#59       // presentReminder:Z
  #120 = Fieldref           #2.#119       // org/scalatest/tools/Framework$ScalaTestRunner.presentReminder:Z
  #121 = NameAndType        #66:#59       // presentReminderWithShortStackTraces:Z
  #122 = Fieldref           #2.#121       // org/scalatest/tools/Framework$ScalaTestRunner.presentReminderWithShortStackTraces:Z
  #123 = NameAndType        #67:#59       // presentReminderWithFullStackTraces:Z
  #124 = Fieldref           #2.#123       // org/scalatest/tools/Framework$ScalaTestRunner.presentReminderWithFullStackTraces:Z
  #125 = NameAndType        #68:#59       // presentReminderWithoutCanceledTests:Z
  #126 = Fieldref           #2.#125       // org/scalatest/tools/Framework$ScalaTestRunner.presentReminderWithoutCanceledTests:Z
  #127 = NameAndType        #69:#59       // presentFilePathname:Z
  #128 = Fieldref           #2.#127       // org/scalatest/tools/Framework$ScalaTestRunner.presentFilePathname:Z
  #129 = NameAndType        #70:#59       // presentJson:Z
  #130 = Fieldref           #2.#129       // org/scalatest/tools/Framework$ScalaTestRunner.presentJson:Z
  #131 = Utf8               ()Lscala/collection/immutable/Set;
  #132 = Utf8               ()Lscala/collection/immutable/Set<Lorg/scalatest/tools/ReporterConfigParam;>;
  #133 = NameAndType        #71:#45       // configSet:Lscala/collection/immutable/Set;
  #134 = Fieldref           #2.#133       // org/scalatest/tools/Framework$ScalaTestRunner.configSet:Lscala/collection/immutable/Set;
  #135 = Utf8               ()Ljava/util/concurrent/atomic/AtomicBoolean;
  #136 = NameAndType        #73:#74       // isDone:Ljava/util/concurrent/atomic/AtomicBoolean;
  #137 = Fieldref           #2.#136       // org/scalatest/tools/Framework$ScalaTestRunner.isDone:Ljava/util/concurrent/atomic/AtomicBoolean;
  #138 = Utf8               ()Ljava/util/concurrent/atomic/AtomicReference;
  #139 = Utf8               ()Ljava/util/concurrent/atomic/AtomicReference<Lscala/Option<Ljava/lang/Thread;>;>;
  #140 = NameAndType        #75:#76       // serverThread:Ljava/util/concurrent/atomic/AtomicReference;
  #141 = Fieldref           #2.#140       // org/scalatest/tools/Framework$ScalaTestRunner.serverThread:Ljava/util/concurrent/atomic/AtomicReference;
  #142 = Utf8               ()Ljava/util/concurrent/LinkedBlockingQueue;
  #143 = Utf8               ()Ljava/util/concurrent/LinkedBlockingQueue<Lorg/scalatest/Status;>;
  #144 = NameAndType        #78:#79       // statusList:Ljava/util/concurrent/LinkedBlockingQueue;
  #145 = Fieldref           #2.#144       // org/scalatest/tools/Framework$ScalaTestRunner.statusList:Ljava/util/concurrent/LinkedBlockingQueue;
  #146 = Utf8               ()Lorg/scalatest/Tracker;
  #147 = NameAndType        #81:#82       // tracker:Lorg/scalatest/Tracker;
  #148 = Fieldref           #2.#147       // org/scalatest/tools/Framework$ScalaTestRunner.tracker:Lorg/scalatest/Tracker;
  #149 = Utf8               ()Lorg/scalatest/tools/Framework$SummaryCounter;
  #150 = NameAndType        #83:#84       // summaryCounter:Lorg/scalatest/tools/Framework$SummaryCounter;
  #151 = Fieldref           #2.#150       // org/scalatest/tools/Framework$ScalaTestRunner.summaryCounter:Lorg/scalatest/tools/Framework$SummaryCounter;
  #152 = Utf8               ()J
  #153 = NameAndType        #85:#86       // runStartTime:J
  #154 = Fieldref           #2.#153       // org/scalatest/tools/Framework$ScalaTestRunner.runStartTime:J
  #155 = Utf8               ()Lorg/scalatest/DispatchReporter;
  #156 = NameAndType        #87:#88       // dispatchReporter:Lorg/scalatest/DispatchReporter;
  #157 = Fieldref           #2.#156       // org/scalatest/tools/Framework$ScalaTestRunner.dispatchReporter:Lorg/scalatest/DispatchReporter;
  #158 = Utf8               ()Lorg/scalatest/tools/SuiteSortingReporter;
  #159 = NameAndType        #89:#90       // suiteSortingReporter:Lorg/scalatest/tools/SuiteSortingReporter;
  #160 = Fieldref           #2.#159       // org/scalatest/tools/Framework$ScalaTestRunner.suiteSortingReporter:Lorg/scalatest/tools/SuiteSortingReporter;
  #161 = Utf8               ()Ljava/util/concurrent/atomic/AtomicInteger;
  #162 = NameAndType        #91:#92       // org$scalatest$tools$Framework$ScalaTestRunner$$atomicThreadCounter:Ljava/util/concurrent/atomic/AtomicInteger;
  #163 = Fieldref           #2.#162       // org/scalatest/tools/Framework$ScalaTestRunner.org$scalatest$tools$Framework$ScalaTestRunner$$atomicThreadCounter:Ljava/util/concurrent/atomic/AtomicInteger;
  #164 = Utf8               ()Ljava/util/concurrent/ThreadFactory;
  #165 = NameAndType        #93:#94       // threadFactory:Ljava/util/concurrent/ThreadFactory;
  #166 = Fieldref           #2.#165       // org/scalatest/tools/Framework$ScalaTestRunner.threadFactory:Ljava/util/concurrent/ThreadFactory;
  #167 = Utf8               ()I
  #168 = NameAndType        #95:#96       // poolSize:I
  #169 = Fieldref           #2.#168       // org/scalatest/tools/Framework$ScalaTestRunner.poolSize:I
  #170 = Utf8               ()Ljava/util/concurrent/ExecutorService;
  #171 = NameAndType        #97:#98       // execSvc:Ljava/util/concurrent/ExecutorService;
  #172 = Fieldref           #2.#171       // org/scalatest/tools/Framework$ScalaTestRunner.execSvc:Ljava/util/concurrent/ExecutorService;
  #173 = Utf8               createTask
  #174 = Utf8               (Lsbt/testing/TaskDef;)Lorg/scalatest/tools/Framework$ScalaTestTask;
  #175 = Utf8               td
  #176 = Utf8               org$scalatest$tools$Framework$ScalaTestRunner$$$outer
  #177 = Utf8               ()Lorg/scalatest/tools/Framework;
  #178 = NameAndType        #176:#177     // org$scalatest$tools$Framework$ScalaTestRunner$$$outer:()Lorg/scalatest/tools/Framework;
  #179 = Methodref          #2.#178       // org/scalatest/tools/Framework$ScalaTestRunner.org$scalatest$tools$Framework$ScalaTestRunner$$$outer:()Lorg/scalatest/tools/Framework;
  #180 = NameAndType        #42:#43       // loader:Ljava/lang/ClassLoader;
  #181 = Fieldref           #2.#180       // org/scalatest/tools/Framework$ScalaTestRunner.loader:Ljava/lang/ClassLoader;
  #182 = NameAndType        #89:#158      // suiteSortingReporter:()Lorg/scalatest/tools/SuiteSortingReporter;
  #183 = Methodref          #2.#182       // org/scalatest/tools/Framework$ScalaTestRunner.suiteSortingReporter:()Lorg/scalatest/tools/SuiteSortingReporter;
  #184 = NameAndType        #81:#146      // tracker:()Lorg/scalatest/Tracker;
  #185 = Methodref          #2.#184       // org/scalatest/tools/Framework$ScalaTestRunner.tracker:()Lorg/scalatest/Tracker;
  #186 = NameAndType        #44:#45       // tagsToInclude:Lscala/collection/immutable/Set;
  #187 = Fieldref           #2.#186       // org/scalatest/tools/Framework$ScalaTestRunner.tagsToInclude:Lscala/collection/immutable/Set;
  #188 = NameAndType        #47:#45       // tagsToExclude:Lscala/collection/immutable/Set;
  #189 = Fieldref           #2.#188       // org/scalatest/tools/Framework$ScalaTestRunner.tagsToExclude:Lscala/collection/immutable/Set;
  #190 = Utf8               scala/collection/ArrayOps$
  #191 = Class              #190          // scala/collection/ArrayOps$
  #192 = Utf8               MODULE$
  #193 = Utf8               Lscala/collection/ArrayOps$;
  #194 = NameAndType        #192:#193     // MODULE$:Lscala/collection/ArrayOps$;
  #195 = Fieldref           #191.#194     // scala/collection/ArrayOps$.MODULE$:Lscala/collection/ArrayOps$;
  #196 = Utf8               scala/Predef$
  #197 = Class              #196          // scala/Predef$
  #198 = Utf8               Lscala/Predef$;
  #199 = NameAndType        #192:#198     // MODULE$:Lscala/Predef$;
  #200 = Fieldref           #197.#199     // scala/Predef$.MODULE$:Lscala/Predef$;
  #201 = Utf8               sbt/testing/TaskDef
  #202 = Class              #201          // sbt/testing/TaskDef
  #203 = Utf8               selectors
  #204 = Utf8               ()[Lsbt/testing/Selector;
  #205 = NameAndType        #203:#204     // selectors:()[Lsbt/testing/Selector;
  #206 = Methodref          #202.#205     // sbt/testing/TaskDef.selectors:()[Lsbt/testing/Selector;
  #207 = Utf8               [Ljava/lang/Object;
  #208 = Class              #207          // "[Ljava/lang/Object;"
  #209 = Utf8               refArrayOps
  #210 = Utf8               ([Ljava/lang/Object;)Ljava/lang/Object;
  #211 = NameAndType        #209:#210     // refArrayOps:([Ljava/lang/Object;)Ljava/lang/Object;
  #212 = Methodref          #197.#211     // scala/Predef$.refArrayOps:([Ljava/lang/Object;)Ljava/lang/Object;
  #213 = NameAndType        #52:#49       // autoSelectors:Lscala/collection/immutable/List;
  #214 = Fieldref           #2.#213       // org/scalatest/tools/Framework$ScalaTestRunner.autoSelectors:Lscala/collection/immutable/List;
  #215 = Utf8               scala/reflect/ClassTag$
  #216 = Class              #215          // scala/reflect/ClassTag$
  #217 = Utf8               Lscala/reflect/ClassTag$;
  #218 = NameAndType        #192:#217     // MODULE$:Lscala/reflect/ClassTag$;
  #219 = Fieldref           #216.#218     // scala/reflect/ClassTag$.MODULE$:Lscala/reflect/ClassTag$;
  #220 = Utf8               sbt/testing/Selector
  #221 = Class              #220          // sbt/testing/Selector
  #222 = Utf8               apply
  #223 = Utf8               (Ljava/lang/Class;)Lscala/reflect/ClassTag;
  #224 = NameAndType        #222:#223     // apply:(Ljava/lang/Class;)Lscala/reflect/ClassTag;
  #225 = Methodref          #216.#224     // scala/reflect/ClassTag$.apply:(Ljava/lang/Class;)Lscala/reflect/ClassTag;
  #226 = Utf8               $plus$plus$extension
  #227 = Utf8               (Ljava/lang/Object;Lscala/collection/IterableOnce;Lscala/reflect/ClassTag;)Ljava/lang/Object;
  #228 = NameAndType        #226:#227     // $plus$plus$extension:(Ljava/lang/Object;Lscala/collection/IterableOnce;Lscala/reflect/ClassTag;)Ljava/lang/Object;
  #229 = Methodref          #191.#228     // scala/collection/ArrayOps$.$plus$plus$extension:(Ljava/lang/Object;Lscala/collection/IterableOnce;Lscala/reflect/ClassTag;)Ljava/lang/Object;
  #230 = Utf8               [Lsbt/testing/Selector;
  #231 = Class              #230          // "[Lsbt/testing/Selector;"
  #232 = Utf8               explicitlySpecified
  #233 = NameAndType        #232:#106     // explicitlySpecified:()Z
  #234 = Methodref          #202.#233     // sbt/testing/TaskDef.explicitlySpecified:()Z
  #235 = NameAndType        #54:#55       // configMap:Lorg/scalatest/ConfigMap;
  #236 = Fieldref           #2.#235       // org/scalatest/tools/Framework$ScalaTestRunner.configMap:Lorg/scalatest/ConfigMap;
  #237 = NameAndType        #83:#149      // summaryCounter:()Lorg/scalatest/tools/Framework$SummaryCounter;
  #238 = Methodref          #2.#237       // org/scalatest/tools/Framework$ScalaTestRunner.summaryCounter:()Lorg/scalatest/tools/Framework$SummaryCounter;
  #239 = NameAndType        #78:#142      // statusList:()Ljava/util/concurrent/LinkedBlockingQueue;
  #240 = Methodref          #2.#239       // org/scalatest/tools/Framework$ScalaTestRunner.statusList:()Ljava/util/concurrent/LinkedBlockingQueue;
  #241 = NameAndType        #58:#106      // useSbtLogInfoReporter:()Z
  #242 = Methodref          #2.#241       // org/scalatest/tools/Framework$ScalaTestRunner.useSbtLogInfoReporter:()Z
  #243 = NameAndType        #60:#106      // presentAllDurations:()Z
  #244 = Methodref          #2.#243       // org/scalatest/tools/Framework$ScalaTestRunner.presentAllDurations:()Z
  #245 = NameAndType        #61:#106      // presentInColor:()Z
  #246 = Methodref          #2.#245       // org/scalatest/tools/Framework$ScalaTestRunner.presentInColor:()Z
  #247 = NameAndType        #62:#106      // presentShortStackTraces:()Z
  #248 = Methodref          #2.#247       // org/scalatest/tools/Framework$ScalaTestRunner.presentShortStackTraces:()Z
  #249 = NameAndType        #63:#106      // presentFullStackTraces:()Z
  #250 = Methodref          #2.#249       // org/scalatest/tools/Framework$ScalaTestRunner.presentFullStackTraces:()Z
  #251 = NameAndType        #64:#106      // presentUnformatted:()Z
  #252 = Methodref          #2.#251       // org/scalatest/tools/Framework$ScalaTestRunner.presentUnformatted:()Z
  #253 = NameAndType        #65:#106      // presentReminder:()Z
  #254 = Methodref          #2.#253       // org/scalatest/tools/Framework$ScalaTestRunner.presentReminder:()Z
  #255 = NameAndType        #66:#106      // presentReminderWithShortStackTraces:()Z
  #256 = Methodref          #2.#255       // org/scalatest/tools/Framework$ScalaTestRunner.presentReminderWithShortStackTraces:()Z
  #257 = NameAndType        #67:#106      // presentReminderWithFullStackTraces:()Z
  #258 = Methodref          #2.#257       // org/scalatest/tools/Framework$ScalaTestRunner.presentReminderWithFullStackTraces:()Z
  #259 = NameAndType        #68:#106      // presentReminderWithoutCanceledTests:()Z
  #260 = Methodref          #2.#259       // org/scalatest/tools/Framework$ScalaTestRunner.presentReminderWithoutCanceledTests:()Z
  #261 = NameAndType        #69:#106      // presentFilePathname:()Z
  #262 = Methodref          #2.#261       // org/scalatest/tools/Framework$ScalaTestRunner.presentFilePathname:()Z
  #263 = NameAndType        #70:#106      // presentJson:()Z
  #264 = Methodref          #2.#263       // org/scalatest/tools/Framework$ScalaTestRunner.presentJson:()Z
  #265 = NameAndType        #71:#131      // configSet:()Lscala/collection/immutable/Set;
  #266 = Methodref          #2.#265       // org/scalatest/tools/Framework$ScalaTestRunner.configSet:()Lscala/collection/immutable/Set;
  #267 = NameAndType        #97:#170      // execSvc:()Ljava/util/concurrent/ExecutorService;
  #268 = Methodref          #2.#267       // org/scalatest/tools/Framework$ScalaTestRunner.execSvc:()Ljava/util/concurrent/ExecutorService;
  #269 = Utf8               <init>
  #270 = Utf8               (Lorg/scalatest/tools/Framework;Lsbt/testing/TaskDef;Ljava/lang/ClassLoader;Lorg/scalatest/tools/SuiteSortingReporter;Lorg/scalatest/Tracker;Lscala/collection/immutable/Set;Lscala/collection/immutable/Set;[Lsbt/testing/Selector;ZLorg/scalatest/ConfigMap;Lorg/scalatest/tools/Framework$SummaryCounter;Ljava/util/concurrent/LinkedBlockingQueue;ZZZZZZZZZZZZLscala/collection/immutable/Set;Ljava/util/concurrent/ExecutorService;)V
  #271 = NameAndType        #269:#270     // "<init>":(Lorg/scalatest/tools/Framework;Lsbt/testing/TaskDef;Ljava/lang/ClassLoader;Lorg/scalatest/tools/SuiteSortingReporter;Lorg/scalatest/Tracker;Lscala/collection/immutable/Set;Lscala/collection/immutable/Set;[Lsbt/testing/Selector;ZLorg/scalatest/ConfigMap;Lorg/scalatest/tools/Framework$SummaryCounter;Ljava/util/concurrent/LinkedBlockingQueue;ZZZZZZZZZZZZLscala/collection/immutable/Set;Ljava/util/concurrent/ExecutorService;)V
  #272 = Methodref          #25.#271      // org/scalatest/tools/Framework$ScalaTestTask."<init>":(Lorg/scalatest/tools/Framework;Lsbt/testing/TaskDef;Ljava/lang/ClassLoader;Lorg/scalatest/tools/SuiteSortingReporter;Lorg/scalatest/Tracker;Lscala/collection/immutable/Set;Lscala/collection/immutable/Set;[Lsbt/testing/Selector;ZLorg/scalatest/ConfigMap;Lorg/scalatest/tools/Framework$SummaryCounter;Ljava/util/concurrent/LinkedBlockingQueue;ZZZZZZZZZZZZLscala/collection/immutable/Set;Ljava/util/concurrent/ExecutorService;)V
  #273 = Utf8               Lsbt/testing/TaskDef;
  #274 = Utf8               filterWildcard
  #275 = Utf8               (Lscala/collection/immutable/List;[Lsbt/testing/TaskDef;)[Lsbt/testing/TaskDef;
  #276 = Utf8               (Lscala/collection/immutable/List<Ljava/lang/String;>;[Lsbt/testing/TaskDef;)[Lsbt/testing/TaskDef;
  #277 = Utf8               paths
  #278 = Utf8               taskDefs
  #279 = Utf8               (Ljava/lang/Object;)Ljava/lang/Object;
  #280 = MethodType         #279          //  (Ljava/lang/Object;)Ljava/lang/Object;
  #281 = Utf8               $anonfun$filterWildcard$1$adapted
  #282 = Utf8               (Lscala/collection/immutable/List;Lsbt/testing/TaskDef;)Ljava/lang/Object;
  #283 = NameAndType        #281:#282     // $anonfun$filterWildcard$1$adapted:(Lscala/collection/immutable/List;Lsbt/testing/TaskDef;)Ljava/lang/Object;
  #284 = Methodref          #2.#283       // org/scalatest/tools/Framework$ScalaTestRunner.$anonfun$filterWildcard$1$adapted:(Lscala/collection/immutable/List;Lsbt/testing/TaskDef;)Ljava/lang/Object;
  #285 = MethodHandle       6:#284        // REF_invokeStatic org/scalatest/tools/Framework$ScalaTestRunner.$anonfun$filterWildcard$1$adapted:(Lscala/collection/immutable/List;Lsbt/testing/TaskDef;)Ljava/lang/Object;
  #286 = Utf8               (Lsbt/testing/TaskDef;)Ljava/lang/Object;
  #287 = MethodType         #286          //  (Lsbt/testing/TaskDef;)Ljava/lang/Object;
  #288 = Integer            5
  #289 = Integer            1
  #290 = Utf8               java/lang/invoke/LambdaMetafactory
  #291 = Class              #290          // java/lang/invoke/LambdaMetafactory
  #292 = Utf8               altMetafactory
  #293 = Utf8               (Ljava/lang/invoke/MethodHandles$Lookup;Ljava/lang/String;Ljava/lang/invoke/MethodType;[Ljava/lang/Object;)Ljava/lang/invoke/CallSite;
  #294 = NameAndType        #292:#293     // altMetafactory:(Ljava/lang/invoke/MethodHandles$Lookup;Ljava/lang/String;Ljava/lang/invoke/MethodType;[Ljava/lang/Object;)Ljava/lang/invoke/CallSite;
  #295 = Methodref          #291.#294     // java/lang/invoke/LambdaMetafactory.altMetafactory:(Ljava/lang/invoke/MethodHandles$Lookup;Ljava/lang/String;Ljava/lang/invoke/MethodType;[Ljava/lang/Object;)Ljava/lang/invoke/CallSite;
  #296 = MethodHandle       6:#295        // REF_invokeStatic java/lang/invoke/LambdaMetafactory.altMetafactory:(Ljava/lang/invoke/MethodHandles$Lookup;Ljava/lang/String;Ljava/lang/invoke/MethodType;[Ljava/lang/Object;)Ljava/lang/invoke/CallSite;
  #297 = Utf8               (Lscala/collection/immutable/List;)Lscala/Function1;
  #298 = NameAndType        #222:#297     // apply:(Lscala/collection/immutable/List;)Lscala/Function1;
  #299 = InvokeDynamic      #0:#298       // #0:apply:(Lscala/collection/immutable/List;)Lscala/Function1;
  #300 = Utf8               filter$extension
  #301 = Utf8               (Ljava/lang/Object;Lscala/Function1;)Ljava/lang/Object;
  #302 = NameAndType        #300:#301     // filter$extension:(Ljava/lang/Object;Lscala/Function1;)Ljava/lang/Object;
  #303 = Methodref          #191.#302     // scala/collection/ArrayOps$.filter$extension:(Ljava/lang/Object;Lscala/Function1;)Ljava/lang/Object;
  #304 = Utf8               [Lsbt/testing/TaskDef;
  #305 = Class              #304          // "[Lsbt/testing/TaskDef;"
  #306 = Utf8               filterMembersOnly
  #307 = Utf8               $anonfun$filterMembersOnly$1$adapted
  #308 = NameAndType        #307:#282     // $anonfun$filterMembersOnly$1$adapted:(Lscala/collection/immutable/List;Lsbt/testing/TaskDef;)Ljava/lang/Object;
  #309 = Methodref          #2.#308       // org/scalatest/tools/Framework$ScalaTestRunner.$anonfun$filterMembersOnly$1$adapted:(Lscala/collection/immutable/List;Lsbt/testing/TaskDef;)Ljava/lang/Object;
  #310 = MethodHandle       6:#309        // REF_invokeStatic org/scalatest/tools/Framework$ScalaTestRunner.$anonfun$filterMembersOnly$1$adapted:(Lscala/collection/immutable/List;Lsbt/testing/TaskDef;)Ljava/lang/Object;
  #311 = InvokeDynamic      #1:#298       // #1:apply:(Lscala/collection/immutable/List;)Lscala/Function1;
  #312 = Utf8               tasks
  #313 = Utf8               ([Lsbt/testing/TaskDef;)[Lsbt/testing/Task;
  #314 = NameAndType        #51:#49       // wildcard:Lscala/collection/immutable/List;
  #315 = Fieldref           #2.#314       // org/scalatest/tools/Framework$ScalaTestRunner.wildcard:Lscala/collection/immutable/List;
  #316 = Utf8               scala/collection/immutable/List
  #317 = Class              #316          // scala/collection/immutable/List
  #318 = Utf8               isEmpty
  #319 = NameAndType        #318:#106     // isEmpty:()Z
  #320 = Methodref          #317.#319     // scala/collection/immutable/List.isEmpty:()Z
  #321 = NameAndType        #48:#49       // membersOnly:Lscala/collection/immutable/List;
  #322 = Fieldref           #2.#321       // org/scalatest/tools/Framework$ScalaTestRunner.membersOnly:Lscala/collection/immutable/List;
  #323 = NameAndType        #274:#275     // filterWildcard:(Lscala/collection/immutable/List;[Lsbt/testing/TaskDef;)[Lsbt/testing/TaskDef;
  #324 = Methodref          #2.#323       // org/scalatest/tools/Framework$ScalaTestRunner.filterWildcard:(Lscala/collection/immutable/List;[Lsbt/testing/TaskDef;)[Lsbt/testing/TaskDef;
  #325 = NameAndType        #306:#275     // filterMembersOnly:(Lscala/collection/immutable/List;[Lsbt/testing/TaskDef;)[Lsbt/testing/TaskDef;
  #326 = Methodref          #2.#325       // org/scalatest/tools/Framework$ScalaTestRunner.filterMembersOnly:(Lscala/collection/immutable/List;[Lsbt/testing/TaskDef;)[Lsbt/testing/TaskDef;
  #327 = Utf8               (Ljava/lang/Object;Ljava/lang/Object;Lscala/reflect/ClassTag;)Ljava/lang/Object;
  #328 = NameAndType        #226:#327     // $plus$plus$extension:(Ljava/lang/Object;Ljava/lang/Object;Lscala/reflect/ClassTag;)Ljava/lang/Object;
  #329 = Methodref          #191.#328     // scala/collection/ArrayOps$.$plus$plus$extension:(Ljava/lang/Object;Ljava/lang/Object;Lscala/reflect/ClassTag;)Ljava/lang/Object;
  #330 = Utf8               distinct$extension
  #331 = NameAndType        #330:#279     // distinct$extension:(Ljava/lang/Object;)Ljava/lang/Object;
  #332 = Methodref          #191.#331     // scala/collection/ArrayOps$.distinct$extension:(Ljava/lang/Object;)Ljava/lang/Object;
  #333 = Utf8               $anonfun$tasks$1
  #334 = Utf8               (Lorg/scalatest/tools/Framework$ScalaTestRunner;Lsbt/testing/TaskDef;)Lscala/Tuple2;
  #335 = NameAndType        #333:#334     // $anonfun$tasks$1:(Lorg/scalatest/tools/Framework$ScalaTestRunner;Lsbt/testing/TaskDef;)Lscala/Tuple2;
  #336 = Methodref          #2.#335       // org/scalatest/tools/Framework$ScalaTestRunner.$anonfun$tasks$1:(Lorg/scalatest/tools/Framework$ScalaTestRunner;Lsbt/testing/TaskDef;)Lscala/Tuple2;
  #337 = MethodHandle       6:#336        // REF_invokeStatic org/scalatest/tools/Framework$ScalaTestRunner.$anonfun$tasks$1:(Lorg/scalatest/tools/Framework$ScalaTestRunner;Lsbt/testing/TaskDef;)Lscala/Tuple2;
  #338 = Utf8               (Lsbt/testing/TaskDef;)Lscala/Tuple2;
  #339 = MethodType         #338          //  (Lsbt/testing/TaskDef;)Lscala/Tuple2;
  #340 = Utf8               (Lorg/scalatest/tools/Framework$ScalaTestRunner;)Lscala/Function1;
  #341 = NameAndType        #222:#340     // apply:(Lorg/scalatest/tools/Framework$ScalaTestRunner;)Lscala/Function1;
  #342 = InvokeDynamic      #2:#341       // #2:apply:(Lorg/scalatest/tools/Framework$ScalaTestRunner;)Lscala/Function1;
  #343 = Utf8               scala/Tuple2
  #344 = Class              #343          // scala/Tuple2
  #345 = Utf8               map$extension
  #346 = Utf8               (Ljava/lang/Object;Lscala/Function1;Lscala/reflect/ClassTag;)Ljava/lang/Object;
  #347 = NameAndType        #345:#346     // map$extension:(Ljava/lang/Object;Lscala/Function1;Lscala/reflect/ClassTag;)Ljava/lang/Object;
  #348 = Methodref          #191.#347     // scala/collection/ArrayOps$.map$extension:(Ljava/lang/Object;Lscala/Function1;Lscala/reflect/ClassTag;)Ljava/lang/Object;
  #349 = Utf8               $anonfun$tasks$2$adapted
  #350 = Utf8               (Lscala/Tuple2;)Ljava/lang/Object;
  #351 = NameAndType        #349:#350     // $anonfun$tasks$2$adapted:(Lscala/Tuple2;)Ljava/lang/Object;
  #352 = Methodref          #2.#351       // org/scalatest/tools/Framework$ScalaTestRunner.$anonfun$tasks$2$adapted:(Lscala/Tuple2;)Ljava/lang/Object;
  #353 = MethodHandle       6:#352        // REF_invokeStatic org/scalatest/tools/Framework$ScalaTestRunner.$anonfun$tasks$2$adapted:(Lscala/Tuple2;)Ljava/lang/Object;
  #354 = MethodType         #350          //  (Lscala/Tuple2;)Ljava/lang/Object;
  #355 = Utf8               ()Lscala/Function1;
  #356 = NameAndType        #222:#355     // apply:()Lscala/Function1;
  #357 = InvokeDynamic      #3:#356       // #3:apply:()Lscala/Function1;
  #358 = Utf8               withFilter$extension
  #359 = Utf8               (Ljava/lang/Object;Lscala/Function1;)Lscala/collection/ArrayOps$WithFilter;
  #360 = NameAndType        #358:#359     // withFilter$extension:(Ljava/lang/Object;Lscala/Function1;)Lscala/collection/ArrayOps$WithFilter;
  #361 = Methodref          #191.#360     // scala/collection/ArrayOps$.withFilter$extension:(Ljava/lang/Object;Lscala/Function1;)Lscala/collection/ArrayOps$WithFilter;
  #362 = Utf8               $anonfun$tasks$3
  #363 = Utf8               (Lscala/Tuple2;)Lsbt/testing/Task;
  #364 = NameAndType        #362:#363     // $anonfun$tasks$3:(Lscala/Tuple2;)Lsbt/testing/Task;
  #365 = Methodref          #2.#364       // org/scalatest/tools/Framework$ScalaTestRunner.$anonfun$tasks$3:(Lscala/Tuple2;)Lsbt/testing/Task;
  #366 = MethodHandle       6:#365        // REF_invokeStatic org/scalatest/tools/Framework$ScalaTestRunner.$anonfun$tasks$3:(Lscala/Tuple2;)Lsbt/testing/Task;
  #367 = MethodType         #363          //  (Lscala/Tuple2;)Lsbt/testing/Task;
  #368 = InvokeDynamic      #4:#356       // #4:apply:()Lscala/Function1;
  #369 = Utf8               sbt/testing/Task
  #370 = Class              #369          // sbt/testing/Task
  #371 = Utf8               map
  #372 = Utf8               (Lscala/Function1;Lscala/reflect/ClassTag;)Ljava/lang/Object;
  #373 = NameAndType        #371:#372     // map:(Lscala/Function1;Lscala/reflect/ClassTag;)Ljava/lang/Object;
  #374 = Methodref          #31.#373      // scala/collection/ArrayOps$WithFilter.map:(Lscala/Function1;Lscala/reflect/ClassTag;)Ljava/lang/Object;
  #375 = Utf8               [Lsbt/testing/Task;
  #376 = Class              #375          // "[Lsbt/testing/Task;"
  #377 = Utf8               done
  #378 = Utf8               ()Ljava/lang/String;
  #379 = NameAndType        #73:#135      // isDone:()Ljava/util/concurrent/atomic/AtomicBoolean;
  #380 = Methodref          #2.#379       // org/scalatest/tools/Framework$ScalaTestRunner.isDone:()Ljava/util/concurrent/atomic/AtomicBoolean;
  #381 = Utf8               java/util/concurrent/atomic/AtomicBoolean
  #382 = Class              #381          // java/util/concurrent/atomic/AtomicBoolean
  #383 = Utf8               getAndSet
  #384 = Utf8               (Z)Z
  #385 = NameAndType        #383:#384     // getAndSet:(Z)Z
  #386 = Methodref          #382.#385     // java/util/concurrent/atomic/AtomicBoolean.getAndSet:(Z)Z
  #387 = Utf8               scala/collection/JavaConverters$
  #388 = Class              #387          // scala/collection/JavaConverters$
  #389 = Utf8               Lscala/collection/JavaConverters$;
  #390 = NameAndType        #192:#389     // MODULE$:Lscala/collection/JavaConverters$;
  #391 = Fieldref           #388.#390     // scala/collection/JavaConverters$.MODULE$:Lscala/collection/JavaConverters$;
  #392 = Utf8               collectionAsScalaIterableConverter
  #393 = Utf8               (Ljava/util/Collection;)Lscala/collection/JavaConverters$AsScala;
  #394 = NameAndType        #392:#393     // collectionAsScalaIterableConverter:(Ljava/util/Collection;)Lscala/collection/JavaConverters$AsScala;
  #395 = Methodref          #388.#394     // scala/collection/JavaConverters$.collectionAsScalaIterableConverter:(Ljava/util/Collection;)Lscala/collection/JavaConverters$AsScala;
  #396 = Utf8               asScala
  #397 = Utf8               ()Ljava/lang/Object;
  #398 = NameAndType        #396:#397     // asScala:()Ljava/lang/Object;
  #399 = Methodref          #36.#398      // scala/collection/JavaConverters$AsScala.asScala:()Ljava/lang/Object;
  #400 = Utf8               scala/collection/IterableOnceOps
  #401 = Class              #400          // scala/collection/IterableOnceOps
  #402 = Utf8               $anonfun$done$1$adapted
  #403 = Utf8               (Lorg/scalatest/Status;)Ljava/lang/Object;
  #404 = NameAndType        #402:#403     // $anonfun$done$1$adapted:(Lorg/scalatest/Status;)Ljava/lang/Object;
  #405 = Methodref          #2.#404       // org/scalatest/tools/Framework$ScalaTestRunner.$anonfun$done$1$adapted:(Lorg/scalatest/Status;)Ljava/lang/Object;
  #406 = MethodHandle       6:#405        // REF_invokeStatic org/scalatest/tools/Framework$ScalaTestRunner.$anonfun$done$1$adapted:(Lorg/scalatest/Status;)Ljava/lang/Object;
  #407 = MethodType         #403          //  (Lorg/scalatest/Status;)Ljava/lang/Object;
  #408 = InvokeDynamic      #5:#356       // #5:apply:()Lscala/Function1;
  #409 = Utf8               foreach
  #410 = Utf8               (Lscala/Function1;)V
  #411 = NameAndType        #409:#410     // foreach:(Lscala/Function1;)V
  #412 = InterfaceMethodref #401.#411     // scala/collection/IterableOnceOps.foreach:(Lscala/Function1;)V
  #413 = NameAndType        #75:#138      // serverThread:()Ljava/util/concurrent/atomic/AtomicReference;
  #414 = Methodref          #2.#413       // org/scalatest/tools/Framework$ScalaTestRunner.serverThread:()Ljava/util/concurrent/atomic/AtomicReference;
  #415 = Utf8               java/util/concurrent/atomic/AtomicReference
  #416 = Class              #415          // java/util/concurrent/atomic/AtomicReference
  #417 = Utf8               get
  #418 = NameAndType        #417:#397     // get:()Ljava/lang/Object;
  #419 = Methodref          #416.#418     // java/util/concurrent/atomic/AtomicReference.get:()Ljava/lang/Object;
  #420 = Utf8               scala/Option
  #421 = Class              #420          // scala/Option
  #422 = Utf8               scala/Some
  #423 = Class              #422          // scala/Some
  #424 = Utf8               value
  #425 = NameAndType        #424:#397     // value:()Ljava/lang/Object;
  #426 = Methodref          #423.#425     // scala/Some.value:()Ljava/lang/Object;
  #427 = Utf8               java/lang/Thread
  #428 = Class              #427          // java/lang/Thread
  #429 = Utf8               join
  #430 = Utf8               ()V
  #431 = NameAndType        #429:#430     // join:()V
  #432 = Methodref          #428.#431     // java/lang/Thread.join:()V
  #433 = Utf8               scala/runtime/BoxedUnit
  #434 = Class              #433          // scala/runtime/BoxedUnit
  #435 = Utf8               UNIT
  #436 = Utf8               Lscala/runtime/BoxedUnit;
  #437 = NameAndType        #435:#436     // UNIT:Lscala/runtime/BoxedUnit;
  #438 = Fieldref           #434.#437     // scala/runtime/BoxedUnit.UNIT:Lscala/runtime/BoxedUnit;
  #439 = Utf8               scala/None$
  #440 = Class              #439          // scala/None$
  #441 = Utf8               Lscala/None$;
  #442 = NameAndType        #192:#441     // MODULE$:Lscala/None$;
  #443 = Fieldref           #440.#442     // scala/None$.MODULE$:Lscala/None$;
  #444 = Utf8               equals
  #445 = Utf8               (Ljava/lang/Object;)Z
  #446 = NameAndType        #444:#445     // equals:(Ljava/lang/Object;)Z
  #447 = Methodref          #4.#446       // java/lang/Object.equals:(Ljava/lang/Object;)Z
  #448 = Utf8               scala/MatchError
  #449 = Class              #448          // scala/MatchError
  #450 = Utf8               (Ljava/lang/Object;)V
  #451 = NameAndType        #269:#450     // "<init>":(Ljava/lang/Object;)V
  #452 = Methodref          #449.#451     // scala/MatchError."<init>":(Ljava/lang/Object;)V
  #453 = Utf8               java/lang/System
  #454 = Class              #453          // java/lang/System
  #455 = Utf8               currentTimeMillis
  #456 = NameAndType        #455:#152     // currentTimeMillis:()J
  #457 = Methodref          #454.#456     // java/lang/System.currentTimeMillis:()J
  #458 = NameAndType        #85:#152      // runStartTime:()J
  #459 = Methodref          #2.#458       // org/scalatest/tools/Framework$ScalaTestRunner.runStartTime:()J
  #460 = Utf8               org/scalatest/events/Summary
  #461 = Class              #460          // org/scalatest/events/Summary
  #462 = Utf8               testsSucceededCount
  #463 = NameAndType        #462:#161     // testsSucceededCount:()Ljava/util/concurrent/atomic/AtomicInteger;
  #464 = Methodref          #28.#463      // org/scalatest/tools/Framework$SummaryCounter.testsSucceededCount:()Ljava/util/concurrent/atomic/AtomicInteger;
  #465 = Utf8               java/util/concurrent/atomic/AtomicInteger
  #466 = Class              #465          // java/util/concurrent/atomic/AtomicInteger
  #467 = NameAndType        #417:#167     // get:()I
  #468 = Methodref          #466.#467     // java/util/concurrent/atomic/AtomicInteger.get:()I
  #469 = Utf8               testsFailedCount
  #470 = NameAndType        #469:#161     // testsFailedCount:()Ljava/util/concurrent/atomic/AtomicInteger;
  #471 = Methodref          #28.#470      // org/scalatest/tools/Framework$SummaryCounter.testsFailedCount:()Ljava/util/concurrent/atomic/AtomicInteger;
  #472 = Utf8               testsIgnoredCount
  #473 = NameAndType        #472:#161     // testsIgnoredCount:()Ljava/util/concurrent/atomic/AtomicInteger;
  #474 = Methodref          #28.#473      // org/scalatest/tools/Framework$SummaryCounter.testsIgnoredCount:()Ljava/util/concurrent/atomic/AtomicInteger;
  #475 = Utf8               testsPendingCount
  #476 = NameAndType        #475:#161     // testsPendingCount:()Ljava/util/concurrent/atomic/AtomicInteger;
  #477 = Methodref          #28.#476      // org/scalatest/tools/Framework$SummaryCounter.testsPendingCount:()Ljava/util/concurrent/atomic/AtomicInteger;
  #478 = Utf8               testsCanceledCount
  #479 = NameAndType        #478:#161     // testsCanceledCount:()Ljava/util/concurrent/atomic/AtomicInteger;
  #480 = Methodref          #28.#479      // org/scalatest/tools/Framework$SummaryCounter.testsCanceledCount:()Ljava/util/concurrent/atomic/AtomicInteger;
  #481 = Utf8               suitesCompletedCount
  #482 = NameAndType        #481:#161     // suitesCompletedCount:()Ljava/util/concurrent/atomic/AtomicInteger;
  #483 = Methodref          #28.#482      // org/scalatest/tools/Framework$SummaryCounter.suitesCompletedCount:()Ljava/util/concurrent/atomic/AtomicInteger;
  #484 = Utf8               suitesAbortedCount
  #485 = NameAndType        #484:#161     // suitesAbortedCount:()Ljava/util/concurrent/atomic/AtomicInteger;
  #486 = Methodref          #28.#485      // org/scalatest/tools/Framework$SummaryCounter.suitesAbortedCount:()Ljava/util/concurrent/atomic/AtomicInteger;
  #487 = Utf8               scopesPendingCount
  #488 = NameAndType        #487:#161     // scopesPendingCount:()Ljava/util/concurrent/atomic/AtomicInteger;
  #489 = Methodref          #28.#488      // org/scalatest/tools/Framework$SummaryCounter.scopesPendingCount:()Ljava/util/concurrent/atomic/AtomicInteger;
  #490 = Utf8               (IIIIIIII)V
  #491 = NameAndType        #269:#490     // "<init>":(IIIIIIII)V
  #492 = Methodref          #461.#491     // org/scalatest/events/Summary."<init>":(IIIIIIII)V
  #493 = NameAndType        #87:#155      // dispatchReporter:()Lorg/scalatest/DispatchReporter;
  #494 = Methodref          #2.#493       // org/scalatest/tools/Framework$ScalaTestRunner.dispatchReporter:()Lorg/scalatest/DispatchReporter;
  #495 = Utf8               org/scalatest/events/RunCompleted
  #496 = Class              #495          // org/scalatest/events/RunCompleted
  #497 = Utf8               org/scalatest/Tracker
  #498 = Class              #497          // org/scalatest/Tracker
  #499 = Utf8               nextOrdinal
  #500 = Utf8               ()Lorg/scalatest/events/Ordinal;
  #501 = NameAndType        #499:#500     // nextOrdinal:()Lorg/scalatest/events/Ordinal;
  #502 = Methodref          #498.#501     // org/scalatest/Tracker.nextOrdinal:()Lorg/scalatest/events/Ordinal;
  #503 = Utf8               scala/runtime/BoxesRunTime
  #504 = Class              #503          // scala/runtime/BoxesRunTime
  #505 = Utf8               boxToLong
  #506 = Utf8               (J)Ljava/lang/Long;
  #507 = NameAndType        #505:#506     // boxToLong:(J)Ljava/lang/Long;
  #508 = Methodref          #504.#507     // scala/runtime/BoxesRunTime.boxToLong:(J)Ljava/lang/Long;
  #509 = Methodref          #423.#451     // scala/Some."<init>":(Ljava/lang/Object;)V
  #510 = Utf8               org/scalatest/events/RunCompleted$
  #511 = Class              #510          // org/scalatest/events/RunCompleted$
  #512 = Utf8               Lorg/scalatest/events/RunCompleted$;
  #513 = NameAndType        #192:#512     // MODULE$:Lorg/scalatest/events/RunCompleted$;
  #514 = Fieldref           #511.#513     // org/scalatest/events/RunCompleted$.MODULE$:Lorg/scalatest/events/RunCompleted$;
  #515 = Utf8               apply$default$4
  #516 = Utf8               ()Lscala/Option;
  #517 = NameAndType        #515:#516     // apply$default$4:()Lscala/Option;
  #518 = Methodref          #511.#517     // org/scalatest/events/RunCompleted$.apply$default$4:()Lscala/Option;
  #519 = Utf8               apply$default$5
  #520 = NameAndType        #519:#516     // apply$default$5:()Lscala/Option;
  #521 = Methodref          #511.#520     // org/scalatest/events/RunCompleted$.apply$default$5:()Lscala/Option;
  #522 = Utf8               apply$default$6
  #523 = NameAndType        #522:#516     // apply$default$6:()Lscala/Option;
  #524 = Methodref          #511.#523     // org/scalatest/events/RunCompleted$.apply$default$6:()Lscala/Option;
  #525 = Utf8               apply$default$7
  #526 = NameAndType        #525:#378     // apply$default$7:()Ljava/lang/String;
  #527 = Methodref          #511.#526     // org/scalatest/events/RunCompleted$.apply$default$7:()Ljava/lang/String;
  #528 = Utf8               apply$default$8
  #529 = NameAndType        #528:#152     // apply$default$8:()J
  #530 = Methodref          #511.#529     // org/scalatest/events/RunCompleted$.apply$default$8:()J
  #531 = Utf8               (Lorg/scalatest/events/Ordinal;Lscala/Option;Lscala/Option;Lscala/Option;Lscala/Option;Lscala/Option;Ljava/lang/String;J)V
  #532 = NameAndType        #269:#531     // "<init>":(Lorg/scalatest/events/Ordinal;Lscala/Option;Lscala/Option;Lscala/Option;Lscala/Option;Lscala/Option;Ljava/lang/String;J)V
  #533 = Methodref          #496.#532     // org/scalatest/events/RunCompleted."<init>":(Lorg/scalatest/events/Ordinal;Lscala/Option;Lscala/Option;Lscala/Option;Lscala/Option;Lscala/Option;Ljava/lang/String;J)V
  #534 = Utf8               org/scalatest/DispatchReporter
  #535 = Class              #534          // org/scalatest/DispatchReporter
  #536 = Utf8               (Lorg/scalatest/events/Event;)V
  #537 = NameAndType        #222:#536     // apply:(Lorg/scalatest/events/Event;)V
  #538 = Methodref          #535.#537     // org/scalatest/DispatchReporter.apply:(Lorg/scalatest/events/Event;)V
  #539 = Utf8               dispatchDisposeAndWaitUntilDone
  #540 = NameAndType        #539:#430     // dispatchDisposeAndWaitUntilDone:()V
  #541 = Methodref          #535.#540     // org/scalatest/DispatchReporter.dispatchDisposeAndWaitUntilDone:()V
  #542 = Utf8               java/util/concurrent/ExecutorService
  #543 = Class              #542          // java/util/concurrent/ExecutorService
  #544 = Utf8               shutdown
  #545 = NameAndType        #544:#430     // shutdown:()V
  #546 = InterfaceMethodref #543.#545     // java/util/concurrent/ExecutorService.shutdown:()V
  #547 = Utf8               org/scalatest/tools/StringReporter$
  #548 = Class              #547          // org/scalatest/tools/StringReporter$
  #549 = Utf8               Lorg/scalatest/tools/StringReporter$;
  #550 = NameAndType        #192:#549     // MODULE$:Lorg/scalatest/tools/StringReporter$;
  #551 = Fieldref           #548.#550     // org/scalatest/tools/StringReporter$.MODULE$:Lorg/scalatest/tools/StringReporter$;
  #552 = Utf8               scala/package$
  #553 = Class              #552          // scala/package$
  #554 = Utf8               Lscala/package$;
  #555 = NameAndType        #192:#554     // MODULE$:Lscala/package$;
  #556 = Fieldref           #553.#555     // scala/package$.MODULE$:Lscala/package$;
  #557 = Utf8               Vector
  #558 = Utf8               ()Lscala/collection/immutable/Vector$;
  #559 = NameAndType        #557:#558     // Vector:()Lscala/collection/immutable/Vector$;
  #560 = Methodref          #553.#559     // scala/package$.Vector:()Lscala/collection/immutable/Vector$;
  #561 = Utf8               scala/collection/immutable/Vector$
  #562 = Class              #561          // scala/collection/immutable/Vector$
  #563 = Utf8               empty
  #564 = Utf8               ()Lscala/collection/immutable/Vector;
  #565 = NameAndType        #563:#564     // empty:()Lscala/collection/immutable/Vector;
  #566 = Methodref          #562.#565     // scala/collection/immutable/Vector$.empty:()Lscala/collection/immutable/Vector;
  #567 = Utf8               reminderEventsQueue
  #568 = NameAndType        #567:#142     // reminderEventsQueue:()Ljava/util/concurrent/LinkedBlockingQueue;
  #569 = Methodref          #28.#568      // org/scalatest/tools/Framework$SummaryCounter.reminderEventsQueue:()Ljava/util/concurrent/LinkedBlockingQueue;
  #570 = Utf8               scala/collection/IterableOnce
  #571 = Class              #570          // scala/collection/IterableOnce
  #572 = Utf8               scala/collection/immutable/Vector
  #573 = Class              #572          // scala/collection/immutable/Vector
  #574 = Utf8               $plus$plus
  #575 = Utf8               (Lscala/collection/IterableOnce;)Ljava/lang/Object;
  #576 = NameAndType        #574:#575     // $plus$plus:(Lscala/collection/IterableOnce;)Ljava/lang/Object;
  #577 = Methodref          #573.#576     // scala/collection/immutable/Vector.$plus$plus:(Lscala/collection/IterableOnce;)Ljava/lang/Object;
  #578 = Utf8               summaryFragments
  #579 = Utf8               (ZLscala/Option;Lscala/Option;Lscala/collection/immutable/Vector;ZZZZZZ)Lscala/collection/immutable/Vector;
  #580 = NameAndType        #578:#579     // summaryFragments:(ZLscala/Option;Lscala/Option;Lscala/collection/immutable/Vector;ZZZZZZ)Lscala/collection/immutable/Vector;
  #581 = Methodref          #548.#580     // org/scalatest/tools/StringReporter$.summaryFragments:(ZLscala/Option;Lscala/Option;Lscala/collection/immutable/Vector;ZZZZZZ)Lscala/collection/immutable/Vector;
  #582 = Utf8               $anonfun$done$2
  #583 = Utf8               (Lorg/scalatest/tools/Framework$ScalaTestRunner;Lorg/scalatest/tools/Fragment;)Ljava/lang/String;
  #584 = NameAndType        #582:#583     // $anonfun$done$2:(Lorg/scalatest/tools/Framework$ScalaTestRunner;Lorg/scalatest/tools/Fragment;)Ljava/lang/String;
  #585 = Methodref          #2.#584       // org/scalatest/tools/Framework$ScalaTestRunner.$anonfun$done$2:(Lorg/scalatest/tools/Framework$ScalaTestRunner;Lorg/scalatest/tools/Fragment;)Ljava/lang/String;
  #586 = MethodHandle       6:#585        // REF_invokeStatic org/scalatest/tools/Framework$ScalaTestRunner.$anonfun$done$2:(Lorg/scalatest/tools/Framework$ScalaTestRunner;Lorg/scalatest/tools/Fragment;)Ljava/lang/String;
  #587 = Utf8               (Lorg/scalatest/tools/Fragment;)Ljava/lang/String;
  #588 = MethodType         #587          //  (Lorg/scalatest/tools/Fragment;)Ljava/lang/String;
  #589 = InvokeDynamic      #6:#341       // #6:apply:(Lorg/scalatest/tools/Framework$ScalaTestRunner;)Lscala/Function1;
  #590 = Utf8               (Lscala/Function1;)Ljava/lang/Object;
  #591 = NameAndType        #371:#590     // map:(Lscala/Function1;)Ljava/lang/Object;
  #592 = Methodref          #573.#591     // scala/collection/immutable/Vector.map:(Lscala/Function1;)Ljava/lang/Object;
  #593 = Utf8               \n
  #594 = String             #593          // \n
  #595 = Utf8               mkString
  #596 = Utf8               (Ljava/lang/String;)Ljava/lang/String;
  #597 = NameAndType        #595:#596     // mkString:(Ljava/lang/String;)Ljava/lang/String;
  #598 = InterfaceMethodref #401.#597     // scala/collection/IterableOnceOps.mkString:(Ljava/lang/String;)Ljava/lang/String;
  #599 = Utf8               java/lang/IllegalStateException
  #600 = Class              #599          // java/lang/IllegalStateException
  #601 = Utf8               done method is called twice
  #602 = String             #601          // done method is called twice
  #603 = Utf8               (Ljava/lang/String;)V
  #604 = NameAndType        #269:#603     // "<init>":(Ljava/lang/String;)V
  #605 = Methodref          #600.#604     // java/lang/IllegalStateException."<init>":(Ljava/lang/String;)V
  #606 = Utf8               thread
  #607 = Utf8               Ljava/lang/Thread;
  #608 = Utf8               duration
  #609 = Utf8               summary
  #610 = Utf8               Lorg/scalatest/events/Summary;
  #611 = Utf8               fragments
  #612 = Utf8               Lscala/collection/immutable/Vector;
  #613 = Utf8               java/lang/String
  #614 = Class              #613          // java/lang/String
  #615 = Utf8               args
  #616 = Utf8               ()[Ljava/lang/String;
  #617 = NameAndType        #40:#41       // runArgs:[Ljava/lang/String;
  #618 = Fieldref           #2.#617       // org/scalatest/tools/Framework$ScalaTestRunner.runArgs:[Ljava/lang/String;
  #619 = Utf8               remoteArgs
  #620 = Utf8               (Lorg/scalatest/tools/Framework$ScalaTestRunner;)V
  #621 = NameAndType        #269:#620     // "<init>":(Lorg/scalatest/tools/Framework$ScalaTestRunner;)V
  #622 = Methodref          #19.#621      // org/scalatest/tools/Framework$ScalaTestRunner$Skeleton$1."<init>":(Lorg/scalatest/tools/Framework$ScalaTestRunner;)V
  #623 = Utf8               (Ljava/lang/Runnable;)V
  #624 = NameAndType        #269:#623     // "<init>":(Ljava/lang/Runnable;)V
  #625 = Methodref          #428.#624     // java/lang/Thread."<init>":(Ljava/lang/Runnable;)V
  #626 = Utf8               start
  #627 = NameAndType        #626:#430     // start:()V
  #628 = Methodref          #428.#627     // java/lang/Thread.start:()V
  #629 = Utf8               set
  #630 = NameAndType        #629:#450     // set:(Ljava/lang/Object;)V
  #631 = Methodref          #416.#630     // java/util/concurrent/atomic/AtomicReference.set:(Ljava/lang/Object;)V
  #632 = Utf8               127.0.0.1
  #633 = String             #632          // 127.0.0.1
  #634 = Utf8               port
  #635 = NameAndType        #634:#167     // port:()I
  #636 = Methodref          #19.#635      // org/scalatest/tools/Framework$ScalaTestRunner$Skeleton$1.port:()I
  #637 = Utf8               java/lang/Integer
  #638 = Class              #637          // java/lang/Integer
  #639 = Utf8               toString
  #640 = Utf8               (I)Ljava/lang/String;
  #641 = NameAndType        #639:#640     // toString:(I)Ljava/lang/String;
  #642 = Methodref          #638.#641     // java/lang/Integer.toString:(I)Ljava/lang/String;
  #643 = Class              #41           // "[Ljava/lang/String;"
  #644 = Utf8               skeleton
  #645 = Utf8               Lorg/scalatest/tools/Framework$ScalaTestRunner$Skeleton$1;
  #646 = NameAndType        #99:#100      // $outer:Lorg/scalatest/tools/Framework;
  #647 = Fieldref           #2.#646       // org/scalatest/tools/Framework$ScalaTestRunner.$outer:Lorg/scalatest/tools/Framework;
  #648 = Utf8               $anonfun$filterWildcard$2
  #649 = Utf8               (Lsbt/testing/TaskDef;Ljava/lang/String;)Z
  #650 = Utf8               td$1
  #651 = Utf8               x$15
  #652 = Utf8               fullyQualifiedName
  #653 = NameAndType        #652:#378     // fullyQualifiedName:()Ljava/lang/String;
  #654 = Methodref          #202.#653     // sbt/testing/TaskDef.fullyQualifiedName:()Ljava/lang/String;
  #655 = Utf8               startsWith
  #656 = Utf8               (Ljava/lang/String;)Z
  #657 = NameAndType        #655:#656     // startsWith:(Ljava/lang/String;)Z
  #658 = Methodref          #614.#657     // java/lang/String.startsWith:(Ljava/lang/String;)Z
  #659 = Utf8               Ljava/lang/String;
  #660 = Utf8               $anonfun$filterWildcard$1
  #661 = Utf8               (Lscala/collection/immutable/List;Lsbt/testing/TaskDef;)Z
  #662 = Utf8               paths$1
  #663 = Utf8               $anonfun$filterWildcard$2$adapted
  #664 = Utf8               (Lsbt/testing/TaskDef;Ljava/lang/String;)Ljava/lang/Object;
  #665 = NameAndType        #663:#664     // $anonfun$filterWildcard$2$adapted:(Lsbt/testing/TaskDef;Ljava/lang/String;)Ljava/lang/Object;
  #666 = Methodref          #2.#665       // org/scalatest/tools/Framework$ScalaTestRunner.$anonfun$filterWildcard$2$adapted:(Lsbt/testing/TaskDef;Ljava/lang/String;)Ljava/lang/Object;
  #667 = MethodHandle       6:#666        // REF_invokeStatic org/scalatest/tools/Framework$ScalaTestRunner.$anonfun$filterWildcard$2$adapted:(Lsbt/testing/TaskDef;Ljava/lang/String;)Ljava/lang/Object;
  #668 = Utf8               (Ljava/lang/String;)Ljava/lang/Object;
  #669 = MethodType         #668          //  (Ljava/lang/String;)Ljava/lang/Object;
  #670 = Utf8               (Lsbt/testing/TaskDef;)Lscala/Function1;
  #671 = NameAndType        #222:#670     // apply:(Lsbt/testing/TaskDef;)Lscala/Function1;
  #672 = InvokeDynamic      #7:#671       // #7:apply:(Lsbt/testing/TaskDef;)Lscala/Function1;
  #673 = Utf8               exists
  #674 = Utf8               (Lscala/Function1;)Z
  #675 = NameAndType        #673:#674     // exists:(Lscala/Function1;)Z
  #676 = Methodref          #317.#675     // scala/collection/immutable/List.exists:(Lscala/Function1;)Z
  #677 = Utf8               $anonfun$filterMembersOnly$2
  #678 = Utf8               td$2
  #679 = Utf8               path
  #680 = Utf8               length
  #681 = NameAndType        #680:#167     // length:()I
  #682 = Methodref          #614.#681     // java/lang/String.length:()I
  #683 = Utf8               substring
  #684 = NameAndType        #683:#640     // substring:(I)Ljava/lang/String;
  #685 = Methodref          #614.#684     // java/lang/String.substring:(I)Ljava/lang/String;
  #686 = Utf8               lastIndexOf
  #687 = Utf8               (I)I
  #688 = NameAndType        #686:#687     // lastIndexOf:(I)I
  #689 = Methodref          #614.#688     // java/lang/String.lastIndexOf:(I)I
  #690 = Utf8               $anonfun$filterMembersOnly$1
  #691 = Utf8               paths$2
  #692 = Utf8               $anonfun$filterMembersOnly$2$adapted
  #693 = NameAndType        #692:#664     // $anonfun$filterMembersOnly$2$adapted:(Lsbt/testing/TaskDef;Ljava/lang/String;)Ljava/lang/Object;
  #694 = Methodref          #2.#693       // org/scalatest/tools/Framework$ScalaTestRunner.$anonfun$filterMembersOnly$2$adapted:(Lsbt/testing/TaskDef;Ljava/lang/String;)Ljava/lang/Object;
  #695 = MethodHandle       6:#694        // REF_invokeStatic org/scalatest/tools/Framework$ScalaTestRunner.$anonfun$filterMembersOnly$2$adapted:(Lsbt/testing/TaskDef;Ljava/lang/String;)Ljava/lang/Object;
  #696 = InvokeDynamic      #8:#671       // #8:apply:(Lsbt/testing/TaskDef;)Lscala/Function1;
  #697 = Utf8               $this
  #698 = Utf8               taskDef
  #699 = NameAndType        #173:#174     // createTask:(Lsbt/testing/TaskDef;)Lorg/scalatest/tools/Framework$ScalaTestTask;
  #700 = Methodref          #2.#699       // org/scalatest/tools/Framework$ScalaTestRunner.createTask:(Lsbt/testing/TaskDef;)Lorg/scalatest/tools/Framework$ScalaTestTask;
  #701 = Utf8               (Ljava/lang/Object;Ljava/lang/Object;)V
  #702 = NameAndType        #269:#701     // "<init>":(Ljava/lang/Object;Ljava/lang/Object;)V
  #703 = Methodref          #344.#702     // scala/Tuple2."<init>":(Ljava/lang/Object;Ljava/lang/Object;)V
  #704 = Utf8               task
  #705 = Utf8               Lorg/scalatest/tools/Framework$ScalaTestTask;
  #706 = Utf8               $anonfun$tasks$2
  #707 = Utf8               (Lscala/Tuple2;)Z
  #708 = Utf8               x$16
  #709 = Utf8               _2
  #710 = NameAndType        #709:#397     // _2:()Ljava/lang/Object;
  #711 = Methodref          #344.#710     // scala/Tuple2._2:()Ljava/lang/Object;
  #712 = Utf8               shouldDiscover
  #713 = NameAndType        #712:#106     // shouldDiscover:()Z
  #714 = Methodref          #25.#713      // org/scalatest/tools/Framework$ScalaTestTask.shouldDiscover:()Z
  #715 = Utf8               Lscala/Tuple2;
  #716 = Utf8               x$17
  #717 = Utf8               $anonfun$done$1
  #718 = Utf8               (Lorg/scalatest/Status;)V
  #719 = Utf8               s
  #720 = Utf8               java/lang/Throwable
  #721 = Class              #720          // java/lang/Throwable
  #722 = Utf8               org/scalatest/Status
  #723 = Class              #722          // org/scalatest/Status
  #724 = Utf8               waitUntilCompleted
  #725 = NameAndType        #724:#430     // waitUntilCompleted:()V
  #726 = InterfaceMethodref #723.#725     // org/scalatest/Status.waitUntilCompleted:()V
  #727 = Utf8               t
  #728 = Utf8               Ljava/lang/Throwable;
  #729 = Utf8               Lorg/scalatest/Status;
  #730 = Utf8               x$18
  #731 = Utf8               org/scalatest/tools/Fragment
  #732 = Class              #731          // org/scalatest/tools/Fragment
  #733 = Utf8               toPossiblyColoredText
  #734 = Utf8               (Z)Ljava/lang/String;
  #735 = NameAndType        #733:#734     // toPossiblyColoredText:(Z)Ljava/lang/String;
  #736 = Methodref          #732.#735     // org/scalatest/tools/Fragment.toPossiblyColoredText:(Z)Ljava/lang/String;
  #737 = Utf8               Lorg/scalatest/tools/Fragment;
  #738 = Utf8               (Lorg/scalatest/tools/Framework;[Ljava/lang/String;Ljava/lang/ClassLoader;Lscala/collection/immutable/Set;Lscala/collection/immutable/Set;Lscala/collection/immutable/List;Lscala/collection/immutable/List;Lscala/collection/immutable/List;Lorg/scalatest/ConfigMap;Lorg/scalatest/tools/ReporterConfigurations;ZZZZZZZZZZZZLscala/collection/immutable/Set;ZJJLorg/scalatest/tools/ConcurrentConfig;Lorg/scalatest/time/Span;)V
  #739 = Utf8               ([Ljava/lang/String;Ljava/lang/ClassLoader;Lscala/collection/immutable/Set<Ljava/lang/String;>;Lscala/collection/immutable/Set<Ljava/lang/String;>;Lscala/collection/immutable/List<Ljava/lang/String;>;Lscala/collection/immutable/List<Ljava/lang/String;>;Lscala/collection/immutable/List<Lsbt/testing/Selector;>;Lorg/scalatest/ConfigMap;Lorg/scalatest/tools/ReporterConfigurations;ZZZZZZZZZZZZLscala/collection/immutable/Set<Lorg/scalatest/tools/ReporterConfigParam;>;ZJJLorg/scalatest/tools/ConcurrentConfig;Lorg/scalatest/time/Span;)V
  #740 = Utf8               detectSlowpokes
  #741 = Utf8               slowpokeDetectionDelay
  #742 = Utf8               slowpokeDetectionPeriod
  #743 = Utf8               concurrentConfig
  #744 = Utf8               testSortingReporterTimeout
  #745 = NameAndType        #269:#430     // "<init>":()V
  #746 = Methodref          #4.#745       // java/lang/Object."<init>":()V
  #747 = Utf8               (Z)V
  #748 = NameAndType        #269:#747     // "<init>":(Z)V
  #749 = Methodref          #382.#748     // java/util/concurrent/atomic/AtomicBoolean."<init>":(Z)V
  #750 = Methodref          #416.#451     // java/util/concurrent/atomic/AtomicReference."<init>":(Ljava/lang/Object;)V
  #751 = Utf8               java/util/concurrent/LinkedBlockingQueue
  #752 = Class              #751          // java/util/concurrent/LinkedBlockingQueue
  #753 = Methodref          #752.#745     // java/util/concurrent/LinkedBlockingQueue."<init>":()V
  #754 = Utf8               org/scalatest/Tracker$
  #755 = Class              #754          // org/scalatest/Tracker$
  #756 = Utf8               Lorg/scalatest/Tracker$;
  #757 = NameAndType        #192:#756     // MODULE$:Lorg/scalatest/Tracker$;
  #758 = Fieldref           #755.#757     // org/scalatest/Tracker$.MODULE$:Lorg/scalatest/Tracker$;
  #759 = Utf8               $lessinit$greater$default$1
  #760 = NameAndType        #759:#500     // $lessinit$greater$default$1:()Lorg/scalatest/events/Ordinal;
  #761 = Methodref          #755.#760     // org/scalatest/Tracker$.$lessinit$greater$default$1:()Lorg/scalatest/events/Ordinal;
  #762 = Utf8               (Lorg/scalatest/events/Ordinal;)V
  #763 = NameAndType        #269:#762     // "<init>":(Lorg/scalatest/events/Ordinal;)V
  #764 = Methodref          #498.#763     // org/scalatest/Tracker."<init>":(Lorg/scalatest/events/Ordinal;)V
  #765 = Utf8               (Lorg/scalatest/tools/Framework;)V
  #766 = NameAndType        #269:#765     // "<init>":(Lorg/scalatest/tools/Framework;)V
  #767 = Methodref          #28.#766      // org/scalatest/tools/Framework$SummaryCounter."<init>":(Lorg/scalatest/tools/Framework;)V
  #768 = Utf8               org/scalatest/tools/ReporterFactory$
  #769 = Class              #768          // org/scalatest/tools/ReporterFactory$
  #770 = Utf8               Lorg/scalatest/tools/ReporterFactory$;
  #771 = NameAndType        #192:#770     // MODULE$:Lorg/scalatest/tools/ReporterFactory$;
  #772 = Fieldref           #769.#771     // org/scalatest/tools/ReporterFactory$.MODULE$:Lorg/scalatest/tools/ReporterFactory$;
  #773 = Utf8               org$scalatest$tools$Framework$$resultHolder
  #774 = Utf8               ()Lorg/scalatest/tools/SuiteResultHolder;
  #775 = NameAndType        #773:#774     // org$scalatest$tools$Framework$$resultHolder:()Lorg/scalatest/tools/SuiteResultHolder;
  #776 = Methodref          #14.#775      // org/scalatest/tools/Framework.org$scalatest$tools$Framework$$resultHolder:()Lorg/scalatest/tools/SuiteResultHolder;
  #777 = Utf8               getDispatchReporter
  #778 = Utf8               (Lorg/scalatest/tools/ReporterConfigurations;Lscala/Option;Lscala/Option;Ljava/lang/ClassLoader;Lscala/Option;ZJJ)Lorg/scalatest/DispatchReporter;
  #779 = NameAndType        #777:#778     // getDispatchReporter:(Lorg/scalatest/tools/ReporterConfigurations;Lscala/Option;Lscala/Option;Ljava/lang/ClassLoader;Lscala/Option;ZJJ)Lorg/scalatest/DispatchReporter;
  #780 = Methodref          #769.#779     // org/scalatest/tools/ReporterFactory$.getDispatchReporter:(Lorg/scalatest/tools/ReporterConfigurations;Lscala/Option;Lscala/Option;Ljava/lang/ClassLoader;Lscala/Option;ZJJ)Lorg/scalatest/DispatchReporter;
  #781 = Utf8               org/scalatest/tools/SuiteSortingReporter
  #782 = Class              #781          // org/scalatest/tools/SuiteSortingReporter
  #783 = Utf8               org/scalatest/time/Span$
  #784 = Class              #783          // org/scalatest/time/Span$
  #785 = Utf8               Lorg/scalatest/time/Span$;
  #786 = NameAndType        #192:#785     // MODULE$:Lorg/scalatest/time/Span$;
  #787 = Fieldref           #784.#786     // org/scalatest/time/Span$.MODULE$:Lorg/scalatest/time/Span$;
  #788 = Utf8               org/scalatest/time/Span
  #789 = Class              #788          // org/scalatest/time/Span
  #790 = Utf8               millisPart
  #791 = NameAndType        #790:#152     // millisPart:()J
  #792 = Methodref          #789.#791     // org/scalatest/time/Span.millisPart:()J
  #793 = Utf8               org/scalatest/time/Millis$
  #794 = Class              #793          // org/scalatest/time/Millis$
  #795 = Utf8               Lorg/scalatest/time/Millis$;
  #796 = NameAndType        #192:#795     // MODULE$:Lorg/scalatest/time/Millis$;
  #797 = Fieldref           #794.#796     // org/scalatest/time/Millis$.MODULE$:Lorg/scalatest/time/Millis$;
  #798 = Utf8               (JLorg/scalatest/time/Units;)Lorg/scalatest/time/Span;
  #799 = NameAndType        #222:#798     // apply:(JLorg/scalatest/time/Units;)Lorg/scalatest/time/Span;
  #800 = Methodref          #784.#799     // org/scalatest/time/Span$.apply:(JLorg/scalatest/time/Units;)Lorg/scalatest/time/Span;
  #801 = Utf8               err
  #802 = Utf8               Ljava/io/PrintStream;
  #803 = NameAndType        #801:#802     // err:Ljava/io/PrintStream;
  #804 = Fieldref           #454.#803     // java/lang/System.err:Ljava/io/PrintStream;
  #805 = Utf8               (Lorg/scalatest/Reporter;Lorg/scalatest/time/Span;Ljava/io/PrintStream;)V
  #806 = NameAndType        #269:#805     // "<init>":(Lorg/scalatest/Reporter;Lorg/scalatest/time/Span;Ljava/io/PrintStream;)V
  #807 = Methodref          #782.#806     // org/scalatest/tools/SuiteSortingReporter."<init>":(Lorg/scalatest/Reporter;Lorg/scalatest/time/Span;Ljava/io/PrintStream;)V
  #808 = Utf8               registerSlowpokeReporter
  #809 = Utf8               (Lorg/scalatest/tools/SuiteSortingReporter;)V
  #810 = NameAndType        #808:#809     // registerSlowpokeReporter:(Lorg/scalatest/tools/SuiteSortingReporter;)V
  #811 = Methodref          #535.#810     // org/scalatest/DispatchReporter.registerSlowpokeReporter:(Lorg/scalatest/tools/SuiteSortingReporter;)V
  #812 = Utf8               org/scalatest/events/RunStarting
  #813 = Class              #812          // org/scalatest/events/RunStarting
  #814 = Utf8               org/scalatest/events/RunStarting$
  #815 = Class              #814          // org/scalatest/events/RunStarting$
  #816 = Utf8               Lorg/scalatest/events/RunStarting$;
  #817 = NameAndType        #192:#816     // MODULE$:Lorg/scalatest/events/RunStarting$;
  #818 = Fieldref           #815.#817     // org/scalatest/events/RunStarting$.MODULE$:Lorg/scalatest/events/RunStarting$;
  #819 = Methodref          #815.#517     // org/scalatest/events/RunStarting$.apply$default$4:()Lscala/Option;
  #820 = Methodref          #815.#520     // org/scalatest/events/RunStarting$.apply$default$5:()Lscala/Option;
  #821 = Methodref          #815.#523     // org/scalatest/events/RunStarting$.apply$default$6:()Lscala/Option;
  #822 = Methodref          #815.#526     // org/scalatest/events/RunStarting$.apply$default$7:()Ljava/lang/String;
  #823 = Methodref          #815.#529     // org/scalatest/events/RunStarting$.apply$default$8:()J
  #824 = Utf8               (Lorg/scalatest/events/Ordinal;ILorg/scalatest/ConfigMap;Lscala/Option;Lscala/Option;Lscala/Option;Ljava/lang/String;J)V
  #825 = NameAndType        #269:#824     // "<init>":(Lorg/scalatest/events/Ordinal;ILorg/scalatest/ConfigMap;Lscala/Option;Lscala/Option;Lscala/Option;Ljava/lang/String;J)V
  #826 = Methodref          #813.#825     // org/scalatest/events/RunStarting."<init>":(Lorg/scalatest/events/Ordinal;ILorg/scalatest/ConfigMap;Lscala/Option;Lscala/Option;Lscala/Option;Ljava/lang/String;J)V
  #827 = Methodref          #466.#745     // java/util/concurrent/atomic/AtomicInteger."<init>":()V
  #828 = Methodref          #17.#621      // org/scalatest/tools/Framework$ScalaTestRunner$$anon$3."<init>":(Lorg/scalatest/tools/Framework$ScalaTestRunner;)V
  #829 = Utf8               org/scalatest/tools/ConcurrentConfig
  #830 = Class              #829          // org/scalatest/tools/ConcurrentConfig
  #831 = Utf8               numThreads
  #832 = NameAndType        #831:#167     // numThreads:()I
  #833 = Methodref          #830.#832     // org/scalatest/tools/ConcurrentConfig.numThreads:()I
  #834 = Utf8               java/lang/Runtime
  #835 = Class              #834          // java/lang/Runtime
  #836 = Utf8               getRuntime
  #837 = Utf8               ()Ljava/lang/Runtime;
  #838 = NameAndType        #836:#837     // getRuntime:()Ljava/lang/Runtime;
  #839 = Methodref          #835.#838     // java/lang/Runtime.getRuntime:()Ljava/lang/Runtime;
  #840 = Utf8               availableProcessors
  #841 = NameAndType        #840:#167     // availableProcessors:()I
  #842 = Methodref          #835.#841     // java/lang/Runtime.availableProcessors:()I
  #843 = NameAndType        #95:#167      // poolSize:()I
  #844 = Methodref          #2.#843       // org/scalatest/tools/Framework$ScalaTestRunner.poolSize:()I
  #845 = NameAndType        #93:#164      // threadFactory:()Ljava/util/concurrent/ThreadFactory;
  #846 = Methodref          #2.#845       // org/scalatest/tools/Framework$ScalaTestRunner.threadFactory:()Ljava/util/concurrent/ThreadFactory;
  #847 = Utf8               java/util/concurrent/Executors
  #848 = Class              #847          // java/util/concurrent/Executors
  #849 = Utf8               newFixedThreadPool
  #850 = Utf8               (ILjava/util/concurrent/ThreadFactory;)Ljava/util/concurrent/ExecutorService;
  #851 = NameAndType        #849:#850     // newFixedThreadPool:(ILjava/util/concurrent/ThreadFactory;)Ljava/util/concurrent/ExecutorService;
  #852 = Methodref          #848.#851     // java/util/concurrent/Executors.newFixedThreadPool:(ILjava/util/concurrent/ThreadFactory;)Ljava/util/concurrent/ExecutorService;
  #853 = Utf8               newCachedThreadPool
  #854 = Utf8               (Ljava/util/concurrent/ThreadFactory;)Ljava/util/concurrent/ExecutorService;
  #855 = NameAndType        #853:#854     // newCachedThreadPool:(Ljava/util/concurrent/ThreadFactory;)Ljava/util/concurrent/ExecutorService;
  #856 = Methodref          #848.#855     // java/util/concurrent/Executors.newCachedThreadPool:(Ljava/util/concurrent/ThreadFactory;)Ljava/util/concurrent/ExecutorService;
  #857 = Utf8               Lorg/scalatest/tools/ConcurrentConfig;
  #858 = Utf8               Lorg/scalatest/time/Span;
  #859 = Utf8               java/lang/ClassLoader
  #860 = Class              #859          // java/lang/ClassLoader
  #861 = Utf8               scala/collection/immutable/Set
  #862 = Class              #861          // scala/collection/immutable/Set
  #863 = Utf8               org/scalatest/ConfigMap
  #864 = Class              #863          // org/scalatest/ConfigMap
  #865 = Utf8               org/scalatest/tools/ReporterConfigurations
  #866 = Class              #865          // org/scalatest/tools/ReporterConfigurations
  #867 = NameAndType        #660:#661     // $anonfun$filterWildcard$1:(Lscala/collection/immutable/List;Lsbt/testing/TaskDef;)Z
  #868 = Methodref          #2.#867       // org/scalatest/tools/Framework$ScalaTestRunner.$anonfun$filterWildcard$1:(Lscala/collection/immutable/List;Lsbt/testing/TaskDef;)Z
  #869 = Utf8               boxToBoolean
  #870 = Utf8               (Z)Ljava/lang/Boolean;
  #871 = NameAndType        #869:#870     // boxToBoolean:(Z)Ljava/lang/Boolean;
  #872 = Methodref          #504.#871     // scala/runtime/BoxesRunTime.boxToBoolean:(Z)Ljava/lang/Boolean;
  #873 = NameAndType        #690:#661     // $anonfun$filterMembersOnly$1:(Lscala/collection/immutable/List;Lsbt/testing/TaskDef;)Z
  #874 = Methodref          #2.#873       // org/scalatest/tools/Framework$ScalaTestRunner.$anonfun$filterMembersOnly$1:(Lscala/collection/immutable/List;Lsbt/testing/TaskDef;)Z
  #875 = NameAndType        #706:#707     // $anonfun$tasks$2:(Lscala/Tuple2;)Z
  #876 = Methodref          #2.#875       // org/scalatest/tools/Framework$ScalaTestRunner.$anonfun$tasks$2:(Lscala/Tuple2;)Z
  #877 = NameAndType        #717:#718     // $anonfun$done$1:(Lorg/scalatest/Status;)V
  #878 = Methodref          #2.#877       // org/scalatest/tools/Framework$ScalaTestRunner.$anonfun$done$1:(Lorg/scalatest/Status;)V
  #879 = NameAndType        #648:#649     // $anonfun$filterWildcard$2:(Lsbt/testing/TaskDef;Ljava/lang/String;)Z
  #880 = Methodref          #2.#879       // org/scalatest/tools/Framework$ScalaTestRunner.$anonfun$filterWildcard$2:(Lsbt/testing/TaskDef;Ljava/lang/String;)Z
  #881 = NameAndType        #677:#649     // $anonfun$filterMembersOnly$2:(Lsbt/testing/TaskDef;Ljava/lang/String;)Z
  #882 = Methodref          #2.#881       // org/scalatest/tools/Framework$ScalaTestRunner.$anonfun$filterMembersOnly$2:(Lsbt/testing/TaskDef;Ljava/lang/String;)Z
  #883 = Utf8               $deserializeLambda$
  #884 = Utf8               (Ljava/lang/invoke/SerializedLambda;)Ljava/lang/Object;
  #885 = Utf8               scala/runtime/LambdaDeserialize
  #886 = Class              #885          // scala/runtime/LambdaDeserialize
  #887 = Utf8               bootstrap
  #888 = Utf8               (Ljava/lang/invoke/MethodHandles$Lookup;Ljava/lang/String;Ljava/lang/invoke/MethodType;[Ljava/lang/invoke/MethodHandle;)Ljava/lang/invoke/CallSite;
  #889 = NameAndType        #887:#888     // bootstrap:(Ljava/lang/invoke/MethodHandles$Lookup;Ljava/lang/String;Ljava/lang/invoke/MethodType;[Ljava/lang/invoke/MethodHandle;)Ljava/lang/invoke/CallSite;
  #890 = Methodref          #886.#889     // scala/runtime/LambdaDeserialize.bootstrap:(Ljava/lang/invoke/MethodHandles$Lookup;Ljava/lang/String;Ljava/lang/invoke/MethodType;[Ljava/lang/invoke/MethodHandle;)Ljava/lang/invoke/CallSite;
  #891 = MethodHandle       6:#890        // REF_invokeStatic scala/runtime/LambdaDeserialize.bootstrap:(Ljava/lang/invoke/MethodHandles$Lookup;Ljava/lang/String;Ljava/lang/invoke/MethodType;[Ljava/lang/invoke/MethodHandle;)Ljava/lang/invoke/CallSite;
  #892 = Utf8               lambdaDeserialize
  #893 = NameAndType        #892:#884     // lambdaDeserialize:(Ljava/lang/invoke/SerializedLambda;)Ljava/lang/Object;
  #894 = InvokeDynamic      #9:#893       // #9:lambdaDeserialize:(Ljava/lang/invoke/SerializedLambda;)Ljava/lang/Object;
  #895 = Utf8               Signature
  #896 = Utf8               Code
  #897 = Utf8               LineNumberTable
  #898 = Utf8               LocalVariableTable
  #899 = Utf8               MethodParameters
  #900 = Utf8               StackMapTable
  #901 = Utf8               InnerClasses
  #902 = Utf8               SourceFile
  #903 = Utf8               BootstrapMethods
  #904 = Utf8               ScalaInlineInfo
  #905 = Utf8               Scala
{
  private final java.lang.String[] runArgs;
    descriptor: [Ljava/lang/String;
    flags: (0x0012) ACC_PRIVATE, ACC_FINAL

  private final java.lang.ClassLoader loader;
    descriptor: Ljava/lang/ClassLoader;
    flags: (0x0012) ACC_PRIVATE, ACC_FINAL

  private final scala.collection.immutable.Set<java.lang.String> tagsToInclude;
    descriptor: Lscala/collection/immutable/Set;
    flags: (0x0012) ACC_PRIVATE, ACC_FINAL
    Signature: #46                          // Lscala/collection/immutable/Set<Ljava/lang/String;>;

  private final scala.collection.immutable.Set<java.lang.String> tagsToExclude;
    descriptor: Lscala/collection/immutable/Set;
    flags: (0x0012) ACC_PRIVATE, ACC_FINAL
    Signature: #46                          // Lscala/collection/immutable/Set<Ljava/lang/String;>;

  private final scala.collection.immutable.List<java.lang.String> membersOnly;
    descriptor: Lscala/collection/immutable/List;
    flags: (0x0012) ACC_PRIVATE, ACC_FINAL
    Signature: #50                          // Lscala/collection/immutable/List<Ljava/lang/String;>;

  private final scala.collection.immutable.List<java.lang.String> wildcard;
    descriptor: Lscala/collection/immutable/List;
    flags: (0x0012) ACC_PRIVATE, ACC_FINAL
    Signature: #50                          // Lscala/collection/immutable/List<Ljava/lang/String;>;

  private final scala.collection.immutable.List<sbt.testing.Selector> autoSelectors;
    descriptor: Lscala/collection/immutable/List;
    flags: (0x0012) ACC_PRIVATE, ACC_FINAL
    Signature: #53                          // Lscala/collection/immutable/List<Lsbt/testing/Selector;>;

  private final org.scalatest.ConfigMap configMap;
    descriptor: Lorg/scalatest/ConfigMap;
    flags: (0x0012) ACC_PRIVATE, ACC_FINAL

  private final org.scalatest.tools.ReporterConfigurations repConfig;
    descriptor: Lorg/scalatest/tools/ReporterConfigurations;
    flags: (0x0012) ACC_PRIVATE, ACC_FINAL

  private final boolean useSbtLogInfoReporter;
    descriptor: Z
    flags: (0x0012) ACC_PRIVATE, ACC_FINAL

  private final boolean presentAllDurations;
    descriptor: Z
    flags: (0x0012) ACC_PRIVATE, ACC_FINAL

  private final boolean presentInColor;
    descriptor: Z
    flags: (0x0012) ACC_PRIVATE, ACC_FINAL

  private final boolean presentShortStackTraces;
    descriptor: Z
    flags: (0x0012) ACC_PRIVATE, ACC_FINAL

  private final boolean presentFullStackTraces;
    descriptor: Z
    flags: (0x0012) ACC_PRIVATE, ACC_FINAL

  private final boolean presentUnformatted;
    descriptor: Z
    flags: (0x0012) ACC_PRIVATE, ACC_FINAL

  private final boolean presentReminder;
    descriptor: Z
    flags: (0x0012) ACC_PRIVATE, ACC_FINAL

  private final boolean presentReminderWithShortStackTraces;
    descriptor: Z
    flags: (0x0012) ACC_PRIVATE, ACC_FINAL

  private final boolean presentReminderWithFullStackTraces;
    descriptor: Z
    flags: (0x0012) ACC_PRIVATE, ACC_FINAL

  private final boolean presentReminderWithoutCanceledTests;
    descriptor: Z
    flags: (0x0012) ACC_PRIVATE, ACC_FINAL

  private final boolean presentFilePathname;
    descriptor: Z
    flags: (0x0012) ACC_PRIVATE, ACC_FINAL

  private final boolean presentJson;
    descriptor: Z
    flags: (0x0012) ACC_PRIVATE, ACC_FINAL

  private final scala.collection.immutable.Set<org.scalatest.tools.ReporterConfigParam> configSet;
    descriptor: Lscala/collection/immutable/Set;
    flags: (0x0012) ACC_PRIVATE, ACC_FINAL
    Signature: #72                          // Lscala/collection/immutable/Set<Lorg/scalatest/tools/ReporterConfigParam;>;

  private final java.util.concurrent.atomic.AtomicBoolean isDone;
    descriptor: Ljava/util/concurrent/atomic/AtomicBoolean;
    flags: (0x0012) ACC_PRIVATE, ACC_FINAL

  private final java.util.concurrent.atomic.AtomicReference<scala.Option<java.lang.Thread>> serverThread;
    descriptor: Ljava/util/concurrent/atomic/AtomicReference;
    flags: (0x0012) ACC_PRIVATE, ACC_FINAL
    Signature: #77                          // Ljava/util/concurrent/atomic/AtomicReference<Lscala/Option<Ljava/lang/Thread;>;>;

  private final java.util.concurrent.LinkedBlockingQueue<org.scalatest.Status> statusList;
    descriptor: Ljava/util/concurrent/LinkedBlockingQueue;
    flags: (0x0012) ACC_PRIVATE, ACC_FINAL
    Signature: #80                          // Ljava/util/concurrent/LinkedBlockingQueue<Lorg/scalatest/Status;>;

  private final org.scalatest.Tracker tracker;
    descriptor: Lorg/scalatest/Tracker;
    flags: (0x0012) ACC_PRIVATE, ACC_FINAL

  private final org.scalatest.tools.Framework$SummaryCounter summaryCounter;
    descriptor: Lorg/scalatest/tools/Framework$SummaryCounter;
    flags: (0x0012) ACC_PRIVATE, ACC_FINAL

  private final long runStartTime;
    descriptor: J
    flags: (0x0012) ACC_PRIVATE, ACC_FINAL

  private final org.scalatest.DispatchReporter dispatchReporter;
    descriptor: Lorg/scalatest/DispatchReporter;
    flags: (0x0012) ACC_PRIVATE, ACC_FINAL

  private final org.scalatest.tools.SuiteSortingReporter suiteSortingReporter;
    descriptor: Lorg/scalatest/tools/SuiteSortingReporter;
    flags: (0x0012) ACC_PRIVATE, ACC_FINAL

  private final java.util.concurrent.atomic.AtomicInteger org$scalatest$tools$Framework$ScalaTestRunner$$atomicThreadCounter;
    descriptor: Ljava/util/concurrent/atomic/AtomicInteger;
    flags: (0x0012) ACC_PRIVATE, ACC_FINAL

  private final java.util.concurrent.ThreadFactory threadFactory;
    descriptor: Ljava/util/concurrent/ThreadFactory;
    flags: (0x0012) ACC_PRIVATE, ACC_FINAL

  private final int poolSize;
    descriptor: I
    flags: (0x0012) ACC_PRIVATE, ACC_FINAL

  private final java.util.concurrent.ExecutorService execSvc;
    descriptor: Ljava/util/concurrent/ExecutorService;
    flags: (0x0012) ACC_PRIVATE, ACC_FINAL

  public final org.scalatest.tools.Framework $outer;
    descriptor: Lorg/scalatest/tools/Framework;
    flags: (0x1011) ACC_PUBLIC, ACC_FINAL, ACC_SYNTHETIC

  public org.scalatest.tools.ReporterConfigurations repConfig();
    descriptor: ()Lorg/scalatest/tools/ReporterConfigurations;
    flags: (0x0001) ACC_PUBLIC
    Code:
      stack=1, locals=1, args_size=1
         0: aload_0
         1: getfield      #103                // Field repConfig:Lorg/scalatest/tools/ReporterConfigurations;
         4: areturn
      LineNumberTable:
        line 643: 0
      LocalVariableTable:
        Start  Length  Slot  Name   Signature
            0       5     0  this   Lorg/scalatest/tools/Framework$ScalaTestRunner;

  public boolean useSbtLogInfoReporter();
    descriptor: ()Z
    flags: (0x0001) ACC_PUBLIC
    Code:
      stack=1, locals=1, args_size=1
         0: aload_0
         1: getfield      #108                // Field useSbtLogInfoReporter:Z
         4: ireturn
      LineNumberTable:
        line 644: 0
      LocalVariableTable:
        Start  Length  Slot  Name   Signature
            0       5     0  this   Lorg/scalatest/tools/Framework$ScalaTestRunner;

  public boolean presentAllDurations();
    descriptor: ()Z
    flags: (0x0001) ACC_PUBLIC
    Code:
      stack=1, locals=1, args_size=1
         0: aload_0
         1: getfield      #110                // Field presentAllDurations:Z
         4: ireturn
      LineNumberTable:
        line 645: 0
      LocalVariableTable:
        Start  Length  Slot  Name   Signature
            0       5     0  this   Lorg/scalatest/tools/Framework$ScalaTestRunner;

  public boolean presentInColor();
    descriptor: ()Z
    flags: (0x0001) ACC_PUBLIC
    Code:
      stack=1, locals=1, args_size=1
         0: aload_0
         1: getfield      #112                // Field presentInColor:Z
         4: ireturn
      LineNumberTable:
        line 646: 0
      LocalVariableTable:
        Start  Length  Slot  Name   Signature
            0       5     0  this   Lorg/scalatest/tools/Framework$ScalaTestRunner;

  public boolean presentShortStackTraces();
    descriptor: ()Z
    flags: (0x0001) ACC_PUBLIC
    Code:
      stack=1, locals=1, args_size=1
         0: aload_0
         1: getfield      #114                // Field presentShortStackTraces:Z
         4: ireturn
      LineNumberTable:
        line 647: 0
      LocalVariableTable:
        Start  Length  Slot  Name   Signature
            0       5     0  this   Lorg/scalatest/tools/Framework$ScalaTestRunner;

  public boolean presentFullStackTraces();
    descriptor: ()Z
    flags: (0x0001) ACC_PUBLIC
    Code:
      stack=1, locals=1, args_size=1
         0: aload_0
         1: getfield      #116                // Field presentFullStackTraces:Z
         4: ireturn
      LineNumberTable:
        line 648: 0
      LocalVariableTable:
        Start  Length  Slot  Name   Signature
            0       5     0  this   Lorg/scalatest/tools/Framework$ScalaTestRunner;

  public boolean presentUnformatted();
    descriptor: ()Z
    flags: (0x0001) ACC_PUBLIC
    Code:
      stack=1, locals=1, args_size=1
         0: aload_0
         1: getfield      #118                // Field presentUnformatted:Z
         4: ireturn
      LineNumberTable:
        line 649: 0
      LocalVariableTable:
        Start  Length  Slot  Name   Signature
            0       5     0  this   Lorg/scalatest/tools/Framework$ScalaTestRunner;

  public boolean presentReminder();
    descriptor: ()Z
    flags: (0x0001) ACC_PUBLIC
    Code:
      stack=1, locals=1, args_size=1
         0: aload_0
         1: getfield      #120                // Field presentReminder:Z
         4: ireturn
      LineNumberTable:
        line 650: 0
      LocalVariableTable:
        Start  Length  Slot  Name   Signature
            0       5     0  this   Lorg/scalatest/tools/Framework$ScalaTestRunner;

  public boolean presentReminderWithShortStackTraces();
    descriptor: ()Z
    flags: (0x0001) ACC_PUBLIC
    Code:
      stack=1, locals=1, args_size=1
         0: aload_0
         1: getfield      #122                // Field presentReminderWithShortStackTraces:Z
         4: ireturn
      LineNumberTable:
        line 651: 0
      LocalVariableTable:
        Start  Length  Slot  Name   Signature
            0       5     0  this   Lorg/scalatest/tools/Framework$ScalaTestRunner;

  public boolean presentReminderWithFullStackTraces();
    descriptor: ()Z
    flags: (0x0001) ACC_PUBLIC
    Code:
      stack=1, locals=1, args_size=1
         0: aload_0
         1: getfield      #124                // Field presentReminderWithFullStackTraces:Z
         4: ireturn
      LineNumberTable:
        line 652: 0
      LocalVariableTable:
        Start  Length  Slot  Name   Signature
            0       5     0  this   Lorg/scalatest/tools/Framework$ScalaTestRunner;

  public boolean presentReminderWithoutCanceledTests();
    descriptor: ()Z
    flags: (0x0001) ACC_PUBLIC
    Code:
      stack=1, locals=1, args_size=1
         0: aload_0
         1: getfield      #126                // Field presentReminderWithoutCanceledTests:Z
         4: ireturn
      LineNumberTable:
        line 653: 0
      LocalVariableTable:
        Start  Length  Slot  Name   Signature
            0       5     0  this   Lorg/scalatest/tools/Framework$ScalaTestRunner;

  public boolean presentFilePathname();
    descriptor: ()Z
    flags: (0x0001) ACC_PUBLIC
    Code:
      stack=1, locals=1, args_size=1
         0: aload_0
         1: getfield      #128                // Field presentFilePathname:Z
         4: ireturn
      LineNumberTable:
        line 654: 0
      LocalVariableTable:
        Start  Length  Slot  Name   Signature
            0       5     0  this   Lorg/scalatest/tools/Framework$ScalaTestRunner;

  public boolean presentJson();
    descriptor: ()Z
    flags: (0x0001) ACC_PUBLIC
    Code:
      stack=1, locals=1, args_size=1
         0: aload_0
         1: getfield      #130                // Field presentJson:Z
         4: ireturn
      LineNumberTable:
        line 655: 0
      LocalVariableTable:
        Start  Length  Slot  Name   Signature
            0       5     0  this   Lorg/scalatest/tools/Framework$ScalaTestRunner;

  public scala.collection.immutable.Set<org.scalatest.tools.ReporterConfigParam> configSet();
    descriptor: ()Lscala/collection/immutable/Set;
    flags: (0x0001) ACC_PUBLIC
    Code:
      stack=1, locals=1, args_size=1
         0: aload_0
         1: getfield      #134                // Field configSet:Lscala/collection/immutable/Set;
         4: areturn
      LineNumberTable:
        line 656: 0
      LocalVariableTable:
        Start  Length  Slot  Name   Signature
            0       5     0  this   Lorg/scalatest/tools/Framework$ScalaTestRunner;
    Signature: #132                         // ()Lscala/collection/immutable/Set<Lorg/scalatest/tools/ReporterConfigParam;>;

  public java.util.concurrent.atomic.AtomicBoolean isDone();
    descriptor: ()Ljava/util/concurrent/atomic/AtomicBoolean;
    flags: (0x0001) ACC_PUBLIC
    Code:
      stack=1, locals=1, args_size=1
         0: aload_0
         1: getfield      #137                // Field isDone:Ljava/util/concurrent/atomic/AtomicBoolean;
         4: areturn
      LineNumberTable:
        line 663: 0
      LocalVariableTable:
        Start  Length  Slot  Name   Signature
            0       5     0  this   Lorg/scalatest/tools/Framework$ScalaTestRunner;

  public java.util.concurrent.atomic.AtomicReference<scala.Option<java.lang.Thread>> serverThread();
    descriptor: ()Ljava/util/concurrent/atomic/AtomicReference;
    flags: (0x0001) ACC_PUBLIC
    Code:
      stack=1, locals=1, args_size=1
         0: aload_0
         1: getfield      #141                // Field serverThread:Ljava/util/concurrent/atomic/AtomicReference;
         4: areturn
      LineNumberTable:
        line 664: 0
      LocalVariableTable:
        Start  Length  Slot  Name   Signature
            0       5     0  this   Lorg/scalatest/tools/Framework$ScalaTestRunner;
    Signature: #139                         // ()Ljava/util/concurrent/atomic/AtomicReference<Lscala/Option<Ljava/lang/Thread;>;>;

  public java.util.concurrent.LinkedBlockingQueue<org.scalatest.Status> statusList();
    descriptor: ()Ljava/util/concurrent/LinkedBlockingQueue;
    flags: (0x0001) ACC_PUBLIC
    Code:
      stack=1, locals=1, args_size=1
         0: aload_0
         1: getfield      #145                // Field statusList:Ljava/util/concurrent/LinkedBlockingQueue;
         4: areturn
      LineNumberTable:
        line 665: 0
      LocalVariableTable:
        Start  Length  Slot  Name   Signature
            0       5     0  this   Lorg/scalatest/tools/Framework$ScalaTestRunner;
    Signature: #143                         // ()Ljava/util/concurrent/LinkedBlockingQueue<Lorg/scalatest/Status;>;

  public org.scalatest.Tracker tracker();
    descriptor: ()Lorg/scalatest/Tracker;
    flags: (0x0001) ACC_PUBLIC
    Code:
      stack=1, locals=1, args_size=1
         0: aload_0
         1: getfield      #148                // Field tracker:Lorg/scalatest/Tracker;
         4: areturn
      LineNumberTable:
        line 666: 0
      LocalVariableTable:
        Start  Length  Slot  Name   Signature
            0       5     0  this   Lorg/scalatest/tools/Framework$ScalaTestRunner;

  public org.scalatest.tools.Framework$SummaryCounter summaryCounter();
    descriptor: ()Lorg/scalatest/tools/Framework$SummaryCounter;
    flags: (0x0001) ACC_PUBLIC
    Code:
      stack=1, locals=1, args_size=1
         0: aload_0
         1: getfield      #151                // Field summaryCounter:Lorg/scalatest/tools/Framework$SummaryCounter;
         4: areturn
      LineNumberTable:
        line 667: 0
      LocalVariableTable:
        Start  Length  Slot  Name   Signature
            0       5     0  this   Lorg/scalatest/tools/Framework$ScalaTestRunner;

  public long runStartTime();
    descriptor: ()J
    flags: (0x0001) ACC_PUBLIC
    Code:
      stack=2, locals=1, args_size=1
         0: aload_0
         1: getfield      #154                // Field runStartTime:J
         4: lreturn
      LineNumberTable:
        line 668: 0
      LocalVariableTable:
        Start  Length  Slot  Name   Signature
            0       5     0  this   Lorg/scalatest/tools/Framework$ScalaTestRunner;

  public org.scalatest.DispatchReporter dispatchReporter();
    descriptor: ()Lorg/scalatest/DispatchReporter;
    flags: (0x0001) ACC_PUBLIC
    Code:
      stack=1, locals=1, args_size=1
         0: aload_0
         1: getfield      #157                // Field dispatchReporter:Lorg/scalatest/DispatchReporter;
         4: areturn
      LineNumberTable:
        line 670: 0
      LocalVariableTable:
        Start  Length  Slot  Name   Signature
            0       5     0  this   Lorg/scalatest/tools/Framework$ScalaTestRunner;

  public org.scalatest.tools.SuiteSortingReporter suiteSortingReporter();
    descriptor: ()Lorg/scalatest/tools/SuiteSortingReporter;
    flags: (0x0001) ACC_PUBLIC
    Code:
      stack=1, locals=1, args_size=1
         0: aload_0
         1: getfield      #160                // Field suiteSortingReporter:Lorg/scalatest/tools/SuiteSortingReporter;
         4: areturn
      LineNumberTable:
        line 672: 0
      LocalVariableTable:
        Start  Length  Slot  Name   Signature
            0       5     0  this   Lorg/scalatest/tools/Framework$ScalaTestRunner;

  public java.util.concurrent.atomic.AtomicInteger org$scalatest$tools$Framework$ScalaTestRunner$$atomicThreadCounter();
    descriptor: ()Ljava/util/concurrent/atomic/AtomicInteger;
    flags: (0x0001) ACC_PUBLIC
    Code:
      stack=1, locals=1, args_size=1
         0: aload_0
         1: getfield      #163                // Field org$scalatest$tools$Framework$ScalaTestRunner$$atomicThreadCounter:Ljava/util/concurrent/atomic/AtomicInteger;
         4: areturn
      LineNumberTable:
        line 683: 0
      LocalVariableTable:
        Start  Length  Slot  Name   Signature
            0       5     0  this   Lorg/scalatest/tools/Framework$ScalaTestRunner;

  public java.util.concurrent.ThreadFactory threadFactory();
    descriptor: ()Ljava/util/concurrent/ThreadFactory;
    flags: (0x0001) ACC_PUBLIC
    Code:
      stack=1, locals=1, args_size=1
         0: aload_0
         1: getfield      #166                // Field threadFactory:Ljava/util/concurrent/ThreadFactory;
         4: areturn
      LineNumberTable:
        line 685: 0
      LocalVariableTable:
        Start  Length  Slot  Name   Signature
            0       5     0  this   Lorg/scalatest/tools/Framework$ScalaTestRunner;

  public int poolSize();
    descriptor: ()I
    flags: (0x0001) ACC_PUBLIC
    Code:
      stack=1, locals=1, args_size=1
         0: aload_0
         1: getfield      #169                // Field poolSize:I
         4: ireturn
      LineNumberTable:
        line 695: 0
      LocalVariableTable:
        Start  Length  Slot  Name   Signature
            0       5     0  this   Lorg/scalatest/tools/Framework$ScalaTestRunner;

  public java.util.concurrent.ExecutorService execSvc();
    descriptor: ()Ljava/util/concurrent/ExecutorService;
    flags: (0x0001) ACC_PUBLIC
    Code:
      stack=1, locals=1, args_size=1
         0: aload_0
         1: getfield      #172                // Field execSvc:Ljava/util/concurrent/ExecutorService;
         4: areturn
      LineNumberTable:
        line 701: 0
      LocalVariableTable:
        Start  Length  Slot  Name   Signature
            0       5     0  this   Lorg/scalatest/tools/Framework$ScalaTestRunner;

  private org.scalatest.tools.Framework$ScalaTestTask createTask(sbt.testing.TaskDef);
    descriptor: (Lsbt/testing/TaskDef;)Lorg/scalatest/tools/Framework$ScalaTestTask;
    flags: (0x0002) ACC_PRIVATE
    Code:
      stack=28, locals=2, args_size=2
         0: new           #25                 // class org/scalatest/tools/Framework$ScalaTestTask
         3: dup
         4: aload_0
         5: invokevirtual #179                // Method org$scalatest$tools$Framework$ScalaTestRunner$$$outer:()Lorg/scalatest/tools/Framework;
         8: aload_1
         9: aload_0
        10: getfield      #181                // Field loader:Ljava/lang/ClassLoader;
        13: aload_0
        14: invokevirtual #183                // Method suiteSortingReporter:()Lorg/scalatest/tools/SuiteSortingReporter;
        17: aload_0
        18: invokevirtual #185                // Method tracker:()Lorg/scalatest/Tracker;
        21: aload_0
        22: getfield      #187                // Field tagsToInclude:Lscala/collection/immutable/Set;
        25: aload_0
        26: getfield      #189                // Field tagsToExclude:Lscala/collection/immutable/Set;
        29: getstatic     #195                // Field scala/collection/ArrayOps$.MODULE$:Lscala/collection/ArrayOps$;
        32: getstatic     #200                // Field scala/Predef$.MODULE$:Lscala/Predef$;
        35: aload_1
        36: invokevirtual #206                // Method sbt/testing/TaskDef.selectors:()[Lsbt/testing/Selector;
        39: checkcast     #208                // class "[Ljava/lang/Object;"
        42: invokevirtual #212                // Method scala/Predef$.refArrayOps:([Ljava/lang/Object;)Ljava/lang/Object;
        45: aload_0
        46: getfield      #214                // Field autoSelectors:Lscala/collection/immutable/List;
        49: getstatic     #219                // Field scala/reflect/ClassTag$.MODULE$:Lscala/reflect/ClassTag$;
        52: ldc           #221                // class sbt/testing/Selector
        54: invokevirtual #225                // Method scala/reflect/ClassTag$.apply:(Ljava/lang/Class;)Lscala/reflect/ClassTag;
        57: invokevirtual #229                // Method scala/collection/ArrayOps$.$plus$plus$extension:(Ljava/lang/Object;Lscala/collection/IterableOnce;Lscala/reflect/ClassTag;)Ljava/lang/Object;
        60: checkcast     #231                // class "[Lsbt/testing/Selector;"
        63: aload_1
        64: invokevirtual #234                // Method sbt/testing/TaskDef.explicitlySpecified:()Z
        67: aload_0
        68: getfield      #236                // Field configMap:Lorg/scalatest/ConfigMap;
        71: aload_0
        72: invokevirtual #238                // Method summaryCounter:()Lorg/scalatest/tools/Framework$SummaryCounter;
        75: aload_0
        76: invokevirtual #240                // Method statusList:()Ljava/util/concurrent/LinkedBlockingQueue;
        79: aload_0
        80: invokevirtual #242                // Method useSbtLogInfoReporter:()Z
        83: aload_0
        84: invokevirtual #244                // Method presentAllDurations:()Z
        87: aload_0
        88: invokevirtual #246                // Method presentInColor:()Z
        91: aload_0
        92: invokevirtual #248                // Method presentShortStackTraces:()Z
        95: aload_0
        96: invokevirtual #250                // Method presentFullStackTraces:()Z
        99: aload_0
       100: invokevirtual #252                // Method presentUnformatted:()Z
       103: aload_0
       104: invokevirtual #254                // Method presentReminder:()Z
       107: aload_0
       108: invokevirtual #256                // Method presentReminderWithShortStackTraces:()Z
       111: aload_0
       112: invokevirtual #258                // Method presentReminderWithFullStackTraces:()Z
       115: aload_0
       116: invokevirtual #260                // Method presentReminderWithoutCanceledTests:()Z
       119: aload_0
       120: invokevirtual #262                // Method presentFilePathname:()Z
       123: aload_0
       124: invokevirtual #264                // Method presentJson:()Z
       127: aload_0
       128: invokevirtual #266                // Method configSet:()Lscala/collection/immutable/Set;
       131: aload_0
       132: invokevirtual #268                // Method execSvc:()Ljava/util/concurrent/ExecutorService;
       135: invokespecial #272                // Method org/scalatest/tools/Framework$ScalaTestTask."<init>":(Lorg/scalatest/tools/Framework;Lsbt/testing/TaskDef;Ljava/lang/ClassLoader;Lorg/scalatest/tools/SuiteSortingReporter;Lorg/scalatest/Tracker;Lscala/collection/immutable/Set;Lscala/collection/immutable/Set;[Lsbt/testing/Selector;ZLorg/scalatest/ConfigMap;Lorg/scalatest/tools/Framework$SummaryCounter;Ljava/util/concurrent/LinkedBlockingQueue;ZZZZZZZZZZZZLscala/collection/immutable/Set;Ljava/util/concurrent/ExecutorService;)V
       138: areturn
      LineNumberTable:
        line 708: 0
        line 709: 8
        line 710: 9
        line 711: 13
        line 712: 17
        line 713: 21
        line 714: 25
        line 715: 32
        line 716: 63
        line 717: 67
        line 718: 71
        line 719: 75
        line 720: 79
        line 721: 83
        line 722: 87
        line 723: 91
        line 724: 95
        line 725: 99
        line 726: 103
        line 727: 107
        line 728: 111
        line 729: 115
        line 730: 119
        line 731: 123
        line 732: 127
        line 733: 131
      LocalVariableTable:
        Start  Length  Slot  Name   Signature
            0     139     0  this   Lorg/scalatest/tools/Framework$ScalaTestRunner;
            0     139     1    td   Lsbt/testing/TaskDef;
    MethodParameters:
      Name                           Flags
      td                             final

  private sbt.testing.TaskDef[] filterWildcard(scala.collection.immutable.List<java.lang.String>, sbt.testing.TaskDef[]);
    descriptor: (Lscala/collection/immutable/List;[Lsbt/testing/TaskDef;)[Lsbt/testing/TaskDef;
    flags: (0x0002) ACC_PRIVATE
    Code:
      stack=3, locals=3, args_size=3
         0: getstatic     #195                // Field scala/collection/ArrayOps$.MODULE$:Lscala/collection/ArrayOps$;
         3: getstatic     #200                // Field scala/Predef$.MODULE$:Lscala/Predef$;
         6: aload_2
         7: checkcast     #208                // class "[Ljava/lang/Object;"
        10: invokevirtual #212                // Method scala/Predef$.refArrayOps:([Ljava/lang/Object;)Ljava/lang/Object;
        13: aload_1
        14: invokedynamic #299,  0            // InvokeDynamic #0:apply:(Lscala/collection/immutable/List;)Lscala/Function1;
        19: invokevirtual #303                // Method scala/collection/ArrayOps$.filter$extension:(Ljava/lang/Object;Lscala/Function1;)Ljava/lang/Object;
        22: checkcast     #305                // class "[Lsbt/testing/TaskDef;"
        25: areturn
      LineNumberTable:
        line 737: 3
      LocalVariableTable:
        Start  Length  Slot  Name   Signature
            0      26     0  this   Lorg/scalatest/tools/Framework$ScalaTestRunner;
            0      26     1 paths   Lscala/collection/immutable/List;
            0      26     2 taskDefs   [Lsbt/testing/TaskDef;
    Signature: #276                         // (Lscala/collection/immutable/List<Ljava/lang/String;>;[Lsbt/testing/TaskDef;)[Lsbt/testing/TaskDef;
    MethodParameters:
      Name                           Flags
      paths                          final
      taskDefs                       final

  private sbt.testing.TaskDef[] filterMembersOnly(scala.collection.immutable.List<java.lang.String>, sbt.testing.TaskDef[]);
    descriptor: (Lscala/collection/immutable/List;[Lsbt/testing/TaskDef;)[Lsbt/testing/TaskDef;
    flags: (0x0002) ACC_PRIVATE
    Code:
      stack=3, locals=3, args_size=3
         0: getstatic     #195                // Field scala/collection/ArrayOps$.MODULE$:Lscala/collection/ArrayOps$;
         3: getstatic     #200                // Field scala/Predef$.MODULE$:Lscala/Predef$;
         6: aload_2
         7: checkcast     #208                // class "[Ljava/lang/Object;"
        10: invokevirtual #212                // Method scala/Predef$.refArrayOps:([Ljava/lang/Object;)Ljava/lang/Object;
        13: aload_1
        14: invokedynamic #311,  0            // InvokeDynamic #1:apply:(Lscala/collection/immutable/List;)Lscala/Function1;
        19: invokevirtual #303                // Method scala/collection/ArrayOps$.filter$extension:(Ljava/lang/Object;Lscala/Function1;)Ljava/lang/Object;
        22: checkcast     #305                // class "[Lsbt/testing/TaskDef;"
        25: areturn
      LineNumberTable:
        line 740: 3
      LocalVariableTable:
        Start  Length  Slot  Name   Signature
            0      26     0  this   Lorg/scalatest/tools/Framework$ScalaTestRunner;
            0      26     1 paths   Lscala/collection/immutable/List;
            0      26     2 taskDefs   [Lsbt/testing/TaskDef;
    Signature: #276                         // (Lscala/collection/immutable/List<Ljava/lang/String;>;[Lsbt/testing/TaskDef;)[Lsbt/testing/TaskDef;
    MethodParameters:
      Name                           Flags
      paths                          final
      taskDefs                       final

  public sbt.testing.Task[] tasks(sbt.testing.TaskDef[]);
    descriptor: ([Lsbt/testing/TaskDef;)[Lsbt/testing/Task;
    flags: (0x0001) ACC_PUBLIC
    Code:
      stack=11, locals=2, args_size=2
         0: getstatic     #195                // Field scala/collection/ArrayOps$.MODULE$:Lscala/collection/ArrayOps$;
         3: getstatic     #200                // Field scala/Predef$.MODULE$:Lscala/Predef$;
         6: getstatic     #195                // Field scala/collection/ArrayOps$.MODULE$:Lscala/collection/ArrayOps$;
         9: getstatic     #200                // Field scala/Predef$.MODULE$:Lscala/Predef$;
        12: aload_0
        13: getfield      #315                // Field wildcard:Lscala/collection/immutable/List;
        16: invokevirtual #320                // Method scala/collection/immutable/List.isEmpty:()Z
        19: ifeq          39
        22: aload_0
        23: getfield      #322                // Field membersOnly:Lscala/collection/immutable/List;
        26: invokevirtual #320                // Method scala/collection/immutable/List.isEmpty:()Z
        29: ifeq          39
        32: aload_1
        33: checkcast     #208                // class "[Ljava/lang/Object;"
        36: goto          98
        39: getstatic     #195                // Field scala/collection/ArrayOps$.MODULE$:Lscala/collection/ArrayOps$;
        42: getstatic     #200                // Field scala/Predef$.MODULE$:Lscala/Predef$;
        45: getstatic     #195                // Field scala/collection/ArrayOps$.MODULE$:Lscala/collection/ArrayOps$;
        48: getstatic     #200                // Field scala/Predef$.MODULE$:Lscala/Predef$;
        51: aload_0
        52: aload_0
        53: getfield      #315                // Field wildcard:Lscala/collection/immutable/List;
        56: aload_1
        57: invokespecial #324                // Method filterWildcard:(Lscala/collection/immutable/List;[Lsbt/testing/TaskDef;)[Lsbt/testing/TaskDef;
        60: checkcast     #208                // class "[Ljava/lang/Object;"
        63: invokevirtual #212                // Method scala/Predef$.refArrayOps:([Ljava/lang/Object;)Ljava/lang/Object;
        66: aload_0
        67: aload_0
        68: getfield      #322                // Field membersOnly:Lscala/collection/immutable/List;
        71: aload_1
        72: invokespecial #326                // Method filterMembersOnly:(Lscala/collection/immutable/List;[Lsbt/testing/TaskDef;)[Lsbt/testing/TaskDef;
        75: getstatic     #219                // Field scala/reflect/ClassTag$.MODULE$:Lscala/reflect/ClassTag$;
        78: ldc           #202                // class sbt/testing/TaskDef
        80: invokevirtual #225                // Method scala/reflect/ClassTag$.apply:(Ljava/lang/Class;)Lscala/reflect/ClassTag;
        83: invokevirtual #329                // Method scala/collection/ArrayOps$.$plus$plus$extension:(Ljava/lang/Object;Ljava/lang/Object;Lscala/reflect/ClassTag;)Ljava/lang/Object;
        86: checkcast     #208                // class "[Ljava/lang/Object;"
        89: invokevirtual #212                // Method scala/Predef$.refArrayOps:([Ljava/lang/Object;)Ljava/lang/Object;
        92: invokevirtual #332                // Method scala/collection/ArrayOps$.distinct$extension:(Ljava/lang/Object;)Ljava/lang/Object;
        95: checkcast     #208                // class "[Ljava/lang/Object;"
        98: invokevirtual #212                // Method scala/Predef$.refArrayOps:([Ljava/lang/Object;)Ljava/lang/Object;
       101: aload_0
       102: invokedynamic #342,  0            // InvokeDynamic #2:apply:(Lorg/scalatest/tools/Framework$ScalaTestRunner;)Lscala/Function1;
       107: getstatic     #219                // Field scala/reflect/ClassTag$.MODULE$:Lscala/reflect/ClassTag$;
       110: ldc_w         #344                // class scala/Tuple2
       113: invokevirtual #225                // Method scala/reflect/ClassTag$.apply:(Ljava/lang/Class;)Lscala/reflect/ClassTag;
       116: invokevirtual #348                // Method scala/collection/ArrayOps$.map$extension:(Ljava/lang/Object;Lscala/Function1;Lscala/reflect/ClassTag;)Ljava/lang/Object;
       119: checkcast     #208                // class "[Ljava/lang/Object;"
       122: invokevirtual #212                // Method scala/Predef$.refArrayOps:([Ljava/lang/Object;)Ljava/lang/Object;
       125: invokedynamic #357,  0            // InvokeDynamic #3:apply:()Lscala/Function1;
       130: invokevirtual #361                // Method scala/collection/ArrayOps$.withFilter$extension:(Ljava/lang/Object;Lscala/Function1;)Lscala/collection/ArrayOps$WithFilter;
       133: invokedynamic #368,  0            // InvokeDynamic #4:apply:()Lscala/Function1;
       138: getstatic     #219                // Field scala/reflect/ClassTag$.MODULE$:Lscala/reflect/ClassTag$;
       141: ldc_w         #370                // class sbt/testing/Task
       144: invokevirtual #225                // Method scala/reflect/ClassTag$.apply:(Ljava/lang/Class;)Lscala/reflect/ClassTag;
       147: invokevirtual #374                // Method scala/collection/ArrayOps$WithFilter.map:(Lscala/Function1;Lscala/reflect/ClassTag;)Ljava/lang/Object;
       150: checkcast     #376                // class "[Lsbt/testing/Task;"
       153: areturn
      StackMapTable: number_of_entries = 2
        frame_type = 255 /* full_frame */
          offset_delta = 39
          locals = [ class org/scalatest/tools/Framework$ScalaTestRunner, class "[Lsbt/testing/TaskDef;" ]
          stack = [ class scala/collection/ArrayOps$, class scala/Predef$, class scala/collection/ArrayOps$, class scala/Predef$ ]
        frame_type = 255 /* full_frame */
          offset_delta = 58
          locals = [ class org/scalatest/tools/Framework$ScalaTestRunner, class "[Lsbt/testing/TaskDef;" ]
          stack = [ class scala/collection/ArrayOps$, class scala/Predef$, class scala/collection/ArrayOps$, class scala/Predef$, class "[Ljava/lang/Object;" ]
      LineNumberTable:
        line 746: 0
      LocalVariableTable:
        Start  Length  Slot  Name   Signature
            0     154     0  this   Lorg/scalatest/tools/Framework$ScalaTestRunner;
            0     154     1 taskDefs   [Lsbt/testing/TaskDef;
    MethodParameters:
      Name                           Flags
      taskDefs                       final

  public java.lang.String done();
    descriptor: ()Ljava/lang/String;
    flags: (0x0001) ACC_PUBLIC
    Code:
      stack=12, locals=9, args_size=1
         0: aload_0
         1: invokevirtual #380                // Method isDone:()Ljava/util/concurrent/atomic/AtomicBoolean;
         4: iconst_1
         5: invokevirtual #386                // Method java/util/concurrent/atomic/AtomicBoolean.getAndSet:(Z)Z
         8: ifne          413
        11: getstatic     #391                // Field scala/collection/JavaConverters$.MODULE$:Lscala/collection/JavaConverters$;
        14: aload_0
        15: invokevirtual #240                // Method statusList:()Ljava/util/concurrent/LinkedBlockingQueue;
        18: invokevirtual #395                // Method scala/collection/JavaConverters$.collectionAsScalaIterableConverter:(Ljava/util/Collection;)Lscala/collection/JavaConverters$AsScala;
        21: invokevirtual #399                // Method scala/collection/JavaConverters$AsScala.asScala:()Ljava/lang/Object;
        24: checkcast     #401                // class scala/collection/IterableOnceOps
        27: invokedynamic #408,  0            // InvokeDynamic #5:apply:()Lscala/Function1;
        32: invokeinterface #412,  2          // InterfaceMethod scala/collection/IterableOnceOps.foreach:(Lscala/Function1;)V
        37: aload_0
        38: invokevirtual #414                // Method serverThread:()Ljava/util/concurrent/atomic/AtomicReference;
        41: invokevirtual #419                // Method java/util/concurrent/atomic/AtomicReference.get:()Ljava/lang/Object;
        44: checkcast     #421                // class scala/Option
        47: astore_2
        48: aload_2
        49: instanceof    #423                // class scala/Some
        52: ifeq          81
        55: aload_2
        56: checkcast     #423                // class scala/Some
        59: astore_3
        60: aload_3
        61: invokevirtual #426                // Method scala/Some.value:()Ljava/lang/Object;
        64: checkcast     #428                // class java/lang/Thread
        67: astore        4
        69: aload         4
        71: invokevirtual #432                // Method java/lang/Thread.join:()V
        74: getstatic     #438                // Field scala/runtime/BoxedUnit.UNIT:Lscala/runtime/BoxedUnit;
        77: astore_1
        78: goto          113
        81: goto          84
        84: getstatic     #443                // Field scala/None$.MODULE$:Lscala/None$;
        87: aload_2
        88: invokevirtual #447                // Method java/lang/Object.equals:(Ljava/lang/Object;)Z
        91: ifeq          101
        94: getstatic     #438                // Field scala/runtime/BoxedUnit.UNIT:Lscala/runtime/BoxedUnit;
        97: astore_1
        98: goto          113
       101: goto          104
       104: new           #449                // class scala/MatchError
       107: dup
       108: aload_2
       109: invokespecial #452                // Method scala/MatchError."<init>":(Ljava/lang/Object;)V
       112: athrow
       113: invokestatic  #457                // Method java/lang/System.currentTimeMillis:()J
       116: aload_0
       117: invokevirtual #459                // Method runStartTime:()J
       120: lsub
       121: lstore        5
       123: new           #461                // class org/scalatest/events/Summary
       126: dup
       127: aload_0
       128: invokevirtual #238                // Method summaryCounter:()Lorg/scalatest/tools/Framework$SummaryCounter;
       131: invokevirtual #464                // Method org/scalatest/tools/Framework$SummaryCounter.testsSucceededCount:()Ljava/util/concurrent/atomic/AtomicInteger;
       134: invokevirtual #468                // Method java/util/concurrent/atomic/AtomicInteger.get:()I
       137: aload_0
       138: invokevirtual #238                // Method summaryCounter:()Lorg/scalatest/tools/Framework$SummaryCounter;
       141: invokevirtual #471                // Method org/scalatest/tools/Framework$SummaryCounter.testsFailedCount:()Ljava/util/concurrent/atomic/AtomicInteger;
       144: invokevirtual #468                // Method java/util/concurrent/atomic/AtomicInteger.get:()I
       147: aload_0
       148: invokevirtual #238                // Method summaryCounter:()Lorg/scalatest/tools/Framework$SummaryCounter;
       151: invokevirtual #474                // Method org/scalatest/tools/Framework$SummaryCounter.testsIgnoredCount:()Ljava/util/concurrent/atomic/AtomicInteger;
       154: invokevirtual #468                // Method java/util/concurrent/atomic/AtomicInteger.get:()I
       157: aload_0
       158: invokevirtual #238                // Method summaryCounter:()Lorg/scalatest/tools/Framework$SummaryCounter;
       161: invokevirtual #477                // Method org/scalatest/tools/Framework$SummaryCounter.testsPendingCount:()Ljava/util/concurrent/atomic/AtomicInteger;
       164: invokevirtual #468                // Method java/util/concurrent/atomic/AtomicInteger.get:()I
       167: aload_0
       168: invokevirtual #238                // Method summaryCounter:()Lorg/scalatest/tools/Framework$SummaryCounter;
       171: invokevirtual #480                // Method org/scalatest/tools/Framework$SummaryCounter.testsCanceledCount:()Ljava/util/concurrent/atomic/AtomicInteger;
       174: invokevirtual #468                // Method java/util/concurrent/atomic/AtomicInteger.get:()I
       177: aload_0
       178: invokevirtual #238                // Method summaryCounter:()Lorg/scalatest/tools/Framework$SummaryCounter;
       181: invokevirtual #483                // Method org/scalatest/tools/Framework$SummaryCounter.suitesCompletedCount:()Ljava/util/concurrent/atomic/AtomicInteger;
       184: invokevirtual #468                // Method java/util/concurrent/atomic/AtomicInteger.get:()I
       187: aload_0
       188: invokevirtual #238                // Method summaryCounter:()Lorg/scalatest/tools/Framework$SummaryCounter;
       191: invokevirtual #486                // Method org/scalatest/tools/Framework$SummaryCounter.suitesAbortedCount:()Ljava/util/concurrent/atomic/AtomicInteger;
       194: invokevirtual #468                // Method java/util/concurrent/atomic/AtomicInteger.get:()I
       197: aload_0
       198: invokevirtual #238                // Method summaryCounter:()Lorg/scalatest/tools/Framework$SummaryCounter;
       201: invokevirtual #489                // Method org/scalatest/tools/Framework$SummaryCounter.scopesPendingCount:()Ljava/util/concurrent/atomic/AtomicInteger;
       204: invokevirtual #468                // Method java/util/concurrent/atomic/AtomicInteger.get:()I
       207: invokespecial #492                // Method org/scalatest/events/Summary."<init>":(IIIIIIII)V
       210: astore        7
       212: aload_0
       213: invokevirtual #494                // Method dispatchReporter:()Lorg/scalatest/DispatchReporter;
       216: new           #496                // class org/scalatest/events/RunCompleted
       219: dup
       220: aload_0
       221: invokevirtual #185                // Method tracker:()Lorg/scalatest/Tracker;
       224: invokevirtual #502                // Method org/scalatest/Tracker.nextOrdinal:()Lorg/scalatest/events/Ordinal;
       227: new           #423                // class scala/Some
       230: dup
       231: lload         5
       233: invokestatic  #508                // Method scala/runtime/BoxesRunTime.boxToLong:(J)Ljava/lang/Long;
       236: invokespecial #509                // Method scala/Some."<init>":(Ljava/lang/Object;)V
       239: new           #423                // class scala/Some
       242: dup
       243: aload         7
       245: invokespecial #509                // Method scala/Some."<init>":(Ljava/lang/Object;)V
       248: getstatic     #514                // Field org/scalatest/events/RunCompleted$.MODULE$:Lorg/scalatest/events/RunCompleted$;
       251: invokevirtual #518                // Method org/scalatest/events/RunCompleted$.apply$default$4:()Lscala/Option;
       254: getstatic     #514                // Field org/scalatest/events/RunCompleted$.MODULE$:Lorg/scalatest/events/RunCompleted$;
       257: invokevirtual #521                // Method org/scalatest/events/RunCompleted$.apply$default$5:()Lscala/Option;
       260: getstatic     #514                // Field org/scalatest/events/RunCompleted$.MODULE$:Lorg/scalatest/events/RunCompleted$;
       263: invokevirtual #524                // Method org/scalatest/events/RunCompleted$.apply$default$6:()Lscala/Option;
       266: getstatic     #514                // Field org/scalatest/events/RunCompleted$.MODULE$:Lorg/scalatest/events/RunCompleted$;
       269: invokevirtual #527                // Method org/scalatest/events/RunCompleted$.apply$default$7:()Ljava/lang/String;
       272: getstatic     #514                // Field org/scalatest/events/RunCompleted$.MODULE$:Lorg/scalatest/events/RunCompleted$;
       275: invokevirtual #530                // Method org/scalatest/events/RunCompleted$.apply$default$8:()J
       278: invokespecial #533                // Method org/scalatest/events/RunCompleted."<init>":(Lorg/scalatest/events/Ordinal;Lscala/Option;Lscala/Option;Lscala/Option;Lscala/Option;Lscala/Option;Ljava/lang/String;J)V
       281: invokevirtual #538                // Method org/scalatest/DispatchReporter.apply:(Lorg/scalatest/events/Event;)V
       284: aload_0
       285: invokevirtual #494                // Method dispatchReporter:()Lorg/scalatest/DispatchReporter;
       288: invokevirtual #541                // Method org/scalatest/DispatchReporter.dispatchDisposeAndWaitUntilDone:()V
       291: aload_0
       292: invokevirtual #268                // Method execSvc:()Ljava/util/concurrent/ExecutorService;
       295: invokeinterface #546,  1          // InterfaceMethod java/util/concurrent/ExecutorService.shutdown:()V
       300: getstatic     #551                // Field org/scalatest/tools/StringReporter$.MODULE$:Lorg/scalatest/tools/StringReporter$;
       303: iconst_1
       304: new           #423                // class scala/Some
       307: dup
       308: lload         5
       310: invokestatic  #508                // Method scala/runtime/BoxesRunTime.boxToLong:(J)Ljava/lang/Long;
       313: invokespecial #509                // Method scala/Some."<init>":(Ljava/lang/Object;)V
       316: new           #423                // class scala/Some
       319: dup
       320: aload         7
       322: invokespecial #509                // Method scala/Some."<init>":(Ljava/lang/Object;)V
       325: getstatic     #556                // Field scala/package$.MODULE$:Lscala/package$;
       328: invokevirtual #560                // Method scala/package$.Vector:()Lscala/collection/immutable/Vector$;
       331: invokevirtual #566                // Method scala/collection/immutable/Vector$.empty:()Lscala/collection/immutable/Vector;
       334: getstatic     #391                // Field scala/collection/JavaConverters$.MODULE$:Lscala/collection/JavaConverters$;
       337: aload_0
       338: invokevirtual #238                // Method summaryCounter:()Lorg/scalatest/tools/Framework$SummaryCounter;
       341: invokevirtual #569                // Method org/scalatest/tools/Framework$SummaryCounter.reminderEventsQueue:()Ljava/util/concurrent/LinkedBlockingQueue;
       344: invokevirtual #395                // Method scala/collection/JavaConverters$.collectionAsScalaIterableConverter:(Ljava/util/Collection;)Lscala/collection/JavaConverters$AsScala;
       347: invokevirtual #399                // Method scala/collection/JavaConverters$AsScala.asScala:()Ljava/lang/Object;
       350: checkcast     #571                // class scala/collection/IterableOnce
       353: invokevirtual #577                // Method scala/collection/immutable/Vector.$plus$plus:(Lscala/collection/IterableOnce;)Ljava/lang/Object;
       356: checkcast     #573                // class scala/collection/immutable/Vector
       359: aload_0
       360: invokevirtual #244                // Method presentAllDurations:()Z
       363: aload_0
       364: invokevirtual #254                // Method presentReminder:()Z
       367: aload_0
       368: invokevirtual #256                // Method presentReminderWithShortStackTraces:()Z
       371: aload_0
       372: invokevirtual #258                // Method presentReminderWithFullStackTraces:()Z
       375: aload_0
       376: invokevirtual #260                // Method presentReminderWithoutCanceledTests:()Z
       379: aload_0
       380: invokevirtual #262                // Method presentFilePathname:()Z
       383: invokevirtual #581                // Method org/scalatest/tools/StringReporter$.summaryFragments:(ZLscala/Option;Lscala/Option;Lscala/collection/immutable/Vector;ZZZZZZ)Lscala/collection/immutable/Vector;
       386: astore        8
       388: aload         8
       390: aload_0
       391: invokedynamic #589,  0            // InvokeDynamic #6:apply:(Lorg/scalatest/tools/Framework$ScalaTestRunner;)Lscala/Function1;
       396: invokevirtual #592                // Method scala/collection/immutable/Vector.map:(Lscala/Function1;)Ljava/lang/Object;
       399: checkcast     #401                // class scala/collection/IterableOnceOps
       402: ldc_w         #594                // String \n
       405: invokeinterface #598,  2          // InterfaceMethod scala/collection/IterableOnceOps.mkString:(Ljava/lang/String;)Ljava/lang/String;
       410: goto          424
       413: new           #600                // class java/lang/IllegalStateException
       416: dup
       417: ldc_w         #602                // String done method is called twice
       420: invokespecial #605                // Method java/lang/IllegalStateException."<init>":(Ljava/lang/String;)V
       423: athrow
       424: areturn
      StackMapTable: number_of_entries = 7
        frame_type = 253 /* append */
          offset_delta = 81
          locals = [ top, class scala/Option ]
        frame_type = 2 /* same */
        frame_type = 16 /* same */
        frame_type = 2 /* same */
        frame_type = 255 /* full_frame */
          offset_delta = 8
          locals = [ class org/scalatest/tools/Framework$ScalaTestRunner, class scala/runtime/BoxedUnit, class scala/Option ]
          stack = []
        frame_type = 249 /* chop */
          offset_delta = 299
        frame_type = 255 /* full_frame */
          offset_delta = 10
          locals = [ class org/scalatest/tools/Framework$ScalaTestRunner, class scala/runtime/BoxedUnit, class scala/Option, top, top, long, class org/scalatest/events/Summary, class scala/collection/immutable/Vector ]
          stack = [ class java/lang/String ]
      LineNumberTable:
        line 752: 0
        line 755: 11
        line 764: 37
        line 765: 48
        line 767: 69
        line 765: 81
        line 768: 84
        line 764: 104
        line 771: 113
        line 772: 123
        line 773: 167
        line 774: 212
        line 775: 284
        line 777: 291
        line 780: 300
        line 781: 303
        line 782: 304
        line 783: 316
        line 784: 325
        line 785: 359
        line 786: 363
        line 787: 367
        line 788: 371
        line 789: 375
        line 790: 379
        line 792: 388
        line 795: 413
      LocalVariableTable:
        Start  Length  Slot  Name   Signature
           69      12     4 thread   Ljava/lang/Thread;
          123     287     5 duration   J
          212     198     7 summary   Lorg/scalatest/events/Summary;
          388      22     8 fragments   Lscala/collection/immutable/Vector;
            0     425     0  this   Lorg/scalatest/tools/Framework$ScalaTestRunner;

  public java.lang.String[] args();
    descriptor: ()[Ljava/lang/String;
    flags: (0x0001) ACC_PUBLIC
    Code:
      stack=1, locals=1, args_size=1
         0: aload_0
         1: getfield      #618                // Field runArgs:[Ljava/lang/String;
         4: areturn
      LineNumberTable:
        line 798: 0
      LocalVariableTable:
        Start  Length  Slot  Name   Signature
            0       5     0  this   Lorg/scalatest/tools/Framework$ScalaTestRunner;

  public java.lang.String[] remoteArgs();
    descriptor: ()[Ljava/lang/String;
    flags: (0x0001) ACC_PUBLIC
    Code:
      stack=4, locals=3, args_size=1
         0: new           #19                 // class org/scalatest/tools/Framework$ScalaTestRunner$Skeleton$1
         3: dup
         4: aload_0
         5: invokespecial #622                // Method org/scalatest/tools/Framework$ScalaTestRunner$Skeleton$1."<init>":(Lorg/scalatest/tools/Framework$ScalaTestRunner;)V
         8: astore_1
         9: new           #428                // class java/lang/Thread
        12: dup
        13: aload_1
        14: invokespecial #625                // Method java/lang/Thread."<init>":(Ljava/lang/Runnable;)V
        17: astore_2
        18: aload_2
        19: invokevirtual #628                // Method java/lang/Thread.start:()V
        22: aload_0
        23: invokevirtual #414                // Method serverThread:()Ljava/util/concurrent/atomic/AtomicReference;
        26: new           #423                // class scala/Some
        29: dup
        30: aload_2
        31: invokespecial #509                // Method scala/Some."<init>":(Ljava/lang/Object;)V
        34: invokevirtual #631                // Method java/util/concurrent/atomic/AtomicReference.set:(Ljava/lang/Object;)V
        37: iconst_2
        38: anewarray     #614                // class java/lang/String
        41: dup
        42: iconst_0
        43: ldc_w         #633                // String 127.0.0.1
        46: aastore
        47: dup
        48: iconst_1
        49: aload_1
        50: invokevirtual #636                // Method org/scalatest/tools/Framework$ScalaTestRunner$Skeleton$1.port:()I
        53: invokestatic  #642                // Method java/lang/Integer.toString:(I)Ljava/lang/String;
        56: aastore
        57: checkcast     #208                // class "[Ljava/lang/Object;"
        60: checkcast     #643                // class "[Ljava/lang/String;"
        63: areturn
      LineNumberTable:
        line 916: 0
        line 917: 9
        line 918: 18
        line 919: 22
        line 920: 37
      LocalVariableTable:
        Start  Length  Slot  Name   Signature
            9      54     1 skeleton   Lorg/scalatest/tools/Framework$ScalaTestRunner$Skeleton$1;
           18      45     2 thread   Ljava/lang/Thread;
            0      64     0  this   Lorg/scalatest/tools/Framework$ScalaTestRunner;

  public org.scalatest.tools.Framework org$scalatest$tools$Framework$ScalaTestRunner$$$outer();
    descriptor: ()Lorg/scalatest/tools/Framework;
    flags: (0x1001) ACC_PUBLIC, ACC_SYNTHETIC
    Code:
      stack=1, locals=1, args_size=1
         0: aload_0
         1: getfield      #647                // Field $outer:Lorg/scalatest/tools/Framework;
         4: areturn
      LineNumberTable:
        line 634: 0
      LocalVariableTable:
        Start  Length  Slot  Name   Signature
            0       5     0  this   Lorg/scalatest/tools/Framework$ScalaTestRunner;

  public static final boolean $anonfun$filterWildcard$2(sbt.testing.TaskDef, java.lang.String);
    descriptor: (Lsbt/testing/TaskDef;Ljava/lang/String;)Z
    flags: (0x1019) ACC_PUBLIC, ACC_STATIC, ACC_FINAL, ACC_SYNTHETIC
    Code:
      stack=2, locals=2, args_size=2
         0: aload_0
         1: invokevirtual #654                // Method sbt/testing/TaskDef.fullyQualifiedName:()Ljava/lang/String;
         4: aload_1
         5: invokevirtual #658                // Method java/lang/String.startsWith:(Ljava/lang/String;)Z
         8: ireturn
      LineNumberTable:
        line 737: 0
      LocalVariableTable:
        Start  Length  Slot  Name   Signature
            0       9     0  td$1   Lsbt/testing/TaskDef;
            0       9     1  x$15   Ljava/lang/String;
    MethodParameters:
      Name                           Flags
      td$1                           final
      x$15                           final

  public static final boolean $anonfun$filterWildcard$1(scala.collection.immutable.List, sbt.testing.TaskDef);
    descriptor: (Lscala/collection/immutable/List;Lsbt/testing/TaskDef;)Z
    flags: (0x1019) ACC_PUBLIC, ACC_STATIC, ACC_FINAL, ACC_SYNTHETIC
    Code:
      stack=2, locals=2, args_size=2
         0: aload_0
         1: aload_1
         2: invokedynamic #672,  0            // InvokeDynamic #7:apply:(Lsbt/testing/TaskDef;)Lscala/Function1;
         7: invokevirtual #676                // Method scala/collection/immutable/List.exists:(Lscala/Function1;)Z
        10: ireturn
      LineNumberTable:
        line 737: 0
      LocalVariableTable:
        Start  Length  Slot  Name   Signature
            0      11     0 paths$1   Lscala/collection/immutable/List;
            0      11     1    td   Lsbt/testing/TaskDef;
    MethodParameters:
      Name                           Flags
      paths$1                        final
      td                             final

  public static final boolean $anonfun$filterMembersOnly$2(sbt.testing.TaskDef, java.lang.String);
    descriptor: (Lsbt/testing/TaskDef;Ljava/lang/String;)Z
    flags: (0x1019) ACC_PUBLIC, ACC_STATIC, ACC_FINAL, ACC_SYNTHETIC
    Code:
      stack=2, locals=2, args_size=2
         0: aload_0
         1: invokevirtual #654                // Method sbt/testing/TaskDef.fullyQualifiedName:()Ljava/lang/String;
         4: aload_1
         5: invokevirtual #658                // Method java/lang/String.startsWith:(Ljava/lang/String;)Z
         8: ifeq          35
        11: aload_0
        12: invokevirtual #654                // Method sbt/testing/TaskDef.fullyQualifiedName:()Ljava/lang/String;
        15: aload_1
        16: invokevirtual #682                // Method java/lang/String.length:()I
        19: invokevirtual #685                // Method java/lang/String.substring:(I)Ljava/lang/String;
        22: bipush        46
        24: invokevirtual #689                // Method java/lang/String.lastIndexOf:(I)I
        27: iconst_0
        28: if_icmpgt     35
        31: iconst_1
        32: goto          36
        35: iconst_0
        36: ireturn
      StackMapTable: number_of_entries = 2
        frame_type = 35 /* same */
        frame_type = 64 /* same_locals_1_stack_item */
          stack = [ int ]
      LineNumberTable:
        line 741: 0
      LocalVariableTable:
        Start  Length  Slot  Name   Signature
            0      37     0  td$2   Lsbt/testing/TaskDef;
            0      37     1  path   Ljava/lang/String;
    MethodParameters:
      Name                           Flags
      td$2                           final
      path                           final

  public static final boolean $anonfun$filterMembersOnly$1(scala.collection.immutable.List, sbt.testing.TaskDef);
    descriptor: (Lscala/collection/immutable/List;Lsbt/testing/TaskDef;)Z
    flags: (0x1019) ACC_PUBLIC, ACC_STATIC, ACC_FINAL, ACC_SYNTHETIC
    Code:
      stack=2, locals=2, args_size=2
         0: aload_0
         1: aload_1
         2: invokedynamic #696,  0            // InvokeDynamic #8:apply:(Lsbt/testing/TaskDef;)Lscala/Function1;
         7: invokevirtual #676                // Method scala/collection/immutable/List.exists:(Lscala/Function1;)Z
        10: ireturn
      LineNumberTable:
        line 741: 0
      LocalVariableTable:
        Start  Length  Slot  Name   Signature
            0      11     0 paths$2   Lscala/collection/immutable/List;
            0      11     1    td   Lsbt/testing/TaskDef;
    MethodParameters:
      Name                           Flags
      paths$2                        final
      td                             final

  public static final scala.Tuple2 $anonfun$tasks$1(org.scalatest.tools.Framework$ScalaTestRunner, sbt.testing.TaskDef);
    descriptor: (Lorg/scalatest/tools/Framework$ScalaTestRunner;Lsbt/testing/TaskDef;)Lscala/Tuple2;
    flags: (0x1019) ACC_PUBLIC, ACC_STATIC, ACC_FINAL, ACC_SYNTHETIC
    Code:
      stack=4, locals=3, args_size=2
         0: aload_0
         1: aload_1
         2: invokespecial #700                // Method createTask:(Lsbt/testing/TaskDef;)Lorg/scalatest/tools/Framework$ScalaTestTask;
         5: astore_2
         6: new           #344                // class scala/Tuple2
         9: dup
        10: aload_1
        11: aload_2
        12: invokespecial #703                // Method scala/Tuple2."<init>":(Ljava/lang/Object;Ljava/lang/Object;)V
        15: areturn
      LineNumberTable:
        line 747: 0
        line 746: 6
        line 747: 11
      LocalVariableTable:
        Start  Length  Slot  Name   Signature
            6       9     2  task   Lorg/scalatest/tools/Framework$ScalaTestTask;
            0      16     0 $this   Lorg/scalatest/tools/Framework$ScalaTestRunner;
            0      16     1 taskDef   Lsbt/testing/TaskDef;
    MethodParameters:
      Name                           Flags
      $this                          final synthetic
      taskDef                        final

  public static final boolean $anonfun$tasks$2(scala.Tuple2);
    descriptor: (Lscala/Tuple2;)Z
    flags: (0x1019) ACC_PUBLIC, ACC_STATIC, ACC_FINAL, ACC_SYNTHETIC
    Code:
      stack=3, locals=4, args_size=1
         0: aload_0
         1: astore_2
         2: aload_2
         3: ifnull        22
         6: aload_2
         7: invokevirtual #711                // Method scala/Tuple2._2:()Ljava/lang/Object;
        10: checkcast     #25                 // class org/scalatest/tools/Framework$ScalaTestTask
        13: astore_3
        14: aload_3
        15: invokevirtual #714                // Method org/scalatest/tools/Framework$ScalaTestTask.shouldDiscover:()Z
        18: istore_1
        19: goto          34
        22: goto          25
        25: new           #449                // class scala/MatchError
        28: dup
        29: aload_2
        30: invokespecial #452                // Method scala/MatchError."<init>":(Ljava/lang/Object;)V
        33: athrow
        34: iload_1
        35: ireturn
      StackMapTable: number_of_entries = 3
        frame_type = 253 /* append */
          offset_delta = 22
          locals = [ top, class scala/Tuple2 ]
        frame_type = 2 /* same */
        frame_type = 255 /* full_frame */
          offset_delta = 8
          locals = [ class scala/Tuple2, int, class scala/Tuple2, class org/scalatest/tools/Framework$ScalaTestTask ]
          stack = []
      LineNumberTable:
        line 746: 0
        line 747: 6
        line 748: 14
        line 746: 22
      LocalVariableTable:
        Start  Length  Slot  Name   Signature
           14       8     3  task   Lorg/scalatest/tools/Framework$ScalaTestTask;
            0      36     0  x$16   Lscala/Tuple2;
    MethodParameters:
      Name                           Flags
      x$16                           final

  public static final sbt.testing.Task $anonfun$tasks$3(scala.Tuple2);
    descriptor: (Lscala/Tuple2;)Lsbt/testing/Task;
    flags: (0x1019) ACC_PUBLIC, ACC_STATIC, ACC_FINAL, ACC_SYNTHETIC
    Code:
      stack=3, locals=4, args_size=1
         0: aload_0
         1: astore_2
         2: aload_2
         3: ifnull        19
         6: aload_2
         7: invokevirtual #711                // Method scala/Tuple2._2:()Ljava/lang/Object;
        10: checkcast     #25                 // class org/scalatest/tools/Framework$ScalaTestTask
        13: astore_3
        14: aload_3
        15: astore_1
        16: goto          31
        19: goto          22
        22: new           #449                // class scala/MatchError
        25: dup
        26: aload_2
        27: invokespecial #452                // Method scala/MatchError."<init>":(Ljava/lang/Object;)V
        30: athrow
        31: aload_1
        32: areturn
      StackMapTable: number_of_entries = 3
        frame_type = 253 /* append */
          offset_delta = 19
          locals = [ top, class scala/Tuple2 ]
        frame_type = 2 /* same */
        frame_type = 255 /* full_frame */
          offset_delta = 8
          locals = [ class scala/Tuple2, class org/scalatest/tools/Framework$ScalaTestTask, class scala/Tuple2, class org/scalatest/tools/Framework$ScalaTestTask ]
          stack = []
      LineNumberTable:
        line 746: 0
        line 747: 6
        line 749: 14
        line 746: 19
      LocalVariableTable:
        Start  Length  Slot  Name   Signature
           14       5     3  task   Lorg/scalatest/tools/Framework$ScalaTestTask;
            0      33     0  x$17   Lscala/Tuple2;
    MethodParameters:
      Name                           Flags
      x$17                           final

  public static final void $anonfun$done$1(org.scalatest.Status);
    descriptor: (Lorg/scalatest/Status;)V
    flags: (0x1019) ACC_PUBLIC, ACC_STATIC, ACC_FINAL, ACC_SYNTHETIC
    Code:
      stack=1, locals=2, args_size=1
         0: aload_0
         1: invokeinterface #726,  1          // InterfaceMethod org/scalatest/Status.waitUntilCompleted:()V
         6: goto          13
         9: astore_1
        10: goto          13
        13: return
      Exception table:
         from    to  target type
             0     6     9   Class java/lang/Throwable
      StackMapTable: number_of_entries = 2
        frame_type = 73 /* same_locals_1_stack_item */
          stack = [ class java/lang/Throwable ]
        frame_type = 3 /* same */
      LineNumberTable:
        line 757: 0
        line 760: 10
      LocalVariableTable:
        Start  Length  Slot  Name   Signature
            9       1     1     t   Ljava/lang/Throwable;
            0      14     0     s   Lorg/scalatest/Status;
    MethodParameters:
      Name                           Flags
      s                              final

  public static final java.lang.String $anonfun$done$2(org.scalatest.tools.Framework$ScalaTestRunner, org.scalatest.tools.Fragment);
    descriptor: (Lorg/scalatest/tools/Framework$ScalaTestRunner;Lorg/scalatest/tools/Fragment;)Ljava/lang/String;
    flags: (0x1019) ACC_PUBLIC, ACC_STATIC, ACC_FINAL, ACC_SYNTHETIC
    Code:
      stack=2, locals=2, args_size=2
         0: aload_1
         1: aload_0
         2: invokevirtual #246                // Method presentInColor:()Z
         5: invokevirtual #736                // Method org/scalatest/tools/Fragment.toPossiblyColoredText:(Z)Ljava/lang/String;
         8: areturn
      LineNumberTable:
        line 792: 0
      LocalVariableTable:
        Start  Length  Slot  Name   Signature
            0       9     0 $this   Lorg/scalatest/tools/Framework$ScalaTestRunner;
            0       9     1  x$18   Lorg/scalatest/tools/Fragment;
    MethodParameters:
      Name                           Flags
      $this                          final synthetic
      x$18                           final

  public org.scalatest.tools.Framework$ScalaTestRunner(java.lang.String[], java.lang.ClassLoader, scala.collection.immutable.Set<java.lang.String>, scala.collection.immutable.Set<java.lang.String>, scala.collection.immutable.List<java.lang.String>, scala.collection.immutable.List<java.lang.String>, scala.collection.immutable.List<sbt.testing.Selector>, org.scalatest.ConfigMap, org.scalatest.tools.ReporterConfigurations, boolean, boolean, boolean, boolean, boolean, boolean, boolean, boolean, boolean, boolean, boolean, boolean, scala.collection.immutable.Set<org.scalatest.tools.ReporterConfigParam>, boolean, long, long, org.scalatest.tools.ConcurrentConfig, org.scalatest.time.Span);
    descriptor: (Lorg/scalatest/tools/Framework;[Ljava/lang/String;Ljava/lang/ClassLoader;Lscala/collection/immutable/Set;Lscala/collection/immutable/Set;Lscala/collection/immutable/List;Lscala/collection/immutable/List;Lscala/collection/immutable/List;Lorg/scalatest/ConfigMap;Lorg/scalatest/tools/ReporterConfigurations;ZZZZZZZZZZZZLscala/collection/immutable/Set;ZJJLorg/scalatest/tools/ConcurrentConfig;Lorg/scalatest/time/Span;)V
    flags: (0x0001) ACC_PUBLIC
    Code:
      stack=12, locals=31, args_size=29
         0: aload_0
         1: aload_2
         2: putfield      #618                // Field runArgs:[Ljava/lang/String;
         5: aload_0
         6: aload_3
         7: putfield      #181                // Field loader:Ljava/lang/ClassLoader;
        10: aload_0
        11: aload         4
        13: putfield      #187                // Field tagsToInclude:Lscala/collection/immutable/Set;
        16: aload_0
        17: aload         5
        19: putfield      #189                // Field tagsToExclude:Lscala/collection/immutable/Set;
        22: aload_0
        23: aload         6
        25: putfield      #322                // Field membersOnly:Lscala/collection/immutable/List;
        28: aload_0
        29: aload         7
        31: putfield      #315                // Field wildcard:Lscala/collection/immutable/List;
        34: aload_0
        35: aload         8
        37: putfield      #214                // Field autoSelectors:Lscala/collection/immutable/List;
        40: aload_0
        41: aload         9
        43: putfield      #236                // Field configMap:Lorg/scalatest/ConfigMap;
        46: aload_0
        47: aload         10
        49: putfield      #103                // Field repConfig:Lorg/scalatest/tools/ReporterConfigurations;
        52: aload_0
        53: iload         11
        55: putfield      #108                // Field useSbtLogInfoReporter:Z
        58: aload_0
        59: iload         12
        61: putfield      #110                // Field presentAllDurations:Z
        64: aload_0
        65: iload         13
        67: putfield      #112                // Field presentInColor:Z
        70: aload_0
        71: iload         14
        73: putfield      #114                // Field presentShortStackTraces:Z
        76: aload_0
        77: iload         15
        79: putfield      #116                // Field presentFullStackTraces:Z
        82: aload_0
        83: iload         16
        85: putfield      #118                // Field presentUnformatted:Z
        88: aload_0
        89: iload         17
        91: putfield      #120                // Field presentReminder:Z
        94: aload_0
        95: iload         18
        97: putfield      #122                // Field presentReminderWithShortStackTraces:Z
       100: aload_0
       101: iload         19
       103: putfield      #124                // Field presentReminderWithFullStackTraces:Z
       106: aload_0
       107: iload         20
       109: putfield      #126                // Field presentReminderWithoutCanceledTests:Z
       112: aload_0
       113: iload         21
       115: putfield      #128                // Field presentFilePathname:Z
       118: aload_0
       119: iload         22
       121: putfield      #130                // Field presentJson:Z
       124: aload_0
       125: aload         23
       127: putfield      #134                // Field configSet:Lscala/collection/immutable/Set;
       130: aload_1
       131: ifnonnull     136
       134: aconst_null
       135: athrow
       136: aload_0
       137: aload_1
       138: putfield      #647                // Field $outer:Lorg/scalatest/tools/Framework;
       141: aload_0
       142: invokespecial #746                // Method java/lang/Object."<init>":()V
       145: aload_0
       146: new           #382                // class java/util/concurrent/atomic/AtomicBoolean
       149: dup
       150: iconst_0
       151: invokespecial #749                // Method java/util/concurrent/atomic/AtomicBoolean."<init>":(Z)V
       154: putfield      #137                // Field isDone:Ljava/util/concurrent/atomic/AtomicBoolean;
       157: aload_0
       158: new           #416                // class java/util/concurrent/atomic/AtomicReference
       161: dup
       162: getstatic     #443                // Field scala/None$.MODULE$:Lscala/None$;
       165: invokespecial #750                // Method java/util/concurrent/atomic/AtomicReference."<init>":(Ljava/lang/Object;)V
       168: putfield      #141                // Field serverThread:Ljava/util/concurrent/atomic/AtomicReference;
       171: aload_0
       172: new           #752                // class java/util/concurrent/LinkedBlockingQueue
       175: dup
       176: invokespecial #753                // Method java/util/concurrent/LinkedBlockingQueue."<init>":()V
       179: putfield      #145                // Field statusList:Ljava/util/concurrent/LinkedBlockingQueue;
       182: aload_0
       183: new           #498                // class org/scalatest/Tracker
       186: dup
       187: getstatic     #758                // Field org/scalatest/Tracker$.MODULE$:Lorg/scalatest/Tracker$;
       190: invokevirtual #761                // Method org/scalatest/Tracker$.$lessinit$greater$default$1:()Lorg/scalatest/events/Ordinal;
       193: invokespecial #764                // Method org/scalatest/Tracker."<init>":(Lorg/scalatest/events/Ordinal;)V
       196: putfield      #148                // Field tracker:Lorg/scalatest/Tracker;
       199: aload_0
       200: new           #28                 // class org/scalatest/tools/Framework$SummaryCounter
       203: dup
       204: aload_1
       205: invokespecial #767                // Method org/scalatest/tools/Framework$SummaryCounter."<init>":(Lorg/scalatest/tools/Framework;)V
       208: putfield      #151                // Field summaryCounter:Lorg/scalatest/tools/Framework$SummaryCounter;
       211: aload_0
       212: invokestatic  #457                // Method java/lang/System.currentTimeMillis:()J
       215: putfield      #154                // Field runStartTime:J
       218: aload_0
       219: getstatic     #772                // Field org/scalatest/tools/ReporterFactory$.MODULE$:Lorg/scalatest/tools/ReporterFactory$;
       222: aload         10
       224: getstatic     #443                // Field scala/None$.MODULE$:Lscala/None$;
       227: getstatic     #443                // Field scala/None$.MODULE$:Lscala/None$;
       230: aload_3
       231: new           #423                // class scala/Some
       234: dup
       235: aload_1
       236: invokevirtual #776                // Method org/scalatest/tools/Framework.org$scalatest$tools$Framework$$resultHolder:()Lorg/scalatest/tools/SuiteResultHolder;
       239: invokespecial #509                // Method scala/Some."<init>":(Ljava/lang/Object;)V
       242: iload         24
       244: lload         25
       246: lload         27
       248: invokevirtual #780                // Method org/scalatest/tools/ReporterFactory$.getDispatchReporter:(Lorg/scalatest/tools/ReporterConfigurations;Lscala/Option;Lscala/Option;Ljava/lang/ClassLoader;Lscala/Option;ZJJ)Lorg/scalatest/DispatchReporter;
       251: putfield      #157                // Field dispatchReporter:Lorg/scalatest/DispatchReporter;
       254: aload_0
       255: new           #782                // class org/scalatest/tools/SuiteSortingReporter
       258: dup
       259: aload_0
       260: invokevirtual #494                // Method dispatchReporter:()Lorg/scalatest/DispatchReporter;
       263: getstatic     #787                // Field org/scalatest/time/Span$.MODULE$:Lorg/scalatest/time/Span$;
       266: aload         30
       268: invokevirtual #792                // Method org/scalatest/time/Span.millisPart:()J
       271: getstatic     #797                // Field org/scalatest/time/Millis$.MODULE$:Lorg/scalatest/time/Millis$;
       274: invokevirtual #800                // Method org/scalatest/time/Span$.apply:(JLorg/scalatest/time/Units;)Lorg/scalatest/time/Span;
       277: getstatic     #804                // Field java/lang/System.err:Ljava/io/PrintStream;
       280: invokespecial #807                // Method org/scalatest/tools/SuiteSortingReporter."<init>":(Lorg/scalatest/Reporter;Lorg/scalatest/time/Span;Ljava/io/PrintStream;)V
       283: putfield      #160                // Field suiteSortingReporter:Lorg/scalatest/tools/SuiteSortingReporter;
       286: iload         24
       288: ifeq          305
       291: aload_0
       292: invokevirtual #494                // Method dispatchReporter:()Lorg/scalatest/DispatchReporter;
       295: aload_0
       296: invokevirtual #183                // Method suiteSortingReporter:()Lorg/scalatest/tools/SuiteSortingReporter;
       299: invokevirtual #811                // Method org/scalatest/DispatchReporter.registerSlowpokeReporter:(Lorg/scalatest/tools/SuiteSortingReporter;)V
       302: goto          305
       305: aload_0
       306: invokevirtual #494                // Method dispatchReporter:()Lorg/scalatest/DispatchReporter;
       309: new           #813                // class org/scalatest/events/RunStarting
       312: dup
       313: aload_0
       314: invokevirtual #185                // Method tracker:()Lorg/scalatest/Tracker;
       317: invokevirtual #502                // Method org/scalatest/Tracker.nextOrdinal:()Lorg/scalatest/events/Ordinal;
       320: iconst_0
       321: aload         9
       323: getstatic     #818                // Field org/scalatest/events/RunStarting$.MODULE$:Lorg/scalatest/events/RunStarting$;
       326: invokevirtual #819                // Method org/scalatest/events/RunStarting$.apply$default$4:()Lscala/Option;
       329: getstatic     #818                // Field org/scalatest/events/RunStarting$.MODULE$:Lorg/scalatest/events/RunStarting$;
       332: invokevirtual #820                // Method org/scalatest/events/RunStarting$.apply$default$5:()Lscala/Option;
       335: getstatic     #818                // Field org/scalatest/events/RunStarting$.MODULE$:Lorg/scalatest/events/RunStarting$;
       338: invokevirtual #821                // Method org/scalatest/events/RunStarting$.apply$default$6:()Lscala/Option;
       341: getstatic     #818                // Field org/scalatest/events/RunStarting$.MODULE$:Lorg/scalatest/events/RunStarting$;
       344: invokevirtual #822                // Method org/scalatest/events/RunStarting$.apply$default$7:()Ljava/lang/String;
       347: getstatic     #818                // Field org/scalatest/events/RunStarting$.MODULE$:Lorg/scalatest/events/RunStarting$;
       350: invokevirtual #823                // Method org/scalatest/events/RunStarting$.apply$default$8:()J
       353: invokespecial #826                // Method org/scalatest/events/RunStarting."<init>":(Lorg/scalatest/events/Ordinal;ILorg/scalatest/ConfigMap;Lscala/Option;Lscala/Option;Lscala/Option;Ljava/lang/String;J)V
       356: invokevirtual #538                // Method org/scalatest/DispatchReporter.apply:(Lorg/scalatest/events/Event;)V
       359: aload_0
       360: new           #466                // class java/util/concurrent/atomic/AtomicInteger
       363: dup
       364: invokespecial #827                // Method java/util/concurrent/atomic/AtomicInteger."<init>":()V
       367: putfield      #163                // Field org$scalatest$tools$Framework$ScalaTestRunner$$atomicThreadCounter:Ljava/util/concurrent/atomic/AtomicInteger;
       370: aload_0
       371: new           #17                 // class org/scalatest/tools/Framework$ScalaTestRunner$$anon$3
       374: dup
       375: aload_0
       376: invokespecial #828                // Method org/scalatest/tools/Framework$ScalaTestRunner$$anon$3."<init>":(Lorg/scalatest/tools/Framework$ScalaTestRunner;)V
       379: putfield      #166                // Field threadFactory:Ljava/util/concurrent/ThreadFactory;
       382: aload_0
       383: aload         29
       385: invokevirtual #833                // Method org/scalatest/tools/ConcurrentConfig.numThreads:()I
       388: iconst_0
       389: if_icmpne     403
       392: invokestatic  #839                // Method java/lang/Runtime.getRuntime:()Ljava/lang/Runtime;
       395: invokevirtual #842                // Method java/lang/Runtime.availableProcessors:()I
       398: iconst_2
       399: imul
       400: goto          408
       403: aload         29
       405: invokevirtual #833                // Method org/scalatest/tools/ConcurrentConfig.numThreads:()I
       408: putfield      #169                // Field poolSize:I
       411: aload_0
       412: aload_0
       413: invokevirtual #844                // Method poolSize:()I
       416: iconst_0
       417: if_icmple     434
       420: aload_0
       421: invokevirtual #844                // Method poolSize:()I
       424: aload_0
       425: invokevirtual #846                // Method threadFactory:()Ljava/util/concurrent/ThreadFactory;
       428: invokestatic  #852                // Method java/util/concurrent/Executors.newFixedThreadPool:(ILjava/util/concurrent/ThreadFactory;)Ljava/util/concurrent/ExecutorService;
       431: goto          441
       434: aload_0
       435: invokevirtual #846                // Method threadFactory:()Ljava/util/concurrent/ThreadFactory;
       438: invokestatic  #856                // Method java/util/concurrent/Executors.newCachedThreadPool:(Ljava/util/concurrent/ThreadFactory;)Ljava/util/concurrent/ExecutorService;
       441: putfield      #172                // Field execSvc:Ljava/util/concurrent/ExecutorService;
       444: return
      StackMapTable: number_of_entries = 6
        frame_type = 251 /* same_frame_extended */
          offset_delta = 136
        frame_type = 255 /* full_frame */
          offset_delta = 168
          locals = [ class org/scalatest/tools/Framework$ScalaTestRunner, class org/scalatest/tools/Framework, class "[Ljava/lang/String;", class java/lang/ClassLoader, class scala/collection/immutable/Set, class scala/collection/immutable/Set, class scala/collection/immutable/List, class scala/collection/immutable/List, class scala/collection/immutable/List, class org/scalatest/ConfigMap, class org/scalatest/tools/ReporterConfigurations, int, int, int, int, int, int, int, int, int, int, int, int, class scala/collection/immutable/Set, int, long, long, class org/scalatest/tools/ConcurrentConfig, class org/scalatest/time/Span ]
          stack = []
        frame_type = 247 /* same_locals_1_stack_item_frame_extended */
          offset_delta = 97
          stack = [ class org/scalatest/tools/Framework$ScalaTestRunner ]
        frame_type = 255 /* full_frame */
          offset_delta = 4
          locals = [ class org/scalatest/tools/Framework$ScalaTestRunner, class org/scalatest/tools/Framework, class "[Ljava/lang/String;", class java/lang/ClassLoader, class scala/collection/immutable/Set, class scala/collection/immutable/Set, class scala/collection/immutable/List, class scala/collection/immutable/List, class scala/collection/immutable/List, class org/scalatest/ConfigMap, class org/scalatest/tools/ReporterConfigurations, int, int, int, int, int, int, int, int, int, int, int, int, class scala/collection/immutable/Set, int, long, long, class org/scalatest/tools/ConcurrentConfig, class org/scalatest/time/Span ]
          stack = [ class org/scalatest/tools/Framework$ScalaTestRunner, int ]
        frame_type = 89 /* same_locals_1_stack_item */
          stack = [ class org/scalatest/tools/Framework$ScalaTestRunner ]
        frame_type = 255 /* full_frame */
          offset_delta = 6
          locals = [ class org/scalatest/tools/Framework$ScalaTestRunner, class org/scalatest/tools/Framework, class "[Ljava/lang/String;", class java/lang/ClassLoader, class scala/collection/immutable/Set, class scala/collection/immutable/Set, class scala/collection/immutable/List, class scala/collection/immutable/List, class scala/collection/immutable/List, class org/scalatest/ConfigMap, class org/scalatest/tools/ReporterConfigurations, int, int, int, int, int, int, int, int, int, int, int, int, class scala/collection/immutable/Set, int, long, long, class org/scalatest/tools/ConcurrentConfig, class org/scalatest/time/Span ]
          stack = [ class org/scalatest/tools/Framework$ScalaTestRunner, class java/util/concurrent/ExecutorService ]
      LineNumberTable:
        line 635: 0
        line 636: 5
        line 637: 10
        line 638: 16
        line 639: 22
        line 640: 28
        line 641: 34
        line 642: 40
        line 643: 46
        line 644: 52
        line 645: 58
        line 646: 64
        line 647: 70
        line 648: 76
        line 649: 82
        line 650: 88
        line 651: 94
        line 652: 100
        line 653: 106
        line 654: 112
        line 655: 118
        line 656: 124
        line 634: 130
        line 662: 141
        line 663: 145
        line 664: 157
        line 665: 171
        line 666: 182
        line 667: 199
        line 668: 211
        line 670: 218
        line 672: 254
        line 673: 255
        line 674: 259
        line 675: 263
        line 676: 277
        line 672: 283
        line 678: 286
        line 679: 291
        line 681: 305
        line 683: 359
        line 685: 370
        line 686: 371
        line 685: 379
        line 695: 382
        line 696: 383
        line 697: 392
        line 699: 403
        line 695: 408
        line 701: 411
        line 702: 412
        line 703: 420
        line 705: 434
        line 701: 441
        line 634: 444
      LocalVariableTable:
        Start  Length  Slot  Name   Signature
            0     445     0  this   Lorg/scalatest/tools/Framework$ScalaTestRunner;
            0     445     1 $outer   Lorg/scalatest/tools/Framework;
            0     445     2 runArgs   [Ljava/lang/String;
            0     445     3 loader   Ljava/lang/ClassLoader;
            0     445     4 tagsToInclude   Lscala/collection/immutable/Set;
            0     445     5 tagsToExclude   Lscala/collection/immutable/Set;
            0     445     6 membersOnly   Lscala/collection/immutable/List;
            0     445     7 wildcard   Lscala/collection/immutable/List;
            0     445     8 autoSelectors   Lscala/collection/immutable/List;
            0     445     9 configMap   Lorg/scalatest/ConfigMap;
            0     445    10 repConfig   Lorg/scalatest/tools/ReporterConfigurations;
            0     445    11 useSbtLogInfoReporter   Z
            0     445    12 presentAllDurations   Z
            0     445    13 presentInColor   Z
            0     445    14 presentShortStackTraces   Z
            0     445    15 presentFullStackTraces   Z
            0     445    16 presentUnformatted   Z
            0     445    17 presentReminder   Z
            0     445    18 presentReminderWithShortStackTraces   Z
            0     445    19 presentReminderWithFullStackTraces   Z
            0     445    20 presentReminderWithoutCanceledTests   Z
            0     445    21 presentFilePathname   Z
            0     445    22 presentJson   Z
            0     445    23 configSet   Lscala/collection/immutable/Set;
            0     445    24 detectSlowpokes   Z
            0     445    25 slowpokeDetectionDelay   J
            0     445    27 slowpokeDetectionPeriod   J
            0     445    29 concurrentConfig   Lorg/scalatest/tools/ConcurrentConfig;
            0     445    30 testSortingReporterTimeout   Lorg/scalatest/time/Span;
    Signature: #739                         // ([Ljava/lang/String;Ljava/lang/ClassLoader;Lscala/collection/immutable/Set<Ljava/lang/String;>;Lscala/collection/immutable/Set<Ljava/lang/String;>;Lscala/collection/immutable/List<Ljava/lang/String;>;Lscala/collection/immutable/List<Ljava/lang/String;>;Lscala/collection/immutable/List<Lsbt/testing/Selector;>;Lorg/scalatest/ConfigMap;Lorg/scalatest/tools/ReporterConfigurations;ZZZZZZZZZZZZLscala/collection/immutable/Set<Lorg/scalatest/tools/ReporterConfigParam;>;ZJJLorg/scalatest/tools/ConcurrentConfig;Lorg/scalatest/time/Span;)V
    MethodParameters:
      Name                           Flags
      $outer                         final synthetic
      runArgs                        final
      loader                         final
      tagsToInclude                  final
      tagsToExclude                  final
      membersOnly                    final
      wildcard                       final
      autoSelectors                  final
      configMap                      final
      repConfig                      final
      useSbtLogInfoReporter          final
      presentAllDurations            final
      presentInColor                 final
      presentShortStackTraces        final
      presentFullStackTraces         final
      presentUnformatted             final
      presentReminder                final
      presentReminderWithShortStackTracesfinal
      presentReminderWithFullStackTracesfinal
      presentReminderWithoutCanceledTestsfinal
      presentFilePathname            final
      presentJson                    final
      configSet                      final
      detectSlowpokes                final
      slowpokeDetectionDelay         final
      slowpokeDetectionPeriod        final
      concurrentConfig               final
      testSortingReporterTimeout     final

  public static final java.lang.Object $anonfun$filterWildcard$1$adapted(scala.collection.immutable.List, sbt.testing.TaskDef);
    descriptor: (Lscala/collection/immutable/List;Lsbt/testing/TaskDef;)Ljava/lang/Object;
    flags: (0x1019) ACC_PUBLIC, ACC_STATIC, ACC_FINAL, ACC_SYNTHETIC
    Code:
      stack=2, locals=2, args_size=2
         0: aload_0
         1: aload_1
         2: invokestatic  #868                // Method $anonfun$filterWildcard$1:(Lscala/collection/immutable/List;Lsbt/testing/TaskDef;)Z
         5: invokestatic  #872                // Method scala/runtime/BoxesRunTime.boxToBoolean:(Z)Ljava/lang/Boolean;
         8: areturn
      LineNumberTable:
        line 737: 0
      LocalVariableTable:
        Start  Length  Slot  Name   Signature
            0       9     0 paths$1   Lscala/collection/immutable/List;
            0       9     1    td   Lsbt/testing/TaskDef;
    MethodParameters:
      Name                           Flags
      paths$1                        final
      td                             final

  public static final java.lang.Object $anonfun$filterMembersOnly$1$adapted(scala.collection.immutable.List, sbt.testing.TaskDef);
    descriptor: (Lscala/collection/immutable/List;Lsbt/testing/TaskDef;)Ljava/lang/Object;
    flags: (0x1019) ACC_PUBLIC, ACC_STATIC, ACC_FINAL, ACC_SYNTHETIC
    Code:
      stack=2, locals=2, args_size=2
         0: aload_0
         1: aload_1
         2: invokestatic  #874                // Method $anonfun$filterMembersOnly$1:(Lscala/collection/immutable/List;Lsbt/testing/TaskDef;)Z
         5: invokestatic  #872                // Method scala/runtime/BoxesRunTime.boxToBoolean:(Z)Ljava/lang/Boolean;
         8: areturn
      LineNumberTable:
        line 740: 0
      LocalVariableTable:
        Start  Length  Slot  Name   Signature
            0       9     0 paths$2   Lscala/collection/immutable/List;
            0       9     1    td   Lsbt/testing/TaskDef;
    MethodParameters:
      Name                           Flags
      paths$2                        final
      td                             final

  public static final java.lang.Object $anonfun$tasks$2$adapted(scala.Tuple2);
    descriptor: (Lscala/Tuple2;)Ljava/lang/Object;
    flags: (0x1019) ACC_PUBLIC, ACC_STATIC, ACC_FINAL, ACC_SYNTHETIC
    Code:
      stack=1, locals=1, args_size=1
         0: aload_0
         1: invokestatic  #876                // Method $anonfun$tasks$2:(Lscala/Tuple2;)Z
         4: invokestatic  #872                // Method scala/runtime/BoxesRunTime.boxToBoolean:(Z)Ljava/lang/Boolean;
         7: areturn
      LineNumberTable:
        line 746: 0
      LocalVariableTable:
        Start  Length  Slot  Name   Signature
            0       8     0  x$16   Lscala/Tuple2;
    MethodParameters:
      Name                           Flags
      x$16                           final

  public static final java.lang.Object $anonfun$done$1$adapted(org.scalatest.Status);
    descriptor: (Lorg/scalatest/Status;)Ljava/lang/Object;
    flags: (0x1019) ACC_PUBLIC, ACC_STATIC, ACC_FINAL, ACC_SYNTHETIC
    Code:
      stack=1, locals=1, args_size=1
         0: aload_0
         1: invokestatic  #878                // Method $anonfun$done$1:(Lorg/scalatest/Status;)V
         4: getstatic     #438                // Field scala/runtime/BoxedUnit.UNIT:Lscala/runtime/BoxedUnit;
         7: areturn
      LineNumberTable:
        line 755: 0
      LocalVariableTable:
        Start  Length  Slot  Name   Signature
            0       8     0     s   Lorg/scalatest/Status;
    MethodParameters:
      Name                           Flags
      s                              final

  public static final java.lang.Object $anonfun$filterWildcard$2$adapted(sbt.testing.TaskDef, java.lang.String);
    descriptor: (Lsbt/testing/TaskDef;Ljava/lang/String;)Ljava/lang/Object;
    flags: (0x1019) ACC_PUBLIC, ACC_STATIC, ACC_FINAL, ACC_SYNTHETIC
    Code:
      stack=2, locals=2, args_size=2
         0: aload_0
         1: aload_1
         2: invokestatic  #880                // Method $anonfun$filterWildcard$2:(Lsbt/testing/TaskDef;Ljava/lang/String;)Z
         5: invokestatic  #872                // Method scala/runtime/BoxesRunTime.boxToBoolean:(Z)Ljava/lang/Boolean;
         8: areturn
      LineNumberTable:
        line 737: 0
      LocalVariableTable:
        Start  Length  Slot  Name   Signature
            0       9     0  td$1   Lsbt/testing/TaskDef;
            0       9     1  x$15   Ljava/lang/String;
    MethodParameters:
      Name                           Flags
      td$1                           final
      x$15                           final

  public static final java.lang.Object $anonfun$filterMembersOnly$2$adapted(sbt.testing.TaskDef, java.lang.String);
    descriptor: (Lsbt/testing/TaskDef;Ljava/lang/String;)Ljava/lang/Object;
    flags: (0x1019) ACC_PUBLIC, ACC_STATIC, ACC_FINAL, ACC_SYNTHETIC
    Code:
      stack=2, locals=2, args_size=2
         0: aload_0
         1: aload_1
         2: invokestatic  #882                // Method $anonfun$filterMembersOnly$2:(Lsbt/testing/TaskDef;Ljava/lang/String;)Z
         5: invokestatic  #872                // Method scala/runtime/BoxesRunTime.boxToBoolean:(Z)Ljava/lang/Boolean;
         8: areturn
      LineNumberTable:
        line 741: 0
      LocalVariableTable:
        Start  Length  Slot  Name   Signature
            0       9     0  td$2   Lsbt/testing/TaskDef;
            0       9     1  path   Ljava/lang/String;
    MethodParameters:
      Name                           Flags
      td$2                           final
      path                           final

  private static java.lang.Object $deserializeLambda$(java.lang.invoke.SerializedLambda);
    descriptor: (Ljava/lang/invoke/SerializedLambda;)Ljava/lang/Object;
    flags: (0x100a) ACC_PRIVATE, ACC_STATIC, ACC_SYNTHETIC
    Code:
      stack=1, locals=1, args_size=1
         0: aload_0
         1: invokedynamic #894,  0            // InvokeDynamic #9:lambdaDeserialize:(Ljava/lang/invoke/SerializedLambda;)Ljava/lang/Object;
         6: areturn
}
InnerClasses:
  public static final #12= #9 of #11;     // Lookup=class java/lang/invoke/MethodHandles$Lookup of class java/lang/invoke/MethodHandles
  public #15= #2 of #14;                  // ScalaTestRunner=class org/scalatest/tools/Framework$ScalaTestRunner of class org/scalatest/tools/Framework
  public final #17;                       // class org/scalatest/tools/Framework$ScalaTestRunner$$anon$3
  public #20= #19;                        // Skeleton$1=class org/scalatest/tools/Framework$ScalaTestRunner$Skeleton$1
  public #23= #22;                        // SkeletonObjectInputStream$1=class org/scalatest/tools/Framework$ScalaTestRunner$SkeletonObjectInputStream$1
  private #26= #25 of #14;                // ScalaTestTask=class org/scalatest/tools/Framework$ScalaTestTask of class org/scalatest/tools/Framework
  public #29= #28 of #14;                 // SummaryCounter=class org/scalatest/tools/Framework$SummaryCounter of class org/scalatest/tools/Framework
  public static #34= #31 of #33;          // WithFilter=class scala/collection/ArrayOps$WithFilter of class scala/collection/ArrayOps
  public static #39= #36 of #38;          // AsScala=class scala/collection/JavaConverters$AsScala of class scala/collection/JavaConverters
SourceFile: "Framework.scala"
BootstrapMethods:
  0: #296 REF_invokeStatic java/lang/invoke/LambdaMetafactory.altMetafactory:(Ljava/lang/invoke/MethodHandles$Lookup;Ljava/lang/String;Ljava/lang/invoke/MethodType;[Ljava/lang/Object;)Ljava/lang/invoke/CallSite;
    Method arguments:
      #280 (Ljava/lang/Object;)Ljava/lang/Object;
      #285 REF_invokeStatic org/scalatest/tools/Framework$ScalaTestRunner.$anonfun$filterWildcard$1$adapted:(Lscala/collection/immutable/List;Lsbt/testing/TaskDef;)Ljava/lang/Object;
      #287 (Lsbt/testing/TaskDef;)Ljava/lang/Object;
      #288 5
      #289 1
      #287 (Lsbt/testing/TaskDef;)Ljava/lang/Object;
  1: #296 REF_invokeStatic java/lang/invoke/LambdaMetafactory.altMetafactory:(Ljava/lang/invoke/MethodHandles$Lookup;Ljava/lang/String;Ljava/lang/invoke/MethodType;[Ljava/lang/Object;)Ljava/lang/invoke/CallSite;
    Method arguments:
      #280 (Ljava/lang/Object;)Ljava/lang/Object;
      #310 REF_invokeStatic org/scalatest/tools/Framework$ScalaTestRunner.$anonfun$filterMembersOnly$1$adapted:(Lscala/collection/immutable/List;Lsbt/testing/TaskDef;)Ljava/lang/Object;
      #287 (Lsbt/testing/TaskDef;)Ljava/lang/Object;
      #288 5
      #289 1
      #287 (Lsbt/testing/TaskDef;)Ljava/lang/Object;
  2: #296 REF_invokeStatic java/lang/invoke/LambdaMetafactory.altMetafactory:(Ljava/lang/invoke/MethodHandles$Lookup;Ljava/lang/String;Ljava/lang/invoke/MethodType;[Ljava/lang/Object;)Ljava/lang/invoke/CallSite;
    Method arguments:
      #280 (Ljava/lang/Object;)Ljava/lang/Object;
      #337 REF_invokeStatic org/scalatest/tools/Framework$ScalaTestRunner.$anonfun$tasks$1:(Lorg/scalatest/tools/Framework$ScalaTestRunner;Lsbt/testing/TaskDef;)Lscala/Tuple2;
      #339 (Lsbt/testing/TaskDef;)Lscala/Tuple2;
      #288 5
      #289 1
      #339 (Lsbt/testing/TaskDef;)Lscala/Tuple2;
  3: #296 REF_invokeStatic java/lang/invoke/LambdaMetafactory.altMetafactory:(Ljava/lang/invoke/MethodHandles$Lookup;Ljava/lang/String;Ljava/lang/invoke/MethodType;[Ljava/lang/Object;)Ljava/lang/invoke/CallSite;
    Method arguments:
      #280 (Ljava/lang/Object;)Ljava/lang/Object;
      #353 REF_invokeStatic org/scalatest/tools/Framework$ScalaTestRunner.$anonfun$tasks$2$adapted:(Lscala/Tuple2;)Ljava/lang/Object;
      #354 (Lscala/Tuple2;)Ljava/lang/Object;
      #288 5
      #289 1
      #354 (Lscala/Tuple2;)Ljava/lang/Object;
  4: #296 REF_invokeStatic java/lang/invoke/LambdaMetafactory.altMetafactory:(Ljava/lang/invoke/MethodHandles$Lookup;Ljava/lang/String;Ljava/lang/invoke/MethodType;[Ljava/lang/Object;)Ljava/lang/invoke/CallSite;
    Method arguments:
      #280 (Ljava/lang/Object;)Ljava/lang/Object;
      #366 REF_invokeStatic org/scalatest/tools/Framework$ScalaTestRunner.$anonfun$tasks$3:(Lscala/Tuple2;)Lsbt/testing/Task;
      #367 (Lscala/Tuple2;)Lsbt/testing/Task;
      #288 5
      #289 1
      #367 (Lscala/Tuple2;)Lsbt/testing/Task;
  5: #296 REF_invokeStatic java/lang/invoke/LambdaMetafactory.altMetafactory:(Ljava/lang/invoke/MethodHandles$Lookup;Ljava/lang/String;Ljava/lang/invoke/MethodType;[Ljava/lang/Object;)Ljava/lang/invoke/CallSite;
    Method arguments:
      #280 (Ljava/lang/Object;)Ljava/lang/Object;
      #406 REF_invokeStatic org/scalatest/tools/Framework$ScalaTestRunner.$anonfun$done$1$adapted:(Lorg/scalatest/Status;)Ljava/lang/Object;
      #407 (Lorg/scalatest/Status;)Ljava/lang/Object;
      #288 5
      #289 1
      #407 (Lorg/scalatest/Status;)Ljava/lang/Object;
  6: #296 REF_invokeStatic java/lang/invoke/LambdaMetafactory.altMetafactory:(Ljava/lang/invoke/MethodHandles$Lookup;Ljava/lang/String;Ljava/lang/invoke/MethodType;[Ljava/lang/Object;)Ljava/lang/invoke/CallSite;
    Method arguments:
      #280 (Ljava/lang/Object;)Ljava/lang/Object;
      #586 REF_invokeStatic org/scalatest/tools/Framework$ScalaTestRunner.$anonfun$done$2:(Lorg/scalatest/tools/Framework$ScalaTestRunner;Lorg/scalatest/tools/Fragment;)Ljava/lang/String;
      #588 (Lorg/scalatest/tools/Fragment;)Ljava/lang/String;
      #288 5
      #289 1
      #588 (Lorg/scalatest/tools/Fragment;)Ljava/lang/String;
  7: #296 REF_invokeStatic java/lang/invoke/LambdaMetafactory.altMetafactory:(Ljava/lang/invoke/MethodHandles$Lookup;Ljava/lang/String;Ljava/lang/invoke/MethodType;[Ljava/lang/Object;)Ljava/lang/invoke/CallSite;
    Method arguments:
      #280 (Ljava/lang/Object;)Ljava/lang/Object;
      #667 REF_invokeStatic org/scalatest/tools/Framework$ScalaTestRunner.$anonfun$filterWildcard$2$adapted:(Lsbt/testing/TaskDef;Ljava/lang/String;)Ljava/lang/Object;
      #669 (Ljava/lang/String;)Ljava/lang/Object;
      #288 5
      #289 1
      #669 (Ljava/lang/String;)Ljava/lang/Object;
  8: #296 REF_invokeStatic java/lang/invoke/LambdaMetafactory.altMetafactory:(Ljava/lang/invoke/MethodHandles$Lookup;Ljava/lang/String;Ljava/lang/invoke/MethodType;[Ljava/lang/Object;)Ljava/lang/invoke/CallSite;
    Method arguments:
      #280 (Ljava/lang/Object;)Ljava/lang/Object;
      #695 REF_invokeStatic org/scalatest/tools/Framework$ScalaTestRunner.$anonfun$filterMembersOnly$2$adapted:(Lsbt/testing/TaskDef;Ljava/lang/String;)Ljava/lang/Object;
      #669 (Ljava/lang/String;)Ljava/lang/Object;
      #288 5
      #289 1
      #669 (Ljava/lang/String;)Ljava/lang/Object;
  9: #891 REF_invokeStatic scala/runtime/LambdaDeserialize.bootstrap:(Ljava/lang/invoke/MethodHandles$Lookup;Ljava/lang/String;Ljava/lang/invoke/MethodType;[Ljava/lang/invoke/MethodHandle;)Ljava/lang/invoke/CallSite;
    Method arguments:
      #406 REF_invokeStatic org/scalatest/tools/Framework$ScalaTestRunner.$anonfun$done$1$adapted:(Lorg/scalatest/Status;)Ljava/lang/Object;
      #586 REF_invokeStatic org/scalatest/tools/Framework$ScalaTestRunner.$anonfun$done$2:(Lorg/scalatest/tools/Framework$ScalaTestRunner;Lorg/scalatest/tools/Fragment;)Ljava/lang/String;
      #310 REF_invokeStatic org/scalatest/tools/Framework$ScalaTestRunner.$anonfun$filterMembersOnly$1$adapted:(Lscala/collection/immutable/List;Lsbt/testing/TaskDef;)Ljava/lang/Object;
      #695 REF_invokeStatic org/scalatest/tools/Framework$ScalaTestRunner.$anonfun$filterMembersOnly$2$adapted:(Lsbt/testing/TaskDef;Ljava/lang/String;)Ljava/lang/Object;
      #285 REF_invokeStatic org/scalatest/tools/Framework$ScalaTestRunner.$anonfun$filterWildcard$1$adapted:(Lscala/collection/immutable/List;Lsbt/testing/TaskDef;)Ljava/lang/Object;
      #667 REF_invokeStatic org/scalatest/tools/Framework$ScalaTestRunner.$anonfun$filterWildcard$2$adapted:(Lsbt/testing/TaskDef;Ljava/lang/String;)Ljava/lang/Object;
      #337 REF_invokeStatic org/scalatest/tools/Framework$ScalaTestRunner.$anonfun$tasks$1:(Lorg/scalatest/tools/Framework$ScalaTestRunner;Lsbt/testing/TaskDef;)Lscala/Tuple2;
      #353 REF_invokeStatic org/scalatest/tools/Framework$ScalaTestRunner.$anonfun$tasks$2$adapted:(Lscala/Tuple2;)Ljava/lang/Object;
      #366 REF_invokeStatic org/scalatest/tools/Framework$ScalaTestRunner.$anonfun$tasks$3:(Lscala/Tuple2;)Lsbt/testing/Task;
  ScalaInlineInfo: length = 0xFE (unknown attribute)
   01 00 00 32 02 CD 02 CE 01 01 92 01 93 01 02 46
   02 47 01 02 B2 02 95 01 01 33 01 1A 01 02 A5 02
   89 01 02 B4 02 98 01 02 94 02 95 01 01 19 01 1A
   01 02 88 02 89 01 02 97 02 98 01 01 4D 01 4E 01
   02 C2 02 C3 01 01 5D 01 5E 01 01 6A 01 6B 01 01
   0D 02 E2 00 02 67 02 68 00 00 47 00 83 00 00 AD
   00 AE 01 00 57 00 9B 00 01 79 01 7A 00 00 61 00
   AA 00 01 32 01 13 01 01 12 01 13 01 00 49 00 87
   00 00 B0 00 B1 00 00 5B 00 A1 01 00 5F 00 A7 00
   00 3C 00 6A 00 00 45 00 6A 00 00 3F 00 6A 00 00
   3D 00 6A 00 00 46 00 6A 00 00 41 00 6A 00 00 43
   00 6A 00 00 42 00 6A 00 00 44 00 6A 00 00 3E 00
   6A 00 00 40 00 6A 00 02 6B 02 68 00 00 38 00 65
   00 00 55 00 98 00 00 4B 00 8A 00 00 4E 00 8E 00
   00 59 00 9E 00 00 53 00 95 00 01 38 01 39 00 00
   5D 00 A4 00 00 51 00 92 00 00 3A 00 6A 00
  Scala: length = 0x0 (unknown attribute)

