Classfile /Users/mw/Projects/slang-braindump/.jar/jar8/assemble/slang-braindump/assemble/content/org/scalatest/tools/JUnitXmlReporter$Testcase$.class
  Last modified May 29, 2022; size 2645 bytes
  SHA-256 checksum 9942b5ed9a0f889eb11bad12f360922a002066c03f13bf14204b265feff3c1bd
  Compiled from "JUnitXmlReporter.scala"
public class org.scalatest.tools.JUnitXmlReporter$Testcase$ extends scala.runtime.AbstractFunction3<java.lang.String, scala.Option<java.lang.String>, java.lang.Object, org.scalatest.tools.JUnitXmlReporter$Testcase> implements java.io.Serializable
  minor version: 0
  major version: 52
  flags: (0x0021) ACC_PUBLIC, ACC_SUPER
  this_class: #2                          // org/scalatest/tools/JUnitXmlReporter$Testcase$
  super_class: #5                         // scala/runtime/AbstractFunction3
  interfaces: 1, fields: 1, methods: 5, attributes: 5
Constant pool:
    #1 = Utf8               org/scalatest/tools/JUnitXmlReporter$Testcase$
    #2 = Class              #1            // org/scalatest/tools/JUnitXmlReporter$Testcase$
    #3 = Utf8               Lscala/runtime/AbstractFunction3<Ljava/lang/String;Lscala/Option<Ljava/lang/String;>;Ljava/lang/Object;Lorg/scalatest/tools/JUnitXmlReporter$Testcase;>;Ljava/io/Serializable;
    #4 = Utf8               scala/runtime/AbstractFunction3
    #5 = Class              #4            // scala/runtime/AbstractFunction3
    #6 = Utf8               java/io/Serializable
    #7 = Class              #6            // java/io/Serializable
    #8 = Utf8               JUnitXmlReporter.scala
    #9 = Utf8               org/scalatest/tools/JUnitXmlReporter$Testcase
   #10 = Class              #9            // org/scalatest/tools/JUnitXmlReporter$Testcase
   #11 = Utf8               org/scalatest/tools/JUnitXmlReporter
   #12 = Class              #11           // org/scalatest/tools/JUnitXmlReporter
   #13 = Utf8               Testcase
   #14 = Utf8               Testcase$
   #15 = Utf8               $outer
   #16 = Utf8               Lorg/scalatest/tools/JUnitXmlReporter;
   #17 = Utf8               toString
   #18 = Utf8               ()Ljava/lang/String;
   #19 = String             #13           // Testcase
   #20 = Utf8               this
   #21 = Utf8               Lorg/scalatest/tools/JUnitXmlReporter$Testcase$;
   #22 = Utf8               apply
   #23 = Utf8               (Ljava/lang/String;Lscala/Option;J)Lorg/scalatest/tools/JUnitXmlReporter$Testcase;
   #24 = Utf8               (Ljava/lang/String;Lscala/Option<Ljava/lang/String;>;J)Lorg/scalatest/tools/JUnitXmlReporter$Testcase;
   #25 = Utf8               name
   #26 = Utf8               className
   #27 = Utf8               timeStamp
   #28 = NameAndType        #15:#16       // $outer:Lorg/scalatest/tools/JUnitXmlReporter;
   #29 = Fieldref           #2.#28        // org/scalatest/tools/JUnitXmlReporter$Testcase$.$outer:Lorg/scalatest/tools/JUnitXmlReporter;
   #30 = Utf8               <init>
   #31 = Utf8               (Lorg/scalatest/tools/JUnitXmlReporter;Ljava/lang/String;Lscala/Option;J)V
   #32 = NameAndType        #30:#31       // "<init>":(Lorg/scalatest/tools/JUnitXmlReporter;Ljava/lang/String;Lscala/Option;J)V
   #33 = Methodref          #10.#32       // org/scalatest/tools/JUnitXmlReporter$Testcase."<init>":(Lorg/scalatest/tools/JUnitXmlReporter;Ljava/lang/String;Lscala/Option;J)V
   #34 = Utf8               Ljava/lang/String;
   #35 = Utf8               Lscala/Option;
   #36 = Utf8               J
   #37 = Utf8               unapply
   #38 = Utf8               (Lorg/scalatest/tools/JUnitXmlReporter$Testcase;)Lscala/Option;
   #39 = Utf8               (Lorg/scalatest/tools/JUnitXmlReporter$Testcase;)Lscala/Option<Lscala/Tuple3<Ljava/lang/String;Lscala/Option<Ljava/lang/String;>;Ljava/lang/Object;>;>;
   #40 = Utf8               x$0
   #41 = Utf8               scala/None$
   #42 = Class              #41           // scala/None$
   #43 = Utf8               MODULE$
   #44 = Utf8               Lscala/None$;
   #45 = NameAndType        #43:#44       // MODULE$:Lscala/None$;
   #46 = Fieldref           #42.#45       // scala/None$.MODULE$:Lscala/None$;
   #47 = Utf8               scala/Some
   #48 = Class              #47           // scala/Some
   #49 = Utf8               scala/Tuple3
   #50 = Class              #49           // scala/Tuple3
   #51 = NameAndType        #25:#18       // name:()Ljava/lang/String;
   #52 = Methodref          #10.#51       // org/scalatest/tools/JUnitXmlReporter$Testcase.name:()Ljava/lang/String;
   #53 = Utf8               ()Lscala/Option;
   #54 = NameAndType        #26:#53       // className:()Lscala/Option;
   #55 = Methodref          #10.#54       // org/scalatest/tools/JUnitXmlReporter$Testcase.className:()Lscala/Option;
   #56 = Utf8               ()J
   #57 = NameAndType        #27:#56       // timeStamp:()J
   #58 = Methodref          #10.#57       // org/scalatest/tools/JUnitXmlReporter$Testcase.timeStamp:()J
   #59 = Utf8               scala/runtime/BoxesRunTime
   #60 = Class              #59           // scala/runtime/BoxesRunTime
   #61 = Utf8               boxToLong
   #62 = Utf8               (J)Ljava/lang/Long;
   #63 = NameAndType        #61:#62       // boxToLong:(J)Ljava/lang/Long;
   #64 = Methodref          #60.#63       // scala/runtime/BoxesRunTime.boxToLong:(J)Ljava/lang/Long;
   #65 = Utf8               (Ljava/lang/Object;Ljava/lang/Object;Ljava/lang/Object;)V
   #66 = NameAndType        #30:#65       // "<init>":(Ljava/lang/Object;Ljava/lang/Object;Ljava/lang/Object;)V
   #67 = Methodref          #50.#66       // scala/Tuple3."<init>":(Ljava/lang/Object;Ljava/lang/Object;Ljava/lang/Object;)V
   #68 = Utf8               (Ljava/lang/Object;)V
   #69 = NameAndType        #30:#68       // "<init>":(Ljava/lang/Object;)V
   #70 = Methodref          #48.#69       // scala/Some."<init>":(Ljava/lang/Object;)V
   #71 = Utf8               Lorg/scalatest/tools/JUnitXmlReporter$Testcase;
   #72 = Utf8               scala/Option
   #73 = Class              #72           // scala/Option
   #74 = Utf8               (Ljava/lang/Object;Ljava/lang/Object;Ljava/lang/Object;)Ljava/lang/Object;
   #75 = Utf8               v1
   #76 = Utf8               v2
   #77 = Utf8               v3
   #78 = Utf8               java/lang/String
   #79 = Class              #78           // java/lang/String
   #80 = Utf8               unboxToLong
   #81 = Utf8               (Ljava/lang/Object;)J
   #82 = NameAndType        #80:#81       // unboxToLong:(Ljava/lang/Object;)J
   #83 = Methodref          #60.#82       // scala/runtime/BoxesRunTime.unboxToLong:(Ljava/lang/Object;)J
   #84 = NameAndType        #22:#23       // apply:(Ljava/lang/String;Lscala/Option;J)Lorg/scalatest/tools/JUnitXmlReporter$Testcase;
   #85 = Methodref          #2.#84        // org/scalatest/tools/JUnitXmlReporter$Testcase$.apply:(Ljava/lang/String;Lscala/Option;J)Lorg/scalatest/tools/JUnitXmlReporter$Testcase;
   #86 = Utf8               Ljava/lang/Object;
   #87 = Utf8               (Lorg/scalatest/tools/JUnitXmlReporter;)V
   #88 = Utf8               ()V
   #89 = NameAndType        #30:#88       // "<init>":()V
   #90 = Methodref          #5.#89        // scala/runtime/AbstractFunction3."<init>":()V
   #91 = Utf8               Code
   #92 = Utf8               LineNumberTable
   #93 = Utf8               LocalVariableTable
   #94 = Utf8               Signature
   #95 = Utf8               MethodParameters
   #96 = Utf8               StackMapTable
   #97 = Utf8               InnerClasses
   #98 = Utf8               SourceFile
   #99 = Utf8               ScalaInlineInfo
  #100 = Utf8               Scala
{
  private final org.scalatest.tools.JUnitXmlReporter $outer;
    descriptor: Lorg/scalatest/tools/JUnitXmlReporter;
    flags: (0x1012) ACC_PRIVATE, ACC_FINAL, ACC_SYNTHETIC

  public final java.lang.String toString();
    descriptor: ()Ljava/lang/String;
    flags: (0x0011) ACC_PUBLIC, ACC_FINAL
    Code:
      stack=1, locals=1, args_size=1
         0: ldc           #19                 // String Testcase
         2: areturn
      LineNumberTable:
        line 510: 0
      LocalVariableTable:
        Start  Length  Slot  Name   Signature
            0       3     0  this   Lorg/scalatest/tools/JUnitXmlReporter$Testcase$;

  public org.scalatest.tools.JUnitXmlReporter$Testcase apply(java.lang.String, scala.Option<java.lang.String>, long);
    descriptor: (Ljava/lang/String;Lscala/Option;J)Lorg/scalatest/tools/JUnitXmlReporter$Testcase;
    flags: (0x0001) ACC_PUBLIC
    Code:
      stack=7, locals=5, args_size=4
         0: new           #10                 // class org/scalatest/tools/JUnitXmlReporter$Testcase
         3: dup
         4: aload_0
         5: getfield      #29                 // Field $outer:Lorg/scalatest/tools/JUnitXmlReporter;
         8: aload_1
         9: aload_2
        10: lload_3
        11: invokespecial #33                 // Method org/scalatest/tools/JUnitXmlReporter$Testcase."<init>":(Lorg/scalatest/tools/JUnitXmlReporter;Ljava/lang/String;Lscala/Option;J)V
        14: areturn
      LineNumberTable:
        line 510: 0
      LocalVariableTable:
        Start  Length  Slot  Name   Signature
            0      15     0  this   Lorg/scalatest/tools/JUnitXmlReporter$Testcase$;
            0      15     1  name   Ljava/lang/String;
            0      15     2 className   Lscala/Option;
            0      15     3 timeStamp   J
    Signature: #24                          // (Ljava/lang/String;Lscala/Option<Ljava/lang/String;>;J)Lorg/scalatest/tools/JUnitXmlReporter$Testcase;
    MethodParameters:
      Name                           Flags
      name                           final
      className                      final
      timeStamp                      final

  public scala.Option<scala.Tuple3<java.lang.String, scala.Option<java.lang.String>, java.lang.Object>> unapply(org.scalatest.tools.JUnitXmlReporter$Testcase);
    descriptor: (Lorg/scalatest/tools/JUnitXmlReporter$Testcase;)Lscala/Option;
    flags: (0x0001) ACC_PUBLIC
    Code:
      stack=8, locals=2, args_size=2
         0: aload_1
         1: ifnonnull     10
         4: getstatic     #46                 // Field scala/None$.MODULE$:Lscala/None$;
         7: goto          39
        10: new           #48                 // class scala/Some
        13: dup
        14: new           #50                 // class scala/Tuple3
        17: dup
        18: aload_1
        19: invokevirtual #52                 // Method org/scalatest/tools/JUnitXmlReporter$Testcase.name:()Ljava/lang/String;
        22: aload_1
        23: invokevirtual #55                 // Method org/scalatest/tools/JUnitXmlReporter$Testcase.className:()Lscala/Option;
        26: aload_1
        27: invokevirtual #58                 // Method org/scalatest/tools/JUnitXmlReporter$Testcase.timeStamp:()J
        30: invokestatic  #64                 // Method scala/runtime/BoxesRunTime.boxToLong:(J)Ljava/lang/Long;
        33: invokespecial #67                 // Method scala/Tuple3."<init>":(Ljava/lang/Object;Ljava/lang/Object;Ljava/lang/Object;)V
        36: invokespecial #70                 // Method scala/Some."<init>":(Ljava/lang/Object;)V
        39: areturn
      StackMapTable: number_of_entries = 2
        frame_type = 10 /* same */
        frame_type = 92 /* same_locals_1_stack_item */
          stack = [ class scala/Option ]
      LineNumberTable:
        line 510: 0
      LocalVariableTable:
        Start  Length  Slot  Name   Signature
            0      40     0  this   Lorg/scalatest/tools/JUnitXmlReporter$Testcase$;
            0      40     1   x$0   Lorg/scalatest/tools/JUnitXmlReporter$Testcase;
    Signature: #39                          // (Lorg/scalatest/tools/JUnitXmlReporter$Testcase;)Lscala/Option<Lscala/Tuple3<Ljava/lang/String;Lscala/Option<Ljava/lang/String;>;Ljava/lang/Object;>;>;
    MethodParameters:
      Name                           Flags
      x$0                            final

  public java.lang.Object apply(java.lang.Object, java.lang.Object, java.lang.Object);
    descriptor: (Ljava/lang/Object;Ljava/lang/Object;Ljava/lang/Object;)Ljava/lang/Object;
    flags: (0x1041) ACC_PUBLIC, ACC_BRIDGE, ACC_SYNTHETIC
    Code:
      stack=5, locals=4, args_size=4
         0: aload_0
         1: aload_1
         2: checkcast     #79                 // class java/lang/String
         5: aload_2
         6: checkcast     #73                 // class scala/Option
         9: aload_3
        10: invokestatic  #83                 // Method scala/runtime/BoxesRunTime.unboxToLong:(Ljava/lang/Object;)J
        13: invokevirtual #85                 // Method apply:(Ljava/lang/String;Lscala/Option;J)Lorg/scalatest/tools/JUnitXmlReporter$Testcase;
        16: areturn
      LineNumberTable:
        line 510: 0
      LocalVariableTable:
        Start  Length  Slot  Name   Signature
            0      17     0  this   Lorg/scalatest/tools/JUnitXmlReporter$Testcase$;
            0      17     1    v1   Ljava/lang/Object;
            0      17     2    v2   Ljava/lang/Object;
            0      17     3    v3   Ljava/lang/Object;
    MethodParameters:
      Name                           Flags
      v1                             final
      v2                             final
      v3                             final

  public org.scalatest.tools.JUnitXmlReporter$Testcase$(org.scalatest.tools.JUnitXmlReporter);
    descriptor: (Lorg/scalatest/tools/JUnitXmlReporter;)V
    flags: (0x0001) ACC_PUBLIC
    Code:
      stack=2, locals=2, args_size=2
         0: aload_1
         1: ifnonnull     6
         4: aconst_null
         5: athrow
         6: aload_0
         7: aload_1
         8: putfield      #29                 // Field $outer:Lorg/scalatest/tools/JUnitXmlReporter;
        11: aload_0
        12: invokespecial #90                 // Method scala/runtime/AbstractFunction3."<init>":()V
        15: return
      StackMapTable: number_of_entries = 1
        frame_type = 6 /* same */
      LineNumberTable:
        line 510: 0
      LocalVariableTable:
        Start  Length  Slot  Name   Signature
            0      16     0  this   Lorg/scalatest/tools/JUnitXmlReporter$Testcase$;
            0      16     1 $outer   Lorg/scalatest/tools/JUnitXmlReporter;
    MethodParameters:
      Name                           Flags
      $outer                         final synthetic
}
InnerClasses:
  public #13= #10 of #12;                 // Testcase=class org/scalatest/tools/JUnitXmlReporter$Testcase of class org/scalatest/tools/JUnitXmlReporter
  public #14= #2 of #12;                  // Testcase$=class org/scalatest/tools/JUnitXmlReporter$Testcase$ of class org/scalatest/tools/JUnitXmlReporter
Signature: #3                           // Lscala/runtime/AbstractFunction3<Ljava/lang/String;Lscala/Option<Ljava/lang/String;>;Ljava/lang/Object;Lorg/scalatest/tools/JUnitXmlReporter$Testcase;>;Ljava/io/Serializable;
SourceFile: "JUnitXmlReporter.scala"
  ScalaInlineInfo: length = 0x1D (unknown attribute)
   01 01 00 05 00 1E 00 57 01 00 16 00 4A 01 00 16
   00 17 01 00 11 00 12 01 00 25 00 26 01
  Scala: length = 0x0 (unknown attribute)

