Classfile /Users/mw/Projects/slang-braindump/.jar/jar8/assemble/slang-braindump/assemble/content/org/scalatest/tools/JvmArg.class
  Last modified May 29, 2022; size 1271 bytes
  SHA-256 checksum f2895826679f0575a7c84429a38c98633502f21a8fca974e5261dbd9e373dcb4
  Compiled from "ScalaTestAntTask.scala"
public class org.scalatest.tools.JvmArg
  minor version: 0
  major version: 52
  flags: (0x0021) ACC_PUBLIC, ACC_SUPER
  this_class: #2                          // org/scalatest/tools/JvmArg
  super_class: #4                         // java/lang/Object
  interfaces: 0, fields: 1, methods: 5, attributes: 4
Constant pool:
   #1 = Utf8               org/scalatest/tools/JvmArg
   #2 = Class              #1             // org/scalatest/tools/JvmArg
   #3 = Utf8               java/lang/Object
   #4 = Class              #3             // java/lang/Object
   #5 = Utf8               ScalaTestAntTask.scala
   #6 = Utf8               Lscala/reflect/ScalaSignature;
   #7 = Utf8               bytes
   #8 = Utf8               \u0006\u0005M2Aa\u0002\u0005\u0005\u001f!)a\u0003\u0001C\u0001/!9!\u0004\u0001a\u0001\n\u0013Y\u0002bB\u0014\u0001\u0001\u0004%I\u0001\u000b\u0005\u0007]\u0001\u0001\u000b\u0015\u0002\u000f\t\u000b=\u0002A\u0011\u0001\u0019\t\u000bI\u0002A\u0011A\u000e\u0003\r)3X.\u0011:h\u0015\tI!\"A\u0003u_>d7O\u0003\u0002\f\u0019\u0005I1oY1mCR,7\u000f\u001e\u0006\u0002\u001b\u0005\u0019qN]4\u0004\u0001M\u0011\u0001\u0001\u0005\t\u0003#Qi\u0011A\u0005\u0006\u0002\'\u0005)1oY1mC&\u0011QC\u0005\u0002\u0007\u0003:L(+\u001a4\u0002\rqJg.\u001b;?)\u0005A\u0002CA\r\u0001\u001b\u0005A\u0011!\u0002<bYV,W#\u0001\u000f\u0011\u0005u!cB\u0001\u0010#!\ty\"#D\u0001!\u0015\t\tc\"\u0001\u0004=e>|GOP\u0005\u0003GI\ta\u0001\u0015:fI\u00164\u0017BA\u0013\'\u0005\u0019\u0019FO]5oO*\u00111EE\u0001\nm\u0006dW/Z0%KF$\"!\u000b\u0017\u0011\u0005EQ\u0013BA\u0016\u0013\u0005\u0011)f.\u001b;\t\u000f5\u001a\u0011\u0011!a\u00019\u0005\u0019\u0001\u0010J\u0019\u0002\rY\fG.^3!\u0003!\u0019X\r\u001e,bYV,GCA\u00152\u0011\u0015QR\u00011\u0001\u001d\u0003!9W\r\u001e,bYV,\u0007
   #9 = Utf8               value
  #10 = Utf8               Ljava/lang/String;
  #11 = Utf8               ()Ljava/lang/String;
  #12 = NameAndType        #9:#10         // value:Ljava/lang/String;
  #13 = Fieldref           #2.#12         // org/scalatest/tools/JvmArg.value:Ljava/lang/String;
  #14 = Utf8               this
  #15 = Utf8               Lorg/scalatest/tools/JvmArg;
  #16 = Utf8               value_$eq
  #17 = Utf8               (Ljava/lang/String;)V
  #18 = Utf8               x$1
  #19 = Utf8               setValue
  #20 = NameAndType        #16:#17        // value_$eq:(Ljava/lang/String;)V
  #21 = Methodref          #2.#20         // org/scalatest/tools/JvmArg.value_$eq:(Ljava/lang/String;)V
  #22 = Utf8               getValue
  #23 = NameAndType        #9:#11         // value:()Ljava/lang/String;
  #24 = Methodref          #2.#23         // org/scalatest/tools/JvmArg.value:()Ljava/lang/String;
  #25 = Utf8               <init>
  #26 = Utf8               ()V
  #27 = NameAndType        #25:#26        // "<init>":()V
  #28 = Methodref          #4.#27         // java/lang/Object."<init>":()V
  #29 = Utf8               Code
  #30 = Utf8               LineNumberTable
  #31 = Utf8               LocalVariableTable
  #32 = Utf8               MethodParameters
  #33 = Utf8               SourceFile
  #34 = Utf8               RuntimeVisibleAnnotations
  #35 = Utf8               ScalaInlineInfo
  #36 = Utf8               ScalaSig
{
  private java.lang.String value;
    descriptor: Ljava/lang/String;
    flags: (0x0002) ACC_PRIVATE

  private java.lang.String value();
    descriptor: ()Ljava/lang/String;
    flags: (0x0002) ACC_PRIVATE
    Code:
      stack=1, locals=1, args_size=1
         0: aload_0
         1: getfield      #13                 // Field value:Ljava/lang/String;
         4: areturn
      LineNumberTable:
        line 1092: 0
      LocalVariableTable:
        Start  Length  Slot  Name   Signature
            0       5     0  this   Lorg/scalatest/tools/JvmArg;

  private void value_$eq(java.lang.String);
    descriptor: (Ljava/lang/String;)V
    flags: (0x0002) ACC_PRIVATE
    Code:
      stack=2, locals=2, args_size=2
         0: aload_0
         1: aload_1
         2: putfield      #13                 // Field value:Ljava/lang/String;
         5: return
      LineNumberTable:
        line 1092: 0
      LocalVariableTable:
        Start  Length  Slot  Name   Signature
            0       6     0  this   Lorg/scalatest/tools/JvmArg;
            0       6     1   x$1   Ljava/lang/String;
    MethodParameters:
      Name                           Flags
      x$1                            final

  public void setValue(java.lang.String);
    descriptor: (Ljava/lang/String;)V
    flags: (0x0001) ACC_PUBLIC
    Code:
      stack=2, locals=2, args_size=2
         0: aload_0
         1: aload_1
         2: invokespecial #21                 // Method value_$eq:(Ljava/lang/String;)V
         5: return
      LineNumberTable:
        line 1094: 0
      LocalVariableTable:
        Start  Length  Slot  Name   Signature
            0       6     0  this   Lorg/scalatest/tools/JvmArg;
            0       6     1 value   Ljava/lang/String;
    MethodParameters:
      Name                           Flags
      value                          final

  public java.lang.String getValue();
    descriptor: ()Ljava/lang/String;
    flags: (0x0001) ACC_PUBLIC
    Code:
      stack=1, locals=1, args_size=1
         0: aload_0
         1: invokespecial #24                 // Method value:()Ljava/lang/String;
         4: areturn
      LineNumberTable:
        line 1095: 0
      LocalVariableTable:
        Start  Length  Slot  Name   Signature
            0       5     0  this   Lorg/scalatest/tools/JvmArg;

  public org.scalatest.tools.JvmArg();
    descriptor: ()V
    flags: (0x0001) ACC_PUBLIC
    Code:
      stack=2, locals=1, args_size=1
         0: aload_0
         1: invokespecial #28                 // Method java/lang/Object."<init>":()V
         4: aload_0
         5: aconst_null
         6: putfield      #13                 // Field value:Ljava/lang/String;
         9: return
      LineNumberTable:
        line 1101: 0
        line 1092: 4
        line 1091: 9
      LocalVariableTable:
        Start  Length  Slot  Name   Signature
            0      10     0  this   Lorg/scalatest/tools/JvmArg;
}
SourceFile: "ScalaTestAntTask.scala"
RuntimeVisibleAnnotations:
  0: #6(#7=s#8)
    scala.reflect.ScalaSignature(
      bytes="\u0006\u0005M2Aa\u0002\u0005\u0005\u001f!)a\u0003\u0001C\u0001/!9!\u0004\u0001a\u0001\n\u0013Y\u0002bB\u0014\u0001\u0001\u0004%I\u0001\u000b\u0005\u0007]\u0001\u0001\u000b\u0015\u0002\u000f\t\u000b=\u0002A\u0011\u0001\u0019\t\u000bI\u0002A\u0011A\u000e\u0003\r)3X.\u0011:h\u0015\tI!\"A\u0003u_>d7O\u0003\u0002\f\u0019\u0005I1oY1mCR,7\u000f\u001e\u0006\u0002\u001b\u0005\u0019qN]4\u0004\u0001M\u0011\u0001\u0001\u0005\t\u0003#Qi\u0011A\u0005\u0006\u0002\'\u0005)1oY1mC&\u0011QC\u0005\u0002\u0007\u0003:L(+\u001a4\u0002\rqJg.\u001b;?)\u0005A\u0002CA\r\u0001\u001b\u0005A\u0011!\u0002<bYV,W#\u0001\u000f\u0011\u0005u!cB\u0001\u0010#!\ty\"#D\u0001!\u0015\t\tc\"\u0001\u0004=e>|GOP\u0005\u0003GI\ta\u0001\u0015:fI\u00164\u0017BA\u0013\'\u0005\u0019\u0019FO]5oO*\u00111EE\u0001\nm\u0006dW/Z0%KF$\"!\u000b\u0017\u0011\u0005EQ\u0013BA\u0016\u0013\u0005\u0011)f.\u001b;\t\u000f5\u001a\u0011\u0011!a\u00019\u0005\u0019\u0001\u0010J\u0019\u0002\rY\fG.^3!\u0003!\u0019X\r\u001e,bYV,GCA\u00152\u0011\u0015QR\u00011\u0001\u001d\u0003!9W\r\u001e,bYV,\u0007"
    )
  ScalaInlineInfo: length = 0x1D (unknown attribute)
   01 00 00 05 00 19 00 1A 00 00 16 00 0B 00 00 13
   00 11 00 00 09 00 0B 01 00 10 00 11 01
  ScalaSig: length = 0x3 (unknown attribute)
   05 02 00
