Classfile /Users/mw/Projects/slang-braindump/.jar/jar8/assemble/slang-braindump/assemble/content/org/scalatest/tools/Memento$.class
  Last modified May 29, 2022; size 9981 bytes
  SHA-256 checksum 3538c25e224c92dd32e3068d4c408557f42eedac2752e6846604325b28a3b647
  Compiled from "Memento.scala"
public final class org.scalatest.tools.Memento$ implements java.io.Serializable
  minor version: 0
  major version: 52
  flags: (0x0031) ACC_PUBLIC, ACC_FINAL, ACC_SUPER
  this_class: #2                          // org/scalatest/tools/Memento$
  super_class: #4                         // java/lang/Object
  interfaces: 1, fields: 2, methods: 20, attributes: 5
Constant pool:
    #1 = Utf8               org/scalatest/tools/Memento$
    #2 = Class              #1            // org/scalatest/tools/Memento$
    #3 = Utf8               java/lang/Object
    #4 = Class              #3            // java/lang/Object
    #5 = Utf8               java/io/Serializable
    #6 = Class              #5            // java/io/Serializable
    #7 = Utf8               Memento.scala
    #8 = Utf8               java/lang/invoke/MethodHandles$Lookup
    #9 = Class              #8            // java/lang/invoke/MethodHandles$Lookup
   #10 = Utf8               java/lang/invoke/MethodHandles
   #11 = Class              #10           // java/lang/invoke/MethodHandles
   #12 = Utf8               Lookup
   #13 = Utf8               MODULE$
   #14 = Utf8               Lorg/scalatest/tools/Memento$;
   #15 = Utf8               SomeNonePat
   #16 = Utf8               Ljava/util/regex/Pattern;
   #17 = Utf8               <clinit>
   #18 = Utf8               ()V
   #19 = Utf8               <init>
   #20 = NameAndType        #19:#18       // "<init>":()V
   #21 = Methodref          #2.#20        // org/scalatest/tools/Memento$."<init>":()V
   #22 = NameAndType        #13:#14       // MODULE$:Lorg/scalatest/tools/Memento$;
   #23 = Fieldref           #2.#22        // org/scalatest/tools/Memento$.MODULE$:Lorg/scalatest/tools/Memento$;
   #24 = Utf8               ^(Some\\(|None)(.*?)\\)?$
   #25 = String             #24           // ^(Some\\(|None)(.*?)\\)?$
   #26 = Utf8               java/util/regex/Pattern
   #27 = Class              #26           // java/util/regex/Pattern
   #28 = Utf8               compile
   #29 = Utf8               (Ljava/lang/String;)Ljava/util/regex/Pattern;
   #30 = NameAndType        #28:#29       // compile:(Ljava/lang/String;)Ljava/util/regex/Pattern;
   #31 = Methodref          #27.#30       // java/util/regex/Pattern.compile:(Ljava/lang/String;)Ljava/util/regex/Pattern;
   #32 = NameAndType        #15:#16       // SomeNonePat:Ljava/util/regex/Pattern;
   #33 = Fieldref           #2.#32        // org/scalatest/tools/Memento$.SomeNonePat:Ljava/util/regex/Pattern;
   #34 = Utf8               apply
   #35 = Utf8               (Lorg/scalatest/events/Event;)Lorg/scalatest/tools/Memento;
   #36 = Utf8               event
   #37 = Utf8               org/scalatest/events/TestFailed
   #38 = Class              #37           // org/scalatest/events/TestFailed
   #39 = Utf8               scala/Tuple4
   #40 = Class              #39           // scala/Tuple4
   #41 = Utf8               TestFailed
   #42 = String             #41           // TestFailed
   #43 = Utf8               rerunner
   #44 = Utf8               ()Lscala/Option;
   #45 = NameAndType        #43:#44       // rerunner:()Lscala/Option;
   #46 = Methodref          #38.#45       // org/scalatest/events/TestFailed.rerunner:()Lscala/Option;
   #47 = Utf8               suiteId
   #48 = Utf8               ()Ljava/lang/String;
   #49 = NameAndType        #47:#48       // suiteId:()Ljava/lang/String;
   #50 = Methodref          #38.#49       // org/scalatest/events/TestFailed.suiteId:()Ljava/lang/String;
   #51 = Utf8               scala/Some
   #52 = Class              #51           // scala/Some
   #53 = Utf8               testName
   #54 = NameAndType        #53:#48       // testName:()Ljava/lang/String;
   #55 = Methodref          #38.#54       // org/scalatest/events/TestFailed.testName:()Ljava/lang/String;
   #56 = Utf8               (Ljava/lang/Object;)V
   #57 = NameAndType        #19:#56       // "<init>":(Ljava/lang/Object;)V
   #58 = Methodref          #52.#57       // scala/Some."<init>":(Ljava/lang/Object;)V
   #59 = Utf8               (Ljava/lang/Object;Ljava/lang/Object;Ljava/lang/Object;Ljava/lang/Object;)V
   #60 = NameAndType        #19:#59       // "<init>":(Ljava/lang/Object;Ljava/lang/Object;Ljava/lang/Object;Ljava/lang/Object;)V
   #61 = Methodref          #40.#60       // scala/Tuple4."<init>":(Ljava/lang/Object;Ljava/lang/Object;Ljava/lang/Object;Ljava/lang/Object;)V
   #62 = Utf8               org/scalatest/events/TestCanceled
   #63 = Class              #62           // org/scalatest/events/TestCanceled
   #64 = Utf8               TestCanceled
   #65 = String             #64           // TestCanceled
   #66 = Methodref          #63.#45       // org/scalatest/events/TestCanceled.rerunner:()Lscala/Option;
   #67 = Methodref          #63.#49       // org/scalatest/events/TestCanceled.suiteId:()Ljava/lang/String;
   #68 = Methodref          #63.#54       // org/scalatest/events/TestCanceled.testName:()Ljava/lang/String;
   #69 = Utf8               org/scalatest/events/SuiteAborted
   #70 = Class              #69           // org/scalatest/events/SuiteAborted
   #71 = Utf8               SuiteAborted
   #72 = String             #71           // SuiteAborted
   #73 = Methodref          #70.#45       // org/scalatest/events/SuiteAborted.rerunner:()Lscala/Option;
   #74 = Methodref          #70.#49       // org/scalatest/events/SuiteAborted.suiteId:()Ljava/lang/String;
   #75 = Utf8               scala/None$
   #76 = Class              #75           // scala/None$
   #77 = Utf8               Lscala/None$;
   #78 = NameAndType        #13:#77       // MODULE$:Lscala/None$;
   #79 = Fieldref           #76.#78       // scala/None$.MODULE$:Lscala/None$;
   #80 = Utf8               unexpected
   #81 = String             #80           // unexpected
   #82 = Utf8               org/scalatest/events/Event
   #83 = Class              #82           // org/scalatest/events/Event
   #84 = Utf8               toString
   #85 = NameAndType        #84:#48       // toString:()Ljava/lang/String;
   #86 = Methodref          #83.#85       // org/scalatest/events/Event.toString:()Ljava/lang/String;
   #87 = Utf8               _1
   #88 = Utf8               ()Ljava/lang/Object;
   #89 = NameAndType        #87:#88       // _1:()Ljava/lang/Object;
   #90 = Methodref          #40.#89       // scala/Tuple4._1:()Ljava/lang/Object;
   #91 = Utf8               java/lang/String
   #92 = Class              #91           // java/lang/String
   #93 = Utf8               _2
   #94 = NameAndType        #93:#88       // _2:()Ljava/lang/Object;
   #95 = Methodref          #40.#94       // scala/Tuple4._2:()Ljava/lang/Object;
   #96 = Utf8               scala/Option
   #97 = Class              #96           // scala/Option
   #98 = Utf8               _3
   #99 = NameAndType        #98:#88       // _3:()Ljava/lang/Object;
  #100 = Methodref          #40.#99       // scala/Tuple4._3:()Ljava/lang/Object;
  #101 = Utf8               _4
  #102 = NameAndType        #101:#88      // _4:()Ljava/lang/Object;
  #103 = Methodref          #40.#102      // scala/Tuple4._4:()Ljava/lang/Object;
  #104 = Utf8               scala/MatchError
  #105 = Class              #104          // scala/MatchError
  #106 = Methodref          #105.#57      // scala/MatchError."<init>":(Ljava/lang/Object;)V
  #107 = Utf8               org/scalatest/tools/Memento
  #108 = Class              #107          // org/scalatest/tools/Memento
  #109 = Utf8               (Ljava/lang/String;Lscala/Option;Ljava/lang/String;Lscala/Option;)V
  #110 = NameAndType        #19:#109      // "<init>":(Ljava/lang/String;Lscala/Option;Ljava/lang/String;Lscala/Option;)V
  #111 = Methodref          #108.#110     // org/scalatest/tools/Memento."<init>":(Ljava/lang/String;Lscala/Option;Ljava/lang/String;Lscala/Option;)V
  #112 = Utf8               eventName
  #113 = Utf8               Ljava/lang/String;
  #114 = Utf8               className
  #115 = Utf8               Lscala/Option;
  #116 = Utf8               this
  #117 = Utf8               Lorg/scalatest/events/Event;
  #118 = Utf8               readFromFile
  #119 = Utf8               (Ljava/lang/String;)Lscala/collection/immutable/List;
  #120 = Utf8               (Ljava/lang/String;)Lscala/collection/immutable/List<Lorg/scalatest/tools/Memento;>;
  #121 = Utf8               fileName
  #122 = Utf8               scala/io/Source$
  #123 = Class              #122          // scala/io/Source$
  #124 = Utf8               Lscala/io/Source$;
  #125 = NameAndType        #13:#124      // MODULE$:Lscala/io/Source$;
  #126 = Fieldref           #123.#125     // scala/io/Source$.MODULE$:Lscala/io/Source$;
  #127 = Utf8               scala/io/Codec$
  #128 = Class              #127          // scala/io/Codec$
  #129 = Utf8               Lscala/io/Codec$;
  #130 = NameAndType        #13:#129      // MODULE$:Lscala/io/Codec$;
  #131 = Fieldref           #128.#130     // scala/io/Codec$.MODULE$:Lscala/io/Codec$;
  #132 = Utf8               fallbackSystemCodec
  #133 = Utf8               ()Lscala/io/Codec;
  #134 = NameAndType        #132:#133     // fallbackSystemCodec:()Lscala/io/Codec;
  #135 = Methodref          #128.#134     // scala/io/Codec$.fallbackSystemCodec:()Lscala/io/Codec;
  #136 = Utf8               fromFile
  #137 = Utf8               (Ljava/lang/String;Lscala/io/Codec;)Lscala/io/BufferedSource;
  #138 = NameAndType        #136:#137     // fromFile:(Ljava/lang/String;Lscala/io/Codec;)Lscala/io/BufferedSource;
  #139 = Methodref          #123.#138     // scala/io/Source$.fromFile:(Ljava/lang/String;Lscala/io/Codec;)Lscala/io/BufferedSource;
  #140 = Utf8               scala/io/BufferedSource
  #141 = Class              #140          // scala/io/BufferedSource
  #142 = Utf8               getLines
  #143 = Utf8               ()Lscala/collection/Iterator;
  #144 = NameAndType        #142:#143     // getLines:()Lscala/collection/Iterator;
  #145 = Methodref          #141.#144     // scala/io/BufferedSource.getLines:()Lscala/collection/Iterator;
  #146 = Utf8               scala/collection/Iterator
  #147 = Class              #146          // scala/collection/Iterator
  #148 = Utf8               toList
  #149 = Utf8               ()Lscala/collection/immutable/List;
  #150 = NameAndType        #148:#149     // toList:()Lscala/collection/immutable/List;
  #151 = InterfaceMethodref #147.#150     // scala/collection/Iterator.toList:()Lscala/collection/immutable/List;
  #152 = Utf8               (Ljava/lang/Object;)Ljava/lang/Object;
  #153 = MethodType         #152          //  (Ljava/lang/Object;)Ljava/lang/Object;
  #154 = Utf8               $anonfun$readFromFile$1
  #155 = Utf8               (Ljava/lang/String;)Lorg/scalatest/tools/Memento;
  #156 = NameAndType        #154:#155     // $anonfun$readFromFile$1:(Ljava/lang/String;)Lorg/scalatest/tools/Memento;
  #157 = Methodref          #2.#156       // org/scalatest/tools/Memento$.$anonfun$readFromFile$1:(Ljava/lang/String;)Lorg/scalatest/tools/Memento;
  #158 = MethodHandle       6:#157        // REF_invokeStatic org/scalatest/tools/Memento$.$anonfun$readFromFile$1:(Ljava/lang/String;)Lorg/scalatest/tools/Memento;
  #159 = MethodType         #155          //  (Ljava/lang/String;)Lorg/scalatest/tools/Memento;
  #160 = Integer            5
  #161 = Integer            1
  #162 = Utf8               java/lang/invoke/LambdaMetafactory
  #163 = Class              #162          // java/lang/invoke/LambdaMetafactory
  #164 = Utf8               altMetafactory
  #165 = Utf8               (Ljava/lang/invoke/MethodHandles$Lookup;Ljava/lang/String;Ljava/lang/invoke/MethodType;[Ljava/lang/Object;)Ljava/lang/invoke/CallSite;
  #166 = NameAndType        #164:#165     // altMetafactory:(Ljava/lang/invoke/MethodHandles$Lookup;Ljava/lang/String;Ljava/lang/invoke/MethodType;[Ljava/lang/Object;)Ljava/lang/invoke/CallSite;
  #167 = Methodref          #163.#166     // java/lang/invoke/LambdaMetafactory.altMetafactory:(Ljava/lang/invoke/MethodHandles$Lookup;Ljava/lang/String;Ljava/lang/invoke/MethodType;[Ljava/lang/Object;)Ljava/lang/invoke/CallSite;
  #168 = MethodHandle       6:#167        // REF_invokeStatic java/lang/invoke/LambdaMetafactory.altMetafactory:(Ljava/lang/invoke/MethodHandles$Lookup;Ljava/lang/String;Ljava/lang/invoke/MethodType;[Ljava/lang/Object;)Ljava/lang/invoke/CallSite;
  #169 = Utf8               ()Lscala/Function1;
  #170 = NameAndType        #34:#169      // apply:()Lscala/Function1;
  #171 = InvokeDynamic      #0:#170       // #0:apply:()Lscala/Function1;
  #172 = Utf8               scala/collection/immutable/List
  #173 = Class              #172          // scala/collection/immutable/List
  #174 = Utf8               map
  #175 = Utf8               (Lscala/Function1;)Lscala/collection/immutable/List;
  #176 = NameAndType        #174:#175     // map:(Lscala/Function1;)Lscala/collection/immutable/List;
  #177 = Methodref          #173.#176     // scala/collection/immutable/List.map:(Lscala/Function1;)Lscala/collection/immutable/List;
  #178 = Utf8               close
  #179 = NameAndType        #178:#18      // close:()V
  #180 = Methodref          #141.#179     // scala/io/BufferedSource.close:()V
  #181 = Utf8               source
  #182 = Utf8               Lscala/io/BufferedSource;
  #183 = Utf8               java/lang/Throwable
  #184 = Class              #183          // java/lang/Throwable
  #185 = Utf8               writeToFile
  #186 = Utf8               (Ljava/lang/String;Lscala/collection/immutable/Set;)V
  #187 = Utf8               (Ljava/lang/String;Lscala/collection/immutable/Set<Lorg/scalatest/tools/Memento;>;)V
  #188 = Utf8               mementos
  #189 = Utf8               java/io/PrintWriter
  #190 = Class              #189          // java/io/PrintWriter
  #191 = Utf8               UTF-8
  #192 = String             #191          // UTF-8
  #193 = Utf8               (Ljava/lang/String;Ljava/lang/String;)V
  #194 = NameAndType        #19:#193      // "<init>":(Ljava/lang/String;Ljava/lang/String;)V
  #195 = Methodref          #190.#194     // java/io/PrintWriter."<init>":(Ljava/lang/String;Ljava/lang/String;)V
  #196 = Utf8               $anonfun$writeToFile$1
  #197 = Utf8               (Lorg/scalatest/tools/Memento;)Ljava/lang/String;
  #198 = NameAndType        #196:#197     // $anonfun$writeToFile$1:(Lorg/scalatest/tools/Memento;)Ljava/lang/String;
  #199 = Methodref          #2.#198       // org/scalatest/tools/Memento$.$anonfun$writeToFile$1:(Lorg/scalatest/tools/Memento;)Ljava/lang/String;
  #200 = MethodHandle       6:#199        // REF_invokeStatic org/scalatest/tools/Memento$.$anonfun$writeToFile$1:(Lorg/scalatest/tools/Memento;)Ljava/lang/String;
  #201 = MethodType         #197          //  (Lorg/scalatest/tools/Memento;)Ljava/lang/String;
  #202 = InvokeDynamic      #1:#170       // #1:apply:()Lscala/Function1;
  #203 = Utf8               scala/collection/immutable/Set
  #204 = Class              #203          // scala/collection/immutable/Set
  #205 = Utf8               (Lscala/Function1;)Ljava/lang/Object;
  #206 = NameAndType        #174:#205     // map:(Lscala/Function1;)Ljava/lang/Object;
  #207 = InterfaceMethodref #204.#206     // scala/collection/immutable/Set.map:(Lscala/Function1;)Ljava/lang/Object;
  #208 = Utf8               scala/collection/IterableOnceOps
  #209 = Class              #208          // scala/collection/IterableOnceOps
  #210 = InterfaceMethodref #209.#150     // scala/collection/IterableOnceOps.toList:()Lscala/collection/immutable/List;
  #211 = Utf8               (Ljava/lang/Object;Ljava/lang/Object;)Ljava/lang/Object;
  #212 = MethodType         #211          //  (Ljava/lang/Object;Ljava/lang/Object;)Ljava/lang/Object;
  #213 = Utf8               $anonfun$writeToFile$2$adapted
  #214 = Utf8               (Ljava/lang/String;Ljava/lang/String;)Ljava/lang/Object;
  #215 = NameAndType        #213:#214     // $anonfun$writeToFile$2$adapted:(Ljava/lang/String;Ljava/lang/String;)Ljava/lang/Object;
  #216 = Methodref          #2.#215       // org/scalatest/tools/Memento$.$anonfun$writeToFile$2$adapted:(Ljava/lang/String;Ljava/lang/String;)Ljava/lang/Object;
  #217 = MethodHandle       6:#216        // REF_invokeStatic org/scalatest/tools/Memento$.$anonfun$writeToFile$2$adapted:(Ljava/lang/String;Ljava/lang/String;)Ljava/lang/Object;
  #218 = MethodType         #214          //  (Ljava/lang/String;Ljava/lang/String;)Ljava/lang/Object;
  #219 = Utf8               ()Lscala/Function2;
  #220 = NameAndType        #34:#219      // apply:()Lscala/Function2;
  #221 = InvokeDynamic      #2:#220       // #2:apply:()Lscala/Function2;
  #222 = Utf8               sortWith
  #223 = Utf8               (Lscala/Function2;)Ljava/lang/Object;
  #224 = NameAndType        #222:#223     // sortWith:(Lscala/Function2;)Ljava/lang/Object;
  #225 = Methodref          #173.#224     // scala/collection/immutable/List.sortWith:(Lscala/Function2;)Ljava/lang/Object;
  #226 = Utf8               $anonfun$writeToFile$3$adapted
  #227 = Utf8               (Ljava/io/PrintWriter;Ljava/lang/String;)Ljava/lang/Object;
  #228 = NameAndType        #226:#227     // $anonfun$writeToFile$3$adapted:(Ljava/io/PrintWriter;Ljava/lang/String;)Ljava/lang/Object;
  #229 = Methodref          #2.#228       // org/scalatest/tools/Memento$.$anonfun$writeToFile$3$adapted:(Ljava/io/PrintWriter;Ljava/lang/String;)Ljava/lang/Object;
  #230 = MethodHandle       6:#229        // REF_invokeStatic org/scalatest/tools/Memento$.$anonfun$writeToFile$3$adapted:(Ljava/io/PrintWriter;Ljava/lang/String;)Ljava/lang/Object;
  #231 = Utf8               (Ljava/lang/String;)Ljava/lang/Object;
  #232 = MethodType         #231          //  (Ljava/lang/String;)Ljava/lang/Object;
  #233 = Utf8               (Ljava/io/PrintWriter;)Lscala/Function1;
  #234 = NameAndType        #34:#233      // apply:(Ljava/io/PrintWriter;)Lscala/Function1;
  #235 = InvokeDynamic      #3:#234       // #3:apply:(Ljava/io/PrintWriter;)Lscala/Function1;
  #236 = Utf8               foreach
  #237 = Utf8               (Lscala/Function1;)V
  #238 = NameAndType        #236:#237     // foreach:(Lscala/Function1;)V
  #239 = Methodref          #173.#238     // scala/collection/immutable/List.foreach:(Lscala/Function1;)V
  #240 = Methodref          #190.#179     // java/io/PrintWriter.close:()V
  #241 = Utf8               lines
  #242 = Utf8               Lscala/collection/immutable/List;
  #243 = Utf8               out
  #244 = Utf8               Ljava/io/PrintWriter;
  #245 = Utf8               Lscala/collection/immutable/Set;
  #246 = Utf8               fromString
  #247 = Utf8               str
  #248 = Utf8
  #249 = String             #248          //
  #250 = Utf8               split
  #251 = Utf8               (Ljava/lang/String;)[Ljava/lang/String;
  #252 = NameAndType        #250:#251     // split:(Ljava/lang/String;)[Ljava/lang/String;
  #253 = Methodref          #92.#252      // java/lang/String.split:(Ljava/lang/String;)[Ljava/lang/String;
  #254 = Utf8               java/lang/Exception
  #255 = Class              #254          // java/lang/Exception
  #256 = Utf8               java/lang/StringBuilder
  #257 = Class              #256          // java/lang/StringBuilder
  #258 = Integer            18
  #259 = Utf8               (I)V
  #260 = NameAndType        #19:#259      // "<init>":(I)V
  #261 = Methodref          #257.#260     // java/lang/StringBuilder."<init>":(I)V
  #262 = Utf8               bad line format [
  #263 = String             #262          // bad line format [
  #264 = Utf8               append
  #265 = Utf8               (Ljava/lang/String;)Ljava/lang/StringBuilder;
  #266 = NameAndType        #264:#265     // append:(Ljava/lang/String;)Ljava/lang/StringBuilder;
  #267 = Methodref          #257.#266     // java/lang/StringBuilder.append:(Ljava/lang/String;)Ljava/lang/StringBuilder;
  #268 = Utf8               ]
  #269 = String             #268          // ]
  #270 = Methodref          #257.#85      // java/lang/StringBuilder.toString:()Ljava/lang/String;
  #271 = Utf8               (Ljava/lang/String;)V
  #272 = NameAndType        #19:#271      // "<init>":(Ljava/lang/String;)V
  #273 = Methodref          #255.#272     // java/lang/Exception."<init>":(Ljava/lang/String;)V
  #274 = Utf8               optionFromString
  #275 = Utf8               (Ljava/lang/String;)Lscala/Option;
  #276 = NameAndType        #274:#275     // optionFromString:(Ljava/lang/String;)Lscala/Option;
  #277 = Methodref          #2.#276       // org/scalatest/tools/Memento$.optionFromString:(Ljava/lang/String;)Lscala/Option;
  #278 = Utf8               decode
  #279 = Utf8               (Ljava/lang/String;)Ljava/lang/String;
  #280 = NameAndType        #278:#279     // decode:(Ljava/lang/String;)Ljava/lang/String;
  #281 = Methodref          #2.#280       // org/scalatest/tools/Memento$.decode:(Ljava/lang/String;)Ljava/lang/String;
  #282 = Utf8               splits
  #283 = Utf8               [Ljava/lang/String;
  #284 = Class              #283          // "[Ljava/lang/String;"
  #285 = Utf8               ()Ljava/util/regex/Pattern;
  #286 = Utf8               (Ljava/lang/String;)Lscala/Option<Ljava/lang/String;>;
  #287 = NameAndType        #15:#285      // SomeNonePat:()Ljava/util/regex/Pattern;
  #288 = Methodref          #2.#287       // org/scalatest/tools/Memento$.SomeNonePat:()Ljava/util/regex/Pattern;
  #289 = Utf8               matcher
  #290 = Utf8               (Ljava/lang/CharSequence;)Ljava/util/regex/Matcher;
  #291 = NameAndType        #289:#290     // matcher:(Ljava/lang/CharSequence;)Ljava/util/regex/Matcher;
  #292 = Methodref          #27.#291      // java/util/regex/Pattern.matcher:(Ljava/lang/CharSequence;)Ljava/util/regex/Matcher;
  #293 = Utf8               java/util/regex/Matcher
  #294 = Class              #293          // java/util/regex/Matcher
  #295 = Utf8               find
  #296 = Utf8               ()Z
  #297 = NameAndType        #295:#296     // find:()Z
  #298 = Methodref          #294.#297     // java/util/regex/Matcher.find:()Z
  #299 = Integer            20
  #300 = Utf8               bad option string [
  #301 = String             #300          // bad option string [
  #302 = Utf8               group
  #303 = Utf8               (I)Ljava/lang/String;
  #304 = NameAndType        #302:#303     // group:(I)Ljava/lang/String;
  #305 = Methodref          #294.#304     // java/util/regex/Matcher.group:(I)Ljava/lang/String;
  #306 = Utf8               hashCode
  #307 = Utf8               ()I
  #308 = NameAndType        #306:#307     // hashCode:()I
  #309 = Methodref          #92.#308      // java/lang/String.hashCode:()I
  #310 = Utf8               None
  #311 = String             #310          // None
  #312 = Utf8               equals
  #313 = Utf8               (Ljava/lang/Object;)Z
  #314 = NameAndType        #312:#313     // equals:(Ljava/lang/Object;)Z
  #315 = Methodref          #92.#314      // java/lang/String.equals:(Ljava/lang/Object;)Z
  #316 = Utf8               Some(
  #317 = String             #316          // Some(
  #318 = Utf8               bad Option format [
  #319 = String             #318          // bad Option format [
  #320 = Utf8               Ljava/util/regex/Matcher;
  #321 = Utf8               encode
  #322 = Utf8               text
  #323 = Utf8               \\\\
  #324 = String             #323          // \\\\
  #325 = Utf8               \\\\5c
  #326 = String             #325          // \\\\5c
  #327 = Utf8               replaceAll
  #328 = Utf8               (Ljava/lang/String;Ljava/lang/String;)Ljava/lang/String;
  #329 = NameAndType        #327:#328     // replaceAll:(Ljava/lang/String;Ljava/lang/String;)Ljava/lang/String;
  #330 = Methodref          #92.#329      // java/lang/String.replaceAll:(Ljava/lang/String;Ljava/lang/String;)Ljava/lang/String;
  #331 = Utf8               \n
  #332 = String             #331          // \n
  #333 = Utf8               \\\\1f
  #334 = String             #333          // \\\\1f
  #335 = Utf8               _
  #336 = String             #335          // _
  #337 = Utf8               \\\\5f
  #338 = String             #337          // \\\\5f
  #339 = Utf8               (Ljava/lang/String;Lscala/Option;Ljava/lang/String;Lscala/Option;)Lorg/scalatest/tools/Memento;
  #340 = Utf8               (Ljava/lang/String;Lscala/Option<Ljava/lang/String;>;Ljava/lang/String;Lscala/Option<Ljava/lang/String;>;)Lorg/scalatest/tools/Memento;
  #341 = Utf8               unapply
  #342 = Utf8               (Lorg/scalatest/tools/Memento;)Lscala/Option;
  #343 = Utf8               (Lorg/scalatest/tools/Memento;)Lscala/Option<Lscala/Tuple4<Ljava/lang/String;Lscala/Option<Ljava/lang/String;>;Ljava/lang/String;Lscala/Option<Ljava/lang/String;>;>;>;
  #344 = Utf8               x$0
  #345 = NameAndType        #112:#48      // eventName:()Ljava/lang/String;
  #346 = Methodref          #108.#345     // org/scalatest/tools/Memento.eventName:()Ljava/lang/String;
  #347 = NameAndType        #114:#44      // className:()Lscala/Option;
  #348 = Methodref          #108.#347     // org/scalatest/tools/Memento.className:()Lscala/Option;
  #349 = Methodref          #108.#49      // org/scalatest/tools/Memento.suiteId:()Ljava/lang/String;
  #350 = NameAndType        #53:#44       // testName:()Lscala/Option;
  #351 = Methodref          #108.#350     // org/scalatest/tools/Memento.testName:()Lscala/Option;
  #352 = Utf8               Lorg/scalatest/tools/Memento;
  #353 = Utf8               writeReplace
  #354 = Utf8               scala/runtime/ModuleSerializationProxy
  #355 = Class              #354          // scala/runtime/ModuleSerializationProxy
  #356 = Utf8               (Ljava/lang/Class;)V
  #357 = NameAndType        #19:#356      // "<init>":(Ljava/lang/Class;)V
  #358 = Methodref          #355.#357     // scala/runtime/ModuleSerializationProxy."<init>":(Ljava/lang/Class;)V
  #359 = Utf8               line
  #360 = NameAndType        #246:#155     // fromString:(Ljava/lang/String;)Lorg/scalatest/tools/Memento;
  #361 = Methodref          #2.#360       // org/scalatest/tools/Memento$.fromString:(Ljava/lang/String;)Lorg/scalatest/tools/Memento;
  #362 = Utf8               x$3
  #363 = Utf8               singleLine
  #364 = NameAndType        #363:#48      // singleLine:()Ljava/lang/String;
  #365 = Methodref          #108.#364     // org/scalatest/tools/Memento.singleLine:()Ljava/lang/String;
  #366 = Utf8               $anonfun$writeToFile$2
  #367 = Utf8               (Ljava/lang/String;Ljava/lang/String;)Z
  #368 = Utf8               x$4
  #369 = Utf8               x$5
  #370 = Utf8               scala/collection/StringOps$
  #371 = Class              #370          // scala/collection/StringOps$
  #372 = Utf8               Lscala/collection/StringOps$;
  #373 = NameAndType        #13:#372      // MODULE$:Lscala/collection/StringOps$;
  #374 = Fieldref           #371.#373     // scala/collection/StringOps$.MODULE$:Lscala/collection/StringOps$;
  #375 = Utf8               scala/Predef$
  #376 = Class              #375          // scala/Predef$
  #377 = Utf8               Lscala/Predef$;
  #378 = NameAndType        #13:#377      // MODULE$:Lscala/Predef$;
  #379 = Fieldref           #376.#378     // scala/Predef$.MODULE$:Lscala/Predef$;
  #380 = Utf8               augmentString
  #381 = NameAndType        #380:#279     // augmentString:(Ljava/lang/String;)Ljava/lang/String;
  #382 = Methodref          #376.#381     // scala/Predef$.augmentString:(Ljava/lang/String;)Ljava/lang/String;
  #383 = Utf8               $less$extension
  #384 = NameAndType        #383:#367     // $less$extension:(Ljava/lang/String;Ljava/lang/String;)Z
  #385 = Methodref          #371.#384     // scala/collection/StringOps$.$less$extension:(Ljava/lang/String;Ljava/lang/String;)Z
  #386 = Utf8               $anonfun$writeToFile$3
  #387 = Utf8               (Ljava/io/PrintWriter;Ljava/lang/String;)V
  #388 = Utf8               out$1
  #389 = Utf8               x$1
  #390 = Utf8               println
  #391 = NameAndType        #390:#271     // println:(Ljava/lang/String;)V
  #392 = Methodref          #190.#391     // java/io/PrintWriter.println:(Ljava/lang/String;)V
  #393 = Methodref          #4.#20        // java/lang/Object."<init>":()V
  #394 = NameAndType        #366:#367     // $anonfun$writeToFile$2:(Ljava/lang/String;Ljava/lang/String;)Z
  #395 = Methodref          #2.#394       // org/scalatest/tools/Memento$.$anonfun$writeToFile$2:(Ljava/lang/String;Ljava/lang/String;)Z
  #396 = Utf8               scala/runtime/BoxesRunTime
  #397 = Class              #396          // scala/runtime/BoxesRunTime
  #398 = Utf8               boxToBoolean
  #399 = Utf8               (Z)Ljava/lang/Boolean;
  #400 = NameAndType        #398:#399     // boxToBoolean:(Z)Ljava/lang/Boolean;
  #401 = Methodref          #397.#400     // scala/runtime/BoxesRunTime.boxToBoolean:(Z)Ljava/lang/Boolean;
  #402 = NameAndType        #386:#387     // $anonfun$writeToFile$3:(Ljava/io/PrintWriter;Ljava/lang/String;)V
  #403 = Methodref          #2.#402       // org/scalatest/tools/Memento$.$anonfun$writeToFile$3:(Ljava/io/PrintWriter;Ljava/lang/String;)V
  #404 = Utf8               scala/runtime/BoxedUnit
  #405 = Class              #404          // scala/runtime/BoxedUnit
  #406 = Utf8               UNIT
  #407 = Utf8               Lscala/runtime/BoxedUnit;
  #408 = NameAndType        #406:#407     // UNIT:Lscala/runtime/BoxedUnit;
  #409 = Fieldref           #405.#408     // scala/runtime/BoxedUnit.UNIT:Lscala/runtime/BoxedUnit;
  #410 = Utf8               $deserializeLambda$
  #411 = Utf8               (Ljava/lang/invoke/SerializedLambda;)Ljava/lang/Object;
  #412 = Utf8               scala/runtime/LambdaDeserialize
  #413 = Class              #412          // scala/runtime/LambdaDeserialize
  #414 = Utf8               bootstrap
  #415 = Utf8               (Ljava/lang/invoke/MethodHandles$Lookup;Ljava/lang/String;Ljava/lang/invoke/MethodType;[Ljava/lang/invoke/MethodHandle;)Ljava/lang/invoke/CallSite;
  #416 = NameAndType        #414:#415     // bootstrap:(Ljava/lang/invoke/MethodHandles$Lookup;Ljava/lang/String;Ljava/lang/invoke/MethodType;[Ljava/lang/invoke/MethodHandle;)Ljava/lang/invoke/CallSite;
  #417 = Methodref          #413.#416     // scala/runtime/LambdaDeserialize.bootstrap:(Ljava/lang/invoke/MethodHandles$Lookup;Ljava/lang/String;Ljava/lang/invoke/MethodType;[Ljava/lang/invoke/MethodHandle;)Ljava/lang/invoke/CallSite;
  #418 = MethodHandle       6:#417        // REF_invokeStatic scala/runtime/LambdaDeserialize.bootstrap:(Ljava/lang/invoke/MethodHandles$Lookup;Ljava/lang/String;Ljava/lang/invoke/MethodType;[Ljava/lang/invoke/MethodHandle;)Ljava/lang/invoke/CallSite;
  #419 = Utf8               lambdaDeserialize
  #420 = NameAndType        #419:#411     // lambdaDeserialize:(Ljava/lang/invoke/SerializedLambda;)Ljava/lang/Object;
  #421 = InvokeDynamic      #4:#420       // #4:lambdaDeserialize:(Ljava/lang/invoke/SerializedLambda;)Ljava/lang/Object;
  #422 = Utf8               Code
  #423 = Utf8               LineNumberTable
  #424 = Utf8               StackMapTable
  #425 = Utf8               LocalVariableTable
  #426 = Utf8               MethodParameters
  #427 = Utf8               Signature
  #428 = Utf8               InnerClasses
  #429 = Utf8               SourceFile
  #430 = Utf8               BootstrapMethods
  #431 = Utf8               ScalaInlineInfo
  #432 = Utf8               Scala
{
  public static final org.scalatest.tools.Memento$ MODULE$;
    descriptor: Lorg/scalatest/tools/Memento$;
    flags: (0x0019) ACC_PUBLIC, ACC_STATIC, ACC_FINAL

  private static final java.util.regex.Pattern SomeNonePat;
    descriptor: Ljava/util/regex/Pattern;
    flags: (0x001a) ACC_PRIVATE, ACC_STATIC, ACC_FINAL

  public static {};
    descriptor: ()V
    flags: (0x0009) ACC_PUBLIC, ACC_STATIC
    Code:
      stack=2, locals=0, args_size=0
         0: new           #2                  // class org/scalatest/tools/Memento$
         3: dup
         4: invokespecial #21                 // Method "<init>":()V
         7: putstatic     #23                 // Field MODULE$:Lorg/scalatest/tools/Memento$;
        10: ldc           #25                 // String ^(Some\\(|None)(.*?)\\)?$
        12: invokestatic  #31                 // Method java/util/regex/Pattern.compile:(Ljava/lang/String;)Ljava/util/regex/Pattern;
        15: putstatic     #33                 // Field SomeNonePat:Ljava/util/regex/Pattern;
        18: return
      LineNumberTable:
        line 85: 0
        line 156: 10
        line 85: 18

  public org.scalatest.tools.Memento apply(org.scalatest.events.Event);
    descriptor: (Lorg/scalatest/events/Event;)Lorg/scalatest/tools/Memento;
    flags: (0x0001) ACC_PUBLIC
    Code:
      stack=8, locals=22, args_size=2
         0: aload_1
         1: astore        6
         3: aload         6
         5: instanceof    #38                 // class org/scalatest/events/TestFailed
         8: ifeq          53
        11: aload         6
        13: checkcast     #38                 // class org/scalatest/events/TestFailed
        16: astore        7
        18: new           #40                 // class scala/Tuple4
        21: dup
        22: ldc           #42                 // String TestFailed
        24: aload         7
        26: invokevirtual #46                 // Method org/scalatest/events/TestFailed.rerunner:()Lscala/Option;
        29: aload         7
        31: invokevirtual #50                 // Method org/scalatest/events/TestFailed.suiteId:()Ljava/lang/String;
        34: new           #52                 // class scala/Some
        37: dup
        38: aload         7
        40: invokevirtual #55                 // Method org/scalatest/events/TestFailed.testName:()Ljava/lang/String;
        43: invokespecial #58                 // Method scala/Some."<init>":(Ljava/lang/Object;)V
        46: invokespecial #61                 // Method scala/Tuple4."<init>":(Ljava/lang/Object;Ljava/lang/Object;Ljava/lang/Object;Ljava/lang/Object;)V
        49: astore_3
        50: goto          177
        53: goto          56
        56: aload         6
        58: instanceof    #63                 // class org/scalatest/events/TestCanceled
        61: ifeq          106
        64: aload         6
        66: checkcast     #63                 // class org/scalatest/events/TestCanceled
        69: astore        8
        71: new           #40                 // class scala/Tuple4
        74: dup
        75: ldc           #65                 // String TestCanceled
        77: aload         8
        79: invokevirtual #66                 // Method org/scalatest/events/TestCanceled.rerunner:()Lscala/Option;
        82: aload         8
        84: invokevirtual #67                 // Method org/scalatest/events/TestCanceled.suiteId:()Ljava/lang/String;
        87: new           #52                 // class scala/Some
        90: dup
        91: aload         8
        93: invokevirtual #68                 // Method org/scalatest/events/TestCanceled.testName:()Ljava/lang/String;
        96: invokespecial #58                 // Method scala/Some."<init>":(Ljava/lang/Object;)V
        99: invokespecial #61                 // Method scala/Tuple4."<init>":(Ljava/lang/Object;Ljava/lang/Object;Ljava/lang/Object;Ljava/lang/Object;)V
       102: astore_3
       103: goto          177
       106: goto          109
       109: aload         6
       111: instanceof    #70                 // class org/scalatest/events/SuiteAborted
       114: ifeq          150
       117: aload         6
       119: checkcast     #70                 // class org/scalatest/events/SuiteAborted
       122: astore        9
       124: new           #40                 // class scala/Tuple4
       127: dup
       128: ldc           #72                 // String SuiteAborted
       130: aload         9
       132: invokevirtual #73                 // Method org/scalatest/events/SuiteAborted.rerunner:()Lscala/Option;
       135: aload         9
       137: invokevirtual #74                 // Method org/scalatest/events/SuiteAborted.suiteId:()Ljava/lang/String;
       140: getstatic     #79                 // Field scala/None$.MODULE$:Lscala/None$;
       143: invokespecial #61                 // Method scala/Tuple4."<init>":(Ljava/lang/Object;Ljava/lang/Object;Ljava/lang/Object;Ljava/lang/Object;)V
       146: astore_3
       147: goto          177
       150: goto          153
       153: new           #40                 // class scala/Tuple4
       156: dup
       157: ldc           #81                 // String unexpected
       159: getstatic     #79                 // Field scala/None$.MODULE$:Lscala/None$;
       162: aload         6
       164: invokevirtual #86                 // Method org/scalatest/events/Event.toString:()Ljava/lang/String;
       167: getstatic     #79                 // Field scala/None$.MODULE$:Lscala/None$;
       170: invokespecial #61                 // Method scala/Tuple4."<init>":(Ljava/lang/Object;Ljava/lang/Object;Ljava/lang/Object;Ljava/lang/Object;)V
       173: astore_3
       174: goto          177
       177: aload_3
       178: astore        5
       180: aload         5
       182: ifnull        292
       185: aload         5
       187: invokevirtual #90                 // Method scala/Tuple4._1:()Ljava/lang/Object;
       190: checkcast     #92                 // class java/lang/String
       193: astore        10
       195: aload         5
       197: invokevirtual #95                 // Method scala/Tuple4._2:()Ljava/lang/Object;
       200: checkcast     #97                 // class scala/Option
       203: astore        11
       205: aload         5
       207: invokevirtual #100                // Method scala/Tuple4._3:()Ljava/lang/Object;
       210: checkcast     #92                 // class java/lang/String
       213: astore        12
       215: aload         5
       217: invokevirtual #103                // Method scala/Tuple4._4:()Ljava/lang/Object;
       220: checkcast     #97                 // class scala/Option
       223: astore        13
       225: aload         10
       227: ifnull        289
       230: aload         10
       232: astore        14
       234: aload         11
       236: ifnull        286
       239: aload         11
       241: astore        15
       243: aload         12
       245: ifnull        283
       248: aload         12
       250: astore        16
       252: aload         13
       254: ifnull        280
       257: aload         13
       259: astore        17
       261: new           #40                 // class scala/Tuple4
       264: dup
       265: aload         14
       267: aload         15
       269: aload         16
       271: aload         17
       273: invokespecial #61                 // Method scala/Tuple4."<init>":(Ljava/lang/Object;Ljava/lang/Object;Ljava/lang/Object;Ljava/lang/Object;)V
       276: astore_2
       277: goto          305
       280: goto          295
       283: goto          295
       286: goto          295
       289: goto          295
       292: goto          295
       295: new           #105                // class scala/MatchError
       298: dup
       299: aload         5
       301: invokespecial #106                // Method scala/MatchError."<init>":(Ljava/lang/Object;)V
       304: athrow
       305: aload_2
       306: astore        4
       308: aload         4
       310: invokevirtual #90                 // Method scala/Tuple4._1:()Ljava/lang/Object;
       313: checkcast     #92                 // class java/lang/String
       316: astore        18
       318: aload         4
       320: invokevirtual #95                 // Method scala/Tuple4._2:()Ljava/lang/Object;
       323: checkcast     #97                 // class scala/Option
       326: astore        19
       328: aload         4
       330: invokevirtual #100                // Method scala/Tuple4._3:()Ljava/lang/Object;
       333: checkcast     #92                 // class java/lang/String
       336: astore        20
       338: aload         4
       340: invokevirtual #103                // Method scala/Tuple4._4:()Ljava/lang/Object;
       343: checkcast     #97                 // class scala/Option
       346: astore        21
       348: new           #108                // class org/scalatest/tools/Memento
       351: dup
       352: aload         18
       354: aload         19
       356: aload         20
       358: aload         21
       360: invokespecial #111                // Method org/scalatest/tools/Memento."<init>":(Ljava/lang/String;Lscala/Option;Ljava/lang/String;Lscala/Option;)V
       363: areturn
      StackMapTable: number_of_entries = 14
        frame_type = 255 /* full_frame */
          offset_delta = 53
          locals = [ class org/scalatest/tools/Memento$, class org/scalatest/events/Event, top, top, top, top, class org/scalatest/events/Event ]
          stack = []
        frame_type = 2 /* same */
        frame_type = 49 /* same */
        frame_type = 2 /* same */
        frame_type = 40 /* same */
        frame_type = 2 /* same */
        frame_type = 255 /* full_frame */
          offset_delta = 23
          locals = [ class org/scalatest/tools/Memento$, class org/scalatest/events/Event, top, class scala/Tuple4, top, top, class org/scalatest/events/Event ]
          stack = []
        frame_type = 255 /* full_frame */
          offset_delta = 102
          locals = [ class org/scalatest/tools/Memento$, class org/scalatest/events/Event, top, class scala/Tuple4, top, class scala/Tuple4, class org/scalatest/events/Event, top, top, top, class java/lang/String, class scala/Option, class java/lang/String, class scala/Option, class java/lang/String, class scala/Option, class java/lang/String ]
          stack = []
        frame_type = 250 /* chop */
          offset_delta = 2
        frame_type = 250 /* chop */
          offset_delta = 2
        frame_type = 250 /* chop */
          offset_delta = 2
        frame_type = 255 /* full_frame */
          offset_delta = 2
          locals = [ class org/scalatest/tools/Memento$, class org/scalatest/events/Event, top, class scala/Tuple4, top, class scala/Tuple4, class org/scalatest/events/Event ]
          stack = []
        frame_type = 2 /* same */
        frame_type = 255 /* full_frame */
          offset_delta = 9
          locals = [ class org/scalatest/tools/Memento$, class org/scalatest/events/Event, class scala/Tuple4, class scala/Tuple4, top, class scala/Tuple4, class org/scalatest/events/Event, top, top, top, class java/lang/String, class scala/Option, class java/lang/String, class scala/Option, class java/lang/String, class scala/Option, class java/lang/String, class scala/Option ]
          stack = []
      LineNumberTable:
        line 95: 0
        line 96: 3
        line 97: 18
        line 96: 53
        line 98: 56
        line 99: 71
        line 98: 106
        line 100: 109
        line 101: 124
        line 100: 150
        line 103: 153
        line 95: 177
        line 90: 180
        line 91: 195
        line 92: 205
        line 93: 215
        line 90: 225
        line 91: 234
        line 92: 243
        line 93: 252
        line 90: 261
        line 93: 280
        line 92: 283
        line 91: 286
        line 90: 289
        line 95: 295
        line 90: 308
        line 91: 318
        line 92: 328
        line 93: 338
        line 106: 348
      LocalVariableTable:
        Start  Length  Slot  Name   Signature
          195      97    10 eventName   Ljava/lang/String;
          205      87    11 className   Lscala/Option;
          215      77    12 suiteId   Ljava/lang/String;
          225      67    13 testName   Lscala/Option;
          318      45    18 eventName   Ljava/lang/String;
          328      35    19 className   Lscala/Option;
          338      25    20 suiteId   Ljava/lang/String;
          348      15    21 testName   Lscala/Option;
            0     364     0  this   Lorg/scalatest/tools/Memento$;
            0     364     1 event   Lorg/scalatest/events/Event;
    MethodParameters:
      Name                           Flags
      event                          final

  public scala.collection.immutable.List<org.scalatest.tools.Memento> readFromFile(java.lang.String);
    descriptor: (Ljava/lang/String;)Lscala/collection/immutable/List;
    flags: (0x0001) ACC_PUBLIC
    Code:
      stack=3, locals=4, args_size=2
         0: getstatic     #126                // Field scala/io/Source$.MODULE$:Lscala/io/Source$;
         3: aload_1
         4: getstatic     #131                // Field scala/io/Codec$.MODULE$:Lscala/io/Codec$;
         7: invokevirtual #135                // Method scala/io/Codec$.fallbackSystemCodec:()Lscala/io/Codec;
        10: invokevirtual #139                // Method scala/io/Source$.fromFile:(Ljava/lang/String;Lscala/io/Codec;)Lscala/io/BufferedSource;
        13: astore_2
        14: aload_2
        15: invokevirtual #145                // Method scala/io/BufferedSource.getLines:()Lscala/collection/Iterator;
        18: invokeinterface #151,  1          // InterfaceMethod scala/collection/Iterator.toList:()Lscala/collection/immutable/List;
        23: invokedynamic #171,  0            // InvokeDynamic #0:apply:()Lscala/Function1;
        28: invokevirtual #177                // Method scala/collection/immutable/List.map:(Lscala/Function1;)Lscala/collection/immutable/List;
        31: goto          41
        34: astore_3
        35: aload_2
        36: invokevirtual #180                // Method scala/io/BufferedSource.close:()V
        39: aload_3
        40: athrow
        41: aload_2
        42: invokevirtual #180                // Method scala/io/BufferedSource.close:()V
        45: areturn
      Exception table:
         from    to  target type
            14    34    34   any
      StackMapTable: number_of_entries = 2
        frame_type = 255 /* full_frame */
          offset_delta = 34
          locals = [ class org/scalatest/tools/Memento$, class java/lang/String, class scala/io/BufferedSource ]
          stack = [ class java/lang/Throwable ]
        frame_type = 70 /* same_locals_1_stack_item */
          stack = [ class scala/collection/immutable/List ]
      LineNumberTable:
        line 114: 0
        line 116: 14
        line 119: 35
      LocalVariableTable:
        Start  Length  Slot  Name   Signature
           14      31     2 source   Lscala/io/BufferedSource;
            0      46     0  this   Lorg/scalatest/tools/Memento$;
            0      46     1 fileName   Ljava/lang/String;
    Signature: #120                         // (Ljava/lang/String;)Lscala/collection/immutable/List<Lorg/scalatest/tools/Memento;>;
    MethodParameters:
      Name                           Flags
      fileName                       final

  public void writeToFile(java.lang.String, scala.collection.immutable.Set<org.scalatest.tools.Memento>);
    descriptor: (Ljava/lang/String;Lscala/collection/immutable/Set;)V
    flags: (0x0001) ACC_PUBLIC
    Code:
      stack=4, locals=6, args_size=3
         0: new           #190                // class java/io/PrintWriter
         3: dup
         4: aload_1
         5: ldc           #192                // String UTF-8
         7: invokespecial #195                // Method java/io/PrintWriter."<init>":(Ljava/lang/String;Ljava/lang/String;)V
        10: astore_3
        11: aload_2
        12: invokedynamic #202,  0            // InvokeDynamic #1:apply:()Lscala/Function1;
        17: invokeinterface #207,  2          // InterfaceMethod scala/collection/immutable/Set.map:(Lscala/Function1;)Ljava/lang/Object;
        22: checkcast     #209                // class scala/collection/IterableOnceOps
        25: invokeinterface #210,  1          // InterfaceMethod scala/collection/IterableOnceOps.toList:()Lscala/collection/immutable/List;
        30: invokedynamic #221,  0            // InvokeDynamic #2:apply:()Lscala/Function2;
        35: invokevirtual #225                // Method scala/collection/immutable/List.sortWith:(Lscala/Function2;)Ljava/lang/Object;
        38: checkcast     #173                // class scala/collection/immutable/List
        41: astore        4
        43: aload         4
        45: aload_3
        46: invokedynamic #235,  0            // InvokeDynamic #3:apply:(Ljava/io/PrintWriter;)Lscala/Function1;
        51: invokevirtual #239                // Method scala/collection/immutable/List.foreach:(Lscala/Function1;)V
        54: goto          66
        57: astore        5
        59: aload_3
        60: invokevirtual #240                // Method java/io/PrintWriter.close:()V
        63: aload         5
        65: athrow
        66: aload_3
        67: invokevirtual #240                // Method java/io/PrintWriter.close:()V
        70: return
      Exception table:
         from    to  target type
            11    57    57   any
      StackMapTable: number_of_entries = 2
        frame_type = 255 /* full_frame */
          offset_delta = 57
          locals = [ class org/scalatest/tools/Memento$, class java/lang/String, class scala/collection/immutable/Set, class java/io/PrintWriter ]
          stack = [ class java/lang/Throwable ]
        frame_type = 252 /* append */
          offset_delta = 8
          locals = [ class scala/collection/immutable/List ]
      LineNumberTable:
        line 127: 0
        line 129: 11
        line 130: 43
        line 132: 59
      LocalVariableTable:
        Start  Length  Slot  Name   Signature
           43      11     4 lines   Lscala/collection/immutable/List;
           11      59     3   out   Ljava/io/PrintWriter;
            0      71     0  this   Lorg/scalatest/tools/Memento$;
            0      71     1 fileName   Ljava/lang/String;
            0      71     2 mementos   Lscala/collection/immutable/Set;
    Signature: #187                         // (Ljava/lang/String;Lscala/collection/immutable/Set<Lorg/scalatest/tools/Memento;>;)V
    MethodParameters:
      Name                           Flags
      fileName                       final
      mementos                       final

  public org.scalatest.tools.Memento fromString(java.lang.String);
    descriptor: (Ljava/lang/String;)Lorg/scalatest/tools/Memento;
    flags: (0x0001) ACC_PUBLIC
    Code:
      stack=6, locals=7, args_size=2
         0: aload_1
         1: ldc           #249                // String
         3: invokevirtual #253                // Method java/lang/String.split:(Ljava/lang/String;)[Ljava/lang/String;
         6: astore_2
         7: aload_2
         8: arraylength
         9: iconst_4
        10: if_icmpeq     50
        13: new           #255                // class java/lang/Exception
        16: dup
        17: new           #257                // class java/lang/StringBuilder
        20: dup
        21: ldc_w         #258                // int 18
        24: invokespecial #261                // Method java/lang/StringBuilder."<init>":(I)V
        27: ldc_w         #263                // String bad line format [
        30: invokevirtual #267                // Method java/lang/StringBuilder.append:(Ljava/lang/String;)Ljava/lang/StringBuilder;
        33: aload_1
        34: invokevirtual #267                // Method java/lang/StringBuilder.append:(Ljava/lang/String;)Ljava/lang/StringBuilder;
        37: ldc_w         #269                // String ]
        40: invokevirtual #267                // Method java/lang/StringBuilder.append:(Ljava/lang/String;)Ljava/lang/StringBuilder;
        43: invokevirtual #270                // Method java/lang/StringBuilder.toString:()Ljava/lang/String;
        46: invokespecial #273                // Method java/lang/Exception."<init>":(Ljava/lang/String;)V
        49: athrow
        50: aload_2
        51: iconst_0
        52: aaload
        53: astore_3
        54: aload_0
        55: aload_2
        56: iconst_1
        57: aaload
        58: invokevirtual #277                // Method optionFromString:(Ljava/lang/String;)Lscala/Option;
        61: astore        4
        63: aload_0
        64: aload_2
        65: iconst_2
        66: aaload
        67: invokevirtual #281                // Method decode:(Ljava/lang/String;)Ljava/lang/String;
        70: astore        5
        72: aload_0
        73: aload_0
        74: aload_2
        75: iconst_3
        76: aaload
        77: invokevirtual #281                // Method decode:(Ljava/lang/String;)Ljava/lang/String;
        80: invokevirtual #277                // Method optionFromString:(Ljava/lang/String;)Lscala/Option;
        83: astore        6
        85: new           #108                // class org/scalatest/tools/Memento
        88: dup
        89: aload_3
        90: aload         4
        92: aload         5
        94: aload         6
        96: invokespecial #111                // Method org/scalatest/tools/Memento."<init>":(Ljava/lang/String;Lscala/Option;Ljava/lang/String;Lscala/Option;)V
        99: areturn
      StackMapTable: number_of_entries = 1
        frame_type = 252 /* append */
          offset_delta = 50
          locals = [ class "[Ljava/lang/String;" ]
      LineNumberTable:
        line 139: 0
        line 141: 7
        line 142: 13
        line 144: 50
        line 145: 54
        line 146: 63
        line 147: 72
        line 149: 85
      LocalVariableTable:
        Start  Length  Slot  Name   Signature
            7      92     2 splits   [Ljava/lang/String;
           54      45     3 eventName   Ljava/lang/String;
           63      36     4 className   Lscala/Option;
           72      27     5 suiteId   Ljava/lang/String;
           85      14     6 testName   Lscala/Option;
            0     100     0  this   Lorg/scalatest/tools/Memento$;
            0     100     1   str   Ljava/lang/String;
    MethodParameters:
      Name                           Flags
      str                            final

  public java.util.regex.Pattern SomeNonePat();
    descriptor: ()Ljava/util/regex/Pattern;
    flags: (0x0001) ACC_PUBLIC
    Code:
      stack=1, locals=1, args_size=1
         0: getstatic     #33                 // Field SomeNonePat:Ljava/util/regex/Pattern;
         3: areturn
      LineNumberTable:
        line 156: 0
      LocalVariableTable:
        Start  Length  Slot  Name   Signature
            0       4     0  this   Lorg/scalatest/tools/Memento$;

  public scala.Option<java.lang.String> optionFromString(java.lang.String);
    descriptor: (Ljava/lang/String;)Lscala/Option;
    flags: (0x0001) ACC_PUBLIC
    Code:
      stack=5, locals=5, args_size=2
         0: aload_0
         1: invokevirtual #288                // Method SomeNonePat:()Ljava/util/regex/Pattern;
         4: aload_1
         5: invokevirtual #292                // Method java/util/regex/Pattern.matcher:(Ljava/lang/CharSequence;)Ljava/util/regex/Matcher;
         8: astore_3
         9: aload_3
        10: invokevirtual #298                // Method java/util/regex/Matcher.find:()Z
        13: ifne          53
        16: new           #255                // class java/lang/Exception
        19: dup
        20: new           #257                // class java/lang/StringBuilder
        23: dup
        24: ldc_w         #299                // int 20
        27: invokespecial #261                // Method java/lang/StringBuilder."<init>":(I)V
        30: ldc_w         #301                // String bad option string [
        33: invokevirtual #267                // Method java/lang/StringBuilder.append:(Ljava/lang/String;)Ljava/lang/StringBuilder;
        36: aload_1
        37: invokevirtual #267                // Method java/lang/StringBuilder.append:(Ljava/lang/String;)Ljava/lang/StringBuilder;
        40: ldc_w         #269                // String ]
        43: invokevirtual #267                // Method java/lang/StringBuilder.append:(Ljava/lang/String;)Ljava/lang/StringBuilder;
        46: invokevirtual #270                // Method java/lang/StringBuilder.toString:()Ljava/lang/String;
        49: invokespecial #273                // Method java/lang/Exception."<init>":(Ljava/lang/String;)V
        52: athrow
        53: aload_3
        54: iconst_1
        55: invokevirtual #305                // Method java/util/regex/Matcher.group:(I)Ljava/lang/String;
        58: astore        4
        60: aload         4
        62: ifnonnull     69
        65: iconst_0
        66: goto          74
        69: aload         4
        71: invokevirtual #309                // Method java/lang/String.hashCode:()I
        74: lookupswitch  { // 2
                 2433880: 100
                80066964: 121
                 default: 151
            }
       100: ldc_w         #311                // String None
       103: aload         4
       105: invokevirtual #315                // Method java/lang/String.equals:(Ljava/lang/Object;)Z
       108: ifeq          118
       111: getstatic     #79                 // Field scala/None$.MODULE$:Lscala/None$;
       114: astore_2
       115: goto          191
       118: goto          154
       121: ldc_w         #317                // String Some(
       124: aload         4
       126: invokevirtual #315                // Method java/lang/String.equals:(Ljava/lang/Object;)Z
       129: ifeq          148
       132: new           #52                 // class scala/Some
       135: dup
       136: aload_3
       137: iconst_2
       138: invokevirtual #305                // Method java/util/regex/Matcher.group:(I)Ljava/lang/String;
       141: invokespecial #58                 // Method scala/Some."<init>":(Ljava/lang/Object;)V
       144: astore_2
       145: goto          191
       148: goto          154
       151: goto          154
       154: new           #255                // class java/lang/Exception
       157: dup
       158: new           #257                // class java/lang/StringBuilder
       161: dup
       162: ldc_w         #299                // int 20
       165: invokespecial #261                // Method java/lang/StringBuilder."<init>":(I)V
       168: ldc_w         #319                // String bad Option format [
       171: invokevirtual #267                // Method java/lang/StringBuilder.append:(Ljava/lang/String;)Ljava/lang/StringBuilder;
       174: aload_1
       175: invokevirtual #267                // Method java/lang/StringBuilder.append:(Ljava/lang/String;)Ljava/lang/StringBuilder;
       178: ldc_w         #269                // String ]
       181: invokevirtual #267                // Method java/lang/StringBuilder.append:(Ljava/lang/String;)Ljava/lang/StringBuilder;
       184: invokevirtual #270                // Method java/lang/StringBuilder.toString:()Ljava/lang/String;
       187: invokespecial #273                // Method java/lang/Exception."<init>":(Ljava/lang/String;)V
       190: athrow
       191: aload_2
       192: areturn
      StackMapTable: number_of_entries = 10
        frame_type = 253 /* append */
          offset_delta = 53
          locals = [ top, class java/util/regex/Matcher ]
        frame_type = 252 /* append */
          offset_delta = 15
          locals = [ class java/lang/String ]
        frame_type = 68 /* same_locals_1_stack_item */
          stack = [ int ]
        frame_type = 25 /* same */
        frame_type = 17 /* same */
        frame_type = 2 /* same */
        frame_type = 26 /* same */
        frame_type = 2 /* same */
        frame_type = 2 /* same */
        frame_type = 255 /* full_frame */
          offset_delta = 36
          locals = [ class org/scalatest/tools/Memento$, class java/lang/String, class scala/Option, class java/util/regex/Matcher, class java/lang/String ]
          stack = []
      LineNumberTable:
        line 158: 0
        line 159: 9
        line 160: 16
        line 162: 53
        line 164: 100
        line 162: 118
        line 163: 121
        line 162: 148
        line 165: 154
        line 162: 191
      LocalVariableTable:
        Start  Length  Slot  Name   Signature
            9     183     3 matcher   Ljava/util/regex/Matcher;
            0     193     0  this   Lorg/scalatest/tools/Memento$;
            0     193     1   str   Ljava/lang/String;
    Signature: #286                         // (Ljava/lang/String;)Lscala/Option<Ljava/lang/String;>;
    MethodParameters:
      Name                           Flags
      str                            final

  public java.lang.String encode(java.lang.String);
    descriptor: (Ljava/lang/String;)Ljava/lang/String;
    flags: (0x0001) ACC_PUBLIC
    Code:
      stack=3, locals=2, args_size=2
         0: aload_1
         1: ldc_w         #324                // String \\\\
         4: ldc_w         #326                // String \\\\5c
         7: invokevirtual #330                // Method java/lang/String.replaceAll:(Ljava/lang/String;Ljava/lang/String;)Ljava/lang/String;
        10: ldc_w         #332                // String \n
        13: ldc_w         #334                // String \\\\1f
        16: invokevirtual #330                // Method java/lang/String.replaceAll:(Ljava/lang/String;Ljava/lang/String;)Ljava/lang/String;
        19: ldc_w         #336                // String _
        22: ldc_w         #338                // String \\\\5f
        25: invokevirtual #330                // Method java/lang/String.replaceAll:(Ljava/lang/String;Ljava/lang/String;)Ljava/lang/String;
        28: ldc           #249                // String
        30: ldc_w         #336                // String _
        33: invokevirtual #330                // Method java/lang/String.replaceAll:(Ljava/lang/String;Ljava/lang/String;)Ljava/lang/String;
        36: areturn
      LineNumberTable:
        line 174: 0
        line 175: 1
        line 176: 10
        line 177: 19
        line 178: 28
      LocalVariableTable:
        Start  Length  Slot  Name   Signature
            0      37     0  this   Lorg/scalatest/tools/Memento$;
            0      37     1  text   Ljava/lang/String;
    MethodParameters:
      Name                           Flags
      text                           final

  public java.lang.String decode(java.lang.String);
    descriptor: (Ljava/lang/String;)Ljava/lang/String;
    flags: (0x0001) ACC_PUBLIC
    Code:
      stack=3, locals=2, args_size=2
         0: aload_1
         1: ldc_w         #336                // String _
         4: ldc           #249                // String
         6: invokevirtual #330                // Method java/lang/String.replaceAll:(Ljava/lang/String;Ljava/lang/String;)Ljava/lang/String;
         9: ldc_w         #338                // String \\\\5f
        12: ldc_w         #336                // String _
        15: invokevirtual #330                // Method java/lang/String.replaceAll:(Ljava/lang/String;Ljava/lang/String;)Ljava/lang/String;
        18: ldc_w         #334                // String \\\\1f
        21: ldc_w         #332                // String \n
        24: invokevirtual #330                // Method java/lang/String.replaceAll:(Ljava/lang/String;Ljava/lang/String;)Ljava/lang/String;
        27: ldc_w         #326                // String \\\\5c
        30: ldc_w         #324                // String \\\\
        33: invokevirtual #330                // Method java/lang/String.replaceAll:(Ljava/lang/String;Ljava/lang/String;)Ljava/lang/String;
        36: areturn
      LineNumberTable:
        line 185: 0
        line 186: 1
        line 187: 9
        line 188: 18
        line 189: 27
      LocalVariableTable:
        Start  Length  Slot  Name   Signature
            0      37     0  this   Lorg/scalatest/tools/Memento$;
            0      37     1  text   Ljava/lang/String;
    MethodParameters:
      Name                           Flags
      text                           final

  public org.scalatest.tools.Memento apply(java.lang.String, scala.Option<java.lang.String>, java.lang.String, scala.Option<java.lang.String>);
    descriptor: (Ljava/lang/String;Lscala/Option;Ljava/lang/String;Lscala/Option;)Lorg/scalatest/tools/Memento;
    flags: (0x0001) ACC_PUBLIC
    Code:
      stack=6, locals=5, args_size=5
         0: new           #108                // class org/scalatest/tools/Memento
         3: dup
         4: aload_1
         5: aload_2
         6: aload_3
         7: aload         4
         9: invokespecial #111                // Method org/scalatest/tools/Memento."<init>":(Ljava/lang/String;Lscala/Option;Ljava/lang/String;Lscala/Option;)V
        12: areturn
      LineNumberTable:
        line 34: 0
      LocalVariableTable:
        Start  Length  Slot  Name   Signature
            0      13     0  this   Lorg/scalatest/tools/Memento$;
            0      13     1 eventName   Ljava/lang/String;
            0      13     2 className   Lscala/Option;
            0      13     3 suiteId   Ljava/lang/String;
            0      13     4 testName   Lscala/Option;
    Signature: #340                         // (Ljava/lang/String;Lscala/Option<Ljava/lang/String;>;Ljava/lang/String;Lscala/Option<Ljava/lang/String;>;)Lorg/scalatest/tools/Memento;
    MethodParameters:
      Name                           Flags
      eventName                      final
      className                      final
      suiteId                        final
      testName                       final

  public scala.Option<scala.Tuple4<java.lang.String, scala.Option<java.lang.String>, java.lang.String, scala.Option<java.lang.String>>> unapply(org.scalatest.tools.Memento);
    descriptor: (Lorg/scalatest/tools/Memento;)Lscala/Option;
    flags: (0x0001) ACC_PUBLIC
    Code:
      stack=8, locals=2, args_size=2
         0: aload_1
         1: ifnonnull     10
         4: getstatic     #79                 // Field scala/None$.MODULE$:Lscala/None$;
         7: goto          40
        10: new           #52                 // class scala/Some
        13: dup
        14: new           #40                 // class scala/Tuple4
        17: dup
        18: aload_1
        19: invokevirtual #346                // Method org/scalatest/tools/Memento.eventName:()Ljava/lang/String;
        22: aload_1
        23: invokevirtual #348                // Method org/scalatest/tools/Memento.className:()Lscala/Option;
        26: aload_1
        27: invokevirtual #349                // Method org/scalatest/tools/Memento.suiteId:()Ljava/lang/String;
        30: aload_1
        31: invokevirtual #351                // Method org/scalatest/tools/Memento.testName:()Lscala/Option;
        34: invokespecial #61                 // Method scala/Tuple4."<init>":(Ljava/lang/Object;Ljava/lang/Object;Ljava/lang/Object;Ljava/lang/Object;)V
        37: invokespecial #58                 // Method scala/Some."<init>":(Ljava/lang/Object;)V
        40: areturn
      StackMapTable: number_of_entries = 2
        frame_type = 10 /* same */
        frame_type = 93 /* same_locals_1_stack_item */
          stack = [ class scala/Option ]
      LineNumberTable:
        line 34: 0
      LocalVariableTable:
        Start  Length  Slot  Name   Signature
            0      41     0  this   Lorg/scalatest/tools/Memento$;
            0      41     1   x$0   Lorg/scalatest/tools/Memento;
    Signature: #343                         // (Lorg/scalatest/tools/Memento;)Lscala/Option<Lscala/Tuple4<Ljava/lang/String;Lscala/Option<Ljava/lang/String;>;Ljava/lang/String;Lscala/Option<Ljava/lang/String;>;>;>;
    MethodParameters:
      Name                           Flags
      x$0                            final

  private java.lang.Object writeReplace();
    descriptor: ()Ljava/lang/Object;
    flags: (0x0002) ACC_PRIVATE
    Code:
      stack=3, locals=1, args_size=1
         0: new           #355                // class scala/runtime/ModuleSerializationProxy
         3: dup
         4: ldc           #2                  // class org/scalatest/tools/Memento$
         6: invokespecial #358                // Method scala/runtime/ModuleSerializationProxy."<init>":(Ljava/lang/Class;)V
         9: areturn
      LineNumberTable:
        line 85: 0
      LocalVariableTable:
        Start  Length  Slot  Name   Signature
            0      10     0  this   Lorg/scalatest/tools/Memento$;

  public static final org.scalatest.tools.Memento $anonfun$readFromFile$1(java.lang.String);
    descriptor: (Ljava/lang/String;)Lorg/scalatest/tools/Memento;
    flags: (0x1019) ACC_PUBLIC, ACC_STATIC, ACC_FINAL, ACC_SYNTHETIC
    Code:
      stack=2, locals=1, args_size=1
         0: getstatic     #23                 // Field MODULE$:Lorg/scalatest/tools/Memento$;
         3: aload_0
         4: invokevirtual #361                // Method fromString:(Ljava/lang/String;)Lorg/scalatest/tools/Memento;
         7: areturn
      LineNumberTable:
        line 117: 0
      LocalVariableTable:
        Start  Length  Slot  Name   Signature
            0       8     0  line   Ljava/lang/String;
    MethodParameters:
      Name                           Flags
      line                           final

  public static final java.lang.String $anonfun$writeToFile$1(org.scalatest.tools.Memento);
    descriptor: (Lorg/scalatest/tools/Memento;)Ljava/lang/String;
    flags: (0x1019) ACC_PUBLIC, ACC_STATIC, ACC_FINAL, ACC_SYNTHETIC
    Code:
      stack=1, locals=1, args_size=1
         0: aload_0
         1: invokevirtual #365                // Method org/scalatest/tools/Memento.singleLine:()Ljava/lang/String;
         4: areturn
      LineNumberTable:
        line 129: 0
      LocalVariableTable:
        Start  Length  Slot  Name   Signature
            0       5     0   x$3   Lorg/scalatest/tools/Memento;
    MethodParameters:
      Name                           Flags
      x$3                            final

  public static final boolean $anonfun$writeToFile$2(java.lang.String, java.lang.String);
    descriptor: (Ljava/lang/String;Ljava/lang/String;)Z
    flags: (0x1019) ACC_PUBLIC, ACC_STATIC, ACC_FINAL, ACC_SYNTHETIC
    Code:
      stack=3, locals=2, args_size=2
         0: getstatic     #374                // Field scala/collection/StringOps$.MODULE$:Lscala/collection/StringOps$;
         3: getstatic     #379                // Field scala/Predef$.MODULE$:Lscala/Predef$;
         6: aload_0
         7: invokevirtual #382                // Method scala/Predef$.augmentString:(Ljava/lang/String;)Ljava/lang/String;
        10: aload_1
        11: invokevirtual #385                // Method scala/collection/StringOps$.$less$extension:(Ljava/lang/String;Ljava/lang/String;)Z
        14: ireturn
      LineNumberTable:
        line 129: 3
      LocalVariableTable:
        Start  Length  Slot  Name   Signature
            0      15     0   x$4   Ljava/lang/String;
            0      15     1   x$5   Ljava/lang/String;
    MethodParameters:
      Name                           Flags
      x$4                            final
      x$5                            final

  public static final void $anonfun$writeToFile$3(java.io.PrintWriter, java.lang.String);
    descriptor: (Ljava/io/PrintWriter;Ljava/lang/String;)V
    flags: (0x1019) ACC_PUBLIC, ACC_STATIC, ACC_FINAL, ACC_SYNTHETIC
    Code:
      stack=2, locals=2, args_size=2
         0: aload_0
         1: aload_1
         2: invokevirtual #392                // Method java/io/PrintWriter.println:(Ljava/lang/String;)V
         5: return
      LineNumberTable:
        line 130: 0
      LocalVariableTable:
        Start  Length  Slot  Name   Signature
            0       6     0 out$1   Ljava/io/PrintWriter;
            0       6     1   x$1   Ljava/lang/String;
    MethodParameters:
      Name                           Flags
      out$1                          final
      x$1                            final

  private org.scalatest.tools.Memento$();
    descriptor: ()V
    flags: (0x0002) ACC_PRIVATE
    Code:
      stack=1, locals=1, args_size=1
         0: aload_0
         1: invokespecial #393                // Method java/lang/Object."<init>":()V
         4: return
      LineNumberTable:
        line 191: 0
        line 85: 4
      LocalVariableTable:
        Start  Length  Slot  Name   Signature
            0       5     0  this   Lorg/scalatest/tools/Memento$;

  public static final java.lang.Object $anonfun$writeToFile$2$adapted(java.lang.String, java.lang.String);
    descriptor: (Ljava/lang/String;Ljava/lang/String;)Ljava/lang/Object;
    flags: (0x1019) ACC_PUBLIC, ACC_STATIC, ACC_FINAL, ACC_SYNTHETIC
    Code:
      stack=2, locals=2, args_size=2
         0: aload_0
         1: aload_1
         2: invokestatic  #395                // Method $anonfun$writeToFile$2:(Ljava/lang/String;Ljava/lang/String;)Z
         5: invokestatic  #401                // Method scala/runtime/BoxesRunTime.boxToBoolean:(Z)Ljava/lang/Boolean;
         8: areturn
      LineNumberTable:
        line 129: 0
      LocalVariableTable:
        Start  Length  Slot  Name   Signature
            0       9     0   x$4   Ljava/lang/String;
            0       9     1   x$5   Ljava/lang/String;
    MethodParameters:
      Name                           Flags
      x$4                            final
      x$5                            final

  public static final java.lang.Object $anonfun$writeToFile$3$adapted(java.io.PrintWriter, java.lang.String);
    descriptor: (Ljava/io/PrintWriter;Ljava/lang/String;)Ljava/lang/Object;
    flags: (0x1019) ACC_PUBLIC, ACC_STATIC, ACC_FINAL, ACC_SYNTHETIC
    Code:
      stack=2, locals=2, args_size=2
         0: aload_0
         1: aload_1
         2: invokestatic  #403                // Method $anonfun$writeToFile$3:(Ljava/io/PrintWriter;Ljava/lang/String;)V
         5: getstatic     #409                // Field scala/runtime/BoxedUnit.UNIT:Lscala/runtime/BoxedUnit;
         8: areturn
      LineNumberTable:
        line 130: 0
      LocalVariableTable:
        Start  Length  Slot  Name   Signature
            0       9     0 out$1   Ljava/io/PrintWriter;
            0       9     1   x$1   Ljava/lang/String;
    MethodParameters:
      Name                           Flags
      out$1                          final
      x$1                            final

  private static java.lang.Object $deserializeLambda$(java.lang.invoke.SerializedLambda);
    descriptor: (Ljava/lang/invoke/SerializedLambda;)Ljava/lang/Object;
    flags: (0x100a) ACC_PRIVATE, ACC_STATIC, ACC_SYNTHETIC
    Code:
      stack=1, locals=1, args_size=1
         0: aload_0
         1: invokedynamic #421,  0            // InvokeDynamic #4:lambdaDeserialize:(Ljava/lang/invoke/SerializedLambda;)Ljava/lang/Object;
         6: areturn
}
InnerClasses:
  public static final #12= #9 of #11;     // Lookup=class java/lang/invoke/MethodHandles$Lookup of class java/lang/invoke/MethodHandles
SourceFile: "Memento.scala"
BootstrapMethods:
  0: #168 REF_invokeStatic java/lang/invoke/LambdaMetafactory.altMetafactory:(Ljava/lang/invoke/MethodHandles$Lookup;Ljava/lang/String;Ljava/lang/invoke/MethodType;[Ljava/lang/Object;)Ljava/lang/invoke/CallSite;
    Method arguments:
      #153 (Ljava/lang/Object;)Ljava/lang/Object;
      #158 REF_invokeStatic org/scalatest/tools/Memento$.$anonfun$readFromFile$1:(Ljava/lang/String;)Lorg/scalatest/tools/Memento;
      #159 (Ljava/lang/String;)Lorg/scalatest/tools/Memento;
      #160 5
      #161 1
      #159 (Ljava/lang/String;)Lorg/scalatest/tools/Memento;
  1: #168 REF_invokeStatic java/lang/invoke/LambdaMetafactory.altMetafactory:(Ljava/lang/invoke/MethodHandles$Lookup;Ljava/lang/String;Ljava/lang/invoke/MethodType;[Ljava/lang/Object;)Ljava/lang/invoke/CallSite;
    Method arguments:
      #153 (Ljava/lang/Object;)Ljava/lang/Object;
      #200 REF_invokeStatic org/scalatest/tools/Memento$.$anonfun$writeToFile$1:(Lorg/scalatest/tools/Memento;)Ljava/lang/String;
      #201 (Lorg/scalatest/tools/Memento;)Ljava/lang/String;
      #160 5
      #161 1
      #201 (Lorg/scalatest/tools/Memento;)Ljava/lang/String;
  2: #168 REF_invokeStatic java/lang/invoke/LambdaMetafactory.altMetafactory:(Ljava/lang/invoke/MethodHandles$Lookup;Ljava/lang/String;Ljava/lang/invoke/MethodType;[Ljava/lang/Object;)Ljava/lang/invoke/CallSite;
    Method arguments:
      #212 (Ljava/lang/Object;Ljava/lang/Object;)Ljava/lang/Object;
      #217 REF_invokeStatic org/scalatest/tools/Memento$.$anonfun$writeToFile$2$adapted:(Ljava/lang/String;Ljava/lang/String;)Ljava/lang/Object;
      #218 (Ljava/lang/String;Ljava/lang/String;)Ljava/lang/Object;
      #160 5
      #161 1
      #218 (Ljava/lang/String;Ljava/lang/String;)Ljava/lang/Object;
  3: #168 REF_invokeStatic java/lang/invoke/LambdaMetafactory.altMetafactory:(Ljava/lang/invoke/MethodHandles$Lookup;Ljava/lang/String;Ljava/lang/invoke/MethodType;[Ljava/lang/Object;)Ljava/lang/invoke/CallSite;
    Method arguments:
      #153 (Ljava/lang/Object;)Ljava/lang/Object;
      #230 REF_invokeStatic org/scalatest/tools/Memento$.$anonfun$writeToFile$3$adapted:(Ljava/io/PrintWriter;Ljava/lang/String;)Ljava/lang/Object;
      #232 (Ljava/lang/String;)Ljava/lang/Object;
      #160 5
      #161 1
      #232 (Ljava/lang/String;)Ljava/lang/Object;
  4: #418 REF_invokeStatic scala/runtime/LambdaDeserialize.bootstrap:(Ljava/lang/invoke/MethodHandles$Lookup;Ljava/lang/String;Ljava/lang/invoke/MethodType;[Ljava/lang/invoke/MethodHandle;)Ljava/lang/invoke/CallSite;
    Method arguments:
      #158 REF_invokeStatic org/scalatest/tools/Memento$.$anonfun$readFromFile$1:(Ljava/lang/String;)Lorg/scalatest/tools/Memento;
      #200 REF_invokeStatic org/scalatest/tools/Memento$.$anonfun$writeToFile$1:(Lorg/scalatest/tools/Memento;)Ljava/lang/String;
      #217 REF_invokeStatic org/scalatest/tools/Memento$.$anonfun$writeToFile$2$adapted:(Ljava/lang/String;Ljava/lang/String;)Ljava/lang/Object;
      #230 REF_invokeStatic org/scalatest/tools/Memento$.$anonfun$writeToFile$3$adapted:(Ljava/io/PrintWriter;Ljava/lang/String;)Ljava/lang/Object;
  ScalaInlineInfo: length = 0x5E (unknown attribute)
   01 01 00 12 00 9A 00 9B 01 00 C4 00 C5 01 01 6E
   01 6F 01 00 D5 00 D6 01 01 82 01 83 01 00 E2 00
   E3 01 00 13 00 12 01 00 0F 01 1D 01 00 22 01 53
   01 00 22 00 23 01 01 16 01 17 01 01 41 01 17 01
   00 F6 00 9B 01 01 12 01 13 01 00 76 00 77 01 01
   55 01 56 01 01 61 00 58 01 00 B9 00 BA 01
  Scala: length = 0x0 (unknown attribute)

