Classfile /Users/mw/Projects/slang-braindump/.jar/jar8/assemble/slang-braindump/assemble/content/org/scalatest/tools/Memento.class
  Last modified May 29, 2022; size 11634 bytes
  SHA-256 checksum f5ece1469fe37cc27b440fbcbd0fa82286fa222f8ee6f5a0688549336b5e5a2b
  Compiled from "Memento.scala"
public class org.scalatest.tools.Memento implements scala.Product,java.io.Serializable
  minor version: 0
  major version: 52
  flags: (0x0021) ACC_PUBLIC, ACC_SUPER
  this_class: #2                          // org/scalatest/tools/Memento
  super_class: #4                         // java/lang/Object
  interfaces: 2, fields: 4, methods: 34, attributes: 6
Constant pool:
    #1 = Utf8               org/scalatest/tools/Memento
    #2 = Class              #1            // org/scalatest/tools/Memento
    #3 = Utf8               java/lang/Object
    #4 = Class              #3            // java/lang/Object
    #5 = Utf8               scala/Product
    #6 = Class              #5            // scala/Product
    #7 = Utf8               java/io/Serializable
    #8 = Class              #7            // java/io/Serializable
    #9 = Utf8               Memento.scala
   #10 = Utf8               Lscala/reflect/ScalaSignature;
   #11 = Utf8               bytes
   #12 = Utf8               \u0006\u0005\u0005uh!B\u0015+\u0001*\u0002\u0004\u0002C$\u0001\u0005+\u0007I\u0011\u0001%\t\u0011E\u0003!\u0011#Q\u0001\n%C\u0001B\u0015\u0001\u0003\u0016\u0004%\ta\u0015\u0005\t/\u0002\u0011\t\u0012)A\u0005)\"A\u0001\f\u0001BK\u0002\u0013\u0005\u0001\n\u0003\u0005Z\u0001\tE\t\u0015!\u0003J\u0011!Q\u0006A!f\u0001\n\u0003\u0019\u0006\u0002C.\u0001\u0005#\u0005\u000b\u0011\u0002+\t\u000bq\u0003A\u0011A/\t\u000b\u0011\u0004A\u0011\u0001%\t\u000b\u0015\u0004A\u0011\u00014\t\u000f)\u0004\u0011\u0011!C\u0001W\"9\u0001\u000fAI\u0001\n\u0003\t\bb\u0002?\u0001#\u0003%\t! \u0005\b\u007f\u0002\t\n\u0011\"\u0001r\u0011!\t\t\u0001AI\u0001\n\u0003i\b\"CA\u0002\u0001\u0005\u0005I\u0011IA\u0003\u0011%\t)\u0002AA\u0001\n\u0003\t9\u0002C\u0005\u0002 \u0001\t\t\u0011\"\u0001\u0002\"!I\u0011Q\u0006\u0001\u0002\u0002\u0013\u0005\u0013q\u0006\u0005\n\u0003{\u0001\u0011\u0011!C\u0001\u0003\u007fA\u0011\"!\u0013\u0001\u0003\u0003%\t%a\u0013\t\u0013\u0005=\u0003!!A\u0005B\u0005E\u0003\"CA*\u0001\u0005\u0005I\u0011IA+\u0011%\t9\u0006AA\u0001\n\u0003\nIf\u0002\u0005\u0002^)B\tAKA0\r\u001dI#\u0006#\u0001+\u0003CBa\u0001X\u000e\u0005\u0002\u00055\u0004bBA87\u0011\u0005\u0011\u0011\u000f\u0005\b\u0003\u0007[B\u0011AAC\u0011\u001d\t\tj\u0007C\u0001\u0003\'Cq!a*\u001c\t\u0003\tI\u000bC\u0005\u00020n\u0011\r\u0011\"\u0001\u00022\"A\u00111Y\u000e!\u0002\u0013\t\u0019\fC\u0004\u0002Fn!\t!a2\t\u000f\u0005-7\u0004\"\u0001\u0002N\"9\u00111[\u000e\u0005\u0002\u0005U\u0007\"CA87\u0005\u0005I\u0011QAm\u0011%\t\u0019oGA\u0001\n\u0003\u000b)\u000fC\u0005\u0002tn\t\t\u0011\"\u0003\u0002v\n9Q*Z7f]R|\'BA\u0016-\u0003\u0015!xn\u001c7t\u0015\tic&A\u0005tG\u0006d\u0017\r^3ti*\tq&A\u0002pe\u001e\u001cB\u0001A\u00198uA\u0011!\'N\u0007\u0002g)\tA\'A\u0003tG\u0006d\u0017-\u0003\u00027g\t1\u0011I\\=SK\u001a\u0004\"A\r\u001d\n\u0005e\u001a$a\u0002)s_\u0012,8\r\u001e\t\u0003w\u0011s!\u0001\u0010\"\u000f\u0005u\nU\"\u0001 \u000b\u0005}\u0002\u0015A\u0002\u001fs_>$hh\u0001\u0001\n\u0003QJ!aQ\u001a\u0002\u000fA\f7m[1hK&\u0011QI\u0012\u0002\r\'\u0016\u0014\u0018.\u00197ju\u0006\u0014G.\u001a\u0006\u0003\u0007N\n\u0011\"\u001a<f]Rt\u0015-\\3\u0016\u0003%\u0003\"A\u0013(\u000f\u0005-c\u0005CA\u001f4\u0013\ti5\'\u0001\u0004Qe\u0016$WMZ\u0005\u0003\u001fB\u0013aa\u0015;sS:<\'BA\'4\u0003))g/\u001a8u\u001d\u0006lW\rI\u0001\nG2\f7o\u001d(b[\u0016,\u0012\u0001\u0016\t\u0004eUK\u0015B\u0001,4\u0005\u0019y\u0005\u000f^5p]\u0006Q1\r\\1tg:\u000bW.\u001a\u0011\u0002\u000fM,\u0018\u000e^3JI\u0006A1/^5uK&#\u0007%\u0001\u0005uKN$h*Y7f\u0003%!Xm\u001d;OC6,\u0007%\u0001\u0004=S:LGO\u0010\u000b\u0006=\u0002\f\'m\u0019\t\u0003?\u0002i\u0011A\u000b\u0005\u0006\u000f&\u0001\r!\u0013\u0005\u0006%&\u0001\r\u0001\u0016\u0005\u00061&\u0001\r!\u0013\u0005\u00065&\u0001\r\u0001V\u0001\u000bg&tw\r\\3MS:,\u0017\u0001\u0004;p\'VLG/\u001a)be\u0006lW#A4\u0011\u0005}C\u0017BA5+\u0005)\u0019V/\u001b;f!\u0006\u0014\u0018-\\\u0001\u0005G>\u0004\u0018\u0010F\u0003_Y6tw\u000eC\u0004H\u0019A\u0005\t\u0019A%\t\u000fIc\u0001\u0013!a\u0001)\"9\u0001\f\u0004I\u0001\u0002\u0004I\u0005b\u0002.\r!\u0003\u0005\r\u0001V\u0001\u000fG>\u0004\u0018\u0010\n3fM\u0006,H\u000e\u001e\u00132+\u0005\u0011(FA%tW\u0005!\bCA;{\u001b\u00051(BA<y\u0003%)hn\u00195fG.,GM\u0003\u0002zg\u0005Q\u0011M\u001c8pi\u0006$\u0018n\u001c8\n\u0005m4(!E;oG\",7m[3e-\u0006\u0014\u0018.\u00198dK\u0006q1m\u001c9zI\u0011,g-Y;mi\u0012\u0012T#\u0001@+\u0005Q\u001b\u0018AD2paf$C-\u001a4bk2$HeM\u0001\u000fG>\u0004\u0018\u0010\n3fM\u0006,H\u000e\u001e\u00135\u00035\u0001(o\u001c3vGR\u0004&/\u001a4jqV\u0011\u0011q\u0001\t\u0005\u0003\u0013\t\u0019\"\u0004\u0002\u0002\f)!\u0011QBA\b\u0003\u0011a\u0017M\\4\u000b\u0005\u0005E\u0011\u0001\u00026bm\u0006L1aTA\u0006\u00031\u0001(o\u001c3vGR\f%/\u001b;z+\t\tI\u0002E\u00023\u00037I1!!\b4\u0005\rIe\u000e^\u0001\u000faJ|G-^2u\u000b2,W.\u001a8u)\u0011\t\u0019#!\u000b\u0011\u0007I\n)#C\u0002\u0002(M\u00121!\u00118z\u0011%\tYcEA\u0001\u0002\u0004\tI\"A\u0002yIE\nq\u0002\u001d:pIV\u001cG/\u0013;fe\u0006$xN]\u000b\u0003\u0003c\u0001b!a\r\u0002:\u0005\rRBAA\u001b\u0015\r\t9dM\u0001\u000bG>dG.Z2uS>t\u0017\u0002BA\u001e\u0003k\u0011\u0001\"\u0013;fe\u0006$xN]\u0001\tG\u0006tW)];bYR!\u0011\u0011IA$!\r\u0011\u00141I\u0005\u0004\u0003\u000b\u001a$a\u0002\"p_2,\u0017M\u001c\u0005\n\u0003W)\u0012\u0011!a\u0001\u0003G\t!\u0003\u001d:pIV\u001cG/\u00127f[\u0016tGOT1nKR!\u0011qAA\'\u0011%\tYCFA\u0001\u0002\u0004\tI\"\u0001\u0005iCND7i\u001c3f)\t\tI\"\u0001\u0005u_N#(/\u001b8h)\t\t9!\u0001\u0004fcV\fGn\u001d\u000b\u0005\u0003\u0003\nY\u0006C\u0005\u0002,e\t\t\u00111\u0001\u0002$\u00059Q*Z7f]R|\u0007CA0\u001c\'\u0011Y\u0012\'a\u0019\u0011\t\u0005\u0015\u00141N\u0007\u0003\u0003ORA!!\u001b\u0002\u0010\u0005\u0011\u0011n\\\u0005\u0004\u000b\u0006\u001dDCAA0\u0003\u0015\t\u0007\u000f\u001d7z)\rq\u00161\u000f\u0005\b\u0003kj\u0002\u0019AA<\u0003\u0015)g/\u001a8u!\u0011\tI(a \u000e\u0005\u0005m$bAA?Y\u00051QM^3oiNLA!!!\u0002|\t)QI^3oi\u0006a!/Z1e\rJ|WNR5mKR!\u0011qQAG!\u0011Y\u0014\u0011\u00120\n\u0007\u0005-eI\u0001\u0003MSN$\bBBAH=\u0001\u0007\u0011*\u0001\u0005gS2,g*Y7f\u0003-9(/\u001b;f)>4\u0015\u000e\\3\u0015\r\u0005U\u00151TAO!\r\u0011\u0014qS\u0005\u0004\u00033\u001b$\u0001B+oSRDa!a$ \u0001\u0004I\u0005bBAP?\u0001\u0007\u0011\u0011U\u0001\t[\u0016lWM\u001c;pgB!!*a)_\u0013\r\t)\u000b\u0015\u0002\u0004\'\u0016$\u0018A\u00034s_6\u001cFO]5oOR\u0019a,a+\t\r\u00055\u0006\u00051\u0001J\u0003\r\u0019HO]\u0001\f\'>lWMT8oKB\u000bG/\u0006\u0002\u00024B!\u0011QWA`\u001b\t\t9L\u0003\u0003\u0002:\u0006m\u0016!\u0002:fO\u0016D(\u0002BA_\u0003\u001f\tA!\u001e;jY&!\u0011\u0011YA\\\u0005\u001d\u0001\u0016\r\u001e;fe:\fAbU8nK:{g.\u001a)bi\u0002\n\u0001c\u001c9uS>tgI]8n\'R\u0014\u0018N\\4\u0015\u0007Q\u000bI\r\u0003\u0004\u0002.\u000e\u0002\r!S\u0001\u0007K:\u001cw\u000eZ3\u0015\u0007%\u000by\r\u0003\u0004\u0002R\u0012\u0002\r!S\u0001\u0005i\u0016DH/\u0001\u0004eK\u000e|G-\u001a\u000b\u0004\u0013\u0006]\u0007BBAiK\u0001\u0007\u0011\nF\u0005_\u00037\fi.a8\u0002b\")qI\na\u0001\u0013\")!K\na\u0001)\")\u0001L\na\u0001\u0013\")!L\na\u0001)\u00069QO\\1qa2LH\u0003BAt\u0003_\u0004BAM+\u0002jB9!\'a;J)&#\u0016bAAwg\t1A+\u001e9mKRB\u0001\"!=(\u0003\u0003\u0005\rAX\u0001\u0004q\u0012\u0002\u0014\u0001D<sSR,\'+\u001a9mC\u000e,GCAA|!\u0011\tI!!?\n\t\u0005m\u00181\u0002\u0002\u0007\u001f\nTWm\u0019;
   #13 = Utf8               java/lang/invoke/MethodHandles$Lookup
   #14 = Class              #13           // java/lang/invoke/MethodHandles$Lookup
   #15 = Utf8               java/lang/invoke/MethodHandles
   #16 = Class              #15           // java/lang/invoke/MethodHandles
   #17 = Utf8               Lookup
   #18 = Utf8               eventName
   #19 = Utf8               Ljava/lang/String;
   #20 = Utf8               className
   #21 = Utf8               Lscala/Option;
   #22 = Utf8               Lscala/Option<Ljava/lang/String;>;
   #23 = Utf8               suiteId
   #24 = Utf8               testName
   #25 = Utf8               unapply
   #26 = Utf8               (Lorg/scalatest/tools/Memento;)Lscala/Option;
   #27 = Utf8               (Lorg/scalatest/tools/Memento;)Lscala/Option<Lscala/Tuple4<Ljava/lang/String;Lscala/Option<Ljava/lang/String;>;Ljava/lang/String;Lscala/Option<Ljava/lang/String;>;>;>;
   #28 = Utf8               x$0
   #29 = Utf8               org/scalatest/tools/Memento$
   #30 = Class              #29           // org/scalatest/tools/Memento$
   #31 = Utf8               MODULE$
   #32 = Utf8               Lorg/scalatest/tools/Memento$;
   #33 = NameAndType        #31:#32       // MODULE$:Lorg/scalatest/tools/Memento$;
   #34 = Fieldref           #30.#33       // org/scalatest/tools/Memento$.MODULE$:Lorg/scalatest/tools/Memento$;
   #35 = NameAndType        #25:#26       // unapply:(Lorg/scalatest/tools/Memento;)Lscala/Option;
   #36 = Methodref          #30.#35       // org/scalatest/tools/Memento$.unapply:(Lorg/scalatest/tools/Memento;)Lscala/Option;
   #37 = Utf8               Lorg/scalatest/tools/Memento;
   #38 = Utf8               apply
   #39 = Utf8               (Ljava/lang/String;Lscala/Option;Ljava/lang/String;Lscala/Option;)Lorg/scalatest/tools/Memento;
   #40 = Utf8               (Ljava/lang/String;Lscala/Option<Ljava/lang/String;>;Ljava/lang/String;Lscala/Option<Ljava/lang/String;>;)Lorg/scalatest/tools/Memento;
   #41 = NameAndType        #38:#39       // apply:(Ljava/lang/String;Lscala/Option;Ljava/lang/String;Lscala/Option;)Lorg/scalatest/tools/Memento;
   #42 = Methodref          #30.#41       // org/scalatest/tools/Memento$.apply:(Ljava/lang/String;Lscala/Option;Ljava/lang/String;Lscala/Option;)Lorg/scalatest/tools/Memento;
   #43 = Utf8               decode
   #44 = Utf8               (Ljava/lang/String;)Ljava/lang/String;
   #45 = Utf8               text
   #46 = NameAndType        #43:#44       // decode:(Ljava/lang/String;)Ljava/lang/String;
   #47 = Methodref          #30.#46       // org/scalatest/tools/Memento$.decode:(Ljava/lang/String;)Ljava/lang/String;
   #48 = Utf8               encode
   #49 = NameAndType        #48:#44       // encode:(Ljava/lang/String;)Ljava/lang/String;
   #50 = Methodref          #30.#49       // org/scalatest/tools/Memento$.encode:(Ljava/lang/String;)Ljava/lang/String;
   #51 = Utf8               optionFromString
   #52 = Utf8               (Ljava/lang/String;)Lscala/Option;
   #53 = Utf8               (Ljava/lang/String;)Lscala/Option<Ljava/lang/String;>;
   #54 = Utf8               str
   #55 = NameAndType        #51:#52       // optionFromString:(Ljava/lang/String;)Lscala/Option;
   #56 = Methodref          #30.#55       // org/scalatest/tools/Memento$.optionFromString:(Ljava/lang/String;)Lscala/Option;
   #57 = Utf8               SomeNonePat
   #58 = Utf8               ()Ljava/util/regex/Pattern;
   #59 = NameAndType        #57:#58       // SomeNonePat:()Ljava/util/regex/Pattern;
   #60 = Methodref          #30.#59       // org/scalatest/tools/Memento$.SomeNonePat:()Ljava/util/regex/Pattern;
   #61 = Utf8               fromString
   #62 = Utf8               (Ljava/lang/String;)Lorg/scalatest/tools/Memento;
   #63 = NameAndType        #61:#62       // fromString:(Ljava/lang/String;)Lorg/scalatest/tools/Memento;
   #64 = Methodref          #30.#63       // org/scalatest/tools/Memento$.fromString:(Ljava/lang/String;)Lorg/scalatest/tools/Memento;
   #65 = Utf8               writeToFile
   #66 = Utf8               (Ljava/lang/String;Lscala/collection/immutable/Set;)V
   #67 = Utf8               (Ljava/lang/String;Lscala/collection/immutable/Set<Lorg/scalatest/tools/Memento;>;)V
   #68 = Utf8               fileName
   #69 = Utf8               mementos
   #70 = NameAndType        #65:#66       // writeToFile:(Ljava/lang/String;Lscala/collection/immutable/Set;)V
   #71 = Methodref          #30.#70       // org/scalatest/tools/Memento$.writeToFile:(Ljava/lang/String;Lscala/collection/immutable/Set;)V
   #72 = Utf8               Lscala/collection/immutable/Set;
   #73 = Utf8               readFromFile
   #74 = Utf8               (Ljava/lang/String;)Lscala/collection/immutable/List;
   #75 = Utf8               (Ljava/lang/String;)Lscala/collection/immutable/List<Lorg/scalatest/tools/Memento;>;
   #76 = NameAndType        #73:#74       // readFromFile:(Ljava/lang/String;)Lscala/collection/immutable/List;
   #77 = Methodref          #30.#76       // org/scalatest/tools/Memento$.readFromFile:(Ljava/lang/String;)Lscala/collection/immutable/List;
   #78 = Utf8               (Lorg/scalatest/events/Event;)Lorg/scalatest/tools/Memento;
   #79 = Utf8               event
   #80 = NameAndType        #38:#78       // apply:(Lorg/scalatest/events/Event;)Lorg/scalatest/tools/Memento;
   #81 = Methodref          #30.#80       // org/scalatest/tools/Memento$.apply:(Lorg/scalatest/events/Event;)Lorg/scalatest/tools/Memento;
   #82 = Utf8               Lorg/scalatest/events/Event;
   #83 = Utf8               productElementNames
   #84 = Utf8               ()Lscala/collection/Iterator;
   #85 = Utf8               ()Lscala/collection/Iterator<Ljava/lang/String;>;
   #86 = Utf8               productElementNames$
   #87 = Utf8               (Lscala/Product;)Lscala/collection/Iterator;
   #88 = NameAndType        #86:#87       // productElementNames$:(Lscala/Product;)Lscala/collection/Iterator;
   #89 = InterfaceMethodref #6.#88        // scala/Product.productElementNames$:(Lscala/Product;)Lscala/collection/Iterator;
   #90 = Utf8               this
   #91 = Utf8               ()Ljava/lang/String;
   #92 = NameAndType        #18:#19       // eventName:Ljava/lang/String;
   #93 = Fieldref           #2.#92        // org/scalatest/tools/Memento.eventName:Ljava/lang/String;
   #94 = Utf8               ()Lscala/Option;
   #95 = Utf8               ()Lscala/Option<Ljava/lang/String;>;
   #96 = NameAndType        #20:#21       // className:Lscala/Option;
   #97 = Fieldref           #2.#96        // org/scalatest/tools/Memento.className:Lscala/Option;
   #98 = NameAndType        #23:#19       // suiteId:Ljava/lang/String;
   #99 = Fieldref           #2.#98        // org/scalatest/tools/Memento.suiteId:Ljava/lang/String;
  #100 = NameAndType        #24:#21       // testName:Lscala/Option;
  #101 = Fieldref           #2.#100       // org/scalatest/tools/Memento.testName:Lscala/Option;
  #102 = Utf8               singleLine
  #103 = Utf8               java/lang/StringBuilder
  #104 = Class              #103          // java/lang/StringBuilder
  #105 = Integer            3
  #106 = Utf8               <init>
  #107 = Utf8               (I)V
  #108 = NameAndType        #106:#107     // "<init>":(I)V
  #109 = Methodref          #104.#108     // java/lang/StringBuilder."<init>":(I)V
  #110 = NameAndType        #18:#91       // eventName:()Ljava/lang/String;
  #111 = Methodref          #2.#110       // org/scalatest/tools/Memento.eventName:()Ljava/lang/String;
  #112 = Utf8               append
  #113 = Utf8               (Ljava/lang/String;)Ljava/lang/StringBuilder;
  #114 = NameAndType        #112:#113     // append:(Ljava/lang/String;)Ljava/lang/StringBuilder;
  #115 = Methodref          #104.#114     // java/lang/StringBuilder.append:(Ljava/lang/String;)Ljava/lang/StringBuilder;
  #116 = Utf8
  #117 = String             #116          //
  #118 = NameAndType        #20:#94       // className:()Lscala/Option;
  #119 = Methodref          #2.#118       // org/scalatest/tools/Memento.className:()Lscala/Option;
  #120 = Utf8               (Ljava/lang/Object;)Ljava/lang/StringBuilder;
  #121 = NameAndType        #112:#120     // append:(Ljava/lang/Object;)Ljava/lang/StringBuilder;
  #122 = Methodref          #104.#121     // java/lang/StringBuilder.append:(Ljava/lang/Object;)Ljava/lang/StringBuilder;
  #123 = NameAndType        #23:#91       // suiteId:()Ljava/lang/String;
  #124 = Methodref          #2.#123       // org/scalatest/tools/Memento.suiteId:()Ljava/lang/String;
  #125 = NameAndType        #24:#94       // testName:()Lscala/Option;
  #126 = Methodref          #2.#125       // org/scalatest/tools/Memento.testName:()Lscala/Option;
  #127 = Utf8               scala/Option
  #128 = Class              #127          // scala/Option
  #129 = Utf8               toString
  #130 = NameAndType        #129:#91      // toString:()Ljava/lang/String;
  #131 = Methodref          #128.#130     // scala/Option.toString:()Ljava/lang/String;
  #132 = Methodref          #104.#130     // java/lang/StringBuilder.toString:()Ljava/lang/String;
  #133 = Utf8               toSuiteParam
  #134 = Utf8               ()Lorg/scalatest/tools/SuiteParam;
  #135 = Utf8               scala/Some
  #136 = Class              #135          // scala/Some
  #137 = Utf8               value
  #138 = Utf8               ()Ljava/lang/Object;
  #139 = NameAndType        #137:#138     // value:()Ljava/lang/Object;
  #140 = Methodref          #136.#139     // scala/Some.value:()Ljava/lang/Object;
  #141 = Utf8               java/lang/String
  #142 = Class              #141          // java/lang/String
  #143 = Utf8               [Ljava/lang/Object;
  #144 = Class              #143          // "[Ljava/lang/Object;"
  #145 = Utf8               [Ljava/lang/String;
  #146 = Class              #145          // "[Ljava/lang/String;"
  #147 = Utf8               scala/None$
  #148 = Class              #147          // scala/None$
  #149 = Utf8               Lscala/None$;
  #150 = NameAndType        #31:#149      // MODULE$:Lscala/None$;
  #151 = Fieldref           #148.#150     // scala/None$.MODULE$:Lscala/None$;
  #152 = Utf8               equals
  #153 = Utf8               (Ljava/lang/Object;)Z
  #154 = NameAndType        #152:#153     // equals:(Ljava/lang/Object;)Z
  #155 = Methodref          #4.#154       // java/lang/Object.equals:(Ljava/lang/Object;)Z
  #156 = Utf8               scala/Array$
  #157 = Class              #156          // scala/Array$
  #158 = Utf8               Lscala/Array$;
  #159 = NameAndType        #31:#158      // MODULE$:Lscala/Array$;
  #160 = Fieldref           #157.#159     // scala/Array$.MODULE$:Lscala/Array$;
  #161 = Utf8               scala/reflect/ClassTag$
  #162 = Class              #161          // scala/reflect/ClassTag$
  #163 = Utf8               Lscala/reflect/ClassTag$;
  #164 = NameAndType        #31:#163      // MODULE$:Lscala/reflect/ClassTag$;
  #165 = Fieldref           #162.#164     // scala/reflect/ClassTag$.MODULE$:Lscala/reflect/ClassTag$;
  #166 = Utf8               (Ljava/lang/Class;)Lscala/reflect/ClassTag;
  #167 = NameAndType        #38:#166      // apply:(Ljava/lang/Class;)Lscala/reflect/ClassTag;
  #168 = Methodref          #162.#167     // scala/reflect/ClassTag$.apply:(Ljava/lang/Class;)Lscala/reflect/ClassTag;
  #169 = Utf8               empty
  #170 = Utf8               (Lscala/reflect/ClassTag;)Ljava/lang/Object;
  #171 = NameAndType        #169:#170     // empty:(Lscala/reflect/ClassTag;)Ljava/lang/Object;
  #172 = Methodref          #157.#171     // scala/Array$.empty:(Lscala/reflect/ClassTag;)Ljava/lang/Object;
  #173 = Utf8               scala/MatchError
  #174 = Class              #173          // scala/MatchError
  #175 = Utf8               (Ljava/lang/Object;)V
  #176 = NameAndType        #106:#175     // "<init>":(Ljava/lang/Object;)V
  #177 = Methodref          #174.#176     // scala/MatchError."<init>":(Ljava/lang/Object;)V
  #178 = MethodType         #138          //  ()Ljava/lang/Object;
  #179 = Utf8               $anonfun$toSuiteParam$1
  #180 = NameAndType        #179:#91      // $anonfun$toSuiteParam$1:()Ljava/lang/String;
  #181 = Methodref          #2.#180       // org/scalatest/tools/Memento.$anonfun$toSuiteParam$1:()Ljava/lang/String;
  #182 = MethodHandle       6:#181        // REF_invokeStatic org/scalatest/tools/Memento.$anonfun$toSuiteParam$1:()Ljava/lang/String;
  #183 = MethodType         #91           //  ()Ljava/lang/String;
  #184 = Integer            5
  #185 = Integer            1
  #186 = Utf8               java/lang/invoke/LambdaMetafactory
  #187 = Class              #186          // java/lang/invoke/LambdaMetafactory
  #188 = Utf8               altMetafactory
  #189 = Utf8               (Ljava/lang/invoke/MethodHandles$Lookup;Ljava/lang/String;Ljava/lang/invoke/MethodType;[Ljava/lang/Object;)Ljava/lang/invoke/CallSite;
  #190 = NameAndType        #188:#189     // altMetafactory:(Ljava/lang/invoke/MethodHandles$Lookup;Ljava/lang/String;Ljava/lang/invoke/MethodType;[Ljava/lang/Object;)Ljava/lang/invoke/CallSite;
  #191 = Methodref          #187.#190     // java/lang/invoke/LambdaMetafactory.altMetafactory:(Ljava/lang/invoke/MethodHandles$Lookup;Ljava/lang/String;Ljava/lang/invoke/MethodType;[Ljava/lang/Object;)Ljava/lang/invoke/CallSite;
  #192 = MethodHandle       6:#191        // REF_invokeStatic java/lang/invoke/LambdaMetafactory.altMetafactory:(Ljava/lang/invoke/MethodHandles$Lookup;Ljava/lang/String;Ljava/lang/invoke/MethodType;[Ljava/lang/Object;)Ljava/lang/invoke/CallSite;
  #193 = Utf8               ()Lscala/Function0;
  #194 = NameAndType        #38:#193      // apply:()Lscala/Function0;
  #195 = InvokeDynamic      #0:#194       // #0:apply:()Lscala/Function0;
  #196 = Utf8               getOrElse
  #197 = Utf8               (Lscala/Function0;)Ljava/lang/Object;
  #198 = NameAndType        #196:#197     // getOrElse:(Lscala/Function0;)Ljava/lang/Object;
  #199 = Methodref          #128.#198     // scala/Option.getOrElse:(Lscala/Function0;)Ljava/lang/Object;
  #200 = Utf8               scala/Tuple2
  #201 = Class              #200          // scala/Tuple2
  #202 = Utf8               org/scalatest/tools/NestedSuiteParam
  #203 = Class              #202          // org/scalatest/tools/NestedSuiteParam
  #204 = Utf8               (Ljava/lang/Object;Ljava/lang/Object;)V
  #205 = NameAndType        #106:#204     // "<init>":(Ljava/lang/Object;Ljava/lang/Object;)V
  #206 = Methodref          #201.#205     // scala/Tuple2."<init>":(Ljava/lang/Object;Ljava/lang/Object;)V
  #207 = Utf8               scala/collection/immutable/Nil$
  #208 = Class              #207          // scala/collection/immutable/Nil$
  #209 = Utf8               Lscala/collection/immutable/Nil$;
  #210 = NameAndType        #31:#209      // MODULE$:Lscala/collection/immutable/Nil$;
  #211 = Fieldref           #208.#210     // scala/collection/immutable/Nil$.MODULE$:Lscala/collection/immutable/Nil$;
  #212 = Utf8               (Lscala/collection/immutable/Seq;Lscala/reflect/ClassTag;)Ljava/lang/Object;
  #213 = NameAndType        #38:#212      // apply:(Lscala/collection/immutable/Seq;Lscala/reflect/ClassTag;)Ljava/lang/Object;
  #214 = Methodref          #157.#213     // scala/Array$.apply:(Lscala/collection/immutable/Seq;Lscala/reflect/ClassTag;)Ljava/lang/Object;
  #215 = Utf8               (Ljava/lang/String;[Ljava/lang/String;[Ljava/lang/String;)V
  #216 = NameAndType        #106:#215     // "<init>":(Ljava/lang/String;[Ljava/lang/String;[Ljava/lang/String;)V
  #217 = Methodref          #203.#216     // org/scalatest/tools/NestedSuiteParam."<init>":(Ljava/lang/String;[Ljava/lang/String;[Ljava/lang/String;)V
  #218 = Utf8               _1
  #219 = NameAndType        #218:#138     // _1:()Ljava/lang/Object;
  #220 = Methodref          #201.#219     // scala/Tuple2._1:()Ljava/lang/Object;
  #221 = Utf8               _2
  #222 = NameAndType        #221:#138     // _2:()Ljava/lang/Object;
  #223 = Methodref          #201.#222     // scala/Tuple2._2:()Ljava/lang/Object;
  #224 = Utf8               [Lorg/scalatest/tools/NestedSuiteParam;
  #225 = Class              #224          // "[Lorg/scalatest/tools/NestedSuiteParam;"
  #226 = Utf8               org/scalatest/tools/SuiteParam
  #227 = Class              #226          // org/scalatest/tools/SuiteParam
  #228 = Utf8               (Ljava/lang/String;[Ljava/lang/String;[Ljava/lang/String;[Lorg/scalatest/tools/NestedSuiteParam;)V
  #229 = NameAndType        #106:#228     // "<init>":(Ljava/lang/String;[Ljava/lang/String;[Ljava/lang/String;[Lorg/scalatest/tools/NestedSuiteParam;)V
  #230 = Methodref          #227.#229     // org/scalatest/tools/SuiteParam."<init>":(Ljava/lang/String;[Ljava/lang/String;[Ljava/lang/String;[Lorg/scalatest/tools/NestedSuiteParam;)V
  #231 = Utf8               name
  #232 = Utf8               nestedSuiteParam
  #233 = Utf8               Lorg/scalatest/tools/NestedSuiteParam;
  #234 = Utf8               testNames
  #235 = Utf8               nestedSuites
  #236 = Utf8               testNamesArray
  #237 = Utf8               classNameStr
  #238 = Utf8               copy
  #239 = Utf8               (Ljava/lang/String;Lscala/Option;Ljava/lang/String;Lscala/Option;)V
  #240 = NameAndType        #106:#239     // "<init>":(Ljava/lang/String;Lscala/Option;Ljava/lang/String;Lscala/Option;)V
  #241 = Methodref          #2.#240       // org/scalatest/tools/Memento."<init>":(Ljava/lang/String;Lscala/Option;Ljava/lang/String;Lscala/Option;)V
  #242 = Utf8               copy$default$1
  #243 = Utf8               copy$default$2
  #244 = Utf8               copy$default$3
  #245 = Utf8               copy$default$4
  #246 = Utf8               productPrefix
  #247 = Utf8               Memento
  #248 = String             #247          // Memento
  #249 = Utf8               productArity
  #250 = Utf8               ()I
  #251 = Utf8               productElement
  #252 = Utf8               (I)Ljava/lang/Object;
  #253 = Utf8               x$1
  #254 = Utf8               scala/runtime/Statics
  #255 = Class              #254          // scala/runtime/Statics
  #256 = Utf8               ioobe
  #257 = NameAndType        #256:#252     // ioobe:(I)Ljava/lang/Object;
  #258 = Methodref          #255.#257     // scala/runtime/Statics.ioobe:(I)Ljava/lang/Object;
  #259 = Utf8               I
  #260 = Utf8               productIterator
  #261 = Utf8               ()Lscala/collection/Iterator<Ljava/lang/Object;>;
  #262 = Utf8               scala/runtime/ScalaRunTime$
  #263 = Class              #262          // scala/runtime/ScalaRunTime$
  #264 = Utf8               Lscala/runtime/ScalaRunTime$;
  #265 = NameAndType        #31:#264      // MODULE$:Lscala/runtime/ScalaRunTime$;
  #266 = Fieldref           #263.#265     // scala/runtime/ScalaRunTime$.MODULE$:Lscala/runtime/ScalaRunTime$;
  #267 = Utf8               typedProductIterator
  #268 = NameAndType        #267:#87      // typedProductIterator:(Lscala/Product;)Lscala/collection/Iterator;
  #269 = Methodref          #263.#268     // scala/runtime/ScalaRunTime$.typedProductIterator:(Lscala/Product;)Lscala/collection/Iterator;
  #270 = Utf8               canEqual
  #271 = Utf8               Ljava/lang/Object;
  #272 = Utf8               productElementName
  #273 = Utf8               (I)Ljava/lang/String;
  #274 = String             #18           // eventName
  #275 = String             #20           // className
  #276 = String             #23           // suiteId
  #277 = String             #24           // testName
  #278 = Utf8               hashCode
  #279 = Utf8               _hashCode
  #280 = Utf8               (Lscala/Product;)I
  #281 = NameAndType        #279:#280     // _hashCode:(Lscala/Product;)I
  #282 = Methodref          #263.#281     // scala/runtime/ScalaRunTime$._hashCode:(Lscala/Product;)I
  #283 = Utf8               _toString
  #284 = Utf8               (Lscala/Product;)Ljava/lang/String;
  #285 = NameAndType        #283:#284     // _toString:(Lscala/Product;)Ljava/lang/String;
  #286 = Methodref          #263.#285     // scala/runtime/ScalaRunTime$._toString:(Lscala/Product;)Ljava/lang/String;
  #287 = NameAndType        #270:#153     // canEqual:(Ljava/lang/Object;)Z
  #288 = Methodref          #2.#287       // org/scalatest/tools/Memento.canEqual:(Ljava/lang/Object;)Z
  #289 = Utf8               unknown
  #290 = String             #289          // unknown
  #291 = Utf8               (Ljava/lang/String;Lscala/Option<Ljava/lang/String;>;Ljava/lang/String;Lscala/Option<Ljava/lang/String;>;)V
  #292 = Utf8               ()V
  #293 = NameAndType        #106:#292     // "<init>":()V
  #294 = Methodref          #4.#293       // java/lang/Object."<init>":()V
  #295 = Utf8               $init$
  #296 = Utf8               (Lscala/Product;)V
  #297 = NameAndType        #295:#296     // $init$:(Lscala/Product;)V
  #298 = InterfaceMethodref #6.#297       // scala/Product.$init$:(Lscala/Product;)V
  #299 = Utf8               $deserializeLambda$
  #300 = Utf8               (Ljava/lang/invoke/SerializedLambda;)Ljava/lang/Object;
  #301 = Utf8               scala/runtime/LambdaDeserialize
  #302 = Class              #301          // scala/runtime/LambdaDeserialize
  #303 = Utf8               bootstrap
  #304 = Utf8               (Ljava/lang/invoke/MethodHandles$Lookup;Ljava/lang/String;Ljava/lang/invoke/MethodType;[Ljava/lang/invoke/MethodHandle;)Ljava/lang/invoke/CallSite;
  #305 = NameAndType        #303:#304     // bootstrap:(Ljava/lang/invoke/MethodHandles$Lookup;Ljava/lang/String;Ljava/lang/invoke/MethodType;[Ljava/lang/invoke/MethodHandle;)Ljava/lang/invoke/CallSite;
  #306 = Methodref          #302.#305     // scala/runtime/LambdaDeserialize.bootstrap:(Ljava/lang/invoke/MethodHandles$Lookup;Ljava/lang/String;Ljava/lang/invoke/MethodType;[Ljava/lang/invoke/MethodHandle;)Ljava/lang/invoke/CallSite;
  #307 = MethodHandle       6:#306        // REF_invokeStatic scala/runtime/LambdaDeserialize.bootstrap:(Ljava/lang/invoke/MethodHandles$Lookup;Ljava/lang/String;Ljava/lang/invoke/MethodType;[Ljava/lang/invoke/MethodHandle;)Ljava/lang/invoke/CallSite;
  #308 = Utf8               lambdaDeserialize
  #309 = NameAndType        #308:#300     // lambdaDeserialize:(Ljava/lang/invoke/SerializedLambda;)Ljava/lang/Object;
  #310 = InvokeDynamic      #1:#309       // #1:lambdaDeserialize:(Ljava/lang/invoke/SerializedLambda;)Ljava/lang/Object;
  #311 = Utf8               Signature
  #312 = Utf8               Code
  #313 = Utf8               LocalVariableTable
  #314 = Utf8               MethodParameters
  #315 = Utf8               LineNumberTable
  #316 = Utf8               StackMapTable
  #317 = Utf8               InnerClasses
  #318 = Utf8               SourceFile
  #319 = Utf8               RuntimeVisibleAnnotations
  #320 = Utf8               BootstrapMethods
  #321 = Utf8               ScalaInlineInfo
  #322 = Utf8               ScalaSig
{
  private final java.lang.String eventName;
    descriptor: Ljava/lang/String;
    flags: (0x0012) ACC_PRIVATE, ACC_FINAL

  private final scala.Option<java.lang.String> className;
    descriptor: Lscala/Option;
    flags: (0x0012) ACC_PRIVATE, ACC_FINAL
    Signature: #22                          // Lscala/Option<Ljava/lang/String;>;

  private final java.lang.String suiteId;
    descriptor: Ljava/lang/String;
    flags: (0x0012) ACC_PRIVATE, ACC_FINAL

  private final scala.Option<java.lang.String> testName;
    descriptor: Lscala/Option;
    flags: (0x0012) ACC_PRIVATE, ACC_FINAL
    Signature: #22                          // Lscala/Option<Ljava/lang/String;>;

  public static scala.Option<scala.Tuple4<java.lang.String, scala.Option<java.lang.String>, java.lang.String, scala.Option<java.lang.String>>> unapply(org.scalatest.tools.Memento);
    descriptor: (Lorg/scalatest/tools/Memento;)Lscala/Option;
    flags: (0x0009) ACC_PUBLIC, ACC_STATIC
    Code:
      stack=2, locals=1, args_size=1
         0: getstatic     #34                 // Field org/scalatest/tools/Memento$.MODULE$:Lorg/scalatest/tools/Memento$;
         3: aload_0
         4: invokevirtual #36                 // Method org/scalatest/tools/Memento$.unapply:(Lorg/scalatest/tools/Memento;)Lscala/Option;
         7: areturn
      LocalVariableTable:
        Start  Length  Slot  Name   Signature
            0       8     0   x$0   Lorg/scalatest/tools/Memento;
    Signature: #27                          // (Lorg/scalatest/tools/Memento;)Lscala/Option<Lscala/Tuple4<Ljava/lang/String;Lscala/Option<Ljava/lang/String;>;Ljava/lang/String;Lscala/Option<Ljava/lang/String;>;>;>;
    MethodParameters:
      Name                           Flags
      x$0                            final

  public static org.scalatest.tools.Memento apply(java.lang.String, scala.Option<java.lang.String>, java.lang.String, scala.Option<java.lang.String>);
    descriptor: (Ljava/lang/String;Lscala/Option;Ljava/lang/String;Lscala/Option;)Lorg/scalatest/tools/Memento;
    flags: (0x0009) ACC_PUBLIC, ACC_STATIC
    Code:
      stack=5, locals=4, args_size=4
         0: getstatic     #34                 // Field org/scalatest/tools/Memento$.MODULE$:Lorg/scalatest/tools/Memento$;
         3: aload_0
         4: aload_1
         5: aload_2
         6: aload_3
         7: invokevirtual #42                 // Method org/scalatest/tools/Memento$.apply:(Ljava/lang/String;Lscala/Option;Ljava/lang/String;Lscala/Option;)Lorg/scalatest/tools/Memento;
        10: areturn
      LocalVariableTable:
        Start  Length  Slot  Name   Signature
            0      11     0 eventName   Ljava/lang/String;
            0      11     1 className   Lscala/Option;
            0      11     2 suiteId   Ljava/lang/String;
            0      11     3 testName   Lscala/Option;
    Signature: #40                          // (Ljava/lang/String;Lscala/Option<Ljava/lang/String;>;Ljava/lang/String;Lscala/Option<Ljava/lang/String;>;)Lorg/scalatest/tools/Memento;
    MethodParameters:
      Name                           Flags
      eventName                      final
      className                      final
      suiteId                        final
      testName                       final

  public static java.lang.String decode(java.lang.String);
    descriptor: (Ljava/lang/String;)Ljava/lang/String;
    flags: (0x0009) ACC_PUBLIC, ACC_STATIC
    Code:
      stack=2, locals=1, args_size=1
         0: getstatic     #34                 // Field org/scalatest/tools/Memento$.MODULE$:Lorg/scalatest/tools/Memento$;
         3: aload_0
         4: invokevirtual #47                 // Method org/scalatest/tools/Memento$.decode:(Ljava/lang/String;)Ljava/lang/String;
         7: areturn
      LocalVariableTable:
        Start  Length  Slot  Name   Signature
            0       8     0  text   Ljava/lang/String;
    MethodParameters:
      Name                           Flags
      text                           final

  public static java.lang.String encode(java.lang.String);
    descriptor: (Ljava/lang/String;)Ljava/lang/String;
    flags: (0x0009) ACC_PUBLIC, ACC_STATIC
    Code:
      stack=2, locals=1, args_size=1
         0: getstatic     #34                 // Field org/scalatest/tools/Memento$.MODULE$:Lorg/scalatest/tools/Memento$;
         3: aload_0
         4: invokevirtual #50                 // Method org/scalatest/tools/Memento$.encode:(Ljava/lang/String;)Ljava/lang/String;
         7: areturn
      LocalVariableTable:
        Start  Length  Slot  Name   Signature
            0       8     0  text   Ljava/lang/String;
    MethodParameters:
      Name                           Flags
      text                           final

  public static scala.Option<java.lang.String> optionFromString(java.lang.String);
    descriptor: (Ljava/lang/String;)Lscala/Option;
    flags: (0x0009) ACC_PUBLIC, ACC_STATIC
    Code:
      stack=2, locals=1, args_size=1
         0: getstatic     #34                 // Field org/scalatest/tools/Memento$.MODULE$:Lorg/scalatest/tools/Memento$;
         3: aload_0
         4: invokevirtual #56                 // Method org/scalatest/tools/Memento$.optionFromString:(Ljava/lang/String;)Lscala/Option;
         7: areturn
      LocalVariableTable:
        Start  Length  Slot  Name   Signature
            0       8     0   str   Ljava/lang/String;
    Signature: #53                          // (Ljava/lang/String;)Lscala/Option<Ljava/lang/String;>;
    MethodParameters:
      Name                           Flags
      str                            final

  public static java.util.regex.Pattern SomeNonePat();
    descriptor: ()Ljava/util/regex/Pattern;
    flags: (0x0009) ACC_PUBLIC, ACC_STATIC
    Code:
      stack=1, locals=0, args_size=0
         0: getstatic     #34                 // Field org/scalatest/tools/Memento$.MODULE$:Lorg/scalatest/tools/Memento$;
         3: invokevirtual #60                 // Method org/scalatest/tools/Memento$.SomeNonePat:()Ljava/util/regex/Pattern;
         6: areturn

  public static org.scalatest.tools.Memento fromString(java.lang.String);
    descriptor: (Ljava/lang/String;)Lorg/scalatest/tools/Memento;
    flags: (0x0009) ACC_PUBLIC, ACC_STATIC
    Code:
      stack=2, locals=1, args_size=1
         0: getstatic     #34                 // Field org/scalatest/tools/Memento$.MODULE$:Lorg/scalatest/tools/Memento$;
         3: aload_0
         4: invokevirtual #64                 // Method org/scalatest/tools/Memento$.fromString:(Ljava/lang/String;)Lorg/scalatest/tools/Memento;
         7: areturn
      LocalVariableTable:
        Start  Length  Slot  Name   Signature
            0       8     0   str   Ljava/lang/String;
    MethodParameters:
      Name                           Flags
      str                            final

  public static void writeToFile(java.lang.String, scala.collection.immutable.Set<org.scalatest.tools.Memento>);
    descriptor: (Ljava/lang/String;Lscala/collection/immutable/Set;)V
    flags: (0x0009) ACC_PUBLIC, ACC_STATIC
    Code:
      stack=3, locals=2, args_size=2
         0: getstatic     #34                 // Field org/scalatest/tools/Memento$.MODULE$:Lorg/scalatest/tools/Memento$;
         3: aload_0
         4: aload_1
         5: invokevirtual #71                 // Method org/scalatest/tools/Memento$.writeToFile:(Ljava/lang/String;Lscala/collection/immutable/Set;)V
         8: return
      LocalVariableTable:
        Start  Length  Slot  Name   Signature
            0       9     0 fileName   Ljava/lang/String;
            0       9     1 mementos   Lscala/collection/immutable/Set;
    Signature: #67                          // (Ljava/lang/String;Lscala/collection/immutable/Set<Lorg/scalatest/tools/Memento;>;)V
    MethodParameters:
      Name                           Flags
      fileName                       final
      mementos                       final

  public static scala.collection.immutable.List<org.scalatest.tools.Memento> readFromFile(java.lang.String);
    descriptor: (Ljava/lang/String;)Lscala/collection/immutable/List;
    flags: (0x0009) ACC_PUBLIC, ACC_STATIC
    Code:
      stack=2, locals=1, args_size=1
         0: getstatic     #34                 // Field org/scalatest/tools/Memento$.MODULE$:Lorg/scalatest/tools/Memento$;
         3: aload_0
         4: invokevirtual #77                 // Method org/scalatest/tools/Memento$.readFromFile:(Ljava/lang/String;)Lscala/collection/immutable/List;
         7: areturn
      LocalVariableTable:
        Start  Length  Slot  Name   Signature
            0       8     0 fileName   Ljava/lang/String;
    Signature: #75                          // (Ljava/lang/String;)Lscala/collection/immutable/List<Lorg/scalatest/tools/Memento;>;
    MethodParameters:
      Name                           Flags
      fileName                       final

  public static org.scalatest.tools.Memento apply(org.scalatest.events.Event);
    descriptor: (Lorg/scalatest/events/Event;)Lorg/scalatest/tools/Memento;
    flags: (0x0009) ACC_PUBLIC, ACC_STATIC
    Code:
      stack=2, locals=1, args_size=1
         0: getstatic     #34                 // Field org/scalatest/tools/Memento$.MODULE$:Lorg/scalatest/tools/Memento$;
         3: aload_0
         4: invokevirtual #81                 // Method org/scalatest/tools/Memento$.apply:(Lorg/scalatest/events/Event;)Lorg/scalatest/tools/Memento;
         7: areturn
      LocalVariableTable:
        Start  Length  Slot  Name   Signature
            0       8     0 event   Lorg/scalatest/events/Event;
    MethodParameters:
      Name                           Flags
      event                          final

  public scala.collection.Iterator<java.lang.String> productElementNames();
    descriptor: ()Lscala/collection/Iterator;
    flags: (0x0001) ACC_PUBLIC
    Code:
      stack=1, locals=1, args_size=1
         0: aload_0
         1: invokestatic  #89                 // InterfaceMethod scala/Product.productElementNames$:(Lscala/Product;)Lscala/collection/Iterator;
         4: areturn
      LineNumberTable:
        line 34: 0
      LocalVariableTable:
        Start  Length  Slot  Name   Signature
            0       5     0  this   Lorg/scalatest/tools/Memento;
    Signature: #85                          // ()Lscala/collection/Iterator<Ljava/lang/String;>;

  public java.lang.String eventName();
    descriptor: ()Ljava/lang/String;
    flags: (0x0001) ACC_PUBLIC
    Code:
      stack=1, locals=1, args_size=1
         0: aload_0
         1: getfield      #93                 // Field eventName:Ljava/lang/String;
         4: areturn
      LineNumberTable:
        line 34: 0
      LocalVariableTable:
        Start  Length  Slot  Name   Signature
            0       5     0  this   Lorg/scalatest/tools/Memento;

  public scala.Option<java.lang.String> className();
    descriptor: ()Lscala/Option;
    flags: (0x0001) ACC_PUBLIC
    Code:
      stack=1, locals=1, args_size=1
         0: aload_0
         1: getfield      #97                 // Field className:Lscala/Option;
         4: areturn
      LineNumberTable:
        line 35: 0
      LocalVariableTable:
        Start  Length  Slot  Name   Signature
            0       5     0  this   Lorg/scalatest/tools/Memento;
    Signature: #95                          // ()Lscala/Option<Ljava/lang/String;>;

  public java.lang.String suiteId();
    descriptor: ()Ljava/lang/String;
    flags: (0x0001) ACC_PUBLIC
    Code:
      stack=1, locals=1, args_size=1
         0: aload_0
         1: getfield      #99                 // Field suiteId:Ljava/lang/String;
         4: areturn
      LineNumberTable:
        line 36: 0
      LocalVariableTable:
        Start  Length  Slot  Name   Signature
            0       5     0  this   Lorg/scalatest/tools/Memento;

  public scala.Option<java.lang.String> testName();
    descriptor: ()Lscala/Option;
    flags: (0x0001) ACC_PUBLIC
    Code:
      stack=1, locals=1, args_size=1
         0: aload_0
         1: getfield      #101                // Field testName:Lscala/Option;
         4: areturn
      LineNumberTable:
        line 37: 0
      LocalVariableTable:
        Start  Length  Slot  Name   Signature
            0       5     0  this   Lorg/scalatest/tools/Memento;
    Signature: #95                          // ()Lscala/Option<Ljava/lang/String;>;

  public java.lang.String singleLine();
    descriptor: ()Ljava/lang/String;
    flags: (0x0001) ACC_PUBLIC
    Code:
      stack=3, locals=1, args_size=1
         0: new           #104                // class java/lang/StringBuilder
         3: dup
         4: ldc           #105                // int 3
         6: invokespecial #109                // Method java/lang/StringBuilder."<init>":(I)V
         9: aload_0
        10: invokevirtual #111                // Method eventName:()Ljava/lang/String;
        13: invokevirtual #115                // Method java/lang/StringBuilder.append:(Ljava/lang/String;)Ljava/lang/StringBuilder;
        16: ldc           #117                // String
        18: invokevirtual #115                // Method java/lang/StringBuilder.append:(Ljava/lang/String;)Ljava/lang/StringBuilder;
        21: aload_0
        22: invokevirtual #119                // Method className:()Lscala/Option;
        25: invokevirtual #122                // Method java/lang/StringBuilder.append:(Ljava/lang/Object;)Ljava/lang/StringBuilder;
        28: ldc           #117                // String
        30: invokevirtual #115                // Method java/lang/StringBuilder.append:(Ljava/lang/String;)Ljava/lang/StringBuilder;
        33: getstatic     #34                 // Field org/scalatest/tools/Memento$.MODULE$:Lorg/scalatest/tools/Memento$;
        36: aload_0
        37: invokevirtual #124                // Method suiteId:()Ljava/lang/String;
        40: invokevirtual #50                 // Method org/scalatest/tools/Memento$.encode:(Ljava/lang/String;)Ljava/lang/String;
        43: invokevirtual #115                // Method java/lang/StringBuilder.append:(Ljava/lang/String;)Ljava/lang/StringBuilder;
        46: ldc           #117                // String
        48: invokevirtual #115                // Method java/lang/StringBuilder.append:(Ljava/lang/String;)Ljava/lang/StringBuilder;
        51: getstatic     #34                 // Field org/scalatest/tools/Memento$.MODULE$:Lorg/scalatest/tools/Memento$;
        54: aload_0
        55: invokevirtual #126                // Method testName:()Lscala/Option;
        58: invokevirtual #131                // Method scala/Option.toString:()Ljava/lang/String;
        61: invokevirtual #50                 // Method org/scalatest/tools/Memento$.encode:(Ljava/lang/String;)Ljava/lang/String;
        64: invokevirtual #115                // Method java/lang/StringBuilder.append:(Ljava/lang/String;)Ljava/lang/StringBuilder;
        67: invokevirtual #132                // Method java/lang/StringBuilder.toString:()Ljava/lang/String;
        70: areturn
      LineNumberTable:
        line 51: 0
        line 49: 9
        line 50: 21
        line 51: 33
        line 52: 51
      LocalVariableTable:
        Start  Length  Slot  Name   Signature
            0      71     0  this   Lorg/scalatest/tools/Memento;

  public org.scalatest.tools.SuiteParam toSuiteParam();
    descriptor: ()Lorg/scalatest/tools/SuiteParam;
    flags: (0x0001) ACC_PUBLIC
    Code:
      stack=8, locals=16, args_size=1
         0: aload_0
         1: invokevirtual #126                // Method testName:()Lscala/Option;
         4: astore        4
         6: aload         4
         8: instanceof    #136                // class scala/Some
        11: ifeq          50
        14: aload         4
        16: checkcast     #136                // class scala/Some
        19: astore        5
        21: aload         5
        23: invokevirtual #140                // Method scala/Some.value:()Ljava/lang/Object;
        26: checkcast     #142                // class java/lang/String
        29: astore        6
        31: iconst_1
        32: anewarray     #142                // class java/lang/String
        35: dup
        36: iconst_0
        37: aload         6
        39: aastore
        40: checkcast     #144                // class "[Ljava/lang/Object;"
        43: checkcast     #146                // class "[Ljava/lang/String;"
        46: astore_2
        47: goto          98
        50: goto          53
        53: getstatic     #151                // Field scala/None$.MODULE$:Lscala/None$;
        56: aload         4
        58: invokevirtual #155                // Method java/lang/Object.equals:(Ljava/lang/Object;)Z
        61: ifeq          85
        64: getstatic     #160                // Field scala/Array$.MODULE$:Lscala/Array$;
        67: getstatic     #165                // Field scala/reflect/ClassTag$.MODULE$:Lscala/reflect/ClassTag$;
        70: ldc           #142                // class java/lang/String
        72: invokevirtual #168                // Method scala/reflect/ClassTag$.apply:(Ljava/lang/Class;)Lscala/reflect/ClassTag;
        75: invokevirtual #172                // Method scala/Array$.empty:(Lscala/reflect/ClassTag;)Ljava/lang/Object;
        78: checkcast     #146                // class "[Ljava/lang/String;"
        81: astore_2
        82: goto          98
        85: goto          88
        88: new           #174                // class scala/MatchError
        91: dup
        92: aload         4
        94: invokespecial #177                // Method scala/MatchError."<init>":(Ljava/lang/Object;)V
        97: athrow
        98: aload_2
        99: astore_3
       100: aload_0
       101: invokevirtual #119                // Method className:()Lscala/Option;
       104: invokedynamic #195,  0            // InvokeDynamic #0:apply:()Lscala/Function0;
       109: invokevirtual #199                // Method scala/Option.getOrElse:(Lscala/Function0;)Ljava/lang/Object;
       112: checkcast     #142                // class java/lang/String
       115: astore        7
       117: aload_0
       118: invokevirtual #124                // Method suiteId:()Ljava/lang/String;
       121: aload         7
       123: astore        10
       125: dup
       126: ifnonnull     138
       129: pop
       130: aload         10
       132: ifnull        146
       135: goto          171
       138: aload         10
       140: invokevirtual #155                // Method java/lang/Object.equals:(Ljava/lang/Object;)Z
       143: ifeq          171
       146: new           #201                // class scala/Tuple2
       149: dup
       150: aload_3
       151: getstatic     #160                // Field scala/Array$.MODULE$:Lscala/Array$;
       154: getstatic     #165                // Field scala/reflect/ClassTag$.MODULE$:Lscala/reflect/ClassTag$;
       157: ldc           #203                // class org/scalatest/tools/NestedSuiteParam
       159: invokevirtual #168                // Method scala/reflect/ClassTag$.apply:(Ljava/lang/Class;)Lscala/reflect/ClassTag;
       162: invokevirtual #172                // Method scala/Array$.empty:(Lscala/reflect/ClassTag;)Ljava/lang/Object;
       165: invokespecial #206                // Method scala/Tuple2."<init>":(Ljava/lang/Object;Ljava/lang/Object;)V
       168: goto          238
       171: new           #203                // class org/scalatest/tools/NestedSuiteParam
       174: dup
       175: aload_0
       176: invokevirtual #124                // Method suiteId:()Ljava/lang/String;
       179: aload_3
       180: getstatic     #160                // Field scala/Array$.MODULE$:Lscala/Array$;
       183: getstatic     #211                // Field scala/collection/immutable/Nil$.MODULE$:Lscala/collection/immutable/Nil$;
       186: getstatic     #165                // Field scala/reflect/ClassTag$.MODULE$:Lscala/reflect/ClassTag$;
       189: ldc           #142                // class java/lang/String
       191: invokevirtual #168                // Method scala/reflect/ClassTag$.apply:(Ljava/lang/Class;)Lscala/reflect/ClassTag;
       194: invokevirtual #214                // Method scala/Array$.apply:(Lscala/collection/immutable/Seq;Lscala/reflect/ClassTag;)Ljava/lang/Object;
       197: checkcast     #146                // class "[Ljava/lang/String;"
       200: invokespecial #217                // Method org/scalatest/tools/NestedSuiteParam."<init>":(Ljava/lang/String;[Ljava/lang/String;[Ljava/lang/String;)V
       203: astore        11
       205: new           #201                // class scala/Tuple2
       208: dup
       209: getstatic     #160                // Field scala/Array$.MODULE$:Lscala/Array$;
       212: getstatic     #165                // Field scala/reflect/ClassTag$.MODULE$:Lscala/reflect/ClassTag$;
       215: ldc           #142                // class java/lang/String
       217: invokevirtual #168                // Method scala/reflect/ClassTag$.apply:(Ljava/lang/Class;)Lscala/reflect/ClassTag;
       220: invokevirtual #172                // Method scala/Array$.empty:(Lscala/reflect/ClassTag;)Ljava/lang/Object;
       223: iconst_1
       224: anewarray     #203                // class org/scalatest/tools/NestedSuiteParam
       227: dup
       228: iconst_0
       229: aload         11
       231: aastore
       232: checkcast     #144                // class "[Ljava/lang/Object;"
       235: invokespecial #206                // Method scala/Tuple2."<init>":(Ljava/lang/Object;Ljava/lang/Object;)V
       238: astore        9
       240: aload         9
       242: ifnull        280
       245: aload         9
       247: invokevirtual #220                // Method scala/Tuple2._1:()Ljava/lang/Object;
       250: checkcast     #146                // class "[Ljava/lang/String;"
       253: astore        12
       255: aload         9
       257: invokevirtual #223                // Method scala/Tuple2._2:()Ljava/lang/Object;
       260: checkcast     #225                // class "[Lorg/scalatest/tools/NestedSuiteParam;"
       263: astore        13
       265: new           #201                // class scala/Tuple2
       268: dup
       269: aload         12
       271: aload         13
       273: invokespecial #206                // Method scala/Tuple2."<init>":(Ljava/lang/Object;Ljava/lang/Object;)V
       276: astore_1
       277: goto          293
       280: goto          283
       283: new           #174                // class scala/MatchError
       286: dup
       287: aload         9
       289: invokespecial #177                // Method scala/MatchError."<init>":(Ljava/lang/Object;)V
       292: athrow
       293: aload_1
       294: astore        8
       296: aload         8
       298: invokevirtual #220                // Method scala/Tuple2._1:()Ljava/lang/Object;
       301: checkcast     #146                // class "[Ljava/lang/String;"
       304: astore        14
       306: aload         8
       308: invokevirtual #223                // Method scala/Tuple2._2:()Ljava/lang/Object;
       311: checkcast     #225                // class "[Lorg/scalatest/tools/NestedSuiteParam;"
       314: astore        15
       316: new           #227                // class org/scalatest/tools/SuiteParam
       319: dup
       320: aload         7
       322: aload         14
       324: getstatic     #160                // Field scala/Array$.MODULE$:Lscala/Array$;
       327: getstatic     #211                // Field scala/collection/immutable/Nil$.MODULE$:Lscala/collection/immutable/Nil$;
       330: getstatic     #165                // Field scala/reflect/ClassTag$.MODULE$:Lscala/reflect/ClassTag$;
       333: ldc           #142                // class java/lang/String
       335: invokevirtual #168                // Method scala/reflect/ClassTag$.apply:(Ljava/lang/Class;)Lscala/reflect/ClassTag;
       338: invokevirtual #214                // Method scala/Array$.apply:(Lscala/collection/immutable/Seq;Lscala/reflect/ClassTag;)Ljava/lang/Object;
       341: checkcast     #146                // class "[Ljava/lang/String;"
       344: aload         15
       346: invokespecial #230                // Method org/scalatest/tools/SuiteParam."<init>":(Ljava/lang/String;[Ljava/lang/String;[Ljava/lang/String;[Lorg/scalatest/tools/NestedSuiteParam;)V
       349: areturn
      StackMapTable: number_of_entries = 12
        frame_type = 255 /* full_frame */
          offset_delta = 50
          locals = [ class org/scalatest/tools/Memento, top, top, top, class scala/Option ]
          stack = []
        frame_type = 2 /* same */
        frame_type = 31 /* same */
        frame_type = 2 /* same */
        frame_type = 255 /* full_frame */
          offset_delta = 9
          locals = [ class org/scalatest/tools/Memento, top, class "[Ljava/lang/String;", top, class scala/Option ]
          stack = []
        frame_type = 255 /* full_frame */
          offset_delta = 39
          locals = [ class org/scalatest/tools/Memento, top, class "[Ljava/lang/String;", class "[Ljava/lang/String;", class scala/Option, top, top, class java/lang/String, top, top, class java/lang/String ]
          stack = [ class java/lang/String ]
        frame_type = 7 /* same */
        frame_type = 24 /* same */
        frame_type = 247 /* same_locals_1_stack_item_frame_extended */
          offset_delta = 66
          stack = [ class scala/Tuple2 ]
        frame_type = 255 /* full_frame */
          offset_delta = 41
          locals = [ class org/scalatest/tools/Memento, top, class "[Ljava/lang/String;", class "[Ljava/lang/String;", class scala/Option, top, top, class java/lang/String, top, class scala/Tuple2, class java/lang/String ]
          stack = []
        frame_type = 2 /* same */
        frame_type = 255 /* full_frame */
          offset_delta = 9
          locals = [ class org/scalatest/tools/Memento, class scala/Tuple2, class "[Ljava/lang/String;", class "[Ljava/lang/String;", class scala/Option, top, top, class java/lang/String, top, class scala/Tuple2, class java/lang/String, top, class "[Ljava/lang/String;", class "[Lorg/scalatest/tools/NestedSuiteParam;" ]
          stack = []
      LineNumberTable:
        line 64: 0
        line 65: 6
        line 66: 53
        line 64: 88
        line 69: 100
        line 72: 117
        line 73: 146
        line 76: 171
        line 78: 205
        line 71: 240
        line 72: 283
        line 71: 296
        line 81: 316
      LocalVariableTable:
        Start  Length  Slot  Name   Signature
           31      19     6  name   Ljava/lang/String;
          205      33    11 nestedSuiteParam   Lorg/scalatest/tools/NestedSuiteParam;
          255      25    12 testNames   [Ljava/lang/String;
          265      15    13 nestedSuites   [Lorg/scalatest/tools/NestedSuiteParam;
          100     249     3 testNamesArray   [Ljava/lang/String;
          117     232     7 classNameStr   Ljava/lang/String;
          306      43    14 testNames   [Ljava/lang/String;
          316      33    15 nestedSuites   [Lorg/scalatest/tools/NestedSuiteParam;
            0     350     0  this   Lorg/scalatest/tools/Memento;

  public org.scalatest.tools.Memento copy(java.lang.String, scala.Option<java.lang.String>, java.lang.String, scala.Option<java.lang.String>);
    descriptor: (Ljava/lang/String;Lscala/Option;Ljava/lang/String;Lscala/Option;)Lorg/scalatest/tools/Memento;
    flags: (0x0001) ACC_PUBLIC
    Code:
      stack=6, locals=5, args_size=5
         0: new           #2                  // class org/scalatest/tools/Memento
         3: dup
         4: aload_1
         5: aload_2
         6: aload_3
         7: aload         4
         9: invokespecial #241                // Method "<init>":(Ljava/lang/String;Lscala/Option;Ljava/lang/String;Lscala/Option;)V
        12: areturn
      LineNumberTable:
        line 34: 0
        line 35: 5
        line 36: 6
        line 37: 7
      LocalVariableTable:
        Start  Length  Slot  Name   Signature
            0      13     0  this   Lorg/scalatest/tools/Memento;
            0      13     1 eventName   Ljava/lang/String;
            0      13     2 className   Lscala/Option;
            0      13     3 suiteId   Ljava/lang/String;
            0      13     4 testName   Lscala/Option;
    Signature: #40                          // (Ljava/lang/String;Lscala/Option<Ljava/lang/String;>;Ljava/lang/String;Lscala/Option<Ljava/lang/String;>;)Lorg/scalatest/tools/Memento;
    MethodParameters:
      Name                           Flags
      eventName                      final
      className                      final
      suiteId                        final
      testName                       final

  public java.lang.String copy$default$1();
    descriptor: ()Ljava/lang/String;
    flags: (0x0001) ACC_PUBLIC
    Code:
      stack=1, locals=1, args_size=1
         0: aload_0
         1: invokevirtual #111                // Method eventName:()Ljava/lang/String;
         4: areturn
      LineNumberTable:
        line 34: 0
      LocalVariableTable:
        Start  Length  Slot  Name   Signature
            0       5     0  this   Lorg/scalatest/tools/Memento;

  public scala.Option<java.lang.String> copy$default$2();
    descriptor: ()Lscala/Option;
    flags: (0x0001) ACC_PUBLIC
    Code:
      stack=1, locals=1, args_size=1
         0: aload_0
         1: invokevirtual #119                // Method className:()Lscala/Option;
         4: areturn
      LineNumberTable:
        line 35: 0
      LocalVariableTable:
        Start  Length  Slot  Name   Signature
            0       5     0  this   Lorg/scalatest/tools/Memento;
    Signature: #95                          // ()Lscala/Option<Ljava/lang/String;>;

  public java.lang.String copy$default$3();
    descriptor: ()Ljava/lang/String;
    flags: (0x0001) ACC_PUBLIC
    Code:
      stack=1, locals=1, args_size=1
         0: aload_0
         1: invokevirtual #124                // Method suiteId:()Ljava/lang/String;
         4: areturn
      LineNumberTable:
        line 36: 0
      LocalVariableTable:
        Start  Length  Slot  Name   Signature
            0       5     0  this   Lorg/scalatest/tools/Memento;

  public scala.Option<java.lang.String> copy$default$4();
    descriptor: ()Lscala/Option;
    flags: (0x0001) ACC_PUBLIC
    Code:
      stack=1, locals=1, args_size=1
         0: aload_0
         1: invokevirtual #126                // Method testName:()Lscala/Option;
         4: areturn
      LineNumberTable:
        line 37: 0
      LocalVariableTable:
        Start  Length  Slot  Name   Signature
            0       5     0  this   Lorg/scalatest/tools/Memento;
    Signature: #95                          // ()Lscala/Option<Ljava/lang/String;>;

  public java.lang.String productPrefix();
    descriptor: ()Ljava/lang/String;
    flags: (0x0001) ACC_PUBLIC
    Code:
      stack=1, locals=1, args_size=1
         0: ldc           #248                // String Memento
         2: areturn
      LineNumberTable:
        line 34: 0
      LocalVariableTable:
        Start  Length  Slot  Name   Signature
            0       3     0  this   Lorg/scalatest/tools/Memento;

  public int productArity();
    descriptor: ()I
    flags: (0x0001) ACC_PUBLIC
    Code:
      stack=1, locals=1, args_size=1
         0: iconst_4
         1: ireturn
      LineNumberTable:
        line 34: 0
      LocalVariableTable:
        Start  Length  Slot  Name   Signature
            0       2     0  this   Lorg/scalatest/tools/Memento;

  public java.lang.Object productElement(int);
    descriptor: (I)Ljava/lang/Object;
    flags: (0x0001) ACC_PUBLIC
    Code:
      stack=1, locals=3, args_size=2
         0: iload_1
         1: istore_2
         2: iload_2
         3: tableswitch   { // 0 to 3
                       0: 32
                       1: 39
                       2: 46
                       3: 53
                 default: 60
            }
        32: aload_0
        33: invokevirtual #111                // Method eventName:()Ljava/lang/String;
        36: goto          67
        39: aload_0
        40: invokevirtual #119                // Method className:()Lscala/Option;
        43: goto          67
        46: aload_0
        47: invokevirtual #124                // Method suiteId:()Ljava/lang/String;
        50: goto          67
        53: aload_0
        54: invokevirtual #126                // Method testName:()Lscala/Option;
        57: goto          67
        60: iload_1
        61: invokestatic  #258                // Method scala/runtime/Statics.ioobe:(I)Ljava/lang/Object;
        64: goto          67
        67: areturn
      StackMapTable: number_of_entries = 6
        frame_type = 252 /* append */
          offset_delta = 32
          locals = [ int ]
        frame_type = 6 /* same */
        frame_type = 6 /* same */
        frame_type = 6 /* same */
        frame_type = 6 /* same */
        frame_type = 70 /* same_locals_1_stack_item */
          stack = [ class java/lang/Object ]
      LineNumberTable:
        line 34: 0
      LocalVariableTable:
        Start  Length  Slot  Name   Signature
            0      68     0  this   Lorg/scalatest/tools/Memento;
            0      68     1   x$1   I
    MethodParameters:
      Name                           Flags
      x$1                            final

  public scala.collection.Iterator<java.lang.Object> productIterator();
    descriptor: ()Lscala/collection/Iterator;
    flags: (0x0001) ACC_PUBLIC
    Code:
      stack=2, locals=1, args_size=1
         0: getstatic     #266                // Field scala/runtime/ScalaRunTime$.MODULE$:Lscala/runtime/ScalaRunTime$;
         3: aload_0
         4: invokevirtual #269                // Method scala/runtime/ScalaRunTime$.typedProductIterator:(Lscala/Product;)Lscala/collection/Iterator;
         7: areturn
      LineNumberTable:
        line 34: 0
      LocalVariableTable:
        Start  Length  Slot  Name   Signature
            0       8     0  this   Lorg/scalatest/tools/Memento;
    Signature: #261                         // ()Lscala/collection/Iterator<Ljava/lang/Object;>;

  public boolean canEqual(java.lang.Object);
    descriptor: (Ljava/lang/Object;)Z
    flags: (0x0001) ACC_PUBLIC
    Code:
      stack=1, locals=2, args_size=2
         0: aload_1
         1: instanceof    #2                  // class org/scalatest/tools/Memento
         4: ireturn
      LineNumberTable:
        line 34: 0
      LocalVariableTable:
        Start  Length  Slot  Name   Signature
            0       5     0  this   Lorg/scalatest/tools/Memento;
            0       5     1   x$1   Ljava/lang/Object;
    MethodParameters:
      Name                           Flags
      x$1                            final

  public java.lang.String productElementName(int);
    descriptor: (I)Ljava/lang/String;
    flags: (0x0001) ACC_PUBLIC
    Code:
      stack=1, locals=3, args_size=2
         0: iload_1
         1: istore_2
         2: iload_2
         3: tableswitch   { // 0 to 3
                       0: 32
                       1: 38
                       2: 44
                       3: 50
                 default: 56
            }
        32: ldc_w         #274                // String eventName
        35: goto          66
        38: ldc_w         #275                // String className
        41: goto          66
        44: ldc_w         #276                // String suiteId
        47: goto          66
        50: ldc_w         #277                // String testName
        53: goto          66
        56: iload_1
        57: invokestatic  #258                // Method scala/runtime/Statics.ioobe:(I)Ljava/lang/Object;
        60: checkcast     #142                // class java/lang/String
        63: goto          66
        66: areturn
      StackMapTable: number_of_entries = 6
        frame_type = 252 /* append */
          offset_delta = 32
          locals = [ int ]
        frame_type = 5 /* same */
        frame_type = 5 /* same */
        frame_type = 5 /* same */
        frame_type = 5 /* same */
        frame_type = 73 /* same_locals_1_stack_item */
          stack = [ class java/lang/String ]
      LineNumberTable:
        line 34: 0
      LocalVariableTable:
        Start  Length  Slot  Name   Signature
            0      67     0  this   Lorg/scalatest/tools/Memento;
            0      67     1   x$1   I
    MethodParameters:
      Name                           Flags
      x$1                            final

  public int hashCode();
    descriptor: ()I
    flags: (0x0001) ACC_PUBLIC
    Code:
      stack=2, locals=1, args_size=1
         0: getstatic     #266                // Field scala/runtime/ScalaRunTime$.MODULE$:Lscala/runtime/ScalaRunTime$;
         3: aload_0
         4: invokevirtual #282                // Method scala/runtime/ScalaRunTime$._hashCode:(Lscala/Product;)I
         7: ireturn
      LineNumberTable:
        line 34: 0
      LocalVariableTable:
        Start  Length  Slot  Name   Signature
            0       8     0  this   Lorg/scalatest/tools/Memento;

  public java.lang.String toString();
    descriptor: ()Ljava/lang/String;
    flags: (0x0001) ACC_PUBLIC
    Code:
      stack=2, locals=1, args_size=1
         0: getstatic     #266                // Field scala/runtime/ScalaRunTime$.MODULE$:Lscala/runtime/ScalaRunTime$;
         3: aload_0
         4: invokevirtual #286                // Method scala/runtime/ScalaRunTime$._toString:(Lscala/Product;)Ljava/lang/String;
         7: areturn
      LineNumberTable:
        line 34: 0
      LocalVariableTable:
        Start  Length  Slot  Name   Signature
            0       8     0  this   Lorg/scalatest/tools/Memento;

  public boolean equals(java.lang.Object);
    descriptor: (Ljava/lang/Object;)Z
    flags: (0x0001) ACC_PUBLIC
    Code:
      stack=2, locals=9, args_size=2
         0: aload_0
         1: aload_1
         2: if_acmpeq     182
         5: aload_1
         6: astore_3
         7: aload_3
         8: instanceof    #2                  // class org/scalatest/tools/Memento
        11: ifeq          19
        14: iconst_1
        15: istore_2
        16: goto          27
        19: goto          22
        22: iconst_0
        23: istore_2
        24: goto          27
        27: iload_2
        28: ifeq          186
        31: aload_1
        32: checkcast     #2                  // class org/scalatest/tools/Memento
        35: astore        4
        37: aload_0
        38: invokevirtual #111                // Method eventName:()Ljava/lang/String;
        41: aload         4
        43: invokevirtual #111                // Method eventName:()Ljava/lang/String;
        46: astore        5
        48: dup
        49: ifnonnull     61
        52: pop
        53: aload         5
        55: ifnull        69
        58: goto          178
        61: aload         5
        63: invokevirtual #155                // Method java/lang/Object.equals:(Ljava/lang/Object;)Z
        66: ifeq          178
        69: aload_0
        70: invokevirtual #119                // Method className:()Lscala/Option;
        73: aload         4
        75: invokevirtual #119                // Method className:()Lscala/Option;
        78: astore        6
        80: dup
        81: ifnonnull     93
        84: pop
        85: aload         6
        87: ifnull        101
        90: goto          178
        93: aload         6
        95: invokevirtual #155                // Method java/lang/Object.equals:(Ljava/lang/Object;)Z
        98: ifeq          178
       101: aload_0
       102: invokevirtual #124                // Method suiteId:()Ljava/lang/String;
       105: aload         4
       107: invokevirtual #124                // Method suiteId:()Ljava/lang/String;
       110: astore        7
       112: dup
       113: ifnonnull     125
       116: pop
       117: aload         7
       119: ifnull        133
       122: goto          178
       125: aload         7
       127: invokevirtual #155                // Method java/lang/Object.equals:(Ljava/lang/Object;)Z
       130: ifeq          178
       133: aload_0
       134: invokevirtual #126                // Method testName:()Lscala/Option;
       137: aload         4
       139: invokevirtual #126                // Method testName:()Lscala/Option;
       142: astore        8
       144: dup
       145: ifnonnull     157
       148: pop
       149: aload         8
       151: ifnull        165
       154: goto          178
       157: aload         8
       159: invokevirtual #155                // Method java/lang/Object.equals:(Ljava/lang/Object;)Z
       162: ifeq          178
       165: aload         4
       167: aload_0
       168: invokevirtual #288                // Method canEqual:(Ljava/lang/Object;)Z
       171: ifeq          178
       174: iconst_1
       175: goto          179
       178: iconst_0
       179: ifeq          186
       182: iconst_1
       183: goto          187
       186: iconst_0
       187: ireturn
      StackMapTable: number_of_entries = 16
        frame_type = 253 /* append */
          offset_delta = 19
          locals = [ top, class java/lang/Object ]
        frame_type = 2 /* same */
        frame_type = 255 /* full_frame */
          offset_delta = 4
          locals = [ class org/scalatest/tools/Memento, class java/lang/Object, int, class java/lang/Object ]
          stack = []
        frame_type = 255 /* full_frame */
          offset_delta = 33
          locals = [ class org/scalatest/tools/Memento, class java/lang/Object, int, class java/lang/Object, class org/scalatest/tools/Memento, class java/lang/String ]
          stack = [ class java/lang/String ]
        frame_type = 7 /* same */
        frame_type = 255 /* full_frame */
          offset_delta = 23
          locals = [ class org/scalatest/tools/Memento, class java/lang/Object, int, class java/lang/Object, class org/scalatest/tools/Memento, class java/lang/String, class scala/Option ]
          stack = [ class scala/Option ]
        frame_type = 7 /* same */
        frame_type = 255 /* full_frame */
          offset_delta = 23
          locals = [ class org/scalatest/tools/Memento, class java/lang/Object, int, class java/lang/Object, class org/scalatest/tools/Memento, class java/lang/String, class scala/Option, class java/lang/String ]
          stack = [ class java/lang/String ]
        frame_type = 7 /* same */
        frame_type = 255 /* full_frame */
          offset_delta = 23
          locals = [ class org/scalatest/tools/Memento, class java/lang/Object, int, class java/lang/Object, class org/scalatest/tools/Memento, class java/lang/String, class scala/Option, class java/lang/String, class scala/Option ]
          stack = [ class scala/Option ]
        frame_type = 7 /* same */
        frame_type = 248 /* chop */
          offset_delta = 12
        frame_type = 64 /* same_locals_1_stack_item */
          stack = [ int ]
        frame_type = 255 /* full_frame */
          offset_delta = 2
          locals = [ class org/scalatest/tools/Memento, class java/lang/Object ]
          stack = []
        frame_type = 253 /* append */
          offset_delta = 3
          locals = [ int, class java/lang/Object ]
        frame_type = 255 /* full_frame */
          offset_delta = 0
          locals = [ class org/scalatest/tools/Memento, class java/lang/Object ]
          stack = [ int ]
      LineNumberTable:
        line 34: 0
      LocalVariableTable:
        Start  Length  Slot  Name   Signature
            0     188     0  this   Lorg/scalatest/tools/Memento;
            0     188     1   x$1   Ljava/lang/Object;
    MethodParameters:
      Name                           Flags
      x$1                            final

  public static final java.lang.String $anonfun$toSuiteParam$1();
    descriptor: ()Ljava/lang/String;
    flags: (0x1019) ACC_PUBLIC, ACC_STATIC, ACC_FINAL, ACC_SYNTHETIC
    Code:
      stack=1, locals=0, args_size=0
         0: ldc_w         #290                // String unknown
         3: areturn
      LineNumberTable:
        line 69: 0

  public org.scalatest.tools.Memento(java.lang.String, scala.Option<java.lang.String>, java.lang.String, scala.Option<java.lang.String>);
    descriptor: (Ljava/lang/String;Lscala/Option;Ljava/lang/String;Lscala/Option;)V
    flags: (0x0001) ACC_PUBLIC
    Code:
      stack=2, locals=5, args_size=5
         0: aload_0
         1: aload_1
         2: putfield      #93                 // Field eventName:Ljava/lang/String;
         5: aload_0
         6: aload_2
         7: putfield      #97                 // Field className:Lscala/Option;
        10: aload_0
        11: aload_3
        12: putfield      #99                 // Field suiteId:Ljava/lang/String;
        15: aload_0
        16: aload         4
        18: putfield      #101                // Field testName:Lscala/Option;
        21: aload_0
        22: invokespecial #294                // Method java/lang/Object."<init>":()V
        25: aload_0
        26: invokestatic  #298                // InterfaceMethod scala/Product.$init$:(Lscala/Product;)V
        29: return
      LineNumberTable:
        line 34: 0
        line 35: 5
        line 36: 10
        line 37: 15
        line 34: 21
      LocalVariableTable:
        Start  Length  Slot  Name   Signature
            0      30     0  this   Lorg/scalatest/tools/Memento;
            0      30     1 eventName   Ljava/lang/String;
            0      30     2 className   Lscala/Option;
            0      30     3 suiteId   Ljava/lang/String;
            0      30     4 testName   Lscala/Option;
    Signature: #291                         // (Ljava/lang/String;Lscala/Option<Ljava/lang/String;>;Ljava/lang/String;Lscala/Option<Ljava/lang/String;>;)V
    MethodParameters:
      Name                           Flags
      eventName                      final
      className                      final
      suiteId                        final
      testName                       final

  private static java.lang.Object $deserializeLambda$(java.lang.invoke.SerializedLambda);
    descriptor: (Ljava/lang/invoke/SerializedLambda;)Ljava/lang/Object;
    flags: (0x100a) ACC_PRIVATE, ACC_STATIC, ACC_SYNTHETIC
    Code:
      stack=1, locals=1, args_size=1
         0: aload_0
         1: invokedynamic #310,  0            // InvokeDynamic #1:lambdaDeserialize:(Ljava/lang/invoke/SerializedLambda;)Ljava/lang/Object;
         6: areturn
}
InnerClasses:
  public static final #17= #14 of #16;    // Lookup=class java/lang/invoke/MethodHandles$Lookup of class java/lang/invoke/MethodHandles
SourceFile: "Memento.scala"
RuntimeVisibleAnnotations:
  0: #10(#11=s#12)
    scala.reflect.ScalaSignature(
      bytes="\u0006\u0005\u0005uh!B\u0015+\u0001*\u0002\u0004\u0002C$\u0001\u0005+\u0007I\u0011\u0001%\t\u0011E\u0003!\u0011#Q\u0001\n%C\u0001B\u0015\u0001\u0003\u0016\u0004%\ta\u0015\u0005\t/\u0002\u0011\t\u0012)A\u0005)\"A\u0001\f\u0001BK\u0002\u0013\u0005\u0001\n\u0003\u0005Z\u0001\tE\t\u0015!\u0003J\u0011!Q\u0006A!f\u0001\n\u0003\u0019\u0006\u0002C.\u0001\u0005#\u0005\u000b\u0011\u0002+\t\u000bq\u0003A\u0011A/\t\u000b\u0011\u0004A\u0011\u0001%\t\u000b\u0015\u0004A\u0011\u00014\t\u000f)\u0004\u0011\u0011!C\u0001W\"9\u0001\u000fAI\u0001\n\u0003\t\bb\u0002?\u0001#\u0003%\t! \u0005\b\u007f\u0002\t\n\u0011\"\u0001r\u0011!\t\t\u0001AI\u0001\n\u0003i\b\"CA\u0002\u0001\u0005\u0005I\u0011IA\u0003\u0011%\t)\u0002AA\u0001\n\u0003\t9\u0002C\u0005\u0002 \u0001\t\t\u0011\"\u0001\u0002\"!I\u0011Q\u0006\u0001\u0002\u0002\u0013\u0005\u0013q\u0006\u0005\n\u0003{\u0001\u0011\u0011!C\u0001\u0003\u007fA\u0011\"!\u0013\u0001\u0003\u0003%\t%a\u0013\t\u0013\u0005=\u0003!!A\u0005B\u0005E\u0003\"CA*\u0001\u0005\u0005I\u0011IA+\u0011%\t9\u0006AA\u0001\n\u0003\nIf\u0002\u0005\u0002^)B\tAKA0\r\u001dI#\u0006#\u0001+\u0003CBa\u0001X\u000e\u0005\u0002\u00055\u0004bBA87\u0011\u0005\u0011\u0011\u000f\u0005\b\u0003\u0007[B\u0011AAC\u0011\u001d\t\tj\u0007C\u0001\u0003\'Cq!a*\u001c\t\u0003\tI\u000bC\u0005\u00020n\u0011\r\u0011\"\u0001\u00022\"A\u00111Y\u000e!\u0002\u0013\t\u0019\fC\u0004\u0002Fn!\t!a2\t\u000f\u0005-7\u0004\"\u0001\u0002N\"9\u00111[\u000e\u0005\u0002\u0005U\u0007\"CA87\u0005\u0005I\u0011QAm\u0011%\t\u0019oGA\u0001\n\u0003\u000b)\u000fC\u0005\u0002tn\t\t\u0011\"\u0003\u0002v\n9Q*Z7f]R|\'BA\u0016-\u0003\u0015!xn\u001c7t\u0015\tic&A\u0005tG\u0006d\u0017\r^3ti*\tq&A\u0002pe\u001e\u001cB\u0001A\u00198uA\u0011!\'N\u0007\u0002g)\tA\'A\u0003tG\u0006d\u0017-\u0003\u00027g\t1\u0011I\\=SK\u001a\u0004\"A\r\u001d\n\u0005e\u001a$a\u0002)s_\u0012,8\r\u001e\t\u0003w\u0011s!\u0001\u0010\"\u000f\u0005u\nU\"\u0001 \u000b\u0005}\u0002\u0015A\u0002\u001fs_>$hh\u0001\u0001\n\u0003QJ!aQ\u001a\u0002\u000fA\f7m[1hK&\u0011QI\u0012\u0002\r\'\u0016\u0014\u0018.\u00197ju\u0006\u0014G.\u001a\u0006\u0003\u0007N\n\u0011\"\u001a<f]Rt\u0015-\\3\u0016\u0003%\u0003\"A\u0013(\u000f\u0005-c\u0005CA\u001f4\u0013\ti5\'\u0001\u0004Qe\u0016$WMZ\u0005\u0003\u001fB\u0013aa\u0015;sS:<\'BA\'4\u0003))g/\u001a8u\u001d\u0006lW\rI\u0001\nG2\f7o\u001d(b[\u0016,\u0012\u0001\u0016\t\u0004eUK\u0015B\u0001,4\u0005\u0019y\u0005\u000f^5p]\u0006Q1\r\\1tg:\u000bW.\u001a\u0011\u0002\u000fM,\u0018\u000e^3JI\u0006A1/^5uK&#\u0007%\u0001\u0005uKN$h*Y7f\u0003%!Xm\u001d;OC6,\u0007%\u0001\u0004=S:LGO\u0010\u000b\u0006=\u0002\f\'m\u0019\t\u0003?\u0002i\u0011A\u000b\u0005\u0006\u000f&\u0001\r!\u0013\u0005\u0006%&\u0001\r\u0001\u0016\u0005\u00061&\u0001\r!\u0013\u0005\u00065&\u0001\r\u0001V\u0001\u000bg&tw\r\\3MS:,\u0017\u0001\u0004;p\'VLG/\u001a)be\u0006lW#A4\u0011\u0005}C\u0017BA5+\u0005)\u0019V/\u001b;f!\u0006\u0014\u0018-\\\u0001\u0005G>\u0004\u0018\u0010F\u0003_Y6tw\u000eC\u0004H\u0019A\u0005\t\u0019A%\t\u000fIc\u0001\u0013!a\u0001)\"9\u0001\f\u0004I\u0001\u0002\u0004I\u0005b\u0002.\r!\u0003\u0005\r\u0001V\u0001\u000fG>\u0004\u0018\u0010\n3fM\u0006,H\u000e\u001e\u00132+\u0005\u0011(FA%tW\u0005!\bCA;{\u001b\u00051(BA<y\u0003%)hn\u00195fG.,GM\u0003\u0002zg\u0005Q\u0011M\u001c8pi\u0006$\u0018n\u001c8\n\u0005m4(!E;oG\",7m[3e-\u0006\u0014\u0018.\u00198dK\u0006q1m\u001c9zI\u0011,g-Y;mi\u0012\u0012T#\u0001@+\u0005Q\u001b\u0018AD2paf$C-\u001a4bk2$HeM\u0001\u000fG>\u0004\u0018\u0010\n3fM\u0006,H\u000e\u001e\u00135\u00035\u0001(o\u001c3vGR\u0004&/\u001a4jqV\u0011\u0011q\u0001\t\u0005\u0003\u0013\t\u0019\"\u0004\u0002\u0002\f)!\u0011QBA\b\u0003\u0011a\u0017M\\4\u000b\u0005\u0005E\u0011\u0001\u00026bm\u0006L1aTA\u0006\u00031\u0001(o\u001c3vGR\f%/\u001b;z+\t\tI\u0002E\u00023\u00037I1!!\b4\u0005\rIe\u000e^\u0001\u000faJ|G-^2u\u000b2,W.\u001a8u)\u0011\t\u0019#!\u000b\u0011\u0007I\n)#C\u0002\u0002(M\u00121!\u00118z\u0011%\tYcEA\u0001\u0002\u0004\tI\"A\u0002yIE\nq\u0002\u001d:pIV\u001cG/\u0013;fe\u0006$xN]\u000b\u0003\u0003c\u0001b!a\r\u0002:\u0005\rRBAA\u001b\u0015\r\t9dM\u0001\u000bG>dG.Z2uS>t\u0017\u0002BA\u001e\u0003k\u0011\u0001\"\u0013;fe\u0006$xN]\u0001\tG\u0006tW)];bYR!\u0011\u0011IA$!\r\u0011\u00141I\u0005\u0004\u0003\u000b\u001a$a\u0002\"p_2,\u0017M\u001c\u0005\n\u0003W)\u0012\u0011!a\u0001\u0003G\t!\u0003\u001d:pIV\u001cG/\u00127f[\u0016tGOT1nKR!\u0011qAA\'\u0011%\tYCFA\u0001\u0002\u0004\tI\"\u0001\u0005iCND7i\u001c3f)\t\tI\"\u0001\u0005u_N#(/\u001b8h)\t\t9!\u0001\u0004fcV\fGn\u001d\u000b\u0005\u0003\u0003\nY\u0006C\u0005\u0002,e\t\t\u00111\u0001\u0002$\u00059Q*Z7f]R|\u0007CA0\u001c\'\u0011Y\u0012\'a\u0019\u0011\t\u0005\u0015\u00141N\u0007\u0003\u0003ORA!!\u001b\u0002\u0010\u0005\u0011\u0011n\\\u0005\u0004\u000b\u0006\u001dDCAA0\u0003\u0015\t\u0007\u000f\u001d7z)\rq\u00161\u000f\u0005\b\u0003kj\u0002\u0019AA<\u0003\u0015)g/\u001a8u!\u0011\tI(a \u000e\u0005\u0005m$bAA?Y\u00051QM^3oiNLA!!!\u0002|\t)QI^3oi\u0006a!/Z1e\rJ|WNR5mKR!\u0011qQAG!\u0011Y\u0014\u0011\u00120\n\u0007\u0005-eI\u0001\u0003MSN$\bBBAH=\u0001\u0007\u0011*\u0001\u0005gS2,g*Y7f\u0003-9(/\u001b;f)>4\u0015\u000e\\3\u0015\r\u0005U\u00151TAO!\r\u0011\u0014qS\u0005\u0004\u00033\u001b$\u0001B+oSRDa!a$ \u0001\u0004I\u0005bBAP?\u0001\u0007\u0011\u0011U\u0001\t[\u0016lWM\u001c;pgB!!*a)_\u0013\r\t)\u000b\u0015\u0002\u0004\'\u0016$\u0018A\u00034s_6\u001cFO]5oOR\u0019a,a+\t\r\u00055\u0006\u00051\u0001J\u0003\r\u0019HO]\u0001\f\'>lWMT8oKB\u000bG/\u0006\u0002\u00024B!\u0011QWA`\u001b\t\t9L\u0003\u0003\u0002:\u0006m\u0016!\u0002:fO\u0016D(\u0002BA_\u0003\u001f\tA!\u001e;jY&!\u0011\u0011YA\\\u0005\u001d\u0001\u0016\r\u001e;fe:\fAbU8nK:{g.\u001a)bi\u0002\n\u0001c\u001c9uS>tgI]8n\'R\u0014\u0018N\\4\u0015\u0007Q\u000bI\r\u0003\u0004\u0002.\u000e\u0002\r!S\u0001\u0007K:\u001cw\u000eZ3\u0015\u0007%\u000by\r\u0003\u0004\u0002R\u0012\u0002\r!S\u0001\u0005i\u0016DH/\u0001\u0004eK\u000e|G-\u001a\u000b\u0004\u0013\u0006]\u0007BBAiK\u0001\u0007\u0011\nF\u0005_\u00037\fi.a8\u0002b\")qI\na\u0001\u0013\")!K\na\u0001)\")\u0001L\na\u0001\u0013\")!L\na\u0001)\u00069QO\\1qa2LH\u0003BAt\u0003_\u0004BAM+\u0002jB9!\'a;J)&#\u0016bAAwg\t1A+\u001e9mKRB\u0001\"!=(\u0003\u0003\u0005\rAX\u0001\u0004q\u0012\u0002\u0014\u0001D<sSR,\'+\u001a9mC\u000e,GCAA|!\u0011\tI!!?\n\t\u0005m\u00181\u0002\u0002\u0007\u001f\nTWm\u0019;"
    )
BootstrapMethods:
  0: #192 REF_invokeStatic java/lang/invoke/LambdaMetafactory.altMetafactory:(Ljava/lang/invoke/MethodHandles$Lookup;Ljava/lang/String;Ljava/lang/invoke/MethodType;[Ljava/lang/Object;)Ljava/lang/invoke/CallSite;
    Method arguments:
      #178 ()Ljava/lang/Object;
      #182 REF_invokeStatic org/scalatest/tools/Memento.$anonfun$toSuiteParam$1:()Ljava/lang/String;
      #183 ()Ljava/lang/String;
      #184 5
      #185 1
      #183 ()Ljava/lang/String;
  1: #307 REF_invokeStatic scala/runtime/LambdaDeserialize.bootstrap:(Ljava/lang/invoke/MethodHandles$Lookup;Ljava/lang/String;Ljava/lang/invoke/MethodType;[Ljava/lang/invoke/MethodHandle;)Ljava/lang/invoke/CallSite;
    Method arguments:
      #182 REF_invokeStatic org/scalatest/tools/Memento.$anonfun$toSuiteParam$1:()Ljava/lang/String;
  ScalaInlineInfo: length = 0x77 (unknown attribute)
   01 00 00 17 00 B3 00 5B 01 00 6A 00 EF 00 01 0E
   00 99 00 00 14 00 5E 00 00 EE 00 27 00 00 F2 00
   5B 00 00 F3 00 5E 00 00 F4 00 5B 00 00 F5 00 5E
   00 00 98 00 99 00 00 12 00 5B 00 01 16 00 FA 00
   00 F9 00 FA 00 00 FB 00 FC 00 01 10 01 11 00 00
   53 00 54 00 01 04 00 54 00 00 F6 00 5B 00 00 66
   00 5B 00 00 17 00 5B 00 00 18 00 5E 00 00 81 00
   5B 00 00 85 00 86 00
  ScalaSig: length = 0x3 (unknown attribute)
   05 02 00
