Classfile /Users/mw/Projects/slang-braindump/.jar/jar8/assemble/slang-braindump/assemble/content/org/scalatest/tools/NestedSuiteElement.class
  Last modified May 29, 2022; size 2682 bytes
  SHA-256 checksum 07d72d1b19b853d560aede596bc74f4adb4542204d9def3b6d86494fccebecd9
  Compiled from "ScalaTestAntTask.scala"
public class org.scalatest.tools.NestedSuiteElement
  minor version: 0
  major version: 52
  flags: (0x0021) ACC_PUBLIC, ACC_SUPER
  this_class: #2                          // org/scalatest/tools/NestedSuiteElement
  super_class: #4                         // java/lang/Object
  interfaces: 0, fields: 2, methods: 8, attributes: 4
Constant pool:
   #1 = Utf8               org/scalatest/tools/NestedSuiteElement
   #2 = Class              #1             // org/scalatest/tools/NestedSuiteElement
   #3 = Utf8               java/lang/Object
   #4 = Class              #3             // java/lang/Object
   #5 = Utf8               ScalaTestAntTask.scala
   #6 = Utf8               Lscala/reflect/ScalaSignature;
   #7 = Utf8               bytes
   #8 = Utf8               \u0006\u000593Aa\u0003\u0007\u0005\'!)!\u0004\u0001C\u00017!9a\u0004\u0001a\u0001\n\u0013y\u0002bB\u0016\u0001\u0001\u0004%I\u0001\f\u0005\u0007e\u0001\u0001\u000b\u0015\u0002\u0011\t\u000fM\u0002!\u0019!C\u0005i!1Q\b\u0001Q\u0001\nUBQA\u0010\u0001\u0005\u0002}BQ!\u0011\u0001\u0005\u0002\tCQ\u0001\u0013\u0001\u0005\u0002}AQ!\u0013\u0001\u0005\u0002)\u0013!CT3ti\u0016$7+^5uK\u0016cW-\\3oi*\u0011QBD\u0001\u0006i>|Gn\u001d\u0006\u0003\u001fA\t\u0011b]2bY\u0006$Xm\u001d;\u000b\u0003E\t1a\u001c:h\u0007\u0001\u0019\"\u0001\u0001\u000b\u0011\u0005UAR\"\u0001\f\u000b\u0003]\tQa]2bY\u0006L!!\u0007\f\u0003\r\u0005s\u0017PU3g\u0003\u0019a\u0014N\\5u}Q\tA\u0004\u0005\u0002\u001e\u00015\tA\"A\u0004tk&$X-\u00133\u0016\u0003\u0001\u0002\"!\t\u0015\u000f\u0005\t2\u0003CA\u0012\u0017\u001b\u0005!#BA\u0013\u0013\u0003\u0019a$o\\8u}%\u0011qEF\u0001\u0007!J,G-\u001a4\n\u0005%R#AB*ue&twM\u0003\u0002(-\u0005Y1/^5uK&#w\fJ3r)\ti\u0003\u0007\u0005\u0002\u0016]%\u0011qF\u0006\u0002\u0005+:LG\u000fC\u00042\u0007\u0005\u0005\t\u0019\u0001\u0011\u0002\u0007a$\u0013\'\u0001\u0005tk&$X-\u00133!\u0003=!Xm\u001d;OC6,7OQ;gM\u0016\u0014X#A\u001b\u0011\u0007YZ\u0004%D\u00018\u0015\tA\u0014(A\u0004nkR\f\'\r\\3\u000b\u0005i2\u0012AC2pY2,7\r^5p]&\u0011Ah\u000e\u0002\u000b\u0019&\u001cHOQ;gM\u0016\u0014\u0018\u0001\u0005;fgRt\u0015-\\3t\u0005V4g-\u001a:!\u0003)\u0019X\r^*vSR,\u0017\n\u001a\u000b\u0003[\u0001CQAH\u0004A\u0002\u0001\n\u0011#\u00193e\u0007>tg-[4ve\u0016$G+Z:u)\ti3\tC\u0003E\u0011\u0001\u0007Q)\u0001\u0003uKN$\bCA\u000fG\u0013\t9EBA\u0006UKN$X\t\\3nK:$\u0018AC4fiN+\u0018\u000e^3JI\u0006aq-\u001a;UKN$h*Y7fgV\t1\nE\u0002\u0016\u0019\u0002J!!\u0014\f\u0003\u000b\u0005\u0013(/Y=
   #9 = Utf8               suiteId
  #10 = Utf8               Ljava/lang/String;
  #11 = Utf8               testNamesBuffer
  #12 = Utf8               Lscala/collection/mutable/ListBuffer;
  #13 = Utf8               Lscala/collection/mutable/ListBuffer<Ljava/lang/String;>;
  #14 = Utf8               ()Ljava/lang/String;
  #15 = NameAndType        #9:#10         // suiteId:Ljava/lang/String;
  #16 = Fieldref           #2.#15         // org/scalatest/tools/NestedSuiteElement.suiteId:Ljava/lang/String;
  #17 = Utf8               this
  #18 = Utf8               Lorg/scalatest/tools/NestedSuiteElement;
  #19 = Utf8               suiteId_$eq
  #20 = Utf8               (Ljava/lang/String;)V
  #21 = Utf8               x$1
  #22 = Utf8               ()Lscala/collection/mutable/ListBuffer;
  #23 = Utf8               ()Lscala/collection/mutable/ListBuffer<Ljava/lang/String;>;
  #24 = NameAndType        #11:#12        // testNamesBuffer:Lscala/collection/mutable/ListBuffer;
  #25 = Fieldref           #2.#24         // org/scalatest/tools/NestedSuiteElement.testNamesBuffer:Lscala/collection/mutable/ListBuffer;
  #26 = Utf8               setSuiteId
  #27 = NameAndType        #19:#20        // suiteId_$eq:(Ljava/lang/String;)V
  #28 = Methodref          #2.#27         // org/scalatest/tools/NestedSuiteElement.suiteId_$eq:(Ljava/lang/String;)V
  #29 = Utf8               addConfiguredTest
  #30 = Utf8               (Lorg/scalatest/tools/TestElement;)V
  #31 = Utf8               test
  #32 = NameAndType        #11:#22        // testNamesBuffer:()Lscala/collection/mutable/ListBuffer;
  #33 = Methodref          #2.#32         // org/scalatest/tools/NestedSuiteElement.testNamesBuffer:()Lscala/collection/mutable/ListBuffer;
  #34 = Utf8               org/scalatest/tools/TestElement
  #35 = Class              #34            // org/scalatest/tools/TestElement
  #36 = Utf8               getName
  #37 = NameAndType        #36:#14        // getName:()Ljava/lang/String;
  #38 = Methodref          #35.#37        // org/scalatest/tools/TestElement.getName:()Ljava/lang/String;
  #39 = Utf8               scala/collection/mutable/ListBuffer
  #40 = Class              #39            // scala/collection/mutable/ListBuffer
  #41 = Utf8               $plus$eq
  #42 = Utf8               (Ljava/lang/Object;)Lscala/collection/mutable/Growable;
  #43 = NameAndType        #41:#42        // $plus$eq:(Ljava/lang/Object;)Lscala/collection/mutable/Growable;
  #44 = Methodref          #40.#43        // scala/collection/mutable/ListBuffer.$plus$eq:(Ljava/lang/Object;)Lscala/collection/mutable/Growable;
  #45 = Utf8               Lorg/scalatest/tools/TestElement;
  #46 = Utf8               getSuiteId
  #47 = NameAndType        #9:#14         // suiteId:()Ljava/lang/String;
  #48 = Methodref          #2.#47         // org/scalatest/tools/NestedSuiteElement.suiteId:()Ljava/lang/String;
  #49 = Utf8               getTestNames
  #50 = Utf8               ()[Ljava/lang/String;
  #51 = Utf8               scala/reflect/ClassTag$
  #52 = Class              #51            // scala/reflect/ClassTag$
  #53 = Utf8               MODULE$
  #54 = Utf8               Lscala/reflect/ClassTag$;
  #55 = NameAndType        #53:#54        // MODULE$:Lscala/reflect/ClassTag$;
  #56 = Fieldref           #52.#55        // scala/reflect/ClassTag$.MODULE$:Lscala/reflect/ClassTag$;
  #57 = Utf8               java/lang/String
  #58 = Class              #57            // java/lang/String
  #59 = Utf8               apply
  #60 = Utf8               (Ljava/lang/Class;)Lscala/reflect/ClassTag;
  #61 = NameAndType        #59:#60        // apply:(Ljava/lang/Class;)Lscala/reflect/ClassTag;
  #62 = Methodref          #52.#61        // scala/reflect/ClassTag$.apply:(Ljava/lang/Class;)Lscala/reflect/ClassTag;
  #63 = Utf8               toArray
  #64 = Utf8               (Lscala/reflect/ClassTag;)Ljava/lang/Object;
  #65 = NameAndType        #63:#64        // toArray:(Lscala/reflect/ClassTag;)Ljava/lang/Object;
  #66 = Methodref          #40.#65        // scala/collection/mutable/ListBuffer.toArray:(Lscala/reflect/ClassTag;)Ljava/lang/Object;
  #67 = Utf8               [Ljava/lang/String;
  #68 = Class              #67            // "[Ljava/lang/String;"
  #69 = Utf8               <init>
  #70 = Utf8               ()V
  #71 = NameAndType        #69:#70        // "<init>":()V
  #72 = Methodref          #4.#71         // java/lang/Object."<init>":()V
  #73 = Methodref          #40.#71        // scala/collection/mutable/ListBuffer."<init>":()V
  #74 = Utf8               Signature
  #75 = Utf8               Code
  #76 = Utf8               LineNumberTable
  #77 = Utf8               LocalVariableTable
  #78 = Utf8               MethodParameters
  #79 = Utf8               SourceFile
  #80 = Utf8               RuntimeVisibleAnnotations
  #81 = Utf8               ScalaInlineInfo
  #82 = Utf8               ScalaSig
{
  private java.lang.String suiteId;
    descriptor: Ljava/lang/String;
    flags: (0x0002) ACC_PRIVATE

  private final scala.collection.mutable.ListBuffer<java.lang.String> testNamesBuffer;
    descriptor: Lscala/collection/mutable/ListBuffer;
    flags: (0x0012) ACC_PRIVATE, ACC_FINAL
    Signature: #13                          // Lscala/collection/mutable/ListBuffer<Ljava/lang/String;>;

  private java.lang.String suiteId();
    descriptor: ()Ljava/lang/String;
    flags: (0x0002) ACC_PRIVATE
    Code:
      stack=1, locals=1, args_size=1
         0: aload_0
         1: getfield      #16                 // Field suiteId:Ljava/lang/String;
         4: areturn
      LineNumberTable:
        line 1036: 0
      LocalVariableTable:
        Start  Length  Slot  Name   Signature
            0       5     0  this   Lorg/scalatest/tools/NestedSuiteElement;

  private void suiteId_$eq(java.lang.String);
    descriptor: (Ljava/lang/String;)V
    flags: (0x0002) ACC_PRIVATE
    Code:
      stack=2, locals=2, args_size=2
         0: aload_0
         1: aload_1
         2: putfield      #16                 // Field suiteId:Ljava/lang/String;
         5: return
      LineNumberTable:
        line 1036: 0
      LocalVariableTable:
        Start  Length  Slot  Name   Signature
            0       6     0  this   Lorg/scalatest/tools/NestedSuiteElement;
            0       6     1   x$1   Ljava/lang/String;
    MethodParameters:
      Name                           Flags
      x$1                            final

  private scala.collection.mutable.ListBuffer<java.lang.String> testNamesBuffer();
    descriptor: ()Lscala/collection/mutable/ListBuffer;
    flags: (0x0002) ACC_PRIVATE
    Code:
      stack=1, locals=1, args_size=1
         0: aload_0
         1: getfield      #25                 // Field testNamesBuffer:Lscala/collection/mutable/ListBuffer;
         4: areturn
      LineNumberTable:
        line 1037: 0
      LocalVariableTable:
        Start  Length  Slot  Name   Signature
            0       5     0  this   Lorg/scalatest/tools/NestedSuiteElement;
    Signature: #23                          // ()Lscala/collection/mutable/ListBuffer<Ljava/lang/String;>;

  public void setSuiteId(java.lang.String);
    descriptor: (Ljava/lang/String;)V
    flags: (0x0001) ACC_PUBLIC
    Code:
      stack=2, locals=2, args_size=2
         0: aload_0
         1: aload_1
         2: invokespecial #28                 // Method suiteId_$eq:(Ljava/lang/String;)V
         5: return
      LineNumberTable:
        line 1040: 0
      LocalVariableTable:
        Start  Length  Slot  Name   Signature
            0       6     0  this   Lorg/scalatest/tools/NestedSuiteElement;
            0       6     1 suiteId   Ljava/lang/String;
    MethodParameters:
      Name                           Flags
      suiteId                        final

  public void addConfiguredTest(org.scalatest.tools.TestElement);
    descriptor: (Lorg/scalatest/tools/TestElement;)V
    flags: (0x0001) ACC_PUBLIC
    Code:
      stack=2, locals=2, args_size=2
         0: aload_0
         1: invokespecial #33                 // Method testNamesBuffer:()Lscala/collection/mutable/ListBuffer;
         4: aload_1
         5: invokevirtual #38                 // Method org/scalatest/tools/TestElement.getName:()Ljava/lang/String;
         8: invokevirtual #44                 // Method scala/collection/mutable/ListBuffer.$plus$eq:(Ljava/lang/Object;)Lscala/collection/mutable/Growable;
        11: pop
        12: return
      LineNumberTable:
        line 1044: 0
      LocalVariableTable:
        Start  Length  Slot  Name   Signature
            0      13     0  this   Lorg/scalatest/tools/NestedSuiteElement;
            0      13     1  test   Lorg/scalatest/tools/TestElement;
    MethodParameters:
      Name                           Flags
      test                           final

  public java.lang.String getSuiteId();
    descriptor: ()Ljava/lang/String;
    flags: (0x0001) ACC_PUBLIC
    Code:
      stack=1, locals=1, args_size=1
         0: aload_0
         1: invokespecial #48                 // Method suiteId:()Ljava/lang/String;
         4: areturn
      LineNumberTable:
        line 1047: 0
      LocalVariableTable:
        Start  Length  Slot  Name   Signature
            0       5     0  this   Lorg/scalatest/tools/NestedSuiteElement;

  public java.lang.String[] getTestNames();
    descriptor: ()[Ljava/lang/String;
    flags: (0x0001) ACC_PUBLIC
    Code:
      stack=3, locals=1, args_size=1
         0: aload_0
         1: invokespecial #33                 // Method testNamesBuffer:()Lscala/collection/mutable/ListBuffer;
         4: getstatic     #56                 // Field scala/reflect/ClassTag$.MODULE$:Lscala/reflect/ClassTag$;
         7: ldc           #58                 // class java/lang/String
         9: invokevirtual #62                 // Method scala/reflect/ClassTag$.apply:(Ljava/lang/Class;)Lscala/reflect/ClassTag;
        12: invokevirtual #66                 // Method scala/collection/mutable/ListBuffer.toArray:(Lscala/reflect/ClassTag;)Ljava/lang/Object;
        15: checkcast     #68                 // class "[Ljava/lang/String;"
        18: areturn
      LineNumberTable:
        line 1048: 0
      LocalVariableTable:
        Start  Length  Slot  Name   Signature
            0      19     0  this   Lorg/scalatest/tools/NestedSuiteElement;

  public org.scalatest.tools.NestedSuiteElement();
    descriptor: ()V
    flags: (0x0001) ACC_PUBLIC
    Code:
      stack=3, locals=1, args_size=1
         0: aload_0
         1: invokespecial #72                 // Method java/lang/Object."<init>":()V
         4: aload_0
         5: aconst_null
         6: putfield      #16                 // Field suiteId:Ljava/lang/String;
         9: aload_0
        10: new           #40                 // class scala/collection/mutable/ListBuffer
        13: dup
        14: invokespecial #73                 // Method scala/collection/mutable/ListBuffer."<init>":()V
        17: putfield      #25                 // Field testNamesBuffer:Lscala/collection/mutable/ListBuffer;
        20: return
      LineNumberTable:
        line 1054: 0
        line 1036: 4
        line 1037: 9
        line 1035: 20
      LocalVariableTable:
        Start  Length  Slot  Name   Signature
            0      21     0  this   Lorg/scalatest/tools/NestedSuiteElement;
}
SourceFile: "ScalaTestAntTask.scala"
RuntimeVisibleAnnotations:
  0: #6(#7=s#8)
    scala.reflect.ScalaSignature(
      bytes="\u0006\u000593Aa\u0003\u0007\u0005\'!)!\u0004\u0001C\u00017!9a\u0004\u0001a\u0001\n\u0013y\u0002bB\u0016\u0001\u0001\u0004%I\u0001\f\u0005\u0007e\u0001\u0001\u000b\u0015\u0002\u0011\t\u000fM\u0002!\u0019!C\u0005i!1Q\b\u0001Q\u0001\nUBQA\u0010\u0001\u0005\u0002}BQ!\u0011\u0001\u0005\u0002\tCQ\u0001\u0013\u0001\u0005\u0002}AQ!\u0013\u0001\u0005\u0002)\u0013!CT3ti\u0016$7+^5uK\u0016cW-\\3oi*\u0011QBD\u0001\u0006i>|Gn\u001d\u0006\u0003\u001fA\t\u0011b]2bY\u0006$Xm\u001d;\u000b\u0003E\t1a\u001c:h\u0007\u0001\u0019\"\u0001\u0001\u000b\u0011\u0005UAR\"\u0001\f\u000b\u0003]\tQa]2bY\u0006L!!\u0007\f\u0003\r\u0005s\u0017PU3g\u0003\u0019a\u0014N\\5u}Q\tA\u0004\u0005\u0002\u001e\u00015\tA\"A\u0004tk&$X-\u00133\u0016\u0003\u0001\u0002\"!\t\u0015\u000f\u0005\t2\u0003CA\u0012\u0017\u001b\u0005!#BA\u0013\u0013\u0003\u0019a$o\\8u}%\u0011qEF\u0001\u0007!J,G-\u001a4\n\u0005%R#AB*ue&twM\u0003\u0002(-\u0005Y1/^5uK&#w\fJ3r)\ti\u0003\u0007\u0005\u0002\u0016]%\u0011qF\u0006\u0002\u0005+:LG\u000fC\u00042\u0007\u0005\u0005\t\u0019\u0001\u0011\u0002\u0007a$\u0013\'\u0001\u0005tk&$X-\u00133!\u0003=!Xm\u001d;OC6,7OQ;gM\u0016\u0014X#A\u001b\u0011\u0007YZ\u0004%D\u00018\u0015\tA\u0014(A\u0004nkR\f\'\r\\3\u000b\u0005i2\u0012AC2pY2,7\r^5p]&\u0011Ah\u000e\u0002\u000b\u0019&\u001cHOQ;gM\u0016\u0014\u0018\u0001\u0005;fgRt\u0015-\\3t\u0005V4g-\u001a:!\u0003)\u0019X\r^*vSR,\u0017\n\u001a\u000b\u0003[\u0001CQAH\u0004A\u0002\u0001\n\u0011#\u00193e\u0007>tg-[4ve\u0016$G+Z:u)\ti3\tC\u0003E\u0011\u0001\u0007Q)\u0001\u0003uKN$\bCA\u000fG\u0013\t9EBA\u0006UKN$X\t\\3nK:$\u0018AC4fiN+\u0018\u000e^3JI\u0006aq-\u001a;UKN$h*Y7fgV\t1\nE\u0002\u0016\u0019\u0002J!!\u0014\f\u0003\u000b\u0005\u0013(/Y="
    )
  ScalaInlineInfo: length = 0x2C (unknown attribute)
   01 00 00 08 00 45 00 46 00 00 1D 00 1E 00 00 2E
   00 0E 00 00 31 00 32 00 00 1A 00 14 00 00 09 00
   0E 01 00 13 00 14 01 00 0B 00 16 01
  ScalaSig: length = 0x3 (unknown attribute)
   05 02 00
