Classfile /Users/mw/Projects/slang-braindump/.jar/jar8/assemble/slang-braindump/assemble/content/org/scalatest/tools/PackageElement.class
  Last modified May 29, 2022; size 1337 bytes
  SHA-256 checksum ebdbf173758283e3136d9b48e104c5466ed1d5e9bde63317b1109ab33fae157d
  Compiled from "ScalaTestAntTask.scala"
public class org.scalatest.tools.PackageElement
  minor version: 0
  major version: 52
  flags: (0x0021) ACC_PUBLIC, ACC_SUPER
  this_class: #2                          // org/scalatest/tools/PackageElement
  super_class: #4                         // java/lang/Object
  interfaces: 0, fields: 1, methods: 5, attributes: 4
Constant pool:
   #1 = Utf8               org/scalatest/tools/PackageElement
   #2 = Class              #1             // org/scalatest/tools/PackageElement
   #3 = Utf8               java/lang/Object
   #4 = Class              #3             // java/lang/Object
   #5 = Utf8               ScalaTestAntTask.scala
   #6 = Utf8               Lscala/reflect/ScalaSignature;
   #7 = Utf8               bytes
   #8 = Utf8               \u0006\u0005M2Aa\u0002\u0005\u0005\u001f!)a\u0003\u0001C\u0001/!9!\u0004\u0001a\u0001\n\u0013Y\u0002bB\u0014\u0001\u0001\u0004%I\u0001\u000b\u0005\u0007]\u0001\u0001\u000b\u0015\u0002\u000f\t\u000b=\u0002A\u0011\u0001\u0019\t\u000bI\u0002A\u0011A\u000e\u0003\u001dA\u000b7m[1hK\u0016cW-\\3oi*\u0011\u0011BC\u0001\u0006i>|Gn\u001d\u0006\u0003\u00171\t\u0011b]2bY\u0006$Xm\u001d;\u000b\u00035\t1a\u001c:h\u0007\u0001\u0019\"\u0001\u0001\t\u0011\u0005E!R\"\u0001\n\u000b\u0003M\tQa]2bY\u0006L!!\u0006\n\u0003\r\u0005s\u0017PU3g\u0003\u0019a\u0014N\\5u}Q\t\u0001\u0004\u0005\u0002\u001a\u00015\t\u0001\"A\u0006qC\u000e\\\u0017mZ3OC6,W#\u0001\u000f\u0011\u0005u!cB\u0001\u0010#!\ty\"#D\u0001!\u0015\t\tc\"\u0001\u0004=e>|GOP\u0005\u0003GI\ta\u0001\u0015:fI\u00164\u0017BA\u0013\'\u0005\u0019\u0019FO]5oO*\u00111EE\u0001\u0010a\u0006\u001c7.Y4f\u001d\u0006lWm\u0018\u0013fcR\u0011\u0011\u0006\f\t\u0003#)J!a\u000b\n\u0003\tUs\u0017\u000e\u001e\u0005\b[\r\t\t\u00111\u0001\u001d\u0003\rAH%M\u0001\ra\u0006\u001c7.Y4f\u001d\u0006lW\rI\u0001\u000bg\u0016$\b+Y2lC\u001e,GCA\u00152\u0011\u0015QR\u00011\u0001\u001d\u0003)9W\r\u001e)bG.\fw-\u001a
   #9 = Utf8               packageName
  #10 = Utf8               Ljava/lang/String;
  #11 = Utf8               ()Ljava/lang/String;
  #12 = NameAndType        #9:#10         // packageName:Ljava/lang/String;
  #13 = Fieldref           #2.#12         // org/scalatest/tools/PackageElement.packageName:Ljava/lang/String;
  #14 = Utf8               this
  #15 = Utf8               Lorg/scalatest/tools/PackageElement;
  #16 = Utf8               packageName_$eq
  #17 = Utf8               (Ljava/lang/String;)V
  #18 = Utf8               x$1
  #19 = Utf8               setPackage
  #20 = NameAndType        #16:#17        // packageName_$eq:(Ljava/lang/String;)V
  #21 = Methodref          #2.#20         // org/scalatest/tools/PackageElement.packageName_$eq:(Ljava/lang/String;)V
  #22 = Utf8               getPackage
  #23 = NameAndType        #9:#11         // packageName:()Ljava/lang/String;
  #24 = Methodref          #2.#23         // org/scalatest/tools/PackageElement.packageName:()Ljava/lang/String;
  #25 = Utf8               <init>
  #26 = Utf8               ()V
  #27 = NameAndType        #25:#26        // "<init>":()V
  #28 = Methodref          #4.#27         // java/lang/Object."<init>":()V
  #29 = Utf8               Code
  #30 = Utf8               LineNumberTable
  #31 = Utf8               LocalVariableTable
  #32 = Utf8               MethodParameters
  #33 = Utf8               SourceFile
  #34 = Utf8               RuntimeVisibleAnnotations
  #35 = Utf8               ScalaInlineInfo
  #36 = Utf8               ScalaSig
{
  private java.lang.String packageName;
    descriptor: Ljava/lang/String;
    flags: (0x0002) ACC_PRIVATE

  private java.lang.String packageName();
    descriptor: ()Ljava/lang/String;
    flags: (0x0002) ACC_PRIVATE
    Code:
      stack=1, locals=1, args_size=1
         0: aload_0
         1: getfield      #13                 // Field packageName:Ljava/lang/String;
         4: areturn
      LineNumberTable:
        line 985: 0
      LocalVariableTable:
        Start  Length  Slot  Name   Signature
            0       5     0  this   Lorg/scalatest/tools/PackageElement;

  private void packageName_$eq(java.lang.String);
    descriptor: (Ljava/lang/String;)V
    flags: (0x0002) ACC_PRIVATE
    Code:
      stack=2, locals=2, args_size=2
         0: aload_0
         1: aload_1
         2: putfield      #13                 // Field packageName:Ljava/lang/String;
         5: return
      LineNumberTable:
        line 985: 0
      LocalVariableTable:
        Start  Length  Slot  Name   Signature
            0       6     0  this   Lorg/scalatest/tools/PackageElement;
            0       6     1   x$1   Ljava/lang/String;
    MethodParameters:
      Name                           Flags
      x$1                            final

  public void setPackage(java.lang.String);
    descriptor: (Ljava/lang/String;)V
    flags: (0x0001) ACC_PUBLIC
    Code:
      stack=2, locals=2, args_size=2
         0: aload_0
         1: aload_1
         2: invokespecial #21                 // Method packageName_$eq:(Ljava/lang/String;)V
         5: return
      LineNumberTable:
        line 988: 0
      LocalVariableTable:
        Start  Length  Slot  Name   Signature
            0       6     0  this   Lorg/scalatest/tools/PackageElement;
            0       6     1 packageName   Ljava/lang/String;
    MethodParameters:
      Name                           Flags
      packageName                    final

  public java.lang.String getPackage();
    descriptor: ()Ljava/lang/String;
    flags: (0x0001) ACC_PUBLIC
    Code:
      stack=1, locals=1, args_size=1
         0: aload_0
         1: invokespecial #24                 // Method packageName:()Ljava/lang/String;
         4: areturn
      LineNumberTable:
        line 991: 0
      LocalVariableTable:
        Start  Length  Slot  Name   Signature
            0       5     0  this   Lorg/scalatest/tools/PackageElement;

  public org.scalatest.tools.PackageElement();
    descriptor: ()V
    flags: (0x0001) ACC_PUBLIC
    Code:
      stack=2, locals=1, args_size=1
         0: aload_0
         1: invokespecial #28                 // Method java/lang/Object."<init>":()V
         4: aload_0
         5: aconst_null
         6: putfield      #13                 // Field packageName:Ljava/lang/String;
         9: return
      LineNumberTable:
        line 997: 0
        line 985: 4
        line 984: 9
      LocalVariableTable:
        Start  Length  Slot  Name   Signature
            0      10     0  this   Lorg/scalatest/tools/PackageElement;
}
SourceFile: "ScalaTestAntTask.scala"
RuntimeVisibleAnnotations:
  0: #6(#7=s#8)
    scala.reflect.ScalaSignature(
      bytes="\u0006\u0005M2Aa\u0002\u0005\u0005\u001f!)a\u0003\u0001C\u0001/!9!\u0004\u0001a\u0001\n\u0013Y\u0002bB\u0014\u0001\u0001\u0004%I\u0001\u000b\u0005\u0007]\u0001\u0001\u000b\u0015\u0002\u000f\t\u000b=\u0002A\u0011\u0001\u0019\t\u000bI\u0002A\u0011A\u000e\u0003\u001dA\u000b7m[1hK\u0016cW-\\3oi*\u0011\u0011BC\u0001\u0006i>|Gn\u001d\u0006\u0003\u00171\t\u0011b]2bY\u0006$Xm\u001d;\u000b\u00035\t1a\u001c:h\u0007\u0001\u0019\"\u0001\u0001\t\u0011\u0005E!R\"\u0001\n\u000b\u0003M\tQa]2bY\u0006L!!\u0006\n\u0003\r\u0005s\u0017PU3g\u0003\u0019a\u0014N\\5u}Q\t\u0001\u0004\u0005\u0002\u001a\u00015\t\u0001\"A\u0006qC\u000e\\\u0017mZ3OC6,W#\u0001\u000f\u0011\u0005u!cB\u0001\u0010#!\ty\"#D\u0001!\u0015\t\tc\"\u0001\u0004=e>|GOP\u0005\u0003GI\ta\u0001\u0015:fI\u00164\u0017BA\u0013\'\u0005\u0019\u0019FO]5oO*\u00111EE\u0001\u0010a\u0006\u001c7.Y4f\u001d\u0006lWm\u0018\u0013fcR\u0011\u0011\u0006\f\t\u0003#)J!a\u000b\n\u0003\tUs\u0017\u000e\u001e\u0005\b[\r\t\t\u00111\u0001\u001d\u0003\rAH%M\u0001\ra\u0006\u001c7.Y4f\u001d\u0006lW\rI\u0001\u000bg\u0016$\b+Y2lC\u001e,GCA\u00152\u0011\u0015QR\u00011\u0001\u001d\u0003)9W\r\u001e)bG.\fw-\u001a"
    )
  ScalaInlineInfo: length = 0x1D (unknown attribute)
   01 00 00 05 00 19 00 1A 00 00 16 00 0B 00 00 09
   00 0B 01 00 10 00 11 01 00 13 00 11 00
  ScalaSig: length = 0x3 (unknown attribute)
   05 02 00
