Classfile /Users/mw/Projects/slang-braindump/.jar/jar8/assemble/slang-braindump/assemble/content/org/scalatest/tools/PrettyPrinter$Box$.class
  Last modified May 29, 2022; size 2207 bytes
  SHA-256 checksum 99d4f85783877fcd7a7baa4c097ce8c5857829c1a18c1d199a40ee130c10dc73
  Compiled from "PrettyPrinter.scala"
public class org.scalatest.tools.PrettyPrinter$Box$ extends scala.runtime.AbstractFunction2<java.lang.Object, java.lang.String, org.scalatest.tools.PrettyPrinter$Box> implements java.io.Serializable
  minor version: 0
  major version: 52
  flags: (0x0021) ACC_PUBLIC, ACC_SUPER
  this_class: #2                          // org/scalatest/tools/PrettyPrinter$Box$
  super_class: #5                         // scala/runtime/AbstractFunction2
  interfaces: 1, fields: 1, methods: 5, attributes: 5
Constant pool:
   #1 = Utf8               org/scalatest/tools/PrettyPrinter$Box$
   #2 = Class              #1             // org/scalatest/tools/PrettyPrinter$Box$
   #3 = Utf8               Lscala/runtime/AbstractFunction2<Ljava/lang/Object;Ljava/lang/String;Lorg/scalatest/tools/PrettyPrinter$Box;>;Ljava/io/Serializable;
   #4 = Utf8               scala/runtime/AbstractFunction2
   #5 = Class              #4             // scala/runtime/AbstractFunction2
   #6 = Utf8               java/io/Serializable
   #7 = Class              #6             // java/io/Serializable
   #8 = Utf8               PrettyPrinter.scala
   #9 = Utf8               org/scalatest/tools/PrettyPrinter$Box
  #10 = Class              #9             // org/scalatest/tools/PrettyPrinter$Box
  #11 = Utf8               org/scalatest/tools/PrettyPrinter
  #12 = Class              #11            // org/scalatest/tools/PrettyPrinter
  #13 = Utf8               Box
  #14 = Utf8               Box$
  #15 = Utf8               $outer
  #16 = Utf8               Lorg/scalatest/tools/PrettyPrinter;
  #17 = Utf8               toString
  #18 = Utf8               ()Ljava/lang/String;
  #19 = String             #13            // Box
  #20 = Utf8               this
  #21 = Utf8               Lorg/scalatest/tools/PrettyPrinter$Box$;
  #22 = Utf8               apply
  #23 = Utf8               (ILjava/lang/String;)Lorg/scalatest/tools/PrettyPrinter$Box;
  #24 = Utf8               col
  #25 = Utf8               s
  #26 = NameAndType        #15:#16        // $outer:Lorg/scalatest/tools/PrettyPrinter;
  #27 = Fieldref           #2.#26         // org/scalatest/tools/PrettyPrinter$Box$.$outer:Lorg/scalatest/tools/PrettyPrinter;
  #28 = Utf8               <init>
  #29 = Utf8               (Lorg/scalatest/tools/PrettyPrinter;ILjava/lang/String;)V
  #30 = NameAndType        #28:#29        // "<init>":(Lorg/scalatest/tools/PrettyPrinter;ILjava/lang/String;)V
  #31 = Methodref          #10.#30        // org/scalatest/tools/PrettyPrinter$Box."<init>":(Lorg/scalatest/tools/PrettyPrinter;ILjava/lang/String;)V
  #32 = Utf8               I
  #33 = Utf8               Ljava/lang/String;
  #34 = Utf8               unapply
  #35 = Utf8               (Lorg/scalatest/tools/PrettyPrinter$Box;)Lscala/Option;
  #36 = Utf8               (Lorg/scalatest/tools/PrettyPrinter$Box;)Lscala/Option<Lscala/Tuple2<Ljava/lang/Object;Ljava/lang/String;>;>;
  #37 = Utf8               x$0
  #38 = Utf8               scala/None$
  #39 = Class              #38            // scala/None$
  #40 = Utf8               MODULE$
  #41 = Utf8               Lscala/None$;
  #42 = NameAndType        #40:#41        // MODULE$:Lscala/None$;
  #43 = Fieldref           #39.#42        // scala/None$.MODULE$:Lscala/None$;
  #44 = Utf8               scala/Some
  #45 = Class              #44            // scala/Some
  #46 = Utf8               scala/Tuple2
  #47 = Class              #46            // scala/Tuple2
  #48 = Utf8               ()I
  #49 = NameAndType        #24:#48        // col:()I
  #50 = Methodref          #10.#49        // org/scalatest/tools/PrettyPrinter$Box.col:()I
  #51 = Utf8               scala/runtime/BoxesRunTime
  #52 = Class              #51            // scala/runtime/BoxesRunTime
  #53 = Utf8               boxToInteger
  #54 = Utf8               (I)Ljava/lang/Integer;
  #55 = NameAndType        #53:#54        // boxToInteger:(I)Ljava/lang/Integer;
  #56 = Methodref          #52.#55        // scala/runtime/BoxesRunTime.boxToInteger:(I)Ljava/lang/Integer;
  #57 = NameAndType        #25:#18        // s:()Ljava/lang/String;
  #58 = Methodref          #10.#57        // org/scalatest/tools/PrettyPrinter$Box.s:()Ljava/lang/String;
  #59 = Utf8               (Ljava/lang/Object;Ljava/lang/Object;)V
  #60 = NameAndType        #28:#59        // "<init>":(Ljava/lang/Object;Ljava/lang/Object;)V
  #61 = Methodref          #47.#60        // scala/Tuple2."<init>":(Ljava/lang/Object;Ljava/lang/Object;)V
  #62 = Utf8               (Ljava/lang/Object;)V
  #63 = NameAndType        #28:#62        // "<init>":(Ljava/lang/Object;)V
  #64 = Methodref          #45.#63        // scala/Some."<init>":(Ljava/lang/Object;)V
  #65 = Utf8               Lorg/scalatest/tools/PrettyPrinter$Box;
  #66 = Utf8               scala/Option
  #67 = Class              #66            // scala/Option
  #68 = Utf8               (Ljava/lang/Object;Ljava/lang/Object;)Ljava/lang/Object;
  #69 = Utf8               v1
  #70 = Utf8               v2
  #71 = Utf8               unboxToInt
  #72 = Utf8               (Ljava/lang/Object;)I
  #73 = NameAndType        #71:#72        // unboxToInt:(Ljava/lang/Object;)I
  #74 = Methodref          #52.#73        // scala/runtime/BoxesRunTime.unboxToInt:(Ljava/lang/Object;)I
  #75 = Utf8               java/lang/String
  #76 = Class              #75            // java/lang/String
  #77 = NameAndType        #22:#23        // apply:(ILjava/lang/String;)Lorg/scalatest/tools/PrettyPrinter$Box;
  #78 = Methodref          #2.#77         // org/scalatest/tools/PrettyPrinter$Box$.apply:(ILjava/lang/String;)Lorg/scalatest/tools/PrettyPrinter$Box;
  #79 = Utf8               Ljava/lang/Object;
  #80 = Utf8               (Lorg/scalatest/tools/PrettyPrinter;)V
  #81 = Utf8               ()V
  #82 = NameAndType        #28:#81        // "<init>":()V
  #83 = Methodref          #5.#82         // scala/runtime/AbstractFunction2."<init>":()V
  #84 = Utf8               Code
  #85 = Utf8               LineNumberTable
  #86 = Utf8               LocalVariableTable
  #87 = Utf8               MethodParameters
  #88 = Utf8               StackMapTable
  #89 = Utf8               Signature
  #90 = Utf8               InnerClasses
  #91 = Utf8               SourceFile
  #92 = Utf8               ScalaInlineInfo
  #93 = Utf8               Scala
{
  private final org.scalatest.tools.PrettyPrinter $outer;
    descriptor: Lorg/scalatest/tools/PrettyPrinter;
    flags: (0x1012) ACC_PRIVATE, ACC_FINAL, ACC_SYNTHETIC

  public final java.lang.String toString();
    descriptor: ()Ljava/lang/String;
    flags: (0x0011) ACC_PUBLIC, ACC_FINAL
    Code:
      stack=1, locals=1, args_size=1
         0: ldc           #19                 // String Box
         2: areturn
      LineNumberTable:
        line 43: 0
      LocalVariableTable:
        Start  Length  Slot  Name   Signature
            0       3     0  this   Lorg/scalatest/tools/PrettyPrinter$Box$;

  public org.scalatest.tools.PrettyPrinter$Box apply(int, java.lang.String);
    descriptor: (ILjava/lang/String;)Lorg/scalatest/tools/PrettyPrinter$Box;
    flags: (0x0001) ACC_PUBLIC
    Code:
      stack=5, locals=3, args_size=3
         0: new           #10                 // class org/scalatest/tools/PrettyPrinter$Box
         3: dup
         4: aload_0
         5: getfield      #27                 // Field $outer:Lorg/scalatest/tools/PrettyPrinter;
         8: iload_1
         9: aload_2
        10: invokespecial #31                 // Method org/scalatest/tools/PrettyPrinter$Box."<init>":(Lorg/scalatest/tools/PrettyPrinter;ILjava/lang/String;)V
        13: areturn
      LineNumberTable:
        line 43: 0
      LocalVariableTable:
        Start  Length  Slot  Name   Signature
            0      14     0  this   Lorg/scalatest/tools/PrettyPrinter$Box$;
            0      14     1   col   I
            0      14     2     s   Ljava/lang/String;
    MethodParameters:
      Name                           Flags
      col                            final
      s                              final

  public scala.Option<scala.Tuple2<java.lang.Object, java.lang.String>> unapply(org.scalatest.tools.PrettyPrinter$Box);
    descriptor: (Lorg/scalatest/tools/PrettyPrinter$Box;)Lscala/Option;
    flags: (0x0001) ACC_PUBLIC
    Code:
      stack=6, locals=2, args_size=2
         0: aload_1
         1: ifnonnull     10
         4: getstatic     #43                 // Field scala/None$.MODULE$:Lscala/None$;
         7: goto          35
        10: new           #45                 // class scala/Some
        13: dup
        14: new           #47                 // class scala/Tuple2
        17: dup
        18: aload_1
        19: invokevirtual #50                 // Method org/scalatest/tools/PrettyPrinter$Box.col:()I
        22: invokestatic  #56                 // Method scala/runtime/BoxesRunTime.boxToInteger:(I)Ljava/lang/Integer;
        25: aload_1
        26: invokevirtual #58                 // Method org/scalatest/tools/PrettyPrinter$Box.s:()Ljava/lang/String;
        29: invokespecial #61                 // Method scala/Tuple2."<init>":(Ljava/lang/Object;Ljava/lang/Object;)V
        32: invokespecial #64                 // Method scala/Some."<init>":(Ljava/lang/Object;)V
        35: areturn
      StackMapTable: number_of_entries = 2
        frame_type = 10 /* same */
        frame_type = 88 /* same_locals_1_stack_item */
          stack = [ class scala/Option ]
      LineNumberTable:
        line 43: 0
      LocalVariableTable:
        Start  Length  Slot  Name   Signature
            0      36     0  this   Lorg/scalatest/tools/PrettyPrinter$Box$;
            0      36     1   x$0   Lorg/scalatest/tools/PrettyPrinter$Box;
    Signature: #36                          // (Lorg/scalatest/tools/PrettyPrinter$Box;)Lscala/Option<Lscala/Tuple2<Ljava/lang/Object;Ljava/lang/String;>;>;
    MethodParameters:
      Name                           Flags
      x$0                            final

  public java.lang.Object apply(java.lang.Object, java.lang.Object);
    descriptor: (Ljava/lang/Object;Ljava/lang/Object;)Ljava/lang/Object;
    flags: (0x1041) ACC_PUBLIC, ACC_BRIDGE, ACC_SYNTHETIC
    Code:
      stack=3, locals=3, args_size=3
         0: aload_0
         1: aload_1
         2: invokestatic  #74                 // Method scala/runtime/BoxesRunTime.unboxToInt:(Ljava/lang/Object;)I
         5: aload_2
         6: checkcast     #76                 // class java/lang/String
         9: invokevirtual #78                 // Method apply:(ILjava/lang/String;)Lorg/scalatest/tools/PrettyPrinter$Box;
        12: areturn
      LineNumberTable:
        line 43: 0
      LocalVariableTable:
        Start  Length  Slot  Name   Signature
            0      13     0  this   Lorg/scalatest/tools/PrettyPrinter$Box$;
            0      13     1    v1   Ljava/lang/Object;
            0      13     2    v2   Ljava/lang/Object;
    MethodParameters:
      Name                           Flags
      v1                             final
      v2                             final

  public org.scalatest.tools.PrettyPrinter$Box$(org.scalatest.tools.PrettyPrinter);
    descriptor: (Lorg/scalatest/tools/PrettyPrinter;)V
    flags: (0x0001) ACC_PUBLIC
    Code:
      stack=2, locals=2, args_size=2
         0: aload_1
         1: ifnonnull     6
         4: aconst_null
         5: athrow
         6: aload_0
         7: aload_1
         8: putfield      #27                 // Field $outer:Lorg/scalatest/tools/PrettyPrinter;
        11: aload_0
        12: invokespecial #83                 // Method scala/runtime/AbstractFunction2."<init>":()V
        15: return
      StackMapTable: number_of_entries = 1
        frame_type = 6 /* same */
      LineNumberTable:
        line 43: 0
      LocalVariableTable:
        Start  Length  Slot  Name   Signature
            0      16     0  this   Lorg/scalatest/tools/PrettyPrinter$Box$;
            0      16     1 $outer   Lorg/scalatest/tools/PrettyPrinter;
    MethodParameters:
      Name                           Flags
      $outer                         final synthetic
}
InnerClasses:
  public #13= #10 of #12;                 // Box=class org/scalatest/tools/PrettyPrinter$Box of class org/scalatest/tools/PrettyPrinter
  public #14= #2 of #12;                  // Box$=class org/scalatest/tools/PrettyPrinter$Box$ of class org/scalatest/tools/PrettyPrinter
Signature: #3                           // Lscala/runtime/AbstractFunction2<Ljava/lang/Object;Ljava/lang/String;Lorg/scalatest/tools/PrettyPrinter$Box;>;Ljava/io/Serializable;
SourceFile: "PrettyPrinter.scala"
  ScalaInlineInfo: length = 0x1D (unknown attribute)
   01 01 00 05 00 1C 00 50 01 00 16 00 17 01 00 16
   00 44 01 00 11 00 12 01 00 22 00 23 01
  Scala: length = 0x0 (unknown attribute)

