Classfile /Users/mw/Projects/slang-braindump/.jar/jar8/assemble/slang-braindump/assemble/content/org/scalatest/tools/ProgressBarPanel.class
  Last modified May 29, 2022; size 4352 bytes
  SHA-256 checksum a2e026536092a7512d3bfc8431708b22ee514f586d78ca91d97509c989dbefc1
  Compiled from "ProgressBarPanel.scala"
public class org.scalatest.tools.ProgressBarPanel extends javax.swing.JPanel
  minor version: 0
  major version: 52
  flags: (0x0021) ACC_PUBLIC, ACC_SUPER
  this_class: #2                          // org/scalatest/tools/ProgressBarPanel
  super_class: #4                         // javax/swing/JPanel
  interfaces: 0, fields: 4, methods: 14, attributes: 4
Constant pool:
    #1 = Utf8               org/scalatest/tools/ProgressBarPanel
    #2 = Class              #1            // org/scalatest/tools/ProgressBarPanel
    #3 = Utf8               javax/swing/JPanel
    #4 = Class              #3            // javax/swing/JPanel
    #5 = Utf8               ProgressBarPanel.scala
    #6 = Utf8               Lscala/reflect/ScalaSignature;
    #7 = Utf8               bytes
    #8 = Utf8               \u0006\u0005u3Qa\u0005\u000b\u0001-iAQa\t\u0001\u0005\u0002\u0015Bq\u0001\u000b\u0001C\u0002\u0013%\u0011\u0006\u0003\u0004.\u0001\u0001\u0006IA\u000b\u0005\b]\u0001\u0011\r\u0011\"\u00030\u0011\u0019\u0001\u0004\u0001)A\u00057!9\u0011\u0007\u0001b\u0001\n\u0013\u0011\u0004B\u0002\u001c\u0001A\u0003%1\u0007C\u00048\u0001\t\u0007I\u0011\u0002\u001d\t\r\u0005\u0003\u0001\u0015!\u0003:\u0011\u0015\u0011\u0005\u0001\"\u0001D\u0011\u0015Q\u0005\u0001\"\u0003D\u0011\u0015Y\u0005\u0001\"\u0001D\u0011\u0015a\u0005\u0001\"\u0001D\u0011\u0015i\u0005\u0001\"\u0001O\u0011\u0015!\u0006\u0001\"\u0001V\u0011\u0015A\u0006\u0001\"\u0001D\u0011\u0015I\u0006\u0001\"\u0001[\u0011\u0015a\u0006\u0001\"\u0001D\u0005A\u0001&o\\4sKN\u001c()\u0019:QC:,GN\u0003\u0002\u0016-\u0005)Ao\\8mg*\u0011q\u0003G\u0001\ng\u000e\fG.\u0019;fgRT\u0011!G\u0001\u0004_J<7C\u0001\u0001\u001c!\ta\u0012%D\u0001\u001e\u0015\tqr$A\u0003to&twMC\u0001!\u0003\u0015Q\u0017M^1y\u0013\t\u0011SD\u0001\u0004K!\u0006tW\r\\\u0001\u0007y%t\u0017\u000e\u001e \u0004\u0001Q\ta\u0005\u0005\u0002(\u00015\tA#A\u0006qe><\'/Z:t\u0005\u0006\u0014X#\u0001\u0016\u0011\u0005\u001dZ\u0013B\u0001\u0017\u0015\u0005!\u0019u\u000e\\8s\u0005\u0006\u0014\u0018\u0001\u00049s_\u001e\u0014Xm]:CCJ\u0004\u0013A\u00033jg\u000e|\u0007+\u00198fYV\t1$A\u0006eSN\u001cw\u000eU1oK2\u0004\u0013a\u00033jg\u000e|\'\nT1cK2,\u0012a\r\t\u00039QJ!!N\u000f\u0003\r)c\u0015MY3m\u00031!\u0017n]2p\u00152\u000b\'-\u001a7!\u00035!\u0017n]2p\u00136\fw-Z+S\u0019V\t\u0011\b\u0005\u0002;\u007f5\t1H\u0003\u0002={\u0005\u0019a.\u001a;\u000b\u0003y\nAA[1wC&\u0011\u0001i\u000f\u0002\u0004+Jc\u0015A\u00043jg\u000e|\u0017*\\1hKV\u0013F\nI\u0001\u0012I&\u001c8m\u001c<fef\u001cF/\u0019:uS:<G#\u0001#\u0011\u0005\u0015CU\"\u0001$\u000b\u0003\u001d\u000bQa]2bY\u0006L!!\u0013$\u0003\tUs\u0017\u000e^\u0001\u0010g\"|w\u000f\u0015:pOJ,7o\u001d\"be\u0006Q!/\u001e8BE>\u0014H/\u001a3\u0002%\u0011L7oY8wKJL8i\\7qY\u0016$X\rZ\u0001\feVt7\u000b^1si&tw\r\u0006\u0002E\u001f\")\u0001K\u0004a\u0001#\u0006IA/Z:u\u0007>,h\u000e\u001e\t\u0003\u000bJK!a\u0015$\u0003\u0007%sG/A\u0006tKR$Vm\u001d;t%VtGC\u0001#W\u0011\u00159v\u00021\u0001R\u0003M!Xm\u001d;t\u0007>l\u0007\u000f\\3uK\u0012\u001cu.\u001e8u\u00031\u0019X/\u001b;f\u0003\n|\'\u000f^3e\u0003)!Xm\u001d;GC&dW\r\u001a\u000b\u0003\tnCQaV\tA\u0002E\u000bQA]3tKR\u0004
    #9 = Utf8               progressBar
   #10 = Utf8               Lorg/scalatest/tools/ColorBar;
   #11 = Utf8               discoPanel
   #12 = Utf8               Ljavax/swing/JPanel;
   #13 = Utf8               discoJLabel
   #14 = Utf8               Ljavax/swing/JLabel;
   #15 = Utf8               discoImageURL
   #16 = Utf8               Ljava/net/URL;
   #17 = Utf8               ()Lorg/scalatest/tools/ColorBar;
   #18 = NameAndType        #9:#10        // progressBar:Lorg/scalatest/tools/ColorBar;
   #19 = Fieldref           #2.#18        // org/scalatest/tools/ProgressBarPanel.progressBar:Lorg/scalatest/tools/ColorBar;
   #20 = Utf8               this
   #21 = Utf8               Lorg/scalatest/tools/ProgressBarPanel;
   #22 = Utf8               ()Ljavax/swing/JPanel;
   #23 = NameAndType        #11:#12       // discoPanel:Ljavax/swing/JPanel;
   #24 = Fieldref           #2.#23        // org/scalatest/tools/ProgressBarPanel.discoPanel:Ljavax/swing/JPanel;
   #25 = Utf8               ()Ljavax/swing/JLabel;
   #26 = NameAndType        #13:#14       // discoJLabel:Ljavax/swing/JLabel;
   #27 = Fieldref           #2.#26        // org/scalatest/tools/ProgressBarPanel.discoJLabel:Ljavax/swing/JLabel;
   #28 = Utf8               ()Ljava/net/URL;
   #29 = NameAndType        #15:#16       // discoImageURL:Ljava/net/URL;
   #30 = Fieldref           #2.#29        // org/scalatest/tools/ProgressBarPanel.discoImageURL:Ljava/net/URL;
   #31 = Utf8               discoveryStarting
   #32 = Utf8               ()V
   #33 = NameAndType        #9:#17        // progressBar:()Lorg/scalatest/tools/ColorBar;
   #34 = Methodref          #2.#33        // org/scalatest/tools/ProgressBarPanel.progressBar:()Lorg/scalatest/tools/ColorBar;
   #35 = Utf8               remove
   #36 = Utf8               (Ljava/awt/Component;)V
   #37 = NameAndType        #35:#36       // remove:(Ljava/awt/Component;)V
   #38 = Methodref          #2.#37        // org/scalatest/tools/ProgressBarPanel.remove:(Ljava/awt/Component;)V
   #39 = NameAndType        #11:#22       // discoPanel:()Ljavax/swing/JPanel;
   #40 = Methodref          #2.#39        // org/scalatest/tools/ProgressBarPanel.discoPanel:()Ljavax/swing/JPanel;
   #41 = Utf8               West
   #42 = String             #41           // West
   #43 = Utf8               add
   #44 = Utf8               (Ljava/awt/Component;Ljava/lang/Object;)V
   #45 = NameAndType        #43:#44       // add:(Ljava/awt/Component;Ljava/lang/Object;)V
   #46 = Methodref          #2.#45        // org/scalatest/tools/ProgressBarPanel.add:(Ljava/awt/Component;Ljava/lang/Object;)V
   #47 = NameAndType        #13:#25       // discoJLabel:()Ljavax/swing/JLabel;
   #48 = Methodref          #2.#47        // org/scalatest/tools/ProgressBarPanel.discoJLabel:()Ljavax/swing/JLabel;
   #49 = Utf8
   #50 = String             #49           //
   #51 = Utf8               javax/swing/JLabel
   #52 = Class              #51           // javax/swing/JLabel
   #53 = Utf8               setText
   #54 = Utf8               (Ljava/lang/String;)V
   #55 = NameAndType        #53:#54       // setText:(Ljava/lang/String;)V
   #56 = Methodref          #52.#55       // javax/swing/JLabel.setText:(Ljava/lang/String;)V
   #57 = Utf8               org/scalatest/Resources$
   #58 = Class              #57           // org/scalatest/Resources$
   #59 = Utf8               MODULE$
   #60 = Utf8               Lorg/scalatest/Resources$;
   #61 = NameAndType        #59:#60       // MODULE$:Lorg/scalatest/Resources$;
   #62 = Fieldref           #58.#61       // org/scalatest/Resources$.MODULE$:Lorg/scalatest/Resources$;
   #63 = Utf8               doingDiscovery
   #64 = Utf8               ()Ljava/lang/String;
   #65 = NameAndType        #63:#64       // doingDiscovery:()Ljava/lang/String;
   #66 = Methodref          #58.#65       // org/scalatest/Resources$.doingDiscovery:()Ljava/lang/String;
   #67 = Utf8               showProgressBar
   #68 = Utf8               Center
   #69 = String             #68           // Center
   #70 = Utf8               runAborted
   #71 = NameAndType        #67:#32       // showProgressBar:()V
   #72 = Methodref          #2.#71        // org/scalatest/tools/ProgressBarPanel.showProgressBar:()V
   #73 = Utf8               org/scalatest/tools/ColorBar
   #74 = Class              #73           // org/scalatest/tools/ColorBar
   #75 = Utf8               setRed
   #76 = NameAndType        #75:#32       // setRed:()V
   #77 = Methodref          #74.#76       // org/scalatest/tools/ColorBar.setRed:()V
   #78 = Utf8               discoveryCompleted
   #79 = Utf8               runStarting
   #80 = Utf8               (I)V
   #81 = Utf8               testCount
   #82 = Utf8               setMax
   #83 = NameAndType        #82:#80       // setMax:(I)V
   #84 = Methodref          #74.#83       // org/scalatest/tools/ColorBar.setMax:(I)V
   #85 = Utf8               setValue
   #86 = NameAndType        #85:#80       // setValue:(I)V
   #87 = Methodref          #74.#86       // org/scalatest/tools/ColorBar.setValue:(I)V
   #88 = Utf8               setGreen
   #89 = NameAndType        #88:#32       // setGreen:()V
   #90 = Methodref          #74.#89       // org/scalatest/tools/ColorBar.setGreen:()V
   #91 = Utf8               I
   #92 = Utf8               setTestsRun
   #93 = Utf8               testsCompletedCount
   #94 = Utf8               suiteAborted
   #95 = Utf8               testFailed
   #96 = NameAndType        #92:#80       // setTestsRun:(I)V
   #97 = Methodref          #2.#96        // org/scalatest/tools/ProgressBarPanel.setTestsRun:(I)V
   #98 = Utf8               reset
   #99 = Utf8               setGray
  #100 = NameAndType        #99:#32       // setGray:()V
  #101 = Methodref          #74.#100      // org/scalatest/tools/ColorBar.setGray:()V
  #102 = Utf8               <init>
  #103 = NameAndType        #102:#32      // "<init>":()V
  #104 = Methodref          #4.#103       // javax/swing/JPanel."<init>":()V
  #105 = Methodref          #74.#103      // org/scalatest/tools/ColorBar."<init>":()V
  #106 = Methodref          #52.#103      // javax/swing/JLabel."<init>":()V
  #107 = Utf8               getClass
  #108 = Utf8               ()Ljava/lang/Class;
  #109 = NameAndType        #107:#108     // getClass:()Ljava/lang/Class;
  #110 = Methodref          #2.#109       // org/scalatest/tools/ProgressBarPanel.getClass:()Ljava/lang/Class;
  #111 = Utf8               java/lang/Class
  #112 = Class              #111          // java/lang/Class
  #113 = Utf8               getClassLoader
  #114 = Utf8               ()Ljava/lang/ClassLoader;
  #115 = NameAndType        #113:#114     // getClassLoader:()Ljava/lang/ClassLoader;
  #116 = Methodref          #112.#115     // java/lang/Class.getClassLoader:()Ljava/lang/ClassLoader;
  #117 = Utf8               images/inProgress.gif
  #118 = String             #117          // images/inProgress.gif
  #119 = Utf8               java/lang/ClassLoader
  #120 = Class              #119          // java/lang/ClassLoader
  #121 = Utf8               getResource
  #122 = Utf8               (Ljava/lang/String;)Ljava/net/URL;
  #123 = NameAndType        #121:#122     // getResource:(Ljava/lang/String;)Ljava/net/URL;
  #124 = Methodref          #120.#123     // java/lang/ClassLoader.getResource:(Ljava/lang/String;)Ljava/net/URL;
  #125 = Utf8               java/awt/BorderLayout
  #126 = Class              #125          // java/awt/BorderLayout
  #127 = Methodref          #126.#103     // java/awt/BorderLayout."<init>":()V
  #128 = Utf8               setLayout
  #129 = Utf8               (Ljava/awt/LayoutManager;)V
  #130 = NameAndType        #128:#129     // setLayout:(Ljava/awt/LayoutManager;)V
  #131 = Methodref          #2.#130       // org/scalatest/tools/ProgressBarPanel.setLayout:(Ljava/awt/LayoutManager;)V
  #132 = Utf8               javax/swing/border/BevelBorder
  #133 = Class              #132          // javax/swing/border/BevelBorder
  #134 = NameAndType        #102:#80      // "<init>":(I)V
  #135 = Methodref          #133.#134     // javax/swing/border/BevelBorder."<init>":(I)V
  #136 = Utf8               setBorder
  #137 = Utf8               (Ljavax/swing/border/Border;)V
  #138 = NameAndType        #136:#137     // setBorder:(Ljavax/swing/border/Border;)V
  #139 = Methodref          #2.#138       // org/scalatest/tools/ProgressBarPanel.setBorder:(Ljavax/swing/border/Border;)V
  #140 = Utf8               javax/swing/ImageIcon
  #141 = Class              #140          // javax/swing/ImageIcon
  #142 = NameAndType        #15:#28       // discoImageURL:()Ljava/net/URL;
  #143 = Methodref          #2.#142       // org/scalatest/tools/ProgressBarPanel.discoImageURL:()Ljava/net/URL;
  #144 = Utf8               (Ljava/net/URL;)V
  #145 = NameAndType        #102:#144     // "<init>":(Ljava/net/URL;)V
  #146 = Methodref          #141.#145     // javax/swing/ImageIcon."<init>":(Ljava/net/URL;)V
  #147 = Utf8               setIcon
  #148 = Utf8               (Ljavax/swing/Icon;)V
  #149 = NameAndType        #147:#148     // setIcon:(Ljavax/swing/Icon;)V
  #150 = Methodref          #52.#149      // javax/swing/JLabel.setIcon:(Ljavax/swing/Icon;)V
  #151 = Utf8               (Ljava/awt/Component;)Ljava/awt/Component;
  #152 = NameAndType        #43:#151      // add:(Ljava/awt/Component;)Ljava/awt/Component;
  #153 = Methodref          #4.#152       // javax/swing/JPanel.add:(Ljava/awt/Component;)Ljava/awt/Component;
  #154 = Utf8               java/awt/Dimension
  #155 = Class              #154          // java/awt/Dimension
  #156 = Utf8               getPreferredSize
  #157 = Utf8               ()Ljava/awt/Dimension;
  #158 = NameAndType        #156:#157     // getPreferredSize:()Ljava/awt/Dimension;
  #159 = Methodref          #2.#158       // org/scalatest/tools/ProgressBarPanel.getPreferredSize:()Ljava/awt/Dimension;
  #160 = Utf8               getWidth
  #161 = Utf8               ()D
  #162 = NameAndType        #160:#161     // getWidth:()D
  #163 = Methodref          #155.#162     // java/awt/Dimension.getWidth:()D
  #164 = Methodref          #4.#158       // javax/swing/JPanel.getPreferredSize:()Ljava/awt/Dimension;
  #165 = Utf8               getHeight
  #166 = NameAndType        #165:#161     // getHeight:()D
  #167 = Methodref          #155.#166     // java/awt/Dimension.getHeight:()D
  #168 = Utf8               (II)V
  #169 = NameAndType        #102:#168     // "<init>":(II)V
  #170 = Methodref          #155.#169     // java/awt/Dimension."<init>":(II)V
  #171 = Utf8               setPreferredSize
  #172 = Utf8               (Ljava/awt/Dimension;)V
  #173 = NameAndType        #171:#172     // setPreferredSize:(Ljava/awt/Dimension;)V
  #174 = Methodref          #2.#173       // org/scalatest/tools/ProgressBarPanel.setPreferredSize:(Ljava/awt/Dimension;)V
  #175 = Utf8               Code
  #176 = Utf8               LineNumberTable
  #177 = Utf8               LocalVariableTable
  #178 = Utf8               MethodParameters
  #179 = Utf8               SourceFile
  #180 = Utf8               RuntimeVisibleAnnotations
  #181 = Utf8               ScalaInlineInfo
  #182 = Utf8               ScalaSig
{
  private final org.scalatest.tools.ColorBar progressBar;
    descriptor: Lorg/scalatest/tools/ColorBar;
    flags: (0x0012) ACC_PRIVATE, ACC_FINAL

  private final javax.swing.JPanel discoPanel;
    descriptor: Ljavax/swing/JPanel;
    flags: (0x0012) ACC_PRIVATE, ACC_FINAL

  private final javax.swing.JLabel discoJLabel;
    descriptor: Ljavax/swing/JLabel;
    flags: (0x0012) ACC_PRIVATE, ACC_FINAL

  private final java.net.URL discoImageURL;
    descriptor: Ljava/net/URL;
    flags: (0x0012) ACC_PRIVATE, ACC_FINAL

  private org.scalatest.tools.ColorBar progressBar();
    descriptor: ()Lorg/scalatest/tools/ColorBar;
    flags: (0x0002) ACC_PRIVATE
    Code:
      stack=1, locals=1, args_size=1
         0: aload_0
         1: getfield      #19                 // Field progressBar:Lorg/scalatest/tools/ColorBar;
         4: areturn
      LineNumberTable:
        line 34: 0
      LocalVariableTable:
        Start  Length  Slot  Name   Signature
            0       5     0  this   Lorg/scalatest/tools/ProgressBarPanel;

  private javax.swing.JPanel discoPanel();
    descriptor: ()Ljavax/swing/JPanel;
    flags: (0x0002) ACC_PRIVATE
    Code:
      stack=1, locals=1, args_size=1
         0: aload_0
         1: getfield      #24                 // Field discoPanel:Ljavax/swing/JPanel;
         4: areturn
      LineNumberTable:
        line 35: 0
      LocalVariableTable:
        Start  Length  Slot  Name   Signature
            0       5     0  this   Lorg/scalatest/tools/ProgressBarPanel;

  private javax.swing.JLabel discoJLabel();
    descriptor: ()Ljavax/swing/JLabel;
    flags: (0x0002) ACC_PRIVATE
    Code:
      stack=1, locals=1, args_size=1
         0: aload_0
         1: getfield      #27                 // Field discoJLabel:Ljavax/swing/JLabel;
         4: areturn
      LineNumberTable:
        line 36: 0
      LocalVariableTable:
        Start  Length  Slot  Name   Signature
            0       5     0  this   Lorg/scalatest/tools/ProgressBarPanel;

  private java.net.URL discoImageURL();
    descriptor: ()Ljava/net/URL;
    flags: (0x0002) ACC_PRIVATE
    Code:
      stack=1, locals=1, args_size=1
         0: aload_0
         1: getfield      #30                 // Field discoImageURL:Ljava/net/URL;
         4: areturn
      LineNumberTable:
        line 37: 0
      LocalVariableTable:
        Start  Length  Slot  Name   Signature
            0       5     0  this   Lorg/scalatest/tools/ProgressBarPanel;

  public void discoveryStarting();
    descriptor: ()V
    flags: (0x0001) ACC_PUBLIC
    Code:
      stack=3, locals=1, args_size=1
         0: aload_0
         1: aload_0
         2: invokespecial #34                 // Method progressBar:()Lorg/scalatest/tools/ColorBar;
         5: invokevirtual #38                 // Method remove:(Ljava/awt/Component;)V
         8: aload_0
         9: aload_0
        10: invokespecial #40                 // Method discoPanel:()Ljavax/swing/JPanel;
        13: ldc           #42                 // String West
        15: invokevirtual #46                 // Method add:(Ljava/awt/Component;Ljava/lang/Object;)V
        18: aload_0
        19: invokespecial #48                 // Method discoJLabel:()Ljavax/swing/JLabel;
        22: ldc           #50                 // String
        24: invokevirtual #56                 // Method javax/swing/JLabel.setText:(Ljava/lang/String;)V
        27: aload_0
        28: invokespecial #48                 // Method discoJLabel:()Ljavax/swing/JLabel;
        31: getstatic     #62                 // Field org/scalatest/Resources$.MODULE$:Lorg/scalatest/Resources$;
        34: invokevirtual #66                 // Method org/scalatest/Resources$.doingDiscovery:()Ljava/lang/String;
        37: invokevirtual #56                 // Method javax/swing/JLabel.setText:(Ljava/lang/String;)V
        40: return
      LineNumberTable:
        line 60: 0
        line 61: 8
        line 64: 18
        line 65: 27
      LocalVariableTable:
        Start  Length  Slot  Name   Signature
            0      41     0  this   Lorg/scalatest/tools/ProgressBarPanel;

  private void showProgressBar();
    descriptor: ()V
    flags: (0x0002) ACC_PRIVATE
    Code:
      stack=3, locals=1, args_size=1
         0: aload_0
         1: aload_0
         2: invokespecial #40                 // Method discoPanel:()Ljavax/swing/JPanel;
         5: invokevirtual #38                 // Method remove:(Ljava/awt/Component;)V
         8: aload_0
         9: aload_0
        10: invokespecial #34                 // Method progressBar:()Lorg/scalatest/tools/ColorBar;
        13: ldc           #69                 // String Center
        15: invokevirtual #46                 // Method add:(Ljava/awt/Component;Ljava/lang/Object;)V
        18: return
      LineNumberTable:
        line 69: 0
        line 70: 8
      LocalVariableTable:
        Start  Length  Slot  Name   Signature
            0      19     0  this   Lorg/scalatest/tools/ProgressBarPanel;

  public void runAborted();
    descriptor: ()V
    flags: (0x0001) ACC_PUBLIC
    Code:
      stack=1, locals=1, args_size=1
         0: aload_0
         1: invokespecial #72                 // Method showProgressBar:()V
         4: aload_0
         5: invokespecial #34                 // Method progressBar:()Lorg/scalatest/tools/ColorBar;
         8: invokevirtual #77                 // Method org/scalatest/tools/ColorBar.setRed:()V
        11: return
      LineNumberTable:
        line 74: 0
        line 75: 4
      LocalVariableTable:
        Start  Length  Slot  Name   Signature
            0      12     0  this   Lorg/scalatest/tools/ProgressBarPanel;

  public void discoveryCompleted();
    descriptor: ()V
    flags: (0x0001) ACC_PUBLIC
    Code:
      stack=1, locals=1, args_size=1
         0: aload_0
         1: invokespecial #72                 // Method showProgressBar:()V
         4: return
      LineNumberTable:
        line 79: 0
      LocalVariableTable:
        Start  Length  Slot  Name   Signature
            0       5     0  this   Lorg/scalatest/tools/ProgressBarPanel;

  public void runStarting(int);
    descriptor: (I)V
    flags: (0x0001) ACC_PUBLIC
    Code:
      stack=2, locals=2, args_size=2
         0: aload_0
         1: invokespecial #34                 // Method progressBar:()Lorg/scalatest/tools/ColorBar;
         4: iload_1
         5: invokevirtual #84                 // Method org/scalatest/tools/ColorBar.setMax:(I)V
         8: aload_0
         9: invokespecial #34                 // Method progressBar:()Lorg/scalatest/tools/ColorBar;
        12: iconst_0
        13: invokevirtual #87                 // Method org/scalatest/tools/ColorBar.setValue:(I)V
        16: aload_0
        17: invokespecial #34                 // Method progressBar:()Lorg/scalatest/tools/ColorBar;
        20: invokevirtual #90                 // Method org/scalatest/tools/ColorBar.setGreen:()V
        23: return
      LineNumberTable:
        line 83: 0
        line 84: 8
        line 85: 16
      LocalVariableTable:
        Start  Length  Slot  Name   Signature
            0      24     0  this   Lorg/scalatest/tools/ProgressBarPanel;
            0      24     1 testCount   I
    MethodParameters:
      Name                           Flags
      testCount                      final

  public void setTestsRun(int);
    descriptor: (I)V
    flags: (0x0001) ACC_PUBLIC
    Code:
      stack=2, locals=2, args_size=2
         0: aload_0
         1: invokespecial #34                 // Method progressBar:()Lorg/scalatest/tools/ColorBar;
         4: iload_1
         5: invokevirtual #87                 // Method org/scalatest/tools/ColorBar.setValue:(I)V
         8: return
      LineNumberTable:
        line 89: 0
      LocalVariableTable:
        Start  Length  Slot  Name   Signature
            0       9     0  this   Lorg/scalatest/tools/ProgressBarPanel;
            0       9     1 testsCompletedCount   I
    MethodParameters:
      Name                           Flags
      testsCompletedCount            final

  public void suiteAborted();
    descriptor: ()V
    flags: (0x0001) ACC_PUBLIC
    Code:
      stack=1, locals=1, args_size=1
         0: aload_0
         1: invokespecial #34                 // Method progressBar:()Lorg/scalatest/tools/ColorBar;
         4: invokevirtual #77                 // Method org/scalatest/tools/ColorBar.setRed:()V
         7: return
      LineNumberTable:
        line 93: 0
      LocalVariableTable:
        Start  Length  Slot  Name   Signature
            0       8     0  this   Lorg/scalatest/tools/ProgressBarPanel;

  public void testFailed(int);
    descriptor: (I)V
    flags: (0x0001) ACC_PUBLIC
    Code:
      stack=2, locals=2, args_size=2
         0: aload_0
         1: invokespecial #34                 // Method progressBar:()Lorg/scalatest/tools/ColorBar;
         4: invokevirtual #77                 // Method org/scalatest/tools/ColorBar.setRed:()V
         7: aload_0
         8: iload_1
         9: invokevirtual #97                 // Method setTestsRun:(I)V
        12: return
      LineNumberTable:
        line 97: 0
        line 98: 7
      LocalVariableTable:
        Start  Length  Slot  Name   Signature
            0      13     0  this   Lorg/scalatest/tools/ProgressBarPanel;
            0      13     1 testsCompletedCount   I
    MethodParameters:
      Name                           Flags
      testsCompletedCount            final

  public void reset();
    descriptor: ()V
    flags: (0x0001) ACC_PUBLIC
    Code:
      stack=1, locals=1, args_size=1
         0: aload_0
         1: invokespecial #72                 // Method showProgressBar:()V
         4: aload_0
         5: invokespecial #34                 // Method progressBar:()Lorg/scalatest/tools/ColorBar;
         8: invokevirtual #101                // Method org/scalatest/tools/ColorBar.setGray:()V
        11: return
      LineNumberTable:
        line 102: 0
        line 103: 4
      LocalVariableTable:
        Start  Length  Slot  Name   Signature
            0      12     0  this   Lorg/scalatest/tools/ProgressBarPanel;

  public org.scalatest.tools.ProgressBarPanel();
    descriptor: ()V
    flags: (0x0001) ACC_PUBLIC
    Code:
      stack=6, locals=1, args_size=1
         0: aload_0
         1: invokespecial #104                // Method javax/swing/JPanel."<init>":()V
         4: aload_0
         5: new           #74                 // class org/scalatest/tools/ColorBar
         8: dup
         9: invokespecial #105                // Method org/scalatest/tools/ColorBar."<init>":()V
        12: putfield      #19                 // Field progressBar:Lorg/scalatest/tools/ColorBar;
        15: aload_0
        16: new           #4                  // class javax/swing/JPanel
        19: dup
        20: invokespecial #104                // Method javax/swing/JPanel."<init>":()V
        23: putfield      #24                 // Field discoPanel:Ljavax/swing/JPanel;
        26: aload_0
        27: new           #52                 // class javax/swing/JLabel
        30: dup
        31: invokespecial #106                // Method javax/swing/JLabel."<init>":()V
        34: putfield      #27                 // Field discoJLabel:Ljavax/swing/JLabel;
        37: aload_0
        38: aload_0
        39: invokevirtual #110                // Method getClass:()Ljava/lang/Class;
        42: invokevirtual #116                // Method java/lang/Class.getClassLoader:()Ljava/lang/ClassLoader;
        45: ldc           #118                // String images/inProgress.gif
        47: invokevirtual #124                // Method java/lang/ClassLoader.getResource:(Ljava/lang/String;)Ljava/net/URL;
        50: putfield      #30                 // Field discoImageURL:Ljava/net/URL;
        53: aload_0
        54: new           #126                // class java/awt/BorderLayout
        57: dup
        58: invokespecial #127                // Method java/awt/BorderLayout."<init>":()V
        61: invokevirtual #131                // Method setLayout:(Ljava/awt/LayoutManager;)V
        64: aload_0
        65: new           #133                // class javax/swing/border/BevelBorder
        68: dup
        69: iconst_1
        70: invokespecial #135                // Method javax/swing/border/BevelBorder."<init>":(I)V
        73: invokevirtual #139                // Method setBorder:(Ljavax/swing/border/Border;)V
        76: aload_0
        77: aload_0
        78: invokespecial #34                 // Method progressBar:()Lorg/scalatest/tools/ColorBar;
        81: ldc           #69                 // String Center
        83: invokevirtual #46                 // Method add:(Ljava/awt/Component;Ljava/lang/Object;)V
        86: aload_0
        87: invokespecial #48                 // Method discoJLabel:()Ljavax/swing/JLabel;
        90: new           #141                // class javax/swing/ImageIcon
        93: dup
        94: aload_0
        95: invokespecial #143                // Method discoImageURL:()Ljava/net/URL;
        98: invokespecial #146                // Method javax/swing/ImageIcon."<init>":(Ljava/net/URL;)V
       101: invokevirtual #150                // Method javax/swing/JLabel.setIcon:(Ljavax/swing/Icon;)V
       104: aload_0
       105: invokespecial #40                 // Method discoPanel:()Ljavax/swing/JPanel;
       108: aload_0
       109: invokespecial #48                 // Method discoJLabel:()Ljavax/swing/JLabel;
       112: invokevirtual #153                // Method javax/swing/JPanel.add:(Ljava/awt/Component;)Ljava/awt/Component;
       115: pop
       116: aload_0
       117: new           #155                // class java/awt/Dimension
       120: dup
       121: aload_0
       122: invokevirtual #159                // Method getPreferredSize:()Ljava/awt/Dimension;
       125: invokevirtual #163                // Method java/awt/Dimension.getWidth:()D
       128: d2i
       129: aload_0
       130: invokespecial #40                 // Method discoPanel:()Ljavax/swing/JPanel;
       133: invokevirtual #164                // Method javax/swing/JPanel.getPreferredSize:()Ljava/awt/Dimension;
       136: invokevirtual #167                // Method java/awt/Dimension.getHeight:()D
       139: d2i
       140: iconst_4
       141: iadd
       142: invokespecial #170                // Method java/awt/Dimension."<init>":(II)V
       145: invokevirtual #174                // Method setPreferredSize:(Ljava/awt/Dimension;)V
       148: return
      LineNumberTable:
        line 33: 0
        line 34: 4
        line 35: 15
        line 36: 26
        line 37: 37
        line 38: 38
        line 37: 50
        line 40: 53
        line 41: 64
        line 42: 76
        line 44: 86
        line 45: 104
        line 51: 116
        line 52: 117
        line 53: 121
        line 54: 129
        line 33: 148
      LocalVariableTable:
        Start  Length  Slot  Name   Signature
            0     149     0  this   Lorg/scalatest/tools/ProgressBarPanel;
}
SourceFile: "ProgressBarPanel.scala"
RuntimeVisibleAnnotations:
  0: #6(#7=s#8)
    scala.reflect.ScalaSignature(
      bytes="\u0006\u0005u3Qa\u0005\u000b\u0001-iAQa\t\u0001\u0005\u0002\u0015Bq\u0001\u000b\u0001C\u0002\u0013%\u0011\u0006\u0003\u0004.\u0001\u0001\u0006IA\u000b\u0005\b]\u0001\u0011\r\u0011\"\u00030\u0011\u0019\u0001\u0004\u0001)A\u00057!9\u0011\u0007\u0001b\u0001\n\u0013\u0011\u0004B\u0002\u001c\u0001A\u0003%1\u0007C\u00048\u0001\t\u0007I\u0011\u0002\u001d\t\r\u0005\u0003\u0001\u0015!\u0003:\u0011\u0015\u0011\u0005\u0001\"\u0001D\u0011\u0015Q\u0005\u0001\"\u0003D\u0011\u0015Y\u0005\u0001\"\u0001D\u0011\u0015a\u0005\u0001\"\u0001D\u0011\u0015i\u0005\u0001\"\u0001O\u0011\u0015!\u0006\u0001\"\u0001V\u0011\u0015A\u0006\u0001\"\u0001D\u0011\u0015I\u0006\u0001\"\u0001[\u0011\u0015a\u0006\u0001\"\u0001D\u0005A\u0001&o\\4sKN\u001c()\u0019:QC:,GN\u0003\u0002\u0016-\u0005)Ao\\8mg*\u0011q\u0003G\u0001\ng\u000e\fG.\u0019;fgRT\u0011!G\u0001\u0004_J<7C\u0001\u0001\u001c!\ta\u0012%D\u0001\u001e\u0015\tqr$A\u0003to&twMC\u0001!\u0003\u0015Q\u0017M^1y\u0013\t\u0011SD\u0001\u0004K!\u0006tW\r\\\u0001\u0007y%t\u0017\u000e\u001e \u0004\u0001Q\ta\u0005\u0005\u0002(\u00015\tA#A\u0006qe><\'/Z:t\u0005\u0006\u0014X#\u0001\u0016\u0011\u0005\u001dZ\u0013B\u0001\u0017\u0015\u0005!\u0019u\u000e\\8s\u0005\u0006\u0014\u0018\u0001\u00049s_\u001e\u0014Xm]:CCJ\u0004\u0013A\u00033jg\u000e|\u0007+\u00198fYV\t1$A\u0006eSN\u001cw\u000eU1oK2\u0004\u0013a\u00033jg\u000e|\'\nT1cK2,\u0012a\r\t\u00039QJ!!N\u000f\u0003\r)c\u0015MY3m\u00031!\u0017n]2p\u00152\u000b\'-\u001a7!\u00035!\u0017n]2p\u00136\fw-Z+S\u0019V\t\u0011\b\u0005\u0002;\u007f5\t1H\u0003\u0002={\u0005\u0019a.\u001a;\u000b\u0003y\nAA[1wC&\u0011\u0001i\u000f\u0002\u0004+Jc\u0015A\u00043jg\u000e|\u0017*\\1hKV\u0013F\nI\u0001\u0012I&\u001c8m\u001c<fef\u001cF/\u0019:uS:<G#\u0001#\u0011\u0005\u0015CU\"\u0001$\u000b\u0003\u001d\u000bQa]2bY\u0006L!!\u0013$\u0003\tUs\u0017\u000e^\u0001\u0010g\"|w\u000f\u0015:pOJ,7o\u001d\"be\u0006Q!/\u001e8BE>\u0014H/\u001a3\u0002%\u0011L7oY8wKJL8i\\7qY\u0016$X\rZ\u0001\feVt7\u000b^1si&tw\r\u0006\u0002E\u001f\")\u0001K\u0004a\u0001#\u0006IA/Z:u\u0007>,h\u000e\u001e\t\u0003\u000bJK!a\u0015$\u0003\u0007%sG/A\u0006tKR$Vm\u001d;t%VtGC\u0001#W\u0011\u00159v\u00021\u0001R\u0003M!Xm\u001d;t\u0007>l\u0007\u000f\\3uK\u0012\u001cu.\u001e8u\u00031\u0019X/\u001b;f\u0003\n|\'\u000f^3e\u0003)!Xm\u001d;GC&dW\r\u001a\u000b\u0003\tnCQaV\tA\u0002E\u000bQA]3tKR\u0004"
    )
  ScalaInlineInfo: length = 0x4A (unknown attribute)
   01 00 00 0E 00 66 00 20 00 00 0F 00 1C 01 00 0D
   00 19 01 00 0B 00 16 01 00 4E 00 20 00 00 1F 00
   20 00 00 09 00 11 01 00 62 00 20 00 00 46 00 20
   00 00 4F 00 50 00 00 5C 00 50 00 00 43 00 20 01
   00 5E 00 20 00 00 5F 00 50 00
  ScalaSig: length = 0x3 (unknown attribute)
   05 02 00
