Classfile /Users/mw/Projects/slang-braindump/.jar/jar8/assemble/slang-braindump/assemble/content/org/scalatest/tools/ReporterConfigParam.class
  Last modified May 29, 2022; size 2720 bytes
  SHA-256 checksum b85f4dcccecf1a058781bf93e23892780c23db90acf0825d942cbe4a2df74f8b
  Compiled from "ReporterConfigParam.scala"
public abstract class org.scalatest.tools.ReporterConfigParam implements scala.Product,java.io.Serializable
  minor version: 0
  major version: 52
  flags: (0x0421) ACC_PUBLIC, ACC_SUPER, ACC_ABSTRACT
  this_class: #2                          // org/scalatest/tools/ReporterConfigParam
  super_class: #4                         // java/lang/Object
  interfaces: 2, fields: 1, methods: 6, attributes: 4
Constant pool:
   #1 = Utf8               org/scalatest/tools/ReporterConfigParam
   #2 = Class              #1             // org/scalatest/tools/ReporterConfigParam
   #3 = Utf8               java/lang/Object
   #4 = Class              #3             // java/lang/Object
   #5 = Utf8               scala/Product
   #6 = Class              #5             // scala/Product
   #7 = Utf8               java/io/Serializable
   #8 = Class              #7             // java/io/Serializable
   #9 = Utf8               ReporterConfigParam.scala
  #10 = Utf8               Lscala/reflect/ScalaSignature;
  #11 = Utf8               bytes
  #12 = Utf8               \u0006\u0005\u00154a\u0001B\u0003\u0002\"\u0015Y\u0001\u0002\u0003\u0012\u0001\u0005\u000b\u0007I\u0011A\u0012\t\u00111\u0002!\u0011!Q\u0001\n\u0011BQ!\f\u0001\u0005\u00029\u00121CU3q_J$XM]\"p]\u001aLw\rU1sC6T!AB\u0004\u0002\u000bQ|w\u000e\\:\u000b\u0005!I\u0011!C:dC2\fG/Z:u\u0015\u0005Q\u0011aA8sON!\u0001\u0001\u0004\n\u0016!\ti\u0001#D\u0001\u000f\u0015\u0005y\u0011!B:dC2\f\u0017BA\t\u000f\u0005\u0019\te.\u001f*fMB\u0011QbE\u0005\u0003)9\u0011q\u0001\u0015:pIV\u001cG\u000f\u0005\u0002\u0017?9\u0011q#\b\b\u00031qi\u0011!\u0007\u0006\u00035m\ta\u0001\u0010:p_Rt4\u0001A\u0005\u0002\u001f%\u0011aDD\u0001\ba\u0006\u001c7.Y4f\u0013\t\u0001\u0013E\u0001\u0007TKJL\u0017\r\\5{C\ndWM\u0003\u0002\u001f\u001d\u0005I1\r[1sC\u000e$XM]\u000b\u0002IA\u0011Q%\u000b\b\u0003M\u001d\u0002\"\u0001\u0007\b\n\u0005!r\u0011A\u0002)sK\u0012,g-\u0003\u0002+W\t11\u000b\u001e:j]\u001eT!\u0001\u000b\b\u0002\u0015\rD\u0017M]1di\u0016\u0014\b%\u0001\u0004=S:LGO\u0010\u000b\u0003_E\u0002\"\u0001\r\u0001\u000e\u0003\u0015AQAI\u0002A\u0002\u0011J#\u0004A\u001a6oeZThP!D\u000b\u001eK5*T(R\'V;\u0016lW/`C\u000eT!\u0001N\u0003\u0002\'\u0019KG\u000e^3s\u00032,\'\u000f\u001e)s_ZLG-\u001a3\u000b\u0005Y*\u0011A\u0005$jYR,\'/\u00138g_B\u0013xN^5eK\u0012T!\u0001O\u0003\u0002)\u0019KG\u000e^3s\u001b\u0006\u00148.\u001e9Qe>4\u0018\u000eZ3e\u0015\tQT!\u0001\nGS2$XM\u001d(pi\u0016\u0004&o\u001c<jI\u0016$\'B\u0001\u001f\u0006\u0003E1\u0015\u000e\u001c;feN\u001bw\u000e]3DY>\u001cX\r\u001a\u0006\u0003}\u0015\t\u0011CR5mi\u0016\u00148kY8qK>\u0003XM\\3e\u0015\t\u0001U!\u0001\nGS2$XM]*d_B,\u0007+\u001a8eS:<\'B\u0001\"\u0006\u0003Q1\u0015\u000e\u001c;feN+\u0018\u000e^3D_6\u0004H.\u001a;fI*\u0011A)B\u0001\u0014\r&dG/\u001a:Tk&$Xm\u0015;beRLgn\u001a\u0006\u0003\r\u0016\t!CR5mi\u0016\u0014H+Z:u\u0007\u0006t7-\u001a7fI*\u0011\u0001*B\u0001\u0012\r&dG/\u001a:UKN$\u0018j\u001a8pe\u0016$\'B\u0001&\u0006\u0003E1\u0015\u000e\u001c;feR+7\u000f\u001e)f]\u0012Lgn\u001a\u0006\u0003\u0019\u0016\t!CR5mi\u0016\u0014H+Z:u\'R\f\'\u000f^5oO*\u0011a*B\u0001\u0014\r&dG/\u001a:UKN$8+^2dK\u0016$W\r\u001a\u0006\u0003!\u0016\t1\u0003\u0015:fg\u0016tG/\u00117m\tV\u0014\u0018\r^5p]NT!AU\u0003\u0002\'A\u0013Xm]3oi\u001aKG.\u001a)bi\"t\u0017-\\3\u000b\u0005Q+\u0011A\u0006)sKN,g\u000e\u001e$vY2\u001cF/Y2l)J\f7-Z:\u000b\u0005Y+\u0011a\u0003)sKN,g\u000e\u001e&t_:T!\u0001W\u0003\u0002EA\u0013Xm]3oiJ+W.\u001b8eKJ<\u0016\u000e\u001e5Gk2d7\u000b^1dWR\u0013\u0018mY3t\u0015\tQV!A\u0012Qe\u0016\u001cXM\u001c;SK6Lg\u000eZ3s/&$\bn\u00155peR\u001cF/Y2l)J\f7-Z:\u000b\u0005q+\u0011a\t)sKN,g\u000e\u001e*f[&tG-\u001a:XSRDw.\u001e;DC:\u001cW\r\\3e)\u0016\u001cHo\u001d\u0006\u0003=\u0016\t\u0011\u0005\u0015:fg\u0016tGOU3nS:$WM],ji\"|W\u000f^*uC\u000e\\GK]1dKNT!\u0001Y\u0003\u0002/A\u0013Xm]3oiNCwN\u001d;Ti\u0006\u001c7\u000e\u0016:bG\u0016\u001c(B\u00012\u0006\u0003I\u0001&/Z:f]R,fNZ8s[\u0006$H/\u001a3\u000b\u0005\u0011,\u0011a\u0005)sKN,g\u000e^,ji\"|W\u000f^\"pY>\u0014\b
  #13 = Utf8               character
  #14 = Utf8               Ljava/lang/String;
  #15 = Utf8               productIterator
  #16 = Utf8               ()Lscala/collection/Iterator;
  #17 = Utf8               ()Lscala/collection/Iterator<Ljava/lang/Object;>;
  #18 = Utf8               productIterator$
  #19 = Utf8               (Lscala/Product;)Lscala/collection/Iterator;
  #20 = NameAndType        #18:#19        // productIterator$:(Lscala/Product;)Lscala/collection/Iterator;
  #21 = InterfaceMethodref #6.#20         // scala/Product.productIterator$:(Lscala/Product;)Lscala/collection/Iterator;
  #22 = Utf8               this
  #23 = Utf8               Lorg/scalatest/tools/ReporterConfigParam;
  #24 = Utf8               productPrefix
  #25 = Utf8               ()Ljava/lang/String;
  #26 = Utf8               productPrefix$
  #27 = Utf8               (Lscala/Product;)Ljava/lang/String;
  #28 = NameAndType        #26:#27        // productPrefix$:(Lscala/Product;)Ljava/lang/String;
  #29 = InterfaceMethodref #6.#28         // scala/Product.productPrefix$:(Lscala/Product;)Ljava/lang/String;
  #30 = Utf8               productElementName
  #31 = Utf8               (I)Ljava/lang/String;
  #32 = Utf8               n
  #33 = Utf8               productElementName$
  #34 = Utf8               (Lscala/Product;I)Ljava/lang/String;
  #35 = NameAndType        #33:#34        // productElementName$:(Lscala/Product;I)Ljava/lang/String;
  #36 = InterfaceMethodref #6.#35         // scala/Product.productElementName$:(Lscala/Product;I)Ljava/lang/String;
  #37 = Utf8               I
  #38 = Utf8               productElementNames
  #39 = Utf8               ()Lscala/collection/Iterator<Ljava/lang/String;>;
  #40 = Utf8               productElementNames$
  #41 = NameAndType        #40:#19        // productElementNames$:(Lscala/Product;)Lscala/collection/Iterator;
  #42 = InterfaceMethodref #6.#41         // scala/Product.productElementNames$:(Lscala/Product;)Lscala/collection/Iterator;
  #43 = NameAndType        #13:#14        // character:Ljava/lang/String;
  #44 = Fieldref           #2.#43         // org/scalatest/tools/ReporterConfigParam.character:Ljava/lang/String;
  #45 = Utf8               <init>
  #46 = Utf8               (Ljava/lang/String;)V
  #47 = Utf8               ()V
  #48 = NameAndType        #45:#47        // "<init>":()V
  #49 = Methodref          #4.#48         // java/lang/Object."<init>":()V
  #50 = Utf8               $init$
  #51 = Utf8               (Lscala/Product;)V
  #52 = NameAndType        #50:#51        // $init$:(Lscala/Product;)V
  #53 = InterfaceMethodref #6.#52         // scala/Product.$init$:(Lscala/Product;)V
  #54 = Utf8               Code
  #55 = Utf8               LineNumberTable
  #56 = Utf8               LocalVariableTable
  #57 = Utf8               Signature
  #58 = Utf8               MethodParameters
  #59 = Utf8               SourceFile
  #60 = Utf8               RuntimeVisibleAnnotations
  #61 = Utf8               ScalaInlineInfo
  #62 = Utf8               ScalaSig
{
  private final java.lang.String character;
    descriptor: Ljava/lang/String;
    flags: (0x0012) ACC_PRIVATE, ACC_FINAL

  public scala.collection.Iterator<java.lang.Object> productIterator();
    descriptor: ()Lscala/collection/Iterator;
    flags: (0x0001) ACC_PUBLIC
    Code:
      stack=1, locals=1, args_size=1
         0: aload_0
         1: invokestatic  #21                 // InterfaceMethod scala/Product.productIterator$:(Lscala/Product;)Lscala/collection/Iterator;
         4: areturn
      LineNumberTable:
        line 19: 0
      LocalVariableTable:
        Start  Length  Slot  Name   Signature
            0       5     0  this   Lorg/scalatest/tools/ReporterConfigParam;
    Signature: #17                          // ()Lscala/collection/Iterator<Ljava/lang/Object;>;

  public java.lang.String productPrefix();
    descriptor: ()Ljava/lang/String;
    flags: (0x0001) ACC_PUBLIC
    Code:
      stack=1, locals=1, args_size=1
         0: aload_0
         1: invokestatic  #29                 // InterfaceMethod scala/Product.productPrefix$:(Lscala/Product;)Ljava/lang/String;
         4: areturn
      LineNumberTable:
        line 19: 0
      LocalVariableTable:
        Start  Length  Slot  Name   Signature
            0       5     0  this   Lorg/scalatest/tools/ReporterConfigParam;

  public java.lang.String productElementName(int);
    descriptor: (I)Ljava/lang/String;
    flags: (0x0001) ACC_PUBLIC
    Code:
      stack=2, locals=2, args_size=2
         0: aload_0
         1: iload_1
         2: invokestatic  #36                 // InterfaceMethod scala/Product.productElementName$:(Lscala/Product;I)Ljava/lang/String;
         5: areturn
      LineNumberTable:
        line 19: 0
      LocalVariableTable:
        Start  Length  Slot  Name   Signature
            0       6     0  this   Lorg/scalatest/tools/ReporterConfigParam;
            0       6     1     n   I
    MethodParameters:
      Name                           Flags
      n                              final

  public scala.collection.Iterator<java.lang.String> productElementNames();
    descriptor: ()Lscala/collection/Iterator;
    flags: (0x0001) ACC_PUBLIC
    Code:
      stack=1, locals=1, args_size=1
         0: aload_0
         1: invokestatic  #42                 // InterfaceMethod scala/Product.productElementNames$:(Lscala/Product;)Lscala/collection/Iterator;
         4: areturn
      LineNumberTable:
        line 19: 0
      LocalVariableTable:
        Start  Length  Slot  Name   Signature
            0       5     0  this   Lorg/scalatest/tools/ReporterConfigParam;
    Signature: #39                          // ()Lscala/collection/Iterator<Ljava/lang/String;>;

  public java.lang.String character();
    descriptor: ()Ljava/lang/String;
    flags: (0x0001) ACC_PUBLIC
    Code:
      stack=1, locals=1, args_size=1
         0: aload_0
         1: getfield      #44                 // Field character:Ljava/lang/String;
         4: areturn
      LineNumberTable:
        line 19: 0
      LocalVariableTable:
        Start  Length  Slot  Name   Signature
            0       5     0  this   Lorg/scalatest/tools/ReporterConfigParam;

  public org.scalatest.tools.ReporterConfigParam(java.lang.String);
    descriptor: (Ljava/lang/String;)V
    flags: (0x0001) ACC_PUBLIC
    Code:
      stack=2, locals=2, args_size=2
         0: aload_0
         1: aload_1
         2: putfield      #44                 // Field character:Ljava/lang/String;
         5: aload_0
         6: invokespecial #49                 // Method java/lang/Object."<init>":()V
         9: aload_0
        10: invokestatic  #53                 // InterfaceMethod scala/Product.$init$:(Lscala/Product;)V
        13: return
      LineNumberTable:
        line 19: 0
      LocalVariableTable:
        Start  Length  Slot  Name   Signature
            0      14     0  this   Lorg/scalatest/tools/ReporterConfigParam;
            0      14     1 character   Ljava/lang/String;
    MethodParameters:
      Name                           Flags
      character                      final
}
SourceFile: "ReporterConfigParam.scala"
RuntimeVisibleAnnotations:
  0: #10(#11=s#12)
    scala.reflect.ScalaSignature(
      bytes="\u0006\u0005\u00154a\u0001B\u0003\u0002\"\u0015Y\u0001\u0002\u0003\u0012\u0001\u0005\u000b\u0007I\u0011A\u0012\t\u00111\u0002!\u0011!Q\u0001\n\u0011BQ!\f\u0001\u0005\u00029\u00121CU3q_J$XM]\"p]\u001aLw\rU1sC6T!AB\u0004\u0002\u000bQ|w\u000e\\:\u000b\u0005!I\u0011!C:dC2\fG/Z:u\u0015\u0005Q\u0011aA8sON!\u0001\u0001\u0004\n\u0016!\ti\u0001#D\u0001\u000f\u0015\u0005y\u0011!B:dC2\f\u0017BA\t\u000f\u0005\u0019\te.\u001f*fMB\u0011QbE\u0005\u0003)9\u0011q\u0001\u0015:pIV\u001cG\u000f\u0005\u0002\u0017?9\u0011q#\b\b\u00031qi\u0011!\u0007\u0006\u00035m\ta\u0001\u0010:p_Rt4\u0001A\u0005\u0002\u001f%\u0011aDD\u0001\ba\u0006\u001c7.Y4f\u0013\t\u0001\u0013E\u0001\u0007TKJL\u0017\r\\5{C\ndWM\u0003\u0002\u001f\u001d\u0005I1\r[1sC\u000e$XM]\u000b\u0002IA\u0011Q%\u000b\b\u0003M\u001d\u0002\"\u0001\u0007\b\n\u0005!r\u0011A\u0002)sK\u0012,g-\u0003\u0002+W\t11\u000b\u001e:j]\u001eT!\u0001\u000b\b\u0002\u0015\rD\u0017M]1di\u0016\u0014\b%\u0001\u0004=S:LGO\u0010\u000b\u0003_E\u0002\"\u0001\r\u0001\u000e\u0003\u0015AQAI\u0002A\u0002\u0011J#\u0004A\u001a6oeZThP!D\u000b\u001eK5*T(R\'V;\u0016lW/`C\u000eT!\u0001N\u0003\u0002\'\u0019KG\u000e^3s\u00032,\'\u000f\u001e)s_ZLG-\u001a3\u000b\u0005Y*\u0011A\u0005$jYR,\'/\u00138g_B\u0013xN^5eK\u0012T!\u0001O\u0003\u0002)\u0019KG\u000e^3s\u001b\u0006\u00148.\u001e9Qe>4\u0018\u000eZ3e\u0015\tQT!\u0001\nGS2$XM\u001d(pi\u0016\u0004&o\u001c<jI\u0016$\'B\u0001\u001f\u0006\u0003E1\u0015\u000e\u001c;feN\u001bw\u000e]3DY>\u001cX\r\u001a\u0006\u0003}\u0015\t\u0011CR5mi\u0016\u00148kY8qK>\u0003XM\\3e\u0015\t\u0001U!\u0001\nGS2$XM]*d_B,\u0007+\u001a8eS:<\'B\u0001\"\u0006\u0003Q1\u0015\u000e\u001c;feN+\u0018\u000e^3D_6\u0004H.\u001a;fI*\u0011A)B\u0001\u0014\r&dG/\u001a:Tk&$Xm\u0015;beRLgn\u001a\u0006\u0003\r\u0016\t!CR5mi\u0016\u0014H+Z:u\u0007\u0006t7-\u001a7fI*\u0011\u0001*B\u0001\u0012\r&dG/\u001a:UKN$\u0018j\u001a8pe\u0016$\'B\u0001&\u0006\u0003E1\u0015\u000e\u001c;feR+7\u000f\u001e)f]\u0012Lgn\u001a\u0006\u0003\u0019\u0016\t!CR5mi\u0016\u0014H+Z:u\'R\f\'\u000f^5oO*\u0011a*B\u0001\u0014\r&dG/\u001a:UKN$8+^2dK\u0016$W\r\u001a\u0006\u0003!\u0016\t1\u0003\u0015:fg\u0016tG/\u00117m\tV\u0014\u0018\r^5p]NT!AU\u0003\u0002\'A\u0013Xm]3oi\u001aKG.\u001a)bi\"t\u0017-\\3\u000b\u0005Q+\u0011A\u0006)sKN,g\u000e\u001e$vY2\u001cF/Y2l)J\f7-Z:\u000b\u0005Y+\u0011a\u0003)sKN,g\u000e\u001e&t_:T!\u0001W\u0003\u0002EA\u0013Xm]3oiJ+W.\u001b8eKJ<\u0016\u000e\u001e5Gk2d7\u000b^1dWR\u0013\u0018mY3t\u0015\tQV!A\u0012Qe\u0016\u001cXM\u001c;SK6Lg\u000eZ3s/&$\bn\u00155peR\u001cF/Y2l)J\f7-Z:\u000b\u0005q+\u0011a\t)sKN,g\u000e\u001e*f[&tG-\u001a:XSRDw.\u001e;DC:\u001cW\r\\3e)\u0016\u001cHo\u001d\u0006\u0003=\u0016\t\u0011\u0005\u0015:fg\u0016tGOU3nS:$WM],ji\"|W\u000f^*uC\u000e\\GK]1dKNT!\u0001Y\u0003\u0002/A\u0013Xm]3oiNCwN\u001d;Ti\u0006\u001c7\u000e\u0016:bG\u0016\u001c(B\u00012\u0006\u0003I\u0001&/Z:f]R,fNZ8s[\u0006$H/\u001a3\u000b\u0005\u0011,\u0011a\u0005)sKN,g\u000e^,ji\"|W\u000f^\"pY>\u0014\b"
    )
  ScalaInlineInfo: length = 0x22 (unknown attribute)
   01 00 00 06 00 2D 00 2E 01 00 0D 00 19 01 00 1E
   00 1F 01 00 26 00 10 01 00 0F 00 10 00 00 18 00
   19 00
  ScalaSig: length = 0x3 (unknown attribute)
   05 02 00
