Classfile /Users/mw/Projects/slang-braindump/.jar/jar8/assemble/slang-braindump/assemble/content/org/scalatest/tools/RunnerJFrame$.class
  Last modified May 29, 2022; size 8737 bytes
  SHA-256 checksum 5d83242f66e2eb013c09730375401bcb8f3c913f02d0c78199161b53565342b5
  Compiled from "RunnerJFrame.scala"
public final class org.scalatest.tools.RunnerJFrame$ implements java.io.Serializable
  minor version: 0
  major version: 52
  flags: (0x0031) ACC_PUBLIC, ACC_FINAL, ACC_SUPER
  this_class: #2                          // org/scalatest/tools/RunnerJFrame$
  super_class: #4                         // java/lang/Object
  interfaces: 1, fields: 1, methods: 7, attributes: 3
Constant pool:
    #1 = Utf8               org/scalatest/tools/RunnerJFrame$
    #2 = Class              #1            // org/scalatest/tools/RunnerJFrame$
    #3 = Utf8               java/lang/Object
    #4 = Class              #3            // java/lang/Object
    #5 = Utf8               java/io/Serializable
    #6 = Class              #5            // java/io/Serializable
    #7 = Utf8               RunnerJFrame.scala
    #8 = Utf8               MODULE$
    #9 = Utf8               Lorg/scalatest/tools/RunnerJFrame$;
   #10 = Utf8               <clinit>
   #11 = Utf8               ()V
   #12 = Utf8               <init>
   #13 = NameAndType        #12:#11       // "<init>":()V
   #14 = Methodref          #2.#13        // org/scalatest/tools/RunnerJFrame$."<init>":()V
   #15 = NameAndType        #8:#9         // MODULE$:Lorg/scalatest/tools/RunnerJFrame$;
   #16 = Fieldref           #2.#15        // org/scalatest/tools/RunnerJFrame$.MODULE$:Lorg/scalatest/tools/RunnerJFrame$;
   #17 = Utf8               getUpperCaseName
   #18 = Utf8               (Lorg/scalatest/events/Event;)Ljava/lang/String;
   #19 = Utf8               event
   #20 = Utf8               org/scalatest/tools/EventToPresent$
   #21 = Class              #20           // org/scalatest/tools/EventToPresent$
   #22 = Utf8               Lorg/scalatest/tools/EventToPresent$;
   #23 = NameAndType        #8:#22        // MODULE$:Lorg/scalatest/tools/EventToPresent$;
   #24 = Fieldref           #21.#23       // org/scalatest/tools/EventToPresent$.MODULE$:Lorg/scalatest/tools/EventToPresent$;
   #25 = Utf8               eventToEventToPresent
   #26 = Utf8               (Lorg/scalatest/events/Event;)Lorg/scalatest/tools/EventToPresent;
   #27 = NameAndType        #25:#26       // eventToEventToPresent:(Lorg/scalatest/events/Event;)Lorg/scalatest/tools/EventToPresent;
   #28 = Methodref          #21.#27       // org/scalatest/tools/EventToPresent$.eventToEventToPresent:(Lorg/scalatest/events/Event;)Lorg/scalatest/tools/EventToPresent;
   #29 = Utf8               (Lorg/scalatest/tools/EventToPresent;)Ljava/lang/String;
   #30 = NameAndType        #17:#29       // getUpperCaseName:(Lorg/scalatest/tools/EventToPresent;)Ljava/lang/String;
   #31 = Methodref          #2.#30        // org/scalatest/tools/RunnerJFrame$.getUpperCaseName:(Lorg/scalatest/tools/EventToPresent;)Ljava/lang/String;
   #32 = Utf8               this
   #33 = Utf8               Lorg/scalatest/events/Event;
   #34 = Utf8               eventToPresent
   #35 = Utf8               org/scalatest/tools/PresentDiscoveryStarting$
   #36 = Class              #35           // org/scalatest/tools/PresentDiscoveryStarting$
   #37 = Utf8               Lorg/scalatest/tools/PresentDiscoveryStarting$;
   #38 = NameAndType        #8:#37        // MODULE$:Lorg/scalatest/tools/PresentDiscoveryStarting$;
   #39 = Fieldref           #36.#38       // org/scalatest/tools/PresentDiscoveryStarting$.MODULE$:Lorg/scalatest/tools/PresentDiscoveryStarting$;
   #40 = Utf8               equals
   #41 = Utf8               (Ljava/lang/Object;)Z
   #42 = NameAndType        #40:#41       // equals:(Ljava/lang/Object;)Z
   #43 = Methodref          #4.#42        // java/lang/Object.equals:(Ljava/lang/Object;)Z
   #44 = Utf8               DISCOVERY_STARTING
   #45 = String             #44           // DISCOVERY_STARTING
   #46 = Utf8               org/scalatest/tools/PresentDiscoveryCompleted$
   #47 = Class              #46           // org/scalatest/tools/PresentDiscoveryCompleted$
   #48 = Utf8               Lorg/scalatest/tools/PresentDiscoveryCompleted$;
   #49 = NameAndType        #8:#48        // MODULE$:Lorg/scalatest/tools/PresentDiscoveryCompleted$;
   #50 = Fieldref           #47.#49       // org/scalatest/tools/PresentDiscoveryCompleted$.MODULE$:Lorg/scalatest/tools/PresentDiscoveryCompleted$;
   #51 = Utf8               DISCOVERY_COMPLETED
   #52 = String             #51           // DISCOVERY_COMPLETED
   #53 = Utf8               org/scalatest/tools/PresentRunStarting$
   #54 = Class              #53           // org/scalatest/tools/PresentRunStarting$
   #55 = Utf8               Lorg/scalatest/tools/PresentRunStarting$;
   #56 = NameAndType        #8:#55        // MODULE$:Lorg/scalatest/tools/PresentRunStarting$;
   #57 = Fieldref           #54.#56       // org/scalatest/tools/PresentRunStarting$.MODULE$:Lorg/scalatest/tools/PresentRunStarting$;
   #58 = Utf8               RUN_STARTING
   #59 = String             #58           // RUN_STARTING
   #60 = Utf8               org/scalatest/tools/PresentTestStarting$
   #61 = Class              #60           // org/scalatest/tools/PresentTestStarting$
   #62 = Utf8               Lorg/scalatest/tools/PresentTestStarting$;
   #63 = NameAndType        #8:#62        // MODULE$:Lorg/scalatest/tools/PresentTestStarting$;
   #64 = Fieldref           #61.#63       // org/scalatest/tools/PresentTestStarting$.MODULE$:Lorg/scalatest/tools/PresentTestStarting$;
   #65 = Utf8               TEST_STARTING
   #66 = String             #65           // TEST_STARTING
   #67 = Utf8               org/scalatest/tools/PresentTestFailed$
   #68 = Class              #67           // org/scalatest/tools/PresentTestFailed$
   #69 = Utf8               Lorg/scalatest/tools/PresentTestFailed$;
   #70 = NameAndType        #8:#69        // MODULE$:Lorg/scalatest/tools/PresentTestFailed$;
   #71 = Fieldref           #68.#70       // org/scalatest/tools/PresentTestFailed$.MODULE$:Lorg/scalatest/tools/PresentTestFailed$;
   #72 = Utf8               TEST_FAILED
   #73 = String             #72           // TEST_FAILED
   #74 = Utf8               org/scalatest/tools/PresentTestSucceeded$
   #75 = Class              #74           // org/scalatest/tools/PresentTestSucceeded$
   #76 = Utf8               Lorg/scalatest/tools/PresentTestSucceeded$;
   #77 = NameAndType        #8:#76        // MODULE$:Lorg/scalatest/tools/PresentTestSucceeded$;
   #78 = Fieldref           #75.#77       // org/scalatest/tools/PresentTestSucceeded$.MODULE$:Lorg/scalatest/tools/PresentTestSucceeded$;
   #79 = Utf8               TEST_SUCCEEDED
   #80 = String             #79           // TEST_SUCCEEDED
   #81 = Utf8               org/scalatest/tools/PresentTestIgnored$
   #82 = Class              #81           // org/scalatest/tools/PresentTestIgnored$
   #83 = Utf8               Lorg/scalatest/tools/PresentTestIgnored$;
   #84 = NameAndType        #8:#83        // MODULE$:Lorg/scalatest/tools/PresentTestIgnored$;
   #85 = Fieldref           #82.#84       // org/scalatest/tools/PresentTestIgnored$.MODULE$:Lorg/scalatest/tools/PresentTestIgnored$;
   #86 = Utf8               TEST_IGNORED
   #87 = String             #86           // TEST_IGNORED
   #88 = Utf8               org/scalatest/tools/PresentTestPending$
   #89 = Class              #88           // org/scalatest/tools/PresentTestPending$
   #90 = Utf8               Lorg/scalatest/tools/PresentTestPending$;
   #91 = NameAndType        #8:#90        // MODULE$:Lorg/scalatest/tools/PresentTestPending$;
   #92 = Fieldref           #89.#91       // org/scalatest/tools/PresentTestPending$.MODULE$:Lorg/scalatest/tools/PresentTestPending$;
   #93 = Utf8               TEST_PENDING
   #94 = String             #93           // TEST_PENDING
   #95 = Utf8               org/scalatest/tools/PresentTestCanceled$
   #96 = Class              #95           // org/scalatest/tools/PresentTestCanceled$
   #97 = Utf8               Lorg/scalatest/tools/PresentTestCanceled$;
   #98 = NameAndType        #8:#97        // MODULE$:Lorg/scalatest/tools/PresentTestCanceled$;
   #99 = Fieldref           #96.#98       // org/scalatest/tools/PresentTestCanceled$.MODULE$:Lorg/scalatest/tools/PresentTestCanceled$;
  #100 = Utf8               TEST_CANCELED
  #101 = String             #100          // TEST_CANCELED
  #102 = Utf8               org/scalatest/tools/PresentSuiteStarting$
  #103 = Class              #102          // org/scalatest/tools/PresentSuiteStarting$
  #104 = Utf8               Lorg/scalatest/tools/PresentSuiteStarting$;
  #105 = NameAndType        #8:#104       // MODULE$:Lorg/scalatest/tools/PresentSuiteStarting$;
  #106 = Fieldref           #103.#105     // org/scalatest/tools/PresentSuiteStarting$.MODULE$:Lorg/scalatest/tools/PresentSuiteStarting$;
  #107 = Utf8               SUITE_STARTING
  #108 = String             #107          // SUITE_STARTING
  #109 = Utf8               org/scalatest/tools/PresentSuiteAborted$
  #110 = Class              #109          // org/scalatest/tools/PresentSuiteAborted$
  #111 = Utf8               Lorg/scalatest/tools/PresentSuiteAborted$;
  #112 = NameAndType        #8:#111       // MODULE$:Lorg/scalatest/tools/PresentSuiteAborted$;
  #113 = Fieldref           #110.#112     // org/scalatest/tools/PresentSuiteAborted$.MODULE$:Lorg/scalatest/tools/PresentSuiteAborted$;
  #114 = Utf8               SUITE_ABORTED
  #115 = String             #114          // SUITE_ABORTED
  #116 = Utf8               org/scalatest/tools/PresentSuiteCompleted$
  #117 = Class              #116          // org/scalatest/tools/PresentSuiteCompleted$
  #118 = Utf8               Lorg/scalatest/tools/PresentSuiteCompleted$;
  #119 = NameAndType        #8:#118       // MODULE$:Lorg/scalatest/tools/PresentSuiteCompleted$;
  #120 = Fieldref           #117.#119     // org/scalatest/tools/PresentSuiteCompleted$.MODULE$:Lorg/scalatest/tools/PresentSuiteCompleted$;
  #121 = Utf8               SUITE_COMPLETED
  #122 = String             #121          // SUITE_COMPLETED
  #123 = Utf8               org/scalatest/tools/PresentInfoProvided$
  #124 = Class              #123          // org/scalatest/tools/PresentInfoProvided$
  #125 = Utf8               Lorg/scalatest/tools/PresentInfoProvided$;
  #126 = NameAndType        #8:#125       // MODULE$:Lorg/scalatest/tools/PresentInfoProvided$;
  #127 = Fieldref           #124.#126     // org/scalatest/tools/PresentInfoProvided$.MODULE$:Lorg/scalatest/tools/PresentInfoProvided$;
  #128 = Utf8               INFO_PROVIDED
  #129 = String             #128          // INFO_PROVIDED
  #130 = Utf8               org/scalatest/tools/PresentAlertProvided$
  #131 = Class              #130          // org/scalatest/tools/PresentAlertProvided$
  #132 = Utf8               Lorg/scalatest/tools/PresentAlertProvided$;
  #133 = NameAndType        #8:#132       // MODULE$:Lorg/scalatest/tools/PresentAlertProvided$;
  #134 = Fieldref           #131.#133     // org/scalatest/tools/PresentAlertProvided$.MODULE$:Lorg/scalatest/tools/PresentAlertProvided$;
  #135 = Utf8               ALERT_PROVIDED
  #136 = String             #135          // ALERT_PROVIDED
  #137 = Utf8               org/scalatest/tools/PresentNoteProvided$
  #138 = Class              #137          // org/scalatest/tools/PresentNoteProvided$
  #139 = Utf8               Lorg/scalatest/tools/PresentNoteProvided$;
  #140 = NameAndType        #8:#139       // MODULE$:Lorg/scalatest/tools/PresentNoteProvided$;
  #141 = Fieldref           #138.#140     // org/scalatest/tools/PresentNoteProvided$.MODULE$:Lorg/scalatest/tools/PresentNoteProvided$;
  #142 = Utf8               NOTE_PROVIDED
  #143 = String             #142          // NOTE_PROVIDED
  #144 = Utf8               org/scalatest/tools/PresentScopeOpened$
  #145 = Class              #144          // org/scalatest/tools/PresentScopeOpened$
  #146 = Utf8               Lorg/scalatest/tools/PresentScopeOpened$;
  #147 = NameAndType        #8:#146       // MODULE$:Lorg/scalatest/tools/PresentScopeOpened$;
  #148 = Fieldref           #145.#147     // org/scalatest/tools/PresentScopeOpened$.MODULE$:Lorg/scalatest/tools/PresentScopeOpened$;
  #149 = Utf8               SCOPE_OPENED
  #150 = String             #149          // SCOPE_OPENED
  #151 = Utf8               org/scalatest/tools/PresentScopeClosed$
  #152 = Class              #151          // org/scalatest/tools/PresentScopeClosed$
  #153 = Utf8               Lorg/scalatest/tools/PresentScopeClosed$;
  #154 = NameAndType        #8:#153       // MODULE$:Lorg/scalatest/tools/PresentScopeClosed$;
  #155 = Fieldref           #152.#154     // org/scalatest/tools/PresentScopeClosed$.MODULE$:Lorg/scalatest/tools/PresentScopeClosed$;
  #156 = Utf8               SCOPE_CLOSED
  #157 = String             #156          // SCOPE_CLOSED
  #158 = Utf8               org/scalatest/tools/PresentScopePending$
  #159 = Class              #158          // org/scalatest/tools/PresentScopePending$
  #160 = Utf8               Lorg/scalatest/tools/PresentScopePending$;
  #161 = NameAndType        #8:#160       // MODULE$:Lorg/scalatest/tools/PresentScopePending$;
  #162 = Fieldref           #159.#161     // org/scalatest/tools/PresentScopePending$.MODULE$:Lorg/scalatest/tools/PresentScopePending$;
  #163 = Utf8               SCOPE_PENDING
  #164 = String             #163          // SCOPE_PENDING
  #165 = Utf8               org/scalatest/tools/PresentMarkupProvided$
  #166 = Class              #165          // org/scalatest/tools/PresentMarkupProvided$
  #167 = Utf8               Lorg/scalatest/tools/PresentMarkupProvided$;
  #168 = NameAndType        #8:#167       // MODULE$:Lorg/scalatest/tools/PresentMarkupProvided$;
  #169 = Fieldref           #166.#168     // org/scalatest/tools/PresentMarkupProvided$.MODULE$:Lorg/scalatest/tools/PresentMarkupProvided$;
  #170 = Utf8               MARKUP_PROVIDED
  #171 = String             #170          // MARKUP_PROVIDED
  #172 = Utf8               org/scalatest/tools/PresentRunStopped$
  #173 = Class              #172          // org/scalatest/tools/PresentRunStopped$
  #174 = Utf8               Lorg/scalatest/tools/PresentRunStopped$;
  #175 = NameAndType        #8:#174       // MODULE$:Lorg/scalatest/tools/PresentRunStopped$;
  #176 = Fieldref           #173.#175     // org/scalatest/tools/PresentRunStopped$.MODULE$:Lorg/scalatest/tools/PresentRunStopped$;
  #177 = Utf8               RUN_STOPPED
  #178 = String             #177          // RUN_STOPPED
  #179 = Utf8               org/scalatest/tools/PresentRunAborted$
  #180 = Class              #179          // org/scalatest/tools/PresentRunAborted$
  #181 = Utf8               Lorg/scalatest/tools/PresentRunAborted$;
  #182 = NameAndType        #8:#181       // MODULE$:Lorg/scalatest/tools/PresentRunAborted$;
  #183 = Fieldref           #180.#182     // org/scalatest/tools/PresentRunAborted$.MODULE$:Lorg/scalatest/tools/PresentRunAborted$;
  #184 = Utf8               RUN_ABORTED
  #185 = String             #184          // RUN_ABORTED
  #186 = Utf8               org/scalatest/tools/PresentRunCompleted$
  #187 = Class              #186          // org/scalatest/tools/PresentRunCompleted$
  #188 = Utf8               Lorg/scalatest/tools/PresentRunCompleted$;
  #189 = NameAndType        #8:#188       // MODULE$:Lorg/scalatest/tools/PresentRunCompleted$;
  #190 = Fieldref           #187.#189     // org/scalatest/tools/PresentRunCompleted$.MODULE$:Lorg/scalatest/tools/PresentRunCompleted$;
  #191 = Utf8               RUN_COMPLETED
  #192 = String             #191          // RUN_COMPLETED
  #193 = Utf8               scala/MatchError
  #194 = Class              #193          // scala/MatchError
  #195 = Utf8               (Ljava/lang/Object;)V
  #196 = NameAndType        #12:#195      // "<init>":(Ljava/lang/Object;)V
  #197 = Methodref          #194.#196     // scala/MatchError."<init>":(Ljava/lang/Object;)V
  #198 = Utf8               Lorg/scalatest/tools/EventToPresent;
  #199 = Utf8               org/scalatest/tools/EventToPresent
  #200 = Class              #199          // org/scalatest/tools/EventToPresent
  #201 = Utf8               java/lang/String
  #202 = Class              #201          // java/lang/String
  #203 = Utf8               getEventToPresentDisplayMessage
  #204 = Utf8               (Lorg/scalatest/events/Event;Z)Ljava/lang/String;
  #205 = Utf8               isRerun
  #206 = Utf8               org/scalatest/Resources$
  #207 = Class              #206          // org/scalatest/Resources$
  #208 = Utf8               Lorg/scalatest/Resources$;
  #209 = NameAndType        #8:#208       // MODULE$:Lorg/scalatest/Resources$;
  #210 = Fieldref           #207.#209     // org/scalatest/Resources$.MODULE$:Lorg/scalatest/Resources$;
  #211 = Utf8               RERUN_DISCOVERY_STARTING
  #212 = Utf8               ()Ljava/lang/String;
  #213 = NameAndType        #211:#212     // RERUN_DISCOVERY_STARTING:()Ljava/lang/String;
  #214 = Methodref          #207.#213     // org/scalatest/Resources$.RERUN_DISCOVERY_STARTING:()Ljava/lang/String;
  #215 = NameAndType        #44:#212      // DISCOVERY_STARTING:()Ljava/lang/String;
  #216 = Methodref          #207.#215     // org/scalatest/Resources$.DISCOVERY_STARTING:()Ljava/lang/String;
  #217 = Utf8               RERUN_DISCOVERY_COMPLETED
  #218 = NameAndType        #217:#212     // RERUN_DISCOVERY_COMPLETED:()Ljava/lang/String;
  #219 = Methodref          #207.#218     // org/scalatest/Resources$.RERUN_DISCOVERY_COMPLETED:()Ljava/lang/String;
  #220 = NameAndType        #51:#212      // DISCOVERY_COMPLETED:()Ljava/lang/String;
  #221 = Methodref          #207.#220     // org/scalatest/Resources$.DISCOVERY_COMPLETED:()Ljava/lang/String;
  #222 = Utf8               RERUN_RUN_STARTING
  #223 = NameAndType        #222:#212     // RERUN_RUN_STARTING:()Ljava/lang/String;
  #224 = Methodref          #207.#223     // org/scalatest/Resources$.RERUN_RUN_STARTING:()Ljava/lang/String;
  #225 = NameAndType        #58:#212      // RUN_STARTING:()Ljava/lang/String;
  #226 = Methodref          #207.#225     // org/scalatest/Resources$.RUN_STARTING:()Ljava/lang/String;
  #227 = Utf8               RERUN_TEST_STARTING
  #228 = NameAndType        #227:#212     // RERUN_TEST_STARTING:()Ljava/lang/String;
  #229 = Methodref          #207.#228     // org/scalatest/Resources$.RERUN_TEST_STARTING:()Ljava/lang/String;
  #230 = NameAndType        #65:#212      // TEST_STARTING:()Ljava/lang/String;
  #231 = Methodref          #207.#230     // org/scalatest/Resources$.TEST_STARTING:()Ljava/lang/String;
  #232 = Utf8               RERUN_TEST_FAILED
  #233 = NameAndType        #232:#212     // RERUN_TEST_FAILED:()Ljava/lang/String;
  #234 = Methodref          #207.#233     // org/scalatest/Resources$.RERUN_TEST_FAILED:()Ljava/lang/String;
  #235 = NameAndType        #72:#212      // TEST_FAILED:()Ljava/lang/String;
  #236 = Methodref          #207.#235     // org/scalatest/Resources$.TEST_FAILED:()Ljava/lang/String;
  #237 = Utf8               RERUN_TEST_SUCCEEDED
  #238 = NameAndType        #237:#212     // RERUN_TEST_SUCCEEDED:()Ljava/lang/String;
  #239 = Methodref          #207.#238     // org/scalatest/Resources$.RERUN_TEST_SUCCEEDED:()Ljava/lang/String;
  #240 = NameAndType        #79:#212      // TEST_SUCCEEDED:()Ljava/lang/String;
  #241 = Methodref          #207.#240     // org/scalatest/Resources$.TEST_SUCCEEDED:()Ljava/lang/String;
  #242 = Utf8               RERUN_TEST_IGNORED
  #243 = NameAndType        #242:#212     // RERUN_TEST_IGNORED:()Ljava/lang/String;
  #244 = Methodref          #207.#243     // org/scalatest/Resources$.RERUN_TEST_IGNORED:()Ljava/lang/String;
  #245 = NameAndType        #86:#212      // TEST_IGNORED:()Ljava/lang/String;
  #246 = Methodref          #207.#245     // org/scalatest/Resources$.TEST_IGNORED:()Ljava/lang/String;
  #247 = Utf8               RERUN_TEST_PENDING
  #248 = NameAndType        #247:#212     // RERUN_TEST_PENDING:()Ljava/lang/String;
  #249 = Methodref          #207.#248     // org/scalatest/Resources$.RERUN_TEST_PENDING:()Ljava/lang/String;
  #250 = NameAndType        #93:#212      // TEST_PENDING:()Ljava/lang/String;
  #251 = Methodref          #207.#250     // org/scalatest/Resources$.TEST_PENDING:()Ljava/lang/String;
  #252 = Utf8               RERUN_TEST_CANCELED
  #253 = NameAndType        #252:#212     // RERUN_TEST_CANCELED:()Ljava/lang/String;
  #254 = Methodref          #207.#253     // org/scalatest/Resources$.RERUN_TEST_CANCELED:()Ljava/lang/String;
  #255 = NameAndType        #100:#212     // TEST_CANCELED:()Ljava/lang/String;
  #256 = Methodref          #207.#255     // org/scalatest/Resources$.TEST_CANCELED:()Ljava/lang/String;
  #257 = Utf8               RERUN_SUITE_STARTING
  #258 = NameAndType        #257:#212     // RERUN_SUITE_STARTING:()Ljava/lang/String;
  #259 = Methodref          #207.#258     // org/scalatest/Resources$.RERUN_SUITE_STARTING:()Ljava/lang/String;
  #260 = NameAndType        #107:#212     // SUITE_STARTING:()Ljava/lang/String;
  #261 = Methodref          #207.#260     // org/scalatest/Resources$.SUITE_STARTING:()Ljava/lang/String;
  #262 = Utf8               RERUN_SUITE_ABORTED
  #263 = NameAndType        #262:#212     // RERUN_SUITE_ABORTED:()Ljava/lang/String;
  #264 = Methodref          #207.#263     // org/scalatest/Resources$.RERUN_SUITE_ABORTED:()Ljava/lang/String;
  #265 = NameAndType        #114:#212     // SUITE_ABORTED:()Ljava/lang/String;
  #266 = Methodref          #207.#265     // org/scalatest/Resources$.SUITE_ABORTED:()Ljava/lang/String;
  #267 = Utf8               RERUN_SUITE_COMPLETED
  #268 = NameAndType        #267:#212     // RERUN_SUITE_COMPLETED:()Ljava/lang/String;
  #269 = Methodref          #207.#268     // org/scalatest/Resources$.RERUN_SUITE_COMPLETED:()Ljava/lang/String;
  #270 = NameAndType        #121:#212     // SUITE_COMPLETED:()Ljava/lang/String;
  #271 = Methodref          #207.#270     // org/scalatest/Resources$.SUITE_COMPLETED:()Ljava/lang/String;
  #272 = Utf8               RERUN_INFO_PROVIDED
  #273 = NameAndType        #272:#212     // RERUN_INFO_PROVIDED:()Ljava/lang/String;
  #274 = Methodref          #207.#273     // org/scalatest/Resources$.RERUN_INFO_PROVIDED:()Ljava/lang/String;
  #275 = NameAndType        #128:#212     // INFO_PROVIDED:()Ljava/lang/String;
  #276 = Methodref          #207.#275     // org/scalatest/Resources$.INFO_PROVIDED:()Ljava/lang/String;
  #277 = Utf8               RERUN_ALERT_PROVIDED
  #278 = NameAndType        #277:#212     // RERUN_ALERT_PROVIDED:()Ljava/lang/String;
  #279 = Methodref          #207.#278     // org/scalatest/Resources$.RERUN_ALERT_PROVIDED:()Ljava/lang/String;
  #280 = NameAndType        #135:#212     // ALERT_PROVIDED:()Ljava/lang/String;
  #281 = Methodref          #207.#280     // org/scalatest/Resources$.ALERT_PROVIDED:()Ljava/lang/String;
  #282 = Utf8               RERUN_NOTE_PROVIDED
  #283 = NameAndType        #282:#212     // RERUN_NOTE_PROVIDED:()Ljava/lang/String;
  #284 = Methodref          #207.#283     // org/scalatest/Resources$.RERUN_NOTE_PROVIDED:()Ljava/lang/String;
  #285 = NameAndType        #142:#212     // NOTE_PROVIDED:()Ljava/lang/String;
  #286 = Methodref          #207.#285     // org/scalatest/Resources$.NOTE_PROVIDED:()Ljava/lang/String;
  #287 = Utf8               RERUN_SCOPE_OPENED
  #288 = NameAndType        #287:#212     // RERUN_SCOPE_OPENED:()Ljava/lang/String;
  #289 = Methodref          #207.#288     // org/scalatest/Resources$.RERUN_SCOPE_OPENED:()Ljava/lang/String;
  #290 = NameAndType        #149:#212     // SCOPE_OPENED:()Ljava/lang/String;
  #291 = Methodref          #207.#290     // org/scalatest/Resources$.SCOPE_OPENED:()Ljava/lang/String;
  #292 = Utf8               RERUN_SCOPE_CLOSED
  #293 = NameAndType        #292:#212     // RERUN_SCOPE_CLOSED:()Ljava/lang/String;
  #294 = Methodref          #207.#293     // org/scalatest/Resources$.RERUN_SCOPE_CLOSED:()Ljava/lang/String;
  #295 = NameAndType        #156:#212     // SCOPE_CLOSED:()Ljava/lang/String;
  #296 = Methodref          #207.#295     // org/scalatest/Resources$.SCOPE_CLOSED:()Ljava/lang/String;
  #297 = Utf8               RERUN_SCOPE_PENDING
  #298 = NameAndType        #297:#212     // RERUN_SCOPE_PENDING:()Ljava/lang/String;
  #299 = Methodref          #207.#298     // org/scalatest/Resources$.RERUN_SCOPE_PENDING:()Ljava/lang/String;
  #300 = NameAndType        #163:#212     // SCOPE_PENDING:()Ljava/lang/String;
  #301 = Methodref          #207.#300     // org/scalatest/Resources$.SCOPE_PENDING:()Ljava/lang/String;
  #302 = Utf8               RERUN_MARKUP_PROVIDED
  #303 = NameAndType        #302:#212     // RERUN_MARKUP_PROVIDED:()Ljava/lang/String;
  #304 = Methodref          #207.#303     // org/scalatest/Resources$.RERUN_MARKUP_PROVIDED:()Ljava/lang/String;
  #305 = NameAndType        #170:#212     // MARKUP_PROVIDED:()Ljava/lang/String;
  #306 = Methodref          #207.#305     // org/scalatest/Resources$.MARKUP_PROVIDED:()Ljava/lang/String;
  #307 = Utf8               RERUN_RUN_STOPPED
  #308 = NameAndType        #307:#212     // RERUN_RUN_STOPPED:()Ljava/lang/String;
  #309 = Methodref          #207.#308     // org/scalatest/Resources$.RERUN_RUN_STOPPED:()Ljava/lang/String;
  #310 = NameAndType        #177:#212     // RUN_STOPPED:()Ljava/lang/String;
  #311 = Methodref          #207.#310     // org/scalatest/Resources$.RUN_STOPPED:()Ljava/lang/String;
  #312 = Utf8               RERUN_RUN_ABORTED
  #313 = NameAndType        #312:#212     // RERUN_RUN_ABORTED:()Ljava/lang/String;
  #314 = Methodref          #207.#313     // org/scalatest/Resources$.RERUN_RUN_ABORTED:()Ljava/lang/String;
  #315 = NameAndType        #184:#212     // RUN_ABORTED:()Ljava/lang/String;
  #316 = Methodref          #207.#315     // org/scalatest/Resources$.RUN_ABORTED:()Ljava/lang/String;
  #317 = NameAndType        #191:#212     // RUN_COMPLETED:()Ljava/lang/String;
  #318 = Methodref          #207.#317     // org/scalatest/Resources$.RUN_COMPLETED:()Ljava/lang/String;
  #319 = Utf8               Z
  #320 = Utf8               org/scalatest/events/Event
  #321 = Class              #320          // org/scalatest/events/Event
  #322 = Utf8               getEventToPresentMenuPresentDisplayMessage
  #323 = Utf8               MENU_PRESENT_DISCOVERY_STARTING
  #324 = NameAndType        #323:#212     // MENU_PRESENT_DISCOVERY_STARTING:()Ljava/lang/String;
  #325 = Methodref          #207.#324     // org/scalatest/Resources$.MENU_PRESENT_DISCOVERY_STARTING:()Ljava/lang/String;
  #326 = Utf8               MENU_PRESENT_DISCOVERY_COMPLETED
  #327 = NameAndType        #326:#212     // MENU_PRESENT_DISCOVERY_COMPLETED:()Ljava/lang/String;
  #328 = Methodref          #207.#327     // org/scalatest/Resources$.MENU_PRESENT_DISCOVERY_COMPLETED:()Ljava/lang/String;
  #329 = Utf8               MENU_PRESENT_RUN_STARTING
  #330 = NameAndType        #329:#212     // MENU_PRESENT_RUN_STARTING:()Ljava/lang/String;
  #331 = Methodref          #207.#330     // org/scalatest/Resources$.MENU_PRESENT_RUN_STARTING:()Ljava/lang/String;
  #332 = Utf8               MENU_PRESENT_TEST_STARTING
  #333 = NameAndType        #332:#212     // MENU_PRESENT_TEST_STARTING:()Ljava/lang/String;
  #334 = Methodref          #207.#333     // org/scalatest/Resources$.MENU_PRESENT_TEST_STARTING:()Ljava/lang/String;
  #335 = Utf8               MENU_PRESENT_TEST_FAILED
  #336 = NameAndType        #335:#212     // MENU_PRESENT_TEST_FAILED:()Ljava/lang/String;
  #337 = Methodref          #207.#336     // org/scalatest/Resources$.MENU_PRESENT_TEST_FAILED:()Ljava/lang/String;
  #338 = Utf8               MENU_PRESENT_TEST_SUCCEEDED
  #339 = NameAndType        #338:#212     // MENU_PRESENT_TEST_SUCCEEDED:()Ljava/lang/String;
  #340 = Methodref          #207.#339     // org/scalatest/Resources$.MENU_PRESENT_TEST_SUCCEEDED:()Ljava/lang/String;
  #341 = Utf8               MENU_PRESENT_TEST_IGNORED
  #342 = NameAndType        #341:#212     // MENU_PRESENT_TEST_IGNORED:()Ljava/lang/String;
  #343 = Methodref          #207.#342     // org/scalatest/Resources$.MENU_PRESENT_TEST_IGNORED:()Ljava/lang/String;
  #344 = Utf8               MENU_PRESENT_TEST_PENDING
  #345 = NameAndType        #344:#212     // MENU_PRESENT_TEST_PENDING:()Ljava/lang/String;
  #346 = Methodref          #207.#345     // org/scalatest/Resources$.MENU_PRESENT_TEST_PENDING:()Ljava/lang/String;
  #347 = Utf8               MENU_PRESENT_TEST_CANCELED
  #348 = NameAndType        #347:#212     // MENU_PRESENT_TEST_CANCELED:()Ljava/lang/String;
  #349 = Methodref          #207.#348     // org/scalatest/Resources$.MENU_PRESENT_TEST_CANCELED:()Ljava/lang/String;
  #350 = Utf8               MENU_PRESENT_SUITE_STARTING
  #351 = NameAndType        #350:#212     // MENU_PRESENT_SUITE_STARTING:()Ljava/lang/String;
  #352 = Methodref          #207.#351     // org/scalatest/Resources$.MENU_PRESENT_SUITE_STARTING:()Ljava/lang/String;
  #353 = Utf8               MENU_PRESENT_SUITE_ABORTED
  #354 = NameAndType        #353:#212     // MENU_PRESENT_SUITE_ABORTED:()Ljava/lang/String;
  #355 = Methodref          #207.#354     // org/scalatest/Resources$.MENU_PRESENT_SUITE_ABORTED:()Ljava/lang/String;
  #356 = Utf8               MENU_PRESENT_SUITE_COMPLETED
  #357 = NameAndType        #356:#212     // MENU_PRESENT_SUITE_COMPLETED:()Ljava/lang/String;
  #358 = Methodref          #207.#357     // org/scalatest/Resources$.MENU_PRESENT_SUITE_COMPLETED:()Ljava/lang/String;
  #359 = Utf8               MENU_PRESENT_INFO_PROVIDED
  #360 = NameAndType        #359:#212     // MENU_PRESENT_INFO_PROVIDED:()Ljava/lang/String;
  #361 = Methodref          #207.#360     // org/scalatest/Resources$.MENU_PRESENT_INFO_PROVIDED:()Ljava/lang/String;
  #362 = Utf8               MENU_PRESENT_ALERT_PROVIDED
  #363 = NameAndType        #362:#212     // MENU_PRESENT_ALERT_PROVIDED:()Ljava/lang/String;
  #364 = Methodref          #207.#363     // org/scalatest/Resources$.MENU_PRESENT_ALERT_PROVIDED:()Ljava/lang/String;
  #365 = Utf8               MENU_PRESENT_NOTE_PROVIDED
  #366 = NameAndType        #365:#212     // MENU_PRESENT_NOTE_PROVIDED:()Ljava/lang/String;
  #367 = Methodref          #207.#366     // org/scalatest/Resources$.MENU_PRESENT_NOTE_PROVIDED:()Ljava/lang/String;
  #368 = Utf8               MENU_PRESENT_SCOPE_OPENED
  #369 = NameAndType        #368:#212     // MENU_PRESENT_SCOPE_OPENED:()Ljava/lang/String;
  #370 = Methodref          #207.#369     // org/scalatest/Resources$.MENU_PRESENT_SCOPE_OPENED:()Ljava/lang/String;
  #371 = Utf8               MENU_PRESENT_SCOPE_CLOSED
  #372 = NameAndType        #371:#212     // MENU_PRESENT_SCOPE_CLOSED:()Ljava/lang/String;
  #373 = Methodref          #207.#372     // org/scalatest/Resources$.MENU_PRESENT_SCOPE_CLOSED:()Ljava/lang/String;
  #374 = Utf8               MENU_PRESENT_SCOPE_PENDING
  #375 = NameAndType        #374:#212     // MENU_PRESENT_SCOPE_PENDING:()Ljava/lang/String;
  #376 = Methodref          #207.#375     // org/scalatest/Resources$.MENU_PRESENT_SCOPE_PENDING:()Ljava/lang/String;
  #377 = Utf8               MENU_PRESENT_MARKUP_PROVIDED
  #378 = NameAndType        #377:#212     // MENU_PRESENT_MARKUP_PROVIDED:()Ljava/lang/String;
  #379 = Methodref          #207.#378     // org/scalatest/Resources$.MENU_PRESENT_MARKUP_PROVIDED:()Ljava/lang/String;
  #380 = Utf8               MENU_PRESENT_RUN_STOPPED
  #381 = NameAndType        #380:#212     // MENU_PRESENT_RUN_STOPPED:()Ljava/lang/String;
  #382 = Methodref          #207.#381     // org/scalatest/Resources$.MENU_PRESENT_RUN_STOPPED:()Ljava/lang/String;
  #383 = Utf8               MENU_PRESENT_RUN_ABORTED
  #384 = NameAndType        #383:#212     // MENU_PRESENT_RUN_ABORTED:()Ljava/lang/String;
  #385 = Methodref          #207.#384     // org/scalatest/Resources$.MENU_PRESENT_RUN_ABORTED:()Ljava/lang/String;
  #386 = Utf8               MENU_PRESENT_RUN_COMPLETED
  #387 = NameAndType        #386:#212     // MENU_PRESENT_RUN_COMPLETED:()Ljava/lang/String;
  #388 = Methodref          #207.#387     // org/scalatest/Resources$.MENU_PRESENT_RUN_COMPLETED:()Ljava/lang/String;
  #389 = Utf8               writeReplace
  #390 = Utf8               ()Ljava/lang/Object;
  #391 = Utf8               scala/runtime/ModuleSerializationProxy
  #392 = Class              #391          // scala/runtime/ModuleSerializationProxy
  #393 = Utf8               (Ljava/lang/Class;)V
  #394 = NameAndType        #12:#393      // "<init>":(Ljava/lang/Class;)V
  #395 = Methodref          #392.#394     // scala/runtime/ModuleSerializationProxy."<init>":(Ljava/lang/Class;)V
  #396 = Methodref          #4.#13        // java/lang/Object."<init>":()V
  #397 = Utf8               Code
  #398 = Utf8               LineNumberTable
  #399 = Utf8               LocalVariableTable
  #400 = Utf8               MethodParameters
  #401 = Utf8               StackMapTable
  #402 = Utf8               SourceFile
  #403 = Utf8               ScalaInlineInfo
  #404 = Utf8               Scala
{
  public static final org.scalatest.tools.RunnerJFrame$ MODULE$;
    descriptor: Lorg/scalatest/tools/RunnerJFrame$;
    flags: (0x0019) ACC_PUBLIC, ACC_STATIC, ACC_FINAL

  public static {};
    descriptor: ()V
    flags: (0x0009) ACC_PUBLIC, ACC_STATIC
    Code:
      stack=2, locals=0, args_size=0
         0: new           #2                  // class org/scalatest/tools/RunnerJFrame$
         3: dup
         4: invokespecial #14                 // Method "<init>":()V
         7: putstatic     #16                 // Field MODULE$:Lorg/scalatest/tools/RunnerJFrame$;
        10: return
      LineNumberTable:
        line 1633: 0

  public java.lang.String getUpperCaseName(org.scalatest.events.Event);
    descriptor: (Lorg/scalatest/events/Event;)Ljava/lang/String;
    flags: (0x0001) ACC_PUBLIC
    Code:
      stack=3, locals=2, args_size=2
         0: aload_0
         1: getstatic     #24                 // Field org/scalatest/tools/EventToPresent$.MODULE$:Lorg/scalatest/tools/EventToPresent$;
         4: aload_1
         5: invokevirtual #28                 // Method org/scalatest/tools/EventToPresent$.eventToEventToPresent:(Lorg/scalatest/events/Event;)Lorg/scalatest/tools/EventToPresent;
         8: invokevirtual #31                 // Method getUpperCaseName:(Lorg/scalatest/tools/EventToPresent;)Ljava/lang/String;
        11: areturn
      LineNumberTable:
        line 1635: 0
      LocalVariableTable:
        Start  Length  Slot  Name   Signature
            0      12     0  this   Lorg/scalatest/tools/RunnerJFrame$;
            0      12     1 event   Lorg/scalatest/events/Event;
    MethodParameters:
      Name                           Flags
      event                          final

  public java.lang.String getUpperCaseName(org.scalatest.tools.EventToPresent);
    descriptor: (Lorg/scalatest/tools/EventToPresent;)Ljava/lang/String;
    flags: (0x0001) ACC_PUBLIC
    Code:
      stack=3, locals=4, args_size=2
         0: aload_1
         1: astore_3
         2: getstatic     #39                 // Field org/scalatest/tools/PresentDiscoveryStarting$.MODULE$:Lorg/scalatest/tools/PresentDiscoveryStarting$;
         5: aload_3
         6: invokevirtual #43                 // Method java/lang/Object.equals:(Ljava/lang/Object;)Z
         9: ifeq          18
        12: ldc           #45                 // String DISCOVERY_STARTING
        14: astore_2
        15: goto          429
        18: goto          21
        21: getstatic     #50                 // Field org/scalatest/tools/PresentDiscoveryCompleted$.MODULE$:Lorg/scalatest/tools/PresentDiscoveryCompleted$;
        24: aload_3
        25: invokevirtual #43                 // Method java/lang/Object.equals:(Ljava/lang/Object;)Z
        28: ifeq          37
        31: ldc           #52                 // String DISCOVERY_COMPLETED
        33: astore_2
        34: goto          429
        37: goto          40
        40: getstatic     #57                 // Field org/scalatest/tools/PresentRunStarting$.MODULE$:Lorg/scalatest/tools/PresentRunStarting$;
        43: aload_3
        44: invokevirtual #43                 // Method java/lang/Object.equals:(Ljava/lang/Object;)Z
        47: ifeq          56
        50: ldc           #59                 // String RUN_STARTING
        52: astore_2
        53: goto          429
        56: goto          59
        59: getstatic     #64                 // Field org/scalatest/tools/PresentTestStarting$.MODULE$:Lorg/scalatest/tools/PresentTestStarting$;
        62: aload_3
        63: invokevirtual #43                 // Method java/lang/Object.equals:(Ljava/lang/Object;)Z
        66: ifeq          75
        69: ldc           #66                 // String TEST_STARTING
        71: astore_2
        72: goto          429
        75: goto          78
        78: getstatic     #71                 // Field org/scalatest/tools/PresentTestFailed$.MODULE$:Lorg/scalatest/tools/PresentTestFailed$;
        81: aload_3
        82: invokevirtual #43                 // Method java/lang/Object.equals:(Ljava/lang/Object;)Z
        85: ifeq          94
        88: ldc           #73                 // String TEST_FAILED
        90: astore_2
        91: goto          429
        94: goto          97
        97: getstatic     #78                 // Field org/scalatest/tools/PresentTestSucceeded$.MODULE$:Lorg/scalatest/tools/PresentTestSucceeded$;
       100: aload_3
       101: invokevirtual #43                 // Method java/lang/Object.equals:(Ljava/lang/Object;)Z
       104: ifeq          113
       107: ldc           #80                 // String TEST_SUCCEEDED
       109: astore_2
       110: goto          429
       113: goto          116
       116: getstatic     #85                 // Field org/scalatest/tools/PresentTestIgnored$.MODULE$:Lorg/scalatest/tools/PresentTestIgnored$;
       119: aload_3
       120: invokevirtual #43                 // Method java/lang/Object.equals:(Ljava/lang/Object;)Z
       123: ifeq          132
       126: ldc           #87                 // String TEST_IGNORED
       128: astore_2
       129: goto          429
       132: goto          135
       135: getstatic     #92                 // Field org/scalatest/tools/PresentTestPending$.MODULE$:Lorg/scalatest/tools/PresentTestPending$;
       138: aload_3
       139: invokevirtual #43                 // Method java/lang/Object.equals:(Ljava/lang/Object;)Z
       142: ifeq          151
       145: ldc           #94                 // String TEST_PENDING
       147: astore_2
       148: goto          429
       151: goto          154
       154: getstatic     #99                 // Field org/scalatest/tools/PresentTestCanceled$.MODULE$:Lorg/scalatest/tools/PresentTestCanceled$;
       157: aload_3
       158: invokevirtual #43                 // Method java/lang/Object.equals:(Ljava/lang/Object;)Z
       161: ifeq          170
       164: ldc           #101                // String TEST_CANCELED
       166: astore_2
       167: goto          429
       170: goto          173
       173: getstatic     #106                // Field org/scalatest/tools/PresentSuiteStarting$.MODULE$:Lorg/scalatest/tools/PresentSuiteStarting$;
       176: aload_3
       177: invokevirtual #43                 // Method java/lang/Object.equals:(Ljava/lang/Object;)Z
       180: ifeq          189
       183: ldc           #108                // String SUITE_STARTING
       185: astore_2
       186: goto          429
       189: goto          192
       192: getstatic     #113                // Field org/scalatest/tools/PresentSuiteAborted$.MODULE$:Lorg/scalatest/tools/PresentSuiteAborted$;
       195: aload_3
       196: invokevirtual #43                 // Method java/lang/Object.equals:(Ljava/lang/Object;)Z
       199: ifeq          208
       202: ldc           #115                // String SUITE_ABORTED
       204: astore_2
       205: goto          429
       208: goto          211
       211: getstatic     #120                // Field org/scalatest/tools/PresentSuiteCompleted$.MODULE$:Lorg/scalatest/tools/PresentSuiteCompleted$;
       214: aload_3
       215: invokevirtual #43                 // Method java/lang/Object.equals:(Ljava/lang/Object;)Z
       218: ifeq          227
       221: ldc           #122                // String SUITE_COMPLETED
       223: astore_2
       224: goto          429
       227: goto          230
       230: getstatic     #127                // Field org/scalatest/tools/PresentInfoProvided$.MODULE$:Lorg/scalatest/tools/PresentInfoProvided$;
       233: aload_3
       234: invokevirtual #43                 // Method java/lang/Object.equals:(Ljava/lang/Object;)Z
       237: ifeq          246
       240: ldc           #129                // String INFO_PROVIDED
       242: astore_2
       243: goto          429
       246: goto          249
       249: getstatic     #134                // Field org/scalatest/tools/PresentAlertProvided$.MODULE$:Lorg/scalatest/tools/PresentAlertProvided$;
       252: aload_3
       253: invokevirtual #43                 // Method java/lang/Object.equals:(Ljava/lang/Object;)Z
       256: ifeq          265
       259: ldc           #136                // String ALERT_PROVIDED
       261: astore_2
       262: goto          429
       265: goto          268
       268: getstatic     #141                // Field org/scalatest/tools/PresentNoteProvided$.MODULE$:Lorg/scalatest/tools/PresentNoteProvided$;
       271: aload_3
       272: invokevirtual #43                 // Method java/lang/Object.equals:(Ljava/lang/Object;)Z
       275: ifeq          284
       278: ldc           #143                // String NOTE_PROVIDED
       280: astore_2
       281: goto          429
       284: goto          287
       287: getstatic     #148                // Field org/scalatest/tools/PresentScopeOpened$.MODULE$:Lorg/scalatest/tools/PresentScopeOpened$;
       290: aload_3
       291: invokevirtual #43                 // Method java/lang/Object.equals:(Ljava/lang/Object;)Z
       294: ifeq          303
       297: ldc           #150                // String SCOPE_OPENED
       299: astore_2
       300: goto          429
       303: goto          306
       306: getstatic     #155                // Field org/scalatest/tools/PresentScopeClosed$.MODULE$:Lorg/scalatest/tools/PresentScopeClosed$;
       309: aload_3
       310: invokevirtual #43                 // Method java/lang/Object.equals:(Ljava/lang/Object;)Z
       313: ifeq          322
       316: ldc           #157                // String SCOPE_CLOSED
       318: astore_2
       319: goto          429
       322: goto          325
       325: getstatic     #162                // Field org/scalatest/tools/PresentScopePending$.MODULE$:Lorg/scalatest/tools/PresentScopePending$;
       328: aload_3
       329: invokevirtual #43                 // Method java/lang/Object.equals:(Ljava/lang/Object;)Z
       332: ifeq          341
       335: ldc           #164                // String SCOPE_PENDING
       337: astore_2
       338: goto          429
       341: goto          344
       344: getstatic     #169                // Field org/scalatest/tools/PresentMarkupProvided$.MODULE$:Lorg/scalatest/tools/PresentMarkupProvided$;
       347: aload_3
       348: invokevirtual #43                 // Method java/lang/Object.equals:(Ljava/lang/Object;)Z
       351: ifeq          360
       354: ldc           #171                // String MARKUP_PROVIDED
       356: astore_2
       357: goto          429
       360: goto          363
       363: getstatic     #176                // Field org/scalatest/tools/PresentRunStopped$.MODULE$:Lorg/scalatest/tools/PresentRunStopped$;
       366: aload_3
       367: invokevirtual #43                 // Method java/lang/Object.equals:(Ljava/lang/Object;)Z
       370: ifeq          379
       373: ldc           #178                // String RUN_STOPPED
       375: astore_2
       376: goto          429
       379: goto          382
       382: getstatic     #183                // Field org/scalatest/tools/PresentRunAborted$.MODULE$:Lorg/scalatest/tools/PresentRunAborted$;
       385: aload_3
       386: invokevirtual #43                 // Method java/lang/Object.equals:(Ljava/lang/Object;)Z
       389: ifeq          398
       392: ldc           #185                // String RUN_ABORTED
       394: astore_2
       395: goto          429
       398: goto          401
       401: getstatic     #190                // Field org/scalatest/tools/PresentRunCompleted$.MODULE$:Lorg/scalatest/tools/PresentRunCompleted$;
       404: aload_3
       405: invokevirtual #43                 // Method java/lang/Object.equals:(Ljava/lang/Object;)Z
       408: ifeq          417
       411: ldc           #192                // String RUN_COMPLETED
       413: astore_2
       414: goto          429
       417: goto          420
       420: new           #194                // class scala/MatchError
       423: dup
       424: aload_3
       425: invokespecial #197                // Method scala/MatchError."<init>":(Ljava/lang/Object;)V
       428: athrow
       429: aload_2
       430: areturn
      StackMapTable: number_of_entries = 45
        frame_type = 253 /* append */
          offset_delta = 18
          locals = [ top, class org/scalatest/tools/EventToPresent ]
        frame_type = 2 /* same */
        frame_type = 15 /* same */
        frame_type = 2 /* same */
        frame_type = 15 /* same */
        frame_type = 2 /* same */
        frame_type = 15 /* same */
        frame_type = 2 /* same */
        frame_type = 15 /* same */
        frame_type = 2 /* same */
        frame_type = 15 /* same */
        frame_type = 2 /* same */
        frame_type = 15 /* same */
        frame_type = 2 /* same */
        frame_type = 15 /* same */
        frame_type = 2 /* same */
        frame_type = 15 /* same */
        frame_type = 2 /* same */
        frame_type = 15 /* same */
        frame_type = 2 /* same */
        frame_type = 15 /* same */
        frame_type = 2 /* same */
        frame_type = 15 /* same */
        frame_type = 2 /* same */
        frame_type = 15 /* same */
        frame_type = 2 /* same */
        frame_type = 15 /* same */
        frame_type = 2 /* same */
        frame_type = 15 /* same */
        frame_type = 2 /* same */
        frame_type = 15 /* same */
        frame_type = 2 /* same */
        frame_type = 15 /* same */
        frame_type = 2 /* same */
        frame_type = 15 /* same */
        frame_type = 2 /* same */
        frame_type = 15 /* same */
        frame_type = 2 /* same */
        frame_type = 15 /* same */
        frame_type = 2 /* same */
        frame_type = 15 /* same */
        frame_type = 2 /* same */
        frame_type = 15 /* same */
        frame_type = 2 /* same */
        frame_type = 255 /* full_frame */
          offset_delta = 8
          locals = [ class org/scalatest/tools/RunnerJFrame$, class org/scalatest/tools/EventToPresent, class java/lang/String, class org/scalatest/tools/EventToPresent ]
          stack = []
      LineNumberTable:
        line 1638: 0
        line 1639: 2
        line 1640: 21
        line 1641: 40
        line 1642: 59
        line 1643: 78
        line 1644: 97
        line 1645: 116
        line 1646: 135
        line 1647: 154
        line 1648: 173
        line 1649: 192
        line 1650: 211
        line 1651: 230
        line 1652: 249
        line 1653: 268
        line 1654: 287
        line 1655: 306
        line 1656: 325
        line 1657: 344
        line 1658: 363
        line 1659: 382
        line 1660: 401
        line 1638: 420
      LocalVariableTable:
        Start  Length  Slot  Name   Signature
            0     431     0  this   Lorg/scalatest/tools/RunnerJFrame$;
            0     431     1 eventToPresent   Lorg/scalatest/tools/EventToPresent;
    MethodParameters:
      Name                           Flags
      eventToPresent                 final

  public java.lang.String getEventToPresentDisplayMessage(org.scalatest.events.Event, boolean);
    descriptor: (Lorg/scalatest/events/Event;Z)Ljava/lang/String;
    flags: (0x0001) ACC_PUBLIC
    Code:
      stack=3, locals=5, args_size=3
         0: getstatic     #24                 // Field org/scalatest/tools/EventToPresent$.MODULE$:Lorg/scalatest/tools/EventToPresent$;
         3: aload_1
         4: invokevirtual #28                 // Method org/scalatest/tools/EventToPresent$.eventToEventToPresent:(Lorg/scalatest/events/Event;)Lorg/scalatest/tools/EventToPresent;
         7: astore        4
         9: getstatic     #39                 // Field org/scalatest/tools/PresentDiscoveryStarting$.MODULE$:Lorg/scalatest/tools/PresentDiscoveryStarting$;
        12: aload         4
        14: invokevirtual #43                 // Method java/lang/Object.equals:(Ljava/lang/Object;)Z
        17: ifeq          43
        20: iload_2
        21: ifeq          33
        24: getstatic     #210                // Field org/scalatest/Resources$.MODULE$:Lorg/scalatest/Resources$;
        27: invokevirtual #214                // Method org/scalatest/Resources$.RERUN_DISCOVERY_STARTING:()Ljava/lang/String;
        30: goto          39
        33: getstatic     #210                // Field org/scalatest/Resources$.MODULE$:Lorg/scalatest/Resources$;
        36: invokevirtual #216                // Method org/scalatest/Resources$.DISCOVERY_STARTING:()Ljava/lang/String;
        39: astore_3
        40: goto          833
        43: goto          46
        46: getstatic     #50                 // Field org/scalatest/tools/PresentDiscoveryCompleted$.MODULE$:Lorg/scalatest/tools/PresentDiscoveryCompleted$;
        49: aload         4
        51: invokevirtual #43                 // Method java/lang/Object.equals:(Ljava/lang/Object;)Z
        54: ifeq          80
        57: iload_2
        58: ifeq          70
        61: getstatic     #210                // Field org/scalatest/Resources$.MODULE$:Lorg/scalatest/Resources$;
        64: invokevirtual #219                // Method org/scalatest/Resources$.RERUN_DISCOVERY_COMPLETED:()Ljava/lang/String;
        67: goto          76
        70: getstatic     #210                // Field org/scalatest/Resources$.MODULE$:Lorg/scalatest/Resources$;
        73: invokevirtual #221                // Method org/scalatest/Resources$.DISCOVERY_COMPLETED:()Ljava/lang/String;
        76: astore_3
        77: goto          833
        80: goto          83
        83: getstatic     #57                 // Field org/scalatest/tools/PresentRunStarting$.MODULE$:Lorg/scalatest/tools/PresentRunStarting$;
        86: aload         4
        88: invokevirtual #43                 // Method java/lang/Object.equals:(Ljava/lang/Object;)Z
        91: ifeq          117
        94: iload_2
        95: ifeq          107
        98: getstatic     #210                // Field org/scalatest/Resources$.MODULE$:Lorg/scalatest/Resources$;
       101: invokevirtual #224                // Method org/scalatest/Resources$.RERUN_RUN_STARTING:()Ljava/lang/String;
       104: goto          113
       107: getstatic     #210                // Field org/scalatest/Resources$.MODULE$:Lorg/scalatest/Resources$;
       110: invokevirtual #226                // Method org/scalatest/Resources$.RUN_STARTING:()Ljava/lang/String;
       113: astore_3
       114: goto          833
       117: goto          120
       120: getstatic     #64                 // Field org/scalatest/tools/PresentTestStarting$.MODULE$:Lorg/scalatest/tools/PresentTestStarting$;
       123: aload         4
       125: invokevirtual #43                 // Method java/lang/Object.equals:(Ljava/lang/Object;)Z
       128: ifeq          154
       131: iload_2
       132: ifeq          144
       135: getstatic     #210                // Field org/scalatest/Resources$.MODULE$:Lorg/scalatest/Resources$;
       138: invokevirtual #229                // Method org/scalatest/Resources$.RERUN_TEST_STARTING:()Ljava/lang/String;
       141: goto          150
       144: getstatic     #210                // Field org/scalatest/Resources$.MODULE$:Lorg/scalatest/Resources$;
       147: invokevirtual #231                // Method org/scalatest/Resources$.TEST_STARTING:()Ljava/lang/String;
       150: astore_3
       151: goto          833
       154: goto          157
       157: getstatic     #71                 // Field org/scalatest/tools/PresentTestFailed$.MODULE$:Lorg/scalatest/tools/PresentTestFailed$;
       160: aload         4
       162: invokevirtual #43                 // Method java/lang/Object.equals:(Ljava/lang/Object;)Z
       165: ifeq          191
       168: iload_2
       169: ifeq          181
       172: getstatic     #210                // Field org/scalatest/Resources$.MODULE$:Lorg/scalatest/Resources$;
       175: invokevirtual #234                // Method org/scalatest/Resources$.RERUN_TEST_FAILED:()Ljava/lang/String;
       178: goto          187
       181: getstatic     #210                // Field org/scalatest/Resources$.MODULE$:Lorg/scalatest/Resources$;
       184: invokevirtual #236                // Method org/scalatest/Resources$.TEST_FAILED:()Ljava/lang/String;
       187: astore_3
       188: goto          833
       191: goto          194
       194: getstatic     #78                 // Field org/scalatest/tools/PresentTestSucceeded$.MODULE$:Lorg/scalatest/tools/PresentTestSucceeded$;
       197: aload         4
       199: invokevirtual #43                 // Method java/lang/Object.equals:(Ljava/lang/Object;)Z
       202: ifeq          228
       205: iload_2
       206: ifeq          218
       209: getstatic     #210                // Field org/scalatest/Resources$.MODULE$:Lorg/scalatest/Resources$;
       212: invokevirtual #239                // Method org/scalatest/Resources$.RERUN_TEST_SUCCEEDED:()Ljava/lang/String;
       215: goto          224
       218: getstatic     #210                // Field org/scalatest/Resources$.MODULE$:Lorg/scalatest/Resources$;
       221: invokevirtual #241                // Method org/scalatest/Resources$.TEST_SUCCEEDED:()Ljava/lang/String;
       224: astore_3
       225: goto          833
       228: goto          231
       231: getstatic     #85                 // Field org/scalatest/tools/PresentTestIgnored$.MODULE$:Lorg/scalatest/tools/PresentTestIgnored$;
       234: aload         4
       236: invokevirtual #43                 // Method java/lang/Object.equals:(Ljava/lang/Object;)Z
       239: ifeq          265
       242: iload_2
       243: ifeq          255
       246: getstatic     #210                // Field org/scalatest/Resources$.MODULE$:Lorg/scalatest/Resources$;
       249: invokevirtual #244                // Method org/scalatest/Resources$.RERUN_TEST_IGNORED:()Ljava/lang/String;
       252: goto          261
       255: getstatic     #210                // Field org/scalatest/Resources$.MODULE$:Lorg/scalatest/Resources$;
       258: invokevirtual #246                // Method org/scalatest/Resources$.TEST_IGNORED:()Ljava/lang/String;
       261: astore_3
       262: goto          833
       265: goto          268
       268: getstatic     #92                 // Field org/scalatest/tools/PresentTestPending$.MODULE$:Lorg/scalatest/tools/PresentTestPending$;
       271: aload         4
       273: invokevirtual #43                 // Method java/lang/Object.equals:(Ljava/lang/Object;)Z
       276: ifeq          302
       279: iload_2
       280: ifeq          292
       283: getstatic     #210                // Field org/scalatest/Resources$.MODULE$:Lorg/scalatest/Resources$;
       286: invokevirtual #249                // Method org/scalatest/Resources$.RERUN_TEST_PENDING:()Ljava/lang/String;
       289: goto          298
       292: getstatic     #210                // Field org/scalatest/Resources$.MODULE$:Lorg/scalatest/Resources$;
       295: invokevirtual #251                // Method org/scalatest/Resources$.TEST_PENDING:()Ljava/lang/String;
       298: astore_3
       299: goto          833
       302: goto          305
       305: getstatic     #99                 // Field org/scalatest/tools/PresentTestCanceled$.MODULE$:Lorg/scalatest/tools/PresentTestCanceled$;
       308: aload         4
       310: invokevirtual #43                 // Method java/lang/Object.equals:(Ljava/lang/Object;)Z
       313: ifeq          339
       316: iload_2
       317: ifeq          329
       320: getstatic     #210                // Field org/scalatest/Resources$.MODULE$:Lorg/scalatest/Resources$;
       323: invokevirtual #254                // Method org/scalatest/Resources$.RERUN_TEST_CANCELED:()Ljava/lang/String;
       326: goto          335
       329: getstatic     #210                // Field org/scalatest/Resources$.MODULE$:Lorg/scalatest/Resources$;
       332: invokevirtual #256                // Method org/scalatest/Resources$.TEST_CANCELED:()Ljava/lang/String;
       335: astore_3
       336: goto          833
       339: goto          342
       342: getstatic     #106                // Field org/scalatest/tools/PresentSuiteStarting$.MODULE$:Lorg/scalatest/tools/PresentSuiteStarting$;
       345: aload         4
       347: invokevirtual #43                 // Method java/lang/Object.equals:(Ljava/lang/Object;)Z
       350: ifeq          376
       353: iload_2
       354: ifeq          366
       357: getstatic     #210                // Field org/scalatest/Resources$.MODULE$:Lorg/scalatest/Resources$;
       360: invokevirtual #259                // Method org/scalatest/Resources$.RERUN_SUITE_STARTING:()Ljava/lang/String;
       363: goto          372
       366: getstatic     #210                // Field org/scalatest/Resources$.MODULE$:Lorg/scalatest/Resources$;
       369: invokevirtual #261                // Method org/scalatest/Resources$.SUITE_STARTING:()Ljava/lang/String;
       372: astore_3
       373: goto          833
       376: goto          379
       379: getstatic     #113                // Field org/scalatest/tools/PresentSuiteAborted$.MODULE$:Lorg/scalatest/tools/PresentSuiteAborted$;
       382: aload         4
       384: invokevirtual #43                 // Method java/lang/Object.equals:(Ljava/lang/Object;)Z
       387: ifeq          413
       390: iload_2
       391: ifeq          403
       394: getstatic     #210                // Field org/scalatest/Resources$.MODULE$:Lorg/scalatest/Resources$;
       397: invokevirtual #264                // Method org/scalatest/Resources$.RERUN_SUITE_ABORTED:()Ljava/lang/String;
       400: goto          409
       403: getstatic     #210                // Field org/scalatest/Resources$.MODULE$:Lorg/scalatest/Resources$;
       406: invokevirtual #266                // Method org/scalatest/Resources$.SUITE_ABORTED:()Ljava/lang/String;
       409: astore_3
       410: goto          833
       413: goto          416
       416: getstatic     #120                // Field org/scalatest/tools/PresentSuiteCompleted$.MODULE$:Lorg/scalatest/tools/PresentSuiteCompleted$;
       419: aload         4
       421: invokevirtual #43                 // Method java/lang/Object.equals:(Ljava/lang/Object;)Z
       424: ifeq          450
       427: iload_2
       428: ifeq          440
       431: getstatic     #210                // Field org/scalatest/Resources$.MODULE$:Lorg/scalatest/Resources$;
       434: invokevirtual #269                // Method org/scalatest/Resources$.RERUN_SUITE_COMPLETED:()Ljava/lang/String;
       437: goto          446
       440: getstatic     #210                // Field org/scalatest/Resources$.MODULE$:Lorg/scalatest/Resources$;
       443: invokevirtual #271                // Method org/scalatest/Resources$.SUITE_COMPLETED:()Ljava/lang/String;
       446: astore_3
       447: goto          833
       450: goto          453
       453: getstatic     #127                // Field org/scalatest/tools/PresentInfoProvided$.MODULE$:Lorg/scalatest/tools/PresentInfoProvided$;
       456: aload         4
       458: invokevirtual #43                 // Method java/lang/Object.equals:(Ljava/lang/Object;)Z
       461: ifeq          487
       464: iload_2
       465: ifeq          477
       468: getstatic     #210                // Field org/scalatest/Resources$.MODULE$:Lorg/scalatest/Resources$;
       471: invokevirtual #274                // Method org/scalatest/Resources$.RERUN_INFO_PROVIDED:()Ljava/lang/String;
       474: goto          483
       477: getstatic     #210                // Field org/scalatest/Resources$.MODULE$:Lorg/scalatest/Resources$;
       480: invokevirtual #276                // Method org/scalatest/Resources$.INFO_PROVIDED:()Ljava/lang/String;
       483: astore_3
       484: goto          833
       487: goto          490
       490: getstatic     #134                // Field org/scalatest/tools/PresentAlertProvided$.MODULE$:Lorg/scalatest/tools/PresentAlertProvided$;
       493: aload         4
       495: invokevirtual #43                 // Method java/lang/Object.equals:(Ljava/lang/Object;)Z
       498: ifeq          524
       501: iload_2
       502: ifeq          514
       505: getstatic     #210                // Field org/scalatest/Resources$.MODULE$:Lorg/scalatest/Resources$;
       508: invokevirtual #279                // Method org/scalatest/Resources$.RERUN_ALERT_PROVIDED:()Ljava/lang/String;
       511: goto          520
       514: getstatic     #210                // Field org/scalatest/Resources$.MODULE$:Lorg/scalatest/Resources$;
       517: invokevirtual #281                // Method org/scalatest/Resources$.ALERT_PROVIDED:()Ljava/lang/String;
       520: astore_3
       521: goto          833
       524: goto          527
       527: getstatic     #141                // Field org/scalatest/tools/PresentNoteProvided$.MODULE$:Lorg/scalatest/tools/PresentNoteProvided$;
       530: aload         4
       532: invokevirtual #43                 // Method java/lang/Object.equals:(Ljava/lang/Object;)Z
       535: ifeq          561
       538: iload_2
       539: ifeq          551
       542: getstatic     #210                // Field org/scalatest/Resources$.MODULE$:Lorg/scalatest/Resources$;
       545: invokevirtual #284                // Method org/scalatest/Resources$.RERUN_NOTE_PROVIDED:()Ljava/lang/String;
       548: goto          557
       551: getstatic     #210                // Field org/scalatest/Resources$.MODULE$:Lorg/scalatest/Resources$;
       554: invokevirtual #286                // Method org/scalatest/Resources$.NOTE_PROVIDED:()Ljava/lang/String;
       557: astore_3
       558: goto          833
       561: goto          564
       564: getstatic     #148                // Field org/scalatest/tools/PresentScopeOpened$.MODULE$:Lorg/scalatest/tools/PresentScopeOpened$;
       567: aload         4
       569: invokevirtual #43                 // Method java/lang/Object.equals:(Ljava/lang/Object;)Z
       572: ifeq          598
       575: iload_2
       576: ifeq          588
       579: getstatic     #210                // Field org/scalatest/Resources$.MODULE$:Lorg/scalatest/Resources$;
       582: invokevirtual #289                // Method org/scalatest/Resources$.RERUN_SCOPE_OPENED:()Ljava/lang/String;
       585: goto          594
       588: getstatic     #210                // Field org/scalatest/Resources$.MODULE$:Lorg/scalatest/Resources$;
       591: invokevirtual #291                // Method org/scalatest/Resources$.SCOPE_OPENED:()Ljava/lang/String;
       594: astore_3
       595: goto          833
       598: goto          601
       601: getstatic     #155                // Field org/scalatest/tools/PresentScopeClosed$.MODULE$:Lorg/scalatest/tools/PresentScopeClosed$;
       604: aload         4
       606: invokevirtual #43                 // Method java/lang/Object.equals:(Ljava/lang/Object;)Z
       609: ifeq          635
       612: iload_2
       613: ifeq          625
       616: getstatic     #210                // Field org/scalatest/Resources$.MODULE$:Lorg/scalatest/Resources$;
       619: invokevirtual #294                // Method org/scalatest/Resources$.RERUN_SCOPE_CLOSED:()Ljava/lang/String;
       622: goto          631
       625: getstatic     #210                // Field org/scalatest/Resources$.MODULE$:Lorg/scalatest/Resources$;
       628: invokevirtual #296                // Method org/scalatest/Resources$.SCOPE_CLOSED:()Ljava/lang/String;
       631: astore_3
       632: goto          833
       635: goto          638
       638: getstatic     #162                // Field org/scalatest/tools/PresentScopePending$.MODULE$:Lorg/scalatest/tools/PresentScopePending$;
       641: aload         4
       643: invokevirtual #43                 // Method java/lang/Object.equals:(Ljava/lang/Object;)Z
       646: ifeq          672
       649: iload_2
       650: ifeq          662
       653: getstatic     #210                // Field org/scalatest/Resources$.MODULE$:Lorg/scalatest/Resources$;
       656: invokevirtual #299                // Method org/scalatest/Resources$.RERUN_SCOPE_PENDING:()Ljava/lang/String;
       659: goto          668
       662: getstatic     #210                // Field org/scalatest/Resources$.MODULE$:Lorg/scalatest/Resources$;
       665: invokevirtual #301                // Method org/scalatest/Resources$.SCOPE_PENDING:()Ljava/lang/String;
       668: astore_3
       669: goto          833
       672: goto          675
       675: getstatic     #169                // Field org/scalatest/tools/PresentMarkupProvided$.MODULE$:Lorg/scalatest/tools/PresentMarkupProvided$;
       678: aload         4
       680: invokevirtual #43                 // Method java/lang/Object.equals:(Ljava/lang/Object;)Z
       683: ifeq          709
       686: iload_2
       687: ifeq          699
       690: getstatic     #210                // Field org/scalatest/Resources$.MODULE$:Lorg/scalatest/Resources$;
       693: invokevirtual #304                // Method org/scalatest/Resources$.RERUN_MARKUP_PROVIDED:()Ljava/lang/String;
       696: goto          705
       699: getstatic     #210                // Field org/scalatest/Resources$.MODULE$:Lorg/scalatest/Resources$;
       702: invokevirtual #306                // Method org/scalatest/Resources$.MARKUP_PROVIDED:()Ljava/lang/String;
       705: astore_3
       706: goto          833
       709: goto          712
       712: getstatic     #176                // Field org/scalatest/tools/PresentRunStopped$.MODULE$:Lorg/scalatest/tools/PresentRunStopped$;
       715: aload         4
       717: invokevirtual #43                 // Method java/lang/Object.equals:(Ljava/lang/Object;)Z
       720: ifeq          746
       723: iload_2
       724: ifeq          736
       727: getstatic     #210                // Field org/scalatest/Resources$.MODULE$:Lorg/scalatest/Resources$;
       730: invokevirtual #309                // Method org/scalatest/Resources$.RERUN_RUN_STOPPED:()Ljava/lang/String;
       733: goto          742
       736: getstatic     #210                // Field org/scalatest/Resources$.MODULE$:Lorg/scalatest/Resources$;
       739: invokevirtual #311                // Method org/scalatest/Resources$.RUN_STOPPED:()Ljava/lang/String;
       742: astore_3
       743: goto          833
       746: goto          749
       749: getstatic     #183                // Field org/scalatest/tools/PresentRunAborted$.MODULE$:Lorg/scalatest/tools/PresentRunAborted$;
       752: aload         4
       754: invokevirtual #43                 // Method java/lang/Object.equals:(Ljava/lang/Object;)Z
       757: ifeq          783
       760: iload_2
       761: ifeq          773
       764: getstatic     #210                // Field org/scalatest/Resources$.MODULE$:Lorg/scalatest/Resources$;
       767: invokevirtual #314                // Method org/scalatest/Resources$.RERUN_RUN_ABORTED:()Ljava/lang/String;
       770: goto          779
       773: getstatic     #210                // Field org/scalatest/Resources$.MODULE$:Lorg/scalatest/Resources$;
       776: invokevirtual #316                // Method org/scalatest/Resources$.RUN_ABORTED:()Ljava/lang/String;
       779: astore_3
       780: goto          833
       783: goto          786
       786: getstatic     #190                // Field org/scalatest/tools/PresentRunCompleted$.MODULE$:Lorg/scalatest/tools/PresentRunCompleted$;
       789: aload         4
       791: invokevirtual #43                 // Method java/lang/Object.equals:(Ljava/lang/Object;)Z
       794: ifeq          820
       797: iload_2
       798: ifeq          810
       801: getstatic     #210                // Field org/scalatest/Resources$.MODULE$:Lorg/scalatest/Resources$;
       804: invokevirtual #318                // Method org/scalatest/Resources$.RUN_COMPLETED:()Ljava/lang/String;
       807: goto          816
       810: getstatic     #210                // Field org/scalatest/Resources$.MODULE$:Lorg/scalatest/Resources$;
       813: invokevirtual #318                // Method org/scalatest/Resources$.RUN_COMPLETED:()Ljava/lang/String;
       816: astore_3
       817: goto          833
       820: goto          823
       823: new           #194                // class scala/MatchError
       826: dup
       827: aload         4
       829: invokespecial #197                // Method scala/MatchError."<init>":(Ljava/lang/Object;)V
       832: athrow
       833: aload_3
       834: areturn
      StackMapTable: number_of_entries = 89
        frame_type = 253 /* append */
          offset_delta = 33
          locals = [ top, class org/scalatest/tools/EventToPresent ]
        frame_type = 69 /* same_locals_1_stack_item */
          stack = [ class java/lang/String ]
        frame_type = 3 /* same */
        frame_type = 2 /* same */
        frame_type = 23 /* same */
        frame_type = 69 /* same_locals_1_stack_item */
          stack = [ class java/lang/String ]
        frame_type = 3 /* same */
        frame_type = 2 /* same */
        frame_type = 23 /* same */
        frame_type = 69 /* same_locals_1_stack_item */
          stack = [ class java/lang/String ]
        frame_type = 3 /* same */
        frame_type = 2 /* same */
        frame_type = 23 /* same */
        frame_type = 69 /* same_locals_1_stack_item */
          stack = [ class java/lang/String ]
        frame_type = 3 /* same */
        frame_type = 2 /* same */
        frame_type = 23 /* same */
        frame_type = 69 /* same_locals_1_stack_item */
          stack = [ class java/lang/String ]
        frame_type = 3 /* same */
        frame_type = 2 /* same */
        frame_type = 23 /* same */
        frame_type = 69 /* same_locals_1_stack_item */
          stack = [ class java/lang/String ]
        frame_type = 3 /* same */
        frame_type = 2 /* same */
        frame_type = 23 /* same */
        frame_type = 69 /* same_locals_1_stack_item */
          stack = [ class java/lang/String ]
        frame_type = 3 /* same */
        frame_type = 2 /* same */
        frame_type = 23 /* same */
        frame_type = 69 /* same_locals_1_stack_item */
          stack = [ class java/lang/String ]
        frame_type = 3 /* same */
        frame_type = 2 /* same */
        frame_type = 23 /* same */
        frame_type = 69 /* same_locals_1_stack_item */
          stack = [ class java/lang/String ]
        frame_type = 3 /* same */
        frame_type = 2 /* same */
        frame_type = 23 /* same */
        frame_type = 69 /* same_locals_1_stack_item */
          stack = [ class java/lang/String ]
        frame_type = 3 /* same */
        frame_type = 2 /* same */
        frame_type = 23 /* same */
        frame_type = 69 /* same_locals_1_stack_item */
          stack = [ class java/lang/String ]
        frame_type = 3 /* same */
        frame_type = 2 /* same */
        frame_type = 23 /* same */
        frame_type = 69 /* same_locals_1_stack_item */
          stack = [ class java/lang/String ]
        frame_type = 3 /* same */
        frame_type = 2 /* same */
        frame_type = 23 /* same */
        frame_type = 69 /* same_locals_1_stack_item */
          stack = [ class java/lang/String ]
        frame_type = 3 /* same */
        frame_type = 2 /* same */
        frame_type = 23 /* same */
        frame_type = 69 /* same_locals_1_stack_item */
          stack = [ class java/lang/String ]
        frame_type = 3 /* same */
        frame_type = 2 /* same */
        frame_type = 23 /* same */
        frame_type = 69 /* same_locals_1_stack_item */
          stack = [ class java/lang/String ]
        frame_type = 3 /* same */
        frame_type = 2 /* same */
        frame_type = 23 /* same */
        frame_type = 69 /* same_locals_1_stack_item */
          stack = [ class java/lang/String ]
        frame_type = 3 /* same */
        frame_type = 2 /* same */
        frame_type = 23 /* same */
        frame_type = 69 /* same_locals_1_stack_item */
          stack = [ class java/lang/String ]
        frame_type = 3 /* same */
        frame_type = 2 /* same */
        frame_type = 23 /* same */
        frame_type = 69 /* same_locals_1_stack_item */
          stack = [ class java/lang/String ]
        frame_type = 3 /* same */
        frame_type = 2 /* same */
        frame_type = 23 /* same */
        frame_type = 69 /* same_locals_1_stack_item */
          stack = [ class java/lang/String ]
        frame_type = 3 /* same */
        frame_type = 2 /* same */
        frame_type = 23 /* same */
        frame_type = 69 /* same_locals_1_stack_item */
          stack = [ class java/lang/String ]
        frame_type = 3 /* same */
        frame_type = 2 /* same */
        frame_type = 23 /* same */
        frame_type = 69 /* same_locals_1_stack_item */
          stack = [ class java/lang/String ]
        frame_type = 3 /* same */
        frame_type = 2 /* same */
        frame_type = 23 /* same */
        frame_type = 69 /* same_locals_1_stack_item */
          stack = [ class java/lang/String ]
        frame_type = 3 /* same */
        frame_type = 2 /* same */
        frame_type = 255 /* full_frame */
          offset_delta = 9
          locals = [ class org/scalatest/tools/RunnerJFrame$, class org/scalatest/events/Event, int, class java/lang/String, class org/scalatest/tools/EventToPresent ]
          stack = []
      LineNumberTable:
        line 1664: 0
        line 1665: 9
        line 1666: 46
        line 1667: 83
        line 1668: 120
        line 1669: 157
        line 1670: 194
        line 1671: 231
        line 1672: 268
        line 1673: 305
        line 1674: 342
        line 1675: 379
        line 1676: 416
        line 1677: 453
        line 1678: 490
        line 1679: 527
        line 1680: 564
        line 1681: 601
        line 1682: 638
        line 1683: 675
        line 1684: 712
        line 1685: 749
        line 1686: 786
        line 1664: 823
      LocalVariableTable:
        Start  Length  Slot  Name   Signature
            0     835     0  this   Lorg/scalatest/tools/RunnerJFrame$;
            0     835     1 event   Lorg/scalatest/events/Event;
            0     835     2 isRerun   Z
    MethodParameters:
      Name                           Flags
      event                          final
      isRerun                        final

  public java.lang.String getEventToPresentMenuPresentDisplayMessage(org.scalatest.tools.EventToPresent);
    descriptor: (Lorg/scalatest/tools/EventToPresent;)Ljava/lang/String;
    flags: (0x0001) ACC_PUBLIC
    Code:
      stack=3, locals=4, args_size=2
         0: aload_1
         1: astore_3
         2: getstatic     #39                 // Field org/scalatest/tools/PresentDiscoveryStarting$.MODULE$:Lorg/scalatest/tools/PresentDiscoveryStarting$;
         5: aload_3
         6: invokevirtual #43                 // Method java/lang/Object.equals:(Ljava/lang/Object;)Z
         9: ifeq          22
        12: getstatic     #210                // Field org/scalatest/Resources$.MODULE$:Lorg/scalatest/Resources$;
        15: invokevirtual #325                // Method org/scalatest/Resources$.MENU_PRESENT_DISCOVERY_STARTING:()Ljava/lang/String;
        18: astore_2
        19: goto          517
        22: goto          25
        25: getstatic     #50                 // Field org/scalatest/tools/PresentDiscoveryCompleted$.MODULE$:Lorg/scalatest/tools/PresentDiscoveryCompleted$;
        28: aload_3
        29: invokevirtual #43                 // Method java/lang/Object.equals:(Ljava/lang/Object;)Z
        32: ifeq          45
        35: getstatic     #210                // Field org/scalatest/Resources$.MODULE$:Lorg/scalatest/Resources$;
        38: invokevirtual #328                // Method org/scalatest/Resources$.MENU_PRESENT_DISCOVERY_COMPLETED:()Ljava/lang/String;
        41: astore_2
        42: goto          517
        45: goto          48
        48: getstatic     #57                 // Field org/scalatest/tools/PresentRunStarting$.MODULE$:Lorg/scalatest/tools/PresentRunStarting$;
        51: aload_3
        52: invokevirtual #43                 // Method java/lang/Object.equals:(Ljava/lang/Object;)Z
        55: ifeq          68
        58: getstatic     #210                // Field org/scalatest/Resources$.MODULE$:Lorg/scalatest/Resources$;
        61: invokevirtual #331                // Method org/scalatest/Resources$.MENU_PRESENT_RUN_STARTING:()Ljava/lang/String;
        64: astore_2
        65: goto          517
        68: goto          71
        71: getstatic     #64                 // Field org/scalatest/tools/PresentTestStarting$.MODULE$:Lorg/scalatest/tools/PresentTestStarting$;
        74: aload_3
        75: invokevirtual #43                 // Method java/lang/Object.equals:(Ljava/lang/Object;)Z
        78: ifeq          91
        81: getstatic     #210                // Field org/scalatest/Resources$.MODULE$:Lorg/scalatest/Resources$;
        84: invokevirtual #334                // Method org/scalatest/Resources$.MENU_PRESENT_TEST_STARTING:()Ljava/lang/String;
        87: astore_2
        88: goto          517
        91: goto          94
        94: getstatic     #71                 // Field org/scalatest/tools/PresentTestFailed$.MODULE$:Lorg/scalatest/tools/PresentTestFailed$;
        97: aload_3
        98: invokevirtual #43                 // Method java/lang/Object.equals:(Ljava/lang/Object;)Z
       101: ifeq          114
       104: getstatic     #210                // Field org/scalatest/Resources$.MODULE$:Lorg/scalatest/Resources$;
       107: invokevirtual #337                // Method org/scalatest/Resources$.MENU_PRESENT_TEST_FAILED:()Ljava/lang/String;
       110: astore_2
       111: goto          517
       114: goto          117
       117: getstatic     #78                 // Field org/scalatest/tools/PresentTestSucceeded$.MODULE$:Lorg/scalatest/tools/PresentTestSucceeded$;
       120: aload_3
       121: invokevirtual #43                 // Method java/lang/Object.equals:(Ljava/lang/Object;)Z
       124: ifeq          137
       127: getstatic     #210                // Field org/scalatest/Resources$.MODULE$:Lorg/scalatest/Resources$;
       130: invokevirtual #340                // Method org/scalatest/Resources$.MENU_PRESENT_TEST_SUCCEEDED:()Ljava/lang/String;
       133: astore_2
       134: goto          517
       137: goto          140
       140: getstatic     #85                 // Field org/scalatest/tools/PresentTestIgnored$.MODULE$:Lorg/scalatest/tools/PresentTestIgnored$;
       143: aload_3
       144: invokevirtual #43                 // Method java/lang/Object.equals:(Ljava/lang/Object;)Z
       147: ifeq          160
       150: getstatic     #210                // Field org/scalatest/Resources$.MODULE$:Lorg/scalatest/Resources$;
       153: invokevirtual #343                // Method org/scalatest/Resources$.MENU_PRESENT_TEST_IGNORED:()Ljava/lang/String;
       156: astore_2
       157: goto          517
       160: goto          163
       163: getstatic     #92                 // Field org/scalatest/tools/PresentTestPending$.MODULE$:Lorg/scalatest/tools/PresentTestPending$;
       166: aload_3
       167: invokevirtual #43                 // Method java/lang/Object.equals:(Ljava/lang/Object;)Z
       170: ifeq          183
       173: getstatic     #210                // Field org/scalatest/Resources$.MODULE$:Lorg/scalatest/Resources$;
       176: invokevirtual #346                // Method org/scalatest/Resources$.MENU_PRESENT_TEST_PENDING:()Ljava/lang/String;
       179: astore_2
       180: goto          517
       183: goto          186
       186: getstatic     #99                 // Field org/scalatest/tools/PresentTestCanceled$.MODULE$:Lorg/scalatest/tools/PresentTestCanceled$;
       189: aload_3
       190: invokevirtual #43                 // Method java/lang/Object.equals:(Ljava/lang/Object;)Z
       193: ifeq          206
       196: getstatic     #210                // Field org/scalatest/Resources$.MODULE$:Lorg/scalatest/Resources$;
       199: invokevirtual #349                // Method org/scalatest/Resources$.MENU_PRESENT_TEST_CANCELED:()Ljava/lang/String;
       202: astore_2
       203: goto          517
       206: goto          209
       209: getstatic     #106                // Field org/scalatest/tools/PresentSuiteStarting$.MODULE$:Lorg/scalatest/tools/PresentSuiteStarting$;
       212: aload_3
       213: invokevirtual #43                 // Method java/lang/Object.equals:(Ljava/lang/Object;)Z
       216: ifeq          229
       219: getstatic     #210                // Field org/scalatest/Resources$.MODULE$:Lorg/scalatest/Resources$;
       222: invokevirtual #352                // Method org/scalatest/Resources$.MENU_PRESENT_SUITE_STARTING:()Ljava/lang/String;
       225: astore_2
       226: goto          517
       229: goto          232
       232: getstatic     #113                // Field org/scalatest/tools/PresentSuiteAborted$.MODULE$:Lorg/scalatest/tools/PresentSuiteAborted$;
       235: aload_3
       236: invokevirtual #43                 // Method java/lang/Object.equals:(Ljava/lang/Object;)Z
       239: ifeq          252
       242: getstatic     #210                // Field org/scalatest/Resources$.MODULE$:Lorg/scalatest/Resources$;
       245: invokevirtual #355                // Method org/scalatest/Resources$.MENU_PRESENT_SUITE_ABORTED:()Ljava/lang/String;
       248: astore_2
       249: goto          517
       252: goto          255
       255: getstatic     #120                // Field org/scalatest/tools/PresentSuiteCompleted$.MODULE$:Lorg/scalatest/tools/PresentSuiteCompleted$;
       258: aload_3
       259: invokevirtual #43                 // Method java/lang/Object.equals:(Ljava/lang/Object;)Z
       262: ifeq          275
       265: getstatic     #210                // Field org/scalatest/Resources$.MODULE$:Lorg/scalatest/Resources$;
       268: invokevirtual #358                // Method org/scalatest/Resources$.MENU_PRESENT_SUITE_COMPLETED:()Ljava/lang/String;
       271: astore_2
       272: goto          517
       275: goto          278
       278: getstatic     #127                // Field org/scalatest/tools/PresentInfoProvided$.MODULE$:Lorg/scalatest/tools/PresentInfoProvided$;
       281: aload_3
       282: invokevirtual #43                 // Method java/lang/Object.equals:(Ljava/lang/Object;)Z
       285: ifeq          298
       288: getstatic     #210                // Field org/scalatest/Resources$.MODULE$:Lorg/scalatest/Resources$;
       291: invokevirtual #361                // Method org/scalatest/Resources$.MENU_PRESENT_INFO_PROVIDED:()Ljava/lang/String;
       294: astore_2
       295: goto          517
       298: goto          301
       301: getstatic     #134                // Field org/scalatest/tools/PresentAlertProvided$.MODULE$:Lorg/scalatest/tools/PresentAlertProvided$;
       304: aload_3
       305: invokevirtual #43                 // Method java/lang/Object.equals:(Ljava/lang/Object;)Z
       308: ifeq          321
       311: getstatic     #210                // Field org/scalatest/Resources$.MODULE$:Lorg/scalatest/Resources$;
       314: invokevirtual #364                // Method org/scalatest/Resources$.MENU_PRESENT_ALERT_PROVIDED:()Ljava/lang/String;
       317: astore_2
       318: goto          517
       321: goto          324
       324: getstatic     #141                // Field org/scalatest/tools/PresentNoteProvided$.MODULE$:Lorg/scalatest/tools/PresentNoteProvided$;
       327: aload_3
       328: invokevirtual #43                 // Method java/lang/Object.equals:(Ljava/lang/Object;)Z
       331: ifeq          344
       334: getstatic     #210                // Field org/scalatest/Resources$.MODULE$:Lorg/scalatest/Resources$;
       337: invokevirtual #367                // Method org/scalatest/Resources$.MENU_PRESENT_NOTE_PROVIDED:()Ljava/lang/String;
       340: astore_2
       341: goto          517
       344: goto          347
       347: getstatic     #148                // Field org/scalatest/tools/PresentScopeOpened$.MODULE$:Lorg/scalatest/tools/PresentScopeOpened$;
       350: aload_3
       351: invokevirtual #43                 // Method java/lang/Object.equals:(Ljava/lang/Object;)Z
       354: ifeq          367
       357: getstatic     #210                // Field org/scalatest/Resources$.MODULE$:Lorg/scalatest/Resources$;
       360: invokevirtual #370                // Method org/scalatest/Resources$.MENU_PRESENT_SCOPE_OPENED:()Ljava/lang/String;
       363: astore_2
       364: goto          517
       367: goto          370
       370: getstatic     #155                // Field org/scalatest/tools/PresentScopeClosed$.MODULE$:Lorg/scalatest/tools/PresentScopeClosed$;
       373: aload_3
       374: invokevirtual #43                 // Method java/lang/Object.equals:(Ljava/lang/Object;)Z
       377: ifeq          390
       380: getstatic     #210                // Field org/scalatest/Resources$.MODULE$:Lorg/scalatest/Resources$;
       383: invokevirtual #373                // Method org/scalatest/Resources$.MENU_PRESENT_SCOPE_CLOSED:()Ljava/lang/String;
       386: astore_2
       387: goto          517
       390: goto          393
       393: getstatic     #162                // Field org/scalatest/tools/PresentScopePending$.MODULE$:Lorg/scalatest/tools/PresentScopePending$;
       396: aload_3
       397: invokevirtual #43                 // Method java/lang/Object.equals:(Ljava/lang/Object;)Z
       400: ifeq          413
       403: getstatic     #210                // Field org/scalatest/Resources$.MODULE$:Lorg/scalatest/Resources$;
       406: invokevirtual #376                // Method org/scalatest/Resources$.MENU_PRESENT_SCOPE_PENDING:()Ljava/lang/String;
       409: astore_2
       410: goto          517
       413: goto          416
       416: getstatic     #169                // Field org/scalatest/tools/PresentMarkupProvided$.MODULE$:Lorg/scalatest/tools/PresentMarkupProvided$;
       419: aload_3
       420: invokevirtual #43                 // Method java/lang/Object.equals:(Ljava/lang/Object;)Z
       423: ifeq          436
       426: getstatic     #210                // Field org/scalatest/Resources$.MODULE$:Lorg/scalatest/Resources$;
       429: invokevirtual #379                // Method org/scalatest/Resources$.MENU_PRESENT_MARKUP_PROVIDED:()Ljava/lang/String;
       432: astore_2
       433: goto          517
       436: goto          439
       439: getstatic     #176                // Field org/scalatest/tools/PresentRunStopped$.MODULE$:Lorg/scalatest/tools/PresentRunStopped$;
       442: aload_3
       443: invokevirtual #43                 // Method java/lang/Object.equals:(Ljava/lang/Object;)Z
       446: ifeq          459
       449: getstatic     #210                // Field org/scalatest/Resources$.MODULE$:Lorg/scalatest/Resources$;
       452: invokevirtual #382                // Method org/scalatest/Resources$.MENU_PRESENT_RUN_STOPPED:()Ljava/lang/String;
       455: astore_2
       456: goto          517
       459: goto          462
       462: getstatic     #183                // Field org/scalatest/tools/PresentRunAborted$.MODULE$:Lorg/scalatest/tools/PresentRunAborted$;
       465: aload_3
       466: invokevirtual #43                 // Method java/lang/Object.equals:(Ljava/lang/Object;)Z
       469: ifeq          482
       472: getstatic     #210                // Field org/scalatest/Resources$.MODULE$:Lorg/scalatest/Resources$;
       475: invokevirtual #385                // Method org/scalatest/Resources$.MENU_PRESENT_RUN_ABORTED:()Ljava/lang/String;
       478: astore_2
       479: goto          517
       482: goto          485
       485: getstatic     #190                // Field org/scalatest/tools/PresentRunCompleted$.MODULE$:Lorg/scalatest/tools/PresentRunCompleted$;
       488: aload_3
       489: invokevirtual #43                 // Method java/lang/Object.equals:(Ljava/lang/Object;)Z
       492: ifeq          505
       495: getstatic     #210                // Field org/scalatest/Resources$.MODULE$:Lorg/scalatest/Resources$;
       498: invokevirtual #388                // Method org/scalatest/Resources$.MENU_PRESENT_RUN_COMPLETED:()Ljava/lang/String;
       501: astore_2
       502: goto          517
       505: goto          508
       508: new           #194                // class scala/MatchError
       511: dup
       512: aload_3
       513: invokespecial #197                // Method scala/MatchError."<init>":(Ljava/lang/Object;)V
       516: athrow
       517: aload_2
       518: areturn
      StackMapTable: number_of_entries = 45
        frame_type = 253 /* append */
          offset_delta = 22
          locals = [ top, class org/scalatest/tools/EventToPresent ]
        frame_type = 2 /* same */
        frame_type = 19 /* same */
        frame_type = 2 /* same */
        frame_type = 19 /* same */
        frame_type = 2 /* same */
        frame_type = 19 /* same */
        frame_type = 2 /* same */
        frame_type = 19 /* same */
        frame_type = 2 /* same */
        frame_type = 19 /* same */
        frame_type = 2 /* same */
        frame_type = 19 /* same */
        frame_type = 2 /* same */
        frame_type = 19 /* same */
        frame_type = 2 /* same */
        frame_type = 19 /* same */
        frame_type = 2 /* same */
        frame_type = 19 /* same */
        frame_type = 2 /* same */
        frame_type = 19 /* same */
        frame_type = 2 /* same */
        frame_type = 19 /* same */
        frame_type = 2 /* same */
        frame_type = 19 /* same */
        frame_type = 2 /* same */
        frame_type = 19 /* same */
        frame_type = 2 /* same */
        frame_type = 19 /* same */
        frame_type = 2 /* same */
        frame_type = 19 /* same */
        frame_type = 2 /* same */
        frame_type = 19 /* same */
        frame_type = 2 /* same */
        frame_type = 19 /* same */
        frame_type = 2 /* same */
        frame_type = 19 /* same */
        frame_type = 2 /* same */
        frame_type = 19 /* same */
        frame_type = 2 /* same */
        frame_type = 19 /* same */
        frame_type = 2 /* same */
        frame_type = 19 /* same */
        frame_type = 2 /* same */
        frame_type = 255 /* full_frame */
          offset_delta = 8
          locals = [ class org/scalatest/tools/RunnerJFrame$, class org/scalatest/tools/EventToPresent, class java/lang/String, class org/scalatest/tools/EventToPresent ]
          stack = []
      LineNumberTable:
        line 1690: 0
        line 1691: 2
        line 1692: 25
        line 1693: 48
        line 1694: 71
        line 1695: 94
        line 1696: 117
        line 1697: 140
        line 1698: 163
        line 1699: 186
        line 1700: 209
        line 1701: 232
        line 1702: 255
        line 1703: 278
        line 1704: 301
        line 1705: 324
        line 1706: 347
        line 1707: 370
        line 1708: 393
        line 1709: 416
        line 1710: 439
        line 1711: 462
        line 1712: 485
        line 1690: 508
      LocalVariableTable:
        Start  Length  Slot  Name   Signature
            0     519     0  this   Lorg/scalatest/tools/RunnerJFrame$;
            0     519     1 eventToPresent   Lorg/scalatest/tools/EventToPresent;
    MethodParameters:
      Name                           Flags
      eventToPresent                 final

  private java.lang.Object writeReplace();
    descriptor: ()Ljava/lang/Object;
    flags: (0x0002) ACC_PRIVATE
    Code:
      stack=3, locals=1, args_size=1
         0: new           #392                // class scala/runtime/ModuleSerializationProxy
         3: dup
         4: ldc           #2                  // class org/scalatest/tools/RunnerJFrame$
         6: invokespecial #395                // Method scala/runtime/ModuleSerializationProxy."<init>":(Ljava/lang/Class;)V
         9: areturn
      LineNumberTable:
        line 1633: 0
      LocalVariableTable:
        Start  Length  Slot  Name   Signature
            0      10     0  this   Lorg/scalatest/tools/RunnerJFrame$;

  private org.scalatest.tools.RunnerJFrame$();
    descriptor: ()V
    flags: (0x0002) ACC_PRIVATE
    Code:
      stack=1, locals=1, args_size=1
         0: aload_0
         1: invokespecial #396                // Method java/lang/Object."<init>":()V
         4: return
      LineNumberTable:
        line 1715: 0
        line 1633: 4
      LocalVariableTable:
        Start  Length  Slot  Name   Signature
            0       5     0  this   Lorg/scalatest/tools/RunnerJFrame$;
}
SourceFile: "RunnerJFrame.scala"
  ScalaInlineInfo: length = 0x22 (unknown attribute)
   01 01 00 06 00 0C 00 0B 01 00 CB 00 CC 01 01 42
   00 1D 01 00 11 00 12 01 00 11 00 1D 01 01 85 01
   86 01
  Scala: length = 0x0 (unknown attribute)

