Classfile /Users/mw/Projects/slang-braindump/.jar/jar8/assemble/slang-braindump/assemble/content/org/scalatest/tools/Runner.class
  Last modified May 29, 2022; size 4433 bytes
  SHA-256 checksum 1b44be9035bcb7194fa2f2b732ea0bdf3089d07a635de30d92c66508b2d6e4fb
  Compiled from "Runner.scala"
public final class org.scalatest.tools.Runner
  minor version: 0
  major version: 52
  flags: (0x0031) ACC_PUBLIC, ACC_FINAL, ACC_SUPER
  this_class: #2                          // org/scalatest/tools/Runner
  super_class: #4                         // java/lang/Object
  interfaces: 0, fields: 0, methods: 2, attributes: 4
Constant pool:
   #1 = Utf8               org/scalatest/tools/Runner
   #2 = Class              #1             // org/scalatest/tools/Runner
   #3 = Utf8               java/lang/Object
   #4 = Class              #3             // java/lang/Object
   #5 = Utf8               Runner.scala
   #6 = Utf8               Lscala/reflect/ScalaSignature;
   #7 = Utf8               bytes
   #8 = Utf8               \u0006\u0005\tUw!\u0002\u0013&\u0011\u0003ac!\u0002\u0018&\u0011\u0003y\u0003\"\u0002\u001c\u0002\t\u00039\u0004b\u0002\u001d\u0002\u0005\u0004%I!\u000f\u0005\u0007{\u0005\u0001\u000b\u0011\u0002\u001e\t\u000fy\n!\u0019!C\u0005s!1q(\u0001Q\u0001\niB\u0001\u0002Q\u0001A\u0002\u0013\u0005q%\u0011\u0005\t\u000b\u0006\u0001\r\u0011\"\u0001(\r\"1A*\u0001Q!\n\tCq!U\u0001C\u0002\u00135!\u000b\u0003\u0004V\u0003\u0001\u0006ia\u0015\u0004\u0005-\u0006!q\u000bC\u00037\u0019\u0011\u0005A\fC\u0004`\u0019\u0001\u0007I\u0011\u00021\t\u000f\u0011d\u0001\u0019!C\u0005K\"1q\r\u0004Q!\n\u0005Dq!\u001b\u0007C\u0002\u0013%!\u000e\u0003\u0004v\u0019\u0001\u0006Ia\u001b\u0005\u0006m2!\te\u001e\u0005\u0007\u0003\u0003aA\u0011\u00011\t\u000f\u0005\r\u0011\u0001\"\u0001\u0002\u0006!9\u0011qE\u0001\u0005\u0002\u0005%\u0002bBA\u0017\u0003\u0011%\u0011q\u0006\u0005\n\u0003o\t!\u0019!C\u0005\u0003sA\u0001\"a\u0012\u0002A\u0003%\u00111\b\u0005\t\u0003\u0013\nA\u0011A\u0014\u0002L!A\u00111P\u0001\u0005\u0002\u001d\ni\b\u0003\u0005\u0002\n\u0006!\taJAF\u0011!\u0011\t%\u0001C\u0001K\t\r\u0003\u0002\u0003B\'\u0003\u0011\u0005QEa\u0014\t\u0011\t\r\u0014\u0001\"\u0001&\u0005KB\u0001Ba\u001d\u0002\t\u00039#Q\u000f\u0005\t\u0005\u0013\u000bA\u0011A\u0014\u0003\f\"A!1Y\u0001\u0005\u0002\u001d\u0012)\r\u0003\u0005\u0003J\u0006!\ta\nBf\u0003\u0019\u0011VO\u001c8fe*\u0011aeJ\u0001\u0006i>|Gn\u001d\u0006\u0003Q%\n\u0011b]2bY\u0006$Xm\u001d;\u000b\u0003)\n1a\u001c:h\u0007\u0001\u0001\"!L\u0001\u000e\u0003\u0015\u0012aAU;o]\u0016\u00148CA\u00011!\t\tD\'D\u00013\u0015\u0005\u0019\u0014!B:dC2\f\u0017BA\u001b3\u0005\u0019\te.\u001f*fM\u00061A(\u001b8jiz\"\u0012\u0001L\u0001\u0016%Vse*\u0012*`\u0015\u001a\u0013\u0016)T#`\'R\u000b%\u000bV0Y+\u0005Q\u0004CA\u0019<\u0013\ta$GA\u0002J]R\faCU+O\u001d\u0016\u0013vL\u0013$S\u00036+ul\u0015+B%R{\u0006\fI\u0001\u0016%Vse*\u0012*`\u0015\u001a\u0013\u0016)T#`\'R\u000b%\u000bV0Z\u0003Y\u0011VK\u0014(F%~SeIU!N\u000b~\u001bF+\u0011*U?f\u0003\u0013aD:qC:\u001c6-\u00197f\r\u0006\u001cGo\u001c:\u0016\u0003\t\u0003\"!M\"\n\u0005\u0011\u0013$A\u0002#pk\ndW-A\nta\u0006t7kY1mK\u001a\u000b7\r^8s?\u0012*\u0017\u000f\u0006\u0002H\u0015B\u0011\u0011\u0007S\u0005\u0003\u0013J\u0012A!\u00168ji\"91\nCA\u0001\u0002\u0004\u0011\u0015a\u0001=%c\u0005\u00012\u000f]1o\'\u000e\fG.\u001a$bGR|\'\u000f\t\u0015\u0003\u00139\u0003\"!M(\n\u0005A\u0013$\u0001\u0003<pY\u0006$\u0018\u000e\\3\u00021\u0011+g-Y;mi:+XNR5mKN$v.\u0011:dQ&4X-F\u0001T\u001f\u0005!V$\u0001\u0002\u00023\u0011+g-Y;mi:+XNR5mKN$v.\u0011:dQ&4X\r\t\u0002\u0011!\u0006\u001c8OR1jYJ+\u0007o\u001c:uKJ\u001c2\u0001\u0004\u0019Y!\tI&,D\u0001(\u0013\tYvE\u0001\u0005SKB|\'\u000f^3s)\u0005i\u0006C\u00010\r\u001b\u0005\t\u0011A\u00064bS2,G-\u00112peR,Gm\u0014:Ti>\u0004\b/\u001a3\u0016\u0003\u0005\u0004\"!\r2\n\u0005\r\u0014$a\u0002\"p_2,\u0017M\\\u0001\u001bM\u0006LG.\u001a3BE>\u0014H/\u001a3PeN#x\u000e\u001d9fI~#S-\u001d\u000b\u0003\u000f\u001aDqaS\b\u0002\u0002\u0003\u0007\u0011-A\fgC&dW\rZ!c_J$X\rZ(s\'R|\u0007\u000f]3eA!\u0012\u0001CT\u0001\u0011eVtGi\u001c8f\'\u0016l\u0017\r\u001d5pe\u0016,\u0012a\u001b\t\u0003YNl\u0011!\u001c\u0006\u0003]>\f!bY8oGV\u0014(/\u001a8u\u0015\t\u0001\u0018/\u0001\u0003vi&d\'\"\u0001:\u0002\t)\fg/Y\u0005\u0003i6\u0014\u0011bU3nCBDwN]3\u0002#I,h\u000eR8oKN+W.\u00199i_J,\u0007%A\u0003baBd\u0017\u0010\u0006\u0002Hq\")\u0011p\u0005a\u0001u\u0006)QM^3oiB\u00111P`\u0007\u0002y*\u0011QpJ\u0001\u0007KZ,g\u000e^:\n\u0005}d(!B#wK:$\u0018AD1mYR+7\u000f^:QCN\u001cX\rZ\u0001\u0005[\u0006Lg\u000eF\u0002H\u0003\u000fAq!!\u0003\u0016\u0001\u0004\tY!\u0001\u0003be\u001e\u001c\b#B\u0019\u0002\u000e\u0005E\u0011bAA\be\t)\u0011I\u001d:bsB!\u00111CA\u0011\u001d\u0011\t)\"!\b\u0011\u0007\u0005]!\'\u0004\u0002\u0002\u001a)\u0019\u00111D\u0016\u0002\rq\u0012xn\u001c;?\u0013\r\tyBM\u0001\u0007!J,G-\u001a4\n\t\u0005\r\u0012Q\u0005\u0002\u0007\'R\u0014\u0018N\\4\u000b\u0007\u0005}!\'A\u0002sk:$2!YA\u0016\u0011\u001d\tIA\u0006a\u0001\u0003\u0017\t\u0011E];o\u001fB$\u0018n\u001c8bY2Lx+\u001b;i!\u0006\u001c8OR1jYJ+\u0007o\u001c:uKJ$R!YA\u0019\u0003gAq!!\u0003\u0018\u0001\u0004\tY\u0001\u0003\u0004\u00026]\u0001\r!Y\u0001\u0018eVtw+\u001b;i!\u0006\u001c8OR1jYJ+\u0007o\u001c:uKJ\f1#\u0019;p[&\u001cG\u000b\u001b:fC\u0012\u001cu.\u001e8uKJ,\"!a\u000f\u0011\t\u0005u\u00121I\u0007\u0003\u0003\u007fQ1!!\u0011n\u0003\u0019\tGo\\7jG&!\u0011QIA \u00055\tEo\\7jG&sG/Z4fe\u0006!\u0012\r^8nS\u000e$\u0006N]3bI\u000e{WO\u001c;fe\u0002\nQ\u0003\\8bI*+f.\u001b;Xe\u0006\u0004\b/\u001a:DY\u0006\u001c8\u000f\u0006\u0003\u0002N\u0005E\u0004\u0007BA(\u0003?\u0002b!!\u0015\u0002X\u0005mSBAA*\u0015\r\t)&]\u0001\u0005Y\u0006tw-\u0003\u0003\u0002Z\u0005M#!B\"mCN\u001c\b\u0003BA/\u0003?b\u0001\u0001B\u0006\u0002bi\t\t\u0011!A\u0003\u0002\u0005\r$AA 1#\u0011\t)\'a\u001b\u0011\u0007E\n9\'C\u0002\u0002jI\u0012qAT8uQ&tw\r\u0005\u0003\u0002R\u00055\u0014\u0002BA8\u0003\'\u0012aa\u00142kK\u000e$\bbBA:5\u0001\u0007\u0011QO\u0001\u0007Y>\fG-\u001a:\u0011\t\u0005E\u0013qO\u0005\u0005\u0003s\n\u0019FA\u0006DY\u0006\u001c8\u000fT8bI\u0016\u0014\u0018A\u00067pC\u0012$Vm\u001d;O\u000f^\u0013\u0018\r\u001d9fe\u000ec\u0017m]:\u0015\t\u0005}\u0014q\u0011\u0019\u0005\u0003\u0003\u000b)\t\u0005\u0004\u0002R\u0005]\u00131\u0011\t\u0005\u0003;\n)\tB\u0006\u0002bm\t\t\u0011!A\u0003\u0002\u0005\r\u0004bBA:7\u0001\u0007\u0011QO\u0001\u0016I>\u0014VO\u001c*v]J+h\u000eR1E_J+hNU;o)-:\u0015QRAL\u0003g\u000bI,!2\u0002J\u0006M\u0017Q\\Aq\u0003W\fi/!=\u0002v\u0006e\u0018Q`A\u0000\u0005\u0013\u0011iAa\u0006\u0003.\tE\u0002bBAH9\u0001\u0007\u0011\u0011S\u0001\tI&\u001c\b/\u0019;dQB\u0019\u0011,a%\n\u0007\u0005UuE\u0001\tESN\u0004\u0018\r^2i%\u0016\u0004xN\u001d;fe\"9\u0011\u0011\u0014\u000fA\u0002\u0005m\u0015AC:vSR,7\u000fT5tiB1\u0011QTAT\u0003[sA!a(\u0002$:!\u0011qCAQ\u0013\u0005\u0019\u0014bAASe\u00059\u0001/Y2lC\u001e,\u0017\u0002BAU\u0003W\u0013A\u0001T5ti*\u0019\u0011Q\u0015\u001a\u0011\u00075\ny+C\u0002\u00022\u0016\u0012!bU;ji\u0016\u0004\u0016M]1n\u0011\u001d\t)\f\ba\u0001\u0003o\u000ba!Y4bS:\u001c\bCBAO\u0003O\u000b\t\u0002C\u0004\u0002<r\u0001\r!!0\u0002\u0013Q,7\u000f^*qK\u000e\u001c\bCBAO\u0003O\u000by\fE\u0002.\u0003\u0003L1!a1&\u0005!!Vm\u001d;Ta\u0016\u001c\u0007bBAd9\u0001\u0007\u0011qW\u0001\u000bUVt\u0017\u000e^:MSN$\bbBAf9\u0001\u0007\u0011QZ\u0001\bgR|\u0007\u000f]3s!\rI\u0016qZ\u0005\u0004\u0003#<#aB*u_B\u0004XM\u001d\u0005\b\u0003+d\u0002\u0019AAl\u0003A!\u0018mZ:U_&s7\r\\;eKN+G\u000f\u0005\u0004\u0002\u0014\u0005e\u0017\u0011C\u0005\u0005\u00037\f)CA\u0002TKRDq!a8\u001d\u0001\u0004\t9.\u0001\tuC\u001e\u001cHk\\#yG2,H-Z*fi\"9\u00111\u001d\u000fA\u0002\u0005\u0015\u0018!C2p]\u001aLw-T1q!\rI\u0016q]\u0005\u0004\u0003S<#!C\"p]\u001aLw-T1q\u0011\u0015qG\u00041\u0001b\u0011\u001d\ty\u000f\ba\u0001\u0003o\u000bq\"\\3nE\u0016\u00148o\u00148ms2K7\u000f\u001e\u0005\b\u0003gd\u0002\u0019AA\\\u000319\u0018\u000e\u001c3dCJ$G*[:u\u0011\u001d\t9\u0010\ba\u0001\u0003o\u000b!\u0002^3ti:;E*[:u\u0011\u001d\tY\u0010\ba\u0001\u0003o\u000bqA];oa\u0006$\b\u000eC\u0004\u0002tq\u0001\r!!\u001e\t\u000f\t\u0005A\u00041\u0001\u0003\u0004\u0005aAm\u001c8f\u0019&\u001cH/\u001a8feB\u0019QF!\u0002\n\u0007\t\u001dQEA\bSk:$uN\\3MSN$XM\\3s\u0011\u0019\u0011Y\u0001\ba\u0001u\u0005A!/\u001e8Ti\u0006l\u0007\u000fC\u0004\u0003\u0010q\u0001\rA!\u0005\u0002!\r|gnY;se\u0016tGoQ8oM&<\u0007cA\u0017\u0003\u0014%\u0019!QC\u0013\u0003!\r{gnY;se\u0016tGoQ8oM&<\u0007b\u0002B\r9\u0001\u0007!1D\u0001\tgV4g-\u001b=fgB)\u0011G!\b\u0003\"%\u0019!q\u0004\u001a\u0003\r=\u0003H/[8o!\u0011\u0011\u0019C!\u000b\u000e\u0005\t\u0015\"b\u0001B\u0014_\u0006)!/Z4fq&!!1\u0006B\u0013\u0005\u001d\u0001\u0016\r\u001e;fe:DqAa\f\u001d\u0001\u0004\t9.\u0001\bdQ>\u001cXM\\*us2,7+\u001a;\t\u000f\tMB\u00041\u0001\u00036\u0005QB/Z:u\'>\u0014H/\u001b8h%\u0016\u0004xN\u001d;feRKW.Z8viB!!q\u0007B\u001f\u001b\t\u0011IDC\u0002\u0003<\u001d\nA\u0001^5nK&!!q\bB\u001d\u0005\u0011\u0019\u0006/\u00198\u0002#\u0011,w\r\\8c\'VLG/\u001a)be\u0006l7\u000f\u0006\u0004\u0002\u001c\n\u0015#\u0011\n\u0005\b\u0005\u000fj\u0002\u0019AAN\u0003%9Gn\u001c2t\u0019&\u001cH\u000fC\u0004\u0003Lu\u0001\r!a6\u0002!\u0005\u001c7-Z:tS\ndWmU;ji\u0016\u001c\u0018a\u0004:fC\u0012lU-\\8ss\u001aKG.Z:\u0015\u0011\u0005m%\u0011\u000bB+\u00053BqAa\u0015\u001f\u0001\u0004\t9,A\u0005gS2,g*Y7fg\"1!q\u000b\u0010A\u0002a\u000b\u0001B]3q_J$XM\u001d\u0005\b\u00057r\u0002\u0019\u0001B/\u0003\u001d!(/Y2lKJ\u00042!\u0017B0\u0013\r\u0011\tg\n\u0002\b)J\f7m[3s\u000399WM\\*vSR,7i\u001c8gS\u001e$bAa\u001a\u0003n\tE\u0004cA\u0017\u0003j%\u0019!1N\u0013\u0003\u0017M+\u0018\u000e^3D_:4\u0017n\u001a\u0005\b\u0005_z\u0002\u0019AAW\u0003)\u0019X/\u001b;f!\u0006\u0014\u0018-\u001c\u0005\b\u0003gz\u0002\u0019AA;\u0003I)\u0007p\u00197vI\u0016\u001cx+\u001b;i\u0013\u001etwN]3\u0015\t\t]$Q\u0011\t\u0007\u0005s\u0012\u0019)!\u0005\u000e\u0005\tm$\u0002\u0002B?\u0005\u007f\n\u0011\"[7nkR\f\'\r\\3\u000b\u0007\t\u0005%\'\u0001\u0006d_2dWm\u0019;j_:LA!a7\u0003|!9!q\u0011\u0011A\u0002\u0005]\u0017\u0001C3yG2,H-Z:\u0002E]LG\u000f[\"mCN\u001cHj\\1eKJ\fe\u000e\u001a#jgB\fGo\u00195SKB|\'\u000f^3s)A\u0011iI!\'\u0003\u001e\n\u001d&Q\u0016BY\u0005k\u0013y\fF\u0002H\u0005\u001fCqA!%\"\u0001\u0004\u0011\u0019*A\u0001g!!\t$QSA;\u0003#;\u0015b\u0001BLe\tIa)\u001e8di&|gN\r\u0005\b\u00057\u000b\u0003\u0019AA\\\u0003-\u0011XO\u001c9bi\"d\u0015n\u001d;\t\u000f\t}\u0015\u00051\u0001\u0003\"\u0006i!/\u001a9peR,\'o\u00159fGN\u00042!\fBR\u0013\r\u0011)+\n\u0002\u0017%\u0016\u0004xN\u001d;fe\u000e{gNZ5hkJ\fG/[8og\"9!\u0011V\u0011A\u0002\t-\u0016aD4sCBD\u0017n\u0019*fa>\u0014H/\u001a:\u0011\tE\u0012i\u0002\u0017\u0005\b\u0005_\u000b\u0003\u0019\u0001BV\u0003A\u0001\u0018m]:GC&d\'+\u001a9peR,\'\u000f\u0003\u0004\u00034\u0006\u0002\r!Y\u0001\u0010I\u0016$Xm\u0019;TY><\bo\\6fg\"9!qW\u0011A\u0002\te\u0016AF:m_^\u0004xn[3EKR,7\r^5p]\u0012+G.Y=\u0011\u0007E\u0012Y,C\u0002\u0003>J\u0012A\u0001T8oO\"9!\u0011Y\u0011A\u0002\te\u0016aF:m_^\u0004xn[3EKR,7\r^5p]B+\'/[8e\u0003U9W\r\u001e*v]B\fG\u000f[\"mCN\u001cHj\\1eKJ$B!!\u001e\u0003H\"9!1\u0014\u0012A\u0002\u0005]\u0016\u0001G;tS:<WI^3oi\u0012K7\u000f]1uG\"$\u0006N]3bIR\u0019qI!4\t\u0011\tE5\u0005\"a\u0001\u0005\u001f\u0004B!\rBi\u000f&\u0019!1\u001b\u001a\u0003\u0011q\u0012\u0017P\\1nKz\u0002
   #9 = Utf8               org/scalatest/tools/Runner$PassFailReporter
  #10 = Class              #9             // org/scalatest/tools/Runner$PassFailReporter
  #11 = Utf8               PassFailReporter
  #12 = Utf8               run
  #13 = Utf8               ([Ljava/lang/String;)Z
  #14 = Utf8               args
  #15 = Utf8               org/scalatest/tools/Runner$
  #16 = Class              #15            // org/scalatest/tools/Runner$
  #17 = Utf8               MODULE$
  #18 = Utf8               Lorg/scalatest/tools/Runner$;
  #19 = NameAndType        #17:#18        // MODULE$:Lorg/scalatest/tools/Runner$;
  #20 = Fieldref           #16.#19        // org/scalatest/tools/Runner$.MODULE$:Lorg/scalatest/tools/Runner$;
  #21 = NameAndType        #12:#13        // run:([Ljava/lang/String;)Z
  #22 = Methodref          #16.#21        // org/scalatest/tools/Runner$.run:([Ljava/lang/String;)Z
  #23 = Utf8               [Ljava/lang/String;
  #24 = Utf8               main
  #25 = Utf8               ([Ljava/lang/String;)V
  #26 = NameAndType        #24:#25        // main:([Ljava/lang/String;)V
  #27 = Methodref          #16.#26        // org/scalatest/tools/Runner$.main:([Ljava/lang/String;)V
  #28 = Utf8               Code
  #29 = Utf8               LocalVariableTable
  #30 = Utf8               MethodParameters
  #31 = Utf8               InnerClasses
  #32 = Utf8               SourceFile
  #33 = Utf8               RuntimeVisibleAnnotations
  #34 = Utf8               ScalaSig
{
  public static boolean run(java.lang.String[]);
    descriptor: ([Ljava/lang/String;)Z
    flags: (0x0009) ACC_PUBLIC, ACC_STATIC
    Code:
      stack=2, locals=1, args_size=1
         0: getstatic     #20                 // Field org/scalatest/tools/Runner$.MODULE$:Lorg/scalatest/tools/Runner$;
         3: aload_0
         4: invokevirtual #22                 // Method org/scalatest/tools/Runner$.run:([Ljava/lang/String;)Z
         7: ireturn
      LocalVariableTable:
        Start  Length  Slot  Name   Signature
            0       8     0  args   [Ljava/lang/String;
    MethodParameters:
      Name                           Flags
      args                           final

  public static void main(java.lang.String[]);
    descriptor: ([Ljava/lang/String;)V
    flags: (0x0009) ACC_PUBLIC, ACC_STATIC
    Code:
      stack=2, locals=1, args_size=1
         0: getstatic     #20                 // Field org/scalatest/tools/Runner$.MODULE$:Lorg/scalatest/tools/Runner$;
         3: aload_0
         4: invokevirtual #27                 // Method org/scalatest/tools/Runner$.main:([Ljava/lang/String;)V
         7: return
      LocalVariableTable:
        Start  Length  Slot  Name   Signature
            0       8     0  args   [Ljava/lang/String;
    MethodParameters:
      Name                           Flags
      args                           final
}
InnerClasses:
  private static #11= #10 of #2;          // PassFailReporter=class org/scalatest/tools/Runner$PassFailReporter of class org/scalatest/tools/Runner
SourceFile: "Runner.scala"
RuntimeVisibleAnnotations:
  0: #6(#7=s#8)
    scala.reflect.ScalaSignature(
      bytes="\u0006\u0005\tUw!\u0002\u0013&\u0011\u0003ac!\u0002\u0018&\u0011\u0003y\u0003\"\u0002\u001c\u0002\t\u00039\u0004b\u0002\u001d\u0002\u0005\u0004%I!\u000f\u0005\u0007{\u0005\u0001\u000b\u0011\u0002\u001e\t\u000fy\n!\u0019!C\u0005s!1q(\u0001Q\u0001\niB\u0001\u0002Q\u0001A\u0002\u0013\u0005q%\u0011\u0005\t\u000b\u0006\u0001\r\u0011\"\u0001(\r\"1A*\u0001Q!\n\tCq!U\u0001C\u0002\u00135!\u000b\u0003\u0004V\u0003\u0001\u0006ia\u0015\u0004\u0005-\u0006!q\u000bC\u00037\u0019\u0011\u0005A\fC\u0004`\u0019\u0001\u0007I\u0011\u00021\t\u000f\u0011d\u0001\u0019!C\u0005K\"1q\r\u0004Q!\n\u0005Dq!\u001b\u0007C\u0002\u0013%!\u000e\u0003\u0004v\u0019\u0001\u0006Ia\u001b\u0005\u0006m2!\te\u001e\u0005\u0007\u0003\u0003aA\u0011\u00011\t\u000f\u0005\r\u0011\u0001\"\u0001\u0002\u0006!9\u0011qE\u0001\u0005\u0002\u0005%\u0002bBA\u0017\u0003\u0011%\u0011q\u0006\u0005\n\u0003o\t!\u0019!C\u0005\u0003sA\u0001\"a\u0012\u0002A\u0003%\u00111\b\u0005\t\u0003\u0013\nA\u0011A\u0014\u0002L!A\u00111P\u0001\u0005\u0002\u001d\ni\b\u0003\u0005\u0002\n\u0006!\taJAF\u0011!\u0011\t%\u0001C\u0001K\t\r\u0003\u0002\u0003B\'\u0003\u0011\u0005QEa\u0014\t\u0011\t\r\u0014\u0001\"\u0001&\u0005KB\u0001Ba\u001d\u0002\t\u00039#Q\u000f\u0005\t\u0005\u0013\u000bA\u0011A\u0014\u0003\f\"A!1Y\u0001\u0005\u0002\u001d\u0012)\r\u0003\u0005\u0003J\u0006!\ta\nBf\u0003\u0019\u0011VO\u001c8fe*\u0011aeJ\u0001\u0006i>|Gn\u001d\u0006\u0003Q%\n\u0011b]2bY\u0006$Xm\u001d;\u000b\u0003)\n1a\u001c:h\u0007\u0001\u0001\"!L\u0001\u000e\u0003\u0015\u0012aAU;o]\u0016\u00148CA\u00011!\t\tD\'D\u00013\u0015\u0005\u0019\u0014!B:dC2\f\u0017BA\u001b3\u0005\u0019\te.\u001f*fM\u00061A(\u001b8jiz\"\u0012\u0001L\u0001\u0016%Vse*\u0012*`\u0015\u001a\u0013\u0016)T#`\'R\u000b%\u000bV0Y+\u0005Q\u0004CA\u0019<\u0013\ta$GA\u0002J]R\faCU+O\u001d\u0016\u0013vL\u0013$S\u00036+ul\u0015+B%R{\u0006\fI\u0001\u0016%Vse*\u0012*`\u0015\u001a\u0013\u0016)T#`\'R\u000b%\u000bV0Z\u0003Y\u0011VK\u0014(F%~SeIU!N\u000b~\u001bF+\u0011*U?f\u0003\u0013aD:qC:\u001c6-\u00197f\r\u0006\u001cGo\u001c:\u0016\u0003\t\u0003\"!M\"\n\u0005\u0011\u0013$A\u0002#pk\ndW-A\nta\u0006t7kY1mK\u001a\u000b7\r^8s?\u0012*\u0017\u000f\u0006\u0002H\u0015B\u0011\u0011\u0007S\u0005\u0003\u0013J\u0012A!\u00168ji\"91\nCA\u0001\u0002\u0004\u0011\u0015a\u0001=%c\u0005\u00012\u000f]1o\'\u000e\fG.\u001a$bGR|\'\u000f\t\u0015\u0003\u00139\u0003\"!M(\n\u0005A\u0013$\u0001\u0003<pY\u0006$\u0018\u000e\\3\u00021\u0011+g-Y;mi:+XNR5mKN$v.\u0011:dQ&4X-F\u0001T\u001f\u0005!V$\u0001\u0002\u00023\u0011+g-Y;mi:+XNR5mKN$v.\u0011:dQ&4X\r\t\u0002\u0011!\u0006\u001c8OR1jYJ+\u0007o\u001c:uKJ\u001c2\u0001\u0004\u0019Y!\tI&,D\u0001(\u0013\tYvE\u0001\u0005SKB|\'\u000f^3s)\u0005i\u0006C\u00010\r\u001b\u0005\t\u0011A\u00064bS2,G-\u00112peR,Gm\u0014:Ti>\u0004\b/\u001a3\u0016\u0003\u0005\u0004\"!\r2\n\u0005\r\u0014$a\u0002\"p_2,\u0017M\\\u0001\u001bM\u0006LG.\u001a3BE>\u0014H/\u001a3PeN#x\u000e\u001d9fI~#S-\u001d\u000b\u0003\u000f\u001aDqaS\b\u0002\u0002\u0003\u0007\u0011-A\fgC&dW\rZ!c_J$X\rZ(s\'R|\u0007\u000f]3eA!\u0012\u0001CT\u0001\u0011eVtGi\u001c8f\'\u0016l\u0017\r\u001d5pe\u0016,\u0012a\u001b\t\u0003YNl\u0011!\u001c\u0006\u0003]>\f!bY8oGV\u0014(/\u001a8u\u0015\t\u0001\u0018/\u0001\u0003vi&d\'\"\u0001:\u0002\t)\fg/Y\u0005\u0003i6\u0014\u0011bU3nCBDwN]3\u0002#I,h\u000eR8oKN+W.\u00199i_J,\u0007%A\u0003baBd\u0017\u0010\u0006\u0002Hq\")\u0011p\u0005a\u0001u\u0006)QM^3oiB\u00111P`\u0007\u0002y*\u0011QpJ\u0001\u0007KZ,g\u000e^:\n\u0005}d(!B#wK:$\u0018AD1mYR+7\u000f^:QCN\u001cX\rZ\u0001\u0005[\u0006Lg\u000eF\u0002H\u0003\u000fAq!!\u0003\u0016\u0001\u0004\tY!\u0001\u0003be\u001e\u001c\b#B\u0019\u0002\u000e\u0005E\u0011bAA\be\t)\u0011I\u001d:bsB!\u00111CA\u0011\u001d\u0011\t)\"!\b\u0011\u0007\u0005]!\'\u0004\u0002\u0002\u001a)\u0019\u00111D\u0016\u0002\rq\u0012xn\u001c;?\u0013\r\tyBM\u0001\u0007!J,G-\u001a4\n\t\u0005\r\u0012Q\u0005\u0002\u0007\'R\u0014\u0018N\\4\u000b\u0007\u0005}!\'A\u0002sk:$2!YA\u0016\u0011\u001d\tIA\u0006a\u0001\u0003\u0017\t\u0011E];o\u001fB$\u0018n\u001c8bY2Lx+\u001b;i!\u0006\u001c8OR1jYJ+\u0007o\u001c:uKJ$R!YA\u0019\u0003gAq!!\u0003\u0018\u0001\u0004\tY\u0001\u0003\u0004\u00026]\u0001\r!Y\u0001\u0018eVtw+\u001b;i!\u0006\u001c8OR1jYJ+\u0007o\u001c:uKJ\f1#\u0019;p[&\u001cG\u000b\u001b:fC\u0012\u001cu.\u001e8uKJ,\"!a\u000f\u0011\t\u0005u\u00121I\u0007\u0003\u0003\u007fQ1!!\u0011n\u0003\u0019\tGo\\7jG&!\u0011QIA \u00055\tEo\\7jG&sG/Z4fe\u0006!\u0012\r^8nS\u000e$\u0006N]3bI\u000e{WO\u001c;fe\u0002\nQ\u0003\\8bI*+f.\u001b;Xe\u0006\u0004\b/\u001a:DY\u0006\u001c8\u000f\u0006\u0003\u0002N\u0005E\u0004\u0007BA(\u0003?\u0002b!!\u0015\u0002X\u0005mSBAA*\u0015\r\t)&]\u0001\u0005Y\u0006tw-\u0003\u0003\u0002Z\u0005M#!B\"mCN\u001c\b\u0003BA/\u0003?b\u0001\u0001B\u0006\u0002bi\t\t\u0011!A\u0003\u0002\u0005\r$AA 1#\u0011\t)\'a\u001b\u0011\u0007E\n9\'C\u0002\u0002jI\u0012qAT8uQ&tw\r\u0005\u0003\u0002R\u00055\u0014\u0002BA8\u0003\'\u0012aa\u00142kK\u000e$\bbBA:5\u0001\u0007\u0011QO\u0001\u0007Y>\fG-\u001a:\u0011\t\u0005E\u0013qO\u0005\u0005\u0003s\n\u0019FA\u0006DY\u0006\u001c8\u000fT8bI\u0016\u0014\u0018A\u00067pC\u0012$Vm\u001d;O\u000f^\u0013\u0018\r\u001d9fe\u000ec\u0017m]:\u0015\t\u0005}\u0014q\u0011\u0019\u0005\u0003\u0003\u000b)\t\u0005\u0004\u0002R\u0005]\u00131\u0011\t\u0005\u0003;\n)\tB\u0006\u0002bm\t\t\u0011!A\u0003\u0002\u0005\r\u0004bBA:7\u0001\u0007\u0011QO\u0001\u0016I>\u0014VO\u001c*v]J+h\u000eR1E_J+hNU;o)-:\u0015QRAL\u0003g\u000bI,!2\u0002J\u0006M\u0017Q\\Aq\u0003W\fi/!=\u0002v\u0006e\u0018Q`A\u0000\u0005\u0013\u0011iAa\u0006\u0003.\tE\u0002bBAH9\u0001\u0007\u0011\u0011S\u0001\tI&\u001c\b/\u0019;dQB\u0019\u0011,a%\n\u0007\u0005UuE\u0001\tESN\u0004\u0018\r^2i%\u0016\u0004xN\u001d;fe\"9\u0011\u0011\u0014\u000fA\u0002\u0005m\u0015AC:vSR,7\u000fT5tiB1\u0011QTAT\u0003[sA!a(\u0002$:!\u0011qCAQ\u0013\u0005\u0019\u0014bAASe\u00059\u0001/Y2lC\u001e,\u0017\u0002BAU\u0003W\u0013A\u0001T5ti*\u0019\u0011Q\u0015\u001a\u0011\u00075\ny+C\u0002\u00022\u0016\u0012!bU;ji\u0016\u0004\u0016M]1n\u0011\u001d\t)\f\ba\u0001\u0003o\u000ba!Y4bS:\u001c\bCBAO\u0003O\u000b\t\u0002C\u0004\u0002<r\u0001\r!!0\u0002\u0013Q,7\u000f^*qK\u000e\u001c\bCBAO\u0003O\u000by\fE\u0002.\u0003\u0003L1!a1&\u0005!!Vm\u001d;Ta\u0016\u001c\u0007bBAd9\u0001\u0007\u0011qW\u0001\u000bUVt\u0017\u000e^:MSN$\bbBAf9\u0001\u0007\u0011QZ\u0001\bgR|\u0007\u000f]3s!\rI\u0016qZ\u0005\u0004\u0003#<#aB*u_B\u0004XM\u001d\u0005\b\u0003+d\u0002\u0019AAl\u0003A!\u0018mZ:U_&s7\r\\;eKN+G\u000f\u0005\u0004\u0002\u0014\u0005e\u0017\u0011C\u0005\u0005\u00037\f)CA\u0002TKRDq!a8\u001d\u0001\u0004\t9.\u0001\tuC\u001e\u001cHk\\#yG2,H-Z*fi\"9\u00111\u001d\u000fA\u0002\u0005\u0015\u0018!C2p]\u001aLw-T1q!\rI\u0016q]\u0005\u0004\u0003S<#!C\"p]\u001aLw-T1q\u0011\u0015qG\u00041\u0001b\u0011\u001d\ty\u000f\ba\u0001\u0003o\u000bq\"\\3nE\u0016\u00148o\u00148ms2K7\u000f\u001e\u0005\b\u0003gd\u0002\u0019AA\\\u000319\u0018\u000e\u001c3dCJ$G*[:u\u0011\u001d\t9\u0010\ba\u0001\u0003o\u000b!\u0002^3ti:;E*[:u\u0011\u001d\tY\u0010\ba\u0001\u0003o\u000bqA];oa\u0006$\b\u000eC\u0004\u0002tq\u0001\r!!\u001e\t\u000f\t\u0005A\u00041\u0001\u0003\u0004\u0005aAm\u001c8f\u0019&\u001cH/\u001a8feB\u0019QF!\u0002\n\u0007\t\u001dQEA\bSk:$uN\\3MSN$XM\\3s\u0011\u0019\u0011Y\u0001\ba\u0001u\u0005A!/\u001e8Ti\u0006l\u0007\u000fC\u0004\u0003\u0010q\u0001\rA!\u0005\u0002!\r|gnY;se\u0016tGoQ8oM&<\u0007cA\u0017\u0003\u0014%\u0019!QC\u0013\u0003!\r{gnY;se\u0016tGoQ8oM&<\u0007b\u0002B\r9\u0001\u0007!1D\u0001\tgV4g-\u001b=fgB)\u0011G!\b\u0003\"%\u0019!q\u0004\u001a\u0003\r=\u0003H/[8o!\u0011\u0011\u0019C!\u000b\u000e\u0005\t\u0015\"b\u0001B\u0014_\u0006)!/Z4fq&!!1\u0006B\u0013\u0005\u001d\u0001\u0016\r\u001e;fe:DqAa\f\u001d\u0001\u0004\t9.\u0001\bdQ>\u001cXM\\*us2,7+\u001a;\t\u000f\tMB\u00041\u0001\u00036\u0005QB/Z:u\'>\u0014H/\u001b8h%\u0016\u0004xN\u001d;feRKW.Z8viB!!q\u0007B\u001f\u001b\t\u0011IDC\u0002\u0003<\u001d\nA\u0001^5nK&!!q\bB\u001d\u0005\u0011\u0019\u0006/\u00198\u0002#\u0011,w\r\\8c\'VLG/\u001a)be\u0006l7\u000f\u0006\u0004\u0002\u001c\n\u0015#\u0011\n\u0005\b\u0005\u000fj\u0002\u0019AAN\u0003%9Gn\u001c2t\u0019&\u001cH\u000fC\u0004\u0003Lu\u0001\r!a6\u0002!\u0005\u001c7-Z:tS\ndWmU;ji\u0016\u001c\u0018a\u0004:fC\u0012lU-\\8ss\u001aKG.Z:\u0015\u0011\u0005m%\u0011\u000bB+\u00053BqAa\u0015\u001f\u0001\u0004\t9,A\u0005gS2,g*Y7fg\"1!q\u000b\u0010A\u0002a\u000b\u0001B]3q_J$XM\u001d\u0005\b\u00057r\u0002\u0019\u0001B/\u0003\u001d!(/Y2lKJ\u00042!\u0017B0\u0013\r\u0011\tg\n\u0002\b)J\f7m[3s\u000399WM\\*vSR,7i\u001c8gS\u001e$bAa\u001a\u0003n\tE\u0004cA\u0017\u0003j%\u0019!1N\u0013\u0003\u0017M+\u0018\u000e^3D_:4\u0017n\u001a\u0005\b\u0005_z\u0002\u0019AAW\u0003)\u0019X/\u001b;f!\u0006\u0014\u0018-\u001c\u0005\b\u0003gz\u0002\u0019AA;\u0003I)\u0007p\u00197vI\u0016\u001cx+\u001b;i\u0013\u001etwN]3\u0015\t\t]$Q\u0011\t\u0007\u0005s\u0012\u0019)!\u0005\u000e\u0005\tm$\u0002\u0002B?\u0005\u007f\n\u0011\"[7nkR\f\'\r\\3\u000b\u0007\t\u0005%\'\u0001\u0006d_2dWm\u0019;j_:LA!a7\u0003|!9!q\u0011\u0011A\u0002\u0005]\u0017\u0001C3yG2,H-Z:\u0002E]LG\u000f[\"mCN\u001cHj\\1eKJ\fe\u000e\u001a#jgB\fGo\u00195SKB|\'\u000f^3s)A\u0011iI!\'\u0003\u001e\n\u001d&Q\u0016BY\u0005k\u0013y\fF\u0002H\u0005\u001fCqA!%\"\u0001\u0004\u0011\u0019*A\u0001g!!\t$QSA;\u0003#;\u0015b\u0001BLe\tIa)\u001e8di&|gN\r\u0005\b\u00057\u000b\u0003\u0019AA\\\u0003-\u0011XO\u001c9bi\"d\u0015n\u001d;\t\u000f\t}\u0015\u00051\u0001\u0003\"\u0006i!/\u001a9peR,\'o\u00159fGN\u00042!\fBR\u0013\r\u0011)+\n\u0002\u0017%\u0016\u0004xN\u001d;fe\u000e{gNZ5hkJ\fG/[8og\"9!\u0011V\u0011A\u0002\t-\u0016aD4sCBD\u0017n\u0019*fa>\u0014H/\u001a:\u0011\tE\u0012i\u0002\u0017\u0005\b\u0005_\u000b\u0003\u0019\u0001BV\u0003A\u0001\u0018m]:GC&d\'+\u001a9peR,\'\u000f\u0003\u0004\u00034\u0006\u0002\r!Y\u0001\u0010I\u0016$Xm\u0019;TY><\bo\\6fg\"9!qW\u0011A\u0002\te\u0016AF:m_^\u0004xn[3EKR,7\r^5p]\u0012+G.Y=\u0011\u0007E\u0012Y,C\u0002\u0003>J\u0012A\u0001T8oO\"9!\u0011Y\u0011A\u0002\te\u0016aF:m_^\u0004xn[3EKR,7\r^5p]B+\'/[8e\u0003U9W\r\u001e*v]B\fG\u000f[\"mCN\u001cHj\\1eKJ$B!!\u001e\u0003H\"9!1\u0014\u0012A\u0002\u0005]\u0016\u0001G;tS:<WI^3oi\u0012K7\u000f]1uG\"$\u0006N]3bIR\u0019qI!4\t\u0011\tE5\u0005\"a\u0001\u0005\u001f\u0004B!\rBi\u000f&\u0019!1\u001b\u001a\u0003\u0011q\u0012\u0017P\\1nKz\u0002"
    )
  ScalaSig: length = 0x3 (unknown attribute)
   05 02 00
