Classfile /Users/mw/Projects/slang-braindump/.jar/jar8/assemble/slang-braindump/assemble/content/org/scalatest/tools/RunnerJFrame$$anon$6.class
  Last modified May 29, 2022; size 1424 bytes
  SHA-256 checksum 9c38af8a7613d3e3cf161988aa82d65895303f13450868b096453d9222fad311
  Compiled from "RunnerJFrame.scala"
public final class org.scalatest.tools.RunnerJFrame$$anon$6 implements java.awt.event.ActionListener
  minor version: 0
  major version: 52
  flags: (0x0031) ACC_PUBLIC, ACC_FINAL, ACC_SUPER
  this_class: #2                          // org/scalatest/tools/RunnerJFrame$$anon$6
  super_class: #4                         // java/lang/Object
  interfaces: 1, fields: 1, methods: 2, attributes: 5
Constant pool:
   #1 = Utf8               org/scalatest/tools/RunnerJFrame$$anon$6
   #2 = Class              #1             // org/scalatest/tools/RunnerJFrame$$anon$6
   #3 = Utf8               java/lang/Object
   #4 = Class              #3             // java/lang/Object
   #5 = Utf8               java/awt/event/ActionListener
   #6 = Class              #5             // java/awt/event/ActionListener
   #7 = Utf8               RunnerJFrame.scala
   #8 = Utf8               org/scalatest/tools/RunnerJFrame
   #9 = Class              #8             // org/scalatest/tools/RunnerJFrame
  #10 = Utf8               setupMenus
  #11 = Utf8               ()V
  #12 = NameAndType        #10:#11        // setupMenus:()V
  #13 = Utf8               $outer
  #14 = Utf8               Lorg/scalatest/tools/RunnerJFrame;
  #15 = Utf8               actionPerformed
  #16 = Utf8               (Ljava/awt/event/ActionEvent;)V
  #17 = Utf8               ae
  #18 = NameAndType        #13:#14        // $outer:Lorg/scalatest/tools/RunnerJFrame;
  #19 = Fieldref           #2.#18         // org/scalatest/tools/RunnerJFrame$$anon$6.$outer:Lorg/scalatest/tools/RunnerJFrame;
  #20 = Utf8               dispose
  #21 = NameAndType        #20:#11        // dispose:()V
  #22 = Methodref          #9.#21         // org/scalatest/tools/RunnerJFrame.dispose:()V
  #23 = Utf8               org$scalatest$tools$RunnerJFrame$$passFailReporter
  #24 = Utf8               Lscala/Option;
  #25 = NameAndType        #23:#24        // org$scalatest$tools$RunnerJFrame$$passFailReporter:Lscala/Option;
  #26 = Fieldref           #9.#25         // org/scalatest/tools/RunnerJFrame.org$scalatest$tools$RunnerJFrame$$passFailReporter:Lscala/Option;
  #27 = Utf8               scala/Some
  #28 = Class              #27            // scala/Some
  #29 = Utf8               scala/runtime/BoxedUnit
  #30 = Class              #29            // scala/runtime/BoxedUnit
  #31 = Utf8               UNIT
  #32 = Utf8               Lscala/runtime/BoxedUnit;
  #33 = NameAndType        #31:#32        // UNIT:Lscala/runtime/BoxedUnit;
  #34 = Fieldref           #30.#33        // scala/runtime/BoxedUnit.UNIT:Lscala/runtime/BoxedUnit;
  #35 = Utf8               scala/None$
  #36 = Class              #35            // scala/None$
  #37 = Utf8               MODULE$
  #38 = Utf8               Lscala/None$;
  #39 = NameAndType        #37:#38        // MODULE$:Lscala/None$;
  #40 = Fieldref           #36.#39        // scala/None$.MODULE$:Lscala/None$;
  #41 = Utf8               equals
  #42 = Utf8               (Ljava/lang/Object;)Z
  #43 = NameAndType        #41:#42        // equals:(Ljava/lang/Object;)Z
  #44 = Methodref          #4.#43         // java/lang/Object.equals:(Ljava/lang/Object;)Z
  #45 = Utf8               java/lang/System
  #46 = Class              #45            // java/lang/System
  #47 = Utf8               exit
  #48 = Utf8               (I)V
  #49 = NameAndType        #47:#48        // exit:(I)V
  #50 = Methodref          #46.#49        // java/lang/System.exit:(I)V
  #51 = Utf8               scala/MatchError
  #52 = Class              #51            // scala/MatchError
  #53 = Utf8               <init>
  #54 = Utf8               (Ljava/lang/Object;)V
  #55 = NameAndType        #53:#54        // "<init>":(Ljava/lang/Object;)V
  #56 = Methodref          #52.#55        // scala/MatchError."<init>":(Ljava/lang/Object;)V
  #57 = Utf8               this
  #58 = Utf8               Lorg/scalatest/tools/RunnerJFrame$$anon$6;
  #59 = Utf8               Ljava/awt/event/ActionEvent;
  #60 = Utf8               scala/Option
  #61 = Class              #60            // scala/Option
  #62 = Utf8               java/awt/event/ActionEvent
  #63 = Class              #62            // java/awt/event/ActionEvent
  #64 = Utf8               (Lorg/scalatest/tools/RunnerJFrame;)V
  #65 = NameAndType        #53:#11        // "<init>":()V
  #66 = Methodref          #4.#65         // java/lang/Object."<init>":()V
  #67 = Utf8               Code
  #68 = Utf8               StackMapTable
  #69 = Utf8               LineNumberTable
  #70 = Utf8               LocalVariableTable
  #71 = Utf8               MethodParameters
  #72 = Utf8               InnerClasses
  #73 = Utf8               EnclosingMethod
  #74 = Utf8               SourceFile
  #75 = Utf8               ScalaInlineInfo
  #76 = Utf8               Scala
{
  private final org.scalatest.tools.RunnerJFrame $outer;
    descriptor: Lorg/scalatest/tools/RunnerJFrame;
    flags: (0x1012) ACC_PRIVATE, ACC_FINAL, ACC_SYNTHETIC

  public void actionPerformed(java.awt.event.ActionEvent);
    descriptor: (Ljava/awt/event/ActionEvent;)V
    flags: (0x0001) ACC_PUBLIC
    Code:
      stack=3, locals=4, args_size=2
         0: aload_0
         1: getfield      #19                 // Field $outer:Lorg/scalatest/tools/RunnerJFrame;
         4: invokevirtual #22                 // Method org/scalatest/tools/RunnerJFrame.dispose:()V
         7: aload_0
         8: getfield      #19                 // Field $outer:Lorg/scalatest/tools/RunnerJFrame;
        11: getfield      #26                 // Field org/scalatest/tools/RunnerJFrame.org$scalatest$tools$RunnerJFrame$$passFailReporter:Lscala/Option;
        14: astore_3
        15: aload_3
        16: instanceof    #28                 // class scala/Some
        19: ifeq          29
        22: getstatic     #34                 // Field scala/runtime/BoxedUnit.UNIT:Lscala/runtime/BoxedUnit;
        25: astore_2
        26: goto          65
        29: goto          32
        32: getstatic     #40                 // Field scala/None$.MODULE$:Lscala/None$;
        35: aload_3
        36: invokevirtual #44                 // Method java/lang/Object.equals:(Ljava/lang/Object;)Z
        39: ifeq          53
        42: iconst_0
        43: invokestatic  #50                 // Method java/lang/System.exit:(I)V
        46: getstatic     #34                 // Field scala/runtime/BoxedUnit.UNIT:Lscala/runtime/BoxedUnit;
        49: astore_2
        50: goto          65
        53: goto          56
        56: new           #52                 // class scala/MatchError
        59: dup
        60: aload_3
        61: invokespecial #56                 // Method scala/MatchError."<init>":(Ljava/lang/Object;)V
        64: athrow
        65: return
      StackMapTable: number_of_entries = 5
        frame_type = 253 /* append */
          offset_delta = 29
          locals = [ top, class scala/Option ]
        frame_type = 2 /* same */
        frame_type = 20 /* same */
        frame_type = 2 /* same */
        frame_type = 255 /* full_frame */
          offset_delta = 8
          locals = [ class org/scalatest/tools/RunnerJFrame$$anon$6, class java/awt/event/ActionEvent, class scala/runtime/BoxedUnit, class scala/Option ]
          stack = []
      LineNumberTable:
        line 669: 0
        line 674: 7
        line 675: 15
        line 676: 32
        line 674: 56
      LocalVariableTable:
        Start  Length  Slot  Name   Signature
            0      66     0  this   Lorg/scalatest/tools/RunnerJFrame$$anon$6;
            0      66     1    ae   Ljava/awt/event/ActionEvent;
    MethodParameters:
      Name                           Flags
      ae                             final

  public org.scalatest.tools.RunnerJFrame$$anon$6(org.scalatest.tools.RunnerJFrame);
    descriptor: (Lorg/scalatest/tools/RunnerJFrame;)V
    flags: (0x0001) ACC_PUBLIC
    Code:
      stack=2, locals=2, args_size=2
         0: aload_1
         1: ifnonnull     6
         4: aconst_null
         5: athrow
         6: aload_0
         7: aload_1
         8: putfield      #19                 // Field $outer:Lorg/scalatest/tools/RunnerJFrame;
        11: aload_0
        12: invokespecial #66                 // Method java/lang/Object."<init>":()V
        15: return
      StackMapTable: number_of_entries = 1
        frame_type = 6 /* same */
      LineNumberTable:
        line 667: 0
      LocalVariableTable:
        Start  Length  Slot  Name   Signature
            0      16     0  this   Lorg/scalatest/tools/RunnerJFrame$$anon$6;
            0      16     1 $outer   Lorg/scalatest/tools/RunnerJFrame;
    MethodParameters:
      Name                           Flags
      $outer                         final synthetic
}
InnerClasses:
  public final #2;                        // class org/scalatest/tools/RunnerJFrame$$anon$6
EnclosingMethod: #9.#12                 // org.scalatest.tools.RunnerJFrame.setupMenus
SourceFile: "RunnerJFrame.scala"
  ScalaInlineInfo: length = 0xE (unknown attribute)
   01 01 00 02 00 35 00 40 01 00 0F 00 10 01
  Scala: length = 0x0 (unknown attribute)

