Classfile /Users/mw/Projects/slang-braindump/.jar/jar8/assemble/slang-braindump/assemble/content/org/scalatest/tools/RunnerJFrame$$anon$7.class
  Last modified May 29, 2022; size 1326 bytes
  SHA-256 checksum d0765fb993588a8242d6bb70b6b9bc0296414e5badeaab0ab74bec11b38242b7
  Compiled from "RunnerJFrame.scala"
public final class org.scalatest.tools.RunnerJFrame$$anon$7 implements java.awt.event.ActionListener
  minor version: 0
  major version: 52
  flags: (0x0031) ACC_PUBLIC, ACC_FINAL, ACC_SUPER
  this_class: #2                          // org/scalatest/tools/RunnerJFrame$$anon$7
  super_class: #4                         // java/lang/Object
  interfaces: 1, fields: 1, methods: 2, attributes: 5
Constant pool:
   #1 = Utf8               org/scalatest/tools/RunnerJFrame$$anon$7
   #2 = Class              #1             // org/scalatest/tools/RunnerJFrame$$anon$7
   #3 = Utf8               java/lang/Object
   #4 = Class              #3             // java/lang/Object
   #5 = Utf8               java/awt/event/ActionListener
   #6 = Class              #5             // java/awt/event/ActionListener
   #7 = Utf8               RunnerJFrame.scala
   #8 = Utf8               org/scalatest/tools/RunnerJFrame
   #9 = Class              #8             // org/scalatest/tools/RunnerJFrame
  #10 = Utf8               setupMenus
  #11 = Utf8               ()V
  #12 = NameAndType        #10:#11        // setupMenus:()V
  #13 = Utf8               $outer
  #14 = Utf8               Lorg/scalatest/tools/RunnerJFrame;
  #15 = Utf8               actionPerformed
  #16 = Utf8               (Ljava/awt/event/ActionEvent;)V
  #17 = Utf8               ae
  #18 = NameAndType        #13:#14        // $outer:Lorg/scalatest/tools/RunnerJFrame;
  #19 = Fieldref           #2.#18         // org/scalatest/tools/RunnerJFrame$$anon$7.$outer:Lorg/scalatest/tools/RunnerJFrame;
  #20 = Utf8               org$scalatest$tools$RunnerJFrame$$runsAndFailures
  #21 = Utf8               ()Lscala/collection/immutable/Set;
  #22 = NameAndType        #20:#21        // org$scalatest$tools$RunnerJFrame$$runsAndFailures:()Lscala/collection/immutable/Set;
  #23 = Methodref          #9.#22         // org/scalatest/tools/RunnerJFrame.org$scalatest$tools$RunnerJFrame$$runsAndFailures:()Lscala/collection/immutable/Set;
  #24 = Utf8               eventTypesToCollect
  #25 = NameAndType        #24:#21        // eventTypesToCollect:()Lscala/collection/immutable/Set;
  #26 = Methodref          #9.#25         // org/scalatest/tools/RunnerJFrame.eventTypesToCollect:()Lscala/collection/immutable/Set;
  #27 = Utf8               scala/collection/immutable/Set
  #28 = Class              #27            // scala/collection/immutable/Set
  #29 = Utf8               intersect
  #30 = Utf8               (Lscala/collection/Set;)Lscala/collection/SetOps;
  #31 = NameAndType        #29:#30        // intersect:(Lscala/collection/Set;)Lscala/collection/SetOps;
  #32 = InterfaceMethodref #28.#31        // scala/collection/immutable/Set.intersect:(Lscala/collection/Set;)Lscala/collection/SetOps;
  #33 = Utf8               org$scalatest$tools$RunnerJFrame$$viewOptions_$eq
  #34 = Utf8               (Lscala/collection/immutable/Set;)V
  #35 = NameAndType        #33:#34        // org$scalatest$tools$RunnerJFrame$$viewOptions_$eq:(Lscala/collection/immutable/Set;)V
  #36 = Methodref          #9.#35         // org/scalatest/tools/RunnerJFrame.org$scalatest$tools$RunnerJFrame$$viewOptions_$eq:(Lscala/collection/immutable/Set;)V
  #37 = Utf8               org$scalatest$tools$RunnerJFrame$$updateViewOptionsAndEventsList
  #38 = NameAndType        #37:#11        // org$scalatest$tools$RunnerJFrame$$updateViewOptionsAndEventsList:()V
  #39 = Methodref          #9.#38         // org/scalatest/tools/RunnerJFrame.org$scalatest$tools$RunnerJFrame$$updateViewOptionsAndEventsList:()V
  #40 = Utf8               this
  #41 = Utf8               Lorg/scalatest/tools/RunnerJFrame$$anon$7;
  #42 = Utf8               Ljava/awt/event/ActionEvent;
  #43 = Utf8               <init>
  #44 = Utf8               (Lorg/scalatest/tools/RunnerJFrame;)V
  #45 = NameAndType        #43:#11        // "<init>":()V
  #46 = Methodref          #4.#45         // java/lang/Object."<init>":()V
  #47 = Utf8               Code
  #48 = Utf8               LineNumberTable
  #49 = Utf8               LocalVariableTable
  #50 = Utf8               MethodParameters
  #51 = Utf8               StackMapTable
  #52 = Utf8               InnerClasses
  #53 = Utf8               EnclosingMethod
  #54 = Utf8               SourceFile
  #55 = Utf8               ScalaInlineInfo
  #56 = Utf8               Scala
{
  private final org.scalatest.tools.RunnerJFrame $outer;
    descriptor: Lorg/scalatest/tools/RunnerJFrame;
    flags: (0x1012) ACC_PRIVATE, ACC_FINAL, ACC_SYNTHETIC

  public void actionPerformed(java.awt.event.ActionEvent);
    descriptor: (Ljava/awt/event/ActionEvent;)V
    flags: (0x0001) ACC_PUBLIC
    Code:
      stack=3, locals=2, args_size=2
         0: aload_0
         1: getfield      #19                 // Field $outer:Lorg/scalatest/tools/RunnerJFrame;
         4: aload_0
         5: getfield      #19                 // Field $outer:Lorg/scalatest/tools/RunnerJFrame;
         8: invokevirtual #23                 // Method org/scalatest/tools/RunnerJFrame.org$scalatest$tools$RunnerJFrame$$runsAndFailures:()Lscala/collection/immutable/Set;
        11: aload_0
        12: getfield      #19                 // Field $outer:Lorg/scalatest/tools/RunnerJFrame;
        15: invokevirtual #26                 // Method org/scalatest/tools/RunnerJFrame.eventTypesToCollect:()Lscala/collection/immutable/Set;
        18: invokeinterface #32,  2           // InterfaceMethod scala/collection/immutable/Set.intersect:(Lscala/collection/Set;)Lscala/collection/SetOps;
        23: checkcast     #28                 // class scala/collection/immutable/Set
        26: invokevirtual #36                 // Method org/scalatest/tools/RunnerJFrame.org$scalatest$tools$RunnerJFrame$$viewOptions_$eq:(Lscala/collection/immutable/Set;)V
        29: aload_0
        30: getfield      #19                 // Field $outer:Lorg/scalatest/tools/RunnerJFrame;
        33: invokevirtual #39                 // Method org/scalatest/tools/RunnerJFrame.org$scalatest$tools$RunnerJFrame$$updateViewOptionsAndEventsList:()V
        36: return
      LineNumberTable:
        line 693: 0
        line 694: 29
      LocalVariableTable:
        Start  Length  Slot  Name   Signature
            0      37     0  this   Lorg/scalatest/tools/RunnerJFrame$$anon$7;
            0      37     1    ae   Ljava/awt/event/ActionEvent;
    MethodParameters:
      Name                           Flags
      ae                             final

  public org.scalatest.tools.RunnerJFrame$$anon$7(org.scalatest.tools.RunnerJFrame);
    descriptor: (Lorg/scalatest/tools/RunnerJFrame;)V
    flags: (0x0001) ACC_PUBLIC
    Code:
      stack=2, locals=2, args_size=2
         0: aload_1
         1: ifnonnull     6
         4: aconst_null
         5: athrow
         6: aload_0
         7: aload_1
         8: putfield      #19                 // Field $outer:Lorg/scalatest/tools/RunnerJFrame;
        11: aload_0
        12: invokespecial #46                 // Method java/lang/Object."<init>":()V
        15: return
      StackMapTable: number_of_entries = 1
        frame_type = 6 /* same */
      LineNumberTable:
        line 691: 0
      LocalVariableTable:
        Start  Length  Slot  Name   Signature
            0      16     0  this   Lorg/scalatest/tools/RunnerJFrame$$anon$7;
            0      16     1 $outer   Lorg/scalatest/tools/RunnerJFrame;
    MethodParameters:
      Name                           Flags
      $outer                         final synthetic
}
InnerClasses:
  public final #2;                        // class org/scalatest/tools/RunnerJFrame$$anon$7
EnclosingMethod: #9.#12                 // org.scalatest.tools.RunnerJFrame.setupMenus
SourceFile: "RunnerJFrame.scala"
  ScalaInlineInfo: length = 0xE (unknown attribute)
   01 01 00 02 00 2B 00 2C 01 00 0F 00 10 01
  Scala: length = 0x0 (unknown attribute)

