Classfile /Users/mw/Projects/slang-braindump/.jar/jar8/assemble/slang-braindump/assemble/content/org/scalatest/tools/SlowpokeConfig.class
  Last modified May 29, 2022; size 5430 bytes
  SHA-256 checksum b7548bbecd714135c588de62f0a9f1203be7a5c0fb875c7f971fc095cd7fce6f
  Compiled from "Runner.scala"
public class org.scalatest.tools.SlowpokeConfig implements scala.Product,java.io.Serializable
  minor version: 0
  major version: 52
  flags: (0x0021) ACC_PUBLIC, ACC_SUPER
  this_class: #2                          // org/scalatest/tools/SlowpokeConfig
  super_class: #4                         // java/lang/Object
  interfaces: 2, fields: 2, methods: 20, attributes: 4
Constant pool:
    #1 = Utf8               org/scalatest/tools/SlowpokeConfig
    #2 = Class              #1            // org/scalatest/tools/SlowpokeConfig
    #3 = Utf8               java/lang/Object
    #4 = Class              #3            // java/lang/Object
    #5 = Utf8               scala/Product
    #6 = Class              #5            // scala/Product
    #7 = Utf8               java/io/Serializable
    #8 = Class              #7            // java/io/Serializable
    #9 = Utf8               Runner.scala
   #10 = Utf8               Lscala/reflect/ScalaSignature;
   #11 = Utf8               bytes
   #12 = Utf8               \u0006\u0005\u00055c!B\r\u001b\u0001j\u0001\u0003\u0002C\u001c\u0001\u0005+\u0007I\u0011\u0001\u001d\t\u0011q\u0002!\u0011#Q\u0001\neB\u0001\"\u0010\u0001\u0003\u0016\u0004%\t\u0001\u000f\u0005\t}\u0001\u0011\t\u0012)A\u0005s!)q\b\u0001C\u0001\u0001\"9Q\tAA\u0001\n\u00031\u0005bB%\u0001#\u0003%\tA\u0013\u0005\b+\u0002\t\n\u0011\"\u0001K\u0011\u001d1\u0006!!A\u0005B]Cq\u0001\u0019\u0001\u0002\u0002\u0013\u0005\u0011\rC\u0004f\u0001\u0005\u0005I\u0011\u00014\t\u000f1\u0004\u0011\u0011!C![\"9A\u000fAA\u0001\n\u0003)\bb\u0002>\u0001\u0003\u0003%\te\u001f\u0005\b{\u0002\t\t\u0011\"\u0011\u007f\u0011!y\b!!A\u0005B\u0005\u0005\u0001\"CA\u0002\u0001\u0005\u0005I\u0011IA\u0003\u000f)\tIAGA\u0001\u0012\u0003Q\u00121\u0002\u0004\n3i\t\t\u0011#\u0001\u001b\u0003\u001bAaaP\n\u0005\u0002\u0005\u0015\u0002\u0002C@\u0014\u0003\u0003%)%!\u0001\t\u0013\u0005\u001d2#!A\u0005\u0002\u0006%\u0002\"CA\u0018\'\u0005\u0005I\u0011QA\u0019\u0011%\t\u0019eEA\u0001\n\u0013\t)E\u0001\bTY><\bo\\6f\u0007>tg-[4\u000b\u0005ma\u0012!\u0002;p_2\u001c(BA\u000f\u001f\u0003%\u00198-\u00197bi\u0016\u001cHOC\u0001 \u0003\ry\'oZ\n\u0005\u0001\u0005:#\u0006\u0005\u0002#K5\t1EC\u0001%\u0003\u0015\u00198-\u00197b\u0013\t13E\u0001\u0004B]f\u0014VM\u001a\t\u0003E!J!!K\u0012\u0003\u000fA\u0013x\u000eZ;diB\u00111\u0006\u000e\b\u0003YIr!!L\u0019\u000e\u00039R!a\f\u0019\u0002\rq\u0012xn\u001c;?\u0007\u0001I\u0011\u0001J\u0005\u0003g\r\nq\u0001]1dW\u0006<W-\u0003\u00026m\ta1+\u001a:jC2L\'0\u00192mK*\u00111gI\u0001\u000eI\u0016d\u0017-_%o\u001b&dG.[:\u0016\u0003e\u0002\"A\t\u001e\n\u0005m\u001a#\u0001\u0002\'p]\u001e\fa\u0002Z3mCfLe.T5mY&\u001c\b%\u0001\bqKJLw\u000eZ%o\u001b&dG.[:\u0002\u001fA,\'/[8e\u0013:l\u0015\u000e\u001c7jg\u0002\na\u0001P5oSRtDcA!D\tB\u0011!\tA\u0007\u00025!)q\'\u0002a\u0001s!)Q(\u0002a\u0001s\u0005!1m\u001c9z)\r\tu\t\u0013\u0005\bo\u0019\u0001\n\u00111\u0001:\u0011\u001did\u0001%AA\u0002e\nabY8qs\u0012\"WMZ1vYR$\u0013\'F\u0001LU\tIDjK\u0001N!\tq5+D\u0001P\u0015\t\u0001\u0016+A\u0005v]\u000eDWmY6fI*\u0011!kI\u0001\u000bC:tw\u000e^1uS>t\u0017B\u0001+P\u0005E)hn\u00195fG.,GMV1sS\u0006t7-Z\u0001\u000fG>\u0004\u0018\u0010\n3fM\u0006,H\u000e\u001e\u00133\u00035\u0001(o\u001c3vGR\u0004&/\u001a4jqV\t\u0001\f\u0005\u0002Z=6\t!L\u0003\u0002\\9\u0006!A.\u00198h\u0015\u0005i\u0016\u0001\u00026bm\u0006L!a\u0018.\u0003\rM#(/\u001b8h\u00031\u0001(o\u001c3vGR\f%/\u001b;z+\u0005\u0011\u0007C\u0001\u0012d\u0013\t!7EA\u0002J]R\fa\u0002\u001d:pIV\u001cG/\u00127f[\u0016tG\u000f\u0006\u0002hUB\u0011!\u0005[\u0005\u0003S\u000e\u00121!\u00118z\u0011\u001dY7\"!AA\u0002\t\f1\u0001\u001f\u00132\u0003=\u0001(o\u001c3vGRLE/\u001a:bi>\u0014X#\u00018\u0011\u0007=\u0014x-D\u0001q\u0015\t\t8%\u0001\u0006d_2dWm\u0019;j_:L!a\u001d9\u0003\u0011%#XM]1u_J\f\u0001bY1o\u000bF,\u0018\r\u001c\u000b\u0003mf\u0004\"AI<\n\u0005a\u001c#a\u0002\"p_2,\u0017M\u001c\u0005\bW6\t\t\u00111\u0001h\u0003I\u0001(o\u001c3vGR,E.Z7f]Rt\u0015-\\3\u0015\u0005ac\bbB6\u000f\u0003\u0003\u0005\rAY\u0001\tQ\u0006\u001c\bnQ8eKR\t!-\u0001\u0005u_N#(/\u001b8h)\u0005A\u0016AB3rk\u0006d7\u000fF\u0002w\u0003\u000fAqa[\t\u0002\u0002\u0003\u0007q-\u0001\bTY><\bo\\6f\u0007>tg-[4\u0011\u0005\t\u001b2#B\n\u0002\u0010\u0005m\u0001cBA\t\u0003/I\u0014(Q\u0007\u0003\u0003\'Q1!!\u0006$\u0003\u001d\u0011XO\u001c;j[\u0016LA!!\u0007\u0002\u0014\t\t\u0012IY:ue\u0006\u001cGOR;oGRLwN\u001c\u001a\u0011\t\u0005u\u00111E\u0007\u0003\u0003?Q1!!\t]\u0003\tIw.C\u00026\u0003?!\"!a\u0003\u0002\u000b\u0005\u0004\b\u000f\\=\u0015\u000b\u0005\u000bY#!\f\t\u000b]2\u0002\u0019A\u001d\t\u000bu2\u0002\u0019A\u001d\u0002\u000fUt\u0017\r\u001d9msR!\u00111GA !\u0015\u0011\u0013QGA\u001d\u0013\r\t9d\t\u0002\u0007\u001fB$\u0018n\u001c8\u0011\u000b\t\nY$O\u001d\n\u0007\u0005u2E\u0001\u0004UkBdWM\r\u0005\t\u0003\u0003:\u0012\u0011!a\u0001\u0003\u0006\u0019\u0001\u0010\n\u0019\u0002\u0019]\u0014\u0018\u000e^3SKBd\u0017mY3\u0015\u0005\u0005\u001d\u0003cA-\u0002J%\u0019\u00111\n.\u0003\r=\u0013\'.Z2u\u0001
   #13 = Utf8               delayInMillis
   #14 = Utf8               J
   #15 = Utf8               periodInMillis
   #16 = Utf8               unapply
   #17 = Utf8               (Lorg/scalatest/tools/SlowpokeConfig;)Lscala/Option;
   #18 = Utf8               (Lorg/scalatest/tools/SlowpokeConfig;)Lscala/Option<Lscala/Tuple2<Ljava/lang/Object;Ljava/lang/Object;>;>;
   #19 = Utf8               x$0
   #20 = Utf8               org/scalatest/tools/SlowpokeConfig$
   #21 = Class              #20           // org/scalatest/tools/SlowpokeConfig$
   #22 = Utf8               MODULE$
   #23 = Utf8               Lorg/scalatest/tools/SlowpokeConfig$;
   #24 = NameAndType        #22:#23       // MODULE$:Lorg/scalatest/tools/SlowpokeConfig$;
   #25 = Fieldref           #21.#24       // org/scalatest/tools/SlowpokeConfig$.MODULE$:Lorg/scalatest/tools/SlowpokeConfig$;
   #26 = NameAndType        #16:#17       // unapply:(Lorg/scalatest/tools/SlowpokeConfig;)Lscala/Option;
   #27 = Methodref          #21.#26       // org/scalatest/tools/SlowpokeConfig$.unapply:(Lorg/scalatest/tools/SlowpokeConfig;)Lscala/Option;
   #28 = Utf8               Lorg/scalatest/tools/SlowpokeConfig;
   #29 = Utf8               apply
   #30 = Utf8               (JJ)Lorg/scalatest/tools/SlowpokeConfig;
   #31 = NameAndType        #29:#30       // apply:(JJ)Lorg/scalatest/tools/SlowpokeConfig;
   #32 = Methodref          #21.#31       // org/scalatest/tools/SlowpokeConfig$.apply:(JJ)Lorg/scalatest/tools/SlowpokeConfig;
   #33 = Utf8               tupled
   #34 = Utf8               ()Lscala/Function1;
   #35 = Utf8               ()Lscala/Function1<Lscala/Tuple2<Ljava/lang/Object;Ljava/lang/Object;>;Lorg/scalatest/tools/SlowpokeConfig;>;
   #36 = NameAndType        #33:#34       // tupled:()Lscala/Function1;
   #37 = Methodref          #21.#36       // org/scalatest/tools/SlowpokeConfig$.tupled:()Lscala/Function1;
   #38 = Utf8               curried
   #39 = Utf8               ()Lscala/Function1<Ljava/lang/Object;Lscala/Function1<Ljava/lang/Object;Lorg/scalatest/tools/SlowpokeConfig;>;>;
   #40 = NameAndType        #38:#34       // curried:()Lscala/Function1;
   #41 = Methodref          #21.#40       // org/scalatest/tools/SlowpokeConfig$.curried:()Lscala/Function1;
   #42 = Utf8               productElementNames
   #43 = Utf8               ()Lscala/collection/Iterator;
   #44 = Utf8               ()Lscala/collection/Iterator<Ljava/lang/String;>;
   #45 = Utf8               productElementNames$
   #46 = Utf8               (Lscala/Product;)Lscala/collection/Iterator;
   #47 = NameAndType        #45:#46       // productElementNames$:(Lscala/Product;)Lscala/collection/Iterator;
   #48 = InterfaceMethodref #6.#47        // scala/Product.productElementNames$:(Lscala/Product;)Lscala/collection/Iterator;
   #49 = Utf8               this
   #50 = Utf8               ()J
   #51 = NameAndType        #13:#14       // delayInMillis:J
   #52 = Fieldref           #2.#51        // org/scalatest/tools/SlowpokeConfig.delayInMillis:J
   #53 = NameAndType        #15:#14       // periodInMillis:J
   #54 = Fieldref           #2.#53        // org/scalatest/tools/SlowpokeConfig.periodInMillis:J
   #55 = Utf8               copy
   #56 = Utf8               <init>
   #57 = Utf8               (JJ)V
   #58 = NameAndType        #56:#57       // "<init>":(JJ)V
   #59 = Methodref          #2.#58        // org/scalatest/tools/SlowpokeConfig."<init>":(JJ)V
   #60 = Utf8               copy$default$1
   #61 = NameAndType        #13:#50       // delayInMillis:()J
   #62 = Methodref          #2.#61        // org/scalatest/tools/SlowpokeConfig.delayInMillis:()J
   #63 = Utf8               copy$default$2
   #64 = NameAndType        #15:#50       // periodInMillis:()J
   #65 = Methodref          #2.#64        // org/scalatest/tools/SlowpokeConfig.periodInMillis:()J
   #66 = Utf8               productPrefix
   #67 = Utf8               ()Ljava/lang/String;
   #68 = Utf8               SlowpokeConfig
   #69 = String             #68           // SlowpokeConfig
   #70 = Utf8               productArity
   #71 = Utf8               ()I
   #72 = Utf8               productElement
   #73 = Utf8               (I)Ljava/lang/Object;
   #74 = Utf8               x$1
   #75 = Utf8               scala/runtime/BoxesRunTime
   #76 = Class              #75           // scala/runtime/BoxesRunTime
   #77 = Utf8               boxToLong
   #78 = Utf8               (J)Ljava/lang/Long;
   #79 = NameAndType        #77:#78       // boxToLong:(J)Ljava/lang/Long;
   #80 = Methodref          #76.#79       // scala/runtime/BoxesRunTime.boxToLong:(J)Ljava/lang/Long;
   #81 = Utf8               scala/runtime/Statics
   #82 = Class              #81           // scala/runtime/Statics
   #83 = Utf8               ioobe
   #84 = NameAndType        #83:#73       // ioobe:(I)Ljava/lang/Object;
   #85 = Methodref          #82.#84       // scala/runtime/Statics.ioobe:(I)Ljava/lang/Object;
   #86 = Utf8               I
   #87 = Utf8               productIterator
   #88 = Utf8               ()Lscala/collection/Iterator<Ljava/lang/Object;>;
   #89 = Utf8               scala/runtime/ScalaRunTime$
   #90 = Class              #89           // scala/runtime/ScalaRunTime$
   #91 = Utf8               Lscala/runtime/ScalaRunTime$;
   #92 = NameAndType        #22:#91       // MODULE$:Lscala/runtime/ScalaRunTime$;
   #93 = Fieldref           #90.#92       // scala/runtime/ScalaRunTime$.MODULE$:Lscala/runtime/ScalaRunTime$;
   #94 = Utf8               typedProductIterator
   #95 = NameAndType        #94:#46       // typedProductIterator:(Lscala/Product;)Lscala/collection/Iterator;
   #96 = Methodref          #90.#95       // scala/runtime/ScalaRunTime$.typedProductIterator:(Lscala/Product;)Lscala/collection/Iterator;
   #97 = Utf8               canEqual
   #98 = Utf8               (Ljava/lang/Object;)Z
   #99 = Utf8               Ljava/lang/Object;
  #100 = Utf8               productElementName
  #101 = Utf8               (I)Ljava/lang/String;
  #102 = String             #13           // delayInMillis
  #103 = String             #15           // periodInMillis
  #104 = Utf8               java/lang/String
  #105 = Class              #104          // java/lang/String
  #106 = Utf8               hashCode
  #107 = Integer            -889275714
  #108 = NameAndType        #66:#67       // productPrefix:()Ljava/lang/String;
  #109 = Methodref          #2.#108       // org/scalatest/tools/SlowpokeConfig.productPrefix:()Ljava/lang/String;
  #110 = NameAndType        #106:#71      // hashCode:()I
  #111 = Methodref          #105.#110     // java/lang/String.hashCode:()I
  #112 = Utf8               mix
  #113 = Utf8               (II)I
  #114 = NameAndType        #112:#113     // mix:(II)I
  #115 = Methodref          #82.#114      // scala/runtime/Statics.mix:(II)I
  #116 = Utf8               longHash
  #117 = Utf8               (J)I
  #118 = NameAndType        #116:#117     // longHash:(J)I
  #119 = Methodref          #82.#118      // scala/runtime/Statics.longHash:(J)I
  #120 = Utf8               finalizeHash
  #121 = NameAndType        #120:#113     // finalizeHash:(II)I
  #122 = Methodref          #82.#121      // scala/runtime/Statics.finalizeHash:(II)I
  #123 = Utf8               toString
  #124 = Utf8               _toString
  #125 = Utf8               (Lscala/Product;)Ljava/lang/String;
  #126 = NameAndType        #124:#125     // _toString:(Lscala/Product;)Ljava/lang/String;
  #127 = Methodref          #90.#126      // scala/runtime/ScalaRunTime$._toString:(Lscala/Product;)Ljava/lang/String;
  #128 = Utf8               equals
  #129 = NameAndType        #97:#98       // canEqual:(Ljava/lang/Object;)Z
  #130 = Methodref          #2.#129       // org/scalatest/tools/SlowpokeConfig.canEqual:(Ljava/lang/Object;)Z
  #131 = Utf8               ()V
  #132 = NameAndType        #56:#131      // "<init>":()V
  #133 = Methodref          #4.#132       // java/lang/Object."<init>":()V
  #134 = Utf8               $init$
  #135 = Utf8               (Lscala/Product;)V
  #136 = NameAndType        #134:#135     // $init$:(Lscala/Product;)V
  #137 = InterfaceMethodref #6.#136       // scala/Product.$init$:(Lscala/Product;)V
  #138 = Utf8               Code
  #139 = Utf8               LocalVariableTable
  #140 = Utf8               Signature
  #141 = Utf8               MethodParameters
  #142 = Utf8               LineNumberTable
  #143 = Utf8               StackMapTable
  #144 = Utf8               SourceFile
  #145 = Utf8               RuntimeVisibleAnnotations
  #146 = Utf8               ScalaInlineInfo
  #147 = Utf8               ScalaSig
{
  private final long delayInMillis;
    descriptor: J
    flags: (0x0012) ACC_PRIVATE, ACC_FINAL

  private final long periodInMillis;
    descriptor: J
    flags: (0x0012) ACC_PRIVATE, ACC_FINAL

  public static scala.Option<scala.Tuple2<java.lang.Object, java.lang.Object>> unapply(org.scalatest.tools.SlowpokeConfig);
    descriptor: (Lorg/scalatest/tools/SlowpokeConfig;)Lscala/Option;
    flags: (0x0009) ACC_PUBLIC, ACC_STATIC
    Code:
      stack=2, locals=1, args_size=1
         0: getstatic     #25                 // Field org/scalatest/tools/SlowpokeConfig$.MODULE$:Lorg/scalatest/tools/SlowpokeConfig$;
         3: aload_0
         4: invokevirtual #27                 // Method org/scalatest/tools/SlowpokeConfig$.unapply:(Lorg/scalatest/tools/SlowpokeConfig;)Lscala/Option;
         7: areturn
      LocalVariableTable:
        Start  Length  Slot  Name   Signature
            0       8     0   x$0   Lorg/scalatest/tools/SlowpokeConfig;
    Signature: #18                          // (Lorg/scalatest/tools/SlowpokeConfig;)Lscala/Option<Lscala/Tuple2<Ljava/lang/Object;Ljava/lang/Object;>;>;
    MethodParameters:
      Name                           Flags
      x$0                            final

  public static org.scalatest.tools.SlowpokeConfig apply(long, long);
    descriptor: (JJ)Lorg/scalatest/tools/SlowpokeConfig;
    flags: (0x0009) ACC_PUBLIC, ACC_STATIC
    Code:
      stack=5, locals=4, args_size=2
         0: getstatic     #25                 // Field org/scalatest/tools/SlowpokeConfig$.MODULE$:Lorg/scalatest/tools/SlowpokeConfig$;
         3: lload_0
         4: lload_2
         5: invokevirtual #32                 // Method org/scalatest/tools/SlowpokeConfig$.apply:(JJ)Lorg/scalatest/tools/SlowpokeConfig;
         8: areturn
      LocalVariableTable:
        Start  Length  Slot  Name   Signature
            0       9     0 delayInMillis   J
            0       9     2 periodInMillis   J
    MethodParameters:
      Name                           Flags
      delayInMillis                  final
      periodInMillis                 final

  public static scala.Function1<scala.Tuple2<java.lang.Object, java.lang.Object>, org.scalatest.tools.SlowpokeConfig> tupled();
    descriptor: ()Lscala/Function1;
    flags: (0x0009) ACC_PUBLIC, ACC_STATIC
    Code:
      stack=1, locals=0, args_size=0
         0: getstatic     #25                 // Field org/scalatest/tools/SlowpokeConfig$.MODULE$:Lorg/scalatest/tools/SlowpokeConfig$;
         3: invokevirtual #37                 // Method org/scalatest/tools/SlowpokeConfig$.tupled:()Lscala/Function1;
         6: areturn
    Signature: #35                          // ()Lscala/Function1<Lscala/Tuple2<Ljava/lang/Object;Ljava/lang/Object;>;Lorg/scalatest/tools/SlowpokeConfig;>;

  public static scala.Function1<java.lang.Object, scala.Function1<java.lang.Object, org.scalatest.tools.SlowpokeConfig>> curried();
    descriptor: ()Lscala/Function1;
    flags: (0x0009) ACC_PUBLIC, ACC_STATIC
    Code:
      stack=1, locals=0, args_size=0
         0: getstatic     #25                 // Field org/scalatest/tools/SlowpokeConfig$.MODULE$:Lorg/scalatest/tools/SlowpokeConfig$;
         3: invokevirtual #41                 // Method org/scalatest/tools/SlowpokeConfig$.curried:()Lscala/Function1;
         6: areturn
    Signature: #39                          // ()Lscala/Function1<Ljava/lang/Object;Lscala/Function1<Ljava/lang/Object;Lorg/scalatest/tools/SlowpokeConfig;>;>;

  public scala.collection.Iterator<java.lang.String> productElementNames();
    descriptor: ()Lscala/collection/Iterator;
    flags: (0x0001) ACC_PUBLIC
    Code:
      stack=1, locals=1, args_size=1
         0: aload_0
         1: invokestatic  #48                 // InterfaceMethod scala/Product.productElementNames$:(Lscala/Product;)Lscala/collection/Iterator;
         4: areturn
      LineNumberTable:
        line 128: 0
      LocalVariableTable:
        Start  Length  Slot  Name   Signature
            0       5     0  this   Lorg/scalatest/tools/SlowpokeConfig;
    Signature: #44                          // ()Lscala/collection/Iterator<Ljava/lang/String;>;

  public long delayInMillis();
    descriptor: ()J
    flags: (0x0001) ACC_PUBLIC
    Code:
      stack=2, locals=1, args_size=1
         0: aload_0
         1: getfield      #52                 // Field delayInMillis:J
         4: lreturn
      LineNumberTable:
        line 128: 0
      LocalVariableTable:
        Start  Length  Slot  Name   Signature
            0       5     0  this   Lorg/scalatest/tools/SlowpokeConfig;

  public long periodInMillis();
    descriptor: ()J
    flags: (0x0001) ACC_PUBLIC
    Code:
      stack=2, locals=1, args_size=1
         0: aload_0
         1: getfield      #54                 // Field periodInMillis:J
         4: lreturn
      LineNumberTable:
        line 128: 0
      LocalVariableTable:
        Start  Length  Slot  Name   Signature
            0       5     0  this   Lorg/scalatest/tools/SlowpokeConfig;

  public org.scalatest.tools.SlowpokeConfig copy(long, long);
    descriptor: (JJ)Lorg/scalatest/tools/SlowpokeConfig;
    flags: (0x0001) ACC_PUBLIC
    Code:
      stack=6, locals=5, args_size=3
         0: new           #2                  // class org/scalatest/tools/SlowpokeConfig
         3: dup
         4: lload_1
         5: lload_3
         6: invokespecial #59                 // Method "<init>":(JJ)V
         9: areturn
      LineNumberTable:
        line 128: 0
      LocalVariableTable:
        Start  Length  Slot  Name   Signature
            0      10     0  this   Lorg/scalatest/tools/SlowpokeConfig;
            0      10     1 delayInMillis   J
            0      10     3 periodInMillis   J
    MethodParameters:
      Name                           Flags
      delayInMillis                  final
      periodInMillis                 final

  public long copy$default$1();
    descriptor: ()J
    flags: (0x0001) ACC_PUBLIC
    Code:
      stack=2, locals=1, args_size=1
         0: aload_0
         1: invokevirtual #62                 // Method delayInMillis:()J
         4: lreturn
      LineNumberTable:
        line 128: 0
      LocalVariableTable:
        Start  Length  Slot  Name   Signature
            0       5     0  this   Lorg/scalatest/tools/SlowpokeConfig;

  public long copy$default$2();
    descriptor: ()J
    flags: (0x0001) ACC_PUBLIC
    Code:
      stack=2, locals=1, args_size=1
         0: aload_0
         1: invokevirtual #65                 // Method periodInMillis:()J
         4: lreturn
      LineNumberTable:
        line 128: 0
      LocalVariableTable:
        Start  Length  Slot  Name   Signature
            0       5     0  this   Lorg/scalatest/tools/SlowpokeConfig;

  public java.lang.String productPrefix();
    descriptor: ()Ljava/lang/String;
    flags: (0x0001) ACC_PUBLIC
    Code:
      stack=1, locals=1, args_size=1
         0: ldc           #69                 // String SlowpokeConfig
         2: areturn
      LineNumberTable:
        line 128: 0
      LocalVariableTable:
        Start  Length  Slot  Name   Signature
            0       3     0  this   Lorg/scalatest/tools/SlowpokeConfig;

  public int productArity();
    descriptor: ()I
    flags: (0x0001) ACC_PUBLIC
    Code:
      stack=1, locals=1, args_size=1
         0: iconst_2
         1: ireturn
      LineNumberTable:
        line 128: 0
      LocalVariableTable:
        Start  Length  Slot  Name   Signature
            0       2     0  this   Lorg/scalatest/tools/SlowpokeConfig;

  public java.lang.Object productElement(int);
    descriptor: (I)Ljava/lang/Object;
    flags: (0x0001) ACC_PUBLIC
    Code:
      stack=2, locals=3, args_size=2
         0: iload_1
         1: istore_2
         2: iload_2
         3: tableswitch   { // 0 to 1
                       0: 24
                       1: 34
                 default: 44
            }
        24: aload_0
        25: invokevirtual #62                 // Method delayInMillis:()J
        28: invokestatic  #80                 // Method scala/runtime/BoxesRunTime.boxToLong:(J)Ljava/lang/Long;
        31: goto          51
        34: aload_0
        35: invokevirtual #65                 // Method periodInMillis:()J
        38: invokestatic  #80                 // Method scala/runtime/BoxesRunTime.boxToLong:(J)Ljava/lang/Long;
        41: goto          51
        44: iload_1
        45: invokestatic  #85                 // Method scala/runtime/Statics.ioobe:(I)Ljava/lang/Object;
        48: goto          51
        51: areturn
      StackMapTable: number_of_entries = 4
        frame_type = 252 /* append */
          offset_delta = 24
          locals = [ int ]
        frame_type = 9 /* same */
        frame_type = 9 /* same */
        frame_type = 70 /* same_locals_1_stack_item */
          stack = [ class java/lang/Object ]
      LineNumberTable:
        line 128: 0
      LocalVariableTable:
        Start  Length  Slot  Name   Signature
            0      52     0  this   Lorg/scalatest/tools/SlowpokeConfig;
            0      52     1   x$1   I
    MethodParameters:
      Name                           Flags
      x$1                            final

  public scala.collection.Iterator<java.lang.Object> productIterator();
    descriptor: ()Lscala/collection/Iterator;
    flags: (0x0001) ACC_PUBLIC
    Code:
      stack=2, locals=1, args_size=1
         0: getstatic     #93                 // Field scala/runtime/ScalaRunTime$.MODULE$:Lscala/runtime/ScalaRunTime$;
         3: aload_0
         4: invokevirtual #96                 // Method scala/runtime/ScalaRunTime$.typedProductIterator:(Lscala/Product;)Lscala/collection/Iterator;
         7: areturn
      LineNumberTable:
        line 128: 0
      LocalVariableTable:
        Start  Length  Slot  Name   Signature
            0       8     0  this   Lorg/scalatest/tools/SlowpokeConfig;
    Signature: #88                          // ()Lscala/collection/Iterator<Ljava/lang/Object;>;

  public boolean canEqual(java.lang.Object);
    descriptor: (Ljava/lang/Object;)Z
    flags: (0x0001) ACC_PUBLIC
    Code:
      stack=1, locals=2, args_size=2
         0: aload_1
         1: instanceof    #2                  // class org/scalatest/tools/SlowpokeConfig
         4: ireturn
      LineNumberTable:
        line 128: 0
      LocalVariableTable:
        Start  Length  Slot  Name   Signature
            0       5     0  this   Lorg/scalatest/tools/SlowpokeConfig;
            0       5     1   x$1   Ljava/lang/Object;
    MethodParameters:
      Name                           Flags
      x$1                            final

  public java.lang.String productElementName(int);
    descriptor: (I)Ljava/lang/String;
    flags: (0x0001) ACC_PUBLIC
    Code:
      stack=1, locals=3, args_size=2
         0: iload_1
         1: istore_2
         2: iload_2
         3: tableswitch   { // 0 to 1
                       0: 24
                       1: 29
                 default: 34
            }
        24: ldc           #102                // String delayInMillis
        26: goto          44
        29: ldc           #103                // String periodInMillis
        31: goto          44
        34: iload_1
        35: invokestatic  #85                 // Method scala/runtime/Statics.ioobe:(I)Ljava/lang/Object;
        38: checkcast     #105                // class java/lang/String
        41: goto          44
        44: areturn
      StackMapTable: number_of_entries = 4
        frame_type = 252 /* append */
          offset_delta = 24
          locals = [ int ]
        frame_type = 4 /* same */
        frame_type = 4 /* same */
        frame_type = 73 /* same_locals_1_stack_item */
          stack = [ class java/lang/String ]
      LineNumberTable:
        line 128: 0
      LocalVariableTable:
        Start  Length  Slot  Name   Signature
            0      45     0  this   Lorg/scalatest/tools/SlowpokeConfig;
            0      45     1   x$1   I
    MethodParameters:
      Name                           Flags
      x$1                            final

  public int hashCode();
    descriptor: ()I
    flags: (0x0001) ACC_PUBLIC
    Code:
      stack=3, locals=2, args_size=1
         0: ldc           #107                // int -889275714
         2: istore_1
         3: iload_1
         4: aload_0
         5: invokevirtual #109                // Method productPrefix:()Ljava/lang/String;
         8: invokevirtual #111                // Method java/lang/String.hashCode:()I
        11: invokestatic  #115                // Method scala/runtime/Statics.mix:(II)I
        14: istore_1
        15: iload_1
        16: aload_0
        17: invokevirtual #62                 // Method delayInMillis:()J
        20: invokestatic  #119                // Method scala/runtime/Statics.longHash:(J)I
        23: invokestatic  #115                // Method scala/runtime/Statics.mix:(II)I
        26: istore_1
        27: iload_1
        28: aload_0
        29: invokevirtual #65                 // Method periodInMillis:()J
        32: invokestatic  #119                // Method scala/runtime/Statics.longHash:(J)I
        35: invokestatic  #115                // Method scala/runtime/Statics.mix:(II)I
        38: istore_1
        39: iload_1
        40: iconst_2
        41: invokestatic  #122                // Method scala/runtime/Statics.finalizeHash:(II)I
        44: ireturn
      LineNumberTable:
        line 128: 0
      LocalVariableTable:
        Start  Length  Slot  Name   Signature
            0      45     0  this   Lorg/scalatest/tools/SlowpokeConfig;

  public java.lang.String toString();
    descriptor: ()Ljava/lang/String;
    flags: (0x0001) ACC_PUBLIC
    Code:
      stack=2, locals=1, args_size=1
         0: getstatic     #93                 // Field scala/runtime/ScalaRunTime$.MODULE$:Lscala/runtime/ScalaRunTime$;
         3: aload_0
         4: invokevirtual #127                // Method scala/runtime/ScalaRunTime$._toString:(Lscala/Product;)Ljava/lang/String;
         7: areturn
      LineNumberTable:
        line 128: 0
      LocalVariableTable:
        Start  Length  Slot  Name   Signature
            0       8     0  this   Lorg/scalatest/tools/SlowpokeConfig;

  public boolean equals(java.lang.Object);
    descriptor: (Ljava/lang/Object;)Z
    flags: (0x0001) ACC_PUBLIC
    Code:
      stack=4, locals=5, args_size=2
         0: aload_0
         1: aload_1
         2: if_acmpeq     80
         5: aload_1
         6: astore_3
         7: aload_3
         8: instanceof    #2                  // class org/scalatest/tools/SlowpokeConfig
        11: ifeq          19
        14: iconst_1
        15: istore_2
        16: goto          27
        19: goto          22
        22: iconst_0
        23: istore_2
        24: goto          27
        27: iload_2
        28: ifeq          84
        31: aload_1
        32: checkcast     #2                  // class org/scalatest/tools/SlowpokeConfig
        35: astore        4
        37: aload_0
        38: invokevirtual #62                 // Method delayInMillis:()J
        41: aload         4
        43: invokevirtual #62                 // Method delayInMillis:()J
        46: lcmp
        47: ifne          76
        50: aload_0
        51: invokevirtual #65                 // Method periodInMillis:()J
        54: aload         4
        56: invokevirtual #65                 // Method periodInMillis:()J
        59: lcmp
        60: ifne          76
        63: aload         4
        65: aload_0
        66: invokevirtual #130                // Method canEqual:(Ljava/lang/Object;)Z
        69: ifeq          76
        72: iconst_1
        73: goto          77
        76: iconst_0
        77: ifeq          84
        80: iconst_1
        81: goto          85
        84: iconst_0
        85: ireturn
      StackMapTable: number_of_entries = 8
        frame_type = 253 /* append */
          offset_delta = 19
          locals = [ top, class java/lang/Object ]
        frame_type = 2 /* same */
        frame_type = 255 /* full_frame */
          offset_delta = 4
          locals = [ class org/scalatest/tools/SlowpokeConfig, class java/lang/Object, int, class java/lang/Object ]
          stack = []
        frame_type = 252 /* append */
          offset_delta = 48
          locals = [ class org/scalatest/tools/SlowpokeConfig ]
        frame_type = 64 /* same_locals_1_stack_item */
          stack = [ int ]
        frame_type = 248 /* chop */
          offset_delta = 2
        frame_type = 253 /* append */
          offset_delta = 3
          locals = [ int, class java/lang/Object ]
        frame_type = 255 /* full_frame */
          offset_delta = 0
          locals = [ class org/scalatest/tools/SlowpokeConfig, class java/lang/Object ]
          stack = [ int ]
      LineNumberTable:
        line 128: 0
      LocalVariableTable:
        Start  Length  Slot  Name   Signature
            0      86     0  this   Lorg/scalatest/tools/SlowpokeConfig;
            0      86     1   x$1   Ljava/lang/Object;
    MethodParameters:
      Name                           Flags
      x$1                            final

  public org.scalatest.tools.SlowpokeConfig(long, long);
    descriptor: (JJ)V
    flags: (0x0001) ACC_PUBLIC
    Code:
      stack=3, locals=5, args_size=3
         0: aload_0
         1: lload_1
         2: putfield      #52                 // Field delayInMillis:J
         5: aload_0
         6: lload_3
         7: putfield      #54                 // Field periodInMillis:J
        10: aload_0
        11: invokespecial #133                // Method java/lang/Object."<init>":()V
        14: aload_0
        15: invokestatic  #137                // InterfaceMethod scala/Product.$init$:(Lscala/Product;)V
        18: return
      LineNumberTable:
        line 128: 0
      LocalVariableTable:
        Start  Length  Slot  Name   Signature
            0      19     0  this   Lorg/scalatest/tools/SlowpokeConfig;
            0      19     1 delayInMillis   J
            0      19     3 periodInMillis   J
    MethodParameters:
      Name                           Flags
      delayInMillis                  final
      periodInMillis                 final
}
SourceFile: "Runner.scala"
RuntimeVisibleAnnotations:
  0: #10(#11=s#12)
    scala.reflect.ScalaSignature(
      bytes="\u0006\u0005\u00055c!B\r\u001b\u0001j\u0001\u0003\u0002C\u001c\u0001\u0005+\u0007I\u0011\u0001\u001d\t\u0011q\u0002!\u0011#Q\u0001\neB\u0001\"\u0010\u0001\u0003\u0016\u0004%\t\u0001\u000f\u0005\t}\u0001\u0011\t\u0012)A\u0005s!)q\b\u0001C\u0001\u0001\"9Q\tAA\u0001\n\u00031\u0005bB%\u0001#\u0003%\tA\u0013\u0005\b+\u0002\t\n\u0011\"\u0001K\u0011\u001d1\u0006!!A\u0005B]Cq\u0001\u0019\u0001\u0002\u0002\u0013\u0005\u0011\rC\u0004f\u0001\u0005\u0005I\u0011\u00014\t\u000f1\u0004\u0011\u0011!C![\"9A\u000fAA\u0001\n\u0003)\bb\u0002>\u0001\u0003\u0003%\te\u001f\u0005\b{\u0002\t\t\u0011\"\u0011\u007f\u0011!y\b!!A\u0005B\u0005\u0005\u0001\"CA\u0002\u0001\u0005\u0005I\u0011IA\u0003\u000f)\tIAGA\u0001\u0012\u0003Q\u00121\u0002\u0004\n3i\t\t\u0011#\u0001\u001b\u0003\u001bAaaP\n\u0005\u0002\u0005\u0015\u0002\u0002C@\u0014\u0003\u0003%)%!\u0001\t\u0013\u0005\u001d2#!A\u0005\u0002\u0006%\u0002\"CA\u0018\'\u0005\u0005I\u0011QA\u0019\u0011%\t\u0019eEA\u0001\n\u0013\t)E\u0001\bTY><\bo\\6f\u0007>tg-[4\u000b\u0005ma\u0012!\u0002;p_2\u001c(BA\u000f\u001f\u0003%\u00198-\u00197bi\u0016\u001cHOC\u0001 \u0003\ry\'oZ\n\u0005\u0001\u0005:#\u0006\u0005\u0002#K5\t1EC\u0001%\u0003\u0015\u00198-\u00197b\u0013\t13E\u0001\u0004B]f\u0014VM\u001a\t\u0003E!J!!K\u0012\u0003\u000fA\u0013x\u000eZ;diB\u00111\u0006\u000e\b\u0003YIr!!L\u0019\u000e\u00039R!a\f\u0019\u0002\rq\u0012xn\u001c;?\u0007\u0001I\u0011\u0001J\u0005\u0003g\r\nq\u0001]1dW\u0006<W-\u0003\u00026m\ta1+\u001a:jC2L\'0\u00192mK*\u00111gI\u0001\u000eI\u0016d\u0017-_%o\u001b&dG.[:\u0016\u0003e\u0002\"A\t\u001e\n\u0005m\u001a#\u0001\u0002\'p]\u001e\fa\u0002Z3mCfLe.T5mY&\u001c\b%\u0001\bqKJLw\u000eZ%o\u001b&dG.[:\u0002\u001fA,\'/[8e\u0013:l\u0015\u000e\u001c7jg\u0002\na\u0001P5oSRtDcA!D\tB\u0011!\tA\u0007\u00025!)q\'\u0002a\u0001s!)Q(\u0002a\u0001s\u0005!1m\u001c9z)\r\tu\t\u0013\u0005\bo\u0019\u0001\n\u00111\u0001:\u0011\u001did\u0001%AA\u0002e\nabY8qs\u0012\"WMZ1vYR$\u0013\'F\u0001LU\tIDjK\u0001N!\tq5+D\u0001P\u0015\t\u0001\u0016+A\u0005v]\u000eDWmY6fI*\u0011!kI\u0001\u000bC:tw\u000e^1uS>t\u0017B\u0001+P\u0005E)hn\u00195fG.,GMV1sS\u0006t7-Z\u0001\u000fG>\u0004\u0018\u0010\n3fM\u0006,H\u000e\u001e\u00133\u00035\u0001(o\u001c3vGR\u0004&/\u001a4jqV\t\u0001\f\u0005\u0002Z=6\t!L\u0003\u0002\\9\u0006!A.\u00198h\u0015\u0005i\u0016\u0001\u00026bm\u0006L!a\u0018.\u0003\rM#(/\u001b8h\u00031\u0001(o\u001c3vGR\f%/\u001b;z+\u0005\u0011\u0007C\u0001\u0012d\u0013\t!7EA\u0002J]R\fa\u0002\u001d:pIV\u001cG/\u00127f[\u0016tG\u000f\u0006\u0002hUB\u0011!\u0005[\u0005\u0003S\u000e\u00121!\u00118z\u0011\u001dY7\"!AA\u0002\t\f1\u0001\u001f\u00132\u0003=\u0001(o\u001c3vGRLE/\u001a:bi>\u0014X#\u00018\u0011\u0007=\u0014x-D\u0001q\u0015\t\t8%\u0001\u0006d_2dWm\u0019;j_:L!a\u001d9\u0003\u0011%#XM]1u_J\f\u0001bY1o\u000bF,\u0018\r\u001c\u000b\u0003mf\u0004\"AI<\n\u0005a\u001c#a\u0002\"p_2,\u0017M\u001c\u0005\bW6\t\t\u00111\u0001h\u0003I\u0001(o\u001c3vGR,E.Z7f]Rt\u0015-\\3\u0015\u0005ac\bbB6\u000f\u0003\u0003\u0005\rAY\u0001\tQ\u0006\u001c\bnQ8eKR\t!-\u0001\u0005u_N#(/\u001b8h)\u0005A\u0016AB3rk\u0006d7\u000fF\u0002w\u0003\u000fAqa[\t\u0002\u0002\u0003\u0007q-\u0001\bTY><\bo\\6f\u0007>tg-[4\u0011\u0005\t\u001b2#B\n\u0002\u0010\u0005m\u0001cBA\t\u0003/I\u0014(Q\u0007\u0003\u0003\'Q1!!\u0006$\u0003\u001d\u0011XO\u001c;j[\u0016LA!!\u0007\u0002\u0014\t\t\u0012IY:ue\u0006\u001cGOR;oGRLwN\u001c\u001a\u0011\t\u0005u\u00111E\u0007\u0003\u0003?Q1!!\t]\u0003\tIw.C\u00026\u0003?!\"!a\u0003\u0002\u000b\u0005\u0004\b\u000f\\=\u0015\u000b\u0005\u000bY#!\f\t\u000b]2\u0002\u0019A\u001d\t\u000bu2\u0002\u0019A\u001d\u0002\u000fUt\u0017\r\u001d9msR!\u00111GA !\u0015\u0011\u0013QGA\u001d\u0013\r\t9d\t\u0002\u0007\u001fB$\u0018n\u001c8\u0011\u000b\t\nY$O\u001d\n\u0007\u0005u2E\u0001\u0004UkBdWM\r\u0005\t\u0003\u0003:\u0012\u0011!a\u0001\u0003\u0006\u0019\u0001\u0010\n\u0019\u0002\u0019]\u0014\u0018\u000e^3SKBd\u0017mY3\u0015\u0005\u0005\u001d\u0003cA-\u0002J%\u0019\u00111\n.\u0003\r=\u0013\'.Z2u\u0001"
    )
  ScalaInlineInfo: length = 0x54 (unknown attribute)
   01 00 00 10 00 38 00 39 00 00 61 00 62 00 00 37
   00 1E 00 00 3C 00 32 00 00 3F 00 32 00 00 0D 00
   32 00 00 80 00 62 00 00 6A 00 47 00 00 0F 00 32
   00 00 46 00 47 00 00 48 00 49 00 00 64 00 65 00
   00 2A 00 2B 00 00 57 00 2B 00 00 42 00 43 00 00
   7B 00 43 00
  ScalaSig: length = 0x3 (unknown attribute)
   05 02 00
