Classfile /Users/mw/Projects/slang-braindump/.jar/jar8/assemble/slang-braindump/assemble/content/org/scalatest/tools/StandardErrReporterConfiguration.class
  Last modified May 29, 2022; size 5804 bytes
  SHA-256 checksum 9ad801eabc69c8b34e7b53f1ba0bd2cd8d6c6c3c2ee1a54be5fdba4c2d18daa1
  Compiled from "ReporterConfiguration.scala"
public class org.scalatest.tools.StandardErrReporterConfiguration extends org.scalatest.tools.ReporterConfiguration
  minor version: 0
  major version: 52
  flags: (0x0021) ACC_PUBLIC, ACC_SUPER
  this_class: #2                          // org/scalatest/tools/StandardErrReporterConfiguration
  super_class: #4                         // org/scalatest/tools/ReporterConfiguration
  interfaces: 0, fields: 1, methods: 17, attributes: 4
Constant pool:
    #1 = Utf8               org/scalatest/tools/StandardErrReporterConfiguration
    #2 = Class              #1            // org/scalatest/tools/StandardErrReporterConfiguration
    #3 = Utf8               org/scalatest/tools/ReporterConfiguration
    #4 = Class              #3            // org/scalatest/tools/ReporterConfiguration
    #5 = Utf8               ReporterConfiguration.scala
    #6 = Utf8               Lscala/reflect/ScalaSignature;
    #7 = Utf8               bytes
    #8 = Utf8               \u0006\u0005\u0005\u0015c!\u0002\f\u0018\u0001^i\u0002\u0002C\u001b\u0001\u0005+\u0007I\u0011\u0001\u001c\t\u0011\t\u0003!\u0011#Q\u0001\n]BQa\u0011\u0001\u0005\u0002\u0011Cqa\u0012\u0001\u0002\u0002\u0013\u0005\u0001\nC\u0004K\u0001E\u0005I\u0011A&\t\u000fY\u0003\u0011\u0011!C!/\"9\u0001\rAA\u0001\n\u0003\t\u0007bB3\u0001\u0003\u0003%\tA\u001a\u0005\bY\u0002\t\t\u0011\"\u0011n\u0011\u001d!\b!!A\u0005\u0002UDqA\u001f\u0001\u0002\u0002\u0013\u00053\u0010C\u0004~\u0001\u0005\u0005I\u0011\t@\t\u0011}\u0004\u0011\u0011!C!\u0003\u0003A\u0011\"a\u0001\u0001\u0003\u0003%\t%!\u0002\b\u0015\u0005%q#!A\t\u0002]\tYAB\u0005\u0017/\u0005\u0005\t\u0012A\f\u0002\u000e!11\t\u0005C\u0001\u0003KA\u0001b \t\u0002\u0002\u0013\u0015\u0013\u0011\u0001\u0005\n\u0003O\u0001\u0012\u0011!CA\u0003SA\u0011\"!\f\u0011\u0003\u0003%\t)a\f\t\u0013\u0005m\u0002#!A\u0005\n\u0005u\"\u0001I*uC:$\u0017M\u001d3FeJ\u0014V\r]8si\u0016\u00148i\u001c8gS\u001e,(/\u0019;j_:T!\u0001G\r\u0002\u000bQ|w\u000e\\:\u000b\u0005iY\u0012!C:dC2\fG/Z:u\u0015\u0005a\u0012aA8sON!\u0001A\b\u0012)!\ty\u0002%D\u0001\u0018\u0013\t\tsCA\u000bSKB|\'\u000f^3s\u0007>tg-[4ve\u0006$\u0018n\u001c8\u0011\u0005\r2S\"\u0001\u0013\u000b\u0003\u0015\nQa]2bY\u0006L!a\n\u0013\u0003\u000fA\u0013x\u000eZ;diB\u0011\u0011F\r\b\u0003UAr!aK\u0018\u000e\u00031R!!\f\u0018\u0002\rq\u0012xn\u001c;?\u0007\u0001I\u0011!J\u0005\u0003c\u0011\nq\u0001]1dW\u0006<W-\u0003\u00024i\ta1+\u001a:jC2L\'0\u00192mK*\u0011\u0011\u0007J\u0001\nG>tg-[4TKR,\u0012a\u000e\t\u0004qqzdBA\u001d;!\tYC%\u0003\u0002<I\u00051\u0001K]3eK\u001aL!!\u0010 \u0003\u0007M+GO\u0003\u0002<IA\u0011q\u0004Q\u0005\u0003\u0003^\u00111CU3q_J$XM]\"p]\u001aLw\rU1sC6\f!bY8oM&<7+\u001a;!\u0003\u0019a\u0014N\\5u}Q\u0011QI\u0012\t\u0003?\u0001AQ!N\u0002A\u0002]\nAaY8qsR\u0011Q)\u0013\u0005\bk\u0011\u0001\n\u00111\u00018\u00039\u0019w\u000e]=%I\u00164\u0017-\u001e7uIE*\u0012\u0001\u0014\u0016\u0003o5[\u0013A\u0014\t\u0003\u001fRk\u0011\u0001\u0015\u0006\u0003#J\u000b\u0011\"\u001e8dQ\u0016\u001c7.\u001a3\u000b\u0005M#\u0013AC1o]>$\u0018\r^5p]&\u0011Q\u000b\u0015\u0002\u0012k:\u001c\u0007.Z2lK\u00124\u0016M]5b]\u000e,\u0017!\u00049s_\u0012,8\r\u001e)sK\u001aL\u00070F\u0001Y!\tIf,D\u0001[\u0015\tYF,\u0001\u0003mC:<\'\"A/\u0002\t)\fg/Y\u0005\u0003?j\u0013aa\u0015;sS:<\u0017\u0001\u00049s_\u0012,8\r^!sSRLX#\u00012\u0011\u0005\r\u001a\u0017B\u00013%\u0005\rIe\u000e^\u0001\u000faJ|G-^2u\u000b2,W.\u001a8u)\t9\'\u000e\u0005\u0002$Q&\u0011\u0011\u000e\n\u0002\u0004\u0003:L\bbB6\t\u0003\u0003\u0005\rAY\u0001\u0004q\u0012\n\u0014a\u00049s_\u0012,8\r^%uKJ\fGo\u001c:\u0016\u00039\u00042a\u001c:h\u001b\u0005\u0001(BA9%\u0003)\u0019w\u000e\u001c7fGRLwN\\\u0005\u0003gB\u0014\u0001\"\u0013;fe\u0006$xN]\u0001\tG\u0006tW)];bYR\u0011a/\u001f\t\u0003G]L!\u0001\u001f\u0013\u0003\u000f\t{w\u000e\\3b]\"91NCA\u0001\u0002\u00049\u0017A\u00059s_\u0012,8\r^#mK6,g\u000e\u001e(b[\u0016$\"\u0001\u0017?\t\u000f-\\\u0011\u0011!a\u0001E\u0006A\u0001.Y:i\u0007>$W\rF\u0001c\u0003!!xn\u0015;sS:<G#\u0001-\u0002\r\u0015\fX/\u00197t)\r1\u0018q\u0001\u0005\bW:\t\t\u00111\u0001h\u0003\u0001\u001aF/\u00198eCJ$WI\u001d:SKB|\'\u000f^3s\u0007>tg-[4ve\u0006$\u0018n\u001c8\u0011\u0005}\u00012#\u0002\t\u0002\u0010\u0005m\u0001CBA\t\u0003/9T)\u0004\u0002\u0002\u0014)\u0019\u0011Q\u0003\u0013\u0002\u000fI,h\u000e^5nK&!\u0011\u0011DA\n\u0005E\t%m\u001d;sC\u000e$h)\u001e8di&|g.\r\t\u0005\u0003;\t\u0019#\u0004\u0002\u0002 )\u0019\u0011\u0011\u0005/\u0002\u0005%|\u0017bA\u001a\u0002 Q\u0011\u00111B\u0001\u0006CB\u0004H.\u001f\u000b\u0004\u000b\u0006-\u0002\"B\u001b\u0014\u0001\u00049\u0014aB;oCB\u0004H.\u001f\u000b\u0005\u0003c\t9\u0004\u0005\u0003$\u0003g9\u0014bAA\u001bI\t1q\n\u001d;j_:D\u0001\"!\u000f\u0015\u0003\u0003\u0005\r!R\u0001\u0004q\u0012\u0002\u0014\u0001D<sSR,\'+\u001a9mC\u000e,GCAA !\rI\u0016\u0011I\u0005\u0004\u0003\u0007R&AB(cU\u0016\u001cG\u000f
    #9 = Utf8               configSet
   #10 = Utf8               Lscala/collection/immutable/Set;
   #11 = Utf8               Lscala/collection/immutable/Set<Lorg/scalatest/tools/ReporterConfigParam;>;
   #12 = Utf8               unapply
   #13 = Utf8               (Lorg/scalatest/tools/StandardErrReporterConfiguration;)Lscala/Option;
   #14 = Utf8               (Lorg/scalatest/tools/StandardErrReporterConfiguration;)Lscala/Option<Lscala/collection/immutable/Set<Lorg/scalatest/tools/ReporterConfigParam;>;>;
   #15 = Utf8               x$0
   #16 = Utf8               org/scalatest/tools/StandardErrReporterConfiguration$
   #17 = Class              #16           // org/scalatest/tools/StandardErrReporterConfiguration$
   #18 = Utf8               MODULE$
   #19 = Utf8               Lorg/scalatest/tools/StandardErrReporterConfiguration$;
   #20 = NameAndType        #18:#19       // MODULE$:Lorg/scalatest/tools/StandardErrReporterConfiguration$;
   #21 = Fieldref           #17.#20       // org/scalatest/tools/StandardErrReporterConfiguration$.MODULE$:Lorg/scalatest/tools/StandardErrReporterConfiguration$;
   #22 = NameAndType        #12:#13       // unapply:(Lorg/scalatest/tools/StandardErrReporterConfiguration;)Lscala/Option;
   #23 = Methodref          #17.#22       // org/scalatest/tools/StandardErrReporterConfiguration$.unapply:(Lorg/scalatest/tools/StandardErrReporterConfiguration;)Lscala/Option;
   #24 = Utf8               Lorg/scalatest/tools/StandardErrReporterConfiguration;
   #25 = Utf8               apply
   #26 = Utf8               (Lscala/collection/immutable/Set;)Lorg/scalatest/tools/StandardErrReporterConfiguration;
   #27 = Utf8               (Lscala/collection/immutable/Set<Lorg/scalatest/tools/ReporterConfigParam;>;)Lorg/scalatest/tools/StandardErrReporterConfiguration;
   #28 = NameAndType        #25:#26       // apply:(Lscala/collection/immutable/Set;)Lorg/scalatest/tools/StandardErrReporterConfiguration;
   #29 = Methodref          #17.#28       // org/scalatest/tools/StandardErrReporterConfiguration$.apply:(Lscala/collection/immutable/Set;)Lorg/scalatest/tools/StandardErrReporterConfiguration;
   #30 = Utf8               andThen
   #31 = Utf8               (Lscala/Function1;)Lscala/Function1;
   #32 = Utf8               <A:Ljava/lang/Object;>(Lscala/Function1<Lorg/scalatest/tools/StandardErrReporterConfiguration;TA;>;)Lscala/Function1<Lscala/collection/immutable/Set<Lorg/scalatest/tools/ReporterConfigParam;>;TA;>;
   #33 = Utf8               g
   #34 = NameAndType        #30:#31       // andThen:(Lscala/Function1;)Lscala/Function1;
   #35 = Methodref          #17.#34       // org/scalatest/tools/StandardErrReporterConfiguration$.andThen:(Lscala/Function1;)Lscala/Function1;
   #36 = Utf8               Lscala/Function1;
   #37 = Utf8               compose
   #38 = Utf8               <A$:Ljava/lang/Object;>(Lscala/Function1<TA$;Lscala/collection/immutable/Set<Lorg/scalatest/tools/ReporterConfigParam;>;>;)Lscala/Function1<TA$;Lorg/scalatest/tools/StandardErrReporterConfiguration;>;
   #39 = NameAndType        #37:#31       // compose:(Lscala/Function1;)Lscala/Function1;
   #40 = Methodref          #17.#39       // org/scalatest/tools/StandardErrReporterConfiguration$.compose:(Lscala/Function1;)Lscala/Function1;
   #41 = Utf8               ()Lscala/collection/immutable/Set;
   #42 = Utf8               ()Lscala/collection/immutable/Set<Lorg/scalatest/tools/ReporterConfigParam;>;
   #43 = NameAndType        #9:#10        // configSet:Lscala/collection/immutable/Set;
   #44 = Fieldref           #2.#43        // org/scalatest/tools/StandardErrReporterConfiguration.configSet:Lscala/collection/immutable/Set;
   #45 = Utf8               this
   #46 = Utf8               copy
   #47 = Utf8               <init>
   #48 = Utf8               (Lscala/collection/immutable/Set;)V
   #49 = NameAndType        #47:#48       // "<init>":(Lscala/collection/immutable/Set;)V
   #50 = Methodref          #2.#49        // org/scalatest/tools/StandardErrReporterConfiguration."<init>":(Lscala/collection/immutable/Set;)V
   #51 = Utf8               copy$default$1
   #52 = NameAndType        #9:#41        // configSet:()Lscala/collection/immutable/Set;
   #53 = Methodref          #2.#52        // org/scalatest/tools/StandardErrReporterConfiguration.configSet:()Lscala/collection/immutable/Set;
   #54 = Utf8               productPrefix
   #55 = Utf8               ()Ljava/lang/String;
   #56 = Utf8               StandardErrReporterConfiguration
   #57 = String             #56           // StandardErrReporterConfiguration
   #58 = Utf8               productArity
   #59 = Utf8               ()I
   #60 = Utf8               productElement
   #61 = Utf8               (I)Ljava/lang/Object;
   #62 = Utf8               x$1
   #63 = Utf8               scala/runtime/Statics
   #64 = Class              #63           // scala/runtime/Statics
   #65 = Utf8               ioobe
   #66 = NameAndType        #65:#61       // ioobe:(I)Ljava/lang/Object;
   #67 = Methodref          #64.#66       // scala/runtime/Statics.ioobe:(I)Ljava/lang/Object;
   #68 = Utf8               I
   #69 = Utf8               java/lang/Object
   #70 = Class              #69           // java/lang/Object
   #71 = Utf8               productIterator
   #72 = Utf8               ()Lscala/collection/Iterator;
   #73 = Utf8               ()Lscala/collection/Iterator<Ljava/lang/Object;>;
   #74 = Utf8               scala/runtime/ScalaRunTime$
   #75 = Class              #74           // scala/runtime/ScalaRunTime$
   #76 = Utf8               Lscala/runtime/ScalaRunTime$;
   #77 = NameAndType        #18:#76       // MODULE$:Lscala/runtime/ScalaRunTime$;
   #78 = Fieldref           #75.#77       // scala/runtime/ScalaRunTime$.MODULE$:Lscala/runtime/ScalaRunTime$;
   #79 = Utf8               typedProductIterator
   #80 = Utf8               (Lscala/Product;)Lscala/collection/Iterator;
   #81 = NameAndType        #79:#80       // typedProductIterator:(Lscala/Product;)Lscala/collection/Iterator;
   #82 = Methodref          #75.#81       // scala/runtime/ScalaRunTime$.typedProductIterator:(Lscala/Product;)Lscala/collection/Iterator;
   #83 = Utf8               canEqual
   #84 = Utf8               (Ljava/lang/Object;)Z
   #85 = Utf8               Ljava/lang/Object;
   #86 = Utf8               productElementName
   #87 = Utf8               (I)Ljava/lang/String;
   #88 = String             #9            // configSet
   #89 = Utf8               java/lang/String
   #90 = Class              #89           // java/lang/String
   #91 = Utf8               hashCode
   #92 = Utf8               _hashCode
   #93 = Utf8               (Lscala/Product;)I
   #94 = NameAndType        #92:#93       // _hashCode:(Lscala/Product;)I
   #95 = Methodref          #75.#94       // scala/runtime/ScalaRunTime$._hashCode:(Lscala/Product;)I
   #96 = Utf8               toString
   #97 = Utf8               _toString
   #98 = Utf8               (Lscala/Product;)Ljava/lang/String;
   #99 = NameAndType        #97:#98       // _toString:(Lscala/Product;)Ljava/lang/String;
  #100 = Methodref          #75.#99       // scala/runtime/ScalaRunTime$._toString:(Lscala/Product;)Ljava/lang/String;
  #101 = Utf8               equals
  #102 = NameAndType        #101:#84      // equals:(Ljava/lang/Object;)Z
  #103 = Methodref          #70.#102      // java/lang/Object.equals:(Ljava/lang/Object;)Z
  #104 = NameAndType        #83:#84       // canEqual:(Ljava/lang/Object;)Z
  #105 = Methodref          #2.#104       // org/scalatest/tools/StandardErrReporterConfiguration.canEqual:(Ljava/lang/Object;)Z
  #106 = Utf8               scala/collection/immutable/Set
  #107 = Class              #106          // scala/collection/immutable/Set
  #108 = Utf8               (Lscala/collection/immutable/Set<Lorg/scalatest/tools/ReporterConfigParam;>;)V
  #109 = Utf8               ()V
  #110 = NameAndType        #47:#109      // "<init>":()V
  #111 = Methodref          #4.#110       // org/scalatest/tools/ReporterConfiguration."<init>":()V
  #112 = Utf8               Signature
  #113 = Utf8               Code
  #114 = Utf8               LocalVariableTable
  #115 = Utf8               MethodParameters
  #116 = Utf8               LineNumberTable
  #117 = Utf8               StackMapTable
  #118 = Utf8               SourceFile
  #119 = Utf8               RuntimeVisibleAnnotations
  #120 = Utf8               ScalaInlineInfo
  #121 = Utf8               ScalaSig
{
  private final scala.collection.immutable.Set<org.scalatest.tools.ReporterConfigParam> configSet;
    descriptor: Lscala/collection/immutable/Set;
    flags: (0x0012) ACC_PRIVATE, ACC_FINAL
    Signature: #11                          // Lscala/collection/immutable/Set<Lorg/scalatest/tools/ReporterConfigParam;>;

  public static scala.Option<scala.collection.immutable.Set<org.scalatest.tools.ReporterConfigParam>> unapply(org.scalatest.tools.StandardErrReporterConfiguration);
    descriptor: (Lorg/scalatest/tools/StandardErrReporterConfiguration;)Lscala/Option;
    flags: (0x0009) ACC_PUBLIC, ACC_STATIC
    Code:
      stack=2, locals=1, args_size=1
         0: getstatic     #21                 // Field org/scalatest/tools/StandardErrReporterConfiguration$.MODULE$:Lorg/scalatest/tools/StandardErrReporterConfiguration$;
         3: aload_0
         4: invokevirtual #23                 // Method org/scalatest/tools/StandardErrReporterConfiguration$.unapply:(Lorg/scalatest/tools/StandardErrReporterConfiguration;)Lscala/Option;
         7: areturn
      LocalVariableTable:
        Start  Length  Slot  Name   Signature
            0       8     0   x$0   Lorg/scalatest/tools/StandardErrReporterConfiguration;
    Signature: #14                          // (Lorg/scalatest/tools/StandardErrReporterConfiguration;)Lscala/Option<Lscala/collection/immutable/Set<Lorg/scalatest/tools/ReporterConfigParam;>;>;
    MethodParameters:
      Name                           Flags
      x$0                            final

  public static org.scalatest.tools.StandardErrReporterConfiguration apply(scala.collection.immutable.Set<org.scalatest.tools.ReporterConfigParam>);
    descriptor: (Lscala/collection/immutable/Set;)Lorg/scalatest/tools/StandardErrReporterConfiguration;
    flags: (0x0009) ACC_PUBLIC, ACC_STATIC
    Code:
      stack=2, locals=1, args_size=1
         0: getstatic     #21                 // Field org/scalatest/tools/StandardErrReporterConfiguration$.MODULE$:Lorg/scalatest/tools/StandardErrReporterConfiguration$;
         3: aload_0
         4: invokevirtual #29                 // Method org/scalatest/tools/StandardErrReporterConfiguration$.apply:(Lscala/collection/immutable/Set;)Lorg/scalatest/tools/StandardErrReporterConfiguration;
         7: areturn
      LocalVariableTable:
        Start  Length  Slot  Name   Signature
            0       8     0 configSet   Lscala/collection/immutable/Set;
    Signature: #27                          // (Lscala/collection/immutable/Set<Lorg/scalatest/tools/ReporterConfigParam;>;)Lorg/scalatest/tools/StandardErrReporterConfiguration;
    MethodParameters:
      Name                           Flags
      configSet                      final

  public static <A extends java.lang.Object> scala.Function1<scala.collection.immutable.Set<org.scalatest.tools.ReporterConfigParam>, A> andThen(scala.Function1<org.scalatest.tools.StandardErrReporterConfiguration, A>);
    descriptor: (Lscala/Function1;)Lscala/Function1;
    flags: (0x0009) ACC_PUBLIC, ACC_STATIC
    Code:
      stack=2, locals=1, args_size=1
         0: getstatic     #21                 // Field org/scalatest/tools/StandardErrReporterConfiguration$.MODULE$:Lorg/scalatest/tools/StandardErrReporterConfiguration$;
         3: aload_0
         4: invokevirtual #35                 // Method org/scalatest/tools/StandardErrReporterConfiguration$.andThen:(Lscala/Function1;)Lscala/Function1;
         7: areturn
      LocalVariableTable:
        Start  Length  Slot  Name   Signature
            0       8     0     g   Lscala/Function1;
    Signature: #32                          // <A:Ljava/lang/Object;>(Lscala/Function1<Lorg/scalatest/tools/StandardErrReporterConfiguration;TA;>;)Lscala/Function1<Lscala/collection/immutable/Set<Lorg/scalatest/tools/ReporterConfigParam;>;TA;>;
    MethodParameters:
      Name                           Flags
      g                              final

  public static <A$ extends java.lang.Object> scala.Function1<A$, org.scalatest.tools.StandardErrReporterConfiguration> compose(scala.Function1<A$, scala.collection.immutable.Set<org.scalatest.tools.ReporterConfigParam>>);
    descriptor: (Lscala/Function1;)Lscala/Function1;
    flags: (0x0009) ACC_PUBLIC, ACC_STATIC
    Code:
      stack=2, locals=1, args_size=1
         0: getstatic     #21                 // Field org/scalatest/tools/StandardErrReporterConfiguration$.MODULE$:Lorg/scalatest/tools/StandardErrReporterConfiguration$;
         3: aload_0
         4: invokevirtual #40                 // Method org/scalatest/tools/StandardErrReporterConfiguration$.compose:(Lscala/Function1;)Lscala/Function1;
         7: areturn
      LocalVariableTable:
        Start  Length  Slot  Name   Signature
            0       8     0     g   Lscala/Function1;
    Signature: #38                          // <A$:Ljava/lang/Object;>(Lscala/Function1<TA$;Lscala/collection/immutable/Set<Lorg/scalatest/tools/ReporterConfigParam;>;>;)Lscala/Function1<TA$;Lorg/scalatest/tools/StandardErrReporterConfiguration;>;
    MethodParameters:
      Name                           Flags
      g                              final

  public scala.collection.immutable.Set<org.scalatest.tools.ReporterConfigParam> configSet();
    descriptor: ()Lscala/collection/immutable/Set;
    flags: (0x0001) ACC_PUBLIC
    Code:
      stack=1, locals=1, args_size=1
         0: aload_0
         1: getfield      #44                 // Field configSet:Lscala/collection/immutable/Set;
         4: areturn
      LineNumberTable:
        line 29: 0
      LocalVariableTable:
        Start  Length  Slot  Name   Signature
            0       5     0  this   Lorg/scalatest/tools/StandardErrReporterConfiguration;
    Signature: #42                          // ()Lscala/collection/immutable/Set<Lorg/scalatest/tools/ReporterConfigParam;>;

  public org.scalatest.tools.StandardErrReporterConfiguration copy(scala.collection.immutable.Set<org.scalatest.tools.ReporterConfigParam>);
    descriptor: (Lscala/collection/immutable/Set;)Lorg/scalatest/tools/StandardErrReporterConfiguration;
    flags: (0x0001) ACC_PUBLIC
    Code:
      stack=3, locals=2, args_size=2
         0: new           #2                  // class org/scalatest/tools/StandardErrReporterConfiguration
         3: dup
         4: aload_1
         5: invokespecial #50                 // Method "<init>":(Lscala/collection/immutable/Set;)V
         8: areturn
      LineNumberTable:
        line 29: 0
      LocalVariableTable:
        Start  Length  Slot  Name   Signature
            0       9     0  this   Lorg/scalatest/tools/StandardErrReporterConfiguration;
            0       9     1 configSet   Lscala/collection/immutable/Set;
    Signature: #27                          // (Lscala/collection/immutable/Set<Lorg/scalatest/tools/ReporterConfigParam;>;)Lorg/scalatest/tools/StandardErrReporterConfiguration;
    MethodParameters:
      Name                           Flags
      configSet                      final

  public scala.collection.immutable.Set<org.scalatest.tools.ReporterConfigParam> copy$default$1();
    descriptor: ()Lscala/collection/immutable/Set;
    flags: (0x0001) ACC_PUBLIC
    Code:
      stack=1, locals=1, args_size=1
         0: aload_0
         1: invokevirtual #53                 // Method configSet:()Lscala/collection/immutable/Set;
         4: areturn
      LineNumberTable:
        line 29: 0
      LocalVariableTable:
        Start  Length  Slot  Name   Signature
            0       5     0  this   Lorg/scalatest/tools/StandardErrReporterConfiguration;
    Signature: #42                          // ()Lscala/collection/immutable/Set<Lorg/scalatest/tools/ReporterConfigParam;>;

  public java.lang.String productPrefix();
    descriptor: ()Ljava/lang/String;
    flags: (0x0001) ACC_PUBLIC
    Code:
      stack=1, locals=1, args_size=1
         0: ldc           #57                 // String StandardErrReporterConfiguration
         2: areturn
      LineNumberTable:
        line 29: 0
      LocalVariableTable:
        Start  Length  Slot  Name   Signature
            0       3     0  this   Lorg/scalatest/tools/StandardErrReporterConfiguration;

  public int productArity();
    descriptor: ()I
    flags: (0x0001) ACC_PUBLIC
    Code:
      stack=1, locals=1, args_size=1
         0: iconst_1
         1: ireturn
      LineNumberTable:
        line 29: 0
      LocalVariableTable:
        Start  Length  Slot  Name   Signature
            0       2     0  this   Lorg/scalatest/tools/StandardErrReporterConfiguration;

  public java.lang.Object productElement(int);
    descriptor: (I)Ljava/lang/Object;
    flags: (0x0001) ACC_PUBLIC
    Code:
      stack=1, locals=3, args_size=2
         0: iload_1
         1: istore_2
         2: iload_2
         3: tableswitch   { // 0 to 0
                       0: 20
                 default: 27
            }
        20: aload_0
        21: invokevirtual #53                 // Method configSet:()Lscala/collection/immutable/Set;
        24: goto          34
        27: iload_1
        28: invokestatic  #67                 // Method scala/runtime/Statics.ioobe:(I)Ljava/lang/Object;
        31: goto          34
        34: areturn
      StackMapTable: number_of_entries = 3
        frame_type = 252 /* append */
          offset_delta = 20
          locals = [ int ]
        frame_type = 6 /* same */
        frame_type = 70 /* same_locals_1_stack_item */
          stack = [ class java/lang/Object ]
      LineNumberTable:
        line 29: 0
      LocalVariableTable:
        Start  Length  Slot  Name   Signature
            0      35     0  this   Lorg/scalatest/tools/StandardErrReporterConfiguration;
            0      35     1   x$1   I
    MethodParameters:
      Name                           Flags
      x$1                            final

  public scala.collection.Iterator<java.lang.Object> productIterator();
    descriptor: ()Lscala/collection/Iterator;
    flags: (0x0001) ACC_PUBLIC
    Code:
      stack=2, locals=1, args_size=1
         0: getstatic     #78                 // Field scala/runtime/ScalaRunTime$.MODULE$:Lscala/runtime/ScalaRunTime$;
         3: aload_0
         4: invokevirtual #82                 // Method scala/runtime/ScalaRunTime$.typedProductIterator:(Lscala/Product;)Lscala/collection/Iterator;
         7: areturn
      LineNumberTable:
        line 29: 0
      LocalVariableTable:
        Start  Length  Slot  Name   Signature
            0       8     0  this   Lorg/scalatest/tools/StandardErrReporterConfiguration;
    Signature: #73                          // ()Lscala/collection/Iterator<Ljava/lang/Object;>;

  public boolean canEqual(java.lang.Object);
    descriptor: (Ljava/lang/Object;)Z
    flags: (0x0001) ACC_PUBLIC
    Code:
      stack=1, locals=2, args_size=2
         0: aload_1
         1: instanceof    #2                  // class org/scalatest/tools/StandardErrReporterConfiguration
         4: ireturn
      LineNumberTable:
        line 29: 0
      LocalVariableTable:
        Start  Length  Slot  Name   Signature
            0       5     0  this   Lorg/scalatest/tools/StandardErrReporterConfiguration;
            0       5     1   x$1   Ljava/lang/Object;
    MethodParameters:
      Name                           Flags
      x$1                            final

  public java.lang.String productElementName(int);
    descriptor: (I)Ljava/lang/String;
    flags: (0x0001) ACC_PUBLIC
    Code:
      stack=1, locals=3, args_size=2
         0: iload_1
         1: istore_2
         2: iload_2
         3: tableswitch   { // 0 to 0
                       0: 20
                 default: 25
            }
        20: ldc           #88                 // String configSet
        22: goto          35
        25: iload_1
        26: invokestatic  #67                 // Method scala/runtime/Statics.ioobe:(I)Ljava/lang/Object;
        29: checkcast     #90                 // class java/lang/String
        32: goto          35
        35: areturn
      StackMapTable: number_of_entries = 3
        frame_type = 252 /* append */
          offset_delta = 20
          locals = [ int ]
        frame_type = 4 /* same */
        frame_type = 73 /* same_locals_1_stack_item */
          stack = [ class java/lang/String ]
      LineNumberTable:
        line 29: 0
      LocalVariableTable:
        Start  Length  Slot  Name   Signature
            0      36     0  this   Lorg/scalatest/tools/StandardErrReporterConfiguration;
            0      36     1   x$1   I
    MethodParameters:
      Name                           Flags
      x$1                            final

  public int hashCode();
    descriptor: ()I
    flags: (0x0001) ACC_PUBLIC
    Code:
      stack=2, locals=1, args_size=1
         0: getstatic     #78                 // Field scala/runtime/ScalaRunTime$.MODULE$:Lscala/runtime/ScalaRunTime$;
         3: aload_0
         4: invokevirtual #95                 // Method scala/runtime/ScalaRunTime$._hashCode:(Lscala/Product;)I
         7: ireturn
      LineNumberTable:
        line 29: 0
      LocalVariableTable:
        Start  Length  Slot  Name   Signature
            0       8     0  this   Lorg/scalatest/tools/StandardErrReporterConfiguration;

  public java.lang.String toString();
    descriptor: ()Ljava/lang/String;
    flags: (0x0001) ACC_PUBLIC
    Code:
      stack=2, locals=1, args_size=1
         0: getstatic     #78                 // Field scala/runtime/ScalaRunTime$.MODULE$:Lscala/runtime/ScalaRunTime$;
         3: aload_0
         4: invokevirtual #100                // Method scala/runtime/ScalaRunTime$._toString:(Lscala/Product;)Ljava/lang/String;
         7: areturn
      LineNumberTable:
        line 29: 0
      LocalVariableTable:
        Start  Length  Slot  Name   Signature
            0       8     0  this   Lorg/scalatest/tools/StandardErrReporterConfiguration;

  public boolean equals(java.lang.Object);
    descriptor: (Ljava/lang/Object;)Z
    flags: (0x0001) ACC_PUBLIC
    Code:
      stack=2, locals=6, args_size=2
         0: aload_0
         1: aload_1
         2: if_acmpeq     86
         5: aload_1
         6: astore_3
         7: aload_3
         8: instanceof    #2                  // class org/scalatest/tools/StandardErrReporterConfiguration
        11: ifeq          19
        14: iconst_1
        15: istore_2
        16: goto          27
        19: goto          22
        22: iconst_0
        23: istore_2
        24: goto          27
        27: iload_2
        28: ifeq          90
        31: aload_1
        32: checkcast     #2                  // class org/scalatest/tools/StandardErrReporterConfiguration
        35: astore        4
        37: aload_0
        38: invokevirtual #53                 // Method configSet:()Lscala/collection/immutable/Set;
        41: aload         4
        43: invokevirtual #53                 // Method configSet:()Lscala/collection/immutable/Set;
        46: astore        5
        48: dup
        49: ifnonnull     61
        52: pop
        53: aload         5
        55: ifnull        69
        58: goto          82
        61: aload         5
        63: invokevirtual #103                // Method java/lang/Object.equals:(Ljava/lang/Object;)Z
        66: ifeq          82
        69: aload         4
        71: aload_0
        72: invokevirtual #105                // Method canEqual:(Ljava/lang/Object;)Z
        75: ifeq          82
        78: iconst_1
        79: goto          83
        82: iconst_0
        83: ifeq          90
        86: iconst_1
        87: goto          91
        90: iconst_0
        91: ireturn
      StackMapTable: number_of_entries = 10
        frame_type = 253 /* append */
          offset_delta = 19
          locals = [ top, class java/lang/Object ]
        frame_type = 2 /* same */
        frame_type = 255 /* full_frame */
          offset_delta = 4
          locals = [ class org/scalatest/tools/StandardErrReporterConfiguration, class java/lang/Object, int, class java/lang/Object ]
          stack = []
        frame_type = 255 /* full_frame */
          offset_delta = 33
          locals = [ class org/scalatest/tools/StandardErrReporterConfiguration, class java/lang/Object, int, class java/lang/Object, class org/scalatest/tools/StandardErrReporterConfiguration, class scala/collection/immutable/Set ]
          stack = [ class scala/collection/immutable/Set ]
        frame_type = 7 /* same */
        frame_type = 12 /* same */
        frame_type = 64 /* same_locals_1_stack_item */
          stack = [ int ]
        frame_type = 255 /* full_frame */
          offset_delta = 2
          locals = [ class org/scalatest/tools/StandardErrReporterConfiguration, class java/lang/Object ]
          stack = []
        frame_type = 253 /* append */
          offset_delta = 3
          locals = [ int, class java/lang/Object ]
        frame_type = 255 /* full_frame */
          offset_delta = 0
          locals = [ class org/scalatest/tools/StandardErrReporterConfiguration, class java/lang/Object ]
          stack = [ int ]
      LineNumberTable:
        line 29: 0
      LocalVariableTable:
        Start  Length  Slot  Name   Signature
            0      92     0  this   Lorg/scalatest/tools/StandardErrReporterConfiguration;
            0      92     1   x$1   Ljava/lang/Object;
    MethodParameters:
      Name                           Flags
      x$1                            final

  public org.scalatest.tools.StandardErrReporterConfiguration(scala.collection.immutable.Set<org.scalatest.tools.ReporterConfigParam>);
    descriptor: (Lscala/collection/immutable/Set;)V
    flags: (0x0001) ACC_PUBLIC
    Code:
      stack=2, locals=2, args_size=2
         0: aload_0
         1: aload_1
         2: putfield      #44                 // Field configSet:Lscala/collection/immutable/Set;
         5: aload_0
         6: invokespecial #111                // Method org/scalatest/tools/ReporterConfiguration."<init>":()V
         9: return
      LineNumberTable:
        line 29: 0
      LocalVariableTable:
        Start  Length  Slot  Name   Signature
            0      10     0  this   Lorg/scalatest/tools/StandardErrReporterConfiguration;
            0      10     1 configSet   Lscala/collection/immutable/Set;
    Signature: #108                         // (Lscala/collection/immutable/Set<Lorg/scalatest/tools/ReporterConfigParam;>;)V
    MethodParameters:
      Name                           Flags
      configSet                      final
}
SourceFile: "ReporterConfiguration.scala"
RuntimeVisibleAnnotations:
  0: #6(#7=s#8)
    scala.reflect.ScalaSignature(
      bytes="\u0006\u0005\u0005\u0015c!\u0002\f\u0018\u0001^i\u0002\u0002C\u001b\u0001\u0005+\u0007I\u0011\u0001\u001c\t\u0011\t\u0003!\u0011#Q\u0001\n]BQa\u0011\u0001\u0005\u0002\u0011Cqa\u0012\u0001\u0002\u0002\u0013\u0005\u0001\nC\u0004K\u0001E\u0005I\u0011A&\t\u000fY\u0003\u0011\u0011!C!/\"9\u0001\rAA\u0001\n\u0003\t\u0007bB3\u0001\u0003\u0003%\tA\u001a\u0005\bY\u0002\t\t\u0011\"\u0011n\u0011\u001d!\b!!A\u0005\u0002UDqA\u001f\u0001\u0002\u0002\u0013\u00053\u0010C\u0004~\u0001\u0005\u0005I\u0011\t@\t\u0011}\u0004\u0011\u0011!C!\u0003\u0003A\u0011\"a\u0001\u0001\u0003\u0003%\t%!\u0002\b\u0015\u0005%q#!A\t\u0002]\tYAB\u0005\u0017/\u0005\u0005\t\u0012A\f\u0002\u000e!11\t\u0005C\u0001\u0003KA\u0001b \t\u0002\u0002\u0013\u0015\u0013\u0011\u0001\u0005\n\u0003O\u0001\u0012\u0011!CA\u0003SA\u0011\"!\f\u0011\u0003\u0003%\t)a\f\t\u0013\u0005m\u0002#!A\u0005\n\u0005u\"\u0001I*uC:$\u0017M\u001d3FeJ\u0014V\r]8si\u0016\u00148i\u001c8gS\u001e,(/\u0019;j_:T!\u0001G\r\u0002\u000bQ|w\u000e\\:\u000b\u0005iY\u0012!C:dC2\fG/Z:u\u0015\u0005a\u0012aA8sON!\u0001A\b\u0012)!\ty\u0002%D\u0001\u0018\u0013\t\tsCA\u000bSKB|\'\u000f^3s\u0007>tg-[4ve\u0006$\u0018n\u001c8\u0011\u0005\r2S\"\u0001\u0013\u000b\u0003\u0015\nQa]2bY\u0006L!a\n\u0013\u0003\u000fA\u0013x\u000eZ;diB\u0011\u0011F\r\b\u0003UAr!aK\u0018\u000e\u00031R!!\f\u0018\u0002\rq\u0012xn\u001c;?\u0007\u0001I\u0011!J\u0005\u0003c\u0011\nq\u0001]1dW\u0006<W-\u0003\u00024i\ta1+\u001a:jC2L\'0\u00192mK*\u0011\u0011\u0007J\u0001\nG>tg-[4TKR,\u0012a\u000e\t\u0004qqzdBA\u001d;!\tYC%\u0003\u0002<I\u00051\u0001K]3eK\u001aL!!\u0010 \u0003\u0007M+GO\u0003\u0002<IA\u0011q\u0004Q\u0005\u0003\u0003^\u00111CU3q_J$XM]\"p]\u001aLw\rU1sC6\f!bY8oM&<7+\u001a;!\u0003\u0019a\u0014N\\5u}Q\u0011QI\u0012\t\u0003?\u0001AQ!N\u0002A\u0002]\nAaY8qsR\u0011Q)\u0013\u0005\bk\u0011\u0001\n\u00111\u00018\u00039\u0019w\u000e]=%I\u00164\u0017-\u001e7uIE*\u0012\u0001\u0014\u0016\u0003o5[\u0013A\u0014\t\u0003\u001fRk\u0011\u0001\u0015\u0006\u0003#J\u000b\u0011\"\u001e8dQ\u0016\u001c7.\u001a3\u000b\u0005M#\u0013AC1o]>$\u0018\r^5p]&\u0011Q\u000b\u0015\u0002\u0012k:\u001c\u0007.Z2lK\u00124\u0016M]5b]\u000e,\u0017!\u00049s_\u0012,8\r\u001e)sK\u001aL\u00070F\u0001Y!\tIf,D\u0001[\u0015\tYF,\u0001\u0003mC:<\'\"A/\u0002\t)\fg/Y\u0005\u0003?j\u0013aa\u0015;sS:<\u0017\u0001\u00049s_\u0012,8\r^!sSRLX#\u00012\u0011\u0005\r\u001a\u0017B\u00013%\u0005\rIe\u000e^\u0001\u000faJ|G-^2u\u000b2,W.\u001a8u)\t9\'\u000e\u0005\u0002$Q&\u0011\u0011\u000e\n\u0002\u0004\u0003:L\bbB6\t\u0003\u0003\u0005\rAY\u0001\u0004q\u0012\n\u0014a\u00049s_\u0012,8\r^%uKJ\fGo\u001c:\u0016\u00039\u00042a\u001c:h\u001b\u0005\u0001(BA9%\u0003)\u0019w\u000e\u001c7fGRLwN\\\u0005\u0003gB\u0014\u0001\"\u0013;fe\u0006$xN]\u0001\tG\u0006tW)];bYR\u0011a/\u001f\t\u0003G]L!\u0001\u001f\u0013\u0003\u000f\t{w\u000e\\3b]\"91NCA\u0001\u0002\u00049\u0017A\u00059s_\u0012,8\r^#mK6,g\u000e\u001e(b[\u0016$\"\u0001\u0017?\t\u000f-\\\u0011\u0011!a\u0001E\u0006A\u0001.Y:i\u0007>$W\rF\u0001c\u0003!!xn\u0015;sS:<G#\u0001-\u0002\r\u0015\fX/\u00197t)\r1\u0018q\u0001\u0005\bW:\t\t\u00111\u0001h\u0003\u0001\u001aF/\u00198eCJ$WI\u001d:SKB|\'\u000f^3s\u0007>tg-[4ve\u0006$\u0018n\u001c8\u0011\u0005}\u00012#\u0002\t\u0002\u0010\u0005m\u0001CBA\t\u0003/9T)\u0004\u0002\u0002\u0014)\u0019\u0011Q\u0003\u0013\u0002\u000fI,h\u000e^5nK&!\u0011\u0011DA\n\u0005E\t%m\u001d;sC\u000e$h)\u001e8di&|g.\r\t\u0005\u0003;\t\u0019#\u0004\u0002\u0002 )\u0019\u0011\u0011\u0005/\u0002\u0005%|\u0017bA\u001a\u0002 Q\u0011\u00111B\u0001\u0006CB\u0004H.\u001f\u000b\u0004\u000b\u0006-\u0002\"B\u001b\u0014\u0001\u00049\u0014aB;oCB\u0004H.\u001f\u000b\u0005\u0003c\t9\u0004\u0005\u0003$\u0003g9\u0014bAA\u001bI\t1q\n\u001d;j_:D\u0001\"!\u000f\u0015\u0003\u0003\u0005\r!R\u0001\u0004q\u0012\u0002\u0014\u0001D<sSR,\'+\u001a9mC\u000e,GCAA !\rI\u0016\u0011I\u0005\u0004\u0003\u0007R&AB(cU\u0016\u001cG\u000f"
    )
  ScalaInlineInfo: length = 0x45 (unknown attribute)
   01 00 00 0D 00 2F 00 30 00 00 53 00 54 00 00 09
   00 29 00 00 2E 00 1A 00 00 33 00 29 00 00 65 00
   54 00 00 5B 00 3B 00 00 3A 00 3B 00 00 3C 00 3D
   00 00 56 00 57 00 00 47 00 48 00 00 36 00 37 00
   00 60 00 37 00
  ScalaSig: length = 0x3 (unknown attribute)
   05 02 00
