Classfile /Users/mw/Projects/slang-braindump/.jar/jar8/assemble/slang-braindump/assemble/content/org/scalatest/tools/StringReporter.class
  Last modified May 29, 2022; size 17914 bytes
  SHA-256 checksum c42ecfc3f8ce5e4731617c42874f256bbc204479d7784a25791cc3019394ed50
  Compiled from "StringReporter.scala"
public abstract class org.scalatest.tools.StringReporter implements org.scalatest.ResourcefulReporter
  minor version: 0
  major version: 52
  flags: (0x0421) ACC_PUBLIC, ACC_SUPER, ACC_ABSTRACT
  this_class: #2                          // org/scalatest/tools/StringReporter
  super_class: #4                         // java/lang/Object
  interfaces: 1, fields: 11, methods: 32, attributes: 6
Constant pool:
    #1 = Utf8               org/scalatest/tools/StringReporter
    #2 = Class              #1            // org/scalatest/tools/StringReporter
    #3 = Utf8               java/lang/Object
    #4 = Class              #3            // java/lang/Object
    #5 = Utf8               org/scalatest/ResourcefulReporter
    #6 = Class              #5            // org/scalatest/ResourcefulReporter
    #7 = Utf8               StringReporter.scala
    #8 = Utf8               Lscala/reflect/ScalaSignature;
    #9 = Utf8               bytes
   #10 = Utf8               \u0006\u0005\recAB\u001a5\u0003\u00031$\b\u0003\u0005F\u0001\t\u0005\t\u0015!\u0003H\u0011!Q\u0005A!A!\u0002\u00139\u0005\u0002C&\u0001\u0005\u0003\u0005\u000b\u0011B$\t\u00111\u0003!\u0011!Q\u0001\n\u001dC\u0001\"\u0014\u0001\u0003\u0002\u0003\u0006Ia\u0012\u0005\t\u001d\u0002\u0011\t\u0011)A\u0005\u000f\"Aq\n\u0001B\u0001B\u0003%q\t\u0003\u0005Q\u0001\t\u0005\t\u0015!\u0003H\u0011!\t\u0006A!A!\u0002\u00139\u0005\u0002\u0003*\u0001\u0005\u0003\u0005\u000b\u0011B$\t\u0011M\u0003!\u0011!Q\u0001\n\u001dCQ\u0001\u0016\u0001\u0005\u0002UCqa\u0019\u0001C\u0002\u0013\u0005A\r\u0003\u0004t\u0001\u0001\u0006I!\u001a\u0005\u0006i\u00021\t\"\u001e\u0005\u0006}\u00021\tb \u0005\b\u00037\u0001A\u0011AA\u000f\u000f!\tI\u0003\u000eE\u0001m\u0005-baB\u001a5\u0011\u00031\u0014Q\u0006\u0005\u0007)N!\t!a\f\t\u0013\u0005E2C1A\u0005\u0002\u0005M\u0002\u0002CA\u001e\'\u0001\u0006I!!\u000e\t\u000f\u0005u2\u0003\"\u0001\u0002@!I\u00111T\n\u0012\u0002\u0013\u0005\u0011Q\u0014\u0005\n\u0003g\u001b\u0012\u0013!C\u0001\u0003kCq!!/\u0014\t\u0003\tY\fC\u0004\u0002xN!\t!!?\t\u000f\t}1\u0003\"\u0001\u0003\"!9!\u0011G\n\u0005\u0002\tM\u0002b\u0002B\u001f\'\u0011\u0005!q\b\u0005\b\u00053\u001aB\u0011\u0001B.\u0011\u001d\u0011\th\u0005C\u0001\u0005gBqAa\"\u0014\t\u0003\u0011I\tC\u0004\u0003\u001eN!\tAa(\t\u000f\t56\u0003\"\u0001\u00030\"9!QX\n\u0005\u0002\t}\u0006\"\u0003Bi\'E\u0005I\u0011AA[\u0011\u001d\u0011\u0019n\u0005C\u0001\u0005+DqAa>\u0014\t\u0003\u0011I\u0010C\u0005\u0004\u0018M\u0011\r\u0011\"\u0002\u0004\u001a!A1\u0011E\n!\u0002\u001b\u0019Y\u0002C\u0005\u0004$M\u0011\r\u0011\"\u0002\u0004&!A1QF\n!\u0002\u001b\u00199\u0003C\u0005\u00040M\u0011\r\u0011\"\u0002\u00042!A1\u0011H\n!\u0002\u001b\u0019\u0019\u0004C\u0005\u0004<M\u0011\r\u0011\"\u0002\u0004>!A1QI\n!\u0002\u001b\u0019y\u0004C\u0005\u0004HM\u0011\r\u0011\"\u0002\u0004J!A1\u0011K\n!\u0002\u001b\u0019Y\u0005C\u0004\u0004TM!\ta!\u0016\u0003\u001dM#(/\u001b8h%\u0016\u0004xN\u001d;fe*\u0011QGN\u0001\u0006i>|Gn\u001d\u0006\u0003oa\n\u0011b]2bY\u0006$Xm\u001d;\u000b\u0003e\n1a\u001c:h\'\r\u00011(\u0011\t\u0003y}j\u0011!\u0010\u0006\u0002}\u0005)1oY1mC&\u0011\u0001)\u0010\u0002\u0007\u0003:L(+\u001a4\u0011\u0005\t\u001bU\"\u0001\u001c\n\u0005\u00113$a\u0005*fg>,(oY3gk2\u0014V\r]8si\u0016\u0014\u0018a\u00059sKN,g\u000e^!mY\u0012+(/\u0019;j_:\u001c8\u0001\u0001\t\u0003y!K!!S\u001f\u0003\u000f\t{w\u000e\\3b]\u0006q\u0001O]3tK:$\u0018J\\\"pY>\u0014\u0018a\u00069sKN,g\u000e^*i_J$8\u000b^1dWR\u0013\u0018mY3t\u0003Y\u0001(/Z:f]R4U\u000f\u001c7Ti\u0006\u001c7\u000e\u0016:bG\u0016\u001c\u0018A\u00059sKN,g\u000e^+oM>\u0014X.\u0019;uK\u0012\fq\u0002\u001d:fg\u0016tGOU3nS:$WM]\u0001$aJ,7/\u001a8u%\u0016l\u0017N\u001c3fe^KG\u000f[*i_J$8\u000b^1dWR\u0013\u0018mY3t\u0003\t\u0002(/Z:f]R\u0014V-\\5oI\u0016\u0014x+\u001b;i\rVdGn\u0015;bG.$&/Y2fg\u0006\u0019\u0003O]3tK:$(+Z7j]\u0012,\'oV5uQ>,HoQ1oG\u0016dW\r\u001a+fgR\u001c\u0018a\u00059sKN,g\u000e\u001e$jY\u0016\u0004\u0016\r\u001e5oC6,\u0017a\u00039sKN,g\u000e\u001e&t_:\fa\u0001P5oSRtD\u0003\u0004,Y3j[F,\u00180`A\u0006\u0014\u0007CA,\u0001\u001b\u0005!\u0004\"B#\r\u0001\u00049\u0005\"\u0002&\r\u0001\u00049\u0005\"B&\r\u0001\u00049\u0005\"\u0002\'\r\u0001\u00049\u0005\"B\'\r\u0001\u00049\u0005\"\u0002(\r\u0001\u00049\u0005\"B(\r\u0001\u00049\u0005\"\u0002)\r\u0001\u00049\u0005\"B)\r\u0001\u00049\u0005\"\u0002*\r\u0001\u00049\u0005\"B*\r\u0001\u00049\u0015!\u0005:f[&tG-\u001a:Fm\u0016tGo\u001d\"vMV\tQ\rE\u0002gW6l\u0011a\u001a\u0006\u0003Q&\fq!\\;uC\ndWM\u0003\u0002k{\u0005Q1m\u001c7mK\u000e$\u0018n\u001c8\n\u00051<\'A\u0003\'jgR\u0014UO\u001a4feB\u0011a.]\u0007\u0002_*\u0011\u0001ON\u0001\u0007KZ,g\u000e^:\n\u0005I|\'\u0001E#yG\u0016\u0004H/[8oC2,e/\u001a8u\u0003I\u0011X-\\5oI\u0016\u0014XI^3oiN\u0014UO\u001a\u0011\u0002)A\u0014\u0018N\u001c;Q_N\u001c\u0018N\u00197z\u0013:\u001cu\u000e\\8s)\t1\u0018\u0010\u0005\u0002=o&\u0011\u00010\u0010\u0002\u0005+:LG\u000fC\u0003{\u001f\u0001\u000710\u0001\u0005ge\u0006<W.\u001a8u!\t9F0\u0003\u0002~i\tAaI]1h[\u0016tG/\u0001\u0007qe&tGOT8D_2|\'\u000fF\u0002w\u0003\u0003Aq!a\u0001\u0011\u0001\u0004\t)!\u0001\u0003uKb$\b\u0003BA\u0004\u0003+qA!!\u0003\u0002\u0012A\u0019\u00111B\u001f\u000e\u0005\u00055!bAA\b\r\u00061AH]8pizJ1!a\u0005>\u0003\u0019\u0001&/\u001a3fM&!\u0011qCA\r\u0005\u0019\u0019FO]5oO*\u0019\u00111C\u001f\u0002\u000b\u0005\u0004\b\u000f\\=\u0015\u0007Y\fy\u0002C\u0004\u0002\"E\u0001\r!a\t\u0002\u000b\u00154XM\u001c;\u0011\u00079\f)#C\u0002\u0002(=\u0014Q!\u0012<f]R\fab\u0015;sS:<\'+\u001a9peR,\'\u000f\u0005\u0002X\'M\u00111c\u000f\u000b\u0003\u0003W\t1c\u001d5peR\u001cF/Y2l)J\f7-Z*ju\u0016,\"!!\u000e\u0011\u0007q\n9$C\u0002\u0002:u\u00121!\u00138u\u0003Q\u0019\bn\u001c:u\'R\f7m\u001b+sC\u000e,7+\u001b>fA\u0005!bM]1h[\u0016tGo],iK:tu.\u0012:s_J$B#!\u0011\u0002T\u0005\r\u00141OA<\u0003{\n\t)a!\u0002\u0006\u0006=\u0005#BA\"\u0003\u001bZh\u0002BA#\u0003\u0013rA!a\u0003\u0002H%\ta(C\u0002\u0002Lu\nq\u0001]1dW\u0006<W-\u0003\u0003\u0002P\u0005E#A\u0002,fGR|\'OC\u0002\u0002LuBq!!\u0016\u0018\u0001\u0004\t9&\u0001\u0006nKN\u001c\u0018mZ3Gk:\u0004r\u0001PA-\u0003;\n)!C\u0002\u0002\\u\u0012\u0011BR;oGRLwN\\\u0019\u0011\u0007q\ny&C\u0002\u0002bu\u00121!\u00118z\u0011\u001d\t)g\u0006a\u0001\u0003O\n\u0011BZ8s[\u0006$H/\u001a:\u0011\u000bq\nI\'!\u001c\n\u0007\u0005-TH\u0001\u0004PaRLwN\u001c\t\u0004]\u0006=\u0014bAA9_\nIai\u001c:nCR$XM\u001d\u0005\b\u0003k:\u0002\u0019AA\u0003\u0003%\u0019X/\u001b;f\u001d\u0006lW\rC\u0004\u0002z]\u0001\r!a\u001f\u0002\u0011Q,7\u000f\u001e(b[\u0016\u0004R\u0001PA5\u0003\u000bAq!a \u0018\u0001\u0004\tY(A\u0004nKN\u001c\u0018mZ3\t\u000b5;\u0002\u0019A$\t\u000b\u0015;\u0002\u0019A$\t\u0013\u0005\u001du\u0003%AA\u0002\u0005%\u0015!C1og&\u001cu\u000e\\8s!\r9\u00161R\u0005\u0004\u0003\u001b#$!C!og&\u001cu\u000e\\8s\u0011%\t\tj\u0006I\u0001\u0002\u0004\t\u0019*\u0001\u0005ekJ\fG/[8o!\u0015a\u0014\u0011NAK!\ra\u0014qS\u0005\u0004\u00033k$\u0001\u0002\'p]\u001e\faD\u001a:bO6,g\u000e^:XQ\u0016tgj\\#se>\u0014H\u0005Z3gCVdG\u000f\n\u001d\u0016\u0005\u0005}%\u0006BAE\u0003C[#!a)\u0011\t\u0005\u0015\u0016qV\u0007\u0003\u0003OSA!!+\u0002,\u0006IQO\\2iK\u000e\\W\r\u001a\u0006\u0004\u0003[k\u0014AC1o]>$\u0018\r^5p]&!\u0011\u0011WAT\u0005E)hn\u00195fG.,GMV1sS\u0006t7-Z\u0001\u001fMJ\fw-\\3oiN<\u0006.\u001a8O_\u0016\u0013(o\u001c:%I\u00164\u0017-\u001e7uIe*\"!a.+\t\u0005M\u0015\u0011U\u0001\u0011MJ\fw-\\3oiN|e.\u0012:s_J$\u0002%!\u0011\u0002>\u0006\u0005\u0017QYAd\u0003\'\f\u0019/!:\u0002h\u0006%\u00181^Aw\u0003_\f\t0a=\u0002v\"9\u0011q\u0018\u000eA\u0002\u0005\u0015\u0011A\u00048pi\u0016lUm]:bO\u00164UO\u001c\u0005\b\u0003\u0007T\u0002\u0019AA,\u0003=)\'O]8s\u001b\u0016\u001c8/Y4f\rVt\u0007bBA@5\u0001\u0007\u0011Q\u0001\u0005\b\u0003\u0013T\u0002\u0019AAf\u0003%!\bN]8xC\ndW\rE\u0003=\u0003S\ni\r\u0005\u0003\u0002D\u0005=\u0017\u0002BAi\u0003#\u0012\u0011\u0002\u00165s_^\f\'\r\\3\t\u000f\u0005U\'\u00041\u0001\u0002X\u0006A\u0011M\\1msNL7\u000f\u0005\u0004\u0002Z\u0006}\u0017QA\u0007\u0003\u00037T1!!8j\u0003%IW.\\;uC\ndW-\u0003\u0003\u0002b\u0006m\'AC%oI\u0016DX\rZ*fc\"9\u0011Q\r\u000eA\u0002\u0005\u001d\u0004bBA;5\u0001\u0007\u00111\u0010\u0005\b\u0003sR\u0002\u0019AA>\u0011\u001d\t\tJ\u0007a\u0001\u0003\'CQ!\u0014\u000eA\u0002\u001dCQ!\u0012\u000eA\u0002\u001dCQa\u0013\u000eA\u0002\u001dCQ\u0001\u0014\u000eA\u0002\u001dCQA\u0015\u000eA\u0002\u001dCq!a\"\u001b\u0001\u0004\tI)\u0001\ttk6l\u0017M]=Ge\u0006<W.\u001a8ugR1\u0012\u0011IA~\u0003\u007f\u0014\tA!\u0004\u0003\u0014\tU!q\u0003B\r\u00057\u0011i\u0002\u0003\u0004\u0002~n\u0001\raR\u0001\reVt7i\\7qY\u0016$X\r\u001a\u0005\b\u0003#[\u0002\u0019AAJ\u0011\u001d\u0011\u0019a\u0007a\u0001\u0005\u000b\tQb];n[\u0006\u0014\u0018p\u00149uS>t\u0007#\u0002\u001f\u0002j\t\u001d\u0001c\u00018\u0003\n%\u0019!1B8\u0003\u000fM+X.\\1ss\"9!qB\u000eA\u0002\tE\u0011!E3yG\u0016\u0004H/[8oC2,e/\u001a8ugB)\u00111IA\'[\")Qi\u0007a\u0001\u000f\")aj\u0007a\u0001\u000f\")qj\u0007a\u0001\u000f\")\u0001k\u0007a\u0001\u000f\")\u0011k\u0007a\u0001\u000f\")!k\u0007a\u0001\u000f\u0006!R\r_2faRLwN\\1m\rJ\fw-\\3oiN$b\"!\u0011\u0003$\t\u001d\"\u0011\u0006B\u0016\u0005[\u0011y\u0003\u0003\u0004\u0003&q\u0001\r!\\\u0001\u0011Kb\u001cW\r\u001d;j_:\fG.\u0012<f]RDQ!\u0012\u000fA\u0002\u001dCQa\u0014\u000fA\u0002\u001dCQ\u0001\u0015\u000fA\u0002\u001dCQ!\u0015\u000fA\u0002\u001dCQA\u0015\u000fA\u0002\u001d\u000bac^5uQB{7o]5cY\u0016d\u0015N\\3Ok6\u0014WM\u001d\u000b\t\u0003\u000b\u0011)D!\u000f\u0003<!9!qG\u000fA\u0002\u0005\u0015\u0011!D:ue&tw\rV8Qe&tG\u000fC\u0004\u0002Jv\u0001\r!a3\t\u000bIk\u0002\u0019A$\u0002-I,7m\u001c:eK\u0012,e/\u001a8u\rJ\fw-\\3oiN$\u0002#!\u0011\u0003B\t5#q\nB)\u0005\'\u0012)Fa\u0016\t\u000f\t\rc\u00041\u0001\u0003F\u0005q!/Z2pe\u0012,G-\u0012<f]R\u001c\bCBAm\u0003?\u00149\u0005E\u0002o\u0005\u0013J1Aa\u0013p\u0005=\u0011VmY8sI\u0006\u0014G.Z#wK:$\bbBAD=\u0001\u0007\u0011\u0011\u0012\u0005\u0006\u001bz\u0001\ra\u0012\u0005\u0006\u000bz\u0001\ra\u0012\u0005\u0006\u0017z\u0001\ra\u0012\u0005\u0006\u0019z\u0001\ra\u0012\u0005\u0006%z\u0001\raR\u0001\u0016S:4w\u000e\u0015:pm&$W\r\u001a$sC\u001elWM\u001c;t)A\t\tE!\u0018\u0003f\t\u001d$\u0011\u000eB6\u0005[\u0012y\u0007C\u0004\u0002\"}\u0001\rAa\u0018\u0011\u00079\u0014\t\'C\u0002\u0003d=\u0014A\"\u00138g_B\u0013xN^5eK\u0012Dq!a\" \u0001\u0004\tI\tC\u0003N?\u0001\u0007q\tC\u0003F?\u0001\u0007q\tC\u0003L?\u0001\u0007q\tC\u0003M?\u0001\u0007q\tC\u0003S?\u0001\u0007q)\u0001\fbY\u0016\u0014H\u000f\u0015:pm&$W\r\u001a$sC\u001elWM\u001c;t)9\t\tE!\u001e\u0003~\t}$\u0011\u0011BB\u0005\u000bCq!!\t!\u0001\u0004\u00119\bE\u0002o\u0005sJ1Aa\u001fp\u00055\tE.\u001a:u!J|g/\u001b3fI\")Q\n\ta\u0001\u000f\")Q\t\ta\u0001\u000f\")1\n\ta\u0001\u000f\")A\n\ta\u0001\u000f\")!\u000b\ta\u0001\u000f\u0006)bn\u001c;f!J|g/\u001b3fI\u001a\u0013\u0018mZ7f]R\u001cHCDA!\u0005\u0017\u0013\u0019J!&\u0003\u0018\ne%1\u0014\u0005\b\u0003C\t\u0003\u0019\u0001BG!\rq\'qR\u0005\u0004\u0005#{\'\u0001\u0004(pi\u0016\u0004&o\u001c<jI\u0016$\u0007\"B\'\"\u0001\u00049\u0005\"B#\"\u0001\u00049\u0005\"B&\"\u0001\u00049\u0005\"\u0002\'\"\u0001\u00049\u0005\"\u0002*\"\u0001\u00049\u0015AH7be.,\b\u000f\u0015:pm&$W\rZ(qi&|g.\u00197Ge\u0006<W.\u001a8u)!\t\tE!)\u0003*\n-\u0006bBA\u0011E\u0001\u0007!1\u0015\t\u0004]\n\u0015\u0016b\u0001BT_\nqQ*\u0019:lkB\u0004&o\u001c<jI\u0016$\u0007bBADE\u0001\u0007\u0011\u0011\u0012\u0005\u0006\u001b\n\u0002\raR\u0001\u0018gR\u0014\u0018N\\4U_B\u0013\u0018N\u001c;XQ\u0016tW*\u0019:lkB$BB!-\u00034\nU&q\u0017B]\u0005w\u0003b!a\u0011\u0002N\u0005\u0015\u0001bBA3G\u0001\u0007\u0011q\r\u0005\b\u0003k\u001a\u0003\u0019AA>\u0011\u001d\tIh\ta\u0001\u0003wBq!a\u0001$\u0001\u0004\t)\u0001C\u0003NG\u0001\u0007q)\u0001\rtiJLgn\u001a+p!JLg\u000e^,iK:tu.\u0012:s_J$\"C!-\u0003B\n\r\'Q\u0019Bd\u0005\u0013\u0014YM!4\u0003P\"9\u0011Q\u000b\u0013A\u0002\u0005]\u0003bBA3I\u0001\u0007\u0011q\r\u0005\b\u0003k\"\u0003\u0019AA\u0003\u0011\u001d\tI\b\na\u0001\u0003wBq!a %\u0001\u0004\tY\bC\u0003FI\u0001\u0007q\tC\u0003NI\u0001\u0007q\tC\u0005\u0002\u0012\u0012\u0002\n\u00111\u0001\u0002\u0014\u0006\u00113\u000f\u001e:j]\u001e$v\u000e\u0015:j]R<\u0006.\u001a8O_\u0016\u0013(o\u001c:%I\u00164\u0017-\u001e7uIa\n\u0011C\u001a:bO6,g\u000e^:G_J,e/\u001a8u)a\t\tEa6\u0003Z\nm\'Q\u001cBp\u0005C\u0014\u0019O!:\u0003h\n%(1\u001e\u0005\b\u0003C1\u0003\u0019AA\u0012\u0011\u0015ie\u00051\u0001H\u0011\u0015)e\u00051\u0001H\u0011\u0015Ye\u00051\u0001H\u0011\u0015ae\u00051\u0001H\u0011\u0015qe\u00051\u0001H\u0011\u0015ye\u00051\u0001H\u0011\u0015\u0001f\u00051\u0001H\u0011\u0015\tf\u00051\u0001H\u0011\u0015\u0011f\u00051\u0001H\u0011\u001d\u0011iO\na\u0001\u0005_\faB]3nS:$WM]#wK:$8\u000fE\u0003\u0003r\nMX.D\u0001j\u0013\r\u0011)0\u001b\u0002\u0004\'\u0016\f\u0018!F:ue&twm\u001d+p!JLg\u000e^(o\u000bJ\u0014xN\u001d\u000b\u001f\u0005c\u0013YP!@\u0003\u0000\u000e\u000511AB\u0003\u0007\u000f\u0019Iaa\u0003\u0004\u000e\r=1\u0011CB\n\u0007+Aq!a0(\u0001\u0004\t)\u0001C\u0004\u0002D\u001e\u0002\r!a\u0016\t\u000f\u0005}t\u00051\u0001\u0002\u0006!9\u0011\u0011Z\u0014A\u0002\u0005-\u0007bBAkO\u0001\u0007\u0011q\u001b\u0005\b\u0003K:\u0003\u0019AA4\u0011\u001d\t)h\na\u0001\u0003wBq!!\u001f(\u0001\u0004\tY\bC\u0004\u0002\u0012\u001e\u0002\r!a%\t\u000b5;\u0003\u0019A$\t\u000b\u0015;\u0003\u0019A$\t\u000b-;\u0003\u0019A$\t\u000b1;\u0003\u0019A$\t\u000bI;\u0003\u0019A$\u0002\u0013\u0005t7/\u001b*fg\u0016$XCAB\u000e\u001f\t\u0019i\"\t\u0002\u0004 \u0005!1d\u0017\u0019n\u0003)\tgn]5SKN,G\u000fI\u0001\nC:\u001c\u0018n\u0012:fK:,\"aa\n\u0010\u0005\r%\u0012EAB\u0016\u0003\u0015Y2l\r\u001an\u0003)\tgn]5He\u0016,g\u000eI\u0001\tC:\u001c\u0018nQ=b]V\u001111G\b\u0003\u0007k\t#aa\u000e\u0002\u000bmY6GN7\u0002\u0013\u0005t7/[\"zC:\u0004\u0013AC1og&LV\r\u001c7poV\u00111qH\b\u0003\u0007\u0003\n#aa\u0011\u0002\u000bmY6gM7\u0002\u0017\u0005t7/[-fY2|w\u000fI\u0001\bC:\u001c\u0018NU3e+\t\u0019Ye\u0004\u0002\u0004N\u0005\u00121qJ\u0001\u00067m\u001b\u0014\'\\\u0001\tC:\u001c\u0018NU3eA\u0005\u0011R.Y6f\tV\u0014\u0018\r^5p]N#(/\u001b8h)\u0011\t)aa\u0016\t\u000f\u0005E%\u00071\u0001\u0002\u0016\u0002
   #11 = Utf8               java/lang/invoke/MethodHandles$Lookup
   #12 = Class              #11           // java/lang/invoke/MethodHandles$Lookup
   #13 = Utf8               java/lang/invoke/MethodHandles
   #14 = Class              #13           // java/lang/invoke/MethodHandles
   #15 = Utf8               Lookup
   #16 = Utf8               presentAllDurations
   #17 = Utf8               Z
   #18 = Utf8               presentShortStackTraces
   #19 = Utf8               presentFullStackTraces
   #20 = Utf8               presentUnformatted
   #21 = Utf8               presentReminder
   #22 = Utf8               presentReminderWithShortStackTraces
   #23 = Utf8               presentReminderWithFullStackTraces
   #24 = Utf8               presentReminderWithoutCanceledTests
   #25 = Utf8               presentFilePathname
   #26 = Utf8               presentJson
   #27 = Utf8               reminderEventsBuf
   #28 = Utf8               Lscala/collection/mutable/ListBuffer;
   #29 = Utf8               Lscala/collection/mutable/ListBuffer<Lorg/scalatest/events/ExceptionalEvent;>;
   #30 = Utf8               makeDurationString
   #31 = Utf8               (J)Ljava/lang/String;
   #32 = Utf8               duration
   #33 = Utf8               org/scalatest/tools/StringReporter$
   #34 = Class              #33           // org/scalatest/tools/StringReporter$
   #35 = Utf8               MODULE$
   #36 = Utf8               Lorg/scalatest/tools/StringReporter$;
   #37 = NameAndType        #35:#36       // MODULE$:Lorg/scalatest/tools/StringReporter$;
   #38 = Fieldref           #34.#37       // org/scalatest/tools/StringReporter$.MODULE$:Lorg/scalatest/tools/StringReporter$;
   #39 = NameAndType        #30:#31       // makeDurationString:(J)Ljava/lang/String;
   #40 = Methodref          #34.#39       // org/scalatest/tools/StringReporter$.makeDurationString:(J)Ljava/lang/String;
   #41 = Utf8               J
   #42 = Utf8               ansiRed
   #43 = Utf8               ()Ljava/lang/String;
   #44 = NameAndType        #42:#43       // ansiRed:()Ljava/lang/String;
   #45 = Methodref          #34.#44       // org/scalatest/tools/StringReporter$.ansiRed:()Ljava/lang/String;
   #46 = Utf8               ansiYellow
   #47 = NameAndType        #46:#43       // ansiYellow:()Ljava/lang/String;
   #48 = Methodref          #34.#47       // org/scalatest/tools/StringReporter$.ansiYellow:()Ljava/lang/String;
   #49 = Utf8               ansiCyan
   #50 = NameAndType        #49:#43       // ansiCyan:()Ljava/lang/String;
   #51 = Methodref          #34.#50       // org/scalatest/tools/StringReporter$.ansiCyan:()Ljava/lang/String;
   #52 = Utf8               ansiGreen
   #53 = NameAndType        #52:#43       // ansiGreen:()Ljava/lang/String;
   #54 = Methodref          #34.#53       // org/scalatest/tools/StringReporter$.ansiGreen:()Ljava/lang/String;
   #55 = Utf8               ansiReset
   #56 = NameAndType        #55:#43       // ansiReset:()Ljava/lang/String;
   #57 = Methodref          #34.#56       // org/scalatest/tools/StringReporter$.ansiReset:()Ljava/lang/String;
   #58 = Utf8               stringsToPrintOnError
   #59 = Utf8               (Ljava/lang/String;Lscala/Function1;Ljava/lang/String;Lscala/Option;Lscala/collection/immutable/IndexedSeq;Lscala/Option;Lscala/Option;Lscala/Option;Lscala/Option;ZZZZZ)Lscala/collection/immutable/Vector;
   #60 = Utf8               (Ljava/lang/String;Lscala/Function1<Ljava/lang/Object;Ljava/lang/String;>;Ljava/lang/String;Lscala/Option<Ljava/lang/Throwable;>;Lscala/collection/immutable/IndexedSeq<Ljava/lang/String;>;Lscala/Option<Lorg/scalatest/events/Formatter;>;Lscala/Option<Ljava/lang/String;>;Lscala/Option<Ljava/lang/String;>;Lscala/Option<Ljava/lang/Object;>;ZZZZZ)Lscala/collection/immutable/Vector<Ljava/lang/String;>;
   #61 = Utf8               noteMessageFun
   #62 = Utf8               errorMessageFun
   #63 = Utf8               message
   #64 = Utf8               throwable
   #65 = Utf8               analysis
   #66 = Utf8               formatter
   #67 = Utf8               suiteName
   #68 = Utf8               testName
   #69 = NameAndType        #58:#59       // stringsToPrintOnError:(Ljava/lang/String;Lscala/Function1;Ljava/lang/String;Lscala/Option;Lscala/collection/immutable/IndexedSeq;Lscala/Option;Lscala/Option;Lscala/Option;Lscala/Option;ZZZZZ)Lscala/collection/immutable/Vector;
   #70 = Methodref          #34.#69       // org/scalatest/tools/StringReporter$.stringsToPrintOnError:(Ljava/lang/String;Lscala/Function1;Ljava/lang/String;Lscala/Option;Lscala/collection/immutable/IndexedSeq;Lscala/Option;Lscala/Option;Lscala/Option;Lscala/Option;ZZZZZ)Lscala/collection/immutable/Vector;
   #71 = Utf8               Ljava/lang/String;
   #72 = Utf8               Lscala/Function1;
   #73 = Utf8               Lscala/Option;
   #74 = Utf8               Lscala/collection/immutable/IndexedSeq;
   #75 = Utf8               fragmentsForEvent
   #76 = Utf8               (Lorg/scalatest/events/Event;ZZZZZZZZZLscala/collection/Seq;)Lscala/collection/immutable/Vector;
   #77 = Utf8               (Lorg/scalatest/events/Event;ZZZZZZZZZLscala/collection/Seq<Lorg/scalatest/events/ExceptionalEvent;>;)Lscala/collection/immutable/Vector<Lorg/scalatest/tools/Fragment;>;
   #78 = Utf8               event
   #79 = Utf8               reminderEvents
   #80 = NameAndType        #75:#76       // fragmentsForEvent:(Lorg/scalatest/events/Event;ZZZZZZZZZLscala/collection/Seq;)Lscala/collection/immutable/Vector;
   #81 = Methodref          #34.#80       // org/scalatest/tools/StringReporter$.fragmentsForEvent:(Lorg/scalatest/events/Event;ZZZZZZZZZLscala/collection/Seq;)Lscala/collection/immutable/Vector;
   #82 = Utf8               Lorg/scalatest/events/Event;
   #83 = Utf8               Lscala/collection/Seq;
   #84 = Utf8               stringToPrintWhenNoError$default$8
   #85 = Utf8               ()Lscala/Option;
   #86 = Utf8               ()Lscala/Option<Ljava/lang/Object;>;
   #87 = NameAndType        #84:#85       // stringToPrintWhenNoError$default$8:()Lscala/Option;
   #88 = Methodref          #34.#87       // org/scalatest/tools/StringReporter$.stringToPrintWhenNoError$default$8:()Lscala/Option;
   #89 = Utf8               stringToPrintWhenNoError
   #90 = Utf8               (Lscala/Function1;Lscala/Option;Ljava/lang/String;Lscala/Option;Lscala/Option;ZZLscala/Option;)Lscala/collection/immutable/Vector;
   #91 = Utf8               (Lscala/Function1<Ljava/lang/Object;Ljava/lang/String;>;Lscala/Option<Lorg/scalatest/events/Formatter;>;Ljava/lang/String;Lscala/Option<Ljava/lang/String;>;Lscala/Option<Ljava/lang/String;>;ZZLscala/Option<Ljava/lang/Object;>;)Lscala/collection/immutable/Vector<Ljava/lang/String;>;
   #92 = Utf8               messageFun
   #93 = NameAndType        #89:#90       // stringToPrintWhenNoError:(Lscala/Function1;Lscala/Option;Ljava/lang/String;Lscala/Option;Lscala/Option;ZZLscala/Option;)Lscala/collection/immutable/Vector;
   #94 = Methodref          #34.#93       // org/scalatest/tools/StringReporter$.stringToPrintWhenNoError:(Lscala/Function1;Lscala/Option;Ljava/lang/String;Lscala/Option;Lscala/Option;ZZLscala/Option;)Lscala/collection/immutable/Vector;
   #95 = Utf8               stringToPrintWhenMarkup
   #96 = Utf8               (Lscala/Option;Lscala/Option;Lscala/Option;Ljava/lang/String;Z)Lscala/collection/immutable/Vector;
   #97 = Utf8               (Lscala/Option<Lorg/scalatest/events/Formatter;>;Lscala/Option<Ljava/lang/String;>;Lscala/Option<Ljava/lang/String;>;Ljava/lang/String;Z)Lscala/collection/immutable/Vector<Ljava/lang/String;>;
   #98 = Utf8               text
   #99 = NameAndType        #95:#96       // stringToPrintWhenMarkup:(Lscala/Option;Lscala/Option;Lscala/Option;Ljava/lang/String;Z)Lscala/collection/immutable/Vector;
  #100 = Methodref          #34.#99       // org/scalatest/tools/StringReporter$.stringToPrintWhenMarkup:(Lscala/Option;Lscala/Option;Lscala/Option;Ljava/lang/String;Z)Lscala/collection/immutable/Vector;
  #101 = Utf8               markupProvidedOptionalFragment
  #102 = Utf8               (Lorg/scalatest/events/MarkupProvided;Lorg/scalatest/tools/AnsiColor;Z)Lscala/collection/immutable/Vector;
  #103 = Utf8               (Lorg/scalatest/events/MarkupProvided;Lorg/scalatest/tools/AnsiColor;Z)Lscala/collection/immutable/Vector<Lorg/scalatest/tools/Fragment;>;
  #104 = Utf8               ansiColor
  #105 = NameAndType        #101:#102     // markupProvidedOptionalFragment:(Lorg/scalatest/events/MarkupProvided;Lorg/scalatest/tools/AnsiColor;Z)Lscala/collection/immutable/Vector;
  #106 = Methodref          #34.#105      // org/scalatest/tools/StringReporter$.markupProvidedOptionalFragment:(Lorg/scalatest/events/MarkupProvided;Lorg/scalatest/tools/AnsiColor;Z)Lscala/collection/immutable/Vector;
  #107 = Utf8               Lorg/scalatest/events/MarkupProvided;
  #108 = Utf8               Lorg/scalatest/tools/AnsiColor;
  #109 = Utf8               noteProvidedFragments
  #110 = Utf8               (Lorg/scalatest/events/NoteProvided;ZZZZZ)Lscala/collection/immutable/Vector;
  #111 = Utf8               (Lorg/scalatest/events/NoteProvided;ZZZZZ)Lscala/collection/immutable/Vector<Lorg/scalatest/tools/Fragment;>;
  #112 = NameAndType        #109:#110     // noteProvidedFragments:(Lorg/scalatest/events/NoteProvided;ZZZZZ)Lscala/collection/immutable/Vector;
  #113 = Methodref          #34.#112      // org/scalatest/tools/StringReporter$.noteProvidedFragments:(Lorg/scalatest/events/NoteProvided;ZZZZZ)Lscala/collection/immutable/Vector;
  #114 = Utf8               Lorg/scalatest/events/NoteProvided;
  #115 = Utf8               alertProvidedFragments
  #116 = Utf8               (Lorg/scalatest/events/AlertProvided;ZZZZZ)Lscala/collection/immutable/Vector;
  #117 = Utf8               (Lorg/scalatest/events/AlertProvided;ZZZZZ)Lscala/collection/immutable/Vector<Lorg/scalatest/tools/Fragment;>;
  #118 = NameAndType        #115:#116     // alertProvidedFragments:(Lorg/scalatest/events/AlertProvided;ZZZZZ)Lscala/collection/immutable/Vector;
  #119 = Methodref          #34.#118      // org/scalatest/tools/StringReporter$.alertProvidedFragments:(Lorg/scalatest/events/AlertProvided;ZZZZZ)Lscala/collection/immutable/Vector;
  #120 = Utf8               Lorg/scalatest/events/AlertProvided;
  #121 = Utf8               infoProvidedFragments
  #122 = Utf8               (Lorg/scalatest/events/InfoProvided;Lorg/scalatest/tools/AnsiColor;ZZZZZ)Lscala/collection/immutable/Vector;
  #123 = Utf8               (Lorg/scalatest/events/InfoProvided;Lorg/scalatest/tools/AnsiColor;ZZZZZ)Lscala/collection/immutable/Vector<Lorg/scalatest/tools/Fragment;>;
  #124 = NameAndType        #121:#122     // infoProvidedFragments:(Lorg/scalatest/events/InfoProvided;Lorg/scalatest/tools/AnsiColor;ZZZZZ)Lscala/collection/immutable/Vector;
  #125 = Methodref          #34.#124      // org/scalatest/tools/StringReporter$.infoProvidedFragments:(Lorg/scalatest/events/InfoProvided;Lorg/scalatest/tools/AnsiColor;ZZZZZ)Lscala/collection/immutable/Vector;
  #126 = Utf8               Lorg/scalatest/events/InfoProvided;
  #127 = Utf8               recordedEventFragments
  #128 = Utf8               (Lscala/collection/immutable/IndexedSeq;Lorg/scalatest/tools/AnsiColor;ZZZZZ)Lscala/collection/immutable/Vector;
  #129 = Utf8               (Lscala/collection/immutable/IndexedSeq<Lorg/scalatest/events/RecordableEvent;>;Lorg/scalatest/tools/AnsiColor;ZZZZZ)Lscala/collection/immutable/Vector<Lorg/scalatest/tools/Fragment;>;
  #130 = Utf8               recordedEvents
  #131 = NameAndType        #127:#128     // recordedEventFragments:(Lscala/collection/immutable/IndexedSeq;Lorg/scalatest/tools/AnsiColor;ZZZZZ)Lscala/collection/immutable/Vector;
  #132 = Methodref          #34.#131      // org/scalatest/tools/StringReporter$.recordedEventFragments:(Lscala/collection/immutable/IndexedSeq;Lorg/scalatest/tools/AnsiColor;ZZZZZ)Lscala/collection/immutable/Vector;
  #133 = Utf8               withPossibleLineNumber
  #134 = Utf8               (Ljava/lang/String;Lscala/Option;Z)Ljava/lang/String;
  #135 = Utf8               (Ljava/lang/String;Lscala/Option<Ljava/lang/Throwable;>;Z)Ljava/lang/String;
  #136 = Utf8               stringToPrint
  #137 = NameAndType        #133:#134     // withPossibleLineNumber:(Ljava/lang/String;Lscala/Option;Z)Ljava/lang/String;
  #138 = Methodref          #34.#137      // org/scalatest/tools/StringReporter$.withPossibleLineNumber:(Ljava/lang/String;Lscala/Option;Z)Ljava/lang/String;
  #139 = Utf8               exceptionalFragments
  #140 = Utf8               (Lorg/scalatest/events/ExceptionalEvent;ZZZZZ)Lscala/collection/immutable/Vector;
  #141 = Utf8               (Lorg/scalatest/events/ExceptionalEvent;ZZZZZ)Lscala/collection/immutable/Vector<Lorg/scalatest/tools/Fragment;>;
  #142 = Utf8               exceptionalEvent
  #143 = NameAndType        #139:#140     // exceptionalFragments:(Lorg/scalatest/events/ExceptionalEvent;ZZZZZ)Lscala/collection/immutable/Vector;
  #144 = Methodref          #34.#143      // org/scalatest/tools/StringReporter$.exceptionalFragments:(Lorg/scalatest/events/ExceptionalEvent;ZZZZZ)Lscala/collection/immutable/Vector;
  #145 = Utf8               Lorg/scalatest/events/ExceptionalEvent;
  #146 = Utf8               summaryFragments
  #147 = Utf8               (ZLscala/Option;Lscala/Option;Lscala/collection/immutable/Vector;ZZZZZZ)Lscala/collection/immutable/Vector;
  #148 = Utf8               (ZLscala/Option<Ljava/lang/Object;>;Lscala/Option<Lorg/scalatest/events/Summary;>;Lscala/collection/immutable/Vector<Lorg/scalatest/events/ExceptionalEvent;>;ZZZZZZ)Lscala/collection/immutable/Vector<Lorg/scalatest/tools/Fragment;>;
  #149 = Utf8               runCompleted
  #150 = Utf8               summaryOption
  #151 = Utf8               exceptionalEvents
  #152 = NameAndType        #146:#147     // summaryFragments:(ZLscala/Option;Lscala/Option;Lscala/collection/immutable/Vector;ZZZZZZ)Lscala/collection/immutable/Vector;
  #153 = Methodref          #34.#152      // org/scalatest/tools/StringReporter$.summaryFragments:(ZLscala/Option;Lscala/Option;Lscala/collection/immutable/Vector;ZZZZZZ)Lscala/collection/immutable/Vector;
  #154 = Utf8               Lscala/collection/immutable/Vector;
  #155 = Utf8               fragmentsOnError
  #156 = Utf8               (Ljava/lang/String;Lscala/Function1;Ljava/lang/String;Lscala/Option;Lscala/collection/immutable/IndexedSeq;Lscala/Option;Lscala/Option;Lscala/Option;Lscala/Option;ZZZZZLorg/scalatest/tools/AnsiColor;)Lscala/collection/immutable/Vector;
  #157 = Utf8               (Ljava/lang/String;Lscala/Function1<Ljava/lang/Object;Ljava/lang/String;>;Ljava/lang/String;Lscala/Option<Ljava/lang/Throwable;>;Lscala/collection/immutable/IndexedSeq<Ljava/lang/String;>;Lscala/Option<Lorg/scalatest/events/Formatter;>;Lscala/Option<Ljava/lang/String;>;Lscala/Option<Ljava/lang/String;>;Lscala/Option<Ljava/lang/Object;>;ZZZZZLorg/scalatest/tools/AnsiColor;)Lscala/collection/immutable/Vector<Lorg/scalatest/tools/Fragment;>;
  #158 = NameAndType        #155:#156     // fragmentsOnError:(Ljava/lang/String;Lscala/Function1;Ljava/lang/String;Lscala/Option;Lscala/collection/immutable/IndexedSeq;Lscala/Option;Lscala/Option;Lscala/Option;Lscala/Option;ZZZZZLorg/scalatest/tools/AnsiColor;)Lscala/collection/immutable/Vector;
  #159 = Methodref          #34.#158      // org/scalatest/tools/StringReporter$.fragmentsOnError:(Ljava/lang/String;Lscala/Function1;Ljava/lang/String;Lscala/Option;Lscala/collection/immutable/IndexedSeq;Lscala/Option;Lscala/Option;Lscala/Option;Lscala/Option;ZZZZZLorg/scalatest/tools/AnsiColor;)Lscala/collection/immutable/Vector;
  #160 = Utf8               fragmentsWhenNoError$default$9
  #161 = NameAndType        #160:#85      // fragmentsWhenNoError$default$9:()Lscala/Option;
  #162 = Methodref          #34.#161      // org/scalatest/tools/StringReporter$.fragmentsWhenNoError$default$9:()Lscala/Option;
  #163 = Utf8               fragmentsWhenNoError$default$8
  #164 = Utf8               ()Lorg/scalatest/tools/AnsiColor;
  #165 = NameAndType        #163:#164     // fragmentsWhenNoError$default$8:()Lorg/scalatest/tools/AnsiColor;
  #166 = Methodref          #34.#165      // org/scalatest/tools/StringReporter$.fragmentsWhenNoError$default$8:()Lorg/scalatest/tools/AnsiColor;
  #167 = Utf8               fragmentsWhenNoError
  #168 = Utf8               (Lscala/Function1;Lscala/Option;Ljava/lang/String;Lscala/Option;Lscala/Option;ZZLorg/scalatest/tools/AnsiColor;Lscala/Option;)Lscala/collection/immutable/Vector;
  #169 = Utf8               (Lscala/Function1<Ljava/lang/Object;Ljava/lang/String;>;Lscala/Option<Lorg/scalatest/events/Formatter;>;Ljava/lang/String;Lscala/Option<Ljava/lang/String;>;Lscala/Option<Ljava/lang/String;>;ZZLorg/scalatest/tools/AnsiColor;Lscala/Option<Ljava/lang/Object;>;)Lscala/collection/immutable/Vector<Lorg/scalatest/tools/Fragment;>;
  #170 = NameAndType        #167:#168     // fragmentsWhenNoError:(Lscala/Function1;Lscala/Option;Ljava/lang/String;Lscala/Option;Lscala/Option;ZZLorg/scalatest/tools/AnsiColor;Lscala/Option;)Lscala/collection/immutable/Vector;
  #171 = Methodref          #34.#170      // org/scalatest/tools/StringReporter$.fragmentsWhenNoError:(Lscala/Function1;Lscala/Option;Ljava/lang/String;Lscala/Option;Lscala/Option;ZZLorg/scalatest/tools/AnsiColor;Lscala/Option;)Lscala/collection/immutable/Vector;
  #172 = Utf8               shortStackTraceSize
  #173 = Utf8               ()I
  #174 = NameAndType        #172:#173     // shortStackTraceSize:()I
  #175 = Methodref          #34.#174      // org/scalatest/tools/StringReporter$.shortStackTraceSize:()I
  #176 = Utf8               ()Lscala/collection/mutable/ListBuffer;
  #177 = Utf8               ()Lscala/collection/mutable/ListBuffer<Lorg/scalatest/events/ExceptionalEvent;>;
  #178 = NameAndType        #27:#28       // reminderEventsBuf:Lscala/collection/mutable/ListBuffer;
  #179 = Fieldref           #2.#178       // org/scalatest/tools/StringReporter.reminderEventsBuf:Lscala/collection/mutable/ListBuffer;
  #180 = Utf8               this
  #181 = Utf8               Lorg/scalatest/tools/StringReporter;
  #182 = Utf8               printPossiblyInColor
  #183 = Utf8               (Lorg/scalatest/tools/Fragment;)V
  #184 = Utf8               fragment
  #185 = Utf8               printNoColor
  #186 = Utf8               (Ljava/lang/String;)V
  #187 = Utf8               apply
  #188 = Utf8               (Lorg/scalatest/events/Event;)V
  #189 = Utf8               org/scalatest/events/ExceptionalEvent
  #190 = Class              #189          // org/scalatest/events/ExceptionalEvent
  #191 = NameAndType        #21:#17       // presentReminder:Z
  #192 = Fieldref           #2.#191       // org/scalatest/tools/StringReporter.presentReminder:Z
  #193 = NameAndType        #24:#17       // presentReminderWithoutCanceledTests:Z
  #194 = Fieldref           #2.#193       // org/scalatest/tools/StringReporter.presentReminderWithoutCanceledTests:Z
  #195 = Utf8               org/scalatest/events/TestFailed
  #196 = Class              #195          // org/scalatest/events/TestFailed
  #197 = NameAndType        #27:#176      // reminderEventsBuf:()Lscala/collection/mutable/ListBuffer;
  #198 = Methodref          #2.#197       // org/scalatest/tools/StringReporter.reminderEventsBuf:()Lscala/collection/mutable/ListBuffer;
  #199 = Utf8               scala/collection/mutable/ListBuffer
  #200 = Class              #199          // scala/collection/mutable/ListBuffer
  #201 = Utf8               $plus$eq
  #202 = Utf8               (Ljava/lang/Object;)Lscala/collection/mutable/Growable;
  #203 = NameAndType        #201:#202     // $plus$eq:(Ljava/lang/Object;)Lscala/collection/mutable/Growable;
  #204 = Methodref          #200.#203     // scala/collection/mutable/ListBuffer.$plus$eq:(Ljava/lang/Object;)Lscala/collection/mutable/Growable;
  #205 = Utf8               scala/runtime/BoxedUnit
  #206 = Class              #205          // scala/runtime/BoxedUnit
  #207 = Utf8               UNIT
  #208 = Utf8               Lscala/runtime/BoxedUnit;
  #209 = NameAndType        #207:#208     // UNIT:Lscala/runtime/BoxedUnit;
  #210 = Fieldref           #206.#209     // scala/runtime/BoxedUnit.UNIT:Lscala/runtime/BoxedUnit;
  #211 = NameAndType        #26:#17       // presentJson:Z
  #212 = Fieldref           #2.#211       // org/scalatest/tools/StringReporter.presentJson:Z
  #213 = Utf8               org/scalatest/events/Event
  #214 = Class              #213          // org/scalatest/events/Event
  #215 = Utf8               toJson
  #216 = NameAndType        #215:#43      // toJson:()Ljava/lang/String;
  #217 = Methodref          #214.#216     // org/scalatest/events/Event.toJson:()Ljava/lang/String;
  #218 = NameAndType        #185:#186     // printNoColor:(Ljava/lang/String;)V
  #219 = Methodref          #2.#218       // org/scalatest/tools/StringReporter.printNoColor:(Ljava/lang/String;)V
  #220 = NameAndType        #20:#17       // presentUnformatted:Z
  #221 = Fieldref           #2.#220       // org/scalatest/tools/StringReporter.presentUnformatted:Z
  #222 = NameAndType        #16:#17       // presentAllDurations:Z
  #223 = Fieldref           #2.#222       // org/scalatest/tools/StringReporter.presentAllDurations:Z
  #224 = NameAndType        #18:#17       // presentShortStackTraces:Z
  #225 = Fieldref           #2.#224       // org/scalatest/tools/StringReporter.presentShortStackTraces:Z
  #226 = NameAndType        #19:#17       // presentFullStackTraces:Z
  #227 = Fieldref           #2.#226       // org/scalatest/tools/StringReporter.presentFullStackTraces:Z
  #228 = NameAndType        #22:#17       // presentReminderWithShortStackTraces:Z
  #229 = Fieldref           #2.#228       // org/scalatest/tools/StringReporter.presentReminderWithShortStackTraces:Z
  #230 = NameAndType        #23:#17       // presentReminderWithFullStackTraces:Z
  #231 = Fieldref           #2.#230       // org/scalatest/tools/StringReporter.presentReminderWithFullStackTraces:Z
  #232 = NameAndType        #25:#17       // presentFilePathname:Z
  #233 = Fieldref           #2.#232       // org/scalatest/tools/StringReporter.presentFilePathname:Z
  #234 = Utf8               (Ljava/lang/Object;)Ljava/lang/Object;
  #235 = MethodType         #234          //  (Ljava/lang/Object;)Ljava/lang/Object;
  #236 = Utf8               $anonfun$apply$1$adapted
  #237 = Utf8               (Lorg/scalatest/tools/StringReporter;Lorg/scalatest/tools/Fragment;)Ljava/lang/Object;
  #238 = NameAndType        #236:#237     // $anonfun$apply$1$adapted:(Lorg/scalatest/tools/StringReporter;Lorg/scalatest/tools/Fragment;)Ljava/lang/Object;
  #239 = Methodref          #2.#238       // org/scalatest/tools/StringReporter.$anonfun$apply$1$adapted:(Lorg/scalatest/tools/StringReporter;Lorg/scalatest/tools/Fragment;)Ljava/lang/Object;
  #240 = MethodHandle       6:#239        // REF_invokeStatic org/scalatest/tools/StringReporter.$anonfun$apply$1$adapted:(Lorg/scalatest/tools/StringReporter;Lorg/scalatest/tools/Fragment;)Ljava/lang/Object;
  #241 = Utf8               (Lorg/scalatest/tools/Fragment;)Ljava/lang/Object;
  #242 = MethodType         #241          //  (Lorg/scalatest/tools/Fragment;)Ljava/lang/Object;
  #243 = Integer            5
  #244 = Integer            1
  #245 = Utf8               java/lang/invoke/LambdaMetafactory
  #246 = Class              #245          // java/lang/invoke/LambdaMetafactory
  #247 = Utf8               altMetafactory
  #248 = Utf8               (Ljava/lang/invoke/MethodHandles$Lookup;Ljava/lang/String;Ljava/lang/invoke/MethodType;[Ljava/lang/Object;)Ljava/lang/invoke/CallSite;
  #249 = NameAndType        #247:#248     // altMetafactory:(Ljava/lang/invoke/MethodHandles$Lookup;Ljava/lang/String;Ljava/lang/invoke/MethodType;[Ljava/lang/Object;)Ljava/lang/invoke/CallSite;
  #250 = Methodref          #246.#249     // java/lang/invoke/LambdaMetafactory.altMetafactory:(Ljava/lang/invoke/MethodHandles$Lookup;Ljava/lang/String;Ljava/lang/invoke/MethodType;[Ljava/lang/Object;)Ljava/lang/invoke/CallSite;
  #251 = MethodHandle       6:#250        // REF_invokeStatic java/lang/invoke/LambdaMetafactory.altMetafactory:(Ljava/lang/invoke/MethodHandles$Lookup;Ljava/lang/String;Ljava/lang/invoke/MethodType;[Ljava/lang/Object;)Ljava/lang/invoke/CallSite;
  #252 = Utf8               (Lorg/scalatest/tools/StringReporter;)Lscala/Function1;
  #253 = NameAndType        #187:#252     // apply:(Lorg/scalatest/tools/StringReporter;)Lscala/Function1;
  #254 = InvokeDynamic      #0:#253       // #0:apply:(Lorg/scalatest/tools/StringReporter;)Lscala/Function1;
  #255 = Utf8               scala/collection/immutable/Vector
  #256 = Class              #255          // scala/collection/immutable/Vector
  #257 = Utf8               foreach
  #258 = Utf8               (Lscala/Function1;)V
  #259 = NameAndType        #257:#258     // foreach:(Lscala/Function1;)V
  #260 = Methodref          #256.#259     // scala/collection/immutable/Vector.foreach:(Lscala/Function1;)V
  #261 = Utf8               $anonfun$apply$1
  #262 = Utf8               (Lorg/scalatest/tools/StringReporter;Lorg/scalatest/tools/Fragment;)V
  #263 = Utf8               $this
  #264 = Utf8               e
  #265 = NameAndType        #182:#183     // printPossiblyInColor:(Lorg/scalatest/tools/Fragment;)V
  #266 = Methodref          #2.#265       // org/scalatest/tools/StringReporter.printPossiblyInColor:(Lorg/scalatest/tools/Fragment;)V
  #267 = Utf8               Lorg/scalatest/tools/Fragment;
  #268 = Utf8               <init>
  #269 = Utf8               (ZZZZZZZZZZZ)V
  #270 = Utf8               presentInColor
  #271 = Utf8               ()V
  #272 = NameAndType        #268:#271     // "<init>":()V
  #273 = Methodref          #4.#272       // java/lang/Object."<init>":()V
  #274 = Methodref          #200.#272     // scala/collection/mutable/ListBuffer."<init>":()V
  #275 = NameAndType        #261:#262     // $anonfun$apply$1:(Lorg/scalatest/tools/StringReporter;Lorg/scalatest/tools/Fragment;)V
  #276 = Methodref          #2.#275       // org/scalatest/tools/StringReporter.$anonfun$apply$1:(Lorg/scalatest/tools/StringReporter;Lorg/scalatest/tools/Fragment;)V
  #277 = Utf8               $deserializeLambda$
  #278 = Utf8               (Ljava/lang/invoke/SerializedLambda;)Ljava/lang/Object;
  #279 = Utf8               scala/runtime/LambdaDeserialize
  #280 = Class              #279          // scala/runtime/LambdaDeserialize
  #281 = Utf8               bootstrap
  #282 = Utf8               (Ljava/lang/invoke/MethodHandles$Lookup;Ljava/lang/String;Ljava/lang/invoke/MethodType;[Ljava/lang/invoke/MethodHandle;)Ljava/lang/invoke/CallSite;
  #283 = NameAndType        #281:#282     // bootstrap:(Ljava/lang/invoke/MethodHandles$Lookup;Ljava/lang/String;Ljava/lang/invoke/MethodType;[Ljava/lang/invoke/MethodHandle;)Ljava/lang/invoke/CallSite;
  #284 = Methodref          #280.#283     // scala/runtime/LambdaDeserialize.bootstrap:(Ljava/lang/invoke/MethodHandles$Lookup;Ljava/lang/String;Ljava/lang/invoke/MethodType;[Ljava/lang/invoke/MethodHandle;)Ljava/lang/invoke/CallSite;
  #285 = MethodHandle       6:#284        // REF_invokeStatic scala/runtime/LambdaDeserialize.bootstrap:(Ljava/lang/invoke/MethodHandles$Lookup;Ljava/lang/String;Ljava/lang/invoke/MethodType;[Ljava/lang/invoke/MethodHandle;)Ljava/lang/invoke/CallSite;
  #286 = Utf8               lambdaDeserialize
  #287 = NameAndType        #286:#278     // lambdaDeserialize:(Ljava/lang/invoke/SerializedLambda;)Ljava/lang/Object;
  #288 = InvokeDynamic      #1:#287       // #1:lambdaDeserialize:(Ljava/lang/invoke/SerializedLambda;)Ljava/lang/Object;
  #289 = Utf8               Signature
  #290 = Utf8               Code
  #291 = Utf8               LocalVariableTable
  #292 = Utf8               MethodParameters
  #293 = Utf8               LineNumberTable
  #294 = Utf8               StackMapTable
  #295 = Utf8               InnerClasses
  #296 = Utf8               SourceFile
  #297 = Utf8               RuntimeVisibleAnnotations
  #298 = Utf8               BootstrapMethods
  #299 = Utf8               ScalaInlineInfo
  #300 = Utf8               ScalaSig
{
  private final boolean presentAllDurations;
    descriptor: Z
    flags: (0x0012) ACC_PRIVATE, ACC_FINAL

  private final boolean presentShortStackTraces;
    descriptor: Z
    flags: (0x0012) ACC_PRIVATE, ACC_FINAL

  private final boolean presentFullStackTraces;
    descriptor: Z
    flags: (0x0012) ACC_PRIVATE, ACC_FINAL

  private final boolean presentUnformatted;
    descriptor: Z
    flags: (0x0012) ACC_PRIVATE, ACC_FINAL

  private final boolean presentReminder;
    descriptor: Z
    flags: (0x0012) ACC_PRIVATE, ACC_FINAL

  private final boolean presentReminderWithShortStackTraces;
    descriptor: Z
    flags: (0x0012) ACC_PRIVATE, ACC_FINAL

  private final boolean presentReminderWithFullStackTraces;
    descriptor: Z
    flags: (0x0012) ACC_PRIVATE, ACC_FINAL

  private final boolean presentReminderWithoutCanceledTests;
    descriptor: Z
    flags: (0x0012) ACC_PRIVATE, ACC_FINAL

  private final boolean presentFilePathname;
    descriptor: Z
    flags: (0x0012) ACC_PRIVATE, ACC_FINAL

  private final boolean presentJson;
    descriptor: Z
    flags: (0x0012) ACC_PRIVATE, ACC_FINAL

  private final scala.collection.mutable.ListBuffer<org.scalatest.events.ExceptionalEvent> reminderEventsBuf;
    descriptor: Lscala/collection/mutable/ListBuffer;
    flags: (0x0012) ACC_PRIVATE, ACC_FINAL
    Signature: #29                          // Lscala/collection/mutable/ListBuffer<Lorg/scalatest/events/ExceptionalEvent;>;

  public static java.lang.String makeDurationString(long);
    descriptor: (J)Ljava/lang/String;
    flags: (0x0009) ACC_PUBLIC, ACC_STATIC
    Code:
      stack=3, locals=2, args_size=1
         0: getstatic     #38                 // Field org/scalatest/tools/StringReporter$.MODULE$:Lorg/scalatest/tools/StringReporter$;
         3: lload_0
         4: invokevirtual #40                 // Method org/scalatest/tools/StringReporter$.makeDurationString:(J)Ljava/lang/String;
         7: areturn
      LocalVariableTable:
        Start  Length  Slot  Name   Signature
            0       8     0 duration   J
    MethodParameters:
      Name                           Flags
      duration                       final

  public static java.lang.String ansiRed();
    descriptor: ()Ljava/lang/String;
    flags: (0x0009) ACC_PUBLIC, ACC_STATIC
    Code:
      stack=1, locals=0, args_size=0
         0: getstatic     #38                 // Field org/scalatest/tools/StringReporter$.MODULE$:Lorg/scalatest/tools/StringReporter$;
         3: invokevirtual #45                 // Method org/scalatest/tools/StringReporter$.ansiRed:()Ljava/lang/String;
         6: areturn

  public static java.lang.String ansiYellow();
    descriptor: ()Ljava/lang/String;
    flags: (0x0009) ACC_PUBLIC, ACC_STATIC
    Code:
      stack=1, locals=0, args_size=0
         0: getstatic     #38                 // Field org/scalatest/tools/StringReporter$.MODULE$:Lorg/scalatest/tools/StringReporter$;
         3: invokevirtual #48                 // Method org/scalatest/tools/StringReporter$.ansiYellow:()Ljava/lang/String;
         6: areturn

  public static java.lang.String ansiCyan();
    descriptor: ()Ljava/lang/String;
    flags: (0x0009) ACC_PUBLIC, ACC_STATIC
    Code:
      stack=1, locals=0, args_size=0
         0: getstatic     #38                 // Field org/scalatest/tools/StringReporter$.MODULE$:Lorg/scalatest/tools/StringReporter$;
         3: invokevirtual #51                 // Method org/scalatest/tools/StringReporter$.ansiCyan:()Ljava/lang/String;
         6: areturn

  public static java.lang.String ansiGreen();
    descriptor: ()Ljava/lang/String;
    flags: (0x0009) ACC_PUBLIC, ACC_STATIC
    Code:
      stack=1, locals=0, args_size=0
         0: getstatic     #38                 // Field org/scalatest/tools/StringReporter$.MODULE$:Lorg/scalatest/tools/StringReporter$;
         3: invokevirtual #54                 // Method org/scalatest/tools/StringReporter$.ansiGreen:()Ljava/lang/String;
         6: areturn

  public static java.lang.String ansiReset();
    descriptor: ()Ljava/lang/String;
    flags: (0x0009) ACC_PUBLIC, ACC_STATIC
    Code:
      stack=1, locals=0, args_size=0
         0: getstatic     #38                 // Field org/scalatest/tools/StringReporter$.MODULE$:Lorg/scalatest/tools/StringReporter$;
         3: invokevirtual #57                 // Method org/scalatest/tools/StringReporter$.ansiReset:()Ljava/lang/String;
         6: areturn

  public static scala.collection.immutable.Vector<java.lang.String> stringsToPrintOnError(java.lang.String, scala.Function1<java.lang.Object, java.lang.String>, java.lang.String, scala.Option<java.lang.Throwable>, scala.collection.immutable.IndexedSeq<java.lang.String>, scala.Option<org.scalatest.events.Formatter>, scala.Option<java.lang.String>, scala.Option<java.lang.String>, scala.Option<java.lang.Object>, boolean, boolean, boolean, boolean, boolean);
    descriptor: (Ljava/lang/String;Lscala/Function1;Ljava/lang/String;Lscala/Option;Lscala/collection/immutable/IndexedSeq;Lscala/Option;Lscala/Option;Lscala/Option;Lscala/Option;ZZZZZ)Lscala/collection/immutable/Vector;
    flags: (0x0009) ACC_PUBLIC, ACC_STATIC
    Code:
      stack=15, locals=14, args_size=14
         0: getstatic     #38                 // Field org/scalatest/tools/StringReporter$.MODULE$:Lorg/scalatest/tools/StringReporter$;
         3: aload_0
         4: aload_1
         5: aload_2
         6: aload_3
         7: aload         4
         9: aload         5
        11: aload         6
        13: aload         7
        15: aload         8
        17: iload         9
        19: iload         10
        21: iload         11
        23: iload         12
        25: iload         13
        27: invokevirtual #70                 // Method org/scalatest/tools/StringReporter$.stringsToPrintOnError:(Ljava/lang/String;Lscala/Function1;Ljava/lang/String;Lscala/Option;Lscala/collection/immutable/IndexedSeq;Lscala/Option;Lscala/Option;Lscala/Option;Lscala/Option;ZZZZZ)Lscala/collection/immutable/Vector;
        30: areturn
      LocalVariableTable:
        Start  Length  Slot  Name   Signature
            0      31     0 noteMessageFun   Ljava/lang/String;
            0      31     1 errorMessageFun   Lscala/Function1;
            0      31     2 message   Ljava/lang/String;
            0      31     3 throwable   Lscala/Option;
            0      31     4 analysis   Lscala/collection/immutable/IndexedSeq;
            0      31     5 formatter   Lscala/Option;
            0      31     6 suiteName   Lscala/Option;
            0      31     7 testName   Lscala/Option;
            0      31     8 duration   Lscala/Option;
            0      31     9 presentUnformatted   Z
            0      31    10 presentAllDurations   Z
            0      31    11 presentShortStackTraces   Z
            0      31    12 presentFullStackTraces   Z
            0      31    13 presentFilePathname   Z
    Signature: #60                          // (Ljava/lang/String;Lscala/Function1<Ljava/lang/Object;Ljava/lang/String;>;Ljava/lang/String;Lscala/Option<Ljava/lang/Throwable;>;Lscala/collection/immutable/IndexedSeq<Ljava/lang/String;>;Lscala/Option<Lorg/scalatest/events/Formatter;>;Lscala/Option<Ljava/lang/String;>;Lscala/Option<Ljava/lang/String;>;Lscala/Option<Ljava/lang/Object;>;ZZZZZ)Lscala/collection/immutable/Vector<Ljava/lang/String;>;
    MethodParameters:
      Name                           Flags
      noteMessageFun                 final
      errorMessageFun                final
      message                        final
      throwable                      final
      analysis                       final
      formatter                      final
      suiteName                      final
      testName                       final
      duration                       final
      presentUnformatted             final
      presentAllDurations            final
      presentShortStackTraces        final
      presentFullStackTraces         final
      presentFilePathname            final

  public static scala.collection.immutable.Vector<org.scalatest.tools.Fragment> fragmentsForEvent(org.scalatest.events.Event, boolean, boolean, boolean, boolean, boolean, boolean, boolean, boolean, boolean, scala.collection.Seq<org.scalatest.events.ExceptionalEvent>);
    descriptor: (Lorg/scalatest/events/Event;ZZZZZZZZZLscala/collection/Seq;)Lscala/collection/immutable/Vector;
    flags: (0x0009) ACC_PUBLIC, ACC_STATIC
    Code:
      stack=12, locals=11, args_size=11
         0: getstatic     #38                 // Field org/scalatest/tools/StringReporter$.MODULE$:Lorg/scalatest/tools/StringReporter$;
         3: aload_0
         4: iload_1
         5: iload_2
         6: iload_3
         7: iload         4
         9: iload         5
        11: iload         6
        13: iload         7
        15: iload         8
        17: iload         9
        19: aload         10
        21: invokevirtual #81                 // Method org/scalatest/tools/StringReporter$.fragmentsForEvent:(Lorg/scalatest/events/Event;ZZZZZZZZZLscala/collection/Seq;)Lscala/collection/immutable/Vector;
        24: areturn
      LocalVariableTable:
        Start  Length  Slot  Name   Signature
            0      25     0 event   Lorg/scalatest/events/Event;
            0      25     1 presentUnformatted   Z
            0      25     2 presentAllDurations   Z
            0      25     3 presentShortStackTraces   Z
            0      25     4 presentFullStackTraces   Z
            0      25     5 presentReminder   Z
            0      25     6 presentReminderWithShortStackTraces   Z
            0      25     7 presentReminderWithFullStackTraces   Z
            0      25     8 presentReminderWithoutCanceledTests   Z
            0      25     9 presentFilePathname   Z
            0      25    10 reminderEvents   Lscala/collection/Seq;
    Signature: #77                          // (Lorg/scalatest/events/Event;ZZZZZZZZZLscala/collection/Seq<Lorg/scalatest/events/ExceptionalEvent;>;)Lscala/collection/immutable/Vector<Lorg/scalatest/tools/Fragment;>;
    MethodParameters:
      Name                           Flags
      event                          final
      presentUnformatted             final
      presentAllDurations            final
      presentShortStackTraces        final
      presentFullStackTraces         final
      presentReminder                final
      presentReminderWithShortStackTracesfinal
      presentReminderWithFullStackTracesfinal
      presentReminderWithoutCanceledTestsfinal
      presentFilePathname            final
      reminderEvents                 final

  public static scala.Option<java.lang.Object> stringToPrintWhenNoError$default$8();
    descriptor: ()Lscala/Option;
    flags: (0x0009) ACC_PUBLIC, ACC_STATIC
    Code:
      stack=1, locals=0, args_size=0
         0: getstatic     #38                 // Field org/scalatest/tools/StringReporter$.MODULE$:Lorg/scalatest/tools/StringReporter$;
         3: invokevirtual #88                 // Method org/scalatest/tools/StringReporter$.stringToPrintWhenNoError$default$8:()Lscala/Option;
         6: areturn
    Signature: #86                          // ()Lscala/Option<Ljava/lang/Object;>;

  public static scala.collection.immutable.Vector<java.lang.String> stringToPrintWhenNoError(scala.Function1<java.lang.Object, java.lang.String>, scala.Option<org.scalatest.events.Formatter>, java.lang.String, scala.Option<java.lang.String>, scala.Option<java.lang.String>, boolean, boolean, scala.Option<java.lang.Object>);
    descriptor: (Lscala/Function1;Lscala/Option;Ljava/lang/String;Lscala/Option;Lscala/Option;ZZLscala/Option;)Lscala/collection/immutable/Vector;
    flags: (0x0009) ACC_PUBLIC, ACC_STATIC
    Code:
      stack=9, locals=8, args_size=8
         0: getstatic     #38                 // Field org/scalatest/tools/StringReporter$.MODULE$:Lorg/scalatest/tools/StringReporter$;
         3: aload_0
         4: aload_1
         5: aload_2
         6: aload_3
         7: aload         4
         9: iload         5
        11: iload         6
        13: aload         7
        15: invokevirtual #94                 // Method org/scalatest/tools/StringReporter$.stringToPrintWhenNoError:(Lscala/Function1;Lscala/Option;Ljava/lang/String;Lscala/Option;Lscala/Option;ZZLscala/Option;)Lscala/collection/immutable/Vector;
        18: areturn
      LocalVariableTable:
        Start  Length  Slot  Name   Signature
            0      19     0 messageFun   Lscala/Function1;
            0      19     1 formatter   Lscala/Option;
            0      19     2 suiteName   Ljava/lang/String;
            0      19     3 testName   Lscala/Option;
            0      19     4 message   Lscala/Option;
            0      19     5 presentAllDurations   Z
            0      19     6 presentUnformatted   Z
            0      19     7 duration   Lscala/Option;
    Signature: #91                          // (Lscala/Function1<Ljava/lang/Object;Ljava/lang/String;>;Lscala/Option<Lorg/scalatest/events/Formatter;>;Ljava/lang/String;Lscala/Option<Ljava/lang/String;>;Lscala/Option<Ljava/lang/String;>;ZZLscala/Option<Ljava/lang/Object;>;)Lscala/collection/immutable/Vector<Ljava/lang/String;>;
    MethodParameters:
      Name                           Flags
      messageFun                     final
      formatter                      final
      suiteName                      final
      testName                       final
      message                        final
      presentAllDurations            final
      presentUnformatted             final
      duration                       final

  public static scala.collection.immutable.Vector<java.lang.String> stringToPrintWhenMarkup(scala.Option<org.scalatest.events.Formatter>, scala.Option<java.lang.String>, scala.Option<java.lang.String>, java.lang.String, boolean);
    descriptor: (Lscala/Option;Lscala/Option;Lscala/Option;Ljava/lang/String;Z)Lscala/collection/immutable/Vector;
    flags: (0x0009) ACC_PUBLIC, ACC_STATIC
    Code:
      stack=6, locals=5, args_size=5
         0: getstatic     #38                 // Field org/scalatest/tools/StringReporter$.MODULE$:Lorg/scalatest/tools/StringReporter$;
         3: aload_0
         4: aload_1
         5: aload_2
         6: aload_3
         7: iload         4
         9: invokevirtual #100                // Method org/scalatest/tools/StringReporter$.stringToPrintWhenMarkup:(Lscala/Option;Lscala/Option;Lscala/Option;Ljava/lang/String;Z)Lscala/collection/immutable/Vector;
        12: areturn
      LocalVariableTable:
        Start  Length  Slot  Name   Signature
            0      13     0 formatter   Lscala/Option;
            0      13     1 suiteName   Lscala/Option;
            0      13     2 testName   Lscala/Option;
            0      13     3  text   Ljava/lang/String;
            0      13     4 presentUnformatted   Z
    Signature: #97                          // (Lscala/Option<Lorg/scalatest/events/Formatter;>;Lscala/Option<Ljava/lang/String;>;Lscala/Option<Ljava/lang/String;>;Ljava/lang/String;Z)Lscala/collection/immutable/Vector<Ljava/lang/String;>;
    MethodParameters:
      Name                           Flags
      formatter                      final
      suiteName                      final
      testName                       final
      text                           final
      presentUnformatted             final

  public static scala.collection.immutable.Vector<org.scalatest.tools.Fragment> markupProvidedOptionalFragment(org.scalatest.events.MarkupProvided, org.scalatest.tools.AnsiColor, boolean);
    descriptor: (Lorg/scalatest/events/MarkupProvided;Lorg/scalatest/tools/AnsiColor;Z)Lscala/collection/immutable/Vector;
    flags: (0x0009) ACC_PUBLIC, ACC_STATIC
    Code:
      stack=4, locals=3, args_size=3
         0: getstatic     #38                 // Field org/scalatest/tools/StringReporter$.MODULE$:Lorg/scalatest/tools/StringReporter$;
         3: aload_0
         4: aload_1
         5: iload_2
         6: invokevirtual #106                // Method org/scalatest/tools/StringReporter$.markupProvidedOptionalFragment:(Lorg/scalatest/events/MarkupProvided;Lorg/scalatest/tools/AnsiColor;Z)Lscala/collection/immutable/Vector;
         9: areturn
      LocalVariableTable:
        Start  Length  Slot  Name   Signature
            0      10     0 event   Lorg/scalatest/events/MarkupProvided;
            0      10     1 ansiColor   Lorg/scalatest/tools/AnsiColor;
            0      10     2 presentUnformatted   Z
    Signature: #103                         // (Lorg/scalatest/events/MarkupProvided;Lorg/scalatest/tools/AnsiColor;Z)Lscala/collection/immutable/Vector<Lorg/scalatest/tools/Fragment;>;
    MethodParameters:
      Name                           Flags
      event                          final
      ansiColor                      final
      presentUnformatted             final

  public static scala.collection.immutable.Vector<org.scalatest.tools.Fragment> noteProvidedFragments(org.scalatest.events.NoteProvided, boolean, boolean, boolean, boolean, boolean);
    descriptor: (Lorg/scalatest/events/NoteProvided;ZZZZZ)Lscala/collection/immutable/Vector;
    flags: (0x0009) ACC_PUBLIC, ACC_STATIC
    Code:
      stack=7, locals=6, args_size=6
         0: getstatic     #38                 // Field org/scalatest/tools/StringReporter$.MODULE$:Lorg/scalatest/tools/StringReporter$;
         3: aload_0
         4: iload_1
         5: iload_2
         6: iload_3
         7: iload         4
         9: iload         5
        11: invokevirtual #113                // Method org/scalatest/tools/StringReporter$.noteProvidedFragments:(Lorg/scalatest/events/NoteProvided;ZZZZZ)Lscala/collection/immutable/Vector;
        14: areturn
      LocalVariableTable:
        Start  Length  Slot  Name   Signature
            0      15     0 event   Lorg/scalatest/events/NoteProvided;
            0      15     1 presentUnformatted   Z
            0      15     2 presentAllDurations   Z
            0      15     3 presentShortStackTraces   Z
            0      15     4 presentFullStackTraces   Z
            0      15     5 presentFilePathname   Z
    Signature: #111                         // (Lorg/scalatest/events/NoteProvided;ZZZZZ)Lscala/collection/immutable/Vector<Lorg/scalatest/tools/Fragment;>;
    MethodParameters:
      Name                           Flags
      event                          final
      presentUnformatted             final
      presentAllDurations            final
      presentShortStackTraces        final
      presentFullStackTraces         final
      presentFilePathname            final

  public static scala.collection.immutable.Vector<org.scalatest.tools.Fragment> alertProvidedFragments(org.scalatest.events.AlertProvided, boolean, boolean, boolean, boolean, boolean);
    descriptor: (Lorg/scalatest/events/AlertProvided;ZZZZZ)Lscala/collection/immutable/Vector;
    flags: (0x0009) ACC_PUBLIC, ACC_STATIC
    Code:
      stack=7, locals=6, args_size=6
         0: getstatic     #38                 // Field org/scalatest/tools/StringReporter$.MODULE$:Lorg/scalatest/tools/StringReporter$;
         3: aload_0
         4: iload_1
         5: iload_2
         6: iload_3
         7: iload         4
         9: iload         5
        11: invokevirtual #119                // Method org/scalatest/tools/StringReporter$.alertProvidedFragments:(Lorg/scalatest/events/AlertProvided;ZZZZZ)Lscala/collection/immutable/Vector;
        14: areturn
      LocalVariableTable:
        Start  Length  Slot  Name   Signature
            0      15     0 event   Lorg/scalatest/events/AlertProvided;
            0      15     1 presentUnformatted   Z
            0      15     2 presentAllDurations   Z
            0      15     3 presentShortStackTraces   Z
            0      15     4 presentFullStackTraces   Z
            0      15     5 presentFilePathname   Z
    Signature: #117                         // (Lorg/scalatest/events/AlertProvided;ZZZZZ)Lscala/collection/immutable/Vector<Lorg/scalatest/tools/Fragment;>;
    MethodParameters:
      Name                           Flags
      event                          final
      presentUnformatted             final
      presentAllDurations            final
      presentShortStackTraces        final
      presentFullStackTraces         final
      presentFilePathname            final

  public static scala.collection.immutable.Vector<org.scalatest.tools.Fragment> infoProvidedFragments(org.scalatest.events.InfoProvided, org.scalatest.tools.AnsiColor, boolean, boolean, boolean, boolean, boolean);
    descriptor: (Lorg/scalatest/events/InfoProvided;Lorg/scalatest/tools/AnsiColor;ZZZZZ)Lscala/collection/immutable/Vector;
    flags: (0x0009) ACC_PUBLIC, ACC_STATIC
    Code:
      stack=8, locals=7, args_size=7
         0: getstatic     #38                 // Field org/scalatest/tools/StringReporter$.MODULE$:Lorg/scalatest/tools/StringReporter$;
         3: aload_0
         4: aload_1
         5: iload_2
         6: iload_3
         7: iload         4
         9: iload         5
        11: iload         6
        13: invokevirtual #125                // Method org/scalatest/tools/StringReporter$.infoProvidedFragments:(Lorg/scalatest/events/InfoProvided;Lorg/scalatest/tools/AnsiColor;ZZZZZ)Lscala/collection/immutable/Vector;
        16: areturn
      LocalVariableTable:
        Start  Length  Slot  Name   Signature
            0      17     0 event   Lorg/scalatest/events/InfoProvided;
            0      17     1 ansiColor   Lorg/scalatest/tools/AnsiColor;
            0      17     2 presentUnformatted   Z
            0      17     3 presentAllDurations   Z
            0      17     4 presentShortStackTraces   Z
            0      17     5 presentFullStackTraces   Z
            0      17     6 presentFilePathname   Z
    Signature: #123                         // (Lorg/scalatest/events/InfoProvided;Lorg/scalatest/tools/AnsiColor;ZZZZZ)Lscala/collection/immutable/Vector<Lorg/scalatest/tools/Fragment;>;
    MethodParameters:
      Name                           Flags
      event                          final
      ansiColor                      final
      presentUnformatted             final
      presentAllDurations            final
      presentShortStackTraces        final
      presentFullStackTraces         final
      presentFilePathname            final

  public static scala.collection.immutable.Vector<org.scalatest.tools.Fragment> recordedEventFragments(scala.collection.immutable.IndexedSeq<org.scalatest.events.RecordableEvent>, org.scalatest.tools.AnsiColor, boolean, boolean, boolean, boolean, boolean);
    descriptor: (Lscala/collection/immutable/IndexedSeq;Lorg/scalatest/tools/AnsiColor;ZZZZZ)Lscala/collection/immutable/Vector;
    flags: (0x0009) ACC_PUBLIC, ACC_STATIC
    Code:
      stack=8, locals=7, args_size=7
         0: getstatic     #38                 // Field org/scalatest/tools/StringReporter$.MODULE$:Lorg/scalatest/tools/StringReporter$;
         3: aload_0
         4: aload_1
         5: iload_2
         6: iload_3
         7: iload         4
         9: iload         5
        11: iload         6
        13: invokevirtual #132                // Method org/scalatest/tools/StringReporter$.recordedEventFragments:(Lscala/collection/immutable/IndexedSeq;Lorg/scalatest/tools/AnsiColor;ZZZZZ)Lscala/collection/immutable/Vector;
        16: areturn
      LocalVariableTable:
        Start  Length  Slot  Name   Signature
            0      17     0 recordedEvents   Lscala/collection/immutable/IndexedSeq;
            0      17     1 ansiColor   Lorg/scalatest/tools/AnsiColor;
            0      17     2 presentUnformatted   Z
            0      17     3 presentAllDurations   Z
            0      17     4 presentShortStackTraces   Z
            0      17     5 presentFullStackTraces   Z
            0      17     6 presentFilePathname   Z
    Signature: #129                         // (Lscala/collection/immutable/IndexedSeq<Lorg/scalatest/events/RecordableEvent;>;Lorg/scalatest/tools/AnsiColor;ZZZZZ)Lscala/collection/immutable/Vector<Lorg/scalatest/tools/Fragment;>;
    MethodParameters:
      Name                           Flags
      recordedEvents                 final
      ansiColor                      final
      presentUnformatted             final
      presentAllDurations            final
      presentShortStackTraces        final
      presentFullStackTraces         final
      presentFilePathname            final

  public static java.lang.String withPossibleLineNumber(java.lang.String, scala.Option<java.lang.Throwable>, boolean);
    descriptor: (Ljava/lang/String;Lscala/Option;Z)Ljava/lang/String;
    flags: (0x0009) ACC_PUBLIC, ACC_STATIC
    Code:
      stack=4, locals=3, args_size=3
         0: getstatic     #38                 // Field org/scalatest/tools/StringReporter$.MODULE$:Lorg/scalatest/tools/StringReporter$;
         3: aload_0
         4: aload_1
         5: iload_2
         6: invokevirtual #138                // Method org/scalatest/tools/StringReporter$.withPossibleLineNumber:(Ljava/lang/String;Lscala/Option;Z)Ljava/lang/String;
         9: areturn
      LocalVariableTable:
        Start  Length  Slot  Name   Signature
            0      10     0 stringToPrint   Ljava/lang/String;
            0      10     1 throwable   Lscala/Option;
            0      10     2 presentFilePathname   Z
    Signature: #135                         // (Ljava/lang/String;Lscala/Option<Ljava/lang/Throwable;>;Z)Ljava/lang/String;
    MethodParameters:
      Name                           Flags
      stringToPrint                  final
      throwable                      final
      presentFilePathname            final

  public static scala.collection.immutable.Vector<org.scalatest.tools.Fragment> exceptionalFragments(org.scalatest.events.ExceptionalEvent, boolean, boolean, boolean, boolean, boolean);
    descriptor: (Lorg/scalatest/events/ExceptionalEvent;ZZZZZ)Lscala/collection/immutable/Vector;
    flags: (0x0009) ACC_PUBLIC, ACC_STATIC
    Code:
      stack=7, locals=6, args_size=6
         0: getstatic     #38                 // Field org/scalatest/tools/StringReporter$.MODULE$:Lorg/scalatest/tools/StringReporter$;
         3: aload_0
         4: iload_1
         5: iload_2
         6: iload_3
         7: iload         4
         9: iload         5
        11: invokevirtual #144                // Method org/scalatest/tools/StringReporter$.exceptionalFragments:(Lorg/scalatest/events/ExceptionalEvent;ZZZZZ)Lscala/collection/immutable/Vector;
        14: areturn
      LocalVariableTable:
        Start  Length  Slot  Name   Signature
            0      15     0 exceptionalEvent   Lorg/scalatest/events/ExceptionalEvent;
            0      15     1 presentAllDurations   Z
            0      15     2 presentReminderWithShortStackTraces   Z
            0      15     3 presentReminderWithFullStackTraces   Z
            0      15     4 presentReminderWithoutCanceledTests   Z
            0      15     5 presentFilePathname   Z
    Signature: #141                         // (Lorg/scalatest/events/ExceptionalEvent;ZZZZZ)Lscala/collection/immutable/Vector<Lorg/scalatest/tools/Fragment;>;
    MethodParameters:
      Name                           Flags
      exceptionalEvent               final
      presentAllDurations            final
      presentReminderWithShortStackTracesfinal
      presentReminderWithFullStackTracesfinal
      presentReminderWithoutCanceledTestsfinal
      presentFilePathname            final

  public static scala.collection.immutable.Vector<org.scalatest.tools.Fragment> summaryFragments(boolean, scala.Option<java.lang.Object>, scala.Option<org.scalatest.events.Summary>, scala.collection.immutable.Vector<org.scalatest.events.ExceptionalEvent>, boolean, boolean, boolean, boolean, boolean, boolean);
    descriptor: (ZLscala/Option;Lscala/Option;Lscala/collection/immutable/Vector;ZZZZZZ)Lscala/collection/immutable/Vector;
    flags: (0x0009) ACC_PUBLIC, ACC_STATIC
    Code:
      stack=11, locals=10, args_size=10
         0: getstatic     #38                 // Field org/scalatest/tools/StringReporter$.MODULE$:Lorg/scalatest/tools/StringReporter$;
         3: iload_0
         4: aload_1
         5: aload_2
         6: aload_3
         7: iload         4
         9: iload         5
        11: iload         6
        13: iload         7
        15: iload         8
        17: iload         9
        19: invokevirtual #153                // Method org/scalatest/tools/StringReporter$.summaryFragments:(ZLscala/Option;Lscala/Option;Lscala/collection/immutable/Vector;ZZZZZZ)Lscala/collection/immutable/Vector;
        22: areturn
      LocalVariableTable:
        Start  Length  Slot  Name   Signature
            0      23     0 runCompleted   Z
            0      23     1 duration   Lscala/Option;
            0      23     2 summaryOption   Lscala/Option;
            0      23     3 exceptionalEvents   Lscala/collection/immutable/Vector;
            0      23     4 presentAllDurations   Z
            0      23     5 presentReminder   Z
            0      23     6 presentReminderWithShortStackTraces   Z
            0      23     7 presentReminderWithFullStackTraces   Z
            0      23     8 presentReminderWithoutCanceledTests   Z
            0      23     9 presentFilePathname   Z
    Signature: #148                         // (ZLscala/Option<Ljava/lang/Object;>;Lscala/Option<Lorg/scalatest/events/Summary;>;Lscala/collection/immutable/Vector<Lorg/scalatest/events/ExceptionalEvent;>;ZZZZZZ)Lscala/collection/immutable/Vector<Lorg/scalatest/tools/Fragment;>;
    MethodParameters:
      Name                           Flags
      runCompleted                   final
      duration                       final
      summaryOption                  final
      exceptionalEvents              final
      presentAllDurations            final
      presentReminder                final
      presentReminderWithShortStackTracesfinal
      presentReminderWithFullStackTracesfinal
      presentReminderWithoutCanceledTestsfinal
      presentFilePathname            final

  public static scala.collection.immutable.Vector<org.scalatest.tools.Fragment> fragmentsOnError(java.lang.String, scala.Function1<java.lang.Object, java.lang.String>, java.lang.String, scala.Option<java.lang.Throwable>, scala.collection.immutable.IndexedSeq<java.lang.String>, scala.Option<org.scalatest.events.Formatter>, scala.Option<java.lang.String>, scala.Option<java.lang.String>, scala.Option<java.lang.Object>, boolean, boolean, boolean, boolean, boolean, org.scalatest.tools.AnsiColor);
    descriptor: (Ljava/lang/String;Lscala/Function1;Ljava/lang/String;Lscala/Option;Lscala/collection/immutable/IndexedSeq;Lscala/Option;Lscala/Option;Lscala/Option;Lscala/Option;ZZZZZLorg/scalatest/tools/AnsiColor;)Lscala/collection/immutable/Vector;
    flags: (0x0009) ACC_PUBLIC, ACC_STATIC
    Code:
      stack=16, locals=15, args_size=15
         0: getstatic     #38                 // Field org/scalatest/tools/StringReporter$.MODULE$:Lorg/scalatest/tools/StringReporter$;
         3: aload_0
         4: aload_1
         5: aload_2
         6: aload_3
         7: aload         4
         9: aload         5
        11: aload         6
        13: aload         7
        15: aload         8
        17: iload         9
        19: iload         10
        21: iload         11
        23: iload         12
        25: iload         13
        27: aload         14
        29: invokevirtual #159                // Method org/scalatest/tools/StringReporter$.fragmentsOnError:(Ljava/lang/String;Lscala/Function1;Ljava/lang/String;Lscala/Option;Lscala/collection/immutable/IndexedSeq;Lscala/Option;Lscala/Option;Lscala/Option;Lscala/Option;ZZZZZLorg/scalatest/tools/AnsiColor;)Lscala/collection/immutable/Vector;
        32: areturn
      LocalVariableTable:
        Start  Length  Slot  Name   Signature
            0      33     0 noteMessageFun   Ljava/lang/String;
            0      33     1 errorMessageFun   Lscala/Function1;
            0      33     2 message   Ljava/lang/String;
            0      33     3 throwable   Lscala/Option;
            0      33     4 analysis   Lscala/collection/immutable/IndexedSeq;
            0      33     5 formatter   Lscala/Option;
            0      33     6 suiteName   Lscala/Option;
            0      33     7 testName   Lscala/Option;
            0      33     8 duration   Lscala/Option;
            0      33     9 presentUnformatted   Z
            0      33    10 presentAllDurations   Z
            0      33    11 presentShortStackTraces   Z
            0      33    12 presentFullStackTraces   Z
            0      33    13 presentFilePathname   Z
            0      33    14 ansiColor   Lorg/scalatest/tools/AnsiColor;
    Signature: #157                         // (Ljava/lang/String;Lscala/Function1<Ljava/lang/Object;Ljava/lang/String;>;Ljava/lang/String;Lscala/Option<Ljava/lang/Throwable;>;Lscala/collection/immutable/IndexedSeq<Ljava/lang/String;>;Lscala/Option<Lorg/scalatest/events/Formatter;>;Lscala/Option<Ljava/lang/String;>;Lscala/Option<Ljava/lang/String;>;Lscala/Option<Ljava/lang/Object;>;ZZZZZLorg/scalatest/tools/AnsiColor;)Lscala/collection/immutable/Vector<Lorg/scalatest/tools/Fragment;>;
    MethodParameters:
      Name                           Flags
      noteMessageFun                 final
      errorMessageFun                final
      message                        final
      throwable                      final
      analysis                       final
      formatter                      final
      suiteName                      final
      testName                       final
      duration                       final
      presentUnformatted             final
      presentAllDurations            final
      presentShortStackTraces        final
      presentFullStackTraces         final
      presentFilePathname            final
      ansiColor                      final

  public static scala.Option<java.lang.Object> fragmentsWhenNoError$default$9();
    descriptor: ()Lscala/Option;
    flags: (0x0009) ACC_PUBLIC, ACC_STATIC
    Code:
      stack=1, locals=0, args_size=0
         0: getstatic     #38                 // Field org/scalatest/tools/StringReporter$.MODULE$:Lorg/scalatest/tools/StringReporter$;
         3: invokevirtual #162                // Method org/scalatest/tools/StringReporter$.fragmentsWhenNoError$default$9:()Lscala/Option;
         6: areturn
    Signature: #86                          // ()Lscala/Option<Ljava/lang/Object;>;

  public static org.scalatest.tools.AnsiColor fragmentsWhenNoError$default$8();
    descriptor: ()Lorg/scalatest/tools/AnsiColor;
    flags: (0x0009) ACC_PUBLIC, ACC_STATIC
    Code:
      stack=1, locals=0, args_size=0
         0: getstatic     #38                 // Field org/scalatest/tools/StringReporter$.MODULE$:Lorg/scalatest/tools/StringReporter$;
         3: invokevirtual #166                // Method org/scalatest/tools/StringReporter$.fragmentsWhenNoError$default$8:()Lorg/scalatest/tools/AnsiColor;
         6: areturn

  public static scala.collection.immutable.Vector<org.scalatest.tools.Fragment> fragmentsWhenNoError(scala.Function1<java.lang.Object, java.lang.String>, scala.Option<org.scalatest.events.Formatter>, java.lang.String, scala.Option<java.lang.String>, scala.Option<java.lang.String>, boolean, boolean, org.scalatest.tools.AnsiColor, scala.Option<java.lang.Object>);
    descriptor: (Lscala/Function1;Lscala/Option;Ljava/lang/String;Lscala/Option;Lscala/Option;ZZLorg/scalatest/tools/AnsiColor;Lscala/Option;)Lscala/collection/immutable/Vector;
    flags: (0x0009) ACC_PUBLIC, ACC_STATIC
    Code:
      stack=10, locals=9, args_size=9
         0: getstatic     #38                 // Field org/scalatest/tools/StringReporter$.MODULE$:Lorg/scalatest/tools/StringReporter$;
         3: aload_0
         4: aload_1
         5: aload_2
         6: aload_3
         7: aload         4
         9: iload         5
        11: iload         6
        13: aload         7
        15: aload         8
        17: invokevirtual #171                // Method org/scalatest/tools/StringReporter$.fragmentsWhenNoError:(Lscala/Function1;Lscala/Option;Ljava/lang/String;Lscala/Option;Lscala/Option;ZZLorg/scalatest/tools/AnsiColor;Lscala/Option;)Lscala/collection/immutable/Vector;
        20: areturn
      LocalVariableTable:
        Start  Length  Slot  Name   Signature
            0      21     0 messageFun   Lscala/Function1;
            0      21     1 formatter   Lscala/Option;
            0      21     2 suiteName   Ljava/lang/String;
            0      21     3 testName   Lscala/Option;
            0      21     4 message   Lscala/Option;
            0      21     5 presentUnformatted   Z
            0      21     6 presentAllDurations   Z
            0      21     7 ansiColor   Lorg/scalatest/tools/AnsiColor;
            0      21     8 duration   Lscala/Option;
    Signature: #169                         // (Lscala/Function1<Ljava/lang/Object;Ljava/lang/String;>;Lscala/Option<Lorg/scalatest/events/Formatter;>;Ljava/lang/String;Lscala/Option<Ljava/lang/String;>;Lscala/Option<Ljava/lang/String;>;ZZLorg/scalatest/tools/AnsiColor;Lscala/Option<Ljava/lang/Object;>;)Lscala/collection/immutable/Vector<Lorg/scalatest/tools/Fragment;>;
    MethodParameters:
      Name                           Flags
      messageFun                     final
      formatter                      final
      suiteName                      final
      testName                       final
      message                        final
      presentUnformatted             final
      presentAllDurations            final
      ansiColor                      final
      duration                       final

  public static int shortStackTraceSize();
    descriptor: ()I
    flags: (0x0009) ACC_PUBLIC, ACC_STATIC
    Code:
      stack=1, locals=0, args_size=0
         0: getstatic     #38                 // Field org/scalatest/tools/StringReporter$.MODULE$:Lorg/scalatest/tools/StringReporter$;
         3: invokevirtual #175                // Method org/scalatest/tools/StringReporter$.shortStackTraceSize:()I
         6: ireturn

  public scala.collection.mutable.ListBuffer<org.scalatest.events.ExceptionalEvent> reminderEventsBuf();
    descriptor: ()Lscala/collection/mutable/ListBuffer;
    flags: (0x0001) ACC_PUBLIC
    Code:
      stack=1, locals=1, args_size=1
         0: aload_0
         1: getfield      #179                // Field reminderEventsBuf:Lscala/collection/mutable/ListBuffer;
         4: areturn
      LineNumberTable:
        line 46: 0
      LocalVariableTable:
        Start  Length  Slot  Name   Signature
            0       5     0  this   Lorg/scalatest/tools/StringReporter;
    Signature: #177                         // ()Lscala/collection/mutable/ListBuffer<Lorg/scalatest/events/ExceptionalEvent;>;

  public abstract void printPossiblyInColor(org.scalatest.tools.Fragment);
    descriptor: (Lorg/scalatest/tools/Fragment;)V
    flags: (0x0401) ACC_PUBLIC, ACC_ABSTRACT
    MethodParameters:
      Name                           Flags
      fragment                       final

  public abstract void printNoColor(java.lang.String);
    descriptor: (Ljava/lang/String;)V
    flags: (0x0401) ACC_PUBLIC, ACC_ABSTRACT
    MethodParameters:
      Name                           Flags
      text                           final

  public void apply(org.scalatest.events.Event);
    descriptor: (Lorg/scalatest/events/Event;)V
    flags: (0x0001) ACC_PUBLIC
    Code:
      stack=12, locals=5, args_size=2
         0: aload_1
         1: astore_3
         2: aload_3
         3: instanceof    #190                // class org/scalatest/events/ExceptionalEvent
         6: ifeq          58
         9: aload_3
        10: checkcast     #190                // class org/scalatest/events/ExceptionalEvent
        13: astore        4
        15: aload_0
        16: getfield      #192                // Field presentReminder:Z
        19: ifeq          55
        22: aload_0
        23: getfield      #194                // Field presentReminderWithoutCanceledTests:Z
        26: ifeq          36
        29: aload_1
        30: instanceof    #196                // class org/scalatest/events/TestFailed
        33: ifeq          48
        36: aload_0
        37: invokevirtual #198                // Method reminderEventsBuf:()Lscala/collection/mutable/ListBuffer;
        40: aload         4
        42: invokevirtual #204                // Method scala/collection/mutable/ListBuffer.$plus$eq:(Ljava/lang/Object;)Lscala/collection/mutable/Growable;
        45: goto          51
        48: getstatic     #210                // Field scala/runtime/BoxedUnit.UNIT:Lscala/runtime/BoxedUnit;
        51: astore_2
        52: goto          68
        55: goto          61
        58: goto          61
        61: getstatic     #210                // Field scala/runtime/BoxedUnit.UNIT:Lscala/runtime/BoxedUnit;
        64: astore_2
        65: goto          68
        68: aload_2
        69: pop
        70: aload_0
        71: getfield      #212                // Field presentJson:Z
        74: ifeq          88
        77: aload_0
        78: aload_1
        79: invokevirtual #217                // Method org/scalatest/events/Event.toJson:()Ljava/lang/String;
        82: invokevirtual #219                // Method printNoColor:(Ljava/lang/String;)V
        85: goto          144
        88: getstatic     #38                 // Field org/scalatest/tools/StringReporter$.MODULE$:Lorg/scalatest/tools/StringReporter$;
        91: aload_1
        92: aload_0
        93: getfield      #221                // Field presentUnformatted:Z
        96: aload_0
        97: getfield      #223                // Field presentAllDurations:Z
       100: aload_0
       101: getfield      #225                // Field presentShortStackTraces:Z
       104: aload_0
       105: getfield      #227                // Field presentFullStackTraces:Z
       108: aload_0
       109: getfield      #192                // Field presentReminder:Z
       112: aload_0
       113: getfield      #229                // Field presentReminderWithShortStackTraces:Z
       116: aload_0
       117: getfield      #231                // Field presentReminderWithFullStackTraces:Z
       120: aload_0
       121: getfield      #194                // Field presentReminderWithoutCanceledTests:Z
       124: aload_0
       125: getfield      #233                // Field presentFilePathname:Z
       128: aload_0
       129: invokevirtual #198                // Method reminderEventsBuf:()Lscala/collection/mutable/ListBuffer;
       132: invokevirtual #81                 // Method org/scalatest/tools/StringReporter$.fragmentsForEvent:(Lorg/scalatest/events/Event;ZZZZZZZZZLscala/collection/Seq;)Lscala/collection/immutable/Vector;
       135: aload_0
       136: invokedynamic #254,  0            // InvokeDynamic #0:apply:(Lorg/scalatest/tools/StringReporter;)Lscala/Function1;
       141: invokevirtual #260                // Method scala/collection/immutable/Vector.foreach:(Lscala/Function1;)V
       144: return
      StackMapTable: number_of_entries = 9
        frame_type = 254 /* append */
          offset_delta = 36
          locals = [ top, class org/scalatest/events/Event, class org/scalatest/events/ExceptionalEvent ]
        frame_type = 11 /* same */
        frame_type = 66 /* same_locals_1_stack_item */
          stack = [ class java/lang/Object ]
        frame_type = 3 /* same */
        frame_type = 250 /* chop */
          offset_delta = 2
        frame_type = 2 /* same */
        frame_type = 255 /* full_frame */
          offset_delta = 6
          locals = [ class org/scalatest/tools/StringReporter, class org/scalatest/events/Event, class java/lang/Object, class org/scalatest/events/Event ]
          stack = []
        frame_type = 19 /* same */
        frame_type = 55 /* same */
      LineNumberTable:
        line 153: 0
        line 154: 2
        line 155: 22
        line 156: 36
        line 155: 48
        line 154: 55
        line 158: 61
        line 153: 68
        line 161: 70
        line 162: 77
        line 164: 88
        line 165: 91
        line 166: 92
        line 167: 96
        line 168: 100
        line 169: 104
        line 170: 108
        line 171: 112
        line 172: 116
        line 173: 120
        line 174: 124
        line 175: 128
        line 176: 135
      LocalVariableTable:
        Start  Length  Slot  Name   Signature
            0     145     0  this   Lorg/scalatest/tools/StringReporter;
            0     145     1 event   Lorg/scalatest/events/Event;
    MethodParameters:
      Name                           Flags
      event                          final

  public static final void $anonfun$apply$1(org.scalatest.tools.StringReporter, org.scalatest.tools.Fragment);
    descriptor: (Lorg/scalatest/tools/StringReporter;Lorg/scalatest/tools/Fragment;)V
    flags: (0x1019) ACC_PUBLIC, ACC_STATIC, ACC_FINAL, ACC_SYNTHETIC
    Code:
      stack=2, locals=2, args_size=2
         0: aload_0
         1: aload_1
         2: invokevirtual #266                // Method printPossiblyInColor:(Lorg/scalatest/tools/Fragment;)V
         5: return
      LineNumberTable:
        line 177: 0
      LocalVariableTable:
        Start  Length  Slot  Name   Signature
            0       6     0 $this   Lorg/scalatest/tools/StringReporter;
            0       6     1     e   Lorg/scalatest/tools/Fragment;
    MethodParameters:
      Name                           Flags
      $this                          final synthetic
      e                              final

  public org.scalatest.tools.StringReporter(boolean, boolean, boolean, boolean, boolean, boolean, boolean, boolean, boolean, boolean, boolean);
    descriptor: (ZZZZZZZZZZZ)V
    flags: (0x0001) ACC_PUBLIC
    Code:
      stack=3, locals=12, args_size=12
         0: aload_0
         1: iload_1
         2: putfield      #223                // Field presentAllDurations:Z
         5: aload_0
         6: iload_3
         7: putfield      #225                // Field presentShortStackTraces:Z
        10: aload_0
        11: iload         4
        13: putfield      #227                // Field presentFullStackTraces:Z
        16: aload_0
        17: iload         5
        19: putfield      #221                // Field presentUnformatted:Z
        22: aload_0
        23: iload         6
        25: putfield      #192                // Field presentReminder:Z
        28: aload_0
        29: iload         7
        31: putfield      #229                // Field presentReminderWithShortStackTraces:Z
        34: aload_0
        35: iload         8
        37: putfield      #231                // Field presentReminderWithFullStackTraces:Z
        40: aload_0
        41: iload         9
        43: putfield      #194                // Field presentReminderWithoutCanceledTests:Z
        46: aload_0
        47: iload         10
        49: putfield      #233                // Field presentFilePathname:Z
        52: aload_0
        53: iload         11
        55: putfield      #212                // Field presentJson:Z
        58: aload_0
        59: invokespecial #273                // Method java/lang/Object."<init>":()V
        62: aload_0
        63: new           #200                // class scala/collection/mutable/ListBuffer
        66: dup
        67: invokespecial #274                // Method scala/collection/mutable/ListBuffer."<init>":()V
        70: putfield      #179                // Field reminderEventsBuf:Lscala/collection/mutable/ListBuffer;
        73: return
      LineNumberTable:
        line 33: 0
        line 35: 5
        line 36: 10
        line 37: 16
        line 38: 22
        line 39: 28
        line 40: 34
        line 41: 40
        line 42: 46
        line 43: 52
        line 44: 58
        line 46: 62
        line 32: 73
      LocalVariableTable:
        Start  Length  Slot  Name   Signature
            0      74     0  this   Lorg/scalatest/tools/StringReporter;
            0      74     1 presentAllDurations   Z
            0      74     2 presentInColor   Z
            0      74     3 presentShortStackTraces   Z
            0      74     4 presentFullStackTraces   Z
            0      74     5 presentUnformatted   Z
            0      74     6 presentReminder   Z
            0      74     7 presentReminderWithShortStackTraces   Z
            0      74     8 presentReminderWithFullStackTraces   Z
            0      74     9 presentReminderWithoutCanceledTests   Z
            0      74    10 presentFilePathname   Z
            0      74    11 presentJson   Z
    MethodParameters:
      Name                           Flags
      presentAllDurations            final
      presentInColor                 final
      presentShortStackTraces        final
      presentFullStackTraces         final
      presentUnformatted             final
      presentReminder                final
      presentReminderWithShortStackTracesfinal
      presentReminderWithFullStackTracesfinal
      presentReminderWithoutCanceledTestsfinal
      presentFilePathname            final
      presentJson                    final

  public static final java.lang.Object $anonfun$apply$1$adapted(org.scalatest.tools.StringReporter, org.scalatest.tools.Fragment);
    descriptor: (Lorg/scalatest/tools/StringReporter;Lorg/scalatest/tools/Fragment;)Ljava/lang/Object;
    flags: (0x1019) ACC_PUBLIC, ACC_STATIC, ACC_FINAL, ACC_SYNTHETIC
    Code:
      stack=2, locals=2, args_size=2
         0: aload_0
         1: aload_1
         2: invokestatic  #276                // Method $anonfun$apply$1:(Lorg/scalatest/tools/StringReporter;Lorg/scalatest/tools/Fragment;)V
         5: getstatic     #210                // Field scala/runtime/BoxedUnit.UNIT:Lscala/runtime/BoxedUnit;
         8: areturn
      LineNumberTable:
        line 176: 0
      LocalVariableTable:
        Start  Length  Slot  Name   Signature
            0       9     0 $this   Lorg/scalatest/tools/StringReporter;
            0       9     1     e   Lorg/scalatest/tools/Fragment;
    MethodParameters:
      Name                           Flags
      $this                          final
      e                              final

  private static java.lang.Object $deserializeLambda$(java.lang.invoke.SerializedLambda);
    descriptor: (Ljava/lang/invoke/SerializedLambda;)Ljava/lang/Object;
    flags: (0x100a) ACC_PRIVATE, ACC_STATIC, ACC_SYNTHETIC
    Code:
      stack=1, locals=1, args_size=1
         0: aload_0
         1: invokedynamic #288,  0            // InvokeDynamic #1:lambdaDeserialize:(Ljava/lang/invoke/SerializedLambda;)Ljava/lang/Object;
         6: areturn
}
InnerClasses:
  public static final #15= #12 of #14;    // Lookup=class java/lang/invoke/MethodHandles$Lookup of class java/lang/invoke/MethodHandles
SourceFile: "StringReporter.scala"
RuntimeVisibleAnnotations:
  0: #8(#9=s#10)
    scala.reflect.ScalaSignature(
      bytes="\u0006\u0005\recAB\u001a5\u0003\u00031$\b\u0003\u0005F\u0001\t\u0005\t\u0015!\u0003H\u0011!Q\u0005A!A!\u0002\u00139\u0005\u0002C&\u0001\u0005\u0003\u0005\u000b\u0011B$\t\u00111\u0003!\u0011!Q\u0001\n\u001dC\u0001\"\u0014\u0001\u0003\u0002\u0003\u0006Ia\u0012\u0005\t\u001d\u0002\u0011\t\u0011)A\u0005\u000f\"Aq\n\u0001B\u0001B\u0003%q\t\u0003\u0005Q\u0001\t\u0005\t\u0015!\u0003H\u0011!\t\u0006A!A!\u0002\u00139\u0005\u0002\u0003*\u0001\u0005\u0003\u0005\u000b\u0011B$\t\u0011M\u0003!\u0011!Q\u0001\n\u001dCQ\u0001\u0016\u0001\u0005\u0002UCqa\u0019\u0001C\u0002\u0013\u0005A\r\u0003\u0004t\u0001\u0001\u0006I!\u001a\u0005\u0006i\u00021\t\"\u001e\u0005\u0006}\u00021\tb \u0005\b\u00037\u0001A\u0011AA\u000f\u000f!\tI\u0003\u000eE\u0001m\u0005-baB\u001a5\u0011\u00031\u0014Q\u0006\u0005\u0007)N!\t!a\f\t\u0013\u0005E2C1A\u0005\u0002\u0005M\u0002\u0002CA\u001e\'\u0001\u0006I!!\u000e\t\u000f\u0005u2\u0003\"\u0001\u0002@!I\u00111T\n\u0012\u0002\u0013\u0005\u0011Q\u0014\u0005\n\u0003g\u001b\u0012\u0013!C\u0001\u0003kCq!!/\u0014\t\u0003\tY\fC\u0004\u0002xN!\t!!?\t\u000f\t}1\u0003\"\u0001\u0003\"!9!\u0011G\n\u0005\u0002\tM\u0002b\u0002B\u001f\'\u0011\u0005!q\b\u0005\b\u00053\u001aB\u0011\u0001B.\u0011\u001d\u0011\th\u0005C\u0001\u0005gBqAa\"\u0014\t\u0003\u0011I\tC\u0004\u0003\u001eN!\tAa(\t\u000f\t56\u0003\"\u0001\u00030\"9!QX\n\u0005\u0002\t}\u0006\"\u0003Bi\'E\u0005I\u0011AA[\u0011\u001d\u0011\u0019n\u0005C\u0001\u0005+DqAa>\u0014\t\u0003\u0011I\u0010C\u0005\u0004\u0018M\u0011\r\u0011\"\u0002\u0004\u001a!A1\u0011E\n!\u0002\u001b\u0019Y\u0002C\u0005\u0004$M\u0011\r\u0011\"\u0002\u0004&!A1QF\n!\u0002\u001b\u00199\u0003C\u0005\u00040M\u0011\r\u0011\"\u0002\u00042!A1\u0011H\n!\u0002\u001b\u0019\u0019\u0004C\u0005\u0004<M\u0011\r\u0011\"\u0002\u0004>!A1QI\n!\u0002\u001b\u0019y\u0004C\u0005\u0004HM\u0011\r\u0011\"\u0002\u0004J!A1\u0011K\n!\u0002\u001b\u0019Y\u0005C\u0004\u0004TM!\ta!\u0016\u0003\u001dM#(/\u001b8h%\u0016\u0004xN\u001d;fe*\u0011QGN\u0001\u0006i>|Gn\u001d\u0006\u0003oa\n\u0011b]2bY\u0006$Xm\u001d;\u000b\u0003e\n1a\u001c:h\'\r\u00011(\u0011\t\u0003y}j\u0011!\u0010\u0006\u0002}\u0005)1oY1mC&\u0011\u0001)\u0010\u0002\u0007\u0003:L(+\u001a4\u0011\u0005\t\u001bU\"\u0001\u001c\n\u0005\u00113$a\u0005*fg>,(oY3gk2\u0014V\r]8si\u0016\u0014\u0018a\u00059sKN,g\u000e^!mY\u0012+(/\u0019;j_:\u001c8\u0001\u0001\t\u0003y!K!!S\u001f\u0003\u000f\t{w\u000e\\3b]\u0006q\u0001O]3tK:$\u0018J\\\"pY>\u0014\u0018a\u00069sKN,g\u000e^*i_J$8\u000b^1dWR\u0013\u0018mY3t\u0003Y\u0001(/Z:f]R4U\u000f\u001c7Ti\u0006\u001c7\u000e\u0016:bG\u0016\u001c\u0018A\u00059sKN,g\u000e^+oM>\u0014X.\u0019;uK\u0012\fq\u0002\u001d:fg\u0016tGOU3nS:$WM]\u0001$aJ,7/\u001a8u%\u0016l\u0017N\u001c3fe^KG\u000f[*i_J$8\u000b^1dWR\u0013\u0018mY3t\u0003\t\u0002(/Z:f]R\u0014V-\\5oI\u0016\u0014x+\u001b;i\rVdGn\u0015;bG.$&/Y2fg\u0006\u0019\u0003O]3tK:$(+Z7j]\u0012,\'oV5uQ>,HoQ1oG\u0016dW\r\u001a+fgR\u001c\u0018a\u00059sKN,g\u000e\u001e$jY\u0016\u0004\u0016\r\u001e5oC6,\u0017a\u00039sKN,g\u000e\u001e&t_:\fa\u0001P5oSRtD\u0003\u0004,Y3j[F,\u00180`A\u0006\u0014\u0007CA,\u0001\u001b\u0005!\u0004\"B#\r\u0001\u00049\u0005\"\u0002&\r\u0001\u00049\u0005\"B&\r\u0001\u00049\u0005\"\u0002\'\r\u0001\u00049\u0005\"B\'\r\u0001\u00049\u0005\"\u0002(\r\u0001\u00049\u0005\"B(\r\u0001\u00049\u0005\"\u0002)\r\u0001\u00049\u0005\"B)\r\u0001\u00049\u0005\"\u0002*\r\u0001\u00049\u0005\"B*\r\u0001\u00049\u0015!\u0005:f[&tG-\u001a:Fm\u0016tGo\u001d\"vMV\tQ\rE\u0002gW6l\u0011a\u001a\u0006\u0003Q&\fq!\\;uC\ndWM\u0003\u0002k{\u0005Q1m\u001c7mK\u000e$\u0018n\u001c8\n\u00051<\'A\u0003\'jgR\u0014UO\u001a4feB\u0011a.]\u0007\u0002_*\u0011\u0001ON\u0001\u0007KZ,g\u000e^:\n\u0005I|\'\u0001E#yG\u0016\u0004H/[8oC2,e/\u001a8u\u0003I\u0011X-\\5oI\u0016\u0014XI^3oiN\u0014UO\u001a\u0011\u0002)A\u0014\u0018N\u001c;Q_N\u001c\u0018N\u00197z\u0013:\u001cu\u000e\\8s)\t1\u0018\u0010\u0005\u0002=o&\u0011\u00010\u0010\u0002\u0005+:LG\u000fC\u0003{\u001f\u0001\u000710\u0001\u0005ge\u0006<W.\u001a8u!\t9F0\u0003\u0002~i\tAaI]1h[\u0016tG/\u0001\u0007qe&tGOT8D_2|\'\u000fF\u0002w\u0003\u0003Aq!a\u0001\u0011\u0001\u0004\t)!\u0001\u0003uKb$\b\u0003BA\u0004\u0003+qA!!\u0003\u0002\u0012A\u0019\u00111B\u001f\u000e\u0005\u00055!bAA\b\r\u00061AH]8pizJ1!a\u0005>\u0003\u0019\u0001&/\u001a3fM&!\u0011qCA\r\u0005\u0019\u0019FO]5oO*\u0019\u00111C\u001f\u0002\u000b\u0005\u0004\b\u000f\\=\u0015\u0007Y\fy\u0002C\u0004\u0002\"E\u0001\r!a\t\u0002\u000b\u00154XM\u001c;\u0011\u00079\f)#C\u0002\u0002(=\u0014Q!\u0012<f]R\fab\u0015;sS:<\'+\u001a9peR,\'\u000f\u0005\u0002X\'M\u00111c\u000f\u000b\u0003\u0003W\t1c\u001d5peR\u001cF/Y2l)J\f7-Z*ju\u0016,\"!!\u000e\u0011\u0007q\n9$C\u0002\u0002:u\u00121!\u00138u\u0003Q\u0019\bn\u001c:u\'R\f7m\u001b+sC\u000e,7+\u001b>fA\u0005!bM]1h[\u0016tGo],iK:tu.\u0012:s_J$B#!\u0011\u0002T\u0005\r\u00141OA<\u0003{\n\t)a!\u0002\u0006\u0006=\u0005#BA\"\u0003\u001bZh\u0002BA#\u0003\u0013rA!a\u0003\u0002H%\ta(C\u0002\u0002Lu\nq\u0001]1dW\u0006<W-\u0003\u0003\u0002P\u0005E#A\u0002,fGR|\'OC\u0002\u0002LuBq!!\u0016\u0018\u0001\u0004\t9&\u0001\u0006nKN\u001c\u0018mZ3Gk:\u0004r\u0001PA-\u0003;\n)!C\u0002\u0002\\u\u0012\u0011BR;oGRLwN\\\u0019\u0011\u0007q\ny&C\u0002\u0002bu\u00121!\u00118z\u0011\u001d\t)g\u0006a\u0001\u0003O\n\u0011BZ8s[\u0006$H/\u001a:\u0011\u000bq\nI\'!\u001c\n\u0007\u0005-TH\u0001\u0004PaRLwN\u001c\t\u0004]\u0006=\u0014bAA9_\nIai\u001c:nCR$XM\u001d\u0005\b\u0003k:\u0002\u0019AA\u0003\u0003%\u0019X/\u001b;f\u001d\u0006lW\rC\u0004\u0002z]\u0001\r!a\u001f\u0002\u0011Q,7\u000f\u001e(b[\u0016\u0004R\u0001PA5\u0003\u000bAq!a \u0018\u0001\u0004\tY(A\u0004nKN\u001c\u0018mZ3\t\u000b5;\u0002\u0019A$\t\u000b\u0015;\u0002\u0019A$\t\u0013\u0005\u001du\u0003%AA\u0002\u0005%\u0015!C1og&\u001cu\u000e\\8s!\r9\u00161R\u0005\u0004\u0003\u001b#$!C!og&\u001cu\u000e\\8s\u0011%\t\tj\u0006I\u0001\u0002\u0004\t\u0019*\u0001\u0005ekJ\fG/[8o!\u0015a\u0014\u0011NAK!\ra\u0014qS\u0005\u0004\u00033k$\u0001\u0002\'p]\u001e\faD\u001a:bO6,g\u000e^:XQ\u0016tgj\\#se>\u0014H\u0005Z3gCVdG\u000f\n\u001d\u0016\u0005\u0005}%\u0006BAE\u0003C[#!a)\u0011\t\u0005\u0015\u0016qV\u0007\u0003\u0003OSA!!+\u0002,\u0006IQO\\2iK\u000e\\W\r\u001a\u0006\u0004\u0003[k\u0014AC1o]>$\u0018\r^5p]&!\u0011\u0011WAT\u0005E)hn\u00195fG.,GMV1sS\u0006t7-Z\u0001\u001fMJ\fw-\\3oiN<\u0006.\u001a8O_\u0016\u0013(o\u001c:%I\u00164\u0017-\u001e7uIe*\"!a.+\t\u0005M\u0015\u0011U\u0001\u0011MJ\fw-\\3oiN|e.\u0012:s_J$\u0002%!\u0011\u0002>\u0006\u0005\u0017QYAd\u0003\'\f\u0019/!:\u0002h\u0006%\u00181^Aw\u0003_\f\t0a=\u0002v\"9\u0011q\u0018\u000eA\u0002\u0005\u0015\u0011A\u00048pi\u0016lUm]:bO\u00164UO\u001c\u0005\b\u0003\u0007T\u0002\u0019AA,\u0003=)\'O]8s\u001b\u0016\u001c8/Y4f\rVt\u0007bBA@5\u0001\u0007\u0011Q\u0001\u0005\b\u0003\u0013T\u0002\u0019AAf\u0003%!\bN]8xC\ndW\rE\u0003=\u0003S\ni\r\u0005\u0003\u0002D\u0005=\u0017\u0002BAi\u0003#\u0012\u0011\u0002\u00165s_^\f\'\r\\3\t\u000f\u0005U\'\u00041\u0001\u0002X\u0006A\u0011M\\1msNL7\u000f\u0005\u0004\u0002Z\u0006}\u0017QA\u0007\u0003\u00037T1!!8j\u0003%IW.\\;uC\ndW-\u0003\u0003\u0002b\u0006m\'AC%oI\u0016DX\rZ*fc\"9\u0011Q\r\u000eA\u0002\u0005\u001d\u0004bBA;5\u0001\u0007\u00111\u0010\u0005\b\u0003sR\u0002\u0019AA>\u0011\u001d\t\tJ\u0007a\u0001\u0003\'CQ!\u0014\u000eA\u0002\u001dCQ!\u0012\u000eA\u0002\u001dCQa\u0013\u000eA\u0002\u001dCQ\u0001\u0014\u000eA\u0002\u001dCQA\u0015\u000eA\u0002\u001dCq!a\"\u001b\u0001\u0004\tI)\u0001\ttk6l\u0017M]=Ge\u0006<W.\u001a8ugR1\u0012\u0011IA~\u0003\u007f\u0014\tA!\u0004\u0003\u0014\tU!q\u0003B\r\u00057\u0011i\u0002\u0003\u0004\u0002~n\u0001\raR\u0001\reVt7i\\7qY\u0016$X\r\u001a\u0005\b\u0003#[\u0002\u0019AAJ\u0011\u001d\u0011\u0019a\u0007a\u0001\u0005\u000b\tQb];n[\u0006\u0014\u0018p\u00149uS>t\u0007#\u0002\u001f\u0002j\t\u001d\u0001c\u00018\u0003\n%\u0019!1B8\u0003\u000fM+X.\\1ss\"9!qB\u000eA\u0002\tE\u0011!E3yG\u0016\u0004H/[8oC2,e/\u001a8ugB)\u00111IA\'[\")Qi\u0007a\u0001\u000f\")aj\u0007a\u0001\u000f\")qj\u0007a\u0001\u000f\")\u0001k\u0007a\u0001\u000f\")\u0011k\u0007a\u0001\u000f\")!k\u0007a\u0001\u000f\u0006!R\r_2faRLwN\\1m\rJ\fw-\\3oiN$b\"!\u0011\u0003$\t\u001d\"\u0011\u0006B\u0016\u0005[\u0011y\u0003\u0003\u0004\u0003&q\u0001\r!\\\u0001\u0011Kb\u001cW\r\u001d;j_:\fG.\u0012<f]RDQ!\u0012\u000fA\u0002\u001dCQa\u0014\u000fA\u0002\u001dCQ\u0001\u0015\u000fA\u0002\u001dCQ!\u0015\u000fA\u0002\u001dCQA\u0015\u000fA\u0002\u001d\u000bac^5uQB{7o]5cY\u0016d\u0015N\\3Ok6\u0014WM\u001d\u000b\t\u0003\u000b\u0011)D!\u000f\u0003<!9!qG\u000fA\u0002\u0005\u0015\u0011!D:ue&tw\rV8Qe&tG\u000fC\u0004\u0002Jv\u0001\r!a3\t\u000bIk\u0002\u0019A$\u0002-I,7m\u001c:eK\u0012,e/\u001a8u\rJ\fw-\\3oiN$\u0002#!\u0011\u0003B\t5#q\nB)\u0005\'\u0012)Fa\u0016\t\u000f\t\rc\u00041\u0001\u0003F\u0005q!/Z2pe\u0012,G-\u0012<f]R\u001c\bCBAm\u0003?\u00149\u0005E\u0002o\u0005\u0013J1Aa\u0013p\u0005=\u0011VmY8sI\u0006\u0014G.Z#wK:$\bbBAD=\u0001\u0007\u0011\u0011\u0012\u0005\u0006\u001bz\u0001\ra\u0012\u0005\u0006\u000bz\u0001\ra\u0012\u0005\u0006\u0017z\u0001\ra\u0012\u0005\u0006\u0019z\u0001\ra\u0012\u0005\u0006%z\u0001\raR\u0001\u0016S:4w\u000e\u0015:pm&$W\r\u001a$sC\u001elWM\u001c;t)A\t\tE!\u0018\u0003f\t\u001d$\u0011\u000eB6\u0005[\u0012y\u0007C\u0004\u0002\"}\u0001\rAa\u0018\u0011\u00079\u0014\t\'C\u0002\u0003d=\u0014A\"\u00138g_B\u0013xN^5eK\u0012Dq!a\" \u0001\u0004\tI\tC\u0003N?\u0001\u0007q\tC\u0003F?\u0001\u0007q\tC\u0003L?\u0001\u0007q\tC\u0003M?\u0001\u0007q\tC\u0003S?\u0001\u0007q)\u0001\fbY\u0016\u0014H\u000f\u0015:pm&$W\r\u001a$sC\u001elWM\u001c;t)9\t\tE!\u001e\u0003~\t}$\u0011\u0011BB\u0005\u000bCq!!\t!\u0001\u0004\u00119\bE\u0002o\u0005sJ1Aa\u001fp\u00055\tE.\u001a:u!J|g/\u001b3fI\")Q\n\ta\u0001\u000f\")Q\t\ta\u0001\u000f\")1\n\ta\u0001\u000f\")A\n\ta\u0001\u000f\")!\u000b\ta\u0001\u000f\u0006)bn\u001c;f!J|g/\u001b3fI\u001a\u0013\u0018mZ7f]R\u001cHCDA!\u0005\u0017\u0013\u0019J!&\u0003\u0018\ne%1\u0014\u0005\b\u0003C\t\u0003\u0019\u0001BG!\rq\'qR\u0005\u0004\u0005#{\'\u0001\u0004(pi\u0016\u0004&o\u001c<jI\u0016$\u0007\"B\'\"\u0001\u00049\u0005\"B#\"\u0001\u00049\u0005\"B&\"\u0001\u00049\u0005\"\u0002\'\"\u0001\u00049\u0005\"\u0002*\"\u0001\u00049\u0015AH7be.,\b\u000f\u0015:pm&$W\rZ(qi&|g.\u00197Ge\u0006<W.\u001a8u)!\t\tE!)\u0003*\n-\u0006bBA\u0011E\u0001\u0007!1\u0015\t\u0004]\n\u0015\u0016b\u0001BT_\nqQ*\u0019:lkB\u0004&o\u001c<jI\u0016$\u0007bBADE\u0001\u0007\u0011\u0011\u0012\u0005\u0006\u001b\n\u0002\raR\u0001\u0018gR\u0014\u0018N\\4U_B\u0013\u0018N\u001c;XQ\u0016tW*\u0019:lkB$BB!-\u00034\nU&q\u0017B]\u0005w\u0003b!a\u0011\u0002N\u0005\u0015\u0001bBA3G\u0001\u0007\u0011q\r\u0005\b\u0003k\u001a\u0003\u0019AA>\u0011\u001d\tIh\ta\u0001\u0003wBq!a\u0001$\u0001\u0004\t)\u0001C\u0003NG\u0001\u0007q)\u0001\rtiJLgn\u001a+p!JLg\u000e^,iK:tu.\u0012:s_J$\"C!-\u0003B\n\r\'Q\u0019Bd\u0005\u0013\u0014YM!4\u0003P\"9\u0011Q\u000b\u0013A\u0002\u0005]\u0003bBA3I\u0001\u0007\u0011q\r\u0005\b\u0003k\"\u0003\u0019AA\u0003\u0011\u001d\tI\b\na\u0001\u0003wBq!a %\u0001\u0004\tY\bC\u0003FI\u0001\u0007q\tC\u0003NI\u0001\u0007q\tC\u0005\u0002\u0012\u0012\u0002\n\u00111\u0001\u0002\u0014\u0006\u00113\u000f\u001e:j]\u001e$v\u000e\u0015:j]R<\u0006.\u001a8O_\u0016\u0013(o\u001c:%I\u00164\u0017-\u001e7uIa\n\u0011C\u001a:bO6,g\u000e^:G_J,e/\u001a8u)a\t\tEa6\u0003Z\nm\'Q\u001cBp\u0005C\u0014\u0019O!:\u0003h\n%(1\u001e\u0005\b\u0003C1\u0003\u0019AA\u0012\u0011\u0015ie\u00051\u0001H\u0011\u0015)e\u00051\u0001H\u0011\u0015Ye\u00051\u0001H\u0011\u0015ae\u00051\u0001H\u0011\u0015qe\u00051\u0001H\u0011\u0015ye\u00051\u0001H\u0011\u0015\u0001f\u00051\u0001H\u0011\u0015\tf\u00051\u0001H\u0011\u0015\u0011f\u00051\u0001H\u0011\u001d\u0011iO\na\u0001\u0005_\faB]3nS:$WM]#wK:$8\u000fE\u0003\u0003r\nMX.D\u0001j\u0013\r\u0011)0\u001b\u0002\u0004\'\u0016\f\u0018!F:ue&twm\u001d+p!JLg\u000e^(o\u000bJ\u0014xN\u001d\u000b\u001f\u0005c\u0013YP!@\u0003\u0000\u000e\u000511AB\u0003\u0007\u000f\u0019Iaa\u0003\u0004\u000e\r=1\u0011CB\n\u0007+Aq!a0(\u0001\u0004\t)\u0001C\u0004\u0002D\u001e\u0002\r!a\u0016\t\u000f\u0005}t\u00051\u0001\u0002\u0006!9\u0011\u0011Z\u0014A\u0002\u0005-\u0007bBAkO\u0001\u0007\u0011q\u001b\u0005\b\u0003K:\u0003\u0019AA4\u0011\u001d\t)h\na\u0001\u0003wBq!!\u001f(\u0001\u0004\tY\bC\u0004\u0002\u0012\u001e\u0002\r!a%\t\u000b5;\u0003\u0019A$\t\u000b\u0015;\u0003\u0019A$\t\u000b-;\u0003\u0019A$\t\u000b1;\u0003\u0019A$\t\u000bI;\u0003\u0019A$\u0002\u0013\u0005t7/\u001b*fg\u0016$XCAB\u000e\u001f\t\u0019i\"\t\u0002\u0004 \u0005!1d\u0017\u0019n\u0003)\tgn]5SKN,G\u000fI\u0001\nC:\u001c\u0018n\u0012:fK:,\"aa\n\u0010\u0005\r%\u0012EAB\u0016\u0003\u0015Y2l\r\u001an\u0003)\tgn]5He\u0016,g\u000eI\u0001\tC:\u001c\u0018nQ=b]V\u001111G\b\u0003\u0007k\t#aa\u000e\u0002\u000bmY6GN7\u0002\u0013\u0005t7/[\"zC:\u0004\u0013AC1og&LV\r\u001c7poV\u00111qH\b\u0003\u0007\u0003\n#aa\u0011\u0002\u000bmY6gM7\u0002\u0017\u0005t7/[-fY2|w\u000fI\u0001\bC:\u001c\u0018NU3e+\t\u0019Ye\u0004\u0002\u0004N\u0005\u00121qJ\u0001\u00067m\u001b\u0014\'\\\u0001\tC:\u001c\u0018NU3eA\u0005\u0011R.Y6f\tV\u0014\u0018\r^5p]N#(/\u001b8h)\u0011\t)aa\u0016\t\u000f\u0005E%\u00071\u0001\u0002\u0016\u0002"
    )
BootstrapMethods:
  0: #251 REF_invokeStatic java/lang/invoke/LambdaMetafactory.altMetafactory:(Ljava/lang/invoke/MethodHandles$Lookup;Ljava/lang/String;Ljava/lang/invoke/MethodType;[Ljava/lang/Object;)Ljava/lang/invoke/CallSite;
    Method arguments:
      #235 (Ljava/lang/Object;)Ljava/lang/Object;
      #240 REF_invokeStatic org/scalatest/tools/StringReporter.$anonfun$apply$1$adapted:(Lorg/scalatest/tools/StringReporter;Lorg/scalatest/tools/Fragment;)Ljava/lang/Object;
      #242 (Lorg/scalatest/tools/Fragment;)Ljava/lang/Object;
      #243 5
      #244 1
      #242 (Lorg/scalatest/tools/Fragment;)Ljava/lang/Object;
  1: #285 REF_invokeStatic scala/runtime/LambdaDeserialize.bootstrap:(Ljava/lang/invoke/MethodHandles$Lookup;Ljava/lang/String;Ljava/lang/invoke/MethodType;[Ljava/lang/invoke/MethodHandle;)Ljava/lang/invoke/CallSite;
    Method arguments:
      #240 REF_invokeStatic org/scalatest/tools/StringReporter.$anonfun$apply$1$adapted:(Lorg/scalatest/tools/StringReporter;Lorg/scalatest/tools/Fragment;)Ljava/lang/Object;
  ScalaInlineInfo: length = 0x27 (unknown attribute)
   01 00 00 07 01 05 01 06 01 00 EC 00 ED 01 01 0C
   01 0D 00 00 BB 00 BC 00 00 B9 00 BA 00 00 B6 00
   B7 00 00 1B 00 B0 00
  ScalaSig: length = 0x3 (unknown attribute)
   05 02 00
