Classfile /Users/mw/Projects/slang-braindump/.jar/jar8/assemble/slang-braindump/assemble/content/org/scalatest/tools/SuiteParam.class
  Last modified May 29, 2022; size 7693 bytes
  SHA-256 checksum 016f4445c9edebb2ae976bc2f42a3f2e04d4e1588e460b3e1b8d6c2a420d11d9
  Compiled from "SuiteParam.scala"
public class org.scalatest.tools.SuiteParam implements scala.Product,java.io.Serializable
  minor version: 0
  major version: 52
  flags: (0x0021) ACC_PUBLIC, ACC_SUPER
  this_class: #2                          // org/scalatest/tools/SuiteParam
  super_class: #4                         // java/lang/Object
  interfaces: 2, fields: 6, methods: 28, attributes: 4
Constant pool:
    #1 = Utf8               org/scalatest/tools/SuiteParam
    #2 = Class              #1            // org/scalatest/tools/SuiteParam
    #3 = Utf8               java/lang/Object
    #4 = Class              #3            // java/lang/Object
    #5 = Utf8               scala/Product
    #6 = Class              #5            // scala/Product
    #7 = Utf8               java/io/Serializable
    #8 = Class              #7            // java/io/Serializable
    #9 = Utf8               SuiteParam.scala
   #10 = Utf8               Lscala/reflect/ScalaSignature;
   #11 = Utf8               bytes
   #12 = Utf8               \u0006\u0005\u0005\u001df!\u0002\u0012$\u0001\u000eJ\u0003\u0002\u0003!\u0001\u0005+\u0007I\u0011A!\t\u0011)\u0003!\u0011#Q\u0001\n\tC\u0001b\u0013\u0001\u0003\u0016\u0004%\t\u0001\u0014\u0005\t!\u0002\u0011\t\u0012)A\u0005\u001b\"A\u0011\u000b\u0001BK\u0002\u0013\u0005A\n\u0003\u0005S\u0001\tE\t\u0015!\u0003N\u0011!\u0019\u0006A!f\u0001\n\u0003!\u0006\u0002\u0003.\u0001\u0005#\u0005\u000b\u0011B+\t\u000bm\u0003A\u0011\u0001/\t\u0011\t\u0004\u0001R1A\u0005\n\rDQa\u001b\u0001\u0005\u00021DQ\u0001\u001d\u0001\u0005\u0002EDq\u0001\u001e\u0001\u0002\u0002\u0013\u0005Q\u000fC\u0004{\u0001E\u0005I\u0011A>\t\u0013\u00055\u0001!%A\u0005\u0002\u0005=\u0001\"CA\n\u0001E\u0005I\u0011AA\b\u0011%\t)\u0002AI\u0001\n\u0003\t9\u0002\u0003\u0005\u0002\u001c\u0001\t\t\u0011\"\u0011d\u0011%\ti\u0002AA\u0001\n\u0003\ty\u0002C\u0005\u0002(\u0001\t\t\u0011\"\u0001\u0002*!I\u0011Q\u0007\u0001\u0002\u0002\u0013\u0005\u0013q\u0007\u0005\n\u0003\u000b\u0002\u0011\u0011!C\u0001\u0003\u000fB\u0011\"a\u0013\u0001\u0003\u0003%\t%!\u0014\t\u0013\u0005E\u0003!!A\u0005B\u0005M\u0003\"CA+\u0001\u0005\u0005I\u0011IA,\u0011%\tI\u0006AA\u0001\n\u0003\nYf\u0002\u0006\u0002`\r\n\t\u0011#\u0001$\u0003C2\u0011BI\u0012\u0002\u0002#\u00051%a\u0019\t\rmcB\u0011AA>\u0011%\t)\u0006HA\u0001\n\u000b\n9\u0006C\u0005\u0002~q\t\t\u0011\"!\u0002\u0000!I\u0011\u0011\u0012\u000f\u0002\u0002\u0013\u0005\u00151\u0012\u0005\n\u0003;c\u0012\u0011!C\u0005\u0003?\u0013!bU;ji\u0016\u0004\u0016M]1n\u0015\t!S%A\u0003u_>d7O\u0003\u0002\'O\u0005I1oY1mCR,7\u000f\u001e\u0006\u0002Q\u0005\u0019qN]4\u0014\t\u0001Q\u0003g\r\t\u0003W9j\u0011\u0001\f\u0006\u0002[\u0005)1oY1mC&\u0011q\u0006\f\u0002\u0007\u0003:L(+\u001a4\u0011\u0005-\n\u0014B\u0001\u001a-\u0005\u001d\u0001&o\u001c3vGR\u0004\"\u0001N\u001f\u000f\u0005UZdB\u0001\u001c;\u001b\u00059$B\u0001\u001d:\u0003\u0019a$o\\8u}\r\u0001\u0011\"A\u0017\n\u0005qb\u0013a\u00029bG.\fw-Z\u0005\u0003}}\u0012AbU3sS\u0006d\u0017N_1cY\u0016T!\u0001\u0010\u0017\u0002\u0013\rd\u0017m]:OC6,W#\u0001\"\u0011\u0005\r;eB\u0001#F!\t1D&\u0003\u0002GY\u00051\u0001K]3eK\u001aL!\u0001S%\u0003\rM#(/\u001b8h\u0015\t1E&\u0001\u0006dY\u0006\u001c8OT1nK\u0002\n\u0011\u0002^3ti:\u000bW.Z:\u0016\u00035\u00032a\u000b(C\u0013\tyEFA\u0003BeJ\f\u00170\u0001\u0006uKN$h*Y7fg\u0002\n\u0011c^5mI\u000e\f\'\u000f\u001a+fgRt\u0015-\\3t\u0003I9\u0018\u000e\u001c3dCJ$G+Z:u\u001d\u0006lWm\u001d\u0011\u0002\u00199,7\u000f^3e\'VLG/Z:\u0016\u0003U\u00032a\u000b(W!\t9\u0006,D\u0001$\u0013\tI6E\u0001\tOKN$X\rZ*vSR,\u0007+\u0019:b[\u0006ia.Z:uK\u0012\u001cV/\u001b;fg\u0002\na\u0001P5oSRtD#B/_?\u0002\f\u0007CA,\u0001\u0011\u0015\u0001\u0015\u00021\u0001C\u0011\u0015Y\u0015\u00021\u0001N\u0011\u0015\t\u0016\u00021\u0001N\u0011\u0015\u0019\u0016\u00021\u0001V\u0003%9Gn\u001c2SK\u001e,\u00070F\u0001e!\t)\'.D\u0001g\u0015\t9\u0007.\u0001\u0003mC:<\'\"A5\u0002\t)\fg/Y\u0005\u0003\u0011\u001a\fa![:HY>\u0014W#A7\u0011\u0005-r\u0017BA8-\u0005\u001d\u0011un\u001c7fC:\fq!\\1uG\",7\u000f\u0006\u0002ne\")1\u000f\u0004a\u0001\u0005\u0006!a.Y7f\u0003\u0011\u0019w\u000e]=\u0015\u000bu3x\u000f_=\t\u000f\u0001k\u0001\u0013!a\u0001\u0005\"91*\u0004I\u0001\u0002\u0004i\u0005bB)\u000e!\u0003\u0005\r!\u0014\u0005\b\'6\u0001\n\u00111\u0001V\u00039\u0019w\u000e]=%I\u00164\u0017-\u001e7uIE*\u0012\u0001 \u0016\u0003\u0005v\\\u0013A \t\u0004\u007f\u0006%QBAA\u0001\u0015\u0011\t\u0019!!\u0002\u0002\u0013Ut7\r[3dW\u0016$\'bAA\u0004Y\u0005Q\u0011M\u001c8pi\u0006$\u0018n\u001c8\n\t\u0005-\u0011\u0011\u0001\u0002\u0012k:\u001c\u0007.Z2lK\u00124\u0016M]5b]\u000e,\u0017AD2paf$C-\u001a4bk2$HEM\u000b\u0003\u0003#Q#!T?\u0002\u001d\r|\u0007/\u001f\u0013eK\u001a\fW\u000f\u001c;%g\u0005q1m\u001c9zI\u0011,g-Y;mi\u0012\"TCAA\rU\t)V0A\u0007qe>$Wo\u0019;Qe\u00164\u0017\u000e_\u0001\raJ|G-^2u\u0003JLG/_\u000b\u0003\u0003C\u00012aKA\u0012\u0013\r\t)\u0003\f\u0002\u0004\u0013:$\u0018A\u00049s_\u0012,8\r^#mK6,g\u000e\u001e\u000b\u0005\u0003W\t\t\u0004E\u0002,\u0003[I1!a\f-\u0005\r\te.\u001f\u0005\n\u0003g!\u0012\u0011!a\u0001\u0003C\t1\u0001\u001f\u00132\u0003=\u0001(o\u001c3vGRLE/\u001a:bi>\u0014XCAA\u001d!\u0019\tY$!\u0011\u0002,5\u0011\u0011Q\b\u0006\u0004\u0003\u007fa\u0013AC2pY2,7\r^5p]&!\u00111IA\u001f\u0005!IE/\u001a:bi>\u0014\u0018\u0001C2b]\u0016\u000bX/\u00197\u0015\u00075\fI\u0005C\u0005\u00024Y\t\t\u00111\u0001\u0002,\u0005\u0011\u0002O]8ek\u000e$X\t\\3nK:$h*Y7f)\r!\u0017q\n\u0005\n\u0003g9\u0012\u0011!a\u0001\u0003C\t\u0001\u0002[1tQ\u000e{G-\u001a\u000b\u0003\u0003C\t\u0001\u0002^8TiJLgn\u001a\u000b\u0002I\u00061Q-];bYN$2!\\A/\u0011%\t\u0019DGA\u0001\u0002\u0004\tY#\u0001\u0006Tk&$X\rU1sC6\u0004\"a\u0016\u000f\u0014\u000bq\t)\'!\u001d\u0011\u0013\u0005\u001d\u0014Q\u000e\"N\u001bVkVBAA5\u0015\r\tY\u0007L\u0001\beVtG/[7f\u0013\u0011\ty\'!\u001b\u0003#\u0005\u00137\u000f\u001e:bGR4UO\\2uS>tG\u0007\u0005\u0003\u0002t\u0005eTBAA;\u0015\r\t9\b[\u0001\u0003S>L1APA;)\t\t\t\'A\u0003baBd\u0017\u0010F\u0005^\u0003\u0003\u000b\u0019)!\"\u0002\b\")\u0001i\ba\u0001\u0005\")1j\ba\u0001\u001b\")\u0011k\ba\u0001\u001b\")1k\ba\u0001+\u00069QO\\1qa2LH\u0003BAG\u00033\u0003RaKAH\u0003\'K1!!%-\u0005\u0019y\u0005\u000f^5p]B91&!&C\u001b6+\u0016bAALY\t1A+\u001e9mKRB\u0001\"a\'!\u0003\u0003\u0005\r!X\u0001\u0004q\u0012\u0002\u0014\u0001D<sSR,\'+\u001a9mC\u000e,GCAAQ!\r)\u00171U\u0005\u0004\u0003K3\'AB(cU\u0016\u001cG\u000f
   #13 = Utf8               globRegex
   #14 = Utf8               Ljava/lang/String;
   #15 = Utf8               className
   #16 = Utf8               testNames
   #17 = Utf8               [Ljava/lang/String;
   #18 = Utf8               wildcardTestNames
   #19 = Utf8               nestedSuites
   #20 = Utf8               [Lorg/scalatest/tools/NestedSuiteParam;
   #21 = Utf8               bitmap$0
   #22 = Utf8               Z
   #23 = Utf8               unapply
   #24 = Utf8               (Lorg/scalatest/tools/SuiteParam;)Lscala/Option;
   #25 = Utf8               (Lorg/scalatest/tools/SuiteParam;)Lscala/Option<Lscala/Tuple4<Ljava/lang/String;[Ljava/lang/String;[Ljava/lang/String;[Lorg/scalatest/tools/NestedSuiteParam;>;>;
   #26 = Utf8               x$0
   #27 = Utf8               org/scalatest/tools/SuiteParam$
   #28 = Class              #27           // org/scalatest/tools/SuiteParam$
   #29 = Utf8               MODULE$
   #30 = Utf8               Lorg/scalatest/tools/SuiteParam$;
   #31 = NameAndType        #29:#30       // MODULE$:Lorg/scalatest/tools/SuiteParam$;
   #32 = Fieldref           #28.#31       // org/scalatest/tools/SuiteParam$.MODULE$:Lorg/scalatest/tools/SuiteParam$;
   #33 = NameAndType        #23:#24       // unapply:(Lorg/scalatest/tools/SuiteParam;)Lscala/Option;
   #34 = Methodref          #28.#33       // org/scalatest/tools/SuiteParam$.unapply:(Lorg/scalatest/tools/SuiteParam;)Lscala/Option;
   #35 = Utf8               Lorg/scalatest/tools/SuiteParam;
   #36 = Utf8               apply
   #37 = Utf8               (Ljava/lang/String;[Ljava/lang/String;[Ljava/lang/String;[Lorg/scalatest/tools/NestedSuiteParam;)Lorg/scalatest/tools/SuiteParam;
   #38 = NameAndType        #36:#37       // apply:(Ljava/lang/String;[Ljava/lang/String;[Ljava/lang/String;[Lorg/scalatest/tools/NestedSuiteParam;)Lorg/scalatest/tools/SuiteParam;
   #39 = Methodref          #28.#38       // org/scalatest/tools/SuiteParam$.apply:(Ljava/lang/String;[Ljava/lang/String;[Ljava/lang/String;[Lorg/scalatest/tools/NestedSuiteParam;)Lorg/scalatest/tools/SuiteParam;
   #40 = Utf8               tupled
   #41 = Utf8               ()Lscala/Function1;
   #42 = Utf8               ()Lscala/Function1<Lscala/Tuple4<Ljava/lang/String;[Ljava/lang/String;[Ljava/lang/String;[Lorg/scalatest/tools/NestedSuiteParam;>;Lorg/scalatest/tools/SuiteParam;>;
   #43 = NameAndType        #40:#41       // tupled:()Lscala/Function1;
   #44 = Methodref          #28.#43       // org/scalatest/tools/SuiteParam$.tupled:()Lscala/Function1;
   #45 = Utf8               curried
   #46 = Utf8               ()Lscala/Function1<Ljava/lang/String;Lscala/Function1<[Ljava/lang/String;Lscala/Function1<[Ljava/lang/String;Lscala/Function1<[Lorg/scalatest/tools/NestedSuiteParam;Lorg/scalatest/tools/SuiteParam;>;>;>;>;
   #47 = NameAndType        #45:#41       // curried:()Lscala/Function1;
   #48 = Methodref          #28.#47       // org/scalatest/tools/SuiteParam$.curried:()Lscala/Function1;
   #49 = Utf8               productElementNames
   #50 = Utf8               ()Lscala/collection/Iterator;
   #51 = Utf8               ()Lscala/collection/Iterator<Ljava/lang/String;>;
   #52 = Utf8               productElementNames$
   #53 = Utf8               (Lscala/Product;)Lscala/collection/Iterator;
   #54 = NameAndType        #52:#53       // productElementNames$:(Lscala/Product;)Lscala/collection/Iterator;
   #55 = InterfaceMethodref #6.#54        // scala/Product.productElementNames$:(Lscala/Product;)Lscala/collection/Iterator;
   #56 = Utf8               this
   #57 = Utf8               ()Ljava/lang/String;
   #58 = NameAndType        #15:#14       // className:Ljava/lang/String;
   #59 = Fieldref           #2.#58        // org/scalatest/tools/SuiteParam.className:Ljava/lang/String;
   #60 = Utf8               ()[Ljava/lang/String;
   #61 = NameAndType        #16:#17       // testNames:[Ljava/lang/String;
   #62 = Fieldref           #2.#61        // org/scalatest/tools/SuiteParam.testNames:[Ljava/lang/String;
   #63 = NameAndType        #18:#17       // wildcardTestNames:[Ljava/lang/String;
   #64 = Fieldref           #2.#63        // org/scalatest/tools/SuiteParam.wildcardTestNames:[Ljava/lang/String;
   #65 = Utf8               ()[Lorg/scalatest/tools/NestedSuiteParam;
   #66 = NameAndType        #19:#20       // nestedSuites:[Lorg/scalatest/tools/NestedSuiteParam;
   #67 = Fieldref           #2.#66        // org/scalatest/tools/SuiteParam.nestedSuites:[Lorg/scalatest/tools/NestedSuiteParam;
   #68 = Utf8               globRegex$lzycompute
   #69 = NameAndType        #21:#22       // bitmap$0:Z
   #70 = Fieldref           #2.#69        // org/scalatest/tools/SuiteParam.bitmap$0:Z
   #71 = NameAndType        #15:#57       // className:()Ljava/lang/String;
   #72 = Methodref          #2.#71        // org/scalatest/tools/SuiteParam.className:()Ljava/lang/String;
   #73 = Utf8               \\.
   #74 = String             #73           // \\.
   #75 = Utf8               \\\\.
   #76 = String             #75           // \\\\.
   #77 = Utf8               java/lang/String
   #78 = Class              #77           // java/lang/String
   #79 = Utf8               replaceAll
   #80 = Utf8               (Ljava/lang/String;Ljava/lang/String;)Ljava/lang/String;
   #81 = NameAndType        #79:#80       // replaceAll:(Ljava/lang/String;Ljava/lang/String;)Ljava/lang/String;
   #82 = Methodref          #78.#81       // java/lang/String.replaceAll:(Ljava/lang/String;Ljava/lang/String;)Ljava/lang/String;
   #83 = Utf8               \\?
   #84 = String             #83           // \\?
   #85 = Utf8               .
   #86 = String             #85           // .
   #87 = Utf8               \\*
   #88 = String             #87           // \\*
   #89 = Utf8               .*
   #90 = String             #89           // .*
   #91 = NameAndType        #13:#14       // globRegex:Ljava/lang/String;
   #92 = Fieldref           #2.#91        // org/scalatest/tools/SuiteParam.globRegex:Ljava/lang/String;
   #93 = Utf8               java/lang/Throwable
   #94 = Class              #93           // java/lang/Throwable
   #95 = NameAndType        #68:#57       // globRegex$lzycompute:()Ljava/lang/String;
   #96 = Methodref          #2.#95        // org/scalatest/tools/SuiteParam.globRegex$lzycompute:()Ljava/lang/String;
   #97 = Utf8               isGlob
   #98 = Utf8               ()Z
   #99 = Utf8               .*(\\[|\\*|\\?).*
  #100 = String             #99           // .*(\\[|\\*|\\?).*
  #101 = Utf8               matches
  #102 = Utf8               (Ljava/lang/String;)Z
  #103 = NameAndType        #101:#102     // matches:(Ljava/lang/String;)Z
  #104 = Methodref          #78.#103      // java/lang/String.matches:(Ljava/lang/String;)Z
  #105 = Utf8               name
  #106 = NameAndType        #97:#98       // isGlob:()Z
  #107 = Methodref          #2.#106       // org/scalatest/tools/SuiteParam.isGlob:()Z
  #108 = Utf8               equals
  #109 = Utf8               (Ljava/lang/Object;)Z
  #110 = NameAndType        #108:#109     // equals:(Ljava/lang/Object;)Z
  #111 = Methodref          #4.#110       // java/lang/Object.equals:(Ljava/lang/Object;)Z
  #112 = NameAndType        #13:#57       // globRegex:()Ljava/lang/String;
  #113 = Methodref          #2.#112       // org/scalatest/tools/SuiteParam.globRegex:()Ljava/lang/String;
  #114 = Utf8               copy
  #115 = Utf8               <init>
  #116 = Utf8               (Ljava/lang/String;[Ljava/lang/String;[Ljava/lang/String;[Lorg/scalatest/tools/NestedSuiteParam;)V
  #117 = NameAndType        #115:#116     // "<init>":(Ljava/lang/String;[Ljava/lang/String;[Ljava/lang/String;[Lorg/scalatest/tools/NestedSuiteParam;)V
  #118 = Methodref          #2.#117       // org/scalatest/tools/SuiteParam."<init>":(Ljava/lang/String;[Ljava/lang/String;[Ljava/lang/String;[Lorg/scalatest/tools/NestedSuiteParam;)V
  #119 = Utf8               copy$default$1
  #120 = Utf8               copy$default$2
  #121 = NameAndType        #16:#60       // testNames:()[Ljava/lang/String;
  #122 = Methodref          #2.#121       // org/scalatest/tools/SuiteParam.testNames:()[Ljava/lang/String;
  #123 = Utf8               copy$default$3
  #124 = NameAndType        #18:#60       // wildcardTestNames:()[Ljava/lang/String;
  #125 = Methodref          #2.#124       // org/scalatest/tools/SuiteParam.wildcardTestNames:()[Ljava/lang/String;
  #126 = Utf8               copy$default$4
  #127 = NameAndType        #19:#65       // nestedSuites:()[Lorg/scalatest/tools/NestedSuiteParam;
  #128 = Methodref          #2.#127       // org/scalatest/tools/SuiteParam.nestedSuites:()[Lorg/scalatest/tools/NestedSuiteParam;
  #129 = Utf8               productPrefix
  #130 = Utf8               SuiteParam
  #131 = String             #130          // SuiteParam
  #132 = Utf8               productArity
  #133 = Utf8               ()I
  #134 = Utf8               productElement
  #135 = Utf8               (I)Ljava/lang/Object;
  #136 = Utf8               x$1
  #137 = Utf8               scala/runtime/Statics
  #138 = Class              #137          // scala/runtime/Statics
  #139 = Utf8               ioobe
  #140 = NameAndType        #139:#135     // ioobe:(I)Ljava/lang/Object;
  #141 = Methodref          #138.#140     // scala/runtime/Statics.ioobe:(I)Ljava/lang/Object;
  #142 = Utf8               I
  #143 = Utf8               productIterator
  #144 = Utf8               ()Lscala/collection/Iterator<Ljava/lang/Object;>;
  #145 = Utf8               scala/runtime/ScalaRunTime$
  #146 = Class              #145          // scala/runtime/ScalaRunTime$
  #147 = Utf8               Lscala/runtime/ScalaRunTime$;
  #148 = NameAndType        #29:#147      // MODULE$:Lscala/runtime/ScalaRunTime$;
  #149 = Fieldref           #146.#148     // scala/runtime/ScalaRunTime$.MODULE$:Lscala/runtime/ScalaRunTime$;
  #150 = Utf8               typedProductIterator
  #151 = NameAndType        #150:#53      // typedProductIterator:(Lscala/Product;)Lscala/collection/Iterator;
  #152 = Methodref          #146.#151     // scala/runtime/ScalaRunTime$.typedProductIterator:(Lscala/Product;)Lscala/collection/Iterator;
  #153 = Utf8               canEqual
  #154 = Utf8               Ljava/lang/Object;
  #155 = Utf8               productElementName
  #156 = Utf8               (I)Ljava/lang/String;
  #157 = String             #15           // className
  #158 = String             #16           // testNames
  #159 = String             #18           // wildcardTestNames
  #160 = String             #19           // nestedSuites
  #161 = Utf8               hashCode
  #162 = Utf8               _hashCode
  #163 = Utf8               (Lscala/Product;)I
  #164 = NameAndType        #162:#163     // _hashCode:(Lscala/Product;)I
  #165 = Methodref          #146.#164     // scala/runtime/ScalaRunTime$._hashCode:(Lscala/Product;)I
  #166 = Utf8               toString
  #167 = Utf8               _toString
  #168 = Utf8               (Lscala/Product;)Ljava/lang/String;
  #169 = NameAndType        #167:#168     // _toString:(Lscala/Product;)Ljava/lang/String;
  #170 = Methodref          #146.#169     // scala/runtime/ScalaRunTime$._toString:(Lscala/Product;)Ljava/lang/String;
  #171 = NameAndType        #153:#109     // canEqual:(Ljava/lang/Object;)Z
  #172 = Methodref          #2.#171       // org/scalatest/tools/SuiteParam.canEqual:(Ljava/lang/Object;)Z
  #173 = Utf8               ()V
  #174 = NameAndType        #115:#173     // "<init>":()V
  #175 = Methodref          #4.#174       // java/lang/Object."<init>":()V
  #176 = Utf8               $init$
  #177 = Utf8               (Lscala/Product;)V
  #178 = NameAndType        #176:#177     // $init$:(Lscala/Product;)V
  #179 = InterfaceMethodref #6.#178       // scala/Product.$init$:(Lscala/Product;)V
  #180 = Utf8               Code
  #181 = Utf8               LocalVariableTable
  #182 = Utf8               Signature
  #183 = Utf8               MethodParameters
  #184 = Utf8               LineNumberTable
  #185 = Utf8               StackMapTable
  #186 = Utf8               SourceFile
  #187 = Utf8               RuntimeVisibleAnnotations
  #188 = Utf8               ScalaInlineInfo
  #189 = Utf8               ScalaSig
{
  private java.lang.String globRegex;
    descriptor: Ljava/lang/String;
    flags: (0x0002) ACC_PRIVATE

  private final java.lang.String className;
    descriptor: Ljava/lang/String;
    flags: (0x0012) ACC_PRIVATE, ACC_FINAL

  private final java.lang.String[] testNames;
    descriptor: [Ljava/lang/String;
    flags: (0x0012) ACC_PRIVATE, ACC_FINAL

  private final java.lang.String[] wildcardTestNames;
    descriptor: [Ljava/lang/String;
    flags: (0x0012) ACC_PRIVATE, ACC_FINAL

  private final org.scalatest.tools.NestedSuiteParam[] nestedSuites;
    descriptor: [Lorg/scalatest/tools/NestedSuiteParam;
    flags: (0x0012) ACC_PRIVATE, ACC_FINAL

  private volatile boolean bitmap$0;
    descriptor: Z
    flags: (0x0042) ACC_PRIVATE, ACC_VOLATILE

  public static scala.Option<scala.Tuple4<java.lang.String, java.lang.String[], java.lang.String[], org.scalatest.tools.NestedSuiteParam[]>> unapply(org.scalatest.tools.SuiteParam);
    descriptor: (Lorg/scalatest/tools/SuiteParam;)Lscala/Option;
    flags: (0x0009) ACC_PUBLIC, ACC_STATIC
    Code:
      stack=2, locals=1, args_size=1
         0: getstatic     #32                 // Field org/scalatest/tools/SuiteParam$.MODULE$:Lorg/scalatest/tools/SuiteParam$;
         3: aload_0
         4: invokevirtual #34                 // Method org/scalatest/tools/SuiteParam$.unapply:(Lorg/scalatest/tools/SuiteParam;)Lscala/Option;
         7: areturn
      LocalVariableTable:
        Start  Length  Slot  Name   Signature
            0       8     0   x$0   Lorg/scalatest/tools/SuiteParam;
    Signature: #25                          // (Lorg/scalatest/tools/SuiteParam;)Lscala/Option<Lscala/Tuple4<Ljava/lang/String;[Ljava/lang/String;[Ljava/lang/String;[Lorg/scalatest/tools/NestedSuiteParam;>;>;
    MethodParameters:
      Name                           Flags
      x$0                            final

  public static org.scalatest.tools.SuiteParam apply(java.lang.String, java.lang.String[], java.lang.String[], org.scalatest.tools.NestedSuiteParam[]);
    descriptor: (Ljava/lang/String;[Ljava/lang/String;[Ljava/lang/String;[Lorg/scalatest/tools/NestedSuiteParam;)Lorg/scalatest/tools/SuiteParam;
    flags: (0x0009) ACC_PUBLIC, ACC_STATIC
    Code:
      stack=5, locals=4, args_size=4
         0: getstatic     #32                 // Field org/scalatest/tools/SuiteParam$.MODULE$:Lorg/scalatest/tools/SuiteParam$;
         3: aload_0
         4: aload_1
         5: aload_2
         6: aload_3
         7: invokevirtual #39                 // Method org/scalatest/tools/SuiteParam$.apply:(Ljava/lang/String;[Ljava/lang/String;[Ljava/lang/String;[Lorg/scalatest/tools/NestedSuiteParam;)Lorg/scalatest/tools/SuiteParam;
        10: areturn
      LocalVariableTable:
        Start  Length  Slot  Name   Signature
            0      11     0 className   Ljava/lang/String;
            0      11     1 testNames   [Ljava/lang/String;
            0      11     2 wildcardTestNames   [Ljava/lang/String;
            0      11     3 nestedSuites   [Lorg/scalatest/tools/NestedSuiteParam;
    MethodParameters:
      Name                           Flags
      className                      final
      testNames                      final
      wildcardTestNames              final
      nestedSuites                   final

  public static scala.Function1<scala.Tuple4<java.lang.String, java.lang.String[], java.lang.String[], org.scalatest.tools.NestedSuiteParam[]>, org.scalatest.tools.SuiteParam> tupled();
    descriptor: ()Lscala/Function1;
    flags: (0x0009) ACC_PUBLIC, ACC_STATIC
    Code:
      stack=1, locals=0, args_size=0
         0: getstatic     #32                 // Field org/scalatest/tools/SuiteParam$.MODULE$:Lorg/scalatest/tools/SuiteParam$;
         3: invokevirtual #44                 // Method org/scalatest/tools/SuiteParam$.tupled:()Lscala/Function1;
         6: areturn
    Signature: #42                          // ()Lscala/Function1<Lscala/Tuple4<Ljava/lang/String;[Ljava/lang/String;[Ljava/lang/String;[Lorg/scalatest/tools/NestedSuiteParam;>;Lorg/scalatest/tools/SuiteParam;>;

  public static scala.Function1<java.lang.String, scala.Function1<java.lang.String[], scala.Function1<java.lang.String[], scala.Function1<org.scalatest.tools.NestedSuiteParam[], org.scalatest.tools.SuiteParam>>>> curried();
    descriptor: ()Lscala/Function1;
    flags: (0x0009) ACC_PUBLIC, ACC_STATIC
    Code:
      stack=1, locals=0, args_size=0
         0: getstatic     #32                 // Field org/scalatest/tools/SuiteParam$.MODULE$:Lorg/scalatest/tools/SuiteParam$;
         3: invokevirtual #48                 // Method org/scalatest/tools/SuiteParam$.curried:()Lscala/Function1;
         6: areturn
    Signature: #46                          // ()Lscala/Function1<Ljava/lang/String;Lscala/Function1<[Ljava/lang/String;Lscala/Function1<[Ljava/lang/String;Lscala/Function1<[Lorg/scalatest/tools/NestedSuiteParam;Lorg/scalatest/tools/SuiteParam;>;>;>;>;

  public scala.collection.Iterator<java.lang.String> productElementNames();
    descriptor: ()Lscala/collection/Iterator;
    flags: (0x0001) ACC_PUBLIC
    Code:
      stack=1, locals=1, args_size=1
         0: aload_0
         1: invokestatic  #55                 // InterfaceMethod scala/Product.productElementNames$:(Lscala/Product;)Lscala/collection/Iterator;
         4: areturn
      LineNumberTable:
        line 18: 0
      LocalVariableTable:
        Start  Length  Slot  Name   Signature
            0       5     0  this   Lorg/scalatest/tools/SuiteParam;
    Signature: #51                          // ()Lscala/collection/Iterator<Ljava/lang/String;>;

  public java.lang.String className();
    descriptor: ()Ljava/lang/String;
    flags: (0x0001) ACC_PUBLIC
    Code:
      stack=1, locals=1, args_size=1
         0: aload_0
         1: getfield      #59                 // Field className:Ljava/lang/String;
         4: areturn
      LineNumberTable:
        line 18: 0
      LocalVariableTable:
        Start  Length  Slot  Name   Signature
            0       5     0  this   Lorg/scalatest/tools/SuiteParam;

  public java.lang.String[] testNames();
    descriptor: ()[Ljava/lang/String;
    flags: (0x0001) ACC_PUBLIC
    Code:
      stack=1, locals=1, args_size=1
         0: aload_0
         1: getfield      #62                 // Field testNames:[Ljava/lang/String;
         4: areturn
      LineNumberTable:
        line 18: 0
      LocalVariableTable:
        Start  Length  Slot  Name   Signature
            0       5     0  this   Lorg/scalatest/tools/SuiteParam;

  public java.lang.String[] wildcardTestNames();
    descriptor: ()[Ljava/lang/String;
    flags: (0x0001) ACC_PUBLIC
    Code:
      stack=1, locals=1, args_size=1
         0: aload_0
         1: getfield      #64                 // Field wildcardTestNames:[Ljava/lang/String;
         4: areturn
      LineNumberTable:
        line 18: 0
      LocalVariableTable:
        Start  Length  Slot  Name   Signature
            0       5     0  this   Lorg/scalatest/tools/SuiteParam;

  public org.scalatest.tools.NestedSuiteParam[] nestedSuites();
    descriptor: ()[Lorg/scalatest/tools/NestedSuiteParam;
    flags: (0x0001) ACC_PUBLIC
    Code:
      stack=1, locals=1, args_size=1
         0: aload_0
         1: getfield      #67                 // Field nestedSuites:[Lorg/scalatest/tools/NestedSuiteParam;
         4: areturn
      LineNumberTable:
        line 18: 0
      LocalVariableTable:
        Start  Length  Slot  Name   Signature
            0       5     0  this   Lorg/scalatest/tools/SuiteParam;

  private java.lang.String globRegex$lzycompute();
    descriptor: ()Ljava/lang/String;
    flags: (0x0002) ACC_PRIVATE
    Code:
      stack=4, locals=2, args_size=1
         0: aload_0
         1: dup
         2: astore_1
         3: monitorenter
         4: aload_0
         5: getfield      #70                 // Field bitmap$0:Z
         8: ifne          45
        11: aload_0
        12: aload_0
        13: invokevirtual #72                 // Method className:()Ljava/lang/String;
        16: ldc           #74                 // String \\.
        18: ldc           #76                 // String \\\\.
        20: invokevirtual #82                 // Method java/lang/String.replaceAll:(Ljava/lang/String;Ljava/lang/String;)Ljava/lang/String;
        23: ldc           #84                 // String \\?
        25: ldc           #86                 // String .
        27: invokevirtual #82                 // Method java/lang/String.replaceAll:(Ljava/lang/String;Ljava/lang/String;)Ljava/lang/String;
        30: ldc           #88                 // String \\*
        32: ldc           #90                 // String .*
        34: invokevirtual #82                 // Method java/lang/String.replaceAll:(Ljava/lang/String;Ljava/lang/String;)Ljava/lang/String;
        37: putfield      #92                 // Field globRegex:Ljava/lang/String;
        40: aload_0
        41: iconst_1
        42: putfield      #70                 // Field bitmap$0:Z
        45: aload_1
        46: monitorexit
        47: goto          53
        50: aload_1
        51: monitorexit
        52: athrow
        53: aload_0
        54: getfield      #92                 // Field globRegex:Ljava/lang/String;
        57: areturn
      Exception table:
         from    to  target type
             4    45    50   any
      StackMapTable: number_of_entries = 3
        frame_type = 252 /* append */
          offset_delta = 45
          locals = [ class org/scalatest/tools/SuiteParam ]
        frame_type = 68 /* same_locals_1_stack_item */
          stack = [ class java/lang/Throwable ]
        frame_type = 2 /* same */
      LineNumberTable:
        line 20: 0
        line 21: 12
        line 22: 16
        line 23: 23
        line 24: 30
        line 20: 37
      LocalVariableTable:
        Start  Length  Slot  Name   Signature
            0      58     0  this   Lorg/scalatest/tools/SuiteParam;

  private java.lang.String globRegex();
    descriptor: ()Ljava/lang/String;
    flags: (0x0002) ACC_PRIVATE
    Code:
      stack=1, locals=1, args_size=1
         0: aload_0
         1: getfield      #70                 // Field bitmap$0:Z
         4: ifne          14
         7: aload_0
         8: invokespecial #96                 // Method globRegex$lzycompute:()Ljava/lang/String;
        11: goto          18
        14: aload_0
        15: getfield      #92                 // Field globRegex:Ljava/lang/String;
        18: areturn
      StackMapTable: number_of_entries = 2
        frame_type = 14 /* same */
        frame_type = 67 /* same_locals_1_stack_item */
          stack = [ class java/lang/String ]
      LineNumberTable:
        line 20: 0
      LocalVariableTable:
        Start  Length  Slot  Name   Signature
            0      19     0  this   Lorg/scalatest/tools/SuiteParam;

  public boolean isGlob();
    descriptor: ()Z
    flags: (0x0001) ACC_PUBLIC
    Code:
      stack=2, locals=1, args_size=1
         0: aload_0
         1: invokevirtual #72                 // Method className:()Ljava/lang/String;
         4: ldc           #100                // String .*(\\[|\\*|\\?).*
         6: invokevirtual #104                // Method java/lang/String.matches:(Ljava/lang/String;)Z
         9: ireturn
      LineNumberTable:
        line 32: 0
      LocalVariableTable:
        Start  Length  Slot  Name   Signature
            0      10     0  this   Lorg/scalatest/tools/SuiteParam;

  public boolean matches(java.lang.String);
    descriptor: (Ljava/lang/String;)Z
    flags: (0x0001) ACC_PUBLIC
    Code:
      stack=2, locals=3, args_size=2
         0: aload_0
         1: invokevirtual #107                // Method isGlob:()Z
         4: ifne          40
         7: aload_1
         8: aload_0
         9: invokevirtual #72                 // Method className:()Ljava/lang/String;
        12: astore_2
        13: dup
        14: ifnonnull     25
        17: pop
        18: aload_2
        19: ifnull        32
        22: goto          36
        25: aload_2
        26: invokevirtual #111                // Method java/lang/Object.equals:(Ljava/lang/Object;)Z
        29: ifeq          36
        32: iconst_1
        33: goto          37
        36: iconst_0
        37: goto          48
        40: aload_1
        41: aload_0
        42: invokespecial #113                // Method globRegex:()Ljava/lang/String;
        45: invokevirtual #104                // Method java/lang/String.matches:(Ljava/lang/String;)Z
        48: ireturn
      StackMapTable: number_of_entries = 6
        frame_type = 255 /* full_frame */
          offset_delta = 25
          locals = [ class org/scalatest/tools/SuiteParam, class java/lang/String, class java/lang/String ]
          stack = [ class java/lang/String ]
        frame_type = 6 /* same */
        frame_type = 3 /* same */
        frame_type = 64 /* same_locals_1_stack_item */
          stack = [ int ]
        frame_type = 250 /* chop */
          offset_delta = 2
        frame_type = 71 /* same_locals_1_stack_item */
          stack = [ int ]
      LineNumberTable:
        line 38: 0
        line 39: 40
      LocalVariableTable:
        Start  Length  Slot  Name   Signature
            0      49     0  this   Lorg/scalatest/tools/SuiteParam;
            0      49     1  name   Ljava/lang/String;
    MethodParameters:
      Name                           Flags
      name                           final

  public org.scalatest.tools.SuiteParam copy(java.lang.String, java.lang.String[], java.lang.String[], org.scalatest.tools.NestedSuiteParam[]);
    descriptor: (Ljava/lang/String;[Ljava/lang/String;[Ljava/lang/String;[Lorg/scalatest/tools/NestedSuiteParam;)Lorg/scalatest/tools/SuiteParam;
    flags: (0x0001) ACC_PUBLIC
    Code:
      stack=6, locals=5, args_size=5
         0: new           #2                  // class org/scalatest/tools/SuiteParam
         3: dup
         4: aload_1
         5: aload_2
         6: aload_3
         7: aload         4
         9: invokespecial #118                // Method "<init>":(Ljava/lang/String;[Ljava/lang/String;[Ljava/lang/String;[Lorg/scalatest/tools/NestedSuiteParam;)V
        12: areturn
      LineNumberTable:
        line 18: 0
      LocalVariableTable:
        Start  Length  Slot  Name   Signature
            0      13     0  this   Lorg/scalatest/tools/SuiteParam;
            0      13     1 className   Ljava/lang/String;
            0      13     2 testNames   [Ljava/lang/String;
            0      13     3 wildcardTestNames   [Ljava/lang/String;
            0      13     4 nestedSuites   [Lorg/scalatest/tools/NestedSuiteParam;
    MethodParameters:
      Name                           Flags
      className                      final
      testNames                      final
      wildcardTestNames              final
      nestedSuites                   final

  public java.lang.String copy$default$1();
    descriptor: ()Ljava/lang/String;
    flags: (0x0001) ACC_PUBLIC
    Code:
      stack=1, locals=1, args_size=1
         0: aload_0
         1: invokevirtual #72                 // Method className:()Ljava/lang/String;
         4: areturn
      LineNumberTable:
        line 18: 0
      LocalVariableTable:
        Start  Length  Slot  Name   Signature
            0       5     0  this   Lorg/scalatest/tools/SuiteParam;

  public java.lang.String[] copy$default$2();
    descriptor: ()[Ljava/lang/String;
    flags: (0x0001) ACC_PUBLIC
    Code:
      stack=1, locals=1, args_size=1
         0: aload_0
         1: invokevirtual #122                // Method testNames:()[Ljava/lang/String;
         4: areturn
      LineNumberTable:
        line 18: 0
      LocalVariableTable:
        Start  Length  Slot  Name   Signature
            0       5     0  this   Lorg/scalatest/tools/SuiteParam;

  public java.lang.String[] copy$default$3();
    descriptor: ()[Ljava/lang/String;
    flags: (0x0001) ACC_PUBLIC
    Code:
      stack=1, locals=1, args_size=1
         0: aload_0
         1: invokevirtual #125                // Method wildcardTestNames:()[Ljava/lang/String;
         4: areturn
      LineNumberTable:
        line 18: 0
      LocalVariableTable:
        Start  Length  Slot  Name   Signature
            0       5     0  this   Lorg/scalatest/tools/SuiteParam;

  public org.scalatest.tools.NestedSuiteParam[] copy$default$4();
    descriptor: ()[Lorg/scalatest/tools/NestedSuiteParam;
    flags: (0x0001) ACC_PUBLIC
    Code:
      stack=1, locals=1, args_size=1
         0: aload_0
         1: invokevirtual #128                // Method nestedSuites:()[Lorg/scalatest/tools/NestedSuiteParam;
         4: areturn
      LineNumberTable:
        line 18: 0
      LocalVariableTable:
        Start  Length  Slot  Name   Signature
            0       5     0  this   Lorg/scalatest/tools/SuiteParam;

  public java.lang.String productPrefix();
    descriptor: ()Ljava/lang/String;
    flags: (0x0001) ACC_PUBLIC
    Code:
      stack=1, locals=1, args_size=1
         0: ldc           #131                // String SuiteParam
         2: areturn
      LineNumberTable:
        line 18: 0
      LocalVariableTable:
        Start  Length  Slot  Name   Signature
            0       3     0  this   Lorg/scalatest/tools/SuiteParam;

  public int productArity();
    descriptor: ()I
    flags: (0x0001) ACC_PUBLIC
    Code:
      stack=1, locals=1, args_size=1
         0: iconst_4
         1: ireturn
      LineNumberTable:
        line 18: 0
      LocalVariableTable:
        Start  Length  Slot  Name   Signature
            0       2     0  this   Lorg/scalatest/tools/SuiteParam;

  public java.lang.Object productElement(int);
    descriptor: (I)Ljava/lang/Object;
    flags: (0x0001) ACC_PUBLIC
    Code:
      stack=1, locals=3, args_size=2
         0: iload_1
         1: istore_2
         2: iload_2
         3: tableswitch   { // 0 to 3
                       0: 32
                       1: 39
                       2: 46
                       3: 53
                 default: 60
            }
        32: aload_0
        33: invokevirtual #72                 // Method className:()Ljava/lang/String;
        36: goto          67
        39: aload_0
        40: invokevirtual #122                // Method testNames:()[Ljava/lang/String;
        43: goto          67
        46: aload_0
        47: invokevirtual #125                // Method wildcardTestNames:()[Ljava/lang/String;
        50: goto          67
        53: aload_0
        54: invokevirtual #128                // Method nestedSuites:()[Lorg/scalatest/tools/NestedSuiteParam;
        57: goto          67
        60: iload_1
        61: invokestatic  #141                // Method scala/runtime/Statics.ioobe:(I)Ljava/lang/Object;
        64: goto          67
        67: areturn
      StackMapTable: number_of_entries = 6
        frame_type = 252 /* append */
          offset_delta = 32
          locals = [ int ]
        frame_type = 6 /* same */
        frame_type = 6 /* same */
        frame_type = 6 /* same */
        frame_type = 6 /* same */
        frame_type = 70 /* same_locals_1_stack_item */
          stack = [ class java/lang/Object ]
      LineNumberTable:
        line 18: 0
      LocalVariableTable:
        Start  Length  Slot  Name   Signature
            0      68     0  this   Lorg/scalatest/tools/SuiteParam;
            0      68     1   x$1   I
    MethodParameters:
      Name                           Flags
      x$1                            final

  public scala.collection.Iterator<java.lang.Object> productIterator();
    descriptor: ()Lscala/collection/Iterator;
    flags: (0x0001) ACC_PUBLIC
    Code:
      stack=2, locals=1, args_size=1
         0: getstatic     #149                // Field scala/runtime/ScalaRunTime$.MODULE$:Lscala/runtime/ScalaRunTime$;
         3: aload_0
         4: invokevirtual #152                // Method scala/runtime/ScalaRunTime$.typedProductIterator:(Lscala/Product;)Lscala/collection/Iterator;
         7: areturn
      LineNumberTable:
        line 18: 0
      LocalVariableTable:
        Start  Length  Slot  Name   Signature
            0       8     0  this   Lorg/scalatest/tools/SuiteParam;
    Signature: #144                         // ()Lscala/collection/Iterator<Ljava/lang/Object;>;

  public boolean canEqual(java.lang.Object);
    descriptor: (Ljava/lang/Object;)Z
    flags: (0x0001) ACC_PUBLIC
    Code:
      stack=1, locals=2, args_size=2
         0: aload_1
         1: instanceof    #2                  // class org/scalatest/tools/SuiteParam
         4: ireturn
      LineNumberTable:
        line 18: 0
      LocalVariableTable:
        Start  Length  Slot  Name   Signature
            0       5     0  this   Lorg/scalatest/tools/SuiteParam;
            0       5     1   x$1   Ljava/lang/Object;
    MethodParameters:
      Name                           Flags
      x$1                            final

  public java.lang.String productElementName(int);
    descriptor: (I)Ljava/lang/String;
    flags: (0x0001) ACC_PUBLIC
    Code:
      stack=1, locals=3, args_size=2
         0: iload_1
         1: istore_2
         2: iload_2
         3: tableswitch   { // 0 to 3
                       0: 32
                       1: 37
                       2: 42
                       3: 47
                 default: 52
            }
        32: ldc           #157                // String className
        34: goto          62
        37: ldc           #158                // String testNames
        39: goto          62
        42: ldc           #159                // String wildcardTestNames
        44: goto          62
        47: ldc           #160                // String nestedSuites
        49: goto          62
        52: iload_1
        53: invokestatic  #141                // Method scala/runtime/Statics.ioobe:(I)Ljava/lang/Object;
        56: checkcast     #78                 // class java/lang/String
        59: goto          62
        62: areturn
      StackMapTable: number_of_entries = 6
        frame_type = 252 /* append */
          offset_delta = 32
          locals = [ int ]
        frame_type = 4 /* same */
        frame_type = 4 /* same */
        frame_type = 4 /* same */
        frame_type = 4 /* same */
        frame_type = 73 /* same_locals_1_stack_item */
          stack = [ class java/lang/String ]
      LineNumberTable:
        line 18: 0
      LocalVariableTable:
        Start  Length  Slot  Name   Signature
            0      63     0  this   Lorg/scalatest/tools/SuiteParam;
            0      63     1   x$1   I
    MethodParameters:
      Name                           Flags
      x$1                            final

  public int hashCode();
    descriptor: ()I
    flags: (0x0001) ACC_PUBLIC
    Code:
      stack=2, locals=1, args_size=1
         0: getstatic     #149                // Field scala/runtime/ScalaRunTime$.MODULE$:Lscala/runtime/ScalaRunTime$;
         3: aload_0
         4: invokevirtual #165                // Method scala/runtime/ScalaRunTime$._hashCode:(Lscala/Product;)I
         7: ireturn
      LineNumberTable:
        line 18: 0
      LocalVariableTable:
        Start  Length  Slot  Name   Signature
            0       8     0  this   Lorg/scalatest/tools/SuiteParam;

  public java.lang.String toString();
    descriptor: ()Ljava/lang/String;
    flags: (0x0001) ACC_PUBLIC
    Code:
      stack=2, locals=1, args_size=1
         0: getstatic     #149                // Field scala/runtime/ScalaRunTime$.MODULE$:Lscala/runtime/ScalaRunTime$;
         3: aload_0
         4: invokevirtual #170                // Method scala/runtime/ScalaRunTime$._toString:(Lscala/Product;)Ljava/lang/String;
         7: areturn
      LineNumberTable:
        line 18: 0
      LocalVariableTable:
        Start  Length  Slot  Name   Signature
            0       8     0  this   Lorg/scalatest/tools/SuiteParam;

  public boolean equals(java.lang.Object);
    descriptor: (Ljava/lang/Object;)Z
    flags: (0x0001) ACC_PUBLIC
    Code:
      stack=2, locals=6, args_size=2
         0: aload_0
         1: aload_1
         2: if_acmpeq     122
         5: aload_1
         6: astore_3
         7: aload_3
         8: instanceof    #2                  // class org/scalatest/tools/SuiteParam
        11: ifeq          19
        14: iconst_1
        15: istore_2
        16: goto          27
        19: goto          22
        22: iconst_0
        23: istore_2
        24: goto          27
        27: iload_2
        28: ifeq          126
        31: aload_1
        32: checkcast     #2                  // class org/scalatest/tools/SuiteParam
        35: astore        4
        37: aload_0
        38: invokevirtual #72                 // Method className:()Ljava/lang/String;
        41: aload         4
        43: invokevirtual #72                 // Method className:()Ljava/lang/String;
        46: astore        5
        48: dup
        49: ifnonnull     61
        52: pop
        53: aload         5
        55: ifnull        69
        58: goto          118
        61: aload         5
        63: invokevirtual #111                // Method java/lang/Object.equals:(Ljava/lang/Object;)Z
        66: ifeq          118
        69: aload_0
        70: invokevirtual #122                // Method testNames:()[Ljava/lang/String;
        73: aload         4
        75: invokevirtual #122                // Method testNames:()[Ljava/lang/String;
        78: if_acmpne     118
        81: aload_0
        82: invokevirtual #125                // Method wildcardTestNames:()[Ljava/lang/String;
        85: aload         4
        87: invokevirtual #125                // Method wildcardTestNames:()[Ljava/lang/String;
        90: if_acmpne     118
        93: aload_0
        94: invokevirtual #128                // Method nestedSuites:()[Lorg/scalatest/tools/NestedSuiteParam;
        97: aload         4
        99: invokevirtual #128                // Method nestedSuites:()[Lorg/scalatest/tools/NestedSuiteParam;
       102: if_acmpne     118
       105: aload         4
       107: aload_0
       108: invokevirtual #172                // Method canEqual:(Ljava/lang/Object;)Z
       111: ifeq          118
       114: iconst_1
       115: goto          119
       118: iconst_0
       119: ifeq          126
       122: iconst_1
       123: goto          127
       126: iconst_0
       127: ireturn
      StackMapTable: number_of_entries = 10
        frame_type = 253 /* append */
          offset_delta = 19
          locals = [ top, class java/lang/Object ]
        frame_type = 2 /* same */
        frame_type = 255 /* full_frame */
          offset_delta = 4
          locals = [ class org/scalatest/tools/SuiteParam, class java/lang/Object, int, class java/lang/Object ]
          stack = []
        frame_type = 255 /* full_frame */
          offset_delta = 33
          locals = [ class org/scalatest/tools/SuiteParam, class java/lang/Object, int, class java/lang/Object, class org/scalatest/tools/SuiteParam, class java/lang/String ]
          stack = [ class java/lang/String ]
        frame_type = 7 /* same */
        frame_type = 48 /* same */
        frame_type = 64 /* same_locals_1_stack_item */
          stack = [ int ]
        frame_type = 255 /* full_frame */
          offset_delta = 2
          locals = [ class org/scalatest/tools/SuiteParam, class java/lang/Object ]
          stack = []
        frame_type = 253 /* append */
          offset_delta = 3
          locals = [ int, class java/lang/Object ]
        frame_type = 255 /* full_frame */
          offset_delta = 0
          locals = [ class org/scalatest/tools/SuiteParam, class java/lang/Object ]
          stack = [ int ]
      LineNumberTable:
        line 18: 0
      LocalVariableTable:
        Start  Length  Slot  Name   Signature
            0     128     0  this   Lorg/scalatest/tools/SuiteParam;
            0     128     1   x$1   Ljava/lang/Object;
    MethodParameters:
      Name                           Flags
      x$1                            final

  public org.scalatest.tools.SuiteParam(java.lang.String, java.lang.String[], java.lang.String[], org.scalatest.tools.NestedSuiteParam[]);
    descriptor: (Ljava/lang/String;[Ljava/lang/String;[Ljava/lang/String;[Lorg/scalatest/tools/NestedSuiteParam;)V
    flags: (0x0001) ACC_PUBLIC
    Code:
      stack=2, locals=5, args_size=5
         0: aload_0
         1: aload_1
         2: putfield      #59                 // Field className:Ljava/lang/String;
         5: aload_0
         6: aload_2
         7: putfield      #62                 // Field testNames:[Ljava/lang/String;
        10: aload_0
        11: aload_3
        12: putfield      #64                 // Field wildcardTestNames:[Ljava/lang/String;
        15: aload_0
        16: aload         4
        18: putfield      #67                 // Field nestedSuites:[Lorg/scalatest/tools/NestedSuiteParam;
        21: aload_0
        22: invokespecial #175                // Method java/lang/Object."<init>":()V
        25: aload_0
        26: invokestatic  #179                // InterfaceMethod scala/Product.$init$:(Lscala/Product;)V
        29: return
      LineNumberTable:
        line 18: 0
      LocalVariableTable:
        Start  Length  Slot  Name   Signature
            0      30     0  this   Lorg/scalatest/tools/SuiteParam;
            0      30     1 className   Ljava/lang/String;
            0      30     2 testNames   [Ljava/lang/String;
            0      30     3 wildcardTestNames   [Ljava/lang/String;
            0      30     4 nestedSuites   [Lorg/scalatest/tools/NestedSuiteParam;
    MethodParameters:
      Name                           Flags
      className                      final
      testNames                      final
      wildcardTestNames              final
      nestedSuites                   final
}
SourceFile: "SuiteParam.scala"
RuntimeVisibleAnnotations:
  0: #10(#11=s#12)
    scala.reflect.ScalaSignature(
      bytes="\u0006\u0005\u0005\u001df!\u0002\u0012$\u0001\u000eJ\u0003\u0002\u0003!\u0001\u0005+\u0007I\u0011A!\t\u0011)\u0003!\u0011#Q\u0001\n\tC\u0001b\u0013\u0001\u0003\u0016\u0004%\t\u0001\u0014\u0005\t!\u0002\u0011\t\u0012)A\u0005\u001b\"A\u0011\u000b\u0001BK\u0002\u0013\u0005A\n\u0003\u0005S\u0001\tE\t\u0015!\u0003N\u0011!\u0019\u0006A!f\u0001\n\u0003!\u0006\u0002\u0003.\u0001\u0005#\u0005\u000b\u0011B+\t\u000bm\u0003A\u0011\u0001/\t\u0011\t\u0004\u0001R1A\u0005\n\rDQa\u001b\u0001\u0005\u00021DQ\u0001\u001d\u0001\u0005\u0002EDq\u0001\u001e\u0001\u0002\u0002\u0013\u0005Q\u000fC\u0004{\u0001E\u0005I\u0011A>\t\u0013\u00055\u0001!%A\u0005\u0002\u0005=\u0001\"CA\n\u0001E\u0005I\u0011AA\b\u0011%\t)\u0002AI\u0001\n\u0003\t9\u0002\u0003\u0005\u0002\u001c\u0001\t\t\u0011\"\u0011d\u0011%\ti\u0002AA\u0001\n\u0003\ty\u0002C\u0005\u0002(\u0001\t\t\u0011\"\u0001\u0002*!I\u0011Q\u0007\u0001\u0002\u0002\u0013\u0005\u0013q\u0007\u0005\n\u0003\u000b\u0002\u0011\u0011!C\u0001\u0003\u000fB\u0011\"a\u0013\u0001\u0003\u0003%\t%!\u0014\t\u0013\u0005E\u0003!!A\u0005B\u0005M\u0003\"CA+\u0001\u0005\u0005I\u0011IA,\u0011%\tI\u0006AA\u0001\n\u0003\nYf\u0002\u0006\u0002`\r\n\t\u0011#\u0001$\u0003C2\u0011BI\u0012\u0002\u0002#\u00051%a\u0019\t\rmcB\u0011AA>\u0011%\t)\u0006HA\u0001\n\u000b\n9\u0006C\u0005\u0002~q\t\t\u0011\"!\u0002\u0000!I\u0011\u0011\u0012\u000f\u0002\u0002\u0013\u0005\u00151\u0012\u0005\n\u0003;c\u0012\u0011!C\u0005\u0003?\u0013!bU;ji\u0016\u0004\u0016M]1n\u0015\t!S%A\u0003u_>d7O\u0003\u0002\'O\u0005I1oY1mCR,7\u000f\u001e\u0006\u0002Q\u0005\u0019qN]4\u0014\t\u0001Q\u0003g\r\t\u0003W9j\u0011\u0001\f\u0006\u0002[\u0005)1oY1mC&\u0011q\u0006\f\u0002\u0007\u0003:L(+\u001a4\u0011\u0005-\n\u0014B\u0001\u001a-\u0005\u001d\u0001&o\u001c3vGR\u0004\"\u0001N\u001f\u000f\u0005UZdB\u0001\u001c;\u001b\u00059$B\u0001\u001d:\u0003\u0019a$o\\8u}\r\u0001\u0011\"A\u0017\n\u0005qb\u0013a\u00029bG.\fw-Z\u0005\u0003}}\u0012AbU3sS\u0006d\u0017N_1cY\u0016T!\u0001\u0010\u0017\u0002\u0013\rd\u0017m]:OC6,W#\u0001\"\u0011\u0005\r;eB\u0001#F!\t1D&\u0003\u0002GY\u00051\u0001K]3eK\u001aL!\u0001S%\u0003\rM#(/\u001b8h\u0015\t1E&\u0001\u0006dY\u0006\u001c8OT1nK\u0002\n\u0011\u0002^3ti:\u000bW.Z:\u0016\u00035\u00032a\u000b(C\u0013\tyEFA\u0003BeJ\f\u00170\u0001\u0006uKN$h*Y7fg\u0002\n\u0011c^5mI\u000e\f\'\u000f\u001a+fgRt\u0015-\\3t\u0003I9\u0018\u000e\u001c3dCJ$G+Z:u\u001d\u0006lWm\u001d\u0011\u0002\u00199,7\u000f^3e\'VLG/Z:\u0016\u0003U\u00032a\u000b(W!\t9\u0006,D\u0001$\u0013\tI6E\u0001\tOKN$X\rZ*vSR,\u0007+\u0019:b[\u0006ia.Z:uK\u0012\u001cV/\u001b;fg\u0002\na\u0001P5oSRtD#B/_?\u0002\f\u0007CA,\u0001\u0011\u0015\u0001\u0015\u00021\u0001C\u0011\u0015Y\u0015\u00021\u0001N\u0011\u0015\t\u0016\u00021\u0001N\u0011\u0015\u0019\u0016\u00021\u0001V\u0003%9Gn\u001c2SK\u001e,\u00070F\u0001e!\t)\'.D\u0001g\u0015\t9\u0007.\u0001\u0003mC:<\'\"A5\u0002\t)\fg/Y\u0005\u0003\u0011\u001a\fa![:HY>\u0014W#A7\u0011\u0005-r\u0017BA8-\u0005\u001d\u0011un\u001c7fC:\fq!\\1uG\",7\u000f\u0006\u0002ne\")1\u000f\u0004a\u0001\u0005\u0006!a.Y7f\u0003\u0011\u0019w\u000e]=\u0015\u000bu3x\u000f_=\t\u000f\u0001k\u0001\u0013!a\u0001\u0005\"91*\u0004I\u0001\u0002\u0004i\u0005bB)\u000e!\u0003\u0005\r!\u0014\u0005\b\'6\u0001\n\u00111\u0001V\u00039\u0019w\u000e]=%I\u00164\u0017-\u001e7uIE*\u0012\u0001 \u0016\u0003\u0005v\\\u0013A \t\u0004\u007f\u0006%QBAA\u0001\u0015\u0011\t\u0019!!\u0002\u0002\u0013Ut7\r[3dW\u0016$\'bAA\u0004Y\u0005Q\u0011M\u001c8pi\u0006$\u0018n\u001c8\n\t\u0005-\u0011\u0011\u0001\u0002\u0012k:\u001c\u0007.Z2lK\u00124\u0016M]5b]\u000e,\u0017AD2paf$C-\u001a4bk2$HEM\u000b\u0003\u0003#Q#!T?\u0002\u001d\r|\u0007/\u001f\u0013eK\u001a\fW\u000f\u001c;%g\u0005q1m\u001c9zI\u0011,g-Y;mi\u0012\"TCAA\rU\t)V0A\u0007qe>$Wo\u0019;Qe\u00164\u0017\u000e_\u0001\raJ|G-^2u\u0003JLG/_\u000b\u0003\u0003C\u00012aKA\u0012\u0013\r\t)\u0003\f\u0002\u0004\u0013:$\u0018A\u00049s_\u0012,8\r^#mK6,g\u000e\u001e\u000b\u0005\u0003W\t\t\u0004E\u0002,\u0003[I1!a\f-\u0005\r\te.\u001f\u0005\n\u0003g!\u0012\u0011!a\u0001\u0003C\t1\u0001\u001f\u00132\u0003=\u0001(o\u001c3vGRLE/\u001a:bi>\u0014XCAA\u001d!\u0019\tY$!\u0011\u0002,5\u0011\u0011Q\b\u0006\u0004\u0003\u007fa\u0013AC2pY2,7\r^5p]&!\u00111IA\u001f\u0005!IE/\u001a:bi>\u0014\u0018\u0001C2b]\u0016\u000bX/\u00197\u0015\u00075\fI\u0005C\u0005\u00024Y\t\t\u00111\u0001\u0002,\u0005\u0011\u0002O]8ek\u000e$X\t\\3nK:$h*Y7f)\r!\u0017q\n\u0005\n\u0003g9\u0012\u0011!a\u0001\u0003C\t\u0001\u0002[1tQ\u000e{G-\u001a\u000b\u0003\u0003C\t\u0001\u0002^8TiJLgn\u001a\u000b\u0002I\u00061Q-];bYN$2!\\A/\u0011%\t\u0019DGA\u0001\u0002\u0004\tY#\u0001\u0006Tk&$X\rU1sC6\u0004\"a\u0016\u000f\u0014\u000bq\t)\'!\u001d\u0011\u0013\u0005\u001d\u0014Q\u000e\"N\u001bVkVBAA5\u0015\r\tY\u0007L\u0001\beVtG/[7f\u0013\u0011\ty\'!\u001b\u0003#\u0005\u00137\u000f\u001e:bGR4UO\\2uS>tG\u0007\u0005\u0003\u0002t\u0005eTBAA;\u0015\r\t9\b[\u0001\u0003S>L1APA;)\t\t\t\'A\u0003baBd\u0017\u0010F\u0005^\u0003\u0003\u000b\u0019)!\"\u0002\b\")\u0001i\ba\u0001\u0005\")1j\ba\u0001\u001b\")\u0011k\ba\u0001\u001b\")1k\ba\u0001+\u00069QO\\1qa2LH\u0003BAG\u00033\u0003RaKAH\u0003\'K1!!%-\u0005\u0019y\u0005\u000f^5p]B91&!&C\u001b6+\u0016bAALY\t1A+\u001e9mKRB\u0001\"a\'!\u0003\u0003\u0005\r!X\u0001\u0004q\u0012\u0002\u0014\u0001D<sSR,\'+\u001a9mC\u000e,GCAAQ!\r)\u00171U\u0005\u0004\u0003K3\'AB(cU\u0016\u001cG\u000f"
    )
  ScalaInlineInfo: length = 0x7C (unknown attribute)
   01 00 00 18 00 73 00 74 00 00 99 00 6D 00 00 0F
   00 39 00 00 72 00 25 00 00 77 00 39 00 00 78 00
   3C 00 00 7B 00 3C 00 00 7E 00 41 00 00 6C 00 6D
   00 00 0D 00 39 01 00 44 00 39 01 00 A1 00 85 00
   00 61 00 62 00 00 65 00 66 00 00 13 00 41 00 00
   84 00 85 00 00 86 00 87 00 00 9B 00 9C 00 00 31
   00 32 00 00 8F 00 32 00 00 81 00 39 00 00 10 00
   3C 00 00 A6 00 39 00 00 12 00 3C 00
  ScalaSig: length = 0x3 (unknown attribute)
   05 02 00
