Classfile /Users/mw/Projects/slang-braindump/.jar/jar8/assemble/slang-braindump/assemble/content/org/scalatest/tools/SuiteResultHolder.class
  Last modified May 29, 2022; size 6015 bytes
  SHA-256 checksum 43a4bce089e78a46ecdd76c4f8326b677222f31c79ff618e1838ea48d5372d3c
  Compiled from "SuiteResultHolder.scala"
public class org.scalatest.tools.SuiteResultHolder
  minor version: 0
  major version: 52
  flags: (0x0021) ACC_PUBLIC, ACC_SUPER
  this_class: #2                          // org/scalatest/tools/SuiteResultHolder
  super_class: #4                         // java/lang/Object
  interfaces: 0, fields: 1, methods: 11, attributes: 6
Constant pool:
    #1 = Utf8               org/scalatest/tools/SuiteResultHolder
    #2 = Class              #1            // org/scalatest/tools/SuiteResultHolder
    #3 = Utf8               java/lang/Object
    #4 = Class              #3            // java/lang/Object
    #5 = Utf8               SuiteResultHolder.scala
    #6 = Utf8               Lscala/reflect/ScalaSignature;
    #7 = Utf8               bytes
    #8 = Utf8               \u0006\u0005q2Qa\u0002\u0005\u0001\u00159AQ!\u0006\u0001\u0005\u0002]AqA\u0007\u0001C\u0002\u0013\u00051\u0004\u0003\u0004(\u0001\u0001\u0006I\u0001\b\u0005\u0006Q\u0001!\t!\u000b\u0005\u0006_\u0001!\t\u0001\r\u0005\u0006o\u0001!\t\u0001\u000f\u0002\u0012\'VLG/\u001a*fgVdG\u000fS8mI\u0016\u0014(BA\u0005\u000b\u0003\u0015!xn\u001c7t\u0015\tYA\"A\u0005tG\u0006d\u0017\r^3ti*\tQ\"A\u0002pe\u001e\u001c\"\u0001A\b\u0011\u0005A\u0019R\"A\t\u000b\u0003I\tQa]2bY\u0006L!\u0001F\t\u0003\r\u0005s\u0017PU3g\u0003\u0019a\u0014N\\5u}\r\u0001A#\u0001\r\u0011\u0005e\u0001Q\"\u0001\u0005\u0002\u0013M,\u0018\u000e^3MSN$X#\u0001\u000f\u0011\u0007u\u0011C%D\u0001\u001f\u0015\ty\u0002%A\u0004nkR\f\'\r\\3\u000b\u0005\u0005\n\u0012AC2pY2,7\r^5p]&\u00111E\b\u0002\u000b\u0019&\u001cHOQ;gM\u0016\u0014\bCA\r&\u0013\t1\u0003BA\u0006Tk&$XMU3tk2$\u0018AC:vSR,G*[:uA\u0005AA\u0005\u001d7vg\u0012*\u0017\u000f\u0006\u0002+[A\u0011\u0001cK\u0005\u0003YE\u0011A!\u00168ji\")a\u0006\u0002a\u0001I\u00051!/Z:vYR\fqa];n[\u0006\u0014\u00180F\u00012!\t\u0011T\'D\u00014\u0015\t!$\"\u0001\u0004fm\u0016tGo]\u0005\u0003mM\u0012qaU;n[\u0006\u0014\u00180A\u0007u_R\fG\u000eR;sCRLwN\\\u000b\u0002sA\u0011\u0001CO\u0005\u0003wE\u0011A\u0001T8oO\u0002
    #9 = Utf8               java/lang/invoke/MethodHandles$Lookup
   #10 = Class              #9            // java/lang/invoke/MethodHandles$Lookup
   #11 = Utf8               java/lang/invoke/MethodHandles
   #12 = Class              #11           // java/lang/invoke/MethodHandles
   #13 = Utf8               Lookup
   #14 = Utf8               scala/math/Numeric$LongIsIntegral$
   #15 = Class              #14           // scala/math/Numeric$LongIsIntegral$
   #16 = Utf8               scala/math/Numeric
   #17 = Class              #16           // scala/math/Numeric
   #18 = Utf8               LongIsIntegral$
   #19 = Utf8               suiteList
   #20 = Utf8               Lscala/collection/mutable/ListBuffer;
   #21 = Utf8               Lscala/collection/mutable/ListBuffer<Lorg/scalatest/tools/SuiteResult;>;
   #22 = Utf8               ()Lscala/collection/mutable/ListBuffer;
   #23 = Utf8               ()Lscala/collection/mutable/ListBuffer<Lorg/scalatest/tools/SuiteResult;>;
   #24 = NameAndType        #19:#20       // suiteList:Lscala/collection/mutable/ListBuffer;
   #25 = Fieldref           #2.#24        // org/scalatest/tools/SuiteResultHolder.suiteList:Lscala/collection/mutable/ListBuffer;
   #26 = Utf8               this
   #27 = Utf8               Lorg/scalatest/tools/SuiteResultHolder;
   #28 = Utf8               $plus$eq
   #29 = Utf8               (Lorg/scalatest/tools/SuiteResult;)V
   #30 = Utf8               result
   #31 = NameAndType        #19:#22       // suiteList:()Lscala/collection/mutable/ListBuffer;
   #32 = Methodref          #2.#31        // org/scalatest/tools/SuiteResultHolder.suiteList:()Lscala/collection/mutable/ListBuffer;
   #33 = Utf8               scala/collection/mutable/ListBuffer
   #34 = Class              #33           // scala/collection/mutable/ListBuffer
   #35 = Utf8               (Ljava/lang/Object;)Lscala/collection/mutable/Growable;
   #36 = NameAndType        #28:#35       // $plus$eq:(Ljava/lang/Object;)Lscala/collection/mutable/Growable;
   #37 = Methodref          #34.#36       // scala/collection/mutable/ListBuffer.$plus$eq:(Ljava/lang/Object;)Lscala/collection/mutable/Growable;
   #38 = Utf8               Lorg/scalatest/tools/SuiteResult;
   #39 = Utf8               summary
   #40 = Utf8               ()Lorg/scalatest/events/Summary;
   #41 = Utf8               scala/Tuple6
   #42 = Class              #41           // scala/Tuple6
   #43 = Utf8               scala/runtime/BoxesRunTime
   #44 = Class              #43           // scala/runtime/BoxesRunTime
   #45 = Utf8               boxToInteger
   #46 = Utf8               (I)Ljava/lang/Integer;
   #47 = NameAndType        #45:#46       // boxToInteger:(I)Ljava/lang/Integer;
   #48 = Methodref          #44.#47       // scala/runtime/BoxesRunTime.boxToInteger:(I)Ljava/lang/Integer;
   #49 = Utf8               <init>
   #50 = Utf8               (Ljava/lang/Object;Ljava/lang/Object;Ljava/lang/Object;Ljava/lang/Object;Ljava/lang/Object;Ljava/lang/Object;)V
   #51 = NameAndType        #49:#50       // "<init>":(Ljava/lang/Object;Ljava/lang/Object;Ljava/lang/Object;Ljava/lang/Object;Ljava/lang/Object;Ljava/lang/Object;)V
   #52 = Methodref          #42.#51       // scala/Tuple6."<init>":(Ljava/lang/Object;Ljava/lang/Object;Ljava/lang/Object;Ljava/lang/Object;Ljava/lang/Object;Ljava/lang/Object;)V
   #53 = Utf8               (Ljava/lang/Object;Ljava/lang/Object;)Ljava/lang/Object;
   #54 = MethodType         #53           //  (Ljava/lang/Object;Ljava/lang/Object;)Ljava/lang/Object;
   #55 = Utf8               $anonfun$summary$1
   #56 = Utf8               (Lscala/Tuple6;Lorg/scalatest/tools/SuiteResult;)Lscala/Tuple6;
   #57 = NameAndType        #55:#56       // $anonfun$summary$1:(Lscala/Tuple6;Lorg/scalatest/tools/SuiteResult;)Lscala/Tuple6;
   #58 = Methodref          #2.#57        // org/scalatest/tools/SuiteResultHolder.$anonfun$summary$1:(Lscala/Tuple6;Lorg/scalatest/tools/SuiteResult;)Lscala/Tuple6;
   #59 = MethodHandle       6:#58         // REF_invokeStatic org/scalatest/tools/SuiteResultHolder.$anonfun$summary$1:(Lscala/Tuple6;Lorg/scalatest/tools/SuiteResult;)Lscala/Tuple6;
   #60 = MethodType         #56           //  (Lscala/Tuple6;Lorg/scalatest/tools/SuiteResult;)Lscala/Tuple6;
   #61 = Integer            5
   #62 = Integer            1
   #63 = Utf8               java/lang/invoke/LambdaMetafactory
   #64 = Class              #63           // java/lang/invoke/LambdaMetafactory
   #65 = Utf8               altMetafactory
   #66 = Utf8               (Ljava/lang/invoke/MethodHandles$Lookup;Ljava/lang/String;Ljava/lang/invoke/MethodType;[Ljava/lang/Object;)Ljava/lang/invoke/CallSite;
   #67 = NameAndType        #65:#66       // altMetafactory:(Ljava/lang/invoke/MethodHandles$Lookup;Ljava/lang/String;Ljava/lang/invoke/MethodType;[Ljava/lang/Object;)Ljava/lang/invoke/CallSite;
   #68 = Methodref          #64.#67       // java/lang/invoke/LambdaMetafactory.altMetafactory:(Ljava/lang/invoke/MethodHandles$Lookup;Ljava/lang/String;Ljava/lang/invoke/MethodType;[Ljava/lang/Object;)Ljava/lang/invoke/CallSite;
   #69 = MethodHandle       6:#68         // REF_invokeStatic java/lang/invoke/LambdaMetafactory.altMetafactory:(Ljava/lang/invoke/MethodHandles$Lookup;Ljava/lang/String;Ljava/lang/invoke/MethodType;[Ljava/lang/Object;)Ljava/lang/invoke/CallSite;
   #70 = Utf8               apply
   #71 = Utf8               ()Lscala/Function2;
   #72 = NameAndType        #70:#71       // apply:()Lscala/Function2;
   #73 = InvokeDynamic      #0:#72        // #0:apply:()Lscala/Function2;
   #74 = Utf8               foldLeft
   #75 = Utf8               (Ljava/lang/Object;Lscala/Function2;)Ljava/lang/Object;
   #76 = NameAndType        #74:#75       // foldLeft:(Ljava/lang/Object;Lscala/Function2;)Ljava/lang/Object;
   #77 = Methodref          #34.#76       // scala/collection/mutable/ListBuffer.foldLeft:(Ljava/lang/Object;Lscala/Function2;)Ljava/lang/Object;
   #78 = Utf8               _1
   #79 = Utf8               ()Ljava/lang/Object;
   #80 = NameAndType        #78:#79       // _1:()Ljava/lang/Object;
   #81 = Methodref          #42.#80       // scala/Tuple6._1:()Ljava/lang/Object;
   #82 = Utf8               unboxToInt
   #83 = Utf8               (Ljava/lang/Object;)I
   #84 = NameAndType        #82:#83       // unboxToInt:(Ljava/lang/Object;)I
   #85 = Methodref          #44.#84       // scala/runtime/BoxesRunTime.unboxToInt:(Ljava/lang/Object;)I
   #86 = Utf8               _2
   #87 = NameAndType        #86:#79       // _2:()Ljava/lang/Object;
   #88 = Methodref          #42.#87       // scala/Tuple6._2:()Ljava/lang/Object;
   #89 = Utf8               _3
   #90 = NameAndType        #89:#79       // _3:()Ljava/lang/Object;
   #91 = Methodref          #42.#90       // scala/Tuple6._3:()Ljava/lang/Object;
   #92 = Utf8               _4
   #93 = NameAndType        #92:#79       // _4:()Ljava/lang/Object;
   #94 = Methodref          #42.#93       // scala/Tuple6._4:()Ljava/lang/Object;
   #95 = Utf8               _5
   #96 = NameAndType        #95:#79       // _5:()Ljava/lang/Object;
   #97 = Methodref          #42.#96       // scala/Tuple6._5:()Ljava/lang/Object;
   #98 = Utf8               _6
   #99 = NameAndType        #98:#79       // _6:()Ljava/lang/Object;
  #100 = Methodref          #42.#99       // scala/Tuple6._6:()Ljava/lang/Object;
  #101 = Utf8               scala/MatchError
  #102 = Class              #101          // scala/MatchError
  #103 = Utf8               (Ljava/lang/Object;)V
  #104 = NameAndType        #49:#103      // "<init>":(Ljava/lang/Object;)V
  #105 = Methodref          #102.#104     // scala/MatchError."<init>":(Ljava/lang/Object;)V
  #106 = Utf8               org/scalatest/events/Summary
  #107 = Class              #106          // org/scalatest/events/Summary
  #108 = Utf8               length
  #109 = Utf8               ()I
  #110 = NameAndType        #108:#109     // length:()I
  #111 = Methodref          #34.#110      // scala/collection/mutable/ListBuffer.length:()I
  #112 = Utf8               (Ljava/lang/Object;)Ljava/lang/Object;
  #113 = MethodType         #112          //  (Ljava/lang/Object;)Ljava/lang/Object;
  #114 = Utf8               $anonfun$summary$2$adapted
  #115 = Utf8               (Lorg/scalatest/tools/SuiteResult;)Ljava/lang/Object;
  #116 = NameAndType        #114:#115     // $anonfun$summary$2$adapted:(Lorg/scalatest/tools/SuiteResult;)Ljava/lang/Object;
  #117 = Methodref          #2.#116       // org/scalatest/tools/SuiteResultHolder.$anonfun$summary$2$adapted:(Lorg/scalatest/tools/SuiteResult;)Ljava/lang/Object;
  #118 = MethodHandle       6:#117        // REF_invokeStatic org/scalatest/tools/SuiteResultHolder.$anonfun$summary$2$adapted:(Lorg/scalatest/tools/SuiteResult;)Ljava/lang/Object;
  #119 = MethodType         #115          //  (Lorg/scalatest/tools/SuiteResult;)Ljava/lang/Object;
  #120 = Utf8               ()Lscala/Function1;
  #121 = NameAndType        #70:#120      // apply:()Lscala/Function1;
  #122 = InvokeDynamic      #1:#121       // #1:apply:()Lscala/Function1;
  #123 = Utf8               filter
  #124 = Utf8               (Lscala/Function1;)Ljava/lang/Object;
  #125 = NameAndType        #123:#124     // filter:(Lscala/Function1;)Ljava/lang/Object;
  #126 = Methodref          #34.#125      // scala/collection/mutable/ListBuffer.filter:(Lscala/Function1;)Ljava/lang/Object;
  #127 = Utf8               (IIIIIIII)V
  #128 = NameAndType        #49:#127      // "<init>":(IIIIIIII)V
  #129 = Methodref          #107.#128     // org/scalatest/events/Summary."<init>":(IIIIIIII)V
  #130 = Utf8               succeeded
  #131 = Utf8               I
  #132 = Utf8               failed
  #133 = Utf8               ignored
  #134 = Utf8               pending
  #135 = Utf8               canceled
  #136 = Utf8               scopesPending
  #137 = Utf8               totalDuration
  #138 = Utf8               ()J
  #139 = Utf8               $anonfun$totalDuration$1$adapted
  #140 = NameAndType        #139:#115     // $anonfun$totalDuration$1$adapted:(Lorg/scalatest/tools/SuiteResult;)Ljava/lang/Object;
  #141 = Methodref          #2.#140       // org/scalatest/tools/SuiteResultHolder.$anonfun$totalDuration$1$adapted:(Lorg/scalatest/tools/SuiteResult;)Ljava/lang/Object;
  #142 = MethodHandle       6:#141        // REF_invokeStatic org/scalatest/tools/SuiteResultHolder.$anonfun$totalDuration$1$adapted:(Lorg/scalatest/tools/SuiteResult;)Ljava/lang/Object;
  #143 = InvokeDynamic      #2:#121       // #2:apply:()Lscala/Function1;
  #144 = Utf8               map
  #145 = NameAndType        #144:#124     // map:(Lscala/Function1;)Ljava/lang/Object;
  #146 = Methodref          #34.#145      // scala/collection/mutable/ListBuffer.map:(Lscala/Function1;)Ljava/lang/Object;
  #147 = Utf8               scala/collection/IterableOnceOps
  #148 = Class              #147          // scala/collection/IterableOnceOps
  #149 = Utf8               MODULE$
  #150 = Utf8               Lscala/math/Numeric$LongIsIntegral$;
  #151 = NameAndType        #149:#150     // MODULE$:Lscala/math/Numeric$LongIsIntegral$;
  #152 = Fieldref           #15.#151      // scala/math/Numeric$LongIsIntegral$.MODULE$:Lscala/math/Numeric$LongIsIntegral$;
  #153 = Utf8               sum
  #154 = Utf8               (Lscala/math/Numeric;)Ljava/lang/Object;
  #155 = NameAndType        #153:#154     // sum:(Lscala/math/Numeric;)Ljava/lang/Object;
  #156 = InterfaceMethodref #148.#155     // scala/collection/IterableOnceOps.sum:(Lscala/math/Numeric;)Ljava/lang/Object;
  #157 = Utf8               unboxToLong
  #158 = Utf8               (Ljava/lang/Object;)J
  #159 = NameAndType        #157:#158     // unboxToLong:(Ljava/lang/Object;)J
  #160 = Methodref          #44.#159      // scala/runtime/BoxesRunTime.unboxToLong:(Ljava/lang/Object;)J
  #161 = Utf8               x0$1
  #162 = Utf8               x1$1
  #163 = Utf8               scala/Tuple2
  #164 = Class              #163          // scala/Tuple2
  #165 = Utf8               (Ljava/lang/Object;Ljava/lang/Object;)V
  #166 = NameAndType        #49:#165      // "<init>":(Ljava/lang/Object;Ljava/lang/Object;)V
  #167 = Methodref          #164.#166     // scala/Tuple2."<init>":(Ljava/lang/Object;Ljava/lang/Object;)V
  #168 = Methodref          #164.#80      // scala/Tuple2._1:()Ljava/lang/Object;
  #169 = Methodref          #164.#87      // scala/Tuple2._2:()Ljava/lang/Object;
  #170 = Utf8               org/scalatest/tools/SuiteResult
  #171 = Class              #170          // org/scalatest/tools/SuiteResult
  #172 = Utf8               testsSucceededCount
  #173 = NameAndType        #172:#109     // testsSucceededCount:()I
  #174 = Methodref          #171.#173     // org/scalatest/tools/SuiteResult.testsSucceededCount:()I
  #175 = Utf8               testsFailedCount
  #176 = NameAndType        #175:#109     // testsFailedCount:()I
  #177 = Methodref          #171.#176     // org/scalatest/tools/SuiteResult.testsFailedCount:()I
  #178 = Utf8               testsIgnoredCount
  #179 = NameAndType        #178:#109     // testsIgnoredCount:()I
  #180 = Methodref          #171.#179     // org/scalatest/tools/SuiteResult.testsIgnoredCount:()I
  #181 = Utf8               testsPendingCount
  #182 = NameAndType        #181:#109     // testsPendingCount:()I
  #183 = Methodref          #171.#182     // org/scalatest/tools/SuiteResult.testsPendingCount:()I
  #184 = Utf8               testsCanceledCount
  #185 = NameAndType        #184:#109     // testsCanceledCount:()I
  #186 = Methodref          #171.#185     // org/scalatest/tools/SuiteResult.testsCanceledCount:()I
  #187 = Utf8               scopesPendingCount
  #188 = NameAndType        #187:#109     // scopesPendingCount:()I
  #189 = Methodref          #171.#188     // org/scalatest/tools/SuiteResult.scopesPendingCount:()I
  #190 = Utf8               r
  #191 = Utf8               Lscala/Tuple6;
  #192 = Utf8               $anonfun$summary$2
  #193 = Utf8               (Lorg/scalatest/tools/SuiteResult;)Z
  #194 = Utf8               x$2
  #195 = Utf8               isCompleted
  #196 = Utf8               ()Z
  #197 = NameAndType        #195:#196     // isCompleted:()Z
  #198 = Methodref          #171.#197     // org/scalatest/tools/SuiteResult.isCompleted:()Z
  #199 = Utf8               $anonfun$totalDuration$1
  #200 = Utf8               (Lorg/scalatest/tools/SuiteResult;)J
  #201 = Utf8               s
  #202 = Utf8               duration
  #203 = Utf8               ()Lscala/Option;
  #204 = NameAndType        #202:#203     // duration:()Lscala/Option;
  #205 = Methodref          #171.#204     // org/scalatest/tools/SuiteResult.duration:()Lscala/Option;
  #206 = Utf8               scala/Option
  #207 = Class              #206          // scala/Option
  #208 = Utf8               isDefined
  #209 = NameAndType        #208:#196     // isDefined:()Z
  #210 = Methodref          #207.#209     // scala/Option.isDefined:()Z
  #211 = Utf8               get
  #212 = NameAndType        #211:#79      // get:()Ljava/lang/Object;
  #213 = Methodref          #207.#212     // scala/Option.get:()Ljava/lang/Object;
  #214 = Utf8               ()V
  #215 = NameAndType        #49:#214      // "<init>":()V
  #216 = Methodref          #4.#215       // java/lang/Object."<init>":()V
  #217 = Methodref          #34.#215      // scala/collection/mutable/ListBuffer."<init>":()V
  #218 = NameAndType        #192:#193     // $anonfun$summary$2:(Lorg/scalatest/tools/SuiteResult;)Z
  #219 = Methodref          #2.#218       // org/scalatest/tools/SuiteResultHolder.$anonfun$summary$2:(Lorg/scalatest/tools/SuiteResult;)Z
  #220 = Utf8               boxToBoolean
  #221 = Utf8               (Z)Ljava/lang/Boolean;
  #222 = NameAndType        #220:#221     // boxToBoolean:(Z)Ljava/lang/Boolean;
  #223 = Methodref          #44.#222      // scala/runtime/BoxesRunTime.boxToBoolean:(Z)Ljava/lang/Boolean;
  #224 = NameAndType        #199:#200     // $anonfun$totalDuration$1:(Lorg/scalatest/tools/SuiteResult;)J
  #225 = Methodref          #2.#224       // org/scalatest/tools/SuiteResultHolder.$anonfun$totalDuration$1:(Lorg/scalatest/tools/SuiteResult;)J
  #226 = Utf8               boxToLong
  #227 = Utf8               (J)Ljava/lang/Long;
  #228 = NameAndType        #226:#227     // boxToLong:(J)Ljava/lang/Long;
  #229 = Methodref          #44.#228      // scala/runtime/BoxesRunTime.boxToLong:(J)Ljava/lang/Long;
  #230 = Utf8               $deserializeLambda$
  #231 = Utf8               (Ljava/lang/invoke/SerializedLambda;)Ljava/lang/Object;
  #232 = Utf8               scala/runtime/LambdaDeserialize
  #233 = Class              #232          // scala/runtime/LambdaDeserialize
  #234 = Utf8               bootstrap
  #235 = Utf8               (Ljava/lang/invoke/MethodHandles$Lookup;Ljava/lang/String;Ljava/lang/invoke/MethodType;[Ljava/lang/invoke/MethodHandle;)Ljava/lang/invoke/CallSite;
  #236 = NameAndType        #234:#235     // bootstrap:(Ljava/lang/invoke/MethodHandles$Lookup;Ljava/lang/String;Ljava/lang/invoke/MethodType;[Ljava/lang/invoke/MethodHandle;)Ljava/lang/invoke/CallSite;
  #237 = Methodref          #233.#236     // scala/runtime/LambdaDeserialize.bootstrap:(Ljava/lang/invoke/MethodHandles$Lookup;Ljava/lang/String;Ljava/lang/invoke/MethodType;[Ljava/lang/invoke/MethodHandle;)Ljava/lang/invoke/CallSite;
  #238 = MethodHandle       6:#237        // REF_invokeStatic scala/runtime/LambdaDeserialize.bootstrap:(Ljava/lang/invoke/MethodHandles$Lookup;Ljava/lang/String;Ljava/lang/invoke/MethodType;[Ljava/lang/invoke/MethodHandle;)Ljava/lang/invoke/CallSite;
  #239 = Utf8               lambdaDeserialize
  #240 = NameAndType        #239:#231     // lambdaDeserialize:(Ljava/lang/invoke/SerializedLambda;)Ljava/lang/Object;
  #241 = InvokeDynamic      #3:#240       // #3:lambdaDeserialize:(Ljava/lang/invoke/SerializedLambda;)Ljava/lang/Object;
  #242 = Utf8               Signature
  #243 = Utf8               Code
  #244 = Utf8               LineNumberTable
  #245 = Utf8               LocalVariableTable
  #246 = Utf8               MethodParameters
  #247 = Utf8               StackMapTable
  #248 = Utf8               InnerClasses
  #249 = Utf8               SourceFile
  #250 = Utf8               RuntimeVisibleAnnotations
  #251 = Utf8               BootstrapMethods
  #252 = Utf8               ScalaInlineInfo
  #253 = Utf8               ScalaSig
{
  private final scala.collection.mutable.ListBuffer<org.scalatest.tools.SuiteResult> suiteList;
    descriptor: Lscala/collection/mutable/ListBuffer;
    flags: (0x0012) ACC_PRIVATE, ACC_FINAL
    Signature: #21                          // Lscala/collection/mutable/ListBuffer<Lorg/scalatest/tools/SuiteResult;>;

  public scala.collection.mutable.ListBuffer<org.scalatest.tools.SuiteResult> suiteList();
    descriptor: ()Lscala/collection/mutable/ListBuffer;
    flags: (0x0001) ACC_PUBLIC
    Code:
      stack=1, locals=1, args_size=1
         0: aload_0
         1: getfield      #25                 // Field suiteList:Lscala/collection/mutable/ListBuffer;
         4: areturn
      LineNumberTable:
        line 23: 0
      LocalVariableTable:
        Start  Length  Slot  Name   Signature
            0       5     0  this   Lorg/scalatest/tools/SuiteResultHolder;
    Signature: #23                          // ()Lscala/collection/mutable/ListBuffer<Lorg/scalatest/tools/SuiteResult;>;

  public void $plus$eq(org.scalatest.tools.SuiteResult);
    descriptor: (Lorg/scalatest/tools/SuiteResult;)V
    flags: (0x0001) ACC_PUBLIC
    Code:
      stack=2, locals=2, args_size=2
         0: aload_0
         1: invokevirtual #32                 // Method suiteList:()Lscala/collection/mutable/ListBuffer;
         4: aload_1
         5: invokevirtual #37                 // Method scala/collection/mutable/ListBuffer.$plus$eq:(Ljava/lang/Object;)Lscala/collection/mutable/Growable;
         8: pop
         9: return
      LineNumberTable:
        line 26: 0
      LocalVariableTable:
        Start  Length  Slot  Name   Signature
            0      10     0  this   Lorg/scalatest/tools/SuiteResultHolder;
            0      10     1 result   Lorg/scalatest/tools/SuiteResult;
    MethodParameters:
      Name                           Flags
      result                         final

  public org.scalatest.events.Summary summary();
    descriptor: ()Lorg/scalatest/events/Summary;
    flags: (0x0001) ACC_PUBLIC
    Code:
      stack=10, locals=16, args_size=1
         0: aload_0
         1: invokevirtual #32                 // Method suiteList:()Lscala/collection/mutable/ListBuffer;
         4: new           #42                 // class scala/Tuple6
         7: dup
         8: iconst_0
         9: invokestatic  #48                 // Method scala/runtime/BoxesRunTime.boxToInteger:(I)Ljava/lang/Integer;
        12: iconst_0
        13: invokestatic  #48                 // Method scala/runtime/BoxesRunTime.boxToInteger:(I)Ljava/lang/Integer;
        16: iconst_0
        17: invokestatic  #48                 // Method scala/runtime/BoxesRunTime.boxToInteger:(I)Ljava/lang/Integer;
        20: iconst_0
        21: invokestatic  #48                 // Method scala/runtime/BoxesRunTime.boxToInteger:(I)Ljava/lang/Integer;
        24: iconst_0
        25: invokestatic  #48                 // Method scala/runtime/BoxesRunTime.boxToInteger:(I)Ljava/lang/Integer;
        28: iconst_0
        29: invokestatic  #48                 // Method scala/runtime/BoxesRunTime.boxToInteger:(I)Ljava/lang/Integer;
        32: invokespecial #52                 // Method scala/Tuple6."<init>":(Ljava/lang/Object;Ljava/lang/Object;Ljava/lang/Object;Ljava/lang/Object;Ljava/lang/Object;Ljava/lang/Object;)V
        35: invokedynamic #73,  0             // InvokeDynamic #0:apply:()Lscala/Function2;
        40: invokevirtual #77                 // Method scala/collection/mutable/ListBuffer.foldLeft:(Ljava/lang/Object;Lscala/Function2;)Ljava/lang/Object;
        43: checkcast     #42                 // class scala/Tuple6
        46: astore_3
        47: aload_3
        48: ifnull        146
        51: aload_3
        52: invokevirtual #81                 // Method scala/Tuple6._1:()Ljava/lang/Object;
        55: invokestatic  #85                 // Method scala/runtime/BoxesRunTime.unboxToInt:(Ljava/lang/Object;)I
        58: istore        4
        60: aload_3
        61: invokevirtual #88                 // Method scala/Tuple6._2:()Ljava/lang/Object;
        64: invokestatic  #85                 // Method scala/runtime/BoxesRunTime.unboxToInt:(Ljava/lang/Object;)I
        67: istore        5
        69: aload_3
        70: invokevirtual #91                 // Method scala/Tuple6._3:()Ljava/lang/Object;
        73: invokestatic  #85                 // Method scala/runtime/BoxesRunTime.unboxToInt:(Ljava/lang/Object;)I
        76: istore        6
        78: aload_3
        79: invokevirtual #94                 // Method scala/Tuple6._4:()Ljava/lang/Object;
        82: invokestatic  #85                 // Method scala/runtime/BoxesRunTime.unboxToInt:(Ljava/lang/Object;)I
        85: istore        7
        87: aload_3
        88: invokevirtual #97                 // Method scala/Tuple6._5:()Ljava/lang/Object;
        91: invokestatic  #85                 // Method scala/runtime/BoxesRunTime.unboxToInt:(Ljava/lang/Object;)I
        94: istore        8
        96: aload_3
        97: invokevirtual #100                // Method scala/Tuple6._6:()Ljava/lang/Object;
       100: invokestatic  #85                 // Method scala/runtime/BoxesRunTime.unboxToInt:(Ljava/lang/Object;)I
       103: istore        9
       105: new           #42                 // class scala/Tuple6
       108: dup
       109: iload         4
       111: invokestatic  #48                 // Method scala/runtime/BoxesRunTime.boxToInteger:(I)Ljava/lang/Integer;
       114: iload         5
       116: invokestatic  #48                 // Method scala/runtime/BoxesRunTime.boxToInteger:(I)Ljava/lang/Integer;
       119: iload         6
       121: invokestatic  #48                 // Method scala/runtime/BoxesRunTime.boxToInteger:(I)Ljava/lang/Integer;
       124: iload         7
       126: invokestatic  #48                 // Method scala/runtime/BoxesRunTime.boxToInteger:(I)Ljava/lang/Integer;
       129: iload         8
       131: invokestatic  #48                 // Method scala/runtime/BoxesRunTime.boxToInteger:(I)Ljava/lang/Integer;
       134: iload         9
       136: invokestatic  #48                 // Method scala/runtime/BoxesRunTime.boxToInteger:(I)Ljava/lang/Integer;
       139: invokespecial #52                 // Method scala/Tuple6."<init>":(Ljava/lang/Object;Ljava/lang/Object;Ljava/lang/Object;Ljava/lang/Object;Ljava/lang/Object;Ljava/lang/Object;)V
       142: astore_1
       143: goto          158
       146: goto          149
       149: new           #102                // class scala/MatchError
       152: dup
       153: aload_3
       154: invokespecial #105                // Method scala/MatchError."<init>":(Ljava/lang/Object;)V
       157: athrow
       158: aload_1
       159: astore_2
       160: aload_2
       161: invokevirtual #81                 // Method scala/Tuple6._1:()Ljava/lang/Object;
       164: invokestatic  #85                 // Method scala/runtime/BoxesRunTime.unboxToInt:(Ljava/lang/Object;)I
       167: istore        10
       169: aload_2
       170: invokevirtual #88                 // Method scala/Tuple6._2:()Ljava/lang/Object;
       173: invokestatic  #85                 // Method scala/runtime/BoxesRunTime.unboxToInt:(Ljava/lang/Object;)I
       176: istore        11
       178: aload_2
       179: invokevirtual #91                 // Method scala/Tuple6._3:()Ljava/lang/Object;
       182: invokestatic  #85                 // Method scala/runtime/BoxesRunTime.unboxToInt:(Ljava/lang/Object;)I
       185: istore        12
       187: aload_2
       188: invokevirtual #94                 // Method scala/Tuple6._4:()Ljava/lang/Object;
       191: invokestatic  #85                 // Method scala/runtime/BoxesRunTime.unboxToInt:(Ljava/lang/Object;)I
       194: istore        13
       196: aload_2
       197: invokevirtual #97                 // Method scala/Tuple6._5:()Ljava/lang/Object;
       200: invokestatic  #85                 // Method scala/runtime/BoxesRunTime.unboxToInt:(Ljava/lang/Object;)I
       203: istore        14
       205: aload_2
       206: invokevirtual #100                // Method scala/Tuple6._6:()Ljava/lang/Object;
       209: invokestatic  #85                 // Method scala/runtime/BoxesRunTime.unboxToInt:(Ljava/lang/Object;)I
       212: istore        15
       214: new           #107                // class org/scalatest/events/Summary
       217: dup
       218: iload         10
       220: iload         11
       222: iload         12
       224: iload         13
       226: iload         14
       228: aload_0
       229: invokevirtual #32                 // Method suiteList:()Lscala/collection/mutable/ListBuffer;
       232: invokevirtual #111                // Method scala/collection/mutable/ListBuffer.length:()I
       235: aload_0
       236: invokevirtual #32                 // Method suiteList:()Lscala/collection/mutable/ListBuffer;
       239: invokedynamic #122,  0            // InvokeDynamic #1:apply:()Lscala/Function1;
       244: invokevirtual #126                // Method scala/collection/mutable/ListBuffer.filter:(Lscala/Function1;)Ljava/lang/Object;
       247: checkcast     #34                 // class scala/collection/mutable/ListBuffer
       250: invokevirtual #111                // Method scala/collection/mutable/ListBuffer.length:()I
       253: iload         15
       255: invokespecial #129                // Method org/scalatest/events/Summary."<init>":(IIIIIIII)V
       258: areturn
      StackMapTable: number_of_entries = 3
        frame_type = 254 /* append */
          offset_delta = 146
          locals = [ top, top, class scala/Tuple6 ]
        frame_type = 2 /* same */
        frame_type = 255 /* full_frame */
          offset_delta = 8
          locals = [ class org/scalatest/tools/SuiteResultHolder, class scala/Tuple6, top, class scala/Tuple6, int, int, int, int, int, int ]
          stack = []
      LineNumberTable:
        line 30: 0
        line 34: 214
      LocalVariableTable:
        Start  Length  Slot  Name   Signature
           60      86     4 succeeded   I
           69      77     5 failed   I
           78      68     6 ignored   I
           87      59     7 pending   I
           96      50     8 canceled   I
          105      41     9 scopesPending   I
          169      89    10 succeeded   I
          178      80    11 failed   I
          187      71    12 ignored   I
          196      62    13 pending   I
          205      53    14 canceled   I
          214      44    15 scopesPending   I
            0     259     0  this   Lorg/scalatest/tools/SuiteResultHolder;

  public long totalDuration();
    descriptor: ()J
    flags: (0x0001) ACC_PUBLIC
    Code:
      stack=2, locals=1, args_size=1
         0: aload_0
         1: invokevirtual #32                 // Method suiteList:()Lscala/collection/mutable/ListBuffer;
         4: invokedynamic #143,  0            // InvokeDynamic #2:apply:()Lscala/Function1;
         9: invokevirtual #146                // Method scala/collection/mutable/ListBuffer.map:(Lscala/Function1;)Ljava/lang/Object;
        12: checkcast     #148                // class scala/collection/IterableOnceOps
        15: getstatic     #152                // Field scala/math/Numeric$LongIsIntegral$.MODULE$:Lscala/math/Numeric$LongIsIntegral$;
        18: invokeinterface #156,  2          // InterfaceMethod scala/collection/IterableOnceOps.sum:(Lscala/math/Numeric;)Ljava/lang/Object;
        23: invokestatic  #160                // Method scala/runtime/BoxesRunTime.unboxToLong:(Ljava/lang/Object;)J
        26: lreturn
      LineNumberTable:
        line 37: 0
      LocalVariableTable:
        Start  Length  Slot  Name   Signature
            0      27     0  this   Lorg/scalatest/tools/SuiteResultHolder;

  public static final scala.Tuple6 $anonfun$summary$1(scala.Tuple6, org.scalatest.tools.SuiteResult);
    descriptor: (Lscala/Tuple6;Lorg/scalatest/tools/SuiteResult;)Lscala/Tuple6;
    flags: (0x1019) ACC_PUBLIC, ACC_STATIC, ACC_FINAL, ACC_SYNTHETIC
    Code:
      stack=9, locals=12, args_size=2
         0: new           #164                // class scala/Tuple2
         3: dup
         4: aload_0
         5: aload_1
         6: invokespecial #167                // Method scala/Tuple2."<init>":(Ljava/lang/Object;Ljava/lang/Object;)V
         9: astore_3
        10: aload_3
        11: ifnull        177
        14: aload_3
        15: invokevirtual #168                // Method scala/Tuple2._1:()Ljava/lang/Object;
        18: checkcast     #42                 // class scala/Tuple6
        21: astore        4
        23: aload_3
        24: invokevirtual #169                // Method scala/Tuple2._2:()Ljava/lang/Object;
        27: checkcast     #171                // class org/scalatest/tools/SuiteResult
        30: astore        5
        32: aload         4
        34: ifnull        174
        37: aload         4
        39: invokevirtual #81                 // Method scala/Tuple6._1:()Ljava/lang/Object;
        42: invokestatic  #85                 // Method scala/runtime/BoxesRunTime.unboxToInt:(Ljava/lang/Object;)I
        45: istore        6
        47: aload         4
        49: invokevirtual #88                 // Method scala/Tuple6._2:()Ljava/lang/Object;
        52: invokestatic  #85                 // Method scala/runtime/BoxesRunTime.unboxToInt:(Ljava/lang/Object;)I
        55: istore        7
        57: aload         4
        59: invokevirtual #91                 // Method scala/Tuple6._3:()Ljava/lang/Object;
        62: invokestatic  #85                 // Method scala/runtime/BoxesRunTime.unboxToInt:(Ljava/lang/Object;)I
        65: istore        8
        67: aload         4
        69: invokevirtual #94                 // Method scala/Tuple6._4:()Ljava/lang/Object;
        72: invokestatic  #85                 // Method scala/runtime/BoxesRunTime.unboxToInt:(Ljava/lang/Object;)I
        75: istore        9
        77: aload         4
        79: invokevirtual #97                 // Method scala/Tuple6._5:()Ljava/lang/Object;
        82: invokestatic  #85                 // Method scala/runtime/BoxesRunTime.unboxToInt:(Ljava/lang/Object;)I
        85: istore        10
        87: aload         4
        89: invokevirtual #100                // Method scala/Tuple6._6:()Ljava/lang/Object;
        92: invokestatic  #85                 // Method scala/runtime/BoxesRunTime.unboxToInt:(Ljava/lang/Object;)I
        95: istore        11
        97: new           #42                 // class scala/Tuple6
       100: dup
       101: iload         6
       103: aload         5
       105: invokevirtual #174                // Method org/scalatest/tools/SuiteResult.testsSucceededCount:()I
       108: iadd
       109: invokestatic  #48                 // Method scala/runtime/BoxesRunTime.boxToInteger:(I)Ljava/lang/Integer;
       112: iload         7
       114: aload         5
       116: invokevirtual #177                // Method org/scalatest/tools/SuiteResult.testsFailedCount:()I
       119: iadd
       120: invokestatic  #48                 // Method scala/runtime/BoxesRunTime.boxToInteger:(I)Ljava/lang/Integer;
       123: iload         8
       125: aload         5
       127: invokevirtual #180                // Method org/scalatest/tools/SuiteResult.testsIgnoredCount:()I
       130: iadd
       131: invokestatic  #48                 // Method scala/runtime/BoxesRunTime.boxToInteger:(I)Ljava/lang/Integer;
       134: iload         9
       136: aload         5
       138: invokevirtual #183                // Method org/scalatest/tools/SuiteResult.testsPendingCount:()I
       141: iadd
       142: invokestatic  #48                 // Method scala/runtime/BoxesRunTime.boxToInteger:(I)Ljava/lang/Integer;
       145: iload         10
       147: aload         5
       149: invokevirtual #186                // Method org/scalatest/tools/SuiteResult.testsCanceledCount:()I
       152: iadd
       153: invokestatic  #48                 // Method scala/runtime/BoxesRunTime.boxToInteger:(I)Ljava/lang/Integer;
       156: iload         11
       158: aload         5
       160: invokevirtual #189                // Method org/scalatest/tools/SuiteResult.scopesPendingCount:()I
       163: iadd
       164: invokestatic  #48                 // Method scala/runtime/BoxesRunTime.boxToInteger:(I)Ljava/lang/Integer;
       167: invokespecial #52                 // Method scala/Tuple6."<init>":(Ljava/lang/Object;Ljava/lang/Object;Ljava/lang/Object;Ljava/lang/Object;Ljava/lang/Object;Ljava/lang/Object;)V
       170: astore_2
       171: goto          189
       174: goto          180
       177: goto          180
       180: new           #102                // class scala/MatchError
       183: dup
       184: aload_3
       185: invokespecial #105                // Method scala/MatchError."<init>":(Ljava/lang/Object;)V
       188: athrow
       189: aload_2
       190: areturn
      StackMapTable: number_of_entries = 4
        frame_type = 255 /* full_frame */
          offset_delta = 174
          locals = [ class scala/Tuple6, class org/scalatest/tools/SuiteResult, top, class scala/Tuple2, class scala/Tuple6, class org/scalatest/tools/SuiteResult ]
          stack = []
        frame_type = 249 /* chop */
          offset_delta = 2
        frame_type = 2 /* same */
        frame_type = 255 /* full_frame */
          offset_delta = 8
          locals = [ class scala/Tuple6, class org/scalatest/tools/SuiteResult, class scala/Tuple6, class scala/Tuple2, class scala/Tuple6, class org/scalatest/tools/SuiteResult, int, int, int, int, int, int ]
          stack = []
      LineNumberTable:
        line 30: 0
        line 31: 97
        line 32: 134
        line 30: 174
      LocalVariableTable:
        Start  Length  Slot  Name   Signature
           47     127     6 succeeded   I
           57     117     7 failed   I
           67     107     8 ignored   I
           77      97     9 pending   I
           87      87    10 canceled   I
           97      77    11 scopesPending   I
           32     145     5     r   Lorg/scalatest/tools/SuiteResult;
            0     191     0  x0$1   Lscala/Tuple6;
            0     191     1  x1$1   Lorg/scalatest/tools/SuiteResult;
    MethodParameters:
      Name                           Flags
      x0$1                           final
      x1$1                           final

  public static final boolean $anonfun$summary$2(org.scalatest.tools.SuiteResult);
    descriptor: (Lorg/scalatest/tools/SuiteResult;)Z
    flags: (0x1019) ACC_PUBLIC, ACC_STATIC, ACC_FINAL, ACC_SYNTHETIC
    Code:
      stack=1, locals=1, args_size=1
         0: aload_0
         1: invokevirtual #198                // Method org/scalatest/tools/SuiteResult.isCompleted:()Z
         4: ifne          11
         7: iconst_1
         8: goto          12
        11: iconst_0
        12: ireturn
      StackMapTable: number_of_entries = 2
        frame_type = 11 /* same */
        frame_type = 64 /* same_locals_1_stack_item */
          stack = [ int ]
      LineNumberTable:
        line 34: 0
      LocalVariableTable:
        Start  Length  Slot  Name   Signature
            0      13     0   x$2   Lorg/scalatest/tools/SuiteResult;
    MethodParameters:
      Name                           Flags
      x$2                            final

  public static final long $anonfun$totalDuration$1(org.scalatest.tools.SuiteResult);
    descriptor: (Lorg/scalatest/tools/SuiteResult;)J
    flags: (0x1019) ACC_PUBLIC, ACC_STATIC, ACC_FINAL, ACC_SYNTHETIC
    Code:
      stack=2, locals=1, args_size=1
         0: aload_0
         1: invokevirtual #205                // Method org/scalatest/tools/SuiteResult.duration:()Lscala/Option;
         4: invokevirtual #210                // Method scala/Option.isDefined:()Z
         7: ifeq          23
        10: aload_0
        11: invokevirtual #205                // Method org/scalatest/tools/SuiteResult.duration:()Lscala/Option;
        14: invokevirtual #213                // Method scala/Option.get:()Ljava/lang/Object;
        17: invokestatic  #160                // Method scala/runtime/BoxesRunTime.unboxToLong:(Ljava/lang/Object;)J
        20: goto          24
        23: lconst_0
        24: lreturn
      StackMapTable: number_of_entries = 2
        frame_type = 23 /* same */
        frame_type = 64 /* same_locals_1_stack_item */
          stack = [ long ]
      LineNumberTable:
        line 37: 0
      LocalVariableTable:
        Start  Length  Slot  Name   Signature
            0      25     0     s   Lorg/scalatest/tools/SuiteResult;
    MethodParameters:
      Name                           Flags
      s                              final

  public org.scalatest.tools.SuiteResultHolder();
    descriptor: ()V
    flags: (0x0001) ACC_PUBLIC
    Code:
      stack=3, locals=1, args_size=1
         0: aload_0
         1: invokespecial #216                // Method java/lang/Object."<init>":()V
         4: aload_0
         5: new           #34                 // class scala/collection/mutable/ListBuffer
         8: dup
         9: invokespecial #217                // Method scala/collection/mutable/ListBuffer."<init>":()V
        12: putfield      #25                 // Field suiteList:Lscala/collection/mutable/ListBuffer;
        15: return
      LineNumberTable:
        line 38: 0
        line 23: 4
        line 21: 15
      LocalVariableTable:
        Start  Length  Slot  Name   Signature
            0      16     0  this   Lorg/scalatest/tools/SuiteResultHolder;

  public static final java.lang.Object $anonfun$summary$2$adapted(org.scalatest.tools.SuiteResult);
    descriptor: (Lorg/scalatest/tools/SuiteResult;)Ljava/lang/Object;
    flags: (0x1019) ACC_PUBLIC, ACC_STATIC, ACC_FINAL, ACC_SYNTHETIC
    Code:
      stack=1, locals=1, args_size=1
         0: aload_0
         1: invokestatic  #219                // Method $anonfun$summary$2:(Lorg/scalatest/tools/SuiteResult;)Z
         4: invokestatic  #223                // Method scala/runtime/BoxesRunTime.boxToBoolean:(Z)Ljava/lang/Boolean;
         7: areturn
      LineNumberTable:
        line 34: 0
      LocalVariableTable:
        Start  Length  Slot  Name   Signature
            0       8     0   x$2   Lorg/scalatest/tools/SuiteResult;
    MethodParameters:
      Name                           Flags
      x$2                            final

  public static final java.lang.Object $anonfun$totalDuration$1$adapted(org.scalatest.tools.SuiteResult);
    descriptor: (Lorg/scalatest/tools/SuiteResult;)Ljava/lang/Object;
    flags: (0x1019) ACC_PUBLIC, ACC_STATIC, ACC_FINAL, ACC_SYNTHETIC
    Code:
      stack=2, locals=1, args_size=1
         0: aload_0
         1: invokestatic  #225                // Method $anonfun$totalDuration$1:(Lorg/scalatest/tools/SuiteResult;)J
         4: invokestatic  #229                // Method scala/runtime/BoxesRunTime.boxToLong:(J)Ljava/lang/Long;
         7: areturn
      LineNumberTable:
        line 37: 0
      LocalVariableTable:
        Start  Length  Slot  Name   Signature
            0       8     0     s   Lorg/scalatest/tools/SuiteResult;
    MethodParameters:
      Name                           Flags
      s                              final

  private static java.lang.Object $deserializeLambda$(java.lang.invoke.SerializedLambda);
    descriptor: (Ljava/lang/invoke/SerializedLambda;)Ljava/lang/Object;
    flags: (0x100a) ACC_PRIVATE, ACC_STATIC, ACC_SYNTHETIC
    Code:
      stack=1, locals=1, args_size=1
         0: aload_0
         1: invokedynamic #241,  0            // InvokeDynamic #3:lambdaDeserialize:(Ljava/lang/invoke/SerializedLambda;)Ljava/lang/Object;
         6: areturn
}
InnerClasses:
  public static final #13= #10 of #12;    // Lookup=class java/lang/invoke/MethodHandles$Lookup of class java/lang/invoke/MethodHandles
  public static #18= #15 of #17;          // LongIsIntegral$=class scala/math/Numeric$LongIsIntegral$ of class scala/math/Numeric
SourceFile: "SuiteResultHolder.scala"
RuntimeVisibleAnnotations:
  0: #6(#7=s#8)
    scala.reflect.ScalaSignature(
      bytes="\u0006\u0005q2Qa\u0002\u0005\u0001\u00159AQ!\u0006\u0001\u0005\u0002]AqA\u0007\u0001C\u0002\u0013\u00051\u0004\u0003\u0004(\u0001\u0001\u0006I\u0001\b\u0005\u0006Q\u0001!\t!\u000b\u0005\u0006_\u0001!\t\u0001\r\u0005\u0006o\u0001!\t\u0001\u000f\u0002\u0012\'VLG/\u001a*fgVdG\u000fS8mI\u0016\u0014(BA\u0005\u000b\u0003\u0015!xn\u001c7t\u0015\tYA\"A\u0005tG\u0006d\u0017\r^3ti*\tQ\"A\u0002pe\u001e\u001c\"\u0001A\b\u0011\u0005A\u0019R\"A\t\u000b\u0003I\tQa]2bY\u0006L!\u0001F\t\u0003\r\u0005s\u0017PU3g\u0003\u0019a\u0014N\\5u}\r\u0001A#\u0001\r\u0011\u0005e\u0001Q\"\u0001\u0005\u0002\u0013M,\u0018\u000e^3MSN$X#\u0001\u000f\u0011\u0007u\u0011C%D\u0001\u001f\u0015\ty\u0002%A\u0004nkR\f\'\r\\3\u000b\u0005\u0005\n\u0012AC2pY2,7\r^5p]&\u00111E\b\u0002\u000b\u0019&\u001cHOQ;gM\u0016\u0014\bCA\r&\u0013\t1\u0003BA\u0006Tk&$XMU3tk2$\u0018AC:vSR,G*[:uA\u0005AA\u0005\u001d7vg\u0012*\u0017\u000f\u0006\u0002+[A\u0011\u0001cK\u0005\u0003YE\u0011A!\u00168ji\")a\u0006\u0002a\u0001I\u00051!/Z:vYR\fqa];n[\u0006\u0014\u00180F\u00012!\t\u0011T\'D\u00014\u0015\t!$\"\u0001\u0004fm\u0016tGo]\u0005\u0003mM\u0012qaU;n[\u0006\u0014\u00180A\u0007u_R\fG\u000eR;sCRLwN\\\u000b\u0002sA\u0011\u0001CO\u0005\u0003wE\u0011A\u0001T8oO\u0002"
    )
BootstrapMethods:
  0: #69 REF_invokeStatic java/lang/invoke/LambdaMetafactory.altMetafactory:(Ljava/lang/invoke/MethodHandles$Lookup;Ljava/lang/String;Ljava/lang/invoke/MethodType;[Ljava/lang/Object;)Ljava/lang/invoke/CallSite;
    Method arguments:
      #54 (Ljava/lang/Object;Ljava/lang/Object;)Ljava/lang/Object;
      #59 REF_invokeStatic org/scalatest/tools/SuiteResultHolder.$anonfun$summary$1:(Lscala/Tuple6;Lorg/scalatest/tools/SuiteResult;)Lscala/Tuple6;
      #60 (Lscala/Tuple6;Lorg/scalatest/tools/SuiteResult;)Lscala/Tuple6;
      #61 5
      #62 1
      #60 (Lscala/Tuple6;Lorg/scalatest/tools/SuiteResult;)Lscala/Tuple6;
  1: #69 REF_invokeStatic java/lang/invoke/LambdaMetafactory.altMetafactory:(Ljava/lang/invoke/MethodHandles$Lookup;Ljava/lang/String;Ljava/lang/invoke/MethodType;[Ljava/lang/Object;)Ljava/lang/invoke/CallSite;
    Method arguments:
      #113 (Ljava/lang/Object;)Ljava/lang/Object;
      #118 REF_invokeStatic org/scalatest/tools/SuiteResultHolder.$anonfun$summary$2$adapted:(Lorg/scalatest/tools/SuiteResult;)Ljava/lang/Object;
      #119 (Lorg/scalatest/tools/SuiteResult;)Ljava/lang/Object;
      #61 5
      #62 1
      #119 (Lorg/scalatest/tools/SuiteResult;)Ljava/lang/Object;
  2: #69 REF_invokeStatic java/lang/invoke/LambdaMetafactory.altMetafactory:(Ljava/lang/invoke/MethodHandles$Lookup;Ljava/lang/String;Ljava/lang/invoke/MethodType;[Ljava/lang/Object;)Ljava/lang/invoke/CallSite;
    Method arguments:
      #113 (Ljava/lang/Object;)Ljava/lang/Object;
      #142 REF_invokeStatic org/scalatest/tools/SuiteResultHolder.$anonfun$totalDuration$1$adapted:(Lorg/scalatest/tools/SuiteResult;)Ljava/lang/Object;
      #119 (Lorg/scalatest/tools/SuiteResult;)Ljava/lang/Object;
      #61 5
      #62 1
      #119 (Lorg/scalatest/tools/SuiteResult;)Ljava/lang/Object;
  3: #238 REF_invokeStatic scala/runtime/LambdaDeserialize.bootstrap:(Ljava/lang/invoke/MethodHandles$Lookup;Ljava/lang/String;Ljava/lang/invoke/MethodType;[Ljava/lang/invoke/MethodHandle;)Ljava/lang/invoke/CallSite;
    Method arguments:
      #59 REF_invokeStatic org/scalatest/tools/SuiteResultHolder.$anonfun$summary$1:(Lscala/Tuple6;Lorg/scalatest/tools/SuiteResult;)Lscala/Tuple6;
      #118 REF_invokeStatic org/scalatest/tools/SuiteResultHolder.$anonfun$summary$2$adapted:(Lorg/scalatest/tools/SuiteResult;)Ljava/lang/Object;
      #142 REF_invokeStatic org/scalatest/tools/SuiteResultHolder.$anonfun$totalDuration$1$adapted:(Lorg/scalatest/tools/SuiteResult;)Ljava/lang/Object;
  ScalaInlineInfo: length = 0x36 (unknown attribute)
   01 00 00 0A 00 37 00 38 01 00 C0 00 C1 01 00 72
   00 73 01 00 C7 00 C8 01 00 8B 00 73 01 00 1C 00
   1D 00 00 31 00 D6 00 00 13 00 16 00 00 27 00 28
   00 00 89 00 8A 00
  ScalaSig: length = 0x3 (unknown attribute)
   05 02 00
