Classfile /Users/mw/Projects/slang-braindump/.jar/jar8/assemble/slang-braindump/assemble/content/org/scalatest/tools/SuiteConfig$.class
  Last modified May 29, 2022; size 2657 bytes
  SHA-256 checksum 55dcce83a9ead4ae2a694fba8d4aa47614b4ec42e37a7dc5159d802569b702f1
  Compiled from "Runner.scala"
public final class org.scalatest.tools.SuiteConfig$ extends scala.runtime.AbstractFunction4<org.scalatest.Suite, org.scalatest.DynaTags, java.lang.Object, java.lang.Object, org.scalatest.tools.SuiteConfig> implements java.io.Serializable
  minor version: 0
  major version: 52
  flags: (0x0031) ACC_PUBLIC, ACC_FINAL, ACC_SUPER
  this_class: #2                          // org/scalatest/tools/SuiteConfig$
  super_class: #5                         // scala/runtime/AbstractFunction4
  interfaces: 1, fields: 1, methods: 7, attributes: 4
Constant pool:
    #1 = Utf8               org/scalatest/tools/SuiteConfig$
    #2 = Class              #1            // org/scalatest/tools/SuiteConfig$
    #3 = Utf8               Lscala/runtime/AbstractFunction4<Lorg/scalatest/Suite;Lorg/scalatest/DynaTags;Ljava/lang/Object;Ljava/lang/Object;Lorg/scalatest/tools/SuiteConfig;>;Ljava/io/Serializable;
    #4 = Utf8               scala/runtime/AbstractFunction4
    #5 = Class              #4            // scala/runtime/AbstractFunction4
    #6 = Utf8               java/io/Serializable
    #7 = Class              #6            // java/io/Serializable
    #8 = Utf8               Runner.scala
    #9 = Utf8               MODULE$
   #10 = Utf8               Lorg/scalatest/tools/SuiteConfig$;
   #11 = Utf8               <clinit>
   #12 = Utf8               ()V
   #13 = Utf8               <init>
   #14 = NameAndType        #13:#12       // "<init>":()V
   #15 = Methodref          #2.#14        // org/scalatest/tools/SuiteConfig$."<init>":()V
   #16 = NameAndType        #9:#10        // MODULE$:Lorg/scalatest/tools/SuiteConfig$;
   #17 = Fieldref           #2.#16        // org/scalatest/tools/SuiteConfig$.MODULE$:Lorg/scalatest/tools/SuiteConfig$;
   #18 = Utf8               toString
   #19 = Utf8               ()Ljava/lang/String;
   #20 = Utf8               SuiteConfig
   #21 = String             #20           // SuiteConfig
   #22 = Utf8               this
   #23 = Utf8               apply
   #24 = Utf8               (Lorg/scalatest/Suite;Lorg/scalatest/DynaTags;ZZ)Lorg/scalatest/tools/SuiteConfig;
   #25 = Utf8               suite
   #26 = Utf8               dynaTags
   #27 = Utf8               requireSelectedTag
   #28 = Utf8               excludeNestedSuites
   #29 = Utf8               org/scalatest/tools/SuiteConfig
   #30 = Class              #29           // org/scalatest/tools/SuiteConfig
   #31 = Utf8               (Lorg/scalatest/Suite;Lorg/scalatest/DynaTags;ZZ)V
   #32 = NameAndType        #13:#31       // "<init>":(Lorg/scalatest/Suite;Lorg/scalatest/DynaTags;ZZ)V
   #33 = Methodref          #30.#32       // org/scalatest/tools/SuiteConfig."<init>":(Lorg/scalatest/Suite;Lorg/scalatest/DynaTags;ZZ)V
   #34 = Utf8               Lorg/scalatest/Suite;
   #35 = Utf8               Lorg/scalatest/DynaTags;
   #36 = Utf8               Z
   #37 = Utf8               unapply
   #38 = Utf8               (Lorg/scalatest/tools/SuiteConfig;)Lscala/Option;
   #39 = Utf8               (Lorg/scalatest/tools/SuiteConfig;)Lscala/Option<Lscala/Tuple4<Lorg/scalatest/Suite;Lorg/scalatest/DynaTags;Ljava/lang/Object;Ljava/lang/Object;>;>;
   #40 = Utf8               x$0
   #41 = Utf8               scala/None$
   #42 = Class              #41           // scala/None$
   #43 = Utf8               Lscala/None$;
   #44 = NameAndType        #9:#43        // MODULE$:Lscala/None$;
   #45 = Fieldref           #42.#44       // scala/None$.MODULE$:Lscala/None$;
   #46 = Utf8               scala/Some
   #47 = Class              #46           // scala/Some
   #48 = Utf8               scala/Tuple4
   #49 = Class              #48           // scala/Tuple4
   #50 = Utf8               ()Lorg/scalatest/Suite;
   #51 = NameAndType        #25:#50       // suite:()Lorg/scalatest/Suite;
   #52 = Methodref          #30.#51       // org/scalatest/tools/SuiteConfig.suite:()Lorg/scalatest/Suite;
   #53 = Utf8               ()Lorg/scalatest/DynaTags;
   #54 = NameAndType        #26:#53       // dynaTags:()Lorg/scalatest/DynaTags;
   #55 = Methodref          #30.#54       // org/scalatest/tools/SuiteConfig.dynaTags:()Lorg/scalatest/DynaTags;
   #56 = Utf8               ()Z
   #57 = NameAndType        #27:#56       // requireSelectedTag:()Z
   #58 = Methodref          #30.#57       // org/scalatest/tools/SuiteConfig.requireSelectedTag:()Z
   #59 = Utf8               scala/runtime/BoxesRunTime
   #60 = Class              #59           // scala/runtime/BoxesRunTime
   #61 = Utf8               boxToBoolean
   #62 = Utf8               (Z)Ljava/lang/Boolean;
   #63 = NameAndType        #61:#62       // boxToBoolean:(Z)Ljava/lang/Boolean;
   #64 = Methodref          #60.#63       // scala/runtime/BoxesRunTime.boxToBoolean:(Z)Ljava/lang/Boolean;
   #65 = NameAndType        #28:#56       // excludeNestedSuites:()Z
   #66 = Methodref          #30.#65       // org/scalatest/tools/SuiteConfig.excludeNestedSuites:()Z
   #67 = Utf8               (Ljava/lang/Object;Ljava/lang/Object;Ljava/lang/Object;Ljava/lang/Object;)V
   #68 = NameAndType        #13:#67       // "<init>":(Ljava/lang/Object;Ljava/lang/Object;Ljava/lang/Object;Ljava/lang/Object;)V
   #69 = Methodref          #49.#68       // scala/Tuple4."<init>":(Ljava/lang/Object;Ljava/lang/Object;Ljava/lang/Object;Ljava/lang/Object;)V
   #70 = Utf8               (Ljava/lang/Object;)V
   #71 = NameAndType        #13:#70       // "<init>":(Ljava/lang/Object;)V
   #72 = Methodref          #47.#71       // scala/Some."<init>":(Ljava/lang/Object;)V
   #73 = Utf8               Lorg/scalatest/tools/SuiteConfig;
   #74 = Utf8               scala/Option
   #75 = Class              #74           // scala/Option
   #76 = Utf8               writeReplace
   #77 = Utf8               ()Ljava/lang/Object;
   #78 = Utf8               scala/runtime/ModuleSerializationProxy
   #79 = Class              #78           // scala/runtime/ModuleSerializationProxy
   #80 = Utf8               (Ljava/lang/Class;)V
   #81 = NameAndType        #13:#80       // "<init>":(Ljava/lang/Class;)V
   #82 = Methodref          #79.#81       // scala/runtime/ModuleSerializationProxy."<init>":(Ljava/lang/Class;)V
   #83 = Utf8               (Ljava/lang/Object;Ljava/lang/Object;Ljava/lang/Object;Ljava/lang/Object;)Ljava/lang/Object;
   #84 = Utf8               v1
   #85 = Utf8               v2
   #86 = Utf8               v3
   #87 = Utf8               v4
   #88 = Utf8               org/scalatest/Suite
   #89 = Class              #88           // org/scalatest/Suite
   #90 = Utf8               org/scalatest/DynaTags
   #91 = Class              #90           // org/scalatest/DynaTags
   #92 = Utf8               unboxToBoolean
   #93 = Utf8               (Ljava/lang/Object;)Z
   #94 = NameAndType        #92:#93       // unboxToBoolean:(Ljava/lang/Object;)Z
   #95 = Methodref          #60.#94       // scala/runtime/BoxesRunTime.unboxToBoolean:(Ljava/lang/Object;)Z
   #96 = NameAndType        #23:#24       // apply:(Lorg/scalatest/Suite;Lorg/scalatest/DynaTags;ZZ)Lorg/scalatest/tools/SuiteConfig;
   #97 = Methodref          #2.#96        // org/scalatest/tools/SuiteConfig$.apply:(Lorg/scalatest/Suite;Lorg/scalatest/DynaTags;ZZ)Lorg/scalatest/tools/SuiteConfig;
   #98 = Utf8               Ljava/lang/Object;
   #99 = Methodref          #5.#14        // scala/runtime/AbstractFunction4."<init>":()V
  #100 = Utf8               Code
  #101 = Utf8               LineNumberTable
  #102 = Utf8               LocalVariableTable
  #103 = Utf8               MethodParameters
  #104 = Utf8               StackMapTable
  #105 = Utf8               Signature
  #106 = Utf8               SourceFile
  #107 = Utf8               ScalaInlineInfo
  #108 = Utf8               Scala
{
  public static final org.scalatest.tools.SuiteConfig$ MODULE$;
    descriptor: Lorg/scalatest/tools/SuiteConfig$;
    flags: (0x0019) ACC_PUBLIC, ACC_STATIC, ACC_FINAL

  public static {};
    descriptor: ()V
    flags: (0x0009) ACC_PUBLIC, ACC_STATIC
    Code:
      stack=2, locals=0, args_size=0
         0: new           #2                  // class org/scalatest/tools/SuiteConfig$
         3: dup
         4: invokespecial #15                 // Method "<init>":()V
         7: putstatic     #17                 // Field MODULE$:Lorg/scalatest/tools/SuiteConfig$;
        10: return
      LineNumberTable:
        line 126: 0

  public final java.lang.String toString();
    descriptor: ()Ljava/lang/String;
    flags: (0x0011) ACC_PUBLIC, ACC_FINAL
    Code:
      stack=1, locals=1, args_size=1
         0: ldc           #21                 // String SuiteConfig
         2: areturn
      LineNumberTable:
        line 126: 0
      LocalVariableTable:
        Start  Length  Slot  Name   Signature
            0       3     0  this   Lorg/scalatest/tools/SuiteConfig$;

  public org.scalatest.tools.SuiteConfig apply(org.scalatest.Suite, org.scalatest.DynaTags, boolean, boolean);
    descriptor: (Lorg/scalatest/Suite;Lorg/scalatest/DynaTags;ZZ)Lorg/scalatest/tools/SuiteConfig;
    flags: (0x0001) ACC_PUBLIC
    Code:
      stack=6, locals=5, args_size=5
         0: new           #30                 // class org/scalatest/tools/SuiteConfig
         3: dup
         4: aload_1
         5: aload_2
         6: iload_3
         7: iload         4
         9: invokespecial #33                 // Method org/scalatest/tools/SuiteConfig."<init>":(Lorg/scalatest/Suite;Lorg/scalatest/DynaTags;ZZ)V
        12: areturn
      LineNumberTable:
        line 126: 0
      LocalVariableTable:
        Start  Length  Slot  Name   Signature
            0      13     0  this   Lorg/scalatest/tools/SuiteConfig$;
            0      13     1 suite   Lorg/scalatest/Suite;
            0      13     2 dynaTags   Lorg/scalatest/DynaTags;
            0      13     3 requireSelectedTag   Z
            0      13     4 excludeNestedSuites   Z
    MethodParameters:
      Name                           Flags
      suite                          final
      dynaTags                       final
      requireSelectedTag             final
      excludeNestedSuites            final

  public scala.Option<scala.Tuple4<org.scalatest.Suite, org.scalatest.DynaTags, java.lang.Object, java.lang.Object>> unapply(org.scalatest.tools.SuiteConfig);
    descriptor: (Lorg/scalatest/tools/SuiteConfig;)Lscala/Option;
    flags: (0x0001) ACC_PUBLIC
    Code:
      stack=8, locals=2, args_size=2
         0: aload_1
         1: ifnonnull     10
         4: getstatic     #45                 // Field scala/None$.MODULE$:Lscala/None$;
         7: goto          46
        10: new           #47                 // class scala/Some
        13: dup
        14: new           #49                 // class scala/Tuple4
        17: dup
        18: aload_1
        19: invokevirtual #52                 // Method org/scalatest/tools/SuiteConfig.suite:()Lorg/scalatest/Suite;
        22: aload_1
        23: invokevirtual #55                 // Method org/scalatest/tools/SuiteConfig.dynaTags:()Lorg/scalatest/DynaTags;
        26: aload_1
        27: invokevirtual #58                 // Method org/scalatest/tools/SuiteConfig.requireSelectedTag:()Z
        30: invokestatic  #64                 // Method scala/runtime/BoxesRunTime.boxToBoolean:(Z)Ljava/lang/Boolean;
        33: aload_1
        34: invokevirtual #66                 // Method org/scalatest/tools/SuiteConfig.excludeNestedSuites:()Z
        37: invokestatic  #64                 // Method scala/runtime/BoxesRunTime.boxToBoolean:(Z)Ljava/lang/Boolean;
        40: invokespecial #69                 // Method scala/Tuple4."<init>":(Ljava/lang/Object;Ljava/lang/Object;Ljava/lang/Object;Ljava/lang/Object;)V
        43: invokespecial #72                 // Method scala/Some."<init>":(Ljava/lang/Object;)V
        46: areturn
      StackMapTable: number_of_entries = 2
        frame_type = 10 /* same */
        frame_type = 99 /* same_locals_1_stack_item */
          stack = [ class scala/Option ]
      LineNumberTable:
        line 126: 0
      LocalVariableTable:
        Start  Length  Slot  Name   Signature
            0      47     0  this   Lorg/scalatest/tools/SuiteConfig$;
            0      47     1   x$0   Lorg/scalatest/tools/SuiteConfig;
    Signature: #39                          // (Lorg/scalatest/tools/SuiteConfig;)Lscala/Option<Lscala/Tuple4<Lorg/scalatest/Suite;Lorg/scalatest/DynaTags;Ljava/lang/Object;Ljava/lang/Object;>;>;
    MethodParameters:
      Name                           Flags
      x$0                            final

  private java.lang.Object writeReplace();
    descriptor: ()Ljava/lang/Object;
    flags: (0x0002) ACC_PRIVATE
    Code:
      stack=3, locals=1, args_size=1
         0: new           #79                 // class scala/runtime/ModuleSerializationProxy
         3: dup
         4: ldc           #2                  // class org/scalatest/tools/SuiteConfig$
         6: invokespecial #82                 // Method scala/runtime/ModuleSerializationProxy."<init>":(Ljava/lang/Class;)V
         9: areturn
      LineNumberTable:
        line 126: 0
      LocalVariableTable:
        Start  Length  Slot  Name   Signature
            0      10     0  this   Lorg/scalatest/tools/SuiteConfig$;

  public java.lang.Object apply(java.lang.Object, java.lang.Object, java.lang.Object, java.lang.Object);
    descriptor: (Ljava/lang/Object;Ljava/lang/Object;Ljava/lang/Object;Ljava/lang/Object;)Ljava/lang/Object;
    flags: (0x1041) ACC_PUBLIC, ACC_BRIDGE, ACC_SYNTHETIC
    Code:
      stack=5, locals=5, args_size=5
         0: aload_0
         1: aload_1
         2: checkcast     #89                 // class org/scalatest/Suite
         5: aload_2
         6: checkcast     #91                 // class org/scalatest/DynaTags
         9: aload_3
        10: invokestatic  #95                 // Method scala/runtime/BoxesRunTime.unboxToBoolean:(Ljava/lang/Object;)Z
        13: aload         4
        15: invokestatic  #95                 // Method scala/runtime/BoxesRunTime.unboxToBoolean:(Ljava/lang/Object;)Z
        18: invokevirtual #97                 // Method apply:(Lorg/scalatest/Suite;Lorg/scalatest/DynaTags;ZZ)Lorg/scalatest/tools/SuiteConfig;
        21: areturn
      LineNumberTable:
        line 126: 0
      LocalVariableTable:
        Start  Length  Slot  Name   Signature
            0      22     0  this   Lorg/scalatest/tools/SuiteConfig$;
            0      22     1    v1   Ljava/lang/Object;
            0      22     2    v2   Ljava/lang/Object;
            0      22     3    v3   Ljava/lang/Object;
            0      22     4    v4   Ljava/lang/Object;
    MethodParameters:
      Name                           Flags
      v1                             final
      v2                             final
      v3                             final
      v4                             final

  private org.scalatest.tools.SuiteConfig$();
    descriptor: ()V
    flags: (0x0002) ACC_PRIVATE
    Code:
      stack=1, locals=1, args_size=1
         0: aload_0
         1: invokespecial #99                 // Method scala/runtime/AbstractFunction4."<init>":()V
         4: return
      LineNumberTable:
        line 126: 0
      LocalVariableTable:
        Start  Length  Slot  Name   Signature
            0       5     0  this   Lorg/scalatest/tools/SuiteConfig$;
}
Signature: #3                           // Lscala/runtime/AbstractFunction4<Lorg/scalatest/Suite;Lorg/scalatest/DynaTags;Ljava/lang/Object;Ljava/lang/Object;Lorg/scalatest/tools/SuiteConfig;>;Ljava/io/Serializable;
SourceFile: "Runner.scala"
  ScalaInlineInfo: length = 0x22 (unknown attribute)
   01 01 00 06 00 0D 00 0C 01 00 17 00 53 01 00 17
   00 18 01 00 12 00 13 01 00 25 00 26 01 00 4C 00
   4D 01
  Scala: length = 0x0 (unknown attribute)

