Classfile /Users/mw/Projects/slang-braindump/.jar/jar8/assemble/slang-braindump/assemble/content/org/scalatest/tools/TestElement.class
  Last modified May 29, 2022; size 1840 bytes
  SHA-256 checksum b0cd19a46c2175931bfc64d18f28fd1d8255e041da83235c91582a969e2af020
  Compiled from "ScalaTestAntTask.scala"
public class org.scalatest.tools.TestElement
  minor version: 0
  major version: 52
  flags: (0x0021) ACC_PUBLIC, ACC_SUPER
  this_class: #2                          // org/scalatest/tools/TestElement
  super_class: #4                         // java/lang/Object
  interfaces: 0, fields: 2, methods: 9, attributes: 4
Constant pool:
   #1 = Utf8               org/scalatest/tools/TestElement
   #2 = Class              #1             // org/scalatest/tools/TestElement
   #3 = Utf8               java/lang/Object
   #4 = Class              #3             // java/lang/Object
   #5 = Utf8               ScalaTestAntTask.scala
   #6 = Utf8               Lscala/reflect/ScalaSignature;
   #7 = Utf8               bytes
   #8 = Utf8               \u0006\u0005\u00053Q\u0001D\u0007\u0001\u001bMAQA\u0007\u0001\u0005\u0002qAqa\b\u0001A\u0002\u0013%\u0001\u0005C\u0004-\u0001\u0001\u0007I\u0011B\u0017\t\rM\u0002\u0001\u0015)\u0003\"\u0011\u001d!\u0004\u00011A\u0005\n\u0001Bq!\u000e\u0001A\u0002\u0013%a\u0007\u0003\u00049\u0001\u0001\u0006K!\t\u0005\u0006s\u0001!\tA\u000f\u0005\u0006y\u0001!\t!\u0010\u0005\u0006\u007f\u0001!\t\u0001\t\u0005\u0006\u0001\u0002!\t\u0001\t\u0002\f)\u0016\u001cH/\u00127f[\u0016tGO\u0003\u0002\u000f\u001f\u0005)Ao\\8mg*\u0011\u0001#E\u0001\ng\u000e\fG.\u0019;fgRT\u0011AE\u0001\u0004_J<7C\u0001\u0001\u0015!\t)\u0002$D\u0001\u0017\u0015\u00059\u0012!B:dC2\f\u0017BA\r\u0017\u0005\u0019\te.\u001f*fM\u00061A(\u001b8jiz\u001a\u0001\u0001F\u0001\u001e!\tq\u0002!D\u0001\u000e\u0003\u0011q\u0017-\\3\u0016\u0003\u0005\u0002\"AI\u0015\u000f\u0005\r:\u0003C\u0001\u0013\u0017\u001b\u0005)#B\u0001\u0014\u001c\u0003\u0019a$o\\8u}%\u0011\u0001FF\u0001\u0007!J,G-\u001a4\n\u0005)Z#AB*ue&twM\u0003\u0002)-\u0005Aa.Y7f?\u0012*\u0017\u000f\u0006\u0002/cA\u0011QcL\u0005\u0003aY\u0011A!\u00168ji\"9!gAA\u0001\u0002\u0004\t\u0013a\u0001=%c\u0005)a.Y7fA\u0005I1/\u001e2tiJLgnZ\u0001\u000egV\u00147\u000f\u001e:j]\u001e|F%Z9\u0015\u00059:\u0004b\u0002\u001a\u0007\u0003\u0003\u0005\r!I\u0001\u000bgV\u00147\u000f\u001e:j]\u001e\u0004\u0013aB:fi:\u000bW.\u001a\u000b\u0003]mBQa\b\u0005A\u0002\u0005\nAb]3u\'V\u00147\u000f\u001e:j]\u001e$\"A\f \t\u000bQJ\u0001\u0019A\u0011\u0002\u000f\u001d,GOT1nK\u0006aq-\u001a;Tk\n\u001cHO]5oO\u0002
   #9 = Utf8               name
  #10 = Utf8               Ljava/lang/String;
  #11 = Utf8               substring
  #12 = Utf8               ()Ljava/lang/String;
  #13 = NameAndType        #9:#10         // name:Ljava/lang/String;
  #14 = Fieldref           #2.#13         // org/scalatest/tools/TestElement.name:Ljava/lang/String;
  #15 = Utf8               this
  #16 = Utf8               Lorg/scalatest/tools/TestElement;
  #17 = Utf8               name_$eq
  #18 = Utf8               (Ljava/lang/String;)V
  #19 = Utf8               x$1
  #20 = NameAndType        #11:#10        // substring:Ljava/lang/String;
  #21 = Fieldref           #2.#20         // org/scalatest/tools/TestElement.substring:Ljava/lang/String;
  #22 = Utf8               substring_$eq
  #23 = Utf8               setName
  #24 = NameAndType        #17:#18        // name_$eq:(Ljava/lang/String;)V
  #25 = Methodref          #2.#24         // org/scalatest/tools/TestElement.name_$eq:(Ljava/lang/String;)V
  #26 = Utf8               setSubstring
  #27 = NameAndType        #22:#18        // substring_$eq:(Ljava/lang/String;)V
  #28 = Methodref          #2.#27         // org/scalatest/tools/TestElement.substring_$eq:(Ljava/lang/String;)V
  #29 = Utf8               getName
  #30 = NameAndType        #9:#12         // name:()Ljava/lang/String;
  #31 = Methodref          #2.#30         // org/scalatest/tools/TestElement.name:()Ljava/lang/String;
  #32 = Utf8               getSubstring
  #33 = NameAndType        #11:#12        // substring:()Ljava/lang/String;
  #34 = Methodref          #2.#33         // org/scalatest/tools/TestElement.substring:()Ljava/lang/String;
  #35 = Utf8               <init>
  #36 = Utf8               ()V
  #37 = NameAndType        #35:#36        // "<init>":()V
  #38 = Methodref          #4.#37         // java/lang/Object."<init>":()V
  #39 = Utf8               Code
  #40 = Utf8               LineNumberTable
  #41 = Utf8               LocalVariableTable
  #42 = Utf8               MethodParameters
  #43 = Utf8               SourceFile
  #44 = Utf8               RuntimeVisibleAnnotations
  #45 = Utf8               ScalaInlineInfo
  #46 = Utf8               ScalaSig
{
  private java.lang.String name;
    descriptor: Ljava/lang/String;
    flags: (0x0002) ACC_PRIVATE

  private java.lang.String substring;
    descriptor: Ljava/lang/String;
    flags: (0x0002) ACC_PRIVATE

  private java.lang.String name();
    descriptor: ()Ljava/lang/String;
    flags: (0x0002) ACC_PRIVATE
    Code:
      stack=1, locals=1, args_size=1
         0: aload_0
         1: getfield      #14                 // Field name:Ljava/lang/String;
         4: areturn
      LineNumberTable:
        line 1020: 0
      LocalVariableTable:
        Start  Length  Slot  Name   Signature
            0       5     0  this   Lorg/scalatest/tools/TestElement;

  private void name_$eq(java.lang.String);
    descriptor: (Ljava/lang/String;)V
    flags: (0x0002) ACC_PRIVATE
    Code:
      stack=2, locals=2, args_size=2
         0: aload_0
         1: aload_1
         2: putfield      #14                 // Field name:Ljava/lang/String;
         5: return
      LineNumberTable:
        line 1020: 0
      LocalVariableTable:
        Start  Length  Slot  Name   Signature
            0       6     0  this   Lorg/scalatest/tools/TestElement;
            0       6     1   x$1   Ljava/lang/String;
    MethodParameters:
      Name                           Flags
      x$1                            final

  private java.lang.String substring();
    descriptor: ()Ljava/lang/String;
    flags: (0x0002) ACC_PRIVATE
    Code:
      stack=1, locals=1, args_size=1
         0: aload_0
         1: getfield      #21                 // Field substring:Ljava/lang/String;
         4: areturn
      LineNumberTable:
        line 1021: 0
      LocalVariableTable:
        Start  Length  Slot  Name   Signature
            0       5     0  this   Lorg/scalatest/tools/TestElement;

  private void substring_$eq(java.lang.String);
    descriptor: (Ljava/lang/String;)V
    flags: (0x0002) ACC_PRIVATE
    Code:
      stack=2, locals=2, args_size=2
         0: aload_0
         1: aload_1
         2: putfield      #21                 // Field substring:Ljava/lang/String;
         5: return
      LineNumberTable:
        line 1021: 0
      LocalVariableTable:
        Start  Length  Slot  Name   Signature
            0       6     0  this   Lorg/scalatest/tools/TestElement;
            0       6     1   x$1   Ljava/lang/String;
    MethodParameters:
      Name                           Flags
      x$1                            final

  public void setName(java.lang.String);
    descriptor: (Ljava/lang/String;)V
    flags: (0x0001) ACC_PUBLIC
    Code:
      stack=2, locals=2, args_size=2
         0: aload_0
         1: aload_1
         2: invokespecial #25                 // Method name_$eq:(Ljava/lang/String;)V
         5: return
      LineNumberTable:
        line 1024: 0
      LocalVariableTable:
        Start  Length  Slot  Name   Signature
            0       6     0  this   Lorg/scalatest/tools/TestElement;
            0       6     1  name   Ljava/lang/String;
    MethodParameters:
      Name                           Flags
      name                           final

  public void setSubstring(java.lang.String);
    descriptor: (Ljava/lang/String;)V
    flags: (0x0001) ACC_PUBLIC
    Code:
      stack=2, locals=2, args_size=2
         0: aload_0
         1: aload_1
         2: invokespecial #28                 // Method substring_$eq:(Ljava/lang/String;)V
         5: return
      LineNumberTable:
        line 1028: 0
      LocalVariableTable:
        Start  Length  Slot  Name   Signature
            0       6     0  this   Lorg/scalatest/tools/TestElement;
            0       6     1 substring   Ljava/lang/String;
    MethodParameters:
      Name                           Flags
      substring                      final

  public java.lang.String getName();
    descriptor: ()Ljava/lang/String;
    flags: (0x0001) ACC_PUBLIC
    Code:
      stack=1, locals=1, args_size=1
         0: aload_0
         1: invokespecial #31                 // Method name:()Ljava/lang/String;
         4: areturn
      LineNumberTable:
        line 1031: 0
      LocalVariableTable:
        Start  Length  Slot  Name   Signature
            0       5     0  this   Lorg/scalatest/tools/TestElement;

  public java.lang.String getSubstring();
    descriptor: ()Ljava/lang/String;
    flags: (0x0001) ACC_PUBLIC
    Code:
      stack=1, locals=1, args_size=1
         0: aload_0
         1: invokespecial #34                 // Method substring:()Ljava/lang/String;
         4: areturn
      LineNumberTable:
        line 1032: 0
      LocalVariableTable:
        Start  Length  Slot  Name   Signature
            0       5     0  this   Lorg/scalatest/tools/TestElement;

  public org.scalatest.tools.TestElement();
    descriptor: ()V
    flags: (0x0001) ACC_PUBLIC
    Code:
      stack=2, locals=1, args_size=1
         0: aload_0
         1: invokespecial #38                 // Method java/lang/Object."<init>":()V
         4: aload_0
         5: aconst_null
         6: putfield      #14                 // Field name:Ljava/lang/String;
         9: aload_0
        10: aconst_null
        11: putfield      #21                 // Field substring:Ljava/lang/String;
        14: return
      LineNumberTable:
        line 1035: 0
        line 1020: 4
        line 1021: 9
        line 1019: 14
      LocalVariableTable:
        Start  Length  Slot  Name   Signature
            0      15     0  this   Lorg/scalatest/tools/TestElement;
}
SourceFile: "ScalaTestAntTask.scala"
RuntimeVisibleAnnotations:
  0: #6(#7=s#8)
    scala.reflect.ScalaSignature(
      bytes="\u0006\u0005\u00053Q\u0001D\u0007\u0001\u001bMAQA\u0007\u0001\u0005\u0002qAqa\b\u0001A\u0002\u0013%\u0001\u0005C\u0004-\u0001\u0001\u0007I\u0011B\u0017\t\rM\u0002\u0001\u0015)\u0003\"\u0011\u001d!\u0004\u00011A\u0005\n\u0001Bq!\u000e\u0001A\u0002\u0013%a\u0007\u0003\u00049\u0001\u0001\u0006K!\t\u0005\u0006s\u0001!\tA\u000f\u0005\u0006y\u0001!\t!\u0010\u0005\u0006\u007f\u0001!\t\u0001\t\u0005\u0006\u0001\u0002!\t\u0001\t\u0002\f)\u0016\u001cH/\u00127f[\u0016tGO\u0003\u0002\u000f\u001f\u0005)Ao\\8mg*\u0011\u0001#E\u0001\ng\u000e\fG.\u0019;fgRT\u0011AE\u0001\u0004_J<7C\u0001\u0001\u0015!\t)\u0002$D\u0001\u0017\u0015\u00059\u0012!B:dC2\f\u0017BA\r\u0017\u0005\u0019\te.\u001f*fM\u00061A(\u001b8jiz\u001a\u0001\u0001F\u0001\u001e!\tq\u0002!D\u0001\u000e\u0003\u0011q\u0017-\\3\u0016\u0003\u0005\u0002\"AI\u0015\u000f\u0005\r:\u0003C\u0001\u0013\u0017\u001b\u0005)#B\u0001\u0014\u001c\u0003\u0019a$o\\8u}%\u0011\u0001FF\u0001\u0007!J,G-\u001a4\n\u0005)Z#AB*ue&twM\u0003\u0002)-\u0005Aa.Y7f?\u0012*\u0017\u000f\u0006\u0002/cA\u0011QcL\u0005\u0003aY\u0011A!\u00168ji\"9!gAA\u0001\u0002\u0004\t\u0013a\u0001=%c\u0005)a.Y7fA\u0005I1/\u001e2tiJLgnZ\u0001\u000egV\u00147\u000f\u001e:j]\u001e|F%Z9\u0015\u00059:\u0004b\u0002\u001a\u0007\u0003\u0003\u0005\r!I\u0001\u000bgV\u00147\u000f\u001e:j]\u001e\u0004\u0013aB:fi:\u000bW.\u001a\u000b\u0003]mBQa\b\u0005A\u0002\u0005\nAb]3u\'V\u00147\u000f\u001e:j]\u001e$\"A\f \t\u000bQJ\u0001\u0019A\u0011\u0002\u000f\u001d,GOT1nK\u0006aq-\u001a;Tk\n\u001cHO]5oO\u0002"
    )
  ScalaInlineInfo: length = 0x31 (unknown attribute)
   01 00 00 09 00 23 00 24 00 00 1D 00 0C 00 00 20
   00 0C 00 00 09 00 0C 01 00 11 00 12 01 00 17 00
   12 00 00 1A 00 12 00 00 0B 00 0C 01 00 16 00 12
   01
  ScalaSig: length = 0x3 (unknown attribute)
   05 02 00
