Classfile /Users/mw/Projects/slang-braindump/.jar/jar8/assemble/slang-braindump/assemble/content/org/scalatest/tools/TestSortingReporter$Slot.class
  Last modified May 29, 2022; size 5308 bytes
  SHA-256 checksum 64a2f664bf4fea0d658a37a12808331a87baa7bdce9c674a12947dd5798c4019
  Compiled from "TestSortingReporter.scala"
public class org.scalatest.tools.TestSortingReporter$Slot implements scala.Product,java.io.Serializable
  minor version: 0
  major version: 52
  flags: (0x0021) ACC_PUBLIC, ACC_SUPER
  this_class: #2                          // org/scalatest/tools/TestSortingReporter$Slot
  super_class: #4                         // java/lang/Object
  interfaces: 2, fields: 6, methods: 23, attributes: 4
Constant pool:
    #1 = Utf8               org/scalatest/tools/TestSortingReporter$Slot
    #2 = Class              #1            // org/scalatest/tools/TestSortingReporter$Slot
    #3 = Utf8               java/lang/Object
    #4 = Class              #3            // java/lang/Object
    #5 = Utf8               scala/Product
    #6 = Class              #5            // scala/Product
    #7 = Utf8               java/io/Serializable
    #8 = Class              #7            // java/io/Serializable
    #9 = Utf8               TestSortingReporter.scala
   #10 = Utf8               org/scalatest/tools/TestSortingReporter
   #11 = Class              #10           // org/scalatest/tools/TestSortingReporter
   #12 = Utf8               Slot
   #13 = Utf8               uuid
   #14 = Utf8               Ljava/util/UUID;
   #15 = Utf8               eventList
   #16 = Utf8               Lscala/collection/mutable/ListBuffer;
   #17 = Utf8               Lscala/collection/mutable/ListBuffer<Lorg/scalatest/events/Event;>;
   #18 = Utf8               completed
   #19 = Utf8               Z
   #20 = Utf8               completedEvent
   #21 = Utf8               ready
   #22 = Utf8               $outer
   #23 = Utf8               Lorg/scalatest/tools/TestSortingReporter;
   #24 = Utf8               productElementNames
   #25 = Utf8               ()Lscala/collection/Iterator;
   #26 = Utf8               ()Lscala/collection/Iterator<Ljava/lang/String;>;
   #27 = Utf8               productElementNames$
   #28 = Utf8               (Lscala/Product;)Lscala/collection/Iterator;
   #29 = NameAndType        #27:#28       // productElementNames$:(Lscala/Product;)Lscala/collection/Iterator;
   #30 = InterfaceMethodref #6.#29        // scala/Product.productElementNames$:(Lscala/Product;)Lscala/collection/Iterator;
   #31 = Utf8               this
   #32 = Utf8               Lorg/scalatest/tools/TestSortingReporter$Slot;
   #33 = Utf8               ()Ljava/util/UUID;
   #34 = NameAndType        #13:#14       // uuid:Ljava/util/UUID;
   #35 = Fieldref           #2.#34        // org/scalatest/tools/TestSortingReporter$Slot.uuid:Ljava/util/UUID;
   #36 = Utf8               ()Lscala/collection/mutable/ListBuffer;
   #37 = Utf8               ()Lscala/collection/mutable/ListBuffer<Lorg/scalatest/events/Event;>;
   #38 = NameAndType        #15:#16       // eventList:Lscala/collection/mutable/ListBuffer;
   #39 = Fieldref           #2.#38        // org/scalatest/tools/TestSortingReporter$Slot.eventList:Lscala/collection/mutable/ListBuffer;
   #40 = Utf8               ()Z
   #41 = NameAndType        #18:#19       // completed:Z
   #42 = Fieldref           #2.#41        // org/scalatest/tools/TestSortingReporter$Slot.completed:Z
   #43 = NameAndType        #20:#19       // completedEvent:Z
   #44 = Fieldref           #2.#43        // org/scalatest/tools/TestSortingReporter$Slot.completedEvent:Z
   #45 = NameAndType        #21:#19       // ready:Z
   #46 = Fieldref           #2.#45        // org/scalatest/tools/TestSortingReporter$Slot.ready:Z
   #47 = Utf8               copy
   #48 = Utf8               (Ljava/util/UUID;Lscala/collection/mutable/ListBuffer;ZZZ)Lorg/scalatest/tools/TestSortingReporter$Slot;
   #49 = Utf8               (Ljava/util/UUID;Lscala/collection/mutable/ListBuffer<Lorg/scalatest/events/Event;>;ZZZ)Lorg/scalatest/tools/TestSortingReporter$Slot;
   #50 = Utf8               org$scalatest$tools$TestSortingReporter$Slot$$$outer
   #51 = Utf8               ()Lorg/scalatest/tools/TestSortingReporter;
   #52 = NameAndType        #50:#51       // org$scalatest$tools$TestSortingReporter$Slot$$$outer:()Lorg/scalatest/tools/TestSortingReporter;
   #53 = Methodref          #2.#52        // org/scalatest/tools/TestSortingReporter$Slot.org$scalatest$tools$TestSortingReporter$Slot$$$outer:()Lorg/scalatest/tools/TestSortingReporter;
   #54 = Utf8               <init>
   #55 = Utf8               (Lorg/scalatest/tools/TestSortingReporter;Ljava/util/UUID;Lscala/collection/mutable/ListBuffer;ZZZ)V
   #56 = NameAndType        #54:#55       // "<init>":(Lorg/scalatest/tools/TestSortingReporter;Ljava/util/UUID;Lscala/collection/mutable/ListBuffer;ZZZ)V
   #57 = Methodref          #2.#56        // org/scalatest/tools/TestSortingReporter$Slot."<init>":(Lorg/scalatest/tools/TestSortingReporter;Ljava/util/UUID;Lscala/collection/mutable/ListBuffer;ZZZ)V
   #58 = Utf8               copy$default$1
   #59 = NameAndType        #13:#33       // uuid:()Ljava/util/UUID;
   #60 = Methodref          #2.#59        // org/scalatest/tools/TestSortingReporter$Slot.uuid:()Ljava/util/UUID;
   #61 = Utf8               copy$default$2
   #62 = NameAndType        #15:#36       // eventList:()Lscala/collection/mutable/ListBuffer;
   #63 = Methodref          #2.#62        // org/scalatest/tools/TestSortingReporter$Slot.eventList:()Lscala/collection/mutable/ListBuffer;
   #64 = Utf8               copy$default$3
   #65 = NameAndType        #18:#40       // completed:()Z
   #66 = Methodref          #2.#65        // org/scalatest/tools/TestSortingReporter$Slot.completed:()Z
   #67 = Utf8               copy$default$4
   #68 = NameAndType        #20:#40       // completedEvent:()Z
   #69 = Methodref          #2.#68        // org/scalatest/tools/TestSortingReporter$Slot.completedEvent:()Z
   #70 = Utf8               copy$default$5
   #71 = NameAndType        #21:#40       // ready:()Z
   #72 = Methodref          #2.#71        // org/scalatest/tools/TestSortingReporter$Slot.ready:()Z
   #73 = Utf8               productPrefix
   #74 = Utf8               ()Ljava/lang/String;
   #75 = String             #12           // Slot
   #76 = Utf8               productArity
   #77 = Utf8               ()I
   #78 = Utf8               productElement
   #79 = Utf8               (I)Ljava/lang/Object;
   #80 = Utf8               x$1
   #81 = Utf8               scala/runtime/BoxesRunTime
   #82 = Class              #81           // scala/runtime/BoxesRunTime
   #83 = Utf8               boxToBoolean
   #84 = Utf8               (Z)Ljava/lang/Boolean;
   #85 = NameAndType        #83:#84       // boxToBoolean:(Z)Ljava/lang/Boolean;
   #86 = Methodref          #82.#85       // scala/runtime/BoxesRunTime.boxToBoolean:(Z)Ljava/lang/Boolean;
   #87 = Utf8               scala/runtime/Statics
   #88 = Class              #87           // scala/runtime/Statics
   #89 = Utf8               ioobe
   #90 = NameAndType        #89:#79       // ioobe:(I)Ljava/lang/Object;
   #91 = Methodref          #88.#90       // scala/runtime/Statics.ioobe:(I)Ljava/lang/Object;
   #92 = Utf8               I
   #93 = Utf8               productIterator
   #94 = Utf8               ()Lscala/collection/Iterator<Ljava/lang/Object;>;
   #95 = Utf8               scala/runtime/ScalaRunTime$
   #96 = Class              #95           // scala/runtime/ScalaRunTime$
   #97 = Utf8               MODULE$
   #98 = Utf8               Lscala/runtime/ScalaRunTime$;
   #99 = NameAndType        #97:#98       // MODULE$:Lscala/runtime/ScalaRunTime$;
  #100 = Fieldref           #96.#99       // scala/runtime/ScalaRunTime$.MODULE$:Lscala/runtime/ScalaRunTime$;
  #101 = Utf8               typedProductIterator
  #102 = NameAndType        #101:#28      // typedProductIterator:(Lscala/Product;)Lscala/collection/Iterator;
  #103 = Methodref          #96.#102      // scala/runtime/ScalaRunTime$.typedProductIterator:(Lscala/Product;)Lscala/collection/Iterator;
  #104 = Utf8               canEqual
  #105 = Utf8               (Ljava/lang/Object;)Z
  #106 = Utf8               Ljava/lang/Object;
  #107 = Utf8               productElementName
  #108 = Utf8               (I)Ljava/lang/String;
  #109 = String             #13           // uuid
  #110 = String             #15           // eventList
  #111 = String             #18           // completed
  #112 = String             #20           // completedEvent
  #113 = String             #21           // ready
  #114 = Utf8               java/lang/String
  #115 = Class              #114          // java/lang/String
  #116 = Utf8               hashCode
  #117 = Integer            -889275714
  #118 = NameAndType        #73:#74       // productPrefix:()Ljava/lang/String;
  #119 = Methodref          #2.#118       // org/scalatest/tools/TestSortingReporter$Slot.productPrefix:()Ljava/lang/String;
  #120 = NameAndType        #116:#77      // hashCode:()I
  #121 = Methodref          #115.#120     // java/lang/String.hashCode:()I
  #122 = Utf8               mix
  #123 = Utf8               (II)I
  #124 = NameAndType        #122:#123     // mix:(II)I
  #125 = Methodref          #88.#124      // scala/runtime/Statics.mix:(II)I
  #126 = Utf8               anyHash
  #127 = Utf8               (Ljava/lang/Object;)I
  #128 = NameAndType        #126:#127     // anyHash:(Ljava/lang/Object;)I
  #129 = Methodref          #88.#128      // scala/runtime/Statics.anyHash:(Ljava/lang/Object;)I
  #130 = Utf8               finalizeHash
  #131 = NameAndType        #130:#123     // finalizeHash:(II)I
  #132 = Methodref          #88.#131      // scala/runtime/Statics.finalizeHash:(II)I
  #133 = Utf8               toString
  #134 = Utf8               _toString
  #135 = Utf8               (Lscala/Product;)Ljava/lang/String;
  #136 = NameAndType        #134:#135     // _toString:(Lscala/Product;)Ljava/lang/String;
  #137 = Methodref          #96.#136      // scala/runtime/ScalaRunTime$._toString:(Lscala/Product;)Ljava/lang/String;
  #138 = Utf8               equals
  #139 = NameAndType        #138:#105     // equals:(Ljava/lang/Object;)Z
  #140 = Methodref          #4.#139       // java/lang/Object.equals:(Ljava/lang/Object;)Z
  #141 = NameAndType        #104:#105     // canEqual:(Ljava/lang/Object;)Z
  #142 = Methodref          #2.#141       // org/scalatest/tools/TestSortingReporter$Slot.canEqual:(Ljava/lang/Object;)Z
  #143 = Utf8               java/util/UUID
  #144 = Class              #143          // java/util/UUID
  #145 = Utf8               scala/collection/mutable/ListBuffer
  #146 = Class              #145          // scala/collection/mutable/ListBuffer
  #147 = NameAndType        #22:#23       // $outer:Lorg/scalatest/tools/TestSortingReporter;
  #148 = Fieldref           #2.#147       // org/scalatest/tools/TestSortingReporter$Slot.$outer:Lorg/scalatest/tools/TestSortingReporter;
  #149 = Utf8               (Ljava/util/UUID;Lscala/collection/mutable/ListBuffer<Lorg/scalatest/events/Event;>;ZZZ)V
  #150 = Utf8               ()V
  #151 = NameAndType        #54:#150      // "<init>":()V
  #152 = Methodref          #4.#151       // java/lang/Object."<init>":()V
  #153 = Utf8               $init$
  #154 = Utf8               (Lscala/Product;)V
  #155 = NameAndType        #153:#154     // $init$:(Lscala/Product;)V
  #156 = InterfaceMethodref #6.#155       // scala/Product.$init$:(Lscala/Product;)V
  #157 = Utf8               Signature
  #158 = Utf8               Code
  #159 = Utf8               LineNumberTable
  #160 = Utf8               LocalVariableTable
  #161 = Utf8               MethodParameters
  #162 = Utf8               StackMapTable
  #163 = Utf8               InnerClasses
  #164 = Utf8               SourceFile
  #165 = Utf8               ScalaInlineInfo
  #166 = Utf8               Scala
{
  private final java.util.UUID uuid;
    descriptor: Ljava/util/UUID;
    flags: (0x0012) ACC_PRIVATE, ACC_FINAL

  private final scala.collection.mutable.ListBuffer<org.scalatest.events.Event> eventList;
    descriptor: Lscala/collection/mutable/ListBuffer;
    flags: (0x0012) ACC_PRIVATE, ACC_FINAL
    Signature: #17                          // Lscala/collection/mutable/ListBuffer<Lorg/scalatest/events/Event;>;

  private final boolean completed;
    descriptor: Z
    flags: (0x0012) ACC_PRIVATE, ACC_FINAL

  private final boolean completedEvent;
    descriptor: Z
    flags: (0x0012) ACC_PRIVATE, ACC_FINAL

  private final boolean ready;
    descriptor: Z
    flags: (0x0012) ACC_PRIVATE, ACC_FINAL

  public final org.scalatest.tools.TestSortingReporter $outer;
    descriptor: Lorg/scalatest/tools/TestSortingReporter;
    flags: (0x1011) ACC_PUBLIC, ACC_FINAL, ACC_SYNTHETIC

  public scala.collection.Iterator<java.lang.String> productElementNames();
    descriptor: ()Lscala/collection/Iterator;
    flags: (0x0001) ACC_PUBLIC
    Code:
      stack=1, locals=1, args_size=1
         0: aload_0
         1: invokestatic  #30                 // InterfaceMethod scala/Product.productElementNames$:(Lscala/Product;)Lscala/collection/Iterator;
         4: areturn
      LineNumberTable:
        line 38: 0
      LocalVariableTable:
        Start  Length  Slot  Name   Signature
            0       5     0  this   Lorg/scalatest/tools/TestSortingReporter$Slot;
    Signature: #26                          // ()Lscala/collection/Iterator<Ljava/lang/String;>;

  public java.util.UUID uuid();
    descriptor: ()Ljava/util/UUID;
    flags: (0x0001) ACC_PUBLIC
    Code:
      stack=1, locals=1, args_size=1
         0: aload_0
         1: getfield      #35                 // Field uuid:Ljava/util/UUID;
         4: areturn
      LineNumberTable:
        line 38: 0
      LocalVariableTable:
        Start  Length  Slot  Name   Signature
            0       5     0  this   Lorg/scalatest/tools/TestSortingReporter$Slot;

  public scala.collection.mutable.ListBuffer<org.scalatest.events.Event> eventList();
    descriptor: ()Lscala/collection/mutable/ListBuffer;
    flags: (0x0001) ACC_PUBLIC
    Code:
      stack=1, locals=1, args_size=1
         0: aload_0
         1: getfield      #39                 // Field eventList:Lscala/collection/mutable/ListBuffer;
         4: areturn
      LineNumberTable:
        line 38: 0
      LocalVariableTable:
        Start  Length  Slot  Name   Signature
            0       5     0  this   Lorg/scalatest/tools/TestSortingReporter$Slot;
    Signature: #37                          // ()Lscala/collection/mutable/ListBuffer<Lorg/scalatest/events/Event;>;

  public boolean completed();
    descriptor: ()Z
    flags: (0x0001) ACC_PUBLIC
    Code:
      stack=1, locals=1, args_size=1
         0: aload_0
         1: getfield      #42                 // Field completed:Z
         4: ireturn
      LineNumberTable:
        line 38: 0
      LocalVariableTable:
        Start  Length  Slot  Name   Signature
            0       5     0  this   Lorg/scalatest/tools/TestSortingReporter$Slot;

  public boolean completedEvent();
    descriptor: ()Z
    flags: (0x0001) ACC_PUBLIC
    Code:
      stack=1, locals=1, args_size=1
         0: aload_0
         1: getfield      #44                 // Field completedEvent:Z
         4: ireturn
      LineNumberTable:
        line 38: 0
      LocalVariableTable:
        Start  Length  Slot  Name   Signature
            0       5     0  this   Lorg/scalatest/tools/TestSortingReporter$Slot;

  public boolean ready();
    descriptor: ()Z
    flags: (0x0001) ACC_PUBLIC
    Code:
      stack=1, locals=1, args_size=1
         0: aload_0
         1: getfield      #46                 // Field ready:Z
         4: ireturn
      LineNumberTable:
        line 38: 0
      LocalVariableTable:
        Start  Length  Slot  Name   Signature
            0       5     0  this   Lorg/scalatest/tools/TestSortingReporter$Slot;

  public org.scalatest.tools.TestSortingReporter$Slot copy(java.util.UUID, scala.collection.mutable.ListBuffer<org.scalatest.events.Event>, boolean, boolean, boolean);
    descriptor: (Ljava/util/UUID;Lscala/collection/mutable/ListBuffer;ZZZ)Lorg/scalatest/tools/TestSortingReporter$Slot;
    flags: (0x0001) ACC_PUBLIC
    Code:
      stack=8, locals=6, args_size=6
         0: new           #2                  // class org/scalatest/tools/TestSortingReporter$Slot
         3: dup
         4: aload_0
         5: invokevirtual #53                 // Method org$scalatest$tools$TestSortingReporter$Slot$$$outer:()Lorg/scalatest/tools/TestSortingReporter;
         8: aload_1
         9: aload_2
        10: iload_3
        11: iload         4
        13: iload         5
        15: invokespecial #57                 // Method "<init>":(Lorg/scalatest/tools/TestSortingReporter;Ljava/util/UUID;Lscala/collection/mutable/ListBuffer;ZZZ)V
        18: areturn
      LineNumberTable:
        line 38: 0
      LocalVariableTable:
        Start  Length  Slot  Name   Signature
            0      19     0  this   Lorg/scalatest/tools/TestSortingReporter$Slot;
            0      19     1  uuid   Ljava/util/UUID;
            0      19     2 eventList   Lscala/collection/mutable/ListBuffer;
            0      19     3 completed   Z
            0      19     4 completedEvent   Z
            0      19     5 ready   Z
    Signature: #49                          // (Ljava/util/UUID;Lscala/collection/mutable/ListBuffer<Lorg/scalatest/events/Event;>;ZZZ)Lorg/scalatest/tools/TestSortingReporter$Slot;
    MethodParameters:
      Name                           Flags
      uuid                           final
      eventList                      final
      completed                      final
      completedEvent                 final
      ready                          final

  public java.util.UUID copy$default$1();
    descriptor: ()Ljava/util/UUID;
    flags: (0x0001) ACC_PUBLIC
    Code:
      stack=1, locals=1, args_size=1
         0: aload_0
         1: invokevirtual #60                 // Method uuid:()Ljava/util/UUID;
         4: areturn
      LineNumberTable:
        line 38: 0
      LocalVariableTable:
        Start  Length  Slot  Name   Signature
            0       5     0  this   Lorg/scalatest/tools/TestSortingReporter$Slot;

  public scala.collection.mutable.ListBuffer<org.scalatest.events.Event> copy$default$2();
    descriptor: ()Lscala/collection/mutable/ListBuffer;
    flags: (0x0001) ACC_PUBLIC
    Code:
      stack=1, locals=1, args_size=1
         0: aload_0
         1: invokevirtual #63                 // Method eventList:()Lscala/collection/mutable/ListBuffer;
         4: areturn
      LineNumberTable:
        line 38: 0
      LocalVariableTable:
        Start  Length  Slot  Name   Signature
            0       5     0  this   Lorg/scalatest/tools/TestSortingReporter$Slot;
    Signature: #37                          // ()Lscala/collection/mutable/ListBuffer<Lorg/scalatest/events/Event;>;

  public boolean copy$default$3();
    descriptor: ()Z
    flags: (0x0001) ACC_PUBLIC
    Code:
      stack=1, locals=1, args_size=1
         0: aload_0
         1: invokevirtual #66                 // Method completed:()Z
         4: ireturn
      LineNumberTable:
        line 38: 0
      LocalVariableTable:
        Start  Length  Slot  Name   Signature
            0       5     0  this   Lorg/scalatest/tools/TestSortingReporter$Slot;

  public boolean copy$default$4();
    descriptor: ()Z
    flags: (0x0001) ACC_PUBLIC
    Code:
      stack=1, locals=1, args_size=1
         0: aload_0
         1: invokevirtual #69                 // Method completedEvent:()Z
         4: ireturn
      LineNumberTable:
        line 38: 0
      LocalVariableTable:
        Start  Length  Slot  Name   Signature
            0       5     0  this   Lorg/scalatest/tools/TestSortingReporter$Slot;

  public boolean copy$default$5();
    descriptor: ()Z
    flags: (0x0001) ACC_PUBLIC
    Code:
      stack=1, locals=1, args_size=1
         0: aload_0
         1: invokevirtual #72                 // Method ready:()Z
         4: ireturn
      LineNumberTable:
        line 38: 0
      LocalVariableTable:
        Start  Length  Slot  Name   Signature
            0       5     0  this   Lorg/scalatest/tools/TestSortingReporter$Slot;

  public java.lang.String productPrefix();
    descriptor: ()Ljava/lang/String;
    flags: (0x0001) ACC_PUBLIC
    Code:
      stack=1, locals=1, args_size=1
         0: ldc           #75                 // String Slot
         2: areturn
      LineNumberTable:
        line 38: 0
      LocalVariableTable:
        Start  Length  Slot  Name   Signature
            0       3     0  this   Lorg/scalatest/tools/TestSortingReporter$Slot;

  public int productArity();
    descriptor: ()I
    flags: (0x0001) ACC_PUBLIC
    Code:
      stack=1, locals=1, args_size=1
         0: iconst_5
         1: ireturn
      LineNumberTable:
        line 38: 0
      LocalVariableTable:
        Start  Length  Slot  Name   Signature
            0       2     0  this   Lorg/scalatest/tools/TestSortingReporter$Slot;

  public java.lang.Object productElement(int);
    descriptor: (I)Ljava/lang/Object;
    flags: (0x0001) ACC_PUBLIC
    Code:
      stack=1, locals=3, args_size=2
         0: iload_1
         1: istore_2
         2: iload_2
         3: tableswitch   { // 0 to 4
                       0: 36
                       1: 43
                       2: 50
                       3: 60
                       4: 70
                 default: 80
            }
        36: aload_0
        37: invokevirtual #60                 // Method uuid:()Ljava/util/UUID;
        40: goto          87
        43: aload_0
        44: invokevirtual #63                 // Method eventList:()Lscala/collection/mutable/ListBuffer;
        47: goto          87
        50: aload_0
        51: invokevirtual #66                 // Method completed:()Z
        54: invokestatic  #86                 // Method scala/runtime/BoxesRunTime.boxToBoolean:(Z)Ljava/lang/Boolean;
        57: goto          87
        60: aload_0
        61: invokevirtual #69                 // Method completedEvent:()Z
        64: invokestatic  #86                 // Method scala/runtime/BoxesRunTime.boxToBoolean:(Z)Ljava/lang/Boolean;
        67: goto          87
        70: aload_0
        71: invokevirtual #72                 // Method ready:()Z
        74: invokestatic  #86                 // Method scala/runtime/BoxesRunTime.boxToBoolean:(Z)Ljava/lang/Boolean;
        77: goto          87
        80: iload_1
        81: invokestatic  #91                 // Method scala/runtime/Statics.ioobe:(I)Ljava/lang/Object;
        84: goto          87
        87: areturn
      StackMapTable: number_of_entries = 7
        frame_type = 252 /* append */
          offset_delta = 36
          locals = [ int ]
        frame_type = 6 /* same */
        frame_type = 6 /* same */
        frame_type = 9 /* same */
        frame_type = 9 /* same */
        frame_type = 9 /* same */
        frame_type = 70 /* same_locals_1_stack_item */
          stack = [ class java/lang/Object ]
      LineNumberTable:
        line 38: 0
      LocalVariableTable:
        Start  Length  Slot  Name   Signature
            0      88     0  this   Lorg/scalatest/tools/TestSortingReporter$Slot;
            0      88     1   x$1   I
    MethodParameters:
      Name                           Flags
      x$1                            final

  public scala.collection.Iterator<java.lang.Object> productIterator();
    descriptor: ()Lscala/collection/Iterator;
    flags: (0x0001) ACC_PUBLIC
    Code:
      stack=2, locals=1, args_size=1
         0: getstatic     #100                // Field scala/runtime/ScalaRunTime$.MODULE$:Lscala/runtime/ScalaRunTime$;
         3: aload_0
         4: invokevirtual #103                // Method scala/runtime/ScalaRunTime$.typedProductIterator:(Lscala/Product;)Lscala/collection/Iterator;
         7: areturn
      LineNumberTable:
        line 38: 0
      LocalVariableTable:
        Start  Length  Slot  Name   Signature
            0       8     0  this   Lorg/scalatest/tools/TestSortingReporter$Slot;
    Signature: #94                          // ()Lscala/collection/Iterator<Ljava/lang/Object;>;

  public boolean canEqual(java.lang.Object);
    descriptor: (Ljava/lang/Object;)Z
    flags: (0x0001) ACC_PUBLIC
    Code:
      stack=1, locals=2, args_size=2
         0: aload_1
         1: instanceof    #2                  // class org/scalatest/tools/TestSortingReporter$Slot
         4: ireturn
      LineNumberTable:
        line 38: 0
      LocalVariableTable:
        Start  Length  Slot  Name   Signature
            0       5     0  this   Lorg/scalatest/tools/TestSortingReporter$Slot;
            0       5     1   x$1   Ljava/lang/Object;
    MethodParameters:
      Name                           Flags
      x$1                            final

  public java.lang.String productElementName(int);
    descriptor: (I)Ljava/lang/String;
    flags: (0x0001) ACC_PUBLIC
    Code:
      stack=1, locals=3, args_size=2
         0: iload_1
         1: istore_2
         2: iload_2
         3: tableswitch   { // 0 to 4
                       0: 36
                       1: 41
                       2: 46
                       3: 51
                       4: 56
                 default: 61
            }
        36: ldc           #109                // String uuid
        38: goto          71
        41: ldc           #110                // String eventList
        43: goto          71
        46: ldc           #111                // String completed
        48: goto          71
        51: ldc           #112                // String completedEvent
        53: goto          71
        56: ldc           #113                // String ready
        58: goto          71
        61: iload_1
        62: invokestatic  #91                 // Method scala/runtime/Statics.ioobe:(I)Ljava/lang/Object;
        65: checkcast     #115                // class java/lang/String
        68: goto          71
        71: areturn
      StackMapTable: number_of_entries = 7
        frame_type = 252 /* append */
          offset_delta = 36
          locals = [ int ]
        frame_type = 4 /* same */
        frame_type = 4 /* same */
        frame_type = 4 /* same */
        frame_type = 4 /* same */
        frame_type = 4 /* same */
        frame_type = 73 /* same_locals_1_stack_item */
          stack = [ class java/lang/String ]
      LineNumberTable:
        line 38: 0
      LocalVariableTable:
        Start  Length  Slot  Name   Signature
            0      72     0  this   Lorg/scalatest/tools/TestSortingReporter$Slot;
            0      72     1   x$1   I
    MethodParameters:
      Name                           Flags
      x$1                            final

  public int hashCode();
    descriptor: ()I
    flags: (0x0001) ACC_PUBLIC
    Code:
      stack=2, locals=2, args_size=1
         0: ldc           #117                // int -889275714
         2: istore_1
         3: iload_1
         4: aload_0
         5: invokevirtual #119                // Method productPrefix:()Ljava/lang/String;
         8: invokevirtual #121                // Method java/lang/String.hashCode:()I
        11: invokestatic  #125                // Method scala/runtime/Statics.mix:(II)I
        14: istore_1
        15: iload_1
        16: aload_0
        17: invokevirtual #60                 // Method uuid:()Ljava/util/UUID;
        20: invokestatic  #129                // Method scala/runtime/Statics.anyHash:(Ljava/lang/Object;)I
        23: invokestatic  #125                // Method scala/runtime/Statics.mix:(II)I
        26: istore_1
        27: iload_1
        28: aload_0
        29: invokevirtual #63                 // Method eventList:()Lscala/collection/mutable/ListBuffer;
        32: invokestatic  #129                // Method scala/runtime/Statics.anyHash:(Ljava/lang/Object;)I
        35: invokestatic  #125                // Method scala/runtime/Statics.mix:(II)I
        38: istore_1
        39: iload_1
        40: aload_0
        41: invokevirtual #66                 // Method completed:()Z
        44: ifeq          53
        47: sipush        1231
        50: goto          56
        53: sipush        1237
        56: invokestatic  #125                // Method scala/runtime/Statics.mix:(II)I
        59: istore_1
        60: iload_1
        61: aload_0
        62: invokevirtual #69                 // Method completedEvent:()Z
        65: ifeq          74
        68: sipush        1231
        71: goto          77
        74: sipush        1237
        77: invokestatic  #125                // Method scala/runtime/Statics.mix:(II)I
        80: istore_1
        81: iload_1
        82: aload_0
        83: invokevirtual #72                 // Method ready:()Z
        86: ifeq          95
        89: sipush        1231
        92: goto          98
        95: sipush        1237
        98: invokestatic  #125                // Method scala/runtime/Statics.mix:(II)I
       101: istore_1
       102: iload_1
       103: iconst_5
       104: invokestatic  #132                // Method scala/runtime/Statics.finalizeHash:(II)I
       107: ireturn
      StackMapTable: number_of_entries = 6
        frame_type = 255 /* full_frame */
          offset_delta = 53
          locals = [ class org/scalatest/tools/TestSortingReporter$Slot, int ]
          stack = [ int ]
        frame_type = 255 /* full_frame */
          offset_delta = 2
          locals = [ class org/scalatest/tools/TestSortingReporter$Slot, int ]
          stack = [ int, int ]
        frame_type = 81 /* same_locals_1_stack_item */
          stack = [ int ]
        frame_type = 255 /* full_frame */
          offset_delta = 2
          locals = [ class org/scalatest/tools/TestSortingReporter$Slot, int ]
          stack = [ int, int ]
        frame_type = 81 /* same_locals_1_stack_item */
          stack = [ int ]
        frame_type = 255 /* full_frame */
          offset_delta = 2
          locals = [ class org/scalatest/tools/TestSortingReporter$Slot, int ]
          stack = [ int, int ]
      LineNumberTable:
        line 38: 0
      LocalVariableTable:
        Start  Length  Slot  Name   Signature
            0     108     0  this   Lorg/scalatest/tools/TestSortingReporter$Slot;

  public java.lang.String toString();
    descriptor: ()Ljava/lang/String;
    flags: (0x0001) ACC_PUBLIC
    Code:
      stack=2, locals=1, args_size=1
         0: getstatic     #100                // Field scala/runtime/ScalaRunTime$.MODULE$:Lscala/runtime/ScalaRunTime$;
         3: aload_0
         4: invokevirtual #137                // Method scala/runtime/ScalaRunTime$._toString:(Lscala/Product;)Ljava/lang/String;
         7: areturn
      LineNumberTable:
        line 38: 0
      LocalVariableTable:
        Start  Length  Slot  Name   Signature
            0       8     0  this   Lorg/scalatest/tools/TestSortingReporter$Slot;

  public boolean equals(java.lang.Object);
    descriptor: (Ljava/lang/Object;)Z
    flags: (0x0001) ACC_PUBLIC
    Code:
      stack=2, locals=7, args_size=2
         0: aload_0
         1: aload_1
         2: if_acmpeq     168
         5: aload_1
         6: astore_3
         7: aload_3
         8: instanceof    #2                  // class org/scalatest/tools/TestSortingReporter$Slot
        11: ifeq          33
        14: aload_3
        15: checkcast     #2                  // class org/scalatest/tools/TestSortingReporter$Slot
        18: invokevirtual #53                 // Method org$scalatest$tools$TestSortingReporter$Slot$$$outer:()Lorg/scalatest/tools/TestSortingReporter;
        21: aload_0
        22: invokevirtual #53                 // Method org$scalatest$tools$TestSortingReporter$Slot$$$outer:()Lorg/scalatest/tools/TestSortingReporter;
        25: if_acmpne     33
        28: iconst_1
        29: istore_2
        30: goto          41
        33: goto          36
        36: iconst_0
        37: istore_2
        38: goto          41
        41: iload_2
        42: ifeq          172
        45: aload_1
        46: checkcast     #2                  // class org/scalatest/tools/TestSortingReporter$Slot
        49: astore        4
        51: aload_0
        52: invokevirtual #66                 // Method completed:()Z
        55: aload         4
        57: invokevirtual #66                 // Method completed:()Z
        60: if_icmpne     164
        63: aload_0
        64: invokevirtual #69                 // Method completedEvent:()Z
        67: aload         4
        69: invokevirtual #69                 // Method completedEvent:()Z
        72: if_icmpne     164
        75: aload_0
        76: invokevirtual #72                 // Method ready:()Z
        79: aload         4
        81: invokevirtual #72                 // Method ready:()Z
        84: if_icmpne     164
        87: aload_0
        88: invokevirtual #60                 // Method uuid:()Ljava/util/UUID;
        91: aload         4
        93: invokevirtual #60                 // Method uuid:()Ljava/util/UUID;
        96: astore        5
        98: dup
        99: ifnonnull     111
       102: pop
       103: aload         5
       105: ifnull        119
       108: goto          164
       111: aload         5
       113: invokevirtual #140                // Method java/lang/Object.equals:(Ljava/lang/Object;)Z
       116: ifeq          164
       119: aload_0
       120: invokevirtual #63                 // Method eventList:()Lscala/collection/mutable/ListBuffer;
       123: aload         4
       125: invokevirtual #63                 // Method eventList:()Lscala/collection/mutable/ListBuffer;
       128: astore        6
       130: dup
       131: ifnonnull     143
       134: pop
       135: aload         6
       137: ifnull        151
       140: goto          164
       143: aload         6
       145: invokevirtual #140                // Method java/lang/Object.equals:(Ljava/lang/Object;)Z
       148: ifeq          164
       151: aload         4
       153: aload_0
       154: invokevirtual #142                // Method canEqual:(Ljava/lang/Object;)Z
       157: ifeq          164
       160: iconst_1
       161: goto          165
       164: iconst_0
       165: ifeq          172
       168: iconst_1
       169: goto          173
       172: iconst_0
       173: ireturn
      StackMapTable: number_of_entries = 12
        frame_type = 253 /* append */
          offset_delta = 33
          locals = [ top, class java/lang/Object ]
        frame_type = 2 /* same */
        frame_type = 255 /* full_frame */
          offset_delta = 4
          locals = [ class org/scalatest/tools/TestSortingReporter$Slot, class java/lang/Object, int, class java/lang/Object ]
          stack = []
        frame_type = 255 /* full_frame */
          offset_delta = 69
          locals = [ class org/scalatest/tools/TestSortingReporter$Slot, class java/lang/Object, int, class java/lang/Object, class org/scalatest/tools/TestSortingReporter$Slot, class java/util/UUID ]
          stack = [ class java/util/UUID ]
        frame_type = 7 /* same */
        frame_type = 255 /* full_frame */
          offset_delta = 23
          locals = [ class org/scalatest/tools/TestSortingReporter$Slot, class java/lang/Object, int, class java/lang/Object, class org/scalatest/tools/TestSortingReporter$Slot, class java/util/UUID, class scala/collection/mutable/ListBuffer ]
          stack = [ class scala/collection/mutable/ListBuffer ]
        frame_type = 7 /* same */
        frame_type = 249 /* chop */
          offset_delta = 12
        frame_type = 64 /* same_locals_1_stack_item */
          stack = [ int ]
        frame_type = 248 /* chop */
          offset_delta = 2
        frame_type = 253 /* append */
          offset_delta = 3
          locals = [ int, class java/lang/Object ]
        frame_type = 255 /* full_frame */
          offset_delta = 0
          locals = [ class org/scalatest/tools/TestSortingReporter$Slot, class java/lang/Object ]
          stack = [ int ]
      LineNumberTable:
        line 38: 0
      LocalVariableTable:
        Start  Length  Slot  Name   Signature
            0     174     0  this   Lorg/scalatest/tools/TestSortingReporter$Slot;
            0     174     1   x$1   Ljava/lang/Object;
    MethodParameters:
      Name                           Flags
      x$1                            final

  public org.scalatest.tools.TestSortingReporter org$scalatest$tools$TestSortingReporter$Slot$$$outer();
    descriptor: ()Lorg/scalatest/tools/TestSortingReporter;
    flags: (0x1001) ACC_PUBLIC, ACC_SYNTHETIC
    Code:
      stack=1, locals=1, args_size=1
         0: aload_0
         1: getfield      #148                // Field $outer:Lorg/scalatest/tools/TestSortingReporter;
         4: areturn
      LineNumberTable:
        line 38: 0
      LocalVariableTable:
        Start  Length  Slot  Name   Signature
            0       5     0  this   Lorg/scalatest/tools/TestSortingReporter$Slot;

  public org.scalatest.tools.TestSortingReporter$Slot(java.util.UUID, scala.collection.mutable.ListBuffer<org.scalatest.events.Event>, boolean, boolean, boolean);
    descriptor: (Lorg/scalatest/tools/TestSortingReporter;Ljava/util/UUID;Lscala/collection/mutable/ListBuffer;ZZZ)V
    flags: (0x0001) ACC_PUBLIC
    Code:
      stack=2, locals=7, args_size=7
         0: aload_0
         1: aload_2
         2: putfield      #35                 // Field uuid:Ljava/util/UUID;
         5: aload_0
         6: aload_3
         7: putfield      #39                 // Field eventList:Lscala/collection/mutable/ListBuffer;
        10: aload_0
        11: iload         4
        13: putfield      #42                 // Field completed:Z
        16: aload_0
        17: iload         5
        19: putfield      #44                 // Field completedEvent:Z
        22: aload_0
        23: iload         6
        25: putfield      #46                 // Field ready:Z
        28: aload_1
        29: ifnonnull     34
        32: aconst_null
        33: athrow
        34: aload_0
        35: aload_1
        36: putfield      #148                // Field $outer:Lorg/scalatest/tools/TestSortingReporter;
        39: aload_0
        40: invokespecial #152                // Method java/lang/Object."<init>":()V
        43: aload_0
        44: invokestatic  #156                // InterfaceMethod scala/Product.$init$:(Lscala/Product;)V
        47: return
      StackMapTable: number_of_entries = 1
        frame_type = 34 /* same */
      LineNumberTable:
        line 38: 0
      LocalVariableTable:
        Start  Length  Slot  Name   Signature
            0      48     0  this   Lorg/scalatest/tools/TestSortingReporter$Slot;
            0      48     1 $outer   Lorg/scalatest/tools/TestSortingReporter;
            0      48     2  uuid   Ljava/util/UUID;
            0      48     3 eventList   Lscala/collection/mutable/ListBuffer;
            0      48     4 completed   Z
            0      48     5 completedEvent   Z
            0      48     6 ready   Z
    Signature: #149                         // (Ljava/util/UUID;Lscala/collection/mutable/ListBuffer<Lorg/scalatest/events/Event;>;ZZZ)V
    MethodParameters:
      Name                           Flags
      $outer                         final synthetic
      uuid                           final
      eventList                      final
      completed                      final
      completedEvent                 final
      ready                          final
}
InnerClasses:
  public #12= #2 of #11;                  // Slot=class org/scalatest/tools/TestSortingReporter$Slot of class org/scalatest/tools/TestSortingReporter
SourceFile: "TestSortingReporter.scala"
  ScalaInlineInfo: length = 0x77 (unknown attribute)
   01 00 00 17 00 36 00 37 00 00 68 00 69 00 00 12
   00 28 00 00 14 00 28 00 00 2F 00 30 00 00 3A 00
   21 00 00 3D 00 24 00 00 40 00 28 00 00 43 00 28
   00 00 46 00 28 00 00 8A 00 69 00 00 0F 00 24 00
   00 74 00 4D 00 00 32 00 33 00 00 4C 00 4D 00 00
   4E 00 4F 00 00 6B 00 6C 00 00 18 00 19 00 00 5D
   00 19 00 00 49 00 4A 00 00 15 00 28 00 00 85 00
   4A 00 00 0D 00 21 00
  Scala: length = 0x0 (unknown attribute)

