Classfile /Users/mw/Projects/slang-braindump/.jar/jar8/assemble/slang-braindump/assemble/content/org/scalatest/tools/TestSortingReporter.class
  Last modified May 29, 2022; size 18846 bytes
  SHA-256 checksum 70bd9f42e4e37cc8d7d4abbf39cfe1fc9e4d9162bd5540dca686c7b218bc59c1
  Compiled from "TestSortingReporter.scala"
public class org.scalatest.tools.TestSortingReporter implements org.scalatest.CatchReporter,org.scalatest.DistributedTestSorter
  minor version: 0
  major version: 52
  flags: (0x0021) ACC_PUBLIC, ACC_SUPER
  this_class: #2                          // org/scalatest/tools/TestSortingReporter
  super_class: #4                         // java/lang/Object
  interfaces: 2, fields: 11, methods: 25, attributes: 5
Constant pool:
    #1 = Utf8               org/scalatest/tools/TestSortingReporter
    #2 = Class              #1            // org/scalatest/tools/TestSortingReporter
    #3 = Utf8               java/lang/Object
    #4 = Class              #3            // java/lang/Object
    #5 = Utf8               org/scalatest/CatchReporter
    #6 = Class              #5            // org/scalatest/CatchReporter
    #7 = Utf8               org/scalatest/DistributedTestSorter
    #8 = Class              #7            // org/scalatest/DistributedTestSorter
    #9 = Utf8               TestSortingReporter.scala
   #10 = Utf8               Lscala/reflect/ScalaSignature;
   #11 = Utf8               bytes
   #12 = Utf8               \u0006\u0005\tmh!\u0002$H\u0001%k\u0005\u0002C.\u0001\u0005\u0003\u0005\u000b\u0011B/\t\u0011!\u0004!\u0011!Q\u0001\n%D\u0001\u0002\u001c\u0001\u0003\u0002\u0003\u0006I!\u001c\u0005\tg\u0002\u0011\t\u0011)A\u0005i\"Aq\u000f\u0001B\u0001B\u0003%\u0001\u0010\u0003\u0005\u007f\u0001\t\u0015\r\u0011\"\u0001\u0000\u0011)\t\t\u0002\u0001B\u0001B\u0003%\u0011\u0011\u0001\u0005\b\u0003\'\u0001A\u0011AA\u000b\r\u0019\t9\u0003\u0001!\u0002*!Q\u00111I\u0005\u0003\u0016\u0004%\t!!\u0012\t\u0015\u0005M\u0013B!E!\u0002\u0013\t9\u0005\u0003\u0006\u0002V%\u0011)\u001a!C\u0001\u0003/B!\"!\u001e\n\u0005#\u0005\u000b\u0011BA-\u0011)\t9(\u0003BK\u0002\u0013\u0005\u0011\u0011\u0010\u0005\u000b\u0003\u0003K!\u0011#Q\u0001\n\u0005m\u0004BCAB\u0013\tU\r\u0011\"\u0001\u0002z!Q\u0011QQ\u0005\u0003\u0012\u0003\u0006I!a\u001f\t\u0015\u0005\u001d\u0015B!f\u0001\n\u0003\tI\b\u0003\u0006\u0002\n&\u0011\t\u0012)A\u0005\u0003wBq!a\u0005\n\t\u0003\tY\tC\u0005\u0002\u001c&\t\t\u0011\"\u0001\u0002\u001e\"I\u0011\u0011V\u0005\u0012\u0002\u0013\u0005\u00111\u0016\u0005\n\u0003\u0003L\u0011\u0013!C\u0001\u0003\u0007D\u0011\"a2\n#\u0003%\t!!3\t\u0013\u00055\u0017\"%A\u0005\u0002\u0005%\u0007\"CAh\u0013E\u0005I\u0011AAe\u0011%\t\t.CA\u0001\n\u0003\n\u0019\u000eC\u0005\u0002`&\t\t\u0011\"\u0001\u0002b\"I\u00111]\u0005\u0002\u0002\u0013\u0005\u0011Q\u001d\u0005\n\u0003cL\u0011\u0011!C!\u0003gD\u0011\"!@\n\u0003\u0003%\t!a@\t\u0013\t\r\u0011\"!A\u0005B\t\u0015\u0001\"\u0003B\u0005\u0013\u0005\u0005I\u0011\tB\u0006\u0011%\u0011i!CA\u0001\n\u0003\u0012y\u0001C\u0005\u0003\u0012%\t\t\u0011\"\u0011\u0003\u0014\u001dI!q\u0003\u0001\u0002\u0002#\u0005!\u0011\u0004\u0004\n\u0003O\u0001\u0011\u0011!E\u0001\u00057Aq!a\u0005&\t\u0003\u0011i\u0003C\u0005\u0003\u000e\u0015\n\t\u0011\"\u0012\u0003\u0010!I!qF\u0013\u0002\u0002\u0013\u0005%\u0011\u0007\u0005\n\u0005{)\u0013\u0011!CA\u0005\u007fA\u0011B!\u0014\u0001\u0005\u0004%IAa\u0014\t\u0011\tM\u0003\u0001)A\u0005\u0005#B\u0011B!\u0016\u0001\u0005\u0004%IAa\u0016\t\u0011\t}\u0003\u0001)A\u0005\u00053B\u0011B!\u0019\u0001\u0001\u0004%I!!9\t\u0013\t\r\u0004\u00011A\u0005\n\t\u0015\u0004b\u0002B8\u0001\u0001\u0006K\u0001\u001e\u0004\u0007\u0005s\u0002\u0001Aa\u001f\t\u0015\t%\u0015G!b\u0001\n\u0003\u0011Y\t\u0003\u0006\u0003\u000eF\u0012\t\u0011)A\u0005\u0003\u001bCq!a\u00052\t\u0003\u0011y\tC\u0004\u0003\u0016F\"\tEa&\t\u0013\te\u0005\u00011A\u0005\n\tm\u0005\"\u0003BV\u0001\u0001\u0007I\u0011\u0002BW\u0011!\u0011\t\f\u0001Q!\n\tu\u0005b\u0002BZ\u0001\u0011\u0005!Q\u0017\u0005\b\u0005_\u0001A\u0011\u0001B^\u0011\u001d\u0011\u0019\r\u0001C\u0001\u0005\u000bDqA!3\u0001\t\u0013\u00119\nC\u0004\u0003L\u0002!\tA!4\t\u000f\tE\u0007\u0001\"\u0003\u0003T\"9!q\u001b\u0001\u0005\n\te\u0007b\u0002Bp\u0001\u0011%!\u0011\u001d\u0005\b\u0005_\u0004A\u0011\u0002BL\u0011\u001d\u0011\u0019\u0010\u0001C\u0005\u0005/CqA!>\u0001\t\u0013\u00119\nC\u0004\u0003x\u0002!IAa&\t\u000f\te\b\u0001\"\u0001\u0003\u0018\n\u0019B+Z:u\'>\u0014H/\u001b8h%\u0016\u0004xN\u001d;fe*\u0011\u0001*S\u0001\u0006i>|Gn\u001d\u0006\u0003\u0015.\u000b\u0011b]2bY\u0006$Xm\u001d;\u000b\u00031\u000b1a\u001c:h\'\u0011\u0001a\n\u0016-\u0011\u0005=\u0013V\"\u0001)\u000b\u0003E\u000bQa]2bY\u0006L!a\u0015)\u0003\r\u0005s\u0017PU3g!\t)f+D\u0001J\u0013\t9\u0016JA\u0007DCR\u001c\u0007NU3q_J$XM\u001d\t\u0003+fK!AW%\u0003+\u0011K7\u000f\u001e:jEV$X\r\u001a+fgR\u001cvN\u001d;fe\u000691/^5uK&#7\u0001\u0001\t\u0003=\u0016t!aX2\u0011\u0005\u0001\u0004V\"A1\u000b\u0005\td\u0016A\u0002\u001fs_>$h(\u0003\u0002e!\u00061\u0001K]3eK\u001aL!AZ4\u0003\rM#(/\u001b8h\u0015\t!\u0007+\u0001\u0005eSN\u0004\u0018\r^2i!\t)&.\u0003\u0002l\u0013\nA!+\u001a9peR,\'/\u0001\bt_J$\u0018N\\4US6,w.\u001e;\u0011\u00059\fX\"A8\u000b\u0005AL\u0015\u0001\u0002;j[\u0016L!A]8\u0003\tM\u0003\u0018M\\\u0001\ni\u0016\u001cHoQ8v]R\u0004\"aT;\n\u0005Y\u0004&aA%oi\u0006Y1/^5uKN{\'\u000f^3s!\ry\u0015p_\u0005\u0003uB\u0013aa\u00149uS>t\u0007CA+}\u0013\ti\u0018J\u0001\fESN$(/\u001b2vi\u0016$7+^5uKN{\'\u000f^3s\u0003\ryW\u000f^\u000b\u0003\u0003\u0003\u0001B!a\u0001\u0002\u000e5\u0011\u0011Q\u0001\u0006\u0005\u0003\u000f\tI!\u0001\u0002j_*\u0011\u00111B\u0001\u0005U\u00064\u0018-\u0003\u0003\u0002\u0010\u0005\u0015!a\u0003)sS:$8\u000b\u001e:fC6\fAa\\;uA\u00051A(\u001b8jiz\"b\"a\u0006\u0002\u001c\u0005u\u0011qDA\u0011\u0003G\t)\u0003E\u0002\u0002\u001a\u0001i\u0011a\u0012\u0005\u00067\"\u0001\r!\u0018\u0005\u0006Q\"\u0001\r!\u001b\u0005\u0006Y\"\u0001\r!\u001c\u0005\u0006g\"\u0001\r\u0001\u001e\u0005\u0006o\"\u0001\r\u0001\u001f\u0005\u0007}\"\u0001\r!!\u0001\u0003\tMcw\u000e^\n\u0007\u00139\u000bY#!\r\u0011\u0007=\u000bi#C\u0002\u00020A\u0013q\u0001\u0015:pIV\u001cG\u000f\u0005\u0003\u00024\u0005ub\u0002BA\u001b\u0003sq1\u0001YA\u001c\u0013\u0005\t\u0016bAA\u001e!\u00069\u0001/Y2lC\u001e,\u0017\u0002BA \u0003\u0003\u0012AbU3sS\u0006d\u0017N_1cY\u0016T1!a\u000fQ\u0003\u0011)X/\u001b3\u0016\u0005\u0005\u001d\u0003\u0003BA%\u0003\u001fj!!a\u0013\u000b\t\u00055\u0013\u0011B\u0001\u0005kRLG.\u0003\u0003\u0002R\u0005-#\u0001B+V\u0013\u0012\u000bQ!^;jI\u0002\n\u0011\"\u001a<f]Rd\u0015n\u001d;\u0016\u0005\u0005e\u0003CBA.\u0003K\nI\'\u0004\u0002\u0002^)!\u0011qLA1\u0003\u001diW\u000f^1cY\u0016T1!a\u0019Q\u0003)\u0019w\u000e\u001c7fGRLwN\\\u0005\u0005\u0003O\niF\u0001\u0006MSN$()\u001e4gKJ\u0004B!a\u001b\u0002r5\u0011\u0011Q\u000e\u0006\u0004\u0003_J\u0015AB3wK:$8/\u0003\u0003\u0002t\u00055$!B#wK:$\u0018AC3wK:$H*[:uA\u0005I1m\\7qY\u0016$X\rZ\u000b\u0003\u0003w\u00022aTA?\u0013\r\ty\b\u0015\u0002\b\u0005>|G.Z1o\u0003)\u0019w.\u001c9mKR,G\rI\u0001\u000fG>l\u0007\u000f\\3uK\u0012,e/\u001a8u\u0003=\u0019w.\u001c9mKR,G-\u0012<f]R\u0004\u0013!\u0002:fC\u0012L\u0018A\u0002:fC\u0012L\b\u0005\u0006\u0007\u0002\u000e\u0006E\u00151SAK\u0003/\u000bI\nE\u0002\u0002\u0010&i\u0011\u0001\u0001\u0005\b\u0003\u0007\"\u0002\u0019AA$\u0011\u001d\t)\u0006\u0006a\u0001\u00033Bq!a\u001e\u0015\u0001\u0004\tY\bC\u0004\u0002\u0004R\u0001\r!a\u001f\t\u000f\u0005\u001dE\u00031\u0001\u0002|\u0005!1m\u001c9z)1\ti)a(\u0002\"\u0006\r\u0016QUAT\u0011%\t\u0019%\u0006I\u0001\u0002\u0004\t9\u0005C\u0005\u0002VU\u0001\n\u00111\u0001\u0002Z!I\u0011qO\u000b\u0011\u0002\u0003\u0007\u00111\u0010\u0005\n\u0003\u0007+\u0002\u0013!a\u0001\u0003wB\u0011\"a\"\u0016!\u0003\u0005\r!a\u001f\u0002\u001d\r|\u0007/\u001f\u0013eK\u001a\fW\u000f\u001c;%cU\u0011\u0011Q\u0016\u0016\u0005\u0003\u000f\nyk\u000b\u0002\u00022B!\u00111WA_\u001b\t\t)L\u0003\u0003\u00028\u0006e\u0016!C;oG\",7m[3e\u0015\r\tY\fU\u0001\u000bC:tw\u000e^1uS>t\u0017\u0002BA`\u0003k\u0013\u0011#\u001e8dQ\u0016\u001c7.\u001a3WCJL\u0017M\\2f\u00039\u0019w\u000e]=%I\u00164\u0017-\u001e7uII*\"!!2+\t\u0005e\u0013qV\u0001\u000fG>\u0004\u0018\u0010\n3fM\u0006,H\u000e\u001e\u00134+\t\tYM\u000b\u0003\u0002|\u0005=\u0016AD2paf$C-\u001a4bk2$H\u0005N\u0001\u000fG>\u0004\u0018\u0010\n3fM\u0006,H\u000e\u001e\u00136\u00035\u0001(o\u001c3vGR\u0004&/\u001a4jqV\u0011\u0011Q\u001b\t\u0005\u0003/\fi.\u0004\u0002\u0002Z*!\u00111\\A\u0005\u0003\u0011a\u0017M\\4\n\u0007\u0019\fI.\u0001\u0007qe>$Wo\u0019;Be&$\u00180F\u0001u\u00039\u0001(o\u001c3vGR,E.Z7f]R$B!a:\u0002nB\u0019q*!;\n\u0007\u0005-\bKA\u0002B]fD\u0001\"a<\u001e\u0003\u0003\u0005\r\u0001^\u0001\u0004q\u0012\n\u0014a\u00049s_\u0012,8\r^%uKJ\fGo\u001c:\u0016\u0005\u0005U\bCBA|\u0003s\f9/\u0004\u0002\u0002b%!\u00111`A1\u0005!IE/\u001a:bi>\u0014\u0018\u0001C2b]\u0016\u000bX/\u00197\u0015\t\u0005m$\u0011\u0001\u0005\n\u0003_|\u0012\u0011!a\u0001\u0003O\f!\u0003\u001d:pIV\u001cG/\u00127f[\u0016tGOT1nKR!\u0011Q\u001bB\u0004\u0011!\ty\u000fIA\u0001\u0002\u0004!\u0018\u0001\u00035bg\"\u001cu\u000eZ3\u0015\u0003Q\f\u0001\u0002^8TiJLgn\u001a\u000b\u0003\u0003+\fa!Z9vC2\u001cH\u0003BA>\u0005+A\u0011\"a<$\u0003\u0003\u0005\r!a:\u0002\tMcw\u000e\u001e\t\u0004\u0003\u001f+3#B\u0013\u0003\u001e\t%\u0002\u0003\u0005B\u0010\u0005K\t9%!\u0017\u0002|\u0005m\u00141PAG\u001b\t\u0011\tCC\u0002\u0003$A\u000bqA];oi&lW-\u0003\u0003\u0003(\t\u0005\"!E!cgR\u0014\u0018m\u0019;Gk:\u001cG/[8okA!\u00111\u0001B\u0016\u0013\u0011\ty$!\u0002\u0015\u0005\te\u0011!B1qa2LH\u0003DAG\u0005g\u0011)Da\u000e\u0003:\tm\u0002bBA\"Q\u0001\u0007\u0011q\t\u0005\b\u0003+B\u0003\u0019AA-\u0011\u001d\t9\b\u000ba\u0001\u0003wBq!a!)\u0001\u0004\tY\bC\u0004\u0002\b\"\u0002\r!a\u001f\u0002\u000fUt\u0017\r\u001d9msR!!\u0011\tB%!\u0011y\u0015Pa\u0011\u0011\u001b=\u0013)%a\u0012\u0002Z\u0005m\u00141PA>\u0013\r\u00119\u0005\u0015\u0002\u0007)V\u0004H.Z\u001b\t\u0013\t-\u0013&!AA\u0002\u00055\u0015a\u0001=%a\u0005iq/Y5uS:<\')\u001e4gKJ,\"A!\u0015\u0011\r\u0005m\u0013QMAG\u000399\u0018-\u001b;j]\u001e\u0014UO\u001a4fe\u0002\nqa\u001d7pi6\u000b\u0007/\u0006\u0002\u0003ZA9\u00111\fB.;\u00065\u0015\u0002\u0002B/\u0003;\u0012q\u0001S1tQ6\u000b\u0007/\u0001\u0005tY>$X*\u00199!\u0003I\u0019w.\u001c9mKR,G\rV3ti\u000e{WO\u001c;\u0002-\r|W\u000e\u001d7fi\u0016$G+Z:u\u0007>,h\u000e^0%KF$BAa\u001a\u0003nA\u0019qJ!\u001b\n\u0007\t-\u0004K\u0001\u0003V]&$\b\u0002CAx_\u0005\u0005\t\u0019\u0001;\u0002\'\r|W\u000e\u001d7fi\u0016$G+Z:u\u0007>,h\u000e\u001e\u0011)\u0007A\u0012\u0019\bE\u0002P\u0005kJ1Aa\u001eQ\u0005!1x\u000e\\1uS2,\'a\u0003+j[\u0016|W\u000f\u001e+bg.\u001cR!\rB?\u0005\u0007\u0003B!a6\u0003\u0000%!!\u0011QAm\u0005\u0019y%M[3diB\u0019QK!\"\n\u0007\t\u001d\u0015JA\u0005US6,\'\u000fV1tW\u0006!1\u000f\\8u+\t\ti)A\u0003tY>$\b\u0005\u0006\u0003\u0003\u0012\nM\u0005cAAHc!9!\u0011\u0012\u001bA\u0002\u00055\u0015a\u0001:v]R\u0011!qM\u0001\fi&lWm\\;u)\u0006\u001c8.\u0006\u0002\u0003\u001eB!q*\u001fBP!\u001dy%\u0011\u0015BI\u0005KK1Aa)Q\u0005\u0019!V\u000f\u001d7feA\u0019QKa*\n\u0007\t%\u0016JA\u0003US6,\'/A\buS6,w.\u001e;UCN\\w\fJ3r)\u0011\u00119Ga,\t\u0013\u0005=x\'!AA\u0002\tu\u0015\u0001\u0004;j[\u0016|W\u000f\u001e+bg.\u0004\u0013\u0001\u00053jgR\u0014\u0018NY;uS:<G+Z:u)\u0011\u00119Ga.\t\r\te\u0016\b1\u0001^\u0003!!Xm\u001d;OC6,GC\u0002B4\u0005{\u0013y\f\u0003\u0004\u0003:j\u0002\r!\u0018\u0005\b\u0005\u0003T\u0004\u0019AA5\u0003\u0015)g/\u001a8u\u00035\u0019w.\u001c9mKR,G\rV3tiR!!q\rBd\u0011\u0019\u0011Il\u000fa\u0001;\u0006\u00192\r[3dW\u000e{W\u000e\u001d7fi\u0016$G+Z:ug\u00069Am\\!qa2LH\u0003\u0002B4\u0005\u001fDqA!1>\u0001\u0004\tI\'\u0001\tiC:$G.Z*vSR,WI^3oiR!!q\rBk\u0011\u001d\u0011\tM\u0010a\u0001\u0003S\n1\u0003[1oI2,G+Z:u\u0007>l\u0007\u000f\\3uK\u0012$bAa\u001a\u0003\\\nu\u0007b\u0002Ba\u007f\u0001\u0007\u0011\u0011\u000e\u0005\u0007\u0005s{\u0004\u0019A/\u0002\u001d\u0019L\'/Z*m_R,e/\u001a8ugR!!q\rBr\u0011\u001d\u0011I\t\u0011a\u0001\u0003\u001bC3\u0001\u0011Bt!\u0011\u0011IOa;\u000e\u0005\u0005e\u0016\u0002\u0002Bw\u0003s\u0013q\u0001^1jYJ,7-A\bgSJ,\'+Z1es\u00163XM\u001c;tQ\r\t%q]\u0001\u0014g\u000eDW\rZ;mKRKW.Z8viR\u000b7o[\u0001\u0012G\u0006t7-\u001a7US6,w.\u001e;UCN\\\u0017a\u0002;j[\u0016|W\u000f^\u0001\nI>$\u0015n\u001d9pg\u0016\u0004
   #13 = Utf8               org/scalactic/Requirements$RequirementsHelper
   #14 = Class              #13           // org/scalactic/Requirements$RequirementsHelper
   #15 = Utf8               org/scalactic/Requirements
   #16 = Class              #15           // org/scalactic/Requirements
   #17 = Utf8               RequirementsHelper
   #18 = Utf8               org/scalatest/tools/TestSortingReporter$Slot
   #19 = Class              #18           // org/scalatest/tools/TestSortingReporter$Slot
   #20 = Utf8               Slot
   #21 = Utf8               org/scalatest/tools/TestSortingReporter$Slot$
   #22 = Class              #21           // org/scalatest/tools/TestSortingReporter$Slot$
   #23 = Utf8               Slot$
   #24 = Utf8               org/scalatest/tools/TestSortingReporter$TimeoutTask
   #25 = Class              #24           // org/scalatest/tools/TestSortingReporter$TimeoutTask
   #26 = Utf8               TimeoutTask
   #27 = Utf8               Slot$module
   #28 = Utf8               Lorg/scalatest/tools/TestSortingReporter$Slot$;
   #29 = Utf8               suiteId
   #30 = Utf8               Ljava/lang/String;
   #31 = Utf8               dispatch
   #32 = Utf8               Lorg/scalatest/Reporter;
   #33 = Utf8               sortingTimeout
   #34 = Utf8               Lorg/scalatest/time/Span;
   #35 = Utf8               testCount
   #36 = Utf8               I
   #37 = Utf8               suiteSorter
   #38 = Utf8               Lscala/Option;
   #39 = Utf8               Lscala/Option<Lorg/scalatest/DistributedSuiteSorter;>;
   #40 = Utf8               out
   #41 = Utf8               Ljava/io/PrintStream;
   #42 = Utf8               waitingBuffer
   #43 = Utf8               Lscala/collection/mutable/ListBuffer;
   #44 = Utf8               Lscala/collection/mutable/ListBuffer<Lorg/scalatest/tools/TestSortingReporter$Slot;>;
   #45 = Utf8               slotMap
   #46 = Utf8               Lscala/collection/mutable/HashMap;
   #47 = Utf8               Lscala/collection/mutable/HashMap<Ljava/lang/String;Lorg/scalatest/tools/TestSortingReporter$Slot;>;
   #48 = Utf8               completedTestCount
   #49 = Utf8               timeoutTask
   #50 = Utf8               Lscala/Option<Lscala/Tuple2<Lorg/scalatest/tools/TestSortingReporter$TimeoutTask;Lorg/scalatest/Timer;>;>;
   #51 = Utf8               apply
   #52 = Utf8               (Lorg/scalatest/events/Event;)V
   #53 = Utf8               event
   #54 = Utf8               apply$
   #55 = Utf8               (Lorg/scalatest/CatchReporter;Lorg/scalatest/events/Event;)V
   #56 = NameAndType        #54:#55       // apply$:(Lorg/scalatest/CatchReporter;Lorg/scalatest/events/Event;)V
   #57 = InterfaceMethodref #6.#56        // org/scalatest/CatchReporter.apply$:(Lorg/scalatest/CatchReporter;Lorg/scalatest/events/Event;)V
   #58 = Utf8               this
   #59 = Utf8               Lorg/scalatest/tools/TestSortingReporter;
   #60 = Utf8               Lorg/scalatest/events/Event;
   #61 = Utf8               dispose
   #62 = Utf8               ()V
   #63 = Utf8               dispose$
   #64 = Utf8               (Lorg/scalatest/CatchReporter;)V
   #65 = NameAndType        #63:#64       // dispose$:(Lorg/scalatest/CatchReporter;)V
   #66 = InterfaceMethodref #6.#65        // org/scalatest/CatchReporter.dispose$:(Lorg/scalatest/CatchReporter;)V
   #67 = Utf8               ()Lorg/scalatest/tools/TestSortingReporter$Slot$;
   #68 = NameAndType        #27:#28       // Slot$module:Lorg/scalatest/tools/TestSortingReporter$Slot$;
   #69 = Fieldref           #2.#68        // org/scalatest/tools/TestSortingReporter.Slot$module:Lorg/scalatest/tools/TestSortingReporter$Slot$;
   #70 = Utf8               Slot$lzycompute$1
   #71 = NameAndType        #70:#62       // Slot$lzycompute$1:()V
   #72 = Methodref          #2.#71        // org/scalatest/tools/TestSortingReporter.Slot$lzycompute$1:()V
   #73 = Utf8               ()Ljava/io/PrintStream;
   #74 = NameAndType        #40:#41       // out:Ljava/io/PrintStream;
   #75 = Fieldref           #2.#74        // org/scalatest/tools/TestSortingReporter.out:Ljava/io/PrintStream;
   #76 = Utf8               ()Lscala/collection/mutable/ListBuffer;
   #77 = Utf8               ()Lscala/collection/mutable/ListBuffer<Lorg/scalatest/tools/TestSortingReporter$Slot;>;
   #78 = NameAndType        #42:#43       // waitingBuffer:Lscala/collection/mutable/ListBuffer;
   #79 = Fieldref           #2.#78        // org/scalatest/tools/TestSortingReporter.waitingBuffer:Lscala/collection/mutable/ListBuffer;
   #80 = Utf8               ()Lscala/collection/mutable/HashMap;
   #81 = Utf8               ()Lscala/collection/mutable/HashMap<Ljava/lang/String;Lorg/scalatest/tools/TestSortingReporter$Slot;>;
   #82 = NameAndType        #45:#46       // slotMap:Lscala/collection/mutable/HashMap;
   #83 = Fieldref           #2.#82        // org/scalatest/tools/TestSortingReporter.slotMap:Lscala/collection/mutable/HashMap;
   #84 = Utf8               ()I
   #85 = NameAndType        #48:#36       // completedTestCount:I
   #86 = Fieldref           #2.#85        // org/scalatest/tools/TestSortingReporter.completedTestCount:I
   #87 = Utf8               completedTestCount_$eq
   #88 = Utf8               (I)V
   #89 = Utf8               x$1
   #90 = Utf8               ()Lscala/Option;
   #91 = Utf8               ()Lscala/Option<Lscala/Tuple2<Lorg/scalatest/tools/TestSortingReporter$TimeoutTask;Lorg/scalatest/Timer;>;>;
   #92 = NameAndType        #49:#38       // timeoutTask:Lscala/Option;
   #93 = Fieldref           #2.#92        // org/scalatest/tools/TestSortingReporter.timeoutTask:Lscala/Option;
   #94 = Utf8               timeoutTask_$eq
   #95 = Utf8               (Lscala/Option;)V
   #96 = Utf8               (Lscala/Option<Lscala/Tuple2<Lorg/scalatest/tools/TestSortingReporter$TimeoutTask;Lorg/scalatest/Timer;>;>;)V
   #97 = Utf8               distributingTest
   #98 = Utf8               (Ljava/lang/String;)V
   #99 = Utf8               testName
  #100 = Utf8               org/scalactic/Requirements$
  #101 = Class              #100          // org/scalactic/Requirements$
  #102 = Utf8               MODULE$
  #103 = Utf8               Lorg/scalactic/Requirements$;
  #104 = NameAndType        #102:#103     // MODULE$:Lorg/scalactic/Requirements$;
  #105 = Fieldref           #101.#104     // org/scalactic/Requirements$.MODULE$:Lorg/scalactic/Requirements$;
  #106 = Utf8               requirementsHelper
  #107 = Utf8               ()Lorg/scalactic/Requirements$RequirementsHelper;
  #108 = NameAndType        #106:#107     // requirementsHelper:()Lorg/scalactic/Requirements$RequirementsHelper;
  #109 = Methodref          #101.#108     // org/scalactic/Requirements$.requirementsHelper:()Lorg/scalactic/Requirements$RequirementsHelper;
  #110 = Utf8               java/lang/String
  #111 = Class              #110          // java/lang/String
  #112 = String             #99           // testName
  #113 = Utf8               [Ljava/lang/Object;
  #114 = Class              #113          // "[Ljava/lang/Object;"
  #115 = Utf8               [Ljava/lang/String;
  #116 = Class              #115          // "[Ljava/lang/String;"
  #117 = Utf8               org/scalactic/Prettifier$
  #118 = Class              #117          // org/scalactic/Prettifier$
  #119 = Utf8               Lorg/scalactic/Prettifier$;
  #120 = NameAndType        #102:#119     // MODULE$:Lorg/scalactic/Prettifier$;
  #121 = Fieldref           #118.#120     // org/scalactic/Prettifier$.MODULE$:Lorg/scalactic/Prettifier$;
  #122 = Utf8               default
  #123 = Utf8               ()Lorg/scalactic/Prettifier;
  #124 = NameAndType        #122:#123     // default:()Lorg/scalactic/Prettifier;
  #125 = Methodref          #118.#124     // org/scalactic/Prettifier$.default:()Lorg/scalactic/Prettifier;
  #126 = Utf8               org/scalactic/source/Position
  #127 = Class              #126          // org/scalactic/source/Position
  #128 = String             #9            // TestSortingReporter.scala
  #129 = Utf8               Please set the environment variable SCALACTIC_FILL_FILE_PATHNAMES to yes at compile time to enable this feature.
  #130 = String             #129          // Please set the environment variable SCALACTIC_FILL_FILE_PATHNAMES to yes at compile time to enable this feature.
  #131 = Utf8               <init>
  #132 = Utf8               (Ljava/lang/String;Ljava/lang/String;I)V
  #133 = NameAndType        #131:#132     // "<init>":(Ljava/lang/String;Ljava/lang/String;I)V
  #134 = Methodref          #127.#133     // org/scalactic/source/Position."<init>":(Ljava/lang/String;Ljava/lang/String;I)V
  #135 = Utf8               macroRequireNonNull
  #136 = Utf8               ([Ljava/lang/String;[Ljava/lang/Object;Lorg/scalactic/Prettifier;Lorg/scalactic/source/Position;)V
  #137 = NameAndType        #135:#136     // macroRequireNonNull:([Ljava/lang/String;[Ljava/lang/Object;Lorg/scalactic/Prettifier;Lorg/scalactic/source/Position;)V
  #138 = Methodref          #14.#137      // org/scalactic/Requirements$RequirementsHelper.macroRequireNonNull:([Ljava/lang/String;[Ljava/lang/Object;Lorg/scalactic/Prettifier;Lorg/scalactic/source/Position;)V
  #139 = NameAndType        #45:#80       // slotMap:()Lscala/collection/mutable/HashMap;
  #140 = Methodref          #2.#139       // org/scalatest/tools/TestSortingReporter.slotMap:()Lscala/collection/mutable/HashMap;
  #141 = Utf8               scala/collection/mutable/HashMap
  #142 = Class              #141          // scala/collection/mutable/HashMap
  #143 = Utf8               contains
  #144 = Utf8               (Ljava/lang/Object;)Z
  #145 = NameAndType        #143:#144     // contains:(Ljava/lang/Object;)Z
  #146 = Methodref          #142.#145     // scala/collection/mutable/HashMap.contains:(Ljava/lang/Object;)Z
  #147 = Utf8               java/lang/IllegalArgumentException
  #148 = Class              #147          // java/lang/IllegalArgumentException
  #149 = Utf8               java/lang/StringBuilder
  #150 = Class              #149          // java/lang/StringBuilder
  #151 = Integer            62
  #152 = NameAndType        #131:#88      // "<init>":(I)V
  #153 = Methodref          #150.#152     // java/lang/StringBuilder."<init>":(I)V
  #154 = Utf8               The passed testname:
  #155 = String             #154          // The passed testname:
  #156 = Utf8               append
  #157 = Utf8               (Ljava/lang/String;)Ljava/lang/StringBuilder;
  #158 = NameAndType        #156:#157     // append:(Ljava/lang/String;)Ljava/lang/StringBuilder;
  #159 = Methodref          #150.#158     // java/lang/StringBuilder.append:(Ljava/lang/String;)Ljava/lang/StringBuilder;
  #160 = Utf8               , was already passed to distributedTests.
  #161 = String             #160          // , was already passed to distributedTests.
  #162 = Utf8               toString
  #163 = Utf8               ()Ljava/lang/String;
  #164 = NameAndType        #162:#163     // toString:()Ljava/lang/String;
  #165 = Methodref          #150.#164     // java/lang/StringBuilder.toString:()Ljava/lang/String;
  #166 = NameAndType        #131:#98      // "<init>":(Ljava/lang/String;)V
  #167 = Methodref          #148.#166     // java/lang/IllegalArgumentException."<init>":(Ljava/lang/String;)V
  #168 = Utf8               java/util/UUID
  #169 = Class              #168          // java/util/UUID
  #170 = Utf8               randomUUID
  #171 = Utf8               ()Ljava/util/UUID;
  #172 = NameAndType        #170:#171     // randomUUID:()Ljava/util/UUID;
  #173 = Methodref          #169.#172     // java/util/UUID.randomUUID:()Ljava/util/UUID;
  #174 = Utf8               scala/collection/mutable/ListBuffer
  #175 = Class              #174          // scala/collection/mutable/ListBuffer
  #176 = NameAndType        #131:#62      // "<init>":()V
  #177 = Methodref          #175.#176     // scala/collection/mutable/ListBuffer."<init>":()V
  #178 = Utf8               (Lorg/scalatest/tools/TestSortingReporter;Ljava/util/UUID;Lscala/collection/mutable/ListBuffer;ZZZ)V
  #179 = NameAndType        #131:#178     // "<init>":(Lorg/scalatest/tools/TestSortingReporter;Ljava/util/UUID;Lscala/collection/mutable/ListBuffer;ZZZ)V
  #180 = Methodref          #19.#179      // org/scalatest/tools/TestSortingReporter$Slot."<init>":(Lorg/scalatest/tools/TestSortingReporter;Ljava/util/UUID;Lscala/collection/mutable/ListBuffer;ZZZ)V
  #181 = Utf8               put
  #182 = Utf8               (Ljava/lang/Object;Ljava/lang/Object;)Lscala/Option;
  #183 = NameAndType        #181:#182     // put:(Ljava/lang/Object;Ljava/lang/Object;)Lscala/Option;
  #184 = Methodref          #142.#183     // scala/collection/mutable/HashMap.put:(Ljava/lang/Object;Ljava/lang/Object;)Lscala/Option;
  #185 = NameAndType        #42:#76       // waitingBuffer:()Lscala/collection/mutable/ListBuffer;
  #186 = Methodref          #2.#185       // org/scalatest/tools/TestSortingReporter.waitingBuffer:()Lscala/collection/mutable/ListBuffer;
  #187 = Utf8               $plus$eq
  #188 = Utf8               (Ljava/lang/Object;)Lscala/collection/mutable/Growable;
  #189 = NameAndType        #187:#188     // $plus$eq:(Ljava/lang/Object;)Lscala/collection/mutable/Growable;
  #190 = Methodref          #175.#189     // scala/collection/mutable/ListBuffer.$plus$eq:(Ljava/lang/Object;)Lscala/collection/mutable/Growable;
  #191 = Utf8               size
  #192 = NameAndType        #191:#84      // size:()I
  #193 = Methodref          #175.#192     // scala/collection/mutable/ListBuffer.size:()I
  #194 = Utf8               scheduleTimeoutTask
  #195 = NameAndType        #194:#62      // scheduleTimeoutTask:()V
  #196 = Methodref          #2.#195       // org/scalatest/tools/TestSortingReporter.scheduleTimeoutTask:()V
  #197 = Utf8               slot
  #198 = Utf8               Lorg/scalatest/tools/TestSortingReporter$Slot;
  #199 = Utf8               java/lang/Throwable
  #200 = Class              #199          // java/lang/Throwable
  #201 = Utf8               (Ljava/lang/String;Lorg/scalatest/events/Event;)V
  #202 = String             #53           // event
  #203 = Utf8               org/scalatest/events/InfoProvided
  #204 = Class              #203          // org/scalatest/events/InfoProvided
  #205 = Utf8               org/scalatest/events/MarkupProvided
  #206 = Class              #205          // org/scalatest/events/MarkupProvided
  #207 = Utf8               org/scalatest/events/AlertProvided
  #208 = Class              #207          // org/scalatest/events/AlertProvided
  #209 = Utf8               org/scalatest/events/NoteProvided
  #210 = Class              #209          // org/scalatest/events/NoteProvided
  #211 = Utf8               (Ljava/lang/Object;)Ljava/lang/Object;
  #212 = NameAndType        #51:#211      // apply:(Ljava/lang/Object;)Ljava/lang/Object;
  #213 = Methodref          #142.#212     // scala/collection/mutable/HashMap.apply:(Ljava/lang/Object;)Ljava/lang/Object;
  #214 = Utf8               eventList
  #215 = NameAndType        #214:#76      // eventList:()Lscala/collection/mutable/ListBuffer;
  #216 = Methodref          #19.#215      // org/scalatest/tools/TestSortingReporter$Slot.eventList:()Lscala/collection/mutable/ListBuffer;
  #217 = Utf8               fireReadyEvents
  #218 = NameAndType        #217:#62      // fireReadyEvents:()V
  #219 = Methodref          #2.#218       // org/scalatest/tools/TestSortingReporter.fireReadyEvents:()V
  #220 = Utf8               scala/runtime/BoxedUnit
  #221 = Class              #220          // scala/runtime/BoxedUnit
  #222 = Utf8               UNIT
  #223 = Utf8               Lscala/runtime/BoxedUnit;
  #224 = NameAndType        #222:#223     // UNIT:Lscala/runtime/BoxedUnit;
  #225 = Fieldref           #221.#224     // scala/runtime/BoxedUnit.UNIT:Lscala/runtime/BoxedUnit;
  #226 = NameAndType        #51:#52       // apply:(Lorg/scalatest/events/Event;)V
  #227 = Methodref          #2.#226       // org/scalatest/tools/TestSortingReporter.apply:(Lorg/scalatest/events/Event;)V
  #228 = Utf8               org/scalatest/events/Event
  #229 = Class              #228          // org/scalatest/events/Event
  #230 = Utf8               completedTest
  #231 = Integer            69
  #232 = Utf8               , has either never started or already completed.
  #233 = String             #232          // , has either never started or already completed.
  #234 = Utf8               ready
  #235 = Utf8               ()Z
  #236 = NameAndType        #234:#235     // ready:()Z
  #237 = Methodref          #19.#236      // org/scalatest/tools/TestSortingReporter$Slot.ready:()Z
  #238 = Integer            45
  #239 = Utf8               , has already completed.
  #240 = String             #239          // , has already completed.
  #241 = Utf8               completedEvent
  #242 = NameAndType        #241:#235     // completedEvent:()Z
  #243 = Methodref          #19.#242      // org/scalatest/tools/TestSortingReporter$Slot.completedEvent:()Z
  #244 = Utf8               copy$default$1
  #245 = NameAndType        #244:#171     // copy$default$1:()Ljava/util/UUID;
  #246 = Methodref          #19.#245      // org/scalatest/tools/TestSortingReporter$Slot.copy$default$1:()Ljava/util/UUID;
  #247 = Utf8               copy$default$2
  #248 = NameAndType        #247:#76      // copy$default$2:()Lscala/collection/mutable/ListBuffer;
  #249 = Methodref          #19.#248      // org/scalatest/tools/TestSortingReporter$Slot.copy$default$2:()Lscala/collection/mutable/ListBuffer;
  #250 = Utf8               copy$default$4
  #251 = NameAndType        #250:#235     // copy$default$4:()Z
  #252 = Methodref          #19.#251      // org/scalatest/tools/TestSortingReporter$Slot.copy$default$4:()Z
  #253 = Utf8               copy
  #254 = Utf8               (Ljava/util/UUID;Lscala/collection/mutable/ListBuffer;ZZZ)Lorg/scalatest/tools/TestSortingReporter$Slot;
  #255 = NameAndType        #253:#254     // copy:(Ljava/util/UUID;Lscala/collection/mutable/ListBuffer;ZZZ)Lorg/scalatest/tools/TestSortingReporter$Slot;
  #256 = Methodref          #19.#255      // org/scalatest/tools/TestSortingReporter$Slot.copy:(Ljava/util/UUID;Lscala/collection/mutable/ListBuffer;ZZZ)Lorg/scalatest/tools/TestSortingReporter$Slot;
  #257 = Utf8               indexOf
  #258 = Utf8               (Ljava/lang/Object;)I
  #259 = NameAndType        #257:#258     // indexOf:(Ljava/lang/Object;)I
  #260 = Methodref          #175.#259     // scala/collection/mutable/ListBuffer.indexOf:(Ljava/lang/Object;)I
  #261 = Utf8               update
  #262 = Utf8               (ILjava/lang/Object;)V
  #263 = NameAndType        #261:#262     // update:(ILjava/lang/Object;)V
  #264 = Methodref          #175.#263     // scala/collection/mutable/ListBuffer.update:(ILjava/lang/Object;)V
  #265 = NameAndType        #48:#84       // completedTestCount:()I
  #266 = Methodref          #2.#265       // org/scalatest/tools/TestSortingReporter.completedTestCount:()I
  #267 = NameAndType        #87:#88       // completedTestCount_$eq:(I)V
  #268 = Methodref          #2.#267       // org/scalatest/tools/TestSortingReporter.completedTestCount_$eq:(I)V
  #269 = Utf8               checkCompletedTests
  #270 = NameAndType        #269:#62      // checkCompletedTests:()V
  #271 = Methodref          #2.#270       // org/scalatest/tools/TestSortingReporter.checkCompletedTests:()V
  #272 = Utf8               Z
  #273 = Utf8               x$2
  #274 = Utf8               x$3
  #275 = Utf8               Ljava/util/UUID;
  #276 = Utf8               x$4
  #277 = Utf8               x$5
  #278 = Utf8               newSlot
  #279 = Utf8               slotIdx
  #280 = NameAndType        #35:#36       // testCount:I
  #281 = Fieldref           #2.#280       // org/scalatest/tools/TestSortingReporter.testCount:I
  #282 = NameAndType        #37:#38       // suiteSorter:Lscala/Option;
  #283 = Fieldref           #2.#282       // org/scalatest/tools/TestSortingReporter.suiteSorter:Lscala/Option;
  #284 = Utf8               scala/Some
  #285 = Class              #284          // scala/Some
  #286 = Utf8               value
  #287 = Utf8               ()Ljava/lang/Object;
  #288 = NameAndType        #286:#287     // value:()Ljava/lang/Object;
  #289 = Methodref          #285.#288     // scala/Some.value:()Ljava/lang/Object;
  #290 = Utf8               org/scalatest/DistributedSuiteSorter
  #291 = Class              #290          // org/scalatest/DistributedSuiteSorter
  #292 = NameAndType        #29:#30       // suiteId:Ljava/lang/String;
  #293 = Fieldref           #2.#292       // org/scalatest/tools/TestSortingReporter.suiteId:Ljava/lang/String;
  #294 = Utf8               completedTests
  #295 = NameAndType        #294:#98      // completedTests:(Ljava/lang/String;)V
  #296 = InterfaceMethodref #291.#295     // org/scalatest/DistributedSuiteSorter.completedTests:(Ljava/lang/String;)V
  #297 = Utf8               scala/None$
  #298 = Class              #297          // scala/None$
  #299 = Utf8               Lscala/None$;
  #300 = NameAndType        #102:#299     // MODULE$:Lscala/None$;
  #301 = Fieldref           #298.#300     // scala/None$.MODULE$:Lscala/None$;
  #302 = Utf8               equals
  #303 = NameAndType        #302:#144     // equals:(Ljava/lang/Object;)Z
  #304 = Methodref          #4.#303       // java/lang/Object.equals:(Ljava/lang/Object;)Z
  #305 = Utf8               scala/MatchError
  #306 = Class              #305          // scala/MatchError
  #307 = Utf8               (Ljava/lang/Object;)V
  #308 = NameAndType        #131:#307     // "<init>":(Ljava/lang/Object;)V
  #309 = Methodref          #306.#308     // scala/MatchError."<init>":(Ljava/lang/Object;)V
  #310 = Utf8               Lorg/scalatest/DistributedSuiteSorter;
  #311 = Utf8               scala/Option
  #312 = Class              #311          // scala/Option
  #313 = Utf8               doApply
  #314 = Utf8               org/scalatest/events/TestStarting
  #315 = Class              #314          // org/scalatest/events/TestStarting
  #316 = NameAndType        #99:#163      // testName:()Ljava/lang/String;
  #317 = Methodref          #315.#316     // org/scalatest/events/TestStarting.testName:()Ljava/lang/String;
  #318 = Utf8               get
  #319 = Utf8               (Ljava/lang/Object;)Lscala/Option;
  #320 = NameAndType        #318:#319     // get:(Ljava/lang/Object;)Lscala/Option;
  #321 = Methodref          #142.#320     // scala/collection/mutable/HashMap.get:(Ljava/lang/Object;)Lscala/Option;
  #322 = NameAndType        #31:#32       // dispatch:Lorg/scalatest/Reporter;
  #323 = Fieldref           #2.#322       // org/scalatest/tools/TestSortingReporter.dispatch:Lorg/scalatest/Reporter;
  #324 = Utf8               org/scalatest/Reporter
  #325 = Class              #324          // org/scalatest/Reporter
  #326 = InterfaceMethodref #325.#226     // org/scalatest/Reporter.apply:(Lorg/scalatest/events/Event;)V
  #327 = Utf8               org/scalatest/events/TestIgnored
  #328 = Class              #327          // org/scalatest/events/TestIgnored
  #329 = Methodref          #328.#316     // org/scalatest/events/TestIgnored.testName:()Ljava/lang/String;
  #330 = Utf8               org/scalatest/events/TestSucceeded
  #331 = Class              #330          // org/scalatest/events/TestSucceeded
  #332 = Methodref          #331.#316     // org/scalatest/events/TestSucceeded.testName:()Ljava/lang/String;
  #333 = Utf8               handleTestCompleted
  #334 = Utf8               (Lorg/scalatest/events/Event;Ljava/lang/String;)V
  #335 = NameAndType        #333:#334     // handleTestCompleted:(Lorg/scalatest/events/Event;Ljava/lang/String;)V
  #336 = Methodref          #2.#335       // org/scalatest/tools/TestSortingReporter.handleTestCompleted:(Lorg/scalatest/events/Event;Ljava/lang/String;)V
  #337 = Utf8               org/scalatest/events/TestFailed
  #338 = Class              #337          // org/scalatest/events/TestFailed
  #339 = Methodref          #338.#316     // org/scalatest/events/TestFailed.testName:()Ljava/lang/String;
  #340 = Utf8               org/scalatest/events/TestPending
  #341 = Class              #340          // org/scalatest/events/TestPending
  #342 = Methodref          #341.#316     // org/scalatest/events/TestPending.testName:()Ljava/lang/String;
  #343 = Utf8               org/scalatest/events/TestCanceled
  #344 = Class              #343          // org/scalatest/events/TestCanceled
  #345 = Methodref          #344.#316     // org/scalatest/events/TestCanceled.testName:()Ljava/lang/String;
  #346 = Utf8               org/scalatest/events/ScopeOpened
  #347 = Class              #346          // org/scalatest/events/ScopeOpened
  #348 = Utf8               handleSuiteEvent
  #349 = NameAndType        #348:#52      // handleSuiteEvent:(Lorg/scalatest/events/Event;)V
  #350 = Methodref          #2.#349       // org/scalatest/tools/TestSortingReporter.handleSuiteEvent:(Lorg/scalatest/events/Event;)V
  #351 = Utf8               org/scalatest/events/ScopeClosed
  #352 = Class              #351          // org/scalatest/events/ScopeClosed
  #353 = Utf8               org/scalatest/events/ScopePending
  #354 = Class              #353          // org/scalatest/events/ScopePending
  #355 = Utf8               listBuffer
  #356 = Utf8               $colon$plus
  #357 = NameAndType        #356:#211     // $colon$plus:(Ljava/lang/Object;)Ljava/lang/Object;
  #358 = Methodref          #175.#357     // scala/collection/mutable/ListBuffer.$colon$plus:(Ljava/lang/Object;)Ljava/lang/Object;
  #359 = Utf8               completed
  #360 = NameAndType        #359:#235     // completed:()Z
  #361 = Methodref          #19.#360      // org/scalatest/tools/TestSortingReporter$Slot.completed:()Z
  #362 = Utf8               copy$default$3
  #363 = NameAndType        #362:#235     // copy$default$3:()Z
  #364 = Methodref          #19.#363      // org/scalatest/tools/TestSortingReporter$Slot.copy$default$3:()Z
  #365 = Utf8               fireSlotEvents
  #366 = Utf8               (Lorg/scalatest/tools/TestSortingReporter$Slot;)V
  #367 = Utf8               length
  #368 = NameAndType        #367:#84      // length:()I
  #369 = Methodref          #175.#368     // scala/collection/mutable/ListBuffer.length:()I
  #370 = Utf8               head
  #371 = NameAndType        #370:#287     // head:()Ljava/lang/Object;
  #372 = Methodref          #175.#371     // scala/collection/mutable/ListBuffer.head:()Ljava/lang/Object;
  #373 = Utf8               remove
  #374 = Utf8               (I)Ljava/lang/Object;
  #375 = NameAndType        #373:#374     // remove:(I)Ljava/lang/Object;
  #376 = Methodref          #175.#375     // scala/collection/mutable/ListBuffer.remove:(I)Ljava/lang/Object;
  #377 = NameAndType        #365:#366     // fireSlotEvents:(Lorg/scalatest/tools/TestSortingReporter$Slot;)V
  #378 = Methodref          #2.#377       // org/scalatest/tools/TestSortingReporter.fireSlotEvents:(Lorg/scalatest/tools/TestSortingReporter$Slot;)V
  #379 = Utf8               cancelTimeoutTask
  #380 = NameAndType        #379:#62      // cancelTimeoutTask:()V
  #381 = Methodref          #2.#380       // org/scalatest/tools/TestSortingReporter.cancelTimeoutTask:()V
  #382 = Utf8               newHead
  #383 = NameAndType        #49:#90       // timeoutTask:()Lscala/Option;
  #384 = Methodref          #2.#383       // org/scalatest/tools/TestSortingReporter.timeoutTask:()Lscala/Option;
  #385 = Utf8               scala/Tuple2
  #386 = Class              #385          // scala/Tuple2
  #387 = Utf8               _1
  #388 = NameAndType        #387:#287     // _1:()Ljava/lang/Object;
  #389 = Methodref          #386.#388     // scala/Tuple2._1:()Ljava/lang/Object;
  #390 = Utf8               _2
  #391 = NameAndType        #390:#287     // _2:()Ljava/lang/Object;
  #392 = Methodref          #386.#391     // scala/Tuple2._2:()Ljava/lang/Object;
  #393 = Utf8               org/scalatest/Timer
  #394 = Class              #393          // org/scalatest/Timer
  #395 = Utf8               uuid
  #396 = NameAndType        #395:#171     // uuid:()Ljava/util/UUID;
  #397 = Methodref          #19.#396      // org/scalatest/tools/TestSortingReporter$Slot.uuid:()Ljava/util/UUID;
  #398 = Utf8               ()Lorg/scalatest/tools/TestSortingReporter$Slot;
  #399 = NameAndType        #197:#398     // slot:()Lorg/scalatest/tools/TestSortingReporter$Slot;
  #400 = Methodref          #25.#399      // org/scalatest/tools/TestSortingReporter$TimeoutTask.slot:()Lorg/scalatest/tools/TestSortingReporter$Slot;
  #401 = Utf8               cancel
  #402 = NameAndType        #401:#62      // cancel:()V
  #403 = Methodref          #25.#402      // org/scalatest/tools/TestSortingReporter$TimeoutTask.cancel:()V
  #404 = Methodref          #394.#402     // org/scalatest/Timer.cancel:()V
  #405 = Utf8               (Lorg/scalatest/tools/TestSortingReporter;Lorg/scalatest/tools/TestSortingReporter$Slot;)V
  #406 = NameAndType        #131:#405     // "<init>":(Lorg/scalatest/tools/TestSortingReporter;Lorg/scalatest/tools/TestSortingReporter$Slot;)V
  #407 = Methodref          #25.#406      // org/scalatest/tools/TestSortingReporter$TimeoutTask."<init>":(Lorg/scalatest/tools/TestSortingReporter;Lorg/scalatest/tools/TestSortingReporter$Slot;)V
  #408 = Methodref          #394.#176     // org/scalatest/Timer."<init>":()V
  #409 = Utf8               (Ljava/lang/Object;Ljava/lang/Object;)V
  #410 = NameAndType        #131:#409     // "<init>":(Ljava/lang/Object;Ljava/lang/Object;)V
  #411 = Methodref          #386.#410     // scala/Tuple2."<init>":(Ljava/lang/Object;Ljava/lang/Object;)V
  #412 = Methodref          #285.#308     // scala/Some."<init>":(Ljava/lang/Object;)V
  #413 = NameAndType        #94:#95       // timeoutTask_$eq:(Lscala/Option;)V
  #414 = Methodref          #2.#413       // org/scalatest/tools/TestSortingReporter.timeoutTask_$eq:(Lscala/Option;)V
  #415 = NameAndType        #33:#34       // sortingTimeout:Lorg/scalatest/time/Span;
  #416 = Fieldref           #2.#415       // org/scalatest/tools/TestSortingReporter.sortingTimeout:Lorg/scalatest/time/Span;
  #417 = Utf8               org/scalatest/time/Span
  #418 = Class              #417          // org/scalatest/time/Span
  #419 = Utf8               millisPart
  #420 = Utf8               ()J
  #421 = NameAndType        #419:#420     // millisPart:()J
  #422 = Methodref          #418.#421     // org/scalatest/time/Span.millisPart:()J
  #423 = Utf8               schedule
  #424 = Utf8               (Lorg/scalatest/TimerTask;J)V
  #425 = NameAndType        #423:#424     // schedule:(Lorg/scalatest/TimerTask;J)V
  #426 = Methodref          #394.#425     // org/scalatest/Timer.schedule:(Lorg/scalatest/TimerTask;J)V
  #427 = Utf8               task
  #428 = Utf8               Lorg/scalatest/tools/TestSortingReporter$TimeoutTask;
  #429 = Utf8               timer
  #430 = Utf8               Lorg/scalatest/Timer;
  #431 = Utf8               oldTask
  #432 = Utf8               oldTimer
  #433 = Utf8               org$scalatest$tools$TestSortingReporter$$timeout
  #434 = NameAndType        #318:#287     // get:()Ljava/lang/Object;
  #435 = Methodref          #312.#434     // scala/Option.get:()Ljava/lang/Object;
  #436 = Utf8               doDispose
  #437 = Utf8               org/scalatest/Reporter$
  #438 = Class              #437          // org/scalatest/Reporter$
  #439 = Utf8               Lorg/scalatest/Reporter$;
  #440 = NameAndType        #102:#439     // MODULE$:Lorg/scalatest/Reporter$;
  #441 = Fieldref           #438.#440     // org/scalatest/Reporter$.MODULE$:Lorg/scalatest/Reporter$;
  #442 = Utf8               propagateDispose
  #443 = Utf8               (Lorg/scalatest/Reporter;)V
  #444 = NameAndType        #442:#443     // propagateDispose:(Lorg/scalatest/Reporter;)V
  #445 = Methodref          #438.#444     // org/scalatest/Reporter$.propagateDispose:(Lorg/scalatest/Reporter;)V
  #446 = Utf8               (Lorg/scalatest/tools/TestSortingReporter;)V
  #447 = NameAndType        #131:#446     // "<init>":(Lorg/scalatest/tools/TestSortingReporter;)V
  #448 = Methodref          #22.#447      // org/scalatest/tools/TestSortingReporter$Slot$."<init>":(Lorg/scalatest/tools/TestSortingReporter;)V
  #449 = Utf8               (Ljava/lang/String;Lorg/scalatest/Reporter;Lorg/scalatest/time/Span;ILscala/Option;Ljava/io/PrintStream;)V
  #450 = Utf8               (Ljava/lang/String;Lorg/scalatest/Reporter;Lorg/scalatest/time/Span;ILscala/Option<Lorg/scalatest/DistributedSuiteSorter;>;Ljava/io/PrintStream;)V
  #451 = Methodref          #4.#176       // java/lang/Object."<init>":()V
  #452 = Utf8               $init$
  #453 = NameAndType        #452:#64      // $init$:(Lorg/scalatest/CatchReporter;)V
  #454 = InterfaceMethodref #6.#453       // org/scalatest/CatchReporter.$init$:(Lorg/scalatest/CatchReporter;)V
  #455 = Utf8               distributingTests
  #456 = NameAndType        #455:#98      // distributingTests:(Ljava/lang/String;)V
  #457 = InterfaceMethodref #291.#456     // org/scalatest/DistributedSuiteSorter.distributingTests:(Ljava/lang/String;)V
  #458 = Methodref          #142.#176     // scala/collection/mutable/HashMap."<init>":()V
  #459 = Utf8               java/io/PrintStream
  #460 = Class              #459          // java/io/PrintStream
  #461 = Utf8               Signature
  #462 = Utf8               Code
  #463 = Utf8               LineNumberTable
  #464 = Utf8               LocalVariableTable
  #465 = Utf8               MethodParameters
  #466 = Utf8               StackMapTable
  #467 = Utf8               InnerClasses
  #468 = Utf8               SourceFile
  #469 = Utf8               RuntimeVisibleAnnotations
  #470 = Utf8               ScalaInlineInfo
  #471 = Utf8               ScalaSig
{
  private volatile org.scalatest.tools.TestSortingReporter$Slot$ Slot$module;
    descriptor: Lorg/scalatest/tools/TestSortingReporter$Slot$;
    flags: (0x0042) ACC_PRIVATE, ACC_VOLATILE

  private final java.lang.String suiteId;
    descriptor: Ljava/lang/String;
    flags: (0x0012) ACC_PRIVATE, ACC_FINAL

  private final org.scalatest.Reporter dispatch;
    descriptor: Lorg/scalatest/Reporter;
    flags: (0x0012) ACC_PRIVATE, ACC_FINAL

  private final org.scalatest.time.Span sortingTimeout;
    descriptor: Lorg/scalatest/time/Span;
    flags: (0x0012) ACC_PRIVATE, ACC_FINAL

  private final int testCount;
    descriptor: I
    flags: (0x0012) ACC_PRIVATE, ACC_FINAL

  private final scala.Option<org.scalatest.DistributedSuiteSorter> suiteSorter;
    descriptor: Lscala/Option;
    flags: (0x0012) ACC_PRIVATE, ACC_FINAL
    Signature: #39                          // Lscala/Option<Lorg/scalatest/DistributedSuiteSorter;>;

  private final java.io.PrintStream out;
    descriptor: Ljava/io/PrintStream;
    flags: (0x0012) ACC_PRIVATE, ACC_FINAL

  private final scala.collection.mutable.ListBuffer<org.scalatest.tools.TestSortingReporter$Slot> waitingBuffer;
    descriptor: Lscala/collection/mutable/ListBuffer;
    flags: (0x0012) ACC_PRIVATE, ACC_FINAL
    Signature: #44                          // Lscala/collection/mutable/ListBuffer<Lorg/scalatest/tools/TestSortingReporter$Slot;>;

  private final scala.collection.mutable.HashMap<java.lang.String, org.scalatest.tools.TestSortingReporter$Slot> slotMap;
    descriptor: Lscala/collection/mutable/HashMap;
    flags: (0x0012) ACC_PRIVATE, ACC_FINAL
    Signature: #47                          // Lscala/collection/mutable/HashMap<Ljava/lang/String;Lorg/scalatest/tools/TestSortingReporter$Slot;>;

  private volatile int completedTestCount;
    descriptor: I
    flags: (0x0042) ACC_PRIVATE, ACC_VOLATILE

  private scala.Option<scala.Tuple2<org.scalatest.tools.TestSortingReporter$TimeoutTask, org.scalatest.Timer>> timeoutTask;
    descriptor: Lscala/Option;
    flags: (0x0002) ACC_PRIVATE
    Signature: #50                          // Lscala/Option<Lscala/Tuple2<Lorg/scalatest/tools/TestSortingReporter$TimeoutTask;Lorg/scalatest/Timer;>;>;

  public void apply(org.scalatest.events.Event);
    descriptor: (Lorg/scalatest/events/Event;)V
    flags: (0x0001) ACC_PUBLIC
    Code:
      stack=2, locals=2, args_size=2
         0: aload_0
         1: aload_1
         2: invokestatic  #57                 // InterfaceMethod org/scalatest/CatchReporter.apply$:(Lorg/scalatest/CatchReporter;Lorg/scalatest/events/Event;)V
         5: return
      LineNumberTable:
        line 28: 0
      LocalVariableTable:
        Start  Length  Slot  Name   Signature
            0       6     0  this   Lorg/scalatest/tools/TestSortingReporter;
            0       6     1 event   Lorg/scalatest/events/Event;
    MethodParameters:
      Name                           Flags
      event                          final

  public void dispose();
    descriptor: ()V
    flags: (0x0001) ACC_PUBLIC
    Code:
      stack=1, locals=1, args_size=1
         0: aload_0
         1: invokestatic  #66                 // InterfaceMethod org/scalatest/CatchReporter.dispose$:(Lorg/scalatest/CatchReporter;)V
         4: return
      LineNumberTable:
        line 28: 0
      LocalVariableTable:
        Start  Length  Slot  Name   Signature
            0       5     0  this   Lorg/scalatest/tools/TestSortingReporter;

  public org.scalatest.tools.TestSortingReporter$Slot$ Slot();
    descriptor: ()Lorg/scalatest/tools/TestSortingReporter$Slot$;
    flags: (0x0001) ACC_PUBLIC
    Code:
      stack=1, locals=1, args_size=1
         0: aload_0
         1: getfield      #69                 // Field Slot$module:Lorg/scalatest/tools/TestSortingReporter$Slot$;
         4: ifnonnull     11
         7: aload_0
         8: invokespecial #72                 // Method Slot$lzycompute$1:()V
        11: aload_0
        12: getfield      #69                 // Field Slot$module:Lorg/scalatest/tools/TestSortingReporter$Slot$;
        15: areturn
      StackMapTable: number_of_entries = 1
        frame_type = 11 /* same */
      LineNumberTable:
        line 38: 0
      LocalVariableTable:
        Start  Length  Slot  Name   Signature
            0      16     0  this   Lorg/scalatest/tools/TestSortingReporter;

  public java.io.PrintStream out();
    descriptor: ()Ljava/io/PrintStream;
    flags: (0x0001) ACC_PUBLIC
    Code:
      stack=1, locals=1, args_size=1
         0: aload_0
         1: getfield      #75                 // Field out:Ljava/io/PrintStream;
         4: areturn
      LineNumberTable:
        line 28: 0
      LocalVariableTable:
        Start  Length  Slot  Name   Signature
            0       5     0  this   Lorg/scalatest/tools/TestSortingReporter;

  private scala.collection.mutable.ListBuffer<org.scalatest.tools.TestSortingReporter$Slot> waitingBuffer();
    descriptor: ()Lscala/collection/mutable/ListBuffer;
    flags: (0x0002) ACC_PRIVATE
    Code:
      stack=1, locals=1, args_size=1
         0: aload_0
         1: getfield      #79                 // Field waitingBuffer:Lscala/collection/mutable/ListBuffer;
         4: areturn
      LineNumberTable:
        line 40: 0
      LocalVariableTable:
        Start  Length  Slot  Name   Signature
            0       5     0  this   Lorg/scalatest/tools/TestSortingReporter;
    Signature: #77                          // ()Lscala/collection/mutable/ListBuffer<Lorg/scalatest/tools/TestSortingReporter$Slot;>;

  private scala.collection.mutable.HashMap<java.lang.String, org.scalatest.tools.TestSortingReporter$Slot> slotMap();
    descriptor: ()Lscala/collection/mutable/HashMap;
    flags: (0x0002) ACC_PRIVATE
    Code:
      stack=1, locals=1, args_size=1
         0: aload_0
         1: getfield      #83                 // Field slotMap:Lscala/collection/mutable/HashMap;
         4: areturn
      LineNumberTable:
        line 41: 0
      LocalVariableTable:
        Start  Length  Slot  Name   Signature
            0       5     0  this   Lorg/scalatest/tools/TestSortingReporter;
    Signature: #81                          // ()Lscala/collection/mutable/HashMap<Ljava/lang/String;Lorg/scalatest/tools/TestSortingReporter$Slot;>;

  private int completedTestCount();
    descriptor: ()I
    flags: (0x0002) ACC_PRIVATE
    Code:
      stack=1, locals=1, args_size=1
         0: aload_0
         1: getfield      #86                 // Field completedTestCount:I
         4: ireturn
      LineNumberTable:
        line 42: 0
      LocalVariableTable:
        Start  Length  Slot  Name   Signature
            0       5     0  this   Lorg/scalatest/tools/TestSortingReporter;

  private void completedTestCount_$eq(int);
    descriptor: (I)V
    flags: (0x0002) ACC_PRIVATE
    Code:
      stack=2, locals=2, args_size=2
         0: aload_0
         1: iload_1
         2: putfield      #86                 // Field completedTestCount:I
         5: return
      LineNumberTable:
        line 42: 0
      LocalVariableTable:
        Start  Length  Slot  Name   Signature
            0       6     0  this   Lorg/scalatest/tools/TestSortingReporter;
            0       6     1   x$1   I
    MethodParameters:
      Name                           Flags
      x$1                            final

  private scala.Option<scala.Tuple2<org.scalatest.tools.TestSortingReporter$TimeoutTask, org.scalatest.Timer>> timeoutTask();
    descriptor: ()Lscala/Option;
    flags: (0x0002) ACC_PRIVATE
    Code:
      stack=1, locals=1, args_size=1
         0: aload_0
         1: getfield      #93                 // Field timeoutTask:Lscala/Option;
         4: areturn
      LineNumberTable:
        line 53: 0
      LocalVariableTable:
        Start  Length  Slot  Name   Signature
            0       5     0  this   Lorg/scalatest/tools/TestSortingReporter;
    Signature: #91                          // ()Lscala/Option<Lscala/Tuple2<Lorg/scalatest/tools/TestSortingReporter$TimeoutTask;Lorg/scalatest/Timer;>;>;

  private void timeoutTask_$eq(scala.Option<scala.Tuple2<org.scalatest.tools.TestSortingReporter$TimeoutTask, org.scalatest.Timer>>);
    descriptor: (Lscala/Option;)V
    flags: (0x0002) ACC_PRIVATE
    Code:
      stack=2, locals=2, args_size=2
         0: aload_0
         1: aload_1
         2: putfield      #93                 // Field timeoutTask:Lscala/Option;
         5: return
      LineNumberTable:
        line 53: 0
      LocalVariableTable:
        Start  Length  Slot  Name   Signature
            0       6     0  this   Lorg/scalatest/tools/TestSortingReporter;
            0       6     1   x$1   Lscala/Option;
    Signature: #96                          // (Lscala/Option<Lscala/Tuple2<Lorg/scalatest/tools/TestSortingReporter$TimeoutTask;Lorg/scalatest/Timer;>;>;)V
    MethodParameters:
      Name                           Flags
      x$1                            final

  public void distributingTest(java.lang.String);
    descriptor: (Ljava/lang/String;)V
    flags: (0x0001) ACC_PUBLIC
    Code:
      stack=9, locals=4, args_size=2
         0: getstatic     #105                // Field org/scalactic/Requirements$.MODULE$:Lorg/scalactic/Requirements$;
         3: invokevirtual #109                // Method org/scalactic/Requirements$.requirementsHelper:()Lorg/scalactic/Requirements$RequirementsHelper;
         6: iconst_1
         7: anewarray     #111                // class java/lang/String
        10: dup
        11: iconst_0
        12: ldc           #112                // String testName
        14: aastore
        15: checkcast     #114                // class "[Ljava/lang/Object;"
        18: checkcast     #116                // class "[Ljava/lang/String;"
        21: iconst_1
        22: anewarray     #4                  // class java/lang/Object
        25: dup
        26: iconst_0
        27: aload_1
        28: aastore
        29: checkcast     #114                // class "[Ljava/lang/Object;"
        32: getstatic     #121                // Field org/scalactic/Prettifier$.MODULE$:Lorg/scalactic/Prettifier$;
        35: invokevirtual #125                // Method org/scalactic/Prettifier$.default:()Lorg/scalactic/Prettifier;
        38: new           #127                // class org/scalactic/source/Position
        41: dup
        42: ldc           #128                // String TestSortingReporter.scala
        44: ldc           #130                // String Please set the environment variable SCALACTIC_FILL_FILE_PATHNAMES to yes at compile time to enable this feature.
        46: bipush        62
        48: invokespecial #134                // Method org/scalactic/source/Position."<init>":(Ljava/lang/String;Ljava/lang/String;I)V
        51: invokevirtual #138                // Method org/scalactic/Requirements$RequirementsHelper.macroRequireNonNull:([Ljava/lang/String;[Ljava/lang/Object;Lorg/scalactic/Prettifier;Lorg/scalactic/source/Position;)V
        54: aload_0
        55: dup
        56: astore_2
        57: monitorenter
        58: aload_0
        59: invokespecial #140                // Method slotMap:()Lscala/collection/mutable/HashMap;
        62: aload_1
        63: invokevirtual #146                // Method scala/collection/mutable/HashMap.contains:(Ljava/lang/Object;)Z
        66: ifeq          103
        69: new           #148                // class java/lang/IllegalArgumentException
        72: dup
        73: new           #150                // class java/lang/StringBuilder
        76: dup
        77: ldc           #151                // int 62
        79: invokespecial #153                // Method java/lang/StringBuilder."<init>":(I)V
        82: ldc           #155                // String The passed testname:
        84: invokevirtual #159                // Method java/lang/StringBuilder.append:(Ljava/lang/String;)Ljava/lang/StringBuilder;
        87: aload_1
        88: invokevirtual #159                // Method java/lang/StringBuilder.append:(Ljava/lang/String;)Ljava/lang/StringBuilder;
        91: ldc           #161                // String , was already passed to distributedTests.
        93: invokevirtual #159                // Method java/lang/StringBuilder.append:(Ljava/lang/String;)Ljava/lang/StringBuilder;
        96: invokevirtual #165                // Method java/lang/StringBuilder.toString:()Ljava/lang/String;
        99: invokespecial #167                // Method java/lang/IllegalArgumentException."<init>":(Ljava/lang/String;)V
       102: athrow
       103: new           #19                 // class org/scalatest/tools/TestSortingReporter$Slot
       106: dup
       107: aload_0
       108: invokestatic  #173                // Method java/util/UUID.randomUUID:()Ljava/util/UUID;
       111: new           #175                // class scala/collection/mutable/ListBuffer
       114: dup
       115: invokespecial #177                // Method scala/collection/mutable/ListBuffer."<init>":()V
       118: iconst_0
       119: iconst_0
       120: iconst_0
       121: invokespecial #180                // Method org/scalatest/tools/TestSortingReporter$Slot."<init>":(Lorg/scalatest/tools/TestSortingReporter;Ljava/util/UUID;Lscala/collection/mutable/ListBuffer;ZZZ)V
       124: astore_3
       125: aload_0
       126: invokespecial #140                // Method slotMap:()Lscala/collection/mutable/HashMap;
       129: aload_1
       130: aload_3
       131: invokevirtual #184                // Method scala/collection/mutable/HashMap.put:(Ljava/lang/Object;Ljava/lang/Object;)Lscala/Option;
       134: pop
       135: aload_0
       136: invokespecial #186                // Method waitingBuffer:()Lscala/collection/mutable/ListBuffer;
       139: aload_3
       140: invokevirtual #190                // Method scala/collection/mutable/ListBuffer.$plus$eq:(Ljava/lang/Object;)Lscala/collection/mutable/Growable;
       143: pop
       144: aload_0
       145: invokespecial #186                // Method waitingBuffer:()Lscala/collection/mutable/ListBuffer;
       148: invokevirtual #193                // Method scala/collection/mutable/ListBuffer.size:()I
       151: iconst_1
       152: if_icmpne     162
       155: aload_0
       156: invokespecial #196                // Method scheduleTimeoutTask:()V
       159: goto          162
       162: aload_2
       163: monitorexit
       164: goto          170
       167: aload_2
       168: monitorexit
       169: athrow
       170: return
      Exception table:
         from    to  target type
            58   162   167   any
      StackMapTable: number_of_entries = 4
        frame_type = 252 /* append */
          offset_delta = 103
          locals = [ class org/scalatest/tools/TestSortingReporter ]
        frame_type = 252 /* append */
          offset_delta = 58
          locals = [ class org/scalatest/tools/TestSortingReporter$Slot ]
        frame_type = 255 /* full_frame */
          offset_delta = 4
          locals = [ class org/scalatest/tools/TestSortingReporter, class java/lang/String, class org/scalatest/tools/TestSortingReporter ]
          stack = [ class java/lang/Throwable ]
        frame_type = 252 /* append */
          offset_delta = 2
          locals = [ class org/scalatest/tools/TestSortingReporter$Slot ]
      LineNumberTable:
        line 62: 0
        line 63: 54
        line 64: 58
        line 65: 69
        line 66: 103
        line 67: 125
        line 68: 135
        line 71: 144
        line 72: 155
        line 71: 162
        line 63: 170
      LocalVariableTable:
        Start  Length  Slot  Name   Signature
          125      37     3  slot   Lorg/scalatest/tools/TestSortingReporter$Slot;
            0     171     0  this   Lorg/scalatest/tools/TestSortingReporter;
            0     171     1 testName   Ljava/lang/String;
    MethodParameters:
      Name                           Flags
      testName                       final

  public void apply(java.lang.String, org.scalatest.events.Event);
    descriptor: (Ljava/lang/String;Lorg/scalatest/events/Event;)V
    flags: (0x0001) ACC_PUBLIC
    Code:
      stack=9, locals=8, args_size=3
         0: getstatic     #105                // Field org/scalactic/Requirements$.MODULE$:Lorg/scalactic/Requirements$;
         3: invokevirtual #109                // Method org/scalactic/Requirements$.requirementsHelper:()Lorg/scalactic/Requirements$RequirementsHelper;
         6: iconst_2
         7: anewarray     #111                // class java/lang/String
        10: dup
        11: iconst_0
        12: ldc           #112                // String testName
        14: aastore
        15: dup
        16: iconst_1
        17: ldc           #202                // String event
        19: aastore
        20: checkcast     #114                // class "[Ljava/lang/Object;"
        23: checkcast     #116                // class "[Ljava/lang/String;"
        26: iconst_2
        27: anewarray     #4                  // class java/lang/Object
        30: dup
        31: iconst_0
        32: aload_1
        33: aastore
        34: dup
        35: iconst_1
        36: aload_2
        37: aastore
        38: checkcast     #114                // class "[Ljava/lang/Object;"
        41: getstatic     #121                // Field org/scalactic/Prettifier$.MODULE$:Lorg/scalactic/Prettifier$;
        44: invokevirtual #125                // Method org/scalactic/Prettifier$.default:()Lorg/scalactic/Prettifier;
        47: new           #127                // class org/scalactic/source/Position
        50: dup
        51: ldc           #128                // String TestSortingReporter.scala
        53: ldc           #130                // String Please set the environment variable SCALACTIC_FILL_FILE_PATHNAMES to yes at compile time to enable this feature.
        55: bipush        77
        57: invokespecial #134                // Method org/scalactic/source/Position."<init>":(Ljava/lang/String;Ljava/lang/String;I)V
        60: invokevirtual #138                // Method org/scalactic/Requirements$RequirementsHelper.macroRequireNonNull:([Ljava/lang/String;[Ljava/lang/Object;Lorg/scalactic/Prettifier;Lorg/scalactic/source/Position;)V
        63: aload_0
        64: dup
        65: astore        5
        67: monitorenter
        68: aload_2
        69: astore        6
        71: aload         6
        73: instanceof    #204                // class org/scalatest/events/InfoProvided
        76: ifeq          85
        79: iconst_1
        80: istore        4
        82: goto          145
        85: goto          88
        88: aload         6
        90: instanceof    #206                // class org/scalatest/events/MarkupProvided
        93: ifeq          102
        96: iconst_1
        97: istore        4
        99: goto          145
       102: goto          105
       105: aload         6
       107: instanceof    #208                // class org/scalatest/events/AlertProvided
       110: ifeq          119
       113: iconst_1
       114: istore        4
       116: goto          145
       119: goto          122
       122: aload         6
       124: instanceof    #210                // class org/scalatest/events/NoteProvided
       127: ifeq          136
       130: iconst_1
       131: istore        4
       133: goto          145
       136: goto          139
       139: iconst_0
       140: istore        4
       142: goto          145
       145: iload         4
       147: ifeq          184
       150: aload_0
       151: invokespecial #140                // Method slotMap:()Lscala/collection/mutable/HashMap;
       154: aload_1
       155: invokevirtual #213                // Method scala/collection/mutable/HashMap.apply:(Ljava/lang/Object;)Ljava/lang/Object;
       158: checkcast     #19                 // class org/scalatest/tools/TestSortingReporter$Slot
       161: astore        7
       163: aload         7
       165: invokevirtual #216                // Method org/scalatest/tools/TestSortingReporter$Slot.eventList:()Lscala/collection/mutable/ListBuffer;
       168: aload_2
       169: invokevirtual #190                // Method scala/collection/mutable/ListBuffer.$plus$eq:(Ljava/lang/Object;)Lscala/collection/mutable/Growable;
       172: pop
       173: aload_0
       174: invokespecial #219                // Method fireReadyEvents:()V
       177: getstatic     #225                // Field scala/runtime/BoxedUnit.UNIT:Lscala/runtime/BoxedUnit;
       180: astore_3
       181: goto          199
       184: goto          187
       187: aload_0
       188: aload_2
       189: invokevirtual #227                // Method apply:(Lorg/scalatest/events/Event;)V
       192: getstatic     #225                // Field scala/runtime/BoxedUnit.UNIT:Lscala/runtime/BoxedUnit;
       195: astore_3
       196: goto          199
       199: aload         5
       201: monitorexit
       202: goto          209
       205: aload         5
       207: monitorexit
       208: athrow
       209: return
      Exception table:
         from    to  target type
            68   199   205   any
      StackMapTable: number_of_entries = 14
        frame_type = 255 /* full_frame */
          offset_delta = 85
          locals = [ class org/scalatest/tools/TestSortingReporter, class java/lang/String, class org/scalatest/events/Event, top, top, class org/scalatest/tools/TestSortingReporter, class org/scalatest/events/Event ]
          stack = []
        frame_type = 2 /* same */
        frame_type = 13 /* same */
        frame_type = 2 /* same */
        frame_type = 13 /* same */
        frame_type = 2 /* same */
        frame_type = 13 /* same */
        frame_type = 2 /* same */
        frame_type = 255 /* full_frame */
          offset_delta = 5
          locals = [ class org/scalatest/tools/TestSortingReporter, class java/lang/String, class org/scalatest/events/Event, top, int, class org/scalatest/tools/TestSortingReporter, class org/scalatest/events/Event ]
          stack = []
        frame_type = 38 /* same */
        frame_type = 2 /* same */
        frame_type = 255 /* full_frame */
          offset_delta = 11
          locals = [ class org/scalatest/tools/TestSortingReporter, class java/lang/String, class org/scalatest/events/Event, class scala/runtime/BoxedUnit, int, class org/scalatest/tools/TestSortingReporter, class org/scalatest/events/Event ]
          stack = []
        frame_type = 255 /* full_frame */
          offset_delta = 5
          locals = [ class org/scalatest/tools/TestSortingReporter, class java/lang/String, class org/scalatest/events/Event, top, top, class org/scalatest/tools/TestSortingReporter ]
          stack = [ class java/lang/Throwable ]
        frame_type = 255 /* full_frame */
          offset_delta = 3
          locals = [ class org/scalatest/tools/TestSortingReporter, class java/lang/String, class org/scalatest/events/Event, class scala/runtime/BoxedUnit, int, class org/scalatest/tools/TestSortingReporter, class org/scalatest/events/Event ]
          stack = []
      LineNumberTable:
        line 77: 0
        line 78: 63
        line 79: 68
        line 80: 71
        line 81: 150
        line 82: 163
        line 83: 173
        line 80: 184
        line 85: 187
        line 79: 199
        line 78: 209
      LocalVariableTable:
        Start  Length  Slot  Name   Signature
          163      17     7  slot   Lorg/scalatest/tools/TestSortingReporter$Slot;
            0     210     0  this   Lorg/scalatest/tools/TestSortingReporter;
            0     210     1 testName   Ljava/lang/String;
            0     210     2 event   Lorg/scalatest/events/Event;
    MethodParameters:
      Name                           Flags
      testName                       final
      event                          final

  public void completedTest(java.lang.String);
    descriptor: (Ljava/lang/String;)V
    flags: (0x0001) ACC_PUBLIC
    Code:
      stack=9, locals=11, args_size=2
         0: getstatic     #105                // Field org/scalactic/Requirements$.MODULE$:Lorg/scalactic/Requirements$;
         3: invokevirtual #109                // Method org/scalactic/Requirements$.requirementsHelper:()Lorg/scalactic/Requirements$RequirementsHelper;
         6: iconst_1
         7: anewarray     #111                // class java/lang/String
        10: dup
        11: iconst_0
        12: ldc           #112                // String testName
        14: aastore
        15: checkcast     #114                // class "[Ljava/lang/Object;"
        18: checkcast     #116                // class "[Ljava/lang/String;"
        21: iconst_1
        22: anewarray     #4                  // class java/lang/Object
        25: dup
        26: iconst_0
        27: aload_1
        28: aastore
        29: checkcast     #114                // class "[Ljava/lang/Object;"
        32: getstatic     #121                // Field org/scalactic/Prettifier$.MODULE$:Lorg/scalactic/Prettifier$;
        35: invokevirtual #125                // Method org/scalactic/Prettifier$.default:()Lorg/scalactic/Prettifier;
        38: new           #127                // class org/scalactic/source/Position
        41: dup
        42: ldc           #128                // String TestSortingReporter.scala
        44: ldc           #130                // String Please set the environment variable SCALACTIC_FILL_FILE_PATHNAMES to yes at compile time to enable this feature.
        46: bipush        96
        48: invokespecial #134                // Method org/scalactic/source/Position."<init>":(Ljava/lang/String;Ljava/lang/String;I)V
        51: invokevirtual #138                // Method org/scalactic/Requirements$RequirementsHelper.macroRequireNonNull:([Ljava/lang/String;[Ljava/lang/Object;Lorg/scalactic/Prettifier;Lorg/scalactic/source/Position;)V
        54: aload_0
        55: dup
        56: astore_2
        57: monitorenter
        58: aload_0
        59: invokespecial #140                // Method slotMap:()Lscala/collection/mutable/HashMap;
        62: aload_1
        63: invokevirtual #146                // Method scala/collection/mutable/HashMap.contains:(Ljava/lang/Object;)Z
        66: ifne          103
        69: new           #148                // class java/lang/IllegalArgumentException
        72: dup
        73: new           #150                // class java/lang/StringBuilder
        76: dup
        77: ldc           #231                // int 69
        79: invokespecial #153                // Method java/lang/StringBuilder."<init>":(I)V
        82: ldc           #155                // String The passed testname:
        84: invokevirtual #159                // Method java/lang/StringBuilder.append:(Ljava/lang/String;)Ljava/lang/StringBuilder;
        87: aload_1
        88: invokevirtual #159                // Method java/lang/StringBuilder.append:(Ljava/lang/String;)Ljava/lang/StringBuilder;
        91: ldc           #233                // String , has either never started or already completed.
        93: invokevirtual #159                // Method java/lang/StringBuilder.append:(Ljava/lang/String;)Ljava/lang/StringBuilder;
        96: invokevirtual #165                // Method java/lang/StringBuilder.toString:()Ljava/lang/String;
        99: invokespecial #167                // Method java/lang/IllegalArgumentException."<init>":(Ljava/lang/String;)V
       102: athrow
       103: aload_0
       104: invokespecial #140                // Method slotMap:()Lscala/collection/mutable/HashMap;
       107: aload_1
       108: invokevirtual #213                // Method scala/collection/mutable/HashMap.apply:(Ljava/lang/Object;)Ljava/lang/Object;
       111: checkcast     #19                 // class org/scalatest/tools/TestSortingReporter$Slot
       114: invokevirtual #237                // Method org/scalatest/tools/TestSortingReporter$Slot.ready:()Z
       117: ifeq          154
       120: new           #148                // class java/lang/IllegalArgumentException
       123: dup
       124: new           #150                // class java/lang/StringBuilder
       127: dup
       128: ldc           #238                // int 45
       130: invokespecial #153                // Method java/lang/StringBuilder."<init>":(I)V
       133: ldc           #155                // String The passed testname:
       135: invokevirtual #159                // Method java/lang/StringBuilder.append:(Ljava/lang/String;)Ljava/lang/StringBuilder;
       138: aload_1
       139: invokevirtual #159                // Method java/lang/StringBuilder.append:(Ljava/lang/String;)Ljava/lang/StringBuilder;
       142: ldc           #240                // String , has already completed.
       144: invokevirtual #159                // Method java/lang/StringBuilder.append:(Ljava/lang/String;)Ljava/lang/StringBuilder;
       147: invokevirtual #165                // Method java/lang/StringBuilder.toString:()Ljava/lang/String;
       150: invokespecial #167                // Method java/lang/IllegalArgumentException."<init>":(Ljava/lang/String;)V
       153: athrow
       154: aload_0
       155: invokespecial #140                // Method slotMap:()Lscala/collection/mutable/HashMap;
       158: aload_1
       159: invokevirtual #213                // Method scala/collection/mutable/HashMap.apply:(Ljava/lang/Object;)Ljava/lang/Object;
       162: checkcast     #19                 // class org/scalatest/tools/TestSortingReporter$Slot
       165: astore_3
       166: iconst_1
       167: istore        5
       169: aload_3
       170: invokevirtual #243                // Method org/scalatest/tools/TestSortingReporter$Slot.completedEvent:()Z
       173: istore        6
       175: aload_3
       176: invokevirtual #246                // Method org/scalatest/tools/TestSortingReporter$Slot.copy$default$1:()Ljava/util/UUID;
       179: astore        7
       181: aload_3
       182: invokevirtual #249                // Method org/scalatest/tools/TestSortingReporter$Slot.copy$default$2:()Lscala/collection/mutable/ListBuffer;
       185: astore        8
       187: aload_3
       188: invokevirtual #252                // Method org/scalatest/tools/TestSortingReporter$Slot.copy$default$4:()Z
       191: istore        9
       193: aload_3
       194: aload         7
       196: aload         8
       198: iconst_1
       199: iload         9
       201: iload         6
       203: invokevirtual #256                // Method org/scalatest/tools/TestSortingReporter$Slot.copy:(Ljava/util/UUID;Lscala/collection/mutable/ListBuffer;ZZZ)Lorg/scalatest/tools/TestSortingReporter$Slot;
       206: astore        4
       208: aload_0
       209: invokespecial #186                // Method waitingBuffer:()Lscala/collection/mutable/ListBuffer;
       212: aload_3
       213: invokevirtual #260                // Method scala/collection/mutable/ListBuffer.indexOf:(Ljava/lang/Object;)I
       216: istore        10
       218: iload         10
       220: iconst_0
       221: if_icmplt     238
       224: aload_0
       225: invokespecial #186                // Method waitingBuffer:()Lscala/collection/mutable/ListBuffer;
       228: iload         10
       230: aload         4
       232: invokevirtual #264                // Method scala/collection/mutable/ListBuffer.update:(ILjava/lang/Object;)V
       235: goto          238
       238: aload_0
       239: invokespecial #140                // Method slotMap:()Lscala/collection/mutable/HashMap;
       242: aload_1
       243: aload         4
       245: invokevirtual #184                // Method scala/collection/mutable/HashMap.put:(Ljava/lang/Object;Ljava/lang/Object;)Lscala/Option;
       248: pop
       249: aload_0
       250: aload_0
       251: invokespecial #266                // Method completedTestCount:()I
       254: iconst_1
       255: iadd
       256: invokespecial #268                // Method completedTestCount_$eq:(I)V
       259: aload_0
       260: invokespecial #219                // Method fireReadyEvents:()V
       263: aload_0
       264: invokespecial #271                // Method checkCompletedTests:()V
       267: aload_2
       268: monitorexit
       269: goto          275
       272: aload_2
       273: monitorexit
       274: athrow
       275: return
      Exception table:
         from    to  target type
            58   267   272   any
      StackMapTable: number_of_entries = 5
        frame_type = 252 /* append */
          offset_delta = 103
          locals = [ class org/scalatest/tools/TestSortingReporter ]
        frame_type = 50 /* same */
        frame_type = 255 /* full_frame */
          offset_delta = 83
          locals = [ class org/scalatest/tools/TestSortingReporter, class java/lang/String, class org/scalatest/tools/TestSortingReporter, class org/scalatest/tools/TestSortingReporter$Slot, class org/scalatest/tools/TestSortingReporter$Slot, int, int, class java/util/UUID, class scala/collection/mutable/ListBuffer, int, int ]
          stack = []
        frame_type = 255 /* full_frame */
          offset_delta = 33
          locals = [ class org/scalatest/tools/TestSortingReporter, class java/lang/String, class org/scalatest/tools/TestSortingReporter ]
          stack = [ class java/lang/Throwable ]
        frame_type = 255 /* full_frame */
          offset_delta = 2
          locals = [ class org/scalatest/tools/TestSortingReporter, class java/lang/String, class org/scalatest/tools/TestSortingReporter, class org/scalatest/tools/TestSortingReporter$Slot, class org/scalatest/tools/TestSortingReporter$Slot, int, int, class java/util/UUID, class scala/collection/mutable/ListBuffer, int, int ]
          stack = []
      LineNumberTable:
        line 96: 0
        line 97: 54
        line 98: 58
        line 99: 69
        line 100: 103
        line 101: 120
        line 102: 154
        line 103: 166
        line 104: 208
        line 105: 218
        line 106: 224
        line 107: 238
        line 108: 249
        line 109: 259
        line 111: 263
        line 97: 275
      LocalVariableTable:
        Start  Length  Slot  Name   Signature
          169      37     5   x$1   Z
          175      31     6   x$2   Z
          181      25     7   x$3   Ljava/util/UUID;
          187      19     8   x$4   Lscala/collection/mutable/ListBuffer;
          193      13     9   x$5   Z
          166     101     3  slot   Lorg/scalatest/tools/TestSortingReporter$Slot;
          208      59     4 newSlot   Lorg/scalatest/tools/TestSortingReporter$Slot;
          218      49    10 slotIdx   I
            0     276     0  this   Lorg/scalatest/tools/TestSortingReporter;
            0     276     1 testName   Ljava/lang/String;
    MethodParameters:
      Name                           Flags
      testName                       final

  private void checkCompletedTests();
    descriptor: ()V
    flags: (0x0002) ACC_PRIVATE
    Code:
      stack=3, locals=5, args_size=1
         0: aload_0
         1: invokespecial #266                // Method completedTestCount:()I
         4: aload_0
         5: getfield      #281                // Field testCount:I
         8: if_icmpne     90
        11: aload_0
        12: getfield      #283                // Field suiteSorter:Lscala/Option;
        15: astore_2
        16: aload_2
        17: instanceof    #285                // class scala/Some
        20: ifeq          55
        23: aload_2
        24: checkcast     #285                // class scala/Some
        27: astore_3
        28: aload_3
        29: invokevirtual #289                // Method scala/Some.value:()Ljava/lang/Object;
        32: checkcast     #291                // class org/scalatest/DistributedSuiteSorter
        35: astore        4
        37: aload         4
        39: aload_0
        40: getfield      #293                // Field suiteId:Ljava/lang/String;
        43: invokeinterface #296,  2          // InterfaceMethod org/scalatest/DistributedSuiteSorter.completedTests:(Ljava/lang/String;)V
        48: getstatic     #225                // Field scala/runtime/BoxedUnit.UNIT:Lscala/runtime/BoxedUnit;
        51: astore_1
        52: goto          87
        55: goto          58
        58: getstatic     #301                // Field scala/None$.MODULE$:Lscala/None$;
        61: aload_2
        62: invokevirtual #304                // Method java/lang/Object.equals:(Ljava/lang/Object;)Z
        65: ifeq          75
        68: getstatic     #225                // Field scala/runtime/BoxedUnit.UNIT:Lscala/runtime/BoxedUnit;
        71: astore_1
        72: goto          87
        75: goto          78
        78: new           #306                // class scala/MatchError
        81: dup
        82: aload_2
        83: invokespecial #309                // Method scala/MatchError."<init>":(Ljava/lang/Object;)V
        86: athrow
        87: goto          90
        90: return
      StackMapTable: number_of_entries = 6
        frame_type = 253 /* append */
          offset_delta = 55
          locals = [ top, class scala/Option ]
        frame_type = 2 /* same */
        frame_type = 16 /* same */
        frame_type = 2 /* same */
        frame_type = 255 /* full_frame */
          offset_delta = 8
          locals = [ class org/scalatest/tools/TestSortingReporter, class scala/runtime/BoxedUnit, class scala/Option ]
          stack = []
        frame_type = 249 /* chop */
          offset_delta = 2
      LineNumberTable:
        line 116: 0
        line 117: 11
        line 118: 16
        line 119: 37
        line 118: 55
        line 120: 58
        line 117: 78
        line 116: 90
      LocalVariableTable:
        Start  Length  Slot  Name   Signature
           37      18     4 suiteSorter   Lorg/scalatest/DistributedSuiteSorter;
            0      91     0  this   Lorg/scalatest/tools/TestSortingReporter;

  public synchronized void doApply(org.scalatest.events.Event);
    descriptor: (Lorg/scalatest/events/Event;)V
    flags: (0x0021) ACC_PUBLIC, ACC_SYNCHRONIZED
    Code:
      stack=3, locals=27, args_size=2
         0: aload_1
         1: astore        5
         3: aload         5
         5: instanceof    #315                // class org/scalatest/events/TestStarting
         8: ifeq          158
        11: aload         5
        13: checkcast     #315                // class org/scalatest/events/TestStarting
        16: astore        6
        18: aload_0
        19: invokespecial #140                // Method slotMap:()Lscala/collection/mutable/HashMap;
        22: aload         6
        24: invokevirtual #317                // Method org/scalatest/events/TestStarting.testName:()Ljava/lang/String;
        27: invokevirtual #321                // Method scala/collection/mutable/HashMap.get:(Ljava/lang/Object;)Lscala/Option;
        30: astore        7
        32: aload         7
        34: instanceof    #285                // class scala/Some
        37: ifeq          106
        40: aload         7
        42: checkcast     #285                // class scala/Some
        45: astore        8
        47: aload         8
        49: invokevirtual #289                // Method scala/Some.value:()Ljava/lang/Object;
        52: checkcast     #19                 // class org/scalatest/tools/TestSortingReporter$Slot
        55: astore        9
        57: aload_0
        58: invokespecial #186                // Method waitingBuffer:()Lscala/collection/mutable/ListBuffer;
        61: aload         9
        63: invokevirtual #260                // Method scala/collection/mutable/ListBuffer.indexOf:(Ljava/lang/Object;)I
        66: istore        10
        68: iload         10
        70: iconst_0
        71: if_icmplt     87
        74: aload         9
        76: invokevirtual #216                // Method org/scalatest/tools/TestSortingReporter$Slot.eventList:()Lscala/collection/mutable/ListBuffer;
        79: aload         6
        81: invokevirtual #190                // Method scala/collection/mutable/ListBuffer.$plus$eq:(Ljava/lang/Object;)Lscala/collection/mutable/Growable;
        84: goto          101
        87: aload_0
        88: getfield      #323                // Field dispatch:Lorg/scalatest/Reporter;
        91: aload         6
        93: invokeinterface #326,  2          // InterfaceMethod org/scalatest/Reporter.apply:(Lorg/scalatest/events/Event;)V
        98: getstatic     #225                // Field scala/runtime/BoxedUnit.UNIT:Lscala/runtime/BoxedUnit;
       101: astore        4
       103: goto          152
       106: goto          109
       109: getstatic     #301                // Field scala/None$.MODULE$:Lscala/None$;
       112: aload         7
       114: invokevirtual #304                // Method java/lang/Object.equals:(Ljava/lang/Object;)Z
       117: ifeq          139
       120: aload_0
       121: getfield      #323                // Field dispatch:Lorg/scalatest/Reporter;
       124: aload         6
       126: invokeinterface #326,  2          // InterfaceMethod org/scalatest/Reporter.apply:(Lorg/scalatest/events/Event;)V
       131: getstatic     #225                // Field scala/runtime/BoxedUnit.UNIT:Lscala/runtime/BoxedUnit;
       134: astore        4
       136: goto          152
       139: goto          142
       142: new           #306                // class scala/MatchError
       145: dup
       146: aload         7
       148: invokespecial #309                // Method scala/MatchError."<init>":(Ljava/lang/Object;)V
       151: athrow
       152: aload         4
       154: astore_2
       155: goto          694
       158: goto          161
       161: aload         5
       163: instanceof    #328                // class org/scalatest/events/TestIgnored
       166: ifeq          313
       169: aload         5
       171: checkcast     #328                // class org/scalatest/events/TestIgnored
       174: astore        11
       176: aload_0
       177: invokespecial #140                // Method slotMap:()Lscala/collection/mutable/HashMap;
       180: aload         11
       182: invokevirtual #329                // Method org/scalatest/events/TestIgnored.testName:()Ljava/lang/String;
       185: invokevirtual #321                // Method scala/collection/mutable/HashMap.get:(Ljava/lang/Object;)Lscala/Option;
       188: astore        12
       190: aload         12
       192: instanceof    #285                // class scala/Some
       195: ifeq          263
       198: aload         12
       200: checkcast     #285                // class scala/Some
       203: astore        13
       205: aload         13
       207: invokevirtual #289                // Method scala/Some.value:()Ljava/lang/Object;
       210: checkcast     #19                 // class org/scalatest/tools/TestSortingReporter$Slot
       213: astore        14
       215: aload_0
       216: invokespecial #186                // Method waitingBuffer:()Lscala/collection/mutable/ListBuffer;
       219: aload         14
       221: invokevirtual #260                // Method scala/collection/mutable/ListBuffer.indexOf:(Ljava/lang/Object;)I
       224: istore        15
       226: iload         15
       228: iconst_0
       229: if_icmplt     245
       232: aload         14
       234: invokevirtual #216                // Method org/scalatest/tools/TestSortingReporter$Slot.eventList:()Lscala/collection/mutable/ListBuffer;
       237: aload         11
       239: invokevirtual #190                // Method scala/collection/mutable/ListBuffer.$plus$eq:(Ljava/lang/Object;)Lscala/collection/mutable/Growable;
       242: goto          259
       245: aload_0
       246: getfield      #323                // Field dispatch:Lorg/scalatest/Reporter;
       249: aload         11
       251: invokeinterface #326,  2          // InterfaceMethod org/scalatest/Reporter.apply:(Lorg/scalatest/events/Event;)V
       256: getstatic     #225                // Field scala/runtime/BoxedUnit.UNIT:Lscala/runtime/BoxedUnit;
       259: astore_3
       260: goto          308
       263: goto          266
       266: getstatic     #301                // Field scala/None$.MODULE$:Lscala/None$;
       269: aload         12
       271: invokevirtual #304                // Method java/lang/Object.equals:(Ljava/lang/Object;)Z
       274: ifeq          295
       277: aload_0
       278: getfield      #323                // Field dispatch:Lorg/scalatest/Reporter;
       281: aload         11
       283: invokeinterface #326,  2          // InterfaceMethod org/scalatest/Reporter.apply:(Lorg/scalatest/events/Event;)V
       288: getstatic     #225                // Field scala/runtime/BoxedUnit.UNIT:Lscala/runtime/BoxedUnit;
       291: astore_3
       292: goto          308
       295: goto          298
       298: new           #306                // class scala/MatchError
       301: dup
       302: aload         12
       304: invokespecial #309                // Method scala/MatchError."<init>":(Ljava/lang/Object;)V
       307: athrow
       308: aload_3
       309: astore_2
       310: goto          694
       313: goto          316
       316: aload         5
       318: instanceof    #331                // class org/scalatest/events/TestSucceeded
       321: ifeq          349
       324: aload         5
       326: checkcast     #331                // class org/scalatest/events/TestSucceeded
       329: astore        16
       331: aload_0
       332: aload         16
       334: aload         16
       336: invokevirtual #332                // Method org/scalatest/events/TestSucceeded.testName:()Ljava/lang/String;
       339: invokespecial #336                // Method handleTestCompleted:(Lorg/scalatest/events/Event;Ljava/lang/String;)V
       342: getstatic     #225                // Field scala/runtime/BoxedUnit.UNIT:Lscala/runtime/BoxedUnit;
       345: astore_2
       346: goto          694
       349: goto          352
       352: aload         5
       354: instanceof    #338                // class org/scalatest/events/TestFailed
       357: ifeq          385
       360: aload         5
       362: checkcast     #338                // class org/scalatest/events/TestFailed
       365: astore        17
       367: aload_0
       368: aload         17
       370: aload         17
       372: invokevirtual #339                // Method org/scalatest/events/TestFailed.testName:()Ljava/lang/String;
       375: invokespecial #336                // Method handleTestCompleted:(Lorg/scalatest/events/Event;Ljava/lang/String;)V
       378: getstatic     #225                // Field scala/runtime/BoxedUnit.UNIT:Lscala/runtime/BoxedUnit;
       381: astore_2
       382: goto          694
       385: goto          388
       388: aload         5
       390: instanceof    #341                // class org/scalatest/events/TestPending
       393: ifeq          421
       396: aload         5
       398: checkcast     #341                // class org/scalatest/events/TestPending
       401: astore        18
       403: aload_0
       404: aload         18
       406: aload         18
       408: invokevirtual #342                // Method org/scalatest/events/TestPending.testName:()Ljava/lang/String;
       411: invokespecial #336                // Method handleTestCompleted:(Lorg/scalatest/events/Event;Ljava/lang/String;)V
       414: getstatic     #225                // Field scala/runtime/BoxedUnit.UNIT:Lscala/runtime/BoxedUnit;
       417: astore_2
       418: goto          694
       421: goto          424
       424: aload         5
       426: instanceof    #344                // class org/scalatest/events/TestCanceled
       429: ifeq          457
       432: aload         5
       434: checkcast     #344                // class org/scalatest/events/TestCanceled
       437: astore        19
       439: aload_0
       440: aload         19
       442: aload         19
       444: invokevirtual #345                // Method org/scalatest/events/TestCanceled.testName:()Ljava/lang/String;
       447: invokespecial #336                // Method handleTestCompleted:(Lorg/scalatest/events/Event;Ljava/lang/String;)V
       450: getstatic     #225                // Field scala/runtime/BoxedUnit.UNIT:Lscala/runtime/BoxedUnit;
       453: astore_2
       454: goto          694
       457: goto          460
       460: aload         5
       462: instanceof    #347                // class org/scalatest/events/ScopeOpened
       465: ifeq          488
       468: aload         5
       470: checkcast     #347                // class org/scalatest/events/ScopeOpened
       473: astore        20
       475: aload_0
       476: aload         20
       478: invokespecial #350                // Method handleSuiteEvent:(Lorg/scalatest/events/Event;)V
       481: getstatic     #225                // Field scala/runtime/BoxedUnit.UNIT:Lscala/runtime/BoxedUnit;
       484: astore_2
       485: goto          694
       488: goto          491
       491: aload         5
       493: instanceof    #352                // class org/scalatest/events/ScopeClosed
       496: ifeq          519
       499: aload         5
       501: checkcast     #352                // class org/scalatest/events/ScopeClosed
       504: astore        21
       506: aload_0
       507: aload         21
       509: invokespecial #350                // Method handleSuiteEvent:(Lorg/scalatest/events/Event;)V
       512: getstatic     #225                // Field scala/runtime/BoxedUnit.UNIT:Lscala/runtime/BoxedUnit;
       515: astore_2
       516: goto          694
       519: goto          522
       522: aload         5
       524: instanceof    #354                // class org/scalatest/events/ScopePending
       527: ifeq          550
       530: aload         5
       532: checkcast     #354                // class org/scalatest/events/ScopePending
       535: astore        22
       537: aload_0
       538: aload         22
       540: invokespecial #350                // Method handleSuiteEvent:(Lorg/scalatest/events/Event;)V
       543: getstatic     #225                // Field scala/runtime/BoxedUnit.UNIT:Lscala/runtime/BoxedUnit;
       546: astore_2
       547: goto          694
       550: goto          553
       553: aload         5
       555: instanceof    #204                // class org/scalatest/events/InfoProvided
       558: ifeq          581
       561: aload         5
       563: checkcast     #204                // class org/scalatest/events/InfoProvided
       566: astore        23
       568: aload_0
       569: aload         23
       571: invokespecial #350                // Method handleSuiteEvent:(Lorg/scalatest/events/Event;)V
       574: getstatic     #225                // Field scala/runtime/BoxedUnit.UNIT:Lscala/runtime/BoxedUnit;
       577: astore_2
       578: goto          694
       581: goto          584
       584: aload         5
       586: instanceof    #208                // class org/scalatest/events/AlertProvided
       589: ifeq          612
       592: aload         5
       594: checkcast     #208                // class org/scalatest/events/AlertProvided
       597: astore        24
       599: aload_0
       600: aload         24
       602: invokespecial #350                // Method handleSuiteEvent:(Lorg/scalatest/events/Event;)V
       605: getstatic     #225                // Field scala/runtime/BoxedUnit.UNIT:Lscala/runtime/BoxedUnit;
       608: astore_2
       609: goto          694
       612: goto          615
       615: aload         5
       617: instanceof    #210                // class org/scalatest/events/NoteProvided
       620: ifeq          643
       623: aload         5
       625: checkcast     #210                // class org/scalatest/events/NoteProvided
       628: astore        25
       630: aload_0
       631: aload         25
       633: invokespecial #350                // Method handleSuiteEvent:(Lorg/scalatest/events/Event;)V
       636: getstatic     #225                // Field scala/runtime/BoxedUnit.UNIT:Lscala/runtime/BoxedUnit;
       639: astore_2
       640: goto          694
       643: goto          646
       646: aload         5
       648: instanceof    #206                // class org/scalatest/events/MarkupProvided
       651: ifeq          674
       654: aload         5
       656: checkcast     #206                // class org/scalatest/events/MarkupProvided
       659: astore        26
       661: aload_0
       662: aload         26
       664: invokespecial #350                // Method handleSuiteEvent:(Lorg/scalatest/events/Event;)V
       667: getstatic     #225                // Field scala/runtime/BoxedUnit.UNIT:Lscala/runtime/BoxedUnit;
       670: astore_2
       671: goto          694
       674: goto          677
       677: aload_0
       678: getfield      #323                // Field dispatch:Lorg/scalatest/Reporter;
       681: aload_1
       682: invokeinterface #326,  2          // InterfaceMethod org/scalatest/Reporter.apply:(Lorg/scalatest/events/Event;)V
       687: getstatic     #225                // Field scala/runtime/BoxedUnit.UNIT:Lscala/runtime/BoxedUnit;
       690: astore_2
       691: goto          694
       694: aload_2
       695: pop
       696: aload_0
       697: invokespecial #219                // Method fireReadyEvents:()V
       700: return
      StackMapTable: number_of_entries = 41
        frame_type = 255 /* full_frame */
          offset_delta = 87
          locals = [ class org/scalatest/tools/TestSortingReporter, class org/scalatest/events/Event, top, top, top, class org/scalatest/events/Event, class org/scalatest/events/TestStarting, class scala/Option, class scala/Some, class org/scalatest/tools/TestSortingReporter$Slot, int ]
          stack = []
        frame_type = 77 /* same_locals_1_stack_item */
          stack = [ class java/lang/Object ]
        frame_type = 248 /* chop */
          offset_delta = 4
        frame_type = 2 /* same */
        frame_type = 29 /* same */
        frame_type = 2 /* same */
        frame_type = 255 /* full_frame */
          offset_delta = 9
          locals = [ class org/scalatest/tools/TestSortingReporter, class org/scalatest/events/Event, top, top, class java/lang/Object, class org/scalatest/events/Event, class org/scalatest/events/TestStarting, class scala/Option ]
          stack = []
        frame_type = 255 /* full_frame */
          offset_delta = 5
          locals = [ class org/scalatest/tools/TestSortingReporter, class org/scalatest/events/Event, top, top, top, class org/scalatest/events/Event ]
          stack = []
        frame_type = 2 /* same */
        frame_type = 255 /* full_frame */
          offset_delta = 83
          locals = [ class org/scalatest/tools/TestSortingReporter, class org/scalatest/events/Event, top, top, top, class org/scalatest/events/Event, top, top, top, top, top, class org/scalatest/events/TestIgnored, class scala/Option, class scala/Some, class org/scalatest/tools/TestSortingReporter$Slot, int ]
          stack = []
        frame_type = 77 /* same_locals_1_stack_item */
          stack = [ class java/lang/Object ]
        frame_type = 248 /* chop */
          offset_delta = 3
        frame_type = 2 /* same */
        frame_type = 28 /* same */
        frame_type = 2 /* same */
        frame_type = 255 /* full_frame */
          offset_delta = 9
          locals = [ class org/scalatest/tools/TestSortingReporter, class org/scalatest/events/Event, top, class java/lang/Object, top, class org/scalatest/events/Event, top, top, top, top, top, class org/scalatest/events/TestIgnored, class scala/Option ]
          stack = []
        frame_type = 255 /* full_frame */
          offset_delta = 4
          locals = [ class org/scalatest/tools/TestSortingReporter, class org/scalatest/events/Event, top, top, top, class org/scalatest/events/Event ]
          stack = []
        frame_type = 2 /* same */
        frame_type = 32 /* same */
        frame_type = 2 /* same */
        frame_type = 32 /* same */
        frame_type = 2 /* same */
        frame_type = 32 /* same */
        frame_type = 2 /* same */
        frame_type = 32 /* same */
        frame_type = 2 /* same */
        frame_type = 27 /* same */
        frame_type = 2 /* same */
        frame_type = 27 /* same */
        frame_type = 2 /* same */
        frame_type = 27 /* same */
        frame_type = 2 /* same */
        frame_type = 27 /* same */
        frame_type = 2 /* same */
        frame_type = 27 /* same */
        frame_type = 2 /* same */
        frame_type = 27 /* same */
        frame_type = 2 /* same */
        frame_type = 27 /* same */
        frame_type = 2 /* same */
        frame_type = 255 /* full_frame */
          offset_delta = 16
          locals = [ class org/scalatest/tools/TestSortingReporter, class org/scalatest/events/Event, class java/lang/Object, top, top, class org/scalatest/events/Event ]
          stack = []
      LineNumberTable:
        line 127: 0
        line 128: 3
        line 129: 18
        line 130: 32
        line 131: 57
        line 132: 68
        line 133: 74
        line 135: 87
        line 130: 106
        line 136: 109
        line 137: 120
        line 136: 139
        line 129: 142
        line 128: 158
        line 139: 161
        line 140: 176
        line 141: 190
        line 142: 215
        line 143: 226
        line 144: 232
        line 146: 245
        line 141: 263
        line 147: 266
        line 148: 277
        line 147: 295
        line 140: 298
        line 139: 313
        line 152: 316
        line 153: 331
        line 152: 349
        line 154: 352
        line 155: 367
        line 154: 385
        line 156: 388
        line 157: 403
        line 156: 421
        line 158: 424
        line 159: 439
        line 158: 457
        line 162: 460
        line 163: 475
        line 162: 488
        line 164: 491
        line 165: 506
        line 164: 519
        line 166: 522
        line 167: 537
        line 166: 550
        line 168: 553
        line 169: 568
        line 168: 581
        line 170: 584
        line 171: 599
        line 170: 612
        line 172: 615
        line 173: 630
        line 172: 643
        line 174: 646
        line 175: 661
        line 174: 674
        line 179: 677
        line 127: 694
        line 181: 696
      LocalVariableTable:
        Start  Length  Slot  Name   Signature
           68      33    10 slotIdx   I
           57      49     9  slot   Lorg/scalatest/tools/TestSortingReporter$Slot;
          226      33    15 slotIdx   I
          215      48    14  slot   Lorg/scalatest/tools/TestSortingReporter$Slot;
            0     701     0  this   Lorg/scalatest/tools/TestSortingReporter;
            0     701     1 event   Lorg/scalatest/events/Event;
    MethodParameters:
      Name                           Flags
      event                          final

  private void handleSuiteEvent(org.scalatest.events.Event);
    descriptor: (Lorg/scalatest/events/Event;)V
    flags: (0x0002) ACC_PRIVATE
    Code:
      stack=8, locals=4, args_size=2
         0: new           #175                // class scala/collection/mutable/ListBuffer
         3: dup
         4: invokespecial #177                // Method scala/collection/mutable/ListBuffer."<init>":()V
         7: astore_2
         8: aload_2
         9: aload_1
        10: invokevirtual #190                // Method scala/collection/mutable/ListBuffer.$plus$eq:(Ljava/lang/Object;)Lscala/collection/mutable/Growable;
        13: pop
        14: new           #19                 // class org/scalatest/tools/TestSortingReporter$Slot
        17: dup
        18: aload_0
        19: invokestatic  #173                // Method java/util/UUID.randomUUID:()Ljava/util/UUID;
        22: aload_2
        23: iconst_1
        24: iconst_1
        25: iconst_1
        26: invokespecial #180                // Method org/scalatest/tools/TestSortingReporter$Slot."<init>":(Lorg/scalatest/tools/TestSortingReporter;Ljava/util/UUID;Lscala/collection/mutable/ListBuffer;ZZZ)V
        29: astore_3
        30: aload_0
        31: invokespecial #186                // Method waitingBuffer:()Lscala/collection/mutable/ListBuffer;
        34: aload_3
        35: invokevirtual #190                // Method scala/collection/mutable/ListBuffer.$plus$eq:(Ljava/lang/Object;)Lscala/collection/mutable/Growable;
        38: pop
        39: return
      LineNumberTable:
        line 188: 0
        line 189: 8
        line 190: 14
        line 191: 30
      LocalVariableTable:
        Start  Length  Slot  Name   Signature
            8      31     2 listBuffer   Lscala/collection/mutable/ListBuffer;
           30       9     3  slot   Lorg/scalatest/tools/TestSortingReporter$Slot;
            0      40     0  this   Lorg/scalatest/tools/TestSortingReporter;
            0      40     1 event   Lorg/scalatest/events/Event;
    MethodParameters:
      Name                           Flags
      event                          final

  private void handleTestCompleted(org.scalatest.events.Event, java.lang.String);
    descriptor: (Lorg/scalatest/events/Event;Ljava/lang/String;)V
    flags: (0x0002) ACC_PRIVATE
    Code:
      stack=6, locals=14, args_size=3
         0: aload_0
         1: invokespecial #140                // Method slotMap:()Lscala/collection/mutable/HashMap;
         4: aload_2
         5: invokevirtual #321                // Method scala/collection/mutable/HashMap.get:(Ljava/lang/Object;)Lscala/Option;
         8: astore        4
        10: aload         4
        12: instanceof    #285                // class scala/Some
        15: ifeq          151
        18: aload         4
        20: checkcast     #285                // class scala/Some
        23: astore        5
        25: aload         5
        27: invokevirtual #289                // Method scala/Some.value:()Ljava/lang/Object;
        30: checkcast     #19                 // class org/scalatest/tools/TestSortingReporter$Slot
        33: astore        6
        35: aload_0
        36: invokespecial #186                // Method waitingBuffer:()Lscala/collection/mutable/ListBuffer;
        39: aload         6
        41: invokevirtual #260                // Method scala/collection/mutable/ListBuffer.indexOf:(Ljava/lang/Object;)I
        44: istore        7
        46: iload         7
        48: iconst_0
        49: if_icmplt     134
        52: aload         6
        54: invokevirtual #216                // Method org/scalatest/tools/TestSortingReporter$Slot.eventList:()Lscala/collection/mutable/ListBuffer;
        57: aload_1
        58: invokevirtual #358                // Method scala/collection/mutable/ListBuffer.$colon$plus:(Ljava/lang/Object;)Ljava/lang/Object;
        61: checkcast     #175                // class scala/collection/mutable/ListBuffer
        64: astore        9
        66: iconst_1
        67: istore        10
        69: aload         6
        71: invokevirtual #361                // Method org/scalatest/tools/TestSortingReporter$Slot.completed:()Z
        74: istore        11
        76: aload         6
        78: invokevirtual #246                // Method org/scalatest/tools/TestSortingReporter$Slot.copy$default$1:()Ljava/util/UUID;
        81: astore        12
        83: aload         6
        85: invokevirtual #364                // Method org/scalatest/tools/TestSortingReporter$Slot.copy$default$3:()Z
        88: istore        13
        90: aload         6
        92: aload         12
        94: aload         9
        96: iload         13
        98: iconst_1
        99: iload         11
       101: invokevirtual #256                // Method org/scalatest/tools/TestSortingReporter$Slot.copy:(Ljava/util/UUID;Lscala/collection/mutable/ListBuffer;ZZZ)Lorg/scalatest/tools/TestSortingReporter$Slot;
       104: astore        8
       106: aload_0
       107: invokespecial #186                // Method waitingBuffer:()Lscala/collection/mutable/ListBuffer;
       110: iload         7
       112: aload         8
       114: invokevirtual #264                // Method scala/collection/mutable/ListBuffer.update:(ILjava/lang/Object;)V
       117: aload_0
       118: invokespecial #140                // Method slotMap:()Lscala/collection/mutable/HashMap;
       121: aload_2
       122: aload         8
       124: invokevirtual #184                // Method scala/collection/mutable/HashMap.put:(Ljava/lang/Object;Ljava/lang/Object;)Lscala/Option;
       127: pop
       128: getstatic     #225                // Field scala/runtime/BoxedUnit.UNIT:Lscala/runtime/BoxedUnit;
       131: goto          147
       134: aload_0
       135: getfield      #323                // Field dispatch:Lorg/scalatest/Reporter;
       138: aload_1
       139: invokeinterface #326,  2          // InterfaceMethod org/scalatest/Reporter.apply:(Lorg/scalatest/events/Event;)V
       144: getstatic     #225                // Field scala/runtime/BoxedUnit.UNIT:Lscala/runtime/BoxedUnit;
       147: astore_3
       148: goto          195
       151: goto          154
       154: getstatic     #301                // Field scala/None$.MODULE$:Lscala/None$;
       157: aload         4
       159: invokevirtual #304                // Method java/lang/Object.equals:(Ljava/lang/Object;)Z
       162: ifeq          182
       165: aload_0
       166: getfield      #323                // Field dispatch:Lorg/scalatest/Reporter;
       169: aload_1
       170: invokeinterface #326,  2          // InterfaceMethod org/scalatest/Reporter.apply:(Lorg/scalatest/events/Event;)V
       175: getstatic     #225                // Field scala/runtime/BoxedUnit.UNIT:Lscala/runtime/BoxedUnit;
       178: astore_3
       179: goto          195
       182: goto          185
       185: new           #306                // class scala/MatchError
       188: dup
       189: aload         4
       191: invokespecial #309                // Method scala/MatchError."<init>":(Ljava/lang/Object;)V
       194: athrow
       195: return
      StackMapTable: number_of_entries = 7
        frame_type = 255 /* full_frame */
          offset_delta = 134
          locals = [ class org/scalatest/tools/TestSortingReporter, class org/scalatest/events/Event, class java/lang/String, top, class scala/Option, class scala/Some, class org/scalatest/tools/TestSortingReporter$Slot, int ]
          stack = []
        frame_type = 76 /* same_locals_1_stack_item */
          stack = [ class scala/runtime/BoxedUnit ]
        frame_type = 248 /* chop */
          offset_delta = 3
        frame_type = 2 /* same */
        frame_type = 27 /* same */
        frame_type = 2 /* same */
        frame_type = 255 /* full_frame */
          offset_delta = 9
          locals = [ class org/scalatest/tools/TestSortingReporter, class org/scalatest/events/Event, class java/lang/String, class scala/runtime/BoxedUnit, class scala/Option ]
          stack = []
      LineNumberTable:
        line 199: 0
        line 200: 10
        line 201: 35
        line 202: 46
        line 203: 52
        line 204: 106
        line 205: 117
        line 208: 134
        line 200: 151
        line 209: 154
        line 210: 165
        line 209: 182
        line 199: 185
      LocalVariableTable:
        Start  Length  Slot  Name   Signature
           66      38     9   x$1   Lscala/collection/mutable/ListBuffer;
           69      35    10   x$2   Z
           76      28    11   x$3   Z
           83      21    12   x$4   Ljava/util/UUID;
           90      14    13   x$5   Z
          106      25     8 newSlot   Lorg/scalatest/tools/TestSortingReporter$Slot;
           46     101     7 slotIdx   I
           35     116     6  slot   Lorg/scalatest/tools/TestSortingReporter$Slot;
            0     196     0  this   Lorg/scalatest/tools/TestSortingReporter;
            0     196     1 event   Lorg/scalatest/events/Event;
            0     196     2 testName   Ljava/lang/String;
    MethodParameters:
      Name                           Flags
      event                          final
      testName                       final

  private void fireSlotEvents(org.scalatest.tools.TestSortingReporter$Slot);
    descriptor: (Lorg/scalatest/tools/TestSortingReporter$Slot;)V
    flags: (0x0002) ACC_PRIVATE
    Code:
      stack=2, locals=5, args_size=2
         0: aload_1
         1: invokevirtual #216                // Method org/scalatest/tools/TestSortingReporter$Slot.eventList:()Lscala/collection/mutable/ListBuffer;
         4: invokevirtual #369                // Method scala/collection/mutable/ListBuffer.length:()I
         7: iconst_1
         8: if_icmple     46
        11: aload_1
        12: invokevirtual #216                // Method org/scalatest/tools/TestSortingReporter$Slot.eventList:()Lscala/collection/mutable/ListBuffer;
        15: invokevirtual #372                // Method scala/collection/mutable/ListBuffer.head:()Ljava/lang/Object;
        18: checkcast     #229                // class org/scalatest/events/Event
        21: astore_3
        22: aload_1
        23: invokevirtual #216                // Method org/scalatest/tools/TestSortingReporter$Slot.eventList:()Lscala/collection/mutable/ListBuffer;
        26: iconst_0
        27: invokevirtual #376                // Method scala/collection/mutable/ListBuffer.remove:(I)Ljava/lang/Object;
        30: pop
        31: aload_0
        32: getfield      #323                // Field dispatch:Lorg/scalatest/Reporter;
        35: aload_3
        36: invokeinterface #326,  2          // InterfaceMethod org/scalatest/Reporter.apply:(Lorg/scalatest/events/Event;)V
        41: aload_1
        42: astore_1
        43: goto          0
        46: aload_1
        47: invokevirtual #216                // Method org/scalatest/tools/TestSortingReporter$Slot.eventList:()Lscala/collection/mutable/ListBuffer;
        50: invokevirtual #369                // Method scala/collection/mutable/ListBuffer.length:()I
        53: iconst_1
        54: if_icmpne     95
        57: aload_1
        58: invokevirtual #216                // Method org/scalatest/tools/TestSortingReporter$Slot.eventList:()Lscala/collection/mutable/ListBuffer;
        61: invokevirtual #372                // Method scala/collection/mutable/ListBuffer.head:()Ljava/lang/Object;
        64: checkcast     #229                // class org/scalatest/events/Event
        67: astore        4
        69: aload_1
        70: invokevirtual #216                // Method org/scalatest/tools/TestSortingReporter$Slot.eventList:()Lscala/collection/mutable/ListBuffer;
        73: iconst_0
        74: invokevirtual #376                // Method scala/collection/mutable/ListBuffer.remove:(I)Ljava/lang/Object;
        77: pop
        78: aload_0
        79: getfield      #323                // Field dispatch:Lorg/scalatest/Reporter;
        82: aload         4
        84: invokeinterface #326,  2          // InterfaceMethod org/scalatest/Reporter.apply:(Lorg/scalatest/events/Event;)V
        89: getstatic     #225                // Field scala/runtime/BoxedUnit.UNIT:Lscala/runtime/BoxedUnit;
        92: goto          98
        95: getstatic     #225                // Field scala/runtime/BoxedUnit.UNIT:Lscala/runtime/BoxedUnit;
        98: pop
        99: return
      StackMapTable: number_of_entries = 4
        frame_type = 0 /* same */
        frame_type = 45 /* same */
        frame_type = 48 /* same */
        frame_type = 66 /* same_locals_1_stack_item */
          stack = [ class scala/runtime/BoxedUnit ]
      LineNumberTable:
        line 216: 0
        line 217: 11
        line 218: 22
        line 219: 31
        line 220: 41
        line 222: 46
        line 223: 57
        line 224: 69
        line 225: 78
        line 222: 95
        line 216: 99
      LocalVariableTable:
        Start  Length  Slot  Name   Signature
           22      24     3  head   Lorg/scalatest/events/Event;
           69      23     4  head   Lorg/scalatest/events/Event;
            0     100     0  this   Lorg/scalatest/tools/TestSortingReporter;
            0     100     1  slot   Lorg/scalatest/tools/TestSortingReporter$Slot;
    MethodParameters:
      Name                           Flags
      slot                           final

  private void fireReadyEvents();
    descriptor: ()V
    flags: (0x0002) ACC_PRIVATE
    Code:
      stack=2, locals=5, args_size=1
         0: aload_0
         1: invokespecial #186                // Method waitingBuffer:()Lscala/collection/mutable/ListBuffer;
         4: invokevirtual #193                // Method scala/collection/mutable/ListBuffer.size:()I
         7: iconst_1
         8: if_icmple     84
        11: aload_0
        12: invokespecial #186                // Method waitingBuffer:()Lscala/collection/mutable/ListBuffer;
        15: invokevirtual #372                // Method scala/collection/mutable/ListBuffer.head:()Ljava/lang/Object;
        18: checkcast     #19                 // class org/scalatest/tools/TestSortingReporter$Slot
        21: astore_2
        22: aload_2
        23: invokevirtual #237                // Method org/scalatest/tools/TestSortingReporter$Slot.ready:()Z
        26: ifeq          78
        29: aload_0
        30: aload_2
        31: invokespecial #378                // Method fireSlotEvents:(Lorg/scalatest/tools/TestSortingReporter$Slot;)V
        34: aload_0
        35: invokespecial #186                // Method waitingBuffer:()Lscala/collection/mutable/ListBuffer;
        38: iconst_0
        39: invokevirtual #376                // Method scala/collection/mutable/ListBuffer.remove:(I)Ljava/lang/Object;
        42: pop
        43: aload_0
        44: invokespecial #381                // Method cancelTimeoutTask:()V
        47: aload_0
        48: invokespecial #186                // Method waitingBuffer:()Lscala/collection/mutable/ListBuffer;
        51: invokevirtual #372                // Method scala/collection/mutable/ListBuffer.head:()Ljava/lang/Object;
        54: checkcast     #19                 // class org/scalatest/tools/TestSortingReporter$Slot
        57: astore_3
        58: aload_3
        59: invokevirtual #237                // Method org/scalatest/tools/TestSortingReporter$Slot.ready:()Z
        62: ifeq          68
        65: goto          0
        68: aload_0
        69: invokespecial #196                // Method scheduleTimeoutTask:()V
        72: getstatic     #225                // Field scala/runtime/BoxedUnit.UNIT:Lscala/runtime/BoxedUnit;
        75: goto          81
        78: getstatic     #225                // Field scala/runtime/BoxedUnit.UNIT:Lscala/runtime/BoxedUnit;
        81: goto          149
        84: aload_0
        85: invokespecial #186                // Method waitingBuffer:()Lscala/collection/mutable/ListBuffer;
        88: invokevirtual #193                // Method scala/collection/mutable/ListBuffer.size:()I
        91: iconst_1
        92: if_icmpne     146
        95: aload_0
        96: invokespecial #186                // Method waitingBuffer:()Lscala/collection/mutable/ListBuffer;
        99: invokevirtual #372                // Method scala/collection/mutable/ListBuffer.head:()Ljava/lang/Object;
       102: checkcast     #19                 // class org/scalatest/tools/TestSortingReporter$Slot
       105: astore        4
       107: aload         4
       109: invokevirtual #237                // Method org/scalatest/tools/TestSortingReporter$Slot.ready:()Z
       112: ifeq          140
       115: aload_0
       116: aload         4
       118: invokespecial #378                // Method fireSlotEvents:(Lorg/scalatest/tools/TestSortingReporter$Slot;)V
       121: aload_0
       122: invokespecial #186                // Method waitingBuffer:()Lscala/collection/mutable/ListBuffer;
       125: iconst_0
       126: invokevirtual #376                // Method scala/collection/mutable/ListBuffer.remove:(I)Ljava/lang/Object;
       129: pop
       130: aload_0
       131: invokespecial #381                // Method cancelTimeoutTask:()V
       134: getstatic     #225                // Field scala/runtime/BoxedUnit.UNIT:Lscala/runtime/BoxedUnit;
       137: goto          143
       140: getstatic     #225                // Field scala/runtime/BoxedUnit.UNIT:Lscala/runtime/BoxedUnit;
       143: goto          149
       146: getstatic     #225                // Field scala/runtime/BoxedUnit.UNIT:Lscala/runtime/BoxedUnit;
       149: pop
       150: return
      StackMapTable: number_of_entries = 9
        frame_type = 0 /* same */
        frame_type = 254 /* append */
          offset_delta = 67
          locals = [ top, class org/scalatest/tools/TestSortingReporter$Slot, class org/scalatest/tools/TestSortingReporter$Slot ]
        frame_type = 250 /* chop */
          offset_delta = 9
        frame_type = 66 /* same_locals_1_stack_item */
          stack = [ class scala/runtime/BoxedUnit ]
        frame_type = 249 /* chop */
          offset_delta = 2
        frame_type = 255 /* full_frame */
          offset_delta = 55
          locals = [ class org/scalatest/tools/TestSortingReporter, top, top, top, class org/scalatest/tools/TestSortingReporter$Slot ]
          stack = []
        frame_type = 66 /* same_locals_1_stack_item */
          stack = [ class scala/runtime/BoxedUnit ]
        frame_type = 255 /* full_frame */
          offset_delta = 2
          locals = [ class org/scalatest/tools/TestSortingReporter ]
          stack = []
        frame_type = 66 /* same_locals_1_stack_item */
          stack = [ class scala/runtime/BoxedUnit ]
      LineNumberTable:
        line 234: 0
        line 235: 11
        line 236: 22
        line 237: 29
        line 238: 34
        line 239: 43
        line 240: 47
        line 241: 58
        line 242: 65
        line 244: 68
        line 236: 78
        line 247: 84
        line 248: 95
        line 249: 107
        line 250: 115
        line 251: 121
        line 252: 130
        line 249: 140
        line 247: 146
        line 234: 150
      LocalVariableTable:
        Start  Length  Slot  Name   Signature
           58      17     3 newHead   Lorg/scalatest/tools/TestSortingReporter$Slot;
           22      59     2  head   Lorg/scalatest/tools/TestSortingReporter$Slot;
          107      36     4  head   Lorg/scalatest/tools/TestSortingReporter$Slot;
            0     151     0  this   Lorg/scalatest/tools/TestSortingReporter;

  private void scheduleTimeoutTask();
    descriptor: ()V
    flags: (0x0002) ACC_PRIVATE
    Code:
      stack=7, locals=23, args_size=1
         0: aload_0
         1: invokespecial #186                // Method waitingBuffer:()Lscala/collection/mutable/ListBuffer;
         4: invokevirtual #372                // Method scala/collection/mutable/ListBuffer.head:()Ljava/lang/Object;
         7: checkcast     #19                 // class org/scalatest/tools/TestSortingReporter$Slot
        10: astore        4
        12: aload_0
        13: invokespecial #384                // Method timeoutTask:()Lscala/Option;
        16: astore        5
        18: aload         5
        20: instanceof    #285                // class scala/Some
        23: ifeq          268
        26: aload         5
        28: checkcast     #285                // class scala/Some
        31: astore        6
        33: aload         6
        35: invokevirtual #289                // Method scala/Some.value:()Ljava/lang/Object;
        38: checkcast     #386                // class scala/Tuple2
        41: astore        7
        43: aload         7
        45: ifnull        265
        48: aload         7
        50: invokevirtual #389                // Method scala/Tuple2._1:()Ljava/lang/Object;
        53: checkcast     #25                 // class org/scalatest/tools/TestSortingReporter$TimeoutTask
        56: astore        8
        58: aload         7
        60: invokevirtual #392                // Method scala/Tuple2._2:()Ljava/lang/Object;
        63: checkcast     #394                // class org/scalatest/Timer
        66: astore        9
        68: aload         4
        70: invokevirtual #397                // Method org/scalatest/tools/TestSortingReporter$Slot.uuid:()Ljava/util/UUID;
        73: aload         8
        75: invokevirtual #400                // Method org/scalatest/tools/TestSortingReporter$TimeoutTask.slot:()Lorg/scalatest/tools/TestSortingReporter$Slot;
        78: invokevirtual #397                // Method org/scalatest/tools/TestSortingReporter$Slot.uuid:()Ljava/util/UUID;
        81: astore        10
        83: dup
        84: ifnonnull     96
        87: pop
        88: aload         10
        90: ifnull        258
        93: goto          104
        96: aload         10
        98: invokevirtual #304                // Method java/lang/Object.equals:(Ljava/lang/Object;)Z
       101: ifne          258
       104: aload         8
       106: invokevirtual #403                // Method org/scalatest/tools/TestSortingReporter$TimeoutTask.cancel:()V
       109: aload         9
       111: invokevirtual #404                // Method org/scalatest/Timer.cancel:()V
       114: new           #386                // class scala/Tuple2
       117: dup
       118: new           #25                 // class org/scalatest/tools/TestSortingReporter$TimeoutTask
       121: dup
       122: aload_0
       123: aload         4
       125: invokespecial #407                // Method org/scalatest/tools/TestSortingReporter$TimeoutTask."<init>":(Lorg/scalatest/tools/TestSortingReporter;Lorg/scalatest/tools/TestSortingReporter$Slot;)V
       128: new           #394                // class org/scalatest/Timer
       131: dup
       132: invokespecial #408                // Method org/scalatest/Timer."<init>":()V
       135: invokespecial #411                // Method scala/Tuple2."<init>":(Ljava/lang/Object;Ljava/lang/Object;)V
       138: astore        12
       140: aload         12
       142: ifnull        180
       145: aload         12
       147: invokevirtual #389                // Method scala/Tuple2._1:()Ljava/lang/Object;
       150: checkcast     #25                 // class org/scalatest/tools/TestSortingReporter$TimeoutTask
       153: astore        13
       155: aload         12
       157: invokevirtual #392                // Method scala/Tuple2._2:()Ljava/lang/Object;
       160: checkcast     #394                // class org/scalatest/Timer
       163: astore        14
       165: new           #386                // class scala/Tuple2
       168: dup
       169: aload         13
       171: aload         14
       173: invokespecial #411                // Method scala/Tuple2."<init>":(Ljava/lang/Object;Ljava/lang/Object;)V
       176: astore_3
       177: goto          193
       180: goto          183
       183: new           #306                // class scala/MatchError
       186: dup
       187: aload         12
       189: invokespecial #309                // Method scala/MatchError."<init>":(Ljava/lang/Object;)V
       192: athrow
       193: aload_3
       194: astore        11
       196: aload         11
       198: invokevirtual #389                // Method scala/Tuple2._1:()Ljava/lang/Object;
       201: checkcast     #25                 // class org/scalatest/tools/TestSortingReporter$TimeoutTask
       204: astore        15
       206: aload         11
       208: invokevirtual #392                // Method scala/Tuple2._2:()Ljava/lang/Object;
       211: checkcast     #394                // class org/scalatest/Timer
       214: astore        16
       216: aload_0
       217: new           #285                // class scala/Some
       220: dup
       221: new           #386                // class scala/Tuple2
       224: dup
       225: aload         15
       227: aload         16
       229: invokespecial #411                // Method scala/Tuple2."<init>":(Ljava/lang/Object;Ljava/lang/Object;)V
       232: invokespecial #412                // Method scala/Some."<init>":(Ljava/lang/Object;)V
       235: invokespecial #414                // Method timeoutTask_$eq:(Lscala/Option;)V
       238: aload         16
       240: aload         15
       242: aload_0
       243: getfield      #416                // Field sortingTimeout:Lorg/scalatest/time/Span;
       246: invokevirtual #422                // Method org/scalatest/time/Span.millisPart:()J
       249: invokevirtual #426                // Method org/scalatest/Timer.schedule:(Lorg/scalatest/TimerTask;J)V
       252: getstatic     #225                // Field scala/runtime/BoxedUnit.UNIT:Lscala/runtime/BoxedUnit;
       255: goto          261
       258: getstatic     #225                // Field scala/runtime/BoxedUnit.UNIT:Lscala/runtime/BoxedUnit;
       261: astore_1
       262: goto          440
       265: goto          271
       268: goto          271
       271: getstatic     #301                // Field scala/None$.MODULE$:Lscala/None$;
       274: aload         5
       276: invokevirtual #304                // Method java/lang/Object.equals:(Ljava/lang/Object;)Z
       279: ifeq          427
       282: new           #386                // class scala/Tuple2
       285: dup
       286: new           #25                 // class org/scalatest/tools/TestSortingReporter$TimeoutTask
       289: dup
       290: aload_0
       291: aload         4
       293: invokespecial #407                // Method org/scalatest/tools/TestSortingReporter$TimeoutTask."<init>":(Lorg/scalatest/tools/TestSortingReporter;Lorg/scalatest/tools/TestSortingReporter$Slot;)V
       296: new           #394                // class org/scalatest/Timer
       299: dup
       300: invokespecial #408                // Method org/scalatest/Timer."<init>":()V
       303: invokespecial #411                // Method scala/Tuple2."<init>":(Ljava/lang/Object;Ljava/lang/Object;)V
       306: astore        18
       308: aload         18
       310: ifnull        348
       313: aload         18
       315: invokevirtual #389                // Method scala/Tuple2._1:()Ljava/lang/Object;
       318: checkcast     #25                 // class org/scalatest/tools/TestSortingReporter$TimeoutTask
       321: astore        19
       323: aload         18
       325: invokevirtual #392                // Method scala/Tuple2._2:()Ljava/lang/Object;
       328: checkcast     #394                // class org/scalatest/Timer
       331: astore        20
       333: new           #386                // class scala/Tuple2
       336: dup
       337: aload         19
       339: aload         20
       341: invokespecial #411                // Method scala/Tuple2."<init>":(Ljava/lang/Object;Ljava/lang/Object;)V
       344: astore_2
       345: goto          361
       348: goto          351
       351: new           #306                // class scala/MatchError
       354: dup
       355: aload         18
       357: invokespecial #309                // Method scala/MatchError."<init>":(Ljava/lang/Object;)V
       360: athrow
       361: aload_2
       362: astore        17
       364: aload         17
       366: invokevirtual #389                // Method scala/Tuple2._1:()Ljava/lang/Object;
       369: checkcast     #25                 // class org/scalatest/tools/TestSortingReporter$TimeoutTask
       372: astore        21
       374: aload         17
       376: invokevirtual #392                // Method scala/Tuple2._2:()Ljava/lang/Object;
       379: checkcast     #394                // class org/scalatest/Timer
       382: astore        22
       384: aload_0
       385: new           #285                // class scala/Some
       388: dup
       389: new           #386                // class scala/Tuple2
       392: dup
       393: aload         21
       395: aload         22
       397: invokespecial #411                // Method scala/Tuple2."<init>":(Ljava/lang/Object;Ljava/lang/Object;)V
       400: invokespecial #412                // Method scala/Some."<init>":(Ljava/lang/Object;)V
       403: invokespecial #414                // Method timeoutTask_$eq:(Lscala/Option;)V
       406: aload         22
       408: aload         21
       410: aload_0
       411: getfield      #416                // Field sortingTimeout:Lorg/scalatest/time/Span;
       414: invokevirtual #422                // Method org/scalatest/time/Span.millisPart:()J
       417: invokevirtual #426                // Method org/scalatest/Timer.schedule:(Lorg/scalatest/TimerTask;J)V
       420: getstatic     #225                // Field scala/runtime/BoxedUnit.UNIT:Lscala/runtime/BoxedUnit;
       423: astore_1
       424: goto          440
       427: goto          430
       430: new           #306                // class scala/MatchError
       433: dup
       434: aload         5
       436: invokespecial #309                // Method scala/MatchError."<init>":(Ljava/lang/Object;)V
       439: athrow
       440: return
      StackMapTable: number_of_entries = 16
        frame_type = 255 /* full_frame */
          offset_delta = 96
          locals = [ class org/scalatest/tools/TestSortingReporter, top, top, top, class org/scalatest/tools/TestSortingReporter$Slot, class scala/Option, class scala/Some, class scala/Tuple2, class org/scalatest/tools/TestSortingReporter$TimeoutTask, class org/scalatest/Timer, class java/util/UUID ]
          stack = [ class java/util/UUID ]
        frame_type = 7 /* same */
        frame_type = 253 /* append */
          offset_delta = 75
          locals = [ top, class scala/Tuple2 ]
        frame_type = 2 /* same */
        frame_type = 255 /* full_frame */
          offset_delta = 9
          locals = [ class org/scalatest/tools/TestSortingReporter, top, top, class scala/Tuple2, class org/scalatest/tools/TestSortingReporter$Slot, class scala/Option, class scala/Some, class scala/Tuple2, class org/scalatest/tools/TestSortingReporter$TimeoutTask, class org/scalatest/Timer, class java/util/UUID, top, class scala/Tuple2, class org/scalatest/tools/TestSortingReporter$TimeoutTask, class org/scalatest/Timer ]
          stack = []
        frame_type = 255 /* full_frame */
          offset_delta = 64
          locals = [ class org/scalatest/tools/TestSortingReporter, top, top, top, class org/scalatest/tools/TestSortingReporter$Slot, class scala/Option, class scala/Some, class scala/Tuple2, class org/scalatest/tools/TestSortingReporter$TimeoutTask, class org/scalatest/Timer, class java/util/UUID ]
          stack = []
        frame_type = 66 /* same_locals_1_stack_item */
          stack = [ class scala/runtime/BoxedUnit ]
        frame_type = 248 /* chop */
          offset_delta = 3
        frame_type = 249 /* chop */
          offset_delta = 2
        frame_type = 2 /* same */
        frame_type = 255 /* full_frame */
          offset_delta = 76
          locals = [ class org/scalatest/tools/TestSortingReporter, top, top, top, class org/scalatest/tools/TestSortingReporter$Slot, class scala/Option, top, top, top, top, top, top, top, top, top, top, top, top, class scala/Tuple2 ]
          stack = []
        frame_type = 2 /* same */
        frame_type = 255 /* full_frame */
          offset_delta = 9
          locals = [ class org/scalatest/tools/TestSortingReporter, top, class scala/Tuple2, top, class org/scalatest/tools/TestSortingReporter$Slot, class scala/Option, top, top, top, top, top, top, top, top, top, top, top, top, class scala/Tuple2, class org/scalatest/tools/TestSortingReporter$TimeoutTask, class org/scalatest/Timer ]
          stack = []
        frame_type = 255 /* full_frame */
          offset_delta = 65
          locals = [ class org/scalatest/tools/TestSortingReporter, top, top, top, class org/scalatest/tools/TestSortingReporter$Slot, class scala/Option ]
          stack = []
        frame_type = 2 /* same */
        frame_type = 255 /* full_frame */
          offset_delta = 9
          locals = [ class org/scalatest/tools/TestSortingReporter, class scala/runtime/BoxedUnit, top, top, class org/scalatest/tools/TestSortingReporter$Slot, class scala/Option ]
          stack = []
      LineNumberTable:
        line 259: 0
        line 260: 12
        line 261: 18
        line 262: 68
        line 263: 104
        line 264: 109
        line 265: 114
        line 266: 216
        line 267: 238
        line 262: 258
        line 261: 265
        line 269: 271
        line 270: 282
        line 271: 384
        line 272: 406
        line 269: 427
        line 260: 430
      LocalVariableTable:
        Start  Length  Slot  Name   Signature
          155      25    13  task   Lorg/scalatest/tools/TestSortingReporter$TimeoutTask;
          165      15    14 timer   Lorg/scalatest/Timer;
          206      49    15  task   Lorg/scalatest/tools/TestSortingReporter$TimeoutTask;
          216      39    16 timer   Lorg/scalatest/Timer;
           58     207     8 oldTask   Lorg/scalatest/tools/TestSortingReporter$TimeoutTask;
           68     197     9 oldTimer   Lorg/scalatest/Timer;
          323      25    19  task   Lorg/scalatest/tools/TestSortingReporter$TimeoutTask;
          333      15    20 timer   Lorg/scalatest/Timer;
          374      49    21  task   Lorg/scalatest/tools/TestSortingReporter$TimeoutTask;
          384      39    22 timer   Lorg/scalatest/Timer;
           12     428     4  head   Lorg/scalatest/tools/TestSortingReporter$Slot;
            0     441     0  this   Lorg/scalatest/tools/TestSortingReporter;

  private void cancelTimeoutTask();
    descriptor: ()V
    flags: (0x0002) ACC_PRIVATE
    Code:
      stack=3, locals=7, args_size=1
         0: aload_0
         1: invokespecial #384                // Method timeoutTask:()Lscala/Option;
         4: astore_2
         5: aload_2
         6: instanceof    #285                // class scala/Some
         9: ifeq          78
        12: aload_2
        13: checkcast     #285                // class scala/Some
        16: astore_3
        17: aload_3
        18: invokevirtual #289                // Method scala/Some.value:()Ljava/lang/Object;
        21: checkcast     #386                // class scala/Tuple2
        24: astore        4
        26: aload         4
        28: ifnull        75
        31: aload         4
        33: invokevirtual #389                // Method scala/Tuple2._1:()Ljava/lang/Object;
        36: checkcast     #25                 // class org/scalatest/tools/TestSortingReporter$TimeoutTask
        39: astore        5
        41: aload         4
        43: invokevirtual #392                // Method scala/Tuple2._2:()Ljava/lang/Object;
        46: checkcast     #394                // class org/scalatest/Timer
        49: astore        6
        51: aload         5
        53: invokevirtual #403                // Method org/scalatest/tools/TestSortingReporter$TimeoutTask.cancel:()V
        56: aload         6
        58: invokevirtual #404                // Method org/scalatest/Timer.cancel:()V
        61: aload_0
        62: getstatic     #301                // Field scala/None$.MODULE$:Lscala/None$;
        65: invokespecial #414                // Method timeoutTask_$eq:(Lscala/Option;)V
        68: getstatic     #225                // Field scala/runtime/BoxedUnit.UNIT:Lscala/runtime/BoxedUnit;
        71: astore_1
        72: goto          110
        75: goto          81
        78: goto          81
        81: getstatic     #301                // Field scala/None$.MODULE$:Lscala/None$;
        84: aload_2
        85: invokevirtual #304                // Method java/lang/Object.equals:(Ljava/lang/Object;)Z
        88: ifeq          98
        91: getstatic     #225                // Field scala/runtime/BoxedUnit.UNIT:Lscala/runtime/BoxedUnit;
        94: astore_1
        95: goto          110
        98: goto          101
       101: new           #306                // class scala/MatchError
       104: dup
       105: aload_2
       106: invokespecial #309                // Method scala/MatchError."<init>":(Ljava/lang/Object;)V
       109: athrow
       110: return
      StackMapTable: number_of_entries = 6
        frame_type = 255 /* full_frame */
          offset_delta = 75
          locals = [ class org/scalatest/tools/TestSortingReporter, top, class scala/Option, class scala/Some, class scala/Tuple2 ]
          stack = []
        frame_type = 249 /* chop */
          offset_delta = 2
        frame_type = 2 /* same */
        frame_type = 16 /* same */
        frame_type = 2 /* same */
        frame_type = 255 /* full_frame */
          offset_delta = 8
          locals = [ class org/scalatest/tools/TestSortingReporter, class scala/runtime/BoxedUnit, class scala/Option ]
          stack = []
      LineNumberTable:
        line 278: 0
        line 279: 5
        line 280: 51
        line 281: 56
        line 282: 61
        line 279: 75
        line 283: 81
        line 278: 101
      LocalVariableTable:
        Start  Length  Slot  Name   Signature
           41      34     5  task   Lorg/scalatest/tools/TestSortingReporter$TimeoutTask;
           51      24     6 timer   Lorg/scalatest/Timer;
            0     111     0  this   Lorg/scalatest/tools/TestSortingReporter;

  public synchronized void org$scalatest$tools$TestSortingReporter$$timeout();
    descriptor: ()V
    flags: (0x0021) ACC_PUBLIC, ACC_SYNCHRONIZED
    Code:
      stack=6, locals=13, args_size=1
         0: aload_0
         1: invokespecial #186                // Method waitingBuffer:()Lscala/collection/mutable/ListBuffer;
         4: invokevirtual #193                // Method scala/collection/mutable/ListBuffer.size:()I
         7: iconst_0
         8: if_icmple     166
        11: aload_0
        12: invokespecial #186                // Method waitingBuffer:()Lscala/collection/mutable/ListBuffer;
        15: invokevirtual #372                // Method scala/collection/mutable/ListBuffer.head:()Ljava/lang/Object;
        18: checkcast     #19                 // class org/scalatest/tools/TestSortingReporter$Slot
        21: astore_2
        22: aload_0
        23: invokespecial #384                // Method timeoutTask:()Lscala/Option;
        26: invokevirtual #435                // Method scala/Option.get:()Ljava/lang/Object;
        29: checkcast     #386                // class scala/Tuple2
        32: astore        4
        34: aload         4
        36: ifnull        55
        39: aload         4
        41: invokevirtual #389                // Method scala/Tuple2._1:()Ljava/lang/Object;
        44: checkcast     #25                 // class org/scalatest/tools/TestSortingReporter$TimeoutTask
        47: astore        5
        49: aload         5
        51: astore_1
        52: goto          68
        55: goto          58
        58: new           #306                // class scala/MatchError
        61: dup
        62: aload         4
        64: invokespecial #309                // Method scala/MatchError."<init>":(Ljava/lang/Object;)V
        67: athrow
        68: aload_1
        69: astore_3
        70: aload_3
        71: invokevirtual #400                // Method org/scalatest/tools/TestSortingReporter$TimeoutTask.slot:()Lorg/scalatest/tools/TestSortingReporter$Slot;
        74: invokevirtual #397                // Method org/scalatest/tools/TestSortingReporter$Slot.uuid:()Ljava/util/UUID;
        77: aload_2
        78: invokevirtual #397                // Method org/scalatest/tools/TestSortingReporter$Slot.uuid:()Ljava/util/UUID;
        81: astore        6
        83: dup
        84: ifnonnull     96
        87: pop
        88: aload         6
        90: ifnull        104
        93: goto          159
        96: aload         6
        98: invokevirtual #304                // Method java/lang/Object.equals:(Ljava/lang/Object;)Z
       101: ifeq          159
       104: iconst_1
       105: istore        8
       107: aload_2
       108: invokevirtual #246                // Method org/scalatest/tools/TestSortingReporter$Slot.copy$default$1:()Ljava/util/UUID;
       111: astore        9
       113: aload_2
       114: invokevirtual #249                // Method org/scalatest/tools/TestSortingReporter$Slot.copy$default$2:()Lscala/collection/mutable/ListBuffer;
       117: astore        10
       119: aload_2
       120: invokevirtual #364                // Method org/scalatest/tools/TestSortingReporter$Slot.copy$default$3:()Z
       123: istore        11
       125: aload_2
       126: invokevirtual #252                // Method org/scalatest/tools/TestSortingReporter$Slot.copy$default$4:()Z
       129: istore        12
       131: aload_2
       132: aload         9
       134: aload         10
       136: iload         11
       138: iload         12
       140: iconst_1
       141: invokevirtual #256                // Method org/scalatest/tools/TestSortingReporter$Slot.copy:(Ljava/util/UUID;Lscala/collection/mutable/ListBuffer;ZZZ)Lorg/scalatest/tools/TestSortingReporter$Slot;
       144: astore        7
       146: aload_0
       147: invokespecial #186                // Method waitingBuffer:()Lscala/collection/mutable/ListBuffer;
       150: iconst_0
       151: aload         7
       153: invokevirtual #264                // Method scala/collection/mutable/ListBuffer.update:(ILjava/lang/Object;)V
       156: goto          159
       159: aload_0
       160: invokespecial #219                // Method fireReadyEvents:()V
       163: goto          166
       166: return
      StackMapTable: number_of_entries = 7
        frame_type = 255 /* full_frame */
          offset_delta = 55
          locals = [ class org/scalatest/tools/TestSortingReporter, top, class org/scalatest/tools/TestSortingReporter$Slot, top, class scala/Tuple2 ]
          stack = []
        frame_type = 2 /* same */
        frame_type = 255 /* full_frame */
          offset_delta = 9
          locals = [ class org/scalatest/tools/TestSortingReporter, class org/scalatest/tools/TestSortingReporter$TimeoutTask, class org/scalatest/tools/TestSortingReporter$Slot, top, class scala/Tuple2, class org/scalatest/tools/TestSortingReporter$TimeoutTask ]
          stack = []
        frame_type = 255 /* full_frame */
          offset_delta = 27
          locals = [ class org/scalatest/tools/TestSortingReporter, class org/scalatest/tools/TestSortingReporter$TimeoutTask, class org/scalatest/tools/TestSortingReporter$Slot, class org/scalatest/tools/TestSortingReporter$TimeoutTask, class scala/Tuple2, class org/scalatest/tools/TestSortingReporter$TimeoutTask, class java/util/UUID ]
          stack = [ class java/util/UUID ]
        frame_type = 7 /* same */
        frame_type = 54 /* same */
        frame_type = 255 /* full_frame */
          offset_delta = 6
          locals = [ class org/scalatest/tools/TestSortingReporter ]
          stack = []
      LineNumberTable:
        line 289: 0
        line 290: 11
        line 291: 22
        line 292: 70
        line 293: 104
        line 294: 146
        line 296: 159
        line 289: 166
      LocalVariableTable:
        Start  Length  Slot  Name   Signature
           49       6     5  task   Lorg/scalatest/tools/TestSortingReporter$TimeoutTask;
          107      37     8   x$1   Z
          113      31     9   x$2   Ljava/util/UUID;
          119      25    10   x$3   Lscala/collection/mutable/ListBuffer;
          125      19    11   x$4   Z
          131      13    12   x$5   Z
          146      10     7 newSlot   Lorg/scalatest/tools/TestSortingReporter$Slot;
           22     141     2  head   Lorg/scalatest/tools/TestSortingReporter$Slot;
           70      93     3  task   Lorg/scalatest/tools/TestSortingReporter$TimeoutTask;
            0     167     0  this   Lorg/scalatest/tools/TestSortingReporter;

  public void doDispose();
    descriptor: ()V
    flags: (0x0001) ACC_PUBLIC
    Code:
      stack=2, locals=1, args_size=1
         0: aload_0
         1: invokespecial #219                // Method fireReadyEvents:()V
         4: getstatic     #441                // Field org/scalatest/Reporter$.MODULE$:Lorg/scalatest/Reporter$;
         7: aload_0
         8: getfield      #323                // Field dispatch:Lorg/scalatest/Reporter;
        11: invokevirtual #445                // Method org/scalatest/Reporter$.propagateDispose:(Lorg/scalatest/Reporter;)V
        14: return
      LineNumberTable:
        line 302: 0
        line 303: 4
      LocalVariableTable:
        Start  Length  Slot  Name   Signature
            0      15     0  this   Lorg/scalatest/tools/TestSortingReporter;

  private final void Slot$lzycompute$1();
    descriptor: ()V
    flags: (0x0012) ACC_PRIVATE, ACC_FINAL
    Code:
      stack=4, locals=2, args_size=1
         0: aload_0
         1: dup
         2: astore_1
         3: monitorenter
         4: aload_0
         5: getfield      #69                 // Field Slot$module:Lorg/scalatest/tools/TestSortingReporter$Slot$;
         8: ifnonnull     23
        11: aload_0
        12: new           #22                 // class org/scalatest/tools/TestSortingReporter$Slot$
        15: dup
        16: aload_0
        17: invokespecial #448                // Method org/scalatest/tools/TestSortingReporter$Slot$."<init>":(Lorg/scalatest/tools/TestSortingReporter;)V
        20: putfield      #69                 // Field Slot$module:Lorg/scalatest/tools/TestSortingReporter$Slot$;
        23: aload_1
        24: monitorexit
        25: goto          31
        28: aload_1
        29: monitorexit
        30: athrow
        31: return
      Exception table:
         from    to  target type
             4    23    28   any
      StackMapTable: number_of_entries = 3
        frame_type = 252 /* append */
          offset_delta = 23
          locals = [ class org/scalatest/tools/TestSortingReporter ]
        frame_type = 68 /* same_locals_1_stack_item */
          stack = [ class java/lang/Throwable ]
        frame_type = 2 /* same */
      LineNumberTable:
        line 38: 0
      LocalVariableTable:
        Start  Length  Slot  Name   Signature
            0      32     0  this   Lorg/scalatest/tools/TestSortingReporter;

  public org.scalatest.tools.TestSortingReporter(java.lang.String, org.scalatest.Reporter, org.scalatest.time.Span, int, scala.Option<org.scalatest.DistributedSuiteSorter>, java.io.PrintStream);
    descriptor: (Ljava/lang/String;Lorg/scalatest/Reporter;Lorg/scalatest/time/Span;ILscala/Option;Ljava/io/PrintStream;)V
    flags: (0x0001) ACC_PUBLIC
    Code:
      stack=3, locals=11, args_size=7
         0: aload_0
         1: aload_1
         2: putfield      #293                // Field suiteId:Ljava/lang/String;
         5: aload_0
         6: aload_2
         7: putfield      #323                // Field dispatch:Lorg/scalatest/Reporter;
        10: aload_0
        11: aload_3
        12: putfield      #416                // Field sortingTimeout:Lorg/scalatest/time/Span;
        15: aload_0
        16: iload         4
        18: putfield      #281                // Field testCount:I
        21: aload_0
        22: aload         5
        24: putfield      #283                // Field suiteSorter:Lscala/Option;
        27: aload_0
        28: aload         6
        30: putfield      #75                 // Field out:Ljava/io/PrintStream;
        33: aload_0
        34: invokespecial #451                // Method java/lang/Object."<init>":()V
        37: aload_0
        38: invokestatic  #454                // InterfaceMethod org/scalatest/CatchReporter.$init$:(Lorg/scalatest/CatchReporter;)V
        41: aload         5
        43: astore        8
        45: aload         8
        47: instanceof    #285                // class scala/Some
        50: ifeq          86
        53: aload         8
        55: checkcast     #285                // class scala/Some
        58: astore        9
        60: aload         9
        62: invokevirtual #289                // Method scala/Some.value:()Ljava/lang/Object;
        65: checkcast     #291                // class org/scalatest/DistributedSuiteSorter
        68: astore        10
        70: aload         10
        72: aload_1
        73: invokeinterface #457,  2          // InterfaceMethod org/scalatest/DistributedSuiteSorter.distributingTests:(Ljava/lang/String;)V
        78: getstatic     #225                // Field scala/runtime/BoxedUnit.UNIT:Lscala/runtime/BoxedUnit;
        81: astore        7
        83: goto          121
        86: goto          89
        89: getstatic     #301                // Field scala/None$.MODULE$:Lscala/None$;
        92: aload         8
        94: invokevirtual #304                // Method java/lang/Object.equals:(Ljava/lang/Object;)Z
        97: ifeq          108
       100: getstatic     #225                // Field scala/runtime/BoxedUnit.UNIT:Lscala/runtime/BoxedUnit;
       103: astore        7
       105: goto          121
       108: goto          111
       111: new           #306                // class scala/MatchError
       114: dup
       115: aload         8
       117: invokespecial #309                // Method scala/MatchError."<init>":(Ljava/lang/Object;)V
       120: athrow
       121: aload_0
       122: new           #175                // class scala/collection/mutable/ListBuffer
       125: dup
       126: invokespecial #177                // Method scala/collection/mutable/ListBuffer."<init>":()V
       129: putfield      #79                 // Field waitingBuffer:Lscala/collection/mutable/ListBuffer;
       132: aload_0
       133: new           #142                // class scala/collection/mutable/HashMap
       136: dup
       137: invokespecial #458                // Method scala/collection/mutable/HashMap."<init>":()V
       140: putfield      #83                 // Field slotMap:Lscala/collection/mutable/HashMap;
       143: aload_0
       144: iconst_0
       145: putfield      #86                 // Field completedTestCount:I
       148: aload_0
       149: invokespecial #271                // Method checkCompletedTests:()V
       152: aload_0
       153: getstatic     #301                // Field scala/None$.MODULE$:Lscala/None$;
       156: putfield      #93                 // Field timeoutTask:Lscala/Option;
       159: return
      StackMapTable: number_of_entries = 5
        frame_type = 255 /* full_frame */
          offset_delta = 86
          locals = [ class org/scalatest/tools/TestSortingReporter, class java/lang/String, class org/scalatest/Reporter, class org/scalatest/time/Span, int, class scala/Option, class java/io/PrintStream, top, class scala/Option ]
          stack = []
        frame_type = 2 /* same */
        frame_type = 18 /* same */
        frame_type = 2 /* same */
        frame_type = 255 /* full_frame */
          offset_delta = 9
          locals = [ class org/scalatest/tools/TestSortingReporter, class java/lang/String, class org/scalatest/Reporter, class org/scalatest/time/Span, int, class scala/Option, class java/io/PrintStream, class scala/runtime/BoxedUnit, class scala/Option ]
          stack = []
      LineNumberTable:
        line 28: 0
        line 30: 41
        line 31: 45
        line 32: 70
        line 31: 86
        line 33: 89
        line 30: 111
        line 40: 121
        line 41: 132
        line 42: 143
        line 44: 148
        line 53: 152
        line 28: 159
      LocalVariableTable:
        Start  Length  Slot  Name   Signature
           70      16    10 suiteSorter   Lorg/scalatest/DistributedSuiteSorter;
            0     160     0  this   Lorg/scalatest/tools/TestSortingReporter;
            0     160     1 suiteId   Ljava/lang/String;
            0     160     2 dispatch   Lorg/scalatest/Reporter;
            0     160     3 sortingTimeout   Lorg/scalatest/time/Span;
            0     160     4 testCount   I
            0     160     5 suiteSorter   Lscala/Option;
            0     160     6   out   Ljava/io/PrintStream;
    Signature: #450                         // (Ljava/lang/String;Lorg/scalatest/Reporter;Lorg/scalatest/time/Span;ILscala/Option<Lorg/scalatest/DistributedSuiteSorter;>;Ljava/io/PrintStream;)V
    MethodParameters:
      Name                           Flags
      suiteId                        final
      dispatch                       final
      sortingTimeout                 final
      testCount                      final
      suiteSorter                    final
      out                            final
}
InnerClasses:
  public static #17= #14 of #16;          // RequirementsHelper=class org/scalactic/Requirements$RequirementsHelper of class org/scalactic/Requirements
  public #20= #19 of #2;                  // Slot=class org/scalatest/tools/TestSortingReporter$Slot of class org/scalatest/tools/TestSortingReporter
  public #23= #22 of #2;                  // Slot$=class org/scalatest/tools/TestSortingReporter$Slot$ of class org/scalatest/tools/TestSortingReporter
  public #26= #25 of #2;                  // TimeoutTask=class org/scalatest/tools/TestSortingReporter$TimeoutTask of class org/scalatest/tools/TestSortingReporter
SourceFile: "TestSortingReporter.scala"
RuntimeVisibleAnnotations:
  0: #10(#11=s#12)
    scala.reflect.ScalaSignature(
      bytes="\u0006\u0005\tmh!\u0002$H\u0001%k\u0005\u0002C.\u0001\u0005\u0003\u0005\u000b\u0011B/\t\u0011!\u0004!\u0011!Q\u0001\n%D\u0001\u0002\u001c\u0001\u0003\u0002\u0003\u0006I!\u001c\u0005\tg\u0002\u0011\t\u0011)A\u0005i\"Aq\u000f\u0001B\u0001B\u0003%\u0001\u0010\u0003\u0005\u007f\u0001\t\u0015\r\u0011\"\u0001\u0000\u0011)\t\t\u0002\u0001B\u0001B\u0003%\u0011\u0011\u0001\u0005\b\u0003\'\u0001A\u0011AA\u000b\r\u0019\t9\u0003\u0001!\u0002*!Q\u00111I\u0005\u0003\u0016\u0004%\t!!\u0012\t\u0015\u0005M\u0013B!E!\u0002\u0013\t9\u0005\u0003\u0006\u0002V%\u0011)\u001a!C\u0001\u0003/B!\"!\u001e\n\u0005#\u0005\u000b\u0011BA-\u0011)\t9(\u0003BK\u0002\u0013\u0005\u0011\u0011\u0010\u0005\u000b\u0003\u0003K!\u0011#Q\u0001\n\u0005m\u0004BCAB\u0013\tU\r\u0011\"\u0001\u0002z!Q\u0011QQ\u0005\u0003\u0012\u0003\u0006I!a\u001f\t\u0015\u0005\u001d\u0015B!f\u0001\n\u0003\tI\b\u0003\u0006\u0002\n&\u0011\t\u0012)A\u0005\u0003wBq!a\u0005\n\t\u0003\tY\tC\u0005\u0002\u001c&\t\t\u0011\"\u0001\u0002\u001e\"I\u0011\u0011V\u0005\u0012\u0002\u0013\u0005\u00111\u0016\u0005\n\u0003\u0003L\u0011\u0013!C\u0001\u0003\u0007D\u0011\"a2\n#\u0003%\t!!3\t\u0013\u00055\u0017\"%A\u0005\u0002\u0005%\u0007\"CAh\u0013E\u0005I\u0011AAe\u0011%\t\t.CA\u0001\n\u0003\n\u0019\u000eC\u0005\u0002`&\t\t\u0011\"\u0001\u0002b\"I\u00111]\u0005\u0002\u0002\u0013\u0005\u0011Q\u001d\u0005\n\u0003cL\u0011\u0011!C!\u0003gD\u0011\"!@\n\u0003\u0003%\t!a@\t\u0013\t\r\u0011\"!A\u0005B\t\u0015\u0001\"\u0003B\u0005\u0013\u0005\u0005I\u0011\tB\u0006\u0011%\u0011i!CA\u0001\n\u0003\u0012y\u0001C\u0005\u0003\u0012%\t\t\u0011\"\u0011\u0003\u0014\u001dI!q\u0003\u0001\u0002\u0002#\u0005!\u0011\u0004\u0004\n\u0003O\u0001\u0011\u0011!E\u0001\u00057Aq!a\u0005&\t\u0003\u0011i\u0003C\u0005\u0003\u000e\u0015\n\t\u0011\"\u0012\u0003\u0010!I!qF\u0013\u0002\u0002\u0013\u0005%\u0011\u0007\u0005\n\u0005{)\u0013\u0011!CA\u0005\u007fA\u0011B!\u0014\u0001\u0005\u0004%IAa\u0014\t\u0011\tM\u0003\u0001)A\u0005\u0005#B\u0011B!\u0016\u0001\u0005\u0004%IAa\u0016\t\u0011\t}\u0003\u0001)A\u0005\u00053B\u0011B!\u0019\u0001\u0001\u0004%I!!9\t\u0013\t\r\u0004\u00011A\u0005\n\t\u0015\u0004b\u0002B8\u0001\u0001\u0006K\u0001\u001e\u0004\u0007\u0005s\u0002\u0001Aa\u001f\t\u0015\t%\u0015G!b\u0001\n\u0003\u0011Y\t\u0003\u0006\u0003\u000eF\u0012\t\u0011)A\u0005\u0003\u001bCq!a\u00052\t\u0003\u0011y\tC\u0004\u0003\u0016F\"\tEa&\t\u0013\te\u0005\u00011A\u0005\n\tm\u0005\"\u0003BV\u0001\u0001\u0007I\u0011\u0002BW\u0011!\u0011\t\f\u0001Q!\n\tu\u0005b\u0002BZ\u0001\u0011\u0005!Q\u0017\u0005\b\u0005_\u0001A\u0011\u0001B^\u0011\u001d\u0011\u0019\r\u0001C\u0001\u0005\u000bDqA!3\u0001\t\u0013\u00119\nC\u0004\u0003L\u0002!\tA!4\t\u000f\tE\u0007\u0001\"\u0003\u0003T\"9!q\u001b\u0001\u0005\n\te\u0007b\u0002Bp\u0001\u0011%!\u0011\u001d\u0005\b\u0005_\u0004A\u0011\u0002BL\u0011\u001d\u0011\u0019\u0010\u0001C\u0005\u0005/CqA!>\u0001\t\u0013\u00119\nC\u0004\u0003x\u0002!IAa&\t\u000f\te\b\u0001\"\u0001\u0003\u0018\n\u0019B+Z:u\'>\u0014H/\u001b8h%\u0016\u0004xN\u001d;fe*\u0011\u0001*S\u0001\u0006i>|Gn\u001d\u0006\u0003\u0015.\u000b\u0011b]2bY\u0006$Xm\u001d;\u000b\u00031\u000b1a\u001c:h\'\u0011\u0001a\n\u0016-\u0011\u0005=\u0013V\"\u0001)\u000b\u0003E\u000bQa]2bY\u0006L!a\u0015)\u0003\r\u0005s\u0017PU3g!\t)f+D\u0001J\u0013\t9\u0016JA\u0007DCR\u001c\u0007NU3q_J$XM\u001d\t\u0003+fK!AW%\u0003+\u0011K7\u000f\u001e:jEV$X\r\u001a+fgR\u001cvN\u001d;fe\u000691/^5uK&#7\u0001\u0001\t\u0003=\u0016t!aX2\u0011\u0005\u0001\u0004V\"A1\u000b\u0005\td\u0016A\u0002\u001fs_>$h(\u0003\u0002e!\u00061\u0001K]3eK\u001aL!AZ4\u0003\rM#(/\u001b8h\u0015\t!\u0007+\u0001\u0005eSN\u0004\u0018\r^2i!\t)&.\u0003\u0002l\u0013\nA!+\u001a9peR,\'/\u0001\bt_J$\u0018N\\4US6,w.\u001e;\u0011\u00059\fX\"A8\u000b\u0005AL\u0015\u0001\u0002;j[\u0016L!A]8\u0003\tM\u0003\u0018M\\\u0001\ni\u0016\u001cHoQ8v]R\u0004\"aT;\n\u0005Y\u0004&aA%oi\u0006Y1/^5uKN{\'\u000f^3s!\ry\u0015p_\u0005\u0003uB\u0013aa\u00149uS>t\u0007CA+}\u0013\ti\u0018J\u0001\fESN$(/\u001b2vi\u0016$7+^5uKN{\'\u000f^3s\u0003\ryW\u000f^\u000b\u0003\u0003\u0003\u0001B!a\u0001\u0002\u000e5\u0011\u0011Q\u0001\u0006\u0005\u0003\u000f\tI!\u0001\u0002j_*\u0011\u00111B\u0001\u0005U\u00064\u0018-\u0003\u0003\u0002\u0010\u0005\u0015!a\u0003)sS:$8\u000b\u001e:fC6\fAa\\;uA\u00051A(\u001b8jiz\"b\"a\u0006\u0002\u001c\u0005u\u0011qDA\u0011\u0003G\t)\u0003E\u0002\u0002\u001a\u0001i\u0011a\u0012\u0005\u00067\"\u0001\r!\u0018\u0005\u0006Q\"\u0001\r!\u001b\u0005\u0006Y\"\u0001\r!\u001c\u0005\u0006g\"\u0001\r\u0001\u001e\u0005\u0006o\"\u0001\r\u0001\u001f\u0005\u0007}\"\u0001\r!!\u0001\u0003\tMcw\u000e^\n\u0007\u00139\u000bY#!\r\u0011\u0007=\u000bi#C\u0002\u00020A\u0013q\u0001\u0015:pIV\u001cG\u000f\u0005\u0003\u00024\u0005ub\u0002BA\u001b\u0003sq1\u0001YA\u001c\u0013\u0005\t\u0016bAA\u001e!\u00069\u0001/Y2lC\u001e,\u0017\u0002BA \u0003\u0003\u0012AbU3sS\u0006d\u0017N_1cY\u0016T1!a\u000fQ\u0003\u0011)X/\u001b3\u0016\u0005\u0005\u001d\u0003\u0003BA%\u0003\u001fj!!a\u0013\u000b\t\u00055\u0013\u0011B\u0001\u0005kRLG.\u0003\u0003\u0002R\u0005-#\u0001B+V\u0013\u0012\u000bQ!^;jI\u0002\n\u0011\"\u001a<f]Rd\u0015n\u001d;\u0016\u0005\u0005e\u0003CBA.\u0003K\nI\'\u0004\u0002\u0002^)!\u0011qLA1\u0003\u001diW\u000f^1cY\u0016T1!a\u0019Q\u0003)\u0019w\u000e\u001c7fGRLwN\\\u0005\u0005\u0003O\niF\u0001\u0006MSN$()\u001e4gKJ\u0004B!a\u001b\u0002r5\u0011\u0011Q\u000e\u0006\u0004\u0003_J\u0015AB3wK:$8/\u0003\u0003\u0002t\u00055$!B#wK:$\u0018AC3wK:$H*[:uA\u0005I1m\\7qY\u0016$X\rZ\u000b\u0003\u0003w\u00022aTA?\u0013\r\ty\b\u0015\u0002\b\u0005>|G.Z1o\u0003)\u0019w.\u001c9mKR,G\rI\u0001\u000fG>l\u0007\u000f\\3uK\u0012,e/\u001a8u\u0003=\u0019w.\u001c9mKR,G-\u0012<f]R\u0004\u0013!\u0002:fC\u0012L\u0018A\u0002:fC\u0012L\b\u0005\u0006\u0007\u0002\u000e\u0006E\u00151SAK\u0003/\u000bI\nE\u0002\u0002\u0010&i\u0011\u0001\u0001\u0005\b\u0003\u0007\"\u0002\u0019AA$\u0011\u001d\t)\u0006\u0006a\u0001\u00033Bq!a\u001e\u0015\u0001\u0004\tY\bC\u0004\u0002\u0004R\u0001\r!a\u001f\t\u000f\u0005\u001dE\u00031\u0001\u0002|\u0005!1m\u001c9z)1\ti)a(\u0002\"\u0006\r\u0016QUAT\u0011%\t\u0019%\u0006I\u0001\u0002\u0004\t9\u0005C\u0005\u0002VU\u0001\n\u00111\u0001\u0002Z!I\u0011qO\u000b\u0011\u0002\u0003\u0007\u00111\u0010\u0005\n\u0003\u0007+\u0002\u0013!a\u0001\u0003wB\u0011\"a\"\u0016!\u0003\u0005\r!a\u001f\u0002\u001d\r|\u0007/\u001f\u0013eK\u001a\fW\u000f\u001c;%cU\u0011\u0011Q\u0016\u0016\u0005\u0003\u000f\nyk\u000b\u0002\u00022B!\u00111WA_\u001b\t\t)L\u0003\u0003\u00028\u0006e\u0016!C;oG\",7m[3e\u0015\r\tY\fU\u0001\u000bC:tw\u000e^1uS>t\u0017\u0002BA`\u0003k\u0013\u0011#\u001e8dQ\u0016\u001c7.\u001a3WCJL\u0017M\\2f\u00039\u0019w\u000e]=%I\u00164\u0017-\u001e7uII*\"!!2+\t\u0005e\u0013qV\u0001\u000fG>\u0004\u0018\u0010\n3fM\u0006,H\u000e\u001e\u00134+\t\tYM\u000b\u0003\u0002|\u0005=\u0016AD2paf$C-\u001a4bk2$H\u0005N\u0001\u000fG>\u0004\u0018\u0010\n3fM\u0006,H\u000e\u001e\u00136\u00035\u0001(o\u001c3vGR\u0004&/\u001a4jqV\u0011\u0011Q\u001b\t\u0005\u0003/\fi.\u0004\u0002\u0002Z*!\u00111\\A\u0005\u0003\u0011a\u0017M\\4\n\u0007\u0019\fI.\u0001\u0007qe>$Wo\u0019;Be&$\u00180F\u0001u\u00039\u0001(o\u001c3vGR,E.Z7f]R$B!a:\u0002nB\u0019q*!;\n\u0007\u0005-\bKA\u0002B]fD\u0001\"a<\u001e\u0003\u0003\u0005\r\u0001^\u0001\u0004q\u0012\n\u0014a\u00049s_\u0012,8\r^%uKJ\fGo\u001c:\u0016\u0005\u0005U\bCBA|\u0003s\f9/\u0004\u0002\u0002b%!\u00111`A1\u0005!IE/\u001a:bi>\u0014\u0018\u0001C2b]\u0016\u000bX/\u00197\u0015\t\u0005m$\u0011\u0001\u0005\n\u0003_|\u0012\u0011!a\u0001\u0003O\f!\u0003\u001d:pIV\u001cG/\u00127f[\u0016tGOT1nKR!\u0011Q\u001bB\u0004\u0011!\ty\u000fIA\u0001\u0002\u0004!\u0018\u0001\u00035bg\"\u001cu\u000eZ3\u0015\u0003Q\f\u0001\u0002^8TiJLgn\u001a\u000b\u0003\u0003+\fa!Z9vC2\u001cH\u0003BA>\u0005+A\u0011\"a<$\u0003\u0003\u0005\r!a:\u0002\tMcw\u000e\u001e\t\u0004\u0003\u001f+3#B\u0013\u0003\u001e\t%\u0002\u0003\u0005B\u0010\u0005K\t9%!\u0017\u0002|\u0005m\u00141PAG\u001b\t\u0011\tCC\u0002\u0003$A\u000bqA];oi&lW-\u0003\u0003\u0003(\t\u0005\"!E!cgR\u0014\u0018m\u0019;Gk:\u001cG/[8okA!\u00111\u0001B\u0016\u0013\u0011\ty$!\u0002\u0015\u0005\te\u0011!B1qa2LH\u0003DAG\u0005g\u0011)Da\u000e\u0003:\tm\u0002bBA\"Q\u0001\u0007\u0011q\t\u0005\b\u0003+B\u0003\u0019AA-\u0011\u001d\t9\b\u000ba\u0001\u0003wBq!a!)\u0001\u0004\tY\bC\u0004\u0002\b\"\u0002\r!a\u001f\u0002\u000fUt\u0017\r\u001d9msR!!\u0011\tB%!\u0011y\u0015Pa\u0011\u0011\u001b=\u0013)%a\u0012\u0002Z\u0005m\u00141PA>\u0013\r\u00119\u0005\u0015\u0002\u0007)V\u0004H.Z\u001b\t\u0013\t-\u0013&!AA\u0002\u00055\u0015a\u0001=%a\u0005iq/Y5uS:<\')\u001e4gKJ,\"A!\u0015\u0011\r\u0005m\u0013QMAG\u000399\u0018-\u001b;j]\u001e\u0014UO\u001a4fe\u0002\nqa\u001d7pi6\u000b\u0007/\u0006\u0002\u0003ZA9\u00111\fB.;\u00065\u0015\u0002\u0002B/\u0003;\u0012q\u0001S1tQ6\u000b\u0007/\u0001\u0005tY>$X*\u00199!\u0003I\u0019w.\u001c9mKR,G\rV3ti\u000e{WO\u001c;\u0002-\r|W\u000e\u001d7fi\u0016$G+Z:u\u0007>,h\u000e^0%KF$BAa\u001a\u0003nA\u0019qJ!\u001b\n\u0007\t-\u0004K\u0001\u0003V]&$\b\u0002CAx_\u0005\u0005\t\u0019\u0001;\u0002\'\r|W\u000e\u001d7fi\u0016$G+Z:u\u0007>,h\u000e\u001e\u0011)\u0007A\u0012\u0019\bE\u0002P\u0005kJ1Aa\u001eQ\u0005!1x\u000e\\1uS2,\'a\u0003+j[\u0016|W\u000f\u001e+bg.\u001cR!\rB?\u0005\u0007\u0003B!a6\u0003\u0000%!!\u0011QAm\u0005\u0019y%M[3diB\u0019QK!\"\n\u0007\t\u001d\u0015JA\u0005US6,\'\u000fV1tW\u0006!1\u000f\\8u+\t\ti)A\u0003tY>$\b\u0005\u0006\u0003\u0003\u0012\nM\u0005cAAHc!9!\u0011\u0012\u001bA\u0002\u00055\u0015a\u0001:v]R\u0011!qM\u0001\fi&lWm\\;u)\u0006\u001c8.\u0006\u0002\u0003\u001eB!q*\u001fBP!\u001dy%\u0011\u0015BI\u0005KK1Aa)Q\u0005\u0019!V\u000f\u001d7feA\u0019QKa*\n\u0007\t%\u0016JA\u0003US6,\'/A\buS6,w.\u001e;UCN\\w\fJ3r)\u0011\u00119Ga,\t\u0013\u0005=x\'!AA\u0002\tu\u0015\u0001\u0004;j[\u0016|W\u000f\u001e+bg.\u0004\u0013\u0001\u00053jgR\u0014\u0018NY;uS:<G+Z:u)\u0011\u00119Ga.\t\r\te\u0016\b1\u0001^\u0003!!Xm\u001d;OC6,GC\u0002B4\u0005{\u0013y\f\u0003\u0004\u0003:j\u0002\r!\u0018\u0005\b\u0005\u0003T\u0004\u0019AA5\u0003\u0015)g/\u001a8u\u00035\u0019w.\u001c9mKR,G\rV3tiR!!q\rBd\u0011\u0019\u0011Il\u000fa\u0001;\u0006\u00192\r[3dW\u000e{W\u000e\u001d7fi\u0016$G+Z:ug\u00069Am\\!qa2LH\u0003\u0002B4\u0005\u001fDqA!1>\u0001\u0004\tI\'\u0001\tiC:$G.Z*vSR,WI^3oiR!!q\rBk\u0011\u001d\u0011\tM\u0010a\u0001\u0003S\n1\u0003[1oI2,G+Z:u\u0007>l\u0007\u000f\\3uK\u0012$bAa\u001a\u0003\\\nu\u0007b\u0002Ba\u007f\u0001\u0007\u0011\u0011\u000e\u0005\u0007\u0005s{\u0004\u0019A/\u0002\u001d\u0019L\'/Z*m_R,e/\u001a8ugR!!q\rBr\u0011\u001d\u0011I\t\u0011a\u0001\u0003\u001bC3\u0001\u0011Bt!\u0011\u0011IOa;\u000e\u0005\u0005e\u0016\u0002\u0002Bw\u0003s\u0013q\u0001^1jYJ,7-A\bgSJ,\'+Z1es\u00163XM\u001c;tQ\r\t%q]\u0001\u0014g\u000eDW\rZ;mKRKW.Z8viR\u000b7o[\u0001\u0012G\u0006t7-\u001a7US6,w.\u001e;UCN\\\u0017a\u0002;j[\u0016|W\u000f^\u0001\nI>$\u0015n\u001d9pg\u0016\u0004"
    )
  ScalaInlineInfo: length = 0x81 (unknown attribute)
   01 00 00 19 00 83 01 C1 00 00 14 00 43 01 00 46
   00 3E 01 00 33 00 C9 00 00 33 00 34 00 01 7B 00
   3E 01 01 0D 00 3E 01 00 E6 00 62 00 00 30 00 54
   01 00 57 00 58 01 00 3D 00 3E 00 00 61 00 62 00
   01 39 00 34 00 01 B4 00 3E 00 00 D9 00 3E 01 01
   6D 01 6E 01 01 5C 00 34 01 01 4D 01 4E 01 01 B1
   00 3E 01 00 28 00 49 00 00 C2 00 3E 01 00 2D 00
   50 01 00 31 00 5A 01 00 5E 00 5F 01 00 2A 00 4C
   01
  ScalaSig: length = 0x3 (unknown attribute)
   05 02 00
