Classfile /Users/mw/Projects/slang-braindump/.jar/jar11/assemble/slang-braindump/assemble/content/scala/collection/parallel/immutable/HashMapCombiner$.class
  Last modified May 29, 2022; size 1067 bytes
  SHA-256 checksum 3fef22bf4985741a38fd0a7e1a8004e3bd8af2c30103cd8e3ea22b280d309c97
  Compiled from "ParHashMap.scala"
public final class scala.collection.parallel.immutable.HashMapCombiner$
  minor version: 0
  major version: 52
  flags: (0x0031) ACC_PUBLIC, ACC_FINAL, ACC_SUPER
  this_class: #2                          // scala/collection/parallel/immutable/HashMapCombiner$
  super_class: #4                         // java/lang/Object
  interfaces: 0, fields: 3, methods: 5, attributes: 4
Constant pool:
   #1 = Utf8               scala/collection/parallel/immutable/HashMapCombiner$
   #2 = Class              #1             // scala/collection/parallel/immutable/HashMapCombiner$
   #3 = Utf8               java/lang/Object
   #4 = Class              #3             // java/lang/Object
   #5 = Utf8               ParHashMap.scala
   #6 = Utf8               scala/collection/parallel/immutable/HashMapCombiner$$anon$1
   #7 = Class              #6             // scala/collection/parallel/immutable/HashMapCombiner$$anon$1
   #8 = Utf8               MODULE$
   #9 = Utf8               Lscala/collection/parallel/immutable/HashMapCombiner$;
  #10 = Utf8               rootbits
  #11 = Utf8               I
  #12 = Utf8               rootsize
  #13 = Utf8               <clinit>
  #14 = Utf8               ()V
  #15 = Utf8               <init>
  #16 = NameAndType        #15:#14        // "<init>":()V
  #17 = Methodref          #2.#16         // scala/collection/parallel/immutable/HashMapCombiner$."<init>":()V
  #18 = NameAndType        #8:#9          // MODULE$:Lscala/collection/parallel/immutable/HashMapCombiner$;
  #19 = Fieldref           #2.#18         // scala/collection/parallel/immutable/HashMapCombiner$.MODULE$:Lscala/collection/parallel/immutable/HashMapCombiner$;
  #20 = NameAndType        #10:#11        // rootbits:I
  #21 = Fieldref           #2.#20         // scala/collection/parallel/immutable/HashMapCombiner$.rootbits:I
  #22 = NameAndType        #12:#11        // rootsize:I
  #23 = Fieldref           #2.#22         // scala/collection/parallel/immutable/HashMapCombiner$.rootsize:I
  #24 = Utf8               apply
  #25 = Utf8               ()Lscala/collection/parallel/immutable/HashMapCombiner;
  #26 = Utf8               <K:Ljava/lang/Object;V:Ljava/lang/Object;>()Lscala/collection/parallel/immutable/HashMapCombiner<TK;TV;>;
  #27 = Methodref          #7.#16         // scala/collection/parallel/immutable/HashMapCombiner$$anon$1."<init>":()V
  #28 = Utf8               this
  #29 = Utf8               ()I
  #30 = Methodref          #4.#16         // java/lang/Object."<init>":()V
  #31 = Utf8               Code
  #32 = Utf8               LineNumberTable
  #33 = Utf8               LocalVariableTable
  #34 = Utf8               Signature
  #35 = Utf8               InnerClasses
  #36 = Utf8               SourceFile
  #37 = Utf8               ScalaInlineInfo
  #38 = Utf8               Scala
{
  public static final scala.collection.parallel.immutable.HashMapCombiner$ MODULE$;
    descriptor: Lscala/collection/parallel/immutable/HashMapCombiner$;
    flags: (0x0019) ACC_PUBLIC, ACC_STATIC, ACC_FINAL

  private static final int rootbits;
    descriptor: I
    flags: (0x001a) ACC_PRIVATE, ACC_STATIC, ACC_FINAL

  private static final int rootsize;
    descriptor: I
    flags: (0x001a) ACC_PRIVATE, ACC_STATIC, ACC_FINAL

  public static {};
    descriptor: ()V
    flags: (0x0009) ACC_PUBLIC, ACC_STATIC
    Code:
      stack=2, locals=0, args_size=0
         0: new           #2                  // class scala/collection/parallel/immutable/HashMapCombiner$
         3: dup
         4: invokespecial #17                 // Method "<init>":()V
         7: putstatic     #19                 // Field MODULE$:Lscala/collection/parallel/immutable/HashMapCombiner$;
        10: iconst_5
        11: putstatic     #21                 // Field rootbits:I
        14: bipush        32
        16: putstatic     #23                 // Field rootsize:I
        19: return
      LineNumberTable:
        line 331: 0
        line 334: 10
        line 335: 14
        line 331: 19

  public <K extends java.lang.Object, V extends java.lang.Object> scala.collection.parallel.immutable.HashMapCombiner<K, V> apply();
    descriptor: ()Lscala/collection/parallel/immutable/HashMapCombiner;
    flags: (0x0001) ACC_PUBLIC
    Code:
      stack=2, locals=1, args_size=1
         0: new           #7                  // class scala/collection/parallel/immutable/HashMapCombiner$$anon$1
         3: dup
         4: invokespecial #27                 // Method scala/collection/parallel/immutable/HashMapCombiner$$anon$1."<init>":()V
         7: areturn
      LineNumberTable:
        line 332: 0
      LocalVariableTable:
        Start  Length  Slot  Name   Signature
            0       8     0  this   Lscala/collection/parallel/immutable/HashMapCombiner$;
    Signature: #26                          // <K:Ljava/lang/Object;V:Ljava/lang/Object;>()Lscala/collection/parallel/immutable/HashMapCombiner<TK;TV;>;

  public int rootbits();
    descriptor: ()I
    flags: (0x0001) ACC_PUBLIC
    Code:
      stack=1, locals=1, args_size=1
         0: getstatic     #21                 // Field rootbits:I
         3: ireturn
      LineNumberTable:
        line 334: 0
      LocalVariableTable:
        Start  Length  Slot  Name   Signature
            0       4     0  this   Lscala/collection/parallel/immutable/HashMapCombiner$;

  public int rootsize();
    descriptor: ()I
    flags: (0x0001) ACC_PUBLIC
    Code:
      stack=1, locals=1, args_size=1
         0: getstatic     #23                 // Field rootsize:I
         3: ireturn
      LineNumberTable:
        line 335: 0
      LocalVariableTable:
        Start  Length  Slot  Name   Signature
            0       4     0  this   Lscala/collection/parallel/immutable/HashMapCombiner$;

  private scala.collection.parallel.immutable.HashMapCombiner$();
    descriptor: ()V
    flags: (0x0002) ACC_PRIVATE
    Code:
      stack=1, locals=1, args_size=1
         0: aload_0
         1: invokespecial #30                 // Method java/lang/Object."<init>":()V
         4: return
      LineNumberTable:
        line 336: 0
        line 331: 4
      LocalVariableTable:
        Start  Length  Slot  Name   Signature
            0       5     0  this   Lscala/collection/parallel/immutable/HashMapCombiner$;
}
InnerClasses:
  public final #7;                        // class scala/collection/parallel/immutable/HashMapCombiner$$anon$1
SourceFile: "ParHashMap.scala"
  ScalaInlineInfo: length = 0x18 (unknown attribute)
   01 01 00 04 00 0F 00 0E 01 00 18 00 19 01 00 0A
   00 1D 01 00 0C 00 1D 01
  Scala: length = 0x0 (unknown attribute)

