Classfile /Users/mw/Projects/slang-braindump/.jar/jar11/assemble/slang-braindump/assemble/content/scala/collection/parallel/immutable/package$.class
  Last modified May 29, 2022; size 904 bytes
  SHA-256 checksum 3e18f4b55acb6f4a6cdd99aeb13617bce2deb74ebed10f418e265ce520bfec5e
  Compiled from "package.scala"
public final class scala.collection.parallel.immutable.package$
  minor version: 0
  major version: 52
  flags: (0x0031) ACC_PUBLIC, ACC_FINAL, ACC_SUPER
  this_class: #2                          // scala/collection/parallel/immutable/package$
  super_class: #4                         // java/lang/Object
  interfaces: 0, fields: 1, methods: 3, attributes: 3
Constant pool:
   #1 = Utf8               scala/collection/parallel/immutable/package$
   #2 = Class              #1             // scala/collection/parallel/immutable/package$
   #3 = Utf8               java/lang/Object
   #4 = Class              #3             // java/lang/Object
   #5 = Utf8               package.scala
   #6 = Utf8               MODULE$
   #7 = Utf8               Lscala/collection/parallel/immutable/package$;
   #8 = Utf8               <clinit>
   #9 = Utf8               ()V
  #10 = Utf8               <init>
  #11 = NameAndType        #10:#9         // "<init>":()V
  #12 = Methodref          #2.#11         // scala/collection/parallel/immutable/package$."<init>":()V
  #13 = NameAndType        #6:#7          // MODULE$:Lscala/collection/parallel/immutable/package$;
  #14 = Fieldref           #2.#13         // scala/collection/parallel/immutable/package$.MODULE$:Lscala/collection/parallel/immutable/package$;
  #15 = Utf8               repetition
  #16 = Utf8               (Ljava/lang/Object;I)Lscala/collection/parallel/immutable/Repetition;
  #17 = Utf8               <T:Ljava/lang/Object;>(TT;I)Lscala/collection/parallel/immutable/Repetition<TT;>;
  #18 = Utf8               elem
  #19 = Utf8               len
  #20 = Utf8               scala/collection/parallel/immutable/Repetition
  #21 = Class              #20            // scala/collection/parallel/immutable/Repetition
  #22 = Utf8               (Ljava/lang/Object;I)V
  #23 = NameAndType        #10:#22        // "<init>":(Ljava/lang/Object;I)V
  #24 = Methodref          #21.#23        // scala/collection/parallel/immutable/Repetition."<init>":(Ljava/lang/Object;I)V
  #25 = Utf8               this
  #26 = Utf8               Ljava/lang/Object;
  #27 = Utf8               I
  #28 = Methodref          #4.#11         // java/lang/Object."<init>":()V
  #29 = Utf8               Code
  #30 = Utf8               LineNumberTable
  #31 = Utf8               LocalVariableTable
  #32 = Utf8               Signature
  #33 = Utf8               MethodParameters
  #34 = Utf8               SourceFile
  #35 = Utf8               ScalaInlineInfo
  #36 = Utf8               Scala
{
  public static final scala.collection.parallel.immutable.package$ MODULE$;
    descriptor: Lscala/collection/parallel/immutable/package$;
    flags: (0x0019) ACC_PUBLIC, ACC_STATIC, ACC_FINAL

  public static {};
    descriptor: ()V
    flags: (0x0009) ACC_PUBLIC, ACC_STATIC
    Code:
      stack=2, locals=0, args_size=0
         0: new           #2                  // class scala/collection/parallel/immutable/package$
         3: dup
         4: invokespecial #12                 // Method "<init>":()V
         7: putstatic     #14                 // Field MODULE$:Lscala/collection/parallel/immutable/package$;
        10: return
      LineNumberTable:
        line 55: 0

  public <T extends java.lang.Object> scala.collection.parallel.immutable.Repetition<T> repetition(T, int);
    descriptor: (Ljava/lang/Object;I)Lscala/collection/parallel/immutable/Repetition;
    flags: (0x0001) ACC_PUBLIC
    Code:
      stack=4, locals=3, args_size=3
         0: new           #21                 // class scala/collection/parallel/immutable/Repetition
         3: dup
         4: aload_1
         5: iload_2
         6: invokespecial #24                 // Method scala/collection/parallel/immutable/Repetition."<init>":(Ljava/lang/Object;I)V
         9: areturn
      LineNumberTable:
        line 57: 0
      LocalVariableTable:
        Start  Length  Slot  Name   Signature
            0      10     0  this   Lscala/collection/parallel/immutable/package$;
            0      10     1  elem   Ljava/lang/Object;
            0      10     2   len   I
    Signature: #17                          // <T:Ljava/lang/Object;>(TT;I)Lscala/collection/parallel/immutable/Repetition<TT;>;
    MethodParameters:
      Name                           Flags
      elem                           final
      len                            final

  private scala.collection.parallel.immutable.package$();
    descriptor: ()V
    flags: (0x0002) ACC_PRIVATE
    Code:
      stack=1, locals=1, args_size=1
         0: aload_0
         1: invokespecial #28                 // Method java/lang/Object."<init>":()V
         4: return
      LineNumberTable:
        line 58: 0
        line 55: 4
      LocalVariableTable:
        Start  Length  Slot  Name   Signature
            0       5     0  this   Lscala/collection/parallel/immutable/package$;
}
SourceFile: "package.scala"
  ScalaInlineInfo: length = 0xE (unknown attribute)
   01 01 00 02 00 0A 00 09 01 00 0F 00 10 01
  Scala: length = 0x0 (unknown attribute)

