Classfile /Users/mw/Projects/slang-braindump/.jar/jar11/assemble/slang-braindump/assemble/content/scala/collection/parallel/immutable/ParRange$ParRangeIterator$.class
  Last modified May 29, 2022; size 866 bytes
  SHA-256 checksum 2de53668cd6c075913011aa991767ded65874010a4eff2e721c981b23e997504
  Compiled from "ParRange.scala"
public class scala.collection.parallel.immutable.ParRange$ParRangeIterator$
  minor version: 0
  major version: 52
  flags: (0x0021) ACC_PUBLIC, ACC_SUPER
  this_class: #2                          // scala/collection/parallel/immutable/ParRange$ParRangeIterator$
  super_class: #4                         // java/lang/Object
  interfaces: 0, fields: 1, methods: 2, attributes: 4
Constant pool:
   #1 = Utf8               scala/collection/parallel/immutable/ParRange$ParRangeIterator$
   #2 = Class              #1             // scala/collection/parallel/immutable/ParRange$ParRangeIterator$
   #3 = Utf8               java/lang/Object
   #4 = Class              #3             // java/lang/Object
   #5 = Utf8               ParRange.scala
   #6 = Utf8               scala/collection/parallel/immutable/ParRange
   #7 = Class              #6             // scala/collection/parallel/immutable/ParRange
   #8 = Utf8               ParRangeIterator$
   #9 = Utf8               $outer
  #10 = Utf8               Lscala/collection/parallel/immutable/ParRange;
  #11 = Utf8               $lessinit$greater$default$1
  #12 = Utf8               ()Lscala/collection/immutable/Range;
  #13 = NameAndType        #9:#10         // $outer:Lscala/collection/parallel/immutable/ParRange;
  #14 = Fieldref           #2.#13         // scala/collection/parallel/immutable/ParRange$ParRangeIterator$.$outer:Lscala/collection/parallel/immutable/ParRange;
  #15 = Utf8               range
  #16 = NameAndType        #15:#12        // range:()Lscala/collection/immutable/Range;
  #17 = Methodref          #7.#16         // scala/collection/parallel/immutable/ParRange.range:()Lscala/collection/immutable/Range;
  #18 = Utf8               this
  #19 = Utf8               Lscala/collection/parallel/immutable/ParRange$ParRangeIterator$;
  #20 = Utf8               <init>
  #21 = Utf8               (Lscala/collection/parallel/immutable/ParRange;)V
  #22 = Utf8               ()V
  #23 = NameAndType        #20:#22        // "<init>":()V
  #24 = Methodref          #4.#23         // java/lang/Object."<init>":()V
  #25 = Utf8               Code
  #26 = Utf8               LineNumberTable
  #27 = Utf8               LocalVariableTable
  #28 = Utf8               StackMapTable
  #29 = Utf8               MethodParameters
  #30 = Utf8               InnerClasses
  #31 = Utf8               SourceFile
  #32 = Utf8               ScalaInlineInfo
  #33 = Utf8               Scala
{
  private final scala.collection.parallel.immutable.ParRange $outer;
    descriptor: Lscala/collection/parallel/immutable/ParRange;
    flags: (0x1012) ACC_PRIVATE, ACC_FINAL, ACC_SYNTHETIC

  public scala.collection.immutable.Range $lessinit$greater$default$1();
    descriptor: ()Lscala/collection/immutable/Range;
    flags: (0x0001) ACC_PUBLIC
    Code:
      stack=1, locals=1, args_size=1
         0: aload_0
         1: getfield      #14                 // Field $outer:Lscala/collection/parallel/immutable/ParRange;
         4: invokevirtual #17                 // Method scala/collection/parallel/immutable/ParRange.range:()Lscala/collection/immutable/Range;
         7: areturn
      LineNumberTable:
        line 51: 0
      LocalVariableTable:
        Start  Length  Slot  Name   Signature
            0       8     0  this   Lscala/collection/parallel/immutable/ParRange$ParRangeIterator$;

  public scala.collection.parallel.immutable.ParRange$ParRangeIterator$(scala.collection.parallel.immutable.ParRange);
    descriptor: (Lscala/collection/parallel/immutable/ParRange;)V
    flags: (0x0001) ACC_PUBLIC
    Code:
      stack=2, locals=2, args_size=2
         0: aload_1
         1: ifnonnull     6
         4: aconst_null
         5: athrow
         6: aload_0
         7: aload_1
         8: putfield      #14                 // Field $outer:Lscala/collection/parallel/immutable/ParRange;
        11: aload_0
        12: invokespecial #24                 // Method java/lang/Object."<init>":()V
        15: return
      StackMapTable: number_of_entries = 1
        frame_type = 6 /* same */
      LineNumberTable:
        line 51: 0
      LocalVariableTable:
        Start  Length  Slot  Name   Signature
            0      16     0  this   Lscala/collection/parallel/immutable/ParRange$ParRangeIterator$;
            0      16     1 $outer   Lscala/collection/parallel/immutable/ParRange;
    MethodParameters:
      Name                           Flags
      $outer                         final synthetic
}
InnerClasses:
  public #8= #2 of #7;                    // ParRangeIterator$=class scala/collection/parallel/immutable/ParRange$ParRangeIterator$ of class scala/collection/parallel/immutable/ParRange
SourceFile: "ParRange.scala"
  ScalaInlineInfo: length = 0xE (unknown attribute)
   01 01 00 02 00 0B 00 0C 01 00 14 00 15 01
  Scala: length = 0x0 (unknown attribute)

