Classfile /Users/mw/Projects/slang-braindump/.jar/jar11/assemble/slang-braindump/assemble/content/coursier/credentials/DirectCredentials.class
  Last modified May 29, 2022; size 19695 bytes
  SHA-256 checksum b44b6a2467c6a07e9427c1a3b4bc851b583266f7d7f7e21d957491ec19e3d15a
  Compiled from "DirectCredentials.scala"
public final class coursier.credentials.DirectCredentials extends coursier.credentials.Credentials implements scala.Product
  minor version: 0
  major version: 52
  flags: (0x0031) ACC_PUBLIC, ACC_FINAL, ACC_SUPER
  this_class: #2                          // coursier/credentials/DirectCredentials
  super_class: #4                         // coursier/credentials/Credentials
  interfaces: 1, fields: 8, methods: 61, attributes: 6
Constant pool:
    #1 = Utf8               coursier/credentials/DirectCredentials
    #2 = Class              #1            // coursier/credentials/DirectCredentials
    #3 = Utf8               coursier/credentials/Credentials
    #4 = Class              #3            // coursier/credentials/Credentials
    #5 = Utf8               scala/Product
    #6 = Class              #5            // scala/Product
    #7 = Utf8               DirectCredentials.scala
    #8 = Utf8               Lscala/reflect/ScalaSignature;
    #9 = Utf8               bytes
   #10 = Utf8               \u0006\u0005\t\u0015d\u0001\u0002\u001f>\u0005\tC\u0001\"\u0017\u0001\u0003\u0006\u0004%\tA\u0017\u0005\tG\u0002\u0011\t\u0011)A\u00057\"AA\r\u0001BC\u0002\u0013\u0005Q\r\u0003\u0005j\u0001\t\u0005\t\u0015!\u0003g\u0011!Q\u0007A!b\u0001\n\u0003Y\u0007\u0002\u00039\u0001\u0005\u0003\u0005\u000b\u0011\u00027\t\u0011E\u0004!Q1A\u0005\u0002\u0015D\u0001B\u001d\u0001\u0003\u0002\u0003\u0006IA\u001a\u0005\tg\u0002\u0011)\u0019!C\u0001i\"A\u0001\u0010\u0001B\u0001B\u0003%Q\u000f\u0003\u0005z\u0001\t\u0015\r\u0011\"\u0001u\u0011!Q\bA!A!\u0002\u0013)\b\u0002C>\u0001\u0005\u000b\u0007I\u0011\u0001;\t\u0011q\u0004!\u0011!Q\u0001\nUD\u0001\" \u0001\u0003\u0006\u0004%\t\u0001\u001e\u0005\t}\u0002\u0011\t\u0011)A\u0005k\"1q\u0010\u0001C\u0001\u0003\u0003Aaa \u0001\u0005\u0002\u0005U\u0001BB@\u0001\t\u0003\t\t\u0003\u0003\u0004\u0000\u0001\u0011\u0005\u00111\u0006\u0005\u0007\u007f\u0002!\t!a\r\t\u000f\u0005U\u0002\u0001\"\u0001\u00028!9\u0011Q\b\u0001\u0005\u0002\u0005}\u0002bBA#\u0001\u0011\u0005\u0011q\t\u0005\u0007\u0003\u0017\u0002A\u0011\u0002;\t\u000f\u00055\u0003\u0001\"\u0001\u0002P!9\u0011\u0011\f\u0001\u0005\u0002\u0005m\u0003bBA2\u0001\u0011\u0005\u0011Q\r\u0005\b\u0003g\u0002A\u0011AA;\u0011\u001d\ti\b\u0001C\u0001\u0003\u007fBq!a!\u0001\t\u0003\t)\tC\u0004\u0002\n\u0002!\t!a#\t\u000f\u0005\u0015\u0003\u0001\"\u0001\u0002\u0010\"9\u00111\u0013\u0001\u0005\u0002\u0005U\u0005bBAM\u0001\u0011\u0005\u00111\u0014\u0005\b\u0003?\u0003A\u0011AAQ\u0011\u001d\t)\u000b\u0001C\u0001\u0003OCq!a+\u0001\t\u0003\ni\u000bC\u0004\u0002>\u0002!\t%a0\t\u000f\u0005-\u0007\u0001\"\u0011\u0002N\"9\u0011\u0011\u001b\u0001\u0005B\u0005M\u0007bBAn\u0001\u0011%\u0011Q\u001c\u0005\b\u0003K\u0004A\u0011IAt\u0011\u001d\tI\u000f\u0001C!\u0003WDq!!<\u0001\t\u0003\ny\u000fC\u0004\u0002v\u0002!\t%a>\b\u000f\u0005mX\b#\u0001\u0002~\u001a1A(\u0010E\u0001\u0003\u007fDaa \u0019\u0005\u0002\tE\u0001b\u0002B\na\u0011\u0005!Q\u0003\u0005\b\u0005\'\u0001D\u0011\u0001B\u000f\u0011\u0019\u00119\u0003\rC\u0001i\"1!\u0011\u0006\u0019\u0005\u0002QDqAa\u00051\t\u0003\t\u0019\u0004C\u0004\u0003\u0014A\"\tAa\u000b\t\u000f\tM\u0001\u0007\"\u0001\u00034!9!1\u0003\u0019\u0005\u0002\tu\u0002b\u0002B\na\u0011\u0005!\u0011\n\u0005\n\u00057\u0002\u0014\u0011!C\u0005\u0005;\u0012\u0011\u0003R5sK\u000e$8I]3eK:$\u0018.\u00197t\u0015\tqt(A\u0006de\u0016$WM\u001c;jC2\u001c(\"\u0001!\u0002\u0011\r|WO]:jKJ\u001c\u0001a\u0005\u0003\u0001\u0007\u001ek\u0005C\u0001#F\u001b\u0005i\u0014B\u0001$>\u0005-\u0019%/\u001a3f]RL\u0017\r\\:\u0011\u0005![U\"A%\u000b\u0003)\u000bQa]2bY\u0006L!\u0001T%\u0003\u000fA\u0013x\u000eZ;diB\u0011aJ\u0016\b\u0003\u001fRs!\u0001U*\u000e\u0003ES!AU!\u0002\rq\u0012xn\u001c;?\u0013\u0005Q\u0015BA+J\u0003\u001d\u0001\u0018mY6bO\u0016L!a\u0016-\u0003\u0019M+\'/[1mSj\f\'\r\\3\u000b\u0005UK\u0015\u0001\u00025pgR,\u0012a\u0017\t\u00039\u0002t!!\u00180\u0011\u0005AK\u0015BA0J\u0003\u0019\u0001&/\u001a3fM&\u0011\u0011M\u0019\u0002\u0007\'R\u0014\u0018N\\4\u000b\u0005}K\u0015!\u00025pgR\u0004\u0013aC;tKJt\u0017-\\3PaR,\u0012A\u001a\t\u0004\u0011\u001e\\\u0016B\u00015J\u0005\u0019y\u0005\u000f^5p]\u0006aQo]3s]\u0006lWm\u00149uA\u0005Y\u0001/Y:to>\u0014Hm\u00149u+\u0005a\u0007c\u0001%h[B\u0019AI\\.\n\u0005=l$\u0001\u0003)bgN<xN\u001d3\u0002\u0019A\f7o]<pe\u0012|\u0005\u000f\u001e\u0011\u0002\u000bI,\u0017\r\\7\u0002\rI,\u0017\r\\7!\u0003!y\u0007\u000f^5p]\u0006dW#A;\u0011\u0005!3\u0018BA<J\u0005\u001d\u0011un\u001c7fC:\f\u0011b\u001c9uS>t\u0017\r\u001c\u0011\u0002\u00135\fGo\u00195I_N$\u0018AC7bi\u000eD\u0007j\\:uA\u0005I\u0001\u000e\u001e;qg>sG._\u0001\u000bQR$\bo](oYf\u0004\u0013A\u00049bgN|eNU3eSJ,7\r^\u0001\u0010a\u0006\u001c8o\u00148SK\u0012L\'/Z2uA\u00051A(\u001b8jiz\"\"#a\u0001\u0002\u0006\u0005\u001d\u0011\u0011BA\u0006\u0003\u001b\ty!!\u0005\u0002\u0014A\u0011A\t\u0001\u0005\u00063F\u0001\ra\u0017\u0005\u0006IF\u0001\rA\u001a\u0005\u0006UF\u0001\r\u0001\u001c\u0005\u0006cF\u0001\rA\u001a\u0005\u0006gF\u0001\r!\u001e\u0005\u0006sF\u0001\r!\u001e\u0005\u0006wF\u0001\r!\u001e\u0005\u0006{F\u0001\r!\u001e\u000b\r\u0003\u0007\t9\"!\u0007\u0002\u001c\u0005u\u0011q\u0004\u0005\u00063J\u0001\ra\u0017\u0005\u0006IJ\u0001\rA\u001a\u0005\u0006UJ\u0001\r\u0001\u001c\u0005\u0006cJ\u0001\rA\u001a\u0005\u0006gJ\u0001\r!\u001e\u000b\u000b\u0003\u0007\t\u0019#!\n\u0002(\u0005%\u0002\"B-\u0014\u0001\u0004Y\u0006\"\u00023\u0014\u0001\u00041\u0007\"\u00026\u0014\u0001\u0004a\u0007\"B9\u0014\u0001\u00041G\u0003CA\u0002\u0003[\ty#!\r\t\u000be#\u0002\u0019A.\t\u000b\u0011$\u0002\u0019\u00014\t\u000b)$\u0002\u0019\u00017\u0015\u0005\u0005\r\u0011\u0001D<ji\",6/\u001a:oC6,G\u0003BA\u0002\u0003sAa!a\u000f\u0017\u0001\u0004Y\u0016\u0001C;tKJt\u0017-\\3\u0002\u0019]LG\u000f\u001b)bgN<xN\u001d3\u0015\t\u0005\r\u0011\u0011\t\u0005\u0007\u0003\u0007:\u0002\u0019A.\u0002\u0011A\f7o]<pe\u0012\f\u0011b^5uQJ+\u0017\r\\7\u0015\t\u0005\r\u0011\u0011\n\u0005\u0006cb\u0001\raW\u0001\t]>tW)\u001c9us\u0006Y\u0011-\u001e;p\u001b\u0006$8\r[3t)\u0015)\u0018\u0011KA+\u0011\u0019\t\u0019F\u0007a\u00017\u0006\u0019QO\u001d7\t\r\u0005]#\u00041\u0001g\u0003\u0019\u0011X-\u00197na\u00059Q.\u0019;dQ\u0016\u001cH#B;\u0002^\u0005}\u0003BBA*7\u0001\u00071\f\u0003\u0004\u0002bm\u0001\raW\u0001\u0005kN,\'/\u0001\bbkRDWM\u001c;jG\u0006$\u0018n\u001c8\u0016\u0005\u0005\u001d\u0004\u0003BA5\u0003_j!!a\u001b\u000b\u0007\u00055t(\u0001\u0003d_J,\u0017\u0002BA9\u0003W\u0012a\"Q;uQ\u0016tG/[2bi&|g.A\u0002hKR$\"!a\u001e\u0011\u000b9\u000bI(a\u0001\n\u0007\u0005m\u0004LA\u0002TKF\f\u0001b^5uQ\"{7\u000f\u001e\u000b\u0005\u0003\u0007\t\t\tC\u0003Z=\u0001\u00071,A\bxSRDWk]3s]\u0006lWm\u00149u)\u0011\t\u0019!a\"\t\u000b\u0011|\u0002\u0019\u00014\u0002\u001f]LG\u000f\u001b)bgN<xN\u001d3PaR$B!a\u0001\u0002\u000e\")!\u000e\ta\u0001YR!\u00111AAI\u0011\u0015\t\u0018\u00051\u0001g\u000319\u0018\u000e\u001e5PaRLwN\\1m)\u0011\t\u0019!a&\t\u000bM\u0014\u0003\u0019A;\u0002\u001b]LG\u000f[\'bi\u000eD\u0007j\\:u)\u0011\t\u0019!!(\t\u000be\u001c\u0003\u0019A;\u0002\u001b]LG\u000f\u001b%uiB\u001cxJ\u001c7z)\u0011\t\u0019!a)\t\u000bm$\u0003\u0019A;\u0002%]LG\u000f\u001b)bgN|eNU3eSJ,7\r\u001e\u000b\u0005\u0003\u0007\tI\u000bC\u0003~K\u0001\u0007Q/\u0001\u0005u_N#(/\u001b8h)\t\ty\u000b\u0005\u0003\u00022\u0006mVBAAZ\u0015\u0011\t),a.\u0002\t1\fgn\u001a\u0006\u0003\u0003s\u000bAA[1wC&\u0019\u0011-a-\u0002\u0011\r\fg.R9vC2$2!^Aa\u0011\u001d\t\u0019m\na\u0001\u0003\u000b\f1a\u001c2k!\rA\u0015qY\u0005\u0004\u0003\u0013L%aA!os\u00061Q-];bYN$2!^Ah\u0011\u001d\t\u0019\r\u000ba\u0001\u0003\u000b\f\u0001\u0002[1tQ\u000e{G-\u001a\u000b\u0003\u0003+\u00042\u0001SAl\u0013\r\tI.\u0013\u0002\u0004\u0013:$\u0018!\u0002;va2,WCAAp!-A\u0015\u0011].gY\u001a,X/^;\n\u0007\u0005\r\u0018J\u0001\u0004UkBdW\rO\u0001\u000eaJ|G-^2u!J,g-\u001b=\u0016\u0005\u0005=\u0016\u0001\u00049s_\u0012,8\r^!sSRLXCAAk\u00039\u0001(o\u001c3vGR,E.Z7f]R$B!!2\u0002r\"9\u00111_\u0017A\u0002\u0005U\u0017!\u00018\u0002%A\u0014x\u000eZ;di\u0016cW-\\3oi:\u000bW.\u001a\u000b\u0005\u0003_\u000bI\u0010C\u0004\u0002t:\u0002\r!!6\u0002#\u0011K\'/Z2u\u0007J,G-\u001a8uS\u0006d7\u000f\u0005\u0002EaM)\u0001G!\u0001\u0003\bA\u0019\u0001Ja\u0001\n\u0007\t\u0015\u0011J\u0001\u0004B]f\u0014VM\u001a\t\u0005\u0005\u0013\u0011y!\u0004\u0002\u0003\f)!!QBA\\\u0003\tIw.C\u0002X\u0005\u0017!\"!!@\u0002\u000b\u0005\u0004\b\u000f\\=\u0015\u0011\u0005\r!q\u0003B\r\u00057AQ!\u0017\u001aA\u0002mCa!a\u000f3\u0001\u0004Y\u0006BBA\"e\u0001\u00071\f\u0006\u0006\u0002\u0004\t}!\u0011\u0005B\u0012\u0005KAQ!W\u001aA\u0002mCa!a\u000f4\u0001\u0004Y\u0006BBA\"g\u0001\u00071\fC\u0003rg\u0001\u0007a-\u0001\teK\u001a\fW\u000f\u001c;NCR\u001c\u0007\u000eS8ti\u0006\u0001B-\u001a4bk2$\b\n\u001e;qg>sG.\u001f\u000b\t\u0003\u0007\u0011iCa\f\u00032!)\u0011l\u000ea\u00017\")Am\u000ea\u0001M\")!n\u000ea\u0001YRQ\u00111\u0001B\u001b\u0005o\u0011IDa\u000f\t\u000beC\u0004\u0019A.\t\u000b\u0011D\u0004\u0019\u00014\t\u000b)D\u0004\u0019\u00017\t\u000bED\u0004\u0019\u00014\u0015\u0019\u0005\r!q\bB!\u0005\u0007\u0012)Ea\u0012\t\u000beK\u0004\u0019A.\t\u000b\u0011L\u0004\u0019\u00014\t\u000b)L\u0004\u0019\u00017\t\u000bEL\u0004\u0019\u00014\t\u000bML\u0004\u0019A;\u0015%\u0005\r!1\nB\'\u0005\u001f\u0012\tFa\u0015\u0003V\t]#\u0011\f\u0005\u00063j\u0002\ra\u0017\u0005\u0006Ij\u0002\rA\u001a\u0005\u0006Uj\u0002\r\u0001\u001c\u0005\u0006cj\u0002\rA\u001a\u0005\u0006gj\u0002\r!\u001e\u0005\u0006sj\u0002\r!\u001e\u0005\u0006wj\u0002\r!\u001e\u0005\u0006{j\u0002\r!^\u0001\roJLG/\u001a*fa2\f7-\u001a\u000b\u0003\u0005?\u0002B!!-\u0003b%!!1MAZ\u0005\u0019y%M[3di\u0002
   #11 = Utf8               java/lang/invoke/MethodHandles$Lookup
   #12 = Class              #11           // java/lang/invoke/MethodHandles$Lookup
   #13 = Utf8               java/lang/invoke/MethodHandles
   #14 = Class              #13           // java/lang/invoke/MethodHandles
   #15 = Utf8               Lookup
   #16 = Utf8               host
   #17 = Utf8               Ljava/lang/String;
   #18 = Utf8               usernameOpt
   #19 = Utf8               Lscala/Option;
   #20 = Utf8               Lscala/Option<Ljava/lang/String;>;
   #21 = Utf8               passwordOpt
   #22 = Utf8               Lscala/Option<Lcoursier/credentials/Password<Ljava/lang/String;>;>;
   #23 = Utf8               realm
   #24 = Utf8               optional
   #25 = Utf8               Z
   #26 = Utf8               matchHost
   #27 = Utf8               httpsOnly
   #28 = Utf8               passOnRedirect
   #29 = Utf8               apply
   #30 = Utf8               (Ljava/lang/String;Lscala/Option;Lscala/Option;Lscala/Option;ZZZZ)Lcoursier/credentials/DirectCredentials;
   #31 = Utf8               (Ljava/lang/String;Lscala/Option<Ljava/lang/String;>;Lscala/Option<Lcoursier/credentials/Password<Ljava/lang/String;>;>;Lscala/Option<Ljava/lang/String;>;ZZZZ)Lcoursier/credentials/DirectCredentials;
   #32 = Utf8               coursier/credentials/DirectCredentials$
   #33 = Class              #32           // coursier/credentials/DirectCredentials$
   #34 = Utf8               MODULE$
   #35 = Utf8               Lcoursier/credentials/DirectCredentials$;
   #36 = NameAndType        #34:#35       // MODULE$:Lcoursier/credentials/DirectCredentials$;
   #37 = Fieldref           #33.#36       // coursier/credentials/DirectCredentials$.MODULE$:Lcoursier/credentials/DirectCredentials$;
   #38 = NameAndType        #29:#30       // apply:(Ljava/lang/String;Lscala/Option;Lscala/Option;Lscala/Option;ZZZZ)Lcoursier/credentials/DirectCredentials;
   #39 = Methodref          #33.#38       // coursier/credentials/DirectCredentials$.apply:(Ljava/lang/String;Lscala/Option;Lscala/Option;Lscala/Option;ZZZZ)Lcoursier/credentials/DirectCredentials;
   #40 = Utf8               (Ljava/lang/String;Lscala/Option;Lscala/Option;Lscala/Option;Z)Lcoursier/credentials/DirectCredentials;
   #41 = Utf8               (Ljava/lang/String;Lscala/Option<Ljava/lang/String;>;Lscala/Option<Lcoursier/credentials/Password<Ljava/lang/String;>;>;Lscala/Option<Ljava/lang/String;>;Z)Lcoursier/credentials/DirectCredentials;
   #42 = NameAndType        #29:#40       // apply:(Ljava/lang/String;Lscala/Option;Lscala/Option;Lscala/Option;Z)Lcoursier/credentials/DirectCredentials;
   #43 = Methodref          #33.#42       // coursier/credentials/DirectCredentials$.apply:(Ljava/lang/String;Lscala/Option;Lscala/Option;Lscala/Option;Z)Lcoursier/credentials/DirectCredentials;
   #44 = Utf8               (Ljava/lang/String;Lscala/Option;Lscala/Option;Lscala/Option;)Lcoursier/credentials/DirectCredentials;
   #45 = Utf8               (Ljava/lang/String;Lscala/Option<Ljava/lang/String;>;Lscala/Option<Lcoursier/credentials/Password<Ljava/lang/String;>;>;Lscala/Option<Ljava/lang/String;>;)Lcoursier/credentials/DirectCredentials;
   #46 = NameAndType        #29:#44       // apply:(Ljava/lang/String;Lscala/Option;Lscala/Option;Lscala/Option;)Lcoursier/credentials/DirectCredentials;
   #47 = Methodref          #33.#46       // coursier/credentials/DirectCredentials$.apply:(Ljava/lang/String;Lscala/Option;Lscala/Option;Lscala/Option;)Lcoursier/credentials/DirectCredentials;
   #48 = Utf8               (Ljava/lang/String;Lscala/Option;Lscala/Option;)Lcoursier/credentials/DirectCredentials;
   #49 = Utf8               (Ljava/lang/String;Lscala/Option<Ljava/lang/String;>;Lscala/Option<Lcoursier/credentials/Password<Ljava/lang/String;>;>;)Lcoursier/credentials/DirectCredentials;
   #50 = NameAndType        #29:#48       // apply:(Ljava/lang/String;Lscala/Option;Lscala/Option;)Lcoursier/credentials/DirectCredentials;
   #51 = Methodref          #33.#50       // coursier/credentials/DirectCredentials$.apply:(Ljava/lang/String;Lscala/Option;Lscala/Option;)Lcoursier/credentials/DirectCredentials;
   #52 = Utf8               ()Lcoursier/credentials/DirectCredentials;
   #53 = NameAndType        #29:#52       // apply:()Lcoursier/credentials/DirectCredentials;
   #54 = Methodref          #33.#53       // coursier/credentials/DirectCredentials$.apply:()Lcoursier/credentials/DirectCredentials;
   #55 = Utf8               defaultHttpsOnly
   #56 = Utf8               ()Z
   #57 = NameAndType        #55:#56       // defaultHttpsOnly:()Z
   #58 = Methodref          #33.#57       // coursier/credentials/DirectCredentials$.defaultHttpsOnly:()Z
   #59 = Utf8               defaultMatchHost
   #60 = NameAndType        #59:#56       // defaultMatchHost:()Z
   #61 = Methodref          #33.#60       // coursier/credentials/DirectCredentials$.defaultMatchHost:()Z
   #62 = Utf8               (Ljava/lang/String;Ljava/lang/String;Ljava/lang/String;Lscala/Option;)Lcoursier/credentials/DirectCredentials;
   #63 = Utf8               (Ljava/lang/String;Ljava/lang/String;Ljava/lang/String;Lscala/Option<Ljava/lang/String;>;)Lcoursier/credentials/DirectCredentials;
   #64 = Utf8               username
   #65 = Utf8               password
   #66 = NameAndType        #29:#62       // apply:(Ljava/lang/String;Ljava/lang/String;Ljava/lang/String;Lscala/Option;)Lcoursier/credentials/DirectCredentials;
   #67 = Methodref          #33.#66       // coursier/credentials/DirectCredentials$.apply:(Ljava/lang/String;Ljava/lang/String;Ljava/lang/String;Lscala/Option;)Lcoursier/credentials/DirectCredentials;
   #68 = Utf8               (Ljava/lang/String;Ljava/lang/String;Ljava/lang/String;)Lcoursier/credentials/DirectCredentials;
   #69 = NameAndType        #29:#68       // apply:(Ljava/lang/String;Ljava/lang/String;Ljava/lang/String;)Lcoursier/credentials/DirectCredentials;
   #70 = Methodref          #33.#69       // coursier/credentials/DirectCredentials$.apply:(Ljava/lang/String;Ljava/lang/String;Ljava/lang/String;)Lcoursier/credentials/DirectCredentials;
   #71 = Utf8               productIterator
   #72 = Utf8               ()Lscala/collection/Iterator;
   #73 = Utf8               ()Lscala/collection/Iterator<Ljava/lang/Object;>;
   #74 = Utf8               productIterator$
   #75 = Utf8               (Lscala/Product;)Lscala/collection/Iterator;
   #76 = NameAndType        #74:#75       // productIterator$:(Lscala/Product;)Lscala/collection/Iterator;
   #77 = InterfaceMethodref #6.#76        // scala/Product.productIterator$:(Lscala/Product;)Lscala/collection/Iterator;
   #78 = Utf8               this
   #79 = Utf8               Lcoursier/credentials/DirectCredentials;
   #80 = Utf8               productElementNames
   #81 = Utf8               ()Lscala/collection/Iterator<Ljava/lang/String;>;
   #82 = Utf8               productElementNames$
   #83 = NameAndType        #82:#75       // productElementNames$:(Lscala/Product;)Lscala/collection/Iterator;
   #84 = InterfaceMethodref #6.#83        // scala/Product.productElementNames$:(Lscala/Product;)Lscala/collection/Iterator;
   #85 = Utf8               ()Ljava/lang/String;
   #86 = NameAndType        #16:#17       // host:Ljava/lang/String;
   #87 = Fieldref           #2.#86        // coursier/credentials/DirectCredentials.host:Ljava/lang/String;
   #88 = Utf8               ()Lscala/Option;
   #89 = Utf8               ()Lscala/Option<Ljava/lang/String;>;
   #90 = NameAndType        #18:#19       // usernameOpt:Lscala/Option;
   #91 = Fieldref           #2.#90        // coursier/credentials/DirectCredentials.usernameOpt:Lscala/Option;
   #92 = Utf8               ()Lscala/Option<Lcoursier/credentials/Password<Ljava/lang/String;>;>;
   #93 = NameAndType        #21:#19       // passwordOpt:Lscala/Option;
   #94 = Fieldref           #2.#93        // coursier/credentials/DirectCredentials.passwordOpt:Lscala/Option;
   #95 = NameAndType        #23:#19       // realm:Lscala/Option;
   #96 = Fieldref           #2.#95        // coursier/credentials/DirectCredentials.realm:Lscala/Option;
   #97 = NameAndType        #24:#25       // optional:Z
   #98 = Fieldref           #2.#97        // coursier/credentials/DirectCredentials.optional:Z
   #99 = NameAndType        #26:#25       // matchHost:Z
  #100 = Fieldref           #2.#99        // coursier/credentials/DirectCredentials.matchHost:Z
  #101 = NameAndType        #27:#25       // httpsOnly:Z
  #102 = Fieldref           #2.#101       // coursier/credentials/DirectCredentials.httpsOnly:Z
  #103 = NameAndType        #28:#25       // passOnRedirect:Z
  #104 = Fieldref           #2.#103       // coursier/credentials/DirectCredentials.passOnRedirect:Z
  #105 = Utf8               withUsername
  #106 = Utf8               (Ljava/lang/String;)Lcoursier/credentials/DirectCredentials;
  #107 = Utf8               scala/Some
  #108 = Class              #107          // scala/Some
  #109 = Utf8               <init>
  #110 = Utf8               (Ljava/lang/Object;)V
  #111 = NameAndType        #109:#110     // "<init>":(Ljava/lang/Object;)V
  #112 = Methodref          #108.#111     // scala/Some."<init>":(Ljava/lang/Object;)V
  #113 = Utf8               withUsernameOpt
  #114 = Utf8               (Lscala/Option;)Lcoursier/credentials/DirectCredentials;
  #115 = NameAndType        #113:#114     // withUsernameOpt:(Lscala/Option;)Lcoursier/credentials/DirectCredentials;
  #116 = Methodref          #2.#115       // coursier/credentials/DirectCredentials.withUsernameOpt:(Lscala/Option;)Lcoursier/credentials/DirectCredentials;
  #117 = Utf8               withPassword
  #118 = Utf8               coursier/credentials/Password$
  #119 = Class              #118          // coursier/credentials/Password$
  #120 = Utf8               Lcoursier/credentials/Password$;
  #121 = NameAndType        #34:#120      // MODULE$:Lcoursier/credentials/Password$;
  #122 = Fieldref           #119.#121     // coursier/credentials/Password$.MODULE$:Lcoursier/credentials/Password$;
  #123 = Utf8               (Ljava/lang/Object;)Lcoursier/credentials/Password;
  #124 = NameAndType        #29:#123      // apply:(Ljava/lang/Object;)Lcoursier/credentials/Password;
  #125 = Methodref          #119.#124     // coursier/credentials/Password$.apply:(Ljava/lang/Object;)Lcoursier/credentials/Password;
  #126 = Utf8               withPasswordOpt
  #127 = NameAndType        #126:#114     // withPasswordOpt:(Lscala/Option;)Lcoursier/credentials/DirectCredentials;
  #128 = Methodref          #2.#127       // coursier/credentials/DirectCredentials.withPasswordOpt:(Lscala/Option;)Lcoursier/credentials/DirectCredentials;
  #129 = Utf8               withRealm
  #130 = Utf8               scala/Option$
  #131 = Class              #130          // scala/Option$
  #132 = Utf8               Lscala/Option$;
  #133 = NameAndType        #34:#132      // MODULE$:Lscala/Option$;
  #134 = Fieldref           #131.#133     // scala/Option$.MODULE$:Lscala/Option$;
  #135 = Utf8               (Ljava/lang/Object;)Lscala/Option;
  #136 = NameAndType        #29:#135      // apply:(Ljava/lang/Object;)Lscala/Option;
  #137 = Methodref          #131.#136     // scala/Option$.apply:(Ljava/lang/Object;)Lscala/Option;
  #138 = NameAndType        #129:#114     // withRealm:(Lscala/Option;)Lcoursier/credentials/DirectCredentials;
  #139 = Methodref          #2.#138       // coursier/credentials/DirectCredentials.withRealm:(Lscala/Option;)Lcoursier/credentials/DirectCredentials;
  #140 = Utf8               nonEmpty
  #141 = NameAndType        #18:#88       // usernameOpt:()Lscala/Option;
  #142 = Methodref          #2.#141       // coursier/credentials/DirectCredentials.usernameOpt:()Lscala/Option;
  #143 = Utf8               scala/Option
  #144 = Class              #143          // scala/Option
  #145 = NameAndType        #140:#56      // nonEmpty:()Z
  #146 = Methodref          #144.#145     // scala/Option.nonEmpty:()Z
  #147 = NameAndType        #21:#88       // passwordOpt:()Lscala/Option;
  #148 = Methodref          #2.#147       // coursier/credentials/DirectCredentials.passwordOpt:()Lscala/Option;
  #149 = Utf8               autoMatches
  #150 = Utf8               (Ljava/lang/String;Lscala/Option;)Z
  #151 = Utf8               (Ljava/lang/String;Lscala/Option<Ljava/lang/String;>;)Z
  #152 = Utf8               url
  #153 = Utf8               realm0
  #154 = Methodref          #2.#145       // coursier/credentials/DirectCredentials.nonEmpty:()Z
  #155 = NameAndType        #26:#56       // matchHost:()Z
  #156 = Methodref          #2.#155       // coursier/credentials/DirectCredentials.matchHost:()Z
  #157 = Utf8               scala/util/Try$
  #158 = Class              #157          // scala/util/Try$
  #159 = Utf8               Lscala/util/Try$;
  #160 = NameAndType        #34:#159      // MODULE$:Lscala/util/Try$;
  #161 = Fieldref           #158.#160     // scala/util/Try$.MODULE$:Lscala/util/Try$;
  #162 = Utf8               ()Ljava/lang/Object;
  #163 = MethodType         #162          //  ()Ljava/lang/Object;
  #164 = Utf8               $anonfun$autoMatches$1
  #165 = Utf8               (Ljava/lang/String;)Ljava/net/URI;
  #166 = NameAndType        #164:#165     // $anonfun$autoMatches$1:(Ljava/lang/String;)Ljava/net/URI;
  #167 = Methodref          #2.#166       // coursier/credentials/DirectCredentials.$anonfun$autoMatches$1:(Ljava/lang/String;)Ljava/net/URI;
  #168 = MethodHandle       6:#167        // REF_invokeStatic coursier/credentials/DirectCredentials.$anonfun$autoMatches$1:(Ljava/lang/String;)Ljava/net/URI;
  #169 = Utf8               ()Ljava/net/URI;
  #170 = MethodType         #169          //  ()Ljava/net/URI;
  #171 = Integer            5
  #172 = Integer            1
  #173 = Utf8               java/lang/invoke/LambdaMetafactory
  #174 = Class              #173          // java/lang/invoke/LambdaMetafactory
  #175 = Utf8               altMetafactory
  #176 = Utf8               (Ljava/lang/invoke/MethodHandles$Lookup;Ljava/lang/String;Ljava/lang/invoke/MethodType;[Ljava/lang/Object;)Ljava/lang/invoke/CallSite;
  #177 = NameAndType        #175:#176     // altMetafactory:(Ljava/lang/invoke/MethodHandles$Lookup;Ljava/lang/String;Ljava/lang/invoke/MethodType;[Ljava/lang/Object;)Ljava/lang/invoke/CallSite;
  #178 = Methodref          #174.#177     // java/lang/invoke/LambdaMetafactory.altMetafactory:(Ljava/lang/invoke/MethodHandles$Lookup;Ljava/lang/String;Ljava/lang/invoke/MethodType;[Ljava/lang/Object;)Ljava/lang/invoke/CallSite;
  #179 = MethodHandle       6:#178        // REF_invokeStatic java/lang/invoke/LambdaMetafactory.altMetafactory:(Ljava/lang/invoke/MethodHandles$Lookup;Ljava/lang/String;Ljava/lang/invoke/MethodType;[Ljava/lang/Object;)Ljava/lang/invoke/CallSite;
  #180 = Utf8               (Ljava/lang/String;)Lscala/Function0;
  #181 = NameAndType        #29:#180      // apply:(Ljava/lang/String;)Lscala/Function0;
  #182 = InvokeDynamic      #0:#181       // #0:apply:(Ljava/lang/String;)Lscala/Function0;
  #183 = Utf8               (Lscala/Function0;)Lscala/util/Try;
  #184 = NameAndType        #29:#183      // apply:(Lscala/Function0;)Lscala/util/Try;
  #185 = Methodref          #158.#184     // scala/util/Try$.apply:(Lscala/Function0;)Lscala/util/Try;
  #186 = Utf8               scala/util/Try
  #187 = Class              #186          // scala/util/Try
  #188 = Utf8               toOption
  #189 = NameAndType        #188:#88      // toOption:()Lscala/Option;
  #190 = Methodref          #187.#189     // scala/util/Try.toOption:()Lscala/Option;
  #191 = Utf8               (Ljava/lang/Object;)Ljava/lang/Object;
  #192 = MethodType         #191          //  (Ljava/lang/Object;)Ljava/lang/Object;
  #193 = Utf8               $anonfun$autoMatches$2
  #194 = Utf8               (Ljava/net/URI;)Lscala/Option;
  #195 = NameAndType        #193:#194     // $anonfun$autoMatches$2:(Ljava/net/URI;)Lscala/Option;
  #196 = Methodref          #2.#195       // coursier/credentials/DirectCredentials.$anonfun$autoMatches$2:(Ljava/net/URI;)Lscala/Option;
  #197 = MethodHandle       6:#196        // REF_invokeStatic coursier/credentials/DirectCredentials.$anonfun$autoMatches$2:(Ljava/net/URI;)Lscala/Option;
  #198 = MethodType         #194          //  (Ljava/net/URI;)Lscala/Option;
  #199 = Utf8               ()Lscala/Function1;
  #200 = NameAndType        #29:#199      // apply:()Lscala/Function1;
  #201 = InvokeDynamic      #1:#200       // #1:apply:()Lscala/Function1;
  #202 = Utf8               flatMap
  #203 = Utf8               (Lscala/Function1;)Lscala/Option;
  #204 = NameAndType        #202:#203     // flatMap:(Lscala/Function1;)Lscala/Option;
  #205 = Methodref          #144.#204     // scala/Option.flatMap:(Lscala/Function1;)Lscala/Option;
  #206 = Utf8               $anonfun$autoMatches$3
  #207 = NameAndType        #206:#194     // $anonfun$autoMatches$3:(Ljava/net/URI;)Lscala/Option;
  #208 = Methodref          #2.#207       // coursier/credentials/DirectCredentials.$anonfun$autoMatches$3:(Ljava/net/URI;)Lscala/Option;
  #209 = MethodHandle       6:#208        // REF_invokeStatic coursier/credentials/DirectCredentials.$anonfun$autoMatches$3:(Ljava/net/URI;)Lscala/Option;
  #210 = InvokeDynamic      #2:#200       // #2:apply:()Lscala/Function1;
  #211 = Utf8               http
  #212 = String             #211          // http
  #213 = Utf8               contains
  #214 = Utf8               (Ljava/lang/Object;)Z
  #215 = NameAndType        #213:#214     // contains:(Ljava/lang/Object;)Z
  #216 = Methodref          #144.#215     // scala/Option.contains:(Ljava/lang/Object;)Z
  #217 = NameAndType        #27:#56       // httpsOnly:()Z
  #218 = Methodref          #2.#217       // coursier/credentials/DirectCredentials.httpsOnly:()Z
  #219 = Utf8               https
  #220 = String             #219          // https
  #221 = NameAndType        #16:#85       // host:()Ljava/lang/String;
  #222 = Methodref          #2.#221       // coursier/credentials/DirectCredentials.host:()Ljava/lang/String;
  #223 = NameAndType        #23:#88       // realm:()Lscala/Option;
  #224 = Methodref          #2.#223       // coursier/credentials/DirectCredentials.realm:()Lscala/Option;
  #225 = Utf8               $anonfun$autoMatches$4$adapted
  #226 = Utf8               (Lscala/Option;Ljava/lang/Object;)Ljava/lang/Object;
  #227 = NameAndType        #225:#226     // $anonfun$autoMatches$4$adapted:(Lscala/Option;Ljava/lang/Object;)Ljava/lang/Object;
  #228 = Methodref          #2.#227       // coursier/credentials/DirectCredentials.$anonfun$autoMatches$4$adapted:(Lscala/Option;Ljava/lang/Object;)Ljava/lang/Object;
  #229 = MethodHandle       6:#228        // REF_invokeStatic coursier/credentials/DirectCredentials.$anonfun$autoMatches$4$adapted:(Lscala/Option;Ljava/lang/Object;)Ljava/lang/Object;
  #230 = Utf8               (Lscala/Option;)Lscala/Function1;
  #231 = NameAndType        #29:#230      // apply:(Lscala/Option;)Lscala/Function1;
  #232 = InvokeDynamic      #3:#231       // #3:apply:(Lscala/Option;)Lscala/Function1;
  #233 = Utf8               forall
  #234 = Utf8               (Lscala/Function1;)Z
  #235 = NameAndType        #233:#234     // forall:(Lscala/Function1;)Z
  #236 = Methodref          #144.#235     // scala/Option.forall:(Lscala/Function1;)Z
  #237 = Utf8               uriOpt
  #238 = Utf8               schemeOpt
  #239 = Utf8               hostOpt
  #240 = Utf8               matches
  #241 = Utf8               (Ljava/lang/String;Ljava/lang/String;)Z
  #242 = Utf8               user
  #243 = Utf8               $anonfun$matches$1
  #244 = NameAndType        #243:#165     // $anonfun$matches$1:(Ljava/lang/String;)Ljava/net/URI;
  #245 = Methodref          #2.#244       // coursier/credentials/DirectCredentials.$anonfun$matches$1:(Ljava/lang/String;)Ljava/net/URI;
  #246 = MethodHandle       6:#245        // REF_invokeStatic coursier/credentials/DirectCredentials.$anonfun$matches$1:(Ljava/lang/String;)Ljava/net/URI;
  #247 = InvokeDynamic      #4:#181       // #4:apply:(Ljava/lang/String;)Lscala/Function0;
  #248 = Utf8               $anonfun$matches$2
  #249 = NameAndType        #248:#194     // $anonfun$matches$2:(Ljava/net/URI;)Lscala/Option;
  #250 = Methodref          #2.#249       // coursier/credentials/DirectCredentials.$anonfun$matches$2:(Ljava/net/URI;)Lscala/Option;
  #251 = MethodHandle       6:#250        // REF_invokeStatic coursier/credentials/DirectCredentials.$anonfun$matches$2:(Ljava/net/URI;)Lscala/Option;
  #252 = InvokeDynamic      #5:#200       // #5:apply:()Lscala/Function1;
  #253 = Utf8               $anonfun$matches$3
  #254 = NameAndType        #253:#194     // $anonfun$matches$3:(Ljava/net/URI;)Lscala/Option;
  #255 = Methodref          #2.#254       // coursier/credentials/DirectCredentials.$anonfun$matches$3:(Ljava/net/URI;)Lscala/Option;
  #256 = MethodHandle       6:#255        // REF_invokeStatic coursier/credentials/DirectCredentials.$anonfun$matches$3:(Ljava/net/URI;)Lscala/Option;
  #257 = InvokeDynamic      #6:#200       // #6:apply:()Lscala/Function1;
  #258 = Utf8               $anonfun$matches$4
  #259 = NameAndType        #258:#194     // $anonfun$matches$4:(Ljava/net/URI;)Lscala/Option;
  #260 = Methodref          #2.#259       // coursier/credentials/DirectCredentials.$anonfun$matches$4:(Ljava/net/URI;)Lscala/Option;
  #261 = MethodHandle       6:#260        // REF_invokeStatic coursier/credentials/DirectCredentials.$anonfun$matches$4:(Ljava/net/URI;)Lscala/Option;
  #262 = InvokeDynamic      #7:#200       // #7:apply:()Lscala/Function1;
  #263 = Utf8               isEmpty
  #264 = NameAndType        #263:#56      // isEmpty:()Z
  #265 = Methodref          #144.#264     // scala/Option.isEmpty:()Z
  #266 = Utf8               java/lang/String
  #267 = Class              #266          // java/lang/String
  #268 = Utf8               userInfoOpt
  #269 = Utf8               authentication
  #270 = Utf8               ()Lcoursier/core/Authentication;
  #271 = Utf8               $anonfun$authentication$1
  #272 = NameAndType        #271:#85      // $anonfun$authentication$1:()Ljava/lang/String;
  #273 = Methodref          #2.#272       // coursier/credentials/DirectCredentials.$anonfun$authentication$1:()Ljava/lang/String;
  #274 = MethodHandle       6:#273        // REF_invokeStatic coursier/credentials/DirectCredentials.$anonfun$authentication$1:()Ljava/lang/String;
  #275 = MethodType         #85           //  ()Ljava/lang/String;
  #276 = Utf8               ()Lscala/Function0;
  #277 = NameAndType        #29:#276      // apply:()Lscala/Function0;
  #278 = InvokeDynamic      #8:#277       // #8:apply:()Lscala/Function0;
  #279 = Utf8               getOrElse
  #280 = Utf8               (Lscala/Function0;)Ljava/lang/Object;
  #281 = NameAndType        #279:#280     // getOrElse:(Lscala/Function0;)Ljava/lang/Object;
  #282 = Methodref          #144.#281     // scala/Option.getOrElse:(Lscala/Function0;)Ljava/lang/Object;
  #283 = Utf8               $anonfun$authentication$2
  #284 = Utf8               (Lcoursier/credentials/Password;)Ljava/lang/String;
  #285 = NameAndType        #283:#284     // $anonfun$authentication$2:(Lcoursier/credentials/Password;)Ljava/lang/String;
  #286 = Methodref          #2.#285       // coursier/credentials/DirectCredentials.$anonfun$authentication$2:(Lcoursier/credentials/Password;)Ljava/lang/String;
  #287 = MethodHandle       6:#286        // REF_invokeStatic coursier/credentials/DirectCredentials.$anonfun$authentication$2:(Lcoursier/credentials/Password;)Ljava/lang/String;
  #288 = MethodType         #284          //  (Lcoursier/credentials/Password;)Ljava/lang/String;
  #289 = InvokeDynamic      #9:#200       // #9:apply:()Lscala/Function1;
  #290 = Utf8               map
  #291 = NameAndType        #290:#203     // map:(Lscala/Function1;)Lscala/Option;
  #292 = Methodref          #144.#291     // scala/Option.map:(Lscala/Function1;)Lscala/Option;
  #293 = NameAndType        #24:#56       // optional:()Z
  #294 = Methodref          #2.#293       // coursier/credentials/DirectCredentials.optional:()Z
  #295 = NameAndType        #28:#56       // passOnRedirect:()Z
  #296 = Methodref          #2.#295       // coursier/credentials/DirectCredentials.passOnRedirect:()Z
  #297 = Utf8               coursier/core/Authentication$
  #298 = Class              #297          // coursier/core/Authentication$
  #299 = Utf8               Lcoursier/core/Authentication$;
  #300 = NameAndType        #34:#299      // MODULE$:Lcoursier/core/Authentication$;
  #301 = Fieldref           #298.#300     // coursier/core/Authentication$.MODULE$:Lcoursier/core/Authentication$;
  #302 = Utf8               (Ljava/lang/String;Lscala/Option;ZLscala/Option;ZZ)Lcoursier/core/Authentication;
  #303 = NameAndType        #29:#302      // apply:(Ljava/lang/String;Lscala/Option;ZLscala/Option;ZZ)Lcoursier/core/Authentication;
  #304 = Methodref          #298.#303     // coursier/core/Authentication$.apply:(Ljava/lang/String;Lscala/Option;ZLscala/Option;ZZ)Lcoursier/core/Authentication;
  #305 = Utf8               x$1
  #306 = Utf8               x$2
  #307 = Utf8               x$3
  #308 = Utf8               x$4
  #309 = Utf8               x$5
  #310 = Utf8               x$6
  #311 = Utf8               get
  #312 = Utf8               ()Lscala/collection/immutable/Seq;
  #313 = Utf8               ()Lscala/collection/immutable/Seq<Lcoursier/credentials/DirectCredentials;>;
  #314 = Utf8               scala/collection/immutable/$colon$colon
  #315 = Class              #314          // scala/collection/immutable/$colon$colon
  #316 = Utf8               scala/collection/immutable/Nil$
  #317 = Class              #316          // scala/collection/immutable/Nil$
  #318 = Utf8               Lscala/collection/immutable/Nil$;
  #319 = NameAndType        #34:#318      // MODULE$:Lscala/collection/immutable/Nil$;
  #320 = Fieldref           #317.#319     // scala/collection/immutable/Nil$.MODULE$:Lscala/collection/immutable/Nil$;
  #321 = Utf8               (Ljava/lang/Object;Lscala/collection/immutable/List;)V
  #322 = NameAndType        #109:#321     // "<init>":(Ljava/lang/Object;Lscala/collection/immutable/List;)V
  #323 = Methodref          #315.#322     // scala/collection/immutable/$colon$colon."<init>":(Ljava/lang/Object;Lscala/collection/immutable/List;)V
  #324 = Utf8               scala/collection/immutable/Seq
  #325 = Class              #324          // scala/collection/immutable/Seq
  #326 = Utf8               withHost
  #327 = Utf8               (Ljava/lang/String;Lscala/Option;Lscala/Option;Lscala/Option;ZZZZ)V
  #328 = NameAndType        #109:#327     // "<init>":(Ljava/lang/String;Lscala/Option;Lscala/Option;Lscala/Option;ZZZZ)V
  #329 = Methodref          #2.#328       // coursier/credentials/DirectCredentials."<init>":(Ljava/lang/String;Lscala/Option;Lscala/Option;Lscala/Option;ZZZZ)V
  #330 = Utf8               (Lscala/Option<Ljava/lang/String;>;)Lcoursier/credentials/DirectCredentials;
  #331 = Utf8               (Lscala/Option<Lcoursier/credentials/Password<Ljava/lang/String;>;>;)Lcoursier/credentials/DirectCredentials;
  #332 = Utf8               withOptional
  #333 = Utf8               (Z)Lcoursier/credentials/DirectCredentials;
  #334 = Utf8               withMatchHost
  #335 = Utf8               withHttpsOnly
  #336 = Utf8               withPassOnRedirect
  #337 = Utf8               toString
  #338 = Utf8               java/lang/StringBuilder
  #339 = Class              #338          // java/lang/StringBuilder
  #340 = Utf8               DirectCredentials(
  #341 = String             #340          // DirectCredentials(
  #342 = Utf8               (Ljava/lang/String;)V
  #343 = NameAndType        #109:#342     // "<init>":(Ljava/lang/String;)V
  #344 = Methodref          #339.#343     // java/lang/StringBuilder."<init>":(Ljava/lang/String;)V
  #345 = Utf8               valueOf
  #346 = Utf8               (Ljava/lang/Object;)Ljava/lang/String;
  #347 = NameAndType        #345:#346     // valueOf:(Ljava/lang/Object;)Ljava/lang/String;
  #348 = Methodref          #267.#347     // java/lang/String.valueOf:(Ljava/lang/Object;)Ljava/lang/String;
  #349 = Utf8               append
  #350 = Utf8               (Ljava/lang/String;)Ljava/lang/StringBuilder;
  #351 = NameAndType        #349:#350     // append:(Ljava/lang/String;)Ljava/lang/StringBuilder;
  #352 = Methodref          #339.#351     // java/lang/StringBuilder.append:(Ljava/lang/String;)Ljava/lang/StringBuilder;
  #353 = Utf8               ,
  #354 = String             #353          // ,
  #355 = Utf8               (Z)Ljava/lang/String;
  #356 = NameAndType        #345:#355     // valueOf:(Z)Ljava/lang/String;
  #357 = Methodref          #267.#356     // java/lang/String.valueOf:(Z)Ljava/lang/String;
  #358 = Utf8               )
  #359 = String             #358          // )
  #360 = NameAndType        #337:#85      // toString:()Ljava/lang/String;
  #361 = Methodref          #339.#360     // java/lang/StringBuilder.toString:()Ljava/lang/String;
  #362 = Utf8               b
  #363 = Utf8               Ljava/lang/StringBuilder;
  #364 = Utf8               canEqual
  #365 = Utf8               obj
  #366 = Utf8               Ljava/lang/Object;
  #367 = Utf8               equals
  #368 = NameAndType        #364:#214     // canEqual:(Ljava/lang/Object;)Z
  #369 = Methodref          #2.#368       // coursier/credentials/DirectCredentials.canEqual:(Ljava/lang/Object;)Z
  #370 = Utf8               java/lang/Object
  #371 = Class              #370          // java/lang/Object
  #372 = NameAndType        #367:#214     // equals:(Ljava/lang/Object;)Z
  #373 = Methodref          #371.#372     // java/lang/Object.equals:(Ljava/lang/Object;)Z
  #374 = Utf8               other
  #375 = Utf8               hashCode
  #376 = Utf8               ()I
  #377 = Utf8               DirectCredentials
  #378 = String             #377          // DirectCredentials
  #379 = Utf8               scala/runtime/Statics
  #380 = Class              #379          // scala/runtime/Statics
  #381 = Utf8               anyHash
  #382 = Utf8               (Ljava/lang/Object;)I
  #383 = NameAndType        #381:#382     // anyHash:(Ljava/lang/Object;)I
  #384 = Methodref          #380.#383     // scala/runtime/Statics.anyHash:(Ljava/lang/Object;)I
  #385 = Utf8               code
  #386 = Utf8               I
  #387 = Utf8               tuple
  #388 = Utf8               ()Lscala/Tuple8;
  #389 = Utf8               ()Lscala/Tuple8<Ljava/lang/String;Lscala/Option<Ljava/lang/String;>;Lscala/Option<Lcoursier/credentials/Password<Ljava/lang/String;>;>;Lscala/Option<Ljava/lang/String;>;Ljava/lang/Object;Ljava/lang/Object;Ljava/lang/Object;Ljava/lang/Object;>;
  #390 = Utf8               scala/Tuple8
  #391 = Class              #390          // scala/Tuple8
  #392 = Utf8               scala/runtime/BoxesRunTime
  #393 = Class              #392          // scala/runtime/BoxesRunTime
  #394 = Utf8               boxToBoolean
  #395 = Utf8               (Z)Ljava/lang/Boolean;
  #396 = NameAndType        #394:#395     // boxToBoolean:(Z)Ljava/lang/Boolean;
  #397 = Methodref          #393.#396     // scala/runtime/BoxesRunTime.boxToBoolean:(Z)Ljava/lang/Boolean;
  #398 = Utf8               (Ljava/lang/Object;Ljava/lang/Object;Ljava/lang/Object;Ljava/lang/Object;Ljava/lang/Object;Ljava/lang/Object;Ljava/lang/Object;Ljava/lang/Object;)V
  #399 = NameAndType        #109:#398     // "<init>":(Ljava/lang/Object;Ljava/lang/Object;Ljava/lang/Object;Ljava/lang/Object;Ljava/lang/Object;Ljava/lang/Object;Ljava/lang/Object;Ljava/lang/Object;)V
  #400 = Methodref          #391.#399     // scala/Tuple8."<init>":(Ljava/lang/Object;Ljava/lang/Object;Ljava/lang/Object;Ljava/lang/Object;Ljava/lang/Object;Ljava/lang/Object;Ljava/lang/Object;Ljava/lang/Object;)V
  #401 = Utf8               productPrefix
  #402 = Utf8               productArity
  #403 = Utf8               productElement
  #404 = Utf8               (I)Ljava/lang/Object;
  #405 = Utf8               n
  #406 = Utf8               java/lang/IndexOutOfBoundsException
  #407 = Class              #406          // java/lang/IndexOutOfBoundsException
  #408 = Utf8               boxToInteger
  #409 = Utf8               (I)Ljava/lang/Integer;
  #410 = NameAndType        #408:#409     // boxToInteger:(I)Ljava/lang/Integer;
  #411 = Methodref          #393.#410     // scala/runtime/BoxesRunTime.boxToInteger:(I)Ljava/lang/Integer;
  #412 = Methodref          #371.#360     // java/lang/Object.toString:()Ljava/lang/String;
  #413 = Methodref          #407.#343     // java/lang/IndexOutOfBoundsException."<init>":(Ljava/lang/String;)V
  #414 = Utf8               productElementName
  #415 = Utf8               (I)Ljava/lang/String;
  #416 = String             #16           // host
  #417 = String             #18           // usernameOpt
  #418 = String             #21           // passwordOpt
  #419 = String             #23           // realm
  #420 = String             #24           // optional
  #421 = String             #26           // matchHost
  #422 = String             #27           // httpsOnly
  #423 = String             #28           // passOnRedirect
  #424 = Utf8               url$1
  #425 = Utf8               java/net/URI
  #426 = Class              #425          // java/net/URI
  #427 = Methodref          #426.#343     // java/net/URI."<init>":(Ljava/lang/String;)V
  #428 = Utf8               uri
  #429 = Utf8               getScheme
  #430 = NameAndType        #429:#85      // getScheme:()Ljava/lang/String;
  #431 = Methodref          #426.#430     // java/net/URI.getScheme:()Ljava/lang/String;
  #432 = Utf8               Ljava/net/URI;
  #433 = Utf8               getHost
  #434 = NameAndType        #433:#85      // getHost:()Ljava/lang/String;
  #435 = Methodref          #426.#434     // java/net/URI.getHost:()Ljava/lang/String;
  #436 = Utf8               $anonfun$autoMatches$4
  #437 = Utf8               (Lscala/Option;Ljava/lang/Object;)Z
  #438 = Utf8               realm0$1
  #439 = Utf8               elem
  #440 = Utf8               url$2
  #441 = Utf8               getUserInfo
  #442 = NameAndType        #441:#85      // getUserInfo:()Ljava/lang/String;
  #443 = Methodref          #426.#442     // java/net/URI.getUserInfo:()Ljava/lang/String;
  #444 = Utf8
  #445 = String             #444          //
  #446 = Utf8               coursier/credentials/Password
  #447 = Class              #446          // coursier/credentials/Password
  #448 = Utf8               value
  #449 = NameAndType        #448:#162     // value:()Ljava/lang/Object;
  #450 = Methodref          #447.#449     // coursier/credentials/Password.value:()Ljava/lang/Object;
  #451 = Utf8               Lcoursier/credentials/Password;
  #452 = Utf8               (Ljava/lang/String;Lscala/Option<Ljava/lang/String;>;Lscala/Option<Lcoursier/credentials/Password<Ljava/lang/String;>;>;Lscala/Option<Ljava/lang/String;>;ZZZZ)V
  #453 = Utf8               ()V
  #454 = NameAndType        #109:#453     // "<init>":()V
  #455 = Methodref          #4.#454       // coursier/credentials/Credentials."<init>":()V
  #456 = Utf8               $init$
  #457 = Utf8               (Lscala/Product;)V
  #458 = NameAndType        #456:#457     // $init$:(Lscala/Product;)V
  #459 = InterfaceMethodref #6.#458       // scala/Product.$init$:(Lscala/Product;)V
  #460 = Utf8               (Ljava/lang/String;Lscala/Option;Lscala/Option;Lscala/Option;Z)V
  #461 = Utf8               (Ljava/lang/String;Lscala/Option<Ljava/lang/String;>;Lscala/Option<Lcoursier/credentials/Password<Ljava/lang/String;>;>;Lscala/Option<Ljava/lang/String;>;Z)V
  #462 = Utf8               (Ljava/lang/String;Lscala/Option;Lscala/Option;Lscala/Option;)V
  #463 = Utf8               (Ljava/lang/String;Lscala/Option<Ljava/lang/String;>;Lscala/Option<Lcoursier/credentials/Password<Ljava/lang/String;>;>;Lscala/Option<Ljava/lang/String;>;)V
  #464 = Utf8               (Ljava/lang/String;Lscala/Option;Lscala/Option;)V
  #465 = Utf8               (Ljava/lang/String;Lscala/Option<Ljava/lang/String;>;Lscala/Option<Lcoursier/credentials/Password<Ljava/lang/String;>;>;)V
  #466 = Utf8               scala/None$
  #467 = Class              #466          // scala/None$
  #468 = Utf8               Lscala/None$;
  #469 = NameAndType        #34:#468      // MODULE$:Lscala/None$;
  #470 = Fieldref           #467.#469     // scala/None$.MODULE$:Lscala/None$;
  #471 = NameAndType        #436:#437     // $anonfun$autoMatches$4:(Lscala/Option;Ljava/lang/Object;)Z
  #472 = Methodref          #2.#471       // coursier/credentials/DirectCredentials.$anonfun$autoMatches$4:(Lscala/Option;Ljava/lang/Object;)Z
  #473 = Utf8               $deserializeLambda$
  #474 = Utf8               (Ljava/lang/invoke/SerializedLambda;)Ljava/lang/Object;
  #475 = Utf8               scala/runtime/LambdaDeserialize
  #476 = Class              #475          // scala/runtime/LambdaDeserialize
  #477 = Utf8               bootstrap
  #478 = Utf8               (Ljava/lang/invoke/MethodHandles$Lookup;Ljava/lang/String;Ljava/lang/invoke/MethodType;[Ljava/lang/invoke/MethodHandle;)Ljava/lang/invoke/CallSite;
  #479 = NameAndType        #477:#478     // bootstrap:(Ljava/lang/invoke/MethodHandles$Lookup;Ljava/lang/String;Ljava/lang/invoke/MethodType;[Ljava/lang/invoke/MethodHandle;)Ljava/lang/invoke/CallSite;
  #480 = Methodref          #476.#479     // scala/runtime/LambdaDeserialize.bootstrap:(Ljava/lang/invoke/MethodHandles$Lookup;Ljava/lang/String;Ljava/lang/invoke/MethodType;[Ljava/lang/invoke/MethodHandle;)Ljava/lang/invoke/CallSite;
  #481 = MethodHandle       6:#480        // REF_invokeStatic scala/runtime/LambdaDeserialize.bootstrap:(Ljava/lang/invoke/MethodHandles$Lookup;Ljava/lang/String;Ljava/lang/invoke/MethodType;[Ljava/lang/invoke/MethodHandle;)Ljava/lang/invoke/CallSite;
  #482 = Utf8               lambdaDeserialize
  #483 = NameAndType        #482:#474     // lambdaDeserialize:(Ljava/lang/invoke/SerializedLambda;)Ljava/lang/Object;
  #484 = InvokeDynamic      #10:#483      // #10:lambdaDeserialize:(Ljava/lang/invoke/SerializedLambda;)Ljava/lang/Object;
  #485 = Utf8               Signature
  #486 = Utf8               Code
  #487 = Utf8               MethodParameters
  #488 = Utf8               LineNumberTable
  #489 = Utf8               LocalVariableTable
  #490 = Utf8               StackMapTable
  #491 = Utf8               InnerClasses
  #492 = Utf8               SourceFile
  #493 = Utf8               RuntimeVisibleAnnotations
  #494 = Utf8               BootstrapMethods
  #495 = Utf8               ScalaInlineInfo
  #496 = Utf8               ScalaSig
{
  private final java.lang.String host;
    descriptor: Ljava/lang/String;
    flags: (0x0012) ACC_PRIVATE, ACC_FINAL

  private final scala.Option<java.lang.String> usernameOpt;
    descriptor: Lscala/Option;
    flags: (0x0012) ACC_PRIVATE, ACC_FINAL
    Signature: #20                          // Lscala/Option<Ljava/lang/String;>;

  private final scala.Option<coursier.credentials.Password<java.lang.String>> passwordOpt;
    descriptor: Lscala/Option;
    flags: (0x0012) ACC_PRIVATE, ACC_FINAL
    Signature: #22                          // Lscala/Option<Lcoursier/credentials/Password<Ljava/lang/String;>;>;

  private final scala.Option<java.lang.String> realm;
    descriptor: Lscala/Option;
    flags: (0x0012) ACC_PRIVATE, ACC_FINAL
    Signature: #20                          // Lscala/Option<Ljava/lang/String;>;

  private final boolean optional;
    descriptor: Z
    flags: (0x0012) ACC_PRIVATE, ACC_FINAL

  private final boolean matchHost;
    descriptor: Z
    flags: (0x0012) ACC_PRIVATE, ACC_FINAL

  private final boolean httpsOnly;
    descriptor: Z
    flags: (0x0012) ACC_PRIVATE, ACC_FINAL

  private final boolean passOnRedirect;
    descriptor: Z
    flags: (0x0012) ACC_PRIVATE, ACC_FINAL

  public static coursier.credentials.DirectCredentials apply(java.lang.String, scala.Option<java.lang.String>, scala.Option<coursier.credentials.Password<java.lang.String>>, scala.Option<java.lang.String>, boolean, boolean, boolean, boolean);
    descriptor: (Ljava/lang/String;Lscala/Option;Lscala/Option;Lscala/Option;ZZZZ)Lcoursier/credentials/DirectCredentials;
    flags: (0x0009) ACC_PUBLIC, ACC_STATIC
    Code:
      stack=9, locals=8, args_size=8
         0: getstatic     #37                 // Field coursier/credentials/DirectCredentials$.MODULE$:Lcoursier/credentials/DirectCredentials$;
         3: aload_0
         4: aload_1
         5: aload_2
         6: aload_3
         7: iload         4
         9: iload         5
        11: iload         6
        13: iload         7
        15: invokevirtual #39                 // Method coursier/credentials/DirectCredentials$.apply:(Ljava/lang/String;Lscala/Option;Lscala/Option;Lscala/Option;ZZZZ)Lcoursier/credentials/DirectCredentials;
        18: areturn
    Signature: #31                          // (Ljava/lang/String;Lscala/Option<Ljava/lang/String;>;Lscala/Option<Lcoursier/credentials/Password<Ljava/lang/String;>;>;Lscala/Option<Ljava/lang/String;>;ZZZZ)Lcoursier/credentials/DirectCredentials;
    MethodParameters:
      Name                           Flags
      host                           final
      usernameOpt                    final
      passwordOpt                    final
      realm                          final
      optional                       final
      matchHost                      final
      httpsOnly                      final
      passOnRedirect                 final

  public static coursier.credentials.DirectCredentials apply(java.lang.String, scala.Option<java.lang.String>, scala.Option<coursier.credentials.Password<java.lang.String>>, scala.Option<java.lang.String>, boolean);
    descriptor: (Ljava/lang/String;Lscala/Option;Lscala/Option;Lscala/Option;Z)Lcoursier/credentials/DirectCredentials;
    flags: (0x0009) ACC_PUBLIC, ACC_STATIC
    Code:
      stack=6, locals=5, args_size=5
         0: getstatic     #37                 // Field coursier/credentials/DirectCredentials$.MODULE$:Lcoursier/credentials/DirectCredentials$;
         3: aload_0
         4: aload_1
         5: aload_2
         6: aload_3
         7: iload         4
         9: invokevirtual #43                 // Method coursier/credentials/DirectCredentials$.apply:(Ljava/lang/String;Lscala/Option;Lscala/Option;Lscala/Option;Z)Lcoursier/credentials/DirectCredentials;
        12: areturn
    Signature: #41                          // (Ljava/lang/String;Lscala/Option<Ljava/lang/String;>;Lscala/Option<Lcoursier/credentials/Password<Ljava/lang/String;>;>;Lscala/Option<Ljava/lang/String;>;Z)Lcoursier/credentials/DirectCredentials;
    MethodParameters:
      Name                           Flags
      host                           final
      usernameOpt                    final
      passwordOpt                    final
      realm                          final
      optional                       final

  public static coursier.credentials.DirectCredentials apply(java.lang.String, scala.Option<java.lang.String>, scala.Option<coursier.credentials.Password<java.lang.String>>, scala.Option<java.lang.String>);
    descriptor: (Ljava/lang/String;Lscala/Option;Lscala/Option;Lscala/Option;)Lcoursier/credentials/DirectCredentials;
    flags: (0x0009) ACC_PUBLIC, ACC_STATIC
    Code:
      stack=5, locals=4, args_size=4
         0: getstatic     #37                 // Field coursier/credentials/DirectCredentials$.MODULE$:Lcoursier/credentials/DirectCredentials$;
         3: aload_0
         4: aload_1
         5: aload_2
         6: aload_3
         7: invokevirtual #47                 // Method coursier/credentials/DirectCredentials$.apply:(Ljava/lang/String;Lscala/Option;Lscala/Option;Lscala/Option;)Lcoursier/credentials/DirectCredentials;
        10: areturn
    Signature: #45                          // (Ljava/lang/String;Lscala/Option<Ljava/lang/String;>;Lscala/Option<Lcoursier/credentials/Password<Ljava/lang/String;>;>;Lscala/Option<Ljava/lang/String;>;)Lcoursier/credentials/DirectCredentials;
    MethodParameters:
      Name                           Flags
      host                           final
      usernameOpt                    final
      passwordOpt                    final
      realm                          final

  public static coursier.credentials.DirectCredentials apply(java.lang.String, scala.Option<java.lang.String>, scala.Option<coursier.credentials.Password<java.lang.String>>);
    descriptor: (Ljava/lang/String;Lscala/Option;Lscala/Option;)Lcoursier/credentials/DirectCredentials;
    flags: (0x0009) ACC_PUBLIC, ACC_STATIC
    Code:
      stack=4, locals=3, args_size=3
         0: getstatic     #37                 // Field coursier/credentials/DirectCredentials$.MODULE$:Lcoursier/credentials/DirectCredentials$;
         3: aload_0
         4: aload_1
         5: aload_2
         6: invokevirtual #51                 // Method coursier/credentials/DirectCredentials$.apply:(Ljava/lang/String;Lscala/Option;Lscala/Option;)Lcoursier/credentials/DirectCredentials;
         9: areturn
    Signature: #49                          // (Ljava/lang/String;Lscala/Option<Ljava/lang/String;>;Lscala/Option<Lcoursier/credentials/Password<Ljava/lang/String;>;>;)Lcoursier/credentials/DirectCredentials;
    MethodParameters:
      Name                           Flags
      host                           final
      usernameOpt                    final
      passwordOpt                    final

  public static coursier.credentials.DirectCredentials apply();
    descriptor: ()Lcoursier/credentials/DirectCredentials;
    flags: (0x0009) ACC_PUBLIC, ACC_STATIC
    Code:
      stack=1, locals=0, args_size=0
         0: getstatic     #37                 // Field coursier/credentials/DirectCredentials$.MODULE$:Lcoursier/credentials/DirectCredentials$;
         3: invokevirtual #54                 // Method coursier/credentials/DirectCredentials$.apply:()Lcoursier/credentials/DirectCredentials;
         6: areturn

  public static boolean defaultHttpsOnly();
    descriptor: ()Z
    flags: (0x0009) ACC_PUBLIC, ACC_STATIC
    Code:
      stack=1, locals=0, args_size=0
         0: getstatic     #37                 // Field coursier/credentials/DirectCredentials$.MODULE$:Lcoursier/credentials/DirectCredentials$;
         3: invokevirtual #58                 // Method coursier/credentials/DirectCredentials$.defaultHttpsOnly:()Z
         6: ireturn

  public static boolean defaultMatchHost();
    descriptor: ()Z
    flags: (0x0009) ACC_PUBLIC, ACC_STATIC
    Code:
      stack=1, locals=0, args_size=0
         0: getstatic     #37                 // Field coursier/credentials/DirectCredentials$.MODULE$:Lcoursier/credentials/DirectCredentials$;
         3: invokevirtual #61                 // Method coursier/credentials/DirectCredentials$.defaultMatchHost:()Z
         6: ireturn

  public static coursier.credentials.DirectCredentials apply(java.lang.String, java.lang.String, java.lang.String, scala.Option<java.lang.String>);
    descriptor: (Ljava/lang/String;Ljava/lang/String;Ljava/lang/String;Lscala/Option;)Lcoursier/credentials/DirectCredentials;
    flags: (0x0009) ACC_PUBLIC, ACC_STATIC
    Code:
      stack=5, locals=4, args_size=4
         0: getstatic     #37                 // Field coursier/credentials/DirectCredentials$.MODULE$:Lcoursier/credentials/DirectCredentials$;
         3: aload_0
         4: aload_1
         5: aload_2
         6: aload_3
         7: invokevirtual #67                 // Method coursier/credentials/DirectCredentials$.apply:(Ljava/lang/String;Ljava/lang/String;Ljava/lang/String;Lscala/Option;)Lcoursier/credentials/DirectCredentials;
        10: areturn
    Signature: #63                          // (Ljava/lang/String;Ljava/lang/String;Ljava/lang/String;Lscala/Option<Ljava/lang/String;>;)Lcoursier/credentials/DirectCredentials;
    MethodParameters:
      Name                           Flags
      host                           final
      username                       final
      password                       final
      realm                          final

  public static coursier.credentials.DirectCredentials apply(java.lang.String, java.lang.String, java.lang.String);
    descriptor: (Ljava/lang/String;Ljava/lang/String;Ljava/lang/String;)Lcoursier/credentials/DirectCredentials;
    flags: (0x0009) ACC_PUBLIC, ACC_STATIC
    Code:
      stack=4, locals=3, args_size=3
         0: getstatic     #37                 // Field coursier/credentials/DirectCredentials$.MODULE$:Lcoursier/credentials/DirectCredentials$;
         3: aload_0
         4: aload_1
         5: aload_2
         6: invokevirtual #70                 // Method coursier/credentials/DirectCredentials$.apply:(Ljava/lang/String;Ljava/lang/String;Ljava/lang/String;)Lcoursier/credentials/DirectCredentials;
         9: areturn
    MethodParameters:
      Name                           Flags
      host                           final
      username                       final
      password                       final

  public scala.collection.Iterator<java.lang.Object> productIterator();
    descriptor: ()Lscala/collection/Iterator;
    flags: (0x0001) ACC_PUBLIC
    Code:
      stack=1, locals=1, args_size=1
         0: aload_0
         1: invokestatic  #77                 // InterfaceMethod scala/Product.productIterator$:(Lscala/Product;)Lscala/collection/Iterator;
         4: areturn
      LineNumberTable:
        line 10: 0
      LocalVariableTable:
        Start  Length  Slot  Name   Signature
            0       5     0  this   Lcoursier/credentials/DirectCredentials;
    Signature: #73                          // ()Lscala/collection/Iterator<Ljava/lang/Object;>;

  public scala.collection.Iterator<java.lang.String> productElementNames();
    descriptor: ()Lscala/collection/Iterator;
    flags: (0x0001) ACC_PUBLIC
    Code:
      stack=1, locals=1, args_size=1
         0: aload_0
         1: invokestatic  #84                 // InterfaceMethod scala/Product.productElementNames$:(Lscala/Product;)Lscala/collection/Iterator;
         4: areturn
      LineNumberTable:
        line 10: 0
      LocalVariableTable:
        Start  Length  Slot  Name   Signature
            0       5     0  this   Lcoursier/credentials/DirectCredentials;
    Signature: #81                          // ()Lscala/collection/Iterator<Ljava/lang/String;>;

  public java.lang.String host();
    descriptor: ()Ljava/lang/String;
    flags: (0x0001) ACC_PUBLIC
    Code:
      stack=1, locals=1, args_size=1
         0: aload_0
         1: getfield      #87                 // Field host:Ljava/lang/String;
         4: areturn
      LineNumberTable:
        line 10: 0
      LocalVariableTable:
        Start  Length  Slot  Name   Signature
            0       5     0  this   Lcoursier/credentials/DirectCredentials;

  public scala.Option<java.lang.String> usernameOpt();
    descriptor: ()Lscala/Option;
    flags: (0x0001) ACC_PUBLIC
    Code:
      stack=1, locals=1, args_size=1
         0: aload_0
         1: getfield      #91                 // Field usernameOpt:Lscala/Option;
         4: areturn
      LineNumberTable:
        line 10: 0
      LocalVariableTable:
        Start  Length  Slot  Name   Signature
            0       5     0  this   Lcoursier/credentials/DirectCredentials;
    Signature: #89                          // ()Lscala/Option<Ljava/lang/String;>;

  public scala.Option<coursier.credentials.Password<java.lang.String>> passwordOpt();
    descriptor: ()Lscala/Option;
    flags: (0x0001) ACC_PUBLIC
    Code:
      stack=1, locals=1, args_size=1
         0: aload_0
         1: getfield      #94                 // Field passwordOpt:Lscala/Option;
         4: areturn
      LineNumberTable:
        line 10: 0
      LocalVariableTable:
        Start  Length  Slot  Name   Signature
            0       5     0  this   Lcoursier/credentials/DirectCredentials;
    Signature: #92                          // ()Lscala/Option<Lcoursier/credentials/Password<Ljava/lang/String;>;>;

  public scala.Option<java.lang.String> realm();
    descriptor: ()Lscala/Option;
    flags: (0x0001) ACC_PUBLIC
    Code:
      stack=1, locals=1, args_size=1
         0: aload_0
         1: getfield      #96                 // Field realm:Lscala/Option;
         4: areturn
      LineNumberTable:
        line 10: 0
      LocalVariableTable:
        Start  Length  Slot  Name   Signature
            0       5     0  this   Lcoursier/credentials/DirectCredentials;
    Signature: #89                          // ()Lscala/Option<Ljava/lang/String;>;

  public boolean optional();
    descriptor: ()Z
    flags: (0x0001) ACC_PUBLIC
    Code:
      stack=1, locals=1, args_size=1
         0: aload_0
         1: getfield      #98                 // Field optional:Z
         4: ireturn
      LineNumberTable:
        line 10: 0
      LocalVariableTable:
        Start  Length  Slot  Name   Signature
            0       5     0  this   Lcoursier/credentials/DirectCredentials;

  public boolean matchHost();
    descriptor: ()Z
    flags: (0x0001) ACC_PUBLIC
    Code:
      stack=1, locals=1, args_size=1
         0: aload_0
         1: getfield      #100                // Field matchHost:Z
         4: ireturn
      LineNumberTable:
        line 10: 0
      LocalVariableTable:
        Start  Length  Slot  Name   Signature
            0       5     0  this   Lcoursier/credentials/DirectCredentials;

  public boolean httpsOnly();
    descriptor: ()Z
    flags: (0x0001) ACC_PUBLIC
    Code:
      stack=1, locals=1, args_size=1
         0: aload_0
         1: getfield      #102                // Field httpsOnly:Z
         4: ireturn
      LineNumberTable:
        line 10: 0
      LocalVariableTable:
        Start  Length  Slot  Name   Signature
            0       5     0  this   Lcoursier/credentials/DirectCredentials;

  public boolean passOnRedirect();
    descriptor: ()Z
    flags: (0x0001) ACC_PUBLIC
    Code:
      stack=1, locals=1, args_size=1
         0: aload_0
         1: getfield      #104                // Field passOnRedirect:Z
         4: ireturn
      LineNumberTable:
        line 10: 0
      LocalVariableTable:
        Start  Length  Slot  Name   Signature
            0       5     0  this   Lcoursier/credentials/DirectCredentials;

  public coursier.credentials.DirectCredentials withUsername(java.lang.String);
    descriptor: (Ljava/lang/String;)Lcoursier/credentials/DirectCredentials;
    flags: (0x0001) ACC_PUBLIC
    Code:
      stack=4, locals=2, args_size=2
         0: aload_0
         1: new           #108                // class scala/Some
         4: dup
         5: aload_1
         6: invokespecial #112                // Method scala/Some."<init>":(Ljava/lang/Object;)V
         9: invokevirtual #116                // Method withUsernameOpt:(Lscala/Option;)Lcoursier/credentials/DirectCredentials;
        12: areturn
      LineNumberTable:
        line 25: 0
      LocalVariableTable:
        Start  Length  Slot  Name   Signature
            0      13     0  this   Lcoursier/credentials/DirectCredentials;
            0      13     1 username   Ljava/lang/String;
    MethodParameters:
      Name                           Flags
      username                       final

  public coursier.credentials.DirectCredentials withPassword(java.lang.String);
    descriptor: (Ljava/lang/String;)Lcoursier/credentials/DirectCredentials;
    flags: (0x0001) ACC_PUBLIC
    Code:
      stack=5, locals=2, args_size=2
         0: aload_0
         1: new           #108                // class scala/Some
         4: dup
         5: getstatic     #122                // Field coursier/credentials/Password$.MODULE$:Lcoursier/credentials/Password$;
         8: aload_1
         9: invokevirtual #125                // Method coursier/credentials/Password$.apply:(Ljava/lang/Object;)Lcoursier/credentials/Password;
        12: invokespecial #112                // Method scala/Some."<init>":(Ljava/lang/Object;)V
        15: invokevirtual #128                // Method withPasswordOpt:(Lscala/Option;)Lcoursier/credentials/DirectCredentials;
        18: areturn
      LineNumberTable:
        line 27: 0
      LocalVariableTable:
        Start  Length  Slot  Name   Signature
            0      19     0  this   Lcoursier/credentials/DirectCredentials;
            0      19     1 password   Ljava/lang/String;
    MethodParameters:
      Name                           Flags
      password                       final

  public coursier.credentials.DirectCredentials withRealm(java.lang.String);
    descriptor: (Ljava/lang/String;)Lcoursier/credentials/DirectCredentials;
    flags: (0x0001) ACC_PUBLIC
    Code:
      stack=3, locals=2, args_size=2
         0: aload_0
         1: getstatic     #134                // Field scala/Option$.MODULE$:Lscala/Option$;
         4: aload_1
         5: invokevirtual #137                // Method scala/Option$.apply:(Ljava/lang/Object;)Lscala/Option;
         8: invokevirtual #139                // Method withRealm:(Lscala/Option;)Lcoursier/credentials/DirectCredentials;
        11: areturn
      LineNumberTable:
        line 29: 0
      LocalVariableTable:
        Start  Length  Slot  Name   Signature
            0      12     0  this   Lcoursier/credentials/DirectCredentials;
            0      12     1 realm   Ljava/lang/String;
    MethodParameters:
      Name                           Flags
      realm                          final

  private boolean nonEmpty();
    descriptor: ()Z
    flags: (0x0002) ACC_PRIVATE
    Code:
      stack=1, locals=1, args_size=1
         0: aload_0
         1: invokevirtual #142                // Method usernameOpt:()Lscala/Option;
         4: invokevirtual #146                // Method scala/Option.nonEmpty:()Z
         7: ifeq          24
        10: aload_0
        11: invokevirtual #148                // Method passwordOpt:()Lscala/Option;
        14: invokevirtual #146                // Method scala/Option.nonEmpty:()Z
        17: ifeq          24
        20: iconst_1
        21: goto          25
        24: iconst_0
        25: ireturn
      StackMapTable: number_of_entries = 2
        frame_type = 24 /* same */
        frame_type = 64 /* same_locals_1_stack_item */
          stack = [ int ]
      LineNumberTable:
        line 32: 0
      LocalVariableTable:
        Start  Length  Slot  Name   Signature
            0      26     0  this   Lcoursier/credentials/DirectCredentials;

  public boolean autoMatches(java.lang.String, scala.Option<java.lang.String>);
    descriptor: (Ljava/lang/String;Lscala/Option;)Z
    flags: (0x0001) ACC_PUBLIC
    Code:
      stack=2, locals=6, args_size=3
         0: aload_0
         1: invokespecial #154                // Method nonEmpty:()Z
         4: ifeq          119
         7: aload_0
         8: invokevirtual #156                // Method matchHost:()Z
        11: ifeq          119
        14: getstatic     #161                // Field scala/util/Try$.MODULE$:Lscala/util/Try$;
        17: aload_1
        18: invokedynamic #182,  0            // InvokeDynamic #0:apply:(Ljava/lang/String;)Lscala/Function0;
        23: invokevirtual #185                // Method scala/util/Try$.apply:(Lscala/Function0;)Lscala/util/Try;
        26: invokevirtual #190                // Method scala/util/Try.toOption:()Lscala/Option;
        29: astore_3
        30: aload_3
        31: invokedynamic #201,  0            // InvokeDynamic #1:apply:()Lscala/Function1;
        36: invokevirtual #205                // Method scala/Option.flatMap:(Lscala/Function1;)Lscala/Option;
        39: astore        4
        41: aload_3
        42: invokedynamic #210,  0            // InvokeDynamic #2:apply:()Lscala/Function1;
        47: invokevirtual #205                // Method scala/Option.flatMap:(Lscala/Function1;)Lscala/Option;
        50: astore        5
        52: aload         4
        54: ldc           #212                // String http
        56: invokevirtual #216                // Method scala/Option.contains:(Ljava/lang/Object;)Z
        59: ifeq          69
        62: aload_0
        63: invokevirtual #218                // Method httpsOnly:()Z
        66: ifeq          79
        69: aload         4
        71: ldc           #220                // String https
        73: invokevirtual #216                // Method scala/Option.contains:(Ljava/lang/Object;)Z
        76: ifeq          111
        79: aload         5
        81: aload_0
        82: invokevirtual #222                // Method host:()Ljava/lang/String;
        85: invokevirtual #216                // Method scala/Option.contains:(Ljava/lang/Object;)Z
        88: ifeq          111
        91: aload_0
        92: invokevirtual #224                // Method realm:()Lscala/Option;
        95: aload_2
        96: invokedynamic #232,  0            // InvokeDynamic #3:apply:(Lscala/Option;)Lscala/Function1;
       101: invokevirtual #236                // Method scala/Option.forall:(Lscala/Function1;)Z
       104: ifeq          111
       107: iconst_1
       108: goto          112
       111: iconst_0
       112: ifeq          119
       115: iconst_1
       116: goto          120
       119: iconst_0
       120: ireturn
      StackMapTable: number_of_entries = 6
        frame_type = 254 /* append */
          offset_delta = 69
          locals = [ class scala/Option, class scala/Option, class scala/Option ]
        frame_type = 9 /* same */
        frame_type = 31 /* same */
        frame_type = 64 /* same_locals_1_stack_item */
          stack = [ int ]
        frame_type = 248 /* chop */
          offset_delta = 6
        frame_type = 64 /* same_locals_1_stack_item */
          stack = [ int ]
      LineNumberTable:
        line 36: 0
        line 37: 14
        line 38: 30
        line 39: 41
        line 40: 52
        line 41: 79
        line 42: 91
      LocalVariableTable:
        Start  Length  Slot  Name   Signature
           30      82     3 uriOpt   Lscala/Option;
           41      71     4 schemeOpt   Lscala/Option;
           52      60     5 hostOpt   Lscala/Option;
            0     121     0  this   Lcoursier/credentials/DirectCredentials;
            0     121     1   url   Ljava/lang/String;
            0     121     2 realm0   Lscala/Option;
    Signature: #151                         // (Ljava/lang/String;Lscala/Option<Ljava/lang/String;>;)Z
    MethodParameters:
      Name                           Flags
      url                            final
      realm0                         final

  public boolean matches(java.lang.String, java.lang.String);
    descriptor: (Ljava/lang/String;Ljava/lang/String;)Z
    flags: (0x0001) ACC_PUBLIC
    Code:
      stack=2, locals=7, args_size=3
         0: aload_0
         1: invokespecial #154                // Method nonEmpty:()Z
         4: ifeq          126
         7: getstatic     #161                // Field scala/util/Try$.MODULE$:Lscala/util/Try$;
        10: aload_1
        11: invokedynamic #247,  0            // InvokeDynamic #4:apply:(Ljava/lang/String;)Lscala/Function0;
        16: invokevirtual #185                // Method scala/util/Try$.apply:(Lscala/Function0;)Lscala/util/Try;
        19: invokevirtual #190                // Method scala/util/Try.toOption:()Lscala/Option;
        22: astore_3
        23: aload_3
        24: invokedynamic #252,  0            // InvokeDynamic #5:apply:()Lscala/Function1;
        29: invokevirtual #205                // Method scala/Option.flatMap:(Lscala/Function1;)Lscala/Option;
        32: astore        4
        34: aload_3
        35: invokedynamic #257,  0            // InvokeDynamic #6:apply:()Lscala/Function1;
        40: invokevirtual #205                // Method scala/Option.flatMap:(Lscala/Function1;)Lscala/Option;
        43: astore        5
        45: aload_3
        46: invokedynamic #262,  0            // InvokeDynamic #7:apply:()Lscala/Function1;
        51: invokevirtual #205                // Method scala/Option.flatMap:(Lscala/Function1;)Lscala/Option;
        54: astore        6
        56: aload         6
        58: invokevirtual #265                // Method scala/Option.isEmpty:()Z
        61: ifeq          118
        64: aload         4
        66: ldc           #212                // String http
        68: invokevirtual #216                // Method scala/Option.contains:(Ljava/lang/Object;)Z
        71: ifeq          81
        74: aload_0
        75: invokevirtual #218                // Method httpsOnly:()Z
        78: ifeq          91
        81: aload         4
        83: ldc           #220                // String https
        85: invokevirtual #216                // Method scala/Option.contains:(Ljava/lang/Object;)Z
        88: ifeq          118
        91: aload         5
        93: aload_0
        94: invokevirtual #222                // Method host:()Ljava/lang/String;
        97: invokevirtual #216                // Method scala/Option.contains:(Ljava/lang/Object;)Z
       100: ifeq          118
       103: aload_0
       104: invokevirtual #142                // Method usernameOpt:()Lscala/Option;
       107: aload_2
       108: invokevirtual #216                // Method scala/Option.contains:(Ljava/lang/Object;)Z
       111: ifeq          118
       114: iconst_1
       115: goto          119
       118: iconst_0
       119: ifeq          126
       122: iconst_1
       123: goto          127
       126: iconst_0
       127: ireturn
      StackMapTable: number_of_entries = 6
        frame_type = 255 /* full_frame */
          offset_delta = 81
          locals = [ class coursier/credentials/DirectCredentials, class java/lang/String, class java/lang/String, class scala/Option, class scala/Option, class scala/Option, class scala/Option ]
          stack = []
        frame_type = 9 /* same */
        frame_type = 26 /* same */
        frame_type = 64 /* same_locals_1_stack_item */
          stack = [ int ]
        frame_type = 255 /* full_frame */
          offset_delta = 6
          locals = [ class coursier/credentials/DirectCredentials, class java/lang/String, class java/lang/String ]
          stack = []
        frame_type = 64 /* same_locals_1_stack_item */
          stack = [ int ]
      LineNumberTable:
        line 47: 0
        line 48: 7
        line 49: 23
        line 50: 34
        line 51: 45
        line 53: 56
        line 54: 64
        line 55: 91
        line 56: 103
      LocalVariableTable:
        Start  Length  Slot  Name   Signature
           23      96     3 uriOpt   Lscala/Option;
           34      85     4 schemeOpt   Lscala/Option;
           45      74     5 hostOpt   Lscala/Option;
           56      63     6 userInfoOpt   Lscala/Option;
            0     128     0  this   Lcoursier/credentials/DirectCredentials;
            0     128     1   url   Ljava/lang/String;
            0     128     2  user   Ljava/lang/String;
    MethodParameters:
      Name                           Flags
      url                            final
      user                           final

  public coursier.core.Authentication authentication();
    descriptor: ()Lcoursier/core/Authentication;
    flags: (0x0001) ACC_PUBLIC
    Code:
      stack=7, locals=7, args_size=1
         0: aload_0
         1: invokevirtual #142                // Method usernameOpt:()Lscala/Option;
         4: invokedynamic #278,  0            // InvokeDynamic #8:apply:()Lscala/Function0;
         9: invokevirtual #282                // Method scala/Option.getOrElse:(Lscala/Function0;)Ljava/lang/Object;
        12: checkcast     #267                // class java/lang/String
        15: astore_1
        16: aload_0
        17: invokevirtual #148                // Method passwordOpt:()Lscala/Option;
        20: invokedynamic #289,  0            // InvokeDynamic #9:apply:()Lscala/Function1;
        25: invokevirtual #292                // Method scala/Option.map:(Lscala/Function1;)Lscala/Option;
        28: astore_2
        29: aload_0
        30: invokevirtual #224                // Method realm:()Lscala/Option;
        33: astore_3
        34: aload_0
        35: invokevirtual #294                // Method optional:()Z
        38: istore        4
        40: aload_0
        41: invokevirtual #218                // Method httpsOnly:()Z
        44: istore        5
        46: aload_0
        47: invokevirtual #296                // Method passOnRedirect:()Z
        50: istore        6
        52: getstatic     #301                // Field coursier/core/Authentication$.MODULE$:Lcoursier/core/Authentication$;
        55: aload_1
        56: aload_2
        57: iload         4
        59: aload_3
        60: iload         5
        62: iload         6
        64: invokevirtual #304                // Method coursier/core/Authentication$.apply:(Ljava/lang/String;Lscala/Option;ZLscala/Option;ZZ)Lcoursier/core/Authentication;
        67: areturn
      LineNumberTable:
        line 61: 0
        line 62: 16
        line 63: 29
        line 64: 34
        line 65: 40
        line 66: 46
        line 60: 52
        line 61: 55
        line 62: 56
        line 64: 57
        line 63: 59
        line 65: 60
        line 66: 62
      LocalVariableTable:
        Start  Length  Slot  Name   Signature
           16      51     1   x$1   Ljava/lang/String;
           29      38     2   x$2   Lscala/Option;
           34      33     3   x$3   Lscala/Option;
           40      27     4   x$4   Z
           46      21     5   x$5   Z
           52      15     6   x$6   Z
            0      68     0  this   Lcoursier/credentials/DirectCredentials;

  public scala.collection.immutable.Seq<coursier.credentials.DirectCredentials> get();
    descriptor: ()Lscala/collection/immutable/Seq;
    flags: (0x0001) ACC_PUBLIC
    Code:
      stack=4, locals=1, args_size=1
         0: new           #315                // class scala/collection/immutable/$colon$colon
         3: dup
         4: aload_0
         5: getstatic     #320                // Field scala/collection/immutable/Nil$.MODULE$:Lscala/collection/immutable/Nil$;
         8: invokespecial #323                // Method scala/collection/immutable/$colon$colon."<init>":(Ljava/lang/Object;Lscala/collection/immutable/List;)V
        11: checkcast     #325                // class scala/collection/immutable/Seq
        14: areturn
      LineNumberTable:
        line 70: 0
      LocalVariableTable:
        Start  Length  Slot  Name   Signature
            0      15     0  this   Lcoursier/credentials/DirectCredentials;
    Signature: #313                         // ()Lscala/collection/immutable/Seq<Lcoursier/credentials/DirectCredentials;>;

  public coursier.credentials.DirectCredentials withHost(java.lang.String);
    descriptor: (Ljava/lang/String;)Lcoursier/credentials/DirectCredentials;
    flags: (0x0001) ACC_PUBLIC
    Code:
      stack=10, locals=2, args_size=2
         0: new           #2                  // class coursier/credentials/DirectCredentials
         3: dup
         4: aload_1
         5: aload_0
         6: invokevirtual #142                // Method usernameOpt:()Lscala/Option;
         9: aload_0
        10: invokevirtual #148                // Method passwordOpt:()Lscala/Option;
        13: aload_0
        14: invokevirtual #224                // Method realm:()Lscala/Option;
        17: aload_0
        18: invokevirtual #294                // Method optional:()Z
        21: aload_0
        22: invokevirtual #156                // Method matchHost:()Z
        25: aload_0
        26: invokevirtual #218                // Method httpsOnly:()Z
        29: aload_0
        30: invokevirtual #296                // Method passOnRedirect:()Z
        33: invokespecial #329                // Method "<init>":(Ljava/lang/String;Lscala/Option;Lscala/Option;Lscala/Option;ZZZZ)V
        36: areturn
      LineNumberTable:
        line 10: 0
      LocalVariableTable:
        Start  Length  Slot  Name   Signature
            0      37     0  this   Lcoursier/credentials/DirectCredentials;
            0      37     1  host   Ljava/lang/String;
    MethodParameters:
      Name                           Flags
      host                           final

  public coursier.credentials.DirectCredentials withUsernameOpt(scala.Option<java.lang.String>);
    descriptor: (Lscala/Option;)Lcoursier/credentials/DirectCredentials;
    flags: (0x0001) ACC_PUBLIC
    Code:
      stack=10, locals=2, args_size=2
         0: new           #2                  // class coursier/credentials/DirectCredentials
         3: dup
         4: aload_0
         5: invokevirtual #222                // Method host:()Ljava/lang/String;
         8: aload_1
         9: aload_0
        10: invokevirtual #148                // Method passwordOpt:()Lscala/Option;
        13: aload_0
        14: invokevirtual #224                // Method realm:()Lscala/Option;
        17: aload_0
        18: invokevirtual #294                // Method optional:()Z
        21: aload_0
        22: invokevirtual #156                // Method matchHost:()Z
        25: aload_0
        26: invokevirtual #218                // Method httpsOnly:()Z
        29: aload_0
        30: invokevirtual #296                // Method passOnRedirect:()Z
        33: invokespecial #329                // Method "<init>":(Ljava/lang/String;Lscala/Option;Lscala/Option;Lscala/Option;ZZZZ)V
        36: areturn
      LineNumberTable:
        line 10: 0
      LocalVariableTable:
        Start  Length  Slot  Name   Signature
            0      37     0  this   Lcoursier/credentials/DirectCredentials;
            0      37     1 usernameOpt   Lscala/Option;
    Signature: #330                         // (Lscala/Option<Ljava/lang/String;>;)Lcoursier/credentials/DirectCredentials;
    MethodParameters:
      Name                           Flags
      usernameOpt                    final

  public coursier.credentials.DirectCredentials withPasswordOpt(scala.Option<coursier.credentials.Password<java.lang.String>>);
    descriptor: (Lscala/Option;)Lcoursier/credentials/DirectCredentials;
    flags: (0x0001) ACC_PUBLIC
    Code:
      stack=10, locals=2, args_size=2
         0: new           #2                  // class coursier/credentials/DirectCredentials
         3: dup
         4: aload_0
         5: invokevirtual #222                // Method host:()Ljava/lang/String;
         8: aload_0
         9: invokevirtual #142                // Method usernameOpt:()Lscala/Option;
        12: aload_1
        13: aload_0
        14: invokevirtual #224                // Method realm:()Lscala/Option;
        17: aload_0
        18: invokevirtual #294                // Method optional:()Z
        21: aload_0
        22: invokevirtual #156                // Method matchHost:()Z
        25: aload_0
        26: invokevirtual #218                // Method httpsOnly:()Z
        29: aload_0
        30: invokevirtual #296                // Method passOnRedirect:()Z
        33: invokespecial #329                // Method "<init>":(Ljava/lang/String;Lscala/Option;Lscala/Option;Lscala/Option;ZZZZ)V
        36: areturn
      LineNumberTable:
        line 10: 0
      LocalVariableTable:
        Start  Length  Slot  Name   Signature
            0      37     0  this   Lcoursier/credentials/DirectCredentials;
            0      37     1 passwordOpt   Lscala/Option;
    Signature: #331                         // (Lscala/Option<Lcoursier/credentials/Password<Ljava/lang/String;>;>;)Lcoursier/credentials/DirectCredentials;
    MethodParameters:
      Name                           Flags
      passwordOpt                    final

  public coursier.credentials.DirectCredentials withRealm(scala.Option<java.lang.String>);
    descriptor: (Lscala/Option;)Lcoursier/credentials/DirectCredentials;
    flags: (0x0001) ACC_PUBLIC
    Code:
      stack=10, locals=2, args_size=2
         0: new           #2                  // class coursier/credentials/DirectCredentials
         3: dup
         4: aload_0
         5: invokevirtual #222                // Method host:()Ljava/lang/String;
         8: aload_0
         9: invokevirtual #142                // Method usernameOpt:()Lscala/Option;
        12: aload_0
        13: invokevirtual #148                // Method passwordOpt:()Lscala/Option;
        16: aload_1
        17: aload_0
        18: invokevirtual #294                // Method optional:()Z
        21: aload_0
        22: invokevirtual #156                // Method matchHost:()Z
        25: aload_0
        26: invokevirtual #218                // Method httpsOnly:()Z
        29: aload_0
        30: invokevirtual #296                // Method passOnRedirect:()Z
        33: invokespecial #329                // Method "<init>":(Ljava/lang/String;Lscala/Option;Lscala/Option;Lscala/Option;ZZZZ)V
        36: areturn
      LineNumberTable:
        line 10: 0
      LocalVariableTable:
        Start  Length  Slot  Name   Signature
            0      37     0  this   Lcoursier/credentials/DirectCredentials;
            0      37     1 realm   Lscala/Option;
    Signature: #330                         // (Lscala/Option<Ljava/lang/String;>;)Lcoursier/credentials/DirectCredentials;
    MethodParameters:
      Name                           Flags
      realm                          final

  public coursier.credentials.DirectCredentials withOptional(boolean);
    descriptor: (Z)Lcoursier/credentials/DirectCredentials;
    flags: (0x0001) ACC_PUBLIC
    Code:
      stack=10, locals=2, args_size=2
         0: new           #2                  // class coursier/credentials/DirectCredentials
         3: dup
         4: aload_0
         5: invokevirtual #222                // Method host:()Ljava/lang/String;
         8: aload_0
         9: invokevirtual #142                // Method usernameOpt:()Lscala/Option;
        12: aload_0
        13: invokevirtual #148                // Method passwordOpt:()Lscala/Option;
        16: aload_0
        17: invokevirtual #224                // Method realm:()Lscala/Option;
        20: iload_1
        21: aload_0
        22: invokevirtual #156                // Method matchHost:()Z
        25: aload_0
        26: invokevirtual #218                // Method httpsOnly:()Z
        29: aload_0
        30: invokevirtual #296                // Method passOnRedirect:()Z
        33: invokespecial #329                // Method "<init>":(Ljava/lang/String;Lscala/Option;Lscala/Option;Lscala/Option;ZZZZ)V
        36: areturn
      LineNumberTable:
        line 10: 0
      LocalVariableTable:
        Start  Length  Slot  Name   Signature
            0      37     0  this   Lcoursier/credentials/DirectCredentials;
            0      37     1 optional   Z
    MethodParameters:
      Name                           Flags
      optional                       final

  public coursier.credentials.DirectCredentials withMatchHost(boolean);
    descriptor: (Z)Lcoursier/credentials/DirectCredentials;
    flags: (0x0001) ACC_PUBLIC
    Code:
      stack=10, locals=2, args_size=2
         0: new           #2                  // class coursier/credentials/DirectCredentials
         3: dup
         4: aload_0
         5: invokevirtual #222                // Method host:()Ljava/lang/String;
         8: aload_0
         9: invokevirtual #142                // Method usernameOpt:()Lscala/Option;
        12: aload_0
        13: invokevirtual #148                // Method passwordOpt:()Lscala/Option;
        16: aload_0
        17: invokevirtual #224                // Method realm:()Lscala/Option;
        20: aload_0
        21: invokevirtual #294                // Method optional:()Z
        24: iload_1
        25: aload_0
        26: invokevirtual #218                // Method httpsOnly:()Z
        29: aload_0
        30: invokevirtual #296                // Method passOnRedirect:()Z
        33: invokespecial #329                // Method "<init>":(Ljava/lang/String;Lscala/Option;Lscala/Option;Lscala/Option;ZZZZ)V
        36: areturn
      LineNumberTable:
        line 10: 0
      LocalVariableTable:
        Start  Length  Slot  Name   Signature
            0      37     0  this   Lcoursier/credentials/DirectCredentials;
            0      37     1 matchHost   Z
    MethodParameters:
      Name                           Flags
      matchHost                      final

  public coursier.credentials.DirectCredentials withHttpsOnly(boolean);
    descriptor: (Z)Lcoursier/credentials/DirectCredentials;
    flags: (0x0001) ACC_PUBLIC
    Code:
      stack=10, locals=2, args_size=2
         0: new           #2                  // class coursier/credentials/DirectCredentials
         3: dup
         4: aload_0
         5: invokevirtual #222                // Method host:()Ljava/lang/String;
         8: aload_0
         9: invokevirtual #142                // Method usernameOpt:()Lscala/Option;
        12: aload_0
        13: invokevirtual #148                // Method passwordOpt:()Lscala/Option;
        16: aload_0
        17: invokevirtual #224                // Method realm:()Lscala/Option;
        20: aload_0
        21: invokevirtual #294                // Method optional:()Z
        24: aload_0
        25: invokevirtual #156                // Method matchHost:()Z
        28: iload_1
        29: aload_0
        30: invokevirtual #296                // Method passOnRedirect:()Z
        33: invokespecial #329                // Method "<init>":(Ljava/lang/String;Lscala/Option;Lscala/Option;Lscala/Option;ZZZZ)V
        36: areturn
      LineNumberTable:
        line 10: 0
      LocalVariableTable:
        Start  Length  Slot  Name   Signature
            0      37     0  this   Lcoursier/credentials/DirectCredentials;
            0      37     1 httpsOnly   Z
    MethodParameters:
      Name                           Flags
      httpsOnly                      final

  public coursier.credentials.DirectCredentials withPassOnRedirect(boolean);
    descriptor: (Z)Lcoursier/credentials/DirectCredentials;
    flags: (0x0001) ACC_PUBLIC
    Code:
      stack=10, locals=2, args_size=2
         0: new           #2                  // class coursier/credentials/DirectCredentials
         3: dup
         4: aload_0
         5: invokevirtual #222                // Method host:()Ljava/lang/String;
         8: aload_0
         9: invokevirtual #142                // Method usernameOpt:()Lscala/Option;
        12: aload_0
        13: invokevirtual #148                // Method passwordOpt:()Lscala/Option;
        16: aload_0
        17: invokevirtual #224                // Method realm:()Lscala/Option;
        20: aload_0
        21: invokevirtual #294                // Method optional:()Z
        24: aload_0
        25: invokevirtual #156                // Method matchHost:()Z
        28: aload_0
        29: invokevirtual #218                // Method httpsOnly:()Z
        32: iload_1
        33: invokespecial #329                // Method "<init>":(Ljava/lang/String;Lscala/Option;Lscala/Option;Lscala/Option;ZZZZ)V
        36: areturn
      LineNumberTable:
        line 10: 0
      LocalVariableTable:
        Start  Length  Slot  Name   Signature
            0      37     0  this   Lcoursier/credentials/DirectCredentials;
            0      37     1 passOnRedirect   Z
    MethodParameters:
      Name                           Flags
      passOnRedirect                 final

  public java.lang.String toString();
    descriptor: ()Ljava/lang/String;
    flags: (0x0001) ACC_PUBLIC
    Code:
      stack=3, locals=2, args_size=1
         0: new           #339                // class java/lang/StringBuilder
         3: dup
         4: ldc_w         #341                // String DirectCredentials(
         7: invokespecial #344                // Method java/lang/StringBuilder."<init>":(Ljava/lang/String;)V
        10: astore_1
        11: aload_1
        12: aload_0
        13: invokevirtual #222                // Method host:()Ljava/lang/String;
        16: invokestatic  #348                // Method java/lang/String.valueOf:(Ljava/lang/Object;)Ljava/lang/String;
        19: invokevirtual #352                // Method java/lang/StringBuilder.append:(Ljava/lang/String;)Ljava/lang/StringBuilder;
        22: pop
        23: aload_1
        24: ldc_w         #354                // String ,
        27: invokevirtual #352                // Method java/lang/StringBuilder.append:(Ljava/lang/String;)Ljava/lang/StringBuilder;
        30: pop
        31: aload_1
        32: aload_0
        33: invokevirtual #142                // Method usernameOpt:()Lscala/Option;
        36: invokestatic  #348                // Method java/lang/String.valueOf:(Ljava/lang/Object;)Ljava/lang/String;
        39: invokevirtual #352                // Method java/lang/StringBuilder.append:(Ljava/lang/String;)Ljava/lang/StringBuilder;
        42: pop
        43: aload_1
        44: ldc_w         #354                // String ,
        47: invokevirtual #352                // Method java/lang/StringBuilder.append:(Ljava/lang/String;)Ljava/lang/StringBuilder;
        50: pop
        51: aload_1
        52: aload_0
        53: invokevirtual #148                // Method passwordOpt:()Lscala/Option;
        56: invokestatic  #348                // Method java/lang/String.valueOf:(Ljava/lang/Object;)Ljava/lang/String;
        59: invokevirtual #352                // Method java/lang/StringBuilder.append:(Ljava/lang/String;)Ljava/lang/StringBuilder;
        62: pop
        63: aload_1
        64: ldc_w         #354                // String ,
        67: invokevirtual #352                // Method java/lang/StringBuilder.append:(Ljava/lang/String;)Ljava/lang/StringBuilder;
        70: pop
        71: aload_1
        72: aload_0
        73: invokevirtual #224                // Method realm:()Lscala/Option;
        76: invokestatic  #348                // Method java/lang/String.valueOf:(Ljava/lang/Object;)Ljava/lang/String;
        79: invokevirtual #352                // Method java/lang/StringBuilder.append:(Ljava/lang/String;)Ljava/lang/StringBuilder;
        82: pop
        83: aload_1
        84: ldc_w         #354                // String ,
        87: invokevirtual #352                // Method java/lang/StringBuilder.append:(Ljava/lang/String;)Ljava/lang/StringBuilder;
        90: pop
        91: aload_1
        92: aload_0
        93: invokevirtual #294                // Method optional:()Z
        96: invokestatic  #357                // Method java/lang/String.valueOf:(Z)Ljava/lang/String;
        99: invokevirtual #352                // Method java/lang/StringBuilder.append:(Ljava/lang/String;)Ljava/lang/StringBuilder;
       102: pop
       103: aload_1
       104: ldc_w         #354                // String ,
       107: invokevirtual #352                // Method java/lang/StringBuilder.append:(Ljava/lang/String;)Ljava/lang/StringBuilder;
       110: pop
       111: aload_1
       112: aload_0
       113: invokevirtual #156                // Method matchHost:()Z
       116: invokestatic  #357                // Method java/lang/String.valueOf:(Z)Ljava/lang/String;
       119: invokevirtual #352                // Method java/lang/StringBuilder.append:(Ljava/lang/String;)Ljava/lang/StringBuilder;
       122: pop
       123: aload_1
       124: ldc_w         #354                // String ,
       127: invokevirtual #352                // Method java/lang/StringBuilder.append:(Ljava/lang/String;)Ljava/lang/StringBuilder;
       130: pop
       131: aload_1
       132: aload_0
       133: invokevirtual #218                // Method httpsOnly:()Z
       136: invokestatic  #357                // Method java/lang/String.valueOf:(Z)Ljava/lang/String;
       139: invokevirtual #352                // Method java/lang/StringBuilder.append:(Ljava/lang/String;)Ljava/lang/StringBuilder;
       142: pop
       143: aload_1
       144: ldc_w         #354                // String ,
       147: invokevirtual #352                // Method java/lang/StringBuilder.append:(Ljava/lang/String;)Ljava/lang/StringBuilder;
       150: pop
       151: aload_1
       152: aload_0
       153: invokevirtual #296                // Method passOnRedirect:()Z
       156: invokestatic  #357                // Method java/lang/String.valueOf:(Z)Ljava/lang/String;
       159: invokevirtual #352                // Method java/lang/StringBuilder.append:(Ljava/lang/String;)Ljava/lang/StringBuilder;
       162: pop
       163: aload_1
       164: ldc_w         #359                // String )
       167: invokevirtual #352                // Method java/lang/StringBuilder.append:(Ljava/lang/String;)Ljava/lang/StringBuilder;
       170: pop
       171: aload_1
       172: invokevirtual #361                // Method java/lang/StringBuilder.toString:()Ljava/lang/String;
       175: areturn
      LineNumberTable:
        line 10: 0
      LocalVariableTable:
        Start  Length  Slot  Name   Signature
           11     164     1     b   Ljava/lang/StringBuilder;
            0     176     0  this   Lcoursier/credentials/DirectCredentials;

  public boolean canEqual(java.lang.Object);
    descriptor: (Ljava/lang/Object;)Z
    flags: (0x0001) ACC_PUBLIC
    Code:
      stack=1, locals=2, args_size=2
         0: aload_1
         1: ifnull        15
         4: aload_1
         5: instanceof    #2                  // class coursier/credentials/DirectCredentials
         8: ifeq          15
        11: iconst_1
        12: goto          16
        15: iconst_0
        16: ireturn
      StackMapTable: number_of_entries = 2
        frame_type = 15 /* same */
        frame_type = 64 /* same_locals_1_stack_item */
          stack = [ int ]
      LineNumberTable:
        line 10: 0
      LocalVariableTable:
        Start  Length  Slot  Name   Signature
            0      17     0  this   Lcoursier/credentials/DirectCredentials;
            0      17     1   obj   Ljava/lang/Object;
    MethodParameters:
      Name                           Flags
      obj                            final

  public boolean equals(java.lang.Object);
    descriptor: (Ljava/lang/Object;)Z
    flags: (0x0001) ACC_PUBLIC
    Code:
      stack=2, locals=7, args_size=2
         0: aload_0
         1: aload_1
         2: if_acmpeq     195
         5: aload_0
         6: aload_1
         7: invokevirtual #369                // Method canEqual:(Ljava/lang/Object;)Z
        10: ifeq          199
        13: aload_1
        14: checkcast     #2                  // class coursier/credentials/DirectCredentials
        17: astore_2
        18: iconst_1
        19: ifeq          191
        22: aload_0
        23: invokevirtual #222                // Method host:()Ljava/lang/String;
        26: aload_2
        27: invokevirtual #222                // Method host:()Ljava/lang/String;
        30: astore_3
        31: dup
        32: ifnonnull     43
        35: pop
        36: aload_3
        37: ifnull        50
        40: goto          191
        43: aload_3
        44: invokevirtual #373                // Method java/lang/Object.equals:(Ljava/lang/Object;)Z
        47: ifeq          191
        50: aload_0
        51: invokevirtual #142                // Method usernameOpt:()Lscala/Option;
        54: aload_2
        55: invokevirtual #142                // Method usernameOpt:()Lscala/Option;
        58: astore        4
        60: dup
        61: ifnonnull     73
        64: pop
        65: aload         4
        67: ifnull        81
        70: goto          191
        73: aload         4
        75: invokevirtual #373                // Method java/lang/Object.equals:(Ljava/lang/Object;)Z
        78: ifeq          191
        81: aload_0
        82: invokevirtual #148                // Method passwordOpt:()Lscala/Option;
        85: aload_2
        86: invokevirtual #148                // Method passwordOpt:()Lscala/Option;
        89: astore        5
        91: dup
        92: ifnonnull     104
        95: pop
        96: aload         5
        98: ifnull        112
       101: goto          191
       104: aload         5
       106: invokevirtual #373                // Method java/lang/Object.equals:(Ljava/lang/Object;)Z
       109: ifeq          191
       112: aload_0
       113: invokevirtual #224                // Method realm:()Lscala/Option;
       116: aload_2
       117: invokevirtual #224                // Method realm:()Lscala/Option;
       120: astore        6
       122: dup
       123: ifnonnull     135
       126: pop
       127: aload         6
       129: ifnull        143
       132: goto          191
       135: aload         6
       137: invokevirtual #373                // Method java/lang/Object.equals:(Ljava/lang/Object;)Z
       140: ifeq          191
       143: aload_0
       144: invokevirtual #294                // Method optional:()Z
       147: aload_2
       148: invokevirtual #294                // Method optional:()Z
       151: if_icmpne     191
       154: aload_0
       155: invokevirtual #156                // Method matchHost:()Z
       158: aload_2
       159: invokevirtual #156                // Method matchHost:()Z
       162: if_icmpne     191
       165: aload_0
       166: invokevirtual #218                // Method httpsOnly:()Z
       169: aload_2
       170: invokevirtual #218                // Method httpsOnly:()Z
       173: if_icmpne     191
       176: aload_0
       177: invokevirtual #296                // Method passOnRedirect:()Z
       180: aload_2
       181: invokevirtual #296                // Method passOnRedirect:()Z
       184: if_icmpne     191
       187: iconst_1
       188: goto          192
       191: iconst_0
       192: ifeq          199
       195: iconst_1
       196: goto          200
       199: iconst_0
       200: ireturn
      StackMapTable: number_of_entries = 13
        frame_type = 255 /* full_frame */
          offset_delta = 43
          locals = [ class coursier/credentials/DirectCredentials, class java/lang/Object, class coursier/credentials/DirectCredentials, class java/lang/String ]
          stack = [ class java/lang/String ]
        frame_type = 6 /* same */
        frame_type = 255 /* full_frame */
          offset_delta = 22
          locals = [ class coursier/credentials/DirectCredentials, class java/lang/Object, class coursier/credentials/DirectCredentials, class java/lang/String, class scala/Option ]
          stack = [ class scala/Option ]
        frame_type = 7 /* same */
        frame_type = 255 /* full_frame */
          offset_delta = 22
          locals = [ class coursier/credentials/DirectCredentials, class java/lang/Object, class coursier/credentials/DirectCredentials, class java/lang/String, class scala/Option, class scala/Option ]
          stack = [ class scala/Option ]
        frame_type = 7 /* same */
        frame_type = 255 /* full_frame */
          offset_delta = 22
          locals = [ class coursier/credentials/DirectCredentials, class java/lang/Object, class coursier/credentials/DirectCredentials, class java/lang/String, class scala/Option, class scala/Option, class scala/Option ]
          stack = [ class scala/Option ]
        frame_type = 7 /* same */
        frame_type = 255 /* full_frame */
          offset_delta = 47
          locals = [ class coursier/credentials/DirectCredentials, class java/lang/Object, class coursier/credentials/DirectCredentials ]
          stack = []
        frame_type = 64 /* same_locals_1_stack_item */
          stack = [ int ]
        frame_type = 250 /* chop */
          offset_delta = 2
        frame_type = 3 /* same */
        frame_type = 64 /* same_locals_1_stack_item */
          stack = [ int ]
      LineNumberTable:
        line 10: 0
      LocalVariableTable:
        Start  Length  Slot  Name   Signature
           18     174     2 other   Lcoursier/credentials/DirectCredentials;
            0     201     0  this   Lcoursier/credentials/DirectCredentials;
            0     201     1   obj   Ljava/lang/Object;
    MethodParameters:
      Name                           Flags
      obj                            final

  public int hashCode();
    descriptor: ()I
    flags: (0x0001) ACC_PUBLIC
    Code:
      stack=2, locals=2, args_size=1
         0: bipush        17
         2: ldc_w         #378                // String DirectCredentials
         5: invokestatic  #384                // Method scala/runtime/Statics.anyHash:(Ljava/lang/Object;)I
         8: iadd
         9: istore_1
        10: bipush        37
        12: iload_1
        13: imul
        14: aload_0
        15: invokevirtual #222                // Method host:()Ljava/lang/String;
        18: invokestatic  #384                // Method scala/runtime/Statics.anyHash:(Ljava/lang/Object;)I
        21: iadd
        22: istore_1
        23: bipush        37
        25: iload_1
        26: imul
        27: aload_0
        28: invokevirtual #142                // Method usernameOpt:()Lscala/Option;
        31: invokestatic  #384                // Method scala/runtime/Statics.anyHash:(Ljava/lang/Object;)I
        34: iadd
        35: istore_1
        36: bipush        37
        38: iload_1
        39: imul
        40: aload_0
        41: invokevirtual #148                // Method passwordOpt:()Lscala/Option;
        44: invokestatic  #384                // Method scala/runtime/Statics.anyHash:(Ljava/lang/Object;)I
        47: iadd
        48: istore_1
        49: bipush        37
        51: iload_1
        52: imul
        53: aload_0
        54: invokevirtual #224                // Method realm:()Lscala/Option;
        57: invokestatic  #384                // Method scala/runtime/Statics.anyHash:(Ljava/lang/Object;)I
        60: iadd
        61: istore_1
        62: bipush        37
        64: iload_1
        65: imul
        66: aload_0
        67: invokevirtual #294                // Method optional:()Z
        70: ifeq          79
        73: sipush        1231
        76: goto          82
        79: sipush        1237
        82: iadd
        83: istore_1
        84: bipush        37
        86: iload_1
        87: imul
        88: aload_0
        89: invokevirtual #156                // Method matchHost:()Z
        92: ifeq          101
        95: sipush        1231
        98: goto          104
       101: sipush        1237
       104: iadd
       105: istore_1
       106: bipush        37
       108: iload_1
       109: imul
       110: aload_0
       111: invokevirtual #218                // Method httpsOnly:()Z
       114: ifeq          123
       117: sipush        1231
       120: goto          126
       123: sipush        1237
       126: iadd
       127: istore_1
       128: bipush        37
       130: iload_1
       131: imul
       132: aload_0
       133: invokevirtual #296                // Method passOnRedirect:()Z
       136: ifeq          145
       139: sipush        1231
       142: goto          148
       145: sipush        1237
       148: iadd
       149: istore_1
       150: bipush        37
       152: iload_1
       153: imul
       154: ireturn
      StackMapTable: number_of_entries = 8
        frame_type = 255 /* full_frame */
          offset_delta = 79
          locals = [ class coursier/credentials/DirectCredentials, int ]
          stack = [ int ]
        frame_type = 255 /* full_frame */
          offset_delta = 2
          locals = [ class coursier/credentials/DirectCredentials, int ]
          stack = [ int, int ]
        frame_type = 82 /* same_locals_1_stack_item */
          stack = [ int ]
        frame_type = 255 /* full_frame */
          offset_delta = 2
          locals = [ class coursier/credentials/DirectCredentials, int ]
          stack = [ int, int ]
        frame_type = 82 /* same_locals_1_stack_item */
          stack = [ int ]
        frame_type = 255 /* full_frame */
          offset_delta = 2
          locals = [ class coursier/credentials/DirectCredentials, int ]
          stack = [ int, int ]
        frame_type = 82 /* same_locals_1_stack_item */
          stack = [ int ]
        frame_type = 255 /* full_frame */
          offset_delta = 2
          locals = [ class coursier/credentials/DirectCredentials, int ]
          stack = [ int, int ]
      LineNumberTable:
        line 10: 0
      LocalVariableTable:
        Start  Length  Slot  Name   Signature
           10     144     1  code   I
            0     155     0  this   Lcoursier/credentials/DirectCredentials;

  private scala.Tuple8<java.lang.String, scala.Option<java.lang.String>, scala.Option<coursier.credentials.Password<java.lang.String>>, scala.Option<java.lang.String>, java.lang.Object, java.lang.Object, java.lang.Object, java.lang.Object> tuple();
    descriptor: ()Lscala/Tuple8;
    flags: (0x0002) ACC_PRIVATE
    Code:
      stack=10, locals=1, args_size=1
         0: new           #391                // class scala/Tuple8
         3: dup
         4: aload_0
         5: invokevirtual #222                // Method host:()Ljava/lang/String;
         8: aload_0
         9: invokevirtual #142                // Method usernameOpt:()Lscala/Option;
        12: aload_0
        13: invokevirtual #148                // Method passwordOpt:()Lscala/Option;
        16: aload_0
        17: invokevirtual #224                // Method realm:()Lscala/Option;
        20: aload_0
        21: invokevirtual #294                // Method optional:()Z
        24: invokestatic  #397                // Method scala/runtime/BoxesRunTime.boxToBoolean:(Z)Ljava/lang/Boolean;
        27: aload_0
        28: invokevirtual #156                // Method matchHost:()Z
        31: invokestatic  #397                // Method scala/runtime/BoxesRunTime.boxToBoolean:(Z)Ljava/lang/Boolean;
        34: aload_0
        35: invokevirtual #218                // Method httpsOnly:()Z
        38: invokestatic  #397                // Method scala/runtime/BoxesRunTime.boxToBoolean:(Z)Ljava/lang/Boolean;
        41: aload_0
        42: invokevirtual #296                // Method passOnRedirect:()Z
        45: invokestatic  #397                // Method scala/runtime/BoxesRunTime.boxToBoolean:(Z)Ljava/lang/Boolean;
        48: invokespecial #400                // Method scala/Tuple8."<init>":(Ljava/lang/Object;Ljava/lang/Object;Ljava/lang/Object;Ljava/lang/Object;Ljava/lang/Object;Ljava/lang/Object;Ljava/lang/Object;Ljava/lang/Object;)V
        51: areturn
      LineNumberTable:
        line 10: 0
      LocalVariableTable:
        Start  Length  Slot  Name   Signature
            0      52     0  this   Lcoursier/credentials/DirectCredentials;
    Signature: #389                         // ()Lscala/Tuple8<Ljava/lang/String;Lscala/Option<Ljava/lang/String;>;Lscala/Option<Lcoursier/credentials/Password<Ljava/lang/String;>;>;Lscala/Option<Ljava/lang/String;>;Ljava/lang/Object;Ljava/lang/Object;Ljava/lang/Object;Ljava/lang/Object;>;

  public java.lang.String productPrefix();
    descriptor: ()Ljava/lang/String;
    flags: (0x0001) ACC_PUBLIC
    Code:
      stack=1, locals=1, args_size=1
         0: ldc_w         #378                // String DirectCredentials
         3: areturn
      LineNumberTable:
        line 10: 0
      LocalVariableTable:
        Start  Length  Slot  Name   Signature
            0       4     0  this   Lcoursier/credentials/DirectCredentials;

  public int productArity();
    descriptor: ()I
    flags: (0x0001) ACC_PUBLIC
    Code:
      stack=1, locals=1, args_size=1
         0: bipush        8
         2: ireturn
      LineNumberTable:
        line 10: 0
      LocalVariableTable:
        Start  Length  Slot  Name   Signature
            0       3     0  this   Lcoursier/credentials/DirectCredentials;

  public java.lang.Object productElement(int);
    descriptor: (I)Ljava/lang/Object;
    flags: (0x0001) ACC_PUBLIC
    Code:
      stack=3, locals=3, args_size=2
         0: iload_1
         1: istore_2
         2: iload_2
         3: tableswitch   { // 0 to 7
                       0: 48
                       1: 55
                       2: 62
                       3: 69
                       4: 76
                       5: 86
                       6: 96
                       7: 106
                 default: 116
            }
        48: aload_0
        49: invokevirtual #222                // Method host:()Ljava/lang/String;
        52: goto          131
        55: aload_0
        56: invokevirtual #142                // Method usernameOpt:()Lscala/Option;
        59: goto          131
        62: aload_0
        63: invokevirtual #148                // Method passwordOpt:()Lscala/Option;
        66: goto          131
        69: aload_0
        70: invokevirtual #224                // Method realm:()Lscala/Option;
        73: goto          131
        76: aload_0
        77: invokevirtual #294                // Method optional:()Z
        80: invokestatic  #397                // Method scala/runtime/BoxesRunTime.boxToBoolean:(Z)Ljava/lang/Boolean;
        83: goto          131
        86: aload_0
        87: invokevirtual #156                // Method matchHost:()Z
        90: invokestatic  #397                // Method scala/runtime/BoxesRunTime.boxToBoolean:(Z)Ljava/lang/Boolean;
        93: goto          131
        96: aload_0
        97: invokevirtual #218                // Method httpsOnly:()Z
       100: invokestatic  #397                // Method scala/runtime/BoxesRunTime.boxToBoolean:(Z)Ljava/lang/Boolean;
       103: goto          131
       106: aload_0
       107: invokevirtual #296                // Method passOnRedirect:()Z
       110: invokestatic  #397                // Method scala/runtime/BoxesRunTime.boxToBoolean:(Z)Ljava/lang/Boolean;
       113: goto          131
       116: new           #407                // class java/lang/IndexOutOfBoundsException
       119: dup
       120: iload_2
       121: invokestatic  #411                // Method scala/runtime/BoxesRunTime.boxToInteger:(I)Ljava/lang/Integer;
       124: invokevirtual #412                // Method java/lang/Object.toString:()Ljava/lang/String;
       127: invokespecial #413                // Method java/lang/IndexOutOfBoundsException."<init>":(Ljava/lang/String;)V
       130: athrow
       131: areturn
      StackMapTable: number_of_entries = 10
        frame_type = 252 /* append */
          offset_delta = 48
          locals = [ int ]
        frame_type = 6 /* same */
        frame_type = 6 /* same */
        frame_type = 6 /* same */
        frame_type = 6 /* same */
        frame_type = 9 /* same */
        frame_type = 9 /* same */
        frame_type = 9 /* same */
        frame_type = 9 /* same */
        frame_type = 78 /* same_locals_1_stack_item */
          stack = [ class java/lang/Object ]
      LineNumberTable:
        line 10: 0
      LocalVariableTable:
        Start  Length  Slot  Name   Signature
            0     132     0  this   Lcoursier/credentials/DirectCredentials;
            0     132     1     n   I
    MethodParameters:
      Name                           Flags
      n                              final

  public java.lang.String productElementName(int);
    descriptor: (I)Ljava/lang/String;
    flags: (0x0001) ACC_PUBLIC
    Code:
      stack=3, locals=3, args_size=2
         0: iload_1
         1: istore_2
         2: iload_2
         3: tableswitch   { // 0 to 7
                       0: 48
                       1: 54
                       2: 60
                       3: 66
                       4: 72
                       5: 78
                       6: 84
                       7: 90
                 default: 96
            }
        48: ldc_w         #416                // String host
        51: goto          111
        54: ldc_w         #417                // String usernameOpt
        57: goto          111
        60: ldc_w         #418                // String passwordOpt
        63: goto          111
        66: ldc_w         #419                // String realm
        69: goto          111
        72: ldc_w         #420                // String optional
        75: goto          111
        78: ldc_w         #421                // String matchHost
        81: goto          111
        84: ldc_w         #422                // String httpsOnly
        87: goto          111
        90: ldc_w         #423                // String passOnRedirect
        93: goto          111
        96: new           #407                // class java/lang/IndexOutOfBoundsException
        99: dup
       100: iload_2
       101: invokestatic  #411                // Method scala/runtime/BoxesRunTime.boxToInteger:(I)Ljava/lang/Integer;
       104: invokevirtual #412                // Method java/lang/Object.toString:()Ljava/lang/String;
       107: invokespecial #413                // Method java/lang/IndexOutOfBoundsException."<init>":(Ljava/lang/String;)V
       110: athrow
       111: areturn
      StackMapTable: number_of_entries = 10
        frame_type = 252 /* append */
          offset_delta = 48
          locals = [ int ]
        frame_type = 5 /* same */
        frame_type = 5 /* same */
        frame_type = 5 /* same */
        frame_type = 5 /* same */
        frame_type = 5 /* same */
        frame_type = 5 /* same */
        frame_type = 5 /* same */
        frame_type = 5 /* same */
        frame_type = 78 /* same_locals_1_stack_item */
          stack = [ class java/lang/String ]
      LineNumberTable:
        line 10: 0
      LocalVariableTable:
        Start  Length  Slot  Name   Signature
            0     112     0  this   Lcoursier/credentials/DirectCredentials;
            0     112     1     n   I
    MethodParameters:
      Name                           Flags
      n                              final

  public static final java.net.URI $anonfun$autoMatches$1(java.lang.String);
    descriptor: (Ljava/lang/String;)Ljava/net/URI;
    flags: (0x1019) ACC_PUBLIC, ACC_STATIC, ACC_FINAL, ACC_SYNTHETIC
    Code:
      stack=3, locals=1, args_size=1
         0: new           #426                // class java/net/URI
         3: dup
         4: aload_0
         5: invokespecial #427                // Method java/net/URI."<init>":(Ljava/lang/String;)V
         8: areturn
      LineNumberTable:
        line 37: 0
      LocalVariableTable:
        Start  Length  Slot  Name   Signature
            0       9     0 url$1   Ljava/lang/String;
    MethodParameters:
      Name                           Flags
      url$1                          final

  public static final scala.Option $anonfun$autoMatches$2(java.net.URI);
    descriptor: (Ljava/net/URI;)Lscala/Option;
    flags: (0x1019) ACC_PUBLIC, ACC_STATIC, ACC_FINAL, ACC_SYNTHETIC
    Code:
      stack=2, locals=1, args_size=1
         0: getstatic     #134                // Field scala/Option$.MODULE$:Lscala/Option$;
         3: aload_0
         4: invokevirtual #431                // Method java/net/URI.getScheme:()Ljava/lang/String;
         7: invokevirtual #137                // Method scala/Option$.apply:(Ljava/lang/Object;)Lscala/Option;
        10: areturn
      LineNumberTable:
        line 38: 0
      LocalVariableTable:
        Start  Length  Slot  Name   Signature
            0      11     0   uri   Ljava/net/URI;
    MethodParameters:
      Name                           Flags
      uri                            final

  public static final scala.Option $anonfun$autoMatches$3(java.net.URI);
    descriptor: (Ljava/net/URI;)Lscala/Option;
    flags: (0x1019) ACC_PUBLIC, ACC_STATIC, ACC_FINAL, ACC_SYNTHETIC
    Code:
      stack=2, locals=1, args_size=1
         0: getstatic     #134                // Field scala/Option$.MODULE$:Lscala/Option$;
         3: aload_0
         4: invokevirtual #435                // Method java/net/URI.getHost:()Ljava/lang/String;
         7: invokevirtual #137                // Method scala/Option$.apply:(Ljava/lang/Object;)Lscala/Option;
        10: areturn
      LineNumberTable:
        line 39: 0
      LocalVariableTable:
        Start  Length  Slot  Name   Signature
            0      11     0   uri   Ljava/net/URI;
    MethodParameters:
      Name                           Flags
      uri                            final

  public static final boolean $anonfun$autoMatches$4(scala.Option, java.lang.Object);
    descriptor: (Lscala/Option;Ljava/lang/Object;)Z
    flags: (0x1019) ACC_PUBLIC, ACC_STATIC, ACC_FINAL, ACC_SYNTHETIC
    Code:
      stack=2, locals=2, args_size=2
         0: aload_0
         1: aload_1
         2: invokevirtual #216                // Method scala/Option.contains:(Ljava/lang/Object;)Z
         5: ireturn
      LineNumberTable:
        line 42: 0
      LocalVariableTable:
        Start  Length  Slot  Name   Signature
            0       6     0 realm0$1   Lscala/Option;
            0       6     1  elem   Ljava/lang/Object;
    MethodParameters:
      Name                           Flags
      realm0$1                       final
      elem                           final

  public static final java.net.URI $anonfun$matches$1(java.lang.String);
    descriptor: (Ljava/lang/String;)Ljava/net/URI;
    flags: (0x1019) ACC_PUBLIC, ACC_STATIC, ACC_FINAL, ACC_SYNTHETIC
    Code:
      stack=3, locals=1, args_size=1
         0: new           #426                // class java/net/URI
         3: dup
         4: aload_0
         5: invokespecial #427                // Method java/net/URI."<init>":(Ljava/lang/String;)V
         8: areturn
      LineNumberTable:
        line 48: 0
      LocalVariableTable:
        Start  Length  Slot  Name   Signature
            0       9     0 url$2   Ljava/lang/String;
    MethodParameters:
      Name                           Flags
      url$2                          final

  public static final scala.Option $anonfun$matches$2(java.net.URI);
    descriptor: (Ljava/net/URI;)Lscala/Option;
    flags: (0x1019) ACC_PUBLIC, ACC_STATIC, ACC_FINAL, ACC_SYNTHETIC
    Code:
      stack=2, locals=1, args_size=1
         0: getstatic     #134                // Field scala/Option$.MODULE$:Lscala/Option$;
         3: aload_0
         4: invokevirtual #431                // Method java/net/URI.getScheme:()Ljava/lang/String;
         7: invokevirtual #137                // Method scala/Option$.apply:(Ljava/lang/Object;)Lscala/Option;
        10: areturn
      LineNumberTable:
        line 49: 0
      LocalVariableTable:
        Start  Length  Slot  Name   Signature
            0      11     0   uri   Ljava/net/URI;
    MethodParameters:
      Name                           Flags
      uri                            final

  public static final scala.Option $anonfun$matches$3(java.net.URI);
    descriptor: (Ljava/net/URI;)Lscala/Option;
    flags: (0x1019) ACC_PUBLIC, ACC_STATIC, ACC_FINAL, ACC_SYNTHETIC
    Code:
      stack=2, locals=1, args_size=1
         0: getstatic     #134                // Field scala/Option$.MODULE$:Lscala/Option$;
         3: aload_0
         4: invokevirtual #435                // Method java/net/URI.getHost:()Ljava/lang/String;
         7: invokevirtual #137                // Method scala/Option$.apply:(Ljava/lang/Object;)Lscala/Option;
        10: areturn
      LineNumberTable:
        line 50: 0
      LocalVariableTable:
        Start  Length  Slot  Name   Signature
            0      11     0   uri   Ljava/net/URI;
    MethodParameters:
      Name                           Flags
      uri                            final

  public static final scala.Option $anonfun$matches$4(java.net.URI);
    descriptor: (Ljava/net/URI;)Lscala/Option;
    flags: (0x1019) ACC_PUBLIC, ACC_STATIC, ACC_FINAL, ACC_SYNTHETIC
    Code:
      stack=2, locals=1, args_size=1
         0: getstatic     #134                // Field scala/Option$.MODULE$:Lscala/Option$;
         3: aload_0
         4: invokevirtual #443                // Method java/net/URI.getUserInfo:()Ljava/lang/String;
         7: invokevirtual #137                // Method scala/Option$.apply:(Ljava/lang/Object;)Lscala/Option;
        10: areturn
      LineNumberTable:
        line 51: 0
      LocalVariableTable:
        Start  Length  Slot  Name   Signature
            0      11     0   uri   Ljava/net/URI;
    MethodParameters:
      Name                           Flags
      uri                            final

  public static final java.lang.String $anonfun$authentication$1();
    descriptor: ()Ljava/lang/String;
    flags: (0x1019) ACC_PUBLIC, ACC_STATIC, ACC_FINAL, ACC_SYNTHETIC
    Code:
      stack=1, locals=0, args_size=0
         0: ldc_w         #445                // String
         3: areturn
      LineNumberTable:
        line 61: 0

  public static final java.lang.String $anonfun$authentication$2(coursier.credentials.Password);
    descriptor: (Lcoursier/credentials/Password;)Ljava/lang/String;
    flags: (0x1019) ACC_PUBLIC, ACC_STATIC, ACC_FINAL, ACC_SYNTHETIC
    Code:
      stack=1, locals=1, args_size=1
         0: aload_0
         1: invokevirtual #450                // Method coursier/credentials/Password.value:()Ljava/lang/Object;
         4: checkcast     #267                // class java/lang/String
         7: areturn
      LineNumberTable:
        line 62: 0
      LocalVariableTable:
        Start  Length  Slot  Name   Signature
            0       8     0   x$1   Lcoursier/credentials/Password;
    MethodParameters:
      Name                           Flags
      x$1                            final

  public coursier.credentials.DirectCredentials(java.lang.String, scala.Option<java.lang.String>, scala.Option<coursier.credentials.Password<java.lang.String>>, scala.Option<java.lang.String>, boolean, boolean, boolean, boolean);
    descriptor: (Ljava/lang/String;Lscala/Option;Lscala/Option;Lscala/Option;ZZZZ)V
    flags: (0x0001) ACC_PUBLIC
    Code:
      stack=2, locals=9, args_size=9
         0: aload_0
         1: aload_1
         2: putfield      #87                 // Field host:Ljava/lang/String;
         5: aload_0
         6: aload_2
         7: putfield      #91                 // Field usernameOpt:Lscala/Option;
        10: aload_0
        11: aload_3
        12: putfield      #94                 // Field passwordOpt:Lscala/Option;
        15: aload_0
        16: aload         4
        18: putfield      #96                 // Field realm:Lscala/Option;
        21: aload_0
        22: iload         5
        24: putfield      #98                 // Field optional:Z
        27: aload_0
        28: iload         6
        30: putfield      #100                // Field matchHost:Z
        33: aload_0
        34: iload         7
        36: putfield      #102                // Field httpsOnly:Z
        39: aload_0
        40: iload         8
        42: putfield      #104                // Field passOnRedirect:Z
        45: aload_0
        46: invokespecial #455                // Method coursier/credentials/Credentials."<init>":()V
        49: aload_0
        50: invokestatic  #459                // InterfaceMethod scala/Product.$init$:(Lscala/Product;)V
        53: return
      LineNumberTable:
        line 10: 0
        line 22: 45
        line 10: 53
      LocalVariableTable:
        Start  Length  Slot  Name   Signature
            0      54     0  this   Lcoursier/credentials/DirectCredentials;
            0      54     1  host   Ljava/lang/String;
            0      54     2 usernameOpt   Lscala/Option;
            0      54     3 passwordOpt   Lscala/Option;
            0      54     4 realm   Lscala/Option;
            0      54     5 optional   Z
            0      54     6 matchHost   Z
            0      54     7 httpsOnly   Z
            0      54     8 passOnRedirect   Z
    Signature: #452                         // (Ljava/lang/String;Lscala/Option<Ljava/lang/String;>;Lscala/Option<Lcoursier/credentials/Password<Ljava/lang/String;>;>;Lscala/Option<Ljava/lang/String;>;ZZZZ)V
    MethodParameters:
      Name                           Flags
      host                           final
      usernameOpt                    final
      passwordOpt                    final
      realm                          final
      optional                       final
      matchHost                      final
      httpsOnly                      final
      passOnRedirect                 final

  public coursier.credentials.DirectCredentials(java.lang.String, scala.Option<java.lang.String>, scala.Option<coursier.credentials.Password<java.lang.String>>, scala.Option<java.lang.String>, boolean);
    descriptor: (Ljava/lang/String;Lscala/Option;Lscala/Option;Lscala/Option;Z)V
    flags: (0x0001) ACC_PUBLIC
    Code:
      stack=9, locals=6, args_size=6
         0: aload_0
         1: aload_1
         2: aload_2
         3: aload_3
         4: aload         4
         6: iload         5
         8: getstatic     #37                 // Field coursier/credentials/DirectCredentials$.MODULE$:Lcoursier/credentials/DirectCredentials$;
        11: invokevirtual #61                 // Method coursier/credentials/DirectCredentials$.defaultMatchHost:()Z
        14: getstatic     #37                 // Field coursier/credentials/DirectCredentials$.MODULE$:Lcoursier/credentials/DirectCredentials$;
        17: invokevirtual #58                 // Method coursier/credentials/DirectCredentials$.defaultHttpsOnly:()Z
        20: iconst_0
        21: invokespecial #329                // Method "<init>":(Ljava/lang/String;Lscala/Option;Lscala/Option;Lscala/Option;ZZZZ)V
        24: return
      LineNumberTable:
        line 10: 0
        line 19: 8
        line 20: 14
        line 21: 20
        line 10: 24
      LocalVariableTable:
        Start  Length  Slot  Name   Signature
            0      25     0  this   Lcoursier/credentials/DirectCredentials;
            0      25     1  host   Ljava/lang/String;
            0      25     2 usernameOpt   Lscala/Option;
            0      25     3 passwordOpt   Lscala/Option;
            0      25     4 realm   Lscala/Option;
            0      25     5 optional   Z
    Signature: #461                         // (Ljava/lang/String;Lscala/Option<Ljava/lang/String;>;Lscala/Option<Lcoursier/credentials/Password<Ljava/lang/String;>;>;Lscala/Option<Ljava/lang/String;>;Z)V
    MethodParameters:
      Name                           Flags
      host                           final
      usernameOpt                    final
      passwordOpt                    final
      realm                          final
      optional                       final

  public coursier.credentials.DirectCredentials(java.lang.String, scala.Option<java.lang.String>, scala.Option<coursier.credentials.Password<java.lang.String>>, scala.Option<java.lang.String>);
    descriptor: (Ljava/lang/String;Lscala/Option;Lscala/Option;Lscala/Option;)V
    flags: (0x0001) ACC_PUBLIC
    Code:
      stack=9, locals=5, args_size=5
         0: aload_0
         1: aload_1
         2: aload_2
         3: aload_3
         4: aload         4
         6: iconst_1
         7: getstatic     #37                 // Field coursier/credentials/DirectCredentials$.MODULE$:Lcoursier/credentials/DirectCredentials$;
        10: invokevirtual #61                 // Method coursier/credentials/DirectCredentials$.defaultMatchHost:()Z
        13: getstatic     #37                 // Field coursier/credentials/DirectCredentials$.MODULE$:Lcoursier/credentials/DirectCredentials$;
        16: invokevirtual #58                 // Method coursier/credentials/DirectCredentials$.defaultHttpsOnly:()Z
        19: iconst_0
        20: invokespecial #329                // Method "<init>":(Ljava/lang/String;Lscala/Option;Lscala/Option;Lscala/Option;ZZZZ)V
        23: return
      LineNumberTable:
        line 10: 0
        line 17: 6
        line 19: 7
        line 20: 13
        line 21: 19
        line 10: 23
      LocalVariableTable:
        Start  Length  Slot  Name   Signature
            0      24     0  this   Lcoursier/credentials/DirectCredentials;
            0      24     1  host   Ljava/lang/String;
            0      24     2 usernameOpt   Lscala/Option;
            0      24     3 passwordOpt   Lscala/Option;
            0      24     4 realm   Lscala/Option;
    Signature: #463                         // (Ljava/lang/String;Lscala/Option<Ljava/lang/String;>;Lscala/Option<Lcoursier/credentials/Password<Ljava/lang/String;>;>;Lscala/Option<Ljava/lang/String;>;)V
    MethodParameters:
      Name                           Flags
      host                           final
      usernameOpt                    final
      passwordOpt                    final
      realm                          final

  public coursier.credentials.DirectCredentials(java.lang.String, scala.Option<java.lang.String>, scala.Option<coursier.credentials.Password<java.lang.String>>);
    descriptor: (Ljava/lang/String;Lscala/Option;Lscala/Option;)V
    flags: (0x0001) ACC_PUBLIC
    Code:
      stack=9, locals=4, args_size=4
         0: aload_0
         1: aload_1
         2: aload_2
         3: aload_3
         4: getstatic     #470                // Field scala/None$.MODULE$:Lscala/None$;
         7: iconst_1
         8: getstatic     #37                 // Field coursier/credentials/DirectCredentials$.MODULE$:Lcoursier/credentials/DirectCredentials$;
        11: invokevirtual #61                 // Method coursier/credentials/DirectCredentials$.defaultMatchHost:()Z
        14: getstatic     #37                 // Field coursier/credentials/DirectCredentials$.MODULE$:Lcoursier/credentials/DirectCredentials$;
        17: invokevirtual #58                 // Method coursier/credentials/DirectCredentials$.defaultHttpsOnly:()Z
        20: iconst_0
        21: invokespecial #329                // Method "<init>":(Ljava/lang/String;Lscala/Option;Lscala/Option;Lscala/Option;ZZZZ)V
        24: return
      LineNumberTable:
        line 10: 0
        line 15: 4
        line 17: 7
        line 19: 8
        line 20: 14
        line 21: 20
        line 10: 24
      LocalVariableTable:
        Start  Length  Slot  Name   Signature
            0      25     0  this   Lcoursier/credentials/DirectCredentials;
            0      25     1  host   Ljava/lang/String;
            0      25     2 usernameOpt   Lscala/Option;
            0      25     3 passwordOpt   Lscala/Option;
    Signature: #465                         // (Ljava/lang/String;Lscala/Option<Ljava/lang/String;>;Lscala/Option<Lcoursier/credentials/Password<Ljava/lang/String;>;>;)V
    MethodParameters:
      Name                           Flags
      host                           final
      usernameOpt                    final
      passwordOpt                    final

  public coursier.credentials.DirectCredentials();
    descriptor: ()V
    flags: (0x0001) ACC_PUBLIC
    Code:
      stack=9, locals=1, args_size=1
         0: aload_0
         1: ldc_w         #445                // String
         4: getstatic     #470                // Field scala/None$.MODULE$:Lscala/None$;
         7: getstatic     #470                // Field scala/None$.MODULE$:Lscala/None$;
        10: getstatic     #470                // Field scala/None$.MODULE$:Lscala/None$;
        13: iconst_1
        14: getstatic     #37                 // Field coursier/credentials/DirectCredentials$.MODULE$:Lcoursier/credentials/DirectCredentials$;
        17: invokevirtual #61                 // Method coursier/credentials/DirectCredentials$.defaultMatchHost:()Z
        20: getstatic     #37                 // Field coursier/credentials/DirectCredentials$.MODULE$:Lcoursier/credentials/DirectCredentials$;
        23: invokevirtual #58                 // Method coursier/credentials/DirectCredentials$.defaultHttpsOnly:()Z
        26: iconst_0
        27: invokespecial #329                // Method "<init>":(Ljava/lang/String;Lscala/Option;Lscala/Option;Lscala/Option;ZZZZ)V
        30: return
      LineNumberTable:
        line 10: 0
        line 11: 1
        line 12: 4
        line 13: 7
        line 15: 10
        line 17: 13
        line 19: 14
        line 20: 20
        line 21: 26
        line 10: 30
      LocalVariableTable:
        Start  Length  Slot  Name   Signature
            0      31     0  this   Lcoursier/credentials/DirectCredentials;

  public static final java.lang.Object $anonfun$autoMatches$4$adapted(scala.Option, java.lang.Object);
    descriptor: (Lscala/Option;Ljava/lang/Object;)Ljava/lang/Object;
    flags: (0x1019) ACC_PUBLIC, ACC_STATIC, ACC_FINAL, ACC_SYNTHETIC
    Code:
      stack=2, locals=2, args_size=2
         0: aload_0
         1: aload_1
         2: invokestatic  #472                // Method $anonfun$autoMatches$4:(Lscala/Option;Ljava/lang/Object;)Z
         5: invokestatic  #397                // Method scala/runtime/BoxesRunTime.boxToBoolean:(Z)Ljava/lang/Boolean;
         8: areturn
      LineNumberTable:
        line 42: 0
      LocalVariableTable:
        Start  Length  Slot  Name   Signature
            0       9     0 realm0$1   Lscala/Option;
            0       9     1  elem   Ljava/lang/Object;
    MethodParameters:
      Name                           Flags
      realm0$1                       final
      elem                           final

  private static java.lang.Object $deserializeLambda$(java.lang.invoke.SerializedLambda);
    descriptor: (Ljava/lang/invoke/SerializedLambda;)Ljava/lang/Object;
    flags: (0x100a) ACC_PRIVATE, ACC_STATIC, ACC_SYNTHETIC
    Code:
      stack=1, locals=1, args_size=1
         0: aload_0
         1: invokedynamic #484,  0            // InvokeDynamic #10:lambdaDeserialize:(Ljava/lang/invoke/SerializedLambda;)Ljava/lang/Object;
         6: areturn
}
InnerClasses:
  public static final #15= #12 of #14;    // Lookup=class java/lang/invoke/MethodHandles$Lookup of class java/lang/invoke/MethodHandles
SourceFile: "DirectCredentials.scala"
RuntimeVisibleAnnotations:
  0: #8(#9=s#10)
    scala.reflect.ScalaSignature(
      bytes="\u0006\u0005\t\u0015d\u0001\u0002\u001f>\u0005\tC\u0001\"\u0017\u0001\u0003\u0006\u0004%\tA\u0017\u0005\tG\u0002\u0011\t\u0011)A\u00057\"AA\r\u0001BC\u0002\u0013\u0005Q\r\u0003\u0005j\u0001\t\u0005\t\u0015!\u0003g\u0011!Q\u0007A!b\u0001\n\u0003Y\u0007\u0002\u00039\u0001\u0005\u0003\u0005\u000b\u0011\u00027\t\u0011E\u0004!Q1A\u0005\u0002\u0015D\u0001B\u001d\u0001\u0003\u0002\u0003\u0006IA\u001a\u0005\tg\u0002\u0011)\u0019!C\u0001i\"A\u0001\u0010\u0001B\u0001B\u0003%Q\u000f\u0003\u0005z\u0001\t\u0015\r\u0011\"\u0001u\u0011!Q\bA!A!\u0002\u0013)\b\u0002C>\u0001\u0005\u000b\u0007I\u0011\u0001;\t\u0011q\u0004!\u0011!Q\u0001\nUD\u0001\" \u0001\u0003\u0006\u0004%\t\u0001\u001e\u0005\t}\u0002\u0011\t\u0011)A\u0005k\"1q\u0010\u0001C\u0001\u0003\u0003Aaa \u0001\u0005\u0002\u0005U\u0001BB@\u0001\t\u0003\t\t\u0003\u0003\u0004\u0000\u0001\u0011\u0005\u00111\u0006\u0005\u0007\u007f\u0002!\t!a\r\t\u000f\u0005U\u0002\u0001\"\u0001\u00028!9\u0011Q\b\u0001\u0005\u0002\u0005}\u0002bBA#\u0001\u0011\u0005\u0011q\t\u0005\u0007\u0003\u0017\u0002A\u0011\u0002;\t\u000f\u00055\u0003\u0001\"\u0001\u0002P!9\u0011\u0011\f\u0001\u0005\u0002\u0005m\u0003bBA2\u0001\u0011\u0005\u0011Q\r\u0005\b\u0003g\u0002A\u0011AA;\u0011\u001d\ti\b\u0001C\u0001\u0003\u007fBq!a!\u0001\t\u0003\t)\tC\u0004\u0002\n\u0002!\t!a#\t\u000f\u0005\u0015\u0003\u0001\"\u0001\u0002\u0010\"9\u00111\u0013\u0001\u0005\u0002\u0005U\u0005bBAM\u0001\u0011\u0005\u00111\u0014\u0005\b\u0003?\u0003A\u0011AAQ\u0011\u001d\t)\u000b\u0001C\u0001\u0003OCq!a+\u0001\t\u0003\ni\u000bC\u0004\u0002>\u0002!\t%a0\t\u000f\u0005-\u0007\u0001\"\u0011\u0002N\"9\u0011\u0011\u001b\u0001\u0005B\u0005M\u0007bBAn\u0001\u0011%\u0011Q\u001c\u0005\b\u0003K\u0004A\u0011IAt\u0011\u001d\tI\u000f\u0001C!\u0003WDq!!<\u0001\t\u0003\ny\u000fC\u0004\u0002v\u0002!\t%a>\b\u000f\u0005mX\b#\u0001\u0002~\u001a1A(\u0010E\u0001\u0003\u007fDaa \u0019\u0005\u0002\tE\u0001b\u0002B\na\u0011\u0005!Q\u0003\u0005\b\u0005\'\u0001D\u0011\u0001B\u000f\u0011\u0019\u00119\u0003\rC\u0001i\"1!\u0011\u0006\u0019\u0005\u0002QDqAa\u00051\t\u0003\t\u0019\u0004C\u0004\u0003\u0014A\"\tAa\u000b\t\u000f\tM\u0001\u0007\"\u0001\u00034!9!1\u0003\u0019\u0005\u0002\tu\u0002b\u0002B\na\u0011\u0005!\u0011\n\u0005\n\u00057\u0002\u0014\u0011!C\u0005\u0005;\u0012\u0011\u0003R5sK\u000e$8I]3eK:$\u0018.\u00197t\u0015\tqt(A\u0006de\u0016$WM\u001c;jC2\u001c(\"\u0001!\u0002\u0011\r|WO]:jKJ\u001c\u0001a\u0005\u0003\u0001\u0007\u001ek\u0005C\u0001#F\u001b\u0005i\u0014B\u0001$>\u0005-\u0019%/\u001a3f]RL\u0017\r\\:\u0011\u0005![U\"A%\u000b\u0003)\u000bQa]2bY\u0006L!\u0001T%\u0003\u000fA\u0013x\u000eZ;diB\u0011aJ\u0016\b\u0003\u001fRs!\u0001U*\u000e\u0003ES!AU!\u0002\rq\u0012xn\u001c;?\u0013\u0005Q\u0015BA+J\u0003\u001d\u0001\u0018mY6bO\u0016L!a\u0016-\u0003\u0019M+\'/[1mSj\f\'\r\\3\u000b\u0005UK\u0015\u0001\u00025pgR,\u0012a\u0017\t\u00039\u0002t!!\u00180\u0011\u0005AK\u0015BA0J\u0003\u0019\u0001&/\u001a3fM&\u0011\u0011M\u0019\u0002\u0007\'R\u0014\u0018N\\4\u000b\u0005}K\u0015!\u00025pgR\u0004\u0013aC;tKJt\u0017-\\3PaR,\u0012A\u001a\t\u0004\u0011\u001e\\\u0016B\u00015J\u0005\u0019y\u0005\u000f^5p]\u0006aQo]3s]\u0006lWm\u00149uA\u0005Y\u0001/Y:to>\u0014Hm\u00149u+\u0005a\u0007c\u0001%h[B\u0019AI\\.\n\u0005=l$\u0001\u0003)bgN<xN\u001d3\u0002\u0019A\f7o]<pe\u0012|\u0005\u000f\u001e\u0011\u0002\u000bI,\u0017\r\\7\u0002\rI,\u0017\r\\7!\u0003!y\u0007\u000f^5p]\u0006dW#A;\u0011\u0005!3\u0018BA<J\u0005\u001d\u0011un\u001c7fC:\f\u0011b\u001c9uS>t\u0017\r\u001c\u0011\u0002\u00135\fGo\u00195I_N$\u0018AC7bi\u000eD\u0007j\\:uA\u0005I\u0001\u000e\u001e;qg>sG._\u0001\u000bQR$\bo](oYf\u0004\u0013A\u00049bgN|eNU3eSJ,7\r^\u0001\u0010a\u0006\u001c8o\u00148SK\u0012L\'/Z2uA\u00051A(\u001b8jiz\"\"#a\u0001\u0002\u0006\u0005\u001d\u0011\u0011BA\u0006\u0003\u001b\ty!!\u0005\u0002\u0014A\u0011A\t\u0001\u0005\u00063F\u0001\ra\u0017\u0005\u0006IF\u0001\rA\u001a\u0005\u0006UF\u0001\r\u0001\u001c\u0005\u0006cF\u0001\rA\u001a\u0005\u0006gF\u0001\r!\u001e\u0005\u0006sF\u0001\r!\u001e\u0005\u0006wF\u0001\r!\u001e\u0005\u0006{F\u0001\r!\u001e\u000b\r\u0003\u0007\t9\"!\u0007\u0002\u001c\u0005u\u0011q\u0004\u0005\u00063J\u0001\ra\u0017\u0005\u0006IJ\u0001\rA\u001a\u0005\u0006UJ\u0001\r\u0001\u001c\u0005\u0006cJ\u0001\rA\u001a\u0005\u0006gJ\u0001\r!\u001e\u000b\u000b\u0003\u0007\t\u0019#!\n\u0002(\u0005%\u0002\"B-\u0014\u0001\u0004Y\u0006\"\u00023\u0014\u0001\u00041\u0007\"\u00026\u0014\u0001\u0004a\u0007\"B9\u0014\u0001\u00041G\u0003CA\u0002\u0003[\ty#!\r\t\u000be#\u0002\u0019A.\t\u000b\u0011$\u0002\u0019\u00014\t\u000b)$\u0002\u0019\u00017\u0015\u0005\u0005\r\u0011\u0001D<ji\",6/\u001a:oC6,G\u0003BA\u0002\u0003sAa!a\u000f\u0017\u0001\u0004Y\u0016\u0001C;tKJt\u0017-\\3\u0002\u0019]LG\u000f\u001b)bgN<xN\u001d3\u0015\t\u0005\r\u0011\u0011\t\u0005\u0007\u0003\u0007:\u0002\u0019A.\u0002\u0011A\f7o]<pe\u0012\f\u0011b^5uQJ+\u0017\r\\7\u0015\t\u0005\r\u0011\u0011\n\u0005\u0006cb\u0001\raW\u0001\t]>tW)\u001c9us\u0006Y\u0011-\u001e;p\u001b\u0006$8\r[3t)\u0015)\u0018\u0011KA+\u0011\u0019\t\u0019F\u0007a\u00017\u0006\u0019QO\u001d7\t\r\u0005]#\u00041\u0001g\u0003\u0019\u0011X-\u00197na\u00059Q.\u0019;dQ\u0016\u001cH#B;\u0002^\u0005}\u0003BBA*7\u0001\u00071\f\u0003\u0004\u0002bm\u0001\raW\u0001\u0005kN,\'/\u0001\bbkRDWM\u001c;jG\u0006$\u0018n\u001c8\u0016\u0005\u0005\u001d\u0004\u0003BA5\u0003_j!!a\u001b\u000b\u0007\u00055t(\u0001\u0003d_J,\u0017\u0002BA9\u0003W\u0012a\"Q;uQ\u0016tG/[2bi&|g.A\u0002hKR$\"!a\u001e\u0011\u000b9\u000bI(a\u0001\n\u0007\u0005m\u0004LA\u0002TKF\f\u0001b^5uQ\"{7\u000f\u001e\u000b\u0005\u0003\u0007\t\t\tC\u0003Z=\u0001\u00071,A\bxSRDWk]3s]\u0006lWm\u00149u)\u0011\t\u0019!a\"\t\u000b\u0011|\u0002\u0019\u00014\u0002\u001f]LG\u000f\u001b)bgN<xN\u001d3PaR$B!a\u0001\u0002\u000e\")!\u000e\ta\u0001YR!\u00111AAI\u0011\u0015\t\u0018\u00051\u0001g\u000319\u0018\u000e\u001e5PaRLwN\\1m)\u0011\t\u0019!a&\t\u000bM\u0014\u0003\u0019A;\u0002\u001b]LG\u000f[\'bi\u000eD\u0007j\\:u)\u0011\t\u0019!!(\t\u000be\u001c\u0003\u0019A;\u0002\u001b]LG\u000f\u001b%uiB\u001cxJ\u001c7z)\u0011\t\u0019!a)\t\u000bm$\u0003\u0019A;\u0002%]LG\u000f\u001b)bgN|eNU3eSJ,7\r\u001e\u000b\u0005\u0003\u0007\tI\u000bC\u0003~K\u0001\u0007Q/\u0001\u0005u_N#(/\u001b8h)\t\ty\u000b\u0005\u0003\u00022\u0006mVBAAZ\u0015\u0011\t),a.\u0002\t1\fgn\u001a\u0006\u0003\u0003s\u000bAA[1wC&\u0019\u0011-a-\u0002\u0011\r\fg.R9vC2$2!^Aa\u0011\u001d\t\u0019m\na\u0001\u0003\u000b\f1a\u001c2k!\rA\u0015qY\u0005\u0004\u0003\u0013L%aA!os\u00061Q-];bYN$2!^Ah\u0011\u001d\t\u0019\r\u000ba\u0001\u0003\u000b\f\u0001\u0002[1tQ\u000e{G-\u001a\u000b\u0003\u0003+\u00042\u0001SAl\u0013\r\tI.\u0013\u0002\u0004\u0013:$\u0018!\u0002;va2,WCAAp!-A\u0015\u0011].gY\u001a,X/^;\n\u0007\u0005\r\u0018J\u0001\u0004UkBdW\rO\u0001\u000eaJ|G-^2u!J,g-\u001b=\u0016\u0005\u0005=\u0016\u0001\u00049s_\u0012,8\r^!sSRLXCAAk\u00039\u0001(o\u001c3vGR,E.Z7f]R$B!!2\u0002r\"9\u00111_\u0017A\u0002\u0005U\u0017!\u00018\u0002%A\u0014x\u000eZ;di\u0016cW-\\3oi:\u000bW.\u001a\u000b\u0005\u0003_\u000bI\u0010C\u0004\u0002t:\u0002\r!!6\u0002#\u0011K\'/Z2u\u0007J,G-\u001a8uS\u0006d7\u000f\u0005\u0002EaM)\u0001G!\u0001\u0003\bA\u0019\u0001Ja\u0001\n\u0007\t\u0015\u0011J\u0001\u0004B]f\u0014VM\u001a\t\u0005\u0005\u0013\u0011y!\u0004\u0002\u0003\f)!!QBA\\\u0003\tIw.C\u0002X\u0005\u0017!\"!!@\u0002\u000b\u0005\u0004\b\u000f\\=\u0015\u0011\u0005\r!q\u0003B\r\u00057AQ!\u0017\u001aA\u0002mCa!a\u000f3\u0001\u0004Y\u0006BBA\"e\u0001\u00071\f\u0006\u0006\u0002\u0004\t}!\u0011\u0005B\u0012\u0005KAQ!W\u001aA\u0002mCa!a\u000f4\u0001\u0004Y\u0006BBA\"g\u0001\u00071\fC\u0003rg\u0001\u0007a-\u0001\teK\u001a\fW\u000f\u001c;NCR\u001c\u0007\u000eS8ti\u0006\u0001B-\u001a4bk2$\b\n\u001e;qg>sG.\u001f\u000b\t\u0003\u0007\u0011iCa\f\u00032!)\u0011l\u000ea\u00017\")Am\u000ea\u0001M\")!n\u000ea\u0001YRQ\u00111\u0001B\u001b\u0005o\u0011IDa\u000f\t\u000beC\u0004\u0019A.\t\u000b\u0011D\u0004\u0019\u00014\t\u000b)D\u0004\u0019\u00017\t\u000bED\u0004\u0019\u00014\u0015\u0019\u0005\r!q\bB!\u0005\u0007\u0012)Ea\u0012\t\u000beK\u0004\u0019A.\t\u000b\u0011L\u0004\u0019\u00014\t\u000b)L\u0004\u0019\u00017\t\u000bEL\u0004\u0019\u00014\t\u000bML\u0004\u0019A;\u0015%\u0005\r!1\nB\'\u0005\u001f\u0012\tFa\u0015\u0003V\t]#\u0011\f\u0005\u00063j\u0002\ra\u0017\u0005\u0006Ij\u0002\rA\u001a\u0005\u0006Uj\u0002\r\u0001\u001c\u0005\u0006cj\u0002\rA\u001a\u0005\u0006gj\u0002\r!\u001e\u0005\u0006sj\u0002\r!\u001e\u0005\u0006wj\u0002\r!\u001e\u0005\u0006{j\u0002\r!^\u0001\roJLG/\u001a*fa2\f7-\u001a\u000b\u0003\u0005?\u0002B!!-\u0003b%!!1MAZ\u0005\u0019y%M[3di\u0002"
    )
BootstrapMethods:
  0: #179 REF_invokeStatic java/lang/invoke/LambdaMetafactory.altMetafactory:(Ljava/lang/invoke/MethodHandles$Lookup;Ljava/lang/String;Ljava/lang/invoke/MethodType;[Ljava/lang/Object;)Ljava/lang/invoke/CallSite;
    Method arguments:
      #163 ()Ljava/lang/Object;
      #168 REF_invokeStatic coursier/credentials/DirectCredentials.$anonfun$autoMatches$1:(Ljava/lang/String;)Ljava/net/URI;
      #170 ()Ljava/net/URI;
      #171 5
      #172 1
      #170 ()Ljava/net/URI;
  1: #179 REF_invokeStatic java/lang/invoke/LambdaMetafactory.altMetafactory:(Ljava/lang/invoke/MethodHandles$Lookup;Ljava/lang/String;Ljava/lang/invoke/MethodType;[Ljava/lang/Object;)Ljava/lang/invoke/CallSite;
    Method arguments:
      #192 (Ljava/lang/Object;)Ljava/lang/Object;
      #197 REF_invokeStatic coursier/credentials/DirectCredentials.$anonfun$autoMatches$2:(Ljava/net/URI;)Lscala/Option;
      #198 (Ljava/net/URI;)Lscala/Option;
      #171 5
      #172 1
      #198 (Ljava/net/URI;)Lscala/Option;
  2: #179 REF_invokeStatic java/lang/invoke/LambdaMetafactory.altMetafactory:(Ljava/lang/invoke/MethodHandles$Lookup;Ljava/lang/String;Ljava/lang/invoke/MethodType;[Ljava/lang/Object;)Ljava/lang/invoke/CallSite;
    Method arguments:
      #192 (Ljava/lang/Object;)Ljava/lang/Object;
      #209 REF_invokeStatic coursier/credentials/DirectCredentials.$anonfun$autoMatches$3:(Ljava/net/URI;)Lscala/Option;
      #198 (Ljava/net/URI;)Lscala/Option;
      #171 5
      #172 1
      #198 (Ljava/net/URI;)Lscala/Option;
  3: #179 REF_invokeStatic java/lang/invoke/LambdaMetafactory.altMetafactory:(Ljava/lang/invoke/MethodHandles$Lookup;Ljava/lang/String;Ljava/lang/invoke/MethodType;[Ljava/lang/Object;)Ljava/lang/invoke/CallSite;
    Method arguments:
      #192 (Ljava/lang/Object;)Ljava/lang/Object;
      #229 REF_invokeStatic coursier/credentials/DirectCredentials.$anonfun$autoMatches$4$adapted:(Lscala/Option;Ljava/lang/Object;)Ljava/lang/Object;
      #192 (Ljava/lang/Object;)Ljava/lang/Object;
      #172 1
  4: #179 REF_invokeStatic java/lang/invoke/LambdaMetafactory.altMetafactory:(Ljava/lang/invoke/MethodHandles$Lookup;Ljava/lang/String;Ljava/lang/invoke/MethodType;[Ljava/lang/Object;)Ljava/lang/invoke/CallSite;
    Method arguments:
      #163 ()Ljava/lang/Object;
      #246 REF_invokeStatic coursier/credentials/DirectCredentials.$anonfun$matches$1:(Ljava/lang/String;)Ljava/net/URI;
      #170 ()Ljava/net/URI;
      #171 5
      #172 1
      #170 ()Ljava/net/URI;
  5: #179 REF_invokeStatic java/lang/invoke/LambdaMetafactory.altMetafactory:(Ljava/lang/invoke/MethodHandles$Lookup;Ljava/lang/String;Ljava/lang/invoke/MethodType;[Ljava/lang/Object;)Ljava/lang/invoke/CallSite;
    Method arguments:
      #192 (Ljava/lang/Object;)Ljava/lang/Object;
      #251 REF_invokeStatic coursier/credentials/DirectCredentials.$anonfun$matches$2:(Ljava/net/URI;)Lscala/Option;
      #198 (Ljava/net/URI;)Lscala/Option;
      #171 5
      #172 1
      #198 (Ljava/net/URI;)Lscala/Option;
  6: #179 REF_invokeStatic java/lang/invoke/LambdaMetafactory.altMetafactory:(Ljava/lang/invoke/MethodHandles$Lookup;Ljava/lang/String;Ljava/lang/invoke/MethodType;[Ljava/lang/Object;)Ljava/lang/invoke/CallSite;
    Method arguments:
      #192 (Ljava/lang/Object;)Ljava/lang/Object;
      #256 REF_invokeStatic coursier/credentials/DirectCredentials.$anonfun$matches$3:(Ljava/net/URI;)Lscala/Option;
      #198 (Ljava/net/URI;)Lscala/Option;
      #171 5
      #172 1
      #198 (Ljava/net/URI;)Lscala/Option;
  7: #179 REF_invokeStatic java/lang/invoke/LambdaMetafactory.altMetafactory:(Ljava/lang/invoke/MethodHandles$Lookup;Ljava/lang/String;Ljava/lang/invoke/MethodType;[Ljava/lang/Object;)Ljava/lang/invoke/CallSite;
    Method arguments:
      #192 (Ljava/lang/Object;)Ljava/lang/Object;
      #261 REF_invokeStatic coursier/credentials/DirectCredentials.$anonfun$matches$4:(Ljava/net/URI;)Lscala/Option;
      #198 (Ljava/net/URI;)Lscala/Option;
      #171 5
      #172 1
      #198 (Ljava/net/URI;)Lscala/Option;
  8: #179 REF_invokeStatic java/lang/invoke/LambdaMetafactory.altMetafactory:(Ljava/lang/invoke/MethodHandles$Lookup;Ljava/lang/String;Ljava/lang/invoke/MethodType;[Ljava/lang/Object;)Ljava/lang/invoke/CallSite;
    Method arguments:
      #163 ()Ljava/lang/Object;
      #274 REF_invokeStatic coursier/credentials/DirectCredentials.$anonfun$authentication$1:()Ljava/lang/String;
      #275 ()Ljava/lang/String;
      #171 5
      #172 1
      #275 ()Ljava/lang/String;
  9: #179 REF_invokeStatic java/lang/invoke/LambdaMetafactory.altMetafactory:(Ljava/lang/invoke/MethodHandles$Lookup;Ljava/lang/String;Ljava/lang/invoke/MethodType;[Ljava/lang/Object;)Ljava/lang/invoke/CallSite;
    Method arguments:
      #192 (Ljava/lang/Object;)Ljava/lang/Object;
      #287 REF_invokeStatic coursier/credentials/DirectCredentials.$anonfun$authentication$2:(Lcoursier/credentials/Password;)Ljava/lang/String;
      #288 (Lcoursier/credentials/Password;)Ljava/lang/String;
      #171 5
      #172 1
      #288 (Lcoursier/credentials/Password;)Ljava/lang/String;
  10: #481 REF_invokeStatic scala/runtime/LambdaDeserialize.bootstrap:(Ljava/lang/invoke/MethodHandles$Lookup;Ljava/lang/String;Ljava/lang/invoke/MethodType;[Ljava/lang/invoke/MethodHandle;)Ljava/lang/invoke/CallSite;
    Method arguments:
      #274 REF_invokeStatic coursier/credentials/DirectCredentials.$anonfun$authentication$1:()Ljava/lang/String;
      #287 REF_invokeStatic coursier/credentials/DirectCredentials.$anonfun$authentication$2:(Lcoursier/credentials/Password;)Ljava/lang/String;
      #168 REF_invokeStatic coursier/credentials/DirectCredentials.$anonfun$autoMatches$1:(Ljava/lang/String;)Ljava/net/URI;
      #197 REF_invokeStatic coursier/credentials/DirectCredentials.$anonfun$autoMatches$2:(Ljava/net/URI;)Lscala/Option;
      #209 REF_invokeStatic coursier/credentials/DirectCredentials.$anonfun$autoMatches$3:(Ljava/net/URI;)Lscala/Option;
      #229 REF_invokeStatic coursier/credentials/DirectCredentials.$anonfun$autoMatches$4$adapted:(Lscala/Option;Ljava/lang/Object;)Ljava/lang/Object;
      #246 REF_invokeStatic coursier/credentials/DirectCredentials.$anonfun$matches$1:(Ljava/lang/String;)Ljava/net/URI;
      #251 REF_invokeStatic coursier/credentials/DirectCredentials.$anonfun$matches$2:(Ljava/net/URI;)Lscala/Option;
      #256 REF_invokeStatic coursier/credentials/DirectCredentials.$anonfun$matches$3:(Ljava/net/URI;)Lscala/Option;
      #261 REF_invokeStatic coursier/credentials/DirectCredentials.$anonfun$matches$4:(Ljava/net/URI;)Lscala/Option;
  ScalaInlineInfo: length = 0x103 (unknown attribute)
   01 01 00 33 01 0F 00 55 01 01 1B 01 1C 01 00 A4
   00 A5 01 00 C1 00 C2 01 00 CE 00 C2 01 01 B4 01
   B5 01 00 E1 00 E2 01 00 F3 00 A5 01 00 F8 00 C2
   01 00 FD 00 C2 01 01 02 00 C2 01 00 6D 01 C5 01
   00 6D 01 D0 01 00 6D 01 CE 01 00 6D 01 CC 01 00
   6D 01 47 01 01 0D 01 0E 01 00 95 00 96 01 01 6C
   00 D6 01 01 6F 00 D6 01 01 37 01 38 01 01 77 01
   78 01 00 10 00 55 01 00 1B 00 38 01 00 1A 00 38
   01 00 F0 00 F1 01 00 8C 00 38 01 00 18 00 38 01
   00 1C 00 38 01 00 15 00 58 01 01 92 01 78 01 01
   93 01 94 01 01 9E 01 9F 01 00 50 00 48 01 00 47
   00 48 01 01 91 00 55 01 00 17 00 58 01 01 51 00
   55 01 01 83 01 84 01 00 12 00 58 01 01 46 00 6A
   01 01 4F 01 4D 01 01 4E 01 4D 01 01 4C 01 4D 01
   01 50 01 4D 01 00 75 00 6A 01 00 7E 00 72 01 00
   81 00 6A 01 00 81 00 72 01 00 69 00 6A 01 00 71
   00 72 01
  ScalaSig: length = 0x3 (unknown attribute)
   05 02 00
