Classfile /Users/mw/Projects/slang-braindump/.jar/jar11/assemble/slang-braindump/assemble/content/org/antlr/runtime/tree/CommonTree.class
  Last modified May 29, 2022; size 3380 bytes
  SHA-256 checksum 13e6a545c50d2e7de5e0701dc4d5fdcf92c3b32cf1bf7785204ff34209dd69bb
  Compiled from "CommonTree.java"
public class org.antlr.runtime.tree.CommonTree extends org.antlr.runtime.tree.BaseTree
  minor version: 0
  major version: 49
  flags: (0x0021) ACC_PUBLIC, ACC_SUPER
  this_class: #7                          // org/antlr/runtime/tree/CommonTree
  super_class: #29                        // org/antlr/runtime/tree/BaseTree
  interfaces: 0, fields: 5, methods: 20, attributes: 1
Constant pool:
    #1 = Methodref          #29.#79       // org/antlr/runtime/tree/BaseTree."<init>":()V
    #2 = Fieldref           #7.#80        // org/antlr/runtime/tree/CommonTree.startIndex:I
    #3 = Fieldref           #7.#81        // org/antlr/runtime/tree/CommonTree.stopIndex:I
    #4 = Fieldref           #7.#82        // org/antlr/runtime/tree/CommonTree.childIndex:I
    #5 = Methodref          #29.#83       // org/antlr/runtime/tree/BaseTree."<init>":(Lorg/antlr/runtime/tree/Tree;)V
    #6 = Fieldref           #7.#84        // org/antlr/runtime/tree/CommonTree.token:Lorg/antlr/runtime/Token;
    #7 = Class              #85           // org/antlr/runtime/tree/CommonTree
    #8 = Methodref          #7.#86        // org/antlr/runtime/tree/CommonTree."<init>":(Lorg/antlr/runtime/tree/CommonTree;)V
    #9 = InterfaceMethodref #87.#88       // org/antlr/runtime/Token.getType:()I
   #10 = InterfaceMethodref #87.#89       // org/antlr/runtime/Token.getText:()Ljava/lang/String;
   #11 = InterfaceMethodref #87.#90       // org/antlr/runtime/Token.getLine:()I
   #12 = Methodref          #7.#91        // org/antlr/runtime/tree/CommonTree.getChildCount:()I
   #13 = Methodref          #7.#92        // org/antlr/runtime/tree/CommonTree.getChild:(I)Lorg/antlr/runtime/tree/Tree;
   #14 = InterfaceMethodref #93.#90       // org/antlr/runtime/tree/Tree.getLine:()I
   #15 = InterfaceMethodref #87.#94       // org/antlr/runtime/Token.getCharPositionInLine:()I
   #16 = InterfaceMethodref #93.#94       // org/antlr/runtime/tree/Tree.getCharPositionInLine:()I
   #17 = InterfaceMethodref #87.#95       // org/antlr/runtime/Token.getTokenIndex:()I
   #18 = Fieldref           #7.#96        // org/antlr/runtime/tree/CommonTree.children:Ljava/util/List;
   #19 = InterfaceMethodref #97.#98       // java/util/List.size:()I
   #20 = InterfaceMethodref #97.#99       // java/util/List.get:(I)Ljava/lang/Object;
   #21 = Methodref          #7.#100       // org/antlr/runtime/tree/CommonTree.setUnknownTokenBoundaries:()V
   #22 = Methodref          #7.#101       // org/antlr/runtime/tree/CommonTree.getTokenStartIndex:()I
   #23 = Methodref          #7.#102       // org/antlr/runtime/tree/CommonTree.getTokenStopIndex:()I
   #24 = Fieldref           #7.#103       // org/antlr/runtime/tree/CommonTree.parent:Lorg/antlr/runtime/tree/CommonTree;
   #25 = Methodref          #7.#104       // org/antlr/runtime/tree/CommonTree.isNil:()Z
   #26 = String             #105          // nil
   #27 = Methodref          #7.#88        // org/antlr/runtime/tree/CommonTree.getType:()I
   #28 = String             #106          // <errornode>
   #29 = Class              #107          // org/antlr/runtime/tree/BaseTree
   #30 = Utf8               token
   #31 = Utf8               Lorg/antlr/runtime/Token;
   #32 = Utf8               startIndex
   #33 = Utf8               I
   #34 = Utf8               stopIndex
   #35 = Utf8               parent
   #36 = Utf8               Lorg/antlr/runtime/tree/CommonTree;
   #37 = Utf8               childIndex
   #38 = Utf8               <init>
   #39 = Utf8               ()V
   #40 = Utf8               Code
   #41 = Utf8               LineNumberTable
   #42 = Utf8               LocalVariableTable
   #43 = Utf8               this
   #44 = Utf8               (Lorg/antlr/runtime/tree/CommonTree;)V
   #45 = Utf8               node
   #46 = Utf8               (Lorg/antlr/runtime/Token;)V
   #47 = Utf8               t
   #48 = Utf8               getToken
   #49 = Utf8               ()Lorg/antlr/runtime/Token;
   #50 = Utf8               dupNode
   #51 = Utf8               ()Lorg/antlr/runtime/tree/Tree;
   #52 = Utf8               isNil
   #53 = Utf8               ()Z
   #54 = Utf8               getType
   #55 = Utf8               ()I
   #56 = Utf8               getText
   #57 = Utf8               ()Ljava/lang/String;
   #58 = Utf8               getLine
   #59 = Utf8               getCharPositionInLine
   #60 = Utf8               getTokenStartIndex
   #61 = Utf8               setTokenStartIndex
   #62 = Utf8               (I)V
   #63 = Utf8               index
   #64 = Utf8               getTokenStopIndex
   #65 = Utf8               setTokenStopIndex
   #66 = Utf8               setUnknownTokenBoundaries
   #67 = Utf8               i
   #68 = Utf8               firstChild
   #69 = Utf8               lastChild
   #70 = Utf8               getChildIndex
   #71 = Utf8               getParent
   #72 = Utf8               setParent
   #73 = Utf8               (Lorg/antlr/runtime/tree/Tree;)V
   #74 = Utf8               Lorg/antlr/runtime/tree/Tree;
   #75 = Utf8               setChildIndex
   #76 = Utf8               toString
   #77 = Utf8               SourceFile
   #78 = Utf8               CommonTree.java
   #79 = NameAndType        #38:#39       // "<init>":()V
   #80 = NameAndType        #32:#33       // startIndex:I
   #81 = NameAndType        #34:#33       // stopIndex:I
   #82 = NameAndType        #37:#33       // childIndex:I
   #83 = NameAndType        #38:#73       // "<init>":(Lorg/antlr/runtime/tree/Tree;)V
   #84 = NameAndType        #30:#31       // token:Lorg/antlr/runtime/Token;
   #85 = Utf8               org/antlr/runtime/tree/CommonTree
   #86 = NameAndType        #38:#44       // "<init>":(Lorg/antlr/runtime/tree/CommonTree;)V
   #87 = Class              #108          // org/antlr/runtime/Token
   #88 = NameAndType        #54:#55       // getType:()I
   #89 = NameAndType        #56:#57       // getText:()Ljava/lang/String;
   #90 = NameAndType        #58:#55       // getLine:()I
   #91 = NameAndType        #109:#55      // getChildCount:()I
   #92 = NameAndType        #110:#111     // getChild:(I)Lorg/antlr/runtime/tree/Tree;
   #93 = Class              #112          // org/antlr/runtime/tree/Tree
   #94 = NameAndType        #59:#55       // getCharPositionInLine:()I
   #95 = NameAndType        #113:#55      // getTokenIndex:()I
   #96 = NameAndType        #114:#115     // children:Ljava/util/List;
   #97 = Class              #116          // java/util/List
   #98 = NameAndType        #117:#55      // size:()I
   #99 = NameAndType        #118:#119     // get:(I)Ljava/lang/Object;
  #100 = NameAndType        #66:#39       // setUnknownTokenBoundaries:()V
  #101 = NameAndType        #60:#55       // getTokenStartIndex:()I
  #102 = NameAndType        #64:#55       // getTokenStopIndex:()I
  #103 = NameAndType        #35:#36       // parent:Lorg/antlr/runtime/tree/CommonTree;
  #104 = NameAndType        #52:#53       // isNil:()Z
  #105 = Utf8               nil
  #106 = Utf8               <errornode>
  #107 = Utf8               org/antlr/runtime/tree/BaseTree
  #108 = Utf8               org/antlr/runtime/Token
  #109 = Utf8               getChildCount
  #110 = Utf8               getChild
  #111 = Utf8               (I)Lorg/antlr/runtime/tree/Tree;
  #112 = Utf8               org/antlr/runtime/tree/Tree
  #113 = Utf8               getTokenIndex
  #114 = Utf8               children
  #115 = Utf8               Ljava/util/List;
  #116 = Utf8               java/util/List
  #117 = Utf8               size
  #118 = Utf8               get
  #119 = Utf8               (I)Ljava/lang/Object;
{
  public org.antlr.runtime.Token token;
    descriptor: Lorg/antlr/runtime/Token;
    flags: (0x0001) ACC_PUBLIC

  protected int startIndex;
    descriptor: I
    flags: (0x0004) ACC_PROTECTED

  protected int stopIndex;
    descriptor: I
    flags: (0x0004) ACC_PROTECTED

  public org.antlr.runtime.tree.CommonTree parent;
    descriptor: Lorg/antlr/runtime/tree/CommonTree;
    flags: (0x0001) ACC_PUBLIC

  public int childIndex;
    descriptor: I
    flags: (0x0001) ACC_PUBLIC

  public org.antlr.runtime.tree.CommonTree();
    descriptor: ()V
    flags: (0x0001) ACC_PUBLIC
    Code:
      stack=2, locals=1, args_size=1
         0: aload_0
         1: invokespecial #1                  // Method org/antlr/runtime/tree/BaseTree."<init>":()V
         4: aload_0
         5: iconst_m1
         6: putfield      #2                  // Field startIndex:I
         9: aload_0
        10: iconst_m1
        11: putfield      #3                  // Field stopIndex:I
        14: aload_0
        15: iconst_m1
        16: putfield      #4                  // Field childIndex:I
        19: return
      LineNumberTable:
        line 53: 0
        line 45: 4
        line 51: 14
        line 53: 19
      LocalVariableTable:
        Start  Length  Slot  Name   Signature
            0      20     0  this   Lorg/antlr/runtime/tree/CommonTree;

  public org.antlr.runtime.tree.CommonTree(org.antlr.runtime.tree.CommonTree);
    descriptor: (Lorg/antlr/runtime/tree/CommonTree;)V
    flags: (0x0001) ACC_PUBLIC
    Code:
      stack=2, locals=2, args_size=2
         0: aload_0
         1: aload_1
         2: invokespecial #5                  // Method org/antlr/runtime/tree/BaseTree."<init>":(Lorg/antlr/runtime/tree/Tree;)V
         5: aload_0
         6: iconst_m1
         7: putfield      #2                  // Field startIndex:I
        10: aload_0
        11: iconst_m1
        12: putfield      #3                  // Field stopIndex:I
        15: aload_0
        16: iconst_m1
        17: putfield      #4                  // Field childIndex:I
        20: aload_0
        21: aload_1
        22: getfield      #6                  // Field token:Lorg/antlr/runtime/Token;
        25: putfield      #6                  // Field token:Lorg/antlr/runtime/Token;
        28: aload_0
        29: aload_1
        30: getfield      #2                  // Field startIndex:I
        33: putfield      #2                  // Field startIndex:I
        36: aload_0
        37: aload_1
        38: getfield      #3                  // Field stopIndex:I
        41: putfield      #3                  // Field stopIndex:I
        44: return
      LineNumberTable:
        line 56: 0
        line 45: 5
        line 51: 15
        line 57: 20
        line 58: 28
        line 59: 36
        line 60: 44
      LocalVariableTable:
        Start  Length  Slot  Name   Signature
            0      45     0  this   Lorg/antlr/runtime/tree/CommonTree;
            0      45     1  node   Lorg/antlr/runtime/tree/CommonTree;

  public org.antlr.runtime.tree.CommonTree(org.antlr.runtime.Token);
    descriptor: (Lorg/antlr/runtime/Token;)V
    flags: (0x0001) ACC_PUBLIC
    Code:
      stack=2, locals=2, args_size=2
         0: aload_0
         1: invokespecial #1                  // Method org/antlr/runtime/tree/BaseTree."<init>":()V
         4: aload_0
         5: iconst_m1
         6: putfield      #2                  // Field startIndex:I
         9: aload_0
        10: iconst_m1
        11: putfield      #3                  // Field stopIndex:I
        14: aload_0
        15: iconst_m1
        16: putfield      #4                  // Field childIndex:I
        19: aload_0
        20: aload_1
        21: putfield      #6                  // Field token:Lorg/antlr/runtime/Token;
        24: return
      LineNumberTable:
        line 62: 0
        line 45: 4
        line 51: 14
        line 63: 19
        line 64: 24
      LocalVariableTable:
        Start  Length  Slot  Name   Signature
            0      25     0  this   Lorg/antlr/runtime/tree/CommonTree;
            0      25     1     t   Lorg/antlr/runtime/Token;

  public org.antlr.runtime.Token getToken();
    descriptor: ()Lorg/antlr/runtime/Token;
    flags: (0x0001) ACC_PUBLIC
    Code:
      stack=1, locals=1, args_size=1
         0: aload_0
         1: getfield      #6                  // Field token:Lorg/antlr/runtime/Token;
         4: areturn
      LineNumberTable:
        line 67: 0
      LocalVariableTable:
        Start  Length  Slot  Name   Signature
            0       5     0  this   Lorg/antlr/runtime/tree/CommonTree;

  public org.antlr.runtime.tree.Tree dupNode();
    descriptor: ()Lorg/antlr/runtime/tree/Tree;
    flags: (0x0001) ACC_PUBLIC
    Code:
      stack=3, locals=1, args_size=1
         0: new           #7                  // class org/antlr/runtime/tree/CommonTree
         3: dup
         4: aload_0
         5: invokespecial #8                  // Method "<init>":(Lorg/antlr/runtime/tree/CommonTree;)V
         8: areturn
      LineNumberTable:
        line 72: 0
      LocalVariableTable:
        Start  Length  Slot  Name   Signature
            0       9     0  this   Lorg/antlr/runtime/tree/CommonTree;

  public boolean isNil();
    descriptor: ()Z
    flags: (0x0001) ACC_PUBLIC
    Code:
      stack=1, locals=1, args_size=1
         0: aload_0
         1: getfield      #6                  // Field token:Lorg/antlr/runtime/Token;
         4: ifnonnull     11
         7: iconst_1
         8: goto          12
        11: iconst_0
        12: ireturn
      LineNumberTable:
        line 77: 0
      LocalVariableTable:
        Start  Length  Slot  Name   Signature
            0      13     0  this   Lorg/antlr/runtime/tree/CommonTree;

  public int getType();
    descriptor: ()I
    flags: (0x0001) ACC_PUBLIC
    Code:
      stack=1, locals=1, args_size=1
         0: aload_0
         1: getfield      #6                  // Field token:Lorg/antlr/runtime/Token;
         4: ifnonnull     9
         7: iconst_0
         8: ireturn
         9: aload_0
        10: getfield      #6                  // Field token:Lorg/antlr/runtime/Token;
        13: invokeinterface #9,  1            // InterfaceMethod org/antlr/runtime/Token.getType:()I
        18: ireturn
      LineNumberTable:
        line 82: 0
        line 83: 7
        line 85: 9
      LocalVariableTable:
        Start  Length  Slot  Name   Signature
            0      19     0  this   Lorg/antlr/runtime/tree/CommonTree;

  public java.lang.String getText();
    descriptor: ()Ljava/lang/String;
    flags: (0x0001) ACC_PUBLIC
    Code:
      stack=1, locals=1, args_size=1
         0: aload_0
         1: getfield      #6                  // Field token:Lorg/antlr/runtime/Token;
         4: ifnonnull     9
         7: aconst_null
         8: areturn
         9: aload_0
        10: getfield      #6                  // Field token:Lorg/antlr/runtime/Token;
        13: invokeinterface #10,  1           // InterfaceMethod org/antlr/runtime/Token.getText:()Ljava/lang/String;
        18: areturn
      LineNumberTable:
        line 90: 0
        line 91: 7
        line 93: 9
      LocalVariableTable:
        Start  Length  Slot  Name   Signature
            0      19     0  this   Lorg/antlr/runtime/tree/CommonTree;

  public int getLine();
    descriptor: ()I
    flags: (0x0001) ACC_PUBLIC
    Code:
      stack=2, locals=1, args_size=1
         0: aload_0
         1: getfield      #6                  // Field token:Lorg/antlr/runtime/Token;
         4: ifnull        19
         7: aload_0
         8: getfield      #6                  // Field token:Lorg/antlr/runtime/Token;
        11: invokeinterface #11,  1           // InterfaceMethod org/antlr/runtime/Token.getLine:()I
        16: ifne          39
        19: aload_0
        20: invokevirtual #12                 // Method getChildCount:()I
        23: ifle          37
        26: aload_0
        27: iconst_0
        28: invokevirtual #13                 // Method getChild:(I)Lorg/antlr/runtime/tree/Tree;
        31: invokeinterface #14,  1           // InterfaceMethod org/antlr/runtime/tree/Tree.getLine:()I
        36: ireturn
        37: iconst_0
        38: ireturn
        39: aload_0
        40: getfield      #6                  // Field token:Lorg/antlr/runtime/Token;
        43: invokeinterface #11,  1           // InterfaceMethod org/antlr/runtime/Token.getLine:()I
        48: ireturn
      LineNumberTable:
        line 98: 0
        line 99: 19
        line 100: 26
        line 102: 37
        line 104: 39
      LocalVariableTable:
        Start  Length  Slot  Name   Signature
            0      49     0  this   Lorg/antlr/runtime/tree/CommonTree;

  public int getCharPositionInLine();
    descriptor: ()I
    flags: (0x0001) ACC_PUBLIC
    Code:
      stack=2, locals=1, args_size=1
         0: aload_0
         1: getfield      #6                  // Field token:Lorg/antlr/runtime/Token;
         4: ifnull        20
         7: aload_0
         8: getfield      #6                  // Field token:Lorg/antlr/runtime/Token;
        11: invokeinterface #15,  1           // InterfaceMethod org/antlr/runtime/Token.getCharPositionInLine:()I
        16: iconst_m1
        17: if_icmpne     40
        20: aload_0
        21: invokevirtual #12                 // Method getChildCount:()I
        24: ifle          38
        27: aload_0
        28: iconst_0
        29: invokevirtual #13                 // Method getChild:(I)Lorg/antlr/runtime/tree/Tree;
        32: invokeinterface #16,  1           // InterfaceMethod org/antlr/runtime/tree/Tree.getCharPositionInLine:()I
        37: ireturn
        38: iconst_0
        39: ireturn
        40: aload_0
        41: getfield      #6                  // Field token:Lorg/antlr/runtime/Token;
        44: invokeinterface #15,  1           // InterfaceMethod org/antlr/runtime/Token.getCharPositionInLine:()I
        49: ireturn
      LineNumberTable:
        line 109: 0
        line 110: 20
        line 111: 27
        line 113: 38
        line 115: 40
      LocalVariableTable:
        Start  Length  Slot  Name   Signature
            0      50     0  this   Lorg/antlr/runtime/tree/CommonTree;

  public int getTokenStartIndex();
    descriptor: ()I
    flags: (0x0001) ACC_PUBLIC
    Code:
      stack=2, locals=1, args_size=1
         0: aload_0
         1: getfield      #2                  // Field startIndex:I
         4: iconst_m1
         5: if_icmpne     25
         8: aload_0
         9: getfield      #6                  // Field token:Lorg/antlr/runtime/Token;
        12: ifnull        25
        15: aload_0
        16: getfield      #6                  // Field token:Lorg/antlr/runtime/Token;
        19: invokeinterface #17,  1           // InterfaceMethod org/antlr/runtime/Token.getTokenIndex:()I
        24: ireturn
        25: aload_0
        26: getfield      #2                  // Field startIndex:I
        29: ireturn
      LineNumberTable:
        line 120: 0
        line 121: 15
        line 123: 25
      LocalVariableTable:
        Start  Length  Slot  Name   Signature
            0      30     0  this   Lorg/antlr/runtime/tree/CommonTree;

  public void setTokenStartIndex(int);
    descriptor: (I)V
    flags: (0x0001) ACC_PUBLIC
    Code:
      stack=2, locals=2, args_size=2
         0: aload_0
         1: iload_1
         2: putfield      #2                  // Field startIndex:I
         5: return
      LineNumberTable:
        line 128: 0
        line 129: 5
      LocalVariableTable:
        Start  Length  Slot  Name   Signature
            0       6     0  this   Lorg/antlr/runtime/tree/CommonTree;
            0       6     1 index   I

  public int getTokenStopIndex();
    descriptor: ()I
    flags: (0x0001) ACC_PUBLIC
    Code:
      stack=2, locals=1, args_size=1
         0: aload_0
         1: getfield      #3                  // Field stopIndex:I
         4: iconst_m1
         5: if_icmpne     25
         8: aload_0
         9: getfield      #6                  // Field token:Lorg/antlr/runtime/Token;
        12: ifnull        25
        15: aload_0
        16: getfield      #6                  // Field token:Lorg/antlr/runtime/Token;
        19: invokeinterface #17,  1           // InterfaceMethod org/antlr/runtime/Token.getTokenIndex:()I
        24: ireturn
        25: aload_0
        26: getfield      #3                  // Field stopIndex:I
        29: ireturn
      LineNumberTable:
        line 133: 0
        line 134: 15
        line 136: 25
      LocalVariableTable:
        Start  Length  Slot  Name   Signature
            0      30     0  this   Lorg/antlr/runtime/tree/CommonTree;

  public void setTokenStopIndex(int);
    descriptor: (I)V
    flags: (0x0001) ACC_PUBLIC
    Code:
      stack=2, locals=2, args_size=2
         0: aload_0
         1: iload_1
         2: putfield      #3                  // Field stopIndex:I
         5: return
      LineNumberTable:
        line 141: 0
        line 142: 5
      LocalVariableTable:
        Start  Length  Slot  Name   Signature
            0       6     0  this   Lorg/antlr/runtime/tree/CommonTree;
            0       6     1 index   I

  public void setUnknownTokenBoundaries();
    descriptor: ()V
    flags: (0x0001) ACC_PUBLIC
    Code:
      stack=4, locals=3, args_size=1
         0: aload_0
         1: getfield      #18                 // Field children:Ljava/util/List;
         4: ifnonnull     40
         7: aload_0
         8: getfield      #2                  // Field startIndex:I
        11: iflt          21
        14: aload_0
        15: getfield      #3                  // Field stopIndex:I
        18: ifge          39
        21: aload_0
        22: aload_0
        23: aload_0
        24: getfield      #6                  // Field token:Lorg/antlr/runtime/Token;
        27: invokeinterface #17,  1           // InterfaceMethod org/antlr/runtime/Token.getTokenIndex:()I
        32: dup_x1
        33: putfield      #3                  // Field stopIndex:I
        36: putfield      #2                  // Field startIndex:I
        39: return
        40: iconst_0
        41: istore_1
        42: iload_1
        43: aload_0
        44: getfield      #18                 // Field children:Ljava/util/List;
        47: invokeinterface #19,  1           // InterfaceMethod java/util/List.size:()I
        52: if_icmpge     77
        55: aload_0
        56: getfield      #18                 // Field children:Ljava/util/List;
        59: iload_1
        60: invokeinterface #20,  2           // InterfaceMethod java/util/List.get:(I)Ljava/lang/Object;
        65: checkcast     #7                  // class org/antlr/runtime/tree/CommonTree
        68: invokevirtual #21                 // Method setUnknownTokenBoundaries:()V
        71: iinc          1, 1
        74: goto          42
        77: aload_0
        78: getfield      #2                  // Field startIndex:I
        81: iflt          92
        84: aload_0
        85: getfield      #3                  // Field stopIndex:I
        88: iflt          92
        91: return
        92: aload_0
        93: getfield      #18                 // Field children:Ljava/util/List;
        96: invokeinterface #19,  1           // InterfaceMethod java/util/List.size:()I
       101: ifle          158
       104: aload_0
       105: getfield      #18                 // Field children:Ljava/util/List;
       108: iconst_0
       109: invokeinterface #20,  2           // InterfaceMethod java/util/List.get:(I)Ljava/lang/Object;
       114: checkcast     #7                  // class org/antlr/runtime/tree/CommonTree
       117: astore_1
       118: aload_0
       119: getfield      #18                 // Field children:Ljava/util/List;
       122: aload_0
       123: getfield      #18                 // Field children:Ljava/util/List;
       126: invokeinterface #19,  1           // InterfaceMethod java/util/List.size:()I
       131: iconst_1
       132: isub
       133: invokeinterface #20,  2           // InterfaceMethod java/util/List.get:(I)Ljava/lang/Object;
       138: checkcast     #7                  // class org/antlr/runtime/tree/CommonTree
       141: astore_2
       142: aload_0
       143: aload_1
       144: invokevirtual #22                 // Method getTokenStartIndex:()I
       147: putfield      #2                  // Field startIndex:I
       150: aload_0
       151: aload_2
       152: invokevirtual #23                 // Method getTokenStopIndex:()I
       155: putfield      #3                  // Field stopIndex:I
       158: return
      LineNumberTable:
        line 149: 0
        line 150: 7
        line 151: 21
        line 153: 39
        line 155: 40
        line 156: 55
        line 155: 71
        line 158: 77
        line 159: 92
        line 160: 104
        line 161: 118
        line 162: 142
        line 163: 150
        line 165: 158
      LocalVariableTable:
        Start  Length  Slot  Name   Signature
           42      35     1     i   I
          118      40     1 firstChild   Lorg/antlr/runtime/tree/CommonTree;
          142      16     2 lastChild   Lorg/antlr/runtime/tree/CommonTree;
            0     159     0  this   Lorg/antlr/runtime/tree/CommonTree;

  public int getChildIndex();
    descriptor: ()I
    flags: (0x0001) ACC_PUBLIC
    Code:
      stack=1, locals=1, args_size=1
         0: aload_0
         1: getfield      #4                  // Field childIndex:I
         4: ireturn
      LineNumberTable:
        line 169: 0
      LocalVariableTable:
        Start  Length  Slot  Name   Signature
            0       5     0  this   Lorg/antlr/runtime/tree/CommonTree;

  public org.antlr.runtime.tree.Tree getParent();
    descriptor: ()Lorg/antlr/runtime/tree/Tree;
    flags: (0x0001) ACC_PUBLIC
    Code:
      stack=1, locals=1, args_size=1
         0: aload_0
         1: getfield      #24                 // Field parent:Lorg/antlr/runtime/tree/CommonTree;
         4: areturn
      LineNumberTable:
        line 174: 0
      LocalVariableTable:
        Start  Length  Slot  Name   Signature
            0       5     0  this   Lorg/antlr/runtime/tree/CommonTree;

  public void setParent(org.antlr.runtime.tree.Tree);
    descriptor: (Lorg/antlr/runtime/tree/Tree;)V
    flags: (0x0001) ACC_PUBLIC
    Code:
      stack=2, locals=2, args_size=2
         0: aload_0
         1: aload_1
         2: checkcast     #7                  // class org/antlr/runtime/tree/CommonTree
         5: putfield      #24                 // Field parent:Lorg/antlr/runtime/tree/CommonTree;
         8: return
      LineNumberTable:
        line 179: 0
        line 180: 8
      LocalVariableTable:
        Start  Length  Slot  Name   Signature
            0       9     0  this   Lorg/antlr/runtime/tree/CommonTree;
            0       9     1     t   Lorg/antlr/runtime/tree/Tree;

  public void setChildIndex(int);
    descriptor: (I)V
    flags: (0x0001) ACC_PUBLIC
    Code:
      stack=2, locals=2, args_size=2
         0: aload_0
         1: iload_1
         2: putfield      #4                  // Field childIndex:I
         5: return
      LineNumberTable:
        line 184: 0
        line 185: 5
      LocalVariableTable:
        Start  Length  Slot  Name   Signature
            0       6     0  this   Lorg/antlr/runtime/tree/CommonTree;
            0       6     1 index   I

  public java.lang.String toString();
    descriptor: ()Ljava/lang/String;
    flags: (0x0001) ACC_PUBLIC
    Code:
      stack=1, locals=1, args_size=1
         0: aload_0
         1: invokevirtual #25                 // Method isNil:()Z
         4: ifeq          10
         7: ldc           #26                 // String nil
         9: areturn
        10: aload_0
        11: invokevirtual #27                 // Method getType:()I
        14: ifne          20
        17: ldc           #28                 // String <errornode>
        19: areturn
        20: aload_0
        21: getfield      #6                  // Field token:Lorg/antlr/runtime/Token;
        24: ifnonnull     29
        27: aconst_null
        28: areturn
        29: aload_0
        30: getfield      #6                  // Field token:Lorg/antlr/runtime/Token;
        33: invokeinterface #10,  1           // InterfaceMethod org/antlr/runtime/Token.getText:()Ljava/lang/String;
        38: areturn
      LineNumberTable:
        line 189: 0
        line 190: 7
        line 192: 10
        line 193: 17
        line 195: 20
        line 196: 27
        line 198: 29
      LocalVariableTable:
        Start  Length  Slot  Name   Signature
            0      39     0  this   Lorg/antlr/runtime/tree/CommonTree;
}
SourceFile: "CommonTree.java"
