Classfile /Users/mw/Projects/slang-braindump/.jar/jar11/assemble/slang-braindump/assemble/content/org/antlr/runtime/tree/DOTTreeGenerator.class
  Last modified May 29, 2022; size 5040 bytes
  SHA-256 checksum 91777187ae6f46e1bb9d482917c2d915e22eb25a8d7bc18f67f7011901e88230
  Compiled from "DOTTreeGenerator.java"
public class org.antlr.runtime.tree.DOTTreeGenerator
  minor version: 0
  major version: 49
  flags: (0x0021) ACC_PUBLIC, ACC_SUPER
  this_class: #60                         // org/antlr/runtime/tree/DOTTreeGenerator
  super_class: #61                        // java/lang/Object
  interfaces: 0, fields: 5, methods: 10, attributes: 1
Constant pool:
    #1 = Methodref          #61.#118      // java/lang/Object."<init>":()V
    #2 = Class              #119          // java/util/HashMap
    #3 = Methodref          #2.#118       // java/util/HashMap."<init>":()V
    #4 = Fieldref           #60.#120      // org/antlr/runtime/tree/DOTTreeGenerator.nodeToNumberMap:Ljava/util/HashMap;
    #5 = Fieldref           #60.#121      // org/antlr/runtime/tree/DOTTreeGenerator.nodeNumber:I
    #6 = Methodref          #55.#122      // org/antlr/stringtemplate/StringTemplate.getInstanceOf:()Lorg/antlr/stringtemplate/StringTemplate;
    #7 = Methodref          #60.#123      // org/antlr/runtime/tree/DOTTreeGenerator.toDOTDefineNodes:(Ljava/lang/Object;Lorg/antlr/runtime/tree/TreeAdaptor;Lorg/antlr/stringtemplate/StringTemplate;)V
    #8 = Methodref          #60.#124      // org/antlr/runtime/tree/DOTTreeGenerator.toDOTDefineEdges:(Ljava/lang/Object;Lorg/antlr/runtime/tree/TreeAdaptor;Lorg/antlr/stringtemplate/StringTemplate;)V
    #9 = Fieldref           #60.#125      // org/antlr/runtime/tree/DOTTreeGenerator._treeST:Lorg/antlr/stringtemplate/StringTemplate;
   #10 = Fieldref           #60.#126      // org/antlr/runtime/tree/DOTTreeGenerator._edgeST:Lorg/antlr/stringtemplate/StringTemplate;
   #11 = Methodref          #60.#127      // org/antlr/runtime/tree/DOTTreeGenerator.toDOT:(Ljava/lang/Object;Lorg/antlr/runtime/tree/TreeAdaptor;Lorg/antlr/stringtemplate/StringTemplate;Lorg/antlr/stringtemplate/StringTemplate;)Lorg/antlr/stringtemplate/StringTemplate;
   #12 = Class              #128          // org/antlr/runtime/tree/CommonTreeAdaptor
   #13 = Methodref          #12.#118      // org/antlr/runtime/tree/CommonTreeAdaptor."<init>":()V
   #14 = Methodref          #60.#129      // org/antlr/runtime/tree/DOTTreeGenerator.toDOT:(Ljava/lang/Object;Lorg/antlr/runtime/tree/TreeAdaptor;)Lorg/antlr/stringtemplate/StringTemplate;
   #15 = InterfaceMethodref #130.#131     // org/antlr/runtime/tree/TreeAdaptor.getChildCount:(Ljava/lang/Object;)I
   #16 = Methodref          #60.#132      // org/antlr/runtime/tree/DOTTreeGenerator.getNodeST:(Lorg/antlr/runtime/tree/TreeAdaptor;Ljava/lang/Object;)Lorg/antlr/stringtemplate/StringTemplate;
   #17 = String             #133          // nodes
   #18 = Methodref          #55.#134      // org/antlr/stringtemplate/StringTemplate.setAttribute:(Ljava/lang/String;Ljava/lang/Object;)V
   #19 = InterfaceMethodref #130.#135     // org/antlr/runtime/tree/TreeAdaptor.getChild:(Ljava/lang/Object;I)Ljava/lang/Object;
   #20 = Class              #136          // java/lang/StringBuilder
   #21 = Methodref          #20.#118      // java/lang/StringBuilder."<init>":()V
   #22 = String             #94           // n
   #23 = Methodref          #20.#137      // java/lang/StringBuilder.append:(Ljava/lang/String;)Ljava/lang/StringBuilder;
   #24 = Methodref          #60.#138      // org/antlr/runtime/tree/DOTTreeGenerator.getNodeNumber:(Ljava/lang/Object;)I
   #25 = Methodref          #20.#139      // java/lang/StringBuilder.append:(I)Ljava/lang/StringBuilder;
   #26 = Methodref          #20.#140      // java/lang/StringBuilder.toString:()Ljava/lang/String;
   #27 = InterfaceMethodref #130.#141     // org/antlr/runtime/tree/TreeAdaptor.getText:(Ljava/lang/Object;)Ljava/lang/String;
   #28 = String             #142          // parent
   #29 = String             #91           // child
   #30 = String             #102          // parentText
   #31 = Methodref          #60.#143      // org/antlr/runtime/tree/DOTTreeGenerator.fixString:(Ljava/lang/String;)Ljava/lang/String;
   #32 = String             #97           // childText
   #33 = String             #144          // edges
   #34 = Fieldref           #60.#145      // org/antlr/runtime/tree/DOTTreeGenerator._nodeST:Lorg/antlr/stringtemplate/StringTemplate;
   #35 = String             #146          // name
   #36 = String             #106          // text
   #37 = Methodref          #2.#147       // java/util/HashMap.get:(Ljava/lang/Object;)Ljava/lang/Object;
   #38 = Class              #148          // java/lang/Integer
   #39 = Methodref          #38.#149      // java/lang/Integer.intValue:()I
   #40 = Methodref          #38.#150      // java/lang/Integer.valueOf:(I)Ljava/lang/Integer;
   #41 = Methodref          #2.#151       // java/util/HashMap.put:(Ljava/lang/Object;Ljava/lang/Object;)Ljava/lang/Object;
   #42 = String             #152          // \"
   #43 = String             #153          // \\\\\"
   #44 = Methodref          #154.#155     // java/lang/String.replaceAll:(Ljava/lang/String;Ljava/lang/String;)Ljava/lang/String;
   #45 = String             #156          // \\t
   #46 = String             #157          //
   #47 = String             #158          // \\n
   #48 = String             #159          // \\\\n
   #49 = String             #160          // \\r
   #50 = String             #161          // \\\\r
   #51 = Methodref          #154.#162     // java/lang/String.length:()I
   #52 = Methodref          #154.#163     // java/lang/String.substring:(II)Ljava/lang/String;
   #53 = String             #164          // ...
   #54 = Methodref          #154.#165     // java/lang/String.substring:(I)Ljava/lang/String;
   #55 = Class              #166          // org/antlr/stringtemplate/StringTemplate
   #56 = String             #167          // digraph {\n\n\tordering=out;\n\tranksep=.4;\n\tbgcolor=\"lightgrey\"; node [shape=box, fixedsize=false, fontsize=12, fontname=\"Helvetica-bold\", fontcolor=\"blue\"\n\t\twidth=.25, height=.25, color=\"black\", fillcolor=\"white\", style=\"filled, solid, bold\"];\n\tedge [arrowsize=.5, color=\"black\", style=\"bold\"]\n\n  $nodes$\n  $edges$\n}\n
   #57 = Methodref          #55.#168      // org/antlr/stringtemplate/StringTemplate."<init>":(Ljava/lang/String;)V
   #58 = String             #169          // $name$ [label=\"$text$\"];\n
   #59 = String             #170          // $parent$ -> $child$ // \"$parentText$\" -> \"$childText$\"\n
   #60 = Class              #171          // org/antlr/runtime/tree/DOTTreeGenerator
   #61 = Class              #172          // java/lang/Object
   #62 = Utf8               _treeST
   #63 = Utf8               Lorg/antlr/stringtemplate/StringTemplate;
   #64 = Utf8               _nodeST
   #65 = Utf8               _edgeST
   #66 = Utf8               nodeToNumberMap
   #67 = Utf8               Ljava/util/HashMap;
   #68 = Utf8               Signature
   #69 = Utf8               Ljava/util/HashMap<Ljava/lang/Object;Ljava/lang/Integer;>;
   #70 = Utf8               nodeNumber
   #71 = Utf8               I
   #72 = Utf8               <init>
   #73 = Utf8               ()V
   #74 = Utf8               Code
   #75 = Utf8               LineNumberTable
   #76 = Utf8               LocalVariableTable
   #77 = Utf8               this
   #78 = Utf8               Lorg/antlr/runtime/tree/DOTTreeGenerator;
   #79 = Utf8               toDOT
   #80 = Utf8               (Ljava/lang/Object;Lorg/antlr/runtime/tree/TreeAdaptor;Lorg/antlr/stringtemplate/StringTemplate;Lorg/antlr/stringtemplate/StringTemplate;)Lorg/antlr/stringtemplate/StringTemplate;
   #81 = Utf8               tree
   #82 = Utf8               Ljava/lang/Object;
   #83 = Utf8               adaptor
   #84 = Utf8               Lorg/antlr/runtime/tree/TreeAdaptor;
   #85 = Utf8               treeST
   #86 = Utf8               (Ljava/lang/Object;Lorg/antlr/runtime/tree/TreeAdaptor;)Lorg/antlr/stringtemplate/StringTemplate;
   #87 = Utf8               (Lorg/antlr/runtime/tree/Tree;)Lorg/antlr/stringtemplate/StringTemplate;
   #88 = Utf8               Lorg/antlr/runtime/tree/Tree;
   #89 = Utf8               toDOTDefineNodes
   #90 = Utf8               (Ljava/lang/Object;Lorg/antlr/runtime/tree/TreeAdaptor;Lorg/antlr/stringtemplate/StringTemplate;)V
   #91 = Utf8               child
   #92 = Utf8               nodeST
   #93 = Utf8               i
   #94 = Utf8               n
   #95 = Utf8               parentNodeST
   #96 = Utf8               toDOTDefineEdges
   #97 = Utf8               childText
   #98 = Utf8               Ljava/lang/String;
   #99 = Utf8               childName
  #100 = Utf8               edgeST
  #101 = Utf8               parentName
  #102 = Utf8               parentText
  #103 = Utf8               getNodeST
  #104 = Utf8               (Lorg/antlr/runtime/tree/TreeAdaptor;Ljava/lang/Object;)Lorg/antlr/stringtemplate/StringTemplate;
  #105 = Utf8               t
  #106 = Utf8               text
  #107 = Utf8               uniqueName
  #108 = Utf8               getNodeNumber
  #109 = Utf8               (Ljava/lang/Object;)I
  #110 = Utf8               nI
  #111 = Utf8               Ljava/lang/Integer;
  #112 = Utf8               fixString
  #113 = Utf8               (Ljava/lang/String;)Ljava/lang/String;
  #114 = Utf8               in
  #115 = Utf8               <clinit>
  #116 = Utf8               SourceFile
  #117 = Utf8               DOTTreeGenerator.java
  #118 = NameAndType        #72:#73       // "<init>":()V
  #119 = Utf8               java/util/HashMap
  #120 = NameAndType        #66:#67       // nodeToNumberMap:Ljava/util/HashMap;
  #121 = NameAndType        #70:#71       // nodeNumber:I
  #122 = NameAndType        #173:#174     // getInstanceOf:()Lorg/antlr/stringtemplate/StringTemplate;
  #123 = NameAndType        #89:#90       // toDOTDefineNodes:(Ljava/lang/Object;Lorg/antlr/runtime/tree/TreeAdaptor;Lorg/antlr/stringtemplate/StringTemplate;)V
  #124 = NameAndType        #96:#90       // toDOTDefineEdges:(Ljava/lang/Object;Lorg/antlr/runtime/tree/TreeAdaptor;Lorg/antlr/stringtemplate/StringTemplate;)V
  #125 = NameAndType        #62:#63       // _treeST:Lorg/antlr/stringtemplate/StringTemplate;
  #126 = NameAndType        #65:#63       // _edgeST:Lorg/antlr/stringtemplate/StringTemplate;
  #127 = NameAndType        #79:#80       // toDOT:(Ljava/lang/Object;Lorg/antlr/runtime/tree/TreeAdaptor;Lorg/antlr/stringtemplate/StringTemplate;Lorg/antlr/stringtemplate/StringTemplate;)Lorg/antlr/stringtemplate/StringTemplate;
  #128 = Utf8               org/antlr/runtime/tree/CommonTreeAdaptor
  #129 = NameAndType        #79:#86       // toDOT:(Ljava/lang/Object;Lorg/antlr/runtime/tree/TreeAdaptor;)Lorg/antlr/stringtemplate/StringTemplate;
  #130 = Class              #175          // org/antlr/runtime/tree/TreeAdaptor
  #131 = NameAndType        #176:#109     // getChildCount:(Ljava/lang/Object;)I
  #132 = NameAndType        #103:#104     // getNodeST:(Lorg/antlr/runtime/tree/TreeAdaptor;Ljava/lang/Object;)Lorg/antlr/stringtemplate/StringTemplate;
  #133 = Utf8               nodes
  #134 = NameAndType        #177:#178     // setAttribute:(Ljava/lang/String;Ljava/lang/Object;)V
  #135 = NameAndType        #179:#180     // getChild:(Ljava/lang/Object;I)Ljava/lang/Object;
  #136 = Utf8               java/lang/StringBuilder
  #137 = NameAndType        #181:#182     // append:(Ljava/lang/String;)Ljava/lang/StringBuilder;
  #138 = NameAndType        #108:#109     // getNodeNumber:(Ljava/lang/Object;)I
  #139 = NameAndType        #181:#183     // append:(I)Ljava/lang/StringBuilder;
  #140 = NameAndType        #184:#185     // toString:()Ljava/lang/String;
  #141 = NameAndType        #186:#187     // getText:(Ljava/lang/Object;)Ljava/lang/String;
  #142 = Utf8               parent
  #143 = NameAndType        #112:#113     // fixString:(Ljava/lang/String;)Ljava/lang/String;
  #144 = Utf8               edges
  #145 = NameAndType        #64:#63       // _nodeST:Lorg/antlr/stringtemplate/StringTemplate;
  #146 = Utf8               name
  #147 = NameAndType        #188:#189     // get:(Ljava/lang/Object;)Ljava/lang/Object;
  #148 = Utf8               java/lang/Integer
  #149 = NameAndType        #190:#191     // intValue:()I
  #150 = NameAndType        #192:#193     // valueOf:(I)Ljava/lang/Integer;
  #151 = NameAndType        #194:#195     // put:(Ljava/lang/Object;Ljava/lang/Object;)Ljava/lang/Object;
  #152 = Utf8               \"
  #153 = Utf8               \\\\\"
  #154 = Class              #196          // java/lang/String
  #155 = NameAndType        #197:#198     // replaceAll:(Ljava/lang/String;Ljava/lang/String;)Ljava/lang/String;
  #156 = Utf8               \\t
  #157 = Utf8
  #158 = Utf8               \\n
  #159 = Utf8               \\\\n
  #160 = Utf8               \\r
  #161 = Utf8               \\\\r
  #162 = NameAndType        #199:#191     // length:()I
  #163 = NameAndType        #200:#201     // substring:(II)Ljava/lang/String;
  #164 = Utf8               ...
  #165 = NameAndType        #200:#202     // substring:(I)Ljava/lang/String;
  #166 = Utf8               org/antlr/stringtemplate/StringTemplate
  #167 = Utf8               digraph {\n\n\tordering=out;\n\tranksep=.4;\n\tbgcolor=\"lightgrey\"; node [shape=box, fixedsize=false, fontsize=12, fontname=\"Helvetica-bold\", fontcolor=\"blue\"\n\t\twidth=.25, height=.25, color=\"black\", fillcolor=\"white\", style=\"filled, solid, bold\"];\n\tedge [arrowsize=.5, color=\"black\", style=\"bold\"]\n\n  $nodes$\n  $edges$\n}\n
  #168 = NameAndType        #72:#203      // "<init>":(Ljava/lang/String;)V
  #169 = Utf8               $name$ [label=\"$text$\"];\n
  #170 = Utf8               $parent$ -> $child$ // \"$parentText$\" -> \"$childText$\"\n
  #171 = Utf8               org/antlr/runtime/tree/DOTTreeGenerator
  #172 = Utf8               java/lang/Object
  #173 = Utf8               getInstanceOf
  #174 = Utf8               ()Lorg/antlr/stringtemplate/StringTemplate;
  #175 = Utf8               org/antlr/runtime/tree/TreeAdaptor
  #176 = Utf8               getChildCount
  #177 = Utf8               setAttribute
  #178 = Utf8               (Ljava/lang/String;Ljava/lang/Object;)V
  #179 = Utf8               getChild
  #180 = Utf8               (Ljava/lang/Object;I)Ljava/lang/Object;
  #181 = Utf8               append
  #182 = Utf8               (Ljava/lang/String;)Ljava/lang/StringBuilder;
  #183 = Utf8               (I)Ljava/lang/StringBuilder;
  #184 = Utf8               toString
  #185 = Utf8               ()Ljava/lang/String;
  #186 = Utf8               getText
  #187 = Utf8               (Ljava/lang/Object;)Ljava/lang/String;
  #188 = Utf8               get
  #189 = Utf8               (Ljava/lang/Object;)Ljava/lang/Object;
  #190 = Utf8               intValue
  #191 = Utf8               ()I
  #192 = Utf8               valueOf
  #193 = Utf8               (I)Ljava/lang/Integer;
  #194 = Utf8               put
  #195 = Utf8               (Ljava/lang/Object;Ljava/lang/Object;)Ljava/lang/Object;
  #196 = Utf8               java/lang/String
  #197 = Utf8               replaceAll
  #198 = Utf8               (Ljava/lang/String;Ljava/lang/String;)Ljava/lang/String;
  #199 = Utf8               length
  #200 = Utf8               substring
  #201 = Utf8               (II)Ljava/lang/String;
  #202 = Utf8               (I)Ljava/lang/String;
  #203 = Utf8               (Ljava/lang/String;)V
{
  public static org.antlr.stringtemplate.StringTemplate _treeST;
    descriptor: Lorg/antlr/stringtemplate/StringTemplate;
    flags: (0x0009) ACC_PUBLIC, ACC_STATIC

  public static org.antlr.stringtemplate.StringTemplate _nodeST;
    descriptor: Lorg/antlr/stringtemplate/StringTemplate;
    flags: (0x0009) ACC_PUBLIC, ACC_STATIC

  public static org.antlr.stringtemplate.StringTemplate _edgeST;
    descriptor: Lorg/antlr/stringtemplate/StringTemplate;
    flags: (0x0009) ACC_PUBLIC, ACC_STATIC

  java.util.HashMap<java.lang.Object, java.lang.Integer> nodeToNumberMap;
    descriptor: Ljava/util/HashMap;
    flags: (0x0000)
    Signature: #69                          // Ljava/util/HashMap<Ljava/lang/Object;Ljava/lang/Integer;>;

  int nodeNumber;
    descriptor: I
    flags: (0x0000)

  public org.antlr.runtime.tree.DOTTreeGenerator();
    descriptor: ()V
    flags: (0x0001) ACC_PUBLIC
    Code:
      stack=3, locals=1, args_size=1
         0: aload_0
         1: invokespecial #1                  // Method java/lang/Object."<init>":()V
         4: aload_0
         5: new           #2                  // class java/util/HashMap
         8: dup
         9: invokespecial #3                  // Method java/util/HashMap."<init>":()V
        12: putfield      #4                  // Field nodeToNumberMap:Ljava/util/HashMap;
        15: aload_0
        16: iconst_0
        17: putfield      #5                  // Field nodeNumber:I
        20: return
      LineNumberTable:
        line 53: 0
        line 74: 4
        line 77: 15
      LocalVariableTable:
        Start  Length  Slot  Name   Signature
            0      21     0  this   Lorg/antlr/runtime/tree/DOTTreeGenerator;

  public org.antlr.stringtemplate.StringTemplate toDOT(java.lang.Object, org.antlr.runtime.tree.TreeAdaptor, org.antlr.stringtemplate.StringTemplate, org.antlr.stringtemplate.StringTemplate);
    descriptor: (Ljava/lang/Object;Lorg/antlr/runtime/tree/TreeAdaptor;Lorg/antlr/stringtemplate/StringTemplate;Lorg/antlr/stringtemplate/StringTemplate;)Lorg/antlr/stringtemplate/StringTemplate;
    flags: (0x0001) ACC_PUBLIC
    Code:
      stack=4, locals=6, args_size=5
         0: aload_3
         1: invokevirtual #6                  // Method org/antlr/stringtemplate/StringTemplate.getInstanceOf:()Lorg/antlr/stringtemplate/StringTemplate;
         4: astore        5
         6: aload_0
         7: iconst_0
         8: putfield      #5                  // Field nodeNumber:I
        11: aload_0
        12: aload_1
        13: aload_2
        14: aload         5
        16: invokevirtual #7                  // Method toDOTDefineNodes:(Ljava/lang/Object;Lorg/antlr/runtime/tree/TreeAdaptor;Lorg/antlr/stringtemplate/StringTemplate;)V
        19: aload_0
        20: iconst_0
        21: putfield      #5                  // Field nodeNumber:I
        24: aload_0
        25: aload_1
        26: aload_2
        27: aload         5
        29: invokevirtual #8                  // Method toDOTDefineEdges:(Ljava/lang/Object;Lorg/antlr/runtime/tree/TreeAdaptor;Lorg/antlr/stringtemplate/StringTemplate;)V
        32: aload         5
        34: areturn
      LineNumberTable:
        line 84: 0
        line 85: 6
        line 86: 11
        line 87: 19
        line 88: 24
        line 95: 32
      LocalVariableTable:
        Start  Length  Slot  Name   Signature
            0      35     0  this   Lorg/antlr/runtime/tree/DOTTreeGenerator;
            0      35     1  tree   Ljava/lang/Object;
            0      35     2 adaptor   Lorg/antlr/runtime/tree/TreeAdaptor;
            0      35     3 _treeST   Lorg/antlr/stringtemplate/StringTemplate;
            0      35     4 _edgeST   Lorg/antlr/stringtemplate/StringTemplate;
            6      29     5 treeST   Lorg/antlr/stringtemplate/StringTemplate;

  public org.antlr.stringtemplate.StringTemplate toDOT(java.lang.Object, org.antlr.runtime.tree.TreeAdaptor);
    descriptor: (Ljava/lang/Object;Lorg/antlr/runtime/tree/TreeAdaptor;)Lorg/antlr/stringtemplate/StringTemplate;
    flags: (0x0001) ACC_PUBLIC
    Code:
      stack=5, locals=3, args_size=3
         0: aload_0
         1: aload_1
         2: aload_2
         3: getstatic     #9                  // Field _treeST:Lorg/antlr/stringtemplate/StringTemplate;
         6: getstatic     #10                 // Field _edgeST:Lorg/antlr/stringtemplate/StringTemplate;
         9: invokevirtual #11                 // Method toDOT:(Ljava/lang/Object;Lorg/antlr/runtime/tree/TreeAdaptor;Lorg/antlr/stringtemplate/StringTemplate;Lorg/antlr/stringtemplate/StringTemplate;)Lorg/antlr/stringtemplate/StringTemplate;
        12: areturn
      LineNumberTable:
        line 101: 0
      LocalVariableTable:
        Start  Length  Slot  Name   Signature
            0      13     0  this   Lorg/antlr/runtime/tree/DOTTreeGenerator;
            0      13     1  tree   Ljava/lang/Object;
            0      13     2 adaptor   Lorg/antlr/runtime/tree/TreeAdaptor;

  public org.antlr.stringtemplate.StringTemplate toDOT(org.antlr.runtime.tree.Tree);
    descriptor: (Lorg/antlr/runtime/tree/Tree;)Lorg/antlr/stringtemplate/StringTemplate;
    flags: (0x0001) ACC_PUBLIC
    Code:
      stack=4, locals=2, args_size=2
         0: aload_0
         1: aload_1
         2: new           #12                 // class org/antlr/runtime/tree/CommonTreeAdaptor
         5: dup
         6: invokespecial #13                 // Method org/antlr/runtime/tree/CommonTreeAdaptor."<init>":()V
         9: invokevirtual #14                 // Method toDOT:(Ljava/lang/Object;Lorg/antlr/runtime/tree/TreeAdaptor;)Lorg/antlr/stringtemplate/StringTemplate;
        12: areturn
      LineNumberTable:
        line 122: 0
      LocalVariableTable:
        Start  Length  Slot  Name   Signature
            0      13     0  this   Lorg/antlr/runtime/tree/DOTTreeGenerator;
            0      13     1  tree   Lorg/antlr/runtime/tree/Tree;

  protected void toDOTDefineNodes(java.lang.Object, org.antlr.runtime.tree.TreeAdaptor, org.antlr.stringtemplate.StringTemplate);
    descriptor: (Ljava/lang/Object;Lorg/antlr/runtime/tree/TreeAdaptor;Lorg/antlr/stringtemplate/StringTemplate;)V
    flags: (0x0004) ACC_PROTECTED
    Code:
      stack=4, locals=9, args_size=4
         0: aload_1
         1: ifnonnull     5
         4: return
         5: aload_2
         6: aload_1
         7: invokeinterface #15,  2           // InterfaceMethod org/antlr/runtime/tree/TreeAdaptor.getChildCount:(Ljava/lang/Object;)I
        12: istore        4
        14: iload         4
        16: ifne          20
        19: return
        20: aload_0
        21: aload_2
        22: aload_1
        23: invokevirtual #16                 // Method getNodeST:(Lorg/antlr/runtime/tree/TreeAdaptor;Ljava/lang/Object;)Lorg/antlr/stringtemplate/StringTemplate;
        26: astore        5
        28: aload_3
        29: ldc           #17                 // String nodes
        31: aload         5
        33: invokevirtual #18                 // Method org/antlr/stringtemplate/StringTemplate.setAttribute:(Ljava/lang/String;Ljava/lang/Object;)V
        36: iconst_0
        37: istore        6
        39: iload         6
        41: iload         4
        43: if_icmpge     88
        46: aload_2
        47: aload_1
        48: iload         6
        50: invokeinterface #19,  3           // InterfaceMethod org/antlr/runtime/tree/TreeAdaptor.getChild:(Ljava/lang/Object;I)Ljava/lang/Object;
        55: astore        7
        57: aload_0
        58: aload_2
        59: aload         7
        61: invokevirtual #16                 // Method getNodeST:(Lorg/antlr/runtime/tree/TreeAdaptor;Ljava/lang/Object;)Lorg/antlr/stringtemplate/StringTemplate;
        64: astore        8
        66: aload_3
        67: ldc           #17                 // String nodes
        69: aload         8
        71: invokevirtual #18                 // Method org/antlr/stringtemplate/StringTemplate.setAttribute:(Ljava/lang/String;Ljava/lang/Object;)V
        74: aload_0
        75: aload         7
        77: aload_2
        78: aload_3
        79: invokevirtual #7                  // Method toDOTDefineNodes:(Ljava/lang/Object;Lorg/antlr/runtime/tree/TreeAdaptor;Lorg/antlr/stringtemplate/StringTemplate;)V
        82: iinc          6, 1
        85: goto          39
        88: return
      LineNumberTable:
        line 129: 0
        line 130: 4
        line 132: 5
        line 133: 14
        line 136: 19
        line 140: 20
        line 141: 28
        line 144: 36
        line 145: 46
        line 146: 57
        line 147: 66
        line 148: 74
        line 144: 82
        line 150: 88
      LocalVariableTable:
        Start  Length  Slot  Name   Signature
           57      25     7 child   Ljava/lang/Object;
           66      16     8 nodeST   Lorg/antlr/stringtemplate/StringTemplate;
           39      49     6     i   I
            0      89     0  this   Lorg/antlr/runtime/tree/DOTTreeGenerator;
            0      89     1  tree   Ljava/lang/Object;
            0      89     2 adaptor   Lorg/antlr/runtime/tree/TreeAdaptor;
            0      89     3 treeST   Lorg/antlr/stringtemplate/StringTemplate;
           14      75     4     n   I
           28      61     5 parentNodeST   Lorg/antlr/stringtemplate/StringTemplate;

  protected void toDOTDefineEdges(java.lang.Object, org.antlr.runtime.tree.TreeAdaptor, org.antlr.stringtemplate.StringTemplate);
    descriptor: (Ljava/lang/Object;Lorg/antlr/runtime/tree/TreeAdaptor;Lorg/antlr/stringtemplate/StringTemplate;)V
    flags: (0x0004) ACC_PROTECTED
    Code:
      stack=4, locals=12, args_size=4
         0: aload_1
         1: ifnonnull     5
         4: return
         5: aload_2
         6: aload_1
         7: invokeinterface #15,  2           // InterfaceMethod org/antlr/runtime/tree/TreeAdaptor.getChildCount:(Ljava/lang/Object;)I
        12: istore        4
        14: iload         4
        16: ifne          20
        19: return
        20: new           #20                 // class java/lang/StringBuilder
        23: dup
        24: invokespecial #21                 // Method java/lang/StringBuilder."<init>":()V
        27: ldc           #22                 // String n
        29: invokevirtual #23                 // Method java/lang/StringBuilder.append:(Ljava/lang/String;)Ljava/lang/StringBuilder;
        32: aload_0
        33: aload_1
        34: invokevirtual #24                 // Method getNodeNumber:(Ljava/lang/Object;)I
        37: invokevirtual #25                 // Method java/lang/StringBuilder.append:(I)Ljava/lang/StringBuilder;
        40: invokevirtual #26                 // Method java/lang/StringBuilder.toString:()Ljava/lang/String;
        43: astore        5
        45: aload_2
        46: aload_1
        47: invokeinterface #27,  2           // InterfaceMethod org/antlr/runtime/tree/TreeAdaptor.getText:(Ljava/lang/Object;)Ljava/lang/String;
        52: astore        6
        54: iconst_0
        55: istore        7
        57: iload         7
        59: iload         4
        61: if_icmpge     185
        64: aload_2
        65: aload_1
        66: iload         7
        68: invokeinterface #19,  3           // InterfaceMethod org/antlr/runtime/tree/TreeAdaptor.getChild:(Ljava/lang/Object;I)Ljava/lang/Object;
        73: astore        8
        75: aload_2
        76: aload         8
        78: invokeinterface #27,  2           // InterfaceMethod org/antlr/runtime/tree/TreeAdaptor.getText:(Ljava/lang/Object;)Ljava/lang/String;
        83: astore        9
        85: new           #20                 // class java/lang/StringBuilder
        88: dup
        89: invokespecial #21                 // Method java/lang/StringBuilder."<init>":()V
        92: ldc           #22                 // String n
        94: invokevirtual #23                 // Method java/lang/StringBuilder.append:(Ljava/lang/String;)Ljava/lang/StringBuilder;
        97: aload_0
        98: aload         8
       100: invokevirtual #24                 // Method getNodeNumber:(Ljava/lang/Object;)I
       103: invokevirtual #25                 // Method java/lang/StringBuilder.append:(I)Ljava/lang/StringBuilder;
       106: invokevirtual #26                 // Method java/lang/StringBuilder.toString:()Ljava/lang/String;
       109: astore        10
       111: getstatic     #10                 // Field _edgeST:Lorg/antlr/stringtemplate/StringTemplate;
       114: invokevirtual #6                  // Method org/antlr/stringtemplate/StringTemplate.getInstanceOf:()Lorg/antlr/stringtemplate/StringTemplate;
       117: astore        11
       119: aload         11
       121: ldc           #28                 // String parent
       123: aload         5
       125: invokevirtual #18                 // Method org/antlr/stringtemplate/StringTemplate.setAttribute:(Ljava/lang/String;Ljava/lang/Object;)V
       128: aload         11
       130: ldc           #29                 // String child
       132: aload         10
       134: invokevirtual #18                 // Method org/antlr/stringtemplate/StringTemplate.setAttribute:(Ljava/lang/String;Ljava/lang/Object;)V
       137: aload         11
       139: ldc           #30                 // String parentText
       141: aload_0
       142: aload         6
       144: invokevirtual #31                 // Method fixString:(Ljava/lang/String;)Ljava/lang/String;
       147: invokevirtual #18                 // Method org/antlr/stringtemplate/StringTemplate.setAttribute:(Ljava/lang/String;Ljava/lang/Object;)V
       150: aload         11
       152: ldc           #32                 // String childText
       154: aload_0
       155: aload         9
       157: invokevirtual #31                 // Method fixString:(Ljava/lang/String;)Ljava/lang/String;
       160: invokevirtual #18                 // Method org/antlr/stringtemplate/StringTemplate.setAttribute:(Ljava/lang/String;Ljava/lang/Object;)V
       163: aload_3
       164: ldc           #33                 // String edges
       166: aload         11
       168: invokevirtual #18                 // Method org/antlr/stringtemplate/StringTemplate.setAttribute:(Ljava/lang/String;Ljava/lang/Object;)V
       171: aload_0
       172: aload         8
       174: aload_2
       175: aload_3
       176: invokevirtual #8                  // Method toDOTDefineEdges:(Ljava/lang/Object;Lorg/antlr/runtime/tree/TreeAdaptor;Lorg/antlr/stringtemplate/StringTemplate;)V
       179: iinc          7, 1
       182: goto          57
       185: return
      LineNumberTable:
        line 156: 0
        line 157: 4
        line 159: 5
        line 160: 14
        line 163: 19
        line 166: 20
        line 169: 45
        line 170: 54
        line 171: 64
        line 172: 75
        line 173: 85
        line 174: 111
        line 175: 119
        line 176: 128
        line 177: 137
        line 178: 150
        line 179: 163
        line 180: 171
        line 170: 179
        line 182: 185
      LocalVariableTable:
        Start  Length  Slot  Name   Signature
           75     104     8 child   Ljava/lang/Object;
           85      94     9 childText   Ljava/lang/String;
          111      68    10 childName   Ljava/lang/String;
          119      60    11 edgeST   Lorg/antlr/stringtemplate/StringTemplate;
           57     128     7     i   I
            0     186     0  this   Lorg/antlr/runtime/tree/DOTTreeGenerator;
            0     186     1  tree   Ljava/lang/Object;
            0     186     2 adaptor   Lorg/antlr/runtime/tree/TreeAdaptor;
            0     186     3 treeST   Lorg/antlr/stringtemplate/StringTemplate;
           14     172     4     n   I
           45     141     5 parentName   Ljava/lang/String;
           54     132     6 parentText   Ljava/lang/String;

  protected org.antlr.stringtemplate.StringTemplate getNodeST(org.antlr.runtime.tree.TreeAdaptor, java.lang.Object);
    descriptor: (Lorg/antlr/runtime/tree/TreeAdaptor;Ljava/lang/Object;)Lorg/antlr/stringtemplate/StringTemplate;
    flags: (0x0004) ACC_PROTECTED
    Code:
      stack=4, locals=6, args_size=3
         0: aload_1
         1: aload_2
         2: invokeinterface #27,  2           // InterfaceMethod org/antlr/runtime/tree/TreeAdaptor.getText:(Ljava/lang/Object;)Ljava/lang/String;
         7: astore_3
         8: getstatic     #34                 // Field _nodeST:Lorg/antlr/stringtemplate/StringTemplate;
        11: invokevirtual #6                  // Method org/antlr/stringtemplate/StringTemplate.getInstanceOf:()Lorg/antlr/stringtemplate/StringTemplate;
        14: astore        4
        16: new           #20                 // class java/lang/StringBuilder
        19: dup
        20: invokespecial #21                 // Method java/lang/StringBuilder."<init>":()V
        23: ldc           #22                 // String n
        25: invokevirtual #23                 // Method java/lang/StringBuilder.append:(Ljava/lang/String;)Ljava/lang/StringBuilder;
        28: aload_0
        29: aload_2
        30: invokevirtual #24                 // Method getNodeNumber:(Ljava/lang/Object;)I
        33: invokevirtual #25                 // Method java/lang/StringBuilder.append:(I)Ljava/lang/StringBuilder;
        36: invokevirtual #26                 // Method java/lang/StringBuilder.toString:()Ljava/lang/String;
        39: astore        5
        41: aload         4
        43: ldc           #35                 // String name
        45: aload         5
        47: invokevirtual #18                 // Method org/antlr/stringtemplate/StringTemplate.setAttribute:(Ljava/lang/String;Ljava/lang/Object;)V
        50: aload         4
        52: ldc           #36                 // String text
        54: aload_0
        55: aload_3
        56: invokevirtual #31                 // Method fixString:(Ljava/lang/String;)Ljava/lang/String;
        59: invokevirtual #18                 // Method org/antlr/stringtemplate/StringTemplate.setAttribute:(Ljava/lang/String;Ljava/lang/Object;)V
        62: aload         4
        64: areturn
      LineNumberTable:
        line 185: 0
        line 186: 8
        line 187: 16
        line 188: 41
        line 190: 50
        line 191: 62
      LocalVariableTable:
        Start  Length  Slot  Name   Signature
            0      65     0  this   Lorg/antlr/runtime/tree/DOTTreeGenerator;
            0      65     1 adaptor   Lorg/antlr/runtime/tree/TreeAdaptor;
            0      65     2     t   Ljava/lang/Object;
            8      57     3  text   Ljava/lang/String;
           16      49     4 nodeST   Lorg/antlr/stringtemplate/StringTemplate;
           41      24     5 uniqueName   Ljava/lang/String;

  protected int getNodeNumber(java.lang.Object);
    descriptor: (Ljava/lang/Object;)I
    flags: (0x0004) ACC_PROTECTED
    Code:
      stack=3, locals=3, args_size=2
         0: aload_0
         1: getfield      #4                  // Field nodeToNumberMap:Ljava/util/HashMap;
         4: aload_1
         5: invokevirtual #37                 // Method java/util/HashMap.get:(Ljava/lang/Object;)Ljava/lang/Object;
         8: checkcast     #38                 // class java/lang/Integer
        11: astore_2
        12: aload_2
        13: ifnull        21
        16: aload_2
        17: invokevirtual #39                 // Method java/lang/Integer.intValue:()I
        20: ireturn
        21: aload_0
        22: getfield      #4                  // Field nodeToNumberMap:Ljava/util/HashMap;
        25: aload_1
        26: aload_0
        27: getfield      #5                  // Field nodeNumber:I
        30: invokestatic  #40                 // Method java/lang/Integer.valueOf:(I)Ljava/lang/Integer;
        33: invokevirtual #41                 // Method java/util/HashMap.put:(Ljava/lang/Object;Ljava/lang/Object;)Ljava/lang/Object;
        36: pop
        37: aload_0
        38: dup
        39: getfield      #5                  // Field nodeNumber:I
        42: iconst_1
        43: iadd
        44: putfield      #5                  // Field nodeNumber:I
        47: aload_0
        48: getfield      #5                  // Field nodeNumber:I
        51: iconst_1
        52: isub
        53: ireturn
      LineNumberTable:
        line 195: 0
        line 196: 12
        line 197: 16
        line 200: 21
        line 201: 37
        line 202: 47
      LocalVariableTable:
        Start  Length  Slot  Name   Signature
            0      54     0  this   Lorg/antlr/runtime/tree/DOTTreeGenerator;
            0      54     1     t   Ljava/lang/Object;
           12      42     2    nI   Ljava/lang/Integer;

  protected java.lang.String fixString(java.lang.String);
    descriptor: (Ljava/lang/String;)Ljava/lang/String;
    flags: (0x0004) ACC_PROTECTED
    Code:
      stack=4, locals=3, args_size=2
         0: aload_1
         1: astore_2
         2: aload_2
         3: ifnull        91
         6: aload_2
         7: ldc           #42                 // String \"
         9: ldc           #43                 // String \\\\\"
        11: invokevirtual #44                 // Method java/lang/String.replaceAll:(Ljava/lang/String;Ljava/lang/String;)Ljava/lang/String;
        14: astore_2
        15: aload_2
        16: ldc           #45                 // String \\t
        18: ldc           #46                 // String
        20: invokevirtual #44                 // Method java/lang/String.replaceAll:(Ljava/lang/String;Ljava/lang/String;)Ljava/lang/String;
        23: astore_2
        24: aload_2
        25: ldc           #47                 // String \\n
        27: ldc           #48                 // String \\\\n
        29: invokevirtual #44                 // Method java/lang/String.replaceAll:(Ljava/lang/String;Ljava/lang/String;)Ljava/lang/String;
        32: astore_2
        33: aload_2
        34: ldc           #49                 // String \\r
        36: ldc           #50                 // String \\\\r
        38: invokevirtual #44                 // Method java/lang/String.replaceAll:(Ljava/lang/String;Ljava/lang/String;)Ljava/lang/String;
        41: astore_2
        42: aload_2
        43: invokevirtual #51                 // Method java/lang/String.length:()I
        46: bipush        20
        48: if_icmple     91
        51: new           #20                 // class java/lang/StringBuilder
        54: dup
        55: invokespecial #21                 // Method java/lang/StringBuilder."<init>":()V
        58: aload_2
        59: iconst_0
        60: bipush        8
        62: invokevirtual #52                 // Method java/lang/String.substring:(II)Ljava/lang/String;
        65: invokevirtual #23                 // Method java/lang/StringBuilder.append:(Ljava/lang/String;)Ljava/lang/StringBuilder;
        68: ldc           #53                 // String ...
        70: invokevirtual #23                 // Method java/lang/StringBuilder.append:(Ljava/lang/String;)Ljava/lang/StringBuilder;
        73: aload_2
        74: aload_2
        75: invokevirtual #51                 // Method java/lang/String.length:()I
        78: bipush        8
        80: isub
        81: invokevirtual #54                 // Method java/lang/String.substring:(I)Ljava/lang/String;
        84: invokevirtual #23                 // Method java/lang/StringBuilder.append:(Ljava/lang/String;)Ljava/lang/StringBuilder;
        87: invokevirtual #26                 // Method java/lang/StringBuilder.toString:()Ljava/lang/String;
        90: astore_2
        91: aload_2
        92: areturn
      LineNumberTable:
        line 208: 0
        line 210: 2
        line 212: 6
        line 213: 15
        line 214: 24
        line 215: 33
        line 216: 42
        line 217: 51
        line 222: 91
      LocalVariableTable:
        Start  Length  Slot  Name   Signature
            0      93     0  this   Lorg/antlr/runtime/tree/DOTTreeGenerator;
            0      93     1    in   Ljava/lang/String;
            2      91     2  text   Ljava/lang/String;

  static {};
    descriptor: ()V
    flags: (0x0008) ACC_STATIC
    Code:
      stack=3, locals=0, args_size=0
         0: new           #55                 // class org/antlr/stringtemplate/StringTemplate
         3: dup
         4: ldc           #56                 // String digraph {\n\n\tordering=out;\n\tranksep=.4;\n\tbgcolor=\"lightgrey\"; node [shape=box, fixedsize=false, fontsize=12, fontname=\"Helvetica-bold\", fontcolor=\"blue\"\n\t\twidth=.25, height=.25, color=\"black\", fillcolor=\"white\", style=\"filled, solid, bold\"];\n\tedge [arrowsize=.5, color=\"black\", style=\"bold\"]\n\n  $nodes$\n  $edges$\n}\n
         6: invokespecial #57                 // Method org/antlr/stringtemplate/StringTemplate."<init>":(Ljava/lang/String;)V
         9: putstatic     #9                  // Field _treeST:Lorg/antlr/stringtemplate/StringTemplate;
        12: new           #55                 // class org/antlr/stringtemplate/StringTemplate
        15: dup
        16: ldc           #58                 // String $name$ [label=\"$text$\"];\n
        18: invokespecial #57                 // Method org/antlr/stringtemplate/StringTemplate."<init>":(Ljava/lang/String;)V
        21: putstatic     #34                 // Field _nodeST:Lorg/antlr/stringtemplate/StringTemplate;
        24: new           #55                 // class org/antlr/stringtemplate/StringTemplate
        27: dup
        28: ldc           #59                 // String $parent$ -> $child$ // \"$parentText$\" -> \"$childText$\"\n
        30: invokespecial #57                 // Method org/antlr/stringtemplate/StringTemplate."<init>":(Ljava/lang/String;)V
        33: putstatic     #10                 // Field _edgeST:Lorg/antlr/stringtemplate/StringTemplate;
        36: return
      LineNumberTable:
        line 55: 0
        line 67: 12
        line 70: 24
}
SourceFile: "DOTTreeGenerator.java"
