Classfile /Users/mw/Projects/slang-braindump/.jar/jar11/assemble/slang-braindump/assemble/content/org/antlr/runtime/tree/RewriteCardinalityException.class
  Last modified May 29, 2022; size 583 bytes
  SHA-256 checksum 9cc37972778b2ac35bae8a928eedb0fe93d72a43783272a2ab114717d11b2c62
  Compiled from "RewriteCardinalityException.java"
public class org.antlr.runtime.tree.RewriteCardinalityException extends java.lang.RuntimeException
  minor version: 0
  major version: 49
  flags: (0x0021) ACC_PUBLIC, ACC_SUPER
  this_class: #3                          // org/antlr/runtime/tree/RewriteCardinalityException
  super_class: #4                         // java/lang/RuntimeException
  interfaces: 0, fields: 1, methods: 2, attributes: 1
Constant pool:
   #1 = Methodref          #4.#18         // java/lang/RuntimeException."<init>":()V
   #2 = Fieldref           #3.#19         // org/antlr/runtime/tree/RewriteCardinalityException.elementDescription:Ljava/lang/String;
   #3 = Class              #20            // org/antlr/runtime/tree/RewriteCardinalityException
   #4 = Class              #21            // java/lang/RuntimeException
   #5 = Utf8               elementDescription
   #6 = Utf8               Ljava/lang/String;
   #7 = Utf8               <init>
   #8 = Utf8               (Ljava/lang/String;)V
   #9 = Utf8               Code
  #10 = Utf8               LineNumberTable
  #11 = Utf8               LocalVariableTable
  #12 = Utf8               this
  #13 = Utf8               Lorg/antlr/runtime/tree/RewriteCardinalityException;
  #14 = Utf8               getMessage
  #15 = Utf8               ()Ljava/lang/String;
  #16 = Utf8               SourceFile
  #17 = Utf8               RewriteCardinalityException.java
  #18 = NameAndType        #7:#22         // "<init>":()V
  #19 = NameAndType        #5:#6          // elementDescription:Ljava/lang/String;
  #20 = Utf8               org/antlr/runtime/tree/RewriteCardinalityException
  #21 = Utf8               java/lang/RuntimeException
  #22 = Utf8               ()V
{
  public java.lang.String elementDescription;
    descriptor: Ljava/lang/String;
    flags: (0x0001) ACC_PUBLIC

  public org.antlr.runtime.tree.RewriteCardinalityException(java.lang.String);
    descriptor: (Ljava/lang/String;)V
    flags: (0x0001) ACC_PUBLIC
    Code:
      stack=2, locals=2, args_size=2
         0: aload_0
         1: invokespecial #1                  // Method java/lang/RuntimeException."<init>":()V
         4: aload_0
         5: aload_1
         6: putfield      #2                  // Field elementDescription:Ljava/lang/String;
         9: return
      LineNumberTable:
        line 37: 0
        line 38: 4
        line 39: 9
      LocalVariableTable:
        Start  Length  Slot  Name   Signature
            0      10     0  this   Lorg/antlr/runtime/tree/RewriteCardinalityException;
            0      10     1 elementDescription   Ljava/lang/String;

  public java.lang.String getMessage();
    descriptor: ()Ljava/lang/String;
    flags: (0x0001) ACC_PUBLIC
    Code:
      stack=1, locals=1, args_size=1
         0: aload_0
         1: getfield      #2                  // Field elementDescription:Ljava/lang/String;
         4: ifnull        12
         7: aload_0
         8: getfield      #2                  // Field elementDescription:Ljava/lang/String;
        11: areturn
        12: aconst_null
        13: areturn
      LineNumberTable:
        line 43: 0
        line 44: 7
        line 46: 12
      LocalVariableTable:
        Start  Length  Slot  Name   Signature
            0      14     0  this   Lorg/antlr/runtime/tree/RewriteCardinalityException;
}
SourceFile: "RewriteCardinalityException.java"
