Classfile /Users/mw/Projects/slang-braindump/.jar/jar11/assemble/slang-braindump/assemble/content/org/antlr/runtime/tree/RewriteEarlyExitException.class
  Last modified May 29, 2022; size 527 bytes
  SHA-256 checksum c2eda9e41c890d116110d7d119de610bbbe06082e244834c58a23043ff6de7a5
  Compiled from "RewriteEarlyExitException.java"
public class org.antlr.runtime.tree.RewriteEarlyExitException extends org.antlr.runtime.tree.RewriteCardinalityException
  minor version: 0
  major version: 49
  flags: (0x0021) ACC_PUBLIC, ACC_SUPER
  this_class: #2                          // org/antlr/runtime/tree/RewriteEarlyExitException
  super_class: #3                         // org/antlr/runtime/tree/RewriteCardinalityException
  interfaces: 0, fields: 0, methods: 2, attributes: 1
Constant pool:
   #1 = Methodref          #3.#16         // org/antlr/runtime/tree/RewriteCardinalityException."<init>":(Ljava/lang/String;)V
   #2 = Class              #17            // org/antlr/runtime/tree/RewriteEarlyExitException
   #3 = Class              #18            // org/antlr/runtime/tree/RewriteCardinalityException
   #4 = Utf8               <init>
   #5 = Utf8               ()V
   #6 = Utf8               Code
   #7 = Utf8               LineNumberTable
   #8 = Utf8               LocalVariableTable
   #9 = Utf8               this
  #10 = Utf8               Lorg/antlr/runtime/tree/RewriteEarlyExitException;
  #11 = Utf8               (Ljava/lang/String;)V
  #12 = Utf8               elementDescription
  #13 = Utf8               Ljava/lang/String;
  #14 = Utf8               SourceFile
  #15 = Utf8               RewriteEarlyExitException.java
  #16 = NameAndType        #4:#11         // "<init>":(Ljava/lang/String;)V
  #17 = Utf8               org/antlr/runtime/tree/RewriteEarlyExitException
  #18 = Utf8               org/antlr/runtime/tree/RewriteCardinalityException
{
  public org.antlr.runtime.tree.RewriteEarlyExitException();
    descriptor: ()V
    flags: (0x0001) ACC_PUBLIC
    Code:
      stack=2, locals=1, args_size=1
         0: aload_0
         1: aconst_null
         2: invokespecial #1                  // Method org/antlr/runtime/tree/RewriteCardinalityException."<init>":(Ljava/lang/String;)V
         5: return
      LineNumberTable:
        line 33: 0
        line 34: 5
      LocalVariableTable:
        Start  Length  Slot  Name   Signature
            0       6     0  this   Lorg/antlr/runtime/tree/RewriteEarlyExitException;

  public org.antlr.runtime.tree.RewriteEarlyExitException(java.lang.String);
    descriptor: (Ljava/lang/String;)V
    flags: (0x0001) ACC_PUBLIC
    Code:
      stack=2, locals=2, args_size=2
         0: aload_0
         1: aload_1
         2: invokespecial #1                  // Method org/antlr/runtime/tree/RewriteCardinalityException."<init>":(Ljava/lang/String;)V
         5: return
      LineNumberTable:
        line 36: 0
        line 37: 5
      LocalVariableTable:
        Start  Length  Slot  Name   Signature
            0       6     0  this   Lorg/antlr/runtime/tree/RewriteEarlyExitException;
            0       6     1 elementDescription   Ljava/lang/String;
}
SourceFile: "RewriteEarlyExitException.java"
