Classfile /Users/mw/Projects/slang-braindump/.jar/jar11/assemble/slang-braindump/assemble/content/org/antlr/runtime/tree/TreeWizard$TreePatternTreeAdaptor.class
  Last modified May 29, 2022; size 750 bytes
  SHA-256 checksum 023d28496ee07e0da02e9309f3634275010f6c11f43aa4021d1e21ce0bc6071c
  Compiled from "TreeWizard.java"
public class org.antlr.runtime.tree.TreeWizard$TreePatternTreeAdaptor extends org.antlr.runtime.tree.CommonTreeAdaptor
  minor version: 0
  major version: 49
  flags: (0x0021) ACC_PUBLIC, ACC_SUPER
  this_class: #4                          // org/antlr/runtime/tree/TreeWizard$TreePatternTreeAdaptor
  super_class: #5                         // org/antlr/runtime/tree/CommonTreeAdaptor
  interfaces: 0, fields: 0, methods: 2, attributes: 2
Constant pool:
   #1 = Methodref          #5.#21         // org/antlr/runtime/tree/CommonTreeAdaptor."<init>":()V
   #2 = Class              #23            // org/antlr/runtime/tree/TreeWizard$TreePattern
   #3 = Methodref          #2.#25         // org/antlr/runtime/tree/TreeWizard$TreePattern."<init>":(Lorg/antlr/runtime/Token;)V
   #4 = Class              #26            // org/antlr/runtime/tree/TreeWizard$TreePatternTreeAdaptor
   #5 = Class              #27            // org/antlr/runtime/tree/CommonTreeAdaptor
   #6 = Utf8               <init>
   #7 = Utf8               ()V
   #8 = Utf8               Code
   #9 = Utf8               LineNumberTable
  #10 = Utf8               LocalVariableTable
  #11 = Utf8               this
  #12 = Utf8               TreePatternTreeAdaptor
  #13 = Utf8               InnerClasses
  #14 = Utf8               Lorg/antlr/runtime/tree/TreeWizard$TreePatternTreeAdaptor;
  #15 = Utf8               create
  #16 = Utf8               (Lorg/antlr/runtime/Token;)Ljava/lang/Object;
  #17 = Utf8               payload
  #18 = Utf8               Lorg/antlr/runtime/Token;
  #19 = Utf8               SourceFile
  #20 = Utf8               TreeWizard.java
  #21 = NameAndType        #6:#7          // "<init>":()V
  #22 = Class              #28            // org/antlr/runtime/tree/TreeWizard
  #23 = Utf8               org/antlr/runtime/tree/TreeWizard$TreePattern
  #24 = Utf8               TreePattern
  #25 = NameAndType        #6:#29         // "<init>":(Lorg/antlr/runtime/Token;)V
  #26 = Utf8               org/antlr/runtime/tree/TreeWizard$TreePatternTreeAdaptor
  #27 = Utf8               org/antlr/runtime/tree/CommonTreeAdaptor
  #28 = Utf8               org/antlr/runtime/tree/TreeWizard
  #29 = Utf8               (Lorg/antlr/runtime/Token;)V
{
  public org.antlr.runtime.tree.TreeWizard$TreePatternTreeAdaptor();
    descriptor: ()V
    flags: (0x0001) ACC_PUBLIC
    Code:
      stack=1, locals=1, args_size=1
         0: aload_0
         1: invokespecial #1                  // Method org/antlr/runtime/tree/CommonTreeAdaptor."<init>":()V
         4: return
      LineNumberTable:
        line 97: 0
      LocalVariableTable:
        Start  Length  Slot  Name   Signature
            0       5     0  this   Lorg/antlr/runtime/tree/TreeWizard$TreePatternTreeAdaptor;

  public java.lang.Object create(org.antlr.runtime.Token);
    descriptor: (Lorg/antlr/runtime/Token;)Ljava/lang/Object;
    flags: (0x0001) ACC_PUBLIC
    Code:
      stack=3, locals=2, args_size=2
         0: new           #2                  // class org/antlr/runtime/tree/TreeWizard$TreePattern
         3: dup
         4: aload_1
         5: invokespecial #3                  // Method org/antlr/runtime/tree/TreeWizard$TreePattern."<init>":(Lorg/antlr/runtime/Token;)V
         8: areturn
      LineNumberTable:
        line 100: 0
      LocalVariableTable:
        Start  Length  Slot  Name   Signature
            0       9     0  this   Lorg/antlr/runtime/tree/TreeWizard$TreePatternTreeAdaptor;
            0       9     1 payload   Lorg/antlr/runtime/Token;
}
SourceFile: "TreeWizard.java"
InnerClasses:
  public static #12= #4 of #22;           // TreePatternTreeAdaptor=class org/antlr/runtime/tree/TreeWizard$TreePatternTreeAdaptor of class org/antlr/runtime/tree/TreeWizard
  public static #24= #2 of #22;           // TreePattern=class org/antlr/runtime/tree/TreeWizard$TreePattern of class org/antlr/runtime/tree/TreeWizard
