Classfile /Users/mw/Projects/slang-braindump/.jar/jar11/assemble/slang-braindump/assemble/content/org/antlr/runtime/tree/TreeVisitor.class
  Last modified May 29, 2022; size 1473 bytes
  SHA-256 checksum e57ec207805407e5c168adf7cff8b8589812af4e997f61263ba0a84fc06a8f5f
  Compiled from "TreeVisitor.java"
public class org.antlr.runtime.tree.TreeVisitor
  minor version: 0
  major version: 49
  flags: (0x0021) ACC_PUBLIC, ACC_SUPER
  this_class: #13                         // org/antlr/runtime/tree/TreeVisitor
  super_class: #14                        // java/lang/Object
  interfaces: 0, fields: 1, methods: 3, attributes: 1
Constant pool:
   #1 = Methodref          #14.#40        // java/lang/Object."<init>":()V
   #2 = Fieldref           #13.#41        // org/antlr/runtime/tree/TreeVisitor.adaptor:Lorg/antlr/runtime/tree/TreeAdaptor;
   #3 = Class              #42            // org/antlr/runtime/tree/CommonTreeAdaptor
   #4 = Methodref          #3.#40         // org/antlr/runtime/tree/CommonTreeAdaptor."<init>":()V
   #5 = Methodref          #13.#43        // org/antlr/runtime/tree/TreeVisitor."<init>":(Lorg/antlr/runtime/tree/TreeAdaptor;)V
   #6 = InterfaceMethodref #44.#45        // org/antlr/runtime/tree/TreeAdaptor.isNil:(Ljava/lang/Object;)Z
   #7 = InterfaceMethodref #46.#47        // org/antlr/runtime/tree/TreeVisitorAction.pre:(Ljava/lang/Object;)Ljava/lang/Object;
   #8 = InterfaceMethodref #44.#48        // org/antlr/runtime/tree/TreeAdaptor.getChildCount:(Ljava/lang/Object;)I
   #9 = InterfaceMethodref #44.#49        // org/antlr/runtime/tree/TreeAdaptor.getChild:(Ljava/lang/Object;I)Ljava/lang/Object;
  #10 = Methodref          #13.#50        // org/antlr/runtime/tree/TreeVisitor.visit:(Ljava/lang/Object;Lorg/antlr/runtime/tree/TreeVisitorAction;)Ljava/lang/Object;
  #11 = InterfaceMethodref #44.#51        // org/antlr/runtime/tree/TreeAdaptor.setChild:(Ljava/lang/Object;ILjava/lang/Object;)V
  #12 = InterfaceMethodref #46.#52        // org/antlr/runtime/tree/TreeVisitorAction.post:(Ljava/lang/Object;)Ljava/lang/Object;
  #13 = Class              #53            // org/antlr/runtime/tree/TreeVisitor
  #14 = Class              #54            // java/lang/Object
  #15 = Utf8               adaptor
  #16 = Utf8               Lorg/antlr/runtime/tree/TreeAdaptor;
  #17 = Utf8               <init>
  #18 = Utf8               (Lorg/antlr/runtime/tree/TreeAdaptor;)V
  #19 = Utf8               Code
  #20 = Utf8               LineNumberTable
  #21 = Utf8               LocalVariableTable
  #22 = Utf8               this
  #23 = Utf8               Lorg/antlr/runtime/tree/TreeVisitor;
  #24 = Utf8               ()V
  #25 = Utf8               visit
  #26 = Utf8               (Ljava/lang/Object;Lorg/antlr/runtime/tree/TreeVisitorAction;)Ljava/lang/Object;
  #27 = Utf8               child
  #28 = Utf8               Ljava/lang/Object;
  #29 = Utf8               visitResult
  #30 = Utf8               childAfterVisit
  #31 = Utf8               i
  #32 = Utf8               I
  #33 = Utf8               t
  #34 = Utf8               action
  #35 = Utf8               Lorg/antlr/runtime/tree/TreeVisitorAction;
  #36 = Utf8               isNil
  #37 = Utf8               Z
  #38 = Utf8               SourceFile
  #39 = Utf8               TreeVisitor.java
  #40 = NameAndType        #17:#24        // "<init>":()V
  #41 = NameAndType        #15:#16        // adaptor:Lorg/antlr/runtime/tree/TreeAdaptor;
  #42 = Utf8               org/antlr/runtime/tree/CommonTreeAdaptor
  #43 = NameAndType        #17:#18        // "<init>":(Lorg/antlr/runtime/tree/TreeAdaptor;)V
  #44 = Class              #55            // org/antlr/runtime/tree/TreeAdaptor
  #45 = NameAndType        #36:#56        // isNil:(Ljava/lang/Object;)Z
  #46 = Class              #57            // org/antlr/runtime/tree/TreeVisitorAction
  #47 = NameAndType        #58:#59        // pre:(Ljava/lang/Object;)Ljava/lang/Object;
  #48 = NameAndType        #60:#61        // getChildCount:(Ljava/lang/Object;)I
  #49 = NameAndType        #62:#63        // getChild:(Ljava/lang/Object;I)Ljava/lang/Object;
  #50 = NameAndType        #25:#26        // visit:(Ljava/lang/Object;Lorg/antlr/runtime/tree/TreeVisitorAction;)Ljava/lang/Object;
  #51 = NameAndType        #64:#65        // setChild:(Ljava/lang/Object;ILjava/lang/Object;)V
  #52 = NameAndType        #66:#59        // post:(Ljava/lang/Object;)Ljava/lang/Object;
  #53 = Utf8               org/antlr/runtime/tree/TreeVisitor
  #54 = Utf8               java/lang/Object
  #55 = Utf8               org/antlr/runtime/tree/TreeAdaptor
  #56 = Utf8               (Ljava/lang/Object;)Z
  #57 = Utf8               org/antlr/runtime/tree/TreeVisitorAction
  #58 = Utf8               pre
  #59 = Utf8               (Ljava/lang/Object;)Ljava/lang/Object;
  #60 = Utf8               getChildCount
  #61 = Utf8               (Ljava/lang/Object;)I
  #62 = Utf8               getChild
  #63 = Utf8               (Ljava/lang/Object;I)Ljava/lang/Object;
  #64 = Utf8               setChild
  #65 = Utf8               (Ljava/lang/Object;ILjava/lang/Object;)V
  #66 = Utf8               post
{
  protected org.antlr.runtime.tree.TreeAdaptor adaptor;
    descriptor: Lorg/antlr/runtime/tree/TreeAdaptor;
    flags: (0x0004) ACC_PROTECTED

  public org.antlr.runtime.tree.TreeVisitor(org.antlr.runtime.tree.TreeAdaptor);
    descriptor: (Lorg/antlr/runtime/tree/TreeAdaptor;)V
    flags: (0x0001) ACC_PUBLIC
    Code:
      stack=2, locals=2, args_size=2
         0: aload_0
         1: invokespecial #1                  // Method java/lang/Object."<init>":()V
         4: aload_0
         5: aload_1
         6: putfield      #2                  // Field adaptor:Lorg/antlr/runtime/tree/TreeAdaptor;
         9: return
      LineNumberTable:
        line 37: 0
        line 38: 4
        line 39: 9
      LocalVariableTable:
        Start  Length  Slot  Name   Signature
            0      10     0  this   Lorg/antlr/runtime/tree/TreeVisitor;
            0      10     1 adaptor   Lorg/antlr/runtime/tree/TreeAdaptor;

  public org.antlr.runtime.tree.TreeVisitor();
    descriptor: ()V
    flags: (0x0001) ACC_PUBLIC
    Code:
      stack=3, locals=1, args_size=1
         0: aload_0
         1: new           #3                  // class org/antlr/runtime/tree/CommonTreeAdaptor
         4: dup
         5: invokespecial #4                  // Method org/antlr/runtime/tree/CommonTreeAdaptor."<init>":()V
         8: invokespecial #5                  // Method "<init>":(Lorg/antlr/runtime/tree/TreeAdaptor;)V
        11: return
      LineNumberTable:
        line 40: 0
      LocalVariableTable:
        Start  Length  Slot  Name   Signature
            0      12     0  this   Lorg/antlr/runtime/tree/TreeVisitor;

  public java.lang.Object visit(java.lang.Object, org.antlr.runtime.tree.TreeVisitorAction);
    descriptor: (Ljava/lang/Object;Lorg/antlr/runtime/tree/TreeVisitorAction;)Ljava/lang/Object;
    flags: (0x0001) ACC_PUBLIC
    Code:
      stack=4, locals=8, args_size=3
         0: aload_0
         1: getfield      #2                  // Field adaptor:Lorg/antlr/runtime/tree/TreeAdaptor;
         4: aload_1
         5: invokeinterface #6,  2            // InterfaceMethod org/antlr/runtime/tree/TreeAdaptor.isNil:(Ljava/lang/Object;)Z
        10: istore_3
        11: aload_2
        12: ifnull        27
        15: iload_3
        16: ifne          27
        19: aload_2
        20: aload_1
        21: invokeinterface #7,  2            // InterfaceMethod org/antlr/runtime/tree/TreeVisitorAction.pre:(Ljava/lang/Object;)Ljava/lang/Object;
        26: astore_1
        27: iconst_0
        28: istore        4
        30: iload         4
        32: aload_0
        33: getfield      #2                  // Field adaptor:Lorg/antlr/runtime/tree/TreeAdaptor;
        36: aload_1
        37: invokeinterface #8,  2            // InterfaceMethod org/antlr/runtime/tree/TreeAdaptor.getChildCount:(Ljava/lang/Object;)I
        42: if_icmpge     109
        45: aload_0
        46: getfield      #2                  // Field adaptor:Lorg/antlr/runtime/tree/TreeAdaptor;
        49: aload_1
        50: iload         4
        52: invokeinterface #9,  3            // InterfaceMethod org/antlr/runtime/tree/TreeAdaptor.getChild:(Ljava/lang/Object;I)Ljava/lang/Object;
        57: astore        5
        59: aload_0
        60: aload         5
        62: aload_2
        63: invokevirtual #10                 // Method visit:(Ljava/lang/Object;Lorg/antlr/runtime/tree/TreeVisitorAction;)Ljava/lang/Object;
        66: astore        6
        68: aload_0
        69: getfield      #2                  // Field adaptor:Lorg/antlr/runtime/tree/TreeAdaptor;
        72: aload_1
        73: iload         4
        75: invokeinterface #9,  3            // InterfaceMethod org/antlr/runtime/tree/TreeAdaptor.getChild:(Ljava/lang/Object;I)Ljava/lang/Object;
        80: astore        7
        82: aload         6
        84: aload         7
        86: if_acmpeq     103
        89: aload_0
        90: getfield      #2                  // Field adaptor:Lorg/antlr/runtime/tree/TreeAdaptor;
        93: aload_1
        94: iload         4
        96: aload         6
        98: invokeinterface #11,  4           // InterfaceMethod org/antlr/runtime/tree/TreeAdaptor.setChild:(Ljava/lang/Object;ILjava/lang/Object;)V
       103: iinc          4, 1
       106: goto          30
       109: aload_2
       110: ifnull        125
       113: iload_3
       114: ifne          125
       117: aload_2
       118: aload_1
       119: invokeinterface #12,  2           // InterfaceMethod org/antlr/runtime/tree/TreeVisitorAction.post:(Ljava/lang/Object;)Ljava/lang/Object;
       124: astore_1
       125: aload_1
       126: areturn
      LineNumberTable:
        line 54: 0
        line 55: 11
        line 56: 19
        line 58: 27
        line 59: 45
        line 60: 59
        line 61: 68
        line 62: 82
        line 63: 89
        line 58: 103
        line 66: 109
        line 67: 125
      LocalVariableTable:
        Start  Length  Slot  Name   Signature
           59      44     5 child   Ljava/lang/Object;
           68      35     6 visitResult   Ljava/lang/Object;
           82      21     7 childAfterVisit   Ljava/lang/Object;
           30      79     4     i   I
            0     127     0  this   Lorg/antlr/runtime/tree/TreeVisitor;
            0     127     1     t   Ljava/lang/Object;
            0     127     2 action   Lorg/antlr/runtime/tree/TreeVisitorAction;
           11     116     3 isNil   Z
}
SourceFile: "TreeVisitor.java"
