Classfile /Users/mw/Projects/slang-braindump/.jar/jar11/assemble/slang-braindump/assemble/content/org/antlr/runtime/tree/TreeRuleReturnScope.class
  Last modified May 29, 2022; size 487 bytes
  SHA-256 checksum da251020891934a827577503089e580fcbb1c61039464ec639dabe917c4e5e0c
  Compiled from "TreeRuleReturnScope.java"
public class org.antlr.runtime.tree.TreeRuleReturnScope extends org.antlr.runtime.RuleReturnScope
  minor version: 0
  major version: 49
  flags: (0x0021) ACC_PUBLIC, ACC_SUPER
  this_class: #3                          // org/antlr/runtime/tree/TreeRuleReturnScope
  super_class: #4                         // org/antlr/runtime/RuleReturnScope
  interfaces: 0, fields: 1, methods: 2, attributes: 1
Constant pool:
   #1 = Methodref          #4.#18         // org/antlr/runtime/RuleReturnScope."<init>":()V
   #2 = Fieldref           #3.#19         // org/antlr/runtime/tree/TreeRuleReturnScope.start:Ljava/lang/Object;
   #3 = Class              #20            // org/antlr/runtime/tree/TreeRuleReturnScope
   #4 = Class              #21            // org/antlr/runtime/RuleReturnScope
   #5 = Utf8               start
   #6 = Utf8               Ljava/lang/Object;
   #7 = Utf8               <init>
   #8 = Utf8               ()V
   #9 = Utf8               Code
  #10 = Utf8               LineNumberTable
  #11 = Utf8               LocalVariableTable
  #12 = Utf8               this
  #13 = Utf8               Lorg/antlr/runtime/tree/TreeRuleReturnScope;
  #14 = Utf8               getStart
  #15 = Utf8               ()Ljava/lang/Object;
  #16 = Utf8               SourceFile
  #17 = Utf8               TreeRuleReturnScope.java
  #18 = NameAndType        #7:#8          // "<init>":()V
  #19 = NameAndType        #5:#6          // start:Ljava/lang/Object;
  #20 = Utf8               org/antlr/runtime/tree/TreeRuleReturnScope
  #21 = Utf8               org/antlr/runtime/RuleReturnScope
{
  public java.lang.Object start;
    descriptor: Ljava/lang/Object;
    flags: (0x0001) ACC_PUBLIC

  public org.antlr.runtime.tree.TreeRuleReturnScope();
    descriptor: ()V
    flags: (0x0001) ACC_PUBLIC
    Code:
      stack=1, locals=1, args_size=1
         0: aload_0
         1: invokespecial #1                  // Method org/antlr/runtime/RuleReturnScope."<init>":()V
         4: return
      LineNumberTable:
        line 39: 0
      LocalVariableTable:
        Start  Length  Slot  Name   Signature
            0       5     0  this   Lorg/antlr/runtime/tree/TreeRuleReturnScope;

  public java.lang.Object getStart();
    descriptor: ()Ljava/lang/Object;
    flags: (0x0001) ACC_PUBLIC
    Code:
      stack=1, locals=1, args_size=1
         0: aload_0
         1: getfield      #2                  // Field start:Ljava/lang/Object;
         4: areturn
      LineNumberTable:
        line 43: 0
      LocalVariableTable:
        Start  Length  Slot  Name   Signature
            0       5     0  this   Lorg/antlr/runtime/tree/TreeRuleReturnScope;
}
SourceFile: "TreeRuleReturnScope.java"
