Classfile /Users/mw/Projects/slang-braindump/.jar/jar11/assemble/slang-braindump/assemble/content/com/zaxxer/nuprocess/linux/LinProcessFactory.class
  Last modified May 29, 2022; size 2010 bytes
  SHA-256 checksum 894511775e97557c1451416c19d95c474688ae5231d332300b148fe52bfd6bc7
  Compiled from "LinProcessFactory.java"
public class com.zaxxer.nuprocess.linux.LinProcessFactory implements com.zaxxer.nuprocess.NuProcessFactory
  minor version: 0
  major version: 51
  flags: (0x0021) ACC_PUBLIC, ACC_SUPER
  this_class: #4                          // com/zaxxer/nuprocess/linux/LinProcessFactory
  super_class: #7                         // java/lang/Object
  interfaces: 1, fields: 0, methods: 3, attributes: 1
Constant pool:
   #1 = Methodref          #7.#43         // java/lang/Object."<init>":()V
   #2 = Class              #44            // com/zaxxer/nuprocess/linux/LinuxProcess
   #3 = Methodref          #2.#45         // com/zaxxer/nuprocess/linux/LinuxProcess."<init>":(Lcom/zaxxer/nuprocess/NuProcessHandler;)V
   #4 = Class              #46            // com/zaxxer/nuprocess/linux/LinProcessFactory
   #5 = Methodref          #2.#47         // com/zaxxer/nuprocess/linux/LinuxProcess.start:(Ljava/util/List;[Ljava/lang/String;Ljava/nio/file/Path;)Lcom/zaxxer/nuprocess/NuProcess;
   #6 = Methodref          #2.#48         // com/zaxxer/nuprocess/linux/LinuxProcess.run:(Ljava/util/List;[Ljava/lang/String;Ljava/nio/file/Path;)V
   #7 = Class              #49            // java/lang/Object
   #8 = Class              #50            // com/zaxxer/nuprocess/NuProcessFactory
   #9 = Utf8               <init>
  #10 = Utf8               ()V
  #11 = Utf8               Code
  #12 = Utf8               LineNumberTable
  #13 = Utf8               LocalVariableTable
  #14 = Utf8               this
  #15 = Utf8               Lcom/zaxxer/nuprocess/linux/LinProcessFactory;
  #16 = Utf8               createProcess
  #17 = Utf8               (Ljava/util/List;[Ljava/lang/String;Lcom/zaxxer/nuprocess/NuProcessHandler;Ljava/nio/file/Path;)Lcom/zaxxer/nuprocess/NuProcess;
  #18 = Utf8               commands
  #19 = Utf8               Ljava/util/List;
  #20 = Utf8               env
  #21 = Utf8               [Ljava/lang/String;
  #22 = Utf8               processListener
  #23 = Utf8               Lcom/zaxxer/nuprocess/NuProcessHandler;
  #24 = Utf8               cwd
  #25 = Utf8               Ljava/nio/file/Path;
  #26 = Utf8               process
  #27 = Utf8               Lcom/zaxxer/nuprocess/linux/LinuxProcess;
  #28 = Utf8               LocalVariableTypeTable
  #29 = Utf8               Ljava/util/List<Ljava/lang/String;>;
  #30 = Utf8               StackMapTable
  #31 = Class              #51            // java/util/List
  #32 = Class              #21            // "[Ljava/lang/String;"
  #33 = Class              #52            // com/zaxxer/nuprocess/NuProcessHandler
  #34 = Class              #53            // java/nio/file/Path
  #35 = Class              #54            // java/lang/Throwable
  #36 = Utf8               Signature
  #37 = Utf8               (Ljava/util/List<Ljava/lang/String;>;[Ljava/lang/String;Lcom/zaxxer/nuprocess/NuProcessHandler;Ljava/nio/file/Path;)Lcom/zaxxer/nuprocess/NuProcess;
  #38 = Utf8               runProcess
  #39 = Utf8               (Ljava/util/List;[Ljava/lang/String;Lcom/zaxxer/nuprocess/NuProcessHandler;Ljava/nio/file/Path;)V
  #40 = Utf8               (Ljava/util/List<Ljava/lang/String;>;[Ljava/lang/String;Lcom/zaxxer/nuprocess/NuProcessHandler;Ljava/nio/file/Path;)V
  #41 = Utf8               SourceFile
  #42 = Utf8               LinProcessFactory.java
  #43 = NameAndType        #9:#10         // "<init>":()V
  #44 = Utf8               com/zaxxer/nuprocess/linux/LinuxProcess
  #45 = NameAndType        #9:#55         // "<init>":(Lcom/zaxxer/nuprocess/NuProcessHandler;)V
  #46 = Utf8               com/zaxxer/nuprocess/linux/LinProcessFactory
  #47 = NameAndType        #56:#57        // start:(Ljava/util/List;[Ljava/lang/String;Ljava/nio/file/Path;)Lcom/zaxxer/nuprocess/NuProcess;
  #48 = NameAndType        #58:#59        // run:(Ljava/util/List;[Ljava/lang/String;Ljava/nio/file/Path;)V
  #49 = Utf8               java/lang/Object
  #50 = Utf8               com/zaxxer/nuprocess/NuProcessFactory
  #51 = Utf8               java/util/List
  #52 = Utf8               com/zaxxer/nuprocess/NuProcessHandler
  #53 = Utf8               java/nio/file/Path
  #54 = Utf8               java/lang/Throwable
  #55 = Utf8               (Lcom/zaxxer/nuprocess/NuProcessHandler;)V
  #56 = Utf8               start
  #57 = Utf8               (Ljava/util/List;[Ljava/lang/String;Ljava/nio/file/Path;)Lcom/zaxxer/nuprocess/NuProcess;
  #58 = Utf8               run
  #59 = Utf8               (Ljava/util/List;[Ljava/lang/String;Ljava/nio/file/Path;)V
{
  public com.zaxxer.nuprocess.linux.LinProcessFactory();
    descriptor: ()V
    flags: (0x0001) ACC_PUBLIC
    Code:
      stack=1, locals=1, args_size=1
         0: aload_0
         1: invokespecial #1                  // Method java/lang/Object."<init>":()V
         4: return
      LineNumberTable:
        line 32: 0
      LocalVariableTable:
        Start  Length  Slot  Name   Signature
            0       5     0  this   Lcom/zaxxer/nuprocess/linux/LinProcessFactory;

  public com.zaxxer.nuprocess.NuProcess createProcess(java.util.List<java.lang.String>, java.lang.String[], com.zaxxer.nuprocess.NuProcessHandler, java.nio.file.Path);
    descriptor: (Ljava/util/List;[Ljava/lang/String;Lcom/zaxxer/nuprocess/NuProcessHandler;Ljava/nio/file/Path;)Lcom/zaxxer/nuprocess/NuProcess;
    flags: (0x0001) ACC_PUBLIC
    Code:
      stack=4, locals=8, args_size=5
         0: new           #2                  // class com/zaxxer/nuprocess/linux/LinuxProcess
         3: dup
         4: aload_3
         5: invokespecial #3                  // Method com/zaxxer/nuprocess/linux/LinuxProcess."<init>":(Lcom/zaxxer/nuprocess/NuProcessHandler;)V
         8: astore        5
        10: ldc           #4                  // class com/zaxxer/nuprocess/linux/LinProcessFactory
        12: dup
        13: astore        6
        15: monitorenter
        16: aload         5
        18: aload_1
        19: aload_2
        20: aload         4
        22: invokevirtual #5                  // Method com/zaxxer/nuprocess/linux/LinuxProcess.start:(Ljava/util/List;[Ljava/lang/String;Ljava/nio/file/Path;)Lcom/zaxxer/nuprocess/NuProcess;
        25: pop
        26: aload         6
        28: monitorexit
        29: goto          40
        32: astore        7
        34: aload         6
        36: monitorexit
        37: aload         7
        39: athrow
        40: aload         5
        42: areturn
      Exception table:
         from    to  target type
            16    29    32   any
            32    37    32   any
      LineNumberTable:
        line 38: 0
        line 39: 10
        line 40: 16
        line 41: 26
        line 42: 40
      LocalVariableTable:
        Start  Length  Slot  Name   Signature
            0      43     0  this   Lcom/zaxxer/nuprocess/linux/LinProcessFactory;
            0      43     1 commands   Ljava/util/List;
            0      43     2   env   [Ljava/lang/String;
            0      43     3 processListener   Lcom/zaxxer/nuprocess/NuProcessHandler;
            0      43     4   cwd   Ljava/nio/file/Path;
           10      33     5 process   Lcom/zaxxer/nuprocess/linux/LinuxProcess;
      LocalVariableTypeTable:
        Start  Length  Slot  Name   Signature
            0      43     1 commands   Ljava/util/List<Ljava/lang/String;>;
      StackMapTable: number_of_entries = 2
        frame_type = 255 /* full_frame */
          offset_delta = 32
          locals = [ class com/zaxxer/nuprocess/linux/LinProcessFactory, class java/util/List, class "[Ljava/lang/String;", class com/zaxxer/nuprocess/NuProcessHandler, class java/nio/file/Path, class com/zaxxer/nuprocess/linux/LinuxProcess, class java/lang/Object ]
          stack = [ class java/lang/Throwable ]
        frame_type = 250 /* chop */
          offset_delta = 7
    Signature: #37                          // (Ljava/util/List<Ljava/lang/String;>;[Ljava/lang/String;Lcom/zaxxer/nuprocess/NuProcessHandler;Ljava/nio/file/Path;)Lcom/zaxxer/nuprocess/NuProcess;

  public void runProcess(java.util.List<java.lang.String>, java.lang.String[], com.zaxxer.nuprocess.NuProcessHandler, java.nio.file.Path);
    descriptor: (Ljava/util/List;[Ljava/lang/String;Lcom/zaxxer/nuprocess/NuProcessHandler;Ljava/nio/file/Path;)V
    flags: (0x0001) ACC_PUBLIC
    Code:
      stack=4, locals=6, args_size=5
         0: new           #2                  // class com/zaxxer/nuprocess/linux/LinuxProcess
         3: dup
         4: aload_3
         5: invokespecial #3                  // Method com/zaxxer/nuprocess/linux/LinuxProcess."<init>":(Lcom/zaxxer/nuprocess/NuProcessHandler;)V
         8: astore        5
        10: aload         5
        12: aload_1
        13: aload_2
        14: aload         4
        16: invokevirtual #6                  // Method com/zaxxer/nuprocess/linux/LinuxProcess.run:(Ljava/util/List;[Ljava/lang/String;Ljava/nio/file/Path;)V
        19: return
      LineNumberTable:
        line 49: 0
        line 50: 10
        line 51: 19
      LocalVariableTable:
        Start  Length  Slot  Name   Signature
            0      20     0  this   Lcom/zaxxer/nuprocess/linux/LinProcessFactory;
            0      20     1 commands   Ljava/util/List;
            0      20     2   env   [Ljava/lang/String;
            0      20     3 processListener   Lcom/zaxxer/nuprocess/NuProcessHandler;
            0      20     4   cwd   Ljava/nio/file/Path;
           10      10     5 process   Lcom/zaxxer/nuprocess/linux/LinuxProcess;
      LocalVariableTypeTable:
        Start  Length  Slot  Name   Signature
            0      20     1 commands   Ljava/util/List<Ljava/lang/String;>;
    Signature: #40                          // (Ljava/util/List<Ljava/lang/String;>;[Ljava/lang/String;Lcom/zaxxer/nuprocess/NuProcessHandler;Ljava/nio/file/Path;)V
}
SourceFile: "LinProcessFactory.java"
