Classfile /Users/mw/Projects/slang-braindump/.jar/jar8/assemble/slang-braindump/assemble/content/com/fasterxml/jackson/core/JsonParser$NumberType.class
  Last modified May 29, 2022; size 1392 bytes
  SHA-256 checksum df2b9cb6884891015965a986ad3ee9b8e959705b5dd699faaf736b8a371ef78b
  Compiled from "JsonParser.java"
public final class com.fasterxml.jackson.core.JsonParser$NumberType extends java.lang.Enum<com.fasterxml.jackson.core.JsonParser$NumberType>
  minor version: 0
  major version: 50
  flags: (0x4031) ACC_PUBLIC, ACC_FINAL, ACC_SUPER, ACC_ENUM
  this_class: #4                          // com/fasterxml/jackson/core/JsonParser$NumberType
  super_class: #20                        // java/lang/Enum
  interfaces: 0, fields: 7, methods: 4, attributes: 3
Constant pool:
   #1 = Fieldref           #4.#50         // com/fasterxml/jackson/core/JsonParser$NumberType.$VALUES:[Lcom/fasterxml/jackson/core/JsonParser$NumberType;
   #2 = Methodref          #51.#52        // "[Lcom/fasterxml/jackson/core/JsonParser$NumberType;".clone:()Ljava/lang/Object;
   #3 = Class              #31            // "[Lcom/fasterxml/jackson/core/JsonParser$NumberType;"
   #4 = Class              #54            // com/fasterxml/jackson/core/JsonParser$NumberType
   #5 = Methodref          #20.#55        // java/lang/Enum.valueOf:(Ljava/lang/Class;Ljava/lang/String;)Ljava/lang/Enum;
   #6 = Methodref          #20.#56        // java/lang/Enum."<init>":(Ljava/lang/String;I)V
   #7 = String             #21            // INT
   #8 = Methodref          #4.#56         // com/fasterxml/jackson/core/JsonParser$NumberType."<init>":(Ljava/lang/String;I)V
   #9 = Fieldref           #4.#57         // com/fasterxml/jackson/core/JsonParser$NumberType.INT:Lcom/fasterxml/jackson/core/JsonParser$NumberType;
  #10 = String             #25            // LONG
  #11 = Fieldref           #4.#58         // com/fasterxml/jackson/core/JsonParser$NumberType.LONG:Lcom/fasterxml/jackson/core/JsonParser$NumberType;
  #12 = String             #26            // BIG_INTEGER
  #13 = Fieldref           #4.#59         // com/fasterxml/jackson/core/JsonParser$NumberType.BIG_INTEGER:Lcom/fasterxml/jackson/core/JsonParser$NumberType;
  #14 = String             #27            // FLOAT
  #15 = Fieldref           #4.#60         // com/fasterxml/jackson/core/JsonParser$NumberType.FLOAT:Lcom/fasterxml/jackson/core/JsonParser$NumberType;
  #16 = String             #28            // DOUBLE
  #17 = Fieldref           #4.#61         // com/fasterxml/jackson/core/JsonParser$NumberType.DOUBLE:Lcom/fasterxml/jackson/core/JsonParser$NumberType;
  #18 = String             #29            // BIG_DECIMAL
  #19 = Fieldref           #4.#62         // com/fasterxml/jackson/core/JsonParser$NumberType.BIG_DECIMAL:Lcom/fasterxml/jackson/core/JsonParser$NumberType;
  #20 = Class              #63            // java/lang/Enum
  #21 = Utf8               INT
  #22 = Utf8               NumberType
  #23 = Utf8               InnerClasses
  #24 = Utf8               Lcom/fasterxml/jackson/core/JsonParser$NumberType;
  #25 = Utf8               LONG
  #26 = Utf8               BIG_INTEGER
  #27 = Utf8               FLOAT
  #28 = Utf8               DOUBLE
  #29 = Utf8               BIG_DECIMAL
  #30 = Utf8               $VALUES
  #31 = Utf8               [Lcom/fasterxml/jackson/core/JsonParser$NumberType;
  #32 = Utf8               values
  #33 = Utf8               ()[Lcom/fasterxml/jackson/core/JsonParser$NumberType;
  #34 = Utf8               Code
  #35 = Utf8               LineNumberTable
  #36 = Utf8               valueOf
  #37 = Utf8               (Ljava/lang/String;)Lcom/fasterxml/jackson/core/JsonParser$NumberType;
  #38 = Utf8               LocalVariableTable
  #39 = Utf8               name
  #40 = Utf8               Ljava/lang/String;
  #41 = Utf8               <init>
  #42 = Utf8               (Ljava/lang/String;I)V
  #43 = Utf8               this
  #44 = Utf8               Signature
  #45 = Utf8               ()V
  #46 = Utf8               <clinit>
  #47 = Utf8               Ljava/lang/Enum<Lcom/fasterxml/jackson/core/JsonParser$NumberType;>;
  #48 = Utf8               SourceFile
  #49 = Utf8               JsonParser.java
  #50 = NameAndType        #30:#31        // $VALUES:[Lcom/fasterxml/jackson/core/JsonParser$NumberType;
  #51 = Class              #31            // "[Lcom/fasterxml/jackson/core/JsonParser$NumberType;"
  #52 = NameAndType        #64:#65        // clone:()Ljava/lang/Object;
  #53 = Class              #66            // com/fasterxml/jackson/core/JsonParser
  #54 = Utf8               com/fasterxml/jackson/core/JsonParser$NumberType
  #55 = NameAndType        #36:#67        // valueOf:(Ljava/lang/Class;Ljava/lang/String;)Ljava/lang/Enum;
  #56 = NameAndType        #41:#42        // "<init>":(Ljava/lang/String;I)V
  #57 = NameAndType        #21:#24        // INT:Lcom/fasterxml/jackson/core/JsonParser$NumberType;
  #58 = NameAndType        #25:#24        // LONG:Lcom/fasterxml/jackson/core/JsonParser$NumberType;
  #59 = NameAndType        #26:#24        // BIG_INTEGER:Lcom/fasterxml/jackson/core/JsonParser$NumberType;
  #60 = NameAndType        #27:#24        // FLOAT:Lcom/fasterxml/jackson/core/JsonParser$NumberType;
  #61 = NameAndType        #28:#24        // DOUBLE:Lcom/fasterxml/jackson/core/JsonParser$NumberType;
  #62 = NameAndType        #29:#24        // BIG_DECIMAL:Lcom/fasterxml/jackson/core/JsonParser$NumberType;
  #63 = Utf8               java/lang/Enum
  #64 = Utf8               clone
  #65 = Utf8               ()Ljava/lang/Object;
  #66 = Utf8               com/fasterxml/jackson/core/JsonParser
  #67 = Utf8               (Ljava/lang/Class;Ljava/lang/String;)Ljava/lang/Enum;
{
  public static final com.fasterxml.jackson.core.JsonParser$NumberType INT;
    descriptor: Lcom/fasterxml/jackson/core/JsonParser$NumberType;
    flags: (0x4019) ACC_PUBLIC, ACC_STATIC, ACC_FINAL, ACC_ENUM

  public static final com.fasterxml.jackson.core.JsonParser$NumberType LONG;
    descriptor: Lcom/fasterxml/jackson/core/JsonParser$NumberType;
    flags: (0x4019) ACC_PUBLIC, ACC_STATIC, ACC_FINAL, ACC_ENUM

  public static final com.fasterxml.jackson.core.JsonParser$NumberType BIG_INTEGER;
    descriptor: Lcom/fasterxml/jackson/core/JsonParser$NumberType;
    flags: (0x4019) ACC_PUBLIC, ACC_STATIC, ACC_FINAL, ACC_ENUM

  public static final com.fasterxml.jackson.core.JsonParser$NumberType FLOAT;
    descriptor: Lcom/fasterxml/jackson/core/JsonParser$NumberType;
    flags: (0x4019) ACC_PUBLIC, ACC_STATIC, ACC_FINAL, ACC_ENUM

  public static final com.fasterxml.jackson.core.JsonParser$NumberType DOUBLE;
    descriptor: Lcom/fasterxml/jackson/core/JsonParser$NumberType;
    flags: (0x4019) ACC_PUBLIC, ACC_STATIC, ACC_FINAL, ACC_ENUM

  public static final com.fasterxml.jackson.core.JsonParser$NumberType BIG_DECIMAL;
    descriptor: Lcom/fasterxml/jackson/core/JsonParser$NumberType;
    flags: (0x4019) ACC_PUBLIC, ACC_STATIC, ACC_FINAL, ACC_ENUM

  private static final com.fasterxml.jackson.core.JsonParser$NumberType[] $VALUES;
    descriptor: [Lcom/fasterxml/jackson/core/JsonParser$NumberType;
    flags: (0x101a) ACC_PRIVATE, ACC_STATIC, ACC_FINAL, ACC_SYNTHETIC

  public static com.fasterxml.jackson.core.JsonParser$NumberType[] values();
    descriptor: ()[Lcom/fasterxml/jackson/core/JsonParser$NumberType;
    flags: (0x0009) ACC_PUBLIC, ACC_STATIC
    Code:
      stack=1, locals=0, args_size=0
         0: getstatic     #1                  // Field $VALUES:[Lcom/fasterxml/jackson/core/JsonParser$NumberType;
         3: invokevirtual #2                  // Method "[Lcom/fasterxml/jackson/core/JsonParser$NumberType;".clone:()Ljava/lang/Object;
         6: checkcast     #3                  // class "[Lcom/fasterxml/jackson/core/JsonParser$NumberType;"
         9: areturn
      LineNumberTable:
        line 40: 0

  public static com.fasterxml.jackson.core.JsonParser$NumberType valueOf(java.lang.String);
    descriptor: (Ljava/lang/String;)Lcom/fasterxml/jackson/core/JsonParser$NumberType;
    flags: (0x0009) ACC_PUBLIC, ACC_STATIC
    Code:
      stack=2, locals=1, args_size=1
         0: ldc           #4                  // class com/fasterxml/jackson/core/JsonParser$NumberType
         2: aload_0
         3: invokestatic  #5                  // Method java/lang/Enum.valueOf:(Ljava/lang/Class;Ljava/lang/String;)Ljava/lang/Enum;
         6: checkcast     #4                  // class com/fasterxml/jackson/core/JsonParser$NumberType
         9: areturn
      LineNumberTable:
        line 40: 0
      LocalVariableTable:
        Start  Length  Slot  Name   Signature
            0      10     0  name   Ljava/lang/String;

  private com.fasterxml.jackson.core.JsonParser$NumberType();
    descriptor: (Ljava/lang/String;I)V
    flags: (0x0002) ACC_PRIVATE
    Code:
      stack=3, locals=3, args_size=3
         0: aload_0
         1: aload_1
         2: iload_2
         3: invokespecial #6                  // Method java/lang/Enum."<init>":(Ljava/lang/String;I)V
         6: return
      LineNumberTable:
        line 40: 0
      LocalVariableTable:
        Start  Length  Slot  Name   Signature
            0       7     0  this   Lcom/fasterxml/jackson/core/JsonParser$NumberType;
    Signature: #45                          // ()V

  static {};
    descriptor: ()V
    flags: (0x0008) ACC_STATIC
    Code:
      stack=4, locals=0, args_size=0
         0: new           #4                  // class com/fasterxml/jackson/core/JsonParser$NumberType
         3: dup
         4: ldc           #7                  // String INT
         6: iconst_0
         7: invokespecial #8                  // Method "<init>":(Ljava/lang/String;I)V
        10: putstatic     #9                  // Field INT:Lcom/fasterxml/jackson/core/JsonParser$NumberType;
        13: new           #4                  // class com/fasterxml/jackson/core/JsonParser$NumberType
        16: dup
        17: ldc           #10                 // String LONG
        19: iconst_1
        20: invokespecial #8                  // Method "<init>":(Ljava/lang/String;I)V
        23: putstatic     #11                 // Field LONG:Lcom/fasterxml/jackson/core/JsonParser$NumberType;
        26: new           #4                  // class com/fasterxml/jackson/core/JsonParser$NumberType
        29: dup
        30: ldc           #12                 // String BIG_INTEGER
        32: iconst_2
        33: invokespecial #8                  // Method "<init>":(Ljava/lang/String;I)V
        36: putstatic     #13                 // Field BIG_INTEGER:Lcom/fasterxml/jackson/core/JsonParser$NumberType;
        39: new           #4                  // class com/fasterxml/jackson/core/JsonParser$NumberType
        42: dup
        43: ldc           #14                 // String FLOAT
        45: iconst_3
        46: invokespecial #8                  // Method "<init>":(Ljava/lang/String;I)V
        49: putstatic     #15                 // Field FLOAT:Lcom/fasterxml/jackson/core/JsonParser$NumberType;
        52: new           #4                  // class com/fasterxml/jackson/core/JsonParser$NumberType
        55: dup
        56: ldc           #16                 // String DOUBLE
        58: iconst_4
        59: invokespecial #8                  // Method "<init>":(Ljava/lang/String;I)V
        62: putstatic     #17                 // Field DOUBLE:Lcom/fasterxml/jackson/core/JsonParser$NumberType;
        65: new           #4                  // class com/fasterxml/jackson/core/JsonParser$NumberType
        68: dup
        69: ldc           #18                 // String BIG_DECIMAL
        71: iconst_5
        72: invokespecial #8                  // Method "<init>":(Ljava/lang/String;I)V
        75: putstatic     #19                 // Field BIG_DECIMAL:Lcom/fasterxml/jackson/core/JsonParser$NumberType;
        78: bipush        6
        80: anewarray     #4                  // class com/fasterxml/jackson/core/JsonParser$NumberType
        83: dup
        84: iconst_0
        85: getstatic     #9                  // Field INT:Lcom/fasterxml/jackson/core/JsonParser$NumberType;
        88: aastore
        89: dup
        90: iconst_1
        91: getstatic     #11                 // Field LONG:Lcom/fasterxml/jackson/core/JsonParser$NumberType;
        94: aastore
        95: dup
        96: iconst_2
        97: getstatic     #13                 // Field BIG_INTEGER:Lcom/fasterxml/jackson/core/JsonParser$NumberType;
       100: aastore
       101: dup
       102: iconst_3
       103: getstatic     #15                 // Field FLOAT:Lcom/fasterxml/jackson/core/JsonParser$NumberType;
       106: aastore
       107: dup
       108: iconst_4
       109: getstatic     #17                 // Field DOUBLE:Lcom/fasterxml/jackson/core/JsonParser$NumberType;
       112: aastore
       113: dup
       114: iconst_5
       115: getstatic     #19                 // Field BIG_DECIMAL:Lcom/fasterxml/jackson/core/JsonParser$NumberType;
       118: aastore
       119: putstatic     #1                  // Field $VALUES:[Lcom/fasterxml/jackson/core/JsonParser$NumberType;
       122: return
      LineNumberTable:
        line 41: 0
        line 40: 78
}
Signature: #47                          // Ljava/lang/Enum<Lcom/fasterxml/jackson/core/JsonParser$NumberType;>;
SourceFile: "JsonParser.java"
InnerClasses:
  public static final #22= #4 of #53;     // NumberType=class com/fasterxml/jackson/core/JsonParser$NumberType of class com/fasterxml/jackson/core/JsonParser
