Classfile /Users/mw/Projects/slang-braindump/.jar/jar8/assemble/slang-braindump/assemble/content/com/fasterxml/jackson/core/JsonFactory.class
  Last modified May 29, 2022; size 27522 bytes
  SHA-256 checksum 24e0b96aa571af8be087f4deb7002a3cb26ccac471c32bc03c18529610b51fbd
  Compiled from "JsonFactory.java"
public class com.fasterxml.jackson.core.JsonFactory extends com.fasterxml.jackson.core.TokenStreamFactory implements com.fasterxml.jackson.core.Versioned,java.io.Serializable
  minor version: 0
  major version: 50
  flags: (0x0021) ACC_PUBLIC, ACC_SUPER
  this_class: #17                         // com/fasterxml/jackson/core/JsonFactory
  super_class: #180                       // com/fasterxml/jackson/core/TokenStreamFactory
  interfaces: 2, fields: 19, methods: 99, attributes: 2
Constant pool:
    #1 = Class              #447          // com/fasterxml/jackson/core/ObjectCodec
    #2 = Methodref          #17.#448      // com/fasterxml/jackson/core/JsonFactory."<init>":(Lcom/fasterxml/jackson/core/ObjectCodec;)V
    #3 = Methodref          #180.#449     // com/fasterxml/jackson/core/TokenStreamFactory."<init>":()V
    #4 = Methodref          #450.#451     // com/fasterxml/jackson/core/sym/CharsToNameCanonicalizer.createRoot:()Lcom/fasterxml/jackson/core/sym/CharsToNameCanonicalizer;
    #5 = Fieldref           #17.#452      // com/fasterxml/jackson/core/JsonFactory._rootCharSymbols:Lcom/fasterxml/jackson/core/sym/CharsToNameCanonicalizer;
    #6 = Methodref          #453.#454     // com/fasterxml/jackson/core/sym/ByteQuadsCanonicalizer.createRoot:()Lcom/fasterxml/jackson/core/sym/ByteQuadsCanonicalizer;
    #7 = Fieldref           #17.#455      // com/fasterxml/jackson/core/JsonFactory._byteSymbolCanonicalizer:Lcom/fasterxml/jackson/core/sym/ByteQuadsCanonicalizer;
    #8 = Fieldref           #17.#456      // com/fasterxml/jackson/core/JsonFactory.DEFAULT_FACTORY_FEATURE_FLAGS:I
    #9 = Fieldref           #17.#457      // com/fasterxml/jackson/core/JsonFactory._factoryFeatures:I
   #10 = Fieldref           #17.#458      // com/fasterxml/jackson/core/JsonFactory.DEFAULT_PARSER_FEATURE_FLAGS:I
   #11 = Fieldref           #17.#459      // com/fasterxml/jackson/core/JsonFactory._parserFeatures:I
   #12 = Fieldref           #17.#460      // com/fasterxml/jackson/core/JsonFactory.DEFAULT_GENERATOR_FEATURE_FLAGS:I
   #13 = Fieldref           #17.#461      // com/fasterxml/jackson/core/JsonFactory._generatorFeatures:I
   #14 = Fieldref           #17.#462      // com/fasterxml/jackson/core/JsonFactory.DEFAULT_ROOT_VALUE_SEPARATOR:Lcom/fasterxml/jackson/core/SerializableString;
   #15 = Fieldref           #17.#463      // com/fasterxml/jackson/core/JsonFactory._rootValueSeparator:Lcom/fasterxml/jackson/core/SerializableString;
   #16 = Fieldref           #17.#464      // com/fasterxml/jackson/core/JsonFactory._objectCodec:Lcom/fasterxml/jackson/core/ObjectCodec;
   #17 = Class              #465          // com/fasterxml/jackson/core/JsonFactory
   #18 = Fieldref           #17.#466      // com/fasterxml/jackson/core/JsonFactory._quoteChar:C
   #19 = Fieldref           #17.#467      // com/fasterxml/jackson/core/JsonFactory._inputDecorator:Lcom/fasterxml/jackson/core/io/InputDecorator;
   #20 = Fieldref           #17.#468      // com/fasterxml/jackson/core/JsonFactory._outputDecorator:Lcom/fasterxml/jackson/core/io/OutputDecorator;
   #21 = Fieldref           #17.#469      // com/fasterxml/jackson/core/JsonFactory._characterEscapes:Lcom/fasterxml/jackson/core/io/CharacterEscapes;
   #22 = Fieldref           #17.#470      // com/fasterxml/jackson/core/JsonFactory._maximumNonEscapedChar:I
   #23 = Fieldref           #39.#457      // com/fasterxml/jackson/core/JsonFactoryBuilder._factoryFeatures:I
   #24 = Fieldref           #39.#471      // com/fasterxml/jackson/core/JsonFactoryBuilder._streamReadFeatures:I
   #25 = Fieldref           #39.#472      // com/fasterxml/jackson/core/JsonFactoryBuilder._streamWriteFeatures:I
   #26 = Fieldref           #39.#467      // com/fasterxml/jackson/core/JsonFactoryBuilder._inputDecorator:Lcom/fasterxml/jackson/core/io/InputDecorator;
   #27 = Fieldref           #39.#468      // com/fasterxml/jackson/core/JsonFactoryBuilder._outputDecorator:Lcom/fasterxml/jackson/core/io/OutputDecorator;
   #28 = Fieldref           #39.#469      // com/fasterxml/jackson/core/JsonFactoryBuilder._characterEscapes:Lcom/fasterxml/jackson/core/io/CharacterEscapes;
   #29 = Fieldref           #39.#463      // com/fasterxml/jackson/core/JsonFactoryBuilder._rootValueSeparator:Lcom/fasterxml/jackson/core/SerializableString;
   #30 = Fieldref           #39.#470      // com/fasterxml/jackson/core/JsonFactoryBuilder._maximumNonEscapedChar:I
   #31 = Fieldref           #39.#466      // com/fasterxml/jackson/core/JsonFactoryBuilder._quoteChar:C
   #32 = Fieldref           #473.#457     // com/fasterxml/jackson/core/TSFBuilder._factoryFeatures:I
   #33 = Fieldref           #473.#471     // com/fasterxml/jackson/core/TSFBuilder._streamReadFeatures:I
   #34 = Fieldref           #473.#472     // com/fasterxml/jackson/core/TSFBuilder._streamWriteFeatures:I
   #35 = Fieldref           #473.#467     // com/fasterxml/jackson/core/TSFBuilder._inputDecorator:Lcom/fasterxml/jackson/core/io/InputDecorator;
   #36 = Fieldref           #473.#468     // com/fasterxml/jackson/core/TSFBuilder._outputDecorator:Lcom/fasterxml/jackson/core/io/OutputDecorator;
   #37 = String             #474          // Factory implementation for format (%s) MUST override `rebuild()` method
   #38 = Methodref          #17.#475      // com/fasterxml/jackson/core/JsonFactory._requireJSONFactory:(Ljava/lang/String;)V
   #39 = Class              #476          // com/fasterxml/jackson/core/JsonFactoryBuilder
   #40 = Methodref          #39.#477      // com/fasterxml/jackson/core/JsonFactoryBuilder."<init>":(Lcom/fasterxml/jackson/core/JsonFactory;)V
   #41 = Methodref          #39.#449      // com/fasterxml/jackson/core/JsonFactoryBuilder."<init>":()V
   #42 = Methodref          #17.#478      // com/fasterxml/jackson/core/JsonFactory._checkInvalidCopy:(Ljava/lang/Class;)V
   #43 = Methodref          #17.#479      // com/fasterxml/jackson/core/JsonFactory."<init>":(Lcom/fasterxml/jackson/core/JsonFactory;Lcom/fasterxml/jackson/core/ObjectCodec;)V
   #44 = Methodref          #173.#480     // java/lang/Object.getClass:()Ljava/lang/Class;
   #45 = Class              #481          // java/lang/IllegalStateException
   #46 = Class              #482          // java/lang/StringBuilder
   #47 = Methodref          #46.#449      // java/lang/StringBuilder."<init>":()V
   #48 = String             #483          // Failed copy():
   #49 = Methodref          #46.#484      // java/lang/StringBuilder.append:(Ljava/lang/String;)Ljava/lang/StringBuilder;
   #50 = Methodref          #485.#486     // java/lang/Class.getName:()Ljava/lang/String;
   #51 = String             #487          //  (version:
   #52 = Methodref          #17.#488      // com/fasterxml/jackson/core/JsonFactory.version:()Lcom/fasterxml/jackson/core/Version;
   #53 = Methodref          #46.#489      // java/lang/StringBuilder.append:(Ljava/lang/Object;)Ljava/lang/StringBuilder;
   #54 = String             #490          // ) does not override copy(); it has to
   #55 = Methodref          #46.#491      // java/lang/StringBuilder.toString:()Ljava/lang/String;
   #56 = Methodref          #45.#492      // java/lang/IllegalStateException."<init>":(Ljava/lang/String;)V
   #57 = Methodref          #17.#493      // com/fasterxml/jackson/core/JsonFactory._isJSONFactory:()Z
   #58 = Methodref          #17.#494      // com/fasterxml/jackson/core/JsonFactory.getFormatName:()Ljava/lang/String;
   #59 = InterfaceMethodref #495.#496     // com/fasterxml/jackson/core/FormatSchema.getSchemaType:()Ljava/lang/String;
   #60 = Methodref          #497.#498     // java/lang/String.equals:(Ljava/lang/Object;)Z
   #61 = String             #499          // JSON
   #62 = Methodref          #17.#500      // com/fasterxml/jackson/core/JsonFactory.hasJSONFormat:(Lcom/fasterxml/jackson/core/format/InputAccessor;)Lcom/fasterxml/jackson/core/format/MatchStrength;
   #63 = Methodref          #128.#500     // com/fasterxml/jackson/core/json/ByteSourceJsonBootstrapper.hasJSONFormat:(Lcom/fasterxml/jackson/core/format/InputAccessor;)Lcom/fasterxml/jackson/core/format/MatchStrength;
   #64 = Fieldref           #501.#502     // com/fasterxml/jackson/core/json/PackageVersion.VERSION:Lcom/fasterxml/jackson/core/Version;
   #65 = Methodref          #17.#503      // com/fasterxml/jackson/core/JsonFactory.enable:(Lcom/fasterxml/jackson/core/JsonFactory$Feature;)Lcom/fasterxml/jackson/core/JsonFactory;
   #66 = Methodref          #17.#504      // com/fasterxml/jackson/core/JsonFactory.disable:(Lcom/fasterxml/jackson/core/JsonFactory$Feature;)Lcom/fasterxml/jackson/core/JsonFactory;
   #67 = Methodref          #183.#505     // com/fasterxml/jackson/core/JsonFactory$Feature.getMask:()I
   #68 = Methodref          #17.#506      // com/fasterxml/jackson/core/JsonFactory.enable:(Lcom/fasterxml/jackson/core/JsonParser$Feature;)Lcom/fasterxml/jackson/core/JsonFactory;
   #69 = Methodref          #17.#507      // com/fasterxml/jackson/core/JsonFactory.disable:(Lcom/fasterxml/jackson/core/JsonParser$Feature;)Lcom/fasterxml/jackson/core/JsonFactory;
   #70 = Methodref          #304.#505     // com/fasterxml/jackson/core/JsonParser$Feature.getMask:()I
   #71 = Methodref          #508.#509     // com/fasterxml/jackson/core/StreamReadFeature.mappedFeature:()Lcom/fasterxml/jackson/core/JsonParser$Feature;
   #72 = Methodref          #17.#510      // com/fasterxml/jackson/core/JsonFactory.enable:(Lcom/fasterxml/jackson/core/JsonGenerator$Feature;)Lcom/fasterxml/jackson/core/JsonFactory;
   #73 = Methodref          #17.#511      // com/fasterxml/jackson/core/JsonFactory.disable:(Lcom/fasterxml/jackson/core/JsonGenerator$Feature;)Lcom/fasterxml/jackson/core/JsonFactory;
   #74 = Methodref          #316.#505     // com/fasterxml/jackson/core/JsonGenerator$Feature.getMask:()I
   #75 = Methodref          #512.#513     // com/fasterxml/jackson/core/StreamWriteFeature.mappedFeature:()Lcom/fasterxml/jackson/core/JsonGenerator$Feature;
   #76 = Class              #514          // com/fasterxml/jackson/core/io/SerializedString
   #77 = Methodref          #76.#492      // com/fasterxml/jackson/core/io/SerializedString."<init>":(Ljava/lang/String;)V
   #78 = InterfaceMethodref #515.#516     // com/fasterxml/jackson/core/SerializableString.getValue:()Ljava/lang/String;
   #79 = Methodref          #17.#517      // com/fasterxml/jackson/core/JsonFactory._createContentReference:(Ljava/lang/Object;)Lcom/fasterxml/jackson/core/io/ContentReference;
   #80 = Methodref          #17.#518      // com/fasterxml/jackson/core/JsonFactory._createContext:(Lcom/fasterxml/jackson/core/io/ContentReference;Z)Lcom/fasterxml/jackson/core/io/IOContext;
   #81 = Class              #519          // java/io/FileInputStream
   #82 = Methodref          #81.#520      // java/io/FileInputStream."<init>":(Ljava/io/File;)V
   #83 = Methodref          #17.#521      // com/fasterxml/jackson/core/JsonFactory._decorate:(Ljava/io/InputStream;Lcom/fasterxml/jackson/core/io/IOContext;)Ljava/io/InputStream;
   #84 = Methodref          #17.#522      // com/fasterxml/jackson/core/JsonFactory._createParser:(Ljava/io/InputStream;Lcom/fasterxml/jackson/core/io/IOContext;)Lcom/fasterxml/jackson/core/JsonParser;
   #85 = Methodref          #17.#523      // com/fasterxml/jackson/core/JsonFactory._optimizedStreamFromURL:(Ljava/net/URL;)Ljava/io/InputStream;
   #86 = Methodref          #17.#524      // com/fasterxml/jackson/core/JsonFactory._decorate:(Ljava/io/Reader;Lcom/fasterxml/jackson/core/io/IOContext;)Ljava/io/Reader;
   #87 = Methodref          #17.#525      // com/fasterxml/jackson/core/JsonFactory._createParser:(Ljava/io/Reader;Lcom/fasterxml/jackson/core/io/IOContext;)Lcom/fasterxml/jackson/core/JsonParser;
   #88 = Methodref          #526.#527     // com/fasterxml/jackson/core/io/InputDecorator.decorate:(Lcom/fasterxml/jackson/core/io/IOContext;[BII)Ljava/io/InputStream;
   #89 = Methodref          #17.#528      // com/fasterxml/jackson/core/JsonFactory._createParser:([BIILcom/fasterxml/jackson/core/io/IOContext;)Lcom/fasterxml/jackson/core/JsonParser;
   #90 = Methodref          #17.#529      // com/fasterxml/jackson/core/JsonFactory._createContentReference:(Ljava/lang/Object;II)Lcom/fasterxml/jackson/core/io/ContentReference;
   #91 = Methodref          #497.#530     // java/lang/String.length:()I
   #92 = Integer            32768
   #93 = Methodref          #17.#531      // com/fasterxml/jackson/core/JsonFactory.canUseCharArrays:()Z
   #94 = Class              #532          // java/io/StringReader
   #95 = Methodref          #94.#492      // java/io/StringReader."<init>":(Ljava/lang/String;)V
   #96 = Methodref          #17.#533      // com/fasterxml/jackson/core/JsonFactory.createParser:(Ljava/io/Reader;)Lcom/fasterxml/jackson/core/JsonParser;
   #97 = Methodref          #166.#534     // com/fasterxml/jackson/core/io/IOContext.allocTokenBuffer:(I)[C
   #98 = Methodref          #497.#535     // java/lang/String.getChars:(II[CI)V
   #99 = Methodref          #17.#536      // com/fasterxml/jackson/core/JsonFactory._createParser:([CIILcom/fasterxml/jackson/core/io/IOContext;Z)Lcom/fasterxml/jackson/core/JsonParser;
  #100 = Methodref          #17.#537      // com/fasterxml/jackson/core/JsonFactory.createParser:([CII)Lcom/fasterxml/jackson/core/JsonParser;
  #101 = Class              #538          // java/io/CharArrayReader
  #102 = Methodref          #101.#539     // java/io/CharArrayReader."<init>":([CII)V
  #103 = Methodref          #17.#540      // com/fasterxml/jackson/core/JsonFactory._decorate:(Ljava/io/DataInput;Lcom/fasterxml/jackson/core/io/IOContext;)Ljava/io/DataInput;
  #104 = Methodref          #17.#541      // com/fasterxml/jackson/core/JsonFactory._createParser:(Ljava/io/DataInput;Lcom/fasterxml/jackson/core/io/IOContext;)Lcom/fasterxml/jackson/core/JsonParser;
  #105 = String             #542          // Non-blocking source not (yet?) supported for this format (%s)
  #106 = Methodref          #17.#543      // com/fasterxml/jackson/core/JsonFactory._createNonBlockingContext:(Ljava/lang/Object;)Lcom/fasterxml/jackson/core/io/IOContext;
  #107 = Methodref          #453.#544     // com/fasterxml/jackson/core/sym/ByteQuadsCanonicalizer.makeChild:(I)Lcom/fasterxml/jackson/core/sym/ByteQuadsCanonicalizer;
  #108 = Class              #545          // com/fasterxml/jackson/core/json/async/NonBlockingJsonParser
  #109 = Methodref          #108.#546     // com/fasterxml/jackson/core/json/async/NonBlockingJsonParser."<init>":(Lcom/fasterxml/jackson/core/io/IOContext;ILcom/fasterxml/jackson/core/sym/ByteQuadsCanonicalizer;)V
  #110 = Methodref          #166.#547     // com/fasterxml/jackson/core/io/IOContext.setEncoding:(Lcom/fasterxml/jackson/core/JsonEncoding;)V
  #111 = Fieldref           #548.#549     // com/fasterxml/jackson/core/JsonEncoding.UTF8:Lcom/fasterxml/jackson/core/JsonEncoding;
  #112 = Methodref          #17.#550      // com/fasterxml/jackson/core/JsonFactory._decorate:(Ljava/io/OutputStream;Lcom/fasterxml/jackson/core/io/IOContext;)Ljava/io/OutputStream;
  #113 = Methodref          #17.#551      // com/fasterxml/jackson/core/JsonFactory._createUTF8Generator:(Ljava/io/OutputStream;Lcom/fasterxml/jackson/core/io/IOContext;)Lcom/fasterxml/jackson/core/JsonGenerator;
  #114 = Methodref          #17.#552      // com/fasterxml/jackson/core/JsonFactory._createWriter:(Ljava/io/OutputStream;Lcom/fasterxml/jackson/core/JsonEncoding;Lcom/fasterxml/jackson/core/io/IOContext;)Ljava/io/Writer;
  #115 = Methodref          #17.#553      // com/fasterxml/jackson/core/JsonFactory._decorate:(Ljava/io/Writer;Lcom/fasterxml/jackson/core/io/IOContext;)Ljava/io/Writer;
  #116 = Methodref          #17.#554      // com/fasterxml/jackson/core/JsonFactory._createGenerator:(Ljava/io/Writer;Lcom/fasterxml/jackson/core/io/IOContext;)Lcom/fasterxml/jackson/core/JsonGenerator;
  #117 = Methodref          #17.#555      // com/fasterxml/jackson/core/JsonFactory.createGenerator:(Ljava/io/OutputStream;Lcom/fasterxml/jackson/core/JsonEncoding;)Lcom/fasterxml/jackson/core/JsonGenerator;
  #118 = Class              #556          // java/io/FileOutputStream
  #119 = Methodref          #118.#520     // java/io/FileOutputStream."<init>":(Ljava/io/File;)V
  #120 = Methodref          #17.#557      // com/fasterxml/jackson/core/JsonFactory._createDataOutputWrapper:(Ljava/io/DataOutput;)Ljava/io/OutputStream;
  #121 = Methodref          #17.#558      // com/fasterxml/jackson/core/JsonFactory.createParser:(Ljava/io/File;)Lcom/fasterxml/jackson/core/JsonParser;
  #122 = Methodref          #17.#559      // com/fasterxml/jackson/core/JsonFactory.createParser:(Ljava/net/URL;)Lcom/fasterxml/jackson/core/JsonParser;
  #123 = Methodref          #17.#560      // com/fasterxml/jackson/core/JsonFactory.createParser:(Ljava/io/InputStream;)Lcom/fasterxml/jackson/core/JsonParser;
  #124 = Methodref          #17.#561      // com/fasterxml/jackson/core/JsonFactory.createParser:([B)Lcom/fasterxml/jackson/core/JsonParser;
  #125 = Methodref          #17.#562      // com/fasterxml/jackson/core/JsonFactory.createParser:([BII)Lcom/fasterxml/jackson/core/JsonParser;
  #126 = Methodref          #17.#563      // com/fasterxml/jackson/core/JsonFactory.createParser:(Ljava/lang/String;)Lcom/fasterxml/jackson/core/JsonParser;
  #127 = Methodref          #17.#564      // com/fasterxml/jackson/core/JsonFactory.createGenerator:(Ljava/io/Writer;)Lcom/fasterxml/jackson/core/JsonGenerator;
  #128 = Class              #565          // com/fasterxml/jackson/core/json/ByteSourceJsonBootstrapper
  #129 = Methodref          #128.#566     // com/fasterxml/jackson/core/json/ByteSourceJsonBootstrapper."<init>":(Lcom/fasterxml/jackson/core/io/IOContext;Ljava/io/InputStream;)V
  #130 = Methodref          #128.#567     // com/fasterxml/jackson/core/json/ByteSourceJsonBootstrapper.constructParser:(ILcom/fasterxml/jackson/core/ObjectCodec;Lcom/fasterxml/jackson/core/sym/ByteQuadsCanonicalizer;Lcom/fasterxml/jackson/core/sym/CharsToNameCanonicalizer;I)Lcom/fasterxml/jackson/core/JsonParser;
  #131 = Class              #568          // com/fasterxml/jackson/core/json/ReaderBasedJsonParser
  #132 = Methodref          #450.#569     // com/fasterxml/jackson/core/sym/CharsToNameCanonicalizer.makeChild:(I)Lcom/fasterxml/jackson/core/sym/CharsToNameCanonicalizer;
  #133 = Methodref          #131.#570     // com/fasterxml/jackson/core/json/ReaderBasedJsonParser."<init>":(Lcom/fasterxml/jackson/core/io/IOContext;ILjava/io/Reader;Lcom/fasterxml/jackson/core/ObjectCodec;Lcom/fasterxml/jackson/core/sym/CharsToNameCanonicalizer;)V
  #134 = Methodref          #131.#571     // com/fasterxml/jackson/core/json/ReaderBasedJsonParser."<init>":(Lcom/fasterxml/jackson/core/io/IOContext;ILjava/io/Reader;Lcom/fasterxml/jackson/core/ObjectCodec;Lcom/fasterxml/jackson/core/sym/CharsToNameCanonicalizer;[CIIZ)V
  #135 = Methodref          #128.#572     // com/fasterxml/jackson/core/json/ByteSourceJsonBootstrapper."<init>":(Lcom/fasterxml/jackson/core/io/IOContext;[BII)V
  #136 = String             #573          // InputData source not (yet?) supported for this format (%s)
  #137 = Methodref          #128.#574     // com/fasterxml/jackson/core/json/ByteSourceJsonBootstrapper.skipUTF8BOM:(Ljava/io/DataInput;)I
  #138 = Class              #575          // com/fasterxml/jackson/core/json/UTF8DataInputJsonParser
  #139 = Methodref          #138.#576     // com/fasterxml/jackson/core/json/UTF8DataInputJsonParser."<init>":(Lcom/fasterxml/jackson/core/io/IOContext;ILjava/io/DataInput;Lcom/fasterxml/jackson/core/ObjectCodec;Lcom/fasterxml/jackson/core/sym/ByteQuadsCanonicalizer;I)V
  #140 = Class              #577          // com/fasterxml/jackson/core/json/WriterBasedJsonGenerator
  #141 = Methodref          #140.#578     // com/fasterxml/jackson/core/json/WriterBasedJsonGenerator."<init>":(Lcom/fasterxml/jackson/core/io/IOContext;ILcom/fasterxml/jackson/core/ObjectCodec;Ljava/io/Writer;C)V
  #142 = Methodref          #140.#579     // com/fasterxml/jackson/core/json/WriterBasedJsonGenerator.setHighestNonEscapedChar:(I)Lcom/fasterxml/jackson/core/JsonGenerator;
  #143 = Methodref          #140.#580     // com/fasterxml/jackson/core/json/WriterBasedJsonGenerator.setCharacterEscapes:(Lcom/fasterxml/jackson/core/io/CharacterEscapes;)Lcom/fasterxml/jackson/core/JsonGenerator;
  #144 = Methodref          #140.#581     // com/fasterxml/jackson/core/json/WriterBasedJsonGenerator.setRootValueSeparator:(Lcom/fasterxml/jackson/core/SerializableString;)Lcom/fasterxml/jackson/core/JsonGenerator;
  #145 = Class              #582          // com/fasterxml/jackson/core/json/UTF8JsonGenerator
  #146 = Methodref          #145.#583     // com/fasterxml/jackson/core/json/UTF8JsonGenerator."<init>":(Lcom/fasterxml/jackson/core/io/IOContext;ILcom/fasterxml/jackson/core/ObjectCodec;Ljava/io/OutputStream;C)V
  #147 = Methodref          #145.#579     // com/fasterxml/jackson/core/json/UTF8JsonGenerator.setHighestNonEscapedChar:(I)Lcom/fasterxml/jackson/core/JsonGenerator;
  #148 = Methodref          #145.#580     // com/fasterxml/jackson/core/json/UTF8JsonGenerator.setCharacterEscapes:(Lcom/fasterxml/jackson/core/io/CharacterEscapes;)Lcom/fasterxml/jackson/core/JsonGenerator;
  #149 = Methodref          #145.#581     // com/fasterxml/jackson/core/json/UTF8JsonGenerator.setRootValueSeparator:(Lcom/fasterxml/jackson/core/SerializableString;)Lcom/fasterxml/jackson/core/JsonGenerator;
  #150 = Class              #584          // com/fasterxml/jackson/core/io/UTF8Writer
  #151 = Methodref          #150.#585     // com/fasterxml/jackson/core/io/UTF8Writer."<init>":(Lcom/fasterxml/jackson/core/io/IOContext;Ljava/io/OutputStream;)V
  #152 = Class              #586          // java/io/OutputStreamWriter
  #153 = Methodref          #548.#587     // com/fasterxml/jackson/core/JsonEncoding.getJavaName:()Ljava/lang/String;
  #154 = Methodref          #152.#588     // java/io/OutputStreamWriter."<init>":(Ljava/io/OutputStream;Ljava/lang/String;)V
  #155 = Methodref          #526.#589     // com/fasterxml/jackson/core/io/InputDecorator.decorate:(Lcom/fasterxml/jackson/core/io/IOContext;Ljava/io/InputStream;)Ljava/io/InputStream;
  #156 = Methodref          #526.#590     // com/fasterxml/jackson/core/io/InputDecorator.decorate:(Lcom/fasterxml/jackson/core/io/IOContext;Ljava/io/Reader;)Ljava/io/Reader;
  #157 = Methodref          #526.#591     // com/fasterxml/jackson/core/io/InputDecorator.decorate:(Lcom/fasterxml/jackson/core/io/IOContext;Ljava/io/DataInput;)Ljava/io/DataInput;
  #158 = Methodref          #592.#593     // com/fasterxml/jackson/core/io/OutputDecorator.decorate:(Lcom/fasterxml/jackson/core/io/IOContext;Ljava/io/OutputStream;)Ljava/io/OutputStream;
  #159 = Methodref          #592.#594     // com/fasterxml/jackson/core/io/OutputDecorator.decorate:(Lcom/fasterxml/jackson/core/io/IOContext;Ljava/io/Writer;)Ljava/io/Writer;
  #160 = Fieldref           #183.#595     // com/fasterxml/jackson/core/JsonFactory$Feature.USE_THREAD_LOCAL_FOR_BUFFER_RECYCLING:Lcom/fasterxml/jackson/core/JsonFactory$Feature;
  #161 = Methodref          #183.#596     // com/fasterxml/jackson/core/JsonFactory$Feature.enabledIn:(I)Z
  #162 = Methodref          #597.#598     // com/fasterxml/jackson/core/util/BufferRecyclers.getBufferRecycler:()Lcom/fasterxml/jackson/core/util/BufferRecycler;
  #163 = Class              #599          // com/fasterxml/jackson/core/util/BufferRecycler
  #164 = Methodref          #163.#449     // com/fasterxml/jackson/core/util/BufferRecycler."<init>":()V
  #165 = Methodref          #600.#601     // com/fasterxml/jackson/core/io/ContentReference.unknown:()Lcom/fasterxml/jackson/core/io/ContentReference;
  #166 = Class              #602          // com/fasterxml/jackson/core/io/IOContext
  #167 = Methodref          #17.#603      // com/fasterxml/jackson/core/JsonFactory._getBufferRecycler:()Lcom/fasterxml/jackson/core/util/BufferRecycler;
  #168 = Methodref          #166.#604     // com/fasterxml/jackson/core/io/IOContext."<init>":(Lcom/fasterxml/jackson/core/util/BufferRecycler;Lcom/fasterxml/jackson/core/io/ContentReference;Z)V
  #169 = Methodref          #17.#605      // com/fasterxml/jackson/core/JsonFactory.canHandleBinaryNatively:()Z
  #170 = Methodref          #600.#606     // com/fasterxml/jackson/core/io/ContentReference.construct:(ZLjava/lang/Object;)Lcom/fasterxml/jackson/core/io/ContentReference;
  #171 = Methodref          #600.#607     // com/fasterxml/jackson/core/io/ContentReference.construct:(ZLjava/lang/Object;II)Lcom/fasterxml/jackson/core/io/ContentReference;
  #172 = Class              #608          // java/lang/UnsupportedOperationException
  #173 = Class              #609          // java/lang/Object
  #174 = Methodref          #497.#610     // java/lang/String.format:(Ljava/lang/String;[Ljava/lang/Object;)Ljava/lang/String;
  #175 = Methodref          #172.#492     // java/lang/UnsupportedOperationException."<init>":(Ljava/lang/String;)V
  #176 = Methodref          #183.#611     // com/fasterxml/jackson/core/JsonFactory$Feature.collectDefaults:()I
  #177 = Methodref          #304.#611     // com/fasterxml/jackson/core/JsonParser$Feature.collectDefaults:()I
  #178 = Methodref          #316.#611     // com/fasterxml/jackson/core/JsonGenerator$Feature.collectDefaults:()I
  #179 = Fieldref           #612.#613     // com/fasterxml/jackson/core/util/DefaultPrettyPrinter.DEFAULT_ROOT_VALUE_SEPARATOR:Lcom/fasterxml/jackson/core/io/SerializedString;
  #180 = Class              #614          // com/fasterxml/jackson/core/TokenStreamFactory
  #181 = Class              #615          // com/fasterxml/jackson/core/Versioned
  #182 = Class              #616          // java/io/Serializable
  #183 = Class              #617          // com/fasterxml/jackson/core/JsonFactory$Feature
  #184 = Utf8               Feature
  #185 = Utf8               InnerClasses
  #186 = Utf8               serialVersionUID
  #187 = Utf8               J
  #188 = Utf8               ConstantValue
  #189 = Long               2l
  #191 = Utf8               FORMAT_NAME_JSON
  #192 = Utf8               Ljava/lang/String;
  #193 = Utf8               DEFAULT_FACTORY_FEATURE_FLAGS
  #194 = Utf8               I
  #195 = Utf8               DEFAULT_PARSER_FEATURE_FLAGS
  #196 = Utf8               DEFAULT_GENERATOR_FEATURE_FLAGS
  #197 = Utf8               DEFAULT_ROOT_VALUE_SEPARATOR
  #198 = Utf8               Lcom/fasterxml/jackson/core/SerializableString;
  #199 = Utf8               DEFAULT_QUOTE_CHAR
  #200 = Utf8               C
  #201 = Integer            34
  #202 = Utf8               _rootCharSymbols
  #203 = Utf8               Lcom/fasterxml/jackson/core/sym/CharsToNameCanonicalizer;
  #204 = Utf8               _byteSymbolCanonicalizer
  #205 = Utf8               Lcom/fasterxml/jackson/core/sym/ByteQuadsCanonicalizer;
  #206 = Utf8               _factoryFeatures
  #207 = Utf8               _parserFeatures
  #208 = Utf8               _generatorFeatures
  #209 = Utf8               _objectCodec
  #210 = Utf8               Lcom/fasterxml/jackson/core/ObjectCodec;
  #211 = Utf8               _characterEscapes
  #212 = Utf8               Lcom/fasterxml/jackson/core/io/CharacterEscapes;
  #213 = Utf8               _inputDecorator
  #214 = Utf8               Lcom/fasterxml/jackson/core/io/InputDecorator;
  #215 = Utf8               _outputDecorator
  #216 = Utf8               Lcom/fasterxml/jackson/core/io/OutputDecorator;
  #217 = Utf8               _rootValueSeparator
  #218 = Utf8               _maximumNonEscapedChar
  #219 = Utf8               _quoteChar
  #220 = Utf8               <init>
  #221 = Utf8               ()V
  #222 = Utf8               Code
  #223 = Utf8               LineNumberTable
  #224 = Utf8               LocalVariableTable
  #225 = Utf8               this
  #226 = Utf8               Lcom/fasterxml/jackson/core/JsonFactory;
  #227 = Utf8               (Lcom/fasterxml/jackson/core/ObjectCodec;)V
  #228 = Utf8               oc
  #229 = Utf8               (Lcom/fasterxml/jackson/core/JsonFactory;Lcom/fasterxml/jackson/core/ObjectCodec;)V
  #230 = Utf8               src
  #231 = Utf8               codec
  #232 = Utf8               (Lcom/fasterxml/jackson/core/JsonFactoryBuilder;)V
  #233 = Utf8               b
  #234 = Utf8               Lcom/fasterxml/jackson/core/JsonFactoryBuilder;
  #235 = Utf8               (Lcom/fasterxml/jackson/core/TSFBuilder;Z)V
  #236 = Utf8               Lcom/fasterxml/jackson/core/TSFBuilder;
  #237 = Utf8               bogus
  #238 = Utf8               Z
  #239 = Utf8               LocalVariableTypeTable
  #240 = Utf8               Lcom/fasterxml/jackson/core/TSFBuilder<**>;
  #241 = Utf8               Signature
  #242 = Utf8               (Lcom/fasterxml/jackson/core/TSFBuilder<**>;Z)V
  #243 = Utf8               rebuild
  #244 = Utf8               ()Lcom/fasterxml/jackson/core/TSFBuilder;
  #245 = Utf8               ()Lcom/fasterxml/jackson/core/TSFBuilder<**>;
  #246 = Utf8               builder
  #247 = Utf8               copy
  #248 = Utf8               ()Lcom/fasterxml/jackson/core/JsonFactory;
  #249 = Utf8               _checkInvalidCopy
  #250 = Utf8               (Ljava/lang/Class;)V
  #251 = Utf8               exp
  #252 = Utf8               Ljava/lang/Class;
  #253 = Utf8               Ljava/lang/Class<*>;
  #254 = Utf8               StackMapTable
  #255 = Utf8               (Ljava/lang/Class<*>;)V
  #256 = Utf8               readResolve
  #257 = Utf8               ()Ljava/lang/Object;
  #258 = Utf8               requiresPropertyOrdering
  #259 = Utf8               ()Z
  #260 = Utf8               canHandleBinaryNatively
  #261 = Utf8               canUseCharArrays
  #262 = Utf8               canParseAsync
  #263 = Utf8               getFormatReadFeatureType
  #264 = Utf8               ()Ljava/lang/Class;
  #265 = Utf8               ()Ljava/lang/Class<+Lcom/fasterxml/jackson/core/FormatFeature;>;
  #266 = Utf8               getFormatWriteFeatureType
  #267 = Utf8               canUseSchema
  #268 = Utf8               (Lcom/fasterxml/jackson/core/FormatSchema;)Z
  #269 = Utf8               schema
  #270 = Utf8               Lcom/fasterxml/jackson/core/FormatSchema;
  #271 = Utf8               ourFormat
  #272 = Class              #618          // java/lang/String
  #273 = Utf8               getFormatName
  #274 = Utf8               ()Ljava/lang/String;
  #275 = Utf8               hasFormat
  #276 = Utf8               (Lcom/fasterxml/jackson/core/format/InputAccessor;)Lcom/fasterxml/jackson/core/format/MatchStrength;
  #277 = Utf8               acc
  #278 = Utf8               Lcom/fasterxml/jackson/core/format/InputAccessor;
  #279 = Utf8               Exceptions
  #280 = Class              #619          // java/io/IOException
  #281 = Utf8               requiresCustomCodec
  #282 = Utf8               hasJSONFormat
  #283 = Utf8               version
  #284 = Utf8               ()Lcom/fasterxml/jackson/core/Version;
  #285 = Utf8               configure
  #286 = Utf8               (Lcom/fasterxml/jackson/core/JsonFactory$Feature;Z)Lcom/fasterxml/jackson/core/JsonFactory;
  #287 = Utf8               f
  #288 = Utf8               Lcom/fasterxml/jackson/core/JsonFactory$Feature;
  #289 = Utf8               state
  #290 = Class              #465          // com/fasterxml/jackson/core/JsonFactory
  #291 = Utf8               Deprecated
  #292 = Utf8               RuntimeVisibleAnnotations
  #293 = Utf8               Ljava/lang/Deprecated;
  #294 = Utf8               enable
  #295 = Utf8               (Lcom/fasterxml/jackson/core/JsonFactory$Feature;)Lcom/fasterxml/jackson/core/JsonFactory;
  #296 = Utf8               disable
  #297 = Utf8               isEnabled
  #298 = Utf8               (Lcom/fasterxml/jackson/core/JsonFactory$Feature;)Z
  #299 = Utf8               getParserFeatures
  #300 = Utf8               ()I
  #301 = Utf8               getGeneratorFeatures
  #302 = Utf8               getFormatParserFeatures
  #303 = Utf8               getFormatGeneratorFeatures
  #304 = Class              #621          // com/fasterxml/jackson/core/JsonParser$Feature
  #305 = Utf8               (Lcom/fasterxml/jackson/core/JsonParser$Feature;Z)Lcom/fasterxml/jackson/core/JsonFactory;
  #306 = Utf8               Lcom/fasterxml/jackson/core/JsonParser$Feature;
  #307 = Utf8               (Lcom/fasterxml/jackson/core/JsonParser$Feature;)Lcom/fasterxml/jackson/core/JsonFactory;
  #308 = Utf8               (Lcom/fasterxml/jackson/core/JsonParser$Feature;)Z
  #309 = Utf8               (Lcom/fasterxml/jackson/core/StreamReadFeature;)Z
  #310 = Utf8               Lcom/fasterxml/jackson/core/StreamReadFeature;
  #311 = Utf8               getInputDecorator
  #312 = Utf8               ()Lcom/fasterxml/jackson/core/io/InputDecorator;
  #313 = Utf8               setInputDecorator
  #314 = Utf8               (Lcom/fasterxml/jackson/core/io/InputDecorator;)Lcom/fasterxml/jackson/core/JsonFactory;
  #315 = Utf8               d
  #316 = Class              #623          // com/fasterxml/jackson/core/JsonGenerator$Feature
  #317 = Utf8               (Lcom/fasterxml/jackson/core/JsonGenerator$Feature;Z)Lcom/fasterxml/jackson/core/JsonFactory;
  #318 = Utf8               Lcom/fasterxml/jackson/core/JsonGenerator$Feature;
  #319 = Utf8               (Lcom/fasterxml/jackson/core/JsonGenerator$Feature;)Lcom/fasterxml/jackson/core/JsonFactory;
  #320 = Utf8               (Lcom/fasterxml/jackson/core/JsonGenerator$Feature;)Z
  #321 = Utf8               (Lcom/fasterxml/jackson/core/StreamWriteFeature;)Z
  #322 = Utf8               Lcom/fasterxml/jackson/core/StreamWriteFeature;
  #323 = Utf8               getCharacterEscapes
  #324 = Utf8               ()Lcom/fasterxml/jackson/core/io/CharacterEscapes;
  #325 = Utf8               setCharacterEscapes
  #326 = Utf8               (Lcom/fasterxml/jackson/core/io/CharacterEscapes;)Lcom/fasterxml/jackson/core/JsonFactory;
  #327 = Utf8               esc
  #328 = Utf8               getOutputDecorator
  #329 = Utf8               ()Lcom/fasterxml/jackson/core/io/OutputDecorator;
  #330 = Utf8               setOutputDecorator
  #331 = Utf8               (Lcom/fasterxml/jackson/core/io/OutputDecorator;)Lcom/fasterxml/jackson/core/JsonFactory;
  #332 = Utf8               setRootValueSeparator
  #333 = Utf8               (Ljava/lang/String;)Lcom/fasterxml/jackson/core/JsonFactory;
  #334 = Utf8               sep
  #335 = Class              #514          // com/fasterxml/jackson/core/io/SerializedString
  #336 = Utf8               getRootValueSeparator
  #337 = Utf8               setCodec
  #338 = Utf8               (Lcom/fasterxml/jackson/core/ObjectCodec;)Lcom/fasterxml/jackson/core/JsonFactory;
  #339 = Utf8               getCodec
  #340 = Utf8               ()Lcom/fasterxml/jackson/core/ObjectCodec;
  #341 = Utf8               createParser
  #342 = Utf8               (Ljava/io/File;)Lcom/fasterxml/jackson/core/JsonParser;
  #343 = Utf8               Ljava/io/File;
  #344 = Utf8               ctxt
  #345 = Utf8               Lcom/fasterxml/jackson/core/io/IOContext;
  #346 = Utf8               in
  #347 = Utf8               Ljava/io/InputStream;
  #348 = Class              #624          // com/fasterxml/jackson/core/JsonParseException
  #349 = Utf8               (Ljava/net/URL;)Lcom/fasterxml/jackson/core/JsonParser;
  #350 = Utf8               url
  #351 = Utf8               Ljava/net/URL;
  #352 = Utf8               (Ljava/io/InputStream;)Lcom/fasterxml/jackson/core/JsonParser;
  #353 = Utf8               (Ljava/io/Reader;)Lcom/fasterxml/jackson/core/JsonParser;
  #354 = Utf8               r
  #355 = Utf8               Ljava/io/Reader;
  #356 = Utf8               ([B)Lcom/fasterxml/jackson/core/JsonParser;
  #357 = Utf8               data
  #358 = Utf8               [B
  #359 = Class              #602          // com/fasterxml/jackson/core/io/IOContext
  #360 = Utf8               ([BII)Lcom/fasterxml/jackson/core/JsonParser;
  #361 = Utf8               offset
  #362 = Utf8               len
  #363 = Utf8               (Ljava/lang/String;)Lcom/fasterxml/jackson/core/JsonParser;
  #364 = Utf8               content
  #365 = Utf8               strLen
  #366 = Utf8               buf
  #367 = Utf8               [C
  #368 = Utf8               ([C)Lcom/fasterxml/jackson/core/JsonParser;
  #369 = Utf8               ([CII)Lcom/fasterxml/jackson/core/JsonParser;
  #370 = Utf8               (Ljava/io/DataInput;)Lcom/fasterxml/jackson/core/JsonParser;
  #371 = Utf8               Ljava/io/DataInput;
  #372 = Utf8               createNonBlockingByteArrayParser
  #373 = Utf8               ()Lcom/fasterxml/jackson/core/JsonParser;
  #374 = Utf8               can
  #375 = Utf8               createGenerator
  #376 = Utf8               (Ljava/io/OutputStream;Lcom/fasterxml/jackson/core/JsonEncoding;)Lcom/fasterxml/jackson/core/JsonGenerator;
  #377 = Utf8               out
  #378 = Utf8               Ljava/io/OutputStream;
  #379 = Utf8               enc
  #380 = Utf8               Lcom/fasterxml/jackson/core/JsonEncoding;
  #381 = Utf8               w
  #382 = Utf8               Ljava/io/Writer;
  #383 = Utf8               (Ljava/io/OutputStream;)Lcom/fasterxml/jackson/core/JsonGenerator;
  #384 = Utf8               (Ljava/io/Writer;)Lcom/fasterxml/jackson/core/JsonGenerator;
  #385 = Utf8               (Ljava/io/File;Lcom/fasterxml/jackson/core/JsonEncoding;)Lcom/fasterxml/jackson/core/JsonGenerator;
  #386 = Class              #625          // java/io/OutputStream
  #387 = Utf8               (Ljava/io/DataOutput;Lcom/fasterxml/jackson/core/JsonEncoding;)Lcom/fasterxml/jackson/core/JsonGenerator;
  #388 = Utf8               Ljava/io/DataOutput;
  #389 = Utf8               (Ljava/io/DataOutput;)Lcom/fasterxml/jackson/core/JsonGenerator;
  #390 = Utf8               createJsonParser
  #391 = Utf8               createJsonGenerator
  #392 = Utf8               _createParser
  #393 = Utf8               (Ljava/io/InputStream;Lcom/fasterxml/jackson/core/io/IOContext;)Lcom/fasterxml/jackson/core/JsonParser;
  #394 = Utf8               (Ljava/io/Reader;Lcom/fasterxml/jackson/core/io/IOContext;)Lcom/fasterxml/jackson/core/JsonParser;
  #395 = Utf8               ([CIILcom/fasterxml/jackson/core/io/IOContext;Z)Lcom/fasterxml/jackson/core/JsonParser;
  #396 = Utf8               recyclable
  #397 = Utf8               ([BIILcom/fasterxml/jackson/core/io/IOContext;)Lcom/fasterxml/jackson/core/JsonParser;
  #398 = Utf8               (Ljava/io/DataInput;Lcom/fasterxml/jackson/core/io/IOContext;)Lcom/fasterxml/jackson/core/JsonParser;
  #399 = Utf8               input
  #400 = Utf8               firstByte
  #401 = Utf8               _createGenerator
  #402 = Utf8               (Ljava/io/Writer;Lcom/fasterxml/jackson/core/io/IOContext;)Lcom/fasterxml/jackson/core/JsonGenerator;
  #403 = Utf8               gen
  #404 = Utf8               Lcom/fasterxml/jackson/core/json/WriterBasedJsonGenerator;
  #405 = Utf8               rootSep
  #406 = Class              #577          // com/fasterxml/jackson/core/json/WriterBasedJsonGenerator
  #407 = Class              #626          // com/fasterxml/jackson/core/SerializableString
  #408 = Utf8               _createUTF8Generator
  #409 = Utf8               (Ljava/io/OutputStream;Lcom/fasterxml/jackson/core/io/IOContext;)Lcom/fasterxml/jackson/core/JsonGenerator;
  #410 = Utf8               Lcom/fasterxml/jackson/core/json/UTF8JsonGenerator;
  #411 = Class              #582          // com/fasterxml/jackson/core/json/UTF8JsonGenerator
  #412 = Utf8               _createWriter
  #413 = Utf8               (Ljava/io/OutputStream;Lcom/fasterxml/jackson/core/JsonEncoding;Lcom/fasterxml/jackson/core/io/IOContext;)Ljava/io/Writer;
  #414 = Utf8               _decorate
  #415 = Utf8               (Ljava/io/InputStream;Lcom/fasterxml/jackson/core/io/IOContext;)Ljava/io/InputStream;
  #416 = Utf8               in2
  #417 = Utf8               (Ljava/io/Reader;Lcom/fasterxml/jackson/core/io/IOContext;)Ljava/io/Reader;
  #418 = Utf8               (Ljava/io/DataInput;Lcom/fasterxml/jackson/core/io/IOContext;)Ljava/io/DataInput;
  #419 = Utf8               (Ljava/io/OutputStream;Lcom/fasterxml/jackson/core/io/IOContext;)Ljava/io/OutputStream;
  #420 = Utf8               out2
  #421 = Utf8               (Ljava/io/Writer;Lcom/fasterxml/jackson/core/io/IOContext;)Ljava/io/Writer;
  #422 = Utf8               _getBufferRecycler
  #423 = Utf8               ()Lcom/fasterxml/jackson/core/util/BufferRecycler;
  #424 = Utf8               _createContext
  #425 = Utf8               (Lcom/fasterxml/jackson/core/io/ContentReference;Z)Lcom/fasterxml/jackson/core/io/IOContext;
  #426 = Utf8               contentRef
  #427 = Utf8               Lcom/fasterxml/jackson/core/io/ContentReference;
  #428 = Utf8               resourceManaged
  #429 = Utf8               (Ljava/lang/Object;Z)Lcom/fasterxml/jackson/core/io/IOContext;
  #430 = Utf8               rawContentRef
  #431 = Utf8               Ljava/lang/Object;
  #432 = Utf8               _createNonBlockingContext
  #433 = Utf8               (Ljava/lang/Object;)Lcom/fasterxml/jackson/core/io/IOContext;
  #434 = Utf8               srcRef
  #435 = Utf8               _createContentReference
  #436 = Utf8               (Ljava/lang/Object;)Lcom/fasterxml/jackson/core/io/ContentReference;
  #437 = Utf8               contentAccessor
  #438 = Utf8               (Ljava/lang/Object;II)Lcom/fasterxml/jackson/core/io/ContentReference;
  #439 = Utf8               length
  #440 = Utf8               _requireJSONFactory
  #441 = Utf8               (Ljava/lang/String;)V
  #442 = Utf8               msg
  #443 = Utf8               _isJSONFactory
  #444 = Utf8               <clinit>
  #445 = Utf8               SourceFile
  #446 = Utf8               JsonFactory.java
  #447 = Utf8               com/fasterxml/jackson/core/ObjectCodec
  #448 = NameAndType        #220:#227     // "<init>":(Lcom/fasterxml/jackson/core/ObjectCodec;)V
  #449 = NameAndType        #220:#221     // "<init>":()V
  #450 = Class              #627          // com/fasterxml/jackson/core/sym/CharsToNameCanonicalizer
  #451 = NameAndType        #628:#629     // createRoot:()Lcom/fasterxml/jackson/core/sym/CharsToNameCanonicalizer;
  #452 = NameAndType        #202:#203     // _rootCharSymbols:Lcom/fasterxml/jackson/core/sym/CharsToNameCanonicalizer;
  #453 = Class              #630          // com/fasterxml/jackson/core/sym/ByteQuadsCanonicalizer
  #454 = NameAndType        #628:#631     // createRoot:()Lcom/fasterxml/jackson/core/sym/ByteQuadsCanonicalizer;
  #455 = NameAndType        #204:#205     // _byteSymbolCanonicalizer:Lcom/fasterxml/jackson/core/sym/ByteQuadsCanonicalizer;
  #456 = NameAndType        #193:#194     // DEFAULT_FACTORY_FEATURE_FLAGS:I
  #457 = NameAndType        #206:#194     // _factoryFeatures:I
  #458 = NameAndType        #195:#194     // DEFAULT_PARSER_FEATURE_FLAGS:I
  #459 = NameAndType        #207:#194     // _parserFeatures:I
  #460 = NameAndType        #196:#194     // DEFAULT_GENERATOR_FEATURE_FLAGS:I
  #461 = NameAndType        #208:#194     // _generatorFeatures:I
  #462 = NameAndType        #197:#198     // DEFAULT_ROOT_VALUE_SEPARATOR:Lcom/fasterxml/jackson/core/SerializableString;
  #463 = NameAndType        #217:#198     // _rootValueSeparator:Lcom/fasterxml/jackson/core/SerializableString;
  #464 = NameAndType        #209:#210     // _objectCodec:Lcom/fasterxml/jackson/core/ObjectCodec;
  #465 = Utf8               com/fasterxml/jackson/core/JsonFactory
  #466 = NameAndType        #219:#200     // _quoteChar:C
  #467 = NameAndType        #213:#214     // _inputDecorator:Lcom/fasterxml/jackson/core/io/InputDecorator;
  #468 = NameAndType        #215:#216     // _outputDecorator:Lcom/fasterxml/jackson/core/io/OutputDecorator;
  #469 = NameAndType        #211:#212     // _characterEscapes:Lcom/fasterxml/jackson/core/io/CharacterEscapes;
  #470 = NameAndType        #218:#194     // _maximumNonEscapedChar:I
  #471 = NameAndType        #632:#194     // _streamReadFeatures:I
  #472 = NameAndType        #633:#194     // _streamWriteFeatures:I
  #473 = Class              #634          // com/fasterxml/jackson/core/TSFBuilder
  #474 = Utf8               Factory implementation for format (%s) MUST override `rebuild()` method
  #475 = NameAndType        #440:#441     // _requireJSONFactory:(Ljava/lang/String;)V
  #476 = Utf8               com/fasterxml/jackson/core/JsonFactoryBuilder
  #477 = NameAndType        #220:#635     // "<init>":(Lcom/fasterxml/jackson/core/JsonFactory;)V
  #478 = NameAndType        #249:#250     // _checkInvalidCopy:(Ljava/lang/Class;)V
  #479 = NameAndType        #220:#229     // "<init>":(Lcom/fasterxml/jackson/core/JsonFactory;Lcom/fasterxml/jackson/core/ObjectCodec;)V
  #480 = NameAndType        #636:#264     // getClass:()Ljava/lang/Class;
  #481 = Utf8               java/lang/IllegalStateException
  #482 = Utf8               java/lang/StringBuilder
  #483 = Utf8               Failed copy():
  #484 = NameAndType        #637:#638     // append:(Ljava/lang/String;)Ljava/lang/StringBuilder;
  #485 = Class              #639          // java/lang/Class
  #486 = NameAndType        #640:#274     // getName:()Ljava/lang/String;
  #487 = Utf8                (version:
  #488 = NameAndType        #283:#284     // version:()Lcom/fasterxml/jackson/core/Version;
  #489 = NameAndType        #637:#641     // append:(Ljava/lang/Object;)Ljava/lang/StringBuilder;
  #490 = Utf8               ) does not override copy(); it has to
  #491 = NameAndType        #642:#274     // toString:()Ljava/lang/String;
  #492 = NameAndType        #220:#441     // "<init>":(Ljava/lang/String;)V
  #493 = NameAndType        #443:#259     // _isJSONFactory:()Z
  #494 = NameAndType        #273:#274     // getFormatName:()Ljava/lang/String;
  #495 = Class              #643          // com/fasterxml/jackson/core/FormatSchema
  #496 = NameAndType        #644:#274     // getSchemaType:()Ljava/lang/String;
  #497 = Class              #618          // java/lang/String
  #498 = NameAndType        #645:#646     // equals:(Ljava/lang/Object;)Z
  #499 = Utf8               JSON
  #500 = NameAndType        #282:#276     // hasJSONFormat:(Lcom/fasterxml/jackson/core/format/InputAccessor;)Lcom/fasterxml/jackson/core/format/MatchStrength;
  #501 = Class              #647          // com/fasterxml/jackson/core/json/PackageVersion
  #502 = NameAndType        #648:#649     // VERSION:Lcom/fasterxml/jackson/core/Version;
  #503 = NameAndType        #294:#295     // enable:(Lcom/fasterxml/jackson/core/JsonFactory$Feature;)Lcom/fasterxml/jackson/core/JsonFactory;
  #504 = NameAndType        #296:#295     // disable:(Lcom/fasterxml/jackson/core/JsonFactory$Feature;)Lcom/fasterxml/jackson/core/JsonFactory;
  #505 = NameAndType        #650:#300     // getMask:()I
  #506 = NameAndType        #294:#307     // enable:(Lcom/fasterxml/jackson/core/JsonParser$Feature;)Lcom/fasterxml/jackson/core/JsonFactory;
  #507 = NameAndType        #296:#307     // disable:(Lcom/fasterxml/jackson/core/JsonParser$Feature;)Lcom/fasterxml/jackson/core/JsonFactory;
  #508 = Class              #651          // com/fasterxml/jackson/core/StreamReadFeature
  #509 = NameAndType        #652:#653     // mappedFeature:()Lcom/fasterxml/jackson/core/JsonParser$Feature;
  #510 = NameAndType        #294:#319     // enable:(Lcom/fasterxml/jackson/core/JsonGenerator$Feature;)Lcom/fasterxml/jackson/core/JsonFactory;
  #511 = NameAndType        #296:#319     // disable:(Lcom/fasterxml/jackson/core/JsonGenerator$Feature;)Lcom/fasterxml/jackson/core/JsonFactory;
  #512 = Class              #654          // com/fasterxml/jackson/core/StreamWriteFeature
  #513 = NameAndType        #652:#655     // mappedFeature:()Lcom/fasterxml/jackson/core/JsonGenerator$Feature;
  #514 = Utf8               com/fasterxml/jackson/core/io/SerializedString
  #515 = Class              #626          // com/fasterxml/jackson/core/SerializableString
  #516 = NameAndType        #656:#274     // getValue:()Ljava/lang/String;
  #517 = NameAndType        #435:#436     // _createContentReference:(Ljava/lang/Object;)Lcom/fasterxml/jackson/core/io/ContentReference;
  #518 = NameAndType        #424:#425     // _createContext:(Lcom/fasterxml/jackson/core/io/ContentReference;Z)Lcom/fasterxml/jackson/core/io/IOContext;
  #519 = Utf8               java/io/FileInputStream
  #520 = NameAndType        #220:#657     // "<init>":(Ljava/io/File;)V
  #521 = NameAndType        #414:#415     // _decorate:(Ljava/io/InputStream;Lcom/fasterxml/jackson/core/io/IOContext;)Ljava/io/InputStream;
  #522 = NameAndType        #392:#393     // _createParser:(Ljava/io/InputStream;Lcom/fasterxml/jackson/core/io/IOContext;)Lcom/fasterxml/jackson/core/JsonParser;
  #523 = NameAndType        #658:#659     // _optimizedStreamFromURL:(Ljava/net/URL;)Ljava/io/InputStream;
  #524 = NameAndType        #414:#417     // _decorate:(Ljava/io/Reader;Lcom/fasterxml/jackson/core/io/IOContext;)Ljava/io/Reader;
  #525 = NameAndType        #392:#394     // _createParser:(Ljava/io/Reader;Lcom/fasterxml/jackson/core/io/IOContext;)Lcom/fasterxml/jackson/core/JsonParser;
  #526 = Class              #660          // com/fasterxml/jackson/core/io/InputDecorator
  #527 = NameAndType        #661:#662     // decorate:(Lcom/fasterxml/jackson/core/io/IOContext;[BII)Ljava/io/InputStream;
  #528 = NameAndType        #392:#397     // _createParser:([BIILcom/fasterxml/jackson/core/io/IOContext;)Lcom/fasterxml/jackson/core/JsonParser;
  #529 = NameAndType        #435:#438     // _createContentReference:(Ljava/lang/Object;II)Lcom/fasterxml/jackson/core/io/ContentReference;
  #530 = NameAndType        #439:#300     // length:()I
  #531 = NameAndType        #261:#259     // canUseCharArrays:()Z
  #532 = Utf8               java/io/StringReader
  #533 = NameAndType        #341:#353     // createParser:(Ljava/io/Reader;)Lcom/fasterxml/jackson/core/JsonParser;
  #534 = NameAndType        #663:#664     // allocTokenBuffer:(I)[C
  #535 = NameAndType        #665:#666     // getChars:(II[CI)V
  #536 = NameAndType        #392:#395     // _createParser:([CIILcom/fasterxml/jackson/core/io/IOContext;Z)Lcom/fasterxml/jackson/core/JsonParser;
  #537 = NameAndType        #341:#369     // createParser:([CII)Lcom/fasterxml/jackson/core/JsonParser;
  #538 = Utf8               java/io/CharArrayReader
  #539 = NameAndType        #220:#667     // "<init>":([CII)V
  #540 = NameAndType        #414:#418     // _decorate:(Ljava/io/DataInput;Lcom/fasterxml/jackson/core/io/IOContext;)Ljava/io/DataInput;
  #541 = NameAndType        #392:#398     // _createParser:(Ljava/io/DataInput;Lcom/fasterxml/jackson/core/io/IOContext;)Lcom/fasterxml/jackson/core/JsonParser;
  #542 = Utf8               Non-blocking source not (yet?) supported for this format (%s)
  #543 = NameAndType        #432:#433     // _createNonBlockingContext:(Ljava/lang/Object;)Lcom/fasterxml/jackson/core/io/IOContext;
  #544 = NameAndType        #668:#669     // makeChild:(I)Lcom/fasterxml/jackson/core/sym/ByteQuadsCanonicalizer;
  #545 = Utf8               com/fasterxml/jackson/core/json/async/NonBlockingJsonParser
  #546 = NameAndType        #220:#670     // "<init>":(Lcom/fasterxml/jackson/core/io/IOContext;ILcom/fasterxml/jackson/core/sym/ByteQuadsCanonicalizer;)V
  #547 = NameAndType        #671:#672     // setEncoding:(Lcom/fasterxml/jackson/core/JsonEncoding;)V
  #548 = Class              #673          // com/fasterxml/jackson/core/JsonEncoding
  #549 = NameAndType        #674:#380     // UTF8:Lcom/fasterxml/jackson/core/JsonEncoding;
  #550 = NameAndType        #414:#419     // _decorate:(Ljava/io/OutputStream;Lcom/fasterxml/jackson/core/io/IOContext;)Ljava/io/OutputStream;
  #551 = NameAndType        #408:#409     // _createUTF8Generator:(Ljava/io/OutputStream;Lcom/fasterxml/jackson/core/io/IOContext;)Lcom/fasterxml/jackson/core/JsonGenerator;
  #552 = NameAndType        #412:#413     // _createWriter:(Ljava/io/OutputStream;Lcom/fasterxml/jackson/core/JsonEncoding;Lcom/fasterxml/jackson/core/io/IOContext;)Ljava/io/Writer;
  #553 = NameAndType        #414:#421     // _decorate:(Ljava/io/Writer;Lcom/fasterxml/jackson/core/io/IOContext;)Ljava/io/Writer;
  #554 = NameAndType        #401:#402     // _createGenerator:(Ljava/io/Writer;Lcom/fasterxml/jackson/core/io/IOContext;)Lcom/fasterxml/jackson/core/JsonGenerator;
  #555 = NameAndType        #375:#376     // createGenerator:(Ljava/io/OutputStream;Lcom/fasterxml/jackson/core/JsonEncoding;)Lcom/fasterxml/jackson/core/JsonGenerator;
  #556 = Utf8               java/io/FileOutputStream
  #557 = NameAndType        #675:#676     // _createDataOutputWrapper:(Ljava/io/DataOutput;)Ljava/io/OutputStream;
  #558 = NameAndType        #341:#342     // createParser:(Ljava/io/File;)Lcom/fasterxml/jackson/core/JsonParser;
  #559 = NameAndType        #341:#349     // createParser:(Ljava/net/URL;)Lcom/fasterxml/jackson/core/JsonParser;
  #560 = NameAndType        #341:#352     // createParser:(Ljava/io/InputStream;)Lcom/fasterxml/jackson/core/JsonParser;
  #561 = NameAndType        #341:#356     // createParser:([B)Lcom/fasterxml/jackson/core/JsonParser;
  #562 = NameAndType        #341:#360     // createParser:([BII)Lcom/fasterxml/jackson/core/JsonParser;
  #563 = NameAndType        #341:#363     // createParser:(Ljava/lang/String;)Lcom/fasterxml/jackson/core/JsonParser;
  #564 = NameAndType        #375:#384     // createGenerator:(Ljava/io/Writer;)Lcom/fasterxml/jackson/core/JsonGenerator;
  #565 = Utf8               com/fasterxml/jackson/core/json/ByteSourceJsonBootstrapper
  #566 = NameAndType        #220:#677     // "<init>":(Lcom/fasterxml/jackson/core/io/IOContext;Ljava/io/InputStream;)V
  #567 = NameAndType        #678:#679     // constructParser:(ILcom/fasterxml/jackson/core/ObjectCodec;Lcom/fasterxml/jackson/core/sym/ByteQuadsCanonicalizer;Lcom/fasterxml/jackson/core/sym/CharsToNameCanonicalizer;I)Lcom/fasterxml/jackson/core/JsonParser;
  #568 = Utf8               com/fasterxml/jackson/core/json/ReaderBasedJsonParser
  #569 = NameAndType        #668:#680     // makeChild:(I)Lcom/fasterxml/jackson/core/sym/CharsToNameCanonicalizer;
  #570 = NameAndType        #220:#681     // "<init>":(Lcom/fasterxml/jackson/core/io/IOContext;ILjava/io/Reader;Lcom/fasterxml/jackson/core/ObjectCodec;Lcom/fasterxml/jackson/core/sym/CharsToNameCanonicalizer;)V
  #571 = NameAndType        #220:#682     // "<init>":(Lcom/fasterxml/jackson/core/io/IOContext;ILjava/io/Reader;Lcom/fasterxml/jackson/core/ObjectCodec;Lcom/fasterxml/jackson/core/sym/CharsToNameCanonicalizer;[CIIZ)V
  #572 = NameAndType        #220:#683     // "<init>":(Lcom/fasterxml/jackson/core/io/IOContext;[BII)V
  #573 = Utf8               InputData source not (yet?) supported for this format (%s)
  #574 = NameAndType        #684:#685     // skipUTF8BOM:(Ljava/io/DataInput;)I
  #575 = Utf8               com/fasterxml/jackson/core/json/UTF8DataInputJsonParser
  #576 = NameAndType        #220:#686     // "<init>":(Lcom/fasterxml/jackson/core/io/IOContext;ILjava/io/DataInput;Lcom/fasterxml/jackson/core/ObjectCodec;Lcom/fasterxml/jackson/core/sym/ByteQuadsCanonicalizer;I)V
  #577 = Utf8               com/fasterxml/jackson/core/json/WriterBasedJsonGenerator
  #578 = NameAndType        #220:#687     // "<init>":(Lcom/fasterxml/jackson/core/io/IOContext;ILcom/fasterxml/jackson/core/ObjectCodec;Ljava/io/Writer;C)V
  #579 = NameAndType        #688:#689     // setHighestNonEscapedChar:(I)Lcom/fasterxml/jackson/core/JsonGenerator;
  #580 = NameAndType        #325:#690     // setCharacterEscapes:(Lcom/fasterxml/jackson/core/io/CharacterEscapes;)Lcom/fasterxml/jackson/core/JsonGenerator;
  #581 = NameAndType        #332:#691     // setRootValueSeparator:(Lcom/fasterxml/jackson/core/SerializableString;)Lcom/fasterxml/jackson/core/JsonGenerator;
  #582 = Utf8               com/fasterxml/jackson/core/json/UTF8JsonGenerator
  #583 = NameAndType        #220:#692     // "<init>":(Lcom/fasterxml/jackson/core/io/IOContext;ILcom/fasterxml/jackson/core/ObjectCodec;Ljava/io/OutputStream;C)V
  #584 = Utf8               com/fasterxml/jackson/core/io/UTF8Writer
  #585 = NameAndType        #220:#693     // "<init>":(Lcom/fasterxml/jackson/core/io/IOContext;Ljava/io/OutputStream;)V
  #586 = Utf8               java/io/OutputStreamWriter
  #587 = NameAndType        #694:#274     // getJavaName:()Ljava/lang/String;
  #588 = NameAndType        #220:#695     // "<init>":(Ljava/io/OutputStream;Ljava/lang/String;)V
  #589 = NameAndType        #661:#696     // decorate:(Lcom/fasterxml/jackson/core/io/IOContext;Ljava/io/InputStream;)Ljava/io/InputStream;
  #590 = NameAndType        #661:#697     // decorate:(Lcom/fasterxml/jackson/core/io/IOContext;Ljava/io/Reader;)Ljava/io/Reader;
  #591 = NameAndType        #661:#698     // decorate:(Lcom/fasterxml/jackson/core/io/IOContext;Ljava/io/DataInput;)Ljava/io/DataInput;
  #592 = Class              #699          // com/fasterxml/jackson/core/io/OutputDecorator
  #593 = NameAndType        #661:#700     // decorate:(Lcom/fasterxml/jackson/core/io/IOContext;Ljava/io/OutputStream;)Ljava/io/OutputStream;
  #594 = NameAndType        #661:#701     // decorate:(Lcom/fasterxml/jackson/core/io/IOContext;Ljava/io/Writer;)Ljava/io/Writer;
  #595 = NameAndType        #702:#288     // USE_THREAD_LOCAL_FOR_BUFFER_RECYCLING:Lcom/fasterxml/jackson/core/JsonFactory$Feature;
  #596 = NameAndType        #703:#704     // enabledIn:(I)Z
  #597 = Class              #705          // com/fasterxml/jackson/core/util/BufferRecyclers
  #598 = NameAndType        #706:#423     // getBufferRecycler:()Lcom/fasterxml/jackson/core/util/BufferRecycler;
  #599 = Utf8               com/fasterxml/jackson/core/util/BufferRecycler
  #600 = Class              #707          // com/fasterxml/jackson/core/io/ContentReference
  #601 = NameAndType        #708:#709     // unknown:()Lcom/fasterxml/jackson/core/io/ContentReference;
  #602 = Utf8               com/fasterxml/jackson/core/io/IOContext
  #603 = NameAndType        #422:#423     // _getBufferRecycler:()Lcom/fasterxml/jackson/core/util/BufferRecycler;
  #604 = NameAndType        #220:#710     // "<init>":(Lcom/fasterxml/jackson/core/util/BufferRecycler;Lcom/fasterxml/jackson/core/io/ContentReference;Z)V
  #605 = NameAndType        #260:#259     // canHandleBinaryNatively:()Z
  #606 = NameAndType        #711:#712     // construct:(ZLjava/lang/Object;)Lcom/fasterxml/jackson/core/io/ContentReference;
  #607 = NameAndType        #711:#713     // construct:(ZLjava/lang/Object;II)Lcom/fasterxml/jackson/core/io/ContentReference;
  #608 = Utf8               java/lang/UnsupportedOperationException
  #609 = Utf8               java/lang/Object
  #610 = NameAndType        #714:#715     // format:(Ljava/lang/String;[Ljava/lang/Object;)Ljava/lang/String;
  #611 = NameAndType        #716:#300     // collectDefaults:()I
  #612 = Class              #717          // com/fasterxml/jackson/core/util/DefaultPrettyPrinter
  #613 = NameAndType        #197:#718     // DEFAULT_ROOT_VALUE_SEPARATOR:Lcom/fasterxml/jackson/core/io/SerializedString;
  #614 = Utf8               com/fasterxml/jackson/core/TokenStreamFactory
  #615 = Utf8               com/fasterxml/jackson/core/Versioned
  #616 = Utf8               java/io/Serializable
  #617 = Utf8               com/fasterxml/jackson/core/JsonFactory$Feature
  #618 = Utf8               java/lang/String
  #619 = Utf8               java/io/IOException
  #620 = Class              #719          // com/fasterxml/jackson/core/JsonParser
  #621 = Utf8               com/fasterxml/jackson/core/JsonParser$Feature
  #622 = Class              #720          // com/fasterxml/jackson/core/JsonGenerator
  #623 = Utf8               com/fasterxml/jackson/core/JsonGenerator$Feature
  #624 = Utf8               com/fasterxml/jackson/core/JsonParseException
  #625 = Utf8               java/io/OutputStream
  #626 = Utf8               com/fasterxml/jackson/core/SerializableString
  #627 = Utf8               com/fasterxml/jackson/core/sym/CharsToNameCanonicalizer
  #628 = Utf8               createRoot
  #629 = Utf8               ()Lcom/fasterxml/jackson/core/sym/CharsToNameCanonicalizer;
  #630 = Utf8               com/fasterxml/jackson/core/sym/ByteQuadsCanonicalizer
  #631 = Utf8               ()Lcom/fasterxml/jackson/core/sym/ByteQuadsCanonicalizer;
  #632 = Utf8               _streamReadFeatures
  #633 = Utf8               _streamWriteFeatures
  #634 = Utf8               com/fasterxml/jackson/core/TSFBuilder
  #635 = Utf8               (Lcom/fasterxml/jackson/core/JsonFactory;)V
  #636 = Utf8               getClass
  #637 = Utf8               append
  #638 = Utf8               (Ljava/lang/String;)Ljava/lang/StringBuilder;
  #639 = Utf8               java/lang/Class
  #640 = Utf8               getName
  #641 = Utf8               (Ljava/lang/Object;)Ljava/lang/StringBuilder;
  #642 = Utf8               toString
  #643 = Utf8               com/fasterxml/jackson/core/FormatSchema
  #644 = Utf8               getSchemaType
  #645 = Utf8               equals
  #646 = Utf8               (Ljava/lang/Object;)Z
  #647 = Utf8               com/fasterxml/jackson/core/json/PackageVersion
  #648 = Utf8               VERSION
  #649 = Utf8               Lcom/fasterxml/jackson/core/Version;
  #650 = Utf8               getMask
  #651 = Utf8               com/fasterxml/jackson/core/StreamReadFeature
  #652 = Utf8               mappedFeature
  #653 = Utf8               ()Lcom/fasterxml/jackson/core/JsonParser$Feature;
  #654 = Utf8               com/fasterxml/jackson/core/StreamWriteFeature
  #655 = Utf8               ()Lcom/fasterxml/jackson/core/JsonGenerator$Feature;
  #656 = Utf8               getValue
  #657 = Utf8               (Ljava/io/File;)V
  #658 = Utf8               _optimizedStreamFromURL
  #659 = Utf8               (Ljava/net/URL;)Ljava/io/InputStream;
  #660 = Utf8               com/fasterxml/jackson/core/io/InputDecorator
  #661 = Utf8               decorate
  #662 = Utf8               (Lcom/fasterxml/jackson/core/io/IOContext;[BII)Ljava/io/InputStream;
  #663 = Utf8               allocTokenBuffer
  #664 = Utf8               (I)[C
  #665 = Utf8               getChars
  #666 = Utf8               (II[CI)V
  #667 = Utf8               ([CII)V
  #668 = Utf8               makeChild
  #669 = Utf8               (I)Lcom/fasterxml/jackson/core/sym/ByteQuadsCanonicalizer;
  #670 = Utf8               (Lcom/fasterxml/jackson/core/io/IOContext;ILcom/fasterxml/jackson/core/sym/ByteQuadsCanonicalizer;)V
  #671 = Utf8               setEncoding
  #672 = Utf8               (Lcom/fasterxml/jackson/core/JsonEncoding;)V
  #673 = Utf8               com/fasterxml/jackson/core/JsonEncoding
  #674 = Utf8               UTF8
  #675 = Utf8               _createDataOutputWrapper
  #676 = Utf8               (Ljava/io/DataOutput;)Ljava/io/OutputStream;
  #677 = Utf8               (Lcom/fasterxml/jackson/core/io/IOContext;Ljava/io/InputStream;)V
  #678 = Utf8               constructParser
  #679 = Utf8               (ILcom/fasterxml/jackson/core/ObjectCodec;Lcom/fasterxml/jackson/core/sym/ByteQuadsCanonicalizer;Lcom/fasterxml/jackson/core/sym/CharsToNameCanonicalizer;I)Lcom/fasterxml/jackson/core/JsonParser;
  #680 = Utf8               (I)Lcom/fasterxml/jackson/core/sym/CharsToNameCanonicalizer;
  #681 = Utf8               (Lcom/fasterxml/jackson/core/io/IOContext;ILjava/io/Reader;Lcom/fasterxml/jackson/core/ObjectCodec;Lcom/fasterxml/jackson/core/sym/CharsToNameCanonicalizer;)V
  #682 = Utf8               (Lcom/fasterxml/jackson/core/io/IOContext;ILjava/io/Reader;Lcom/fasterxml/jackson/core/ObjectCodec;Lcom/fasterxml/jackson/core/sym/CharsToNameCanonicalizer;[CIIZ)V
  #683 = Utf8               (Lcom/fasterxml/jackson/core/io/IOContext;[BII)V
  #684 = Utf8               skipUTF8BOM
  #685 = Utf8               (Ljava/io/DataInput;)I
  #686 = Utf8               (Lcom/fasterxml/jackson/core/io/IOContext;ILjava/io/DataInput;Lcom/fasterxml/jackson/core/ObjectCodec;Lcom/fasterxml/jackson/core/sym/ByteQuadsCanonicalizer;I)V
  #687 = Utf8               (Lcom/fasterxml/jackson/core/io/IOContext;ILcom/fasterxml/jackson/core/ObjectCodec;Ljava/io/Writer;C)V
  #688 = Utf8               setHighestNonEscapedChar
  #689 = Utf8               (I)Lcom/fasterxml/jackson/core/JsonGenerator;
  #690 = Utf8               (Lcom/fasterxml/jackson/core/io/CharacterEscapes;)Lcom/fasterxml/jackson/core/JsonGenerator;
  #691 = Utf8               (Lcom/fasterxml/jackson/core/SerializableString;)Lcom/fasterxml/jackson/core/JsonGenerator;
  #692 = Utf8               (Lcom/fasterxml/jackson/core/io/IOContext;ILcom/fasterxml/jackson/core/ObjectCodec;Ljava/io/OutputStream;C)V
  #693 = Utf8               (Lcom/fasterxml/jackson/core/io/IOContext;Ljava/io/OutputStream;)V
  #694 = Utf8               getJavaName
  #695 = Utf8               (Ljava/io/OutputStream;Ljava/lang/String;)V
  #696 = Utf8               (Lcom/fasterxml/jackson/core/io/IOContext;Ljava/io/InputStream;)Ljava/io/InputStream;
  #697 = Utf8               (Lcom/fasterxml/jackson/core/io/IOContext;Ljava/io/Reader;)Ljava/io/Reader;
  #698 = Utf8               (Lcom/fasterxml/jackson/core/io/IOContext;Ljava/io/DataInput;)Ljava/io/DataInput;
  #699 = Utf8               com/fasterxml/jackson/core/io/OutputDecorator
  #700 = Utf8               (Lcom/fasterxml/jackson/core/io/IOContext;Ljava/io/OutputStream;)Ljava/io/OutputStream;
  #701 = Utf8               (Lcom/fasterxml/jackson/core/io/IOContext;Ljava/io/Writer;)Ljava/io/Writer;
  #702 = Utf8               USE_THREAD_LOCAL_FOR_BUFFER_RECYCLING
  #703 = Utf8               enabledIn
  #704 = Utf8               (I)Z
  #705 = Utf8               com/fasterxml/jackson/core/util/BufferRecyclers
  #706 = Utf8               getBufferRecycler
  #707 = Utf8               com/fasterxml/jackson/core/io/ContentReference
  #708 = Utf8               unknown
  #709 = Utf8               ()Lcom/fasterxml/jackson/core/io/ContentReference;
  #710 = Utf8               (Lcom/fasterxml/jackson/core/util/BufferRecycler;Lcom/fasterxml/jackson/core/io/ContentReference;Z)V
  #711 = Utf8               construct
  #712 = Utf8               (ZLjava/lang/Object;)Lcom/fasterxml/jackson/core/io/ContentReference;
  #713 = Utf8               (ZLjava/lang/Object;II)Lcom/fasterxml/jackson/core/io/ContentReference;
  #714 = Utf8               format
  #715 = Utf8               (Ljava/lang/String;[Ljava/lang/Object;)Ljava/lang/String;
  #716 = Utf8               collectDefaults
  #717 = Utf8               com/fasterxml/jackson/core/util/DefaultPrettyPrinter
  #718 = Utf8               Lcom/fasterxml/jackson/core/io/SerializedString;
  #719 = Utf8               com/fasterxml/jackson/core/JsonParser
  #720 = Utf8               com/fasterxml/jackson/core/JsonGenerator
{
  private static final long serialVersionUID;
    descriptor: J
    flags: (0x001a) ACC_PRIVATE, ACC_STATIC, ACC_FINAL
    ConstantValue: long 2l

  public static final java.lang.String FORMAT_NAME_JSON;
    descriptor: Ljava/lang/String;
    flags: (0x0019) ACC_PUBLIC, ACC_STATIC, ACC_FINAL
    ConstantValue: String JSON

  protected static final int DEFAULT_FACTORY_FEATURE_FLAGS;
    descriptor: I
    flags: (0x001c) ACC_PROTECTED, ACC_STATIC, ACC_FINAL

  protected static final int DEFAULT_PARSER_FEATURE_FLAGS;
    descriptor: I
    flags: (0x001c) ACC_PROTECTED, ACC_STATIC, ACC_FINAL

  protected static final int DEFAULT_GENERATOR_FEATURE_FLAGS;
    descriptor: I
    flags: (0x001c) ACC_PROTECTED, ACC_STATIC, ACC_FINAL

  public static final com.fasterxml.jackson.core.SerializableString DEFAULT_ROOT_VALUE_SEPARATOR;
    descriptor: Lcom/fasterxml/jackson/core/SerializableString;
    flags: (0x0019) ACC_PUBLIC, ACC_STATIC, ACC_FINAL

  public static final char DEFAULT_QUOTE_CHAR;
    descriptor: C
    flags: (0x0019) ACC_PUBLIC, ACC_STATIC, ACC_FINAL
    ConstantValue: int 34

  protected final transient com.fasterxml.jackson.core.sym.CharsToNameCanonicalizer _rootCharSymbols;
    descriptor: Lcom/fasterxml/jackson/core/sym/CharsToNameCanonicalizer;
    flags: (0x0094) ACC_PROTECTED, ACC_FINAL, ACC_TRANSIENT

  protected final transient com.fasterxml.jackson.core.sym.ByteQuadsCanonicalizer _byteSymbolCanonicalizer;
    descriptor: Lcom/fasterxml/jackson/core/sym/ByteQuadsCanonicalizer;
    flags: (0x0094) ACC_PROTECTED, ACC_FINAL, ACC_TRANSIENT

  protected int _factoryFeatures;
    descriptor: I
    flags: (0x0004) ACC_PROTECTED

  protected int _parserFeatures;
    descriptor: I
    flags: (0x0004) ACC_PROTECTED

  protected int _generatorFeatures;
    descriptor: I
    flags: (0x0004) ACC_PROTECTED

  protected com.fasterxml.jackson.core.ObjectCodec _objectCodec;
    descriptor: Lcom/fasterxml/jackson/core/ObjectCodec;
    flags: (0x0004) ACC_PROTECTED

  protected com.fasterxml.jackson.core.io.CharacterEscapes _characterEscapes;
    descriptor: Lcom/fasterxml/jackson/core/io/CharacterEscapes;
    flags: (0x0004) ACC_PROTECTED

  protected com.fasterxml.jackson.core.io.InputDecorator _inputDecorator;
    descriptor: Lcom/fasterxml/jackson/core/io/InputDecorator;
    flags: (0x0004) ACC_PROTECTED

  protected com.fasterxml.jackson.core.io.OutputDecorator _outputDecorator;
    descriptor: Lcom/fasterxml/jackson/core/io/OutputDecorator;
    flags: (0x0004) ACC_PROTECTED

  protected com.fasterxml.jackson.core.SerializableString _rootValueSeparator;
    descriptor: Lcom/fasterxml/jackson/core/SerializableString;
    flags: (0x0004) ACC_PROTECTED

  protected int _maximumNonEscapedChar;
    descriptor: I
    flags: (0x0004) ACC_PROTECTED

  protected final char _quoteChar;
    descriptor: C
    flags: (0x0014) ACC_PROTECTED, ACC_FINAL

  public com.fasterxml.jackson.core.JsonFactory();
    descriptor: ()V
    flags: (0x0001) ACC_PUBLIC
    Code:
      stack=2, locals=1, args_size=1
         0: aload_0
         1: aconst_null
         2: checkcast     #1                  // class com/fasterxml/jackson/core/ObjectCodec
         5: invokespecial #2                  // Method "<init>":(Lcom/fasterxml/jackson/core/ObjectCodec;)V
         8: return
      LineNumberTable:
        line 314: 0
      LocalVariableTable:
        Start  Length  Slot  Name   Signature
            0       9     0  this   Lcom/fasterxml/jackson/core/JsonFactory;

  public com.fasterxml.jackson.core.JsonFactory(com.fasterxml.jackson.core.ObjectCodec);
    descriptor: (Lcom/fasterxml/jackson/core/ObjectCodec;)V
    flags: (0x0001) ACC_PUBLIC
    Code:
      stack=2, locals=2, args_size=2
         0: aload_0
         1: invokespecial #3                  // Method com/fasterxml/jackson/core/TokenStreamFactory."<init>":()V
         4: aload_0
         5: invokestatic  #4                  // Method com/fasterxml/jackson/core/sym/CharsToNameCanonicalizer.createRoot:()Lcom/fasterxml/jackson/core/sym/CharsToNameCanonicalizer;
         8: putfield      #5                  // Field _rootCharSymbols:Lcom/fasterxml/jackson/core/sym/CharsToNameCanonicalizer;
        11: aload_0
        12: invokestatic  #6                  // Method com/fasterxml/jackson/core/sym/ByteQuadsCanonicalizer.createRoot:()Lcom/fasterxml/jackson/core/sym/ByteQuadsCanonicalizer;
        15: putfield      #7                  // Field _byteSymbolCanonicalizer:Lcom/fasterxml/jackson/core/sym/ByteQuadsCanonicalizer;
        18: aload_0
        19: getstatic     #8                  // Field DEFAULT_FACTORY_FEATURE_FLAGS:I
        22: putfield      #9                  // Field _factoryFeatures:I
        25: aload_0
        26: getstatic     #10                 // Field DEFAULT_PARSER_FEATURE_FLAGS:I
        29: putfield      #11                 // Field _parserFeatures:I
        32: aload_0
        33: getstatic     #12                 // Field DEFAULT_GENERATOR_FEATURE_FLAGS:I
        36: putfield      #13                 // Field _generatorFeatures:I
        39: aload_0
        40: getstatic     #14                 // Field DEFAULT_ROOT_VALUE_SEPARATOR:Lcom/fasterxml/jackson/core/SerializableString;
        43: putfield      #15                 // Field _rootValueSeparator:Lcom/fasterxml/jackson/core/SerializableString;
        46: aload_0
        47: aload_1
        48: putfield      #16                 // Field _objectCodec:Lcom/fasterxml/jackson/core/ObjectCodec;
        51: aload_0
        52: bipush        34
        54: putfield      #18                 // Field _quoteChar:C
        57: return
      LineNumberTable:
        line 316: 0
        line 204: 4
        line 215: 11
        line 226: 18
        line 231: 25
        line 236: 32
        line 279: 39
        line 317: 46
        line 318: 51
        line 319: 57
      LocalVariableTable:
        Start  Length  Slot  Name   Signature
            0      58     0  this   Lcom/fasterxml/jackson/core/JsonFactory;
            0      58     1    oc   Lcom/fasterxml/jackson/core/ObjectCodec;

  protected com.fasterxml.jackson.core.JsonFactory(com.fasterxml.jackson.core.JsonFactory, com.fasterxml.jackson.core.ObjectCodec);
    descriptor: (Lcom/fasterxml/jackson/core/JsonFactory;Lcom/fasterxml/jackson/core/ObjectCodec;)V
    flags: (0x0004) ACC_PROTECTED
    Code:
      stack=2, locals=3, args_size=3
         0: aload_0
         1: invokespecial #3                  // Method com/fasterxml/jackson/core/TokenStreamFactory."<init>":()V
         4: aload_0
         5: invokestatic  #4                  // Method com/fasterxml/jackson/core/sym/CharsToNameCanonicalizer.createRoot:()Lcom/fasterxml/jackson/core/sym/CharsToNameCanonicalizer;
         8: putfield      #5                  // Field _rootCharSymbols:Lcom/fasterxml/jackson/core/sym/CharsToNameCanonicalizer;
        11: aload_0
        12: invokestatic  #6                  // Method com/fasterxml/jackson/core/sym/ByteQuadsCanonicalizer.createRoot:()Lcom/fasterxml/jackson/core/sym/ByteQuadsCanonicalizer;
        15: putfield      #7                  // Field _byteSymbolCanonicalizer:Lcom/fasterxml/jackson/core/sym/ByteQuadsCanonicalizer;
        18: aload_0
        19: getstatic     #8                  // Field DEFAULT_FACTORY_FEATURE_FLAGS:I
        22: putfield      #9                  // Field _factoryFeatures:I
        25: aload_0
        26: getstatic     #10                 // Field DEFAULT_PARSER_FEATURE_FLAGS:I
        29: putfield      #11                 // Field _parserFeatures:I
        32: aload_0
        33: getstatic     #12                 // Field DEFAULT_GENERATOR_FEATURE_FLAGS:I
        36: putfield      #13                 // Field _generatorFeatures:I
        39: aload_0
        40: getstatic     #14                 // Field DEFAULT_ROOT_VALUE_SEPARATOR:Lcom/fasterxml/jackson/core/SerializableString;
        43: putfield      #15                 // Field _rootValueSeparator:Lcom/fasterxml/jackson/core/SerializableString;
        46: aload_0
        47: aload_2
        48: putfield      #16                 // Field _objectCodec:Lcom/fasterxml/jackson/core/ObjectCodec;
        51: aload_0
        52: aload_1
        53: getfield      #9                  // Field _factoryFeatures:I
        56: putfield      #9                  // Field _factoryFeatures:I
        59: aload_0
        60: aload_1
        61: getfield      #11                 // Field _parserFeatures:I
        64: putfield      #11                 // Field _parserFeatures:I
        67: aload_0
        68: aload_1
        69: getfield      #13                 // Field _generatorFeatures:I
        72: putfield      #13                 // Field _generatorFeatures:I
        75: aload_0
        76: aload_1
        77: getfield      #19                 // Field _inputDecorator:Lcom/fasterxml/jackson/core/io/InputDecorator;
        80: putfield      #19                 // Field _inputDecorator:Lcom/fasterxml/jackson/core/io/InputDecorator;
        83: aload_0
        84: aload_1
        85: getfield      #20                 // Field _outputDecorator:Lcom/fasterxml/jackson/core/io/OutputDecorator;
        88: putfield      #20                 // Field _outputDecorator:Lcom/fasterxml/jackson/core/io/OutputDecorator;
        91: aload_0
        92: aload_1
        93: getfield      #21                 // Field _characterEscapes:Lcom/fasterxml/jackson/core/io/CharacterEscapes;
        96: putfield      #21                 // Field _characterEscapes:Lcom/fasterxml/jackson/core/io/CharacterEscapes;
        99: aload_0
       100: aload_1
       101: getfield      #15                 // Field _rootValueSeparator:Lcom/fasterxml/jackson/core/SerializableString;
       104: putfield      #15                 // Field _rootValueSeparator:Lcom/fasterxml/jackson/core/SerializableString;
       107: aload_0
       108: aload_1
       109: getfield      #22                 // Field _maximumNonEscapedChar:I
       112: putfield      #22                 // Field _maximumNonEscapedChar:I
       115: aload_0
       116: aload_1
       117: getfield      #18                 // Field _quoteChar:C
       120: putfield      #18                 // Field _quoteChar:C
       123: return
      LineNumberTable:
        line 330: 0
        line 204: 4
        line 215: 11
        line 226: 18
        line 231: 25
        line 236: 32
        line 279: 39
        line 331: 46
        line 334: 51
        line 335: 59
        line 336: 67
        line 337: 75
        line 338: 83
        line 341: 91
        line 342: 99
        line 343: 107
        line 344: 115
        line 345: 123
      LocalVariableTable:
        Start  Length  Slot  Name   Signature
            0     124     0  this   Lcom/fasterxml/jackson/core/JsonFactory;
            0     124     1   src   Lcom/fasterxml/jackson/core/JsonFactory;
            0     124     2 codec   Lcom/fasterxml/jackson/core/ObjectCodec;

  public com.fasterxml.jackson.core.JsonFactory(com.fasterxml.jackson.core.JsonFactoryBuilder);
    descriptor: (Lcom/fasterxml/jackson/core/JsonFactoryBuilder;)V
    flags: (0x0001) ACC_PUBLIC
    Code:
      stack=2, locals=2, args_size=2
         0: aload_0
         1: invokespecial #3                  // Method com/fasterxml/jackson/core/TokenStreamFactory."<init>":()V
         4: aload_0
         5: invokestatic  #4                  // Method com/fasterxml/jackson/core/sym/CharsToNameCanonicalizer.createRoot:()Lcom/fasterxml/jackson/core/sym/CharsToNameCanonicalizer;
         8: putfield      #5                  // Field _rootCharSymbols:Lcom/fasterxml/jackson/core/sym/CharsToNameCanonicalizer;
        11: aload_0
        12: invokestatic  #6                  // Method com/fasterxml/jackson/core/sym/ByteQuadsCanonicalizer.createRoot:()Lcom/fasterxml/jackson/core/sym/ByteQuadsCanonicalizer;
        15: putfield      #7                  // Field _byteSymbolCanonicalizer:Lcom/fasterxml/jackson/core/sym/ByteQuadsCanonicalizer;
        18: aload_0
        19: getstatic     #8                  // Field DEFAULT_FACTORY_FEATURE_FLAGS:I
        22: putfield      #9                  // Field _factoryFeatures:I
        25: aload_0
        26: getstatic     #10                 // Field DEFAULT_PARSER_FEATURE_FLAGS:I
        29: putfield      #11                 // Field _parserFeatures:I
        32: aload_0
        33: getstatic     #12                 // Field DEFAULT_GENERATOR_FEATURE_FLAGS:I
        36: putfield      #13                 // Field _generatorFeatures:I
        39: aload_0
        40: getstatic     #14                 // Field DEFAULT_ROOT_VALUE_SEPARATOR:Lcom/fasterxml/jackson/core/SerializableString;
        43: putfield      #15                 // Field _rootValueSeparator:Lcom/fasterxml/jackson/core/SerializableString;
        46: aload_0
        47: aconst_null
        48: putfield      #16                 // Field _objectCodec:Lcom/fasterxml/jackson/core/ObjectCodec;
        51: aload_0
        52: aload_1
        53: getfield      #23                 // Field com/fasterxml/jackson/core/JsonFactoryBuilder._factoryFeatures:I
        56: putfield      #9                  // Field _factoryFeatures:I
        59: aload_0
        60: aload_1
        61: getfield      #24                 // Field com/fasterxml/jackson/core/JsonFactoryBuilder._streamReadFeatures:I
        64: putfield      #11                 // Field _parserFeatures:I
        67: aload_0
        68: aload_1
        69: getfield      #25                 // Field com/fasterxml/jackson/core/JsonFactoryBuilder._streamWriteFeatures:I
        72: putfield      #13                 // Field _generatorFeatures:I
        75: aload_0
        76: aload_1
        77: getfield      #26                 // Field com/fasterxml/jackson/core/JsonFactoryBuilder._inputDecorator:Lcom/fasterxml/jackson/core/io/InputDecorator;
        80: putfield      #19                 // Field _inputDecorator:Lcom/fasterxml/jackson/core/io/InputDecorator;
        83: aload_0
        84: aload_1
        85: getfield      #27                 // Field com/fasterxml/jackson/core/JsonFactoryBuilder._outputDecorator:Lcom/fasterxml/jackson/core/io/OutputDecorator;
        88: putfield      #20                 // Field _outputDecorator:Lcom/fasterxml/jackson/core/io/OutputDecorator;
        91: aload_0
        92: aload_1
        93: getfield      #28                 // Field com/fasterxml/jackson/core/JsonFactoryBuilder._characterEscapes:Lcom/fasterxml/jackson/core/io/CharacterEscapes;
        96: putfield      #21                 // Field _characterEscapes:Lcom/fasterxml/jackson/core/io/CharacterEscapes;
        99: aload_0
       100: aload_1
       101: getfield      #29                 // Field com/fasterxml/jackson/core/JsonFactoryBuilder._rootValueSeparator:Lcom/fasterxml/jackson/core/SerializableString;
       104: putfield      #15                 // Field _rootValueSeparator:Lcom/fasterxml/jackson/core/SerializableString;
       107: aload_0
       108: aload_1
       109: getfield      #30                 // Field com/fasterxml/jackson/core/JsonFactoryBuilder._maximumNonEscapedChar:I
       112: putfield      #22                 // Field _maximumNonEscapedChar:I
       115: aload_0
       116: aload_1
       117: getfield      #31                 // Field com/fasterxml/jackson/core/JsonFactoryBuilder._quoteChar:C
       120: putfield      #18                 // Field _quoteChar:C
       123: return
      LineNumberTable:
        line 354: 0
        line 204: 4
        line 215: 11
        line 226: 18
        line 231: 25
        line 236: 32
        line 279: 39
        line 355: 46
        line 358: 51
        line 359: 59
        line 360: 67
        line 361: 75
        line 362: 83
        line 365: 91
        line 366: 99
        line 367: 107
        line 368: 115
        line 369: 123
      LocalVariableTable:
        Start  Length  Slot  Name   Signature
            0     124     0  this   Lcom/fasterxml/jackson/core/JsonFactory;
            0     124     1     b   Lcom/fasterxml/jackson/core/JsonFactoryBuilder;

  protected com.fasterxml.jackson.core.JsonFactory(com.fasterxml.jackson.core.TSFBuilder<?, ?>, boolean);
    descriptor: (Lcom/fasterxml/jackson/core/TSFBuilder;Z)V
    flags: (0x0004) ACC_PROTECTED
    Code:
      stack=2, locals=3, args_size=3
         0: aload_0
         1: invokespecial #3                  // Method com/fasterxml/jackson/core/TokenStreamFactory."<init>":()V
         4: aload_0
         5: invokestatic  #4                  // Method com/fasterxml/jackson/core/sym/CharsToNameCanonicalizer.createRoot:()Lcom/fasterxml/jackson/core/sym/CharsToNameCanonicalizer;
         8: putfield      #5                  // Field _rootCharSymbols:Lcom/fasterxml/jackson/core/sym/CharsToNameCanonicalizer;
        11: aload_0
        12: invokestatic  #6                  // Method com/fasterxml/jackson/core/sym/ByteQuadsCanonicalizer.createRoot:()Lcom/fasterxml/jackson/core/sym/ByteQuadsCanonicalizer;
        15: putfield      #7                  // Field _byteSymbolCanonicalizer:Lcom/fasterxml/jackson/core/sym/ByteQuadsCanonicalizer;
        18: aload_0
        19: getstatic     #8                  // Field DEFAULT_FACTORY_FEATURE_FLAGS:I
        22: putfield      #9                  // Field _factoryFeatures:I
        25: aload_0
        26: getstatic     #10                 // Field DEFAULT_PARSER_FEATURE_FLAGS:I
        29: putfield      #11                 // Field _parserFeatures:I
        32: aload_0
        33: getstatic     #12                 // Field DEFAULT_GENERATOR_FEATURE_FLAGS:I
        36: putfield      #13                 // Field _generatorFeatures:I
        39: aload_0
        40: getstatic     #14                 // Field DEFAULT_ROOT_VALUE_SEPARATOR:Lcom/fasterxml/jackson/core/SerializableString;
        43: putfield      #15                 // Field _rootValueSeparator:Lcom/fasterxml/jackson/core/SerializableString;
        46: aload_0
        47: aconst_null
        48: putfield      #16                 // Field _objectCodec:Lcom/fasterxml/jackson/core/ObjectCodec;
        51: aload_0
        52: aload_1
        53: getfield      #32                 // Field com/fasterxml/jackson/core/TSFBuilder._factoryFeatures:I
        56: putfield      #9                  // Field _factoryFeatures:I
        59: aload_0
        60: aload_1
        61: getfield      #33                 // Field com/fasterxml/jackson/core/TSFBuilder._streamReadFeatures:I
        64: putfield      #11                 // Field _parserFeatures:I
        67: aload_0
        68: aload_1
        69: getfield      #34                 // Field com/fasterxml/jackson/core/TSFBuilder._streamWriteFeatures:I
        72: putfield      #13                 // Field _generatorFeatures:I
        75: aload_0
        76: aload_1
        77: getfield      #35                 // Field com/fasterxml/jackson/core/TSFBuilder._inputDecorator:Lcom/fasterxml/jackson/core/io/InputDecorator;
        80: putfield      #19                 // Field _inputDecorator:Lcom/fasterxml/jackson/core/io/InputDecorator;
        83: aload_0
        84: aload_1
        85: getfield      #36                 // Field com/fasterxml/jackson/core/TSFBuilder._outputDecorator:Lcom/fasterxml/jackson/core/io/OutputDecorator;
        88: putfield      #20                 // Field _outputDecorator:Lcom/fasterxml/jackson/core/io/OutputDecorator;
        91: aload_0
        92: aconst_null
        93: putfield      #21                 // Field _characterEscapes:Lcom/fasterxml/jackson/core/io/CharacterEscapes;
        96: aload_0
        97: aconst_null
        98: putfield      #15                 // Field _rootValueSeparator:Lcom/fasterxml/jackson/core/SerializableString;
       101: aload_0
       102: iconst_0
       103: putfield      #22                 // Field _maximumNonEscapedChar:I
       106: aload_0
       107: bipush        34
       109: putfield      #18                 // Field _quoteChar:C
       112: return
      LineNumberTable:
        line 379: 0
        line 204: 4
        line 215: 11
        line 226: 18
        line 231: 25
        line 236: 32
        line 279: 39
        line 380: 46
        line 382: 51
        line 383: 59
        line 384: 67
        line 385: 75
        line 386: 83
        line 389: 91
        line 390: 96
        line 391: 101
        line 392: 106
        line 393: 112
      LocalVariableTable:
        Start  Length  Slot  Name   Signature
            0     113     0  this   Lcom/fasterxml/jackson/core/JsonFactory;
            0     113     1     b   Lcom/fasterxml/jackson/core/TSFBuilder;
            0     113     2 bogus   Z
      LocalVariableTypeTable:
        Start  Length  Slot  Name   Signature
            0     113     1     b   Lcom/fasterxml/jackson/core/TSFBuilder<**>;
    Signature: #242                         // (Lcom/fasterxml/jackson/core/TSFBuilder<**>;Z)V

  public com.fasterxml.jackson.core.TSFBuilder<?, ?> rebuild();
    descriptor: ()Lcom/fasterxml/jackson/core/TSFBuilder;
    flags: (0x0001) ACC_PUBLIC
    Code:
      stack=3, locals=1, args_size=1
         0: aload_0
         1: ldc           #37                 // String Factory implementation for format (%s) MUST override `rebuild()` method
         3: invokespecial #38                 // Method _requireJSONFactory:(Ljava/lang/String;)V
         6: new           #39                 // class com/fasterxml/jackson/core/JsonFactoryBuilder
         9: dup
        10: aload_0
        11: invokespecial #40                 // Method com/fasterxml/jackson/core/JsonFactoryBuilder."<init>":(Lcom/fasterxml/jackson/core/JsonFactory;)V
        14: areturn
      LineNumberTable:
        line 405: 0
        line 406: 6
      LocalVariableTable:
        Start  Length  Slot  Name   Signature
            0      15     0  this   Lcom/fasterxml/jackson/core/JsonFactory;
    Signature: #245                         // ()Lcom/fasterxml/jackson/core/TSFBuilder<**>;

  public static com.fasterxml.jackson.core.TSFBuilder<?, ?> builder();
    descriptor: ()Lcom/fasterxml/jackson/core/TSFBuilder;
    flags: (0x0009) ACC_PUBLIC, ACC_STATIC
    Code:
      stack=2, locals=0, args_size=0
         0: new           #39                 // class com/fasterxml/jackson/core/JsonFactoryBuilder
         3: dup
         4: invokespecial #41                 // Method com/fasterxml/jackson/core/JsonFactoryBuilder."<init>":()V
         7: areturn
      LineNumberTable:
        line 421: 0
    Signature: #245                         // ()Lcom/fasterxml/jackson/core/TSFBuilder<**>;

  public com.fasterxml.jackson.core.JsonFactory copy();
    descriptor: ()Lcom/fasterxml/jackson/core/JsonFactory;
    flags: (0x0001) ACC_PUBLIC
    Code:
      stack=4, locals=1, args_size=1
         0: aload_0
         1: ldc           #17                 // class com/fasterxml/jackson/core/JsonFactory
         3: invokevirtual #42                 // Method _checkInvalidCopy:(Ljava/lang/Class;)V
         6: new           #17                 // class com/fasterxml/jackson/core/JsonFactory
         9: dup
        10: aload_0
        11: aconst_null
        12: invokespecial #43                 // Method "<init>":(Lcom/fasterxml/jackson/core/JsonFactory;Lcom/fasterxml/jackson/core/ObjectCodec;)V
        15: areturn
      LineNumberTable:
        line 442: 0
        line 444: 6
      LocalVariableTable:
        Start  Length  Slot  Name   Signature
            0      16     0  this   Lcom/fasterxml/jackson/core/JsonFactory;

  protected void _checkInvalidCopy(java.lang.Class<?>);
    descriptor: (Ljava/lang/Class;)V
    flags: (0x0004) ACC_PROTECTED
    Code:
      stack=4, locals=2, args_size=2
         0: aload_0
         1: invokevirtual #44                 // Method java/lang/Object.getClass:()Ljava/lang/Class;
         4: aload_1
         5: if_acmpeq     58
         8: new           #45                 // class java/lang/IllegalStateException
        11: dup
        12: new           #46                 // class java/lang/StringBuilder
        15: dup
        16: invokespecial #47                 // Method java/lang/StringBuilder."<init>":()V
        19: ldc           #48                 // String Failed copy():
        21: invokevirtual #49                 // Method java/lang/StringBuilder.append:(Ljava/lang/String;)Ljava/lang/StringBuilder;
        24: aload_0
        25: invokevirtual #44                 // Method java/lang/Object.getClass:()Ljava/lang/Class;
        28: invokevirtual #50                 // Method java/lang/Class.getName:()Ljava/lang/String;
        31: invokevirtual #49                 // Method java/lang/StringBuilder.append:(Ljava/lang/String;)Ljava/lang/StringBuilder;
        34: ldc           #51                 // String  (version:
        36: invokevirtual #49                 // Method java/lang/StringBuilder.append:(Ljava/lang/String;)Ljava/lang/StringBuilder;
        39: aload_0
        40: invokevirtual #52                 // Method version:()Lcom/fasterxml/jackson/core/Version;
        43: invokevirtual #53                 // Method java/lang/StringBuilder.append:(Ljava/lang/Object;)Ljava/lang/StringBuilder;
        46: ldc           #54                 // String ) does not override copy(); it has to
        48: invokevirtual #49                 // Method java/lang/StringBuilder.append:(Ljava/lang/String;)Ljava/lang/StringBuilder;
        51: invokevirtual #55                 // Method java/lang/StringBuilder.toString:()Ljava/lang/String;
        54: invokespecial #56                 // Method java/lang/IllegalStateException."<init>":(Ljava/lang/String;)V
        57: athrow
        58: return
      LineNumberTable:
        line 449: 0
        line 450: 8
        line 451: 40
        line 453: 58
      LocalVariableTable:
        Start  Length  Slot  Name   Signature
            0      59     0  this   Lcom/fasterxml/jackson/core/JsonFactory;
            0      59     1   exp   Ljava/lang/Class;
      LocalVariableTypeTable:
        Start  Length  Slot  Name   Signature
            0      59     1   exp   Ljava/lang/Class<*>;
      StackMapTable: number_of_entries = 1
        frame_type = 58 /* same */
    Signature: #255                         // (Ljava/lang/Class<*>;)V

  protected java.lang.Object readResolve();
    descriptor: ()Ljava/lang/Object;
    flags: (0x0004) ACC_PROTECTED
    Code:
      stack=4, locals=1, args_size=1
         0: new           #17                 // class com/fasterxml/jackson/core/JsonFactory
         3: dup
         4: aload_0
         5: aload_0
         6: getfield      #16                 // Field _objectCodec:Lcom/fasterxml/jackson/core/ObjectCodec;
         9: invokespecial #43                 // Method "<init>":(Lcom/fasterxml/jackson/core/JsonFactory;Lcom/fasterxml/jackson/core/ObjectCodec;)V
        12: areturn
      LineNumberTable:
        line 471: 0
      LocalVariableTable:
        Start  Length  Slot  Name   Signature
            0      13     0  this   Lcom/fasterxml/jackson/core/JsonFactory;

  public boolean requiresPropertyOrdering();
    descriptor: ()Z
    flags: (0x0001) ACC_PUBLIC
    Code:
      stack=1, locals=1, args_size=1
         0: iconst_0
         1: ireturn
      LineNumberTable:
        line 499: 0
      LocalVariableTable:
        Start  Length  Slot  Name   Signature
            0       2     0  this   Lcom/fasterxml/jackson/core/JsonFactory;

  public boolean canHandleBinaryNatively();
    descriptor: ()Z
    flags: (0x0001) ACC_PUBLIC
    Code:
      stack=1, locals=1, args_size=1
         0: iconst_0
         1: ireturn
      LineNumberTable:
        line 517: 0
      LocalVariableTable:
        Start  Length  Slot  Name   Signature
            0       2     0  this   Lcom/fasterxml/jackson/core/JsonFactory;

  public boolean canUseCharArrays();
    descriptor: ()Z
    flags: (0x0001) ACC_PUBLIC
    Code:
      stack=1, locals=1, args_size=1
         0: iconst_1
         1: ireturn
      LineNumberTable:
        line 534: 0
      LocalVariableTable:
        Start  Length  Slot  Name   Signature
            0       2     0  this   Lcom/fasterxml/jackson/core/JsonFactory;

  public boolean canParseAsync();
    descriptor: ()Z
    flags: (0x0001) ACC_PUBLIC
    Code:
      stack=1, locals=1, args_size=1
         0: aload_0
         1: invokespecial #57                 // Method _isJSONFactory:()Z
         4: ireturn
      LineNumberTable:
        line 551: 0
      LocalVariableTable:
        Start  Length  Slot  Name   Signature
            0       5     0  this   Lcom/fasterxml/jackson/core/JsonFactory;

  public java.lang.Class<? extends com.fasterxml.jackson.core.FormatFeature> getFormatReadFeatureType();
    descriptor: ()Ljava/lang/Class;
    flags: (0x0001) ACC_PUBLIC
    Code:
      stack=1, locals=1, args_size=1
         0: aconst_null
         1: areturn
      LineNumberTable:
        line 556: 0
      LocalVariableTable:
        Start  Length  Slot  Name   Signature
            0       2     0  this   Lcom/fasterxml/jackson/core/JsonFactory;
    Signature: #265                         // ()Ljava/lang/Class<+Lcom/fasterxml/jackson/core/FormatFeature;>;

  public java.lang.Class<? extends com.fasterxml.jackson.core.FormatFeature> getFormatWriteFeatureType();
    descriptor: ()Ljava/lang/Class;
    flags: (0x0001) ACC_PUBLIC
    Code:
      stack=1, locals=1, args_size=1
         0: aconst_null
         1: areturn
      LineNumberTable:
        line 561: 0
      LocalVariableTable:
        Start  Length  Slot  Name   Signature
            0       2     0  this   Lcom/fasterxml/jackson/core/JsonFactory;
    Signature: #265                         // ()Ljava/lang/Class<+Lcom/fasterxml/jackson/core/FormatFeature;>;

  public boolean canUseSchema(com.fasterxml.jackson.core.FormatSchema);
    descriptor: (Lcom/fasterxml/jackson/core/FormatSchema;)Z
    flags: (0x0001) ACC_PUBLIC
    Code:
      stack=2, locals=3, args_size=2
         0: aload_1
         1: ifnonnull     6
         4: iconst_0
         5: ireturn
         6: aload_0
         7: invokevirtual #58                 // Method getFormatName:()Ljava/lang/String;
        10: astore_2
        11: aload_2
        12: ifnull        32
        15: aload_2
        16: aload_1
        17: invokeinterface #59,  1           // InterfaceMethod com/fasterxml/jackson/core/FormatSchema.getSchemaType:()Ljava/lang/String;
        22: invokevirtual #60                 // Method java/lang/String.equals:(Ljava/lang/Object;)Z
        25: ifeq          32
        28: iconst_1
        29: goto          33
        32: iconst_0
        33: ireturn
      LineNumberTable:
        line 585: 0
        line 586: 4
        line 588: 6
        line 589: 11
      LocalVariableTable:
        Start  Length  Slot  Name   Signature
            0      34     0  this   Lcom/fasterxml/jackson/core/JsonFactory;
            0      34     1 schema   Lcom/fasterxml/jackson/core/FormatSchema;
           11      23     2 ourFormat   Ljava/lang/String;
      StackMapTable: number_of_entries = 3
        frame_type = 6 /* same */
        frame_type = 252 /* append */
          offset_delta = 25
          locals = [ class java/lang/String ]
        frame_type = 64 /* same_locals_1_stack_item */
          stack = [ int ]

  public java.lang.String getFormatName();
    descriptor: ()Ljava/lang/String;
    flags: (0x0001) ACC_PUBLIC
    Code:
      stack=2, locals=1, args_size=1
         0: aload_0
         1: invokevirtual #44                 // Method java/lang/Object.getClass:()Ljava/lang/Class;
         4: ldc           #17                 // class com/fasterxml/jackson/core/JsonFactory
         6: if_acmpne     12
         9: ldc           #61                 // String JSON
        11: areturn
        12: aconst_null
        13: areturn
      LineNumberTable:
        line 608: 0
        line 609: 9
        line 611: 12
      LocalVariableTable:
        Start  Length  Slot  Name   Signature
            0      14     0  this   Lcom/fasterxml/jackson/core/JsonFactory;
      StackMapTable: number_of_entries = 1
        frame_type = 12 /* same */

  public com.fasterxml.jackson.core.format.MatchStrength hasFormat(com.fasterxml.jackson.core.format.InputAccessor) throws java.io.IOException;
    descriptor: (Lcom/fasterxml/jackson/core/format/InputAccessor;)Lcom/fasterxml/jackson/core/format/MatchStrength;
    flags: (0x0001) ACC_PUBLIC
    Code:
      stack=2, locals=2, args_size=2
         0: aload_0
         1: invokevirtual #44                 // Method java/lang/Object.getClass:()Ljava/lang/Class;
         4: ldc           #17                 // class com/fasterxml/jackson/core/JsonFactory
         6: if_acmpne     15
         9: aload_0
        10: aload_1
        11: invokevirtual #62                 // Method hasJSONFormat:(Lcom/fasterxml/jackson/core/format/InputAccessor;)Lcom/fasterxml/jackson/core/format/MatchStrength;
        14: areturn
        15: aconst_null
        16: areturn
      LineNumberTable:
        line 617: 0
        line 618: 9
        line 620: 15
      LocalVariableTable:
        Start  Length  Slot  Name   Signature
            0      17     0  this   Lcom/fasterxml/jackson/core/JsonFactory;
            0      17     1   acc   Lcom/fasterxml/jackson/core/format/InputAccessor;
      StackMapTable: number_of_entries = 1
        frame_type = 15 /* same */
    Exceptions:
      throws java.io.IOException

  public boolean requiresCustomCodec();
    descriptor: ()Z
    flags: (0x0001) ACC_PUBLIC
    Code:
      stack=1, locals=1, args_size=1
         0: iconst_0
         1: ireturn
      LineNumberTable:
        line 637: 0
      LocalVariableTable:
        Start  Length  Slot  Name   Signature
            0       2     0  this   Lcom/fasterxml/jackson/core/JsonFactory;

  protected com.fasterxml.jackson.core.format.MatchStrength hasJSONFormat(com.fasterxml.jackson.core.format.InputAccessor) throws java.io.IOException;
    descriptor: (Lcom/fasterxml/jackson/core/format/InputAccessor;)Lcom/fasterxml/jackson/core/format/MatchStrength;
    flags: (0x0004) ACC_PROTECTED
    Code:
      stack=1, locals=2, args_size=2
         0: aload_1
         1: invokestatic  #63                 // Method com/fasterxml/jackson/core/json/ByteSourceJsonBootstrapper.hasJSONFormat:(Lcom/fasterxml/jackson/core/format/InputAccessor;)Lcom/fasterxml/jackson/core/format/MatchStrength;
         4: areturn
      LineNumberTable:
        line 641: 0
      LocalVariableTable:
        Start  Length  Slot  Name   Signature
            0       5     0  this   Lcom/fasterxml/jackson/core/JsonFactory;
            0       5     1   acc   Lcom/fasterxml/jackson/core/format/InputAccessor;
    Exceptions:
      throws java.io.IOException

  public com.fasterxml.jackson.core.Version version();
    descriptor: ()Lcom/fasterxml/jackson/core/Version;
    flags: (0x0001) ACC_PUBLIC
    Code:
      stack=1, locals=1, args_size=1
         0: getstatic     #64                 // Field com/fasterxml/jackson/core/json/PackageVersion.VERSION:Lcom/fasterxml/jackson/core/Version;
         3: areturn
      LineNumberTable:
        line 652: 0
      LocalVariableTable:
        Start  Length  Slot  Name   Signature
            0       4     0  this   Lcom/fasterxml/jackson/core/JsonFactory;

  public final com.fasterxml.jackson.core.JsonFactory configure(com.fasterxml.jackson.core.JsonFactory$Feature, boolean);
    descriptor: (Lcom/fasterxml/jackson/core/JsonFactory$Feature;Z)Lcom/fasterxml/jackson/core/JsonFactory;
    flags: (0x0011) ACC_PUBLIC, ACC_FINAL
    Code:
      stack=2, locals=3, args_size=3
         0: iload_2
         1: ifeq          12
         4: aload_0
         5: aload_1
         6: invokevirtual #65                 // Method enable:(Lcom/fasterxml/jackson/core/JsonFactory$Feature;)Lcom/fasterxml/jackson/core/JsonFactory;
         9: goto          17
        12: aload_0
        13: aload_1
        14: invokevirtual #66                 // Method disable:(Lcom/fasterxml/jackson/core/JsonFactory$Feature;)Lcom/fasterxml/jackson/core/JsonFactory;
        17: areturn
      LineNumberTable:
        line 674: 0
      LocalVariableTable:
        Start  Length  Slot  Name   Signature
            0      18     0  this   Lcom/fasterxml/jackson/core/JsonFactory;
            0      18     1     f   Lcom/fasterxml/jackson/core/JsonFactory$Feature;
            0      18     2 state   Z
      StackMapTable: number_of_entries = 2
        frame_type = 12 /* same */
        frame_type = 68 /* same_locals_1_stack_item */
          stack = [ class com/fasterxml/jackson/core/JsonFactory ]
    Deprecated: true
    RuntimeVisibleAnnotations:
      0: #293()
        java.lang.Deprecated

  public com.fasterxml.jackson.core.JsonFactory enable(com.fasterxml.jackson.core.JsonFactory$Feature);
    descriptor: (Lcom/fasterxml/jackson/core/JsonFactory$Feature;)Lcom/fasterxml/jackson/core/JsonFactory;
    flags: (0x0001) ACC_PUBLIC
    Code:
      stack=3, locals=2, args_size=2
         0: aload_0
         1: dup
         2: getfield      #9                  // Field _factoryFeatures:I
         5: aload_1
         6: invokevirtual #67                 // Method com/fasterxml/jackson/core/JsonFactory$Feature.getMask:()I
         9: ior
        10: putfield      #9                  // Field _factoryFeatures:I
        13: aload_0
        14: areturn
      LineNumberTable:
        line 689: 0
        line 690: 13
      LocalVariableTable:
        Start  Length  Slot  Name   Signature
            0      15     0  this   Lcom/fasterxml/jackson/core/JsonFactory;
            0      15     1     f   Lcom/fasterxml/jackson/core/JsonFactory$Feature;
    Deprecated: true
    RuntimeVisibleAnnotations:
      0: #293()
        java.lang.Deprecated

  public com.fasterxml.jackson.core.JsonFactory disable(com.fasterxml.jackson.core.JsonFactory$Feature);
    descriptor: (Lcom/fasterxml/jackson/core/JsonFactory$Feature;)Lcom/fasterxml/jackson/core/JsonFactory;
    flags: (0x0001) ACC_PUBLIC
    Code:
      stack=4, locals=2, args_size=2
         0: aload_0
         1: dup
         2: getfield      #9                  // Field _factoryFeatures:I
         5: aload_1
         6: invokevirtual #67                 // Method com/fasterxml/jackson/core/JsonFactory$Feature.getMask:()I
         9: iconst_m1
        10: ixor
        11: iand
        12: putfield      #9                  // Field _factoryFeatures:I
        15: aload_0
        16: areturn
      LineNumberTable:
        line 705: 0
        line 706: 15
      LocalVariableTable:
        Start  Length  Slot  Name   Signature
            0      17     0  this   Lcom/fasterxml/jackson/core/JsonFactory;
            0      17     1     f   Lcom/fasterxml/jackson/core/JsonFactory$Feature;
    Deprecated: true
    RuntimeVisibleAnnotations:
      0: #293()
        java.lang.Deprecated

  public final boolean isEnabled(com.fasterxml.jackson.core.JsonFactory$Feature);
    descriptor: (Lcom/fasterxml/jackson/core/JsonFactory$Feature;)Z
    flags: (0x0011) ACC_PUBLIC, ACC_FINAL
    Code:
      stack=2, locals=2, args_size=2
         0: aload_0
         1: getfield      #9                  // Field _factoryFeatures:I
         4: aload_1
         5: invokevirtual #67                 // Method com/fasterxml/jackson/core/JsonFactory$Feature.getMask:()I
         8: iand
         9: ifeq          16
        12: iconst_1
        13: goto          17
        16: iconst_0
        17: ireturn
      LineNumberTable:
        line 717: 0
      LocalVariableTable:
        Start  Length  Slot  Name   Signature
            0      18     0  this   Lcom/fasterxml/jackson/core/JsonFactory;
            0      18     1     f   Lcom/fasterxml/jackson/core/JsonFactory$Feature;
      StackMapTable: number_of_entries = 2
        frame_type = 16 /* same */
        frame_type = 64 /* same_locals_1_stack_item */
          stack = [ int ]

  public final int getParserFeatures();
    descriptor: ()I
    flags: (0x0011) ACC_PUBLIC, ACC_FINAL
    Code:
      stack=1, locals=1, args_size=1
         0: aload_0
         1: getfield      #11                 // Field _parserFeatures:I
         4: ireturn
      LineNumberTable:
        line 722: 0
      LocalVariableTable:
        Start  Length  Slot  Name   Signature
            0       5     0  this   Lcom/fasterxml/jackson/core/JsonFactory;

  public final int getGeneratorFeatures();
    descriptor: ()I
    flags: (0x0011) ACC_PUBLIC, ACC_FINAL
    Code:
      stack=1, locals=1, args_size=1
         0: aload_0
         1: getfield      #13                 // Field _generatorFeatures:I
         4: ireturn
      LineNumberTable:
        line 727: 0
      LocalVariableTable:
        Start  Length  Slot  Name   Signature
            0       5     0  this   Lcom/fasterxml/jackson/core/JsonFactory;

  public int getFormatParserFeatures();
    descriptor: ()I
    flags: (0x0001) ACC_PUBLIC
    Code:
      stack=1, locals=1, args_size=1
         0: iconst_0
         1: ireturn
      LineNumberTable:
        line 733: 0
      LocalVariableTable:
        Start  Length  Slot  Name   Signature
            0       2     0  this   Lcom/fasterxml/jackson/core/JsonFactory;

  public int getFormatGeneratorFeatures();
    descriptor: ()I
    flags: (0x0001) ACC_PUBLIC
    Code:
      stack=1, locals=1, args_size=1
         0: iconst_0
         1: ireturn
      LineNumberTable:
        line 739: 0
      LocalVariableTable:
        Start  Length  Slot  Name   Signature
            0       2     0  this   Lcom/fasterxml/jackson/core/JsonFactory;

  public final com.fasterxml.jackson.core.JsonFactory configure(com.fasterxml.jackson.core.JsonParser$Feature, boolean);
    descriptor: (Lcom/fasterxml/jackson/core/JsonParser$Feature;Z)Lcom/fasterxml/jackson/core/JsonFactory;
    flags: (0x0011) ACC_PUBLIC, ACC_FINAL
    Code:
      stack=2, locals=3, args_size=3
         0: iload_2
         1: ifeq          12
         4: aload_0
         5: aload_1
         6: invokevirtual #68                 // Method enable:(Lcom/fasterxml/jackson/core/JsonParser$Feature;)Lcom/fasterxml/jackson/core/JsonFactory;
         9: goto          17
        12: aload_0
        13: aload_1
        14: invokevirtual #69                 // Method disable:(Lcom/fasterxml/jackson/core/JsonParser$Feature;)Lcom/fasterxml/jackson/core/JsonFactory;
        17: areturn
      LineNumberTable:
        line 758: 0
      LocalVariableTable:
        Start  Length  Slot  Name   Signature
            0      18     0  this   Lcom/fasterxml/jackson/core/JsonFactory;
            0      18     1     f   Lcom/fasterxml/jackson/core/JsonParser$Feature;
            0      18     2 state   Z
      StackMapTable: number_of_entries = 2
        frame_type = 12 /* same */
        frame_type = 68 /* same_locals_1_stack_item */
          stack = [ class com/fasterxml/jackson/core/JsonFactory ]

  public com.fasterxml.jackson.core.JsonFactory enable(com.fasterxml.jackson.core.JsonParser$Feature);
    descriptor: (Lcom/fasterxml/jackson/core/JsonParser$Feature;)Lcom/fasterxml/jackson/core/JsonFactory;
    flags: (0x0001) ACC_PUBLIC
    Code:
      stack=3, locals=2, args_size=2
         0: aload_0
         1: dup
         2: getfield      #11                 // Field _parserFeatures:I
         5: aload_1
         6: invokevirtual #70                 // Method com/fasterxml/jackson/core/JsonParser$Feature.getMask:()I
         9: ior
        10: putfield      #11                 // Field _parserFeatures:I
        13: aload_0
        14: areturn
      LineNumberTable:
        line 770: 0
        line 771: 13
      LocalVariableTable:
        Start  Length  Slot  Name   Signature
            0      15     0  this   Lcom/fasterxml/jackson/core/JsonFactory;
            0      15     1     f   Lcom/fasterxml/jackson/core/JsonParser$Feature;

  public com.fasterxml.jackson.core.JsonFactory disable(com.fasterxml.jackson.core.JsonParser$Feature);
    descriptor: (Lcom/fasterxml/jackson/core/JsonParser$Feature;)Lcom/fasterxml/jackson/core/JsonFactory;
    flags: (0x0001) ACC_PUBLIC
    Code:
      stack=4, locals=2, args_size=2
         0: aload_0
         1: dup
         2: getfield      #11                 // Field _parserFeatures:I
         5: aload_1
         6: invokevirtual #70                 // Method com/fasterxml/jackson/core/JsonParser$Feature.getMask:()I
         9: iconst_m1
        10: ixor
        11: iand
        12: putfield      #11                 // Field _parserFeatures:I
        15: aload_0
        16: areturn
      LineNumberTable:
        line 783: 0
        line 784: 15
      LocalVariableTable:
        Start  Length  Slot  Name   Signature
            0      17     0  this   Lcom/fasterxml/jackson/core/JsonFactory;
            0      17     1     f   Lcom/fasterxml/jackson/core/JsonParser$Feature;

  public final boolean isEnabled(com.fasterxml.jackson.core.JsonParser$Feature);
    descriptor: (Lcom/fasterxml/jackson/core/JsonParser$Feature;)Z
    flags: (0x0011) ACC_PUBLIC, ACC_FINAL
    Code:
      stack=2, locals=2, args_size=2
         0: aload_0
         1: getfield      #11                 // Field _parserFeatures:I
         4: aload_1
         5: invokevirtual #70                 // Method com/fasterxml/jackson/core/JsonParser$Feature.getMask:()I
         8: iand
         9: ifeq          16
        12: iconst_1
        13: goto          17
        16: iconst_0
        17: ireturn
      LineNumberTable:
        line 796: 0
      LocalVariableTable:
        Start  Length  Slot  Name   Signature
            0      18     0  this   Lcom/fasterxml/jackson/core/JsonFactory;
            0      18     1     f   Lcom/fasterxml/jackson/core/JsonParser$Feature;
      StackMapTable: number_of_entries = 2
        frame_type = 16 /* same */
        frame_type = 64 /* same_locals_1_stack_item */
          stack = [ int ]

  public final boolean isEnabled(com.fasterxml.jackson.core.StreamReadFeature);
    descriptor: (Lcom/fasterxml/jackson/core/StreamReadFeature;)Z
    flags: (0x0011) ACC_PUBLIC, ACC_FINAL
    Code:
      stack=2, locals=2, args_size=2
         0: aload_0
         1: getfield      #11                 // Field _parserFeatures:I
         4: aload_1
         5: invokevirtual #71                 // Method com/fasterxml/jackson/core/StreamReadFeature.mappedFeature:()Lcom/fasterxml/jackson/core/JsonParser$Feature;
         8: invokevirtual #70                 // Method com/fasterxml/jackson/core/JsonParser$Feature.getMask:()I
        11: iand
        12: ifeq          19
        15: iconst_1
        16: goto          20
        19: iconst_0
        20: ireturn
      LineNumberTable:
        line 809: 0
      LocalVariableTable:
        Start  Length  Slot  Name   Signature
            0      21     0  this   Lcom/fasterxml/jackson/core/JsonFactory;
            0      21     1     f   Lcom/fasterxml/jackson/core/StreamReadFeature;
      StackMapTable: number_of_entries = 2
        frame_type = 19 /* same */
        frame_type = 64 /* same_locals_1_stack_item */
          stack = [ int ]

  public com.fasterxml.jackson.core.io.InputDecorator getInputDecorator();
    descriptor: ()Lcom/fasterxml/jackson/core/io/InputDecorator;
    flags: (0x0001) ACC_PUBLIC
    Code:
      stack=1, locals=1, args_size=1
         0: aload_0
         1: getfield      #19                 // Field _inputDecorator:Lcom/fasterxml/jackson/core/io/InputDecorator;
         4: areturn
      LineNumberTable:
        line 819: 0
      LocalVariableTable:
        Start  Length  Slot  Name   Signature
            0       5     0  this   Lcom/fasterxml/jackson/core/JsonFactory;

  public com.fasterxml.jackson.core.JsonFactory setInputDecorator(com.fasterxml.jackson.core.io.InputDecorator);
    descriptor: (Lcom/fasterxml/jackson/core/io/InputDecorator;)Lcom/fasterxml/jackson/core/JsonFactory;
    flags: (0x0001) ACC_PUBLIC
    Code:
      stack=2, locals=2, args_size=2
         0: aload_0
         1: aload_1
         2: putfield      #19                 // Field _inputDecorator:Lcom/fasterxml/jackson/core/io/InputDecorator;
         5: aload_0
         6: areturn
      LineNumberTable:
        line 833: 0
        line 834: 5
      LocalVariableTable:
        Start  Length  Slot  Name   Signature
            0       7     0  this   Lcom/fasterxml/jackson/core/JsonFactory;
            0       7     1     d   Lcom/fasterxml/jackson/core/io/InputDecorator;
    Deprecated: true
    RuntimeVisibleAnnotations:
      0: #293()
        java.lang.Deprecated

  public final com.fasterxml.jackson.core.JsonFactory configure(com.fasterxml.jackson.core.JsonGenerator$Feature, boolean);
    descriptor: (Lcom/fasterxml/jackson/core/JsonGenerator$Feature;Z)Lcom/fasterxml/jackson/core/JsonFactory;
    flags: (0x0011) ACC_PUBLIC, ACC_FINAL
    Code:
      stack=2, locals=3, args_size=3
         0: iload_2
         1: ifeq          12
         4: aload_0
         5: aload_1
         6: invokevirtual #72                 // Method enable:(Lcom/fasterxml/jackson/core/JsonGenerator$Feature;)Lcom/fasterxml/jackson/core/JsonFactory;
         9: goto          17
        12: aload_0
        13: aload_1
        14: invokevirtual #73                 // Method disable:(Lcom/fasterxml/jackson/core/JsonGenerator$Feature;)Lcom/fasterxml/jackson/core/JsonFactory;
        17: areturn
      LineNumberTable:
        line 853: 0
      LocalVariableTable:
        Start  Length  Slot  Name   Signature
            0      18     0  this   Lcom/fasterxml/jackson/core/JsonFactory;
            0      18     1     f   Lcom/fasterxml/jackson/core/JsonGenerator$Feature;
            0      18     2 state   Z
      StackMapTable: number_of_entries = 2
        frame_type = 12 /* same */
        frame_type = 68 /* same_locals_1_stack_item */
          stack = [ class com/fasterxml/jackson/core/JsonFactory ]

  public com.fasterxml.jackson.core.JsonFactory enable(com.fasterxml.jackson.core.JsonGenerator$Feature);
    descriptor: (Lcom/fasterxml/jackson/core/JsonGenerator$Feature;)Lcom/fasterxml/jackson/core/JsonFactory;
    flags: (0x0001) ACC_PUBLIC
    Code:
      stack=3, locals=2, args_size=2
         0: aload_0
         1: dup
         2: getfield      #13                 // Field _generatorFeatures:I
         5: aload_1
         6: invokevirtual #74                 // Method com/fasterxml/jackson/core/JsonGenerator$Feature.getMask:()I
         9: ior
        10: putfield      #13                 // Field _generatorFeatures:I
        13: aload_0
        14: areturn
      LineNumberTable:
        line 865: 0
        line 866: 13
      LocalVariableTable:
        Start  Length  Slot  Name   Signature
            0      15     0  this   Lcom/fasterxml/jackson/core/JsonFactory;
            0      15     1     f   Lcom/fasterxml/jackson/core/JsonGenerator$Feature;

  public com.fasterxml.jackson.core.JsonFactory disable(com.fasterxml.jackson.core.JsonGenerator$Feature);
    descriptor: (Lcom/fasterxml/jackson/core/JsonGenerator$Feature;)Lcom/fasterxml/jackson/core/JsonFactory;
    flags: (0x0001) ACC_PUBLIC
    Code:
      stack=4, locals=2, args_size=2
         0: aload_0
         1: dup
         2: getfield      #13                 // Field _generatorFeatures:I
         5: aload_1
         6: invokevirtual #74                 // Method com/fasterxml/jackson/core/JsonGenerator$Feature.getMask:()I
         9: iconst_m1
        10: ixor
        11: iand
        12: putfield      #13                 // Field _generatorFeatures:I
        15: aload_0
        16: areturn
      LineNumberTable:
        line 878: 0
        line 879: 15
      LocalVariableTable:
        Start  Length  Slot  Name   Signature
            0      17     0  this   Lcom/fasterxml/jackson/core/JsonFactory;
            0      17     1     f   Lcom/fasterxml/jackson/core/JsonGenerator$Feature;

  public final boolean isEnabled(com.fasterxml.jackson.core.JsonGenerator$Feature);
    descriptor: (Lcom/fasterxml/jackson/core/JsonGenerator$Feature;)Z
    flags: (0x0011) ACC_PUBLIC, ACC_FINAL
    Code:
      stack=2, locals=2, args_size=2
         0: aload_0
         1: getfield      #13                 // Field _generatorFeatures:I
         4: aload_1
         5: invokevirtual #74                 // Method com/fasterxml/jackson/core/JsonGenerator$Feature.getMask:()I
         8: iand
         9: ifeq          16
        12: iconst_1
        13: goto          17
        16: iconst_0
        17: ireturn
      LineNumberTable:
        line 891: 0
      LocalVariableTable:
        Start  Length  Slot  Name   Signature
            0      18     0  this   Lcom/fasterxml/jackson/core/JsonFactory;
            0      18     1     f   Lcom/fasterxml/jackson/core/JsonGenerator$Feature;
      StackMapTable: number_of_entries = 2
        frame_type = 16 /* same */
        frame_type = 64 /* same_locals_1_stack_item */
          stack = [ int ]

  public final boolean isEnabled(com.fasterxml.jackson.core.StreamWriteFeature);
    descriptor: (Lcom/fasterxml/jackson/core/StreamWriteFeature;)Z
    flags: (0x0011) ACC_PUBLIC, ACC_FINAL
    Code:
      stack=2, locals=2, args_size=2
         0: aload_0
         1: getfield      #13                 // Field _generatorFeatures:I
         4: aload_1
         5: invokevirtual #75                 // Method com/fasterxml/jackson/core/StreamWriteFeature.mappedFeature:()Lcom/fasterxml/jackson/core/JsonGenerator$Feature;
         8: invokevirtual #74                 // Method com/fasterxml/jackson/core/JsonGenerator$Feature.getMask:()I
        11: iand
        12: ifeq          19
        15: iconst_1
        16: goto          20
        19: iconst_0
        20: ireturn
      LineNumberTable:
        line 904: 0
      LocalVariableTable:
        Start  Length  Slot  Name   Signature
            0      21     0  this   Lcom/fasterxml/jackson/core/JsonFactory;
            0      21     1     f   Lcom/fasterxml/jackson/core/StreamWriteFeature;
      StackMapTable: number_of_entries = 2
        frame_type = 19 /* same */
        frame_type = 64 /* same_locals_1_stack_item */
          stack = [ int ]

  public com.fasterxml.jackson.core.io.CharacterEscapes getCharacterEscapes();
    descriptor: ()Lcom/fasterxml/jackson/core/io/CharacterEscapes;
    flags: (0x0001) ACC_PUBLIC
    Code:
      stack=1, locals=1, args_size=1
         0: aload_0
         1: getfield      #21                 // Field _characterEscapes:Lcom/fasterxml/jackson/core/io/CharacterEscapes;
         4: areturn
      LineNumberTable:
        line 913: 0
      LocalVariableTable:
        Start  Length  Slot  Name   Signature
            0       5     0  this   Lcom/fasterxml/jackson/core/JsonFactory;

  public com.fasterxml.jackson.core.JsonFactory setCharacterEscapes(com.fasterxml.jackson.core.io.CharacterEscapes);
    descriptor: (Lcom/fasterxml/jackson/core/io/CharacterEscapes;)Lcom/fasterxml/jackson/core/JsonFactory;
    flags: (0x0001) ACC_PUBLIC
    Code:
      stack=2, locals=2, args_size=2
         0: aload_0
         1: aload_1
         2: putfield      #21                 // Field _characterEscapes:Lcom/fasterxml/jackson/core/io/CharacterEscapes;
         5: aload_0
         6: areturn
      LineNumberTable:
        line 924: 0
        line 925: 5
      LocalVariableTable:
        Start  Length  Slot  Name   Signature
            0       7     0  this   Lcom/fasterxml/jackson/core/JsonFactory;
            0       7     1   esc   Lcom/fasterxml/jackson/core/io/CharacterEscapes;

  public com.fasterxml.jackson.core.io.OutputDecorator getOutputDecorator();
    descriptor: ()Lcom/fasterxml/jackson/core/io/OutputDecorator;
    flags: (0x0001) ACC_PUBLIC
    Code:
      stack=1, locals=1, args_size=1
         0: aload_0
         1: getfield      #20                 // Field _outputDecorator:Lcom/fasterxml/jackson/core/io/OutputDecorator;
         4: areturn
      LineNumberTable:
        line 936: 0
      LocalVariableTable:
        Start  Length  Slot  Name   Signature
            0       5     0  this   Lcom/fasterxml/jackson/core/JsonFactory;

  public com.fasterxml.jackson.core.JsonFactory setOutputDecorator(com.fasterxml.jackson.core.io.OutputDecorator);
    descriptor: (Lcom/fasterxml/jackson/core/io/OutputDecorator;)Lcom/fasterxml/jackson/core/JsonFactory;
    flags: (0x0001) ACC_PUBLIC
    Code:
      stack=2, locals=2, args_size=2
         0: aload_0
         1: aload_1
         2: putfield      #20                 // Field _outputDecorator:Lcom/fasterxml/jackson/core/io/OutputDecorator;
         5: aload_0
         6: areturn
      LineNumberTable:
        line 950: 0
        line 951: 5
      LocalVariableTable:
        Start  Length  Slot  Name   Signature
            0       7     0  this   Lcom/fasterxml/jackson/core/JsonFactory;
            0       7     1     d   Lcom/fasterxml/jackson/core/io/OutputDecorator;
    Deprecated: true
    RuntimeVisibleAnnotations:
      0: #293()
        java.lang.Deprecated

  public com.fasterxml.jackson.core.JsonFactory setRootValueSeparator(java.lang.String);
    descriptor: (Ljava/lang/String;)Lcom/fasterxml/jackson/core/JsonFactory;
    flags: (0x0001) ACC_PUBLIC
    Code:
      stack=4, locals=2, args_size=2
         0: aload_0
         1: aload_1
         2: ifnonnull     9
         5: aconst_null
         6: goto          17
         9: new           #76                 // class com/fasterxml/jackson/core/io/SerializedString
        12: dup
        13: aload_1
        14: invokespecial #77                 // Method com/fasterxml/jackson/core/io/SerializedString."<init>":(Ljava/lang/String;)V
        17: putfield      #15                 // Field _rootValueSeparator:Lcom/fasterxml/jackson/core/SerializableString;
        20: aload_0
        21: areturn
      LineNumberTable:
        line 964: 0
        line 965: 20
      LocalVariableTable:
        Start  Length  Slot  Name   Signature
            0      22     0  this   Lcom/fasterxml/jackson/core/JsonFactory;
            0      22     1   sep   Ljava/lang/String;
      StackMapTable: number_of_entries = 2
        frame_type = 73 /* same_locals_1_stack_item */
          stack = [ class com/fasterxml/jackson/core/JsonFactory ]
        frame_type = 255 /* full_frame */
          offset_delta = 7
          locals = [ class com/fasterxml/jackson/core/JsonFactory, class java/lang/String ]
          stack = [ class com/fasterxml/jackson/core/JsonFactory, class com/fasterxml/jackson/core/io/SerializedString ]

  public java.lang.String getRootValueSeparator();
    descriptor: ()Ljava/lang/String;
    flags: (0x0001) ACC_PUBLIC
    Code:
      stack=1, locals=1, args_size=1
         0: aload_0
         1: getfield      #15                 // Field _rootValueSeparator:Lcom/fasterxml/jackson/core/SerializableString;
         4: ifnonnull     11
         7: aconst_null
         8: goto          20
        11: aload_0
        12: getfield      #15                 // Field _rootValueSeparator:Lcom/fasterxml/jackson/core/SerializableString;
        15: invokeinterface #78,  1           // InterfaceMethod com/fasterxml/jackson/core/SerializableString.getValue:()Ljava/lang/String;
        20: areturn
      LineNumberTable:
        line 972: 0
      LocalVariableTable:
        Start  Length  Slot  Name   Signature
            0      21     0  this   Lcom/fasterxml/jackson/core/JsonFactory;
      StackMapTable: number_of_entries = 2
        frame_type = 11 /* same */
        frame_type = 72 /* same_locals_1_stack_item */
          stack = [ class java/lang/String ]

  public com.fasterxml.jackson.core.JsonFactory setCodec(com.fasterxml.jackson.core.ObjectCodec);
    descriptor: (Lcom/fasterxml/jackson/core/ObjectCodec;)Lcom/fasterxml/jackson/core/JsonFactory;
    flags: (0x0001) ACC_PUBLIC
    Code:
      stack=2, locals=2, args_size=2
         0: aload_0
         1: aload_1
         2: putfield      #16                 // Field _objectCodec:Lcom/fasterxml/jackson/core/ObjectCodec;
         5: aload_0
         6: areturn
      LineNumberTable:
        line 993: 0
        line 994: 5
      LocalVariableTable:
        Start  Length  Slot  Name   Signature
            0       7     0  this   Lcom/fasterxml/jackson/core/JsonFactory;
            0       7     1    oc   Lcom/fasterxml/jackson/core/ObjectCodec;

  public com.fasterxml.jackson.core.ObjectCodec getCodec();
    descriptor: ()Lcom/fasterxml/jackson/core/ObjectCodec;
    flags: (0x0001) ACC_PUBLIC
    Code:
      stack=1, locals=1, args_size=1
         0: aload_0
         1: getfield      #16                 // Field _objectCodec:Lcom/fasterxml/jackson/core/ObjectCodec;
         4: areturn
      LineNumberTable:
        line 997: 0
      LocalVariableTable:
        Start  Length  Slot  Name   Signature
            0       5     0  this   Lcom/fasterxml/jackson/core/JsonFactory;

  public com.fasterxml.jackson.core.JsonParser createParser(java.io.File) throws java.io.IOException, com.fasterxml.jackson.core.JsonParseException;
    descriptor: (Ljava/io/File;)Lcom/fasterxml/jackson/core/JsonParser;
    flags: (0x0001) ACC_PUBLIC
    Code:
      stack=4, locals=4, args_size=2
         0: aload_0
         1: aload_0
         2: aload_1
         3: invokevirtual #79                 // Method _createContentReference:(Ljava/lang/Object;)Lcom/fasterxml/jackson/core/io/ContentReference;
         6: iconst_1
         7: invokevirtual #80                 // Method _createContext:(Lcom/fasterxml/jackson/core/io/ContentReference;Z)Lcom/fasterxml/jackson/core/io/IOContext;
        10: astore_2
        11: new           #81                 // class java/io/FileInputStream
        14: dup
        15: aload_1
        16: invokespecial #82                 // Method java/io/FileInputStream."<init>":(Ljava/io/File;)V
        19: astore_3
        20: aload_0
        21: aload_0
        22: aload_3
        23: aload_2
        24: invokevirtual #83                 // Method _decorate:(Ljava/io/InputStream;Lcom/fasterxml/jackson/core/io/IOContext;)Ljava/io/InputStream;
        27: aload_2
        28: invokevirtual #84                 // Method _createParser:(Ljava/io/InputStream;Lcom/fasterxml/jackson/core/io/IOContext;)Lcom/fasterxml/jackson/core/JsonParser;
        31: areturn
      LineNumberTable:
        line 1028: 0
        line 1029: 11
        line 1030: 20
      LocalVariableTable:
        Start  Length  Slot  Name   Signature
            0      32     0  this   Lcom/fasterxml/jackson/core/JsonFactory;
            0      32     1     f   Ljava/io/File;
           11      21     2  ctxt   Lcom/fasterxml/jackson/core/io/IOContext;
           20      12     3    in   Ljava/io/InputStream;
    Exceptions:
      throws java.io.IOException, com.fasterxml.jackson.core.JsonParseException

  public com.fasterxml.jackson.core.JsonParser createParser(java.net.URL) throws java.io.IOException, com.fasterxml.jackson.core.JsonParseException;
    descriptor: (Ljava/net/URL;)Lcom/fasterxml/jackson/core/JsonParser;
    flags: (0x0001) ACC_PUBLIC
    Code:
      stack=4, locals=4, args_size=2
         0: aload_0
         1: aload_0
         2: aload_1
         3: invokevirtual #79                 // Method _createContentReference:(Ljava/lang/Object;)Lcom/fasterxml/jackson/core/io/ContentReference;
         6: iconst_1
         7: invokevirtual #80                 // Method _createContext:(Lcom/fasterxml/jackson/core/io/ContentReference;Z)Lcom/fasterxml/jackson/core/io/IOContext;
        10: astore_2
        11: aload_0
        12: aload_1
        13: invokevirtual #85                 // Method _optimizedStreamFromURL:(Ljava/net/URL;)Ljava/io/InputStream;
        16: astore_3
        17: aload_0
        18: aload_0
        19: aload_3
        20: aload_2
        21: invokevirtual #83                 // Method _decorate:(Ljava/io/InputStream;Lcom/fasterxml/jackson/core/io/IOContext;)Ljava/io/InputStream;
        24: aload_2
        25: invokevirtual #84                 // Method _createParser:(Ljava/io/InputStream;Lcom/fasterxml/jackson/core/io/IOContext;)Lcom/fasterxml/jackson/core/JsonParser;
        28: areturn
      LineNumberTable:
        line 1054: 0
        line 1055: 11
        line 1056: 17
      LocalVariableTable:
        Start  Length  Slot  Name   Signature
            0      29     0  this   Lcom/fasterxml/jackson/core/JsonFactory;
            0      29     1   url   Ljava/net/URL;
           11      18     2  ctxt   Lcom/fasterxml/jackson/core/io/IOContext;
           17      12     3    in   Ljava/io/InputStream;
    Exceptions:
      throws java.io.IOException, com.fasterxml.jackson.core.JsonParseException

  public com.fasterxml.jackson.core.JsonParser createParser(java.io.InputStream) throws java.io.IOException, com.fasterxml.jackson.core.JsonParseException;
    descriptor: (Ljava/io/InputStream;)Lcom/fasterxml/jackson/core/JsonParser;
    flags: (0x0001) ACC_PUBLIC
    Code:
      stack=4, locals=3, args_size=2
         0: aload_0
         1: aload_0
         2: aload_1
         3: invokevirtual #79                 // Method _createContentReference:(Ljava/lang/Object;)Lcom/fasterxml/jackson/core/io/ContentReference;
         6: iconst_0
         7: invokevirtual #80                 // Method _createContext:(Lcom/fasterxml/jackson/core/io/ContentReference;Z)Lcom/fasterxml/jackson/core/io/IOContext;
        10: astore_2
        11: aload_0
        12: aload_0
        13: aload_1
        14: aload_2
        15: invokevirtual #83                 // Method _decorate:(Ljava/io/InputStream;Lcom/fasterxml/jackson/core/io/IOContext;)Ljava/io/InputStream;
        18: aload_2
        19: invokevirtual #84                 // Method _createParser:(Ljava/io/InputStream;Lcom/fasterxml/jackson/core/io/IOContext;)Lcom/fasterxml/jackson/core/JsonParser;
        22: areturn
      LineNumberTable:
        line 1082: 0
        line 1083: 11
      LocalVariableTable:
        Start  Length  Slot  Name   Signature
            0      23     0  this   Lcom/fasterxml/jackson/core/JsonFactory;
            0      23     1    in   Ljava/io/InputStream;
           11      12     2  ctxt   Lcom/fasterxml/jackson/core/io/IOContext;
    Exceptions:
      throws java.io.IOException, com.fasterxml.jackson.core.JsonParseException

  public com.fasterxml.jackson.core.JsonParser createParser(java.io.Reader) throws java.io.IOException, com.fasterxml.jackson.core.JsonParseException;
    descriptor: (Ljava/io/Reader;)Lcom/fasterxml/jackson/core/JsonParser;
    flags: (0x0001) ACC_PUBLIC
    Code:
      stack=4, locals=3, args_size=2
         0: aload_0
         1: aload_0
         2: aload_1
         3: invokevirtual #79                 // Method _createContentReference:(Ljava/lang/Object;)Lcom/fasterxml/jackson/core/io/ContentReference;
         6: iconst_0
         7: invokevirtual #80                 // Method _createContext:(Lcom/fasterxml/jackson/core/io/ContentReference;Z)Lcom/fasterxml/jackson/core/io/IOContext;
        10: astore_2
        11: aload_0
        12: aload_0
        13: aload_1
        14: aload_2
        15: invokevirtual #86                 // Method _decorate:(Ljava/io/Reader;Lcom/fasterxml/jackson/core/io/IOContext;)Ljava/io/Reader;
        18: aload_2
        19: invokevirtual #87                 // Method _createParser:(Ljava/io/Reader;Lcom/fasterxml/jackson/core/io/IOContext;)Lcom/fasterxml/jackson/core/JsonParser;
        22: areturn
      LineNumberTable:
        line 1103: 0
        line 1104: 11
      LocalVariableTable:
        Start  Length  Slot  Name   Signature
            0      23     0  this   Lcom/fasterxml/jackson/core/JsonFactory;
            0      23     1     r   Ljava/io/Reader;
           11      12     2  ctxt   Lcom/fasterxml/jackson/core/io/IOContext;
    Exceptions:
      throws java.io.IOException, com.fasterxml.jackson.core.JsonParseException

  public com.fasterxml.jackson.core.JsonParser createParser(byte[]) throws java.io.IOException, com.fasterxml.jackson.core.JsonParseException;
    descriptor: ([B)Lcom/fasterxml/jackson/core/JsonParser;
    flags: (0x0001) ACC_PUBLIC
    Code:
      stack=5, locals=4, args_size=2
         0: aload_0
         1: aload_0
         2: aload_1
         3: invokevirtual #79                 // Method _createContentReference:(Ljava/lang/Object;)Lcom/fasterxml/jackson/core/io/ContentReference;
         6: iconst_1
         7: invokevirtual #80                 // Method _createContext:(Lcom/fasterxml/jackson/core/io/ContentReference;Z)Lcom/fasterxml/jackson/core/io/IOContext;
        10: astore_2
        11: aload_0
        12: getfield      #19                 // Field _inputDecorator:Lcom/fasterxml/jackson/core/io/InputDecorator;
        15: ifnull        42
        18: aload_0
        19: getfield      #19                 // Field _inputDecorator:Lcom/fasterxml/jackson/core/io/InputDecorator;
        22: aload_2
        23: aload_1
        24: iconst_0
        25: aload_1
        26: arraylength
        27: invokevirtual #88                 // Method com/fasterxml/jackson/core/io/InputDecorator.decorate:(Lcom/fasterxml/jackson/core/io/IOContext;[BII)Ljava/io/InputStream;
        30: astore_3
        31: aload_3
        32: ifnull        42
        35: aload_0
        36: aload_3
        37: aload_2
        38: invokevirtual #84                 // Method _createParser:(Ljava/io/InputStream;Lcom/fasterxml/jackson/core/io/IOContext;)Lcom/fasterxml/jackson/core/JsonParser;
        41: areturn
        42: aload_0
        43: aload_1
        44: iconst_0
        45: aload_1
        46: arraylength
        47: aload_2
        48: invokevirtual #89                 // Method _createParser:([BIILcom/fasterxml/jackson/core/io/IOContext;)Lcom/fasterxml/jackson/core/JsonParser;
        51: areturn
      LineNumberTable:
        line 1115: 0
        line 1116: 11
        line 1117: 18
        line 1118: 31
        line 1119: 35
        line 1122: 42
      LocalVariableTable:
        Start  Length  Slot  Name   Signature
           31      11     3    in   Ljava/io/InputStream;
            0      52     0  this   Lcom/fasterxml/jackson/core/JsonFactory;
            0      52     1  data   [B
           11      41     2  ctxt   Lcom/fasterxml/jackson/core/io/IOContext;
      StackMapTable: number_of_entries = 1
        frame_type = 252 /* append */
          offset_delta = 42
          locals = [ class com/fasterxml/jackson/core/io/IOContext ]
    Exceptions:
      throws java.io.IOException, com.fasterxml.jackson.core.JsonParseException

  public com.fasterxml.jackson.core.JsonParser createParser(byte[], int, int) throws java.io.IOException, com.fasterxml.jackson.core.JsonParseException;
    descriptor: ([BII)Lcom/fasterxml/jackson/core/JsonParser;
    flags: (0x0001) ACC_PUBLIC
    Code:
      stack=5, locals=6, args_size=4
         0: aload_0
         1: aload_0
         2: aload_1
         3: iload_2
         4: iload_3
         5: invokevirtual #90                 // Method _createContentReference:(Ljava/lang/Object;II)Lcom/fasterxml/jackson/core/io/ContentReference;
         8: iconst_1
         9: invokevirtual #80                 // Method _createContext:(Lcom/fasterxml/jackson/core/io/ContentReference;Z)Lcom/fasterxml/jackson/core/io/IOContext;
        12: astore        4
        14: aload_0
        15: getfield      #19                 // Field _inputDecorator:Lcom/fasterxml/jackson/core/io/InputDecorator;
        18: ifnull        49
        21: aload_0
        22: getfield      #19                 // Field _inputDecorator:Lcom/fasterxml/jackson/core/io/InputDecorator;
        25: aload         4
        27: aload_1
        28: iload_2
        29: iload_3
        30: invokevirtual #88                 // Method com/fasterxml/jackson/core/io/InputDecorator.decorate:(Lcom/fasterxml/jackson/core/io/IOContext;[BII)Ljava/io/InputStream;
        33: astore        5
        35: aload         5
        37: ifnull        49
        40: aload_0
        41: aload         5
        43: aload         4
        45: invokevirtual #84                 // Method _createParser:(Ljava/io/InputStream;Lcom/fasterxml/jackson/core/io/IOContext;)Lcom/fasterxml/jackson/core/JsonParser;
        48: areturn
        49: aload_0
        50: aload_1
        51: iload_2
        52: iload_3
        53: aload         4
        55: invokevirtual #89                 // Method _createParser:([BIILcom/fasterxml/jackson/core/io/IOContext;)Lcom/fasterxml/jackson/core/JsonParser;
        58: areturn
      LineNumberTable:
        line 1137: 0
        line 1139: 14
        line 1140: 21
        line 1141: 35
        line 1142: 40
        line 1145: 49
      LocalVariableTable:
        Start  Length  Slot  Name   Signature
           35      14     5    in   Ljava/io/InputStream;
            0      59     0  this   Lcom/fasterxml/jackson/core/JsonFactory;
            0      59     1  data   [B
            0      59     2 offset   I
            0      59     3   len   I
           14      45     4  ctxt   Lcom/fasterxml/jackson/core/io/IOContext;
      StackMapTable: number_of_entries = 1
        frame_type = 252 /* append */
          offset_delta = 49
          locals = [ class com/fasterxml/jackson/core/io/IOContext ]
    Exceptions:
      throws java.io.IOException, com.fasterxml.jackson.core.JsonParseException

  public com.fasterxml.jackson.core.JsonParser createParser(java.lang.String) throws java.io.IOException, com.fasterxml.jackson.core.JsonParseException;
    descriptor: (Ljava/lang/String;)Lcom/fasterxml/jackson/core/JsonParser;
    flags: (0x0001) ACC_PUBLIC
    Code:
      stack=6, locals=5, args_size=2
         0: aload_1
         1: invokevirtual #91                 // Method java/lang/String.length:()I
         4: istore_2
         5: aload_0
         6: getfield      #19                 // Field _inputDecorator:Lcom/fasterxml/jackson/core/io/InputDecorator;
         9: ifnonnull     25
        12: iload_2
        13: ldc           #92                 // int 32768
        15: if_icmpgt     25
        18: aload_0
        19: invokevirtual #93                 // Method canUseCharArrays:()Z
        22: ifne          38
        25: aload_0
        26: new           #94                 // class java/io/StringReader
        29: dup
        30: aload_1
        31: invokespecial #95                 // Method java/io/StringReader."<init>":(Ljava/lang/String;)V
        34: invokevirtual #96                 // Method createParser:(Ljava/io/Reader;)Lcom/fasterxml/jackson/core/JsonParser;
        37: areturn
        38: aload_0
        39: aload_0
        40: aload_1
        41: invokevirtual #79                 // Method _createContentReference:(Ljava/lang/Object;)Lcom/fasterxml/jackson/core/io/ContentReference;
        44: iconst_1
        45: invokevirtual #80                 // Method _createContext:(Lcom/fasterxml/jackson/core/io/ContentReference;Z)Lcom/fasterxml/jackson/core/io/IOContext;
        48: astore_3
        49: aload_3
        50: iload_2
        51: invokevirtual #97                 // Method com/fasterxml/jackson/core/io/IOContext.allocTokenBuffer:(I)[C
        54: astore        4
        56: aload_1
        57: iconst_0
        58: iload_2
        59: aload         4
        61: iconst_0
        62: invokevirtual #98                 // Method java/lang/String.getChars:(II[CI)V
        65: aload_0
        66: aload         4
        68: iconst_0
        69: iload_2
        70: aload_3
        71: iconst_1
        72: invokevirtual #99                 // Method _createParser:([CIILcom/fasterxml/jackson/core/io/IOContext;Z)Lcom/fasterxml/jackson/core/JsonParser;
        75: areturn
      LineNumberTable:
        line 1156: 0
        line 1158: 5
        line 1161: 25
        line 1163: 38
        line 1164: 49
        line 1165: 56
        line 1166: 65
      LocalVariableTable:
        Start  Length  Slot  Name   Signature
            0      76     0  this   Lcom/fasterxml/jackson/core/JsonFactory;
            0      76     1 content   Ljava/lang/String;
            5      71     2 strLen   I
           49      27     3  ctxt   Lcom/fasterxml/jackson/core/io/IOContext;
           56      20     4   buf   [C
      StackMapTable: number_of_entries = 2
        frame_type = 252 /* append */
          offset_delta = 25
          locals = [ int ]
        frame_type = 12 /* same */
    Exceptions:
      throws java.io.IOException, com.fasterxml.jackson.core.JsonParseException

  public com.fasterxml.jackson.core.JsonParser createParser(char[]) throws java.io.IOException;
    descriptor: ([C)Lcom/fasterxml/jackson/core/JsonParser;
    flags: (0x0001) ACC_PUBLIC
    Code:
      stack=4, locals=2, args_size=2
         0: aload_0
         1: aload_1
         2: iconst_0
         3: aload_1
         4: arraylength
         5: invokevirtual #100                // Method createParser:([CII)Lcom/fasterxml/jackson/core/JsonParser;
         8: areturn
      LineNumberTable:
        line 1177: 0
      LocalVariableTable:
        Start  Length  Slot  Name   Signature
            0       9     0  this   Lcom/fasterxml/jackson/core/JsonFactory;
            0       9     1 content   [C
    Exceptions:
      throws java.io.IOException

  public com.fasterxml.jackson.core.JsonParser createParser(char[], int, int) throws java.io.IOException;
    descriptor: ([CII)Lcom/fasterxml/jackson/core/JsonParser;
    flags: (0x0001) ACC_PUBLIC
    Code:
      stack=9, locals=4, args_size=4
         0: aload_0
         1: getfield      #19                 // Field _inputDecorator:Lcom/fasterxml/jackson/core/io/InputDecorator;
         4: ifnull        22
         7: aload_0
         8: new           #101                // class java/io/CharArrayReader
        11: dup
        12: aload_1
        13: iload_2
        14: iload_3
        15: invokespecial #102                // Method java/io/CharArrayReader."<init>":([CII)V
        18: invokevirtual #96                 // Method createParser:(Ljava/io/Reader;)Lcom/fasterxml/jackson/core/JsonParser;
        21: areturn
        22: aload_0
        23: aload_1
        24: iload_2
        25: iload_3
        26: aload_0
        27: aload_0
        28: aload_1
        29: iload_2
        30: iload_3
        31: invokevirtual #90                 // Method _createContentReference:(Ljava/lang/Object;II)Lcom/fasterxml/jackson/core/io/ContentReference;
        34: iconst_1
        35: invokevirtual #80                 // Method _createContext:(Lcom/fasterxml/jackson/core/io/ContentReference;Z)Lcom/fasterxml/jackson/core/io/IOContext;
        38: iconst_0
        39: invokevirtual #99                 // Method _createParser:([CIILcom/fasterxml/jackson/core/io/IOContext;Z)Lcom/fasterxml/jackson/core/JsonParser;
        42: areturn
      LineNumberTable:
        line 1187: 0
        line 1188: 7
        line 1190: 22
        line 1191: 31
        line 1190: 39
      LocalVariableTable:
        Start  Length  Slot  Name   Signature
            0      43     0  this   Lcom/fasterxml/jackson/core/JsonFactory;
            0      43     1 content   [C
            0      43     2 offset   I
            0      43     3   len   I
      StackMapTable: number_of_entries = 1
        frame_type = 22 /* same */
    Exceptions:
      throws java.io.IOException

  public com.fasterxml.jackson.core.JsonParser createParser(java.io.DataInput) throws java.io.IOException;
    descriptor: (Ljava/io/DataInput;)Lcom/fasterxml/jackson/core/JsonParser;
    flags: (0x0001) ACC_PUBLIC
    Code:
      stack=4, locals=3, args_size=2
         0: aload_0
         1: aload_0
         2: aload_1
         3: invokevirtual #79                 // Method _createContentReference:(Ljava/lang/Object;)Lcom/fasterxml/jackson/core/io/ContentReference;
         6: iconst_0
         7: invokevirtual #80                 // Method _createContext:(Lcom/fasterxml/jackson/core/io/ContentReference;Z)Lcom/fasterxml/jackson/core/io/IOContext;
        10: astore_2
        11: aload_0
        12: aload_0
        13: aload_1
        14: aload_2
        15: invokevirtual #103                // Method _decorate:(Ljava/io/DataInput;Lcom/fasterxml/jackson/core/io/IOContext;)Ljava/io/DataInput;
        18: aload_2
        19: invokevirtual #104                // Method _createParser:(Ljava/io/DataInput;Lcom/fasterxml/jackson/core/io/IOContext;)Lcom/fasterxml/jackson/core/JsonParser;
        22: areturn
      LineNumberTable:
        line 1207: 0
        line 1208: 11
      LocalVariableTable:
        Start  Length  Slot  Name   Signature
            0      23     0  this   Lcom/fasterxml/jackson/core/JsonFactory;
            0      23     1    in   Ljava/io/DataInput;
           11      12     2  ctxt   Lcom/fasterxml/jackson/core/io/IOContext;
    Exceptions:
      throws java.io.IOException

  public com.fasterxml.jackson.core.JsonParser createNonBlockingByteArrayParser() throws java.io.IOException;
    descriptor: ()Lcom/fasterxml/jackson/core/JsonParser;
    flags: (0x0001) ACC_PUBLIC
    Code:
      stack=5, locals=3, args_size=1
         0: aload_0
         1: ldc           #105                // String Non-blocking source not (yet?) supported for this format (%s)
         3: invokespecial #38                 // Method _requireJSONFactory:(Ljava/lang/String;)V
         6: aload_0
         7: aconst_null
         8: invokevirtual #106                // Method _createNonBlockingContext:(Ljava/lang/Object;)Lcom/fasterxml/jackson/core/io/IOContext;
        11: astore_1
        12: aload_0
        13: getfield      #7                  // Field _byteSymbolCanonicalizer:Lcom/fasterxml/jackson/core/sym/ByteQuadsCanonicalizer;
        16: aload_0
        17: getfield      #9                  // Field _factoryFeatures:I
        20: invokevirtual #107                // Method com/fasterxml/jackson/core/sym/ByteQuadsCanonicalizer.makeChild:(I)Lcom/fasterxml/jackson/core/sym/ByteQuadsCanonicalizer;
        23: astore_2
        24: new           #108                // class com/fasterxml/jackson/core/json/async/NonBlockingJsonParser
        27: dup
        28: aload_1
        29: aload_0
        30: getfield      #11                 // Field _parserFeatures:I
        33: aload_2
        34: invokespecial #109                // Method com/fasterxml/jackson/core/json/async/NonBlockingJsonParser."<init>":(Lcom/fasterxml/jackson/core/io/IOContext;ILcom/fasterxml/jackson/core/sym/ByteQuadsCanonicalizer;)V
        37: areturn
      LineNumberTable:
        line 1238: 0
        line 1239: 6
        line 1240: 12
        line 1241: 24
      LocalVariableTable:
        Start  Length  Slot  Name   Signature
            0      38     0  this   Lcom/fasterxml/jackson/core/JsonFactory;
           12      26     1  ctxt   Lcom/fasterxml/jackson/core/io/IOContext;
           24      14     2   can   Lcom/fasterxml/jackson/core/sym/ByteQuadsCanonicalizer;
    Exceptions:
      throws java.io.IOException

  public com.fasterxml.jackson.core.JsonGenerator createGenerator(java.io.OutputStream, com.fasterxml.jackson.core.JsonEncoding) throws java.io.IOException;
    descriptor: (Ljava/io/OutputStream;Lcom/fasterxml/jackson/core/JsonEncoding;)Lcom/fasterxml/jackson/core/JsonGenerator;
    flags: (0x0001) ACC_PUBLIC
    Code:
      stack=4, locals=5, args_size=3
         0: aload_0
         1: aload_0
         2: aload_1
         3: invokevirtual #79                 // Method _createContentReference:(Ljava/lang/Object;)Lcom/fasterxml/jackson/core/io/ContentReference;
         6: iconst_0
         7: invokevirtual #80                 // Method _createContext:(Lcom/fasterxml/jackson/core/io/ContentReference;Z)Lcom/fasterxml/jackson/core/io/IOContext;
        10: astore_3
        11: aload_3
        12: aload_2
        13: invokevirtual #110                // Method com/fasterxml/jackson/core/io/IOContext.setEncoding:(Lcom/fasterxml/jackson/core/JsonEncoding;)V
        16: aload_2
        17: getstatic     #111                // Field com/fasterxml/jackson/core/JsonEncoding.UTF8:Lcom/fasterxml/jackson/core/JsonEncoding;
        20: if_acmpne     35
        23: aload_0
        24: aload_0
        25: aload_1
        26: aload_3
        27: invokevirtual #112                // Method _decorate:(Ljava/io/OutputStream;Lcom/fasterxml/jackson/core/io/IOContext;)Ljava/io/OutputStream;
        30: aload_3
        31: invokevirtual #113                // Method _createUTF8Generator:(Ljava/io/OutputStream;Lcom/fasterxml/jackson/core/io/IOContext;)Lcom/fasterxml/jackson/core/JsonGenerator;
        34: areturn
        35: aload_0
        36: aload_1
        37: aload_2
        38: aload_3
        39: invokevirtual #114                // Method _createWriter:(Ljava/io/OutputStream;Lcom/fasterxml/jackson/core/JsonEncoding;Lcom/fasterxml/jackson/core/io/IOContext;)Ljava/io/Writer;
        42: astore        4
        44: aload_0
        45: aload_0
        46: aload         4
        48: aload_3
        49: invokevirtual #115                // Method _decorate:(Ljava/io/Writer;Lcom/fasterxml/jackson/core/io/IOContext;)Ljava/io/Writer;
        52: aload_3
        53: invokevirtual #116                // Method _createGenerator:(Ljava/io/Writer;Lcom/fasterxml/jackson/core/io/IOContext;)Lcom/fasterxml/jackson/core/JsonGenerator;
        56: areturn
      LineNumberTable:
        line 1277: 0
        line 1278: 11
        line 1279: 16
        line 1280: 23
        line 1282: 35
        line 1283: 44
      LocalVariableTable:
        Start  Length  Slot  Name   Signature
            0      57     0  this   Lcom/fasterxml/jackson/core/JsonFactory;
            0      57     1   out   Ljava/io/OutputStream;
            0      57     2   enc   Lcom/fasterxml/jackson/core/JsonEncoding;
           11      46     3  ctxt   Lcom/fasterxml/jackson/core/io/IOContext;
           44      13     4     w   Ljava/io/Writer;
      StackMapTable: number_of_entries = 1
        frame_type = 252 /* append */
          offset_delta = 35
          locals = [ class com/fasterxml/jackson/core/io/IOContext ]
    Exceptions:
      throws java.io.IOException

  public com.fasterxml.jackson.core.JsonGenerator createGenerator(java.io.OutputStream) throws java.io.IOException;
    descriptor: (Ljava/io/OutputStream;)Lcom/fasterxml/jackson/core/JsonGenerator;
    flags: (0x0001) ACC_PUBLIC
    Code:
      stack=3, locals=2, args_size=2
         0: aload_0
         1: aload_1
         2: getstatic     #111                // Field com/fasterxml/jackson/core/JsonEncoding.UTF8:Lcom/fasterxml/jackson/core/JsonEncoding;
         5: invokevirtual #117                // Method createGenerator:(Ljava/io/OutputStream;Lcom/fasterxml/jackson/core/JsonEncoding;)Lcom/fasterxml/jackson/core/JsonGenerator;
         8: areturn
      LineNumberTable:
        line 1296: 0
      LocalVariableTable:
        Start  Length  Slot  Name   Signature
            0       9     0  this   Lcom/fasterxml/jackson/core/JsonFactory;
            0       9     1   out   Ljava/io/OutputStream;
    Exceptions:
      throws java.io.IOException

  public com.fasterxml.jackson.core.JsonGenerator createGenerator(java.io.Writer) throws java.io.IOException;
    descriptor: (Ljava/io/Writer;)Lcom/fasterxml/jackson/core/JsonGenerator;
    flags: (0x0001) ACC_PUBLIC
    Code:
      stack=4, locals=3, args_size=2
         0: aload_0
         1: aload_0
         2: aload_1
         3: invokevirtual #79                 // Method _createContentReference:(Ljava/lang/Object;)Lcom/fasterxml/jackson/core/io/ContentReference;
         6: iconst_0
         7: invokevirtual #80                 // Method _createContext:(Lcom/fasterxml/jackson/core/io/ContentReference;Z)Lcom/fasterxml/jackson/core/io/IOContext;
        10: astore_2
        11: aload_0
        12: aload_0
        13: aload_1
        14: aload_2
        15: invokevirtual #115                // Method _decorate:(Ljava/io/Writer;Lcom/fasterxml/jackson/core/io/IOContext;)Ljava/io/Writer;
        18: aload_2
        19: invokevirtual #116                // Method _createGenerator:(Ljava/io/Writer;Lcom/fasterxml/jackson/core/io/IOContext;)Lcom/fasterxml/jackson/core/JsonGenerator;
        22: areturn
      LineNumberTable:
        line 1316: 0
        line 1317: 11
      LocalVariableTable:
        Start  Length  Slot  Name   Signature
            0      23     0  this   Lcom/fasterxml/jackson/core/JsonFactory;
            0      23     1     w   Ljava/io/Writer;
           11      12     2  ctxt   Lcom/fasterxml/jackson/core/io/IOContext;
    Exceptions:
      throws java.io.IOException

  public com.fasterxml.jackson.core.JsonGenerator createGenerator(java.io.File, com.fasterxml.jackson.core.JsonEncoding) throws java.io.IOException;
    descriptor: (Ljava/io/File;Lcom/fasterxml/jackson/core/JsonEncoding;)Lcom/fasterxml/jackson/core/JsonGenerator;
    flags: (0x0001) ACC_PUBLIC
    Code:
      stack=4, locals=6, args_size=3
         0: new           #118                // class java/io/FileOutputStream
         3: dup
         4: aload_1
         5: invokespecial #119                // Method java/io/FileOutputStream."<init>":(Ljava/io/File;)V
         8: astore_3
         9: aload_0
        10: aload_0
        11: aload_3
        12: invokevirtual #79                 // Method _createContentReference:(Ljava/lang/Object;)Lcom/fasterxml/jackson/core/io/ContentReference;
        15: iconst_1
        16: invokevirtual #80                 // Method _createContext:(Lcom/fasterxml/jackson/core/io/ContentReference;Z)Lcom/fasterxml/jackson/core/io/IOContext;
        19: astore        4
        21: aload         4
        23: aload_2
        24: invokevirtual #110                // Method com/fasterxml/jackson/core/io/IOContext.setEncoding:(Lcom/fasterxml/jackson/core/JsonEncoding;)V
        27: aload_2
        28: getstatic     #111                // Field com/fasterxml/jackson/core/JsonEncoding.UTF8:Lcom/fasterxml/jackson/core/JsonEncoding;
        31: if_acmpne     48
        34: aload_0
        35: aload_0
        36: aload_3
        37: aload         4
        39: invokevirtual #112                // Method _decorate:(Ljava/io/OutputStream;Lcom/fasterxml/jackson/core/io/IOContext;)Ljava/io/OutputStream;
        42: aload         4
        44: invokevirtual #113                // Method _createUTF8Generator:(Ljava/io/OutputStream;Lcom/fasterxml/jackson/core/io/IOContext;)Lcom/fasterxml/jackson/core/JsonGenerator;
        47: areturn
        48: aload_0
        49: aload_3
        50: aload_2
        51: aload         4
        53: invokevirtual #114                // Method _createWriter:(Ljava/io/OutputStream;Lcom/fasterxml/jackson/core/JsonEncoding;Lcom/fasterxml/jackson/core/io/IOContext;)Ljava/io/Writer;
        56: astore        5
        58: aload_0
        59: aload_0
        60: aload         5
        62: aload         4
        64: invokevirtual #115                // Method _decorate:(Ljava/io/Writer;Lcom/fasterxml/jackson/core/io/IOContext;)Ljava/io/Writer;
        67: aload         4
        69: invokevirtual #116                // Method _createGenerator:(Ljava/io/Writer;Lcom/fasterxml/jackson/core/io/IOContext;)Lcom/fasterxml/jackson/core/JsonGenerator;
        72: areturn
      LineNumberTable:
        line 1339: 0
        line 1341: 9
        line 1342: 21
        line 1343: 27
        line 1344: 34
        line 1346: 48
        line 1347: 58
      LocalVariableTable:
        Start  Length  Slot  Name   Signature
            0      73     0  this   Lcom/fasterxml/jackson/core/JsonFactory;
            0      73     1     f   Ljava/io/File;
            0      73     2   enc   Lcom/fasterxml/jackson/core/JsonEncoding;
            9      64     3   out   Ljava/io/OutputStream;
           21      52     4  ctxt   Lcom/fasterxml/jackson/core/io/IOContext;
           58      15     5     w   Ljava/io/Writer;
      StackMapTable: number_of_entries = 1
        frame_type = 253 /* append */
          offset_delta = 48
          locals = [ class java/io/OutputStream, class com/fasterxml/jackson/core/io/IOContext ]
    Exceptions:
      throws java.io.IOException

  public com.fasterxml.jackson.core.JsonGenerator createGenerator(java.io.DataOutput, com.fasterxml.jackson.core.JsonEncoding) throws java.io.IOException;
    descriptor: (Ljava/io/DataOutput;Lcom/fasterxml/jackson/core/JsonEncoding;)Lcom/fasterxml/jackson/core/JsonGenerator;
    flags: (0x0001) ACC_PUBLIC
    Code:
      stack=3, locals=3, args_size=3
         0: aload_0
         1: aload_0
         2: aload_1
         3: invokevirtual #120                // Method _createDataOutputWrapper:(Ljava/io/DataOutput;)Ljava/io/OutputStream;
         6: aload_2
         7: invokevirtual #117                // Method createGenerator:(Ljava/io/OutputStream;Lcom/fasterxml/jackson/core/JsonEncoding;)Lcom/fasterxml/jackson/core/JsonGenerator;
        10: areturn
      LineNumberTable:
        line 1358: 0
      LocalVariableTable:
        Start  Length  Slot  Name   Signature
            0      11     0  this   Lcom/fasterxml/jackson/core/JsonFactory;
            0      11     1   out   Ljava/io/DataOutput;
            0      11     2   enc   Lcom/fasterxml/jackson/core/JsonEncoding;
    Exceptions:
      throws java.io.IOException

  public com.fasterxml.jackson.core.JsonGenerator createGenerator(java.io.DataOutput) throws java.io.IOException;
    descriptor: (Ljava/io/DataOutput;)Lcom/fasterxml/jackson/core/JsonGenerator;
    flags: (0x0001) ACC_PUBLIC
    Code:
      stack=3, locals=2, args_size=2
         0: aload_0
         1: aload_0
         2: aload_1
         3: invokevirtual #120                // Method _createDataOutputWrapper:(Ljava/io/DataOutput;)Ljava/io/OutputStream;
         6: getstatic     #111                // Field com/fasterxml/jackson/core/JsonEncoding.UTF8:Lcom/fasterxml/jackson/core/JsonEncoding;
         9: invokevirtual #117                // Method createGenerator:(Ljava/io/OutputStream;Lcom/fasterxml/jackson/core/JsonEncoding;)Lcom/fasterxml/jackson/core/JsonGenerator;
        12: areturn
      LineNumberTable:
        line 1371: 0
      LocalVariableTable:
        Start  Length  Slot  Name   Signature
            0      13     0  this   Lcom/fasterxml/jackson/core/JsonFactory;
            0      13     1   out   Ljava/io/DataOutput;
    Exceptions:
      throws java.io.IOException

  public com.fasterxml.jackson.core.JsonParser createJsonParser(java.io.File) throws java.io.IOException, com.fasterxml.jackson.core.JsonParseException;
    descriptor: (Ljava/io/File;)Lcom/fasterxml/jackson/core/JsonParser;
    flags: (0x0001) ACC_PUBLIC
    Code:
      stack=2, locals=2, args_size=2
         0: aload_0
         1: aload_1
         2: invokevirtual #121                // Method createParser:(Ljava/io/File;)Lcom/fasterxml/jackson/core/JsonParser;
         5: areturn
      LineNumberTable:
        line 1406: 0
      LocalVariableTable:
        Start  Length  Slot  Name   Signature
            0       6     0  this   Lcom/fasterxml/jackson/core/JsonFactory;
            0       6     1     f   Ljava/io/File;
    Exceptions:
      throws java.io.IOException, com.fasterxml.jackson.core.JsonParseException
    Deprecated: true
    RuntimeVisibleAnnotations:
      0: #293()
        java.lang.Deprecated

  public com.fasterxml.jackson.core.JsonParser createJsonParser(java.net.URL) throws java.io.IOException, com.fasterxml.jackson.core.JsonParseException;
    descriptor: (Ljava/net/URL;)Lcom/fasterxml/jackson/core/JsonParser;
    flags: (0x0001) ACC_PUBLIC
    Code:
      stack=2, locals=2, args_size=2
         0: aload_0
         1: aload_1
         2: invokevirtual #122                // Method createParser:(Ljava/net/URL;)Lcom/fasterxml/jackson/core/JsonParser;
         5: areturn
      LineNumberTable:
        line 1434: 0
      LocalVariableTable:
        Start  Length  Slot  Name   Signature
            0       6     0  this   Lcom/fasterxml/jackson/core/JsonFactory;
            0       6     1   url   Ljava/net/URL;
    Exceptions:
      throws java.io.IOException, com.fasterxml.jackson.core.JsonParseException
    Deprecated: true
    RuntimeVisibleAnnotations:
      0: #293()
        java.lang.Deprecated

  public com.fasterxml.jackson.core.JsonParser createJsonParser(java.io.InputStream) throws java.io.IOException, com.fasterxml.jackson.core.JsonParseException;
    descriptor: (Ljava/io/InputStream;)Lcom/fasterxml/jackson/core/JsonParser;
    flags: (0x0001) ACC_PUBLIC
    Code:
      stack=2, locals=2, args_size=2
         0: aload_0
         1: aload_1
         2: invokevirtual #123                // Method createParser:(Ljava/io/InputStream;)Lcom/fasterxml/jackson/core/JsonParser;
         5: areturn
      LineNumberTable:
        line 1465: 0
      LocalVariableTable:
        Start  Length  Slot  Name   Signature
            0       6     0  this   Lcom/fasterxml/jackson/core/JsonFactory;
            0       6     1    in   Ljava/io/InputStream;
    Exceptions:
      throws java.io.IOException, com.fasterxml.jackson.core.JsonParseException
    Deprecated: true
    RuntimeVisibleAnnotations:
      0: #293()
        java.lang.Deprecated

  public com.fasterxml.jackson.core.JsonParser createJsonParser(java.io.Reader) throws java.io.IOException, com.fasterxml.jackson.core.JsonParseException;
    descriptor: (Ljava/io/Reader;)Lcom/fasterxml/jackson/core/JsonParser;
    flags: (0x0001) ACC_PUBLIC
    Code:
      stack=2, locals=2, args_size=2
         0: aload_0
         1: aload_1
         2: invokevirtual #96                 // Method createParser:(Ljava/io/Reader;)Lcom/fasterxml/jackson/core/JsonParser;
         5: areturn
      LineNumberTable:
        line 1489: 0
      LocalVariableTable:
        Start  Length  Slot  Name   Signature
            0       6     0  this   Lcom/fasterxml/jackson/core/JsonFactory;
            0       6     1     r   Ljava/io/Reader;
    Exceptions:
      throws java.io.IOException, com.fasterxml.jackson.core.JsonParseException
    Deprecated: true
    RuntimeVisibleAnnotations:
      0: #293()
        java.lang.Deprecated

  public com.fasterxml.jackson.core.JsonParser createJsonParser(byte[]) throws java.io.IOException, com.fasterxml.jackson.core.JsonParseException;
    descriptor: ([B)Lcom/fasterxml/jackson/core/JsonParser;
    flags: (0x0001) ACC_PUBLIC
    Code:
      stack=2, locals=2, args_size=2
         0: aload_0
         1: aload_1
         2: invokevirtual #124                // Method createParser:([B)Lcom/fasterxml/jackson/core/JsonParser;
         5: areturn
      LineNumberTable:
        line 1506: 0
      LocalVariableTable:
        Start  Length  Slot  Name   Signature
            0       6     0  this   Lcom/fasterxml/jackson/core/JsonFactory;
            0       6     1  data   [B
    Exceptions:
      throws java.io.IOException, com.fasterxml.jackson.core.JsonParseException
    Deprecated: true
    RuntimeVisibleAnnotations:
      0: #293()
        java.lang.Deprecated

  public com.fasterxml.jackson.core.JsonParser createJsonParser(byte[], int, int) throws java.io.IOException, com.fasterxml.jackson.core.JsonParseException;
    descriptor: ([BII)Lcom/fasterxml/jackson/core/JsonParser;
    flags: (0x0001) ACC_PUBLIC
    Code:
      stack=4, locals=4, args_size=4
         0: aload_0
         1: aload_1
         2: iload_2
         3: iload_3
         4: invokevirtual #125                // Method createParser:([BII)Lcom/fasterxml/jackson/core/JsonParser;
         7: areturn
      LineNumberTable:
        line 1526: 0
      LocalVariableTable:
        Start  Length  Slot  Name   Signature
            0       8     0  this   Lcom/fasterxml/jackson/core/JsonFactory;
            0       8     1  data   [B
            0       8     2 offset   I
            0       8     3   len   I
    Exceptions:
      throws java.io.IOException, com.fasterxml.jackson.core.JsonParseException
    Deprecated: true
    RuntimeVisibleAnnotations:
      0: #293()
        java.lang.Deprecated

  public com.fasterxml.jackson.core.JsonParser createJsonParser(java.lang.String) throws java.io.IOException, com.fasterxml.jackson.core.JsonParseException;
    descriptor: (Ljava/lang/String;)Lcom/fasterxml/jackson/core/JsonParser;
    flags: (0x0001) ACC_PUBLIC
    Code:
      stack=2, locals=2, args_size=2
         0: aload_0
         1: aload_1
         2: invokevirtual #126                // Method createParser:(Ljava/lang/String;)Lcom/fasterxml/jackson/core/JsonParser;
         5: areturn
      LineNumberTable:
        line 1544: 0
      LocalVariableTable:
        Start  Length  Slot  Name   Signature
            0       6     0  this   Lcom/fasterxml/jackson/core/JsonFactory;
            0       6     1 content   Ljava/lang/String;
    Exceptions:
      throws java.io.IOException, com.fasterxml.jackson.core.JsonParseException
    Deprecated: true
    RuntimeVisibleAnnotations:
      0: #293()
        java.lang.Deprecated

  public com.fasterxml.jackson.core.JsonGenerator createJsonGenerator(java.io.OutputStream, com.fasterxml.jackson.core.JsonEncoding) throws java.io.IOException;
    descriptor: (Ljava/io/OutputStream;Lcom/fasterxml/jackson/core/JsonEncoding;)Lcom/fasterxml/jackson/core/JsonGenerator;
    flags: (0x0001) ACC_PUBLIC
    Code:
      stack=3, locals=3, args_size=3
         0: aload_0
         1: aload_1
         2: aload_2
         3: invokevirtual #117                // Method createGenerator:(Ljava/io/OutputStream;Lcom/fasterxml/jackson/core/JsonEncoding;)Lcom/fasterxml/jackson/core/JsonGenerator;
         6: areturn
      LineNumberTable:
        line 1581: 0
      LocalVariableTable:
        Start  Length  Slot  Name   Signature
            0       7     0  this   Lcom/fasterxml/jackson/core/JsonFactory;
            0       7     1   out   Ljava/io/OutputStream;
            0       7     2   enc   Lcom/fasterxml/jackson/core/JsonEncoding;
    Exceptions:
      throws java.io.IOException
    Deprecated: true
    RuntimeVisibleAnnotations:
      0: #293()
        java.lang.Deprecated

  public com.fasterxml.jackson.core.JsonGenerator createJsonGenerator(java.io.Writer) throws java.io.IOException;
    descriptor: (Ljava/io/Writer;)Lcom/fasterxml/jackson/core/JsonGenerator;
    flags: (0x0001) ACC_PUBLIC
    Code:
      stack=2, locals=2, args_size=2
         0: aload_0
         1: aload_1
         2: invokevirtual #127                // Method createGenerator:(Ljava/io/Writer;)Lcom/fasterxml/jackson/core/JsonGenerator;
         5: areturn
      LineNumberTable:
        line 1605: 0
      LocalVariableTable:
        Start  Length  Slot  Name   Signature
            0       6     0  this   Lcom/fasterxml/jackson/core/JsonFactory;
            0       6     1   out   Ljava/io/Writer;
    Exceptions:
      throws java.io.IOException
    Deprecated: true
    RuntimeVisibleAnnotations:
      0: #293()
        java.lang.Deprecated

  public com.fasterxml.jackson.core.JsonGenerator createJsonGenerator(java.io.OutputStream) throws java.io.IOException;
    descriptor: (Ljava/io/OutputStream;)Lcom/fasterxml/jackson/core/JsonGenerator;
    flags: (0x0001) ACC_PUBLIC
    Code:
      stack=3, locals=2, args_size=2
         0: aload_0
         1: aload_1
         2: getstatic     #111                // Field com/fasterxml/jackson/core/JsonEncoding.UTF8:Lcom/fasterxml/jackson/core/JsonEncoding;
         5: invokevirtual #117                // Method createGenerator:(Ljava/io/OutputStream;Lcom/fasterxml/jackson/core/JsonEncoding;)Lcom/fasterxml/jackson/core/JsonGenerator;
         8: areturn
      LineNumberTable:
        line 1624: 0
      LocalVariableTable:
        Start  Length  Slot  Name   Signature
            0       9     0  this   Lcom/fasterxml/jackson/core/JsonFactory;
            0       9     1   out   Ljava/io/OutputStream;
    Exceptions:
      throws java.io.IOException
    Deprecated: true
    RuntimeVisibleAnnotations:
      0: #293()
        java.lang.Deprecated

  protected com.fasterxml.jackson.core.JsonParser _createParser(java.io.InputStream, com.fasterxml.jackson.core.io.IOContext) throws java.io.IOException;
    descriptor: (Ljava/io/InputStream;Lcom/fasterxml/jackson/core/io/IOContext;)Lcom/fasterxml/jackson/core/JsonParser;
    flags: (0x0004) ACC_PROTECTED
    Code:
      stack=6, locals=3, args_size=3
         0: new           #128                // class com/fasterxml/jackson/core/json/ByteSourceJsonBootstrapper
         3: dup
         4: aload_2
         5: aload_1
         6: invokespecial #129                // Method com/fasterxml/jackson/core/json/ByteSourceJsonBootstrapper."<init>":(Lcom/fasterxml/jackson/core/io/IOContext;Ljava/io/InputStream;)V
         9: aload_0
        10: getfield      #11                 // Field _parserFeatures:I
        13: aload_0
        14: getfield      #16                 // Field _objectCodec:Lcom/fasterxml/jackson/core/ObjectCodec;
        17: aload_0
        18: getfield      #7                  // Field _byteSymbolCanonicalizer:Lcom/fasterxml/jackson/core/sym/ByteQuadsCanonicalizer;
        21: aload_0
        22: getfield      #5                  // Field _rootCharSymbols:Lcom/fasterxml/jackson/core/sym/CharsToNameCanonicalizer;
        25: aload_0
        26: getfield      #9                  // Field _factoryFeatures:I
        29: invokevirtual #130                // Method com/fasterxml/jackson/core/json/ByteSourceJsonBootstrapper.constructParser:(ILcom/fasterxml/jackson/core/ObjectCodec;Lcom/fasterxml/jackson/core/sym/ByteQuadsCanonicalizer;Lcom/fasterxml/jackson/core/sym/CharsToNameCanonicalizer;I)Lcom/fasterxml/jackson/core/JsonParser;
        32: areturn
      LineNumberTable:
        line 1655: 0
      LocalVariableTable:
        Start  Length  Slot  Name   Signature
            0      33     0  this   Lcom/fasterxml/jackson/core/JsonFactory;
            0      33     1    in   Ljava/io/InputStream;
            0      33     2  ctxt   Lcom/fasterxml/jackson/core/io/IOContext;
    Exceptions:
      throws java.io.IOException

  protected com.fasterxml.jackson.core.JsonParser _createParser(java.io.Reader, com.fasterxml.jackson.core.io.IOContext) throws java.io.IOException;
    descriptor: (Ljava/io/Reader;Lcom/fasterxml/jackson/core/io/IOContext;)Lcom/fasterxml/jackson/core/JsonParser;
    flags: (0x0004) ACC_PROTECTED
    Code:
      stack=8, locals=3, args_size=3
         0: new           #131                // class com/fasterxml/jackson/core/json/ReaderBasedJsonParser
         3: dup
         4: aload_2
         5: aload_0
         6: getfield      #11                 // Field _parserFeatures:I
         9: aload_1
        10: aload_0
        11: getfield      #16                 // Field _objectCodec:Lcom/fasterxml/jackson/core/ObjectCodec;
        14: aload_0
        15: getfield      #5                  // Field _rootCharSymbols:Lcom/fasterxml/jackson/core/sym/CharsToNameCanonicalizer;
        18: aload_0
        19: getfield      #9                  // Field _factoryFeatures:I
        22: invokevirtual #132                // Method com/fasterxml/jackson/core/sym/CharsToNameCanonicalizer.makeChild:(I)Lcom/fasterxml/jackson/core/sym/CharsToNameCanonicalizer;
        25: invokespecial #133                // Method com/fasterxml/jackson/core/json/ReaderBasedJsonParser."<init>":(Lcom/fasterxml/jackson/core/io/IOContext;ILjava/io/Reader;Lcom/fasterxml/jackson/core/ObjectCodec;Lcom/fasterxml/jackson/core/sym/CharsToNameCanonicalizer;)V
        28: areturn
      LineNumberTable:
        line 1679: 0
        line 1680: 22
        line 1679: 28
      LocalVariableTable:
        Start  Length  Slot  Name   Signature
            0      29     0  this   Lcom/fasterxml/jackson/core/JsonFactory;
            0      29     1     r   Ljava/io/Reader;
            0      29     2  ctxt   Lcom/fasterxml/jackson/core/io/IOContext;
    Exceptions:
      throws java.io.IOException

  protected com.fasterxml.jackson.core.JsonParser _createParser(char[], int, int, com.fasterxml.jackson.core.io.IOContext, boolean) throws java.io.IOException;
    descriptor: ([CIILcom/fasterxml/jackson/core/io/IOContext;Z)Lcom/fasterxml/jackson/core/JsonParser;
    flags: (0x0004) ACC_PROTECTED
    Code:
      stack=11, locals=6, args_size=6
         0: new           #131                // class com/fasterxml/jackson/core/json/ReaderBasedJsonParser
         3: dup
         4: aload         4
         6: aload_0
         7: getfield      #11                 // Field _parserFeatures:I
        10: aconst_null
        11: aload_0
        12: getfield      #16                 // Field _objectCodec:Lcom/fasterxml/jackson/core/ObjectCodec;
        15: aload_0
        16: getfield      #5                  // Field _rootCharSymbols:Lcom/fasterxml/jackson/core/sym/CharsToNameCanonicalizer;
        19: aload_0
        20: getfield      #9                  // Field _factoryFeatures:I
        23: invokevirtual #132                // Method com/fasterxml/jackson/core/sym/CharsToNameCanonicalizer.makeChild:(I)Lcom/fasterxml/jackson/core/sym/CharsToNameCanonicalizer;
        26: aload_1
        27: iload_2
        28: iload_2
        29: iload_3
        30: iadd
        31: iload         5
        33: invokespecial #134                // Method com/fasterxml/jackson/core/json/ReaderBasedJsonParser."<init>":(Lcom/fasterxml/jackson/core/io/IOContext;ILjava/io/Reader;Lcom/fasterxml/jackson/core/ObjectCodec;Lcom/fasterxml/jackson/core/sym/CharsToNameCanonicalizer;[CIIZ)V
        36: areturn
      LineNumberTable:
        line 1701: 0
        line 1702: 23
        line 1701: 36
      LocalVariableTable:
        Start  Length  Slot  Name   Signature
            0      37     0  this   Lcom/fasterxml/jackson/core/JsonFactory;
            0      37     1  data   [C
            0      37     2 offset   I
            0      37     3   len   I
            0      37     4  ctxt   Lcom/fasterxml/jackson/core/io/IOContext;
            0      37     5 recyclable   Z
    Exceptions:
      throws java.io.IOException

  protected com.fasterxml.jackson.core.JsonParser _createParser(byte[], int, int, com.fasterxml.jackson.core.io.IOContext) throws java.io.IOException;
    descriptor: ([BIILcom/fasterxml/jackson/core/io/IOContext;)Lcom/fasterxml/jackson/core/JsonParser;
    flags: (0x0004) ACC_PROTECTED
    Code:
      stack=6, locals=5, args_size=5
         0: new           #128                // class com/fasterxml/jackson/core/json/ByteSourceJsonBootstrapper
         3: dup
         4: aload         4
         6: aload_1
         7: iload_2
         8: iload_3
         9: invokespecial #135                // Method com/fasterxml/jackson/core/json/ByteSourceJsonBootstrapper."<init>":(Lcom/fasterxml/jackson/core/io/IOContext;[BII)V
        12: aload_0
        13: getfield      #11                 // Field _parserFeatures:I
        16: aload_0
        17: getfield      #16                 // Field _objectCodec:Lcom/fasterxml/jackson/core/ObjectCodec;
        20: aload_0
        21: getfield      #7                  // Field _byteSymbolCanonicalizer:Lcom/fasterxml/jackson/core/sym/ByteQuadsCanonicalizer;
        24: aload_0
        25: getfield      #5                  // Field _rootCharSymbols:Lcom/fasterxml/jackson/core/sym/CharsToNameCanonicalizer;
        28: aload_0
        29: getfield      #9                  // Field _factoryFeatures:I
        32: invokevirtual #130                // Method com/fasterxml/jackson/core/json/ByteSourceJsonBootstrapper.constructParser:(ILcom/fasterxml/jackson/core/ObjectCodec;Lcom/fasterxml/jackson/core/sym/ByteQuadsCanonicalizer;Lcom/fasterxml/jackson/core/sym/CharsToNameCanonicalizer;I)Lcom/fasterxml/jackson/core/JsonParser;
        35: areturn
      LineNumberTable:
        line 1728: 0
      LocalVariableTable:
        Start  Length  Slot  Name   Signature
            0      36     0  this   Lcom/fasterxml/jackson/core/JsonFactory;
            0      36     1  data   [B
            0      36     2 offset   I
            0      36     3   len   I
            0      36     4  ctxt   Lcom/fasterxml/jackson/core/io/IOContext;
    Exceptions:
      throws java.io.IOException

  protected com.fasterxml.jackson.core.JsonParser _createParser(java.io.DataInput, com.fasterxml.jackson.core.io.IOContext) throws java.io.IOException;
    descriptor: (Ljava/io/DataInput;Lcom/fasterxml/jackson/core/io/IOContext;)Lcom/fasterxml/jackson/core/JsonParser;
    flags: (0x0004) ACC_PROTECTED
    Code:
      stack=8, locals=5, args_size=3
         0: aload_0
         1: ldc           #136                // String InputData source not (yet?) supported for this format (%s)
         3: invokespecial #38                 // Method _requireJSONFactory:(Ljava/lang/String;)V
         6: aload_1
         7: invokestatic  #137                // Method com/fasterxml/jackson/core/json/ByteSourceJsonBootstrapper.skipUTF8BOM:(Ljava/io/DataInput;)I
        10: istore_3
        11: aload_0
        12: getfield      #7                  // Field _byteSymbolCanonicalizer:Lcom/fasterxml/jackson/core/sym/ByteQuadsCanonicalizer;
        15: aload_0
        16: getfield      #9                  // Field _factoryFeatures:I
        19: invokevirtual #107                // Method com/fasterxml/jackson/core/sym/ByteQuadsCanonicalizer.makeChild:(I)Lcom/fasterxml/jackson/core/sym/ByteQuadsCanonicalizer;
        22: astore        4
        24: new           #138                // class com/fasterxml/jackson/core/json/UTF8DataInputJsonParser
        27: dup
        28: aload_2
        29: aload_0
        30: getfield      #11                 // Field _parserFeatures:I
        33: aload_1
        34: aload_0
        35: getfield      #16                 // Field _objectCodec:Lcom/fasterxml/jackson/core/ObjectCodec;
        38: aload         4
        40: iload_3
        41: invokespecial #139                // Method com/fasterxml/jackson/core/json/UTF8DataInputJsonParser."<init>":(Lcom/fasterxml/jackson/core/io/IOContext;ILjava/io/DataInput;Lcom/fasterxml/jackson/core/ObjectCodec;Lcom/fasterxml/jackson/core/sym/ByteQuadsCanonicalizer;I)V
        44: areturn
      LineNumberTable:
        line 1748: 0
        line 1751: 6
        line 1752: 11
        line 1753: 24
      LocalVariableTable:
        Start  Length  Slot  Name   Signature
            0      45     0  this   Lcom/fasterxml/jackson/core/JsonFactory;
            0      45     1 input   Ljava/io/DataInput;
            0      45     2  ctxt   Lcom/fasterxml/jackson/core/io/IOContext;
           11      34     3 firstByte   I
           24      21     4   can   Lcom/fasterxml/jackson/core/sym/ByteQuadsCanonicalizer;
    Exceptions:
      throws java.io.IOException

  protected com.fasterxml.jackson.core.JsonGenerator _createGenerator(java.io.Writer, com.fasterxml.jackson.core.io.IOContext) throws java.io.IOException;
    descriptor: (Ljava/io/Writer;Lcom/fasterxml/jackson/core/io/IOContext;)Lcom/fasterxml/jackson/core/JsonGenerator;
    flags: (0x0004) ACC_PROTECTED
    Code:
      stack=7, locals=5, args_size=3
         0: new           #140                // class com/fasterxml/jackson/core/json/WriterBasedJsonGenerator
         3: dup
         4: aload_2
         5: aload_0
         6: getfield      #13                 // Field _generatorFeatures:I
         9: aload_0
        10: getfield      #16                 // Field _objectCodec:Lcom/fasterxml/jackson/core/ObjectCodec;
        13: aload_1
        14: aload_0
        15: getfield      #18                 // Field _quoteChar:C
        18: invokespecial #141                // Method com/fasterxml/jackson/core/json/WriterBasedJsonGenerator."<init>":(Lcom/fasterxml/jackson/core/io/IOContext;ILcom/fasterxml/jackson/core/ObjectCodec;Ljava/io/Writer;C)V
        21: astore_3
        22: aload_0
        23: getfield      #22                 // Field _maximumNonEscapedChar:I
        26: ifle          38
        29: aload_3
        30: aload_0
        31: getfield      #22                 // Field _maximumNonEscapedChar:I
        34: invokevirtual #142                // Method com/fasterxml/jackson/core/json/WriterBasedJsonGenerator.setHighestNonEscapedChar:(I)Lcom/fasterxml/jackson/core/JsonGenerator;
        37: pop
        38: aload_0
        39: getfield      #21                 // Field _characterEscapes:Lcom/fasterxml/jackson/core/io/CharacterEscapes;
        42: ifnull        54
        45: aload_3
        46: aload_0
        47: getfield      #21                 // Field _characterEscapes:Lcom/fasterxml/jackson/core/io/CharacterEscapes;
        50: invokevirtual #143                // Method com/fasterxml/jackson/core/json/WriterBasedJsonGenerator.setCharacterEscapes:(Lcom/fasterxml/jackson/core/io/CharacterEscapes;)Lcom/fasterxml/jackson/core/JsonGenerator;
        53: pop
        54: aload_0
        55: getfield      #15                 // Field _rootValueSeparator:Lcom/fasterxml/jackson/core/SerializableString;
        58: astore        4
        60: aload         4
        62: getstatic     #14                 // Field DEFAULT_ROOT_VALUE_SEPARATOR:Lcom/fasterxml/jackson/core/SerializableString;
        65: if_acmpeq     75
        68: aload_3
        69: aload         4
        71: invokevirtual #144                // Method com/fasterxml/jackson/core/json/WriterBasedJsonGenerator.setRootValueSeparator:(Lcom/fasterxml/jackson/core/SerializableString;)Lcom/fasterxml/jackson/core/JsonGenerator;
        74: pop
        75: aload_3
        76: areturn
      LineNumberTable:
        line 1783: 0
        line 1785: 22
        line 1786: 29
        line 1788: 38
        line 1789: 45
        line 1791: 54
        line 1792: 60
        line 1793: 68
        line 1795: 75
      LocalVariableTable:
        Start  Length  Slot  Name   Signature
            0      77     0  this   Lcom/fasterxml/jackson/core/JsonFactory;
            0      77     1   out   Ljava/io/Writer;
            0      77     2  ctxt   Lcom/fasterxml/jackson/core/io/IOContext;
           22      55     3   gen   Lcom/fasterxml/jackson/core/json/WriterBasedJsonGenerator;
           60      17     4 rootSep   Lcom/fasterxml/jackson/core/SerializableString;
      StackMapTable: number_of_entries = 3
        frame_type = 252 /* append */
          offset_delta = 38
          locals = [ class com/fasterxml/jackson/core/json/WriterBasedJsonGenerator ]
        frame_type = 15 /* same */
        frame_type = 252 /* append */
          offset_delta = 20
          locals = [ class com/fasterxml/jackson/core/SerializableString ]
    Exceptions:
      throws java.io.IOException

  protected com.fasterxml.jackson.core.JsonGenerator _createUTF8Generator(java.io.OutputStream, com.fasterxml.jackson.core.io.IOContext) throws java.io.IOException;
    descriptor: (Ljava/io/OutputStream;Lcom/fasterxml/jackson/core/io/IOContext;)Lcom/fasterxml/jackson/core/JsonGenerator;
    flags: (0x0004) ACC_PROTECTED
    Code:
      stack=7, locals=5, args_size=3
         0: new           #145                // class com/fasterxml/jackson/core/json/UTF8JsonGenerator
         3: dup
         4: aload_2
         5: aload_0
         6: getfield      #13                 // Field _generatorFeatures:I
         9: aload_0
        10: getfield      #16                 // Field _objectCodec:Lcom/fasterxml/jackson/core/ObjectCodec;
        13: aload_1
        14: aload_0
        15: getfield      #18                 // Field _quoteChar:C
        18: invokespecial #146                // Method com/fasterxml/jackson/core/json/UTF8JsonGenerator."<init>":(Lcom/fasterxml/jackson/core/io/IOContext;ILcom/fasterxml/jackson/core/ObjectCodec;Ljava/io/OutputStream;C)V
        21: astore_3
        22: aload_0
        23: getfield      #22                 // Field _maximumNonEscapedChar:I
        26: ifle          38
        29: aload_3
        30: aload_0
        31: getfield      #22                 // Field _maximumNonEscapedChar:I
        34: invokevirtual #147                // Method com/fasterxml/jackson/core/json/UTF8JsonGenerator.setHighestNonEscapedChar:(I)Lcom/fasterxml/jackson/core/JsonGenerator;
        37: pop
        38: aload_0
        39: getfield      #21                 // Field _characterEscapes:Lcom/fasterxml/jackson/core/io/CharacterEscapes;
        42: ifnull        54
        45: aload_3
        46: aload_0
        47: getfield      #21                 // Field _characterEscapes:Lcom/fasterxml/jackson/core/io/CharacterEscapes;
        50: invokevirtual #148                // Method com/fasterxml/jackson/core/json/UTF8JsonGenerator.setCharacterEscapes:(Lcom/fasterxml/jackson/core/io/CharacterEscapes;)Lcom/fasterxml/jackson/core/JsonGenerator;
        53: pop
        54: aload_0
        55: getfield      #15                 // Field _rootValueSeparator:Lcom/fasterxml/jackson/core/SerializableString;
        58: astore        4
        60: aload         4
        62: getstatic     #14                 // Field DEFAULT_ROOT_VALUE_SEPARATOR:Lcom/fasterxml/jackson/core/SerializableString;
        65: if_acmpeq     75
        68: aload_3
        69: aload         4
        71: invokevirtual #149                // Method com/fasterxml/jackson/core/json/UTF8JsonGenerator.setRootValueSeparator:(Lcom/fasterxml/jackson/core/SerializableString;)Lcom/fasterxml/jackson/core/JsonGenerator;
        74: pop
        75: aload_3
        76: areturn
      LineNumberTable:
        line 1816: 0
        line 1818: 22
        line 1819: 29
        line 1821: 38
        line 1822: 45
        line 1824: 54
        line 1825: 60
        line 1826: 68
        line 1828: 75
      LocalVariableTable:
        Start  Length  Slot  Name   Signature
            0      77     0  this   Lcom/fasterxml/jackson/core/JsonFactory;
            0      77     1   out   Ljava/io/OutputStream;
            0      77     2  ctxt   Lcom/fasterxml/jackson/core/io/IOContext;
           22      55     3   gen   Lcom/fasterxml/jackson/core/json/UTF8JsonGenerator;
           60      17     4 rootSep   Lcom/fasterxml/jackson/core/SerializableString;
      StackMapTable: number_of_entries = 3
        frame_type = 252 /* append */
          offset_delta = 38
          locals = [ class com/fasterxml/jackson/core/json/UTF8JsonGenerator ]
        frame_type = 15 /* same */
        frame_type = 252 /* append */
          offset_delta = 20
          locals = [ class com/fasterxml/jackson/core/SerializableString ]
    Exceptions:
      throws java.io.IOException

  protected java.io.Writer _createWriter(java.io.OutputStream, com.fasterxml.jackson.core.JsonEncoding, com.fasterxml.jackson.core.io.IOContext) throws java.io.IOException;
    descriptor: (Ljava/io/OutputStream;Lcom/fasterxml/jackson/core/JsonEncoding;Lcom/fasterxml/jackson/core/io/IOContext;)Ljava/io/Writer;
    flags: (0x0004) ACC_PROTECTED
    Code:
      stack=4, locals=4, args_size=4
         0: aload_2
         1: getstatic     #111                // Field com/fasterxml/jackson/core/JsonEncoding.UTF8:Lcom/fasterxml/jackson/core/JsonEncoding;
         4: if_acmpne     17
         7: new           #150                // class com/fasterxml/jackson/core/io/UTF8Writer
        10: dup
        11: aload_3
        12: aload_1
        13: invokespecial #151                // Method com/fasterxml/jackson/core/io/UTF8Writer."<init>":(Lcom/fasterxml/jackson/core/io/IOContext;Ljava/io/OutputStream;)V
        16: areturn
        17: new           #152                // class java/io/OutputStreamWriter
        20: dup
        21: aload_1
        22: aload_2
        23: invokevirtual #153                // Method com/fasterxml/jackson/core/JsonEncoding.getJavaName:()Ljava/lang/String;
        26: invokespecial #154                // Method java/io/OutputStreamWriter."<init>":(Ljava/io/OutputStream;Ljava/lang/String;)V
        29: areturn
      LineNumberTable:
        line 1834: 0
        line 1835: 7
        line 1838: 17
      LocalVariableTable:
        Start  Length  Slot  Name   Signature
            0      30     0  this   Lcom/fasterxml/jackson/core/JsonFactory;
            0      30     1   out   Ljava/io/OutputStream;
            0      30     2   enc   Lcom/fasterxml/jackson/core/JsonEncoding;
            0      30     3  ctxt   Lcom/fasterxml/jackson/core/io/IOContext;
      StackMapTable: number_of_entries = 1
        frame_type = 17 /* same */
    Exceptions:
      throws java.io.IOException

  protected final java.io.InputStream _decorate(java.io.InputStream, com.fasterxml.jackson.core.io.IOContext) throws java.io.IOException;
    descriptor: (Ljava/io/InputStream;Lcom/fasterxml/jackson/core/io/IOContext;)Ljava/io/InputStream;
    flags: (0x0014) ACC_PROTECTED, ACC_FINAL
    Code:
      stack=3, locals=4, args_size=3
         0: aload_0
         1: getfield      #19                 // Field _inputDecorator:Lcom/fasterxml/jackson/core/io/InputDecorator;
         4: ifnull        23
         7: aload_0
         8: getfield      #19                 // Field _inputDecorator:Lcom/fasterxml/jackson/core/io/InputDecorator;
        11: aload_2
        12: aload_1
        13: invokevirtual #155                // Method com/fasterxml/jackson/core/io/InputDecorator.decorate:(Lcom/fasterxml/jackson/core/io/IOContext;Ljava/io/InputStream;)Ljava/io/InputStream;
        16: astore_3
        17: aload_3
        18: ifnull        23
        21: aload_3
        22: areturn
        23: aload_1
        24: areturn
      LineNumberTable:
        line 1848: 0
        line 1849: 7
        line 1850: 17
        line 1851: 21
        line 1854: 23
      LocalVariableTable:
        Start  Length  Slot  Name   Signature
           17       6     3   in2   Ljava/io/InputStream;
            0      25     0  this   Lcom/fasterxml/jackson/core/JsonFactory;
            0      25     1    in   Ljava/io/InputStream;
            0      25     2  ctxt   Lcom/fasterxml/jackson/core/io/IOContext;
      StackMapTable: number_of_entries = 1
        frame_type = 23 /* same */
    Exceptions:
      throws java.io.IOException

  protected final java.io.Reader _decorate(java.io.Reader, com.fasterxml.jackson.core.io.IOContext) throws java.io.IOException;
    descriptor: (Ljava/io/Reader;Lcom/fasterxml/jackson/core/io/IOContext;)Ljava/io/Reader;
    flags: (0x0014) ACC_PROTECTED, ACC_FINAL
    Code:
      stack=3, locals=4, args_size=3
         0: aload_0
         1: getfield      #19                 // Field _inputDecorator:Lcom/fasterxml/jackson/core/io/InputDecorator;
         4: ifnull        23
         7: aload_0
         8: getfield      #19                 // Field _inputDecorator:Lcom/fasterxml/jackson/core/io/InputDecorator;
        11: aload_2
        12: aload_1
        13: invokevirtual #156                // Method com/fasterxml/jackson/core/io/InputDecorator.decorate:(Lcom/fasterxml/jackson/core/io/IOContext;Ljava/io/Reader;)Ljava/io/Reader;
        16: astore_3
        17: aload_3
        18: ifnull        23
        21: aload_3
        22: areturn
        23: aload_1
        24: areturn
      LineNumberTable:
        line 1858: 0
        line 1859: 7
        line 1860: 17
        line 1861: 21
        line 1864: 23
      LocalVariableTable:
        Start  Length  Slot  Name   Signature
           17       6     3   in2   Ljava/io/Reader;
            0      25     0  this   Lcom/fasterxml/jackson/core/JsonFactory;
            0      25     1    in   Ljava/io/Reader;
            0      25     2  ctxt   Lcom/fasterxml/jackson/core/io/IOContext;
      StackMapTable: number_of_entries = 1
        frame_type = 23 /* same */
    Exceptions:
      throws java.io.IOException

  protected final java.io.DataInput _decorate(java.io.DataInput, com.fasterxml.jackson.core.io.IOContext) throws java.io.IOException;
    descriptor: (Ljava/io/DataInput;Lcom/fasterxml/jackson/core/io/IOContext;)Ljava/io/DataInput;
    flags: (0x0014) ACC_PROTECTED, ACC_FINAL
    Code:
      stack=3, locals=4, args_size=3
         0: aload_0
         1: getfield      #19                 // Field _inputDecorator:Lcom/fasterxml/jackson/core/io/InputDecorator;
         4: ifnull        23
         7: aload_0
         8: getfield      #19                 // Field _inputDecorator:Lcom/fasterxml/jackson/core/io/InputDecorator;
        11: aload_2
        12: aload_1
        13: invokevirtual #157                // Method com/fasterxml/jackson/core/io/InputDecorator.decorate:(Lcom/fasterxml/jackson/core/io/IOContext;Ljava/io/DataInput;)Ljava/io/DataInput;
        16: astore_3
        17: aload_3
        18: ifnull        23
        21: aload_3
        22: areturn
        23: aload_1
        24: areturn
      LineNumberTable:
        line 1869: 0
        line 1870: 7
        line 1871: 17
        line 1872: 21
        line 1875: 23
      LocalVariableTable:
        Start  Length  Slot  Name   Signature
           17       6     3   in2   Ljava/io/DataInput;
            0      25     0  this   Lcom/fasterxml/jackson/core/JsonFactory;
            0      25     1    in   Ljava/io/DataInput;
            0      25     2  ctxt   Lcom/fasterxml/jackson/core/io/IOContext;
      StackMapTable: number_of_entries = 1
        frame_type = 23 /* same */
    Exceptions:
      throws java.io.IOException

  protected final java.io.OutputStream _decorate(java.io.OutputStream, com.fasterxml.jackson.core.io.IOContext) throws java.io.IOException;
    descriptor: (Ljava/io/OutputStream;Lcom/fasterxml/jackson/core/io/IOContext;)Ljava/io/OutputStream;
    flags: (0x0014) ACC_PROTECTED, ACC_FINAL
    Code:
      stack=3, locals=4, args_size=3
         0: aload_0
         1: getfield      #20                 // Field _outputDecorator:Lcom/fasterxml/jackson/core/io/OutputDecorator;
         4: ifnull        23
         7: aload_0
         8: getfield      #20                 // Field _outputDecorator:Lcom/fasterxml/jackson/core/io/OutputDecorator;
        11: aload_2
        12: aload_1
        13: invokevirtual #158                // Method com/fasterxml/jackson/core/io/OutputDecorator.decorate:(Lcom/fasterxml/jackson/core/io/IOContext;Ljava/io/OutputStream;)Ljava/io/OutputStream;
        16: astore_3
        17: aload_3
        18: ifnull        23
        21: aload_3
        22: areturn
        23: aload_1
        24: areturn
      LineNumberTable:
        line 1879: 0
        line 1880: 7
        line 1881: 17
        line 1882: 21
        line 1885: 23
      LocalVariableTable:
        Start  Length  Slot  Name   Signature
           17       6     3  out2   Ljava/io/OutputStream;
            0      25     0  this   Lcom/fasterxml/jackson/core/JsonFactory;
            0      25     1   out   Ljava/io/OutputStream;
            0      25     2  ctxt   Lcom/fasterxml/jackson/core/io/IOContext;
      StackMapTable: number_of_entries = 1
        frame_type = 23 /* same */
    Exceptions:
      throws java.io.IOException

  protected final java.io.Writer _decorate(java.io.Writer, com.fasterxml.jackson.core.io.IOContext) throws java.io.IOException;
    descriptor: (Ljava/io/Writer;Lcom/fasterxml/jackson/core/io/IOContext;)Ljava/io/Writer;
    flags: (0x0014) ACC_PROTECTED, ACC_FINAL
    Code:
      stack=3, locals=4, args_size=3
         0: aload_0
         1: getfield      #20                 // Field _outputDecorator:Lcom/fasterxml/jackson/core/io/OutputDecorator;
         4: ifnull        23
         7: aload_0
         8: getfield      #20                 // Field _outputDecorator:Lcom/fasterxml/jackson/core/io/OutputDecorator;
        11: aload_2
        12: aload_1
        13: invokevirtual #159                // Method com/fasterxml/jackson/core/io/OutputDecorator.decorate:(Lcom/fasterxml/jackson/core/io/IOContext;Ljava/io/Writer;)Ljava/io/Writer;
        16: astore_3
        17: aload_3
        18: ifnull        23
        21: aload_3
        22: areturn
        23: aload_1
        24: areturn
      LineNumberTable:
        line 1889: 0
        line 1890: 7
        line 1891: 17
        line 1892: 21
        line 1895: 23
      LocalVariableTable:
        Start  Length  Slot  Name   Signature
           17       6     3  out2   Ljava/io/Writer;
            0      25     0  this   Lcom/fasterxml/jackson/core/JsonFactory;
            0      25     1   out   Ljava/io/Writer;
            0      25     2  ctxt   Lcom/fasterxml/jackson/core/io/IOContext;
      StackMapTable: number_of_entries = 1
        frame_type = 23 /* same */
    Exceptions:
      throws java.io.IOException

  public com.fasterxml.jackson.core.util.BufferRecycler _getBufferRecycler();
    descriptor: ()Lcom/fasterxml/jackson/core/util/BufferRecycler;
    flags: (0x0001) ACC_PUBLIC
    Code:
      stack=2, locals=1, args_size=1
         0: getstatic     #160                // Field com/fasterxml/jackson/core/JsonFactory$Feature.USE_THREAD_LOCAL_FOR_BUFFER_RECYCLING:Lcom/fasterxml/jackson/core/JsonFactory$Feature;
         3: aload_0
         4: getfield      #9                  // Field _factoryFeatures:I
         7: invokevirtual #161                // Method com/fasterxml/jackson/core/JsonFactory$Feature.enabledIn:(I)Z
        10: ifeq          17
        13: invokestatic  #162                // Method com/fasterxml/jackson/core/util/BufferRecyclers.getBufferRecycler:()Lcom/fasterxml/jackson/core/util/BufferRecycler;
        16: areturn
        17: new           #163                // class com/fasterxml/jackson/core/util/BufferRecycler
        20: dup
        21: invokespecial #164                // Method com/fasterxml/jackson/core/util/BufferRecycler."<init>":()V
        24: areturn
      LineNumberTable:
        line 1917: 0
        line 1918: 13
        line 1920: 17
      LocalVariableTable:
        Start  Length  Slot  Name   Signature
            0      25     0  this   Lcom/fasterxml/jackson/core/JsonFactory;
      StackMapTable: number_of_entries = 1
        frame_type = 17 /* same */

  protected com.fasterxml.jackson.core.io.IOContext _createContext(com.fasterxml.jackson.core.io.ContentReference, boolean);
    descriptor: (Lcom/fasterxml/jackson/core/io/ContentReference;Z)Lcom/fasterxml/jackson/core/io/IOContext;
    flags: (0x0004) ACC_PROTECTED
    Code:
      stack=5, locals=3, args_size=3
         0: aload_1
         1: ifnonnull     8
         4: invokestatic  #165                // Method com/fasterxml/jackson/core/io/ContentReference.unknown:()Lcom/fasterxml/jackson/core/io/ContentReference;
         7: astore_1
         8: new           #166                // class com/fasterxml/jackson/core/io/IOContext
        11: dup
        12: aload_0
        13: invokevirtual #167                // Method _getBufferRecycler:()Lcom/fasterxml/jackson/core/util/BufferRecycler;
        16: aload_1
        17: iload_2
        18: invokespecial #168                // Method com/fasterxml/jackson/core/io/IOContext."<init>":(Lcom/fasterxml/jackson/core/util/BufferRecycler;Lcom/fasterxml/jackson/core/io/ContentReference;Z)V
        21: areturn
      LineNumberTable:
        line 1934: 0
        line 1935: 4
        line 1937: 8
      LocalVariableTable:
        Start  Length  Slot  Name   Signature
            0      22     0  this   Lcom/fasterxml/jackson/core/JsonFactory;
            0      22     1 contentRef   Lcom/fasterxml/jackson/core/io/ContentReference;
            0      22     2 resourceManaged   Z
      StackMapTable: number_of_entries = 1
        frame_type = 8 /* same */

  protected com.fasterxml.jackson.core.io.IOContext _createContext(java.lang.Object, boolean);
    descriptor: (Ljava/lang/Object;Z)Lcom/fasterxml/jackson/core/io/IOContext;
    flags: (0x0004) ACC_PROTECTED
    Code:
      stack=5, locals=3, args_size=3
         0: new           #166                // class com/fasterxml/jackson/core/io/IOContext
         3: dup
         4: aload_0
         5: invokevirtual #167                // Method _getBufferRecycler:()Lcom/fasterxml/jackson/core/util/BufferRecycler;
         8: aload_0
         9: aload_1
        10: invokevirtual #79                 // Method _createContentReference:(Ljava/lang/Object;)Lcom/fasterxml/jackson/core/io/ContentReference;
        13: iload_2
        14: invokespecial #168                // Method com/fasterxml/jackson/core/io/IOContext."<init>":(Lcom/fasterxml/jackson/core/util/BufferRecycler;Lcom/fasterxml/jackson/core/io/ContentReference;Z)V
        17: areturn
      LineNumberTable:
        line 1952: 0
        line 1953: 10
        line 1952: 17
      LocalVariableTable:
        Start  Length  Slot  Name   Signature
            0      18     0  this   Lcom/fasterxml/jackson/core/JsonFactory;
            0      18     1 rawContentRef   Ljava/lang/Object;
            0      18     2 resourceManaged   Z
    Deprecated: true
    RuntimeVisibleAnnotations:
      0: #293()
        java.lang.Deprecated

  protected com.fasterxml.jackson.core.io.IOContext _createNonBlockingContext(java.lang.Object);
    descriptor: (Ljava/lang/Object;)Lcom/fasterxml/jackson/core/io/IOContext;
    flags: (0x0004) ACC_PROTECTED
    Code:
      stack=5, locals=2, args_size=2
         0: new           #166                // class com/fasterxml/jackson/core/io/IOContext
         3: dup
         4: aload_0
         5: invokevirtual #167                // Method _getBufferRecycler:()Lcom/fasterxml/jackson/core/util/BufferRecycler;
         8: aload_0
         9: aload_1
        10: invokevirtual #79                 // Method _createContentReference:(Ljava/lang/Object;)Lcom/fasterxml/jackson/core/io/ContentReference;
        13: iconst_0
        14: invokespecial #168                // Method com/fasterxml/jackson/core/io/IOContext."<init>":(Lcom/fasterxml/jackson/core/util/BufferRecycler;Lcom/fasterxml/jackson/core/io/ContentReference;Z)V
        17: areturn
      LineNumberTable:
        line 1970: 0
        line 1971: 10
        line 1970: 17
      LocalVariableTable:
        Start  Length  Slot  Name   Signature
            0      18     0  this   Lcom/fasterxml/jackson/core/JsonFactory;
            0      18     1 srcRef   Ljava/lang/Object;

  protected com.fasterxml.jackson.core.io.ContentReference _createContentReference(java.lang.Object);
    descriptor: (Ljava/lang/Object;)Lcom/fasterxml/jackson/core/io/ContentReference;
    flags: (0x0004) ACC_PROTECTED
    Code:
      stack=2, locals=2, args_size=2
         0: aload_0
         1: invokevirtual #169                // Method canHandleBinaryNatively:()Z
         4: ifne          11
         7: iconst_1
         8: goto          12
        11: iconst_0
        12: aload_1
        13: invokestatic  #170                // Method com/fasterxml/jackson/core/io/ContentReference.construct:(ZLjava/lang/Object;)Lcom/fasterxml/jackson/core/io/ContentReference;
        16: areturn
      LineNumberTable:
        line 1990: 0
      LocalVariableTable:
        Start  Length  Slot  Name   Signature
            0      17     0  this   Lcom/fasterxml/jackson/core/JsonFactory;
            0      17     1 contentAccessor   Ljava/lang/Object;
      StackMapTable: number_of_entries = 2
        frame_type = 11 /* same */
        frame_type = 64 /* same_locals_1_stack_item */
          stack = [ int ]

  protected com.fasterxml.jackson.core.io.ContentReference _createContentReference(java.lang.Object, int, int);
    descriptor: (Ljava/lang/Object;II)Lcom/fasterxml/jackson/core/io/ContentReference;
    flags: (0x0004) ACC_PROTECTED
    Code:
      stack=4, locals=4, args_size=4
         0: aload_0
         1: invokevirtual #169                // Method canHandleBinaryNatively:()Z
         4: ifne          11
         7: iconst_1
         8: goto          12
        11: iconst_0
        12: aload_1
        13: iload_2
        14: iload_3
        15: invokestatic  #171                // Method com/fasterxml/jackson/core/io/ContentReference.construct:(ZLjava/lang/Object;II)Lcom/fasterxml/jackson/core/io/ContentReference;
        18: areturn
      LineNumberTable:
        line 2013: 0
      LocalVariableTable:
        Start  Length  Slot  Name   Signature
            0      19     0  this   Lcom/fasterxml/jackson/core/JsonFactory;
            0      19     1 contentAccessor   Ljava/lang/Object;
            0      19     2 offset   I
            0      19     3 length   I
      StackMapTable: number_of_entries = 2
        frame_type = 11 /* same */
        frame_type = 64 /* same_locals_1_stack_item */
          stack = [ int ]

  private final void _requireJSONFactory(java.lang.String);
    descriptor: (Ljava/lang/String;)V
    flags: (0x0012) ACC_PRIVATE, ACC_FINAL
    Code:
      stack=7, locals=2, args_size=2
         0: aload_0
         1: invokespecial #57                 // Method _isJSONFactory:()Z
         4: ifne          30
         7: new           #172                // class java/lang/UnsupportedOperationException
        10: dup
        11: aload_1
        12: iconst_1
        13: anewarray     #173                // class java/lang/Object
        16: dup
        17: iconst_0
        18: aload_0
        19: invokevirtual #58                 // Method getFormatName:()Ljava/lang/String;
        22: aastore
        23: invokestatic  #174                // Method java/lang/String.format:(Ljava/lang/String;[Ljava/lang/Object;)Ljava/lang/String;
        26: invokespecial #175                // Method java/lang/UnsupportedOperationException."<init>":(Ljava/lang/String;)V
        29: athrow
        30: return
      LineNumberTable:
        line 2038: 0
        line 2039: 7
        line 2041: 30
      LocalVariableTable:
        Start  Length  Slot  Name   Signature
            0      31     0  this   Lcom/fasterxml/jackson/core/JsonFactory;
            0      31     1   msg   Ljava/lang/String;
      StackMapTable: number_of_entries = 1
        frame_type = 30 /* same */

  private final boolean _isJSONFactory();
    descriptor: ()Z
    flags: (0x0012) ACC_PRIVATE, ACC_FINAL
    Code:
      stack=2, locals=1, args_size=1
         0: aload_0
         1: invokevirtual #58                 // Method getFormatName:()Ljava/lang/String;
         4: ldc           #61                 // String JSON
         6: if_acmpne     13
         9: iconst_1
        10: goto          14
        13: iconst_0
        14: ireturn
      LineNumberTable:
        line 2046: 0
      LocalVariableTable:
        Start  Length  Slot  Name   Signature
            0      15     0  this   Lcom/fasterxml/jackson/core/JsonFactory;
      StackMapTable: number_of_entries = 2
        frame_type = 13 /* same */
        frame_type = 64 /* same_locals_1_stack_item */
          stack = [ int ]

  static {};
    descriptor: ()V
    flags: (0x0008) ACC_STATIC
    Code:
      stack=1, locals=0, args_size=0
         0: invokestatic  #176                // Method com/fasterxml/jackson/core/JsonFactory$Feature.collectDefaults:()I
         3: putstatic     #8                  // Field DEFAULT_FACTORY_FEATURE_FLAGS:I
         6: invokestatic  #177                // Method com/fasterxml/jackson/core/JsonParser$Feature.collectDefaults:()I
         9: putstatic     #10                 // Field DEFAULT_PARSER_FEATURE_FLAGS:I
        12: invokestatic  #178                // Method com/fasterxml/jackson/core/JsonGenerator$Feature.collectDefaults:()I
        15: putstatic     #12                 // Field DEFAULT_GENERATOR_FEATURE_FLAGS:I
        18: getstatic     #179                // Field com/fasterxml/jackson/core/util/DefaultPrettyPrinter.DEFAULT_ROOT_VALUE_SEPARATOR:Lcom/fasterxml/jackson/core/io/SerializedString;
        21: putstatic     #14                 // Field DEFAULT_ROOT_VALUE_SEPARATOR:Lcom/fasterxml/jackson/core/SerializableString;
        24: return
      LineNumberTable:
        line 172: 0
        line 178: 6
        line 184: 12
        line 186: 18
}
SourceFile: "JsonFactory.java"
InnerClasses:
  public static final #184= #183 of #17;  // Feature=class com/fasterxml/jackson/core/JsonFactory$Feature of class com/fasterxml/jackson/core/JsonFactory
  public static final #184= #304 of #620; // Feature=class com/fasterxml/jackson/core/JsonParser$Feature of class com/fasterxml/jackson/core/JsonParser
  public static final #184= #316 of #622; // Feature=class com/fasterxml/jackson/core/JsonGenerator$Feature of class com/fasterxml/jackson/core/JsonGenerator
