Classfile /Users/mw/Projects/slang-braindump/.jar/jar8/assemble/slang-braindump/assemble/content/org/sireum/$internal/RC.class
  Last modified May 29, 2022; size 22387 bytes
  SHA-256 checksum 22d9dae52f6b168d96b2c396d9263c9775ad3f9aa54f816c9d97e6a6389aca09
  Compiled from "RC.scala"
public class org.sireum.$internal.RC
  minor version: 0
  major version: 52
  flags: (0x0021) ACC_PUBLIC, ACC_SUPER
  this_class: #2                          // org/sireum/$internal/RC
  super_class: #4                         // java/lang/Object
  interfaces: 0, fields: 1, methods: 23, attributes: 6
Constant pool:
    #1 = Utf8               org/sireum/$internal/RC
    #2 = Class              #1            // org/sireum/$internal/RC
    #3 = Utf8               java/lang/Object
    #4 = Class              #3            // java/lang/Object
    #5 = Utf8               RC.scala
    #6 = Utf8               Lscala/reflect/ScalaSignature;
    #7 = Utf8               bytes
    #8 = Utf8               \u0006\u0005\u0005mx!\u0002\t\u0012\u0011\u0003Ab!\u0002\u000e\u0012\u0011\u0003Y\u0002\"\u0002\u0012\u0002\t\u0003\u0019\u0003\"\u0002\u0013\u0002\t\u0003)\u0003BB%\u0002\u0005\u0013\u0005!\n\u0003\u0005\u0002X\u0005\u0011I\u0011AA-\r\u0015Q\u0012\u0003AAP\u0011)\t\tK\u0002BC\u0002\u0013\u0005\u00111\u0015\u0005\u000b\u0003c3!\u0011!Q\u0001\n\u0005\u0015\u0006B\u0002\u0012\u0007\t\u0003\t\u0019\fC\u0004\u0002:\u001a!\t!a/\t\u000f\u0005=b\u0001\"\u0001\u0002X\"9\u0011\u0011\u0012\u0004\u0005\u0002\u0005}\u0007bBAt\r\u0011\u0005\u0011\u0011\u001e\u0005\b\u0003_4A\u0011AAy\u0011\u001d\t)P\u0002C\u0001\u0003o\f!AU\"\u000b\u0005I\u0019\u0012!\u0003\u0013j]R,\'O\\1m\u0015\t!R#\u0001\u0004tSJ,W/\u001c\u0006\u0002-\u0005\u0019qN]4\u0004\u0001A\u0011\u0011$A\u0007\u0002#\t\u0011!kQ\n\u0003\u0003q\u0001\"!\b\u0011\u000e\u0003yQ\u0011aH\u0001\u0006g\u000e\fG.Y\u0005\u0003Cy\u0011a!\u00118z%\u00164\u0017A\u0002\u001fj]&$h\bF\u0001\u0019\u0003\u0019!x\u000e\u0016:jKR\u0011a\u0005\u000f\t\u0005O)jSF\u0004\u0002\u001aQ%\u0011\u0011&E\u0001\u0005)JLW-\u0003\u0002,Y\t!aj\u001c3f\u0015\tI\u0013\u0003\u0005\u0002/k9\u0011qf\r\t\u0003ayi\u0011!\r\u0006\u0003e]\ta\u0001\u0010:p_Rt\u0014B\u0001\u001b\u001f\u0003\u0019\u0001&/\u001a3fM&\u0011ag\u000e\u0002\u0007\'R\u0014\u0018N\\4\u000b\u0005Qr\u0002\"B\u001d\u0004\u0001\u0004Q\u0014!A7\u0011\tmr\u0004)L\u0007\u0002y)\u0011QHH\u0001\u000bG>dG.Z2uS>t\u0017BA =\u0005\ri\u0015\r\u001d\t\u0004\u0003\u001akcB\u0001\"E\u001d\t\u00014)C\u0001 \u0013\t)e$A\u0004qC\u000e\\\u0017mZ3\n\u0005\u001dC%A\u0002,fGR|\'O\u0003\u0002F=\u0005!A/\u001a=u)\tYe\f\u0006\u0002M\u001dB!a&\u0014!.\u0013\tyt\u0007C\u0003P\t\u0001\u0007\u0001+A\u0001q!\u0015i\u0012\u000bQ*\\\u0013\t\u0011fDA\u0005Gk:\u001cG/[8oeA\u0011A+W\u0007\u0002+*\u0011akV\u0001\u0003S>T\u0011\u0001W\u0001\u0005U\u00064\u0018-\u0003\u0002[+\n!a)\u001b7f!\tiB,\u0003\u0002^=\t9!i\\8mK\u0006t\u0007\"B0\u0005\u0001\u0004\u0001\u0015\u0001\u0003:fYB\u000bG\u000f[:)\u0007\u0011\t7\u000e\u0005\u0002cS6\t1M\u0003\u0002eK\u0006A\u0011N\u001c;fe:\fGN\u0003\u0002gO\u00061Q.Y2s_NT!\u0001\u001b\u0010\u0002\u000fI,g\r\\3di&\u0011!n\u0019\u0002\n[\u0006\u001c\'o\\%na2\fTb\b7n_b\f\t!!\u0004\u0002 \u0005E2\u0002A\u0019\u0005I1<b.A\u0003nC\u000e\u0014x.\r\u0003\u0017YB$\u0018gA\u0013re>\t!/I\u0001t\u0003-i\u0017m\u0019:p\u000b:<\u0017N\\32\u0007\u0015*hoD\u0001wC\u00059\u0018!\n<8]A\u0002\u0003&[7qY\u0016lWM\u001c;fI\u0002Jg\u000eI*dC2\f\u0007E\r\u00182c9\u0002T&\u0014\u001d*c\u00111B._?2\u0007\u0015R8pD\u0001|C\u0005a\u0018\u0001C5t\u0005VtG\r\\32\u0007\u0015rxpD\u0001\u00003\u0005\t\u0011G\u0002\fm\u0003\u0007\tY!M\u0003&\u0003\u000b\t9a\u0004\u0002\u0002\b\u0005\u0012\u0011\u0011B\u0001\u000bSN\u0014E.Y2lE>D\u0018gA\u0013\u007f\u007fF2a\u0003\\A\b\u0003/\tT!JA\t\u0003\'y!!a\u0005\"\u0005\u0005U\u0011!C2mCN\u001ch*Y7fc\u0015)\u0013\u0011DA\u000e\u001f\t\tY\"\t\u0002\u0002\u001e\u00059rN]4/g&\u0014X-^7/I%tG/\u001a:oC2t#kQ\u0019\u0007-1\f\t#!\u000b2\u000b\u0015\n\u0019#!\n\u0010\u0005\u0005\u0015\u0012EAA\u0014\u0003)iW\r\u001e5pI:\u000bW.Z\u0019\u0006K\u0005-\u0012QF\b\u0003\u0003[\t#!a\f\u0002\u0011Q,\u0007\u0010^%na2\fdA\u00067\u00024\u0005m\u0012\'B\u0013\u00026\u0005]rBAA\u001cC\t\tI$A\u0005tS\u001et\u0017\r^;sKFBq\u0004\\A\u001f\u0003\u000f\n\t&\r\u0004%Y\u0006}\u0012\u0011I\u0005\u0005\u0003\u0003\n\u0019%\u0001\u0003MSN$(bAA#y\u0005I\u0011.\\7vi\u0006\u0014G.Z\u0019\u0007?1\fI%a\u00132\r\u0011b\u0017qHA!c\u0015)\u0013QJA(\u001f\t\ty%H\u0001\u007fd\u0019yB.a\u0015\u0002VE2A\u0005\\A \u0003\u0003\nT!JA\'\u0003\u001f\naAY1tKZ\"D\u0003BA.\u0003?\"2\u0001TA/\u0011\u0015yU\u00011\u0001Q\u0011\u0015yV\u00011\u0001AQ\u0011)\u0011-a\u00192!}a\u0017QMA4\u0003[\n\u0019(!\u001f\u0002\u0000\u0005-\u0015\u0007\u0002\u0013m/9\fdA\u00067\u0002j\u0005-\u0014gA\u0013reF\u001aQ%\u001e<2\rYa\u0017qNA9c\r)#p_\u0019\u0004Ky|\u0018G\u0002\fm\u0003k\n9(M\u0003&\u0003\u000b\t9!M\u0002&}~\fdA\u00067\u0002|\u0005u\u0014\'B\u0013\u0002\u0012\u0005M\u0011\'B\u0013\u0002\u001a\u0005m\u0011G\u0002\fm\u0003\u0003\u000b\u0019)M\u0003&\u0003G\t)#M\u0003&\u0003\u000b\u000b9i\u0004\u0002\u0002\b\u0006\u0012\u0011\u0011R\u0001\u000bE\u0006\u001cXM\u000e\u001bJ[Bd\u0017G\u0002\fm\u0003\u001b\u000by)M\u0003&\u0003k\t9$\r\u0005 Y\u0006E\u00151SAMc\u0019!C.a\u0010\u0002BE2q\u0004\\AK\u0003/\u000bd\u0001\n7\u0002@\u0005\u0005\u0013\'B\u0013\u0002N\u0005=\u0013GB\u0010m\u00037\u000bi*\r\u0004%Y\u0006}\u0012\u0011I\u0019\u0006K\u00055\u0013qJ\n\u0003\rq\t\u0011aY\u000b\u0003\u0003K\u0003B!a*\u0002.6\u0011\u0011\u0011\u0016\u0006\u0004\u0003W+\u0017\u0001\u00032mC\u000e\\\'m\u001c=\n\t\u0005=\u0016\u0011\u0016\u0002\b\u0007>tG/\u001a=u\u0003\t\u0019\u0007\u0005\u0006\u0003\u00026\u0006]\u0006CA\r\u0007\u0011\u001d\t\t+\u0003a\u0001\u0003K\u000b!bY8n[>t\u0017*\u001c9m)!\ti,a3\u0002P\u0006M\u0007#BA`\u0003\u0007debAAa\u000f5\ta!\u0003\u0003\u0002F\u0006\u001d\'\u0001B#yaJL1!!3f\u0005\u001d\tE.[1tKNDa!!4\u000b\u0001\u0004Y\u0016AB5t)\u0016DH\u000f\u0003\u0004`\u0015\u0001\u0007\u0011\u0011\u001b\t\u0006\u0003\u007f\u000b\u0019\r\u0011\u0005\u0007\u001f*\u0001\r!!6\u0011\u000b\u0005}\u00161\u0019)\u0015\t\u0005e\u0017Q\u001c\u000b\u0005\u0003{\u000bY\u000e\u0003\u0004P\u0017\u0001\u0007\u0011Q\u001b\u0005\u0007?.\u0001\r!!5\u0015\t\u0005\u0005\u0018Q\u001d\u000b\u0005\u0003{\u000b\u0019\u000f\u0003\u0004P\u0019\u0001\u0007\u0011Q\u001b\u0005\u0007?2\u0001\r!!5\u0002\u000bU\u0014\u0018n\u00144\u0015\u00075\nY\u000f\u0003\u0004\u0002n6\u0001\raU\u0001\u0002M\u0006A!/Z1e)\u0016DH\u000fF\u0002.\u0003gDa!!<\u000f\u0001\u0004\u0019\u0016A\u0003:fC\u0012\u0014\u0015m]37iQ\u0019Q&!?\t\r\u00055x\u00021\u0001T\u0001
    #9 = Utf8               java/lang/invoke/MethodHandles$Lookup
   #10 = Class              #9            // java/lang/invoke/MethodHandles$Lookup
   #11 = Utf8               java/lang/invoke/MethodHandles
   #12 = Class              #11           // java/lang/invoke/MethodHandles
   #13 = Utf8               Lookup
   #14 = Utf8               java/util/Base64$Encoder
   #15 = Class              #14           // java/util/Base64$Encoder
   #16 = Utf8               java/util/Base64
   #17 = Class              #16           // java/util/Base64
   #18 = Utf8               Encoder
   #19 = Utf8               org/sireum/$internal/Trie$Node
   #20 = Class              #19           // org/sireum/$internal/Trie$Node
   #21 = Utf8               org/sireum/$internal/Trie
   #22 = Class              #21           // org/sireum/$internal/Trie
   #23 = Utf8               Node
   #24 = Utf8               scala/collection/mutable/ArraySeq$ofRef
   #25 = Class              #24           // scala/collection/mutable/ArraySeq$ofRef
   #26 = Utf8               scala/collection/mutable/ArraySeq
   #27 = Class              #26           // scala/collection/mutable/ArraySeq
   #28 = Utf8               ofRef
   #29 = Utf8               scala/reflect/api/Constants$ConstantApi
   #30 = Class              #29           // scala/reflect/api/Constants$ConstantApi
   #31 = Utf8               scala/reflect/api/Constants
   #32 = Class              #31           // scala/reflect/api/Constants
   #33 = Utf8               ConstantApi
   #34 = Utf8               scala/reflect/api/Constants$ConstantExtractor
   #35 = Class              #34           // scala/reflect/api/Constants$ConstantExtractor
   #36 = Utf8               ConstantExtractor
   #37 = Utf8               scala/reflect/api/Exprs$Expr
   #38 = Class              #37           // scala/reflect/api/Exprs$Expr
   #39 = Utf8               scala/reflect/api/Exprs
   #40 = Class              #39           // scala/reflect/api/Exprs
   #41 = Utf8               Expr
   #42 = Utf8               scala/reflect/api/Internals$InternalApi
   #43 = Class              #42           // scala/reflect/api/Internals$InternalApi
   #44 = Utf8               scala/reflect/api/Internals
   #45 = Class              #44           // scala/reflect/api/Internals
   #46 = Utf8               InternalApi
   #47 = Utf8               scala/reflect/api/Internals$ReificationSupportApi
   #48 = Class              #47           // scala/reflect/api/Internals$ReificationSupportApi
   #49 = Utf8               ReificationSupportApi
   #50 = Utf8               scala/reflect/api/Internals$ReificationSupportApi$SyntacticAppliedExtractor
   #51 = Class              #50           // scala/reflect/api/Internals$ReificationSupportApi$SyntacticAppliedExtractor
   #52 = Utf8               SyntacticAppliedExtractor
   #53 = Utf8               scala/reflect/api/Internals$ReificationSupportApi$SyntacticBlockExtractor
   #54 = Class              #53           // scala/reflect/api/Internals$ReificationSupportApi$SyntacticBlockExtractor
   #55 = Utf8               SyntacticBlockExtractor
   #56 = Utf8               scala/reflect/api/Internals$ReificationSupportApi$SyntacticDefDefExtractor
   #57 = Class              #56           // scala/reflect/api/Internals$ReificationSupportApi$SyntacticDefDefExtractor
   #58 = Utf8               SyntacticDefDefExtractor
   #59 = Utf8               scala/reflect/api/Internals$ReificationSupportApi$SyntacticSelectTermExtractor
   #60 = Class              #59           // scala/reflect/api/Internals$ReificationSupportApi$SyntacticSelectTermExtractor
   #61 = Utf8               SyntacticSelectTermExtractor
   #62 = Utf8               scala/reflect/api/Internals$ReificationSupportApi$SyntacticSelectTypeExtractor
   #63 = Class              #62           // scala/reflect/api/Internals$ReificationSupportApi$SyntacticSelectTypeExtractor
   #64 = Utf8               SyntacticSelectTypeExtractor
   #65 = Utf8               scala/reflect/api/Internals$ReificationSupportApi$SyntacticTermIdentExtractor
   #66 = Class              #65           // scala/reflect/api/Internals$ReificationSupportApi$SyntacticTermIdentExtractor
   #67 = Utf8               SyntacticTermIdentExtractor
   #68 = Utf8               scala/reflect/api/Internals$ReificationSupportApi$SyntacticTupleExtractor
   #69 = Class              #68           // scala/reflect/api/Internals$ReificationSupportApi$SyntacticTupleExtractor
   #70 = Utf8               SyntacticTupleExtractor
   #71 = Utf8               scala/reflect/api/Internals$ReificationSupportApi$SyntacticTypeAppliedExtractor
   #72 = Class              #71           // scala/reflect/api/Internals$ReificationSupportApi$SyntacticTypeAppliedExtractor
   #73 = Utf8               SyntacticTypeAppliedExtractor
   #74 = Utf8               scala/reflect/api/Internals$ReificationSupportApi$SyntacticTypeIdentExtractor
   #75 = Class              #74           // scala/reflect/api/Internals$ReificationSupportApi$SyntacticTypeIdentExtractor
   #76 = Utf8               SyntacticTypeIdentExtractor
   #77 = Utf8               scala/reflect/api/Names$NameApi
   #78 = Class              #77           // scala/reflect/api/Names$NameApi
   #79 = Utf8               scala/reflect/api/Names
   #80 = Class              #79           // scala/reflect/api/Names
   #81 = Utf8               NameApi
   #82 = Utf8               scala/reflect/api/Names$TermNameApi
   #83 = Class              #82           // scala/reflect/api/Names$TermNameApi
   #84 = Utf8               TermNameApi
   #85 = Utf8               scala/reflect/api/Names$TermNameExtractor
   #86 = Class              #85           // scala/reflect/api/Names$TermNameExtractor
   #87 = Utf8               TermNameExtractor
   #88 = Utf8               scala/reflect/api/Names$TypeNameApi
   #89 = Class              #88           // scala/reflect/api/Names$TypeNameApi
   #90 = Utf8               TypeNameApi
   #91 = Utf8               scala/reflect/api/Names$TypeNameExtractor
   #92 = Class              #91           // scala/reflect/api/Names$TypeNameExtractor
   #93 = Utf8               TypeNameExtractor
   #94 = Utf8               scala/reflect/api/Trees$DefDefApi
   #95 = Class              #94           // scala/reflect/api/Trees$DefDefApi
   #96 = Utf8               scala/reflect/api/Trees
   #97 = Class              #96           // scala/reflect/api/Trees
   #98 = Utf8               DefDefApi
   #99 = Utf8               scala/reflect/api/Trees$IdentApi
  #100 = Class              #99           // scala/reflect/api/Trees$IdentApi
  #101 = Utf8               IdentApi
  #102 = Utf8               scala/reflect/api/Trees$IdentExtractor
  #103 = Class              #102          // scala/reflect/api/Trees$IdentExtractor
  #104 = Utf8               IdentExtractor
  #105 = Utf8               scala/reflect/api/Trees$LiteralApi
  #106 = Class              #105          // scala/reflect/api/Trees$LiteralApi
  #107 = Utf8               LiteralApi
  #108 = Utf8               scala/reflect/api/Trees$LiteralExtractor
  #109 = Class              #108          // scala/reflect/api/Trees$LiteralExtractor
  #110 = Utf8               LiteralExtractor
  #111 = Utf8               scala/reflect/api/Trees$ModifiersApi
  #112 = Class              #111          // scala/reflect/api/Trees$ModifiersApi
  #113 = Utf8               ModifiersApi
  #114 = Utf8               scala/reflect/api/Trees$SelectApi
  #115 = Class              #114          // scala/reflect/api/Trees$SelectApi
  #116 = Utf8               SelectApi
  #117 = Utf8               scala/reflect/api/Trees$TreeApi
  #118 = Class              #117          // scala/reflect/api/Trees$TreeApi
  #119 = Utf8               TreeApi
  #120 = Utf8               scala/reflect/api/TypeTags$WeakTypeTag
  #121 = Class              #120          // scala/reflect/api/TypeTags$WeakTypeTag
  #122 = Utf8               scala/reflect/api/TypeTags
  #123 = Class              #122          // scala/reflect/api/TypeTags
  #124 = Utf8               WeakTypeTag
  #125 = Utf8               scala/reflect/api/TypeTags$WeakTypeTag$
  #126 = Class              #125          // scala/reflect/api/TypeTags$WeakTypeTag$
  #127 = Utf8               WeakTypeTag$
  #128 = Utf8               c
  #129 = Utf8               Lscala/reflect/macros/blackbox/Context;
  #130 = Utf8               toTrie
  #131 = Utf8               (Lscala/collection/Map;)Lorg/sireum/$internal/Trie$Node;
  #132 = Utf8               (Lscala/collection/Map<Lscala/collection/immutable/Vector<Ljava/lang/String;>;Ljava/lang/String;>;)Lorg/sireum/$internal/Trie$Node<Ljava/lang/String;Ljava/lang/String;>;
  #133 = Utf8               m
  #134 = Utf8               org/sireum/$internal/RC$
  #135 = Class              #134          // org/sireum/$internal/RC$
  #136 = Utf8               MODULE$
  #137 = Utf8               Lorg/sireum/$internal/RC$;
  #138 = NameAndType        #136:#137     // MODULE$:Lorg/sireum/$internal/RC$;
  #139 = Fieldref           #135.#138     // org/sireum/$internal/RC$.MODULE$:Lorg/sireum/$internal/RC$;
  #140 = NameAndType        #130:#131     // toTrie:(Lscala/collection/Map;)Lorg/sireum/$internal/Trie$Node;
  #141 = Methodref          #135.#140     // org/sireum/$internal/RC$.toTrie:(Lscala/collection/Map;)Lorg/sireum/$internal/Trie$Node;
  #142 = Utf8               Lscala/collection/Map;
  #143 = Utf8               ()Lscala/reflect/macros/blackbox/Context;
  #144 = NameAndType        #128:#129     // c:Lscala/reflect/macros/blackbox/Context;
  #145 = Fieldref           #2.#144       // org/sireum/$internal/RC.c:Lscala/reflect/macros/blackbox/Context;
  #146 = Utf8               this
  #147 = Utf8               Lorg/sireum/$internal/RC;
  #148 = Utf8               commonImpl
  #149 = Utf8               (ZLscala/reflect/api/Exprs$Expr;Lscala/reflect/api/Exprs$Expr;)Lscala/reflect/api/Exprs$Expr;
  #150 = Utf8               (ZLscala/reflect/api/Exprs$Expr<Lscala/collection/immutable/Vector<Ljava/lang/String;>;>;Lscala/reflect/api/Exprs$Expr<Lscala/Function2<Lscala/collection/immutable/Vector<Ljava/lang/String;>;Ljava/io/File;Ljava/lang/Object;>;>;)Lscala/reflect/api/Exprs$Expr<Lscala/collection/immutable/Map<Lscala/collection/immutable/Vector<Ljava/lang/String;>;Ljava/lang/String;>;>;
  #151 = Utf8               isText
  #152 = Utf8               relPaths
  #153 = Utf8               p
  #154 = NameAndType        #128:#143     // c:()Lscala/reflect/macros/blackbox/Context;
  #155 = Methodref          #2.#154       // org/sireum/$internal/RC.c:()Lscala/reflect/macros/blackbox/Context;
  #156 = Utf8               tree
  #157 = Utf8               ()Lscala/reflect/api/Trees$TreeApi;
  #158 = NameAndType        #156:#157     // tree:()Lscala/reflect/api/Trees$TreeApi;
  #159 = InterfaceMethodref #38.#158      // scala/reflect/api/Exprs$Expr.tree:()Lscala/reflect/api/Trees$TreeApi;
  #160 = Utf8               org/sireum/$internal/Macro$
  #161 = Class              #160          // org/sireum/$internal/Macro$
  #162 = Utf8               Lorg/sireum/$internal/Macro$;
  #163 = NameAndType        #136:#162     // MODULE$:Lorg/sireum/$internal/Macro$;
  #164 = Fieldref           #161.#163     // org/sireum/$internal/Macro$.MODULE$:Lorg/sireum/$internal/Macro$;
  #165 = Utf8               eval$default$3
  #166 = Utf8               (Lscala/reflect/macros/blackbox/Context;)I
  #167 = NameAndType        #165:#166     // eval$default$3:(Lscala/reflect/macros/blackbox/Context;)I
  #168 = Methodref          #161.#167     // org/sireum/$internal/Macro$.eval$default$3:(Lscala/reflect/macros/blackbox/Context;)I
  #169 = Utf8               eval
  #170 = Utf8               (Lscala/reflect/macros/blackbox/Context;Ljava/lang/Object;I)Ljava/lang/Object;
  #171 = NameAndType        #169:#170     // eval:(Lscala/reflect/macros/blackbox/Context;Ljava/lang/Object;I)Ljava/lang/Object;
  #172 = Methodref          #161.#171     // org/sireum/$internal/Macro$.eval:(Lscala/reflect/macros/blackbox/Context;Ljava/lang/Object;I)Ljava/lang/Object;
  #173 = Utf8               scala/Function2
  #174 = Class              #173          // scala/Function2
  #175 = Utf8               scala/collection/immutable/Vector
  #176 = Class              #175          // scala/collection/immutable/Vector
  #177 = Utf8               scala/package$
  #178 = Class              #177          // scala/package$
  #179 = Utf8               Lscala/package$;
  #180 = NameAndType        #136:#179     // MODULE$:Lscala/package$;
  #181 = Fieldref           #178.#180     // scala/package$.MODULE$:Lscala/package$;
  #182 = Utf8               Vector
  #183 = Utf8               ()Lscala/collection/immutable/Vector$;
  #184 = NameAndType        #182:#183     // Vector:()Lscala/collection/immutable/Vector$;
  #185 = Methodref          #178.#184     // scala/package$.Vector:()Lscala/collection/immutable/Vector$;
  #186 = Utf8               scala/collection/immutable/Nil$
  #187 = Class              #186          // scala/collection/immutable/Nil$
  #188 = Utf8               Lscala/collection/immutable/Nil$;
  #189 = NameAndType        #136:#188     // MODULE$:Lscala/collection/immutable/Nil$;
  #190 = Fieldref           #187.#189     // scala/collection/immutable/Nil$.MODULE$:Lscala/collection/immutable/Nil$;
  #191 = Utf8               scala/collection/immutable/Vector$
  #192 = Class              #191          // scala/collection/immutable/Vector$
  #193 = Utf8               apply
  #194 = Utf8               (Lscala/collection/immutable/Seq;)Ljava/lang/Object;
  #195 = NameAndType        #193:#194     // apply:(Lscala/collection/immutable/Seq;)Ljava/lang/Object;
  #196 = Methodref          #192.#195     // scala/collection/immutable/Vector$.apply:(Lscala/collection/immutable/Seq;)Ljava/lang/Object;
  #197 = Utf8               scala/runtime/ObjectRef
  #198 = Class              #197          // scala/runtime/ObjectRef
  #199 = Utf8               create
  #200 = Utf8               (Ljava/lang/Object;)Lscala/runtime/ObjectRef;
  #201 = NameAndType        #199:#200     // create:(Ljava/lang/Object;)Lscala/runtime/ObjectRef;
  #202 = Methodref          #198.#201     // scala/runtime/ObjectRef.create:(Ljava/lang/Object;)Lscala/runtime/ObjectRef;
  #203 = Utf8               nonEmpty
  #204 = Utf8               ()Z
  #205 = NameAndType        #203:#204     // nonEmpty:()Z
  #206 = Methodref          #176.#205     // scala/collection/immutable/Vector.nonEmpty:()Z
  #207 = Utf8               (Ljava/lang/Object;)Ljava/lang/Object;
  #208 = MethodType         #207          //  (Ljava/lang/Object;)Ljava/lang/Object;
  #209 = Utf8               $anonfun$commonImpl$8$adapted
  #210 = Utf8               (Lorg/sireum/$internal/RC;Lscala/reflect/api/Exprs$Expr;Lscala/Function2;ZLscala/runtime/ObjectRef;Ljava/lang/String;)Ljava/lang/Object;
  #211 = NameAndType        #209:#210     // $anonfun$commonImpl$8$adapted:(Lorg/sireum/$internal/RC;Lscala/reflect/api/Exprs$Expr;Lscala/Function2;ZLscala/runtime/ObjectRef;Ljava/lang/String;)Ljava/lang/Object;
  #212 = Methodref          #2.#211       // org/sireum/$internal/RC.$anonfun$commonImpl$8$adapted:(Lorg/sireum/$internal/RC;Lscala/reflect/api/Exprs$Expr;Lscala/Function2;ZLscala/runtime/ObjectRef;Ljava/lang/String;)Ljava/lang/Object;
  #213 = MethodHandle       6:#212        // REF_invokeStatic org/sireum/$internal/RC.$anonfun$commonImpl$8$adapted:(Lorg/sireum/$internal/RC;Lscala/reflect/api/Exprs$Expr;Lscala/Function2;ZLscala/runtime/ObjectRef;Ljava/lang/String;)Ljava/lang/Object;
  #214 = Utf8               (Ljava/lang/String;)Ljava/lang/Object;
  #215 = MethodType         #214          //  (Ljava/lang/String;)Ljava/lang/Object;
  #216 = Integer            5
  #217 = Integer            1
  #218 = Utf8               java/lang/invoke/LambdaMetafactory
  #219 = Class              #218          // java/lang/invoke/LambdaMetafactory
  #220 = Utf8               altMetafactory
  #221 = Utf8               (Ljava/lang/invoke/MethodHandles$Lookup;Ljava/lang/String;Ljava/lang/invoke/MethodType;[Ljava/lang/Object;)Ljava/lang/invoke/CallSite;
  #222 = NameAndType        #220:#221     // altMetafactory:(Ljava/lang/invoke/MethodHandles$Lookup;Ljava/lang/String;Ljava/lang/invoke/MethodType;[Ljava/lang/Object;)Ljava/lang/invoke/CallSite;
  #223 = Methodref          #219.#222     // java/lang/invoke/LambdaMetafactory.altMetafactory:(Ljava/lang/invoke/MethodHandles$Lookup;Ljava/lang/String;Ljava/lang/invoke/MethodType;[Ljava/lang/Object;)Ljava/lang/invoke/CallSite;
  #224 = MethodHandle       6:#223        // REF_invokeStatic java/lang/invoke/LambdaMetafactory.altMetafactory:(Ljava/lang/invoke/MethodHandles$Lookup;Ljava/lang/String;Ljava/lang/invoke/MethodType;[Ljava/lang/Object;)Ljava/lang/invoke/CallSite;
  #225 = Utf8               (Lorg/sireum/$internal/RC;Lscala/reflect/api/Exprs$Expr;Lscala/Function2;ZLscala/runtime/ObjectRef;)Lscala/Function1;
  #226 = NameAndType        #193:#225     // apply:(Lorg/sireum/$internal/RC;Lscala/reflect/api/Exprs$Expr;Lscala/Function2;ZLscala/runtime/ObjectRef;)Lscala/Function1;
  #227 = InvokeDynamic      #0:#226       // #0:apply:(Lorg/sireum/$internal/RC;Lscala/reflect/api/Exprs$Expr;Lscala/Function2;ZLscala/runtime/ObjectRef;)Lscala/Function1;
  #228 = Utf8               foreach
  #229 = Utf8               (Lscala/Function1;)V
  #230 = NameAndType        #228:#229     // foreach:(Lscala/Function1;)V
  #231 = Methodref          #176.#230     // scala/collection/immutable/Vector.foreach:(Lscala/Function1;)V
  #232 = Utf8               .
  #233 = String             #232          // .
  #234 = Utf8               it$1
  #235 = Utf8               (Ljava/lang/String;Lscala/reflect/api/Exprs$Expr;Lscala/Function2;ZLscala/runtime/ObjectRef;)V
  #236 = NameAndType        #234:#235     // it$1:(Ljava/lang/String;Lscala/reflect/api/Exprs$Expr;Lscala/Function2;ZLscala/runtime/ObjectRef;)V
  #237 = Methodref          #2.#236       // org/sireum/$internal/RC.it$1:(Ljava/lang/String;Lscala/reflect/api/Exprs$Expr;Lscala/Function2;ZLscala/runtime/ObjectRef;)V
  #238 = Utf8               scala/reflect/macros/blackbox/Context
  #239 = Class              #238          // scala/reflect/macros/blackbox/Context
  #240 = Utf8               universe
  #241 = Utf8               ()Lscala/reflect/macros/Universe;
  #242 = NameAndType        #240:#241     // universe:()Lscala/reflect/macros/Universe;
  #243 = InterfaceMethodref #239.#242     // scala/reflect/macros/blackbox/Context.universe:()Lscala/reflect/macros/Universe;
  #244 = Utf8               scala/reflect/macros/Universe
  #245 = Class              #244          // scala/reflect/macros/Universe
  #246 = Utf8               internal
  #247 = Utf8               ()Lscala/reflect/api/Internals$InternalApi;
  #248 = NameAndType        #246:#247     // internal:()Lscala/reflect/api/Internals$InternalApi;
  #249 = Methodref          #245.#248     // scala/reflect/macros/Universe.internal:()Lscala/reflect/api/Internals$InternalApi;
  #250 = Utf8               reificationSupport
  #251 = Utf8               ()Lscala/reflect/api/Internals$ReificationSupportApi;
  #252 = NameAndType        #250:#251     // reificationSupport:()Lscala/reflect/api/Internals$ReificationSupportApi;
  #253 = InterfaceMethodref #43.#252      // scala/reflect/api/Internals$InternalApi.reificationSupport:()Lscala/reflect/api/Internals$ReificationSupportApi;
  #254 = Utf8               SyntacticApplied
  #255 = Utf8               ()Lscala/reflect/api/Internals$ReificationSupportApi$SyntacticAppliedExtractor;
  #256 = NameAndType        #254:#255     // SyntacticApplied:()Lscala/reflect/api/Internals$ReificationSupportApi$SyntacticAppliedExtractor;
  #257 = InterfaceMethodref #48.#256      // scala/reflect/api/Internals$ReificationSupportApi.SyntacticApplied:()Lscala/reflect/api/Internals$ReificationSupportApi$SyntacticAppliedExtractor;
  #258 = Utf8               SyntacticTypeApplied
  #259 = Utf8               ()Lscala/reflect/api/Internals$ReificationSupportApi$SyntacticTypeAppliedExtractor;
  #260 = NameAndType        #258:#259     // SyntacticTypeApplied:()Lscala/reflect/api/Internals$ReificationSupportApi$SyntacticTypeAppliedExtractor;
  #261 = InterfaceMethodref #48.#260      // scala/reflect/api/Internals$ReificationSupportApi.SyntacticTypeApplied:()Lscala/reflect/api/Internals$ReificationSupportApi$SyntacticTypeAppliedExtractor;
  #262 = Utf8               SyntacticSelectTerm
  #263 = Utf8               ()Lscala/reflect/api/Internals$ReificationSupportApi$SyntacticSelectTermExtractor;
  #264 = NameAndType        #262:#263     // SyntacticSelectTerm:()Lscala/reflect/api/Internals$ReificationSupportApi$SyntacticSelectTermExtractor;
  #265 = InterfaceMethodref #48.#264      // scala/reflect/api/Internals$ReificationSupportApi.SyntacticSelectTerm:()Lscala/reflect/api/Internals$ReificationSupportApi$SyntacticSelectTermExtractor;
  #266 = Utf8               SyntacticTermIdent
  #267 = Utf8               ()Lscala/reflect/api/Internals$ReificationSupportApi$SyntacticTermIdentExtractor;
  #268 = NameAndType        #266:#267     // SyntacticTermIdent:()Lscala/reflect/api/Internals$ReificationSupportApi$SyntacticTermIdentExtractor;
  #269 = InterfaceMethodref #48.#268      // scala/reflect/api/Internals$ReificationSupportApi.SyntacticTermIdent:()Lscala/reflect/api/Internals$ReificationSupportApi$SyntacticTermIdentExtractor;
  #270 = Utf8               TermName
  #271 = Utf8               ()Lscala/reflect/api/Names$TermNameExtractor;
  #272 = NameAndType        #270:#271     // TermName:()Lscala/reflect/api/Names$TermNameExtractor;
  #273 = Methodref          #245.#272     // scala/reflect/macros/Universe.TermName:()Lscala/reflect/api/Names$TermNameExtractor;
  #274 = Utf8               scala
  #275 = String             #274          // scala
  #276 = Utf8               (Ljava/lang/String;)Lscala/reflect/api/Names$TermNameApi;
  #277 = NameAndType        #193:#276     // apply:(Ljava/lang/String;)Lscala/reflect/api/Names$TermNameApi;
  #278 = Methodref          #86.#277      // scala/reflect/api/Names$TermNameExtractor.apply:(Ljava/lang/String;)Lscala/reflect/api/Names$TermNameApi;
  #279 = Utf8               (Lscala/reflect/api/Names$TermNameApi;Z)Lscala/reflect/api/Trees$IdentApi;
  #280 = NameAndType        #193:#279     // apply:(Lscala/reflect/api/Names$TermNameApi;Z)Lscala/reflect/api/Trees$IdentApi;
  #281 = InterfaceMethodref #66.#280      // scala/reflect/api/Internals$ReificationSupportApi$SyntacticTermIdentExtractor.apply:(Lscala/reflect/api/Names$TermNameApi;Z)Lscala/reflect/api/Trees$IdentApi;
  #282 = Utf8               collection
  #283 = String             #282          // collection
  #284 = Utf8               (Lscala/reflect/api/Trees$TreeApi;Lscala/reflect/api/Names$TermNameApi;)Lscala/reflect/api/Trees$SelectApi;
  #285 = NameAndType        #193:#284     // apply:(Lscala/reflect/api/Trees$TreeApi;Lscala/reflect/api/Names$TermNameApi;)Lscala/reflect/api/Trees$SelectApi;
  #286 = InterfaceMethodref #60.#285      // scala/reflect/api/Internals$ReificationSupportApi$SyntacticSelectTermExtractor.apply:(Lscala/reflect/api/Trees$TreeApi;Lscala/reflect/api/Names$TermNameApi;)Lscala/reflect/api/Trees$SelectApi;
  #287 = Utf8               immutable
  #288 = String             #287          // immutable
  #289 = Utf8               ListMap
  #290 = String             #289          // ListMap
  #291 = Utf8               scala/collection/immutable/$colon$colon
  #292 = Class              #291          // scala/collection/immutable/$colon$colon
  #293 = Utf8               SyntacticAppliedType
  #294 = NameAndType        #293:#259     // SyntacticAppliedType:()Lscala/reflect/api/Internals$ReificationSupportApi$SyntacticTypeAppliedExtractor;
  #295 = InterfaceMethodref #48.#294      // scala/reflect/api/Internals$ReificationSupportApi.SyntacticAppliedType:()Lscala/reflect/api/Internals$ReificationSupportApi$SyntacticTypeAppliedExtractor;
  #296 = Utf8               SyntacticTypeIdent
  #297 = Utf8               ()Lscala/reflect/api/Internals$ReificationSupportApi$SyntacticTypeIdentExtractor;
  #298 = NameAndType        #296:#297     // SyntacticTypeIdent:()Lscala/reflect/api/Internals$ReificationSupportApi$SyntacticTypeIdentExtractor;
  #299 = InterfaceMethodref #48.#298      // scala/reflect/api/Internals$ReificationSupportApi.SyntacticTypeIdent:()Lscala/reflect/api/Internals$ReificationSupportApi$SyntacticTypeIdentExtractor;
  #300 = Utf8               TypeName
  #301 = Utf8               ()Lscala/reflect/api/Names$TypeNameExtractor;
  #302 = NameAndType        #300:#301     // TypeName:()Lscala/reflect/api/Names$TypeNameExtractor;
  #303 = Methodref          #245.#302     // scala/reflect/macros/Universe.TypeName:()Lscala/reflect/api/Names$TypeNameExtractor;
  #304 = String             #182          // Vector
  #305 = Utf8               (Ljava/lang/String;)Lscala/reflect/api/Names$TypeNameApi;
  #306 = NameAndType        #193:#305     // apply:(Ljava/lang/String;)Lscala/reflect/api/Names$TypeNameApi;
  #307 = Methodref          #92.#306      // scala/reflect/api/Names$TypeNameExtractor.apply:(Ljava/lang/String;)Lscala/reflect/api/Names$TypeNameApi;
  #308 = Utf8               (Lscala/reflect/api/Names$TypeNameApi;)Lscala/reflect/api/Trees$IdentApi;
  #309 = NameAndType        #193:#308     // apply:(Lscala/reflect/api/Names$TypeNameApi;)Lscala/reflect/api/Trees$IdentApi;
  #310 = InterfaceMethodref #75.#309      // scala/reflect/api/Internals$ReificationSupportApi$SyntacticTypeIdentExtractor.apply:(Lscala/reflect/api/Names$TypeNameApi;)Lscala/reflect/api/Trees$IdentApi;
  #311 = Utf8               SyntacticSelectType
  #312 = Utf8               ()Lscala/reflect/api/Internals$ReificationSupportApi$SyntacticSelectTypeExtractor;
  #313 = NameAndType        #311:#312     // SyntacticSelectType:()Lscala/reflect/api/Internals$ReificationSupportApi$SyntacticSelectTypeExtractor;
  #314 = InterfaceMethodref #48.#313      // scala/reflect/api/Internals$ReificationSupportApi.SyntacticSelectType:()Lscala/reflect/api/Internals$ReificationSupportApi$SyntacticSelectTypeExtractor;
  #315 = Utf8               Predef
  #316 = String             #315          // Predef
  #317 = Utf8               String
  #318 = String             #317          // String
  #319 = Utf8               (Lscala/reflect/api/Trees$TreeApi;Lscala/reflect/api/Names$TypeNameApi;)Lscala/reflect/api/Trees$SelectApi;
  #320 = NameAndType        #193:#319     // apply:(Lscala/reflect/api/Trees$TreeApi;Lscala/reflect/api/Names$TypeNameApi;)Lscala/reflect/api/Trees$SelectApi;
  #321 = InterfaceMethodref #63.#320      // scala/reflect/api/Internals$ReificationSupportApi$SyntacticSelectTypeExtractor.apply:(Lscala/reflect/api/Trees$TreeApi;Lscala/reflect/api/Names$TypeNameApi;)Lscala/reflect/api/Trees$SelectApi;
  #322 = Utf8               <init>
  #323 = Utf8               (Ljava/lang/Object;Lscala/collection/immutable/List;)V
  #324 = NameAndType        #322:#323     // "<init>":(Ljava/lang/Object;Lscala/collection/immutable/List;)V
  #325 = Methodref          #292.#324     // scala/collection/immutable/$colon$colon."<init>":(Ljava/lang/Object;Lscala/collection/immutable/List;)V
  #326 = Utf8               scala/collection/immutable/List
  #327 = Class              #326          // scala/collection/immutable/List
  #328 = Utf8               (Lscala/reflect/api/Trees$TreeApi;Lscala/collection/immutable/List;)Lscala/reflect/api/Trees$TreeApi;
  #329 = NameAndType        #193:#328     // apply:(Lscala/reflect/api/Trees$TreeApi;Lscala/collection/immutable/List;)Lscala/reflect/api/Trees$TreeApi;
  #330 = InterfaceMethodref #72.#329      // scala/reflect/api/Internals$ReificationSupportApi$SyntacticTypeAppliedExtractor.apply:(Lscala/reflect/api/Trees$TreeApi;Lscala/collection/immutable/List;)Lscala/reflect/api/Trees$TreeApi;
  #331 = Utf8               elem
  #332 = Utf8               Ljava/lang/Object;
  #333 = NameAndType        #331:#332     // elem:Ljava/lang/Object;
  #334 = Fieldref           #198.#333     // scala/runtime/ObjectRef.elem:Ljava/lang/Object;
  #335 = Utf8               toList
  #336 = Utf8               ()Lscala/collection/immutable/List;
  #337 = NameAndType        #335:#336     // toList:()Lscala/collection/immutable/List;
  #338 = Methodref          #176.#337     // scala/collection/immutable/Vector.toList:()Lscala/collection/immutable/List;
  #339 = InterfaceMethodref #51.#329      // scala/reflect/api/Internals$ReificationSupportApi$SyntacticAppliedExtractor.apply:(Lscala/reflect/api/Trees$TreeApi;Lscala/collection/immutable/List;)Lscala/reflect/api/Trees$TreeApi;
  #340 = Utf8               ()Lscala/reflect/api/TypeTags$WeakTypeTag$;
  #341 = NameAndType        #124:#340     // WeakTypeTag:()Lscala/reflect/api/TypeTags$WeakTypeTag$;
  #342 = Methodref          #245.#341     // scala/reflect/macros/Universe.WeakTypeTag:()Lscala/reflect/api/TypeTags$WeakTypeTag$;
  #343 = Utf8               Nothing
  #344 = Utf8               ()Lscala/reflect/api/TypeTags$WeakTypeTag;
  #345 = NameAndType        #343:#344     // Nothing:()Lscala/reflect/api/TypeTags$WeakTypeTag;
  #346 = Methodref          #126.#345     // scala/reflect/api/TypeTags$WeakTypeTag$.Nothing:()Lscala/reflect/api/TypeTags$WeakTypeTag;
  #347 = Utf8               (Lscala/reflect/api/Trees$TreeApi;Lscala/reflect/api/TypeTags$WeakTypeTag;)Lscala/reflect/api/Exprs$Expr;
  #348 = NameAndType        #41:#347      // Expr:(Lscala/reflect/api/Trees$TreeApi;Lscala/reflect/api/TypeTags$WeakTypeTag;)Lscala/reflect/api/Exprs$Expr;
  #349 = InterfaceMethodref #239.#348     // scala/reflect/macros/blackbox/Context.Expr:(Lscala/reflect/api/Trees$TreeApi;Lscala/reflect/api/TypeTags$WeakTypeTag;)Lscala/reflect/api/Exprs$Expr;
  #350 = Utf8               x$1
  #351 = Utf8               x$2
  #352 = Utf8               Lscala/reflect/api/Trees$TreeApi;
  #353 = Utf8               x$3
  #354 = Utf8               I
  #355 = Utf8               x$4
  #356 = Utf8               x$5
  #357 = Utf8               x$6
  #358 = Utf8               pf
  #359 = Utf8               Lscala/Function2;
  #360 = Utf8               rps
  #361 = Utf8               Lscala/collection/immutable/Vector;
  #362 = Utf8               args
  #363 = Utf8               Lscala/runtime/ObjectRef;
  #364 = Utf8               r
  #365 = Utf8               Z
  #366 = Utf8               Lscala/reflect/api/Exprs$Expr;
  #367 = Utf8               textImpl
  #368 = Utf8               (Lscala/reflect/api/Exprs$Expr;Lscala/reflect/api/Exprs$Expr;)Lscala/reflect/api/Exprs$Expr;
  #369 = Utf8               (Lscala/reflect/api/Exprs$Expr<Lscala/collection/immutable/Vector<Ljava/lang/String;>;>;Lscala/reflect/api/Exprs$Expr<Lscala/Function2<Lscala/collection/immutable/Vector<Ljava/lang/String;>;Ljava/io/File;Ljava/lang/Object;>;>;)Lscala/reflect/api/Exprs$Expr<Lscala/collection/immutable/Map<Lscala/collection/immutable/Vector<Ljava/lang/String;>;Ljava/lang/String;>;>;
  #370 = NameAndType        #148:#149     // commonImpl:(ZLscala/reflect/api/Exprs$Expr;Lscala/reflect/api/Exprs$Expr;)Lscala/reflect/api/Exprs$Expr;
  #371 = Methodref          #2.#370       // org/sireum/$internal/RC.commonImpl:(ZLscala/reflect/api/Exprs$Expr;Lscala/reflect/api/Exprs$Expr;)Lscala/reflect/api/Exprs$Expr;
  #372 = Utf8               base64Impl
  #373 = Utf8               uriOf
  #374 = Utf8               (Ljava/io/File;)Ljava/lang/String;
  #375 = Utf8               f
  #376 = Utf8               java/io/File
  #377 = Class              #376          // java/io/File
  #378 = Utf8               toURI
  #379 = Utf8               ()Ljava/net/URI;
  #380 = NameAndType        #378:#379     // toURI:()Ljava/net/URI;
  #381 = Methodref          #377.#380     // java/io/File.toURI:()Ljava/net/URI;
  #382 = Utf8               java/net/URI
  #383 = Class              #382          // java/net/URI
  #384 = Utf8               toASCIIString
  #385 = Utf8               ()Ljava/lang/String;
  #386 = NameAndType        #384:#385     // toASCIIString:()Ljava/lang/String;
  #387 = Methodref          #383.#386     // java/net/URI.toASCIIString:()Ljava/lang/String;
  #388 = Utf8               Ljava/io/File;
  #389 = Utf8               readText
  #390 = Utf8               java/lang/String
  #391 = Class              #390          // java/lang/String
  #392 = Utf8               toPath
  #393 = Utf8               ()Ljava/nio/file/Path;
  #394 = NameAndType        #392:#393     // toPath:()Ljava/nio/file/Path;
  #395 = Methodref          #377.#394     // java/io/File.toPath:()Ljava/nio/file/Path;
  #396 = Utf8               java/nio/file/Files
  #397 = Class              #396          // java/nio/file/Files
  #398 = Utf8               readAllBytes
  #399 = Utf8               (Ljava/nio/file/Path;)[B
  #400 = NameAndType        #398:#399     // readAllBytes:(Ljava/nio/file/Path;)[B
  #401 = Methodref          #397.#400     // java/nio/file/Files.readAllBytes:(Ljava/nio/file/Path;)[B
  #402 = Utf8               java/nio/charset/StandardCharsets
  #403 = Class              #402          // java/nio/charset/StandardCharsets
  #404 = Utf8               UTF_8
  #405 = Utf8               Ljava/nio/charset/Charset;
  #406 = NameAndType        #404:#405     // UTF_8:Ljava/nio/charset/Charset;
  #407 = Fieldref           #403.#406     // java/nio/charset/StandardCharsets.UTF_8:Ljava/nio/charset/Charset;
  #408 = Utf8               ([BLjava/nio/charset/Charset;)V
  #409 = NameAndType        #322:#408     // "<init>":([BLjava/nio/charset/Charset;)V
  #410 = Methodref          #391.#409     // java/lang/String."<init>":([BLjava/nio/charset/Charset;)V
  #411 = Utf8               readBase64
  #412 = Utf8               getEncoder
  #413 = Utf8               ()Ljava/util/Base64$Encoder;
  #414 = NameAndType        #412:#413     // getEncoder:()Ljava/util/Base64$Encoder;
  #415 = Methodref          #17.#414      // java/util/Base64.getEncoder:()Ljava/util/Base64$Encoder;
  #416 = Utf8               encodeToString
  #417 = Utf8               ([B)Ljava/lang/String;
  #418 = NameAndType        #416:#417     // encodeToString:([B)Ljava/lang/String;
  #419 = Methodref          #15.#418      // java/util/Base64$Encoder.encodeToString:([B)Ljava/lang/String;
  #420 = Utf8               $anonfun$commonImpl$1
  #421 = Utf8               (Lorg/sireum/$internal/RC;Ljava/lang/String;)Lscala/reflect/api/Trees$LiteralApi;
  #422 = Utf8               $this
  #423 = Utf8               Literal
  #424 = Utf8               ()Lscala/reflect/api/Trees$LiteralExtractor;
  #425 = NameAndType        #423:#424     // Literal:()Lscala/reflect/api/Trees$LiteralExtractor;
  #426 = Methodref          #245.#425     // scala/reflect/macros/Universe.Literal:()Lscala/reflect/api/Trees$LiteralExtractor;
  #427 = Utf8               Constant
  #428 = Utf8               ()Lscala/reflect/api/Constants$ConstantExtractor;
  #429 = NameAndType        #427:#428     // Constant:()Lscala/reflect/api/Constants$ConstantExtractor;
  #430 = Methodref          #245.#429     // scala/reflect/macros/Universe.Constant:()Lscala/reflect/api/Constants$ConstantExtractor;
  #431 = Utf8               (Ljava/lang/Object;)Lscala/reflect/api/Constants$ConstantApi;
  #432 = NameAndType        #193:#431     // apply:(Ljava/lang/Object;)Lscala/reflect/api/Constants$ConstantApi;
  #433 = Methodref          #35.#432      // scala/reflect/api/Constants$ConstantExtractor.apply:(Ljava/lang/Object;)Lscala/reflect/api/Constants$ConstantApi;
  #434 = Utf8               (Lscala/reflect/api/Constants$ConstantApi;)Lscala/reflect/api/Trees$LiteralApi;
  #435 = NameAndType        #193:#434     // apply:(Lscala/reflect/api/Constants$ConstantApi;)Lscala/reflect/api/Trees$LiteralApi;
  #436 = Methodref          #109.#435     // scala/reflect/api/Trees$LiteralExtractor.apply:(Lscala/reflect/api/Constants$ConstantApi;)Lscala/reflect/api/Trees$LiteralApi;
  #437 = Utf8               Ljava/lang/String;
  #438 = Utf8               $anonfun$commonImpl$2
  #439 = Utf8               $anonfun$commonImpl$3
  #440 = Utf8               (Lorg/sireum/$internal/RC;I)Lscala/reflect/api/Names$TermNameApi;
  #441 = Utf8               n
  #442 = Utf8               java/lang/StringBuilder
  #443 = Class              #442          // java/lang/StringBuilder
  #444 = Utf8               (I)V
  #445 = NameAndType        #322:#444     // "<init>":(I)V
  #446 = Methodref          #443.#445     // java/lang/StringBuilder."<init>":(I)V
  #447 = String             #375          // f
  #448 = Utf8               append
  #449 = Utf8               (Ljava/lang/String;)Ljava/lang/StringBuilder;
  #450 = NameAndType        #448:#449     // append:(Ljava/lang/String;)Ljava/lang/StringBuilder;
  #451 = Methodref          #443.#450     // java/lang/StringBuilder.append:(Ljava/lang/String;)Ljava/lang/StringBuilder;
  #452 = Utf8               (I)Ljava/lang/StringBuilder;
  #453 = NameAndType        #448:#452     // append:(I)Ljava/lang/StringBuilder;
  #454 = Methodref          #443.#453     // java/lang/StringBuilder.append:(I)Ljava/lang/StringBuilder;
  #455 = Utf8               toString
  #456 = NameAndType        #455:#385     // toString:()Ljava/lang/String;
  #457 = Methodref          #443.#456     // java/lang/StringBuilder.toString:()Ljava/lang/String;
  #458 = Utf8               $anonfun$commonImpl$4
  #459 = Utf8               (Lorg/sireum/$internal/RC;Lscala/Tuple2;)Lscala/reflect/api/Trees$DefDefApi;
  #460 = Utf8               SyntacticDefDef
  #461 = Utf8               ()Lscala/reflect/api/Internals$ReificationSupportApi$SyntacticDefDefExtractor;
  #462 = NameAndType        #460:#461     // SyntacticDefDef:()Lscala/reflect/api/Internals$ReificationSupportApi$SyntacticDefDefExtractor;
  #463 = InterfaceMethodref #48.#462      // scala/reflect/api/Internals$ReificationSupportApi.SyntacticDefDef:()Lscala/reflect/api/Internals$ReificationSupportApi$SyntacticDefDefExtractor;
  #464 = Utf8               NoMods
  #465 = Utf8               ()Lscala/reflect/api/Trees$ModifiersApi;
  #466 = NameAndType        #464:#465     // NoMods:()Lscala/reflect/api/Trees$ModifiersApi;
  #467 = Methodref          #245.#466     // scala/reflect/macros/Universe.NoMods:()Lscala/reflect/api/Trees$ModifiersApi;
  #468 = Utf8               scala/Tuple2
  #469 = Class              #468          // scala/Tuple2
  #470 = Utf8               _1
  #471 = Utf8               ()Ljava/lang/Object;
  #472 = NameAndType        #470:#471     // _1:()Ljava/lang/Object;
  #473 = Methodref          #469.#472     // scala/Tuple2._1:()Ljava/lang/Object;
  #474 = Utf8               _2
  #475 = NameAndType        #474:#471     // _2:()Ljava/lang/Object;
  #476 = Methodref          #469.#475     // scala/Tuple2._2:()Ljava/lang/Object;
  #477 = Utf8               (Lscala/reflect/api/Trees$ModifiersApi;Lscala/reflect/api/Names$TermNameApi;Lscala/collection/immutable/List;Lscala/collection/immutable/List;Lscala/reflect/api/Trees$TreeApi;Lscala/reflect/api/Trees$TreeApi;)Lscala/reflect/api/Trees$DefDefApi;
  #478 = NameAndType        #193:#477     // apply:(Lscala/reflect/api/Trees$ModifiersApi;Lscala/reflect/api/Names$TermNameApi;Lscala/collection/immutable/List;Lscala/collection/immutable/List;Lscala/reflect/api/Trees$TreeApi;Lscala/reflect/api/Trees$TreeApi;)Lscala/reflect/api/Trees$DefDefApi;
  #479 = InterfaceMethodref #57.#478      // scala/reflect/api/Internals$ReificationSupportApi$SyntacticDefDefExtractor.apply:(Lscala/reflect/api/Trees$ModifiersApi;Lscala/reflect/api/Names$TermNameApi;Lscala/collection/immutable/List;Lscala/collection/immutable/List;Lscala/reflect/api/Trees$TreeApi;Lscala/reflect/api/Trees$TreeApi;)Lscala/reflect/api/Trees$DefDefApi;
  #480 = Utf8               Lscala/Tuple2;
  #481 = Utf8               $anonfun$commonImpl$5
  #482 = Utf8               (Lorg/sireum/$internal/RC;Lscala/reflect/api/Names$TermNameApi;)Lscala/reflect/api/Trees$TreeApi;
  #483 = Utf8               Ident
  #484 = Utf8               ()Lscala/reflect/api/Trees$IdentExtractor;
  #485 = NameAndType        #483:#484     // Ident:()Lscala/reflect/api/Trees$IdentExtractor;
  #486 = Methodref          #245.#485     // scala/reflect/macros/Universe.Ident:()Lscala/reflect/api/Trees$IdentExtractor;
  #487 = Utf8               (Lscala/reflect/api/Names$NameApi;)Lscala/reflect/api/Trees$IdentApi;
  #488 = NameAndType        #193:#487     // apply:(Lscala/reflect/api/Names$NameApi;)Lscala/reflect/api/Trees$IdentApi;
  #489 = Methodref          #103.#488     // scala/reflect/api/Trees$IdentExtractor.apply:(Lscala/reflect/api/Names$NameApi;)Lscala/reflect/api/Trees$IdentApi;
  #490 = Utf8               Lscala/reflect/api/Names$TermNameApi;
  #491 = Utf8               $anonfun$commonImpl$6
  #492 = Utf8               (Lorg/sireum/$internal/RC;Lscala/reflect/api/Trees$TreeApi;Lscala/reflect/api/Trees$TreeApi;)Lscala/reflect/api/Trees$TreeApi;
  #493 = Utf8               f1
  #494 = Utf8               f2
  #495 = Utf8               $plus
  #496 = String             #495          // $plus
  #497 = Utf8               $anonfun$commonImpl$7
  #498 = Utf8               (Lorg/sireum/$internal/RC;Ljava/lang/String;Lscala/Function2;ZLscala/runtime/ObjectRef;Ljava/io/File;)V
  #499 = Utf8               anchorPath$1
  #500 = Utf8               pf$1
  #501 = Utf8               isText$1
  #502 = Utf8               args$1
  #503 = Utf8               file
  #504 = Utf8               rec$1
  #505 = Utf8               (Ljava/io/File;Ljava/lang/String;Lscala/Function2;ZLscala/runtime/ObjectRef;)V
  #506 = NameAndType        #504:#505     // rec$1:(Ljava/io/File;Ljava/lang/String;Lscala/Function2;ZLscala/runtime/ObjectRef;)V
  #507 = Methodref          #2.#506       // org/sireum/$internal/RC.rec$1:(Ljava/io/File;Ljava/lang/String;Lscala/Function2;ZLscala/runtime/ObjectRef;)V
  #508 = Utf8               isFile
  #509 = NameAndType        #508:#204     // isFile:()Z
  #510 = Methodref          #377.#509     // java/io/File.isFile:()Z
  #511 = NameAndType        #373:#374     // uriOf:(Ljava/io/File;)Ljava/lang/String;
  #512 = Methodref          #2.#511       // org/sireum/$internal/RC.uriOf:(Ljava/io/File;)Ljava/lang/String;
  #513 = Utf8               startsWith
  #514 = Utf8               (Ljava/lang/String;)Z
  #515 = NameAndType        #513:#514     // startsWith:(Ljava/lang/String;)Z
  #516 = Methodref          #391.#515     // java/lang/String.startsWith:(Ljava/lang/String;)Z
  #517 = Utf8               scala/Predef$
  #518 = Class              #517          // scala/Predef$
  #519 = Utf8               Lscala/Predef$;
  #520 = NameAndType        #136:#519     // MODULE$:Lscala/Predef$;
  #521 = Fieldref           #518.#520     // scala/Predef$.MODULE$:Lscala/Predef$;
  #522 = Utf8               scala/collection/StringOps$
  #523 = Class              #522          // scala/collection/StringOps$
  #524 = Utf8               Lscala/collection/StringOps$;
  #525 = NameAndType        #136:#524     // MODULE$:Lscala/collection/StringOps$;
  #526 = Fieldref           #523.#525     // scala/collection/StringOps$.MODULE$:Lscala/collection/StringOps$;
  #527 = Utf8               length
  #528 = Utf8               ()I
  #529 = NameAndType        #527:#528     // length:()I
  #530 = Methodref          #391.#529     // java/lang/String.length:()I
  #531 = Utf8               substring
  #532 = Utf8               (I)Ljava/lang/String;
  #533 = NameAndType        #531:#532     // substring:(I)Ljava/lang/String;
  #534 = Methodref          #391.#533     // java/lang/String.substring:(I)Ljava/lang/String;
  #535 = Utf8               augmentString
  #536 = Utf8               (Ljava/lang/String;)Ljava/lang/String;
  #537 = NameAndType        #535:#536     // augmentString:(Ljava/lang/String;)Ljava/lang/String;
  #538 = Methodref          #518.#537     // scala/Predef$.augmentString:(Ljava/lang/String;)Ljava/lang/String;
  #539 = Utf8               split$extension
  #540 = Utf8               (Ljava/lang/String;C)[Ljava/lang/String;
  #541 = NameAndType        #539:#540     // split$extension:(Ljava/lang/String;C)[Ljava/lang/String;
  #542 = Methodref          #523.#541     // scala/collection/StringOps$.split$extension:(Ljava/lang/String;C)[Ljava/lang/String;
  #543 = Utf8               [Ljava/lang/Object;
  #544 = Class              #543          // "[Ljava/lang/Object;"
  #545 = Utf8               wrapRefArray
  #546 = Utf8               ([Ljava/lang/Object;)Lscala/collection/mutable/ArraySeq$ofRef;
  #547 = NameAndType        #545:#546     // wrapRefArray:([Ljava/lang/Object;)Lscala/collection/mutable/ArraySeq$ofRef;
  #548 = Methodref          #518.#547     // scala/Predef$.wrapRefArray:([Ljava/lang/Object;)Lscala/collection/mutable/ArraySeq$ofRef;
  #549 = Utf8               toVector
  #550 = Utf8               ()Lscala/collection/immutable/Vector;
  #551 = NameAndType        #549:#550     // toVector:()Lscala/collection/immutable/Vector;
  #552 = Methodref          #25.#551      // scala/collection/mutable/ArraySeq$ofRef.toVector:()Lscala/collection/immutable/Vector;
  #553 = Utf8               (Ljava/lang/Object;Ljava/lang/Object;)Ljava/lang/Object;
  #554 = NameAndType        #193:#553     // apply:(Ljava/lang/Object;Ljava/lang/Object;)Ljava/lang/Object;
  #555 = InterfaceMethodref #174.#554     // scala/Function2.apply:(Ljava/lang/Object;Ljava/lang/Object;)Ljava/lang/Object;
  #556 = Utf8               scala/runtime/BoxesRunTime
  #557 = Class              #556          // scala/runtime/BoxesRunTime
  #558 = Utf8               unboxToBoolean
  #559 = Utf8               (Ljava/lang/Object;)Z
  #560 = NameAndType        #558:#559     // unboxToBoolean:(Ljava/lang/Object;)Z
  #561 = Methodref          #557.#560     // scala/runtime/BoxesRunTime.unboxToBoolean:(Ljava/lang/Object;)Z
  #562 = NameAndType        #420:#421     // $anonfun$commonImpl$1:(Lorg/sireum/$internal/RC;Ljava/lang/String;)Lscala/reflect/api/Trees$LiteralApi;
  #563 = Methodref          #2.#562       // org/sireum/$internal/RC.$anonfun$commonImpl$1:(Lorg/sireum/$internal/RC;Ljava/lang/String;)Lscala/reflect/api/Trees$LiteralApi;
  #564 = MethodHandle       6:#563        // REF_invokeStatic org/sireum/$internal/RC.$anonfun$commonImpl$1:(Lorg/sireum/$internal/RC;Ljava/lang/String;)Lscala/reflect/api/Trees$LiteralApi;
  #565 = Utf8               (Ljava/lang/String;)Lscala/reflect/api/Trees$LiteralApi;
  #566 = MethodType         #565          //  (Ljava/lang/String;)Lscala/reflect/api/Trees$LiteralApi;
  #567 = Utf8               (Lorg/sireum/$internal/RC;)Lscala/Function1;
  #568 = NameAndType        #193:#567     // apply:(Lorg/sireum/$internal/RC;)Lscala/Function1;
  #569 = InvokeDynamic      #1:#568       // #1:apply:(Lorg/sireum/$internal/RC;)Lscala/Function1;
  #570 = Utf8               map
  #571 = Utf8               (Lscala/Function1;)Ljava/lang/Object;
  #572 = NameAndType        #570:#571     // map:(Lscala/Function1;)Ljava/lang/Object;
  #573 = Methodref          #176.#572     // scala/collection/immutable/Vector.map:(Lscala/Function1;)Ljava/lang/Object;
  #574 = NameAndType        #389:#374     // readText:(Ljava/io/File;)Ljava/lang/String;
  #575 = Methodref          #2.#574       // org/sireum/$internal/RC.readText:(Ljava/io/File;)Ljava/lang/String;
  #576 = NameAndType        #411:#374     // readBase64:(Ljava/io/File;)Ljava/lang/String;
  #577 = Methodref          #2.#576       // org/sireum/$internal/RC.readBase64:(Ljava/io/File;)Ljava/lang/String;
  #578 = Utf8               grouped$extension
  #579 = Utf8               (Ljava/lang/String;I)Lscala/collection/Iterator;
  #580 = NameAndType        #578:#579     // grouped$extension:(Ljava/lang/String;I)Lscala/collection/Iterator;
  #581 = Methodref          #523.#580     // scala/collection/StringOps$.grouped$extension:(Ljava/lang/String;I)Lscala/collection/Iterator;
  #582 = Utf8               scala/collection/Iterator
  #583 = Class              #582          // scala/collection/Iterator
  #584 = Utf8               toSeq
  #585 = Utf8               ()Lscala/collection/immutable/Seq;
  #586 = NameAndType        #584:#585     // toSeq:()Lscala/collection/immutable/Seq;
  #587 = InterfaceMethodref #583.#586     // scala/collection/Iterator.toSeq:()Lscala/collection/immutable/Seq;
  #588 = NameAndType        #438:#421     // $anonfun$commonImpl$2:(Lorg/sireum/$internal/RC;Ljava/lang/String;)Lscala/reflect/api/Trees$LiteralApi;
  #589 = Methodref          #2.#588       // org/sireum/$internal/RC.$anonfun$commonImpl$2:(Lorg/sireum/$internal/RC;Ljava/lang/String;)Lscala/reflect/api/Trees$LiteralApi;
  #590 = MethodHandle       6:#589        // REF_invokeStatic org/sireum/$internal/RC.$anonfun$commonImpl$2:(Lorg/sireum/$internal/RC;Ljava/lang/String;)Lscala/reflect/api/Trees$LiteralApi;
  #591 = InvokeDynamic      #2:#568       // #2:apply:(Lorg/sireum/$internal/RC;)Lscala/Function1;
  #592 = Utf8               scala/collection/immutable/Seq
  #593 = Class              #592          // scala/collection/immutable/Seq
  #594 = InterfaceMethodref #593.#572     // scala/collection/immutable/Seq.map:(Lscala/Function1;)Ljava/lang/Object;
  #595 = Utf8               indices
  #596 = Utf8               ()Lscala/collection/immutable/Range;
  #597 = NameAndType        #595:#596     // indices:()Lscala/collection/immutable/Range;
  #598 = InterfaceMethodref #593.#597     // scala/collection/immutable/Seq.indices:()Lscala/collection/immutable/Range;
  #599 = Utf8               scala/collection/immutable/Range
  #600 = Class              #599          // scala/collection/immutable/Range
  #601 = Methodref          #600.#551     // scala/collection/immutable/Range.toVector:()Lscala/collection/immutable/Vector;
  #602 = Utf8               $anonfun$commonImpl$3$adapted
  #603 = Utf8               (Lorg/sireum/$internal/RC;Ljava/lang/Object;)Lscala/reflect/api/Names$TermNameApi;
  #604 = NameAndType        #602:#603     // $anonfun$commonImpl$3$adapted:(Lorg/sireum/$internal/RC;Ljava/lang/Object;)Lscala/reflect/api/Names$TermNameApi;
  #605 = Methodref          #2.#604       // org/sireum/$internal/RC.$anonfun$commonImpl$3$adapted:(Lorg/sireum/$internal/RC;Ljava/lang/Object;)Lscala/reflect/api/Names$TermNameApi;
  #606 = MethodHandle       6:#605        // REF_invokeStatic org/sireum/$internal/RC.$anonfun$commonImpl$3$adapted:(Lorg/sireum/$internal/RC;Ljava/lang/Object;)Lscala/reflect/api/Names$TermNameApi;
  #607 = Utf8               (Ljava/lang/Object;)Lscala/reflect/api/Names$TermNameApi;
  #608 = MethodType         #607          //  (Ljava/lang/Object;)Lscala/reflect/api/Names$TermNameApi;
  #609 = InvokeDynamic      #3:#568       // #3:apply:(Lorg/sireum/$internal/RC;)Lscala/Function1;
  #610 = Utf8               zip
  #611 = Utf8               (Lscala/collection/IterableOnce;)Ljava/lang/Object;
  #612 = NameAndType        #610:#611     // zip:(Lscala/collection/IterableOnce;)Ljava/lang/Object;
  #613 = Methodref          #176.#612     // scala/collection/immutable/Vector.zip:(Lscala/collection/IterableOnce;)Ljava/lang/Object;
  #614 = Utf8               scala/collection/StrictOptimizedIterableOps
  #615 = Class              #614          // scala/collection/StrictOptimizedIterableOps
  #616 = NameAndType        #458:#459     // $anonfun$commonImpl$4:(Lorg/sireum/$internal/RC;Lscala/Tuple2;)Lscala/reflect/api/Trees$DefDefApi;
  #617 = Methodref          #2.#616       // org/sireum/$internal/RC.$anonfun$commonImpl$4:(Lorg/sireum/$internal/RC;Lscala/Tuple2;)Lscala/reflect/api/Trees$DefDefApi;
  #618 = MethodHandle       6:#617        // REF_invokeStatic org/sireum/$internal/RC.$anonfun$commonImpl$4:(Lorg/sireum/$internal/RC;Lscala/Tuple2;)Lscala/reflect/api/Trees$DefDefApi;
  #619 = Utf8               (Lscala/Tuple2;)Lscala/reflect/api/Trees$DefDefApi;
  #620 = MethodType         #619          //  (Lscala/Tuple2;)Lscala/reflect/api/Trees$DefDefApi;
  #621 = InvokeDynamic      #4:#568       // #4:apply:(Lorg/sireum/$internal/RC;)Lscala/Function1;
  #622 = InterfaceMethodref #615.#572     // scala/collection/StrictOptimizedIterableOps.map:(Lscala/Function1;)Ljava/lang/Object;
  #623 = Utf8               SyntacticBlock
  #624 = Utf8               ()Lscala/reflect/api/Internals$ReificationSupportApi$SyntacticBlockExtractor;
  #625 = NameAndType        #623:#624     // SyntacticBlock:()Lscala/reflect/api/Internals$ReificationSupportApi$SyntacticBlockExtractor;
  #626 = InterfaceMethodref #48.#625      // scala/reflect/api/Internals$ReificationSupportApi.SyntacticBlock:()Lscala/reflect/api/Internals$ReificationSupportApi$SyntacticBlockExtractor;
  #627 = NameAndType        #481:#482     // $anonfun$commonImpl$5:(Lorg/sireum/$internal/RC;Lscala/reflect/api/Names$TermNameApi;)Lscala/reflect/api/Trees$TreeApi;
  #628 = Methodref          #2.#627       // org/sireum/$internal/RC.$anonfun$commonImpl$5:(Lorg/sireum/$internal/RC;Lscala/reflect/api/Names$TermNameApi;)Lscala/reflect/api/Trees$TreeApi;
  #629 = MethodHandle       6:#628        // REF_invokeStatic org/sireum/$internal/RC.$anonfun$commonImpl$5:(Lorg/sireum/$internal/RC;Lscala/reflect/api/Names$TermNameApi;)Lscala/reflect/api/Trees$TreeApi;
  #630 = Utf8               (Lscala/reflect/api/Names$TermNameApi;)Lscala/reflect/api/Trees$TreeApi;
  #631 = MethodType         #630          //  (Lscala/reflect/api/Names$TermNameApi;)Lscala/reflect/api/Trees$TreeApi;
  #632 = InvokeDynamic      #5:#568       // #5:apply:(Lorg/sireum/$internal/RC;)Lscala/Function1;
  #633 = Utf8               scala/collection/IterableOnceOps
  #634 = Class              #633          // scala/collection/IterableOnceOps
  #635 = MethodType         #553          //  (Ljava/lang/Object;Ljava/lang/Object;)Ljava/lang/Object;
  #636 = NameAndType        #491:#492     // $anonfun$commonImpl$6:(Lorg/sireum/$internal/RC;Lscala/reflect/api/Trees$TreeApi;Lscala/reflect/api/Trees$TreeApi;)Lscala/reflect/api/Trees$TreeApi;
  #637 = Methodref          #2.#636       // org/sireum/$internal/RC.$anonfun$commonImpl$6:(Lorg/sireum/$internal/RC;Lscala/reflect/api/Trees$TreeApi;Lscala/reflect/api/Trees$TreeApi;)Lscala/reflect/api/Trees$TreeApi;
  #638 = MethodHandle       6:#637        // REF_invokeStatic org/sireum/$internal/RC.$anonfun$commonImpl$6:(Lorg/sireum/$internal/RC;Lscala/reflect/api/Trees$TreeApi;Lscala/reflect/api/Trees$TreeApi;)Lscala/reflect/api/Trees$TreeApi;
  #639 = Utf8               (Lscala/reflect/api/Trees$TreeApi;Lscala/reflect/api/Trees$TreeApi;)Lscala/reflect/api/Trees$TreeApi;
  #640 = MethodType         #639          //  (Lscala/reflect/api/Trees$TreeApi;Lscala/reflect/api/Trees$TreeApi;)Lscala/reflect/api/Trees$TreeApi;
  #641 = Utf8               (Lorg/sireum/$internal/RC;)Lscala/Function2;
  #642 = NameAndType        #193:#641     // apply:(Lorg/sireum/$internal/RC;)Lscala/Function2;
  #643 = InvokeDynamic      #6:#642       // #6:apply:(Lorg/sireum/$internal/RC;)Lscala/Function2;
  #644 = Utf8               reduce
  #645 = Utf8               (Lscala/Function2;)Ljava/lang/Object;
  #646 = NameAndType        #644:#645     // reduce:(Lscala/Function2;)Ljava/lang/Object;
  #647 = InterfaceMethodref #634.#646     // scala/collection/IterableOnceOps.reduce:(Lscala/Function2;)Ljava/lang/Object;
  #648 = Utf8               $colon$plus
  #649 = NameAndType        #648:#207     // $colon$plus:(Ljava/lang/Object;)Ljava/lang/Object;
  #650 = Methodref          #176.#649     // scala/collection/immutable/Vector.$colon$plus:(Ljava/lang/Object;)Ljava/lang/Object;
  #651 = InterfaceMethodref #634.#337     // scala/collection/IterableOnceOps.toList:()Lscala/collection/immutable/List;
  #652 = Utf8               (Lscala/collection/immutable/List;)Lscala/reflect/api/Trees$TreeApi;
  #653 = NameAndType        #193:#652     // apply:(Lscala/collection/immutable/List;)Lscala/reflect/api/Trees$TreeApi;
  #654 = InterfaceMethodref #54.#653      // scala/reflect/api/Internals$ReificationSupportApi$SyntacticBlockExtractor.apply:(Lscala/collection/immutable/List;)Lscala/reflect/api/Trees$TreeApi;
  #655 = Utf8               SyntacticTuple
  #656 = Utf8               ()Lscala/reflect/api/Internals$ReificationSupportApi$SyntacticTupleExtractor;
  #657 = NameAndType        #655:#656     // SyntacticTuple:()Lscala/reflect/api/Internals$ReificationSupportApi$SyntacticTupleExtractor;
  #658 = InterfaceMethodref #48.#657      // scala/reflect/api/Internals$ReificationSupportApi.SyntacticTuple:()Lscala/reflect/api/Internals$ReificationSupportApi$SyntacticTupleExtractor;
  #659 = InterfaceMethodref #69.#653      // scala/reflect/api/Internals$ReificationSupportApi$SyntacticTupleExtractor.apply:(Lscala/collection/immutable/List;)Lscala/reflect/api/Trees$TreeApi;
  #660 = Utf8               isDirectory
  #661 = NameAndType        #660:#204     // isDirectory:()Z
  #662 = Methodref          #377.#661     // java/io/File.isDirectory:()Z
  #663 = Utf8               scala/collection/ArrayOps$
  #664 = Class              #663          // scala/collection/ArrayOps$
  #665 = Utf8               Lscala/collection/ArrayOps$;
  #666 = NameAndType        #136:#665     // MODULE$:Lscala/collection/ArrayOps$;
  #667 = Fieldref           #664.#666     // scala/collection/ArrayOps$.MODULE$:Lscala/collection/ArrayOps$;
  #668 = Utf8               listFiles
  #669 = Utf8               ()[Ljava/io/File;
  #670 = NameAndType        #668:#669     // listFiles:()[Ljava/io/File;
  #671 = Methodref          #377.#670     // java/io/File.listFiles:()[Ljava/io/File;
  #672 = Utf8               refArrayOps
  #673 = Utf8               ([Ljava/lang/Object;)Ljava/lang/Object;
  #674 = NameAndType        #672:#673     // refArrayOps:([Ljava/lang/Object;)Ljava/lang/Object;
  #675 = Methodref          #518.#674     // scala/Predef$.refArrayOps:([Ljava/lang/Object;)Ljava/lang/Object;
  #676 = Utf8               $anonfun$commonImpl$7$adapted
  #677 = Utf8               (Lorg/sireum/$internal/RC;Ljava/lang/String;Lscala/Function2;ZLscala/runtime/ObjectRef;Ljava/io/File;)Ljava/lang/Object;
  #678 = NameAndType        #676:#677     // $anonfun$commonImpl$7$adapted:(Lorg/sireum/$internal/RC;Ljava/lang/String;Lscala/Function2;ZLscala/runtime/ObjectRef;Ljava/io/File;)Ljava/lang/Object;
  #679 = Methodref          #2.#678       // org/sireum/$internal/RC.$anonfun$commonImpl$7$adapted:(Lorg/sireum/$internal/RC;Ljava/lang/String;Lscala/Function2;ZLscala/runtime/ObjectRef;Ljava/io/File;)Ljava/lang/Object;
  #680 = MethodHandle       6:#679        // REF_invokeStatic org/sireum/$internal/RC.$anonfun$commonImpl$7$adapted:(Lorg/sireum/$internal/RC;Ljava/lang/String;Lscala/Function2;ZLscala/runtime/ObjectRef;Ljava/io/File;)Ljava/lang/Object;
  #681 = Utf8               (Ljava/io/File;)Ljava/lang/Object;
  #682 = MethodType         #681          //  (Ljava/io/File;)Ljava/lang/Object;
  #683 = Utf8               (Lorg/sireum/$internal/RC;Ljava/lang/String;Lscala/Function2;ZLscala/runtime/ObjectRef;)Lscala/Function1;
  #684 = NameAndType        #193:#683     // apply:(Lorg/sireum/$internal/RC;Ljava/lang/String;Lscala/Function2;ZLscala/runtime/ObjectRef;)Lscala/Function1;
  #685 = InvokeDynamic      #7:#684       // #7:apply:(Lorg/sireum/$internal/RC;Ljava/lang/String;Lscala/Function2;ZLscala/runtime/ObjectRef;)Lscala/Function1;
  #686 = Utf8               foreach$extension
  #687 = Utf8               (Ljava/lang/Object;Lscala/Function1;)V
  #688 = NameAndType        #686:#687     // foreach$extension:(Ljava/lang/Object;Lscala/Function1;)V
  #689 = Methodref          #664.#688     // scala/collection/ArrayOps$.foreach$extension:(Ljava/lang/Object;Lscala/Function1;)V
  #690 = Utf8               pathSegments
  #691 = Utf8               content
  #692 = Utf8               s
  #693 = Utf8               Lscala/collection/immutable/Seq;
  #694 = Utf8               fs
  #695 = Utf8               ms
  #696 = Utf8               b
  #697 = Utf8               path
  #698 = Utf8               filePath
  #699 = Utf8               rp
  #700 = Utf8               p$1
  #701 = Utf8               pos
  #702 = Utf8               ()Lscala/reflect/api/Position;
  #703 = NameAndType        #701:#702     // pos:()Lscala/reflect/api/Position;
  #704 = InterfaceMethodref #118.#703     // scala/reflect/api/Trees$TreeApi.pos:()Lscala/reflect/api/Position;
  #705 = Utf8               scala/reflect/api/Position
  #706 = Class              #705          // scala/reflect/api/Position
  #707 = Utf8               source
  #708 = Utf8               ()Lscala/reflect/internal/util/SourceFile;
  #709 = NameAndType        #707:#708     // source:()Lscala/reflect/internal/util/SourceFile;
  #710 = InterfaceMethodref #706.#709     // scala/reflect/api/Position.source:()Lscala/reflect/internal/util/SourceFile;
  #711 = Utf8               scala/reflect/internal/util/SourceFile
  #712 = Class              #711          // scala/reflect/internal/util/SourceFile
  #713 = Utf8               ()Lscala/reflect/io/AbstractFile;
  #714 = NameAndType        #503:#713     // file:()Lscala/reflect/io/AbstractFile;
  #715 = Methodref          #712.#714     // scala/reflect/internal/util/SourceFile.file:()Lscala/reflect/io/AbstractFile;
  #716 = Utf8               scala/reflect/io/AbstractFile
  #717 = Class              #716          // scala/reflect/io/AbstractFile
  #718 = Utf8               canonicalPath
  #719 = NameAndType        #718:#385     // canonicalPath:()Ljava/lang/String;
  #720 = Methodref          #717.#719     // scala/reflect/io/AbstractFile.canonicalPath:()Ljava/lang/String;
  #721 = Utf8               (Ljava/lang/String;)V
  #722 = NameAndType        #322:#721     // "<init>":(Ljava/lang/String;)V
  #723 = Methodref          #377.#722     // java/io/File."<init>":(Ljava/lang/String;)V
  #724 = Utf8               getParentFile
  #725 = Utf8               ()Ljava/io/File;
  #726 = NameAndType        #724:#725     // getParentFile:()Ljava/io/File;
  #727 = Methodref          #377.#726     // java/io/File.getParentFile:()Ljava/io/File;
  #728 = Utf8               (Ljava/io/File;Ljava/lang/String;)V
  #729 = NameAndType        #322:#728     // "<init>":(Ljava/io/File;Ljava/lang/String;)V
  #730 = Methodref          #377.#729     // java/io/File."<init>":(Ljava/io/File;Ljava/lang/String;)V
  #731 = Utf8               anchorDir
  #732 = Utf8               anchorPath
  #733 = Utf8               $anonfun$commonImpl$8
  #734 = Utf8               (Lorg/sireum/$internal/RC;Lscala/reflect/api/Exprs$Expr;Lscala/Function2;ZLscala/runtime/ObjectRef;Ljava/lang/String;)V
  #735 = Utf8               (Lscala/reflect/macros/blackbox/Context;)V
  #736 = Utf8               ()V
  #737 = NameAndType        #322:#736     // "<init>":()V
  #738 = Methodref          #4.#737       // java/lang/Object."<init>":()V
  #739 = NameAndType        #733:#734     // $anonfun$commonImpl$8:(Lorg/sireum/$internal/RC;Lscala/reflect/api/Exprs$Expr;Lscala/Function2;ZLscala/runtime/ObjectRef;Ljava/lang/String;)V
  #740 = Methodref          #2.#739       // org/sireum/$internal/RC.$anonfun$commonImpl$8:(Lorg/sireum/$internal/RC;Lscala/reflect/api/Exprs$Expr;Lscala/Function2;ZLscala/runtime/ObjectRef;Ljava/lang/String;)V
  #741 = Utf8               scala/runtime/BoxedUnit
  #742 = Class              #741          // scala/runtime/BoxedUnit
  #743 = Utf8               UNIT
  #744 = Utf8               Lscala/runtime/BoxedUnit;
  #745 = NameAndType        #743:#744     // UNIT:Lscala/runtime/BoxedUnit;
  #746 = Fieldref           #742.#745     // scala/runtime/BoxedUnit.UNIT:Lscala/runtime/BoxedUnit;
  #747 = Utf8               unboxToInt
  #748 = Utf8               (Ljava/lang/Object;)I
  #749 = NameAndType        #747:#748     // unboxToInt:(Ljava/lang/Object;)I
  #750 = Methodref          #557.#749     // scala/runtime/BoxesRunTime.unboxToInt:(Ljava/lang/Object;)I
  #751 = NameAndType        #439:#440     // $anonfun$commonImpl$3:(Lorg/sireum/$internal/RC;I)Lscala/reflect/api/Names$TermNameApi;
  #752 = Methodref          #2.#751       // org/sireum/$internal/RC.$anonfun$commonImpl$3:(Lorg/sireum/$internal/RC;I)Lscala/reflect/api/Names$TermNameApi;
  #753 = NameAndType        #497:#498     // $anonfun$commonImpl$7:(Lorg/sireum/$internal/RC;Ljava/lang/String;Lscala/Function2;ZLscala/runtime/ObjectRef;Ljava/io/File;)V
  #754 = Methodref          #2.#753       // org/sireum/$internal/RC.$anonfun$commonImpl$7:(Lorg/sireum/$internal/RC;Ljava/lang/String;Lscala/Function2;ZLscala/runtime/ObjectRef;Ljava/io/File;)V
  #755 = Utf8               $deserializeLambda$
  #756 = Utf8               (Ljava/lang/invoke/SerializedLambda;)Ljava/lang/Object;
  #757 = Utf8               scala/runtime/LambdaDeserialize
  #758 = Class              #757          // scala/runtime/LambdaDeserialize
  #759 = Utf8               bootstrap
  #760 = Utf8               (Ljava/lang/invoke/MethodHandles$Lookup;Ljava/lang/String;Ljava/lang/invoke/MethodType;[Ljava/lang/invoke/MethodHandle;)Ljava/lang/invoke/CallSite;
  #761 = NameAndType        #759:#760     // bootstrap:(Ljava/lang/invoke/MethodHandles$Lookup;Ljava/lang/String;Ljava/lang/invoke/MethodType;[Ljava/lang/invoke/MethodHandle;)Ljava/lang/invoke/CallSite;
  #762 = Methodref          #758.#761     // scala/runtime/LambdaDeserialize.bootstrap:(Ljava/lang/invoke/MethodHandles$Lookup;Ljava/lang/String;Ljava/lang/invoke/MethodType;[Ljava/lang/invoke/MethodHandle;)Ljava/lang/invoke/CallSite;
  #763 = MethodHandle       6:#762        // REF_invokeStatic scala/runtime/LambdaDeserialize.bootstrap:(Ljava/lang/invoke/MethodHandles$Lookup;Ljava/lang/String;Ljava/lang/invoke/MethodType;[Ljava/lang/invoke/MethodHandle;)Ljava/lang/invoke/CallSite;
  #764 = Utf8               lambdaDeserialize
  #765 = NameAndType        #764:#756     // lambdaDeserialize:(Ljava/lang/invoke/SerializedLambda;)Ljava/lang/Object;
  #766 = InvokeDynamic      #8:#765       // #8:lambdaDeserialize:(Ljava/lang/invoke/SerializedLambda;)Ljava/lang/Object;
  #767 = Utf8               Code
  #768 = Utf8               LocalVariableTable
  #769 = Utf8               Signature
  #770 = Utf8               MethodParameters
  #771 = Utf8               LineNumberTable
  #772 = Utf8               StackMapTable
  #773 = Utf8               InnerClasses
  #774 = Utf8               SourceFile
  #775 = Utf8               RuntimeVisibleAnnotations
  #776 = Utf8               BootstrapMethods
  #777 = Utf8               ScalaInlineInfo
  #778 = Utf8               ScalaSig
{
  private final scala.reflect.macros.blackbox.Context c;
    descriptor: Lscala/reflect/macros/blackbox/Context;
    flags: (0x0012) ACC_PRIVATE, ACC_FINAL

  public static org.sireum.$internal.Trie$Node<java.lang.String, java.lang.String> toTrie(scala.collection.Map<scala.collection.immutable.Vector<java.lang.String>, java.lang.String>);
    descriptor: (Lscala/collection/Map;)Lorg/sireum/$internal/Trie$Node;
    flags: (0x0009) ACC_PUBLIC, ACC_STATIC
    Code:
      stack=2, locals=1, args_size=1
         0: getstatic     #139                // Field org/sireum/$internal/RC$.MODULE$:Lorg/sireum/$internal/RC$;
         3: aload_0
         4: invokevirtual #141                // Method org/sireum/$internal/RC$.toTrie:(Lscala/collection/Map;)Lorg/sireum/$internal/Trie$Node;
         7: areturn
      LocalVariableTable:
        Start  Length  Slot  Name   Signature
            0       8     0     m   Lscala/collection/Map;
    Signature: #132                         // (Lscala/collection/Map<Lscala/collection/immutable/Vector<Ljava/lang/String;>;Ljava/lang/String;>;)Lorg/sireum/$internal/Trie$Node<Ljava/lang/String;Ljava/lang/String;>;
    MethodParameters:
      Name                           Flags
      m                              final

  public scala.reflect.macros.blackbox.Context c();
    descriptor: ()Lscala/reflect/macros/blackbox/Context;
    flags: (0x0001) ACC_PUBLIC
    Code:
      stack=1, locals=1, args_size=1
         0: aload_0
         1: getfield      #145                // Field c:Lscala/reflect/macros/blackbox/Context;
         4: areturn
      LineNumberTable:
        line 62: 0
      LocalVariableTable:
        Start  Length  Slot  Name   Signature
            0       5     0  this   Lorg/sireum/$internal/RC;

  public scala.reflect.api.Exprs$Expr<scala.collection.immutable.Map<scala.collection.immutable.Vector<java.lang.String>, java.lang.String>> commonImpl(boolean, scala.reflect.api.Exprs$Expr<scala.collection.immutable.Vector<java.lang.String>>, scala.reflect.api.Exprs$Expr<scala.Function2<scala.collection.immutable.Vector<java.lang.String>, java.io.File, java.lang.Object>>);
    descriptor: (ZLscala/reflect/api/Exprs$Expr;Lscala/reflect/api/Exprs$Expr;)Lscala/reflect/api/Exprs$Expr;
    flags: (0x0001) ACC_PUBLIC
    Code:
      stack=13, locals=14, args_size=4
         0: aload_0
         1: invokevirtual #155                // Method c:()Lscala/reflect/macros/blackbox/Context;
         4: astore        5
         6: aload_3
         7: invokeinterface #159,  1          // InterfaceMethod scala/reflect/api/Exprs$Expr.tree:()Lscala/reflect/api/Trees$TreeApi;
        12: astore        6
        14: getstatic     #164                // Field org/sireum/$internal/Macro$.MODULE$:Lorg/sireum/$internal/Macro$;
        17: aload         5
        19: invokevirtual #168                // Method org/sireum/$internal/Macro$.eval$default$3:(Lscala/reflect/macros/blackbox/Context;)I
        22: istore        7
        24: getstatic     #164                // Field org/sireum/$internal/Macro$.MODULE$:Lorg/sireum/$internal/Macro$;
        27: aload         5
        29: aload         6
        31: iload         7
        33: invokevirtual #172                // Method org/sireum/$internal/Macro$.eval:(Lscala/reflect/macros/blackbox/Context;Ljava/lang/Object;I)Ljava/lang/Object;
        36: checkcast     #174                // class scala/Function2
        39: astore        4
        41: aload_0
        42: invokevirtual #155                // Method c:()Lscala/reflect/macros/blackbox/Context;
        45: astore        9
        47: aload_2
        48: invokeinterface #159,  1          // InterfaceMethod scala/reflect/api/Exprs$Expr.tree:()Lscala/reflect/api/Trees$TreeApi;
        53: astore        10
        55: getstatic     #164                // Field org/sireum/$internal/Macro$.MODULE$:Lorg/sireum/$internal/Macro$;
        58: aload         9
        60: invokevirtual #168                // Method org/sireum/$internal/Macro$.eval$default$3:(Lscala/reflect/macros/blackbox/Context;)I
        63: istore        11
        65: getstatic     #164                // Field org/sireum/$internal/Macro$.MODULE$:Lorg/sireum/$internal/Macro$;
        68: aload         9
        70: aload         10
        72: iload         11
        74: invokevirtual #172                // Method org/sireum/$internal/Macro$.eval:(Lscala/reflect/macros/blackbox/Context;Ljava/lang/Object;I)Ljava/lang/Object;
        77: checkcast     #176                // class scala/collection/immutable/Vector
        80: astore        8
        82: getstatic     #181                // Field scala/package$.MODULE$:Lscala/package$;
        85: invokevirtual #185                // Method scala/package$.Vector:()Lscala/collection/immutable/Vector$;
        88: getstatic     #190                // Field scala/collection/immutable/Nil$.MODULE$:Lscala/collection/immutable/Nil$;
        91: invokevirtual #196                // Method scala/collection/immutable/Vector$.apply:(Lscala/collection/immutable/Seq;)Ljava/lang/Object;
        94: checkcast     #176                // class scala/collection/immutable/Vector
        97: invokestatic  #202                // Method scala/runtime/ObjectRef.create:(Ljava/lang/Object;)Lscala/runtime/ObjectRef;
       100: astore        12
       102: aload         8
       104: invokevirtual #206                // Method scala/collection/immutable/Vector.nonEmpty:()Z
       107: ifeq          130
       110: aload         8
       112: aload_0
       113: aload_3
       114: aload         4
       116: iload_1
       117: aload         12
       119: invokedynamic #227,  0            // InvokeDynamic #0:apply:(Lorg/sireum/$internal/RC;Lscala/reflect/api/Exprs$Expr;Lscala/Function2;ZLscala/runtime/ObjectRef;)Lscala/Function1;
       124: invokevirtual #231                // Method scala/collection/immutable/Vector.foreach:(Lscala/Function1;)V
       127: goto          142
       130: aload_0
       131: ldc           #233                // String .
       133: aload_3
       134: aload         4
       136: iload_1
       137: aload         12
       139: invokespecial #237                // Method it$1:(Ljava/lang/String;Lscala/reflect/api/Exprs$Expr;Lscala/Function2;ZLscala/runtime/ObjectRef;)V
       142: aload_0
       143: invokevirtual #155                // Method c:()Lscala/reflect/macros/blackbox/Context;
       146: invokeinterface #243,  1          // InterfaceMethod scala/reflect/macros/blackbox/Context.universe:()Lscala/reflect/macros/Universe;
       151: invokevirtual #249                // Method scala/reflect/macros/Universe.internal:()Lscala/reflect/api/Internals$InternalApi;
       154: invokeinterface #253,  1          // InterfaceMethod scala/reflect/api/Internals$InternalApi.reificationSupport:()Lscala/reflect/api/Internals$ReificationSupportApi;
       159: invokeinterface #257,  1          // InterfaceMethod scala/reflect/api/Internals$ReificationSupportApi.SyntacticApplied:()Lscala/reflect/api/Internals$ReificationSupportApi$SyntacticAppliedExtractor;
       164: aload_0
       165: invokevirtual #155                // Method c:()Lscala/reflect/macros/blackbox/Context;
       168: invokeinterface #243,  1          // InterfaceMethod scala/reflect/macros/blackbox/Context.universe:()Lscala/reflect/macros/Universe;
       173: invokevirtual #249                // Method scala/reflect/macros/Universe.internal:()Lscala/reflect/api/Internals$InternalApi;
       176: invokeinterface #253,  1          // InterfaceMethod scala/reflect/api/Internals$InternalApi.reificationSupport:()Lscala/reflect/api/Internals$ReificationSupportApi;
       181: invokeinterface #261,  1          // InterfaceMethod scala/reflect/api/Internals$ReificationSupportApi.SyntacticTypeApplied:()Lscala/reflect/api/Internals$ReificationSupportApi$SyntacticTypeAppliedExtractor;
       186: aload_0
       187: invokevirtual #155                // Method c:()Lscala/reflect/macros/blackbox/Context;
       190: invokeinterface #243,  1          // InterfaceMethod scala/reflect/macros/blackbox/Context.universe:()Lscala/reflect/macros/Universe;
       195: invokevirtual #249                // Method scala/reflect/macros/Universe.internal:()Lscala/reflect/api/Internals$InternalApi;
       198: invokeinterface #253,  1          // InterfaceMethod scala/reflect/api/Internals$InternalApi.reificationSupport:()Lscala/reflect/api/Internals$ReificationSupportApi;
       203: invokeinterface #265,  1          // InterfaceMethod scala/reflect/api/Internals$ReificationSupportApi.SyntacticSelectTerm:()Lscala/reflect/api/Internals$ReificationSupportApi$SyntacticSelectTermExtractor;
       208: aload_0
       209: invokevirtual #155                // Method c:()Lscala/reflect/macros/blackbox/Context;
       212: invokeinterface #243,  1          // InterfaceMethod scala/reflect/macros/blackbox/Context.universe:()Lscala/reflect/macros/Universe;
       217: invokevirtual #249                // Method scala/reflect/macros/Universe.internal:()Lscala/reflect/api/Internals$InternalApi;
       220: invokeinterface #253,  1          // InterfaceMethod scala/reflect/api/Internals$InternalApi.reificationSupport:()Lscala/reflect/api/Internals$ReificationSupportApi;
       225: invokeinterface #265,  1          // InterfaceMethod scala/reflect/api/Internals$ReificationSupportApi.SyntacticSelectTerm:()Lscala/reflect/api/Internals$ReificationSupportApi$SyntacticSelectTermExtractor;
       230: aload_0
       231: invokevirtual #155                // Method c:()Lscala/reflect/macros/blackbox/Context;
       234: invokeinterface #243,  1          // InterfaceMethod scala/reflect/macros/blackbox/Context.universe:()Lscala/reflect/macros/Universe;
       239: invokevirtual #249                // Method scala/reflect/macros/Universe.internal:()Lscala/reflect/api/Internals$InternalApi;
       242: invokeinterface #253,  1          // InterfaceMethod scala/reflect/api/Internals$InternalApi.reificationSupport:()Lscala/reflect/api/Internals$ReificationSupportApi;
       247: invokeinterface #265,  1          // InterfaceMethod scala/reflect/api/Internals$ReificationSupportApi.SyntacticSelectTerm:()Lscala/reflect/api/Internals$ReificationSupportApi$SyntacticSelectTermExtractor;
       252: aload_0
       253: invokevirtual #155                // Method c:()Lscala/reflect/macros/blackbox/Context;
       256: invokeinterface #243,  1          // InterfaceMethod scala/reflect/macros/blackbox/Context.universe:()Lscala/reflect/macros/Universe;
       261: invokevirtual #249                // Method scala/reflect/macros/Universe.internal:()Lscala/reflect/api/Internals$InternalApi;
       264: invokeinterface #253,  1          // InterfaceMethod scala/reflect/api/Internals$InternalApi.reificationSupport:()Lscala/reflect/api/Internals$ReificationSupportApi;
       269: invokeinterface #269,  1          // InterfaceMethod scala/reflect/api/Internals$ReificationSupportApi.SyntacticTermIdent:()Lscala/reflect/api/Internals$ReificationSupportApi$SyntacticTermIdentExtractor;
       274: aload_0
       275: invokevirtual #155                // Method c:()Lscala/reflect/macros/blackbox/Context;
       278: invokeinterface #243,  1          // InterfaceMethod scala/reflect/macros/blackbox/Context.universe:()Lscala/reflect/macros/Universe;
       283: invokevirtual #273                // Method scala/reflect/macros/Universe.TermName:()Lscala/reflect/api/Names$TermNameExtractor;
       286: ldc_w         #275                // String scala
       289: invokevirtual #278                // Method scala/reflect/api/Names$TermNameExtractor.apply:(Ljava/lang/String;)Lscala/reflect/api/Names$TermNameApi;
       292: iconst_0
       293: invokeinterface #281,  3          // InterfaceMethod scala/reflect/api/Internals$ReificationSupportApi$SyntacticTermIdentExtractor.apply:(Lscala/reflect/api/Names$TermNameApi;Z)Lscala/reflect/api/Trees$IdentApi;
       298: aload_0
       299: invokevirtual #155                // Method c:()Lscala/reflect/macros/blackbox/Context;
       302: invokeinterface #243,  1          // InterfaceMethod scala/reflect/macros/blackbox/Context.universe:()Lscala/reflect/macros/Universe;
       307: invokevirtual #273                // Method scala/reflect/macros/Universe.TermName:()Lscala/reflect/api/Names$TermNameExtractor;
       310: ldc_w         #283                // String collection
       313: invokevirtual #278                // Method scala/reflect/api/Names$TermNameExtractor.apply:(Ljava/lang/String;)Lscala/reflect/api/Names$TermNameApi;
       316: invokeinterface #286,  3          // InterfaceMethod scala/reflect/api/Internals$ReificationSupportApi$SyntacticSelectTermExtractor.apply:(Lscala/reflect/api/Trees$TreeApi;Lscala/reflect/api/Names$TermNameApi;)Lscala/reflect/api/Trees$SelectApi;
       321: aload_0
       322: invokevirtual #155                // Method c:()Lscala/reflect/macros/blackbox/Context;
       325: invokeinterface #243,  1          // InterfaceMethod scala/reflect/macros/blackbox/Context.universe:()Lscala/reflect/macros/Universe;
       330: invokevirtual #273                // Method scala/reflect/macros/Universe.TermName:()Lscala/reflect/api/Names$TermNameExtractor;
       333: ldc_w         #288                // String immutable
       336: invokevirtual #278                // Method scala/reflect/api/Names$TermNameExtractor.apply:(Ljava/lang/String;)Lscala/reflect/api/Names$TermNameApi;
       339: invokeinterface #286,  3          // InterfaceMethod scala/reflect/api/Internals$ReificationSupportApi$SyntacticSelectTermExtractor.apply:(Lscala/reflect/api/Trees$TreeApi;Lscala/reflect/api/Names$TermNameApi;)Lscala/reflect/api/Trees$SelectApi;
       344: aload_0
       345: invokevirtual #155                // Method c:()Lscala/reflect/macros/blackbox/Context;
       348: invokeinterface #243,  1          // InterfaceMethod scala/reflect/macros/blackbox/Context.universe:()Lscala/reflect/macros/Universe;
       353: invokevirtual #273                // Method scala/reflect/macros/Universe.TermName:()Lscala/reflect/api/Names$TermNameExtractor;
       356: ldc_w         #290                // String ListMap
       359: invokevirtual #278                // Method scala/reflect/api/Names$TermNameExtractor.apply:(Ljava/lang/String;)Lscala/reflect/api/Names$TermNameApi;
       362: invokeinterface #286,  3          // InterfaceMethod scala/reflect/api/Internals$ReificationSupportApi$SyntacticSelectTermExtractor.apply:(Lscala/reflect/api/Trees$TreeApi;Lscala/reflect/api/Names$TermNameApi;)Lscala/reflect/api/Trees$SelectApi;
       367: new           #292                // class scala/collection/immutable/$colon$colon
       370: dup
       371: aload_0
       372: invokevirtual #155                // Method c:()Lscala/reflect/macros/blackbox/Context;
       375: invokeinterface #243,  1          // InterfaceMethod scala/reflect/macros/blackbox/Context.universe:()Lscala/reflect/macros/Universe;
       380: invokevirtual #249                // Method scala/reflect/macros/Universe.internal:()Lscala/reflect/api/Internals$InternalApi;
       383: invokeinterface #253,  1          // InterfaceMethod scala/reflect/api/Internals$InternalApi.reificationSupport:()Lscala/reflect/api/Internals$ReificationSupportApi;
       388: invokeinterface #295,  1          // InterfaceMethod scala/reflect/api/Internals$ReificationSupportApi.SyntacticAppliedType:()Lscala/reflect/api/Internals$ReificationSupportApi$SyntacticTypeAppliedExtractor;
       393: aload_0
       394: invokevirtual #155                // Method c:()Lscala/reflect/macros/blackbox/Context;
       397: invokeinterface #243,  1          // InterfaceMethod scala/reflect/macros/blackbox/Context.universe:()Lscala/reflect/macros/Universe;
       402: invokevirtual #249                // Method scala/reflect/macros/Universe.internal:()Lscala/reflect/api/Internals$InternalApi;
       405: invokeinterface #253,  1          // InterfaceMethod scala/reflect/api/Internals$InternalApi.reificationSupport:()Lscala/reflect/api/Internals$ReificationSupportApi;
       410: invokeinterface #299,  1          // InterfaceMethod scala/reflect/api/Internals$ReificationSupportApi.SyntacticTypeIdent:()Lscala/reflect/api/Internals$ReificationSupportApi$SyntacticTypeIdentExtractor;
       415: aload_0
       416: invokevirtual #155                // Method c:()Lscala/reflect/macros/blackbox/Context;
       419: invokeinterface #243,  1          // InterfaceMethod scala/reflect/macros/blackbox/Context.universe:()Lscala/reflect/macros/Universe;
       424: invokevirtual #303                // Method scala/reflect/macros/Universe.TypeName:()Lscala/reflect/api/Names$TypeNameExtractor;
       427: ldc_w         #304                // String Vector
       430: invokevirtual #307                // Method scala/reflect/api/Names$TypeNameExtractor.apply:(Ljava/lang/String;)Lscala/reflect/api/Names$TypeNameApi;
       433: invokeinterface #310,  2          // InterfaceMethod scala/reflect/api/Internals$ReificationSupportApi$SyntacticTypeIdentExtractor.apply:(Lscala/reflect/api/Names$TypeNameApi;)Lscala/reflect/api/Trees$IdentApi;
       438: new           #292                // class scala/collection/immutable/$colon$colon
       441: dup
       442: aload_0
       443: invokevirtual #155                // Method c:()Lscala/reflect/macros/blackbox/Context;
       446: invokeinterface #243,  1          // InterfaceMethod scala/reflect/macros/blackbox/Context.universe:()Lscala/reflect/macros/Universe;
       451: invokevirtual #249                // Method scala/reflect/macros/Universe.internal:()Lscala/reflect/api/Internals$InternalApi;
       454: invokeinterface #253,  1          // InterfaceMethod scala/reflect/api/Internals$InternalApi.reificationSupport:()Lscala/reflect/api/Internals$ReificationSupportApi;
       459: invokeinterface #314,  1          // InterfaceMethod scala/reflect/api/Internals$ReificationSupportApi.SyntacticSelectType:()Lscala/reflect/api/Internals$ReificationSupportApi$SyntacticSelectTypeExtractor;
       464: aload_0
       465: invokevirtual #155                // Method c:()Lscala/reflect/macros/blackbox/Context;
       468: invokeinterface #243,  1          // InterfaceMethod scala/reflect/macros/blackbox/Context.universe:()Lscala/reflect/macros/Universe;
       473: invokevirtual #249                // Method scala/reflect/macros/Universe.internal:()Lscala/reflect/api/Internals$InternalApi;
       476: invokeinterface #253,  1          // InterfaceMethod scala/reflect/api/Internals$InternalApi.reificationSupport:()Lscala/reflect/api/Internals$ReificationSupportApi;
       481: invokeinterface #269,  1          // InterfaceMethod scala/reflect/api/Internals$ReificationSupportApi.SyntacticTermIdent:()Lscala/reflect/api/Internals$ReificationSupportApi$SyntacticTermIdentExtractor;
       486: aload_0
       487: invokevirtual #155                // Method c:()Lscala/reflect/macros/blackbox/Context;
       490: invokeinterface #243,  1          // InterfaceMethod scala/reflect/macros/blackbox/Context.universe:()Lscala/reflect/macros/Universe;
       495: invokevirtual #273                // Method scala/reflect/macros/Universe.TermName:()Lscala/reflect/api/Names$TermNameExtractor;
       498: ldc_w         #316                // String Predef
       501: invokevirtual #278                // Method scala/reflect/api/Names$TermNameExtractor.apply:(Ljava/lang/String;)Lscala/reflect/api/Names$TermNameApi;
       504: iconst_0
       505: invokeinterface #281,  3          // InterfaceMethod scala/reflect/api/Internals$ReificationSupportApi$SyntacticTermIdentExtractor.apply:(Lscala/reflect/api/Names$TermNameApi;Z)Lscala/reflect/api/Trees$IdentApi;
       510: aload_0
       511: invokevirtual #155                // Method c:()Lscala/reflect/macros/blackbox/Context;
       514: invokeinterface #243,  1          // InterfaceMethod scala/reflect/macros/blackbox/Context.universe:()Lscala/reflect/macros/Universe;
       519: invokevirtual #303                // Method scala/reflect/macros/Universe.TypeName:()Lscala/reflect/api/Names$TypeNameExtractor;
       522: ldc_w         #318                // String String
       525: invokevirtual #307                // Method scala/reflect/api/Names$TypeNameExtractor.apply:(Ljava/lang/String;)Lscala/reflect/api/Names$TypeNameApi;
       528: invokeinterface #321,  3          // InterfaceMethod scala/reflect/api/Internals$ReificationSupportApi$SyntacticSelectTypeExtractor.apply:(Lscala/reflect/api/Trees$TreeApi;Lscala/reflect/api/Names$TypeNameApi;)Lscala/reflect/api/Trees$SelectApi;
       533: getstatic     #190                // Field scala/collection/immutable/Nil$.MODULE$:Lscala/collection/immutable/Nil$;
       536: invokespecial #325                // Method scala/collection/immutable/$colon$colon."<init>":(Ljava/lang/Object;Lscala/collection/immutable/List;)V
       539: checkcast     #327                // class scala/collection/immutable/List
       542: invokeinterface #330,  3          // InterfaceMethod scala/reflect/api/Internals$ReificationSupportApi$SyntacticTypeAppliedExtractor.apply:(Lscala/reflect/api/Trees$TreeApi;Lscala/collection/immutable/List;)Lscala/reflect/api/Trees$TreeApi;
       547: new           #292                // class scala/collection/immutable/$colon$colon
       550: dup
       551: aload_0
       552: invokevirtual #155                // Method c:()Lscala/reflect/macros/blackbox/Context;
       555: invokeinterface #243,  1          // InterfaceMethod scala/reflect/macros/blackbox/Context.universe:()Lscala/reflect/macros/Universe;
       560: invokevirtual #249                // Method scala/reflect/macros/Universe.internal:()Lscala/reflect/api/Internals$InternalApi;
       563: invokeinterface #253,  1          // InterfaceMethod scala/reflect/api/Internals$InternalApi.reificationSupport:()Lscala/reflect/api/Internals$ReificationSupportApi;
       568: invokeinterface #314,  1          // InterfaceMethod scala/reflect/api/Internals$ReificationSupportApi.SyntacticSelectType:()Lscala/reflect/api/Internals$ReificationSupportApi$SyntacticSelectTypeExtractor;
       573: aload_0
       574: invokevirtual #155                // Method c:()Lscala/reflect/macros/blackbox/Context;
       577: invokeinterface #243,  1          // InterfaceMethod scala/reflect/macros/blackbox/Context.universe:()Lscala/reflect/macros/Universe;
       582: invokevirtual #249                // Method scala/reflect/macros/Universe.internal:()Lscala/reflect/api/Internals$InternalApi;
       585: invokeinterface #253,  1          // InterfaceMethod scala/reflect/api/Internals$InternalApi.reificationSupport:()Lscala/reflect/api/Internals$ReificationSupportApi;
       590: invokeinterface #269,  1          // InterfaceMethod scala/reflect/api/Internals$ReificationSupportApi.SyntacticTermIdent:()Lscala/reflect/api/Internals$ReificationSupportApi$SyntacticTermIdentExtractor;
       595: aload_0
       596: invokevirtual #155                // Method c:()Lscala/reflect/macros/blackbox/Context;
       599: invokeinterface #243,  1          // InterfaceMethod scala/reflect/macros/blackbox/Context.universe:()Lscala/reflect/macros/Universe;
       604: invokevirtual #273                // Method scala/reflect/macros/Universe.TermName:()Lscala/reflect/api/Names$TermNameExtractor;
       607: ldc_w         #316                // String Predef
       610: invokevirtual #278                // Method scala/reflect/api/Names$TermNameExtractor.apply:(Ljava/lang/String;)Lscala/reflect/api/Names$TermNameApi;
       613: iconst_0
       614: invokeinterface #281,  3          // InterfaceMethod scala/reflect/api/Internals$ReificationSupportApi$SyntacticTermIdentExtractor.apply:(Lscala/reflect/api/Names$TermNameApi;Z)Lscala/reflect/api/Trees$IdentApi;
       619: aload_0
       620: invokevirtual #155                // Method c:()Lscala/reflect/macros/blackbox/Context;
       623: invokeinterface #243,  1          // InterfaceMethod scala/reflect/macros/blackbox/Context.universe:()Lscala/reflect/macros/Universe;
       628: invokevirtual #303                // Method scala/reflect/macros/Universe.TypeName:()Lscala/reflect/api/Names$TypeNameExtractor;
       631: ldc_w         #318                // String String
       634: invokevirtual #307                // Method scala/reflect/api/Names$TypeNameExtractor.apply:(Ljava/lang/String;)Lscala/reflect/api/Names$TypeNameApi;
       637: invokeinterface #321,  3          // InterfaceMethod scala/reflect/api/Internals$ReificationSupportApi$SyntacticSelectTypeExtractor.apply:(Lscala/reflect/api/Trees$TreeApi;Lscala/reflect/api/Names$TypeNameApi;)Lscala/reflect/api/Trees$SelectApi;
       642: getstatic     #190                // Field scala/collection/immutable/Nil$.MODULE$:Lscala/collection/immutable/Nil$;
       645: invokespecial #325                // Method scala/collection/immutable/$colon$colon."<init>":(Ljava/lang/Object;Lscala/collection/immutable/List;)V
       648: invokespecial #325                // Method scala/collection/immutable/$colon$colon."<init>":(Ljava/lang/Object;Lscala/collection/immutable/List;)V
       651: checkcast     #327                // class scala/collection/immutable/List
       654: invokeinterface #330,  3          // InterfaceMethod scala/reflect/api/Internals$ReificationSupportApi$SyntacticTypeAppliedExtractor.apply:(Lscala/reflect/api/Trees$TreeApi;Lscala/collection/immutable/List;)Lscala/reflect/api/Trees$TreeApi;
       659: new           #292                // class scala/collection/immutable/$colon$colon
       662: dup
       663: aload         12
       665: getfield      #334                // Field scala/runtime/ObjectRef.elem:Ljava/lang/Object;
       668: checkcast     #176                // class scala/collection/immutable/Vector
       671: invokevirtual #338                // Method scala/collection/immutable/Vector.toList:()Lscala/collection/immutable/List;
       674: getstatic     #190                // Field scala/collection/immutable/Nil$.MODULE$:Lscala/collection/immutable/Nil$;
       677: invokespecial #325                // Method scala/collection/immutable/$colon$colon."<init>":(Ljava/lang/Object;Lscala/collection/immutable/List;)V
       680: checkcast     #327                // class scala/collection/immutable/List
       683: invokeinterface #339,  3          // InterfaceMethod scala/reflect/api/Internals$ReificationSupportApi$SyntacticAppliedExtractor.apply:(Lscala/reflect/api/Trees$TreeApi;Lscala/collection/immutable/List;)Lscala/reflect/api/Trees$TreeApi;
       688: astore        13
       690: aload_0
       691: invokevirtual #155                // Method c:()Lscala/reflect/macros/blackbox/Context;
       694: aload         13
       696: aload_0
       697: invokevirtual #155                // Method c:()Lscala/reflect/macros/blackbox/Context;
       700: invokeinterface #243,  1          // InterfaceMethod scala/reflect/macros/blackbox/Context.universe:()Lscala/reflect/macros/Universe;
       705: invokevirtual #342                // Method scala/reflect/macros/Universe.WeakTypeTag:()Lscala/reflect/api/TypeTags$WeakTypeTag$;
       708: invokevirtual #346                // Method scala/reflect/api/TypeTags$WeakTypeTag$.Nothing:()Lscala/reflect/api/TypeTags$WeakTypeTag;
       711: invokeinterface #349,  3          // InterfaceMethod scala/reflect/macros/blackbox/Context.Expr:(Lscala/reflect/api/Trees$TreeApi;Lscala/reflect/api/TypeTags$WeakTypeTag;)Lscala/reflect/api/Exprs$Expr;
       716: areturn
      StackMapTable: number_of_entries = 2
        frame_type = 255 /* full_frame */
          offset_delta = 130
          locals = [ class org/sireum/$internal/RC, int, class scala/reflect/api/Exprs$Expr, class scala/reflect/api/Exprs$Expr, class scala/Function2, class scala/reflect/macros/blackbox/Context, class scala/reflect/api/Trees$TreeApi, int, class scala/collection/immutable/Vector, class scala/reflect/macros/blackbox/Context, class scala/reflect/api/Trees$TreeApi, int, class scala/runtime/ObjectRef ]
          stack = []
        frame_type = 11 /* same */
      LineNumberTable:
        line 71: 0
        line 72: 41
        line 73: 82
        line 101: 102
        line 103: 142
        line 105: 690
      LocalVariableTable:
        Start  Length  Slot  Name   Signature
            6      33     5   x$1   Lscala/reflect/macros/blackbox/Context;
           14      25     6   x$2   Lscala/reflect/api/Trees$TreeApi;
           24      15     7   x$3   I
           47      33     9   x$4   Lscala/reflect/macros/blackbox/Context;
           55      25    10   x$5   Lscala/reflect/api/Trees$TreeApi;
           65      15    11   x$6   I
           41     675     4    pf   Lscala/Function2;
           82     634     8   rps   Lscala/collection/immutable/Vector;
          102     614    12  args   Lscala/runtime/ObjectRef;
          690      26    13     r   Lscala/reflect/api/Trees$TreeApi;
            0     717     0  this   Lorg/sireum/$internal/RC;
            0     717     1 isText   Z
            0     717     2 relPaths   Lscala/reflect/api/Exprs$Expr;
            0     717     3     p   Lscala/reflect/api/Exprs$Expr;
    Signature: #150                         // (ZLscala/reflect/api/Exprs$Expr<Lscala/collection/immutable/Vector<Ljava/lang/String;>;>;Lscala/reflect/api/Exprs$Expr<Lscala/Function2<Lscala/collection/immutable/Vector<Ljava/lang/String;>;Ljava/io/File;Ljava/lang/Object;>;>;)Lscala/reflect/api/Exprs$Expr<Lscala/collection/immutable/Map<Lscala/collection/immutable/Vector<Ljava/lang/String;>;Ljava/lang/String;>;>;
    MethodParameters:
      Name                           Flags
      isText                         final
      relPaths                       final
      p                              final

  public scala.reflect.api.Exprs$Expr<scala.collection.immutable.Map<scala.collection.immutable.Vector<java.lang.String>, java.lang.String>> textImpl(scala.reflect.api.Exprs$Expr<scala.collection.immutable.Vector<java.lang.String>>, scala.reflect.api.Exprs$Expr<scala.Function2<scala.collection.immutable.Vector<java.lang.String>, java.io.File, java.lang.Object>>);
    descriptor: (Lscala/reflect/api/Exprs$Expr;Lscala/reflect/api/Exprs$Expr;)Lscala/reflect/api/Exprs$Expr;
    flags: (0x0001) ACC_PUBLIC
    Code:
      stack=4, locals=3, args_size=3
         0: aload_0
         1: iconst_1
         2: aload_1
         3: aload_2
         4: invokevirtual #371                // Method commonImpl:(ZLscala/reflect/api/Exprs$Expr;Lscala/reflect/api/Exprs$Expr;)Lscala/reflect/api/Exprs$Expr;
         7: areturn
      LineNumberTable:
        line 109: 0
      LocalVariableTable:
        Start  Length  Slot  Name   Signature
            0       8     0  this   Lorg/sireum/$internal/RC;
            0       8     1 relPaths   Lscala/reflect/api/Exprs$Expr;
            0       8     2     p   Lscala/reflect/api/Exprs$Expr;
    Signature: #369                         // (Lscala/reflect/api/Exprs$Expr<Lscala/collection/immutable/Vector<Ljava/lang/String;>;>;Lscala/reflect/api/Exprs$Expr<Lscala/Function2<Lscala/collection/immutable/Vector<Ljava/lang/String;>;Ljava/io/File;Ljava/lang/Object;>;>;)Lscala/reflect/api/Exprs$Expr<Lscala/collection/immutable/Map<Lscala/collection/immutable/Vector<Ljava/lang/String;>;Ljava/lang/String;>;>;
    MethodParameters:
      Name                           Flags
      relPaths                       final
      p                              final

  public scala.reflect.api.Exprs$Expr<scala.collection.immutable.Map<scala.collection.immutable.Vector<java.lang.String>, java.lang.String>> base64Impl(scala.reflect.api.Exprs$Expr<scala.collection.immutable.Vector<java.lang.String>>, scala.reflect.api.Exprs$Expr<scala.Function2<scala.collection.immutable.Vector<java.lang.String>, java.io.File, java.lang.Object>>);
    descriptor: (Lscala/reflect/api/Exprs$Expr;Lscala/reflect/api/Exprs$Expr;)Lscala/reflect/api/Exprs$Expr;
    flags: (0x0001) ACC_PUBLIC
    Code:
      stack=4, locals=3, args_size=3
         0: aload_0
         1: iconst_0
         2: aload_1
         3: aload_2
         4: invokevirtual #371                // Method commonImpl:(ZLscala/reflect/api/Exprs$Expr;Lscala/reflect/api/Exprs$Expr;)Lscala/reflect/api/Exprs$Expr;
         7: areturn
      LineNumberTable:
        line 114: 0
      LocalVariableTable:
        Start  Length  Slot  Name   Signature
            0       8     0  this   Lorg/sireum/$internal/RC;
            0       8     1 relPaths   Lscala/reflect/api/Exprs$Expr;
            0       8     2     p   Lscala/reflect/api/Exprs$Expr;
    Signature: #369                         // (Lscala/reflect/api/Exprs$Expr<Lscala/collection/immutable/Vector<Ljava/lang/String;>;>;Lscala/reflect/api/Exprs$Expr<Lscala/Function2<Lscala/collection/immutable/Vector<Ljava/lang/String;>;Ljava/io/File;Ljava/lang/Object;>;>;)Lscala/reflect/api/Exprs$Expr<Lscala/collection/immutable/Map<Lscala/collection/immutable/Vector<Ljava/lang/String;>;Ljava/lang/String;>;>;
    MethodParameters:
      Name                           Flags
      relPaths                       final
      p                              final

  public java.lang.String uriOf(java.io.File);
    descriptor: (Ljava/io/File;)Ljava/lang/String;
    flags: (0x0001) ACC_PUBLIC
    Code:
      stack=1, locals=2, args_size=2
         0: aload_1
         1: invokevirtual #381                // Method java/io/File.toURI:()Ljava/net/URI;
         4: invokevirtual #387                // Method java/net/URI.toASCIIString:()Ljava/lang/String;
         7: areturn
      LineNumberTable:
        line 116: 0
      LocalVariableTable:
        Start  Length  Slot  Name   Signature
            0       8     0  this   Lorg/sireum/$internal/RC;
            0       8     1     f   Ljava/io/File;
    MethodParameters:
      Name                           Flags
      f                              final

  public java.lang.String readText(java.io.File);
    descriptor: (Ljava/io/File;)Ljava/lang/String;
    flags: (0x0001) ACC_PUBLIC
    Code:
      stack=4, locals=2, args_size=2
         0: new           #391                // class java/lang/String
         3: dup
         4: aload_1
         5: invokevirtual #395                // Method java/io/File.toPath:()Ljava/nio/file/Path;
         8: invokestatic  #401                // Method java/nio/file/Files.readAllBytes:(Ljava/nio/file/Path;)[B
        11: getstatic     #407                // Field java/nio/charset/StandardCharsets.UTF_8:Ljava/nio/charset/Charset;
        14: invokespecial #410                // Method java/lang/String."<init>":([BLjava/nio/charset/Charset;)V
        17: areturn
      LineNumberTable:
        line 118: 0
      LocalVariableTable:
        Start  Length  Slot  Name   Signature
            0      18     0  this   Lorg/sireum/$internal/RC;
            0      18     1     f   Ljava/io/File;
    MethodParameters:
      Name                           Flags
      f                              final

  public java.lang.String readBase64(java.io.File);
    descriptor: (Ljava/io/File;)Ljava/lang/String;
    flags: (0x0001) ACC_PUBLIC
    Code:
      stack=2, locals=2, args_size=2
         0: invokestatic  #415                // Method java/util/Base64.getEncoder:()Ljava/util/Base64$Encoder;
         3: aload_1
         4: invokevirtual #395                // Method java/io/File.toPath:()Ljava/nio/file/Path;
         7: invokestatic  #401                // Method java/nio/file/Files.readAllBytes:(Ljava/nio/file/Path;)[B
        10: invokevirtual #419                // Method java/util/Base64$Encoder.encodeToString:([B)Ljava/lang/String;
        13: areturn
      LineNumberTable:
        line 120: 0
      LocalVariableTable:
        Start  Length  Slot  Name   Signature
            0      14     0  this   Lorg/sireum/$internal/RC;
            0      14     1     f   Ljava/io/File;
    MethodParameters:
      Name                           Flags
      f                              final

  public static final scala.reflect.api.Trees$LiteralApi $anonfun$commonImpl$1(org.sireum.$internal.RC, java.lang.String);
    descriptor: (Lorg/sireum/$internal/RC;Ljava/lang/String;)Lscala/reflect/api/Trees$LiteralApi;
    flags: (0x1019) ACC_PUBLIC, ACC_STATIC, ACC_FINAL, ACC_SYNTHETIC
    Code:
      stack=3, locals=2, args_size=2
         0: aload_0
         1: invokevirtual #155                // Method c:()Lscala/reflect/macros/blackbox/Context;
         4: invokeinterface #243,  1          // InterfaceMethod scala/reflect/macros/blackbox/Context.universe:()Lscala/reflect/macros/Universe;
         9: invokevirtual #426                // Method scala/reflect/macros/Universe.Literal:()Lscala/reflect/api/Trees$LiteralExtractor;
        12: aload_0
        13: invokevirtual #155                // Method c:()Lscala/reflect/macros/blackbox/Context;
        16: invokeinterface #243,  1          // InterfaceMethod scala/reflect/macros/blackbox/Context.universe:()Lscala/reflect/macros/Universe;
        21: invokevirtual #430                // Method scala/reflect/macros/Universe.Constant:()Lscala/reflect/api/Constants$ConstantExtractor;
        24: aload_1
        25: invokevirtual #433                // Method scala/reflect/api/Constants$ConstantExtractor.apply:(Ljava/lang/Object;)Lscala/reflect/api/Constants$ConstantApi;
        28: invokevirtual #436                // Method scala/reflect/api/Trees$LiteralExtractor.apply:(Lscala/reflect/api/Constants$ConstantApi;)Lscala/reflect/api/Trees$LiteralApi;
        31: areturn
      LineNumberTable:
        line 85: 0
      LocalVariableTable:
        Start  Length  Slot  Name   Signature
            0      32     0 $this   Lorg/sireum/$internal/RC;
            0      32     1     p   Ljava/lang/String;
    MethodParameters:
      Name                           Flags
      $this                          final synthetic
      p                              final

  public static final scala.reflect.api.Trees$LiteralApi $anonfun$commonImpl$2(org.sireum.$internal.RC, java.lang.String);
    descriptor: (Lorg/sireum/$internal/RC;Ljava/lang/String;)Lscala/reflect/api/Trees$LiteralApi;
    flags: (0x1019) ACC_PUBLIC, ACC_STATIC, ACC_FINAL, ACC_SYNTHETIC
    Code:
      stack=3, locals=2, args_size=2
         0: aload_0
         1: invokevirtual #155                // Method c:()Lscala/reflect/macros/blackbox/Context;
         4: invokeinterface #243,  1          // InterfaceMethod scala/reflect/macros/blackbox/Context.universe:()Lscala/reflect/macros/Universe;
         9: invokevirtual #426                // Method scala/reflect/macros/Universe.Literal:()Lscala/reflect/api/Trees$LiteralExtractor;
        12: aload_0
        13: invokevirtual #155                // Method c:()Lscala/reflect/macros/blackbox/Context;
        16: invokeinterface #243,  1          // InterfaceMethod scala/reflect/macros/blackbox/Context.universe:()Lscala/reflect/macros/Universe;
        21: invokevirtual #430                // Method scala/reflect/macros/Universe.Constant:()Lscala/reflect/api/Constants$ConstantExtractor;
        24: aload_1
        25: invokevirtual #433                // Method scala/reflect/api/Constants$ConstantExtractor.apply:(Ljava/lang/Object;)Lscala/reflect/api/Constants$ConstantApi;
        28: invokevirtual #436                // Method scala/reflect/api/Trees$LiteralExtractor.apply:(Lscala/reflect/api/Constants$ConstantApi;)Lscala/reflect/api/Trees$LiteralApi;
        31: areturn
      LineNumberTable:
        line 87: 0
      LocalVariableTable:
        Start  Length  Slot  Name   Signature
            0      32     0 $this   Lorg/sireum/$internal/RC;
            0      32     1     c   Ljava/lang/String;
    MethodParameters:
      Name                           Flags
      $this                          final synthetic
      c                              final

  public static final scala.reflect.api.Names$TermNameApi $anonfun$commonImpl$3(org.sireum.$internal.RC, int);
    descriptor: (Lorg/sireum/$internal/RC;I)Lscala/reflect/api/Names$TermNameApi;
    flags: (0x1019) ACC_PUBLIC, ACC_STATIC, ACC_FINAL, ACC_SYNTHETIC
    Code:
      stack=4, locals=2, args_size=2
         0: aload_0
         1: invokevirtual #155                // Method c:()Lscala/reflect/macros/blackbox/Context;
         4: invokeinterface #243,  1          // InterfaceMethod scala/reflect/macros/blackbox/Context.universe:()Lscala/reflect/macros/Universe;
         9: invokevirtual #273                // Method scala/reflect/macros/Universe.TermName:()Lscala/reflect/api/Names$TermNameExtractor;
        12: new           #443                // class java/lang/StringBuilder
        15: dup
        16: ldc           #217                // int 1
        18: invokespecial #446                // Method java/lang/StringBuilder."<init>":(I)V
        21: ldc_w         #447                // String f
        24: invokevirtual #451                // Method java/lang/StringBuilder.append:(Ljava/lang/String;)Ljava/lang/StringBuilder;
        27: iload_1
        28: invokevirtual #454                // Method java/lang/StringBuilder.append:(I)Ljava/lang/StringBuilder;
        31: invokevirtual #457                // Method java/lang/StringBuilder.toString:()Ljava/lang/String;
        34: invokevirtual #278                // Method scala/reflect/api/Names$TermNameExtractor.apply:(Ljava/lang/String;)Lscala/reflect/api/Names$TermNameApi;
        37: areturn
      LineNumberTable:
        line 88: 0
      LocalVariableTable:
        Start  Length  Slot  Name   Signature
            0      38     0 $this   Lorg/sireum/$internal/RC;
            0      38     1     n   I
    MethodParameters:
      Name                           Flags
      $this                          final synthetic
      n                              final

  public static final scala.reflect.api.Trees$DefDefApi $anonfun$commonImpl$4(org.sireum.$internal.RC, scala.Tuple2);
    descriptor: (Lorg/sireum/$internal/RC;Lscala/Tuple2;)Lscala/reflect/api/Trees$DefDefApi;
    flags: (0x1019) ACC_PUBLIC, ACC_STATIC, ACC_FINAL, ACC_SYNTHETIC
    Code:
      stack=9, locals=2, args_size=2
         0: aload_0
         1: invokevirtual #155                // Method c:()Lscala/reflect/macros/blackbox/Context;
         4: invokeinterface #243,  1          // InterfaceMethod scala/reflect/macros/blackbox/Context.universe:()Lscala/reflect/macros/Universe;
         9: invokevirtual #249                // Method scala/reflect/macros/Universe.internal:()Lscala/reflect/api/Internals$InternalApi;
        12: invokeinterface #253,  1          // InterfaceMethod scala/reflect/api/Internals$InternalApi.reificationSupport:()Lscala/reflect/api/Internals$ReificationSupportApi;
        17: invokeinterface #463,  1          // InterfaceMethod scala/reflect/api/Internals$ReificationSupportApi.SyntacticDefDef:()Lscala/reflect/api/Internals$ReificationSupportApi$SyntacticDefDefExtractor;
        22: aload_0
        23: invokevirtual #155                // Method c:()Lscala/reflect/macros/blackbox/Context;
        26: invokeinterface #243,  1          // InterfaceMethod scala/reflect/macros/blackbox/Context.universe:()Lscala/reflect/macros/Universe;
        31: invokevirtual #467                // Method scala/reflect/macros/Universe.NoMods:()Lscala/reflect/api/Trees$ModifiersApi;
        34: aload_1
        35: invokevirtual #473                // Method scala/Tuple2._1:()Ljava/lang/Object;
        38: checkcast     #83                 // class scala/reflect/api/Names$TermNameApi
        41: getstatic     #190                // Field scala/collection/immutable/Nil$.MODULE$:Lscala/collection/immutable/Nil$;
        44: getstatic     #190                // Field scala/collection/immutable/Nil$.MODULE$:Lscala/collection/immutable/Nil$;
        47: aload_0
        48: invokevirtual #155                // Method c:()Lscala/reflect/macros/blackbox/Context;
        51: invokeinterface #243,  1          // InterfaceMethod scala/reflect/macros/blackbox/Context.universe:()Lscala/reflect/macros/Universe;
        56: invokevirtual #249                // Method scala/reflect/macros/Universe.internal:()Lscala/reflect/api/Internals$InternalApi;
        59: invokeinterface #253,  1          // InterfaceMethod scala/reflect/api/Internals$InternalApi.reificationSupport:()Lscala/reflect/api/Internals$ReificationSupportApi;
        64: invokeinterface #314,  1          // InterfaceMethod scala/reflect/api/Internals$ReificationSupportApi.SyntacticSelectType:()Lscala/reflect/api/Internals$ReificationSupportApi$SyntacticSelectTypeExtractor;
        69: aload_0
        70: invokevirtual #155                // Method c:()Lscala/reflect/macros/blackbox/Context;
        73: invokeinterface #243,  1          // InterfaceMethod scala/reflect/macros/blackbox/Context.universe:()Lscala/reflect/macros/Universe;
        78: invokevirtual #249                // Method scala/reflect/macros/Universe.internal:()Lscala/reflect/api/Internals$InternalApi;
        81: invokeinterface #253,  1          // InterfaceMethod scala/reflect/api/Internals$InternalApi.reificationSupport:()Lscala/reflect/api/Internals$ReificationSupportApi;
        86: invokeinterface #269,  1          // InterfaceMethod scala/reflect/api/Internals$ReificationSupportApi.SyntacticTermIdent:()Lscala/reflect/api/Internals$ReificationSupportApi$SyntacticTermIdentExtractor;
        91: aload_0
        92: invokevirtual #155                // Method c:()Lscala/reflect/macros/blackbox/Context;
        95: invokeinterface #243,  1          // InterfaceMethod scala/reflect/macros/blackbox/Context.universe:()Lscala/reflect/macros/Universe;
       100: invokevirtual #273                // Method scala/reflect/macros/Universe.TermName:()Lscala/reflect/api/Names$TermNameExtractor;
       103: ldc_w         #316                // String Predef
       106: invokevirtual #278                // Method scala/reflect/api/Names$TermNameExtractor.apply:(Ljava/lang/String;)Lscala/reflect/api/Names$TermNameApi;
       109: iconst_0
       110: invokeinterface #281,  3          // InterfaceMethod scala/reflect/api/Internals$ReificationSupportApi$SyntacticTermIdentExtractor.apply:(Lscala/reflect/api/Names$TermNameApi;Z)Lscala/reflect/api/Trees$IdentApi;
       115: aload_0
       116: invokevirtual #155                // Method c:()Lscala/reflect/macros/blackbox/Context;
       119: invokeinterface #243,  1          // InterfaceMethod scala/reflect/macros/blackbox/Context.universe:()Lscala/reflect/macros/Universe;
       124: invokevirtual #303                // Method scala/reflect/macros/Universe.TypeName:()Lscala/reflect/api/Names$TypeNameExtractor;
       127: ldc_w         #318                // String String
       130: invokevirtual #307                // Method scala/reflect/api/Names$TypeNameExtractor.apply:(Ljava/lang/String;)Lscala/reflect/api/Names$TypeNameApi;
       133: invokeinterface #321,  3          // InterfaceMethod scala/reflect/api/Internals$ReificationSupportApi$SyntacticSelectTypeExtractor.apply:(Lscala/reflect/api/Trees$TreeApi;Lscala/reflect/api/Names$TypeNameApi;)Lscala/reflect/api/Trees$SelectApi;
       138: aload_1
       139: invokevirtual #476                // Method scala/Tuple2._2:()Ljava/lang/Object;
       142: checkcast     #118                // class scala/reflect/api/Trees$TreeApi
       145: invokeinterface #479,  7          // InterfaceMethod scala/reflect/api/Internals$ReificationSupportApi$SyntacticDefDefExtractor.apply:(Lscala/reflect/api/Trees$ModifiersApi;Lscala/reflect/api/Names$TermNameApi;Lscala/collection/immutable/List;Lscala/collection/immutable/List;Lscala/reflect/api/Trees$TreeApi;Lscala/reflect/api/Trees$TreeApi;)Lscala/reflect/api/Trees$DefDefApi;
       150: areturn
      LineNumberTable:
        line 89: 0
      LocalVariableTable:
        Start  Length  Slot  Name   Signature
            0     151     0 $this   Lorg/sireum/$internal/RC;
            0     151     1     p   Lscala/Tuple2;
    MethodParameters:
      Name                           Flags
      $this                          final synthetic
      p                              final

  public static final scala.reflect.api.Trees$TreeApi $anonfun$commonImpl$5(org.sireum.$internal.RC, scala.reflect.api.Names$TermNameApi);
    descriptor: (Lorg/sireum/$internal/RC;Lscala/reflect/api/Names$TermNameApi;)Lscala/reflect/api/Trees$TreeApi;
    flags: (0x1019) ACC_PUBLIC, ACC_STATIC, ACC_FINAL, ACC_SYNTHETIC
    Code:
      stack=2, locals=2, args_size=2
         0: aload_0
         1: invokevirtual #155                // Method c:()Lscala/reflect/macros/blackbox/Context;
         4: invokeinterface #243,  1          // InterfaceMethod scala/reflect/macros/blackbox/Context.universe:()Lscala/reflect/macros/Universe;
         9: invokevirtual #486                // Method scala/reflect/macros/Universe.Ident:()Lscala/reflect/api/Trees$IdentExtractor;
        12: aload_1
        13: checkcast     #78                 // class scala/reflect/api/Names$NameApi
        16: invokevirtual #489                // Method scala/reflect/api/Trees$IdentExtractor.apply:(Lscala/reflect/api/Names$NameApi;)Lscala/reflect/api/Trees$IdentApi;
        19: areturn
      LineNumberTable:
        line 90: 0
      LocalVariableTable:
        Start  Length  Slot  Name   Signature
            0      20     0 $this   Lorg/sireum/$internal/RC;
            0      20     1     f   Lscala/reflect/api/Names$TermNameApi;
    MethodParameters:
      Name                           Flags
      $this                          final synthetic
      f                              final

  public static final scala.reflect.api.Trees$TreeApi $anonfun$commonImpl$6(org.sireum.$internal.RC, scala.reflect.api.Trees$TreeApi, scala.reflect.api.Trees$TreeApi);
    descriptor: (Lorg/sireum/$internal/RC;Lscala/reflect/api/Trees$TreeApi;Lscala/reflect/api/Trees$TreeApi;)Lscala/reflect/api/Trees$TreeApi;
    flags: (0x1019) ACC_PUBLIC, ACC_STATIC, ACC_FINAL, ACC_SYNTHETIC
    Code:
      stack=8, locals=3, args_size=3
         0: aload_0
         1: invokevirtual #155                // Method c:()Lscala/reflect/macros/blackbox/Context;
         4: invokeinterface #243,  1          // InterfaceMethod scala/reflect/macros/blackbox/Context.universe:()Lscala/reflect/macros/Universe;
         9: invokevirtual #249                // Method scala/reflect/macros/Universe.internal:()Lscala/reflect/api/Internals$InternalApi;
        12: invokeinterface #253,  1          // InterfaceMethod scala/reflect/api/Internals$InternalApi.reificationSupport:()Lscala/reflect/api/Internals$ReificationSupportApi;
        17: invokeinterface #257,  1          // InterfaceMethod scala/reflect/api/Internals$ReificationSupportApi.SyntacticApplied:()Lscala/reflect/api/Internals$ReificationSupportApi$SyntacticAppliedExtractor;
        22: aload_0
        23: invokevirtual #155                // Method c:()Lscala/reflect/macros/blackbox/Context;
        26: invokeinterface #243,  1          // InterfaceMethod scala/reflect/macros/blackbox/Context.universe:()Lscala/reflect/macros/Universe;
        31: invokevirtual #249                // Method scala/reflect/macros/Universe.internal:()Lscala/reflect/api/Internals$InternalApi;
        34: invokeinterface #253,  1          // InterfaceMethod scala/reflect/api/Internals$InternalApi.reificationSupport:()Lscala/reflect/api/Internals$ReificationSupportApi;
        39: invokeinterface #265,  1          // InterfaceMethod scala/reflect/api/Internals$ReificationSupportApi.SyntacticSelectTerm:()Lscala/reflect/api/Internals$ReificationSupportApi$SyntacticSelectTermExtractor;
        44: aload_1
        45: aload_0
        46: invokevirtual #155                // Method c:()Lscala/reflect/macros/blackbox/Context;
        49: invokeinterface #243,  1          // InterfaceMethod scala/reflect/macros/blackbox/Context.universe:()Lscala/reflect/macros/Universe;
        54: invokevirtual #273                // Method scala/reflect/macros/Universe.TermName:()Lscala/reflect/api/Names$TermNameExtractor;
        57: ldc_w         #496                // String $plus
        60: invokevirtual #278                // Method scala/reflect/api/Names$TermNameExtractor.apply:(Ljava/lang/String;)Lscala/reflect/api/Names$TermNameApi;
        63: invokeinterface #286,  3          // InterfaceMethod scala/reflect/api/Internals$ReificationSupportApi$SyntacticSelectTermExtractor.apply:(Lscala/reflect/api/Trees$TreeApi;Lscala/reflect/api/Names$TermNameApi;)Lscala/reflect/api/Trees$SelectApi;
        68: new           #292                // class scala/collection/immutable/$colon$colon
        71: dup
        72: new           #292                // class scala/collection/immutable/$colon$colon
        75: dup
        76: aload_2
        77: getstatic     #190                // Field scala/collection/immutable/Nil$.MODULE$:Lscala/collection/immutable/Nil$;
        80: invokespecial #325                // Method scala/collection/immutable/$colon$colon."<init>":(Ljava/lang/Object;Lscala/collection/immutable/List;)V
        83: checkcast     #327                // class scala/collection/immutable/List
        86: getstatic     #190                // Field scala/collection/immutable/Nil$.MODULE$:Lscala/collection/immutable/Nil$;
        89: invokespecial #325                // Method scala/collection/immutable/$colon$colon."<init>":(Ljava/lang/Object;Lscala/collection/immutable/List;)V
        92: checkcast     #327                // class scala/collection/immutable/List
        95: invokeinterface #339,  3          // InterfaceMethod scala/reflect/api/Internals$ReificationSupportApi$SyntacticAppliedExtractor.apply:(Lscala/reflect/api/Trees$TreeApi;Lscala/collection/immutable/List;)Lscala/reflect/api/Trees$TreeApi;
       100: areturn
      LineNumberTable:
        line 90: 0
      LocalVariableTable:
        Start  Length  Slot  Name   Signature
            0     101     0 $this   Lorg/sireum/$internal/RC;
            0     101     1    f1   Lscala/reflect/api/Trees$TreeApi;
            0     101     2    f2   Lscala/reflect/api/Trees$TreeApi;
    MethodParameters:
      Name                           Flags
      $this                          final synthetic
      f1                             final
      f2                             final

  public static final void $anonfun$commonImpl$7(org.sireum.$internal.RC, java.lang.String, scala.Function2, boolean, scala.runtime.ObjectRef, java.io.File);
    descriptor: (Lorg/sireum/$internal/RC;Ljava/lang/String;Lscala/Function2;ZLscala/runtime/ObjectRef;Ljava/io/File;)V
    flags: (0x1019) ACC_PUBLIC, ACC_STATIC, ACC_FINAL, ACC_SYNTHETIC
    Code:
      stack=6, locals=6, args_size=6
         0: aload_0
         1: aload         5
         3: aload_1
         4: aload_2
         5: iload_3
         6: aload         4
         8: invokespecial #507                // Method rec$1:(Ljava/io/File;Ljava/lang/String;Lscala/Function2;ZLscala/runtime/ObjectRef;)V
        11: return
      LineNumberTable:
        line 95: 0
      LocalVariableTable:
        Start  Length  Slot  Name   Signature
            0      12     0 $this   Lorg/sireum/$internal/RC;
            0      12     1 anchorPath$1   Ljava/lang/String;
            0      12     2  pf$1   Lscala/Function2;
            0      12     3 isText$1   Z
            0      12     4 args$1   Lscala/runtime/ObjectRef;
            0      12     5  file   Ljava/io/File;
    MethodParameters:
      Name                           Flags
      $this                          final synthetic
      anchorPath$1                   final
      pf$1                           final
      isText$1                       final
      args$1                         final
      file                           final

  private final void rec$1(java.io.File, java.lang.String, scala.Function2, boolean, scala.runtime.ObjectRef);
    descriptor: (Ljava/io/File;Ljava/lang/String;Lscala/Function2;ZLscala/runtime/ObjectRef;)V
    flags: (0x0012) ACC_PRIVATE, ACC_FINAL
    Code:
      stack=11, locals=14, args_size=6
         0: aload_1
         1: invokevirtual #510                // Method java/io/File.isFile:()Z
         4: ifeq          434
         7: aload_0
         8: aload_1
         9: invokevirtual #512                // Method uriOf:(Ljava/io/File;)Ljava/lang/String;
        12: astore        6
        14: aload         6
        16: aload_2
        17: invokevirtual #516                // Method java/lang/String.startsWith:(Ljava/lang/String;)Z
        20: ifeq          431
        23: getstatic     #521                // Field scala/Predef$.MODULE$:Lscala/Predef$;
        26: getstatic     #526                // Field scala/collection/StringOps$.MODULE$:Lscala/collection/StringOps$;
        29: getstatic     #521                // Field scala/Predef$.MODULE$:Lscala/Predef$;
        32: aload         6
        34: aload_2
        35: invokevirtual #530                // Method java/lang/String.length:()I
        38: invokevirtual #534                // Method java/lang/String.substring:(I)Ljava/lang/String;
        41: invokevirtual #538                // Method scala/Predef$.augmentString:(Ljava/lang/String;)Ljava/lang/String;
        44: bipush        47
        46: invokevirtual #542                // Method scala/collection/StringOps$.split$extension:(Ljava/lang/String;C)[Ljava/lang/String;
        49: checkcast     #544                // class "[Ljava/lang/Object;"
        52: invokevirtual #548                // Method scala/Predef$.wrapRefArray:([Ljava/lang/Object;)Lscala/collection/mutable/ArraySeq$ofRef;
        55: invokevirtual #552                // Method scala/collection/mutable/ArraySeq$ofRef.toVector:()Lscala/collection/immutable/Vector;
        58: astore        7
        60: aload_3
        61: aload         7
        63: aload_1
        64: invokeinterface #555,  3          // InterfaceMethod scala/Function2.apply:(Ljava/lang/Object;Ljava/lang/Object;)Ljava/lang/Object;
        69: invokestatic  #561                // Method scala/runtime/BoxesRunTime.unboxToBoolean:(Ljava/lang/Object;)Z
        72: ifeq          428
        75: aload         7
        77: aload_0
        78: invokedynamic #569,  0            // InvokeDynamic #1:apply:(Lorg/sireum/$internal/RC;)Lscala/Function1;
        83: invokevirtual #573                // Method scala/collection/immutable/Vector.map:(Lscala/Function1;)Ljava/lang/Object;
        86: checkcast     #176                // class scala/collection/immutable/Vector
        89: astore        8
        91: iload         4
        93: ifeq          104
        96: aload_0
        97: aload_1
        98: invokevirtual #575                // Method readText:(Ljava/io/File;)Ljava/lang/String;
       101: goto          109
       104: aload_0
       105: aload_1
       106: invokevirtual #577                // Method readBase64:(Ljava/io/File;)Ljava/lang/String;
       109: astore        9
       111: getstatic     #526                // Field scala/collection/StringOps$.MODULE$:Lscala/collection/StringOps$;
       114: getstatic     #521                // Field scala/Predef$.MODULE$:Lscala/Predef$;
       117: aload         9
       119: invokevirtual #538                // Method scala/Predef$.augmentString:(Ljava/lang/String;)Ljava/lang/String;
       122: sipush        20000
       125: invokevirtual #581                // Method scala/collection/StringOps$.grouped$extension:(Ljava/lang/String;I)Lscala/collection/Iterator;
       128: invokeinterface #587,  1          // InterfaceMethod scala/collection/Iterator.toSeq:()Lscala/collection/immutable/Seq;
       133: aload_0
       134: invokedynamic #591,  0            // InvokeDynamic #2:apply:(Lorg/sireum/$internal/RC;)Lscala/Function1;
       139: invokeinterface #594,  2          // InterfaceMethod scala/collection/immutable/Seq.map:(Lscala/Function1;)Ljava/lang/Object;
       144: checkcast     #593                // class scala/collection/immutable/Seq
       147: astore        10
       149: aload         10
       151: invokeinterface #598,  1          // InterfaceMethod scala/collection/immutable/Seq.indices:()Lscala/collection/immutable/Range;
       156: invokevirtual #601                // Method scala/collection/immutable/Range.toVector:()Lscala/collection/immutable/Vector;
       159: aload_0
       160: invokedynamic #609,  0            // InvokeDynamic #3:apply:(Lorg/sireum/$internal/RC;)Lscala/Function1;
       165: invokevirtual #573                // Method scala/collection/immutable/Vector.map:(Lscala/Function1;)Ljava/lang/Object;
       168: checkcast     #176                // class scala/collection/immutable/Vector
       171: astore        11
       173: aload         11
       175: aload         10
       177: invokevirtual #613                // Method scala/collection/immutable/Vector.zip:(Lscala/collection/IterableOnce;)Ljava/lang/Object;
       180: checkcast     #615                // class scala/collection/StrictOptimizedIterableOps
       183: aload_0
       184: invokedynamic #621,  0            // InvokeDynamic #4:apply:(Lorg/sireum/$internal/RC;)Lscala/Function1;
       189: invokeinterface #622,  2          // InterfaceMethod scala/collection/StrictOptimizedIterableOps.map:(Lscala/Function1;)Ljava/lang/Object;
       194: checkcast     #176                // class scala/collection/immutable/Vector
       197: astore        12
       199: aload_0
       200: invokevirtual #155                // Method c:()Lscala/reflect/macros/blackbox/Context;
       203: invokeinterface #243,  1          // InterfaceMethod scala/reflect/macros/blackbox/Context.universe:()Lscala/reflect/macros/Universe;
       208: invokevirtual #249                // Method scala/reflect/macros/Universe.internal:()Lscala/reflect/api/Internals$InternalApi;
       211: invokeinterface #253,  1          // InterfaceMethod scala/reflect/api/Internals$InternalApi.reificationSupport:()Lscala/reflect/api/Internals$ReificationSupportApi;
       216: invokeinterface #626,  1          // InterfaceMethod scala/reflect/api/Internals$ReificationSupportApi.SyntacticBlock:()Lscala/reflect/api/Internals$ReificationSupportApi$SyntacticBlockExtractor;
       221: aload         12
       223: aload         11
       225: aload_0
       226: invokedynamic #632,  0            // InvokeDynamic #5:apply:(Lorg/sireum/$internal/RC;)Lscala/Function1;
       231: invokevirtual #573                // Method scala/collection/immutable/Vector.map:(Lscala/Function1;)Ljava/lang/Object;
       234: checkcast     #634                // class scala/collection/IterableOnceOps
       237: aload_0
       238: invokedynamic #643,  0            // InvokeDynamic #6:apply:(Lorg/sireum/$internal/RC;)Lscala/Function2;
       243: invokeinterface #647,  2          // InterfaceMethod scala/collection/IterableOnceOps.reduce:(Lscala/Function2;)Ljava/lang/Object;
       248: invokevirtual #650                // Method scala/collection/immutable/Vector.$colon$plus:(Ljava/lang/Object;)Ljava/lang/Object;
       251: checkcast     #634                // class scala/collection/IterableOnceOps
       254: invokeinterface #651,  1          // InterfaceMethod scala/collection/IterableOnceOps.toList:()Lscala/collection/immutable/List;
       259: invokeinterface #654,  2          // InterfaceMethod scala/reflect/api/Internals$ReificationSupportApi$SyntacticBlockExtractor.apply:(Lscala/collection/immutable/List;)Lscala/reflect/api/Trees$TreeApi;
       264: astore        13
       266: aload         5
       268: aload         5
       270: getfield      #334                // Field scala/runtime/ObjectRef.elem:Ljava/lang/Object;
       273: checkcast     #176                // class scala/collection/immutable/Vector
       276: aload_0
       277: invokevirtual #155                // Method c:()Lscala/reflect/macros/blackbox/Context;
       280: invokeinterface #243,  1          // InterfaceMethod scala/reflect/macros/blackbox/Context.universe:()Lscala/reflect/macros/Universe;
       285: invokevirtual #249                // Method scala/reflect/macros/Universe.internal:()Lscala/reflect/api/Internals$InternalApi;
       288: invokeinterface #253,  1          // InterfaceMethod scala/reflect/api/Internals$InternalApi.reificationSupport:()Lscala/reflect/api/Internals$ReificationSupportApi;
       293: invokeinterface #658,  1          // InterfaceMethod scala/reflect/api/Internals$ReificationSupportApi.SyntacticTuple:()Lscala/reflect/api/Internals$ReificationSupportApi$SyntacticTupleExtractor;
       298: new           #292                // class scala/collection/immutable/$colon$colon
       301: dup
       302: aload_0
       303: invokevirtual #155                // Method c:()Lscala/reflect/macros/blackbox/Context;
       306: invokeinterface #243,  1          // InterfaceMethod scala/reflect/macros/blackbox/Context.universe:()Lscala/reflect/macros/Universe;
       311: invokevirtual #249                // Method scala/reflect/macros/Universe.internal:()Lscala/reflect/api/Internals$InternalApi;
       314: invokeinterface #253,  1          // InterfaceMethod scala/reflect/api/Internals$InternalApi.reificationSupport:()Lscala/reflect/api/Internals$ReificationSupportApi;
       319: invokeinterface #257,  1          // InterfaceMethod scala/reflect/api/Internals$ReificationSupportApi.SyntacticApplied:()Lscala/reflect/api/Internals$ReificationSupportApi$SyntacticAppliedExtractor;
       324: aload_0
       325: invokevirtual #155                // Method c:()Lscala/reflect/macros/blackbox/Context;
       328: invokeinterface #243,  1          // InterfaceMethod scala/reflect/macros/blackbox/Context.universe:()Lscala/reflect/macros/Universe;
       333: invokevirtual #249                // Method scala/reflect/macros/Universe.internal:()Lscala/reflect/api/Internals$InternalApi;
       336: invokeinterface #253,  1          // InterfaceMethod scala/reflect/api/Internals$InternalApi.reificationSupport:()Lscala/reflect/api/Internals$ReificationSupportApi;
       341: invokeinterface #269,  1          // InterfaceMethod scala/reflect/api/Internals$ReificationSupportApi.SyntacticTermIdent:()Lscala/reflect/api/Internals$ReificationSupportApi$SyntacticTermIdentExtractor;
       346: aload_0
       347: invokevirtual #155                // Method c:()Lscala/reflect/macros/blackbox/Context;
       350: invokeinterface #243,  1          // InterfaceMethod scala/reflect/macros/blackbox/Context.universe:()Lscala/reflect/macros/Universe;
       355: invokevirtual #273                // Method scala/reflect/macros/Universe.TermName:()Lscala/reflect/api/Names$TermNameExtractor;
       358: ldc_w         #304                // String Vector
       361: invokevirtual #278                // Method scala/reflect/api/Names$TermNameExtractor.apply:(Ljava/lang/String;)Lscala/reflect/api/Names$TermNameApi;
       364: iconst_0
       365: invokeinterface #281,  3          // InterfaceMethod scala/reflect/api/Internals$ReificationSupportApi$SyntacticTermIdentExtractor.apply:(Lscala/reflect/api/Names$TermNameApi;Z)Lscala/reflect/api/Trees$IdentApi;
       370: new           #292                // class scala/collection/immutable/$colon$colon
       373: dup
       374: aload         8
       376: invokevirtual #338                // Method scala/collection/immutable/Vector.toList:()Lscala/collection/immutable/List;
       379: getstatic     #190                // Field scala/collection/immutable/Nil$.MODULE$:Lscala/collection/immutable/Nil$;
       382: invokespecial #325                // Method scala/collection/immutable/$colon$colon."<init>":(Ljava/lang/Object;Lscala/collection/immutable/List;)V
       385: checkcast     #327                // class scala/collection/immutable/List
       388: invokeinterface #339,  3          // InterfaceMethod scala/reflect/api/Internals$ReificationSupportApi$SyntacticAppliedExtractor.apply:(Lscala/reflect/api/Trees$TreeApi;Lscala/collection/immutable/List;)Lscala/reflect/api/Trees$TreeApi;
       393: new           #292                // class scala/collection/immutable/$colon$colon
       396: dup
       397: aload         13
       399: getstatic     #190                // Field scala/collection/immutable/Nil$.MODULE$:Lscala/collection/immutable/Nil$;
       402: invokespecial #325                // Method scala/collection/immutable/$colon$colon."<init>":(Ljava/lang/Object;Lscala/collection/immutable/List;)V
       405: invokespecial #325                // Method scala/collection/immutable/$colon$colon."<init>":(Ljava/lang/Object;Lscala/collection/immutable/List;)V
       408: checkcast     #327                // class scala/collection/immutable/List
       411: invokeinterface #659,  2          // InterfaceMethod scala/reflect/api/Internals$ReificationSupportApi$SyntacticTupleExtractor.apply:(Lscala/collection/immutable/List;)Lscala/reflect/api/Trees$TreeApi;
       416: invokevirtual #650                // Method scala/collection/immutable/Vector.$colon$plus:(Ljava/lang/Object;)Ljava/lang/Object;
       419: checkcast     #176                // class scala/collection/immutable/Vector
       422: putfield      #334                // Field scala/runtime/ObjectRef.elem:Ljava/lang/Object;
       425: goto          428
       428: goto          431
       431: goto          475
       434: aload_1
       435: invokevirtual #662                // Method java/io/File.isDirectory:()Z
       438: ifeq          475
       441: getstatic     #667                // Field scala/collection/ArrayOps$.MODULE$:Lscala/collection/ArrayOps$;
       444: getstatic     #521                // Field scala/Predef$.MODULE$:Lscala/Predef$;
       447: aload_1
       448: invokevirtual #671                // Method java/io/File.listFiles:()[Ljava/io/File;
       451: checkcast     #544                // class "[Ljava/lang/Object;"
       454: invokevirtual #675                // Method scala/Predef$.refArrayOps:([Ljava/lang/Object;)Ljava/lang/Object;
       457: aload_0
       458: aload_2
       459: aload_3
       460: iload         4
       462: aload         5
       464: invokedynamic #685,  0            // InvokeDynamic #7:apply:(Lorg/sireum/$internal/RC;Ljava/lang/String;Lscala/Function2;ZLscala/runtime/ObjectRef;)Lscala/Function1;
       469: invokevirtual #689                // Method scala/collection/ArrayOps$.foreach$extension:(Ljava/lang/Object;Lscala/Function1;)V
       472: goto          475
       475: return
      StackMapTable: number_of_entries = 6
        frame_type = 254 /* append */
          offset_delta = 104
          locals = [ class java/lang/String, class scala/collection/immutable/Vector, class scala/collection/immutable/Vector ]
        frame_type = 68 /* same_locals_1_stack_item */
          stack = [ class java/lang/String ]
        frame_type = 250 /* chop */
          offset_delta = 318
        frame_type = 250 /* chop */
          offset_delta = 2
        frame_type = 250 /* chop */
          offset_delta = 2
        frame_type = 40 /* same */
      LineNumberTable:
        line 80: 0
        line 81: 7
        line 82: 14
        line 83: 23
        line 84: 60
        line 85: 75
        line 86: 91
        line 87: 111
        line 88: 149
        line 89: 173
        line 90: 199
        line 91: 266
        line 84: 428
        line 82: 431
        line 94: 434
        line 95: 444
        line 94: 475
      LocalVariableTable:
        Start  Length  Slot  Name   Signature
           91     334     8 pathSegments   Lscala/collection/immutable/Vector;
          111     314     9 content   Ljava/lang/String;
          149     276    10     s   Lscala/collection/immutable/Seq;
          173     252    11    fs   Lscala/collection/immutable/Vector;
          199     226    12    ms   Lscala/collection/immutable/Vector;
          266     159    13     b   Lscala/reflect/api/Trees$TreeApi;
           60     368     7  path   Lscala/collection/immutable/Vector;
           14     417     6 filePath   Ljava/lang/String;
            0     476     0  this   Lorg/sireum/$internal/RC;
            0     476     1  file   Ljava/io/File;
            0     476     2 anchorPath$1   Ljava/lang/String;
            0     476     3  pf$1   Lscala/Function2;
            0     476     4 isText$1   Z
            0     476     5 args$1   Lscala/runtime/ObjectRef;
    MethodParameters:
      Name                           Flags
      file                           final
      anchorPath$1                   final
      pf$1                           final
      isText$1                       final
      args$1                         final

  private final void it$1(java.lang.String, scala.reflect.api.Exprs$Expr, scala.Function2, boolean, scala.runtime.ObjectRef);
    descriptor: (Ljava/lang/String;Lscala/reflect/api/Exprs$Expr;Lscala/Function2;ZLscala/runtime/ObjectRef;)V
    flags: (0x0012) ACC_PRIVATE, ACC_FINAL
    Code:
      stack=6, locals=8, args_size=6
         0: new           #377                // class java/io/File
         3: dup
         4: new           #377                // class java/io/File
         7: dup
         8: aload_2
         9: invokeinterface #159,  1          // InterfaceMethod scala/reflect/api/Exprs$Expr.tree:()Lscala/reflect/api/Trees$TreeApi;
        14: invokeinterface #704,  1          // InterfaceMethod scala/reflect/api/Trees$TreeApi.pos:()Lscala/reflect/api/Position;
        19: invokeinterface #710,  1          // InterfaceMethod scala/reflect/api/Position.source:()Lscala/reflect/internal/util/SourceFile;
        24: invokevirtual #715                // Method scala/reflect/internal/util/SourceFile.file:()Lscala/reflect/io/AbstractFile;
        27: invokevirtual #720                // Method scala/reflect/io/AbstractFile.canonicalPath:()Ljava/lang/String;
        30: invokespecial #723                // Method java/io/File."<init>":(Ljava/lang/String;)V
        33: invokevirtual #727                // Method java/io/File.getParentFile:()Ljava/io/File;
        36: aload_1
        37: invokespecial #730                // Method java/io/File."<init>":(Ljava/io/File;Ljava/lang/String;)V
        40: astore        6
        42: aload_0
        43: aload         6
        45: invokevirtual #512                // Method uriOf:(Ljava/io/File;)Ljava/lang/String;
        48: astore        7
        50: aload_0
        51: aload         6
        53: aload         7
        55: aload_3
        56: iload         4
        58: aload         5
        60: invokespecial #507                // Method rec$1:(Ljava/io/File;Ljava/lang/String;Lscala/Function2;ZLscala/runtime/ObjectRef;)V
        63: return
      LineNumberTable:
        line 76: 0
        line 77: 42
        line 98: 50
      LocalVariableTable:
        Start  Length  Slot  Name   Signature
           42      21     6 anchorDir   Ljava/io/File;
           50      13     7 anchorPath   Ljava/lang/String;
            0      64     0  this   Lorg/sireum/$internal/RC;
            0      64     1    rp   Ljava/lang/String;
            0      64     2   p$1   Lscala/reflect/api/Exprs$Expr;
            0      64     3  pf$1   Lscala/Function2;
            0      64     4 isText$1   Z
            0      64     5 args$1   Lscala/runtime/ObjectRef;
    MethodParameters:
      Name                           Flags
      rp                             final
      p$1                            final
      pf$1                           final
      isText$1                       final
      args$1                         final

  public static final void $anonfun$commonImpl$8(org.sireum.$internal.RC, scala.reflect.api.Exprs$Expr, scala.Function2, boolean, scala.runtime.ObjectRef, java.lang.String);
    descriptor: (Lorg/sireum/$internal/RC;Lscala/reflect/api/Exprs$Expr;Lscala/Function2;ZLscala/runtime/ObjectRef;Ljava/lang/String;)V
    flags: (0x1019) ACC_PUBLIC, ACC_STATIC, ACC_FINAL, ACC_SYNTHETIC
    Code:
      stack=6, locals=6, args_size=6
         0: aload_0
         1: aload         5
         3: aload_1
         4: aload_2
         5: iload_3
         6: aload         4
         8: invokespecial #237                // Method it$1:(Ljava/lang/String;Lscala/reflect/api/Exprs$Expr;Lscala/Function2;ZLscala/runtime/ObjectRef;)V
        11: return
      LineNumberTable:
        line 101: 0
      LocalVariableTable:
        Start  Length  Slot  Name   Signature
            0      12     0 $this   Lorg/sireum/$internal/RC;
            0      12     1   p$1   Lscala/reflect/api/Exprs$Expr;
            0      12     2  pf$1   Lscala/Function2;
            0      12     3 isText$1   Z
            0      12     4 args$1   Lscala/runtime/ObjectRef;
            0      12     5    rp   Ljava/lang/String;
    MethodParameters:
      Name                           Flags
      $this                          final synthetic
      p$1                            final
      pf$1                           final
      isText$1                       final
      args$1                         final
      rp                             final

  public org.sireum.$internal.RC(scala.reflect.macros.blackbox.Context);
    descriptor: (Lscala/reflect/macros/blackbox/Context;)V
    flags: (0x0001) ACC_PUBLIC
    Code:
      stack=2, locals=2, args_size=2
         0: aload_0
         1: aload_1
         2: putfield      #145                // Field c:Lscala/reflect/macros/blackbox/Context;
         5: aload_0
         6: invokespecial #738                // Method java/lang/Object."<init>":()V
         9: return
      LineNumberTable:
        line 62: 0
      LocalVariableTable:
        Start  Length  Slot  Name   Signature
            0      10     0  this   Lorg/sireum/$internal/RC;
            0      10     1     c   Lscala/reflect/macros/blackbox/Context;
    MethodParameters:
      Name                           Flags
      c                              final

  public static final java.lang.Object $anonfun$commonImpl$8$adapted(org.sireum.$internal.RC, scala.reflect.api.Exprs$Expr, scala.Function2, boolean, scala.runtime.ObjectRef, java.lang.String);
    descriptor: (Lorg/sireum/$internal/RC;Lscala/reflect/api/Exprs$Expr;Lscala/Function2;ZLscala/runtime/ObjectRef;Ljava/lang/String;)Ljava/lang/Object;
    flags: (0x1019) ACC_PUBLIC, ACC_STATIC, ACC_FINAL, ACC_SYNTHETIC
    Code:
      stack=6, locals=6, args_size=6
         0: aload_0
         1: aload_1
         2: aload_2
         3: iload_3
         4: aload         4
         6: aload         5
         8: invokestatic  #740                // Method $anonfun$commonImpl$8:(Lorg/sireum/$internal/RC;Lscala/reflect/api/Exprs$Expr;Lscala/Function2;ZLscala/runtime/ObjectRef;Ljava/lang/String;)V
        11: getstatic     #746                // Field scala/runtime/BoxedUnit.UNIT:Lscala/runtime/BoxedUnit;
        14: areturn
      LineNumberTable:
        line 101: 0
      LocalVariableTable:
        Start  Length  Slot  Name   Signature
            0      15     0 $this   Lorg/sireum/$internal/RC;
            0      15     1   p$1   Lscala/reflect/api/Exprs$Expr;
            0      15     2  pf$1   Lscala/Function2;
            0      15     3 isText$1   Z
            0      15     4 args$1   Lscala/runtime/ObjectRef;
            0      15     5    rp   Ljava/lang/String;
    MethodParameters:
      Name                           Flags
      $this                          final
      p$1                            final
      pf$1                           final
      isText$1                       final
      args$1                         final
      rp                             final

  public static final scala.reflect.api.Names$TermNameApi $anonfun$commonImpl$3$adapted(org.sireum.$internal.RC, java.lang.Object);
    descriptor: (Lorg/sireum/$internal/RC;Ljava/lang/Object;)Lscala/reflect/api/Names$TermNameApi;
    flags: (0x1019) ACC_PUBLIC, ACC_STATIC, ACC_FINAL, ACC_SYNTHETIC
    Code:
      stack=2, locals=2, args_size=2
         0: aload_0
         1: aload_1
         2: invokestatic  #750                // Method scala/runtime/BoxesRunTime.unboxToInt:(Ljava/lang/Object;)I
         5: invokestatic  #752                // Method $anonfun$commonImpl$3:(Lorg/sireum/$internal/RC;I)Lscala/reflect/api/Names$TermNameApi;
         8: areturn
      LineNumberTable:
        line 88: 0
      LocalVariableTable:
        Start  Length  Slot  Name   Signature
            0       9     0 $this   Lorg/sireum/$internal/RC;
            0       9     1     n   Ljava/lang/Object;
    MethodParameters:
      Name                           Flags
      $this                          final
      n                              final

  public static final java.lang.Object $anonfun$commonImpl$7$adapted(org.sireum.$internal.RC, java.lang.String, scala.Function2, boolean, scala.runtime.ObjectRef, java.io.File);
    descriptor: (Lorg/sireum/$internal/RC;Ljava/lang/String;Lscala/Function2;ZLscala/runtime/ObjectRef;Ljava/io/File;)Ljava/lang/Object;
    flags: (0x1019) ACC_PUBLIC, ACC_STATIC, ACC_FINAL, ACC_SYNTHETIC
    Code:
      stack=6, locals=6, args_size=6
         0: aload_0
         1: aload_1
         2: aload_2
         3: iload_3
         4: aload         4
         6: aload         5
         8: invokestatic  #754                // Method $anonfun$commonImpl$7:(Lorg/sireum/$internal/RC;Ljava/lang/String;Lscala/Function2;ZLscala/runtime/ObjectRef;Ljava/io/File;)V
        11: getstatic     #746                // Field scala/runtime/BoxedUnit.UNIT:Lscala/runtime/BoxedUnit;
        14: areturn
      LineNumberTable:
        line 95: 0
      LocalVariableTable:
        Start  Length  Slot  Name   Signature
            0      15     0 $this   Lorg/sireum/$internal/RC;
            0      15     1 anchorPath$1   Ljava/lang/String;
            0      15     2  pf$1   Lscala/Function2;
            0      15     3 isText$1   Z
            0      15     4 args$1   Lscala/runtime/ObjectRef;
            0      15     5  file   Ljava/io/File;
    MethodParameters:
      Name                           Flags
      $this                          final
      anchorPath$1                   final
      pf$1                           final
      isText$1                       final
      args$1                         final
      file                           final

  private static java.lang.Object $deserializeLambda$(java.lang.invoke.SerializedLambda);
    descriptor: (Ljava/lang/invoke/SerializedLambda;)Ljava/lang/Object;
    flags: (0x100a) ACC_PRIVATE, ACC_STATIC, ACC_SYNTHETIC
    Code:
      stack=1, locals=1, args_size=1
         0: aload_0
         1: invokedynamic #766,  0            // InvokeDynamic #8:lambdaDeserialize:(Ljava/lang/invoke/SerializedLambda;)Ljava/lang/Object;
         6: areturn
}
InnerClasses:
  public static final #13= #10 of #12;    // Lookup=class java/lang/invoke/MethodHandles$Lookup of class java/lang/invoke/MethodHandles
  public static #18= #15 of #17;          // Encoder=class java/util/Base64$Encoder of class java/util/Base64
  public static #23= #20 of #22;          // Node=class org/sireum/$internal/Trie$Node of class org/sireum/$internal/Trie
  public static final #28= #25 of #27;    // ofRef=class scala/collection/mutable/ArraySeq$ofRef of class scala/collection/mutable/ArraySeq
  public abstract #33= #30 of #32;        // ConstantApi=class scala/reflect/api/Constants$ConstantApi of class scala/reflect/api/Constants
  public abstract #36= #35 of #32;        // ConstantExtractor=class scala/reflect/api/Constants$ConstantExtractor of class scala/reflect/api/Constants
  public #41= #38 of #40;                 // Expr=class scala/reflect/api/Exprs$Expr of class scala/reflect/api/Exprs
  public #46= #43 of #45;                 // InternalApi=class scala/reflect/api/Internals$InternalApi of class scala/reflect/api/Internals
  public #49= #48 of #45;                 // ReificationSupportApi=class scala/reflect/api/Internals$ReificationSupportApi of class scala/reflect/api/Internals
  public #52= #51 of #48;                 // SyntacticAppliedExtractor=class scala/reflect/api/Internals$ReificationSupportApi$SyntacticAppliedExtractor of class scala/reflect/api/Internals$ReificationSupportApi
  public #55= #54 of #48;                 // SyntacticBlockExtractor=class scala/reflect/api/Internals$ReificationSupportApi$SyntacticBlockExtractor of class scala/reflect/api/Internals$ReificationSupportApi
  public #58= #57 of #48;                 // SyntacticDefDefExtractor=class scala/reflect/api/Internals$ReificationSupportApi$SyntacticDefDefExtractor of class scala/reflect/api/Internals$ReificationSupportApi
  public #61= #60 of #48;                 // SyntacticSelectTermExtractor=class scala/reflect/api/Internals$ReificationSupportApi$SyntacticSelectTermExtractor of class scala/reflect/api/Internals$ReificationSupportApi
  public #64= #63 of #48;                 // SyntacticSelectTypeExtractor=class scala/reflect/api/Internals$ReificationSupportApi$SyntacticSelectTypeExtractor of class scala/reflect/api/Internals$ReificationSupportApi
  public #67= #66 of #48;                 // SyntacticTermIdentExtractor=class scala/reflect/api/Internals$ReificationSupportApi$SyntacticTermIdentExtractor of class scala/reflect/api/Internals$ReificationSupportApi
  public #70= #69 of #48;                 // SyntacticTupleExtractor=class scala/reflect/api/Internals$ReificationSupportApi$SyntacticTupleExtractor of class scala/reflect/api/Internals$ReificationSupportApi
  public #73= #72 of #48;                 // SyntacticTypeAppliedExtractor=class scala/reflect/api/Internals$ReificationSupportApi$SyntacticTypeAppliedExtractor of class scala/reflect/api/Internals$ReificationSupportApi
  public #76= #75 of #48;                 // SyntacticTypeIdentExtractor=class scala/reflect/api/Internals$ReificationSupportApi$SyntacticTypeIdentExtractor of class scala/reflect/api/Internals$ReificationSupportApi
  public abstract #81= #78 of #80;        // NameApi=class scala/reflect/api/Names$NameApi of class scala/reflect/api/Names
  public #84= #83 of #80;                 // TermNameApi=class scala/reflect/api/Names$TermNameApi of class scala/reflect/api/Names
  public abstract #87= #86 of #80;        // TermNameExtractor=class scala/reflect/api/Names$TermNameExtractor of class scala/reflect/api/Names
  public #90= #89 of #80;                 // TypeNameApi=class scala/reflect/api/Names$TypeNameApi of class scala/reflect/api/Names
  public abstract #93= #92 of #80;        // TypeNameExtractor=class scala/reflect/api/Names$TypeNameExtractor of class scala/reflect/api/Names
  public #98= #95 of #97;                 // DefDefApi=class scala/reflect/api/Trees$DefDefApi of class scala/reflect/api/Trees
  public #101= #100 of #97;               // IdentApi=class scala/reflect/api/Trees$IdentApi of class scala/reflect/api/Trees
  public abstract #104= #103 of #97;      // IdentExtractor=class scala/reflect/api/Trees$IdentExtractor of class scala/reflect/api/Trees
  public #107= #106 of #97;               // LiteralApi=class scala/reflect/api/Trees$LiteralApi of class scala/reflect/api/Trees
  public abstract #110= #109 of #97;      // LiteralExtractor=class scala/reflect/api/Trees$LiteralExtractor of class scala/reflect/api/Trees
  public abstract #113= #112 of #97;      // ModifiersApi=class scala/reflect/api/Trees$ModifiersApi of class scala/reflect/api/Trees
  public #116= #115 of #97;               // SelectApi=class scala/reflect/api/Trees$SelectApi of class scala/reflect/api/Trees
  public #119= #118 of #97;               // TreeApi=class scala/reflect/api/Trees$TreeApi of class scala/reflect/api/Trees
  public #124= #121 of #123;              // WeakTypeTag=class scala/reflect/api/TypeTags$WeakTypeTag of class scala/reflect/api/TypeTags
  public #127= #126 of #123;              // WeakTypeTag$=class scala/reflect/api/TypeTags$WeakTypeTag$ of class scala/reflect/api/TypeTags
SourceFile: "RC.scala"
RuntimeVisibleAnnotations:
  0: #6(#7=s#8)
    scala.reflect.ScalaSignature(
      bytes="\u0006\u0005\u0005mx!\u0002\t\u0012\u0011\u0003Ab!\u0002\u000e\u0012\u0011\u0003Y\u0002\"\u0002\u0012\u0002\t\u0003\u0019\u0003\"\u0002\u0013\u0002\t\u0003)\u0003BB%\u0002\u0005\u0013\u0005!\n\u0003\u0005\u0002X\u0005\u0011I\u0011AA-\r\u0015Q\u0012\u0003AAP\u0011)\t\tK\u0002BC\u0002\u0013\u0005\u00111\u0015\u0005\u000b\u0003c3!\u0011!Q\u0001\n\u0005\u0015\u0006B\u0002\u0012\u0007\t\u0003\t\u0019\fC\u0004\u0002:\u001a!\t!a/\t\u000f\u0005=b\u0001\"\u0001\u0002X\"9\u0011\u0011\u0012\u0004\u0005\u0002\u0005}\u0007bBAt\r\u0011\u0005\u0011\u0011\u001e\u0005\b\u0003_4A\u0011AAy\u0011\u001d\t)P\u0002C\u0001\u0003o\f!AU\"\u000b\u0005I\u0019\u0012!\u0003\u0013j]R,\'O\\1m\u0015\t!R#\u0001\u0004tSJ,W/\u001c\u0006\u0002-\u0005\u0019qN]4\u0004\u0001A\u0011\u0011$A\u0007\u0002#\t\u0011!kQ\n\u0003\u0003q\u0001\"!\b\u0011\u000e\u0003yQ\u0011aH\u0001\u0006g\u000e\fG.Y\u0005\u0003Cy\u0011a!\u00118z%\u00164\u0017A\u0002\u001fj]&$h\bF\u0001\u0019\u0003\u0019!x\u000e\u0016:jKR\u0011a\u0005\u000f\t\u0005O)jSF\u0004\u0002\u001aQ%\u0011\u0011&E\u0001\u0005)JLW-\u0003\u0002,Y\t!aj\u001c3f\u0015\tI\u0013\u0003\u0005\u0002/k9\u0011qf\r\t\u0003ayi\u0011!\r\u0006\u0003e]\ta\u0001\u0010:p_Rt\u0014B\u0001\u001b\u001f\u0003\u0019\u0001&/\u001a3fM&\u0011ag\u000e\u0002\u0007\'R\u0014\u0018N\\4\u000b\u0005Qr\u0002\"B\u001d\u0004\u0001\u0004Q\u0014!A7\u0011\tmr\u0004)L\u0007\u0002y)\u0011QHH\u0001\u000bG>dG.Z2uS>t\u0017BA =\u0005\ri\u0015\r\u001d\t\u0004\u0003\u001akcB\u0001\"E\u001d\t\u00014)C\u0001 \u0013\t)e$A\u0004qC\u000e\\\u0017mZ3\n\u0005\u001dC%A\u0002,fGR|\'O\u0003\u0002F=\u0005!A/\u001a=u)\tYe\f\u0006\u0002M\u001dB!a&\u0014!.\u0013\tyt\u0007C\u0003P\t\u0001\u0007\u0001+A\u0001q!\u0015i\u0012\u000bQ*\\\u0013\t\u0011fDA\u0005Gk:\u001cG/[8oeA\u0011A+W\u0007\u0002+*\u0011akV\u0001\u0003S>T\u0011\u0001W\u0001\u0005U\u00064\u0018-\u0003\u0002[+\n!a)\u001b7f!\tiB,\u0003\u0002^=\t9!i\\8mK\u0006t\u0007\"B0\u0005\u0001\u0004\u0001\u0015\u0001\u0003:fYB\u000bG\u000f[:)\u0007\u0011\t7\u000e\u0005\u0002cS6\t1M\u0003\u0002eK\u0006A\u0011N\u001c;fe:\fGN\u0003\u0002gO\u00061Q.Y2s_NT!\u0001\u001b\u0010\u0002\u000fI,g\r\\3di&\u0011!n\u0019\u0002\n[\u0006\u001c\'o\\%na2\fTb\b7n_b\f\t!!\u0004\u0002 \u0005E2\u0002A\u0019\u0005I1<b.A\u0003nC\u000e\u0014x.\r\u0003\u0017YB$\u0018gA\u0013re>\t!/I\u0001t\u0003-i\u0017m\u0019:p\u000b:<\u0017N\\32\u0007\u0015*hoD\u0001wC\u00059\u0018!\n<8]A\u0002\u0003&[7qY\u0016lWM\u001c;fI\u0002Jg\u000eI*dC2\f\u0007E\r\u00182c9\u0002T&\u0014\u001d*c\u00111B._?2\u0007\u0015R8pD\u0001|C\u0005a\u0018\u0001C5t\u0005VtG\r\\32\u0007\u0015rxpD\u0001\u00003\u0005\t\u0011G\u0002\fm\u0003\u0007\tY!M\u0003&\u0003\u000b\t9a\u0004\u0002\u0002\b\u0005\u0012\u0011\u0011B\u0001\u000bSN\u0014E.Y2lE>D\u0018gA\u0013\u007f\u007fF2a\u0003\\A\b\u0003/\tT!JA\t\u0003\'y!!a\u0005\"\u0005\u0005U\u0011!C2mCN\u001ch*Y7fc\u0015)\u0013\u0011DA\u000e\u001f\t\tY\"\t\u0002\u0002\u001e\u00059rN]4/g&\u0014X-^7/I%tG/\u001a:oC2t#kQ\u0019\u0007-1\f\t#!\u000b2\u000b\u0015\n\u0019#!\n\u0010\u0005\u0005\u0015\u0012EAA\u0014\u0003)iW\r\u001e5pI:\u000bW.Z\u0019\u0006K\u0005-\u0012QF\b\u0003\u0003[\t#!a\f\u0002\u0011Q,\u0007\u0010^%na2\fdA\u00067\u00024\u0005m\u0012\'B\u0013\u00026\u0005]rBAA\u001cC\t\tI$A\u0005tS\u001et\u0017\r^;sKFBq\u0004\\A\u001f\u0003\u000f\n\t&\r\u0004%Y\u0006}\u0012\u0011I\u0005\u0005\u0003\u0003\n\u0019%\u0001\u0003MSN$(bAA#y\u0005I\u0011.\\7vi\u0006\u0014G.Z\u0019\u0007?1\fI%a\u00132\r\u0011b\u0017qHA!c\u0015)\u0013QJA(\u001f\t\ty%H\u0001\u007fd\u0019yB.a\u0015\u0002VE2A\u0005\\A \u0003\u0003\nT!JA\'\u0003\u001f\naAY1tKZ\"D\u0003BA.\u0003?\"2\u0001TA/\u0011\u0015yU\u00011\u0001Q\u0011\u0015yV\u00011\u0001AQ\u0011)\u0011-a\u00192!}a\u0017QMA4\u0003[\n\u0019(!\u001f\u0002\u0000\u0005-\u0015\u0007\u0002\u0013m/9\fdA\u00067\u0002j\u0005-\u0014gA\u0013reF\u001aQ%\u001e<2\rYa\u0017qNA9c\r)#p_\u0019\u0004Ky|\u0018G\u0002\fm\u0003k\n9(M\u0003&\u0003\u000b\t9!M\u0002&}~\fdA\u00067\u0002|\u0005u\u0014\'B\u0013\u0002\u0012\u0005M\u0011\'B\u0013\u0002\u001a\u0005m\u0011G\u0002\fm\u0003\u0003\u000b\u0019)M\u0003&\u0003G\t)#M\u0003&\u0003\u000b\u000b9i\u0004\u0002\u0002\b\u0006\u0012\u0011\u0011R\u0001\u000bE\u0006\u001cXM\u000e\u001bJ[Bd\u0017G\u0002\fm\u0003\u001b\u000by)M\u0003&\u0003k\t9$\r\u0005 Y\u0006E\u00151SAMc\u0019!C.a\u0010\u0002BE2q\u0004\\AK\u0003/\u000bd\u0001\n7\u0002@\u0005\u0005\u0013\'B\u0013\u0002N\u0005=\u0013GB\u0010m\u00037\u000bi*\r\u0004%Y\u0006}\u0012\u0011I\u0019\u0006K\u00055\u0013qJ\n\u0003\rq\t\u0011aY\u000b\u0003\u0003K\u0003B!a*\u0002.6\u0011\u0011\u0011\u0016\u0006\u0004\u0003W+\u0017\u0001\u00032mC\u000e\\\'m\u001c=\n\t\u0005=\u0016\u0011\u0016\u0002\b\u0007>tG/\u001a=u\u0003\t\u0019\u0007\u0005\u0006\u0003\u00026\u0006]\u0006CA\r\u0007\u0011\u001d\t\t+\u0003a\u0001\u0003K\u000b!bY8n[>t\u0017*\u001c9m)!\ti,a3\u0002P\u0006M\u0007#BA`\u0003\u0007debAAa\u000f5\ta!\u0003\u0003\u0002F\u0006\u001d\'\u0001B#yaJL1!!3f\u0005\u001d\tE.[1tKNDa!!4\u000b\u0001\u0004Y\u0016AB5t)\u0016DH\u000f\u0003\u0004`\u0015\u0001\u0007\u0011\u0011\u001b\t\u0006\u0003\u007f\u000b\u0019\r\u0011\u0005\u0007\u001f*\u0001\r!!6\u0011\u000b\u0005}\u00161\u0019)\u0015\t\u0005e\u0017Q\u001c\u000b\u0005\u0003{\u000bY\u000e\u0003\u0004P\u0017\u0001\u0007\u0011Q\u001b\u0005\u0007?.\u0001\r!!5\u0015\t\u0005\u0005\u0018Q\u001d\u000b\u0005\u0003{\u000b\u0019\u000f\u0003\u0004P\u0019\u0001\u0007\u0011Q\u001b\u0005\u0007?2\u0001\r!!5\u0002\u000bU\u0014\u0018n\u00144\u0015\u00075\nY\u000f\u0003\u0004\u0002n6\u0001\raU\u0001\u0002M\u0006A!/Z1e)\u0016DH\u000fF\u0002.\u0003gDa!!<\u000f\u0001\u0004\u0019\u0016A\u0003:fC\u0012\u0014\u0015m]37iQ\u0019Q&!?\t\r\u00055x\u00021\u0001T\u0001"
    )
BootstrapMethods:
  0: #224 REF_invokeStatic java/lang/invoke/LambdaMetafactory.altMetafactory:(Ljava/lang/invoke/MethodHandles$Lookup;Ljava/lang/String;Ljava/lang/invoke/MethodType;[Ljava/lang/Object;)Ljava/lang/invoke/CallSite;
    Method arguments:
      #208 (Ljava/lang/Object;)Ljava/lang/Object;
      #213 REF_invokeStatic org/sireum/$internal/RC.$anonfun$commonImpl$8$adapted:(Lorg/sireum/$internal/RC;Lscala/reflect/api/Exprs$Expr;Lscala/Function2;ZLscala/runtime/ObjectRef;Ljava/lang/String;)Ljava/lang/Object;
      #215 (Ljava/lang/String;)Ljava/lang/Object;
      #216 5
      #217 1
      #215 (Ljava/lang/String;)Ljava/lang/Object;
  1: #224 REF_invokeStatic java/lang/invoke/LambdaMetafactory.altMetafactory:(Ljava/lang/invoke/MethodHandles$Lookup;Ljava/lang/String;Ljava/lang/invoke/MethodType;[Ljava/lang/Object;)Ljava/lang/invoke/CallSite;
    Method arguments:
      #208 (Ljava/lang/Object;)Ljava/lang/Object;
      #564 REF_invokeStatic org/sireum/$internal/RC.$anonfun$commonImpl$1:(Lorg/sireum/$internal/RC;Ljava/lang/String;)Lscala/reflect/api/Trees$LiteralApi;
      #566 (Ljava/lang/String;)Lscala/reflect/api/Trees$LiteralApi;
      #216 5
      #217 1
      #566 (Ljava/lang/String;)Lscala/reflect/api/Trees$LiteralApi;
  2: #224 REF_invokeStatic java/lang/invoke/LambdaMetafactory.altMetafactory:(Ljava/lang/invoke/MethodHandles$Lookup;Ljava/lang/String;Ljava/lang/invoke/MethodType;[Ljava/lang/Object;)Ljava/lang/invoke/CallSite;
    Method arguments:
      #208 (Ljava/lang/Object;)Ljava/lang/Object;
      #590 REF_invokeStatic org/sireum/$internal/RC.$anonfun$commonImpl$2:(Lorg/sireum/$internal/RC;Ljava/lang/String;)Lscala/reflect/api/Trees$LiteralApi;
      #566 (Ljava/lang/String;)Lscala/reflect/api/Trees$LiteralApi;
      #216 5
      #217 1
      #566 (Ljava/lang/String;)Lscala/reflect/api/Trees$LiteralApi;
  3: #224 REF_invokeStatic java/lang/invoke/LambdaMetafactory.altMetafactory:(Ljava/lang/invoke/MethodHandles$Lookup;Ljava/lang/String;Ljava/lang/invoke/MethodType;[Ljava/lang/Object;)Ljava/lang/invoke/CallSite;
    Method arguments:
      #208 (Ljava/lang/Object;)Ljava/lang/Object;
      #606 REF_invokeStatic org/sireum/$internal/RC.$anonfun$commonImpl$3$adapted:(Lorg/sireum/$internal/RC;Ljava/lang/Object;)Lscala/reflect/api/Names$TermNameApi;
      #608 (Ljava/lang/Object;)Lscala/reflect/api/Names$TermNameApi;
      #216 5
      #217 1
      #608 (Ljava/lang/Object;)Lscala/reflect/api/Names$TermNameApi;
  4: #224 REF_invokeStatic java/lang/invoke/LambdaMetafactory.altMetafactory:(Ljava/lang/invoke/MethodHandles$Lookup;Ljava/lang/String;Ljava/lang/invoke/MethodType;[Ljava/lang/Object;)Ljava/lang/invoke/CallSite;
    Method arguments:
      #208 (Ljava/lang/Object;)Ljava/lang/Object;
      #618 REF_invokeStatic org/sireum/$internal/RC.$anonfun$commonImpl$4:(Lorg/sireum/$internal/RC;Lscala/Tuple2;)Lscala/reflect/api/Trees$DefDefApi;
      #620 (Lscala/Tuple2;)Lscala/reflect/api/Trees$DefDefApi;
      #216 5
      #217 1
      #620 (Lscala/Tuple2;)Lscala/reflect/api/Trees$DefDefApi;
  5: #224 REF_invokeStatic java/lang/invoke/LambdaMetafactory.altMetafactory:(Ljava/lang/invoke/MethodHandles$Lookup;Ljava/lang/String;Ljava/lang/invoke/MethodType;[Ljava/lang/Object;)Ljava/lang/invoke/CallSite;
    Method arguments:
      #208 (Ljava/lang/Object;)Ljava/lang/Object;
      #629 REF_invokeStatic org/sireum/$internal/RC.$anonfun$commonImpl$5:(Lorg/sireum/$internal/RC;Lscala/reflect/api/Names$TermNameApi;)Lscala/reflect/api/Trees$TreeApi;
      #631 (Lscala/reflect/api/Names$TermNameApi;)Lscala/reflect/api/Trees$TreeApi;
      #216 5
      #217 1
      #631 (Lscala/reflect/api/Names$TermNameApi;)Lscala/reflect/api/Trees$TreeApi;
  6: #224 REF_invokeStatic java/lang/invoke/LambdaMetafactory.altMetafactory:(Ljava/lang/invoke/MethodHandles$Lookup;Ljava/lang/String;Ljava/lang/invoke/MethodType;[Ljava/lang/Object;)Ljava/lang/invoke/CallSite;
    Method arguments:
      #635 (Ljava/lang/Object;Ljava/lang/Object;)Ljava/lang/Object;
      #638 REF_invokeStatic org/sireum/$internal/RC.$anonfun$commonImpl$6:(Lorg/sireum/$internal/RC;Lscala/reflect/api/Trees$TreeApi;Lscala/reflect/api/Trees$TreeApi;)Lscala/reflect/api/Trees$TreeApi;
      #640 (Lscala/reflect/api/Trees$TreeApi;Lscala/reflect/api/Trees$TreeApi;)Lscala/reflect/api/Trees$TreeApi;
      #216 5
      #217 1
      #640 (Lscala/reflect/api/Trees$TreeApi;Lscala/reflect/api/Trees$TreeApi;)Lscala/reflect/api/Trees$TreeApi;
  7: #224 REF_invokeStatic java/lang/invoke/LambdaMetafactory.altMetafactory:(Ljava/lang/invoke/MethodHandles$Lookup;Ljava/lang/String;Ljava/lang/invoke/MethodType;[Ljava/lang/Object;)Ljava/lang/invoke/CallSite;
    Method arguments:
      #208 (Ljava/lang/Object;)Ljava/lang/Object;
      #680 REF_invokeStatic org/sireum/$internal/RC.$anonfun$commonImpl$7$adapted:(Lorg/sireum/$internal/RC;Ljava/lang/String;Lscala/Function2;ZLscala/runtime/ObjectRef;Ljava/io/File;)Ljava/lang/Object;
      #682 (Ljava/io/File;)Ljava/lang/Object;
      #216 5
      #217 1
      #682 (Ljava/io/File;)Ljava/lang/Object;
  8: #763 REF_invokeStatic scala/runtime/LambdaDeserialize.bootstrap:(Ljava/lang/invoke/MethodHandles$Lookup;Ljava/lang/String;Ljava/lang/invoke/MethodType;[Ljava/lang/invoke/MethodHandle;)Ljava/lang/invoke/CallSite;
    Method arguments:
      #564 REF_invokeStatic org/sireum/$internal/RC.$anonfun$commonImpl$1:(Lorg/sireum/$internal/RC;Ljava/lang/String;)Lscala/reflect/api/Trees$LiteralApi;
      #590 REF_invokeStatic org/sireum/$internal/RC.$anonfun$commonImpl$2:(Lorg/sireum/$internal/RC;Ljava/lang/String;)Lscala/reflect/api/Trees$LiteralApi;
      #606 REF_invokeStatic org/sireum/$internal/RC.$anonfun$commonImpl$3$adapted:(Lorg/sireum/$internal/RC;Ljava/lang/Object;)Lscala/reflect/api/Names$TermNameApi;
      #618 REF_invokeStatic org/sireum/$internal/RC.$anonfun$commonImpl$4:(Lorg/sireum/$internal/RC;Lscala/Tuple2;)Lscala/reflect/api/Trees$DefDefApi;
      #629 REF_invokeStatic org/sireum/$internal/RC.$anonfun$commonImpl$5:(Lorg/sireum/$internal/RC;Lscala/reflect/api/Names$TermNameApi;)Lscala/reflect/api/Trees$TreeApi;
      #638 REF_invokeStatic org/sireum/$internal/RC.$anonfun$commonImpl$6:(Lorg/sireum/$internal/RC;Lscala/reflect/api/Trees$TreeApi;Lscala/reflect/api/Trees$TreeApi;)Lscala/reflect/api/Trees$TreeApi;
      #680 REF_invokeStatic org/sireum/$internal/RC.$anonfun$commonImpl$7$adapted:(Lorg/sireum/$internal/RC;Ljava/lang/String;Lscala/Function2;ZLscala/runtime/ObjectRef;Ljava/io/File;)Ljava/lang/Object;
      #213 REF_invokeStatic org/sireum/$internal/RC.$anonfun$commonImpl$8$adapted:(Lorg/sireum/$internal/RC;Lscala/reflect/api/Exprs$Expr;Lscala/Function2;ZLscala/runtime/ObjectRef;Ljava/lang/String;)Ljava/lang/Object;
  ScalaInlineInfo: length = 0x6D (unknown attribute)
   01 00 00 15 01 A4 01 A5 01 01 B6 01 A5 01 01 B7
   01 B8 01 02 5A 02 5B 01 01 CA 01 CB 01 01 E1 01
   E2 01 01 EB 01 EC 01 01 F1 01 F2 01 02 A4 02 A5
   01 02 DD 02 DE 01 00 D1 00 D2 01 01 42 02 DF 00
   01 74 01 70 00 00 80 00 8F 00 00 94 00 95 00 00
   EA 00 EB 01 01 9B 01 76 00 01 85 01 76 00 01 F8
   01 F9 01 01 6F 01 70 00 01 75 01 76 00
  ScalaSig: length = 0x3 (unknown attribute)
   05 02 00
