Classfile /Users/mw/Projects/slang-braindump/.jar/jar8/assemble/slang-braindump/assemble/content/org/sireum/project/Module$.class
  Last modified May 29, 2022; size 4244 bytes
  SHA-256 checksum e211ab73c60c5ca6b662f6c9342104f3225cc231a6925c82a6dab2e2fe25a82c
  Compiled from "Project.scala"
public final class org.sireum.project.Module$
  minor version: 0
  major version: 52
  flags: (0x0031) ACC_PUBLIC, ACC_FINAL, ACC_SUPER
  this_class: #2                          // org/sireum/project/Module$
  super_class: #4                         // java/lang/Object
  interfaces: 0, fields: 2, methods: 5, attributes: 4
Constant pool:
    #1 = Utf8               org/sireum/project/Module$
    #2 = Class              #1            // org/sireum/project/Module$
    #3 = Utf8               java/lang/Object
    #4 = Class              #3            // java/lang/Object
    #5 = Utf8               Project.scala
    #6 = Utf8               org/sireum/$internal/PackageTrait$ISZ$
    #7 = Class              #6            // org/sireum/$internal/PackageTrait$ISZ$
    #8 = Utf8               org/sireum/$internal/PackageTrait
    #9 = Class              #8            // org/sireum/$internal/PackageTrait
   #10 = Utf8               ISZ$
   #11 = Utf8               org/sireum/project/Target$Js$
   #12 = Class              #11           // org/sireum/project/Target$Js$
   #13 = Utf8               org/sireum/project/Target
   #14 = Class              #13           // org/sireum/project/Target
   #15 = Utf8               Js$
   #16 = Utf8               org/sireum/project/Target$Jvm$
   #17 = Class              #16           // org/sireum/project/Target$Jvm$
   #18 = Utf8               Jvm$
   #19 = Utf8               org/sireum/project/Target$Type
   #20 = Class              #19           // org/sireum/project/Target$Type
   #21 = Utf8               Type
   #22 = Utf8               MODULE$
   #23 = Utf8               Lorg/sireum/project/Module$;
   #24 = Utf8               allTargets
   #25 = Utf8               Lorg/sireum/IS;
   #26 = Utf8               Lorg/sireum/IS<Lorg/sireum/Z;Lorg/sireum/project/Target$Type;>;
   #27 = Utf8               <clinit>
   #28 = Utf8               ()V
   #29 = Utf8               <init>
   #30 = NameAndType        #29:#28       // "<init>":()V
   #31 = Methodref          #2.#30        // org/sireum/project/Module$."<init>":()V
   #32 = NameAndType        #22:#23       // MODULE$:Lorg/sireum/project/Module$;
   #33 = Fieldref           #2.#32        // org/sireum/project/Module$.MODULE$:Lorg/sireum/project/Module$;
   #34 = Utf8               org/sireum/package$
   #35 = Class              #34           // org/sireum/package$
   #36 = Utf8               Lorg/sireum/package$;
   #37 = NameAndType        #22:#36       // MODULE$:Lorg/sireum/package$;
   #38 = Fieldref           #35.#37       // org/sireum/package$.MODULE$:Lorg/sireum/package$;
   #39 = Utf8               ISZ
   #40 = Utf8               ()Lorg/sireum/$internal/PackageTrait$ISZ$;
   #41 = NameAndType        #39:#40       // ISZ:()Lorg/sireum/$internal/PackageTrait$ISZ$;
   #42 = Methodref          #35.#41       // org/sireum/package$.ISZ:()Lorg/sireum/$internal/PackageTrait$ISZ$;
   #43 = Utf8               scala/runtime/ScalaRunTime$
   #44 = Class              #43           // scala/runtime/ScalaRunTime$
   #45 = Utf8               Lscala/runtime/ScalaRunTime$;
   #46 = NameAndType        #22:#45       // MODULE$:Lscala/runtime/ScalaRunTime$;
   #47 = Fieldref           #44.#46       // scala/runtime/ScalaRunTime$.MODULE$:Lscala/runtime/ScalaRunTime$;
   #48 = Utf8               Lorg/sireum/project/Target$Jvm$;
   #49 = NameAndType        #22:#48       // MODULE$:Lorg/sireum/project/Target$Jvm$;
   #50 = Fieldref           #17.#49       // org/sireum/project/Target$Jvm$.MODULE$:Lorg/sireum/project/Target$Jvm$;
   #51 = Utf8               Lorg/sireum/project/Target$Js$;
   #52 = NameAndType        #22:#51       // MODULE$:Lorg/sireum/project/Target$Js$;
   #53 = Fieldref           #12.#52       // org/sireum/project/Target$Js$.MODULE$:Lorg/sireum/project/Target$Js$;
   #54 = Utf8               [Ljava/lang/Object;
   #55 = Class              #54           // "[Ljava/lang/Object;"
   #56 = Utf8               wrapRefArray
   #57 = Utf8               ([Ljava/lang/Object;)Lscala/collection/immutable/ArraySeq;
   #58 = NameAndType        #56:#57       // wrapRefArray:([Ljava/lang/Object;)Lscala/collection/immutable/ArraySeq;
   #59 = Methodref          #44.#58       // scala/runtime/ScalaRunTime$.wrapRefArray:([Ljava/lang/Object;)Lscala/collection/immutable/ArraySeq;
   #60 = Utf8               apply
   #61 = Utf8               (Lscala/collection/immutable/Seq;)Lorg/sireum/IS;
   #62 = NameAndType        #60:#61       // apply:(Lscala/collection/immutable/Seq;)Lorg/sireum/IS;
   #63 = Methodref          #7.#62        // org/sireum/$internal/PackageTrait$ISZ$.apply:(Lscala/collection/immutable/Seq;)Lorg/sireum/IS;
   #64 = NameAndType        #24:#25       // allTargets:Lorg/sireum/IS;
   #65 = Fieldref           #2.#64        // org/sireum/project/Module$.allTargets:Lorg/sireum/IS;
   #66 = Utf8               ()Lorg/sireum/IS;
   #67 = Utf8               ()Lorg/sireum/IS<Lorg/sireum/Z;Lorg/sireum/project/Target$Type;>;
   #68 = Utf8               this
   #69 = Utf8               (Ljava/lang/String;Ljava/lang/String;Lorg/sireum/Option;Lorg/sireum/IS;Lorg/sireum/IS;Lorg/sireum/IS;Lorg/sireum/IS;Lorg/sireum/IS;Lorg/sireum/IS;Lorg/sireum/IS;Lorg/sireum/Option;)Lorg/sireum/project/Module;
   #70 = Utf8               (Ljava/lang/String;Ljava/lang/String;Lorg/sireum/Option<Lorg/sireum/String;>;Lorg/sireum/IS<Lorg/sireum/Z;Lorg/sireum/String;>;Lorg/sireum/IS<Lorg/sireum/Z;Lorg/sireum/project/Target$Type;>;Lorg/sireum/IS<Lorg/sireum/Z;Lorg/sireum/String;>;Lorg/sireum/IS<Lorg/sireum/Z;Lorg/sireum/String;>;Lorg/sireum/IS<Lorg/sireum/Z;Lorg/sireum/String;>;Lorg/sireum/IS<Lorg/sireum/Z;Lorg/sireum/String;>;Lorg/sireum/IS<Lorg/sireum/Z;Lorg/sireum/String;>;Lorg/sireum/Option<Lorg/sireum/project/PublishInfo;>;)Lorg/sireum/project/Module;
   #71 = Utf8               id
   #72 = Utf8               basePath
   #73 = Utf8               subPathOpt
   #74 = Utf8               deps
   #75 = Utf8               targets
   #76 = Utf8               ivyDeps
   #77 = Utf8               sources
   #78 = Utf8               resources
   #79 = Utf8               testSources
   #80 = Utf8               testResources
   #81 = Utf8               publishInfoOpt
   #82 = Utf8               org/sireum/project/Module
   #83 = Class              #82           // org/sireum/project/Module
   #84 = Utf8               (Ljava/lang/String;Ljava/lang/String;Lorg/sireum/Option;Lorg/sireum/IS;Lorg/sireum/IS;Lorg/sireum/IS;Lorg/sireum/IS;Lorg/sireum/IS;Lorg/sireum/IS;Lorg/sireum/IS;Lorg/sireum/Option;)V
   #85 = NameAndType        #29:#84       // "<init>":(Ljava/lang/String;Ljava/lang/String;Lorg/sireum/Option;Lorg/sireum/IS;Lorg/sireum/IS;Lorg/sireum/IS;Lorg/sireum/IS;Lorg/sireum/IS;Lorg/sireum/IS;Lorg/sireum/IS;Lorg/sireum/Option;)V
   #86 = Methodref          #83.#85       // org/sireum/project/Module."<init>":(Ljava/lang/String;Ljava/lang/String;Lorg/sireum/Option;Lorg/sireum/IS;Lorg/sireum/IS;Lorg/sireum/IS;Lorg/sireum/IS;Lorg/sireum/IS;Lorg/sireum/IS;Lorg/sireum/IS;Lorg/sireum/Option;)V
   #87 = Utf8               Ljava/lang/String;
   #88 = Utf8               Lorg/sireum/Option;
   #89 = Utf8               unapply
   #90 = Utf8               (Lorg/sireum/project/Module;)Lscala/Some;
   #91 = Utf8               (Lorg/sireum/project/Module;)Lscala/Some<Lscala/Tuple11<Lorg/sireum/String;Lorg/sireum/String;Lorg/sireum/Option<Lorg/sireum/String;>;Lorg/sireum/IS<Lorg/sireum/Z;Lorg/sireum/String;>;Lorg/sireum/IS<Lorg/sireum/Z;Lorg/sireum/project/Target$Type;>;Lorg/sireum/IS<Lorg/sireum/Z;Lorg/sireum/String;>;Lorg/sireum/IS<Lorg/sireum/Z;Lorg/sireum/String;>;Lorg/sireum/IS<Lorg/sireum/Z;Lorg/sireum/String;>;Lorg/sireum/IS<Lorg/sireum/Z;Lorg/sireum/String;>;Lorg/sireum/IS<Lorg/sireum/Z;Lorg/sireum/String;>;Lorg/sireum/Option<Lorg/sireum/project/PublishInfo;>;>;>;
   #92 = Utf8               o
   #93 = Utf8               scala/Some
   #94 = Class              #93           // scala/Some
   #95 = Utf8               scala/Tuple11
   #96 = Class              #95           // scala/Tuple11
   #97 = Utf8               org/sireum/String
   #98 = Class              #97           // org/sireum/String
   #99 = Utf8               ()Ljava/lang/String;
  #100 = NameAndType        #71:#99       // id:()Ljava/lang/String;
  #101 = Methodref          #83.#100      // org/sireum/project/Module.id:()Ljava/lang/String;
  #102 = Utf8               (Ljava/lang/String;)V
  #103 = NameAndType        #29:#102      // "<init>":(Ljava/lang/String;)V
  #104 = Methodref          #98.#103      // org/sireum/String."<init>":(Ljava/lang/String;)V
  #105 = NameAndType        #72:#99       // basePath:()Ljava/lang/String;
  #106 = Methodref          #83.#105      // org/sireum/project/Module.basePath:()Ljava/lang/String;
  #107 = Utf8               ()Lorg/sireum/Option;
  #108 = NameAndType        #73:#107      // subPathOpt:()Lorg/sireum/Option;
  #109 = Methodref          #83.#108      // org/sireum/project/Module.subPathOpt:()Lorg/sireum/Option;
  #110 = NameAndType        #74:#66       // deps:()Lorg/sireum/IS;
  #111 = Methodref          #83.#110      // org/sireum/project/Module.deps:()Lorg/sireum/IS;
  #112 = NameAndType        #75:#66       // targets:()Lorg/sireum/IS;
  #113 = Methodref          #83.#112      // org/sireum/project/Module.targets:()Lorg/sireum/IS;
  #114 = NameAndType        #76:#66       // ivyDeps:()Lorg/sireum/IS;
  #115 = Methodref          #83.#114      // org/sireum/project/Module.ivyDeps:()Lorg/sireum/IS;
  #116 = NameAndType        #77:#66       // sources:()Lorg/sireum/IS;
  #117 = Methodref          #83.#116      // org/sireum/project/Module.sources:()Lorg/sireum/IS;
  #118 = NameAndType        #78:#66       // resources:()Lorg/sireum/IS;
  #119 = Methodref          #83.#118      // org/sireum/project/Module.resources:()Lorg/sireum/IS;
  #120 = NameAndType        #79:#66       // testSources:()Lorg/sireum/IS;
  #121 = Methodref          #83.#120      // org/sireum/project/Module.testSources:()Lorg/sireum/IS;
  #122 = NameAndType        #80:#66       // testResources:()Lorg/sireum/IS;
  #123 = Methodref          #83.#122      // org/sireum/project/Module.testResources:()Lorg/sireum/IS;
  #124 = NameAndType        #81:#107      // publishInfoOpt:()Lorg/sireum/Option;
  #125 = Methodref          #83.#124      // org/sireum/project/Module.publishInfoOpt:()Lorg/sireum/Option;
  #126 = Utf8               (Ljava/lang/Object;Ljava/lang/Object;Ljava/lang/Object;Ljava/lang/Object;Ljava/lang/Object;Ljava/lang/Object;Ljava/lang/Object;Ljava/lang/Object;Ljava/lang/Object;Ljava/lang/Object;Ljava/lang/Object;)V
  #127 = NameAndType        #29:#126      // "<init>":(Ljava/lang/Object;Ljava/lang/Object;Ljava/lang/Object;Ljava/lang/Object;Ljava/lang/Object;Ljava/lang/Object;Ljava/lang/Object;Ljava/lang/Object;Ljava/lang/Object;Ljava/lang/Object;Ljava/lang/Object;)V
  #128 = Methodref          #96.#127      // scala/Tuple11."<init>":(Ljava/lang/Object;Ljava/lang/Object;Ljava/lang/Object;Ljava/lang/Object;Ljava/lang/Object;Ljava/lang/Object;Ljava/lang/Object;Ljava/lang/Object;Ljava/lang/Object;Ljava/lang/Object;Ljava/lang/Object;)V
  #129 = Utf8               (Ljava/lang/Object;)V
  #130 = NameAndType        #29:#129      // "<init>":(Ljava/lang/Object;)V
  #131 = Methodref          #94.#130      // scala/Some."<init>":(Ljava/lang/Object;)V
  #132 = Utf8               Lorg/sireum/project/Module;
  #133 = Methodref          #4.#30        // java/lang/Object."<init>":()V
  #134 = Utf8               Signature
  #135 = Utf8               Code
  #136 = Utf8               LineNumberTable
  #137 = Utf8               LocalVariableTable
  #138 = Utf8               MethodParameters
  #139 = Utf8               InnerClasses
  #140 = Utf8               SourceFile
  #141 = Utf8               ScalaInlineInfo
  #142 = Utf8               Scala
{
  public static final org.sireum.project.Module$ MODULE$;
    descriptor: Lorg/sireum/project/Module$;
    flags: (0x0019) ACC_PUBLIC, ACC_STATIC, ACC_FINAL

  private static final org.sireum.IS<org.sireum.Z, org.sireum.project.Target$Type> allTargets;
    descriptor: Lorg/sireum/IS;
    flags: (0x001a) ACC_PRIVATE, ACC_STATIC, ACC_FINAL
    Signature: #26                          // Lorg/sireum/IS<Lorg/sireum/Z;Lorg/sireum/project/Target$Type;>;

  public static {};
    descriptor: ()V
    flags: (0x0009) ACC_PUBLIC, ACC_STATIC
    Code:
      stack=6, locals=0, args_size=0
         0: new           #2                  // class org/sireum/project/Module$
         3: dup
         4: invokespecial #31                 // Method "<init>":()V
         7: putstatic     #33                 // Field MODULE$:Lorg/sireum/project/Module$;
        10: getstatic     #38                 // Field org/sireum/package$.MODULE$:Lorg/sireum/package$;
        13: invokevirtual #42                 // Method org/sireum/package$.ISZ:()Lorg/sireum/$internal/PackageTrait$ISZ$;
        16: getstatic     #47                 // Field scala/runtime/ScalaRunTime$.MODULE$:Lscala/runtime/ScalaRunTime$;
        19: iconst_2
        20: anewarray     #20                 // class org/sireum/project/Target$Type
        23: dup
        24: iconst_0
        25: getstatic     #50                 // Field org/sireum/project/Target$Jvm$.MODULE$:Lorg/sireum/project/Target$Jvm$;
        28: aastore
        29: dup
        30: iconst_1
        31: getstatic     #53                 // Field org/sireum/project/Target$Js$.MODULE$:Lorg/sireum/project/Target$Js$;
        34: aastore
        35: checkcast     #55                 // class "[Ljava/lang/Object;"
        38: invokevirtual #59                 // Method scala/runtime/ScalaRunTime$.wrapRefArray:([Ljava/lang/Object;)Lscala/collection/immutable/ArraySeq;
        41: invokevirtual #63                 // Method org/sireum/$internal/PackageTrait$ISZ$.apply:(Lscala/collection/immutable/Seq;)Lorg/sireum/IS;
        44: putstatic     #65                 // Field allTargets:Lorg/sireum/IS;
        47: return
      LineNumberTable:
        line 169: 0
        line 170: 10
        line 169: 47

  public org.sireum.IS<org.sireum.Z, org.sireum.project.Target$Type> allTargets();
    descriptor: ()Lorg/sireum/IS;
    flags: (0x0001) ACC_PUBLIC
    Code:
      stack=1, locals=1, args_size=1
         0: getstatic     #65                 // Field allTargets:Lorg/sireum/IS;
         3: areturn
      LineNumberTable:
        line 170: 0
      LocalVariableTable:
        Start  Length  Slot  Name   Signature
            0       4     0  this   Lorg/sireum/project/Module$;
    Signature: #67                          // ()Lorg/sireum/IS<Lorg/sireum/Z;Lorg/sireum/project/Target$Type;>;

  public org.sireum.project.Module apply(java.lang.String, java.lang.String, org.sireum.Option<org.sireum.String>, org.sireum.IS<org.sireum.Z, org.sireum.String>, org.sireum.IS<org.sireum.Z, org.sireum.project.Target$Type>, org.sireum.IS<org.sireum.Z, org.sireum.String>, org.sireum.IS<org.sireum.Z, org.sireum.String>, org.sireum.IS<org.sireum.Z, org.sireum.String>, org.sireum.IS<org.sireum.Z, org.sireum.String>, org.sireum.IS<org.sireum.Z, org.sireum.String>, org.sireum.Option<org.sireum.project.PublishInfo>);
    descriptor: (Ljava/lang/String;Ljava/lang/String;Lorg/sireum/Option;Lorg/sireum/IS;Lorg/sireum/IS;Lorg/sireum/IS;Lorg/sireum/IS;Lorg/sireum/IS;Lorg/sireum/IS;Lorg/sireum/IS;Lorg/sireum/Option;)Lorg/sireum/project/Module;
    flags: (0x0001) ACC_PUBLIC
    Code:
      stack=13, locals=12, args_size=12
         0: new           #83                 // class org/sireum/project/Module
         3: dup
         4: aload_1
         5: aload_2
         6: aload_3
         7: aload         4
         9: aload         5
        11: aload         6
        13: aload         7
        15: aload         8
        17: aload         9
        19: aload         10
        21: aload         11
        23: invokespecial #86                 // Method org/sireum/project/Module."<init>":(Ljava/lang/String;Ljava/lang/String;Lorg/sireum/Option;Lorg/sireum/IS;Lorg/sireum/IS;Lorg/sireum/IS;Lorg/sireum/IS;Lorg/sireum/IS;Lorg/sireum/IS;Lorg/sireum/IS;Lorg/sireum/Option;)V
        26: areturn
      LineNumberTable:
        line 169: 0
      LocalVariableTable:
        Start  Length  Slot  Name   Signature
            0      27     0  this   Lorg/sireum/project/Module$;
            0      27     1    id   Ljava/lang/String;
            0      27     2 basePath   Ljava/lang/String;
            0      27     3 subPathOpt   Lorg/sireum/Option;
            0      27     4  deps   Lorg/sireum/IS;
            0      27     5 targets   Lorg/sireum/IS;
            0      27     6 ivyDeps   Lorg/sireum/IS;
            0      27     7 sources   Lorg/sireum/IS;
            0      27     8 resources   Lorg/sireum/IS;
            0      27     9 testSources   Lorg/sireum/IS;
            0      27    10 testResources   Lorg/sireum/IS;
            0      27    11 publishInfoOpt   Lorg/sireum/Option;
    Signature: #70                          // (Ljava/lang/String;Ljava/lang/String;Lorg/sireum/Option<Lorg/sireum/String;>;Lorg/sireum/IS<Lorg/sireum/Z;Lorg/sireum/String;>;Lorg/sireum/IS<Lorg/sireum/Z;Lorg/sireum/project/Target$Type;>;Lorg/sireum/IS<Lorg/sireum/Z;Lorg/sireum/String;>;Lorg/sireum/IS<Lorg/sireum/Z;Lorg/sireum/String;>;Lorg/sireum/IS<Lorg/sireum/Z;Lorg/sireum/String;>;Lorg/sireum/IS<Lorg/sireum/Z;Lorg/sireum/String;>;Lorg/sireum/IS<Lorg/sireum/Z;Lorg/sireum/String;>;Lorg/sireum/Option<Lorg/sireum/project/PublishInfo;>;)Lorg/sireum/project/Module;
    MethodParameters:
      Name                           Flags
      id                             final
      basePath                       final
      subPathOpt                     final
      deps                           final
      targets                        final
      ivyDeps                        final
      sources                        final
      resources                      final
      testSources                    final
      testResources                  final
      publishInfoOpt                 final

  public scala.Some<scala.Tuple11<org.sireum.String, org.sireum.String, org.sireum.Option<org.sireum.String>, org.sireum.IS<org.sireum.Z, org.sireum.String>, org.sireum.IS<org.sireum.Z, org.sireum.project.Target$Type>, org.sireum.IS<org.sireum.Z, org.sireum.String>, org.sireum.IS<org.sireum.Z, org.sireum.String>, org.sireum.IS<org.sireum.Z, org.sireum.String>, org.sireum.IS<org.sireum.Z, org.sireum.String>, org.sireum.IS<org.sireum.Z, org.sireum.String>, org.sireum.Option<org.sireum.project.PublishInfo>>> unapply(org.sireum.project.Module);
    descriptor: (Lorg/sireum/project/Module;)Lscala/Some;
    flags: (0x0001) ACC_PUBLIC
    Code:
      stack=15, locals=2, args_size=2
         0: new           #94                 // class scala/Some
         3: dup
         4: new           #96                 // class scala/Tuple11
         7: dup
         8: new           #98                 // class org/sireum/String
        11: dup
        12: aload_1
        13: invokevirtual #101                // Method org/sireum/project/Module.id:()Ljava/lang/String;
        16: invokespecial #104                // Method org/sireum/String."<init>":(Ljava/lang/String;)V
        19: new           #98                 // class org/sireum/String
        22: dup
        23: aload_1
        24: invokevirtual #106                // Method org/sireum/project/Module.basePath:()Ljava/lang/String;
        27: invokespecial #104                // Method org/sireum/String."<init>":(Ljava/lang/String;)V
        30: aload_1
        31: invokevirtual #109                // Method org/sireum/project/Module.subPathOpt:()Lorg/sireum/Option;
        34: aload_1
        35: invokevirtual #111                // Method org/sireum/project/Module.deps:()Lorg/sireum/IS;
        38: aload_1
        39: invokevirtual #113                // Method org/sireum/project/Module.targets:()Lorg/sireum/IS;
        42: aload_1
        43: invokevirtual #115                // Method org/sireum/project/Module.ivyDeps:()Lorg/sireum/IS;
        46: aload_1
        47: invokevirtual #117                // Method org/sireum/project/Module.sources:()Lorg/sireum/IS;
        50: aload_1
        51: invokevirtual #119                // Method org/sireum/project/Module.resources:()Lorg/sireum/IS;
        54: aload_1
        55: invokevirtual #121                // Method org/sireum/project/Module.testSources:()Lorg/sireum/IS;
        58: aload_1
        59: invokevirtual #123                // Method org/sireum/project/Module.testResources:()Lorg/sireum/IS;
        62: aload_1
        63: invokevirtual #125                // Method org/sireum/project/Module.publishInfoOpt:()Lorg/sireum/Option;
        66: invokespecial #128                // Method scala/Tuple11."<init>":(Ljava/lang/Object;Ljava/lang/Object;Ljava/lang/Object;Ljava/lang/Object;Ljava/lang/Object;Ljava/lang/Object;Ljava/lang/Object;Ljava/lang/Object;Ljava/lang/Object;Ljava/lang/Object;Ljava/lang/Object;)V
        69: invokespecial #131                // Method scala/Some."<init>":(Ljava/lang/Object;)V
        72: areturn
      LineNumberTable:
        line 169: 0
      LocalVariableTable:
        Start  Length  Slot  Name   Signature
            0      73     0  this   Lorg/sireum/project/Module$;
            0      73     1     o   Lorg/sireum/project/Module;
    Signature: #91                          // (Lorg/sireum/project/Module;)Lscala/Some<Lscala/Tuple11<Lorg/sireum/String;Lorg/sireum/String;Lorg/sireum/Option<Lorg/sireum/String;>;Lorg/sireum/IS<Lorg/sireum/Z;Lorg/sireum/String;>;Lorg/sireum/IS<Lorg/sireum/Z;Lorg/sireum/project/Target$Type;>;Lorg/sireum/IS<Lorg/sireum/Z;Lorg/sireum/String;>;Lorg/sireum/IS<Lorg/sireum/Z;Lorg/sireum/String;>;Lorg/sireum/IS<Lorg/sireum/Z;Lorg/sireum/String;>;Lorg/sireum/IS<Lorg/sireum/Z;Lorg/sireum/String;>;Lorg/sireum/IS<Lorg/sireum/Z;Lorg/sireum/String;>;Lorg/sireum/Option<Lorg/sireum/project/PublishInfo;>;>;>;
    MethodParameters:
      Name                           Flags
      o                              final

  private org.sireum.project.Module$();
    descriptor: ()V
    flags: (0x0002) ACC_PRIVATE
    Code:
      stack=1, locals=1, args_size=1
         0: aload_0
         1: invokespecial #133                // Method java/lang/Object."<init>":()V
         4: return
      LineNumberTable:
        line 169: 0
      LocalVariableTable:
        Start  Length  Slot  Name   Signature
            0       5     0  this   Lorg/sireum/project/Module$;
}
InnerClasses:
  public #10= #7 of #9;                   // ISZ$=class org/sireum/$internal/PackageTrait$ISZ$ of class org/sireum/$internal/PackageTrait
  public static final #15= #12 of #14;    // Js$=class org/sireum/project/Target$Js$ of class org/sireum/project/Target
  public static final #18= #17 of #14;    // Jvm$=class org/sireum/project/Target$Jvm$ of class org/sireum/project/Target
  public static #21= #20 of #14;          // Type=class org/sireum/project/Target$Type of class org/sireum/project/Target
SourceFile: "Project.scala"
  ScalaInlineInfo: length = 0x18 (unknown attribute)
   01 01 00 04 00 1D 00 1C 01 00 18 00 42 01 00 3C
   00 45 01 00 59 00 5A 01
  Scala: length = 0x0 (unknown attribute)

