Classfile /Users/mw/Projects/slang-braindump/.jar/jar8/assemble/slang-braindump/assemble/content/org/sireum/project/Target.class
  Last modified May 29, 2022; size 3040 bytes
  SHA-256 checksum ac0190c74c5d06b824a1158d4b2e269e84de0deaaf565ff95cdeb7092de78672
  Compiled from "Project.scala"
public final class org.sireum.project.Target
  minor version: 0
  major version: 52
  flags: (0x0031) ACC_PUBLIC, ACC_FINAL, ACC_SUPER
  this_class: #2                          // org/sireum/project/Target
  super_class: #4                         // java/lang/Object
  interfaces: 0, fields: 0, methods: 6, attributes: 4
Constant pool:
   #1 = Utf8               org/sireum/project/Target
   #2 = Class              #1             // org/sireum/project/Target
   #3 = Utf8               java/lang/Object
   #4 = Class              #3             // java/lang/Object
   #5 = Utf8               Project.scala
   #6 = Utf8               Lscala/reflect/ScalaSignature;
   #7 = Utf8               bytes
   #8 = Utf8               \u0006\u0005\u0005%v!B\u0016-\u0011\u0003\u0019d!B\u001b-\u0011\u00031\u0004\"B!\u0002\t\u0003\u0011eaB\"\u0002!\u0003\r\t\u0003\u0012\u0005\u0006-\u000e!\ta\u0016\u0005\u00067\u000e1\t\u0001\u0018\u0005\u0006A\u000e1\t!\u0019\u0005\u0006K\u000e!)\u0001\u0018\u0005\u0006M\u000e!)a\u001a\u0005\u0006[\u000e!)A\u001c\u0005\u0006i\u000e!)!\u0019\u0005\b\u0003G\nAQAA3\u0011\u001d\ty\'\u0001C\u0003\u0003c:q!a\u001e\u0002\u0011\u000b\u000bIFB\u0004\u0002T\u0005A))!\u0016\t\r\u0005sA\u0011AA,\u0011\u0015Yf\u0002\"\u0001]\u0011\u0015\u0001g\u0002\"\u0001b\u0011%\t\tADA\u0001\n\u0003\n\u0019\u0001C\u0005\u0002\u00149\t\t\u0011\"\u0001\u0002\u0016!I\u0011q\u0003\b\u0002\u0002\u0013\u0005\u00111\f\u0005\n\u0003Kq\u0011\u0011!C!\u0003OA\u0011\"!\u000e\u000f\u0003\u0003%\t!a\u0018\t\u0013\u0005\u0005c\"!A\u0005B\u0005\r\u0003\"CA#\u001d\u0005\u0005I\u0011IA$\u0011%\tIEDA\u0001\n\u0013\tYe\u0002\u0004\u0002z\u0005A)i \u0004\u0006m\u0006A)i\u001e\u0005\u0006\u0003n!\tA \u0005\u00067n!\t\u0001\u0018\u0005\u0006An!\t!\u0019\u0005\n\u0003\u0003Y\u0012\u0011!C!\u0003\u0007A\u0011\"a\u0005\u001c\u0003\u0003%\t!!\u0006\t\u0013\u0005]1$!A\u0005\u0002\u0005e\u0001\"CA\u00137\u0005\u0005I\u0011IA\u0014\u0011%\t)dGA\u0001\n\u0003\t9\u0004C\u0005\u0002Bm\t\t\u0011\"\u0011\u0002D!I\u0011QI\u000e\u0002\u0002\u0013\u0005\u0013q\t\u0005\n\u0003\u0013Z\u0012\u0011!C\u0005\u0003\u0017B\u0001\"a\u001f\u0002\u0005\u0004%\t\u0001\u0018\u0005\b\u0003{\n\u0001\u0015!\u0003^\u0011%\ty(\u0001b\u0001\n\u0003\t\t\t\u0003\u0005\u0002\u001e\u0006\u0001\u000b\u0011BAB\u0003\u0019!\u0016M]4fi*\u0011QFL\u0001\baJ|\'.Z2u\u0015\ty\u0003\'\u0001\u0004tSJ,W/\u001c\u0006\u0002c\u0005\u0019qN]4\u0004\u0001A\u0011A\'A\u0007\u0002Y\t1A+\u0019:hKR\u001c2!A\u001c>!\tA4(D\u0001:\u0015\u0005Q\u0014!B:dC2\f\u0017B\u0001\u001f:\u0005\u0019\te.\u001f*fMB\u0011ahP\u0007\u0002]%\u0011\u0001I\f\u0002\b\u000b:,XnU5h\u0003\u0019a\u0014N\\5u}Q\t1G\u0001\u0003UsB,7\u0003B\u00028\u000b\"\u0003\"A\u0010$\n\u0005\u001ds#!C%n[V$\u0018M\u00197f!\rI\u0015\u000b\u0016\b\u0003\u0015>s!a\u0013(\u000e\u00031S!!\u0014\u001a\u0002\rq\u0012xn\u001c;?\u0013\u0005Q\u0014B\u0001):\u0003\u001d\u0001\u0018mY6bO\u0016L!AU*\u0003\u000f=\u0013H-\u001a:fI*\u0011\u0001+\u000f\t\u0003+\u000ei\u0011!A\u0001\u0007I%t\u0017\u000e\u001e\u0013\u0015\u0003a\u0003\"\u0001O-\n\u0005iK$\u0001B+oSR\fqa\u001c:eS:\fG.F\u0001^!\tqd,\u0003\u0002`]\t\t!,\u0001\u0003oC6,W#\u00012\u0011\u0005y\u001a\u0017B\u00013/\u0005\u0019\u0019FO]5oO\u0006!\u0001.Y:i\u0003\u001dI7/R9vC2$\"\u0001[6\u0011\u0005yJ\u0017B\u00016/\u0005\u0005\u0011\u0005\"\u00027\t\u0001\u0004!\u0016!B8uQ\u0016\u0014\u0018aB2p[B\f\'/\u001a\u000b\u0003_J\u0004\"\u0001\u000f9\n\u0005EL$aA%oi\")1/\u0003a\u0001)\u0006!A\u000f[1u\u0003\u0019\u0019HO]5oO&\u001a1a\u0007\b\u0003\u0005)\u001b8#B\u000e8)b\\\bC\u0001\u001dz\u0013\tQ\u0018HA\u0004Qe>$Wo\u0019;\u0011\u0005%c\u0018BA?T\u00051\u0019VM]5bY&T\u0018M\u00197f)\u0005y\bCA+\u001c\u00035\u0001(o\u001c3vGR\u0004&/\u001a4jqV\u0011\u0011Q\u0001\t\u0005\u0003\u000f\t\t\"\u0004\u0002\u0002\n)!\u00111BA\u0007\u0003\u0011a\u0017M\\4\u000b\u0005\u0005=\u0011\u0001\u00026bm\u0006L1\u0001ZA\u0005\u00031\u0001(o\u001c3vGR\f%/\u001b;z+\u0005y\u0017A\u00049s_\u0012,8\r^#mK6,g\u000e\u001e\u000b\u0005\u00037\t\t\u0003E\u00029\u0003;I1!a\b:\u0005\r\te.\u001f\u0005\t\u0003G\t\u0013\u0011!a\u0001_\u0006\u0019\u0001\u0010J\u0019\u0002\u001fA\u0014x\u000eZ;di&#XM]1u_J,\"!!\u000b\u0011\r\u0005-\u0012\u0011GA\u000e\u001b\t\tiCC\u0002\u00020e\n!bY8mY\u0016\u001cG/[8o\u0013\u0011\t\u0019$!\f\u0003\u0011%#XM]1u_J\f\u0001bY1o\u000bF,\u0018\r\u001c\u000b\u0005\u0003s\ty\u0004E\u00029\u0003wI1!!\u0010:\u0005\u001d\u0011un\u001c7fC:D\u0011\"a\t$\u0003\u0003\u0005\r!a\u0007\u0002\u0011!\f7\u000f[\"pI\u0016$\u0012a\\\u0001\ti>\u001cFO]5oOR\u0011\u0011QA\u0001\roJLG/\u001a*fa2\f7-\u001a\u000b\u0003\u0003\u001b\u0002B!a\u0002\u0002P%!\u0011\u0011KA\u0005\u0005\u0019y%M[3di\n\u0019!J^7\u0014\u000b99D\u000b_>\u0015\u0005\u0005e\u0003CA+\u000f)\u0011\tY\"!\u0018\t\u0011\u0005\rB#!AA\u0002=$B!!\u000f\u0002b!I\u00111\u0005\f\u0002\u0002\u0003\u0007\u00111D\u0001\u0007Eft\u0015-\\3\u0015\t\u0005\u001d\u0014Q\u000e\t\u0005}\u0005%D+C\u0002\u0002l9\u0012aa\u00149uS>t\u0007\"\u00021\f\u0001\u0004\u0011\u0017!\u00032z\u001fJ$\u0017N\\1m)\u0011\t9\'a\u001d\t\r\u0005UD\u00021\u0001^\u0003\u0005q\u0017a\u0001&w[\u0006\u0011!j]\u0001\u000e]VlwJZ#mK6,g\u000e^:\u0002\u001d9,Xn\u00144FY\u0016lWM\u001c;tA\u0005AQ\r\\3nK:$8/\u0006\u0002\u0002\u0004B)\u0011QQAI):!\u0011qQAH\u001d\u0011\tI)!$\u000f\u0007-\u000bY)C\u00012\u0013\ty\u0003\'\u0003\u0002Q]%!\u00111SAK\u0005\rI5KW\u0005\u0005\u0003/\u000bIJ\u0001\u0007QC\u000e\\\u0017mZ3Ue\u0006LGOC\u0002\u0002\u001c:\n\u0011\u0002J5oi\u0016\u0014h.\u00197\u0002\u0013\u0015dW-\\3oiN\u0004\u0003fA\u0001\u0002\"B\u0019a(a)\n\u0007\u0005\u0015fF\u0001\u0003f]Vl\u0007f\u0001\u0001\u0002\"\u0002
   #9 = Utf8               org/sireum/project/Target$Js$
  #10 = Class              #9             // org/sireum/project/Target$Js$
  #11 = Utf8               Js$
  #12 = Utf8               org/sireum/project/Target$Jvm$
  #13 = Class              #12            // org/sireum/project/Target$Jvm$
  #14 = Utf8               Jvm$
  #15 = Utf8               org/sireum/project/Target$Type
  #16 = Class              #15            // org/sireum/project/Target$Type
  #17 = Utf8               Type
  #18 = Utf8               elements
  #19 = Utf8               ()Lorg/sireum/IS;
  #20 = Utf8               ()Lorg/sireum/IS<Lorg/sireum/Z;Lorg/sireum/project/Target$Type;>;
  #21 = Utf8               org/sireum/project/Target$
  #22 = Class              #21            // org/sireum/project/Target$
  #23 = Utf8               MODULE$
  #24 = Utf8               Lorg/sireum/project/Target$;
  #25 = NameAndType        #23:#24        // MODULE$:Lorg/sireum/project/Target$;
  #26 = Fieldref           #22.#25        // org/sireum/project/Target$.MODULE$:Lorg/sireum/project/Target$;
  #27 = NameAndType        #18:#19        // elements:()Lorg/sireum/IS;
  #28 = Methodref          #22.#27        // org/sireum/project/Target$.elements:()Lorg/sireum/IS;
  #29 = Utf8               numOfElements
  #30 = Utf8               ()Lorg/sireum/Z;
  #31 = NameAndType        #29:#30        // numOfElements:()Lorg/sireum/Z;
  #32 = Methodref          #22.#31        // org/sireum/project/Target$.numOfElements:()Lorg/sireum/Z;
  #33 = Utf8               byOrdinal
  #34 = Utf8               (Lorg/sireum/Z;)Lorg/sireum/Option;
  #35 = Utf8               (Lorg/sireum/Z;)Lorg/sireum/Option<Lorg/sireum/project/Target$Type;>;
  #36 = Utf8               n
  #37 = NameAndType        #33:#34        // byOrdinal:(Lorg/sireum/Z;)Lorg/sireum/Option;
  #38 = Methodref          #22.#37        // org/sireum/project/Target$.byOrdinal:(Lorg/sireum/Z;)Lorg/sireum/Option;
  #39 = Utf8               Lorg/sireum/Z;
  #40 = Utf8               byName
  #41 = Utf8               (Ljava/lang/String;)Lorg/sireum/Option;
  #42 = Utf8               (Ljava/lang/String;)Lorg/sireum/Option<Lorg/sireum/project/Target$Type;>;
  #43 = Utf8               name
  #44 = NameAndType        #40:#41        // byName:(Ljava/lang/String;)Lorg/sireum/Option;
  #45 = Methodref          #22.#44        // org/sireum/project/Target$.byName:(Ljava/lang/String;)Lorg/sireum/Option;
  #46 = Utf8               Ljava/lang/String;
  #47 = Utf8               string
  #48 = Utf8               ()Ljava/lang/String;
  #49 = NameAndType        #47:#48        // string:()Ljava/lang/String;
  #50 = Methodref          #22.#49        // org/sireum/project/Target$.string:()Ljava/lang/String;
  #51 = Utf8               $clone
  #52 = Utf8               ()Lorg/sireum/$internal/ImmutableMarker;
  #53 = NameAndType        #51:#52        // $clone:()Lorg/sireum/$internal/ImmutableMarker;
  #54 = Methodref          #22.#53        // org/sireum/project/Target$.$clone:()Lorg/sireum/$internal/ImmutableMarker;
  #55 = Utf8               Code
  #56 = Utf8               Signature
  #57 = Utf8               LocalVariableTable
  #58 = Utf8               MethodParameters
  #59 = Utf8               InnerClasses
  #60 = Utf8               SourceFile
  #61 = Utf8               RuntimeVisibleAnnotations
  #62 = Utf8               ScalaSig
{
  public static org.sireum.IS<org.sireum.Z, org.sireum.project.Target$Type> elements();
    descriptor: ()Lorg/sireum/IS;
    flags: (0x0009) ACC_PUBLIC, ACC_STATIC
    Code:
      stack=1, locals=0, args_size=0
         0: getstatic     #26                 // Field org/sireum/project/Target$.MODULE$:Lorg/sireum/project/Target$;
         3: invokevirtual #28                 // Method org/sireum/project/Target$.elements:()Lorg/sireum/IS;
         6: areturn
    Signature: #20                          // ()Lorg/sireum/IS<Lorg/sireum/Z;Lorg/sireum/project/Target$Type;>;

  public static org.sireum.Z numOfElements();
    descriptor: ()Lorg/sireum/Z;
    flags: (0x0009) ACC_PUBLIC, ACC_STATIC
    Code:
      stack=1, locals=0, args_size=0
         0: getstatic     #26                 // Field org/sireum/project/Target$.MODULE$:Lorg/sireum/project/Target$;
         3: invokevirtual #32                 // Method org/sireum/project/Target$.numOfElements:()Lorg/sireum/Z;
         6: areturn

  public static org.sireum.Option<org.sireum.project.Target$Type> byOrdinal(org.sireum.Z);
    descriptor: (Lorg/sireum/Z;)Lorg/sireum/Option;
    flags: (0x0009) ACC_PUBLIC, ACC_STATIC
    Code:
      stack=2, locals=1, args_size=1
         0: getstatic     #26                 // Field org/sireum/project/Target$.MODULE$:Lorg/sireum/project/Target$;
         3: aload_0
         4: invokevirtual #38                 // Method org/sireum/project/Target$.byOrdinal:(Lorg/sireum/Z;)Lorg/sireum/Option;
         7: areturn
      LocalVariableTable:
        Start  Length  Slot  Name   Signature
            0       8     0     n   Lorg/sireum/Z;
    Signature: #35                          // (Lorg/sireum/Z;)Lorg/sireum/Option<Lorg/sireum/project/Target$Type;>;
    MethodParameters:
      Name                           Flags
      n                              final

  public static org.sireum.Option<org.sireum.project.Target$Type> byName(java.lang.String);
    descriptor: (Ljava/lang/String;)Lorg/sireum/Option;
    flags: (0x0009) ACC_PUBLIC, ACC_STATIC
    Code:
      stack=2, locals=1, args_size=1
         0: getstatic     #26                 // Field org/sireum/project/Target$.MODULE$:Lorg/sireum/project/Target$;
         3: aload_0
         4: invokevirtual #45                 // Method org/sireum/project/Target$.byName:(Ljava/lang/String;)Lorg/sireum/Option;
         7: areturn
      LocalVariableTable:
        Start  Length  Slot  Name   Signature
            0       8     0  name   Ljava/lang/String;
    Signature: #42                          // (Ljava/lang/String;)Lorg/sireum/Option<Lorg/sireum/project/Target$Type;>;
    MethodParameters:
      Name                           Flags
      name                           final

  public static java.lang.String string();
    descriptor: ()Ljava/lang/String;
    flags: (0x0009) ACC_PUBLIC, ACC_STATIC
    Code:
      stack=1, locals=0, args_size=0
         0: getstatic     #26                 // Field org/sireum/project/Target$.MODULE$:Lorg/sireum/project/Target$;
         3: invokevirtual #50                 // Method org/sireum/project/Target$.string:()Ljava/lang/String;
         6: areturn

  public static org.sireum.$internal.ImmutableMarker $clone();
    descriptor: ()Lorg/sireum/$internal/ImmutableMarker;
    flags: (0x0009) ACC_PUBLIC, ACC_STATIC
    Code:
      stack=1, locals=0, args_size=0
         0: getstatic     #26                 // Field org/sireum/project/Target$.MODULE$:Lorg/sireum/project/Target$;
         3: invokevirtual #54                 // Method org/sireum/project/Target$.$clone:()Lorg/sireum/$internal/ImmutableMarker;
         6: areturn
}
InnerClasses:
  public static final #11= #10 of #2;     // Js$=class org/sireum/project/Target$Js$ of class org/sireum/project/Target
  public static final #14= #13 of #2;     // Jvm$=class org/sireum/project/Target$Jvm$ of class org/sireum/project/Target
  public static #17= #16 of #2;           // Type=class org/sireum/project/Target$Type of class org/sireum/project/Target
SourceFile: "Project.scala"
RuntimeVisibleAnnotations:
  0: #6(#7=s#8)
    scala.reflect.ScalaSignature(
      bytes="\u0006\u0005\u0005%v!B\u0016-\u0011\u0003\u0019d!B\u001b-\u0011\u00031\u0004\"B!\u0002\t\u0003\u0011eaB\"\u0002!\u0003\r\t\u0003\u0012\u0005\u0006-\u000e!\ta\u0016\u0005\u00067\u000e1\t\u0001\u0018\u0005\u0006A\u000e1\t!\u0019\u0005\u0006K\u000e!)\u0001\u0018\u0005\u0006M\u000e!)a\u001a\u0005\u0006[\u000e!)A\u001c\u0005\u0006i\u000e!)!\u0019\u0005\b\u0003G\nAQAA3\u0011\u001d\ty\'\u0001C\u0003\u0003c:q!a\u001e\u0002\u0011\u000b\u000bIFB\u0004\u0002T\u0005A))!\u0016\t\r\u0005sA\u0011AA,\u0011\u0015Yf\u0002\"\u0001]\u0011\u0015\u0001g\u0002\"\u0001b\u0011%\t\tADA\u0001\n\u0003\n\u0019\u0001C\u0005\u0002\u00149\t\t\u0011\"\u0001\u0002\u0016!I\u0011q\u0003\b\u0002\u0002\u0013\u0005\u00111\f\u0005\n\u0003Kq\u0011\u0011!C!\u0003OA\u0011\"!\u000e\u000f\u0003\u0003%\t!a\u0018\t\u0013\u0005\u0005c\"!A\u0005B\u0005\r\u0003\"CA#\u001d\u0005\u0005I\u0011IA$\u0011%\tIEDA\u0001\n\u0013\tYe\u0002\u0004\u0002z\u0005A)i \u0004\u0006m\u0006A)i\u001e\u0005\u0006\u0003n!\tA \u0005\u00067n!\t\u0001\u0018\u0005\u0006An!\t!\u0019\u0005\n\u0003\u0003Y\u0012\u0011!C!\u0003\u0007A\u0011\"a\u0005\u001c\u0003\u0003%\t!!\u0006\t\u0013\u0005]1$!A\u0005\u0002\u0005e\u0001\"CA\u00137\u0005\u0005I\u0011IA\u0014\u0011%\t)dGA\u0001\n\u0003\t9\u0004C\u0005\u0002Bm\t\t\u0011\"\u0011\u0002D!I\u0011QI\u000e\u0002\u0002\u0013\u0005\u0013q\t\u0005\n\u0003\u0013Z\u0012\u0011!C\u0005\u0003\u0017B\u0001\"a\u001f\u0002\u0005\u0004%\t\u0001\u0018\u0005\b\u0003{\n\u0001\u0015!\u0003^\u0011%\ty(\u0001b\u0001\n\u0003\t\t\t\u0003\u0005\u0002\u001e\u0006\u0001\u000b\u0011BAB\u0003\u0019!\u0016M]4fi*\u0011QFL\u0001\baJ|\'.Z2u\u0015\ty\u0003\'\u0001\u0004tSJ,W/\u001c\u0006\u0002c\u0005\u0019qN]4\u0004\u0001A\u0011A\'A\u0007\u0002Y\t1A+\u0019:hKR\u001c2!A\u001c>!\tA4(D\u0001:\u0015\u0005Q\u0014!B:dC2\f\u0017B\u0001\u001f:\u0005\u0019\te.\u001f*fMB\u0011ahP\u0007\u0002]%\u0011\u0001I\f\u0002\b\u000b:,XnU5h\u0003\u0019a\u0014N\\5u}Q\t1G\u0001\u0003UsB,7\u0003B\u00028\u000b\"\u0003\"A\u0010$\n\u0005\u001ds#!C%n[V$\u0018M\u00197f!\rI\u0015\u000b\u0016\b\u0003\u0015>s!a\u0013(\u000e\u00031S!!\u0014\u001a\u0002\rq\u0012xn\u001c;?\u0013\u0005Q\u0014B\u0001):\u0003\u001d\u0001\u0018mY6bO\u0016L!AU*\u0003\u000f=\u0013H-\u001a:fI*\u0011\u0001+\u000f\t\u0003+\u000ei\u0011!A\u0001\u0007I%t\u0017\u000e\u001e\u0013\u0015\u0003a\u0003\"\u0001O-\n\u0005iK$\u0001B+oSR\fqa\u001c:eS:\fG.F\u0001^!\tqd,\u0003\u0002`]\t\t!,\u0001\u0003oC6,W#\u00012\u0011\u0005y\u001a\u0017B\u00013/\u0005\u0019\u0019FO]5oO\u0006!\u0001.Y:i\u0003\u001dI7/R9vC2$\"\u0001[6\u0011\u0005yJ\u0017B\u00016/\u0005\u0005\u0011\u0005\"\u00027\t\u0001\u0004!\u0016!B8uQ\u0016\u0014\u0018aB2p[B\f\'/\u001a\u000b\u0003_J\u0004\"\u0001\u000f9\n\u0005EL$aA%oi\")1/\u0003a\u0001)\u0006!A\u000f[1u\u0003\u0019\u0019HO]5oO&\u001a1a\u0007\b\u0003\u0005)\u001b8#B\u000e8)b\\\bC\u0001\u001dz\u0013\tQ\u0018HA\u0004Qe>$Wo\u0019;\u0011\u0005%c\u0018BA?T\u00051\u0019VM]5bY&T\u0018M\u00197f)\u0005y\bCA+\u001c\u00035\u0001(o\u001c3vGR\u0004&/\u001a4jqV\u0011\u0011Q\u0001\t\u0005\u0003\u000f\t\t\"\u0004\u0002\u0002\n)!\u00111BA\u0007\u0003\u0011a\u0017M\\4\u000b\u0005\u0005=\u0011\u0001\u00026bm\u0006L1\u0001ZA\u0005\u00031\u0001(o\u001c3vGR\f%/\u001b;z+\u0005y\u0017A\u00049s_\u0012,8\r^#mK6,g\u000e\u001e\u000b\u0005\u00037\t\t\u0003E\u00029\u0003;I1!a\b:\u0005\r\te.\u001f\u0005\t\u0003G\t\u0013\u0011!a\u0001_\u0006\u0019\u0001\u0010J\u0019\u0002\u001fA\u0014x\u000eZ;di&#XM]1u_J,\"!!\u000b\u0011\r\u0005-\u0012\u0011GA\u000e\u001b\t\tiCC\u0002\u00020e\n!bY8mY\u0016\u001cG/[8o\u0013\u0011\t\u0019$!\f\u0003\u0011%#XM]1u_J\f\u0001bY1o\u000bF,\u0018\r\u001c\u000b\u0005\u0003s\ty\u0004E\u00029\u0003wI1!!\u0010:\u0005\u001d\u0011un\u001c7fC:D\u0011\"a\t$\u0003\u0003\u0005\r!a\u0007\u0002\u0011!\f7\u000f[\"pI\u0016$\u0012a\\\u0001\ti>\u001cFO]5oOR\u0011\u0011QA\u0001\roJLG/\u001a*fa2\f7-\u001a\u000b\u0003\u0003\u001b\u0002B!a\u0002\u0002P%!\u0011\u0011KA\u0005\u0005\u0019y%M[3di\n\u0019!J^7\u0014\u000b99D\u000b_>\u0015\u0005\u0005e\u0003CA+\u000f)\u0011\tY\"!\u0018\t\u0011\u0005\rB#!AA\u0002=$B!!\u000f\u0002b!I\u00111\u0005\f\u0002\u0002\u0003\u0007\u00111D\u0001\u0007Eft\u0015-\\3\u0015\t\u0005\u001d\u0014Q\u000e\t\u0005}\u0005%D+C\u0002\u0002l9\u0012aa\u00149uS>t\u0007\"\u00021\f\u0001\u0004\u0011\u0017!\u00032z\u001fJ$\u0017N\\1m)\u0011\t9\'a\u001d\t\r\u0005UD\u00021\u0001^\u0003\u0005q\u0017a\u0001&w[\u0006\u0011!j]\u0001\u000e]VlwJZ#mK6,g\u000e^:\u0002\u001d9,Xn\u00144FY\u0016lWM\u001c;tA\u0005AQ\r\\3nK:$8/\u0006\u0002\u0002\u0004B)\u0011QQAI):!\u0011qQAH\u001d\u0011\tI)!$\u000f\u0007-\u000bY)C\u00012\u0013\ty\u0003\'\u0003\u0002Q]%!\u00111SAK\u0005\rI5KW\u0005\u0005\u0003/\u000bIJ\u0001\u0007QC\u000e\\\u0017mZ3Ue\u0006LGOC\u0002\u0002\u001c:\n\u0011\u0002J5oi\u0016\u0014h.\u00197\u0002\u0013\u0015dW-\\3oiN\u0004\u0003fA\u0001\u0002\"B\u0019a(a)\n\u0007\u0005\u0015fF\u0001\u0003f]Vl\u0007f\u0001\u0001\u0002\"\u0002"
    )
  ScalaSig: length = 0x3 (unknown attribute)
   05 02 00
