Classfile /Users/mw/Projects/slang-braindump/.jar/jar11/assemble/slang-braindump/assemble/content/org/scalactic/anyvals/CompileTimeAssertions$.class
  Last modified May 29, 2022; size 2897 bytes
  SHA-256 checksum 70c40a51d8cb6e5850c917fda606780b6e3c3a8f8d1f888c3732be51fbb6680c
  Compiled from "CompileTimeAssertions.scala"
public final class org.scalactic.anyvals.CompileTimeAssertions$ implements org.scalactic.anyvals.CompileTimeAssertions
  minor version: 0
  major version: 52
  flags: (0x0031) ACC_PUBLIC, ACC_FINAL, ACC_SUPER
  this_class: #2                          // org/scalactic/anyvals/CompileTimeAssertions$
  super_class: #4                         // java/lang/Object
  interfaces: 1, fields: 1, methods: 8, attributes: 4
Constant pool:
   #1 = Utf8               org/scalactic/anyvals/CompileTimeAssertions$
   #2 = Class              #1             // org/scalactic/anyvals/CompileTimeAssertions$
   #3 = Utf8               java/lang/Object
   #4 = Class              #3             // java/lang/Object
   #5 = Utf8               org/scalactic/anyvals/CompileTimeAssertions
   #6 = Class              #5             // org/scalactic/anyvals/CompileTimeAssertions
   #7 = Utf8               CompileTimeAssertions.scala
   #8 = Utf8               scala/reflect/api/Exprs$Expr
   #9 = Class              #8             // scala/reflect/api/Exprs$Expr
  #10 = Utf8               scala/reflect/api/Exprs
  #11 = Class              #10            // scala/reflect/api/Exprs
  #12 = Utf8               Expr
  #13 = Utf8               MODULE$
  #14 = Utf8               Lorg/scalactic/anyvals/CompileTimeAssertions$;
  #15 = Utf8               <clinit>
  #16 = Utf8               ()V
  #17 = Utf8               <init>
  #18 = NameAndType        #17:#16        // "<init>":()V
  #19 = Methodref          #2.#18         // org/scalactic/anyvals/CompileTimeAssertions$."<init>":()V
  #20 = NameAndType        #13:#14        // MODULE$:Lorg/scalactic/anyvals/CompileTimeAssertions$;
  #21 = Fieldref           #2.#20         // org/scalactic/anyvals/CompileTimeAssertions$.MODULE$:Lorg/scalactic/anyvals/CompileTimeAssertions$;
  #22 = Utf8               $init$
  #23 = Utf8               (Lorg/scalactic/anyvals/CompileTimeAssertions;)V
  #24 = NameAndType        #22:#23        // $init$:(Lorg/scalactic/anyvals/CompileTimeAssertions;)V
  #25 = InterfaceMethodref #6.#24         // org/scalactic/anyvals/CompileTimeAssertions.$init$:(Lorg/scalactic/anyvals/CompileTimeAssertions;)V
  #26 = Utf8               ensureValidIntLiteral
  #27 = Utf8               (Lscala/reflect/macros/whitebox/Context;Lscala/reflect/api/Exprs$Expr;Ljava/lang/String;Ljava/lang/String;Lscala/Function1;)V
  #28 = Utf8               (Lscala/reflect/macros/whitebox/Context;Lscala/reflect/api/Exprs$Expr<Ljava/lang/Object;>;Ljava/lang/String;Ljava/lang/String;Lscala/Function1<Ljava/lang/Object;Ljava/lang/Object;>;)V
  #29 = Utf8               c
  #30 = Utf8               value
  #31 = Utf8               notValidMsg
  #32 = Utf8               notLiteralMsg
  #33 = Utf8               isValid
  #34 = Utf8               ensureValidIntLiteral$
  #35 = Utf8               (Lorg/scalactic/anyvals/CompileTimeAssertions;Lscala/reflect/macros/whitebox/Context;Lscala/reflect/api/Exprs$Expr;Ljava/lang/String;Ljava/lang/String;Lscala/Function1;)V
  #36 = NameAndType        #34:#35        // ensureValidIntLiteral$:(Lorg/scalactic/anyvals/CompileTimeAssertions;Lscala/reflect/macros/whitebox/Context;Lscala/reflect/api/Exprs$Expr;Ljava/lang/String;Ljava/lang/String;Lscala/Function1;)V
  #37 = InterfaceMethodref #6.#36         // org/scalactic/anyvals/CompileTimeAssertions.ensureValidIntLiteral$:(Lorg/scalactic/anyvals/CompileTimeAssertions;Lscala/reflect/macros/whitebox/Context;Lscala/reflect/api/Exprs$Expr;Ljava/lang/String;Ljava/lang/String;Lscala/Function1;)V
  #38 = Utf8               this
  #39 = Utf8               Lscala/reflect/macros/whitebox/Context;
  #40 = Utf8               Lscala/reflect/api/Exprs$Expr;
  #41 = Utf8               Ljava/lang/String;
  #42 = Utf8               Lscala/Function1;
  #43 = Utf8               ensureValidLongLiteral
  #44 = Utf8               ensureValidLongLiteral$
  #45 = NameAndType        #44:#35        // ensureValidLongLiteral$:(Lorg/scalactic/anyvals/CompileTimeAssertions;Lscala/reflect/macros/whitebox/Context;Lscala/reflect/api/Exprs$Expr;Ljava/lang/String;Ljava/lang/String;Lscala/Function1;)V
  #46 = InterfaceMethodref #6.#45         // org/scalactic/anyvals/CompileTimeAssertions.ensureValidLongLiteral$:(Lorg/scalactic/anyvals/CompileTimeAssertions;Lscala/reflect/macros/whitebox/Context;Lscala/reflect/api/Exprs$Expr;Ljava/lang/String;Ljava/lang/String;Lscala/Function1;)V
  #47 = Utf8               ensureValidFloatLiteral
  #48 = Utf8               ensureValidFloatLiteral$
  #49 = NameAndType        #48:#35        // ensureValidFloatLiteral$:(Lorg/scalactic/anyvals/CompileTimeAssertions;Lscala/reflect/macros/whitebox/Context;Lscala/reflect/api/Exprs$Expr;Ljava/lang/String;Ljava/lang/String;Lscala/Function1;)V
  #50 = InterfaceMethodref #6.#49         // org/scalactic/anyvals/CompileTimeAssertions.ensureValidFloatLiteral$:(Lorg/scalactic/anyvals/CompileTimeAssertions;Lscala/reflect/macros/whitebox/Context;Lscala/reflect/api/Exprs$Expr;Ljava/lang/String;Ljava/lang/String;Lscala/Function1;)V
  #51 = Utf8               ensureValidDoubleLiteral
  #52 = Utf8               ensureValidDoubleLiteral$
  #53 = NameAndType        #52:#35        // ensureValidDoubleLiteral$:(Lorg/scalactic/anyvals/CompileTimeAssertions;Lscala/reflect/macros/whitebox/Context;Lscala/reflect/api/Exprs$Expr;Ljava/lang/String;Ljava/lang/String;Lscala/Function1;)V
  #54 = InterfaceMethodref #6.#53         // org/scalactic/anyvals/CompileTimeAssertions.ensureValidDoubleLiteral$:(Lorg/scalactic/anyvals/CompileTimeAssertions;Lscala/reflect/macros/whitebox/Context;Lscala/reflect/api/Exprs$Expr;Ljava/lang/String;Ljava/lang/String;Lscala/Function1;)V
  #55 = Utf8               ensureValidStringLiteral
  #56 = Utf8               (Lscala/reflect/macros/whitebox/Context;Lscala/reflect/api/Exprs$Expr<Ljava/lang/String;>;Ljava/lang/String;Ljava/lang/String;Lscala/Function1<Ljava/lang/String;Ljava/lang/Object;>;)V
  #57 = Utf8               ensureValidStringLiteral$
  #58 = NameAndType        #57:#35        // ensureValidStringLiteral$:(Lorg/scalactic/anyvals/CompileTimeAssertions;Lscala/reflect/macros/whitebox/Context;Lscala/reflect/api/Exprs$Expr;Ljava/lang/String;Ljava/lang/String;Lscala/Function1;)V
  #59 = InterfaceMethodref #6.#58         // org/scalactic/anyvals/CompileTimeAssertions.ensureValidStringLiteral$:(Lorg/scalactic/anyvals/CompileTimeAssertions;Lscala/reflect/macros/whitebox/Context;Lscala/reflect/api/Exprs$Expr;Ljava/lang/String;Ljava/lang/String;Lscala/Function1;)V
  #60 = Utf8               ensureValidCharLiteral
  #61 = Utf8               ensureValidCharLiteral$
  #62 = NameAndType        #61:#35        // ensureValidCharLiteral$:(Lorg/scalactic/anyvals/CompileTimeAssertions;Lscala/reflect/macros/whitebox/Context;Lscala/reflect/api/Exprs$Expr;Ljava/lang/String;Ljava/lang/String;Lscala/Function1;)V
  #63 = InterfaceMethodref #6.#62         // org/scalactic/anyvals/CompileTimeAssertions.ensureValidCharLiteral$:(Lorg/scalactic/anyvals/CompileTimeAssertions;Lscala/reflect/macros/whitebox/Context;Lscala/reflect/api/Exprs$Expr;Ljava/lang/String;Ljava/lang/String;Lscala/Function1;)V
  #64 = Methodref          #4.#18         // java/lang/Object."<init>":()V
  #65 = Utf8               Code
  #66 = Utf8               LineNumberTable
  #67 = Utf8               LocalVariableTable
  #68 = Utf8               Signature
  #69 = Utf8               MethodParameters
  #70 = Utf8               InnerClasses
  #71 = Utf8               SourceFile
  #72 = Utf8               ScalaInlineInfo
  #73 = Utf8               Scala
{
  public static final org.scalactic.anyvals.CompileTimeAssertions$ MODULE$;
    descriptor: Lorg/scalactic/anyvals/CompileTimeAssertions$;
    flags: (0x0019) ACC_PUBLIC, ACC_STATIC, ACC_FINAL

  public static {};
    descriptor: ()V
    flags: (0x0009) ACC_PUBLIC, ACC_STATIC
    Code:
      stack=2, locals=0, args_size=0
         0: new           #2                  // class org/scalactic/anyvals/CompileTimeAssertions$
         3: dup
         4: invokespecial #19                 // Method "<init>":()V
         7: putstatic     #21                 // Field MODULE$:Lorg/scalactic/anyvals/CompileTimeAssertions$;
        10: getstatic     #21                 // Field MODULE$:Lorg/scalactic/anyvals/CompileTimeAssertions$;
        13: invokestatic  #25                 // InterfaceMethod org/scalactic/anyvals/CompileTimeAssertions.$init$:(Lorg/scalactic/anyvals/CompileTimeAssertions;)V
        16: return
      LineNumberTable:
        line 401: 0

  public void ensureValidIntLiteral(scala.reflect.macros.whitebox.Context, scala.reflect.api.Exprs$Expr<java.lang.Object>, java.lang.String, java.lang.String, scala.Function1<java.lang.Object, java.lang.Object>);
    descriptor: (Lscala/reflect/macros/whitebox/Context;Lscala/reflect/api/Exprs$Expr;Ljava/lang/String;Ljava/lang/String;Lscala/Function1;)V
    flags: (0x0001) ACC_PUBLIC
    Code:
      stack=6, locals=6, args_size=6
         0: aload_0
         1: aload_1
         2: aload_2
         3: aload_3
         4: aload         4
         6: aload         5
         8: invokestatic  #37                 // InterfaceMethod org/scalactic/anyvals/CompileTimeAssertions.ensureValidIntLiteral$:(Lorg/scalactic/anyvals/CompileTimeAssertions;Lscala/reflect/macros/whitebox/Context;Lscala/reflect/api/Exprs$Expr;Ljava/lang/String;Ljava/lang/String;Lscala/Function1;)V
        11: return
      LineNumberTable:
        line 401: 0
      LocalVariableTable:
        Start  Length  Slot  Name   Signature
            0      12     0  this   Lorg/scalactic/anyvals/CompileTimeAssertions$;
            0      12     1     c   Lscala/reflect/macros/whitebox/Context;
            0      12     2 value   Lscala/reflect/api/Exprs$Expr;
            0      12     3 notValidMsg   Ljava/lang/String;
            0      12     4 notLiteralMsg   Ljava/lang/String;
            0      12     5 isValid   Lscala/Function1;
    Signature: #28                          // (Lscala/reflect/macros/whitebox/Context;Lscala/reflect/api/Exprs$Expr<Ljava/lang/Object;>;Ljava/lang/String;Ljava/lang/String;Lscala/Function1<Ljava/lang/Object;Ljava/lang/Object;>;)V
    MethodParameters:
      Name                           Flags
      c                              final
      value                          final
      notValidMsg                    final
      notLiteralMsg                  final
      isValid                        final

  public void ensureValidLongLiteral(scala.reflect.macros.whitebox.Context, scala.reflect.api.Exprs$Expr<java.lang.Object>, java.lang.String, java.lang.String, scala.Function1<java.lang.Object, java.lang.Object>);
    descriptor: (Lscala/reflect/macros/whitebox/Context;Lscala/reflect/api/Exprs$Expr;Ljava/lang/String;Ljava/lang/String;Lscala/Function1;)V
    flags: (0x0001) ACC_PUBLIC
    Code:
      stack=6, locals=6, args_size=6
         0: aload_0
         1: aload_1
         2: aload_2
         3: aload_3
         4: aload         4
         6: aload         5
         8: invokestatic  #46                 // InterfaceMethod org/scalactic/anyvals/CompileTimeAssertions.ensureValidLongLiteral$:(Lorg/scalactic/anyvals/CompileTimeAssertions;Lscala/reflect/macros/whitebox/Context;Lscala/reflect/api/Exprs$Expr;Ljava/lang/String;Ljava/lang/String;Lscala/Function1;)V
        11: return
      LineNumberTable:
        line 401: 0
      LocalVariableTable:
        Start  Length  Slot  Name   Signature
            0      12     0  this   Lorg/scalactic/anyvals/CompileTimeAssertions$;
            0      12     1     c   Lscala/reflect/macros/whitebox/Context;
            0      12     2 value   Lscala/reflect/api/Exprs$Expr;
            0      12     3 notValidMsg   Ljava/lang/String;
            0      12     4 notLiteralMsg   Ljava/lang/String;
            0      12     5 isValid   Lscala/Function1;
    Signature: #28                          // (Lscala/reflect/macros/whitebox/Context;Lscala/reflect/api/Exprs$Expr<Ljava/lang/Object;>;Ljava/lang/String;Ljava/lang/String;Lscala/Function1<Ljava/lang/Object;Ljava/lang/Object;>;)V
    MethodParameters:
      Name                           Flags
      c                              final
      value                          final
      notValidMsg                    final
      notLiteralMsg                  final
      isValid                        final

  public void ensureValidFloatLiteral(scala.reflect.macros.whitebox.Context, scala.reflect.api.Exprs$Expr<java.lang.Object>, java.lang.String, java.lang.String, scala.Function1<java.lang.Object, java.lang.Object>);
    descriptor: (Lscala/reflect/macros/whitebox/Context;Lscala/reflect/api/Exprs$Expr;Ljava/lang/String;Ljava/lang/String;Lscala/Function1;)V
    flags: (0x0001) ACC_PUBLIC
    Code:
      stack=6, locals=6, args_size=6
         0: aload_0
         1: aload_1
         2: aload_2
         3: aload_3
         4: aload         4
         6: aload         5
         8: invokestatic  #50                 // InterfaceMethod org/scalactic/anyvals/CompileTimeAssertions.ensureValidFloatLiteral$:(Lorg/scalactic/anyvals/CompileTimeAssertions;Lscala/reflect/macros/whitebox/Context;Lscala/reflect/api/Exprs$Expr;Ljava/lang/String;Ljava/lang/String;Lscala/Function1;)V
        11: return
      LineNumberTable:
        line 401: 0
      LocalVariableTable:
        Start  Length  Slot  Name   Signature
            0      12     0  this   Lorg/scalactic/anyvals/CompileTimeAssertions$;
            0      12     1     c   Lscala/reflect/macros/whitebox/Context;
            0      12     2 value   Lscala/reflect/api/Exprs$Expr;
            0      12     3 notValidMsg   Ljava/lang/String;
            0      12     4 notLiteralMsg   Ljava/lang/String;
            0      12     5 isValid   Lscala/Function1;
    Signature: #28                          // (Lscala/reflect/macros/whitebox/Context;Lscala/reflect/api/Exprs$Expr<Ljava/lang/Object;>;Ljava/lang/String;Ljava/lang/String;Lscala/Function1<Ljava/lang/Object;Ljava/lang/Object;>;)V
    MethodParameters:
      Name                           Flags
      c                              final
      value                          final
      notValidMsg                    final
      notLiteralMsg                  final
      isValid                        final

  public void ensureValidDoubleLiteral(scala.reflect.macros.whitebox.Context, scala.reflect.api.Exprs$Expr<java.lang.Object>, java.lang.String, java.lang.String, scala.Function1<java.lang.Object, java.lang.Object>);
    descriptor: (Lscala/reflect/macros/whitebox/Context;Lscala/reflect/api/Exprs$Expr;Ljava/lang/String;Ljava/lang/String;Lscala/Function1;)V
    flags: (0x0001) ACC_PUBLIC
    Code:
      stack=6, locals=6, args_size=6
         0: aload_0
         1: aload_1
         2: aload_2
         3: aload_3
         4: aload         4
         6: aload         5
         8: invokestatic  #54                 // InterfaceMethod org/scalactic/anyvals/CompileTimeAssertions.ensureValidDoubleLiteral$:(Lorg/scalactic/anyvals/CompileTimeAssertions;Lscala/reflect/macros/whitebox/Context;Lscala/reflect/api/Exprs$Expr;Ljava/lang/String;Ljava/lang/String;Lscala/Function1;)V
        11: return
      LineNumberTable:
        line 401: 0
      LocalVariableTable:
        Start  Length  Slot  Name   Signature
            0      12     0  this   Lorg/scalactic/anyvals/CompileTimeAssertions$;
            0      12     1     c   Lscala/reflect/macros/whitebox/Context;
            0      12     2 value   Lscala/reflect/api/Exprs$Expr;
            0      12     3 notValidMsg   Ljava/lang/String;
            0      12     4 notLiteralMsg   Ljava/lang/String;
            0      12     5 isValid   Lscala/Function1;
    Signature: #28                          // (Lscala/reflect/macros/whitebox/Context;Lscala/reflect/api/Exprs$Expr<Ljava/lang/Object;>;Ljava/lang/String;Ljava/lang/String;Lscala/Function1<Ljava/lang/Object;Ljava/lang/Object;>;)V
    MethodParameters:
      Name                           Flags
      c                              final
      value                          final
      notValidMsg                    final
      notLiteralMsg                  final
      isValid                        final

  public void ensureValidStringLiteral(scala.reflect.macros.whitebox.Context, scala.reflect.api.Exprs$Expr<java.lang.String>, java.lang.String, java.lang.String, scala.Function1<java.lang.String, java.lang.Object>);
    descriptor: (Lscala/reflect/macros/whitebox/Context;Lscala/reflect/api/Exprs$Expr;Ljava/lang/String;Ljava/lang/String;Lscala/Function1;)V
    flags: (0x0001) ACC_PUBLIC
    Code:
      stack=6, locals=6, args_size=6
         0: aload_0
         1: aload_1
         2: aload_2
         3: aload_3
         4: aload         4
         6: aload         5
         8: invokestatic  #59                 // InterfaceMethod org/scalactic/anyvals/CompileTimeAssertions.ensureValidStringLiteral$:(Lorg/scalactic/anyvals/CompileTimeAssertions;Lscala/reflect/macros/whitebox/Context;Lscala/reflect/api/Exprs$Expr;Ljava/lang/String;Ljava/lang/String;Lscala/Function1;)V
        11: return
      LineNumberTable:
        line 401: 0
      LocalVariableTable:
        Start  Length  Slot  Name   Signature
            0      12     0  this   Lorg/scalactic/anyvals/CompileTimeAssertions$;
            0      12     1     c   Lscala/reflect/macros/whitebox/Context;
            0      12     2 value   Lscala/reflect/api/Exprs$Expr;
            0      12     3 notValidMsg   Ljava/lang/String;
            0      12     4 notLiteralMsg   Ljava/lang/String;
            0      12     5 isValid   Lscala/Function1;
    Signature: #56                          // (Lscala/reflect/macros/whitebox/Context;Lscala/reflect/api/Exprs$Expr<Ljava/lang/String;>;Ljava/lang/String;Ljava/lang/String;Lscala/Function1<Ljava/lang/String;Ljava/lang/Object;>;)V
    MethodParameters:
      Name                           Flags
      c                              final
      value                          final
      notValidMsg                    final
      notLiteralMsg                  final
      isValid                        final

  public void ensureValidCharLiteral(scala.reflect.macros.whitebox.Context, scala.reflect.api.Exprs$Expr<java.lang.Object>, java.lang.String, java.lang.String, scala.Function1<java.lang.Object, java.lang.Object>);
    descriptor: (Lscala/reflect/macros/whitebox/Context;Lscala/reflect/api/Exprs$Expr;Ljava/lang/String;Ljava/lang/String;Lscala/Function1;)V
    flags: (0x0001) ACC_PUBLIC
    Code:
      stack=6, locals=6, args_size=6
         0: aload_0
         1: aload_1
         2: aload_2
         3: aload_3
         4: aload         4
         6: aload         5
         8: invokestatic  #63                 // InterfaceMethod org/scalactic/anyvals/CompileTimeAssertions.ensureValidCharLiteral$:(Lorg/scalactic/anyvals/CompileTimeAssertions;Lscala/reflect/macros/whitebox/Context;Lscala/reflect/api/Exprs$Expr;Ljava/lang/String;Ljava/lang/String;Lscala/Function1;)V
        11: return
      LineNumberTable:
        line 401: 0
      LocalVariableTable:
        Start  Length  Slot  Name   Signature
            0      12     0  this   Lorg/scalactic/anyvals/CompileTimeAssertions$;
            0      12     1     c   Lscala/reflect/macros/whitebox/Context;
            0      12     2 value   Lscala/reflect/api/Exprs$Expr;
            0      12     3 notValidMsg   Ljava/lang/String;
            0      12     4 notLiteralMsg   Ljava/lang/String;
            0      12     5 isValid   Lscala/Function1;
    Signature: #28                          // (Lscala/reflect/macros/whitebox/Context;Lscala/reflect/api/Exprs$Expr<Ljava/lang/Object;>;Ljava/lang/String;Ljava/lang/String;Lscala/Function1<Ljava/lang/Object;Ljava/lang/Object;>;)V
    MethodParameters:
      Name                           Flags
      c                              final
      value                          final
      notValidMsg                    final
      notLiteralMsg                  final
      isValid                        final

  private org.scalactic.anyvals.CompileTimeAssertions$();
    descriptor: ()V
    flags: (0x0002) ACC_PRIVATE
    Code:
      stack=1, locals=1, args_size=1
         0: aload_0
         1: invokespecial #64                 // Method java/lang/Object."<init>":()V
         4: return
      LineNumberTable:
        line 401: 0
      LocalVariableTable:
        Start  Length  Slot  Name   Signature
            0       5     0  this   Lorg/scalactic/anyvals/CompileTimeAssertions$;
}
InnerClasses:
  public #12= #9 of #11;                  // Expr=class scala/reflect/api/Exprs$Expr of class scala/reflect/api/Exprs
SourceFile: "CompileTimeAssertions.scala"
  ScalaInlineInfo: length = 0x27 (unknown attribute)
   01 01 00 07 00 11 00 10 01 00 3C 00 1B 01 00 33
   00 1B 01 00 2F 00 1B 01 00 1A 00 1B 01 00 2B 00
   1B 01 00 37 00 1B 01
  Scala: length = 0x0 (unknown attribute)

