Classfile /Users/mw/Projects/slang-braindump/.jar/jar11/assemble/slang-braindump/assemble/content/org/scalactic/anyvals/End$.class
  Last modified May 29, 2022; size 1114 bytes
  SHA-256 checksum 83b15fb9793a61e971ab62867c8c2a31962865ceb7245f11fe98b63b62a1a435
  Compiled from "End.scala"
public final class org.scalactic.anyvals.End$
  minor version: 0
  major version: 52
  flags: (0x0031) ACC_PUBLIC, ACC_FINAL, ACC_SUPER
  this_class: #2                          // org/scalactic/anyvals/End$
  super_class: #4                         // java/lang/Object
  interfaces: 0, fields: 1, methods: 4, attributes: 3
Constant pool:
   #1 = Utf8               org/scalactic/anyvals/End$
   #2 = Class              #1             // org/scalactic/anyvals/End$
   #3 = Utf8               java/lang/Object
   #4 = Class              #3             // java/lang/Object
   #5 = Utf8               End.scala
   #6 = Utf8               MODULE$
   #7 = Utf8               Lorg/scalactic/anyvals/End$;
   #8 = Utf8               <clinit>
   #9 = Utf8               ()V
  #10 = Utf8               <init>
  #11 = NameAndType        #10:#9         // "<init>":()V
  #12 = Methodref          #2.#11         // org/scalactic/anyvals/End$."<init>":()V
  #13 = NameAndType        #6:#7          // MODULE$:Lorg/scalactic/anyvals/End$;
  #14 = Fieldref           #2.#13         // org/scalactic/anyvals/End$.MODULE$:Lorg/scalactic/anyvals/End$;
  #15 = Utf8               $colon$colon
  #16 = Utf8               (Ljava/lang/Object;)Lscala/collection/immutable/List;
  #17 = Utf8               <T:Ljava/lang/Object;>(TT;)Lscala/collection/immutable/List<TT;>;
  #18 = Utf8               element
  #19 = Utf8               org/scalactic/anyvals/NonEmptyList$
  #20 = Class              #19            // org/scalactic/anyvals/NonEmptyList$
  #21 = Utf8               Lorg/scalactic/anyvals/NonEmptyList$;
  #22 = NameAndType        #6:#21         // MODULE$:Lorg/scalactic/anyvals/NonEmptyList$;
  #23 = Fieldref           #20.#22        // org/scalactic/anyvals/NonEmptyList$.MODULE$:Lorg/scalactic/anyvals/NonEmptyList$;
  #24 = Utf8               scala/collection/immutable/Nil$
  #25 = Class              #24            // scala/collection/immutable/Nil$
  #26 = Utf8               Lscala/collection/immutable/Nil$;
  #27 = NameAndType        #6:#26         // MODULE$:Lscala/collection/immutable/Nil$;
  #28 = Fieldref           #25.#27        // scala/collection/immutable/Nil$.MODULE$:Lscala/collection/immutable/Nil$;
  #29 = Utf8               apply
  #30 = Utf8               (Ljava/lang/Object;Lscala/collection/immutable/Seq;)Lscala/collection/immutable/List;
  #31 = NameAndType        #29:#30        // apply:(Ljava/lang/Object;Lscala/collection/immutable/Seq;)Lscala/collection/immutable/List;
  #32 = Methodref          #20.#31        // org/scalactic/anyvals/NonEmptyList$.apply:(Ljava/lang/Object;Lscala/collection/immutable/Seq;)Lscala/collection/immutable/List;
  #33 = Utf8               this
  #34 = Utf8               Ljava/lang/Object;
  #35 = Utf8               toString
  #36 = Utf8               ()Ljava/lang/String;
  #37 = Utf8               End
  #38 = String             #37            // End
  #39 = Methodref          #4.#11         // java/lang/Object."<init>":()V
  #40 = Utf8               Code
  #41 = Utf8               LineNumberTable
  #42 = Utf8               LocalVariableTable
  #43 = Utf8               Signature
  #44 = Utf8               MethodParameters
  #45 = Utf8               SourceFile
  #46 = Utf8               ScalaInlineInfo
  #47 = Utf8               Scala
{
  public static final org.scalactic.anyvals.End$ MODULE$;
    descriptor: Lorg/scalactic/anyvals/End$;
    flags: (0x0019) ACC_PUBLIC, ACC_STATIC, ACC_FINAL

  public static {};
    descriptor: ()V
    flags: (0x0009) ACC_PUBLIC, ACC_STATIC
    Code:
      stack=2, locals=0, args_size=0
         0: new           #2                  // class org/scalactic/anyvals/End$
         3: dup
         4: invokespecial #12                 // Method "<init>":()V
         7: putstatic     #14                 // Field MODULE$:Lorg/scalactic/anyvals/End$;
        10: return
      LineNumberTable:
        line 45: 0

  public <T extends java.lang.Object> scala.collection.immutable.List<T> $colon$colon(T);
    descriptor: (Ljava/lang/Object;)Lscala/collection/immutable/List;
    flags: (0x0001) ACC_PUBLIC
    Code:
      stack=3, locals=2, args_size=2
         0: getstatic     #23                 // Field org/scalactic/anyvals/NonEmptyList$.MODULE$:Lorg/scalactic/anyvals/NonEmptyList$;
         3: aload_1
         4: getstatic     #28                 // Field scala/collection/immutable/Nil$.MODULE$:Lscala/collection/immutable/Nil$;
         7: invokevirtual #32                 // Method org/scalactic/anyvals/NonEmptyList$.apply:(Ljava/lang/Object;Lscala/collection/immutable/Seq;)Lscala/collection/immutable/List;
        10: areturn
      LineNumberTable:
        line 60: 0
      LocalVariableTable:
        Start  Length  Slot  Name   Signature
            0      11     0  this   Lorg/scalactic/anyvals/End$;
            0      11     1 element   Ljava/lang/Object;
    Signature: #17                          // <T:Ljava/lang/Object;>(TT;)Lscala/collection/immutable/List<TT;>;
    MethodParameters:
      Name                           Flags
      element                        final

  public java.lang.String toString();
    descriptor: ()Ljava/lang/String;
    flags: (0x0001) ACC_PUBLIC
    Code:
      stack=1, locals=1, args_size=1
         0: ldc           #38                 // String End
         2: areturn
      LineNumberTable:
        line 65: 0
      LocalVariableTable:
        Start  Length  Slot  Name   Signature
            0       3     0  this   Lorg/scalactic/anyvals/End$;

  private org.scalactic.anyvals.End$();
    descriptor: ()V
    flags: (0x0002) ACC_PRIVATE
    Code:
      stack=1, locals=1, args_size=1
         0: aload_0
         1: invokespecial #39                 // Method java/lang/Object."<init>":()V
         4: return
      LineNumberTable:
        line 66: 0
        line 45: 4
      LocalVariableTable:
        Start  Length  Slot  Name   Signature
            0       5     0  this   Lorg/scalactic/anyvals/End$;
}
SourceFile: "End.scala"
  ScalaInlineInfo: length = 0x13 (unknown attribute)
   01 01 00 03 00 0F 00 10 01 00 0A 00 09 01 00 23
   00 24 01
  Scala: length = 0x0 (unknown attribute)

