Classfile /Users/mw/Projects/slang-braindump/.jar/jar11/assemble/slang-braindump/assemble/content/org/scalactic/anyvals/NonEmptyMap$.class
  Last modified May 29, 2022; size 36400 bytes
  SHA-256 checksum a289de0f1c67f6ff7a250b02956c7cb83090b3a5ab044b8747c18f9c8a5ebd29
  Compiled from "NonEmptyMap.scala"
public final class org.scalactic.anyvals.NonEmptyMap$
  minor version: 0
  major version: 52
  flags: (0x0031) ACC_PUBLIC, ACC_FINAL, ACC_SUPER
  this_class: #2                          // org/scalactic/anyvals/NonEmptyMap$
  super_class: #4                         // java/lang/Object
  interfaces: 0, fields: 1, methods: 99, attributes: 5
Constant pool:
    #1 = Utf8               org/scalactic/anyvals/NonEmptyMap$
    #2 = Class              #1            // org/scalactic/anyvals/NonEmptyMap$
    #3 = Utf8               java/lang/Object
    #4 = Class              #3            // java/lang/Object
    #5 = Utf8               NonEmptyMap.scala
    #6 = Utf8               java/lang/invoke/MethodHandles$Lookup
    #7 = Class              #6            // java/lang/invoke/MethodHandles$Lookup
    #8 = Utf8               java/lang/invoke/MethodHandles
    #9 = Class              #8            // java/lang/invoke/MethodHandles
   #10 = Utf8               Lookup
   #11 = Utf8               MODULE$
   #12 = Utf8               Lorg/scalactic/anyvals/NonEmptyMap$;
   #13 = Utf8               <clinit>
   #14 = Utf8               ()V
   #15 = Utf8               <init>
   #16 = NameAndType        #15:#14       // "<init>":()V
   #17 = Methodref          #2.#16        // org/scalactic/anyvals/NonEmptyMap$."<init>":()V
   #18 = NameAndType        #11:#12       // MODULE$:Lorg/scalactic/anyvals/NonEmptyMap$;
   #19 = Fieldref           #2.#18        // org/scalactic/anyvals/NonEmptyMap$.MODULE$:Lorg/scalactic/anyvals/NonEmptyMap$;
   #20 = Utf8               apply
   #21 = Utf8               (Lscala/Tuple2;Lscala/collection/immutable/Seq;)Lscala/collection/immutable/Map;
   #22 = Utf8               <K:Ljava/lang/Object;V:Ljava/lang/Object;>(Lscala/Tuple2<TK;TV;>;Lscala/collection/immutable/Seq<Lscala/Tuple2<TK;TV;>;>;)Lscala/collection/immutable/Map<TK;TV;>;
   #23 = Utf8               firstElement
   #24 = Utf8               otherElements
   #25 = Utf8               scala/$less$colon$less$
   #26 = Class              #25           // scala/$less$colon$less$
   #27 = Utf8               Lscala/$less$colon$less$;
   #28 = NameAndType        #11:#27       // MODULE$:Lscala/$less$colon$less$;
   #29 = Fieldref           #26.#28       // scala/$less$colon$less$.MODULE$:Lscala/$less$colon$less$;
   #30 = Utf8               refl
   #31 = Utf8               ()Lscala/$eq$colon$eq;
   #32 = NameAndType        #30:#31       // refl:()Lscala/$eq$colon$eq;
   #33 = Methodref          #26.#32       // scala/$less$colon$less$.refl:()Lscala/$eq$colon$eq;
   #34 = Utf8               scala/collection/immutable/Seq
   #35 = Class              #34           // scala/collection/immutable/Seq
   #36 = Utf8               toMap
   #37 = Utf8               (Lscala/$less$colon$less;)Lscala/collection/immutable/Map;
   #38 = NameAndType        #36:#37       // toMap:(Lscala/$less$colon$less;)Lscala/collection/immutable/Map;
   #39 = InterfaceMethodref #35.#38       // scala/collection/immutable/Seq.toMap:(Lscala/$less$colon$less;)Lscala/collection/immutable/Map;
   #40 = Utf8               scala/collection/immutable/Map
   #41 = Class              #40           // scala/collection/immutable/Map
   #42 = Utf8               $plus
   #43 = Utf8               (Lscala/Tuple2;)Lscala/collection/immutable/MapOps;
   #44 = NameAndType        #42:#43       // $plus:(Lscala/Tuple2;)Lscala/collection/immutable/MapOps;
   #45 = InterfaceMethodref #41.#44       // scala/collection/immutable/Map.$plus:(Lscala/Tuple2;)Lscala/collection/immutable/MapOps;
   #46 = Utf8               this
   #47 = Utf8               Lscala/Tuple2;
   #48 = Utf8               Lscala/collection/immutable/Seq;
   #49 = Utf8               unapplySeq
   #50 = Utf8               (Lscala/collection/immutable/Map;)Lscala/Option;
   #51 = Utf8               <K:Ljava/lang/Object;V:Ljava/lang/Object;>(Lscala/collection/immutable/Map<TK;TV;>;)Lscala/Option<Lscala/collection/immutable/Seq<Lscala/Tuple2<TK;TV;>;>;>;
   #52 = Utf8               nonEmptyMap
   #53 = Utf8               scala/Some
   #54 = Class              #53           // scala/Some
   #55 = Utf8               toSeq$extension
   #56 = Utf8               (Lscala/collection/immutable/Map;)Lscala/collection/immutable/Seq;
   #57 = NameAndType        #55:#56       // toSeq$extension:(Lscala/collection/immutable/Map;)Lscala/collection/immutable/Seq;
   #58 = Methodref          #2.#57        // org/scalactic/anyvals/NonEmptyMap$.toSeq$extension:(Lscala/collection/immutable/Map;)Lscala/collection/immutable/Seq;
   #59 = Utf8               (Ljava/lang/Object;)V
   #60 = NameAndType        #15:#59       // "<init>":(Ljava/lang/Object;)V
   #61 = Methodref          #54.#60       // scala/Some."<init>":(Ljava/lang/Object;)V
   #62 = Utf8               Lscala/collection/immutable/Map;
   #63 = Utf8               from
   #64 = Utf8               (Lscala/collection/Seq;)Lscala/Option;
   #65 = Utf8               <K:Ljava/lang/Object;V:Ljava/lang/Object;>(Lscala/collection/Seq<Lscala/Tuple2<TK;TV;>;>;)Lscala/Option<Lorg/scalactic/anyvals/NonEmptyMap<TK;TV;>;>;
   #66 = Utf8               seq
   #67 = Utf8               scala/collection/Seq
   #68 = Class              #67           // scala/collection/Seq
   #69 = Utf8               headOption
   #70 = Utf8               ()Lscala/Option;
   #71 = NameAndType        #69:#70       // headOption:()Lscala/Option;
   #72 = InterfaceMethodref #68.#71       // scala/collection/Seq.headOption:()Lscala/Option;
   #73 = Utf8               scala/None$
   #74 = Class              #73           // scala/None$
   #75 = Utf8               Lscala/None$;
   #76 = NameAndType        #11:#75       // MODULE$:Lscala/None$;
   #77 = Fieldref           #74.#76       // scala/None$.MODULE$:Lscala/None$;
   #78 = Utf8               equals
   #79 = Utf8               (Ljava/lang/Object;)Z
   #80 = NameAndType        #78:#79       // equals:(Ljava/lang/Object;)Z
   #81 = Methodref          #4.#80        // java/lang/Object.equals:(Ljava/lang/Object;)Z
   #82 = Utf8               value
   #83 = Utf8               ()Ljava/lang/Object;
   #84 = NameAndType        #82:#83       // value:()Ljava/lang/Object;
   #85 = Methodref          #54.#84       // scala/Some.value:()Ljava/lang/Object;
   #86 = Utf8               scala/Tuple2
   #87 = Class              #86           // scala/Tuple2
   #88 = Utf8               org/scalactic/anyvals/NonEmptyMap
   #89 = Class              #88           // org/scalactic/anyvals/NonEmptyMap
   #90 = Utf8               scala/collection/immutable/Map$
   #91 = Class              #90           // scala/collection/immutable/Map$
   #92 = Utf8               Lscala/collection/immutable/Map$;
   #93 = NameAndType        #11:#92       // MODULE$:Lscala/collection/immutable/Map$;
   #94 = Fieldref           #91.#93       // scala/collection/immutable/Map$.MODULE$:Lscala/collection/immutable/Map$;
   #95 = Utf8               empty
   #96 = Utf8               ()Lscala/collection/immutable/Map;
   #97 = NameAndType        #95:#96       // empty:()Lscala/collection/immutable/Map;
   #98 = Methodref          #91.#97       // scala/collection/immutable/Map$.empty:()Lscala/collection/immutable/Map;
   #99 = Utf8               tail
  #100 = NameAndType        #99:#83       // tail:()Ljava/lang/Object;
  #101 = InterfaceMethodref #68.#100      // scala/collection/Seq.tail:()Ljava/lang/Object;
  #102 = Utf8               scala/collection/IterableOnceOps
  #103 = Class              #102          // scala/collection/IterableOnceOps
  #104 = InterfaceMethodref #103.#38      // scala/collection/IterableOnceOps.toMap:(Lscala/$less$colon$less;)Lscala/collection/immutable/Map;
  #105 = Utf8               $plus$plus
  #106 = Utf8               (Lscala/collection/IterableOnce;)Lscala/collection/IterableOps;
  #107 = NameAndType        #105:#106     // $plus$plus:(Lscala/collection/IterableOnce;)Lscala/collection/IterableOps;
  #108 = InterfaceMethodref #41.#107      // scala/collection/immutable/Map.$plus$plus:(Lscala/collection/IterableOnce;)Lscala/collection/IterableOps;
  #109 = Utf8               scala/collection/immutable/MapOps
  #110 = Class              #109          // scala/collection/immutable/MapOps
  #111 = InterfaceMethodref #110.#44      // scala/collection/immutable/MapOps.$plus:(Lscala/Tuple2;)Lscala/collection/immutable/MapOps;
  #112 = Utf8               (Lscala/collection/immutable/Map;)V
  #113 = NameAndType        #15:#112      // "<init>":(Lscala/collection/immutable/Map;)V
  #114 = Methodref          #89.#113      // org/scalactic/anyvals/NonEmptyMap."<init>":(Lscala/collection/immutable/Map;)V
  #115 = Utf8               scala/MatchError
  #116 = Class              #115          // scala/MatchError
  #117 = Methodref          #116.#60      // scala/MatchError."<init>":(Ljava/lang/Object;)V
  #118 = Utf8               first
  #119 = Utf8               Lscala/collection/Seq;
  #120 = Utf8               scala/Option
  #121 = Class              #120          // scala/Option
  #122 = Utf8               (Lscala/collection/Map;)Lscala/Option;
  #123 = Utf8               <K:Ljava/lang/Object;V:Ljava/lang/Object;>(Lscala/collection/Map<TK;TV;>;)Lscala/Option<Lorg/scalactic/anyvals/NonEmptyMap<TK;TV;>;>;
  #124 = Utf8               map
  #125 = Utf8               scala/collection/Map
  #126 = Class              #125          // scala/collection/Map
  #127 = InterfaceMethodref #126.#71      // scala/collection/Map.headOption:()Lscala/Option;
  #128 = Utf8               Lscala/collection/Map;
  #129 = Utf8               nonEmptyMapToMap
  #130 = Utf8               (Lscala/collection/immutable/Map;)Lscala/collection/immutable/Map;
  #131 = Utf8               <K:Ljava/lang/Object;V:Ljava/lang/Object;>(Lscala/collection/immutable/Map<TK;TV;>;)Lscala/collection/immutable/Map<TK;TV;>;
  #132 = Utf8               $plus$plus$extension
  #133 = Utf8               (Lscala/collection/immutable/Map;Lscala/collection/immutable/Map;)Lscala/collection/immutable/Map;
  #134 = Utf8               <V1:Ljava/lang/Object;K:Ljava/lang/Object;V:Ljava/lang/Object;>(Lscala/collection/immutable/Map<TK;TV;>;Lscala/collection/immutable/Map<TK;TV1;>;)Lscala/collection/immutable/Map<TK;TV1;>;
  #135 = Utf8               $this
  #136 = Utf8               other
  #137 = Utf8               (Lscala/collection/immutable/Map;Lorg/scalactic/Every;)Lscala/collection/immutable/Map;
  #138 = Utf8               <V1:Ljava/lang/Object;K:Ljava/lang/Object;V:Ljava/lang/Object;>(Lscala/collection/immutable/Map<TK;TV;>;Lorg/scalactic/Every<Lscala/Tuple2<TK;TV1;>;>;)Lscala/collection/immutable/Map<TK;TV1;>;
  #139 = Utf8               org/scalactic/Every
  #140 = Class              #139          // org/scalactic/Every
  #141 = Utf8               toVector
  #142 = Utf8               ()Lscala/collection/immutable/Vector;
  #143 = NameAndType        #141:#142     // toVector:()Lscala/collection/immutable/Vector;
  #144 = Methodref          #140.#143     // org/scalactic/Every.toVector:()Lscala/collection/immutable/Vector;
  #145 = Utf8               Lorg/scalactic/Every;
  #146 = Utf8               (Lscala/collection/immutable/Map;Lscala/collection/IterableOnce;)Lscala/collection/immutable/Map;
  #147 = Utf8               <V1:Ljava/lang/Object;K:Ljava/lang/Object;V:Ljava/lang/Object;>(Lscala/collection/immutable/Map<TK;TV;>;Lscala/collection/IterableOnce<Lscala/Tuple2<TK;TV1;>;>;)Lscala/collection/immutable/Map<TK;TV1;>;
  #148 = Utf8               scala/collection/IterableOnceExtensionMethods$
  #149 = Class              #148          // scala/collection/IterableOnceExtensionMethods$
  #150 = Utf8               Lscala/collection/IterableOnceExtensionMethods$;
  #151 = NameAndType        #11:#150      // MODULE$:Lscala/collection/IterableOnceExtensionMethods$;
  #152 = Fieldref           #149.#151     // scala/collection/IterableOnceExtensionMethods$.MODULE$:Lscala/collection/IterableOnceExtensionMethods$;
  #153 = Utf8               scala/collection/IterableOnce$
  #154 = Class              #153          // scala/collection/IterableOnce$
  #155 = Utf8               Lscala/collection/IterableOnce$;
  #156 = NameAndType        #11:#155      // MODULE$:Lscala/collection/IterableOnce$;
  #157 = Fieldref           #154.#156     // scala/collection/IterableOnce$.MODULE$:Lscala/collection/IterableOnce$;
  #158 = Utf8               iterableOnceExtensionMethods
  #159 = Utf8               (Lscala/collection/IterableOnce;)Lscala/collection/IterableOnce;
  #160 = NameAndType        #158:#159     // iterableOnceExtensionMethods:(Lscala/collection/IterableOnce;)Lscala/collection/IterableOnce;
  #161 = Methodref          #154.#160     // scala/collection/IterableOnce$.iterableOnceExtensionMethods:(Lscala/collection/IterableOnce;)Lscala/collection/IterableOnce;
  #162 = Utf8               isEmpty$extension
  #163 = Utf8               (Lscala/collection/IterableOnce;)Z
  #164 = NameAndType        #162:#163     // isEmpty$extension:(Lscala/collection/IterableOnce;)Z
  #165 = Methodref          #149.#164     // scala/collection/IterableOnceExtensionMethods$.isEmpty$extension:(Lscala/collection/IterableOnce;)Z
  #166 = Utf8               toMap$extension
  #167 = Utf8               (Lscala/collection/IterableOnce;Lscala/$less$colon$less;)Lscala/collection/immutable/Map;
  #168 = NameAndType        #166:#167     // toMap$extension:(Lscala/collection/IterableOnce;Lscala/$less$colon$less;)Lscala/collection/immutable/Map;
  #169 = Methodref          #149.#168     // scala/collection/IterableOnceExtensionMethods$.toMap$extension:(Lscala/collection/IterableOnce;Lscala/$less$colon$less;)Lscala/collection/immutable/Map;
  #170 = Utf8               Lscala/collection/IterableOnce;
  #171 = Utf8               $plus$colon$extension
  #172 = Utf8               (Lscala/collection/immutable/Map;Lscala/Tuple2;)Lscala/collection/immutable/Map;
  #173 = Utf8               <V1:Ljava/lang/Object;K:Ljava/lang/Object;V:Ljava/lang/Object;>(Lscala/collection/immutable/Map<TK;TV;>;Lscala/Tuple2<TK;TV1;>;)Lscala/collection/immutable/Map<TK;TV1;>;
  #174 = Utf8               entry
  #175 = Utf8               $plus$plus$colon$extension
  #176 = Utf8               $plus$extension
  #177 = Utf8               (Lscala/collection/immutable/Map;Lscala/collection/immutable/Seq;)Lscala/collection/immutable/Map;
  #178 = Utf8               <V1:Ljava/lang/Object;K:Ljava/lang/Object;V:Ljava/lang/Object;>(Lscala/collection/immutable/Map<TK;TV;>;Lscala/collection/immutable/Seq<Lscala/Tuple2<TK;TV1;>;>;)Lscala/collection/immutable/Map<TK;TV1;>;
  #179 = Utf8               entries
  #180 = Utf8               addString$extension
  #181 = Utf8               (Lscala/collection/immutable/Map;Lscala/collection/mutable/StringBuilder;)Lscala/collection/mutable/StringBuilder;
  #182 = Utf8               <K:Ljava/lang/Object;V:Ljava/lang/Object;>(Lscala/collection/immutable/Map<TK;TV;>;Lscala/collection/mutable/StringBuilder;)Lscala/collection/mutable/StringBuilder;
  #183 = Utf8               sb
  #184 = Utf8               addString
  #185 = Utf8               (Lscala/collection/mutable/StringBuilder;)Lscala/collection/mutable/StringBuilder;
  #186 = NameAndType        #184:#185     // addString:(Lscala/collection/mutable/StringBuilder;)Lscala/collection/mutable/StringBuilder;
  #187 = InterfaceMethodref #41.#186      // scala/collection/immutable/Map.addString:(Lscala/collection/mutable/StringBuilder;)Lscala/collection/mutable/StringBuilder;
  #188 = Utf8               Lscala/collection/mutable/StringBuilder;
  #189 = Utf8               (Lscala/collection/immutable/Map;Lscala/collection/mutable/StringBuilder;Ljava/lang/String;)Lscala/collection/mutable/StringBuilder;
  #190 = Utf8               <K:Ljava/lang/Object;V:Ljava/lang/Object;>(Lscala/collection/immutable/Map<TK;TV;>;Lscala/collection/mutable/StringBuilder;Ljava/lang/String;)Lscala/collection/mutable/StringBuilder;
  #191 = Utf8               sep
  #192 = Utf8               (Lscala/collection/mutable/StringBuilder;Ljava/lang/String;)Lscala/collection/mutable/StringBuilder;
  #193 = NameAndType        #184:#192     // addString:(Lscala/collection/mutable/StringBuilder;Ljava/lang/String;)Lscala/collection/mutable/StringBuilder;
  #194 = InterfaceMethodref #41.#193      // scala/collection/immutable/Map.addString:(Lscala/collection/mutable/StringBuilder;Ljava/lang/String;)Lscala/collection/mutable/StringBuilder;
  #195 = Utf8               Ljava/lang/String;
  #196 = Utf8               (Lscala/collection/immutable/Map;Lscala/collection/mutable/StringBuilder;Ljava/lang/String;Ljava/lang/String;Ljava/lang/String;)Lscala/collection/mutable/StringBuilder;
  #197 = Utf8               <K:Ljava/lang/Object;V:Ljava/lang/Object;>(Lscala/collection/immutable/Map<TK;TV;>;Lscala/collection/mutable/StringBuilder;Ljava/lang/String;Ljava/lang/String;Ljava/lang/String;)Lscala/collection/mutable/StringBuilder;
  #198 = Utf8               start
  #199 = Utf8               end
  #200 = Utf8               (Lscala/collection/mutable/StringBuilder;Ljava/lang/String;Ljava/lang/String;Ljava/lang/String;)Lscala/collection/mutable/StringBuilder;
  #201 = NameAndType        #184:#200     // addString:(Lscala/collection/mutable/StringBuilder;Ljava/lang/String;Ljava/lang/String;Ljava/lang/String;)Lscala/collection/mutable/StringBuilder;
  #202 = InterfaceMethodref #41.#201      // scala/collection/immutable/Map.addString:(Lscala/collection/mutable/StringBuilder;Ljava/lang/String;Ljava/lang/String;Ljava/lang/String;)Lscala/collection/mutable/StringBuilder;
  #203 = Utf8               apply$extension
  #204 = Utf8               (Lscala/collection/immutable/Map;Ljava/lang/Object;)Ljava/lang/Object;
  #205 = Utf8               <K:Ljava/lang/Object;V:Ljava/lang/Object;>(Lscala/collection/immutable/Map<TK;TV;>;TK;)TV;
  #206 = Utf8               k
  #207 = Utf8               (Ljava/lang/Object;)Ljava/lang/Object;
  #208 = NameAndType        #20:#207      // apply:(Ljava/lang/Object;)Ljava/lang/Object;
  #209 = InterfaceMethodref #41.#208      // scala/collection/immutable/Map.apply:(Ljava/lang/Object;)Ljava/lang/Object;
  #210 = Utf8               Ljava/lang/Object;
  #211 = Utf8               collectFirst$extension
  #212 = Utf8               (Lscala/collection/immutable/Map;Lscala/PartialFunction;)Lscala/Option;
  #213 = Utf8               <U:Ljava/lang/Object;K:Ljava/lang/Object;V:Ljava/lang/Object;>(Lscala/collection/immutable/Map<TK;TV;>;Lscala/PartialFunction<Lscala/Tuple2<TK;TV;>;TU;>;)Lscala/Option<TU;>;
  #214 = Utf8               pf
  #215 = Utf8               collectFirst
  #216 = Utf8               (Lscala/PartialFunction;)Lscala/Option;
  #217 = NameAndType        #215:#216     // collectFirst:(Lscala/PartialFunction;)Lscala/Option;
  #218 = InterfaceMethodref #41.#217      // scala/collection/immutable/Map.collectFirst:(Lscala/PartialFunction;)Lscala/Option;
  #219 = Utf8               Lscala/PartialFunction;
  #220 = Utf8               contains$extension
  #221 = Utf8               (Lscala/collection/immutable/Map;Ljava/lang/Object;)Z
  #222 = Utf8               <K:Ljava/lang/Object;V:Ljava/lang/Object;>(Lscala/collection/immutable/Map<TK;TV;>;TK;)Z
  #223 = Utf8               key
  #224 = Utf8               contains
  #225 = NameAndType        #224:#79      // contains:(Ljava/lang/Object;)Z
  #226 = InterfaceMethodref #41.#225      // scala/collection/immutable/Map.contains:(Ljava/lang/Object;)Z
  #227 = Utf8               copyToArray$extension
  #228 = Utf8               (Lscala/collection/immutable/Map;[Lscala/Tuple2;)V
  #229 = Utf8               <V1:Ljava/lang/Object;K:Ljava/lang/Object;V:Ljava/lang/Object;>(Lscala/collection/immutable/Map<TK;TV;>;[Lscala/Tuple2<TK;TV1;>;)V
  #230 = Utf8               arr
  #231 = Utf8               copyToArray
  #232 = Utf8               (Ljava/lang/Object;)I
  #233 = NameAndType        #231:#232     // copyToArray:(Ljava/lang/Object;)I
  #234 = InterfaceMethodref #41.#233      // scala/collection/immutable/Map.copyToArray:(Ljava/lang/Object;)I
  #235 = Utf8               [Lscala/Tuple2;
  #236 = Utf8               (Lscala/collection/immutable/Map;[Lscala/Tuple2;I)V
  #237 = Utf8               <V1:Ljava/lang/Object;K:Ljava/lang/Object;V:Ljava/lang/Object;>(Lscala/collection/immutable/Map<TK;TV;>;[Lscala/Tuple2<TK;TV1;>;I)V
  #238 = Utf8               (Ljava/lang/Object;I)I
  #239 = NameAndType        #231:#238     // copyToArray:(Ljava/lang/Object;I)I
  #240 = InterfaceMethodref #41.#239      // scala/collection/immutable/Map.copyToArray:(Ljava/lang/Object;I)I
  #241 = Utf8               I
  #242 = Utf8               (Lscala/collection/immutable/Map;[Lscala/Tuple2;II)V
  #243 = Utf8               <V1:Ljava/lang/Object;K:Ljava/lang/Object;V:Ljava/lang/Object;>(Lscala/collection/immutable/Map<TK;TV;>;[Lscala/Tuple2<TK;TV1;>;II)V
  #244 = Utf8               len
  #245 = Utf8               (Ljava/lang/Object;II)I
  #246 = NameAndType        #231:#245     // copyToArray:(Ljava/lang/Object;II)I
  #247 = InterfaceMethodref #41.#246      // scala/collection/immutable/Map.copyToArray:(Ljava/lang/Object;II)I
  #248 = Utf8               copyToBuffer$extension
  #249 = Utf8               (Lscala/collection/immutable/Map;Lscala/collection/mutable/Buffer;)V
  #250 = Utf8               <V1:Ljava/lang/Object;K:Ljava/lang/Object;V:Ljava/lang/Object;>(Lscala/collection/immutable/Map<TK;TV;>;Lscala/collection/mutable/Buffer<Lscala/Tuple2<TK;TV1;>;>;)V
  #251 = Utf8               buf
  #252 = Utf8               copyToBuffer
  #253 = Utf8               (Lscala/collection/mutable/Buffer;)V
  #254 = NameAndType        #252:#253     // copyToBuffer:(Lscala/collection/mutable/Buffer;)V
  #255 = InterfaceMethodref #41.#254      // scala/collection/immutable/Map.copyToBuffer:(Lscala/collection/mutable/Buffer;)V
  #256 = Utf8               Lscala/collection/mutable/Buffer;
  #257 = Utf8               count$extension
  #258 = Utf8               (Lscala/collection/immutable/Map;Lscala/Function1;)I
  #259 = Utf8               <K:Ljava/lang/Object;V:Ljava/lang/Object;>(Lscala/collection/immutable/Map<TK;TV;>;Lscala/Function1<Lscala/Tuple2<TK;TV;>;Ljava/lang/Object;>;)I
  #260 = Utf8               p
  #261 = Utf8               count
  #262 = Utf8               (Lscala/Function1;)I
  #263 = NameAndType        #261:#262     // count:(Lscala/Function1;)I
  #264 = InterfaceMethodref #41.#263      // scala/collection/immutable/Map.count:(Lscala/Function1;)I
  #265 = Utf8               Lscala/Function1;
  #266 = Utf8               exists$extension
  #267 = Utf8               (Lscala/collection/immutable/Map;Lscala/Function1;)Z
  #268 = Utf8               <K:Ljava/lang/Object;V:Ljava/lang/Object;>(Lscala/collection/immutable/Map<TK;TV;>;Lscala/Function1<Lscala/Tuple2<TK;TV;>;Ljava/lang/Object;>;)Z
  #269 = Utf8               exists
  #270 = Utf8               (Lscala/Function1;)Z
  #271 = NameAndType        #269:#270     // exists:(Lscala/Function1;)Z
  #272 = InterfaceMethodref #41.#271      // scala/collection/immutable/Map.exists:(Lscala/Function1;)Z
  #273 = Utf8               find$extension
  #274 = Utf8               (Lscala/collection/immutable/Map;Lscala/Function1;)Lscala/Option;
  #275 = Utf8               <K:Ljava/lang/Object;V:Ljava/lang/Object;>(Lscala/collection/immutable/Map<TK;TV;>;Lscala/Function1<Lscala/Tuple2<TK;TV;>;Ljava/lang/Object;>;)Lscala/Option<Lscala/Tuple2<TK;TV;>;>;
  #276 = Utf8               find
  #277 = Utf8               (Lscala/Function1;)Lscala/Option;
  #278 = NameAndType        #276:#277     // find:(Lscala/Function1;)Lscala/Option;
  #279 = InterfaceMethodref #41.#278      // scala/collection/immutable/Map.find:(Lscala/Function1;)Lscala/Option;
  #280 = Utf8               flatMap$extension
  #281 = Utf8               (Lscala/collection/immutable/Map;Lscala/Function1;)Lscala/collection/immutable/Map;
  #282 = Utf8               <K1:Ljava/lang/Object;V1:Ljava/lang/Object;K:Ljava/lang/Object;V:Ljava/lang/Object;>(Lscala/collection/immutable/Map<TK;TV;>;Lscala/Function1<Lscala/Tuple2<TK;TV;>;Lorg/scalactic/anyvals/NonEmptyMap<TK1;TV1;>;>;)Lscala/collection/immutable/Map<TK1;TV1;>;
  #283 = Utf8               f
  #284 = Utf8               scala/collection/mutable/ArrayBuffer
  #285 = Class              #284          // scala/collection/mutable/ArrayBuffer
  #286 = Methodref          #285.#16      // scala/collection/mutable/ArrayBuffer."<init>":()V
  #287 = MethodType         #207          //  (Ljava/lang/Object;)Ljava/lang/Object;
  #288 = Utf8               $anonfun$flatMap$1
  #289 = Utf8               (Lscala/collection/mutable/ArrayBuffer;Lscala/Function1;Lscala/Tuple2;)Lscala/collection/mutable/ArrayBuffer;
  #290 = NameAndType        #288:#289     // $anonfun$flatMap$1:(Lscala/collection/mutable/ArrayBuffer;Lscala/Function1;Lscala/Tuple2;)Lscala/collection/mutable/ArrayBuffer;
  #291 = Methodref          #2.#290       // org/scalactic/anyvals/NonEmptyMap$.$anonfun$flatMap$1:(Lscala/collection/mutable/ArrayBuffer;Lscala/Function1;Lscala/Tuple2;)Lscala/collection/mutable/ArrayBuffer;
  #292 = MethodHandle       6:#291        // REF_invokeStatic org/scalactic/anyvals/NonEmptyMap$.$anonfun$flatMap$1:(Lscala/collection/mutable/ArrayBuffer;Lscala/Function1;Lscala/Tuple2;)Lscala/collection/mutable/ArrayBuffer;
  #293 = Utf8               (Lscala/Tuple2;)Lscala/collection/mutable/ArrayBuffer;
  #294 = MethodType         #293          //  (Lscala/Tuple2;)Lscala/collection/mutable/ArrayBuffer;
  #295 = Integer            5
  #296 = Integer            1
  #297 = Utf8               java/lang/invoke/LambdaMetafactory
  #298 = Class              #297          // java/lang/invoke/LambdaMetafactory
  #299 = Utf8               altMetafactory
  #300 = Utf8               (Ljava/lang/invoke/MethodHandles$Lookup;Ljava/lang/String;Ljava/lang/invoke/MethodType;[Ljava/lang/Object;)Ljava/lang/invoke/CallSite;
  #301 = NameAndType        #299:#300     // altMetafactory:(Ljava/lang/invoke/MethodHandles$Lookup;Ljava/lang/String;Ljava/lang/invoke/MethodType;[Ljava/lang/Object;)Ljava/lang/invoke/CallSite;
  #302 = Methodref          #298.#301     // java/lang/invoke/LambdaMetafactory.altMetafactory:(Ljava/lang/invoke/MethodHandles$Lookup;Ljava/lang/String;Ljava/lang/invoke/MethodType;[Ljava/lang/Object;)Ljava/lang/invoke/CallSite;
  #303 = MethodHandle       6:#302        // REF_invokeStatic java/lang/invoke/LambdaMetafactory.altMetafactory:(Ljava/lang/invoke/MethodHandles$Lookup;Ljava/lang/String;Ljava/lang/invoke/MethodType;[Ljava/lang/Object;)Ljava/lang/invoke/CallSite;
  #304 = Utf8               (Lscala/collection/mutable/ArrayBuffer;Lscala/Function1;)Lscala/Function1;
  #305 = NameAndType        #20:#304      // apply:(Lscala/collection/mutable/ArrayBuffer;Lscala/Function1;)Lscala/Function1;
  #306 = InvokeDynamic      #0:#305       // #0:apply:(Lscala/collection/mutable/ArrayBuffer;Lscala/Function1;)Lscala/Function1;
  #307 = Utf8               foreach
  #308 = Utf8               (Lscala/Function1;)V
  #309 = NameAndType        #307:#308     // foreach:(Lscala/Function1;)V
  #310 = InterfaceMethodref #41.#309      // scala/collection/immutable/Map.foreach:(Lscala/Function1;)V
  #311 = Methodref          #285.#38      // scala/collection/mutable/ArrayBuffer.toMap:(Lscala/$less$colon$less;)Lscala/collection/immutable/Map;
  #312 = Utf8               Lscala/collection/mutable/ArrayBuffer;
  #313 = Utf8               fold$extension
  #314 = Utf8               (Lscala/collection/immutable/Map;Ljava/lang/Object;Lscala/Function2;)Ljava/lang/Object;
  #315 = Utf8               <U:Ljava/lang/Object;K:Ljava/lang/Object;V:Ljava/lang/Object;>(Lscala/collection/immutable/Map<TK;TV;>;TU;Lscala/Function2<TU;TU;TU;>;)TU;
  #316 = Utf8               z
  #317 = Utf8               op
  #318 = Utf8               fold
  #319 = Utf8               (Ljava/lang/Object;Lscala/Function2;)Ljava/lang/Object;
  #320 = NameAndType        #318:#319     // fold:(Ljava/lang/Object;Lscala/Function2;)Ljava/lang/Object;
  #321 = InterfaceMethodref #41.#320      // scala/collection/immutable/Map.fold:(Ljava/lang/Object;Lscala/Function2;)Ljava/lang/Object;
  #322 = Utf8               Lscala/Function2;
  #323 = Utf8               foldLeft$extension
  #324 = Utf8               <B:Ljava/lang/Object;K:Ljava/lang/Object;V:Ljava/lang/Object;>(Lscala/collection/immutable/Map<TK;TV;>;TB;Lscala/Function2<TB;Lscala/Tuple2<TK;TV;>;TB;>;)TB;
  #325 = Utf8               foldLeft
  #326 = NameAndType        #325:#319     // foldLeft:(Ljava/lang/Object;Lscala/Function2;)Ljava/lang/Object;
  #327 = InterfaceMethodref #41.#326      // scala/collection/immutable/Map.foldLeft:(Ljava/lang/Object;Lscala/Function2;)Ljava/lang/Object;
  #328 = Utf8               foldRight$extension
  #329 = Utf8               <B:Ljava/lang/Object;K:Ljava/lang/Object;V:Ljava/lang/Object;>(Lscala/collection/immutable/Map<TK;TV;>;TB;Lscala/Function2<Lscala/Tuple2<TK;TV;>;TB;TB;>;)TB;
  #330 = Utf8               foldRight
  #331 = NameAndType        #330:#319     // foldRight:(Ljava/lang/Object;Lscala/Function2;)Ljava/lang/Object;
  #332 = InterfaceMethodref #41.#331      // scala/collection/immutable/Map.foldRight:(Ljava/lang/Object;Lscala/Function2;)Ljava/lang/Object;
  #333 = Utf8               forall$extension
  #334 = Utf8               forall
  #335 = NameAndType        #334:#270     // forall:(Lscala/Function1;)Z
  #336 = InterfaceMethodref #41.#335      // scala/collection/immutable/Map.forall:(Lscala/Function1;)Z
  #337 = Utf8               foreach$extension
  #338 = Utf8               (Lscala/collection/immutable/Map;Lscala/Function1;)V
  #339 = Utf8               <K:Ljava/lang/Object;V:Ljava/lang/Object;>(Lscala/collection/immutable/Map<TK;TV;>;Lscala/Function1<Lscala/Tuple2<TK;TV;>;Lscala/runtime/BoxedUnit;>;)V
  #340 = Utf8               groupBy$extension
  #341 = Utf8               <K:Ljava/lang/Object;V:Ljava/lang/Object;>(Lscala/collection/immutable/Map<TK;TV;>;Lscala/Function1<Lscala/Tuple2<TK;TV;>;TK;>;)Lscala/collection/immutable/Map<TK;Lorg/scalactic/anyvals/NonEmptyMap<TK;TV;>;>;
  #342 = Utf8               groupBy
  #343 = Utf8               (Lscala/Function1;)Lscala/collection/immutable/Map;
  #344 = NameAndType        #342:#343     // groupBy:(Lscala/Function1;)Lscala/collection/immutable/Map;
  #345 = InterfaceMethodref #41.#344      // scala/collection/immutable/Map.groupBy:(Lscala/Function1;)Lscala/collection/immutable/Map;
  #346 = Utf8               $anonfun$groupBy$1$adapted
  #347 = Utf8               (Lscala/collection/immutable/Map;)Ljava/lang/Object;
  #348 = NameAndType        #346:#347     // $anonfun$groupBy$1$adapted:(Lscala/collection/immutable/Map;)Ljava/lang/Object;
  #349 = Methodref          #2.#348       // org/scalactic/anyvals/NonEmptyMap$.$anonfun$groupBy$1$adapted:(Lscala/collection/immutable/Map;)Ljava/lang/Object;
  #350 = MethodHandle       6:#349        // REF_invokeStatic org/scalactic/anyvals/NonEmptyMap$.$anonfun$groupBy$1$adapted:(Lscala/collection/immutable/Map;)Ljava/lang/Object;
  #351 = MethodType         #347          //  (Lscala/collection/immutable/Map;)Ljava/lang/Object;
  #352 = Utf8               ()Lscala/Function1;
  #353 = NameAndType        #20:#352      // apply:()Lscala/Function1;
  #354 = InvokeDynamic      #1:#353       // #1:apply:()Lscala/Function1;
  #355 = Utf8               mapValues
  #356 = Utf8               (Lscala/Function1;)Lscala/collection/MapView;
  #357 = NameAndType        #355:#356     // mapValues:(Lscala/Function1;)Lscala/collection/MapView;
  #358 = InterfaceMethodref #41.#357      // scala/collection/immutable/Map.mapValues:(Lscala/Function1;)Lscala/collection/MapView;
  #359 = Utf8               scala/collection/MapView
  #360 = Class              #359          // scala/collection/MapView
  #361 = InterfaceMethodref #360.#38      // scala/collection/MapView.toMap:(Lscala/$less$colon$less;)Lscala/collection/immutable/Map;
  #362 = Utf8               mapKToMap
  #363 = Utf8               grouped$extension
  #364 = Utf8               (Lscala/collection/immutable/Map;I)Lscala/collection/Iterator;
  #365 = Utf8               <K:Ljava/lang/Object;V:Ljava/lang/Object;>(Lscala/collection/immutable/Map<TK;TV;>;I)Lscala/collection/Iterator<Lorg/scalactic/anyvals/NonEmptyMap<TK;TV;>;>;
  #366 = Utf8               size
  #367 = Utf8               grouped
  #368 = Utf8               (I)Lscala/collection/Iterator;
  #369 = NameAndType        #367:#368     // grouped:(I)Lscala/collection/Iterator;
  #370 = InterfaceMethodref #41.#369      // scala/collection/immutable/Map.grouped:(I)Lscala/collection/Iterator;
  #371 = Utf8               $anonfun$grouped$1$adapted
  #372 = NameAndType        #371:#347     // $anonfun$grouped$1$adapted:(Lscala/collection/immutable/Map;)Ljava/lang/Object;
  #373 = Methodref          #2.#372       // org/scalactic/anyvals/NonEmptyMap$.$anonfun$grouped$1$adapted:(Lscala/collection/immutable/Map;)Ljava/lang/Object;
  #374 = MethodHandle       6:#373        // REF_invokeStatic org/scalactic/anyvals/NonEmptyMap$.$anonfun$grouped$1$adapted:(Lscala/collection/immutable/Map;)Ljava/lang/Object;
  #375 = InvokeDynamic      #2:#353       // #2:apply:()Lscala/Function1;
  #376 = Utf8               scala/collection/Iterator
  #377 = Class              #376          // scala/collection/Iterator
  #378 = Utf8               (Lscala/Function1;)Lscala/collection/Iterator;
  #379 = NameAndType        #124:#378     // map:(Lscala/Function1;)Lscala/collection/Iterator;
  #380 = InterfaceMethodref #377.#379     // scala/collection/Iterator.map:(Lscala/Function1;)Lscala/collection/Iterator;
  #381 = Utf8               itOfMap
  #382 = Utf8               Lscala/collection/Iterator;
  #383 = Utf8               hasDefiniteSize$extension
  #384 = Utf8               (Lscala/collection/immutable/Map;)Z
  #385 = Utf8               <K:Ljava/lang/Object;V:Ljava/lang/Object;>(Lscala/collection/immutable/Map<TK;TV;>;)Z
  #386 = Utf8               head$extension
  #387 = Utf8               (Lscala/collection/immutable/Map;)Lscala/Tuple2;
  #388 = Utf8               <K:Ljava/lang/Object;V:Ljava/lang/Object;>(Lscala/collection/immutable/Map<TK;TV;>;)Lscala/Tuple2<TK;TV;>;
  #389 = Utf8               head
  #390 = NameAndType        #389:#83      // head:()Ljava/lang/Object;
  #391 = InterfaceMethodref #41.#390      // scala/collection/immutable/Map.head:()Ljava/lang/Object;
  #392 = Utf8               headOption$extension
  #393 = Utf8               <K:Ljava/lang/Object;V:Ljava/lang/Object;>(Lscala/collection/immutable/Map<TK;TV;>;)Lscala/Option<Lscala/Tuple2<TK;TV;>;>;
  #394 = InterfaceMethodref #41.#71       // scala/collection/immutable/Map.headOption:()Lscala/Option;
  #395 = Utf8               isDefinedAt$extension
  #396 = Utf8               isDefinedAt
  #397 = NameAndType        #396:#79      // isDefinedAt:(Ljava/lang/Object;)Z
  #398 = InterfaceMethodref #41.#397      // scala/collection/immutable/Map.isDefinedAt:(Ljava/lang/Object;)Z
  #399 = Utf8               isTraversableAgain$extension
  #400 = Utf8               iterator$extension
  #401 = Utf8               (Lscala/collection/immutable/Map;)Lscala/collection/Iterator;
  #402 = Utf8               <K:Ljava/lang/Object;V:Ljava/lang/Object;>(Lscala/collection/immutable/Map<TK;TV;>;)Lscala/collection/Iterator<Lscala/Tuple2<TK;TV;>;>;
  #403 = Utf8               iterator
  #404 = Utf8               ()Lscala/collection/Iterator;
  #405 = NameAndType        #403:#404     // iterator:()Lscala/collection/Iterator;
  #406 = InterfaceMethodref #41.#405      // scala/collection/immutable/Map.iterator:()Lscala/collection/Iterator;
  #407 = Utf8               last$extension
  #408 = Utf8               last
  #409 = NameAndType        #408:#83      // last:()Ljava/lang/Object;
  #410 = InterfaceMethodref #41.#409      // scala/collection/immutable/Map.last:()Ljava/lang/Object;
  #411 = Utf8               lastOption$extension
  #412 = Utf8               lastOption
  #413 = NameAndType        #412:#70      // lastOption:()Lscala/Option;
  #414 = InterfaceMethodref #41.#413      // scala/collection/immutable/Map.lastOption:()Lscala/Option;
  #415 = Utf8               map$extension
  #416 = Utf8               <K1:Ljava/lang/Object;V1:Ljava/lang/Object;K:Ljava/lang/Object;V:Ljava/lang/Object;>(Lscala/collection/immutable/Map<TK;TV;>;Lscala/Function1<Lscala/Tuple2<TK;TV;>;Lscala/Tuple2<TK1;TV1;>;>;)Lscala/collection/immutable/Map<TK1;TV1;>;
  #417 = Utf8               (Lscala/Function1;)Lscala/collection/IterableOps;
  #418 = NameAndType        #124:#417     // map:(Lscala/Function1;)Lscala/collection/IterableOps;
  #419 = InterfaceMethodref #41.#418      // scala/collection/immutable/Map.map:(Lscala/Function1;)Lscala/collection/IterableOps;
  #420 = Utf8               max$extension
  #421 = Utf8               (Lscala/collection/immutable/Map;Lscala/math/Ordering;)Lscala/Tuple2;
  #422 = Utf8               <U:Ljava/lang/Object;K:Ljava/lang/Object;V:Ljava/lang/Object;>(Lscala/collection/immutable/Map<TK;TV;>;Lscala/math/Ordering<TU;>;)Lscala/Tuple2<TK;TV;>;
  #423 = Utf8               cmp
  #424 = Utf8               max
  #425 = Utf8               (Lscala/math/Ordering;)Ljava/lang/Object;
  #426 = NameAndType        #424:#425     // max:(Lscala/math/Ordering;)Ljava/lang/Object;
  #427 = InterfaceMethodref #41.#426      // scala/collection/immutable/Map.max:(Lscala/math/Ordering;)Ljava/lang/Object;
  #428 = Utf8               Lscala/math/Ordering;
  #429 = Utf8               maxBy$extension
  #430 = Utf8               (Lscala/collection/immutable/Map;Lscala/Function1;Lscala/math/Ordering;)Lscala/Tuple2;
  #431 = Utf8               <U:Ljava/lang/Object;K:Ljava/lang/Object;V:Ljava/lang/Object;>(Lscala/collection/immutable/Map<TK;TV;>;Lscala/Function1<Lscala/Tuple2<TK;TV;>;TU;>;Lscala/math/Ordering<TU;>;)Lscala/Tuple2<TK;TV;>;
  #432 = Utf8               maxBy
  #433 = Utf8               (Lscala/Function1;Lscala/math/Ordering;)Ljava/lang/Object;
  #434 = NameAndType        #432:#433     // maxBy:(Lscala/Function1;Lscala/math/Ordering;)Ljava/lang/Object;
  #435 = InterfaceMethodref #41.#434      // scala/collection/immutable/Map.maxBy:(Lscala/Function1;Lscala/math/Ordering;)Ljava/lang/Object;
  #436 = Utf8               min$extension
  #437 = Utf8               min
  #438 = NameAndType        #437:#425     // min:(Lscala/math/Ordering;)Ljava/lang/Object;
  #439 = InterfaceMethodref #41.#438      // scala/collection/immutable/Map.min:(Lscala/math/Ordering;)Ljava/lang/Object;
  #440 = Utf8               minBy$extension
  #441 = Utf8               minBy
  #442 = NameAndType        #441:#433     // minBy:(Lscala/Function1;Lscala/math/Ordering;)Ljava/lang/Object;
  #443 = InterfaceMethodref #41.#442      // scala/collection/immutable/Map.minBy:(Lscala/Function1;Lscala/math/Ordering;)Ljava/lang/Object;
  #444 = Utf8               mkString$extension
  #445 = Utf8               (Lscala/collection/immutable/Map;)Ljava/lang/String;
  #446 = Utf8               <K:Ljava/lang/Object;V:Ljava/lang/Object;>(Lscala/collection/immutable/Map<TK;TV;>;)Ljava/lang/String;
  #447 = Utf8               mkString
  #448 = Utf8               ()Ljava/lang/String;
  #449 = NameAndType        #447:#448     // mkString:()Ljava/lang/String;
  #450 = InterfaceMethodref #41.#449      // scala/collection/immutable/Map.mkString:()Ljava/lang/String;
  #451 = Utf8               (Lscala/collection/immutable/Map;Ljava/lang/String;)Ljava/lang/String;
  #452 = Utf8               <K:Ljava/lang/Object;V:Ljava/lang/Object;>(Lscala/collection/immutable/Map<TK;TV;>;Ljava/lang/String;)Ljava/lang/String;
  #453 = Utf8               (Ljava/lang/String;)Ljava/lang/String;
  #454 = NameAndType        #447:#453     // mkString:(Ljava/lang/String;)Ljava/lang/String;
  #455 = InterfaceMethodref #41.#454      // scala/collection/immutable/Map.mkString:(Ljava/lang/String;)Ljava/lang/String;
  #456 = Utf8               (Lscala/collection/immutable/Map;Ljava/lang/String;Ljava/lang/String;Ljava/lang/String;)Ljava/lang/String;
  #457 = Utf8               <K:Ljava/lang/Object;V:Ljava/lang/Object;>(Lscala/collection/immutable/Map<TK;TV;>;Ljava/lang/String;Ljava/lang/String;Ljava/lang/String;)Ljava/lang/String;
  #458 = Utf8               (Ljava/lang/String;Ljava/lang/String;Ljava/lang/String;)Ljava/lang/String;
  #459 = NameAndType        #447:#458     // mkString:(Ljava/lang/String;Ljava/lang/String;Ljava/lang/String;)Ljava/lang/String;
  #460 = InterfaceMethodref #41.#459      // scala/collection/immutable/Map.mkString:(Ljava/lang/String;Ljava/lang/String;Ljava/lang/String;)Ljava/lang/String;
  #461 = Utf8               nonEmpty$extension
  #462 = Utf8               product$extension
  #463 = Utf8               (Lscala/collection/immutable/Map;Lscala/math/Numeric;)Ljava/lang/Object;
  #464 = Utf8               <U:Ljava/lang/Object;K:Ljava/lang/Object;V:Ljava/lang/Object;>(Lscala/collection/immutable/Map<TK;TV;>;Lscala/math/Numeric<TU;>;)TU;
  #465 = Utf8               num
  #466 = Utf8               product
  #467 = Utf8               (Lscala/math/Numeric;)Ljava/lang/Object;
  #468 = NameAndType        #466:#467     // product:(Lscala/math/Numeric;)Ljava/lang/Object;
  #469 = InterfaceMethodref #41.#468      // scala/collection/immutable/Map.product:(Lscala/math/Numeric;)Ljava/lang/Object;
  #470 = Utf8               Lscala/math/Numeric;
  #471 = Utf8               reduce$extension
  #472 = Utf8               (Lscala/collection/immutable/Map;Lscala/Function2;)Ljava/lang/Object;
  #473 = Utf8               <U:Ljava/lang/Object;K:Ljava/lang/Object;V:Ljava/lang/Object;>(Lscala/collection/immutable/Map<TK;TV;>;Lscala/Function2<TU;TU;TU;>;)TU;
  #474 = Utf8               reduce
  #475 = Utf8               (Lscala/Function2;)Ljava/lang/Object;
  #476 = NameAndType        #474:#475     // reduce:(Lscala/Function2;)Ljava/lang/Object;
  #477 = InterfaceMethodref #41.#476      // scala/collection/immutable/Map.reduce:(Lscala/Function2;)Ljava/lang/Object;
  #478 = Utf8               reduceLeft$extension
  #479 = Utf8               <U:Ljava/lang/Object;K:Ljava/lang/Object;V:Ljava/lang/Object;>(Lscala/collection/immutable/Map<TK;TV;>;Lscala/Function2<TU;Lscala/Tuple2<TK;TV;>;TU;>;)TU;
  #480 = Utf8               reduceLeft
  #481 = NameAndType        #480:#475     // reduceLeft:(Lscala/Function2;)Ljava/lang/Object;
  #482 = InterfaceMethodref #41.#481      // scala/collection/immutable/Map.reduceLeft:(Lscala/Function2;)Ljava/lang/Object;
  #483 = Utf8               reduceLeftOption$extension
  #484 = Utf8               (Lscala/collection/immutable/Map;Lscala/Function2;)Lscala/Option;
  #485 = Utf8               <U:Ljava/lang/Object;K:Ljava/lang/Object;V:Ljava/lang/Object;>(Lscala/collection/immutable/Map<TK;TV;>;Lscala/Function2<TU;Lscala/Tuple2<TK;TV;>;TU;>;)Lscala/Option<TU;>;
  #486 = Utf8               reduceLeftOption
  #487 = Utf8               (Lscala/Function2;)Lscala/Option;
  #488 = NameAndType        #486:#487     // reduceLeftOption:(Lscala/Function2;)Lscala/Option;
  #489 = InterfaceMethodref #41.#488      // scala/collection/immutable/Map.reduceLeftOption:(Lscala/Function2;)Lscala/Option;
  #490 = Utf8               reduceOption$extension
  #491 = Utf8               <U:Ljava/lang/Object;K:Ljava/lang/Object;V:Ljava/lang/Object;>(Lscala/collection/immutable/Map<TK;TV;>;Lscala/Function2<TU;TU;TU;>;)Lscala/Option<TU;>;
  #492 = Utf8               reduceOption
  #493 = NameAndType        #492:#487     // reduceOption:(Lscala/Function2;)Lscala/Option;
  #494 = InterfaceMethodref #41.#493      // scala/collection/immutable/Map.reduceOption:(Lscala/Function2;)Lscala/Option;
  #495 = Utf8               reduceRight$extension
  #496 = Utf8               <U:Ljava/lang/Object;K:Ljava/lang/Object;V:Ljava/lang/Object;>(Lscala/collection/immutable/Map<TK;TV;>;Lscala/Function2<Lscala/Tuple2<TK;TV;>;TU;TU;>;)TU;
  #497 = Utf8               reduceRight
  #498 = NameAndType        #497:#475     // reduceRight:(Lscala/Function2;)Ljava/lang/Object;
  #499 = InterfaceMethodref #41.#498      // scala/collection/immutable/Map.reduceRight:(Lscala/Function2;)Ljava/lang/Object;
  #500 = Utf8               reduceRightOption$extension
  #501 = Utf8               <U:Ljava/lang/Object;K:Ljava/lang/Object;V:Ljava/lang/Object;>(Lscala/collection/immutable/Map<TK;TV;>;Lscala/Function2<Lscala/Tuple2<TK;TV;>;TU;TU;>;)Lscala/Option<TU;>;
  #502 = Utf8               reduceRightOption
  #503 = NameAndType        #502:#487     // reduceRightOption:(Lscala/Function2;)Lscala/Option;
  #504 = InterfaceMethodref #41.#503      // scala/collection/immutable/Map.reduceRightOption:(Lscala/Function2;)Lscala/Option;
  #505 = Utf8               sameElements$extension
  #506 = Utf8               (Lscala/collection/immutable/Map;Lscala/collection/Iterable;)Z
  #507 = Utf8               <U:Ljava/lang/Object;K:Ljava/lang/Object;V:Ljava/lang/Object;>(Lscala/collection/immutable/Map<TK;TV;>;Lscala/collection/Iterable<TU;>;)Z
  #508 = Utf8               that
  #509 = Utf8               (Lscala/collection/IterableOnce;Lscala/collection/IterableOnce;)Z
  #510 = NameAndType        #505:#509     // sameElements$extension:(Lscala/collection/IterableOnce;Lscala/collection/IterableOnce;)Z
  #511 = Methodref          #149.#510     // scala/collection/IterableOnceExtensionMethods$.sameElements$extension:(Lscala/collection/IterableOnce;Lscala/collection/IterableOnce;)Z
  #512 = Utf8               Lscala/collection/Iterable;
  #513 = Utf8               (Lscala/collection/immutable/Map;Lorg/scalactic/Every;)Z
  #514 = Utf8               <U:Ljava/lang/Object;K:Ljava/lang/Object;V:Ljava/lang/Object;>(Lscala/collection/immutable/Map<TK;TV;>;Lorg/scalactic/Every<TU;>;)Z
  #515 = Utf8               (Lscala/collection/immutable/Map;Lscala/collection/immutable/Map;)Z
  #516 = Utf8               <V1:Ljava/lang/Object;K:Ljava/lang/Object;V:Ljava/lang/Object;>(Lscala/collection/immutable/Map<TK;TV;>;Lscala/collection/immutable/Map<TK;TV1;>;)Z
  #517 = Utf8               scan$extension
  #518 = Utf8               (Lscala/collection/immutable/Map;Lscala/Tuple2;Lscala/Function2;)Lscala/collection/immutable/Map;
  #519 = Utf8               <V1:Ljava/lang/Object;K:Ljava/lang/Object;V:Ljava/lang/Object;>(Lscala/collection/immutable/Map<TK;TV;>;Lscala/Tuple2<TK;TV1;>;Lscala/Function2<Lscala/Tuple2<TK;TV1;>;Lscala/Tuple2<TK;TV1;>;Lscala/Tuple2<TK;TV1;>;>;)Lscala/collection/immutable/Map<TK;TV1;>;
  #520 = Utf8               scan
  #521 = NameAndType        #520:#319     // scan:(Ljava/lang/Object;Lscala/Function2;)Ljava/lang/Object;
  #522 = InterfaceMethodref #41.#521      // scala/collection/immutable/Map.scan:(Ljava/lang/Object;Lscala/Function2;)Ljava/lang/Object;
  #523 = Utf8               sliding$extension
  #524 = Utf8               sliding
  #525 = NameAndType        #524:#368     // sliding:(I)Lscala/collection/Iterator;
  #526 = InterfaceMethodref #41.#525      // scala/collection/immutable/Map.sliding:(I)Lscala/collection/Iterator;
  #527 = Utf8               $anonfun$sliding$1$adapted
  #528 = NameAndType        #527:#347     // $anonfun$sliding$1$adapted:(Lscala/collection/immutable/Map;)Ljava/lang/Object;
  #529 = Methodref          #2.#528       // org/scalactic/anyvals/NonEmptyMap$.$anonfun$sliding$1$adapted:(Lscala/collection/immutable/Map;)Ljava/lang/Object;
  #530 = MethodHandle       6:#529        // REF_invokeStatic org/scalactic/anyvals/NonEmptyMap$.$anonfun$sliding$1$adapted:(Lscala/collection/immutable/Map;)Ljava/lang/Object;
  #531 = InvokeDynamic      #3:#353       // #3:apply:()Lscala/Function1;
  #532 = Utf8               (Lscala/collection/immutable/Map;II)Lscala/collection/Iterator;
  #533 = Utf8               <K:Ljava/lang/Object;V:Ljava/lang/Object;>(Lscala/collection/immutable/Map<TK;TV;>;II)Lscala/collection/Iterator<Lorg/scalactic/anyvals/NonEmptyMap<TK;TV;>;>;
  #534 = Utf8               step
  #535 = Utf8               (II)Lscala/collection/Iterator;
  #536 = NameAndType        #524:#535     // sliding:(II)Lscala/collection/Iterator;
  #537 = InterfaceMethodref #41.#536      // scala/collection/immutable/Map.sliding:(II)Lscala/collection/Iterator;
  #538 = Utf8               $anonfun$sliding$2$adapted
  #539 = NameAndType        #538:#347     // $anonfun$sliding$2$adapted:(Lscala/collection/immutable/Map;)Ljava/lang/Object;
  #540 = Methodref          #2.#539       // org/scalactic/anyvals/NonEmptyMap$.$anonfun$sliding$2$adapted:(Lscala/collection/immutable/Map;)Ljava/lang/Object;
  #541 = MethodHandle       6:#540        // REF_invokeStatic org/scalactic/anyvals/NonEmptyMap$.$anonfun$sliding$2$adapted:(Lscala/collection/immutable/Map;)Ljava/lang/Object;
  #542 = InvokeDynamic      #4:#353       // #4:apply:()Lscala/Function1;
  #543 = Utf8               size$extension
  #544 = Utf8               (Lscala/collection/immutable/Map;)I
  #545 = Utf8               <K:Ljava/lang/Object;V:Ljava/lang/Object;>(Lscala/collection/immutable/Map<TK;TV;>;)I
  #546 = Utf8               ()I
  #547 = NameAndType        #366:#546     // size:()I
  #548 = InterfaceMethodref #41.#547      // scala/collection/immutable/Map.size:()I
  #549 = Utf8               stringPrefix$extension
  #550 = Utf8               NonEmptyMap
  #551 = String             #550          // NonEmptyMap
  #552 = Utf8               sum$extension
  #553 = Utf8               sum
  #554 = NameAndType        #553:#467     // sum:(Lscala/math/Numeric;)Ljava/lang/Object;
  #555 = InterfaceMethodref #41.#554      // scala/collection/immutable/Map.sum:(Lscala/math/Numeric;)Ljava/lang/Object;
  #556 = Utf8               to$extension
  #557 = Utf8               (Lscala/collection/immutable/Map;Lscala/collection/Factory;)Ljava/lang/Object;
  #558 = Utf8               <Col:Ljava/lang/Object;K:Ljava/lang/Object;V:Ljava/lang/Object;>(Lscala/collection/immutable/Map<TK;TV;>;Lscala/collection/Factory<Lscala/Tuple2<TK;TV;>;TCol;>;)TCol;
  #559 = Utf8               factory
  #560 = Utf8               to
  #561 = Utf8               (Lscala/collection/Factory;)Ljava/lang/Object;
  #562 = NameAndType        #560:#561     // to:(Lscala/collection/Factory;)Ljava/lang/Object;
  #563 = InterfaceMethodref #41.#562      // scala/collection/immutable/Map.to:(Lscala/collection/Factory;)Ljava/lang/Object;
  #564 = Utf8               Lscala/collection/Factory;
  #565 = Utf8               toArray$extension
  #566 = Utf8               (Lscala/collection/immutable/Map;Lscala/reflect/ClassTag;)Ljava/lang/Object;
  #567 = Utf8               <U:Ljava/lang/Object;K:Ljava/lang/Object;V:Ljava/lang/Object;>(Lscala/collection/immutable/Map<TK;TV;>;Lscala/reflect/ClassTag<TU;>;)Ljava/lang/Object;
  #568 = Utf8               classTag
  #569 = Utf8               toArray
  #570 = Utf8               (Lscala/reflect/ClassTag;)Ljava/lang/Object;
  #571 = NameAndType        #569:#570     // toArray:(Lscala/reflect/ClassTag;)Ljava/lang/Object;
  #572 = InterfaceMethodref #41.#571      // scala/collection/immutable/Map.toArray:(Lscala/reflect/ClassTag;)Ljava/lang/Object;
  #573 = Utf8               Lscala/reflect/ClassTag;
  #574 = Utf8               toVector$extension
  #575 = Utf8               (Lscala/collection/immutable/Map;)Lscala/collection/immutable/Vector;
  #576 = Utf8               <K:Ljava/lang/Object;V:Ljava/lang/Object;>(Lscala/collection/immutable/Map<TK;TV;>;)Lscala/collection/immutable/Vector<Lscala/Tuple2<TK;TV;>;>;
  #577 = InterfaceMethodref #41.#143      // scala/collection/immutable/Map.toVector:()Lscala/collection/immutable/Vector;
  #578 = Utf8               toBuffer$extension
  #579 = Utf8               (Lscala/collection/immutable/Map;)Lscala/collection/mutable/Buffer;
  #580 = Utf8               <U:Ljava/lang/Object;K:Ljava/lang/Object;V:Ljava/lang/Object;>(Lscala/collection/immutable/Map<TK;TV;>;)Lscala/collection/mutable/Buffer<TU;>;
  #581 = Utf8               toBuffer
  #582 = Utf8               ()Lscala/collection/mutable/Buffer;
  #583 = NameAndType        #581:#582     // toBuffer:()Lscala/collection/mutable/Buffer;
  #584 = InterfaceMethodref #41.#583      // scala/collection/immutable/Map.toBuffer:()Lscala/collection/mutable/Buffer;
  #585 = Utf8               toIndexedSeq$extension
  #586 = Utf8               (Lscala/collection/immutable/Map;)Lscala/collection/immutable/IndexedSeq;
  #587 = Utf8               <K:Ljava/lang/Object;V:Ljava/lang/Object;>(Lscala/collection/immutable/Map<TK;TV;>;)Lscala/collection/immutable/IndexedSeq<Lscala/Tuple2<TK;TV;>;>;
  #588 = Utf8               toIterable$extension
  #589 = Utf8               (Lscala/collection/immutable/Map;)Lscala/collection/Iterable;
  #590 = Utf8               <K:Ljava/lang/Object;V:Ljava/lang/Object;>(Lscala/collection/immutable/Map<TK;TV;>;)Lscala/collection/Iterable<Lscala/Tuple2<TK;TV;>;>;
  #591 = Utf8               toIterable
  #592 = Utf8               ()Lscala/collection/Iterable;
  #593 = NameAndType        #591:#592     // toIterable:()Lscala/collection/Iterable;
  #594 = InterfaceMethodref #41.#593      // scala/collection/immutable/Map.toIterable:()Lscala/collection/Iterable;
  #595 = Utf8               toIterator$extension
  #596 = Utf8               toIterator
  #597 = NameAndType        #596:#404     // toIterator:()Lscala/collection/Iterator;
  #598 = InterfaceMethodref #41.#597      // scala/collection/immutable/Map.toIterator:()Lscala/collection/Iterator;
  #599 = Utf8               <K:Ljava/lang/Object;V:Ljava/lang/Object;>(Lscala/collection/immutable/Map<TK;TV;>;)Lscala/collection/immutable/Seq<Lscala/Tuple2<TK;TV;>;>;
  #600 = Utf8               scala/collection/immutable/Seq$
  #601 = Class              #600          // scala/collection/immutable/Seq$
  #602 = Utf8               Lscala/collection/immutable/Seq$;
  #603 = NameAndType        #11:#602      // MODULE$:Lscala/collection/immutable/Seq$;
  #604 = Fieldref           #601.#603     // scala/collection/immutable/Seq$.MODULE$:Lscala/collection/immutable/Seq$;
  #605 = Utf8               ()Lscala/collection/SeqOps;
  #606 = NameAndType        #95:#605      // empty:()Lscala/collection/SeqOps;
  #607 = Methodref          #601.#606     // scala/collection/immutable/Seq$.empty:()Lscala/collection/SeqOps;
  #608 = Utf8               toSeq
  #609 = Utf8               ()Lscala/collection/immutable/Seq;
  #610 = NameAndType        #608:#609     // toSeq:()Lscala/collection/immutable/Seq;
  #611 = InterfaceMethodref #41.#610      // scala/collection/immutable/Map.toSeq:()Lscala/collection/immutable/Seq;
  #612 = Utf8               scala/collection/SeqOps
  #613 = Class              #612          // scala/collection/SeqOps
  #614 = Utf8               (Lscala/collection/IterableOnce;)Ljava/lang/Object;
  #615 = NameAndType        #105:#614     // $plus$plus:(Lscala/collection/IterableOnce;)Ljava/lang/Object;
  #616 = InterfaceMethodref #613.#615     // scala/collection/SeqOps.$plus$plus:(Lscala/collection/IterableOnce;)Ljava/lang/Object;
  #617 = Utf8               toSet$extension
  #618 = Utf8               (Lscala/collection/immutable/Map;)Lscala/collection/immutable/Set;
  #619 = Utf8               <U:Ljava/lang/Object;K:Ljava/lang/Object;V:Ljava/lang/Object;>(Lscala/collection/immutable/Map<TK;TV;>;)Lscala/collection/immutable/Set<TU;>;
  #620 = Utf8               toSet
  #621 = Utf8               ()Lscala/collection/immutable/Set;
  #622 = NameAndType        #620:#621     // toSet:()Lscala/collection/immutable/Set;
  #623 = InterfaceMethodref #41.#622      // scala/collection/immutable/Map.toSet:()Lscala/collection/immutable/Set;
  #624 = Utf8               toStream$extension
  #625 = Utf8               (Lscala/collection/immutable/Map;)Lscala/collection/immutable/Stream;
  #626 = Utf8               <K:Ljava/lang/Object;V:Ljava/lang/Object;>(Lscala/collection/immutable/Map<TK;TV;>;)Lscala/collection/immutable/Stream<Lscala/Tuple2<TK;TV;>;>;
  #627 = Utf8               toStream
  #628 = Utf8               ()Lscala/collection/immutable/Stream;
  #629 = NameAndType        #627:#628     // toStream:()Lscala/collection/immutable/Stream;
  #630 = InterfaceMethodref #41.#629      // scala/collection/immutable/Map.toStream:()Lscala/collection/immutable/Stream;
  #631 = Utf8               toString$extension
  #632 = Utf8               java/lang/StringBuilder
  #633 = Class              #632          // java/lang/StringBuilder
  #634 = Integer            13
  #635 = Utf8               (I)V
  #636 = NameAndType        #15:#635      // "<init>":(I)V
  #637 = Methodref          #633.#636     // java/lang/StringBuilder."<init>":(I)V
  #638 = Utf8               NonEmptyMap(
  #639 = String             #638          // NonEmptyMap(
  #640 = Utf8               append
  #641 = Utf8               (Ljava/lang/String;)Ljava/lang/StringBuilder;
  #642 = NameAndType        #640:#641     // append:(Ljava/lang/String;)Ljava/lang/StringBuilder;
  #643 = Methodref          #633.#642     // java/lang/StringBuilder.append:(Ljava/lang/String;)Ljava/lang/StringBuilder;
  #644 = Utf8               ,
  #645 = String             #644          // ,
  #646 = Utf8               )
  #647 = String             #646          // )
  #648 = Utf8               toString
  #649 = NameAndType        #648:#448     // toString:()Ljava/lang/String;
  #650 = Methodref          #633.#649     // java/lang/StringBuilder.toString:()Ljava/lang/String;
  #651 = Utf8               unzip$extension
  #652 = Utf8               (Lscala/collection/immutable/Map;Lscala/Function1;)Lscala/Tuple2;
  #653 = Utf8               <L:Ljava/lang/Object;R:Ljava/lang/Object;K:Ljava/lang/Object;V:Ljava/lang/Object;>(Lscala/collection/immutable/Map<TK;TV;>;Lscala/Function1<Lscala/Tuple2<TK;TV;>;Lscala/Tuple2<TL;TR;>;>;)Lscala/Tuple2<Lscala/collection/immutable/Iterable<TL;>;Lscala/collection/immutable/Iterable<TR;>;>;
  #654 = Utf8               asPair
  #655 = Utf8               unzip
  #656 = Utf8               (Lscala/Function1;)Lscala/Tuple2;
  #657 = NameAndType        #655:#656     // unzip:(Lscala/Function1;)Lscala/Tuple2;
  #658 = InterfaceMethodref #41.#657      // scala/collection/immutable/Map.unzip:(Lscala/Function1;)Lscala/Tuple2;
  #659 = Utf8               unzip3$extension
  #660 = Utf8               (Lscala/collection/immutable/Map;Lscala/Function1;)Lscala/Tuple3;
  #661 = Utf8               <L:Ljava/lang/Object;M:Ljava/lang/Object;R:Ljava/lang/Object;K:Ljava/lang/Object;V:Ljava/lang/Object;>(Lscala/collection/immutable/Map<TK;TV;>;Lscala/Function1<Lscala/Tuple2<TK;TV;>;Lscala/Tuple3<TL;TM;TR;>;>;)Lscala/Tuple3<Lscala/collection/immutable/Iterable<TL;>;Lscala/collection/immutable/Iterable<TM;>;Lscala/collection/immutable/Iterable<TR;>;>;
  #662 = Utf8               asTriple
  #663 = Utf8               unzip3
  #664 = Utf8               (Lscala/Function1;)Lscala/Tuple3;
  #665 = NameAndType        #663:#664     // unzip3:(Lscala/Function1;)Lscala/Tuple3;
  #666 = InterfaceMethodref #41.#665      // scala/collection/immutable/Map.unzip3:(Lscala/Function1;)Lscala/Tuple3;
  #667 = Utf8               updated$extension
  #668 = Utf8               (Lscala/collection/immutable/Map;Ljava/lang/Object;Ljava/lang/Object;)Lscala/collection/immutable/Map;
  #669 = Utf8               <V1:Ljava/lang/Object;K:Ljava/lang/Object;V:Ljava/lang/Object;>(Lscala/collection/immutable/Map<TK;TV;>;TK;TV1;)Lscala/collection/immutable/Map<TK;TV1;>;
  #670 = Utf8               updated
  #671 = Utf8               (Ljava/lang/Object;Ljava/lang/Object;)Lscala/collection/immutable/MapOps;
  #672 = NameAndType        #670:#671     // updated:(Ljava/lang/Object;Ljava/lang/Object;)Lscala/collection/immutable/MapOps;
  #673 = InterfaceMethodref #41.#672      // scala/collection/immutable/Map.updated:(Ljava/lang/Object;Ljava/lang/Object;)Lscala/collection/immutable/MapOps;
  #674 = Utf8               zipAll$extension
  #675 = Utf8               (Lscala/collection/immutable/Map;Lscala/collection/Iterable;Lscala/Tuple2;Ljava/lang/Object;)Lscala/collection/immutable/Map;
  #676 = Utf8               <O:Ljava/lang/Object;V1:Ljava/lang/Object;K:Ljava/lang/Object;V:Ljava/lang/Object;>(Lscala/collection/immutable/Map<TK;TV;>;Lscala/collection/Iterable<TO;>;Lscala/Tuple2<TK;TV1;>;TO;)Lscala/collection/immutable/Map<Lscala/Tuple2<TK;TV1;>;TO;>;
  #677 = Utf8               thisElem
  #678 = Utf8               otherElem
  #679 = Utf8               zipAll
  #680 = Utf8               (Lscala/collection/Iterable;Ljava/lang/Object;Ljava/lang/Object;)Ljava/lang/Object;
  #681 = NameAndType        #679:#680     // zipAll:(Lscala/collection/Iterable;Ljava/lang/Object;Ljava/lang/Object;)Ljava/lang/Object;
  #682 = InterfaceMethodref #41.#681      // scala/collection/immutable/Map.zipAll:(Lscala/collection/Iterable;Ljava/lang/Object;Ljava/lang/Object;)Ljava/lang/Object;
  #683 = Utf8               zipWithIndex$extension
  #684 = Utf8               <V1:Ljava/lang/Object;K:Ljava/lang/Object;V:Ljava/lang/Object;>(Lscala/collection/immutable/Map<TK;TV;>;)Lscala/collection/immutable/Map<Lscala/Tuple2<TK;TV1;>;Ljava/lang/Object;>;
  #685 = Utf8               zipWithIndex
  #686 = NameAndType        #685:#83      // zipWithIndex:()Ljava/lang/Object;
  #687 = InterfaceMethodref #41.#686      // scala/collection/immutable/Map.zipWithIndex:()Ljava/lang/Object;
  #688 = Utf8               hashCode$extension
  #689 = Utf8               hashCode
  #690 = NameAndType        #689:#546     // hashCode:()I
  #691 = InterfaceMethodref #126.#690     // scala/collection/Map.hashCode:()I
  #692 = Utf8               equals$extension
  #693 = Utf8               <K:Ljava/lang/Object;V:Ljava/lang/Object;>(Lscala/collection/immutable/Map<TK;TV;>;Ljava/lang/Object;)Z
  #694 = Utf8               x$1
  #695 = NameAndType        #36:#96       // toMap:()Lscala/collection/immutable/Map;
  #696 = Methodref          #89.#695      // org/scalactic/anyvals/NonEmptyMap.toMap:()Lscala/collection/immutable/Map;
  #697 = Utf8               buf$1
  #698 = Utf8               f$1
  #699 = Utf8               ele
  #700 = Utf8               scala/Function1
  #701 = Class              #700          // scala/Function1
  #702 = InterfaceMethodref #701.#208     // scala/Function1.apply:(Ljava/lang/Object;)Ljava/lang/Object;
  #703 = Utf8               $plus$plus$eq
  #704 = Utf8               (Lscala/collection/IterableOnce;)Lscala/collection/mutable/Growable;
  #705 = NameAndType        #703:#704     // $plus$plus$eq:(Lscala/collection/IterableOnce;)Lscala/collection/mutable/Growable;
  #706 = Methodref          #285.#705     // scala/collection/mutable/ArrayBuffer.$plus$plus$eq:(Lscala/collection/IterableOnce;)Lscala/collection/mutable/Growable;
  #707 = Utf8               $anonfun$groupBy$1
  #708 = Utf8               list
  #709 = Utf8               $anonfun$grouped$1
  #710 = Utf8               $anonfun$sliding$1
  #711 = Utf8               $anonfun$sliding$2
  #712 = Utf8               x$2
  #713 = Methodref          #4.#16        // java/lang/Object."<init>":()V
  #714 = NameAndType        #707:#130     // $anonfun$groupBy$1:(Lscala/collection/immutable/Map;)Lscala/collection/immutable/Map;
  #715 = Methodref          #2.#714       // org/scalactic/anyvals/NonEmptyMap$.$anonfun$groupBy$1:(Lscala/collection/immutable/Map;)Lscala/collection/immutable/Map;
  #716 = NameAndType        #709:#130     // $anonfun$grouped$1:(Lscala/collection/immutable/Map;)Lscala/collection/immutable/Map;
  #717 = Methodref          #2.#716       // org/scalactic/anyvals/NonEmptyMap$.$anonfun$grouped$1:(Lscala/collection/immutable/Map;)Lscala/collection/immutable/Map;
  #718 = NameAndType        #710:#130     // $anonfun$sliding$1:(Lscala/collection/immutable/Map;)Lscala/collection/immutable/Map;
  #719 = Methodref          #2.#718       // org/scalactic/anyvals/NonEmptyMap$.$anonfun$sliding$1:(Lscala/collection/immutable/Map;)Lscala/collection/immutable/Map;
  #720 = NameAndType        #711:#130     // $anonfun$sliding$2:(Lscala/collection/immutable/Map;)Lscala/collection/immutable/Map;
  #721 = Methodref          #2.#720       // org/scalactic/anyvals/NonEmptyMap$.$anonfun$sliding$2:(Lscala/collection/immutable/Map;)Lscala/collection/immutable/Map;
  #722 = Utf8               $deserializeLambda$
  #723 = Utf8               (Ljava/lang/invoke/SerializedLambda;)Ljava/lang/Object;
  #724 = Utf8               scala/runtime/LambdaDeserialize
  #725 = Class              #724          // scala/runtime/LambdaDeserialize
  #726 = Utf8               bootstrap
  #727 = Utf8               (Ljava/lang/invoke/MethodHandles$Lookup;Ljava/lang/String;Ljava/lang/invoke/MethodType;[Ljava/lang/invoke/MethodHandle;)Ljava/lang/invoke/CallSite;
  #728 = NameAndType        #726:#727     // bootstrap:(Ljava/lang/invoke/MethodHandles$Lookup;Ljava/lang/String;Ljava/lang/invoke/MethodType;[Ljava/lang/invoke/MethodHandle;)Ljava/lang/invoke/CallSite;
  #729 = Methodref          #725.#728     // scala/runtime/LambdaDeserialize.bootstrap:(Ljava/lang/invoke/MethodHandles$Lookup;Ljava/lang/String;Ljava/lang/invoke/MethodType;[Ljava/lang/invoke/MethodHandle;)Ljava/lang/invoke/CallSite;
  #730 = MethodHandle       6:#729        // REF_invokeStatic scala/runtime/LambdaDeserialize.bootstrap:(Ljava/lang/invoke/MethodHandles$Lookup;Ljava/lang/String;Ljava/lang/invoke/MethodType;[Ljava/lang/invoke/MethodHandle;)Ljava/lang/invoke/CallSite;
  #731 = Utf8               lambdaDeserialize
  #732 = NameAndType        #731:#723     // lambdaDeserialize:(Ljava/lang/invoke/SerializedLambda;)Ljava/lang/Object;
  #733 = InvokeDynamic      #5:#732       // #5:lambdaDeserialize:(Ljava/lang/invoke/SerializedLambda;)Ljava/lang/Object;
  #734 = Utf8               Code
  #735 = Utf8               LineNumberTable
  #736 = Utf8               LocalVariableTable
  #737 = Utf8               Signature
  #738 = Utf8               MethodParameters
  #739 = Utf8               StackMapTable
  #740 = Utf8               InnerClasses
  #741 = Utf8               SourceFile
  #742 = Utf8               BootstrapMethods
  #743 = Utf8               ScalaInlineInfo
  #744 = Utf8               Scala
{
  public static final org.scalactic.anyvals.NonEmptyMap$ MODULE$;
    descriptor: Lorg/scalactic/anyvals/NonEmptyMap$;
    flags: (0x0019) ACC_PUBLIC, ACC_STATIC, ACC_FINAL

  public static {};
    descriptor: ()V
    flags: (0x0009) ACC_PUBLIC, ACC_STATIC
    Code:
      stack=2, locals=0, args_size=0
         0: new           #2                  // class org/scalactic/anyvals/NonEmptyMap$
         3: dup
         4: invokespecial #17                 // Method "<init>":()V
         7: putstatic     #19                 // Field MODULE$:Lorg/scalactic/anyvals/NonEmptyMap$;
        10: return
      LineNumberTable:
        line 903: 0

  public <K extends java.lang.Object, V extends java.lang.Object> scala.collection.immutable.Map<K, V> apply(scala.Tuple2<K, V>, scala.collection.immutable.Seq<scala.Tuple2<K, V>>);
    descriptor: (Lscala/Tuple2;Lscala/collection/immutable/Seq;)Lscala/collection/immutable/Map;
    flags: (0x0001) ACC_PUBLIC
    Code:
      stack=2, locals=3, args_size=3
         0: aload_2
         1: getstatic     #29                 // Field scala/$less$colon$less$.MODULE$:Lscala/$less$colon$less$;
         4: invokevirtual #33                 // Method scala/$less$colon$less$.refl:()Lscala/$eq$colon$eq;
         7: invokeinterface #39,  2           // InterfaceMethod scala/collection/immutable/Seq.toMap:(Lscala/$less$colon$less;)Lscala/collection/immutable/Map;
        12: aload_1
        13: invokeinterface #45,  2           // InterfaceMethod scala/collection/immutable/Map.$plus:(Lscala/Tuple2;)Lscala/collection/immutable/MapOps;
        18: checkcast     #41                 // class scala/collection/immutable/Map
        21: areturn
      LineNumberTable:
        line 913: 0
      LocalVariableTable:
        Start  Length  Slot  Name   Signature
            0      22     0  this   Lorg/scalactic/anyvals/NonEmptyMap$;
            0      22     1 firstElement   Lscala/Tuple2;
            0      22     2 otherElements   Lscala/collection/immutable/Seq;
    Signature: #22                          // <K:Ljava/lang/Object;V:Ljava/lang/Object;>(Lscala/Tuple2<TK;TV;>;Lscala/collection/immutable/Seq<Lscala/Tuple2<TK;TV;>;>;)Lscala/collection/immutable/Map<TK;TV;>;
    MethodParameters:
      Name                           Flags
      firstElement                   final
      otherElements                  final

  public <K extends java.lang.Object, V extends java.lang.Object> scala.Option<scala.collection.immutable.Seq<scala.Tuple2<K, V>>> unapplySeq(scala.collection.immutable.Map<K, V>);
    descriptor: (Lscala/collection/immutable/Map;)Lscala/Option;
    flags: (0x0001) ACC_PUBLIC
    Code:
      stack=4, locals=2, args_size=2
         0: new           #54                 // class scala/Some
         3: dup
         4: aload_0
         5: aload_1
         6: invokevirtual #58                 // Method toSeq$extension:(Lscala/collection/immutable/Map;)Lscala/collection/immutable/Seq;
         9: invokespecial #61                 // Method scala/Some."<init>":(Ljava/lang/Object;)V
        12: areturn
      LineNumberTable:
        line 923: 0
      LocalVariableTable:
        Start  Length  Slot  Name   Signature
            0      13     0  this   Lorg/scalactic/anyvals/NonEmptyMap$;
            0      13     1 nonEmptyMap   Lscala/collection/immutable/Map;
    Signature: #51                          // <K:Ljava/lang/Object;V:Ljava/lang/Object;>(Lscala/collection/immutable/Map<TK;TV;>;)Lscala/Option<Lscala/collection/immutable/Seq<Lscala/Tuple2<TK;TV;>;>;>;
    MethodParameters:
      Name                           Flags
      nonEmptyMap                    final

  public <K extends java.lang.Object, V extends java.lang.Object> scala.Option<org.scalactic.anyvals.NonEmptyMap<K, V>> from(scala.collection.Seq<scala.Tuple2<K, V>>);
    descriptor: (Lscala/collection/Seq;)Lscala/Option;
    flags: (0x0001) ACC_PUBLIC
    Code:
      stack=7, locals=6, args_size=2
         0: aload_1
         1: invokeinterface #72,  1           // InterfaceMethod scala/collection/Seq.headOption:()Lscala/Option;
         6: astore_3
         7: getstatic     #77                 // Field scala/None$.MODULE$:Lscala/None$;
        10: aload_3
        11: invokevirtual #81                 // Method java/lang/Object.equals:(Ljava/lang/Object;)Z
        14: ifeq          24
        17: getstatic     #77                 // Field scala/None$.MODULE$:Lscala/None$;
        20: astore_2
        21: goto          124
        24: goto          27
        27: aload_3
        28: instanceof    #54                 // class scala/Some
        31: ifeq          112
        34: aload_3
        35: checkcast     #54                 // class scala/Some
        38: astore        4
        40: aload         4
        42: invokevirtual #85                 // Method scala/Some.value:()Ljava/lang/Object;
        45: checkcast     #87                 // class scala/Tuple2
        48: astore        5
        50: new           #54                 // class scala/Some
        53: dup
        54: new           #89                 // class org/scalactic/anyvals/NonEmptyMap
        57: dup
        58: getstatic     #94                 // Field scala/collection/immutable/Map$.MODULE$:Lscala/collection/immutable/Map$;
        61: invokevirtual #98                 // Method scala/collection/immutable/Map$.empty:()Lscala/collection/immutable/Map;
        64: aload_1
        65: invokeinterface #101,  1          // InterfaceMethod scala/collection/Seq.tail:()Ljava/lang/Object;
        70: checkcast     #103                // class scala/collection/IterableOnceOps
        73: getstatic     #29                 // Field scala/$less$colon$less$.MODULE$:Lscala/$less$colon$less$;
        76: invokevirtual #33                 // Method scala/$less$colon$less$.refl:()Lscala/$eq$colon$eq;
        79: invokeinterface #104,  2          // InterfaceMethod scala/collection/IterableOnceOps.toMap:(Lscala/$less$colon$less;)Lscala/collection/immutable/Map;
        84: invokeinterface #108,  2          // InterfaceMethod scala/collection/immutable/Map.$plus$plus:(Lscala/collection/IterableOnce;)Lscala/collection/IterableOps;
        89: checkcast     #110                // class scala/collection/immutable/MapOps
        92: aload         5
        94: invokeinterface #111,  2          // InterfaceMethod scala/collection/immutable/MapOps.$plus:(Lscala/Tuple2;)Lscala/collection/immutable/MapOps;
        99: checkcast     #41                 // class scala/collection/immutable/Map
       102: invokespecial #114                // Method org/scalactic/anyvals/NonEmptyMap."<init>":(Lscala/collection/immutable/Map;)V
       105: invokespecial #61                 // Method scala/Some."<init>":(Ljava/lang/Object;)V
       108: astore_2
       109: goto          124
       112: goto          115
       115: new           #116                // class scala/MatchError
       118: dup
       119: aload_3
       120: invokespecial #117                // Method scala/MatchError."<init>":(Ljava/lang/Object;)V
       123: athrow
       124: aload_2
       125: areturn
      StackMapTable: number_of_entries = 5
        frame_type = 253 /* append */
          offset_delta = 24
          locals = [ top, class scala/Option ]
        frame_type = 2 /* same */
        frame_type = 251 /* same_frame_extended */
          offset_delta = 84
        frame_type = 2 /* same */
        frame_type = 255 /* full_frame */
          offset_delta = 8
          locals = [ class org/scalactic/anyvals/NonEmptyMap$, class scala/collection/Seq, class scala/Option, class scala/Option ]
          stack = []
      LineNumberTable:
        line 935: 0
        line 936: 7
        line 937: 27
        line 935: 115
      LocalVariableTable:
        Start  Length  Slot  Name   Signature
           50      62     5 first   Lscala/Tuple2;
            0     126     0  this   Lorg/scalactic/anyvals/NonEmptyMap$;
            0     126     1   seq   Lscala/collection/Seq;
    Signature: #65                          // <K:Ljava/lang/Object;V:Ljava/lang/Object;>(Lscala/collection/Seq<Lscala/Tuple2<TK;TV;>;>;)Lscala/Option<Lorg/scalactic/anyvals/NonEmptyMap<TK;TV;>;>;
    MethodParameters:
      Name                           Flags
      seq                            final

  public <K extends java.lang.Object, V extends java.lang.Object> scala.Option<org.scalactic.anyvals.NonEmptyMap<K, V>> from(scala.collection.Map<K, V>);
    descriptor: (Lscala/collection/Map;)Lscala/Option;
    flags: (0x0001) ACC_PUBLIC
    Code:
      stack=6, locals=4, args_size=2
         0: aload_1
         1: invokeinterface #127,  1          // InterfaceMethod scala/collection/Map.headOption:()Lscala/Option;
         6: astore_3
         7: getstatic     #77                 // Field scala/None$.MODULE$:Lscala/None$;
        10: aload_3
        11: invokevirtual #81                 // Method java/lang/Object.equals:(Ljava/lang/Object;)Z
        14: ifeq          24
        17: getstatic     #77                 // Field scala/None$.MODULE$:Lscala/None$;
        20: astore_2
        21: goto          79
        24: goto          27
        27: aload_3
        28: instanceof    #54                 // class scala/Some
        31: ifeq          67
        34: new           #54                 // class scala/Some
        37: dup
        38: new           #89                 // class org/scalactic/anyvals/NonEmptyMap
        41: dup
        42: getstatic     #94                 // Field scala/collection/immutable/Map$.MODULE$:Lscala/collection/immutable/Map$;
        45: invokevirtual #98                 // Method scala/collection/immutable/Map$.empty:()Lscala/collection/immutable/Map;
        48: aload_1
        49: invokeinterface #108,  2          // InterfaceMethod scala/collection/immutable/Map.$plus$plus:(Lscala/collection/IterableOnce;)Lscala/collection/IterableOps;
        54: checkcast     #41                 // class scala/collection/immutable/Map
        57: invokespecial #114                // Method org/scalactic/anyvals/NonEmptyMap."<init>":(Lscala/collection/immutable/Map;)V
        60: invokespecial #61                 // Method scala/Some."<init>":(Ljava/lang/Object;)V
        63: astore_2
        64: goto          79
        67: goto          70
        70: new           #116                // class scala/MatchError
        73: dup
        74: aload_3
        75: invokespecial #117                // Method scala/MatchError."<init>":(Ljava/lang/Object;)V
        78: athrow
        79: aload_2
        80: areturn
      StackMapTable: number_of_entries = 5
        frame_type = 253 /* append */
          offset_delta = 24
          locals = [ top, class scala/Option ]
        frame_type = 2 /* same */
        frame_type = 39 /* same */
        frame_type = 2 /* same */
        frame_type = 255 /* full_frame */
          offset_delta = 8
          locals = [ class org/scalactic/anyvals/NonEmptyMap$, class scala/collection/Map, class scala/Option, class scala/Option ]
          stack = []
      LineNumberTable:
        line 941: 0
        line 942: 7
        line 943: 27
        line 941: 70
      LocalVariableTable:
        Start  Length  Slot  Name   Signature
            0      81     0  this   Lorg/scalactic/anyvals/NonEmptyMap$;
            0      81     1   map   Lscala/collection/Map;
    Signature: #123                         // <K:Ljava/lang/Object;V:Ljava/lang/Object;>(Lscala/collection/Map<TK;TV;>;)Lscala/Option<Lorg/scalactic/anyvals/NonEmptyMap<TK;TV;>;>;
    MethodParameters:
      Name                           Flags
      map                            final

  public <K extends java.lang.Object, V extends java.lang.Object> scala.collection.immutable.Map<K, V> nonEmptyMapToMap(scala.collection.immutable.Map<K, V>);
    descriptor: (Lscala/collection/immutable/Map;)Lscala/collection/immutable/Map;
    flags: (0x0001) ACC_PUBLIC
    Code:
      stack=1, locals=2, args_size=2
         0: aload_1
         1: areturn
      LineNumberTable:
        line 966: 0
      LocalVariableTable:
        Start  Length  Slot  Name   Signature
            0       2     0  this   Lorg/scalactic/anyvals/NonEmptyMap$;
            0       2     1 nonEmptyMap   Lscala/collection/immutable/Map;
    Signature: #131                         // <K:Ljava/lang/Object;V:Ljava/lang/Object;>(Lscala/collection/immutable/Map<TK;TV;>;)Lscala/collection/immutable/Map<TK;TV;>;
    MethodParameters:
      Name                           Flags
      nonEmptyMap                    final

  public final <V1 extends java.lang.Object, K extends java.lang.Object, V extends java.lang.Object> scala.collection.immutable.Map<K, V1> $plus$plus$extension(scala.collection.immutable.Map<K, V>, scala.collection.immutable.Map<K, V1>);
    descriptor: (Lscala/collection/immutable/Map;Lscala/collection/immutable/Map;)Lscala/collection/immutable/Map;
    flags: (0x0011) ACC_PUBLIC, ACC_FINAL
    Code:
      stack=2, locals=3, args_size=3
         0: aload_1
         1: aload_2
         2: invokeinterface #108,  2          // InterfaceMethod scala/collection/immutable/Map.$plus$plus:(Lscala/collection/IterableOnce;)Lscala/collection/IterableOps;
         7: checkcast     #41                 // class scala/collection/immutable/Map
        10: areturn
      LineNumberTable:
        line 118: 0
      LocalVariableTable:
        Start  Length  Slot  Name   Signature
            0      11     0  this   Lorg/scalactic/anyvals/NonEmptyMap$;
            0      11     1 $this   Lscala/collection/immutable/Map;
            0      11     2 other   Lscala/collection/immutable/Map;
    Signature: #134                         // <V1:Ljava/lang/Object;K:Ljava/lang/Object;V:Ljava/lang/Object;>(Lscala/collection/immutable/Map<TK;TV;>;Lscala/collection/immutable/Map<TK;TV1;>;)Lscala/collection/immutable/Map<TK;TV1;>;
    MethodParameters:
      Name                           Flags
      $this                          final
      other                          final

  public final <V1 extends java.lang.Object, K extends java.lang.Object, V extends java.lang.Object> scala.collection.immutable.Map<K, V1> $plus$plus$extension(scala.collection.immutable.Map<K, V>, org.scalactic.Every<scala.Tuple2<K, V1>>);
    descriptor: (Lscala/collection/immutable/Map;Lorg/scalactic/Every;)Lscala/collection/immutable/Map;
    flags: (0x0011) ACC_PUBLIC, ACC_FINAL
    Code:
      stack=2, locals=3, args_size=3
         0: aload_1
         1: aload_2
         2: invokevirtual #144                // Method org/scalactic/Every.toVector:()Lscala/collection/immutable/Vector;
         5: invokeinterface #108,  2          // InterfaceMethod scala/collection/immutable/Map.$plus$plus:(Lscala/collection/IterableOnce;)Lscala/collection/IterableOps;
        10: checkcast     #41                 // class scala/collection/immutable/Map
        13: areturn
      LineNumberTable:
        line 128: 0
      LocalVariableTable:
        Start  Length  Slot  Name   Signature
            0      14     0  this   Lorg/scalactic/anyvals/NonEmptyMap$;
            0      14     1 $this   Lscala/collection/immutable/Map;
            0      14     2 other   Lorg/scalactic/Every;
    Signature: #138                         // <V1:Ljava/lang/Object;K:Ljava/lang/Object;V:Ljava/lang/Object;>(Lscala/collection/immutable/Map<TK;TV;>;Lorg/scalactic/Every<Lscala/Tuple2<TK;TV1;>;>;)Lscala/collection/immutable/Map<TK;TV1;>;
    MethodParameters:
      Name                           Flags
      $this                          final
      other                          final

  public final <V1 extends java.lang.Object, K extends java.lang.Object, V extends java.lang.Object> scala.collection.immutable.Map<K, V1> $plus$plus$extension(scala.collection.immutable.Map<K, V>, scala.collection.IterableOnce<scala.Tuple2<K, V1>>);
    descriptor: (Lscala/collection/immutable/Map;Lscala/collection/IterableOnce;)Lscala/collection/immutable/Map;
    flags: (0x0011) ACC_PUBLIC, ACC_FINAL
    Code:
      stack=4, locals=3, args_size=3
         0: getstatic     #152                // Field scala/collection/IterableOnceExtensionMethods$.MODULE$:Lscala/collection/IterableOnceExtensionMethods$;
         3: getstatic     #157                // Field scala/collection/IterableOnce$.MODULE$:Lscala/collection/IterableOnce$;
         6: aload_2
         7: invokevirtual #161                // Method scala/collection/IterableOnce$.iterableOnceExtensionMethods:(Lscala/collection/IterableOnce;)Lscala/collection/IterableOnce;
        10: invokevirtual #165                // Method scala/collection/IterableOnceExtensionMethods$.isEmpty$extension:(Lscala/collection/IterableOnce;)Z
        13: ifeq          20
        16: aload_1
        17: goto          48
        20: aload_1
        21: getstatic     #152                // Field scala/collection/IterableOnceExtensionMethods$.MODULE$:Lscala/collection/IterableOnceExtensionMethods$;
        24: getstatic     #157                // Field scala/collection/IterableOnce$.MODULE$:Lscala/collection/IterableOnce$;
        27: aload_2
        28: invokevirtual #161                // Method scala/collection/IterableOnce$.iterableOnceExtensionMethods:(Lscala/collection/IterableOnce;)Lscala/collection/IterableOnce;
        31: getstatic     #29                 // Field scala/$less$colon$less$.MODULE$:Lscala/$less$colon$less$;
        34: invokevirtual #33                 // Method scala/$less$colon$less$.refl:()Lscala/$eq$colon$eq;
        37: invokevirtual #169                // Method scala/collection/IterableOnceExtensionMethods$.toMap$extension:(Lscala/collection/IterableOnce;Lscala/$less$colon$less;)Lscala/collection/immutable/Map;
        40: invokeinterface #108,  2          // InterfaceMethod scala/collection/immutable/Map.$plus$plus:(Lscala/collection/IterableOnce;)Lscala/collection/IterableOps;
        45: checkcast     #41                 // class scala/collection/immutable/Map
        48: areturn
      StackMapTable: number_of_entries = 2
        frame_type = 20 /* same */
        frame_type = 91 /* same_locals_1_stack_item */
          stack = [ class scala/collection/immutable/Map ]
      LineNumberTable:
        line 142: 0
      LocalVariableTable:
        Start  Length  Slot  Name   Signature
            0      49     0  this   Lorg/scalactic/anyvals/NonEmptyMap$;
            0      49     1 $this   Lscala/collection/immutable/Map;
            0      49     2 other   Lscala/collection/IterableOnce;
    Signature: #147                         // <V1:Ljava/lang/Object;K:Ljava/lang/Object;V:Ljava/lang/Object;>(Lscala/collection/immutable/Map<TK;TV;>;Lscala/collection/IterableOnce<Lscala/Tuple2<TK;TV1;>;>;)Lscala/collection/immutable/Map<TK;TV1;>;
    MethodParameters:
      Name                           Flags
      $this                          final
      other                          final

  public final <V1 extends java.lang.Object, K extends java.lang.Object, V extends java.lang.Object> scala.collection.immutable.Map<K, V1> $plus$colon$extension(scala.collection.immutable.Map<K, V>, scala.Tuple2<K, V1>);
    descriptor: (Lscala/collection/immutable/Map;Lscala/Tuple2;)Lscala/collection/immutable/Map;
    flags: (0x0011) ACC_PUBLIC, ACC_FINAL
    Code:
      stack=2, locals=3, args_size=3
         0: aload_1
         1: aload_2
         2: invokeinterface #45,  2           // InterfaceMethod scala/collection/immutable/Map.$plus:(Lscala/Tuple2;)Lscala/collection/immutable/MapOps;
         7: checkcast     #41                 // class scala/collection/immutable/Map
        10: areturn
      LineNumberTable:
        line 154: 0
      LocalVariableTable:
        Start  Length  Slot  Name   Signature
            0      11     0  this   Lorg/scalactic/anyvals/NonEmptyMap$;
            0      11     1 $this   Lscala/collection/immutable/Map;
            0      11     2 entry   Lscala/Tuple2;
    Signature: #173                         // <V1:Ljava/lang/Object;K:Ljava/lang/Object;V:Ljava/lang/Object;>(Lscala/collection/immutable/Map<TK;TV;>;Lscala/Tuple2<TK;TV1;>;)Lscala/collection/immutable/Map<TK;TV1;>;
    MethodParameters:
      Name                           Flags
      $this                          final
      entry                          final

  public final <V1 extends java.lang.Object, K extends java.lang.Object, V extends java.lang.Object> scala.collection.immutable.Map<K, V1> $plus$plus$colon$extension(scala.collection.immutable.Map<K, V>, scala.collection.immutable.Map<K, V1>);
    descriptor: (Lscala/collection/immutable/Map;Lscala/collection/immutable/Map;)Lscala/collection/immutable/Map;
    flags: (0x0011) ACC_PUBLIC, ACC_FINAL
    Code:
      stack=2, locals=3, args_size=3
         0: aload_1
         1: aload_2
         2: invokeinterface #108,  2          // InterfaceMethod scala/collection/immutable/Map.$plus$plus:(Lscala/collection/IterableOnce;)Lscala/collection/IterableOps;
         7: checkcast     #41                 // class scala/collection/immutable/Map
        10: areturn
      LineNumberTable:
        line 166: 0
      LocalVariableTable:
        Start  Length  Slot  Name   Signature
            0      11     0  this   Lorg/scalactic/anyvals/NonEmptyMap$;
            0      11     1 $this   Lscala/collection/immutable/Map;
            0      11     2 other   Lscala/collection/immutable/Map;
    Signature: #134                         // <V1:Ljava/lang/Object;K:Ljava/lang/Object;V:Ljava/lang/Object;>(Lscala/collection/immutable/Map<TK;TV;>;Lscala/collection/immutable/Map<TK;TV1;>;)Lscala/collection/immutable/Map<TK;TV1;>;
    MethodParameters:
      Name                           Flags
      $this                          final
      other                          final

  public final <V1 extends java.lang.Object, K extends java.lang.Object, V extends java.lang.Object> scala.collection.immutable.Map<K, V1> $plus$plus$colon$extension(scala.collection.immutable.Map<K, V>, org.scalactic.Every<scala.Tuple2<K, V1>>);
    descriptor: (Lscala/collection/immutable/Map;Lorg/scalactic/Every;)Lscala/collection/immutable/Map;
    flags: (0x0011) ACC_PUBLIC, ACC_FINAL
    Code:
      stack=2, locals=3, args_size=3
         0: aload_1
         1: aload_2
         2: invokevirtual #144                // Method org/scalactic/Every.toVector:()Lscala/collection/immutable/Vector;
         5: invokeinterface #108,  2          // InterfaceMethod scala/collection/immutable/Map.$plus$plus:(Lscala/collection/IterableOnce;)Lscala/collection/IterableOps;
        10: checkcast     #41                 // class scala/collection/immutable/Map
        13: areturn
      LineNumberTable:
        line 178: 0
      LocalVariableTable:
        Start  Length  Slot  Name   Signature
            0      14     0  this   Lorg/scalactic/anyvals/NonEmptyMap$;
            0      14     1 $this   Lscala/collection/immutable/Map;
            0      14     2 other   Lorg/scalactic/Every;
    Signature: #138                         // <V1:Ljava/lang/Object;K:Ljava/lang/Object;V:Ljava/lang/Object;>(Lscala/collection/immutable/Map<TK;TV;>;Lorg/scalactic/Every<Lscala/Tuple2<TK;TV1;>;>;)Lscala/collection/immutable/Map<TK;TV1;>;
    MethodParameters:
      Name                           Flags
      $this                          final
      other                          final

  public final <V1 extends java.lang.Object, K extends java.lang.Object, V extends java.lang.Object> scala.collection.immutable.Map<K, V1> $plus$plus$colon$extension(scala.collection.immutable.Map<K, V>, scala.collection.IterableOnce<scala.Tuple2<K, V1>>);
    descriptor: (Lscala/collection/immutable/Map;Lscala/collection/IterableOnce;)Lscala/collection/immutable/Map;
    flags: (0x0011) ACC_PUBLIC, ACC_FINAL
    Code:
      stack=4, locals=3, args_size=3
         0: getstatic     #152                // Field scala/collection/IterableOnceExtensionMethods$.MODULE$:Lscala/collection/IterableOnceExtensionMethods$;
         3: getstatic     #157                // Field scala/collection/IterableOnce$.MODULE$:Lscala/collection/IterableOnce$;
         6: aload_2
         7: invokevirtual #161                // Method scala/collection/IterableOnce$.iterableOnceExtensionMethods:(Lscala/collection/IterableOnce;)Lscala/collection/IterableOnce;
        10: invokevirtual #165                // Method scala/collection/IterableOnceExtensionMethods$.isEmpty$extension:(Lscala/collection/IterableOnce;)Z
        13: ifeq          20
        16: aload_1
        17: goto          48
        20: aload_1
        21: getstatic     #152                // Field scala/collection/IterableOnceExtensionMethods$.MODULE$:Lscala/collection/IterableOnceExtensionMethods$;
        24: getstatic     #157                // Field scala/collection/IterableOnce$.MODULE$:Lscala/collection/IterableOnce$;
        27: aload_2
        28: invokevirtual #161                // Method scala/collection/IterableOnce$.iterableOnceExtensionMethods:(Lscala/collection/IterableOnce;)Lscala/collection/IterableOnce;
        31: getstatic     #29                 // Field scala/$less$colon$less$.MODULE$:Lscala/$less$colon$less$;
        34: invokevirtual #33                 // Method scala/$less$colon$less$.refl:()Lscala/$eq$colon$eq;
        37: invokevirtual #169                // Method scala/collection/IterableOnceExtensionMethods$.toMap$extension:(Lscala/collection/IterableOnce;Lscala/$less$colon$less;)Lscala/collection/immutable/Map;
        40: invokeinterface #108,  2          // InterfaceMethod scala/collection/immutable/Map.$plus$plus:(Lscala/collection/IterableOnce;)Lscala/collection/IterableOps;
        45: checkcast     #41                 // class scala/collection/immutable/Map
        48: areturn
      StackMapTable: number_of_entries = 2
        frame_type = 20 /* same */
        frame_type = 91 /* same_locals_1_stack_item */
          stack = [ class scala/collection/immutable/Map ]
      LineNumberTable:
        line 190: 0
      LocalVariableTable:
        Start  Length  Slot  Name   Signature
            0      49     0  this   Lorg/scalactic/anyvals/NonEmptyMap$;
            0      49     1 $this   Lscala/collection/immutable/Map;
            0      49     2 other   Lscala/collection/IterableOnce;
    Signature: #147                         // <V1:Ljava/lang/Object;K:Ljava/lang/Object;V:Ljava/lang/Object;>(Lscala/collection/immutable/Map<TK;TV;>;Lscala/collection/IterableOnce<Lscala/Tuple2<TK;TV1;>;>;)Lscala/collection/immutable/Map<TK;TV1;>;
    MethodParameters:
      Name                           Flags
      $this                          final
      other                          final

  public final <V1 extends java.lang.Object, K extends java.lang.Object, V extends java.lang.Object> scala.collection.immutable.Map<K, V1> $plus$extension(scala.collection.immutable.Map<K, V>, scala.Tuple2<K, V1>);
    descriptor: (Lscala/collection/immutable/Map;Lscala/Tuple2;)Lscala/collection/immutable/Map;
    flags: (0x0011) ACC_PUBLIC, ACC_FINAL
    Code:
      stack=2, locals=3, args_size=3
         0: aload_1
         1: aload_2
         2: invokeinterface #45,  2           // InterfaceMethod scala/collection/immutable/Map.$plus:(Lscala/Tuple2;)Lscala/collection/immutable/MapOps;
         7: checkcast     #41                 // class scala/collection/immutable/Map
        10: areturn
      LineNumberTable:
        line 198: 0
      LocalVariableTable:
        Start  Length  Slot  Name   Signature
            0      11     0  this   Lorg/scalactic/anyvals/NonEmptyMap$;
            0      11     1 $this   Lscala/collection/immutable/Map;
            0      11     2 entry   Lscala/Tuple2;
    Signature: #173                         // <V1:Ljava/lang/Object;K:Ljava/lang/Object;V:Ljava/lang/Object;>(Lscala/collection/immutable/Map<TK;TV;>;Lscala/Tuple2<TK;TV1;>;)Lscala/collection/immutable/Map<TK;TV1;>;
    MethodParameters:
      Name                           Flags
      $this                          final
      entry                          final

  public final <V1 extends java.lang.Object, K extends java.lang.Object, V extends java.lang.Object> scala.collection.immutable.Map<K, V1> $plus$extension(scala.collection.immutable.Map<K, V>, scala.collection.immutable.Seq<scala.Tuple2<K, V1>>);
    descriptor: (Lscala/collection/immutable/Map;Lscala/collection/immutable/Seq;)Lscala/collection/immutable/Map;
    flags: (0x0011) ACC_PUBLIC, ACC_FINAL
    Code:
      stack=2, locals=3, args_size=3
         0: aload_1
         1: aload_2
         2: invokeinterface #108,  2          // InterfaceMethod scala/collection/immutable/Map.$plus$plus:(Lscala/collection/IterableOnce;)Lscala/collection/IterableOps;
         7: checkcast     #41                 // class scala/collection/immutable/Map
        10: areturn
      LineNumberTable:
        line 206: 0
      LocalVariableTable:
        Start  Length  Slot  Name   Signature
            0      11     0  this   Lorg/scalactic/anyvals/NonEmptyMap$;
            0      11     1 $this   Lscala/collection/immutable/Map;
            0      11     2 entries   Lscala/collection/immutable/Seq;
    Signature: #178                         // <V1:Ljava/lang/Object;K:Ljava/lang/Object;V:Ljava/lang/Object;>(Lscala/collection/immutable/Map<TK;TV;>;Lscala/collection/immutable/Seq<Lscala/Tuple2<TK;TV1;>;>;)Lscala/collection/immutable/Map<TK;TV1;>;
    MethodParameters:
      Name                           Flags
      $this                          final
      entries                        final

  public final <K extends java.lang.Object, V extends java.lang.Object> scala.collection.mutable.StringBuilder addString$extension(scala.collection.immutable.Map<K, V>, scala.collection.mutable.StringBuilder);
    descriptor: (Lscala/collection/immutable/Map;Lscala/collection/mutable/StringBuilder;)Lscala/collection/mutable/StringBuilder;
    flags: (0x0011) ACC_PUBLIC, ACC_FINAL
    Code:
      stack=2, locals=3, args_size=3
         0: aload_1
         1: aload_2
         2: invokeinterface #187,  2          // InterfaceMethod scala/collection/immutable/Map.addString:(Lscala/collection/mutable/StringBuilder;)Lscala/collection/mutable/StringBuilder;
         7: areturn
      LineNumberTable:
        line 215: 0
      LocalVariableTable:
        Start  Length  Slot  Name   Signature
            0       8     0  this   Lorg/scalactic/anyvals/NonEmptyMap$;
            0       8     1 $this   Lscala/collection/immutable/Map;
            0       8     2    sb   Lscala/collection/mutable/StringBuilder;
    Signature: #182                         // <K:Ljava/lang/Object;V:Ljava/lang/Object;>(Lscala/collection/immutable/Map<TK;TV;>;Lscala/collection/mutable/StringBuilder;)Lscala/collection/mutable/StringBuilder;
    MethodParameters:
      Name                           Flags
      $this                          final
      sb                             final

  public final <K extends java.lang.Object, V extends java.lang.Object> scala.collection.mutable.StringBuilder addString$extension(scala.collection.immutable.Map<K, V>, scala.collection.mutable.StringBuilder, java.lang.String);
    descriptor: (Lscala/collection/immutable/Map;Lscala/collection/mutable/StringBuilder;Ljava/lang/String;)Lscala/collection/mutable/StringBuilder;
    flags: (0x0011) ACC_PUBLIC, ACC_FINAL
    Code:
      stack=3, locals=4, args_size=4
         0: aload_1
         1: aload_2
         2: aload_3
         3: invokeinterface #194,  3          // InterfaceMethod scala/collection/immutable/Map.addString:(Lscala/collection/mutable/StringBuilder;Ljava/lang/String;)Lscala/collection/mutable/StringBuilder;
         8: areturn
      LineNumberTable:
        line 226: 0
      LocalVariableTable:
        Start  Length  Slot  Name   Signature
            0       9     0  this   Lorg/scalactic/anyvals/NonEmptyMap$;
            0       9     1 $this   Lscala/collection/immutable/Map;
            0       9     2    sb   Lscala/collection/mutable/StringBuilder;
            0       9     3   sep   Ljava/lang/String;
    Signature: #190                         // <K:Ljava/lang/Object;V:Ljava/lang/Object;>(Lscala/collection/immutable/Map<TK;TV;>;Lscala/collection/mutable/StringBuilder;Ljava/lang/String;)Lscala/collection/mutable/StringBuilder;
    MethodParameters:
      Name                           Flags
      $this                          final
      sb                             final
      sep                            final

  public final <K extends java.lang.Object, V extends java.lang.Object> scala.collection.mutable.StringBuilder addString$extension(scala.collection.immutable.Map<K, V>, scala.collection.mutable.StringBuilder, java.lang.String, java.lang.String, java.lang.String);
    descriptor: (Lscala/collection/immutable/Map;Lscala/collection/mutable/StringBuilder;Ljava/lang/String;Ljava/lang/String;Ljava/lang/String;)Lscala/collection/mutable/StringBuilder;
    flags: (0x0011) ACC_PUBLIC, ACC_FINAL
    Code:
      stack=5, locals=6, args_size=6
         0: aload_1
         1: aload_2
         2: aload_3
         3: aload         4
         5: aload         5
         7: invokeinterface #202,  5          // InterfaceMethod scala/collection/immutable/Map.addString:(Lscala/collection/mutable/StringBuilder;Ljava/lang/String;Ljava/lang/String;Ljava/lang/String;)Lscala/collection/mutable/StringBuilder;
        12: areturn
      LineNumberTable:
        line 239: 0
      LocalVariableTable:
        Start  Length  Slot  Name   Signature
            0      13     0  this   Lorg/scalactic/anyvals/NonEmptyMap$;
            0      13     1 $this   Lscala/collection/immutable/Map;
            0      13     2    sb   Lscala/collection/mutable/StringBuilder;
            0      13     3 start   Ljava/lang/String;
            0      13     4   sep   Ljava/lang/String;
            0      13     5   end   Ljava/lang/String;
    Signature: #197                         // <K:Ljava/lang/Object;V:Ljava/lang/Object;>(Lscala/collection/immutable/Map<TK;TV;>;Lscala/collection/mutable/StringBuilder;Ljava/lang/String;Ljava/lang/String;Ljava/lang/String;)Lscala/collection/mutable/StringBuilder;
    MethodParameters:
      Name                           Flags
      $this                          final
      sb                             final
      start                          final
      sep                            final
      end                            final

  public final <K extends java.lang.Object, V extends java.lang.Object> V apply$extension(scala.collection.immutable.Map<K, V>, K);
    descriptor: (Lscala/collection/immutable/Map;Ljava/lang/Object;)Ljava/lang/Object;
    flags: (0x0011) ACC_PUBLIC, ACC_FINAL
    Code:
      stack=2, locals=3, args_size=3
         0: aload_1
         1: aload_2
         2: invokeinterface #209,  2          // InterfaceMethod scala/collection/immutable/Map.apply:(Ljava/lang/Object;)Ljava/lang/Object;
         7: areturn
      LineNumberTable:
        line 246: 0
      LocalVariableTable:
        Start  Length  Slot  Name   Signature
            0       8     0  this   Lorg/scalactic/anyvals/NonEmptyMap$;
            0       8     1 $this   Lscala/collection/immutable/Map;
            0       8     2     k   Ljava/lang/Object;
    Signature: #205                         // <K:Ljava/lang/Object;V:Ljava/lang/Object;>(Lscala/collection/immutable/Map<TK;TV;>;TK;)TV;
    MethodParameters:
      Name                           Flags
      $this                          final
      k                              final

  public final <U extends java.lang.Object, K extends java.lang.Object, V extends java.lang.Object> scala.Option<U> collectFirst$extension(scala.collection.immutable.Map<K, V>, scala.PartialFunction<scala.Tuple2<K, V>, U>);
    descriptor: (Lscala/collection/immutable/Map;Lscala/PartialFunction;)Lscala/Option;
    flags: (0x0011) ACC_PUBLIC, ACC_FINAL
    Code:
      stack=2, locals=3, args_size=3
         0: aload_1
         1: aload_2
         2: invokeinterface #218,  2          // InterfaceMethod scala/collection/immutable/Map.collectFirst:(Lscala/PartialFunction;)Lscala/Option;
         7: areturn
      LineNumberTable:
        line 255: 0
      LocalVariableTable:
        Start  Length  Slot  Name   Signature
            0       8     0  this   Lorg/scalactic/anyvals/NonEmptyMap$;
            0       8     1 $this   Lscala/collection/immutable/Map;
            0       8     2    pf   Lscala/PartialFunction;
    Signature: #213                         // <U:Ljava/lang/Object;K:Ljava/lang/Object;V:Ljava/lang/Object;>(Lscala/collection/immutable/Map<TK;TV;>;Lscala/PartialFunction<Lscala/Tuple2<TK;TV;>;TU;>;)Lscala/Option<TU;>;
    MethodParameters:
      Name                           Flags
      $this                          final
      pf                             final

  public final <K extends java.lang.Object, V extends java.lang.Object> boolean contains$extension(scala.collection.immutable.Map<K, V>, K);
    descriptor: (Lscala/collection/immutable/Map;Ljava/lang/Object;)Z
    flags: (0x0011) ACC_PUBLIC, ACC_FINAL
    Code:
      stack=2, locals=3, args_size=3
         0: aload_1
         1: aload_2
         2: invokeinterface #226,  2          // InterfaceMethod scala/collection/immutable/Map.contains:(Ljava/lang/Object;)Z
         7: ireturn
      LineNumberTable:
        line 263: 0
      LocalVariableTable:
        Start  Length  Slot  Name   Signature
            0       8     0  this   Lorg/scalactic/anyvals/NonEmptyMap$;
            0       8     1 $this   Lscala/collection/immutable/Map;
            0       8     2   key   Ljava/lang/Object;
    Signature: #222                         // <K:Ljava/lang/Object;V:Ljava/lang/Object;>(Lscala/collection/immutable/Map<TK;TV;>;TK;)Z
    MethodParameters:
      Name                           Flags
      $this                          final
      key                            final

  public final <V1 extends java.lang.Object, K extends java.lang.Object, V extends java.lang.Object> void copyToArray$extension(scala.collection.immutable.Map<K, V>, scala.Tuple2<K, V1>[]);
    descriptor: (Lscala/collection/immutable/Map;[Lscala/Tuple2;)V
    flags: (0x0011) ACC_PUBLIC, ACC_FINAL
    Code:
      stack=2, locals=3, args_size=3
         0: aload_1
         1: aload_2
         2: invokeinterface #234,  2          // InterfaceMethod scala/collection/immutable/Map.copyToArray:(Ljava/lang/Object;)I
         7: pop
         8: return
      LineNumberTable:
        line 271: 0
      LocalVariableTable:
        Start  Length  Slot  Name   Signature
            0       9     0  this   Lorg/scalactic/anyvals/NonEmptyMap$;
            0       9     1 $this   Lscala/collection/immutable/Map;
            0       9     2   arr   [Lscala/Tuple2;
    Signature: #229                         // <V1:Ljava/lang/Object;K:Ljava/lang/Object;V:Ljava/lang/Object;>(Lscala/collection/immutable/Map<TK;TV;>;[Lscala/Tuple2<TK;TV1;>;)V
    MethodParameters:
      Name                           Flags
      $this                          final
      arr                            final

  public final <V1 extends java.lang.Object, K extends java.lang.Object, V extends java.lang.Object> void copyToArray$extension(scala.collection.immutable.Map<K, V>, scala.Tuple2<K, V1>[], int);
    descriptor: (Lscala/collection/immutable/Map;[Lscala/Tuple2;I)V
    flags: (0x0011) ACC_PUBLIC, ACC_FINAL
    Code:
      stack=3, locals=4, args_size=4
         0: aload_1
         1: aload_2
         2: iload_3
         3: invokeinterface #240,  3          // InterfaceMethod scala/collection/immutable/Map.copyToArray:(Ljava/lang/Object;I)I
         8: pop
         9: return
      LineNumberTable:
        line 280: 0
      LocalVariableTable:
        Start  Length  Slot  Name   Signature
            0      10     0  this   Lorg/scalactic/anyvals/NonEmptyMap$;
            0      10     1 $this   Lscala/collection/immutable/Map;
            0      10     2   arr   [Lscala/Tuple2;
            0      10     3 start   I
    Signature: #237                         // <V1:Ljava/lang/Object;K:Ljava/lang/Object;V:Ljava/lang/Object;>(Lscala/collection/immutable/Map<TK;TV;>;[Lscala/Tuple2<TK;TV1;>;I)V
    MethodParameters:
      Name                           Flags
      $this                          final
      arr                            final
      start                          final

  public final <V1 extends java.lang.Object, K extends java.lang.Object, V extends java.lang.Object> void copyToArray$extension(scala.collection.immutable.Map<K, V>, scala.Tuple2<K, V1>[], int, int);
    descriptor: (Lscala/collection/immutable/Map;[Lscala/Tuple2;II)V
    flags: (0x0011) ACC_PUBLIC, ACC_FINAL
    Code:
      stack=4, locals=5, args_size=5
         0: aload_1
         1: aload_2
         2: iload_3
         3: iload         4
         5: invokeinterface #247,  4          // InterfaceMethod scala/collection/immutable/Map.copyToArray:(Ljava/lang/Object;II)I
        10: pop
        11: return
      LineNumberTable:
        line 291: 0
      LocalVariableTable:
        Start  Length  Slot  Name   Signature
            0      12     0  this   Lorg/scalactic/anyvals/NonEmptyMap$;
            0      12     1 $this   Lscala/collection/immutable/Map;
            0      12     2   arr   [Lscala/Tuple2;
            0      12     3 start   I
            0      12     4   len   I
    Signature: #243                         // <V1:Ljava/lang/Object;K:Ljava/lang/Object;V:Ljava/lang/Object;>(Lscala/collection/immutable/Map<TK;TV;>;[Lscala/Tuple2<TK;TV1;>;II)V
    MethodParameters:
      Name                           Flags
      $this                          final
      arr                            final
      start                          final
      len                            final

  public final <V1 extends java.lang.Object, K extends java.lang.Object, V extends java.lang.Object> void copyToBuffer$extension(scala.collection.immutable.Map<K, V>, scala.collection.mutable.Buffer<scala.Tuple2<K, V1>>);
    descriptor: (Lscala/collection/immutable/Map;Lscala/collection/mutable/Buffer;)V
    flags: (0x0011) ACC_PUBLIC, ACC_FINAL
    Code:
      stack=2, locals=3, args_size=3
         0: aload_1
         1: aload_2
         2: invokeinterface #255,  2          // InterfaceMethod scala/collection/immutable/Map.copyToBuffer:(Lscala/collection/mutable/Buffer;)V
         7: return
      LineNumberTable:
        line 298: 0
      LocalVariableTable:
        Start  Length  Slot  Name   Signature
            0       8     0  this   Lorg/scalactic/anyvals/NonEmptyMap$;
            0       8     1 $this   Lscala/collection/immutable/Map;
            0       8     2   buf   Lscala/collection/mutable/Buffer;
    Signature: #250                         // <V1:Ljava/lang/Object;K:Ljava/lang/Object;V:Ljava/lang/Object;>(Lscala/collection/immutable/Map<TK;TV;>;Lscala/collection/mutable/Buffer<Lscala/Tuple2<TK;TV1;>;>;)V
    MethodParameters:
      Name                           Flags
      $this                          final
      buf                            final

  public final <K extends java.lang.Object, V extends java.lang.Object> int count$extension(scala.collection.immutable.Map<K, V>, scala.Function1<scala.Tuple2<K, V>, java.lang.Object>);
    descriptor: (Lscala/collection/immutable/Map;Lscala/Function1;)I
    flags: (0x0011) ACC_PUBLIC, ACC_FINAL
    Code:
      stack=2, locals=3, args_size=3
         0: aload_1
         1: aload_2
         2: invokeinterface #264,  2          // InterfaceMethod scala/collection/immutable/Map.count:(Lscala/Function1;)I
         7: ireturn
      LineNumberTable:
        line 306: 0
      LocalVariableTable:
        Start  Length  Slot  Name   Signature
            0       8     0  this   Lorg/scalactic/anyvals/NonEmptyMap$;
            0       8     1 $this   Lscala/collection/immutable/Map;
            0       8     2     p   Lscala/Function1;
    Signature: #259                         // <K:Ljava/lang/Object;V:Ljava/lang/Object;>(Lscala/collection/immutable/Map<TK;TV;>;Lscala/Function1<Lscala/Tuple2<TK;TV;>;Ljava/lang/Object;>;)I
    MethodParameters:
      Name                           Flags
      $this                          final
      p                              final

  public final <K extends java.lang.Object, V extends java.lang.Object> boolean exists$extension(scala.collection.immutable.Map<K, V>, scala.Function1<scala.Tuple2<K, V>, java.lang.Object>);
    descriptor: (Lscala/collection/immutable/Map;Lscala/Function1;)Z
    flags: (0x0011) ACC_PUBLIC, ACC_FINAL
    Code:
      stack=2, locals=3, args_size=3
         0: aload_1
         1: aload_2
         2: invokeinterface #272,  2          // InterfaceMethod scala/collection/immutable/Map.exists:(Lscala/Function1;)Z
         7: ireturn
      LineNumberTable:
        line 322: 0
      LocalVariableTable:
        Start  Length  Slot  Name   Signature
            0       8     0  this   Lorg/scalactic/anyvals/NonEmptyMap$;
            0       8     1 $this   Lscala/collection/immutable/Map;
            0       8     2     p   Lscala/Function1;
    Signature: #268                         // <K:Ljava/lang/Object;V:Ljava/lang/Object;>(Lscala/collection/immutable/Map<TK;TV;>;Lscala/Function1<Lscala/Tuple2<TK;TV;>;Ljava/lang/Object;>;)Z
    MethodParameters:
      Name                           Flags
      $this                          final
      p                              final

  public final <K extends java.lang.Object, V extends java.lang.Object> scala.Option<scala.Tuple2<K, V>> find$extension(scala.collection.immutable.Map<K, V>, scala.Function1<scala.Tuple2<K, V>, java.lang.Object>);
    descriptor: (Lscala/collection/immutable/Map;Lscala/Function1;)Lscala/Option;
    flags: (0x0011) ACC_PUBLIC, ACC_FINAL
    Code:
      stack=2, locals=3, args_size=3
         0: aload_1
         1: aload_2
         2: invokeinterface #279,  2          // InterfaceMethod scala/collection/immutable/Map.find:(Lscala/Function1;)Lscala/Option;
         7: areturn
      LineNumberTable:
        line 330: 0
      LocalVariableTable:
        Start  Length  Slot  Name   Signature
            0       8     0  this   Lorg/scalactic/anyvals/NonEmptyMap$;
            0       8     1 $this   Lscala/collection/immutable/Map;
            0       8     2     p   Lscala/Function1;
    Signature: #275                         // <K:Ljava/lang/Object;V:Ljava/lang/Object;>(Lscala/collection/immutable/Map<TK;TV;>;Lscala/Function1<Lscala/Tuple2<TK;TV;>;Ljava/lang/Object;>;)Lscala/Option<Lscala/Tuple2<TK;TV;>;>;
    MethodParameters:
      Name                           Flags
      $this                          final
      p                              final

  public final <K1 extends java.lang.Object, V1 extends java.lang.Object, K extends java.lang.Object, V extends java.lang.Object> scala.collection.immutable.Map<K1, V1> flatMap$extension(scala.collection.immutable.Map<K, V>, scala.Function1<scala.Tuple2<K, V>, org.scalactic.anyvals.NonEmptyMap<K1, V1>>);
    descriptor: (Lscala/collection/immutable/Map;Lscala/Function1;)Lscala/collection/immutable/Map;
    flags: (0x0011) ACC_PUBLIC, ACC_FINAL
    Code:
      stack=3, locals=4, args_size=3
         0: new           #285                // class scala/collection/mutable/ArrayBuffer
         3: dup
         4: invokespecial #286                // Method scala/collection/mutable/ArrayBuffer."<init>":()V
         7: astore_3
         8: aload_1
         9: aload_3
        10: aload_2
        11: invokedynamic #306,  0            // InvokeDynamic #0:apply:(Lscala/collection/mutable/ArrayBuffer;Lscala/Function1;)Lscala/Function1;
        16: invokeinterface #310,  2          // InterfaceMethod scala/collection/immutable/Map.foreach:(Lscala/Function1;)V
        21: aload_3
        22: getstatic     #29                 // Field scala/$less$colon$less$.MODULE$:Lscala/$less$colon$less$;
        25: invokevirtual #33                 // Method scala/$less$colon$less$.refl:()Lscala/$eq$colon$eq;
        28: invokevirtual #311                // Method scala/collection/mutable/ArrayBuffer.toMap:(Lscala/$less$colon$less;)Lscala/collection/immutable/Map;
        31: areturn
      LineNumberTable:
        line 342: 0
        line 343: 8
        line 345: 21
      LocalVariableTable:
        Start  Length  Slot  Name   Signature
            8      23     3   buf   Lscala/collection/mutable/ArrayBuffer;
            0      32     0  this   Lorg/scalactic/anyvals/NonEmptyMap$;
            0      32     1 $this   Lscala/collection/immutable/Map;
            0      32     2     f   Lscala/Function1;
    Signature: #282                         // <K1:Ljava/lang/Object;V1:Ljava/lang/Object;K:Ljava/lang/Object;V:Ljava/lang/Object;>(Lscala/collection/immutable/Map<TK;TV;>;Lscala/Function1<Lscala/Tuple2<TK;TV;>;Lorg/scalactic/anyvals/NonEmptyMap<TK1;TV1;>;>;)Lscala/collection/immutable/Map<TK1;TV1;>;
    MethodParameters:
      Name                           Flags
      $this                          final
      f                              final

  public final <U extends java.lang.Object, K extends java.lang.Object, V extends java.lang.Object> U fold$extension(scala.collection.immutable.Map<K, V>, U, scala.Function2<U, U, U>);
    descriptor: (Lscala/collection/immutable/Map;Ljava/lang/Object;Lscala/Function2;)Ljava/lang/Object;
    flags: (0x0011) ACC_PUBLIC, ACC_FINAL
    Code:
      stack=3, locals=4, args_size=4
         0: aload_1
         1: aload_2
         2: aload_3
         3: invokeinterface #321,  3          // InterfaceMethod scala/collection/immutable/Map.fold:(Ljava/lang/Object;Lscala/Function2;)Ljava/lang/Object;
         8: areturn
      LineNumberTable:
        line 362: 0
      LocalVariableTable:
        Start  Length  Slot  Name   Signature
            0       9     0  this   Lorg/scalactic/anyvals/NonEmptyMap$;
            0       9     1 $this   Lscala/collection/immutable/Map;
            0       9     2     z   Ljava/lang/Object;
            0       9     3    op   Lscala/Function2;
    Signature: #315                         // <U:Ljava/lang/Object;K:Ljava/lang/Object;V:Ljava/lang/Object;>(Lscala/collection/immutable/Map<TK;TV;>;TU;Lscala/Function2<TU;TU;TU;>;)TU;
    MethodParameters:
      Name                           Flags
      $this                          final
      z                              final
      op                             final

  public final <B extends java.lang.Object, K extends java.lang.Object, V extends java.lang.Object> B foldLeft$extension(scala.collection.immutable.Map<K, V>, B, scala.Function2<B, scala.Tuple2<K, V>, B>);
    descriptor: (Lscala/collection/immutable/Map;Ljava/lang/Object;Lscala/Function2;)Ljava/lang/Object;
    flags: (0x0011) ACC_PUBLIC, ACC_FINAL
    Code:
      stack=3, locals=4, args_size=4
         0: aload_1
         1: aload_2
         2: aload_3
         3: invokeinterface #327,  3          // InterfaceMethod scala/collection/immutable/Map.foldLeft:(Ljava/lang/Object;Lscala/Function2;)Ljava/lang/Object;
         8: areturn
      LineNumberTable:
        line 381: 0
      LocalVariableTable:
        Start  Length  Slot  Name   Signature
            0       9     0  this   Lorg/scalactic/anyvals/NonEmptyMap$;
            0       9     1 $this   Lscala/collection/immutable/Map;
            0       9     2     z   Ljava/lang/Object;
            0       9     3    op   Lscala/Function2;
    Signature: #324                         // <B:Ljava/lang/Object;K:Ljava/lang/Object;V:Ljava/lang/Object;>(Lscala/collection/immutable/Map<TK;TV;>;TB;Lscala/Function2<TB;Lscala/Tuple2<TK;TV;>;TB;>;)TB;
    MethodParameters:
      Name                           Flags
      $this                          final
      z                              final
      op                             final

  public final <B extends java.lang.Object, K extends java.lang.Object, V extends java.lang.Object> B foldRight$extension(scala.collection.immutable.Map<K, V>, B, scala.Function2<scala.Tuple2<K, V>, B, B>);
    descriptor: (Lscala/collection/immutable/Map;Ljava/lang/Object;Lscala/Function2;)Ljava/lang/Object;
    flags: (0x0011) ACC_PUBLIC, ACC_FINAL
    Code:
      stack=3, locals=4, args_size=4
         0: aload_1
         1: aload_2
         2: aload_3
         3: invokeinterface #332,  3          // InterfaceMethod scala/collection/immutable/Map.foldRight:(Ljava/lang/Object;Lscala/Function2;)Ljava/lang/Object;
         8: areturn
      LineNumberTable:
        line 400: 0
      LocalVariableTable:
        Start  Length  Slot  Name   Signature
            0       9     0  this   Lorg/scalactic/anyvals/NonEmptyMap$;
            0       9     1 $this   Lscala/collection/immutable/Map;
            0       9     2     z   Ljava/lang/Object;
            0       9     3    op   Lscala/Function2;
    Signature: #329                         // <B:Ljava/lang/Object;K:Ljava/lang/Object;V:Ljava/lang/Object;>(Lscala/collection/immutable/Map<TK;TV;>;TB;Lscala/Function2<Lscala/Tuple2<TK;TV;>;TB;TB;>;)TB;
    MethodParameters:
      Name                           Flags
      $this                          final
      z                              final
      op                             final

  public final <K extends java.lang.Object, V extends java.lang.Object> boolean forall$extension(scala.collection.immutable.Map<K, V>, scala.Function1<scala.Tuple2<K, V>, java.lang.Object>);
    descriptor: (Lscala/collection/immutable/Map;Lscala/Function1;)Z
    flags: (0x0011) ACC_PUBLIC, ACC_FINAL
    Code:
      stack=2, locals=3, args_size=3
         0: aload_1
         1: aload_2
         2: invokeinterface #336,  2          // InterfaceMethod scala/collection/immutable/Map.forall:(Lscala/Function1;)Z
         7: ireturn
      LineNumberTable:
        line 408: 0
      LocalVariableTable:
        Start  Length  Slot  Name   Signature
            0       8     0  this   Lorg/scalactic/anyvals/NonEmptyMap$;
            0       8     1 $this   Lscala/collection/immutable/Map;
            0       8     2     p   Lscala/Function1;
    Signature: #268                         // <K:Ljava/lang/Object;V:Ljava/lang/Object;>(Lscala/collection/immutable/Map<TK;TV;>;Lscala/Function1<Lscala/Tuple2<TK;TV;>;Ljava/lang/Object;>;)Z
    MethodParameters:
      Name                           Flags
      $this                          final
      p                              final

  public final <K extends java.lang.Object, V extends java.lang.Object> void foreach$extension(scala.collection.immutable.Map<K, V>, scala.Function1<scala.Tuple2<K, V>, scala.runtime.BoxedUnit>);
    descriptor: (Lscala/collection/immutable/Map;Lscala/Function1;)V
    flags: (0x0011) ACC_PUBLIC, ACC_FINAL
    Code:
      stack=2, locals=3, args_size=3
         0: aload_1
         1: aload_2
         2: invokeinterface #310,  2          // InterfaceMethod scala/collection/immutable/Map.foreach:(Lscala/Function1;)V
         7: return
      LineNumberTable:
        line 415: 0
      LocalVariableTable:
        Start  Length  Slot  Name   Signature
            0       8     0  this   Lorg/scalactic/anyvals/NonEmptyMap$;
            0       8     1 $this   Lscala/collection/immutable/Map;
            0       8     2     f   Lscala/Function1;
    Signature: #339                         // <K:Ljava/lang/Object;V:Ljava/lang/Object;>(Lscala/collection/immutable/Map<TK;TV;>;Lscala/Function1<Lscala/Tuple2<TK;TV;>;Lscala/runtime/BoxedUnit;>;)V
    MethodParameters:
      Name                           Flags
      $this                          final
      f                              final

  public final <K extends java.lang.Object, V extends java.lang.Object> scala.collection.immutable.Map<K, org.scalactic.anyvals.NonEmptyMap<K, V>> groupBy$extension(scala.collection.immutable.Map<K, V>, scala.Function1<scala.Tuple2<K, V>, K>);
    descriptor: (Lscala/collection/immutable/Map;Lscala/Function1;)Lscala/collection/immutable/Map;
    flags: (0x0011) ACC_PUBLIC, ACC_FINAL
    Code:
      stack=2, locals=4, args_size=3
         0: aload_1
         1: aload_2
         2: invokeinterface #345,  2          // InterfaceMethod scala/collection/immutable/Map.groupBy:(Lscala/Function1;)Lscala/collection/immutable/Map;
         7: astore_3
         8: aload_3
         9: invokedynamic #354,  0            // InvokeDynamic #1:apply:()Lscala/Function1;
        14: invokeinterface #358,  2          // InterfaceMethod scala/collection/immutable/Map.mapValues:(Lscala/Function1;)Lscala/collection/MapView;
        19: getstatic     #29                 // Field scala/$less$colon$less$.MODULE$:Lscala/$less$colon$less$;
        22: invokevirtual #33                 // Method scala/$less$colon$less$.refl:()Lscala/$eq$colon$eq;
        25: invokeinterface #361,  2          // InterfaceMethod scala/collection/MapView.toMap:(Lscala/$less$colon$less;)Lscala/collection/immutable/Map;
        30: areturn
      LineNumberTable:
        line 432: 0
        line 433: 8
      LocalVariableTable:
        Start  Length  Slot  Name   Signature
            8      22     3 mapKToMap   Lscala/collection/immutable/Map;
            0      31     0  this   Lorg/scalactic/anyvals/NonEmptyMap$;
            0      31     1 $this   Lscala/collection/immutable/Map;
            0      31     2     f   Lscala/Function1;
    Signature: #341                         // <K:Ljava/lang/Object;V:Ljava/lang/Object;>(Lscala/collection/immutable/Map<TK;TV;>;Lscala/Function1<Lscala/Tuple2<TK;TV;>;TK;>;)Lscala/collection/immutable/Map<TK;Lorg/scalactic/anyvals/NonEmptyMap<TK;TV;>;>;
    MethodParameters:
      Name                           Flags
      $this                          final
      f                              final

  public final <K extends java.lang.Object, V extends java.lang.Object> scala.collection.Iterator<org.scalactic.anyvals.NonEmptyMap<K, V>> grouped$extension(scala.collection.immutable.Map<K, V>, int);
    descriptor: (Lscala/collection/immutable/Map;I)Lscala/collection/Iterator;
    flags: (0x0011) ACC_PUBLIC, ACC_FINAL
    Code:
      stack=2, locals=4, args_size=3
         0: aload_1
         1: iload_2
         2: invokeinterface #370,  2          // InterfaceMethod scala/collection/immutable/Map.grouped:(I)Lscala/collection/Iterator;
         7: astore_3
         8: aload_3
         9: invokedynamic #375,  0            // InvokeDynamic #2:apply:()Lscala/Function1;
        14: invokeinterface #380,  2          // InterfaceMethod scala/collection/Iterator.map:(Lscala/Function1;)Lscala/collection/Iterator;
        19: areturn
      LineNumberTable:
        line 443: 0
        line 444: 8
      LocalVariableTable:
        Start  Length  Slot  Name   Signature
            8      11     3 itOfMap   Lscala/collection/Iterator;
            0      20     0  this   Lorg/scalactic/anyvals/NonEmptyMap$;
            0      20     1 $this   Lscala/collection/immutable/Map;
            0      20     2  size   I
    Signature: #365                         // <K:Ljava/lang/Object;V:Ljava/lang/Object;>(Lscala/collection/immutable/Map<TK;TV;>;I)Lscala/collection/Iterator<Lorg/scalactic/anyvals/NonEmptyMap<TK;TV;>;>;
    MethodParameters:
      Name                           Flags
      $this                          final
      size                           final

  public final <K extends java.lang.Object, V extends java.lang.Object> boolean hasDefiniteSize$extension(scala.collection.immutable.Map<K, V>);
    descriptor: (Lscala/collection/immutable/Map;)Z
    flags: (0x0011) ACC_PUBLIC, ACC_FINAL
    Code:
      stack=1, locals=2, args_size=2
         0: iconst_1
         1: ireturn
      LineNumberTable:
        line 450: 0
      LocalVariableTable:
        Start  Length  Slot  Name   Signature
            0       2     0  this   Lorg/scalactic/anyvals/NonEmptyMap$;
            0       2     1 $this   Lscala/collection/immutable/Map;
    Signature: #385                         // <K:Ljava/lang/Object;V:Ljava/lang/Object;>(Lscala/collection/immutable/Map<TK;TV;>;)Z
    MethodParameters:
      Name                           Flags
      $this                          final

  public final <K extends java.lang.Object, V extends java.lang.Object> scala.Tuple2<K, V> head$extension(scala.collection.immutable.Map<K, V>);
    descriptor: (Lscala/collection/immutable/Map;)Lscala/Tuple2;
    flags: (0x0011) ACC_PUBLIC, ACC_FINAL
    Code:
      stack=1, locals=2, args_size=2
         0: aload_1
         1: invokeinterface #391,  1          // InterfaceMethod scala/collection/immutable/Map.head:()Ljava/lang/Object;
         6: checkcast     #87                 // class scala/Tuple2
         9: areturn
      LineNumberTable:
        line 459: 0
      LocalVariableTable:
        Start  Length  Slot  Name   Signature
            0      10     0  this   Lorg/scalactic/anyvals/NonEmptyMap$;
            0      10     1 $this   Lscala/collection/immutable/Map;
    Signature: #388                         // <K:Ljava/lang/Object;V:Ljava/lang/Object;>(Lscala/collection/immutable/Map<TK;TV;>;)Lscala/Tuple2<TK;TV;>;
    MethodParameters:
      Name                           Flags
      $this                          final

  public final <K extends java.lang.Object, V extends java.lang.Object> scala.Option<scala.Tuple2<K, V>> headOption$extension(scala.collection.immutable.Map<K, V>);
    descriptor: (Lscala/collection/immutable/Map;)Lscala/Option;
    flags: (0x0011) ACC_PUBLIC, ACC_FINAL
    Code:
      stack=1, locals=2, args_size=2
         0: aload_1
         1: invokeinterface #394,  1          // InterfaceMethod scala/collection/immutable/Map.headOption:()Lscala/Option;
         6: areturn
      LineNumberTable:
        line 470: 0
      LocalVariableTable:
        Start  Length  Slot  Name   Signature
            0       7     0  this   Lorg/scalactic/anyvals/NonEmptyMap$;
            0       7     1 $this   Lscala/collection/immutable/Map;
    Signature: #393                         // <K:Ljava/lang/Object;V:Ljava/lang/Object;>(Lscala/collection/immutable/Map<TK;TV;>;)Lscala/Option<Lscala/Tuple2<TK;TV;>;>;
    MethodParameters:
      Name                           Flags
      $this                          final

  public final <K extends java.lang.Object, V extends java.lang.Object> boolean isDefinedAt$extension(scala.collection.immutable.Map<K, V>, K);
    descriptor: (Lscala/collection/immutable/Map;Ljava/lang/Object;)Z
    flags: (0x0011) ACC_PUBLIC, ACC_FINAL
    Code:
      stack=2, locals=3, args_size=3
         0: aload_1
         1: aload_2
         2: invokeinterface #398,  2          // InterfaceMethod scala/collection/immutable/Map.isDefinedAt:(Ljava/lang/Object;)Z
         7: ireturn
      LineNumberTable:
        line 478: 0
      LocalVariableTable:
        Start  Length  Slot  Name   Signature
            0       8     0  this   Lorg/scalactic/anyvals/NonEmptyMap$;
            0       8     1 $this   Lscala/collection/immutable/Map;
            0       8     2   key   Ljava/lang/Object;
    Signature: #222                         // <K:Ljava/lang/Object;V:Ljava/lang/Object;>(Lscala/collection/immutable/Map<TK;TV;>;TK;)Z
    MethodParameters:
      Name                           Flags
      $this                          final
      key                            final

  public final <K extends java.lang.Object, V extends java.lang.Object> boolean isEmpty$extension(scala.collection.immutable.Map<K, V>);
    descriptor: (Lscala/collection/immutable/Map;)Z
    flags: (0x0011) ACC_PUBLIC, ACC_FINAL
    Code:
      stack=1, locals=2, args_size=2
         0: iconst_0
         1: ireturn
      LineNumberTable:
        line 485: 0
      LocalVariableTable:
        Start  Length  Slot  Name   Signature
            0       2     0  this   Lorg/scalactic/anyvals/NonEmptyMap$;
            0       2     1 $this   Lscala/collection/immutable/Map;
    Signature: #385                         // <K:Ljava/lang/Object;V:Ljava/lang/Object;>(Lscala/collection/immutable/Map<TK;TV;>;)Z
    MethodParameters:
      Name                           Flags
      $this                          final

  public final <K extends java.lang.Object, V extends java.lang.Object> boolean isTraversableAgain$extension(scala.collection.immutable.Map<K, V>);
    descriptor: (Lscala/collection/immutable/Map;)Z
    flags: (0x0011) ACC_PUBLIC, ACC_FINAL
    Code:
      stack=1, locals=2, args_size=2
         0: iconst_1
         1: ireturn
      LineNumberTable:
        line 492: 0
      LocalVariableTable:
        Start  Length  Slot  Name   Signature
            0       2     0  this   Lorg/scalactic/anyvals/NonEmptyMap$;
            0       2     1 $this   Lscala/collection/immutable/Map;
    Signature: #385                         // <K:Ljava/lang/Object;V:Ljava/lang/Object;>(Lscala/collection/immutable/Map<TK;TV;>;)Z
    MethodParameters:
      Name                           Flags
      $this                          final

  public final <K extends java.lang.Object, V extends java.lang.Object> scala.collection.Iterator<scala.Tuple2<K, V>> iterator$extension(scala.collection.immutable.Map<K, V>);
    descriptor: (Lscala/collection/immutable/Map;)Lscala/collection/Iterator;
    flags: (0x0011) ACC_PUBLIC, ACC_FINAL
    Code:
      stack=1, locals=2, args_size=2
         0: aload_1
         1: invokeinterface #406,  1          // InterfaceMethod scala/collection/immutable/Map.iterator:()Lscala/collection/Iterator;
         6: areturn
      LineNumberTable:
        line 499: 0
      LocalVariableTable:
        Start  Length  Slot  Name   Signature
            0       7     0  this   Lorg/scalactic/anyvals/NonEmptyMap$;
            0       7     1 $this   Lscala/collection/immutable/Map;
    Signature: #402                         // <K:Ljava/lang/Object;V:Ljava/lang/Object;>(Lscala/collection/immutable/Map<TK;TV;>;)Lscala/collection/Iterator<Lscala/Tuple2<TK;TV;>;>;
    MethodParameters:
      Name                           Flags
      $this                          final

  public final <K extends java.lang.Object, V extends java.lang.Object> scala.Tuple2<K, V> last$extension(scala.collection.immutable.Map<K, V>);
    descriptor: (Lscala/collection/immutable/Map;)Lscala/Tuple2;
    flags: (0x0011) ACC_PUBLIC, ACC_FINAL
    Code:
      stack=1, locals=2, args_size=2
         0: aload_1
         1: invokeinterface #410,  1          // InterfaceMethod scala/collection/immutable/Map.last:()Ljava/lang/Object;
         6: checkcast     #87                 // class scala/Tuple2
         9: areturn
      LineNumberTable:
        line 506: 0
      LocalVariableTable:
        Start  Length  Slot  Name   Signature
            0      10     0  this   Lorg/scalactic/anyvals/NonEmptyMap$;
            0      10     1 $this   Lscala/collection/immutable/Map;
    Signature: #388                         // <K:Ljava/lang/Object;V:Ljava/lang/Object;>(Lscala/collection/immutable/Map<TK;TV;>;)Lscala/Tuple2<TK;TV;>;
    MethodParameters:
      Name                           Flags
      $this                          final

  public final <K extends java.lang.Object, V extends java.lang.Object> scala.Option<scala.Tuple2<K, V>> lastOption$extension(scala.collection.immutable.Map<K, V>);
    descriptor: (Lscala/collection/immutable/Map;)Lscala/Option;
    flags: (0x0011) ACC_PUBLIC, ACC_FINAL
    Code:
      stack=1, locals=2, args_size=2
         0: aload_1
         1: invokeinterface #414,  1          // InterfaceMethod scala/collection/immutable/Map.lastOption:()Lscala/Option;
         6: areturn
      LineNumberTable:
        line 513: 0
      LocalVariableTable:
        Start  Length  Slot  Name   Signature
            0       7     0  this   Lorg/scalactic/anyvals/NonEmptyMap$;
            0       7     1 $this   Lscala/collection/immutable/Map;
    Signature: #393                         // <K:Ljava/lang/Object;V:Ljava/lang/Object;>(Lscala/collection/immutable/Map<TK;TV;>;)Lscala/Option<Lscala/Tuple2<TK;TV;>;>;
    MethodParameters:
      Name                           Flags
      $this                          final

  public final <K1 extends java.lang.Object, V1 extends java.lang.Object, K extends java.lang.Object, V extends java.lang.Object> scala.collection.immutable.Map<K1, V1> map$extension(scala.collection.immutable.Map<K, V>, scala.Function1<scala.Tuple2<K, V>, scala.Tuple2<K1, V1>>);
    descriptor: (Lscala/collection/immutable/Map;Lscala/Function1;)Lscala/collection/immutable/Map;
    flags: (0x0011) ACC_PUBLIC, ACC_FINAL
    Code:
      stack=2, locals=3, args_size=3
         0: aload_1
         1: aload_2
         2: invokeinterface #419,  2          // InterfaceMethod scala/collection/immutable/Map.map:(Lscala/Function1;)Lscala/collection/IterableOps;
         7: checkcast     #41                 // class scala/collection/immutable/Map
        10: areturn
      LineNumberTable:
        line 524: 0
      LocalVariableTable:
        Start  Length  Slot  Name   Signature
            0      11     0  this   Lorg/scalactic/anyvals/NonEmptyMap$;
            0      11     1 $this   Lscala/collection/immutable/Map;
            0      11     2     f   Lscala/Function1;
    Signature: #416                         // <K1:Ljava/lang/Object;V1:Ljava/lang/Object;K:Ljava/lang/Object;V:Ljava/lang/Object;>(Lscala/collection/immutable/Map<TK;TV;>;Lscala/Function1<Lscala/Tuple2<TK;TV;>;Lscala/Tuple2<TK1;TV1;>;>;)Lscala/collection/immutable/Map<TK1;TV1;>;
    MethodParameters:
      Name                           Flags
      $this                          final
      f                              final

  public final <U extends java.lang.Object, K extends java.lang.Object, V extends java.lang.Object> scala.Tuple2<K, V> max$extension(scala.collection.immutable.Map<K, V>, scala.math.Ordering<U>);
    descriptor: (Lscala/collection/immutable/Map;Lscala/math/Ordering;)Lscala/Tuple2;
    flags: (0x0011) ACC_PUBLIC, ACC_FINAL
    Code:
      stack=2, locals=3, args_size=3
         0: aload_1
         1: aload_2
         2: invokeinterface #427,  2          // InterfaceMethod scala/collection/immutable/Map.max:(Lscala/math/Ordering;)Ljava/lang/Object;
         7: checkcast     #87                 // class scala/Tuple2
        10: areturn
      LineNumberTable:
        line 531: 0
      LocalVariableTable:
        Start  Length  Slot  Name   Signature
            0      11     0  this   Lorg/scalactic/anyvals/NonEmptyMap$;
            0      11     1 $this   Lscala/collection/immutable/Map;
            0      11     2   cmp   Lscala/math/Ordering;
    Signature: #422                         // <U:Ljava/lang/Object;K:Ljava/lang/Object;V:Ljava/lang/Object;>(Lscala/collection/immutable/Map<TK;TV;>;Lscala/math/Ordering<TU;>;)Lscala/Tuple2<TK;TV;>;
    MethodParameters:
      Name                           Flags
      $this                          final
      cmp                            final

  public final <U extends java.lang.Object, K extends java.lang.Object, V extends java.lang.Object> scala.Tuple2<K, V> maxBy$extension(scala.collection.immutable.Map<K, V>, scala.Function1<scala.Tuple2<K, V>, U>, scala.math.Ordering<U>);
    descriptor: (Lscala/collection/immutable/Map;Lscala/Function1;Lscala/math/Ordering;)Lscala/Tuple2;
    flags: (0x0011) ACC_PUBLIC, ACC_FINAL
    Code:
      stack=3, locals=4, args_size=4
         0: aload_1
         1: aload_2
         2: aload_3
         3: invokeinterface #435,  3          // InterfaceMethod scala/collection/immutable/Map.maxBy:(Lscala/Function1;Lscala/math/Ordering;)Ljava/lang/Object;
         8: checkcast     #87                 // class scala/Tuple2
        11: areturn
      LineNumberTable:
        line 538: 0
      LocalVariableTable:
        Start  Length  Slot  Name   Signature
            0      12     0  this   Lorg/scalactic/anyvals/NonEmptyMap$;
            0      12     1 $this   Lscala/collection/immutable/Map;
            0      12     2     f   Lscala/Function1;
            0      12     3   cmp   Lscala/math/Ordering;
    Signature: #431                         // <U:Ljava/lang/Object;K:Ljava/lang/Object;V:Ljava/lang/Object;>(Lscala/collection/immutable/Map<TK;TV;>;Lscala/Function1<Lscala/Tuple2<TK;TV;>;TU;>;Lscala/math/Ordering<TU;>;)Lscala/Tuple2<TK;TV;>;
    MethodParameters:
      Name                           Flags
      $this                          final
      f                              final
      cmp                            final

  public final <U extends java.lang.Object, K extends java.lang.Object, V extends java.lang.Object> scala.Tuple2<K, V> min$extension(scala.collection.immutable.Map<K, V>, scala.math.Ordering<U>);
    descriptor: (Lscala/collection/immutable/Map;Lscala/math/Ordering;)Lscala/Tuple2;
    flags: (0x0011) ACC_PUBLIC, ACC_FINAL
    Code:
      stack=2, locals=3, args_size=3
         0: aload_1
         1: aload_2
         2: invokeinterface #439,  2          // InterfaceMethod scala/collection/immutable/Map.min:(Lscala/math/Ordering;)Ljava/lang/Object;
         7: checkcast     #87                 // class scala/Tuple2
        10: areturn
      LineNumberTable:
        line 545: 0
      LocalVariableTable:
        Start  Length  Slot  Name   Signature
            0      11     0  this   Lorg/scalactic/anyvals/NonEmptyMap$;
            0      11     1 $this   Lscala/collection/immutable/Map;
            0      11     2   cmp   Lscala/math/Ordering;
    Signature: #422                         // <U:Ljava/lang/Object;K:Ljava/lang/Object;V:Ljava/lang/Object;>(Lscala/collection/immutable/Map<TK;TV;>;Lscala/math/Ordering<TU;>;)Lscala/Tuple2<TK;TV;>;
    MethodParameters:
      Name                           Flags
      $this                          final
      cmp                            final

  public final <U extends java.lang.Object, K extends java.lang.Object, V extends java.lang.Object> scala.Tuple2<K, V> minBy$extension(scala.collection.immutable.Map<K, V>, scala.Function1<scala.Tuple2<K, V>, U>, scala.math.Ordering<U>);
    descriptor: (Lscala/collection/immutable/Map;Lscala/Function1;Lscala/math/Ordering;)Lscala/Tuple2;
    flags: (0x0011) ACC_PUBLIC, ACC_FINAL
    Code:
      stack=3, locals=4, args_size=4
         0: aload_1
         1: aload_2
         2: aload_3
         3: invokeinterface #443,  3          // InterfaceMethod scala/collection/immutable/Map.minBy:(Lscala/Function1;Lscala/math/Ordering;)Ljava/lang/Object;
         8: checkcast     #87                 // class scala/Tuple2
        11: areturn
      LineNumberTable:
        line 552: 0
      LocalVariableTable:
        Start  Length  Slot  Name   Signature
            0      12     0  this   Lorg/scalactic/anyvals/NonEmptyMap$;
            0      12     1 $this   Lscala/collection/immutable/Map;
            0      12     2     f   Lscala/Function1;
            0      12     3   cmp   Lscala/math/Ordering;
    Signature: #431                         // <U:Ljava/lang/Object;K:Ljava/lang/Object;V:Ljava/lang/Object;>(Lscala/collection/immutable/Map<TK;TV;>;Lscala/Function1<Lscala/Tuple2<TK;TV;>;TU;>;Lscala/math/Ordering<TU;>;)Lscala/Tuple2<TK;TV;>;
    MethodParameters:
      Name                           Flags
      $this                          final
      f                              final
      cmp                            final

  public final <K extends java.lang.Object, V extends java.lang.Object> java.lang.String mkString$extension(scala.collection.immutable.Map<K, V>);
    descriptor: (Lscala/collection/immutable/Map;)Ljava/lang/String;
    flags: (0x0011) ACC_PUBLIC, ACC_FINAL
    Code:
      stack=1, locals=2, args_size=2
         0: aload_1
         1: invokeinterface #450,  1          // InterfaceMethod scala/collection/immutable/Map.mkString:()Ljava/lang/String;
         6: areturn
      LineNumberTable:
        line 560: 0
      LocalVariableTable:
        Start  Length  Slot  Name   Signature
            0       7     0  this   Lorg/scalactic/anyvals/NonEmptyMap$;
            0       7     1 $this   Lscala/collection/immutable/Map;
    Signature: #446                         // <K:Ljava/lang/Object;V:Ljava/lang/Object;>(Lscala/collection/immutable/Map<TK;TV;>;)Ljava/lang/String;
    MethodParameters:
      Name                           Flags
      $this                          final

  public final <K extends java.lang.Object, V extends java.lang.Object> java.lang.String mkString$extension(scala.collection.immutable.Map<K, V>, java.lang.String);
    descriptor: (Lscala/collection/immutable/Map;Ljava/lang/String;)Ljava/lang/String;
    flags: (0x0011) ACC_PUBLIC, ACC_FINAL
    Code:
      stack=2, locals=3, args_size=3
         0: aload_1
         1: aload_2
         2: invokeinterface #455,  2          // InterfaceMethod scala/collection/immutable/Map.mkString:(Ljava/lang/String;)Ljava/lang/String;
         7: areturn
      LineNumberTable:
        line 569: 0
      LocalVariableTable:
        Start  Length  Slot  Name   Signature
            0       8     0  this   Lorg/scalactic/anyvals/NonEmptyMap$;
            0       8     1 $this   Lscala/collection/immutable/Map;
            0       8     2   sep   Ljava/lang/String;
    Signature: #452                         // <K:Ljava/lang/Object;V:Ljava/lang/Object;>(Lscala/collection/immutable/Map<TK;TV;>;Ljava/lang/String;)Ljava/lang/String;
    MethodParameters:
      Name                           Flags
      $this                          final
      sep                            final

  public final <K extends java.lang.Object, V extends java.lang.Object> java.lang.String mkString$extension(scala.collection.immutable.Map<K, V>, java.lang.String, java.lang.String, java.lang.String);
    descriptor: (Lscala/collection/immutable/Map;Ljava/lang/String;Ljava/lang/String;Ljava/lang/String;)Ljava/lang/String;
    flags: (0x0011) ACC_PUBLIC, ACC_FINAL
    Code:
      stack=4, locals=5, args_size=5
         0: aload_1
         1: aload_2
         2: aload_3
         3: aload         4
         5: invokeinterface #460,  4          // InterfaceMethod scala/collection/immutable/Map.mkString:(Ljava/lang/String;Ljava/lang/String;Ljava/lang/String;)Ljava/lang/String;
        10: areturn
      LineNumberTable:
        line 581: 0
      LocalVariableTable:
        Start  Length  Slot  Name   Signature
            0      11     0  this   Lorg/scalactic/anyvals/NonEmptyMap$;
            0      11     1 $this   Lscala/collection/immutable/Map;
            0      11     2 start   Ljava/lang/String;
            0      11     3   sep   Ljava/lang/String;
            0      11     4   end   Ljava/lang/String;
    Signature: #457                         // <K:Ljava/lang/Object;V:Ljava/lang/Object;>(Lscala/collection/immutable/Map<TK;TV;>;Ljava/lang/String;Ljava/lang/String;Ljava/lang/String;)Ljava/lang/String;
    MethodParameters:
      Name                           Flags
      $this                          final
      start                          final
      sep                            final
      end                            final

  public final <K extends java.lang.Object, V extends java.lang.Object> boolean nonEmpty$extension(scala.collection.immutable.Map<K, V>);
    descriptor: (Lscala/collection/immutable/Map;)Z
    flags: (0x0011) ACC_PUBLIC, ACC_FINAL
    Code:
      stack=1, locals=2, args_size=2
         0: iconst_1
         1: ireturn
      LineNumberTable:
        line 588: 0
      LocalVariableTable:
        Start  Length  Slot  Name   Signature
            0       2     0  this   Lorg/scalactic/anyvals/NonEmptyMap$;
            0       2     1 $this   Lscala/collection/immutable/Map;
    Signature: #385                         // <K:Ljava/lang/Object;V:Ljava/lang/Object;>(Lscala/collection/immutable/Map<TK;TV;>;)Z
    MethodParameters:
      Name                           Flags
      $this                          final

  public final <U extends java.lang.Object, K extends java.lang.Object, V extends java.lang.Object> U product$extension(scala.collection.immutable.Map<K, V>, scala.math.Numeric<U>);
    descriptor: (Lscala/collection/immutable/Map;Lscala/math/Numeric;)Ljava/lang/Object;
    flags: (0x0011) ACC_PUBLIC, ACC_FINAL
    Code:
      stack=2, locals=3, args_size=3
         0: aload_1
         1: aload_2
         2: invokeinterface #469,  2          // InterfaceMethod scala/collection/immutable/Map.product:(Lscala/math/Numeric;)Ljava/lang/Object;
         7: areturn
      LineNumberTable:
        line 599: 0
      LocalVariableTable:
        Start  Length  Slot  Name   Signature
            0       8     0  this   Lorg/scalactic/anyvals/NonEmptyMap$;
            0       8     1 $this   Lscala/collection/immutable/Map;
            0       8     2   num   Lscala/math/Numeric;
    Signature: #464                         // <U:Ljava/lang/Object;K:Ljava/lang/Object;V:Ljava/lang/Object;>(Lscala/collection/immutable/Map<TK;TV;>;Lscala/math/Numeric<TU;>;)TU;
    MethodParameters:
      Name                           Flags
      $this                          final
      num                            final

  public final <U extends java.lang.Object, K extends java.lang.Object, V extends java.lang.Object> U reduce$extension(scala.collection.immutable.Map<K, V>, scala.Function2<U, U, U>);
    descriptor: (Lscala/collection/immutable/Map;Lscala/Function2;)Ljava/lang/Object;
    flags: (0x0011) ACC_PUBLIC, ACC_FINAL
    Code:
      stack=2, locals=3, args_size=3
         0: aload_1
         1: aload_2
         2: invokeinterface #477,  2          // InterfaceMethod scala/collection/immutable/Map.reduce:(Lscala/Function2;)Ljava/lang/Object;
         7: areturn
      LineNumberTable:
        line 612: 0
      LocalVariableTable:
        Start  Length  Slot  Name   Signature
            0       8     0  this   Lorg/scalactic/anyvals/NonEmptyMap$;
            0       8     1 $this   Lscala/collection/immutable/Map;
            0       8     2    op   Lscala/Function2;
    Signature: #473                         // <U:Ljava/lang/Object;K:Ljava/lang/Object;V:Ljava/lang/Object;>(Lscala/collection/immutable/Map<TK;TV;>;Lscala/Function2<TU;TU;TU;>;)TU;
    MethodParameters:
      Name                           Flags
      $this                          final
      op                             final

  public final <U extends java.lang.Object, K extends java.lang.Object, V extends java.lang.Object> U reduceLeft$extension(scala.collection.immutable.Map<K, V>, scala.Function2<U, scala.Tuple2<K, V>, U>);
    descriptor: (Lscala/collection/immutable/Map;Lscala/Function2;)Ljava/lang/Object;
    flags: (0x0011) ACC_PUBLIC, ACC_FINAL
    Code:
      stack=2, locals=3, args_size=3
         0: aload_1
         1: aload_2
         2: invokeinterface #482,  2          // InterfaceMethod scala/collection/immutable/Map.reduceLeft:(Lscala/Function2;)Ljava/lang/Object;
         7: areturn
      LineNumberTable:
        line 629: 0
      LocalVariableTable:
        Start  Length  Slot  Name   Signature
            0       8     0  this   Lorg/scalactic/anyvals/NonEmptyMap$;
            0       8     1 $this   Lscala/collection/immutable/Map;
            0       8     2    op   Lscala/Function2;
    Signature: #479                         // <U:Ljava/lang/Object;K:Ljava/lang/Object;V:Ljava/lang/Object;>(Lscala/collection/immutable/Map<TK;TV;>;Lscala/Function2<TU;Lscala/Tuple2<TK;TV;>;TU;>;)TU;
    MethodParameters:
      Name                           Flags
      $this                          final
      op                             final

  public final <U extends java.lang.Object, K extends java.lang.Object, V extends java.lang.Object> scala.Option<U> reduceLeftOption$extension(scala.collection.immutable.Map<K, V>, scala.Function2<U, scala.Tuple2<K, V>, U>);
    descriptor: (Lscala/collection/immutable/Map;Lscala/Function2;)Lscala/Option;
    flags: (0x0011) ACC_PUBLIC, ACC_FINAL
    Code:
      stack=2, locals=3, args_size=3
         0: aload_1
         1: aload_2
         2: invokeinterface #489,  2          // InterfaceMethod scala/collection/immutable/Map.reduceLeftOption:(Lscala/Function2;)Lscala/Option;
         7: areturn
      LineNumberTable:
        line 639: 0
      LocalVariableTable:
        Start  Length  Slot  Name   Signature
            0       8     0  this   Lorg/scalactic/anyvals/NonEmptyMap$;
            0       8     1 $this   Lscala/collection/immutable/Map;
            0       8     2    op   Lscala/Function2;
    Signature: #485                         // <U:Ljava/lang/Object;K:Ljava/lang/Object;V:Ljava/lang/Object;>(Lscala/collection/immutable/Map<TK;TV;>;Lscala/Function2<TU;Lscala/Tuple2<TK;TV;>;TU;>;)Lscala/Option<TU;>;
    MethodParameters:
      Name                           Flags
      $this                          final
      op                             final

  public final <U extends java.lang.Object, K extends java.lang.Object, V extends java.lang.Object> scala.Option<U> reduceOption$extension(scala.collection.immutable.Map<K, V>, scala.Function2<U, U, U>);
    descriptor: (Lscala/collection/immutable/Map;Lscala/Function2;)Lscala/Option;
    flags: (0x0011) ACC_PUBLIC, ACC_FINAL
    Code:
      stack=2, locals=3, args_size=3
         0: aload_1
         1: aload_2
         2: invokeinterface #494,  2          // InterfaceMethod scala/collection/immutable/Map.reduceOption:(Lscala/Function2;)Lscala/Option;
         7: areturn
      LineNumberTable:
        line 641: 0
      LocalVariableTable:
        Start  Length  Slot  Name   Signature
            0       8     0  this   Lorg/scalactic/anyvals/NonEmptyMap$;
            0       8     1 $this   Lscala/collection/immutable/Map;
            0       8     2    op   Lscala/Function2;
    Signature: #491                         // <U:Ljava/lang/Object;K:Ljava/lang/Object;V:Ljava/lang/Object;>(Lscala/collection/immutable/Map<TK;TV;>;Lscala/Function2<TU;TU;TU;>;)Lscala/Option<TU;>;
    MethodParameters:
      Name                           Flags
      $this                          final
      op                             final

  public final <U extends java.lang.Object, K extends java.lang.Object, V extends java.lang.Object> U reduceRight$extension(scala.collection.immutable.Map<K, V>, scala.Function2<scala.Tuple2<K, V>, U, U>);
    descriptor: (Lscala/collection/immutable/Map;Lscala/Function2;)Ljava/lang/Object;
    flags: (0x0011) ACC_PUBLIC, ACC_FINAL
    Code:
      stack=2, locals=3, args_size=3
         0: aload_1
         1: aload_2
         2: invokeinterface #499,  2          // InterfaceMethod scala/collection/immutable/Map.reduceRight:(Lscala/Function2;)Ljava/lang/Object;
         7: areturn
      LineNumberTable:
        line 658: 0
      LocalVariableTable:
        Start  Length  Slot  Name   Signature
            0       8     0  this   Lorg/scalactic/anyvals/NonEmptyMap$;
            0       8     1 $this   Lscala/collection/immutable/Map;
            0       8     2    op   Lscala/Function2;
    Signature: #496                         // <U:Ljava/lang/Object;K:Ljava/lang/Object;V:Ljava/lang/Object;>(Lscala/collection/immutable/Map<TK;TV;>;Lscala/Function2<Lscala/Tuple2<TK;TV;>;TU;TU;>;)TU;
    MethodParameters:
      Name                           Flags
      $this                          final
      op                             final

  public final <U extends java.lang.Object, K extends java.lang.Object, V extends java.lang.Object> scala.Option<U> reduceRightOption$extension(scala.collection.immutable.Map<K, V>, scala.Function2<scala.Tuple2<K, V>, U, U>);
    descriptor: (Lscala/collection/immutable/Map;Lscala/Function2;)Lscala/Option;
    flags: (0x0011) ACC_PUBLIC, ACC_FINAL
    Code:
      stack=2, locals=3, args_size=3
         0: aload_1
         1: aload_2
         2: invokeinterface #504,  2          // InterfaceMethod scala/collection/immutable/Map.reduceRightOption:(Lscala/Function2;)Lscala/Option;
         7: areturn
      LineNumberTable:
        line 667: 0
      LocalVariableTable:
        Start  Length  Slot  Name   Signature
            0       8     0  this   Lorg/scalactic/anyvals/NonEmptyMap$;
            0       8     1 $this   Lscala/collection/immutable/Map;
            0       8     2    op   Lscala/Function2;
    Signature: #501                         // <U:Ljava/lang/Object;K:Ljava/lang/Object;V:Ljava/lang/Object;>(Lscala/collection/immutable/Map<TK;TV;>;Lscala/Function2<Lscala/Tuple2<TK;TV;>;TU;TU;>;)Lscala/Option<TU;>;
    MethodParameters:
      Name                           Flags
      $this                          final
      op                             final

  public final <U extends java.lang.Object, K extends java.lang.Object, V extends java.lang.Object> boolean sameElements$extension(scala.collection.immutable.Map<K, V>, scala.collection.Iterable<U>);
    descriptor: (Lscala/collection/immutable/Map;Lscala/collection/Iterable;)Z
    flags: (0x0011) ACC_PUBLIC, ACC_FINAL
    Code:
      stack=3, locals=3, args_size=3
         0: getstatic     #152                // Field scala/collection/IterableOnceExtensionMethods$.MODULE$:Lscala/collection/IterableOnceExtensionMethods$;
         3: getstatic     #157                // Field scala/collection/IterableOnce$.MODULE$:Lscala/collection/IterableOnce$;
         6: aload_1
         7: invokevirtual #161                // Method scala/collection/IterableOnce$.iterableOnceExtensionMethods:(Lscala/collection/IterableOnce;)Lscala/collection/IterableOnce;
        10: aload_2
        11: invokevirtual #511                // Method scala/collection/IterableOnceExtensionMethods$.sameElements$extension:(Lscala/collection/IterableOnce;Lscala/collection/IterableOnce;)Z
        14: ireturn
      LineNumberTable:
        line 676: 3
      LocalVariableTable:
        Start  Length  Slot  Name   Signature
            0      15     0  this   Lorg/scalactic/anyvals/NonEmptyMap$;
            0      15     1 $this   Lscala/collection/immutable/Map;
            0      15     2  that   Lscala/collection/Iterable;
    Signature: #507                         // <U:Ljava/lang/Object;K:Ljava/lang/Object;V:Ljava/lang/Object;>(Lscala/collection/immutable/Map<TK;TV;>;Lscala/collection/Iterable<TU;>;)Z
    MethodParameters:
      Name                           Flags
      $this                          final
      that                           final

  public final <U extends java.lang.Object, K extends java.lang.Object, V extends java.lang.Object> boolean sameElements$extension(scala.collection.immutable.Map<K, V>, org.scalactic.Every<U>);
    descriptor: (Lscala/collection/immutable/Map;Lorg/scalactic/Every;)Z
    flags: (0x0011) ACC_PUBLIC, ACC_FINAL
    Code:
      stack=3, locals=3, args_size=3
         0: getstatic     #152                // Field scala/collection/IterableOnceExtensionMethods$.MODULE$:Lscala/collection/IterableOnceExtensionMethods$;
         3: getstatic     #157                // Field scala/collection/IterableOnce$.MODULE$:Lscala/collection/IterableOnce$;
         6: aload_1
         7: invokevirtual #161                // Method scala/collection/IterableOnce$.iterableOnceExtensionMethods:(Lscala/collection/IterableOnce;)Lscala/collection/IterableOnce;
        10: aload_2
        11: invokevirtual #144                // Method org/scalactic/Every.toVector:()Lscala/collection/immutable/Vector;
        14: invokevirtual #511                // Method scala/collection/IterableOnceExtensionMethods$.sameElements$extension:(Lscala/collection/IterableOnce;Lscala/collection/IterableOnce;)Z
        17: ireturn
      LineNumberTable:
        line 685: 3
      LocalVariableTable:
        Start  Length  Slot  Name   Signature
            0      18     0  this   Lorg/scalactic/anyvals/NonEmptyMap$;
            0      18     1 $this   Lscala/collection/immutable/Map;
            0      18     2  that   Lorg/scalactic/Every;
    Signature: #514                         // <U:Ljava/lang/Object;K:Ljava/lang/Object;V:Ljava/lang/Object;>(Lscala/collection/immutable/Map<TK;TV;>;Lorg/scalactic/Every<TU;>;)Z
    MethodParameters:
      Name                           Flags
      $this                          final
      that                           final

  public final <V1 extends java.lang.Object, K extends java.lang.Object, V extends java.lang.Object> boolean sameElements$extension(scala.collection.immutable.Map<K, V>, scala.collection.immutable.Map<K, V1>);
    descriptor: (Lscala/collection/immutable/Map;Lscala/collection/immutable/Map;)Z
    flags: (0x0011) ACC_PUBLIC, ACC_FINAL
    Code:
      stack=3, locals=3, args_size=3
         0: getstatic     #152                // Field scala/collection/IterableOnceExtensionMethods$.MODULE$:Lscala/collection/IterableOnceExtensionMethods$;
         3: getstatic     #157                // Field scala/collection/IterableOnce$.MODULE$:Lscala/collection/IterableOnce$;
         6: aload_1
         7: invokevirtual #161                // Method scala/collection/IterableOnce$.iterableOnceExtensionMethods:(Lscala/collection/IterableOnce;)Lscala/collection/IterableOnce;
        10: aload_2
        11: invokevirtual #511                // Method scala/collection/IterableOnceExtensionMethods$.sameElements$extension:(Lscala/collection/IterableOnce;Lscala/collection/IterableOnce;)Z
        14: ireturn
      LineNumberTable:
        line 694: 3
      LocalVariableTable:
        Start  Length  Slot  Name   Signature
            0      15     0  this   Lorg/scalactic/anyvals/NonEmptyMap$;
            0      15     1 $this   Lscala/collection/immutable/Map;
            0      15     2  that   Lscala/collection/immutable/Map;
    Signature: #516                         // <V1:Ljava/lang/Object;K:Ljava/lang/Object;V:Ljava/lang/Object;>(Lscala/collection/immutable/Map<TK;TV;>;Lscala/collection/immutable/Map<TK;TV1;>;)Z
    MethodParameters:
      Name                           Flags
      $this                          final
      that                           final

  public final <V1 extends java.lang.Object, K extends java.lang.Object, V extends java.lang.Object> scala.collection.immutable.Map<K, V1> scan$extension(scala.collection.immutable.Map<K, V>, scala.Tuple2<K, V1>, scala.Function2<scala.Tuple2<K, V1>, scala.Tuple2<K, V1>, scala.Tuple2<K, V1>>);
    descriptor: (Lscala/collection/immutable/Map;Lscala/Tuple2;Lscala/Function2;)Lscala/collection/immutable/Map;
    flags: (0x0011) ACC_PUBLIC, ACC_FINAL
    Code:
      stack=3, locals=4, args_size=4
         0: aload_1
         1: aload_2
         2: aload_3
         3: invokeinterface #522,  3          // InterfaceMethod scala/collection/immutable/Map.scan:(Ljava/lang/Object;Lscala/Function2;)Ljava/lang/Object;
         8: checkcast     #103                // class scala/collection/IterableOnceOps
        11: getstatic     #29                 // Field scala/$less$colon$less$.MODULE$:Lscala/$less$colon$less$;
        14: invokevirtual #33                 // Method scala/$less$colon$less$.refl:()Lscala/$eq$colon$eq;
        17: invokeinterface #104,  2          // InterfaceMethod scala/collection/IterableOnceOps.toMap:(Lscala/$less$colon$less;)Lscala/collection/immutable/Map;
        22: areturn
      LineNumberTable:
        line 709: 0
      LocalVariableTable:
        Start  Length  Slot  Name   Signature
            0      23     0  this   Lorg/scalactic/anyvals/NonEmptyMap$;
            0      23     1 $this   Lscala/collection/immutable/Map;
            0      23     2     z   Lscala/Tuple2;
            0      23     3    op   Lscala/Function2;
    Signature: #519                         // <V1:Ljava/lang/Object;K:Ljava/lang/Object;V:Ljava/lang/Object;>(Lscala/collection/immutable/Map<TK;TV;>;Lscala/Tuple2<TK;TV1;>;Lscala/Function2<Lscala/Tuple2<TK;TV1;>;Lscala/Tuple2<TK;TV1;>;Lscala/Tuple2<TK;TV1;>;>;)Lscala/collection/immutable/Map<TK;TV1;>;
    MethodParameters:
      Name                           Flags
      $this                          final
      z                              final
      op                             final

  public final <K extends java.lang.Object, V extends java.lang.Object> scala.collection.Iterator<org.scalactic.anyvals.NonEmptyMap<K, V>> sliding$extension(scala.collection.immutable.Map<K, V>, int);
    descriptor: (Lscala/collection/immutable/Map;I)Lscala/collection/Iterator;
    flags: (0x0011) ACC_PUBLIC, ACC_FINAL
    Code:
      stack=2, locals=3, args_size=3
         0: aload_1
         1: iload_2
         2: invokeinterface #526,  2          // InterfaceMethod scala/collection/immutable/Map.sliding:(I)Lscala/collection/Iterator;
         7: invokedynamic #531,  0            // InvokeDynamic #3:apply:()Lscala/Function1;
        12: invokeinterface #380,  2          // InterfaceMethod scala/collection/Iterator.map:(Lscala/Function1;)Lscala/collection/Iterator;
        17: areturn
      LineNumberTable:
        line 718: 0
      LocalVariableTable:
        Start  Length  Slot  Name   Signature
            0      18     0  this   Lorg/scalactic/anyvals/NonEmptyMap$;
            0      18     1 $this   Lscala/collection/immutable/Map;
            0      18     2  size   I
    Signature: #365                         // <K:Ljava/lang/Object;V:Ljava/lang/Object;>(Lscala/collection/immutable/Map<TK;TV;>;I)Lscala/collection/Iterator<Lorg/scalactic/anyvals/NonEmptyMap<TK;TV;>;>;
    MethodParameters:
      Name                           Flags
      $this                          final
      size                           final

  public final <K extends java.lang.Object, V extends java.lang.Object> scala.collection.Iterator<org.scalactic.anyvals.NonEmptyMap<K, V>> sliding$extension(scala.collection.immutable.Map<K, V>, int, int);
    descriptor: (Lscala/collection/immutable/Map;II)Lscala/collection/Iterator;
    flags: (0x0011) ACC_PUBLIC, ACC_FINAL
    Code:
      stack=3, locals=4, args_size=4
         0: aload_1
         1: iload_2
         2: iload_3
         3: invokeinterface #537,  3          // InterfaceMethod scala/collection/immutable/Map.sliding:(II)Lscala/collection/Iterator;
         8: invokedynamic #542,  0            // InvokeDynamic #4:apply:()Lscala/Function1;
        13: invokeinterface #380,  2          // InterfaceMethod scala/collection/Iterator.map:(Lscala/Function1;)Lscala/collection/Iterator;
        18: areturn
      LineNumberTable:
        line 729: 0
      LocalVariableTable:
        Start  Length  Slot  Name   Signature
            0      19     0  this   Lorg/scalactic/anyvals/NonEmptyMap$;
            0      19     1 $this   Lscala/collection/immutable/Map;
            0      19     2  size   I
            0      19     3  step   I
    Signature: #533                         // <K:Ljava/lang/Object;V:Ljava/lang/Object;>(Lscala/collection/immutable/Map<TK;TV;>;II)Lscala/collection/Iterator<Lorg/scalactic/anyvals/NonEmptyMap<TK;TV;>;>;
    MethodParameters:
      Name                           Flags
      $this                          final
      size                           final
      step                           final

  public final <K extends java.lang.Object, V extends java.lang.Object> int size$extension(scala.collection.immutable.Map<K, V>);
    descriptor: (Lscala/collection/immutable/Map;)I
    flags: (0x0011) ACC_PUBLIC, ACC_FINAL
    Code:
      stack=1, locals=2, args_size=2
         0: aload_1
         1: invokeinterface #548,  1          // InterfaceMethod scala/collection/immutable/Map.size:()I
         6: ireturn
      LineNumberTable:
        line 740: 0
      LocalVariableTable:
        Start  Length  Slot  Name   Signature
            0       7     0  this   Lorg/scalactic/anyvals/NonEmptyMap$;
            0       7     1 $this   Lscala/collection/immutable/Map;
    Signature: #545                         // <K:Ljava/lang/Object;V:Ljava/lang/Object;>(Lscala/collection/immutable/Map<TK;TV;>;)I
    MethodParameters:
      Name                           Flags
      $this                          final

  public final <K extends java.lang.Object, V extends java.lang.Object> java.lang.String stringPrefix$extension(scala.collection.immutable.Map<K, V>);
    descriptor: (Lscala/collection/immutable/Map;)Ljava/lang/String;
    flags: (0x0011) ACC_PUBLIC, ACC_FINAL
    Code:
      stack=1, locals=2, args_size=2
         0: ldc_w         #551                // String NonEmptyMap
         3: areturn
      LineNumberTable:
        line 747: 0
      LocalVariableTable:
        Start  Length  Slot  Name   Signature
            0       4     0  this   Lorg/scalactic/anyvals/NonEmptyMap$;
            0       4     1 $this   Lscala/collection/immutable/Map;
    Signature: #446                         // <K:Ljava/lang/Object;V:Ljava/lang/Object;>(Lscala/collection/immutable/Map<TK;TV;>;)Ljava/lang/String;
    MethodParameters:
      Name                           Flags
      $this                          final

  public final <U extends java.lang.Object, K extends java.lang.Object, V extends java.lang.Object> U sum$extension(scala.collection.immutable.Map<K, V>, scala.math.Numeric<U>);
    descriptor: (Lscala/collection/immutable/Map;Lscala/math/Numeric;)Ljava/lang/Object;
    flags: (0x0011) ACC_PUBLIC, ACC_FINAL
    Code:
      stack=2, locals=3, args_size=3
         0: aload_1
         1: aload_2
         2: invokeinterface #555,  2          // InterfaceMethod scala/collection/immutable/Map.sum:(Lscala/math/Numeric;)Ljava/lang/Object;
         7: areturn
      LineNumberTable:
        line 758: 0
      LocalVariableTable:
        Start  Length  Slot  Name   Signature
            0       8     0  this   Lorg/scalactic/anyvals/NonEmptyMap$;
            0       8     1 $this   Lscala/collection/immutable/Map;
            0       8     2   num   Lscala/math/Numeric;
    Signature: #464                         // <U:Ljava/lang/Object;K:Ljava/lang/Object;V:Ljava/lang/Object;>(Lscala/collection/immutable/Map<TK;TV;>;Lscala/math/Numeric<TU;>;)TU;
    MethodParameters:
      Name                           Flags
      $this                          final
      num                            final

  public final <Col extends java.lang.Object, K extends java.lang.Object, V extends java.lang.Object> Col to$extension(scala.collection.immutable.Map<K, V>, scala.collection.Factory<scala.Tuple2<K, V>, Col>);
    descriptor: (Lscala/collection/immutable/Map;Lscala/collection/Factory;)Ljava/lang/Object;
    flags: (0x0011) ACC_PUBLIC, ACC_FINAL
    Code:
      stack=2, locals=3, args_size=3
         0: aload_1
         1: aload_2
         2: invokeinterface #563,  2          // InterfaceMethod scala/collection/immutable/Map.to:(Lscala/collection/Factory;)Ljava/lang/Object;
         7: areturn
      LineNumberTable:
        line 770: 0
      LocalVariableTable:
        Start  Length  Slot  Name   Signature
            0       8     0  this   Lorg/scalactic/anyvals/NonEmptyMap$;
            0       8     1 $this   Lscala/collection/immutable/Map;
            0       8     2 factory   Lscala/collection/Factory;
    Signature: #558                         // <Col:Ljava/lang/Object;K:Ljava/lang/Object;V:Ljava/lang/Object;>(Lscala/collection/immutable/Map<TK;TV;>;Lscala/collection/Factory<Lscala/Tuple2<TK;TV;>;TCol;>;)TCol;
    MethodParameters:
      Name                           Flags
      $this                          final
      factory                        final

  public final <U extends java.lang.Object, K extends java.lang.Object, V extends java.lang.Object> java.lang.Object toArray$extension(scala.collection.immutable.Map<K, V>, scala.reflect.ClassTag<U>);
    descriptor: (Lscala/collection/immutable/Map;Lscala/reflect/ClassTag;)Ljava/lang/Object;
    flags: (0x0011) ACC_PUBLIC, ACC_FINAL
    Code:
      stack=2, locals=3, args_size=3
         0: aload_1
         1: aload_2
         2: invokeinterface #572,  2          // InterfaceMethod scala/collection/immutable/Map.toArray:(Lscala/reflect/ClassTag;)Ljava/lang/Object;
         7: areturn
      LineNumberTable:
        line 777: 0
      LocalVariableTable:
        Start  Length  Slot  Name   Signature
            0       8     0  this   Lorg/scalactic/anyvals/NonEmptyMap$;
            0       8     1 $this   Lscala/collection/immutable/Map;
            0       8     2 classTag   Lscala/reflect/ClassTag;
    Signature: #567                         // <U:Ljava/lang/Object;K:Ljava/lang/Object;V:Ljava/lang/Object;>(Lscala/collection/immutable/Map<TK;TV;>;Lscala/reflect/ClassTag<TU;>;)Ljava/lang/Object;
    MethodParameters:
      Name                           Flags
      $this                          final
      classTag                       final

  public final <K extends java.lang.Object, V extends java.lang.Object> scala.collection.immutable.Vector<scala.Tuple2<K, V>> toVector$extension(scala.collection.immutable.Map<K, V>);
    descriptor: (Lscala/collection/immutable/Map;)Lscala/collection/immutable/Vector;
    flags: (0x0011) ACC_PUBLIC, ACC_FINAL
    Code:
      stack=1, locals=2, args_size=2
         0: aload_1
         1: invokeinterface #577,  1          // InterfaceMethod scala/collection/immutable/Map.toVector:()Lscala/collection/immutable/Vector;
         6: areturn
      LineNumberTable:
        line 784: 0
      LocalVariableTable:
        Start  Length  Slot  Name   Signature
            0       7     0  this   Lorg/scalactic/anyvals/NonEmptyMap$;
            0       7     1 $this   Lscala/collection/immutable/Map;
    Signature: #576                         // <K:Ljava/lang/Object;V:Ljava/lang/Object;>(Lscala/collection/immutable/Map<TK;TV;>;)Lscala/collection/immutable/Vector<Lscala/Tuple2<TK;TV;>;>;
    MethodParameters:
      Name                           Flags
      $this                          final

  public final <U extends java.lang.Object, K extends java.lang.Object, V extends java.lang.Object> scala.collection.mutable.Buffer<U> toBuffer$extension(scala.collection.immutable.Map<K, V>);
    descriptor: (Lscala/collection/immutable/Map;)Lscala/collection/mutable/Buffer;
    flags: (0x0011) ACC_PUBLIC, ACC_FINAL
    Code:
      stack=1, locals=2, args_size=2
         0: aload_1
         1: invokeinterface #584,  1          // InterfaceMethod scala/collection/immutable/Map.toBuffer:()Lscala/collection/mutable/Buffer;
         6: areturn
      LineNumberTable:
        line 791: 0
      LocalVariableTable:
        Start  Length  Slot  Name   Signature
            0       7     0  this   Lorg/scalactic/anyvals/NonEmptyMap$;
            0       7     1 $this   Lscala/collection/immutable/Map;
    Signature: #580                         // <U:Ljava/lang/Object;K:Ljava/lang/Object;V:Ljava/lang/Object;>(Lscala/collection/immutable/Map<TK;TV;>;)Lscala/collection/mutable/Buffer<TU;>;
    MethodParameters:
      Name                           Flags
      $this                          final

  public final <K extends java.lang.Object, V extends java.lang.Object> scala.collection.immutable.IndexedSeq<scala.Tuple2<K, V>> toIndexedSeq$extension(scala.collection.immutable.Map<K, V>);
    descriptor: (Lscala/collection/immutable/Map;)Lscala/collection/immutable/IndexedSeq;
    flags: (0x0011) ACC_PUBLIC, ACC_FINAL
    Code:
      stack=1, locals=2, args_size=2
         0: aload_1
         1: invokeinterface #577,  1          // InterfaceMethod scala/collection/immutable/Map.toVector:()Lscala/collection/immutable/Vector;
         6: areturn
      LineNumberTable:
        line 798: 0
      LocalVariableTable:
        Start  Length  Slot  Name   Signature
            0       7     0  this   Lorg/scalactic/anyvals/NonEmptyMap$;
            0       7     1 $this   Lscala/collection/immutable/Map;
    Signature: #587                         // <K:Ljava/lang/Object;V:Ljava/lang/Object;>(Lscala/collection/immutable/Map<TK;TV;>;)Lscala/collection/immutable/IndexedSeq<Lscala/Tuple2<TK;TV;>;>;
    MethodParameters:
      Name                           Flags
      $this                          final

  public final <K extends java.lang.Object, V extends java.lang.Object> scala.collection.Iterable<scala.Tuple2<K, V>> toIterable$extension(scala.collection.immutable.Map<K, V>);
    descriptor: (Lscala/collection/immutable/Map;)Lscala/collection/Iterable;
    flags: (0x0011) ACC_PUBLIC, ACC_FINAL
    Code:
      stack=1, locals=2, args_size=2
         0: aload_1
         1: invokeinterface #594,  1          // InterfaceMethod scala/collection/immutable/Map.toIterable:()Lscala/collection/Iterable;
         6: areturn
      LineNumberTable:
        line 805: 0
      LocalVariableTable:
        Start  Length  Slot  Name   Signature
            0       7     0  this   Lorg/scalactic/anyvals/NonEmptyMap$;
            0       7     1 $this   Lscala/collection/immutable/Map;
    Signature: #590                         // <K:Ljava/lang/Object;V:Ljava/lang/Object;>(Lscala/collection/immutable/Map<TK;TV;>;)Lscala/collection/Iterable<Lscala/Tuple2<TK;TV;>;>;
    MethodParameters:
      Name                           Flags
      $this                          final

  public final <K extends java.lang.Object, V extends java.lang.Object> scala.collection.Iterator<scala.Tuple2<K, V>> toIterator$extension(scala.collection.immutable.Map<K, V>);
    descriptor: (Lscala/collection/immutable/Map;)Lscala/collection/Iterator;
    flags: (0x0011) ACC_PUBLIC, ACC_FINAL
    Code:
      stack=1, locals=2, args_size=2
         0: aload_1
         1: invokeinterface #598,  1          // InterfaceMethod scala/collection/immutable/Map.toIterator:()Lscala/collection/Iterator;
         6: areturn
      LineNumberTable:
        line 812: 0
      LocalVariableTable:
        Start  Length  Slot  Name   Signature
            0       7     0  this   Lorg/scalactic/anyvals/NonEmptyMap$;
            0       7     1 $this   Lscala/collection/immutable/Map;
    Signature: #402                         // <K:Ljava/lang/Object;V:Ljava/lang/Object;>(Lscala/collection/immutable/Map<TK;TV;>;)Lscala/collection/Iterator<Lscala/Tuple2<TK;TV;>;>;
    MethodParameters:
      Name                           Flags
      $this                          final

  public final <K extends java.lang.Object, V extends java.lang.Object> scala.collection.immutable.Seq<scala.Tuple2<K, V>> toSeq$extension(scala.collection.immutable.Map<K, V>);
    descriptor: (Lscala/collection/immutable/Map;)Lscala/collection/immutable/Seq;
    flags: (0x0011) ACC_PUBLIC, ACC_FINAL
    Code:
      stack=2, locals=2, args_size=2
         0: getstatic     #604                // Field scala/collection/immutable/Seq$.MODULE$:Lscala/collection/immutable/Seq$;
         3: invokevirtual #607                // Method scala/collection/immutable/Seq$.empty:()Lscala/collection/SeqOps;
         6: aload_1
         7: invokeinterface #611,  1          // InterfaceMethod scala/collection/immutable/Map.toSeq:()Lscala/collection/immutable/Seq;
        12: invokeinterface #616,  2          // InterfaceMethod scala/collection/SeqOps.$plus$plus:(Lscala/collection/IterableOnce;)Ljava/lang/Object;
        17: checkcast     #35                 // class scala/collection/immutable/Seq
        20: areturn
      LineNumberTable:
        line 819: 0
      LocalVariableTable:
        Start  Length  Slot  Name   Signature
            0      21     0  this   Lorg/scalactic/anyvals/NonEmptyMap$;
            0      21     1 $this   Lscala/collection/immutable/Map;
    Signature: #599                         // <K:Ljava/lang/Object;V:Ljava/lang/Object;>(Lscala/collection/immutable/Map<TK;TV;>;)Lscala/collection/immutable/Seq<Lscala/Tuple2<TK;TV;>;>;
    MethodParameters:
      Name                           Flags
      $this                          final

  public final <U extends java.lang.Object, K extends java.lang.Object, V extends java.lang.Object> scala.collection.immutable.Set<U> toSet$extension(scala.collection.immutable.Map<K, V>);
    descriptor: (Lscala/collection/immutable/Map;)Lscala/collection/immutable/Set;
    flags: (0x0011) ACC_PUBLIC, ACC_FINAL
    Code:
      stack=1, locals=2, args_size=2
         0: aload_1
         1: invokeinterface #623,  1          // InterfaceMethod scala/collection/immutable/Map.toSet:()Lscala/collection/immutable/Set;
         6: areturn
      LineNumberTable:
        line 826: 0
      LocalVariableTable:
        Start  Length  Slot  Name   Signature
            0       7     0  this   Lorg/scalactic/anyvals/NonEmptyMap$;
            0       7     1 $this   Lscala/collection/immutable/Map;
    Signature: #619                         // <U:Ljava/lang/Object;K:Ljava/lang/Object;V:Ljava/lang/Object;>(Lscala/collection/immutable/Map<TK;TV;>;)Lscala/collection/immutable/Set<TU;>;
    MethodParameters:
      Name                           Flags
      $this                          final

  public final <K extends java.lang.Object, V extends java.lang.Object> scala.collection.immutable.Stream<scala.Tuple2<K, V>> toStream$extension(scala.collection.immutable.Map<K, V>);
    descriptor: (Lscala/collection/immutable/Map;)Lscala/collection/immutable/Stream;
    flags: (0x0011) ACC_PUBLIC, ACC_FINAL
    Code:
      stack=1, locals=2, args_size=2
         0: aload_1
         1: invokeinterface #630,  1          // InterfaceMethod scala/collection/immutable/Map.toStream:()Lscala/collection/immutable/Stream;
         6: areturn
      LineNumberTable:
        line 833: 0
      LocalVariableTable:
        Start  Length  Slot  Name   Signature
            0       7     0  this   Lorg/scalactic/anyvals/NonEmptyMap$;
            0       7     1 $this   Lscala/collection/immutable/Map;
    Signature: #626                         // <K:Ljava/lang/Object;V:Ljava/lang/Object;>(Lscala/collection/immutable/Map<TK;TV;>;)Lscala/collection/immutable/Stream<Lscala/Tuple2<TK;TV;>;>;
    MethodParameters:
      Name                           Flags
      $this                          final

  public final <K extends java.lang.Object, V extends java.lang.Object> java.lang.String toString$extension(scala.collection.immutable.Map<K, V>);
    descriptor: (Lscala/collection/immutable/Map;)Ljava/lang/String;
    flags: (0x0011) ACC_PUBLIC, ACC_FINAL
    Code:
      stack=3, locals=2, args_size=2
         0: new           #633                // class java/lang/StringBuilder
         3: dup
         4: ldc_w         #634                // int 13
         7: invokespecial #637                // Method java/lang/StringBuilder."<init>":(I)V
        10: ldc_w         #639                // String NonEmptyMap(
        13: invokevirtual #643                // Method java/lang/StringBuilder.append:(Ljava/lang/String;)Ljava/lang/StringBuilder;
        16: aload_1
        17: ldc_w         #645                // String ,
        20: invokeinterface #455,  2          // InterfaceMethod scala/collection/immutable/Map.mkString:(Ljava/lang/String;)Ljava/lang/String;
        25: invokevirtual #643                // Method java/lang/StringBuilder.append:(Ljava/lang/String;)Ljava/lang/StringBuilder;
        28: ldc_w         #647                // String )
        31: invokevirtual #643                // Method java/lang/StringBuilder.append:(Ljava/lang/String;)Ljava/lang/StringBuilder;
        34: invokevirtual #650                // Method java/lang/StringBuilder.toString:()Ljava/lang/String;
        37: areturn
      LineNumberTable:
        line 841: 0
      LocalVariableTable:
        Start  Length  Slot  Name   Signature
            0      38     0  this   Lorg/scalactic/anyvals/NonEmptyMap$;
            0      38     1 $this   Lscala/collection/immutable/Map;
    Signature: #446                         // <K:Ljava/lang/Object;V:Ljava/lang/Object;>(Lscala/collection/immutable/Map<TK;TV;>;)Ljava/lang/String;
    MethodParameters:
      Name                           Flags
      $this                          final

  public final <L extends java.lang.Object, R extends java.lang.Object, K extends java.lang.Object, V extends java.lang.Object> scala.Tuple2<scala.collection.immutable.Iterable<L>, scala.collection.immutable.Iterable<R>> unzip$extension(scala.collection.immutable.Map<K, V>, scala.Function1<scala.Tuple2<K, V>, scala.Tuple2<L, R>>);
    descriptor: (Lscala/collection/immutable/Map;Lscala/Function1;)Lscala/Tuple2;
    flags: (0x0011) ACC_PUBLIC, ACC_FINAL
    Code:
      stack=2, locals=3, args_size=3
         0: aload_1
         1: aload_2
         2: invokeinterface #658,  2          // InterfaceMethod scala/collection/immutable/Map.unzip:(Lscala/Function1;)Lscala/Tuple2;
         7: areturn
      LineNumberTable:
        line 851: 0
      LocalVariableTable:
        Start  Length  Slot  Name   Signature
            0       8     0  this   Lorg/scalactic/anyvals/NonEmptyMap$;
            0       8     1 $this   Lscala/collection/immutable/Map;
            0       8     2 asPair   Lscala/Function1;
    Signature: #653                         // <L:Ljava/lang/Object;R:Ljava/lang/Object;K:Ljava/lang/Object;V:Ljava/lang/Object;>(Lscala/collection/immutable/Map<TK;TV;>;Lscala/Function1<Lscala/Tuple2<TK;TV;>;Lscala/Tuple2<TL;TR;>;>;)Lscala/Tuple2<Lscala/collection/immutable/Iterable<TL;>;Lscala/collection/immutable/Iterable<TR;>;>;
    MethodParameters:
      Name                           Flags
      $this                          final
      asPair                         final

  public final <L extends java.lang.Object, M extends java.lang.Object, R extends java.lang.Object, K extends java.lang.Object, V extends java.lang.Object> scala.Tuple3<scala.collection.immutable.Iterable<L>, scala.collection.immutable.Iterable<M>, scala.collection.immutable.Iterable<R>> unzip3$extension(scala.collection.immutable.Map<K, V>, scala.Function1<scala.Tuple2<K, V>, scala.Tuple3<L, M, R>>);
    descriptor: (Lscala/collection/immutable/Map;Lscala/Function1;)Lscala/Tuple3;
    flags: (0x0011) ACC_PUBLIC, ACC_FINAL
    Code:
      stack=2, locals=3, args_size=3
         0: aload_1
         1: aload_2
         2: invokeinterface #666,  2          // InterfaceMethod scala/collection/immutable/Map.unzip3:(Lscala/Function1;)Lscala/Tuple3;
         7: areturn
      LineNumberTable:
        line 862: 0
      LocalVariableTable:
        Start  Length  Slot  Name   Signature
            0       8     0  this   Lorg/scalactic/anyvals/NonEmptyMap$;
            0       8     1 $this   Lscala/collection/immutable/Map;
            0       8     2 asTriple   Lscala/Function1;
    Signature: #661                         // <L:Ljava/lang/Object;M:Ljava/lang/Object;R:Ljava/lang/Object;K:Ljava/lang/Object;V:Ljava/lang/Object;>(Lscala/collection/immutable/Map<TK;TV;>;Lscala/Function1<Lscala/Tuple2<TK;TV;>;Lscala/Tuple3<TL;TM;TR;>;>;)Lscala/Tuple3<Lscala/collection/immutable/Iterable<TL;>;Lscala/collection/immutable/Iterable<TM;>;Lscala/collection/immutable/Iterable<TR;>;>;
    MethodParameters:
      Name                           Flags
      $this                          final
      asTriple                       final

  public final <V1 extends java.lang.Object, K extends java.lang.Object, V extends java.lang.Object> scala.collection.immutable.Map<K, V1> updated$extension(scala.collection.immutable.Map<K, V>, K, V1);
    descriptor: (Lscala/collection/immutable/Map;Ljava/lang/Object;Ljava/lang/Object;)Lscala/collection/immutable/Map;
    flags: (0x0011) ACC_PUBLIC, ACC_FINAL
    Code:
      stack=3, locals=4, args_size=4
         0: aload_1
         1: aload_2
         2: aload_3
         3: invokeinterface #673,  3          // InterfaceMethod scala/collection/immutable/Map.updated:(Ljava/lang/Object;Ljava/lang/Object;)Lscala/collection/immutable/MapOps;
         8: checkcast     #41                 // class scala/collection/immutable/Map
        11: areturn
      LineNumberTable:
        line 872: 0
      LocalVariableTable:
        Start  Length  Slot  Name   Signature
            0      12     0  this   Lorg/scalactic/anyvals/NonEmptyMap$;
            0      12     1 $this   Lscala/collection/immutable/Map;
            0      12     2   key   Ljava/lang/Object;
            0      12     3 value   Ljava/lang/Object;
    Signature: #669                         // <V1:Ljava/lang/Object;K:Ljava/lang/Object;V:Ljava/lang/Object;>(Lscala/collection/immutable/Map<TK;TV;>;TK;TV1;)Lscala/collection/immutable/Map<TK;TV1;>;
    MethodParameters:
      Name                           Flags
      $this                          final
      key                            final
      value                          final

  public final <O extends java.lang.Object, V1 extends java.lang.Object, K extends java.lang.Object, V extends java.lang.Object> scala.collection.immutable.Map<scala.Tuple2<K, V1>, O> zipAll$extension(scala.collection.immutable.Map<K, V>, scala.collection.Iterable<O>, scala.Tuple2<K, V1>, O);
    descriptor: (Lscala/collection/immutable/Map;Lscala/collection/Iterable;Lscala/Tuple2;Ljava/lang/Object;)Lscala/collection/immutable/Map;
    flags: (0x0011) ACC_PUBLIC, ACC_FINAL
    Code:
      stack=4, locals=5, args_size=5
         0: aload_1
         1: aload_2
         2: aload_3
         3: aload         4
         5: invokeinterface #682,  4          // InterfaceMethod scala/collection/immutable/Map.zipAll:(Lscala/collection/Iterable;Ljava/lang/Object;Ljava/lang/Object;)Ljava/lang/Object;
        10: checkcast     #103                // class scala/collection/IterableOnceOps
        13: getstatic     #29                 // Field scala/$less$colon$less$.MODULE$:Lscala/$less$colon$less$;
        16: invokevirtual #33                 // Method scala/$less$colon$less$.refl:()Lscala/$eq$colon$eq;
        19: invokeinterface #104,  2          // InterfaceMethod scala/collection/IterableOnceOps.toMap:(Lscala/$less$colon$less;)Lscala/collection/immutable/Map;
        24: areturn
      LineNumberTable:
        line 890: 0
      LocalVariableTable:
        Start  Length  Slot  Name   Signature
            0      25     0  this   Lorg/scalactic/anyvals/NonEmptyMap$;
            0      25     1 $this   Lscala/collection/immutable/Map;
            0      25     2 other   Lscala/collection/Iterable;
            0      25     3 thisElem   Lscala/Tuple2;
            0      25     4 otherElem   Ljava/lang/Object;
    Signature: #676                         // <O:Ljava/lang/Object;V1:Ljava/lang/Object;K:Ljava/lang/Object;V:Ljava/lang/Object;>(Lscala/collection/immutable/Map<TK;TV;>;Lscala/collection/Iterable<TO;>;Lscala/Tuple2<TK;TV1;>;TO;)Lscala/collection/immutable/Map<Lscala/Tuple2<TK;TV1;>;TO;>;
    MethodParameters:
      Name                           Flags
      $this                          final
      other                          final
      thisElem                       final
      otherElem                      final

  public final <V1 extends java.lang.Object, K extends java.lang.Object, V extends java.lang.Object> scala.collection.immutable.Map<scala.Tuple2<K, V1>, java.lang.Object> zipWithIndex$extension(scala.collection.immutable.Map<K, V>);
    descriptor: (Lscala/collection/immutable/Map;)Lscala/collection/immutable/Map;
    flags: (0x0011) ACC_PUBLIC, ACC_FINAL
    Code:
      stack=2, locals=2, args_size=2
         0: aload_1
         1: invokeinterface #687,  1          // InterfaceMethod scala/collection/immutable/Map.zipWithIndex:()Ljava/lang/Object;
         6: checkcast     #103                // class scala/collection/IterableOnceOps
         9: getstatic     #29                 // Field scala/$less$colon$less$.MODULE$:Lscala/$less$colon$less$;
        12: invokevirtual #33                 // Method scala/$less$colon$less$.refl:()Lscala/$eq$colon$eq;
        15: invokeinterface #104,  2          // InterfaceMethod scala/collection/IterableOnceOps.toMap:(Lscala/$less$colon$less;)Lscala/collection/immutable/Map;
        20: areturn
      LineNumberTable:
        line 897: 0
      LocalVariableTable:
        Start  Length  Slot  Name   Signature
            0      21     0  this   Lorg/scalactic/anyvals/NonEmptyMap$;
            0      21     1 $this   Lscala/collection/immutable/Map;
    Signature: #684                         // <V1:Ljava/lang/Object;K:Ljava/lang/Object;V:Ljava/lang/Object;>(Lscala/collection/immutable/Map<TK;TV;>;)Lscala/collection/immutable/Map<Lscala/Tuple2<TK;TV1;>;Ljava/lang/Object;>;
    MethodParameters:
      Name                           Flags
      $this                          final

  public final <K extends java.lang.Object, V extends java.lang.Object> int hashCode$extension(scala.collection.immutable.Map<K, V>);
    descriptor: (Lscala/collection/immutable/Map;)I
    flags: (0x0011) ACC_PUBLIC, ACC_FINAL
    Code:
      stack=1, locals=2, args_size=2
         0: aload_1
         1: invokeinterface #691,  1          // InterfaceMethod scala/collection/Map.hashCode:()I
         6: ireturn
      LineNumberTable:
        line 108: 0
      LocalVariableTable:
        Start  Length  Slot  Name   Signature
            0       7     0  this   Lorg/scalactic/anyvals/NonEmptyMap$;
            0       7     1 $this   Lscala/collection/immutable/Map;
    Signature: #545                         // <K:Ljava/lang/Object;V:Ljava/lang/Object;>(Lscala/collection/immutable/Map<TK;TV;>;)I
    MethodParameters:
      Name                           Flags
      $this                          final

  public final <K extends java.lang.Object, V extends java.lang.Object> boolean equals$extension(scala.collection.immutable.Map<K, V>, java.lang.Object);
    descriptor: (Lscala/collection/immutable/Map;Ljava/lang/Object;)Z
    flags: (0x0011) ACC_PUBLIC, ACC_FINAL
    Code:
      stack=2, locals=7, args_size=3
         0: aload_2
         1: astore        4
         3: aload         4
         5: instanceof    #89                 // class org/scalactic/anyvals/NonEmptyMap
         8: ifeq          16
        11: iconst_1
        12: istore_3
        13: goto          24
        16: goto          19
        19: iconst_0
        20: istore_3
        21: goto          24
        24: iload_3
        25: ifeq          83
        28: aload_2
        29: ifnonnull     36
        32: aconst_null
        33: goto          43
        36: aload_2
        37: checkcast     #89                 // class org/scalactic/anyvals/NonEmptyMap
        40: invokevirtual #696                // Method org/scalactic/anyvals/NonEmptyMap.toMap:()Lscala/collection/immutable/Map;
        43: astore        5
        45: aload_1
        46: aload         5
        48: astore        6
        50: dup
        51: ifnonnull     63
        54: pop
        55: aload         6
        57: ifnull        71
        60: goto          75
        63: aload         6
        65: invokevirtual #81                 // Method java/lang/Object.equals:(Ljava/lang/Object;)Z
        68: ifeq          75
        71: iconst_1
        72: goto          76
        75: iconst_0
        76: ifeq          83
        79: iconst_1
        80: goto          84
        83: iconst_0
        84: ireturn
      StackMapTable: number_of_entries = 11
        frame_type = 253 /* append */
          offset_delta = 16
          locals = [ top, class java/lang/Object ]
        frame_type = 2 /* same */
        frame_type = 255 /* full_frame */
          offset_delta = 4
          locals = [ class org/scalactic/anyvals/NonEmptyMap$, class scala/collection/immutable/Map, class java/lang/Object, int, class java/lang/Object ]
          stack = []
        frame_type = 11 /* same */
        frame_type = 70 /* same_locals_1_stack_item */
          stack = [ class scala/collection/immutable/Map ]
        frame_type = 255 /* full_frame */
          offset_delta = 19
          locals = [ class org/scalactic/anyvals/NonEmptyMap$, class scala/collection/immutable/Map, class java/lang/Object, int, class java/lang/Object, class scala/collection/immutable/Map, class scala/collection/immutable/Map ]
          stack = [ class scala/collection/immutable/Map ]
        frame_type = 7 /* same */
        frame_type = 3 /* same */
        frame_type = 64 /* same_locals_1_stack_item */
          stack = [ int ]
        frame_type = 249 /* chop */
          offset_delta = 6
        frame_type = 64 /* same_locals_1_stack_item */
          stack = [ int ]
      LineNumberTable:
        line 108: 0
      LocalVariableTable:
        Start  Length  Slot  Name   Signature
            0      85     0  this   Lorg/scalactic/anyvals/NonEmptyMap$;
            0      85     1 $this   Lscala/collection/immutable/Map;
            0      85     2   x$1   Ljava/lang/Object;
    Signature: #693                         // <K:Ljava/lang/Object;V:Ljava/lang/Object;>(Lscala/collection/immutable/Map<TK;TV;>;Ljava/lang/Object;)Z
    MethodParameters:
      Name                           Flags
      $this                          final
      x$1                            final

  public static final scala.collection.mutable.ArrayBuffer $anonfun$flatMap$1(scala.collection.mutable.ArrayBuffer, scala.Function1, scala.Tuple2);
    descriptor: (Lscala/collection/mutable/ArrayBuffer;Lscala/Function1;Lscala/Tuple2;)Lscala/collection/mutable/ArrayBuffer;
    flags: (0x1019) ACC_PUBLIC, ACC_STATIC, ACC_FINAL, ACC_SYNTHETIC
    Code:
      stack=3, locals=3, args_size=3
         0: aload_0
         1: aload_1
         2: aload_2
         3: invokeinterface #702,  2          // InterfaceMethod scala/Function1.apply:(Ljava/lang/Object;)Ljava/lang/Object;
         8: checkcast     #89                 // class org/scalactic/anyvals/NonEmptyMap
        11: invokevirtual #696                // Method org/scalactic/anyvals/NonEmptyMap.toMap:()Lscala/collection/immutable/Map;
        14: invokevirtual #706                // Method scala/collection/mutable/ArrayBuffer.$plus$plus$eq:(Lscala/collection/IterableOnce;)Lscala/collection/mutable/Growable;
        17: checkcast     #285                // class scala/collection/mutable/ArrayBuffer
        20: areturn
      LineNumberTable:
        line 344: 0
      LocalVariableTable:
        Start  Length  Slot  Name   Signature
            0      21     0 buf$1   Lscala/collection/mutable/ArrayBuffer;
            0      21     1   f$1   Lscala/Function1;
            0      21     2   ele   Lscala/Tuple2;
    MethodParameters:
      Name                           Flags
      buf$1                          final
      f$1                            final
      ele                            final

  public static final scala.collection.immutable.Map $anonfun$groupBy$1(scala.collection.immutable.Map);
    descriptor: (Lscala/collection/immutable/Map;)Lscala/collection/immutable/Map;
    flags: (0x1019) ACC_PUBLIC, ACC_STATIC, ACC_FINAL, ACC_SYNTHETIC
    Code:
      stack=1, locals=1, args_size=1
         0: aload_0
         1: areturn
      LineNumberTable:
        line 433: 0
      LocalVariableTable:
        Start  Length  Slot  Name   Signature
            0       2     0  list   Lscala/collection/immutable/Map;
    MethodParameters:
      Name                           Flags
      list                           final

  public static final scala.collection.immutable.Map $anonfun$grouped$1(scala.collection.immutable.Map);
    descriptor: (Lscala/collection/immutable/Map;)Lscala/collection/immutable/Map;
    flags: (0x1019) ACC_PUBLIC, ACC_STATIC, ACC_FINAL, ACC_SYNTHETIC
    Code:
      stack=1, locals=1, args_size=1
         0: aload_0
         1: areturn
      LineNumberTable:
        line 444: 0
      LocalVariableTable:
        Start  Length  Slot  Name   Signature
            0       2     0  list   Lscala/collection/immutable/Map;
    MethodParameters:
      Name                           Flags
      list                           final

  public static final scala.collection.immutable.Map $anonfun$sliding$1(scala.collection.immutable.Map);
    descriptor: (Lscala/collection/immutable/Map;)Lscala/collection/immutable/Map;
    flags: (0x1019) ACC_PUBLIC, ACC_STATIC, ACC_FINAL, ACC_SYNTHETIC
    Code:
      stack=1, locals=1, args_size=1
         0: aload_0
         1: areturn
      LineNumberTable:
        line 718: 0
      LocalVariableTable:
        Start  Length  Slot  Name   Signature
            0       2     0   x$1   Lscala/collection/immutable/Map;
    MethodParameters:
      Name                           Flags
      x$1                            final

  public static final scala.collection.immutable.Map $anonfun$sliding$2(scala.collection.immutable.Map);
    descriptor: (Lscala/collection/immutable/Map;)Lscala/collection/immutable/Map;
    flags: (0x1019) ACC_PUBLIC, ACC_STATIC, ACC_FINAL, ACC_SYNTHETIC
    Code:
      stack=1, locals=1, args_size=1
         0: aload_0
         1: areturn
      LineNumberTable:
        line 729: 0
      LocalVariableTable:
        Start  Length  Slot  Name   Signature
            0       2     0   x$2   Lscala/collection/immutable/Map;
    MethodParameters:
      Name                           Flags
      x$2                            final

  private org.scalactic.anyvals.NonEmptyMap$();
    descriptor: ()V
    flags: (0x0002) ACC_PRIVATE
    Code:
      stack=1, locals=1, args_size=1
         0: aload_0
         1: invokespecial #713                // Method java/lang/Object."<init>":()V
         4: return
      LineNumberTable:
        line 967: 0
        line 903: 4
      LocalVariableTable:
        Start  Length  Slot  Name   Signature
            0       5     0  this   Lorg/scalactic/anyvals/NonEmptyMap$;

  public static final java.lang.Object $anonfun$groupBy$1$adapted(scala.collection.immutable.Map);
    descriptor: (Lscala/collection/immutable/Map;)Ljava/lang/Object;
    flags: (0x1019) ACC_PUBLIC, ACC_STATIC, ACC_FINAL, ACC_SYNTHETIC
    Code:
      stack=3, locals=1, args_size=1
         0: new           #89                 // class org/scalactic/anyvals/NonEmptyMap
         3: dup
         4: aload_0
         5: invokestatic  #715                // Method $anonfun$groupBy$1:(Lscala/collection/immutable/Map;)Lscala/collection/immutable/Map;
         8: invokespecial #114                // Method org/scalactic/anyvals/NonEmptyMap."<init>":(Lscala/collection/immutable/Map;)V
        11: areturn
      LineNumberTable:
        line 433: 0
      LocalVariableTable:
        Start  Length  Slot  Name   Signature
            0      12     0  list   Lscala/collection/immutable/Map;
    MethodParameters:
      Name                           Flags
      list                           final

  public static final java.lang.Object $anonfun$grouped$1$adapted(scala.collection.immutable.Map);
    descriptor: (Lscala/collection/immutable/Map;)Ljava/lang/Object;
    flags: (0x1019) ACC_PUBLIC, ACC_STATIC, ACC_FINAL, ACC_SYNTHETIC
    Code:
      stack=3, locals=1, args_size=1
         0: new           #89                 // class org/scalactic/anyvals/NonEmptyMap
         3: dup
         4: aload_0
         5: invokestatic  #717                // Method $anonfun$grouped$1:(Lscala/collection/immutable/Map;)Lscala/collection/immutable/Map;
         8: invokespecial #114                // Method org/scalactic/anyvals/NonEmptyMap."<init>":(Lscala/collection/immutable/Map;)V
        11: areturn
      LineNumberTable:
        line 444: 0
      LocalVariableTable:
        Start  Length  Slot  Name   Signature
            0      12     0  list   Lscala/collection/immutable/Map;
    MethodParameters:
      Name                           Flags
      list                           final

  public static final java.lang.Object $anonfun$sliding$1$adapted(scala.collection.immutable.Map);
    descriptor: (Lscala/collection/immutable/Map;)Ljava/lang/Object;
    flags: (0x1019) ACC_PUBLIC, ACC_STATIC, ACC_FINAL, ACC_SYNTHETIC
    Code:
      stack=3, locals=1, args_size=1
         0: new           #89                 // class org/scalactic/anyvals/NonEmptyMap
         3: dup
         4: aload_0
         5: invokestatic  #719                // Method $anonfun$sliding$1:(Lscala/collection/immutable/Map;)Lscala/collection/immutable/Map;
         8: invokespecial #114                // Method org/scalactic/anyvals/NonEmptyMap."<init>":(Lscala/collection/immutable/Map;)V
        11: areturn
      LineNumberTable:
        line 718: 0
      LocalVariableTable:
        Start  Length  Slot  Name   Signature
            0      12     0   x$1   Lscala/collection/immutable/Map;
    MethodParameters:
      Name                           Flags
      x$1                            final

  public static final java.lang.Object $anonfun$sliding$2$adapted(scala.collection.immutable.Map);
    descriptor: (Lscala/collection/immutable/Map;)Ljava/lang/Object;
    flags: (0x1019) ACC_PUBLIC, ACC_STATIC, ACC_FINAL, ACC_SYNTHETIC
    Code:
      stack=3, locals=1, args_size=1
         0: new           #89                 // class org/scalactic/anyvals/NonEmptyMap
         3: dup
         4: aload_0
         5: invokestatic  #721                // Method $anonfun$sliding$2:(Lscala/collection/immutable/Map;)Lscala/collection/immutable/Map;
         8: invokespecial #114                // Method org/scalactic/anyvals/NonEmptyMap."<init>":(Lscala/collection/immutable/Map;)V
        11: areturn
      LineNumberTable:
        line 729: 0
      LocalVariableTable:
        Start  Length  Slot  Name   Signature
            0      12     0   x$2   Lscala/collection/immutable/Map;
    MethodParameters:
      Name                           Flags
      x$2                            final

  private static java.lang.Object $deserializeLambda$(java.lang.invoke.SerializedLambda);
    descriptor: (Ljava/lang/invoke/SerializedLambda;)Ljava/lang/Object;
    flags: (0x100a) ACC_PRIVATE, ACC_STATIC, ACC_SYNTHETIC
    Code:
      stack=1, locals=1, args_size=1
         0: aload_0
         1: invokedynamic #733,  0            // InvokeDynamic #5:lambdaDeserialize:(Ljava/lang/invoke/SerializedLambda;)Ljava/lang/Object;
         6: areturn
}
InnerClasses:
  public static final #10= #7 of #9;      // Lookup=class java/lang/invoke/MethodHandles$Lookup of class java/lang/invoke/MethodHandles
SourceFile: "NonEmptyMap.scala"
BootstrapMethods:
  0: #303 REF_invokeStatic java/lang/invoke/LambdaMetafactory.altMetafactory:(Ljava/lang/invoke/MethodHandles$Lookup;Ljava/lang/String;Ljava/lang/invoke/MethodType;[Ljava/lang/Object;)Ljava/lang/invoke/CallSite;
    Method arguments:
      #287 (Ljava/lang/Object;)Ljava/lang/Object;
      #292 REF_invokeStatic org/scalactic/anyvals/NonEmptyMap$.$anonfun$flatMap$1:(Lscala/collection/mutable/ArrayBuffer;Lscala/Function1;Lscala/Tuple2;)Lscala/collection/mutable/ArrayBuffer;
      #294 (Lscala/Tuple2;)Lscala/collection/mutable/ArrayBuffer;
      #295 5
      #296 1
      #294 (Lscala/Tuple2;)Lscala/collection/mutable/ArrayBuffer;
  1: #303 REF_invokeStatic java/lang/invoke/LambdaMetafactory.altMetafactory:(Ljava/lang/invoke/MethodHandles$Lookup;Ljava/lang/String;Ljava/lang/invoke/MethodType;[Ljava/lang/Object;)Ljava/lang/invoke/CallSite;
    Method arguments:
      #287 (Ljava/lang/Object;)Ljava/lang/Object;
      #350 REF_invokeStatic org/scalactic/anyvals/NonEmptyMap$.$anonfun$groupBy$1$adapted:(Lscala/collection/immutable/Map;)Ljava/lang/Object;
      #351 (Lscala/collection/immutable/Map;)Ljava/lang/Object;
      #295 5
      #296 1
      #351 (Lscala/collection/immutable/Map;)Ljava/lang/Object;
  2: #303 REF_invokeStatic java/lang/invoke/LambdaMetafactory.altMetafactory:(Ljava/lang/invoke/MethodHandles$Lookup;Ljava/lang/String;Ljava/lang/invoke/MethodType;[Ljava/lang/Object;)Ljava/lang/invoke/CallSite;
    Method arguments:
      #287 (Ljava/lang/Object;)Ljava/lang/Object;
      #374 REF_invokeStatic org/scalactic/anyvals/NonEmptyMap$.$anonfun$grouped$1$adapted:(Lscala/collection/immutable/Map;)Ljava/lang/Object;
      #351 (Lscala/collection/immutable/Map;)Ljava/lang/Object;
      #295 5
      #296 1
      #351 (Lscala/collection/immutable/Map;)Ljava/lang/Object;
  3: #303 REF_invokeStatic java/lang/invoke/LambdaMetafactory.altMetafactory:(Ljava/lang/invoke/MethodHandles$Lookup;Ljava/lang/String;Ljava/lang/invoke/MethodType;[Ljava/lang/Object;)Ljava/lang/invoke/CallSite;
    Method arguments:
      #287 (Ljava/lang/Object;)Ljava/lang/Object;
      #530 REF_invokeStatic org/scalactic/anyvals/NonEmptyMap$.$anonfun$sliding$1$adapted:(Lscala/collection/immutable/Map;)Ljava/lang/Object;
      #351 (Lscala/collection/immutable/Map;)Ljava/lang/Object;
      #295 5
      #296 1
      #351 (Lscala/collection/immutable/Map;)Ljava/lang/Object;
  4: #303 REF_invokeStatic java/lang/invoke/LambdaMetafactory.altMetafactory:(Ljava/lang/invoke/MethodHandles$Lookup;Ljava/lang/String;Ljava/lang/invoke/MethodType;[Ljava/lang/Object;)Ljava/lang/invoke/CallSite;
    Method arguments:
      #287 (Ljava/lang/Object;)Ljava/lang/Object;
      #541 REF_invokeStatic org/scalactic/anyvals/NonEmptyMap$.$anonfun$sliding$2$adapted:(Lscala/collection/immutable/Map;)Ljava/lang/Object;
      #351 (Lscala/collection/immutable/Map;)Ljava/lang/Object;
      #295 5
      #296 1
      #351 (Lscala/collection/immutable/Map;)Ljava/lang/Object;
  5: #730 REF_invokeStatic scala/runtime/LambdaDeserialize.bootstrap:(Ljava/lang/invoke/MethodHandles$Lookup;Ljava/lang/String;Ljava/lang/invoke/MethodType;[Ljava/lang/invoke/MethodHandle;)Ljava/lang/invoke/CallSite;
    Method arguments:
      #292 REF_invokeStatic org/scalactic/anyvals/NonEmptyMap$.$anonfun$flatMap$1:(Lscala/collection/mutable/ArrayBuffer;Lscala/Function1;Lscala/Tuple2;)Lscala/collection/mutable/ArrayBuffer;
      #350 REF_invokeStatic org/scalactic/anyvals/NonEmptyMap$.$anonfun$groupBy$1$adapted:(Lscala/collection/immutable/Map;)Ljava/lang/Object;
      #374 REF_invokeStatic org/scalactic/anyvals/NonEmptyMap$.$anonfun$grouped$1$adapted:(Lscala/collection/immutable/Map;)Ljava/lang/Object;
      #530 REF_invokeStatic org/scalactic/anyvals/NonEmptyMap$.$anonfun$sliding$1$adapted:(Lscala/collection/immutable/Map;)Ljava/lang/Object;
      #541 REF_invokeStatic org/scalactic/anyvals/NonEmptyMap$.$anonfun$sliding$2$adapted:(Lscala/collection/immutable/Map;)Ljava/lang/Object;
  ScalaInlineInfo: length = 0x1E9 (unknown attribute)
   01 01 00 61 01 20 01 21 01 02 C3 00 82 01 01 5A
   01 5B 01 02 C5 00 82 01 01 73 01 5B 01 02 C6 00
   82 01 02 0F 01 5B 01 02 C7 00 82 01 02 1A 01 5B
   01 00 AB 00 AC 01 00 B0 00 AC 01 00 B0 00 B1 01
   00 AF 00 89 01 00 AF 00 92 01 00 AF 00 85 01 00
   84 00 89 01 00 84 00 92 01 00 84 00 85 01 00 0F
   00 0E 01 00 B4 00 B5 01 00 B4 00 BD 01 00 B4 00
   C4 01 00 14 00 15 01 00 CB 00 CC 01 00 D3 00 D4
   01 00 DC 00 DD 01 00 E3 00 E4 01 00 E3 00 EC 01
   00 E3 00 F2 01 00 F8 00 F9 01 01 01 01 02 01 02
   B4 00 DD 01 01 0A 01 0B 01 01 11 01 12 01 01 18
   01 19 01 01 39 01 3A 01 01 43 01 3A 01 01 48 01
   3A 01 01 4D 01 0B 01 01 51 01 52 01 00 3F 00 7A
   01 00 3F 00 40 01 01 54 01 19 01 01 6B 01 6C 01
   01 7F 01 80 01 02 B0 02 20 01 01 82 01 83 01 01
   88 00 32 01 01 8B 00 DD 01 00 A2 01 80 01 01 8F
   01 80 01 01 90 01 91 01 01 97 01 83 01 01 9B 00
   32 01 01 9F 01 19 01 01 A4 01 A5 01 01 AD 01 AE
   01 01 B4 01 A5 01 01 B8 01 AE 01 01 BC 01 BD 01
   01 BC 01 C3 01 01 BC 01 C8 01 01 CD 01 80 01 00
   81 00 82 01 01 CE 01 CF 01 01 D7 01 D8 01 01 DE
   01 D8 01 01 E3 01 E4 01 01 EA 01 E4 01 01 EF 01
   D8 01 01 F4 01 E4 01 01 F9 02 01 01 01 F9 01 FA
   01 01 F9 02 03 01 02 05 02 06 01 02 1F 02 20 01
   02 0B 01 6C 01 02 0B 02 14 01 02 25 01 BD 01 02
   28 01 CF 01 02 2C 02 2D 01 02 35 02 36 01 02 42
   02 43 01 02 49 02 4A 01 02 4C 02 4D 01 02 53 01
   91 01 00 37 00 38 01 02 69 02 6A 01 02 70 02 71
   01 02 77 01 BD 01 02 3E 02 3F 01 00 31 00 32 01
   02 8B 02 8C 01 02 93 02 94 01 02 9B 02 9C 01 02
   A2 02 A3 01 02 AB 00 82 01
  Scala: length = 0x0 (unknown attribute)

