Classfile /Users/mw/Projects/slang-braindump/.jar/jar11/assemble/slang-braindump/assemble/content/org/scalactic/anyvals/PercentageIntMacro.class
  Last modified May 29, 2022; size 1539 bytes
  SHA-256 checksum 759318b7815d1bb25ab7fe41c5960706f2869b528eb440f72938ad6beb7b420e
  Compiled from "PercentageIntMacros.scala"
public final class org.scalactic.anyvals.PercentageIntMacro
  minor version: 0
  major version: 52
  flags: (0x0031) ACC_PUBLIC, ACC_FINAL, ACC_SUPER
  this_class: #2                          // org/scalactic/anyvals/PercentageIntMacro
  super_class: #4                         // java/lang/Object
  interfaces: 0, fields: 0, methods: 2, attributes: 4
Constant pool:
   #1 = Utf8               org/scalactic/anyvals/PercentageIntMacro
   #2 = Class              #1             // org/scalactic/anyvals/PercentageIntMacro
   #3 = Utf8               java/lang/Object
   #4 = Class              #3             // java/lang/Object
   #5 = Utf8               PercentageIntMacros.scala
   #6 = Utf8               Lscala/reflect/ScalaSignature;
   #7 = Utf8               bytes
   #8 = Utf8               \u0006\u0005\u0011;a!\u0002\u0004\t\u0002!aaA\u0002\b\u0007\u0011\u0003Aq\u0002C\u0003\u0017\u0003\u0011\u0005\u0001\u0004C\u0003\u001a\u0003\u0011\u0005!\u0004C\u0003$\u0003\u0011\u0005A%\u0001\nQKJ\u001cWM\u001c;bO\u0016Le\u000e^\'bGJ|\'BA\u0004\t\u0003\u001d\tg.\u001f<bYNT!!\u0003\u0006\u0002\u0013M\u001c\u0017\r\\1di&\u001c\'\"A\u0006\u0002\u0007=\u0014x\r\u0005\u0002\u000e\u00035\taA\u0001\nQKJ\u001cWM\u001c;bO\u0016Le\u000e^\'bGJ|7CA\u0001\u0011!\t\tB#D\u0001\u0013\u0015\u0005\u0019\u0012!B:dC2\f\u0017BA\u000b\u0013\u0005\u0019\te.\u001f*fM\u00061A(\u001b8jiz\u001a\u0001\u0001F\u0001\r\u0003\u001dI7OV1mS\u0012$\"a\u0007\u0010\u0011\u0005Ea\u0012BA\u000f\u0013\u0005\u001d\u0011un\u001c7fC:DQaH\u0002A\u0002\u0001\n\u0011!\u001b\t\u0003#\u0005J!A\t\n\u0003\u0007%sG/A\u0003baBd\u0017\u0010\u0006\u0002&SQ\u0011a%\u0011\t\u0004OirdB\u0001\u0015*\u0019\u0001AQA\u000b\u0003A\u0002-\n\u0011a\u0019\t\u0003Y]r!!\f\u001b\u000f\u00059\ndBA\t0\u0013\t\u0001$#A\u0004sK\u001adWm\u0019;\n\u0005I\u001a\u0014AB7bGJ|7O\u0003\u00021%%\u0011QGN\u0001\ba\u0006\u001c7.Y4f\u0015\t\u00114\'\u0003\u00029s\t91i\u001c8uKb$(BA\u001b7\u0013\tYDH\u0001\u0003FqB\u0014\u0018BA\u001f7\u0005\u001d\tE.[1tKN\u0004\"!D \n\u0005\u00013!!\u0004)fe\u000e,g\u000e^1hK&sG\u000fC\u0003C\t\u0001\u00071)A\u0003wC2,X\rE\u0002(u\u0001\u0002
   #9 = Utf8               scala/reflect/api/Exprs$Expr
  #10 = Class              #9             // scala/reflect/api/Exprs$Expr
  #11 = Utf8               scala/reflect/api/Exprs
  #12 = Class              #11            // scala/reflect/api/Exprs
  #13 = Utf8               Expr
  #14 = Utf8               apply
  #15 = Utf8               (Lscala/reflect/macros/whitebox/Context;Lscala/reflect/api/Exprs$Expr;)Lscala/reflect/api/Exprs$Expr;
  #16 = Utf8               (Lscala/reflect/macros/whitebox/Context;Lscala/reflect/api/Exprs$Expr<Ljava/lang/Object;>;)Lscala/reflect/api/Exprs$Expr<Lorg/scalactic/anyvals/PercentageInt;>;
  #17 = Utf8               c
  #18 = Utf8               value
  #19 = Utf8               org/scalactic/anyvals/PercentageIntMacro$
  #20 = Class              #19            // org/scalactic/anyvals/PercentageIntMacro$
  #21 = Utf8               MODULE$
  #22 = Utf8               Lorg/scalactic/anyvals/PercentageIntMacro$;
  #23 = NameAndType        #21:#22        // MODULE$:Lorg/scalactic/anyvals/PercentageIntMacro$;
  #24 = Fieldref           #20.#23        // org/scalactic/anyvals/PercentageIntMacro$.MODULE$:Lorg/scalactic/anyvals/PercentageIntMacro$;
  #25 = NameAndType        #14:#15        // apply:(Lscala/reflect/macros/whitebox/Context;Lscala/reflect/api/Exprs$Expr;)Lscala/reflect/api/Exprs$Expr;
  #26 = Methodref          #20.#25        // org/scalactic/anyvals/PercentageIntMacro$.apply:(Lscala/reflect/macros/whitebox/Context;Lscala/reflect/api/Exprs$Expr;)Lscala/reflect/api/Exprs$Expr;
  #27 = Utf8               Lscala/reflect/macros/whitebox/Context;
  #28 = Utf8               Lscala/reflect/api/Exprs$Expr;
  #29 = Utf8               isValid
  #30 = Utf8               (I)Z
  #31 = Utf8               i
  #32 = NameAndType        #29:#30        // isValid:(I)Z
  #33 = Methodref          #20.#32        // org/scalactic/anyvals/PercentageIntMacro$.isValid:(I)Z
  #34 = Utf8               I
  #35 = Utf8               Code
  #36 = Utf8               LocalVariableTable
  #37 = Utf8               Signature
  #38 = Utf8               MethodParameters
  #39 = Utf8               InnerClasses
  #40 = Utf8               SourceFile
  #41 = Utf8               RuntimeVisibleAnnotations
  #42 = Utf8               ScalaSig
{
  public static scala.reflect.api.Exprs$Expr<org.scalactic.anyvals.PercentageInt> apply(scala.reflect.macros.whitebox.Context, scala.reflect.api.Exprs$Expr<java.lang.Object>);
    descriptor: (Lscala/reflect/macros/whitebox/Context;Lscala/reflect/api/Exprs$Expr;)Lscala/reflect/api/Exprs$Expr;
    flags: (0x0009) ACC_PUBLIC, ACC_STATIC
    Code:
      stack=3, locals=2, args_size=2
         0: getstatic     #24                 // Field org/scalactic/anyvals/PercentageIntMacro$.MODULE$:Lorg/scalactic/anyvals/PercentageIntMacro$;
         3: aload_0
         4: aload_1
         5: invokevirtual #26                 // Method org/scalactic/anyvals/PercentageIntMacro$.apply:(Lscala/reflect/macros/whitebox/Context;Lscala/reflect/api/Exprs$Expr;)Lscala/reflect/api/Exprs$Expr;
         8: areturn
      LocalVariableTable:
        Start  Length  Slot  Name   Signature
            0       9     0     c   Lscala/reflect/macros/whitebox/Context;
            0       9     1 value   Lscala/reflect/api/Exprs$Expr;
    Signature: #16                          // (Lscala/reflect/macros/whitebox/Context;Lscala/reflect/api/Exprs$Expr<Ljava/lang/Object;>;)Lscala/reflect/api/Exprs$Expr<Lorg/scalactic/anyvals/PercentageInt;>;
    MethodParameters:
      Name                           Flags
      c                              final
      value                          final

  public static boolean isValid(int);
    descriptor: (I)Z
    flags: (0x0009) ACC_PUBLIC, ACC_STATIC
    Code:
      stack=2, locals=1, args_size=1
         0: getstatic     #24                 // Field org/scalactic/anyvals/PercentageIntMacro$.MODULE$:Lorg/scalactic/anyvals/PercentageIntMacro$;
         3: iload_0
         4: invokevirtual #33                 // Method org/scalactic/anyvals/PercentageIntMacro$.isValid:(I)Z
         7: ireturn
      LocalVariableTable:
        Start  Length  Slot  Name   Signature
            0       8     0     i   I
    MethodParameters:
      Name                           Flags
      i                              final
}
InnerClasses:
  public #13= #10 of #12;                 // Expr=class scala/reflect/api/Exprs$Expr of class scala/reflect/api/Exprs
SourceFile: "PercentageIntMacros.scala"
RuntimeVisibleAnnotations:
  0: #6(#7=s#8)
    scala.reflect.ScalaSignature(
      bytes="\u0006\u0005\u0011;a!\u0002\u0004\t\u0002!aaA\u0002\b\u0007\u0011\u0003Aq\u0002C\u0003\u0017\u0003\u0011\u0005\u0001\u0004C\u0003\u001a\u0003\u0011\u0005!\u0004C\u0003$\u0003\u0011\u0005A%\u0001\nQKJ\u001cWM\u001c;bO\u0016Le\u000e^\'bGJ|\'BA\u0004\t\u0003\u001d\tg.\u001f<bYNT!!\u0003\u0006\u0002\u0013M\u001c\u0017\r\\1di&\u001c\'\"A\u0006\u0002\u0007=\u0014x\r\u0005\u0002\u000e\u00035\taA\u0001\nQKJ\u001cWM\u001c;bO\u0016Le\u000e^\'bGJ|7CA\u0001\u0011!\t\tB#D\u0001\u0013\u0015\u0005\u0019\u0012!B:dC2\f\u0017BA\u000b\u0013\u0005\u0019\te.\u001f*fM\u00061A(\u001b8jiz\u001a\u0001\u0001F\u0001\r\u0003\u001dI7OV1mS\u0012$\"a\u0007\u0010\u0011\u0005Ea\u0012BA\u000f\u0013\u0005\u001d\u0011un\u001c7fC:DQaH\u0002A\u0002\u0001\n\u0011!\u001b\t\u0003#\u0005J!A\t\n\u0003\u0007%sG/A\u0003baBd\u0017\u0010\u0006\u0002&SQ\u0011a%\u0011\t\u0004OirdB\u0001\u0015*\u0019\u0001AQA\u000b\u0003A\u0002-\n\u0011a\u0019\t\u0003Y]r!!\f\u001b\u000f\u00059\ndBA\t0\u0013\t\u0001$#A\u0004sK\u001adWm\u0019;\n\u0005I\u001a\u0014AB7bGJ|7O\u0003\u00021%%\u0011QGN\u0001\ba\u0006\u001c7.Y4f\u0015\t\u00114\'\u0003\u00029s\t91i\u001c8uKb$(BA\u001b7\u0013\tYDH\u0001\u0003FqB\u0014\u0018BA\u001f7\u0005\u001d\tE.[1tKN\u0004\"!D \n\u0005\u00013!!\u0004)fe\u000e,g\u000e^1hK&sG\u000fC\u0003C\t\u0001\u00071)A\u0003wC2,X\rE\u0002(u\u0001\u0002"
    )
  ScalaSig: length = 0x3 (unknown attribute)
   05 02 00
