Classfile /Users/mw/Projects/slang-braindump/.jar/jar11/assemble/slang-braindump/assemble/content/org/scalactic/anyvals/PosFloat.class
  Last modified May 29, 2022; size 30464 bytes
  SHA-256 checksum c5c21f6ed293b9c29e716c1fddc0172678909bbc0e8ee1aa59b4ab2294dfce33
  Compiled from "PosFloat.scala"
public final class org.scalactic.anyvals.PosFloat
  minor version: 0
  major version: 52
  flags: (0x0031) ACC_PUBLIC, ACC_FINAL, ACC_SUPER
  this_class: #2                          // org/scalactic/anyvals/PosFloat
  super_class: #4                         // java/lang/Object
  interfaces: 0, fields: 1, methods: 198, attributes: 4
Constant pool:
    #1 = Utf8               org/scalactic/anyvals/PosFloat
    #2 = Class              #1            // org/scalactic/anyvals/PosFloat
    #3 = Utf8               java/lang/Object
    #4 = Class              #3            // java/lang/Object
    #5 = Utf8               PosFloat.scala
    #6 = Utf8               Lscala/reflect/ScalaSignature;
    #7 = Utf8               bytes
    #8 = Utf8               \u0006\u0005!-baBAT\u0003S\u0013\u0011q\u0017\u0005\u000b\u0003\u000b\u0004!Q1A\u0005\u0002\u0005\u001d\u0007BCAh\u0001\t\u0005\t\u0015!\u0003\u0002J\"q\u0011\u0011\u001b\u0001\u0005\u0002\u0003\u0005\t\u0011!A\u0005\n\u0005M\u0007bBAn\u0001\u0011\u0005\u0013Q\u001c\u0005\b\u0003k\u0004A\u0011AA|\u0011\u001d\ty\u0010\u0001C\u0001\u0005\u0003AqA!\u0003\u0001\t\u0003\u0011Y\u0001C\u0004\u0003\u0014\u0001!\tA!\u0006\t\u000f\tu\u0001\u0001\"\u0001\u0003 !9!q\u0005\u0001\u0005\u0002\u0005\u001d\u0007b\u0002B\u0015\u0001\u0011\u0005!1\u0006\u0005\b\u0005g\u0001A\u0011\u0001B\u001b\u0011\u001d\u00119\u0004\u0001C\u0001\u0005sAqA!\u0011\u0001\t\u0003\u0011\u0019\u0005C\u0004\u0003J\u0001!\tAa\u0013\t\u000f\t%\u0003\u0001\"\u0001\u0003V!9!\u0011\n\u0001\u0005\u0002\te\u0003b\u0002B%\u0001\u0011\u0005!Q\f\u0005\b\u0005\u0013\u0002A\u0011\u0001B1\u0011\u001d\u0011I\u0005\u0001C\u0001\u0005KBqA!\u0013\u0001\t\u0003\u0011I\u0007C\u0004\u0003n\u0001!\tAa\u001c\t\u000f\t5\u0004\u0001\"\u0001\u0003t!9!Q\u000e\u0001\u0005\u0002\t]\u0004b\u0002B7\u0001\u0011\u0005!1\u0010\u0005\b\u0005[\u0002A\u0011\u0001B@\u0011\u001d\u0011i\u0007\u0001C\u0001\u0005\u0007CqA!\u001c\u0001\t\u0003\u00119\tC\u0004\u0003\f\u0002!\tA!$\t\u000f\t-\u0005\u0001\"\u0001\u0003\u0012\"9!1\u0012\u0001\u0005\u0002\tU\u0005b\u0002BF\u0001\u0011\u0005!\u0011\u0014\u0005\b\u0005\u0017\u0003A\u0011\u0001BO\u0011\u001d\u0011Y\t\u0001C\u0001\u0005CCqAa#\u0001\t\u0003\u0011)\u000bC\u0004\u0003*\u0002!\tAa+\t\u000f\t%\u0006\u0001\"\u0001\u00030\"9!\u0011\u0016\u0001\u0005\u0002\tM\u0006b\u0002BU\u0001\u0011\u0005!q\u0017\u0005\b\u0005S\u0003A\u0011\u0001B^\u0011\u001d\u0011I\u000b\u0001C\u0001\u0005\u007fCqA!+\u0001\t\u0003\u0011\u0019\rC\u0004\u0003B\u0001!\tAa2\t\u000f\t\u0005\u0003\u0001\"\u0001\u0003L\"9!\u0011\t\u0001\u0005\u0002\t=\u0007b\u0002B!\u0001\u0011\u0005!1\u001b\u0005\b\u0005\u0003\u0002A\u0011\u0001Bl\u0011\u001d\u0011\t\u0005\u0001C\u0001\u00057DqA!\u0011\u0001\t\u0003\u0011y\u000eC\u0004\u0003d\u0002!\tA!:\t\u000f\t\r\b\u0001\"\u0001\u0003j\"9!1\u001d\u0001\u0005\u0002\t5\bb\u0002Br\u0001\u0011\u0005!\u0011\u001f\u0005\b\u0005G\u0004A\u0011\u0001B{\u0011\u001d\u0011\u0019\u000f\u0001C\u0001\u0005sDqAa9\u0001\t\u0003\u0011i\u0010C\u0004\u0004\u0002\u0001!\taa\u0001\t\u000f\r\u0005\u0001\u0001\"\u0001\u0004\b!91\u0011\u0001\u0001\u0005\u0002\r-\u0001bBB\u0001\u0001\u0011\u00051q\u0002\u0005\b\u0007\u0003\u0001A\u0011AB\n\u0011\u001d\u0019\t\u0001\u0001C\u0001\u0007/Aqa!\u0001\u0001\t\u0003\u0019Y\u0002C\u0004\u0004 \u0001!\ta!\t\t\u000f\r}\u0001\u0001\"\u0001\u0004&!91q\u0004\u0001\u0005\u0002\r%\u0002bBB\u0010\u0001\u0011\u00051Q\u0006\u0005\b\u0007?\u0001A\u0011AB\u0019\u0011\u001d\u0019y\u0002\u0001C\u0001\u0007kAqaa\b\u0001\t\u0003\u0019I\u0004C\u0004\u0004>\u0001!\taa\u0010\t\u000f\ru\u0002\u0001\"\u0001\u0004D!91Q\b\u0001\u0005\u0002\r\u001d\u0003bBB\u001f\u0001\u0011\u000511\n\u0005\b\u0007{\u0001A\u0011AB(\u0011\u001d\u0019i\u0004\u0001C\u0001\u0007\'Bqa!\u0010\u0001\t\u0003\u00199\u0006C\u0004\u0004\\\u0001!\ta!\u0018\t\u000f\r\r\u0004\u0001\"\u0001\u0004f!91\u0011\u000e\u0001\u0005\u0002\r-\u0004bBB7\u0001\u0011\u0005\u0011q\u0019\u0005\b\u0007_\u0002A\u0011AAd\u0011\u001d\u0019\t\b\u0001C\u0001\u0007gBqaa \u0001\t\u0003\u0019\t\tC\u0004\u0004\n\u0002!\tA!\u000e\t\u000f\r-\u0005\u0001\"\u0001\u0004\u000e\"91Q\u0013\u0001\u0005\u0002\r]\u0005bBBN\u0001\u0011\u000511\u000e\u0005\b\u0007;\u0003A\u0011AB6\u0011%\u0019y\nAA\u0001\n\u0003\u001a\t\u000bC\u0005\u0004$\u0002\t\t\u0011\"\u0011\u0004&\u001eA1\u0011WAU\u0011\u0003\u0019\u0019L\u0002\u0005\u0002(\u0006%\u0006\u0012AB[\u0011\u001d\t\t.\u0018C\u0001\u0007{C\u0011ba0^\u0005\u0004%)A!\u000e\t\u0011\r\u0005W\f)A\u0007\u0003+D\u0011ba1^\u0005\u0004%)A!\u000e\t\u0011\r\u0015W\f)A\u0007\u0003+Dqaa2^\t\u0003\u0019I\rC\u0004\u0004ru#\taa5\t\u000f\r]W\f\"\u0001\u0004Z\"91\u0011^/\u0005\u0002\r-\bb\u0002C\b;\u0012\u0005A\u0011\u0003\u0005\b\tSiF\u0011\u0001C\u0016\u0011\u001d!y%\u0018C\u0001\t#Bq\u0001\"\u0016^\t\u0003!9\u0006\u0003\u0005\u0005fu\u0013I1\u0001C4\u0011\u001d)9!\u0018C\u0002\u000b\u0013Aq!b\u0004^\t\u0007)\t\u0002C\u0004\u0006\u0016u#\u0019!b\u0006\t\u000f\u0015\u0005R\fb\u0001\u0006$!9QqE/\u0005\u0004\u0015%\u0002bBC\u001a;\u0012\rQQ\u0007\u0005\b\u000b\u007fiF1AC!\u0011%)Y%\u0018b\u0001\n\u0007)i\u0005\u0003\u0005\u0006Vu\u0003\u000b\u0011BC(\u0011%)9&\u0018b\u0001\n\u000b\u0011)\u0004\u0003\u0005\u0006Zu\u0003\u000bQBAk\u0011%)Y&\u0018b\u0001\n\u000b\u0011)\u0004\u0003\u0005\u0006^u\u0003\u000bQBAk\u0011%)y&\u0018b\u0001\n\u0003)i\u0005\u0003\u0005\u0006pu\u0003\u000b\u0011BC(\u0011\u001d)\u0019(\u0018C\u0003\u000bkBq!b\u001f^\t\u000b)i\bC\u0004\u0006\u0002v#)!b!\t\u000f\u0015\u001dU\f\"\u0002\u0006\n\"9QQR/\u0005\u0006\u0015=\u0005bBCJ;\u0012\u0015QQ\u0013\u0005\b\u000b3kFQACN\u0011\u001d)y*\u0018C\u0003\u000bCCq!\"*^\t\u000b)9\u000bC\u0004\u0006,v#)!\",\t\u000f\u0015EV\f\"\u0002\u00064\"9Q1X/\u0005\u0006\u0015u\u0006bBC^;\u0012\u0015QQ\u0019\u0005\b\u000bwkFQACg\u0011\u001d)Y,\u0018C\u0003\u000b+Dq!b/^\t\u000b)i\u000eC\u0004\u0006<v#)!\":\t\u000f\u0015mV\f\"\u0002\u0006n\"9QQ_/\u0005\u0006\u0015]\bbBC{;\u0012\u0015Qq \u0005\b\u000bklFQ\u0001D\u0004\u0011\u001d))0\u0018C\u0003\r\u001fAq!\">^\t\u000b19\u0002C\u0004\u0006vv#)Ab\b\t\u000f\u0015UX\f\"\u0002\u0007(!9aqF/\u0005\u0006\u0019E\u0002b\u0002D\u0018;\u0012\u0015a\u0011\b\u0005\b\r_iFQ\u0001D!\u0011\u001d1y#\u0018C\u0003\r\u0013BqAb\f^\t\u000b1\t\u0006C\u0004\u00070u#)A\"\u0017\t\u000f\u0019=R\f\"\u0002\u0007b!9a\u0011N/\u0005\u0006\u0019-\u0004b\u0002D5;\u0012\u0015a1\u000f\u0005\b\rSjFQ\u0001D>\u0011\u001d1I\'\u0018C\u0003\r\u0007CqA\"\u001b^\t\u000b1Y\tC\u0004\u0007ju#)Ab%\t\u000f\u0019%T\f\"\u0002\u0007\u001c\"9Q\u0011W/\u0005\u0006\u0019\r\u0006bBCY;\u0012\u0015a1\u0016\u0005\b\u000bckFQ\u0001DZ\u0011\u001d)\t,\u0018C\u0003\rwCq!\"-^\t\u000b1\u0019\rC\u0004\u00062v#)Ab3\t\u000f\u0015EV\f\"\u0002\u0007T\"9a1\\/\u0005\u0006\u0019u\u0007b\u0002Dn;\u0012\u0015aQ\u001d\u0005\b\r7lFQ\u0001Dw\u0011\u001d1Y.\u0018C\u0003\rkDqAb7^\t\u000b1i\u0010C\u0004\u0007\\v#)a\"\u0002\t\u000f\u0019mW\f\"\u0002\b\u000e!9qQC/\u0005\u0006\u001d]\u0001bBD\u000b;\u0012\u0015qq\u0004\u0005\b\u000f+iFQAD\u0014\u0011\u001d9)\"\u0018C\u0003\u000f_Aqa\"\u0006^\t\u000b99\u0004C\u0004\b\u0016u#)ab\u0010\t\u000f\u001dUQ\f\"\u0002\bH!9qqJ/\u0005\u0006\u001dE\u0003bBD(;\u0012\u0015q\u0011\f\u0005\b\u000f\u001fjFQAD1\u0011\u001d9y%\u0018C\u0003\u000fSBqab\u0014^\t\u000b9\t\bC\u0004\bPu#)a\"\u001f\t\u000f\u001d=S\f\"\u0002\b\u0002\"9q\u0011R/\u0005\u0006\u001d-\u0005bBDE;\u0012\u0015q1\u0013\u0005\b\u000f\u0013kFQADN\u0011\u001d9I)\u0018C\u0003\u000fGCqa\"#^\t\u000b9Y\u000bC\u0004\b\nv#)ab-\t\u000f\u001d%U\f\"\u0002\b<\"9q1Y/\u0005\u0006\u001d\u0015\u0007bBDg;\u0012\u0015qq\u001a\u0005\b\u000f/lFQADm\u0011\u001d9i.\u0018C\u0003\u000f?Dqab9^\t\u000b9)\u000fC\u0004\bjv#)ab;\t\u000f\u001dMX\f\"\u0002\bv\"9q\u0011`/\u0005\u0006\u001dm\bbBD\u0000;\u0012\u0015\u0001\u0012\u0001\u0005\b\u0011\u000biFQ\u0001E\u0004\u0011\u001dAy!\u0018C\u0003\u0011#Aq\u0001#\u0006^\t\u000bA9\u0002C\u0005\t\u001cu\u000b\t\u0011\"\u0002\t\u001e!I\u0001\u0012E/\u0002\u0002\u0013\u0015\u00012\u0005\u0002\t!>\u001ch\t\\8bi*!\u00111VAW\u0003\u001d\tg.\u001f<bYNTA!a,\u00022\u0006I1oY1mC\u000e$\u0018n\u0019\u0006\u0003\u0003g\u000b1a\u001c:h\u0007\u0001\u00192\u0001AA]!\u0011\tY,!1\u000e\u0005\u0005u&BAA`\u0003\u0015\u00198-\u00197b\u0013\u0011\t\u0019-!0\u0003\r\u0005s\u0017PV1m\u0003\u00151\u0018\r\\;f+\t\tI\r\u0005\u0003\u0002<\u0006-\u0017\u0002BAg\u0003{\u0013QA\u00127pCR\faA^1mk\u0016\u0004\u0013A\u0002\u001fj]&$h\b\u0006\u0003\u0002V\u0006e\u0007cAAl\u00015\u0011\u0011\u0011\u0016\u0005\b\u0003\u000b\u001c\u0001\u0019AAe\u0003!!xn\u0015;sS:<GCAAp!\u0011\t\t/a<\u000f\t\u0005\r\u00181\u001e\t\u0005\u0003K\fi,\u0004\u0002\u0002h*!\u0011\u0011^A[\u0003\u0019a$o\\8u}%!\u0011Q^A_\u0003\u0019\u0001&/\u001a3fM&!\u0011\u0011_Az\u0005\u0019\u0019FO]5oO*!\u0011Q^A_\u0003\u0019!xNQ=uKV\u0011\u0011\u0011 \t\u0005\u0003w\u000bY0\u0003\u0003\u0002~\u0006u&\u0001\u0002\"zi\u0016\fq\u0001^8TQ>\u0014H/\u0006\u0002\u0003\u0004A!\u00111\u0018B\u0003\u0013\u0011\u00119!!0\u0003\u000bMCwN\u001d;\u0002\rQ|7\t[1s+\t\u0011i\u0001\u0005\u0003\u0002<\n=\u0011\u0002\u0002B\t\u0003{\u0013Aa\u00115be\u0006)Ao\\%oiV\u0011!q\u0003\t\u0005\u0003w\u0013I\"\u0003\u0003\u0003\u001c\u0005u&aA%oi\u00061Ao\u001c\'p]\u001e,\"A!\t\u0011\t\u0005m&1E\u0005\u0005\u0005K\tiL\u0001\u0003M_:<\u0017a\u0002;p\r2|\u0017\r^\u0001\ti>$u.\u001e2mKV\u0011!Q\u0006\t\u0005\u0003w\u0013y#\u0003\u0003\u00032\u0005u&A\u0002#pk\ndW-A\u0006v]\u0006\u0014\u0018p\u0018\u0013qYV\u001cXCAAk\u00031)h.\u0019:z?\u0012j\u0017N\\;t+\t\u0011Y\u0004\u0005\u0003\u0002X\nu\u0012\u0002\u0002B \u0003S\u0013\u0001BT3h\r2|\u0017\r^\u0001\u0006IAdWo\u001d\u000b\u0005\u0003?\u0014)\u0005C\u0004\u0003H9\u0001\r!a8\u0002\u0003a\fQ\u0001\n7fgN$BA!\u0014\u0003TA!\u00111\u0018B(\u0013\u0011\u0011\t&!0\u0003\u000f\t{w\u000e\\3b]\"9!qI\bA\u0002\u0005eH\u0003\u0002B\'\u0005/BqAa\u0012\u0011\u0001\u0004\u0011\u0019\u0001\u0006\u0003\u0003N\tm\u0003b\u0002B$#\u0001\u0007!Q\u0002\u000b\u0005\u0005\u001b\u0012y\u0006C\u0004\u0003HI\u0001\rAa\u0006\u0015\t\t5#1\r\u0005\b\u0005\u000f\u001a\u0002\u0019\u0001B\u0011)\u0011\u0011iEa\u001a\t\u000f\t\u001dC\u00031\u0001\u0002JR!!Q\nB6\u0011\u001d\u00119%\u0006a\u0001\u0005[\t\u0001\u0002\n7fgN$S-\u001d\u000b\u0005\u0005\u001b\u0012\t\bC\u0004\u0003HY\u0001\r!!?\u0015\t\t5#Q\u000f\u0005\b\u0005\u000f:\u0002\u0019\u0001B\u0002)\u0011\u0011iE!\u001f\t\u000f\t\u001d\u0003\u00041\u0001\u0003\u000eQ!!Q\nB?\u0011\u001d\u00119%\u0007a\u0001\u0005/!BA!\u0014\u0003\u0002\"9!q\t\u000eA\u0002\t\u0005B\u0003\u0002B\'\u0005\u000bCqAa\u0012\u001c\u0001\u0004\tI\r\u0006\u0003\u0003N\t%\u0005b\u0002B$9\u0001\u0007!QF\u0001\tI\u001d\u0014X-\u0019;feR!!Q\nBH\u0011\u001d\u00119%\ba\u0001\u0003s$BA!\u0014\u0003\u0014\"9!q\t\u0010A\u0002\t\rA\u0003\u0002B\'\u0005/CqAa\u0012 \u0001\u0004\u0011i\u0001\u0006\u0003\u0003N\tm\u0005b\u0002B$A\u0001\u0007!q\u0003\u000b\u0005\u0005\u001b\u0012y\nC\u0004\u0003H\u0005\u0002\rA!\t\u0015\t\t5#1\u0015\u0005\b\u0005\u000f\u0012\u0003\u0019AAe)\u0011\u0011iEa*\t\u000f\t\u001d3\u00051\u0001\u0003.\u0005YAe\u001a:fCR,\'\u000fJ3r)\u0011\u0011iE!,\t\u000f\t\u001dC\u00051\u0001\u0002zR!!Q\nBY\u0011\u001d\u00119%\na\u0001\u0005\u0007!BA!\u0014\u00036\"9!q\t\u0014A\u0002\t5A\u0003\u0002B\'\u0005sCqAa\u0012(\u0001\u0004\u00119\u0002\u0006\u0003\u0003N\tu\u0006b\u0002B$Q\u0001\u0007!\u0011\u0005\u000b\u0005\u0005\u001b\u0012\t\rC\u0004\u0003H%\u0002\r!!3\u0015\t\t5#Q\u0019\u0005\b\u0005\u000fR\u0003\u0019\u0001B\u0017)\u0011\tIM!3\t\u000f\t\u001d3\u00061\u0001\u0002zR!\u0011\u0011\u001aBg\u0011\u001d\u00119\u0005\fa\u0001\u0005\u0007!B!!3\u0003R\"9!qI\u0017A\u0002\t5A\u0003BAe\u0005+DqAa\u0012/\u0001\u0004\u00119\u0002\u0006\u0003\u0002J\ne\u0007b\u0002B$_\u0001\u0007!\u0011\u0005\u000b\u0005\u0003\u0013\u0014i\u000eC\u0004\u0003HA\u0002\r!!3\u0015\t\t5\"\u0011\u001d\u0005\b\u0005\u000f\n\u0004\u0019\u0001B\u0017\u0003\u0019!S.\u001b8vgR!\u0011\u0011\u001aBt\u0011\u001d\u00119E\ra\u0001\u0003s$B!!3\u0003l\"9!qI\u001aA\u0002\t\rA\u0003BAe\u0005_DqAa\u00125\u0001\u0004\u0011i\u0001\u0006\u0003\u0002J\nM\bb\u0002B$k\u0001\u0007!q\u0003\u000b\u0005\u0003\u0013\u00149\u0010C\u0004\u0003HY\u0002\rA!\t\u0015\t\u0005%\'1 \u0005\b\u0005\u000f:\u0004\u0019AAe)\u0011\u0011iCa@\t\u000f\t\u001d\u0003\b1\u0001\u0003.\u00051A\u0005^5nKN$B!!3\u0004\u0006!9!qI\u001dA\u0002\u0005eH\u0003BAe\u0007\u0013AqAa\u0012;\u0001\u0004\u0011\u0019\u0001\u0006\u0003\u0002J\u000e5\u0001b\u0002B$w\u0001\u0007!Q\u0002\u000b\u0005\u0003\u0013\u001c\t\u0002C\u0004\u0003Hq\u0002\rAa\u0006\u0015\t\u0005%7Q\u0003\u0005\b\u0005\u000fj\u0004\u0019\u0001B\u0011)\u0011\tIm!\u0007\t\u000f\t\u001dc\b1\u0001\u0002JR!!QFB\u000f\u0011\u001d\u00119e\u0010a\u0001\u0005[\tA\u0001\n3jmR!\u0011\u0011ZB\u0012\u0011\u001d\u00119\u0005\u0011a\u0001\u0003s$B!!3\u0004(!9!qI!A\u0002\t\rA\u0003BAe\u0007WAqAa\u0012C\u0001\u0004\u0011i\u0001\u0006\u0003\u0002J\u000e=\u0002b\u0002B$\u0007\u0002\u0007!q\u0003\u000b\u0005\u0003\u0013\u001c\u0019\u0004C\u0004\u0003H\u0011\u0003\rA!\t\u0015\t\u0005%7q\u0007\u0005\b\u0005\u000f*\u0005\u0019AAe)\u0011\u0011ica\u000f\t\u000f\t\u001dc\t1\u0001\u0003.\u0005AA\u0005]3sG\u0016tG\u000f\u0006\u0003\u0002J\u000e\u0005\u0003b\u0002B$\u000f\u0002\u0007\u0011\u0011 \u000b\u0005\u0003\u0013\u001c)\u0005C\u0004\u0003H!\u0003\rAa\u0001\u0015\t\u0005%7\u0011\n\u0005\b\u0005\u000fJ\u0005\u0019\u0001B\u0007)\u0011\tIm!\u0014\t\u000f\t\u001d#\n1\u0001\u0003\u0018Q!\u0011\u0011ZB)\u0011\u001d\u00119e\u0013a\u0001\u0005C!B!!3\u0004V!9!q\t\'A\u0002\u0005%G\u0003\u0002B\u0017\u00073BqAa\u0012N\u0001\u0004\u0011i#A\u0002nCb$B!!6\u0004`!91\u0011\r(A\u0002\u0005U\u0017\u0001\u0002;iCR\f1!\\5o)\u0011\t)na\u001a\t\u000f\r\u0005t\n1\u0001\u0002V\u00069\u0011n],i_2,WC\u0001B\'\u0003%!xNU1eS\u0006t7/A\u0005u_\u0012+wM]3fg\u0006iQM\\:ve&twMV1mS\u0012$B!!6\u0004v!91qO*A\u0002\re\u0014!\u00014\u0011\u0011\u0005m61PAe\u0003\u0013LAa! \u0002>\nIa)\u001e8di&|g.M\u0001\u0006e>,h\u000eZ\u000b\u0003\u0007\u0007\u0003B!a6\u0004\u0006&!1qQAU\u0005\u001d\u0001vn\u001d.J]R\fAaY3jY\u0006)a\r\\8peV\u00111q\u0012\t\u0005\u0003/\u001c\t*\u0003\u0003\u0004\u0014\u0006%&!\u0003)pgj3En\\1u\u0003\u0011\u0001H.^:\u0015\t\u0005U7\u0011\u0014\u0005\b\u0005\u000f:\u0006\u0019ABH\u00035I7\u000fU8t\u0013:4\u0017N\\5us\u0006A\u0011n\u001d$j]&$X-\u0001\u0005iCND7i\u001c3f)\t\u00119\"\u0001\u0004fcV\fGn\u001d\u000b\u0005\u0005\u001b\u001a9\u000bC\u0005\u0004*n\u000b\t\u00111\u0001\u0004,\u0006\u0019\u0001\u0010J\u0019\u0011\t\u0005m6QV\u0005\u0005\u0007_\u000biLA\u0002B]f\f\u0001\u0002U8t\r2|\u0017\r\u001e\t\u0004\u0003/l6cA/\u00048B!\u00111XB]\u0013\u0011\u0019Y,!0\u0003\r\u0005s\u0017PU3g)\t\u0019\u0019,\u0001\u0005NCb4\u0016\r\\;f\u0003%i\u0015\r\u001f,bYV,\u0007%\u0001\u0005NS:4\u0016\r\\;f\u0003%i\u0015N\u001c,bYV,\u0007%\u0001\u0003ge>lG\u0003BBf\u0007#\u0004b!a/\u0004N\u0006U\u0017\u0002BBh\u0003{\u0013aa\u00149uS>t\u0007bBAcG\u0002\u0007\u0011\u0011\u001a\u000b\u0005\u0003+\u001c)\u000eC\u0004\u0002F\u0012\u0004\r!!3\u0002\u0017Q\u0014\u00180\u001b8h-\u0006d\u0017\u000e\u001a\u000b\u0005\u00077\u001c9\u000f\u0005\u0004\u0004^\u000e\r\u0018Q[\u0007\u0003\u0007?TAa!9\u0002>\u0006!Q\u000f^5m\u0013\u0011\u0019)oa8\u0003\u0007Q\u0013\u0018\u0010C\u0004\u0002F\u0016\u0004\r!!3\u0002\u0015A\f7o](s\u000b2\u001cX-\u0006\u0003\u0004n\u000euH\u0003BBx\t\u001b!Ba!=\u0005\nA111_B{\u0007sl!!!,\n\t\r]\u0018Q\u0016\u0002\u000b-\u0006d\u0017\u000eZ1uS>t\u0007\u0003BB~\u0007{d\u0001\u0001B\u0004\u0004\u0000\u001a\u0014\r\u0001\"\u0001\u0003\u0003\u0015\u000bB\u0001b\u0001\u0004,B!\u00111\u0018C\u0003\u0013\u0011!9!!0\u0003\u000f9{G\u000f[5oO\"91q\u000f4A\u0002\u0011-\u0001\u0003CA^\u0007w\nIm!?\t\u000f\u0005\u0015g\r1\u0001\u0002J\u0006Qqm\\8e\u001fJ,En]3\u0016\t\u0011MAq\u0004\u000b\u0005\t+!9\u0003\u0006\u0003\u0005\u0018\u0011\r\u0002\u0003CBz\t3\t)\u000e\"\b\n\t\u0011m\u0011Q\u0016\u0002\u0003\u001fJ\u0004Baa?\u0005 \u00119A\u0011E4C\u0002\u0011\u0005!!\u0001\"\t\u000f\r]t\r1\u0001\u0005&AA\u00111XB>\u0003\u0013$i\u0002C\u0004\u0002F\u001e\u0004\r!!3\u0002\u0017ILw\r\u001b;Pe\u0016c7/Z\u000b\u0005\t[!)\u0005\u0006\u0003\u00050\u00115C\u0003\u0002C\u0019\t\u0013\u0002\u0002\u0002b\r\u0005>\u0011\r\u0013Q\u001b\b\u0005\tk!ID\u0004\u0003\u0002f\u0012]\u0012BAA`\u0013\u0011!Y$!0\u0002\u000fA\f7m[1hK&!Aq\bC!\u0005\u0019)\u0015\u000e\u001e5fe*!A1HA_!\u0011\u0019Y\u0010\"\u0012\u0005\u000f\u0011\u001d\u0003N1\u0001\u0005\u0002\t\tA\nC\u0004\u0004x!\u0004\r\u0001b\u0013\u0011\u0011\u0005m61PAe\t\u0007Bq!!2i\u0001\u0004\tI-A\u0004jgZ\u000bG.\u001b3\u0015\t\t5C1\u000b\u0005\b\u0003\u000bL\u0007\u0019AAe\u0003)1\'o\\7Pe\u0016c7/\u001a\u000b\u0007\u0003+$I\u0006b\u0017\t\u000f\u0005\u0015\'\u000e1\u0001\u0002J\"AAQ\f6\u0005\u0002\u0004!y&A\u0004eK\u001a\fW\u000f\u001c;\u0011\r\u0005mF\u0011MAk\u0013\u0011!\u0019\'!0\u0003\u0011q\u0012\u0017P\\1nKz\nQ!\u00199qYf$B!!6\u0005j!9\u0011QY6A\u0002\u0005%\u0007&B6\u0005n\u0011\u0005\u0005\u0003\u0002C8\t{j!\u0001\"\u001d\u000b\t\u0011MDQO\u0001\tS:$XM\u001d8bY*!Aq\u000fC=\u0003\u0019i\u0017m\u0019:pg*!A1PA_\u0003\u001d\u0011XM\u001a7fGRLA\u0001b \u0005r\tIQ.Y2s_&k\u0007\u000f\\\u0019\u0012?\u0011\rEQ\u0011CE\t7#Y\u000bb.\u0005J\u0012e7\u0002A\u0019\bI\u0011\r\u0015Q\u0017CD\u0003\u0015i\u0017m\u0019:pc\u001d1B1\u0011CF\t\'\u000bT!\nCG\t\u001f{!\u0001b$\"\u0005\u0011E\u0015aC7bGJ|WI\\4j]\u0016\fT!\nCK\t/{!\u0001b&\"\u0005\u0011e\u0015!\n<8]A\u0002\u0003&[7qY\u0016lWM\u001c;fI\u0002Jg\u000eI*dC2\f\u0007E\r\u00182c9\u0002T&\u0014\u001d*c\u001d1B1\u0011CO\tK\u000bT!\nCP\tC{!\u0001\")\"\u0005\u0011\r\u0016\u0001C5t\u0005VtG\r\\32\u000b\u0015\"9\u000b\"+\u0010\u0005\u0011%\u0016$\u0001\u00012\u000fY!\u0019\t\",\u00056F*Q\u0005b,\u00052>\u0011A\u0011W\u0011\u0003\tg\u000b!\"[:CY\u0006\u001c7NY8yc\u0015)Cq\u0015CUc\u001d1B1\u0011C]\t\u0003\fT!\nC^\t{{!\u0001\"0\"\u0005\u0011}\u0016!C2mCN\u001ch*Y7fc\u0015)C1\u0019Cc\u001f\t!)-\t\u0002\u0005H\u0006!sN]4/g\u000e\fG.Y2uS\u000et\u0013M\\=wC2\u001ch\u0006U8t\r2|\u0017\r^\'bGJ|G%M\u0004\u0017\t\u0007#Y\rb52\u000b\u0015\"i\rb4\u0010\u0005\u0011=\u0017E\u0001Ci\u0003)iW\r\u001e5pI:\u000bW.Z\u0019\u0006K\u0011UGq[\b\u0003\t/\f#\u0001\"\u001a2\u000fY!\u0019\tb7\u0005dF*Q\u0005\"8\u0005`>\u0011Aq\\\u0011\u0003\tC\f\u0011b]5h]\u0006$XO]32\u0013}!\u0019\t\":\u0005t\u0012u\u0018g\u0002\u0013\u0005\u0004\u0012\u001dH\u0011^\u0005\u0005\tS$Y/\u0001\u0003MSN$(\u0002\u0002Cw\t_\f\u0011\"[7nkR\f\'\r\\3\u000b\t\u0011E\u0018QX\u0001\u000bG>dG.Z2uS>t\u0017gB\u0010\u0005\u0004\u0012UHq_\u0019\bI\u0011\rEq\u001dCuc\u0015)C\u0011 C~\u001f\t!Y0H\u0001\u0000d\u001dyB1\u0011C\u0000\u000b\u0003\tt\u0001\nCB\tO$I/M\u0003&\u000b\u0007))a\u0004\u0002\u0006\u0006u\ta@\u0001\u0007xS\u0012,g\u000eV8GY>\fG\u000f\u0006\u0003\u0002J\u0016-\u0001bBC\u0007Y\u0002\u0007\u0011Q[\u0001\u0004a>\u001c\u0018!D<jI\u0016tGk\u001c#pk\ndW\r\u0006\u0003\u0003.\u0015M\u0001bBC\u0007[\u0002\u0007\u0011Q[\u0001\u0011o&$WM\u001c+p!>\u001cHi\\;cY\u0016$B!\"\u0007\u0006 A!\u0011q[C\u000e\u0013\u0011)i\"!+\u0003\u0013A{7\u000fR8vE2,\u0007bBC\u0007]\u0002\u0007\u0011Q[\u0001\u0011o&$WM\u001c+p!>\u001c(L\u00127pCR$Baa$\u0006&!9QQB8A\u0002\u0005U\u0017!E<jI\u0016tGk\u001c)pgj#u.\u001e2mKR!Q1FC\u0019!\u0011\t9.\"\f\n\t\u0015=\u0012\u0011\u0016\u0002\u000b!>\u001c(\fR8vE2,\u0007bBC\u0007a\u0002\u0007\u0011Q[\u0001\u0014o&$WM\u001c+p\u001d>t\',\u001a:p\r2|\u0017\r\u001e\u000b\u0005\u000bo)i\u0004\u0005\u0003\u0002X\u0016e\u0012\u0002BC\u001e\u0003S\u0013ABT8o5\u0016\u0014xN\u00127pCRDq!\"\u0004r\u0001\u0004\t).\u0001\u000bxS\u0012,g\u000eV8O_:TVM]8E_V\u0014G.\u001a\u000b\u0005\u000b\u0007*I\u0005\u0005\u0003\u0002X\u0016\u0015\u0013\u0002BC$\u0003S\u0013QBT8o5\u0016\u0014x\u000eR8vE2,\u0007bBC\u0007e\u0002\u0007\u0011Q[\u0001\t_J$WM]5oOV\u0011Qq\n\t\u0007\tg)\t&!6\n\t\u0015MC\u0011\t\u0002\t\u001fJ$WM]5oO\u0006IqN\u001d3fe&tw\rI\u0001\u0011!>\u001c\u0018\u000e^5wK&sg-\u001b8jif\f\u0011\u0003U8tSRLg/Z%oM&t\u0017\u000e^=!\u0003Ai\u0015N\u001c)pg&$\u0018N^3WC2,X-A\tNS:\u0004vn]5uSZ,g+\u00197vK\u0002\n1\u0002]8t\r2|\u0017\r^(sI\":\u00110b\u0019\u0006j\u0015-\u0004\u0003BA^\u000bKJA!b\u001a\u0002>\nQA-\u001a9sK\u000e\fG/\u001a3\u0002\u000f5,7o]1hK\u0006\u0012QQN\u0001\u00022QCW\r\t4pe6,\'\u000f\\=!S6\u0004H.[2ji\u0002\u0002xn\u001d$m_\u0006$xJ\u001d3!M&,G\u000e\u001a\u0011iCN\u0004#-Z3oA\u0011,\u0007O]3dCR,G\rI1oI\u0002:\u0018\u000e\u001c7!E\u0016\u0004#/Z7pm\u0016$\u0007%\u001b8!C\u00022W\u000f^;sK\u00022XM]:j_:\u0004sN\u001a\u0011TG\u0006d\u0017\rV3ti:\u0002\u0003\u000b\\3bg\u0016\u0004So]3!i\",\u0007e\u001c:eKJLgn\u001a\u0011gS\u0016dG\rI5ogR,\u0017\r\u001a\u0018\u0002\u0019A|7O\u00127pCR|%\u000f\u001a\u0011)\u000fi,\u0019\'\"\u001b\u0006l\u0005\u0011Bo\\*ue&tw\rJ3yi\u0016t7/[8o)\u0011\ti.b\u001e\t\u000f\u0015e4\u00101\u0001\u0002V\u0006)A\u0005\u001e5jg\u0006\u0001Bo\u001c\"zi\u0016$S\r\u001f;f]NLwN\u001c\u000b\u0005\u0003s,y\bC\u0004\u0006zq\u0004\r!!6\u0002#Q|7\u000b[8si\u0012*\u0007\u0010^3og&|g\u000e\u0006\u0003\u0003\u0004\u0015\u0015\u0005bBC={\u0002\u0007\u0011Q[\u0001\u0011i>\u001c\u0005.\u0019:%Kb$XM\\:j_:$BA!\u0004\u0006\f\"9Q\u0011\u0010@A\u0002\u0005U\u0017a\u0004;p\u0013:$H%\u001a=uK:\u001c\u0018n\u001c8\u0015\t\t]Q\u0011\u0013\u0005\b\u000bsz\b\u0019AAk\u0003A!x\u000eT8oO\u0012*\u0007\u0010^3og&|g\u000e\u0006\u0003\u0003\"\u0015]\u0005\u0002CC=\u0003\u0003\u0001\r!!6\u0002#Q|g\t\\8bi\u0012*\u0007\u0010^3og&|g\u000e\u0006\u0003\u0002J\u0016u\u0005\u0002CC=\u0003\u0007\u0001\r!!6\u0002%Q|Gi\\;cY\u0016$S\r\u001f;f]NLwN\u001c\u000b\u0005\u0005[)\u0019\u000b\u0003\u0005\u0006z\u0005\u0015\u0001\u0019AAk\u0003U)h.\u0019:z?\u0012\u0002H.^:%Kb$XM\\:j_:$B!!6\u0006*\"AQ\u0011PA\u0004\u0001\u0004\t).\u0001\fv]\u0006\u0014\u0018p\u0018\u0013nS:,8\u000fJ3yi\u0016t7/[8o)\u0011\u0011Y$b,\t\u0011\u0015e\u0014\u0011\u0002a\u0001\u0003+\fq\u0002\n9mkN$S\r\u001f;f]NLwN\u001c\u000b\u0005\u000bk+I\f\u0006\u0003\u0002`\u0016]\u0006\u0002\u0003B$\u0003\u0017\u0001\r!a8\t\u0011\u0015e\u00141\u0002a\u0001\u0003+\fq\u0002\n7fgN$S\r\u001f;f]NLwN\u001c\u000b\u0005\u000b\u007f+\u0019\r\u0006\u0003\u0003N\u0015\u0005\u0007\u0002\u0003B$\u0003\u001b\u0001\r!!?\t\u0011\u0015e\u0014Q\u0002a\u0001\u0003+$B!b2\u0006LR!!QJCe\u0011!\u00119%a\u0004A\u0002\t\r\u0001\u0002CC=\u0003\u001f\u0001\r!!6\u0015\t\u0015=W1\u001b\u000b\u0005\u0005\u001b*\t\u000e\u0003\u0005\u0003H\u0005E\u0001\u0019\u0001B\u0007\u0011!)I(!\u0005A\u0002\u0005UG\u0003BCl\u000b7$BA!\u0014\u0006Z\"A!qIA\n\u0001\u0004\u00119\u0002\u0003\u0005\u0006z\u0005M\u0001\u0019AAk)\u0011)y.b9\u0015\t\t5S\u0011\u001d\u0005\t\u0005\u000f\n)\u00021\u0001\u0003\"!AQ\u0011PA\u000b\u0001\u0004\t)\u000e\u0006\u0003\u0006h\u0016-H\u0003\u0002B\'\u000bSD\u0001Ba\u0012\u0002\u0018\u0001\u0007\u0011\u0011\u001a\u0005\t\u000bs\n9\u00021\u0001\u0002VR!Qq^Cz)\u0011\u0011i%\"=\t\u0011\t\u001d\u0013\u0011\u0004a\u0001\u0005[A\u0001\"\"\u001f\u0002\u001a\u0001\u0007\u0011Q[\u0001\u0013I1,7o\u001d\u0013fc\u0012*\u0007\u0010^3og&|g\u000e\u0006\u0003\u0006z\u0016uH\u0003\u0002B\'\u000bwD\u0001Ba\u0012\u0002\u001c\u0001\u0007\u0011\u0011 \u0005\t\u000bs\nY\u00021\u0001\u0002VR!a\u0011\u0001D\u0003)\u0011\u0011iEb\u0001\t\u0011\t\u001d\u0013Q\u0004a\u0001\u0005\u0007A\u0001\"\"\u001f\u0002\u001e\u0001\u0007\u0011Q\u001b\u000b\u0005\r\u00131i\u0001\u0006\u0003\u0003N\u0019-\u0001\u0002\u0003B$\u0003?\u0001\rA!\u0004\t\u0011\u0015e\u0014q\u0004a\u0001\u0003+$BA\"\u0005\u0007\u0016Q!!Q\nD\n\u0011!\u00119%!\tA\u0002\t]\u0001\u0002CC=\u0003C\u0001\r!!6\u0015\t\u0019eaQ\u0004\u000b\u0005\u0005\u001b2Y\u0002\u0003\u0005\u0003H\u0005\r\u0002\u0019\u0001B\u0011\u0011!)I(a\tA\u0002\u0005UG\u0003\u0002D\u0011\rK!BA!\u0014\u0007$!A!qIA\u0013\u0001\u0004\tI\r\u0003\u0005\u0006z\u0005\u0015\u0002\u0019AAk)\u00111IC\"\f\u0015\t\t5c1\u0006\u0005\t\u0005\u000f\n9\u00031\u0001\u0003.!AQ\u0011PA\u0014\u0001\u0004\t).\u0001\n%OJ,\u0017\r^3sI\u0015DH/\u001a8tS>tG\u0003\u0002D\u001a\ro!BA!\u0014\u00076!A!qIA\u0015\u0001\u0004\tI\u0010\u0003\u0005\u0006z\u0005%\u0002\u0019AAk)\u00111YDb\u0010\u0015\t\t5cQ\b\u0005\t\u0005\u000f\nY\u00031\u0001\u0003\u0004!AQ\u0011PA\u0016\u0001\u0004\t)\u000e\u0006\u0003\u0007D\u0019\u001dC\u0003\u0002B\'\r\u000bB\u0001Ba\u0012\u0002.\u0001\u0007!Q\u0002\u0005\t\u000bs\ni\u00031\u0001\u0002VR!a1\nD()\u0011\u0011iE\"\u0014\t\u0011\t\u001d\u0013q\u0006a\u0001\u0005/A\u0001\"\"\u001f\u00020\u0001\u0007\u0011Q\u001b\u000b\u0005\r\'29\u0006\u0006\u0003\u0003N\u0019U\u0003\u0002\u0003B$\u0003c\u0001\rA!\t\t\u0011\u0015e\u0014\u0011\u0007a\u0001\u0003+$BAb\u0017\u0007`Q!!Q\nD/\u0011!\u00119%a\rA\u0002\u0005%\u0007\u0002CC=\u0003g\u0001\r!!6\u0015\t\u0019\rdq\r\u000b\u0005\u0005\u001b2)\u0007\u0003\u0005\u0003H\u0005U\u0002\u0019\u0001B\u0017\u0011!)I(!\u000eA\u0002\u0005U\u0017!\u0006\u0013he\u0016\fG/\u001a:%KF$S\r\u001f;f]NLwN\u001c\u000b\u0005\r[2\t\b\u0006\u0003\u0003N\u0019=\u0004\u0002\u0003B$\u0003o\u0001\r!!?\t\u0011\u0015e\u0014q\u0007a\u0001\u0003+$BA\"\u001e\u0007zQ!!Q\nD<\u0011!\u00119%!\u000fA\u0002\t\r\u0001\u0002CC=\u0003s\u0001\r!!6\u0015\t\u0019ud\u0011\u0011\u000b\u0005\u0005\u001b2y\b\u0003\u0005\u0003H\u0005m\u0002\u0019\u0001B\u0007\u0011!)I(a\u000fA\u0002\u0005UG\u0003\u0002DC\r\u0013#BA!\u0014\u0007\b\"A!qIA\u001f\u0001\u0004\u00119\u0002\u0003\u0005\u0006z\u0005u\u0002\u0019AAk)\u00111iI\"%\u0015\t\t5cq\u0012\u0005\t\u0005\u000f\ny\u00041\u0001\u0003\"!AQ\u0011PA \u0001\u0004\t)\u000e\u0006\u0003\u0007\u0016\u001aeE\u0003\u0002B\'\r/C\u0001Ba\u0012\u0002B\u0001\u0007\u0011\u0011\u001a\u0005\t\u000bs\n\t\u00051\u0001\u0002VR!aQ\u0014DQ)\u0011\u0011iEb(\t\u0011\t\u001d\u00131\ta\u0001\u0005[A\u0001\"\"\u001f\u0002D\u0001\u0007\u0011Q\u001b\u000b\u0005\rK3I\u000b\u0006\u0003\u0002J\u001a\u001d\u0006\u0002\u0003B$\u0003\u000b\u0002\r!!?\t\u0011\u0015e\u0014Q\ta\u0001\u0003+$BA\",\u00072R!\u0011\u0011\u001aDX\u0011!\u00119%a\u0012A\u0002\t\r\u0001\u0002CC=\u0003\u000f\u0002\r!!6\u0015\t\u0019Uf\u0011\u0018\u000b\u0005\u0003\u001349\f\u0003\u0005\u0003H\u0005%\u0003\u0019\u0001B\u0007\u0011!)I(!\u0013A\u0002\u0005UG\u0003\u0002D_\r\u0003$B!!3\u0007@\"A!qIA&\u0001\u0004\u00119\u0002\u0003\u0005\u0006z\u0005-\u0003\u0019AAk)\u00111)M\"3\u0015\t\u0005%gq\u0019\u0005\t\u0005\u000f\ni\u00051\u0001\u0003\"!AQ\u0011PA\'\u0001\u0004\t)\u000e\u0006\u0003\u0007N\u001aEG\u0003BAe\r\u001fD\u0001Ba\u0012\u0002P\u0001\u0007\u0011\u0011\u001a\u0005\t\u000bs\ny\u00051\u0001\u0002VR!aQ\u001bDm)\u0011\u0011iCb6\t\u0011\t\u001d\u0013\u0011\u000ba\u0001\u0005[A\u0001\"\"\u001f\u0002R\u0001\u0007\u0011Q[\u0001\u0011I5Lg.^:%Kb$XM\\:j_:$BAb8\u0007dR!\u0011\u0011\u001aDq\u0011!\u00119%a\u0015A\u0002\u0005e\b\u0002CC=\u0003\'\u0002\r!!6\u0015\t\u0019\u001dh1\u001e\u000b\u0005\u0003\u00134I\u000f\u0003\u0005\u0003H\u0005U\u0003\u0019\u0001B\u0002\u0011!)I(!\u0016A\u0002\u0005UG\u0003\u0002Dx\rg$B!!3\u0007r\"A!qIA,\u0001\u0004\u0011i\u0001\u0003\u0005\u0006z\u0005]\u0003\u0019AAk)\u001119Pb?\u0015\t\u0005%g\u0011 \u0005\t\u0005\u000f\nI\u00061\u0001\u0003\u0018!AQ\u0011PA-\u0001\u0004\t)\u000e\u0006\u0003\u0007\u0000\u001e\rA\u0003BAe\u000f\u0003A\u0001Ba\u0012\u0002\\\u0001\u0007!\u0011\u0005\u0005\t\u000bs\nY\u00061\u0001\u0002VR!qqAD\u0006)\u0011\tIm\"\u0003\t\u0011\t\u001d\u0013Q\fa\u0001\u0003\u0013D\u0001\"\"\u001f\u0002^\u0001\u0007\u0011Q\u001b\u000b\u0005\u000f\u001f9\u0019\u0002\u0006\u0003\u0003.\u001dE\u0001\u0002\u0003B$\u0003?\u0002\rA!\f\t\u0011\u0015e\u0014q\fa\u0001\u0003+\f\u0001\u0003\n;j[\u0016\u001cH%\u001a=uK:\u001c\u0018n\u001c8\u0015\t\u001deqQ\u0004\u000b\u0005\u0003\u0013<Y\u0002\u0003\u0005\u0003H\u0005\u0005\u0004\u0019AA}\u0011!)I(!\u0019A\u0002\u0005UG\u0003BD\u0011\u000fK!B!!3\b$!A!qIA2\u0001\u0004\u0011\u0019\u0001\u0003\u0005\u0006z\u0005\r\u0004\u0019AAk)\u00119Ic\"\f\u0015\t\u0005%w1\u0006\u0005\t\u0005\u000f\n)\u00071\u0001\u0003\u000e!AQ\u0011PA3\u0001\u0004\t)\u000e\u0006\u0003\b2\u001dUB\u0003BAe\u000fgA\u0001Ba\u0012\u0002h\u0001\u0007!q\u0003\u0005\t\u000bs\n9\u00071\u0001\u0002VR!q\u0011HD\u001f)\u0011\tImb\u000f\t\u0011\t\u001d\u0013\u0011\u000ea\u0001\u0005CA\u0001\"\"\u001f\u0002j\u0001\u0007\u0011Q\u001b\u000b\u0005\u000f\u0003:)\u0005\u0006\u0003\u0002J\u001e\r\u0003\u0002\u0003B$\u0003W\u0002\r!!3\t\u0011\u0015e\u00141\u000ea\u0001\u0003+$Ba\"\u0013\bNQ!!QFD&\u0011!\u00119%!\u001cA\u0002\t5\u0002\u0002CC=\u0003[\u0002\r!!6\u0002\u001d\u0011\"\u0017N\u001e\u0013fqR,gn]5p]R!q1KD,)\u0011\tIm\"\u0016\t\u0011\t\u001d\u0013q\u000ea\u0001\u0003sD\u0001\"\"\u001f\u0002p\u0001\u0007\u0011Q\u001b\u000b\u0005\u000f7:y\u0006\u0006\u0003\u0002J\u001eu\u0003\u0002\u0003B$\u0003c\u0002\rAa\u0001\t\u0011\u0015e\u0014\u0011\u000fa\u0001\u0003+$Bab\u0019\bhQ!\u0011\u0011ZD3\u0011!\u00119%a\u001dA\u0002\t5\u0001\u0002CC=\u0003g\u0002\r!!6\u0015\t\u001d-tq\u000e\u000b\u0005\u0003\u0013<i\u0007\u0003\u0005\u0003H\u0005U\u0004\u0019\u0001B\f\u0011!)I(!\u001eA\u0002\u0005UG\u0003BD:\u000fo\"B!!3\bv!A!qIA<\u0001\u0004\u0011\t\u0003\u0003\u0005\u0006z\u0005]\u0004\u0019AAk)\u00119Yhb \u0015\t\u0005%wQ\u0010\u0005\t\u0005\u000f\nI\b1\u0001\u0002J\"AQ\u0011PA=\u0001\u0004\t)\u000e\u0006\u0003\b\u0004\u001e\u001dE\u0003\u0002B\u0017\u000f\u000bC\u0001Ba\u0012\u0002|\u0001\u0007!Q\u0006\u0005\t\u000bs\nY\b1\u0001\u0002V\u0006\u0011B\u0005]3sG\u0016tG\u000fJ3yi\u0016t7/[8o)\u00119ii\"%\u0015\t\u0005%wq\u0012\u0005\t\u0005\u000f\ni\b1\u0001\u0002z\"AQ\u0011PA?\u0001\u0004\t)\u000e\u0006\u0003\b\u0016\u001eeE\u0003BAe\u000f/C\u0001Ba\u0012\u0002\u0000\u0001\u0007!1\u0001\u0005\t\u000bs\ny\b1\u0001\u0002VR!qQTDQ)\u0011\tImb(\t\u0011\t\u001d\u0013\u0011\u0011a\u0001\u0005\u001bA\u0001\"\"\u001f\u0002\u0002\u0002\u0007\u0011Q\u001b\u000b\u0005\u000fK;I\u000b\u0006\u0003\u0002J\u001e\u001d\u0006\u0002\u0003B$\u0003\u0007\u0003\rAa\u0006\t\u0011\u0015e\u00141\u0011a\u0001\u0003+$Ba\",\b2R!\u0011\u0011ZDX\u0011!\u00119%!\"A\u0002\t\u0005\u0002\u0002CC=\u0003\u000b\u0003\r!!6\u0015\t\u001dUv\u0011\u0018\u000b\u0005\u0003\u0013<9\f\u0003\u0005\u0003H\u0005\u001d\u0005\u0019AAe\u0011!)I(a\"A\u0002\u0005UG\u0003BD_\u000f\u0003$BA!\f\b@\"A!qIAE\u0001\u0004\u0011i\u0003\u0003\u0005\u0006z\u0005%\u0005\u0019AAk\u00035i\u0017\r\u001f\u0013fqR,gn]5p]R!qqYDf)\u0011\t)n\"3\t\u0011\r\u0005\u00141\u0012a\u0001\u0003+D\u0001\"\"\u001f\u0002\f\u0002\u0007\u0011Q[\u0001\u000e[&tG%\u001a=uK:\u001c\u0018n\u001c8\u0015\t\u001dEwQ\u001b\u000b\u0005\u0003+<\u0019\u000e\u0003\u0005\u0004b\u00055\u0005\u0019AAk\u0011!)I(!$A\u0002\u0005U\u0017!E5t/\"|G.\u001a\u0013fqR,gn]5p]R!!QJDn\u0011!)I(a$A\u0002\u0005U\u0017a\u0005;p%\u0006$\u0017.\u00198tI\u0015DH/\u001a8tS>tG\u0003BAe\u000fCD\u0001\"\"\u001f\u0002\u0012\u0002\u0007\u0011Q[\u0001\u0014i>$Um\u001a:fKN$S\r\u001f;f]NLwN\u001c\u000b\u0005\u0003\u0013<9\u000f\u0003\u0005\u0006z\u0005M\u0005\u0019AAk\u0003])gn];sS:<g+\u00197jI\u0012*\u0007\u0010^3og&|g\u000e\u0006\u0003\bn\u001eEH\u0003BAk\u000f_D\u0001ba\u001e\u0002\u0016\u0002\u00071\u0011\u0010\u0005\t\u000bs\n)\n1\u0001\u0002V\u0006y!o\\;oI\u0012*\u0007\u0010^3og&|g\u000e\u0006\u0003\u0004\u0004\u001e]\b\u0002CC=\u0003/\u0003\r!!6\u0002\u001d\r,\u0017\u000e\u001c\u0013fqR,gn]5p]R!\u0011Q[D\u007f\u0011!)I(!\'A\u0002\u0005U\u0017a\u00044m_>\u0014H%\u001a=uK:\u001c\u0018n\u001c8\u0015\t\r=\u00052\u0001\u0005\t\u000bs\nY\n1\u0001\u0002V\u0006q\u0001\u000f\\;tI\u0015DH/\u001a8tS>tG\u0003\u0002E\u0005\u0011\u001b!B!!6\t\f!A!qIAO\u0001\u0004\u0019y\t\u0003\u0005\u0006z\u0005u\u0005\u0019AAk\u0003]I7\u000fU8t\u0013:4\u0017N\\5us\u0012*\u0007\u0010^3og&|g\u000e\u0006\u0003\u0003N!M\u0001\u0002CC=\u0003?\u0003\r!!6\u0002%%\u001ch)\u001b8ji\u0016$S\r\u001f;f]NLwN\u001c\u000b\u0005\u0005\u001bBI\u0002\u0003\u0005\u0006z\u0005\u0005\u0006\u0019AAk\u0003IA\u0017m\u001d5D_\u0012,G%\u001a=uK:\u001c\u0018n\u001c8\u0015\t\r\u0005\u0006r\u0004\u0005\t\u000bs\n\u0019\u000b1\u0001\u0002V\u0006\u0001R-];bYN$S\r\u001f;f]NLwN\u001c\u000b\u0005\u0011KAI\u0003\u0006\u0003\u0003N!\u001d\u0002BCBU\u0003K\u000b\t\u00111\u0001\u0004,\"AQ\u0011PAS\u0001\u0004\t)\u000e
    #9 = Utf8               value
   #10 = Utf8               F
   #11 = Utf8               equals$extension
   #12 = Utf8               (FLjava/lang/Object;)Z
   #13 = Utf8               $this
   #14 = Utf8               x$1
   #15 = Utf8               org/scalactic/anyvals/PosFloat$
   #16 = Class              #15           // org/scalactic/anyvals/PosFloat$
   #17 = Utf8               MODULE$
   #18 = Utf8               Lorg/scalactic/anyvals/PosFloat$;
   #19 = NameAndType        #17:#18       // MODULE$:Lorg/scalactic/anyvals/PosFloat$;
   #20 = Fieldref           #16.#19       // org/scalactic/anyvals/PosFloat$.MODULE$:Lorg/scalactic/anyvals/PosFloat$;
   #21 = NameAndType        #11:#12       // equals$extension:(FLjava/lang/Object;)Z
   #22 = Methodref          #16.#21       // org/scalactic/anyvals/PosFloat$.equals$extension:(FLjava/lang/Object;)Z
   #23 = Utf8               Ljava/lang/Object;
   #24 = Utf8               hashCode$extension
   #25 = Utf8               (F)I
   #26 = NameAndType        #24:#25       // hashCode$extension:(F)I
   #27 = Methodref          #16.#26       // org/scalactic/anyvals/PosFloat$.hashCode$extension:(F)I
   #28 = Utf8               isFinite$extension
   #29 = Utf8               (F)Z
   #30 = NameAndType        #28:#29       // isFinite$extension:(F)Z
   #31 = Methodref          #16.#30       // org/scalactic/anyvals/PosFloat$.isFinite$extension:(F)Z
   #32 = Utf8               isPosInfinity$extension
   #33 = NameAndType        #32:#29       // isPosInfinity$extension:(F)Z
   #34 = Methodref          #16.#33       // org/scalactic/anyvals/PosFloat$.isPosInfinity$extension:(F)Z
   #35 = Utf8               plus$extension
   #36 = Utf8               (FF)F
   #37 = Utf8               x
   #38 = NameAndType        #35:#36       // plus$extension:(FF)F
   #39 = Methodref          #16.#38       // org/scalactic/anyvals/PosFloat$.plus$extension:(FF)F
   #40 = Utf8               floor$extension
   #41 = Utf8               (F)F
   #42 = NameAndType        #40:#41       // floor$extension:(F)F
   #43 = Methodref          #16.#42       // org/scalactic/anyvals/PosFloat$.floor$extension:(F)F
   #44 = Utf8               ceil$extension
   #45 = NameAndType        #44:#41       // ceil$extension:(F)F
   #46 = Methodref          #16.#45       // org/scalactic/anyvals/PosFloat$.ceil$extension:(F)F
   #47 = Utf8               round$extension
   #48 = NameAndType        #47:#25       // round$extension:(F)I
   #49 = Methodref          #16.#48       // org/scalactic/anyvals/PosFloat$.round$extension:(F)I
   #50 = Utf8               ensuringValid$extension
   #51 = Utf8               (FLscala/Function1;)F
   #52 = Utf8               f
   #53 = NameAndType        #50:#51       // ensuringValid$extension:(FLscala/Function1;)F
   #54 = Methodref          #16.#53       // org/scalactic/anyvals/PosFloat$.ensuringValid$extension:(FLscala/Function1;)F
   #55 = Utf8               Lscala/Function1;
   #56 = Utf8               toDegrees$extension
   #57 = NameAndType        #56:#41       // toDegrees$extension:(F)F
   #58 = Methodref          #16.#57       // org/scalactic/anyvals/PosFloat$.toDegrees$extension:(F)F
   #59 = Utf8               toRadians$extension
   #60 = NameAndType        #59:#41       // toRadians$extension:(F)F
   #61 = Methodref          #16.#60       // org/scalactic/anyvals/PosFloat$.toRadians$extension:(F)F
   #62 = Utf8               isWhole$extension
   #63 = NameAndType        #62:#29       // isWhole$extension:(F)Z
   #64 = Methodref          #16.#63       // org/scalactic/anyvals/PosFloat$.isWhole$extension:(F)Z
   #65 = Utf8               min$extension
   #66 = Utf8               that
   #67 = NameAndType        #65:#36       // min$extension:(FF)F
   #68 = Methodref          #16.#67       // org/scalactic/anyvals/PosFloat$.min$extension:(FF)F
   #69 = Utf8               max$extension
   #70 = NameAndType        #69:#36       // max$extension:(FF)F
   #71 = Methodref          #16.#70       // org/scalactic/anyvals/PosFloat$.max$extension:(FF)F
   #72 = Utf8               $percent$extension
   #73 = Utf8               (FD)D
   #74 = NameAndType        #72:#73       // $percent$extension:(FD)D
   #75 = Methodref          #16.#74       // org/scalactic/anyvals/PosFloat$.$percent$extension:(FD)D
   #76 = Utf8               D
   #77 = NameAndType        #72:#36       // $percent$extension:(FF)F
   #78 = Methodref          #16.#77       // org/scalactic/anyvals/PosFloat$.$percent$extension:(FF)F
   #79 = Utf8               (FJ)F
   #80 = NameAndType        #72:#79       // $percent$extension:(FJ)F
   #81 = Methodref          #16.#80       // org/scalactic/anyvals/PosFloat$.$percent$extension:(FJ)F
   #82 = Utf8               J
   #83 = Utf8               (FI)F
   #84 = NameAndType        #72:#83       // $percent$extension:(FI)F
   #85 = Methodref          #16.#84       // org/scalactic/anyvals/PosFloat$.$percent$extension:(FI)F
   #86 = Utf8               I
   #87 = Utf8               (FC)F
   #88 = NameAndType        #72:#87       // $percent$extension:(FC)F
   #89 = Methodref          #16.#88       // org/scalactic/anyvals/PosFloat$.$percent$extension:(FC)F
   #90 = Utf8               C
   #91 = Utf8               (FS)F
   #92 = NameAndType        #72:#91       // $percent$extension:(FS)F
   #93 = Methodref          #16.#92       // org/scalactic/anyvals/PosFloat$.$percent$extension:(FS)F
   #94 = Utf8               S
   #95 = Utf8               (FB)F
   #96 = NameAndType        #72:#95       // $percent$extension:(FB)F
   #97 = Methodref          #16.#96       // org/scalactic/anyvals/PosFloat$.$percent$extension:(FB)F
   #98 = Utf8               B
   #99 = Utf8               $div$extension
  #100 = NameAndType        #99:#73       // $div$extension:(FD)D
  #101 = Methodref          #16.#100      // org/scalactic/anyvals/PosFloat$.$div$extension:(FD)D
  #102 = NameAndType        #99:#36       // $div$extension:(FF)F
  #103 = Methodref          #16.#102      // org/scalactic/anyvals/PosFloat$.$div$extension:(FF)F
  #104 = NameAndType        #99:#79       // $div$extension:(FJ)F
  #105 = Methodref          #16.#104      // org/scalactic/anyvals/PosFloat$.$div$extension:(FJ)F
  #106 = NameAndType        #99:#83       // $div$extension:(FI)F
  #107 = Methodref          #16.#106      // org/scalactic/anyvals/PosFloat$.$div$extension:(FI)F
  #108 = NameAndType        #99:#87       // $div$extension:(FC)F
  #109 = Methodref          #16.#108      // org/scalactic/anyvals/PosFloat$.$div$extension:(FC)F
  #110 = NameAndType        #99:#91       // $div$extension:(FS)F
  #111 = Methodref          #16.#110      // org/scalactic/anyvals/PosFloat$.$div$extension:(FS)F
  #112 = NameAndType        #99:#95       // $div$extension:(FB)F
  #113 = Methodref          #16.#112      // org/scalactic/anyvals/PosFloat$.$div$extension:(FB)F
  #114 = Utf8               $times$extension
  #115 = NameAndType        #114:#73      // $times$extension:(FD)D
  #116 = Methodref          #16.#115      // org/scalactic/anyvals/PosFloat$.$times$extension:(FD)D
  #117 = NameAndType        #114:#36      // $times$extension:(FF)F
  #118 = Methodref          #16.#117      // org/scalactic/anyvals/PosFloat$.$times$extension:(FF)F
  #119 = NameAndType        #114:#79      // $times$extension:(FJ)F
  #120 = Methodref          #16.#119      // org/scalactic/anyvals/PosFloat$.$times$extension:(FJ)F
  #121 = NameAndType        #114:#83      // $times$extension:(FI)F
  #122 = Methodref          #16.#121      // org/scalactic/anyvals/PosFloat$.$times$extension:(FI)F
  #123 = NameAndType        #114:#87      // $times$extension:(FC)F
  #124 = Methodref          #16.#123      // org/scalactic/anyvals/PosFloat$.$times$extension:(FC)F
  #125 = NameAndType        #114:#91      // $times$extension:(FS)F
  #126 = Methodref          #16.#125      // org/scalactic/anyvals/PosFloat$.$times$extension:(FS)F
  #127 = NameAndType        #114:#95      // $times$extension:(FB)F
  #128 = Methodref          #16.#127      // org/scalactic/anyvals/PosFloat$.$times$extension:(FB)F
  #129 = Utf8               $minus$extension
  #130 = NameAndType        #129:#73      // $minus$extension:(FD)D
  #131 = Methodref          #16.#130      // org/scalactic/anyvals/PosFloat$.$minus$extension:(FD)D
  #132 = NameAndType        #129:#36      // $minus$extension:(FF)F
  #133 = Methodref          #16.#132      // org/scalactic/anyvals/PosFloat$.$minus$extension:(FF)F
  #134 = NameAndType        #129:#79      // $minus$extension:(FJ)F
  #135 = Methodref          #16.#134      // org/scalactic/anyvals/PosFloat$.$minus$extension:(FJ)F
  #136 = NameAndType        #129:#83      // $minus$extension:(FI)F
  #137 = Methodref          #16.#136      // org/scalactic/anyvals/PosFloat$.$minus$extension:(FI)F
  #138 = NameAndType        #129:#87      // $minus$extension:(FC)F
  #139 = Methodref          #16.#138      // org/scalactic/anyvals/PosFloat$.$minus$extension:(FC)F
  #140 = NameAndType        #129:#91      // $minus$extension:(FS)F
  #141 = Methodref          #16.#140      // org/scalactic/anyvals/PosFloat$.$minus$extension:(FS)F
  #142 = NameAndType        #129:#95      // $minus$extension:(FB)F
  #143 = Methodref          #16.#142      // org/scalactic/anyvals/PosFloat$.$minus$extension:(FB)F
  #144 = Utf8               $plus$extension
  #145 = NameAndType        #144:#73      // $plus$extension:(FD)D
  #146 = Methodref          #16.#145      // org/scalactic/anyvals/PosFloat$.$plus$extension:(FD)D
  #147 = NameAndType        #144:#36      // $plus$extension:(FF)F
  #148 = Methodref          #16.#147      // org/scalactic/anyvals/PosFloat$.$plus$extension:(FF)F
  #149 = NameAndType        #144:#79      // $plus$extension:(FJ)F
  #150 = Methodref          #16.#149      // org/scalactic/anyvals/PosFloat$.$plus$extension:(FJ)F
  #151 = NameAndType        #144:#83      // $plus$extension:(FI)F
  #152 = Methodref          #16.#151      // org/scalactic/anyvals/PosFloat$.$plus$extension:(FI)F
  #153 = NameAndType        #144:#87      // $plus$extension:(FC)F
  #154 = Methodref          #16.#153      // org/scalactic/anyvals/PosFloat$.$plus$extension:(FC)F
  #155 = NameAndType        #144:#91      // $plus$extension:(FS)F
  #156 = Methodref          #16.#155      // org/scalactic/anyvals/PosFloat$.$plus$extension:(FS)F
  #157 = NameAndType        #144:#95      // $plus$extension:(FB)F
  #158 = Methodref          #16.#157      // org/scalactic/anyvals/PosFloat$.$plus$extension:(FB)F
  #159 = Utf8               $greater$eq$extension
  #160 = Utf8               (FD)Z
  #161 = NameAndType        #159:#160     // $greater$eq$extension:(FD)Z
  #162 = Methodref          #16.#161      // org/scalactic/anyvals/PosFloat$.$greater$eq$extension:(FD)Z
  #163 = Utf8               (FF)Z
  #164 = NameAndType        #159:#163     // $greater$eq$extension:(FF)Z
  #165 = Methodref          #16.#164      // org/scalactic/anyvals/PosFloat$.$greater$eq$extension:(FF)Z
  #166 = Utf8               (FJ)Z
  #167 = NameAndType        #159:#166     // $greater$eq$extension:(FJ)Z
  #168 = Methodref          #16.#167      // org/scalactic/anyvals/PosFloat$.$greater$eq$extension:(FJ)Z
  #169 = Utf8               (FI)Z
  #170 = NameAndType        #159:#169     // $greater$eq$extension:(FI)Z
  #171 = Methodref          #16.#170      // org/scalactic/anyvals/PosFloat$.$greater$eq$extension:(FI)Z
  #172 = Utf8               (FC)Z
  #173 = NameAndType        #159:#172     // $greater$eq$extension:(FC)Z
  #174 = Methodref          #16.#173      // org/scalactic/anyvals/PosFloat$.$greater$eq$extension:(FC)Z
  #175 = Utf8               (FS)Z
  #176 = NameAndType        #159:#175     // $greater$eq$extension:(FS)Z
  #177 = Methodref          #16.#176      // org/scalactic/anyvals/PosFloat$.$greater$eq$extension:(FS)Z
  #178 = Utf8               (FB)Z
  #179 = NameAndType        #159:#178     // $greater$eq$extension:(FB)Z
  #180 = Methodref          #16.#179      // org/scalactic/anyvals/PosFloat$.$greater$eq$extension:(FB)Z
  #181 = Utf8               $greater$extension
  #182 = NameAndType        #181:#160     // $greater$extension:(FD)Z
  #183 = Methodref          #16.#182      // org/scalactic/anyvals/PosFloat$.$greater$extension:(FD)Z
  #184 = NameAndType        #181:#163     // $greater$extension:(FF)Z
  #185 = Methodref          #16.#184      // org/scalactic/anyvals/PosFloat$.$greater$extension:(FF)Z
  #186 = NameAndType        #181:#166     // $greater$extension:(FJ)Z
  #187 = Methodref          #16.#186      // org/scalactic/anyvals/PosFloat$.$greater$extension:(FJ)Z
  #188 = NameAndType        #181:#169     // $greater$extension:(FI)Z
  #189 = Methodref          #16.#188      // org/scalactic/anyvals/PosFloat$.$greater$extension:(FI)Z
  #190 = NameAndType        #181:#172     // $greater$extension:(FC)Z
  #191 = Methodref          #16.#190      // org/scalactic/anyvals/PosFloat$.$greater$extension:(FC)Z
  #192 = NameAndType        #181:#175     // $greater$extension:(FS)Z
  #193 = Methodref          #16.#192      // org/scalactic/anyvals/PosFloat$.$greater$extension:(FS)Z
  #194 = NameAndType        #181:#178     // $greater$extension:(FB)Z
  #195 = Methodref          #16.#194      // org/scalactic/anyvals/PosFloat$.$greater$extension:(FB)Z
  #196 = Utf8               $less$eq$extension
  #197 = NameAndType        #196:#160     // $less$eq$extension:(FD)Z
  #198 = Methodref          #16.#197      // org/scalactic/anyvals/PosFloat$.$less$eq$extension:(FD)Z
  #199 = NameAndType        #196:#163     // $less$eq$extension:(FF)Z
  #200 = Methodref          #16.#199      // org/scalactic/anyvals/PosFloat$.$less$eq$extension:(FF)Z
  #201 = NameAndType        #196:#166     // $less$eq$extension:(FJ)Z
  #202 = Methodref          #16.#201      // org/scalactic/anyvals/PosFloat$.$less$eq$extension:(FJ)Z
  #203 = NameAndType        #196:#169     // $less$eq$extension:(FI)Z
  #204 = Methodref          #16.#203      // org/scalactic/anyvals/PosFloat$.$less$eq$extension:(FI)Z
  #205 = NameAndType        #196:#172     // $less$eq$extension:(FC)Z
  #206 = Methodref          #16.#205      // org/scalactic/anyvals/PosFloat$.$less$eq$extension:(FC)Z
  #207 = NameAndType        #196:#175     // $less$eq$extension:(FS)Z
  #208 = Methodref          #16.#207      // org/scalactic/anyvals/PosFloat$.$less$eq$extension:(FS)Z
  #209 = NameAndType        #196:#178     // $less$eq$extension:(FB)Z
  #210 = Methodref          #16.#209      // org/scalactic/anyvals/PosFloat$.$less$eq$extension:(FB)Z
  #211 = Utf8               $less$extension
  #212 = NameAndType        #211:#160     // $less$extension:(FD)Z
  #213 = Methodref          #16.#212      // org/scalactic/anyvals/PosFloat$.$less$extension:(FD)Z
  #214 = NameAndType        #211:#163     // $less$extension:(FF)Z
  #215 = Methodref          #16.#214      // org/scalactic/anyvals/PosFloat$.$less$extension:(FF)Z
  #216 = NameAndType        #211:#166     // $less$extension:(FJ)Z
  #217 = Methodref          #16.#216      // org/scalactic/anyvals/PosFloat$.$less$extension:(FJ)Z
  #218 = NameAndType        #211:#169     // $less$extension:(FI)Z
  #219 = Methodref          #16.#218      // org/scalactic/anyvals/PosFloat$.$less$extension:(FI)Z
  #220 = NameAndType        #211:#172     // $less$extension:(FC)Z
  #221 = Methodref          #16.#220      // org/scalactic/anyvals/PosFloat$.$less$extension:(FC)Z
  #222 = NameAndType        #211:#175     // $less$extension:(FS)Z
  #223 = Methodref          #16.#222      // org/scalactic/anyvals/PosFloat$.$less$extension:(FS)Z
  #224 = NameAndType        #211:#178     // $less$extension:(FB)Z
  #225 = Methodref          #16.#224      // org/scalactic/anyvals/PosFloat$.$less$extension:(FB)Z
  #226 = Utf8               (FLjava/lang/String;)Ljava/lang/String;
  #227 = NameAndType        #144:#226     // $plus$extension:(FLjava/lang/String;)Ljava/lang/String;
  #228 = Methodref          #16.#227      // org/scalactic/anyvals/PosFloat$.$plus$extension:(FLjava/lang/String;)Ljava/lang/String;
  #229 = Utf8               Ljava/lang/String;
  #230 = Utf8               unary_$minus$extension
  #231 = NameAndType        #230:#41      // unary_$minus$extension:(F)F
  #232 = Methodref          #16.#231      // org/scalactic/anyvals/PosFloat$.unary_$minus$extension:(F)F
  #233 = Utf8               unary_$plus$extension
  #234 = NameAndType        #233:#41      // unary_$plus$extension:(F)F
  #235 = Methodref          #16.#234      // org/scalactic/anyvals/PosFloat$.unary_$plus$extension:(F)F
  #236 = Utf8               toDouble$extension
  #237 = Utf8               (F)D
  #238 = NameAndType        #236:#237     // toDouble$extension:(F)D
  #239 = Methodref          #16.#238      // org/scalactic/anyvals/PosFloat$.toDouble$extension:(F)D
  #240 = Utf8               toFloat$extension
  #241 = NameAndType        #240:#41      // toFloat$extension:(F)F
  #242 = Methodref          #16.#241      // org/scalactic/anyvals/PosFloat$.toFloat$extension:(F)F
  #243 = Utf8               toLong$extension
  #244 = Utf8               (F)J
  #245 = NameAndType        #243:#244     // toLong$extension:(F)J
  #246 = Methodref          #16.#245      // org/scalactic/anyvals/PosFloat$.toLong$extension:(F)J
  #247 = Utf8               toInt$extension
  #248 = NameAndType        #247:#25      // toInt$extension:(F)I
  #249 = Methodref          #16.#248      // org/scalactic/anyvals/PosFloat$.toInt$extension:(F)I
  #250 = Utf8               toChar$extension
  #251 = Utf8               (F)C
  #252 = NameAndType        #250:#251     // toChar$extension:(F)C
  #253 = Methodref          #16.#252      // org/scalactic/anyvals/PosFloat$.toChar$extension:(F)C
  #254 = Utf8               toShort$extension
  #255 = Utf8               (F)S
  #256 = NameAndType        #254:#255     // toShort$extension:(F)S
  #257 = Methodref          #16.#256      // org/scalactic/anyvals/PosFloat$.toShort$extension:(F)S
  #258 = Utf8               toByte$extension
  #259 = Utf8               (F)B
  #260 = NameAndType        #258:#259     // toByte$extension:(F)B
  #261 = Methodref          #16.#260      // org/scalactic/anyvals/PosFloat$.toByte$extension:(F)B
  #262 = Utf8               toString$extension
  #263 = Utf8               (F)Ljava/lang/String;
  #264 = NameAndType        #262:#263     // toString$extension:(F)Ljava/lang/String;
  #265 = Methodref          #16.#264      // org/scalactic/anyvals/PosFloat$.toString$extension:(F)Ljava/lang/String;
  #266 = Utf8               posFloatOrd
  #267 = Utf8               ()Lscala/math/Ordering;
  #268 = Utf8               ()Lscala/math/Ordering<Lorg/scalactic/anyvals/PosFloat;>;
  #269 = NameAndType        #266:#267     // posFloatOrd:()Lscala/math/Ordering;
  #270 = Methodref          #16.#269      // org/scalactic/anyvals/PosFloat$.posFloatOrd:()Lscala/math/Ordering;
  #271 = Utf8               MinPositiveValue
  #272 = Utf8               ()F
  #273 = NameAndType        #271:#272     // MinPositiveValue:()F
  #274 = Methodref          #16.#273      // org/scalactic/anyvals/PosFloat$.MinPositiveValue:()F
  #275 = Utf8               PositiveInfinity
  #276 = NameAndType        #275:#272     // PositiveInfinity:()F
  #277 = Methodref          #16.#276      // org/scalactic/anyvals/PosFloat$.PositiveInfinity:()F
  #278 = Utf8               ordering
  #279 = NameAndType        #278:#267     // ordering:()Lscala/math/Ordering;
  #280 = Methodref          #16.#279      // org/scalactic/anyvals/PosFloat$.ordering:()Lscala/math/Ordering;
  #281 = Utf8               widenToNonZeroDouble
  #282 = Utf8               pos
  #283 = NameAndType        #281:#237     // widenToNonZeroDouble:(F)D
  #284 = Methodref          #16.#283      // org/scalactic/anyvals/PosFloat$.widenToNonZeroDouble:(F)D
  #285 = Utf8               widenToNonZeroFloat
  #286 = NameAndType        #285:#41      // widenToNonZeroFloat:(F)F
  #287 = Methodref          #16.#286      // org/scalactic/anyvals/PosFloat$.widenToNonZeroFloat:(F)F
  #288 = Utf8               widenToPosZDouble
  #289 = NameAndType        #288:#237     // widenToPosZDouble:(F)D
  #290 = Methodref          #16.#289      // org/scalactic/anyvals/PosFloat$.widenToPosZDouble:(F)D
  #291 = Utf8               widenToPosZFloat
  #292 = NameAndType        #291:#41      // widenToPosZFloat:(F)F
  #293 = Methodref          #16.#292      // org/scalactic/anyvals/PosFloat$.widenToPosZFloat:(F)F
  #294 = Utf8               widenToPosDouble
  #295 = NameAndType        #294:#237     // widenToPosDouble:(F)D
  #296 = Methodref          #16.#295      // org/scalactic/anyvals/PosFloat$.widenToPosDouble:(F)D
  #297 = Utf8               widenToDouble
  #298 = NameAndType        #297:#237     // widenToDouble:(F)D
  #299 = Methodref          #16.#298      // org/scalactic/anyvals/PosFloat$.widenToDouble:(F)D
  #300 = Utf8               widenToFloat
  #301 = NameAndType        #300:#41      // widenToFloat:(F)F
  #302 = Methodref          #16.#301      // org/scalactic/anyvals/PosFloat$.widenToFloat:(F)F
  #303 = Utf8               fromOrElse
  #304 = Utf8               (FLscala/Function0;)F
  #305 = Utf8               default
  #306 = NameAndType        #303:#304     // fromOrElse:(FLscala/Function0;)F
  #307 = Methodref          #16.#306      // org/scalactic/anyvals/PosFloat$.fromOrElse:(FLscala/Function0;)F
  #308 = Utf8               Lscala/Function0;
  #309 = Utf8               isValid
  #310 = NameAndType        #309:#29      // isValid:(F)Z
  #311 = Methodref          #16.#310      // org/scalactic/anyvals/PosFloat$.isValid:(F)Z
  #312 = Utf8               rightOrElse
  #313 = Utf8               (FLscala/Function1;)Lscala/util/Either;
  #314 = Utf8               <L:Ljava/lang/Object;>(FLscala/Function1<Ljava/lang/Object;TL;>;)Lscala/util/Either<TL;Lorg/scalactic/anyvals/PosFloat;>;
  #315 = NameAndType        #312:#313     // rightOrElse:(FLscala/Function1;)Lscala/util/Either;
  #316 = Methodref          #16.#315      // org/scalactic/anyvals/PosFloat$.rightOrElse:(FLscala/Function1;)Lscala/util/Either;
  #317 = Utf8               goodOrElse
  #318 = Utf8               (FLscala/Function1;)Lorg/scalactic/Or;
  #319 = Utf8               <B:Ljava/lang/Object;>(FLscala/Function1<Ljava/lang/Object;TB;>;)Lorg/scalactic/Or<Lorg/scalactic/anyvals/PosFloat;TB;>;
  #320 = NameAndType        #317:#318     // goodOrElse:(FLscala/Function1;)Lorg/scalactic/Or;
  #321 = Methodref          #16.#320      // org/scalactic/anyvals/PosFloat$.goodOrElse:(FLscala/Function1;)Lorg/scalactic/Or;
  #322 = Utf8               passOrElse
  #323 = Utf8               (FLscala/Function1;)Lorg/scalactic/Validation;
  #324 = Utf8               <E:Ljava/lang/Object;>(FLscala/Function1<Ljava/lang/Object;TE;>;)Lorg/scalactic/Validation<TE;>;
  #325 = NameAndType        #322:#323     // passOrElse:(FLscala/Function1;)Lorg/scalactic/Validation;
  #326 = Methodref          #16.#325      // org/scalactic/anyvals/PosFloat$.passOrElse:(FLscala/Function1;)Lorg/scalactic/Validation;
  #327 = Utf8               tryingValid
  #328 = Utf8               (F)Lscala/util/Try;
  #329 = Utf8               (F)Lscala/util/Try<Lorg/scalactic/anyvals/PosFloat;>;
  #330 = NameAndType        #327:#328     // tryingValid:(F)Lscala/util/Try;
  #331 = Methodref          #16.#330      // org/scalactic/anyvals/PosFloat$.tryingValid:(F)Lscala/util/Try;
  #332 = Utf8               from
  #333 = Utf8               (F)Lscala/Option;
  #334 = Utf8               (F)Lscala/Option<Lorg/scalactic/anyvals/PosFloat;>;
  #335 = NameAndType        #332:#333     // from:(F)Lscala/Option;
  #336 = Methodref          #16.#335      // org/scalactic/anyvals/PosFloat$.from:(F)Lscala/Option;
  #337 = Utf8               MinValue
  #338 = NameAndType        #337:#272     // MinValue:()F
  #339 = Methodref          #16.#338      // org/scalactic/anyvals/PosFloat$.MinValue:()F
  #340 = Utf8               MaxValue
  #341 = NameAndType        #340:#272     // MaxValue:()F
  #342 = Methodref          #16.#341      // org/scalactic/anyvals/PosFloat$.MaxValue:()F
  #343 = NameAndType        #9:#10        // value:F
  #344 = Fieldref           #2.#343       // org/scalactic/anyvals/PosFloat.value:F
  #345 = Utf8               this
  #346 = Utf8               Lorg/scalactic/anyvals/PosFloat;
  #347 = Utf8               toString
  #348 = Utf8               ()Ljava/lang/String;
  #349 = NameAndType        #9:#272       // value:()F
  #350 = Methodref          #2.#349       // org/scalactic/anyvals/PosFloat.value:()F
  #351 = Utf8               toByte
  #352 = Utf8               ()B
  #353 = Utf8               toShort
  #354 = Utf8               ()S
  #355 = Utf8               toChar
  #356 = Utf8               ()C
  #357 = Utf8               toInt
  #358 = Utf8               ()I
  #359 = Utf8               toLong
  #360 = Utf8               ()J
  #361 = Utf8               toFloat
  #362 = Utf8               toDouble
  #363 = Utf8               ()D
  #364 = Utf8               unary_$plus
  #365 = Utf8               unary_$minus
  #366 = Utf8               $plus
  #367 = Utf8               (Ljava/lang/String;)Ljava/lang/String;
  #368 = Utf8               $less
  #369 = Utf8               (B)Z
  #370 = Utf8               (S)Z
  #371 = Utf8               (C)Z
  #372 = Utf8               (I)Z
  #373 = Utf8               (J)Z
  #374 = Utf8               (D)Z
  #375 = Utf8               $less$eq
  #376 = Utf8               $greater
  #377 = Utf8               $greater$eq
  #378 = Utf8               (B)F
  #379 = Utf8               (S)F
  #380 = Utf8               (C)F
  #381 = Utf8               (I)F
  #382 = Utf8               (J)F
  #383 = Utf8               (D)D
  #384 = Utf8               $minus
  #385 = Utf8               $times
  #386 = Utf8               $div
  #387 = Utf8               $percent
  #388 = Utf8               max
  #389 = Utf8               min
  #390 = Utf8               isWhole
  #391 = Utf8               ()Z
  #392 = Utf8               toRadians
  #393 = Utf8               toDegrees
  #394 = Utf8               ensuringValid
  #395 = Utf8               (Lscala/Function1;)F
  #396 = Utf8               (Lscala/Function1<Ljava/lang/Object;Ljava/lang/Object;>;)F
  #397 = Utf8               round
  #398 = Utf8               ceil
  #399 = Utf8               floor
  #400 = Utf8               plus
  #401 = Utf8               isPosInfinity
  #402 = Utf8               isFinite
  #403 = Utf8               hashCode
  #404 = Utf8               equals
  #405 = Utf8               (Ljava/lang/Object;)Z
  #406 = Utf8               <init>
  #407 = Utf8               (F)V
  #408 = Utf8               ()V
  #409 = NameAndType        #406:#408     // "<init>":()V
  #410 = Methodref          #4.#409       // java/lang/Object."<init>":()V
  #411 = Utf8               Code
  #412 = Utf8               LocalVariableTable
  #413 = Utf8               MethodParameters
  #414 = Utf8               Signature
  #415 = Utf8               Deprecated
  #416 = Utf8               LineNumberTable
  #417 = Utf8               SourceFile
  #418 = Utf8               RuntimeVisibleAnnotations
  #419 = Utf8               ScalaInlineInfo
  #420 = Utf8               ScalaSig
{
  private final float value;
    descriptor: F
    flags: (0x0012) ACC_PRIVATE, ACC_FINAL

  public static boolean equals$extension(float, java.lang.Object);
    descriptor: (FLjava/lang/Object;)Z
    flags: (0x0009) ACC_PUBLIC, ACC_STATIC
    Code:
      stack=3, locals=2, args_size=2
         0: getstatic     #20                 // Field org/scalactic/anyvals/PosFloat$.MODULE$:Lorg/scalactic/anyvals/PosFloat$;
         3: fload_0
         4: aload_1
         5: invokevirtual #22                 // Method org/scalactic/anyvals/PosFloat$.equals$extension:(FLjava/lang/Object;)Z
         8: ireturn
      LocalVariableTable:
        Start  Length  Slot  Name   Signature
            0       9     0 $this   F
            0       9     1   x$1   Ljava/lang/Object;
    MethodParameters:
      Name                           Flags
      $this                          final
      x$1                            final

  public static int hashCode$extension(float);
    descriptor: (F)I
    flags: (0x0009) ACC_PUBLIC, ACC_STATIC
    Code:
      stack=2, locals=1, args_size=1
         0: getstatic     #20                 // Field org/scalactic/anyvals/PosFloat$.MODULE$:Lorg/scalactic/anyvals/PosFloat$;
         3: fload_0
         4: invokevirtual #27                 // Method org/scalactic/anyvals/PosFloat$.hashCode$extension:(F)I
         7: ireturn
      LocalVariableTable:
        Start  Length  Slot  Name   Signature
            0       8     0 $this   F
    MethodParameters:
      Name                           Flags
      $this                          final

  public static boolean isFinite$extension(float);
    descriptor: (F)Z
    flags: (0x0009) ACC_PUBLIC, ACC_STATIC
    Code:
      stack=2, locals=1, args_size=1
         0: getstatic     #20                 // Field org/scalactic/anyvals/PosFloat$.MODULE$:Lorg/scalactic/anyvals/PosFloat$;
         3: fload_0
         4: invokevirtual #31                 // Method org/scalactic/anyvals/PosFloat$.isFinite$extension:(F)Z
         7: ireturn
      LocalVariableTable:
        Start  Length  Slot  Name   Signature
            0       8     0 $this   F
    MethodParameters:
      Name                           Flags
      $this                          final

  public static boolean isPosInfinity$extension(float);
    descriptor: (F)Z
    flags: (0x0009) ACC_PUBLIC, ACC_STATIC
    Code:
      stack=2, locals=1, args_size=1
         0: getstatic     #20                 // Field org/scalactic/anyvals/PosFloat$.MODULE$:Lorg/scalactic/anyvals/PosFloat$;
         3: fload_0
         4: invokevirtual #34                 // Method org/scalactic/anyvals/PosFloat$.isPosInfinity$extension:(F)Z
         7: ireturn
      LocalVariableTable:
        Start  Length  Slot  Name   Signature
            0       8     0 $this   F
    MethodParameters:
      Name                           Flags
      $this                          final

  public static float plus$extension(float, float);
    descriptor: (FF)F
    flags: (0x0009) ACC_PUBLIC, ACC_STATIC
    Code:
      stack=3, locals=2, args_size=2
         0: getstatic     #20                 // Field org/scalactic/anyvals/PosFloat$.MODULE$:Lorg/scalactic/anyvals/PosFloat$;
         3: fload_0
         4: fload_1
         5: invokevirtual #39                 // Method org/scalactic/anyvals/PosFloat$.plus$extension:(FF)F
         8: freturn
      LocalVariableTable:
        Start  Length  Slot  Name   Signature
            0       9     0 $this   F
            0       9     1     x   F
    MethodParameters:
      Name                           Flags
      $this                          final
      x                              final

  public static float floor$extension(float);
    descriptor: (F)F
    flags: (0x0009) ACC_PUBLIC, ACC_STATIC
    Code:
      stack=2, locals=1, args_size=1
         0: getstatic     #20                 // Field org/scalactic/anyvals/PosFloat$.MODULE$:Lorg/scalactic/anyvals/PosFloat$;
         3: fload_0
         4: invokevirtual #43                 // Method org/scalactic/anyvals/PosFloat$.floor$extension:(F)F
         7: freturn
      LocalVariableTable:
        Start  Length  Slot  Name   Signature
            0       8     0 $this   F
    MethodParameters:
      Name                           Flags
      $this                          final

  public static float ceil$extension(float);
    descriptor: (F)F
    flags: (0x0009) ACC_PUBLIC, ACC_STATIC
    Code:
      stack=2, locals=1, args_size=1
         0: getstatic     #20                 // Field org/scalactic/anyvals/PosFloat$.MODULE$:Lorg/scalactic/anyvals/PosFloat$;
         3: fload_0
         4: invokevirtual #46                 // Method org/scalactic/anyvals/PosFloat$.ceil$extension:(F)F
         7: freturn
      LocalVariableTable:
        Start  Length  Slot  Name   Signature
            0       8     0 $this   F
    MethodParameters:
      Name                           Flags
      $this                          final

  public static int round$extension(float);
    descriptor: (F)I
    flags: (0x0009) ACC_PUBLIC, ACC_STATIC
    Code:
      stack=2, locals=1, args_size=1
         0: getstatic     #20                 // Field org/scalactic/anyvals/PosFloat$.MODULE$:Lorg/scalactic/anyvals/PosFloat$;
         3: fload_0
         4: invokevirtual #49                 // Method org/scalactic/anyvals/PosFloat$.round$extension:(F)I
         7: ireturn
      LocalVariableTable:
        Start  Length  Slot  Name   Signature
            0       8     0 $this   F
    MethodParameters:
      Name                           Flags
      $this                          final

  public static float ensuringValid$extension(float, scala.Function1);
    descriptor: (FLscala/Function1;)F
    flags: (0x0009) ACC_PUBLIC, ACC_STATIC
    Code:
      stack=3, locals=2, args_size=2
         0: getstatic     #20                 // Field org/scalactic/anyvals/PosFloat$.MODULE$:Lorg/scalactic/anyvals/PosFloat$;
         3: fload_0
         4: aload_1
         5: invokevirtual #54                 // Method org/scalactic/anyvals/PosFloat$.ensuringValid$extension:(FLscala/Function1;)F
         8: freturn
      LocalVariableTable:
        Start  Length  Slot  Name   Signature
            0       9     0 $this   F
            0       9     1     f   Lscala/Function1;
    MethodParameters:
      Name                           Flags
      $this                          final
      f                              final

  public static float toDegrees$extension(float);
    descriptor: (F)F
    flags: (0x0009) ACC_PUBLIC, ACC_STATIC
    Code:
      stack=2, locals=1, args_size=1
         0: getstatic     #20                 // Field org/scalactic/anyvals/PosFloat$.MODULE$:Lorg/scalactic/anyvals/PosFloat$;
         3: fload_0
         4: invokevirtual #58                 // Method org/scalactic/anyvals/PosFloat$.toDegrees$extension:(F)F
         7: freturn
      LocalVariableTable:
        Start  Length  Slot  Name   Signature
            0       8     0 $this   F
    MethodParameters:
      Name                           Flags
      $this                          final

  public static float toRadians$extension(float);
    descriptor: (F)F
    flags: (0x0009) ACC_PUBLIC, ACC_STATIC
    Code:
      stack=2, locals=1, args_size=1
         0: getstatic     #20                 // Field org/scalactic/anyvals/PosFloat$.MODULE$:Lorg/scalactic/anyvals/PosFloat$;
         3: fload_0
         4: invokevirtual #61                 // Method org/scalactic/anyvals/PosFloat$.toRadians$extension:(F)F
         7: freturn
      LocalVariableTable:
        Start  Length  Slot  Name   Signature
            0       8     0 $this   F
    MethodParameters:
      Name                           Flags
      $this                          final

  public static boolean isWhole$extension(float);
    descriptor: (F)Z
    flags: (0x0009) ACC_PUBLIC, ACC_STATIC
    Code:
      stack=2, locals=1, args_size=1
         0: getstatic     #20                 // Field org/scalactic/anyvals/PosFloat$.MODULE$:Lorg/scalactic/anyvals/PosFloat$;
         3: fload_0
         4: invokevirtual #64                 // Method org/scalactic/anyvals/PosFloat$.isWhole$extension:(F)Z
         7: ireturn
      LocalVariableTable:
        Start  Length  Slot  Name   Signature
            0       8     0 $this   F
    MethodParameters:
      Name                           Flags
      $this                          final

  public static float min$extension(float, float);
    descriptor: (FF)F
    flags: (0x0009) ACC_PUBLIC, ACC_STATIC
    Code:
      stack=3, locals=2, args_size=2
         0: getstatic     #20                 // Field org/scalactic/anyvals/PosFloat$.MODULE$:Lorg/scalactic/anyvals/PosFloat$;
         3: fload_0
         4: fload_1
         5: invokevirtual #68                 // Method org/scalactic/anyvals/PosFloat$.min$extension:(FF)F
         8: freturn
      LocalVariableTable:
        Start  Length  Slot  Name   Signature
            0       9     0 $this   F
            0       9     1  that   F
    MethodParameters:
      Name                           Flags
      $this                          final
      that                           final

  public static float max$extension(float, float);
    descriptor: (FF)F
    flags: (0x0009) ACC_PUBLIC, ACC_STATIC
    Code:
      stack=3, locals=2, args_size=2
         0: getstatic     #20                 // Field org/scalactic/anyvals/PosFloat$.MODULE$:Lorg/scalactic/anyvals/PosFloat$;
         3: fload_0
         4: fload_1
         5: invokevirtual #71                 // Method org/scalactic/anyvals/PosFloat$.max$extension:(FF)F
         8: freturn
      LocalVariableTable:
        Start  Length  Slot  Name   Signature
            0       9     0 $this   F
            0       9     1  that   F
    MethodParameters:
      Name                           Flags
      $this                          final
      that                           final

  public static double $percent$extension(float, double);
    descriptor: (FD)D
    flags: (0x0009) ACC_PUBLIC, ACC_STATIC
    Code:
      stack=4, locals=3, args_size=2
         0: getstatic     #20                 // Field org/scalactic/anyvals/PosFloat$.MODULE$:Lorg/scalactic/anyvals/PosFloat$;
         3: fload_0
         4: dload_1
         5: invokevirtual #75                 // Method org/scalactic/anyvals/PosFloat$.$percent$extension:(FD)D
         8: dreturn
      LocalVariableTable:
        Start  Length  Slot  Name   Signature
            0       9     0 $this   F
            0       9     1     x   D
    MethodParameters:
      Name                           Flags
      $this                          final
      x                              final

  public static float $percent$extension(float, float);
    descriptor: (FF)F
    flags: (0x0009) ACC_PUBLIC, ACC_STATIC
    Code:
      stack=3, locals=2, args_size=2
         0: getstatic     #20                 // Field org/scalactic/anyvals/PosFloat$.MODULE$:Lorg/scalactic/anyvals/PosFloat$;
         3: fload_0
         4: fload_1
         5: invokevirtual #78                 // Method org/scalactic/anyvals/PosFloat$.$percent$extension:(FF)F
         8: freturn
      LocalVariableTable:
        Start  Length  Slot  Name   Signature
            0       9     0 $this   F
            0       9     1     x   F
    MethodParameters:
      Name                           Flags
      $this                          final
      x                              final

  public static float $percent$extension(float, long);
    descriptor: (FJ)F
    flags: (0x0009) ACC_PUBLIC, ACC_STATIC
    Code:
      stack=4, locals=3, args_size=2
         0: getstatic     #20                 // Field org/scalactic/anyvals/PosFloat$.MODULE$:Lorg/scalactic/anyvals/PosFloat$;
         3: fload_0
         4: lload_1
         5: invokevirtual #81                 // Method org/scalactic/anyvals/PosFloat$.$percent$extension:(FJ)F
         8: freturn
      LocalVariableTable:
        Start  Length  Slot  Name   Signature
            0       9     0 $this   F
            0       9     1     x   J
    MethodParameters:
      Name                           Flags
      $this                          final
      x                              final

  public static float $percent$extension(float, int);
    descriptor: (FI)F
    flags: (0x0009) ACC_PUBLIC, ACC_STATIC
    Code:
      stack=3, locals=2, args_size=2
         0: getstatic     #20                 // Field org/scalactic/anyvals/PosFloat$.MODULE$:Lorg/scalactic/anyvals/PosFloat$;
         3: fload_0
         4: iload_1
         5: invokevirtual #85                 // Method org/scalactic/anyvals/PosFloat$.$percent$extension:(FI)F
         8: freturn
      LocalVariableTable:
        Start  Length  Slot  Name   Signature
            0       9     0 $this   F
            0       9     1     x   I
    MethodParameters:
      Name                           Flags
      $this                          final
      x                              final

  public static float $percent$extension(float, char);
    descriptor: (FC)F
    flags: (0x0009) ACC_PUBLIC, ACC_STATIC
    Code:
      stack=3, locals=2, args_size=2
         0: getstatic     #20                 // Field org/scalactic/anyvals/PosFloat$.MODULE$:Lorg/scalactic/anyvals/PosFloat$;
         3: fload_0
         4: iload_1
         5: invokevirtual #89                 // Method org/scalactic/anyvals/PosFloat$.$percent$extension:(FC)F
         8: freturn
      LocalVariableTable:
        Start  Length  Slot  Name   Signature
            0       9     0 $this   F
            0       9     1     x   C
    MethodParameters:
      Name                           Flags
      $this                          final
      x                              final

  public static float $percent$extension(float, short);
    descriptor: (FS)F
    flags: (0x0009) ACC_PUBLIC, ACC_STATIC
    Code:
      stack=3, locals=2, args_size=2
         0: getstatic     #20                 // Field org/scalactic/anyvals/PosFloat$.MODULE$:Lorg/scalactic/anyvals/PosFloat$;
         3: fload_0
         4: iload_1
         5: invokevirtual #93                 // Method org/scalactic/anyvals/PosFloat$.$percent$extension:(FS)F
         8: freturn
      LocalVariableTable:
        Start  Length  Slot  Name   Signature
            0       9     0 $this   F
            0       9     1     x   S
    MethodParameters:
      Name                           Flags
      $this                          final
      x                              final

  public static float $percent$extension(float, byte);
    descriptor: (FB)F
    flags: (0x0009) ACC_PUBLIC, ACC_STATIC
    Code:
      stack=3, locals=2, args_size=2
         0: getstatic     #20                 // Field org/scalactic/anyvals/PosFloat$.MODULE$:Lorg/scalactic/anyvals/PosFloat$;
         3: fload_0
         4: iload_1
         5: invokevirtual #97                 // Method org/scalactic/anyvals/PosFloat$.$percent$extension:(FB)F
         8: freturn
      LocalVariableTable:
        Start  Length  Slot  Name   Signature
            0       9     0 $this   F
            0       9     1     x   B
    MethodParameters:
      Name                           Flags
      $this                          final
      x                              final

  public static double $div$extension(float, double);
    descriptor: (FD)D
    flags: (0x0009) ACC_PUBLIC, ACC_STATIC
    Code:
      stack=4, locals=3, args_size=2
         0: getstatic     #20                 // Field org/scalactic/anyvals/PosFloat$.MODULE$:Lorg/scalactic/anyvals/PosFloat$;
         3: fload_0
         4: dload_1
         5: invokevirtual #101                // Method org/scalactic/anyvals/PosFloat$.$div$extension:(FD)D
         8: dreturn
      LocalVariableTable:
        Start  Length  Slot  Name   Signature
            0       9     0 $this   F
            0       9     1     x   D
    MethodParameters:
      Name                           Flags
      $this                          final
      x                              final

  public static float $div$extension(float, float);
    descriptor: (FF)F
    flags: (0x0009) ACC_PUBLIC, ACC_STATIC
    Code:
      stack=3, locals=2, args_size=2
         0: getstatic     #20                 // Field org/scalactic/anyvals/PosFloat$.MODULE$:Lorg/scalactic/anyvals/PosFloat$;
         3: fload_0
         4: fload_1
         5: invokevirtual #103                // Method org/scalactic/anyvals/PosFloat$.$div$extension:(FF)F
         8: freturn
      LocalVariableTable:
        Start  Length  Slot  Name   Signature
            0       9     0 $this   F
            0       9     1     x   F
    MethodParameters:
      Name                           Flags
      $this                          final
      x                              final

  public static float $div$extension(float, long);
    descriptor: (FJ)F
    flags: (0x0009) ACC_PUBLIC, ACC_STATIC
    Code:
      stack=4, locals=3, args_size=2
         0: getstatic     #20                 // Field org/scalactic/anyvals/PosFloat$.MODULE$:Lorg/scalactic/anyvals/PosFloat$;
         3: fload_0
         4: lload_1
         5: invokevirtual #105                // Method org/scalactic/anyvals/PosFloat$.$div$extension:(FJ)F
         8: freturn
      LocalVariableTable:
        Start  Length  Slot  Name   Signature
            0       9     0 $this   F
            0       9     1     x   J
    MethodParameters:
      Name                           Flags
      $this                          final
      x                              final

  public static float $div$extension(float, int);
    descriptor: (FI)F
    flags: (0x0009) ACC_PUBLIC, ACC_STATIC
    Code:
      stack=3, locals=2, args_size=2
         0: getstatic     #20                 // Field org/scalactic/anyvals/PosFloat$.MODULE$:Lorg/scalactic/anyvals/PosFloat$;
         3: fload_0
         4: iload_1
         5: invokevirtual #107                // Method org/scalactic/anyvals/PosFloat$.$div$extension:(FI)F
         8: freturn
      LocalVariableTable:
        Start  Length  Slot  Name   Signature
            0       9     0 $this   F
            0       9     1     x   I
    MethodParameters:
      Name                           Flags
      $this                          final
      x                              final

  public static float $div$extension(float, char);
    descriptor: (FC)F
    flags: (0x0009) ACC_PUBLIC, ACC_STATIC
    Code:
      stack=3, locals=2, args_size=2
         0: getstatic     #20                 // Field org/scalactic/anyvals/PosFloat$.MODULE$:Lorg/scalactic/anyvals/PosFloat$;
         3: fload_0
         4: iload_1
         5: invokevirtual #109                // Method org/scalactic/anyvals/PosFloat$.$div$extension:(FC)F
         8: freturn
      LocalVariableTable:
        Start  Length  Slot  Name   Signature
            0       9     0 $this   F
            0       9     1     x   C
    MethodParameters:
      Name                           Flags
      $this                          final
      x                              final

  public static float $div$extension(float, short);
    descriptor: (FS)F
    flags: (0x0009) ACC_PUBLIC, ACC_STATIC
    Code:
      stack=3, locals=2, args_size=2
         0: getstatic     #20                 // Field org/scalactic/anyvals/PosFloat$.MODULE$:Lorg/scalactic/anyvals/PosFloat$;
         3: fload_0
         4: iload_1
         5: invokevirtual #111                // Method org/scalactic/anyvals/PosFloat$.$div$extension:(FS)F
         8: freturn
      LocalVariableTable:
        Start  Length  Slot  Name   Signature
            0       9     0 $this   F
            0       9     1     x   S
    MethodParameters:
      Name                           Flags
      $this                          final
      x                              final

  public static float $div$extension(float, byte);
    descriptor: (FB)F
    flags: (0x0009) ACC_PUBLIC, ACC_STATIC
    Code:
      stack=3, locals=2, args_size=2
         0: getstatic     #20                 // Field org/scalactic/anyvals/PosFloat$.MODULE$:Lorg/scalactic/anyvals/PosFloat$;
         3: fload_0
         4: iload_1
         5: invokevirtual #113                // Method org/scalactic/anyvals/PosFloat$.$div$extension:(FB)F
         8: freturn
      LocalVariableTable:
        Start  Length  Slot  Name   Signature
            0       9     0 $this   F
            0       9     1     x   B
    MethodParameters:
      Name                           Flags
      $this                          final
      x                              final

  public static double $times$extension(float, double);
    descriptor: (FD)D
    flags: (0x0009) ACC_PUBLIC, ACC_STATIC
    Code:
      stack=4, locals=3, args_size=2
         0: getstatic     #20                 // Field org/scalactic/anyvals/PosFloat$.MODULE$:Lorg/scalactic/anyvals/PosFloat$;
         3: fload_0
         4: dload_1
         5: invokevirtual #116                // Method org/scalactic/anyvals/PosFloat$.$times$extension:(FD)D
         8: dreturn
      LocalVariableTable:
        Start  Length  Slot  Name   Signature
            0       9     0 $this   F
            0       9     1     x   D
    MethodParameters:
      Name                           Flags
      $this                          final
      x                              final

  public static float $times$extension(float, float);
    descriptor: (FF)F
    flags: (0x0009) ACC_PUBLIC, ACC_STATIC
    Code:
      stack=3, locals=2, args_size=2
         0: getstatic     #20                 // Field org/scalactic/anyvals/PosFloat$.MODULE$:Lorg/scalactic/anyvals/PosFloat$;
         3: fload_0
         4: fload_1
         5: invokevirtual #118                // Method org/scalactic/anyvals/PosFloat$.$times$extension:(FF)F
         8: freturn
      LocalVariableTable:
        Start  Length  Slot  Name   Signature
            0       9     0 $this   F
            0       9     1     x   F
    MethodParameters:
      Name                           Flags
      $this                          final
      x                              final

  public static float $times$extension(float, long);
    descriptor: (FJ)F
    flags: (0x0009) ACC_PUBLIC, ACC_STATIC
    Code:
      stack=4, locals=3, args_size=2
         0: getstatic     #20                 // Field org/scalactic/anyvals/PosFloat$.MODULE$:Lorg/scalactic/anyvals/PosFloat$;
         3: fload_0
         4: lload_1
         5: invokevirtual #120                // Method org/scalactic/anyvals/PosFloat$.$times$extension:(FJ)F
         8: freturn
      LocalVariableTable:
        Start  Length  Slot  Name   Signature
            0       9     0 $this   F
            0       9     1     x   J
    MethodParameters:
      Name                           Flags
      $this                          final
      x                              final

  public static float $times$extension(float, int);
    descriptor: (FI)F
    flags: (0x0009) ACC_PUBLIC, ACC_STATIC
    Code:
      stack=3, locals=2, args_size=2
         0: getstatic     #20                 // Field org/scalactic/anyvals/PosFloat$.MODULE$:Lorg/scalactic/anyvals/PosFloat$;
         3: fload_0
         4: iload_1
         5: invokevirtual #122                // Method org/scalactic/anyvals/PosFloat$.$times$extension:(FI)F
         8: freturn
      LocalVariableTable:
        Start  Length  Slot  Name   Signature
            0       9     0 $this   F
            0       9     1     x   I
    MethodParameters:
      Name                           Flags
      $this                          final
      x                              final

  public static float $times$extension(float, char);
    descriptor: (FC)F
    flags: (0x0009) ACC_PUBLIC, ACC_STATIC
    Code:
      stack=3, locals=2, args_size=2
         0: getstatic     #20                 // Field org/scalactic/anyvals/PosFloat$.MODULE$:Lorg/scalactic/anyvals/PosFloat$;
         3: fload_0
         4: iload_1
         5: invokevirtual #124                // Method org/scalactic/anyvals/PosFloat$.$times$extension:(FC)F
         8: freturn
      LocalVariableTable:
        Start  Length  Slot  Name   Signature
            0       9     0 $this   F
            0       9     1     x   C
    MethodParameters:
      Name                           Flags
      $this                          final
      x                              final

  public static float $times$extension(float, short);
    descriptor: (FS)F
    flags: (0x0009) ACC_PUBLIC, ACC_STATIC
    Code:
      stack=3, locals=2, args_size=2
         0: getstatic     #20                 // Field org/scalactic/anyvals/PosFloat$.MODULE$:Lorg/scalactic/anyvals/PosFloat$;
         3: fload_0
         4: iload_1
         5: invokevirtual #126                // Method org/scalactic/anyvals/PosFloat$.$times$extension:(FS)F
         8: freturn
      LocalVariableTable:
        Start  Length  Slot  Name   Signature
            0       9     0 $this   F
            0       9     1     x   S
    MethodParameters:
      Name                           Flags
      $this                          final
      x                              final

  public static float $times$extension(float, byte);
    descriptor: (FB)F
    flags: (0x0009) ACC_PUBLIC, ACC_STATIC
    Code:
      stack=3, locals=2, args_size=2
         0: getstatic     #20                 // Field org/scalactic/anyvals/PosFloat$.MODULE$:Lorg/scalactic/anyvals/PosFloat$;
         3: fload_0
         4: iload_1
         5: invokevirtual #128                // Method org/scalactic/anyvals/PosFloat$.$times$extension:(FB)F
         8: freturn
      LocalVariableTable:
        Start  Length  Slot  Name   Signature
            0       9     0 $this   F
            0       9     1     x   B
    MethodParameters:
      Name                           Flags
      $this                          final
      x                              final

  public static double $minus$extension(float, double);
    descriptor: (FD)D
    flags: (0x0009) ACC_PUBLIC, ACC_STATIC
    Code:
      stack=4, locals=3, args_size=2
         0: getstatic     #20                 // Field org/scalactic/anyvals/PosFloat$.MODULE$:Lorg/scalactic/anyvals/PosFloat$;
         3: fload_0
         4: dload_1
         5: invokevirtual #131                // Method org/scalactic/anyvals/PosFloat$.$minus$extension:(FD)D
         8: dreturn
      LocalVariableTable:
        Start  Length  Slot  Name   Signature
            0       9     0 $this   F
            0       9     1     x   D
    MethodParameters:
      Name                           Flags
      $this                          final
      x                              final

  public static float $minus$extension(float, float);
    descriptor: (FF)F
    flags: (0x0009) ACC_PUBLIC, ACC_STATIC
    Code:
      stack=3, locals=2, args_size=2
         0: getstatic     #20                 // Field org/scalactic/anyvals/PosFloat$.MODULE$:Lorg/scalactic/anyvals/PosFloat$;
         3: fload_0
         4: fload_1
         5: invokevirtual #133                // Method org/scalactic/anyvals/PosFloat$.$minus$extension:(FF)F
         8: freturn
      LocalVariableTable:
        Start  Length  Slot  Name   Signature
            0       9     0 $this   F
            0       9     1     x   F
    MethodParameters:
      Name                           Flags
      $this                          final
      x                              final

  public static float $minus$extension(float, long);
    descriptor: (FJ)F
    flags: (0x0009) ACC_PUBLIC, ACC_STATIC
    Code:
      stack=4, locals=3, args_size=2
         0: getstatic     #20                 // Field org/scalactic/anyvals/PosFloat$.MODULE$:Lorg/scalactic/anyvals/PosFloat$;
         3: fload_0
         4: lload_1
         5: invokevirtual #135                // Method org/scalactic/anyvals/PosFloat$.$minus$extension:(FJ)F
         8: freturn
      LocalVariableTable:
        Start  Length  Slot  Name   Signature
            0       9     0 $this   F
            0       9     1     x   J
    MethodParameters:
      Name                           Flags
      $this                          final
      x                              final

  public static float $minus$extension(float, int);
    descriptor: (FI)F
    flags: (0x0009) ACC_PUBLIC, ACC_STATIC
    Code:
      stack=3, locals=2, args_size=2
         0: getstatic     #20                 // Field org/scalactic/anyvals/PosFloat$.MODULE$:Lorg/scalactic/anyvals/PosFloat$;
         3: fload_0
         4: iload_1
         5: invokevirtual #137                // Method org/scalactic/anyvals/PosFloat$.$minus$extension:(FI)F
         8: freturn
      LocalVariableTable:
        Start  Length  Slot  Name   Signature
            0       9     0 $this   F
            0       9     1     x   I
    MethodParameters:
      Name                           Flags
      $this                          final
      x                              final

  public static float $minus$extension(float, char);
    descriptor: (FC)F
    flags: (0x0009) ACC_PUBLIC, ACC_STATIC
    Code:
      stack=3, locals=2, args_size=2
         0: getstatic     #20                 // Field org/scalactic/anyvals/PosFloat$.MODULE$:Lorg/scalactic/anyvals/PosFloat$;
         3: fload_0
         4: iload_1
         5: invokevirtual #139                // Method org/scalactic/anyvals/PosFloat$.$minus$extension:(FC)F
         8: freturn
      LocalVariableTable:
        Start  Length  Slot  Name   Signature
            0       9     0 $this   F
            0       9     1     x   C
    MethodParameters:
      Name                           Flags
      $this                          final
      x                              final

  public static float $minus$extension(float, short);
    descriptor: (FS)F
    flags: (0x0009) ACC_PUBLIC, ACC_STATIC
    Code:
      stack=3, locals=2, args_size=2
         0: getstatic     #20                 // Field org/scalactic/anyvals/PosFloat$.MODULE$:Lorg/scalactic/anyvals/PosFloat$;
         3: fload_0
         4: iload_1
         5: invokevirtual #141                // Method org/scalactic/anyvals/PosFloat$.$minus$extension:(FS)F
         8: freturn
      LocalVariableTable:
        Start  Length  Slot  Name   Signature
            0       9     0 $this   F
            0       9     1     x   S
    MethodParameters:
      Name                           Flags
      $this                          final
      x                              final

  public static float $minus$extension(float, byte);
    descriptor: (FB)F
    flags: (0x0009) ACC_PUBLIC, ACC_STATIC
    Code:
      stack=3, locals=2, args_size=2
         0: getstatic     #20                 // Field org/scalactic/anyvals/PosFloat$.MODULE$:Lorg/scalactic/anyvals/PosFloat$;
         3: fload_0
         4: iload_1
         5: invokevirtual #143                // Method org/scalactic/anyvals/PosFloat$.$minus$extension:(FB)F
         8: freturn
      LocalVariableTable:
        Start  Length  Slot  Name   Signature
            0       9     0 $this   F
            0       9     1     x   B
    MethodParameters:
      Name                           Flags
      $this                          final
      x                              final

  public static double $plus$extension(float, double);
    descriptor: (FD)D
    flags: (0x0009) ACC_PUBLIC, ACC_STATIC
    Code:
      stack=4, locals=3, args_size=2
         0: getstatic     #20                 // Field org/scalactic/anyvals/PosFloat$.MODULE$:Lorg/scalactic/anyvals/PosFloat$;
         3: fload_0
         4: dload_1
         5: invokevirtual #146                // Method org/scalactic/anyvals/PosFloat$.$plus$extension:(FD)D
         8: dreturn
      LocalVariableTable:
        Start  Length  Slot  Name   Signature
            0       9     0 $this   F
            0       9     1     x   D
    MethodParameters:
      Name                           Flags
      $this                          final
      x                              final

  public static float $plus$extension(float, float);
    descriptor: (FF)F
    flags: (0x0009) ACC_PUBLIC, ACC_STATIC
    Code:
      stack=3, locals=2, args_size=2
         0: getstatic     #20                 // Field org/scalactic/anyvals/PosFloat$.MODULE$:Lorg/scalactic/anyvals/PosFloat$;
         3: fload_0
         4: fload_1
         5: invokevirtual #148                // Method org/scalactic/anyvals/PosFloat$.$plus$extension:(FF)F
         8: freturn
      LocalVariableTable:
        Start  Length  Slot  Name   Signature
            0       9     0 $this   F
            0       9     1     x   F
    MethodParameters:
      Name                           Flags
      $this                          final
      x                              final

  public static float $plus$extension(float, long);
    descriptor: (FJ)F
    flags: (0x0009) ACC_PUBLIC, ACC_STATIC
    Code:
      stack=4, locals=3, args_size=2
         0: getstatic     #20                 // Field org/scalactic/anyvals/PosFloat$.MODULE$:Lorg/scalactic/anyvals/PosFloat$;
         3: fload_0
         4: lload_1
         5: invokevirtual #150                // Method org/scalactic/anyvals/PosFloat$.$plus$extension:(FJ)F
         8: freturn
      LocalVariableTable:
        Start  Length  Slot  Name   Signature
            0       9     0 $this   F
            0       9     1     x   J
    MethodParameters:
      Name                           Flags
      $this                          final
      x                              final

  public static float $plus$extension(float, int);
    descriptor: (FI)F
    flags: (0x0009) ACC_PUBLIC, ACC_STATIC
    Code:
      stack=3, locals=2, args_size=2
         0: getstatic     #20                 // Field org/scalactic/anyvals/PosFloat$.MODULE$:Lorg/scalactic/anyvals/PosFloat$;
         3: fload_0
         4: iload_1
         5: invokevirtual #152                // Method org/scalactic/anyvals/PosFloat$.$plus$extension:(FI)F
         8: freturn
      LocalVariableTable:
        Start  Length  Slot  Name   Signature
            0       9     0 $this   F
            0       9     1     x   I
    MethodParameters:
      Name                           Flags
      $this                          final
      x                              final

  public static float $plus$extension(float, char);
    descriptor: (FC)F
    flags: (0x0009) ACC_PUBLIC, ACC_STATIC
    Code:
      stack=3, locals=2, args_size=2
         0: getstatic     #20                 // Field org/scalactic/anyvals/PosFloat$.MODULE$:Lorg/scalactic/anyvals/PosFloat$;
         3: fload_0
         4: iload_1
         5: invokevirtual #154                // Method org/scalactic/anyvals/PosFloat$.$plus$extension:(FC)F
         8: freturn
      LocalVariableTable:
        Start  Length  Slot  Name   Signature
            0       9     0 $this   F
            0       9     1     x   C
    MethodParameters:
      Name                           Flags
      $this                          final
      x                              final

  public static float $plus$extension(float, short);
    descriptor: (FS)F
    flags: (0x0009) ACC_PUBLIC, ACC_STATIC
    Code:
      stack=3, locals=2, args_size=2
         0: getstatic     #20                 // Field org/scalactic/anyvals/PosFloat$.MODULE$:Lorg/scalactic/anyvals/PosFloat$;
         3: fload_0
         4: iload_1
         5: invokevirtual #156                // Method org/scalactic/anyvals/PosFloat$.$plus$extension:(FS)F
         8: freturn
      LocalVariableTable:
        Start  Length  Slot  Name   Signature
            0       9     0 $this   F
            0       9     1     x   S
    MethodParameters:
      Name                           Flags
      $this                          final
      x                              final

  public static float $plus$extension(float, byte);
    descriptor: (FB)F
    flags: (0x0009) ACC_PUBLIC, ACC_STATIC
    Code:
      stack=3, locals=2, args_size=2
         0: getstatic     #20                 // Field org/scalactic/anyvals/PosFloat$.MODULE$:Lorg/scalactic/anyvals/PosFloat$;
         3: fload_0
         4: iload_1
         5: invokevirtual #158                // Method org/scalactic/anyvals/PosFloat$.$plus$extension:(FB)F
         8: freturn
      LocalVariableTable:
        Start  Length  Slot  Name   Signature
            0       9     0 $this   F
            0       9     1     x   B
    MethodParameters:
      Name                           Flags
      $this                          final
      x                              final

  public static boolean $greater$eq$extension(float, double);
    descriptor: (FD)Z
    flags: (0x0009) ACC_PUBLIC, ACC_STATIC
    Code:
      stack=4, locals=3, args_size=2
         0: getstatic     #20                 // Field org/scalactic/anyvals/PosFloat$.MODULE$:Lorg/scalactic/anyvals/PosFloat$;
         3: fload_0
         4: dload_1
         5: invokevirtual #162                // Method org/scalactic/anyvals/PosFloat$.$greater$eq$extension:(FD)Z
         8: ireturn
      LocalVariableTable:
        Start  Length  Slot  Name   Signature
            0       9     0 $this   F
            0       9     1     x   D
    MethodParameters:
      Name                           Flags
      $this                          final
      x                              final

  public static boolean $greater$eq$extension(float, float);
    descriptor: (FF)Z
    flags: (0x0009) ACC_PUBLIC, ACC_STATIC
    Code:
      stack=3, locals=2, args_size=2
         0: getstatic     #20                 // Field org/scalactic/anyvals/PosFloat$.MODULE$:Lorg/scalactic/anyvals/PosFloat$;
         3: fload_0
         4: fload_1
         5: invokevirtual #165                // Method org/scalactic/anyvals/PosFloat$.$greater$eq$extension:(FF)Z
         8: ireturn
      LocalVariableTable:
        Start  Length  Slot  Name   Signature
            0       9     0 $this   F
            0       9     1     x   F
    MethodParameters:
      Name                           Flags
      $this                          final
      x                              final

  public static boolean $greater$eq$extension(float, long);
    descriptor: (FJ)Z
    flags: (0x0009) ACC_PUBLIC, ACC_STATIC
    Code:
      stack=4, locals=3, args_size=2
         0: getstatic     #20                 // Field org/scalactic/anyvals/PosFloat$.MODULE$:Lorg/scalactic/anyvals/PosFloat$;
         3: fload_0
         4: lload_1
         5: invokevirtual #168                // Method org/scalactic/anyvals/PosFloat$.$greater$eq$extension:(FJ)Z
         8: ireturn
      LocalVariableTable:
        Start  Length  Slot  Name   Signature
            0       9     0 $this   F
            0       9     1     x   J
    MethodParameters:
      Name                           Flags
      $this                          final
      x                              final

  public static boolean $greater$eq$extension(float, int);
    descriptor: (FI)Z
    flags: (0x0009) ACC_PUBLIC, ACC_STATIC
    Code:
      stack=3, locals=2, args_size=2
         0: getstatic     #20                 // Field org/scalactic/anyvals/PosFloat$.MODULE$:Lorg/scalactic/anyvals/PosFloat$;
         3: fload_0
         4: iload_1
         5: invokevirtual #171                // Method org/scalactic/anyvals/PosFloat$.$greater$eq$extension:(FI)Z
         8: ireturn
      LocalVariableTable:
        Start  Length  Slot  Name   Signature
            0       9     0 $this   F
            0       9     1     x   I
    MethodParameters:
      Name                           Flags
      $this                          final
      x                              final

  public static boolean $greater$eq$extension(float, char);
    descriptor: (FC)Z
    flags: (0x0009) ACC_PUBLIC, ACC_STATIC
    Code:
      stack=3, locals=2, args_size=2
         0: getstatic     #20                 // Field org/scalactic/anyvals/PosFloat$.MODULE$:Lorg/scalactic/anyvals/PosFloat$;
         3: fload_0
         4: iload_1
         5: invokevirtual #174                // Method org/scalactic/anyvals/PosFloat$.$greater$eq$extension:(FC)Z
         8: ireturn
      LocalVariableTable:
        Start  Length  Slot  Name   Signature
            0       9     0 $this   F
            0       9     1     x   C
    MethodParameters:
      Name                           Flags
      $this                          final
      x                              final

  public static boolean $greater$eq$extension(float, short);
    descriptor: (FS)Z
    flags: (0x0009) ACC_PUBLIC, ACC_STATIC
    Code:
      stack=3, locals=2, args_size=2
         0: getstatic     #20                 // Field org/scalactic/anyvals/PosFloat$.MODULE$:Lorg/scalactic/anyvals/PosFloat$;
         3: fload_0
         4: iload_1
         5: invokevirtual #177                // Method org/scalactic/anyvals/PosFloat$.$greater$eq$extension:(FS)Z
         8: ireturn
      LocalVariableTable:
        Start  Length  Slot  Name   Signature
            0       9     0 $this   F
            0       9     1     x   S
    MethodParameters:
      Name                           Flags
      $this                          final
      x                              final

  public static boolean $greater$eq$extension(float, byte);
    descriptor: (FB)Z
    flags: (0x0009) ACC_PUBLIC, ACC_STATIC
    Code:
      stack=3, locals=2, args_size=2
         0: getstatic     #20                 // Field org/scalactic/anyvals/PosFloat$.MODULE$:Lorg/scalactic/anyvals/PosFloat$;
         3: fload_0
         4: iload_1
         5: invokevirtual #180                // Method org/scalactic/anyvals/PosFloat$.$greater$eq$extension:(FB)Z
         8: ireturn
      LocalVariableTable:
        Start  Length  Slot  Name   Signature
            0       9     0 $this   F
            0       9     1     x   B
    MethodParameters:
      Name                           Flags
      $this                          final
      x                              final

  public static boolean $greater$extension(float, double);
    descriptor: (FD)Z
    flags: (0x0009) ACC_PUBLIC, ACC_STATIC
    Code:
      stack=4, locals=3, args_size=2
         0: getstatic     #20                 // Field org/scalactic/anyvals/PosFloat$.MODULE$:Lorg/scalactic/anyvals/PosFloat$;
         3: fload_0
         4: dload_1
         5: invokevirtual #183                // Method org/scalactic/anyvals/PosFloat$.$greater$extension:(FD)Z
         8: ireturn
      LocalVariableTable:
        Start  Length  Slot  Name   Signature
            0       9     0 $this   F
            0       9     1     x   D
    MethodParameters:
      Name                           Flags
      $this                          final
      x                              final

  public static boolean $greater$extension(float, float);
    descriptor: (FF)Z
    flags: (0x0009) ACC_PUBLIC, ACC_STATIC
    Code:
      stack=3, locals=2, args_size=2
         0: getstatic     #20                 // Field org/scalactic/anyvals/PosFloat$.MODULE$:Lorg/scalactic/anyvals/PosFloat$;
         3: fload_0
         4: fload_1
         5: invokevirtual #185                // Method org/scalactic/anyvals/PosFloat$.$greater$extension:(FF)Z
         8: ireturn
      LocalVariableTable:
        Start  Length  Slot  Name   Signature
            0       9     0 $this   F
            0       9     1     x   F
    MethodParameters:
      Name                           Flags
      $this                          final
      x                              final

  public static boolean $greater$extension(float, long);
    descriptor: (FJ)Z
    flags: (0x0009) ACC_PUBLIC, ACC_STATIC
    Code:
      stack=4, locals=3, args_size=2
         0: getstatic     #20                 // Field org/scalactic/anyvals/PosFloat$.MODULE$:Lorg/scalactic/anyvals/PosFloat$;
         3: fload_0
         4: lload_1
         5: invokevirtual #187                // Method org/scalactic/anyvals/PosFloat$.$greater$extension:(FJ)Z
         8: ireturn
      LocalVariableTable:
        Start  Length  Slot  Name   Signature
            0       9     0 $this   F
            0       9     1     x   J
    MethodParameters:
      Name                           Flags
      $this                          final
      x                              final

  public static boolean $greater$extension(float, int);
    descriptor: (FI)Z
    flags: (0x0009) ACC_PUBLIC, ACC_STATIC
    Code:
      stack=3, locals=2, args_size=2
         0: getstatic     #20                 // Field org/scalactic/anyvals/PosFloat$.MODULE$:Lorg/scalactic/anyvals/PosFloat$;
         3: fload_0
         4: iload_1
         5: invokevirtual #189                // Method org/scalactic/anyvals/PosFloat$.$greater$extension:(FI)Z
         8: ireturn
      LocalVariableTable:
        Start  Length  Slot  Name   Signature
            0       9     0 $this   F
            0       9     1     x   I
    MethodParameters:
      Name                           Flags
      $this                          final
      x                              final

  public static boolean $greater$extension(float, char);
    descriptor: (FC)Z
    flags: (0x0009) ACC_PUBLIC, ACC_STATIC
    Code:
      stack=3, locals=2, args_size=2
         0: getstatic     #20                 // Field org/scalactic/anyvals/PosFloat$.MODULE$:Lorg/scalactic/anyvals/PosFloat$;
         3: fload_0
         4: iload_1
         5: invokevirtual #191                // Method org/scalactic/anyvals/PosFloat$.$greater$extension:(FC)Z
         8: ireturn
      LocalVariableTable:
        Start  Length  Slot  Name   Signature
            0       9     0 $this   F
            0       9     1     x   C
    MethodParameters:
      Name                           Flags
      $this                          final
      x                              final

  public static boolean $greater$extension(float, short);
    descriptor: (FS)Z
    flags: (0x0009) ACC_PUBLIC, ACC_STATIC
    Code:
      stack=3, locals=2, args_size=2
         0: getstatic     #20                 // Field org/scalactic/anyvals/PosFloat$.MODULE$:Lorg/scalactic/anyvals/PosFloat$;
         3: fload_0
         4: iload_1
         5: invokevirtual #193                // Method org/scalactic/anyvals/PosFloat$.$greater$extension:(FS)Z
         8: ireturn
      LocalVariableTable:
        Start  Length  Slot  Name   Signature
            0       9     0 $this   F
            0       9     1     x   S
    MethodParameters:
      Name                           Flags
      $this                          final
      x                              final

  public static boolean $greater$extension(float, byte);
    descriptor: (FB)Z
    flags: (0x0009) ACC_PUBLIC, ACC_STATIC
    Code:
      stack=3, locals=2, args_size=2
         0: getstatic     #20                 // Field org/scalactic/anyvals/PosFloat$.MODULE$:Lorg/scalactic/anyvals/PosFloat$;
         3: fload_0
         4: iload_1
         5: invokevirtual #195                // Method org/scalactic/anyvals/PosFloat$.$greater$extension:(FB)Z
         8: ireturn
      LocalVariableTable:
        Start  Length  Slot  Name   Signature
            0       9     0 $this   F
            0       9     1     x   B
    MethodParameters:
      Name                           Flags
      $this                          final
      x                              final

  public static boolean $less$eq$extension(float, double);
    descriptor: (FD)Z
    flags: (0x0009) ACC_PUBLIC, ACC_STATIC
    Code:
      stack=4, locals=3, args_size=2
         0: getstatic     #20                 // Field org/scalactic/anyvals/PosFloat$.MODULE$:Lorg/scalactic/anyvals/PosFloat$;
         3: fload_0
         4: dload_1
         5: invokevirtual #198                // Method org/scalactic/anyvals/PosFloat$.$less$eq$extension:(FD)Z
         8: ireturn
      LocalVariableTable:
        Start  Length  Slot  Name   Signature
            0       9     0 $this   F
            0       9     1     x   D
    MethodParameters:
      Name                           Flags
      $this                          final
      x                              final

  public static boolean $less$eq$extension(float, float);
    descriptor: (FF)Z
    flags: (0x0009) ACC_PUBLIC, ACC_STATIC
    Code:
      stack=3, locals=2, args_size=2
         0: getstatic     #20                 // Field org/scalactic/anyvals/PosFloat$.MODULE$:Lorg/scalactic/anyvals/PosFloat$;
         3: fload_0
         4: fload_1
         5: invokevirtual #200                // Method org/scalactic/anyvals/PosFloat$.$less$eq$extension:(FF)Z
         8: ireturn
      LocalVariableTable:
        Start  Length  Slot  Name   Signature
            0       9     0 $this   F
            0       9     1     x   F
    MethodParameters:
      Name                           Flags
      $this                          final
      x                              final

  public static boolean $less$eq$extension(float, long);
    descriptor: (FJ)Z
    flags: (0x0009) ACC_PUBLIC, ACC_STATIC
    Code:
      stack=4, locals=3, args_size=2
         0: getstatic     #20                 // Field org/scalactic/anyvals/PosFloat$.MODULE$:Lorg/scalactic/anyvals/PosFloat$;
         3: fload_0
         4: lload_1
         5: invokevirtual #202                // Method org/scalactic/anyvals/PosFloat$.$less$eq$extension:(FJ)Z
         8: ireturn
      LocalVariableTable:
        Start  Length  Slot  Name   Signature
            0       9     0 $this   F
            0       9     1     x   J
    MethodParameters:
      Name                           Flags
      $this                          final
      x                              final

  public static boolean $less$eq$extension(float, int);
    descriptor: (FI)Z
    flags: (0x0009) ACC_PUBLIC, ACC_STATIC
    Code:
      stack=3, locals=2, args_size=2
         0: getstatic     #20                 // Field org/scalactic/anyvals/PosFloat$.MODULE$:Lorg/scalactic/anyvals/PosFloat$;
         3: fload_0
         4: iload_1
         5: invokevirtual #204                // Method org/scalactic/anyvals/PosFloat$.$less$eq$extension:(FI)Z
         8: ireturn
      LocalVariableTable:
        Start  Length  Slot  Name   Signature
            0       9     0 $this   F
            0       9     1     x   I
    MethodParameters:
      Name                           Flags
      $this                          final
      x                              final

  public static boolean $less$eq$extension(float, char);
    descriptor: (FC)Z
    flags: (0x0009) ACC_PUBLIC, ACC_STATIC
    Code:
      stack=3, locals=2, args_size=2
         0: getstatic     #20                 // Field org/scalactic/anyvals/PosFloat$.MODULE$:Lorg/scalactic/anyvals/PosFloat$;
         3: fload_0
         4: iload_1
         5: invokevirtual #206                // Method org/scalactic/anyvals/PosFloat$.$less$eq$extension:(FC)Z
         8: ireturn
      LocalVariableTable:
        Start  Length  Slot  Name   Signature
            0       9     0 $this   F
            0       9     1     x   C
    MethodParameters:
      Name                           Flags
      $this                          final
      x                              final

  public static boolean $less$eq$extension(float, short);
    descriptor: (FS)Z
    flags: (0x0009) ACC_PUBLIC, ACC_STATIC
    Code:
      stack=3, locals=2, args_size=2
         0: getstatic     #20                 // Field org/scalactic/anyvals/PosFloat$.MODULE$:Lorg/scalactic/anyvals/PosFloat$;
         3: fload_0
         4: iload_1
         5: invokevirtual #208                // Method org/scalactic/anyvals/PosFloat$.$less$eq$extension:(FS)Z
         8: ireturn
      LocalVariableTable:
        Start  Length  Slot  Name   Signature
            0       9     0 $this   F
            0       9     1     x   S
    MethodParameters:
      Name                           Flags
      $this                          final
      x                              final

  public static boolean $less$eq$extension(float, byte);
    descriptor: (FB)Z
    flags: (0x0009) ACC_PUBLIC, ACC_STATIC
    Code:
      stack=3, locals=2, args_size=2
         0: getstatic     #20                 // Field org/scalactic/anyvals/PosFloat$.MODULE$:Lorg/scalactic/anyvals/PosFloat$;
         3: fload_0
         4: iload_1
         5: invokevirtual #210                // Method org/scalactic/anyvals/PosFloat$.$less$eq$extension:(FB)Z
         8: ireturn
      LocalVariableTable:
        Start  Length  Slot  Name   Signature
            0       9     0 $this   F
            0       9     1     x   B
    MethodParameters:
      Name                           Flags
      $this                          final
      x                              final

  public static boolean $less$extension(float, double);
    descriptor: (FD)Z
    flags: (0x0009) ACC_PUBLIC, ACC_STATIC
    Code:
      stack=4, locals=3, args_size=2
         0: getstatic     #20                 // Field org/scalactic/anyvals/PosFloat$.MODULE$:Lorg/scalactic/anyvals/PosFloat$;
         3: fload_0
         4: dload_1
         5: invokevirtual #213                // Method org/scalactic/anyvals/PosFloat$.$less$extension:(FD)Z
         8: ireturn
      LocalVariableTable:
        Start  Length  Slot  Name   Signature
            0       9     0 $this   F
            0       9     1     x   D
    MethodParameters:
      Name                           Flags
      $this                          final
      x                              final

  public static boolean $less$extension(float, float);
    descriptor: (FF)Z
    flags: (0x0009) ACC_PUBLIC, ACC_STATIC
    Code:
      stack=3, locals=2, args_size=2
         0: getstatic     #20                 // Field org/scalactic/anyvals/PosFloat$.MODULE$:Lorg/scalactic/anyvals/PosFloat$;
         3: fload_0
         4: fload_1
         5: invokevirtual #215                // Method org/scalactic/anyvals/PosFloat$.$less$extension:(FF)Z
         8: ireturn
      LocalVariableTable:
        Start  Length  Slot  Name   Signature
            0       9     0 $this   F
            0       9     1     x   F
    MethodParameters:
      Name                           Flags
      $this                          final
      x                              final

  public static boolean $less$extension(float, long);
    descriptor: (FJ)Z
    flags: (0x0009) ACC_PUBLIC, ACC_STATIC
    Code:
      stack=4, locals=3, args_size=2
         0: getstatic     #20                 // Field org/scalactic/anyvals/PosFloat$.MODULE$:Lorg/scalactic/anyvals/PosFloat$;
         3: fload_0
         4: lload_1
         5: invokevirtual #217                // Method org/scalactic/anyvals/PosFloat$.$less$extension:(FJ)Z
         8: ireturn
      LocalVariableTable:
        Start  Length  Slot  Name   Signature
            0       9     0 $this   F
            0       9     1     x   J
    MethodParameters:
      Name                           Flags
      $this                          final
      x                              final

  public static boolean $less$extension(float, int);
    descriptor: (FI)Z
    flags: (0x0009) ACC_PUBLIC, ACC_STATIC
    Code:
      stack=3, locals=2, args_size=2
         0: getstatic     #20                 // Field org/scalactic/anyvals/PosFloat$.MODULE$:Lorg/scalactic/anyvals/PosFloat$;
         3: fload_0
         4: iload_1
         5: invokevirtual #219                // Method org/scalactic/anyvals/PosFloat$.$less$extension:(FI)Z
         8: ireturn
      LocalVariableTable:
        Start  Length  Slot  Name   Signature
            0       9     0 $this   F
            0       9     1     x   I
    MethodParameters:
      Name                           Flags
      $this                          final
      x                              final

  public static boolean $less$extension(float, char);
    descriptor: (FC)Z
    flags: (0x0009) ACC_PUBLIC, ACC_STATIC
    Code:
      stack=3, locals=2, args_size=2
         0: getstatic     #20                 // Field org/scalactic/anyvals/PosFloat$.MODULE$:Lorg/scalactic/anyvals/PosFloat$;
         3: fload_0
         4: iload_1
         5: invokevirtual #221                // Method org/scalactic/anyvals/PosFloat$.$less$extension:(FC)Z
         8: ireturn
      LocalVariableTable:
        Start  Length  Slot  Name   Signature
            0       9     0 $this   F
            0       9     1     x   C
    MethodParameters:
      Name                           Flags
      $this                          final
      x                              final

  public static boolean $less$extension(float, short);
    descriptor: (FS)Z
    flags: (0x0009) ACC_PUBLIC, ACC_STATIC
    Code:
      stack=3, locals=2, args_size=2
         0: getstatic     #20                 // Field org/scalactic/anyvals/PosFloat$.MODULE$:Lorg/scalactic/anyvals/PosFloat$;
         3: fload_0
         4: iload_1
         5: invokevirtual #223                // Method org/scalactic/anyvals/PosFloat$.$less$extension:(FS)Z
         8: ireturn
      LocalVariableTable:
        Start  Length  Slot  Name   Signature
            0       9     0 $this   F
            0       9     1     x   S
    MethodParameters:
      Name                           Flags
      $this                          final
      x                              final

  public static boolean $less$extension(float, byte);
    descriptor: (FB)Z
    flags: (0x0009) ACC_PUBLIC, ACC_STATIC
    Code:
      stack=3, locals=2, args_size=2
         0: getstatic     #20                 // Field org/scalactic/anyvals/PosFloat$.MODULE$:Lorg/scalactic/anyvals/PosFloat$;
         3: fload_0
         4: iload_1
         5: invokevirtual #225                // Method org/scalactic/anyvals/PosFloat$.$less$extension:(FB)Z
         8: ireturn
      LocalVariableTable:
        Start  Length  Slot  Name   Signature
            0       9     0 $this   F
            0       9     1     x   B
    MethodParameters:
      Name                           Flags
      $this                          final
      x                              final

  public static java.lang.String $plus$extension(float, java.lang.String);
    descriptor: (FLjava/lang/String;)Ljava/lang/String;
    flags: (0x0009) ACC_PUBLIC, ACC_STATIC
    Code:
      stack=3, locals=2, args_size=2
         0: getstatic     #20                 // Field org/scalactic/anyvals/PosFloat$.MODULE$:Lorg/scalactic/anyvals/PosFloat$;
         3: fload_0
         4: aload_1
         5: invokevirtual #228                // Method org/scalactic/anyvals/PosFloat$.$plus$extension:(FLjava/lang/String;)Ljava/lang/String;
         8: areturn
      LocalVariableTable:
        Start  Length  Slot  Name   Signature
            0       9     0 $this   F
            0       9     1     x   Ljava/lang/String;
    MethodParameters:
      Name                           Flags
      $this                          final
      x                              final

  public static float unary_$minus$extension(float);
    descriptor: (F)F
    flags: (0x0009) ACC_PUBLIC, ACC_STATIC
    Code:
      stack=2, locals=1, args_size=1
         0: getstatic     #20                 // Field org/scalactic/anyvals/PosFloat$.MODULE$:Lorg/scalactic/anyvals/PosFloat$;
         3: fload_0
         4: invokevirtual #232                // Method org/scalactic/anyvals/PosFloat$.unary_$minus$extension:(F)F
         7: freturn
      LocalVariableTable:
        Start  Length  Slot  Name   Signature
            0       8     0 $this   F
    MethodParameters:
      Name                           Flags
      $this                          final

  public static float unary_$plus$extension(float);
    descriptor: (F)F
    flags: (0x0009) ACC_PUBLIC, ACC_STATIC
    Code:
      stack=2, locals=1, args_size=1
         0: getstatic     #20                 // Field org/scalactic/anyvals/PosFloat$.MODULE$:Lorg/scalactic/anyvals/PosFloat$;
         3: fload_0
         4: invokevirtual #235                // Method org/scalactic/anyvals/PosFloat$.unary_$plus$extension:(F)F
         7: freturn
      LocalVariableTable:
        Start  Length  Slot  Name   Signature
            0       8     0 $this   F
    MethodParameters:
      Name                           Flags
      $this                          final

  public static double toDouble$extension(float);
    descriptor: (F)D
    flags: (0x0009) ACC_PUBLIC, ACC_STATIC
    Code:
      stack=2, locals=1, args_size=1
         0: getstatic     #20                 // Field org/scalactic/anyvals/PosFloat$.MODULE$:Lorg/scalactic/anyvals/PosFloat$;
         3: fload_0
         4: invokevirtual #239                // Method org/scalactic/anyvals/PosFloat$.toDouble$extension:(F)D
         7: dreturn
      LocalVariableTable:
        Start  Length  Slot  Name   Signature
            0       8     0 $this   F
    MethodParameters:
      Name                           Flags
      $this                          final

  public static float toFloat$extension(float);
    descriptor: (F)F
    flags: (0x0009) ACC_PUBLIC, ACC_STATIC
    Code:
      stack=2, locals=1, args_size=1
         0: getstatic     #20                 // Field org/scalactic/anyvals/PosFloat$.MODULE$:Lorg/scalactic/anyvals/PosFloat$;
         3: fload_0
         4: invokevirtual #242                // Method org/scalactic/anyvals/PosFloat$.toFloat$extension:(F)F
         7: freturn
      LocalVariableTable:
        Start  Length  Slot  Name   Signature
            0       8     0 $this   F
    MethodParameters:
      Name                           Flags
      $this                          final

  public static long toLong$extension(float);
    descriptor: (F)J
    flags: (0x0009) ACC_PUBLIC, ACC_STATIC
    Code:
      stack=2, locals=1, args_size=1
         0: getstatic     #20                 // Field org/scalactic/anyvals/PosFloat$.MODULE$:Lorg/scalactic/anyvals/PosFloat$;
         3: fload_0
         4: invokevirtual #246                // Method org/scalactic/anyvals/PosFloat$.toLong$extension:(F)J
         7: lreturn
      LocalVariableTable:
        Start  Length  Slot  Name   Signature
            0       8     0 $this   F
    MethodParameters:
      Name                           Flags
      $this                          final

  public static int toInt$extension(float);
    descriptor: (F)I
    flags: (0x0009) ACC_PUBLIC, ACC_STATIC
    Code:
      stack=2, locals=1, args_size=1
         0: getstatic     #20                 // Field org/scalactic/anyvals/PosFloat$.MODULE$:Lorg/scalactic/anyvals/PosFloat$;
         3: fload_0
         4: invokevirtual #249                // Method org/scalactic/anyvals/PosFloat$.toInt$extension:(F)I
         7: ireturn
      LocalVariableTable:
        Start  Length  Slot  Name   Signature
            0       8     0 $this   F
    MethodParameters:
      Name                           Flags
      $this                          final

  public static char toChar$extension(float);
    descriptor: (F)C
    flags: (0x0009) ACC_PUBLIC, ACC_STATIC
    Code:
      stack=2, locals=1, args_size=1
         0: getstatic     #20                 // Field org/scalactic/anyvals/PosFloat$.MODULE$:Lorg/scalactic/anyvals/PosFloat$;
         3: fload_0
         4: invokevirtual #253                // Method org/scalactic/anyvals/PosFloat$.toChar$extension:(F)C
         7: ireturn
      LocalVariableTable:
        Start  Length  Slot  Name   Signature
            0       8     0 $this   F
    MethodParameters:
      Name                           Flags
      $this                          final

  public static short toShort$extension(float);
    descriptor: (F)S
    flags: (0x0009) ACC_PUBLIC, ACC_STATIC
    Code:
      stack=2, locals=1, args_size=1
         0: getstatic     #20                 // Field org/scalactic/anyvals/PosFloat$.MODULE$:Lorg/scalactic/anyvals/PosFloat$;
         3: fload_0
         4: invokevirtual #257                // Method org/scalactic/anyvals/PosFloat$.toShort$extension:(F)S
         7: ireturn
      LocalVariableTable:
        Start  Length  Slot  Name   Signature
            0       8     0 $this   F
    MethodParameters:
      Name                           Flags
      $this                          final

  public static byte toByte$extension(float);
    descriptor: (F)B
    flags: (0x0009) ACC_PUBLIC, ACC_STATIC
    Code:
      stack=2, locals=1, args_size=1
         0: getstatic     #20                 // Field org/scalactic/anyvals/PosFloat$.MODULE$:Lorg/scalactic/anyvals/PosFloat$;
         3: fload_0
         4: invokevirtual #261                // Method org/scalactic/anyvals/PosFloat$.toByte$extension:(F)B
         7: ireturn
      LocalVariableTable:
        Start  Length  Slot  Name   Signature
            0       8     0 $this   F
    MethodParameters:
      Name                           Flags
      $this                          final

  public static java.lang.String toString$extension(float);
    descriptor: (F)Ljava/lang/String;
    flags: (0x0009) ACC_PUBLIC, ACC_STATIC
    Code:
      stack=2, locals=1, args_size=1
         0: getstatic     #20                 // Field org/scalactic/anyvals/PosFloat$.MODULE$:Lorg/scalactic/anyvals/PosFloat$;
         3: fload_0
         4: invokevirtual #265                // Method org/scalactic/anyvals/PosFloat$.toString$extension:(F)Ljava/lang/String;
         7: areturn
      LocalVariableTable:
        Start  Length  Slot  Name   Signature
            0       8     0 $this   F
    MethodParameters:
      Name                           Flags
      $this                          final

  public static scala.math.Ordering<org.scalactic.anyvals.PosFloat> posFloatOrd();
    descriptor: ()Lscala/math/Ordering;
    flags: (0x0009) ACC_PUBLIC, ACC_STATIC
    Code:
      stack=1, locals=0, args_size=0
         0: getstatic     #20                 // Field org/scalactic/anyvals/PosFloat$.MODULE$:Lorg/scalactic/anyvals/PosFloat$;
         3: invokevirtual #270                // Method org/scalactic/anyvals/PosFloat$.posFloatOrd:()Lscala/math/Ordering;
         6: areturn
    Signature: #268                         // ()Lscala/math/Ordering<Lorg/scalactic/anyvals/PosFloat;>;
    Deprecated: true

  public static float MinPositiveValue();
    descriptor: ()F
    flags: (0x0009) ACC_PUBLIC, ACC_STATIC
    Code:
      stack=1, locals=0, args_size=0
         0: getstatic     #20                 // Field org/scalactic/anyvals/PosFloat$.MODULE$:Lorg/scalactic/anyvals/PosFloat$;
         3: invokevirtual #274                // Method org/scalactic/anyvals/PosFloat$.MinPositiveValue:()F
         6: freturn

  public static float PositiveInfinity();
    descriptor: ()F
    flags: (0x0009) ACC_PUBLIC, ACC_STATIC
    Code:
      stack=1, locals=0, args_size=0
         0: getstatic     #20                 // Field org/scalactic/anyvals/PosFloat$.MODULE$:Lorg/scalactic/anyvals/PosFloat$;
         3: invokevirtual #277                // Method org/scalactic/anyvals/PosFloat$.PositiveInfinity:()F
         6: freturn

  public static scala.math.Ordering<org.scalactic.anyvals.PosFloat> ordering();
    descriptor: ()Lscala/math/Ordering;
    flags: (0x0009) ACC_PUBLIC, ACC_STATIC
    Code:
      stack=1, locals=0, args_size=0
         0: getstatic     #20                 // Field org/scalactic/anyvals/PosFloat$.MODULE$:Lorg/scalactic/anyvals/PosFloat$;
         3: invokevirtual #280                // Method org/scalactic/anyvals/PosFloat$.ordering:()Lscala/math/Ordering;
         6: areturn
    Signature: #268                         // ()Lscala/math/Ordering<Lorg/scalactic/anyvals/PosFloat;>;

  public static double widenToNonZeroDouble(float);
    descriptor: (F)D
    flags: (0x0009) ACC_PUBLIC, ACC_STATIC
    Code:
      stack=2, locals=1, args_size=1
         0: getstatic     #20                 // Field org/scalactic/anyvals/PosFloat$.MODULE$:Lorg/scalactic/anyvals/PosFloat$;
         3: fload_0
         4: invokevirtual #284                // Method org/scalactic/anyvals/PosFloat$.widenToNonZeroDouble:(F)D
         7: dreturn
      LocalVariableTable:
        Start  Length  Slot  Name   Signature
            0       8     0   pos   F
    MethodParameters:
      Name                           Flags
      pos                            final

  public static float widenToNonZeroFloat(float);
    descriptor: (F)F
    flags: (0x0009) ACC_PUBLIC, ACC_STATIC
    Code:
      stack=2, locals=1, args_size=1
         0: getstatic     #20                 // Field org/scalactic/anyvals/PosFloat$.MODULE$:Lorg/scalactic/anyvals/PosFloat$;
         3: fload_0
         4: invokevirtual #287                // Method org/scalactic/anyvals/PosFloat$.widenToNonZeroFloat:(F)F
         7: freturn
      LocalVariableTable:
        Start  Length  Slot  Name   Signature
            0       8     0   pos   F
    MethodParameters:
      Name                           Flags
      pos                            final

  public static double widenToPosZDouble(float);
    descriptor: (F)D
    flags: (0x0009) ACC_PUBLIC, ACC_STATIC
    Code:
      stack=2, locals=1, args_size=1
         0: getstatic     #20                 // Field org/scalactic/anyvals/PosFloat$.MODULE$:Lorg/scalactic/anyvals/PosFloat$;
         3: fload_0
         4: invokevirtual #290                // Method org/scalactic/anyvals/PosFloat$.widenToPosZDouble:(F)D
         7: dreturn
      LocalVariableTable:
        Start  Length  Slot  Name   Signature
            0       8     0   pos   F
    MethodParameters:
      Name                           Flags
      pos                            final

  public static float widenToPosZFloat(float);
    descriptor: (F)F
    flags: (0x0009) ACC_PUBLIC, ACC_STATIC
    Code:
      stack=2, locals=1, args_size=1
         0: getstatic     #20                 // Field org/scalactic/anyvals/PosFloat$.MODULE$:Lorg/scalactic/anyvals/PosFloat$;
         3: fload_0
         4: invokevirtual #293                // Method org/scalactic/anyvals/PosFloat$.widenToPosZFloat:(F)F
         7: freturn
      LocalVariableTable:
        Start  Length  Slot  Name   Signature
            0       8     0   pos   F
    MethodParameters:
      Name                           Flags
      pos                            final

  public static double widenToPosDouble(float);
    descriptor: (F)D
    flags: (0x0009) ACC_PUBLIC, ACC_STATIC
    Code:
      stack=2, locals=1, args_size=1
         0: getstatic     #20                 // Field org/scalactic/anyvals/PosFloat$.MODULE$:Lorg/scalactic/anyvals/PosFloat$;
         3: fload_0
         4: invokevirtual #296                // Method org/scalactic/anyvals/PosFloat$.widenToPosDouble:(F)D
         7: dreturn
      LocalVariableTable:
        Start  Length  Slot  Name   Signature
            0       8     0   pos   F
    MethodParameters:
      Name                           Flags
      pos                            final

  public static double widenToDouble(float);
    descriptor: (F)D
    flags: (0x0009) ACC_PUBLIC, ACC_STATIC
    Code:
      stack=2, locals=1, args_size=1
         0: getstatic     #20                 // Field org/scalactic/anyvals/PosFloat$.MODULE$:Lorg/scalactic/anyvals/PosFloat$;
         3: fload_0
         4: invokevirtual #299                // Method org/scalactic/anyvals/PosFloat$.widenToDouble:(F)D
         7: dreturn
      LocalVariableTable:
        Start  Length  Slot  Name   Signature
            0       8     0   pos   F
    MethodParameters:
      Name                           Flags
      pos                            final

  public static float widenToFloat(float);
    descriptor: (F)F
    flags: (0x0009) ACC_PUBLIC, ACC_STATIC
    Code:
      stack=2, locals=1, args_size=1
         0: getstatic     #20                 // Field org/scalactic/anyvals/PosFloat$.MODULE$:Lorg/scalactic/anyvals/PosFloat$;
         3: fload_0
         4: invokevirtual #302                // Method org/scalactic/anyvals/PosFloat$.widenToFloat:(F)F
         7: freturn
      LocalVariableTable:
        Start  Length  Slot  Name   Signature
            0       8     0   pos   F
    MethodParameters:
      Name                           Flags
      pos                            final

  public static float fromOrElse(float, scala.Function0);
    descriptor: (FLscala/Function0;)F
    flags: (0x0009) ACC_PUBLIC, ACC_STATIC
    Code:
      stack=3, locals=2, args_size=2
         0: getstatic     #20                 // Field org/scalactic/anyvals/PosFloat$.MODULE$:Lorg/scalactic/anyvals/PosFloat$;
         3: fload_0
         4: aload_1
         5: invokevirtual #307                // Method org/scalactic/anyvals/PosFloat$.fromOrElse:(FLscala/Function0;)F
         8: freturn
      LocalVariableTable:
        Start  Length  Slot  Name   Signature
            0       9     0 value   F
            0       9     1 default   Lscala/Function0;
    MethodParameters:
      Name                           Flags
      value                          final
      default                        final

  public static boolean isValid(float);
    descriptor: (F)Z
    flags: (0x0009) ACC_PUBLIC, ACC_STATIC
    Code:
      stack=2, locals=1, args_size=1
         0: getstatic     #20                 // Field org/scalactic/anyvals/PosFloat$.MODULE$:Lorg/scalactic/anyvals/PosFloat$;
         3: fload_0
         4: invokevirtual #311                // Method org/scalactic/anyvals/PosFloat$.isValid:(F)Z
         7: ireturn
      LocalVariableTable:
        Start  Length  Slot  Name   Signature
            0       8     0 value   F
    MethodParameters:
      Name                           Flags
      value                          final

  public static <L extends java.lang.Object> scala.util.Either<L, org.scalactic.anyvals.PosFloat> rightOrElse(float, scala.Function1<java.lang.Object, L>);
    descriptor: (FLscala/Function1;)Lscala/util/Either;
    flags: (0x0009) ACC_PUBLIC, ACC_STATIC
    Code:
      stack=3, locals=2, args_size=2
         0: getstatic     #20                 // Field org/scalactic/anyvals/PosFloat$.MODULE$:Lorg/scalactic/anyvals/PosFloat$;
         3: fload_0
         4: aload_1
         5: invokevirtual #316                // Method org/scalactic/anyvals/PosFloat$.rightOrElse:(FLscala/Function1;)Lscala/util/Either;
         8: areturn
      LocalVariableTable:
        Start  Length  Slot  Name   Signature
            0       9     0 value   F
            0       9     1     f   Lscala/Function1;
    Signature: #314                         // <L:Ljava/lang/Object;>(FLscala/Function1<Ljava/lang/Object;TL;>;)Lscala/util/Either<TL;Lorg/scalactic/anyvals/PosFloat;>;
    MethodParameters:
      Name                           Flags
      value                          final
      f                              final

  public static <B extends java.lang.Object> org.scalactic.Or<org.scalactic.anyvals.PosFloat, B> goodOrElse(float, scala.Function1<java.lang.Object, B>);
    descriptor: (FLscala/Function1;)Lorg/scalactic/Or;
    flags: (0x0009) ACC_PUBLIC, ACC_STATIC
    Code:
      stack=3, locals=2, args_size=2
         0: getstatic     #20                 // Field org/scalactic/anyvals/PosFloat$.MODULE$:Lorg/scalactic/anyvals/PosFloat$;
         3: fload_0
         4: aload_1
         5: invokevirtual #321                // Method org/scalactic/anyvals/PosFloat$.goodOrElse:(FLscala/Function1;)Lorg/scalactic/Or;
         8: areturn
      LocalVariableTable:
        Start  Length  Slot  Name   Signature
            0       9     0 value   F
            0       9     1     f   Lscala/Function1;
    Signature: #319                         // <B:Ljava/lang/Object;>(FLscala/Function1<Ljava/lang/Object;TB;>;)Lorg/scalactic/Or<Lorg/scalactic/anyvals/PosFloat;TB;>;
    MethodParameters:
      Name                           Flags
      value                          final
      f                              final

  public static <E extends java.lang.Object> org.scalactic.Validation<E> passOrElse(float, scala.Function1<java.lang.Object, E>);
    descriptor: (FLscala/Function1;)Lorg/scalactic/Validation;
    flags: (0x0009) ACC_PUBLIC, ACC_STATIC
    Code:
      stack=3, locals=2, args_size=2
         0: getstatic     #20                 // Field org/scalactic/anyvals/PosFloat$.MODULE$:Lorg/scalactic/anyvals/PosFloat$;
         3: fload_0
         4: aload_1
         5: invokevirtual #326                // Method org/scalactic/anyvals/PosFloat$.passOrElse:(FLscala/Function1;)Lorg/scalactic/Validation;
         8: areturn
      LocalVariableTable:
        Start  Length  Slot  Name   Signature
            0       9     0 value   F
            0       9     1     f   Lscala/Function1;
    Signature: #324                         // <E:Ljava/lang/Object;>(FLscala/Function1<Ljava/lang/Object;TE;>;)Lorg/scalactic/Validation<TE;>;
    MethodParameters:
      Name                           Flags
      value                          final
      f                              final

  public static scala.util.Try<org.scalactic.anyvals.PosFloat> tryingValid(float);
    descriptor: (F)Lscala/util/Try;
    flags: (0x0009) ACC_PUBLIC, ACC_STATIC
    Code:
      stack=2, locals=1, args_size=1
         0: getstatic     #20                 // Field org/scalactic/anyvals/PosFloat$.MODULE$:Lorg/scalactic/anyvals/PosFloat$;
         3: fload_0
         4: invokevirtual #331                // Method org/scalactic/anyvals/PosFloat$.tryingValid:(F)Lscala/util/Try;
         7: areturn
      LocalVariableTable:
        Start  Length  Slot  Name   Signature
            0       8     0 value   F
    Signature: #329                         // (F)Lscala/util/Try<Lorg/scalactic/anyvals/PosFloat;>;
    MethodParameters:
      Name                           Flags
      value                          final

  public static scala.Option<org.scalactic.anyvals.PosFloat> from(float);
    descriptor: (F)Lscala/Option;
    flags: (0x0009) ACC_PUBLIC, ACC_STATIC
    Code:
      stack=2, locals=1, args_size=1
         0: getstatic     #20                 // Field org/scalactic/anyvals/PosFloat$.MODULE$:Lorg/scalactic/anyvals/PosFloat$;
         3: fload_0
         4: invokevirtual #336                // Method org/scalactic/anyvals/PosFloat$.from:(F)Lscala/Option;
         7: areturn
      LocalVariableTable:
        Start  Length  Slot  Name   Signature
            0       8     0 value   F
    Signature: #334                         // (F)Lscala/Option<Lorg/scalactic/anyvals/PosFloat;>;
    MethodParameters:
      Name                           Flags
      value                          final

  public static float MinValue();
    descriptor: ()F
    flags: (0x0009) ACC_PUBLIC, ACC_STATIC
    Code:
      stack=1, locals=0, args_size=0
         0: getstatic     #20                 // Field org/scalactic/anyvals/PosFloat$.MODULE$:Lorg/scalactic/anyvals/PosFloat$;
         3: invokevirtual #339                // Method org/scalactic/anyvals/PosFloat$.MinValue:()F
         6: freturn

  public static float MaxValue();
    descriptor: ()F
    flags: (0x0009) ACC_PUBLIC, ACC_STATIC
    Code:
      stack=1, locals=0, args_size=0
         0: getstatic     #20                 // Field org/scalactic/anyvals/PosFloat$.MODULE$:Lorg/scalactic/anyvals/PosFloat$;
         3: invokevirtual #342                // Method org/scalactic/anyvals/PosFloat$.MaxValue:()F
         6: freturn

  public float value();
    descriptor: ()F
    flags: (0x0001) ACC_PUBLIC
    Code:
      stack=1, locals=1, args_size=1
         0: aload_0
         1: getfield      #344                // Field value:F
         4: freturn
      LineNumberTable:
        line 147: 0
      LocalVariableTable:
        Start  Length  Slot  Name   Signature
            0       5     0  this   Lorg/scalactic/anyvals/PosFloat;

  public java.lang.String toString();
    descriptor: ()Ljava/lang/String;
    flags: (0x0001) ACC_PUBLIC
    Code:
      stack=2, locals=1, args_size=1
         0: getstatic     #20                 // Field org/scalactic/anyvals/PosFloat$.MODULE$:Lorg/scalactic/anyvals/PosFloat$;
         3: aload_0
         4: invokevirtual #350                // Method value:()F
         7: invokevirtual #265                // Method org/scalactic/anyvals/PosFloat$.toString$extension:(F)Ljava/lang/String;
        10: areturn
      LineNumberTable:
        line 152: 0
      LocalVariableTable:
        Start  Length  Slot  Name   Signature
            0      11     0  this   Lorg/scalactic/anyvals/PosFloat;

  public byte toByte();
    descriptor: ()B
    flags: (0x0001) ACC_PUBLIC
    Code:
      stack=2, locals=1, args_size=1
         0: getstatic     #20                 // Field org/scalactic/anyvals/PosFloat$.MODULE$:Lorg/scalactic/anyvals/PosFloat$;
         3: aload_0
         4: invokevirtual #350                // Method value:()F
         7: invokevirtual #261                // Method org/scalactic/anyvals/PosFloat$.toByte$extension:(F)B
        10: ireturn
      LineNumberTable:
        line 157: 0
      LocalVariableTable:
        Start  Length  Slot  Name   Signature
            0      11     0  this   Lorg/scalactic/anyvals/PosFloat;

  public short toShort();
    descriptor: ()S
    flags: (0x0001) ACC_PUBLIC
    Code:
      stack=2, locals=1, args_size=1
         0: getstatic     #20                 // Field org/scalactic/anyvals/PosFloat$.MODULE$:Lorg/scalactic/anyvals/PosFloat$;
         3: aload_0
         4: invokevirtual #350                // Method value:()F
         7: invokevirtual #257                // Method org/scalactic/anyvals/PosFloat$.toShort$extension:(F)S
        10: ireturn
      LineNumberTable:
        line 162: 0
      LocalVariableTable:
        Start  Length  Slot  Name   Signature
            0      11     0  this   Lorg/scalactic/anyvals/PosFloat;

  public char toChar();
    descriptor: ()C
    flags: (0x0001) ACC_PUBLIC
    Code:
      stack=2, locals=1, args_size=1
         0: getstatic     #20                 // Field org/scalactic/anyvals/PosFloat$.MODULE$:Lorg/scalactic/anyvals/PosFloat$;
         3: aload_0
         4: invokevirtual #350                // Method value:()F
         7: invokevirtual #253                // Method org/scalactic/anyvals/PosFloat$.toChar$extension:(F)C
        10: ireturn
      LineNumberTable:
        line 167: 0
      LocalVariableTable:
        Start  Length  Slot  Name   Signature
            0      11     0  this   Lorg/scalactic/anyvals/PosFloat;

  public int toInt();
    descriptor: ()I
    flags: (0x0001) ACC_PUBLIC
    Code:
      stack=2, locals=1, args_size=1
         0: getstatic     #20                 // Field org/scalactic/anyvals/PosFloat$.MODULE$:Lorg/scalactic/anyvals/PosFloat$;
         3: aload_0
         4: invokevirtual #350                // Method value:()F
         7: invokevirtual #249                // Method org/scalactic/anyvals/PosFloat$.toInt$extension:(F)I
        10: ireturn
      LineNumberTable:
        line 172: 0
      LocalVariableTable:
        Start  Length  Slot  Name   Signature
            0      11     0  this   Lorg/scalactic/anyvals/PosFloat;

  public long toLong();
    descriptor: ()J
    flags: (0x0001) ACC_PUBLIC
    Code:
      stack=2, locals=1, args_size=1
         0: getstatic     #20                 // Field org/scalactic/anyvals/PosFloat$.MODULE$:Lorg/scalactic/anyvals/PosFloat$;
         3: aload_0
         4: invokevirtual #350                // Method value:()F
         7: invokevirtual #246                // Method org/scalactic/anyvals/PosFloat$.toLong$extension:(F)J
        10: lreturn
      LineNumberTable:
        line 177: 0
      LocalVariableTable:
        Start  Length  Slot  Name   Signature
            0      11     0  this   Lorg/scalactic/anyvals/PosFloat;

  public float toFloat();
    descriptor: ()F
    flags: (0x0001) ACC_PUBLIC
    Code:
      stack=2, locals=1, args_size=1
         0: getstatic     #20                 // Field org/scalactic/anyvals/PosFloat$.MODULE$:Lorg/scalactic/anyvals/PosFloat$;
         3: aload_0
         4: invokevirtual #350                // Method value:()F
         7: invokevirtual #242                // Method org/scalactic/anyvals/PosFloat$.toFloat$extension:(F)F
        10: freturn
      LineNumberTable:
        line 182: 0
      LocalVariableTable:
        Start  Length  Slot  Name   Signature
            0      11     0  this   Lorg/scalactic/anyvals/PosFloat;

  public double toDouble();
    descriptor: ()D
    flags: (0x0001) ACC_PUBLIC
    Code:
      stack=2, locals=1, args_size=1
         0: getstatic     #20                 // Field org/scalactic/anyvals/PosFloat$.MODULE$:Lorg/scalactic/anyvals/PosFloat$;
         3: aload_0
         4: invokevirtual #350                // Method value:()F
         7: invokevirtual #239                // Method org/scalactic/anyvals/PosFloat$.toDouble$extension:(F)D
        10: dreturn
      LineNumberTable:
        line 187: 0
      LocalVariableTable:
        Start  Length  Slot  Name   Signature
            0      11     0  this   Lorg/scalactic/anyvals/PosFloat;

  public float unary_$plus();
    descriptor: ()F
    flags: (0x0001) ACC_PUBLIC
    Code:
      stack=2, locals=1, args_size=1
         0: getstatic     #20                 // Field org/scalactic/anyvals/PosFloat$.MODULE$:Lorg/scalactic/anyvals/PosFloat$;
         3: aload_0
         4: invokevirtual #350                // Method value:()F
         7: invokevirtual #235                // Method org/scalactic/anyvals/PosFloat$.unary_$plus$extension:(F)F
        10: freturn
      LineNumberTable:
        line 190: 0
      LocalVariableTable:
        Start  Length  Slot  Name   Signature
            0      11     0  this   Lorg/scalactic/anyvals/PosFloat;

  public float unary_$minus();
    descriptor: ()F
    flags: (0x0001) ACC_PUBLIC
    Code:
      stack=2, locals=1, args_size=1
         0: getstatic     #20                 // Field org/scalactic/anyvals/PosFloat$.MODULE$:Lorg/scalactic/anyvals/PosFloat$;
         3: aload_0
         4: invokevirtual #350                // Method value:()F
         7: invokevirtual #232                // Method org/scalactic/anyvals/PosFloat$.unary_$minus$extension:(F)F
        10: freturn
      LineNumberTable:
        line 192: 0
      LocalVariableTable:
        Start  Length  Slot  Name   Signature
            0      11     0  this   Lorg/scalactic/anyvals/PosFloat;

  public java.lang.String $plus(java.lang.String);
    descriptor: (Ljava/lang/String;)Ljava/lang/String;
    flags: (0x0001) ACC_PUBLIC
    Code:
      stack=3, locals=2, args_size=2
         0: getstatic     #20                 // Field org/scalactic/anyvals/PosFloat$.MODULE$:Lorg/scalactic/anyvals/PosFloat$;
         3: aload_0
         4: invokevirtual #350                // Method value:()F
         7: aload_1
         8: invokevirtual #228                // Method org/scalactic/anyvals/PosFloat$.$plus$extension:(FLjava/lang/String;)Ljava/lang/String;
        11: areturn
      LineNumberTable:
        line 197: 0
      LocalVariableTable:
        Start  Length  Slot  Name   Signature
            0      12     0  this   Lorg/scalactic/anyvals/PosFloat;
            0      12     1     x   Ljava/lang/String;
    MethodParameters:
      Name                           Flags
      x                              final

  public boolean $less(byte);
    descriptor: (B)Z
    flags: (0x0001) ACC_PUBLIC
    Code:
      stack=3, locals=2, args_size=2
         0: getstatic     #20                 // Field org/scalactic/anyvals/PosFloat$.MODULE$:Lorg/scalactic/anyvals/PosFloat$;
         3: aload_0
         4: invokevirtual #350                // Method value:()F
         7: iload_1
         8: invokevirtual #225                // Method org/scalactic/anyvals/PosFloat$.$less$extension:(FB)Z
        11: ireturn
      LineNumberTable:
        line 200: 0
      LocalVariableTable:
        Start  Length  Slot  Name   Signature
            0      12     0  this   Lorg/scalactic/anyvals/PosFloat;
            0      12     1     x   B
    MethodParameters:
      Name                           Flags
      x                              final

  public boolean $less(short);
    descriptor: (S)Z
    flags: (0x0001) ACC_PUBLIC
    Code:
      stack=3, locals=2, args_size=2
         0: getstatic     #20                 // Field org/scalactic/anyvals/PosFloat$.MODULE$:Lorg/scalactic/anyvals/PosFloat$;
         3: aload_0
         4: invokevirtual #350                // Method value:()F
         7: iload_1
         8: invokevirtual #223                // Method org/scalactic/anyvals/PosFloat$.$less$extension:(FS)Z
        11: ireturn
      LineNumberTable:
        line 202: 0
      LocalVariableTable:
        Start  Length  Slot  Name   Signature
            0      12     0  this   Lorg/scalactic/anyvals/PosFloat;
            0      12     1     x   S
    MethodParameters:
      Name                           Flags
      x                              final

  public boolean $less(char);
    descriptor: (C)Z
    flags: (0x0001) ACC_PUBLIC
    Code:
      stack=3, locals=2, args_size=2
         0: getstatic     #20                 // Field org/scalactic/anyvals/PosFloat$.MODULE$:Lorg/scalactic/anyvals/PosFloat$;
         3: aload_0
         4: invokevirtual #350                // Method value:()F
         7: iload_1
         8: invokevirtual #221                // Method org/scalactic/anyvals/PosFloat$.$less$extension:(FC)Z
        11: ireturn
      LineNumberTable:
        line 204: 0
      LocalVariableTable:
        Start  Length  Slot  Name   Signature
            0      12     0  this   Lorg/scalactic/anyvals/PosFloat;
            0      12     1     x   C
    MethodParameters:
      Name                           Flags
      x                              final

  public boolean $less(int);
    descriptor: (I)Z
    flags: (0x0001) ACC_PUBLIC
    Code:
      stack=3, locals=2, args_size=2
         0: getstatic     #20                 // Field org/scalactic/anyvals/PosFloat$.MODULE$:Lorg/scalactic/anyvals/PosFloat$;
         3: aload_0
         4: invokevirtual #350                // Method value:()F
         7: iload_1
         8: invokevirtual #219                // Method org/scalactic/anyvals/PosFloat$.$less$extension:(FI)Z
        11: ireturn
      LineNumberTable:
        line 206: 0
      LocalVariableTable:
        Start  Length  Slot  Name   Signature
            0      12     0  this   Lorg/scalactic/anyvals/PosFloat;
            0      12     1     x   I
    MethodParameters:
      Name                           Flags
      x                              final

  public boolean $less(long);
    descriptor: (J)Z
    flags: (0x0001) ACC_PUBLIC
    Code:
      stack=4, locals=3, args_size=2
         0: getstatic     #20                 // Field org/scalactic/anyvals/PosFloat$.MODULE$:Lorg/scalactic/anyvals/PosFloat$;
         3: aload_0
         4: invokevirtual #350                // Method value:()F
         7: lload_1
         8: invokevirtual #217                // Method org/scalactic/anyvals/PosFloat$.$less$extension:(FJ)Z
        11: ireturn
      LineNumberTable:
        line 208: 0
      LocalVariableTable:
        Start  Length  Slot  Name   Signature
            0      12     0  this   Lorg/scalactic/anyvals/PosFloat;
            0      12     1     x   J
    MethodParameters:
      Name                           Flags
      x                              final

  public boolean $less(float);
    descriptor: (F)Z
    flags: (0x0001) ACC_PUBLIC
    Code:
      stack=3, locals=2, args_size=2
         0: getstatic     #20                 // Field org/scalactic/anyvals/PosFloat$.MODULE$:Lorg/scalactic/anyvals/PosFloat$;
         3: aload_0
         4: invokevirtual #350                // Method value:()F
         7: fload_1
         8: invokevirtual #215                // Method org/scalactic/anyvals/PosFloat$.$less$extension:(FF)Z
        11: ireturn
      LineNumberTable:
        line 210: 0
      LocalVariableTable:
        Start  Length  Slot  Name   Signature
            0      12     0  this   Lorg/scalactic/anyvals/PosFloat;
            0      12     1     x   F
    MethodParameters:
      Name                           Flags
      x                              final

  public boolean $less(double);
    descriptor: (D)Z
    flags: (0x0001) ACC_PUBLIC
    Code:
      stack=4, locals=3, args_size=2
         0: getstatic     #20                 // Field org/scalactic/anyvals/PosFloat$.MODULE$:Lorg/scalactic/anyvals/PosFloat$;
         3: aload_0
         4: invokevirtual #350                // Method value:()F
         7: dload_1
         8: invokevirtual #213                // Method org/scalactic/anyvals/PosFloat$.$less$extension:(FD)Z
        11: ireturn
      LineNumberTable:
        line 212: 0
      LocalVariableTable:
        Start  Length  Slot  Name   Signature
            0      12     0  this   Lorg/scalactic/anyvals/PosFloat;
            0      12     1     x   D
    MethodParameters:
      Name                           Flags
      x                              final

  public boolean $less$eq(byte);
    descriptor: (B)Z
    flags: (0x0001) ACC_PUBLIC
    Code:
      stack=3, locals=2, args_size=2
         0: getstatic     #20                 // Field org/scalactic/anyvals/PosFloat$.MODULE$:Lorg/scalactic/anyvals/PosFloat$;
         3: aload_0
         4: invokevirtual #350                // Method value:()F
         7: iload_1
         8: invokevirtual #210                // Method org/scalactic/anyvals/PosFloat$.$less$eq$extension:(FB)Z
        11: ireturn
      LineNumberTable:
        line 215: 0
      LocalVariableTable:
        Start  Length  Slot  Name   Signature
            0      12     0  this   Lorg/scalactic/anyvals/PosFloat;
            0      12     1     x   B
    MethodParameters:
      Name                           Flags
      x                              final

  public boolean $less$eq(short);
    descriptor: (S)Z
    flags: (0x0001) ACC_PUBLIC
    Code:
      stack=3, locals=2, args_size=2
         0: getstatic     #20                 // Field org/scalactic/anyvals/PosFloat$.MODULE$:Lorg/scalactic/anyvals/PosFloat$;
         3: aload_0
         4: invokevirtual #350                // Method value:()F
         7: iload_1
         8: invokevirtual #208                // Method org/scalactic/anyvals/PosFloat$.$less$eq$extension:(FS)Z
        11: ireturn
      LineNumberTable:
        line 217: 0
      LocalVariableTable:
        Start  Length  Slot  Name   Signature
            0      12     0  this   Lorg/scalactic/anyvals/PosFloat;
            0      12     1     x   S
    MethodParameters:
      Name                           Flags
      x                              final

  public boolean $less$eq(char);
    descriptor: (C)Z
    flags: (0x0001) ACC_PUBLIC
    Code:
      stack=3, locals=2, args_size=2
         0: getstatic     #20                 // Field org/scalactic/anyvals/PosFloat$.MODULE$:Lorg/scalactic/anyvals/PosFloat$;
         3: aload_0
         4: invokevirtual #350                // Method value:()F
         7: iload_1
         8: invokevirtual #206                // Method org/scalactic/anyvals/PosFloat$.$less$eq$extension:(FC)Z
        11: ireturn
      LineNumberTable:
        line 219: 0
      LocalVariableTable:
        Start  Length  Slot  Name   Signature
            0      12     0  this   Lorg/scalactic/anyvals/PosFloat;
            0      12     1     x   C
    MethodParameters:
      Name                           Flags
      x                              final

  public boolean $less$eq(int);
    descriptor: (I)Z
    flags: (0x0001) ACC_PUBLIC
    Code:
      stack=3, locals=2, args_size=2
         0: getstatic     #20                 // Field org/scalactic/anyvals/PosFloat$.MODULE$:Lorg/scalactic/anyvals/PosFloat$;
         3: aload_0
         4: invokevirtual #350                // Method value:()F
         7: iload_1
         8: invokevirtual #204                // Method org/scalactic/anyvals/PosFloat$.$less$eq$extension:(FI)Z
        11: ireturn
      LineNumberTable:
        line 221: 0
      LocalVariableTable:
        Start  Length  Slot  Name   Signature
            0      12     0  this   Lorg/scalactic/anyvals/PosFloat;
            0      12     1     x   I
    MethodParameters:
      Name                           Flags
      x                              final

  public boolean $less$eq(long);
    descriptor: (J)Z
    flags: (0x0001) ACC_PUBLIC
    Code:
      stack=4, locals=3, args_size=2
         0: getstatic     #20                 // Field org/scalactic/anyvals/PosFloat$.MODULE$:Lorg/scalactic/anyvals/PosFloat$;
         3: aload_0
         4: invokevirtual #350                // Method value:()F
         7: lload_1
         8: invokevirtual #202                // Method org/scalactic/anyvals/PosFloat$.$less$eq$extension:(FJ)Z
        11: ireturn
      LineNumberTable:
        line 223: 0
      LocalVariableTable:
        Start  Length  Slot  Name   Signature
            0      12     0  this   Lorg/scalactic/anyvals/PosFloat;
            0      12     1     x   J
    MethodParameters:
      Name                           Flags
      x                              final

  public boolean $less$eq(float);
    descriptor: (F)Z
    flags: (0x0001) ACC_PUBLIC
    Code:
      stack=3, locals=2, args_size=2
         0: getstatic     #20                 // Field org/scalactic/anyvals/PosFloat$.MODULE$:Lorg/scalactic/anyvals/PosFloat$;
         3: aload_0
         4: invokevirtual #350                // Method value:()F
         7: fload_1
         8: invokevirtual #200                // Method org/scalactic/anyvals/PosFloat$.$less$eq$extension:(FF)Z
        11: ireturn
      LineNumberTable:
        line 225: 0
      LocalVariableTable:
        Start  Length  Slot  Name   Signature
            0      12     0  this   Lorg/scalactic/anyvals/PosFloat;
            0      12     1     x   F
    MethodParameters:
      Name                           Flags
      x                              final

  public boolean $less$eq(double);
    descriptor: (D)Z
    flags: (0x0001) ACC_PUBLIC
    Code:
      stack=4, locals=3, args_size=2
         0: getstatic     #20                 // Field org/scalactic/anyvals/PosFloat$.MODULE$:Lorg/scalactic/anyvals/PosFloat$;
         3: aload_0
         4: invokevirtual #350                // Method value:()F
         7: dload_1
         8: invokevirtual #198                // Method org/scalactic/anyvals/PosFloat$.$less$eq$extension:(FD)Z
        11: ireturn
      LineNumberTable:
        line 227: 0
      LocalVariableTable:
        Start  Length  Slot  Name   Signature
            0      12     0  this   Lorg/scalactic/anyvals/PosFloat;
            0      12     1     x   D
    MethodParameters:
      Name                           Flags
      x                              final

  public boolean $greater(byte);
    descriptor: (B)Z
    flags: (0x0001) ACC_PUBLIC
    Code:
      stack=3, locals=2, args_size=2
         0: getstatic     #20                 // Field org/scalactic/anyvals/PosFloat$.MODULE$:Lorg/scalactic/anyvals/PosFloat$;
         3: aload_0
         4: invokevirtual #350                // Method value:()F
         7: iload_1
         8: invokevirtual #195                // Method org/scalactic/anyvals/PosFloat$.$greater$extension:(FB)Z
        11: ireturn
      LineNumberTable:
        line 230: 0
      LocalVariableTable:
        Start  Length  Slot  Name   Signature
            0      12     0  this   Lorg/scalactic/anyvals/PosFloat;
            0      12     1     x   B
    MethodParameters:
      Name                           Flags
      x                              final

  public boolean $greater(short);
    descriptor: (S)Z
    flags: (0x0001) ACC_PUBLIC
    Code:
      stack=3, locals=2, args_size=2
         0: getstatic     #20                 // Field org/scalactic/anyvals/PosFloat$.MODULE$:Lorg/scalactic/anyvals/PosFloat$;
         3: aload_0
         4: invokevirtual #350                // Method value:()F
         7: iload_1
         8: invokevirtual #193                // Method org/scalactic/anyvals/PosFloat$.$greater$extension:(FS)Z
        11: ireturn
      LineNumberTable:
        line 232: 0
      LocalVariableTable:
        Start  Length  Slot  Name   Signature
            0      12     0  this   Lorg/scalactic/anyvals/PosFloat;
            0      12     1     x   S
    MethodParameters:
      Name                           Flags
      x                              final

  public boolean $greater(char);
    descriptor: (C)Z
    flags: (0x0001) ACC_PUBLIC
    Code:
      stack=3, locals=2, args_size=2
         0: getstatic     #20                 // Field org/scalactic/anyvals/PosFloat$.MODULE$:Lorg/scalactic/anyvals/PosFloat$;
         3: aload_0
         4: invokevirtual #350                // Method value:()F
         7: iload_1
         8: invokevirtual #191                // Method org/scalactic/anyvals/PosFloat$.$greater$extension:(FC)Z
        11: ireturn
      LineNumberTable:
        line 234: 0
      LocalVariableTable:
        Start  Length  Slot  Name   Signature
            0      12     0  this   Lorg/scalactic/anyvals/PosFloat;
            0      12     1     x   C
    MethodParameters:
      Name                           Flags
      x                              final

  public boolean $greater(int);
    descriptor: (I)Z
    flags: (0x0001) ACC_PUBLIC
    Code:
      stack=3, locals=2, args_size=2
         0: getstatic     #20                 // Field org/scalactic/anyvals/PosFloat$.MODULE$:Lorg/scalactic/anyvals/PosFloat$;
         3: aload_0
         4: invokevirtual #350                // Method value:()F
         7: iload_1
         8: invokevirtual #189                // Method org/scalactic/anyvals/PosFloat$.$greater$extension:(FI)Z
        11: ireturn
      LineNumberTable:
        line 236: 0
      LocalVariableTable:
        Start  Length  Slot  Name   Signature
            0      12     0  this   Lorg/scalactic/anyvals/PosFloat;
            0      12     1     x   I
    MethodParameters:
      Name                           Flags
      x                              final

  public boolean $greater(long);
    descriptor: (J)Z
    flags: (0x0001) ACC_PUBLIC
    Code:
      stack=4, locals=3, args_size=2
         0: getstatic     #20                 // Field org/scalactic/anyvals/PosFloat$.MODULE$:Lorg/scalactic/anyvals/PosFloat$;
         3: aload_0
         4: invokevirtual #350                // Method value:()F
         7: lload_1
         8: invokevirtual #187                // Method org/scalactic/anyvals/PosFloat$.$greater$extension:(FJ)Z
        11: ireturn
      LineNumberTable:
        line 238: 0
      LocalVariableTable:
        Start  Length  Slot  Name   Signature
            0      12     0  this   Lorg/scalactic/anyvals/PosFloat;
            0      12     1     x   J
    MethodParameters:
      Name                           Flags
      x                              final

  public boolean $greater(float);
    descriptor: (F)Z
    flags: (0x0001) ACC_PUBLIC
    Code:
      stack=3, locals=2, args_size=2
         0: getstatic     #20                 // Field org/scalactic/anyvals/PosFloat$.MODULE$:Lorg/scalactic/anyvals/PosFloat$;
         3: aload_0
         4: invokevirtual #350                // Method value:()F
         7: fload_1
         8: invokevirtual #185                // Method org/scalactic/anyvals/PosFloat$.$greater$extension:(FF)Z
        11: ireturn
      LineNumberTable:
        line 240: 0
      LocalVariableTable:
        Start  Length  Slot  Name   Signature
            0      12     0  this   Lorg/scalactic/anyvals/PosFloat;
            0      12     1     x   F
    MethodParameters:
      Name                           Flags
      x                              final

  public boolean $greater(double);
    descriptor: (D)Z
    flags: (0x0001) ACC_PUBLIC
    Code:
      stack=4, locals=3, args_size=2
         0: getstatic     #20                 // Field org/scalactic/anyvals/PosFloat$.MODULE$:Lorg/scalactic/anyvals/PosFloat$;
         3: aload_0
         4: invokevirtual #350                // Method value:()F
         7: dload_1
         8: invokevirtual #183                // Method org/scalactic/anyvals/PosFloat$.$greater$extension:(FD)Z
        11: ireturn
      LineNumberTable:
        line 242: 0
      LocalVariableTable:
        Start  Length  Slot  Name   Signature
            0      12     0  this   Lorg/scalactic/anyvals/PosFloat;
            0      12     1     x   D
    MethodParameters:
      Name                           Flags
      x                              final

  public boolean $greater$eq(byte);
    descriptor: (B)Z
    flags: (0x0001) ACC_PUBLIC
    Code:
      stack=3, locals=2, args_size=2
         0: getstatic     #20                 // Field org/scalactic/anyvals/PosFloat$.MODULE$:Lorg/scalactic/anyvals/PosFloat$;
         3: aload_0
         4: invokevirtual #350                // Method value:()F
         7: iload_1
         8: invokevirtual #180                // Method org/scalactic/anyvals/PosFloat$.$greater$eq$extension:(FB)Z
        11: ireturn
      LineNumberTable:
        line 245: 0
      LocalVariableTable:
        Start  Length  Slot  Name   Signature
            0      12     0  this   Lorg/scalactic/anyvals/PosFloat;
            0      12     1     x   B
    MethodParameters:
      Name                           Flags
      x                              final

  public boolean $greater$eq(short);
    descriptor: (S)Z
    flags: (0x0001) ACC_PUBLIC
    Code:
      stack=3, locals=2, args_size=2
         0: getstatic     #20                 // Field org/scalactic/anyvals/PosFloat$.MODULE$:Lorg/scalactic/anyvals/PosFloat$;
         3: aload_0
         4: invokevirtual #350                // Method value:()F
         7: iload_1
         8: invokevirtual #177                // Method org/scalactic/anyvals/PosFloat$.$greater$eq$extension:(FS)Z
        11: ireturn
      LineNumberTable:
        line 247: 0
      LocalVariableTable:
        Start  Length  Slot  Name   Signature
            0      12     0  this   Lorg/scalactic/anyvals/PosFloat;
            0      12     1     x   S
    MethodParameters:
      Name                           Flags
      x                              final

  public boolean $greater$eq(char);
    descriptor: (C)Z
    flags: (0x0001) ACC_PUBLIC
    Code:
      stack=3, locals=2, args_size=2
         0: getstatic     #20                 // Field org/scalactic/anyvals/PosFloat$.MODULE$:Lorg/scalactic/anyvals/PosFloat$;
         3: aload_0
         4: invokevirtual #350                // Method value:()F
         7: iload_1
         8: invokevirtual #174                // Method org/scalactic/anyvals/PosFloat$.$greater$eq$extension:(FC)Z
        11: ireturn
      LineNumberTable:
        line 249: 0
      LocalVariableTable:
        Start  Length  Slot  Name   Signature
            0      12     0  this   Lorg/scalactic/anyvals/PosFloat;
            0      12     1     x   C
    MethodParameters:
      Name                           Flags
      x                              final

  public boolean $greater$eq(int);
    descriptor: (I)Z
    flags: (0x0001) ACC_PUBLIC
    Code:
      stack=3, locals=2, args_size=2
         0: getstatic     #20                 // Field org/scalactic/anyvals/PosFloat$.MODULE$:Lorg/scalactic/anyvals/PosFloat$;
         3: aload_0
         4: invokevirtual #350                // Method value:()F
         7: iload_1
         8: invokevirtual #171                // Method org/scalactic/anyvals/PosFloat$.$greater$eq$extension:(FI)Z
        11: ireturn
      LineNumberTable:
        line 251: 0
      LocalVariableTable:
        Start  Length  Slot  Name   Signature
            0      12     0  this   Lorg/scalactic/anyvals/PosFloat;
            0      12     1     x   I
    MethodParameters:
      Name                           Flags
      x                              final

  public boolean $greater$eq(long);
    descriptor: (J)Z
    flags: (0x0001) ACC_PUBLIC
    Code:
      stack=4, locals=3, args_size=2
         0: getstatic     #20                 // Field org/scalactic/anyvals/PosFloat$.MODULE$:Lorg/scalactic/anyvals/PosFloat$;
         3: aload_0
         4: invokevirtual #350                // Method value:()F
         7: lload_1
         8: invokevirtual #168                // Method org/scalactic/anyvals/PosFloat$.$greater$eq$extension:(FJ)Z
        11: ireturn
      LineNumberTable:
        line 253: 0
      LocalVariableTable:
        Start  Length  Slot  Name   Signature
            0      12     0  this   Lorg/scalactic/anyvals/PosFloat;
            0      12     1     x   J
    MethodParameters:
      Name                           Flags
      x                              final

  public boolean $greater$eq(float);
    descriptor: (F)Z
    flags: (0x0001) ACC_PUBLIC
    Code:
      stack=3, locals=2, args_size=2
         0: getstatic     #20                 // Field org/scalactic/anyvals/PosFloat$.MODULE$:Lorg/scalactic/anyvals/PosFloat$;
         3: aload_0
         4: invokevirtual #350                // Method value:()F
         7: fload_1
         8: invokevirtual #165                // Method org/scalactic/anyvals/PosFloat$.$greater$eq$extension:(FF)Z
        11: ireturn
      LineNumberTable:
        line 255: 0
      LocalVariableTable:
        Start  Length  Slot  Name   Signature
            0      12     0  this   Lorg/scalactic/anyvals/PosFloat;
            0      12     1     x   F
    MethodParameters:
      Name                           Flags
      x                              final

  public boolean $greater$eq(double);
    descriptor: (D)Z
    flags: (0x0001) ACC_PUBLIC
    Code:
      stack=4, locals=3, args_size=2
         0: getstatic     #20                 // Field org/scalactic/anyvals/PosFloat$.MODULE$:Lorg/scalactic/anyvals/PosFloat$;
         3: aload_0
         4: invokevirtual #350                // Method value:()F
         7: dload_1
         8: invokevirtual #162                // Method org/scalactic/anyvals/PosFloat$.$greater$eq$extension:(FD)Z
        11: ireturn
      LineNumberTable:
        line 257: 0
      LocalVariableTable:
        Start  Length  Slot  Name   Signature
            0      12     0  this   Lorg/scalactic/anyvals/PosFloat;
            0      12     1     x   D
    MethodParameters:
      Name                           Flags
      x                              final

  public float $plus(byte);
    descriptor: (B)F
    flags: (0x0001) ACC_PUBLIC
    Code:
      stack=3, locals=2, args_size=2
         0: getstatic     #20                 // Field org/scalactic/anyvals/PosFloat$.MODULE$:Lorg/scalactic/anyvals/PosFloat$;
         3: aload_0
         4: invokevirtual #350                // Method value:()F
         7: iload_1
         8: invokevirtual #158                // Method org/scalactic/anyvals/PosFloat$.$plus$extension:(FB)F
        11: freturn
      LineNumberTable:
        line 260: 0
      LocalVariableTable:
        Start  Length  Slot  Name   Signature
            0      12     0  this   Lorg/scalactic/anyvals/PosFloat;
            0      12     1     x   B
    MethodParameters:
      Name                           Flags
      x                              final

  public float $plus(short);
    descriptor: (S)F
    flags: (0x0001) ACC_PUBLIC
    Code:
      stack=3, locals=2, args_size=2
         0: getstatic     #20                 // Field org/scalactic/anyvals/PosFloat$.MODULE$:Lorg/scalactic/anyvals/PosFloat$;
         3: aload_0
         4: invokevirtual #350                // Method value:()F
         7: iload_1
         8: invokevirtual #156                // Method org/scalactic/anyvals/PosFloat$.$plus$extension:(FS)F
        11: freturn
      LineNumberTable:
        line 262: 0
      LocalVariableTable:
        Start  Length  Slot  Name   Signature
            0      12     0  this   Lorg/scalactic/anyvals/PosFloat;
            0      12     1     x   S
    MethodParameters:
      Name                           Flags
      x                              final

  public float $plus(char);
    descriptor: (C)F
    flags: (0x0001) ACC_PUBLIC
    Code:
      stack=3, locals=2, args_size=2
         0: getstatic     #20                 // Field org/scalactic/anyvals/PosFloat$.MODULE$:Lorg/scalactic/anyvals/PosFloat$;
         3: aload_0
         4: invokevirtual #350                // Method value:()F
         7: iload_1
         8: invokevirtual #154                // Method org/scalactic/anyvals/PosFloat$.$plus$extension:(FC)F
        11: freturn
      LineNumberTable:
        line 264: 0
      LocalVariableTable:
        Start  Length  Slot  Name   Signature
            0      12     0  this   Lorg/scalactic/anyvals/PosFloat;
            0      12     1     x   C
    MethodParameters:
      Name                           Flags
      x                              final

  public float $plus(int);
    descriptor: (I)F
    flags: (0x0001) ACC_PUBLIC
    Code:
      stack=3, locals=2, args_size=2
         0: getstatic     #20                 // Field org/scalactic/anyvals/PosFloat$.MODULE$:Lorg/scalactic/anyvals/PosFloat$;
         3: aload_0
         4: invokevirtual #350                // Method value:()F
         7: iload_1
         8: invokevirtual #152                // Method org/scalactic/anyvals/PosFloat$.$plus$extension:(FI)F
        11: freturn
      LineNumberTable:
        line 266: 0
      LocalVariableTable:
        Start  Length  Slot  Name   Signature
            0      12     0  this   Lorg/scalactic/anyvals/PosFloat;
            0      12     1     x   I
    MethodParameters:
      Name                           Flags
      x                              final

  public float $plus(long);
    descriptor: (J)F
    flags: (0x0001) ACC_PUBLIC
    Code:
      stack=4, locals=3, args_size=2
         0: getstatic     #20                 // Field org/scalactic/anyvals/PosFloat$.MODULE$:Lorg/scalactic/anyvals/PosFloat$;
         3: aload_0
         4: invokevirtual #350                // Method value:()F
         7: lload_1
         8: invokevirtual #150                // Method org/scalactic/anyvals/PosFloat$.$plus$extension:(FJ)F
        11: freturn
      LineNumberTable:
        line 268: 0
      LocalVariableTable:
        Start  Length  Slot  Name   Signature
            0      12     0  this   Lorg/scalactic/anyvals/PosFloat;
            0      12     1     x   J
    MethodParameters:
      Name                           Flags
      x                              final

  public float $plus(float);
    descriptor: (F)F
    flags: (0x0001) ACC_PUBLIC
    Code:
      stack=3, locals=2, args_size=2
         0: getstatic     #20                 // Field org/scalactic/anyvals/PosFloat$.MODULE$:Lorg/scalactic/anyvals/PosFloat$;
         3: aload_0
         4: invokevirtual #350                // Method value:()F
         7: fload_1
         8: invokevirtual #148                // Method org/scalactic/anyvals/PosFloat$.$plus$extension:(FF)F
        11: freturn
      LineNumberTable:
        line 270: 0
      LocalVariableTable:
        Start  Length  Slot  Name   Signature
            0      12     0  this   Lorg/scalactic/anyvals/PosFloat;
            0      12     1     x   F
    MethodParameters:
      Name                           Flags
      x                              final

  public double $plus(double);
    descriptor: (D)D
    flags: (0x0001) ACC_PUBLIC
    Code:
      stack=4, locals=3, args_size=2
         0: getstatic     #20                 // Field org/scalactic/anyvals/PosFloat$.MODULE$:Lorg/scalactic/anyvals/PosFloat$;
         3: aload_0
         4: invokevirtual #350                // Method value:()F
         7: dload_1
         8: invokevirtual #146                // Method org/scalactic/anyvals/PosFloat$.$plus$extension:(FD)D
        11: dreturn
      LineNumberTable:
        line 272: 0
      LocalVariableTable:
        Start  Length  Slot  Name   Signature
            0      12     0  this   Lorg/scalactic/anyvals/PosFloat;
            0      12     1     x   D
    MethodParameters:
      Name                           Flags
      x                              final

  public float $minus(byte);
    descriptor: (B)F
    flags: (0x0001) ACC_PUBLIC
    Code:
      stack=3, locals=2, args_size=2
         0: getstatic     #20                 // Field org/scalactic/anyvals/PosFloat$.MODULE$:Lorg/scalactic/anyvals/PosFloat$;
         3: aload_0
         4: invokevirtual #350                // Method value:()F
         7: iload_1
         8: invokevirtual #143                // Method org/scalactic/anyvals/PosFloat$.$minus$extension:(FB)F
        11: freturn
      LineNumberTable:
        line 275: 0
      LocalVariableTable:
        Start  Length  Slot  Name   Signature
            0      12     0  this   Lorg/scalactic/anyvals/PosFloat;
            0      12     1     x   B
    MethodParameters:
      Name                           Flags
      x                              final

  public float $minus(short);
    descriptor: (S)F
    flags: (0x0001) ACC_PUBLIC
    Code:
      stack=3, locals=2, args_size=2
         0: getstatic     #20                 // Field org/scalactic/anyvals/PosFloat$.MODULE$:Lorg/scalactic/anyvals/PosFloat$;
         3: aload_0
         4: invokevirtual #350                // Method value:()F
         7: iload_1
         8: invokevirtual #141                // Method org/scalactic/anyvals/PosFloat$.$minus$extension:(FS)F
        11: freturn
      LineNumberTable:
        line 277: 0
      LocalVariableTable:
        Start  Length  Slot  Name   Signature
            0      12     0  this   Lorg/scalactic/anyvals/PosFloat;
            0      12     1     x   S
    MethodParameters:
      Name                           Flags
      x                              final

  public float $minus(char);
    descriptor: (C)F
    flags: (0x0001) ACC_PUBLIC
    Code:
      stack=3, locals=2, args_size=2
         0: getstatic     #20                 // Field org/scalactic/anyvals/PosFloat$.MODULE$:Lorg/scalactic/anyvals/PosFloat$;
         3: aload_0
         4: invokevirtual #350                // Method value:()F
         7: iload_1
         8: invokevirtual #139                // Method org/scalactic/anyvals/PosFloat$.$minus$extension:(FC)F
        11: freturn
      LineNumberTable:
        line 279: 0
      LocalVariableTable:
        Start  Length  Slot  Name   Signature
            0      12     0  this   Lorg/scalactic/anyvals/PosFloat;
            0      12     1     x   C
    MethodParameters:
      Name                           Flags
      x                              final

  public float $minus(int);
    descriptor: (I)F
    flags: (0x0001) ACC_PUBLIC
    Code:
      stack=3, locals=2, args_size=2
         0: getstatic     #20                 // Field org/scalactic/anyvals/PosFloat$.MODULE$:Lorg/scalactic/anyvals/PosFloat$;
         3: aload_0
         4: invokevirtual #350                // Method value:()F
         7: iload_1
         8: invokevirtual #137                // Method org/scalactic/anyvals/PosFloat$.$minus$extension:(FI)F
        11: freturn
      LineNumberTable:
        line 281: 0
      LocalVariableTable:
        Start  Length  Slot  Name   Signature
            0      12     0  this   Lorg/scalactic/anyvals/PosFloat;
            0      12     1     x   I
    MethodParameters:
      Name                           Flags
      x                              final

  public float $minus(long);
    descriptor: (J)F
    flags: (0x0001) ACC_PUBLIC
    Code:
      stack=4, locals=3, args_size=2
         0: getstatic     #20                 // Field org/scalactic/anyvals/PosFloat$.MODULE$:Lorg/scalactic/anyvals/PosFloat$;
         3: aload_0
         4: invokevirtual #350                // Method value:()F
         7: lload_1
         8: invokevirtual #135                // Method org/scalactic/anyvals/PosFloat$.$minus$extension:(FJ)F
        11: freturn
      LineNumberTable:
        line 283: 0
      LocalVariableTable:
        Start  Length  Slot  Name   Signature
            0      12     0  this   Lorg/scalactic/anyvals/PosFloat;
            0      12     1     x   J
    MethodParameters:
      Name                           Flags
      x                              final

  public float $minus(float);
    descriptor: (F)F
    flags: (0x0001) ACC_PUBLIC
    Code:
      stack=3, locals=2, args_size=2
         0: getstatic     #20                 // Field org/scalactic/anyvals/PosFloat$.MODULE$:Lorg/scalactic/anyvals/PosFloat$;
         3: aload_0
         4: invokevirtual #350                // Method value:()F
         7: fload_1
         8: invokevirtual #133                // Method org/scalactic/anyvals/PosFloat$.$minus$extension:(FF)F
        11: freturn
      LineNumberTable:
        line 285: 0
      LocalVariableTable:
        Start  Length  Slot  Name   Signature
            0      12     0  this   Lorg/scalactic/anyvals/PosFloat;
            0      12     1     x   F
    MethodParameters:
      Name                           Flags
      x                              final

  public double $minus(double);
    descriptor: (D)D
    flags: (0x0001) ACC_PUBLIC
    Code:
      stack=4, locals=3, args_size=2
         0: getstatic     #20                 // Field org/scalactic/anyvals/PosFloat$.MODULE$:Lorg/scalactic/anyvals/PosFloat$;
         3: aload_0
         4: invokevirtual #350                // Method value:()F
         7: dload_1
         8: invokevirtual #131                // Method org/scalactic/anyvals/PosFloat$.$minus$extension:(FD)D
        11: dreturn
      LineNumberTable:
        line 287: 0
      LocalVariableTable:
        Start  Length  Slot  Name   Signature
            0      12     0  this   Lorg/scalactic/anyvals/PosFloat;
            0      12     1     x   D
    MethodParameters:
      Name                           Flags
      x                              final

  public float $times(byte);
    descriptor: (B)F
    flags: (0x0001) ACC_PUBLIC
    Code:
      stack=3, locals=2, args_size=2
         0: getstatic     #20                 // Field org/scalactic/anyvals/PosFloat$.MODULE$:Lorg/scalactic/anyvals/PosFloat$;
         3: aload_0
         4: invokevirtual #350                // Method value:()F
         7: iload_1
         8: invokevirtual #128                // Method org/scalactic/anyvals/PosFloat$.$times$extension:(FB)F
        11: freturn
      LineNumberTable:
        line 290: 0
      LocalVariableTable:
        Start  Length  Slot  Name   Signature
            0      12     0  this   Lorg/scalactic/anyvals/PosFloat;
            0      12     1     x   B
    MethodParameters:
      Name                           Flags
      x                              final

  public float $times(short);
    descriptor: (S)F
    flags: (0x0001) ACC_PUBLIC
    Code:
      stack=3, locals=2, args_size=2
         0: getstatic     #20                 // Field org/scalactic/anyvals/PosFloat$.MODULE$:Lorg/scalactic/anyvals/PosFloat$;
         3: aload_0
         4: invokevirtual #350                // Method value:()F
         7: iload_1
         8: invokevirtual #126                // Method org/scalactic/anyvals/PosFloat$.$times$extension:(FS)F
        11: freturn
      LineNumberTable:
        line 292: 0
      LocalVariableTable:
        Start  Length  Slot  Name   Signature
            0      12     0  this   Lorg/scalactic/anyvals/PosFloat;
            0      12     1     x   S
    MethodParameters:
      Name                           Flags
      x                              final

  public float $times(char);
    descriptor: (C)F
    flags: (0x0001) ACC_PUBLIC
    Code:
      stack=3, locals=2, args_size=2
         0: getstatic     #20                 // Field org/scalactic/anyvals/PosFloat$.MODULE$:Lorg/scalactic/anyvals/PosFloat$;
         3: aload_0
         4: invokevirtual #350                // Method value:()F
         7: iload_1
         8: invokevirtual #124                // Method org/scalactic/anyvals/PosFloat$.$times$extension:(FC)F
        11: freturn
      LineNumberTable:
        line 294: 0
      LocalVariableTable:
        Start  Length  Slot  Name   Signature
            0      12     0  this   Lorg/scalactic/anyvals/PosFloat;
            0      12     1     x   C
    MethodParameters:
      Name                           Flags
      x                              final

  public float $times(int);
    descriptor: (I)F
    flags: (0x0001) ACC_PUBLIC
    Code:
      stack=3, locals=2, args_size=2
         0: getstatic     #20                 // Field org/scalactic/anyvals/PosFloat$.MODULE$:Lorg/scalactic/anyvals/PosFloat$;
         3: aload_0
         4: invokevirtual #350                // Method value:()F
         7: iload_1
         8: invokevirtual #122                // Method org/scalactic/anyvals/PosFloat$.$times$extension:(FI)F
        11: freturn
      LineNumberTable:
        line 296: 0
      LocalVariableTable:
        Start  Length  Slot  Name   Signature
            0      12     0  this   Lorg/scalactic/anyvals/PosFloat;
            0      12     1     x   I
    MethodParameters:
      Name                           Flags
      x                              final

  public float $times(long);
    descriptor: (J)F
    flags: (0x0001) ACC_PUBLIC
    Code:
      stack=4, locals=3, args_size=2
         0: getstatic     #20                 // Field org/scalactic/anyvals/PosFloat$.MODULE$:Lorg/scalactic/anyvals/PosFloat$;
         3: aload_0
         4: invokevirtual #350                // Method value:()F
         7: lload_1
         8: invokevirtual #120                // Method org/scalactic/anyvals/PosFloat$.$times$extension:(FJ)F
        11: freturn
      LineNumberTable:
        line 298: 0
      LocalVariableTable:
        Start  Length  Slot  Name   Signature
            0      12     0  this   Lorg/scalactic/anyvals/PosFloat;
            0      12     1     x   J
    MethodParameters:
      Name                           Flags
      x                              final

  public float $times(float);
    descriptor: (F)F
    flags: (0x0001) ACC_PUBLIC
    Code:
      stack=3, locals=2, args_size=2
         0: getstatic     #20                 // Field org/scalactic/anyvals/PosFloat$.MODULE$:Lorg/scalactic/anyvals/PosFloat$;
         3: aload_0
         4: invokevirtual #350                // Method value:()F
         7: fload_1
         8: invokevirtual #118                // Method org/scalactic/anyvals/PosFloat$.$times$extension:(FF)F
        11: freturn
      LineNumberTable:
        line 300: 0
      LocalVariableTable:
        Start  Length  Slot  Name   Signature
            0      12     0  this   Lorg/scalactic/anyvals/PosFloat;
            0      12     1     x   F
    MethodParameters:
      Name                           Flags
      x                              final

  public double $times(double);
    descriptor: (D)D
    flags: (0x0001) ACC_PUBLIC
    Code:
      stack=4, locals=3, args_size=2
         0: getstatic     #20                 // Field org/scalactic/anyvals/PosFloat$.MODULE$:Lorg/scalactic/anyvals/PosFloat$;
         3: aload_0
         4: invokevirtual #350                // Method value:()F
         7: dload_1
         8: invokevirtual #116                // Method org/scalactic/anyvals/PosFloat$.$times$extension:(FD)D
        11: dreturn
      LineNumberTable:
        line 302: 0
      LocalVariableTable:
        Start  Length  Slot  Name   Signature
            0      12     0  this   Lorg/scalactic/anyvals/PosFloat;
            0      12     1     x   D
    MethodParameters:
      Name                           Flags
      x                              final

  public float $div(byte);
    descriptor: (B)F
    flags: (0x0001) ACC_PUBLIC
    Code:
      stack=3, locals=2, args_size=2
         0: getstatic     #20                 // Field org/scalactic/anyvals/PosFloat$.MODULE$:Lorg/scalactic/anyvals/PosFloat$;
         3: aload_0
         4: invokevirtual #350                // Method value:()F
         7: iload_1
         8: invokevirtual #113                // Method org/scalactic/anyvals/PosFloat$.$div$extension:(FB)F
        11: freturn
      LineNumberTable:
        line 305: 0
      LocalVariableTable:
        Start  Length  Slot  Name   Signature
            0      12     0  this   Lorg/scalactic/anyvals/PosFloat;
            0      12     1     x   B
    MethodParameters:
      Name                           Flags
      x                              final

  public float $div(short);
    descriptor: (S)F
    flags: (0x0001) ACC_PUBLIC
    Code:
      stack=3, locals=2, args_size=2
         0: getstatic     #20                 // Field org/scalactic/anyvals/PosFloat$.MODULE$:Lorg/scalactic/anyvals/PosFloat$;
         3: aload_0
         4: invokevirtual #350                // Method value:()F
         7: iload_1
         8: invokevirtual #111                // Method org/scalactic/anyvals/PosFloat$.$div$extension:(FS)F
        11: freturn
      LineNumberTable:
        line 307: 0
      LocalVariableTable:
        Start  Length  Slot  Name   Signature
            0      12     0  this   Lorg/scalactic/anyvals/PosFloat;
            0      12     1     x   S
    MethodParameters:
      Name                           Flags
      x                              final

  public float $div(char);
    descriptor: (C)F
    flags: (0x0001) ACC_PUBLIC
    Code:
      stack=3, locals=2, args_size=2
         0: getstatic     #20                 // Field org/scalactic/anyvals/PosFloat$.MODULE$:Lorg/scalactic/anyvals/PosFloat$;
         3: aload_0
         4: invokevirtual #350                // Method value:()F
         7: iload_1
         8: invokevirtual #109                // Method org/scalactic/anyvals/PosFloat$.$div$extension:(FC)F
        11: freturn
      LineNumberTable:
        line 309: 0
      LocalVariableTable:
        Start  Length  Slot  Name   Signature
            0      12     0  this   Lorg/scalactic/anyvals/PosFloat;
            0      12     1     x   C
    MethodParameters:
      Name                           Flags
      x                              final

  public float $div(int);
    descriptor: (I)F
    flags: (0x0001) ACC_PUBLIC
    Code:
      stack=3, locals=2, args_size=2
         0: getstatic     #20                 // Field org/scalactic/anyvals/PosFloat$.MODULE$:Lorg/scalactic/anyvals/PosFloat$;
         3: aload_0
         4: invokevirtual #350                // Method value:()F
         7: iload_1
         8: invokevirtual #107                // Method org/scalactic/anyvals/PosFloat$.$div$extension:(FI)F
        11: freturn
      LineNumberTable:
        line 311: 0
      LocalVariableTable:
        Start  Length  Slot  Name   Signature
            0      12     0  this   Lorg/scalactic/anyvals/PosFloat;
            0      12     1     x   I
    MethodParameters:
      Name                           Flags
      x                              final

  public float $div(long);
    descriptor: (J)F
    flags: (0x0001) ACC_PUBLIC
    Code:
      stack=4, locals=3, args_size=2
         0: getstatic     #20                 // Field org/scalactic/anyvals/PosFloat$.MODULE$:Lorg/scalactic/anyvals/PosFloat$;
         3: aload_0
         4: invokevirtual #350                // Method value:()F
         7: lload_1
         8: invokevirtual #105                // Method org/scalactic/anyvals/PosFloat$.$div$extension:(FJ)F
        11: freturn
      LineNumberTable:
        line 313: 0
      LocalVariableTable:
        Start  Length  Slot  Name   Signature
            0      12     0  this   Lorg/scalactic/anyvals/PosFloat;
            0      12     1     x   J
    MethodParameters:
      Name                           Flags
      x                              final

  public float $div(float);
    descriptor: (F)F
    flags: (0x0001) ACC_PUBLIC
    Code:
      stack=3, locals=2, args_size=2
         0: getstatic     #20                 // Field org/scalactic/anyvals/PosFloat$.MODULE$:Lorg/scalactic/anyvals/PosFloat$;
         3: aload_0
         4: invokevirtual #350                // Method value:()F
         7: fload_1
         8: invokevirtual #103                // Method org/scalactic/anyvals/PosFloat$.$div$extension:(FF)F
        11: freturn
      LineNumberTable:
        line 315: 0
      LocalVariableTable:
        Start  Length  Slot  Name   Signature
            0      12     0  this   Lorg/scalactic/anyvals/PosFloat;
            0      12     1     x   F
    MethodParameters:
      Name                           Flags
      x                              final

  public double $div(double);
    descriptor: (D)D
    flags: (0x0001) ACC_PUBLIC
    Code:
      stack=4, locals=3, args_size=2
         0: getstatic     #20                 // Field org/scalactic/anyvals/PosFloat$.MODULE$:Lorg/scalactic/anyvals/PosFloat$;
         3: aload_0
         4: invokevirtual #350                // Method value:()F
         7: dload_1
         8: invokevirtual #101                // Method org/scalactic/anyvals/PosFloat$.$div$extension:(FD)D
        11: dreturn
      LineNumberTable:
        line 317: 0
      LocalVariableTable:
        Start  Length  Slot  Name   Signature
            0      12     0  this   Lorg/scalactic/anyvals/PosFloat;
            0      12     1     x   D
    MethodParameters:
      Name                           Flags
      x                              final

  public float $percent(byte);
    descriptor: (B)F
    flags: (0x0001) ACC_PUBLIC
    Code:
      stack=3, locals=2, args_size=2
         0: getstatic     #20                 // Field org/scalactic/anyvals/PosFloat$.MODULE$:Lorg/scalactic/anyvals/PosFloat$;
         3: aload_0
         4: invokevirtual #350                // Method value:()F
         7: iload_1
         8: invokevirtual #97                 // Method org/scalactic/anyvals/PosFloat$.$percent$extension:(FB)F
        11: freturn
      LineNumberTable:
        line 320: 0
      LocalVariableTable:
        Start  Length  Slot  Name   Signature
            0      12     0  this   Lorg/scalactic/anyvals/PosFloat;
            0      12     1     x   B
    MethodParameters:
      Name                           Flags
      x                              final

  public float $percent(short);
    descriptor: (S)F
    flags: (0x0001) ACC_PUBLIC
    Code:
      stack=3, locals=2, args_size=2
         0: getstatic     #20                 // Field org/scalactic/anyvals/PosFloat$.MODULE$:Lorg/scalactic/anyvals/PosFloat$;
         3: aload_0
         4: invokevirtual #350                // Method value:()F
         7: iload_1
         8: invokevirtual #93                 // Method org/scalactic/anyvals/PosFloat$.$percent$extension:(FS)F
        11: freturn
      LineNumberTable:
        line 322: 0
      LocalVariableTable:
        Start  Length  Slot  Name   Signature
            0      12     0  this   Lorg/scalactic/anyvals/PosFloat;
            0      12     1     x   S
    MethodParameters:
      Name                           Flags
      x                              final

  public float $percent(char);
    descriptor: (C)F
    flags: (0x0001) ACC_PUBLIC
    Code:
      stack=3, locals=2, args_size=2
         0: getstatic     #20                 // Field org/scalactic/anyvals/PosFloat$.MODULE$:Lorg/scalactic/anyvals/PosFloat$;
         3: aload_0
         4: invokevirtual #350                // Method value:()F
         7: iload_1
         8: invokevirtual #89                 // Method org/scalactic/anyvals/PosFloat$.$percent$extension:(FC)F
        11: freturn
      LineNumberTable:
        line 324: 0
      LocalVariableTable:
        Start  Length  Slot  Name   Signature
            0      12     0  this   Lorg/scalactic/anyvals/PosFloat;
            0      12     1     x   C
    MethodParameters:
      Name                           Flags
      x                              final

  public float $percent(int);
    descriptor: (I)F
    flags: (0x0001) ACC_PUBLIC
    Code:
      stack=3, locals=2, args_size=2
         0: getstatic     #20                 // Field org/scalactic/anyvals/PosFloat$.MODULE$:Lorg/scalactic/anyvals/PosFloat$;
         3: aload_0
         4: invokevirtual #350                // Method value:()F
         7: iload_1
         8: invokevirtual #85                 // Method org/scalactic/anyvals/PosFloat$.$percent$extension:(FI)F
        11: freturn
      LineNumberTable:
        line 326: 0
      LocalVariableTable:
        Start  Length  Slot  Name   Signature
            0      12     0  this   Lorg/scalactic/anyvals/PosFloat;
            0      12     1     x   I
    MethodParameters:
      Name                           Flags
      x                              final

  public float $percent(long);
    descriptor: (J)F
    flags: (0x0001) ACC_PUBLIC
    Code:
      stack=4, locals=3, args_size=2
         0: getstatic     #20                 // Field org/scalactic/anyvals/PosFloat$.MODULE$:Lorg/scalactic/anyvals/PosFloat$;
         3: aload_0
         4: invokevirtual #350                // Method value:()F
         7: lload_1
         8: invokevirtual #81                 // Method org/scalactic/anyvals/PosFloat$.$percent$extension:(FJ)F
        11: freturn
      LineNumberTable:
        line 328: 0
      LocalVariableTable:
        Start  Length  Slot  Name   Signature
            0      12     0  this   Lorg/scalactic/anyvals/PosFloat;
            0      12     1     x   J
    MethodParameters:
      Name                           Flags
      x                              final

  public float $percent(float);
    descriptor: (F)F
    flags: (0x0001) ACC_PUBLIC
    Code:
      stack=3, locals=2, args_size=2
         0: getstatic     #20                 // Field org/scalactic/anyvals/PosFloat$.MODULE$:Lorg/scalactic/anyvals/PosFloat$;
         3: aload_0
         4: invokevirtual #350                // Method value:()F
         7: fload_1
         8: invokevirtual #78                 // Method org/scalactic/anyvals/PosFloat$.$percent$extension:(FF)F
        11: freturn
      LineNumberTable:
        line 330: 0
      LocalVariableTable:
        Start  Length  Slot  Name   Signature
            0      12     0  this   Lorg/scalactic/anyvals/PosFloat;
            0      12     1     x   F
    MethodParameters:
      Name                           Flags
      x                              final

  public double $percent(double);
    descriptor: (D)D
    flags: (0x0001) ACC_PUBLIC
    Code:
      stack=4, locals=3, args_size=2
         0: getstatic     #20                 // Field org/scalactic/anyvals/PosFloat$.MODULE$:Lorg/scalactic/anyvals/PosFloat$;
         3: aload_0
         4: invokevirtual #350                // Method value:()F
         7: dload_1
         8: invokevirtual #75                 // Method org/scalactic/anyvals/PosFloat$.$percent$extension:(FD)D
        11: dreturn
      LineNumberTable:
        line 332: 0
      LocalVariableTable:
        Start  Length  Slot  Name   Signature
            0      12     0  this   Lorg/scalactic/anyvals/PosFloat;
            0      12     1     x   D
    MethodParameters:
      Name                           Flags
      x                              final

  public float max(float);
    descriptor: (F)F
    flags: (0x0001) ACC_PUBLIC
    Code:
      stack=3, locals=2, args_size=2
         0: getstatic     #20                 // Field org/scalactic/anyvals/PosFloat$.MODULE$:Lorg/scalactic/anyvals/PosFloat$;
         3: aload_0
         4: invokevirtual #350                // Method value:()F
         7: fload_1
         8: invokevirtual #71                 // Method org/scalactic/anyvals/PosFloat$.max$extension:(FF)F
        11: freturn
      LineNumberTable:
        line 339: 0
      LocalVariableTable:
        Start  Length  Slot  Name   Signature
            0      12     0  this   Lorg/scalactic/anyvals/PosFloat;
            0      12     1  that   F
    MethodParameters:
      Name                           Flags
      that                           final

  public float min(float);
    descriptor: (F)F
    flags: (0x0001) ACC_PUBLIC
    Code:
      stack=3, locals=2, args_size=2
         0: getstatic     #20                 // Field org/scalactic/anyvals/PosFloat$.MODULE$:Lorg/scalactic/anyvals/PosFloat$;
         3: aload_0
         4: invokevirtual #350                // Method value:()F
         7: fload_1
         8: invokevirtual #68                 // Method org/scalactic/anyvals/PosFloat$.min$extension:(FF)F
        11: freturn
      LineNumberTable:
        line 344: 0
      LocalVariableTable:
        Start  Length  Slot  Name   Signature
            0      12     0  this   Lorg/scalactic/anyvals/PosFloat;
            0      12     1  that   F
    MethodParameters:
      Name                           Flags
      that                           final

  public boolean isWhole();
    descriptor: ()Z
    flags: (0x0001) ACC_PUBLIC
    Code:
      stack=2, locals=1, args_size=1
         0: getstatic     #20                 // Field org/scalactic/anyvals/PosFloat$.MODULE$:Lorg/scalactic/anyvals/PosFloat$;
         3: aload_0
         4: invokevirtual #350                // Method value:()F
         7: invokevirtual #64                 // Method org/scalactic/anyvals/PosFloat$.isWhole$extension:(F)Z
        10: ireturn
      LineNumberTable:
        line 349: 0
      LocalVariableTable:
        Start  Length  Slot  Name   Signature
            0      11     0  this   Lorg/scalactic/anyvals/PosFloat;

  public float toRadians();
    descriptor: ()F
    flags: (0x0001) ACC_PUBLIC
    Code:
      stack=2, locals=1, args_size=1
         0: getstatic     #20                 // Field org/scalactic/anyvals/PosFloat$.MODULE$:Lorg/scalactic/anyvals/PosFloat$;
         3: aload_0
         4: invokevirtual #350                // Method value:()F
         7: invokevirtual #61                 // Method org/scalactic/anyvals/PosFloat$.toRadians$extension:(F)F
        10: freturn
      LineNumberTable:
        line 359: 0
      LocalVariableTable:
        Start  Length  Slot  Name   Signature
            0      11     0  this   Lorg/scalactic/anyvals/PosFloat;

  public float toDegrees();
    descriptor: ()F
    flags: (0x0001) ACC_PUBLIC
    Code:
      stack=2, locals=1, args_size=1
         0: getstatic     #20                 // Field org/scalactic/anyvals/PosFloat$.MODULE$:Lorg/scalactic/anyvals/PosFloat$;
         3: aload_0
         4: invokevirtual #350                // Method value:()F
         7: invokevirtual #58                 // Method org/scalactic/anyvals/PosFloat$.toDegrees$extension:(F)F
        10: freturn
      LineNumberTable:
        line 365: 0
      LocalVariableTable:
        Start  Length  Slot  Name   Signature
            0      11     0  this   Lorg/scalactic/anyvals/PosFloat;

  public float ensuringValid(scala.Function1<java.lang.Object, java.lang.Object>);
    descriptor: (Lscala/Function1;)F
    flags: (0x0001) ACC_PUBLIC
    Code:
      stack=3, locals=2, args_size=2
         0: getstatic     #20                 // Field org/scalactic/anyvals/PosFloat$.MODULE$:Lorg/scalactic/anyvals/PosFloat$;
         3: aload_0
         4: invokevirtual #350                // Method value:()F
         7: aload_1
         8: invokevirtual #54                 // Method org/scalactic/anyvals/PosFloat$.ensuringValid$extension:(FLscala/Function1;)F
        11: freturn
      LineNumberTable:
        line 397: 0
      LocalVariableTable:
        Start  Length  Slot  Name   Signature
            0      12     0  this   Lorg/scalactic/anyvals/PosFloat;
            0      12     1     f   Lscala/Function1;
    Signature: #396                         // (Lscala/Function1<Ljava/lang/Object;Ljava/lang/Object;>;)F
    MethodParameters:
      Name                           Flags
      f                              final

  public int round();
    descriptor: ()I
    flags: (0x0001) ACC_PUBLIC
    Code:
      stack=2, locals=1, args_size=1
         0: getstatic     #20                 // Field org/scalactic/anyvals/PosFloat$.MODULE$:Lorg/scalactic/anyvals/PosFloat$;
         3: aload_0
         4: invokevirtual #350                // Method value:()F
         7: invokevirtual #49                 // Method org/scalactic/anyvals/PosFloat$.round$extension:(F)I
        10: ireturn
      LineNumberTable:
        line 407: 0
      LocalVariableTable:
        Start  Length  Slot  Name   Signature
            0      11     0  this   Lorg/scalactic/anyvals/PosFloat;

  public float ceil();
    descriptor: ()F
    flags: (0x0001) ACC_PUBLIC
    Code:
      stack=2, locals=1, args_size=1
         0: getstatic     #20                 // Field org/scalactic/anyvals/PosFloat$.MODULE$:Lorg/scalactic/anyvals/PosFloat$;
         3: aload_0
         4: invokevirtual #350                // Method value:()F
         7: invokevirtual #46                 // Method org/scalactic/anyvals/PosFloat$.ceil$extension:(F)F
        10: freturn
      LineNumberTable:
        line 413: 0
      LocalVariableTable:
        Start  Length  Slot  Name   Signature
            0      11     0  this   Lorg/scalactic/anyvals/PosFloat;

  public float floor();
    descriptor: ()F
    flags: (0x0001) ACC_PUBLIC
    Code:
      stack=2, locals=1, args_size=1
         0: getstatic     #20                 // Field org/scalactic/anyvals/PosFloat$.MODULE$:Lorg/scalactic/anyvals/PosFloat$;
         3: aload_0
         4: invokevirtual #350                // Method value:()F
         7: invokevirtual #43                 // Method org/scalactic/anyvals/PosFloat$.floor$extension:(F)F
        10: freturn
      LineNumberTable:
        line 419: 0
      LocalVariableTable:
        Start  Length  Slot  Name   Signature
            0      11     0  this   Lorg/scalactic/anyvals/PosFloat;

  public float plus(float);
    descriptor: (F)F
    flags: (0x0001) ACC_PUBLIC
    Code:
      stack=3, locals=2, args_size=2
         0: getstatic     #20                 // Field org/scalactic/anyvals/PosFloat$.MODULE$:Lorg/scalactic/anyvals/PosFloat$;
         3: aload_0
         4: invokevirtual #350                // Method value:()F
         7: fload_1
         8: invokevirtual #39                 // Method org/scalactic/anyvals/PosFloat$.plus$extension:(FF)F
        11: freturn
      LineNumberTable:
        line 431: 0
      LocalVariableTable:
        Start  Length  Slot  Name   Signature
            0      12     0  this   Lorg/scalactic/anyvals/PosFloat;
            0      12     1     x   F
    MethodParameters:
      Name                           Flags
      x                              final

  public boolean isPosInfinity();
    descriptor: ()Z
    flags: (0x0001) ACC_PUBLIC
    Code:
      stack=2, locals=1, args_size=1
         0: getstatic     #20                 // Field org/scalactic/anyvals/PosFloat$.MODULE$:Lorg/scalactic/anyvals/PosFloat$;
         3: aload_0
         4: invokevirtual #350                // Method value:()F
         7: invokevirtual #34                 // Method org/scalactic/anyvals/PosFloat$.isPosInfinity$extension:(F)Z
        10: ireturn
      LineNumberTable:
        line 436: 0
      LocalVariableTable:
        Start  Length  Slot  Name   Signature
            0      11     0  this   Lorg/scalactic/anyvals/PosFloat;

  public boolean isFinite();
    descriptor: ()Z
    flags: (0x0001) ACC_PUBLIC
    Code:
      stack=2, locals=1, args_size=1
         0: getstatic     #20                 // Field org/scalactic/anyvals/PosFloat$.MODULE$:Lorg/scalactic/anyvals/PosFloat$;
         3: aload_0
         4: invokevirtual #350                // Method value:()F
         7: invokevirtual #31                 // Method org/scalactic/anyvals/PosFloat$.isFinite$extension:(F)Z
        10: ireturn
      LineNumberTable:
        line 441: 0
      LocalVariableTable:
        Start  Length  Slot  Name   Signature
            0      11     0  this   Lorg/scalactic/anyvals/PosFloat;

  public int hashCode();
    descriptor: ()I
    flags: (0x0001) ACC_PUBLIC
    Code:
      stack=2, locals=1, args_size=1
         0: getstatic     #20                 // Field org/scalactic/anyvals/PosFloat$.MODULE$:Lorg/scalactic/anyvals/PosFloat$;
         3: aload_0
         4: invokevirtual #350                // Method value:()F
         7: invokevirtual #27                 // Method org/scalactic/anyvals/PosFloat$.hashCode$extension:(F)I
        10: ireturn
      LineNumberTable:
        line 147: 0
      LocalVariableTable:
        Start  Length  Slot  Name   Signature
            0      11     0  this   Lorg/scalactic/anyvals/PosFloat;

  public boolean equals(java.lang.Object);
    descriptor: (Ljava/lang/Object;)Z
    flags: (0x0001) ACC_PUBLIC
    Code:
      stack=3, locals=2, args_size=2
         0: getstatic     #20                 // Field org/scalactic/anyvals/PosFloat$.MODULE$:Lorg/scalactic/anyvals/PosFloat$;
         3: aload_0
         4: invokevirtual #350                // Method value:()F
         7: aload_1
         8: invokevirtual #22                 // Method org/scalactic/anyvals/PosFloat$.equals$extension:(FLjava/lang/Object;)Z
        11: ireturn
      LineNumberTable:
        line 147: 0
      LocalVariableTable:
        Start  Length  Slot  Name   Signature
            0      12     0  this   Lorg/scalactic/anyvals/PosFloat;
            0      12     1   x$1   Ljava/lang/Object;
    MethodParameters:
      Name                           Flags
      x$1                            final

  public org.scalactic.anyvals.PosFloat(float);
    descriptor: (F)V
    flags: (0x0001) ACC_PUBLIC
    Code:
      stack=2, locals=2, args_size=2
         0: aload_0
         1: fload_1
         2: putfield      #344                // Field value:F
         5: aload_0
         6: invokespecial #410                // Method java/lang/Object."<init>":()V
         9: return
      LineNumberTable:
        line 147: 0
      LocalVariableTable:
        Start  Length  Slot  Name   Signature
            0      10     0  this   Lorg/scalactic/anyvals/PosFloat;
            0      10     1 value   F
    MethodParameters:
      Name                           Flags
      value                          final
}
SourceFile: "PosFloat.scala"
RuntimeVisibleAnnotations:
  0: #6(#7=s#8)
    scala.reflect.ScalaSignature(
      bytes="\u0006\u0005!-baBAT\u0003S\u0013\u0011q\u0017\u0005\u000b\u0003\u000b\u0004!Q1A\u0005\u0002\u0005\u001d\u0007BCAh\u0001\t\u0005\t\u0015!\u0003\u0002J\"q\u0011\u0011\u001b\u0001\u0005\u0002\u0003\u0005\t\u0011!A\u0005\n\u0005M\u0007bBAn\u0001\u0011\u0005\u0013Q\u001c\u0005\b\u0003k\u0004A\u0011AA|\u0011\u001d\ty\u0010\u0001C\u0001\u0005\u0003AqA!\u0003\u0001\t\u0003\u0011Y\u0001C\u0004\u0003\u0014\u0001!\tA!\u0006\t\u000f\tu\u0001\u0001\"\u0001\u0003 !9!q\u0005\u0001\u0005\u0002\u0005\u001d\u0007b\u0002B\u0015\u0001\u0011\u0005!1\u0006\u0005\b\u0005g\u0001A\u0011\u0001B\u001b\u0011\u001d\u00119\u0004\u0001C\u0001\u0005sAqA!\u0011\u0001\t\u0003\u0011\u0019\u0005C\u0004\u0003J\u0001!\tAa\u0013\t\u000f\t%\u0003\u0001\"\u0001\u0003V!9!\u0011\n\u0001\u0005\u0002\te\u0003b\u0002B%\u0001\u0011\u0005!Q\f\u0005\b\u0005\u0013\u0002A\u0011\u0001B1\u0011\u001d\u0011I\u0005\u0001C\u0001\u0005KBqA!\u0013\u0001\t\u0003\u0011I\u0007C\u0004\u0003n\u0001!\tAa\u001c\t\u000f\t5\u0004\u0001\"\u0001\u0003t!9!Q\u000e\u0001\u0005\u0002\t]\u0004b\u0002B7\u0001\u0011\u0005!1\u0010\u0005\b\u0005[\u0002A\u0011\u0001B@\u0011\u001d\u0011i\u0007\u0001C\u0001\u0005\u0007CqA!\u001c\u0001\t\u0003\u00119\tC\u0004\u0003\f\u0002!\tA!$\t\u000f\t-\u0005\u0001\"\u0001\u0003\u0012\"9!1\u0012\u0001\u0005\u0002\tU\u0005b\u0002BF\u0001\u0011\u0005!\u0011\u0014\u0005\b\u0005\u0017\u0003A\u0011\u0001BO\u0011\u001d\u0011Y\t\u0001C\u0001\u0005CCqAa#\u0001\t\u0003\u0011)\u000bC\u0004\u0003*\u0002!\tAa+\t\u000f\t%\u0006\u0001\"\u0001\u00030\"9!\u0011\u0016\u0001\u0005\u0002\tM\u0006b\u0002BU\u0001\u0011\u0005!q\u0017\u0005\b\u0005S\u0003A\u0011\u0001B^\u0011\u001d\u0011I\u000b\u0001C\u0001\u0005\u007fCqA!+\u0001\t\u0003\u0011\u0019\rC\u0004\u0003B\u0001!\tAa2\t\u000f\t\u0005\u0003\u0001\"\u0001\u0003L\"9!\u0011\t\u0001\u0005\u0002\t=\u0007b\u0002B!\u0001\u0011\u0005!1\u001b\u0005\b\u0005\u0003\u0002A\u0011\u0001Bl\u0011\u001d\u0011\t\u0005\u0001C\u0001\u00057DqA!\u0011\u0001\t\u0003\u0011y\u000eC\u0004\u0003d\u0002!\tA!:\t\u000f\t\r\b\u0001\"\u0001\u0003j\"9!1\u001d\u0001\u0005\u0002\t5\bb\u0002Br\u0001\u0011\u0005!\u0011\u001f\u0005\b\u0005G\u0004A\u0011\u0001B{\u0011\u001d\u0011\u0019\u000f\u0001C\u0001\u0005sDqAa9\u0001\t\u0003\u0011i\u0010C\u0004\u0004\u0002\u0001!\taa\u0001\t\u000f\r\u0005\u0001\u0001\"\u0001\u0004\b!91\u0011\u0001\u0001\u0005\u0002\r-\u0001bBB\u0001\u0001\u0011\u00051q\u0002\u0005\b\u0007\u0003\u0001A\u0011AB\n\u0011\u001d\u0019\t\u0001\u0001C\u0001\u0007/Aqa!\u0001\u0001\t\u0003\u0019Y\u0002C\u0004\u0004 \u0001!\ta!\t\t\u000f\r}\u0001\u0001\"\u0001\u0004&!91q\u0004\u0001\u0005\u0002\r%\u0002bBB\u0010\u0001\u0011\u00051Q\u0006\u0005\b\u0007?\u0001A\u0011AB\u0019\u0011\u001d\u0019y\u0002\u0001C\u0001\u0007kAqaa\b\u0001\t\u0003\u0019I\u0004C\u0004\u0004>\u0001!\taa\u0010\t\u000f\ru\u0002\u0001\"\u0001\u0004D!91Q\b\u0001\u0005\u0002\r\u001d\u0003bBB\u001f\u0001\u0011\u000511\n\u0005\b\u0007{\u0001A\u0011AB(\u0011\u001d\u0019i\u0004\u0001C\u0001\u0007\'Bqa!\u0010\u0001\t\u0003\u00199\u0006C\u0004\u0004\\\u0001!\ta!\u0018\t\u000f\r\r\u0004\u0001\"\u0001\u0004f!91\u0011\u000e\u0001\u0005\u0002\r-\u0004bBB7\u0001\u0011\u0005\u0011q\u0019\u0005\b\u0007_\u0002A\u0011AAd\u0011\u001d\u0019\t\b\u0001C\u0001\u0007gBqaa \u0001\t\u0003\u0019\t\tC\u0004\u0004\n\u0002!\tA!\u000e\t\u000f\r-\u0005\u0001\"\u0001\u0004\u000e\"91Q\u0013\u0001\u0005\u0002\r]\u0005bBBN\u0001\u0011\u000511\u000e\u0005\b\u0007;\u0003A\u0011AB6\u0011%\u0019y\nAA\u0001\n\u0003\u001a\t\u000bC\u0005\u0004$\u0002\t\t\u0011\"\u0011\u0004&\u001eA1\u0011WAU\u0011\u0003\u0019\u0019L\u0002\u0005\u0002(\u0006%\u0006\u0012AB[\u0011\u001d\t\t.\u0018C\u0001\u0007{C\u0011ba0^\u0005\u0004%)A!\u000e\t\u0011\r\u0005W\f)A\u0007\u0003+D\u0011ba1^\u0005\u0004%)A!\u000e\t\u0011\r\u0015W\f)A\u0007\u0003+Dqaa2^\t\u0003\u0019I\rC\u0004\u0004ru#\taa5\t\u000f\r]W\f\"\u0001\u0004Z\"91\u0011^/\u0005\u0002\r-\bb\u0002C\b;\u0012\u0005A\u0011\u0003\u0005\b\tSiF\u0011\u0001C\u0016\u0011\u001d!y%\u0018C\u0001\t#Bq\u0001\"\u0016^\t\u0003!9\u0006\u0003\u0005\u0005fu\u0013I1\u0001C4\u0011\u001d)9!\u0018C\u0002\u000b\u0013Aq!b\u0004^\t\u0007)\t\u0002C\u0004\u0006\u0016u#\u0019!b\u0006\t\u000f\u0015\u0005R\fb\u0001\u0006$!9QqE/\u0005\u0004\u0015%\u0002bBC\u001a;\u0012\rQQ\u0007\u0005\b\u000b\u007fiF1AC!\u0011%)Y%\u0018b\u0001\n\u0007)i\u0005\u0003\u0005\u0006Vu\u0003\u000b\u0011BC(\u0011%)9&\u0018b\u0001\n\u000b\u0011)\u0004\u0003\u0005\u0006Zu\u0003\u000bQBAk\u0011%)Y&\u0018b\u0001\n\u000b\u0011)\u0004\u0003\u0005\u0006^u\u0003\u000bQBAk\u0011%)y&\u0018b\u0001\n\u0003)i\u0005\u0003\u0005\u0006pu\u0003\u000b\u0011BC(\u0011\u001d)\u0019(\u0018C\u0003\u000bkBq!b\u001f^\t\u000b)i\bC\u0004\u0006\u0002v#)!b!\t\u000f\u0015\u001dU\f\"\u0002\u0006\n\"9QQR/\u0005\u0006\u0015=\u0005bBCJ;\u0012\u0015QQ\u0013\u0005\b\u000b3kFQACN\u0011\u001d)y*\u0018C\u0003\u000bCCq!\"*^\t\u000b)9\u000bC\u0004\u0006,v#)!\",\t\u000f\u0015EV\f\"\u0002\u00064\"9Q1X/\u0005\u0006\u0015u\u0006bBC^;\u0012\u0015QQ\u0019\u0005\b\u000bwkFQACg\u0011\u001d)Y,\u0018C\u0003\u000b+Dq!b/^\t\u000b)i\u000eC\u0004\u0006<v#)!\":\t\u000f\u0015mV\f\"\u0002\u0006n\"9QQ_/\u0005\u0006\u0015]\bbBC{;\u0012\u0015Qq \u0005\b\u000bklFQ\u0001D\u0004\u0011\u001d))0\u0018C\u0003\r\u001fAq!\">^\t\u000b19\u0002C\u0004\u0006vv#)Ab\b\t\u000f\u0015UX\f\"\u0002\u0007(!9aqF/\u0005\u0006\u0019E\u0002b\u0002D\u0018;\u0012\u0015a\u0011\b\u0005\b\r_iFQ\u0001D!\u0011\u001d1y#\u0018C\u0003\r\u0013BqAb\f^\t\u000b1\t\u0006C\u0004\u00070u#)A\"\u0017\t\u000f\u0019=R\f\"\u0002\u0007b!9a\u0011N/\u0005\u0006\u0019-\u0004b\u0002D5;\u0012\u0015a1\u000f\u0005\b\rSjFQ\u0001D>\u0011\u001d1I\'\u0018C\u0003\r\u0007CqA\"\u001b^\t\u000b1Y\tC\u0004\u0007ju#)Ab%\t\u000f\u0019%T\f\"\u0002\u0007\u001c\"9Q\u0011W/\u0005\u0006\u0019\r\u0006bBCY;\u0012\u0015a1\u0016\u0005\b\u000bckFQ\u0001DZ\u0011\u001d)\t,\u0018C\u0003\rwCq!\"-^\t\u000b1\u0019\rC\u0004\u00062v#)Ab3\t\u000f\u0015EV\f\"\u0002\u0007T\"9a1\\/\u0005\u0006\u0019u\u0007b\u0002Dn;\u0012\u0015aQ\u001d\u0005\b\r7lFQ\u0001Dw\u0011\u001d1Y.\u0018C\u0003\rkDqAb7^\t\u000b1i\u0010C\u0004\u0007\\v#)a\"\u0002\t\u000f\u0019mW\f\"\u0002\b\u000e!9qQC/\u0005\u0006\u001d]\u0001bBD\u000b;\u0012\u0015qq\u0004\u0005\b\u000f+iFQAD\u0014\u0011\u001d9)\"\u0018C\u0003\u000f_Aqa\"\u0006^\t\u000b99\u0004C\u0004\b\u0016u#)ab\u0010\t\u000f\u001dUQ\f\"\u0002\bH!9qqJ/\u0005\u0006\u001dE\u0003bBD(;\u0012\u0015q\u0011\f\u0005\b\u000f\u001fjFQAD1\u0011\u001d9y%\u0018C\u0003\u000fSBqab\u0014^\t\u000b9\t\bC\u0004\bPu#)a\"\u001f\t\u000f\u001d=S\f\"\u0002\b\u0002\"9q\u0011R/\u0005\u0006\u001d-\u0005bBDE;\u0012\u0015q1\u0013\u0005\b\u000f\u0013kFQADN\u0011\u001d9I)\u0018C\u0003\u000fGCqa\"#^\t\u000b9Y\u000bC\u0004\b\nv#)ab-\t\u000f\u001d%U\f\"\u0002\b<\"9q1Y/\u0005\u0006\u001d\u0015\u0007bBDg;\u0012\u0015qq\u001a\u0005\b\u000f/lFQADm\u0011\u001d9i.\u0018C\u0003\u000f?Dqab9^\t\u000b9)\u000fC\u0004\bjv#)ab;\t\u000f\u001dMX\f\"\u0002\bv\"9q\u0011`/\u0005\u0006\u001dm\bbBD\u0000;\u0012\u0015\u0001\u0012\u0001\u0005\b\u0011\u000biFQ\u0001E\u0004\u0011\u001dAy!\u0018C\u0003\u0011#Aq\u0001#\u0006^\t\u000bA9\u0002C\u0005\t\u001cu\u000b\t\u0011\"\u0002\t\u001e!I\u0001\u0012E/\u0002\u0002\u0013\u0015\u00012\u0005\u0002\t!>\u001ch\t\\8bi*!\u00111VAW\u0003\u001d\tg.\u001f<bYNTA!a,\u00022\u0006I1oY1mC\u000e$\u0018n\u0019\u0006\u0003\u0003g\u000b1a\u001c:h\u0007\u0001\u00192\u0001AA]!\u0011\tY,!1\u000e\u0005\u0005u&BAA`\u0003\u0015\u00198-\u00197b\u0013\u0011\t\u0019-!0\u0003\r\u0005s\u0017PV1m\u0003\u00151\u0018\r\\;f+\t\tI\r\u0005\u0003\u0002<\u0006-\u0017\u0002BAg\u0003{\u0013QA\u00127pCR\faA^1mk\u0016\u0004\u0013A\u0002\u001fj]&$h\b\u0006\u0003\u0002V\u0006e\u0007cAAl\u00015\u0011\u0011\u0011\u0016\u0005\b\u0003\u000b\u001c\u0001\u0019AAe\u0003!!xn\u0015;sS:<GCAAp!\u0011\t\t/a<\u000f\t\u0005\r\u00181\u001e\t\u0005\u0003K\fi,\u0004\u0002\u0002h*!\u0011\u0011^A[\u0003\u0019a$o\\8u}%!\u0011Q^A_\u0003\u0019\u0001&/\u001a3fM&!\u0011\u0011_Az\u0005\u0019\u0019FO]5oO*!\u0011Q^A_\u0003\u0019!xNQ=uKV\u0011\u0011\u0011 \t\u0005\u0003w\u000bY0\u0003\u0003\u0002~\u0006u&\u0001\u0002\"zi\u0016\fq\u0001^8TQ>\u0014H/\u0006\u0002\u0003\u0004A!\u00111\u0018B\u0003\u0013\u0011\u00119!!0\u0003\u000bMCwN\u001d;\u0002\rQ|7\t[1s+\t\u0011i\u0001\u0005\u0003\u0002<\n=\u0011\u0002\u0002B\t\u0003{\u0013Aa\u00115be\u0006)Ao\\%oiV\u0011!q\u0003\t\u0005\u0003w\u0013I\"\u0003\u0003\u0003\u001c\u0005u&aA%oi\u00061Ao\u001c\'p]\u001e,\"A!\t\u0011\t\u0005m&1E\u0005\u0005\u0005K\tiL\u0001\u0003M_:<\u0017a\u0002;p\r2|\u0017\r^\u0001\ti>$u.\u001e2mKV\u0011!Q\u0006\t\u0005\u0003w\u0013y#\u0003\u0003\u00032\u0005u&A\u0002#pk\ndW-A\u0006v]\u0006\u0014\u0018p\u0018\u0013qYV\u001cXCAAk\u00031)h.\u0019:z?\u0012j\u0017N\\;t+\t\u0011Y\u0004\u0005\u0003\u0002X\nu\u0012\u0002\u0002B \u0003S\u0013\u0001BT3h\r2|\u0017\r^\u0001\u0006IAdWo\u001d\u000b\u0005\u0003?\u0014)\u0005C\u0004\u0003H9\u0001\r!a8\u0002\u0003a\fQ\u0001\n7fgN$BA!\u0014\u0003TA!\u00111\u0018B(\u0013\u0011\u0011\t&!0\u0003\u000f\t{w\u000e\\3b]\"9!qI\bA\u0002\u0005eH\u0003\u0002B\'\u0005/BqAa\u0012\u0011\u0001\u0004\u0011\u0019\u0001\u0006\u0003\u0003N\tm\u0003b\u0002B$#\u0001\u0007!Q\u0002\u000b\u0005\u0005\u001b\u0012y\u0006C\u0004\u0003HI\u0001\rAa\u0006\u0015\t\t5#1\r\u0005\b\u0005\u000f\u001a\u0002\u0019\u0001B\u0011)\u0011\u0011iEa\u001a\t\u000f\t\u001dC\u00031\u0001\u0002JR!!Q\nB6\u0011\u001d\u00119%\u0006a\u0001\u0005[\t\u0001\u0002\n7fgN$S-\u001d\u000b\u0005\u0005\u001b\u0012\t\bC\u0004\u0003HY\u0001\r!!?\u0015\t\t5#Q\u000f\u0005\b\u0005\u000f:\u0002\u0019\u0001B\u0002)\u0011\u0011iE!\u001f\t\u000f\t\u001d\u0003\u00041\u0001\u0003\u000eQ!!Q\nB?\u0011\u001d\u00119%\u0007a\u0001\u0005/!BA!\u0014\u0003\u0002\"9!q\t\u000eA\u0002\t\u0005B\u0003\u0002B\'\u0005\u000bCqAa\u0012\u001c\u0001\u0004\tI\r\u0006\u0003\u0003N\t%\u0005b\u0002B$9\u0001\u0007!QF\u0001\tI\u001d\u0014X-\u0019;feR!!Q\nBH\u0011\u001d\u00119%\ba\u0001\u0003s$BA!\u0014\u0003\u0014\"9!q\t\u0010A\u0002\t\rA\u0003\u0002B\'\u0005/CqAa\u0012 \u0001\u0004\u0011i\u0001\u0006\u0003\u0003N\tm\u0005b\u0002B$A\u0001\u0007!q\u0003\u000b\u0005\u0005\u001b\u0012y\nC\u0004\u0003H\u0005\u0002\rA!\t\u0015\t\t5#1\u0015\u0005\b\u0005\u000f\u0012\u0003\u0019AAe)\u0011\u0011iEa*\t\u000f\t\u001d3\u00051\u0001\u0003.\u0005YAe\u001a:fCR,\'\u000fJ3r)\u0011\u0011iE!,\t\u000f\t\u001dC\u00051\u0001\u0002zR!!Q\nBY\u0011\u001d\u00119%\na\u0001\u0005\u0007!BA!\u0014\u00036\"9!q\t\u0014A\u0002\t5A\u0003\u0002B\'\u0005sCqAa\u0012(\u0001\u0004\u00119\u0002\u0006\u0003\u0003N\tu\u0006b\u0002B$Q\u0001\u0007!\u0011\u0005\u000b\u0005\u0005\u001b\u0012\t\rC\u0004\u0003H%\u0002\r!!3\u0015\t\t5#Q\u0019\u0005\b\u0005\u000fR\u0003\u0019\u0001B\u0017)\u0011\tIM!3\t\u000f\t\u001d3\u00061\u0001\u0002zR!\u0011\u0011\u001aBg\u0011\u001d\u00119\u0005\fa\u0001\u0005\u0007!B!!3\u0003R\"9!qI\u0017A\u0002\t5A\u0003BAe\u0005+DqAa\u0012/\u0001\u0004\u00119\u0002\u0006\u0003\u0002J\ne\u0007b\u0002B$_\u0001\u0007!\u0011\u0005\u000b\u0005\u0003\u0013\u0014i\u000eC\u0004\u0003HA\u0002\r!!3\u0015\t\t5\"\u0011\u001d\u0005\b\u0005\u000f\n\u0004\u0019\u0001B\u0017\u0003\u0019!S.\u001b8vgR!\u0011\u0011\u001aBt\u0011\u001d\u00119E\ra\u0001\u0003s$B!!3\u0003l\"9!qI\u001aA\u0002\t\rA\u0003BAe\u0005_DqAa\u00125\u0001\u0004\u0011i\u0001\u0006\u0003\u0002J\nM\bb\u0002B$k\u0001\u0007!q\u0003\u000b\u0005\u0003\u0013\u00149\u0010C\u0004\u0003HY\u0002\rA!\t\u0015\t\u0005%\'1 \u0005\b\u0005\u000f:\u0004\u0019AAe)\u0011\u0011iCa@\t\u000f\t\u001d\u0003\b1\u0001\u0003.\u00051A\u0005^5nKN$B!!3\u0004\u0006!9!qI\u001dA\u0002\u0005eH\u0003BAe\u0007\u0013AqAa\u0012;\u0001\u0004\u0011\u0019\u0001\u0006\u0003\u0002J\u000e5\u0001b\u0002B$w\u0001\u0007!Q\u0002\u000b\u0005\u0003\u0013\u001c\t\u0002C\u0004\u0003Hq\u0002\rAa\u0006\u0015\t\u0005%7Q\u0003\u0005\b\u0005\u000fj\u0004\u0019\u0001B\u0011)\u0011\tIm!\u0007\t\u000f\t\u001dc\b1\u0001\u0002JR!!QFB\u000f\u0011\u001d\u00119e\u0010a\u0001\u0005[\tA\u0001\n3jmR!\u0011\u0011ZB\u0012\u0011\u001d\u00119\u0005\u0011a\u0001\u0003s$B!!3\u0004(!9!qI!A\u0002\t\rA\u0003BAe\u0007WAqAa\u0012C\u0001\u0004\u0011i\u0001\u0006\u0003\u0002J\u000e=\u0002b\u0002B$\u0007\u0002\u0007!q\u0003\u000b\u0005\u0003\u0013\u001c\u0019\u0004C\u0004\u0003H\u0011\u0003\rA!\t\u0015\t\u0005%7q\u0007\u0005\b\u0005\u000f*\u0005\u0019AAe)\u0011\u0011ica\u000f\t\u000f\t\u001dc\t1\u0001\u0003.\u0005AA\u0005]3sG\u0016tG\u000f\u0006\u0003\u0002J\u000e\u0005\u0003b\u0002B$\u000f\u0002\u0007\u0011\u0011 \u000b\u0005\u0003\u0013\u001c)\u0005C\u0004\u0003H!\u0003\rAa\u0001\u0015\t\u0005%7\u0011\n\u0005\b\u0005\u000fJ\u0005\u0019\u0001B\u0007)\u0011\tIm!\u0014\t\u000f\t\u001d#\n1\u0001\u0003\u0018Q!\u0011\u0011ZB)\u0011\u001d\u00119e\u0013a\u0001\u0005C!B!!3\u0004V!9!q\t\'A\u0002\u0005%G\u0003\u0002B\u0017\u00073BqAa\u0012N\u0001\u0004\u0011i#A\u0002nCb$B!!6\u0004`!91\u0011\r(A\u0002\u0005U\u0017\u0001\u0002;iCR\f1!\\5o)\u0011\t)na\u001a\t\u000f\r\u0005t\n1\u0001\u0002V\u00069\u0011n],i_2,WC\u0001B\'\u0003%!xNU1eS\u0006t7/A\u0005u_\u0012+wM]3fg\u0006iQM\\:ve&twMV1mS\u0012$B!!6\u0004v!91qO*A\u0002\re\u0014!\u00014\u0011\u0011\u0005m61PAe\u0003\u0013LAa! \u0002>\nIa)\u001e8di&|g.M\u0001\u0006e>,h\u000eZ\u000b\u0003\u0007\u0007\u0003B!a6\u0004\u0006&!1qQAU\u0005\u001d\u0001vn\u001d.J]R\fAaY3jY\u0006)a\r\\8peV\u00111q\u0012\t\u0005\u0003/\u001c\t*\u0003\u0003\u0004\u0014\u0006%&!\u0003)pgj3En\\1u\u0003\u0011\u0001H.^:\u0015\t\u0005U7\u0011\u0014\u0005\b\u0005\u000f:\u0006\u0019ABH\u00035I7\u000fU8t\u0013:4\u0017N\\5us\u0006A\u0011n\u001d$j]&$X-\u0001\u0005iCND7i\u001c3f)\t\u00119\"\u0001\u0004fcV\fGn\u001d\u000b\u0005\u0005\u001b\u001a9\u000bC\u0005\u0004*n\u000b\t\u00111\u0001\u0004,\u0006\u0019\u0001\u0010J\u0019\u0011\t\u0005m6QV\u0005\u0005\u0007_\u000biLA\u0002B]f\f\u0001\u0002U8t\r2|\u0017\r\u001e\t\u0004\u0003/l6cA/\u00048B!\u00111XB]\u0013\u0011\u0019Y,!0\u0003\r\u0005s\u0017PU3g)\t\u0019\u0019,\u0001\u0005NCb4\u0016\r\\;f\u0003%i\u0015\r\u001f,bYV,\u0007%\u0001\u0005NS:4\u0016\r\\;f\u0003%i\u0015N\u001c,bYV,\u0007%\u0001\u0003ge>lG\u0003BBf\u0007#\u0004b!a/\u0004N\u0006U\u0017\u0002BBh\u0003{\u0013aa\u00149uS>t\u0007bBAcG\u0002\u0007\u0011\u0011\u001a\u000b\u0005\u0003+\u001c)\u000eC\u0004\u0002F\u0012\u0004\r!!3\u0002\u0017Q\u0014\u00180\u001b8h-\u0006d\u0017\u000e\u001a\u000b\u0005\u00077\u001c9\u000f\u0005\u0004\u0004^\u000e\r\u0018Q[\u0007\u0003\u0007?TAa!9\u0002>\u0006!Q\u000f^5m\u0013\u0011\u0019)oa8\u0003\u0007Q\u0013\u0018\u0010C\u0004\u0002F\u0016\u0004\r!!3\u0002\u0015A\f7o](s\u000b2\u001cX-\u0006\u0003\u0004n\u000euH\u0003BBx\t\u001b!Ba!=\u0005\nA111_B{\u0007sl!!!,\n\t\r]\u0018Q\u0016\u0002\u000b-\u0006d\u0017\u000eZ1uS>t\u0007\u0003BB~\u0007{d\u0001\u0001B\u0004\u0004\u0000\u001a\u0014\r\u0001\"\u0001\u0003\u0003\u0015\u000bB\u0001b\u0001\u0004,B!\u00111\u0018C\u0003\u0013\u0011!9!!0\u0003\u000f9{G\u000f[5oO\"91q\u000f4A\u0002\u0011-\u0001\u0003CA^\u0007w\nIm!?\t\u000f\u0005\u0015g\r1\u0001\u0002J\u0006Qqm\\8e\u001fJ,En]3\u0016\t\u0011MAq\u0004\u000b\u0005\t+!9\u0003\u0006\u0003\u0005\u0018\u0011\r\u0002\u0003CBz\t3\t)\u000e\"\b\n\t\u0011m\u0011Q\u0016\u0002\u0003\u001fJ\u0004Baa?\u0005 \u00119A\u0011E4C\u0002\u0011\u0005!!\u0001\"\t\u000f\r]t\r1\u0001\u0005&AA\u00111XB>\u0003\u0013$i\u0002C\u0004\u0002F\u001e\u0004\r!!3\u0002\u0017ILw\r\u001b;Pe\u0016c7/Z\u000b\u0005\t[!)\u0005\u0006\u0003\u00050\u00115C\u0003\u0002C\u0019\t\u0013\u0002\u0002\u0002b\r\u0005>\u0011\r\u0013Q\u001b\b\u0005\tk!ID\u0004\u0003\u0002f\u0012]\u0012BAA`\u0013\u0011!Y$!0\u0002\u000fA\f7m[1hK&!Aq\bC!\u0005\u0019)\u0015\u000e\u001e5fe*!A1HA_!\u0011\u0019Y\u0010\"\u0012\u0005\u000f\u0011\u001d\u0003N1\u0001\u0005\u0002\t\tA\nC\u0004\u0004x!\u0004\r\u0001b\u0013\u0011\u0011\u0005m61PAe\t\u0007Bq!!2i\u0001\u0004\tI-A\u0004jgZ\u000bG.\u001b3\u0015\t\t5C1\u000b\u0005\b\u0003\u000bL\u0007\u0019AAe\u0003)1\'o\\7Pe\u0016c7/\u001a\u000b\u0007\u0003+$I\u0006b\u0017\t\u000f\u0005\u0015\'\u000e1\u0001\u0002J\"AAQ\f6\u0005\u0002\u0004!y&A\u0004eK\u001a\fW\u000f\u001c;\u0011\r\u0005mF\u0011MAk\u0013\u0011!\u0019\'!0\u0003\u0011q\u0012\u0017P\\1nKz\nQ!\u00199qYf$B!!6\u0005j!9\u0011QY6A\u0002\u0005%\u0007&B6\u0005n\u0011\u0005\u0005\u0003\u0002C8\t{j!\u0001\"\u001d\u000b\t\u0011MDQO\u0001\tS:$XM\u001d8bY*!Aq\u000fC=\u0003\u0019i\u0017m\u0019:pg*!A1PA_\u0003\u001d\u0011XM\u001a7fGRLA\u0001b \u0005r\tIQ.Y2s_&k\u0007\u000f\\\u0019\u0012?\u0011\rEQ\u0011CE\t7#Y\u000bb.\u0005J\u0012e7\u0002A\u0019\bI\u0011\r\u0015Q\u0017CD\u0003\u0015i\u0017m\u0019:pc\u001d1B1\u0011CF\t\'\u000bT!\nCG\t\u001f{!\u0001b$\"\u0005\u0011E\u0015aC7bGJ|WI\\4j]\u0016\fT!\nCK\t/{!\u0001b&\"\u0005\u0011e\u0015!\n<8]A\u0002\u0003&[7qY\u0016lWM\u001c;fI\u0002Jg\u000eI*dC2\f\u0007E\r\u00182c9\u0002T&\u0014\u001d*c\u001d1B1\u0011CO\tK\u000bT!\nCP\tC{!\u0001\")\"\u0005\u0011\r\u0016\u0001C5t\u0005VtG\r\\32\u000b\u0015\"9\u000b\"+\u0010\u0005\u0011%\u0016$\u0001\u00012\u000fY!\u0019\t\",\u00056F*Q\u0005b,\u00052>\u0011A\u0011W\u0011\u0003\tg\u000b!\"[:CY\u0006\u001c7NY8yc\u0015)Cq\u0015CUc\u001d1B1\u0011C]\t\u0003\fT!\nC^\t{{!\u0001\"0\"\u0005\u0011}\u0016!C2mCN\u001ch*Y7fc\u0015)C1\u0019Cc\u001f\t!)-\t\u0002\u0005H\u0006!sN]4/g\u000e\fG.Y2uS\u000et\u0013M\\=wC2\u001ch\u0006U8t\r2|\u0017\r^\'bGJ|G%M\u0004\u0017\t\u0007#Y\rb52\u000b\u0015\"i\rb4\u0010\u0005\u0011=\u0017E\u0001Ci\u0003)iW\r\u001e5pI:\u000bW.Z\u0019\u0006K\u0011UGq[\b\u0003\t/\f#\u0001\"\u001a2\u000fY!\u0019\tb7\u0005dF*Q\u0005\"8\u0005`>\u0011Aq\\\u0011\u0003\tC\f\u0011b]5h]\u0006$XO]32\u0013}!\u0019\t\":\u0005t\u0012u\u0018g\u0002\u0013\u0005\u0004\u0012\u001dH\u0011^\u0005\u0005\tS$Y/\u0001\u0003MSN$(\u0002\u0002Cw\t_\f\u0011\"[7nkR\f\'\r\\3\u000b\t\u0011E\u0018QX\u0001\u000bG>dG.Z2uS>t\u0017gB\u0010\u0005\u0004\u0012UHq_\u0019\bI\u0011\rEq\u001dCuc\u0015)C\u0011 C~\u001f\t!Y0H\u0001\u0000d\u001dyB1\u0011C\u0000\u000b\u0003\tt\u0001\nCB\tO$I/M\u0003&\u000b\u0007))a\u0004\u0002\u0006\u0006u\ta@\u0001\u0007xS\u0012,g\u000eV8GY>\fG\u000f\u0006\u0003\u0002J\u0016-\u0001bBC\u0007Y\u0002\u0007\u0011Q[\u0001\u0004a>\u001c\u0018!D<jI\u0016tGk\u001c#pk\ndW\r\u0006\u0003\u0003.\u0015M\u0001bBC\u0007[\u0002\u0007\u0011Q[\u0001\u0011o&$WM\u001c+p!>\u001cHi\\;cY\u0016$B!\"\u0007\u0006 A!\u0011q[C\u000e\u0013\u0011)i\"!+\u0003\u0013A{7\u000fR8vE2,\u0007bBC\u0007]\u0002\u0007\u0011Q[\u0001\u0011o&$WM\u001c+p!>\u001c(L\u00127pCR$Baa$\u0006&!9QQB8A\u0002\u0005U\u0017!E<jI\u0016tGk\u001c)pgj#u.\u001e2mKR!Q1FC\u0019!\u0011\t9.\"\f\n\t\u0015=\u0012\u0011\u0016\u0002\u000b!>\u001c(\fR8vE2,\u0007bBC\u0007a\u0002\u0007\u0011Q[\u0001\u0014o&$WM\u001c+p\u001d>t\',\u001a:p\r2|\u0017\r\u001e\u000b\u0005\u000bo)i\u0004\u0005\u0003\u0002X\u0016e\u0012\u0002BC\u001e\u0003S\u0013ABT8o5\u0016\u0014xN\u00127pCRDq!\"\u0004r\u0001\u0004\t).\u0001\u000bxS\u0012,g\u000eV8O_:TVM]8E_V\u0014G.\u001a\u000b\u0005\u000b\u0007*I\u0005\u0005\u0003\u0002X\u0016\u0015\u0013\u0002BC$\u0003S\u0013QBT8o5\u0016\u0014x\u000eR8vE2,\u0007bBC\u0007e\u0002\u0007\u0011Q[\u0001\t_J$WM]5oOV\u0011Qq\n\t\u0007\tg)\t&!6\n\t\u0015MC\u0011\t\u0002\t\u001fJ$WM]5oO\u0006IqN\u001d3fe&tw\rI\u0001\u0011!>\u001c\u0018\u000e^5wK&sg-\u001b8jif\f\u0011\u0003U8tSRLg/Z%oM&t\u0017\u000e^=!\u0003Ai\u0015N\u001c)pg&$\u0018N^3WC2,X-A\tNS:\u0004vn]5uSZ,g+\u00197vK\u0002\n1\u0002]8t\r2|\u0017\r^(sI\":\u00110b\u0019\u0006j\u0015-\u0004\u0003BA^\u000bKJA!b\u001a\u0002>\nQA-\u001a9sK\u000e\fG/\u001a3\u0002\u000f5,7o]1hK\u0006\u0012QQN\u0001\u00022QCW\r\t4pe6,\'\u000f\\=!S6\u0004H.[2ji\u0002\u0002xn\u001d$m_\u0006$xJ\u001d3!M&,G\u000e\u001a\u0011iCN\u0004#-Z3oA\u0011,\u0007O]3dCR,G\rI1oI\u0002:\u0018\u000e\u001c7!E\u0016\u0004#/Z7pm\u0016$\u0007%\u001b8!C\u00022W\u000f^;sK\u00022XM]:j_:\u0004sN\u001a\u0011TG\u0006d\u0017\rV3ti:\u0002\u0003\u000b\\3bg\u0016\u0004So]3!i\",\u0007e\u001c:eKJLgn\u001a\u0011gS\u0016dG\rI5ogR,\u0017\r\u001a\u0018\u0002\u0019A|7O\u00127pCR|%\u000f\u001a\u0011)\u000fi,\u0019\'\"\u001b\u0006l\u0005\u0011Bo\\*ue&tw\rJ3yi\u0016t7/[8o)\u0011\ti.b\u001e\t\u000f\u0015e4\u00101\u0001\u0002V\u0006)A\u0005\u001e5jg\u0006\u0001Bo\u001c\"zi\u0016$S\r\u001f;f]NLwN\u001c\u000b\u0005\u0003s,y\bC\u0004\u0006zq\u0004\r!!6\u0002#Q|7\u000b[8si\u0012*\u0007\u0010^3og&|g\u000e\u0006\u0003\u0003\u0004\u0015\u0015\u0005bBC={\u0002\u0007\u0011Q[\u0001\u0011i>\u001c\u0005.\u0019:%Kb$XM\\:j_:$BA!\u0004\u0006\f\"9Q\u0011\u0010@A\u0002\u0005U\u0017a\u0004;p\u0013:$H%\u001a=uK:\u001c\u0018n\u001c8\u0015\t\t]Q\u0011\u0013\u0005\b\u000bsz\b\u0019AAk\u0003A!x\u000eT8oO\u0012*\u0007\u0010^3og&|g\u000e\u0006\u0003\u0003\"\u0015]\u0005\u0002CC=\u0003\u0003\u0001\r!!6\u0002#Q|g\t\\8bi\u0012*\u0007\u0010^3og&|g\u000e\u0006\u0003\u0002J\u0016u\u0005\u0002CC=\u0003\u0007\u0001\r!!6\u0002%Q|Gi\\;cY\u0016$S\r\u001f;f]NLwN\u001c\u000b\u0005\u0005[)\u0019\u000b\u0003\u0005\u0006z\u0005\u0015\u0001\u0019AAk\u0003U)h.\u0019:z?\u0012\u0002H.^:%Kb$XM\\:j_:$B!!6\u0006*\"AQ\u0011PA\u0004\u0001\u0004\t).\u0001\fv]\u0006\u0014\u0018p\u0018\u0013nS:,8\u000fJ3yi\u0016t7/[8o)\u0011\u0011Y$b,\t\u0011\u0015e\u0014\u0011\u0002a\u0001\u0003+\fq\u0002\n9mkN$S\r\u001f;f]NLwN\u001c\u000b\u0005\u000bk+I\f\u0006\u0003\u0002`\u0016]\u0006\u0002\u0003B$\u0003\u0017\u0001\r!a8\t\u0011\u0015e\u00141\u0002a\u0001\u0003+\fq\u0002\n7fgN$S\r\u001f;f]NLwN\u001c\u000b\u0005\u000b\u007f+\u0019\r\u0006\u0003\u0003N\u0015\u0005\u0007\u0002\u0003B$\u0003\u001b\u0001\r!!?\t\u0011\u0015e\u0014Q\u0002a\u0001\u0003+$B!b2\u0006LR!!QJCe\u0011!\u00119%a\u0004A\u0002\t\r\u0001\u0002CC=\u0003\u001f\u0001\r!!6\u0015\t\u0015=W1\u001b\u000b\u0005\u0005\u001b*\t\u000e\u0003\u0005\u0003H\u0005E\u0001\u0019\u0001B\u0007\u0011!)I(!\u0005A\u0002\u0005UG\u0003BCl\u000b7$BA!\u0014\u0006Z\"A!qIA\n\u0001\u0004\u00119\u0002\u0003\u0005\u0006z\u0005M\u0001\u0019AAk)\u0011)y.b9\u0015\t\t5S\u0011\u001d\u0005\t\u0005\u000f\n)\u00021\u0001\u0003\"!AQ\u0011PA\u000b\u0001\u0004\t)\u000e\u0006\u0003\u0006h\u0016-H\u0003\u0002B\'\u000bSD\u0001Ba\u0012\u0002\u0018\u0001\u0007\u0011\u0011\u001a\u0005\t\u000bs\n9\u00021\u0001\u0002VR!Qq^Cz)\u0011\u0011i%\"=\t\u0011\t\u001d\u0013\u0011\u0004a\u0001\u0005[A\u0001\"\"\u001f\u0002\u001a\u0001\u0007\u0011Q[\u0001\u0013I1,7o\u001d\u0013fc\u0012*\u0007\u0010^3og&|g\u000e\u0006\u0003\u0006z\u0016uH\u0003\u0002B\'\u000bwD\u0001Ba\u0012\u0002\u001c\u0001\u0007\u0011\u0011 \u0005\t\u000bs\nY\u00021\u0001\u0002VR!a\u0011\u0001D\u0003)\u0011\u0011iEb\u0001\t\u0011\t\u001d\u0013Q\u0004a\u0001\u0005\u0007A\u0001\"\"\u001f\u0002\u001e\u0001\u0007\u0011Q\u001b\u000b\u0005\r\u00131i\u0001\u0006\u0003\u0003N\u0019-\u0001\u0002\u0003B$\u0003?\u0001\rA!\u0004\t\u0011\u0015e\u0014q\u0004a\u0001\u0003+$BA\"\u0005\u0007\u0016Q!!Q\nD\n\u0011!\u00119%!\tA\u0002\t]\u0001\u0002CC=\u0003C\u0001\r!!6\u0015\t\u0019eaQ\u0004\u000b\u0005\u0005\u001b2Y\u0002\u0003\u0005\u0003H\u0005\r\u0002\u0019\u0001B\u0011\u0011!)I(a\tA\u0002\u0005UG\u0003\u0002D\u0011\rK!BA!\u0014\u0007$!A!qIA\u0013\u0001\u0004\tI\r\u0003\u0005\u0006z\u0005\u0015\u0002\u0019AAk)\u00111IC\"\f\u0015\t\t5c1\u0006\u0005\t\u0005\u000f\n9\u00031\u0001\u0003.!AQ\u0011PA\u0014\u0001\u0004\t).\u0001\n%OJ,\u0017\r^3sI\u0015DH/\u001a8tS>tG\u0003\u0002D\u001a\ro!BA!\u0014\u00076!A!qIA\u0015\u0001\u0004\tI\u0010\u0003\u0005\u0006z\u0005%\u0002\u0019AAk)\u00111YDb\u0010\u0015\t\t5cQ\b\u0005\t\u0005\u000f\nY\u00031\u0001\u0003\u0004!AQ\u0011PA\u0016\u0001\u0004\t)\u000e\u0006\u0003\u0007D\u0019\u001dC\u0003\u0002B\'\r\u000bB\u0001Ba\u0012\u0002.\u0001\u0007!Q\u0002\u0005\t\u000bs\ni\u00031\u0001\u0002VR!a1\nD()\u0011\u0011iE\"\u0014\t\u0011\t\u001d\u0013q\u0006a\u0001\u0005/A\u0001\"\"\u001f\u00020\u0001\u0007\u0011Q\u001b\u000b\u0005\r\'29\u0006\u0006\u0003\u0003N\u0019U\u0003\u0002\u0003B$\u0003c\u0001\rA!\t\t\u0011\u0015e\u0014\u0011\u0007a\u0001\u0003+$BAb\u0017\u0007`Q!!Q\nD/\u0011!\u00119%a\rA\u0002\u0005%\u0007\u0002CC=\u0003g\u0001\r!!6\u0015\t\u0019\rdq\r\u000b\u0005\u0005\u001b2)\u0007\u0003\u0005\u0003H\u0005U\u0002\u0019\u0001B\u0017\u0011!)I(!\u000eA\u0002\u0005U\u0017!\u0006\u0013he\u0016\fG/\u001a:%KF$S\r\u001f;f]NLwN\u001c\u000b\u0005\r[2\t\b\u0006\u0003\u0003N\u0019=\u0004\u0002\u0003B$\u0003o\u0001\r!!?\t\u0011\u0015e\u0014q\u0007a\u0001\u0003+$BA\"\u001e\u0007zQ!!Q\nD<\u0011!\u00119%!\u000fA\u0002\t\r\u0001\u0002CC=\u0003s\u0001\r!!6\u0015\t\u0019ud\u0011\u0011\u000b\u0005\u0005\u001b2y\b\u0003\u0005\u0003H\u0005m\u0002\u0019\u0001B\u0007\u0011!)I(a\u000fA\u0002\u0005UG\u0003\u0002DC\r\u0013#BA!\u0014\u0007\b\"A!qIA\u001f\u0001\u0004\u00119\u0002\u0003\u0005\u0006z\u0005u\u0002\u0019AAk)\u00111iI\"%\u0015\t\t5cq\u0012\u0005\t\u0005\u000f\ny\u00041\u0001\u0003\"!AQ\u0011PA \u0001\u0004\t)\u000e\u0006\u0003\u0007\u0016\u001aeE\u0003\u0002B\'\r/C\u0001Ba\u0012\u0002B\u0001\u0007\u0011\u0011\u001a\u0005\t\u000bs\n\t\u00051\u0001\u0002VR!aQ\u0014DQ)\u0011\u0011iEb(\t\u0011\t\u001d\u00131\ta\u0001\u0005[A\u0001\"\"\u001f\u0002D\u0001\u0007\u0011Q\u001b\u000b\u0005\rK3I\u000b\u0006\u0003\u0002J\u001a\u001d\u0006\u0002\u0003B$\u0003\u000b\u0002\r!!?\t\u0011\u0015e\u0014Q\ta\u0001\u0003+$BA\",\u00072R!\u0011\u0011\u001aDX\u0011!\u00119%a\u0012A\u0002\t\r\u0001\u0002CC=\u0003\u000f\u0002\r!!6\u0015\t\u0019Uf\u0011\u0018\u000b\u0005\u0003\u001349\f\u0003\u0005\u0003H\u0005%\u0003\u0019\u0001B\u0007\u0011!)I(!\u0013A\u0002\u0005UG\u0003\u0002D_\r\u0003$B!!3\u0007@\"A!qIA&\u0001\u0004\u00119\u0002\u0003\u0005\u0006z\u0005-\u0003\u0019AAk)\u00111)M\"3\u0015\t\u0005%gq\u0019\u0005\t\u0005\u000f\ni\u00051\u0001\u0003\"!AQ\u0011PA\'\u0001\u0004\t)\u000e\u0006\u0003\u0007N\u001aEG\u0003BAe\r\u001fD\u0001Ba\u0012\u0002P\u0001\u0007\u0011\u0011\u001a\u0005\t\u000bs\ny\u00051\u0001\u0002VR!aQ\u001bDm)\u0011\u0011iCb6\t\u0011\t\u001d\u0013\u0011\u000ba\u0001\u0005[A\u0001\"\"\u001f\u0002R\u0001\u0007\u0011Q[\u0001\u0011I5Lg.^:%Kb$XM\\:j_:$BAb8\u0007dR!\u0011\u0011\u001aDq\u0011!\u00119%a\u0015A\u0002\u0005e\b\u0002CC=\u0003\'\u0002\r!!6\u0015\t\u0019\u001dh1\u001e\u000b\u0005\u0003\u00134I\u000f\u0003\u0005\u0003H\u0005U\u0003\u0019\u0001B\u0002\u0011!)I(!\u0016A\u0002\u0005UG\u0003\u0002Dx\rg$B!!3\u0007r\"A!qIA,\u0001\u0004\u0011i\u0001\u0003\u0005\u0006z\u0005]\u0003\u0019AAk)\u001119Pb?\u0015\t\u0005%g\u0011 \u0005\t\u0005\u000f\nI\u00061\u0001\u0003\u0018!AQ\u0011PA-\u0001\u0004\t)\u000e\u0006\u0003\u0007\u0000\u001e\rA\u0003BAe\u000f\u0003A\u0001Ba\u0012\u0002\\\u0001\u0007!\u0011\u0005\u0005\t\u000bs\nY\u00061\u0001\u0002VR!qqAD\u0006)\u0011\tIm\"\u0003\t\u0011\t\u001d\u0013Q\fa\u0001\u0003\u0013D\u0001\"\"\u001f\u0002^\u0001\u0007\u0011Q\u001b\u000b\u0005\u000f\u001f9\u0019\u0002\u0006\u0003\u0003.\u001dE\u0001\u0002\u0003B$\u0003?\u0002\rA!\f\t\u0011\u0015e\u0014q\fa\u0001\u0003+\f\u0001\u0003\n;j[\u0016\u001cH%\u001a=uK:\u001c\u0018n\u001c8\u0015\t\u001deqQ\u0004\u000b\u0005\u0003\u0013<Y\u0002\u0003\u0005\u0003H\u0005\u0005\u0004\u0019AA}\u0011!)I(!\u0019A\u0002\u0005UG\u0003BD\u0011\u000fK!B!!3\b$!A!qIA2\u0001\u0004\u0011\u0019\u0001\u0003\u0005\u0006z\u0005\r\u0004\u0019AAk)\u00119Ic\"\f\u0015\t\u0005%w1\u0006\u0005\t\u0005\u000f\n)\u00071\u0001\u0003\u000e!AQ\u0011PA3\u0001\u0004\t)\u000e\u0006\u0003\b2\u001dUB\u0003BAe\u000fgA\u0001Ba\u0012\u0002h\u0001\u0007!q\u0003\u0005\t\u000bs\n9\u00071\u0001\u0002VR!q\u0011HD\u001f)\u0011\tImb\u000f\t\u0011\t\u001d\u0013\u0011\u000ea\u0001\u0005CA\u0001\"\"\u001f\u0002j\u0001\u0007\u0011Q\u001b\u000b\u0005\u000f\u0003:)\u0005\u0006\u0003\u0002J\u001e\r\u0003\u0002\u0003B$\u0003W\u0002\r!!3\t\u0011\u0015e\u00141\u000ea\u0001\u0003+$Ba\"\u0013\bNQ!!QFD&\u0011!\u00119%!\u001cA\u0002\t5\u0002\u0002CC=\u0003[\u0002\r!!6\u0002\u001d\u0011\"\u0017N\u001e\u0013fqR,gn]5p]R!q1KD,)\u0011\tIm\"\u0016\t\u0011\t\u001d\u0013q\u000ea\u0001\u0003sD\u0001\"\"\u001f\u0002p\u0001\u0007\u0011Q\u001b\u000b\u0005\u000f7:y\u0006\u0006\u0003\u0002J\u001eu\u0003\u0002\u0003B$\u0003c\u0002\rAa\u0001\t\u0011\u0015e\u0014\u0011\u000fa\u0001\u0003+$Bab\u0019\bhQ!\u0011\u0011ZD3\u0011!\u00119%a\u001dA\u0002\t5\u0001\u0002CC=\u0003g\u0002\r!!6\u0015\t\u001d-tq\u000e\u000b\u0005\u0003\u0013<i\u0007\u0003\u0005\u0003H\u0005U\u0004\u0019\u0001B\f\u0011!)I(!\u001eA\u0002\u0005UG\u0003BD:\u000fo\"B!!3\bv!A!qIA<\u0001\u0004\u0011\t\u0003\u0003\u0005\u0006z\u0005]\u0004\u0019AAk)\u00119Yhb \u0015\t\u0005%wQ\u0010\u0005\t\u0005\u000f\nI\b1\u0001\u0002J\"AQ\u0011PA=\u0001\u0004\t)\u000e\u0006\u0003\b\u0004\u001e\u001dE\u0003\u0002B\u0017\u000f\u000bC\u0001Ba\u0012\u0002|\u0001\u0007!Q\u0006\u0005\t\u000bs\nY\b1\u0001\u0002V\u0006\u0011B\u0005]3sG\u0016tG\u000fJ3yi\u0016t7/[8o)\u00119ii\"%\u0015\t\u0005%wq\u0012\u0005\t\u0005\u000f\ni\b1\u0001\u0002z\"AQ\u0011PA?\u0001\u0004\t)\u000e\u0006\u0003\b\u0016\u001eeE\u0003BAe\u000f/C\u0001Ba\u0012\u0002\u0000\u0001\u0007!1\u0001\u0005\t\u000bs\ny\b1\u0001\u0002VR!qQTDQ)\u0011\tImb(\t\u0011\t\u001d\u0013\u0011\u0011a\u0001\u0005\u001bA\u0001\"\"\u001f\u0002\u0002\u0002\u0007\u0011Q\u001b\u000b\u0005\u000fK;I\u000b\u0006\u0003\u0002J\u001e\u001d\u0006\u0002\u0003B$\u0003\u0007\u0003\rAa\u0006\t\u0011\u0015e\u00141\u0011a\u0001\u0003+$Ba\",\b2R!\u0011\u0011ZDX\u0011!\u00119%!\"A\u0002\t\u0005\u0002\u0002CC=\u0003\u000b\u0003\r!!6\u0015\t\u001dUv\u0011\u0018\u000b\u0005\u0003\u0013<9\f\u0003\u0005\u0003H\u0005\u001d\u0005\u0019AAe\u0011!)I(a\"A\u0002\u0005UG\u0003BD_\u000f\u0003$BA!\f\b@\"A!qIAE\u0001\u0004\u0011i\u0003\u0003\u0005\u0006z\u0005%\u0005\u0019AAk\u00035i\u0017\r\u001f\u0013fqR,gn]5p]R!qqYDf)\u0011\t)n\"3\t\u0011\r\u0005\u00141\u0012a\u0001\u0003+D\u0001\"\"\u001f\u0002\f\u0002\u0007\u0011Q[\u0001\u000e[&tG%\u001a=uK:\u001c\u0018n\u001c8\u0015\t\u001dEwQ\u001b\u000b\u0005\u0003+<\u0019\u000e\u0003\u0005\u0004b\u00055\u0005\u0019AAk\u0011!)I(!$A\u0002\u0005U\u0017!E5t/\"|G.\u001a\u0013fqR,gn]5p]R!!QJDn\u0011!)I(a$A\u0002\u0005U\u0017a\u0005;p%\u0006$\u0017.\u00198tI\u0015DH/\u001a8tS>tG\u0003BAe\u000fCD\u0001\"\"\u001f\u0002\u0012\u0002\u0007\u0011Q[\u0001\u0014i>$Um\u001a:fKN$S\r\u001f;f]NLwN\u001c\u000b\u0005\u0003\u0013<9\u000f\u0003\u0005\u0006z\u0005M\u0005\u0019AAk\u0003])gn];sS:<g+\u00197jI\u0012*\u0007\u0010^3og&|g\u000e\u0006\u0003\bn\u001eEH\u0003BAk\u000f_D\u0001ba\u001e\u0002\u0016\u0002\u00071\u0011\u0010\u0005\t\u000bs\n)\n1\u0001\u0002V\u0006y!o\\;oI\u0012*\u0007\u0010^3og&|g\u000e\u0006\u0003\u0004\u0004\u001e]\b\u0002CC=\u0003/\u0003\r!!6\u0002\u001d\r,\u0017\u000e\u001c\u0013fqR,gn]5p]R!\u0011Q[D\u007f\u0011!)I(!\'A\u0002\u0005U\u0017a\u00044m_>\u0014H%\u001a=uK:\u001c\u0018n\u001c8\u0015\t\r=\u00052\u0001\u0005\t\u000bs\nY\n1\u0001\u0002V\u0006q\u0001\u000f\\;tI\u0015DH/\u001a8tS>tG\u0003\u0002E\u0005\u0011\u001b!B!!6\t\f!A!qIAO\u0001\u0004\u0019y\t\u0003\u0005\u0006z\u0005u\u0005\u0019AAk\u0003]I7\u000fU8t\u0013:4\u0017N\\5us\u0012*\u0007\u0010^3og&|g\u000e\u0006\u0003\u0003N!M\u0001\u0002CC=\u0003?\u0003\r!!6\u0002%%\u001ch)\u001b8ji\u0016$S\r\u001f;f]NLwN\u001c\u000b\u0005\u0005\u001bBI\u0002\u0003\u0005\u0006z\u0005\u0005\u0006\u0019AAk\u0003IA\u0017m\u001d5D_\u0012,G%\u001a=uK:\u001c\u0018n\u001c8\u0015\t\r\u0005\u0006r\u0004\u0005\t\u000bs\n\u0019\u000b1\u0001\u0002V\u0006\u0001R-];bYN$S\r\u001f;f]NLwN\u001c\u000b\u0005\u0011KAI\u0003\u0006\u0003\u0003N!\u001d\u0002BCBU\u0003K\u000b\t\u00111\u0001\u0004,\"AQ\u0011PAS\u0001\u0004\t)\u000e"
    )
  ScalaInlineInfo: length = 0x1C6 (unknown attribute)
   01 01 00 5A 01 82 01 7A 01 01 82 01 7C 01 01 82
   01 7F 01 01 82 00 29 01 01 82 01 7D 01 01 82 01
   7E 01 01 82 01 7B 01 01 78 01 71 01 01 78 01 73
   01 01 78 01 76 01 01 78 00 1D 01 01 78 01 74 01
   01 78 01 75 01 01 78 01 72 01 01 79 01 71 01 01
   79 01 73 01 01 79 01 76 01 01 79 00 1D 01 01 79
   01 74 01 01 79 01 75 01 01 79 01 72 01 01 70 01
   71 01 01 70 01 73 01 01 70 01 76 01 01 70 00 1D
   01 01 70 01 74 01 01 70 01 75 01 01 70 01 72 01
   01 77 01 71 01 01 77 01 73 01 01 77 01 76 01 01
   77 00 1D 01 01 77 01 74 01 01 77 01 75 01 01 77
   01 72 01 01 80 01 7A 01 01 80 01 7C 01 01 80 01
   7F 01 01 80 00 29 01 01 80 01 7D 01 01 80 01 7E
   01 01 80 01 7B 01 01 83 01 7A 01 01 83 01 7C 01
   01 83 01 7F 01 01 83 00 29 01 01 83 01 7D 01 01
   83 01 7E 01 01 83 01 7B 01 01 6E 01 7A 01 01 6E
   01 7C 01 01 6E 01 7F 01 01 6E 00 29 01 01 6E 01
   7D 01 01 6E 01 7E 01 01 6E 01 6F 01 01 6E 01 7B
   01 01 81 01 7A 01 01 81 01 7C 01 01 81 01 7F 01
   01 81 00 29 01 01 81 01 7D 01 01 81 01 7E 01 01
   81 01 7B 01 01 96 01 97 01 01 8E 01 10 01 01 8A
   01 8B 01 01 94 01 95 01 01 8F 01 10 01 01 93 01
   66 01 01 92 01 87 01 01 91 01 87 01 01 86 01 87
   01 01 84 00 29 01 01 85 00 29 01 01 90 00 29 01
   01 8D 01 66 01 01 5F 01 60 01 01 63 01 64 01 01
   89 01 10 01 01 6A 01 6B 01 01 69 01 10 01 01 65
   01 66 01 01 67 01 68 01 01 88 01 10 01 01 61 01
   62 01 01 5B 01 5C 01 01 6D 01 10 01 01 6C 01 10
   01 00 09 01 10 01
  ScalaSig: length = 0x3 (unknown attribute)
   05 02 00
