Classfile /Users/mw/Projects/slang-braindump/.jar/jar11/assemble/slang-braindump/assemble/content/org/scalactic/source/TypeInfoMacro.class
  Last modified May 29, 2022; size 1759 bytes
  SHA-256 checksum 772fc8cdd8144a65a1caa713bf02d8e16fb59ec516a82fb2dd4863c9bd9eb8b7
  Compiled from "TypeInfoMacro.scala"
public final class org.scalactic.source.TypeInfoMacro
  minor version: 0
  major version: 52
  flags: (0x0031) ACC_PUBLIC, ACC_FINAL, ACC_SUPER
  this_class: #2                          // org/scalactic/source/TypeInfoMacro
  super_class: #4                         // java/lang/Object
  interfaces: 0, fields: 0, methods: 1, attributes: 4
Constant pool:
   #1 = Utf8               org/scalactic/source/TypeInfoMacro
   #2 = Class              #1             // org/scalactic/source/TypeInfoMacro
   #3 = Utf8               java/lang/Object
   #4 = Class              #3             // java/lang/Object
   #5 = Utf8               TypeInfoMacro.scala
   #6 = Utf8               Lscala/reflect/ScalaSignature;
   #7 = Utf8               bytes
   #8 = Utf8               \u0006\u0005\u0011<Q\u0001B\u0003\t\u000211QAD\u0003\t\u0002=AQAF\u0001\u0005\u0002]AQ\u0001G\u0001\u0005\u0002e\tQ\u0002V=qK&sgm\\\'bGJ|\'B\u0001\u0004\b\u0003\u0019\u0019x.\u001e:dK*\u0011\u0001\"C\u0001\ng\u000e\fG.Y2uS\u000eT\u0011AC\u0001\u0004_J<7\u0001\u0001\t\u0003\u001b\u0005i\u0011!\u0002\u0002\u000e)f\u0004X-\u00138g_6\u000b7M]8\u0014\u0005\u0005\u0001\u0002CA\t\u0015\u001b\u0005\u0011\"\"A\n\u0002\u000bM\u001c\u0017\r\\1\n\u0005U\u0011\"AB!osJ+g-\u0001\u0004=S:LGO\u0010\u000b\u0002\u0019\u0005Yq-\u001a8UsB,\u0017J\u001c4p+\tQr\u000b\u0006\u0002\u001ceQ\u0011A$\u0018\u0019\u0003;\t\u00022A\b)W\u001d\ty2J\u0004\u0002!\u0013B\u0011\u0011E\t\u0007\u0001\t%\u00193!!A\u0001\u0002\u000b\u0005AE\u0001\tpo:,\'OU3qC&\u0014h\u0006^=qKF\u0011Q\u0005\u000b\t\u0003#\u0019J!a\n\n\u0003\u000f9{G\u000f[5oOJ\u0019\u0011&\f$\u0007\t)\u0002\u0001\u0001\u000b\u0002\ryI,g-\u001b8f[\u0016tGO\u0010\u0006\u0003Y-\ta\u0001\u0010:p_Rt\u0004c\u0001\u00180c5\tq!\u0003\u00021\u000f\t\u0001R*Y2s_>;h.\u001a:SKB\f\u0017N\u001d\b\u0003CIBQaM\u0002A\u0002Q\nqaY8oi\u0016DH\u000f\u0005\u00026\u0007:\u0011a\u0007\u0011\b\u0003our!\u0001O\u001e\u000f\u0005eRT\"A\u0016\n\u0003MI!\u0001\u0010\n\u0002\u000fI,g\r\\3di&\u0011ahP\u0001\u0007[\u0006\u001c\'o\\:\u000b\u0005q\u0012\u0012BA!C\u0003\u001d\u0001\u0018mY6bO\u0016T!AP \n\u0005\u0011+%aB\"p]R,\u0007\u0010\u001e\u0006\u0003\u0003\n\u0003\"!E$\n\u0005!\u0013\"!C*j]\u001edW\r^8o\u0013\tQu&A\u0001d\u0013\taU*\u0001\u0005v]&4XM]:f\u0013\t!eJ\u0003\u0002P\u0005\u0006A!\r\\1dW\n|\u00070\u0003\u0002R%\n!Q\t\u001f9s\u0013\t\u0019FKA\u0003FqB\u00148O\u0003\u0002V\u007f\u0005\u0019\u0011\r]5\u0011\u0005\u0005:F!\u0002-\u0004\u0005\u0004I&!\u0001+\u0012\u0005\u0015R\u0006CA\t\\\u0013\ta&CA\u0002B]fDqAX\u0002\u0002\u0002\u0003\u000fq,\u0001\u0006fm&$WM\\2fIE\u00022!\r1W\u0013\t\t\'MA\u0006XK\u0006\\G+\u001f9f)\u0006<\u0017BA2C\u0005\u001d\tE.[1tKN\u0004
   #9 = Utf8               scala/reflect/api/Exprs$Expr
  #10 = Class              #9             // scala/reflect/api/Exprs$Expr
  #11 = Utf8               scala/reflect/api/Exprs
  #12 = Class              #11            // scala/reflect/api/Exprs
  #13 = Utf8               Expr
  #14 = Utf8               scala/reflect/api/TypeTags$WeakTypeTag
  #15 = Class              #14            // scala/reflect/api/TypeTags$WeakTypeTag
  #16 = Utf8               scala/reflect/api/TypeTags
  #17 = Class              #16            // scala/reflect/api/TypeTags
  #18 = Utf8               WeakTypeTag
  #19 = Utf8               genTypeInfo
  #20 = Utf8               (Lscala/reflect/macros/whitebox/Context;Lscala/reflect/api/TypeTags$WeakTypeTag;)Lscala/reflect/api/Exprs$Expr;
  #21 = Utf8               <T:Ljava/lang/Object;>(Lscala/reflect/macros/whitebox/Context;Lscala/reflect/api/TypeTags$WeakTypeTag<TT;>;)Lscala/reflect/api/Exprs$Expr<TT;>;
  #22 = Utf8               context
  #23 = Utf8               evidence$1
  #24 = Utf8               org/scalactic/source/TypeInfoMacro$
  #25 = Class              #24            // org/scalactic/source/TypeInfoMacro$
  #26 = Utf8               MODULE$
  #27 = Utf8               Lorg/scalactic/source/TypeInfoMacro$;
  #28 = NameAndType        #26:#27        // MODULE$:Lorg/scalactic/source/TypeInfoMacro$;
  #29 = Fieldref           #25.#28        // org/scalactic/source/TypeInfoMacro$.MODULE$:Lorg/scalactic/source/TypeInfoMacro$;
  #30 = NameAndType        #19:#20        // genTypeInfo:(Lscala/reflect/macros/whitebox/Context;Lscala/reflect/api/TypeTags$WeakTypeTag;)Lscala/reflect/api/Exprs$Expr;
  #31 = Methodref          #25.#30        // org/scalactic/source/TypeInfoMacro$.genTypeInfo:(Lscala/reflect/macros/whitebox/Context;Lscala/reflect/api/TypeTags$WeakTypeTag;)Lscala/reflect/api/Exprs$Expr;
  #32 = Utf8               Lscala/reflect/macros/whitebox/Context;
  #33 = Utf8               Lscala/reflect/api/TypeTags$WeakTypeTag;
  #34 = Utf8               Code
  #35 = Utf8               LocalVariableTable
  #36 = Utf8               Signature
  #37 = Utf8               MethodParameters
  #38 = Utf8               InnerClasses
  #39 = Utf8               SourceFile
  #40 = Utf8               RuntimeVisibleAnnotations
  #41 = Utf8               ScalaSig
{
  public static <T extends java.lang.Object> scala.reflect.api.Exprs$Expr<T> genTypeInfo(scala.reflect.macros.whitebox.Context, scala.reflect.api.TypeTags$WeakTypeTag<T>);
    descriptor: (Lscala/reflect/macros/whitebox/Context;Lscala/reflect/api/TypeTags$WeakTypeTag;)Lscala/reflect/api/Exprs$Expr;
    flags: (0x0009) ACC_PUBLIC, ACC_STATIC
    Code:
      stack=3, locals=2, args_size=2
         0: getstatic     #29                 // Field org/scalactic/source/TypeInfoMacro$.MODULE$:Lorg/scalactic/source/TypeInfoMacro$;
         3: aload_0
         4: aload_1
         5: invokevirtual #31                 // Method org/scalactic/source/TypeInfoMacro$.genTypeInfo:(Lscala/reflect/macros/whitebox/Context;Lscala/reflect/api/TypeTags$WeakTypeTag;)Lscala/reflect/api/Exprs$Expr;
         8: areturn
      LocalVariableTable:
        Start  Length  Slot  Name   Signature
            0       9     0 context   Lscala/reflect/macros/whitebox/Context;
            0       9     1 evidence$1   Lscala/reflect/api/TypeTags$WeakTypeTag;
    Signature: #21                          // <T:Ljava/lang/Object;>(Lscala/reflect/macros/whitebox/Context;Lscala/reflect/api/TypeTags$WeakTypeTag<TT;>;)Lscala/reflect/api/Exprs$Expr<TT;>;
    MethodParameters:
      Name                           Flags
      context                        final
      evidence$1                     final
}
InnerClasses:
  public #13= #10 of #12;                 // Expr=class scala/reflect/api/Exprs$Expr of class scala/reflect/api/Exprs
  public #18= #15 of #17;                 // WeakTypeTag=class scala/reflect/api/TypeTags$WeakTypeTag of class scala/reflect/api/TypeTags
SourceFile: "TypeInfoMacro.scala"
RuntimeVisibleAnnotations:
  0: #6(#7=s#8)
    scala.reflect.ScalaSignature(
      bytes="\u0006\u0005\u0011<Q\u0001B\u0003\t\u000211QAD\u0003\t\u0002=AQAF\u0001\u0005\u0002]AQ\u0001G\u0001\u0005\u0002e\tQ\u0002V=qK&sgm\\\'bGJ|\'B\u0001\u0004\b\u0003\u0019\u0019x.\u001e:dK*\u0011\u0001\"C\u0001\ng\u000e\fG.Y2uS\u000eT\u0011AC\u0001\u0004_J<7\u0001\u0001\t\u0003\u001b\u0005i\u0011!\u0002\u0002\u000e)f\u0004X-\u00138g_6\u000b7M]8\u0014\u0005\u0005\u0001\u0002CA\t\u0015\u001b\u0005\u0011\"\"A\n\u0002\u000bM\u001c\u0017\r\\1\n\u0005U\u0011\"AB!osJ+g-\u0001\u0004=S:LGO\u0010\u000b\u0002\u0019\u0005Yq-\u001a8UsB,\u0017J\u001c4p+\tQr\u000b\u0006\u0002\u001ceQ\u0011A$\u0018\u0019\u0003;\t\u00022A\b)W\u001d\ty2J\u0004\u0002!\u0013B\u0011\u0011E\t\u0007\u0001\t%\u00193!!A\u0001\u0002\u000b\u0005AE\u0001\tpo:,\'OU3qC&\u0014h\u0006^=qKF\u0011Q\u0005\u000b\t\u0003#\u0019J!a\n\n\u0003\u000f9{G\u000f[5oOJ\u0019\u0011&\f$\u0007\t)\u0002\u0001\u0001\u000b\u0002\ryI,g-\u001b8f[\u0016tGO\u0010\u0006\u0003Y-\ta\u0001\u0010:p_Rt\u0004c\u0001\u00180c5\tq!\u0003\u00021\u000f\t\u0001R*Y2s_>;h.\u001a:SKB\f\u0017N\u001d\b\u0003CIBQaM\u0002A\u0002Q\nqaY8oi\u0016DH\u000f\u0005\u00026\u0007:\u0011a\u0007\u0011\b\u0003our!\u0001O\u001e\u000f\u0005eRT\"A\u0016\n\u0003MI!\u0001\u0010\n\u0002\u000fI,g\r\\3di&\u0011ahP\u0001\u0007[\u0006\u001c\'o\\:\u000b\u0005q\u0012\u0012BA!C\u0003\u001d\u0001\u0018mY6bO\u0016T!AP \n\u0005\u0011+%aB\"p]R,\u0007\u0010\u001e\u0006\u0003\u0003\n\u0003\"!E$\n\u0005!\u0013\"!C*j]\u001edW\r^8o\u0013\tQu&A\u0001d\u0013\taU*\u0001\u0005v]&4XM]:f\u0013\t!eJ\u0003\u0002P\u0005\u0006A!\r\\1dW\n|\u00070\u0003\u0002R%\n!Q\t\u001f9s\u0013\t\u0019FKA\u0003FqB\u00148O\u0003\u0002V\u007f\u0005\u0019\u0011\r]5\u0011\u0005\u0005:F!\u0002-\u0004\u0005\u0004I&!\u0001+\u0012\u0005\u0015R\u0006CA\t\\\u0013\ta&CA\u0002B]fDqAX\u0002\u0002\u0002\u0003\u000fq,\u0001\u0006fm&$WM\\2fIE\u00022!\r1W\u0013\t\t\'MA\u0006XK\u0006\\G+\u001f9f)\u0006<\u0017BA2C\u0005\u001d\tE.[1tKN\u0004"
    )
  ScalaSig: length = 0x3 (unknown attribute)
   05 02 00
