Classfile /Users/mw/Projects/slang-braindump/.jar/jar8/assemble/slang-braindump/assemble/content/argonaut/ACursors.class
  Last modified May 29, 2022; size 1355 bytes
  SHA-256 checksum 83f2e169bf27896893d7666631741697c8a2a9ae492a73c09705ca2ad1e64065
  Compiled from "ACursor.scala"
public interface argonaut.ACursors
  minor version: 0
  major version: 52
  flags: (0x0601) ACC_PUBLIC, ACC_INTERFACE, ACC_ABSTRACT
  this_class: #2                          // argonaut/ACursors
  super_class: #4                         // java/lang/Object
  interfaces: 0, fields: 0, methods: 5, attributes: 4
Constant pool:
   #1 = Utf8               argonaut/ACursors
   #2 = Class              #1             // argonaut/ACursors
   #3 = Utf8               java/lang/Object
   #4 = Class              #3             // java/lang/Object
   #5 = Utf8               ACursor.scala
   #6 = Utf8               Lscala/reflect/ScalaSignature;
   #7 = Utf8               bytes
   #8 = Utf8               \u0006\u0005\t2q\u0001B\u0003\u0011\u0002\u0007\u0005\u0001\u0002C\u0003\u0010\u0001\u0011\u0005\u0001\u0003C\u0003\u0015\u0001\u0011\u0005Q\u0003C\u0003 \u0001\u0011\u0005\u0001E\u0001\u0005B\u0007V\u00148o\u001c:t\u0015\u00051\u0011\u0001C1sO>t\u0017-\u001e;\u0004\u0001M\u0011\u0001!\u0003\t\u0003\u00155i\u0011a\u0003\u0006\u0002\u0019\u0005)1oY1mC&\u0011ab\u0003\u0002\u0007\u0003:L(+\u001a4\u0002\r\u0011Jg.\u001b;%)\u0005\t\u0002C\u0001\u0006\u0013\u0013\t\u00192B\u0001\u0003V]&$\u0018!C8l\u0003\u000e+(o]8s)\t1\"\u0004\u0005\u0002\u001815\tQ!\u0003\u0002\u001a\u000b\t9\u0011iQ;sg>\u0014\b\"B\u000e\u0003\u0001\u0004a\u0012AB2veN|\'\u000f\u0005\u0002\u0018;%\u0011a$\u0002\u0002\b\u0011\u000e+(o]8s\u0003-1\u0017-\u001b7B\u0007V\u00148o\u001c:\u0015\u0005Y\t\u0003\"B\u000e\u0004\u0001\u0004a\u0002
   #9 = Utf8               okACursor$
  #10 = Utf8               (Largonaut/ACursors;Largonaut/HCursor;)Largonaut/ACursor;
  #11 = Utf8               $this
  #12 = Utf8               cursor
  #13 = Utf8               okACursor
  #14 = Utf8               (Largonaut/HCursor;)Largonaut/ACursor;
  #15 = NameAndType        #13:#14        // okACursor:(Largonaut/HCursor;)Largonaut/ACursor;
  #16 = InterfaceMethodref #2.#15         // argonaut/ACursors.okACursor:(Largonaut/HCursor;)Largonaut/ACursor;
  #17 = Utf8               Largonaut/ACursors;
  #18 = Utf8               Largonaut/HCursor;
  #19 = Utf8               argonaut/ACursor$
  #20 = Class              #19            // argonaut/ACursor$
  #21 = Utf8               MODULE$
  #22 = Utf8               Largonaut/ACursor$;
  #23 = NameAndType        #21:#22        // MODULE$:Largonaut/ACursor$;
  #24 = Fieldref           #20.#23        // argonaut/ACursor$.MODULE$:Largonaut/ACursor$;
  #25 = Utf8               ok
  #26 = NameAndType        #25:#14        // ok:(Largonaut/HCursor;)Largonaut/ACursor;
  #27 = Methodref          #20.#26        // argonaut/ACursor$.ok:(Largonaut/HCursor;)Largonaut/ACursor;
  #28 = Utf8               this
  #29 = Utf8               failACursor$
  #30 = Utf8               failACursor
  #31 = NameAndType        #30:#14        // failACursor:(Largonaut/HCursor;)Largonaut/ACursor;
  #32 = InterfaceMethodref #2.#31         // argonaut/ACursors.failACursor:(Largonaut/HCursor;)Largonaut/ACursor;
  #33 = Utf8               fail
  #34 = NameAndType        #33:#14        // fail:(Largonaut/HCursor;)Largonaut/ACursor;
  #35 = Methodref          #20.#34        // argonaut/ACursor$.fail:(Largonaut/HCursor;)Largonaut/ACursor;
  #36 = Utf8               $init$
  #37 = Utf8               (Largonaut/ACursors;)V
  #38 = Utf8               Code
  #39 = Utf8               LineNumberTable
  #40 = Utf8               LocalVariableTable
  #41 = Utf8               MethodParameters
  #42 = Utf8               SourceFile
  #43 = Utf8               RuntimeVisibleAnnotations
  #44 = Utf8               ScalaInlineInfo
  #45 = Utf8               ScalaSig
{
  public static argonaut.ACursor okACursor$(argonaut.ACursors, argonaut.HCursor);
    descriptor: (Largonaut/ACursors;Largonaut/HCursor;)Largonaut/ACursor;
    flags: (0x1009) ACC_PUBLIC, ACC_STATIC, ACC_SYNTHETIC
    Code:
      stack=2, locals=2, args_size=2
         0: aload_0
         1: aload_1
         2: invokespecial #16                 // InterfaceMethod okACursor:(Largonaut/HCursor;)Largonaut/ACursor;
         5: areturn
      LineNumberTable:
        line 266: 0
      LocalVariableTable:
        Start  Length  Slot  Name   Signature
            0       6     0 $this   Largonaut/ACursors;
            0       6     1 cursor   Largonaut/HCursor;
    MethodParameters:
      Name                           Flags
      $this                          final synthetic
      cursor                         final

  public default argonaut.ACursor okACursor(argonaut.HCursor);
    descriptor: (Largonaut/HCursor;)Largonaut/ACursor;
    flags: (0x0001) ACC_PUBLIC
    Code:
      stack=2, locals=2, args_size=2
         0: getstatic     #24                 // Field argonaut/ACursor$.MODULE$:Largonaut/ACursor$;
         3: aload_1
         4: invokevirtual #27                 // Method argonaut/ACursor$.ok:(Largonaut/HCursor;)Largonaut/ACursor;
         7: areturn
      LineNumberTable:
        line 267: 0
      LocalVariableTable:
        Start  Length  Slot  Name   Signature
            0       8     0  this   Largonaut/ACursors;
            0       8     1 cursor   Largonaut/HCursor;
    MethodParameters:
      Name                           Flags
      cursor                         final

  public static argonaut.ACursor failACursor$(argonaut.ACursors, argonaut.HCursor);
    descriptor: (Largonaut/ACursors;Largonaut/HCursor;)Largonaut/ACursor;
    flags: (0x1009) ACC_PUBLIC, ACC_STATIC, ACC_SYNTHETIC
    Code:
      stack=2, locals=2, args_size=2
         0: aload_0
         1: aload_1
         2: invokespecial #32                 // InterfaceMethod failACursor:(Largonaut/HCursor;)Largonaut/ACursor;
         5: areturn
      LineNumberTable:
        line 269: 0
      LocalVariableTable:
        Start  Length  Slot  Name   Signature
            0       6     0 $this   Largonaut/ACursors;
            0       6     1 cursor   Largonaut/HCursor;
    MethodParameters:
      Name                           Flags
      $this                          final synthetic
      cursor                         final

  public default argonaut.ACursor failACursor(argonaut.HCursor);
    descriptor: (Largonaut/HCursor;)Largonaut/ACursor;
    flags: (0x0001) ACC_PUBLIC
    Code:
      stack=2, locals=2, args_size=2
         0: getstatic     #24                 // Field argonaut/ACursor$.MODULE$:Largonaut/ACursor$;
         3: aload_1
         4: invokevirtual #35                 // Method argonaut/ACursor$.fail:(Largonaut/HCursor;)Largonaut/ACursor;
         7: areturn
      LineNumberTable:
        line 270: 0
      LocalVariableTable:
        Start  Length  Slot  Name   Signature
            0       8     0  this   Largonaut/ACursors;
            0       8     1 cursor   Largonaut/HCursor;
    MethodParameters:
      Name                           Flags
      cursor                         final

  public static void $init$(argonaut.ACursors);
    descriptor: (Largonaut/ACursors;)V
    flags: (0x0009) ACC_PUBLIC, ACC_STATIC
    Code:
      stack=0, locals=1, args_size=1
         0: return
      LineNumberTable:
        line 265: 0
      LocalVariableTable:
        Start  Length  Slot  Name   Signature
            0       1     0 $this   Largonaut/ACursors;
    MethodParameters:
      Name                           Flags
      $this                          final synthetic
}
SourceFile: "ACursor.scala"
RuntimeVisibleAnnotations:
  0: #6(#7=s#8)
    scala.reflect.ScalaSignature(
      bytes="\u0006\u0005\t2q\u0001B\u0003\u0011\u0002\u0007\u0005\u0001\u0002C\u0003\u0010\u0001\u0011\u0005\u0001\u0003C\u0003\u0015\u0001\u0011\u0005Q\u0003C\u0003 \u0001\u0011\u0005\u0001E\u0001\u0005B\u0007V\u00148o\u001c:t\u0015\u00051\u0011\u0001C1sO>t\u0017-\u001e;\u0004\u0001M\u0011\u0001!\u0003\t\u0003\u00155i\u0011a\u0003\u0006\u0002\u0019\u0005)1oY1mC&\u0011ab\u0003\u0002\u0007\u0003:L(+\u001a4\u0002\r\u0011Jg.\u001b;%)\u0005\t\u0002C\u0001\u0006\u0013\u0013\t\u00192B\u0001\u0003V]&$\u0018!C8l\u0003\u000e+(o]8s)\t1\"\u0004\u0005\u0002\u001815\tQ!\u0003\u0002\u001a\u000b\t9\u0011iQ;sg>\u0014\b\"B\u000e\u0003\u0001\u0004a\u0012AB2veN|\'\u000f\u0005\u0002\u0018;%\u0011a$\u0002\u0002\b\u0011\u000e+(o]8s\u0003-1\u0017-\u001b7B\u0007V\u00148o\u001c:\u0015\u0005Y\t\u0003\"B\u000e\u0004\u0001\u0004a\u0002"
    )
  ScalaInlineInfo: length = 0x1D (unknown attribute)
   01 00 00 05 00 24 00 25 01 00 1E 00 0E 00 00 1D
   00 0A 01 00 0D 00 0E 00 00 09 00 0A 01
  ScalaSig: length = 0x3 (unknown attribute)
   05 02 00
