Classfile /Users/mw/Projects/slang-braindump/.jar/jar8/assemble/slang-braindump/assemble/content/argonaut/CObject$.class
  Last modified May 29, 2022; size 2696 bytes
  SHA-256 checksum 8b52d4aa371e655e73f733f3db9d8f444a63912e1cc1ccc1a2cff709520a0c03
  Compiled from "Cursor.scala"
public final class argonaut.CObject$ extends scala.runtime.AbstractFunction4<argonaut.Cursor, java.lang.Object, argonaut.JsonObject, scala.Tuple2<java.lang.String, argonaut.Json>, argonaut.CObject> implements java.io.Serializable
  minor version: 0
  major version: 52
  flags: (0x0031) ACC_PUBLIC, ACC_FINAL, ACC_SUPER
  this_class: #2                          // argonaut/CObject$
  super_class: #5                         // scala/runtime/AbstractFunction4
  interfaces: 1, fields: 1, methods: 7, attributes: 4
Constant pool:
    #1 = Utf8               argonaut/CObject$
    #2 = Class              #1            // argonaut/CObject$
    #3 = Utf8               Lscala/runtime/AbstractFunction4<Largonaut/Cursor;Ljava/lang/Object;Largonaut/JsonObject;Lscala/Tuple2<Ljava/lang/String;Largonaut/Json;>;Largonaut/CObject;>;Ljava/io/Serializable;
    #4 = Utf8               scala/runtime/AbstractFunction4
    #5 = Class              #4            // scala/runtime/AbstractFunction4
    #6 = Utf8               java/io/Serializable
    #7 = Class              #6            // java/io/Serializable
    #8 = Utf8               Cursor.scala
    #9 = Utf8               MODULE$
   #10 = Utf8               Largonaut/CObject$;
   #11 = Utf8               <clinit>
   #12 = Utf8               ()V
   #13 = Utf8               <init>
   #14 = NameAndType        #13:#12       // "<init>":()V
   #15 = Methodref          #2.#14        // argonaut/CObject$."<init>":()V
   #16 = NameAndType        #9:#10        // MODULE$:Largonaut/CObject$;
   #17 = Fieldref           #2.#16        // argonaut/CObject$.MODULE$:Largonaut/CObject$;
   #18 = Utf8               toString
   #19 = Utf8               ()Ljava/lang/String;
   #20 = Utf8               CObject
   #21 = String             #20           // CObject
   #22 = Utf8               this
   #23 = Utf8               apply
   #24 = Utf8               (Largonaut/Cursor;ZLargonaut/JsonObject;Lscala/Tuple2;)Largonaut/CObject;
   #25 = Utf8               (Largonaut/Cursor;ZLargonaut/JsonObject;Lscala/Tuple2<Ljava/lang/String;Largonaut/Json;>;)Largonaut/CObject;
   #26 = Utf8               p
   #27 = Utf8               u
   #28 = Utf8               o
   #29 = Utf8               x
   #30 = Utf8               argonaut/CObject
   #31 = Class              #30           // argonaut/CObject
   #32 = Utf8               (Largonaut/Cursor;ZLargonaut/JsonObject;Lscala/Tuple2;)V
   #33 = NameAndType        #13:#32       // "<init>":(Largonaut/Cursor;ZLargonaut/JsonObject;Lscala/Tuple2;)V
   #34 = Methodref          #31.#33       // argonaut/CObject."<init>":(Largonaut/Cursor;ZLargonaut/JsonObject;Lscala/Tuple2;)V
   #35 = Utf8               Largonaut/Cursor;
   #36 = Utf8               Z
   #37 = Utf8               Largonaut/JsonObject;
   #38 = Utf8               Lscala/Tuple2;
   #39 = Utf8               unapply
   #40 = Utf8               (Largonaut/CObject;)Lscala/Option;
   #41 = Utf8               (Largonaut/CObject;)Lscala/Option<Lscala/Tuple4<Largonaut/Cursor;Ljava/lang/Object;Largonaut/JsonObject;Lscala/Tuple2<Ljava/lang/String;Largonaut/Json;>;>;>;
   #42 = Utf8               x$0
   #43 = Utf8               scala/None$
   #44 = Class              #43           // scala/None$
   #45 = Utf8               Lscala/None$;
   #46 = NameAndType        #9:#45        // MODULE$:Lscala/None$;
   #47 = Fieldref           #44.#46       // scala/None$.MODULE$:Lscala/None$;
   #48 = Utf8               scala/Some
   #49 = Class              #48           // scala/Some
   #50 = Utf8               scala/Tuple4
   #51 = Class              #50           // scala/Tuple4
   #52 = Utf8               ()Largonaut/Cursor;
   #53 = NameAndType        #26:#52       // p:()Largonaut/Cursor;
   #54 = Methodref          #31.#53       // argonaut/CObject.p:()Largonaut/Cursor;
   #55 = Utf8               ()Z
   #56 = NameAndType        #27:#55       // u:()Z
   #57 = Methodref          #31.#56       // argonaut/CObject.u:()Z
   #58 = Utf8               scala/runtime/BoxesRunTime
   #59 = Class              #58           // scala/runtime/BoxesRunTime
   #60 = Utf8               boxToBoolean
   #61 = Utf8               (Z)Ljava/lang/Boolean;
   #62 = NameAndType        #60:#61       // boxToBoolean:(Z)Ljava/lang/Boolean;
   #63 = Methodref          #59.#62       // scala/runtime/BoxesRunTime.boxToBoolean:(Z)Ljava/lang/Boolean;
   #64 = Utf8               ()Largonaut/JsonObject;
   #65 = NameAndType        #28:#64       // o:()Largonaut/JsonObject;
   #66 = Methodref          #31.#65       // argonaut/CObject.o:()Largonaut/JsonObject;
   #67 = Utf8               ()Lscala/Tuple2;
   #68 = NameAndType        #29:#67       // x:()Lscala/Tuple2;
   #69 = Methodref          #31.#68       // argonaut/CObject.x:()Lscala/Tuple2;
   #70 = Utf8               (Ljava/lang/Object;Ljava/lang/Object;Ljava/lang/Object;Ljava/lang/Object;)V
   #71 = NameAndType        #13:#70       // "<init>":(Ljava/lang/Object;Ljava/lang/Object;Ljava/lang/Object;Ljava/lang/Object;)V
   #72 = Methodref          #51.#71       // scala/Tuple4."<init>":(Ljava/lang/Object;Ljava/lang/Object;Ljava/lang/Object;Ljava/lang/Object;)V
   #73 = Utf8               (Ljava/lang/Object;)V
   #74 = NameAndType        #13:#73       // "<init>":(Ljava/lang/Object;)V
   #75 = Methodref          #49.#74       // scala/Some."<init>":(Ljava/lang/Object;)V
   #76 = Utf8               Largonaut/CObject;
   #77 = Utf8               scala/Option
   #78 = Class              #77           // scala/Option
   #79 = Utf8               writeReplace
   #80 = Utf8               ()Ljava/lang/Object;
   #81 = Utf8               scala/runtime/ModuleSerializationProxy
   #82 = Class              #81           // scala/runtime/ModuleSerializationProxy
   #83 = Utf8               (Ljava/lang/Class;)V
   #84 = NameAndType        #13:#83       // "<init>":(Ljava/lang/Class;)V
   #85 = Methodref          #82.#84       // scala/runtime/ModuleSerializationProxy."<init>":(Ljava/lang/Class;)V
   #86 = Utf8               (Ljava/lang/Object;Ljava/lang/Object;Ljava/lang/Object;Ljava/lang/Object;)Ljava/lang/Object;
   #87 = Utf8               v1
   #88 = Utf8               v2
   #89 = Utf8               v3
   #90 = Utf8               v4
   #91 = Utf8               argonaut/Cursor
   #92 = Class              #91           // argonaut/Cursor
   #93 = Utf8               unboxToBoolean
   #94 = Utf8               (Ljava/lang/Object;)Z
   #95 = NameAndType        #93:#94       // unboxToBoolean:(Ljava/lang/Object;)Z
   #96 = Methodref          #59.#95       // scala/runtime/BoxesRunTime.unboxToBoolean:(Ljava/lang/Object;)Z
   #97 = Utf8               argonaut/JsonObject
   #98 = Class              #97           // argonaut/JsonObject
   #99 = Utf8               scala/Tuple2
  #100 = Class              #99           // scala/Tuple2
  #101 = NameAndType        #23:#24       // apply:(Largonaut/Cursor;ZLargonaut/JsonObject;Lscala/Tuple2;)Largonaut/CObject;
  #102 = Methodref          #2.#101       // argonaut/CObject$.apply:(Largonaut/Cursor;ZLargonaut/JsonObject;Lscala/Tuple2;)Largonaut/CObject;
  #103 = Utf8               Ljava/lang/Object;
  #104 = Methodref          #5.#14        // scala/runtime/AbstractFunction4."<init>":()V
  #105 = Utf8               Code
  #106 = Utf8               LineNumberTable
  #107 = Utf8               LocalVariableTable
  #108 = Utf8               Signature
  #109 = Utf8               MethodParameters
  #110 = Utf8               StackMapTable
  #111 = Utf8               SourceFile
  #112 = Utf8               ScalaInlineInfo
  #113 = Utf8               Scala
{
  public static final argonaut.CObject$ MODULE$;
    descriptor: Largonaut/CObject$;
    flags: (0x0019) ACC_PUBLIC, ACC_STATIC, ACC_FINAL

  public static {};
    descriptor: ()V
    flags: (0x0009) ACC_PUBLIC, ACC_STATIC
    Code:
      stack=2, locals=0, args_size=0
         0: new           #2                  // class argonaut/CObject$
         3: dup
         4: invokespecial #15                 // Method "<init>":()V
         7: putstatic     #17                 // Field MODULE$:Largonaut/CObject$;
        10: return
      LineNumberTable:
        line 449: 0

  public final java.lang.String toString();
    descriptor: ()Ljava/lang/String;
    flags: (0x0011) ACC_PUBLIC, ACC_FINAL
    Code:
      stack=1, locals=1, args_size=1
         0: ldc           #21                 // String CObject
         2: areturn
      LineNumberTable:
        line 449: 0
      LocalVariableTable:
        Start  Length  Slot  Name   Signature
            0       3     0  this   Largonaut/CObject$;

  public argonaut.CObject apply(argonaut.Cursor, boolean, argonaut.JsonObject, scala.Tuple2<java.lang.String, argonaut.Json>);
    descriptor: (Largonaut/Cursor;ZLargonaut/JsonObject;Lscala/Tuple2;)Largonaut/CObject;
    flags: (0x0001) ACC_PUBLIC
    Code:
      stack=6, locals=5, args_size=5
         0: new           #31                 // class argonaut/CObject
         3: dup
         4: aload_1
         5: iload_2
         6: aload_3
         7: aload         4
         9: invokespecial #34                 // Method argonaut/CObject."<init>":(Largonaut/Cursor;ZLargonaut/JsonObject;Lscala/Tuple2;)V
        12: areturn
      LineNumberTable:
        line 449: 0
      LocalVariableTable:
        Start  Length  Slot  Name   Signature
            0      13     0  this   Largonaut/CObject$;
            0      13     1     p   Largonaut/Cursor;
            0      13     2     u   Z
            0      13     3     o   Largonaut/JsonObject;
            0      13     4     x   Lscala/Tuple2;
    Signature: #25                          // (Largonaut/Cursor;ZLargonaut/JsonObject;Lscala/Tuple2<Ljava/lang/String;Largonaut/Json;>;)Largonaut/CObject;
    MethodParameters:
      Name                           Flags
      p                              final
      u                              final
      o                              final
      x                              final

  public scala.Option<scala.Tuple4<argonaut.Cursor, java.lang.Object, argonaut.JsonObject, scala.Tuple2<java.lang.String, argonaut.Json>>> unapply(argonaut.CObject);
    descriptor: (Largonaut/CObject;)Lscala/Option;
    flags: (0x0001) ACC_PUBLIC
    Code:
      stack=8, locals=2, args_size=2
         0: aload_1
         1: ifnonnull     10
         4: getstatic     #47                 // Field scala/None$.MODULE$:Lscala/None$;
         7: goto          43
        10: new           #49                 // class scala/Some
        13: dup
        14: new           #51                 // class scala/Tuple4
        17: dup
        18: aload_1
        19: invokevirtual #54                 // Method argonaut/CObject.p:()Largonaut/Cursor;
        22: aload_1
        23: invokevirtual #57                 // Method argonaut/CObject.u:()Z
        26: invokestatic  #63                 // Method scala/runtime/BoxesRunTime.boxToBoolean:(Z)Ljava/lang/Boolean;
        29: aload_1
        30: invokevirtual #66                 // Method argonaut/CObject.o:()Largonaut/JsonObject;
        33: aload_1
        34: invokevirtual #69                 // Method argonaut/CObject.x:()Lscala/Tuple2;
        37: invokespecial #72                 // Method scala/Tuple4."<init>":(Ljava/lang/Object;Ljava/lang/Object;Ljava/lang/Object;Ljava/lang/Object;)V
        40: invokespecial #75                 // Method scala/Some."<init>":(Ljava/lang/Object;)V
        43: areturn
      StackMapTable: number_of_entries = 2
        frame_type = 10 /* same */
        frame_type = 96 /* same_locals_1_stack_item */
          stack = [ class scala/Option ]
      LineNumberTable:
        line 449: 0
      LocalVariableTable:
        Start  Length  Slot  Name   Signature
            0      44     0  this   Largonaut/CObject$;
            0      44     1   x$0   Largonaut/CObject;
    Signature: #41                          // (Largonaut/CObject;)Lscala/Option<Lscala/Tuple4<Largonaut/Cursor;Ljava/lang/Object;Largonaut/JsonObject;Lscala/Tuple2<Ljava/lang/String;Largonaut/Json;>;>;>;
    MethodParameters:
      Name                           Flags
      x$0                            final

  private java.lang.Object writeReplace();
    descriptor: ()Ljava/lang/Object;
    flags: (0x0002) ACC_PRIVATE
    Code:
      stack=3, locals=1, args_size=1
         0: new           #82                 // class scala/runtime/ModuleSerializationProxy
         3: dup
         4: ldc           #2                  // class argonaut/CObject$
         6: invokespecial #85                 // Method scala/runtime/ModuleSerializationProxy."<init>":(Ljava/lang/Class;)V
         9: areturn
      LineNumberTable:
        line 449: 0
      LocalVariableTable:
        Start  Length  Slot  Name   Signature
            0      10     0  this   Largonaut/CObject$;

  public java.lang.Object apply(java.lang.Object, java.lang.Object, java.lang.Object, java.lang.Object);
    descriptor: (Ljava/lang/Object;Ljava/lang/Object;Ljava/lang/Object;Ljava/lang/Object;)Ljava/lang/Object;
    flags: (0x1041) ACC_PUBLIC, ACC_BRIDGE, ACC_SYNTHETIC
    Code:
      stack=5, locals=5, args_size=5
         0: aload_0
         1: aload_1
         2: checkcast     #92                 // class argonaut/Cursor
         5: aload_2
         6: invokestatic  #96                 // Method scala/runtime/BoxesRunTime.unboxToBoolean:(Ljava/lang/Object;)Z
         9: aload_3
        10: checkcast     #98                 // class argonaut/JsonObject
        13: aload         4
        15: checkcast     #100                // class scala/Tuple2
        18: invokevirtual #102                // Method apply:(Largonaut/Cursor;ZLargonaut/JsonObject;Lscala/Tuple2;)Largonaut/CObject;
        21: areturn
      LineNumberTable:
        line 449: 0
      LocalVariableTable:
        Start  Length  Slot  Name   Signature
            0      22     0  this   Largonaut/CObject$;
            0      22     1    v1   Ljava/lang/Object;
            0      22     2    v2   Ljava/lang/Object;
            0      22     3    v3   Ljava/lang/Object;
            0      22     4    v4   Ljava/lang/Object;
    MethodParameters:
      Name                           Flags
      v1                             final
      v2                             final
      v3                             final
      v4                             final

  private argonaut.CObject$();
    descriptor: ()V
    flags: (0x0002) ACC_PRIVATE
    Code:
      stack=1, locals=1, args_size=1
         0: aload_0
         1: invokespecial #104                // Method scala/runtime/AbstractFunction4."<init>":()V
         4: return
      LineNumberTable:
        line 449: 0
      LocalVariableTable:
        Start  Length  Slot  Name   Signature
            0       5     0  this   Largonaut/CObject$;
}
Signature: #3                           // Lscala/runtime/AbstractFunction4<Largonaut/Cursor;Ljava/lang/Object;Largonaut/JsonObject;Lscala/Tuple2<Ljava/lang/String;Largonaut/Json;>;Largonaut/CObject;>;Ljava/io/Serializable;
SourceFile: "Cursor.scala"
  ScalaInlineInfo: length = 0x22 (unknown attribute)
   01 01 00 06 00 0D 00 0C 01 00 17 00 18 01 00 17
   00 56 01 00 12 00 13 01 00 27 00 28 01 00 4F 00
   50 01
  Scala: length = 0x0 (unknown attribute)

