Classfile /Users/mw/Projects/slang-braindump/.jar/jar8/assemble/slang-braindump/assemble/content/argonaut/Context$$anon$1.class
  Last modified May 29, 2022; size 799 bytes
  SHA-256 checksum c12a32f81d3cb5c94ff392624d4bc06ae79773f357c96eefdef360edfe58aa32
  Compiled from "Context.scala"
public final class argonaut.Context$$anon$1 extends argonaut.Context
  minor version: 0
  major version: 52
  flags: (0x0031) ACC_PUBLIC, ACC_FINAL, ACC_SUPER
  this_class: #2                          // argonaut/Context$$anon$1
  super_class: #4                         // argonaut/Context
  interfaces: 0, fields: 1, methods: 3, attributes: 5
Constant pool:
   #1 = Utf8               argonaut/Context$$anon$1
   #2 = Class              #1             // argonaut/Context$$anon$1
   #3 = Utf8               argonaut/Context
   #4 = Class              #3             // argonaut/Context
   #5 = Utf8               Context.scala
   #6 = Utf8               argonaut/Context$
   #7 = Class              #6             // argonaut/Context$
   #8 = Utf8               empty
   #9 = Utf8               ()Largonaut/Context;
  #10 = NameAndType        #8:#9          // empty:()Largonaut/Context;
  #11 = Utf8               toList
  #12 = Utf8               Lscala/collection/immutable/Nil$;
  #13 = Utf8               ()Lscala/collection/immutable/Nil$;
  #14 = NameAndType        #11:#12        // toList:Lscala/collection/immutable/Nil$;
  #15 = Fieldref           #2.#14         // argonaut/Context$$anon$1.toList:Lscala/collection/immutable/Nil$;
  #16 = Utf8               this
  #17 = Utf8               Largonaut/Context$$anon$1;
  #18 = Utf8               ()Lscala/collection/immutable/List;
  #19 = NameAndType        #11:#13        // toList:()Lscala/collection/immutable/Nil$;
  #20 = Methodref          #2.#19         // argonaut/Context$$anon$1.toList:()Lscala/collection/immutable/Nil$;
  #21 = Utf8               <init>
  #22 = Utf8               ()V
  #23 = NameAndType        #21:#22        // "<init>":()V
  #24 = Methodref          #4.#23         // argonaut/Context."<init>":()V
  #25 = Utf8               scala/collection/immutable/Nil$
  #26 = Class              #25            // scala/collection/immutable/Nil$
  #27 = Utf8               MODULE$
  #28 = NameAndType        #27:#12        // MODULE$:Lscala/collection/immutable/Nil$;
  #29 = Fieldref           #26.#28        // scala/collection/immutable/Nil$.MODULE$:Lscala/collection/immutable/Nil$;
  #30 = Utf8               Code
  #31 = Utf8               LineNumberTable
  #32 = Utf8               LocalVariableTable
  #33 = Utf8               InnerClasses
  #34 = Utf8               EnclosingMethod
  #35 = Utf8               SourceFile
  #36 = Utf8               ScalaInlineInfo
  #37 = Utf8               Scala
{
  private final scala.collection.immutable.Nil$ toList;
    descriptor: Lscala/collection/immutable/Nil$;
    flags: (0x0012) ACC_PRIVATE, ACC_FINAL

  public scala.collection.immutable.Nil$ toList();
    descriptor: ()Lscala/collection/immutable/Nil$;
    flags: (0x0001) ACC_PUBLIC
    Code:
      stack=1, locals=1, args_size=1
         0: aload_0
         1: getfield      #15                 // Field toList:Lscala/collection/immutable/Nil$;
         4: areturn
      LineNumberTable:
        line 15: 0
      LocalVariableTable:
        Start  Length  Slot  Name   Signature
            0       5     0  this   Largonaut/Context$$anon$1;

  public scala.collection.immutable.List toList();
    descriptor: ()Lscala/collection/immutable/List;
    flags: (0x1041) ACC_PUBLIC, ACC_BRIDGE, ACC_SYNTHETIC
    Code:
      stack=1, locals=1, args_size=1
         0: aload_0
         1: invokevirtual #20                 // Method toList:()Lscala/collection/immutable/Nil$;
         4: areturn
      LineNumberTable:
        line 14: 0
      LocalVariableTable:
        Start  Length  Slot  Name   Signature
            0       5     0  this   Largonaut/Context$$anon$1;

  public argonaut.Context$$anon$1();
    descriptor: ()V
    flags: (0x0001) ACC_PUBLIC
    Code:
      stack=2, locals=1, args_size=1
         0: aload_0
         1: invokespecial #24                 // Method argonaut/Context."<init>":()V
         4: aload_0
         5: getstatic     #29                 // Field scala/collection/immutable/Nil$.MODULE$:Lscala/collection/immutable/Nil$;
         8: putfield      #15                 // Field toList:Lscala/collection/immutable/Nil$;
        11: return
      LineNumberTable:
        line 14: 0
        line 15: 4
        line 14: 11
      LocalVariableTable:
        Start  Length  Slot  Name   Signature
            0      12     0  this   Largonaut/Context$$anon$1;
}
InnerClasses:
  public final #2;                        // class argonaut/Context$$anon$1
EnclosingMethod: #7.#10                 // argonaut.Context$.empty
SourceFile: "Context.scala"
  ScalaInlineInfo: length = 0x13 (unknown attribute)
   01 01 00 03 00 15 00 16 01 00 0B 00 12 01 00 0B
   00 0D 01
  Scala: length = 0x0 (unknown attribute)

