Classfile /Users/mw/Projects/slang-braindump/.jar/jar8/assemble/slang-braindump/assemble/content/argonaut/ContextElement.class
  Last modified May 29, 2022; size 3416 bytes
  SHA-256 checksum 89696b2943c08c620e5a60a512907486fb4029356517c9c93e82d22c483ccc31
  Compiled from "Context.scala"
public abstract class argonaut.ContextElement implements scala.Product,java.io.Serializable
  minor version: 0
  major version: 52
  flags: (0x0421) ACC_PUBLIC, ACC_SUPER, ACC_ABSTRACT
  this_class: #2                          // argonaut/ContextElement
  super_class: #4                         // java/lang/Object
  interfaces: 2, fields: 0, methods: 10, attributes: 4
Constant pool:
    #1 = Utf8               argonaut/ContextElement
    #2 = Class              #1            // argonaut/ContextElement
    #3 = Utf8               java/lang/Object
    #4 = Class              #3            // java/lang/Object
    #5 = Utf8               scala/Product
    #6 = Class              #5            // scala/Product
    #7 = Utf8               java/io/Serializable
    #8 = Class              #7            // java/io/Serializable
    #9 = Utf8               Context.scala
   #10 = Utf8               Lscala/reflect/ScalaSignature;
   #11 = Utf8               bytes
   #12 = Utf8               \u0006\u0005i3Q!\u0003\u0006\u0002\"5AQa\t\u0001\u0005\u0002\u0011BQa\n\u0001\u0005\u0002!BQ\u0001\f\u0001\u0005\u00025BQ!\u000f\u0001\u0005\u0002i:Q\u0001\u0012\u0006\t\u0002\u00153Q!\u0003\u0006\t\u0002\u0019CQa\t\u0004\u0005\u0002ECqA\u0015\u0004\u0002\u0002\u0013%1K\u0001\bD_:$X\r\u001f;FY\u0016lWM\u001c;\u000b\u0003-\t\u0001\"\u0019:h_:\fW\u000f^\u0002\u0001\'\u0011\u0001a\u0002F\f\u0011\u0005=\u0011R\"\u0001\t\u000b\u0003E\tQa]2bY\u0006L!a\u0005\t\u0003\r\u0005s\u0017PU3g!\tyQ#\u0003\u0002\u0017!\t9\u0001K]8ek\u000e$\bC\u0001\r!\u001d\tIbD\u0004\u0002\u001b;5\t1D\u0003\u0002\u001d\u0019\u00051AH]8pizJ\u0011!E\u0005\u0003?A\tq\u0001]1dW\u0006<W-\u0003\u0002\"E\ta1+\u001a:jC2L\'0\u00192mK*\u0011q\u0004E\u0001\u0007y%t\u0017\u000e\u001e \u0015\u0003\u0015\u0002\"A\n\u0001\u000e\u0003)\tAA[:p]V\t\u0011\u0006\u0005\u0002\'U%\u00111F\u0003\u0002\u0005\u0015N|g.A\u0003gS\u0016dG-F\u0001/!\ryq&M\u0005\u0003aA\u0011aa\u00149uS>t\u0007C\u0001\u001a6\u001d\t13\'\u0003\u00025\u0015\u0005!!j]8o\u0013\t1tGA\u0005Kg>tg)[3mI&\u0011\u0001H\u0003\u0002\u0006\u0015N|gn]\u0001\u0006S:$W\r_\u000b\u0002wA\u0019qb\f\u001f\u0011\u0005=i\u0014B\u0001 \u0011\u0005\rIe\u000e^\u0015\u0004\u0001\u0001\u0013\u0015BA!\u000b\u00051\t%O]1z\u0007>tG/\u001a=u\u0013\t\u0019%BA\u0007PE*,7\r^\"p]R,\u0007\u0010^\u0001\u000f\u0007>tG/\u001a=u\u000b2,W.\u001a8u!\t1ca\u0005\u0003\u0007\u001d\u001dS\u0005C\u0001\u0014I\u0013\tI%BA\bD_:$X\r\u001f;FY\u0016lWM\u001c;t!\tY\u0005+D\u0001M\u0015\tie*\u0001\u0002j_*\tq*\u0001\u0003kCZ\f\u0017BA\u0011M)\u0005)\u0015\u0001D<sSR,\'+\u001a9mC\u000e,G#\u0001+\u0011\u0005UCV\"\u0001,\u000b\u0005]s\u0015\u0001\u00027b]\u001eL!!\u0017,\u0003\r=\u0013\'.Z2u\u0001
   #13 = Utf8               objectContext
   #14 = Utf8               (Ljava/lang/String;Largonaut/Json;)Largonaut/ContextElement;
   #15 = Utf8               f
   #16 = Utf8               j
   #17 = Utf8               argonaut/ContextElement$
   #18 = Class              #17           // argonaut/ContextElement$
   #19 = Utf8               MODULE$
   #20 = Utf8               Largonaut/ContextElement$;
   #21 = NameAndType        #19:#20       // MODULE$:Largonaut/ContextElement$;
   #22 = Fieldref           #18.#21       // argonaut/ContextElement$.MODULE$:Largonaut/ContextElement$;
   #23 = NameAndType        #13:#14       // objectContext:(Ljava/lang/String;Largonaut/Json;)Largonaut/ContextElement;
   #24 = Methodref          #18.#23       // argonaut/ContextElement$.objectContext:(Ljava/lang/String;Largonaut/Json;)Largonaut/ContextElement;
   #25 = Utf8               arrayContext
   #26 = Utf8               (ILargonaut/Json;)Largonaut/ContextElement;
   #27 = Utf8               n
   #28 = NameAndType        #25:#26       // arrayContext:(ILargonaut/Json;)Largonaut/ContextElement;
   #29 = Methodref          #18.#28       // argonaut/ContextElement$.arrayContext:(ILargonaut/Json;)Largonaut/ContextElement;
   #30 = Utf8               productIterator
   #31 = Utf8               ()Lscala/collection/Iterator;
   #32 = Utf8               ()Lscala/collection/Iterator<Ljava/lang/Object;>;
   #33 = Utf8               productIterator$
   #34 = Utf8               (Lscala/Product;)Lscala/collection/Iterator;
   #35 = NameAndType        #33:#34       // productIterator$:(Lscala/Product;)Lscala/collection/Iterator;
   #36 = InterfaceMethodref #6.#35        // scala/Product.productIterator$:(Lscala/Product;)Lscala/collection/Iterator;
   #37 = Utf8               this
   #38 = Utf8               Largonaut/ContextElement;
   #39 = Utf8               productPrefix
   #40 = Utf8               ()Ljava/lang/String;
   #41 = Utf8               productPrefix$
   #42 = Utf8               (Lscala/Product;)Ljava/lang/String;
   #43 = NameAndType        #41:#42       // productPrefix$:(Lscala/Product;)Ljava/lang/String;
   #44 = InterfaceMethodref #6.#43        // scala/Product.productPrefix$:(Lscala/Product;)Ljava/lang/String;
   #45 = Utf8               productElementName
   #46 = Utf8               (I)Ljava/lang/String;
   #47 = Utf8               productElementName$
   #48 = Utf8               (Lscala/Product;I)Ljava/lang/String;
   #49 = NameAndType        #47:#48       // productElementName$:(Lscala/Product;I)Ljava/lang/String;
   #50 = InterfaceMethodref #6.#49        // scala/Product.productElementName$:(Lscala/Product;I)Ljava/lang/String;
   #51 = Utf8               I
   #52 = Utf8               productElementNames
   #53 = Utf8               ()Lscala/collection/Iterator<Ljava/lang/String;>;
   #54 = Utf8               productElementNames$
   #55 = NameAndType        #54:#34       // productElementNames$:(Lscala/Product;)Lscala/collection/Iterator;
   #56 = InterfaceMethodref #6.#55        // scala/Product.productElementNames$:(Lscala/Product;)Lscala/collection/Iterator;
   #57 = Utf8               json
   #58 = Utf8               ()Largonaut/Json;
   #59 = Utf8               argonaut/ArrayContext
   #60 = Class              #59           // argonaut/ArrayContext
   #61 = NameAndType        #16:#58       // j:()Largonaut/Json;
   #62 = Methodref          #60.#61       // argonaut/ArrayContext.j:()Largonaut/Json;
   #63 = Utf8               argonaut/ObjectContext
   #64 = Class              #63           // argonaut/ObjectContext
   #65 = Methodref          #64.#61       // argonaut/ObjectContext.j:()Largonaut/Json;
   #66 = Utf8               scala/MatchError
   #67 = Class              #66           // scala/MatchError
   #68 = Utf8               <init>
   #69 = Utf8               (Ljava/lang/Object;)V
   #70 = NameAndType        #68:#69       // "<init>":(Ljava/lang/Object;)V
   #71 = Methodref          #67.#70       // scala/MatchError."<init>":(Ljava/lang/Object;)V
   #72 = Utf8               Largonaut/Json;
   #73 = Utf8               argonaut/Json
   #74 = Class              #73           // argonaut/Json
   #75 = Utf8               field
   #76 = Utf8               ()Lscala/Option;
   #77 = Utf8               ()Lscala/Option<Ljava/lang/String;>;
   #78 = Utf8               scala/None$
   #79 = Class              #78           // scala/None$
   #80 = Utf8               Lscala/None$;
   #81 = NameAndType        #19:#80       // MODULE$:Lscala/None$;
   #82 = Fieldref           #79.#81       // scala/None$.MODULE$:Lscala/None$;
   #83 = NameAndType        #15:#40       // f:()Ljava/lang/String;
   #84 = Methodref          #64.#83       // argonaut/ObjectContext.f:()Ljava/lang/String;
   #85 = Utf8               scala/Some
   #86 = Class              #85           // scala/Some
   #87 = Methodref          #86.#70       // scala/Some."<init>":(Ljava/lang/Object;)V
   #88 = Utf8               Ljava/lang/String;
   #89 = Utf8               scala/Option
   #90 = Class              #89           // scala/Option
   #91 = Utf8               index
   #92 = Utf8               ()Lscala/Option<Ljava/lang/Object;>;
   #93 = Utf8               ()I
   #94 = NameAndType        #27:#93       // n:()I
   #95 = Methodref          #60.#94       // argonaut/ArrayContext.n:()I
   #96 = Utf8               scala/runtime/BoxesRunTime
   #97 = Class              #96           // scala/runtime/BoxesRunTime
   #98 = Utf8               boxToInteger
   #99 = Utf8               (I)Ljava/lang/Integer;
  #100 = NameAndType        #98:#99       // boxToInteger:(I)Ljava/lang/Integer;
  #101 = Methodref          #97.#100      // scala/runtime/BoxesRunTime.boxToInteger:(I)Ljava/lang/Integer;
  #102 = Utf8               ()V
  #103 = NameAndType        #68:#102      // "<init>":()V
  #104 = Methodref          #4.#103       // java/lang/Object."<init>":()V
  #105 = Utf8               $init$
  #106 = Utf8               (Lscala/Product;)V
  #107 = NameAndType        #105:#106     // $init$:(Lscala/Product;)V
  #108 = InterfaceMethodref #6.#107       // scala/Product.$init$:(Lscala/Product;)V
  #109 = Utf8               Code
  #110 = Utf8               MethodParameters
  #111 = Utf8               LineNumberTable
  #112 = Utf8               LocalVariableTable
  #113 = Utf8               Signature
  #114 = Utf8               StackMapTable
  #115 = Utf8               SourceFile
  #116 = Utf8               RuntimeVisibleAnnotations
  #117 = Utf8               ScalaInlineInfo
  #118 = Utf8               ScalaSig
{
  public static argonaut.ContextElement objectContext(java.lang.String, argonaut.Json);
    descriptor: (Ljava/lang/String;Largonaut/Json;)Largonaut/ContextElement;
    flags: (0x0009) ACC_PUBLIC, ACC_STATIC
    Code:
      stack=3, locals=2, args_size=2
         0: getstatic     #22                 // Field argonaut/ContextElement$.MODULE$:Largonaut/ContextElement$;
         3: aload_0
         4: aload_1
         5: invokevirtual #24                 // Method argonaut/ContextElement$.objectContext:(Ljava/lang/String;Largonaut/Json;)Largonaut/ContextElement;
         8: areturn
    MethodParameters:
      Name                           Flags
      f                              final
      j                              final

  public static argonaut.ContextElement arrayContext(int, argonaut.Json);
    descriptor: (ILargonaut/Json;)Largonaut/ContextElement;
    flags: (0x0009) ACC_PUBLIC, ACC_STATIC
    Code:
      stack=3, locals=2, args_size=2
         0: getstatic     #22                 // Field argonaut/ContextElement$.MODULE$:Largonaut/ContextElement$;
         3: iload_0
         4: aload_1
         5: invokevirtual #29                 // Method argonaut/ContextElement$.arrayContext:(ILargonaut/Json;)Largonaut/ContextElement;
         8: areturn
    MethodParameters:
      Name                           Flags
      n                              final
      j                              final

  public scala.collection.Iterator<java.lang.Object> productIterator();
    descriptor: ()Lscala/collection/Iterator;
    flags: (0x0001) ACC_PUBLIC
    Code:
      stack=1, locals=1, args_size=1
         0: aload_0
         1: invokestatic  #36                 // InterfaceMethod scala/Product.productIterator$:(Lscala/Product;)Lscala/collection/Iterator;
         4: areturn
      LineNumberTable:
        line 26: 0
      LocalVariableTable:
        Start  Length  Slot  Name   Signature
            0       5     0  this   Largonaut/ContextElement;
    Signature: #32                          // ()Lscala/collection/Iterator<Ljava/lang/Object;>;

  public java.lang.String productPrefix();
    descriptor: ()Ljava/lang/String;
    flags: (0x0001) ACC_PUBLIC
    Code:
      stack=1, locals=1, args_size=1
         0: aload_0
         1: invokestatic  #44                 // InterfaceMethod scala/Product.productPrefix$:(Lscala/Product;)Ljava/lang/String;
         4: areturn
      LineNumberTable:
        line 26: 0
      LocalVariableTable:
        Start  Length  Slot  Name   Signature
            0       5     0  this   Largonaut/ContextElement;

  public java.lang.String productElementName(int);
    descriptor: (I)Ljava/lang/String;
    flags: (0x0001) ACC_PUBLIC
    Code:
      stack=2, locals=2, args_size=2
         0: aload_0
         1: iload_1
         2: invokestatic  #50                 // InterfaceMethod scala/Product.productElementName$:(Lscala/Product;I)Ljava/lang/String;
         5: areturn
      LineNumberTable:
        line 26: 0
      LocalVariableTable:
        Start  Length  Slot  Name   Signature
            0       6     0  this   Largonaut/ContextElement;
            0       6     1     n   I
    MethodParameters:
      Name                           Flags
      n                              final

  public scala.collection.Iterator<java.lang.String> productElementNames();
    descriptor: ()Lscala/collection/Iterator;
    flags: (0x0001) ACC_PUBLIC
    Code:
      stack=1, locals=1, args_size=1
         0: aload_0
         1: invokestatic  #56                 // InterfaceMethod scala/Product.productElementNames$:(Lscala/Product;)Lscala/collection/Iterator;
         4: areturn
      LineNumberTable:
        line 26: 0
      LocalVariableTable:
        Start  Length  Slot  Name   Signature
            0       5     0  this   Largonaut/ContextElement;
    Signature: #53                          // ()Lscala/collection/Iterator<Ljava/lang/String;>;

  public argonaut.Json json();
    descriptor: ()Largonaut/Json;
    flags: (0x0001) ACC_PUBLIC
    Code:
      stack=3, locals=7, args_size=1
         0: aload_0
         1: astore_2
         2: aload_2
         3: instanceof    #60                 // class argonaut/ArrayContext
         6: ifeq          26
         9: aload_2
        10: checkcast     #60                 // class argonaut/ArrayContext
        13: astore_3
        14: aload_3
        15: invokevirtual #62                 // Method argonaut/ArrayContext.j:()Largonaut/Json;
        18: astore        4
        20: aload         4
        22: astore_1
        23: goto          67
        26: goto          29
        29: aload_2
        30: instanceof    #64                 // class argonaut/ObjectContext
        33: ifeq          55
        36: aload_2
        37: checkcast     #64                 // class argonaut/ObjectContext
        40: astore        5
        42: aload         5
        44: invokevirtual #65                 // Method argonaut/ObjectContext.j:()Largonaut/Json;
        47: astore        6
        49: aload         6
        51: astore_1
        52: goto          67
        55: goto          58
        58: new           #67                 // class scala/MatchError
        61: dup
        62: aload_2
        63: invokespecial #71                 // Method scala/MatchError."<init>":(Ljava/lang/Object;)V
        66: athrow
        67: aload_1
        68: areturn
      StackMapTable: number_of_entries = 5
        frame_type = 253 /* append */
          offset_delta = 26
          locals = [ top, class argonaut/ContextElement ]
        frame_type = 2 /* same */
        frame_type = 25 /* same */
        frame_type = 2 /* same */
        frame_type = 255 /* full_frame */
          offset_delta = 8
          locals = [ class argonaut/ContextElement, class argonaut/Json, class argonaut/ContextElement ]
          stack = []
      LineNumberTable:
        line 28: 0
        line 29: 2
        line 30: 29
        line 28: 58
      LocalVariableTable:
        Start  Length  Slot  Name   Signature
           18       8     4     j   Largonaut/Json;
           47       8     6     j   Largonaut/Json;
            0      69     0  this   Largonaut/ContextElement;

  public scala.Option<java.lang.String> field();
    descriptor: ()Lscala/Option;
    flags: (0x0001) ACC_PUBLIC
    Code:
      stack=3, locals=5, args_size=1
         0: aload_0
         1: astore_2
         2: aload_2
         3: instanceof    #60                 // class argonaut/ArrayContext
         6: ifeq          16
         9: getstatic     #82                 // Field scala/None$.MODULE$:Lscala/None$;
        12: astore_1
        13: goto          62
        16: goto          19
        19: aload_2
        20: instanceof    #64                 // class argonaut/ObjectContext
        23: ifeq          50
        26: aload_2
        27: checkcast     #64                 // class argonaut/ObjectContext
        30: astore_3
        31: aload_3
        32: invokevirtual #84                 // Method argonaut/ObjectContext.f:()Ljava/lang/String;
        35: astore        4
        37: new           #86                 // class scala/Some
        40: dup
        41: aload         4
        43: invokespecial #87                 // Method scala/Some."<init>":(Ljava/lang/Object;)V
        46: astore_1
        47: goto          62
        50: goto          53
        53: new           #67                 // class scala/MatchError
        56: dup
        57: aload_2
        58: invokespecial #71                 // Method scala/MatchError."<init>":(Ljava/lang/Object;)V
        61: athrow
        62: aload_1
        63: areturn
      StackMapTable: number_of_entries = 5
        frame_type = 253 /* append */
          offset_delta = 16
          locals = [ top, class argonaut/ContextElement ]
        frame_type = 2 /* same */
        frame_type = 30 /* same */
        frame_type = 2 /* same */
        frame_type = 255 /* full_frame */
          offset_delta = 8
          locals = [ class argonaut/ContextElement, class scala/Option, class argonaut/ContextElement ]
          stack = []
      LineNumberTable:
        line 34: 0
        line 35: 2
        line 36: 19
        line 34: 53
      LocalVariableTable:
        Start  Length  Slot  Name   Signature
           35      15     4     f   Ljava/lang/String;
            0      64     0  this   Largonaut/ContextElement;
    Signature: #77                          // ()Lscala/Option<Ljava/lang/String;>;

  public scala.Option<java.lang.Object> index();
    descriptor: ()Lscala/Option;
    flags: (0x0001) ACC_PUBLIC
    Code:
      stack=3, locals=5, args_size=1
         0: aload_0
         1: astore_2
         2: aload_2
         3: instanceof    #60                 // class argonaut/ArrayContext
         6: ifeq          36
         9: aload_2
        10: checkcast     #60                 // class argonaut/ArrayContext
        13: astore_3
        14: aload_3
        15: invokevirtual #95                 // Method argonaut/ArrayContext.n:()I
        18: istore        4
        20: new           #86                 // class scala/Some
        23: dup
        24: iload         4
        26: invokestatic  #101                // Method scala/runtime/BoxesRunTime.boxToInteger:(I)Ljava/lang/Integer;
        29: invokespecial #87                 // Method scala/Some."<init>":(Ljava/lang/Object;)V
        32: astore_1
        33: goto          65
        36: goto          39
        39: aload_2
        40: instanceof    #64                 // class argonaut/ObjectContext
        43: ifeq          53
        46: getstatic     #82                 // Field scala/None$.MODULE$:Lscala/None$;
        49: astore_1
        50: goto          65
        53: goto          56
        56: new           #67                 // class scala/MatchError
        59: dup
        60: aload_2
        61: invokespecial #71                 // Method scala/MatchError."<init>":(Ljava/lang/Object;)V
        64: athrow
        65: aload_1
        66: areturn
      StackMapTable: number_of_entries = 5
        frame_type = 253 /* append */
          offset_delta = 36
          locals = [ top, class argonaut/ContextElement ]
        frame_type = 2 /* same */
        frame_type = 13 /* same */
        frame_type = 2 /* same */
        frame_type = 255 /* full_frame */
          offset_delta = 8
          locals = [ class argonaut/ContextElement, class scala/Option, class argonaut/ContextElement ]
          stack = []
      LineNumberTable:
        line 40: 0
        line 41: 2
        line 42: 39
        line 40: 56
      LocalVariableTable:
        Start  Length  Slot  Name   Signature
           18      18     4     n   I
            0      67     0  this   Largonaut/ContextElement;
    Signature: #92                          // ()Lscala/Option<Ljava/lang/Object;>;

  public argonaut.ContextElement();
    descriptor: ()V
    flags: (0x0001) ACC_PUBLIC
    Code:
      stack=1, locals=1, args_size=1
         0: aload_0
         1: invokespecial #104                // Method java/lang/Object."<init>":()V
         4: aload_0
         5: invokestatic  #108                // InterfaceMethod scala/Product.$init$:(Lscala/Product;)V
         8: return
      LineNumberTable:
        line 26: 0
      LocalVariableTable:
        Start  Length  Slot  Name   Signature
            0       9     0  this   Largonaut/ContextElement;
}
SourceFile: "Context.scala"
RuntimeVisibleAnnotations:
  0: #10(#11=s#12)
    scala.reflect.ScalaSignature(
      bytes="\u0006\u0005i3Q!\u0003\u0006\u0002\"5AQa\t\u0001\u0005\u0002\u0011BQa\n\u0001\u0005\u0002!BQ\u0001\f\u0001\u0005\u00025BQ!\u000f\u0001\u0005\u0002i:Q\u0001\u0012\u0006\t\u0002\u00153Q!\u0003\u0006\t\u0002\u0019CQa\t\u0004\u0005\u0002ECqA\u0015\u0004\u0002\u0002\u0013%1K\u0001\bD_:$X\r\u001f;FY\u0016lWM\u001c;\u000b\u0003-\t\u0001\"\u0019:h_:\fW\u000f^\u0002\u0001\'\u0011\u0001a\u0002F\f\u0011\u0005=\u0011R\"\u0001\t\u000b\u0003E\tQa]2bY\u0006L!a\u0005\t\u0003\r\u0005s\u0017PU3g!\tyQ#\u0003\u0002\u0017!\t9\u0001K]8ek\u000e$\bC\u0001\r!\u001d\tIbD\u0004\u0002\u001b;5\t1D\u0003\u0002\u001d\u0019\u00051AH]8pizJ\u0011!E\u0005\u0003?A\tq\u0001]1dW\u0006<W-\u0003\u0002\"E\ta1+\u001a:jC2L\'0\u00192mK*\u0011q\u0004E\u0001\u0007y%t\u0017\u000e\u001e \u0015\u0003\u0015\u0002\"A\n\u0001\u000e\u0003)\tAA[:p]V\t\u0011\u0006\u0005\u0002\'U%\u00111F\u0003\u0002\u0005\u0015N|g.A\u0003gS\u0016dG-F\u0001/!\ryq&M\u0005\u0003aA\u0011aa\u00149uS>t\u0007C\u0001\u001a6\u001d\t13\'\u0003\u00025\u0015\u0005!!j]8o\u0013\t1tGA\u0005Kg>tg)[3mI&\u0011\u0001H\u0003\u0002\u0006\u0015N|gn]\u0001\u0006S:$W\r_\u000b\u0002wA\u0019qb\f\u001f\u0011\u0005=i\u0014B\u0001 \u0011\u0005\rIe\u000e^\u0015\u0004\u0001\u0001\u0013\u0015BA!\u000b\u00051\t%O]1z\u0007>tG/\u001a=u\u0013\t\u0019%BA\u0007PE*,7\r^\"p]R,\u0007\u0010^\u0001\u000f\u0007>tG/\u001a=u\u000b2,W.\u001a8u!\t1ca\u0005\u0003\u0007\u001d\u001dS\u0005C\u0001\u0014I\u0013\tI%BA\bD_:$X\r\u001f;FY\u0016lWM\u001c;t!\tY\u0005+D\u0001M\u0015\tie*\u0001\u0002j_*\tq*\u0001\u0003kCZ\f\u0017BA\u0011M)\u0005)\u0015\u0001D<sSR,\'+\u001a9mC\u000e,G#\u0001+\u0011\u0005UCV\"\u0001,\u000b\u0005]s\u0015\u0001\u00027b]\u001eL!!\u0017,\u0003\r=\u0013\'.Z2u\u0001"
    )
  ScalaInlineInfo: length = 0x2C (unknown attribute)
   01 00 00 08 00 44 00 66 00 00 4B 00 4C 00 00 5B
   00 4C 00 00 39 00 3A 00 00 2D 00 2E 00 00 34 00
   1F 00 00 1E 00 1F 00 00 27 00 28 00
  ScalaSig: length = 0x3 (unknown attribute)
   05 02 00
