Classfile /Users/mw/Projects/slang-braindump/.jar/jar8/assemble/slang-braindump/assemble/content/argonaut/CursorHistory$.class
  Last modified May 29, 2022; size 2054 bytes
  SHA-256 checksum eeb0a10854ef7c38796adc03d19eeeb15101066413e4caa9b9cafd856f16a868
  Compiled from "CursorHistory.scala"
public final class argonaut.CursorHistory$ implements argonaut.CursorHistorys,java.io.Serializable
  minor version: 0
  major version: 52
  flags: (0x0031) ACC_PUBLIC, ACC_FINAL, ACC_SUPER
  this_class: #2                          // argonaut/CursorHistory$
  super_class: #4                         // java/lang/Object
  interfaces: 2, fields: 1, methods: 7, attributes: 3
Constant pool:
   #1 = Utf8               argonaut/CursorHistory$
   #2 = Class              #1             // argonaut/CursorHistory$
   #3 = Utf8               java/lang/Object
   #4 = Class              #3             // java/lang/Object
   #5 = Utf8               argonaut/CursorHistorys
   #6 = Class              #5             // argonaut/CursorHistorys
   #7 = Utf8               java/io/Serializable
   #8 = Class              #7             // java/io/Serializable
   #9 = Utf8               CursorHistory.scala
  #10 = Utf8               MODULE$
  #11 = Utf8               Largonaut/CursorHistory$;
  #12 = Utf8               <clinit>
  #13 = Utf8               ()V
  #14 = Utf8               <init>
  #15 = NameAndType        #14:#13        // "<init>":()V
  #16 = Methodref          #2.#15         // argonaut/CursorHistory$."<init>":()V
  #17 = NameAndType        #10:#11        // MODULE$:Largonaut/CursorHistory$;
  #18 = Fieldref           #2.#17         // argonaut/CursorHistory$.MODULE$:Largonaut/CursorHistory$;
  #19 = Utf8               $init$
  #20 = Utf8               (Largonaut/CursorHistorys;)V
  #21 = NameAndType        #19:#20        // $init$:(Largonaut/CursorHistorys;)V
  #22 = InterfaceMethodref #6.#21         // argonaut/CursorHistorys.$init$:(Largonaut/CursorHistorys;)V
  #23 = Utf8               empty
  #24 = Utf8               ()Largonaut/CursorHistory;
  #25 = Utf8               empty$
  #26 = Utf8               (Largonaut/CursorHistorys;)Largonaut/CursorHistory;
  #27 = NameAndType        #25:#26        // empty$:(Largonaut/CursorHistorys;)Largonaut/CursorHistory;
  #28 = InterfaceMethodref #6.#27         // argonaut/CursorHistorys.empty$:(Largonaut/CursorHistorys;)Largonaut/CursorHistory;
  #29 = Utf8               this
  #30 = Utf8               start
  #31 = Utf8               (Largonaut/CursorOp;)Largonaut/CursorHistory;
  #32 = Utf8               e
  #33 = Utf8               start$
  #34 = Utf8               (Largonaut/CursorHistorys;Largonaut/CursorOp;)Largonaut/CursorHistory;
  #35 = NameAndType        #33:#34        // start$:(Largonaut/CursorHistorys;Largonaut/CursorOp;)Largonaut/CursorHistory;
  #36 = InterfaceMethodref #6.#35         // argonaut/CursorHistorys.start$:(Largonaut/CursorHistorys;Largonaut/CursorOp;)Largonaut/CursorHistory;
  #37 = Utf8               Largonaut/CursorOp;
  #38 = Utf8               apply
  #39 = Utf8               (Lscala/collection/immutable/List;)Largonaut/CursorHistory;
  #40 = Utf8               (Lscala/collection/immutable/List<Largonaut/CursorOp;>;)Largonaut/CursorHistory;
  #41 = Utf8               toList
  #42 = Utf8               argonaut/CursorHistory
  #43 = Class              #42            // argonaut/CursorHistory
  #44 = Utf8               (Lscala/collection/immutable/List;)V
  #45 = NameAndType        #14:#44        // "<init>":(Lscala/collection/immutable/List;)V
  #46 = Methodref          #43.#45        // argonaut/CursorHistory."<init>":(Lscala/collection/immutable/List;)V
  #47 = Utf8               Lscala/collection/immutable/List;
  #48 = Utf8               unapply
  #49 = Utf8               (Largonaut/CursorHistory;)Lscala/Option;
  #50 = Utf8               (Largonaut/CursorHistory;)Lscala/Option<Lscala/collection/immutable/List<Largonaut/CursorOp;>;>;
  #51 = Utf8               x$0
  #52 = Utf8               scala/None$
  #53 = Class              #52            // scala/None$
  #54 = Utf8               Lscala/None$;
  #55 = NameAndType        #10:#54        // MODULE$:Lscala/None$;
  #56 = Fieldref           #53.#55        // scala/None$.MODULE$:Lscala/None$;
  #57 = Utf8               scala/Some
  #58 = Class              #57            // scala/Some
  #59 = Utf8               ()Lscala/collection/immutable/List;
  #60 = NameAndType        #41:#59        // toList:()Lscala/collection/immutable/List;
  #61 = Methodref          #43.#60        // argonaut/CursorHistory.toList:()Lscala/collection/immutable/List;
  #62 = Utf8               (Ljava/lang/Object;)V
  #63 = NameAndType        #14:#62        // "<init>":(Ljava/lang/Object;)V
  #64 = Methodref          #58.#63        // scala/Some."<init>":(Ljava/lang/Object;)V
  #65 = Utf8               Largonaut/CursorHistory;
  #66 = Utf8               scala/Option
  #67 = Class              #66            // scala/Option
  #68 = Utf8               writeReplace
  #69 = Utf8               ()Ljava/lang/Object;
  #70 = Utf8               scala/runtime/ModuleSerializationProxy
  #71 = Class              #70            // scala/runtime/ModuleSerializationProxy
  #72 = Utf8               (Ljava/lang/Class;)V
  #73 = NameAndType        #14:#72        // "<init>":(Ljava/lang/Class;)V
  #74 = Methodref          #71.#73        // scala/runtime/ModuleSerializationProxy."<init>":(Ljava/lang/Class;)V
  #75 = Methodref          #4.#15         // java/lang/Object."<init>":()V
  #76 = Utf8               Code
  #77 = Utf8               LineNumberTable
  #78 = Utf8               LocalVariableTable
  #79 = Utf8               MethodParameters
  #80 = Utf8               Signature
  #81 = Utf8               StackMapTable
  #82 = Utf8               SourceFile
  #83 = Utf8               ScalaInlineInfo
  #84 = Utf8               Scala
{
  public static final argonaut.CursorHistory$ MODULE$;
    descriptor: Largonaut/CursorHistory$;
    flags: (0x0019) ACC_PUBLIC, ACC_STATIC, ACC_FINAL

  public static {};
    descriptor: ()V
    flags: (0x0009) ACC_PUBLIC, ACC_STATIC
    Code:
      stack=2, locals=0, args_size=0
         0: new           #2                  // class argonaut/CursorHistory$
         3: dup
         4: invokespecial #16                 // Method "<init>":()V
         7: putstatic     #18                 // Field MODULE$:Largonaut/CursorHistory$;
        10: getstatic     #18                 // Field MODULE$:Largonaut/CursorHistory$;
        13: invokestatic  #22                 // InterfaceMethod argonaut/CursorHistorys.$init$:(Largonaut/CursorHistorys;)V
        16: return
      LineNumberTable:
        line 42: 0

  public argonaut.CursorHistory empty();
    descriptor: ()Largonaut/CursorHistory;
    flags: (0x0001) ACC_PUBLIC
    Code:
      stack=1, locals=1, args_size=1
         0: aload_0
         1: invokestatic  #28                 // InterfaceMethod argonaut/CursorHistorys.empty$:(Largonaut/CursorHistorys;)Largonaut/CursorHistory;
         4: areturn
      LineNumberTable:
        line 42: 0
      LocalVariableTable:
        Start  Length  Slot  Name   Signature
            0       5     0  this   Largonaut/CursorHistory$;

  public argonaut.CursorHistory start(argonaut.CursorOp);
    descriptor: (Largonaut/CursorOp;)Largonaut/CursorHistory;
    flags: (0x0001) ACC_PUBLIC
    Code:
      stack=2, locals=2, args_size=2
         0: aload_0
         1: aload_1
         2: invokestatic  #36                 // InterfaceMethod argonaut/CursorHistorys.start$:(Largonaut/CursorHistorys;Largonaut/CursorOp;)Largonaut/CursorHistory;
         5: areturn
      LineNumberTable:
        line 42: 0
      LocalVariableTable:
        Start  Length  Slot  Name   Signature
            0       6     0  this   Largonaut/CursorHistory$;
            0       6     1     e   Largonaut/CursorOp;
    MethodParameters:
      Name                           Flags
      e                              final

  public argonaut.CursorHistory apply(scala.collection.immutable.List<argonaut.CursorOp>);
    descriptor: (Lscala/collection/immutable/List;)Largonaut/CursorHistory;
    flags: (0x0001) ACC_PUBLIC
    Code:
      stack=3, locals=2, args_size=2
         0: new           #43                 // class argonaut/CursorHistory
         3: dup
         4: aload_1
         5: invokespecial #46                 // Method argonaut/CursorHistory."<init>":(Lscala/collection/immutable/List;)V
         8: areturn
      LineNumberTable:
        line 10: 0
      LocalVariableTable:
        Start  Length  Slot  Name   Signature
            0       9     0  this   Largonaut/CursorHistory$;
            0       9     1 toList   Lscala/collection/immutable/List;
    Signature: #40                          // (Lscala/collection/immutable/List<Largonaut/CursorOp;>;)Largonaut/CursorHistory;
    MethodParameters:
      Name                           Flags
      toList                         final

  public scala.Option<scala.collection.immutable.List<argonaut.CursorOp>> unapply(argonaut.CursorHistory);
    descriptor: (Largonaut/CursorHistory;)Lscala/Option;
    flags: (0x0001) ACC_PUBLIC
    Code:
      stack=3, locals=2, args_size=2
         0: aload_1
         1: ifnonnull     10
         4: getstatic     #56                 // Field scala/None$.MODULE$:Lscala/None$;
         7: goto          21
        10: new           #58                 // class scala/Some
        13: dup
        14: aload_1
        15: invokevirtual #61                 // Method argonaut/CursorHistory.toList:()Lscala/collection/immutable/List;
        18: invokespecial #64                 // Method scala/Some."<init>":(Ljava/lang/Object;)V
        21: areturn
      StackMapTable: number_of_entries = 2
        frame_type = 10 /* same */
        frame_type = 74 /* same_locals_1_stack_item */
          stack = [ class scala/Option ]
      LineNumberTable:
        line 10: 0
      LocalVariableTable:
        Start  Length  Slot  Name   Signature
            0      22     0  this   Largonaut/CursorHistory$;
            0      22     1   x$0   Largonaut/CursorHistory;
    Signature: #50                          // (Largonaut/CursorHistory;)Lscala/Option<Lscala/collection/immutable/List<Largonaut/CursorOp;>;>;
    MethodParameters:
      Name                           Flags
      x$0                            final

  private java.lang.Object writeReplace();
    descriptor: ()Ljava/lang/Object;
    flags: (0x0002) ACC_PRIVATE
    Code:
      stack=3, locals=1, args_size=1
         0: new           #71                 // class scala/runtime/ModuleSerializationProxy
         3: dup
         4: ldc           #2                  // class argonaut/CursorHistory$
         6: invokespecial #74                 // Method scala/runtime/ModuleSerializationProxy."<init>":(Ljava/lang/Class;)V
         9: areturn
      LineNumberTable:
        line 42: 0
      LocalVariableTable:
        Start  Length  Slot  Name   Signature
            0      10     0  this   Largonaut/CursorHistory$;

  private argonaut.CursorHistory$();
    descriptor: ()V
    flags: (0x0002) ACC_PRIVATE
    Code:
      stack=1, locals=1, args_size=1
         0: aload_0
         1: invokespecial #75                 // Method java/lang/Object."<init>":()V
         4: return
      LineNumberTable:
        line 42: 0
      LocalVariableTable:
        Start  Length  Slot  Name   Signature
            0       5     0  this   Largonaut/CursorHistory$;
}
SourceFile: "CursorHistory.scala"
  ScalaInlineInfo: length = 0x22 (unknown attribute)
   01 01 00 06 00 0E 00 0D 01 00 26 00 27 01 00 17
   00 18 01 00 1E 00 1F 01 00 30 00 31 01 00 44 00
   45 01
  Scala: length = 0x0 (unknown attribute)

