Classfile /Users/mw/Projects/slang-braindump/.jar/jar8/assemble/slang-braindump/assemble/content/argonaut/CursorOp$.class
  Last modified May 29, 2022; size 1327 bytes
  SHA-256 checksum 3822a0696ed3fada584993813977a3ba610d8f4057631393a8cd86efea4db150
  Compiled from "CursorOp.scala"
public final class argonaut.CursorOp$ implements argonaut.CursorOps,java.io.Serializable
  minor version: 0
  major version: 52
  flags: (0x0031) ACC_PUBLIC, ACC_FINAL, ACC_SUPER
  this_class: #2                          // argonaut/CursorOp$
  super_class: #4                         // java/lang/Object
  interfaces: 2, fields: 1, methods: 6, attributes: 3
Constant pool:
   #1 = Utf8               argonaut/CursorOp$
   #2 = Class              #1             // argonaut/CursorOp$
   #3 = Utf8               java/lang/Object
   #4 = Class              #3             // java/lang/Object
   #5 = Utf8               argonaut/CursorOps
   #6 = Class              #5             // argonaut/CursorOps
   #7 = Utf8               java/io/Serializable
   #8 = Class              #7             // java/io/Serializable
   #9 = Utf8               CursorOp.scala
  #10 = Utf8               MODULE$
  #11 = Utf8               Largonaut/CursorOp$;
  #12 = Utf8               <clinit>
  #13 = Utf8               ()V
  #14 = Utf8               <init>
  #15 = NameAndType        #14:#13        // "<init>":()V
  #16 = Methodref          #2.#15         // argonaut/CursorOp$."<init>":()V
  #17 = NameAndType        #10:#11        // MODULE$:Largonaut/CursorOp$;
  #18 = Fieldref           #2.#17         // argonaut/CursorOp$.MODULE$:Largonaut/CursorOp$;
  #19 = Utf8               $init$
  #20 = Utf8               (Largonaut/CursorOps;)V
  #21 = NameAndType        #19:#20        // $init$:(Largonaut/CursorOps;)V
  #22 = InterfaceMethodref #6.#21         // argonaut/CursorOps.$init$:(Largonaut/CursorOps;)V
  #23 = Utf8               reattemptOp
  #24 = Utf8               ()Largonaut/CursorOp;
  #25 = Utf8               reattemptOp$
  #26 = Utf8               (Largonaut/CursorOps;)Largonaut/CursorOp;
  #27 = NameAndType        #25:#26        // reattemptOp$:(Largonaut/CursorOps;)Largonaut/CursorOp;
  #28 = InterfaceMethodref #6.#27         // argonaut/CursorOps.reattemptOp$:(Largonaut/CursorOps;)Largonaut/CursorOp;
  #29 = Utf8               this
  #30 = Utf8               failedOp
  #31 = Utf8               (Largonaut/CursorOpElement;)Largonaut/CursorOp;
  #32 = Utf8               o
  #33 = Utf8               failedOp$
  #34 = Utf8               (Largonaut/CursorOps;Largonaut/CursorOpElement;)Largonaut/CursorOp;
  #35 = NameAndType        #33:#34        // failedOp$:(Largonaut/CursorOps;Largonaut/CursorOpElement;)Largonaut/CursorOp;
  #36 = InterfaceMethodref #6.#35         // argonaut/CursorOps.failedOp$:(Largonaut/CursorOps;Largonaut/CursorOpElement;)Largonaut/CursorOp;
  #37 = Utf8               Largonaut/CursorOpElement;
  #38 = Utf8               apply
  #39 = Utf8               argonaut/El
  #40 = Class              #39            // argonaut/El
  #41 = Utf8               (Largonaut/CursorOpElement;Z)V
  #42 = NameAndType        #14:#41        // "<init>":(Largonaut/CursorOpElement;Z)V
  #43 = Methodref          #40.#42        // argonaut/El."<init>":(Largonaut/CursorOpElement;Z)V
  #44 = Utf8               writeReplace
  #45 = Utf8               ()Ljava/lang/Object;
  #46 = Utf8               scala/runtime/ModuleSerializationProxy
  #47 = Class              #46            // scala/runtime/ModuleSerializationProxy
  #48 = Utf8               (Ljava/lang/Class;)V
  #49 = NameAndType        #14:#48        // "<init>":(Ljava/lang/Class;)V
  #50 = Methodref          #47.#49        // scala/runtime/ModuleSerializationProxy."<init>":(Ljava/lang/Class;)V
  #51 = Methodref          #4.#15         // java/lang/Object."<init>":()V
  #52 = Utf8               Code
  #53 = Utf8               LineNumberTable
  #54 = Utf8               LocalVariableTable
  #55 = Utf8               MethodParameters
  #56 = Utf8               SourceFile
  #57 = Utf8               ScalaInlineInfo
  #58 = Utf8               Scala
{
  public static final argonaut.CursorOp$ MODULE$;
    descriptor: Largonaut/CursorOp$;
    flags: (0x0019) ACC_PUBLIC, ACC_STATIC, ACC_FINAL

  public static {};
    descriptor: ()V
    flags: (0x0009) ACC_PUBLIC, ACC_STATIC
    Code:
      stack=2, locals=0, args_size=0
         0: new           #2                  // class argonaut/CursorOp$
         3: dup
         4: invokespecial #16                 // Method "<init>":()V
         7: putstatic     #18                 // Field MODULE$:Largonaut/CursorOp$;
        10: getstatic     #18                 // Field MODULE$:Largonaut/CursorOp$;
        13: invokestatic  #22                 // InterfaceMethod argonaut/CursorOps.$init$:(Largonaut/CursorOps;)V
        16: return
      LineNumberTable:
        line 26: 0

  public argonaut.CursorOp reattemptOp();
    descriptor: ()Largonaut/CursorOp;
    flags: (0x0001) ACC_PUBLIC
    Code:
      stack=1, locals=1, args_size=1
         0: aload_0
         1: invokestatic  #28                 // InterfaceMethod argonaut/CursorOps.reattemptOp$:(Largonaut/CursorOps;)Largonaut/CursorOp;
         4: areturn
      LineNumberTable:
        line 26: 0
      LocalVariableTable:
        Start  Length  Slot  Name   Signature
            0       5     0  this   Largonaut/CursorOp$;

  public argonaut.CursorOp failedOp(argonaut.CursorOpElement);
    descriptor: (Largonaut/CursorOpElement;)Largonaut/CursorOp;
    flags: (0x0001) ACC_PUBLIC
    Code:
      stack=2, locals=2, args_size=2
         0: aload_0
         1: aload_1
         2: invokestatic  #36                 // InterfaceMethod argonaut/CursorOps.failedOp$:(Largonaut/CursorOps;Largonaut/CursorOpElement;)Largonaut/CursorOp;
         5: areturn
      LineNumberTable:
        line 26: 0
      LocalVariableTable:
        Start  Length  Slot  Name   Signature
            0       6     0  this   Largonaut/CursorOp$;
            0       6     1     o   Largonaut/CursorOpElement;
    MethodParameters:
      Name                           Flags
      o                              final

  public argonaut.CursorOp apply(argonaut.CursorOpElement);
    descriptor: (Largonaut/CursorOpElement;)Largonaut/CursorOp;
    flags: (0x0001) ACC_PUBLIC
    Code:
      stack=4, locals=2, args_size=2
         0: new           #40                 // class argonaut/El
         3: dup
         4: aload_1
         5: iconst_1
         6: invokespecial #43                 // Method argonaut/El."<init>":(Largonaut/CursorOpElement;Z)V
         9: areturn
      LineNumberTable:
        line 28: 0
      LocalVariableTable:
        Start  Length  Slot  Name   Signature
            0      10     0  this   Largonaut/CursorOp$;
            0      10     1     o   Largonaut/CursorOpElement;
    MethodParameters:
      Name                           Flags
      o                              final

  private java.lang.Object writeReplace();
    descriptor: ()Ljava/lang/Object;
    flags: (0x0002) ACC_PRIVATE
    Code:
      stack=3, locals=1, args_size=1
         0: new           #47                 // class scala/runtime/ModuleSerializationProxy
         3: dup
         4: ldc           #2                  // class argonaut/CursorOp$
         6: invokespecial #50                 // Method scala/runtime/ModuleSerializationProxy."<init>":(Ljava/lang/Class;)V
         9: areturn
      LineNumberTable:
        line 26: 0
      LocalVariableTable:
        Start  Length  Slot  Name   Signature
            0      10     0  this   Largonaut/CursorOp$;

  private argonaut.CursorOp$();
    descriptor: ()V
    flags: (0x0002) ACC_PRIVATE
    Code:
      stack=1, locals=1, args_size=1
         0: aload_0
         1: invokespecial #51                 // Method java/lang/Object."<init>":()V
         4: return
      LineNumberTable:
        line 26: 0
      LocalVariableTable:
        Start  Length  Slot  Name   Signature
            0       5     0  this   Largonaut/CursorOp$;
}
SourceFile: "CursorOp.scala"
  ScalaInlineInfo: length = 0x1D (unknown attribute)
   01 01 00 05 00 0E 00 0D 01 00 26 00 1F 01 00 1E
   00 1F 01 00 17 00 18 01 00 2C 00 2D 01
  Scala: length = 0x0 (unknown attribute)

