Classfile /Users/mw/Projects/slang-braindump/.jar/jar8/assemble/slang-braindump/assemble/content/argonaut/DecodeResults.class
  Last modified May 29, 2022; size 3826 bytes
  SHA-256 checksum 44a6a7ae7ba482d38ec4447876057e5e8700e6409247e871c19ce6b0553a5737
  Compiled from "DecodeResult.scala"
public interface argonaut.DecodeResults
  minor version: 0
  major version: 52
  flags: (0x0601) ACC_PUBLIC, ACC_INTERFACE, ACC_ABSTRACT
  this_class: #2                          // argonaut/DecodeResults
  super_class: #4                         // java/lang/Object
  interfaces: 0, fields: 0, methods: 7, attributes: 4
Constant pool:
    #1 = Utf8               argonaut/DecodeResults
    #2 = Class              #1            // argonaut/DecodeResults
    #3 = Utf8               java/lang/Object
    #4 = Class              #3            // java/lang/Object
    #5 = Utf8               DecodeResult.scala
    #6 = Utf8               Lscala/reflect/ScalaSignature;
    #7 = Utf8               bytes
    #8 = Utf8               \u0006\u0005=4qAB\u0004\u0011\u0002\u0007\u0005!\u0002C\u0003\u0012\u0001\u0011\u0005!#\u0002\u0003\u0017\u0001\u00019\u0002\"\u0002 \u0001\t\u0003y\u0004\"\u0002%\u0001\t\u0003I\u0005\"\u0002*\u0001\t\u000b\u0019&!\u0004#fG>$WMU3tk2$8OC\u0001\t\u0003!\t\'oZ8oCV$8\u0001A\n\u0003\u0001-\u0001\"\u0001D\b\u000e\u00035Q\u0011AD\u0001\u0006g\u000e\fG.Y\u0005\u0003!5\u0011a!\u00118z%\u00164\u0017A\u0002\u0013j]&$H\u0005F\u0001\u0014!\taA#\u0003\u0002\u0016\u001b\t!QK\\5u\u00051!UmY8eK\u0016KG\u000f[3s+\tAR\u0007\u0005\u0003\u001aC\u0011\u001adB\u0001\u000e \u001d\tYb$D\u0001\u001d\u0015\ti\u0012\"\u0001\u0004=e>|GOP\u0005\u0002\u001d%\u0011\u0001%D\u0001\ba\u0006\u001c7.Y4f\u0013\t\u00113E\u0001\u0004FSRDWM\u001d\u0006\u0003A5\u0001B\u0001D\u0013(_%\u0011a%\u0004\u0002\u0007)V\u0004H.\u001a\u001a\u0011\u0005!bcBA\u0015+!\tYR\"\u0003\u0002,\u001b\u00051\u0001K]3eK\u001aL!!\f\u0018\u0003\rM#(/\u001b8h\u0015\tYS\u0002\u0005\u00021c5\tq!\u0003\u00023\u000f\ti1)\u001e:t_JD\u0015n\u001d;pef\u0004\"\u0001N\u001b\r\u0001\u0011)aG\u0001b\u0001o\t\t\u0011)\u0005\u00029wA\u0011A\"O\u0005\u0003u5\u0011qAT8uQ&tw\r\u0005\u0002\ry%\u0011Q(\u0004\u0002\u0004\u0003:L\u0018\u0001C8l%\u0016\u001cX\u000f\u001c;\u0016\u0005\u0001+ECA!G!\r\u0001$\tR\u0005\u0003\u0007\u001e\u0011A\u0002R3d_\u0012,\'+Z:vYR\u0004\"\u0001N#\u0005\u000bY\u001a!\u0019A\u001c\t\u000b\u001d\u001b\u0001\u0019\u0001#\u0002\u000bY\fG.^3\u0002\u0015\u0019\f\u0017\u000e\u001c*fgVdG/\u0006\u0002K\u001bR\u00191J\u0014)\u0011\u0007A\u0012E\n\u0005\u00025\u001b\u0012)a\u0007\u0002b\u0001o!)q\n\u0002a\u0001O\u0005\t1\u000fC\u0003R\t\u0001\u0007q&A\u0001i\u0003\u0011awn\u001c9\u0016\u0007Qcf\u000b\u0006\u0003V1v\u0013\u0007C\u0001\u001bW\t\u00159VA1\u00018\u0005\u0005A\u0006\"B-\u0006\u0001\u0004Q\u0016!\u00013\u0011\u0007A\u00125\f\u0005\u000259\u0012)a\'\u0002b\u0001o!)a,\u0002a\u0001?\u0006\tQ\rE\u0003\rA\u001ezS+\u0003\u0002b\u001b\tIa)\u001e8di&|gN\r\u0005\u0006G\u0016\u0001\r\u0001Z\u0001\u0002MB!A\"Z.h\u0013\t1WBA\u0005Gk:\u001cG/[8ocA!\u0011$I+[Q\t)\u0011\u000e\u0005\u0002k[6\t1N\u0003\u0002m\u001b\u0005Q\u0011M\u001c8pi\u0006$\u0018n\u001c8\n\u00059\\\'a\u0002;bS2\u0014Xm\u0019
    #9 = Utf8               okResult$
   #10 = Utf8               (Largonaut/DecodeResults;Ljava/lang/Object;)Largonaut/DecodeResult;
   #11 = Utf8               $this
   #12 = Utf8               value
   #13 = Utf8               okResult
   #14 = Utf8               (Ljava/lang/Object;)Largonaut/DecodeResult;
   #15 = NameAndType        #13:#14       // okResult:(Ljava/lang/Object;)Largonaut/DecodeResult;
   #16 = InterfaceMethodref #2.#15        // argonaut/DecodeResults.okResult:(Ljava/lang/Object;)Largonaut/DecodeResult;
   #17 = Utf8               Largonaut/DecodeResults;
   #18 = Utf8               Ljava/lang/Object;
   #19 = Utf8               <A:Ljava/lang/Object;>(TA;)Largonaut/DecodeResult<TA;>;
   #20 = Utf8               argonaut/DecodeResult$
   #21 = Class              #20           // argonaut/DecodeResult$
   #22 = Utf8               MODULE$
   #23 = Utf8               Largonaut/DecodeResult$;
   #24 = NameAndType        #22:#23       // MODULE$:Largonaut/DecodeResult$;
   #25 = Fieldref           #21.#24       // argonaut/DecodeResult$.MODULE$:Largonaut/DecodeResult$;
   #26 = Utf8               ok
   #27 = NameAndType        #26:#14       // ok:(Ljava/lang/Object;)Largonaut/DecodeResult;
   #28 = Methodref          #21.#27       // argonaut/DecodeResult$.ok:(Ljava/lang/Object;)Largonaut/DecodeResult;
   #29 = Utf8               this
   #30 = Utf8               failResult$
   #31 = Utf8               (Largonaut/DecodeResults;Ljava/lang/String;Largonaut/CursorHistory;)Largonaut/DecodeResult;
   #32 = Utf8               s
   #33 = Utf8               h
   #34 = Utf8               failResult
   #35 = Utf8               (Ljava/lang/String;Largonaut/CursorHistory;)Largonaut/DecodeResult;
   #36 = NameAndType        #34:#35       // failResult:(Ljava/lang/String;Largonaut/CursorHistory;)Largonaut/DecodeResult;
   #37 = InterfaceMethodref #2.#36        // argonaut/DecodeResults.failResult:(Ljava/lang/String;Largonaut/CursorHistory;)Largonaut/DecodeResult;
   #38 = Utf8               Ljava/lang/String;
   #39 = Utf8               Largonaut/CursorHistory;
   #40 = Utf8               <A:Ljava/lang/Object;>(Ljava/lang/String;Largonaut/CursorHistory;)Largonaut/DecodeResult<TA;>;
   #41 = Utf8               fail
   #42 = NameAndType        #41:#35       // fail:(Ljava/lang/String;Largonaut/CursorHistory;)Largonaut/DecodeResult;
   #43 = Methodref          #21.#42       // argonaut/DecodeResult$.fail:(Ljava/lang/String;Largonaut/CursorHistory;)Largonaut/DecodeResult;
   #44 = Utf8               loop$
   #45 = Utf8               (Largonaut/DecodeResults;Largonaut/DecodeResult;Lscala/Function2;Lscala/Function1;)Ljava/lang/Object;
   #46 = Utf8               d
   #47 = Utf8               e
   #48 = Utf8               f
   #49 = Utf8               loop
   #50 = Utf8               (Largonaut/DecodeResult;Lscala/Function2;Lscala/Function1;)Ljava/lang/Object;
   #51 = NameAndType        #49:#50       // loop:(Largonaut/DecodeResult;Lscala/Function2;Lscala/Function1;)Ljava/lang/Object;
   #52 = InterfaceMethodref #2.#51        // argonaut/DecodeResults.loop:(Largonaut/DecodeResult;Lscala/Function2;Lscala/Function1;)Ljava/lang/Object;
   #53 = Utf8               Largonaut/DecodeResult;
   #54 = Utf8               Lscala/Function2;
   #55 = Utf8               Lscala/Function1;
   #56 = Utf8               <A:Ljava/lang/Object;X:Ljava/lang/Object;>(Largonaut/DecodeResult<TA;>;Lscala/Function2<Ljava/lang/String;Largonaut/CursorHistory;TX;>;Lscala/Function1<TA;Lscala/util/Either<TX;Largonaut/DecodeResult<TA;>;>;>;)TX;
   #57 = Utf8               argonaut/DecodeResult
   #58 = Class              #57           // argonaut/DecodeResult
   #59 = Utf8               isError
   #60 = Utf8               ()Z
   #61 = NameAndType        #59:#60       // isError:()Z
   #62 = Methodref          #58.#61       // argonaut/DecodeResult.isError:()Z
   #63 = Utf8               message
   #64 = Utf8               ()Lscala/Option;
   #65 = NameAndType        #63:#64       // message:()Lscala/Option;
   #66 = Methodref          #58.#65       // argonaut/DecodeResult.message:()Lscala/Option;
   #67 = Utf8               scala/Option
   #68 = Class              #67           // scala/Option
   #69 = Utf8               get
   #70 = Utf8               ()Ljava/lang/Object;
   #71 = NameAndType        #69:#70       // get:()Ljava/lang/Object;
   #72 = Methodref          #68.#71       // scala/Option.get:()Ljava/lang/Object;
   #73 = Utf8               history
   #74 = NameAndType        #73:#64       // history:()Lscala/Option;
   #75 = Methodref          #58.#74       // argonaut/DecodeResult.history:()Lscala/Option;
   #76 = Utf8               scala/Function2
   #77 = Class              #76           // scala/Function2
   #78 = Utf8               apply
   #79 = Utf8               (Ljava/lang/Object;Ljava/lang/Object;)Ljava/lang/Object;
   #80 = NameAndType        #78:#79       // apply:(Ljava/lang/Object;Ljava/lang/Object;)Ljava/lang/Object;
   #81 = InterfaceMethodref #77.#80       // scala/Function2.apply:(Ljava/lang/Object;Ljava/lang/Object;)Ljava/lang/Object;
   #82 = NameAndType        #12:#64       // value:()Lscala/Option;
   #83 = Methodref          #58.#82       // argonaut/DecodeResult.value:()Lscala/Option;
   #84 = Utf8               scala/Function1
   #85 = Class              #84           // scala/Function1
   #86 = Utf8               (Ljava/lang/Object;)Ljava/lang/Object;
   #87 = NameAndType        #78:#86       // apply:(Ljava/lang/Object;)Ljava/lang/Object;
   #88 = InterfaceMethodref #85.#87       // scala/Function1.apply:(Ljava/lang/Object;)Ljava/lang/Object;
   #89 = Utf8               scala/util/Either
   #90 = Class              #89           // scala/util/Either
   #91 = Utf8               scala/util/Left
   #92 = Class              #91           // scala/util/Left
   #93 = NameAndType        #12:#70       // value:()Ljava/lang/Object;
   #94 = Methodref          #92.#93       // scala/util/Left.value:()Ljava/lang/Object;
   #95 = Utf8               scala/util/Right
   #96 = Class              #95           // scala/util/Right
   #97 = Methodref          #96.#93       // scala/util/Right.value:()Ljava/lang/Object;
   #98 = Utf8               scala/MatchError
   #99 = Class              #98           // scala/MatchError
  #100 = Utf8               <init>
  #101 = Utf8               (Ljava/lang/Object;)V
  #102 = NameAndType        #100:#101     // "<init>":(Ljava/lang/Object;)V
  #103 = Methodref          #99.#102      // scala/MatchError."<init>":(Ljava/lang/Object;)V
  #104 = Utf8               x
  #105 = Utf8               a
  #106 = Utf8               $init$
  #107 = Utf8               (Largonaut/DecodeResults;)V
  #108 = Utf8               Code
  #109 = Utf8               LineNumberTable
  #110 = Utf8               LocalVariableTable
  #111 = Utf8               MethodParameters
  #112 = Utf8               Signature
  #113 = Utf8               StackMapTable
  #114 = Utf8               SourceFile
  #115 = Utf8               RuntimeVisibleAnnotations
  #116 = Utf8               ScalaInlineInfo
  #117 = Utf8               ScalaSig
{
  public static argonaut.DecodeResult okResult$(argonaut.DecodeResults, java.lang.Object);
    descriptor: (Largonaut/DecodeResults;Ljava/lang/Object;)Largonaut/DecodeResult;
    flags: (0x1009) ACC_PUBLIC, ACC_STATIC, ACC_SYNTHETIC
    Code:
      stack=2, locals=2, args_size=2
         0: aload_0
         1: aload_1
         2: invokespecial #16                 // InterfaceMethod okResult:(Ljava/lang/Object;)Largonaut/DecodeResult;
         5: areturn
      LineNumberTable:
        line 66: 0
      LocalVariableTable:
        Start  Length  Slot  Name   Signature
            0       6     0 $this   Largonaut/DecodeResults;
            0       6     1 value   Ljava/lang/Object;
    MethodParameters:
      Name                           Flags
      $this                          final synthetic
      value                          final

  public default <A extends java.lang.Object> argonaut.DecodeResult<A> okResult(A);
    descriptor: (Ljava/lang/Object;)Largonaut/DecodeResult;
    flags: (0x0001) ACC_PUBLIC
    Code:
      stack=2, locals=2, args_size=2
         0: getstatic     #25                 // Field argonaut/DecodeResult$.MODULE$:Largonaut/DecodeResult$;
         3: aload_1
         4: invokevirtual #28                 // Method argonaut/DecodeResult$.ok:(Ljava/lang/Object;)Largonaut/DecodeResult;
         7: areturn
      LineNumberTable:
        line 67: 0
      LocalVariableTable:
        Start  Length  Slot  Name   Signature
            0       8     0  this   Largonaut/DecodeResults;
            0       8     1 value   Ljava/lang/Object;
    Signature: #19                          // <A:Ljava/lang/Object;>(TA;)Largonaut/DecodeResult<TA;>;
    MethodParameters:
      Name                           Flags
      value                          final

  public static argonaut.DecodeResult failResult$(argonaut.DecodeResults, java.lang.String, argonaut.CursorHistory);
    descriptor: (Largonaut/DecodeResults;Ljava/lang/String;Largonaut/CursorHistory;)Largonaut/DecodeResult;
    flags: (0x1009) ACC_PUBLIC, ACC_STATIC, ACC_SYNTHETIC
    Code:
      stack=3, locals=3, args_size=3
         0: aload_0
         1: aload_1
         2: aload_2
         3: invokespecial #37                 // InterfaceMethod failResult:(Ljava/lang/String;Largonaut/CursorHistory;)Largonaut/DecodeResult;
         6: areturn
      LineNumberTable:
        line 69: 0
      LocalVariableTable:
        Start  Length  Slot  Name   Signature
            0       7     0 $this   Largonaut/DecodeResults;
            0       7     1     s   Ljava/lang/String;
            0       7     2     h   Largonaut/CursorHistory;
    MethodParameters:
      Name                           Flags
      $this                          final synthetic
      s                              final
      h                              final

  public default <A extends java.lang.Object> argonaut.DecodeResult<A> failResult(java.lang.String, argonaut.CursorHistory);
    descriptor: (Ljava/lang/String;Largonaut/CursorHistory;)Largonaut/DecodeResult;
    flags: (0x0001) ACC_PUBLIC
    Code:
      stack=3, locals=3, args_size=3
         0: getstatic     #25                 // Field argonaut/DecodeResult$.MODULE$:Largonaut/DecodeResult$;
         3: aload_1
         4: aload_2
         5: invokevirtual #43                 // Method argonaut/DecodeResult$.fail:(Ljava/lang/String;Largonaut/CursorHistory;)Largonaut/DecodeResult;
         8: areturn
      LineNumberTable:
        line 70: 0
      LocalVariableTable:
        Start  Length  Slot  Name   Signature
            0       9     0  this   Largonaut/DecodeResults;
            0       9     1     s   Ljava/lang/String;
            0       9     2     h   Largonaut/CursorHistory;
    Signature: #40                          // <A:Ljava/lang/Object;>(Ljava/lang/String;Largonaut/CursorHistory;)Largonaut/DecodeResult<TA;>;
    MethodParameters:
      Name                           Flags
      s                              final
      h                              final

  public static java.lang.Object loop$(argonaut.DecodeResults, argonaut.DecodeResult, scala.Function2, scala.Function1);
    descriptor: (Largonaut/DecodeResults;Largonaut/DecodeResult;Lscala/Function2;Lscala/Function1;)Ljava/lang/Object;
    flags: (0x1009) ACC_PUBLIC, ACC_STATIC, ACC_SYNTHETIC
    Code:
      stack=4, locals=4, args_size=4
         0: aload_0
         1: aload_1
         2: aload_2
         3: aload_3
         4: invokespecial #52                 // InterfaceMethod loop:(Largonaut/DecodeResult;Lscala/Function2;Lscala/Function1;)Ljava/lang/Object;
         7: areturn
      LineNumberTable:
        line 73: 0
      LocalVariableTable:
        Start  Length  Slot  Name   Signature
            0       8     0 $this   Largonaut/DecodeResults;
            0       8     1     d   Largonaut/DecodeResult;
            0       8     2     e   Lscala/Function2;
            0       8     3     f   Lscala/Function1;
    MethodParameters:
      Name                           Flags
      $this                          final synthetic
      d                              final
      e                              final
      f                              final

  public default <A extends java.lang.Object, X extends java.lang.Object> X loop(argonaut.DecodeResult<A>, scala.Function2<java.lang.String, argonaut.CursorHistory, X>, scala.Function1<A, scala.util.Either<X, argonaut.DecodeResult<A>>>);
    descriptor: (Largonaut/DecodeResult;Lscala/Function2;Lscala/Function1;)Ljava/lang/Object;
    flags: (0x0001) ACC_PUBLIC
    Code:
      stack=3, locals=11, args_size=4
         0: aload_1
         1: invokevirtual #62                 // Method argonaut/DecodeResult.isError:()Z
         4: ifeq          30
         7: aload_2
         8: aload_1
         9: invokevirtual #66                 // Method argonaut/DecodeResult.message:()Lscala/Option;
        12: invokevirtual #72                 // Method scala/Option.get:()Ljava/lang/Object;
        15: aload_1
        16: invokevirtual #75                 // Method argonaut/DecodeResult.history:()Lscala/Option;
        19: invokevirtual #72                 // Method scala/Option.get:()Ljava/lang/Object;
        22: invokeinterface #81,  3           // InterfaceMethod scala/Function2.apply:(Ljava/lang/Object;Ljava/lang/Object;)Ljava/lang/Object;
        27: goto          130
        30: aload_3
        31: aload_1
        32: invokevirtual #83                 // Method argonaut/DecodeResult.value:()Lscala/Option;
        35: invokevirtual #72                 // Method scala/Option.get:()Ljava/lang/Object;
        38: invokeinterface #88,  2           // InterfaceMethod scala/Function1.apply:(Ljava/lang/Object;)Ljava/lang/Object;
        43: checkcast     #90                 // class scala/util/Either
        46: astore        6
        48: aload         6
        50: instanceof    #92                 // class scala/util/Left
        53: ifeq          77
        56: aload         6
        58: checkcast     #92                 // class scala/util/Left
        61: astore        7
        63: aload         7
        65: invokevirtual #94                 // Method scala/util/Left.value:()Ljava/lang/Object;
        68: astore        8
        70: aload         8
        72: astore        5
        74: goto          128
        77: goto          80
        80: aload         6
        82: instanceof    #96                 // class scala/util/Right
        85: ifeq          115
        88: aload         6
        90: checkcast     #96                 // class scala/util/Right
        93: astore        9
        95: aload         9
        97: invokevirtual #97                 // Method scala/util/Right.value:()Ljava/lang/Object;
       100: checkcast     #58                 // class argonaut/DecodeResult
       103: astore        10
       105: aload         10
       107: aload_2
       108: aload_3
       109: astore_3
       110: astore_2
       111: astore_1
       112: goto          0
       115: goto          118
       118: new           #99                 // class scala/MatchError
       121: dup
       122: aload         6
       124: invokespecial #103                // Method scala/MatchError."<init>":(Ljava/lang/Object;)V
       127: athrow
       128: aload         5
       130: areturn
      StackMapTable: number_of_entries = 8
        frame_type = 0 /* same */
        frame_type = 29 /* same */
        frame_type = 254 /* append */
          offset_delta = 46
          locals = [ top, top, class scala/util/Either ]
        frame_type = 2 /* same */
        frame_type = 34 /* same */
        frame_type = 2 /* same */
        frame_type = 255 /* full_frame */
          offset_delta = 9
          locals = [ class argonaut/DecodeResults, class argonaut/DecodeResult, class scala/Function2, class scala/Function1, top, class java/lang/Object, class scala/util/Either, class scala/util/Left, class java/lang/Object ]
          stack = []
        frame_type = 255 /* full_frame */
          offset_delta = 1
          locals = [ class argonaut/DecodeResults, class argonaut/DecodeResult, class scala/Function2, class scala/Function1 ]
          stack = [ class java/lang/Object ]
      LineNumberTable:
        line 74: 0
        line 75: 7
        line 77: 30
        line 78: 48
        line 79: 80
        line 77: 118
      LocalVariableTable:
        Start  Length  Slot  Name   Signature
           68       9     8     x   Ljava/lang/Object;
          103      12    10     a   Largonaut/DecodeResult;
            0     131     0  this   Largonaut/DecodeResults;
            0     131     1     d   Largonaut/DecodeResult;
            0     131     2     e   Lscala/Function2;
            0     131     3     f   Lscala/Function1;
    Signature: #56                          // <A:Ljava/lang/Object;X:Ljava/lang/Object;>(Largonaut/DecodeResult<TA;>;Lscala/Function2<Ljava/lang/String;Largonaut/CursorHistory;TX;>;Lscala/Function1<TA;Lscala/util/Either<TX;Largonaut/DecodeResult<TA;>;>;>;)TX;
    MethodParameters:
      Name                           Flags
      d                              final
      e                              final
      f                              final

  public static void $init$(argonaut.DecodeResults);
    descriptor: (Largonaut/DecodeResults;)V
    flags: (0x0009) ACC_PUBLIC, ACC_STATIC
    Code:
      stack=0, locals=1, args_size=1
         0: return
      LineNumberTable:
        line 63: 0
      LocalVariableTable:
        Start  Length  Slot  Name   Signature
            0       1     0 $this   Largonaut/DecodeResults;
    MethodParameters:
      Name                           Flags
      $this                          final synthetic
}
SourceFile: "DecodeResult.scala"
RuntimeVisibleAnnotations:
  0: #6(#7=s#8)
    scala.reflect.ScalaSignature(
      bytes="\u0006\u0005=4qAB\u0004\u0011\u0002\u0007\u0005!\u0002C\u0003\u0012\u0001\u0011\u0005!#\u0002\u0003\u0017\u0001\u00019\u0002\"\u0002 \u0001\t\u0003y\u0004\"\u0002%\u0001\t\u0003I\u0005\"\u0002*\u0001\t\u000b\u0019&!\u0004#fG>$WMU3tk2$8OC\u0001\t\u0003!\t\'oZ8oCV$8\u0001A\n\u0003\u0001-\u0001\"\u0001D\b\u000e\u00035Q\u0011AD\u0001\u0006g\u000e\fG.Y\u0005\u0003!5\u0011a!\u00118z%\u00164\u0017A\u0002\u0013j]&$H\u0005F\u0001\u0014!\taA#\u0003\u0002\u0016\u001b\t!QK\\5u\u00051!UmY8eK\u0016KG\u000f[3s+\tAR\u0007\u0005\u0003\u001aC\u0011\u001adB\u0001\u000e \u001d\tYb$D\u0001\u001d\u0015\ti\u0012\"\u0001\u0004=e>|GOP\u0005\u0002\u001d%\u0011\u0001%D\u0001\ba\u0006\u001c7.Y4f\u0013\t\u00113E\u0001\u0004FSRDWM\u001d\u0006\u0003A5\u0001B\u0001D\u0013(_%\u0011a%\u0004\u0002\u0007)V\u0004H.\u001a\u001a\u0011\u0005!bcBA\u0015+!\tYR\"\u0003\u0002,\u001b\u00051\u0001K]3eK\u001aL!!\f\u0018\u0003\rM#(/\u001b8h\u0015\tYS\u0002\u0005\u00021c5\tq!\u0003\u00023\u000f\ti1)\u001e:t_JD\u0015n\u001d;pef\u0004\"\u0001N\u001b\r\u0001\u0011)aG\u0001b\u0001o\t\t\u0011)\u0005\u00029wA\u0011A\"O\u0005\u0003u5\u0011qAT8uQ&tw\r\u0005\u0002\ry%\u0011Q(\u0004\u0002\u0004\u0003:L\u0018\u0001C8l%\u0016\u001cX\u000f\u001c;\u0016\u0005\u0001+ECA!G!\r\u0001$\tR\u0005\u0003\u0007\u001e\u0011A\u0002R3d_\u0012,\'+Z:vYR\u0004\"\u0001N#\u0005\u000bY\u001a!\u0019A\u001c\t\u000b\u001d\u001b\u0001\u0019\u0001#\u0002\u000bY\fG.^3\u0002\u0015\u0019\f\u0017\u000e\u001c*fgVdG/\u0006\u0002K\u001bR\u00191J\u0014)\u0011\u0007A\u0012E\n\u0005\u00025\u001b\u0012)a\u0007\u0002b\u0001o!)q\n\u0002a\u0001O\u0005\t1\u000fC\u0003R\t\u0001\u0007q&A\u0001i\u0003\u0011awn\u001c9\u0016\u0007Qcf\u000b\u0006\u0003V1v\u0013\u0007C\u0001\u001bW\t\u00159VA1\u00018\u0005\u0005A\u0006\"B-\u0006\u0001\u0004Q\u0016!\u00013\u0011\u0007A\u00125\f\u0005\u000259\u0012)a\'\u0002b\u0001o!)a,\u0002a\u0001?\u0006\tQ\rE\u0003\rA\u001ezS+\u0003\u0002b\u001b\tIa)\u001e8di&|gN\r\u0005\u0006G\u0016\u0001\r\u0001Z\u0001\u0002MB!A\"Z.h\u0013\t1WBA\u0005Gk:\u001cG/[8ocA!\u0011$I+[Q\t)\u0011\u000e\u0005\u0002k[6\t1N\u0003\u0002m\u001b\u0005Q\u0011M\u001c8pi\u0006$\u0018n\u001c8\n\u00059\\\'a\u0002;bS2\u0014Xm\u0019"
    )
  ScalaInlineInfo: length = 0x27 (unknown attribute)
   01 00 00 07 00 6A 00 6B 01 00 22 00 23 00 00 1E
   00 1F 01 00 31 00 32 01 00 2C 00 2D 01 00 0D 00
   0E 00 00 09 00 0A 01
  ScalaSig: length = 0x3 (unknown attribute)
   05 02 00
