Classfile /Users/mw/Projects/slang-braindump/.jar/jar8/assemble/slang-braindump/assemble/content/argonaut/HCursor.class
  Last modified May 29, 2022; size 21564 bytes
  SHA-256 checksum 87c3c46fff34d5b6d3a996929e39ee84510ab1bf338620f93d7a0c4f5cbf4ca4
  Compiled from "HCursor.scala"
public class argonaut.HCursor implements scala.Product,java.io.Serializable
  minor version: 0
  major version: 52
  flags: (0x0021) ACC_PUBLIC, ACC_SUPER
  this_class: #2                          // argonaut/HCursor
  super_class: #4                         // java/lang/Object
  interfaces: 2, fields: 2, methods: 97, attributes: 6
Constant pool:
    #1 = Utf8               argonaut/HCursor
    #2 = Class              #1            // argonaut/HCursor
    #3 = Utf8               java/lang/Object
    #4 = Class              #3            // java/lang/Object
    #5 = Utf8               scala/Product
    #6 = Class              #5            // scala/Product
    #7 = Utf8               java/io/Serializable
    #8 = Class              #7            // java/io/Serializable
    #9 = Utf8               HCursor.scala
   #10 = Utf8               Lscala/reflect/ScalaSignature;
   #11 = Utf8               bytes
   #12 = Utf8               \u0006\u0005\r\u0005b\u0001\u0002\'N\u0001BC\u0001B\u001a\u0001\u0003\u0016\u0004%\ta\u001a\u0005\tY\u0002\u0011\t\u0012)A\u0005Q\"AQ\u000e\u0001BK\u0002\u0013\u0005a\u000e\u0003\u0005s\u0001\tE\t\u0015!\u0003p\u0011\u0015\u0019\b\u0001\"\u0001u\u0011\u0015A\b\u0001\"\u0001z\u0011\u0015i\b\u0001\"\u0001\u007f\u0011\u001d\t9\u0003\u0001C\u0001\u0003SAq!a\u000e\u0001\t\u0003\tI\u0004\u0003\u0004\u0002^\u0001!\t!\u001f\u0005\b\u0003?\u0002A\u0011AA1\u0011\u001d\tI\u0007\u0001C\u0001\u0003WBq!a\u001e\u0001\t\u0003\tI\bC\u0004\u0002~\u0001!\t!a \t\u000f\u0005\u0015\u0005\u0001\"\u0001\u0002\b\"9\u00111\u0012\u0001\u0005\u0002\u00055\u0005bBAS\u0001\u0011\u0005\u0011Q\u0012\u0005\b\u0003O\u0003A\u0011AAU\u0011\u001d\tI\f\u0001C\u0001\u0003wCa!!2\u0001\t\u0003I\bBBAd\u0001\u0011\u0005\u0011\u0010\u0003\u0004\u0002J\u0002!\t!\u001f\u0005\u0007\u0003\u0017\u0004A\u0011A=\t\u000f\u00055\u0007\u0001\"\u0001\u0002P\"9\u00111\u001c\u0001\u0005\u0002\u0005u\u0007bBAq\u0001\u0011\u0005\u00111\u001d\u0005\b\u0003O\u0004A\u0011AAu\u0011\u001d\ti\u000f\u0001C\u0001\u0003_Dq!!@\u0001\t\u0003\ty\u0010C\u0004\u0003\u0004\u0001!\tA!\u0002\t\u000f\t%\u0001\u0001\"\u0001\u0003\f!9!q\u0002\u0001\u0005\u0002\tE\u0001b\u0002B\u000b\u0001\u0011\u0005!q\u0003\u0005\b\u0005;\u0001A\u0011\u0001B\u0010\u0011\u001d\u0011\u0019\u0003\u0001C\u0001\u0005KAqA!\u000b\u0001\t\u0003\u0011Y\u0003\u0003\u0004\u00030\u0001!\t!\u001f\u0005\u0007\u0005c\u0001A\u0011A=\t\u000f\tM\u0002\u0001\"\u0001\u00036!9!\u0011\b\u0001\u0005\u0002\tm\u0002b\u0002B \u0001\u0011\u0005!\u0011\t\u0005\b\u0005\u000b\u0002A\u0011\u0001B$\u0011\u0019\u0011Y\u0005\u0001C\u0001s\"1!Q\n\u0001\u0005\u0002eDaAa\u0014\u0001\t\u0003I\bB\u0002B)\u0001\u0011\u0005\u0011\u0010\u0003\u0004\u0003T\u0001!\t!\u001f\u0005\u0007\u0005+\u0002A\u0011A=\t\r\t]\u0003\u0001\"\u0001z\u0011\u001d\u0011I\u0006\u0001C\u0001\u00057BaAa\u0018\u0001\t\u0003I\bB\u0002B1\u0001\u0011\u0005\u0011\u0010C\u0004\u0003d\u0001!\tA!\u001a\t\u000f\t5\u0004\u0001\"\u0001\u0003p!1!1\u000f\u0001\u0005\u0002eDqA!\u001e\u0001\t\u0003\t\t\u0007C\u0004\u0003x\u0001!\t!!\u0019\t\u0013\te\u0004!!A\u0005\u0002\tm\u0004\"\u0003BA\u0001E\u0005I\u0011\u0001BB\u0011%\u0011I\nAI\u0001\n\u0003\u0011Y\nC\u0005\u0003 \u0002\t\t\u0011\"\u0011\u0003\"\"I!\u0011\u0017\u0001\u0002\u0002\u0013\u0005!1\u0017\u0005\n\u0005k\u0003\u0011\u0011!C\u0001\u0005oC\u0011B!0\u0001\u0003\u0003%\tEa0\t\u0013\t5\u0007!!A\u0005\u0002\t=\u0007\"\u0003Bj\u0001\u0005\u0005I\u0011\tBk\u0011%\u0011I\u000eAA\u0001\n\u0003\u0012Y\u000eC\u0005\u0003^\u0002\t\t\u0011\"\u0011\u0003`\"I!\u0011\u001d\u0001\u0002\u0002\u0013\u0005#1]\u0004\b\u0005Ol\u0005\u0012\u0001Bu\r\u0019aU\n#\u0001\u0003l\"11o\u0012C\u0001\u0005{D\u0011Ba@H\u0003\u0003%\ti!\u0001\t\u0013\r\u001dq)!A\u0005\u0002\u000e%\u0001\"CB\f\u000f\u0006\u0005I\u0011BB\r\u0005\u001dA5)\u001e:t_JT\u0011AT\u0001\tCJ<wN\\1vi\u000e\u00011\u0003\u0002\u0001R/j\u0003\"AU+\u000e\u0003MS\u0011\u0001V\u0001\u0006g\u000e\fG.Y\u0005\u0003-N\u0013a!\u00118z%\u00164\u0007C\u0001*Y\u0013\tI6KA\u0004Qe>$Wo\u0019;\u0011\u0005m\u001bgB\u0001/b\u001d\ti\u0006-D\u0001_\u0015\tyv*\u0001\u0004=e>|GOP\u0005\u0002)&\u0011!mU\u0001\ba\u0006\u001c7.Y4f\u0013\t!WM\u0001\u0007TKJL\u0017\r\\5{C\ndWM\u0003\u0002c\'\u000611-\u001e:t_J,\u0012\u0001\u001b\t\u0003S*l\u0011!T\u0005\u0003W6\u0013aaQ;sg>\u0014\u0018aB2veN|\'\u000fI\u0001\bQ&\u001cHo\u001c:z+\u0005y\u0007CA5q\u0013\t\tXJA\u0007DkJ\u001cxN\u001d%jgR|\'/_\u0001\tQ&\u001cHo\u001c:zA\u00051A(\u001b8jiz\"2!\u001e<x!\tI\u0007\u0001C\u0003g\u000b\u0001\u0007\u0001\u000eC\u0003n\u000b\u0001\u0007q.A\u0004bGV\u00148o\u001c:\u0016\u0003i\u0004\"![>\n\u0005ql%aB!DkJ\u001cxN]\u0001\bU\u0012,7m\u001c3f+\ry\u00181\u0002\u000b\u0005\u0003\u0003\ti\u0002E\u0003j\u0003\u0007\t9!C\u0002\u0002\u00065\u0013A\u0002R3d_\u0012,\'+Z:vYR\u0004B!!\u0003\u0002\f1\u0001AaBA\u0007\u000f\t\u0007\u0011q\u0002\u0002\u0002\u0003F!\u0011\u0011CA\f!\r\u0011\u00161C\u0005\u0004\u0003+\u0019&a\u0002(pi\"Lgn\u001a\t\u0004%\u0006e\u0011bAA\u000e\'\n\u0019\u0011I\\=\t\u000f\u0005}q\u0001q\u0001\u0002\"\u0005\tQ\rE\u0003j\u0003G\t9!C\u0002\u0002&5\u0013!\u0002R3d_\u0012,\'j]8o\u0003\t\t7/\u0006\u0003\u0002,\u0005EB\u0003BA\u0017\u0003g\u0001R![A\u0002\u0003_\u0001B!!\u0003\u00022\u00119\u0011Q\u0002\u0005C\u0002\u0005=\u0001bBA\u0010\u0011\u0001\u000f\u0011Q\u0007\t\u0006S\u0006\r\u0012qF\u0001\u0004O\u0016$X\u0003BA\u001e\u0003\u0007\"B!!\u0010\u0002JQ!\u0011qHA#!\u0015I\u00171AA!!\u0011\tI!a\u0011\u0005\u000f\u00055\u0011B1\u0001\u0002\u0010!9\u0011qD\u0005A\u0004\u0005\u001d\u0003#B5\u0002$\u0005\u0005\u0003bBA&\u0013\u0001\u0007\u0011QJ\u0001\u0005]\u0006lW\r\u0005\u0003\u0002P\u0005]c\u0002BA)\u0003\'\u0002\"!X*\n\u0007\u0005U3+\u0001\u0004Qe\u0016$WMZ\u0005\u0005\u00033\nYF\u0001\u0004TiJLgn\u001a\u0006\u0004\u0003+\u001a\u0016!\u00044bS2,G-Q\"veN|\'/A\u0003g_\u000e,8/\u0006\u0002\u0002dA\u0019\u0011.!\u001a\n\u0007\u0005\u001dTJ\u0001\u0003Kg>t\u0017A\u0006\u0013he\u0016\fG/\u001a:%[&tWo\u001d\u0013he\u0016\fG/\u001a:\u0015\u0007U\fi\u0007C\u0004\u0002p1\u0001\r!!\u001d\u0002\u0003-\u0004rAUA:\u0003G\n\u0019\'C\u0002\u0002vM\u0013\u0011BR;oGRLwN\\\u0019\u0002\u0013]LG\u000f\u001b$pGV\u001cHcA;\u0002|!9\u0011qN\u0007A\u0002\u0005E\u0014aA:fiR\u0019Q/!!\t\u000f\u0005\re\u00021\u0001\u0002d\u0005\t!.A\u0005%G>dwN\u001c\u0013fcR\u0019Q/!#\t\u000f\u0005\ru\u00021\u0001\u0002d\u0005)A.\u001a4ugV\u0011\u0011q\u0012\t\u0006%\u0006E\u0015QS\u0005\u0004\u0003\'\u001b&AB(qi&|g\u000e\u0005\u0003\u0002\u0018\u0006uebA5\u0002\u001a&\u0019\u00111T\'\u0002\t)\u001bxN\\\u0005\u0005\u0003?\u000b\tKA\u0005Kg>t\u0017I\u001d:bs&\u0019\u00111U\'\u0003\u000b)\u001bxN\\:\u0002\rILw\r\u001b;t\u0003!1\u0017.\u001a7e\'\u0016$XCAAV!\u0015\u0011\u0016\u0011SAW!\u0019\ty%a,\u00024&!\u0011\u0011WA.\u0005\r\u0019V\r\u001e\t\u0005\u0003/\u000b),\u0003\u0003\u00028\u0006\u0005&!\u0003&t_:4\u0015.\u001a7e\u0003\u00191\u0017.\u001a7egV\u0011\u0011Q\u0018\t\u0006%\u0006E\u0015q\u0018\t\u00067\u0006\u0005\u00171W\u0005\u0004\u0003\u0007,\'\u0001\u0002\'jgR\fA\u0001\\3gi\u0006)!/[4ii\u0006)a-\u001b:ti\u0006!A.Y:u\u0003]!S.\u001b8vg\u0012bWm]:%[&tWo\u001d\u0013d_2|g\u000eF\u0002{\u0003#Dq!a5\u0019\u0001\u0004\t).A\u0001o!\r\u0011\u0016q[\u0005\u0004\u00033\u001c&aA%oi\u0006)A.\u001a4u\u001dR\u0019!0a8\t\u000f\u0005M\u0017\u00041\u0001\u0002V\u0006QBeY8m_:$S.\u001b8vg\u0012:\'/Z1uKJ$S.\u001b8vgR\u0019!0!:\t\u000f\u0005M\'\u00041\u0001\u0002V\u00061!/[4ii:#2A_Av\u0011\u001d\t\u0019n\u0007a\u0001\u0003+\fq\u0003J9nCJ\\G\u0005\\3tg\u0012j\u0017N\\;tI\r|Gn\u001c8\u0015\u0007i\f\t\u0010C\u0004\u0002tr\u0001\r!!>\u0002\u0003A\u0004rAUA:\u0003G\n9\u0010E\u0002S\u0003sL1!a?T\u0005\u001d\u0011un\u001c7fC:\fa\u0001\\3gi\u0006#Hc\u0001>\u0003\u0002!9\u00111_\u000fA\u0002\u0005U\u0018A\u0007\u0013d_2|g\u000eJ7j]V\u001cHe\u001a:fCR,\'\u000fJ9nCJ\\Gc\u0001>\u0003\b!9\u00111\u001f\u0010A\u0002\u0005U\u0018a\u0002:jO\"$\u0018\t\u001e\u000b\u0004u\n5\u0001bBAz?\u0001\u0007\u0011Q_\u0001\u0005M&tG\rF\u0002{\u0005\'Aq!a=!\u0001\u0004\t)0\u0001\u0007%[&tWo\u001d\u0013nS:,8\u000fF\u0002{\u00053AqAa\u0007\"\u0001\u0004\t\u0019,A\u0001r\u0003\u00151\u0017.\u001a7e)\rQ(\u0011\u0005\u0005\b\u00057\u0011\u0003\u0019AAZ\u0003M!S.\u001b8vg\u0012j\u0017N\\;tI\t\u001cH.Y:i)\rQ(q\u0005\u0005\b\u00057\u0019\u0003\u0019AAZ\u0003%!wn\u001e8GS\u0016dG\rF\u0002{\u0005[AqAa\u0007%\u0001\u0004\t\u0019,A\u0005e_^t\u0017I\u001d:bs\u0006qAEY:mCNDGEY:mCND\u0017!\u0004\u0013nS:,8\u000f\n2tY\u0006\u001c\b\u000eF\u0002{\u0005oAq!a=(\u0001\u0004\t)0\u0001\u0004e_^t\u0017\t\u001e\u000b\u0004u\nu\u0002bBAzQ\u0001\u0007\u0011Q_\u0001\u000bI\u0015\fHEY:mCNDGc\u0001>\u0003D!9\u00111[\u0015A\u0002\u0005U\u0017!\u00023po:tEc\u0001>\u0003J!9\u00111\u001b\u0016A\u0002\u0005U\u0017A\u00023fY\u0016$X-A\u0006v]\u0006\u0014\u0018p\u0018\u0013cC:<\u0017A\u00043fY\u0016$XmR8QCJ,g\u000e^\u0001\rI\u0016dW\r^3H_2+g\r^\u0001\u000eI\u0016dW\r^3H_JKw\r\u001b;\u0002\u001b\u0011,G.\u001a;f\u000f>4\u0015N]:u\u00031!W\r\\3uK\u001e{G*Y:u\u00035!W\r\\3uK\u001e{g)[3mIR\u0019!P!\u0018\t\u000f\tm!\u00071\u0001\u00024\u0006YA-\u001a7fi\u0016dUM\u001a;t\u00031!W\r\\3uKJKw\r\u001b;t\u0003!\u0019X\r\u001e\'fMR\u001cHc\u0001>\u0003h!9!\u0011N\u001bA\u0002\t-\u0014!\u0001=\u0011\u000bm\u000b\t-a\u0019\u0002\u0013M,GOU5hQR\u001cHc\u0001>\u0003r!9!\u0011\u000e\u001cA\u0002\t-\u0014AA;q\u00031)h.\u0019:z?\u0012j\u0017N\\;t\u0003\u0011)h\u000eZ8\u0002\t\r|\u0007/\u001f\u000b\u0006k\nu$q\u0010\u0005\bMj\u0002\n\u00111\u0001i\u0011\u001di\'\b%AA\u0002=\fabY8qs\u0012\"WMZ1vYR$\u0013\'\u0006\u0002\u0003\u0006*\u001a\u0001Na\",\u0005\t%\u0005\u0003\u0002BF\u0005+k!A!$\u000b\t\t=%\u0011S\u0001\nk:\u001c\u0007.Z2lK\u0012T1Aa%T\u0003)\tgN\\8uCRLwN\\\u0005\u0005\u0005/\u0013iIA\tv]\u000eDWmY6fIZ\u000b\'/[1oG\u0016\fabY8qs\u0012\"WMZ1vYR$#\'\u0006\u0002\u0003\u001e*\u001aqNa\"\u0002\u001bA\u0014x\u000eZ;diB\u0013XMZ5y+\t\u0011\u0019\u000b\u0005\u0003\u0003&\n=VB\u0001BT\u0015\u0011\u0011IKa+\u0002\t1\fgn\u001a\u0006\u0003\u0005[\u000bAA[1wC&!\u0011\u0011\fBT\u00031\u0001(o\u001c3vGR\f%/\u001b;z+\t\t).\u0001\bqe>$Wo\u0019;FY\u0016lWM\u001c;\u0015\t\u0005]!\u0011\u0018\u0005\n\u0005w{\u0014\u0011!a\u0001\u0003+\f1\u0001\u001f\u00132\u0003=\u0001(o\u001c3vGRLE/\u001a:bi>\u0014XC\u0001Ba!\u0019\u0011\u0019M!3\u0002\u00185\u0011!Q\u0019\u0006\u0004\u0005\u000f\u001c\u0016AC2pY2,7\r^5p]&!!1\u001aBc\u0005!IE/\u001a:bi>\u0014\u0018\u0001C2b]\u0016\u000bX/\u00197\u0015\t\u0005](\u0011\u001b\u0005\n\u0005w\u000b\u0015\u0011!a\u0001\u0003/\t!\u0003\u001d:pIV\u001cG/\u00127f[\u0016tGOT1nKR!!1\u0015Bl\u0011%\u0011YLQA\u0001\u0002\u0004\t).\u0001\u0005iCND7i\u001c3f)\t\t).\u0001\u0005u_N#(/\u001b8h)\t\u0011\u0019+\u0001\u0004fcV\fGn\u001d\u000b\u0005\u0003o\u0014)\u000fC\u0005\u0003<\u0016\u000b\t\u00111\u0001\u0002\u0018\u00059\u0001jQ;sg>\u0014\bCA5H\'\u00199\u0015K!<\u0003tB\u0019\u0011Na<\n\u0007\tEXJ\u0001\u0005I\u0007V\u00148o\u001c:t!\u0011\u0011)Pa?\u000e\u0005\t](\u0002\u0002B}\u0005W\u000b!![8\n\u0007\u0011\u00149\u0010\u0006\u0002\u0003j\u0006)\u0011\r\u001d9msR)Qoa\u0001\u0004\u0006!)a-\u0013a\u0001Q\")Q.\u0013a\u0001_\u00069QO\\1qa2LH\u0003BB\u0006\u0007\'\u0001RAUAI\u0007\u001b\u0001RAUB\bQ>L1a!\u0005T\u0005\u0019!V\u000f\u001d7fe!A1Q\u0003&\u0002\u0002\u0003\u0007Q/A\u0002yIA\nAb\u001e:ji\u0016\u0014V\r\u001d7bG\u0016$\"aa\u0007\u0011\t\t\u00156QD\u0005\u0005\u0007?\u00119K\u0001\u0004PE*,7\r\u001e
   #13 = Utf8               java/lang/invoke/MethodHandles$Lookup
   #14 = Class              #13           // java/lang/invoke/MethodHandles$Lookup
   #15 = Utf8               java/lang/invoke/MethodHandles
   #16 = Class              #15           // java/lang/invoke/MethodHandles
   #17 = Utf8               Lookup
   #18 = Utf8               cursor
   #19 = Utf8               Largonaut/Cursor;
   #20 = Utf8               history
   #21 = Utf8               Largonaut/CursorHistory;
   #22 = Utf8               unapply
   #23 = Utf8               (Largonaut/HCursor;)Lscala/Option;
   #24 = Utf8               (Largonaut/HCursor;)Lscala/Option<Lscala/Tuple2<Largonaut/Cursor;Largonaut/CursorHistory;>;>;
   #25 = Utf8               x$0
   #26 = Utf8               argonaut/HCursor$
   #27 = Class              #26           // argonaut/HCursor$
   #28 = Utf8               MODULE$
   #29 = Utf8               Largonaut/HCursor$;
   #30 = NameAndType        #28:#29       // MODULE$:Largonaut/HCursor$;
   #31 = Fieldref           #27.#30       // argonaut/HCursor$.MODULE$:Largonaut/HCursor$;
   #32 = NameAndType        #22:#23       // unapply:(Largonaut/HCursor;)Lscala/Option;
   #33 = Methodref          #27.#32       // argonaut/HCursor$.unapply:(Largonaut/HCursor;)Lscala/Option;
   #34 = Utf8               apply
   #35 = Utf8               (Largonaut/Cursor;Largonaut/CursorHistory;)Largonaut/HCursor;
   #36 = NameAndType        #34:#35       // apply:(Largonaut/Cursor;Largonaut/CursorHistory;)Largonaut/HCursor;
   #37 = Methodref          #27.#36       // argonaut/HCursor$.apply:(Largonaut/Cursor;Largonaut/CursorHistory;)Largonaut/HCursor;
   #38 = Utf8               productElementNames
   #39 = Utf8               ()Lscala/collection/Iterator;
   #40 = Utf8               ()Lscala/collection/Iterator<Ljava/lang/String;>;
   #41 = Utf8               productElementNames$
   #42 = Utf8               (Lscala/Product;)Lscala/collection/Iterator;
   #43 = NameAndType        #41:#42       // productElementNames$:(Lscala/Product;)Lscala/collection/Iterator;
   #44 = InterfaceMethodref #6.#43        // scala/Product.productElementNames$:(Lscala/Product;)Lscala/collection/Iterator;
   #45 = Utf8               this
   #46 = Utf8               Largonaut/HCursor;
   #47 = Utf8               ()Largonaut/Cursor;
   #48 = NameAndType        #18:#19       // cursor:Largonaut/Cursor;
   #49 = Fieldref           #2.#48        // argonaut/HCursor.cursor:Largonaut/Cursor;
   #50 = Utf8               ()Largonaut/CursorHistory;
   #51 = NameAndType        #20:#21       // history:Largonaut/CursorHistory;
   #52 = Fieldref           #2.#51        // argonaut/HCursor.history:Largonaut/CursorHistory;
   #53 = Utf8               acursor
   #54 = Utf8               ()Largonaut/ACursor;
   #55 = Utf8               argonaut/ACursor$
   #56 = Class              #55           // argonaut/ACursor$
   #57 = Utf8               Largonaut/ACursor$;
   #58 = NameAndType        #28:#57       // MODULE$:Largonaut/ACursor$;
   #59 = Fieldref           #56.#58       // argonaut/ACursor$.MODULE$:Largonaut/ACursor$;
   #60 = Utf8               ok
   #61 = Utf8               (Largonaut/HCursor;)Largonaut/ACursor;
   #62 = NameAndType        #60:#61       // ok:(Largonaut/HCursor;)Largonaut/ACursor;
   #63 = Methodref          #56.#62       // argonaut/ACursor$.ok:(Largonaut/HCursor;)Largonaut/ACursor;
   #64 = Utf8               jdecode
   #65 = Utf8               (Largonaut/DecodeJson;)Largonaut/DecodeResult;
   #66 = Utf8               <A:Ljava/lang/Object;>(Largonaut/DecodeJson<TA;>;)Largonaut/DecodeResult<TA;>;
   #67 = Utf8               e
   #68 = Utf8               argonaut/DecodeJson
   #69 = Class              #68           // argonaut/DecodeJson
   #70 = Utf8               decode
   #71 = Utf8               (Largonaut/HCursor;)Largonaut/DecodeResult;
   #72 = NameAndType        #70:#71       // decode:(Largonaut/HCursor;)Largonaut/DecodeResult;
   #73 = InterfaceMethodref #69.#72       // argonaut/DecodeJson.decode:(Largonaut/HCursor;)Largonaut/DecodeResult;
   #74 = Utf8               Largonaut/DecodeJson;
   #75 = Utf8               as
   #76 = NameAndType        #64:#65       // jdecode:(Largonaut/DecodeJson;)Largonaut/DecodeResult;
   #77 = Methodref          #2.#76        // argonaut/HCursor.jdecode:(Largonaut/DecodeJson;)Largonaut/DecodeResult;
   #78 = Utf8               get
   #79 = Utf8               (Ljava/lang/String;Largonaut/DecodeJson;)Largonaut/DecodeResult;
   #80 = Utf8               <A:Ljava/lang/Object;>(Ljava/lang/String;Largonaut/DecodeJson<TA;>;)Largonaut/DecodeResult<TA;>;
   #81 = Utf8               name
   #82 = Utf8               $minus$minus$bslash
   #83 = Utf8               (Ljava/lang/String;)Largonaut/ACursor;
   #84 = NameAndType        #82:#83       // $minus$minus$bslash:(Ljava/lang/String;)Largonaut/ACursor;
   #85 = Methodref          #2.#84        // argonaut/HCursor.$minus$minus$bslash:(Ljava/lang/String;)Largonaut/ACursor;
   #86 = Utf8               argonaut/ACursor
   #87 = Class              #86           // argonaut/ACursor
   #88 = NameAndType        #75:#65       // as:(Largonaut/DecodeJson;)Largonaut/DecodeResult;
   #89 = Methodref          #87.#88       // argonaut/ACursor.as:(Largonaut/DecodeJson;)Largonaut/DecodeResult;
   #90 = Utf8               Ljava/lang/String;
   #91 = Utf8               failedACursor
   #92 = Utf8               fail
   #93 = NameAndType        #92:#61       // fail:(Largonaut/HCursor;)Largonaut/ACursor;
   #94 = Methodref          #56.#93       // argonaut/ACursor$.fail:(Largonaut/HCursor;)Largonaut/ACursor;
   #95 = Utf8               focus
   #96 = Utf8               ()Largonaut/Json;
   #97 = NameAndType        #18:#47       // cursor:()Largonaut/Cursor;
   #98 = Methodref          #2.#97        // argonaut/HCursor.cursor:()Largonaut/Cursor;
   #99 = Utf8               argonaut/Cursor
  #100 = Class              #99           // argonaut/Cursor
  #101 = NameAndType        #95:#96       // focus:()Largonaut/Json;
  #102 = Methodref          #100.#101     // argonaut/Cursor.focus:()Largonaut/Json;
  #103 = Utf8               $greater$minus$greater
  #104 = Utf8               (Lscala/Function1;)Largonaut/HCursor;
  #105 = Utf8               (Lscala/Function1<Largonaut/Json;Largonaut/Json;>;)Largonaut/HCursor;
  #106 = Utf8               k
  #107 = Utf8               withFocus
  #108 = NameAndType        #107:#104     // withFocus:(Lscala/Function1;)Largonaut/HCursor;
  #109 = Methodref          #2.#108       // argonaut/HCursor.withFocus:(Lscala/Function1;)Largonaut/HCursor;
  #110 = Utf8               Lscala/Function1;
  #111 = Utf8               (Lscala/Function1;)Largonaut/Cursor;
  #112 = NameAndType        #107:#111     // withFocus:(Lscala/Function1;)Largonaut/Cursor;
  #113 = Methodref          #100.#112     // argonaut/Cursor.withFocus:(Lscala/Function1;)Largonaut/Cursor;
  #114 = NameAndType        #20:#50       // history:()Largonaut/CursorHistory;
  #115 = Methodref          #2.#114       // argonaut/HCursor.history:()Largonaut/CursorHistory;
  #116 = Utf8               <init>
  #117 = Utf8               (Largonaut/Cursor;Largonaut/CursorHistory;)V
  #118 = NameAndType        #116:#117     // "<init>":(Largonaut/Cursor;Largonaut/CursorHistory;)V
  #119 = Methodref          #2.#118       // argonaut/HCursor."<init>":(Largonaut/Cursor;Largonaut/CursorHistory;)V
  #120 = Utf8               set
  #121 = Utf8               (Largonaut/Json;)Largonaut/HCursor;
  #122 = Utf8               j
  #123 = Utf8               (Ljava/lang/Object;)Ljava/lang/Object;
  #124 = MethodType         #123          //  (Ljava/lang/Object;)Ljava/lang/Object;
  #125 = Utf8               $anonfun$set$1
  #126 = Utf8               (Largonaut/Json;Largonaut/Json;)Largonaut/Json;
  #127 = NameAndType        #125:#126     // $anonfun$set$1:(Largonaut/Json;Largonaut/Json;)Largonaut/Json;
  #128 = Methodref          #2.#127       // argonaut/HCursor.$anonfun$set$1:(Largonaut/Json;Largonaut/Json;)Largonaut/Json;
  #129 = MethodHandle       6:#128        // REF_invokeStatic argonaut/HCursor.$anonfun$set$1:(Largonaut/Json;Largonaut/Json;)Largonaut/Json;
  #130 = Utf8               (Largonaut/Json;)Largonaut/Json;
  #131 = MethodType         #130          //  (Largonaut/Json;)Largonaut/Json;
  #132 = Integer            5
  #133 = Integer            1
  #134 = Utf8               java/lang/invoke/LambdaMetafactory
  #135 = Class              #134          // java/lang/invoke/LambdaMetafactory
  #136 = Utf8               altMetafactory
  #137 = Utf8               (Ljava/lang/invoke/MethodHandles$Lookup;Ljava/lang/String;Ljava/lang/invoke/MethodType;[Ljava/lang/Object;)Ljava/lang/invoke/CallSite;
  #138 = NameAndType        #136:#137     // altMetafactory:(Ljava/lang/invoke/MethodHandles$Lookup;Ljava/lang/String;Ljava/lang/invoke/MethodType;[Ljava/lang/Object;)Ljava/lang/invoke/CallSite;
  #139 = Methodref          #135.#138     // java/lang/invoke/LambdaMetafactory.altMetafactory:(Ljava/lang/invoke/MethodHandles$Lookup;Ljava/lang/String;Ljava/lang/invoke/MethodType;[Ljava/lang/Object;)Ljava/lang/invoke/CallSite;
  #140 = MethodHandle       6:#139        // REF_invokeStatic java/lang/invoke/LambdaMetafactory.altMetafactory:(Ljava/lang/invoke/MethodHandles$Lookup;Ljava/lang/String;Ljava/lang/invoke/MethodType;[Ljava/lang/Object;)Ljava/lang/invoke/CallSite;
  #141 = Utf8               (Largonaut/Json;)Lscala/Function1;
  #142 = NameAndType        #34:#141      // apply:(Largonaut/Json;)Lscala/Function1;
  #143 = InvokeDynamic      #0:#142       // #0:apply:(Largonaut/Json;)Lscala/Function1;
  #144 = Utf8               Largonaut/Json;
  #145 = Utf8               $colon$eq
  #146 = NameAndType        #120:#121     // set:(Largonaut/Json;)Largonaut/HCursor;
  #147 = Methodref          #2.#146       // argonaut/HCursor.set:(Largonaut/Json;)Largonaut/HCursor;
  #148 = Utf8               lefts
  #149 = Utf8               ()Lscala/Option;
  #150 = Utf8               ()Lscala/Option<Lscala/collection/immutable/List<Largonaut/Json;>;>;
  #151 = NameAndType        #148:#149     // lefts:()Lscala/Option;
  #152 = Methodref          #100.#151     // argonaut/Cursor.lefts:()Lscala/Option;
  #153 = Utf8               rights
  #154 = NameAndType        #153:#149     // rights:()Lscala/Option;
  #155 = Methodref          #100.#154     // argonaut/Cursor.rights:()Lscala/Option;
  #156 = Utf8               fieldSet
  #157 = Utf8               ()Lscala/Option<Lscala/collection/immutable/Set<Ljava/lang/String;>;>;
  #158 = NameAndType        #156:#149     // fieldSet:()Lscala/Option;
  #159 = Methodref          #100.#158     // argonaut/Cursor.fieldSet:()Lscala/Option;
  #160 = Utf8               fields
  #161 = Utf8               ()Lscala/Option<Lscala/collection/immutable/List<Ljava/lang/String;>;>;
  #162 = NameAndType        #160:#149     // fields:()Lscala/Option;
  #163 = Methodref          #100.#162     // argonaut/Cursor.fields:()Lscala/Option;
  #164 = Utf8               left
  #165 = Utf8               $anonfun$left$1
  #166 = Utf8               (Largonaut/Cursor;)Lscala/Option;
  #167 = NameAndType        #165:#166     // $anonfun$left$1:(Largonaut/Cursor;)Lscala/Option;
  #168 = Methodref          #2.#167       // argonaut/HCursor.$anonfun$left$1:(Largonaut/Cursor;)Lscala/Option;
  #169 = MethodHandle       6:#168        // REF_invokeStatic argonaut/HCursor.$anonfun$left$1:(Largonaut/Cursor;)Lscala/Option;
  #170 = MethodType         #166          //  (Largonaut/Cursor;)Lscala/Option;
  #171 = Utf8               ()Lscala/Function1;
  #172 = NameAndType        #34:#171      // apply:()Lscala/Function1;
  #173 = InvokeDynamic      #1:#172       // #1:apply:()Lscala/Function1;
  #174 = Utf8               argonaut/CursorOpLeft$
  #175 = Class              #174          // argonaut/CursorOpLeft$
  #176 = Utf8               Largonaut/CursorOpLeft$;
  #177 = NameAndType        #28:#176      // MODULE$:Largonaut/CursorOpLeft$;
  #178 = Fieldref           #175.#177     // argonaut/CursorOpLeft$.MODULE$:Largonaut/CursorOpLeft$;
  #179 = Utf8               argonaut/CursorHistory
  #180 = Class              #179          // argonaut/CursorHistory
  #181 = Utf8               acursorElement
  #182 = Utf8               (Lscala/Function1;Largonaut/Cursor;Largonaut/CursorOpElement;)Largonaut/ACursor;
  #183 = NameAndType        #181:#182     // acursorElement:(Lscala/Function1;Largonaut/Cursor;Largonaut/CursorOpElement;)Largonaut/ACursor;
  #184 = Methodref          #180.#183     // argonaut/CursorHistory.acursorElement:(Lscala/Function1;Largonaut/Cursor;Largonaut/CursorOpElement;)Largonaut/ACursor;
  #185 = Utf8               right
  #186 = Utf8               $anonfun$right$1
  #187 = NameAndType        #186:#166     // $anonfun$right$1:(Largonaut/Cursor;)Lscala/Option;
  #188 = Methodref          #2.#187       // argonaut/HCursor.$anonfun$right$1:(Largonaut/Cursor;)Lscala/Option;
  #189 = MethodHandle       6:#188        // REF_invokeStatic argonaut/HCursor.$anonfun$right$1:(Largonaut/Cursor;)Lscala/Option;
  #190 = InvokeDynamic      #2:#172       // #2:apply:()Lscala/Function1;
  #191 = Utf8               argonaut/CursorOpRight$
  #192 = Class              #191          // argonaut/CursorOpRight$
  #193 = Utf8               Largonaut/CursorOpRight$;
  #194 = NameAndType        #28:#193      // MODULE$:Largonaut/CursorOpRight$;
  #195 = Fieldref           #192.#194     // argonaut/CursorOpRight$.MODULE$:Largonaut/CursorOpRight$;
  #196 = Utf8               first
  #197 = Utf8               $anonfun$first$1
  #198 = NameAndType        #197:#166     // $anonfun$first$1:(Largonaut/Cursor;)Lscala/Option;
  #199 = Methodref          #2.#198       // argonaut/HCursor.$anonfun$first$1:(Largonaut/Cursor;)Lscala/Option;
  #200 = MethodHandle       6:#199        // REF_invokeStatic argonaut/HCursor.$anonfun$first$1:(Largonaut/Cursor;)Lscala/Option;
  #201 = InvokeDynamic      #3:#172       // #3:apply:()Lscala/Function1;
  #202 = Utf8               argonaut/CursorOpFirst$
  #203 = Class              #202          // argonaut/CursorOpFirst$
  #204 = Utf8               Largonaut/CursorOpFirst$;
  #205 = NameAndType        #28:#204      // MODULE$:Largonaut/CursorOpFirst$;
  #206 = Fieldref           #203.#205     // argonaut/CursorOpFirst$.MODULE$:Largonaut/CursorOpFirst$;
  #207 = Utf8               last
  #208 = Utf8               $anonfun$last$1
  #209 = NameAndType        #208:#166     // $anonfun$last$1:(Largonaut/Cursor;)Lscala/Option;
  #210 = Methodref          #2.#209       // argonaut/HCursor.$anonfun$last$1:(Largonaut/Cursor;)Lscala/Option;
  #211 = MethodHandle       6:#210        // REF_invokeStatic argonaut/HCursor.$anonfun$last$1:(Largonaut/Cursor;)Lscala/Option;
  #212 = InvokeDynamic      #4:#172       // #4:apply:()Lscala/Function1;
  #213 = Utf8               argonaut/CursorOpLast$
  #214 = Class              #213          // argonaut/CursorOpLast$
  #215 = Utf8               Largonaut/CursorOpLast$;
  #216 = NameAndType        #28:#215      // MODULE$:Largonaut/CursorOpLast$;
  #217 = Fieldref           #214.#216     // argonaut/CursorOpLast$.MODULE$:Largonaut/CursorOpLast$;
  #218 = Utf8               $minus$less$minus$colon
  #219 = Utf8               (I)Largonaut/ACursor;
  #220 = Utf8               n
  #221 = Utf8               leftN
  #222 = NameAndType        #221:#219     // leftN:(I)Largonaut/ACursor;
  #223 = Methodref          #2.#222       // argonaut/HCursor.leftN:(I)Largonaut/ACursor;
  #224 = Utf8               I
  #225 = Utf8               $anonfun$leftN$1
  #226 = Utf8               (ILargonaut/Cursor;)Lscala/Option;
  #227 = NameAndType        #225:#226     // $anonfun$leftN$1:(ILargonaut/Cursor;)Lscala/Option;
  #228 = Methodref          #2.#227       // argonaut/HCursor.$anonfun$leftN$1:(ILargonaut/Cursor;)Lscala/Option;
  #229 = MethodHandle       6:#228        // REF_invokeStatic argonaut/HCursor.$anonfun$leftN$1:(ILargonaut/Cursor;)Lscala/Option;
  #230 = Utf8               (I)Lscala/Function1;
  #231 = NameAndType        #34:#230      // apply:(I)Lscala/Function1;
  #232 = InvokeDynamic      #5:#231       // #5:apply:(I)Lscala/Function1;
  #233 = Utf8               argonaut/CursorOpLeftN
  #234 = Class              #233          // argonaut/CursorOpLeftN
  #235 = Utf8               (I)V
  #236 = NameAndType        #116:#235     // "<init>":(I)V
  #237 = Methodref          #234.#236     // argonaut/CursorOpLeftN."<init>":(I)V
  #238 = Utf8               $colon$minus$greater$minus
  #239 = Utf8               rightN
  #240 = NameAndType        #239:#219     // rightN:(I)Largonaut/ACursor;
  #241 = Methodref          #2.#240       // argonaut/HCursor.rightN:(I)Largonaut/ACursor;
  #242 = Utf8               $anonfun$rightN$1
  #243 = NameAndType        #242:#226     // $anonfun$rightN$1:(ILargonaut/Cursor;)Lscala/Option;
  #244 = Methodref          #2.#243       // argonaut/HCursor.$anonfun$rightN$1:(ILargonaut/Cursor;)Lscala/Option;
  #245 = MethodHandle       6:#244        // REF_invokeStatic argonaut/HCursor.$anonfun$rightN$1:(ILargonaut/Cursor;)Lscala/Option;
  #246 = InvokeDynamic      #6:#231       // #6:apply:(I)Lscala/Function1;
  #247 = Utf8               argonaut/CursorOpRightN
  #248 = Class              #247          // argonaut/CursorOpRightN
  #249 = Methodref          #248.#236     // argonaut/CursorOpRightN."<init>":(I)V
  #250 = Utf8               $qmark$less$minus$colon
  #251 = Utf8               (Lscala/Function1;)Largonaut/ACursor;
  #252 = Utf8               (Lscala/Function1<Largonaut/Json;Ljava/lang/Object;>;)Largonaut/ACursor;
  #253 = Utf8               p
  #254 = Utf8               leftAt
  #255 = NameAndType        #254:#251     // leftAt:(Lscala/Function1;)Largonaut/ACursor;
  #256 = Methodref          #2.#255       // argonaut/HCursor.leftAt:(Lscala/Function1;)Largonaut/ACursor;
  #257 = Utf8               $anonfun$leftAt$1
  #258 = Utf8               (Lscala/Function1;Largonaut/Cursor;)Lscala/Option;
  #259 = NameAndType        #257:#258     // $anonfun$leftAt$1:(Lscala/Function1;Largonaut/Cursor;)Lscala/Option;
  #260 = Methodref          #2.#259       // argonaut/HCursor.$anonfun$leftAt$1:(Lscala/Function1;Largonaut/Cursor;)Lscala/Option;
  #261 = MethodHandle       6:#260        // REF_invokeStatic argonaut/HCursor.$anonfun$leftAt$1:(Lscala/Function1;Largonaut/Cursor;)Lscala/Option;
  #262 = Utf8               (Lscala/Function1;)Lscala/Function1;
  #263 = NameAndType        #34:#262      // apply:(Lscala/Function1;)Lscala/Function1;
  #264 = InvokeDynamic      #7:#263       // #7:apply:(Lscala/Function1;)Lscala/Function1;
  #265 = Utf8               argonaut/CursorOpLeftAt
  #266 = Class              #265          // argonaut/CursorOpLeftAt
  #267 = Utf8               (Lscala/Function1;)V
  #268 = NameAndType        #116:#267     // "<init>":(Lscala/Function1;)V
  #269 = Methodref          #266.#268     // argonaut/CursorOpLeftAt."<init>":(Lscala/Function1;)V
  #270 = Utf8               $colon$minus$greater$qmark
  #271 = Utf8               rightAt
  #272 = NameAndType        #271:#251     // rightAt:(Lscala/Function1;)Largonaut/ACursor;
  #273 = Methodref          #2.#272       // argonaut/HCursor.rightAt:(Lscala/Function1;)Largonaut/ACursor;
  #274 = Utf8               $anonfun$rightAt$1
  #275 = NameAndType        #274:#258     // $anonfun$rightAt$1:(Lscala/Function1;Largonaut/Cursor;)Lscala/Option;
  #276 = Methodref          #2.#275       // argonaut/HCursor.$anonfun$rightAt$1:(Lscala/Function1;Largonaut/Cursor;)Lscala/Option;
  #277 = MethodHandle       6:#276        // REF_invokeStatic argonaut/HCursor.$anonfun$rightAt$1:(Lscala/Function1;Largonaut/Cursor;)Lscala/Option;
  #278 = InvokeDynamic      #8:#263       // #8:apply:(Lscala/Function1;)Lscala/Function1;
  #279 = Utf8               argonaut/CursorOpRightAt
  #280 = Class              #279          // argonaut/CursorOpRightAt
  #281 = Methodref          #280.#268     // argonaut/CursorOpRightAt."<init>":(Lscala/Function1;)V
  #282 = Utf8               find
  #283 = Utf8               $anonfun$find$1
  #284 = NameAndType        #283:#258     // $anonfun$find$1:(Lscala/Function1;Largonaut/Cursor;)Lscala/Option;
  #285 = Methodref          #2.#284       // argonaut/HCursor.$anonfun$find$1:(Lscala/Function1;Largonaut/Cursor;)Lscala/Option;
  #286 = MethodHandle       6:#285        // REF_invokeStatic argonaut/HCursor.$anonfun$find$1:(Lscala/Function1;Largonaut/Cursor;)Lscala/Option;
  #287 = InvokeDynamic      #9:#263       // #9:apply:(Lscala/Function1;)Lscala/Function1;
  #288 = Utf8               argonaut/CursorOpFind
  #289 = Class              #288          // argonaut/CursorOpFind
  #290 = Methodref          #289.#268     // argonaut/CursorOpFind."<init>":(Lscala/Function1;)V
  #291 = Utf8               $minus$minus
  #292 = Utf8               q
  #293 = Utf8               field
  #294 = NameAndType        #293:#83      // field:(Ljava/lang/String;)Largonaut/ACursor;
  #295 = Methodref          #2.#294       // argonaut/HCursor.field:(Ljava/lang/String;)Largonaut/ACursor;
  #296 = Utf8               $anonfun$field$1
  #297 = Utf8               (Ljava/lang/String;Largonaut/Cursor;)Lscala/Option;
  #298 = NameAndType        #296:#297     // $anonfun$field$1:(Ljava/lang/String;Largonaut/Cursor;)Lscala/Option;
  #299 = Methodref          #2.#298       // argonaut/HCursor.$anonfun$field$1:(Ljava/lang/String;Largonaut/Cursor;)Lscala/Option;
  #300 = MethodHandle       6:#299        // REF_invokeStatic argonaut/HCursor.$anonfun$field$1:(Ljava/lang/String;Largonaut/Cursor;)Lscala/Option;
  #301 = Utf8               (Ljava/lang/String;)Lscala/Function1;
  #302 = NameAndType        #34:#301      // apply:(Ljava/lang/String;)Lscala/Function1;
  #303 = InvokeDynamic      #10:#302      // #10:apply:(Ljava/lang/String;)Lscala/Function1;
  #304 = Utf8               argonaut/CursorOpField
  #305 = Class              #304          // argonaut/CursorOpField
  #306 = Utf8               (Ljava/lang/String;)V
  #307 = NameAndType        #116:#306     // "<init>":(Ljava/lang/String;)V
  #308 = Methodref          #305.#307     // argonaut/CursorOpField."<init>":(Ljava/lang/String;)V
  #309 = Utf8               downField
  #310 = NameAndType        #309:#83      // downField:(Ljava/lang/String;)Largonaut/ACursor;
  #311 = Methodref          #2.#310       // argonaut/HCursor.downField:(Ljava/lang/String;)Largonaut/ACursor;
  #312 = Utf8               $anonfun$downField$1
  #313 = NameAndType        #312:#297     // $anonfun$downField$1:(Ljava/lang/String;Largonaut/Cursor;)Lscala/Option;
  #314 = Methodref          #2.#313       // argonaut/HCursor.$anonfun$downField$1:(Ljava/lang/String;Largonaut/Cursor;)Lscala/Option;
  #315 = MethodHandle       6:#314        // REF_invokeStatic argonaut/HCursor.$anonfun$downField$1:(Ljava/lang/String;Largonaut/Cursor;)Lscala/Option;
  #316 = InvokeDynamic      #11:#302      // #11:apply:(Ljava/lang/String;)Lscala/Function1;
  #317 = Utf8               argonaut/CursorOpDownField
  #318 = Class              #317          // argonaut/CursorOpDownField
  #319 = Methodref          #318.#307     // argonaut/CursorOpDownField."<init>":(Ljava/lang/String;)V
  #320 = Utf8               downArray
  #321 = Utf8               $anonfun$downArray$1
  #322 = NameAndType        #321:#166     // $anonfun$downArray$1:(Largonaut/Cursor;)Lscala/Option;
  #323 = Methodref          #2.#322       // argonaut/HCursor.$anonfun$downArray$1:(Largonaut/Cursor;)Lscala/Option;
  #324 = MethodHandle       6:#323        // REF_invokeStatic argonaut/HCursor.$anonfun$downArray$1:(Largonaut/Cursor;)Lscala/Option;
  #325 = InvokeDynamic      #12:#172      // #12:apply:()Lscala/Function1;
  #326 = Utf8               argonaut/CursorOpDownArray$
  #327 = Class              #326          // argonaut/CursorOpDownArray$
  #328 = Utf8               Largonaut/CursorOpDownArray$;
  #329 = NameAndType        #28:#328      // MODULE$:Largonaut/CursorOpDownArray$;
  #330 = Fieldref           #327.#329     // argonaut/CursorOpDownArray$.MODULE$:Largonaut/CursorOpDownArray$;
  #331 = Utf8               $bslash$bslash
  #332 = NameAndType        #320:#54      // downArray:()Largonaut/ACursor;
  #333 = Methodref          #2.#332       // argonaut/HCursor.downArray:()Largonaut/ACursor;
  #334 = Utf8               $minus$bslash
  #335 = Utf8               downAt
  #336 = NameAndType        #335:#251     // downAt:(Lscala/Function1;)Largonaut/ACursor;
  #337 = Methodref          #2.#336       // argonaut/HCursor.downAt:(Lscala/Function1;)Largonaut/ACursor;
  #338 = Utf8               $anonfun$downAt$1
  #339 = NameAndType        #338:#258     // $anonfun$downAt$1:(Lscala/Function1;Largonaut/Cursor;)Lscala/Option;
  #340 = Methodref          #2.#339       // argonaut/HCursor.$anonfun$downAt$1:(Lscala/Function1;Largonaut/Cursor;)Lscala/Option;
  #341 = MethodHandle       6:#340        // REF_invokeStatic argonaut/HCursor.$anonfun$downAt$1:(Lscala/Function1;Largonaut/Cursor;)Lscala/Option;
  #342 = InvokeDynamic      #13:#263      // #13:apply:(Lscala/Function1;)Lscala/Function1;
  #343 = Utf8               argonaut/CursorOpDownAt
  #344 = Class              #343          // argonaut/CursorOpDownAt
  #345 = Methodref          #344.#268     // argonaut/CursorOpDownAt."<init>":(Lscala/Function1;)V
  #346 = Utf8               $eq$bslash
  #347 = Utf8               downN
  #348 = NameAndType        #347:#219     // downN:(I)Largonaut/ACursor;
  #349 = Methodref          #2.#348       // argonaut/HCursor.downN:(I)Largonaut/ACursor;
  #350 = Utf8               $anonfun$downN$1
  #351 = NameAndType        #350:#226     // $anonfun$downN$1:(ILargonaut/Cursor;)Lscala/Option;
  #352 = Methodref          #2.#351       // argonaut/HCursor.$anonfun$downN$1:(ILargonaut/Cursor;)Lscala/Option;
  #353 = MethodHandle       6:#352        // REF_invokeStatic argonaut/HCursor.$anonfun$downN$1:(ILargonaut/Cursor;)Lscala/Option;
  #354 = InvokeDynamic      #14:#231      // #14:apply:(I)Lscala/Function1;
  #355 = Utf8               argonaut/CursorOpDownN
  #356 = Class              #355          // argonaut/CursorOpDownN
  #357 = Methodref          #356.#236     // argonaut/CursorOpDownN."<init>":(I)V
  #358 = Utf8               delete
  #359 = Utf8               deleteGoParent
  #360 = NameAndType        #359:#54      // deleteGoParent:()Largonaut/ACursor;
  #361 = Methodref          #2.#360       // argonaut/HCursor.deleteGoParent:()Largonaut/ACursor;
  #362 = Utf8               unary_$bang
  #363 = Utf8               $anonfun$deleteGoParent$1
  #364 = NameAndType        #363:#166     // $anonfun$deleteGoParent$1:(Largonaut/Cursor;)Lscala/Option;
  #365 = Methodref          #2.#364       // argonaut/HCursor.$anonfun$deleteGoParent$1:(Largonaut/Cursor;)Lscala/Option;
  #366 = MethodHandle       6:#365        // REF_invokeStatic argonaut/HCursor.$anonfun$deleteGoParent$1:(Largonaut/Cursor;)Lscala/Option;
  #367 = InvokeDynamic      #15:#172      // #15:apply:()Lscala/Function1;
  #368 = Utf8               argonaut/CursorOpDeleteGoParent$
  #369 = Class              #368          // argonaut/CursorOpDeleteGoParent$
  #370 = Utf8               Largonaut/CursorOpDeleteGoParent$;
  #371 = NameAndType        #28:#370      // MODULE$:Largonaut/CursorOpDeleteGoParent$;
  #372 = Fieldref           #369.#371     // argonaut/CursorOpDeleteGoParent$.MODULE$:Largonaut/CursorOpDeleteGoParent$;
  #373 = Utf8               deleteGoLeft
  #374 = Utf8               $anonfun$deleteGoLeft$1
  #375 = NameAndType        #374:#166     // $anonfun$deleteGoLeft$1:(Largonaut/Cursor;)Lscala/Option;
  #376 = Methodref          #2.#375       // argonaut/HCursor.$anonfun$deleteGoLeft$1:(Largonaut/Cursor;)Lscala/Option;
  #377 = MethodHandle       6:#376        // REF_invokeStatic argonaut/HCursor.$anonfun$deleteGoLeft$1:(Largonaut/Cursor;)Lscala/Option;
  #378 = InvokeDynamic      #16:#172      // #16:apply:()Lscala/Function1;
  #379 = Utf8               argonaut/CursorOpDeleteGoLeft$
  #380 = Class              #379          // argonaut/CursorOpDeleteGoLeft$
  #381 = Utf8               Largonaut/CursorOpDeleteGoLeft$;
  #382 = NameAndType        #28:#381      // MODULE$:Largonaut/CursorOpDeleteGoLeft$;
  #383 = Fieldref           #380.#382     // argonaut/CursorOpDeleteGoLeft$.MODULE$:Largonaut/CursorOpDeleteGoLeft$;
  #384 = Utf8               deleteGoRight
  #385 = Utf8               $anonfun$deleteGoRight$1
  #386 = NameAndType        #385:#166     // $anonfun$deleteGoRight$1:(Largonaut/Cursor;)Lscala/Option;
  #387 = Methodref          #2.#386       // argonaut/HCursor.$anonfun$deleteGoRight$1:(Largonaut/Cursor;)Lscala/Option;
  #388 = MethodHandle       6:#387        // REF_invokeStatic argonaut/HCursor.$anonfun$deleteGoRight$1:(Largonaut/Cursor;)Lscala/Option;
  #389 = InvokeDynamic      #17:#172      // #17:apply:()Lscala/Function1;
  #390 = Utf8               argonaut/CursorOpDeleteGoRight$
  #391 = Class              #390          // argonaut/CursorOpDeleteGoRight$
  #392 = Utf8               Largonaut/CursorOpDeleteGoRight$;
  #393 = NameAndType        #28:#392      // MODULE$:Largonaut/CursorOpDeleteGoRight$;
  #394 = Fieldref           #391.#393     // argonaut/CursorOpDeleteGoRight$.MODULE$:Largonaut/CursorOpDeleteGoRight$;
  #395 = Utf8               deleteGoFirst
  #396 = Utf8               $anonfun$deleteGoFirst$1
  #397 = NameAndType        #396:#166     // $anonfun$deleteGoFirst$1:(Largonaut/Cursor;)Lscala/Option;
  #398 = Methodref          #2.#397       // argonaut/HCursor.$anonfun$deleteGoFirst$1:(Largonaut/Cursor;)Lscala/Option;
  #399 = MethodHandle       6:#398        // REF_invokeStatic argonaut/HCursor.$anonfun$deleteGoFirst$1:(Largonaut/Cursor;)Lscala/Option;
  #400 = InvokeDynamic      #18:#172      // #18:apply:()Lscala/Function1;
  #401 = Utf8               argonaut/CursorOpDeleteGoFirst$
  #402 = Class              #401          // argonaut/CursorOpDeleteGoFirst$
  #403 = Utf8               Largonaut/CursorOpDeleteGoFirst$;
  #404 = NameAndType        #28:#403      // MODULE$:Largonaut/CursorOpDeleteGoFirst$;
  #405 = Fieldref           #402.#404     // argonaut/CursorOpDeleteGoFirst$.MODULE$:Largonaut/CursorOpDeleteGoFirst$;
  #406 = Utf8               deleteGoLast
  #407 = Utf8               $anonfun$deleteGoLast$1
  #408 = NameAndType        #407:#166     // $anonfun$deleteGoLast$1:(Largonaut/Cursor;)Lscala/Option;
  #409 = Methodref          #2.#408       // argonaut/HCursor.$anonfun$deleteGoLast$1:(Largonaut/Cursor;)Lscala/Option;
  #410 = MethodHandle       6:#409        // REF_invokeStatic argonaut/HCursor.$anonfun$deleteGoLast$1:(Largonaut/Cursor;)Lscala/Option;
  #411 = InvokeDynamic      #19:#172      // #19:apply:()Lscala/Function1;
  #412 = Utf8               argonaut/CursorOpDeleteGoLast$
  #413 = Class              #412          // argonaut/CursorOpDeleteGoLast$
  #414 = Utf8               Largonaut/CursorOpDeleteGoLast$;
  #415 = NameAndType        #28:#414      // MODULE$:Largonaut/CursorOpDeleteGoLast$;
  #416 = Fieldref           #413.#415     // argonaut/CursorOpDeleteGoLast$.MODULE$:Largonaut/CursorOpDeleteGoLast$;
  #417 = Utf8               deleteGoField
  #418 = Utf8               $anonfun$deleteGoField$1
  #419 = NameAndType        #418:#297     // $anonfun$deleteGoField$1:(Ljava/lang/String;Largonaut/Cursor;)Lscala/Option;
  #420 = Methodref          #2.#419       // argonaut/HCursor.$anonfun$deleteGoField$1:(Ljava/lang/String;Largonaut/Cursor;)Lscala/Option;
  #421 = MethodHandle       6:#420        // REF_invokeStatic argonaut/HCursor.$anonfun$deleteGoField$1:(Ljava/lang/String;Largonaut/Cursor;)Lscala/Option;
  #422 = InvokeDynamic      #20:#302      // #20:apply:(Ljava/lang/String;)Lscala/Function1;
  #423 = Utf8               argonaut/CursorOpDeleteGoField
  #424 = Class              #423          // argonaut/CursorOpDeleteGoField
  #425 = Methodref          #424.#307     // argonaut/CursorOpDeleteGoField."<init>":(Ljava/lang/String;)V
  #426 = Utf8               deleteLefts
  #427 = Utf8               $anonfun$deleteLefts$1
  #428 = NameAndType        #427:#166     // $anonfun$deleteLefts$1:(Largonaut/Cursor;)Lscala/Option;
  #429 = Methodref          #2.#428       // argonaut/HCursor.$anonfun$deleteLefts$1:(Largonaut/Cursor;)Lscala/Option;
  #430 = MethodHandle       6:#429        // REF_invokeStatic argonaut/HCursor.$anonfun$deleteLefts$1:(Largonaut/Cursor;)Lscala/Option;
  #431 = InvokeDynamic      #21:#172      // #21:apply:()Lscala/Function1;
  #432 = Utf8               argonaut/CursorOpDeleteLefts$
  #433 = Class              #432          // argonaut/CursorOpDeleteLefts$
  #434 = Utf8               Largonaut/CursorOpDeleteLefts$;
  #435 = NameAndType        #28:#434      // MODULE$:Largonaut/CursorOpDeleteLefts$;
  #436 = Fieldref           #433.#435     // argonaut/CursorOpDeleteLefts$.MODULE$:Largonaut/CursorOpDeleteLefts$;
  #437 = Utf8               deleteRights
  #438 = Utf8               $anonfun$deleteRights$1
  #439 = NameAndType        #438:#166     // $anonfun$deleteRights$1:(Largonaut/Cursor;)Lscala/Option;
  #440 = Methodref          #2.#439       // argonaut/HCursor.$anonfun$deleteRights$1:(Largonaut/Cursor;)Lscala/Option;
  #441 = MethodHandle       6:#440        // REF_invokeStatic argonaut/HCursor.$anonfun$deleteRights$1:(Largonaut/Cursor;)Lscala/Option;
  #442 = InvokeDynamic      #22:#172      // #22:apply:()Lscala/Function1;
  #443 = Utf8               argonaut/CursorOpDeleteRights$
  #444 = Class              #443          // argonaut/CursorOpDeleteRights$
  #445 = Utf8               Largonaut/CursorOpDeleteRights$;
  #446 = NameAndType        #28:#445      // MODULE$:Largonaut/CursorOpDeleteRights$;
  #447 = Fieldref           #444.#446     // argonaut/CursorOpDeleteRights$.MODULE$:Largonaut/CursorOpDeleteRights$;
  #448 = Utf8               setLefts
  #449 = Utf8               (Lscala/collection/immutable/List;)Largonaut/ACursor;
  #450 = Utf8               (Lscala/collection/immutable/List<Largonaut/Json;>;)Largonaut/ACursor;
  #451 = Utf8               x
  #452 = Utf8               $anonfun$setLefts$1
  #453 = Utf8               (Lscala/collection/immutable/List;Largonaut/Cursor;)Lscala/Option;
  #454 = NameAndType        #452:#453     // $anonfun$setLefts$1:(Lscala/collection/immutable/List;Largonaut/Cursor;)Lscala/Option;
  #455 = Methodref          #2.#454       // argonaut/HCursor.$anonfun$setLefts$1:(Lscala/collection/immutable/List;Largonaut/Cursor;)Lscala/Option;
  #456 = MethodHandle       6:#455        // REF_invokeStatic argonaut/HCursor.$anonfun$setLefts$1:(Lscala/collection/immutable/List;Largonaut/Cursor;)Lscala/Option;
  #457 = Utf8               (Lscala/collection/immutable/List;)Lscala/Function1;
  #458 = NameAndType        #34:#457      // apply:(Lscala/collection/immutable/List;)Lscala/Function1;
  #459 = InvokeDynamic      #23:#458      // #23:apply:(Lscala/collection/immutable/List;)Lscala/Function1;
  #460 = Utf8               argonaut/CursorOpSetLefts
  #461 = Class              #460          // argonaut/CursorOpSetLefts
  #462 = Utf8               (Lscala/collection/immutable/List;)V
  #463 = NameAndType        #116:#462     // "<init>":(Lscala/collection/immutable/List;)V
  #464 = Methodref          #461.#463     // argonaut/CursorOpSetLefts."<init>":(Lscala/collection/immutable/List;)V
  #465 = Utf8               Lscala/collection/immutable/List;
  #466 = Utf8               setRights
  #467 = Utf8               $anonfun$setRights$1
  #468 = NameAndType        #467:#453     // $anonfun$setRights$1:(Lscala/collection/immutable/List;Largonaut/Cursor;)Lscala/Option;
  #469 = Methodref          #2.#468       // argonaut/HCursor.$anonfun$setRights$1:(Lscala/collection/immutable/List;Largonaut/Cursor;)Lscala/Option;
  #470 = MethodHandle       6:#469        // REF_invokeStatic argonaut/HCursor.$anonfun$setRights$1:(Lscala/collection/immutable/List;Largonaut/Cursor;)Lscala/Option;
  #471 = InvokeDynamic      #24:#458      // #24:apply:(Lscala/collection/immutable/List;)Lscala/Function1;
  #472 = Utf8               argonaut/CursorOpSetRights
  #473 = Class              #472          // argonaut/CursorOpSetRights
  #474 = Methodref          #473.#463     // argonaut/CursorOpSetRights."<init>":(Lscala/collection/immutable/List;)V
  #475 = Utf8               up
  #476 = Utf8               $anonfun$up$1
  #477 = NameAndType        #476:#166     // $anonfun$up$1:(Largonaut/Cursor;)Lscala/Option;
  #478 = Methodref          #2.#477       // argonaut/HCursor.$anonfun$up$1:(Largonaut/Cursor;)Lscala/Option;
  #479 = MethodHandle       6:#478        // REF_invokeStatic argonaut/HCursor.$anonfun$up$1:(Largonaut/Cursor;)Lscala/Option;
  #480 = InvokeDynamic      #25:#172      // #25:apply:()Lscala/Function1;
  #481 = Utf8               argonaut/CursorOpUp$
  #482 = Class              #481          // argonaut/CursorOpUp$
  #483 = Utf8               Largonaut/CursorOpUp$;
  #484 = NameAndType        #28:#483      // MODULE$:Largonaut/CursorOpUp$;
  #485 = Fieldref           #482.#484     // argonaut/CursorOpUp$.MODULE$:Largonaut/CursorOpUp$;
  #486 = Utf8               unary_$minus
  #487 = Utf8               undo
  #488 = NameAndType        #487:#96      // undo:()Largonaut/Json;
  #489 = Methodref          #100.#488     // argonaut/Cursor.undo:()Largonaut/Json;
  #490 = Utf8               copy
  #491 = Utf8               copy$default$1
  #492 = Utf8               copy$default$2
  #493 = Utf8               productPrefix
  #494 = Utf8               ()Ljava/lang/String;
  #495 = Utf8               HCursor
  #496 = String             #495          // HCursor
  #497 = Utf8               productArity
  #498 = Utf8               ()I
  #499 = Utf8               productElement
  #500 = Utf8               (I)Ljava/lang/Object;
  #501 = Utf8               x$1
  #502 = Utf8               scala/runtime/Statics
  #503 = Class              #502          // scala/runtime/Statics
  #504 = Utf8               ioobe
  #505 = NameAndType        #504:#500     // ioobe:(I)Ljava/lang/Object;
  #506 = Methodref          #503.#505     // scala/runtime/Statics.ioobe:(I)Ljava/lang/Object;
  #507 = Utf8               productIterator
  #508 = Utf8               ()Lscala/collection/Iterator<Ljava/lang/Object;>;
  #509 = Utf8               scala/runtime/ScalaRunTime$
  #510 = Class              #509          // scala/runtime/ScalaRunTime$
  #511 = Utf8               Lscala/runtime/ScalaRunTime$;
  #512 = NameAndType        #28:#511      // MODULE$:Lscala/runtime/ScalaRunTime$;
  #513 = Fieldref           #510.#512     // scala/runtime/ScalaRunTime$.MODULE$:Lscala/runtime/ScalaRunTime$;
  #514 = Utf8               typedProductIterator
  #515 = NameAndType        #514:#42      // typedProductIterator:(Lscala/Product;)Lscala/collection/Iterator;
  #516 = Methodref          #510.#515     // scala/runtime/ScalaRunTime$.typedProductIterator:(Lscala/Product;)Lscala/collection/Iterator;
  #517 = Utf8               canEqual
  #518 = Utf8               (Ljava/lang/Object;)Z
  #519 = Utf8               Ljava/lang/Object;
  #520 = Utf8               productElementName
  #521 = Utf8               (I)Ljava/lang/String;
  #522 = String             #18           // cursor
  #523 = String             #20           // history
  #524 = Utf8               java/lang/String
  #525 = Class              #524          // java/lang/String
  #526 = Utf8               hashCode
  #527 = Utf8               _hashCode
  #528 = Utf8               (Lscala/Product;)I
  #529 = NameAndType        #527:#528     // _hashCode:(Lscala/Product;)I
  #530 = Methodref          #510.#529     // scala/runtime/ScalaRunTime$._hashCode:(Lscala/Product;)I
  #531 = Utf8               toString
  #532 = Utf8               _toString
  #533 = Utf8               (Lscala/Product;)Ljava/lang/String;
  #534 = NameAndType        #532:#533     // _toString:(Lscala/Product;)Ljava/lang/String;
  #535 = Methodref          #510.#534     // scala/runtime/ScalaRunTime$._toString:(Lscala/Product;)Ljava/lang/String;
  #536 = Utf8               equals
  #537 = NameAndType        #536:#518     // equals:(Ljava/lang/Object;)Z
  #538 = Methodref          #4.#537       // java/lang/Object.equals:(Ljava/lang/Object;)Z
  #539 = NameAndType        #517:#518     // canEqual:(Ljava/lang/Object;)Z
  #540 = Methodref          #2.#539       // argonaut/HCursor.canEqual:(Ljava/lang/Object;)Z
  #541 = Utf8               j$1
  #542 = Utf8               x$2
  #543 = NameAndType        #164:#149     // left:()Lscala/Option;
  #544 = Methodref          #100.#543     // argonaut/Cursor.left:()Lscala/Option;
  #545 = Utf8               x$3
  #546 = NameAndType        #185:#149     // right:()Lscala/Option;
  #547 = Methodref          #100.#546     // argonaut/Cursor.right:()Lscala/Option;
  #548 = Utf8               x$4
  #549 = NameAndType        #196:#149     // first:()Lscala/Option;
  #550 = Methodref          #100.#549     // argonaut/Cursor.first:()Lscala/Option;
  #551 = Utf8               x$5
  #552 = NameAndType        #207:#149     // last:()Lscala/Option;
  #553 = Methodref          #100.#552     // argonaut/Cursor.last:()Lscala/Option;
  #554 = Utf8               n$1
  #555 = Utf8               x$6
  #556 = Utf8               (I)Lscala/Option;
  #557 = NameAndType        #221:#556     // leftN:(I)Lscala/Option;
  #558 = Methodref          #100.#557     // argonaut/Cursor.leftN:(I)Lscala/Option;
  #559 = Utf8               n$2
  #560 = Utf8               x$7
  #561 = NameAndType        #239:#556     // rightN:(I)Lscala/Option;
  #562 = Methodref          #100.#561     // argonaut/Cursor.rightN:(I)Lscala/Option;
  #563 = Utf8               p$1
  #564 = Utf8               x$8
  #565 = Utf8               (Lscala/Function1;)Lscala/Option;
  #566 = NameAndType        #254:#565     // leftAt:(Lscala/Function1;)Lscala/Option;
  #567 = Methodref          #100.#566     // argonaut/Cursor.leftAt:(Lscala/Function1;)Lscala/Option;
  #568 = Utf8               p$2
  #569 = Utf8               x$9
  #570 = NameAndType        #271:#565     // rightAt:(Lscala/Function1;)Lscala/Option;
  #571 = Methodref          #100.#570     // argonaut/Cursor.rightAt:(Lscala/Function1;)Lscala/Option;
  #572 = Utf8               p$3
  #573 = Utf8               x$10
  #574 = NameAndType        #282:#565     // find:(Lscala/Function1;)Lscala/Option;
  #575 = Methodref          #100.#574     // argonaut/Cursor.find:(Lscala/Function1;)Lscala/Option;
  #576 = Utf8               q$1
  #577 = Utf8               x$11
  #578 = Utf8               (Ljava/lang/String;)Lscala/Option;
  #579 = NameAndType        #293:#578     // field:(Ljava/lang/String;)Lscala/Option;
  #580 = Methodref          #100.#579     // argonaut/Cursor.field:(Ljava/lang/String;)Lscala/Option;
  #581 = Utf8               q$2
  #582 = Utf8               x$12
  #583 = NameAndType        #309:#578     // downField:(Ljava/lang/String;)Lscala/Option;
  #584 = Methodref          #100.#583     // argonaut/Cursor.downField:(Ljava/lang/String;)Lscala/Option;
  #585 = Utf8               x$13
  #586 = NameAndType        #320:#149     // downArray:()Lscala/Option;
  #587 = Methodref          #100.#586     // argonaut/Cursor.downArray:()Lscala/Option;
  #588 = Utf8               p$4
  #589 = Utf8               x$14
  #590 = NameAndType        #335:#565     // downAt:(Lscala/Function1;)Lscala/Option;
  #591 = Methodref          #100.#590     // argonaut/Cursor.downAt:(Lscala/Function1;)Lscala/Option;
  #592 = Utf8               n$3
  #593 = Utf8               x$15
  #594 = NameAndType        #347:#556     // downN:(I)Lscala/Option;
  #595 = Methodref          #100.#594     // argonaut/Cursor.downN:(I)Lscala/Option;
  #596 = Utf8               x$16
  #597 = NameAndType        #359:#149     // deleteGoParent:()Lscala/Option;
  #598 = Methodref          #100.#597     // argonaut/Cursor.deleteGoParent:()Lscala/Option;
  #599 = Utf8               x$17
  #600 = NameAndType        #373:#149     // deleteGoLeft:()Lscala/Option;
  #601 = Methodref          #100.#600     // argonaut/Cursor.deleteGoLeft:()Lscala/Option;
  #602 = Utf8               x$18
  #603 = NameAndType        #384:#149     // deleteGoRight:()Lscala/Option;
  #604 = Methodref          #100.#603     // argonaut/Cursor.deleteGoRight:()Lscala/Option;
  #605 = Utf8               x$19
  #606 = NameAndType        #395:#149     // deleteGoFirst:()Lscala/Option;
  #607 = Methodref          #100.#606     // argonaut/Cursor.deleteGoFirst:()Lscala/Option;
  #608 = Utf8               x$20
  #609 = NameAndType        #406:#149     // deleteGoLast:()Lscala/Option;
  #610 = Methodref          #100.#609     // argonaut/Cursor.deleteGoLast:()Lscala/Option;
  #611 = Utf8               q$3
  #612 = Utf8               x$21
  #613 = NameAndType        #417:#578     // deleteGoField:(Ljava/lang/String;)Lscala/Option;
  #614 = Methodref          #100.#613     // argonaut/Cursor.deleteGoField:(Ljava/lang/String;)Lscala/Option;
  #615 = Utf8               x$22
  #616 = NameAndType        #426:#149     // deleteLefts:()Lscala/Option;
  #617 = Methodref          #100.#616     // argonaut/Cursor.deleteLefts:()Lscala/Option;
  #618 = Utf8               x$23
  #619 = NameAndType        #437:#149     // deleteRights:()Lscala/Option;
  #620 = Methodref          #100.#619     // argonaut/Cursor.deleteRights:()Lscala/Option;
  #621 = Utf8               x$27
  #622 = Utf8               x$24
  #623 = Utf8               (Lscala/collection/immutable/List;)Lscala/Option;
  #624 = NameAndType        #448:#623     // setLefts:(Lscala/collection/immutable/List;)Lscala/Option;
  #625 = Methodref          #100.#624     // argonaut/Cursor.setLefts:(Lscala/collection/immutable/List;)Lscala/Option;
  #626 = Utf8               x$28
  #627 = Utf8               x$25
  #628 = NameAndType        #466:#623     // setRights:(Lscala/collection/immutable/List;)Lscala/Option;
  #629 = Methodref          #100.#628     // argonaut/Cursor.setRights:(Lscala/collection/immutable/List;)Lscala/Option;
  #630 = Utf8               x$26
  #631 = NameAndType        #475:#149     // up:()Lscala/Option;
  #632 = Methodref          #100.#631     // argonaut/Cursor.up:()Lscala/Option;
  #633 = Utf8               ()V
  #634 = NameAndType        #116:#633     // "<init>":()V
  #635 = Methodref          #4.#634       // java/lang/Object."<init>":()V
  #636 = Utf8               $init$
  #637 = Utf8               (Lscala/Product;)V
  #638 = NameAndType        #636:#637     // $init$:(Lscala/Product;)V
  #639 = InterfaceMethodref #6.#638       // scala/Product.$init$:(Lscala/Product;)V
  #640 = Utf8               $deserializeLambda$
  #641 = Utf8               (Ljava/lang/invoke/SerializedLambda;)Ljava/lang/Object;
  #642 = Utf8               scala/runtime/LambdaDeserialize
  #643 = Class              #642          // scala/runtime/LambdaDeserialize
  #644 = Utf8               bootstrap
  #645 = Utf8               (Ljava/lang/invoke/MethodHandles$Lookup;Ljava/lang/String;Ljava/lang/invoke/MethodType;[Ljava/lang/invoke/MethodHandle;)Ljava/lang/invoke/CallSite;
  #646 = NameAndType        #644:#645     // bootstrap:(Ljava/lang/invoke/MethodHandles$Lookup;Ljava/lang/String;Ljava/lang/invoke/MethodType;[Ljava/lang/invoke/MethodHandle;)Ljava/lang/invoke/CallSite;
  #647 = Methodref          #643.#646     // scala/runtime/LambdaDeserialize.bootstrap:(Ljava/lang/invoke/MethodHandles$Lookup;Ljava/lang/String;Ljava/lang/invoke/MethodType;[Ljava/lang/invoke/MethodHandle;)Ljava/lang/invoke/CallSite;
  #648 = MethodHandle       6:#647        // REF_invokeStatic scala/runtime/LambdaDeserialize.bootstrap:(Ljava/lang/invoke/MethodHandles$Lookup;Ljava/lang/String;Ljava/lang/invoke/MethodType;[Ljava/lang/invoke/MethodHandle;)Ljava/lang/invoke/CallSite;
  #649 = Utf8               lambdaDeserialize
  #650 = NameAndType        #649:#641     // lambdaDeserialize:(Ljava/lang/invoke/SerializedLambda;)Ljava/lang/Object;
  #651 = InvokeDynamic      #26:#650      // #26:lambdaDeserialize:(Ljava/lang/invoke/SerializedLambda;)Ljava/lang/Object;
  #652 = Utf8               Code
  #653 = Utf8               Signature
  #654 = Utf8               MethodParameters
  #655 = Utf8               LineNumberTable
  #656 = Utf8               LocalVariableTable
  #657 = Utf8               StackMapTable
  #658 = Utf8               InnerClasses
  #659 = Utf8               SourceFile
  #660 = Utf8               RuntimeVisibleAnnotations
  #661 = Utf8               BootstrapMethods
  #662 = Utf8               ScalaInlineInfo
  #663 = Utf8               ScalaSig
{
  private final argonaut.Cursor cursor;
    descriptor: Largonaut/Cursor;
    flags: (0x0012) ACC_PRIVATE, ACC_FINAL

  private final argonaut.CursorHistory history;
    descriptor: Largonaut/CursorHistory;
    flags: (0x0012) ACC_PRIVATE, ACC_FINAL

  public static scala.Option<scala.Tuple2<argonaut.Cursor, argonaut.CursorHistory>> unapply(argonaut.HCursor);
    descriptor: (Largonaut/HCursor;)Lscala/Option;
    flags: (0x0009) ACC_PUBLIC, ACC_STATIC
    Code:
      stack=2, locals=1, args_size=1
         0: getstatic     #31                 // Field argonaut/HCursor$.MODULE$:Largonaut/HCursor$;
         3: aload_0
         4: invokevirtual #33                 // Method argonaut/HCursor$.unapply:(Largonaut/HCursor;)Lscala/Option;
         7: areturn
    Signature: #24                          // (Largonaut/HCursor;)Lscala/Option<Lscala/Tuple2<Largonaut/Cursor;Largonaut/CursorHistory;>;>;
    MethodParameters:
      Name                           Flags
      x$0                            final

  public static argonaut.HCursor apply(argonaut.Cursor, argonaut.CursorHistory);
    descriptor: (Largonaut/Cursor;Largonaut/CursorHistory;)Largonaut/HCursor;
    flags: (0x0009) ACC_PUBLIC, ACC_STATIC
    Code:
      stack=3, locals=2, args_size=2
         0: getstatic     #31                 // Field argonaut/HCursor$.MODULE$:Largonaut/HCursor$;
         3: aload_0
         4: aload_1
         5: invokevirtual #37                 // Method argonaut/HCursor$.apply:(Largonaut/Cursor;Largonaut/CursorHistory;)Largonaut/HCursor;
         8: areturn
    MethodParameters:
      Name                           Flags
      cursor                         final
      history                        final

  public scala.collection.Iterator<java.lang.String> productElementNames();
    descriptor: ()Lscala/collection/Iterator;
    flags: (0x0001) ACC_PUBLIC
    Code:
      stack=1, locals=1, args_size=1
         0: aload_0
         1: invokestatic  #44                 // InterfaceMethod scala/Product.productElementNames$:(Lscala/Product;)Lscala/collection/Iterator;
         4: areturn
      LineNumberTable:
        line 3: 0
      LocalVariableTable:
        Start  Length  Slot  Name   Signature
            0       5     0  this   Largonaut/HCursor;
    Signature: #40                          // ()Lscala/collection/Iterator<Ljava/lang/String;>;

  public argonaut.Cursor cursor();
    descriptor: ()Largonaut/Cursor;
    flags: (0x0001) ACC_PUBLIC
    Code:
      stack=1, locals=1, args_size=1
         0: aload_0
         1: getfield      #49                 // Field cursor:Largonaut/Cursor;
         4: areturn
      LineNumberTable:
        line 3: 0
      LocalVariableTable:
        Start  Length  Slot  Name   Signature
            0       5     0  this   Largonaut/HCursor;

  public argonaut.CursorHistory history();
    descriptor: ()Largonaut/CursorHistory;
    flags: (0x0001) ACC_PUBLIC
    Code:
      stack=1, locals=1, args_size=1
         0: aload_0
         1: getfield      #52                 // Field history:Largonaut/CursorHistory;
         4: areturn
      LineNumberTable:
        line 3: 0
      LocalVariableTable:
        Start  Length  Slot  Name   Signature
            0       5     0  this   Largonaut/HCursor;

  public argonaut.ACursor acursor();
    descriptor: ()Largonaut/ACursor;
    flags: (0x0001) ACC_PUBLIC
    Code:
      stack=2, locals=1, args_size=1
         0: getstatic     #59                 // Field argonaut/ACursor$.MODULE$:Largonaut/ACursor$;
         3: aload_0
         4: invokevirtual #63                 // Method argonaut/ACursor$.ok:(Largonaut/HCursor;)Largonaut/ACursor;
         7: areturn
      LineNumberTable:
        line 7: 0
      LocalVariableTable:
        Start  Length  Slot  Name   Signature
            0       8     0  this   Largonaut/HCursor;

  public <A extends java.lang.Object> argonaut.DecodeResult<A> jdecode(argonaut.DecodeJson<A>);
    descriptor: (Largonaut/DecodeJson;)Largonaut/DecodeResult;
    flags: (0x0001) ACC_PUBLIC
    Code:
      stack=2, locals=2, args_size=2
         0: aload_1
         1: aload_0
         2: invokeinterface #73,  2           // InterfaceMethod argonaut/DecodeJson.decode:(Largonaut/HCursor;)Largonaut/DecodeResult;
         7: areturn
      LineNumberTable:
        line 13: 0
      LocalVariableTable:
        Start  Length  Slot  Name   Signature
            0       8     0  this   Largonaut/HCursor;
            0       8     1     e   Largonaut/DecodeJson;
    Signature: #66                          // <A:Ljava/lang/Object;>(Largonaut/DecodeJson<TA;>;)Largonaut/DecodeResult<TA;>;
    MethodParameters:
      Name                           Flags
      e                              final

  public <A extends java.lang.Object> argonaut.DecodeResult<A> as(argonaut.DecodeJson<A>);
    descriptor: (Largonaut/DecodeJson;)Largonaut/DecodeResult;
    flags: (0x0001) ACC_PUBLIC
    Code:
      stack=2, locals=2, args_size=2
         0: aload_0
         1: aload_1
         2: invokevirtual #77                 // Method jdecode:(Largonaut/DecodeJson;)Largonaut/DecodeResult;
         5: areturn
      LineNumberTable:
        line 20: 0
      LocalVariableTable:
        Start  Length  Slot  Name   Signature
            0       6     0  this   Largonaut/HCursor;
            0       6     1     e   Largonaut/DecodeJson;
    Signature: #66                          // <A:Ljava/lang/Object;>(Largonaut/DecodeJson<TA;>;)Largonaut/DecodeResult<TA;>;
    MethodParameters:
      Name                           Flags
      e                              final

  public <A extends java.lang.Object> argonaut.DecodeResult<A> get(java.lang.String, argonaut.DecodeJson<A>);
    descriptor: (Ljava/lang/String;Largonaut/DecodeJson;)Largonaut/DecodeResult;
    flags: (0x0001) ACC_PUBLIC
    Code:
      stack=2, locals=3, args_size=3
         0: aload_0
         1: aload_1
         2: invokevirtual #85                 // Method $minus$minus$bslash:(Ljava/lang/String;)Largonaut/ACursor;
         5: aload_2
         6: invokevirtual #89                 // Method argonaut/ACursor.as:(Largonaut/DecodeJson;)Largonaut/DecodeResult;
         9: areturn
      LineNumberTable:
        line 26: 0
      LocalVariableTable:
        Start  Length  Slot  Name   Signature
            0      10     0  this   Largonaut/HCursor;
            0      10     1  name   Ljava/lang/String;
            0      10     2     e   Largonaut/DecodeJson;
    Signature: #80                          // <A:Ljava/lang/Object;>(Ljava/lang/String;Largonaut/DecodeJson<TA;>;)Largonaut/DecodeResult<TA;>;
    MethodParameters:
      Name                           Flags
      name                           final
      e                              final

  public argonaut.ACursor failedACursor();
    descriptor: ()Largonaut/ACursor;
    flags: (0x0001) ACC_PUBLIC
    Code:
      stack=2, locals=1, args_size=1
         0: getstatic     #59                 // Field argonaut/ACursor$.MODULE$:Largonaut/ACursor$;
         3: aload_0
         4: invokevirtual #94                 // Method argonaut/ACursor$.fail:(Largonaut/HCursor;)Largonaut/ACursor;
         7: areturn
      LineNumberTable:
        line 29: 0
      LocalVariableTable:
        Start  Length  Slot  Name   Signature
            0       8     0  this   Largonaut/HCursor;

  public argonaut.Json focus();
    descriptor: ()Largonaut/Json;
    flags: (0x0001) ACC_PUBLIC
    Code:
      stack=1, locals=1, args_size=1
         0: aload_0
         1: invokevirtual #98                 // Method cursor:()Largonaut/Cursor;
         4: invokevirtual #102                // Method argonaut/Cursor.focus:()Largonaut/Json;
         7: areturn
      LineNumberTable:
        line 33: 0
      LocalVariableTable:
        Start  Length  Slot  Name   Signature
            0       8     0  this   Largonaut/HCursor;

  public argonaut.HCursor $greater$minus$greater(scala.Function1<argonaut.Json, argonaut.Json>);
    descriptor: (Lscala/Function1;)Largonaut/HCursor;
    flags: (0x0001) ACC_PUBLIC
    Code:
      stack=2, locals=2, args_size=2
         0: aload_0
         1: aload_1
         2: invokevirtual #109                // Method withFocus:(Lscala/Function1;)Largonaut/HCursor;
         5: areturn
      LineNumberTable:
        line 37: 0
      LocalVariableTable:
        Start  Length  Slot  Name   Signature
            0       6     0  this   Largonaut/HCursor;
            0       6     1     k   Lscala/Function1;
    Signature: #105                         // (Lscala/Function1<Largonaut/Json;Largonaut/Json;>;)Largonaut/HCursor;
    MethodParameters:
      Name                           Flags
      k                              final

  public argonaut.HCursor withFocus(scala.Function1<argonaut.Json, argonaut.Json>);
    descriptor: (Lscala/Function1;)Largonaut/HCursor;
    flags: (0x0001) ACC_PUBLIC
    Code:
      stack=4, locals=2, args_size=2
         0: new           #2                  // class argonaut/HCursor
         3: dup
         4: aload_0
         5: invokevirtual #98                 // Method cursor:()Largonaut/Cursor;
         8: aload_1
         9: invokevirtual #113                // Method argonaut/Cursor.withFocus:(Lscala/Function1;)Largonaut/Cursor;
        12: aload_0
        13: invokevirtual #115                // Method history:()Largonaut/CursorHistory;
        16: invokespecial #119                // Method "<init>":(Largonaut/Cursor;Largonaut/CursorHistory;)V
        19: areturn
      LineNumberTable:
        line 41: 0
      LocalVariableTable:
        Start  Length  Slot  Name   Signature
            0      20     0  this   Largonaut/HCursor;
            0      20     1     k   Lscala/Function1;
    Signature: #105                         // (Lscala/Function1<Largonaut/Json;Largonaut/Json;>;)Largonaut/HCursor;
    MethodParameters:
      Name                           Flags
      k                              final

  public argonaut.HCursor set(argonaut.Json);
    descriptor: (Largonaut/Json;)Largonaut/HCursor;
    flags: (0x0001) ACC_PUBLIC
    Code:
      stack=2, locals=2, args_size=2
         0: aload_0
         1: aload_1
         2: invokedynamic #143,  0            // InvokeDynamic #0:apply:(Largonaut/Json;)Lscala/Function1;
         7: invokevirtual #109                // Method withFocus:(Lscala/Function1;)Largonaut/HCursor;
        10: areturn
      LineNumberTable:
        line 45: 0
      LocalVariableTable:
        Start  Length  Slot  Name   Signature
            0      11     0  this   Largonaut/HCursor;
            0      11     1     j   Largonaut/Json;
    MethodParameters:
      Name                           Flags
      j                              final

  public argonaut.HCursor $colon$eq(argonaut.Json);
    descriptor: (Largonaut/Json;)Largonaut/HCursor;
    flags: (0x0001) ACC_PUBLIC
    Code:
      stack=2, locals=2, args_size=2
         0: aload_0
         1: aload_1
         2: invokevirtual #147                // Method set:(Largonaut/Json;)Largonaut/HCursor;
         5: areturn
      LineNumberTable:
        line 49: 0
      LocalVariableTable:
        Start  Length  Slot  Name   Signature
            0       6     0  this   Largonaut/HCursor;
            0       6     1     j   Largonaut/Json;
    MethodParameters:
      Name                           Flags
      j                              final

  public scala.Option<scala.collection.immutable.List<argonaut.Json>> lefts();
    descriptor: ()Lscala/Option;
    flags: (0x0001) ACC_PUBLIC
    Code:
      stack=1, locals=1, args_size=1
         0: aload_0
         1: invokevirtual #98                 // Method cursor:()Largonaut/Cursor;
         4: invokevirtual #152                // Method argonaut/Cursor.lefts:()Lscala/Option;
         7: areturn
      LineNumberTable:
        line 55: 0
      LocalVariableTable:
        Start  Length  Slot  Name   Signature
            0       8     0  this   Largonaut/HCursor;
    Signature: #150                         // ()Lscala/Option<Lscala/collection/immutable/List<Largonaut/Json;>;>;

  public scala.Option<scala.collection.immutable.List<argonaut.Json>> rights();
    descriptor: ()Lscala/Option;
    flags: (0x0001) ACC_PUBLIC
    Code:
      stack=1, locals=1, args_size=1
         0: aload_0
         1: invokevirtual #98                 // Method cursor:()Largonaut/Cursor;
         4: invokevirtual #155                // Method argonaut/Cursor.rights:()Lscala/Option;
         7: areturn
      LineNumberTable:
        line 61: 0
      LocalVariableTable:
        Start  Length  Slot  Name   Signature
            0       8     0  this   Largonaut/HCursor;
    Signature: #150                         // ()Lscala/Option<Lscala/collection/immutable/List<Largonaut/Json;>;>;

  public scala.Option<scala.collection.immutable.Set<java.lang.String>> fieldSet();
    descriptor: ()Lscala/Option;
    flags: (0x0001) ACC_PUBLIC
    Code:
      stack=1, locals=1, args_size=1
         0: aload_0
         1: invokevirtual #98                 // Method cursor:()Largonaut/Cursor;
         4: invokevirtual #159                // Method argonaut/Cursor.fieldSet:()Lscala/Option;
         7: areturn
      LineNumberTable:
        line 67: 0
      LocalVariableTable:
        Start  Length  Slot  Name   Signature
            0       8     0  this   Largonaut/HCursor;
    Signature: #157                         // ()Lscala/Option<Lscala/collection/immutable/Set<Ljava/lang/String;>;>;

  public scala.Option<scala.collection.immutable.List<java.lang.String>> fields();
    descriptor: ()Lscala/Option;
    flags: (0x0001) ACC_PUBLIC
    Code:
      stack=1, locals=1, args_size=1
         0: aload_0
         1: invokevirtual #98                 // Method cursor:()Largonaut/Cursor;
         4: invokevirtual #163                // Method argonaut/Cursor.fields:()Lscala/Option;
         7: areturn
      LineNumberTable:
        line 73: 0
      LocalVariableTable:
        Start  Length  Slot  Name   Signature
            0       8     0  this   Largonaut/HCursor;
    Signature: #161                         // ()Lscala/Option<Lscala/collection/immutable/List<Ljava/lang/String;>;>;

  public argonaut.ACursor left();
    descriptor: ()Largonaut/ACursor;
    flags: (0x0001) ACC_PUBLIC
    Code:
      stack=4, locals=1, args_size=1
         0: aload_0
         1: invokevirtual #115                // Method history:()Largonaut/CursorHistory;
         4: invokedynamic #173,  0            // InvokeDynamic #1:apply:()Lscala/Function1;
         9: aload_0
        10: invokevirtual #98                 // Method cursor:()Largonaut/Cursor;
        13: getstatic     #178                // Field argonaut/CursorOpLeft$.MODULE$:Largonaut/CursorOpLeft$;
        16: invokevirtual #184                // Method argonaut/CursorHistory.acursorElement:(Lscala/Function1;Largonaut/Cursor;Largonaut/CursorOpElement;)Largonaut/ACursor;
        19: areturn
      LineNumberTable:
        line 77: 0
      LocalVariableTable:
        Start  Length  Slot  Name   Signature
            0      20     0  this   Largonaut/HCursor;

  public argonaut.ACursor right();
    descriptor: ()Largonaut/ACursor;
    flags: (0x0001) ACC_PUBLIC
    Code:
      stack=4, locals=1, args_size=1
         0: aload_0
         1: invokevirtual #115                // Method history:()Largonaut/CursorHistory;
         4: invokedynamic #190,  0            // InvokeDynamic #2:apply:()Lscala/Function1;
         9: aload_0
        10: invokevirtual #98                 // Method cursor:()Largonaut/Cursor;
        13: getstatic     #195                // Field argonaut/CursorOpRight$.MODULE$:Largonaut/CursorOpRight$;
        16: invokevirtual #184                // Method argonaut/CursorHistory.acursorElement:(Lscala/Function1;Largonaut/Cursor;Largonaut/CursorOpElement;)Largonaut/ACursor;
        19: areturn
      LineNumberTable:
        line 81: 0
      LocalVariableTable:
        Start  Length  Slot  Name   Signature
            0      20     0  this   Largonaut/HCursor;

  public argonaut.ACursor first();
    descriptor: ()Largonaut/ACursor;
    flags: (0x0001) ACC_PUBLIC
    Code:
      stack=4, locals=1, args_size=1
         0: aload_0
         1: invokevirtual #115                // Method history:()Largonaut/CursorHistory;
         4: invokedynamic #201,  0            // InvokeDynamic #3:apply:()Lscala/Function1;
         9: aload_0
        10: invokevirtual #98                 // Method cursor:()Largonaut/Cursor;
        13: getstatic     #206                // Field argonaut/CursorOpFirst$.MODULE$:Largonaut/CursorOpFirst$;
        16: invokevirtual #184                // Method argonaut/CursorHistory.acursorElement:(Lscala/Function1;Largonaut/Cursor;Largonaut/CursorOpElement;)Largonaut/ACursor;
        19: areturn
      LineNumberTable:
        line 85: 0
      LocalVariableTable:
        Start  Length  Slot  Name   Signature
            0      20     0  this   Largonaut/HCursor;

  public argonaut.ACursor last();
    descriptor: ()Largonaut/ACursor;
    flags: (0x0001) ACC_PUBLIC
    Code:
      stack=4, locals=1, args_size=1
         0: aload_0
         1: invokevirtual #115                // Method history:()Largonaut/CursorHistory;
         4: invokedynamic #212,  0            // InvokeDynamic #4:apply:()Lscala/Function1;
         9: aload_0
        10: invokevirtual #98                 // Method cursor:()Largonaut/Cursor;
        13: getstatic     #217                // Field argonaut/CursorOpLast$.MODULE$:Largonaut/CursorOpLast$;
        16: invokevirtual #184                // Method argonaut/CursorHistory.acursorElement:(Lscala/Function1;Largonaut/Cursor;Largonaut/CursorOpElement;)Largonaut/ACursor;
        19: areturn
      LineNumberTable:
        line 89: 0
      LocalVariableTable:
        Start  Length  Slot  Name   Signature
            0      20     0  this   Largonaut/HCursor;

  public argonaut.ACursor $minus$less$minus$colon(int);
    descriptor: (I)Largonaut/ACursor;
    flags: (0x0001) ACC_PUBLIC
    Code:
      stack=2, locals=2, args_size=2
         0: aload_0
         1: iload_1
         2: invokevirtual #223                // Method leftN:(I)Largonaut/ACursor;
         5: areturn
      LineNumberTable:
        line 93: 0
      LocalVariableTable:
        Start  Length  Slot  Name   Signature
            0       6     0  this   Largonaut/HCursor;
            0       6     1     n   I
    MethodParameters:
      Name                           Flags
      n                              final

  public argonaut.ACursor leftN(int);
    descriptor: (I)Largonaut/ACursor;
    flags: (0x0001) ACC_PUBLIC
    Code:
      stack=6, locals=2, args_size=2
         0: aload_0
         1: invokevirtual #115                // Method history:()Largonaut/CursorHistory;
         4: iload_1
         5: invokedynamic #232,  0            // InvokeDynamic #5:apply:(I)Lscala/Function1;
        10: aload_0
        11: invokevirtual #98                 // Method cursor:()Largonaut/Cursor;
        14: new           #234                // class argonaut/CursorOpLeftN
        17: dup
        18: iload_1
        19: invokespecial #237                // Method argonaut/CursorOpLeftN."<init>":(I)V
        22: invokevirtual #184                // Method argonaut/CursorHistory.acursorElement:(Lscala/Function1;Largonaut/Cursor;Largonaut/CursorOpElement;)Largonaut/ACursor;
        25: areturn
      LineNumberTable:
        line 97: 0
      LocalVariableTable:
        Start  Length  Slot  Name   Signature
            0      26     0  this   Largonaut/HCursor;
            0      26     1     n   I
    MethodParameters:
      Name                           Flags
      n                              final

  public argonaut.ACursor $colon$minus$greater$minus(int);
    descriptor: (I)Largonaut/ACursor;
    flags: (0x0001) ACC_PUBLIC
    Code:
      stack=2, locals=2, args_size=2
         0: aload_0
         1: iload_1
         2: invokevirtual #241                // Method rightN:(I)Largonaut/ACursor;
         5: areturn
      LineNumberTable:
        line 101: 0
      LocalVariableTable:
        Start  Length  Slot  Name   Signature
            0       6     0  this   Largonaut/HCursor;
            0       6     1     n   I
    MethodParameters:
      Name                           Flags
      n                              final

  public argonaut.ACursor rightN(int);
    descriptor: (I)Largonaut/ACursor;
    flags: (0x0001) ACC_PUBLIC
    Code:
      stack=6, locals=2, args_size=2
         0: aload_0
         1: invokevirtual #115                // Method history:()Largonaut/CursorHistory;
         4: iload_1
         5: invokedynamic #246,  0            // InvokeDynamic #6:apply:(I)Lscala/Function1;
        10: aload_0
        11: invokevirtual #98                 // Method cursor:()Largonaut/Cursor;
        14: new           #248                // class argonaut/CursorOpRightN
        17: dup
        18: iload_1
        19: invokespecial #249                // Method argonaut/CursorOpRightN."<init>":(I)V
        22: invokevirtual #184                // Method argonaut/CursorHistory.acursorElement:(Lscala/Function1;Largonaut/Cursor;Largonaut/CursorOpElement;)Largonaut/ACursor;
        25: areturn
      LineNumberTable:
        line 105: 0
      LocalVariableTable:
        Start  Length  Slot  Name   Signature
            0      26     0  this   Largonaut/HCursor;
            0      26     1     n   I
    MethodParameters:
      Name                           Flags
      n                              final

  public argonaut.ACursor $qmark$less$minus$colon(scala.Function1<argonaut.Json, java.lang.Object>);
    descriptor: (Lscala/Function1;)Largonaut/ACursor;
    flags: (0x0001) ACC_PUBLIC
    Code:
      stack=2, locals=2, args_size=2
         0: aload_0
         1: aload_1
         2: invokevirtual #256                // Method leftAt:(Lscala/Function1;)Largonaut/ACursor;
         5: areturn
      LineNumberTable:
        line 109: 0
      LocalVariableTable:
        Start  Length  Slot  Name   Signature
            0       6     0  this   Largonaut/HCursor;
            0       6     1     p   Lscala/Function1;
    Signature: #252                         // (Lscala/Function1<Largonaut/Json;Ljava/lang/Object;>;)Largonaut/ACursor;
    MethodParameters:
      Name                           Flags
      p                              final

  public argonaut.ACursor leftAt(scala.Function1<argonaut.Json, java.lang.Object>);
    descriptor: (Lscala/Function1;)Largonaut/ACursor;
    flags: (0x0001) ACC_PUBLIC
    Code:
      stack=6, locals=2, args_size=2
         0: aload_0
         1: invokevirtual #115                // Method history:()Largonaut/CursorHistory;
         4: aload_1
         5: invokedynamic #264,  0            // InvokeDynamic #7:apply:(Lscala/Function1;)Lscala/Function1;
        10: aload_0
        11: invokevirtual #98                 // Method cursor:()Largonaut/Cursor;
        14: new           #266                // class argonaut/CursorOpLeftAt
        17: dup
        18: aload_1
        19: invokespecial #269                // Method argonaut/CursorOpLeftAt."<init>":(Lscala/Function1;)V
        22: invokevirtual #184                // Method argonaut/CursorHistory.acursorElement:(Lscala/Function1;Largonaut/Cursor;Largonaut/CursorOpElement;)Largonaut/ACursor;
        25: areturn
      LineNumberTable:
        line 113: 0
      LocalVariableTable:
        Start  Length  Slot  Name   Signature
            0      26     0  this   Largonaut/HCursor;
            0      26     1     p   Lscala/Function1;
    Signature: #252                         // (Lscala/Function1<Largonaut/Json;Ljava/lang/Object;>;)Largonaut/ACursor;
    MethodParameters:
      Name                           Flags
      p                              final

  public argonaut.ACursor $colon$minus$greater$qmark(scala.Function1<argonaut.Json, java.lang.Object>);
    descriptor: (Lscala/Function1;)Largonaut/ACursor;
    flags: (0x0001) ACC_PUBLIC
    Code:
      stack=2, locals=2, args_size=2
         0: aload_0
         1: aload_1
         2: invokevirtual #273                // Method rightAt:(Lscala/Function1;)Largonaut/ACursor;
         5: areturn
      LineNumberTable:
        line 117: 0
      LocalVariableTable:
        Start  Length  Slot  Name   Signature
            0       6     0  this   Largonaut/HCursor;
            0       6     1     p   Lscala/Function1;
    Signature: #252                         // (Lscala/Function1<Largonaut/Json;Ljava/lang/Object;>;)Largonaut/ACursor;
    MethodParameters:
      Name                           Flags
      p                              final

  public argonaut.ACursor rightAt(scala.Function1<argonaut.Json, java.lang.Object>);
    descriptor: (Lscala/Function1;)Largonaut/ACursor;
    flags: (0x0001) ACC_PUBLIC
    Code:
      stack=6, locals=2, args_size=2
         0: aload_0
         1: invokevirtual #115                // Method history:()Largonaut/CursorHistory;
         4: aload_1
         5: invokedynamic #278,  0            // InvokeDynamic #8:apply:(Lscala/Function1;)Lscala/Function1;
        10: aload_0
        11: invokevirtual #98                 // Method cursor:()Largonaut/Cursor;
        14: new           #280                // class argonaut/CursorOpRightAt
        17: dup
        18: aload_1
        19: invokespecial #281                // Method argonaut/CursorOpRightAt."<init>":(Lscala/Function1;)V
        22: invokevirtual #184                // Method argonaut/CursorHistory.acursorElement:(Lscala/Function1;Largonaut/Cursor;Largonaut/CursorOpElement;)Largonaut/ACursor;
        25: areturn
      LineNumberTable:
        line 121: 0
      LocalVariableTable:
        Start  Length  Slot  Name   Signature
            0      26     0  this   Largonaut/HCursor;
            0      26     1     p   Lscala/Function1;
    Signature: #252                         // (Lscala/Function1<Largonaut/Json;Ljava/lang/Object;>;)Largonaut/ACursor;
    MethodParameters:
      Name                           Flags
      p                              final

  public argonaut.ACursor find(scala.Function1<argonaut.Json, java.lang.Object>);
    descriptor: (Lscala/Function1;)Largonaut/ACursor;
    flags: (0x0001) ACC_PUBLIC
    Code:
      stack=6, locals=2, args_size=2
         0: aload_0
         1: invokevirtual #115                // Method history:()Largonaut/CursorHistory;
         4: aload_1
         5: invokedynamic #287,  0            // InvokeDynamic #9:apply:(Lscala/Function1;)Lscala/Function1;
        10: aload_0
        11: invokevirtual #98                 // Method cursor:()Largonaut/Cursor;
        14: new           #289                // class argonaut/CursorOpFind
        17: dup
        18: aload_1
        19: invokespecial #290                // Method argonaut/CursorOpFind."<init>":(Lscala/Function1;)V
        22: invokevirtual #184                // Method argonaut/CursorHistory.acursorElement:(Lscala/Function1;Largonaut/Cursor;Largonaut/CursorOpElement;)Largonaut/ACursor;
        25: areturn
      LineNumberTable:
        line 125: 0
      LocalVariableTable:
        Start  Length  Slot  Name   Signature
            0      26     0  this   Largonaut/HCursor;
            0      26     1     p   Lscala/Function1;
    Signature: #252                         // (Lscala/Function1<Largonaut/Json;Ljava/lang/Object;>;)Largonaut/ACursor;
    MethodParameters:
      Name                           Flags
      p                              final

  public argonaut.ACursor $minus$minus(java.lang.String);
    descriptor: (Ljava/lang/String;)Largonaut/ACursor;
    flags: (0x0001) ACC_PUBLIC
    Code:
      stack=2, locals=2, args_size=2
         0: aload_0
         1: aload_1
         2: invokevirtual #295                // Method field:(Ljava/lang/String;)Largonaut/ACursor;
         5: areturn
      LineNumberTable:
        line 129: 0
      LocalVariableTable:
        Start  Length  Slot  Name   Signature
            0       6     0  this   Largonaut/HCursor;
            0       6     1     q   Ljava/lang/String;
    MethodParameters:
      Name                           Flags
      q                              final

  public argonaut.ACursor field(java.lang.String);
    descriptor: (Ljava/lang/String;)Largonaut/ACursor;
    flags: (0x0001) ACC_PUBLIC
    Code:
      stack=6, locals=2, args_size=2
         0: aload_0
         1: invokevirtual #115                // Method history:()Largonaut/CursorHistory;
         4: aload_1
         5: invokedynamic #303,  0            // InvokeDynamic #10:apply:(Ljava/lang/String;)Lscala/Function1;
        10: aload_0
        11: invokevirtual #98                 // Method cursor:()Largonaut/Cursor;
        14: new           #305                // class argonaut/CursorOpField
        17: dup
        18: aload_1
        19: invokespecial #308                // Method argonaut/CursorOpField."<init>":(Ljava/lang/String;)V
        22: invokevirtual #184                // Method argonaut/CursorHistory.acursorElement:(Lscala/Function1;Largonaut/Cursor;Largonaut/CursorOpElement;)Largonaut/ACursor;
        25: areturn
      LineNumberTable:
        line 133: 0
      LocalVariableTable:
        Start  Length  Slot  Name   Signature
            0      26     0  this   Largonaut/HCursor;
            0      26     1     q   Ljava/lang/String;
    MethodParameters:
      Name                           Flags
      q                              final

  public argonaut.ACursor $minus$minus$bslash(java.lang.String);
    descriptor: (Ljava/lang/String;)Largonaut/ACursor;
    flags: (0x0001) ACC_PUBLIC
    Code:
      stack=2, locals=2, args_size=2
         0: aload_0
         1: aload_1
         2: invokevirtual #311                // Method downField:(Ljava/lang/String;)Largonaut/ACursor;
         5: areturn
      LineNumberTable:
        line 137: 0
      LocalVariableTable:
        Start  Length  Slot  Name   Signature
            0       6     0  this   Largonaut/HCursor;
            0       6     1     q   Ljava/lang/String;
    MethodParameters:
      Name                           Flags
      q                              final

  public argonaut.ACursor downField(java.lang.String);
    descriptor: (Ljava/lang/String;)Largonaut/ACursor;
    flags: (0x0001) ACC_PUBLIC
    Code:
      stack=6, locals=2, args_size=2
         0: aload_0
         1: invokevirtual #115                // Method history:()Largonaut/CursorHistory;
         4: aload_1
         5: invokedynamic #316,  0            // InvokeDynamic #11:apply:(Ljava/lang/String;)Lscala/Function1;
        10: aload_0
        11: invokevirtual #98                 // Method cursor:()Largonaut/Cursor;
        14: new           #318                // class argonaut/CursorOpDownField
        17: dup
        18: aload_1
        19: invokespecial #319                // Method argonaut/CursorOpDownField."<init>":(Ljava/lang/String;)V
        22: invokevirtual #184                // Method argonaut/CursorHistory.acursorElement:(Lscala/Function1;Largonaut/Cursor;Largonaut/CursorOpElement;)Largonaut/ACursor;
        25: areturn
      LineNumberTable:
        line 141: 0
      LocalVariableTable:
        Start  Length  Slot  Name   Signature
            0      26     0  this   Largonaut/HCursor;
            0      26     1     q   Ljava/lang/String;
    MethodParameters:
      Name                           Flags
      q                              final

  public argonaut.ACursor downArray();
    descriptor: ()Largonaut/ACursor;
    flags: (0x0001) ACC_PUBLIC
    Code:
      stack=4, locals=1, args_size=1
         0: aload_0
         1: invokevirtual #115                // Method history:()Largonaut/CursorHistory;
         4: invokedynamic #325,  0            // InvokeDynamic #12:apply:()Lscala/Function1;
         9: aload_0
        10: invokevirtual #98                 // Method cursor:()Largonaut/Cursor;
        13: getstatic     #330                // Field argonaut/CursorOpDownArray$.MODULE$:Largonaut/CursorOpDownArray$;
        16: invokevirtual #184                // Method argonaut/CursorHistory.acursorElement:(Lscala/Function1;Largonaut/Cursor;Largonaut/CursorOpElement;)Largonaut/ACursor;
        19: areturn
      LineNumberTable:
        line 145: 0
      LocalVariableTable:
        Start  Length  Slot  Name   Signature
            0      20     0  this   Largonaut/HCursor;

  public argonaut.ACursor $bslash$bslash();
    descriptor: ()Largonaut/ACursor;
    flags: (0x0001) ACC_PUBLIC
    Code:
      stack=1, locals=1, args_size=1
         0: aload_0
         1: invokevirtual #333                // Method downArray:()Largonaut/ACursor;
         4: areturn
      LineNumberTable:
        line 149: 0
      LocalVariableTable:
        Start  Length  Slot  Name   Signature
            0       5     0  this   Largonaut/HCursor;

  public argonaut.ACursor $minus$bslash(scala.Function1<argonaut.Json, java.lang.Object>);
    descriptor: (Lscala/Function1;)Largonaut/ACursor;
    flags: (0x0001) ACC_PUBLIC
    Code:
      stack=2, locals=2, args_size=2
         0: aload_0
         1: aload_1
         2: invokevirtual #337                // Method downAt:(Lscala/Function1;)Largonaut/ACursor;
         5: areturn
      LineNumberTable:
        line 153: 0
      LocalVariableTable:
        Start  Length  Slot  Name   Signature
            0       6     0  this   Largonaut/HCursor;
            0       6     1     p   Lscala/Function1;
    Signature: #252                         // (Lscala/Function1<Largonaut/Json;Ljava/lang/Object;>;)Largonaut/ACursor;
    MethodParameters:
      Name                           Flags
      p                              final

  public argonaut.ACursor downAt(scala.Function1<argonaut.Json, java.lang.Object>);
    descriptor: (Lscala/Function1;)Largonaut/ACursor;
    flags: (0x0001) ACC_PUBLIC
    Code:
      stack=6, locals=2, args_size=2
         0: aload_0
         1: invokevirtual #115                // Method history:()Largonaut/CursorHistory;
         4: aload_1
         5: invokedynamic #342,  0            // InvokeDynamic #13:apply:(Lscala/Function1;)Lscala/Function1;
        10: aload_0
        11: invokevirtual #98                 // Method cursor:()Largonaut/Cursor;
        14: new           #344                // class argonaut/CursorOpDownAt
        17: dup
        18: aload_1
        19: invokespecial #345                // Method argonaut/CursorOpDownAt."<init>":(Lscala/Function1;)V
        22: invokevirtual #184                // Method argonaut/CursorHistory.acursorElement:(Lscala/Function1;Largonaut/Cursor;Largonaut/CursorOpElement;)Largonaut/ACursor;
        25: areturn
      LineNumberTable:
        line 157: 0
      LocalVariableTable:
        Start  Length  Slot  Name   Signature
            0      26     0  this   Largonaut/HCursor;
            0      26     1     p   Lscala/Function1;
    Signature: #252                         // (Lscala/Function1<Largonaut/Json;Ljava/lang/Object;>;)Largonaut/ACursor;
    MethodParameters:
      Name                           Flags
      p                              final

  public argonaut.ACursor $eq$bslash(int);
    descriptor: (I)Largonaut/ACursor;
    flags: (0x0001) ACC_PUBLIC
    Code:
      stack=2, locals=2, args_size=2
         0: aload_0
         1: iload_1
         2: invokevirtual #349                // Method downN:(I)Largonaut/ACursor;
         5: areturn
      LineNumberTable:
        line 161: 0
      LocalVariableTable:
        Start  Length  Slot  Name   Signature
            0       6     0  this   Largonaut/HCursor;
            0       6     1     n   I
    MethodParameters:
      Name                           Flags
      n                              final

  public argonaut.ACursor downN(int);
    descriptor: (I)Largonaut/ACursor;
    flags: (0x0001) ACC_PUBLIC
    Code:
      stack=6, locals=2, args_size=2
         0: aload_0
         1: invokevirtual #115                // Method history:()Largonaut/CursorHistory;
         4: iload_1
         5: invokedynamic #354,  0            // InvokeDynamic #14:apply:(I)Lscala/Function1;
        10: aload_0
        11: invokevirtual #98                 // Method cursor:()Largonaut/Cursor;
        14: new           #356                // class argonaut/CursorOpDownN
        17: dup
        18: iload_1
        19: invokespecial #357                // Method argonaut/CursorOpDownN."<init>":(I)V
        22: invokevirtual #184                // Method argonaut/CursorHistory.acursorElement:(Lscala/Function1;Largonaut/Cursor;Largonaut/CursorOpElement;)Largonaut/ACursor;
        25: areturn
      LineNumberTable:
        line 165: 0
      LocalVariableTable:
        Start  Length  Slot  Name   Signature
            0      26     0  this   Largonaut/HCursor;
            0      26     1     n   I
    MethodParameters:
      Name                           Flags
      n                              final

  public argonaut.ACursor delete();
    descriptor: ()Largonaut/ACursor;
    flags: (0x0001) ACC_PUBLIC
    Code:
      stack=1, locals=1, args_size=1
         0: aload_0
         1: invokevirtual #361                // Method deleteGoParent:()Largonaut/ACursor;
         4: areturn
      LineNumberTable:
        line 169: 0
      LocalVariableTable:
        Start  Length  Slot  Name   Signature
            0       5     0  this   Largonaut/HCursor;

  public argonaut.ACursor unary_$bang();
    descriptor: ()Largonaut/ACursor;
    flags: (0x0001) ACC_PUBLIC
    Code:
      stack=1, locals=1, args_size=1
         0: aload_0
         1: invokevirtual #361                // Method deleteGoParent:()Largonaut/ACursor;
         4: areturn
      LineNumberTable:
        line 173: 0
      LocalVariableTable:
        Start  Length  Slot  Name   Signature
            0       5     0  this   Largonaut/HCursor;

  public argonaut.ACursor deleteGoParent();
    descriptor: ()Largonaut/ACursor;
    flags: (0x0001) ACC_PUBLIC
    Code:
      stack=4, locals=1, args_size=1
         0: aload_0
         1: invokevirtual #115                // Method history:()Largonaut/CursorHistory;
         4: invokedynamic #367,  0            // InvokeDynamic #15:apply:()Lscala/Function1;
         9: aload_0
        10: invokevirtual #98                 // Method cursor:()Largonaut/Cursor;
        13: getstatic     #372                // Field argonaut/CursorOpDeleteGoParent$.MODULE$:Largonaut/CursorOpDeleteGoParent$;
        16: invokevirtual #184                // Method argonaut/CursorHistory.acursorElement:(Lscala/Function1;Largonaut/Cursor;Largonaut/CursorOpElement;)Largonaut/ACursor;
        19: areturn
      LineNumberTable:
        line 177: 0
      LocalVariableTable:
        Start  Length  Slot  Name   Signature
            0      20     0  this   Largonaut/HCursor;

  public argonaut.ACursor deleteGoLeft();
    descriptor: ()Largonaut/ACursor;
    flags: (0x0001) ACC_PUBLIC
    Code:
      stack=4, locals=1, args_size=1
         0: aload_0
         1: invokevirtual #115                // Method history:()Largonaut/CursorHistory;
         4: invokedynamic #378,  0            // InvokeDynamic #16:apply:()Lscala/Function1;
         9: aload_0
        10: invokevirtual #98                 // Method cursor:()Largonaut/Cursor;
        13: getstatic     #383                // Field argonaut/CursorOpDeleteGoLeft$.MODULE$:Largonaut/CursorOpDeleteGoLeft$;
        16: invokevirtual #184                // Method argonaut/CursorHistory.acursorElement:(Lscala/Function1;Largonaut/Cursor;Largonaut/CursorOpElement;)Largonaut/ACursor;
        19: areturn
      LineNumberTable:
        line 181: 0
      LocalVariableTable:
        Start  Length  Slot  Name   Signature
            0      20     0  this   Largonaut/HCursor;

  public argonaut.ACursor deleteGoRight();
    descriptor: ()Largonaut/ACursor;
    flags: (0x0001) ACC_PUBLIC
    Code:
      stack=4, locals=1, args_size=1
         0: aload_0
         1: invokevirtual #115                // Method history:()Largonaut/CursorHistory;
         4: invokedynamic #389,  0            // InvokeDynamic #17:apply:()Lscala/Function1;
         9: aload_0
        10: invokevirtual #98                 // Method cursor:()Largonaut/Cursor;
        13: getstatic     #394                // Field argonaut/CursorOpDeleteGoRight$.MODULE$:Largonaut/CursorOpDeleteGoRight$;
        16: invokevirtual #184                // Method argonaut/CursorHistory.acursorElement:(Lscala/Function1;Largonaut/Cursor;Largonaut/CursorOpElement;)Largonaut/ACursor;
        19: areturn
      LineNumberTable:
        line 185: 0
      LocalVariableTable:
        Start  Length  Slot  Name   Signature
            0      20     0  this   Largonaut/HCursor;

  public argonaut.ACursor deleteGoFirst();
    descriptor: ()Largonaut/ACursor;
    flags: (0x0001) ACC_PUBLIC
    Code:
      stack=4, locals=1, args_size=1
         0: aload_0
         1: invokevirtual #115                // Method history:()Largonaut/CursorHistory;
         4: invokedynamic #400,  0            // InvokeDynamic #18:apply:()Lscala/Function1;
         9: aload_0
        10: invokevirtual #98                 // Method cursor:()Largonaut/Cursor;
        13: getstatic     #405                // Field argonaut/CursorOpDeleteGoFirst$.MODULE$:Largonaut/CursorOpDeleteGoFirst$;
        16: invokevirtual #184                // Method argonaut/CursorHistory.acursorElement:(Lscala/Function1;Largonaut/Cursor;Largonaut/CursorOpElement;)Largonaut/ACursor;
        19: areturn
      LineNumberTable:
        line 189: 0
      LocalVariableTable:
        Start  Length  Slot  Name   Signature
            0      20     0  this   Largonaut/HCursor;

  public argonaut.ACursor deleteGoLast();
    descriptor: ()Largonaut/ACursor;
    flags: (0x0001) ACC_PUBLIC
    Code:
      stack=4, locals=1, args_size=1
         0: aload_0
         1: invokevirtual #115                // Method history:()Largonaut/CursorHistory;
         4: invokedynamic #411,  0            // InvokeDynamic #19:apply:()Lscala/Function1;
         9: aload_0
        10: invokevirtual #98                 // Method cursor:()Largonaut/Cursor;
        13: getstatic     #416                // Field argonaut/CursorOpDeleteGoLast$.MODULE$:Largonaut/CursorOpDeleteGoLast$;
        16: invokevirtual #184                // Method argonaut/CursorHistory.acursorElement:(Lscala/Function1;Largonaut/Cursor;Largonaut/CursorOpElement;)Largonaut/ACursor;
        19: areturn
      LineNumberTable:
        line 193: 0
      LocalVariableTable:
        Start  Length  Slot  Name   Signature
            0      20     0  this   Largonaut/HCursor;

  public argonaut.ACursor deleteGoField(java.lang.String);
    descriptor: (Ljava/lang/String;)Largonaut/ACursor;
    flags: (0x0001) ACC_PUBLIC
    Code:
      stack=6, locals=2, args_size=2
         0: aload_0
         1: invokevirtual #115                // Method history:()Largonaut/CursorHistory;
         4: aload_1
         5: invokedynamic #422,  0            // InvokeDynamic #20:apply:(Ljava/lang/String;)Lscala/Function1;
        10: aload_0
        11: invokevirtual #98                 // Method cursor:()Largonaut/Cursor;
        14: new           #424                // class argonaut/CursorOpDeleteGoField
        17: dup
        18: aload_1
        19: invokespecial #425                // Method argonaut/CursorOpDeleteGoField."<init>":(Ljava/lang/String;)V
        22: invokevirtual #184                // Method argonaut/CursorHistory.acursorElement:(Lscala/Function1;Largonaut/Cursor;Largonaut/CursorOpElement;)Largonaut/ACursor;
        25: areturn
      LineNumberTable:
        line 197: 0
      LocalVariableTable:
        Start  Length  Slot  Name   Signature
            0      26     0  this   Largonaut/HCursor;
            0      26     1     q   Ljava/lang/String;
    MethodParameters:
      Name                           Flags
      q                              final

  public argonaut.ACursor deleteLefts();
    descriptor: ()Largonaut/ACursor;
    flags: (0x0001) ACC_PUBLIC
    Code:
      stack=4, locals=1, args_size=1
         0: aload_0
         1: invokevirtual #115                // Method history:()Largonaut/CursorHistory;
         4: invokedynamic #431,  0            // InvokeDynamic #21:apply:()Lscala/Function1;
         9: aload_0
        10: invokevirtual #98                 // Method cursor:()Largonaut/Cursor;
        13: getstatic     #436                // Field argonaut/CursorOpDeleteLefts$.MODULE$:Largonaut/CursorOpDeleteLefts$;
        16: invokevirtual #184                // Method argonaut/CursorHistory.acursorElement:(Lscala/Function1;Largonaut/Cursor;Largonaut/CursorOpElement;)Largonaut/ACursor;
        19: areturn
      LineNumberTable:
        line 201: 0
      LocalVariableTable:
        Start  Length  Slot  Name   Signature
            0      20     0  this   Largonaut/HCursor;

  public argonaut.ACursor deleteRights();
    descriptor: ()Largonaut/ACursor;
    flags: (0x0001) ACC_PUBLIC
    Code:
      stack=4, locals=1, args_size=1
         0: aload_0
         1: invokevirtual #115                // Method history:()Largonaut/CursorHistory;
         4: invokedynamic #442,  0            // InvokeDynamic #22:apply:()Lscala/Function1;
         9: aload_0
        10: invokevirtual #98                 // Method cursor:()Largonaut/Cursor;
        13: getstatic     #447                // Field argonaut/CursorOpDeleteRights$.MODULE$:Largonaut/CursorOpDeleteRights$;
        16: invokevirtual #184                // Method argonaut/CursorHistory.acursorElement:(Lscala/Function1;Largonaut/Cursor;Largonaut/CursorOpElement;)Largonaut/ACursor;
        19: areturn
      LineNumberTable:
        line 205: 0
      LocalVariableTable:
        Start  Length  Slot  Name   Signature
            0      20     0  this   Largonaut/HCursor;

  public argonaut.ACursor setLefts(scala.collection.immutable.List<argonaut.Json>);
    descriptor: (Lscala/collection/immutable/List;)Largonaut/ACursor;
    flags: (0x0001) ACC_PUBLIC
    Code:
      stack=6, locals=2, args_size=2
         0: aload_0
         1: invokevirtual #115                // Method history:()Largonaut/CursorHistory;
         4: aload_1
         5: invokedynamic #459,  0            // InvokeDynamic #23:apply:(Lscala/collection/immutable/List;)Lscala/Function1;
        10: aload_0
        11: invokevirtual #98                 // Method cursor:()Largonaut/Cursor;
        14: new           #461                // class argonaut/CursorOpSetLefts
        17: dup
        18: aload_1
        19: invokespecial #464                // Method argonaut/CursorOpSetLefts."<init>":(Lscala/collection/immutable/List;)V
        22: invokevirtual #184                // Method argonaut/CursorHistory.acursorElement:(Lscala/Function1;Largonaut/Cursor;Largonaut/CursorOpElement;)Largonaut/ACursor;
        25: areturn
      LineNumberTable:
        line 209: 0
      LocalVariableTable:
        Start  Length  Slot  Name   Signature
            0      26     0  this   Largonaut/HCursor;
            0      26     1     x   Lscala/collection/immutable/List;
    Signature: #450                         // (Lscala/collection/immutable/List<Largonaut/Json;>;)Largonaut/ACursor;
    MethodParameters:
      Name                           Flags
      x                              final

  public argonaut.ACursor setRights(scala.collection.immutable.List<argonaut.Json>);
    descriptor: (Lscala/collection/immutable/List;)Largonaut/ACursor;
    flags: (0x0001) ACC_PUBLIC
    Code:
      stack=6, locals=2, args_size=2
         0: aload_0
         1: invokevirtual #115                // Method history:()Largonaut/CursorHistory;
         4: aload_1
         5: invokedynamic #471,  0            // InvokeDynamic #24:apply:(Lscala/collection/immutable/List;)Lscala/Function1;
        10: aload_0
        11: invokevirtual #98                 // Method cursor:()Largonaut/Cursor;
        14: new           #473                // class argonaut/CursorOpSetRights
        17: dup
        18: aload_1
        19: invokespecial #474                // Method argonaut/CursorOpSetRights."<init>":(Lscala/collection/immutable/List;)V
        22: invokevirtual #184                // Method argonaut/CursorHistory.acursorElement:(Lscala/Function1;Largonaut/Cursor;Largonaut/CursorOpElement;)Largonaut/ACursor;
        25: areturn
      LineNumberTable:
        line 213: 0
      LocalVariableTable:
        Start  Length  Slot  Name   Signature
            0      26     0  this   Largonaut/HCursor;
            0      26     1     x   Lscala/collection/immutable/List;
    Signature: #450                         // (Lscala/collection/immutable/List<Largonaut/Json;>;)Largonaut/ACursor;
    MethodParameters:
      Name                           Flags
      x                              final

  public argonaut.ACursor up();
    descriptor: ()Largonaut/ACursor;
    flags: (0x0001) ACC_PUBLIC
    Code:
      stack=4, locals=1, args_size=1
         0: aload_0
         1: invokevirtual #115                // Method history:()Largonaut/CursorHistory;
         4: invokedynamic #480,  0            // InvokeDynamic #25:apply:()Lscala/Function1;
         9: aload_0
        10: invokevirtual #98                 // Method cursor:()Largonaut/Cursor;
        13: getstatic     #485                // Field argonaut/CursorOpUp$.MODULE$:Largonaut/CursorOpUp$;
        16: invokevirtual #184                // Method argonaut/CursorHistory.acursorElement:(Lscala/Function1;Largonaut/Cursor;Largonaut/CursorOpElement;)Largonaut/ACursor;
        19: areturn
      LineNumberTable:
        line 217: 0
      LocalVariableTable:
        Start  Length  Slot  Name   Signature
            0      20     0  this   Largonaut/HCursor;

  public argonaut.Json unary_$minus();
    descriptor: ()Largonaut/Json;
    flags: (0x0001) ACC_PUBLIC
    Code:
      stack=1, locals=1, args_size=1
         0: aload_0
         1: invokevirtual #98                 // Method cursor:()Largonaut/Cursor;
         4: invokevirtual #489                // Method argonaut/Cursor.undo:()Largonaut/Json;
         7: areturn
      LineNumberTable:
        line 221: 0
      LocalVariableTable:
        Start  Length  Slot  Name   Signature
            0       8     0  this   Largonaut/HCursor;

  public argonaut.Json undo();
    descriptor: ()Largonaut/Json;
    flags: (0x0001) ACC_PUBLIC
    Code:
      stack=1, locals=1, args_size=1
         0: aload_0
         1: invokevirtual #98                 // Method cursor:()Largonaut/Cursor;
         4: invokevirtual #489                // Method argonaut/Cursor.undo:()Largonaut/Json;
         7: areturn
      LineNumberTable:
        line 225: 0
      LocalVariableTable:
        Start  Length  Slot  Name   Signature
            0       8     0  this   Largonaut/HCursor;

  public argonaut.HCursor copy(argonaut.Cursor, argonaut.CursorHistory);
    descriptor: (Largonaut/Cursor;Largonaut/CursorHistory;)Largonaut/HCursor;
    flags: (0x0001) ACC_PUBLIC
    Code:
      stack=4, locals=3, args_size=3
         0: new           #2                  // class argonaut/HCursor
         3: dup
         4: aload_1
         5: aload_2
         6: invokespecial #119                // Method "<init>":(Largonaut/Cursor;Largonaut/CursorHistory;)V
         9: areturn
      LineNumberTable:
        line 3: 0
      LocalVariableTable:
        Start  Length  Slot  Name   Signature
            0      10     0  this   Largonaut/HCursor;
            0      10     1 cursor   Largonaut/Cursor;
            0      10     2 history   Largonaut/CursorHistory;
    MethodParameters:
      Name                           Flags
      cursor                         final
      history                        final

  public argonaut.Cursor copy$default$1();
    descriptor: ()Largonaut/Cursor;
    flags: (0x0001) ACC_PUBLIC
    Code:
      stack=1, locals=1, args_size=1
         0: aload_0
         1: invokevirtual #98                 // Method cursor:()Largonaut/Cursor;
         4: areturn
      LineNumberTable:
        line 3: 0
      LocalVariableTable:
        Start  Length  Slot  Name   Signature
            0       5     0  this   Largonaut/HCursor;

  public argonaut.CursorHistory copy$default$2();
    descriptor: ()Largonaut/CursorHistory;
    flags: (0x0001) ACC_PUBLIC
    Code:
      stack=1, locals=1, args_size=1
         0: aload_0
         1: invokevirtual #115                // Method history:()Largonaut/CursorHistory;
         4: areturn
      LineNumberTable:
        line 3: 0
      LocalVariableTable:
        Start  Length  Slot  Name   Signature
            0       5     0  this   Largonaut/HCursor;

  public java.lang.String productPrefix();
    descriptor: ()Ljava/lang/String;
    flags: (0x0001) ACC_PUBLIC
    Code:
      stack=1, locals=1, args_size=1
         0: ldc_w         #496                // String HCursor
         3: areturn
      LineNumberTable:
        line 3: 0
      LocalVariableTable:
        Start  Length  Slot  Name   Signature
            0       4     0  this   Largonaut/HCursor;

  public int productArity();
    descriptor: ()I
    flags: (0x0001) ACC_PUBLIC
    Code:
      stack=1, locals=1, args_size=1
         0: iconst_2
         1: ireturn
      LineNumberTable:
        line 3: 0
      LocalVariableTable:
        Start  Length  Slot  Name   Signature
            0       2     0  this   Largonaut/HCursor;

  public java.lang.Object productElement(int);
    descriptor: (I)Ljava/lang/Object;
    flags: (0x0001) ACC_PUBLIC
    Code:
      stack=1, locals=3, args_size=2
         0: iload_1
         1: istore_2
         2: iload_2
         3: tableswitch   { // 0 to 1
                       0: 24
                       1: 31
                 default: 38
            }
        24: aload_0
        25: invokevirtual #98                 // Method cursor:()Largonaut/Cursor;
        28: goto          45
        31: aload_0
        32: invokevirtual #115                // Method history:()Largonaut/CursorHistory;
        35: goto          45
        38: iload_1
        39: invokestatic  #506                // Method scala/runtime/Statics.ioobe:(I)Ljava/lang/Object;
        42: goto          45
        45: areturn
      StackMapTable: number_of_entries = 4
        frame_type = 252 /* append */
          offset_delta = 24
          locals = [ int ]
        frame_type = 6 /* same */
        frame_type = 6 /* same */
        frame_type = 70 /* same_locals_1_stack_item */
          stack = [ class java/lang/Object ]
      LineNumberTable:
        line 3: 0
      LocalVariableTable:
        Start  Length  Slot  Name   Signature
            0      46     0  this   Largonaut/HCursor;
            0      46     1   x$1   I
    MethodParameters:
      Name                           Flags
      x$1                            final

  public scala.collection.Iterator<java.lang.Object> productIterator();
    descriptor: ()Lscala/collection/Iterator;
    flags: (0x0001) ACC_PUBLIC
    Code:
      stack=2, locals=1, args_size=1
         0: getstatic     #513                // Field scala/runtime/ScalaRunTime$.MODULE$:Lscala/runtime/ScalaRunTime$;
         3: aload_0
         4: invokevirtual #516                // Method scala/runtime/ScalaRunTime$.typedProductIterator:(Lscala/Product;)Lscala/collection/Iterator;
         7: areturn
      LineNumberTable:
        line 3: 0
      LocalVariableTable:
        Start  Length  Slot  Name   Signature
            0       8     0  this   Largonaut/HCursor;
    Signature: #508                         // ()Lscala/collection/Iterator<Ljava/lang/Object;>;

  public boolean canEqual(java.lang.Object);
    descriptor: (Ljava/lang/Object;)Z
    flags: (0x0001) ACC_PUBLIC
    Code:
      stack=1, locals=2, args_size=2
         0: aload_1
         1: instanceof    #2                  // class argonaut/HCursor
         4: ireturn
      LineNumberTable:
        line 3: 0
      LocalVariableTable:
        Start  Length  Slot  Name   Signature
            0       5     0  this   Largonaut/HCursor;
            0       5     1   x$1   Ljava/lang/Object;
    MethodParameters:
      Name                           Flags
      x$1                            final

  public java.lang.String productElementName(int);
    descriptor: (I)Ljava/lang/String;
    flags: (0x0001) ACC_PUBLIC
    Code:
      stack=1, locals=3, args_size=2
         0: iload_1
         1: istore_2
         2: iload_2
         3: tableswitch   { // 0 to 1
                       0: 24
                       1: 30
                 default: 36
            }
        24: ldc_w         #522                // String cursor
        27: goto          46
        30: ldc_w         #523                // String history
        33: goto          46
        36: iload_1
        37: invokestatic  #506                // Method scala/runtime/Statics.ioobe:(I)Ljava/lang/Object;
        40: checkcast     #525                // class java/lang/String
        43: goto          46
        46: areturn
      StackMapTable: number_of_entries = 4
        frame_type = 252 /* append */
          offset_delta = 24
          locals = [ int ]
        frame_type = 5 /* same */
        frame_type = 5 /* same */
        frame_type = 73 /* same_locals_1_stack_item */
          stack = [ class java/lang/String ]
      LineNumberTable:
        line 3: 0
      LocalVariableTable:
        Start  Length  Slot  Name   Signature
            0      47     0  this   Largonaut/HCursor;
            0      47     1   x$1   I
    MethodParameters:
      Name                           Flags
      x$1                            final

  public int hashCode();
    descriptor: ()I
    flags: (0x0001) ACC_PUBLIC
    Code:
      stack=2, locals=1, args_size=1
         0: getstatic     #513                // Field scala/runtime/ScalaRunTime$.MODULE$:Lscala/runtime/ScalaRunTime$;
         3: aload_0
         4: invokevirtual #530                // Method scala/runtime/ScalaRunTime$._hashCode:(Lscala/Product;)I
         7: ireturn
      LineNumberTable:
        line 3: 0
      LocalVariableTable:
        Start  Length  Slot  Name   Signature
            0       8     0  this   Largonaut/HCursor;

  public java.lang.String toString();
    descriptor: ()Ljava/lang/String;
    flags: (0x0001) ACC_PUBLIC
    Code:
      stack=2, locals=1, args_size=1
         0: getstatic     #513                // Field scala/runtime/ScalaRunTime$.MODULE$:Lscala/runtime/ScalaRunTime$;
         3: aload_0
         4: invokevirtual #535                // Method scala/runtime/ScalaRunTime$._toString:(Lscala/Product;)Ljava/lang/String;
         7: areturn
      LineNumberTable:
        line 3: 0
      LocalVariableTable:
        Start  Length  Slot  Name   Signature
            0       8     0  this   Largonaut/HCursor;

  public boolean equals(java.lang.Object);
    descriptor: (Ljava/lang/Object;)Z
    flags: (0x0001) ACC_PUBLIC
    Code:
      stack=2, locals=7, args_size=2
         0: aload_0
         1: aload_1
         2: if_acmpeq     118
         5: aload_1
         6: astore_3
         7: aload_3
         8: instanceof    #2                  // class argonaut/HCursor
        11: ifeq          19
        14: iconst_1
        15: istore_2
        16: goto          27
        19: goto          22
        22: iconst_0
        23: istore_2
        24: goto          27
        27: iload_2
        28: ifeq          122
        31: aload_1
        32: checkcast     #2                  // class argonaut/HCursor
        35: astore        4
        37: aload_0
        38: invokevirtual #98                 // Method cursor:()Largonaut/Cursor;
        41: aload         4
        43: invokevirtual #98                 // Method cursor:()Largonaut/Cursor;
        46: astore        5
        48: dup
        49: ifnonnull     61
        52: pop
        53: aload         5
        55: ifnull        69
        58: goto          114
        61: aload         5
        63: invokevirtual #538                // Method java/lang/Object.equals:(Ljava/lang/Object;)Z
        66: ifeq          114
        69: aload_0
        70: invokevirtual #115                // Method history:()Largonaut/CursorHistory;
        73: aload         4
        75: invokevirtual #115                // Method history:()Largonaut/CursorHistory;
        78: astore        6
        80: dup
        81: ifnonnull     93
        84: pop
        85: aload         6
        87: ifnull        101
        90: goto          114
        93: aload         6
        95: invokevirtual #538                // Method java/lang/Object.equals:(Ljava/lang/Object;)Z
        98: ifeq          114
       101: aload         4
       103: aload_0
       104: invokevirtual #540                // Method canEqual:(Ljava/lang/Object;)Z
       107: ifeq          114
       110: iconst_1
       111: goto          115
       114: iconst_0
       115: ifeq          122
       118: iconst_1
       119: goto          123
       122: iconst_0
       123: ireturn
      StackMapTable: number_of_entries = 12
        frame_type = 253 /* append */
          offset_delta = 19
          locals = [ top, class java/lang/Object ]
        frame_type = 2 /* same */
        frame_type = 255 /* full_frame */
          offset_delta = 4
          locals = [ class argonaut/HCursor, class java/lang/Object, int, class java/lang/Object ]
          stack = []
        frame_type = 255 /* full_frame */
          offset_delta = 33
          locals = [ class argonaut/HCursor, class java/lang/Object, int, class java/lang/Object, class argonaut/HCursor, class argonaut/Cursor ]
          stack = [ class argonaut/Cursor ]
        frame_type = 7 /* same */
        frame_type = 255 /* full_frame */
          offset_delta = 23
          locals = [ class argonaut/HCursor, class java/lang/Object, int, class java/lang/Object, class argonaut/HCursor, class argonaut/Cursor, class argonaut/CursorHistory ]
          stack = [ class argonaut/CursorHistory ]
        frame_type = 7 /* same */
        frame_type = 250 /* chop */
          offset_delta = 12
        frame_type = 64 /* same_locals_1_stack_item */
          stack = [ int ]
        frame_type = 255 /* full_frame */
          offset_delta = 2
          locals = [ class argonaut/HCursor, class java/lang/Object ]
          stack = []
        frame_type = 253 /* append */
          offset_delta = 3
          locals = [ int, class java/lang/Object ]
        frame_type = 255 /* full_frame */
          offset_delta = 0
          locals = [ class argonaut/HCursor, class java/lang/Object ]
          stack = [ int ]
      LineNumberTable:
        line 3: 0
      LocalVariableTable:
        Start  Length  Slot  Name   Signature
            0     124     0  this   Largonaut/HCursor;
            0     124     1   x$1   Ljava/lang/Object;
    MethodParameters:
      Name                           Flags
      x$1                            final

  public static final argonaut.Json $anonfun$set$1(argonaut.Json, argonaut.Json);
    descriptor: (Largonaut/Json;Largonaut/Json;)Largonaut/Json;
    flags: (0x1019) ACC_PUBLIC, ACC_STATIC, ACC_FINAL, ACC_SYNTHETIC
    Code:
      stack=1, locals=2, args_size=2
         0: aload_0
         1: areturn
      LineNumberTable:
        line 45: 0
      LocalVariableTable:
        Start  Length  Slot  Name   Signature
            0       2     0   j$1   Largonaut/Json;
            0       2     1   x$1   Largonaut/Json;
    MethodParameters:
      Name                           Flags
      j$1                            final
      x$1                            final

  public static final scala.Option $anonfun$left$1(argonaut.Cursor);
    descriptor: (Largonaut/Cursor;)Lscala/Option;
    flags: (0x1019) ACC_PUBLIC, ACC_STATIC, ACC_FINAL, ACC_SYNTHETIC
    Code:
      stack=1, locals=1, args_size=1
         0: aload_0
         1: invokevirtual #544                // Method argonaut/Cursor.left:()Lscala/Option;
         4: areturn
      LineNumberTable:
        line 77: 0
      LocalVariableTable:
        Start  Length  Slot  Name   Signature
            0       5     0   x$2   Largonaut/Cursor;
    MethodParameters:
      Name                           Flags
      x$2                            final

  public static final scala.Option $anonfun$right$1(argonaut.Cursor);
    descriptor: (Largonaut/Cursor;)Lscala/Option;
    flags: (0x1019) ACC_PUBLIC, ACC_STATIC, ACC_FINAL, ACC_SYNTHETIC
    Code:
      stack=1, locals=1, args_size=1
         0: aload_0
         1: invokevirtual #547                // Method argonaut/Cursor.right:()Lscala/Option;
         4: areturn
      LineNumberTable:
        line 81: 0
      LocalVariableTable:
        Start  Length  Slot  Name   Signature
            0       5     0   x$3   Largonaut/Cursor;
    MethodParameters:
      Name                           Flags
      x$3                            final

  public static final scala.Option $anonfun$first$1(argonaut.Cursor);
    descriptor: (Largonaut/Cursor;)Lscala/Option;
    flags: (0x1019) ACC_PUBLIC, ACC_STATIC, ACC_FINAL, ACC_SYNTHETIC
    Code:
      stack=1, locals=1, args_size=1
         0: aload_0
         1: invokevirtual #550                // Method argonaut/Cursor.first:()Lscala/Option;
         4: areturn
      LineNumberTable:
        line 85: 0
      LocalVariableTable:
        Start  Length  Slot  Name   Signature
            0       5     0   x$4   Largonaut/Cursor;
    MethodParameters:
      Name                           Flags
      x$4                            final

  public static final scala.Option $anonfun$last$1(argonaut.Cursor);
    descriptor: (Largonaut/Cursor;)Lscala/Option;
    flags: (0x1019) ACC_PUBLIC, ACC_STATIC, ACC_FINAL, ACC_SYNTHETIC
    Code:
      stack=1, locals=1, args_size=1
         0: aload_0
         1: invokevirtual #553                // Method argonaut/Cursor.last:()Lscala/Option;
         4: areturn
      LineNumberTable:
        line 89: 0
      LocalVariableTable:
        Start  Length  Slot  Name   Signature
            0       5     0   x$5   Largonaut/Cursor;
    MethodParameters:
      Name                           Flags
      x$5                            final

  public static final scala.Option $anonfun$leftN$1(int, argonaut.Cursor);
    descriptor: (ILargonaut/Cursor;)Lscala/Option;
    flags: (0x1019) ACC_PUBLIC, ACC_STATIC, ACC_FINAL, ACC_SYNTHETIC
    Code:
      stack=2, locals=2, args_size=2
         0: aload_1
         1: iload_0
         2: invokevirtual #558                // Method argonaut/Cursor.leftN:(I)Lscala/Option;
         5: areturn
      LineNumberTable:
        line 97: 0
      LocalVariableTable:
        Start  Length  Slot  Name   Signature
            0       6     0   n$1   I
            0       6     1   x$6   Largonaut/Cursor;
    MethodParameters:
      Name                           Flags
      n$1                            final
      x$6                            final

  public static final scala.Option $anonfun$rightN$1(int, argonaut.Cursor);
    descriptor: (ILargonaut/Cursor;)Lscala/Option;
    flags: (0x1019) ACC_PUBLIC, ACC_STATIC, ACC_FINAL, ACC_SYNTHETIC
    Code:
      stack=2, locals=2, args_size=2
         0: aload_1
         1: iload_0
         2: invokevirtual #562                // Method argonaut/Cursor.rightN:(I)Lscala/Option;
         5: areturn
      LineNumberTable:
        line 105: 0
      LocalVariableTable:
        Start  Length  Slot  Name   Signature
            0       6     0   n$2   I
            0       6     1   x$7   Largonaut/Cursor;
    MethodParameters:
      Name                           Flags
      n$2                            final
      x$7                            final

  public static final scala.Option $anonfun$leftAt$1(scala.Function1, argonaut.Cursor);
    descriptor: (Lscala/Function1;Largonaut/Cursor;)Lscala/Option;
    flags: (0x1019) ACC_PUBLIC, ACC_STATIC, ACC_FINAL, ACC_SYNTHETIC
    Code:
      stack=2, locals=2, args_size=2
         0: aload_1
         1: aload_0
         2: invokevirtual #567                // Method argonaut/Cursor.leftAt:(Lscala/Function1;)Lscala/Option;
         5: areturn
      LineNumberTable:
        line 113: 0
      LocalVariableTable:
        Start  Length  Slot  Name   Signature
            0       6     0   p$1   Lscala/Function1;
            0       6     1   x$8   Largonaut/Cursor;
    MethodParameters:
      Name                           Flags
      p$1                            final
      x$8                            final

  public static final scala.Option $anonfun$rightAt$1(scala.Function1, argonaut.Cursor);
    descriptor: (Lscala/Function1;Largonaut/Cursor;)Lscala/Option;
    flags: (0x1019) ACC_PUBLIC, ACC_STATIC, ACC_FINAL, ACC_SYNTHETIC
    Code:
      stack=2, locals=2, args_size=2
         0: aload_1
         1: aload_0
         2: invokevirtual #571                // Method argonaut/Cursor.rightAt:(Lscala/Function1;)Lscala/Option;
         5: areturn
      LineNumberTable:
        line 121: 0
      LocalVariableTable:
        Start  Length  Slot  Name   Signature
            0       6     0   p$2   Lscala/Function1;
            0       6     1   x$9   Largonaut/Cursor;
    MethodParameters:
      Name                           Flags
      p$2                            final
      x$9                            final

  public static final scala.Option $anonfun$find$1(scala.Function1, argonaut.Cursor);
    descriptor: (Lscala/Function1;Largonaut/Cursor;)Lscala/Option;
    flags: (0x1019) ACC_PUBLIC, ACC_STATIC, ACC_FINAL, ACC_SYNTHETIC
    Code:
      stack=2, locals=2, args_size=2
         0: aload_1
         1: aload_0
         2: invokevirtual #575                // Method argonaut/Cursor.find:(Lscala/Function1;)Lscala/Option;
         5: areturn
      LineNumberTable:
        line 125: 0
      LocalVariableTable:
        Start  Length  Slot  Name   Signature
            0       6     0   p$3   Lscala/Function1;
            0       6     1  x$10   Largonaut/Cursor;
    MethodParameters:
      Name                           Flags
      p$3                            final
      x$10                           final

  public static final scala.Option $anonfun$field$1(java.lang.String, argonaut.Cursor);
    descriptor: (Ljava/lang/String;Largonaut/Cursor;)Lscala/Option;
    flags: (0x1019) ACC_PUBLIC, ACC_STATIC, ACC_FINAL, ACC_SYNTHETIC
    Code:
      stack=2, locals=2, args_size=2
         0: aload_1
         1: aload_0
         2: invokevirtual #580                // Method argonaut/Cursor.field:(Ljava/lang/String;)Lscala/Option;
         5: areturn
      LineNumberTable:
        line 133: 0
      LocalVariableTable:
        Start  Length  Slot  Name   Signature
            0       6     0   q$1   Ljava/lang/String;
            0       6     1  x$11   Largonaut/Cursor;
    MethodParameters:
      Name                           Flags
      q$1                            final
      x$11                           final

  public static final scala.Option $anonfun$downField$1(java.lang.String, argonaut.Cursor);
    descriptor: (Ljava/lang/String;Largonaut/Cursor;)Lscala/Option;
    flags: (0x1019) ACC_PUBLIC, ACC_STATIC, ACC_FINAL, ACC_SYNTHETIC
    Code:
      stack=2, locals=2, args_size=2
         0: aload_1
         1: aload_0
         2: invokevirtual #584                // Method argonaut/Cursor.downField:(Ljava/lang/String;)Lscala/Option;
         5: areturn
      LineNumberTable:
        line 141: 0
      LocalVariableTable:
        Start  Length  Slot  Name   Signature
            0       6     0   q$2   Ljava/lang/String;
            0       6     1  x$12   Largonaut/Cursor;
    MethodParameters:
      Name                           Flags
      q$2                            final
      x$12                           final

  public static final scala.Option $anonfun$downArray$1(argonaut.Cursor);
    descriptor: (Largonaut/Cursor;)Lscala/Option;
    flags: (0x1019) ACC_PUBLIC, ACC_STATIC, ACC_FINAL, ACC_SYNTHETIC
    Code:
      stack=1, locals=1, args_size=1
         0: aload_0
         1: invokevirtual #587                // Method argonaut/Cursor.downArray:()Lscala/Option;
         4: areturn
      LineNumberTable:
        line 145: 0
      LocalVariableTable:
        Start  Length  Slot  Name   Signature
            0       5     0  x$13   Largonaut/Cursor;
    MethodParameters:
      Name                           Flags
      x$13                           final

  public static final scala.Option $anonfun$downAt$1(scala.Function1, argonaut.Cursor);
    descriptor: (Lscala/Function1;Largonaut/Cursor;)Lscala/Option;
    flags: (0x1019) ACC_PUBLIC, ACC_STATIC, ACC_FINAL, ACC_SYNTHETIC
    Code:
      stack=2, locals=2, args_size=2
         0: aload_1
         1: aload_0
         2: invokevirtual #591                // Method argonaut/Cursor.downAt:(Lscala/Function1;)Lscala/Option;
         5: areturn
      LineNumberTable:
        line 157: 0
      LocalVariableTable:
        Start  Length  Slot  Name   Signature
            0       6     0   p$4   Lscala/Function1;
            0       6     1  x$14   Largonaut/Cursor;
    MethodParameters:
      Name                           Flags
      p$4                            final
      x$14                           final

  public static final scala.Option $anonfun$downN$1(int, argonaut.Cursor);
    descriptor: (ILargonaut/Cursor;)Lscala/Option;
    flags: (0x1019) ACC_PUBLIC, ACC_STATIC, ACC_FINAL, ACC_SYNTHETIC
    Code:
      stack=2, locals=2, args_size=2
         0: aload_1
         1: iload_0
         2: invokevirtual #595                // Method argonaut/Cursor.downN:(I)Lscala/Option;
         5: areturn
      LineNumberTable:
        line 165: 0
      LocalVariableTable:
        Start  Length  Slot  Name   Signature
            0       6     0   n$3   I
            0       6     1  x$15   Largonaut/Cursor;
    MethodParameters:
      Name                           Flags
      n$3                            final
      x$15                           final

  public static final scala.Option $anonfun$deleteGoParent$1(argonaut.Cursor);
    descriptor: (Largonaut/Cursor;)Lscala/Option;
    flags: (0x1019) ACC_PUBLIC, ACC_STATIC, ACC_FINAL, ACC_SYNTHETIC
    Code:
      stack=1, locals=1, args_size=1
         0: aload_0
         1: invokevirtual #598                // Method argonaut/Cursor.deleteGoParent:()Lscala/Option;
         4: areturn
      LineNumberTable:
        line 177: 0
      LocalVariableTable:
        Start  Length  Slot  Name   Signature
            0       5     0  x$16   Largonaut/Cursor;
    MethodParameters:
      Name                           Flags
      x$16                           final

  public static final scala.Option $anonfun$deleteGoLeft$1(argonaut.Cursor);
    descriptor: (Largonaut/Cursor;)Lscala/Option;
    flags: (0x1019) ACC_PUBLIC, ACC_STATIC, ACC_FINAL, ACC_SYNTHETIC
    Code:
      stack=1, locals=1, args_size=1
         0: aload_0
         1: invokevirtual #601                // Method argonaut/Cursor.deleteGoLeft:()Lscala/Option;
         4: areturn
      LineNumberTable:
        line 181: 0
      LocalVariableTable:
        Start  Length  Slot  Name   Signature
            0       5     0  x$17   Largonaut/Cursor;
    MethodParameters:
      Name                           Flags
      x$17                           final

  public static final scala.Option $anonfun$deleteGoRight$1(argonaut.Cursor);
    descriptor: (Largonaut/Cursor;)Lscala/Option;
    flags: (0x1019) ACC_PUBLIC, ACC_STATIC, ACC_FINAL, ACC_SYNTHETIC
    Code:
      stack=1, locals=1, args_size=1
         0: aload_0
         1: invokevirtual #604                // Method argonaut/Cursor.deleteGoRight:()Lscala/Option;
         4: areturn
      LineNumberTable:
        line 185: 0
      LocalVariableTable:
        Start  Length  Slot  Name   Signature
            0       5     0  x$18   Largonaut/Cursor;
    MethodParameters:
      Name                           Flags
      x$18                           final

  public static final scala.Option $anonfun$deleteGoFirst$1(argonaut.Cursor);
    descriptor: (Largonaut/Cursor;)Lscala/Option;
    flags: (0x1019) ACC_PUBLIC, ACC_STATIC, ACC_FINAL, ACC_SYNTHETIC
    Code:
      stack=1, locals=1, args_size=1
         0: aload_0
         1: invokevirtual #607                // Method argonaut/Cursor.deleteGoFirst:()Lscala/Option;
         4: areturn
      LineNumberTable:
        line 189: 0
      LocalVariableTable:
        Start  Length  Slot  Name   Signature
            0       5     0  x$19   Largonaut/Cursor;
    MethodParameters:
      Name                           Flags
      x$19                           final

  public static final scala.Option $anonfun$deleteGoLast$1(argonaut.Cursor);
    descriptor: (Largonaut/Cursor;)Lscala/Option;
    flags: (0x1019) ACC_PUBLIC, ACC_STATIC, ACC_FINAL, ACC_SYNTHETIC
    Code:
      stack=1, locals=1, args_size=1
         0: aload_0
         1: invokevirtual #610                // Method argonaut/Cursor.deleteGoLast:()Lscala/Option;
         4: areturn
      LineNumberTable:
        line 193: 0
      LocalVariableTable:
        Start  Length  Slot  Name   Signature
            0       5     0  x$20   Largonaut/Cursor;
    MethodParameters:
      Name                           Flags
      x$20                           final

  public static final scala.Option $anonfun$deleteGoField$1(java.lang.String, argonaut.Cursor);
    descriptor: (Ljava/lang/String;Largonaut/Cursor;)Lscala/Option;
    flags: (0x1019) ACC_PUBLIC, ACC_STATIC, ACC_FINAL, ACC_SYNTHETIC
    Code:
      stack=2, locals=2, args_size=2
         0: aload_1
         1: aload_0
         2: invokevirtual #614                // Method argonaut/Cursor.deleteGoField:(Ljava/lang/String;)Lscala/Option;
         5: areturn
      LineNumberTable:
        line 197: 0
      LocalVariableTable:
        Start  Length  Slot  Name   Signature
            0       6     0   q$3   Ljava/lang/String;
            0       6     1  x$21   Largonaut/Cursor;
    MethodParameters:
      Name                           Flags
      q$3                            final
      x$21                           final

  public static final scala.Option $anonfun$deleteLefts$1(argonaut.Cursor);
    descriptor: (Largonaut/Cursor;)Lscala/Option;
    flags: (0x1019) ACC_PUBLIC, ACC_STATIC, ACC_FINAL, ACC_SYNTHETIC
    Code:
      stack=1, locals=1, args_size=1
         0: aload_0
         1: invokevirtual #617                // Method argonaut/Cursor.deleteLefts:()Lscala/Option;
         4: areturn
      LineNumberTable:
        line 201: 0
      LocalVariableTable:
        Start  Length  Slot  Name   Signature
            0       5     0  x$22   Largonaut/Cursor;
    MethodParameters:
      Name                           Flags
      x$22                           final

  public static final scala.Option $anonfun$deleteRights$1(argonaut.Cursor);
    descriptor: (Largonaut/Cursor;)Lscala/Option;
    flags: (0x1019) ACC_PUBLIC, ACC_STATIC, ACC_FINAL, ACC_SYNTHETIC
    Code:
      stack=1, locals=1, args_size=1
         0: aload_0
         1: invokevirtual #620                // Method argonaut/Cursor.deleteRights:()Lscala/Option;
         4: areturn
      LineNumberTable:
        line 205: 0
      LocalVariableTable:
        Start  Length  Slot  Name   Signature
            0       5     0  x$23   Largonaut/Cursor;
    MethodParameters:
      Name                           Flags
      x$23                           final

  public static final scala.Option $anonfun$setLefts$1(scala.collection.immutable.List, argonaut.Cursor);
    descriptor: (Lscala/collection/immutable/List;Largonaut/Cursor;)Lscala/Option;
    flags: (0x1019) ACC_PUBLIC, ACC_STATIC, ACC_FINAL, ACC_SYNTHETIC
    Code:
      stack=2, locals=2, args_size=2
         0: aload_1
         1: aload_0
         2: invokevirtual #625                // Method argonaut/Cursor.setLefts:(Lscala/collection/immutable/List;)Lscala/Option;
         5: areturn
      LineNumberTable:
        line 209: 0
      LocalVariableTable:
        Start  Length  Slot  Name   Signature
            0       6     0  x$27   Lscala/collection/immutable/List;
            0       6     1  x$24   Largonaut/Cursor;
    MethodParameters:
      Name                           Flags
      x$27                           final
      x$24                           final

  public static final scala.Option $anonfun$setRights$1(scala.collection.immutable.List, argonaut.Cursor);
    descriptor: (Lscala/collection/immutable/List;Largonaut/Cursor;)Lscala/Option;
    flags: (0x1019) ACC_PUBLIC, ACC_STATIC, ACC_FINAL, ACC_SYNTHETIC
    Code:
      stack=2, locals=2, args_size=2
         0: aload_1
         1: aload_0
         2: invokevirtual #629                // Method argonaut/Cursor.setRights:(Lscala/collection/immutable/List;)Lscala/Option;
         5: areturn
      LineNumberTable:
        line 213: 0
      LocalVariableTable:
        Start  Length  Slot  Name   Signature
            0       6     0  x$28   Lscala/collection/immutable/List;
            0       6     1  x$25   Largonaut/Cursor;
    MethodParameters:
      Name                           Flags
      x$28                           final
      x$25                           final

  public static final scala.Option $anonfun$up$1(argonaut.Cursor);
    descriptor: (Largonaut/Cursor;)Lscala/Option;
    flags: (0x1019) ACC_PUBLIC, ACC_STATIC, ACC_FINAL, ACC_SYNTHETIC
    Code:
      stack=1, locals=1, args_size=1
         0: aload_0
         1: invokevirtual #632                // Method argonaut/Cursor.up:()Lscala/Option;
         4: areturn
      LineNumberTable:
        line 217: 0
      LocalVariableTable:
        Start  Length  Slot  Name   Signature
            0       5     0  x$26   Largonaut/Cursor;
    MethodParameters:
      Name                           Flags
      x$26                           final

  public argonaut.HCursor(argonaut.Cursor, argonaut.CursorHistory);
    descriptor: (Largonaut/Cursor;Largonaut/CursorHistory;)V
    flags: (0x0001) ACC_PUBLIC
    Code:
      stack=2, locals=3, args_size=3
         0: aload_0
         1: aload_1
         2: putfield      #49                 // Field cursor:Largonaut/Cursor;
         5: aload_0
         6: aload_2
         7: putfield      #52                 // Field history:Largonaut/CursorHistory;
        10: aload_0
        11: invokespecial #635                // Method java/lang/Object."<init>":()V
        14: aload_0
        15: invokestatic  #639                // InterfaceMethod scala/Product.$init$:(Lscala/Product;)V
        18: return
      LineNumberTable:
        line 3: 0
      LocalVariableTable:
        Start  Length  Slot  Name   Signature
            0      19     0  this   Largonaut/HCursor;
            0      19     1 cursor   Largonaut/Cursor;
            0      19     2 history   Largonaut/CursorHistory;
    MethodParameters:
      Name                           Flags
      cursor                         final
      history                        final

  private static java.lang.Object $deserializeLambda$(java.lang.invoke.SerializedLambda);
    descriptor: (Ljava/lang/invoke/SerializedLambda;)Ljava/lang/Object;
    flags: (0x100a) ACC_PRIVATE, ACC_STATIC, ACC_SYNTHETIC
    Code:
      stack=1, locals=1, args_size=1
         0: aload_0
         1: invokedynamic #651,  0            // InvokeDynamic #26:lambdaDeserialize:(Ljava/lang/invoke/SerializedLambda;)Ljava/lang/Object;
         6: areturn
}
InnerClasses:
  public static final #17= #14 of #16;    // Lookup=class java/lang/invoke/MethodHandles$Lookup of class java/lang/invoke/MethodHandles
SourceFile: "HCursor.scala"
RuntimeVisibleAnnotations:
  0: #10(#11=s#12)
    scala.reflect.ScalaSignature(
      bytes="\u0006\u0005\r\u0005b\u0001\u0002\'N\u0001BC\u0001B\u001a\u0001\u0003\u0016\u0004%\ta\u001a\u0005\tY\u0002\u0011\t\u0012)A\u0005Q\"AQ\u000e\u0001BK\u0002\u0013\u0005a\u000e\u0003\u0005s\u0001\tE\t\u0015!\u0003p\u0011\u0015\u0019\b\u0001\"\u0001u\u0011\u0015A\b\u0001\"\u0001z\u0011\u0015i\b\u0001\"\u0001\u007f\u0011\u001d\t9\u0003\u0001C\u0001\u0003SAq!a\u000e\u0001\t\u0003\tI\u0004\u0003\u0004\u0002^\u0001!\t!\u001f\u0005\b\u0003?\u0002A\u0011AA1\u0011\u001d\tI\u0007\u0001C\u0001\u0003WBq!a\u001e\u0001\t\u0003\tI\bC\u0004\u0002~\u0001!\t!a \t\u000f\u0005\u0015\u0005\u0001\"\u0001\u0002\b\"9\u00111\u0012\u0001\u0005\u0002\u00055\u0005bBAS\u0001\u0011\u0005\u0011Q\u0012\u0005\b\u0003O\u0003A\u0011AAU\u0011\u001d\tI\f\u0001C\u0001\u0003wCa!!2\u0001\t\u0003I\bBBAd\u0001\u0011\u0005\u0011\u0010\u0003\u0004\u0002J\u0002!\t!\u001f\u0005\u0007\u0003\u0017\u0004A\u0011A=\t\u000f\u00055\u0007\u0001\"\u0001\u0002P\"9\u00111\u001c\u0001\u0005\u0002\u0005u\u0007bBAq\u0001\u0011\u0005\u00111\u001d\u0005\b\u0003O\u0004A\u0011AAu\u0011\u001d\ti\u000f\u0001C\u0001\u0003_Dq!!@\u0001\t\u0003\ty\u0010C\u0004\u0003\u0004\u0001!\tA!\u0002\t\u000f\t%\u0001\u0001\"\u0001\u0003\f!9!q\u0002\u0001\u0005\u0002\tE\u0001b\u0002B\u000b\u0001\u0011\u0005!q\u0003\u0005\b\u0005;\u0001A\u0011\u0001B\u0010\u0011\u001d\u0011\u0019\u0003\u0001C\u0001\u0005KAqA!\u000b\u0001\t\u0003\u0011Y\u0003\u0003\u0004\u00030\u0001!\t!\u001f\u0005\u0007\u0005c\u0001A\u0011A=\t\u000f\tM\u0002\u0001\"\u0001\u00036!9!\u0011\b\u0001\u0005\u0002\tm\u0002b\u0002B \u0001\u0011\u0005!\u0011\t\u0005\b\u0005\u000b\u0002A\u0011\u0001B$\u0011\u0019\u0011Y\u0005\u0001C\u0001s\"1!Q\n\u0001\u0005\u0002eDaAa\u0014\u0001\t\u0003I\bB\u0002B)\u0001\u0011\u0005\u0011\u0010\u0003\u0004\u0003T\u0001!\t!\u001f\u0005\u0007\u0005+\u0002A\u0011A=\t\r\t]\u0003\u0001\"\u0001z\u0011\u001d\u0011I\u0006\u0001C\u0001\u00057BaAa\u0018\u0001\t\u0003I\bB\u0002B1\u0001\u0011\u0005\u0011\u0010C\u0004\u0003d\u0001!\tA!\u001a\t\u000f\t5\u0004\u0001\"\u0001\u0003p!1!1\u000f\u0001\u0005\u0002eDqA!\u001e\u0001\t\u0003\t\t\u0007C\u0004\u0003x\u0001!\t!!\u0019\t\u0013\te\u0004!!A\u0005\u0002\tm\u0004\"\u0003BA\u0001E\u0005I\u0011\u0001BB\u0011%\u0011I\nAI\u0001\n\u0003\u0011Y\nC\u0005\u0003 \u0002\t\t\u0011\"\u0011\u0003\"\"I!\u0011\u0017\u0001\u0002\u0002\u0013\u0005!1\u0017\u0005\n\u0005k\u0003\u0011\u0011!C\u0001\u0005oC\u0011B!0\u0001\u0003\u0003%\tEa0\t\u0013\t5\u0007!!A\u0005\u0002\t=\u0007\"\u0003Bj\u0001\u0005\u0005I\u0011\tBk\u0011%\u0011I\u000eAA\u0001\n\u0003\u0012Y\u000eC\u0005\u0003^\u0002\t\t\u0011\"\u0011\u0003`\"I!\u0011\u001d\u0001\u0002\u0002\u0013\u0005#1]\u0004\b\u0005Ol\u0005\u0012\u0001Bu\r\u0019aU\n#\u0001\u0003l\"11o\u0012C\u0001\u0005{D\u0011Ba@H\u0003\u0003%\ti!\u0001\t\u0013\r\u001dq)!A\u0005\u0002\u000e%\u0001\"CB\f\u000f\u0006\u0005I\u0011BB\r\u0005\u001dA5)\u001e:t_JT\u0011AT\u0001\tCJ<wN\\1vi\u000e\u00011\u0003\u0002\u0001R/j\u0003\"AU+\u000e\u0003MS\u0011\u0001V\u0001\u0006g\u000e\fG.Y\u0005\u0003-N\u0013a!\u00118z%\u00164\u0007C\u0001*Y\u0013\tI6KA\u0004Qe>$Wo\u0019;\u0011\u0005m\u001bgB\u0001/b\u001d\ti\u0006-D\u0001_\u0015\tyv*\u0001\u0004=e>|GOP\u0005\u0002)&\u0011!mU\u0001\ba\u0006\u001c7.Y4f\u0013\t!WM\u0001\u0007TKJL\u0017\r\\5{C\ndWM\u0003\u0002c\'\u000611-\u001e:t_J,\u0012\u0001\u001b\t\u0003S*l\u0011!T\u0005\u0003W6\u0013aaQ;sg>\u0014\u0018aB2veN|\'\u000fI\u0001\bQ&\u001cHo\u001c:z+\u0005y\u0007CA5q\u0013\t\tXJA\u0007DkJ\u001cxN\u001d%jgR|\'/_\u0001\tQ&\u001cHo\u001c:zA\u00051A(\u001b8jiz\"2!\u001e<x!\tI\u0007\u0001C\u0003g\u000b\u0001\u0007\u0001\u000eC\u0003n\u000b\u0001\u0007q.A\u0004bGV\u00148o\u001c:\u0016\u0003i\u0004\"![>\n\u0005ql%aB!DkJ\u001cxN]\u0001\bU\u0012,7m\u001c3f+\ry\u00181\u0002\u000b\u0005\u0003\u0003\ti\u0002E\u0003j\u0003\u0007\t9!C\u0002\u0002\u00065\u0013A\u0002R3d_\u0012,\'+Z:vYR\u0004B!!\u0003\u0002\f1\u0001AaBA\u0007\u000f\t\u0007\u0011q\u0002\u0002\u0002\u0003F!\u0011\u0011CA\f!\r\u0011\u00161C\u0005\u0004\u0003+\u0019&a\u0002(pi\"Lgn\u001a\t\u0004%\u0006e\u0011bAA\u000e\'\n\u0019\u0011I\\=\t\u000f\u0005}q\u0001q\u0001\u0002\"\u0005\tQ\rE\u0003j\u0003G\t9!C\u0002\u0002&5\u0013!\u0002R3d_\u0012,\'j]8o\u0003\t\t7/\u0006\u0003\u0002,\u0005EB\u0003BA\u0017\u0003g\u0001R![A\u0002\u0003_\u0001B!!\u0003\u00022\u00119\u0011Q\u0002\u0005C\u0002\u0005=\u0001bBA\u0010\u0011\u0001\u000f\u0011Q\u0007\t\u0006S\u0006\r\u0012qF\u0001\u0004O\u0016$X\u0003BA\u001e\u0003\u0007\"B!!\u0010\u0002JQ!\u0011qHA#!\u0015I\u00171AA!!\u0011\tI!a\u0011\u0005\u000f\u00055\u0011B1\u0001\u0002\u0010!9\u0011qD\u0005A\u0004\u0005\u001d\u0003#B5\u0002$\u0005\u0005\u0003bBA&\u0013\u0001\u0007\u0011QJ\u0001\u0005]\u0006lW\r\u0005\u0003\u0002P\u0005]c\u0002BA)\u0003\'\u0002\"!X*\n\u0007\u0005U3+\u0001\u0004Qe\u0016$WMZ\u0005\u0005\u00033\nYF\u0001\u0004TiJLgn\u001a\u0006\u0004\u0003+\u001a\u0016!\u00044bS2,G-Q\"veN|\'/A\u0003g_\u000e,8/\u0006\u0002\u0002dA\u0019\u0011.!\u001a\n\u0007\u0005\u001dTJ\u0001\u0003Kg>t\u0017A\u0006\u0013he\u0016\fG/\u001a:%[&tWo\u001d\u0013he\u0016\fG/\u001a:\u0015\u0007U\fi\u0007C\u0004\u0002p1\u0001\r!!\u001d\u0002\u0003-\u0004rAUA:\u0003G\n\u0019\'C\u0002\u0002vM\u0013\u0011BR;oGRLwN\\\u0019\u0002\u0013]LG\u000f\u001b$pGV\u001cHcA;\u0002|!9\u0011qN\u0007A\u0002\u0005E\u0014aA:fiR\u0019Q/!!\t\u000f\u0005\re\u00021\u0001\u0002d\u0005\t!.A\u0005%G>dwN\u001c\u0013fcR\u0019Q/!#\t\u000f\u0005\ru\u00021\u0001\u0002d\u0005)A.\u001a4ugV\u0011\u0011q\u0012\t\u0006%\u0006E\u0015QS\u0005\u0004\u0003\'\u001b&AB(qi&|g\u000e\u0005\u0003\u0002\u0018\u0006uebA5\u0002\u001a&\u0019\u00111T\'\u0002\t)\u001bxN\\\u0005\u0005\u0003?\u000b\tKA\u0005Kg>t\u0017I\u001d:bs&\u0019\u00111U\'\u0003\u000b)\u001bxN\\:\u0002\rILw\r\u001b;t\u0003!1\u0017.\u001a7e\'\u0016$XCAAV!\u0015\u0011\u0016\u0011SAW!\u0019\ty%a,\u00024&!\u0011\u0011WA.\u0005\r\u0019V\r\u001e\t\u0005\u0003/\u000b),\u0003\u0003\u00028\u0006\u0005&!\u0003&t_:4\u0015.\u001a7e\u0003\u00191\u0017.\u001a7egV\u0011\u0011Q\u0018\t\u0006%\u0006E\u0015q\u0018\t\u00067\u0006\u0005\u00171W\u0005\u0004\u0003\u0007,\'\u0001\u0002\'jgR\fA\u0001\\3gi\u0006)!/[4ii\u0006)a-\u001b:ti\u0006!A.Y:u\u0003]!S.\u001b8vg\u0012bWm]:%[&tWo\u001d\u0013d_2|g\u000eF\u0002{\u0003#Dq!a5\u0019\u0001\u0004\t).A\u0001o!\r\u0011\u0016q[\u0005\u0004\u00033\u001c&aA%oi\u0006)A.\u001a4u\u001dR\u0019!0a8\t\u000f\u0005M\u0017\u00041\u0001\u0002V\u0006QBeY8m_:$S.\u001b8vg\u0012:\'/Z1uKJ$S.\u001b8vgR\u0019!0!:\t\u000f\u0005M\'\u00041\u0001\u0002V\u00061!/[4ii:#2A_Av\u0011\u001d\t\u0019n\u0007a\u0001\u0003+\fq\u0003J9nCJ\\G\u0005\\3tg\u0012j\u0017N\\;tI\r|Gn\u001c8\u0015\u0007i\f\t\u0010C\u0004\u0002tr\u0001\r!!>\u0002\u0003A\u0004rAUA:\u0003G\n9\u0010E\u0002S\u0003sL1!a?T\u0005\u001d\u0011un\u001c7fC:\fa\u0001\\3gi\u0006#Hc\u0001>\u0003\u0002!9\u00111_\u000fA\u0002\u0005U\u0018A\u0007\u0013d_2|g\u000eJ7j]V\u001cHe\u001a:fCR,\'\u000fJ9nCJ\\Gc\u0001>\u0003\b!9\u00111\u001f\u0010A\u0002\u0005U\u0018a\u0002:jO\"$\u0018\t\u001e\u000b\u0004u\n5\u0001bBAz?\u0001\u0007\u0011Q_\u0001\u0005M&tG\rF\u0002{\u0005\'Aq!a=!\u0001\u0004\t)0\u0001\u0007%[&tWo\u001d\u0013nS:,8\u000fF\u0002{\u00053AqAa\u0007\"\u0001\u0004\t\u0019,A\u0001r\u0003\u00151\u0017.\u001a7e)\rQ(\u0011\u0005\u0005\b\u00057\u0011\u0003\u0019AAZ\u0003M!S.\u001b8vg\u0012j\u0017N\\;tI\t\u001cH.Y:i)\rQ(q\u0005\u0005\b\u00057\u0019\u0003\u0019AAZ\u0003%!wn\u001e8GS\u0016dG\rF\u0002{\u0005[AqAa\u0007%\u0001\u0004\t\u0019,A\u0005e_^t\u0017I\u001d:bs\u0006qAEY:mCNDGEY:mCND\u0017!\u0004\u0013nS:,8\u000f\n2tY\u0006\u001c\b\u000eF\u0002{\u0005oAq!a=(\u0001\u0004\t)0\u0001\u0004e_^t\u0017\t\u001e\u000b\u0004u\nu\u0002bBAzQ\u0001\u0007\u0011Q_\u0001\u000bI\u0015\fHEY:mCNDGc\u0001>\u0003D!9\u00111[\u0015A\u0002\u0005U\u0017!\u00023po:tEc\u0001>\u0003J!9\u00111\u001b\u0016A\u0002\u0005U\u0017A\u00023fY\u0016$X-A\u0006v]\u0006\u0014\u0018p\u0018\u0013cC:<\u0017A\u00043fY\u0016$XmR8QCJ,g\u000e^\u0001\rI\u0016dW\r^3H_2+g\r^\u0001\u000eI\u0016dW\r^3H_JKw\r\u001b;\u0002\u001b\u0011,G.\u001a;f\u000f>4\u0015N]:u\u00031!W\r\\3uK\u001e{G*Y:u\u00035!W\r\\3uK\u001e{g)[3mIR\u0019!P!\u0018\t\u000f\tm!\u00071\u0001\u00024\u0006YA-\u001a7fi\u0016dUM\u001a;t\u00031!W\r\\3uKJKw\r\u001b;t\u0003!\u0019X\r\u001e\'fMR\u001cHc\u0001>\u0003h!9!\u0011N\u001bA\u0002\t-\u0014!\u0001=\u0011\u000bm\u000b\t-a\u0019\u0002\u0013M,GOU5hQR\u001cHc\u0001>\u0003r!9!\u0011\u000e\u001cA\u0002\t-\u0014AA;q\u00031)h.\u0019:z?\u0012j\u0017N\\;t\u0003\u0011)h\u000eZ8\u0002\t\r|\u0007/\u001f\u000b\u0006k\nu$q\u0010\u0005\bMj\u0002\n\u00111\u0001i\u0011\u001di\'\b%AA\u0002=\fabY8qs\u0012\"WMZ1vYR$\u0013\'\u0006\u0002\u0003\u0006*\u001a\u0001Na\",\u0005\t%\u0005\u0003\u0002BF\u0005+k!A!$\u000b\t\t=%\u0011S\u0001\nk:\u001c\u0007.Z2lK\u0012T1Aa%T\u0003)\tgN\\8uCRLwN\\\u0005\u0005\u0005/\u0013iIA\tv]\u000eDWmY6fIZ\u000b\'/[1oG\u0016\fabY8qs\u0012\"WMZ1vYR$#\'\u0006\u0002\u0003\u001e*\u001aqNa\"\u0002\u001bA\u0014x\u000eZ;diB\u0013XMZ5y+\t\u0011\u0019\u000b\u0005\u0003\u0003&\n=VB\u0001BT\u0015\u0011\u0011IKa+\u0002\t1\fgn\u001a\u0006\u0003\u0005[\u000bAA[1wC&!\u0011\u0011\fBT\u00031\u0001(o\u001c3vGR\f%/\u001b;z+\t\t).\u0001\bqe>$Wo\u0019;FY\u0016lWM\u001c;\u0015\t\u0005]!\u0011\u0018\u0005\n\u0005w{\u0014\u0011!a\u0001\u0003+\f1\u0001\u001f\u00132\u0003=\u0001(o\u001c3vGRLE/\u001a:bi>\u0014XC\u0001Ba!\u0019\u0011\u0019M!3\u0002\u00185\u0011!Q\u0019\u0006\u0004\u0005\u000f\u001c\u0016AC2pY2,7\r^5p]&!!1\u001aBc\u0005!IE/\u001a:bi>\u0014\u0018\u0001C2b]\u0016\u000bX/\u00197\u0015\t\u0005](\u0011\u001b\u0005\n\u0005w\u000b\u0015\u0011!a\u0001\u0003/\t!\u0003\u001d:pIV\u001cG/\u00127f[\u0016tGOT1nKR!!1\u0015Bl\u0011%\u0011YLQA\u0001\u0002\u0004\t).\u0001\u0005iCND7i\u001c3f)\t\t).\u0001\u0005u_N#(/\u001b8h)\t\u0011\u0019+\u0001\u0004fcV\fGn\u001d\u000b\u0005\u0003o\u0014)\u000fC\u0005\u0003<\u0016\u000b\t\u00111\u0001\u0002\u0018\u00059\u0001jQ;sg>\u0014\bCA5H\'\u00199\u0015K!<\u0003tB\u0019\u0011Na<\n\u0007\tEXJ\u0001\u0005I\u0007V\u00148o\u001c:t!\u0011\u0011)Pa?\u000e\u0005\t](\u0002\u0002B}\u0005W\u000b!![8\n\u0007\u0011\u00149\u0010\u0006\u0002\u0003j\u0006)\u0011\r\u001d9msR)Qoa\u0001\u0004\u0006!)a-\u0013a\u0001Q\")Q.\u0013a\u0001_\u00069QO\\1qa2LH\u0003BB\u0006\u0007\'\u0001RAUAI\u0007\u001b\u0001RAUB\bQ>L1a!\u0005T\u0005\u0019!V\u000f\u001d7fe!A1Q\u0003&\u0002\u0002\u0003\u0007Q/A\u0002yIA\nAb\u001e:ji\u0016\u0014V\r\u001d7bG\u0016$\"aa\u0007\u0011\t\t\u00156QD\u0005\u0005\u0007?\u00119K\u0001\u0004PE*,7\r\u001e"
    )
BootstrapMethods:
  0: #140 REF_invokeStatic java/lang/invoke/LambdaMetafactory.altMetafactory:(Ljava/lang/invoke/MethodHandles$Lookup;Ljava/lang/String;Ljava/lang/invoke/MethodType;[Ljava/lang/Object;)Ljava/lang/invoke/CallSite;
    Method arguments:
      #124 (Ljava/lang/Object;)Ljava/lang/Object;
      #129 REF_invokeStatic argonaut/HCursor.$anonfun$set$1:(Largonaut/Json;Largonaut/Json;)Largonaut/Json;
      #131 (Largonaut/Json;)Largonaut/Json;
      #132 5
      #133 1
      #131 (Largonaut/Json;)Largonaut/Json;
  1: #140 REF_invokeStatic java/lang/invoke/LambdaMetafactory.altMetafactory:(Ljava/lang/invoke/MethodHandles$Lookup;Ljava/lang/String;Ljava/lang/invoke/MethodType;[Ljava/lang/Object;)Ljava/lang/invoke/CallSite;
    Method arguments:
      #124 (Ljava/lang/Object;)Ljava/lang/Object;
      #169 REF_invokeStatic argonaut/HCursor.$anonfun$left$1:(Largonaut/Cursor;)Lscala/Option;
      #170 (Largonaut/Cursor;)Lscala/Option;
      #132 5
      #133 1
      #170 (Largonaut/Cursor;)Lscala/Option;
  2: #140 REF_invokeStatic java/lang/invoke/LambdaMetafactory.altMetafactory:(Ljava/lang/invoke/MethodHandles$Lookup;Ljava/lang/String;Ljava/lang/invoke/MethodType;[Ljava/lang/Object;)Ljava/lang/invoke/CallSite;
    Method arguments:
      #124 (Ljava/lang/Object;)Ljava/lang/Object;
      #189 REF_invokeStatic argonaut/HCursor.$anonfun$right$1:(Largonaut/Cursor;)Lscala/Option;
      #170 (Largonaut/Cursor;)Lscala/Option;
      #132 5
      #133 1
      #170 (Largonaut/Cursor;)Lscala/Option;
  3: #140 REF_invokeStatic java/lang/invoke/LambdaMetafactory.altMetafactory:(Ljava/lang/invoke/MethodHandles$Lookup;Ljava/lang/String;Ljava/lang/invoke/MethodType;[Ljava/lang/Object;)Ljava/lang/invoke/CallSite;
    Method arguments:
      #124 (Ljava/lang/Object;)Ljava/lang/Object;
      #200 REF_invokeStatic argonaut/HCursor.$anonfun$first$1:(Largonaut/Cursor;)Lscala/Option;
      #170 (Largonaut/Cursor;)Lscala/Option;
      #132 5
      #133 1
      #170 (Largonaut/Cursor;)Lscala/Option;
  4: #140 REF_invokeStatic java/lang/invoke/LambdaMetafactory.altMetafactory:(Ljava/lang/invoke/MethodHandles$Lookup;Ljava/lang/String;Ljava/lang/invoke/MethodType;[Ljava/lang/Object;)Ljava/lang/invoke/CallSite;
    Method arguments:
      #124 (Ljava/lang/Object;)Ljava/lang/Object;
      #211 REF_invokeStatic argonaut/HCursor.$anonfun$last$1:(Largonaut/Cursor;)Lscala/Option;
      #170 (Largonaut/Cursor;)Lscala/Option;
      #132 5
      #133 1
      #170 (Largonaut/Cursor;)Lscala/Option;
  5: #140 REF_invokeStatic java/lang/invoke/LambdaMetafactory.altMetafactory:(Ljava/lang/invoke/MethodHandles$Lookup;Ljava/lang/String;Ljava/lang/invoke/MethodType;[Ljava/lang/Object;)Ljava/lang/invoke/CallSite;
    Method arguments:
      #124 (Ljava/lang/Object;)Ljava/lang/Object;
      #229 REF_invokeStatic argonaut/HCursor.$anonfun$leftN$1:(ILargonaut/Cursor;)Lscala/Option;
      #170 (Largonaut/Cursor;)Lscala/Option;
      #132 5
      #133 1
      #170 (Largonaut/Cursor;)Lscala/Option;
  6: #140 REF_invokeStatic java/lang/invoke/LambdaMetafactory.altMetafactory:(Ljava/lang/invoke/MethodHandles$Lookup;Ljava/lang/String;Ljava/lang/invoke/MethodType;[Ljava/lang/Object;)Ljava/lang/invoke/CallSite;
    Method arguments:
      #124 (Ljava/lang/Object;)Ljava/lang/Object;
      #245 REF_invokeStatic argonaut/HCursor.$anonfun$rightN$1:(ILargonaut/Cursor;)Lscala/Option;
      #170 (Largonaut/Cursor;)Lscala/Option;
      #132 5
      #133 1
      #170 (Largonaut/Cursor;)Lscala/Option;
  7: #140 REF_invokeStatic java/lang/invoke/LambdaMetafactory.altMetafactory:(Ljava/lang/invoke/MethodHandles$Lookup;Ljava/lang/String;Ljava/lang/invoke/MethodType;[Ljava/lang/Object;)Ljava/lang/invoke/CallSite;
    Method arguments:
      #124 (Ljava/lang/Object;)Ljava/lang/Object;
      #261 REF_invokeStatic argonaut/HCursor.$anonfun$leftAt$1:(Lscala/Function1;Largonaut/Cursor;)Lscala/Option;
      #170 (Largonaut/Cursor;)Lscala/Option;
      #132 5
      #133 1
      #170 (Largonaut/Cursor;)Lscala/Option;
  8: #140 REF_invokeStatic java/lang/invoke/LambdaMetafactory.altMetafactory:(Ljava/lang/invoke/MethodHandles$Lookup;Ljava/lang/String;Ljava/lang/invoke/MethodType;[Ljava/lang/Object;)Ljava/lang/invoke/CallSite;
    Method arguments:
      #124 (Ljava/lang/Object;)Ljava/lang/Object;
      #277 REF_invokeStatic argonaut/HCursor.$anonfun$rightAt$1:(Lscala/Function1;Largonaut/Cursor;)Lscala/Option;
      #170 (Largonaut/Cursor;)Lscala/Option;
      #132 5
      #133 1
      #170 (Largonaut/Cursor;)Lscala/Option;
  9: #140 REF_invokeStatic java/lang/invoke/LambdaMetafactory.altMetafactory:(Ljava/lang/invoke/MethodHandles$Lookup;Ljava/lang/String;Ljava/lang/invoke/MethodType;[Ljava/lang/Object;)Ljava/lang/invoke/CallSite;
    Method arguments:
      #124 (Ljava/lang/Object;)Ljava/lang/Object;
      #286 REF_invokeStatic argonaut/HCursor.$anonfun$find$1:(Lscala/Function1;Largonaut/Cursor;)Lscala/Option;
      #170 (Largonaut/Cursor;)Lscala/Option;
      #132 5
      #133 1
      #170 (Largonaut/Cursor;)Lscala/Option;
  10: #140 REF_invokeStatic java/lang/invoke/LambdaMetafactory.altMetafactory:(Ljava/lang/invoke/MethodHandles$Lookup;Ljava/lang/String;Ljava/lang/invoke/MethodType;[Ljava/lang/Object;)Ljava/lang/invoke/CallSite;
    Method arguments:
      #124 (Ljava/lang/Object;)Ljava/lang/Object;
      #300 REF_invokeStatic argonaut/HCursor.$anonfun$field$1:(Ljava/lang/String;Largonaut/Cursor;)Lscala/Option;
      #170 (Largonaut/Cursor;)Lscala/Option;
      #132 5
      #133 1
      #170 (Largonaut/Cursor;)Lscala/Option;
  11: #140 REF_invokeStatic java/lang/invoke/LambdaMetafactory.altMetafactory:(Ljava/lang/invoke/MethodHandles$Lookup;Ljava/lang/String;Ljava/lang/invoke/MethodType;[Ljava/lang/Object;)Ljava/lang/invoke/CallSite;
    Method arguments:
      #124 (Ljava/lang/Object;)Ljava/lang/Object;
      #315 REF_invokeStatic argonaut/HCursor.$anonfun$downField$1:(Ljava/lang/String;Largonaut/Cursor;)Lscala/Option;
      #170 (Largonaut/Cursor;)Lscala/Option;
      #132 5
      #133 1
      #170 (Largonaut/Cursor;)Lscala/Option;
  12: #140 REF_invokeStatic java/lang/invoke/LambdaMetafactory.altMetafactory:(Ljava/lang/invoke/MethodHandles$Lookup;Ljava/lang/String;Ljava/lang/invoke/MethodType;[Ljava/lang/Object;)Ljava/lang/invoke/CallSite;
    Method arguments:
      #124 (Ljava/lang/Object;)Ljava/lang/Object;
      #324 REF_invokeStatic argonaut/HCursor.$anonfun$downArray$1:(Largonaut/Cursor;)Lscala/Option;
      #170 (Largonaut/Cursor;)Lscala/Option;
      #132 5
      #133 1
      #170 (Largonaut/Cursor;)Lscala/Option;
  13: #140 REF_invokeStatic java/lang/invoke/LambdaMetafactory.altMetafactory:(Ljava/lang/invoke/MethodHandles$Lookup;Ljava/lang/String;Ljava/lang/invoke/MethodType;[Ljava/lang/Object;)Ljava/lang/invoke/CallSite;
    Method arguments:
      #124 (Ljava/lang/Object;)Ljava/lang/Object;
      #341 REF_invokeStatic argonaut/HCursor.$anonfun$downAt$1:(Lscala/Function1;Largonaut/Cursor;)Lscala/Option;
      #170 (Largonaut/Cursor;)Lscala/Option;
      #132 5
      #133 1
      #170 (Largonaut/Cursor;)Lscala/Option;
  14: #140 REF_invokeStatic java/lang/invoke/LambdaMetafactory.altMetafactory:(Ljava/lang/invoke/MethodHandles$Lookup;Ljava/lang/String;Ljava/lang/invoke/MethodType;[Ljava/lang/Object;)Ljava/lang/invoke/CallSite;
    Method arguments:
      #124 (Ljava/lang/Object;)Ljava/lang/Object;
      #353 REF_invokeStatic argonaut/HCursor.$anonfun$downN$1:(ILargonaut/Cursor;)Lscala/Option;
      #170 (Largonaut/Cursor;)Lscala/Option;
      #132 5
      #133 1
      #170 (Largonaut/Cursor;)Lscala/Option;
  15: #140 REF_invokeStatic java/lang/invoke/LambdaMetafactory.altMetafactory:(Ljava/lang/invoke/MethodHandles$Lookup;Ljava/lang/String;Ljava/lang/invoke/MethodType;[Ljava/lang/Object;)Ljava/lang/invoke/CallSite;
    Method arguments:
      #124 (Ljava/lang/Object;)Ljava/lang/Object;
      #366 REF_invokeStatic argonaut/HCursor.$anonfun$deleteGoParent$1:(Largonaut/Cursor;)Lscala/Option;
      #170 (Largonaut/Cursor;)Lscala/Option;
      #132 5
      #133 1
      #170 (Largonaut/Cursor;)Lscala/Option;
  16: #140 REF_invokeStatic java/lang/invoke/LambdaMetafactory.altMetafactory:(Ljava/lang/invoke/MethodHandles$Lookup;Ljava/lang/String;Ljava/lang/invoke/MethodType;[Ljava/lang/Object;)Ljava/lang/invoke/CallSite;
    Method arguments:
      #124 (Ljava/lang/Object;)Ljava/lang/Object;
      #377 REF_invokeStatic argonaut/HCursor.$anonfun$deleteGoLeft$1:(Largonaut/Cursor;)Lscala/Option;
      #170 (Largonaut/Cursor;)Lscala/Option;
      #132 5
      #133 1
      #170 (Largonaut/Cursor;)Lscala/Option;
  17: #140 REF_invokeStatic java/lang/invoke/LambdaMetafactory.altMetafactory:(Ljava/lang/invoke/MethodHandles$Lookup;Ljava/lang/String;Ljava/lang/invoke/MethodType;[Ljava/lang/Object;)Ljava/lang/invoke/CallSite;
    Method arguments:
      #124 (Ljava/lang/Object;)Ljava/lang/Object;
      #388 REF_invokeStatic argonaut/HCursor.$anonfun$deleteGoRight$1:(Largonaut/Cursor;)Lscala/Option;
      #170 (Largonaut/Cursor;)Lscala/Option;
      #132 5
      #133 1
      #170 (Largonaut/Cursor;)Lscala/Option;
  18: #140 REF_invokeStatic java/lang/invoke/LambdaMetafactory.altMetafactory:(Ljava/lang/invoke/MethodHandles$Lookup;Ljava/lang/String;Ljava/lang/invoke/MethodType;[Ljava/lang/Object;)Ljava/lang/invoke/CallSite;
    Method arguments:
      #124 (Ljava/lang/Object;)Ljava/lang/Object;
      #399 REF_invokeStatic argonaut/HCursor.$anonfun$deleteGoFirst$1:(Largonaut/Cursor;)Lscala/Option;
      #170 (Largonaut/Cursor;)Lscala/Option;
      #132 5
      #133 1
      #170 (Largonaut/Cursor;)Lscala/Option;
  19: #140 REF_invokeStatic java/lang/invoke/LambdaMetafactory.altMetafactory:(Ljava/lang/invoke/MethodHandles$Lookup;Ljava/lang/String;Ljava/lang/invoke/MethodType;[Ljava/lang/Object;)Ljava/lang/invoke/CallSite;
    Method arguments:
      #124 (Ljava/lang/Object;)Ljava/lang/Object;
      #410 REF_invokeStatic argonaut/HCursor.$anonfun$deleteGoLast$1:(Largonaut/Cursor;)Lscala/Option;
      #170 (Largonaut/Cursor;)Lscala/Option;
      #132 5
      #133 1
      #170 (Largonaut/Cursor;)Lscala/Option;
  20: #140 REF_invokeStatic java/lang/invoke/LambdaMetafactory.altMetafactory:(Ljava/lang/invoke/MethodHandles$Lookup;Ljava/lang/String;Ljava/lang/invoke/MethodType;[Ljava/lang/Object;)Ljava/lang/invoke/CallSite;
    Method arguments:
      #124 (Ljava/lang/Object;)Ljava/lang/Object;
      #421 REF_invokeStatic argonaut/HCursor.$anonfun$deleteGoField$1:(Ljava/lang/String;Largonaut/Cursor;)Lscala/Option;
      #170 (Largonaut/Cursor;)Lscala/Option;
      #132 5
      #133 1
      #170 (Largonaut/Cursor;)Lscala/Option;
  21: #140 REF_invokeStatic java/lang/invoke/LambdaMetafactory.altMetafactory:(Ljava/lang/invoke/MethodHandles$Lookup;Ljava/lang/String;Ljava/lang/invoke/MethodType;[Ljava/lang/Object;)Ljava/lang/invoke/CallSite;
    Method arguments:
      #124 (Ljava/lang/Object;)Ljava/lang/Object;
      #430 REF_invokeStatic argonaut/HCursor.$anonfun$deleteLefts$1:(Largonaut/Cursor;)Lscala/Option;
      #170 (Largonaut/Cursor;)Lscala/Option;
      #132 5
      #133 1
      #170 (Largonaut/Cursor;)Lscala/Option;
  22: #140 REF_invokeStatic java/lang/invoke/LambdaMetafactory.altMetafactory:(Ljava/lang/invoke/MethodHandles$Lookup;Ljava/lang/String;Ljava/lang/invoke/MethodType;[Ljava/lang/Object;)Ljava/lang/invoke/CallSite;
    Method arguments:
      #124 (Ljava/lang/Object;)Ljava/lang/Object;
      #441 REF_invokeStatic argonaut/HCursor.$anonfun$deleteRights$1:(Largonaut/Cursor;)Lscala/Option;
      #170 (Largonaut/Cursor;)Lscala/Option;
      #132 5
      #133 1
      #170 (Largonaut/Cursor;)Lscala/Option;
  23: #140 REF_invokeStatic java/lang/invoke/LambdaMetafactory.altMetafactory:(Ljava/lang/invoke/MethodHandles$Lookup;Ljava/lang/String;Ljava/lang/invoke/MethodType;[Ljava/lang/Object;)Ljava/lang/invoke/CallSite;
    Method arguments:
      #124 (Ljava/lang/Object;)Ljava/lang/Object;
      #456 REF_invokeStatic argonaut/HCursor.$anonfun$setLefts$1:(Lscala/collection/immutable/List;Largonaut/Cursor;)Lscala/Option;
      #170 (Largonaut/Cursor;)Lscala/Option;
      #132 5
      #133 1
      #170 (Largonaut/Cursor;)Lscala/Option;
  24: #140 REF_invokeStatic java/lang/invoke/LambdaMetafactory.altMetafactory:(Ljava/lang/invoke/MethodHandles$Lookup;Ljava/lang/String;Ljava/lang/invoke/MethodType;[Ljava/lang/Object;)Ljava/lang/invoke/CallSite;
    Method arguments:
      #124 (Ljava/lang/Object;)Ljava/lang/Object;
      #470 REF_invokeStatic argonaut/HCursor.$anonfun$setRights$1:(Lscala/collection/immutable/List;Largonaut/Cursor;)Lscala/Option;
      #170 (Largonaut/Cursor;)Lscala/Option;
      #132 5
      #133 1
      #170 (Largonaut/Cursor;)Lscala/Option;
  25: #140 REF_invokeStatic java/lang/invoke/LambdaMetafactory.altMetafactory:(Ljava/lang/invoke/MethodHandles$Lookup;Ljava/lang/String;Ljava/lang/invoke/MethodType;[Ljava/lang/Object;)Ljava/lang/invoke/CallSite;
    Method arguments:
      #124 (Ljava/lang/Object;)Ljava/lang/Object;
      #479 REF_invokeStatic argonaut/HCursor.$anonfun$up$1:(Largonaut/Cursor;)Lscala/Option;
      #170 (Largonaut/Cursor;)Lscala/Option;
      #132 5
      #133 1
      #170 (Largonaut/Cursor;)Lscala/Option;
  26: #648 REF_invokeStatic scala/runtime/LambdaDeserialize.bootstrap:(Ljava/lang/invoke/MethodHandles$Lookup;Ljava/lang/String;Ljava/lang/invoke/MethodType;[Ljava/lang/invoke/MethodHandle;)Ljava/lang/invoke/CallSite;
    Method arguments:
      #421 REF_invokeStatic argonaut/HCursor.$anonfun$deleteGoField$1:(Ljava/lang/String;Largonaut/Cursor;)Lscala/Option;
      #399 REF_invokeStatic argonaut/HCursor.$anonfun$deleteGoFirst$1:(Largonaut/Cursor;)Lscala/Option;
      #410 REF_invokeStatic argonaut/HCursor.$anonfun$deleteGoLast$1:(Largonaut/Cursor;)Lscala/Option;
      #377 REF_invokeStatic argonaut/HCursor.$anonfun$deleteGoLeft$1:(Largonaut/Cursor;)Lscala/Option;
      #366 REF_invokeStatic argonaut/HCursor.$anonfun$deleteGoParent$1:(Largonaut/Cursor;)Lscala/Option;
      #388 REF_invokeStatic argonaut/HCursor.$anonfun$deleteGoRight$1:(Largonaut/Cursor;)Lscala/Option;
      #430 REF_invokeStatic argonaut/HCursor.$anonfun$deleteLefts$1:(Largonaut/Cursor;)Lscala/Option;
      #441 REF_invokeStatic argonaut/HCursor.$anonfun$deleteRights$1:(Largonaut/Cursor;)Lscala/Option;
      #324 REF_invokeStatic argonaut/HCursor.$anonfun$downArray$1:(Largonaut/Cursor;)Lscala/Option;
      #341 REF_invokeStatic argonaut/HCursor.$anonfun$downAt$1:(Lscala/Function1;Largonaut/Cursor;)Lscala/Option;
      #315 REF_invokeStatic argonaut/HCursor.$anonfun$downField$1:(Ljava/lang/String;Largonaut/Cursor;)Lscala/Option;
      #353 REF_invokeStatic argonaut/HCursor.$anonfun$downN$1:(ILargonaut/Cursor;)Lscala/Option;
      #300 REF_invokeStatic argonaut/HCursor.$anonfun$field$1:(Ljava/lang/String;Largonaut/Cursor;)Lscala/Option;
      #286 REF_invokeStatic argonaut/HCursor.$anonfun$find$1:(Lscala/Function1;Largonaut/Cursor;)Lscala/Option;
      #200 REF_invokeStatic argonaut/HCursor.$anonfun$first$1:(Largonaut/Cursor;)Lscala/Option;
      #211 REF_invokeStatic argonaut/HCursor.$anonfun$last$1:(Largonaut/Cursor;)Lscala/Option;
      #169 REF_invokeStatic argonaut/HCursor.$anonfun$left$1:(Largonaut/Cursor;)Lscala/Option;
      #261 REF_invokeStatic argonaut/HCursor.$anonfun$leftAt$1:(Lscala/Function1;Largonaut/Cursor;)Lscala/Option;
      #229 REF_invokeStatic argonaut/HCursor.$anonfun$leftN$1:(ILargonaut/Cursor;)Lscala/Option;
      #189 REF_invokeStatic argonaut/HCursor.$anonfun$right$1:(Largonaut/Cursor;)Lscala/Option;
      #277 REF_invokeStatic argonaut/HCursor.$anonfun$rightAt$1:(Lscala/Function1;Largonaut/Cursor;)Lscala/Option;
      #245 REF_invokeStatic argonaut/HCursor.$anonfun$rightN$1:(ILargonaut/Cursor;)Lscala/Option;
      #129 REF_invokeStatic argonaut/HCursor.$anonfun$set$1:(Largonaut/Json;Largonaut/Json;)Largonaut/Json;
      #456 REF_invokeStatic argonaut/HCursor.$anonfun$setLefts$1:(Lscala/collection/immutable/List;Largonaut/Cursor;)Lscala/Option;
      #470 REF_invokeStatic argonaut/HCursor.$anonfun$setRights$1:(Lscala/collection/immutable/List;Largonaut/Cursor;)Lscala/Option;
      #479 REF_invokeStatic argonaut/HCursor.$anonfun$up$1:(Largonaut/Cursor;)Lscala/Option;
  ScalaInlineInfo: length = 0x1DA (unknown attribute)
   01 00 00 5E 01 A2 01 29 01 01 8C 00 A6 01 01 97
   00 A6 01 01 76 00 A6 01 01 6B 00 A6 01 01 81 00
   A6 01 01 AB 00 A6 01 01 B6 00 A6 01 01 41 00 A6
   01 01 52 01 02 01 01 38 01 29 01 01 5E 00 E2 01
   01 28 01 29 01 01 1B 01 02 01 00 C5 00 A6 01 00
   D0 00 A6 01 00 A5 00 A6 01 01 01 01 02 01 00 E1
   00 E2 01 00 BA 00 A6 01 01 12 01 02 01 00 F2 00
   E2 01 00 7D 00 7E 01 01 C4 01 C5 01 01 D3 01 C5
   01 01 DC 00 A6 01 01 4B 00 36 00 00 91 00 79 00
   00 EE 00 DB 00 01 0E 00 FB 00 01 5A 00 DB 00 00
   67 00 68 00 01 4E 00 FB 00 00 DA 00 DB 00 01 23
   00 53 00 00 52 00 53 00 00 FA 00 FB 00 00 74 00
   75 00 00 35 00 36 00 00 4B 00 41 00 02 05 02 06
   00 01 EA 00 23 00 01 EB 00 2F 00 01 EC 00 32 00
   00 12 00 2F 00 01 66 00 36 00 01 A1 00 53 00 01
   8B 00 36 00 01 96 00 36 00 01 75 00 36 00 01 67
   00 36 00 01 80 00 36 00 01 AA 00 36 00 01 B5 00
   36 00 01 40 00 36 00 01 4F 00 FB 00 01 35 00 53
   00 01 5B 00 DB 00 02 18 02 06 00 00 5B 00 36 00
   01 25 00 53 00 00 9C 00 95 00 00 A0 00 95 00 01
   1A 00 FB 00 00 C4 00 36 00 00 5F 00 60 00 00 4E
   00 4F 00 02 0E 01 F2 00 00 14 00 32 00 00 40 00
   41 00 00 CF 00 36 00 00 A4 00 36 00 00 FE 00 FB
   00 00 DD 00 DB 00 00 94 00 95 00 01 F1 01 F2 00
   01 F3 01 F4 00 02 08 02 09 00 00 26 00 27 00 01
   FB 00 27 00 01 ED 01 EE 00 00 B9 00 36 00 01 0F
   00 FB 00 00 EF 00 DB 00 00 99 00 95 00 00 78 00
   79 00 01 C0 01 C1 00 01 D2 01 C1 00 02 13 01 EE
   00 01 6A 00 36 00 01 E6 00 60 00 01 E7 00 60 00
   01 DB 00 36 00 00 6B 00 68 00
  ScalaSig: length = 0x3 (unknown attribute)
   05 02 00
