Classfile /Users/mw/Projects/slang-braindump/.jar/jar8/assemble/slang-braindump/assemble/content/argonaut/Info.class
  Last modified May 29, 2022; size 639 bytes
  SHA-256 checksum 114dee2d0227c1279e4435889e54fc195a3b23313bdb07843a10440416840d43
  Compiled from "info.scala"
public final class argonaut.Info
  minor version: 0
  major version: 52
  flags: (0x0031) ACC_PUBLIC, ACC_FINAL, ACC_SUPER
  this_class: #2                          // argonaut/Info
  super_class: #4                         // java/lang/Object
  interfaces: 0, fields: 0, methods: 2, attributes: 3
Constant pool:
   #1 = Utf8               argonaut/Info
   #2 = Class              #1             // argonaut/Info
   #3 = Utf8               java/lang/Object
   #4 = Class              #3             // java/lang/Object
   #5 = Utf8               info.scala
   #6 = Utf8               Lscala/reflect/ScalaSignature;
   #7 = Utf8               bytes
   #8 = Utf8               \u0006\u0005\u0011:Qa\u0002\u0005\t\u0002-1Q!\u0004\u0005\t\u00029AQ!F\u0001\u0005\u0002YAqaF\u0001C\u0002\u0013\u0005\u0001\u0004\u0003\u0004\"\u0003\u0001\u0006I!\u0007\u0005\bE\u0005\u0011\r\u0011\"\u0001\u0019\u0011\u0019\u0019\u0013\u0001)A\u00053\u0005!\u0011J\u001c4p\u0015\u0005I\u0011\u0001C1sO>t\u0017-\u001e;\u0004\u0001A\u0011A\"A\u0007\u0002\u0011\t!\u0011J\u001c4p\'\t\tq\u0002\u0005\u0002\u0011\'5\t\u0011CC\u0001\u0013\u0003\u0015\u00198-\u00197b\u0013\t!\u0012C\u0001\u0004B]f\u0014VMZ\u0001\u0007y%t\u0017\u000e\u001e \u0015\u0003-\tqA^3sg&|g.F\u0001\u001a!\tQr$D\u0001\u001c\u0015\taR$\u0001\u0003mC:<\'\"\u0001\u0010\u0002\t)\fg/Y\u0005\u0003Am\u0011aa\u0015;sS:<\u0017\u0001\u0003<feNLwN\u001c\u0011\u0002\t9\fW.Z\u0001\u0006]\u0006lW\r\t
   #9 = Utf8               name
  #10 = Utf8               ()Ljava/lang/String;
  #11 = Utf8               argonaut/Info$
  #12 = Class              #11            // argonaut/Info$
  #13 = Utf8               MODULE$
  #14 = Utf8               Largonaut/Info$;
  #15 = NameAndType        #13:#14        // MODULE$:Largonaut/Info$;
  #16 = Fieldref           #12.#15        // argonaut/Info$.MODULE$:Largonaut/Info$;
  #17 = NameAndType        #9:#10         // name:()Ljava/lang/String;
  #18 = Methodref          #12.#17        // argonaut/Info$.name:()Ljava/lang/String;
  #19 = Utf8               version
  #20 = NameAndType        #19:#10        // version:()Ljava/lang/String;
  #21 = Methodref          #12.#20        // argonaut/Info$.version:()Ljava/lang/String;
  #22 = Utf8               Code
  #23 = Utf8               SourceFile
  #24 = Utf8               RuntimeVisibleAnnotations
  #25 = Utf8               ScalaSig
{
  public static java.lang.String name();
    descriptor: ()Ljava/lang/String;
    flags: (0x0009) ACC_PUBLIC, ACC_STATIC
    Code:
      stack=1, locals=0, args_size=0
         0: getstatic     #16                 // Field argonaut/Info$.MODULE$:Largonaut/Info$;
         3: invokevirtual #18                 // Method argonaut/Info$.name:()Ljava/lang/String;
         6: areturn

  public static java.lang.String version();
    descriptor: ()Ljava/lang/String;
    flags: (0x0009) ACC_PUBLIC, ACC_STATIC
    Code:
      stack=1, locals=0, args_size=0
         0: getstatic     #16                 // Field argonaut/Info$.MODULE$:Largonaut/Info$;
         3: invokevirtual #21                 // Method argonaut/Info$.version:()Ljava/lang/String;
         6: areturn
}
SourceFile: "info.scala"
RuntimeVisibleAnnotations:
  0: #6(#7=s#8)
    scala.reflect.ScalaSignature(
      bytes="\u0006\u0005\u0011:Qa\u0002\u0005\t\u0002-1Q!\u0004\u0005\t\u00029AQ!F\u0001\u0005\u0002YAqaF\u0001C\u0002\u0013\u0005\u0001\u0004\u0003\u0004\"\u0003\u0001\u0006I!\u0007\u0005\bE\u0005\u0011\r\u0011\"\u0001\u0019\u0011\u0019\u0019\u0013\u0001)A\u00053\u0005!\u0011J\u001c4p\u0015\u0005I\u0011\u0001C1sO>t\u0017-\u001e;\u0004\u0001A\u0011A\"A\u0007\u0002\u0011\t!\u0011J\u001c4p\'\t\tq\u0002\u0005\u0002\u0011\'5\t\u0011CC\u0001\u0013\u0003\u0015\u00198-\u00197b\u0013\t!\u0012C\u0001\u0004B]f\u0014VMZ\u0001\u0007y%t\u0017\u000e\u001e \u0015\u0003-\tqA^3sg&|g.F\u0001\u001a!\tQr$D\u0001\u001c\u0015\taR$\u0001\u0003mC:<\'\"\u0001\u0010\u0002\t)\fg/Y\u0005\u0003Am\u0011aa\u0015;sS:<\u0017\u0001\u0003<feNLwN\u001c\u0011\u0002\t9\fW.Z\u0001\u0006]\u0006lW\r\t"
    )
  ScalaSig: length = 0x3 (unknown attribute)
   05 02 00
