Classfile /Users/mw/Projects/slang-braindump/.jar/jar8/assemble/slang-braindump/assemble/content/argonaut/JBool.class
  Last modified May 29, 2022; size 4283 bytes
  SHA-256 checksum d7195800385ae59cfcf56d08c42ac50ca35834099439a29eebe88c6d83b837d1
  Compiled from "Json.scala"
public class argonaut.JBool extends argonaut.Json
  minor version: 0
  major version: 52
  flags: (0x0021) ACC_PUBLIC, ACC_SUPER
  this_class: #2                          // argonaut/JBool
  super_class: #4                         // argonaut/Json
  interfaces: 0, fields: 1, methods: 16, attributes: 4
Constant pool:
    #1 = Utf8               argonaut/JBool
    #2 = Class              #1            // argonaut/JBool
    #3 = Utf8               argonaut/Json
    #4 = Class              #3            // argonaut/Json
    #5 = Utf8               Json.scala
    #6 = Utf8               Lscala/reflect/ScalaSignature;
    #7 = Utf8               bytes
    #8 = Utf8               \u0006\u0005\u0005\u0015b!B\u000b\u0017\u0001ZA\u0002\u0002\u0003\u0019\u0001\u0005+\u0007I\u0011A\u0019\t\u0011U\u0002!\u0011#Q\u0001\nIBQA\u000e\u0001\u0005\u0002]BqA\u000f\u0001\u0002\u0002\u0013\u00051\bC\u0004>\u0001E\u0005I\u0011\u0001 \t\u000f%\u0003\u0011\u0011!C!\u0015\"91\u000bAA\u0001\n\u0003!\u0006b\u0002-\u0001\u0003\u0003%\t!\u0017\u0005\b?\u0002\t\t\u0011\"\u0011a\u0011\u001d9\u0007!!A\u0005\u0002!DqA\u001b\u0001\u0002\u0002\u0013\u00053\u000eC\u0004n\u0001\u0005\u0005I\u0011\t8\t\u000f=\u0004\u0011\u0011!C!a\u001eA!OFA\u0001\u0012\u000312O\u0002\u0005\u0016-\u0005\u0005\t\u0012\u0001\fu\u0011\u00191t\u0002\"\u0001\u0002\u0002!I\u00111A\b\u0002\u0002\u0013\u0015\u0013Q\u0001\u0005\n\u0003\u000fy\u0011\u0011!CA\u0003\u0013A\u0011\"!\u0004\u0010\u0003\u0003%\t)a\u0004\t\u0013\u0005mq\"!A\u0005\n\u0005u!!\u0002&C_>d\'\"A\f\u0002\u0011\u0005\u0014xm\u001c8bkR\u001cB\u0001A\r\u001eGA\u0011!dG\u0007\u0002-%\u0011AD\u0006\u0002\u0005\u0015N|g\u000e\u0005\u0002\u001fC5\tqDC\u0001!\u0003\u0015\u00198-\u00197b\u0013\t\u0011sDA\u0004Qe>$Wo\u0019;\u0011\u0005\u0011jcBA\u0013,\u001d\t1#&D\u0001(\u0015\tA\u0013&\u0001\u0004=e>|GOP\u0002\u0001\u0013\u0005\u0001\u0013B\u0001\u0017 \u0003\u001d\u0001\u0018mY6bO\u0016L!AL\u0018\u0003\u0019M+\'/[1mSj\f\'\r\\3\u000b\u00051z\u0012!\u00012\u0016\u0003I\u0002\"AH\u001a\n\u0005Qz\"a\u0002\"p_2,\u0017M\\\u0001\u0003E\u0002\na\u0001P5oSRtDC\u0001\u001d:!\tQ\u0002\u0001C\u00031\u0007\u0001\u0007!\'\u0001\u0003d_BLHC\u0001\u001d=\u0011\u001d\u0001D\u0001%AA\u0002I\nabY8qs\u0012\"WMZ1vYR$\u0013\'F\u0001@U\t\u0011\u0004iK\u0001B!\t\u0011u)D\u0001D\u0015\t!U)A\u0005v]\u000eDWmY6fI*\u0011aiH\u0001\u000bC:tw\u000e^1uS>t\u0017B\u0001%D\u0005E)hn\u00195fG.,GMV1sS\u0006t7-Z\u0001\u000eaJ|G-^2u!J,g-\u001b=\u0016\u0003-\u0003\"\u0001T)\u000e\u00035S!AT(\u0002\t1\fgn\u001a\u0006\u0002!\u0006!!.\u0019<b\u0013\t\u0011VJ\u0001\u0004TiJLgnZ\u0001\raJ|G-^2u\u0003JLG/_\u000b\u0002+B\u0011aDV\u0005\u0003/~\u00111!\u00138u\u00039\u0001(o\u001c3vGR,E.Z7f]R$\"AW/\u0011\u0005yY\u0016B\u0001/ \u0005\r\te.\u001f\u0005\b=\"\t\t\u00111\u0001V\u0003\rAH%M\u0001\u0010aJ|G-^2u\u0013R,\'/\u0019;peV\t\u0011\rE\u0002cKjk\u0011a\u0019\u0006\u0003I~\t!bY8mY\u0016\u001cG/[8o\u0013\t17M\u0001\u0005Ji\u0016\u0014\u0018\r^8s\u0003!\u0019\u0017M\\#rk\u0006dGC\u0001\u001aj\u0011\u001dq&\"!AA\u0002i\u000b!\u0003\u001d:pIV\u001cG/\u00127f[\u0016tGOT1nKR\u00111\n\u001c\u0005\b=.\t\t\u00111\u0001V\u0003!A\u0017m\u001d5D_\u0012,G#A+\u0002\r\u0015\fX/\u00197t)\t\u0011\u0014\u000fC\u0004_\u001b\u0005\u0005\t\u0019\u0001.\u0002\u000b)\u0013un\u001c7\u0011\u0005iy1cA\bvwB!a/\u001f\u001a9\u001b\u00059(B\u0001= \u0003\u001d\u0011XO\u001c;j[\u0016L!A_<\u0003#\u0005\u00137\u000f\u001e:bGR4UO\\2uS>t\u0017\u0007\u0005\u0002}\u007f6\tQP\u0003\u0002\u007f\u001f\u0006\u0011\u0011n\\\u0005\u0003]u$\u0012a]\u0001\ti>\u001cFO]5oOR\t1*A\u0003baBd\u0017\u0010F\u00029\u0003\u0017AQ\u0001\r\nA\u0002I\nq!\u001e8baBd\u0017\u0010\u0006\u0003\u0002\u0012\u0005]\u0001\u0003\u0002\u0010\u0002\u0014IJ1!!\u0006 \u0005\u0019y\u0005\u000f^5p]\"A\u0011\u0011D\n\u0002\u0002\u0003\u0007\u0001(A\u0002yIA\nAb\u001e:ji\u0016\u0014V\r\u001d7bG\u0016$\"!a\b\u0011\u00071\u000b\t#C\u0002\u0002$5\u0013aa\u00142kK\u000e$\b
    #9 = Utf8               b
   #10 = Utf8               Z
   #11 = Utf8               unapply
   #12 = Utf8               (Largonaut/JBool;)Lscala/Option;
   #13 = Utf8               (Largonaut/JBool;)Lscala/Option<Ljava/lang/Object;>;
   #14 = Utf8               x$0
   #15 = Utf8               argonaut/JBool$
   #16 = Class              #15           // argonaut/JBool$
   #17 = Utf8               MODULE$
   #18 = Utf8               Largonaut/JBool$;
   #19 = NameAndType        #17:#18       // MODULE$:Largonaut/JBool$;
   #20 = Fieldref           #16.#19       // argonaut/JBool$.MODULE$:Largonaut/JBool$;
   #21 = NameAndType        #11:#12       // unapply:(Largonaut/JBool;)Lscala/Option;
   #22 = Methodref          #16.#21       // argonaut/JBool$.unapply:(Largonaut/JBool;)Lscala/Option;
   #23 = Utf8               apply
   #24 = Utf8               (Z)Largonaut/JBool;
   #25 = NameAndType        #23:#24       // apply:(Z)Largonaut/JBool;
   #26 = Methodref          #16.#25       // argonaut/JBool$.apply:(Z)Largonaut/JBool;
   #27 = Utf8               andThen
   #28 = Utf8               (Lscala/Function1;)Lscala/Function1;
   #29 = Utf8               <A:Ljava/lang/Object;>(Lscala/Function1<Largonaut/JBool;TA;>;)Lscala/Function1<Ljava/lang/Object;TA;>;
   #30 = Utf8               g
   #31 = NameAndType        #27:#28       // andThen:(Lscala/Function1;)Lscala/Function1;
   #32 = Methodref          #16.#31       // argonaut/JBool$.andThen:(Lscala/Function1;)Lscala/Function1;
   #33 = Utf8               compose
   #34 = Utf8               <A:Ljava/lang/Object;>(Lscala/Function1<TA;Ljava/lang/Object;>;)Lscala/Function1<TA;Largonaut/JBool;>;
   #35 = NameAndType        #33:#28       // compose:(Lscala/Function1;)Lscala/Function1;
   #36 = Methodref          #16.#35       // argonaut/JBool$.compose:(Lscala/Function1;)Lscala/Function1;
   #37 = Utf8               ()Z
   #38 = NameAndType        #9:#10        // b:Z
   #39 = Fieldref           #2.#38        // argonaut/JBool.b:Z
   #40 = Utf8               this
   #41 = Utf8               Largonaut/JBool;
   #42 = Utf8               copy
   #43 = Utf8               <init>
   #44 = Utf8               (Z)V
   #45 = NameAndType        #43:#44       // "<init>":(Z)V
   #46 = Methodref          #2.#45        // argonaut/JBool."<init>":(Z)V
   #47 = Utf8               copy$default$1
   #48 = NameAndType        #9:#37        // b:()Z
   #49 = Methodref          #2.#48        // argonaut/JBool.b:()Z
   #50 = Utf8               productPrefix
   #51 = Utf8               ()Ljava/lang/String;
   #52 = Utf8               JBool
   #53 = String             #52           // JBool
   #54 = Utf8               productArity
   #55 = Utf8               ()I
   #56 = Utf8               productElement
   #57 = Utf8               (I)Ljava/lang/Object;
   #58 = Utf8               x$1
   #59 = Utf8               scala/runtime/BoxesRunTime
   #60 = Class              #59           // scala/runtime/BoxesRunTime
   #61 = Utf8               boxToBoolean
   #62 = Utf8               (Z)Ljava/lang/Boolean;
   #63 = NameAndType        #61:#62       // boxToBoolean:(Z)Ljava/lang/Boolean;
   #64 = Methodref          #60.#63       // scala/runtime/BoxesRunTime.boxToBoolean:(Z)Ljava/lang/Boolean;
   #65 = Utf8               scala/runtime/Statics
   #66 = Class              #65           // scala/runtime/Statics
   #67 = Utf8               ioobe
   #68 = NameAndType        #67:#57       // ioobe:(I)Ljava/lang/Object;
   #69 = Methodref          #66.#68       // scala/runtime/Statics.ioobe:(I)Ljava/lang/Object;
   #70 = Utf8               I
   #71 = Utf8               java/lang/Object
   #72 = Class              #71           // java/lang/Object
   #73 = Utf8               productIterator
   #74 = Utf8               ()Lscala/collection/Iterator;
   #75 = Utf8               ()Lscala/collection/Iterator<Ljava/lang/Object;>;
   #76 = Utf8               scala/runtime/ScalaRunTime$
   #77 = Class              #76           // scala/runtime/ScalaRunTime$
   #78 = Utf8               Lscala/runtime/ScalaRunTime$;
   #79 = NameAndType        #17:#78       // MODULE$:Lscala/runtime/ScalaRunTime$;
   #80 = Fieldref           #77.#79       // scala/runtime/ScalaRunTime$.MODULE$:Lscala/runtime/ScalaRunTime$;
   #81 = Utf8               typedProductIterator
   #82 = Utf8               (Lscala/Product;)Lscala/collection/Iterator;
   #83 = NameAndType        #81:#82       // typedProductIterator:(Lscala/Product;)Lscala/collection/Iterator;
   #84 = Methodref          #77.#83       // scala/runtime/ScalaRunTime$.typedProductIterator:(Lscala/Product;)Lscala/collection/Iterator;
   #85 = Utf8               canEqual
   #86 = Utf8               (Ljava/lang/Object;)Z
   #87 = Utf8               Ljava/lang/Object;
   #88 = Utf8               productElementName
   #89 = Utf8               (I)Ljava/lang/String;
   #90 = String             #9            // b
   #91 = Utf8               java/lang/String
   #92 = Class              #91           // java/lang/String
   #93 = Utf8               hashCode
   #94 = Integer            -889275714
   #95 = NameAndType        #50:#51       // productPrefix:()Ljava/lang/String;
   #96 = Methodref          #2.#95        // argonaut/JBool.productPrefix:()Ljava/lang/String;
   #97 = NameAndType        #93:#55       // hashCode:()I
   #98 = Methodref          #92.#97       // java/lang/String.hashCode:()I
   #99 = Utf8               mix
  #100 = Utf8               (II)I
  #101 = NameAndType        #99:#100      // mix:(II)I
  #102 = Methodref          #66.#101      // scala/runtime/Statics.mix:(II)I
  #103 = Utf8               finalizeHash
  #104 = NameAndType        #103:#100     // finalizeHash:(II)I
  #105 = Methodref          #66.#104      // scala/runtime/Statics.finalizeHash:(II)I
  #106 = Utf8               equals
  #107 = NameAndType        #85:#86       // canEqual:(Ljava/lang/Object;)Z
  #108 = Methodref          #2.#107       // argonaut/JBool.canEqual:(Ljava/lang/Object;)Z
  #109 = Utf8               ()V
  #110 = NameAndType        #43:#109      // "<init>":()V
  #111 = Methodref          #4.#110       // argonaut/Json."<init>":()V
  #112 = Utf8               Code
  #113 = Utf8               Signature
  #114 = Utf8               MethodParameters
  #115 = Utf8               LineNumberTable
  #116 = Utf8               LocalVariableTable
  #117 = Utf8               StackMapTable
  #118 = Utf8               SourceFile
  #119 = Utf8               RuntimeVisibleAnnotations
  #120 = Utf8               ScalaInlineInfo
  #121 = Utf8               ScalaSig
{
  private final boolean b;
    descriptor: Z
    flags: (0x0012) ACC_PRIVATE, ACC_FINAL

  public static scala.Option<java.lang.Object> unapply(argonaut.JBool);
    descriptor: (Largonaut/JBool;)Lscala/Option;
    flags: (0x0009) ACC_PUBLIC, ACC_STATIC
    Code:
      stack=2, locals=1, args_size=1
         0: getstatic     #20                 // Field argonaut/JBool$.MODULE$:Largonaut/JBool$;
         3: aload_0
         4: invokevirtual #22                 // Method argonaut/JBool$.unapply:(Largonaut/JBool;)Lscala/Option;
         7: areturn
    Signature: #13                          // (Largonaut/JBool;)Lscala/Option<Ljava/lang/Object;>;
    MethodParameters:
      Name                           Flags
      x$0                            final

  public static argonaut.JBool apply(boolean);
    descriptor: (Z)Largonaut/JBool;
    flags: (0x0009) ACC_PUBLIC, ACC_STATIC
    Code:
      stack=2, locals=1, args_size=1
         0: getstatic     #20                 // Field argonaut/JBool$.MODULE$:Largonaut/JBool$;
         3: iload_0
         4: invokevirtual #26                 // Method argonaut/JBool$.apply:(Z)Largonaut/JBool;
         7: areturn
    MethodParameters:
      Name                           Flags
      b                              final

  public static <A extends java.lang.Object> scala.Function1<java.lang.Object, A> andThen(scala.Function1<argonaut.JBool, A>);
    descriptor: (Lscala/Function1;)Lscala/Function1;
    flags: (0x0009) ACC_PUBLIC, ACC_STATIC
    Code:
      stack=2, locals=1, args_size=1
         0: getstatic     #20                 // Field argonaut/JBool$.MODULE$:Largonaut/JBool$;
         3: aload_0
         4: invokevirtual #32                 // Method argonaut/JBool$.andThen:(Lscala/Function1;)Lscala/Function1;
         7: areturn
    Signature: #29                          // <A:Ljava/lang/Object;>(Lscala/Function1<Largonaut/JBool;TA;>;)Lscala/Function1<Ljava/lang/Object;TA;>;
    MethodParameters:
      Name                           Flags
      g                              final

  public static <A extends java.lang.Object> scala.Function1<A, argonaut.JBool> compose(scala.Function1<A, java.lang.Object>);
    descriptor: (Lscala/Function1;)Lscala/Function1;
    flags: (0x0009) ACC_PUBLIC, ACC_STATIC
    Code:
      stack=2, locals=1, args_size=1
         0: getstatic     #20                 // Field argonaut/JBool$.MODULE$:Largonaut/JBool$;
         3: aload_0
         4: invokevirtual #36                 // Method argonaut/JBool$.compose:(Lscala/Function1;)Lscala/Function1;
         7: areturn
    Signature: #34                          // <A:Ljava/lang/Object;>(Lscala/Function1<TA;Ljava/lang/Object;>;)Lscala/Function1<TA;Largonaut/JBool;>;
    MethodParameters:
      Name                           Flags
      g                              final

  public boolean b();
    descriptor: ()Z
    flags: (0x0001) ACC_PUBLIC
    Code:
      stack=1, locals=1, args_size=1
         0: aload_0
         1: getfield      #39                 // Field b:Z
         4: ireturn
      LineNumberTable:
        line 480: 0
      LocalVariableTable:
        Start  Length  Slot  Name   Signature
            0       5     0  this   Largonaut/JBool;

  public argonaut.JBool copy(boolean);
    descriptor: (Z)Largonaut/JBool;
    flags: (0x0001) ACC_PUBLIC
    Code:
      stack=3, locals=2, args_size=2
         0: new           #2                  // class argonaut/JBool
         3: dup
         4: iload_1
         5: invokespecial #46                 // Method "<init>":(Z)V
         8: areturn
      LineNumberTable:
        line 480: 0
      LocalVariableTable:
        Start  Length  Slot  Name   Signature
            0       9     0  this   Largonaut/JBool;
            0       9     1     b   Z
    MethodParameters:
      Name                           Flags
      b                              final

  public boolean copy$default$1();
    descriptor: ()Z
    flags: (0x0001) ACC_PUBLIC
    Code:
      stack=1, locals=1, args_size=1
         0: aload_0
         1: invokevirtual #49                 // Method b:()Z
         4: ireturn
      LineNumberTable:
        line 480: 0
      LocalVariableTable:
        Start  Length  Slot  Name   Signature
            0       5     0  this   Largonaut/JBool;

  public java.lang.String productPrefix();
    descriptor: ()Ljava/lang/String;
    flags: (0x0001) ACC_PUBLIC
    Code:
      stack=1, locals=1, args_size=1
         0: ldc           #53                 // String JBool
         2: areturn
      LineNumberTable:
        line 480: 0
      LocalVariableTable:
        Start  Length  Slot  Name   Signature
            0       3     0  this   Largonaut/JBool;

  public int productArity();
    descriptor: ()I
    flags: (0x0001) ACC_PUBLIC
    Code:
      stack=1, locals=1, args_size=1
         0: iconst_1
         1: ireturn
      LineNumberTable:
        line 480: 0
      LocalVariableTable:
        Start  Length  Slot  Name   Signature
            0       2     0  this   Largonaut/JBool;

  public java.lang.Object productElement(int);
    descriptor: (I)Ljava/lang/Object;
    flags: (0x0001) ACC_PUBLIC
    Code:
      stack=1, locals=3, args_size=2
         0: iload_1
         1: istore_2
         2: iload_2
         3: tableswitch   { // 0 to 0
                       0: 20
                 default: 30
            }
        20: aload_0
        21: invokevirtual #49                 // Method b:()Z
        24: invokestatic  #64                 // Method scala/runtime/BoxesRunTime.boxToBoolean:(Z)Ljava/lang/Boolean;
        27: goto          37
        30: iload_1
        31: invokestatic  #69                 // Method scala/runtime/Statics.ioobe:(I)Ljava/lang/Object;
        34: goto          37
        37: areturn
      StackMapTable: number_of_entries = 3
        frame_type = 252 /* append */
          offset_delta = 20
          locals = [ int ]
        frame_type = 9 /* same */
        frame_type = 70 /* same_locals_1_stack_item */
          stack = [ class java/lang/Object ]
      LineNumberTable:
        line 480: 0
      LocalVariableTable:
        Start  Length  Slot  Name   Signature
            0      38     0  this   Largonaut/JBool;
            0      38     1   x$1   I
    MethodParameters:
      Name                           Flags
      x$1                            final

  public scala.collection.Iterator<java.lang.Object> productIterator();
    descriptor: ()Lscala/collection/Iterator;
    flags: (0x0001) ACC_PUBLIC
    Code:
      stack=2, locals=1, args_size=1
         0: getstatic     #80                 // Field scala/runtime/ScalaRunTime$.MODULE$:Lscala/runtime/ScalaRunTime$;
         3: aload_0
         4: invokevirtual #84                 // Method scala/runtime/ScalaRunTime$.typedProductIterator:(Lscala/Product;)Lscala/collection/Iterator;
         7: areturn
      LineNumberTable:
        line 480: 0
      LocalVariableTable:
        Start  Length  Slot  Name   Signature
            0       8     0  this   Largonaut/JBool;
    Signature: #75                          // ()Lscala/collection/Iterator<Ljava/lang/Object;>;

  public boolean canEqual(java.lang.Object);
    descriptor: (Ljava/lang/Object;)Z
    flags: (0x0001) ACC_PUBLIC
    Code:
      stack=1, locals=2, args_size=2
         0: aload_1
         1: instanceof    #2                  // class argonaut/JBool
         4: ireturn
      LineNumberTable:
        line 480: 0
      LocalVariableTable:
        Start  Length  Slot  Name   Signature
            0       5     0  this   Largonaut/JBool;
            0       5     1   x$1   Ljava/lang/Object;
    MethodParameters:
      Name                           Flags
      x$1                            final

  public java.lang.String productElementName(int);
    descriptor: (I)Ljava/lang/String;
    flags: (0x0001) ACC_PUBLIC
    Code:
      stack=1, locals=3, args_size=2
         0: iload_1
         1: istore_2
         2: iload_2
         3: tableswitch   { // 0 to 0
                       0: 20
                 default: 25
            }
        20: ldc           #90                 // String b
        22: goto          35
        25: iload_1
        26: invokestatic  #69                 // Method scala/runtime/Statics.ioobe:(I)Ljava/lang/Object;
        29: checkcast     #92                 // class java/lang/String
        32: goto          35
        35: areturn
      StackMapTable: number_of_entries = 3
        frame_type = 252 /* append */
          offset_delta = 20
          locals = [ int ]
        frame_type = 4 /* same */
        frame_type = 73 /* same_locals_1_stack_item */
          stack = [ class java/lang/String ]
      LineNumberTable:
        line 480: 0
      LocalVariableTable:
        Start  Length  Slot  Name   Signature
            0      36     0  this   Largonaut/JBool;
            0      36     1   x$1   I
    MethodParameters:
      Name                           Flags
      x$1                            final

  public int hashCode();
    descriptor: ()I
    flags: (0x0001) ACC_PUBLIC
    Code:
      stack=2, locals=2, args_size=1
         0: ldc           #94                 // int -889275714
         2: istore_1
         3: iload_1
         4: aload_0
         5: invokevirtual #96                 // Method productPrefix:()Ljava/lang/String;
         8: invokevirtual #98                 // Method java/lang/String.hashCode:()I
        11: invokestatic  #102                // Method scala/runtime/Statics.mix:(II)I
        14: istore_1
        15: iload_1
        16: aload_0
        17: invokevirtual #49                 // Method b:()Z
        20: ifeq          29
        23: sipush        1231
        26: goto          32
        29: sipush        1237
        32: invokestatic  #102                // Method scala/runtime/Statics.mix:(II)I
        35: istore_1
        36: iload_1
        37: iconst_1
        38: invokestatic  #105                // Method scala/runtime/Statics.finalizeHash:(II)I
        41: ireturn
      StackMapTable: number_of_entries = 2
        frame_type = 255 /* full_frame */
          offset_delta = 29
          locals = [ class argonaut/JBool, int ]
          stack = [ int ]
        frame_type = 255 /* full_frame */
          offset_delta = 2
          locals = [ class argonaut/JBool, int ]
          stack = [ int, int ]
      LineNumberTable:
        line 480: 0
      LocalVariableTable:
        Start  Length  Slot  Name   Signature
            0      42     0  this   Largonaut/JBool;

  public boolean equals(java.lang.Object);
    descriptor: (Ljava/lang/Object;)Z
    flags: (0x0001) ACC_PUBLIC
    Code:
      stack=2, locals=5, args_size=2
         0: aload_0
         1: aload_1
         2: if_acmpeq     66
         5: aload_1
         6: astore_3
         7: aload_3
         8: instanceof    #2                  // class argonaut/JBool
        11: ifeq          19
        14: iconst_1
        15: istore_2
        16: goto          27
        19: goto          22
        22: iconst_0
        23: istore_2
        24: goto          27
        27: iload_2
        28: ifeq          70
        31: aload_1
        32: checkcast     #2                  // class argonaut/JBool
        35: astore        4
        37: aload_0
        38: invokevirtual #49                 // Method b:()Z
        41: aload         4
        43: invokevirtual #49                 // Method b:()Z
        46: if_icmpne     62
        49: aload         4
        51: aload_0
        52: invokevirtual #108                // Method canEqual:(Ljava/lang/Object;)Z
        55: ifeq          62
        58: iconst_1
        59: goto          63
        62: iconst_0
        63: ifeq          70
        66: iconst_1
        67: goto          71
        70: iconst_0
        71: ireturn
      StackMapTable: number_of_entries = 8
        frame_type = 253 /* append */
          offset_delta = 19
          locals = [ top, class java/lang/Object ]
        frame_type = 2 /* same */
        frame_type = 255 /* full_frame */
          offset_delta = 4
          locals = [ class argonaut/JBool, class java/lang/Object, int, class java/lang/Object ]
          stack = []
        frame_type = 252 /* append */
          offset_delta = 34
          locals = [ class argonaut/JBool ]
        frame_type = 64 /* same_locals_1_stack_item */
          stack = [ int ]
        frame_type = 248 /* chop */
          offset_delta = 2
        frame_type = 253 /* append */
          offset_delta = 3
          locals = [ int, class java/lang/Object ]
        frame_type = 255 /* full_frame */
          offset_delta = 0
          locals = [ class argonaut/JBool, class java/lang/Object ]
          stack = [ int ]
      LineNumberTable:
        line 480: 0
      LocalVariableTable:
        Start  Length  Slot  Name   Signature
            0      72     0  this   Largonaut/JBool;
            0      72     1   x$1   Ljava/lang/Object;
    MethodParameters:
      Name                           Flags
      x$1                            final

  public argonaut.JBool(boolean);
    descriptor: (Z)V
    flags: (0x0001) ACC_PUBLIC
    Code:
      stack=2, locals=2, args_size=2
         0: aload_0
         1: iload_1
         2: putfield      #39                 // Field b:Z
         5: aload_0
         6: invokespecial #111                // Method argonaut/Json."<init>":()V
         9: return
      LineNumberTable:
        line 480: 0
      LocalVariableTable:
        Start  Length  Slot  Name   Signature
            0      10     0  this   Largonaut/JBool;
            0      10     1     b   Z
    MethodParameters:
      Name                           Flags
      b                              final
}
SourceFile: "Json.scala"
RuntimeVisibleAnnotations:
  0: #6(#7=s#8)
    scala.reflect.ScalaSignature(
      bytes="\u0006\u0005\u0005\u0015b!B\u000b\u0017\u0001ZA\u0002\u0002\u0003\u0019\u0001\u0005+\u0007I\u0011A\u0019\t\u0011U\u0002!\u0011#Q\u0001\nIBQA\u000e\u0001\u0005\u0002]BqA\u000f\u0001\u0002\u0002\u0013\u00051\bC\u0004>\u0001E\u0005I\u0011\u0001 \t\u000f%\u0003\u0011\u0011!C!\u0015\"91\u000bAA\u0001\n\u0003!\u0006b\u0002-\u0001\u0003\u0003%\t!\u0017\u0005\b?\u0002\t\t\u0011\"\u0011a\u0011\u001d9\u0007!!A\u0005\u0002!DqA\u001b\u0001\u0002\u0002\u0013\u00053\u000eC\u0004n\u0001\u0005\u0005I\u0011\t8\t\u000f=\u0004\u0011\u0011!C!a\u001eA!OFA\u0001\u0012\u000312O\u0002\u0005\u0016-\u0005\u0005\t\u0012\u0001\fu\u0011\u00191t\u0002\"\u0001\u0002\u0002!I\u00111A\b\u0002\u0002\u0013\u0015\u0013Q\u0001\u0005\n\u0003\u000fy\u0011\u0011!CA\u0003\u0013A\u0011\"!\u0004\u0010\u0003\u0003%\t)a\u0004\t\u0013\u0005mq\"!A\u0005\n\u0005u!!\u0002&C_>d\'\"A\f\u0002\u0011\u0005\u0014xm\u001c8bkR\u001cB\u0001A\r\u001eGA\u0011!dG\u0007\u0002-%\u0011AD\u0006\u0002\u0005\u0015N|g\u000e\u0005\u0002\u001fC5\tqDC\u0001!\u0003\u0015\u00198-\u00197b\u0013\t\u0011sDA\u0004Qe>$Wo\u0019;\u0011\u0005\u0011jcBA\u0013,\u001d\t1#&D\u0001(\u0015\tA\u0013&\u0001\u0004=e>|GOP\u0002\u0001\u0013\u0005\u0001\u0013B\u0001\u0017 \u0003\u001d\u0001\u0018mY6bO\u0016L!AL\u0018\u0003\u0019M+\'/[1mSj\f\'\r\\3\u000b\u00051z\u0012!\u00012\u0016\u0003I\u0002\"AH\u001a\n\u0005Qz\"a\u0002\"p_2,\u0017M\\\u0001\u0003E\u0002\na\u0001P5oSRtDC\u0001\u001d:!\tQ\u0002\u0001C\u00031\u0007\u0001\u0007!\'\u0001\u0003d_BLHC\u0001\u001d=\u0011\u001d\u0001D\u0001%AA\u0002I\nabY8qs\u0012\"WMZ1vYR$\u0013\'F\u0001@U\t\u0011\u0004iK\u0001B!\t\u0011u)D\u0001D\u0015\t!U)A\u0005v]\u000eDWmY6fI*\u0011aiH\u0001\u000bC:tw\u000e^1uS>t\u0017B\u0001%D\u0005E)hn\u00195fG.,GMV1sS\u0006t7-Z\u0001\u000eaJ|G-^2u!J,g-\u001b=\u0016\u0003-\u0003\"\u0001T)\u000e\u00035S!AT(\u0002\t1\fgn\u001a\u0006\u0002!\u0006!!.\u0019<b\u0013\t\u0011VJ\u0001\u0004TiJLgnZ\u0001\raJ|G-^2u\u0003JLG/_\u000b\u0002+B\u0011aDV\u0005\u0003/~\u00111!\u00138u\u00039\u0001(o\u001c3vGR,E.Z7f]R$\"AW/\u0011\u0005yY\u0016B\u0001/ \u0005\r\te.\u001f\u0005\b=\"\t\t\u00111\u0001V\u0003\rAH%M\u0001\u0010aJ|G-^2u\u0013R,\'/\u0019;peV\t\u0011\rE\u0002cKjk\u0011a\u0019\u0006\u0003I~\t!bY8mY\u0016\u001cG/[8o\u0013\t17M\u0001\u0005Ji\u0016\u0014\u0018\r^8s\u0003!\u0019\u0017M\\#rk\u0006dGC\u0001\u001aj\u0011\u001dq&\"!AA\u0002i\u000b!\u0003\u001d:pIV\u001cG/\u00127f[\u0016tGOT1nKR\u00111\n\u001c\u0005\b=.\t\t\u00111\u0001V\u0003!A\u0017m\u001d5D_\u0012,G#A+\u0002\r\u0015\fX/\u00197t)\t\u0011\u0014\u000fC\u0004_\u001b\u0005\u0005\t\u0019\u0001.\u0002\u000b)\u0013un\u001c7\u0011\u0005iy1cA\bvwB!a/\u001f\u001a9\u001b\u00059(B\u0001= \u0003\u001d\u0011XO\u001c;j[\u0016L!A_<\u0003#\u0005\u00137\u000f\u001e:bGR4UO\\2uS>t\u0017\u0007\u0005\u0002}\u007f6\tQP\u0003\u0002\u007f\u001f\u0006\u0011\u0011n\\\u0005\u0003]u$\u0012a]\u0001\ti>\u001cFO]5oOR\t1*A\u0003baBd\u0017\u0010F\u00029\u0003\u0017AQ\u0001\r\nA\u0002I\nq!\u001e8baBd\u0017\u0010\u0006\u0003\u0002\u0012\u0005]\u0001\u0003\u0002\u0010\u0002\u0014IJ1!!\u0006 \u0005\u0019y\u0005\u000f^5p]\"A\u0011\u0011D\n\u0002\u0002\u0003\u0007\u0001(A\u0002yIA\nAb\u001e:ji\u0016\u0014V\r\u001d7bG\u0016$\"!a\b\u0011\u00071\u000b\t#C\u0002\u0002$5\u0013aa\u00142kK\u000e$\b"
    )
  ScalaInlineInfo: length = 0x40 (unknown attribute)
   01 00 00 0C 00 2B 00 2C 00 00 09 00 25 00 00 55
   00 56 00 00 2A 00 18 00 00 2F 00 25 00 00 6A 00
   56 00 00 5D 00 37 00 00 36 00 37 00 00 38 00 39
   00 00 58 00 59 00 00 49 00 4A 00 00 32 00 33 00

  ScalaSig: length = 0x3 (unknown attribute)
   05 02 00
