Classfile /Users/mw/Projects/slang-braindump/.jar/jar8/assemble/slang-braindump/assemble/content/argonaut/JObject.class
  Last modified May 29, 2022; size 4328 bytes
  SHA-256 checksum 4a1e7a3d773ccc110840c401845a7b10ed0888515c6be56e8ae516890567a9e3
  Compiled from "Json.scala"
public class argonaut.JObject extends argonaut.Json
  minor version: 0
  major version: 52
  flags: (0x0021) ACC_PUBLIC, ACC_SUPER
  this_class: #2                          // argonaut/JObject
  super_class: #4                         // argonaut/Json
  interfaces: 0, fields: 1, methods: 16, attributes: 4
Constant pool:
    #1 = Utf8               argonaut/JObject
    #2 = Class              #1            // argonaut/JObject
    #3 = Utf8               argonaut/Json
    #4 = Class              #3            // argonaut/Json
    #5 = Utf8               Json.scala
    #6 = Utf8               Lscala/reflect/ScalaSignature;
    #7 = Utf8               bytes
    #8 = Utf8               \u0006\u0005\u0005-b!B\u000b\u0017\u0001ZA\u0002\u0002\u0003\u0019\u0001\u0005+\u0007I\u0011A\u0019\t\u0011U\u0002!\u0011#Q\u0001\nIBQA\u000e\u0001\u0005\u0002]BqA\u000f\u0001\u0002\u0002\u0013\u00051\bC\u0004>\u0001E\u0005I\u0011\u0001 \t\u000f%\u0003\u0011\u0011!C!\u0015\"91\u000bAA\u0001\n\u0003!\u0006b\u0002-\u0001\u0003\u0003%\t!\u0017\u0005\b?\u0002\t\t\u0011\"\u0011a\u0011\u001d9\u0007!!A\u0005\u0002!Dq!\u001c\u0001\u0002\u0002\u0013\u0005c\u000eC\u0004q\u0001\u0005\u0005I\u0011I9\t\u000fI\u0004\u0011\u0011!C!g\u001eAQOFA\u0001\u0012\u00031bO\u0002\u0005\u0016-\u0005\u0005\t\u0012\u0001\fx\u0011\u00191t\u0002\"\u0001\u0002\b!I\u0011\u0011B\b\u0002\u0002\u0013\u0015\u00131\u0002\u0005\n\u0003\u001by\u0011\u0011!CA\u0003\u001fA\u0011\"a\u0005\u0010\u0003\u0003%\t)!\u0006\t\u0013\u0005\u0005r\"!A\u0005\n\u0005\r\"a\u0002&PE*,7\r\u001e\u0006\u0002/\u0005A\u0011M]4p]\u0006,Ho\u0005\u0003\u00013u\u0019\u0003C\u0001\u000e\u001c\u001b\u00051\u0012B\u0001\u000f\u0017\u0005\u0011Q5o\u001c8\u0011\u0005y\tS\"A\u0010\u000b\u0003\u0001\nQa]2bY\u0006L!AI\u0010\u0003\u000fA\u0013x\u000eZ;diB\u0011A%\f\b\u0003K-r!A\n\u0016\u000e\u0003\u001dR!\u0001K\u0015\u0002\rq\u0012xn\u001c;?\u0007\u0001I\u0011\u0001I\u0005\u0003Y}\tq\u0001]1dW\u0006<W-\u0003\u0002/_\ta1+\u001a:jC2L\'0\u00192mK*\u0011AfH\u0001\u0002_V\t!\u0007\u0005\u0002\u001bg%\u0011AG\u0006\u0002\u000b\u0015N|gn\u00142kK\u000e$\u0018AA8!\u0003\u0019a\u0014N\\5u}Q\u0011\u0001(\u000f\t\u00035\u0001AQ\u0001M\u0002A\u0002I\nAaY8qsR\u0011\u0001\b\u0010\u0005\ba\u0011\u0001\n\u00111\u00013\u00039\u0019w\u000e]=%I\u00164\u0017-\u001e7uIE*\u0012a\u0010\u0016\u0003e\u0001[\u0013!\u0011\t\u0003\u0005\u001ek\u0011a\u0011\u0006\u0003\t\u0016\u000b\u0011\"\u001e8dQ\u0016\u001c7.\u001a3\u000b\u0005\u0019{\u0012AC1o]>$\u0018\r^5p]&\u0011\u0001j\u0011\u0002\u0012k:\u001c\u0007.Z2lK\u00124\u0016M]5b]\u000e,\u0017!\u00049s_\u0012,8\r\u001e)sK\u001aL\u00070F\u0001L!\ta\u0015+D\u0001N\u0015\tqu*\u0001\u0003mC:<\'\"\u0001)\u0002\t)\fg/Y\u0005\u0003%6\u0013aa\u0015;sS:<\u0017\u0001\u00049s_\u0012,8\r^!sSRLX#A+\u0011\u0005y1\u0016BA, \u0005\rIe\u000e^\u0001\u000faJ|G-^2u\u000b2,W.\u001a8u)\tQV\f\u0005\u0002\u001f7&\u0011Al\b\u0002\u0004\u0003:L\bb\u00020\t\u0003\u0003\u0005\r!V\u0001\u0004q\u0012\n\u0014a\u00049s_\u0012,8\r^%uKJ\fGo\u001c:\u0016\u0003\u0005\u00042AY3[\u001b\u0005\u0019\'B\u00013 \u0003)\u0019w\u000e\u001c7fGRLwN\\\u0005\u0003M\u000e\u0014\u0001\"\u0013;fe\u0006$xN]\u0001\tG\u0006tW)];bYR\u0011\u0011\u000e\u001c\t\u0003=)L!a[\u0010\u0003\u000f\t{w\u000e\\3b]\"9aLCA\u0001\u0002\u0004Q\u0016A\u00059s_\u0012,8\r^#mK6,g\u000e\u001e(b[\u0016$\"aS8\t\u000fy[\u0011\u0011!a\u0001+\u0006A\u0001.Y:i\u0007>$W\rF\u0001V\u0003\u0019)\u0017/^1mgR\u0011\u0011\u000e\u001e\u0005\b=6\t\t\u00111\u0001[\u0003\u001dQuJ\u00196fGR\u0004\"AG\b\u0014\u0007=Ah\u0010\u0005\u0003zyJBT\"\u0001>\u000b\u0005m|\u0012a\u0002:v]RLW.Z\u0005\u0003{j\u0014\u0011#\u00112tiJ\f7\r\u001e$v]\u000e$\u0018n\u001c82!\ry\u0018QA\u0007\u0003\u0003\u0003Q1!a\u0001P\u0003\tIw.C\u0002/\u0003\u0003!\u0012A^\u0001\ti>\u001cFO]5oOR\t1*A\u0003baBd\u0017\u0010F\u00029\u0003#AQ\u0001\r\nA\u0002I\nq!\u001e8baBd\u0017\u0010\u0006\u0003\u0002\u0018\u0005u\u0001\u0003\u0002\u0010\u0002\u001aIJ1!a\u0007 \u0005\u0019y\u0005\u000f^5p]\"A\u0011qD\n\u0002\u0002\u0003\u0007\u0001(A\u0002yIA\nAb\u001e:ji\u0016\u0014V\r\u001d7bG\u0016$\"!!\n\u0011\u00071\u000b9#C\u0002\u0002*5\u0013aa\u00142kK\u000e$\b
    #9 = Utf8               o
   #10 = Utf8               Largonaut/JsonObject;
   #11 = Utf8               unapply
   #12 = Utf8               (Largonaut/JObject;)Lscala/Option;
   #13 = Utf8               (Largonaut/JObject;)Lscala/Option<Largonaut/JsonObject;>;
   #14 = Utf8               x$0
   #15 = Utf8               argonaut/JObject$
   #16 = Class              #15           // argonaut/JObject$
   #17 = Utf8               MODULE$
   #18 = Utf8               Largonaut/JObject$;
   #19 = NameAndType        #17:#18       // MODULE$:Largonaut/JObject$;
   #20 = Fieldref           #16.#19       // argonaut/JObject$.MODULE$:Largonaut/JObject$;
   #21 = NameAndType        #11:#12       // unapply:(Largonaut/JObject;)Lscala/Option;
   #22 = Methodref          #16.#21       // argonaut/JObject$.unapply:(Largonaut/JObject;)Lscala/Option;
   #23 = Utf8               apply
   #24 = Utf8               (Largonaut/JsonObject;)Largonaut/JObject;
   #25 = NameAndType        #23:#24       // apply:(Largonaut/JsonObject;)Largonaut/JObject;
   #26 = Methodref          #16.#25       // argonaut/JObject$.apply:(Largonaut/JsonObject;)Largonaut/JObject;
   #27 = Utf8               andThen
   #28 = Utf8               (Lscala/Function1;)Lscala/Function1;
   #29 = Utf8               <A:Ljava/lang/Object;>(Lscala/Function1<Largonaut/JObject;TA;>;)Lscala/Function1<Largonaut/JsonObject;TA;>;
   #30 = Utf8               g
   #31 = NameAndType        #27:#28       // andThen:(Lscala/Function1;)Lscala/Function1;
   #32 = Methodref          #16.#31       // argonaut/JObject$.andThen:(Lscala/Function1;)Lscala/Function1;
   #33 = Utf8               compose
   #34 = Utf8               <A:Ljava/lang/Object;>(Lscala/Function1<TA;Largonaut/JsonObject;>;)Lscala/Function1<TA;Largonaut/JObject;>;
   #35 = NameAndType        #33:#28       // compose:(Lscala/Function1;)Lscala/Function1;
   #36 = Methodref          #16.#35       // argonaut/JObject$.compose:(Lscala/Function1;)Lscala/Function1;
   #37 = Utf8               ()Largonaut/JsonObject;
   #38 = NameAndType        #9:#10        // o:Largonaut/JsonObject;
   #39 = Fieldref           #2.#38        // argonaut/JObject.o:Largonaut/JsonObject;
   #40 = Utf8               this
   #41 = Utf8               Largonaut/JObject;
   #42 = Utf8               copy
   #43 = Utf8               <init>
   #44 = Utf8               (Largonaut/JsonObject;)V
   #45 = NameAndType        #43:#44       // "<init>":(Largonaut/JsonObject;)V
   #46 = Methodref          #2.#45        // argonaut/JObject."<init>":(Largonaut/JsonObject;)V
   #47 = Utf8               copy$default$1
   #48 = NameAndType        #9:#37        // o:()Largonaut/JsonObject;
   #49 = Methodref          #2.#48        // argonaut/JObject.o:()Largonaut/JsonObject;
   #50 = Utf8               productPrefix
   #51 = Utf8               ()Ljava/lang/String;
   #52 = Utf8               JObject
   #53 = String             #52           // JObject
   #54 = Utf8               productArity
   #55 = Utf8               ()I
   #56 = Utf8               productElement
   #57 = Utf8               (I)Ljava/lang/Object;
   #58 = Utf8               x$1
   #59 = Utf8               scala/runtime/Statics
   #60 = Class              #59           // scala/runtime/Statics
   #61 = Utf8               ioobe
   #62 = NameAndType        #61:#57       // ioobe:(I)Ljava/lang/Object;
   #63 = Methodref          #60.#62       // scala/runtime/Statics.ioobe:(I)Ljava/lang/Object;
   #64 = Utf8               I
   #65 = Utf8               java/lang/Object
   #66 = Class              #65           // java/lang/Object
   #67 = Utf8               productIterator
   #68 = Utf8               ()Lscala/collection/Iterator;
   #69 = Utf8               ()Lscala/collection/Iterator<Ljava/lang/Object;>;
   #70 = Utf8               scala/runtime/ScalaRunTime$
   #71 = Class              #70           // scala/runtime/ScalaRunTime$
   #72 = Utf8               Lscala/runtime/ScalaRunTime$;
   #73 = NameAndType        #17:#72       // MODULE$:Lscala/runtime/ScalaRunTime$;
   #74 = Fieldref           #71.#73       // scala/runtime/ScalaRunTime$.MODULE$:Lscala/runtime/ScalaRunTime$;
   #75 = Utf8               typedProductIterator
   #76 = Utf8               (Lscala/Product;)Lscala/collection/Iterator;
   #77 = NameAndType        #75:#76       // typedProductIterator:(Lscala/Product;)Lscala/collection/Iterator;
   #78 = Methodref          #71.#77       // scala/runtime/ScalaRunTime$.typedProductIterator:(Lscala/Product;)Lscala/collection/Iterator;
   #79 = Utf8               canEqual
   #80 = Utf8               (Ljava/lang/Object;)Z
   #81 = Utf8               Ljava/lang/Object;
   #82 = Utf8               productElementName
   #83 = Utf8               (I)Ljava/lang/String;
   #84 = String             #9            // o
   #85 = Utf8               java/lang/String
   #86 = Class              #85           // java/lang/String
   #87 = Utf8               hashCode
   #88 = Utf8               _hashCode
   #89 = Utf8               (Lscala/Product;)I
   #90 = NameAndType        #88:#89       // _hashCode:(Lscala/Product;)I
   #91 = Methodref          #71.#90       // scala/runtime/ScalaRunTime$._hashCode:(Lscala/Product;)I
   #92 = Utf8               equals
   #93 = NameAndType        #92:#80       // equals:(Ljava/lang/Object;)Z
   #94 = Methodref          #66.#93       // java/lang/Object.equals:(Ljava/lang/Object;)Z
   #95 = NameAndType        #79:#80       // canEqual:(Ljava/lang/Object;)Z
   #96 = Methodref          #2.#95        // argonaut/JObject.canEqual:(Ljava/lang/Object;)Z
   #97 = Utf8               argonaut/JsonObject
   #98 = Class              #97           // argonaut/JsonObject
   #99 = Utf8               ()V
  #100 = NameAndType        #43:#99       // "<init>":()V
  #101 = Methodref          #4.#100       // argonaut/Json."<init>":()V
  #102 = Utf8               Code
  #103 = Utf8               Signature
  #104 = Utf8               MethodParameters
  #105 = Utf8               LineNumberTable
  #106 = Utf8               LocalVariableTable
  #107 = Utf8               StackMapTable
  #108 = Utf8               SourceFile
  #109 = Utf8               RuntimeVisibleAnnotations
  #110 = Utf8               ScalaInlineInfo
  #111 = Utf8               ScalaSig
{
  private final argonaut.JsonObject o;
    descriptor: Largonaut/JsonObject;
    flags: (0x0012) ACC_PRIVATE, ACC_FINAL

  public static scala.Option<argonaut.JsonObject> unapply(argonaut.JObject);
    descriptor: (Largonaut/JObject;)Lscala/Option;
    flags: (0x0009) ACC_PUBLIC, ACC_STATIC
    Code:
      stack=2, locals=1, args_size=1
         0: getstatic     #20                 // Field argonaut/JObject$.MODULE$:Largonaut/JObject$;
         3: aload_0
         4: invokevirtual #22                 // Method argonaut/JObject$.unapply:(Largonaut/JObject;)Lscala/Option;
         7: areturn
    Signature: #13                          // (Largonaut/JObject;)Lscala/Option<Largonaut/JsonObject;>;
    MethodParameters:
      Name                           Flags
      x$0                            final

  public static argonaut.JObject apply(argonaut.JsonObject);
    descriptor: (Largonaut/JsonObject;)Largonaut/JObject;
    flags: (0x0009) ACC_PUBLIC, ACC_STATIC
    Code:
      stack=2, locals=1, args_size=1
         0: getstatic     #20                 // Field argonaut/JObject$.MODULE$:Largonaut/JObject$;
         3: aload_0
         4: invokevirtual #26                 // Method argonaut/JObject$.apply:(Largonaut/JsonObject;)Largonaut/JObject;
         7: areturn
    MethodParameters:
      Name                           Flags
      o                              final

  public static <A extends java.lang.Object> scala.Function1<argonaut.JsonObject, A> andThen(scala.Function1<argonaut.JObject, A>);
    descriptor: (Lscala/Function1;)Lscala/Function1;
    flags: (0x0009) ACC_PUBLIC, ACC_STATIC
    Code:
      stack=2, locals=1, args_size=1
         0: getstatic     #20                 // Field argonaut/JObject$.MODULE$:Largonaut/JObject$;
         3: aload_0
         4: invokevirtual #32                 // Method argonaut/JObject$.andThen:(Lscala/Function1;)Lscala/Function1;
         7: areturn
    Signature: #29                          // <A:Ljava/lang/Object;>(Lscala/Function1<Largonaut/JObject;TA;>;)Lscala/Function1<Largonaut/JsonObject;TA;>;
    MethodParameters:
      Name                           Flags
      g                              final

  public static <A extends java.lang.Object> scala.Function1<A, argonaut.JObject> compose(scala.Function1<A, argonaut.JsonObject>);
    descriptor: (Lscala/Function1;)Lscala/Function1;
    flags: (0x0009) ACC_PUBLIC, ACC_STATIC
    Code:
      stack=2, locals=1, args_size=1
         0: getstatic     #20                 // Field argonaut/JObject$.MODULE$:Largonaut/JObject$;
         3: aload_0
         4: invokevirtual #36                 // Method argonaut/JObject$.compose:(Lscala/Function1;)Lscala/Function1;
         7: areturn
    Signature: #34                          // <A:Ljava/lang/Object;>(Lscala/Function1<TA;Largonaut/JsonObject;>;)Lscala/Function1<TA;Largonaut/JObject;>;
    MethodParameters:
      Name                           Flags
      g                              final

  public argonaut.JsonObject o();
    descriptor: ()Largonaut/JsonObject;
    flags: (0x0001) ACC_PUBLIC
    Code:
      stack=1, locals=1, args_size=1
         0: aload_0
         1: getfield      #39                 // Field o:Largonaut/JsonObject;
         4: areturn
      LineNumberTable:
        line 484: 0
      LocalVariableTable:
        Start  Length  Slot  Name   Signature
            0       5     0  this   Largonaut/JObject;

  public argonaut.JObject copy(argonaut.JsonObject);
    descriptor: (Largonaut/JsonObject;)Largonaut/JObject;
    flags: (0x0001) ACC_PUBLIC
    Code:
      stack=3, locals=2, args_size=2
         0: new           #2                  // class argonaut/JObject
         3: dup
         4: aload_1
         5: invokespecial #46                 // Method "<init>":(Largonaut/JsonObject;)V
         8: areturn
      LineNumberTable:
        line 484: 0
      LocalVariableTable:
        Start  Length  Slot  Name   Signature
            0       9     0  this   Largonaut/JObject;
            0       9     1     o   Largonaut/JsonObject;
    MethodParameters:
      Name                           Flags
      o                              final

  public argonaut.JsonObject copy$default$1();
    descriptor: ()Largonaut/JsonObject;
    flags: (0x0001) ACC_PUBLIC
    Code:
      stack=1, locals=1, args_size=1
         0: aload_0
         1: invokevirtual #49                 // Method o:()Largonaut/JsonObject;
         4: areturn
      LineNumberTable:
        line 484: 0
      LocalVariableTable:
        Start  Length  Slot  Name   Signature
            0       5     0  this   Largonaut/JObject;

  public java.lang.String productPrefix();
    descriptor: ()Ljava/lang/String;
    flags: (0x0001) ACC_PUBLIC
    Code:
      stack=1, locals=1, args_size=1
         0: ldc           #53                 // String JObject
         2: areturn
      LineNumberTable:
        line 484: 0
      LocalVariableTable:
        Start  Length  Slot  Name   Signature
            0       3     0  this   Largonaut/JObject;

  public int productArity();
    descriptor: ()I
    flags: (0x0001) ACC_PUBLIC
    Code:
      stack=1, locals=1, args_size=1
         0: iconst_1
         1: ireturn
      LineNumberTable:
        line 484: 0
      LocalVariableTable:
        Start  Length  Slot  Name   Signature
            0       2     0  this   Largonaut/JObject;

  public java.lang.Object productElement(int);
    descriptor: (I)Ljava/lang/Object;
    flags: (0x0001) ACC_PUBLIC
    Code:
      stack=1, locals=3, args_size=2
         0: iload_1
         1: istore_2
         2: iload_2
         3: tableswitch   { // 0 to 0
                       0: 20
                 default: 27
            }
        20: aload_0
        21: invokevirtual #49                 // Method o:()Largonaut/JsonObject;
        24: goto          34
        27: iload_1
        28: invokestatic  #63                 // Method scala/runtime/Statics.ioobe:(I)Ljava/lang/Object;
        31: goto          34
        34: areturn
      StackMapTable: number_of_entries = 3
        frame_type = 252 /* append */
          offset_delta = 20
          locals = [ int ]
        frame_type = 6 /* same */
        frame_type = 70 /* same_locals_1_stack_item */
          stack = [ class java/lang/Object ]
      LineNumberTable:
        line 484: 0
      LocalVariableTable:
        Start  Length  Slot  Name   Signature
            0      35     0  this   Largonaut/JObject;
            0      35     1   x$1   I
    MethodParameters:
      Name                           Flags
      x$1                            final

  public scala.collection.Iterator<java.lang.Object> productIterator();
    descriptor: ()Lscala/collection/Iterator;
    flags: (0x0001) ACC_PUBLIC
    Code:
      stack=2, locals=1, args_size=1
         0: getstatic     #74                 // Field scala/runtime/ScalaRunTime$.MODULE$:Lscala/runtime/ScalaRunTime$;
         3: aload_0
         4: invokevirtual #78                 // Method scala/runtime/ScalaRunTime$.typedProductIterator:(Lscala/Product;)Lscala/collection/Iterator;
         7: areturn
      LineNumberTable:
        line 484: 0
      LocalVariableTable:
        Start  Length  Slot  Name   Signature
            0       8     0  this   Largonaut/JObject;
    Signature: #69                          // ()Lscala/collection/Iterator<Ljava/lang/Object;>;

  public boolean canEqual(java.lang.Object);
    descriptor: (Ljava/lang/Object;)Z
    flags: (0x0001) ACC_PUBLIC
    Code:
      stack=1, locals=2, args_size=2
         0: aload_1
         1: instanceof    #2                  // class argonaut/JObject
         4: ireturn
      LineNumberTable:
        line 484: 0
      LocalVariableTable:
        Start  Length  Slot  Name   Signature
            0       5     0  this   Largonaut/JObject;
            0       5     1   x$1   Ljava/lang/Object;
    MethodParameters:
      Name                           Flags
      x$1                            final

  public java.lang.String productElementName(int);
    descriptor: (I)Ljava/lang/String;
    flags: (0x0001) ACC_PUBLIC
    Code:
      stack=1, locals=3, args_size=2
         0: iload_1
         1: istore_2
         2: iload_2
         3: tableswitch   { // 0 to 0
                       0: 20
                 default: 25
            }
        20: ldc           #84                 // String o
        22: goto          35
        25: iload_1
        26: invokestatic  #63                 // Method scala/runtime/Statics.ioobe:(I)Ljava/lang/Object;
        29: checkcast     #86                 // class java/lang/String
        32: goto          35
        35: areturn
      StackMapTable: number_of_entries = 3
        frame_type = 252 /* append */
          offset_delta = 20
          locals = [ int ]
        frame_type = 4 /* same */
        frame_type = 73 /* same_locals_1_stack_item */
          stack = [ class java/lang/String ]
      LineNumberTable:
        line 484: 0
      LocalVariableTable:
        Start  Length  Slot  Name   Signature
            0      36     0  this   Largonaut/JObject;
            0      36     1   x$1   I
    MethodParameters:
      Name                           Flags
      x$1                            final

  public int hashCode();
    descriptor: ()I
    flags: (0x0001) ACC_PUBLIC
    Code:
      stack=2, locals=1, args_size=1
         0: getstatic     #74                 // Field scala/runtime/ScalaRunTime$.MODULE$:Lscala/runtime/ScalaRunTime$;
         3: aload_0
         4: invokevirtual #91                 // Method scala/runtime/ScalaRunTime$._hashCode:(Lscala/Product;)I
         7: ireturn
      LineNumberTable:
        line 484: 0
      LocalVariableTable:
        Start  Length  Slot  Name   Signature
            0       8     0  this   Largonaut/JObject;

  public boolean equals(java.lang.Object);
    descriptor: (Ljava/lang/Object;)Z
    flags: (0x0001) ACC_PUBLIC
    Code:
      stack=2, locals=6, args_size=2
         0: aload_0
         1: aload_1
         2: if_acmpeq     86
         5: aload_1
         6: astore_3
         7: aload_3
         8: instanceof    #2                  // class argonaut/JObject
        11: ifeq          19
        14: iconst_1
        15: istore_2
        16: goto          27
        19: goto          22
        22: iconst_0
        23: istore_2
        24: goto          27
        27: iload_2
        28: ifeq          90
        31: aload_1
        32: checkcast     #2                  // class argonaut/JObject
        35: astore        4
        37: aload_0
        38: invokevirtual #49                 // Method o:()Largonaut/JsonObject;
        41: aload         4
        43: invokevirtual #49                 // Method o:()Largonaut/JsonObject;
        46: astore        5
        48: dup
        49: ifnonnull     61
        52: pop
        53: aload         5
        55: ifnull        69
        58: goto          82
        61: aload         5
        63: invokevirtual #94                 // Method java/lang/Object.equals:(Ljava/lang/Object;)Z
        66: ifeq          82
        69: aload         4
        71: aload_0
        72: invokevirtual #96                 // Method canEqual:(Ljava/lang/Object;)Z
        75: ifeq          82
        78: iconst_1
        79: goto          83
        82: iconst_0
        83: ifeq          90
        86: iconst_1
        87: goto          91
        90: iconst_0
        91: ireturn
      StackMapTable: number_of_entries = 10
        frame_type = 253 /* append */
          offset_delta = 19
          locals = [ top, class java/lang/Object ]
        frame_type = 2 /* same */
        frame_type = 255 /* full_frame */
          offset_delta = 4
          locals = [ class argonaut/JObject, class java/lang/Object, int, class java/lang/Object ]
          stack = []
        frame_type = 255 /* full_frame */
          offset_delta = 33
          locals = [ class argonaut/JObject, class java/lang/Object, int, class java/lang/Object, class argonaut/JObject, class argonaut/JsonObject ]
          stack = [ class argonaut/JsonObject ]
        frame_type = 7 /* same */
        frame_type = 12 /* same */
        frame_type = 64 /* same_locals_1_stack_item */
          stack = [ int ]
        frame_type = 255 /* full_frame */
          offset_delta = 2
          locals = [ class argonaut/JObject, class java/lang/Object ]
          stack = []
        frame_type = 253 /* append */
          offset_delta = 3
          locals = [ int, class java/lang/Object ]
        frame_type = 255 /* full_frame */
          offset_delta = 0
          locals = [ class argonaut/JObject, class java/lang/Object ]
          stack = [ int ]
      LineNumberTable:
        line 484: 0
      LocalVariableTable:
        Start  Length  Slot  Name   Signature
            0      92     0  this   Largonaut/JObject;
            0      92     1   x$1   Ljava/lang/Object;
    MethodParameters:
      Name                           Flags
      x$1                            final

  public argonaut.JObject(argonaut.JsonObject);
    descriptor: (Largonaut/JsonObject;)V
    flags: (0x0001) ACC_PUBLIC
    Code:
      stack=2, locals=2, args_size=2
         0: aload_0
         1: aload_1
         2: putfield      #39                 // Field o:Largonaut/JsonObject;
         5: aload_0
         6: invokespecial #101                // Method argonaut/Json."<init>":()V
         9: return
      LineNumberTable:
        line 484: 0
      LocalVariableTable:
        Start  Length  Slot  Name   Signature
            0      10     0  this   Largonaut/JObject;
            0      10     1     o   Largonaut/JsonObject;
    MethodParameters:
      Name                           Flags
      o                              final
}
SourceFile: "Json.scala"
RuntimeVisibleAnnotations:
  0: #6(#7=s#8)
    scala.reflect.ScalaSignature(
      bytes="\u0006\u0005\u0005-b!B\u000b\u0017\u0001ZA\u0002\u0002\u0003\u0019\u0001\u0005+\u0007I\u0011A\u0019\t\u0011U\u0002!\u0011#Q\u0001\nIBQA\u000e\u0001\u0005\u0002]BqA\u000f\u0001\u0002\u0002\u0013\u00051\bC\u0004>\u0001E\u0005I\u0011\u0001 \t\u000f%\u0003\u0011\u0011!C!\u0015\"91\u000bAA\u0001\n\u0003!\u0006b\u0002-\u0001\u0003\u0003%\t!\u0017\u0005\b?\u0002\t\t\u0011\"\u0011a\u0011\u001d9\u0007!!A\u0005\u0002!Dq!\u001c\u0001\u0002\u0002\u0013\u0005c\u000eC\u0004q\u0001\u0005\u0005I\u0011I9\t\u000fI\u0004\u0011\u0011!C!g\u001eAQOFA\u0001\u0012\u00031bO\u0002\u0005\u0016-\u0005\u0005\t\u0012\u0001\fx\u0011\u00191t\u0002\"\u0001\u0002\b!I\u0011\u0011B\b\u0002\u0002\u0013\u0015\u00131\u0002\u0005\n\u0003\u001by\u0011\u0011!CA\u0003\u001fA\u0011\"a\u0005\u0010\u0003\u0003%\t)!\u0006\t\u0013\u0005\u0005r\"!A\u0005\n\u0005\r\"a\u0002&PE*,7\r\u001e\u0006\u0002/\u0005A\u0011M]4p]\u0006,Ho\u0005\u0003\u00013u\u0019\u0003C\u0001\u000e\u001c\u001b\u00051\u0012B\u0001\u000f\u0017\u0005\u0011Q5o\u001c8\u0011\u0005y\tS\"A\u0010\u000b\u0003\u0001\nQa]2bY\u0006L!AI\u0010\u0003\u000fA\u0013x\u000eZ;diB\u0011A%\f\b\u0003K-r!A\n\u0016\u000e\u0003\u001dR!\u0001K\u0015\u0002\rq\u0012xn\u001c;?\u0007\u0001I\u0011\u0001I\u0005\u0003Y}\tq\u0001]1dW\u0006<W-\u0003\u0002/_\ta1+\u001a:jC2L\'0\u00192mK*\u0011AfH\u0001\u0002_V\t!\u0007\u0005\u0002\u001bg%\u0011AG\u0006\u0002\u000b\u0015N|gn\u00142kK\u000e$\u0018AA8!\u0003\u0019a\u0014N\\5u}Q\u0011\u0001(\u000f\t\u00035\u0001AQ\u0001M\u0002A\u0002I\nAaY8qsR\u0011\u0001\b\u0010\u0005\ba\u0011\u0001\n\u00111\u00013\u00039\u0019w\u000e]=%I\u00164\u0017-\u001e7uIE*\u0012a\u0010\u0016\u0003e\u0001[\u0013!\u0011\t\u0003\u0005\u001ek\u0011a\u0011\u0006\u0003\t\u0016\u000b\u0011\"\u001e8dQ\u0016\u001c7.\u001a3\u000b\u0005\u0019{\u0012AC1o]>$\u0018\r^5p]&\u0011\u0001j\u0011\u0002\u0012k:\u001c\u0007.Z2lK\u00124\u0016M]5b]\u000e,\u0017!\u00049s_\u0012,8\r\u001e)sK\u001aL\u00070F\u0001L!\ta\u0015+D\u0001N\u0015\tqu*\u0001\u0003mC:<\'\"\u0001)\u0002\t)\fg/Y\u0005\u0003%6\u0013aa\u0015;sS:<\u0017\u0001\u00049s_\u0012,8\r^!sSRLX#A+\u0011\u0005y1\u0016BA, \u0005\rIe\u000e^\u0001\u000faJ|G-^2u\u000b2,W.\u001a8u)\tQV\f\u0005\u0002\u001f7&\u0011Al\b\u0002\u0004\u0003:L\bb\u00020\t\u0003\u0003\u0005\r!V\u0001\u0004q\u0012\n\u0014a\u00049s_\u0012,8\r^%uKJ\fGo\u001c:\u0016\u0003\u0005\u00042AY3[\u001b\u0005\u0019\'B\u00013 \u0003)\u0019w\u000e\u001c7fGRLwN\\\u0005\u0003M\u000e\u0014\u0001\"\u0013;fe\u0006$xN]\u0001\tG\u0006tW)];bYR\u0011\u0011\u000e\u001c\t\u0003=)L!a[\u0010\u0003\u000f\t{w\u000e\\3b]\"9aLCA\u0001\u0002\u0004Q\u0016A\u00059s_\u0012,8\r^#mK6,g\u000e\u001e(b[\u0016$\"aS8\t\u000fy[\u0011\u0011!a\u0001+\u0006A\u0001.Y:i\u0007>$W\rF\u0001V\u0003\u0019)\u0017/^1mgR\u0011\u0011\u000e\u001e\u0005\b=6\t\t\u00111\u0001[\u0003\u001dQuJ\u00196fGR\u0004\"AG\b\u0014\u0007=Ah\u0010\u0005\u0003zyJBT\"\u0001>\u000b\u0005m|\u0012a\u0002:v]RLW.Z\u0005\u0003{j\u0014\u0011#\u00112tiJ\f7\r\u001e$v]\u000e$\u0018n\u001c82!\ry\u0018QA\u0007\u0003\u0003\u0003Q1!a\u0001P\u0003\tIw.C\u0002/\u0003\u0003!\u0012A^\u0001\ti>\u001cFO]5oOR\t1*A\u0003baBd\u0017\u0010F\u00029\u0003#AQ\u0001\r\nA\u0002I\nq!\u001e8baBd\u0017\u0010\u0006\u0003\u0002\u0018\u0005u\u0001\u0003\u0002\u0010\u0002\u001aIJ1!a\u0007 \u0005\u0019y\u0005\u000f^5p]\"A\u0011qD\n\u0002\u0002\u0003\u0007\u0001(A\u0002yIA\nAb\u001e:ji\u0016\u0014V\r\u001d7bG\u0016$\"!!\n\u0011\u00071\u000b9#C\u0002\u0002*5\u0013aa\u00142kK\u000e$\b"
    )
  ScalaInlineInfo: length = 0x40 (unknown attribute)
   01 00 00 0C 00 2B 00 2C 00 00 4F 00 50 00 00 2A
   00 18 00 00 2F 00 25 00 00 5C 00 50 00 00 57 00
   37 00 00 09 00 25 00 00 36 00 37 00 00 38 00 39
   00 00 52 00 53 00 00 43 00 44 00 00 32 00 33 00

  ScalaSig: length = 0x3 (unknown attribute)
   05 02 00
