Classfile /Users/mw/Projects/slang-braindump/.jar/jar8/assemble/slang-braindump/assemble/content/argonaut/JsonObjectInstance.class
  Last modified May 29, 2022; size 14549 bytes
  SHA-256 checksum f717867e230a6849eb50c7b44674b7ea559d73cdb1b989ee28411200ff9475c6
  Compiled from "JsonObject.scala"
public class argonaut.JsonObjectInstance extends argonaut.JsonObject implements scala.Product,java.io.Serializable
  minor version: 0
  major version: 52
  flags: (0x0021) ACC_PUBLIC, ACC_SUPER
  this_class: #2                          // argonaut/JsonObjectInstance
  super_class: #4                         // argonaut/JsonObject
  interfaces: 2, fields: 2, methods: 46, attributes: 6
Constant pool:
    #1 = Utf8               argonaut/JsonObjectInstance
    #2 = Class              #1            // argonaut/JsonObjectInstance
    #3 = Utf8               argonaut/JsonObject
    #4 = Class              #3            // argonaut/JsonObject
    #5 = Utf8               scala/Product
    #6 = Class              #5            // scala/Product
    #7 = Utf8               java/io/Serializable
    #8 = Class              #7            // java/io/Serializable
    #9 = Utf8               JsonObject.scala
   #10 = Utf8               Lscala/reflect/ScalaSignature;
   #11 = Utf8               bytes
   #12 = Utf8               \u0006\u0005\tma!B\u0017/\u0001:\u0002\u0004\u0002\u0003%\u0001\u0005+\u0007I\u0011A%\t\u0011u\u0003!\u0011#Q\u0001\n)C\u0001B\u0018\u0001\u0003\u0016\u0004%\ta\u0018\u0005\tG\u0002\u0011\t\u0012)A\u0005A\")A\r\u0001C\u0001K\")\u0011\u000e\u0001C\u0001\u0013\")!\u000e\u0001C\u0001W\")\u0001\u000f\u0001C\u0001c\")q\u000f\u0001C\u0001q\")!\u0010\u0001C\u0001w\")Q\u0010\u0001C\u0001}\"9\u0011q\u0001\u0001\u0005\u0002\u0005%\u0001bBA\u000b\u0001\u0011\u0005\u0011q\u0003\u0005\b\u0003?\u0001A\u0011AA\f\u0011\u001d\t\t\u0003\u0001C\u0001\u0003GAq!a\n\u0001\t\u0003\tI\u0003C\u0004\u00028\u0001!\t!!\u000f\t\u000f\u0005u\u0002\u0001\"\u0001\u0002@!9\u00111\t\u0001\u0005\u0002\u0005\u0015\u0003bBA\'\u0001\u0011\u0005\u0011q\n\u0005\b\u0003\'\u0002A\u0011AA+\u0011\u001d\ti\u0006\u0001C!\u0003?Bq!a\u001a\u0001\t\u0003\nI\u0007C\u0004\u0002v\u0001!\t%a\u001e\t\u0013\u0005e\u0004!!A\u0005\u0002\u0005m\u0004\"CAA\u0001E\u0005I\u0011AAB\u0011%\tI\nAI\u0001\n\u0003\tY\nC\u0005\u0002 \u0002\t\t\u0011\"\u0011\u0002\"\"I\u0011\u0011\u0017\u0001\u0002\u0002\u0013\u0005\u0011Q\u000b\u0005\n\u0003g\u0003\u0011\u0011!C\u0001\u0003kC\u0011\"a/\u0001\u0003\u0003%\t%!0\t\u0013\u0005-\u0007!!A\u0005\u0002\u00055\u0007\"CAi\u0001\u0005\u0005I\u0011IAj\u000f)\t9NLA\u0001\u0012\u0003q\u0013\u0011\u001c\u0004\n[9\n\t\u0011#\u0001/\u00037Da\u0001Z\u0012\u0005\u0002\u0005M\b\"CA/G\u0005\u0005IQIA{\u0011!i8%!A\u0005\u0002\u0006]\b\"CA\u007fGE\u0005I\u0011AAB\u0011%\typII\u0001\n\u0003\tY\nC\u0005\u0003\u0002\r\n\t\u0011\"!\u0003\u0004!I!QB\u0012\u0012\u0002\u0013\u0005\u00111\u0011\u0005\n\u0005\u001f\u0019\u0013\u0013!C\u0001\u00037C\u0011B!\u0005$\u0003\u0003%IAa\u0005\u0003%)\u001bxN\\(cU\u0016\u001cG/\u00138ti\u0006t7-\u001a\u0006\u0002_\u0005A\u0011M]4p]\u0006,Ho\u0005\u0003\u0001cUZ\u0004C\u0001\u001a4\u001b\u0005q\u0013B\u0001\u001b/\u0005)Q5o\u001c8PE*,7\r\u001e\t\u0003mej\u0011a\u000e\u0006\u0002q\u0005)1oY1mC&\u0011!h\u000e\u0002\b!J|G-^2u!\taTI\u0004\u0002>\u0007:\u0011aHQ\u0007\u0002\u007f)\u0011\u0001)Q\u0001\u0007yI|w\u000e\u001e \u0004\u0001%\t\u0001(\u0003\u0002Eo\u00059\u0001/Y2lC\u001e,\u0017B\u0001$H\u00051\u0019VM]5bY&T\u0018M\u00197f\u0015\t!u\'A\u0005gS\u0016dGm]\'baV\t!\n\u0005\u0003L\u001fJSfB\u0001\'N!\tqt\'\u0003\u0002Oo\u00051\u0001K]3eK\u001aL!\u0001U)\u0003\u00075\u000b\u0007O\u0003\u0002OoA\u00111K\u0016\b\u0003eQK!!\u0016\u0018\u0002\t)\u001bxN\\\u0005\u0003/b\u0013\u0011BS:p]\u001aKW\r\u001c3\n\u0005es#!\u0002&t_:\u001c\bC\u0001\u001a\\\u0013\tafF\u0001\u0003Kg>t\u0017A\u00034jK2$7/T1qA\u0005iqN\u001d3fe\u0016$g)[3mIN,\u0012\u0001\u0019\t\u0004y\u0005\u0014\u0016B\u00012H\u0005\u00191Vm\u0019;pe\u0006qqN\u001d3fe\u0016$g)[3mIN\u0004\u0013A\u0002\u001fj]&$h\bF\u0002gO\"\u0004\"A\r\u0001\t\u000f!+\u0001\u0013!a\u0001\u0015\"9a,\u0002I\u0001\u0002\u0004\u0001\u0017!\u0002;p\u001b\u0006\u0004\u0018!\u0002\u0013qYV\u001cHcA\u0019m]\")Qn\u0002a\u0001%\u0006\ta\rC\u0003p\u000f\u0001\u0007!,A\u0001k\u0003-!3m\u001c7p]\u0012\u0002H.^:\u0015\u0005E\u0012\b\"B:\t\u0001\u0004!\u0018A\u00014k!\u00111TO\u0015.\n\u0005Y<$A\u0002+va2,\'\'A\u0006%a2,8\u000fJ2pY>tGCA\u0019z\u0011\u0015\u0019\u0018\u00021\u0001u\u0003\u0019!S.\u001b8vgR\u0011\u0011\u0007 \u0005\u0006[*\u0001\rAU\u0001\u0006CB\u0004H.\u001f\u000b\u0004\u007f\u0006\u0015\u0001\u0003\u0002\u001c\u0002\u0002iK1!a\u00018\u0005\u0019y\u0005\u000f^5p]\")Qn\u0003a\u0001%\u0006Iq/\u001b;i\u0015N|gn\u001d\u000b\u0004c\u0005-\u0001bBA\u0007\u0019\u0001\u0007\u0011qB\u0001\u0002WB)a\'!\u0005[5&\u0019\u00111C\u001c\u0003\u0013\u0019+hn\u0019;j_:\f\u0014aB5t\u000b6\u0004H/_\u000b\u0003\u00033\u00012ANA\u000e\u0013\r\tib\u000e\u0002\b\u0005>|G.Z1o\u0003)I7OT8u\u000b6\u0004H/_\u0001\rIEl\u0017M]6%c6\f\'o\u001b\u000b\u0005\u00033\t)\u0003C\u0003n\u001f\u0001\u0007!+\u0001\u0004u_2K7\u000f^\u000b\u0003\u0003W\u0001R\u0001PA\u0017\u0003cI1!a\fH\u0005\u0011a\u0015n\u001d;\u0011\u0007M\u000b\u0019$C\u0002\u00026a\u0013\u0011BS:p]\u0006\u001b8o\\2\u0002\rY\fG.^3t+\t\tY\u0004\u0005\u0003=\u0003[Q\u0016A\u00024jK2$7/\u0006\u0002\u0002BA!A(!\fS\u0003!1\u0017.\u001a7e\'\u0016$XCAA$!\u0011Y\u0015\u0011\n*\n\u0007\u0005-\u0013KA\u0002TKR\f1!\\1q)\r\t\u0014\u0011\u000b\u0005\u0007[R\u0001\r!a\u0004\u0002\tML\'0Z\u000b\u0003\u0003/\u00022ANA-\u0013\r\tYf\u000e\u0002\u0004\u0013:$\u0018\u0001\u0003;p\'R\u0014\u0018N\\4\u0015\u0005\u0005\u0005\u0004cA&\u0002d%\u0019\u0011QM)\u0003\rM#(/\u001b8h\u0003\u0019)\u0017/^1mgR!\u0011\u0011DA6\u0011\u001d\tig\u0006a\u0001\u0003_\n\u0011a\u001c\t\u0004m\u0005E\u0014bAA:o\t\u0019\u0011I\\=\u0002\u0011!\f7\u000f[\"pI\u0016$\"!a\u0016\u0002\t\r|\u0007/\u001f\u000b\u0006M\u0006u\u0014q\u0010\u0005\b\u0011f\u0001\n\u00111\u0001K\u0011\u001dq\u0016\u0004%AA\u0002\u0001\fabY8qs\u0012\"WMZ1vYR$\u0013\'\u0006\u0002\u0002\u0006*\u001a!*a\",\u0005\u0005%\u0005\u0003BAF\u0003+k!!!$\u000b\t\u0005=\u0015\u0011S\u0001\nk:\u001c\u0007.Z2lK\u0012T1!a%8\u0003)\tgN\\8uCRLwN\\\u0005\u0005\u0003/\u000biIA\tv]\u000eDWmY6fIZ\u000b\'/[1oG\u0016\fabY8qs\u0012\"WMZ1vYR$#\'\u0006\u0002\u0002\u001e*\u001a\u0001-a\"\u0002\u001bA\u0014x\u000eZ;diB\u0013XMZ5y+\t\t\u0019\u000b\u0005\u0003\u0002&\u0006=VBAAT\u0015\u0011\tI+a+\u0002\t1\fgn\u001a\u0006\u0003\u0003[\u000bAA[1wC&!\u0011QMAT\u00031\u0001(o\u001c3vGR\f%/\u001b;z\u00039\u0001(o\u001c3vGR,E.Z7f]R$B!a\u001c\u00028\"I\u0011\u0011\u0018\u0010\u0002\u0002\u0003\u0007\u0011qK\u0001\u0004q\u0012\n\u0014a\u00049s_\u0012,8\r^%uKJ\fGo\u001c:\u0016\u0005\u0005}\u0006CBAa\u0003\u000f\fy\'\u0004\u0002\u0002D*\u0019\u0011QY\u001c\u0002\u0015\r|G\u000e\\3di&|g.\u0003\u0003\u0002J\u0006\r\'\u0001C%uKJ\fGo\u001c:\u0002\u0011\r\fg.R9vC2$B!!\u0007\u0002P\"I\u0011\u0011\u0018\u0011\u0002\u0002\u0003\u0007\u0011qN\u0001\u0013aJ|G-^2u\u000b2,W.\u001a8u\u001d\u0006lW\r\u0006\u0003\u0002$\u0006U\u0007\"CA]C\u0005\u0005\t\u0019AA,\u0003IQ5o\u001c8PE*,7\r^%ogR\fgnY3\u0011\u0005I\u001a3#B\u0012\u0002^\u0006%\bcBAp\u0003KT\u0005MZ\u0007\u0003\u0003CT1!a98\u0003\u001d\u0011XO\u001c;j[\u0016LA!a:\u0002b\n\t\u0012IY:ue\u0006\u001cGOR;oGRLwN\u001c\u001a\u0011\t\u0005-\u0018\u0011_\u0007\u0003\u0003[TA!a<\u0002,\u0006\u0011\u0011n\\\u0005\u0004\r\u00065HCAAm)\t\t\u0019\u000bF\u0003g\u0003s\fY\u0010C\u0004IMA\u0005\t\u0019\u0001&\t\u000fy3\u0003\u0013!a\u0001A\u0006y\u0011\r\u001d9ms\u0012\"WMZ1vYR$\u0013\'A\bbaBd\u0017\u0010\n3fM\u0006,H\u000e\u001e\u00133\u0003\u001d)h.\u00199qYf$BA!\u0002\u0003\nA)a\'!\u0001\u0003\bA!a\'\u001e&a\u0011!\u0011Y!KA\u0001\u0002\u00041\u0017a\u0001=%a\u0005YB\u0005\\3tg&t\u0017\u000e\u001e\u0013he\u0016\fG/\u001a:%I\u00164\u0017-\u001e7uIE\n1\u0004\n7fgNLg.\u001b;%OJ,\u0017\r^3sI\u0011,g-Y;mi\u0012\u0012\u0014\u0001D<sSR,\'+\u001a9mC\u000e,GC\u0001B\u000b!\u0011\t)Ka\u0006\n\t\te\u0011q\u0015\u0002\u0007\u001f\nTWm\u0019;
   #13 = Utf8               java/lang/invoke/MethodHandles$Lookup
   #14 = Class              #13           // java/lang/invoke/MethodHandles$Lookup
   #15 = Utf8               java/lang/invoke/MethodHandles
   #16 = Class              #15           // java/lang/invoke/MethodHandles
   #17 = Utf8               Lookup
   #18 = Utf8               fieldsMap
   #19 = Utf8               Lscala/collection/immutable/Map;
   #20 = Utf8               Lscala/collection/immutable/Map<Ljava/lang/String;Largonaut/Json;>;
   #21 = Utf8               orderedFields
   #22 = Utf8               Lscala/collection/immutable/Vector;
   #23 = Utf8               Lscala/collection/immutable/Vector<Ljava/lang/String;>;
   #24 = Utf8               $lessinit$greater$default$2
   #25 = Utf8               ()Lscala/collection/immutable/Vector;
   #26 = Utf8               ()Lscala/collection/immutable/Vector<Ljava/lang/String;>;
   #27 = Utf8               argonaut/JsonObjectInstance$
   #28 = Class              #27           // argonaut/JsonObjectInstance$
   #29 = Utf8               MODULE$
   #30 = Utf8               Largonaut/JsonObjectInstance$;
   #31 = NameAndType        #29:#30       // MODULE$:Largonaut/JsonObjectInstance$;
   #32 = Fieldref           #28.#31       // argonaut/JsonObjectInstance$.MODULE$:Largonaut/JsonObjectInstance$;
   #33 = NameAndType        #24:#25       // $lessinit$greater$default$2:()Lscala/collection/immutable/Vector;
   #34 = Methodref          #28.#33       // argonaut/JsonObjectInstance$.$lessinit$greater$default$2:()Lscala/collection/immutable/Vector;
   #35 = Utf8               $lessinit$greater$default$1
   #36 = Utf8               ()Lscala/collection/immutable/Map;
   #37 = Utf8               ()Lscala/collection/immutable/Map<Ljava/lang/String;Largonaut/Json;>;
   #38 = NameAndType        #35:#36       // $lessinit$greater$default$1:()Lscala/collection/immutable/Map;
   #39 = Methodref          #28.#38       // argonaut/JsonObjectInstance$.$lessinit$greater$default$1:()Lscala/collection/immutable/Map;
   #40 = Utf8               unapply
   #41 = Utf8               (Largonaut/JsonObjectInstance;)Lscala/Option;
   #42 = Utf8               (Largonaut/JsonObjectInstance;)Lscala/Option<Lscala/Tuple2<Lscala/collection/immutable/Map<Ljava/lang/String;Largonaut/Json;>;Lscala/collection/immutable/Vector<Ljava/lang/String;>;>;>;
   #43 = Utf8               x$0
   #44 = NameAndType        #40:#41       // unapply:(Largonaut/JsonObjectInstance;)Lscala/Option;
   #45 = Methodref          #28.#44       // argonaut/JsonObjectInstance$.unapply:(Largonaut/JsonObjectInstance;)Lscala/Option;
   #46 = Utf8               apply$default$2
   #47 = NameAndType        #46:#25       // apply$default$2:()Lscala/collection/immutable/Vector;
   #48 = Methodref          #28.#47       // argonaut/JsonObjectInstance$.apply$default$2:()Lscala/collection/immutable/Vector;
   #49 = Utf8               apply$default$1
   #50 = NameAndType        #49:#36       // apply$default$1:()Lscala/collection/immutable/Map;
   #51 = Methodref          #28.#50       // argonaut/JsonObjectInstance$.apply$default$1:()Lscala/collection/immutable/Map;
   #52 = Utf8               tupled
   #53 = Utf8               ()Lscala/Function1;
   #54 = Utf8               ()Lscala/Function1<Lscala/Tuple2<Lscala/collection/immutable/Map<Ljava/lang/String;Largonaut/Json;>;Lscala/collection/immutable/Vector<Ljava/lang/String;>;>;Largonaut/JsonObjectInstance;>;
   #55 = NameAndType        #52:#53       // tupled:()Lscala/Function1;
   #56 = Methodref          #28.#55       // argonaut/JsonObjectInstance$.tupled:()Lscala/Function1;
   #57 = Utf8               curried
   #58 = Utf8               ()Lscala/Function1<Lscala/collection/immutable/Map<Ljava/lang/String;Largonaut/Json;>;Lscala/Function1<Lscala/collection/immutable/Vector<Ljava/lang/String;>;Largonaut/JsonObjectInstance;>;>;
   #59 = NameAndType        #57:#53       // curried:()Lscala/Function1;
   #60 = Methodref          #28.#59       // argonaut/JsonObjectInstance$.curried:()Lscala/Function1;
   #61 = Utf8               productElementNames
   #62 = Utf8               ()Lscala/collection/Iterator;
   #63 = Utf8               ()Lscala/collection/Iterator<Ljava/lang/String;>;
   #64 = Utf8               productElementNames$
   #65 = Utf8               (Lscala/Product;)Lscala/collection/Iterator;
   #66 = NameAndType        #64:#65       // productElementNames$:(Lscala/Product;)Lscala/collection/Iterator;
   #67 = InterfaceMethodref #6.#66        // scala/Product.productElementNames$:(Lscala/Product;)Lscala/collection/Iterator;
   #68 = Utf8               this
   #69 = Utf8               Largonaut/JsonObjectInstance;
   #70 = NameAndType        #18:#19       // fieldsMap:Lscala/collection/immutable/Map;
   #71 = Fieldref           #2.#70        // argonaut/JsonObjectInstance.fieldsMap:Lscala/collection/immutable/Map;
   #72 = NameAndType        #21:#22       // orderedFields:Lscala/collection/immutable/Vector;
   #73 = Fieldref           #2.#72        // argonaut/JsonObjectInstance.orderedFields:Lscala/collection/immutable/Vector;
   #74 = Utf8               toMap
   #75 = NameAndType        #18:#36       // fieldsMap:()Lscala/collection/immutable/Map;
   #76 = Methodref          #2.#75        // argonaut/JsonObjectInstance.fieldsMap:()Lscala/collection/immutable/Map;
   #77 = Utf8               $plus
   #78 = Utf8               (Ljava/lang/String;Largonaut/Json;)Largonaut/JsonObject;
   #79 = Utf8               f
   #80 = Utf8               j
   #81 = Utf8               scala/collection/immutable/Map
   #82 = Class              #81           // scala/collection/immutable/Map
   #83 = Utf8               contains
   #84 = Utf8               (Ljava/lang/Object;)Z
   #85 = NameAndType        #83:#84       // contains:(Ljava/lang/Object;)Z
   #86 = InterfaceMethodref #82.#85       // scala/collection/immutable/Map.contains:(Ljava/lang/Object;)Z
   #87 = Utf8               updated
   #88 = Utf8               (Ljava/lang/Object;Ljava/lang/Object;)Lscala/collection/immutable/MapOps;
   #89 = NameAndType        #87:#88       // updated:(Ljava/lang/Object;Ljava/lang/Object;)Lscala/collection/immutable/MapOps;
   #90 = InterfaceMethodref #82.#89       // scala/collection/immutable/Map.updated:(Ljava/lang/Object;Ljava/lang/Object;)Lscala/collection/immutable/MapOps;
   #91 = Utf8               copy$default$2
   #92 = NameAndType        #91:#25       // copy$default$2:()Lscala/collection/immutable/Vector;
   #93 = Methodref          #2.#92        // argonaut/JsonObjectInstance.copy$default$2:()Lscala/collection/immutable/Vector;
   #94 = Utf8               copy
   #95 = Utf8               (Lscala/collection/immutable/Map;Lscala/collection/immutable/Vector;)Largonaut/JsonObjectInstance;
   #96 = NameAndType        #94:#95       // copy:(Lscala/collection/immutable/Map;Lscala/collection/immutable/Vector;)Largonaut/JsonObjectInstance;
   #97 = Methodref          #2.#96        // argonaut/JsonObjectInstance.copy:(Lscala/collection/immutable/Map;Lscala/collection/immutable/Vector;)Largonaut/JsonObjectInstance;
   #98 = NameAndType        #21:#25       // orderedFields:()Lscala/collection/immutable/Vector;
   #99 = Methodref          #2.#98        // argonaut/JsonObjectInstance.orderedFields:()Lscala/collection/immutable/Vector;
  #100 = Utf8               scala/collection/immutable/Vector
  #101 = Class              #100          // scala/collection/immutable/Vector
  #102 = Utf8               $colon$plus
  #103 = Utf8               (Ljava/lang/Object;)Ljava/lang/Object;
  #104 = NameAndType        #102:#103     // $colon$plus:(Ljava/lang/Object;)Ljava/lang/Object;
  #105 = Methodref          #101.#104     // scala/collection/immutable/Vector.$colon$plus:(Ljava/lang/Object;)Ljava/lang/Object;
  #106 = Utf8               Ljava/lang/String;
  #107 = Utf8               Largonaut/Json;
  #108 = Utf8               (Lscala/Tuple2;)Largonaut/JsonObject;
  #109 = Utf8               (Lscala/Tuple2<Ljava/lang/String;Largonaut/Json;>;)Largonaut/JsonObject;
  #110 = Utf8               fj
  #111 = Utf8               scala/Tuple2
  #112 = Class              #111          // scala/Tuple2
  #113 = Utf8               _1
  #114 = Utf8               ()Ljava/lang/Object;
  #115 = NameAndType        #113:#114     // _1:()Ljava/lang/Object;
  #116 = Methodref          #112.#115     // scala/Tuple2._1:()Ljava/lang/Object;
  #117 = Utf8               java/lang/String
  #118 = Class              #117          // java/lang/String
  #119 = Utf8               _2
  #120 = NameAndType        #119:#114     // _2:()Ljava/lang/Object;
  #121 = Methodref          #112.#120     // scala/Tuple2._2:()Ljava/lang/Object;
  #122 = Utf8               argonaut/Json
  #123 = Class              #122          // argonaut/Json
  #124 = NameAndType        #77:#78       // $plus:(Ljava/lang/String;Largonaut/Json;)Largonaut/JsonObject;
  #125 = Methodref          #2.#124       // argonaut/JsonObjectInstance.$plus:(Ljava/lang/String;Largonaut/Json;)Largonaut/JsonObject;
  #126 = Utf8               Lscala/Tuple2;
  #127 = Utf8               $plus$colon
  #128 = Utf8               <init>
  #129 = Utf8               (Ljava/lang/Object;Ljava/lang/Object;)V
  #130 = NameAndType        #128:#129     // "<init>":(Ljava/lang/Object;Ljava/lang/Object;)V
  #131 = Methodref          #112.#130     // scala/Tuple2."<init>":(Ljava/lang/Object;Ljava/lang/Object;)V
  #132 = Utf8               scala/MatchError
  #133 = Class              #132          // scala/MatchError
  #134 = Utf8               (Ljava/lang/Object;)V
  #135 = NameAndType        #128:#134     // "<init>":(Ljava/lang/Object;)V
  #136 = Methodref          #133.#135     // scala/MatchError."<init>":(Ljava/lang/Object;)V
  #137 = NameAndType        #127:#103     // $plus$colon:(Ljava/lang/Object;)Ljava/lang/Object;
  #138 = Methodref          #101.#137     // scala/collection/immutable/Vector.$plus$colon:(Ljava/lang/Object;)Ljava/lang/Object;
  #139 = Utf8               $minus
  #140 = Utf8               (Ljava/lang/String;)Largonaut/JsonObject;
  #141 = Utf8               (Ljava/lang/Object;)Lscala/collection/immutable/MapOps;
  #142 = NameAndType        #139:#141     // $minus:(Ljava/lang/Object;)Lscala/collection/immutable/MapOps;
  #143 = InterfaceMethodref #82.#142      // scala/collection/immutable/Map.$minus:(Ljava/lang/Object;)Lscala/collection/immutable/MapOps;
  #144 = MethodType         #103          //  (Ljava/lang/Object;)Ljava/lang/Object;
  #145 = Utf8               $anonfun$$minus$1$adapted
  #146 = Utf8               (Ljava/lang/String;Ljava/lang/String;)Ljava/lang/Object;
  #147 = NameAndType        #145:#146     // $anonfun$$minus$1$adapted:(Ljava/lang/String;Ljava/lang/String;)Ljava/lang/Object;
  #148 = Methodref          #2.#147       // argonaut/JsonObjectInstance.$anonfun$$minus$1$adapted:(Ljava/lang/String;Ljava/lang/String;)Ljava/lang/Object;
  #149 = MethodHandle       6:#148        // REF_invokeStatic argonaut/JsonObjectInstance.$anonfun$$minus$1$adapted:(Ljava/lang/String;Ljava/lang/String;)Ljava/lang/Object;
  #150 = Utf8               (Ljava/lang/String;)Ljava/lang/Object;
  #151 = MethodType         #150          //  (Ljava/lang/String;)Ljava/lang/Object;
  #152 = Integer            5
  #153 = Integer            1
  #154 = Utf8               java/lang/invoke/LambdaMetafactory
  #155 = Class              #154          // java/lang/invoke/LambdaMetafactory
  #156 = Utf8               altMetafactory
  #157 = Utf8               (Ljava/lang/invoke/MethodHandles$Lookup;Ljava/lang/String;Ljava/lang/invoke/MethodType;[Ljava/lang/Object;)Ljava/lang/invoke/CallSite;
  #158 = NameAndType        #156:#157     // altMetafactory:(Ljava/lang/invoke/MethodHandles$Lookup;Ljava/lang/String;Ljava/lang/invoke/MethodType;[Ljava/lang/Object;)Ljava/lang/invoke/CallSite;
  #159 = Methodref          #155.#158     // java/lang/invoke/LambdaMetafactory.altMetafactory:(Ljava/lang/invoke/MethodHandles$Lookup;Ljava/lang/String;Ljava/lang/invoke/MethodType;[Ljava/lang/Object;)Ljava/lang/invoke/CallSite;
  #160 = MethodHandle       6:#159        // REF_invokeStatic java/lang/invoke/LambdaMetafactory.altMetafactory:(Ljava/lang/invoke/MethodHandles$Lookup;Ljava/lang/String;Ljava/lang/invoke/MethodType;[Ljava/lang/Object;)Ljava/lang/invoke/CallSite;
  #161 = Utf8               apply
  #162 = Utf8               (Ljava/lang/String;)Lscala/Function1;
  #163 = NameAndType        #161:#162     // apply:(Ljava/lang/String;)Lscala/Function1;
  #164 = InvokeDynamic      #0:#163       // #0:apply:(Ljava/lang/String;)Lscala/Function1;
  #165 = Utf8               filterNot
  #166 = Utf8               (Lscala/Function1;)Ljava/lang/Object;
  #167 = NameAndType        #165:#166     // filterNot:(Lscala/Function1;)Ljava/lang/Object;
  #168 = Methodref          #101.#167     // scala/collection/immutable/Vector.filterNot:(Lscala/Function1;)Ljava/lang/Object;
  #169 = Utf8               (Ljava/lang/String;)Lscala/Option;
  #170 = Utf8               (Ljava/lang/String;)Lscala/Option<Largonaut/Json;>;
  #171 = Utf8               get
  #172 = Utf8               (Ljava/lang/Object;)Lscala/Option;
  #173 = NameAndType        #171:#172     // get:(Ljava/lang/Object;)Lscala/Option;
  #174 = InterfaceMethodref #82.#173      // scala/collection/immutable/Map.get:(Ljava/lang/Object;)Lscala/Option;
  #175 = Utf8               withJsons
  #176 = Utf8               (Lscala/Function1;)Largonaut/JsonObject;
  #177 = Utf8               (Lscala/Function1<Largonaut/Json;Largonaut/Json;>;)Largonaut/JsonObject;
  #178 = Utf8               k
  #179 = Utf8               map
  #180 = NameAndType        #179:#176     // map:(Lscala/Function1;)Largonaut/JsonObject;
  #181 = Methodref          #2.#180       // argonaut/JsonObjectInstance.map:(Lscala/Function1;)Largonaut/JsonObject;
  #182 = Utf8               Lscala/Function1;
  #183 = Utf8               isEmpty
  #184 = Utf8               ()Z
  #185 = NameAndType        #183:#184     // isEmpty:()Z
  #186 = InterfaceMethodref #82.#185      // scala/collection/immutable/Map.isEmpty:()Z
  #187 = Utf8               isNotEmpty
  #188 = Methodref          #2.#185       // argonaut/JsonObjectInstance.isEmpty:()Z
  #189 = Utf8               $qmark$qmark
  #190 = Utf8               (Ljava/lang/String;)Z
  #191 = Utf8               toList
  #192 = Utf8               ()Lscala/collection/immutable/List;
  #193 = Utf8               ()Lscala/collection/immutable/List<Lscala/Tuple2<Ljava/lang/String;Largonaut/Json;>;>;
  #194 = Utf8               $anonfun$toList$1
  #195 = Utf8               (Largonaut/JsonObjectInstance;Ljava/lang/String;)Lscala/Tuple2;
  #196 = NameAndType        #194:#195     // $anonfun$toList$1:(Largonaut/JsonObjectInstance;Ljava/lang/String;)Lscala/Tuple2;
  #197 = Methodref          #2.#196       // argonaut/JsonObjectInstance.$anonfun$toList$1:(Largonaut/JsonObjectInstance;Ljava/lang/String;)Lscala/Tuple2;
  #198 = MethodHandle       6:#197        // REF_invokeStatic argonaut/JsonObjectInstance.$anonfun$toList$1:(Largonaut/JsonObjectInstance;Ljava/lang/String;)Lscala/Tuple2;
  #199 = Utf8               (Ljava/lang/String;)Lscala/Tuple2;
  #200 = MethodType         #199          //  (Ljava/lang/String;)Lscala/Tuple2;
  #201 = Utf8               (Largonaut/JsonObjectInstance;)Lscala/Function1;
  #202 = NameAndType        #161:#201     // apply:(Largonaut/JsonObjectInstance;)Lscala/Function1;
  #203 = InvokeDynamic      #1:#202       // #1:apply:(Largonaut/JsonObjectInstance;)Lscala/Function1;
  #204 = NameAndType        #179:#166     // map:(Lscala/Function1;)Ljava/lang/Object;
  #205 = Methodref          #101.#204     // scala/collection/immutable/Vector.map:(Lscala/Function1;)Ljava/lang/Object;
  #206 = Utf8               scala/collection/IterableOnceOps
  #207 = Class              #206          // scala/collection/IterableOnceOps
  #208 = NameAndType        #191:#192     // toList:()Lscala/collection/immutable/List;
  #209 = InterfaceMethodref #207.#208     // scala/collection/IterableOnceOps.toList:()Lscala/collection/immutable/List;
  #210 = Utf8               values
  #211 = Utf8               ()Lscala/collection/immutable/List<Largonaut/Json;>;
  #212 = Utf8               $anonfun$values$1
  #213 = Utf8               (Largonaut/JsonObjectInstance;Ljava/lang/String;)Largonaut/Json;
  #214 = NameAndType        #212:#213     // $anonfun$values$1:(Largonaut/JsonObjectInstance;Ljava/lang/String;)Largonaut/Json;
  #215 = Methodref          #2.#214       // argonaut/JsonObjectInstance.$anonfun$values$1:(Largonaut/JsonObjectInstance;Ljava/lang/String;)Largonaut/Json;
  #216 = MethodHandle       6:#215        // REF_invokeStatic argonaut/JsonObjectInstance.$anonfun$values$1:(Largonaut/JsonObjectInstance;Ljava/lang/String;)Largonaut/Json;
  #217 = Utf8               (Ljava/lang/String;)Largonaut/Json;
  #218 = MethodType         #217          //  (Ljava/lang/String;)Largonaut/Json;
  #219 = InvokeDynamic      #2:#202       // #2:apply:(Largonaut/JsonObjectInstance;)Lscala/Function1;
  #220 = Utf8               fields
  #221 = Utf8               ()Lscala/collection/immutable/List<Ljava/lang/String;>;
  #222 = Methodref          #101.#208     // scala/collection/immutable/Vector.toList:()Lscala/collection/immutable/List;
  #223 = Utf8               fieldSet
  #224 = Utf8               ()Lscala/collection/immutable/Set;
  #225 = Utf8               ()Lscala/collection/immutable/Set<Ljava/lang/String;>;
  #226 = Utf8               toSet
  #227 = NameAndType        #226:#224     // toSet:()Lscala/collection/immutable/Set;
  #228 = Methodref          #101.#227     // scala/collection/immutable/Vector.toSet:()Lscala/collection/immutable/Set;
  #229 = Utf8               scala/Predef$
  #230 = Class              #229          // scala/Predef$
  #231 = Utf8               Lscala/Predef$;
  #232 = NameAndType        #29:#231      // MODULE$:Lscala/Predef$;
  #233 = Fieldref           #230.#232     // scala/Predef$.MODULE$:Lscala/Predef$;
  #234 = Utf8               Map
  #235 = Utf8               ()Lscala/collection/immutable/Map$;
  #236 = NameAndType        #234:#235     // Map:()Lscala/collection/immutable/Map$;
  #237 = Methodref          #230.#236     // scala/Predef$.Map:()Lscala/collection/immutable/Map$;
  #238 = Utf8               scala/collection/immutable/Map$
  #239 = Class              #238          // scala/collection/immutable/Map$
  #240 = Utf8               empty
  #241 = NameAndType        #240:#36      // empty:()Lscala/collection/immutable/Map;
  #242 = Methodref          #239.#241     // scala/collection/immutable/Map$.empty:()Lscala/collection/immutable/Map;
  #243 = Utf8               (Ljava/lang/Object;Ljava/lang/Object;)Ljava/lang/Object;
  #244 = MethodType         #243          //  (Ljava/lang/Object;Ljava/lang/Object;)Ljava/lang/Object;
  #245 = Utf8               $anonfun$map$1
  #246 = Utf8               (Lscala/Function1;Lscala/collection/immutable/Map;Lscala/Tuple2;)Lscala/collection/immutable/Map;
  #247 = NameAndType        #245:#246     // $anonfun$map$1:(Lscala/Function1;Lscala/collection/immutable/Map;Lscala/Tuple2;)Lscala/collection/immutable/Map;
  #248 = Methodref          #2.#247       // argonaut/JsonObjectInstance.$anonfun$map$1:(Lscala/Function1;Lscala/collection/immutable/Map;Lscala/Tuple2;)Lscala/collection/immutable/Map;
  #249 = MethodHandle       6:#248        // REF_invokeStatic argonaut/JsonObjectInstance.$anonfun$map$1:(Lscala/Function1;Lscala/collection/immutable/Map;Lscala/Tuple2;)Lscala/collection/immutable/Map;
  #250 = Utf8               (Lscala/collection/immutable/Map;Lscala/Tuple2;)Lscala/collection/immutable/Map;
  #251 = MethodType         #250          //  (Lscala/collection/immutable/Map;Lscala/Tuple2;)Lscala/collection/immutable/Map;
  #252 = Utf8               (Lscala/Function1;)Lscala/Function2;
  #253 = NameAndType        #161:#252     // apply:(Lscala/Function1;)Lscala/Function2;
  #254 = InvokeDynamic      #3:#253       // #3:apply:(Lscala/Function1;)Lscala/Function2;
  #255 = Utf8               foldLeft
  #256 = Utf8               (Ljava/lang/Object;Lscala/Function2;)Ljava/lang/Object;
  #257 = NameAndType        #255:#256     // foldLeft:(Ljava/lang/Object;Lscala/Function2;)Ljava/lang/Object;
  #258 = InterfaceMethodref #82.#257      // scala/collection/immutable/Map.foldLeft:(Ljava/lang/Object;Lscala/Function2;)Ljava/lang/Object;
  #259 = Utf8               size
  #260 = Utf8               ()I
  #261 = NameAndType        #220:#192     // fields:()Lscala/collection/immutable/List;
  #262 = Methodref          #2.#261       // argonaut/JsonObjectInstance.fields:()Lscala/collection/immutable/List;
  #263 = Utf8               scala/collection/immutable/List
  #264 = Class              #263          // scala/collection/immutable/List
  #265 = NameAndType        #259:#260     // size:()I
  #266 = Methodref          #264.#265     // scala/collection/immutable/List.size:()I
  #267 = Utf8               toString
  #268 = Utf8               ()Ljava/lang/String;
  #269 = Utf8               java/lang/StringBuilder
  #270 = Class              #269          // java/lang/StringBuilder
  #271 = Integer            8
  #272 = Utf8               (I)V
  #273 = NameAndType        #128:#272     // "<init>":(I)V
  #274 = Methodref          #270.#273     // java/lang/StringBuilder."<init>":(I)V
  #275 = Utf8               object[
  #276 = String             #275          // object[
  #277 = Utf8               append
  #278 = Utf8               (Ljava/lang/String;)Ljava/lang/StringBuilder;
  #279 = NameAndType        #277:#278     // append:(Ljava/lang/String;)Ljava/lang/StringBuilder;
  #280 = Methodref          #270.#279     // java/lang/StringBuilder.append:(Ljava/lang/String;)Ljava/lang/StringBuilder;
  #281 = Utf8               $anonfun$toString$1
  #282 = Utf8               (Lscala/Tuple2;)Ljava/lang/String;
  #283 = NameAndType        #281:#282     // $anonfun$toString$1:(Lscala/Tuple2;)Ljava/lang/String;
  #284 = Methodref          #2.#283       // argonaut/JsonObjectInstance.$anonfun$toString$1:(Lscala/Tuple2;)Ljava/lang/String;
  #285 = MethodHandle       6:#284        // REF_invokeStatic argonaut/JsonObjectInstance.$anonfun$toString$1:(Lscala/Tuple2;)Ljava/lang/String;
  #286 = MethodType         #282          //  (Lscala/Tuple2;)Ljava/lang/String;
  #287 = NameAndType        #161:#53      // apply:()Lscala/Function1;
  #288 = InvokeDynamic      #4:#287       // #4:apply:()Lscala/Function1;
  #289 = InterfaceMethodref #82.#204      // scala/collection/immutable/Map.map:(Lscala/Function1;)Ljava/lang/Object;
  #290 = Utf8               ,
  #291 = String             #290          // ,
  #292 = Utf8               mkString
  #293 = Utf8               (Ljava/lang/String;)Ljava/lang/String;
  #294 = NameAndType        #292:#293     // mkString:(Ljava/lang/String;)Ljava/lang/String;
  #295 = InterfaceMethodref #207.#294     // scala/collection/IterableOnceOps.mkString:(Ljava/lang/String;)Ljava/lang/String;
  #296 = Utf8               ]
  #297 = String             #296          // ]
  #298 = NameAndType        #267:#268     // toString:()Ljava/lang/String;
  #299 = Methodref          #270.#298     // java/lang/StringBuilder.toString:()Ljava/lang/String;
  #300 = Utf8               equals
  #301 = Utf8               o
  #302 = Utf8               java/lang/Object
  #303 = Class              #302          // java/lang/Object
  #304 = NameAndType        #300:#84      // equals:(Ljava/lang/Object;)Z
  #305 = Methodref          #303.#304     // java/lang/Object.equals:(Ljava/lang/Object;)Z
  #306 = Utf8               otherMap
  #307 = Utf8               Ljava/lang/Object;
  #308 = Utf8               hashCode
  #309 = Utf8               scala/collection/Map
  #310 = Class              #309          // scala/collection/Map
  #311 = NameAndType        #308:#260     // hashCode:()I
  #312 = InterfaceMethodref #310.#311     // scala/collection/Map.hashCode:()I
  #313 = Utf8               (Lscala/collection/immutable/Map<Ljava/lang/String;Largonaut/Json;>;Lscala/collection/immutable/Vector<Ljava/lang/String;>;)Largonaut/JsonObjectInstance;
  #314 = Utf8               (Lscala/collection/immutable/Map;Lscala/collection/immutable/Vector;)V
  #315 = NameAndType        #128:#314     // "<init>":(Lscala/collection/immutable/Map;Lscala/collection/immutable/Vector;)V
  #316 = Methodref          #2.#315       // argonaut/JsonObjectInstance."<init>":(Lscala/collection/immutable/Map;Lscala/collection/immutable/Vector;)V
  #317 = Utf8               copy$default$1
  #318 = Utf8               productPrefix
  #319 = Utf8               JsonObjectInstance
  #320 = String             #319          // JsonObjectInstance
  #321 = Utf8               productArity
  #322 = Utf8               productElement
  #323 = Utf8               (I)Ljava/lang/Object;
  #324 = Utf8               x$1
  #325 = Utf8               scala/runtime/Statics
  #326 = Class              #325          // scala/runtime/Statics
  #327 = Utf8               ioobe
  #328 = NameAndType        #327:#323     // ioobe:(I)Ljava/lang/Object;
  #329 = Methodref          #326.#328     // scala/runtime/Statics.ioobe:(I)Ljava/lang/Object;
  #330 = Utf8               I
  #331 = Utf8               productIterator
  #332 = Utf8               ()Lscala/collection/Iterator<Ljava/lang/Object;>;
  #333 = Utf8               scala/runtime/ScalaRunTime$
  #334 = Class              #333          // scala/runtime/ScalaRunTime$
  #335 = Utf8               Lscala/runtime/ScalaRunTime$;
  #336 = NameAndType        #29:#335      // MODULE$:Lscala/runtime/ScalaRunTime$;
  #337 = Fieldref           #334.#336     // scala/runtime/ScalaRunTime$.MODULE$:Lscala/runtime/ScalaRunTime$;
  #338 = Utf8               typedProductIterator
  #339 = NameAndType        #338:#65      // typedProductIterator:(Lscala/Product;)Lscala/collection/Iterator;
  #340 = Methodref          #334.#339     // scala/runtime/ScalaRunTime$.typedProductIterator:(Lscala/Product;)Lscala/collection/Iterator;
  #341 = Utf8               canEqual
  #342 = Utf8               productElementName
  #343 = Utf8               (I)Ljava/lang/String;
  #344 = String             #18           // fieldsMap
  #345 = String             #21           // orderedFields
  #346 = Utf8               $anonfun$$minus$1
  #347 = Utf8               (Ljava/lang/String;Ljava/lang/String;)Z
  #348 = Utf8               f$1
  #349 = Utf8               x$2
  #350 = Utf8               $this
  #351 = Utf8               field
  #352 = NameAndType        #161:#103     // apply:(Ljava/lang/Object;)Ljava/lang/Object;
  #353 = InterfaceMethodref #82.#352      // scala/collection/immutable/Map.apply:(Ljava/lang/Object;)Ljava/lang/Object;
  #354 = Utf8               f$2
  #355 = Utf8               x0$1
  #356 = Utf8               x1$1
  #357 = Utf8               scala/Function1
  #358 = Class              #357          // scala/Function1
  #359 = InterfaceMethodref #358.#352     // scala/Function1.apply:(Ljava/lang/Object;)Ljava/lang/Object;
  #360 = Utf8               key
  #361 = Utf8               value
  #362 = Utf8               acc
  #363 = Utf8               x$3
  #364 = Methodref          #112.#298     // scala/Tuple2.toString:()Ljava/lang/String;
  #365 = Utf8               (Lscala/collection/immutable/Map<Ljava/lang/String;Largonaut/Json;>;Lscala/collection/immutable/Vector<Ljava/lang/String;>;)V
  #366 = Utf8               ()V
  #367 = NameAndType        #128:#366     // "<init>":()V
  #368 = Methodref          #4.#367       // argonaut/JsonObject."<init>":()V
  #369 = Utf8               $init$
  #370 = Utf8               (Lscala/Product;)V
  #371 = NameAndType        #369:#370     // $init$:(Lscala/Product;)V
  #372 = InterfaceMethodref #6.#371       // scala/Product.$init$:(Lscala/Product;)V
  #373 = NameAndType        #346:#347     // $anonfun$$minus$1:(Ljava/lang/String;Ljava/lang/String;)Z
  #374 = Methodref          #2.#373       // argonaut/JsonObjectInstance.$anonfun$$minus$1:(Ljava/lang/String;Ljava/lang/String;)Z
  #375 = Utf8               scala/runtime/BoxesRunTime
  #376 = Class              #375          // scala/runtime/BoxesRunTime
  #377 = Utf8               boxToBoolean
  #378 = Utf8               (Z)Ljava/lang/Boolean;
  #379 = NameAndType        #377:#378     // boxToBoolean:(Z)Ljava/lang/Boolean;
  #380 = Methodref          #376.#379     // scala/runtime/BoxesRunTime.boxToBoolean:(Z)Ljava/lang/Boolean;
  #381 = Utf8               $deserializeLambda$
  #382 = Utf8               (Ljava/lang/invoke/SerializedLambda;)Ljava/lang/Object;
  #383 = Utf8               scala/runtime/LambdaDeserialize
  #384 = Class              #383          // scala/runtime/LambdaDeserialize
  #385 = Utf8               bootstrap
  #386 = Utf8               (Ljava/lang/invoke/MethodHandles$Lookup;Ljava/lang/String;Ljava/lang/invoke/MethodType;[Ljava/lang/invoke/MethodHandle;)Ljava/lang/invoke/CallSite;
  #387 = NameAndType        #385:#386     // bootstrap:(Ljava/lang/invoke/MethodHandles$Lookup;Ljava/lang/String;Ljava/lang/invoke/MethodType;[Ljava/lang/invoke/MethodHandle;)Ljava/lang/invoke/CallSite;
  #388 = Methodref          #384.#387     // scala/runtime/LambdaDeserialize.bootstrap:(Ljava/lang/invoke/MethodHandles$Lookup;Ljava/lang/String;Ljava/lang/invoke/MethodType;[Ljava/lang/invoke/MethodHandle;)Ljava/lang/invoke/CallSite;
  #389 = MethodHandle       6:#388        // REF_invokeStatic scala/runtime/LambdaDeserialize.bootstrap:(Ljava/lang/invoke/MethodHandles$Lookup;Ljava/lang/String;Ljava/lang/invoke/MethodType;[Ljava/lang/invoke/MethodHandle;)Ljava/lang/invoke/CallSite;
  #390 = Utf8               lambdaDeserialize
  #391 = NameAndType        #390:#382     // lambdaDeserialize:(Ljava/lang/invoke/SerializedLambda;)Ljava/lang/Object;
  #392 = InvokeDynamic      #5:#391       // #5:lambdaDeserialize:(Ljava/lang/invoke/SerializedLambda;)Ljava/lang/Object;
  #393 = Utf8               Signature
  #394 = Utf8               Code
  #395 = Utf8               MethodParameters
  #396 = Utf8               LineNumberTable
  #397 = Utf8               LocalVariableTable
  #398 = Utf8               StackMapTable
  #399 = Utf8               InnerClasses
  #400 = Utf8               SourceFile
  #401 = Utf8               RuntimeVisibleAnnotations
  #402 = Utf8               BootstrapMethods
  #403 = Utf8               ScalaInlineInfo
  #404 = Utf8               ScalaSig
{
  private final scala.collection.immutable.Map<java.lang.String, argonaut.Json> fieldsMap;
    descriptor: Lscala/collection/immutable/Map;
    flags: (0x0012) ACC_PRIVATE, ACC_FINAL
    Signature: #20                          // Lscala/collection/immutable/Map<Ljava/lang/String;Largonaut/Json;>;

  private final scala.collection.immutable.Vector<java.lang.String> orderedFields;
    descriptor: Lscala/collection/immutable/Vector;
    flags: (0x0012) ACC_PRIVATE, ACC_FINAL
    Signature: #23                          // Lscala/collection/immutable/Vector<Ljava/lang/String;>;

  public static scala.collection.immutable.Vector<java.lang.String> $lessinit$greater$default$2();
    descriptor: ()Lscala/collection/immutable/Vector;
    flags: (0x0009) ACC_PUBLIC, ACC_STATIC
    Code:
      stack=1, locals=0, args_size=0
         0: getstatic     #32                 // Field argonaut/JsonObjectInstance$.MODULE$:Largonaut/JsonObjectInstance$;
         3: invokevirtual #34                 // Method argonaut/JsonObjectInstance$.$lessinit$greater$default$2:()Lscala/collection/immutable/Vector;
         6: areturn
    Signature: #26                          // ()Lscala/collection/immutable/Vector<Ljava/lang/String;>;

  public static scala.collection.immutable.Map<java.lang.String, argonaut.Json> $lessinit$greater$default$1();
    descriptor: ()Lscala/collection/immutable/Map;
    flags: (0x0009) ACC_PUBLIC, ACC_STATIC
    Code:
      stack=1, locals=0, args_size=0
         0: getstatic     #32                 // Field argonaut/JsonObjectInstance$.MODULE$:Largonaut/JsonObjectInstance$;
         3: invokevirtual #39                 // Method argonaut/JsonObjectInstance$.$lessinit$greater$default$1:()Lscala/collection/immutable/Map;
         6: areturn
    Signature: #37                          // ()Lscala/collection/immutable/Map<Ljava/lang/String;Largonaut/Json;>;

  public static scala.Option<scala.Tuple2<scala.collection.immutable.Map<java.lang.String, argonaut.Json>, scala.collection.immutable.Vector<java.lang.String>>> unapply(argonaut.JsonObjectInstance);
    descriptor: (Largonaut/JsonObjectInstance;)Lscala/Option;
    flags: (0x0009) ACC_PUBLIC, ACC_STATIC
    Code:
      stack=2, locals=1, args_size=1
         0: getstatic     #32                 // Field argonaut/JsonObjectInstance$.MODULE$:Largonaut/JsonObjectInstance$;
         3: aload_0
         4: invokevirtual #45                 // Method argonaut/JsonObjectInstance$.unapply:(Largonaut/JsonObjectInstance;)Lscala/Option;
         7: areturn
    Signature: #42                          // (Largonaut/JsonObjectInstance;)Lscala/Option<Lscala/Tuple2<Lscala/collection/immutable/Map<Ljava/lang/String;Largonaut/Json;>;Lscala/collection/immutable/Vector<Ljava/lang/String;>;>;>;
    MethodParameters:
      Name                           Flags
      x$0                            final

  public static scala.collection.immutable.Vector<java.lang.String> apply$default$2();
    descriptor: ()Lscala/collection/immutable/Vector;
    flags: (0x0009) ACC_PUBLIC, ACC_STATIC
    Code:
      stack=1, locals=0, args_size=0
         0: getstatic     #32                 // Field argonaut/JsonObjectInstance$.MODULE$:Largonaut/JsonObjectInstance$;
         3: invokevirtual #48                 // Method argonaut/JsonObjectInstance$.apply$default$2:()Lscala/collection/immutable/Vector;
         6: areturn
    Signature: #26                          // ()Lscala/collection/immutable/Vector<Ljava/lang/String;>;

  public static scala.collection.immutable.Map<java.lang.String, argonaut.Json> apply$default$1();
    descriptor: ()Lscala/collection/immutable/Map;
    flags: (0x0009) ACC_PUBLIC, ACC_STATIC
    Code:
      stack=1, locals=0, args_size=0
         0: getstatic     #32                 // Field argonaut/JsonObjectInstance$.MODULE$:Largonaut/JsonObjectInstance$;
         3: invokevirtual #51                 // Method argonaut/JsonObjectInstance$.apply$default$1:()Lscala/collection/immutable/Map;
         6: areturn
    Signature: #37                          // ()Lscala/collection/immutable/Map<Ljava/lang/String;Largonaut/Json;>;

  public static scala.Function1<scala.Tuple2<scala.collection.immutable.Map<java.lang.String, argonaut.Json>, scala.collection.immutable.Vector<java.lang.String>>, argonaut.JsonObjectInstance> tupled();
    descriptor: ()Lscala/Function1;
    flags: (0x0009) ACC_PUBLIC, ACC_STATIC
    Code:
      stack=1, locals=0, args_size=0
         0: getstatic     #32                 // Field argonaut/JsonObjectInstance$.MODULE$:Largonaut/JsonObjectInstance$;
         3: invokevirtual #56                 // Method argonaut/JsonObjectInstance$.tupled:()Lscala/Function1;
         6: areturn
    Signature: #54                          // ()Lscala/Function1<Lscala/Tuple2<Lscala/collection/immutable/Map<Ljava/lang/String;Largonaut/Json;>;Lscala/collection/immutable/Vector<Ljava/lang/String;>;>;Largonaut/JsonObjectInstance;>;

  public static scala.Function1<scala.collection.immutable.Map<java.lang.String, argonaut.Json>, scala.Function1<scala.collection.immutable.Vector<java.lang.String>, argonaut.JsonObjectInstance>> curried();
    descriptor: ()Lscala/Function1;
    flags: (0x0009) ACC_PUBLIC, ACC_STATIC
    Code:
      stack=1, locals=0, args_size=0
         0: getstatic     #32                 // Field argonaut/JsonObjectInstance$.MODULE$:Largonaut/JsonObjectInstance$;
         3: invokevirtual #60                 // Method argonaut/JsonObjectInstance$.curried:()Lscala/Function1;
         6: areturn
    Signature: #58                          // ()Lscala/Function1<Lscala/collection/immutable/Map<Ljava/lang/String;Largonaut/Json;>;Lscala/Function1<Lscala/collection/immutable/Vector<Ljava/lang/String;>;Largonaut/JsonObjectInstance;>;>;

  public scala.collection.Iterator<java.lang.String> productElementNames();
    descriptor: ()Lscala/collection/Iterator;
    flags: (0x0001) ACC_PUBLIC
    Code:
      stack=1, locals=1, args_size=1
         0: aload_0
         1: invokestatic  #67                 // InterfaceMethod scala/Product.productElementNames$:(Lscala/Product;)Lscala/collection/Iterator;
         4: areturn
      LineNumberTable:
        line 92: 0
      LocalVariableTable:
        Start  Length  Slot  Name   Signature
            0       5     0  this   Largonaut/JsonObjectInstance;
    Signature: #63                          // ()Lscala/collection/Iterator<Ljava/lang/String;>;

  public scala.collection.immutable.Map<java.lang.String, argonaut.Json> fieldsMap();
    descriptor: ()Lscala/collection/immutable/Map;
    flags: (0x0001) ACC_PUBLIC
    Code:
      stack=1, locals=1, args_size=1
         0: aload_0
         1: getfield      #71                 // Field fieldsMap:Lscala/collection/immutable/Map;
         4: areturn
      LineNumberTable:
        line 93: 0
      LocalVariableTable:
        Start  Length  Slot  Name   Signature
            0       5     0  this   Largonaut/JsonObjectInstance;
    Signature: #37                          // ()Lscala/collection/immutable/Map<Ljava/lang/String;Largonaut/Json;>;

  public scala.collection.immutable.Vector<java.lang.String> orderedFields();
    descriptor: ()Lscala/collection/immutable/Vector;
    flags: (0x0001) ACC_PUBLIC
    Code:
      stack=1, locals=1, args_size=1
         0: aload_0
         1: getfield      #73                 // Field orderedFields:Lscala/collection/immutable/Vector;
         4: areturn
      LineNumberTable:
        line 94: 0
      LocalVariableTable:
        Start  Length  Slot  Name   Signature
            0       5     0  this   Largonaut/JsonObjectInstance;
    Signature: #26                          // ()Lscala/collection/immutable/Vector<Ljava/lang/String;>;

  public scala.collection.immutable.Map<java.lang.String, argonaut.Json> toMap();
    descriptor: ()Lscala/collection/immutable/Map;
    flags: (0x0001) ACC_PUBLIC
    Code:
      stack=1, locals=1, args_size=1
         0: aload_0
         1: invokevirtual #76                 // Method fieldsMap:()Lscala/collection/immutable/Map;
         4: areturn
      LineNumberTable:
        line 97: 0
      LocalVariableTable:
        Start  Length  Slot  Name   Signature
            0       5     0  this   Largonaut/JsonObjectInstance;
    Signature: #37                          // ()Lscala/collection/immutable/Map<Ljava/lang/String;Largonaut/Json;>;

  public argonaut.JsonObject $plus(java.lang.String, argonaut.Json);
    descriptor: (Ljava/lang/String;Largonaut/Json;)Largonaut/JsonObject;
    flags: (0x0001) ACC_PUBLIC
    Code:
      stack=4, locals=3, args_size=3
         0: aload_0
         1: invokevirtual #76                 // Method fieldsMap:()Lscala/collection/immutable/Map;
         4: aload_1
         5: invokeinterface #86,  2           // InterfaceMethod scala/collection/immutable/Map.contains:(Ljava/lang/Object;)Z
        10: ifeq          38
        13: aload_0
        14: aload_0
        15: invokevirtual #76                 // Method fieldsMap:()Lscala/collection/immutable/Map;
        18: aload_1
        19: aload_2
        20: invokeinterface #90,  3           // InterfaceMethod scala/collection/immutable/Map.updated:(Ljava/lang/Object;Ljava/lang/Object;)Lscala/collection/immutable/MapOps;
        25: checkcast     #82                 // class scala/collection/immutable/Map
        28: aload_0
        29: invokevirtual #93                 // Method copy$default$2:()Lscala/collection/immutable/Vector;
        32: invokevirtual #97                 // Method copy:(Lscala/collection/immutable/Map;Lscala/collection/immutable/Vector;)Largonaut/JsonObjectInstance;
        35: goto          67
        38: aload_0
        39: aload_0
        40: invokevirtual #76                 // Method fieldsMap:()Lscala/collection/immutable/Map;
        43: aload_1
        44: aload_2
        45: invokeinterface #90,  3           // InterfaceMethod scala/collection/immutable/Map.updated:(Ljava/lang/Object;Ljava/lang/Object;)Lscala/collection/immutable/MapOps;
        50: checkcast     #82                 // class scala/collection/immutable/Map
        53: aload_0
        54: invokevirtual #99                 // Method orderedFields:()Lscala/collection/immutable/Vector;
        57: aload_1
        58: invokevirtual #105                // Method scala/collection/immutable/Vector.$colon$plus:(Ljava/lang/Object;)Ljava/lang/Object;
        61: checkcast     #101                // class scala/collection/immutable/Vector
        64: invokevirtual #97                 // Method copy:(Lscala/collection/immutable/Map;Lscala/collection/immutable/Vector;)Largonaut/JsonObjectInstance;
        67: areturn
      StackMapTable: number_of_entries = 2
        frame_type = 38 /* same */
        frame_type = 92 /* same_locals_1_stack_item */
          stack = [ class argonaut/JsonObjectInstance ]
      LineNumberTable:
        line 100: 0
        line 101: 13
        line 103: 38
      LocalVariableTable:
        Start  Length  Slot  Name   Signature
            0      68     0  this   Largonaut/JsonObjectInstance;
            0      68     1     f   Ljava/lang/String;
            0      68     2     j   Largonaut/Json;
    MethodParameters:
      Name                           Flags
      f                              final
      j                              final

  public argonaut.JsonObject $colon$plus(scala.Tuple2<java.lang.String, argonaut.Json>);
    descriptor: (Lscala/Tuple2;)Largonaut/JsonObject;
    flags: (0x0001) ACC_PUBLIC
    Code:
      stack=3, locals=2, args_size=2
         0: aload_0
         1: aload_1
         2: invokevirtual #116                // Method scala/Tuple2._1:()Ljava/lang/Object;
         5: checkcast     #118                // class java/lang/String
         8: aload_1
         9: invokevirtual #121                // Method scala/Tuple2._2:()Ljava/lang/Object;
        12: checkcast     #123                // class argonaut/Json
        15: invokevirtual #125                // Method $plus:(Ljava/lang/String;Largonaut/Json;)Largonaut/JsonObject;
        18: areturn
      LineNumberTable:
        line 108: 0
      LocalVariableTable:
        Start  Length  Slot  Name   Signature
            0      19     0  this   Largonaut/JsonObjectInstance;
            0      19     1    fj   Lscala/Tuple2;
    Signature: #109                         // (Lscala/Tuple2<Ljava/lang/String;Largonaut/Json;>;)Largonaut/JsonObject;
    MethodParameters:
      Name                           Flags
      fj                             final

  public argonaut.JsonObject $plus$colon(scala.Tuple2<java.lang.String, argonaut.Json>);
    descriptor: (Lscala/Tuple2;)Largonaut/JsonObject;
    flags: (0x0001) ACC_PUBLIC
    Code:
      stack=4, locals=10, args_size=2
         0: aload_1
         1: astore        4
         3: aload         4
         5: ifnull        43
         8: aload         4
        10: invokevirtual #116                // Method scala/Tuple2._1:()Ljava/lang/Object;
        13: checkcast     #118                // class java/lang/String
        16: astore        5
        18: aload         4
        20: invokevirtual #121                // Method scala/Tuple2._2:()Ljava/lang/Object;
        23: checkcast     #123                // class argonaut/Json
        26: astore        6
        28: new           #112                // class scala/Tuple2
        31: dup
        32: aload         5
        34: aload         6
        36: invokespecial #131                // Method scala/Tuple2."<init>":(Ljava/lang/Object;Ljava/lang/Object;)V
        39: astore_2
        40: goto          56
        43: goto          46
        46: new           #133                // class scala/MatchError
        49: dup
        50: aload         4
        52: invokespecial #136                // Method scala/MatchError."<init>":(Ljava/lang/Object;)V
        55: athrow
        56: aload_2
        57: astore_3
        58: aload_3
        59: invokevirtual #116                // Method scala/Tuple2._1:()Ljava/lang/Object;
        62: checkcast     #118                // class java/lang/String
        65: astore        7
        67: aload_3
        68: invokevirtual #121                // Method scala/Tuple2._2:()Ljava/lang/Object;
        71: checkcast     #123                // class argonaut/Json
        74: astore        8
        76: aload_0
        77: invokevirtual #76                 // Method fieldsMap:()Lscala/collection/immutable/Map;
        80: aload         7
        82: invokeinterface #86,  2           // InterfaceMethod scala/collection/immutable/Map.contains:(Ljava/lang/Object;)Z
        87: ifeq          117
        90: aload_0
        91: aload_0
        92: invokevirtual #76                 // Method fieldsMap:()Lscala/collection/immutable/Map;
        95: aload         7
        97: aload         8
        99: invokeinterface #90,  3           // InterfaceMethod scala/collection/immutable/Map.updated:(Ljava/lang/Object;Ljava/lang/Object;)Lscala/collection/immutable/MapOps;
       104: checkcast     #82                 // class scala/collection/immutable/Map
       107: aload_0
       108: invokevirtual #93                 // Method copy$default$2:()Lscala/collection/immutable/Vector;
       111: invokevirtual #97                 // Method copy:(Lscala/collection/immutable/Map;Lscala/collection/immutable/Vector;)Largonaut/JsonObjectInstance;
       114: goto          153
       117: aload_0
       118: aload_0
       119: invokevirtual #76                 // Method fieldsMap:()Lscala/collection/immutable/Map;
       122: aload         7
       124: aload         8
       126: invokeinterface #90,  3           // InterfaceMethod scala/collection/immutable/Map.updated:(Ljava/lang/Object;Ljava/lang/Object;)Lscala/collection/immutable/MapOps;
       131: checkcast     #82                 // class scala/collection/immutable/Map
       134: aload         7
       136: astore        9
       138: aload_0
       139: invokevirtual #99                 // Method orderedFields:()Lscala/collection/immutable/Vector;
       142: aload         9
       144: invokevirtual #138                // Method scala/collection/immutable/Vector.$plus$colon:(Ljava/lang/Object;)Ljava/lang/Object;
       147: checkcast     #101                // class scala/collection/immutable/Vector
       150: invokevirtual #97                 // Method copy:(Lscala/collection/immutable/Map;Lscala/collection/immutable/Vector;)Largonaut/JsonObjectInstance;
       153: areturn
      StackMapTable: number_of_entries = 5
        frame_type = 254 /* append */
          offset_delta = 43
          locals = [ top, top, class scala/Tuple2 ]
        frame_type = 2 /* same */
        frame_type = 255 /* full_frame */
          offset_delta = 9
          locals = [ class argonaut/JsonObjectInstance, class scala/Tuple2, class scala/Tuple2, top, class scala/Tuple2, class java/lang/String, class argonaut/Json ]
          stack = []
        frame_type = 255 /* full_frame */
          offset_delta = 60
          locals = [ class argonaut/JsonObjectInstance, class scala/Tuple2, class scala/Tuple2, class scala/Tuple2, class scala/Tuple2, class java/lang/String, class argonaut/Json, class java/lang/String, class argonaut/Json ]
          stack = []
        frame_type = 99 /* same_locals_1_stack_item */
          stack = [ class argonaut/JsonObjectInstance ]
      LineNumberTable:
        line 112: 0
        line 113: 76
        line 114: 90
        line 116: 117
      LocalVariableTable:
        Start  Length  Slot  Name   Signature
           16      27     5     f   Ljava/lang/String;
           26      17     6     j   Largonaut/Json;
           65      88     7     f   Ljava/lang/String;
           74      79     8     j   Largonaut/Json;
            0     154     0  this   Largonaut/JsonObjectInstance;
            0     154     1    fj   Lscala/Tuple2;
    Signature: #109                         // (Lscala/Tuple2<Ljava/lang/String;Largonaut/Json;>;)Largonaut/JsonObject;
    MethodParameters:
      Name                           Flags
      fj                             final

  public argonaut.JsonObject $minus(java.lang.String);
    descriptor: (Ljava/lang/String;)Largonaut/JsonObject;
    flags: (0x0001) ACC_PUBLIC
    Code:
      stack=4, locals=2, args_size=2
         0: aload_0
         1: aload_0
         2: invokevirtual #76                 // Method fieldsMap:()Lscala/collection/immutable/Map;
         5: aload_1
         6: invokeinterface #143,  2          // InterfaceMethod scala/collection/immutable/Map.$minus:(Ljava/lang/Object;)Lscala/collection/immutable/MapOps;
        11: checkcast     #82                 // class scala/collection/immutable/Map
        14: aload_0
        15: invokevirtual #99                 // Method orderedFields:()Lscala/collection/immutable/Vector;
        18: aload_1
        19: invokedynamic #164,  0            // InvokeDynamic #0:apply:(Ljava/lang/String;)Lscala/Function1;
        24: invokevirtual #168                // Method scala/collection/immutable/Vector.filterNot:(Lscala/Function1;)Ljava/lang/Object;
        27: checkcast     #101                // class scala/collection/immutable/Vector
        30: invokevirtual #97                 // Method copy:(Lscala/collection/immutable/Map;Lscala/collection/immutable/Vector;)Largonaut/JsonObjectInstance;
        33: areturn
      LineNumberTable:
        line 120: 0
      LocalVariableTable:
        Start  Length  Slot  Name   Signature
            0      34     0  this   Largonaut/JsonObjectInstance;
            0      34     1     f   Ljava/lang/String;
    MethodParameters:
      Name                           Flags
      f                              final

  public scala.Option<argonaut.Json> apply(java.lang.String);
    descriptor: (Ljava/lang/String;)Lscala/Option;
    flags: (0x0001) ACC_PUBLIC
    Code:
      stack=2, locals=2, args_size=2
         0: aload_0
         1: invokevirtual #76                 // Method fieldsMap:()Lscala/collection/immutable/Map;
         4: aload_1
         5: invokeinterface #174,  2          // InterfaceMethod scala/collection/immutable/Map.get:(Ljava/lang/Object;)Lscala/Option;
        10: areturn
      LineNumberTable:
        line 122: 0
      LocalVariableTable:
        Start  Length  Slot  Name   Signature
            0      11     0  this   Largonaut/JsonObjectInstance;
            0      11     1     f   Ljava/lang/String;
    Signature: #170                         // (Ljava/lang/String;)Lscala/Option<Largonaut/Json;>;
    MethodParameters:
      Name                           Flags
      f                              final

  public argonaut.JsonObject withJsons(scala.Function1<argonaut.Json, argonaut.Json>);
    descriptor: (Lscala/Function1;)Largonaut/JsonObject;
    flags: (0x0001) ACC_PUBLIC
    Code:
      stack=2, locals=2, args_size=2
         0: aload_0
         1: aload_1
         2: invokevirtual #181                // Method map:(Lscala/Function1;)Largonaut/JsonObject;
         5: areturn
      LineNumberTable:
        line 124: 0
      LocalVariableTable:
        Start  Length  Slot  Name   Signature
            0       6     0  this   Largonaut/JsonObjectInstance;
            0       6     1     k   Lscala/Function1;
    Signature: #177                         // (Lscala/Function1<Largonaut/Json;Largonaut/Json;>;)Largonaut/JsonObject;
    MethodParameters:
      Name                           Flags
      k                              final

  public boolean isEmpty();
    descriptor: ()Z
    flags: (0x0001) ACC_PUBLIC
    Code:
      stack=1, locals=1, args_size=1
         0: aload_0
         1: invokevirtual #76                 // Method fieldsMap:()Lscala/collection/immutable/Map;
         4: invokeinterface #186,  1          // InterfaceMethod scala/collection/immutable/Map.isEmpty:()Z
         9: ireturn
      LineNumberTable:
        line 126: 0
      LocalVariableTable:
        Start  Length  Slot  Name   Signature
            0      10     0  this   Largonaut/JsonObjectInstance;

  public boolean isNotEmpty();
    descriptor: ()Z
    flags: (0x0001) ACC_PUBLIC
    Code:
      stack=1, locals=1, args_size=1
         0: aload_0
         1: invokevirtual #188                // Method isEmpty:()Z
         4: ifne          11
         7: iconst_1
         8: goto          12
        11: iconst_0
        12: ireturn
      StackMapTable: number_of_entries = 2
        frame_type = 11 /* same */
        frame_type = 64 /* same_locals_1_stack_item */
          stack = [ int ]
      LineNumberTable:
        line 128: 0
      LocalVariableTable:
        Start  Length  Slot  Name   Signature
            0      13     0  this   Largonaut/JsonObjectInstance;

  public boolean $qmark$qmark(java.lang.String);
    descriptor: (Ljava/lang/String;)Z
    flags: (0x0001) ACC_PUBLIC
    Code:
      stack=2, locals=2, args_size=2
         0: aload_0
         1: invokevirtual #76                 // Method fieldsMap:()Lscala/collection/immutable/Map;
         4: aload_1
         5: invokeinterface #86,  2           // InterfaceMethod scala/collection/immutable/Map.contains:(Ljava/lang/Object;)Z
        10: ireturn
      LineNumberTable:
        line 130: 0
      LocalVariableTable:
        Start  Length  Slot  Name   Signature
            0      11     0  this   Largonaut/JsonObjectInstance;
            0      11     1     f   Ljava/lang/String;
    MethodParameters:
      Name                           Flags
      f                              final

  public scala.collection.immutable.List<scala.Tuple2<java.lang.String, argonaut.Json>> toList();
    descriptor: ()Lscala/collection/immutable/List;
    flags: (0x0001) ACC_PUBLIC
    Code:
      stack=2, locals=1, args_size=1
         0: aload_0
         1: invokevirtual #99                 // Method orderedFields:()Lscala/collection/immutable/Vector;
         4: aload_0
         5: invokedynamic #203,  0            // InvokeDynamic #1:apply:(Largonaut/JsonObjectInstance;)Lscala/Function1;
        10: invokevirtual #205                // Method scala/collection/immutable/Vector.map:(Lscala/Function1;)Ljava/lang/Object;
        13: checkcast     #207                // class scala/collection/IterableOnceOps
        16: invokeinterface #209,  1          // InterfaceMethod scala/collection/IterableOnceOps.toList:()Lscala/collection/immutable/List;
        21: areturn
      LineNumberTable:
        line 132: 0
      LocalVariableTable:
        Start  Length  Slot  Name   Signature
            0      22     0  this   Largonaut/JsonObjectInstance;
    Signature: #193                         // ()Lscala/collection/immutable/List<Lscala/Tuple2<Ljava/lang/String;Largonaut/Json;>;>;

  public scala.collection.immutable.List<argonaut.Json> values();
    descriptor: ()Lscala/collection/immutable/List;
    flags: (0x0001) ACC_PUBLIC
    Code:
      stack=2, locals=1, args_size=1
         0: aload_0
         1: invokevirtual #99                 // Method orderedFields:()Lscala/collection/immutable/Vector;
         4: aload_0
         5: invokedynamic #219,  0            // InvokeDynamic #2:apply:(Largonaut/JsonObjectInstance;)Lscala/Function1;
        10: invokevirtual #205                // Method scala/collection/immutable/Vector.map:(Lscala/Function1;)Ljava/lang/Object;
        13: checkcast     #207                // class scala/collection/IterableOnceOps
        16: invokeinterface #209,  1          // InterfaceMethod scala/collection/IterableOnceOps.toList:()Lscala/collection/immutable/List;
        21: areturn
      LineNumberTable:
        line 134: 0
      LocalVariableTable:
        Start  Length  Slot  Name   Signature
            0      22     0  this   Largonaut/JsonObjectInstance;
    Signature: #211                         // ()Lscala/collection/immutable/List<Largonaut/Json;>;

  public scala.collection.immutable.List<java.lang.String> fields();
    descriptor: ()Lscala/collection/immutable/List;
    flags: (0x0001) ACC_PUBLIC
    Code:
      stack=1, locals=1, args_size=1
         0: aload_0
         1: invokevirtual #99                 // Method orderedFields:()Lscala/collection/immutable/Vector;
         4: invokevirtual #222                // Method scala/collection/immutable/Vector.toList:()Lscala/collection/immutable/List;
         7: areturn
      LineNumberTable:
        line 136: 0
      LocalVariableTable:
        Start  Length  Slot  Name   Signature
            0       8     0  this   Largonaut/JsonObjectInstance;
    Signature: #221                         // ()Lscala/collection/immutable/List<Ljava/lang/String;>;

  public scala.collection.immutable.Set<java.lang.String> fieldSet();
    descriptor: ()Lscala/collection/immutable/Set;
    flags: (0x0001) ACC_PUBLIC
    Code:
      stack=1, locals=1, args_size=1
         0: aload_0
         1: invokevirtual #99                 // Method orderedFields:()Lscala/collection/immutable/Vector;
         4: invokevirtual #228                // Method scala/collection/immutable/Vector.toSet:()Lscala/collection/immutable/Set;
         7: areturn
      LineNumberTable:
        line 138: 0
      LocalVariableTable:
        Start  Length  Slot  Name   Signature
            0       8     0  this   Largonaut/JsonObjectInstance;
    Signature: #225                         // ()Lscala/collection/immutable/Set<Ljava/lang/String;>;

  public argonaut.JsonObject map(scala.Function1<argonaut.Json, argonaut.Json>);
    descriptor: (Lscala/Function1;)Largonaut/JsonObject;
    flags: (0x0001) ACC_PUBLIC
    Code:
      stack=4, locals=2, args_size=2
         0: aload_0
         1: aload_0
         2: invokevirtual #76                 // Method fieldsMap:()Lscala/collection/immutable/Map;
         5: getstatic     #233                // Field scala/Predef$.MODULE$:Lscala/Predef$;
         8: invokevirtual #237                // Method scala/Predef$.Map:()Lscala/collection/immutable/Map$;
        11: invokevirtual #242                // Method scala/collection/immutable/Map$.empty:()Lscala/collection/immutable/Map;
        14: aload_1
        15: invokedynamic #254,  0            // InvokeDynamic #3:apply:(Lscala/Function1;)Lscala/Function2;
        20: invokeinterface #258,  3          // InterfaceMethod scala/collection/immutable/Map.foldLeft:(Ljava/lang/Object;Lscala/Function2;)Ljava/lang/Object;
        25: checkcast     #82                 // class scala/collection/immutable/Map
        28: aload_0
        29: invokevirtual #93                 // Method copy$default$2:()Lscala/collection/immutable/Vector;
        32: invokevirtual #97                 // Method copy:(Lscala/collection/immutable/Map;Lscala/collection/immutable/Vector;)Largonaut/JsonObjectInstance;
        35: areturn
      LineNumberTable:
        line 140: 0
      LocalVariableTable:
        Start  Length  Slot  Name   Signature
            0      36     0  this   Largonaut/JsonObjectInstance;
            0      36     1     f   Lscala/Function1;
    Signature: #177                         // (Lscala/Function1<Largonaut/Json;Largonaut/Json;>;)Largonaut/JsonObject;
    MethodParameters:
      Name                           Flags
      f                              final

  public int size();
    descriptor: ()I
    flags: (0x0001) ACC_PUBLIC
    Code:
      stack=1, locals=1, args_size=1
         0: aload_0
         1: invokevirtual #262                // Method fields:()Lscala/collection/immutable/List;
         4: invokevirtual #266                // Method scala/collection/immutable/List.size:()I
         7: ireturn
      LineNumberTable:
        line 142: 0
      LocalVariableTable:
        Start  Length  Slot  Name   Signature
            0       8     0  this   Largonaut/JsonObjectInstance;

  public java.lang.String toString();
    descriptor: ()Ljava/lang/String;
    flags: (0x0001) ACC_PUBLIC
    Code:
      stack=3, locals=1, args_size=1
         0: new           #270                // class java/lang/StringBuilder
         3: dup
         4: ldc_w         #271                // int 8
         7: invokespecial #274                // Method java/lang/StringBuilder."<init>":(I)V
        10: ldc_w         #276                // String object[
        13: invokevirtual #280                // Method java/lang/StringBuilder.append:(Ljava/lang/String;)Ljava/lang/StringBuilder;
        16: aload_0
        17: invokevirtual #76                 // Method fieldsMap:()Lscala/collection/immutable/Map;
        20: invokedynamic #288,  0            // InvokeDynamic #4:apply:()Lscala/Function1;
        25: invokeinterface #289,  2          // InterfaceMethod scala/collection/immutable/Map.map:(Lscala/Function1;)Ljava/lang/Object;
        30: checkcast     #207                // class scala/collection/IterableOnceOps
        33: ldc_w         #291                // String ,
        36: invokeinterface #295,  2          // InterfaceMethod scala/collection/IterableOnceOps.mkString:(Ljava/lang/String;)Ljava/lang/String;
        41: invokevirtual #280                // Method java/lang/StringBuilder.append:(Ljava/lang/String;)Ljava/lang/StringBuilder;
        44: ldc_w         #297                // String ]
        47: invokevirtual #280                // Method java/lang/StringBuilder.append:(Ljava/lang/String;)Ljava/lang/StringBuilder;
        50: invokevirtual #299                // Method java/lang/StringBuilder.toString:()Ljava/lang/String;
        53: areturn
      LineNumberTable:
        line 145: 0
      LocalVariableTable:
        Start  Length  Slot  Name   Signature
            0      54     0  this   Largonaut/JsonObjectInstance;

  public boolean equals(java.lang.Object);
    descriptor: (Ljava/lang/Object;)Z
    flags: (0x0001) ACC_PUBLIC
    Code:
      stack=2, locals=7, args_size=2
         0: aload_1
         1: astore_3
         2: aload_3
         3: instanceof    #2                  // class argonaut/JsonObjectInstance
         6: ifeq          60
         9: aload_3
        10: checkcast     #2                  // class argonaut/JsonObjectInstance
        13: astore        4
        15: aload         4
        17: invokevirtual #76                 // Method fieldsMap:()Lscala/collection/immutable/Map;
        20: astore        5
        22: aload_0
        23: invokevirtual #76                 // Method fieldsMap:()Lscala/collection/immutable/Map;
        26: aload         5
        28: astore        6
        30: dup
        31: ifnonnull     43
        34: pop
        35: aload         6
        37: ifnull        51
        40: goto          55
        43: aload         6
        45: invokevirtual #305                // Method java/lang/Object.equals:(Ljava/lang/Object;)Z
        48: ifeq          55
        51: iconst_1
        52: goto          56
        55: iconst_0
        56: istore_2
        57: goto          68
        60: goto          63
        63: iconst_0
        64: istore_2
        65: goto          68
        68: iload_2
        69: ireturn
      StackMapTable: number_of_entries = 7
        frame_type = 255 /* full_frame */
          offset_delta = 43
          locals = [ class argonaut/JsonObjectInstance, class java/lang/Object, top, class java/lang/Object, class argonaut/JsonObjectInstance, class scala/collection/immutable/Map, class scala/collection/immutable/Map ]
          stack = [ class scala/collection/immutable/Map ]
        frame_type = 7 /* same */
        frame_type = 3 /* same */
        frame_type = 64 /* same_locals_1_stack_item */
          stack = [ int ]
        frame_type = 248 /* chop */
          offset_delta = 3
        frame_type = 2 /* same */
        frame_type = 255 /* full_frame */
          offset_delta = 4
          locals = [ class argonaut/JsonObjectInstance, class java/lang/Object, int, class java/lang/Object ]
          stack = []
      LineNumberTable:
        line 149: 0
        line 150: 2
        line 151: 63
        line 149: 68
      LocalVariableTable:
        Start  Length  Slot  Name   Signature
           20      40     5 otherMap   Lscala/collection/immutable/Map;
            0      70     0  this   Largonaut/JsonObjectInstance;
            0      70     1     o   Ljava/lang/Object;
    MethodParameters:
      Name                           Flags
      o                              final

  public int hashCode();
    descriptor: ()I
    flags: (0x0001) ACC_PUBLIC
    Code:
      stack=1, locals=1, args_size=1
         0: aload_0
         1: invokevirtual #76                 // Method fieldsMap:()Lscala/collection/immutable/Map;
         4: invokeinterface #312,  1          // InterfaceMethod scala/collection/Map.hashCode:()I
         9: ireturn
      LineNumberTable:
        line 155: 0
      LocalVariableTable:
        Start  Length  Slot  Name   Signature
            0      10     0  this   Largonaut/JsonObjectInstance;

  public argonaut.JsonObjectInstance copy(scala.collection.immutable.Map<java.lang.String, argonaut.Json>, scala.collection.immutable.Vector<java.lang.String>);
    descriptor: (Lscala/collection/immutable/Map;Lscala/collection/immutable/Vector;)Largonaut/JsonObjectInstance;
    flags: (0x0001) ACC_PUBLIC
    Code:
      stack=4, locals=3, args_size=3
         0: new           #2                  // class argonaut/JsonObjectInstance
         3: dup
         4: aload_1
         5: aload_2
         6: invokespecial #316                // Method "<init>":(Lscala/collection/immutable/Map;Lscala/collection/immutable/Vector;)V
         9: areturn
      LineNumberTable:
        line 92: 0
        line 93: 4
        line 94: 5
      LocalVariableTable:
        Start  Length  Slot  Name   Signature
            0      10     0  this   Largonaut/JsonObjectInstance;
            0      10     1 fieldsMap   Lscala/collection/immutable/Map;
            0      10     2 orderedFields   Lscala/collection/immutable/Vector;
    Signature: #313                         // (Lscala/collection/immutable/Map<Ljava/lang/String;Largonaut/Json;>;Lscala/collection/immutable/Vector<Ljava/lang/String;>;)Largonaut/JsonObjectInstance;
    MethodParameters:
      Name                           Flags
      fieldsMap                      final
      orderedFields                  final

  public scala.collection.immutable.Map<java.lang.String, argonaut.Json> copy$default$1();
    descriptor: ()Lscala/collection/immutable/Map;
    flags: (0x0001) ACC_PUBLIC
    Code:
      stack=1, locals=1, args_size=1
         0: aload_0
         1: invokevirtual #76                 // Method fieldsMap:()Lscala/collection/immutable/Map;
         4: areturn
      LineNumberTable:
        line 93: 0
      LocalVariableTable:
        Start  Length  Slot  Name   Signature
            0       5     0  this   Largonaut/JsonObjectInstance;
    Signature: #37                          // ()Lscala/collection/immutable/Map<Ljava/lang/String;Largonaut/Json;>;

  public scala.collection.immutable.Vector<java.lang.String> copy$default$2();
    descriptor: ()Lscala/collection/immutable/Vector;
    flags: (0x0001) ACC_PUBLIC
    Code:
      stack=1, locals=1, args_size=1
         0: aload_0
         1: invokevirtual #99                 // Method orderedFields:()Lscala/collection/immutable/Vector;
         4: areturn
      LineNumberTable:
        line 94: 0
      LocalVariableTable:
        Start  Length  Slot  Name   Signature
            0       5     0  this   Largonaut/JsonObjectInstance;
    Signature: #26                          // ()Lscala/collection/immutable/Vector<Ljava/lang/String;>;

  public java.lang.String productPrefix();
    descriptor: ()Ljava/lang/String;
    flags: (0x0001) ACC_PUBLIC
    Code:
      stack=1, locals=1, args_size=1
         0: ldc_w         #320                // String JsonObjectInstance
         3: areturn
      LineNumberTable:
        line 92: 0
      LocalVariableTable:
        Start  Length  Slot  Name   Signature
            0       4     0  this   Largonaut/JsonObjectInstance;

  public int productArity();
    descriptor: ()I
    flags: (0x0001) ACC_PUBLIC
    Code:
      stack=1, locals=1, args_size=1
         0: iconst_2
         1: ireturn
      LineNumberTable:
        line 92: 0
      LocalVariableTable:
        Start  Length  Slot  Name   Signature
            0       2     0  this   Largonaut/JsonObjectInstance;

  public java.lang.Object productElement(int);
    descriptor: (I)Ljava/lang/Object;
    flags: (0x0001) ACC_PUBLIC
    Code:
      stack=1, locals=3, args_size=2
         0: iload_1
         1: istore_2
         2: iload_2
         3: tableswitch   { // 0 to 1
                       0: 24
                       1: 31
                 default: 38
            }
        24: aload_0
        25: invokevirtual #76                 // Method fieldsMap:()Lscala/collection/immutable/Map;
        28: goto          45
        31: aload_0
        32: invokevirtual #99                 // Method orderedFields:()Lscala/collection/immutable/Vector;
        35: goto          45
        38: iload_1
        39: invokestatic  #329                // Method scala/runtime/Statics.ioobe:(I)Ljava/lang/Object;
        42: goto          45
        45: areturn
      StackMapTable: number_of_entries = 4
        frame_type = 252 /* append */
          offset_delta = 24
          locals = [ int ]
        frame_type = 6 /* same */
        frame_type = 6 /* same */
        frame_type = 70 /* same_locals_1_stack_item */
          stack = [ class java/lang/Object ]
      LineNumberTable:
        line 92: 0
      LocalVariableTable:
        Start  Length  Slot  Name   Signature
            0      46     0  this   Largonaut/JsonObjectInstance;
            0      46     1   x$1   I
    MethodParameters:
      Name                           Flags
      x$1                            final

  public scala.collection.Iterator<java.lang.Object> productIterator();
    descriptor: ()Lscala/collection/Iterator;
    flags: (0x0001) ACC_PUBLIC
    Code:
      stack=2, locals=1, args_size=1
         0: getstatic     #337                // Field scala/runtime/ScalaRunTime$.MODULE$:Lscala/runtime/ScalaRunTime$;
         3: aload_0
         4: invokevirtual #340                // Method scala/runtime/ScalaRunTime$.typedProductIterator:(Lscala/Product;)Lscala/collection/Iterator;
         7: areturn
      LineNumberTable:
        line 92: 0
      LocalVariableTable:
        Start  Length  Slot  Name   Signature
            0       8     0  this   Largonaut/JsonObjectInstance;
    Signature: #332                         // ()Lscala/collection/Iterator<Ljava/lang/Object;>;

  public boolean canEqual(java.lang.Object);
    descriptor: (Ljava/lang/Object;)Z
    flags: (0x0001) ACC_PUBLIC
    Code:
      stack=1, locals=2, args_size=2
         0: aload_1
         1: instanceof    #2                  // class argonaut/JsonObjectInstance
         4: ireturn
      LineNumberTable:
        line 92: 0
      LocalVariableTable:
        Start  Length  Slot  Name   Signature
            0       5     0  this   Largonaut/JsonObjectInstance;
            0       5     1   x$1   Ljava/lang/Object;
    MethodParameters:
      Name                           Flags
      x$1                            final

  public java.lang.String productElementName(int);
    descriptor: (I)Ljava/lang/String;
    flags: (0x0001) ACC_PUBLIC
    Code:
      stack=1, locals=3, args_size=2
         0: iload_1
         1: istore_2
         2: iload_2
         3: tableswitch   { // 0 to 1
                       0: 24
                       1: 30
                 default: 36
            }
        24: ldc_w         #344                // String fieldsMap
        27: goto          46
        30: ldc_w         #345                // String orderedFields
        33: goto          46
        36: iload_1
        37: invokestatic  #329                // Method scala/runtime/Statics.ioobe:(I)Ljava/lang/Object;
        40: checkcast     #118                // class java/lang/String
        43: goto          46
        46: areturn
      StackMapTable: number_of_entries = 4
        frame_type = 252 /* append */
          offset_delta = 24
          locals = [ int ]
        frame_type = 5 /* same */
        frame_type = 5 /* same */
        frame_type = 73 /* same_locals_1_stack_item */
          stack = [ class java/lang/String ]
      LineNumberTable:
        line 92: 0
      LocalVariableTable:
        Start  Length  Slot  Name   Signature
            0      47     0  this   Largonaut/JsonObjectInstance;
            0      47     1   x$1   I
    MethodParameters:
      Name                           Flags
      x$1                            final

  public static final boolean $anonfun$$minus$1(java.lang.String, java.lang.String);
    descriptor: (Ljava/lang/String;Ljava/lang/String;)Z
    flags: (0x1019) ACC_PUBLIC, ACC_STATIC, ACC_FINAL, ACC_SYNTHETIC
    Code:
      stack=2, locals=3, args_size=2
         0: aload_1
         1: aload_0
         2: astore_2
         3: dup
         4: ifnonnull     15
         7: pop
         8: aload_2
         9: ifnull        22
        12: goto          26
        15: aload_2
        16: invokevirtual #305                // Method java/lang/Object.equals:(Ljava/lang/Object;)Z
        19: ifeq          26
        22: iconst_1
        23: goto          27
        26: iconst_0
        27: ireturn
      StackMapTable: number_of_entries = 4
        frame_type = 255 /* full_frame */
          offset_delta = 15
          locals = [ class java/lang/String, class java/lang/String, class java/lang/String ]
          stack = [ class java/lang/String ]
        frame_type = 6 /* same */
        frame_type = 3 /* same */
        frame_type = 64 /* same_locals_1_stack_item */
          stack = [ int ]
      LineNumberTable:
        line 120: 0
      LocalVariableTable:
        Start  Length  Slot  Name   Signature
            0      28     0   f$1   Ljava/lang/String;
            0      28     1   x$2   Ljava/lang/String;
    MethodParameters:
      Name                           Flags
      f$1                            final
      x$2                            final

  public static final scala.Tuple2 $anonfun$toList$1(argonaut.JsonObjectInstance, java.lang.String);
    descriptor: (Largonaut/JsonObjectInstance;Ljava/lang/String;)Lscala/Tuple2;
    flags: (0x1019) ACC_PUBLIC, ACC_STATIC, ACC_FINAL, ACC_SYNTHETIC
    Code:
      stack=5, locals=2, args_size=2
         0: new           #112                // class scala/Tuple2
         3: dup
         4: aload_1
         5: aload_0
         6: invokevirtual #76                 // Method fieldsMap:()Lscala/collection/immutable/Map;
         9: aload_1
        10: invokeinterface #353,  2          // InterfaceMethod scala/collection/immutable/Map.apply:(Ljava/lang/Object;)Ljava/lang/Object;
        15: invokespecial #131                // Method scala/Tuple2."<init>":(Ljava/lang/Object;Ljava/lang/Object;)V
        18: areturn
      LineNumberTable:
        line 132: 0
      LocalVariableTable:
        Start  Length  Slot  Name   Signature
            0      19     0 $this   Largonaut/JsonObjectInstance;
            0      19     1 field   Ljava/lang/String;
    MethodParameters:
      Name                           Flags
      $this                          final synthetic
      field                          final

  public static final argonaut.Json $anonfun$values$1(argonaut.JsonObjectInstance, java.lang.String);
    descriptor: (Largonaut/JsonObjectInstance;Ljava/lang/String;)Largonaut/Json;
    flags: (0x1019) ACC_PUBLIC, ACC_STATIC, ACC_FINAL, ACC_SYNTHETIC
    Code:
      stack=2, locals=2, args_size=2
         0: aload_0
         1: invokevirtual #76                 // Method fieldsMap:()Lscala/collection/immutable/Map;
         4: aload_1
         5: invokeinterface #353,  2          // InterfaceMethod scala/collection/immutable/Map.apply:(Ljava/lang/Object;)Ljava/lang/Object;
        10: checkcast     #123                // class argonaut/Json
        13: areturn
      LineNumberTable:
        line 134: 0
      LocalVariableTable:
        Start  Length  Slot  Name   Signature
            0      14     0 $this   Largonaut/JsonObjectInstance;
            0      14     1 field   Ljava/lang/String;
    MethodParameters:
      Name                           Flags
      $this                          final synthetic
      field                          final

  public static final scala.collection.immutable.Map $anonfun$map$1(scala.Function1, scala.collection.immutable.Map, scala.Tuple2);
    descriptor: (Lscala/Function1;Lscala/collection/immutable/Map;Lscala/Tuple2;)Lscala/collection/immutable/Map;
    flags: (0x1019) ACC_PUBLIC, ACC_STATIC, ACC_FINAL, ACC_SYNTHETIC
    Code:
      stack=4, locals=9, args_size=3
         0: new           #112                // class scala/Tuple2
         3: dup
         4: aload_1
         5: aload_2
         6: invokespecial #131                // Method scala/Tuple2."<init>":(Ljava/lang/Object;Ljava/lang/Object;)V
         9: astore        4
        11: aload         4
        13: ifnull        88
        16: aload         4
        18: invokevirtual #116                // Method scala/Tuple2._1:()Ljava/lang/Object;
        21: checkcast     #82                 // class scala/collection/immutable/Map
        24: astore        5
        26: aload         4
        28: invokevirtual #121                // Method scala/Tuple2._2:()Ljava/lang/Object;
        31: checkcast     #112                // class scala/Tuple2
        34: astore        6
        36: aload         6
        38: ifnull        85
        41: aload         6
        43: invokevirtual #116                // Method scala/Tuple2._1:()Ljava/lang/Object;
        46: checkcast     #118                // class java/lang/String
        49: astore        7
        51: aload         6
        53: invokevirtual #121                // Method scala/Tuple2._2:()Ljava/lang/Object;
        56: checkcast     #123                // class argonaut/Json
        59: astore        8
        61: aload         5
        63: aload         7
        65: aload_0
        66: aload         8
        68: invokeinterface #359,  2          // InterfaceMethod scala/Function1.apply:(Ljava/lang/Object;)Ljava/lang/Object;
        73: invokeinterface #90,  3           // InterfaceMethod scala/collection/immutable/Map.updated:(Ljava/lang/Object;Ljava/lang/Object;)Lscala/collection/immutable/MapOps;
        78: checkcast     #82                 // class scala/collection/immutable/Map
        81: astore_3
        82: goto          101
        85: goto          91
        88: goto          91
        91: new           #133                // class scala/MatchError
        94: dup
        95: aload         4
        97: invokespecial #136                // Method scala/MatchError."<init>":(Ljava/lang/Object;)V
       100: athrow
       101: aload_3
       102: areturn
      StackMapTable: number_of_entries = 4
        frame_type = 255 /* full_frame */
          offset_delta = 85
          locals = [ class scala/Function1, class scala/collection/immutable/Map, class scala/Tuple2, top, class scala/Tuple2, class scala/collection/immutable/Map, class scala/Tuple2 ]
          stack = []
        frame_type = 249 /* chop */
          offset_delta = 2
        frame_type = 2 /* same */
        frame_type = 255 /* full_frame */
          offset_delta = 9
          locals = [ class scala/Function1, class scala/collection/immutable/Map, class scala/Tuple2, class scala/collection/immutable/Map, class scala/Tuple2, class scala/collection/immutable/Map, class scala/Tuple2, class java/lang/String, class argonaut/Json ]
          stack = []
      LineNumberTable:
        line 140: 0
      LocalVariableTable:
        Start  Length  Slot  Name   Signature
           49      36     7   key   Ljava/lang/String;
           59      26     8 value   Largonaut/Json;
           24      64     5   acc   Lscala/collection/immutable/Map;
            0     103     0   f$2   Lscala/Function1;
            0     103     1  x0$1   Lscala/collection/immutable/Map;
            0     103     2  x1$1   Lscala/Tuple2;
    MethodParameters:
      Name                           Flags
      f$2                            final
      x0$1                           final
      x1$1                           final

  public static final java.lang.String $anonfun$toString$1(scala.Tuple2);
    descriptor: (Lscala/Tuple2;)Ljava/lang/String;
    flags: (0x1019) ACC_PUBLIC, ACC_STATIC, ACC_FINAL, ACC_SYNTHETIC
    Code:
      stack=1, locals=1, args_size=1
         0: aload_0
         1: invokevirtual #364                // Method scala/Tuple2.toString:()Ljava/lang/String;
         4: areturn
      LineNumberTable:
        line 145: 0
      LocalVariableTable:
        Start  Length  Slot  Name   Signature
            0       5     0   x$3   Lscala/Tuple2;
    MethodParameters:
      Name                           Flags
      x$3                            final

  public argonaut.JsonObjectInstance(scala.collection.immutable.Map<java.lang.String, argonaut.Json>, scala.collection.immutable.Vector<java.lang.String>);
    descriptor: (Lscala/collection/immutable/Map;Lscala/collection/immutable/Vector;)V
    flags: (0x0001) ACC_PUBLIC
    Code:
      stack=2, locals=3, args_size=3
         0: aload_0
         1: aload_1
         2: putfield      #71                 // Field fieldsMap:Lscala/collection/immutable/Map;
         5: aload_0
         6: aload_2
         7: putfield      #73                 // Field orderedFields:Lscala/collection/immutable/Vector;
        10: aload_0
        11: invokespecial #368                // Method argonaut/JsonObject."<init>":()V
        14: aload_0
        15: invokestatic  #372                // InterfaceMethod scala/Product.$init$:(Lscala/Product;)V
        18: return
      LineNumberTable:
        line 93: 0
        line 94: 5
        line 95: 10
        line 92: 18
      LocalVariableTable:
        Start  Length  Slot  Name   Signature
            0      19     0  this   Largonaut/JsonObjectInstance;
            0      19     1 fieldsMap   Lscala/collection/immutable/Map;
            0      19     2 orderedFields   Lscala/collection/immutable/Vector;
    Signature: #365                         // (Lscala/collection/immutable/Map<Ljava/lang/String;Largonaut/Json;>;Lscala/collection/immutable/Vector<Ljava/lang/String;>;)V
    MethodParameters:
      Name                           Flags
      fieldsMap                      final
      orderedFields                  final

  public static final java.lang.Object $anonfun$$minus$1$adapted(java.lang.String, java.lang.String);
    descriptor: (Ljava/lang/String;Ljava/lang/String;)Ljava/lang/Object;
    flags: (0x1019) ACC_PUBLIC, ACC_STATIC, ACC_FINAL, ACC_SYNTHETIC
    Code:
      stack=2, locals=2, args_size=2
         0: aload_0
         1: aload_1
         2: invokestatic  #374                // Method $anonfun$$minus$1:(Ljava/lang/String;Ljava/lang/String;)Z
         5: invokestatic  #380                // Method scala/runtime/BoxesRunTime.boxToBoolean:(Z)Ljava/lang/Boolean;
         8: areturn
      LineNumberTable:
        line 120: 0
      LocalVariableTable:
        Start  Length  Slot  Name   Signature
            0       9     0   f$1   Ljava/lang/String;
            0       9     1   x$2   Ljava/lang/String;
    MethodParameters:
      Name                           Flags
      f$1                            final
      x$2                            final

  private static java.lang.Object $deserializeLambda$(java.lang.invoke.SerializedLambda);
    descriptor: (Ljava/lang/invoke/SerializedLambda;)Ljava/lang/Object;
    flags: (0x100a) ACC_PRIVATE, ACC_STATIC, ACC_SYNTHETIC
    Code:
      stack=1, locals=1, args_size=1
         0: aload_0
         1: invokedynamic #392,  0            // InvokeDynamic #5:lambdaDeserialize:(Ljava/lang/invoke/SerializedLambda;)Ljava/lang/Object;
         6: areturn
}
InnerClasses:
  public static final #17= #14 of #16;    // Lookup=class java/lang/invoke/MethodHandles$Lookup of class java/lang/invoke/MethodHandles
SourceFile: "JsonObject.scala"
RuntimeVisibleAnnotations:
  0: #10(#11=s#12)
    scala.reflect.ScalaSignature(
      bytes="\u0006\u0005\tma!B\u0017/\u0001:\u0002\u0004\u0002\u0003%\u0001\u0005+\u0007I\u0011A%\t\u0011u\u0003!\u0011#Q\u0001\n)C\u0001B\u0018\u0001\u0003\u0016\u0004%\ta\u0018\u0005\tG\u0002\u0011\t\u0012)A\u0005A\")A\r\u0001C\u0001K\")\u0011\u000e\u0001C\u0001\u0013\")!\u000e\u0001C\u0001W\")\u0001\u000f\u0001C\u0001c\")q\u000f\u0001C\u0001q\")!\u0010\u0001C\u0001w\")Q\u0010\u0001C\u0001}\"9\u0011q\u0001\u0001\u0005\u0002\u0005%\u0001bBA\u000b\u0001\u0011\u0005\u0011q\u0003\u0005\b\u0003?\u0001A\u0011AA\f\u0011\u001d\t\t\u0003\u0001C\u0001\u0003GAq!a\n\u0001\t\u0003\tI\u0003C\u0004\u00028\u0001!\t!!\u000f\t\u000f\u0005u\u0002\u0001\"\u0001\u0002@!9\u00111\t\u0001\u0005\u0002\u0005\u0015\u0003bBA\'\u0001\u0011\u0005\u0011q\n\u0005\b\u0003\'\u0002A\u0011AA+\u0011\u001d\ti\u0006\u0001C!\u0003?Bq!a\u001a\u0001\t\u0003\nI\u0007C\u0004\u0002v\u0001!\t%a\u001e\t\u0013\u0005e\u0004!!A\u0005\u0002\u0005m\u0004\"CAA\u0001E\u0005I\u0011AAB\u0011%\tI\nAI\u0001\n\u0003\tY\nC\u0005\u0002 \u0002\t\t\u0011\"\u0011\u0002\"\"I\u0011\u0011\u0017\u0001\u0002\u0002\u0013\u0005\u0011Q\u000b\u0005\n\u0003g\u0003\u0011\u0011!C\u0001\u0003kC\u0011\"a/\u0001\u0003\u0003%\t%!0\t\u0013\u0005-\u0007!!A\u0005\u0002\u00055\u0007\"CAi\u0001\u0005\u0005I\u0011IAj\u000f)\t9NLA\u0001\u0012\u0003q\u0013\u0011\u001c\u0004\n[9\n\t\u0011#\u0001/\u00037Da\u0001Z\u0012\u0005\u0002\u0005M\b\"CA/G\u0005\u0005IQIA{\u0011!i8%!A\u0005\u0002\u0006]\b\"CA\u007fGE\u0005I\u0011AAB\u0011%\typII\u0001\n\u0003\tY\nC\u0005\u0003\u0002\r\n\t\u0011\"!\u0003\u0004!I!QB\u0012\u0012\u0002\u0013\u0005\u00111\u0011\u0005\n\u0005\u001f\u0019\u0013\u0013!C\u0001\u00037C\u0011B!\u0005$\u0003\u0003%IAa\u0005\u0003%)\u001bxN\\(cU\u0016\u001cG/\u00138ti\u0006t7-\u001a\u0006\u0002_\u0005A\u0011M]4p]\u0006,Ho\u0005\u0003\u0001cUZ\u0004C\u0001\u001a4\u001b\u0005q\u0013B\u0001\u001b/\u0005)Q5o\u001c8PE*,7\r\u001e\t\u0003mej\u0011a\u000e\u0006\u0002q\u0005)1oY1mC&\u0011!h\u000e\u0002\b!J|G-^2u!\taTI\u0004\u0002>\u0007:\u0011aHQ\u0007\u0002\u007f)\u0011\u0001)Q\u0001\u0007yI|w\u000e\u001e \u0004\u0001%\t\u0001(\u0003\u0002Eo\u00059\u0001/Y2lC\u001e,\u0017B\u0001$H\u00051\u0019VM]5bY&T\u0018M\u00197f\u0015\t!u\'A\u0005gS\u0016dGm]\'baV\t!\n\u0005\u0003L\u001fJSfB\u0001\'N!\tqt\'\u0003\u0002Oo\u00051\u0001K]3eK\u001aL!\u0001U)\u0003\u00075\u000b\u0007O\u0003\u0002OoA\u00111K\u0016\b\u0003eQK!!\u0016\u0018\u0002\t)\u001bxN\\\u0005\u0003/b\u0013\u0011BS:p]\u001aKW\r\u001c3\n\u0005es#!\u0002&t_:\u001c\bC\u0001\u001a\\\u0013\tafF\u0001\u0003Kg>t\u0017A\u00034jK2$7/T1qA\u0005iqN\u001d3fe\u0016$g)[3mIN,\u0012\u0001\u0019\t\u0004y\u0005\u0014\u0016B\u00012H\u0005\u00191Vm\u0019;pe\u0006qqN\u001d3fe\u0016$g)[3mIN\u0004\u0013A\u0002\u001fj]&$h\bF\u0002gO\"\u0004\"A\r\u0001\t\u000f!+\u0001\u0013!a\u0001\u0015\"9a,\u0002I\u0001\u0002\u0004\u0001\u0017!\u0002;p\u001b\u0006\u0004\u0018!\u0002\u0013qYV\u001cHcA\u0019m]\")Qn\u0002a\u0001%\u0006\ta\rC\u0003p\u000f\u0001\u0007!,A\u0001k\u0003-!3m\u001c7p]\u0012\u0002H.^:\u0015\u0005E\u0012\b\"B:\t\u0001\u0004!\u0018A\u00014k!\u00111TO\u0015.\n\u0005Y<$A\u0002+va2,\'\'A\u0006%a2,8\u000fJ2pY>tGCA\u0019z\u0011\u0015\u0019\u0018\u00021\u0001u\u0003\u0019!S.\u001b8vgR\u0011\u0011\u0007 \u0005\u0006[*\u0001\rAU\u0001\u0006CB\u0004H.\u001f\u000b\u0004\u007f\u0006\u0015\u0001\u0003\u0002\u001c\u0002\u0002iK1!a\u00018\u0005\u0019y\u0005\u000f^5p]\")Qn\u0003a\u0001%\u0006Iq/\u001b;i\u0015N|gn\u001d\u000b\u0004c\u0005-\u0001bBA\u0007\u0019\u0001\u0007\u0011qB\u0001\u0002WB)a\'!\u0005[5&\u0019\u00111C\u001c\u0003\u0013\u0019+hn\u0019;j_:\f\u0014aB5t\u000b6\u0004H/_\u000b\u0003\u00033\u00012ANA\u000e\u0013\r\tib\u000e\u0002\b\u0005>|G.Z1o\u0003)I7OT8u\u000b6\u0004H/_\u0001\rIEl\u0017M]6%c6\f\'o\u001b\u000b\u0005\u00033\t)\u0003C\u0003n\u001f\u0001\u0007!+\u0001\u0004u_2K7\u000f^\u000b\u0003\u0003W\u0001R\u0001PA\u0017\u0003cI1!a\fH\u0005\u0011a\u0015n\u001d;\u0011\u0007M\u000b\u0019$C\u0002\u00026a\u0013\u0011BS:p]\u0006\u001b8o\\2\u0002\rY\fG.^3t+\t\tY\u0004\u0005\u0003=\u0003[Q\u0016A\u00024jK2$7/\u0006\u0002\u0002BA!A(!\fS\u0003!1\u0017.\u001a7e\'\u0016$XCAA$!\u0011Y\u0015\u0011\n*\n\u0007\u0005-\u0013KA\u0002TKR\f1!\\1q)\r\t\u0014\u0011\u000b\u0005\u0007[R\u0001\r!a\u0004\u0002\tML\'0Z\u000b\u0003\u0003/\u00022ANA-\u0013\r\tYf\u000e\u0002\u0004\u0013:$\u0018\u0001\u0003;p\'R\u0014\u0018N\\4\u0015\u0005\u0005\u0005\u0004cA&\u0002d%\u0019\u0011QM)\u0003\rM#(/\u001b8h\u0003\u0019)\u0017/^1mgR!\u0011\u0011DA6\u0011\u001d\tig\u0006a\u0001\u0003_\n\u0011a\u001c\t\u0004m\u0005E\u0014bAA:o\t\u0019\u0011I\\=\u0002\u0011!\f7\u000f[\"pI\u0016$\"!a\u0016\u0002\t\r|\u0007/\u001f\u000b\u0006M\u0006u\u0014q\u0010\u0005\b\u0011f\u0001\n\u00111\u0001K\u0011\u001dq\u0016\u0004%AA\u0002\u0001\fabY8qs\u0012\"WMZ1vYR$\u0013\'\u0006\u0002\u0002\u0006*\u001a!*a\",\u0005\u0005%\u0005\u0003BAF\u0003+k!!!$\u000b\t\u0005=\u0015\u0011S\u0001\nk:\u001c\u0007.Z2lK\u0012T1!a%8\u0003)\tgN\\8uCRLwN\\\u0005\u0005\u0003/\u000biIA\tv]\u000eDWmY6fIZ\u000b\'/[1oG\u0016\fabY8qs\u0012\"WMZ1vYR$#\'\u0006\u0002\u0002\u001e*\u001a\u0001-a\"\u0002\u001bA\u0014x\u000eZ;diB\u0013XMZ5y+\t\t\u0019\u000b\u0005\u0003\u0002&\u0006=VBAAT\u0015\u0011\tI+a+\u0002\t1\fgn\u001a\u0006\u0003\u0003[\u000bAA[1wC&!\u0011QMAT\u00031\u0001(o\u001c3vGR\f%/\u001b;z\u00039\u0001(o\u001c3vGR,E.Z7f]R$B!a\u001c\u00028\"I\u0011\u0011\u0018\u0010\u0002\u0002\u0003\u0007\u0011qK\u0001\u0004q\u0012\n\u0014a\u00049s_\u0012,8\r^%uKJ\fGo\u001c:\u0016\u0005\u0005}\u0006CBAa\u0003\u000f\fy\'\u0004\u0002\u0002D*\u0019\u0011QY\u001c\u0002\u0015\r|G\u000e\\3di&|g.\u0003\u0003\u0002J\u0006\r\'\u0001C%uKJ\fGo\u001c:\u0002\u0011\r\fg.R9vC2$B!!\u0007\u0002P\"I\u0011\u0011\u0018\u0011\u0002\u0002\u0003\u0007\u0011qN\u0001\u0013aJ|G-^2u\u000b2,W.\u001a8u\u001d\u0006lW\r\u0006\u0003\u0002$\u0006U\u0007\"CA]C\u0005\u0005\t\u0019AA,\u0003IQ5o\u001c8PE*,7\r^%ogR\fgnY3\u0011\u0005I\u001a3#B\u0012\u0002^\u0006%\bcBAp\u0003KT\u0005MZ\u0007\u0003\u0003CT1!a98\u0003\u001d\u0011XO\u001c;j[\u0016LA!a:\u0002b\n\t\u0012IY:ue\u0006\u001cGOR;oGRLwN\u001c\u001a\u0011\t\u0005-\u0018\u0011_\u0007\u0003\u0003[TA!a<\u0002,\u0006\u0011\u0011n\\\u0005\u0004\r\u00065HCAAm)\t\t\u0019\u000bF\u0003g\u0003s\fY\u0010C\u0004IMA\u0005\t\u0019\u0001&\t\u000fy3\u0003\u0013!a\u0001A\u0006y\u0011\r\u001d9ms\u0012\"WMZ1vYR$\u0013\'A\bbaBd\u0017\u0010\n3fM\u0006,H\u000e\u001e\u00133\u0003\u001d)h.\u00199qYf$BA!\u0002\u0003\nA)a\'!\u0001\u0003\bA!a\'\u001e&a\u0011!\u0011Y!KA\u0001\u0002\u00041\u0017a\u0001=%a\u0005YB\u0005\\3tg&t\u0017\u000e\u001e\u0013he\u0016\fG/\u001a:%I\u00164\u0017-\u001e7uIE\n1\u0004\n7fgNLg.\u001b;%OJ,\u0017\r^3sI\u0011,g-Y;mi\u0012\u0012\u0014\u0001D<sSR,\'+\u001a9mC\u000e,GC\u0001B\u000b!\u0011\t)Ka\u0006\n\t\te\u0011q\u0015\u0002\u0007\u001f\nTWm\u0019;"
    )
BootstrapMethods:
  0: #160 REF_invokeStatic java/lang/invoke/LambdaMetafactory.altMetafactory:(Ljava/lang/invoke/MethodHandles$Lookup;Ljava/lang/String;Ljava/lang/invoke/MethodType;[Ljava/lang/Object;)Ljava/lang/invoke/CallSite;
    Method arguments:
      #144 (Ljava/lang/Object;)Ljava/lang/Object;
      #149 REF_invokeStatic argonaut/JsonObjectInstance.$anonfun$$minus$1$adapted:(Ljava/lang/String;Ljava/lang/String;)Ljava/lang/Object;
      #151 (Ljava/lang/String;)Ljava/lang/Object;
      #152 5
      #153 1
      #151 (Ljava/lang/String;)Ljava/lang/Object;
  1: #160 REF_invokeStatic java/lang/invoke/LambdaMetafactory.altMetafactory:(Ljava/lang/invoke/MethodHandles$Lookup;Ljava/lang/String;Ljava/lang/invoke/MethodType;[Ljava/lang/Object;)Ljava/lang/invoke/CallSite;
    Method arguments:
      #144 (Ljava/lang/Object;)Ljava/lang/Object;
      #198 REF_invokeStatic argonaut/JsonObjectInstance.$anonfun$toList$1:(Largonaut/JsonObjectInstance;Ljava/lang/String;)Lscala/Tuple2;
      #200 (Ljava/lang/String;)Lscala/Tuple2;
      #152 5
      #153 1
      #200 (Ljava/lang/String;)Lscala/Tuple2;
  2: #160 REF_invokeStatic java/lang/invoke/LambdaMetafactory.altMetafactory:(Ljava/lang/invoke/MethodHandles$Lookup;Ljava/lang/String;Ljava/lang/invoke/MethodType;[Ljava/lang/Object;)Ljava/lang/invoke/CallSite;
    Method arguments:
      #144 (Ljava/lang/Object;)Ljava/lang/Object;
      #216 REF_invokeStatic argonaut/JsonObjectInstance.$anonfun$values$1:(Largonaut/JsonObjectInstance;Ljava/lang/String;)Largonaut/Json;
      #218 (Ljava/lang/String;)Largonaut/Json;
      #152 5
      #153 1
      #218 (Ljava/lang/String;)Largonaut/Json;
  3: #160 REF_invokeStatic java/lang/invoke/LambdaMetafactory.altMetafactory:(Ljava/lang/invoke/MethodHandles$Lookup;Ljava/lang/String;Ljava/lang/invoke/MethodType;[Ljava/lang/Object;)Ljava/lang/invoke/CallSite;
    Method arguments:
      #244 (Ljava/lang/Object;Ljava/lang/Object;)Ljava/lang/Object;
      #249 REF_invokeStatic argonaut/JsonObjectInstance.$anonfun$map$1:(Lscala/Function1;Lscala/collection/immutable/Map;Lscala/Tuple2;)Lscala/collection/immutable/Map;
      #251 (Lscala/collection/immutable/Map;Lscala/Tuple2;)Lscala/collection/immutable/Map;
      #152 5
      #153 1
      #251 (Lscala/collection/immutable/Map;Lscala/Tuple2;)Lscala/collection/immutable/Map;
  4: #160 REF_invokeStatic java/lang/invoke/LambdaMetafactory.altMetafactory:(Ljava/lang/invoke/MethodHandles$Lookup;Ljava/lang/String;Ljava/lang/invoke/MethodType;[Ljava/lang/Object;)Ljava/lang/invoke/CallSite;
    Method arguments:
      #144 (Ljava/lang/Object;)Ljava/lang/Object;
      #285 REF_invokeStatic argonaut/JsonObjectInstance.$anonfun$toString$1:(Lscala/Tuple2;)Ljava/lang/String;
      #286 (Lscala/Tuple2;)Ljava/lang/String;
      #152 5
      #153 1
      #286 (Lscala/Tuple2;)Ljava/lang/String;
  5: #389 REF_invokeStatic scala/runtime/LambdaDeserialize.bootstrap:(Ljava/lang/invoke/MethodHandles$Lookup;Ljava/lang/String;Ljava/lang/invoke/MethodType;[Ljava/lang/invoke/MethodHandle;)Ljava/lang/invoke/CallSite;
    Method arguments:
      #149 REF_invokeStatic argonaut/JsonObjectInstance.$anonfun$$minus$1$adapted:(Ljava/lang/String;Ljava/lang/String;)Ljava/lang/Object;
      #249 REF_invokeStatic argonaut/JsonObjectInstance.$anonfun$map$1:(Lscala/Function1;Lscala/collection/immutable/Map;Lscala/Tuple2;)Lscala/collection/immutable/Map;
      #198 REF_invokeStatic argonaut/JsonObjectInstance.$anonfun$toList$1:(Largonaut/JsonObjectInstance;Ljava/lang/String;)Lscala/Tuple2;
      #285 REF_invokeStatic argonaut/JsonObjectInstance.$anonfun$toString$1:(Lscala/Tuple2;)Ljava/lang/String;
      #216 REF_invokeStatic argonaut/JsonObjectInstance.$anonfun$values$1:(Largonaut/JsonObjectInstance;Ljava/lang/String;)Largonaut/Json;
  ScalaInlineInfo: length = 0xC2 (unknown attribute)
   01 00 00 26 01 5A 01 5B 01 00 91 00 92 01 00 F5
   00 F6 01 00 C2 00 C3 01 01 19 01 1A 01 00 D4 00
   D5 01 00 66 00 6C 00 00 8B 00 8C 00 00 4D 00 4E
   00 00 7F 00 6C 00 00 BD 00 BE 00 00 80 01 3A 00
   00 A1 00 A9 00 01 55 00 54 00 00 5E 00 5F 00 01
   3D 00 24 00 00 5B 00 19 00 01 2C 00 54 00 00 DF
   00 E0 00 00 DC 00 C0 00 00 12 00 24 00 01 34 01
   04 00 00 B7 00 B8 00 00 BB 00 B8 00 00 B3 00 B0
   00 00 15 00 19 00 01 41 01 04 00 01 42 01 43 00
   01 56 01 57 00 00 3D 00 3E 00 01 4B 00 3E 00 01
   3E 01 0C 00 01 03 01 04 00 00 BF 00 C0 00 00 4A
   00 24 00 01 0B 01 0C 00 00 D2 00 C0 00 00 AF 00
   B0 00
  ScalaSig: length = 0x3 (unknown attribute)
   05 02 00
