Classfile /Users/mw/Projects/slang-braindump/.jar/jar8/assemble/slang-braindump/assemble/content/argonaut/JsonObject$.class
  Last modified May 29, 2022; size 3117 bytes
  SHA-256 checksum 2397f81ec7e76ec5aa3874a086728c70f774c280252daadb8bd812ac6b7405e2
  Compiled from "JsonObject.scala"
public final class argonaut.JsonObject$ implements argonaut.JsonObjects
  minor version: 0
  major version: 52
  flags: (0x0031) ACC_PUBLIC, ACC_FINAL, ACC_SUPER
  this_class: #2                          // argonaut/JsonObject$
  super_class: #4                         // java/lang/Object
  interfaces: 1, fields: 1, methods: 7, attributes: 5
Constant pool:
    #1 = Utf8               argonaut/JsonObject$
    #2 = Class              #1            // argonaut/JsonObject$
    #3 = Utf8               java/lang/Object
    #4 = Class              #3            // java/lang/Object
    #5 = Utf8               argonaut/JsonObjects
    #6 = Class              #5            // argonaut/JsonObjects
    #7 = Utf8               JsonObject.scala
    #8 = Utf8               java/lang/invoke/MethodHandles$Lookup
    #9 = Class              #8            // java/lang/invoke/MethodHandles$Lookup
   #10 = Utf8               java/lang/invoke/MethodHandles
   #11 = Class              #10           // java/lang/invoke/MethodHandles
   #12 = Utf8               Lookup
   #13 = Utf8               MODULE$
   #14 = Utf8               Largonaut/JsonObject$;
   #15 = Utf8               <clinit>
   #16 = Utf8               ()V
   #17 = Utf8               <init>
   #18 = NameAndType        #17:#16       // "<init>":()V
   #19 = Methodref          #2.#18        // argonaut/JsonObject$."<init>":()V
   #20 = NameAndType        #13:#14       // MODULE$:Largonaut/JsonObject$;
   #21 = Fieldref           #2.#20        // argonaut/JsonObject$.MODULE$:Largonaut/JsonObject$;
   #22 = Utf8               empty
   #23 = Utf8               ()Largonaut/JsonObject;
   #24 = Utf8               argonaut/JsonObjectInstance
   #25 = Class              #24           // argonaut/JsonObjectInstance
   #26 = Utf8               argonaut/JsonObjectInstance$
   #27 = Class              #26           // argonaut/JsonObjectInstance$
   #28 = Utf8               Largonaut/JsonObjectInstance$;
   #29 = NameAndType        #13:#28       // MODULE$:Largonaut/JsonObjectInstance$;
   #30 = Fieldref           #27.#29       // argonaut/JsonObjectInstance$.MODULE$:Largonaut/JsonObjectInstance$;
   #31 = Utf8               apply$default$1
   #32 = Utf8               ()Lscala/collection/immutable/Map;
   #33 = NameAndType        #31:#32       // apply$default$1:()Lscala/collection/immutable/Map;
   #34 = Methodref          #27.#33       // argonaut/JsonObjectInstance$.apply$default$1:()Lscala/collection/immutable/Map;
   #35 = Utf8               apply$default$2
   #36 = Utf8               ()Lscala/collection/immutable/Vector;
   #37 = NameAndType        #35:#36       // apply$default$2:()Lscala/collection/immutable/Vector;
   #38 = Methodref          #27.#37       // argonaut/JsonObjectInstance$.apply$default$2:()Lscala/collection/immutable/Vector;
   #39 = Utf8               (Lscala/collection/immutable/Map;Lscala/collection/immutable/Vector;)V
   #40 = NameAndType        #17:#39       // "<init>":(Lscala/collection/immutable/Map;Lscala/collection/immutable/Vector;)V
   #41 = Methodref          #25.#40       // argonaut/JsonObjectInstance."<init>":(Lscala/collection/immutable/Map;Lscala/collection/immutable/Vector;)V
   #42 = Utf8               this
   #43 = Utf8               single
   #44 = Utf8               (Ljava/lang/String;Largonaut/Json;)Largonaut/JsonObject;
   #45 = Utf8               f
   #46 = Utf8               j
   #47 = NameAndType        #22:#23       // empty:()Largonaut/JsonObject;
   #48 = Methodref          #2.#47        // argonaut/JsonObject$.empty:()Largonaut/JsonObject;
   #49 = Utf8               argonaut/JsonObject
   #50 = Class              #49           // argonaut/JsonObject
   #51 = Utf8               $plus
   #52 = NameAndType        #51:#44       // $plus:(Ljava/lang/String;Largonaut/Json;)Largonaut/JsonObject;
   #53 = Methodref          #50.#52       // argonaut/JsonObject.$plus:(Ljava/lang/String;Largonaut/Json;)Largonaut/JsonObject;
   #54 = Utf8               Ljava/lang/String;
   #55 = Utf8               Largonaut/Json;
   #56 = Utf8               fromTraversableOnce
   #57 = Utf8               (Lscala/collection/IterableOnce;)Largonaut/JsonObject;
   #58 = Utf8               (Lscala/collection/IterableOnce<Lscala/Tuple2<Ljava/lang/String;Largonaut/Json;>;>;)Largonaut/JsonObject;
   #59 = Utf8               t
   #60 = Utf8               scala/collection/IterableOnceExtensionMethods$
   #61 = Class              #60           // scala/collection/IterableOnceExtensionMethods$
   #62 = Utf8               Lscala/collection/IterableOnceExtensionMethods$;
   #63 = NameAndType        #13:#62       // MODULE$:Lscala/collection/IterableOnceExtensionMethods$;
   #64 = Fieldref           #61.#63       // scala/collection/IterableOnceExtensionMethods$.MODULE$:Lscala/collection/IterableOnceExtensionMethods$;
   #65 = Utf8               scala/collection/IterableOnce$
   #66 = Class              #65           // scala/collection/IterableOnce$
   #67 = Utf8               Lscala/collection/IterableOnce$;
   #68 = NameAndType        #13:#67       // MODULE$:Lscala/collection/IterableOnce$;
   #69 = Fieldref           #66.#68       // scala/collection/IterableOnce$.MODULE$:Lscala/collection/IterableOnce$;
   #70 = Utf8               iterableOnceExtensionMethods
   #71 = Utf8               (Lscala/collection/IterableOnce;)Lscala/collection/IterableOnce;
   #72 = NameAndType        #70:#71       // iterableOnceExtensionMethods:(Lscala/collection/IterableOnce;)Lscala/collection/IterableOnce;
   #73 = Methodref          #66.#72       // scala/collection/IterableOnce$.iterableOnceExtensionMethods:(Lscala/collection/IterableOnce;)Lscala/collection/IterableOnce;
   #74 = Utf8               (Ljava/lang/Object;Ljava/lang/Object;)Ljava/lang/Object;
   #75 = MethodType         #74           //  (Ljava/lang/Object;Ljava/lang/Object;)Ljava/lang/Object;
   #76 = Utf8               $anonfun$fromTraversableOnce$1
   #77 = Utf8               (Largonaut/JsonObject;Lscala/Tuple2;)Largonaut/JsonObject;
   #78 = NameAndType        #76:#77       // $anonfun$fromTraversableOnce$1:(Largonaut/JsonObject;Lscala/Tuple2;)Largonaut/JsonObject;
   #79 = Methodref          #2.#78        // argonaut/JsonObject$.$anonfun$fromTraversableOnce$1:(Largonaut/JsonObject;Lscala/Tuple2;)Largonaut/JsonObject;
   #80 = MethodHandle       6:#79         // REF_invokeStatic argonaut/JsonObject$.$anonfun$fromTraversableOnce$1:(Largonaut/JsonObject;Lscala/Tuple2;)Largonaut/JsonObject;
   #81 = MethodType         #77           //  (Largonaut/JsonObject;Lscala/Tuple2;)Largonaut/JsonObject;
   #82 = Integer            5
   #83 = Integer            1
   #84 = Utf8               java/lang/invoke/LambdaMetafactory
   #85 = Class              #84           // java/lang/invoke/LambdaMetafactory
   #86 = Utf8               altMetafactory
   #87 = Utf8               (Ljava/lang/invoke/MethodHandles$Lookup;Ljava/lang/String;Ljava/lang/invoke/MethodType;[Ljava/lang/Object;)Ljava/lang/invoke/CallSite;
   #88 = NameAndType        #86:#87       // altMetafactory:(Ljava/lang/invoke/MethodHandles$Lookup;Ljava/lang/String;Ljava/lang/invoke/MethodType;[Ljava/lang/Object;)Ljava/lang/invoke/CallSite;
   #89 = Methodref          #85.#88       // java/lang/invoke/LambdaMetafactory.altMetafactory:(Ljava/lang/invoke/MethodHandles$Lookup;Ljava/lang/String;Ljava/lang/invoke/MethodType;[Ljava/lang/Object;)Ljava/lang/invoke/CallSite;
   #90 = MethodHandle       6:#89         // REF_invokeStatic java/lang/invoke/LambdaMetafactory.altMetafactory:(Ljava/lang/invoke/MethodHandles$Lookup;Ljava/lang/String;Ljava/lang/invoke/MethodType;[Ljava/lang/Object;)Ljava/lang/invoke/CallSite;
   #91 = Utf8               apply
   #92 = Utf8               ()Lscala/Function2;
   #93 = NameAndType        #91:#92       // apply:()Lscala/Function2;
   #94 = InvokeDynamic      #0:#93        // #0:apply:()Lscala/Function2;
   #95 = Utf8               foldLeft$extension
   #96 = Utf8               (Lscala/collection/IterableOnce;Ljava/lang/Object;Lscala/Function2;)Ljava/lang/Object;
   #97 = NameAndType        #95:#96       // foldLeft$extension:(Lscala/collection/IterableOnce;Ljava/lang/Object;Lscala/Function2;)Ljava/lang/Object;
   #98 = Methodref          #61.#97       // scala/collection/IterableOnceExtensionMethods$.foldLeft$extension:(Lscala/collection/IterableOnce;Ljava/lang/Object;Lscala/Function2;)Ljava/lang/Object;
   #99 = Utf8               Lscala/collection/IterableOnce;
  #100 = Utf8               x$4
  #101 = Utf8               x$5
  #102 = Utf8               $colon$plus
  #103 = Utf8               (Lscala/Tuple2;)Largonaut/JsonObject;
  #104 = NameAndType        #102:#103     // $colon$plus:(Lscala/Tuple2;)Largonaut/JsonObject;
  #105 = Methodref          #50.#104      // argonaut/JsonObject.$colon$plus:(Lscala/Tuple2;)Largonaut/JsonObject;
  #106 = Utf8               Largonaut/JsonObject;
  #107 = Utf8               Lscala/Tuple2;
  #108 = Methodref          #4.#18        // java/lang/Object."<init>":()V
  #109 = Utf8               $deserializeLambda$
  #110 = Utf8               (Ljava/lang/invoke/SerializedLambda;)Ljava/lang/Object;
  #111 = Utf8               scala/runtime/LambdaDeserialize
  #112 = Class              #111          // scala/runtime/LambdaDeserialize
  #113 = Utf8               bootstrap
  #114 = Utf8               (Ljava/lang/invoke/MethodHandles$Lookup;Ljava/lang/String;Ljava/lang/invoke/MethodType;[Ljava/lang/invoke/MethodHandle;)Ljava/lang/invoke/CallSite;
  #115 = NameAndType        #113:#114     // bootstrap:(Ljava/lang/invoke/MethodHandles$Lookup;Ljava/lang/String;Ljava/lang/invoke/MethodType;[Ljava/lang/invoke/MethodHandle;)Ljava/lang/invoke/CallSite;
  #116 = Methodref          #112.#115     // scala/runtime/LambdaDeserialize.bootstrap:(Ljava/lang/invoke/MethodHandles$Lookup;Ljava/lang/String;Ljava/lang/invoke/MethodType;[Ljava/lang/invoke/MethodHandle;)Ljava/lang/invoke/CallSite;
  #117 = MethodHandle       6:#116        // REF_invokeStatic scala/runtime/LambdaDeserialize.bootstrap:(Ljava/lang/invoke/MethodHandles$Lookup;Ljava/lang/String;Ljava/lang/invoke/MethodType;[Ljava/lang/invoke/MethodHandle;)Ljava/lang/invoke/CallSite;
  #118 = Utf8               lambdaDeserialize
  #119 = NameAndType        #118:#110     // lambdaDeserialize:(Ljava/lang/invoke/SerializedLambda;)Ljava/lang/Object;
  #120 = InvokeDynamic      #1:#119       // #1:lambdaDeserialize:(Ljava/lang/invoke/SerializedLambda;)Ljava/lang/Object;
  #121 = Utf8               Code
  #122 = Utf8               LineNumberTable
  #123 = Utf8               LocalVariableTable
  #124 = Utf8               MethodParameters
  #125 = Utf8               Signature
  #126 = Utf8               InnerClasses
  #127 = Utf8               SourceFile
  #128 = Utf8               BootstrapMethods
  #129 = Utf8               ScalaInlineInfo
  #130 = Utf8               Scala
{
  public static final argonaut.JsonObject$ MODULE$;
    descriptor: Largonaut/JsonObject$;
    flags: (0x0019) ACC_PUBLIC, ACC_STATIC, ACC_FINAL

  public static {};
    descriptor: ()V
    flags: (0x0009) ACC_PUBLIC, ACC_STATIC
    Code:
      stack=2, locals=0, args_size=0
         0: new           #2                  // class argonaut/JsonObject$
         3: dup
         4: invokespecial #19                 // Method "<init>":()V
         7: putstatic     #21                 // Field MODULE$:Largonaut/JsonObject$;
        10: return
      LineNumberTable:
        line 158: 0

  public argonaut.JsonObject empty();
    descriptor: ()Largonaut/JsonObject;
    flags: (0x0001) ACC_PUBLIC
    Code:
      stack=4, locals=1, args_size=1
         0: new           #25                 // class argonaut/JsonObjectInstance
         3: dup
         4: getstatic     #30                 // Field argonaut/JsonObjectInstance$.MODULE$:Largonaut/JsonObjectInstance$;
         7: invokevirtual #34                 // Method argonaut/JsonObjectInstance$.apply$default$1:()Lscala/collection/immutable/Map;
        10: getstatic     #30                 // Field argonaut/JsonObjectInstance$.MODULE$:Largonaut/JsonObjectInstance$;
        13: invokevirtual #38                 // Method argonaut/JsonObjectInstance$.apply$default$2:()Lscala/collection/immutable/Vector;
        16: invokespecial #41                 // Method argonaut/JsonObjectInstance."<init>":(Lscala/collection/immutable/Map;Lscala/collection/immutable/Vector;)V
        19: areturn
      LineNumberTable:
        line 162: 0
      LocalVariableTable:
        Start  Length  Slot  Name   Signature
            0      20     0  this   Largonaut/JsonObject$;

  public argonaut.JsonObject single(java.lang.String, argonaut.Json);
    descriptor: (Ljava/lang/String;Largonaut/Json;)Largonaut/JsonObject;
    flags: (0x0001) ACC_PUBLIC
    Code:
      stack=3, locals=3, args_size=3
         0: aload_0
         1: invokevirtual #48                 // Method empty:()Largonaut/JsonObject;
         4: aload_1
         5: aload_2
         6: invokevirtual #53                 // Method argonaut/JsonObject.$plus:(Ljava/lang/String;Largonaut/Json;)Largonaut/JsonObject;
         9: areturn
      LineNumberTable:
        line 167: 0
      LocalVariableTable:
        Start  Length  Slot  Name   Signature
            0      10     0  this   Largonaut/JsonObject$;
            0      10     1     f   Ljava/lang/String;
            0      10     2     j   Largonaut/Json;
    MethodParameters:
      Name                           Flags
      f                              final
      j                              final

  public argonaut.JsonObject fromTraversableOnce(scala.collection.IterableOnce<scala.Tuple2<java.lang.String, argonaut.Json>>);
    descriptor: (Lscala/collection/IterableOnce;)Largonaut/JsonObject;
    flags: (0x0001) ACC_PUBLIC
    Code:
      stack=4, locals=2, args_size=2
         0: getstatic     #64                 // Field scala/collection/IterableOnceExtensionMethods$.MODULE$:Lscala/collection/IterableOnceExtensionMethods$;
         3: getstatic     #69                 // Field scala/collection/IterableOnce$.MODULE$:Lscala/collection/IterableOnce$;
         6: aload_1
         7: invokevirtual #73                 // Method scala/collection/IterableOnce$.iterableOnceExtensionMethods:(Lscala/collection/IterableOnce;)Lscala/collection/IterableOnce;
        10: aload_0
        11: invokevirtual #48                 // Method empty:()Largonaut/JsonObject;
        14: invokedynamic #94,  0             // InvokeDynamic #0:apply:()Lscala/Function2;
        19: invokevirtual #98                 // Method scala/collection/IterableOnceExtensionMethods$.foldLeft$extension:(Lscala/collection/IterableOnce;Ljava/lang/Object;Lscala/Function2;)Ljava/lang/Object;
        22: checkcast     #50                 // class argonaut/JsonObject
        25: areturn
      LineNumberTable:
        line 173: 3
      LocalVariableTable:
        Start  Length  Slot  Name   Signature
            0      26     0  this   Largonaut/JsonObject$;
            0      26     1     t   Lscala/collection/IterableOnce;
    Signature: #58                          // (Lscala/collection/IterableOnce<Lscala/Tuple2<Ljava/lang/String;Largonaut/Json;>;>;)Largonaut/JsonObject;
    MethodParameters:
      Name                           Flags
      t                              final

  public static final argonaut.JsonObject $anonfun$fromTraversableOnce$1(argonaut.JsonObject, scala.Tuple2);
    descriptor: (Largonaut/JsonObject;Lscala/Tuple2;)Largonaut/JsonObject;
    flags: (0x1019) ACC_PUBLIC, ACC_STATIC, ACC_FINAL, ACC_SYNTHETIC
    Code:
      stack=2, locals=2, args_size=2
         0: aload_0
         1: aload_1
         2: invokevirtual #105                // Method argonaut/JsonObject.$colon$plus:(Lscala/Tuple2;)Largonaut/JsonObject;
         5: areturn
      LineNumberTable:
        line 173: 0
      LocalVariableTable:
        Start  Length  Slot  Name   Signature
            0       6     0   x$4   Largonaut/JsonObject;
            0       6     1   x$5   Lscala/Tuple2;
    MethodParameters:
      Name                           Flags
      x$4                            final
      x$5                            final

  private argonaut.JsonObject$();
    descriptor: ()V
    flags: (0x0002) ACC_PRIVATE
    Code:
      stack=1, locals=1, args_size=1
         0: aload_0
         1: invokespecial #108                // Method java/lang/Object."<init>":()V
         4: return
      LineNumberTable:
        line 158: 0
      LocalVariableTable:
        Start  Length  Slot  Name   Signature
            0       5     0  this   Largonaut/JsonObject$;

  private static java.lang.Object $deserializeLambda$(java.lang.invoke.SerializedLambda);
    descriptor: (Ljava/lang/invoke/SerializedLambda;)Ljava/lang/Object;
    flags: (0x100a) ACC_PRIVATE, ACC_STATIC, ACC_SYNTHETIC
    Code:
      stack=1, locals=1, args_size=1
         0: aload_0
         1: invokedynamic #120,  0            // InvokeDynamic #1:lambdaDeserialize:(Ljava/lang/invoke/SerializedLambda;)Ljava/lang/Object;
         6: areturn
}
InnerClasses:
  public static final #12= #9 of #11;     // Lookup=class java/lang/invoke/MethodHandles$Lookup of class java/lang/invoke/MethodHandles
SourceFile: "JsonObject.scala"
BootstrapMethods:
  0: #90 REF_invokeStatic java/lang/invoke/LambdaMetafactory.altMetafactory:(Ljava/lang/invoke/MethodHandles$Lookup;Ljava/lang/String;Ljava/lang/invoke/MethodType;[Ljava/lang/Object;)Ljava/lang/invoke/CallSite;
    Method arguments:
      #75 (Ljava/lang/Object;Ljava/lang/Object;)Ljava/lang/Object;
      #80 REF_invokeStatic argonaut/JsonObject$.$anonfun$fromTraversableOnce$1:(Largonaut/JsonObject;Lscala/Tuple2;)Largonaut/JsonObject;
      #81 (Largonaut/JsonObject;Lscala/Tuple2;)Largonaut/JsonObject;
      #82 5
      #83 1
      #81 (Largonaut/JsonObject;Lscala/Tuple2;)Largonaut/JsonObject;
  1: #117 REF_invokeStatic scala/runtime/LambdaDeserialize.bootstrap:(Ljava/lang/invoke/MethodHandles$Lookup;Ljava/lang/String;Ljava/lang/invoke/MethodType;[Ljava/lang/invoke/MethodHandle;)Ljava/lang/invoke/CallSite;
    Method arguments:
      #80 REF_invokeStatic argonaut/JsonObject$.$anonfun$fromTraversableOnce$1:(Largonaut/JsonObject;Lscala/Tuple2;)Largonaut/JsonObject;
  ScalaInlineInfo: length = 0x1D (unknown attribute)
   01 01 00 05 00 4C 00 4D 01 00 11 00 10 01 00 16
   00 17 01 00 38 00 39 01 00 2B 00 2C 01
  Scala: length = 0x0 (unknown attribute)

