Classfile /Users/mw/Projects/slang-braindump/.jar/jar8/assemble/slang-braindump/assemble/content/argonaut/Json$.class
  Last modified May 29, 2022; size 8000 bytes
  SHA-256 checksum 277d09ed5673a5c6ed530c36052e6757fe7b959000ae925910677924da0c3b4d
  Compiled from "Json.scala"
public final class argonaut.Json$ implements argonaut.Jsons,java.io.Serializable
  minor version: 0
  major version: 52
  flags: (0x0031) ACC_PUBLIC, ACC_FINAL, ACC_SUPER
  this_class: #2                          // argonaut/Json$
  super_class: #4                         // java/lang/Object
  interfaces: 2, fields: 12, methods: 43, attributes: 3
Constant pool:
    #1 = Utf8               argonaut/Json$
    #2 = Class              #1            // argonaut/Json$
    #3 = Utf8               java/lang/Object
    #4 = Class              #3            // java/lang/Object
    #5 = Utf8               argonaut/Jsons
    #6 = Class              #5            // argonaut/Jsons
    #7 = Utf8               java/io/Serializable
    #8 = Class              #7            // java/io/Serializable
    #9 = Utf8               Json.scala
   #10 = Utf8               MODULE$
   #11 = Utf8               Largonaut/Json$;
   #12 = Utf8               jNull
   #13 = Utf8               Largonaut/Json;
   #14 = Utf8               jBool
   #15 = Utf8               Lscala/Function1;
   #16 = Utf8               Lscala/Function1<Ljava/lang/Object;Largonaut/Json;>;
   #17 = Utf8               jString
   #18 = Utf8               Lscala/Function1<Ljava/lang/String;Largonaut/Json;>;
   #19 = Utf8               jArray
   #20 = Utf8               Lscala/Function1<Lscala/collection/immutable/List<Largonaut/Json;>;Largonaut/Json;>;
   #21 = Utf8               jObject
   #22 = Utf8               Lscala/Function1<Largonaut/JsonObject;Largonaut/Json;>;
   #23 = Utf8               jTrue
   #24 = Utf8               jFalse
   #25 = Utf8               jZero
   #26 = Utf8               jEmptyString
   #27 = Utf8               jEmptyArray
   #28 = Utf8               jEmptyObject
   #29 = Utf8               <clinit>
   #30 = Utf8               ()V
   #31 = Utf8               <init>
   #32 = NameAndType        #31:#30       // "<init>":()V
   #33 = Methodref          #2.#32        // argonaut/Json$."<init>":()V
   #34 = NameAndType        #10:#11       // MODULE$:Largonaut/Json$;
   #35 = Fieldref           #2.#34        // argonaut/Json$.MODULE$:Largonaut/Json$;
   #36 = Utf8               $init$
   #37 = Utf8               (Largonaut/Jsons;)V
   #38 = NameAndType        #36:#37       // $init$:(Largonaut/Jsons;)V
   #39 = InterfaceMethodref #6.#38        // argonaut/Jsons.$init$:(Largonaut/Jsons;)V
   #40 = Utf8               jNumber
   #41 = Utf8               (Largonaut/JsonNumber;)Largonaut/Json;
   #42 = Utf8               n
   #43 = Utf8               jNumber$
   #44 = Utf8               (Largonaut/Jsons;Largonaut/JsonNumber;)Largonaut/Json;
   #45 = NameAndType        #43:#44       // jNumber$:(Largonaut/Jsons;Largonaut/JsonNumber;)Largonaut/Json;
   #46 = InterfaceMethodref #6.#45        // argonaut/Jsons.jNumber$:(Largonaut/Jsons;Largonaut/JsonNumber;)Largonaut/Json;
   #47 = Utf8               this
   #48 = Utf8               Largonaut/JsonNumber;
   #49 = Utf8               (I)Largonaut/Json;
   #50 = Utf8               (Largonaut/Jsons;I)Largonaut/Json;
   #51 = NameAndType        #43:#50       // jNumber$:(Largonaut/Jsons;I)Largonaut/Json;
   #52 = InterfaceMethodref #6.#51        // argonaut/Jsons.jNumber$:(Largonaut/Jsons;I)Largonaut/Json;
   #53 = Utf8               I
   #54 = Utf8               (J)Largonaut/Json;
   #55 = Utf8               (Largonaut/Jsons;J)Largonaut/Json;
   #56 = NameAndType        #43:#55       // jNumber$:(Largonaut/Jsons;J)Largonaut/Json;
   #57 = InterfaceMethodref #6.#56        // argonaut/Jsons.jNumber$:(Largonaut/Jsons;J)Largonaut/Json;
   #58 = Utf8               J
   #59 = Utf8               (D)Lscala/Option;
   #60 = Utf8               (D)Lscala/Option<Largonaut/Json;>;
   #61 = Utf8               (Largonaut/Jsons;D)Lscala/Option;
   #62 = NameAndType        #43:#61       // jNumber$:(Largonaut/Jsons;D)Lscala/Option;
   #63 = InterfaceMethodref #6.#62        // argonaut/Jsons.jNumber$:(Largonaut/Jsons;D)Lscala/Option;
   #64 = Utf8               D
   #65 = Utf8               jNumberOrNull
   #66 = Utf8               (D)Largonaut/Json;
   #67 = Utf8               jNumberOrNull$
   #68 = Utf8               (Largonaut/Jsons;D)Largonaut/Json;
   #69 = NameAndType        #67:#68       // jNumberOrNull$:(Largonaut/Jsons;D)Largonaut/Json;
   #70 = InterfaceMethodref #6.#69        // argonaut/Jsons.jNumberOrNull$:(Largonaut/Jsons;D)Largonaut/Json;
   #71 = Utf8               jNumberOrString
   #72 = Utf8               jNumberOrString$
   #73 = NameAndType        #72:#68       // jNumberOrString$:(Largonaut/Jsons;D)Largonaut/Json;
   #74 = InterfaceMethodref #6.#73        // argonaut/Jsons.jNumberOrString$:(Largonaut/Jsons;D)Largonaut/Json;
   #75 = Utf8               (Lscala/math/BigDecimal;)Largonaut/Json;
   #76 = Utf8               (Largonaut/Jsons;Lscala/math/BigDecimal;)Largonaut/Json;
   #77 = NameAndType        #43:#76       // jNumber$:(Largonaut/Jsons;Lscala/math/BigDecimal;)Largonaut/Json;
   #78 = InterfaceMethodref #6.#77        // argonaut/Jsons.jNumber$:(Largonaut/Jsons;Lscala/math/BigDecimal;)Largonaut/Json;
   #79 = Utf8               Lscala/math/BigDecimal;
   #80 = Utf8               (Ljava/lang/String;)Lscala/Option;
   #81 = Utf8               (Ljava/lang/String;)Lscala/Option<Largonaut/Json;>;
   #82 = Utf8               (Largonaut/Jsons;Ljava/lang/String;)Lscala/Option;
   #83 = NameAndType        #43:#82       // jNumber$:(Largonaut/Jsons;Ljava/lang/String;)Lscala/Option;
   #84 = InterfaceMethodref #6.#83        // argonaut/Jsons.jNumber$:(Largonaut/Jsons;Ljava/lang/String;)Lscala/Option;
   #85 = Utf8               Ljava/lang/String;
   #86 = NameAndType        #67:#82       // jNumberOrNull$:(Largonaut/Jsons;Ljava/lang/String;)Lscala/Option;
   #87 = InterfaceMethodref #6.#86        // argonaut/Jsons.jNumberOrNull$:(Largonaut/Jsons;Ljava/lang/String;)Lscala/Option;
   #88 = NameAndType        #72:#82       // jNumberOrString$:(Largonaut/Jsons;Ljava/lang/String;)Lscala/Option;
   #89 = InterfaceMethodref #6.#88        // argonaut/Jsons.jNumberOrString$:(Largonaut/Jsons;Ljava/lang/String;)Lscala/Option;
   #90 = Utf8               jSingleArray
   #91 = Utf8               (Largonaut/Json;)Largonaut/Json;
   #92 = Utf8               j
   #93 = Utf8               jSingleArray$
   #94 = Utf8               (Largonaut/Jsons;Largonaut/Json;)Largonaut/Json;
   #95 = NameAndType        #93:#94       // jSingleArray$:(Largonaut/Jsons;Largonaut/Json;)Largonaut/Json;
   #96 = InterfaceMethodref #6.#95        // argonaut/Jsons.jSingleArray$:(Largonaut/Jsons;Largonaut/Json;)Largonaut/Json;
   #97 = Utf8               jArrayElements
   #98 = Utf8               (Lscala/collection/immutable/Seq;)Largonaut/Json;
   #99 = Utf8               (Lscala/collection/immutable/Seq<Largonaut/Json;>;)Largonaut/Json;
  #100 = Utf8               elements
  #101 = Utf8               jArrayElements$
  #102 = Utf8               (Largonaut/Jsons;Lscala/collection/immutable/Seq;)Largonaut/Json;
  #103 = NameAndType        #101:#102     // jArrayElements$:(Largonaut/Jsons;Lscala/collection/immutable/Seq;)Largonaut/Json;
  #104 = InterfaceMethodref #6.#103       // argonaut/Jsons.jArrayElements$:(Largonaut/Jsons;Lscala/collection/immutable/Seq;)Largonaut/Json;
  #105 = Utf8               Lscala/collection/immutable/Seq;
  #106 = Utf8               jSingleObject
  #107 = Utf8               (Ljava/lang/String;Largonaut/Json;)Largonaut/Json;
  #108 = Utf8               k
  #109 = Utf8               v
  #110 = Utf8               jSingleObject$
  #111 = Utf8               (Largonaut/Jsons;Ljava/lang/String;Largonaut/Json;)Largonaut/Json;
  #112 = NameAndType        #110:#111     // jSingleObject$:(Largonaut/Jsons;Ljava/lang/String;Largonaut/Json;)Largonaut/Json;
  #113 = InterfaceMethodref #6.#112       // argonaut/Jsons.jSingleObject$:(Largonaut/Jsons;Ljava/lang/String;Largonaut/Json;)Largonaut/Json;
  #114 = Utf8               jObjectAssocList
  #115 = Utf8               (Lscala/collection/immutable/List;)Largonaut/Json;
  #116 = Utf8               (Lscala/collection/immutable/List<Lscala/Tuple2<Ljava/lang/String;Largonaut/Json;>;>;)Largonaut/Json;
  #117 = Utf8               x
  #118 = Utf8               jObjectAssocList$
  #119 = Utf8               (Largonaut/Jsons;Lscala/collection/immutable/List;)Largonaut/Json;
  #120 = NameAndType        #118:#119     // jObjectAssocList$:(Largonaut/Jsons;Lscala/collection/immutable/List;)Largonaut/Json;
  #121 = InterfaceMethodref #6.#120       // argonaut/Jsons.jObjectAssocList$:(Largonaut/Jsons;Lscala/collection/immutable/List;)Largonaut/Json;
  #122 = Utf8               Lscala/collection/immutable/List;
  #123 = Utf8               jObjectFields
  #124 = Utf8               (Lscala/collection/immutable/Seq<Lscala/Tuple2<Ljava/lang/String;Largonaut/Json;>;>;)Largonaut/Json;
  #125 = Utf8               jObjectFields$
  #126 = NameAndType        #125:#102     // jObjectFields$:(Largonaut/Jsons;Lscala/collection/immutable/Seq;)Largonaut/Json;
  #127 = InterfaceMethodref #6.#126       // argonaut/Jsons.jObjectFields$:(Largonaut/Jsons;Lscala/collection/immutable/Seq;)Largonaut/Json;
  #128 = Utf8               ()Largonaut/Json;
  #129 = NameAndType        #12:#13       // jNull:Largonaut/Json;
  #130 = Fieldref           #2.#129       // argonaut/Json$.jNull:Largonaut/Json;
  #131 = Utf8               ()Lscala/Function1;
  #132 = Utf8               ()Lscala/Function1<Ljava/lang/Object;Largonaut/Json;>;
  #133 = NameAndType        #14:#15       // jBool:Lscala/Function1;
  #134 = Fieldref           #2.#133       // argonaut/Json$.jBool:Lscala/Function1;
  #135 = Utf8               ()Lscala/Function1<Ljava/lang/String;Largonaut/Json;>;
  #136 = NameAndType        #17:#15       // jString:Lscala/Function1;
  #137 = Fieldref           #2.#136       // argonaut/Json$.jString:Lscala/Function1;
  #138 = Utf8               ()Lscala/Function1<Lscala/collection/immutable/List<Largonaut/Json;>;Largonaut/Json;>;
  #139 = NameAndType        #19:#15       // jArray:Lscala/Function1;
  #140 = Fieldref           #2.#139       // argonaut/Json$.jArray:Lscala/Function1;
  #141 = Utf8               ()Lscala/Function1<Largonaut/JsonObject;Largonaut/Json;>;
  #142 = NameAndType        #21:#15       // jObject:Lscala/Function1;
  #143 = Fieldref           #2.#142       // argonaut/Json$.jObject:Lscala/Function1;
  #144 = NameAndType        #23:#13       // jTrue:Largonaut/Json;
  #145 = Fieldref           #2.#144       // argonaut/Json$.jTrue:Largonaut/Json;
  #146 = NameAndType        #24:#13       // jFalse:Largonaut/Json;
  #147 = Fieldref           #2.#146       // argonaut/Json$.jFalse:Largonaut/Json;
  #148 = NameAndType        #25:#13       // jZero:Largonaut/Json;
  #149 = Fieldref           #2.#148       // argonaut/Json$.jZero:Largonaut/Json;
  #150 = NameAndType        #26:#13       // jEmptyString:Largonaut/Json;
  #151 = Fieldref           #2.#150       // argonaut/Json$.jEmptyString:Largonaut/Json;
  #152 = NameAndType        #27:#13       // jEmptyArray:Largonaut/Json;
  #153 = Fieldref           #2.#152       // argonaut/Json$.jEmptyArray:Largonaut/Json;
  #154 = NameAndType        #28:#13       // jEmptyObject:Largonaut/Json;
  #155 = Fieldref           #2.#154       // argonaut/Json$.jEmptyObject:Largonaut/Json;
  #156 = Utf8               argonaut$Jsons$_setter_$jNull_$eq
  #157 = Utf8               (Largonaut/Json;)V
  #158 = Utf8               x$1
  #159 = Utf8               argonaut$Jsons$_setter_$jBool_$eq
  #160 = Utf8               (Lscala/Function1;)V
  #161 = Utf8               (Lscala/Function1<Ljava/lang/Object;Largonaut/Json;>;)V
  #162 = Utf8               argonaut$Jsons$_setter_$jString_$eq
  #163 = Utf8               (Lscala/Function1<Ljava/lang/String;Largonaut/Json;>;)V
  #164 = Utf8               argonaut$Jsons$_setter_$jArray_$eq
  #165 = Utf8               (Lscala/Function1<Lscala/collection/immutable/List<Largonaut/Json;>;Largonaut/Json;>;)V
  #166 = Utf8               argonaut$Jsons$_setter_$jObject_$eq
  #167 = Utf8               (Lscala/Function1<Largonaut/JsonObject;Largonaut/Json;>;)V
  #168 = Utf8               argonaut$Jsons$_setter_$jTrue_$eq
  #169 = Utf8               argonaut$Jsons$_setter_$jFalse_$eq
  #170 = Utf8               argonaut$Jsons$_setter_$jZero_$eq
  #171 = Utf8               argonaut$Jsons$_setter_$jEmptyString_$eq
  #172 = Utf8               argonaut$Jsons$_setter_$jEmptyArray_$eq
  #173 = Utf8               argonaut$Jsons$_setter_$jEmptyObject_$eq
  #174 = Utf8               apply
  #175 = Utf8               fields
  #176 = Utf8               scala/collection/immutable/Seq
  #177 = Class              #176          // scala/collection/immutable/Seq
  #178 = Utf8               toList
  #179 = Utf8               ()Lscala/collection/immutable/List;
  #180 = NameAndType        #178:#179     // toList:()Lscala/collection/immutable/List;
  #181 = InterfaceMethodref #177.#180     // scala/collection/immutable/Seq.toList:()Lscala/collection/immutable/List;
  #182 = NameAndType        #114:#115     // jObjectAssocList:(Lscala/collection/immutable/List;)Largonaut/Json;
  #183 = Methodref          #2.#182       // argonaut/Json$.jObjectAssocList:(Lscala/collection/immutable/List;)Largonaut/Json;
  #184 = Utf8               obj
  #185 = Utf8               array
  #186 = NameAndType        #19:#131      // jArray:()Lscala/Function1;
  #187 = Methodref          #2.#186       // argonaut/Json$.jArray:()Lscala/Function1;
  #188 = Utf8               scala/Function1
  #189 = Class              #188          // scala/Function1
  #190 = Utf8               (Ljava/lang/Object;)Ljava/lang/Object;
  #191 = NameAndType        #174:#190     // apply:(Ljava/lang/Object;)Ljava/lang/Object;
  #192 = InterfaceMethodref #189.#191     // scala/Function1.apply:(Ljava/lang/Object;)Ljava/lang/Object;
  #193 = Utf8               argonaut/Json
  #194 = Class              #193          // argonaut/Json
  #195 = Utf8               writeReplace
  #196 = Utf8               ()Ljava/lang/Object;
  #197 = Utf8               scala/runtime/ModuleSerializationProxy
  #198 = Class              #197          // scala/runtime/ModuleSerializationProxy
  #199 = Utf8               (Ljava/lang/Class;)V
  #200 = NameAndType        #31:#199      // "<init>":(Ljava/lang/Class;)V
  #201 = Methodref          #198.#200     // scala/runtime/ModuleSerializationProxy."<init>":(Ljava/lang/Class;)V
  #202 = Methodref          #4.#32        // java/lang/Object."<init>":()V
  #203 = Utf8               Signature
  #204 = Utf8               Code
  #205 = Utf8               LineNumberTable
  #206 = Utf8               LocalVariableTable
  #207 = Utf8               MethodParameters
  #208 = Utf8               SourceFile
  #209 = Utf8               ScalaInlineInfo
  #210 = Utf8               Scala
{
  public static final argonaut.Json$ MODULE$;
    descriptor: Largonaut/Json$;
    flags: (0x0019) ACC_PUBLIC, ACC_STATIC, ACC_FINAL

  private static argonaut.Json jNull;
    descriptor: Largonaut/Json;
    flags: (0x000a) ACC_PRIVATE, ACC_STATIC

  private static scala.Function1<java.lang.Object, argonaut.Json> jBool;
    descriptor: Lscala/Function1;
    flags: (0x000a) ACC_PRIVATE, ACC_STATIC
    Signature: #16                          // Lscala/Function1<Ljava/lang/Object;Largonaut/Json;>;

  private static scala.Function1<java.lang.String, argonaut.Json> jString;
    descriptor: Lscala/Function1;
    flags: (0x000a) ACC_PRIVATE, ACC_STATIC
    Signature: #18                          // Lscala/Function1<Ljava/lang/String;Largonaut/Json;>;

  private static scala.Function1<scala.collection.immutable.List<argonaut.Json>, argonaut.Json> jArray;
    descriptor: Lscala/Function1;
    flags: (0x000a) ACC_PRIVATE, ACC_STATIC
    Signature: #20                          // Lscala/Function1<Lscala/collection/immutable/List<Largonaut/Json;>;Largonaut/Json;>;

  private static scala.Function1<argonaut.JsonObject, argonaut.Json> jObject;
    descriptor: Lscala/Function1;
    flags: (0x000a) ACC_PRIVATE, ACC_STATIC
    Signature: #22                          // Lscala/Function1<Largonaut/JsonObject;Largonaut/Json;>;

  private static argonaut.Json jTrue;
    descriptor: Largonaut/Json;
    flags: (0x000a) ACC_PRIVATE, ACC_STATIC

  private static argonaut.Json jFalse;
    descriptor: Largonaut/Json;
    flags: (0x000a) ACC_PRIVATE, ACC_STATIC

  private static argonaut.Json jZero;
    descriptor: Largonaut/Json;
    flags: (0x000a) ACC_PRIVATE, ACC_STATIC

  private static argonaut.Json jEmptyString;
    descriptor: Largonaut/Json;
    flags: (0x000a) ACC_PRIVATE, ACC_STATIC

  private static argonaut.Json jEmptyArray;
    descriptor: Largonaut/Json;
    flags: (0x000a) ACC_PRIVATE, ACC_STATIC

  private static argonaut.Json jEmptyObject;
    descriptor: Largonaut/Json;
    flags: (0x000a) ACC_PRIVATE, ACC_STATIC

  public static {};
    descriptor: ()V
    flags: (0x0009) ACC_PUBLIC, ACC_STATIC
    Code:
      stack=2, locals=0, args_size=0
         0: new           #2                  // class argonaut/Json$
         3: dup
         4: invokespecial #33                 // Method "<init>":()V
         7: putstatic     #35                 // Field MODULE$:Largonaut/Json$;
        10: getstatic     #35                 // Field MODULE$:Largonaut/Json$;
        13: invokestatic  #39                 // InterfaceMethod argonaut/Jsons.$init$:(Largonaut/Jsons;)V
        16: return
      LineNumberTable:
        line 486: 0

  public argonaut.Json jNumber(argonaut.JsonNumber);
    descriptor: (Largonaut/JsonNumber;)Largonaut/Json;
    flags: (0x0001) ACC_PUBLIC
    Code:
      stack=2, locals=2, args_size=2
         0: aload_0
         1: aload_1
         2: invokestatic  #46                 // InterfaceMethod argonaut/Jsons.jNumber$:(Largonaut/Jsons;Largonaut/JsonNumber;)Largonaut/Json;
         5: areturn
      LineNumberTable:
        line 486: 0
      LocalVariableTable:
        Start  Length  Slot  Name   Signature
            0       6     0  this   Largonaut/Json$;
            0       6     1     n   Largonaut/JsonNumber;
    MethodParameters:
      Name                           Flags
      n                              final

  public argonaut.Json jNumber(int);
    descriptor: (I)Largonaut/Json;
    flags: (0x0001) ACC_PUBLIC
    Code:
      stack=2, locals=2, args_size=2
         0: aload_0
         1: iload_1
         2: invokestatic  #52                 // InterfaceMethod argonaut/Jsons.jNumber$:(Largonaut/Jsons;I)Largonaut/Json;
         5: areturn
      LineNumberTable:
        line 486: 0
      LocalVariableTable:
        Start  Length  Slot  Name   Signature
            0       6     0  this   Largonaut/Json$;
            0       6     1     n   I
    MethodParameters:
      Name                           Flags
      n                              final

  public argonaut.Json jNumber(long);
    descriptor: (J)Largonaut/Json;
    flags: (0x0001) ACC_PUBLIC
    Code:
      stack=3, locals=3, args_size=2
         0: aload_0
         1: lload_1
         2: invokestatic  #57                 // InterfaceMethod argonaut/Jsons.jNumber$:(Largonaut/Jsons;J)Largonaut/Json;
         5: areturn
      LineNumberTable:
        line 486: 0
      LocalVariableTable:
        Start  Length  Slot  Name   Signature
            0       6     0  this   Largonaut/Json$;
            0       6     1     n   J
    MethodParameters:
      Name                           Flags
      n                              final

  public scala.Option<argonaut.Json> jNumber(double);
    descriptor: (D)Lscala/Option;
    flags: (0x0001) ACC_PUBLIC
    Code:
      stack=3, locals=3, args_size=2
         0: aload_0
         1: dload_1
         2: invokestatic  #63                 // InterfaceMethod argonaut/Jsons.jNumber$:(Largonaut/Jsons;D)Lscala/Option;
         5: areturn
      LineNumberTable:
        line 486: 0
      LocalVariableTable:
        Start  Length  Slot  Name   Signature
            0       6     0  this   Largonaut/Json$;
            0       6     1     n   D
    Signature: #60                          // (D)Lscala/Option<Largonaut/Json;>;
    MethodParameters:
      Name                           Flags
      n                              final

  public argonaut.Json jNumberOrNull(double);
    descriptor: (D)Largonaut/Json;
    flags: (0x0001) ACC_PUBLIC
    Code:
      stack=3, locals=3, args_size=2
         0: aload_0
         1: dload_1
         2: invokestatic  #70                 // InterfaceMethod argonaut/Jsons.jNumberOrNull$:(Largonaut/Jsons;D)Largonaut/Json;
         5: areturn
      LineNumberTable:
        line 486: 0
      LocalVariableTable:
        Start  Length  Slot  Name   Signature
            0       6     0  this   Largonaut/Json$;
            0       6     1     n   D
    MethodParameters:
      Name                           Flags
      n                              final

  public argonaut.Json jNumberOrString(double);
    descriptor: (D)Largonaut/Json;
    flags: (0x0001) ACC_PUBLIC
    Code:
      stack=3, locals=3, args_size=2
         0: aload_0
         1: dload_1
         2: invokestatic  #74                 // InterfaceMethod argonaut/Jsons.jNumberOrString$:(Largonaut/Jsons;D)Largonaut/Json;
         5: areturn
      LineNumberTable:
        line 486: 0
      LocalVariableTable:
        Start  Length  Slot  Name   Signature
            0       6     0  this   Largonaut/Json$;
            0       6     1     n   D
    MethodParameters:
      Name                           Flags
      n                              final

  public argonaut.Json jNumber(scala.math.BigDecimal);
    descriptor: (Lscala/math/BigDecimal;)Largonaut/Json;
    flags: (0x0001) ACC_PUBLIC
    Code:
      stack=2, locals=2, args_size=2
         0: aload_0
         1: aload_1
         2: invokestatic  #78                 // InterfaceMethod argonaut/Jsons.jNumber$:(Largonaut/Jsons;Lscala/math/BigDecimal;)Largonaut/Json;
         5: areturn
      LineNumberTable:
        line 486: 0
      LocalVariableTable:
        Start  Length  Slot  Name   Signature
            0       6     0  this   Largonaut/Json$;
            0       6     1     n   Lscala/math/BigDecimal;
    MethodParameters:
      Name                           Flags
      n                              final

  public scala.Option<argonaut.Json> jNumber(java.lang.String);
    descriptor: (Ljava/lang/String;)Lscala/Option;
    flags: (0x0001) ACC_PUBLIC
    Code:
      stack=2, locals=2, args_size=2
         0: aload_0
         1: aload_1
         2: invokestatic  #84                 // InterfaceMethod argonaut/Jsons.jNumber$:(Largonaut/Jsons;Ljava/lang/String;)Lscala/Option;
         5: areturn
      LineNumberTable:
        line 486: 0
      LocalVariableTable:
        Start  Length  Slot  Name   Signature
            0       6     0  this   Largonaut/Json$;
            0       6     1     n   Ljava/lang/String;
    Signature: #81                          // (Ljava/lang/String;)Lscala/Option<Largonaut/Json;>;
    MethodParameters:
      Name                           Flags
      n                              final

  public scala.Option<argonaut.Json> jNumberOrNull(java.lang.String);
    descriptor: (Ljava/lang/String;)Lscala/Option;
    flags: (0x0001) ACC_PUBLIC
    Code:
      stack=2, locals=2, args_size=2
         0: aload_0
         1: aload_1
         2: invokestatic  #87                 // InterfaceMethod argonaut/Jsons.jNumberOrNull$:(Largonaut/Jsons;Ljava/lang/String;)Lscala/Option;
         5: areturn
      LineNumberTable:
        line 486: 0
      LocalVariableTable:
        Start  Length  Slot  Name   Signature
            0       6     0  this   Largonaut/Json$;
            0       6     1     n   Ljava/lang/String;
    Signature: #81                          // (Ljava/lang/String;)Lscala/Option<Largonaut/Json;>;
    MethodParameters:
      Name                           Flags
      n                              final

  public scala.Option<argonaut.Json> jNumberOrString(java.lang.String);
    descriptor: (Ljava/lang/String;)Lscala/Option;
    flags: (0x0001) ACC_PUBLIC
    Code:
      stack=2, locals=2, args_size=2
         0: aload_0
         1: aload_1
         2: invokestatic  #89                 // InterfaceMethod argonaut/Jsons.jNumberOrString$:(Largonaut/Jsons;Ljava/lang/String;)Lscala/Option;
         5: areturn
      LineNumberTable:
        line 486: 0
      LocalVariableTable:
        Start  Length  Slot  Name   Signature
            0       6     0  this   Largonaut/Json$;
            0       6     1     n   Ljava/lang/String;
    Signature: #81                          // (Ljava/lang/String;)Lscala/Option<Largonaut/Json;>;
    MethodParameters:
      Name                           Flags
      n                              final

  public argonaut.Json jSingleArray(argonaut.Json);
    descriptor: (Largonaut/Json;)Largonaut/Json;
    flags: (0x0001) ACC_PUBLIC
    Code:
      stack=2, locals=2, args_size=2
         0: aload_0
         1: aload_1
         2: invokestatic  #96                 // InterfaceMethod argonaut/Jsons.jSingleArray$:(Largonaut/Jsons;Largonaut/Json;)Largonaut/Json;
         5: areturn
      LineNumberTable:
        line 486: 0
      LocalVariableTable:
        Start  Length  Slot  Name   Signature
            0       6     0  this   Largonaut/Json$;
            0       6     1     j   Largonaut/Json;
    MethodParameters:
      Name                           Flags
      j                              final

  public argonaut.Json jArrayElements(scala.collection.immutable.Seq<argonaut.Json>);
    descriptor: (Lscala/collection/immutable/Seq;)Largonaut/Json;
    flags: (0x0001) ACC_PUBLIC
    Code:
      stack=2, locals=2, args_size=2
         0: aload_0
         1: aload_1
         2: invokestatic  #104                // InterfaceMethod argonaut/Jsons.jArrayElements$:(Largonaut/Jsons;Lscala/collection/immutable/Seq;)Largonaut/Json;
         5: areturn
      LineNumberTable:
        line 486: 0
      LocalVariableTable:
        Start  Length  Slot  Name   Signature
            0       6     0  this   Largonaut/Json$;
            0       6     1 elements   Lscala/collection/immutable/Seq;
    Signature: #99                          // (Lscala/collection/immutable/Seq<Largonaut/Json;>;)Largonaut/Json;
    MethodParameters:
      Name                           Flags
      elements                       final

  public argonaut.Json jSingleObject(java.lang.String, argonaut.Json);
    descriptor: (Ljava/lang/String;Largonaut/Json;)Largonaut/Json;
    flags: (0x0001) ACC_PUBLIC
    Code:
      stack=3, locals=3, args_size=3
         0: aload_0
         1: aload_1
         2: aload_2
         3: invokestatic  #113                // InterfaceMethod argonaut/Jsons.jSingleObject$:(Largonaut/Jsons;Ljava/lang/String;Largonaut/Json;)Largonaut/Json;
         6: areturn
      LineNumberTable:
        line 486: 0
      LocalVariableTable:
        Start  Length  Slot  Name   Signature
            0       7     0  this   Largonaut/Json$;
            0       7     1     k   Ljava/lang/String;
            0       7     2     v   Largonaut/Json;
    MethodParameters:
      Name                           Flags
      k                              final
      v                              final

  public argonaut.Json jObjectAssocList(scala.collection.immutable.List<scala.Tuple2<java.lang.String, argonaut.Json>>);
    descriptor: (Lscala/collection/immutable/List;)Largonaut/Json;
    flags: (0x0001) ACC_PUBLIC
    Code:
      stack=2, locals=2, args_size=2
         0: aload_0
         1: aload_1
         2: invokestatic  #121                // InterfaceMethod argonaut/Jsons.jObjectAssocList$:(Largonaut/Jsons;Lscala/collection/immutable/List;)Largonaut/Json;
         5: areturn
      LineNumberTable:
        line 486: 0
      LocalVariableTable:
        Start  Length  Slot  Name   Signature
            0       6     0  this   Largonaut/Json$;
            0       6     1     x   Lscala/collection/immutable/List;
    Signature: #116                         // (Lscala/collection/immutable/List<Lscala/Tuple2<Ljava/lang/String;Largonaut/Json;>;>;)Largonaut/Json;
    MethodParameters:
      Name                           Flags
      x                              final

  public argonaut.Json jObjectFields(scala.collection.immutable.Seq<scala.Tuple2<java.lang.String, argonaut.Json>>);
    descriptor: (Lscala/collection/immutable/Seq;)Largonaut/Json;
    flags: (0x0001) ACC_PUBLIC
    Code:
      stack=2, locals=2, args_size=2
         0: aload_0
         1: aload_1
         2: invokestatic  #127                // InterfaceMethod argonaut/Jsons.jObjectFields$:(Largonaut/Jsons;Lscala/collection/immutable/Seq;)Largonaut/Json;
         5: areturn
      LineNumberTable:
        line 486: 0
      LocalVariableTable:
        Start  Length  Slot  Name   Signature
            0       6     0  this   Largonaut/Json$;
            0       6     1     x   Lscala/collection/immutable/Seq;
    Signature: #124                         // (Lscala/collection/immutable/Seq<Lscala/Tuple2<Ljava/lang/String;Largonaut/Json;>;>;)Largonaut/Json;
    MethodParameters:
      Name                           Flags
      x                              final

  public argonaut.Json jNull();
    descriptor: ()Largonaut/Json;
    flags: (0x0001) ACC_PUBLIC
    Code:
      stack=1, locals=1, args_size=1
         0: getstatic     #130                // Field jNull:Largonaut/Json;
         3: areturn
      LineNumberTable:
        line 486: 0
      LocalVariableTable:
        Start  Length  Slot  Name   Signature
            0       4     0  this   Largonaut/Json$;

  public scala.Function1<java.lang.Object, argonaut.Json> jBool();
    descriptor: ()Lscala/Function1;
    flags: (0x0001) ACC_PUBLIC
    Code:
      stack=1, locals=1, args_size=1
         0: getstatic     #134                // Field jBool:Lscala/Function1;
         3: areturn
      LineNumberTable:
        line 486: 0
      LocalVariableTable:
        Start  Length  Slot  Name   Signature
            0       4     0  this   Largonaut/Json$;
    Signature: #132                         // ()Lscala/Function1<Ljava/lang/Object;Largonaut/Json;>;

  public scala.Function1<java.lang.String, argonaut.Json> jString();
    descriptor: ()Lscala/Function1;
    flags: (0x0001) ACC_PUBLIC
    Code:
      stack=1, locals=1, args_size=1
         0: getstatic     #137                // Field jString:Lscala/Function1;
         3: areturn
      LineNumberTable:
        line 486: 0
      LocalVariableTable:
        Start  Length  Slot  Name   Signature
            0       4     0  this   Largonaut/Json$;
    Signature: #135                         // ()Lscala/Function1<Ljava/lang/String;Largonaut/Json;>;

  public scala.Function1<scala.collection.immutable.List<argonaut.Json>, argonaut.Json> jArray();
    descriptor: ()Lscala/Function1;
    flags: (0x0001) ACC_PUBLIC
    Code:
      stack=1, locals=1, args_size=1
         0: getstatic     #140                // Field jArray:Lscala/Function1;
         3: areturn
      LineNumberTable:
        line 486: 0
      LocalVariableTable:
        Start  Length  Slot  Name   Signature
            0       4     0  this   Largonaut/Json$;
    Signature: #138                         // ()Lscala/Function1<Lscala/collection/immutable/List<Largonaut/Json;>;Largonaut/Json;>;

  public scala.Function1<argonaut.JsonObject, argonaut.Json> jObject();
    descriptor: ()Lscala/Function1;
    flags: (0x0001) ACC_PUBLIC
    Code:
      stack=1, locals=1, args_size=1
         0: getstatic     #143                // Field jObject:Lscala/Function1;
         3: areturn
      LineNumberTable:
        line 486: 0
      LocalVariableTable:
        Start  Length  Slot  Name   Signature
            0       4     0  this   Largonaut/Json$;
    Signature: #141                         // ()Lscala/Function1<Largonaut/JsonObject;Largonaut/Json;>;

  public argonaut.Json jTrue();
    descriptor: ()Largonaut/Json;
    flags: (0x0001) ACC_PUBLIC
    Code:
      stack=1, locals=1, args_size=1
         0: getstatic     #145                // Field jTrue:Largonaut/Json;
         3: areturn
      LineNumberTable:
        line 486: 0
      LocalVariableTable:
        Start  Length  Slot  Name   Signature
            0       4     0  this   Largonaut/Json$;

  public argonaut.Json jFalse();
    descriptor: ()Largonaut/Json;
    flags: (0x0001) ACC_PUBLIC
    Code:
      stack=1, locals=1, args_size=1
         0: getstatic     #147                // Field jFalse:Largonaut/Json;
         3: areturn
      LineNumberTable:
        line 486: 0
      LocalVariableTable:
        Start  Length  Slot  Name   Signature
            0       4     0  this   Largonaut/Json$;

  public argonaut.Json jZero();
    descriptor: ()Largonaut/Json;
    flags: (0x0001) ACC_PUBLIC
    Code:
      stack=1, locals=1, args_size=1
         0: getstatic     #149                // Field jZero:Largonaut/Json;
         3: areturn
      LineNumberTable:
        line 486: 0
      LocalVariableTable:
        Start  Length  Slot  Name   Signature
            0       4     0  this   Largonaut/Json$;

  public argonaut.Json jEmptyString();
    descriptor: ()Largonaut/Json;
    flags: (0x0001) ACC_PUBLIC
    Code:
      stack=1, locals=1, args_size=1
         0: getstatic     #151                // Field jEmptyString:Largonaut/Json;
         3: areturn
      LineNumberTable:
        line 486: 0
      LocalVariableTable:
        Start  Length  Slot  Name   Signature
            0       4     0  this   Largonaut/Json$;

  public argonaut.Json jEmptyArray();
    descriptor: ()Largonaut/Json;
    flags: (0x0001) ACC_PUBLIC
    Code:
      stack=1, locals=1, args_size=1
         0: getstatic     #153                // Field jEmptyArray:Largonaut/Json;
         3: areturn
      LineNumberTable:
        line 486: 0
      LocalVariableTable:
        Start  Length  Slot  Name   Signature
            0       4     0  this   Largonaut/Json$;

  public argonaut.Json jEmptyObject();
    descriptor: ()Largonaut/Json;
    flags: (0x0001) ACC_PUBLIC
    Code:
      stack=1, locals=1, args_size=1
         0: getstatic     #155                // Field jEmptyObject:Largonaut/Json;
         3: areturn
      LineNumberTable:
        line 486: 0
      LocalVariableTable:
        Start  Length  Slot  Name   Signature
            0       4     0  this   Largonaut/Json$;

  public void argonaut$Jsons$_setter_$jNull_$eq(argonaut.Json);
    descriptor: (Largonaut/Json;)V
    flags: (0x0001) ACC_PUBLIC
    Code:
      stack=1, locals=2, args_size=2
         0: aload_1
         1: putstatic     #130                // Field jNull:Largonaut/Json;
         4: return
      LineNumberTable:
        line 486: 0
      LocalVariableTable:
        Start  Length  Slot  Name   Signature
            0       5     0  this   Largonaut/Json$;
            0       5     1   x$1   Largonaut/Json;
    MethodParameters:
      Name                           Flags
      x$1                            final

  public void argonaut$Jsons$_setter_$jBool_$eq(scala.Function1<java.lang.Object, argonaut.Json>);
    descriptor: (Lscala/Function1;)V
    flags: (0x0001) ACC_PUBLIC
    Code:
      stack=1, locals=2, args_size=2
         0: aload_1
         1: putstatic     #134                // Field jBool:Lscala/Function1;
         4: return
      LineNumberTable:
        line 486: 0
      LocalVariableTable:
        Start  Length  Slot  Name   Signature
            0       5     0  this   Largonaut/Json$;
            0       5     1   x$1   Lscala/Function1;
    Signature: #161                         // (Lscala/Function1<Ljava/lang/Object;Largonaut/Json;>;)V
    MethodParameters:
      Name                           Flags
      x$1                            final

  public void argonaut$Jsons$_setter_$jString_$eq(scala.Function1<java.lang.String, argonaut.Json>);
    descriptor: (Lscala/Function1;)V
    flags: (0x0001) ACC_PUBLIC
    Code:
      stack=1, locals=2, args_size=2
         0: aload_1
         1: putstatic     #137                // Field jString:Lscala/Function1;
         4: return
      LineNumberTable:
        line 486: 0
      LocalVariableTable:
        Start  Length  Slot  Name   Signature
            0       5     0  this   Largonaut/Json$;
            0       5     1   x$1   Lscala/Function1;
    Signature: #163                         // (Lscala/Function1<Ljava/lang/String;Largonaut/Json;>;)V
    MethodParameters:
      Name                           Flags
      x$1                            final

  public void argonaut$Jsons$_setter_$jArray_$eq(scala.Function1<scala.collection.immutable.List<argonaut.Json>, argonaut.Json>);
    descriptor: (Lscala/Function1;)V
    flags: (0x0001) ACC_PUBLIC
    Code:
      stack=1, locals=2, args_size=2
         0: aload_1
         1: putstatic     #140                // Field jArray:Lscala/Function1;
         4: return
      LineNumberTable:
        line 486: 0
      LocalVariableTable:
        Start  Length  Slot  Name   Signature
            0       5     0  this   Largonaut/Json$;
            0       5     1   x$1   Lscala/Function1;
    Signature: #165                         // (Lscala/Function1<Lscala/collection/immutable/List<Largonaut/Json;>;Largonaut/Json;>;)V
    MethodParameters:
      Name                           Flags
      x$1                            final

  public void argonaut$Jsons$_setter_$jObject_$eq(scala.Function1<argonaut.JsonObject, argonaut.Json>);
    descriptor: (Lscala/Function1;)V
    flags: (0x0001) ACC_PUBLIC
    Code:
      stack=1, locals=2, args_size=2
         0: aload_1
         1: putstatic     #143                // Field jObject:Lscala/Function1;
         4: return
      LineNumberTable:
        line 486: 0
      LocalVariableTable:
        Start  Length  Slot  Name   Signature
            0       5     0  this   Largonaut/Json$;
            0       5     1   x$1   Lscala/Function1;
    Signature: #167                         // (Lscala/Function1<Largonaut/JsonObject;Largonaut/Json;>;)V
    MethodParameters:
      Name                           Flags
      x$1                            final

  public void argonaut$Jsons$_setter_$jTrue_$eq(argonaut.Json);
    descriptor: (Largonaut/Json;)V
    flags: (0x0001) ACC_PUBLIC
    Code:
      stack=1, locals=2, args_size=2
         0: aload_1
         1: putstatic     #145                // Field jTrue:Largonaut/Json;
         4: return
      LineNumberTable:
        line 486: 0
      LocalVariableTable:
        Start  Length  Slot  Name   Signature
            0       5     0  this   Largonaut/Json$;
            0       5     1   x$1   Largonaut/Json;
    MethodParameters:
      Name                           Flags
      x$1                            final

  public void argonaut$Jsons$_setter_$jFalse_$eq(argonaut.Json);
    descriptor: (Largonaut/Json;)V
    flags: (0x0001) ACC_PUBLIC
    Code:
      stack=1, locals=2, args_size=2
         0: aload_1
         1: putstatic     #147                // Field jFalse:Largonaut/Json;
         4: return
      LineNumberTable:
        line 486: 0
      LocalVariableTable:
        Start  Length  Slot  Name   Signature
            0       5     0  this   Largonaut/Json$;
            0       5     1   x$1   Largonaut/Json;
    MethodParameters:
      Name                           Flags
      x$1                            final

  public void argonaut$Jsons$_setter_$jZero_$eq(argonaut.Json);
    descriptor: (Largonaut/Json;)V
    flags: (0x0001) ACC_PUBLIC
    Code:
      stack=1, locals=2, args_size=2
         0: aload_1
         1: putstatic     #149                // Field jZero:Largonaut/Json;
         4: return
      LineNumberTable:
        line 486: 0
      LocalVariableTable:
        Start  Length  Slot  Name   Signature
            0       5     0  this   Largonaut/Json$;
            0       5     1   x$1   Largonaut/Json;
    MethodParameters:
      Name                           Flags
      x$1                            final

  public void argonaut$Jsons$_setter_$jEmptyString_$eq(argonaut.Json);
    descriptor: (Largonaut/Json;)V
    flags: (0x0001) ACC_PUBLIC
    Code:
      stack=1, locals=2, args_size=2
         0: aload_1
         1: putstatic     #151                // Field jEmptyString:Largonaut/Json;
         4: return
      LineNumberTable:
        line 486: 0
      LocalVariableTable:
        Start  Length  Slot  Name   Signature
            0       5     0  this   Largonaut/Json$;
            0       5     1   x$1   Largonaut/Json;
    MethodParameters:
      Name                           Flags
      x$1                            final

  public void argonaut$Jsons$_setter_$jEmptyArray_$eq(argonaut.Json);
    descriptor: (Largonaut/Json;)V
    flags: (0x0001) ACC_PUBLIC
    Code:
      stack=1, locals=2, args_size=2
         0: aload_1
         1: putstatic     #153                // Field jEmptyArray:Largonaut/Json;
         4: return
      LineNumberTable:
        line 486: 0
      LocalVariableTable:
        Start  Length  Slot  Name   Signature
            0       5     0  this   Largonaut/Json$;
            0       5     1   x$1   Largonaut/Json;
    MethodParameters:
      Name                           Flags
      x$1                            final

  public void argonaut$Jsons$_setter_$jEmptyObject_$eq(argonaut.Json);
    descriptor: (Largonaut/Json;)V
    flags: (0x0001) ACC_PUBLIC
    Code:
      stack=1, locals=2, args_size=2
         0: aload_1
         1: putstatic     #155                // Field jEmptyObject:Largonaut/Json;
         4: return
      LineNumberTable:
        line 486: 0
      LocalVariableTable:
        Start  Length  Slot  Name   Signature
            0       5     0  this   Largonaut/Json$;
            0       5     1   x$1   Largonaut/Json;
    MethodParameters:
      Name                           Flags
      x$1                            final

  public argonaut.Json apply(scala.collection.immutable.Seq<scala.Tuple2<java.lang.String, argonaut.Json>>);
    descriptor: (Lscala/collection/immutable/Seq;)Largonaut/Json;
    flags: (0x0001) ACC_PUBLIC
    Code:
      stack=2, locals=2, args_size=2
         0: aload_0
         1: aload_1
         2: invokeinterface #181,  1          // InterfaceMethod scala/collection/immutable/Seq.toList:()Lscala/collection/immutable/List;
         7: invokevirtual #183                // Method jObjectAssocList:(Lscala/collection/immutable/List;)Largonaut/Json;
        10: areturn
      LineNumberTable:
        line 488: 0
      LocalVariableTable:
        Start  Length  Slot  Name   Signature
            0      11     0  this   Largonaut/Json$;
            0      11     1 fields   Lscala/collection/immutable/Seq;
    Signature: #124                         // (Lscala/collection/immutable/Seq<Lscala/Tuple2<Ljava/lang/String;Largonaut/Json;>;>;)Largonaut/Json;
    MethodParameters:
      Name                           Flags
      fields                         final

  public argonaut.Json obj(scala.collection.immutable.Seq<scala.Tuple2<java.lang.String, argonaut.Json>>);
    descriptor: (Lscala/collection/immutable/Seq;)Largonaut/Json;
    flags: (0x0001) ACC_PUBLIC
    Code:
      stack=2, locals=2, args_size=2
         0: aload_0
         1: aload_1
         2: invokeinterface #181,  1          // InterfaceMethod scala/collection/immutable/Seq.toList:()Lscala/collection/immutable/List;
         7: invokevirtual #183                // Method jObjectAssocList:(Lscala/collection/immutable/List;)Largonaut/Json;
        10: areturn
      LineNumberTable:
        line 491: 0
      LocalVariableTable:
        Start  Length  Slot  Name   Signature
            0      11     0  this   Largonaut/Json$;
            0      11     1 fields   Lscala/collection/immutable/Seq;
    Signature: #124                         // (Lscala/collection/immutable/Seq<Lscala/Tuple2<Ljava/lang/String;Largonaut/Json;>;>;)Largonaut/Json;
    MethodParameters:
      Name                           Flags
      fields                         final

  public argonaut.Json array(scala.collection.immutable.Seq<argonaut.Json>);
    descriptor: (Lscala/collection/immutable/Seq;)Largonaut/Json;
    flags: (0x0001) ACC_PUBLIC
    Code:
      stack=2, locals=2, args_size=2
         0: aload_0
         1: invokevirtual #187                // Method jArray:()Lscala/Function1;
         4: aload_1
         5: invokeinterface #181,  1          // InterfaceMethod scala/collection/immutable/Seq.toList:()Lscala/collection/immutable/List;
        10: invokeinterface #192,  2          // InterfaceMethod scala/Function1.apply:(Ljava/lang/Object;)Ljava/lang/Object;
        15: checkcast     #194                // class argonaut/Json
        18: areturn
      LineNumberTable:
        line 494: 0
      LocalVariableTable:
        Start  Length  Slot  Name   Signature
            0      19     0  this   Largonaut/Json$;
            0      19     1 elements   Lscala/collection/immutable/Seq;
    Signature: #99                          // (Lscala/collection/immutable/Seq<Largonaut/Json;>;)Largonaut/Json;
    MethodParameters:
      Name                           Flags
      elements                       final

  private java.lang.Object writeReplace();
    descriptor: ()Ljava/lang/Object;
    flags: (0x0002) ACC_PRIVATE
    Code:
      stack=3, locals=1, args_size=1
         0: new           #198                // class scala/runtime/ModuleSerializationProxy
         3: dup
         4: ldc           #2                  // class argonaut/Json$
         6: invokespecial #201                // Method scala/runtime/ModuleSerializationProxy."<init>":(Ljava/lang/Class;)V
         9: areturn
      LineNumberTable:
        line 486: 0
      LocalVariableTable:
        Start  Length  Slot  Name   Signature
            0      10     0  this   Largonaut/Json$;

  private argonaut.Json$();
    descriptor: ()V
    flags: (0x0002) ACC_PRIVATE
    Code:
      stack=1, locals=1, args_size=1
         0: aload_0
         1: invokespecial #202                // Method java/lang/Object."<init>":()V
         4: return
      LineNumberTable:
        line 486: 0
      LocalVariableTable:
        Start  Length  Slot  Name   Signature
            0       5     0  this   Largonaut/Json$;
}
SourceFile: "Json.scala"
  ScalaInlineInfo: length = 0xD6 (unknown attribute)
   01 01 00 2A 00 1F 00 1E 01 00 AE 00 62 01 00 A4
   00 A0 01 00 9F 00 A0 01 00 AC 00 9D 01 00 AD 00
   9D 01 00 AB 00 9D 01 00 A9 00 9D 01 00 9C 00 9D
   01 00 A6 00 A0 01 00 A2 00 A0 01 00 A8 00 9D 01
   00 AA 00 9D 01 00 B9 00 62 01 00 13 00 83 01 00
   61 00 62 01 00 0E 00 83 01 00 1B 00 80 01 00 1C
   00 80 01 00 1A 00 80 01 00 18 00 80 01 00 0C 00
   80 01 00 28 00 3B 01 00 28 00 31 01 00 28 00 36
   01 00 28 00 29 01 00 28 00 50 01 00 28 00 4B 01
   00 41 00 42 01 00 41 00 50 01 00 47 00 42 01 00
   47 00 50 01 00 15 00 83 01 00 72 00 73 01 00 7B
   00 62 01 00 5A 00 5B 01 00 6A 00 6B 01 00 11 00
   83 01 00 17 00 80 01 00 19 00 80 01 00 B8 00 62
   01 00 C3 00 C4 01
  Scala: length = 0x0 (unknown attribute)

