Classfile /Users/mw/Projects/slang-braindump/.jar/jar8/assemble/slang-braindump/assemble/content/argonaut/Jsons.class
  Last modified May 29, 2022; size 14678 bytes
  SHA-256 checksum 3f24bd24c99c47c86abe59924fab9afc5f1f10c31e0e33735405553c05fb78ba
  Compiled from "Json.scala"
public interface argonaut.Jsons
  minor version: 0
  major version: 52
  flags: (0x0601) ACC_PUBLIC, ACC_INTERFACE, ACC_ABSTRACT
  this_class: #2                          // argonaut/Jsons
  super_class: #4                         // java/lang/Object
  interfaces: 0, fields: 0, methods: 66, attributes: 6
Constant pool:
    #1 = Utf8               argonaut/Jsons
    #2 = Class              #1            // argonaut/Jsons
    #3 = Utf8               java/lang/Object
    #4 = Class              #3            // java/lang/Object
    #5 = Utf8               Json.scala
    #6 = Utf8               Lscala/reflect/ScalaSignature;
    #7 = Utf8               bytes
    #8 = Utf8               \u0006\u0005\u0005Mda\u0002\u0012$!\u0003\r\tA\n\u0005\u0006[\u0001!\tAL\u0003\u0005e\u0001\u00011\'\u0002\u00037\u0001\u00019T\u0001B$\u0001\u0001!+A\u0001\u0015\u0001\u0001\u0011\u0016!\u0011\u000b\u0001\u0001S\u000b\u00119\u0006\u0001\u0001-\t\u000fi\u0003!\u0019!C\u00017\"9A\f\u0001b\u0001\n\u0003i\u0006\"B1\u0001\t\u0003\u0011\u0007\"B1\u0001\t\u0003A\u0007\"B1\u0001\t\u0003i\u0007\"B1\u0001\t\u0003\u0011\b\"\u0002>\u0001\t\u0003Y\b\"B?\u0001\t\u0003q\bBB1\u0001\t\u0003\t\t\u0001\u0003\u0004b\u0001\u0011\u0005\u00111\u0002\u0005\u0007u\u0002!\t!a\u0004\t\ru\u0004A\u0011AA\n\u0011%\t9\u0002\u0001b\u0001\n\u0003\tI\u0002C\u0005\u0002 \u0001\u0011\r\u0011\"\u0001\u0002\"!I\u0011q\u0005\u0001C\u0002\u0013\u0005\u0011\u0011\u0006\u0005\t\u0003g\u0001!\u0019!C\u00017\"A\u0011Q\u0007\u0001C\u0002\u0013\u00051\f\u0003\u0005\u00028\u0001\u0011\r\u0011\"\u0001\\\u0011!\tI\u0004\u0001b\u0001\n\u0003Y\u0006\u0002CA\u001e\u0001\t\u0007I\u0011A.\t\u000f\u0005u\u0002\u0001\"\u0001\u0002@!9\u0011Q\t\u0001\u0005\u0002\u0005\u001d\u0003\u0002CA*\u0001\t\u0007I\u0011A.\t\u000f\u0005U\u0003\u0001\"\u0001\u0002X!9\u0011\u0011\r\u0001\u0005\u0002\u0005\r\u0004bBA6\u0001\u0011\u0005\u0011Q\u000e\u0002\u0006\u0015N|gn\u001d\u0006\u0002I\u0005A\u0011M]4p]\u0006,Ho\u0001\u0001\u0014\u0005\u00019\u0003C\u0001\u0015,\u001b\u0005I#\"\u0001\u0016\u0002\u000bM\u001c\u0017\r\\1\n\u00051J#AB!osJ+g-\u0001\u0004%S:LG\u000f\n\u000b\u0002_A\u0011\u0001\u0006M\u0005\u0003c%\u0012A!\u00168ji\nY!j]8o\u0005>|G.Z1o!\tAC\'\u0003\u00026S\t9!i\\8mK\u0006t\'!\u0003&t_:\f%O]1z!\rA\u0004i\u0011\b\u0003syr!AO\u001f\u000e\u0003mR!\u0001P\u0013\u0002\rq\u0012xn\u001c;?\u0013\u0005Q\u0013BA *\u0003\u001d\u0001\u0018mY6bO\u0016L!!\u0011\"\u0003\t1K7\u000f\u001e\u0006\u0003\u007f%\u0002\"\u0001R#\u000e\u0003\rJ!AR\u0012\u0003\t)\u001bxN\u001c\u0002\u000b\u0015N|gn\u0015;sS:<\u0007CA%N\u001d\tQ5\n\u0005\u0002;S%\u0011A*K\u0001\u0007!J,G-\u001a4\n\u00059{%AB*ue&twM\u0003\u0002MS\tI!j]8o\r&,G\u000e\u001a\u0002\n\u0015N|g.Q:t_\u000e\u0004B\u0001K*V\u0007&\u0011A+\u000b\u0002\u0007)V\u0004H.\u001a\u001a\u0011\u0005Y+Q\"\u0001\u0001\u0003\u001b)\u001bxN\\!tg>\u001cG*[:u!\rA\u0004)\u0017\t\u0003-\u001a\tQA\u001b(vY2,\u0012aQ\u0001\u0006U\n{w\u000e\\\u000b\u0002=B!\u0001fX\u001aD\u0013\t\u0001\u0017FA\u0005Gk:\u001cG/[8oc\u00059!NT;nE\u0016\u0014HCA\"d\u0011\u0015!\'\u00021\u0001f\u0003\u0005q\u0007C\u0001#g\u0013\t97E\u0001\u0006Kg>tg*^7cKJ$\"aQ5\t\u000b\u0011\\\u0001\u0019\u00016\u0011\u0005!Z\u0017B\u00017*\u0005\rIe\u000e\u001e\u000b\u0003\u0007:DQ\u0001\u001a\u0007A\u0002=\u0004\"\u0001\u000b9\n\u0005EL#\u0001\u0002\'p]\u001e$\"a\u001d<\u0011\u0007!\"8)\u0003\u0002vS\t1q\n\u001d;j_:DQ\u0001Z\u0007A\u0002]\u0004\"\u0001\u000b=\n\u0005eL#A\u0002#pk\ndW-A\u0007k\u001dVl\'-\u001a:Pe:+H\u000e\u001c\u000b\u0003\u0007rDQ\u0001\u001a\bA\u0002]\fqB\u001b(v[\n,\'o\u0014:TiJLgn\u001a\u000b\u0003\u0007~DQ\u0001Z\bA\u0002]$2aQA\u0002\u0011\u0019!\u0007\u00031\u0001\u0002\u0006A\u0019\u0001(a\u0002\n\u0007\u0005%!I\u0001\u0006CS\u001e$UmY5nC2$2a]A\u0007\u0011\u0015!\u0017\u00031\u0001I)\r\u0019\u0018\u0011\u0003\u0005\u0006IJ\u0001\r\u0001\u0013\u000b\u0004g\u0006U\u0001\"\u00023\u0014\u0001\u0004A\u0015a\u00026TiJLgnZ\u000b\u0003\u00037\u0001R\u0001K0\u0002\u001e\r\u0003\"A\u0016\u0003\u0002\r)\f%O]1z+\t\t\u0019\u0003E\u0003)?\u0006\u00152\t\u0005\u0002W\u0007\u00059!n\u00142kK\u000e$XCAA\u0016!\u0015As,!\fD!\r!\u0015qF\u0005\u0004\u0003c\u0019#A\u0003&t_:|%M[3di\u0006)!\u000e\u0016:vK\u00061!NR1mg\u0016\fQA\u001b.fe>\fAB[#naRL8\u000b\u001e:j]\u001e\f1B[#naRL\u0018I\u001d:bs\u0006a!nU5oO2,\u0017I\u001d:bsR\u00191)!\u0011\t\r\u0005\rC\u00041\u0001D\u0003\u0005Q\u0017A\u00046BeJ\f\u00170\u00127f[\u0016tGo\u001d\u000b\u0004\u0007\u0006%\u0003bBA&;\u0001\u0007\u0011QJ\u0001\tK2,W.\u001a8ugB!\u0001&a\u0014D\u0013\r\t\t&\u000b\u0002\u000byI,\u0007/Z1uK\u0012t\u0014\u0001\u00046F[B$\u0018p\u00142kK\u000e$\u0018!\u00046TS:<G.Z(cU\u0016\u001cG\u000fF\u0003D\u00033\ni\u0006\u0003\u0004\u0002\\}\u0001\r!V\u0001\u0002W\"1\u0011qL\u0010A\u0002\r\u000b\u0011A^\u0001\u0011U>\u0013\'.Z2u\u0003N\u001cxn\u0019\'jgR$2aQA3\u0011\u001d\t9\u0007\ta\u0001\u0003S\n\u0011\u0001\u001f\t\u0003-\u001e\tQB[(cU\u0016\u001cGOR5fY\u0012\u001cHcA\"\u0002p!9\u0011qM\u0011A\u0002\u0005E\u0004\u0003\u0002\u0015\u0002PI\u0003
    #9 = Utf8               java/lang/invoke/MethodHandles$Lookup
   #10 = Class              #9            // java/lang/invoke/MethodHandles$Lookup
   #11 = Utf8               java/lang/invoke/MethodHandles
   #12 = Class              #11           // java/lang/invoke/MethodHandles
   #13 = Utf8               Lookup
   #14 = Utf8               argonaut$Jsons$_setter_$jNull_$eq
   #15 = Utf8               (Largonaut/Json;)V
   #16 = Utf8               x$1
   #17 = Utf8               argonaut$Jsons$_setter_$jBool_$eq
   #18 = Utf8               (Lscala/Function1;)V
   #19 = Utf8               (Lscala/Function1<Ljava/lang/Object;Largonaut/Json;>;)V
   #20 = Utf8               argonaut$Jsons$_setter_$jString_$eq
   #21 = Utf8               (Lscala/Function1<Ljava/lang/String;Largonaut/Json;>;)V
   #22 = Utf8               argonaut$Jsons$_setter_$jArray_$eq
   #23 = Utf8               (Lscala/Function1<Lscala/collection/immutable/List<Largonaut/Json;>;Largonaut/Json;>;)V
   #24 = Utf8               argonaut$Jsons$_setter_$jObject_$eq
   #25 = Utf8               (Lscala/Function1<Largonaut/JsonObject;Largonaut/Json;>;)V
   #26 = Utf8               argonaut$Jsons$_setter_$jTrue_$eq
   #27 = Utf8               argonaut$Jsons$_setter_$jFalse_$eq
   #28 = Utf8               argonaut$Jsons$_setter_$jZero_$eq
   #29 = Utf8               argonaut$Jsons$_setter_$jEmptyString_$eq
   #30 = Utf8               argonaut$Jsons$_setter_$jEmptyArray_$eq
   #31 = Utf8               argonaut$Jsons$_setter_$jEmptyObject_$eq
   #32 = Utf8               jNull
   #33 = Utf8               ()Largonaut/Json;
   #34 = Utf8               jBool
   #35 = Utf8               ()Lscala/Function1;
   #36 = Utf8               ()Lscala/Function1<Ljava/lang/Object;Largonaut/Json;>;
   #37 = Utf8               jNumber$
   #38 = Utf8               (Largonaut/Jsons;Largonaut/JsonNumber;)Largonaut/Json;
   #39 = Utf8               $this
   #40 = Utf8               n
   #41 = Utf8               jNumber
   #42 = Utf8               (Largonaut/JsonNumber;)Largonaut/Json;
   #43 = NameAndType        #41:#42       // jNumber:(Largonaut/JsonNumber;)Largonaut/Json;
   #44 = InterfaceMethodref #2.#43        // argonaut/Jsons.jNumber:(Largonaut/JsonNumber;)Largonaut/Json;
   #45 = Utf8               Largonaut/Jsons;
   #46 = Utf8               Largonaut/JsonNumber;
   #47 = Utf8               argonaut/JNumber
   #48 = Class              #47           // argonaut/JNumber
   #49 = Utf8               <init>
   #50 = Utf8               (Largonaut/JsonNumber;)V
   #51 = NameAndType        #49:#50       // "<init>":(Largonaut/JsonNumber;)V
   #52 = Methodref          #48.#51       // argonaut/JNumber."<init>":(Largonaut/JsonNumber;)V
   #53 = Utf8               this
   #54 = Utf8               (Largonaut/Jsons;I)Largonaut/Json;
   #55 = Utf8               (I)Largonaut/Json;
   #56 = NameAndType        #41:#55       // jNumber:(I)Largonaut/Json;
   #57 = InterfaceMethodref #2.#56        // argonaut/Jsons.jNumber:(I)Largonaut/Json;
   #58 = Utf8               I
   #59 = Utf8               argonaut/JsonIdentity$
   #60 = Class              #59           // argonaut/JsonIdentity$
   #61 = Utf8               MODULE$
   #62 = Utf8               Largonaut/JsonIdentity$;
   #63 = NameAndType        #61:#62       // MODULE$:Largonaut/JsonIdentity$;
   #64 = Fieldref           #60.#63       // argonaut/JsonIdentity$.MODULE$:Largonaut/JsonIdentity$;
   #65 = Utf8               scala/runtime/BoxesRunTime
   #66 = Class              #65           // scala/runtime/BoxesRunTime
   #67 = Utf8               boxToInteger
   #68 = Utf8               (I)Ljava/lang/Integer;
   #69 = NameAndType        #67:#68       // boxToInteger:(I)Ljava/lang/Integer;
   #70 = Methodref          #66.#69       // scala/runtime/BoxesRunTime.boxToInteger:(I)Ljava/lang/Integer;
   #71 = Utf8               ToJsonIdentity
   #72 = Utf8               (Ljava/lang/Object;)Ljava/lang/Object;
   #73 = NameAndType        #71:#72       // ToJsonIdentity:(Ljava/lang/Object;)Ljava/lang/Object;
   #74 = Methodref          #60.#73       // argonaut/JsonIdentity$.ToJsonIdentity:(Ljava/lang/Object;)Ljava/lang/Object;
   #75 = Utf8               argonaut/EncodeJsonNumber$
   #76 = Class              #75           // argonaut/EncodeJsonNumber$
   #77 = Utf8               Largonaut/EncodeJsonNumber$;
   #78 = NameAndType        #61:#77       // MODULE$:Largonaut/EncodeJsonNumber$;
   #79 = Fieldref           #76.#78       // argonaut/EncodeJsonNumber$.MODULE$:Largonaut/EncodeJsonNumber$;
   #80 = Utf8               encodeJsonNumberInt
   #81 = Utf8               ()Largonaut/EncodeJsonNumber;
   #82 = NameAndType        #80:#81       // encodeJsonNumberInt:()Largonaut/EncodeJsonNumber;
   #83 = Methodref          #76.#82       // argonaut/EncodeJsonNumber$.encodeJsonNumberInt:()Largonaut/EncodeJsonNumber;
   #84 = Utf8               asJsonNumber$extension
   #85 = Utf8               (Ljava/lang/Object;Largonaut/EncodeJsonNumber;)Largonaut/JsonNumber;
   #86 = NameAndType        #84:#85       // asJsonNumber$extension:(Ljava/lang/Object;Largonaut/EncodeJsonNumber;)Largonaut/JsonNumber;
   #87 = Methodref          #60.#86       // argonaut/JsonIdentity$.asJsonNumber$extension:(Ljava/lang/Object;Largonaut/EncodeJsonNumber;)Largonaut/JsonNumber;
   #88 = Utf8               (Largonaut/Jsons;J)Largonaut/Json;
   #89 = Utf8               (J)Largonaut/Json;
   #90 = NameAndType        #41:#89       // jNumber:(J)Largonaut/Json;
   #91 = InterfaceMethodref #2.#90        // argonaut/Jsons.jNumber:(J)Largonaut/Json;
   #92 = Utf8               J
   #93 = Utf8               boxToLong
   #94 = Utf8               (J)Ljava/lang/Long;
   #95 = NameAndType        #93:#94       // boxToLong:(J)Ljava/lang/Long;
   #96 = Methodref          #66.#95       // scala/runtime/BoxesRunTime.boxToLong:(J)Ljava/lang/Long;
   #97 = Utf8               encodeJsonNumberLong
   #98 = NameAndType        #97:#81       // encodeJsonNumberLong:()Largonaut/EncodeJsonNumber;
   #99 = Methodref          #76.#98       // argonaut/EncodeJsonNumber$.encodeJsonNumberLong:()Largonaut/EncodeJsonNumber;
  #100 = Utf8               (Largonaut/Jsons;D)Lscala/Option;
  #101 = Utf8               (D)Lscala/Option;
  #102 = NameAndType        #41:#101      // jNumber:(D)Lscala/Option;
  #103 = InterfaceMethodref #2.#102       // argonaut/Jsons.jNumber:(D)Lscala/Option;
  #104 = Utf8               D
  #105 = Utf8               (D)Lscala/Option<Largonaut/Json;>;
  #106 = Utf8               boxToDouble
  #107 = Utf8               (D)Ljava/lang/Double;
  #108 = NameAndType        #106:#107     // boxToDouble:(D)Ljava/lang/Double;
  #109 = Methodref          #66.#108      // scala/runtime/BoxesRunTime.boxToDouble:(D)Ljava/lang/Double;
  #110 = Utf8               encodeJsonNumberDouble
  #111 = Utf8               ()Largonaut/EncodePossibleJsonNumber;
  #112 = NameAndType        #110:#111     // encodeJsonNumberDouble:()Largonaut/EncodePossibleJsonNumber;
  #113 = Methodref          #76.#112      // argonaut/EncodeJsonNumber$.encodeJsonNumberDouble:()Largonaut/EncodePossibleJsonNumber;
  #114 = Utf8               asPossibleJsonNumber$extension
  #115 = Utf8               (Ljava/lang/Object;Largonaut/EncodePossibleJsonNumber;)Lscala/Option;
  #116 = NameAndType        #114:#115     // asPossibleJsonNumber$extension:(Ljava/lang/Object;Largonaut/EncodePossibleJsonNumber;)Lscala/Option;
  #117 = Methodref          #60.#116      // argonaut/JsonIdentity$.asPossibleJsonNumber$extension:(Ljava/lang/Object;Largonaut/EncodePossibleJsonNumber;)Lscala/Option;
  #118 = MethodType         #72           //  (Ljava/lang/Object;)Ljava/lang/Object;
  #119 = Utf8               $anonfun$jNumber$1
  #120 = Utf8               (Largonaut/JsonNumber;)Largonaut/JNumber;
  #121 = NameAndType        #119:#120     // $anonfun$jNumber$1:(Largonaut/JsonNumber;)Largonaut/JNumber;
  #122 = InterfaceMethodref #2.#121       // argonaut/Jsons.$anonfun$jNumber$1:(Largonaut/JsonNumber;)Largonaut/JNumber;
  #123 = MethodHandle       6:#122        // REF_invokeStatic argonaut/Jsons.$anonfun$jNumber$1:(Largonaut/JsonNumber;)Largonaut/JNumber;
  #124 = MethodType         #120          //  (Largonaut/JsonNumber;)Largonaut/JNumber;
  #125 = Integer            5
  #126 = Integer            1
  #127 = Utf8               java/lang/invoke/LambdaMetafactory
  #128 = Class              #127          // java/lang/invoke/LambdaMetafactory
  #129 = Utf8               altMetafactory
  #130 = Utf8               (Ljava/lang/invoke/MethodHandles$Lookup;Ljava/lang/String;Ljava/lang/invoke/MethodType;[Ljava/lang/Object;)Ljava/lang/invoke/CallSite;
  #131 = NameAndType        #129:#130     // altMetafactory:(Ljava/lang/invoke/MethodHandles$Lookup;Ljava/lang/String;Ljava/lang/invoke/MethodType;[Ljava/lang/Object;)Ljava/lang/invoke/CallSite;
  #132 = Methodref          #128.#131     // java/lang/invoke/LambdaMetafactory.altMetafactory:(Ljava/lang/invoke/MethodHandles$Lookup;Ljava/lang/String;Ljava/lang/invoke/MethodType;[Ljava/lang/Object;)Ljava/lang/invoke/CallSite;
  #133 = MethodHandle       6:#132        // REF_invokeStatic java/lang/invoke/LambdaMetafactory.altMetafactory:(Ljava/lang/invoke/MethodHandles$Lookup;Ljava/lang/String;Ljava/lang/invoke/MethodType;[Ljava/lang/Object;)Ljava/lang/invoke/CallSite;
  #134 = Utf8               apply
  #135 = NameAndType        #134:#35      // apply:()Lscala/Function1;
  #136 = InvokeDynamic      #0:#135       // #0:apply:()Lscala/Function1;
  #137 = Utf8               scala/Option
  #138 = Class              #137          // scala/Option
  #139 = Utf8               map
  #140 = Utf8               (Lscala/Function1;)Lscala/Option;
  #141 = NameAndType        #139:#140     // map:(Lscala/Function1;)Lscala/Option;
  #142 = Methodref          #138.#141     // scala/Option.map:(Lscala/Function1;)Lscala/Option;
  #143 = Utf8               jNumberOrNull$
  #144 = Utf8               (Largonaut/Jsons;D)Largonaut/Json;
  #145 = Utf8               jNumberOrNull
  #146 = Utf8               (D)Largonaut/Json;
  #147 = NameAndType        #145:#146     // jNumberOrNull:(D)Largonaut/Json;
  #148 = InterfaceMethodref #2.#147       // argonaut/Jsons.jNumberOrNull:(D)Largonaut/Json;
  #149 = Utf8               ()Ljava/lang/Object;
  #150 = MethodType         #149          //  ()Ljava/lang/Object;
  #151 = Utf8               $anonfun$jNumberOrNull$1
  #152 = Utf8               (Largonaut/Jsons;)Largonaut/Json;
  #153 = NameAndType        #151:#152     // $anonfun$jNumberOrNull$1:(Largonaut/Jsons;)Largonaut/Json;
  #154 = InterfaceMethodref #2.#153       // argonaut/Jsons.$anonfun$jNumberOrNull$1:(Largonaut/Jsons;)Largonaut/Json;
  #155 = MethodHandle       6:#154        // REF_invokeStatic argonaut/Jsons.$anonfun$jNumberOrNull$1:(Largonaut/Jsons;)Largonaut/Json;
  #156 = MethodType         #33           //  ()Largonaut/Json;
  #157 = Utf8               (Largonaut/Jsons;)Lscala/Function0;
  #158 = NameAndType        #134:#157     // apply:(Largonaut/Jsons;)Lscala/Function0;
  #159 = InvokeDynamic      #1:#158       // #1:apply:(Largonaut/Jsons;)Lscala/Function0;
  #160 = Utf8               getOrElse
  #161 = Utf8               (Lscala/Function0;)Ljava/lang/Object;
  #162 = NameAndType        #160:#161     // getOrElse:(Lscala/Function0;)Ljava/lang/Object;
  #163 = Methodref          #138.#162     // scala/Option.getOrElse:(Lscala/Function0;)Ljava/lang/Object;
  #164 = Utf8               argonaut/Json
  #165 = Class              #164          // argonaut/Json
  #166 = Utf8               jNumberOrString$
  #167 = Utf8               jNumberOrString
  #168 = NameAndType        #167:#146     // jNumberOrString:(D)Largonaut/Json;
  #169 = InterfaceMethodref #2.#168       // argonaut/Jsons.jNumberOrString:(D)Largonaut/Json;
  #170 = Utf8               $anonfun$jNumberOrString$1
  #171 = NameAndType        #170:#144     // $anonfun$jNumberOrString$1:(Largonaut/Jsons;D)Largonaut/Json;
  #172 = InterfaceMethodref #2.#171       // argonaut/Jsons.$anonfun$jNumberOrString$1:(Largonaut/Jsons;D)Largonaut/Json;
  #173 = MethodHandle       6:#172        // REF_invokeStatic argonaut/Jsons.$anonfun$jNumberOrString$1:(Largonaut/Jsons;D)Largonaut/Json;
  #174 = Utf8               (Largonaut/Jsons;D)Lscala/Function0;
  #175 = NameAndType        #134:#174     // apply:(Largonaut/Jsons;D)Lscala/Function0;
  #176 = InvokeDynamic      #2:#175       // #2:apply:(Largonaut/Jsons;D)Lscala/Function0;
  #177 = Utf8               $anonfun$jNumberOrString$2
  #178 = NameAndType        #177:#42      // $anonfun$jNumberOrString$2:(Largonaut/JsonNumber;)Largonaut/Json;
  #179 = InterfaceMethodref #2.#178       // argonaut/Jsons.$anonfun$jNumberOrString$2:(Largonaut/JsonNumber;)Largonaut/Json;
  #180 = MethodHandle       6:#179        // REF_invokeStatic argonaut/Jsons.$anonfun$jNumberOrString$2:(Largonaut/JsonNumber;)Largonaut/Json;
  #181 = MethodType         #42           //  (Largonaut/JsonNumber;)Largonaut/Json;
  #182 = InvokeDynamic      #3:#135       // #3:apply:()Lscala/Function1;
  #183 = Utf8               fold
  #184 = Utf8               (Lscala/Function0;Lscala/Function1;)Ljava/lang/Object;
  #185 = NameAndType        #183:#184     // fold:(Lscala/Function0;Lscala/Function1;)Ljava/lang/Object;
  #186 = Methodref          #138.#185     // scala/Option.fold:(Lscala/Function0;Lscala/Function1;)Ljava/lang/Object;
  #187 = Utf8               (Largonaut/Jsons;Lscala/math/BigDecimal;)Largonaut/Json;
  #188 = Utf8               (Lscala/math/BigDecimal;)Largonaut/Json;
  #189 = NameAndType        #41:#188      // jNumber:(Lscala/math/BigDecimal;)Largonaut/Json;
  #190 = InterfaceMethodref #2.#189       // argonaut/Jsons.jNumber:(Lscala/math/BigDecimal;)Largonaut/Json;
  #191 = Utf8               Lscala/math/BigDecimal;
  #192 = Utf8               argonaut/JsonBigDecimal
  #193 = Class              #192          // argonaut/JsonBigDecimal
  #194 = Utf8               (Lscala/math/BigDecimal;)V
  #195 = NameAndType        #49:#194      // "<init>":(Lscala/math/BigDecimal;)V
  #196 = Methodref          #193.#195     // argonaut/JsonBigDecimal."<init>":(Lscala/math/BigDecimal;)V
  #197 = Utf8               (Largonaut/Jsons;Ljava/lang/String;)Lscala/Option;
  #198 = Utf8               (Ljava/lang/String;)Lscala/Option;
  #199 = NameAndType        #41:#198      // jNumber:(Ljava/lang/String;)Lscala/Option;
  #200 = InterfaceMethodref #2.#199       // argonaut/Jsons.jNumber:(Ljava/lang/String;)Lscala/Option;
  #201 = Utf8               Ljava/lang/String;
  #202 = Utf8               (Ljava/lang/String;)Lscala/Option<Largonaut/Json;>;
  #203 = Utf8               argonaut/JsonNumber$
  #204 = Class              #203          // argonaut/JsonNumber$
  #205 = Utf8               Largonaut/JsonNumber$;
  #206 = NameAndType        #61:#205      // MODULE$:Largonaut/JsonNumber$;
  #207 = Fieldref           #204.#206     // argonaut/JsonNumber$.MODULE$:Largonaut/JsonNumber$;
  #208 = Utf8               fromString
  #209 = NameAndType        #208:#198     // fromString:(Ljava/lang/String;)Lscala/Option;
  #210 = Methodref          #204.#209     // argonaut/JsonNumber$.fromString:(Ljava/lang/String;)Lscala/Option;
  #211 = Utf8               $anonfun$jNumber$2
  #212 = NameAndType        #211:#42      // $anonfun$jNumber$2:(Largonaut/JsonNumber;)Largonaut/Json;
  #213 = InterfaceMethodref #2.#212       // argonaut/Jsons.$anonfun$jNumber$2:(Largonaut/JsonNumber;)Largonaut/Json;
  #214 = MethodHandle       6:#213        // REF_invokeStatic argonaut/Jsons.$anonfun$jNumber$2:(Largonaut/JsonNumber;)Largonaut/Json;
  #215 = InvokeDynamic      #4:#135       // #4:apply:()Lscala/Function1;
  #216 = NameAndType        #145:#198     // jNumberOrNull:(Ljava/lang/String;)Lscala/Option;
  #217 = InterfaceMethodref #2.#216       // argonaut/Jsons.jNumberOrNull:(Ljava/lang/String;)Lscala/Option;
  #218 = Utf8               NaN
  #219 = String             #218          // NaN
  #220 = Utf8               equals
  #221 = Utf8               (Ljava/lang/Object;)Z
  #222 = NameAndType        #220:#221     // equals:(Ljava/lang/Object;)Z
  #223 = Methodref          #4.#222       // java/lang/Object.equals:(Ljava/lang/Object;)Z
  #224 = Utf8               Infinity
  #225 = String             #224          // Infinity
  #226 = Utf8               +Infinity
  #227 = String             #226          // +Infinity
  #228 = Utf8               -Infinity
  #229 = String             #228          // -Infinity
  #230 = Utf8               scala/Some
  #231 = Class              #230          // scala/Some
  #232 = NameAndType        #32:#33       // jNull:()Largonaut/Json;
  #233 = InterfaceMethodref #2.#232       // argonaut/Jsons.jNull:()Largonaut/Json;
  #234 = Utf8               (Ljava/lang/Object;)V
  #235 = NameAndType        #49:#234      // "<init>":(Ljava/lang/Object;)V
  #236 = Methodref          #231.#235     // scala/Some."<init>":(Ljava/lang/Object;)V
  #237 = Utf8               $anonfun$jNumberOrNull$2
  #238 = NameAndType        #237:#42      // $anonfun$jNumberOrNull$2:(Largonaut/JsonNumber;)Largonaut/Json;
  #239 = InterfaceMethodref #2.#238       // argonaut/Jsons.$anonfun$jNumberOrNull$2:(Largonaut/JsonNumber;)Largonaut/Json;
  #240 = MethodHandle       6:#239        // REF_invokeStatic argonaut/Jsons.$anonfun$jNumberOrNull$2:(Largonaut/JsonNumber;)Largonaut/Json;
  #241 = InvokeDynamic      #5:#135       // #5:apply:()Lscala/Function1;
  #242 = Utf8               java/lang/String
  #243 = Class              #242          // java/lang/String
  #244 = NameAndType        #167:#198     // jNumberOrString:(Ljava/lang/String;)Lscala/Option;
  #245 = InterfaceMethodref #2.#244       // argonaut/Jsons.jNumberOrString:(Ljava/lang/String;)Lscala/Option;
  #246 = Utf8               jString
  #247 = NameAndType        #246:#35      // jString:()Lscala/Function1;
  #248 = InterfaceMethodref #2.#247       // argonaut/Jsons.jString:()Lscala/Function1;
  #249 = Utf8               scala/Function1
  #250 = Class              #249          // scala/Function1
  #251 = NameAndType        #134:#72      // apply:(Ljava/lang/Object;)Ljava/lang/Object;
  #252 = InterfaceMethodref #250.#251     // scala/Function1.apply:(Ljava/lang/Object;)Ljava/lang/Object;
  #253 = Utf8               $anonfun$jNumberOrString$3
  #254 = NameAndType        #253:#42      // $anonfun$jNumberOrString$3:(Largonaut/JsonNumber;)Largonaut/Json;
  #255 = InterfaceMethodref #2.#254       // argonaut/Jsons.$anonfun$jNumberOrString$3:(Largonaut/JsonNumber;)Largonaut/Json;
  #256 = MethodHandle       6:#255        // REF_invokeStatic argonaut/Jsons.$anonfun$jNumberOrString$3:(Largonaut/JsonNumber;)Largonaut/Json;
  #257 = InvokeDynamic      #6:#135       // #6:apply:()Lscala/Function1;
  #258 = Utf8               ()Lscala/Function1<Ljava/lang/String;Largonaut/Json;>;
  #259 = Utf8               jArray
  #260 = Utf8               ()Lscala/Function1<Lscala/collection/immutable/List<Largonaut/Json;>;Largonaut/Json;>;
  #261 = Utf8               jObject
  #262 = Utf8               ()Lscala/Function1<Largonaut/JsonObject;Largonaut/Json;>;
  #263 = Utf8               jTrue
  #264 = Utf8               jFalse
  #265 = Utf8               jZero
  #266 = Utf8               jEmptyString
  #267 = Utf8               jEmptyArray
  #268 = Utf8               jSingleArray$
  #269 = Utf8               (Largonaut/Jsons;Largonaut/Json;)Largonaut/Json;
  #270 = Utf8               j
  #271 = Utf8               jSingleArray
  #272 = Utf8               (Largonaut/Json;)Largonaut/Json;
  #273 = NameAndType        #271:#272     // jSingleArray:(Largonaut/Json;)Largonaut/Json;
  #274 = InterfaceMethodref #2.#273       // argonaut/Jsons.jSingleArray:(Largonaut/Json;)Largonaut/Json;
  #275 = Utf8               Largonaut/Json;
  #276 = Utf8               argonaut/JArray
  #277 = Class              #276          // argonaut/JArray
  #278 = Utf8               scala/collection/immutable/$colon$colon
  #279 = Class              #278          // scala/collection/immutable/$colon$colon
  #280 = Utf8               scala/collection/immutable/Nil$
  #281 = Class              #280          // scala/collection/immutable/Nil$
  #282 = Utf8               Lscala/collection/immutable/Nil$;
  #283 = NameAndType        #61:#282      // MODULE$:Lscala/collection/immutable/Nil$;
  #284 = Fieldref           #281.#283     // scala/collection/immutable/Nil$.MODULE$:Lscala/collection/immutable/Nil$;
  #285 = Utf8               (Ljava/lang/Object;Lscala/collection/immutable/List;)V
  #286 = NameAndType        #49:#285      // "<init>":(Ljava/lang/Object;Lscala/collection/immutable/List;)V
  #287 = Methodref          #279.#286     // scala/collection/immutable/$colon$colon."<init>":(Ljava/lang/Object;Lscala/collection/immutable/List;)V
  #288 = Utf8               scala/collection/immutable/List
  #289 = Class              #288          // scala/collection/immutable/List
  #290 = Utf8               (Lscala/collection/immutable/List;)V
  #291 = NameAndType        #49:#290      // "<init>":(Lscala/collection/immutable/List;)V
  #292 = Methodref          #277.#291     // argonaut/JArray."<init>":(Lscala/collection/immutable/List;)V
  #293 = Utf8               jArrayElements$
  #294 = Utf8               (Largonaut/Jsons;Lscala/collection/immutable/Seq;)Largonaut/Json;
  #295 = Utf8               elements
  #296 = Utf8               jArrayElements
  #297 = Utf8               (Lscala/collection/immutable/Seq;)Largonaut/Json;
  #298 = NameAndType        #296:#297     // jArrayElements:(Lscala/collection/immutable/Seq;)Largonaut/Json;
  #299 = InterfaceMethodref #2.#298       // argonaut/Jsons.jArrayElements:(Lscala/collection/immutable/Seq;)Largonaut/Json;
  #300 = Utf8               Lscala/collection/immutable/Seq;
  #301 = Utf8               (Lscala/collection/immutable/Seq<Largonaut/Json;>;)Largonaut/Json;
  #302 = NameAndType        #259:#35      // jArray:()Lscala/Function1;
  #303 = InterfaceMethodref #2.#302       // argonaut/Jsons.jArray:()Lscala/Function1;
  #304 = Utf8               scala/collection/immutable/Seq
  #305 = Class              #304          // scala/collection/immutable/Seq
  #306 = Utf8               toList
  #307 = Utf8               ()Lscala/collection/immutable/List;
  #308 = NameAndType        #306:#307     // toList:()Lscala/collection/immutable/List;
  #309 = InterfaceMethodref #305.#308     // scala/collection/immutable/Seq.toList:()Lscala/collection/immutable/List;
  #310 = Utf8               jEmptyObject
  #311 = Utf8               jSingleObject$
  #312 = Utf8               (Largonaut/Jsons;Ljava/lang/String;Largonaut/Json;)Largonaut/Json;
  #313 = Utf8               k
  #314 = Utf8               v
  #315 = Utf8               jSingleObject
  #316 = Utf8               (Ljava/lang/String;Largonaut/Json;)Largonaut/Json;
  #317 = NameAndType        #315:#316     // jSingleObject:(Ljava/lang/String;Largonaut/Json;)Largonaut/Json;
  #318 = InterfaceMethodref #2.#317       // argonaut/Jsons.jSingleObject:(Ljava/lang/String;Largonaut/Json;)Largonaut/Json;
  #319 = Utf8               argonaut/JObject
  #320 = Class              #319          // argonaut/JObject
  #321 = Utf8               argonaut/JsonObject$
  #322 = Class              #321          // argonaut/JsonObject$
  #323 = Utf8               Largonaut/JsonObject$;
  #324 = NameAndType        #61:#323      // MODULE$:Largonaut/JsonObject$;
  #325 = Fieldref           #322.#324     // argonaut/JsonObject$.MODULE$:Largonaut/JsonObject$;
  #326 = Utf8               single
  #327 = Utf8               (Ljava/lang/String;Largonaut/Json;)Largonaut/JsonObject;
  #328 = NameAndType        #326:#327     // single:(Ljava/lang/String;Largonaut/Json;)Largonaut/JsonObject;
  #329 = Methodref          #322.#328     // argonaut/JsonObject$.single:(Ljava/lang/String;Largonaut/Json;)Largonaut/JsonObject;
  #330 = Utf8               (Largonaut/JsonObject;)V
  #331 = NameAndType        #49:#330      // "<init>":(Largonaut/JsonObject;)V
  #332 = Methodref          #320.#331     // argonaut/JObject."<init>":(Largonaut/JsonObject;)V
  #333 = Utf8               jObjectAssocList$
  #334 = Utf8               (Largonaut/Jsons;Lscala/collection/immutable/List;)Largonaut/Json;
  #335 = Utf8               x
  #336 = Utf8               jObjectAssocList
  #337 = Utf8               (Lscala/collection/immutable/List;)Largonaut/Json;
  #338 = NameAndType        #336:#337     // jObjectAssocList:(Lscala/collection/immutable/List;)Largonaut/Json;
  #339 = InterfaceMethodref #2.#338       // argonaut/Jsons.jObjectAssocList:(Lscala/collection/immutable/List;)Largonaut/Json;
  #340 = Utf8               Lscala/collection/immutable/List;
  #341 = Utf8               (Lscala/collection/immutable/List<Lscala/Tuple2<Ljava/lang/String;Largonaut/Json;>;>;)Largonaut/Json;
  #342 = Utf8               fromTraversableOnce
  #343 = Utf8               (Lscala/collection/IterableOnce;)Largonaut/JsonObject;
  #344 = NameAndType        #342:#343     // fromTraversableOnce:(Lscala/collection/IterableOnce;)Largonaut/JsonObject;
  #345 = Methodref          #322.#344     // argonaut/JsonObject$.fromTraversableOnce:(Lscala/collection/IterableOnce;)Largonaut/JsonObject;
  #346 = Utf8               jObjectFields$
  #347 = Utf8               jObjectFields
  #348 = NameAndType        #347:#297     // jObjectFields:(Lscala/collection/immutable/Seq;)Largonaut/Json;
  #349 = InterfaceMethodref #2.#348       // argonaut/Jsons.jObjectFields:(Lscala/collection/immutable/Seq;)Largonaut/Json;
  #350 = Utf8               (Lscala/collection/immutable/Seq<Lscala/Tuple2<Ljava/lang/String;Largonaut/Json;>;>;)Largonaut/Json;
  #351 = Utf8               $anonfun$jBool$1
  #352 = Utf8               (Z)Largonaut/JBool;
  #353 = Utf8               x$29
  #354 = Utf8               argonaut/JBool
  #355 = Class              #354          // argonaut/JBool
  #356 = Utf8               (Z)V
  #357 = NameAndType        #49:#356      // "<init>":(Z)V
  #358 = Methodref          #355.#357     // argonaut/JBool."<init>":(Z)V
  #359 = Utf8               Z
  #360 = Utf8               n$1
  #361 = Utf8               toString
  #362 = Utf8               ()Ljava/lang/String;
  #363 = NameAndType        #361:#362     // toString:()Ljava/lang/String;
  #364 = Methodref          #4.#363       // java/lang/Object.toString:()Ljava/lang/String;
  #365 = Utf8               x$30
  #366 = Utf8               argonaut/JsonNumber
  #367 = Class              #366          // argonaut/JsonNumber
  #368 = Utf8               asJson
  #369 = NameAndType        #368:#33      // asJson:()Largonaut/Json;
  #370 = Methodref          #367.#369     // argonaut/JsonNumber.asJson:()Largonaut/Json;
  #371 = Utf8               x$31
  #372 = Utf8               x$32
  #373 = Utf8               x$33
  #374 = Utf8               $anonfun$jString$1
  #375 = Utf8               (Ljava/lang/String;)Largonaut/JString;
  #376 = Utf8               x$34
  #377 = Utf8               argonaut/JString
  #378 = Class              #377          // argonaut/JString
  #379 = Utf8               (Ljava/lang/String;)V
  #380 = NameAndType        #49:#379      // "<init>":(Ljava/lang/String;)V
  #381 = Methodref          #378.#380     // argonaut/JString."<init>":(Ljava/lang/String;)V
  #382 = Utf8               $anonfun$jArray$1
  #383 = Utf8               (Lscala/collection/immutable/List;)Largonaut/JArray;
  #384 = Utf8               x$35
  #385 = Utf8               $anonfun$jObject$1
  #386 = Utf8               (Largonaut/JsonObject;)Largonaut/JObject;
  #387 = Utf8               x$36
  #388 = Utf8               Largonaut/JsonObject;
  #389 = Utf8               $init$
  #390 = Utf8               (Largonaut/Jsons;)V
  #391 = Utf8               argonaut/JNull$
  #392 = Class              #391          // argonaut/JNull$
  #393 = Utf8               Largonaut/JNull$;
  #394 = NameAndType        #61:#393      // MODULE$:Largonaut/JNull$;
  #395 = Fieldref           #392.#394     // argonaut/JNull$.MODULE$:Largonaut/JNull$;
  #396 = NameAndType        #14:#15       // argonaut$Jsons$_setter_$jNull_$eq:(Largonaut/Json;)V
  #397 = InterfaceMethodref #2.#396       // argonaut/Jsons.argonaut$Jsons$_setter_$jNull_$eq:(Largonaut/Json;)V
  #398 = Utf8               $anonfun$jBool$1$adapted
  #399 = Utf8               (Ljava/lang/Object;)Largonaut/JBool;
  #400 = NameAndType        #398:#399     // $anonfun$jBool$1$adapted:(Ljava/lang/Object;)Largonaut/JBool;
  #401 = InterfaceMethodref #2.#400       // argonaut/Jsons.$anonfun$jBool$1$adapted:(Ljava/lang/Object;)Largonaut/JBool;
  #402 = MethodHandle       6:#401        // REF_invokeStatic argonaut/Jsons.$anonfun$jBool$1$adapted:(Ljava/lang/Object;)Largonaut/JBool;
  #403 = MethodType         #399          //  (Ljava/lang/Object;)Largonaut/JBool;
  #404 = InvokeDynamic      #7:#135       // #7:apply:()Lscala/Function1;
  #405 = NameAndType        #17:#18       // argonaut$Jsons$_setter_$jBool_$eq:(Lscala/Function1;)V
  #406 = InterfaceMethodref #2.#405       // argonaut/Jsons.argonaut$Jsons$_setter_$jBool_$eq:(Lscala/Function1;)V
  #407 = NameAndType        #374:#375     // $anonfun$jString$1:(Ljava/lang/String;)Largonaut/JString;
  #408 = InterfaceMethodref #2.#407       // argonaut/Jsons.$anonfun$jString$1:(Ljava/lang/String;)Largonaut/JString;
  #409 = MethodHandle       6:#408        // REF_invokeStatic argonaut/Jsons.$anonfun$jString$1:(Ljava/lang/String;)Largonaut/JString;
  #410 = MethodType         #375          //  (Ljava/lang/String;)Largonaut/JString;
  #411 = InvokeDynamic      #8:#135       // #8:apply:()Lscala/Function1;
  #412 = NameAndType        #20:#18       // argonaut$Jsons$_setter_$jString_$eq:(Lscala/Function1;)V
  #413 = InterfaceMethodref #2.#412       // argonaut/Jsons.argonaut$Jsons$_setter_$jString_$eq:(Lscala/Function1;)V
  #414 = NameAndType        #382:#383     // $anonfun$jArray$1:(Lscala/collection/immutable/List;)Largonaut/JArray;
  #415 = InterfaceMethodref #2.#414       // argonaut/Jsons.$anonfun$jArray$1:(Lscala/collection/immutable/List;)Largonaut/JArray;
  #416 = MethodHandle       6:#415        // REF_invokeStatic argonaut/Jsons.$anonfun$jArray$1:(Lscala/collection/immutable/List;)Largonaut/JArray;
  #417 = MethodType         #383          //  (Lscala/collection/immutable/List;)Largonaut/JArray;
  #418 = InvokeDynamic      #9:#135       // #9:apply:()Lscala/Function1;
  #419 = NameAndType        #22:#18       // argonaut$Jsons$_setter_$jArray_$eq:(Lscala/Function1;)V
  #420 = InterfaceMethodref #2.#419       // argonaut/Jsons.argonaut$Jsons$_setter_$jArray_$eq:(Lscala/Function1;)V
  #421 = NameAndType        #385:#386     // $anonfun$jObject$1:(Largonaut/JsonObject;)Largonaut/JObject;
  #422 = InterfaceMethodref #2.#421       // argonaut/Jsons.$anonfun$jObject$1:(Largonaut/JsonObject;)Largonaut/JObject;
  #423 = MethodHandle       6:#422        // REF_invokeStatic argonaut/Jsons.$anonfun$jObject$1:(Largonaut/JsonObject;)Largonaut/JObject;
  #424 = MethodType         #386          //  (Largonaut/JsonObject;)Largonaut/JObject;
  #425 = InvokeDynamic      #10:#135      // #10:apply:()Lscala/Function1;
  #426 = NameAndType        #24:#18       // argonaut$Jsons$_setter_$jObject_$eq:(Lscala/Function1;)V
  #427 = InterfaceMethodref #2.#426       // argonaut/Jsons.argonaut$Jsons$_setter_$jObject_$eq:(Lscala/Function1;)V
  #428 = NameAndType        #26:#15       // argonaut$Jsons$_setter_$jTrue_$eq:(Largonaut/Json;)V
  #429 = InterfaceMethodref #2.#428       // argonaut/Jsons.argonaut$Jsons$_setter_$jTrue_$eq:(Largonaut/Json;)V
  #430 = NameAndType        #27:#15       // argonaut$Jsons$_setter_$jFalse_$eq:(Largonaut/Json;)V
  #431 = InterfaceMethodref #2.#430       // argonaut/Jsons.argonaut$Jsons$_setter_$jFalse_$eq:(Largonaut/Json;)V
  #432 = Utf8               argonaut/JsonLong
  #433 = Class              #432          // argonaut/JsonLong
  #434 = Utf8               (J)V
  #435 = NameAndType        #49:#434      // "<init>":(J)V
  #436 = Methodref          #433.#435     // argonaut/JsonLong."<init>":(J)V
  #437 = NameAndType        #28:#15       // argonaut$Jsons$_setter_$jZero_$eq:(Largonaut/Json;)V
  #438 = InterfaceMethodref #2.#437       // argonaut/Jsons.argonaut$Jsons$_setter_$jZero_$eq:(Largonaut/Json;)V
  #439 = Utf8
  #440 = String             #439          //
  #441 = NameAndType        #29:#15       // argonaut$Jsons$_setter_$jEmptyString_$eq:(Largonaut/Json;)V
  #442 = InterfaceMethodref #2.#441       // argonaut/Jsons.argonaut$Jsons$_setter_$jEmptyString_$eq:(Largonaut/Json;)V
  #443 = NameAndType        #30:#15       // argonaut$Jsons$_setter_$jEmptyArray_$eq:(Largonaut/Json;)V
  #444 = InterfaceMethodref #2.#443       // argonaut/Jsons.argonaut$Jsons$_setter_$jEmptyArray_$eq:(Largonaut/Json;)V
  #445 = Utf8               empty
  #446 = Utf8               ()Largonaut/JsonObject;
  #447 = NameAndType        #445:#446     // empty:()Largonaut/JsonObject;
  #448 = Methodref          #322.#447     // argonaut/JsonObject$.empty:()Largonaut/JsonObject;
  #449 = NameAndType        #31:#15       // argonaut$Jsons$_setter_$jEmptyObject_$eq:(Largonaut/Json;)V
  #450 = InterfaceMethodref #2.#449       // argonaut/Jsons.argonaut$Jsons$_setter_$jEmptyObject_$eq:(Largonaut/Json;)V
  #451 = Utf8               unboxToBoolean
  #452 = NameAndType        #451:#221     // unboxToBoolean:(Ljava/lang/Object;)Z
  #453 = Methodref          #66.#452      // scala/runtime/BoxesRunTime.unboxToBoolean:(Ljava/lang/Object;)Z
  #454 = NameAndType        #351:#352     // $anonfun$jBool$1:(Z)Largonaut/JBool;
  #455 = InterfaceMethodref #2.#454       // argonaut/Jsons.$anonfun$jBool$1:(Z)Largonaut/JBool;
  #456 = Utf8               Ljava/lang/Object;
  #457 = Utf8               $deserializeLambda$
  #458 = Utf8               (Ljava/lang/invoke/SerializedLambda;)Ljava/lang/Object;
  #459 = Utf8               scala/runtime/LambdaDeserialize
  #460 = Class              #459          // scala/runtime/LambdaDeserialize
  #461 = Utf8               bootstrap
  #462 = Utf8               (Ljava/lang/invoke/MethodHandles$Lookup;Ljava/lang/String;Ljava/lang/invoke/MethodType;[Ljava/lang/invoke/MethodHandle;)Ljava/lang/invoke/CallSite;
  #463 = NameAndType        #461:#462     // bootstrap:(Ljava/lang/invoke/MethodHandles$Lookup;Ljava/lang/String;Ljava/lang/invoke/MethodType;[Ljava/lang/invoke/MethodHandle;)Ljava/lang/invoke/CallSite;
  #464 = Methodref          #460.#463     // scala/runtime/LambdaDeserialize.bootstrap:(Ljava/lang/invoke/MethodHandles$Lookup;Ljava/lang/String;Ljava/lang/invoke/MethodType;[Ljava/lang/invoke/MethodHandle;)Ljava/lang/invoke/CallSite;
  #465 = MethodHandle       6:#464        // REF_invokeStatic scala/runtime/LambdaDeserialize.bootstrap:(Ljava/lang/invoke/MethodHandles$Lookup;Ljava/lang/String;Ljava/lang/invoke/MethodType;[Ljava/lang/invoke/MethodHandle;)Ljava/lang/invoke/CallSite;
  #466 = Utf8               lambdaDeserialize
  #467 = NameAndType        #466:#458     // lambdaDeserialize:(Ljava/lang/invoke/SerializedLambda;)Ljava/lang/Object;
  #468 = InvokeDynamic      #11:#467      // #11:lambdaDeserialize:(Ljava/lang/invoke/SerializedLambda;)Ljava/lang/Object;
  #469 = Utf8               MethodParameters
  #470 = Utf8               Signature
  #471 = Utf8               Code
  #472 = Utf8               LineNumberTable
  #473 = Utf8               LocalVariableTable
  #474 = Utf8               StackMapTable
  #475 = Utf8               InnerClasses
  #476 = Utf8               SourceFile
  #477 = Utf8               RuntimeVisibleAnnotations
  #478 = Utf8               BootstrapMethods
  #479 = Utf8               ScalaInlineInfo
  #480 = Utf8               ScalaSig
{
  public abstract void argonaut$Jsons$_setter_$jNull_$eq(argonaut.Json);
    descriptor: (Largonaut/Json;)V
    flags: (0x0401) ACC_PUBLIC, ACC_ABSTRACT
    MethodParameters:
      Name                           Flags
      x$1                            final

  public abstract void argonaut$Jsons$_setter_$jBool_$eq(scala.Function1<java.lang.Object, argonaut.Json>);
    descriptor: (Lscala/Function1;)V
    flags: (0x0401) ACC_PUBLIC, ACC_ABSTRACT
    Signature: #19                          // (Lscala/Function1<Ljava/lang/Object;Largonaut/Json;>;)V
    MethodParameters:
      Name                           Flags
      x$1                            final

  public abstract void argonaut$Jsons$_setter_$jString_$eq(scala.Function1<java.lang.String, argonaut.Json>);
    descriptor: (Lscala/Function1;)V
    flags: (0x0401) ACC_PUBLIC, ACC_ABSTRACT
    Signature: #21                          // (Lscala/Function1<Ljava/lang/String;Largonaut/Json;>;)V
    MethodParameters:
      Name                           Flags
      x$1                            final

  public abstract void argonaut$Jsons$_setter_$jArray_$eq(scala.Function1<scala.collection.immutable.List<argonaut.Json>, argonaut.Json>);
    descriptor: (Lscala/Function1;)V
    flags: (0x0401) ACC_PUBLIC, ACC_ABSTRACT
    Signature: #23                          // (Lscala/Function1<Lscala/collection/immutable/List<Largonaut/Json;>;Largonaut/Json;>;)V
    MethodParameters:
      Name                           Flags
      x$1                            final

  public abstract void argonaut$Jsons$_setter_$jObject_$eq(scala.Function1<argonaut.JsonObject, argonaut.Json>);
    descriptor: (Lscala/Function1;)V
    flags: (0x0401) ACC_PUBLIC, ACC_ABSTRACT
    Signature: #25                          // (Lscala/Function1<Largonaut/JsonObject;Largonaut/Json;>;)V
    MethodParameters:
      Name                           Flags
      x$1                            final

  public abstract void argonaut$Jsons$_setter_$jTrue_$eq(argonaut.Json);
    descriptor: (Largonaut/Json;)V
    flags: (0x0401) ACC_PUBLIC, ACC_ABSTRACT
    MethodParameters:
      Name                           Flags
      x$1                            final

  public abstract void argonaut$Jsons$_setter_$jFalse_$eq(argonaut.Json);
    descriptor: (Largonaut/Json;)V
    flags: (0x0401) ACC_PUBLIC, ACC_ABSTRACT
    MethodParameters:
      Name                           Flags
      x$1                            final

  public abstract void argonaut$Jsons$_setter_$jZero_$eq(argonaut.Json);
    descriptor: (Largonaut/Json;)V
    flags: (0x0401) ACC_PUBLIC, ACC_ABSTRACT
    MethodParameters:
      Name                           Flags
      x$1                            final

  public abstract void argonaut$Jsons$_setter_$jEmptyString_$eq(argonaut.Json);
    descriptor: (Largonaut/Json;)V
    flags: (0x0401) ACC_PUBLIC, ACC_ABSTRACT
    MethodParameters:
      Name                           Flags
      x$1                            final

  public abstract void argonaut$Jsons$_setter_$jEmptyArray_$eq(argonaut.Json);
    descriptor: (Largonaut/Json;)V
    flags: (0x0401) ACC_PUBLIC, ACC_ABSTRACT
    MethodParameters:
      Name                           Flags
      x$1                            final

  public abstract void argonaut$Jsons$_setter_$jEmptyObject_$eq(argonaut.Json);
    descriptor: (Largonaut/Json;)V
    flags: (0x0401) ACC_PUBLIC, ACC_ABSTRACT
    MethodParameters:
      Name                           Flags
      x$1                            final

  public abstract argonaut.Json jNull();
    descriptor: ()Largonaut/Json;
    flags: (0x0401) ACC_PUBLIC, ACC_ABSTRACT

  public abstract scala.Function1<java.lang.Object, argonaut.Json> jBool();
    descriptor: ()Lscala/Function1;
    flags: (0x0401) ACC_PUBLIC, ACC_ABSTRACT
    Signature: #36                          // ()Lscala/Function1<Ljava/lang/Object;Largonaut/Json;>;

  public static argonaut.Json jNumber$(argonaut.Jsons, argonaut.JsonNumber);
    descriptor: (Largonaut/Jsons;Largonaut/JsonNumber;)Largonaut/Json;
    flags: (0x1009) ACC_PUBLIC, ACC_STATIC, ACC_SYNTHETIC
    Code:
      stack=2, locals=2, args_size=2
         0: aload_0
         1: aload_1
         2: invokespecial #44                 // InterfaceMethod jNumber:(Largonaut/JsonNumber;)Largonaut/Json;
         5: areturn
      LineNumberTable:
        line 527: 0
      LocalVariableTable:
        Start  Length  Slot  Name   Signature
            0       6     0 $this   Largonaut/Jsons;
            0       6     1     n   Largonaut/JsonNumber;
    MethodParameters:
      Name                           Flags
      $this                          final synthetic
      n                              final

  public default argonaut.Json jNumber(argonaut.JsonNumber);
    descriptor: (Largonaut/JsonNumber;)Largonaut/Json;
    flags: (0x0001) ACC_PUBLIC
    Code:
      stack=3, locals=2, args_size=2
         0: new           #48                 // class argonaut/JNumber
         3: dup
         4: aload_1
         5: invokespecial #52                 // Method argonaut/JNumber."<init>":(Largonaut/JsonNumber;)V
         8: areturn
      LineNumberTable:
        line 527: 0
      LocalVariableTable:
        Start  Length  Slot  Name   Signature
            0       9     0  this   Largonaut/Jsons;
            0       9     1     n   Largonaut/JsonNumber;
    MethodParameters:
      Name                           Flags
      n                              final

  public static argonaut.Json jNumber$(argonaut.Jsons, int);
    descriptor: (Largonaut/Jsons;I)Largonaut/Json;
    flags: (0x1009) ACC_PUBLIC, ACC_STATIC, ACC_SYNTHETIC
    Code:
      stack=2, locals=2, args_size=2
         0: aload_0
         1: iload_1
         2: invokespecial #57                 // InterfaceMethod jNumber:(I)Largonaut/Json;
         5: areturn
      LineNumberTable:
        line 532: 0
      LocalVariableTable:
        Start  Length  Slot  Name   Signature
            0       6     0 $this   Largonaut/Jsons;
            0       6     1     n   I
    MethodParameters:
      Name                           Flags
      $this                          final synthetic
      n                              final

  public default argonaut.Json jNumber(int);
    descriptor: (I)Largonaut/Json;
    flags: (0x0001) ACC_PUBLIC
    Code:
      stack=5, locals=2, args_size=2
         0: new           #48                 // class argonaut/JNumber
         3: dup
         4: getstatic     #64                 // Field argonaut/JsonIdentity$.MODULE$:Largonaut/JsonIdentity$;
         7: getstatic     #64                 // Field argonaut/JsonIdentity$.MODULE$:Largonaut/JsonIdentity$;
        10: iload_1
        11: invokestatic  #70                 // Method scala/runtime/BoxesRunTime.boxToInteger:(I)Ljava/lang/Integer;
        14: invokevirtual #74                 // Method argonaut/JsonIdentity$.ToJsonIdentity:(Ljava/lang/Object;)Ljava/lang/Object;
        17: getstatic     #79                 // Field argonaut/EncodeJsonNumber$.MODULE$:Largonaut/EncodeJsonNumber$;
        20: invokevirtual #83                 // Method argonaut/EncodeJsonNumber$.encodeJsonNumberInt:()Largonaut/EncodeJsonNumber;
        23: invokevirtual #87                 // Method argonaut/JsonIdentity$.asJsonNumber$extension:(Ljava/lang/Object;Largonaut/EncodeJsonNumber;)Largonaut/JsonNumber;
        26: invokespecial #52                 // Method argonaut/JNumber."<init>":(Largonaut/JsonNumber;)V
        29: areturn
      LineNumberTable:
        line 532: 0
      LocalVariableTable:
        Start  Length  Slot  Name   Signature
            0      30     0  this   Largonaut/Jsons;
            0      30     1     n   I
    MethodParameters:
      Name                           Flags
      n                              final

  public static argonaut.Json jNumber$(argonaut.Jsons, long);
    descriptor: (Largonaut/Jsons;J)Largonaut/Json;
    flags: (0x1009) ACC_PUBLIC, ACC_STATIC, ACC_SYNTHETIC
    Code:
      stack=3, locals=3, args_size=2
         0: aload_0
         1: lload_1
         2: invokespecial #91                 // InterfaceMethod jNumber:(J)Largonaut/Json;
         5: areturn
      LineNumberTable:
        line 537: 0
      LocalVariableTable:
        Start  Length  Slot  Name   Signature
            0       6     0 $this   Largonaut/Jsons;
            0       6     1     n   J
    MethodParameters:
      Name                           Flags
      $this                          final synthetic
      n                              final

  public default argonaut.Json jNumber(long);
    descriptor: (J)Largonaut/Json;
    flags: (0x0001) ACC_PUBLIC
    Code:
      stack=6, locals=3, args_size=2
         0: new           #48                 // class argonaut/JNumber
         3: dup
         4: getstatic     #64                 // Field argonaut/JsonIdentity$.MODULE$:Largonaut/JsonIdentity$;
         7: getstatic     #64                 // Field argonaut/JsonIdentity$.MODULE$:Largonaut/JsonIdentity$;
        10: lload_1
        11: invokestatic  #96                 // Method scala/runtime/BoxesRunTime.boxToLong:(J)Ljava/lang/Long;
        14: invokevirtual #74                 // Method argonaut/JsonIdentity$.ToJsonIdentity:(Ljava/lang/Object;)Ljava/lang/Object;
        17: getstatic     #79                 // Field argonaut/EncodeJsonNumber$.MODULE$:Largonaut/EncodeJsonNumber$;
        20: invokevirtual #99                 // Method argonaut/EncodeJsonNumber$.encodeJsonNumberLong:()Largonaut/EncodeJsonNumber;
        23: invokevirtual #87                 // Method argonaut/JsonIdentity$.asJsonNumber$extension:(Ljava/lang/Object;Largonaut/EncodeJsonNumber;)Largonaut/JsonNumber;
        26: invokespecial #52                 // Method argonaut/JNumber."<init>":(Largonaut/JsonNumber;)V
        29: areturn
      LineNumberTable:
        line 537: 0
      LocalVariableTable:
        Start  Length  Slot  Name   Signature
            0      30     0  this   Largonaut/Jsons;
            0      30     1     n   J
    MethodParameters:
      Name                           Flags
      n                              final

  public static scala.Option jNumber$(argonaut.Jsons, double);
    descriptor: (Largonaut/Jsons;D)Lscala/Option;
    flags: (0x1009) ACC_PUBLIC, ACC_STATIC, ACC_SYNTHETIC
    Code:
      stack=3, locals=3, args_size=2
         0: aload_0
         1: dload_1
         2: invokespecial #103                // InterfaceMethod jNumber:(D)Lscala/Option;
         5: areturn
      LineNumberTable:
        line 544: 0
      LocalVariableTable:
        Start  Length  Slot  Name   Signature
            0       6     0 $this   Largonaut/Jsons;
            0       6     1     n   D
    MethodParameters:
      Name                           Flags
      $this                          final synthetic
      n                              final

  public default scala.Option<argonaut.Json> jNumber(double);
    descriptor: (D)Lscala/Option;
    flags: (0x0001) ACC_PUBLIC
    Code:
      stack=4, locals=3, args_size=2
         0: getstatic     #64                 // Field argonaut/JsonIdentity$.MODULE$:Largonaut/JsonIdentity$;
         3: getstatic     #64                 // Field argonaut/JsonIdentity$.MODULE$:Largonaut/JsonIdentity$;
         6: dload_1
         7: invokestatic  #109                // Method scala/runtime/BoxesRunTime.boxToDouble:(D)Ljava/lang/Double;
        10: invokevirtual #74                 // Method argonaut/JsonIdentity$.ToJsonIdentity:(Ljava/lang/Object;)Ljava/lang/Object;
        13: getstatic     #79                 // Field argonaut/EncodeJsonNumber$.MODULE$:Largonaut/EncodeJsonNumber$;
        16: invokevirtual #113                // Method argonaut/EncodeJsonNumber$.encodeJsonNumberDouble:()Largonaut/EncodePossibleJsonNumber;
        19: invokevirtual #117                // Method argonaut/JsonIdentity$.asPossibleJsonNumber$extension:(Ljava/lang/Object;Largonaut/EncodePossibleJsonNumber;)Lscala/Option;
        22: invokedynamic #136,  0            // InvokeDynamic #0:apply:()Lscala/Function1;
        27: invokevirtual #142                // Method scala/Option.map:(Lscala/Function1;)Lscala/Option;
        30: areturn
      LineNumberTable:
        line 544: 0
      LocalVariableTable:
        Start  Length  Slot  Name   Signature
            0      31     0  this   Largonaut/Jsons;
            0      31     1     n   D
    Signature: #105                         // (D)Lscala/Option<Largonaut/Json;>;
    MethodParameters:
      Name                           Flags
      n                              final

  public static argonaut.Json jNumberOrNull$(argonaut.Jsons, double);
    descriptor: (Largonaut/Jsons;D)Largonaut/Json;
    flags: (0x1009) ACC_PUBLIC, ACC_STATIC, ACC_SYNTHETIC
    Code:
      stack=3, locals=3, args_size=2
         0: aload_0
         1: dload_1
         2: invokespecial #148                // InterfaceMethod jNumberOrNull:(D)Largonaut/Json;
         5: areturn
      LineNumberTable:
        line 552: 0
      LocalVariableTable:
        Start  Length  Slot  Name   Signature
            0       6     0 $this   Largonaut/Jsons;
            0       6     1     n   D
    MethodParameters:
      Name                           Flags
      $this                          final synthetic
      n                              final

  public default argonaut.Json jNumberOrNull(double);
    descriptor: (D)Largonaut/Json;
    flags: (0x0001) ACC_PUBLIC
    Code:
      stack=3, locals=3, args_size=2
         0: aload_0
         1: dload_1
         2: invokeinterface #103,  3          // InterfaceMethod jNumber:(D)Lscala/Option;
         7: aload_0
         8: invokedynamic #159,  0            // InvokeDynamic #1:apply:(Largonaut/Jsons;)Lscala/Function0;
        13: invokevirtual #163                // Method scala/Option.getOrElse:(Lscala/Function0;)Ljava/lang/Object;
        16: checkcast     #165                // class argonaut/Json
        19: areturn
      LineNumberTable:
        line 552: 0
      LocalVariableTable:
        Start  Length  Slot  Name   Signature
            0      20     0  this   Largonaut/Jsons;
            0      20     1     n   D
    MethodParameters:
      Name                           Flags
      n                              final

  public static argonaut.Json jNumberOrString$(argonaut.Jsons, double);
    descriptor: (Largonaut/Jsons;D)Largonaut/Json;
    flags: (0x1009) ACC_PUBLIC, ACC_STATIC, ACC_SYNTHETIC
    Code:
      stack=3, locals=3, args_size=2
         0: aload_0
         1: dload_1
         2: invokespecial #169                // InterfaceMethod jNumberOrString:(D)Largonaut/Json;
         5: areturn
      LineNumberTable:
        line 563: 0
      LocalVariableTable:
        Start  Length  Slot  Name   Signature
            0       6     0 $this   Largonaut/Jsons;
            0       6     1     n   D
    MethodParameters:
      Name                           Flags
      $this                          final synthetic
      n                              final

  public default argonaut.Json jNumberOrString(double);
    descriptor: (D)Largonaut/Json;
    flags: (0x0001) ACC_PUBLIC
    Code:
      stack=4, locals=3, args_size=2
         0: getstatic     #64                 // Field argonaut/JsonIdentity$.MODULE$:Largonaut/JsonIdentity$;
         3: getstatic     #64                 // Field argonaut/JsonIdentity$.MODULE$:Largonaut/JsonIdentity$;
         6: dload_1
         7: invokestatic  #109                // Method scala/runtime/BoxesRunTime.boxToDouble:(D)Ljava/lang/Double;
        10: invokevirtual #74                 // Method argonaut/JsonIdentity$.ToJsonIdentity:(Ljava/lang/Object;)Ljava/lang/Object;
        13: getstatic     #79                 // Field argonaut/EncodeJsonNumber$.MODULE$:Largonaut/EncodeJsonNumber$;
        16: invokevirtual #113                // Method argonaut/EncodeJsonNumber$.encodeJsonNumberDouble:()Largonaut/EncodePossibleJsonNumber;
        19: invokevirtual #117                // Method argonaut/JsonIdentity$.asPossibleJsonNumber$extension:(Ljava/lang/Object;Largonaut/EncodePossibleJsonNumber;)Lscala/Option;
        22: aload_0
        23: dload_1
        24: invokedynamic #176,  0            // InvokeDynamic #2:apply:(Largonaut/Jsons;D)Lscala/Function0;
        29: invokedynamic #182,  0            // InvokeDynamic #3:apply:()Lscala/Function1;
        34: invokevirtual #186                // Method scala/Option.fold:(Lscala/Function0;Lscala/Function1;)Ljava/lang/Object;
        37: checkcast     #165                // class argonaut/Json
        40: areturn
      LineNumberTable:
        line 563: 0
      LocalVariableTable:
        Start  Length  Slot  Name   Signature
            0      41     0  this   Largonaut/Jsons;
            0      41     1     n   D
    MethodParameters:
      Name                           Flags
      n                              final

  public static argonaut.Json jNumber$(argonaut.Jsons, scala.math.BigDecimal);
    descriptor: (Largonaut/Jsons;Lscala/math/BigDecimal;)Largonaut/Json;
    flags: (0x1009) ACC_PUBLIC, ACC_STATIC, ACC_SYNTHETIC
    Code:
      stack=2, locals=2, args_size=2
         0: aload_0
         1: aload_1
         2: invokespecial #190                // InterfaceMethod jNumber:(Lscala/math/BigDecimal;)Largonaut/Json;
         5: areturn
      LineNumberTable:
        line 568: 0
      LocalVariableTable:
        Start  Length  Slot  Name   Signature
            0       6     0 $this   Largonaut/Jsons;
            0       6     1     n   Lscala/math/BigDecimal;
    MethodParameters:
      Name                           Flags
      $this                          final synthetic
      n                              final

  public default argonaut.Json jNumber(scala.math.BigDecimal);
    descriptor: (Lscala/math/BigDecimal;)Largonaut/Json;
    flags: (0x0001) ACC_PUBLIC
    Code:
      stack=5, locals=2, args_size=2
         0: new           #48                 // class argonaut/JNumber
         3: dup
         4: new           #193                // class argonaut/JsonBigDecimal
         7: dup
         8: aload_1
         9: invokespecial #196                // Method argonaut/JsonBigDecimal."<init>":(Lscala/math/BigDecimal;)V
        12: invokespecial #52                 // Method argonaut/JNumber."<init>":(Largonaut/JsonNumber;)V
        15: areturn
      LineNumberTable:
        line 568: 0
      LocalVariableTable:
        Start  Length  Slot  Name   Signature
            0      16     0  this   Largonaut/Jsons;
            0      16     1     n   Lscala/math/BigDecimal;
    MethodParameters:
      Name                           Flags
      n                              final

  public static scala.Option jNumber$(argonaut.Jsons, java.lang.String);
    descriptor: (Largonaut/Jsons;Ljava/lang/String;)Lscala/Option;
    flags: (0x1009) ACC_PUBLIC, ACC_STATIC, ACC_SYNTHETIC
    Code:
      stack=2, locals=2, args_size=2
         0: aload_0
         1: aload_1
         2: invokespecial #200                // InterfaceMethod jNumber:(Ljava/lang/String;)Lscala/Option;
         5: areturn
      LineNumberTable:
        line 573: 0
      LocalVariableTable:
        Start  Length  Slot  Name   Signature
            0       6     0 $this   Largonaut/Jsons;
            0       6     1     n   Ljava/lang/String;
    MethodParameters:
      Name                           Flags
      $this                          final synthetic
      n                              final

  public default scala.Option<argonaut.Json> jNumber(java.lang.String);
    descriptor: (Ljava/lang/String;)Lscala/Option;
    flags: (0x0001) ACC_PUBLIC
    Code:
      stack=2, locals=2, args_size=2
         0: getstatic     #207                // Field argonaut/JsonNumber$.MODULE$:Largonaut/JsonNumber$;
         3: aload_1
         4: invokevirtual #210                // Method argonaut/JsonNumber$.fromString:(Ljava/lang/String;)Lscala/Option;
         7: invokedynamic #215,  0            // InvokeDynamic #4:apply:()Lscala/Function1;
        12: invokevirtual #142                // Method scala/Option.map:(Lscala/Function1;)Lscala/Option;
        15: areturn
      LineNumberTable:
        line 573: 0
      LocalVariableTable:
        Start  Length  Slot  Name   Signature
            0      16     0  this   Largonaut/Jsons;
            0      16     1     n   Ljava/lang/String;
    Signature: #202                         // (Ljava/lang/String;)Lscala/Option<Largonaut/Json;>;
    MethodParameters:
      Name                           Flags
      n                              final

  public static scala.Option jNumberOrNull$(argonaut.Jsons, java.lang.String);
    descriptor: (Largonaut/Jsons;Ljava/lang/String;)Lscala/Option;
    flags: (0x1009) ACC_PUBLIC, ACC_STATIC, ACC_SYNTHETIC
    Code:
      stack=2, locals=2, args_size=2
         0: aload_0
         1: aload_1
         2: invokespecial #217                // InterfaceMethod jNumberOrNull:(Ljava/lang/String;)Lscala/Option;
         5: areturn
      LineNumberTable:
        line 581: 0
      LocalVariableTable:
        Start  Length  Slot  Name   Signature
            0       6     0 $this   Largonaut/Jsons;
            0       6     1     n   Ljava/lang/String;
    MethodParameters:
      Name                           Flags
      $this                          final synthetic
      n                              final

  public default scala.Option<argonaut.Json> jNumberOrNull(java.lang.String);
    descriptor: (Ljava/lang/String;)Lscala/Option;
    flags: (0x0001) ACC_PUBLIC
    Code:
      stack=3, locals=5, args_size=2
         0: aload_1
         1: astore        4
         3: ldc           #219                // String NaN
         5: aload         4
         7: invokevirtual #223                // Method java/lang/Object.equals:(Ljava/lang/Object;)Z
        10: ifeq          18
        13: iconst_1
        14: istore_3
        15: goto          80
        18: goto          21
        21: ldc           #225                // String Infinity
        23: aload         4
        25: invokevirtual #223                // Method java/lang/Object.equals:(Ljava/lang/Object;)Z
        28: ifeq          36
        31: iconst_1
        32: istore_3
        33: goto          80
        36: goto          39
        39: ldc           #227                // String +Infinity
        41: aload         4
        43: invokevirtual #223                // Method java/lang/Object.equals:(Ljava/lang/Object;)Z
        46: ifeq          54
        49: iconst_1
        50: istore_3
        51: goto          80
        54: goto          57
        57: ldc           #229                // String -Infinity
        59: aload         4
        61: invokevirtual #223                // Method java/lang/Object.equals:(Ljava/lang/Object;)Z
        64: ifeq          72
        67: iconst_1
        68: istore_3
        69: goto          80
        72: goto          75
        75: iconst_0
        76: istore_3
        77: goto          80
        80: iload_3
        81: ifeq          101
        84: new           #231                // class scala/Some
        87: dup
        88: aload_0
        89: invokeinterface #233,  1          // InterfaceMethod jNull:()Largonaut/Json;
        94: invokespecial #236                // Method scala/Some."<init>":(Ljava/lang/Object;)V
        97: astore_2
        98: goto          123
       101: goto          104
       104: getstatic     #207                // Field argonaut/JsonNumber$.MODULE$:Largonaut/JsonNumber$;
       107: aload_1
       108: invokevirtual #210                // Method argonaut/JsonNumber$.fromString:(Ljava/lang/String;)Lscala/Option;
       111: invokedynamic #241,  0            // InvokeDynamic #5:apply:()Lscala/Function1;
       116: invokevirtual #142                // Method scala/Option.map:(Lscala/Function1;)Lscala/Option;
       119: astore_2
       120: goto          123
       123: aload_2
       124: areturn
      StackMapTable: number_of_entries = 12
        frame_type = 254 /* append */
          offset_delta = 18
          locals = [ top, top, class java/lang/String ]
        frame_type = 2 /* same */
        frame_type = 14 /* same */
        frame_type = 2 /* same */
        frame_type = 14 /* same */
        frame_type = 2 /* same */
        frame_type = 14 /* same */
        frame_type = 2 /* same */
        frame_type = 255 /* full_frame */
          offset_delta = 4
          locals = [ class argonaut/Jsons, class java/lang/String, top, int, class java/lang/String ]
          stack = []
        frame_type = 20 /* same */
        frame_type = 2 /* same */
        frame_type = 255 /* full_frame */
          offset_delta = 18
          locals = [ class argonaut/Jsons, class java/lang/String, class scala/Option, int, class java/lang/String ]
          stack = []
      LineNumberTable:
        line 581: 0
        line 582: 3
        line 583: 104
        line 581: 123
      LocalVariableTable:
        Start  Length  Slot  Name   Signature
            0     125     0  this   Largonaut/Jsons;
            0     125     1     n   Ljava/lang/String;
    Signature: #202                         // (Ljava/lang/String;)Lscala/Option<Largonaut/Json;>;
    MethodParameters:
      Name                           Flags
      n                              final

  public static scala.Option jNumberOrString$(argonaut.Jsons, java.lang.String);
    descriptor: (Largonaut/Jsons;Ljava/lang/String;)Lscala/Option;
    flags: (0x1009) ACC_PUBLIC, ACC_STATIC, ACC_SYNTHETIC
    Code:
      stack=2, locals=2, args_size=2
         0: aload_0
         1: aload_1
         2: invokespecial #245                // InterfaceMethod jNumberOrString:(Ljava/lang/String;)Lscala/Option;
         5: areturn
      LineNumberTable:
        line 595: 0
      LocalVariableTable:
        Start  Length  Slot  Name   Signature
            0       6     0 $this   Largonaut/Jsons;
            0       6     1     n   Ljava/lang/String;
    MethodParameters:
      Name                           Flags
      $this                          final synthetic
      n                              final

  public default scala.Option<argonaut.Json> jNumberOrString(java.lang.String);
    descriptor: (Ljava/lang/String;)Lscala/Option;
    flags: (0x0001) ACC_PUBLIC
    Code:
      stack=4, locals=5, args_size=2
         0: aload_1
         1: astore        4
         3: ldc           #219                // String NaN
         5: aload         4
         7: invokevirtual #223                // Method java/lang/Object.equals:(Ljava/lang/Object;)Z
        10: ifeq          18
        13: iconst_1
        14: istore_3
        15: goto          80
        18: goto          21
        21: ldc           #225                // String Infinity
        23: aload         4
        25: invokevirtual #223                // Method java/lang/Object.equals:(Ljava/lang/Object;)Z
        28: ifeq          36
        31: iconst_1
        32: istore_3
        33: goto          80
        36: goto          39
        39: ldc           #227                // String +Infinity
        41: aload         4
        43: invokevirtual #223                // Method java/lang/Object.equals:(Ljava/lang/Object;)Z
        46: ifeq          54
        49: iconst_1
        50: istore_3
        51: goto          80
        54: goto          57
        57: ldc           #229                // String -Infinity
        59: aload         4
        61: invokevirtual #223                // Method java/lang/Object.equals:(Ljava/lang/Object;)Z
        64: ifeq          72
        67: iconst_1
        68: istore_3
        69: goto          80
        72: goto          75
        75: iconst_0
        76: istore_3
        77: goto          80
        80: iload_3
        81: ifeq          108
        84: new           #231                // class scala/Some
        87: dup
        88: aload_0
        89: invokeinterface #248,  1          // InterfaceMethod jString:()Lscala/Function1;
        94: aload         4
        96: invokeinterface #252,  2          // InterfaceMethod scala/Function1.apply:(Ljava/lang/Object;)Ljava/lang/Object;
       101: invokespecial #236                // Method scala/Some."<init>":(Ljava/lang/Object;)V
       104: astore_2
       105: goto          130
       108: goto          111
       111: getstatic     #207                // Field argonaut/JsonNumber$.MODULE$:Largonaut/JsonNumber$;
       114: aload_1
       115: invokevirtual #210                // Method argonaut/JsonNumber$.fromString:(Ljava/lang/String;)Lscala/Option;
       118: invokedynamic #257,  0            // InvokeDynamic #6:apply:()Lscala/Function1;
       123: invokevirtual #142                // Method scala/Option.map:(Lscala/Function1;)Lscala/Option;
       126: astore_2
       127: goto          130
       130: aload_2
       131: areturn
      StackMapTable: number_of_entries = 12
        frame_type = 254 /* append */
          offset_delta = 18
          locals = [ top, top, class java/lang/String ]
        frame_type = 2 /* same */
        frame_type = 14 /* same */
        frame_type = 2 /* same */
        frame_type = 14 /* same */
        frame_type = 2 /* same */
        frame_type = 14 /* same */
        frame_type = 2 /* same */
        frame_type = 255 /* full_frame */
          offset_delta = 4
          locals = [ class argonaut/Jsons, class java/lang/String, top, int, class java/lang/String ]
          stack = []
        frame_type = 27 /* same */
        frame_type = 2 /* same */
        frame_type = 255 /* full_frame */
          offset_delta = 18
          locals = [ class argonaut/Jsons, class java/lang/String, class scala/Option, int, class java/lang/String ]
          stack = []
      LineNumberTable:
        line 595: 0
        line 596: 3
        line 597: 111
        line 595: 130
      LocalVariableTable:
        Start  Length  Slot  Name   Signature
            0     132     0  this   Largonaut/Jsons;
            0     132     1     n   Ljava/lang/String;
    Signature: #202                         // (Ljava/lang/String;)Lscala/Option<Largonaut/Json;>;
    MethodParameters:
      Name                           Flags
      n                              final

  public abstract scala.Function1<java.lang.String, argonaut.Json> jString();
    descriptor: ()Lscala/Function1;
    flags: (0x0401) ACC_PUBLIC, ACC_ABSTRACT
    Signature: #258                         // ()Lscala/Function1<Ljava/lang/String;Largonaut/Json;>;

  public abstract scala.Function1<scala.collection.immutable.List<argonaut.Json>, argonaut.Json> jArray();
    descriptor: ()Lscala/Function1;
    flags: (0x0401) ACC_PUBLIC, ACC_ABSTRACT
    Signature: #260                         // ()Lscala/Function1<Lscala/collection/immutable/List<Largonaut/Json;>;Largonaut/Json;>;

  public abstract scala.Function1<argonaut.JsonObject, argonaut.Json> jObject();
    descriptor: ()Lscala/Function1;
    flags: (0x0401) ACC_PUBLIC, ACC_ABSTRACT
    Signature: #262                         // ()Lscala/Function1<Largonaut/JsonObject;Largonaut/Json;>;

  public abstract argonaut.Json jTrue();
    descriptor: ()Largonaut/Json;
    flags: (0x0401) ACC_PUBLIC, ACC_ABSTRACT

  public abstract argonaut.Json jFalse();
    descriptor: ()Largonaut/Json;
    flags: (0x0401) ACC_PUBLIC, ACC_ABSTRACT

  public abstract argonaut.Json jZero();
    descriptor: ()Largonaut/Json;
    flags: (0x0401) ACC_PUBLIC, ACC_ABSTRACT

  public abstract argonaut.Json jEmptyString();
    descriptor: ()Largonaut/Json;
    flags: (0x0401) ACC_PUBLIC, ACC_ABSTRACT

  public abstract argonaut.Json jEmptyArray();
    descriptor: ()Largonaut/Json;
    flags: (0x0401) ACC_PUBLIC, ACC_ABSTRACT

  public static argonaut.Json jSingleArray$(argonaut.Jsons, argonaut.Json);
    descriptor: (Largonaut/Jsons;Largonaut/Json;)Largonaut/Json;
    flags: (0x1009) ACC_PUBLIC, ACC_STATIC, ACC_SYNTHETIC
    Code:
      stack=2, locals=2, args_size=2
         0: aload_0
         1: aload_1
         2: invokespecial #274                // InterfaceMethod jSingleArray:(Largonaut/Json;)Largonaut/Json;
         5: areturn
      LineNumberTable:
        line 651: 0
      LocalVariableTable:
        Start  Length  Slot  Name   Signature
            0       6     0 $this   Largonaut/Jsons;
            0       6     1     j   Largonaut/Json;
    MethodParameters:
      Name                           Flags
      $this                          final synthetic
      j                              final

  public default argonaut.Json jSingleArray(argonaut.Json);
    descriptor: (Largonaut/Json;)Largonaut/Json;
    flags: (0x0001) ACC_PUBLIC
    Code:
      stack=6, locals=2, args_size=2
         0: new           #277                // class argonaut/JArray
         3: dup
         4: new           #279                // class scala/collection/immutable/$colon$colon
         7: dup
         8: aload_1
         9: getstatic     #284                // Field scala/collection/immutable/Nil$.MODULE$:Lscala/collection/immutable/Nil$;
        12: invokespecial #287                // Method scala/collection/immutable/$colon$colon."<init>":(Ljava/lang/Object;Lscala/collection/immutable/List;)V
        15: checkcast     #289                // class scala/collection/immutable/List
        18: invokespecial #292                // Method argonaut/JArray."<init>":(Lscala/collection/immutable/List;)V
        21: areturn
      LineNumberTable:
        line 652: 0
      LocalVariableTable:
        Start  Length  Slot  Name   Signature
            0      22     0  this   Largonaut/Jsons;
            0      22     1     j   Largonaut/Json;
    MethodParameters:
      Name                           Flags
      j                              final

  public static argonaut.Json jArrayElements$(argonaut.Jsons, scala.collection.immutable.Seq);
    descriptor: (Largonaut/Jsons;Lscala/collection/immutable/Seq;)Largonaut/Json;
    flags: (0x1009) ACC_PUBLIC, ACC_STATIC, ACC_SYNTHETIC
    Code:
      stack=2, locals=2, args_size=2
         0: aload_0
         1: aload_1
         2: invokespecial #299                // InterfaceMethod jArrayElements:(Lscala/collection/immutable/Seq;)Largonaut/Json;
         5: areturn
      LineNumberTable:
        line 657: 0
      LocalVariableTable:
        Start  Length  Slot  Name   Signature
            0       6     0 $this   Largonaut/Jsons;
            0       6     1 elements   Lscala/collection/immutable/Seq;
    MethodParameters:
      Name                           Flags
      $this                          final synthetic
      elements                       final

  public default argonaut.Json jArrayElements(scala.collection.immutable.Seq<argonaut.Json>);
    descriptor: (Lscala/collection/immutable/Seq;)Largonaut/Json;
    flags: (0x0001) ACC_PUBLIC
    Code:
      stack=2, locals=2, args_size=2
         0: aload_0
         1: invokeinterface #303,  1          // InterfaceMethod jArray:()Lscala/Function1;
         6: aload_1
         7: invokeinterface #309,  1          // InterfaceMethod scala/collection/immutable/Seq.toList:()Lscala/collection/immutable/List;
        12: invokeinterface #252,  2          // InterfaceMethod scala/Function1.apply:(Ljava/lang/Object;)Ljava/lang/Object;
        17: checkcast     #165                // class argonaut/Json
        20: areturn
      LineNumberTable:
        line 658: 0
      LocalVariableTable:
        Start  Length  Slot  Name   Signature
            0      21     0  this   Largonaut/Jsons;
            0      21     1 elements   Lscala/collection/immutable/Seq;
    Signature: #301                         // (Lscala/collection/immutable/Seq<Largonaut/Json;>;)Largonaut/Json;
    MethodParameters:
      Name                           Flags
      elements                       final

  public abstract argonaut.Json jEmptyObject();
    descriptor: ()Largonaut/Json;
    flags: (0x0401) ACC_PUBLIC, ACC_ABSTRACT

  public static argonaut.Json jSingleObject$(argonaut.Jsons, java.lang.String, argonaut.Json);
    descriptor: (Largonaut/Jsons;Ljava/lang/String;Largonaut/Json;)Largonaut/Json;
    flags: (0x1009) ACC_PUBLIC, ACC_STATIC, ACC_SYNTHETIC
    Code:
      stack=3, locals=3, args_size=3
         0: aload_0
         1: aload_1
         2: aload_2
         3: invokespecial #318                // InterfaceMethod jSingleObject:(Ljava/lang/String;Largonaut/Json;)Largonaut/Json;
         6: areturn
      LineNumberTable:
        line 669: 0
      LocalVariableTable:
        Start  Length  Slot  Name   Signature
            0       7     0 $this   Largonaut/Jsons;
            0       7     1     k   Ljava/lang/String;
            0       7     2     v   Largonaut/Json;
    MethodParameters:
      Name                           Flags
      $this                          final synthetic
      k                              final
      v                              final

  public default argonaut.Json jSingleObject(java.lang.String, argonaut.Json);
    descriptor: (Ljava/lang/String;Largonaut/Json;)Largonaut/Json;
    flags: (0x0001) ACC_PUBLIC
    Code:
      stack=5, locals=3, args_size=3
         0: new           #320                // class argonaut/JObject
         3: dup
         4: getstatic     #325                // Field argonaut/JsonObject$.MODULE$:Largonaut/JsonObject$;
         7: aload_1
         8: aload_2
         9: invokevirtual #329                // Method argonaut/JsonObject$.single:(Ljava/lang/String;Largonaut/Json;)Largonaut/JsonObject;
        12: invokespecial #332                // Method argonaut/JObject."<init>":(Largonaut/JsonObject;)V
        15: areturn
      LineNumberTable:
        line 670: 0
      LocalVariableTable:
        Start  Length  Slot  Name   Signature
            0      16     0  this   Largonaut/Jsons;
            0      16     1     k   Ljava/lang/String;
            0      16     2     v   Largonaut/Json;
    MethodParameters:
      Name                           Flags
      k                              final
      v                              final

  public static argonaut.Json jObjectAssocList$(argonaut.Jsons, scala.collection.immutable.List);
    descriptor: (Largonaut/Jsons;Lscala/collection/immutable/List;)Largonaut/Json;
    flags: (0x1009) ACC_PUBLIC, ACC_STATIC, ACC_SYNTHETIC
    Code:
      stack=2, locals=2, args_size=2
         0: aload_0
         1: aload_1
         2: invokespecial #339                // InterfaceMethod jObjectAssocList:(Lscala/collection/immutable/List;)Largonaut/Json;
         5: areturn
      LineNumberTable:
        line 675: 0
      LocalVariableTable:
        Start  Length  Slot  Name   Signature
            0       6     0 $this   Largonaut/Jsons;
            0       6     1     x   Lscala/collection/immutable/List;
    MethodParameters:
      Name                           Flags
      $this                          final synthetic
      x                              final

  public default argonaut.Json jObjectAssocList(scala.collection.immutable.List<scala.Tuple2<java.lang.String, argonaut.Json>>);
    descriptor: (Lscala/collection/immutable/List;)Largonaut/Json;
    flags: (0x0001) ACC_PUBLIC
    Code:
      stack=4, locals=2, args_size=2
         0: new           #320                // class argonaut/JObject
         3: dup
         4: getstatic     #325                // Field argonaut/JsonObject$.MODULE$:Largonaut/JsonObject$;
         7: aload_1
         8: invokevirtual #345                // Method argonaut/JsonObject$.fromTraversableOnce:(Lscala/collection/IterableOnce;)Largonaut/JsonObject;
        11: invokespecial #332                // Method argonaut/JObject."<init>":(Largonaut/JsonObject;)V
        14: areturn
      LineNumberTable:
        line 676: 0
      LocalVariableTable:
        Start  Length  Slot  Name   Signature
            0      15     0  this   Largonaut/Jsons;
            0      15     1     x   Lscala/collection/immutable/List;
    Signature: #341                         // (Lscala/collection/immutable/List<Lscala/Tuple2<Ljava/lang/String;Largonaut/Json;>;>;)Largonaut/Json;
    MethodParameters:
      Name                           Flags
      x                              final

  public static argonaut.Json jObjectFields$(argonaut.Jsons, scala.collection.immutable.Seq);
    descriptor: (Largonaut/Jsons;Lscala/collection/immutable/Seq;)Largonaut/Json;
    flags: (0x1009) ACC_PUBLIC, ACC_STATIC, ACC_SYNTHETIC
    Code:
      stack=2, locals=2, args_size=2
         0: aload_0
         1: aload_1
         2: invokespecial #349                // InterfaceMethod jObjectFields:(Lscala/collection/immutable/Seq;)Largonaut/Json;
         5: areturn
      LineNumberTable:
        line 681: 0
      LocalVariableTable:
        Start  Length  Slot  Name   Signature
            0       6     0 $this   Largonaut/Jsons;
            0       6     1     x   Lscala/collection/immutable/Seq;
    MethodParameters:
      Name                           Flags
      $this                          final synthetic
      x                              final

  public default argonaut.Json jObjectFields(scala.collection.immutable.Seq<scala.Tuple2<java.lang.String, argonaut.Json>>);
    descriptor: (Lscala/collection/immutable/Seq;)Largonaut/Json;
    flags: (0x0001) ACC_PUBLIC
    Code:
      stack=4, locals=2, args_size=2
         0: new           #320                // class argonaut/JObject
         3: dup
         4: getstatic     #325                // Field argonaut/JsonObject$.MODULE$:Largonaut/JsonObject$;
         7: aload_1
         8: invokevirtual #345                // Method argonaut/JsonObject$.fromTraversableOnce:(Lscala/collection/IterableOnce;)Largonaut/JsonObject;
        11: invokespecial #332                // Method argonaut/JObject."<init>":(Largonaut/JsonObject;)V
        14: areturn
      LineNumberTable:
        line 682: 0
      LocalVariableTable:
        Start  Length  Slot  Name   Signature
            0      15     0  this   Largonaut/Jsons;
            0      15     1     x   Lscala/collection/immutable/Seq;
    Signature: #350                         // (Lscala/collection/immutable/Seq<Lscala/Tuple2<Ljava/lang/String;Largonaut/Json;>;>;)Largonaut/Json;
    MethodParameters:
      Name                           Flags
      x                              final

  public static argonaut.JBool $anonfun$jBool$1(boolean);
    descriptor: (Z)Largonaut/JBool;
    flags: (0x1009) ACC_PUBLIC, ACC_STATIC, ACC_SYNTHETIC
    Code:
      stack=3, locals=1, args_size=1
         0: new           #355                // class argonaut/JBool
         3: dup
         4: iload_0
         5: invokespecial #358                // Method argonaut/JBool."<init>":(Z)V
         8: areturn
      LineNumberTable:
        line 522: 0
      LocalVariableTable:
        Start  Length  Slot  Name   Signature
            0       9     0  x$29   Z
    MethodParameters:
      Name                           Flags
      x$29                           final

  public static argonaut.JNumber $anonfun$jNumber$1(argonaut.JsonNumber);
    descriptor: (Largonaut/JsonNumber;)Largonaut/JNumber;
    flags: (0x1009) ACC_PUBLIC, ACC_STATIC, ACC_SYNTHETIC
    Code:
      stack=3, locals=1, args_size=1
         0: new           #48                 // class argonaut/JNumber
         3: dup
         4: aload_0
         5: invokespecial #52                 // Method argonaut/JNumber."<init>":(Largonaut/JsonNumber;)V
         8: areturn
      LineNumberTable:
        line 544: 0
      LocalVariableTable:
        Start  Length  Slot  Name   Signature
            0       9     0     n   Largonaut/JsonNumber;
    MethodParameters:
      Name                           Flags
      n                              final

  public static argonaut.Json $anonfun$jNumberOrNull$1(argonaut.Jsons);
    descriptor: (Largonaut/Jsons;)Largonaut/Json;
    flags: (0x1009) ACC_PUBLIC, ACC_STATIC, ACC_SYNTHETIC
    Code:
      stack=1, locals=1, args_size=1
         0: aload_0
         1: invokeinterface #233,  1          // InterfaceMethod jNull:()Largonaut/Json;
         6: areturn
      LineNumberTable:
        line 552: 0
      LocalVariableTable:
        Start  Length  Slot  Name   Signature
            0       7     0 $this   Largonaut/Jsons;
    MethodParameters:
      Name                           Flags
      $this                          final synthetic

  public static argonaut.Json $anonfun$jNumberOrString$1(argonaut.Jsons, double);
    descriptor: (Largonaut/Jsons;D)Largonaut/Json;
    flags: (0x1009) ACC_PUBLIC, ACC_STATIC, ACC_SYNTHETIC
    Code:
      stack=3, locals=3, args_size=2
         0: aload_0
         1: invokeinterface #248,  1          // InterfaceMethod jString:()Lscala/Function1;
         6: dload_1
         7: invokestatic  #109                // Method scala/runtime/BoxesRunTime.boxToDouble:(D)Ljava/lang/Double;
        10: invokevirtual #364                // Method java/lang/Object.toString:()Ljava/lang/String;
        13: invokeinterface #252,  2          // InterfaceMethod scala/Function1.apply:(Ljava/lang/Object;)Ljava/lang/Object;
        18: checkcast     #165                // class argonaut/Json
        21: areturn
      LineNumberTable:
        line 563: 0
      LocalVariableTable:
        Start  Length  Slot  Name   Signature
            0      22     0 $this   Largonaut/Jsons;
            0      22     1   n$1   D
    MethodParameters:
      Name                           Flags
      $this                          final synthetic
      n$1                            final

  public static argonaut.Json $anonfun$jNumberOrString$2(argonaut.JsonNumber);
    descriptor: (Largonaut/JsonNumber;)Largonaut/Json;
    flags: (0x1009) ACC_PUBLIC, ACC_STATIC, ACC_SYNTHETIC
    Code:
      stack=1, locals=1, args_size=1
         0: aload_0
         1: invokevirtual #370                // Method argonaut/JsonNumber.asJson:()Largonaut/Json;
         4: areturn
      LineNumberTable:
        line 563: 0
      LocalVariableTable:
        Start  Length  Slot  Name   Signature
            0       5     0  x$30   Largonaut/JsonNumber;
    MethodParameters:
      Name                           Flags
      x$30                           final

  public static argonaut.Json $anonfun$jNumber$2(argonaut.JsonNumber);
    descriptor: (Largonaut/JsonNumber;)Largonaut/Json;
    flags: (0x1009) ACC_PUBLIC, ACC_STATIC, ACC_SYNTHETIC
    Code:
      stack=1, locals=1, args_size=1
         0: aload_0
         1: invokevirtual #370                // Method argonaut/JsonNumber.asJson:()Largonaut/Json;
         4: areturn
      LineNumberTable:
        line 573: 0
      LocalVariableTable:
        Start  Length  Slot  Name   Signature
            0       5     0  x$31   Largonaut/JsonNumber;
    MethodParameters:
      Name                           Flags
      x$31                           final

  public static argonaut.Json $anonfun$jNumberOrNull$2(argonaut.JsonNumber);
    descriptor: (Largonaut/JsonNumber;)Largonaut/Json;
    flags: (0x1009) ACC_PUBLIC, ACC_STATIC, ACC_SYNTHETIC
    Code:
      stack=1, locals=1, args_size=1
         0: aload_0
         1: invokevirtual #370                // Method argonaut/JsonNumber.asJson:()Largonaut/Json;
         4: areturn
      LineNumberTable:
        line 583: 0
      LocalVariableTable:
        Start  Length  Slot  Name   Signature
            0       5     0  x$32   Largonaut/JsonNumber;
    MethodParameters:
      Name                           Flags
      x$32                           final

  public static argonaut.Json $anonfun$jNumberOrString$3(argonaut.JsonNumber);
    descriptor: (Largonaut/JsonNumber;)Largonaut/Json;
    flags: (0x1009) ACC_PUBLIC, ACC_STATIC, ACC_SYNTHETIC
    Code:
      stack=1, locals=1, args_size=1
         0: aload_0
         1: invokevirtual #370                // Method argonaut/JsonNumber.asJson:()Largonaut/Json;
         4: areturn
      LineNumberTable:
        line 597: 0
      LocalVariableTable:
        Start  Length  Slot  Name   Signature
            0       5     0  x$33   Largonaut/JsonNumber;
    MethodParameters:
      Name                           Flags
      x$33                           final

  public static argonaut.JString $anonfun$jString$1(java.lang.String);
    descriptor: (Ljava/lang/String;)Largonaut/JString;
    flags: (0x1009) ACC_PUBLIC, ACC_STATIC, ACC_SYNTHETIC
    Code:
      stack=3, locals=1, args_size=1
         0: new           #378                // class argonaut/JString
         3: dup
         4: aload_0
         5: invokespecial #381                // Method argonaut/JString."<init>":(Ljava/lang/String;)V
         8: areturn
      LineNumberTable:
        line 604: 0
      LocalVariableTable:
        Start  Length  Slot  Name   Signature
            0       9     0  x$34   Ljava/lang/String;
    MethodParameters:
      Name                           Flags
      x$34                           final

  public static argonaut.JArray $anonfun$jArray$1(scala.collection.immutable.List);
    descriptor: (Lscala/collection/immutable/List;)Largonaut/JArray;
    flags: (0x1009) ACC_PUBLIC, ACC_STATIC, ACC_SYNTHETIC
    Code:
      stack=3, locals=1, args_size=1
         0: new           #277                // class argonaut/JArray
         3: dup
         4: aload_0
         5: invokespecial #292                // Method argonaut/JArray."<init>":(Lscala/collection/immutable/List;)V
         8: areturn
      LineNumberTable:
        line 610: 0
      LocalVariableTable:
        Start  Length  Slot  Name   Signature
            0       9     0  x$35   Lscala/collection/immutable/List;
    MethodParameters:
      Name                           Flags
      x$35                           final

  public static argonaut.JObject $anonfun$jObject$1(argonaut.JsonObject);
    descriptor: (Largonaut/JsonObject;)Largonaut/JObject;
    flags: (0x1009) ACC_PUBLIC, ACC_STATIC, ACC_SYNTHETIC
    Code:
      stack=3, locals=1, args_size=1
         0: new           #320                // class argonaut/JObject
         3: dup
         4: aload_0
         5: invokespecial #332                // Method argonaut/JObject."<init>":(Largonaut/JsonObject;)V
         8: areturn
      LineNumberTable:
        line 616: 0
      LocalVariableTable:
        Start  Length  Slot  Name   Signature
            0       9     0  x$36   Largonaut/JsonObject;
    MethodParameters:
      Name                           Flags
      x$36                           final

  public static void $init$(argonaut.Jsons);
    descriptor: (Largonaut/Jsons;)V
    flags: (0x0009) ACC_PUBLIC, ACC_STATIC
    Code:
      stack=7, locals=1, args_size=1
         0: aload_0
         1: getstatic     #395                // Field argonaut/JNull$.MODULE$:Largonaut/JNull$;
         4: invokeinterface #397,  2          // InterfaceMethod argonaut$Jsons$_setter_$jNull_$eq:(Largonaut/Json;)V
         9: aload_0
        10: invokedynamic #404,  0            // InvokeDynamic #7:apply:()Lscala/Function1;
        15: invokeinterface #406,  2          // InterfaceMethod argonaut$Jsons$_setter_$jBool_$eq:(Lscala/Function1;)V
        20: aload_0
        21: invokedynamic #411,  0            // InvokeDynamic #8:apply:()Lscala/Function1;
        26: invokeinterface #413,  2          // InterfaceMethod argonaut$Jsons$_setter_$jString_$eq:(Lscala/Function1;)V
        31: aload_0
        32: invokedynamic #418,  0            // InvokeDynamic #9:apply:()Lscala/Function1;
        37: invokeinterface #420,  2          // InterfaceMethod argonaut$Jsons$_setter_$jArray_$eq:(Lscala/Function1;)V
        42: aload_0
        43: invokedynamic #425,  0            // InvokeDynamic #10:apply:()Lscala/Function1;
        48: invokeinterface #427,  2          // InterfaceMethod argonaut$Jsons$_setter_$jObject_$eq:(Lscala/Function1;)V
        53: aload_0
        54: new           #355                // class argonaut/JBool
        57: dup
        58: iconst_1
        59: invokespecial #358                // Method argonaut/JBool."<init>":(Z)V
        62: invokeinterface #429,  2          // InterfaceMethod argonaut$Jsons$_setter_$jTrue_$eq:(Largonaut/Json;)V
        67: aload_0
        68: new           #355                // class argonaut/JBool
        71: dup
        72: iconst_0
        73: invokespecial #358                // Method argonaut/JBool."<init>":(Z)V
        76: invokeinterface #431,  2          // InterfaceMethod argonaut$Jsons$_setter_$jFalse_$eq:(Largonaut/Json;)V
        81: aload_0
        82: new           #48                 // class argonaut/JNumber
        85: dup
        86: new           #433                // class argonaut/JsonLong
        89: dup
        90: lconst_0
        91: invokespecial #436                // Method argonaut/JsonLong."<init>":(J)V
        94: invokespecial #52                 // Method argonaut/JNumber."<init>":(Largonaut/JsonNumber;)V
        97: invokeinterface #438,  2          // InterfaceMethod argonaut$Jsons$_setter_$jZero_$eq:(Largonaut/Json;)V
       102: aload_0
       103: new           #378                // class argonaut/JString
       106: dup
       107: ldc_w         #440                // String
       110: invokespecial #381                // Method argonaut/JString."<init>":(Ljava/lang/String;)V
       113: invokeinterface #442,  2          // InterfaceMethod argonaut$Jsons$_setter_$jEmptyString_$eq:(Largonaut/Json;)V
       118: aload_0
       119: new           #277                // class argonaut/JArray
       122: dup
       123: getstatic     #284                // Field scala/collection/immutable/Nil$.MODULE$:Lscala/collection/immutable/Nil$;
       126: invokespecial #292                // Method argonaut/JArray."<init>":(Lscala/collection/immutable/List;)V
       129: invokeinterface #444,  2          // InterfaceMethod argonaut$Jsons$_setter_$jEmptyArray_$eq:(Largonaut/Json;)V
       134: aload_0
       135: new           #320                // class argonaut/JObject
       138: dup
       139: getstatic     #325                // Field argonaut/JsonObject$.MODULE$:Largonaut/JsonObject$;
       142: invokevirtual #448                // Method argonaut/JsonObject$.empty:()Largonaut/JsonObject;
       145: invokespecial #332                // Method argonaut/JObject."<init>":(Largonaut/JsonObject;)V
       148: invokeinterface #450,  2          // InterfaceMethod argonaut$Jsons$_setter_$jEmptyObject_$eq:(Largonaut/Json;)V
       153: return
      LineNumberTable:
        line 515: 0
        line 516: 1
        line 521: 9
        line 522: 10
        line 603: 20
        line 604: 21
        line 609: 31
        line 610: 32
        line 615: 42
        line 616: 43
        line 621: 53
        line 622: 54
        line 627: 67
        line 628: 68
        line 633: 81
        line 634: 82
        line 639: 102
        line 640: 103
        line 645: 118
        line 646: 119
        line 663: 134
        line 664: 135
        line 504: 153
      LocalVariableTable:
        Start  Length  Slot  Name   Signature
            0     154     0 $this   Largonaut/Jsons;
    MethodParameters:
      Name                           Flags
      $this                          final synthetic

  public static argonaut.JBool $anonfun$jBool$1$adapted(java.lang.Object);
    descriptor: (Ljava/lang/Object;)Largonaut/JBool;
    flags: (0x1009) ACC_PUBLIC, ACC_STATIC, ACC_SYNTHETIC
    Code:
      stack=1, locals=1, args_size=1
         0: aload_0
         1: invokestatic  #453                // Method scala/runtime/BoxesRunTime.unboxToBoolean:(Ljava/lang/Object;)Z
         4: invokestatic  #455                // InterfaceMethod $anonfun$jBool$1:(Z)Largonaut/JBool;
         7: areturn
      LineNumberTable:
        line 522: 0
      LocalVariableTable:
        Start  Length  Slot  Name   Signature
            0       8     0  x$29   Ljava/lang/Object;
    MethodParameters:
      Name                           Flags
      x$29                           final

  private static java.lang.Object $deserializeLambda$(java.lang.invoke.SerializedLambda);
    descriptor: (Ljava/lang/invoke/SerializedLambda;)Ljava/lang/Object;
    flags: (0x100a) ACC_PRIVATE, ACC_STATIC, ACC_SYNTHETIC
    Code:
      stack=1, locals=1, args_size=1
         0: aload_0
         1: invokedynamic #468,  0            // InvokeDynamic #11:lambdaDeserialize:(Ljava/lang/invoke/SerializedLambda;)Ljava/lang/Object;
         6: areturn
}
InnerClasses:
  public static final #13= #10 of #12;    // Lookup=class java/lang/invoke/MethodHandles$Lookup of class java/lang/invoke/MethodHandles
SourceFile: "Json.scala"
RuntimeVisibleAnnotations:
  0: #6(#7=s#8)
    scala.reflect.ScalaSignature(
      bytes="\u0006\u0005\u0005Mda\u0002\u0012$!\u0003\r\tA\n\u0005\u0006[\u0001!\tAL\u0003\u0005e\u0001\u00011\'\u0002\u00037\u0001\u00019T\u0001B$\u0001\u0001!+A\u0001\u0015\u0001\u0001\u0011\u0016!\u0011\u000b\u0001\u0001S\u000b\u00119\u0006\u0001\u0001-\t\u000fi\u0003!\u0019!C\u00017\"9A\f\u0001b\u0001\n\u0003i\u0006\"B1\u0001\t\u0003\u0011\u0007\"B1\u0001\t\u0003A\u0007\"B1\u0001\t\u0003i\u0007\"B1\u0001\t\u0003\u0011\b\"\u0002>\u0001\t\u0003Y\b\"B?\u0001\t\u0003q\bBB1\u0001\t\u0003\t\t\u0001\u0003\u0004b\u0001\u0011\u0005\u00111\u0002\u0005\u0007u\u0002!\t!a\u0004\t\ru\u0004A\u0011AA\n\u0011%\t9\u0002\u0001b\u0001\n\u0003\tI\u0002C\u0005\u0002 \u0001\u0011\r\u0011\"\u0001\u0002\"!I\u0011q\u0005\u0001C\u0002\u0013\u0005\u0011\u0011\u0006\u0005\t\u0003g\u0001!\u0019!C\u00017\"A\u0011Q\u0007\u0001C\u0002\u0013\u00051\f\u0003\u0005\u00028\u0001\u0011\r\u0011\"\u0001\\\u0011!\tI\u0004\u0001b\u0001\n\u0003Y\u0006\u0002CA\u001e\u0001\t\u0007I\u0011A.\t\u000f\u0005u\u0002\u0001\"\u0001\u0002@!9\u0011Q\t\u0001\u0005\u0002\u0005\u001d\u0003\u0002CA*\u0001\t\u0007I\u0011A.\t\u000f\u0005U\u0003\u0001\"\u0001\u0002X!9\u0011\u0011\r\u0001\u0005\u0002\u0005\r\u0004bBA6\u0001\u0011\u0005\u0011Q\u000e\u0002\u0006\u0015N|gn\u001d\u0006\u0002I\u0005A\u0011M]4p]\u0006,Ho\u0001\u0001\u0014\u0005\u00019\u0003C\u0001\u0015,\u001b\u0005I#\"\u0001\u0016\u0002\u000bM\u001c\u0017\r\\1\n\u00051J#AB!osJ+g-\u0001\u0004%S:LG\u000f\n\u000b\u0002_A\u0011\u0001\u0006M\u0005\u0003c%\u0012A!\u00168ji\nY!j]8o\u0005>|G.Z1o!\tAC\'\u0003\u00026S\t9!i\\8mK\u0006t\'!\u0003&t_:\f%O]1z!\rA\u0004i\u0011\b\u0003syr!AO\u001f\u000e\u0003mR!\u0001P\u0013\u0002\rq\u0012xn\u001c;?\u0013\u0005Q\u0013BA *\u0003\u001d\u0001\u0018mY6bO\u0016L!!\u0011\"\u0003\t1K7\u000f\u001e\u0006\u0003\u007f%\u0002\"\u0001R#\u000e\u0003\rJ!AR\u0012\u0003\t)\u001bxN\u001c\u0002\u000b\u0015N|gn\u0015;sS:<\u0007CA%N\u001d\tQ5\n\u0005\u0002;S%\u0011A*K\u0001\u0007!J,G-\u001a4\n\u00059{%AB*ue&twM\u0003\u0002MS\tI!j]8o\r&,G\u000e\u001a\u0002\n\u0015N|g.Q:t_\u000e\u0004B\u0001K*V\u0007&\u0011A+\u000b\u0002\u0007)V\u0004H.\u001a\u001a\u0011\u0005Y+Q\"\u0001\u0001\u0003\u001b)\u001bxN\\!tg>\u001cG*[:u!\rA\u0004)\u0017\t\u0003-\u001a\tQA\u001b(vY2,\u0012aQ\u0001\u0006U\n{w\u000e\\\u000b\u0002=B!\u0001fX\u001aD\u0013\t\u0001\u0017FA\u0005Gk:\u001cG/[8oc\u00059!NT;nE\u0016\u0014HCA\"d\u0011\u0015!\'\u00021\u0001f\u0003\u0005q\u0007C\u0001#g\u0013\t97E\u0001\u0006Kg>tg*^7cKJ$\"aQ5\t\u000b\u0011\\\u0001\u0019\u00016\u0011\u0005!Z\u0017B\u00017*\u0005\rIe\u000e\u001e\u000b\u0003\u0007:DQ\u0001\u001a\u0007A\u0002=\u0004\"\u0001\u000b9\n\u0005EL#\u0001\u0002\'p]\u001e$\"a\u001d<\u0011\u0007!\"8)\u0003\u0002vS\t1q\n\u001d;j_:DQ\u0001Z\u0007A\u0002]\u0004\"\u0001\u000b=\n\u0005eL#A\u0002#pk\ndW-A\u0007k\u001dVl\'-\u001a:Pe:+H\u000e\u001c\u000b\u0003\u0007rDQ\u0001\u001a\bA\u0002]\fqB\u001b(v[\n,\'o\u0014:TiJLgn\u001a\u000b\u0003\u0007~DQ\u0001Z\bA\u0002]$2aQA\u0002\u0011\u0019!\u0007\u00031\u0001\u0002\u0006A\u0019\u0001(a\u0002\n\u0007\u0005%!I\u0001\u0006CS\u001e$UmY5nC2$2a]A\u0007\u0011\u0015!\u0017\u00031\u0001I)\r\u0019\u0018\u0011\u0003\u0005\u0006IJ\u0001\r\u0001\u0013\u000b\u0004g\u0006U\u0001\"\u00023\u0014\u0001\u0004A\u0015a\u00026TiJLgnZ\u000b\u0003\u00037\u0001R\u0001K0\u0002\u001e\r\u0003\"A\u0016\u0003\u0002\r)\f%O]1z+\t\t\u0019\u0003E\u0003)?\u0006\u00152\t\u0005\u0002W\u0007\u00059!n\u00142kK\u000e$XCAA\u0016!\u0015As,!\fD!\r!\u0015qF\u0005\u0004\u0003c\u0019#A\u0003&t_:|%M[3di\u0006)!\u000e\u0016:vK\u00061!NR1mg\u0016\fQA\u001b.fe>\fAB[#naRL8\u000b\u001e:j]\u001e\f1B[#naRL\u0018I\u001d:bs\u0006a!nU5oO2,\u0017I\u001d:bsR\u00191)!\u0011\t\r\u0005\rC\u00041\u0001D\u0003\u0005Q\u0017A\u00046BeJ\f\u00170\u00127f[\u0016tGo\u001d\u000b\u0004\u0007\u0006%\u0003bBA&;\u0001\u0007\u0011QJ\u0001\tK2,W.\u001a8ugB!\u0001&a\u0014D\u0013\r\t\t&\u000b\u0002\u000byI,\u0007/Z1uK\u0012t\u0014\u0001\u00046F[B$\u0018p\u00142kK\u000e$\u0018!\u00046TS:<G.Z(cU\u0016\u001cG\u000fF\u0003D\u00033\ni\u0006\u0003\u0004\u0002\\}\u0001\r!V\u0001\u0002W\"1\u0011qL\u0010A\u0002\r\u000b\u0011A^\u0001\u0011U>\u0013\'.Z2u\u0003N\u001cxn\u0019\'jgR$2aQA3\u0011\u001d\t9\u0007\ta\u0001\u0003S\n\u0011\u0001\u001f\t\u0003-\u001e\tQB[(cU\u0016\u001cGOR5fY\u0012\u001cHcA\"\u0002p!9\u0011qM\u0011A\u0002\u0005E\u0004\u0003\u0002\u0015\u0002PI\u0003"
    )
BootstrapMethods:
  0: #133 REF_invokeStatic java/lang/invoke/LambdaMetafactory.altMetafactory:(Ljava/lang/invoke/MethodHandles$Lookup;Ljava/lang/String;Ljava/lang/invoke/MethodType;[Ljava/lang/Object;)Ljava/lang/invoke/CallSite;
    Method arguments:
      #118 (Ljava/lang/Object;)Ljava/lang/Object;
      #123 REF_invokeStatic argonaut/Jsons.$anonfun$jNumber$1:(Largonaut/JsonNumber;)Largonaut/JNumber;
      #124 (Largonaut/JsonNumber;)Largonaut/JNumber;
      #125 5
      #126 1
      #124 (Largonaut/JsonNumber;)Largonaut/JNumber;
  1: #133 REF_invokeStatic java/lang/invoke/LambdaMetafactory.altMetafactory:(Ljava/lang/invoke/MethodHandles$Lookup;Ljava/lang/String;Ljava/lang/invoke/MethodType;[Ljava/lang/Object;)Ljava/lang/invoke/CallSite;
    Method arguments:
      #150 ()Ljava/lang/Object;
      #155 REF_invokeStatic argonaut/Jsons.$anonfun$jNumberOrNull$1:(Largonaut/Jsons;)Largonaut/Json;
      #156 ()Largonaut/Json;
      #125 5
      #126 1
      #156 ()Largonaut/Json;
  2: #133 REF_invokeStatic java/lang/invoke/LambdaMetafactory.altMetafactory:(Ljava/lang/invoke/MethodHandles$Lookup;Ljava/lang/String;Ljava/lang/invoke/MethodType;[Ljava/lang/Object;)Ljava/lang/invoke/CallSite;
    Method arguments:
      #150 ()Ljava/lang/Object;
      #173 REF_invokeStatic argonaut/Jsons.$anonfun$jNumberOrString$1:(Largonaut/Jsons;D)Largonaut/Json;
      #156 ()Largonaut/Json;
      #125 5
      #126 1
      #156 ()Largonaut/Json;
  3: #133 REF_invokeStatic java/lang/invoke/LambdaMetafactory.altMetafactory:(Ljava/lang/invoke/MethodHandles$Lookup;Ljava/lang/String;Ljava/lang/invoke/MethodType;[Ljava/lang/Object;)Ljava/lang/invoke/CallSite;
    Method arguments:
      #118 (Ljava/lang/Object;)Ljava/lang/Object;
      #180 REF_invokeStatic argonaut/Jsons.$anonfun$jNumberOrString$2:(Largonaut/JsonNumber;)Largonaut/Json;
      #181 (Largonaut/JsonNumber;)Largonaut/Json;
      #125 5
      #126 1
      #181 (Largonaut/JsonNumber;)Largonaut/Json;
  4: #133 REF_invokeStatic java/lang/invoke/LambdaMetafactory.altMetafactory:(Ljava/lang/invoke/MethodHandles$Lookup;Ljava/lang/String;Ljava/lang/invoke/MethodType;[Ljava/lang/Object;)Ljava/lang/invoke/CallSite;
    Method arguments:
      #118 (Ljava/lang/Object;)Ljava/lang/Object;
      #214 REF_invokeStatic argonaut/Jsons.$anonfun$jNumber$2:(Largonaut/JsonNumber;)Largonaut/Json;
      #181 (Largonaut/JsonNumber;)Largonaut/Json;
      #125 5
      #126 1
      #181 (Largonaut/JsonNumber;)Largonaut/Json;
  5: #133 REF_invokeStatic java/lang/invoke/LambdaMetafactory.altMetafactory:(Ljava/lang/invoke/MethodHandles$Lookup;Ljava/lang/String;Ljava/lang/invoke/MethodType;[Ljava/lang/Object;)Ljava/lang/invoke/CallSite;
    Method arguments:
      #118 (Ljava/lang/Object;)Ljava/lang/Object;
      #240 REF_invokeStatic argonaut/Jsons.$anonfun$jNumberOrNull$2:(Largonaut/JsonNumber;)Largonaut/Json;
      #181 (Largonaut/JsonNumber;)Largonaut/Json;
      #125 5
      #126 1
      #181 (Largonaut/JsonNumber;)Largonaut/Json;
  6: #133 REF_invokeStatic java/lang/invoke/LambdaMetafactory.altMetafactory:(Ljava/lang/invoke/MethodHandles$Lookup;Ljava/lang/String;Ljava/lang/invoke/MethodType;[Ljava/lang/Object;)Ljava/lang/invoke/CallSite;
    Method arguments:
      #118 (Ljava/lang/Object;)Ljava/lang/Object;
      #256 REF_invokeStatic argonaut/Jsons.$anonfun$jNumberOrString$3:(Largonaut/JsonNumber;)Largonaut/Json;
      #181 (Largonaut/JsonNumber;)Largonaut/Json;
      #125 5
      #126 1
      #181 (Largonaut/JsonNumber;)Largonaut/Json;
  7: #133 REF_invokeStatic java/lang/invoke/LambdaMetafactory.altMetafactory:(Ljava/lang/invoke/MethodHandles$Lookup;Ljava/lang/String;Ljava/lang/invoke/MethodType;[Ljava/lang/Object;)Ljava/lang/invoke/CallSite;
    Method arguments:
      #118 (Ljava/lang/Object;)Ljava/lang/Object;
      #402 REF_invokeStatic argonaut/Jsons.$anonfun$jBool$1$adapted:(Ljava/lang/Object;)Largonaut/JBool;
      #403 (Ljava/lang/Object;)Largonaut/JBool;
      #125 5
      #126 1
      #403 (Ljava/lang/Object;)Largonaut/JBool;
  8: #133 REF_invokeStatic java/lang/invoke/LambdaMetafactory.altMetafactory:(Ljava/lang/invoke/MethodHandles$Lookup;Ljava/lang/String;Ljava/lang/invoke/MethodType;[Ljava/lang/Object;)Ljava/lang/invoke/CallSite;
    Method arguments:
      #118 (Ljava/lang/Object;)Ljava/lang/Object;
      #409 REF_invokeStatic argonaut/Jsons.$anonfun$jString$1:(Ljava/lang/String;)Largonaut/JString;
      #410 (Ljava/lang/String;)Largonaut/JString;
      #125 5
      #126 1
      #410 (Ljava/lang/String;)Largonaut/JString;
  9: #133 REF_invokeStatic java/lang/invoke/LambdaMetafactory.altMetafactory:(Ljava/lang/invoke/MethodHandles$Lookup;Ljava/lang/String;Ljava/lang/invoke/MethodType;[Ljava/lang/Object;)Ljava/lang/invoke/CallSite;
    Method arguments:
      #118 (Ljava/lang/Object;)Ljava/lang/Object;
      #416 REF_invokeStatic argonaut/Jsons.$anonfun$jArray$1:(Lscala/collection/immutable/List;)Largonaut/JArray;
      #417 (Lscala/collection/immutable/List;)Largonaut/JArray;
      #125 5
      #126 1
      #417 (Lscala/collection/immutable/List;)Largonaut/JArray;
  10: #133 REF_invokeStatic java/lang/invoke/LambdaMetafactory.altMetafactory:(Ljava/lang/invoke/MethodHandles$Lookup;Ljava/lang/String;Ljava/lang/invoke/MethodType;[Ljava/lang/Object;)Ljava/lang/invoke/CallSite;
    Method arguments:
      #118 (Ljava/lang/Object;)Ljava/lang/Object;
      #423 REF_invokeStatic argonaut/Jsons.$anonfun$jObject$1:(Largonaut/JsonObject;)Largonaut/JObject;
      #424 (Largonaut/JsonObject;)Largonaut/JObject;
      #125 5
      #126 1
      #424 (Largonaut/JsonObject;)Largonaut/JObject;
  11: #465 REF_invokeStatic scala/runtime/LambdaDeserialize.bootstrap:(Ljava/lang/invoke/MethodHandles$Lookup;Ljava/lang/String;Ljava/lang/invoke/MethodType;[Ljava/lang/invoke/MethodHandle;)Ljava/lang/invoke/CallSite;
    Method arguments:
      #416 REF_invokeStatic argonaut/Jsons.$anonfun$jArray$1:(Lscala/collection/immutable/List;)Largonaut/JArray;
      #402 REF_invokeStatic argonaut/Jsons.$anonfun$jBool$1$adapted:(Ljava/lang/Object;)Largonaut/JBool;
      #123 REF_invokeStatic argonaut/Jsons.$anonfun$jNumber$1:(Largonaut/JsonNumber;)Largonaut/JNumber;
      #214 REF_invokeStatic argonaut/Jsons.$anonfun$jNumber$2:(Largonaut/JsonNumber;)Largonaut/Json;
      #155 REF_invokeStatic argonaut/Jsons.$anonfun$jNumberOrNull$1:(Largonaut/Jsons;)Largonaut/Json;
      #240 REF_invokeStatic argonaut/Jsons.$anonfun$jNumberOrNull$2:(Largonaut/JsonNumber;)Largonaut/Json;
      #173 REF_invokeStatic argonaut/Jsons.$anonfun$jNumberOrString$1:(Largonaut/Jsons;D)Largonaut/Json;
      #180 REF_invokeStatic argonaut/Jsons.$anonfun$jNumberOrString$2:(Largonaut/JsonNumber;)Largonaut/Json;
      #256 REF_invokeStatic argonaut/Jsons.$anonfun$jNumberOrString$3:(Largonaut/JsonNumber;)Largonaut/Json;
      #423 REF_invokeStatic argonaut/Jsons.$anonfun$jObject$1:(Largonaut/JsonObject;)Largonaut/JObject;
      #409 REF_invokeStatic argonaut/Jsons.$anonfun$jString$1:(Ljava/lang/String;)Largonaut/JString;
  ScalaInlineInfo: length = 0x149 (unknown attribute)
   01 00 00 41 01 7E 01 7F 01 01 5F 01 60 01 01 8E
   01 8F 01 00 77 00 78 01 00 D3 00 2A 01 00 97 00
   98 01 00 ED 00 2A 01 00 AA 00 90 01 00 B1 00 2A
   01 00 FD 00 2A 01 01 81 01 82 01 01 76 01 77 01
   01 85 01 86 01 00 16 00 12 00 00 11 00 12 00 00
   1E 00 0F 00 00 1F 00 0F 00 00 1D 00 0F 00 00 1B
   00 0F 00 00 0E 00 0F 00 00 18 00 12 00 00 14 00
   12 00 00 1A 00 0F 00 00 1C 00 0F 00 01 03 00 23
   00 01 28 01 29 00 01 25 01 26 01 00 22 00 23 00
   01 0B 00 21 00 01 36 00 21 00 01 0A 00 21 00 01
   08 00 21 00 00 20 00 21 00 00 29 00 65 00 00 29
   00 37 00 00 29 00 59 00 00 29 00 2A 00 00 29 00
   C6 00 00 29 00 BC 00 00 25 00 64 01 00 25 00 36
   01 00 25 00 58 01 00 25 00 26 01 00 25 00 C5 01
   00 25 00 BB 01 00 91 00 92 00 00 91 00 C6 00 00
   8F 00 90 01 00 8F 00 C5 01 00 A7 00 92 00 00 A7
   00 C6 00 00 A6 00 90 01 00 A6 00 C5 01 01 05 00
   23 00 01 50 01 51 00 01 4D 01 4E 01 01 5B 01 29
   00 01 5A 01 26 01 01 0F 01 10 00 01 0C 01 0D 01
   01 3B 01 3C 00 01 37 01 38 01 00 F6 00 23 00 01
   07 00 21 00 01 09 00 21 00
  ScalaSig: length = 0x3 (unknown attribute)
   05 02 00
