Classfile /Users/mw/Projects/slang-braindump/.jar/jar8/assemble/slang-braindump/assemble/content/argonaut/Parse$.class
  Last modified May 29, 2022; size 4233 bytes
  SHA-256 checksum 364298429ee22868072a3d0cdeec0b44b275662f905eaaead3e4d86123c6ed10
  Compiled from "Parse.scala"
public final class argonaut.Parse$ extends java.lang.Object implements argonaut.Parse<java.lang.String>
  minor version: 0
  major version: 52
  flags: (0x0031) ACC_PUBLIC, ACC_FINAL, ACC_SUPER
  this_class: #2                          // argonaut/Parse$
  super_class: #5                         // java/lang/Object
  interfaces: 1, fields: 1, methods: 14, attributes: 4
Constant pool:
    #1 = Utf8               argonaut/Parse$
    #2 = Class              #1            // argonaut/Parse$
    #3 = Utf8               Ljava/lang/Object;Largonaut/Parse<Ljava/lang/String;>;
    #4 = Utf8               java/lang/Object
    #5 = Class              #4            // java/lang/Object
    #6 = Utf8               argonaut/Parse
    #7 = Class              #6            // argonaut/Parse
    #8 = Utf8               Parse.scala
    #9 = Utf8               MODULE$
   #10 = Utf8               Largonaut/Parse$;
   #11 = Utf8               <clinit>
   #12 = Utf8               ()V
   #13 = Utf8               <init>
   #14 = NameAndType        #13:#12       // "<init>":()V
   #15 = Methodref          #2.#14        // argonaut/Parse$."<init>":()V
   #16 = NameAndType        #9:#10        // MODULE$:Largonaut/Parse$;
   #17 = Fieldref           #2.#16        // argonaut/Parse$.MODULE$:Largonaut/Parse$;
   #18 = Utf8               $init$
   #19 = Utf8               (Largonaut/Parse;)V
   #20 = NameAndType        #18:#19       // $init$:(Largonaut/Parse;)V
   #21 = InterfaceMethodref #7.#20        // argonaut/Parse.$init$:(Largonaut/Parse;)V
   #22 = Utf8               parseWith
   #23 = Utf8               (Ljava/lang/Object;Lscala/Function1;Lscala/Function1;)Ljava/lang/Object;
   #24 = Utf8               value
   #25 = Utf8               success
   #26 = Utf8               failure
   #27 = Utf8               parseWith$
   #28 = Utf8               (Largonaut/Parse;Ljava/lang/Object;Lscala/Function1;Lscala/Function1;)Ljava/lang/Object;
   #29 = NameAndType        #27:#28       // parseWith$:(Largonaut/Parse;Ljava/lang/Object;Lscala/Function1;Lscala/Function1;)Ljava/lang/Object;
   #30 = InterfaceMethodref #7.#29        // argonaut/Parse.parseWith$:(Largonaut/Parse;Ljava/lang/Object;Lscala/Function1;Lscala/Function1;)Ljava/lang/Object;
   #31 = Utf8               this
   #32 = Utf8               Ljava/lang/Object;
   #33 = Utf8               Lscala/Function1;
   #34 = Utf8               parseOr
   #35 = Utf8               (Ljava/lang/Object;Lscala/Function1;Lscala/Function0;)Ljava/lang/Object;
   #36 = Utf8               parseOr$
   #37 = Utf8               (Largonaut/Parse;Ljava/lang/Object;Lscala/Function1;Lscala/Function0;)Ljava/lang/Object;
   #38 = NameAndType        #36:#37       // parseOr$:(Largonaut/Parse;Ljava/lang/Object;Lscala/Function1;Lscala/Function0;)Ljava/lang/Object;
   #39 = InterfaceMethodref #7.#38        // argonaut/Parse.parseOr$:(Largonaut/Parse;Ljava/lang/Object;Lscala/Function1;Lscala/Function0;)Ljava/lang/Object;
   #40 = Utf8               Lscala/Function0;
   #41 = Utf8               parseOption
   #42 = Utf8               (Ljava/lang/Object;)Lscala/Option;
   #43 = Utf8               parseOption$
   #44 = Utf8               (Largonaut/Parse;Ljava/lang/Object;)Lscala/Option;
   #45 = NameAndType        #43:#44       // parseOption$:(Largonaut/Parse;Ljava/lang/Object;)Lscala/Option;
   #46 = InterfaceMethodref #7.#45        // argonaut/Parse.parseOption$:(Largonaut/Parse;Ljava/lang/Object;)Lscala/Option;
   #47 = Utf8               decode
   #48 = Utf8               (Ljava/lang/Object;Largonaut/DecodeJson;)Lscala/util/Either;
   #49 = Utf8               evidence$1
   #50 = Utf8               decode$
   #51 = Utf8               (Largonaut/Parse;Ljava/lang/Object;Largonaut/DecodeJson;)Lscala/util/Either;
   #52 = NameAndType        #50:#51       // decode$:(Largonaut/Parse;Ljava/lang/Object;Largonaut/DecodeJson;)Lscala/util/Either;
   #53 = InterfaceMethodref #7.#52        // argonaut/Parse.decode$:(Largonaut/Parse;Ljava/lang/Object;Largonaut/DecodeJson;)Lscala/util/Either;
   #54 = Utf8               Largonaut/DecodeJson;
   #55 = Utf8               decodeWith
   #56 = Utf8               (Ljava/lang/Object;Lscala/Function1;Lscala/Function1;Lscala/Function2;Largonaut/DecodeJson;)Ljava/lang/Object;
   #57 = Utf8               parsefailure
   #58 = Utf8               decodefailure
   #59 = Utf8               evidence$2
   #60 = Utf8               decodeWith$
   #61 = Utf8               (Largonaut/Parse;Ljava/lang/Object;Lscala/Function1;Lscala/Function1;Lscala/Function2;Largonaut/DecodeJson;)Ljava/lang/Object;
   #62 = NameAndType        #60:#61       // decodeWith$:(Largonaut/Parse;Ljava/lang/Object;Lscala/Function1;Lscala/Function1;Lscala/Function2;Largonaut/DecodeJson;)Ljava/lang/Object;
   #63 = InterfaceMethodref #7.#62        // argonaut/Parse.decodeWith$:(Largonaut/Parse;Ljava/lang/Object;Lscala/Function1;Lscala/Function1;Lscala/Function2;Largonaut/DecodeJson;)Ljava/lang/Object;
   #64 = Utf8               Lscala/Function2;
   #65 = Utf8               decodeWithEither
   #66 = Utf8               (Ljava/lang/Object;Lscala/Function1;Lscala/Function1;Largonaut/DecodeJson;)Ljava/lang/Object;
   #67 = Utf8               evidence$3
   #68 = Utf8               decodeWithEither$
   #69 = Utf8               (Largonaut/Parse;Ljava/lang/Object;Lscala/Function1;Lscala/Function1;Largonaut/DecodeJson;)Ljava/lang/Object;
   #70 = NameAndType        #68:#69       // decodeWithEither$:(Largonaut/Parse;Ljava/lang/Object;Lscala/Function1;Lscala/Function1;Largonaut/DecodeJson;)Ljava/lang/Object;
   #71 = InterfaceMethodref #7.#70        // argonaut/Parse.decodeWithEither$:(Largonaut/Parse;Ljava/lang/Object;Lscala/Function1;Lscala/Function1;Largonaut/DecodeJson;)Ljava/lang/Object;
   #72 = Utf8               decodeWithMessage
   #73 = Utf8               evidence$4
   #74 = Utf8               decodeWithMessage$
   #75 = NameAndType        #74:#69       // decodeWithMessage$:(Largonaut/Parse;Ljava/lang/Object;Lscala/Function1;Lscala/Function1;Largonaut/DecodeJson;)Ljava/lang/Object;
   #76 = InterfaceMethodref #7.#75        // argonaut/Parse.decodeWithMessage$:(Largonaut/Parse;Ljava/lang/Object;Lscala/Function1;Lscala/Function1;Largonaut/DecodeJson;)Ljava/lang/Object;
   #77 = Utf8               decodeOr
   #78 = Utf8               (Ljava/lang/Object;Lscala/Function1;Lscala/Function0;Largonaut/DecodeJson;)Ljava/lang/Object;
   #79 = Utf8               default
   #80 = Utf8               evidence$5
   #81 = Utf8               decodeOr$
   #82 = Utf8               (Largonaut/Parse;Ljava/lang/Object;Lscala/Function1;Lscala/Function0;Largonaut/DecodeJson;)Ljava/lang/Object;
   #83 = NameAndType        #81:#82       // decodeOr$:(Largonaut/Parse;Ljava/lang/Object;Lscala/Function1;Lscala/Function0;Largonaut/DecodeJson;)Ljava/lang/Object;
   #84 = InterfaceMethodref #7.#83        // argonaut/Parse.decodeOr$:(Largonaut/Parse;Ljava/lang/Object;Lscala/Function1;Lscala/Function0;Largonaut/DecodeJson;)Ljava/lang/Object;
   #85 = Utf8               decodeOption
   #86 = Utf8               (Ljava/lang/Object;Largonaut/DecodeJson;)Lscala/Option;
   #87 = Utf8               evidence$6
   #88 = Utf8               decodeOption$
   #89 = Utf8               (Largonaut/Parse;Ljava/lang/Object;Largonaut/DecodeJson;)Lscala/Option;
   #90 = NameAndType        #88:#89       // decodeOption$:(Largonaut/Parse;Ljava/lang/Object;Largonaut/DecodeJson;)Lscala/Option;
   #91 = InterfaceMethodref #7.#90        // argonaut/Parse.decodeOption$:(Largonaut/Parse;Ljava/lang/Object;Largonaut/DecodeJson;)Lscala/Option;
   #92 = Utf8               decodeEither
   #93 = Utf8               evidence$7
   #94 = Utf8               decodeEither$
   #95 = NameAndType        #94:#51       // decodeEither$:(Largonaut/Parse;Ljava/lang/Object;Largonaut/DecodeJson;)Lscala/util/Either;
   #96 = InterfaceMethodref #7.#95        // argonaut/Parse.decodeEither$:(Largonaut/Parse;Ljava/lang/Object;Largonaut/DecodeJson;)Lscala/util/Either;
   #97 = Utf8               parse
   #98 = Utf8               (Ljava/lang/String;)Lscala/util/Either;
   #99 = Utf8               (Ljava/lang/String;)Lscala/util/Either<Ljava/lang/String;Largonaut/Json;>;
  #100 = Utf8               argonaut/JsonParser$
  #101 = Class              #100          // argonaut/JsonParser$
  #102 = Utf8               Largonaut/JsonParser$;
  #103 = NameAndType        #9:#102       // MODULE$:Largonaut/JsonParser$;
  #104 = Fieldref           #101.#103     // argonaut/JsonParser$.MODULE$:Largonaut/JsonParser$;
  #105 = NameAndType        #97:#98       // parse:(Ljava/lang/String;)Lscala/util/Either;
  #106 = Methodref          #101.#105     // argonaut/JsonParser$.parse:(Ljava/lang/String;)Lscala/util/Either;
  #107 = Utf8               Ljava/lang/String;
  #108 = Utf8               (Ljava/lang/Object;)Lscala/util/Either;
  #109 = Utf8               java/lang/String
  #110 = Class              #109          // java/lang/String
  #111 = Methodref          #2.#105       // argonaut/Parse$.parse:(Ljava/lang/String;)Lscala/util/Either;
  #112 = Methodref          #5.#14        // java/lang/Object."<init>":()V
  #113 = Utf8               Code
  #114 = Utf8               LineNumberTable
  #115 = Utf8               LocalVariableTable
  #116 = Utf8               MethodParameters
  #117 = Utf8               Signature
  #118 = Utf8               SourceFile
  #119 = Utf8               ScalaInlineInfo
  #120 = Utf8               Scala
{
  public static final argonaut.Parse$ MODULE$;
    descriptor: Largonaut/Parse$;
    flags: (0x0019) ACC_PUBLIC, ACC_STATIC, ACC_FINAL

  public static {};
    descriptor: ()V
    flags: (0x0009) ACC_PUBLIC, ACC_STATIC
    Code:
      stack=2, locals=0, args_size=0
         0: new           #2                  // class argonaut/Parse$
         3: dup
         4: invokespecial #15                 // Method "<init>":()V
         7: putstatic     #17                 // Field MODULE$:Largonaut/Parse$;
        10: getstatic     #17                 // Field MODULE$:Largonaut/Parse$;
        13: invokestatic  #21                 // InterfaceMethod argonaut/Parse.$init$:(Largonaut/Parse;)V
        16: return
      LineNumberTable:
        line 111: 0

  public java.lang.Object parseWith(java.lang.Object, scala.Function1, scala.Function1);
    descriptor: (Ljava/lang/Object;Lscala/Function1;Lscala/Function1;)Ljava/lang/Object;
    flags: (0x0001) ACC_PUBLIC
    Code:
      stack=4, locals=4, args_size=4
         0: aload_0
         1: aload_1
         2: aload_2
         3: aload_3
         4: invokestatic  #30                 // InterfaceMethod argonaut/Parse.parseWith$:(Largonaut/Parse;Ljava/lang/Object;Lscala/Function1;Lscala/Function1;)Ljava/lang/Object;
         7: areturn
      LineNumberTable:
        line 111: 0
      LocalVariableTable:
        Start  Length  Slot  Name   Signature
            0       8     0  this   Largonaut/Parse$;
            0       8     1 value   Ljava/lang/Object;
            0       8     2 success   Lscala/Function1;
            0       8     3 failure   Lscala/Function1;
    MethodParameters:
      Name                           Flags
      value                          final
      success                        final
      failure                        final

  public java.lang.Object parseOr(java.lang.Object, scala.Function1, scala.Function0);
    descriptor: (Ljava/lang/Object;Lscala/Function1;Lscala/Function0;)Ljava/lang/Object;
    flags: (0x0001) ACC_PUBLIC
    Code:
      stack=4, locals=4, args_size=4
         0: aload_0
         1: aload_1
         2: aload_2
         3: aload_3
         4: invokestatic  #39                 // InterfaceMethod argonaut/Parse.parseOr$:(Largonaut/Parse;Ljava/lang/Object;Lscala/Function1;Lscala/Function0;)Ljava/lang/Object;
         7: areturn
      LineNumberTable:
        line 111: 0
      LocalVariableTable:
        Start  Length  Slot  Name   Signature
            0       8     0  this   Largonaut/Parse$;
            0       8     1 value   Ljava/lang/Object;
            0       8     2 success   Lscala/Function1;
            0       8     3 failure   Lscala/Function0;
    MethodParameters:
      Name                           Flags
      value                          final
      success                        final
      failure                        final

  public scala.Option parseOption(java.lang.Object);
    descriptor: (Ljava/lang/Object;)Lscala/Option;
    flags: (0x0001) ACC_PUBLIC
    Code:
      stack=2, locals=2, args_size=2
         0: aload_0
         1: aload_1
         2: invokestatic  #46                 // InterfaceMethod argonaut/Parse.parseOption$:(Largonaut/Parse;Ljava/lang/Object;)Lscala/Option;
         5: areturn
      LineNumberTable:
        line 111: 0
      LocalVariableTable:
        Start  Length  Slot  Name   Signature
            0       6     0  this   Largonaut/Parse$;
            0       6     1 value   Ljava/lang/Object;
    MethodParameters:
      Name                           Flags
      value                          final

  public scala.util.Either decode(java.lang.Object, argonaut.DecodeJson);
    descriptor: (Ljava/lang/Object;Largonaut/DecodeJson;)Lscala/util/Either;
    flags: (0x0001) ACC_PUBLIC
    Code:
      stack=3, locals=3, args_size=3
         0: aload_0
         1: aload_1
         2: aload_2
         3: invokestatic  #53                 // InterfaceMethod argonaut/Parse.decode$:(Largonaut/Parse;Ljava/lang/Object;Largonaut/DecodeJson;)Lscala/util/Either;
         6: areturn
      LineNumberTable:
        line 111: 0
      LocalVariableTable:
        Start  Length  Slot  Name   Signature
            0       7     0  this   Largonaut/Parse$;
            0       7     1 value   Ljava/lang/Object;
            0       7     2 evidence$1   Largonaut/DecodeJson;
    MethodParameters:
      Name                           Flags
      value                          final
      evidence$1                     final

  public java.lang.Object decodeWith(java.lang.Object, scala.Function1, scala.Function1, scala.Function2, argonaut.DecodeJson);
    descriptor: (Ljava/lang/Object;Lscala/Function1;Lscala/Function1;Lscala/Function2;Largonaut/DecodeJson;)Ljava/lang/Object;
    flags: (0x0001) ACC_PUBLIC
    Code:
      stack=6, locals=6, args_size=6
         0: aload_0
         1: aload_1
         2: aload_2
         3: aload_3
         4: aload         4
         6: aload         5
         8: invokestatic  #63                 // InterfaceMethod argonaut/Parse.decodeWith$:(Largonaut/Parse;Ljava/lang/Object;Lscala/Function1;Lscala/Function1;Lscala/Function2;Largonaut/DecodeJson;)Ljava/lang/Object;
        11: areturn
      LineNumberTable:
        line 111: 0
      LocalVariableTable:
        Start  Length  Slot  Name   Signature
            0      12     0  this   Largonaut/Parse$;
            0      12     1 value   Ljava/lang/Object;
            0      12     2 success   Lscala/Function1;
            0      12     3 parsefailure   Lscala/Function1;
            0      12     4 decodefailure   Lscala/Function2;
            0      12     5 evidence$2   Largonaut/DecodeJson;
    MethodParameters:
      Name                           Flags
      value                          final
      success                        final
      parsefailure                   final
      decodefailure                  final
      evidence$2                     final

  public java.lang.Object decodeWithEither(java.lang.Object, scala.Function1, scala.Function1, argonaut.DecodeJson);
    descriptor: (Ljava/lang/Object;Lscala/Function1;Lscala/Function1;Largonaut/DecodeJson;)Ljava/lang/Object;
    flags: (0x0001) ACC_PUBLIC
    Code:
      stack=5, locals=5, args_size=5
         0: aload_0
         1: aload_1
         2: aload_2
         3: aload_3
         4: aload         4
         6: invokestatic  #71                 // InterfaceMethod argonaut/Parse.decodeWithEither$:(Largonaut/Parse;Ljava/lang/Object;Lscala/Function1;Lscala/Function1;Largonaut/DecodeJson;)Ljava/lang/Object;
         9: areturn
      LineNumberTable:
        line 111: 0
      LocalVariableTable:
        Start  Length  Slot  Name   Signature
            0      10     0  this   Largonaut/Parse$;
            0      10     1 value   Ljava/lang/Object;
            0      10     2 success   Lscala/Function1;
            0      10     3 failure   Lscala/Function1;
            0      10     4 evidence$3   Largonaut/DecodeJson;
    MethodParameters:
      Name                           Flags
      value                          final
      success                        final
      failure                        final
      evidence$3                     final

  public java.lang.Object decodeWithMessage(java.lang.Object, scala.Function1, scala.Function1, argonaut.DecodeJson);
    descriptor: (Ljava/lang/Object;Lscala/Function1;Lscala/Function1;Largonaut/DecodeJson;)Ljava/lang/Object;
    flags: (0x0001) ACC_PUBLIC
    Code:
      stack=5, locals=5, args_size=5
         0: aload_0
         1: aload_1
         2: aload_2
         3: aload_3
         4: aload         4
         6: invokestatic  #76                 // InterfaceMethod argonaut/Parse.decodeWithMessage$:(Largonaut/Parse;Ljava/lang/Object;Lscala/Function1;Lscala/Function1;Largonaut/DecodeJson;)Ljava/lang/Object;
         9: areturn
      LineNumberTable:
        line 111: 0
      LocalVariableTable:
        Start  Length  Slot  Name   Signature
            0      10     0  this   Largonaut/Parse$;
            0      10     1 value   Ljava/lang/Object;
            0      10     2 success   Lscala/Function1;
            0      10     3 failure   Lscala/Function1;
            0      10     4 evidence$4   Largonaut/DecodeJson;
    MethodParameters:
      Name                           Flags
      value                          final
      success                        final
      failure                        final
      evidence$4                     final

  public java.lang.Object decodeOr(java.lang.Object, scala.Function1, scala.Function0, argonaut.DecodeJson);
    descriptor: (Ljava/lang/Object;Lscala/Function1;Lscala/Function0;Largonaut/DecodeJson;)Ljava/lang/Object;
    flags: (0x0001) ACC_PUBLIC
    Code:
      stack=5, locals=5, args_size=5
         0: aload_0
         1: aload_1
         2: aload_2
         3: aload_3
         4: aload         4
         6: invokestatic  #84                 // InterfaceMethod argonaut/Parse.decodeOr$:(Largonaut/Parse;Ljava/lang/Object;Lscala/Function1;Lscala/Function0;Largonaut/DecodeJson;)Ljava/lang/Object;
         9: areturn
      LineNumberTable:
        line 111: 0
      LocalVariableTable:
        Start  Length  Slot  Name   Signature
            0      10     0  this   Largonaut/Parse$;
            0      10     1 value   Ljava/lang/Object;
            0      10     2 success   Lscala/Function1;
            0      10     3 default   Lscala/Function0;
            0      10     4 evidence$5   Largonaut/DecodeJson;
    MethodParameters:
      Name                           Flags
      value                          final
      success                        final
      default                        final
      evidence$5                     final

  public scala.Option decodeOption(java.lang.Object, argonaut.DecodeJson);
    descriptor: (Ljava/lang/Object;Largonaut/DecodeJson;)Lscala/Option;
    flags: (0x0001) ACC_PUBLIC
    Code:
      stack=3, locals=3, args_size=3
         0: aload_0
         1: aload_1
         2: aload_2
         3: invokestatic  #91                 // InterfaceMethod argonaut/Parse.decodeOption$:(Largonaut/Parse;Ljava/lang/Object;Largonaut/DecodeJson;)Lscala/Option;
         6: areturn
      LineNumberTable:
        line 111: 0
      LocalVariableTable:
        Start  Length  Slot  Name   Signature
            0       7     0  this   Largonaut/Parse$;
            0       7     1 value   Ljava/lang/Object;
            0       7     2 evidence$6   Largonaut/DecodeJson;
    MethodParameters:
      Name                           Flags
      value                          final
      evidence$6                     final

  public scala.util.Either decodeEither(java.lang.Object, argonaut.DecodeJson);
    descriptor: (Ljava/lang/Object;Largonaut/DecodeJson;)Lscala/util/Either;
    flags: (0x0001) ACC_PUBLIC
    Code:
      stack=3, locals=3, args_size=3
         0: aload_0
         1: aload_1
         2: aload_2
         3: invokestatic  #96                 // InterfaceMethod argonaut/Parse.decodeEither$:(Largonaut/Parse;Ljava/lang/Object;Largonaut/DecodeJson;)Lscala/util/Either;
         6: areturn
      LineNumberTable:
        line 111: 0
      LocalVariableTable:
        Start  Length  Slot  Name   Signature
            0       7     0  this   Largonaut/Parse$;
            0       7     1 value   Ljava/lang/Object;
            0       7     2 evidence$7   Largonaut/DecodeJson;
    MethodParameters:
      Name                           Flags
      value                          final
      evidence$7                     final

  public scala.util.Either<java.lang.String, argonaut.Json> parse(java.lang.String);
    descriptor: (Ljava/lang/String;)Lscala/util/Either;
    flags: (0x0001) ACC_PUBLIC
    Code:
      stack=2, locals=2, args_size=2
         0: getstatic     #104                // Field argonaut/JsonParser$.MODULE$:Largonaut/JsonParser$;
         3: aload_1
         4: invokevirtual #106                // Method argonaut/JsonParser$.parse:(Ljava/lang/String;)Lscala/util/Either;
         7: areturn
      LineNumberTable:
        line 118: 0
      LocalVariableTable:
        Start  Length  Slot  Name   Signature
            0       8     0  this   Largonaut/Parse$;
            0       8     1 value   Ljava/lang/String;
    Signature: #99                          // (Ljava/lang/String;)Lscala/util/Either<Ljava/lang/String;Largonaut/Json;>;
    MethodParameters:
      Name                           Flags
      value                          final

  public scala.util.Either parse(java.lang.Object);
    descriptor: (Ljava/lang/Object;)Lscala/util/Either;
    flags: (0x1041) ACC_PUBLIC, ACC_BRIDGE, ACC_SYNTHETIC
    Code:
      stack=2, locals=2, args_size=2
         0: aload_0
         1: aload_1
         2: checkcast     #110                // class java/lang/String
         5: invokevirtual #111                // Method parse:(Ljava/lang/String;)Lscala/util/Either;
         8: areturn
      LineNumberTable:
        line 111: 0
      LocalVariableTable:
        Start  Length  Slot  Name   Signature
            0       9     0  this   Largonaut/Parse$;
            0       9     1 value   Ljava/lang/Object;
    MethodParameters:
      Name                           Flags
      value                          final

  private argonaut.Parse$();
    descriptor: ()V
    flags: (0x0002) ACC_PRIVATE
    Code:
      stack=1, locals=1, args_size=1
         0: aload_0
         1: invokespecial #112                // Method java/lang/Object."<init>":()V
         4: return
      LineNumberTable:
        line 111: 0
      LocalVariableTable:
        Start  Length  Slot  Name   Signature
            0       5     0  this   Largonaut/Parse$;
}
Signature: #3                           // Ljava/lang/Object;Largonaut/Parse<Ljava/lang/String;>;
SourceFile: "Parse.scala"
  ScalaInlineInfo: length = 0x45 (unknown attribute)
   01 01 00 0D 00 0D 00 0C 01 00 2F 00 30 01 00 5C
   00 30 01 00 55 00 56 01 00 4D 00 4E 01 00 37 00
   38 01 00 41 00 42 01 00 48 00 42 01 00 61 00 6C
   01 00 61 00 62 01 00 29 00 2A 01 00 22 00 23 01
   00 16 00 17 01
  Scala: length = 0x0 (unknown attribute)

