Classfile /Users/mw/Projects/slang-braindump/.jar/jar8/assemble/slang-braindump/assemble/content/scala/util/control/NoStackTrace.class
  Last modified May 29, 2022; size 1610 bytes
  SHA-256 checksum f75362fa5fdf7442fa0827e66192a96fc03f882a358144f1cc006afda391dbe4
  Compiled from "NoStackTrace.scala"
public interface scala.util.control.NoStackTrace
  minor version: 0
  major version: 52
  flags: (0x0601) ACC_PUBLIC, ACC_INTERFACE, ACC_ABSTRACT
  this_class: #2                          // scala/util/control/NoStackTrace
  super_class: #4                         // java/lang/Object
  interfaces: 0, fields: 0, methods: 5, attributes: 4
Constant pool:
   #1 = Utf8               scala/util/control/NoStackTrace
   #2 = Class              #1             // scala/util/control/NoStackTrace
   #3 = Utf8               java/lang/Object
   #4 = Class              #3             // java/lang/Object
   #5 = Utf8               NoStackTrace.scala
   #6 = Utf8               Lscala/reflect/ScalaSignature;
   #7 = Utf8               bytes
   #8 = Utf8               \u0006\u0005\u00193qAC\u0006\u0011\u0002\u0007\u0005!\u0003C\u0003\u001c\u0001\u0011\u0005A\u0004C\u0003!\u0001\u0011\u0005\u0013\u0005C\u0006#\u0001A\u0005\u0019\u0011!A\u0005\n\rZs!\u0002\u0017\f\u0011\u0003ic!\u0002\u0006\f\u0011\u0003y\u0003\"B\u001d\u0006\t\u0003Q\u0004\"B\u001e\u0006\t\u000ba\u0004B\u0002!\u0006A\u00036Q\bC\u0004B\u000b\u0005\u0005I\u0011\u0002\"\u0003\u00199{7\u000b^1dWR\u0013\u0018mY3\u000b\u00051i\u0011aB2p]R\u0014x\u000e\u001c\u0006\u0003\u001d=\tA!\u001e;jY*\t\u0001#A\u0003tG\u0006d\u0017m\u0001\u0001\u0014\u0005\u0001\u0019\u0002C\u0001\u000b\u0019\u001d\t)b#D\u0001\u0010\u0013\t9r\"A\u0004qC\u000e\\\u0017mZ3\n\u0005eQ\"!\u0003+ie><\u0018M\u00197f\u0015\t9r\"\u0001\u0004%S:LG\u000f\n\u000b\u0002;A\u0011QCH\u0005\u0003?=\u0011A!\u00168ji\u0006\u0001b-\u001b7m\u0013:\u001cF/Y2l)J\f7-\u001a\u000b\u0002\'\u000512/\u001e9fe\u00122\u0017\u000e\u001c7J]N#\u0018mY6Ue\u0006\u001cW\rF\u0001%!\t)#&D\u0001\'\u0015\t9\u0003&\u0001\u0003mC:<\'\"A\u0015\u0002\t)\fg/Y\u0005\u00033\u0019J!\u0001\t\u0016\u0002\u00199{7\u000b^1dWR\u0013\u0018mY3\u0011\u00059*Q\"A\u0006\u0014\u0007\u0015\u00014\u0007\u0005\u0002\u0016c%\u0011!g\u0004\u0002\u0007\u0003:L(+\u001a4\u0011\u0005Q:T\"A\u001b\u000b\u0005YB\u0013AA5p\u0013\tATG\u0001\u0007TKJL\u0017\r\\5{C\ndW-\u0001\u0004=S:LGO\u0010\u000b\u0002[\u0005ian\\*vaB\u0014Xm]:j_:,\u0012!\u0010\t\u0003+yJ!aP\b\u0003\u000f\t{w\u000e\\3b]\u0006qqL\\8TkB\u0004(/Z:tS>t\u0017\u0001D<sSR,\'+\u001a9mC\u000e,G#A\"\u0011\u0005\u0015\"\u0015BA#\'\u0005\u0019y%M[3di\u0002
   #9 = Utf8               noSuppression
  #10 = Utf8               ()Z
  #11 = Utf8               scala/util/control/NoStackTrace$
  #12 = Class              #11            // scala/util/control/NoStackTrace$
  #13 = Utf8               MODULE$
  #14 = Utf8               Lscala/util/control/NoStackTrace$;
  #15 = NameAndType        #13:#14        // MODULE$:Lscala/util/control/NoStackTrace$;
  #16 = Fieldref           #12.#15        // scala/util/control/NoStackTrace$.MODULE$:Lscala/util/control/NoStackTrace$;
  #17 = NameAndType        #9:#10         // noSuppression:()Z
  #18 = Methodref          #12.#17        // scala/util/control/NoStackTrace$.noSuppression:()Z
  #19 = Utf8               scala$util$control$NoStackTrace$$super$fillInStackTrace
  #20 = Utf8               ()Ljava/lang/Throwable;
  #21 = Utf8               fillInStackTrace$
  #22 = Utf8               (Lscala/util/control/NoStackTrace;)Ljava/lang/Throwable;
  #23 = Utf8               $this
  #24 = Utf8               fillInStackTrace
  #25 = NameAndType        #24:#20        // fillInStackTrace:()Ljava/lang/Throwable;
  #26 = InterfaceMethodref #2.#25         // scala/util/control/NoStackTrace.fillInStackTrace:()Ljava/lang/Throwable;
  #27 = Utf8               Lscala/util/control/NoStackTrace;
  #28 = NameAndType        #19:#20        // scala$util$control$NoStackTrace$$super$fillInStackTrace:()Ljava/lang/Throwable;
  #29 = InterfaceMethodref #2.#28         // scala/util/control/NoStackTrace.scala$util$control$NoStackTrace$$super$fillInStackTrace:()Ljava/lang/Throwable;
  #30 = Utf8               java/lang/Throwable
  #31 = Class              #30            // java/lang/Throwable
  #32 = Utf8               this
  #33 = Utf8               $init$
  #34 = Utf8               (Lscala/util/control/NoStackTrace;)V
  #35 = Utf8               Code
  #36 = Utf8               LineNumberTable
  #37 = Utf8               LocalVariableTable
  #38 = Utf8               MethodParameters
  #39 = Utf8               StackMapTable
  #40 = Utf8               SourceFile
  #41 = Utf8               RuntimeVisibleAnnotations
  #42 = Utf8               ScalaInlineInfo
  #43 = Utf8               ScalaSig
{
  public static boolean noSuppression();
    descriptor: ()Z
    flags: (0x0009) ACC_PUBLIC, ACC_STATIC
    Code:
      stack=1, locals=0, args_size=0
         0: getstatic     #16                 // Field scala/util/control/NoStackTrace$.MODULE$:Lscala/util/control/NoStackTrace$;
         3: invokevirtual #18                 // Method scala/util/control/NoStackTrace$.noSuppression:()Z
         6: ireturn

  public abstract java.lang.Throwable scala$util$control$NoStackTrace$$super$fillInStackTrace();
    descriptor: ()Ljava/lang/Throwable;
    flags: (0x1401) ACC_PUBLIC, ACC_ABSTRACT, ACC_SYNTHETIC

  public static java.lang.Throwable fillInStackTrace$(scala.util.control.NoStackTrace);
    descriptor: (Lscala/util/control/NoStackTrace;)Ljava/lang/Throwable;
    flags: (0x1009) ACC_PUBLIC, ACC_STATIC, ACC_SYNTHETIC
    Code:
      stack=1, locals=1, args_size=1
         0: aload_0
         1: invokespecial #26                 // InterfaceMethod fillInStackTrace:()Ljava/lang/Throwable;
         4: areturn
      LineNumberTable:
        line 24: 0
      LocalVariableTable:
        Start  Length  Slot  Name   Signature
            0       5     0 $this   Lscala/util/control/NoStackTrace;
    MethodParameters:
      Name                           Flags
      $this                          final synthetic

  public default java.lang.Throwable fillInStackTrace();
    descriptor: ()Ljava/lang/Throwable;
    flags: (0x0001) ACC_PUBLIC
    Code:
      stack=1, locals=1, args_size=1
         0: getstatic     #16                 // Field scala/util/control/NoStackTrace$.MODULE$:Lscala/util/control/NoStackTrace$;
         3: invokevirtual #18                 // Method scala/util/control/NoStackTrace$.noSuppression:()Z
         6: ifeq          16
         9: aload_0
        10: invokeinterface #29,  1           // InterfaceMethod scala$util$control$NoStackTrace$$super$fillInStackTrace:()Ljava/lang/Throwable;
        15: areturn
        16: aload_0
        17: checkcast     #31                 // class java/lang/Throwable
        20: areturn
      StackMapTable: number_of_entries = 1
        frame_type = 16 /* same */
      LineNumberTable:
        line 25: 0
        line 26: 16
      LocalVariableTable:
        Start  Length  Slot  Name   Signature
            0      21     0  this   Lscala/util/control/NoStackTrace;

  public static void $init$(scala.util.control.NoStackTrace);
    descriptor: (Lscala/util/control/NoStackTrace;)V
    flags: (0x0009) ACC_PUBLIC, ACC_STATIC
    Code:
      stack=0, locals=1, args_size=1
         0: return
      LineNumberTable:
        line 23: 0
      LocalVariableTable:
        Start  Length  Slot  Name   Signature
            0       1     0 $this   Lscala/util/control/NoStackTrace;
    MethodParameters:
      Name                           Flags
      $this                          final synthetic
}
SourceFile: "NoStackTrace.scala"
RuntimeVisibleAnnotations:
  0: #6(#7=s#8)
    scala.reflect.ScalaSignature(
      bytes="\u0006\u0005\u00193qAC\u0006\u0011\u0002\u0007\u0005!\u0003C\u0003\u001c\u0001\u0011\u0005A\u0004C\u0003!\u0001\u0011\u0005\u0013\u0005C\u0006#\u0001A\u0005\u0019\u0011!A\u0005\n\rZs!\u0002\u0017\f\u0011\u0003ic!\u0002\u0006\f\u0011\u0003y\u0003\"B\u001d\u0006\t\u0003Q\u0004\"B\u001e\u0006\t\u000ba\u0004B\u0002!\u0006A\u00036Q\bC\u0004B\u000b\u0005\u0005I\u0011\u0002\"\u0003\u00199{7\u000b^1dWR\u0013\u0018mY3\u000b\u00051i\u0011aB2p]R\u0014x\u000e\u001c\u0006\u0003\u001d=\tA!\u001e;jY*\t\u0001#A\u0003tG\u0006d\u0017m\u0001\u0001\u0014\u0005\u0001\u0019\u0002C\u0001\u000b\u0019\u001d\t)b#D\u0001\u0010\u0013\t9r\"A\u0004qC\u000e\\\u0017mZ3\n\u0005eQ\"!\u0003+ie><\u0018M\u00197f\u0015\t9r\"\u0001\u0004%S:LG\u000f\n\u000b\u0002;A\u0011QCH\u0005\u0003?=\u0011A!\u00168ji\u0006\u0001b-\u001b7m\u0013:\u001cF/Y2l)J\f7-\u001a\u000b\u0002\'\u000512/\u001e9fe\u00122\u0017\u000e\u001c7J]N#\u0018mY6Ue\u0006\u001cW\rF\u0001%!\t)#&D\u0001\'\u0015\t9\u0003&\u0001\u0003mC:<\'\"A\u0015\u0002\t)\fg/Y\u0005\u00033\u0019J!\u0001\t\u0016\u0002\u00199{7\u000b^1dWR\u0013\u0018mY3\u0011\u00059*Q\"A\u0006\u0014\u0007\u0015\u00014\u0007\u0005\u0002\u0016c%\u0011!g\u0004\u0002\u0007\u0003:L(+\u001a4\u0011\u0005Q:T\"A\u001b\u000b\u0005YB\u0013AA5p\u0013\tATG\u0001\u0007TKJL\u0017\r\\5{C\ndW-\u0001\u0004=S:LGO\u0010\u000b\u0002[\u0005ian\\*vaB\u0014Xm]:j_:,\u0012!\u0010\t\u0003+yJ!aP\b\u0003\u000f\t{w\u000e\\3b]\u0006qqL\\8TkB\u0004(/Z:tS>t\u0017\u0001D<sSR,\'+\u001a9mC\u000e,G#A\"\u0011\u0005\u0015\"\u0015BA#\'\u0005\u0019y%M[3di\u0002"
    )
  ScalaInlineInfo: length = 0x18 (unknown attribute)
   01 00 00 04 00 21 00 22 01 00 18 00 14 00 00 15
   00 16 01 00 13 00 14 01
  ScalaSig: length = 0x3 (unknown attribute)
   05 02 00
