Classfile /Users/mw/Projects/slang-braindump/.jar/jar8/assemble/slang-braindump/assemble/content/scala/util/control/TailCalls$Done.class
  Last modified May 29, 2022; size 3193 bytes
  SHA-256 checksum 31d123d9e8f2063a6369b7da950e7df46256f99a41ff266b1ddd291558ed242e
  Compiled from "TailCalls.scala"
public class scala.util.control.TailCalls$Done<A extends java.lang.Object> extends scala.util.control.TailCalls$TailRec<A> implements scala.Product, java.io.Serializable
  minor version: 0
  major version: 52
  flags: (0x0021) ACC_PUBLIC, ACC_SUPER
  this_class: #2                          // scala/util/control/TailCalls$Done
  super_class: #5                         // scala/util/control/TailCalls$TailRec
  interfaces: 2, fields: 1, methods: 14, attributes: 5
Constant pool:
    #1 = Utf8               scala/util/control/TailCalls$Done
    #2 = Class              #1            // scala/util/control/TailCalls$Done
    #3 = Utf8               <A:Ljava/lang/Object;>Lscala/util/control/TailCalls$TailRec<TA;>;Lscala/Product;Ljava/io/Serializable;
    #4 = Utf8               scala/util/control/TailCalls$TailRec
    #5 = Class              #4            // scala/util/control/TailCalls$TailRec
    #6 = Utf8               scala/Product
    #7 = Class              #6            // scala/Product
    #8 = Utf8               java/io/Serializable
    #9 = Class              #8            // java/io/Serializable
   #10 = Utf8               TailCalls.scala
   #11 = Utf8               scala/runtime/ScalaRunTime$$anon$1
   #12 = Class              #11           // scala/runtime/ScalaRunTime$$anon$1
   #13 = Utf8               scala/util/control/TailCalls
   #14 = Class              #13           // scala/util/control/TailCalls
   #15 = Utf8               Done
   #16 = Utf8               TailRec
   #17 = Utf8               value
   #18 = Utf8               Ljava/lang/Object;
   #19 = Utf8               TA;
   #20 = Utf8               productElementNames
   #21 = Utf8               ()Lscala/collection/Iterator;
   #22 = Utf8               ()Lscala/collection/Iterator<Ljava/lang/String;>;
   #23 = Utf8               productElementNames$
   #24 = Utf8               (Lscala/Product;)Lscala/collection/Iterator;
   #25 = NameAndType        #23:#24       // productElementNames$:(Lscala/Product;)Lscala/collection/Iterator;
   #26 = InterfaceMethodref #7.#25        // scala/Product.productElementNames$:(Lscala/Product;)Lscala/collection/Iterator;
   #27 = Utf8               this
   #28 = Utf8               Lscala/util/control/TailCalls$Done;
   #29 = Utf8               ()Ljava/lang/Object;
   #30 = Utf8               ()TA;
   #31 = NameAndType        #17:#18       // value:Ljava/lang/Object;
   #32 = Fieldref           #2.#31        // scala/util/control/TailCalls$Done.value:Ljava/lang/Object;
   #33 = Utf8               copy
   #34 = Utf8               (Ljava/lang/Object;)Lscala/util/control/TailCalls$Done;
   #35 = Utf8               <A:Ljava/lang/Object;>(TA;)Lscala/util/control/TailCalls$Done<TA;>;
   #36 = Utf8               <init>
   #37 = Utf8               (Ljava/lang/Object;)V
   #38 = NameAndType        #36:#37       // "<init>":(Ljava/lang/Object;)V
   #39 = Methodref          #2.#38        // scala/util/control/TailCalls$Done."<init>":(Ljava/lang/Object;)V
   #40 = Utf8               copy$default$1
   #41 = Utf8               <A:Ljava/lang/Object;>()TA;
   #42 = NameAndType        #17:#29       // value:()Ljava/lang/Object;
   #43 = Methodref          #2.#42        // scala/util/control/TailCalls$Done.value:()Ljava/lang/Object;
   #44 = Utf8               productPrefix
   #45 = Utf8               ()Ljava/lang/String;
   #46 = String             #15           // Done
   #47 = Utf8               productArity
   #48 = Utf8               ()I
   #49 = Utf8               productElement
   #50 = Utf8               (I)Ljava/lang/Object;
   #51 = Utf8               x$1
   #52 = Utf8               scala/runtime/Statics
   #53 = Class              #52           // scala/runtime/Statics
   #54 = Utf8               ioobe
   #55 = NameAndType        #54:#50       // ioobe:(I)Ljava/lang/Object;
   #56 = Methodref          #53.#55       // scala/runtime/Statics.ioobe:(I)Ljava/lang/Object;
   #57 = Utf8               I
   #58 = Utf8               productIterator
   #59 = Utf8               ()Lscala/collection/Iterator<Ljava/lang/Object;>;
   #60 = Utf8               (Lscala/Product;)V
   #61 = NameAndType        #36:#60       // "<init>":(Lscala/Product;)V
   #62 = Methodref          #12.#61       // scala/runtime/ScalaRunTime$$anon$1."<init>":(Lscala/Product;)V
   #63 = Utf8               canEqual
   #64 = Utf8               (Ljava/lang/Object;)Z
   #65 = Utf8               productElementName
   #66 = Utf8               (I)Ljava/lang/String;
   #67 = String             #17           // value
   #68 = Utf8               java/lang/String
   #69 = Class              #68           // java/lang/String
   #70 = Utf8               hashCode
   #71 = Utf8               scala/util/hashing/MurmurHash3$
   #72 = Class              #71           // scala/util/hashing/MurmurHash3$
   #73 = Utf8               MODULE$
   #74 = Utf8               Lscala/util/hashing/MurmurHash3$;
   #75 = NameAndType        #73:#74       // MODULE$:Lscala/util/hashing/MurmurHash3$;
   #76 = Fieldref           #72.#75       // scala/util/hashing/MurmurHash3$.MODULE$:Lscala/util/hashing/MurmurHash3$;
   #77 = Utf8               productHash
   #78 = Utf8               (Lscala/Product;)I
   #79 = NameAndType        #77:#78       // productHash:(Lscala/Product;)I
   #80 = Methodref          #72.#79       // scala/util/hashing/MurmurHash3$.productHash:(Lscala/Product;)I
   #81 = Utf8               toString
   #82 = Utf8               scala/runtime/ScalaRunTime$
   #83 = Class              #82           // scala/runtime/ScalaRunTime$
   #84 = Utf8               Lscala/runtime/ScalaRunTime$;
   #85 = NameAndType        #73:#84       // MODULE$:Lscala/runtime/ScalaRunTime$;
   #86 = Fieldref           #83.#85       // scala/runtime/ScalaRunTime$.MODULE$:Lscala/runtime/ScalaRunTime$;
   #87 = Utf8               _toString
   #88 = Utf8               (Lscala/Product;)Ljava/lang/String;
   #89 = NameAndType        #87:#88       // _toString:(Lscala/Product;)Ljava/lang/String;
   #90 = Methodref          #83.#89       // scala/runtime/ScalaRunTime$._toString:(Lscala/Product;)Ljava/lang/String;
   #91 = Utf8               equals
   #92 = Utf8               scala/runtime/BoxesRunTime
   #93 = Class              #92           // scala/runtime/BoxesRunTime
   #94 = Utf8               (Ljava/lang/Object;Ljava/lang/Object;)Z
   #95 = NameAndType        #91:#94       // equals:(Ljava/lang/Object;Ljava/lang/Object;)Z
   #96 = Methodref          #93.#95       // scala/runtime/BoxesRunTime.equals:(Ljava/lang/Object;Ljava/lang/Object;)Z
   #97 = NameAndType        #63:#64       // canEqual:(Ljava/lang/Object;)Z
   #98 = Methodref          #2.#97        // scala/util/control/TailCalls$Done.canEqual:(Ljava/lang/Object;)Z
   #99 = Utf8               (TA;)V
  #100 = Utf8               ()V
  #101 = NameAndType        #36:#100      // "<init>":()V
  #102 = Methodref          #5.#101       // scala/util/control/TailCalls$TailRec."<init>":()V
  #103 = Utf8               Signature
  #104 = Utf8               Code
  #105 = Utf8               LineNumberTable
  #106 = Utf8               LocalVariableTable
  #107 = Utf8               MethodParameters
  #108 = Utf8               StackMapTable
  #109 = Utf8               InnerClasses
  #110 = Utf8               SourceFile
  #111 = Utf8               ScalaInlineInfo
  #112 = Utf8               Scala
{
  private final A value;
    descriptor: Ljava/lang/Object;
    flags: (0x0012) ACC_PRIVATE, ACC_FINAL
    Signature: #19                          // TA;

  public scala.collection.Iterator<java.lang.String> productElementNames();
    descriptor: ()Lscala/collection/Iterator;
    flags: (0x0001) ACC_PUBLIC
    Code:
      stack=1, locals=1, args_size=1
         0: aload_0
         1: invokestatic  #26                 // InterfaceMethod scala/Product.productElementNames$:(Lscala/Product;)Lscala/collection/Iterator;
         4: areturn
      LineNumberTable:
        line 95: 0
      LocalVariableTable:
        Start  Length  Slot  Name   Signature
            0       5     0  this   Lscala/util/control/TailCalls$Done;
    Signature: #22                          // ()Lscala/collection/Iterator<Ljava/lang/String;>;

  public A value();
    descriptor: ()Ljava/lang/Object;
    flags: (0x0001) ACC_PUBLIC
    Code:
      stack=1, locals=1, args_size=1
         0: aload_0
         1: getfield      #32                 // Field value:Ljava/lang/Object;
         4: areturn
      LineNumberTable:
        line 95: 0
      LocalVariableTable:
        Start  Length  Slot  Name   Signature
            0       5     0  this   Lscala/util/control/TailCalls$Done;
    Signature: #30                          // ()TA;

  public <A extends java.lang.Object> scala.util.control.TailCalls$Done<A> copy(A);
    descriptor: (Ljava/lang/Object;)Lscala/util/control/TailCalls$Done;
    flags: (0x0001) ACC_PUBLIC
    Code:
      stack=3, locals=2, args_size=2
         0: new           #2                  // class scala/util/control/TailCalls$Done
         3: dup
         4: aload_1
         5: invokespecial #39                 // Method "<init>":(Ljava/lang/Object;)V
         8: areturn
      LineNumberTable:
        line 95: 0
      LocalVariableTable:
        Start  Length  Slot  Name   Signature
            0       9     0  this   Lscala/util/control/TailCalls$Done;
            0       9     1 value   Ljava/lang/Object;
    Signature: #35                          // <A:Ljava/lang/Object;>(TA;)Lscala/util/control/TailCalls$Done<TA;>;
    MethodParameters:
      Name                           Flags
      value                          final

  public <A extends java.lang.Object> A copy$default$1();
    descriptor: ()Ljava/lang/Object;
    flags: (0x0001) ACC_PUBLIC
    Code:
      stack=1, locals=1, args_size=1
         0: aload_0
         1: invokevirtual #43                 // Method value:()Ljava/lang/Object;
         4: areturn
      LineNumberTable:
        line 95: 0
      LocalVariableTable:
        Start  Length  Slot  Name   Signature
            0       5     0  this   Lscala/util/control/TailCalls$Done;
    Signature: #41                          // <A:Ljava/lang/Object;>()TA;

  public java.lang.String productPrefix();
    descriptor: ()Ljava/lang/String;
    flags: (0x0001) ACC_PUBLIC
    Code:
      stack=1, locals=1, args_size=1
         0: ldc           #46                 // String Done
         2: areturn
      LineNumberTable:
        line 95: 0
      LocalVariableTable:
        Start  Length  Slot  Name   Signature
            0       3     0  this   Lscala/util/control/TailCalls$Done;

  public int productArity();
    descriptor: ()I
    flags: (0x0001) ACC_PUBLIC
    Code:
      stack=1, locals=1, args_size=1
         0: iconst_1
         1: ireturn
      LineNumberTable:
        line 95: 0
      LocalVariableTable:
        Start  Length  Slot  Name   Signature
            0       2     0  this   Lscala/util/control/TailCalls$Done;

  public java.lang.Object productElement(int);
    descriptor: (I)Ljava/lang/Object;
    flags: (0x0001) ACC_PUBLIC
    Code:
      stack=1, locals=2, args_size=2
         0: iload_1
         1: tableswitch   { // 0 to 0
                       0: 20
                 default: 25
            }
        20: aload_0
        21: invokevirtual #43                 // Method value:()Ljava/lang/Object;
        24: areturn
        25: iload_1
        26: invokestatic  #56                 // Method scala/runtime/Statics.ioobe:(I)Ljava/lang/Object;
        29: areturn
      StackMapTable: number_of_entries = 2
        frame_type = 20 /* same */
        frame_type = 4 /* same */
      LineNumberTable:
        line 95: 0
      LocalVariableTable:
        Start  Length  Slot  Name   Signature
            0      30     0  this   Lscala/util/control/TailCalls$Done;
            0      30     1   x$1   I
    MethodParameters:
      Name                           Flags
      x$1                            final

  public scala.collection.Iterator<java.lang.Object> productIterator();
    descriptor: ()Lscala/collection/Iterator;
    flags: (0x0001) ACC_PUBLIC
    Code:
      stack=3, locals=1, args_size=1
         0: new           #12                 // class scala/runtime/ScalaRunTime$$anon$1
         3: dup
         4: aload_0
         5: invokespecial #62                 // Method scala/runtime/ScalaRunTime$$anon$1."<init>":(Lscala/Product;)V
         8: areturn
      LineNumberTable:
        line 95: 0
      LocalVariableTable:
        Start  Length  Slot  Name   Signature
            0       9     0  this   Lscala/util/control/TailCalls$Done;
    Signature: #59                          // ()Lscala/collection/Iterator<Ljava/lang/Object;>;

  public boolean canEqual(java.lang.Object);
    descriptor: (Ljava/lang/Object;)Z
    flags: (0x0001) ACC_PUBLIC
    Code:
      stack=1, locals=2, args_size=2
         0: aload_1
         1: instanceof    #2                  // class scala/util/control/TailCalls$Done
         4: ireturn
      LineNumberTable:
        line 95: 0
      LocalVariableTable:
        Start  Length  Slot  Name   Signature
            0       5     0  this   Lscala/util/control/TailCalls$Done;
            0       5     1   x$1   Ljava/lang/Object;
    MethodParameters:
      Name                           Flags
      x$1                            final

  public java.lang.String productElementName(int);
    descriptor: (I)Ljava/lang/String;
    flags: (0x0001) ACC_PUBLIC
    Code:
      stack=1, locals=2, args_size=2
         0: iload_1
         1: tableswitch   { // 0 to 0
                       0: 20
                 default: 23
            }
        20: ldc           #67                 // String value
        22: areturn
        23: iload_1
        24: invokestatic  #56                 // Method scala/runtime/Statics.ioobe:(I)Ljava/lang/Object;
        27: checkcast     #69                 // class java/lang/String
        30: areturn
      StackMapTable: number_of_entries = 2
        frame_type = 20 /* same */
        frame_type = 2 /* same */
      LineNumberTable:
        line 95: 0
      LocalVariableTable:
        Start  Length  Slot  Name   Signature
            0      31     0  this   Lscala/util/control/TailCalls$Done;
            0      31     1   x$1   I
    MethodParameters:
      Name                           Flags
      x$1                            final

  public int hashCode();
    descriptor: ()I
    flags: (0x0001) ACC_PUBLIC
    Code:
      stack=2, locals=1, args_size=1
         0: getstatic     #76                 // Field scala/util/hashing/MurmurHash3$.MODULE$:Lscala/util/hashing/MurmurHash3$;
         3: aload_0
         4: invokevirtual #80                 // Method scala/util/hashing/MurmurHash3$.productHash:(Lscala/Product;)I
         7: ireturn
      LineNumberTable:
        line 95: 0
      LocalVariableTable:
        Start  Length  Slot  Name   Signature
            0       8     0  this   Lscala/util/control/TailCalls$Done;

  public java.lang.String toString();
    descriptor: ()Ljava/lang/String;
    flags: (0x0001) ACC_PUBLIC
    Code:
      stack=2, locals=1, args_size=1
         0: getstatic     #86                 // Field scala/runtime/ScalaRunTime$.MODULE$:Lscala/runtime/ScalaRunTime$;
         3: aload_0
         4: invokevirtual #90                 // Method scala/runtime/ScalaRunTime$._toString:(Lscala/Product;)Ljava/lang/String;
         7: areturn
      LineNumberTable:
        line 95: 0
      LocalVariableTable:
        Start  Length  Slot  Name   Signature
            0       8     0  this   Lscala/util/control/TailCalls$Done;

  public boolean equals(java.lang.Object);
    descriptor: (Ljava/lang/Object;)Z
    flags: (0x0001) ACC_PUBLIC
    Code:
      stack=2, locals=4, args_size=2
         0: aload_0
         1: aload_1
         2: if_acmpeq     58
         5: aload_1
         6: instanceof    #2                  // class scala/util/control/TailCalls$Done
         9: ifeq          17
        12: iconst_1
        13: istore_2
        14: goto          19
        17: iconst_0
        18: istore_2
        19: iload_2
        20: ifeq          60
        23: aload_1
        24: checkcast     #2                  // class scala/util/control/TailCalls$Done
        27: astore_3
        28: aload_0
        29: invokevirtual #43                 // Method value:()Ljava/lang/Object;
        32: aload_3
        33: invokevirtual #43                 // Method value:()Ljava/lang/Object;
        36: invokestatic  #96                 // Method scala/runtime/BoxesRunTime.equals:(Ljava/lang/Object;Ljava/lang/Object;)Z
        39: ifeq          54
        42: aload_3
        43: aload_0
        44: invokevirtual #98                 // Method canEqual:(Ljava/lang/Object;)Z
        47: ifeq          54
        50: iconst_1
        51: goto          55
        54: iconst_0
        55: ifeq          60
        58: iconst_1
        59: ireturn
        60: iconst_0
        61: ireturn
      StackMapTable: number_of_entries = 6
        frame_type = 17 /* same */
        frame_type = 252 /* append */
          offset_delta = 1
          locals = [ int ]
        frame_type = 252 /* append */
          offset_delta = 34
          locals = [ class scala/util/control/TailCalls$Done ]
        frame_type = 64 /* same_locals_1_stack_item */
          stack = [ int ]
        frame_type = 249 /* chop */
          offset_delta = 2
        frame_type = 252 /* append */
          offset_delta = 1
          locals = [ int ]
      LineNumberTable:
        line 95: 0
      LocalVariableTable:
        Start  Length  Slot  Name   Signature
            0      62     0  this   Lscala/util/control/TailCalls$Done;
            0      62     1   x$1   Ljava/lang/Object;
    MethodParameters:
      Name                           Flags
      x$1                            final

  public scala.util.control.TailCalls$Done(A);
    descriptor: (Ljava/lang/Object;)V
    flags: (0x0001) ACC_PUBLIC
    Code:
      stack=2, locals=2, args_size=2
         0: aload_0
         1: aload_1
         2: putfield      #32                 // Field value:Ljava/lang/Object;
         5: aload_0
         6: invokespecial #102                // Method scala/util/control/TailCalls$TailRec."<init>":()V
         9: return
      LineNumberTable:
        line 95: 0
      LocalVariableTable:
        Start  Length  Slot  Name   Signature
            0      10     0  this   Lscala/util/control/TailCalls$Done;
            0      10     1 value   Ljava/lang/Object;
    Signature: #99                          // (TA;)V
    MethodParameters:
      Name                           Flags
      value                          final
}
InnerClasses:
  public final #12;                       // class scala/runtime/ScalaRunTime$$anon$1
  public static #15= #2 of #14;           // Done=class scala/util/control/TailCalls$Done of class scala/util/control/TailCalls
  public static abstract #16= #5 of #14;  // TailRec=class scala/util/control/TailCalls$TailRec of class scala/util/control/TailCalls
Signature: #3                           // <A:Ljava/lang/Object;>Lscala/util/control/TailCalls$TailRec<TA;>;Lscala/Product;Ljava/io/Serializable;
SourceFile: "TailCalls.scala"
  ScalaInlineInfo: length = 0x4A (unknown attribute)
   01 00 00 0E 00 24 00 25 00 00 3F 00 40 00 00 21
   00 22 00 00 28 00 1D 00 00 5B 00 40 00 00 46 00
   30 00 00 2F 00 30 00 00 31 00 32 00 00 41 00 42
   00 00 14 00 15 00 00 3A 00 15 00 00 2C 00 2D 00
   00 51 00 2D 00 00 11 00 1D 00
  Scala: length = 0x0 (unknown attribute)

