Classfile /Users/mw/Projects/slang-braindump/.jar/jar8/assemble/slang-braindump/assemble/content/scala/util/control/TailCalls$Call$.class
  Last modified May 29, 2022; size 1842 bytes
  SHA-256 checksum d54f48308c13688d27beea71b4e03fdcb36c93dd908c0c1415aa8fa4c7f8ef9e
  Compiled from "TailCalls.scala"
public class scala.util.control.TailCalls$Call$ implements java.io.Serializable
  minor version: 0
  major version: 52
  flags: (0x0021) ACC_PUBLIC, ACC_SUPER
  this_class: #2                          // scala/util/control/TailCalls$Call$
  super_class: #4                         // java/lang/Object
  interfaces: 1, fields: 1, methods: 6, attributes: 4
Constant pool:
   #1 = Utf8               scala/util/control/TailCalls$Call$
   #2 = Class              #1             // scala/util/control/TailCalls$Call$
   #3 = Utf8               java/lang/Object
   #4 = Class              #3             // java/lang/Object
   #5 = Utf8               java/io/Serializable
   #6 = Class              #5             // java/io/Serializable
   #7 = Utf8               TailCalls.scala
   #8 = Utf8               scala/util/control/TailCalls$Call
   #9 = Class              #8             // scala/util/control/TailCalls$Call
  #10 = Utf8               scala/util/control/TailCalls
  #11 = Class              #10            // scala/util/control/TailCalls
  #12 = Utf8               Call
  #13 = Utf8               Call$
  #14 = Utf8               scala/util/control/TailCalls$TailRec
  #15 = Class              #14            // scala/util/control/TailCalls$TailRec
  #16 = Utf8               TailRec
  #17 = Utf8               MODULE$
  #18 = Utf8               Lscala/util/control/TailCalls$Call$;
  #19 = Utf8               <clinit>
  #20 = Utf8               ()V
  #21 = Utf8               <init>
  #22 = NameAndType        #21:#20        // "<init>":()V
  #23 = Methodref          #2.#22         // scala/util/control/TailCalls$Call$."<init>":()V
  #24 = NameAndType        #17:#18        // MODULE$:Lscala/util/control/TailCalls$Call$;
  #25 = Fieldref           #2.#24         // scala/util/control/TailCalls$Call$.MODULE$:Lscala/util/control/TailCalls$Call$;
  #26 = Utf8               toString
  #27 = Utf8               ()Ljava/lang/String;
  #28 = String             #12            // Call
  #29 = Utf8               this
  #30 = Utf8               apply
  #31 = Utf8               (Lscala/Function0;)Lscala/util/control/TailCalls$Call;
  #32 = Utf8               <A:Ljava/lang/Object;>(Lscala/Function0<Lscala/util/control/TailCalls$TailRec<TA;>;>;)Lscala/util/control/TailCalls$Call<TA;>;
  #33 = Utf8               rest
  #34 = Utf8               (Lscala/Function0;)V
  #35 = NameAndType        #21:#34        // "<init>":(Lscala/Function0;)V
  #36 = Methodref          #9.#35         // scala/util/control/TailCalls$Call."<init>":(Lscala/Function0;)V
  #37 = Utf8               Lscala/Function0;
  #38 = Utf8               unapply
  #39 = Utf8               (Lscala/util/control/TailCalls$Call;)Lscala/Option;
  #40 = Utf8               <A:Ljava/lang/Object;>(Lscala/util/control/TailCalls$Call<TA;>;)Lscala/Option<Lscala/Function0<Lscala/util/control/TailCalls$TailRec<TA;>;>;>;
  #41 = Utf8               x$0
  #42 = Utf8               scala/None$
  #43 = Class              #42            // scala/None$
  #44 = Utf8               Lscala/None$;
  #45 = NameAndType        #17:#44        // MODULE$:Lscala/None$;
  #46 = Fieldref           #43.#45        // scala/None$.MODULE$:Lscala/None$;
  #47 = Utf8               scala/Some
  #48 = Class              #47            // scala/Some
  #49 = Utf8               ()Lscala/Function0;
  #50 = NameAndType        #33:#49        // rest:()Lscala/Function0;
  #51 = Methodref          #9.#50         // scala/util/control/TailCalls$Call.rest:()Lscala/Function0;
  #52 = Utf8               (Ljava/lang/Object;)V
  #53 = NameAndType        #21:#52        // "<init>":(Ljava/lang/Object;)V
  #54 = Methodref          #48.#53        // scala/Some."<init>":(Ljava/lang/Object;)V
  #55 = Utf8               Lscala/util/control/TailCalls$Call;
  #56 = Utf8               writeReplace
  #57 = Utf8               ()Ljava/lang/Object;
  #58 = Utf8               scala/runtime/ModuleSerializationProxy
  #59 = Class              #58            // scala/runtime/ModuleSerializationProxy
  #60 = Utf8               (Ljava/lang/Class;)V
  #61 = NameAndType        #21:#60        // "<init>":(Ljava/lang/Class;)V
  #62 = Methodref          #59.#61        // scala/runtime/ModuleSerializationProxy."<init>":(Ljava/lang/Class;)V
  #63 = Methodref          #4.#22         // java/lang/Object."<init>":()V
  #64 = Utf8               Code
  #65 = Utf8               LineNumberTable
  #66 = Utf8               LocalVariableTable
  #67 = Utf8               Signature
  #68 = Utf8               MethodParameters
  #69 = Utf8               StackMapTable
  #70 = Utf8               InnerClasses
  #71 = Utf8               SourceFile
  #72 = Utf8               ScalaInlineInfo
  #73 = Utf8               Scala
{
  public static final scala.util.control.TailCalls$Call$ MODULE$;
    descriptor: Lscala/util/control/TailCalls$Call$;
    flags: (0x0019) ACC_PUBLIC, ACC_STATIC, ACC_FINAL

  public static {};
    descriptor: ()V
    flags: (0x0009) ACC_PUBLIC, ACC_STATIC
    Code:
      stack=2, locals=0, args_size=0
         0: new           #2                  // class scala/util/control/TailCalls$Call$
         3: dup
         4: invokespecial #23                 // Method "<init>":()V
         7: putstatic     #25                 // Field MODULE$:Lscala/util/control/TailCalls$Call$;
        10: return
      LineNumberTable:
        line 91: 0

  public final java.lang.String toString();
    descriptor: ()Ljava/lang/String;
    flags: (0x0011) ACC_PUBLIC, ACC_FINAL
    Code:
      stack=1, locals=1, args_size=1
         0: ldc           #28                 // String Call
         2: areturn
      LineNumberTable:
        line 91: 0
      LocalVariableTable:
        Start  Length  Slot  Name   Signature
            0       3     0  this   Lscala/util/control/TailCalls$Call$;

  public <A extends java.lang.Object> scala.util.control.TailCalls$Call<A> apply(scala.Function0<scala.util.control.TailCalls$TailRec<A>>);
    descriptor: (Lscala/Function0;)Lscala/util/control/TailCalls$Call;
    flags: (0x0001) ACC_PUBLIC
    Code:
      stack=3, locals=2, args_size=2
         0: new           #9                  // class scala/util/control/TailCalls$Call
         3: dup
         4: aload_1
         5: invokespecial #36                 // Method scala/util/control/TailCalls$Call."<init>":(Lscala/Function0;)V
         8: areturn
      LineNumberTable:
        line 91: 0
      LocalVariableTable:
        Start  Length  Slot  Name   Signature
            0       9     0  this   Lscala/util/control/TailCalls$Call$;
            0       9     1  rest   Lscala/Function0;
    Signature: #32                          // <A:Ljava/lang/Object;>(Lscala/Function0<Lscala/util/control/TailCalls$TailRec<TA;>;>;)Lscala/util/control/TailCalls$Call<TA;>;
    MethodParameters:
      Name                           Flags
      rest                           final

  public <A extends java.lang.Object> scala.Option<scala.Function0<scala.util.control.TailCalls$TailRec<A>>> unapply(scala.util.control.TailCalls$Call<A>);
    descriptor: (Lscala/util/control/TailCalls$Call;)Lscala/Option;
    flags: (0x0001) ACC_PUBLIC
    Code:
      stack=3, locals=2, args_size=2
         0: aload_1
         1: ifnonnull     8
         4: getstatic     #46                 // Field scala/None$.MODULE$:Lscala/None$;
         7: areturn
         8: new           #48                 // class scala/Some
        11: dup
        12: aload_1
        13: invokevirtual #51                 // Method scala/util/control/TailCalls$Call.rest:()Lscala/Function0;
        16: invokespecial #54                 // Method scala/Some."<init>":(Ljava/lang/Object;)V
        19: areturn
      StackMapTable: number_of_entries = 1
        frame_type = 8 /* same */
      LineNumberTable:
        line 91: 0
      LocalVariableTable:
        Start  Length  Slot  Name   Signature
            0      20     0  this   Lscala/util/control/TailCalls$Call$;
            0      20     1   x$0   Lscala/util/control/TailCalls$Call;
    Signature: #40                          // <A:Ljava/lang/Object;>(Lscala/util/control/TailCalls$Call<TA;>;)Lscala/Option<Lscala/Function0<Lscala/util/control/TailCalls$TailRec<TA;>;>;>;
    MethodParameters:
      Name                           Flags
      x$0                            final

  private java.lang.Object writeReplace();
    descriptor: ()Ljava/lang/Object;
    flags: (0x0002) ACC_PRIVATE
    Code:
      stack=3, locals=1, args_size=1
         0: new           #59                 // class scala/runtime/ModuleSerializationProxy
         3: dup
         4: ldc           #2                  // class scala/util/control/TailCalls$Call$
         6: invokespecial #62                 // Method scala/runtime/ModuleSerializationProxy."<init>":(Ljava/lang/Class;)V
         9: areturn
      LineNumberTable:
        line 91: 0
      LocalVariableTable:
        Start  Length  Slot  Name   Signature
            0      10     0  this   Lscala/util/control/TailCalls$Call$;

  public scala.util.control.TailCalls$Call$();
    descriptor: ()V
    flags: (0x0001) ACC_PUBLIC
    Code:
      stack=1, locals=1, args_size=1
         0: aload_0
         1: invokespecial #63                 // Method java/lang/Object."<init>":()V
         4: return
      LineNumberTable:
        line 91: 0
      LocalVariableTable:
        Start  Length  Slot  Name   Signature
            0       5     0  this   Lscala/util/control/TailCalls$Call$;
}
InnerClasses:
  public static #12= #9 of #11;           // Call=class scala/util/control/TailCalls$Call of class scala/util/control/TailCalls
  public static #13= #2 of #11;           // Call$=class scala/util/control/TailCalls$Call$ of class scala/util/control/TailCalls
  public static abstract #16= #15 of #11; // TailRec=class scala/util/control/TailCalls$TailRec of class scala/util/control/TailCalls
SourceFile: "TailCalls.scala"
  ScalaInlineInfo: length = 0x1D (unknown attribute)
   01 01 00 05 00 15 00 14 01 00 1E 00 1F 01 00 1A
   00 1B 01 00 26 00 27 01 00 38 00 39 01
  Scala: length = 0x0 (unknown attribute)

