Classfile /Users/mw/Projects/slang-braindump/.jar/jar11/assemble/slang-braindump/assemble/content/scala/util/matching/Regex$MatchIterator$$anon$4.class
  Last modified May 29, 2022; size 2742 bytes
  SHA-256 checksum 414465282bdb28730ffba5eaac9e51714379830f2426f781d56beceeb9a3a047
  Compiled from "Regex.scala"
public final class scala.util.matching.Regex$MatchIterator$$anon$4 extends scala.collection.AbstractIterator<scala.util.matching.Regex$Match> implements scala.util.matching.Regex$Replacement
  minor version: 0
  major version: 52
  flags: (0x0031) ACC_PUBLIC, ACC_FINAL, ACC_SUPER
  this_class: #2                          // scala/util/matching/Regex$MatchIterator$$anon$4
  super_class: #5                         // scala/collection/AbstractIterator
  interfaces: 1, fields: 2, methods: 9, attributes: 6
Constant pool:
    #1 = Utf8               scala/util/matching/Regex$MatchIterator$$anon$4
    #2 = Class              #1            // scala/util/matching/Regex$MatchIterator$$anon$4
    #3 = Utf8               Lscala/collection/AbstractIterator<Lscala/util/matching/Regex$Match;>;Lscala/util/matching/Regex$Replacement;
    #4 = Utf8               scala/collection/AbstractIterator
    #5 = Class              #4            // scala/collection/AbstractIterator
    #6 = Utf8               scala/util/matching/Regex$Replacement
    #7 = Class              #6            // scala/util/matching/Regex$Replacement
    #8 = Utf8               Regex.scala
    #9 = Utf8               scala/util/matching/Regex$MatchIterator
   #10 = Class              #9            // scala/util/matching/Regex$MatchIterator
   #11 = Utf8               replacementData
   #12 = Utf8               ()Lscala/collection/AbstractIterator;
   #13 = NameAndType        #11:#12       // replacementData:()Lscala/collection/AbstractIterator;
   #14 = Utf8               scala/util/matching/Regex$Match
   #15 = Class              #14           // scala/util/matching/Regex$Match
   #16 = Utf8               scala/util/matching/Regex
   #17 = Class              #16           // scala/util/matching/Regex
   #18 = Utf8               Match
   #19 = Utf8               MatchIterator
   #20 = Utf8               Replacement
   #21 = Utf8               scala$util$matching$Regex$Replacement$$sb
   #22 = Utf8               Ljava/lang/StringBuffer;
   #23 = Utf8               $outer
   #24 = Utf8               Lscala/util/matching/Regex$MatchIterator;
   #25 = Utf8               replaced
   #26 = Utf8               ()Ljava/lang/String;
   #27 = Utf8               replaced$
   #28 = Utf8               (Lscala/util/matching/Regex$Replacement;)Ljava/lang/String;
   #29 = NameAndType        #27:#28       // replaced$:(Lscala/util/matching/Regex$Replacement;)Ljava/lang/String;
   #30 = InterfaceMethodref #7.#29        // scala/util/matching/Regex$Replacement.replaced$:(Lscala/util/matching/Regex$Replacement;)Ljava/lang/String;
   #31 = Utf8               this
   #32 = Utf8               Lscala/util/matching/Regex$MatchIterator$$anon$4;
   #33 = Utf8               replace
   #34 = Utf8               (Ljava/lang/String;)Ljava/util/regex/Matcher;
   #35 = Utf8               rs
   #36 = Utf8               replace$
   #37 = Utf8               (Lscala/util/matching/Regex$Replacement;Ljava/lang/String;)Ljava/util/regex/Matcher;
   #38 = NameAndType        #36:#37       // replace$:(Lscala/util/matching/Regex$Replacement;Ljava/lang/String;)Ljava/util/regex/Matcher;
   #39 = InterfaceMethodref #7.#38        // scala/util/matching/Regex$Replacement.replace$:(Lscala/util/matching/Regex$Replacement;Ljava/lang/String;)Ljava/util/regex/Matcher;
   #40 = Utf8               Ljava/lang/String;
   #41 = Utf8               ()Ljava/lang/StringBuffer;
   #42 = NameAndType        #21:#22       // scala$util$matching$Regex$Replacement$$sb:Ljava/lang/StringBuffer;
   #43 = Fieldref           #2.#42        // scala/util/matching/Regex$MatchIterator$$anon$4.scala$util$matching$Regex$Replacement$$sb:Ljava/lang/StringBuffer;
   #44 = Utf8               scala$util$matching$Regex$Replacement$_setter_$scala$util$matching$Regex$Replacement$$sb_$eq
   #45 = Utf8               (Ljava/lang/StringBuffer;)V
   #46 = Utf8               x$1
   #47 = Utf8               matcher
   #48 = Utf8               ()Ljava/util/regex/Matcher;
   #49 = NameAndType        #23:#24       // $outer:Lscala/util/matching/Regex$MatchIterator;
   #50 = Fieldref           #2.#49        // scala/util/matching/Regex$MatchIterator$$anon$4.$outer:Lscala/util/matching/Regex$MatchIterator;
   #51 = NameAndType        #47:#48       // matcher:()Ljava/util/regex/Matcher;
   #52 = Methodref          #10.#51       // scala/util/matching/Regex$MatchIterator.matcher:()Ljava/util/regex/Matcher;
   #53 = Utf8               hasNext
   #54 = Utf8               ()Z
   #55 = NameAndType        #53:#54       // hasNext:()Z
   #56 = Methodref          #10.#55       // scala/util/matching/Regex$MatchIterator.hasNext:()Z
   #57 = Utf8               next
   #58 = Utf8               ()Lscala/util/matching/Regex$Match;
   #59 = NameAndType        #57:#26       // next:()Ljava/lang/String;
   #60 = Methodref          #10.#59       // scala/util/matching/Regex$MatchIterator.next:()Ljava/lang/String;
   #61 = Utf8               source
   #62 = Utf8               ()Ljava/lang/CharSequence;
   #63 = NameAndType        #61:#62       // source:()Ljava/lang/CharSequence;
   #64 = Methodref          #10.#63       // scala/util/matching/Regex$MatchIterator.source:()Ljava/lang/CharSequence;
   #65 = Methodref          #2.#51        // scala/util/matching/Regex$MatchIterator$$anon$4.matcher:()Ljava/util/regex/Matcher;
   #66 = Utf8               _groupNames
   #67 = Utf8               ()Lscala/collection/immutable/Seq;
   #68 = NameAndType        #66:#67       // _groupNames:()Lscala/collection/immutable/Seq;
   #69 = Methodref          #10.#68       // scala/util/matching/Regex$MatchIterator._groupNames:()Lscala/collection/immutable/Seq;
   #70 = Utf8               <init>
   #71 = Utf8               (Ljava/lang/CharSequence;Ljava/util/regex/Matcher;Lscala/collection/immutable/Seq;)V
   #72 = NameAndType        #70:#71       // "<init>":(Ljava/lang/CharSequence;Ljava/util/regex/Matcher;Lscala/collection/immutable/Seq;)V
   #73 = Methodref          #15.#72       // scala/util/matching/Regex$Match."<init>":(Ljava/lang/CharSequence;Ljava/util/regex/Matcher;Lscala/collection/immutable/Seq;)V
   #74 = Utf8               force
   #75 = NameAndType        #74:#58       // force:()Lscala/util/matching/Regex$Match;
   #76 = Methodref          #15.#75       // scala/util/matching/Regex$Match.force:()Lscala/util/matching/Regex$Match;
   #77 = Utf8               ()Ljava/lang/Object;
   #78 = NameAndType        #57:#58       // next:()Lscala/util/matching/Regex$Match;
   #79 = Methodref          #2.#78        // scala/util/matching/Regex$MatchIterator$$anon$4.next:()Lscala/util/matching/Regex$Match;
   #80 = Utf8               (Lscala/util/matching/Regex$MatchIterator;)V
   #81 = Utf8               ()V
   #82 = NameAndType        #70:#81       // "<init>":()V
   #83 = Methodref          #5.#82        // scala/collection/AbstractIterator."<init>":()V
   #84 = Utf8               $init$
   #85 = Utf8               (Lscala/util/matching/Regex$Replacement;)V
   #86 = NameAndType        #84:#85       // $init$:(Lscala/util/matching/Regex$Replacement;)V
   #87 = InterfaceMethodref #7.#86        // scala/util/matching/Regex$Replacement.$init$:(Lscala/util/matching/Regex$Replacement;)V
   #88 = Utf8               scala/runtime/Statics
   #89 = Class              #88           // scala/runtime/Statics
   #90 = Utf8               releaseFence
   #91 = NameAndType        #90:#81       // releaseFence:()V
   #92 = Methodref          #89.#91       // scala/runtime/Statics.releaseFence:()V
   #93 = Utf8               Code
   #94 = Utf8               LineNumberTable
   #95 = Utf8               LocalVariableTable
   #96 = Utf8               MethodParameters
   #97 = Utf8               StackMapTable
   #98 = Utf8               InnerClasses
   #99 = Utf8               EnclosingMethod
  #100 = Utf8               Signature
  #101 = Utf8               SourceFile
  #102 = Utf8               ScalaInlineInfo
  #103 = Utf8               Scala
{
  private java.lang.StringBuffer scala$util$matching$Regex$Replacement$$sb;
    descriptor: Ljava/lang/StringBuffer;
    flags: (0x0002) ACC_PRIVATE

  private final scala.util.matching.Regex$MatchIterator $outer;
    descriptor: Lscala/util/matching/Regex$MatchIterator;
    flags: (0x1012) ACC_PRIVATE, ACC_FINAL, ACC_SYNTHETIC

  public java.lang.String replaced();
    descriptor: ()Ljava/lang/String;
    flags: (0x0001) ACC_PUBLIC
    Code:
      stack=1, locals=1, args_size=1
         0: aload_0
         1: invokestatic  #30                 // InterfaceMethod scala/util/matching/Regex$Replacement.replaced$:(Lscala/util/matching/Regex$Replacement;)Ljava/lang/String;
         4: areturn
      LineNumberTable:
        line 876: 0
      LocalVariableTable:
        Start  Length  Slot  Name   Signature
            0       5     0  this   Lscala/util/matching/Regex$MatchIterator$$anon$4;

  public java.util.regex.Matcher replace(java.lang.String);
    descriptor: (Ljava/lang/String;)Ljava/util/regex/Matcher;
    flags: (0x0001) ACC_PUBLIC
    Code:
      stack=2, locals=2, args_size=2
         0: aload_0
         1: aload_1
         2: invokestatic  #39                 // InterfaceMethod scala/util/matching/Regex$Replacement.replace$:(Lscala/util/matching/Regex$Replacement;Ljava/lang/String;)Ljava/util/regex/Matcher;
         5: areturn
      LineNumberTable:
        line 876: 0
      LocalVariableTable:
        Start  Length  Slot  Name   Signature
            0       6     0  this   Lscala/util/matching/Regex$MatchIterator$$anon$4;
            0       6     1    rs   Ljava/lang/String;
    MethodParameters:
      Name                           Flags
      rs                             final

  public java.lang.StringBuffer scala$util$matching$Regex$Replacement$$sb();
    descriptor: ()Ljava/lang/StringBuffer;
    flags: (0x0001) ACC_PUBLIC
    Code:
      stack=1, locals=1, args_size=1
         0: aload_0
         1: getfield      #43                 // Field scala$util$matching$Regex$Replacement$$sb:Ljava/lang/StringBuffer;
         4: areturn
      LineNumberTable:
        line 876: 0
      LocalVariableTable:
        Start  Length  Slot  Name   Signature
            0       5     0  this   Lscala/util/matching/Regex$MatchIterator$$anon$4;

  public final void scala$util$matching$Regex$Replacement$_setter_$scala$util$matching$Regex$Replacement$$sb_$eq(java.lang.StringBuffer);
    descriptor: (Ljava/lang/StringBuffer;)V
    flags: (0x0011) ACC_PUBLIC, ACC_FINAL
    Code:
      stack=2, locals=2, args_size=2
         0: aload_0
         1: aload_1
         2: putfield      #43                 // Field scala$util$matching$Regex$Replacement$$sb:Ljava/lang/StringBuffer;
         5: return
      LineNumberTable:
        line 876: 0
      LocalVariableTable:
        Start  Length  Slot  Name   Signature
            0       6     0  this   Lscala/util/matching/Regex$MatchIterator$$anon$4;
            0       6     1   x$1   Ljava/lang/StringBuffer;
    MethodParameters:
      Name                           Flags
      x$1                            final

  public java.util.regex.Matcher matcher();
    descriptor: ()Ljava/util/regex/Matcher;
    flags: (0x0001) ACC_PUBLIC
    Code:
      stack=1, locals=1, args_size=1
         0: aload_0
         1: getfield      #50                 // Field $outer:Lscala/util/matching/Regex$MatchIterator;
         4: invokevirtual #52                 // Method scala/util/matching/Regex$MatchIterator.matcher:()Ljava/util/regex/Matcher;
         7: areturn
      LineNumberTable:
        line 877: 0
      LocalVariableTable:
        Start  Length  Slot  Name   Signature
            0       8     0  this   Lscala/util/matching/Regex$MatchIterator$$anon$4;

  public boolean hasNext();
    descriptor: ()Z
    flags: (0x0001) ACC_PUBLIC
    Code:
      stack=1, locals=1, args_size=1
         0: aload_0
         1: getfield      #50                 // Field $outer:Lscala/util/matching/Regex$MatchIterator;
         4: invokevirtual #56                 // Method scala/util/matching/Regex$MatchIterator.hasNext:()Z
         7: ireturn
      LineNumberTable:
        line 878: 0
      LocalVariableTable:
        Start  Length  Slot  Name   Signature
            0       8     0  this   Lscala/util/matching/Regex$MatchIterator$$anon$4;

  public scala.util.matching.Regex$Match next();
    descriptor: ()Lscala/util/matching/Regex$Match;
    flags: (0x0001) ACC_PUBLIC
    Code:
      stack=5, locals=1, args_size=1
         0: aload_0
         1: getfield      #50                 // Field $outer:Lscala/util/matching/Regex$MatchIterator;
         4: invokevirtual #60                 // Method scala/util/matching/Regex$MatchIterator.next:()Ljava/lang/String;
         7: pop
         8: new           #15                 // class scala/util/matching/Regex$Match
        11: dup
        12: aload_0
        13: getfield      #50                 // Field $outer:Lscala/util/matching/Regex$MatchIterator;
        16: invokevirtual #64                 // Method scala/util/matching/Regex$MatchIterator.source:()Ljava/lang/CharSequence;
        19: aload_0
        20: invokevirtual #65                 // Method matcher:()Ljava/util/regex/Matcher;
        23: aload_0
        24: getfield      #50                 // Field $outer:Lscala/util/matching/Regex$MatchIterator;
        27: invokevirtual #69                 // Method scala/util/matching/Regex$MatchIterator._groupNames:()Lscala/collection/immutable/Seq;
        30: invokespecial #73                 // Method scala/util/matching/Regex$Match."<init>":(Ljava/lang/CharSequence;Ljava/util/regex/Matcher;Lscala/collection/immutable/Seq;)V
        33: invokevirtual #76                 // Method scala/util/matching/Regex$Match.force:()Lscala/util/matching/Regex$Match;
        36: areturn
      LineNumberTable:
        line 879: 0
      LocalVariableTable:
        Start  Length  Slot  Name   Signature
            0      37     0  this   Lscala/util/matching/Regex$MatchIterator$$anon$4;

  public java.lang.Object next();
    descriptor: ()Ljava/lang/Object;
    flags: (0x1041) ACC_PUBLIC, ACC_BRIDGE, ACC_SYNTHETIC
    Code:
      stack=1, locals=1, args_size=1
         0: aload_0
         1: invokevirtual #79                 // Method next:()Lscala/util/matching/Regex$Match;
         4: areturn
      LineNumberTable:
        line 876: 0
      LocalVariableTable:
        Start  Length  Slot  Name   Signature
            0       5     0  this   Lscala/util/matching/Regex$MatchIterator$$anon$4;

  public scala.util.matching.Regex$MatchIterator$$anon$4(scala.util.matching.Regex$MatchIterator);
    descriptor: (Lscala/util/matching/Regex$MatchIterator;)V
    flags: (0x0001) ACC_PUBLIC
    Code:
      stack=2, locals=2, args_size=2
         0: aload_1
         1: ifnonnull     6
         4: aconst_null
         5: athrow
         6: aload_0
         7: aload_1
         8: putfield      #50                 // Field $outer:Lscala/util/matching/Regex$MatchIterator;
        11: aload_0
        12: invokespecial #83                 // Method scala/collection/AbstractIterator."<init>":()V
        15: aload_0
        16: invokestatic  #87                 // InterfaceMethod scala/util/matching/Regex$Replacement.$init$:(Lscala/util/matching/Regex$Replacement;)V
        19: invokestatic  #92                 // Method scala/runtime/Statics.releaseFence:()V
        22: return
      StackMapTable: number_of_entries = 1
        frame_type = 6 /* same */
      LineNumberTable:
        line 876: 0
      LocalVariableTable:
        Start  Length  Slot  Name   Signature
            0      23     0  this   Lscala/util/matching/Regex$MatchIterator$$anon$4;
            0      23     1 $outer   Lscala/util/matching/Regex$MatchIterator;
    MethodParameters:
      Name                           Flags
      $outer                         final synthetic
}
InnerClasses:
  public static #18= #15 of #17;          // Match=class scala/util/matching/Regex$Match of class scala/util/matching/Regex
  public static #19= #10 of #17;          // MatchIterator=class scala/util/matching/Regex$MatchIterator of class scala/util/matching/Regex
  public final #2;                        // class scala/util/matching/Regex$MatchIterator$$anon$4
  public static #20= #7 of #17;           // Replacement=class scala/util/matching/Regex$Replacement of class scala/util/matching/Regex
EnclosingMethod: #10.#13                // scala.util.matching.Regex$MatchIterator.replacementData
Signature: #3                           // Lscala/collection/AbstractIterator<Lscala/util/matching/Regex$Match;>;Lscala/util/matching/Regex$Replacement;
SourceFile: "Regex.scala"
  ScalaInlineInfo: length = 0x31 (unknown attribute)
   01 01 00 09 00 46 00 50 01 00 35 00 36 01 00 2F
   00 30 01 00 39 00 4D 01 00 39 00 3A 01 00 21 00
   22 01 00 19 00 1A 01 00 15 00 29 01 00 2C 00 2D
   01
  Scala: length = 0x0 (unknown attribute)

