Classfile /Users/mw/Projects/slang-braindump/.jar/jar11/assemble/slang-braindump/assemble/content/scala/util/matching/Regex$$anon$2.class
  Last modified May 29, 2022; size 1419 bytes
  SHA-256 checksum 833d6a8eb0a942b00e6c25730ccfa5cfbdef49d03b1564c5ac72c9049b1bf5fe
  Compiled from "Regex.scala"
public final class scala.util.matching.Regex$$anon$2 extends scala.util.matching.Regex implements scala.util.matching.UnanchoredRegex
  minor version: 0
  major version: 52
  flags: (0x0031) ACC_PUBLIC, ACC_FINAL, ACC_SUPER
  this_class: #2                          // scala/util/matching/Regex$$anon$2
  super_class: #4                         // scala/util/matching/Regex
  interfaces: 1, fields: 1, methods: 4, attributes: 5
Constant pool:
   #1 = Utf8               scala/util/matching/Regex$$anon$2
   #2 = Class              #1             // scala/util/matching/Regex$$anon$2
   #3 = Utf8               scala/util/matching/Regex
   #4 = Class              #3             // scala/util/matching/Regex
   #5 = Utf8               scala/util/matching/UnanchoredRegex
   #6 = Class              #5             // scala/util/matching/UnanchoredRegex
   #7 = Utf8               Regex.scala
   #8 = Utf8               unanchored
   #9 = Utf8               ()Lscala/util/matching/UnanchoredRegex;
  #10 = NameAndType        #8:#9          // unanchored:()Lscala/util/matching/UnanchoredRegex;
  #11 = Utf8               $outer
  #12 = Utf8               Lscala/util/matching/Regex;
  #13 = Utf8               runMatcher
  #14 = Utf8               (Ljava/util/regex/Matcher;)Z
  #15 = Utf8               m
  #16 = Utf8               runMatcher$
  #17 = Utf8               (Lscala/util/matching/UnanchoredRegex;Ljava/util/regex/Matcher;)Z
  #18 = NameAndType        #16:#17        // runMatcher$:(Lscala/util/matching/UnanchoredRegex;Ljava/util/regex/Matcher;)Z
  #19 = InterfaceMethodref #6.#18         // scala/util/matching/UnanchoredRegex.runMatcher$:(Lscala/util/matching/UnanchoredRegex;Ljava/util/regex/Matcher;)Z
  #20 = Utf8               this
  #21 = Utf8               Lscala/util/matching/Regex$$anon$2;
  #22 = Utf8               Ljava/util/regex/Matcher;
  #23 = Utf8               unanchored$
  #24 = Utf8               (Lscala/util/matching/UnanchoredRegex;)Lscala/util/matching/UnanchoredRegex;
  #25 = NameAndType        #23:#24        // unanchored$:(Lscala/util/matching/UnanchoredRegex;)Lscala/util/matching/UnanchoredRegex;
  #26 = InterfaceMethodref #6.#25         // scala/util/matching/UnanchoredRegex.unanchored$:(Lscala/util/matching/UnanchoredRegex;)Lscala/util/matching/UnanchoredRegex;
  #27 = Utf8               anchored
  #28 = Utf8               ()Lscala/util/matching/Regex;
  #29 = NameAndType        #11:#12        // $outer:Lscala/util/matching/Regex;
  #30 = Fieldref           #2.#29         // scala/util/matching/Regex$$anon$2.$outer:Lscala/util/matching/Regex;
  #31 = Utf8               <init>
  #32 = Utf8               (Lscala/util/matching/Regex;)V
  #33 = Utf8               pattern
  #34 = Utf8               ()Ljava/util/regex/Pattern;
  #35 = NameAndType        #33:#34        // pattern:()Ljava/util/regex/Pattern;
  #36 = Methodref          #4.#35         // scala/util/matching/Regex.pattern:()Ljava/util/regex/Pattern;
  #37 = Utf8               scala$util$matching$Regex$$groupNames
  #38 = Utf8               Lscala/collection/immutable/Seq;
  #39 = NameAndType        #37:#38        // scala$util$matching$Regex$$groupNames:Lscala/collection/immutable/Seq;
  #40 = Fieldref           #4.#39         // scala/util/matching/Regex.scala$util$matching$Regex$$groupNames:Lscala/collection/immutable/Seq;
  #41 = Utf8               (Ljava/util/regex/Pattern;Lscala/collection/immutable/Seq;)V
  #42 = NameAndType        #31:#41        // "<init>":(Ljava/util/regex/Pattern;Lscala/collection/immutable/Seq;)V
  #43 = Methodref          #4.#42         // scala/util/matching/Regex."<init>":(Ljava/util/regex/Pattern;Lscala/collection/immutable/Seq;)V
  #44 = Utf8               Code
  #45 = Utf8               LineNumberTable
  #46 = Utf8               LocalVariableTable
  #47 = Utf8               MethodParameters
  #48 = Utf8               StackMapTable
  #49 = Utf8               InnerClasses
  #50 = Utf8               EnclosingMethod
  #51 = Utf8               SourceFile
  #52 = Utf8               ScalaInlineInfo
  #53 = Utf8               Scala
{
  private final scala.util.matching.Regex $outer;
    descriptor: Lscala/util/matching/Regex;
    flags: (0x1012) ACC_PRIVATE, ACC_FINAL, ACC_SYNTHETIC

  public boolean runMatcher(java.util.regex.Matcher);
    descriptor: (Ljava/util/regex/Matcher;)Z
    flags: (0x0001) ACC_PUBLIC
    Code:
      stack=2, locals=2, args_size=2
         0: aload_0
         1: aload_1
         2: invokestatic  #19                 // InterfaceMethod scala/util/matching/UnanchoredRegex.runMatcher$:(Lscala/util/matching/UnanchoredRegex;Ljava/util/regex/Matcher;)Z
         5: ireturn
      LineNumberTable:
        line 592: 0
      LocalVariableTable:
        Start  Length  Slot  Name   Signature
            0       6     0  this   Lscala/util/matching/Regex$$anon$2;
            0       6     1     m   Ljava/util/regex/Matcher;
    MethodParameters:
      Name                           Flags
      m                              final

  public scala.util.matching.UnanchoredRegex unanchored();
    descriptor: ()Lscala/util/matching/UnanchoredRegex;
    flags: (0x0001) ACC_PUBLIC
    Code:
      stack=1, locals=1, args_size=1
         0: aload_0
         1: invokestatic  #26                 // InterfaceMethod scala/util/matching/UnanchoredRegex.unanchored$:(Lscala/util/matching/UnanchoredRegex;)Lscala/util/matching/UnanchoredRegex;
         4: areturn
      LineNumberTable:
        line 592: 0
      LocalVariableTable:
        Start  Length  Slot  Name   Signature
            0       5     0  this   Lscala/util/matching/Regex$$anon$2;

  public scala.util.matching.Regex anchored();
    descriptor: ()Lscala/util/matching/Regex;
    flags: (0x0001) ACC_PUBLIC
    Code:
      stack=1, locals=1, args_size=1
         0: aload_0
         1: getfield      #30                 // Field $outer:Lscala/util/matching/Regex;
         4: areturn
      LineNumberTable:
        line 592: 0
      LocalVariableTable:
        Start  Length  Slot  Name   Signature
            0       5     0  this   Lscala/util/matching/Regex$$anon$2;

  public scala.util.matching.Regex$$anon$2(scala.util.matching.Regex);
    descriptor: (Lscala/util/matching/Regex;)V
    flags: (0x0001) ACC_PUBLIC
    Code:
      stack=3, locals=2, args_size=2
         0: aload_1
         1: ifnonnull     6
         4: aconst_null
         5: athrow
         6: aload_0
         7: aload_1
         8: putfield      #30                 // Field $outer:Lscala/util/matching/Regex;
        11: aload_0
        12: aload_1
        13: invokevirtual #36                 // Method scala/util/matching/Regex.pattern:()Ljava/util/regex/Pattern;
        16: aload_1
        17: getfield      #40                 // Field scala/util/matching/Regex.scala$util$matching$Regex$$groupNames:Lscala/collection/immutable/Seq;
        20: invokespecial #43                 // Method scala/util/matching/Regex."<init>":(Ljava/util/regex/Pattern;Lscala/collection/immutable/Seq;)V
        23: return
      StackMapTable: number_of_entries = 1
        frame_type = 6 /* same */
      LineNumberTable:
        line 592: 0
        line 592: 23
      LocalVariableTable:
        Start  Length  Slot  Name   Signature
            0      24     0  this   Lscala/util/matching/Regex$$anon$2;
            0      24     1 $outer   Lscala/util/matching/Regex;
    MethodParameters:
      Name                           Flags
      $outer                         final synthetic
}
InnerClasses:
  public final #2;                        // class scala/util/matching/Regex$$anon$2
EnclosingMethod: #4.#10                 // scala.util.matching.Regex.unanchored
SourceFile: "Regex.scala"
  ScalaInlineInfo: length = 0x18 (unknown attribute)
   01 01 00 04 00 1F 00 20 01 00 1B 00 1C 01 00 0D
   00 0E 01 00 08 00 09 01
  Scala: length = 0x0 (unknown attribute)

