Classfile /Users/mw/Projects/slang-braindump/.jar/jar11/assemble/slang-braindump/assemble/content/org/scalatest/concurrent/AbstractPatienceConfiguration$PatienceConfigProxy.class
  Last modified May 29, 2022; size 1276 bytes
  SHA-256 checksum ab8633184c2844dd772c228795e682c62078907a500840428b71499ba21b4110
  Compiled from "AbstractPatienceConfiguration.scala"
public final class org.scalatest.concurrent.AbstractPatienceConfiguration$PatienceConfigProxy implements java.io.Serializable
  minor version: 0
  major version: 52
  flags: (0x0031) ACC_PUBLIC, ACC_FINAL, ACC_SUPER
  this_class: #2                          // org/scalatest/concurrent/AbstractPatienceConfiguration$PatienceConfigProxy
  super_class: #4                         // java/lang/Object
  interfaces: 1, fields: 2, methods: 2, attributes: 4
Constant pool:
   #1 = Utf8               org/scalatest/concurrent/AbstractPatienceConfiguration$PatienceConfigProxy
   #2 = Class              #1             // org/scalatest/concurrent/AbstractPatienceConfiguration$PatienceConfigProxy
   #3 = Utf8               java/lang/Object
   #4 = Class              #3             // java/lang/Object
   #5 = Utf8               java/io/Serializable
   #6 = Class              #5             // java/io/Serializable
   #7 = Utf8               AbstractPatienceConfiguration.scala
   #8 = Utf8               org/scalatest/concurrent/AbstractPatienceConfiguration$PatienceConfig
   #9 = Class              #8             // org/scalatest/concurrent/AbstractPatienceConfiguration$PatienceConfig
  #10 = Utf8               org/scalatest/concurrent/AbstractPatienceConfiguration
  #11 = Class              #10            // org/scalatest/concurrent/AbstractPatienceConfiguration
  #12 = Utf8               PatienceConfig
  #13 = Utf8               PatienceConfigProxy
  #14 = Utf8               timeout
  #15 = Utf8               Lorg/scalatest/time/Span;
  #16 = Utf8               interval
  #17 = Utf8               readResolve
  #18 = Utf8               ()Ljava/lang/Object;
  #19 = Utf8               org/scalatest/concurrent/AbstractPatienceConfiguration$
  #20 = Class              #19            // org/scalatest/concurrent/AbstractPatienceConfiguration$
  #21 = Utf8               MODULE$
  #22 = Utf8               Lorg/scalatest/concurrent/AbstractPatienceConfiguration$;
  #23 = NameAndType        #21:#22        // MODULE$:Lorg/scalatest/concurrent/AbstractPatienceConfiguration$;
  #24 = Fieldref           #20.#23        // org/scalatest/concurrent/AbstractPatienceConfiguration$.MODULE$:Lorg/scalatest/concurrent/AbstractPatienceConfiguration$;
  #25 = NameAndType        #14:#15        // timeout:Lorg/scalatest/time/Span;
  #26 = Fieldref           #2.#25         // org/scalatest/concurrent/AbstractPatienceConfiguration$PatienceConfigProxy.timeout:Lorg/scalatest/time/Span;
  #27 = NameAndType        #16:#15        // interval:Lorg/scalatest/time/Span;
  #28 = Fieldref           #2.#27         // org/scalatest/concurrent/AbstractPatienceConfiguration$PatienceConfigProxy.interval:Lorg/scalatest/time/Span;
  #29 = Utf8               <init>
  #30 = Utf8               (Lorg/scalatest/concurrent/AbstractPatienceConfiguration;Lorg/scalatest/time/Span;Lorg/scalatest/time/Span;)V
  #31 = NameAndType        #29:#30        // "<init>":(Lorg/scalatest/concurrent/AbstractPatienceConfiguration;Lorg/scalatest/time/Span;Lorg/scalatest/time/Span;)V
  #32 = Methodref          #9.#31         // org/scalatest/concurrent/AbstractPatienceConfiguration$PatienceConfig."<init>":(Lorg/scalatest/concurrent/AbstractPatienceConfiguration;Lorg/scalatest/time/Span;Lorg/scalatest/time/Span;)V
  #33 = Utf8               this
  #34 = Utf8               Lorg/scalatest/concurrent/AbstractPatienceConfiguration$PatienceConfigProxy;
  #35 = Utf8               (Lorg/scalatest/time/Span;Lorg/scalatest/time/Span;)V
  #36 = Utf8               ()V
  #37 = NameAndType        #29:#36        // "<init>":()V
  #38 = Methodref          #4.#37         // java/lang/Object."<init>":()V
  #39 = Utf8               Code
  #40 = Utf8               LineNumberTable
  #41 = Utf8               LocalVariableTable
  #42 = Utf8               MethodParameters
  #43 = Utf8               InnerClasses
  #44 = Utf8               SourceFile
  #45 = Utf8               ScalaInlineInfo
  #46 = Utf8               Scala
{
  private final org.scalatest.time.Span timeout;
    descriptor: Lorg/scalatest/time/Span;
    flags: (0x0012) ACC_PRIVATE, ACC_FINAL

  private final org.scalatest.time.Span interval;
    descriptor: Lorg/scalatest/time/Span;
    flags: (0x0012) ACC_PRIVATE, ACC_FINAL

  private java.lang.Object readResolve();
    descriptor: ()Ljava/lang/Object;
    flags: (0x0002) ACC_PRIVATE
    Code:
      stack=5, locals=1, args_size=1
         0: new           #9                  // class org/scalatest/concurrent/AbstractPatienceConfiguration$PatienceConfig
         3: dup
         4: getstatic     #24                 // Field org/scalatest/concurrent/AbstractPatienceConfiguration$.MODULE$:Lorg/scalatest/concurrent/AbstractPatienceConfiguration$;
         7: aload_0
         8: getfield      #26                 // Field timeout:Lorg/scalatest/time/Span;
        11: aload_0
        12: getfield      #28                 // Field interval:Lorg/scalatest/time/Span;
        15: invokespecial #32                 // Method org/scalatest/concurrent/AbstractPatienceConfiguration$PatienceConfig."<init>":(Lorg/scalatest/concurrent/AbstractPatienceConfiguration;Lorg/scalatest/time/Span;Lorg/scalatest/time/Span;)V
        18: areturn
      LineNumberTable:
        line 114: 0
      LocalVariableTable:
        Start  Length  Slot  Name   Signature
            0      19     0  this   Lorg/scalatest/concurrent/AbstractPatienceConfiguration$PatienceConfigProxy;

  public org.scalatest.concurrent.AbstractPatienceConfiguration$PatienceConfigProxy(org.scalatest.time.Span, org.scalatest.time.Span);
    descriptor: (Lorg/scalatest/time/Span;Lorg/scalatest/time/Span;)V
    flags: (0x0001) ACC_PUBLIC
    Code:
      stack=2, locals=3, args_size=3
         0: aload_0
         1: aload_1
         2: putfield      #26                 // Field timeout:Lorg/scalatest/time/Span;
         5: aload_0
         6: aload_2
         7: putfield      #28                 // Field interval:Lorg/scalatest/time/Span;
        10: aload_0
        11: invokespecial #38                 // Method java/lang/Object."<init>":()V
        14: return
      LineNumberTable:
        line 113: 0
      LocalVariableTable:
        Start  Length  Slot  Name   Signature
            0      15     0  this   Lorg/scalatest/concurrent/AbstractPatienceConfiguration$PatienceConfigProxy;
            0      15     1 timeout   Lorg/scalatest/time/Span;
            0      15     2 interval   Lorg/scalatest/time/Span;
    MethodParameters:
      Name                           Flags
      timeout                        final
      interval                       final
}
InnerClasses:
  public final #12= #9 of #11;            // PatienceConfig=class org/scalatest/concurrent/AbstractPatienceConfiguration$PatienceConfig of class org/scalatest/concurrent/AbstractPatienceConfiguration
  private static final #13= #2 of #11;    // PatienceConfigProxy=class org/scalatest/concurrent/AbstractPatienceConfiguration$PatienceConfigProxy of class org/scalatest/concurrent/AbstractPatienceConfiguration
SourceFile: "AbstractPatienceConfiguration.scala"
  ScalaInlineInfo: length = 0xE (unknown attribute)
   01 01 00 02 00 1D 00 23 01 00 11 00 12 01
  Scala: length = 0x0 (unknown attribute)

