Classfile /Users/mw/Projects/slang-braindump/.jar/jar11/assemble/slang-braindump/assemble/content/org/scalatest/concurrent/Conductors$Conductor$Clock.class
  Last modified May 29, 2022; size 5221 bytes
  SHA-256 checksum e5c0147ddd91233e3bb7369416897b3c9cd5f1597681aa505ec3af021cad5986
  Compiled from "Conductors.scala"
public class org.scalatest.concurrent.Conductors$Conductor$Clock
  minor version: 0
  major version: 52
  flags: (0x0021) ACC_PUBLIC, ACC_SUPER
  this_class: #2                          // org/scalatest/concurrent/Conductors$Conductor$Clock
  super_class: #4                         // java/lang/Object
  interfaces: 0, fields: 5, methods: 18, attributes: 5
Constant pool:
    #1 = Utf8               org/scalatest/concurrent/Conductors$Conductor$Clock
    #2 = Class              #1            // org/scalatest/concurrent/Conductors$Conductor$Clock
    #3 = Utf8               java/lang/Object
    #4 = Class              #3            // java/lang/Object
    #5 = Utf8               Conductors.scala
    #6 = Utf8               java/lang/invoke/MethodHandles$Lookup
    #7 = Class              #6            // java/lang/invoke/MethodHandles$Lookup
    #8 = Utf8               java/lang/invoke/MethodHandles
    #9 = Class              #8            // java/lang/invoke/MethodHandles
   #10 = Utf8               Lookup
   #11 = Utf8               org/scalatest/concurrent/Conductors$Conductor
   #12 = Class              #11           // org/scalatest/concurrent/Conductors$Conductor
   #13 = Utf8               org/scalatest/concurrent/Conductors
   #14 = Class              #13           // org/scalatest/concurrent/Conductors
   #15 = Utf8               Conductor
   #16 = Utf8               Clock
   #17 = Utf8               currentTime
   #18 = Utf8               I
   #19 = Utf8               lock
   #20 = Utf8               Ljava/lang/Object;
   #21 = Utf8               rwLock
   #22 = Utf8               Ljava/util/concurrent/locks/ReentrantReadWriteLock;
   #23 = Utf8               highestBeatBeingWaitedOn
   #24 = Utf8               $outer
   #25 = Utf8               Lorg/scalatest/concurrent/Conductors$Conductor;
   #26 = Utf8               ()I
   #27 = NameAndType        #17:#18       // currentTime:I
   #28 = Fieldref           #2.#27        // org/scalatest/concurrent/Conductors$Conductor$Clock.currentTime:I
   #29 = Utf8               this
   #30 = Utf8               Lorg/scalatest/concurrent/Conductors$Conductor$Clock;
   #31 = Utf8               currentTime_$eq
   #32 = Utf8               (I)V
   #33 = Utf8               x$1
   #34 = Utf8               ()Ljava/lang/Object;
   #35 = NameAndType        #19:#20       // lock:Ljava/lang/Object;
   #36 = Fieldref           #2.#35        // org/scalatest/concurrent/Conductors$Conductor$Clock.lock:Ljava/lang/Object;
   #37 = Utf8               ()Ljava/util/concurrent/locks/ReentrantReadWriteLock;
   #38 = NameAndType        #21:#22       // rwLock:Ljava/util/concurrent/locks/ReentrantReadWriteLock;
   #39 = Fieldref           #2.#38        // org/scalatest/concurrent/Conductors$Conductor$Clock.rwLock:Ljava/util/concurrent/locks/ReentrantReadWriteLock;
   #40 = NameAndType        #23:#18       // highestBeatBeingWaitedOn:I
   #41 = Fieldref           #2.#40        // org/scalatest/concurrent/Conductors$Conductor$Clock.highestBeatBeingWaitedOn:I
   #42 = Utf8               highestBeatBeingWaitedOn_$eq
   #43 = Utf8               advance
   #44 = Utf8               ()Lorg/scalatest/Succeeded$;
   #45 = NameAndType        #19:#34       // lock:()Ljava/lang/Object;
   #46 = Methodref          #2.#45        // org/scalatest/concurrent/Conductors$Conductor$Clock.lock:()Ljava/lang/Object;
   #47 = Utf8               org/scalatest/concurrent/PimpedReadWriteLock$
   #48 = Class              #47           // org/scalatest/concurrent/PimpedReadWriteLock$
   #49 = Utf8               MODULE$
   #50 = Utf8               Lorg/scalatest/concurrent/PimpedReadWriteLock$;
   #51 = NameAndType        #49:#50       // MODULE$:Lorg/scalatest/concurrent/PimpedReadWriteLock$;
   #52 = Fieldref           #48.#51       // org/scalatest/concurrent/PimpedReadWriteLock$.MODULE$:Lorg/scalatest/concurrent/PimpedReadWriteLock$;
   #53 = NameAndType        #21:#37       // rwLock:()Ljava/util/concurrent/locks/ReentrantReadWriteLock;
   #54 = Methodref          #2.#53        // org/scalatest/concurrent/Conductors$Conductor$Clock.rwLock:()Ljava/util/concurrent/locks/ReentrantReadWriteLock;
   #55 = Utf8               pimpMyReadWriteLock
   #56 = Utf8               (Ljava/util/concurrent/locks/ReadWriteLock;)Lorg/scalatest/concurrent/PimpedReadWriteLock;
   #57 = NameAndType        #55:#56       // pimpMyReadWriteLock:(Ljava/util/concurrent/locks/ReadWriteLock;)Lorg/scalatest/concurrent/PimpedReadWriteLock;
   #58 = Methodref          #48.#57       // org/scalatest/concurrent/PimpedReadWriteLock$.pimpMyReadWriteLock:(Ljava/util/concurrent/locks/ReadWriteLock;)Lorg/scalatest/concurrent/PimpedReadWriteLock;
   #59 = Utf8               ()V
   #60 = MethodType         #59           //  ()V
   #61 = Utf8               $anonfun$advance$1
   #62 = Utf8               (Lorg/scalatest/concurrent/Conductors$Conductor$Clock;)V
   #63 = NameAndType        #61:#62       // $anonfun$advance$1:(Lorg/scalatest/concurrent/Conductors$Conductor$Clock;)V
   #64 = Methodref          #2.#63        // org/scalatest/concurrent/Conductors$Conductor$Clock.$anonfun$advance$1:(Lorg/scalatest/concurrent/Conductors$Conductor$Clock;)V
   #65 = MethodHandle       6:#64         // REF_invokeStatic org/scalatest/concurrent/Conductors$Conductor$Clock.$anonfun$advance$1:(Lorg/scalatest/concurrent/Conductors$Conductor$Clock;)V
   #66 = Integer            1
   #67 = Utf8               java/lang/invoke/LambdaMetafactory
   #68 = Class              #67           // java/lang/invoke/LambdaMetafactory
   #69 = Utf8               altMetafactory
   #70 = Utf8               (Ljava/lang/invoke/MethodHandles$Lookup;Ljava/lang/String;Ljava/lang/invoke/MethodType;[Ljava/lang/Object;)Ljava/lang/invoke/CallSite;
   #71 = NameAndType        #69:#70       // altMetafactory:(Ljava/lang/invoke/MethodHandles$Lookup;Ljava/lang/String;Ljava/lang/invoke/MethodType;[Ljava/lang/Object;)Ljava/lang/invoke/CallSite;
   #72 = Methodref          #68.#71       // java/lang/invoke/LambdaMetafactory.altMetafactory:(Ljava/lang/invoke/MethodHandles$Lookup;Ljava/lang/String;Ljava/lang/invoke/MethodType;[Ljava/lang/Object;)Ljava/lang/invoke/CallSite;
   #73 = MethodHandle       6:#72         // REF_invokeStatic java/lang/invoke/LambdaMetafactory.altMetafactory:(Ljava/lang/invoke/MethodHandles$Lookup;Ljava/lang/String;Ljava/lang/invoke/MethodType;[Ljava/lang/Object;)Ljava/lang/invoke/CallSite;
   #74 = Utf8               apply$mcV$sp
   #75 = Utf8               (Lorg/scalatest/concurrent/Conductors$Conductor$Clock;)Lscala/runtime/java8/JFunction0$mcV$sp;
   #76 = NameAndType        #74:#75       // apply$mcV$sp:(Lorg/scalatest/concurrent/Conductors$Conductor$Clock;)Lscala/runtime/java8/JFunction0$mcV$sp;
   #77 = InvokeDynamic      #0:#76        // #0:apply$mcV$sp:(Lorg/scalatest/concurrent/Conductors$Conductor$Clock;)Lscala/runtime/java8/JFunction0$mcV$sp;
   #78 = Utf8               org/scalatest/concurrent/PimpedReadWriteLock
   #79 = Class              #78           // org/scalatest/concurrent/PimpedReadWriteLock
   #80 = Utf8               write
   #81 = Utf8               (Lscala/Function0;)Ljava/lang/Object;
   #82 = NameAndType        #80:#81       // write:(Lscala/Function0;)Ljava/lang/Object;
   #83 = Methodref          #79.#82       // org/scalatest/concurrent/PimpedReadWriteLock.write:(Lscala/Function0;)Ljava/lang/Object;
   #84 = Utf8               notifyAll
   #85 = NameAndType        #84:#59       // notifyAll:()V
   #86 = Methodref          #4.#85        // java/lang/Object.notifyAll:()V
   #87 = Utf8               org/scalatest/Succeeded$
   #88 = Class              #87           // org/scalatest/Succeeded$
   #89 = Utf8               Lorg/scalatest/Succeeded$;
   #90 = NameAndType        #49:#89       // MODULE$:Lorg/scalatest/Succeeded$;
   #91 = Fieldref           #88.#90       // org/scalatest/Succeeded$.MODULE$:Lorg/scalatest/Succeeded$;
   #92 = Utf8               java/lang/Throwable
   #93 = Class              #92           // java/lang/Throwable
   #94 = Utf8               currentBeat
   #95 = MethodType         #26           //  ()I
   #96 = Utf8               $anonfun$currentBeat$1
   #97 = Utf8               (Lorg/scalatest/concurrent/Conductors$Conductor$Clock;)I
   #98 = NameAndType        #96:#97       // $anonfun$currentBeat$1:(Lorg/scalatest/concurrent/Conductors$Conductor$Clock;)I
   #99 = Methodref          #2.#98        // org/scalatest/concurrent/Conductors$Conductor$Clock.$anonfun$currentBeat$1:(Lorg/scalatest/concurrent/Conductors$Conductor$Clock;)I
  #100 = MethodHandle       6:#99         // REF_invokeStatic org/scalatest/concurrent/Conductors$Conductor$Clock.$anonfun$currentBeat$1:(Lorg/scalatest/concurrent/Conductors$Conductor$Clock;)I
  #101 = Utf8               apply$mcI$sp
  #102 = Utf8               (Lorg/scalatest/concurrent/Conductors$Conductor$Clock;)Lscala/runtime/java8/JFunction0$mcI$sp;
  #103 = NameAndType        #101:#102     // apply$mcI$sp:(Lorg/scalatest/concurrent/Conductors$Conductor$Clock;)Lscala/runtime/java8/JFunction0$mcI$sp;
  #104 = InvokeDynamic      #1:#103       // #1:apply$mcI$sp:(Lorg/scalatest/concurrent/Conductors$Conductor$Clock;)Lscala/runtime/java8/JFunction0$mcI$sp;
  #105 = Utf8               read
  #106 = NameAndType        #105:#81      // read:(Lscala/Function0;)Ljava/lang/Object;
  #107 = Methodref          #79.#106      // org/scalatest/concurrent/PimpedReadWriteLock.read:(Lscala/Function0;)Ljava/lang/Object;
  #108 = Utf8               scala/runtime/BoxesRunTime
  #109 = Class              #108          // scala/runtime/BoxesRunTime
  #110 = Utf8               unboxToInt
  #111 = Utf8               (Ljava/lang/Object;)I
  #112 = NameAndType        #110:#111     // unboxToInt:(Ljava/lang/Object;)I
  #113 = Methodref          #109.#112     // scala/runtime/BoxesRunTime.unboxToInt:(Ljava/lang/Object;)I
  #114 = Utf8               waitForBeat
  #115 = Utf8               (I)Lorg/scalatest/Succeeded$;
  #116 = Utf8               beat
  #117 = NameAndType        #23:#26       // highestBeatBeingWaitedOn:()I
  #118 = Methodref          #2.#117       // org/scalatest/concurrent/Conductors$Conductor$Clock.highestBeatBeingWaitedOn:()I
  #119 = NameAndType        #42:#32       // highestBeatBeingWaitedOn_$eq:(I)V
  #120 = Methodref          #2.#119       // org/scalatest/concurrent/Conductors$Conductor$Clock.highestBeatBeingWaitedOn_$eq:(I)V
  #121 = NameAndType        #94:#26       // currentBeat:()I
  #122 = Methodref          #2.#121       // org/scalatest/concurrent/Conductors$Conductor$Clock.currentBeat:()I
  #123 = Utf8               liftedTree1$1
  #124 = NameAndType        #123:#59      // liftedTree1$1:()V
  #125 = Methodref          #2.#124       // org/scalatest/concurrent/Conductors$Conductor$Clock.liftedTree1$1:()V
  #126 = Utf8               isAnyThreadWaitingForABeat
  #127 = Utf8               ()Z
  #128 = NameAndType        #17:#26       // currentTime:()I
  #129 = Methodref          #2.#128       // org/scalatest/concurrent/Conductors$Conductor$Clock.currentTime:()I
  #130 = Utf8               withClockFrozen
  #131 = Utf8               <T:Ljava/lang/Object;>(Lscala/Function0<TT;>;)TT;
  #132 = Utf8               fun
  #133 = Utf8               Lscala/Function0;
  #134 = Utf8               isFrozen
  #135 = Utf8               java/util/concurrent/locks/ReentrantReadWriteLock
  #136 = Class              #135          // java/util/concurrent/locks/ReentrantReadWriteLock
  #137 = Utf8               getReadLockCount
  #138 = NameAndType        #137:#26      // getReadLockCount:()I
  #139 = Methodref          #136.#138     // java/util/concurrent/locks/ReentrantReadWriteLock.getReadLockCount:()I
  #140 = Utf8               org$scalatest$concurrent$Conductors$Conductor$Clock$$$outer
  #141 = Utf8               ()Lorg/scalatest/concurrent/Conductors$Conductor;
  #142 = NameAndType        #24:#25       // $outer:Lorg/scalatest/concurrent/Conductors$Conductor;
  #143 = Fieldref           #2.#142       // org/scalatest/concurrent/Conductors$Conductor$Clock.$outer:Lorg/scalatest/concurrent/Conductors$Conductor;
  #144 = Utf8               $this
  #145 = NameAndType        #31:#32       // currentTime_$eq:(I)V
  #146 = Methodref          #2.#145       // org/scalatest/concurrent/Conductors$Conductor$Clock.currentTime_$eq:(I)V
  #147 = Utf8               java/lang/InterruptedException
  #148 = Class              #147          // java/lang/InterruptedException
  #149 = Utf8               wait
  #150 = NameAndType        #149:#59      // wait:()V
  #151 = Methodref          #4.#150       // java/lang/Object.wait:()V
  #152 = Utf8               java/lang/AssertionError
  #153 = Class              #152          // java/lang/AssertionError
  #154 = Utf8               <init>
  #155 = Utf8               (Ljava/lang/Object;)V
  #156 = NameAndType        #154:#155     // "<init>":(Ljava/lang/Object;)V
  #157 = Methodref          #153.#156     // java/lang/AssertionError."<init>":(Ljava/lang/Object;)V
  #158 = Utf8               e
  #159 = Utf8               Ljava/lang/InterruptedException;
  #160 = Utf8               (Lorg/scalatest/concurrent/Conductors$Conductor;)V
  #161 = NameAndType        #154:#59      // "<init>":()V
  #162 = Methodref          #4.#161       // java/lang/Object."<init>":()V
  #163 = Methodref          #136.#161     // java/util/concurrent/locks/ReentrantReadWriteLock."<init>":()V
  #164 = Utf8               $deserializeLambda$
  #165 = Utf8               (Ljava/lang/invoke/SerializedLambda;)Ljava/lang/Object;
  #166 = Utf8               scala/runtime/LambdaDeserialize
  #167 = Class              #166          // scala/runtime/LambdaDeserialize
  #168 = Utf8               bootstrap
  #169 = Utf8               (Ljava/lang/invoke/MethodHandles$Lookup;Ljava/lang/String;Ljava/lang/invoke/MethodType;[Ljava/lang/invoke/MethodHandle;)Ljava/lang/invoke/CallSite;
  #170 = NameAndType        #168:#169     // bootstrap:(Ljava/lang/invoke/MethodHandles$Lookup;Ljava/lang/String;Ljava/lang/invoke/MethodType;[Ljava/lang/invoke/MethodHandle;)Ljava/lang/invoke/CallSite;
  #171 = Methodref          #167.#170     // scala/runtime/LambdaDeserialize.bootstrap:(Ljava/lang/invoke/MethodHandles$Lookup;Ljava/lang/String;Ljava/lang/invoke/MethodType;[Ljava/lang/invoke/MethodHandle;)Ljava/lang/invoke/CallSite;
  #172 = MethodHandle       6:#171        // REF_invokeStatic scala/runtime/LambdaDeserialize.bootstrap:(Ljava/lang/invoke/MethodHandles$Lookup;Ljava/lang/String;Ljava/lang/invoke/MethodType;[Ljava/lang/invoke/MethodHandle;)Ljava/lang/invoke/CallSite;
  #173 = Utf8               lambdaDeserialize
  #174 = NameAndType        #173:#165     // lambdaDeserialize:(Ljava/lang/invoke/SerializedLambda;)Ljava/lang/Object;
  #175 = InvokeDynamic      #2:#174       // #2:lambdaDeserialize:(Ljava/lang/invoke/SerializedLambda;)Ljava/lang/Object;
  #176 = Utf8               Code
  #177 = Utf8               LineNumberTable
  #178 = Utf8               LocalVariableTable
  #179 = Utf8               MethodParameters
  #180 = Utf8               StackMapTable
  #181 = Utf8               Signature
  #182 = Utf8               InnerClasses
  #183 = Utf8               SourceFile
  #184 = Utf8               BootstrapMethods
  #185 = Utf8               ScalaInlineInfo
  #186 = Utf8               Scala
{
  private int currentTime;
    descriptor: I
    flags: (0x0002) ACC_PRIVATE

  private final java.lang.Object lock;
    descriptor: Ljava/lang/Object;
    flags: (0x0012) ACC_PRIVATE, ACC_FINAL

  private final java.util.concurrent.locks.ReentrantReadWriteLock rwLock;
    descriptor: Ljava/util/concurrent/locks/ReentrantReadWriteLock;
    flags: (0x0012) ACC_PRIVATE, ACC_FINAL

  private int highestBeatBeingWaitedOn;
    descriptor: I
    flags: (0x0002) ACC_PRIVATE

  public final org.scalatest.concurrent.Conductors$Conductor $outer;
    descriptor: Lorg/scalatest/concurrent/Conductors$Conductor;
    flags: (0x1011) ACC_PUBLIC, ACC_FINAL, ACC_SYNTHETIC

  private int currentTime();
    descriptor: ()I
    flags: (0x0002) ACC_PRIVATE
    Code:
      stack=1, locals=1, args_size=1
         0: aload_0
         1: getfield      #28                 // Field currentTime:I
         4: ireturn
      LineNumberTable:
        line 876: 0
      LocalVariableTable:
        Start  Length  Slot  Name   Signature
            0       5     0  this   Lorg/scalatest/concurrent/Conductors$Conductor$Clock;

  private void currentTime_$eq(int);
    descriptor: (I)V
    flags: (0x0002) ACC_PRIVATE
    Code:
      stack=2, locals=2, args_size=2
         0: aload_0
         1: iload_1
         2: putfield      #28                 // Field currentTime:I
         5: return
      LineNumberTable:
        line 876: 0
      LocalVariableTable:
        Start  Length  Slot  Name   Signature
            0       6     0  this   Lorg/scalatest/concurrent/Conductors$Conductor$Clock;
            0       6     1   x$1   I
    MethodParameters:
      Name                           Flags
      x$1                            final

  private java.lang.Object lock();
    descriptor: ()Ljava/lang/Object;
    flags: (0x0002) ACC_PRIVATE
    Code:
      stack=1, locals=1, args_size=1
         0: aload_0
         1: getfield      #36                 // Field lock:Ljava/lang/Object;
         4: areturn
      LineNumberTable:
        line 880: 0
      LocalVariableTable:
        Start  Length  Slot  Name   Signature
            0       5     0  this   Lorg/scalatest/concurrent/Conductors$Conductor$Clock;

  private java.util.concurrent.locks.ReentrantReadWriteLock rwLock();
    descriptor: ()Ljava/util/concurrent/locks/ReentrantReadWriteLock;
    flags: (0x0002) ACC_PRIVATE
    Code:
      stack=1, locals=1, args_size=1
         0: aload_0
         1: getfield      #39                 // Field rwLock:Ljava/util/concurrent/locks/ReentrantReadWriteLock;
         4: areturn
      LineNumberTable:
        line 896: 0
      LocalVariableTable:
        Start  Length  Slot  Name   Signature
            0       5     0  this   Lorg/scalatest/concurrent/Conductors$Conductor$Clock;

  private int highestBeatBeingWaitedOn();
    descriptor: ()I
    flags: (0x0002) ACC_PRIVATE
    Code:
      stack=1, locals=1, args_size=1
         0: aload_0
         1: getfield      #41                 // Field highestBeatBeingWaitedOn:I
         4: ireturn
      LineNumberTable:
        line 898: 0
      LocalVariableTable:
        Start  Length  Slot  Name   Signature
            0       5     0  this   Lorg/scalatest/concurrent/Conductors$Conductor$Clock;

  private void highestBeatBeingWaitedOn_$eq(int);
    descriptor: (I)V
    flags: (0x0002) ACC_PRIVATE
    Code:
      stack=2, locals=2, args_size=2
         0: aload_0
         1: iload_1
         2: putfield      #41                 // Field highestBeatBeingWaitedOn:I
         5: return
      LineNumberTable:
        line 898: 0
      LocalVariableTable:
        Start  Length  Slot  Name   Signature
            0       6     0  this   Lorg/scalatest/concurrent/Conductors$Conductor$Clock;
            0       6     1   x$1   I
    MethodParameters:
      Name                           Flags
      x$1                            final

  public org.scalatest.Succeeded$ advance();
    descriptor: ()Lorg/scalatest/Succeeded$;
    flags: (0x0001) ACC_PUBLIC
    Code:
      stack=2, locals=2, args_size=1
         0: aload_0
         1: invokespecial #46                 // Method lock:()Ljava/lang/Object;
         4: dup
         5: astore_1
         6: monitorenter
         7: getstatic     #52                 // Field org/scalatest/concurrent/PimpedReadWriteLock$.MODULE$:Lorg/scalatest/concurrent/PimpedReadWriteLock$;
        10: aload_0
        11: invokespecial #54                 // Method rwLock:()Ljava/util/concurrent/locks/ReentrantReadWriteLock;
        14: invokevirtual #58                 // Method org/scalatest/concurrent/PimpedReadWriteLock$.pimpMyReadWriteLock:(Ljava/util/concurrent/locks/ReadWriteLock;)Lorg/scalatest/concurrent/PimpedReadWriteLock;
        17: aload_0
        18: invokedynamic #77,  0             // InvokeDynamic #0:apply$mcV$sp:(Lorg/scalatest/concurrent/Conductors$Conductor$Clock;)Lscala/runtime/java8/JFunction0$mcV$sp;
        23: invokevirtual #83                 // Method org/scalatest/concurrent/PimpedReadWriteLock.write:(Lscala/Function0;)Ljava/lang/Object;
        26: pop
        27: aload_0
        28: invokespecial #46                 // Method lock:()Ljava/lang/Object;
        31: invokevirtual #86                 // Method java/lang/Object.notifyAll:()V
        34: aload_1
        35: monitorexit
        36: goto          42
        39: aload_1
        40: monitorexit
        41: athrow
        42: getstatic     #91                 // Field org/scalatest/Succeeded$.MODULE$:Lorg/scalatest/Succeeded$;
        45: areturn
      Exception table:
         from    to  target type
             7    34    39   any
      StackMapTable: number_of_entries = 2
        frame_type = 255 /* full_frame */
          offset_delta = 39
          locals = [ class org/scalatest/concurrent/Conductors$Conductor$Clock, class java/lang/Object ]
          stack = [ class java/lang/Throwable ]
        frame_type = 2 /* same */
      LineNumberTable:
        line 915: 0
        line 916: 7
        line 917: 17
        line 919: 27
        line 921: 42
      LocalVariableTable:
        Start  Length  Slot  Name   Signature
            0      46     0  this   Lorg/scalatest/concurrent/Conductors$Conductor$Clock;

  public int currentBeat();
    descriptor: ()I
    flags: (0x0001) ACC_PUBLIC
    Code:
      stack=2, locals=3, args_size=1
         0: aload_0
         1: invokespecial #46                 // Method lock:()Ljava/lang/Object;
         4: dup
         5: astore_1
         6: monitorenter
         7: getstatic     #52                 // Field org/scalatest/concurrent/PimpedReadWriteLock$.MODULE$:Lorg/scalatest/concurrent/PimpedReadWriteLock$;
        10: aload_0
        11: invokespecial #54                 // Method rwLock:()Ljava/util/concurrent/locks/ReentrantReadWriteLock;
        14: invokevirtual #58                 // Method org/scalatest/concurrent/PimpedReadWriteLock$.pimpMyReadWriteLock:(Ljava/util/concurrent/locks/ReadWriteLock;)Lorg/scalatest/concurrent/PimpedReadWriteLock;
        17: aload_0
        18: invokedynamic #104,  0            // InvokeDynamic #1:apply$mcI$sp:(Lorg/scalatest/concurrent/Conductors$Conductor$Clock;)Lscala/runtime/java8/JFunction0$mcI$sp;
        23: invokevirtual #107                // Method org/scalatest/concurrent/PimpedReadWriteLock.read:(Lscala/Function0;)Ljava/lang/Object;
        26: invokestatic  #113                // Method scala/runtime/BoxesRunTime.unboxToInt:(Ljava/lang/Object;)I
        29: istore_2
        30: aload_1
        31: monitorexit
        32: iload_2
        33: goto          39
        36: aload_1
        37: monitorexit
        38: athrow
        39: ireturn
      Exception table:
         from    to  target type
             7    30    36   any
      StackMapTable: number_of_entries = 2
        frame_type = 255 /* full_frame */
          offset_delta = 36
          locals = [ class org/scalatest/concurrent/Conductors$Conductor$Clock, class java/lang/Object ]
          stack = [ class java/lang/Throwable ]
        frame_type = 255 /* full_frame */
          offset_delta = 2
          locals = [ class org/scalatest/concurrent/Conductors$Conductor$Clock, class java/lang/Object, int ]
          stack = [ int ]
      LineNumberTable:
        line 928: 0
        line 929: 7
        line 928: 39
      LocalVariableTable:
        Start  Length  Slot  Name   Signature
            0      40     0  this   Lorg/scalatest/concurrent/Conductors$Conductor$Clock;

  public org.scalatest.Succeeded$ waitForBeat(int);
    descriptor: (I)Lorg/scalatest/Succeeded$;
    flags: (0x0001) ACC_PUBLIC
    Code:
      stack=2, locals=3, args_size=2
         0: aload_0
         1: invokespecial #46                 // Method lock:()Ljava/lang/Object;
         4: dup
         5: astore_2
         6: monitorenter
         7: iload_1
         8: aload_0
         9: invokespecial #118                // Method highestBeatBeingWaitedOn:()I
        12: if_icmple     23
        15: aload_0
        16: iload_1
        17: invokespecial #120                // Method highestBeatBeingWaitedOn_$eq:(I)V
        20: goto          23
        23: aload_0
        24: invokevirtual #122                // Method currentBeat:()I
        27: iload_1
        28: if_icmpge     38
        31: aload_0
        32: invokespecial #125                // Method liftedTree1$1:()V
        35: goto          23
        38: aload_2
        39: monitorexit
        40: goto          46
        43: aload_2
        44: monitorexit
        45: athrow
        46: getstatic     #91                 // Field org/scalatest/Succeeded$.MODULE$:Lorg/scalatest/Succeeded$;
        49: areturn
      Exception table:
         from    to  target type
             7    38    43   any
      StackMapTable: number_of_entries = 4
        frame_type = 252 /* append */
          offset_delta = 23
          locals = [ class java/lang/Object ]
        frame_type = 14 /* same */
        frame_type = 68 /* same_locals_1_stack_item */
          stack = [ class java/lang/Throwable ]
        frame_type = 2 /* same */
      LineNumberTable:
        line 937: 0
        line 938: 7
        line 939: 15
        line 940: 23
        line 941: 31
        line 940: 38
        line 948: 46
      LocalVariableTable:
        Start  Length  Slot  Name   Signature
            0      50     0  this   Lorg/scalatest/concurrent/Conductors$Conductor$Clock;
            0      50     1  beat   I
    MethodParameters:
      Name                           Flags
      beat                           final

  public boolean isAnyThreadWaitingForABeat();
    descriptor: ()Z
    flags: (0x0001) ACC_PUBLIC
    Code:
      stack=2, locals=3, args_size=1
         0: aload_0
         1: invokespecial #46                 // Method lock:()Ljava/lang/Object;
         4: dup
         5: astore_1
         6: monitorenter
         7: aload_0
         8: invokespecial #118                // Method highestBeatBeingWaitedOn:()I
        11: aload_0
        12: invokespecial #129                // Method currentTime:()I
        15: if_icmple     22
        18: iconst_1
        19: goto          23
        22: iconst_0
        23: istore_2
        24: aload_1
        25: monitorexit
        26: iload_2
        27: goto          33
        30: aload_1
        31: monitorexit
        32: athrow
        33: ireturn
      Exception table:
         from    to  target type
             7    24    30   any
      StackMapTable: number_of_entries = 4
        frame_type = 252 /* append */
          offset_delta = 22
          locals = [ class java/lang/Object ]
        frame_type = 64 /* same_locals_1_stack_item */
          stack = [ int ]
        frame_type = 70 /* same_locals_1_stack_item */
          stack = [ class java/lang/Throwable ]
        frame_type = 255 /* full_frame */
          offset_delta = 2
          locals = [ class org/scalatest/concurrent/Conductors$Conductor$Clock, class java/lang/Object, int ]
          stack = [ int ]
      LineNumberTable:
        line 961: 0
      LocalVariableTable:
        Start  Length  Slot  Name   Signature
            0      34     0  this   Lorg/scalatest/concurrent/Conductors$Conductor$Clock;

  public <T extends java.lang.Object> T withClockFrozen(scala.Function0<T>);
    descriptor: (Lscala/Function0;)Ljava/lang/Object;
    flags: (0x0001) ACC_PUBLIC
    Code:
      stack=2, locals=2, args_size=2
         0: getstatic     #52                 // Field org/scalatest/concurrent/PimpedReadWriteLock$.MODULE$:Lorg/scalatest/concurrent/PimpedReadWriteLock$;
         3: aload_0
         4: invokespecial #54                 // Method rwLock:()Ljava/util/concurrent/locks/ReentrantReadWriteLock;
         7: invokevirtual #58                 // Method org/scalatest/concurrent/PimpedReadWriteLock$.pimpMyReadWriteLock:(Ljava/util/concurrent/locks/ReadWriteLock;)Lorg/scalatest/concurrent/PimpedReadWriteLock;
        10: aload_1
        11: invokevirtual #107                // Method org/scalatest/concurrent/PimpedReadWriteLock.read:(Lscala/Function0;)Ljava/lang/Object;
        14: areturn
      LineNumberTable:
        line 970: 0
      LocalVariableTable:
        Start  Length  Slot  Name   Signature
            0      15     0  this   Lorg/scalatest/concurrent/Conductors$Conductor$Clock;
            0      15     1   fun   Lscala/Function0;
    Signature: #131                         // <T:Ljava/lang/Object;>(Lscala/Function0<TT;>;)TT;
    MethodParameters:
      Name                           Flags
      fun                            final

  public boolean isFrozen();
    descriptor: ()Z
    flags: (0x0001) ACC_PUBLIC
    Code:
      stack=2, locals=1, args_size=1
         0: aload_0
         1: invokespecial #54                 // Method rwLock:()Ljava/util/concurrent/locks/ReentrantReadWriteLock;
         4: invokevirtual #139                // Method java/util/concurrent/locks/ReentrantReadWriteLock.getReadLockCount:()I
         7: iconst_0
         8: if_icmple     15
        11: iconst_1
        12: goto          16
        15: iconst_0
        16: ireturn
      StackMapTable: number_of_entries = 2
        frame_type = 15 /* same */
        frame_type = 64 /* same_locals_1_stack_item */
          stack = [ int ]
      LineNumberTable:
        line 975: 0
      LocalVariableTable:
        Start  Length  Slot  Name   Signature
            0      17     0  this   Lorg/scalatest/concurrent/Conductors$Conductor$Clock;

  public org.scalatest.concurrent.Conductors$Conductor org$scalatest$concurrent$Conductors$Conductor$Clock$$$outer();
    descriptor: ()Lorg/scalatest/concurrent/Conductors$Conductor;
    flags: (0x1001) ACC_PUBLIC, ACC_SYNTHETIC
    Code:
      stack=1, locals=1, args_size=1
         0: aload_0
         1: getfield      #143                // Field $outer:Lorg/scalatest/concurrent/Conductors$Conductor;
         4: areturn
      LineNumberTable:
        line 870: 0
      LocalVariableTable:
        Start  Length  Slot  Name   Signature
            0       5     0  this   Lorg/scalatest/concurrent/Conductors$Conductor$Clock;

  public static final void $anonfun$advance$1(org.scalatest.concurrent.Conductors$Conductor$Clock);
    descriptor: (Lorg/scalatest/concurrent/Conductors$Conductor$Clock;)V
    flags: (0x1019) ACC_PUBLIC, ACC_STATIC, ACC_FINAL, ACC_SYNTHETIC
    Code:
      stack=3, locals=1, args_size=1
         0: aload_0
         1: aload_0
         2: invokespecial #129                // Method currentTime:()I
         5: iconst_1
         6: iadd
         7: invokespecial #146                // Method currentTime_$eq:(I)V
        10: return
      LineNumberTable:
        line 917: 0
      LocalVariableTable:
        Start  Length  Slot  Name   Signature
            0      11     0 $this   Lorg/scalatest/concurrent/Conductors$Conductor$Clock;
    MethodParameters:
      Name                           Flags
      $this                          final synthetic

  public static final int $anonfun$currentBeat$1(org.scalatest.concurrent.Conductors$Conductor$Clock);
    descriptor: (Lorg/scalatest/concurrent/Conductors$Conductor$Clock;)I
    flags: (0x1019) ACC_PUBLIC, ACC_STATIC, ACC_FINAL, ACC_SYNTHETIC
    Code:
      stack=1, locals=1, args_size=1
         0: aload_0
         1: invokespecial #129                // Method currentTime:()I
         4: ireturn
      LineNumberTable:
        line 929: 0
      LocalVariableTable:
        Start  Length  Slot  Name   Signature
            0       5     0 $this   Lorg/scalatest/concurrent/Conductors$Conductor$Clock;
    MethodParameters:
      Name                           Flags
      $this                          final synthetic

  private final void liftedTree1$1();
    descriptor: ()V
    flags: (0x1012) ACC_PRIVATE, ACC_FINAL, ACC_SYNTHETIC
    Code:
      stack=3, locals=2, args_size=1
         0: aload_0
         1: invokespecial #46                 // Method lock:()Ljava/lang/Object;
         4: invokevirtual #151                // Method java/lang/Object.wait:()V
         7: goto          20
        10: astore_1
        11: new           #153                // class java/lang/AssertionError
        14: dup
        15: aload_1
        16: invokespecial #157                // Method java/lang/AssertionError."<init>":(Ljava/lang/Object;)V
        19: athrow
        20: return
      Exception table:
         from    to  target type
             0     7    10   Class java/lang/InterruptedException
      StackMapTable: number_of_entries = 2
        frame_type = 74 /* same_locals_1_stack_item */
          stack = [ class java/lang/InterruptedException ]
        frame_type = 9 /* same */
      LineNumberTable:
        line 942: 0
        line 944: 11
      LocalVariableTable:
        Start  Length  Slot  Name   Signature
           10      10     1     e   Ljava/lang/InterruptedException;
            0      21     0  this   Lorg/scalatest/concurrent/Conductors$Conductor$Clock;

  public org.scalatest.concurrent.Conductors$Conductor$Clock(org.scalatest.concurrent.Conductors$Conductor);
    descriptor: (Lorg/scalatest/concurrent/Conductors$Conductor;)V
    flags: (0x0001) ACC_PUBLIC
    Code:
      stack=3, locals=2, args_size=2
         0: aload_1
         1: ifnonnull     6
         4: aconst_null
         5: athrow
         6: aload_0
         7: aload_1
         8: putfield      #143                // Field $outer:Lorg/scalatest/concurrent/Conductors$Conductor;
        11: aload_0
        12: invokespecial #162                // Method java/lang/Object."<init>":()V
        15: aload_0
        16: iconst_0
        17: putfield      #28                 // Field currentTime:I
        20: aload_0
        21: new           #4                  // class java/lang/Object
        24: dup
        25: invokespecial #162                // Method java/lang/Object."<init>":()V
        28: putfield      #36                 // Field lock:Ljava/lang/Object;
        31: aload_0
        32: new           #136                // class java/util/concurrent/locks/ReentrantReadWriteLock
        35: dup
        36: invokespecial #163                // Method java/util/concurrent/locks/ReentrantReadWriteLock."<init>":()V
        39: putfield      #39                 // Field rwLock:Ljava/util/concurrent/locks/ReentrantReadWriteLock;
        42: aload_0
        43: iconst_0
        44: putfield      #41                 // Field highestBeatBeingWaitedOn:I
        47: return
      StackMapTable: number_of_entries = 1
        frame_type = 6 /* same */
      LineNumberTable:
        line 870: 0
        line 1020: 11
        line 876: 15
        line 880: 20
        line 896: 31
        line 898: 42
        line 870: 47
      LocalVariableTable:
        Start  Length  Slot  Name   Signature
            0      48     0  this   Lorg/scalatest/concurrent/Conductors$Conductor$Clock;
            0      48     1 $outer   Lorg/scalatest/concurrent/Conductors$Conductor;
    MethodParameters:
      Name                           Flags
      $outer                         final synthetic

  private static java.lang.Object $deserializeLambda$(java.lang.invoke.SerializedLambda);
    descriptor: (Ljava/lang/invoke/SerializedLambda;)Ljava/lang/Object;
    flags: (0x100a) ACC_PRIVATE, ACC_STATIC, ACC_SYNTHETIC
    Code:
      stack=1, locals=1, args_size=1
         0: aload_0
         1: invokedynamic #175,  0            // InvokeDynamic #2:lambdaDeserialize:(Ljava/lang/invoke/SerializedLambda;)Ljava/lang/Object;
         6: areturn
}
InnerClasses:
  public static final #10= #7 of #9;      // Lookup=class java/lang/invoke/MethodHandles$Lookup of class java/lang/invoke/MethodHandles
  public final #15= #12 of #14;           // Conductor=class org/scalatest/concurrent/Conductors$Conductor of class org/scalatest/concurrent/Conductors
  private #16= #2 of #12;                 // Clock=class org/scalatest/concurrent/Conductors$Conductor$Clock of class org/scalatest/concurrent/Conductors$Conductor
SourceFile: "Conductors.scala"
BootstrapMethods:
  0: #73 REF_invokeStatic java/lang/invoke/LambdaMetafactory.altMetafactory:(Ljava/lang/invoke/MethodHandles$Lookup;Ljava/lang/String;Ljava/lang/invoke/MethodType;[Ljava/lang/Object;)Ljava/lang/invoke/CallSite;
    Method arguments:
      #60 ()V
      #65 REF_invokeStatic org/scalatest/concurrent/Conductors$Conductor$Clock.$anonfun$advance$1:(Lorg/scalatest/concurrent/Conductors$Conductor$Clock;)V
      #60 ()V
      #66 1
  1: #73 REF_invokeStatic java/lang/invoke/LambdaMetafactory.altMetafactory:(Ljava/lang/invoke/MethodHandles$Lookup;Ljava/lang/String;Ljava/lang/invoke/MethodType;[Ljava/lang/Object;)Ljava/lang/invoke/CallSite;
    Method arguments:
      #95 ()I
      #100 REF_invokeStatic org/scalatest/concurrent/Conductors$Conductor$Clock.$anonfun$currentBeat$1:(Lorg/scalatest/concurrent/Conductors$Conductor$Clock;)I
      #95 ()I
      #66 1
  2: #172 REF_invokeStatic scala/runtime/LambdaDeserialize.bootstrap:(Ljava/lang/invoke/MethodHandles$Lookup;Ljava/lang/String;Ljava/lang/invoke/MethodType;[Ljava/lang/invoke/MethodHandle;)Ljava/lang/invoke/CallSite;
    Method arguments:
      #65 REF_invokeStatic org/scalatest/concurrent/Conductors$Conductor$Clock.$anonfun$advance$1:(Lorg/scalatest/concurrent/Conductors$Conductor$Clock;)V
      #100 REF_invokeStatic org/scalatest/concurrent/Conductors$Conductor$Clock.$anonfun$currentBeat$1:(Lorg/scalatest/concurrent/Conductors$Conductor$Clock;)I
  ScalaInlineInfo: length = 0x59 (unknown attribute)
   01 00 00 11 00 3D 00 3E 01 00 60 00 61 01 00 9A
   00 A0 00 00 2B 00 2C 00 00 5E 00 1A 00 00 11 00
   1A 01 00 1F 00 20 01 00 17 00 1A 01 00 2A 00 20
   01 00 7E 00 7F 00 00 86 00 7F 00 00 7B 00 3B 01
   00 13 00 22 01 00 8C 00 8D 00 00 15 00 25 01 00
   72 00 73 00 00 82 00 51 00
  Scala: length = 0x0 (unknown attribute)

