Classfile /Users/mw/Projects/slang-braindump/.jar/jar11/assemble/slang-braindump/assemble/content/org/scalatest/concurrent/Conductors$Conductor.class
  Last modified May 29, 2022; size 16133 bytes
  SHA-256 checksum 767c84e34623fd8bbedbc620c172bf25e1303c95ccf22b3ff2c648c1eb35fd39
  Compiled from "Conductors.scala"
public final class org.scalatest.concurrent.Conductors$Conductor
  minor version: 0
  major version: 52
  flags: (0x0031) ACC_PUBLIC, ACC_FINAL, ACC_SUPER
  this_class: #2                          // org/scalatest/concurrent/Conductors$Conductor
  super_class: #4                         // java/lang/Object
  interfaces: 0, fields: 15, methods: 38, attributes: 5
Constant pool:
    #1 = Utf8               org/scalatest/concurrent/Conductors$Conductor
    #2 = Class              #1            // org/scalatest/concurrent/Conductors$Conductor
    #3 = Utf8               java/lang/Object
    #4 = Class              #3            // java/lang/Object
    #5 = Utf8               Conductors.scala
    #6 = Utf8               java/lang/invoke/MethodHandles$Lookup
    #7 = Class              #6            // java/lang/invoke/MethodHandles$Lookup
    #8 = Utf8               java/lang/invoke/MethodHandles
    #9 = Class              #8            // java/lang/invoke/MethodHandles
   #10 = Utf8               Lookup
   #11 = Utf8               org/scalatest/concurrent/AbstractPatienceConfiguration$PatienceConfig
   #12 = Class              #11           // org/scalatest/concurrent/AbstractPatienceConfiguration$PatienceConfig
   #13 = Utf8               org/scalatest/concurrent/AbstractPatienceConfiguration
   #14 = Class              #13           // org/scalatest/concurrent/AbstractPatienceConfiguration
   #15 = Utf8               PatienceConfig
   #16 = Utf8               org/scalatest/concurrent/Conductors
   #17 = Class              #16           // org/scalatest/concurrent/Conductors
   #18 = Utf8               Conductor
   #19 = Utf8               org/scalatest/concurrent/Conductors$Conductor$Clock
   #20 = Class              #19           // org/scalatest/concurrent/Conductors$Conductor$Clock
   #21 = Utf8               Clock
   #22 = Utf8               org/scalatest/concurrent/Conductors$Conductor$ClockThread
   #23 = Class              #22           // org/scalatest/concurrent/Conductors$Conductor$ClockThread
   #24 = Utf8               ClockThread
   #25 = Utf8               org/scalatest/concurrent/Conductors$Conductor$ClockThread$
   #26 = Class              #25           // org/scalatest/concurrent/Conductors$Conductor$ClockThread$
   #27 = Utf8               ClockThread$
   #28 = Utf8               org/scalatest/concurrent/Conductors$Conductor$ConductorState
   #29 = Class              #28           // org/scalatest/concurrent/Conductors$Conductor$ConductorState
   #30 = Utf8               ConductorState
   #31 = Utf8               org/scalatest/concurrent/Conductors$Conductor$Setup$
   #32 = Class              #31           // org/scalatest/concurrent/Conductors$Conductor$Setup$
   #33 = Utf8               Setup$
   #34 = Utf8               org/scalatest/concurrent/Conductors$Conductor$TestFinished$
   #35 = Class              #34           // org/scalatest/concurrent/Conductors$Conductor$TestFinished$
   #36 = Utf8               TestFinished$
   #37 = Utf8               org/scalatest/concurrent/Conductors$Conductor$TestStarted$
   #38 = Class              #37           // org/scalatest/concurrent/Conductors$Conductor$TestStarted$
   #39 = Utf8               TestStarted$
   #40 = Utf8               org/scalatest/concurrent/Conductors$Conductor$TestThread
   #41 = Class              #40           // org/scalatest/concurrent/Conductors$Conductor$TestThread
   #42 = Utf8               TestThread
   #43 = Utf8               org/scalatest/concurrent/Conductors$Conductor$TestThread$
   #44 = Class              #43           // org/scalatest/concurrent/Conductors$Conductor$TestThread$
   #45 = Utf8               TestThread$
   #46 = Utf8               org/scalatest/concurrent/PatienceConfiguration$Interval
   #47 = Class              #46           // org/scalatest/concurrent/PatienceConfiguration$Interval
   #48 = Utf8               org/scalatest/concurrent/PatienceConfiguration
   #49 = Class              #48           // org/scalatest/concurrent/PatienceConfiguration
   #50 = Utf8               Interval
   #51 = Utf8               org/scalatest/concurrent/PatienceConfiguration$Timeout
   #52 = Class              #51           // org/scalatest/concurrent/PatienceConfiguration$Timeout
   #53 = Utf8               Timeout
   #54 = Utf8               TestThread$module
   #55 = Utf8               Lorg/scalatest/concurrent/Conductors$Conductor$TestThread$;
   #56 = Utf8               ClockThread$module
   #57 = Utf8               Lorg/scalatest/concurrent/Conductors$Conductor$ClockThread$;
   #58 = Utf8               Setup$module
   #59 = Utf8               Lorg/scalatest/concurrent/Conductors$Conductor$Setup$;
   #60 = Utf8               TestStarted$module
   #61 = Utf8               Lorg/scalatest/concurrent/Conductors$Conductor$TestStarted$;
   #62 = Utf8               TestFinished$module
   #63 = Utf8               Lorg/scalatest/concurrent/Conductors$Conductor$TestFinished$;
   #64 = Utf8               org$scalatest$concurrent$Conductors$Conductor$$clock
   #65 = Utf8               Lorg/scalatest/concurrent/Conductors$Conductor$Clock;
   #66 = Utf8               org$scalatest$concurrent$Conductors$Conductor$$threadGroup
   #67 = Utf8               Ljava/lang/ThreadGroup;
   #68 = Utf8               threads
   #69 = Utf8               Ljava/util/concurrent/CopyOnWriteArrayList;
   #70 = Utf8               Ljava/util/concurrent/CopyOnWriteArrayList<Ljava/lang/Thread;>;
   #71 = Utf8               threadNames
   #72 = Utf8               Ljava/util/concurrent/CopyOnWriteArrayList<Ljava/lang/String;>;
   #73 = Utf8               org$scalatest$concurrent$Conductors$Conductor$$mainThread
   #74 = Utf8               Ljava/lang/Thread;
   #75 = Utf8               org$scalatest$concurrent$Conductors$Conductor$$firstExceptionThrown
   #76 = Utf8               Ljava/util/concurrent/ArrayBlockingQueue;
   #77 = Utf8               Ljava/util/concurrent/ArrayBlockingQueue<Ljava/lang/Throwable;>;
   #78 = Utf8               org$scalatest$concurrent$Conductors$Conductor$$testThreadsStartingCounter
   #79 = Utf8               Lorg/scalatest/concurrent/TestThreadsStartingCounter;
   #80 = Utf8               org$scalatest$concurrent$Conductors$Conductor$$greenLightForTestThreads
   #81 = Utf8               Lorg/scalatest/CountDownLatch;
   #82 = Utf8               currentState
   #83 = Utf8               Ljava/util/concurrent/atomic/AtomicReference;
   #84 = Utf8               Ljava/util/concurrent/atomic/AtomicReference<Lorg/scalatest/concurrent/Conductors$Conductor$ConductorState;>;
   #85 = Utf8               $outer
   #86 = Utf8               Lorg/scalatest/concurrent/Conductors;
   #87 = Utf8               ()Lorg/scalatest/concurrent/Conductors$Conductor$TestThread$;
   #88 = NameAndType        #54:#55       // TestThread$module:Lorg/scalatest/concurrent/Conductors$Conductor$TestThread$;
   #89 = Fieldref           #2.#88        // org/scalatest/concurrent/Conductors$Conductor.TestThread$module:Lorg/scalatest/concurrent/Conductors$Conductor$TestThread$;
   #90 = Utf8               TestThread$lzycompute$1
   #91 = Utf8               ()V
   #92 = NameAndType        #90:#91       // TestThread$lzycompute$1:()V
   #93 = Methodref          #2.#92        // org/scalatest/concurrent/Conductors$Conductor.TestThread$lzycompute$1:()V
   #94 = Utf8               this
   #95 = Utf8               Lorg/scalatest/concurrent/Conductors$Conductor;
   #96 = Utf8               ()Lorg/scalatest/concurrent/Conductors$Conductor$ClockThread$;
   #97 = NameAndType        #56:#57       // ClockThread$module:Lorg/scalatest/concurrent/Conductors$Conductor$ClockThread$;
   #98 = Fieldref           #2.#97        // org/scalatest/concurrent/Conductors$Conductor.ClockThread$module:Lorg/scalatest/concurrent/Conductors$Conductor$ClockThread$;
   #99 = Utf8               ClockThread$lzycompute$1
  #100 = NameAndType        #99:#91       // ClockThread$lzycompute$1:()V
  #101 = Methodref          #2.#100       // org/scalatest/concurrent/Conductors$Conductor.ClockThread$lzycompute$1:()V
  #102 = Utf8               Setup
  #103 = Utf8               ()Lorg/scalatest/concurrent/Conductors$Conductor$Setup$;
  #104 = NameAndType        #58:#59       // Setup$module:Lorg/scalatest/concurrent/Conductors$Conductor$Setup$;
  #105 = Fieldref           #2.#104       // org/scalatest/concurrent/Conductors$Conductor.Setup$module:Lorg/scalatest/concurrent/Conductors$Conductor$Setup$;
  #106 = Utf8               Setup$lzycompute$1
  #107 = NameAndType        #106:#91      // Setup$lzycompute$1:()V
  #108 = Methodref          #2.#107       // org/scalatest/concurrent/Conductors$Conductor.Setup$lzycompute$1:()V
  #109 = Utf8               TestStarted
  #110 = Utf8               ()Lorg/scalatest/concurrent/Conductors$Conductor$TestStarted$;
  #111 = NameAndType        #60:#61       // TestStarted$module:Lorg/scalatest/concurrent/Conductors$Conductor$TestStarted$;
  #112 = Fieldref           #2.#111       // org/scalatest/concurrent/Conductors$Conductor.TestStarted$module:Lorg/scalatest/concurrent/Conductors$Conductor$TestStarted$;
  #113 = Utf8               TestStarted$lzycompute$1
  #114 = NameAndType        #113:#91      // TestStarted$lzycompute$1:()V
  #115 = Methodref          #2.#114       // org/scalatest/concurrent/Conductors$Conductor.TestStarted$lzycompute$1:()V
  #116 = Utf8               TestFinished
  #117 = Utf8               ()Lorg/scalatest/concurrent/Conductors$Conductor$TestFinished$;
  #118 = NameAndType        #62:#63       // TestFinished$module:Lorg/scalatest/concurrent/Conductors$Conductor$TestFinished$;
  #119 = Fieldref           #2.#118       // org/scalatest/concurrent/Conductors$Conductor.TestFinished$module:Lorg/scalatest/concurrent/Conductors$Conductor$TestFinished$;
  #120 = Utf8               TestFinished$lzycompute$1
  #121 = NameAndType        #120:#91      // TestFinished$lzycompute$1:()V
  #122 = Methodref          #2.#121       // org/scalatest/concurrent/Conductors$Conductor.TestFinished$lzycompute$1:()V
  #123 = Utf8               ()Lorg/scalatest/concurrent/Conductors$Conductor$Clock;
  #124 = NameAndType        #64:#65       // org$scalatest$concurrent$Conductors$Conductor$$clock:Lorg/scalatest/concurrent/Conductors$Conductor$Clock;
  #125 = Fieldref           #2.#124       // org/scalatest/concurrent/Conductors$Conductor.org$scalatest$concurrent$Conductors$Conductor$$clock:Lorg/scalatest/concurrent/Conductors$Conductor$Clock;
  #126 = Utf8               ()Ljava/lang/ThreadGroup;
  #127 = NameAndType        #66:#67       // org$scalatest$concurrent$Conductors$Conductor$$threadGroup:Ljava/lang/ThreadGroup;
  #128 = Fieldref           #2.#127       // org/scalatest/concurrent/Conductors$Conductor.org$scalatest$concurrent$Conductors$Conductor$$threadGroup:Ljava/lang/ThreadGroup;
  #129 = Utf8               ()Ljava/util/concurrent/CopyOnWriteArrayList;
  #130 = Utf8               ()Ljava/util/concurrent/CopyOnWriteArrayList<Ljava/lang/Thread;>;
  #131 = NameAndType        #68:#69       // threads:Ljava/util/concurrent/CopyOnWriteArrayList;
  #132 = Fieldref           #2.#131       // org/scalatest/concurrent/Conductors$Conductor.threads:Ljava/util/concurrent/CopyOnWriteArrayList;
  #133 = Utf8               ()Ljava/util/concurrent/CopyOnWriteArrayList<Ljava/lang/String;>;
  #134 = NameAndType        #71:#69       // threadNames:Ljava/util/concurrent/CopyOnWriteArrayList;
  #135 = Fieldref           #2.#134       // org/scalatest/concurrent/Conductors$Conductor.threadNames:Ljava/util/concurrent/CopyOnWriteArrayList;
  #136 = Utf8               ()Ljava/lang/Thread;
  #137 = NameAndType        #73:#74       // org$scalatest$concurrent$Conductors$Conductor$$mainThread:Ljava/lang/Thread;
  #138 = Fieldref           #2.#137       // org/scalatest/concurrent/Conductors$Conductor.org$scalatest$concurrent$Conductors$Conductor$$mainThread:Ljava/lang/Thread;
  #139 = Utf8               thread
  #140 = Utf8               (Lscala/Function0;)Ljava/lang/Thread;
  #141 = Utf8               (Lscala/Function0<Ljava/lang/Object;>;)Ljava/lang/Thread;
  #142 = Utf8               fun
  #143 = Utf8               java/lang/StringBuilder
  #144 = Class              #143          // java/lang/StringBuilder
  #145 = Integer            17
  #146 = Utf8               <init>
  #147 = Utf8               (I)V
  #148 = NameAndType        #146:#147     // "<init>":(I)V
  #149 = Methodref          #144.#148     // java/lang/StringBuilder."<init>":(I)V
  #150 = Utf8               Conductor-Thread-
  #151 = String             #150          // Conductor-Thread-
  #152 = Utf8               append
  #153 = Utf8               (Ljava/lang/String;)Ljava/lang/StringBuilder;
  #154 = NameAndType        #152:#153     // append:(Ljava/lang/String;)Ljava/lang/StringBuilder;
  #155 = Methodref          #144.#154     // java/lang/StringBuilder.append:(Ljava/lang/String;)Ljava/lang/StringBuilder;
  #156 = NameAndType        #68:#129      // threads:()Ljava/util/concurrent/CopyOnWriteArrayList;
  #157 = Methodref          #2.#156       // org/scalatest/concurrent/Conductors$Conductor.threads:()Ljava/util/concurrent/CopyOnWriteArrayList;
  #158 = Utf8               java/util/concurrent/CopyOnWriteArrayList
  #159 = Class              #158          // java/util/concurrent/CopyOnWriteArrayList
  #160 = Utf8               size
  #161 = Utf8               ()I
  #162 = NameAndType        #160:#161     // size:()I
  #163 = Methodref          #159.#162     // java/util/concurrent/CopyOnWriteArrayList.size:()I
  #164 = Utf8               (I)Ljava/lang/StringBuilder;
  #165 = NameAndType        #152:#164     // append:(I)Ljava/lang/StringBuilder;
  #166 = Methodref          #144.#165     // java/lang/StringBuilder.append:(I)Ljava/lang/StringBuilder;
  #167 = Utf8               toString
  #168 = Utf8               ()Ljava/lang/String;
  #169 = NameAndType        #167:#168     // toString:()Ljava/lang/String;
  #170 = Methodref          #144.#169     // java/lang/StringBuilder.toString:()Ljava/lang/String;
  #171 = Utf8               org/scalactic/source/Position
  #172 = Class              #171          // org/scalactic/source/Position
  #173 = String             #5            // Conductors.scala
  #174 = Utf8               Please set the environment variable SCALACTIC_FILL_FILE_PATHNAMES to yes at compile time to enable this feature.
  #175 = String             #174          // Please set the environment variable SCALACTIC_FILL_FILE_PATHNAMES to yes at compile time to enable this feature.
  #176 = Utf8               (Ljava/lang/String;Ljava/lang/String;I)V
  #177 = NameAndType        #146:#176     // "<init>":(Ljava/lang/String;Ljava/lang/String;I)V
  #178 = Methodref          #172.#177     // org/scalactic/source/Position."<init>":(Ljava/lang/String;Ljava/lang/String;I)V
  #179 = Utf8               threadNamed
  #180 = Utf8               (Ljava/lang/String;Lscala/Function0;Lorg/scalactic/source/Position;)Ljava/lang/Thread;
  #181 = NameAndType        #179:#180     // threadNamed:(Ljava/lang/String;Lscala/Function0;Lorg/scalactic/source/Position;)Ljava/lang/Thread;
  #182 = Methodref          #2.#181       // org/scalatest/concurrent/Conductors$Conductor.threadNamed:(Ljava/lang/String;Lscala/Function0;Lorg/scalactic/source/Position;)Ljava/lang/Thread;
  #183 = Utf8               Lscala/Function0;
  #184 = Utf8               (Ljava/lang/String;Lscala/Function0<Ljava/lang/Object;>;Lorg/scalactic/source/Position;)Ljava/lang/Thread;
  #185 = Utf8               name
  #186 = Utf8               pos
  #187 = Utf8               ()Ljava/util/concurrent/atomic/AtomicReference;
  #188 = NameAndType        #82:#187      // currentState:()Ljava/util/concurrent/atomic/AtomicReference;
  #189 = Methodref          #2.#188       // org/scalatest/concurrent/Conductors$Conductor.currentState:()Ljava/util/concurrent/atomic/AtomicReference;
  #190 = Utf8               java/util/concurrent/atomic/AtomicReference
  #191 = Class              #190          // java/util/concurrent/atomic/AtomicReference
  #192 = Utf8               get
  #193 = Utf8               ()Ljava/lang/Object;
  #194 = NameAndType        #192:#193     // get:()Ljava/lang/Object;
  #195 = Methodref          #191.#194     // java/util/concurrent/atomic/AtomicReference.get:()Ljava/lang/Object;
  #196 = NameAndType        #116:#117     // TestFinished:()Lorg/scalatest/concurrent/Conductors$Conductor$TestFinished$;
  #197 = Methodref          #2.#196       // org/scalatest/concurrent/Conductors$Conductor.TestFinished:()Lorg/scalatest/concurrent/Conductors$Conductor$TestFinished$;
  #198 = Utf8               equals
  #199 = Utf8               (Ljava/lang/Object;)Z
  #200 = NameAndType        #198:#199     // equals:(Ljava/lang/Object;)Z
  #201 = Methodref          #4.#200       // java/lang/Object.equals:(Ljava/lang/Object;)Z
  #202 = Utf8               org/scalatest/exceptions/NotAllowedException
  #203 = Class              #202          // org/scalatest/exceptions/NotAllowedException
  #204 = Utf8               org/scalatest/Resources$
  #205 = Class              #204          // org/scalatest/Resources$
  #206 = Utf8               MODULE$
  #207 = Utf8               Lorg/scalatest/Resources$;
  #208 = NameAndType        #206:#207     // MODULE$:Lorg/scalatest/Resources$;
  #209 = Fieldref           #205.#208     // org/scalatest/Resources$.MODULE$:Lorg/scalatest/Resources$;
  #210 = Utf8               threadCalledAfterConductingHasCompleted
  #211 = NameAndType        #210:#168     // threadCalledAfterConductingHasCompleted:()Ljava/lang/String;
  #212 = Methodref          #205.#211     // org/scalatest/Resources$.threadCalledAfterConductingHasCompleted:()Ljava/lang/String;
  #213 = Utf8               (Ljava/lang/String;Lorg/scalactic/source/Position;)V
  #214 = NameAndType        #146:#213     // "<init>":(Ljava/lang/String;Lorg/scalactic/source/Position;)V
  #215 = Methodref          #203.#214     // org/scalatest/exceptions/NotAllowedException."<init>":(Ljava/lang/String;Lorg/scalactic/source/Position;)V
  #216 = NameAndType        #71:#129      // threadNames:()Ljava/util/concurrent/CopyOnWriteArrayList;
  #217 = Methodref          #2.#216       // org/scalatest/concurrent/Conductors$Conductor.threadNames:()Ljava/util/concurrent/CopyOnWriteArrayList;
  #218 = Utf8               contains
  #219 = NameAndType        #218:#199     // contains:(Ljava/lang/Object;)Z
  #220 = Methodref          #159.#219     // java/util/concurrent/CopyOnWriteArrayList.contains:(Ljava/lang/Object;)Z
  #221 = Utf8               cantRegisterThreadsWithSameName
  #222 = Utf8               (Ljava/lang/Object;)Ljava/lang/String;
  #223 = NameAndType        #221:#222     // cantRegisterThreadsWithSameName:(Ljava/lang/Object;)Ljava/lang/String;
  #224 = Methodref          #205.#223     // org/scalatest/Resources$.cantRegisterThreadsWithSameName:(Ljava/lang/Object;)Ljava/lang/String;
  #225 = MethodType         #91           //  ()V
  #226 = Utf8               $anonfun$threadNamed$1
  #227 = Utf8               (Lscala/Function0;)V
  #228 = NameAndType        #226:#227     // $anonfun$threadNamed$1:(Lscala/Function0;)V
  #229 = Methodref          #2.#228       // org/scalatest/concurrent/Conductors$Conductor.$anonfun$threadNamed$1:(Lscala/Function0;)V
  #230 = MethodHandle       6:#229        // REF_invokeStatic org/scalatest/concurrent/Conductors$Conductor.$anonfun$threadNamed$1:(Lscala/Function0;)V
  #231 = Integer            1
  #232 = Utf8               java/lang/invoke/LambdaMetafactory
  #233 = Class              #232          // java/lang/invoke/LambdaMetafactory
  #234 = Utf8               altMetafactory
  #235 = Utf8               (Ljava/lang/invoke/MethodHandles$Lookup;Ljava/lang/String;Ljava/lang/invoke/MethodType;[Ljava/lang/Object;)Ljava/lang/invoke/CallSite;
  #236 = NameAndType        #234:#235     // altMetafactory:(Ljava/lang/invoke/MethodHandles$Lookup;Ljava/lang/String;Ljava/lang/invoke/MethodType;[Ljava/lang/Object;)Ljava/lang/invoke/CallSite;
  #237 = Methodref          #233.#236     // java/lang/invoke/LambdaMetafactory.altMetafactory:(Ljava/lang/invoke/MethodHandles$Lookup;Ljava/lang/String;Ljava/lang/invoke/MethodType;[Ljava/lang/Object;)Ljava/lang/invoke/CallSite;
  #238 = MethodHandle       6:#237        // REF_invokeStatic java/lang/invoke/LambdaMetafactory.altMetafactory:(Ljava/lang/invoke/MethodHandles$Lookup;Ljava/lang/String;Ljava/lang/invoke/MethodType;[Ljava/lang/Object;)Ljava/lang/invoke/CallSite;
  #239 = Utf8               apply$mcV$sp
  #240 = Utf8               (Lscala/Function0;)Lscala/runtime/java8/JFunction0$mcV$sp;
  #241 = NameAndType        #239:#240     // apply$mcV$sp:(Lscala/Function0;)Lscala/runtime/java8/JFunction0$mcV$sp;
  #242 = InvokeDynamic      #0:#241       // #0:apply$mcV$sp:(Lscala/Function0;)Lscala/runtime/java8/JFunction0$mcV$sp;
  #243 = Utf8               (Lorg/scalatest/concurrent/Conductors$Conductor;Ljava/lang/String;Lscala/Function0;)V
  #244 = NameAndType        #146:#243     // "<init>":(Lorg/scalatest/concurrent/Conductors$Conductor;Ljava/lang/String;Lscala/Function0;)V
  #245 = Methodref          #41.#244      // org/scalatest/concurrent/Conductors$Conductor$TestThread."<init>":(Lorg/scalatest/concurrent/Conductors$Conductor;Ljava/lang/String;Lscala/Function0;)V
  #246 = Utf8               add
  #247 = NameAndType        #246:#199     // add:(Ljava/lang/Object;)Z
  #248 = Methodref          #159.#247     // java/util/concurrent/CopyOnWriteArrayList.add:(Ljava/lang/Object;)Z
  #249 = Utf8               start
  #250 = NameAndType        #249:#91      // start:()V
  #251 = Methodref          #41.#250      // org/scalatest/concurrent/Conductors$Conductor$TestThread.start:()V
  #252 = Utf8               t
  #253 = Utf8               Lorg/scalatest/concurrent/Conductors$Conductor$TestThread;
  #254 = Utf8               Ljava/lang/String;
  #255 = Utf8               Lorg/scalactic/source/Position;
  #256 = Utf8               java/lang/String
  #257 = Class              #256          // java/lang/String
  #258 = Utf8               scala/Function0
  #259 = Class              #258          // scala/Function0
  #260 = Utf8               ()Ljava/util/concurrent/ArrayBlockingQueue;
  #261 = Utf8               ()Ljava/util/concurrent/ArrayBlockingQueue<Ljava/lang/Throwable;>;
  #262 = NameAndType        #75:#76       // org$scalatest$concurrent$Conductors$Conductor$$firstExceptionThrown:Ljava/util/concurrent/ArrayBlockingQueue;
  #263 = Fieldref           #2.#262       // org/scalatest/concurrent/Conductors$Conductor.org$scalatest$concurrent$Conductors$Conductor$$firstExceptionThrown:Ljava/util/concurrent/ArrayBlockingQueue;
  #264 = Utf8               whenFinished
  #265 = Utf8               (Lscala/Function0;Lorg/scalactic/source/Position;)Lorg/scalatest/compatible/Assertion;
  #266 = Utf8               (Lscala/Function0<Lorg/scalatest/compatible/Assertion;>;Lorg/scalactic/source/Position;)Lorg/scalatest/compatible/Assertion;
  #267 = Utf8               java/lang/Thread
  #268 = Class              #267          // java/lang/Thread
  #269 = Utf8               currentThread
  #270 = NameAndType        #269:#136     // currentThread:()Ljava/lang/Thread;
  #271 = Methodref          #268.#270     // java/lang/Thread.currentThread:()Ljava/lang/Thread;
  #272 = NameAndType        #73:#136      // org$scalatest$concurrent$Conductors$Conductor$$mainThread:()Ljava/lang/Thread;
  #273 = Methodref          #2.#272       // org/scalatest/concurrent/Conductors$Conductor.org$scalatest$concurrent$Conductors$Conductor$$mainThread:()Ljava/lang/Thread;
  #274 = Utf8               whenFinishedCanOnlyBeCalledByMainThread
  #275 = NameAndType        #274:#168     // whenFinishedCanOnlyBeCalledByMainThread:()Ljava/lang/String;
  #276 = Methodref          #205.#275     // org/scalatest/Resources$.whenFinishedCanOnlyBeCalledByMainThread:()Ljava/lang/String;
  #277 = Utf8               conductingHasBegun
  #278 = Utf8               ()Z
  #279 = NameAndType        #277:#278     // conductingHasBegun:()Z
  #280 = Methodref          #2.#279       // org/scalatest/concurrent/Conductors$Conductor.conductingHasBegun:()Z
  #281 = Utf8               cannotInvokeWhenFinishedAfterConduct
  #282 = NameAndType        #281:#168     // cannotInvokeWhenFinishedAfterConduct:()Ljava/lang/String;
  #283 = Methodref          #205.#282     // org/scalatest/Resources$.cannotInvokeWhenFinishedAfterConduct:()Ljava/lang/String;
  #284 = NameAndType        #85:#86       // $outer:Lorg/scalatest/concurrent/Conductors;
  #285 = Fieldref           #2.#284       // org/scalatest/concurrent/Conductors$Conductor.$outer:Lorg/scalatest/concurrent/Conductors;
  #286 = Utf8               patienceConfig
  #287 = Utf8               ()Lorg/scalatest/concurrent/AbstractPatienceConfiguration$PatienceConfig;
  #288 = NameAndType        #286:#287     // patienceConfig:()Lorg/scalatest/concurrent/AbstractPatienceConfiguration$PatienceConfig;
  #289 = InterfaceMethodref #17.#288      // org/scalatest/concurrent/Conductors.patienceConfig:()Lorg/scalatest/concurrent/AbstractPatienceConfiguration$PatienceConfig;
  #290 = Utf8               conduct
  #291 = Utf8               (Lorg/scalatest/concurrent/AbstractPatienceConfiguration$PatienceConfig;Lorg/scalactic/source/Position;)Lorg/scalatest/compatible/Assertion;
  #292 = NameAndType        #290:#291     // conduct:(Lorg/scalatest/concurrent/AbstractPatienceConfiguration$PatienceConfig;Lorg/scalactic/source/Position;)Lorg/scalatest/compatible/Assertion;
  #293 = Methodref          #2.#292       // org/scalatest/concurrent/Conductors$Conductor.conduct:(Lorg/scalatest/concurrent/AbstractPatienceConfiguration$PatienceConfig;Lorg/scalactic/source/Position;)Lorg/scalatest/compatible/Assertion;
  #294 = Utf8               apply
  #295 = NameAndType        #294:#193     // apply:()Ljava/lang/Object;
  #296 = InterfaceMethodref #259.#295     // scala/Function0.apply:()Ljava/lang/Object;
  #297 = Utf8               org/scalatest/compatible/Assertion
  #298 = Class              #297          // org/scalatest/compatible/Assertion
  #299 = Utf8               waitForBeat
  #300 = Utf8               (ILorg/scalactic/source/Position;)Lorg/scalatest/Succeeded$;
  #301 = Utf8               beat
  #302 = Utf8               cannotWaitForBeatZero
  #303 = NameAndType        #302:#168     // cannotWaitForBeatZero:()Ljava/lang/String;
  #304 = Methodref          #205.#303     // org/scalatest/Resources$.cannotWaitForBeatZero:()Ljava/lang/String;
  #305 = Utf8               cannotWaitForNegativeBeat
  #306 = NameAndType        #305:#168     // cannotWaitForNegativeBeat:()Ljava/lang/String;
  #307 = Methodref          #205.#306     // org/scalatest/Resources$.cannotWaitForNegativeBeat:()Ljava/lang/String;
  #308 = NameAndType        #64:#123      // org$scalatest$concurrent$Conductors$Conductor$$clock:()Lorg/scalatest/concurrent/Conductors$Conductor$Clock;
  #309 = Methodref          #2.#308       // org/scalatest/concurrent/Conductors$Conductor.org$scalatest$concurrent$Conductors$Conductor$$clock:()Lorg/scalatest/concurrent/Conductors$Conductor$Clock;
  #310 = Utf8               (I)Lorg/scalatest/Succeeded$;
  #311 = NameAndType        #299:#310     // waitForBeat:(I)Lorg/scalatest/Succeeded$;
  #312 = Methodref          #20.#311      // org/scalatest/concurrent/Conductors$Conductor$Clock.waitForBeat:(I)Lorg/scalatest/Succeeded$;
  #313 = Utf8               I
  #314 = Utf8               currentBeat
  #315 = NameAndType        #314:#161     // currentBeat:()I
  #316 = Methodref          #20.#315      // org/scalatest/concurrent/Conductors$Conductor$Clock.currentBeat:()I
  #317 = Utf8               withConductorFrozen
  #318 = Utf8               (Lscala/Function0;)Ljava/lang/Object;
  #319 = Utf8               <T:Ljava/lang/Object;>(Lscala/Function0<TT;>;)TT;
  #320 = Utf8               withClockFrozen
  #321 = NameAndType        #320:#318     // withClockFrozen:(Lscala/Function0;)Ljava/lang/Object;
  #322 = Methodref          #20.#321      // org/scalatest/concurrent/Conductors$Conductor$Clock.withClockFrozen:(Lscala/Function0;)Ljava/lang/Object;
  #323 = Utf8               isConductorFrozen
  #324 = Utf8               isFrozen
  #325 = NameAndType        #324:#278     // isFrozen:()Z
  #326 = Methodref          #20.#325      // org/scalatest/concurrent/Conductors$Conductor$Clock.isFrozen:()Z
  #327 = Utf8               ()Lorg/scalatest/concurrent/TestThreadsStartingCounter;
  #328 = NameAndType        #78:#79       // org$scalatest$concurrent$Conductors$Conductor$$testThreadsStartingCounter:Lorg/scalatest/concurrent/TestThreadsStartingCounter;
  #329 = Fieldref           #2.#328       // org/scalatest/concurrent/Conductors$Conductor.org$scalatest$concurrent$Conductors$Conductor$$testThreadsStartingCounter:Lorg/scalatest/concurrent/TestThreadsStartingCounter;
  #330 = Utf8               ()Lorg/scalatest/CountDownLatch;
  #331 = NameAndType        #80:#81       // org$scalatest$concurrent$Conductors$Conductor$$greenLightForTestThreads:Lorg/scalatest/CountDownLatch;
  #332 = Fieldref           #2.#331       // org/scalatest/concurrent/Conductors$Conductor.org$scalatest$concurrent$Conductors$Conductor$$greenLightForTestThreads:Lorg/scalatest/CountDownLatch;
  #333 = Utf8               config
  #334 = Utf8               timeout
  #335 = Utf8               ()Lorg/scalatest/time/Span;
  #336 = NameAndType        #334:#335     // timeout:()Lorg/scalatest/time/Span;
  #337 = Methodref          #12.#336      // org/scalatest/concurrent/AbstractPatienceConfiguration$PatienceConfig.timeout:()Lorg/scalatest/time/Span;
  #338 = Utf8               interval
  #339 = NameAndType        #338:#335     // interval:()Lorg/scalatest/time/Span;
  #340 = Methodref          #12.#339      // org/scalatest/concurrent/AbstractPatienceConfiguration$PatienceConfig.interval:()Lorg/scalatest/time/Span;
  #341 = Utf8               conductImpl
  #342 = Utf8               (Lorg/scalatest/time/Span;Lorg/scalatest/time/Span;Lorg/scalactic/source/Position;)Lorg/scalatest/compatible/Assertion;
  #343 = NameAndType        #341:#342     // conductImpl:(Lorg/scalatest/time/Span;Lorg/scalatest/time/Span;Lorg/scalactic/source/Position;)Lorg/scalatest/compatible/Assertion;
  #344 = Methodref          #2.#343       // org/scalatest/concurrent/Conductors$Conductor.conductImpl:(Lorg/scalatest/time/Span;Lorg/scalatest/time/Span;Lorg/scalactic/source/Position;)Lorg/scalatest/compatible/Assertion;
  #345 = Utf8               Lorg/scalatest/concurrent/AbstractPatienceConfiguration$PatienceConfig;
  #346 = Utf8               (Lorg/scalatest/concurrent/PatienceConfiguration$Timeout;Lorg/scalatest/concurrent/PatienceConfiguration$Interval;Lorg/scalactic/source/Position;)Lorg/scalatest/compatible/Assertion;
  #347 = Utf8               value
  #348 = NameAndType        #347:#335     // value:()Lorg/scalatest/time/Span;
  #349 = Methodref          #52.#348      // org/scalatest/concurrent/PatienceConfiguration$Timeout.value:()Lorg/scalatest/time/Span;
  #350 = Methodref          #47.#348      // org/scalatest/concurrent/PatienceConfiguration$Interval.value:()Lorg/scalatest/time/Span;
  #351 = Utf8               Lorg/scalatest/concurrent/PatienceConfiguration$Timeout;
  #352 = Utf8               Lorg/scalatest/concurrent/PatienceConfiguration$Interval;
  #353 = Utf8               (Lorg/scalatest/concurrent/PatienceConfiguration$Timeout;Lorg/scalatest/concurrent/AbstractPatienceConfiguration$PatienceConfig;Lorg/scalactic/source/Position;)Lorg/scalatest/compatible/Assertion;
  #354 = Utf8               (Lorg/scalatest/concurrent/PatienceConfiguration$Interval;Lorg/scalatest/concurrent/AbstractPatienceConfiguration$PatienceConfig;Lorg/scalactic/source/Position;)Lorg/scalatest/compatible/Assertion;
  #355 = Utf8               ()Ljava/util/concurrent/atomic/AtomicReference<Lorg/scalatest/concurrent/Conductors$Conductor$ConductorState;>;
  #356 = NameAndType        #82:#83       // currentState:Ljava/util/concurrent/atomic/AtomicReference;
  #357 = Fieldref           #2.#356       // org/scalatest/concurrent/Conductors$Conductor.currentState:Ljava/util/concurrent/atomic/AtomicReference;
  #358 = Utf8               testWasStarted
  #359 = NameAndType        #358:#278     // testWasStarted:()Z
  #360 = Methodref          #29.#359      // org/scalatest/concurrent/Conductors$Conductor$ConductorState.testWasStarted:()Z
  #361 = Utf8               clockInterval
  #362 = Utf8               cannotCallConductTwice
  #363 = NameAndType        #362:#168     // cannotCallConductTwice:()Ljava/lang/String;
  #364 = Methodref          #205.#363     // org/scalatest/Resources$.cannotCallConductTwice:()Ljava/lang/String;
  #365 = NameAndType        #109:#110     // TestStarted:()Lorg/scalatest/concurrent/Conductors$Conductor$TestStarted$;
  #366 = Methodref          #2.#365       // org/scalatest/concurrent/Conductors$Conductor.TestStarted:()Lorg/scalatest/concurrent/Conductors$Conductor$TestStarted$;
  #367 = Utf8               set
  #368 = Utf8               (Ljava/lang/Object;)V
  #369 = NameAndType        #367:#368     // set:(Ljava/lang/Object;)V
  #370 = Methodref          #191.#369     // java/util/concurrent/atomic/AtomicReference.set:(Ljava/lang/Object;)V
  #371 = NameAndType        #78:#327      // org$scalatest$concurrent$Conductors$Conductor$$testThreadsStartingCounter:()Lorg/scalatest/concurrent/TestThreadsStartingCounter;
  #372 = Methodref          #2.#371       // org/scalatest/concurrent/Conductors$Conductor.org$scalatest$concurrent$Conductors$Conductor$$testThreadsStartingCounter:()Lorg/scalatest/concurrent/TestThreadsStartingCounter;
  #373 = Utf8               org/scalatest/concurrent/TestThreadsStartingCounter
  #374 = Class              #373          // org/scalatest/concurrent/TestThreadsStartingCounter
  #375 = Utf8               waitUntilAllTestThreadsHaveStarted
  #376 = NameAndType        #375:#91      // waitUntilAllTestThreadsHaveStarted:()V
  #377 = Methodref          #374.#376     // org/scalatest/concurrent/TestThreadsStartingCounter.waitUntilAllTestThreadsHaveStarted:()V
  #378 = NameAndType        #80:#330      // org$scalatest$concurrent$Conductors$Conductor$$greenLightForTestThreads:()Lorg/scalatest/CountDownLatch;
  #379 = Methodref          #2.#378       // org/scalatest/concurrent/Conductors$Conductor.org$scalatest$concurrent$Conductors$Conductor$$greenLightForTestThreads:()Lorg/scalatest/CountDownLatch;
  #380 = Utf8               org/scalatest/CountDownLatch
  #381 = Class              #380          // org/scalatest/CountDownLatch
  #382 = Utf8               countDown
  #383 = NameAndType        #382:#91      // countDown:()V
  #384 = Methodref          #381.#383     // org/scalatest/CountDownLatch.countDown:()V
  #385 = Utf8               (Lorg/scalatest/concurrent/Conductors$Conductor;Lorg/scalatest/time/Span;Lorg/scalatest/time/Span;)V
  #386 = NameAndType        #146:#385     // "<init>":(Lorg/scalatest/concurrent/Conductors$Conductor;Lorg/scalatest/time/Span;Lorg/scalatest/time/Span;)V
  #387 = Methodref          #23.#386      // org/scalatest/concurrent/Conductors$Conductor$ClockThread."<init>":(Lorg/scalatest/concurrent/Conductors$Conductor;Lorg/scalatest/time/Span;Lorg/scalatest/time/Span;)V
  #388 = Methodref          #23.#250      // org/scalatest/concurrent/Conductors$Conductor$ClockThread.start:()V
  #389 = Utf8               waitForThreads
  #390 = Utf8               ()Lorg/scalatest/Succeeded$;
  #391 = NameAndType        #389:#390     // waitForThreads:()Lorg/scalatest/Succeeded$;
  #392 = Methodref          #2.#391       // org/scalatest/concurrent/Conductors$Conductor.waitForThreads:()Lorg/scalatest/Succeeded$;
  #393 = NameAndType        #75:#260      // org$scalatest$concurrent$Conductors$Conductor$$firstExceptionThrown:()Ljava/util/concurrent/ArrayBlockingQueue;
  #394 = Methodref          #2.#393       // org/scalatest/concurrent/Conductors$Conductor.org$scalatest$concurrent$Conductors$Conductor$$firstExceptionThrown:()Ljava/util/concurrent/ArrayBlockingQueue;
  #395 = Utf8               java/util/concurrent/ArrayBlockingQueue
  #396 = Class              #395          // java/util/concurrent/ArrayBlockingQueue
  #397 = Utf8               isEmpty
  #398 = NameAndType        #397:#278     // isEmpty:()Z
  #399 = Methodref          #396.#398     // java/util/concurrent/ArrayBlockingQueue.isEmpty:()Z
  #400 = Utf8               peek
  #401 = NameAndType        #400:#193     // peek:()Ljava/lang/Object;
  #402 = Methodref          #396.#401     // java/util/concurrent/ArrayBlockingQueue.peek:()Ljava/lang/Object;
  #403 = Utf8               java/lang/Throwable
  #404 = Class              #403          // java/lang/Throwable
  #405 = Utf8               org/scalatest/Succeeded$
  #406 = Class              #405          // org/scalatest/Succeeded$
  #407 = Utf8               Lorg/scalatest/Succeeded$;
  #408 = NameAndType        #206:#407     // MODULE$:Lorg/scalatest/Succeeded$;
  #409 = Fieldref           #406.#408     // org/scalatest/Succeeded$.MODULE$:Lorg/scalatest/Succeeded$;
  #410 = Utf8               clockThread
  #411 = Utf8               Lorg/scalatest/concurrent/Conductors$Conductor$ClockThread;
  #412 = Utf8               Lorg/scalatest/time/Span;
  #413 = Utf8               scala/runtime/BooleanRef
  #414 = Class              #413          // scala/runtime/BooleanRef
  #415 = Utf8               create
  #416 = Utf8               (Z)Lscala/runtime/BooleanRef;
  #417 = NameAndType        #415:#416     // create:(Z)Lscala/runtime/BooleanRef;
  #418 = Methodref          #414.#417     // scala/runtime/BooleanRef.create:(Z)Lscala/runtime/BooleanRef;
  #419 = Utf8               elem
  #420 = Utf8               Z
  #421 = NameAndType        #419:#420     // elem:Z
  #422 = Fieldref           #414.#421     // scala/runtime/BooleanRef.elem:Z
  #423 = Utf8               org/scalatest/concurrent/PimpedThreadGroup$
  #424 = Class              #423          // org/scalatest/concurrent/PimpedThreadGroup$
  #425 = Utf8               Lorg/scalatest/concurrent/PimpedThreadGroup$;
  #426 = NameAndType        #206:#425     // MODULE$:Lorg/scalatest/concurrent/PimpedThreadGroup$;
  #427 = Fieldref           #424.#426     // org/scalatest/concurrent/PimpedThreadGroup$.MODULE$:Lorg/scalatest/concurrent/PimpedThreadGroup$;
  #428 = NameAndType        #66:#126      // org$scalatest$concurrent$Conductors$Conductor$$threadGroup:()Ljava/lang/ThreadGroup;
  #429 = Methodref          #2.#428       // org/scalatest/concurrent/Conductors$Conductor.org$scalatest$concurrent$Conductors$Conductor$$threadGroup:()Ljava/lang/ThreadGroup;
  #430 = Utf8               threadGroupToPimpedThreadGroup
  #431 = Utf8               (Ljava/lang/ThreadGroup;)Lorg/scalatest/concurrent/PimpedThreadGroup;
  #432 = NameAndType        #430:#431     // threadGroupToPimpedThreadGroup:(Ljava/lang/ThreadGroup;)Lorg/scalatest/concurrent/PimpedThreadGroup;
  #433 = Methodref          #424.#432     // org/scalatest/concurrent/PimpedThreadGroup$.threadGroupToPimpedThreadGroup:(Ljava/lang/ThreadGroup;)Lorg/scalatest/concurrent/PimpedThreadGroup;
  #434 = Utf8               org/scalatest/concurrent/PimpedThreadGroup
  #435 = Class              #434          // org/scalatest/concurrent/PimpedThreadGroup
  #436 = Utf8               areAnyThreadsAlive
  #437 = NameAndType        #436:#278     // areAnyThreadsAlive:()Z
  #438 = Methodref          #435.#437     // org/scalatest/concurrent/PimpedThreadGroup.areAnyThreadsAlive:()Z
  #439 = Utf8               getThreads
  #440 = Utf8               ()Lscala/collection/immutable/List;
  #441 = NameAndType        #439:#440     // getThreads:()Lscala/collection/immutable/List;
  #442 = Methodref          #435.#441     // org/scalatest/concurrent/PimpedThreadGroup.getThreads:()Lscala/collection/immutable/List;
  #443 = Utf8               (Ljava/lang/Object;)Ljava/lang/Object;
  #444 = MethodType         #443          //  (Ljava/lang/Object;)Ljava/lang/Object;
  #445 = Utf8               $anonfun$waitForThreads$1$adapted
  #446 = Utf8               (Lorg/scalatest/concurrent/Conductors$Conductor;Lscala/runtime/BooleanRef;Ljava/lang/Thread;)Ljava/lang/Object;
  #447 = NameAndType        #445:#446     // $anonfun$waitForThreads$1$adapted:(Lorg/scalatest/concurrent/Conductors$Conductor;Lscala/runtime/BooleanRef;Ljava/lang/Thread;)Ljava/lang/Object;
  #448 = Methodref          #2.#447       // org/scalatest/concurrent/Conductors$Conductor.$anonfun$waitForThreads$1$adapted:(Lorg/scalatest/concurrent/Conductors$Conductor;Lscala/runtime/BooleanRef;Ljava/lang/Thread;)Ljava/lang/Object;
  #449 = MethodHandle       6:#448        // REF_invokeStatic org/scalatest/concurrent/Conductors$Conductor.$anonfun$waitForThreads$1$adapted:(Lorg/scalatest/concurrent/Conductors$Conductor;Lscala/runtime/BooleanRef;Ljava/lang/Thread;)Ljava/lang/Object;
  #450 = Utf8               (Ljava/lang/Thread;)Ljava/lang/Object;
  #451 = MethodType         #450          //  (Ljava/lang/Thread;)Ljava/lang/Object;
  #452 = Integer            5
  #453 = Utf8               (Lorg/scalatest/concurrent/Conductors$Conductor;Lscala/runtime/BooleanRef;)Lscala/Function1;
  #454 = NameAndType        #294:#453     // apply:(Lorg/scalatest/concurrent/Conductors$Conductor;Lscala/runtime/BooleanRef;)Lscala/Function1;
  #455 = InvokeDynamic      #1:#454       // #1:apply:(Lorg/scalatest/concurrent/Conductors$Conductor;Lscala/runtime/BooleanRef;)Lscala/Function1;
  #456 = Utf8               scala/collection/immutable/List
  #457 = Class              #456          // scala/collection/immutable/List
  #458 = Utf8               foreach
  #459 = Utf8               (Lscala/Function1;)V
  #460 = NameAndType        #458:#459     // foreach:(Lscala/Function1;)V
  #461 = Methodref          #457.#460     // scala/collection/immutable/List.foreach:(Lscala/Function1;)V
  #462 = Utf8               interrupted
  #463 = Utf8               Lscala/runtime/BooleanRef;
  #464 = Utf8               (Lorg/scalatest/concurrent/Conductors$Conductor;)V
  #465 = NameAndType        #146:#464     // "<init>":(Lorg/scalatest/concurrent/Conductors$Conductor;)V
  #466 = Methodref          #44.#465      // org/scalatest/concurrent/Conductors$Conductor$TestThread$."<init>":(Lorg/scalatest/concurrent/Conductors$Conductor;)V
  #467 = Methodref          #26.#465      // org/scalatest/concurrent/Conductors$Conductor$ClockThread$."<init>":(Lorg/scalatest/concurrent/Conductors$Conductor;)V
  #468 = Methodref          #32.#465      // org/scalatest/concurrent/Conductors$Conductor$Setup$."<init>":(Lorg/scalatest/concurrent/Conductors$Conductor;)V
  #469 = Methodref          #38.#465      // org/scalatest/concurrent/Conductors$Conductor$TestStarted$."<init>":(Lorg/scalatest/concurrent/Conductors$Conductor;)V
  #470 = Methodref          #35.#465      // org/scalatest/concurrent/Conductors$Conductor$TestFinished$."<init>":(Lorg/scalatest/concurrent/Conductors$Conductor;)V
  #471 = Utf8               fun$1
  #472 = Utf8               $anonfun$waitForThreads$1
  #473 = Utf8               (Lorg/scalatest/concurrent/Conductors$Conductor;Lscala/runtime/BooleanRef;Ljava/lang/Thread;)V
  #474 = Utf8               $this
  #475 = Utf8               interrupted$1
  #476 = Utf8               java/lang/InterruptedException
  #477 = Class              #476          // java/lang/InterruptedException
  #478 = Utf8               isAlive
  #479 = NameAndType        #478:#278     // isAlive:()Z
  #480 = Methodref          #268.#479     // java/lang/Thread.isAlive:()Z
  #481 = Utf8               join
  #482 = NameAndType        #481:#91      // join:()V
  #483 = Methodref          #268.#482     // java/lang/Thread.join:()V
  #484 = Utf8               e
  #485 = Utf8               Ljava/lang/InterruptedException;
  #486 = Utf8               (Lorg/scalatest/concurrent/Conductors;)V
  #487 = NameAndType        #146:#91      // "<init>":()V
  #488 = Methodref          #4.#487       // java/lang/Object."<init>":()V
  #489 = Methodref          #20.#465      // org/scalatest/concurrent/Conductors$Conductor$Clock."<init>":(Lorg/scalatest/concurrent/Conductors$Conductor;)V
  #490 = Utf8               java/lang/ThreadGroup
  #491 = Class              #490          // java/lang/ThreadGroup
  #492 = Utf8               Orchestra
  #493 = String             #492          // Orchestra
  #494 = Utf8               (Ljava/lang/String;)V
  #495 = NameAndType        #146:#494     // "<init>":(Ljava/lang/String;)V
  #496 = Methodref          #491.#495     // java/lang/ThreadGroup."<init>":(Ljava/lang/String;)V
  #497 = Methodref          #159.#487     // java/util/concurrent/CopyOnWriteArrayList."<init>":()V
  #498 = Methodref          #396.#148     // java/util/concurrent/ArrayBlockingQueue."<init>":(I)V
  #499 = Methodref          #374.#487     // org/scalatest/concurrent/TestThreadsStartingCounter."<init>":()V
  #500 = Methodref          #381.#148     // org/scalatest/CountDownLatch."<init>":(I)V
  #501 = NameAndType        #102:#103     // Setup:()Lorg/scalatest/concurrent/Conductors$Conductor$Setup$;
  #502 = Methodref          #2.#501       // org/scalatest/concurrent/Conductors$Conductor.Setup:()Lorg/scalatest/concurrent/Conductors$Conductor$Setup$;
  #503 = NameAndType        #146:#368     // "<init>":(Ljava/lang/Object;)V
  #504 = Methodref          #191.#503     // java/util/concurrent/atomic/AtomicReference."<init>":(Ljava/lang/Object;)V
  #505 = NameAndType        #472:#473     // $anonfun$waitForThreads$1:(Lorg/scalatest/concurrent/Conductors$Conductor;Lscala/runtime/BooleanRef;Ljava/lang/Thread;)V
  #506 = Methodref          #2.#505       // org/scalatest/concurrent/Conductors$Conductor.$anonfun$waitForThreads$1:(Lorg/scalatest/concurrent/Conductors$Conductor;Lscala/runtime/BooleanRef;Ljava/lang/Thread;)V
  #507 = Utf8               scala/runtime/BoxedUnit
  #508 = Class              #507          // scala/runtime/BoxedUnit
  #509 = Utf8               UNIT
  #510 = Utf8               Lscala/runtime/BoxedUnit;
  #511 = NameAndType        #509:#510     // UNIT:Lscala/runtime/BoxedUnit;
  #512 = Fieldref           #508.#511     // scala/runtime/BoxedUnit.UNIT:Lscala/runtime/BoxedUnit;
  #513 = Utf8               $deserializeLambda$
  #514 = Utf8               (Ljava/lang/invoke/SerializedLambda;)Ljava/lang/Object;
  #515 = Utf8               scala/runtime/LambdaDeserialize
  #516 = Class              #515          // scala/runtime/LambdaDeserialize
  #517 = Utf8               bootstrap
  #518 = Utf8               (Ljava/lang/invoke/MethodHandles$Lookup;Ljava/lang/String;Ljava/lang/invoke/MethodType;[Ljava/lang/invoke/MethodHandle;)Ljava/lang/invoke/CallSite;
  #519 = NameAndType        #517:#518     // bootstrap:(Ljava/lang/invoke/MethodHandles$Lookup;Ljava/lang/String;Ljava/lang/invoke/MethodType;[Ljava/lang/invoke/MethodHandle;)Ljava/lang/invoke/CallSite;
  #520 = Methodref          #516.#519     // scala/runtime/LambdaDeserialize.bootstrap:(Ljava/lang/invoke/MethodHandles$Lookup;Ljava/lang/String;Ljava/lang/invoke/MethodType;[Ljava/lang/invoke/MethodHandle;)Ljava/lang/invoke/CallSite;
  #521 = MethodHandle       6:#520        // REF_invokeStatic scala/runtime/LambdaDeserialize.bootstrap:(Ljava/lang/invoke/MethodHandles$Lookup;Ljava/lang/String;Ljava/lang/invoke/MethodType;[Ljava/lang/invoke/MethodHandle;)Ljava/lang/invoke/CallSite;
  #522 = Utf8               lambdaDeserialize
  #523 = NameAndType        #522:#514     // lambdaDeserialize:(Ljava/lang/invoke/SerializedLambda;)Ljava/lang/Object;
  #524 = InvokeDynamic      #2:#523       // #2:lambdaDeserialize:(Ljava/lang/invoke/SerializedLambda;)Ljava/lang/Object;
  #525 = Utf8               Signature
  #526 = Utf8               Code
  #527 = Utf8               StackMapTable
  #528 = Utf8               LineNumberTable
  #529 = Utf8               LocalVariableTable
  #530 = Utf8               MethodParameters
  #531 = Utf8               InnerClasses
  #532 = Utf8               SourceFile
  #533 = Utf8               BootstrapMethods
  #534 = Utf8               ScalaInlineInfo
  #535 = Utf8               Scala
{
  private volatile org.scalatest.concurrent.Conductors$Conductor$TestThread$ TestThread$module;
    descriptor: Lorg/scalatest/concurrent/Conductors$Conductor$TestThread$;
    flags: (0x0042) ACC_PRIVATE, ACC_VOLATILE

  private volatile org.scalatest.concurrent.Conductors$Conductor$ClockThread$ ClockThread$module;
    descriptor: Lorg/scalatest/concurrent/Conductors$Conductor$ClockThread$;
    flags: (0x0042) ACC_PRIVATE, ACC_VOLATILE

  private volatile org.scalatest.concurrent.Conductors$Conductor$Setup$ Setup$module;
    descriptor: Lorg/scalatest/concurrent/Conductors$Conductor$Setup$;
    flags: (0x0042) ACC_PRIVATE, ACC_VOLATILE

  private volatile org.scalatest.concurrent.Conductors$Conductor$TestStarted$ TestStarted$module;
    descriptor: Lorg/scalatest/concurrent/Conductors$Conductor$TestStarted$;
    flags: (0x0042) ACC_PRIVATE, ACC_VOLATILE

  private volatile org.scalatest.concurrent.Conductors$Conductor$TestFinished$ TestFinished$module;
    descriptor: Lorg/scalatest/concurrent/Conductors$Conductor$TestFinished$;
    flags: (0x0042) ACC_PRIVATE, ACC_VOLATILE

  private final org.scalatest.concurrent.Conductors$Conductor$Clock org$scalatest$concurrent$Conductors$Conductor$$clock;
    descriptor: Lorg/scalatest/concurrent/Conductors$Conductor$Clock;
    flags: (0x0012) ACC_PRIVATE, ACC_FINAL

  private final java.lang.ThreadGroup org$scalatest$concurrent$Conductors$Conductor$$threadGroup;
    descriptor: Ljava/lang/ThreadGroup;
    flags: (0x0012) ACC_PRIVATE, ACC_FINAL

  private final java.util.concurrent.CopyOnWriteArrayList<java.lang.Thread> threads;
    descriptor: Ljava/util/concurrent/CopyOnWriteArrayList;
    flags: (0x0012) ACC_PRIVATE, ACC_FINAL
    Signature: #70                          // Ljava/util/concurrent/CopyOnWriteArrayList<Ljava/lang/Thread;>;

  private final java.util.concurrent.CopyOnWriteArrayList<java.lang.String> threadNames;
    descriptor: Ljava/util/concurrent/CopyOnWriteArrayList;
    flags: (0x0012) ACC_PRIVATE, ACC_FINAL
    Signature: #72                          // Ljava/util/concurrent/CopyOnWriteArrayList<Ljava/lang/String;>;

  private final java.lang.Thread org$scalatest$concurrent$Conductors$Conductor$$mainThread;
    descriptor: Ljava/lang/Thread;
    flags: (0x0012) ACC_PRIVATE, ACC_FINAL

  private final java.util.concurrent.ArrayBlockingQueue<java.lang.Throwable> org$scalatest$concurrent$Conductors$Conductor$$firstExceptionThrown;
    descriptor: Ljava/util/concurrent/ArrayBlockingQueue;
    flags: (0x0012) ACC_PRIVATE, ACC_FINAL
    Signature: #77                          // Ljava/util/concurrent/ArrayBlockingQueue<Ljava/lang/Throwable;>;

  private final org.scalatest.concurrent.TestThreadsStartingCounter org$scalatest$concurrent$Conductors$Conductor$$testThreadsStartingCounter;
    descriptor: Lorg/scalatest/concurrent/TestThreadsStartingCounter;
    flags: (0x0012) ACC_PRIVATE, ACC_FINAL

  private final org.scalatest.CountDownLatch org$scalatest$concurrent$Conductors$Conductor$$greenLightForTestThreads;
    descriptor: Lorg/scalatest/CountDownLatch;
    flags: (0x0012) ACC_PRIVATE, ACC_FINAL

  private final java.util.concurrent.atomic.AtomicReference<org.scalatest.concurrent.Conductors$Conductor$ConductorState> currentState;
    descriptor: Ljava/util/concurrent/atomic/AtomicReference;
    flags: (0x0012) ACC_PRIVATE, ACC_FINAL
    Signature: #84                          // Ljava/util/concurrent/atomic/AtomicReference<Lorg/scalatest/concurrent/Conductors$Conductor$ConductorState;>;

  private final org.scalatest.concurrent.Conductors $outer;
    descriptor: Lorg/scalatest/concurrent/Conductors;
    flags: (0x1012) ACC_PRIVATE, ACC_FINAL, ACC_SYNTHETIC

  private org.scalatest.concurrent.Conductors$Conductor$TestThread$ TestThread();
    descriptor: ()Lorg/scalatest/concurrent/Conductors$Conductor$TestThread$;
    flags: (0x0002) ACC_PRIVATE
    Code:
      stack=1, locals=1, args_size=1
         0: aload_0
         1: getfield      #89                 // Field TestThread$module:Lorg/scalatest/concurrent/Conductors$Conductor$TestThread$;
         4: ifnonnull     11
         7: aload_0
         8: invokespecial #93                 // Method TestThread$lzycompute$1:()V
        11: aload_0
        12: getfield      #89                 // Field TestThread$module:Lorg/scalatest/concurrent/Conductors$Conductor$TestThread$;
        15: areturn
      StackMapTable: number_of_entries = 1
        frame_type = 11 /* same */
      LineNumberTable:
        line 563: 0
      LocalVariableTable:
        Start  Length  Slot  Name   Signature
            0      16     0  this   Lorg/scalatest/concurrent/Conductors$Conductor;

  private org.scalatest.concurrent.Conductors$Conductor$ClockThread$ ClockThread();
    descriptor: ()Lorg/scalatest/concurrent/Conductors$Conductor$ClockThread$;
    flags: (0x0002) ACC_PRIVATE
    Code:
      stack=1, locals=1, args_size=1
         0: aload_0
         1: getfield      #98                 // Field ClockThread$module:Lorg/scalatest/concurrent/Conductors$Conductor$ClockThread$;
         4: ifnonnull     11
         7: aload_0
         8: invokespecial #101                // Method ClockThread$lzycompute$1:()V
        11: aload_0
        12: getfield      #98                 // Field ClockThread$module:Lorg/scalatest/concurrent/Conductors$Conductor$ClockThread$;
        15: areturn
      StackMapTable: number_of_entries = 1
        frame_type = 11 /* same */
      LineNumberTable:
        line 1020: 0
      LocalVariableTable:
        Start  Length  Slot  Name   Signature
            0      16     0  this   Lorg/scalatest/concurrent/Conductors$Conductor;

  private org.scalatest.concurrent.Conductors$Conductor$Setup$ Setup();
    descriptor: ()Lorg/scalatest/concurrent/Conductors$Conductor$Setup$;
    flags: (0x0002) ACC_PRIVATE
    Code:
      stack=1, locals=1, args_size=1
         0: aload_0
         1: getfield      #105                // Field Setup$module:Lorg/scalatest/concurrent/Conductors$Conductor$Setup$;
         4: ifnonnull     11
         7: aload_0
         8: invokespecial #108                // Method Setup$lzycompute$1:()V
        11: aload_0
        12: getfield      #105                // Field Setup$module:Lorg/scalatest/concurrent/Conductors$Conductor$Setup$;
        15: areturn
      StackMapTable: number_of_entries = 1
        frame_type = 11 /* same */
      LineNumberTable:
        line 1130: 0
      LocalVariableTable:
        Start  Length  Slot  Name   Signature
            0      16     0  this   Lorg/scalatest/concurrent/Conductors$Conductor;

  private org.scalatest.concurrent.Conductors$Conductor$TestStarted$ TestStarted();
    descriptor: ()Lorg/scalatest/concurrent/Conductors$Conductor$TestStarted$;
    flags: (0x0002) ACC_PRIVATE
    Code:
      stack=1, locals=1, args_size=1
         0: aload_0
         1: getfield      #112                // Field TestStarted$module:Lorg/scalatest/concurrent/Conductors$Conductor$TestStarted$;
         4: ifnonnull     11
         7: aload_0
         8: invokespecial #115                // Method TestStarted$lzycompute$1:()V
        11: aload_0
        12: getfield      #112                // Field TestStarted$module:Lorg/scalatest/concurrent/Conductors$Conductor$TestStarted$;
        15: areturn
      StackMapTable: number_of_entries = 1
        frame_type = 11 /* same */
      LineNumberTable:
        line 1137: 0
      LocalVariableTable:
        Start  Length  Slot  Name   Signature
            0      16     0  this   Lorg/scalatest/concurrent/Conductors$Conductor;

  private org.scalatest.concurrent.Conductors$Conductor$TestFinished$ TestFinished();
    descriptor: ()Lorg/scalatest/concurrent/Conductors$Conductor$TestFinished$;
    flags: (0x0002) ACC_PRIVATE
    Code:
      stack=1, locals=1, args_size=1
         0: aload_0
         1: getfield      #119                // Field TestFinished$module:Lorg/scalatest/concurrent/Conductors$Conductor$TestFinished$;
         4: ifnonnull     11
         7: aload_0
         8: invokespecial #122                // Method TestFinished$lzycompute$1:()V
        11: aload_0
        12: getfield      #119                // Field TestFinished$module:Lorg/scalatest/concurrent/Conductors$Conductor$TestFinished$;
        15: areturn
      StackMapTable: number_of_entries = 1
        frame_type = 11 /* same */
      LineNumberTable:
        line 1145: 0
      LocalVariableTable:
        Start  Length  Slot  Name   Signature
            0      16     0  this   Lorg/scalatest/concurrent/Conductors$Conductor;

  public final org.scalatest.concurrent.Conductors$Conductor$Clock org$scalatest$concurrent$Conductors$Conductor$$clock();
    descriptor: ()Lorg/scalatest/concurrent/Conductors$Conductor$Clock;
    flags: (0x0011) ACC_PUBLIC, ACC_FINAL
    Code:
      stack=1, locals=1, args_size=1
         0: aload_0
         1: getfield      #125                // Field org$scalatest$concurrent$Conductors$Conductor$$clock:Lorg/scalatest/concurrent/Conductors$Conductor$Clock;
         4: areturn
      LineNumberTable:
        line 492: 0
      LocalVariableTable:
        Start  Length  Slot  Name   Signature
            0       5     0  this   Lorg/scalatest/concurrent/Conductors$Conductor;

  public final java.lang.ThreadGroup org$scalatest$concurrent$Conductors$Conductor$$threadGroup();
    descriptor: ()Ljava/lang/ThreadGroup;
    flags: (0x0011) ACC_PUBLIC, ACC_FINAL
    Code:
      stack=1, locals=1, args_size=1
         0: aload_0
         1: getfield      #128                // Field org$scalatest$concurrent$Conductors$Conductor$$threadGroup:Ljava/lang/ThreadGroup;
         4: areturn
      LineNumberTable:
        line 497: 0
      LocalVariableTable:
        Start  Length  Slot  Name   Signature
            0       5     0  this   Lorg/scalatest/concurrent/Conductors$Conductor;

  private final java.util.concurrent.CopyOnWriteArrayList<java.lang.Thread> threads();
    descriptor: ()Ljava/util/concurrent/CopyOnWriteArrayList;
    flags: (0x0012) ACC_PRIVATE, ACC_FINAL
    Code:
      stack=1, locals=1, args_size=1
         0: aload_0
         1: getfield      #132                // Field threads:Ljava/util/concurrent/CopyOnWriteArrayList;
         4: areturn
      LineNumberTable:
        line 502: 0
      LocalVariableTable:
        Start  Length  Slot  Name   Signature
            0       5     0  this   Lorg/scalatest/concurrent/Conductors$Conductor;
    Signature: #130                         // ()Ljava/util/concurrent/CopyOnWriteArrayList<Ljava/lang/Thread;>;

  private final java.util.concurrent.CopyOnWriteArrayList<java.lang.String> threadNames();
    descriptor: ()Ljava/util/concurrent/CopyOnWriteArrayList;
    flags: (0x0012) ACC_PRIVATE, ACC_FINAL
    Code:
      stack=1, locals=1, args_size=1
         0: aload_0
         1: getfield      #135                // Field threadNames:Ljava/util/concurrent/CopyOnWriteArrayList;
         4: areturn
      LineNumberTable:
        line 506: 0
      LocalVariableTable:
        Start  Length  Slot  Name   Signature
            0       5     0  this   Lorg/scalatest/concurrent/Conductors$Conductor;
    Signature: #133                         // ()Ljava/util/concurrent/CopyOnWriteArrayList<Ljava/lang/String;>;

  public final java.lang.Thread org$scalatest$concurrent$Conductors$Conductor$$mainThread();
    descriptor: ()Ljava/lang/Thread;
    flags: (0x0011) ACC_PUBLIC, ACC_FINAL
    Code:
      stack=1, locals=1, args_size=1
         0: aload_0
         1: getfield      #138                // Field org$scalatest$concurrent$Conductors$Conductor$$mainThread:Ljava/lang/Thread;
         4: areturn
      LineNumberTable:
        line 509: 0
      LocalVariableTable:
        Start  Length  Slot  Name   Signature
            0       5     0  this   Lorg/scalatest/concurrent/Conductors$Conductor;

  public java.lang.Thread thread(scala.Function0<java.lang.Object>);
    descriptor: (Lscala/Function0;)Ljava/lang/Thread;
    flags: (0x0001) ACC_PUBLIC
    Code:
      stack=8, locals=2, args_size=2
         0: aload_0
         1: new           #144                // class java/lang/StringBuilder
         4: dup
         5: ldc           #145                // int 17
         7: invokespecial #149                // Method java/lang/StringBuilder."<init>":(I)V
        10: ldc           #151                // String Conductor-Thread-
        12: invokevirtual #155                // Method java/lang/StringBuilder.append:(Ljava/lang/String;)Ljava/lang/StringBuilder;
        15: aload_0
        16: invokespecial #157                // Method threads:()Ljava/util/concurrent/CopyOnWriteArrayList;
        19: invokevirtual #163                // Method java/util/concurrent/CopyOnWriteArrayList.size:()I
        22: invokevirtual #166                // Method java/lang/StringBuilder.append:(I)Ljava/lang/StringBuilder;
        25: invokevirtual #170                // Method java/lang/StringBuilder.toString:()Ljava/lang/String;
        28: aload_1
        29: new           #172                // class org/scalactic/source/Position
        32: dup
        33: ldc           #173                // String Conductors.scala
        35: ldc           #175                // String Please set the environment variable SCALACTIC_FILL_FILE_PATHNAMES to yes at compile time to enable this feature.
        37: sipush        525
        40: invokespecial #178                // Method org/scalactic/source/Position."<init>":(Ljava/lang/String;Ljava/lang/String;I)V
        43: invokevirtual #182                // Method threadNamed:(Ljava/lang/String;Lscala/Function0;Lorg/scalactic/source/Position;)Ljava/lang/Thread;
        46: areturn
      LineNumberTable:
        line 525: 0
      LocalVariableTable:
        Start  Length  Slot  Name   Signature
            0      47     0  this   Lorg/scalatest/concurrent/Conductors$Conductor;
            0      47     1   fun   Lscala/Function0;
    Signature: #141                         // (Lscala/Function0<Ljava/lang/Object;>;)Ljava/lang/Thread;
    MethodParameters:
      Name                           Flags
      fun                            final

  public java.lang.Thread threadNamed(java.lang.String, scala.Function0<java.lang.Object>, org.scalactic.source.Position);
    descriptor: (Ljava/lang/String;Lscala/Function0;Lorg/scalactic/source/Position;)Ljava/lang/Thread;
    flags: (0x0001) ACC_PUBLIC
    Code:
      stack=5, locals=7, args_size=4
         0: aload_0
         1: invokespecial #189                // Method currentState:()Ljava/util/concurrent/atomic/AtomicReference;
         4: invokevirtual #195                // Method java/util/concurrent/atomic/AtomicReference.get:()Ljava/lang/Object;
         7: checkcast     #29                 // class org/scalatest/concurrent/Conductors$Conductor$ConductorState
        10: astore        5
        12: aload_0
        13: invokespecial #197                // Method TestFinished:()Lorg/scalatest/concurrent/Conductors$Conductor$TestFinished$;
        16: aload         5
        18: invokevirtual #201                // Method java/lang/Object.equals:(Ljava/lang/Object;)Z
        21: ifeq          39
        24: new           #203                // class org/scalatest/exceptions/NotAllowedException
        27: dup
        28: getstatic     #209                // Field org/scalatest/Resources$.MODULE$:Lorg/scalatest/Resources$;
        31: invokevirtual #212                // Method org/scalatest/Resources$.threadCalledAfterConductingHasCompleted:()Ljava/lang/String;
        34: aload_3
        35: invokespecial #215                // Method org/scalatest/exceptions/NotAllowedException."<init>":(Ljava/lang/String;Lorg/scalactic/source/Position;)V
        38: athrow
        39: goto          42
        42: aload_0
        43: invokespecial #217                // Method threadNames:()Ljava/util/concurrent/CopyOnWriteArrayList;
        46: aload_1
        47: invokevirtual #220                // Method java/util/concurrent/CopyOnWriteArrayList.contains:(Ljava/lang/Object;)Z
        50: ifeq          69
        53: new           #203                // class org/scalatest/exceptions/NotAllowedException
        56: dup
        57: getstatic     #209                // Field org/scalatest/Resources$.MODULE$:Lorg/scalatest/Resources$;
        60: aload_1
        61: invokevirtual #224                // Method org/scalatest/Resources$.cantRegisterThreadsWithSameName:(Ljava/lang/Object;)Ljava/lang/String;
        64: aload_3
        65: invokespecial #215                // Method org/scalatest/exceptions/NotAllowedException."<init>":(Ljava/lang/String;Lorg/scalactic/source/Position;)V
        68: athrow
        69: new           #41                 // class org/scalatest/concurrent/Conductors$Conductor$TestThread
        72: dup
        73: aload_0
        74: aload_1
        75: aload_2
        76: invokedynamic #242,  0            // InvokeDynamic #0:apply$mcV$sp:(Lscala/Function0;)Lscala/runtime/java8/JFunction0$mcV$sp;
        81: invokespecial #245                // Method org/scalatest/concurrent/Conductors$Conductor$TestThread."<init>":(Lorg/scalatest/concurrent/Conductors$Conductor;Ljava/lang/String;Lscala/Function0;)V
        84: astore        6
        86: aload_0
        87: invokespecial #157                // Method threads:()Ljava/util/concurrent/CopyOnWriteArrayList;
        90: aload         6
        92: invokevirtual #248                // Method java/util/concurrent/CopyOnWriteArrayList.add:(Ljava/lang/Object;)Z
        95: pop
        96: aload_0
        97: invokespecial #217                // Method threadNames:()Ljava/util/concurrent/CopyOnWriteArrayList;
       100: aload_1
       101: invokevirtual #248                // Method java/util/concurrent/CopyOnWriteArrayList.add:(Ljava/lang/Object;)Z
       104: pop
       105: aload         6
       107: invokevirtual #251                // Method org/scalatest/concurrent/Conductors$Conductor$TestThread.start:()V
       110: aload         6
       112: astore        4
       114: goto          117
       117: aload         4
       119: areturn
      StackMapTable: number_of_entries = 4
        frame_type = 253 /* append */
          offset_delta = 39
          locals = [ top, class org/scalatest/concurrent/Conductors$Conductor$ConductorState ]
        frame_type = 2 /* same */
        frame_type = 26 /* same */
        frame_type = 255 /* full_frame */
          offset_delta = 47
          locals = [ class org/scalatest/concurrent/Conductors$Conductor, class java/lang/String, class scala/Function0, class org/scalactic/source/Position, class org/scalatest/concurrent/Conductors$Conductor$TestThread, class org/scalatest/concurrent/Conductors$Conductor$ConductorState, class org/scalatest/concurrent/Conductors$Conductor$TestThread ]
          stack = []
      LineNumberTable:
        line 539: 0
        line 540: 12
        line 541: 24
        line 540: 39
        line 543: 42
        line 544: 53
        line 545: 69
        line 546: 86
        line 547: 96
        line 548: 105
        line 549: 110
        line 539: 117
      LocalVariableTable:
        Start  Length  Slot  Name   Signature
           86      26     6     t   Lorg/scalatest/concurrent/Conductors$Conductor$TestThread;
            0     120     0  this   Lorg/scalatest/concurrent/Conductors$Conductor;
            0     120     1  name   Ljava/lang/String;
            0     120     2   fun   Lscala/Function0;
            0     120     3   pos   Lorg/scalactic/source/Position;
    Signature: #184                         // (Ljava/lang/String;Lscala/Function0<Ljava/lang/Object;>;Lorg/scalactic/source/Position;)Ljava/lang/Thread;
    MethodParameters:
      Name                           Flags
      name                           final
      fun                            final
      pos                            final

  public java.util.concurrent.ArrayBlockingQueue<java.lang.Throwable> org$scalatest$concurrent$Conductors$Conductor$$firstExceptionThrown();
    descriptor: ()Ljava/util/concurrent/ArrayBlockingQueue;
    flags: (0x0001) ACC_PUBLIC
    Code:
      stack=1, locals=1, args_size=1
         0: aload_0
         1: getfield      #263                // Field org$scalatest$concurrent$Conductors$Conductor$$firstExceptionThrown:Ljava/util/concurrent/ArrayBlockingQueue;
         4: areturn
      LineNumberTable:
        line 601: 0
      LocalVariableTable:
        Start  Length  Slot  Name   Signature
            0       5     0  this   Lorg/scalatest/concurrent/Conductors$Conductor;
    Signature: #261                         // ()Ljava/util/concurrent/ArrayBlockingQueue<Ljava/lang/Throwable;>;

  public org.scalatest.compatible.Assertion whenFinished(scala.Function0<org.scalatest.compatible.Assertion>, org.scalactic.source.Position);
    descriptor: (Lscala/Function0;Lorg/scalactic/source/Position;)Lorg/scalatest/compatible/Assertion;
    flags: (0x0001) ACC_PUBLIC
    Code:
      stack=4, locals=4, args_size=3
         0: invokestatic  #271                // Method java/lang/Thread.currentThread:()Ljava/lang/Thread;
         3: aload_0
         4: invokevirtual #273                // Method org$scalatest$concurrent$Conductors$Conductor$$mainThread:()Ljava/lang/Thread;
         7: astore_3
         8: dup
         9: ifnonnull     20
        12: pop
        13: aload_3
        14: ifnull        42
        17: goto          27
        20: aload_3
        21: invokevirtual #201                // Method java/lang/Object.equals:(Ljava/lang/Object;)Z
        24: ifne          42
        27: new           #203                // class org/scalatest/exceptions/NotAllowedException
        30: dup
        31: getstatic     #209                // Field org/scalatest/Resources$.MODULE$:Lorg/scalatest/Resources$;
        34: invokevirtual #276                // Method org/scalatest/Resources$.whenFinishedCanOnlyBeCalledByMainThread:()Ljava/lang/String;
        37: aload_2
        38: invokespecial #215                // Method org/scalatest/exceptions/NotAllowedException."<init>":(Ljava/lang/String;Lorg/scalactic/source/Position;)V
        41: athrow
        42: aload_0
        43: invokevirtual #280                // Method conductingHasBegun:()Z
        46: ifeq          64
        49: new           #203                // class org/scalatest/exceptions/NotAllowedException
        52: dup
        53: getstatic     #209                // Field org/scalatest/Resources$.MODULE$:Lorg/scalatest/Resources$;
        56: invokevirtual #283                // Method org/scalatest/Resources$.cannotInvokeWhenFinishedAfterConduct:()Ljava/lang/String;
        59: aload_2
        60: invokespecial #215                // Method org/scalatest/exceptions/NotAllowedException."<init>":(Ljava/lang/String;Lorg/scalactic/source/Position;)V
        63: athrow
        64: aload_0
        65: aload_0
        66: getfield      #285                // Field $outer:Lorg/scalatest/concurrent/Conductors;
        69: invokeinterface #289,  1          // InterfaceMethod org/scalatest/concurrent/Conductors.patienceConfig:()Lorg/scalatest/concurrent/AbstractPatienceConfiguration$PatienceConfig;
        74: aload_2
        75: invokevirtual #293                // Method conduct:(Lorg/scalatest/concurrent/AbstractPatienceConfiguration$PatienceConfig;Lorg/scalactic/source/Position;)Lorg/scalatest/compatible/Assertion;
        78: pop
        79: aload_1
        80: invokeinterface #296,  1          // InterfaceMethod scala/Function0.apply:()Ljava/lang/Object;
        85: checkcast     #298                // class org/scalatest/compatible/Assertion
        88: areturn
      StackMapTable: number_of_entries = 4
        frame_type = 255 /* full_frame */
          offset_delta = 20
          locals = [ class org/scalatest/concurrent/Conductors$Conductor, class scala/Function0, class org/scalactic/source/Position, class java/lang/Thread ]
          stack = [ class java/lang/Thread ]
        frame_type = 6 /* same */
        frame_type = 14 /* same */
        frame_type = 21 /* same */
      LineNumberTable:
        line 639: 0
        line 640: 27
        line 642: 42
        line 643: 49
        line 645: 64
        line 647: 79
      LocalVariableTable:
        Start  Length  Slot  Name   Signature
            0      89     0  this   Lorg/scalatest/concurrent/Conductors$Conductor;
            0      89     1   fun   Lscala/Function0;
            0      89     2   pos   Lorg/scalactic/source/Position;
    Signature: #266                         // (Lscala/Function0<Lorg/scalatest/compatible/Assertion;>;Lorg/scalactic/source/Position;)Lorg/scalatest/compatible/Assertion;
    MethodParameters:
      Name                           Flags
      fun                            final
      pos                            final

  public org.scalatest.Succeeded$ waitForBeat(int, org.scalactic.source.Position);
    descriptor: (ILorg/scalactic/source/Position;)Lorg/scalatest/Succeeded$;
    flags: (0x0001) ACC_PUBLIC
    Code:
      stack=4, locals=3, args_size=3
         0: iload_1
         1: iconst_0
         2: if_icmpne     20
         5: new           #203                // class org/scalatest/exceptions/NotAllowedException
         8: dup
         9: getstatic     #209                // Field org/scalatest/Resources$.MODULE$:Lorg/scalatest/Resources$;
        12: invokevirtual #304                // Method org/scalatest/Resources$.cannotWaitForBeatZero:()Ljava/lang/String;
        15: aload_2
        16: invokespecial #215                // Method org/scalatest/exceptions/NotAllowedException."<init>":(Ljava/lang/String;Lorg/scalactic/source/Position;)V
        19: athrow
        20: iload_1
        21: iconst_0
        22: if_icmpge     40
        25: new           #203                // class org/scalatest/exceptions/NotAllowedException
        28: dup
        29: getstatic     #209                // Field org/scalatest/Resources$.MODULE$:Lorg/scalatest/Resources$;
        32: invokevirtual #307                // Method org/scalatest/Resources$.cannotWaitForNegativeBeat:()Ljava/lang/String;
        35: aload_2
        36: invokespecial #215                // Method org/scalatest/exceptions/NotAllowedException."<init>":(Ljava/lang/String;Lorg/scalactic/source/Position;)V
        39: athrow
        40: aload_0
        41: invokevirtual #309                // Method org$scalatest$concurrent$Conductors$Conductor$$clock:()Lorg/scalatest/concurrent/Conductors$Conductor$Clock;
        44: iload_1
        45: invokevirtual #312                // Method org/scalatest/concurrent/Conductors$Conductor$Clock.waitForBeat:(I)Lorg/scalatest/Succeeded$;
        48: areturn
      StackMapTable: number_of_entries = 2
        frame_type = 20 /* same */
        frame_type = 19 /* same */
      LineNumberTable:
        line 658: 0
        line 659: 5
        line 660: 20
        line 661: 25
        line 662: 40
      LocalVariableTable:
        Start  Length  Slot  Name   Signature
            0      49     0  this   Lorg/scalatest/concurrent/Conductors$Conductor;
            0      49     1  beat   I
            0      49     2   pos   Lorg/scalactic/source/Position;
    MethodParameters:
      Name                           Flags
      beat                           final
      pos                            final

  public int beat();
    descriptor: ()I
    flags: (0x0001) ACC_PUBLIC
    Code:
      stack=1, locals=1, args_size=1
         0: aload_0
         1: invokevirtual #309                // Method org$scalatest$concurrent$Conductors$Conductor$$clock:()Lorg/scalatest/concurrent/Conductors$Conductor$Clock;
         4: invokevirtual #316                // Method org/scalatest/concurrent/Conductors$Conductor$Clock.currentBeat:()I
         7: ireturn
      LineNumberTable:
        line 670: 0
      LocalVariableTable:
        Start  Length  Slot  Name   Signature
            0       8     0  this   Lorg/scalatest/concurrent/Conductors$Conductor;

  public <T extends java.lang.Object> T withConductorFrozen(scala.Function0<T>);
    descriptor: (Lscala/Function0;)Ljava/lang/Object;
    flags: (0x0001) ACC_PUBLIC
    Code:
      stack=2, locals=2, args_size=2
         0: aload_0
         1: invokevirtual #309                // Method org$scalatest$concurrent$Conductors$Conductor$$clock:()Lorg/scalatest/concurrent/Conductors$Conductor$Clock;
         4: aload_1
         5: invokevirtual #322                // Method org/scalatest/concurrent/Conductors$Conductor$Clock.withClockFrozen:(Lscala/Function0;)Ljava/lang/Object;
         8: areturn
      LineNumberTable:
        line 684: 0
      LocalVariableTable:
        Start  Length  Slot  Name   Signature
            0       9     0  this   Lorg/scalatest/concurrent/Conductors$Conductor;
            0       9     1   fun   Lscala/Function0;
    Signature: #319                         // <T:Ljava/lang/Object;>(Lscala/Function0<TT;>;)TT;
    MethodParameters:
      Name                           Flags
      fun                            final

  public boolean isConductorFrozen();
    descriptor: ()Z
    flags: (0x0001) ACC_PUBLIC
    Code:
      stack=1, locals=1, args_size=1
         0: aload_0
         1: invokevirtual #309                // Method org$scalatest$concurrent$Conductors$Conductor$$clock:()Lorg/scalatest/concurrent/Conductors$Conductor$Clock;
         4: invokevirtual #326                // Method org/scalatest/concurrent/Conductors$Conductor$Clock.isFrozen:()Z
         7: ireturn
      LineNumberTable:
        line 694: 0
      LocalVariableTable:
        Start  Length  Slot  Name   Signature
            0       8     0  this   Lorg/scalatest/concurrent/Conductors$Conductor;

  public org.scalatest.concurrent.TestThreadsStartingCounter org$scalatest$concurrent$Conductors$Conductor$$testThreadsStartingCounter();
    descriptor: ()Lorg/scalatest/concurrent/TestThreadsStartingCounter;
    flags: (0x0001) ACC_PUBLIC
    Code:
      stack=1, locals=1, args_size=1
         0: aload_0
         1: getfield      #329                // Field org$scalatest$concurrent$Conductors$Conductor$$testThreadsStartingCounter:Lorg/scalatest/concurrent/TestThreadsStartingCounter;
         4: areturn
      LineNumberTable:
        line 696: 0
      LocalVariableTable:
        Start  Length  Slot  Name   Signature
            0       5     0  this   Lorg/scalatest/concurrent/Conductors$Conductor;

  public org.scalatest.CountDownLatch org$scalatest$concurrent$Conductors$Conductor$$greenLightForTestThreads();
    descriptor: ()Lorg/scalatest/CountDownLatch;
    flags: (0x0001) ACC_PUBLIC
    Code:
      stack=1, locals=1, args_size=1
         0: aload_0
         1: getfield      #332                // Field org$scalatest$concurrent$Conductors$Conductor$$greenLightForTestThreads:Lorg/scalatest/CountDownLatch;
         4: areturn
      LineNumberTable:
        line 702: 0
      LocalVariableTable:
        Start  Length  Slot  Name   Signature
            0       5     0  this   Lorg/scalatest/concurrent/Conductors$Conductor;

  public org.scalatest.compatible.Assertion conduct(org.scalatest.concurrent.AbstractPatienceConfiguration$PatienceConfig, org.scalactic.source.Position);
    descriptor: (Lorg/scalatest/concurrent/AbstractPatienceConfiguration$PatienceConfig;Lorg/scalactic/source/Position;)Lorg/scalatest/compatible/Assertion;
    flags: (0x0001) ACC_PUBLIC
    Code:
      stack=4, locals=3, args_size=3
         0: aload_0
         1: aload_1
         2: invokevirtual #337                // Method org/scalatest/concurrent/AbstractPatienceConfiguration$PatienceConfig.timeout:()Lorg/scalatest/time/Span;
         5: aload_1
         6: invokevirtual #340                // Method org/scalatest/concurrent/AbstractPatienceConfiguration$PatienceConfig.interval:()Lorg/scalatest/time/Span;
         9: aload_2
        10: invokespecial #344                // Method conductImpl:(Lorg/scalatest/time/Span;Lorg/scalatest/time/Span;Lorg/scalactic/source/Position;)Lorg/scalatest/compatible/Assertion;
        13: areturn
      LineNumberTable:
        line 712: 0
      LocalVariableTable:
        Start  Length  Slot  Name   Signature
            0      14     0  this   Lorg/scalatest/concurrent/Conductors$Conductor;
            0      14     1 config   Lorg/scalatest/concurrent/AbstractPatienceConfiguration$PatienceConfig;
            0      14     2   pos   Lorg/scalactic/source/Position;
    MethodParameters:
      Name                           Flags
      config                         final
      pos                            final

  public org.scalatest.compatible.Assertion conduct(org.scalatest.concurrent.PatienceConfiguration$Timeout, org.scalatest.concurrent.PatienceConfiguration$Interval, org.scalactic.source.Position);
    descriptor: (Lorg/scalatest/concurrent/PatienceConfiguration$Timeout;Lorg/scalatest/concurrent/PatienceConfiguration$Interval;Lorg/scalactic/source/Position;)Lorg/scalatest/compatible/Assertion;
    flags: (0x0001) ACC_PUBLIC
    Code:
      stack=4, locals=4, args_size=4
         0: aload_0
         1: aload_1
         2: invokevirtual #349                // Method org/scalatest/concurrent/PatienceConfiguration$Timeout.value:()Lorg/scalatest/time/Span;
         5: aload_2
         6: invokevirtual #350                // Method org/scalatest/concurrent/PatienceConfiguration$Interval.value:()Lorg/scalatest/time/Span;
         9: aload_3
        10: invokespecial #344                // Method conductImpl:(Lorg/scalatest/time/Span;Lorg/scalatest/time/Span;Lorg/scalactic/source/Position;)Lorg/scalatest/compatible/Assertion;
        13: areturn
      LineNumberTable:
        line 730: 0
      LocalVariableTable:
        Start  Length  Slot  Name   Signature
            0      14     0  this   Lorg/scalatest/concurrent/Conductors$Conductor;
            0      14     1 timeout   Lorg/scalatest/concurrent/PatienceConfiguration$Timeout;
            0      14     2 interval   Lorg/scalatest/concurrent/PatienceConfiguration$Interval;
            0      14     3   pos   Lorg/scalactic/source/Position;
    MethodParameters:
      Name                           Flags
      timeout                        final
      interval                       final
      pos                            final

  public org.scalatest.compatible.Assertion conduct(org.scalatest.concurrent.PatienceConfiguration$Timeout, org.scalatest.concurrent.AbstractPatienceConfiguration$PatienceConfig, org.scalactic.source.Position);
    descriptor: (Lorg/scalatest/concurrent/PatienceConfiguration$Timeout;Lorg/scalatest/concurrent/AbstractPatienceConfiguration$PatienceConfig;Lorg/scalactic/source/Position;)Lorg/scalatest/compatible/Assertion;
    flags: (0x0001) ACC_PUBLIC
    Code:
      stack=4, locals=4, args_size=4
         0: aload_0
         1: aload_1
         2: invokevirtual #349                // Method org/scalatest/concurrent/PatienceConfiguration$Timeout.value:()Lorg/scalatest/time/Span;
         5: aload_2
         6: invokevirtual #340                // Method org/scalatest/concurrent/AbstractPatienceConfiguration$PatienceConfig.interval:()Lorg/scalatest/time/Span;
         9: aload_3
        10: invokespecial #344                // Method conductImpl:(Lorg/scalatest/time/Span;Lorg/scalatest/time/Span;Lorg/scalactic/source/Position;)Lorg/scalatest/compatible/Assertion;
        13: areturn
      LineNumberTable:
        line 749: 0
      LocalVariableTable:
        Start  Length  Slot  Name   Signature
            0      14     0  this   Lorg/scalatest/concurrent/Conductors$Conductor;
            0      14     1 timeout   Lorg/scalatest/concurrent/PatienceConfiguration$Timeout;
            0      14     2 config   Lorg/scalatest/concurrent/AbstractPatienceConfiguration$PatienceConfig;
            0      14     3   pos   Lorg/scalactic/source/Position;
    MethodParameters:
      Name                           Flags
      timeout                        final
      config                         final
      pos                            final

  public org.scalatest.compatible.Assertion conduct(org.scalatest.concurrent.PatienceConfiguration$Interval, org.scalatest.concurrent.AbstractPatienceConfiguration$PatienceConfig, org.scalactic.source.Position);
    descriptor: (Lorg/scalatest/concurrent/PatienceConfiguration$Interval;Lorg/scalatest/concurrent/AbstractPatienceConfiguration$PatienceConfig;Lorg/scalactic/source/Position;)Lorg/scalatest/compatible/Assertion;
    flags: (0x0001) ACC_PUBLIC
    Code:
      stack=4, locals=4, args_size=4
         0: aload_0
         1: aload_2
         2: invokevirtual #337                // Method org/scalatest/concurrent/AbstractPatienceConfiguration$PatienceConfig.timeout:()Lorg/scalatest/time/Span;
         5: aload_1
         6: invokevirtual #350                // Method org/scalatest/concurrent/PatienceConfiguration$Interval.value:()Lorg/scalatest/time/Span;
         9: aload_3
        10: invokespecial #344                // Method conductImpl:(Lorg/scalatest/time/Span;Lorg/scalatest/time/Span;Lorg/scalactic/source/Position;)Lorg/scalatest/compatible/Assertion;
        13: areturn
      LineNumberTable:
        line 768: 0
      LocalVariableTable:
        Start  Length  Slot  Name   Signature
            0      14     0  this   Lorg/scalatest/concurrent/Conductors$Conductor;
            0      14     1 interval   Lorg/scalatest/concurrent/PatienceConfiguration$Interval;
            0      14     2 config   Lorg/scalatest/concurrent/AbstractPatienceConfiguration$PatienceConfig;
            0      14     3   pos   Lorg/scalactic/source/Position;
    MethodParameters:
      Name                           Flags
      interval                       final
      config                         final
      pos                            final

  private java.util.concurrent.atomic.AtomicReference<org.scalatest.concurrent.Conductors$Conductor$ConductorState> currentState();
    descriptor: ()Ljava/util/concurrent/atomic/AtomicReference;
    flags: (0x0002) ACC_PRIVATE
    Code:
      stack=1, locals=1, args_size=1
         0: aload_0
         1: getfield      #357                // Field currentState:Ljava/util/concurrent/atomic/AtomicReference;
         4: areturn
      LineNumberTable:
        line 771: 0
      LocalVariableTable:
        Start  Length  Slot  Name   Signature
            0       5     0  this   Lorg/scalatest/concurrent/Conductors$Conductor;
    Signature: #355                         // ()Ljava/util/concurrent/atomic/AtomicReference<Lorg/scalatest/concurrent/Conductors$Conductor$ConductorState;>;

  public boolean conductingHasBegun();
    descriptor: ()Z
    flags: (0x0001) ACC_PUBLIC
    Code:
      stack=1, locals=1, args_size=1
         0: aload_0
         1: invokespecial #189                // Method currentState:()Ljava/util/concurrent/atomic/AtomicReference;
         4: invokevirtual #195                // Method java/util/concurrent/atomic/AtomicReference.get:()Ljava/lang/Object;
         7: checkcast     #29                 // class org/scalatest/concurrent/Conductors$Conductor$ConductorState
        10: invokevirtual #360                // Method org/scalatest/concurrent/Conductors$Conductor$ConductorState.testWasStarted:()Z
        13: ireturn
      LineNumberTable:
        line 785: 0
      LocalVariableTable:
        Start  Length  Slot  Name   Signature
            0      14     0  this   Lorg/scalatest/concurrent/Conductors$Conductor;

  private org.scalatest.compatible.Assertion conductImpl(org.scalatest.time.Span, org.scalatest.time.Span, org.scalactic.source.Position);
    descriptor: (Lorg/scalatest/time/Span;Lorg/scalatest/time/Span;Lorg/scalactic/source/Position;)Lorg/scalatest/compatible/Assertion;
    flags: (0x0002) ACC_PRIVATE
    Code:
      stack=5, locals=5, args_size=4
         0: aload_0
         1: invokevirtual #280                // Method conductingHasBegun:()Z
         4: ifeq          22
         7: new           #203                // class org/scalatest/exceptions/NotAllowedException
        10: dup
        11: getstatic     #209                // Field org/scalatest/Resources$.MODULE$:Lorg/scalatest/Resources$;
        14: invokevirtual #364                // Method org/scalatest/Resources$.cannotCallConductTwice:()Ljava/lang/String;
        17: aload_3
        18: invokespecial #215                // Method org/scalatest/exceptions/NotAllowedException."<init>":(Ljava/lang/String;Lorg/scalactic/source/Position;)V
        21: athrow
        22: aload_0
        23: invokespecial #189                // Method currentState:()Ljava/util/concurrent/atomic/AtomicReference;
        26: aload_0
        27: invokespecial #366                // Method TestStarted:()Lorg/scalatest/concurrent/Conductors$Conductor$TestStarted$;
        30: invokevirtual #370                // Method java/util/concurrent/atomic/AtomicReference.set:(Ljava/lang/Object;)V
        33: aload_0
        34: invokespecial #157                // Method threads:()Ljava/util/concurrent/CopyOnWriteArrayList;
        37: invokevirtual #163                // Method java/util/concurrent/CopyOnWriteArrayList.size:()I
        40: iconst_0
        41: if_icmple     54
        44: aload_0
        45: invokevirtual #372                // Method org$scalatest$concurrent$Conductors$Conductor$$testThreadsStartingCounter:()Lorg/scalatest/concurrent/TestThreadsStartingCounter;
        48: invokevirtual #377                // Method org/scalatest/concurrent/TestThreadsStartingCounter.waitUntilAllTestThreadsHaveStarted:()V
        51: goto          54
        54: aload_0
        55: invokevirtual #379                // Method org$scalatest$concurrent$Conductors$Conductor$$greenLightForTestThreads:()Lorg/scalatest/CountDownLatch;
        58: invokevirtual #384                // Method org/scalatest/CountDownLatch.countDown:()V
        61: new           #23                 // class org/scalatest/concurrent/Conductors$Conductor$ClockThread
        64: dup
        65: aload_0
        66: aload_1
        67: aload_2
        68: invokespecial #387                // Method org/scalatest/concurrent/Conductors$Conductor$ClockThread."<init>":(Lorg/scalatest/concurrent/Conductors$Conductor;Lorg/scalatest/time/Span;Lorg/scalatest/time/Span;)V
        71: astore        4
        73: aload         4
        75: invokevirtual #388                // Method org/scalatest/concurrent/Conductors$Conductor$ClockThread.start:()V
        78: aload_0
        79: invokespecial #392                // Method waitForThreads:()Lorg/scalatest/Succeeded$;
        82: pop
        83: aload_0
        84: invokespecial #189                // Method currentState:()Ljava/util/concurrent/atomic/AtomicReference;
        87: aload_0
        88: invokespecial #197                // Method TestFinished:()Lorg/scalatest/concurrent/Conductors$Conductor$TestFinished$;
        91: invokevirtual #370                // Method java/util/concurrent/atomic/AtomicReference.set:(Ljava/lang/Object;)V
        94: aload_0
        95: invokevirtual #394                // Method org$scalatest$concurrent$Conductors$Conductor$$firstExceptionThrown:()Ljava/util/concurrent/ArrayBlockingQueue;
        98: invokevirtual #399                // Method java/util/concurrent/ArrayBlockingQueue.isEmpty:()Z
       101: ifne          115
       104: aload_0
       105: invokevirtual #394                // Method org$scalatest$concurrent$Conductors$Conductor$$firstExceptionThrown:()Ljava/util/concurrent/ArrayBlockingQueue;
       108: invokevirtual #402                // Method java/util/concurrent/ArrayBlockingQueue.peek:()Ljava/lang/Object;
       111: checkcast     #404                // class java/lang/Throwable
       114: athrow
       115: getstatic     #409                // Field org/scalatest/Succeeded$.MODULE$:Lorg/scalatest/Succeeded$;
       118: areturn
      StackMapTable: number_of_entries = 3
        frame_type = 22 /* same */
        frame_type = 31 /* same */
        frame_type = 252 /* append */
          offset_delta = 60
          locals = [ class org/scalatest/concurrent/Conductors$Conductor$ClockThread ]
      LineNumberTable:
        line 791: 0
        line 792: 7
        line 794: 22
        line 797: 33
        line 798: 44
        line 802: 54
        line 805: 61
        line 806: 73
        line 809: 78
        line 812: 83
        line 814: 94
        line 815: 104
        line 816: 115
      LocalVariableTable:
        Start  Length  Slot  Name   Signature
           73      45     4 clockThread   Lorg/scalatest/concurrent/Conductors$Conductor$ClockThread;
            0     119     0  this   Lorg/scalatest/concurrent/Conductors$Conductor;
            0     119     1 timeout   Lorg/scalatest/time/Span;
            0     119     2 clockInterval   Lorg/scalatest/time/Span;
            0     119     3   pos   Lorg/scalactic/source/Position;
    MethodParameters:
      Name                           Flags
      timeout                        final
      clockInterval                  final
      pos                            final

  private org.scalatest.Succeeded$ waitForThreads();
    descriptor: ()Lorg/scalatest/Succeeded$;
    flags: (0x0002) ACC_PRIVATE
    Code:
      stack=3, locals=2, args_size=1
         0: iconst_0
         1: invokestatic  #418                // Method scala/runtime/BooleanRef.create:(Z)Lscala/runtime/BooleanRef;
         4: astore_1
         5: aload_1
         6: getfield      #422                // Field scala/runtime/BooleanRef.elem:Z
         9: ifne          54
        12: getstatic     #427                // Field org/scalatest/concurrent/PimpedThreadGroup$.MODULE$:Lorg/scalatest/concurrent/PimpedThreadGroup$;
        15: aload_0
        16: invokevirtual #429                // Method org$scalatest$concurrent$Conductors$Conductor$$threadGroup:()Ljava/lang/ThreadGroup;
        19: invokevirtual #433                // Method org/scalatest/concurrent/PimpedThreadGroup$.threadGroupToPimpedThreadGroup:(Ljava/lang/ThreadGroup;)Lorg/scalatest/concurrent/PimpedThreadGroup;
        22: invokevirtual #438                // Method org/scalatest/concurrent/PimpedThreadGroup.areAnyThreadsAlive:()Z
        25: ifeq          54
        28: getstatic     #427                // Field org/scalatest/concurrent/PimpedThreadGroup$.MODULE$:Lorg/scalatest/concurrent/PimpedThreadGroup$;
        31: aload_0
        32: invokevirtual #429                // Method org$scalatest$concurrent$Conductors$Conductor$$threadGroup:()Ljava/lang/ThreadGroup;
        35: invokevirtual #433                // Method org/scalatest/concurrent/PimpedThreadGroup$.threadGroupToPimpedThreadGroup:(Ljava/lang/ThreadGroup;)Lorg/scalatest/concurrent/PimpedThreadGroup;
        38: invokevirtual #442                // Method org/scalatest/concurrent/PimpedThreadGroup.getThreads:()Lscala/collection/immutable/List;
        41: aload_0
        42: aload_1
        43: invokedynamic #455,  0            // InvokeDynamic #1:apply:(Lorg/scalatest/concurrent/Conductors$Conductor;Lscala/runtime/BooleanRef;)Lscala/Function1;
        48: invokevirtual #461                // Method scala/collection/immutable/List.foreach:(Lscala/Function1;)V
        51: goto          5
        54: getstatic     #409                // Field org/scalatest/Succeeded$.MODULE$:Lorg/scalatest/Succeeded$;
        57: areturn
      StackMapTable: number_of_entries = 2
        frame_type = 252 /* append */
          offset_delta = 5
          locals = [ class scala/runtime/BooleanRef ]
        frame_type = 48 /* same */
      LineNumberTable:
        line 836: 0
        line 837: 5
        line 838: 28
        line 853: 54
      LocalVariableTable:
        Start  Length  Slot  Name   Signature
            5      52     1 interrupted   Lscala/runtime/BooleanRef;
            0      58     0  this   Lorg/scalatest/concurrent/Conductors$Conductor;

  private final void TestThread$lzycompute$1();
    descriptor: ()V
    flags: (0x0012) ACC_PRIVATE, ACC_FINAL
    Code:
      stack=4, locals=2, args_size=1
         0: aload_0
         1: dup
         2: astore_1
         3: monitorenter
         4: aload_0
         5: getfield      #89                 // Field TestThread$module:Lorg/scalatest/concurrent/Conductors$Conductor$TestThread$;
         8: ifnonnull     23
        11: aload_0
        12: new           #44                 // class org/scalatest/concurrent/Conductors$Conductor$TestThread$
        15: dup
        16: aload_0
        17: invokespecial #466                // Method org/scalatest/concurrent/Conductors$Conductor$TestThread$."<init>":(Lorg/scalatest/concurrent/Conductors$Conductor;)V
        20: putfield      #89                 // Field TestThread$module:Lorg/scalatest/concurrent/Conductors$Conductor$TestThread$;
        23: aload_1
        24: monitorexit
        25: goto          31
        28: aload_1
        29: monitorexit
        30: athrow
        31: return
      Exception table:
         from    to  target type
             4    23    28   any
      StackMapTable: number_of_entries = 3
        frame_type = 252 /* append */
          offset_delta = 23
          locals = [ class org/scalatest/concurrent/Conductors$Conductor ]
        frame_type = 68 /* same_locals_1_stack_item */
          stack = [ class java/lang/Throwable ]
        frame_type = 2 /* same */
      LineNumberTable:
        line 563: 0
      LocalVariableTable:
        Start  Length  Slot  Name   Signature
            0      32     0  this   Lorg/scalatest/concurrent/Conductors$Conductor;

  private final void ClockThread$lzycompute$1();
    descriptor: ()V
    flags: (0x0012) ACC_PRIVATE, ACC_FINAL
    Code:
      stack=4, locals=2, args_size=1
         0: aload_0
         1: dup
         2: astore_1
         3: monitorenter
         4: aload_0
         5: getfield      #98                 // Field ClockThread$module:Lorg/scalatest/concurrent/Conductors$Conductor$ClockThread$;
         8: ifnonnull     23
        11: aload_0
        12: new           #26                 // class org/scalatest/concurrent/Conductors$Conductor$ClockThread$
        15: dup
        16: aload_0
        17: invokespecial #467                // Method org/scalatest/concurrent/Conductors$Conductor$ClockThread$."<init>":(Lorg/scalatest/concurrent/Conductors$Conductor;)V
        20: putfield      #98                 // Field ClockThread$module:Lorg/scalatest/concurrent/Conductors$Conductor$ClockThread$;
        23: aload_1
        24: monitorexit
        25: goto          31
        28: aload_1
        29: monitorexit
        30: athrow
        31: return
      Exception table:
         from    to  target type
             4    23    28   any
      StackMapTable: number_of_entries = 3
        frame_type = 252 /* append */
          offset_delta = 23
          locals = [ class org/scalatest/concurrent/Conductors$Conductor ]
        frame_type = 68 /* same_locals_1_stack_item */
          stack = [ class java/lang/Throwable ]
        frame_type = 2 /* same */
      LineNumberTable:
        line 1020: 0
      LocalVariableTable:
        Start  Length  Slot  Name   Signature
            0      32     0  this   Lorg/scalatest/concurrent/Conductors$Conductor;

  private final void Setup$lzycompute$1();
    descriptor: ()V
    flags: (0x0012) ACC_PRIVATE, ACC_FINAL
    Code:
      stack=4, locals=2, args_size=1
         0: aload_0
         1: dup
         2: astore_1
         3: monitorenter
         4: aload_0
         5: getfield      #105                // Field Setup$module:Lorg/scalatest/concurrent/Conductors$Conductor$Setup$;
         8: ifnonnull     23
        11: aload_0
        12: new           #32                 // class org/scalatest/concurrent/Conductors$Conductor$Setup$
        15: dup
        16: aload_0
        17: invokespecial #468                // Method org/scalatest/concurrent/Conductors$Conductor$Setup$."<init>":(Lorg/scalatest/concurrent/Conductors$Conductor;)V
        20: putfield      #105                // Field Setup$module:Lorg/scalatest/concurrent/Conductors$Conductor$Setup$;
        23: aload_1
        24: monitorexit
        25: goto          31
        28: aload_1
        29: monitorexit
        30: athrow
        31: return
      Exception table:
         from    to  target type
             4    23    28   any
      StackMapTable: number_of_entries = 3
        frame_type = 252 /* append */
          offset_delta = 23
          locals = [ class org/scalatest/concurrent/Conductors$Conductor ]
        frame_type = 68 /* same_locals_1_stack_item */
          stack = [ class java/lang/Throwable ]
        frame_type = 2 /* same */
      LineNumberTable:
        line 1130: 0
      LocalVariableTable:
        Start  Length  Slot  Name   Signature
            0      32     0  this   Lorg/scalatest/concurrent/Conductors$Conductor;

  private final void TestStarted$lzycompute$1();
    descriptor: ()V
    flags: (0x0012) ACC_PRIVATE, ACC_FINAL
    Code:
      stack=4, locals=2, args_size=1
         0: aload_0
         1: dup
         2: astore_1
         3: monitorenter
         4: aload_0
         5: getfield      #112                // Field TestStarted$module:Lorg/scalatest/concurrent/Conductors$Conductor$TestStarted$;
         8: ifnonnull     23
        11: aload_0
        12: new           #38                 // class org/scalatest/concurrent/Conductors$Conductor$TestStarted$
        15: dup
        16: aload_0
        17: invokespecial #469                // Method org/scalatest/concurrent/Conductors$Conductor$TestStarted$."<init>":(Lorg/scalatest/concurrent/Conductors$Conductor;)V
        20: putfield      #112                // Field TestStarted$module:Lorg/scalatest/concurrent/Conductors$Conductor$TestStarted$;
        23: aload_1
        24: monitorexit
        25: goto          31
        28: aload_1
        29: monitorexit
        30: athrow
        31: return
      Exception table:
         from    to  target type
             4    23    28   any
      StackMapTable: number_of_entries = 3
        frame_type = 252 /* append */
          offset_delta = 23
          locals = [ class org/scalatest/concurrent/Conductors$Conductor ]
        frame_type = 68 /* same_locals_1_stack_item */
          stack = [ class java/lang/Throwable ]
        frame_type = 2 /* same */
      LineNumberTable:
        line 1137: 0
      LocalVariableTable:
        Start  Length  Slot  Name   Signature
            0      32     0  this   Lorg/scalatest/concurrent/Conductors$Conductor;

  private final void TestFinished$lzycompute$1();
    descriptor: ()V
    flags: (0x0012) ACC_PRIVATE, ACC_FINAL
    Code:
      stack=4, locals=2, args_size=1
         0: aload_0
         1: dup
         2: astore_1
         3: monitorenter
         4: aload_0
         5: getfield      #119                // Field TestFinished$module:Lorg/scalatest/concurrent/Conductors$Conductor$TestFinished$;
         8: ifnonnull     23
        11: aload_0
        12: new           #35                 // class org/scalatest/concurrent/Conductors$Conductor$TestFinished$
        15: dup
        16: aload_0
        17: invokespecial #470                // Method org/scalatest/concurrent/Conductors$Conductor$TestFinished$."<init>":(Lorg/scalatest/concurrent/Conductors$Conductor;)V
        20: putfield      #119                // Field TestFinished$module:Lorg/scalatest/concurrent/Conductors$Conductor$TestFinished$;
        23: aload_1
        24: monitorexit
        25: goto          31
        28: aload_1
        29: monitorexit
        30: athrow
        31: return
      Exception table:
         from    to  target type
             4    23    28   any
      StackMapTable: number_of_entries = 3
        frame_type = 252 /* append */
          offset_delta = 23
          locals = [ class org/scalatest/concurrent/Conductors$Conductor ]
        frame_type = 68 /* same_locals_1_stack_item */
          stack = [ class java/lang/Throwable ]
        frame_type = 2 /* same */
      LineNumberTable:
        line 1145: 0
      LocalVariableTable:
        Start  Length  Slot  Name   Signature
            0      32     0  this   Lorg/scalatest/concurrent/Conductors$Conductor;

  public static final void $anonfun$threadNamed$1(scala.Function0);
    descriptor: (Lscala/Function0;)V
    flags: (0x1019) ACC_PUBLIC, ACC_STATIC, ACC_FINAL, ACC_SYNTHETIC
    Code:
      stack=1, locals=1, args_size=1
         0: aload_0
         1: invokeinterface #296,  1          // InterfaceMethod scala/Function0.apply:()Ljava/lang/Object;
         6: pop
         7: return
      LineNumberTable:
        line 545: 0
      LocalVariableTable:
        Start  Length  Slot  Name   Signature
            0       8     0 fun$1   Lscala/Function0;
    MethodParameters:
      Name                           Flags
      fun$1                          final

  public static final void $anonfun$waitForThreads$1(org.scalatest.concurrent.Conductors$Conductor, scala.runtime.BooleanRef, java.lang.Thread);
    descriptor: (Lorg/scalatest/concurrent/Conductors$Conductor;Lscala/runtime/BooleanRef;Ljava/lang/Thread;)V
    flags: (0x1019) ACC_PUBLIC, ACC_STATIC, ACC_FINAL, ACC_SYNTHETIC
    Code:
      stack=2, locals=4, args_size=3
         0: aload_1
         1: getfield      #422                // Field scala/runtime/BooleanRef.elem:Z
         4: ifne          43
         7: aload_2
         8: invokevirtual #480                // Method java/lang/Thread.isAlive:()Z
        11: ifeq          43
        14: aload_0
        15: invokevirtual #394                // Method org$scalatest$concurrent$Conductors$Conductor$$firstExceptionThrown:()Ljava/util/concurrent/ArrayBlockingQueue;
        18: invokevirtual #399                // Method java/util/concurrent/ArrayBlockingQueue.isEmpty:()Z
        21: ifeq          43
        24: aload_2
        25: invokevirtual #483                // Method java/lang/Thread.join:()V
        28: goto          40
        31: astore_3
        32: aload_1
        33: iconst_1
        34: putfield      #422                // Field scala/runtime/BooleanRef.elem:Z
        37: goto          40
        40: goto          43
        43: return
      Exception table:
         from    to  target type
            24    28    31   Class java/lang/InterruptedException
      StackMapTable: number_of_entries = 3
        frame_type = 95 /* same_locals_1_stack_item */
          stack = [ class java/lang/InterruptedException ]
        frame_type = 8 /* same */
        frame_type = 2 /* same */
      LineNumberTable:
        line 839: 0
        line 841: 24
        line 849: 32
        line 839: 43
      LocalVariableTable:
        Start  Length  Slot  Name   Signature
           31       6     3     e   Ljava/lang/InterruptedException;
            0      44     0 $this   Lorg/scalatest/concurrent/Conductors$Conductor;
            0      44     1 interrupted$1   Lscala/runtime/BooleanRef;
            0      44     2     t   Ljava/lang/Thread;
    MethodParameters:
      Name                           Flags
      $this                          final synthetic
      interrupted$1                  final
      t                              final

  public org.scalatest.concurrent.Conductors$Conductor(org.scalatest.concurrent.Conductors);
    descriptor: (Lorg/scalatest/concurrent/Conductors;)V
    flags: (0x0001) ACC_PUBLIC
    Code:
      stack=4, locals=2, args_size=2
         0: aload_1
         1: ifnonnull     6
         4: aconst_null
         5: athrow
         6: aload_0
         7: aload_1
         8: putfield      #285                // Field $outer:Lorg/scalatest/concurrent/Conductors;
        11: aload_0
        12: invokespecial #488                // Method java/lang/Object."<init>":()V
        15: aload_0
        16: new           #20                 // class org/scalatest/concurrent/Conductors$Conductor$Clock
        19: dup
        20: aload_0
        21: invokespecial #489                // Method org/scalatest/concurrent/Conductors$Conductor$Clock."<init>":(Lorg/scalatest/concurrent/Conductors$Conductor;)V
        24: putfield      #125                // Field org$scalatest$concurrent$Conductors$Conductor$$clock:Lorg/scalatest/concurrent/Conductors$Conductor$Clock;
        27: aload_0
        28: new           #491                // class java/lang/ThreadGroup
        31: dup
        32: ldc_w         #493                // String Orchestra
        35: invokespecial #496                // Method java/lang/ThreadGroup."<init>":(Ljava/lang/String;)V
        38: putfield      #128                // Field org$scalatest$concurrent$Conductors$Conductor$$threadGroup:Ljava/lang/ThreadGroup;
        41: aload_0
        42: new           #159                // class java/util/concurrent/CopyOnWriteArrayList
        45: dup
        46: invokespecial #497                // Method java/util/concurrent/CopyOnWriteArrayList."<init>":()V
        49: putfield      #132                // Field threads:Ljava/util/concurrent/CopyOnWriteArrayList;
        52: aload_0
        53: new           #159                // class java/util/concurrent/CopyOnWriteArrayList
        56: dup
        57: invokespecial #497                // Method java/util/concurrent/CopyOnWriteArrayList."<init>":()V
        60: putfield      #135                // Field threadNames:Ljava/util/concurrent/CopyOnWriteArrayList;
        63: aload_0
        64: invokestatic  #271                // Method java/lang/Thread.currentThread:()Ljava/lang/Thread;
        67: putfield      #138                // Field org$scalatest$concurrent$Conductors$Conductor$$mainThread:Ljava/lang/Thread;
        70: aload_0
        71: new           #396                // class java/util/concurrent/ArrayBlockingQueue
        74: dup
        75: iconst_1
        76: invokespecial #498                // Method java/util/concurrent/ArrayBlockingQueue."<init>":(I)V
        79: putfield      #263                // Field org$scalatest$concurrent$Conductors$Conductor$$firstExceptionThrown:Ljava/util/concurrent/ArrayBlockingQueue;
        82: aload_0
        83: new           #374                // class org/scalatest/concurrent/TestThreadsStartingCounter
        86: dup
        87: invokespecial #499                // Method org/scalatest/concurrent/TestThreadsStartingCounter."<init>":()V
        90: putfield      #329                // Field org$scalatest$concurrent$Conductors$Conductor$$testThreadsStartingCounter:Lorg/scalatest/concurrent/TestThreadsStartingCounter;
        93: aload_0
        94: new           #381                // class org/scalatest/CountDownLatch
        97: dup
        98: iconst_1
        99: invokespecial #500                // Method org/scalatest/CountDownLatch."<init>":(I)V
       102: putfield      #332                // Field org$scalatest$concurrent$Conductors$Conductor$$greenLightForTestThreads:Lorg/scalatest/CountDownLatch;
       105: aload_0
       106: new           #191                // class java/util/concurrent/atomic/AtomicReference
       109: dup
       110: aload_0
       111: invokespecial #502                // Method Setup:()Lorg/scalatest/concurrent/Conductors$Conductor$Setup$;
       114: invokespecial #504                // Method java/util/concurrent/atomic/AtomicReference."<init>":(Ljava/lang/Object;)V
       117: putfield      #357                // Field currentState:Ljava/util/concurrent/atomic/AtomicReference;
       120: return
      StackMapTable: number_of_entries = 1
        frame_type = 6 /* same */
      LineNumberTable:
        line 485: 0
        line 1147: 11
        line 492: 15
        line 497: 27
        line 502: 41
        line 506: 52
        line 509: 63
        line 601: 70
        line 696: 82
        line 702: 93
        line 771: 105
        line 485: 120
      LocalVariableTable:
        Start  Length  Slot  Name   Signature
            0     121     0  this   Lorg/scalatest/concurrent/Conductors$Conductor;
            0     121     1 $outer   Lorg/scalatest/concurrent/Conductors;
    MethodParameters:
      Name                           Flags
      $outer                         final synthetic

  public static final java.lang.Object $anonfun$waitForThreads$1$adapted(org.scalatest.concurrent.Conductors$Conductor, scala.runtime.BooleanRef, java.lang.Thread);
    descriptor: (Lorg/scalatest/concurrent/Conductors$Conductor;Lscala/runtime/BooleanRef;Ljava/lang/Thread;)Ljava/lang/Object;
    flags: (0x1019) ACC_PUBLIC, ACC_STATIC, ACC_FINAL, ACC_SYNTHETIC
    Code:
      stack=3, locals=3, args_size=3
         0: aload_0
         1: aload_1
         2: aload_2
         3: invokestatic  #506                // Method $anonfun$waitForThreads$1:(Lorg/scalatest/concurrent/Conductors$Conductor;Lscala/runtime/BooleanRef;Ljava/lang/Thread;)V
         6: getstatic     #512                // Field scala/runtime/BoxedUnit.UNIT:Lscala/runtime/BoxedUnit;
         9: areturn
      LineNumberTable:
        line 838: 0
      LocalVariableTable:
        Start  Length  Slot  Name   Signature
            0      10     0 $this   Lorg/scalatest/concurrent/Conductors$Conductor;
            0      10     1 interrupted$1   Lscala/runtime/BooleanRef;
            0      10     2     t   Ljava/lang/Thread;
    MethodParameters:
      Name                           Flags
      $this                          final
      interrupted$1                  final
      t                              final

  private static java.lang.Object $deserializeLambda$(java.lang.invoke.SerializedLambda);
    descriptor: (Ljava/lang/invoke/SerializedLambda;)Ljava/lang/Object;
    flags: (0x100a) ACC_PRIVATE, ACC_STATIC, ACC_SYNTHETIC
    Code:
      stack=1, locals=1, args_size=1
         0: aload_0
         1: invokedynamic #524,  0            // InvokeDynamic #2:lambdaDeserialize:(Ljava/lang/invoke/SerializedLambda;)Ljava/lang/Object;
         6: areturn
}
InnerClasses:
  public static final #10= #7 of #9;      // Lookup=class java/lang/invoke/MethodHandles$Lookup of class java/lang/invoke/MethodHandles
  public final #15= #12 of #14;           // PatienceConfig=class org/scalatest/concurrent/AbstractPatienceConfiguration$PatienceConfig of class org/scalatest/concurrent/AbstractPatienceConfiguration
  public final #18= #2 of #17;            // Conductor=class org/scalatest/concurrent/Conductors$Conductor of class org/scalatest/concurrent/Conductors
  private #21= #20 of #2;                 // Clock=class org/scalatest/concurrent/Conductors$Conductor$Clock of class org/scalatest/concurrent/Conductors$Conductor
  private #24= #23 of #2;                 // ClockThread=class org/scalatest/concurrent/Conductors$Conductor$ClockThread of class org/scalatest/concurrent/Conductors$Conductor
  private #27= #26 of #2;                 // ClockThread$=class org/scalatest/concurrent/Conductors$Conductor$ClockThread$ of class org/scalatest/concurrent/Conductors$Conductor
  private abstract #30= #29 of #2;        // ConductorState=class org/scalatest/concurrent/Conductors$Conductor$ConductorState of class org/scalatest/concurrent/Conductors$Conductor
  private #33= #32 of #2;                 // Setup$=class org/scalatest/concurrent/Conductors$Conductor$Setup$ of class org/scalatest/concurrent/Conductors$Conductor
  private #36= #35 of #2;                 // TestFinished$=class org/scalatest/concurrent/Conductors$Conductor$TestFinished$ of class org/scalatest/concurrent/Conductors$Conductor
  private #39= #38 of #2;                 // TestStarted$=class org/scalatest/concurrent/Conductors$Conductor$TestStarted$ of class org/scalatest/concurrent/Conductors$Conductor
  private #42= #41 of #2;                 // TestThread=class org/scalatest/concurrent/Conductors$Conductor$TestThread of class org/scalatest/concurrent/Conductors$Conductor
  private #45= #44 of #2;                 // TestThread$=class org/scalatest/concurrent/Conductors$Conductor$TestThread$ of class org/scalatest/concurrent/Conductors$Conductor
  public static final #50= #47 of #49;    // Interval=class org/scalatest/concurrent/PatienceConfiguration$Interval of class org/scalatest/concurrent/PatienceConfiguration
  public static final #53= #52 of #49;    // Timeout=class org/scalatest/concurrent/PatienceConfiguration$Timeout of class org/scalatest/concurrent/PatienceConfiguration
SourceFile: "Conductors.scala"
BootstrapMethods:
  0: #238 REF_invokeStatic java/lang/invoke/LambdaMetafactory.altMetafactory:(Ljava/lang/invoke/MethodHandles$Lookup;Ljava/lang/String;Ljava/lang/invoke/MethodType;[Ljava/lang/Object;)Ljava/lang/invoke/CallSite;
    Method arguments:
      #225 ()V
      #230 REF_invokeStatic org/scalatest/concurrent/Conductors$Conductor.$anonfun$threadNamed$1:(Lscala/Function0;)V
      #225 ()V
      #231 1
  1: #238 REF_invokeStatic java/lang/invoke/LambdaMetafactory.altMetafactory:(Ljava/lang/invoke/MethodHandles$Lookup;Ljava/lang/String;Ljava/lang/invoke/MethodType;[Ljava/lang/Object;)Ljava/lang/invoke/CallSite;
    Method arguments:
      #444 (Ljava/lang/Object;)Ljava/lang/Object;
      #449 REF_invokeStatic org/scalatest/concurrent/Conductors$Conductor.$anonfun$waitForThreads$1$adapted:(Lorg/scalatest/concurrent/Conductors$Conductor;Lscala/runtime/BooleanRef;Ljava/lang/Thread;)Ljava/lang/Object;
      #451 (Ljava/lang/Thread;)Ljava/lang/Object;
      #452 5
      #231 1
      #451 (Ljava/lang/Thread;)Ljava/lang/Object;
  2: #521 REF_invokeStatic scala/runtime/LambdaDeserialize.bootstrap:(Ljava/lang/invoke/MethodHandles$Lookup;Ljava/lang/String;Ljava/lang/invoke/MethodType;[Ljava/lang/invoke/MethodHandle;)Ljava/lang/invoke/CallSite;
    Method arguments:
      #230 REF_invokeStatic org/scalatest/concurrent/Conductors$Conductor.$anonfun$threadNamed$1:(Lscala/Function0;)V
      #449 REF_invokeStatic org/scalatest/concurrent/Conductors$Conductor.$anonfun$waitForThreads$1$adapted:(Lorg/scalatest/concurrent/Conductors$Conductor;Lscala/runtime/BooleanRef;Ljava/lang/Thread;)Ljava/lang/Object;
  ScalaInlineInfo: length = 0xBD (unknown attribute)
   01 01 00 25 00 E2 00 E3 01 01 D8 01 D9 01 01 BD
   01 BE 01 00 92 01 E6 01 00 18 00 60 01 00 63 00
   5B 01 00 66 00 67 01 00 6A 00 5B 01 00 74 00 75
   01 00 78 00 5B 01 00 6D 00 6E 01 00 71 00 5B 01
   00 2A 00 57 01 00 5A 00 5B 01 01 2D 00 A1 01 01
   22 01 23 01 01 22 01 62 01 01 22 01 61 01 01 22
   01 5A 01 01 55 01 56 01 01 15 01 16 01 00 52 00
   BB 01 01 43 01 16 01 00 40 00 7B 01 00 4B 01 04
   01 00 50 01 4A 01 00 49 00 88 01 00 4E 01 47 01
   00 42 00 7E 01 00 8B 00 8C 01 00 B3 00 B4 01 00
   47 00 81 01 00 44 00 81 01 01 2B 01 2C 01 01 85
   01 86 01 01 08 01 09 01 01 3D 01 3E 01
  Scala: length = 0x0 (unknown attribute)

