Classfile /Users/mw/Projects/slang-braindump/.jar/jar11/assemble/slang-braindump/assemble/content/org/scalatest/concurrent/Futures$FutureConcept.class
  Last modified May 29, 2022; size 6137 bytes
  SHA-256 checksum a507b48edf45fb574cf5b9c780f73e70e03020d4c284b46dafcefbe6040382ae
  Compiled from "Futures.scala"
public interface org.scalatest.concurrent.Futures$FutureConcept<T extends java.lang.Object>
  minor version: 0
  major version: 52
  flags: (0x0601) ACC_PUBLIC, ACC_INTERFACE, ACC_ABSTRACT
  this_class: #2                          // org/scalatest/concurrent/Futures$FutureConcept
  super_class: #5                         // java/lang/Object
  interfaces: 0, fields: 0, methods: 16, attributes: 5
Constant pool:
    #1 = Utf8               org/scalatest/concurrent/Futures$FutureConcept
    #2 = Class              #1            // org/scalatest/concurrent/Futures$FutureConcept
    #3 = Utf8               <T:Ljava/lang/Object;>Ljava/lang/Object;
    #4 = Utf8               java/lang/Object
    #5 = Class              #4            // java/lang/Object
    #6 = Utf8               Futures.scala
    #7 = Utf8               org/scalatest/concurrent/AbstractPatienceConfiguration$PatienceConfig
    #8 = Class              #7            // org/scalatest/concurrent/AbstractPatienceConfiguration$PatienceConfig
    #9 = Utf8               org/scalatest/concurrent/AbstractPatienceConfiguration
   #10 = Class              #9            // org/scalatest/concurrent/AbstractPatienceConfiguration
   #11 = Utf8               PatienceConfig
   #12 = Utf8               org/scalatest/concurrent/Futures
   #13 = Class              #12           // org/scalatest/concurrent/Futures
   #14 = Utf8               FutureConcept
   #15 = Utf8               org/scalatest/concurrent/PatienceConfiguration$Interval
   #16 = Class              #15           // org/scalatest/concurrent/PatienceConfiguration$Interval
   #17 = Utf8               org/scalatest/concurrent/PatienceConfiguration
   #18 = Class              #17           // org/scalatest/concurrent/PatienceConfiguration
   #19 = Utf8               Interval
   #20 = Utf8               org/scalatest/concurrent/PatienceConfiguration$Timeout
   #21 = Class              #20           // org/scalatest/concurrent/PatienceConfiguration$Timeout
   #22 = Utf8               Timeout
   #23 = Utf8               eitherValue
   #24 = Utf8               ()Lscala/Option;
   #25 = Utf8               ()Lscala/Option<Lscala/util/Either<Ljava/lang/Throwable;TT;>;>;
   #26 = Utf8               isExpired
   #27 = Utf8               ()Z
   #28 = Utf8               isCanceled
   #29 = Utf8               isReadyWithin$
   #30 = Utf8               (Lorg/scalatest/concurrent/Futures$FutureConcept;Lorg/scalatest/time/Span;Lorg/scalatest/concurrent/AbstractPatienceConfiguration$PatienceConfig;Lorg/scalactic/source/Position;)Z
   #31 = Utf8               $this
   #32 = Utf8               timeout
   #33 = Utf8               config
   #34 = Utf8               pos
   #35 = Utf8               isReadyWithin
   #36 = Utf8               (Lorg/scalatest/time/Span;Lorg/scalatest/concurrent/AbstractPatienceConfiguration$PatienceConfig;Lorg/scalactic/source/Position;)Z
   #37 = NameAndType        #35:#36       // isReadyWithin:(Lorg/scalatest/time/Span;Lorg/scalatest/concurrent/AbstractPatienceConfiguration$PatienceConfig;Lorg/scalactic/source/Position;)Z
   #38 = InterfaceMethodref #2.#37        // org/scalatest/concurrent/Futures$FutureConcept.isReadyWithin:(Lorg/scalatest/time/Span;Lorg/scalatest/concurrent/AbstractPatienceConfiguration$PatienceConfig;Lorg/scalactic/source/Position;)Z
   #39 = Utf8               Lorg/scalatest/concurrent/Futures$FutureConcept;
   #40 = Utf8               Lorg/scalatest/time/Span;
   #41 = Utf8               Lorg/scalatest/concurrent/AbstractPatienceConfiguration$PatienceConfig;
   #42 = Utf8               Lorg/scalactic/source/Position;
   #43 = Utf8               java/lang/Throwable
   #44 = Class              #43           // java/lang/Throwable
   #45 = Utf8               org$scalatest$concurrent$Futures$FutureConcept$$$outer
   #46 = Utf8               ()Lorg/scalatest/concurrent/Futures;
   #47 = NameAndType        #45:#46       // org$scalatest$concurrent$Futures$FutureConcept$$$outer:()Lorg/scalatest/concurrent/Futures;
   #48 = InterfaceMethodref #2.#47        // org/scalatest/concurrent/Futures$FutureConcept.org$scalatest$concurrent$Futures$FutureConcept$$$outer:()Lorg/scalatest/concurrent/Futures;
   #49 = Utf8               interval
   #50 = Utf8               ()Lorg/scalatest/time/Span;
   #51 = NameAndType        #49:#50       // interval:()Lorg/scalatest/time/Span;
   #52 = Methodref          #8.#51        // org/scalatest/concurrent/AbstractPatienceConfiguration$PatienceConfig.interval:()Lorg/scalatest/time/Span;
   #53 = Utf8               <init>
   #54 = Utf8               (Lorg/scalatest/concurrent/AbstractPatienceConfiguration;Lorg/scalatest/time/Span;Lorg/scalatest/time/Span;)V
   #55 = NameAndType        #53:#54       // "<init>":(Lorg/scalatest/concurrent/AbstractPatienceConfiguration;Lorg/scalatest/time/Span;Lorg/scalatest/time/Span;)V
   #56 = Methodref          #8.#55        // org/scalatest/concurrent/AbstractPatienceConfiguration$PatienceConfig."<init>":(Lorg/scalatest/concurrent/AbstractPatienceConfiguration;Lorg/scalatest/time/Span;Lorg/scalatest/time/Span;)V
   #57 = Utf8               futureValueImpl
   #58 = Utf8               (Lorg/scalactic/source/Position;Lorg/scalatest/concurrent/AbstractPatienceConfiguration$PatienceConfig;)Ljava/lang/Object;
   #59 = NameAndType        #57:#58       // futureValueImpl:(Lorg/scalactic/source/Position;Lorg/scalatest/concurrent/AbstractPatienceConfiguration$PatienceConfig;)Ljava/lang/Object;
   #60 = InterfaceMethodref #2.#59        // org/scalatest/concurrent/Futures$FutureConcept.futureValueImpl:(Lorg/scalactic/source/Position;Lorg/scalatest/concurrent/AbstractPatienceConfiguration$PatienceConfig;)Ljava/lang/Object;
   #61 = Utf8               org/scalatest/exceptions/TimeoutField
   #62 = Class              #61           // org/scalatest/exceptions/TimeoutField
   #63 = Utf8               this
   #64 = Utf8               org/scalatest/time/Span
   #65 = Class              #64           // org/scalatest/time/Span
   #66 = Utf8               org/scalactic/source/Position
   #67 = Class              #66           // org/scalactic/source/Position
   #68 = Utf8               futureValue$
   #69 = Utf8               (Lorg/scalatest/concurrent/Futures$FutureConcept;Lorg/scalatest/concurrent/PatienceConfiguration$Timeout;Lorg/scalatest/concurrent/PatienceConfiguration$Interval;Lorg/scalactic/source/Position;)Ljava/lang/Object;
   #70 = Utf8               futureValue
   #71 = Utf8               (Lorg/scalatest/concurrent/PatienceConfiguration$Timeout;Lorg/scalatest/concurrent/PatienceConfiguration$Interval;Lorg/scalactic/source/Position;)Ljava/lang/Object;
   #72 = NameAndType        #70:#71       // futureValue:(Lorg/scalatest/concurrent/PatienceConfiguration$Timeout;Lorg/scalatest/concurrent/PatienceConfiguration$Interval;Lorg/scalactic/source/Position;)Ljava/lang/Object;
   #73 = InterfaceMethodref #2.#72        // org/scalatest/concurrent/Futures$FutureConcept.futureValue:(Lorg/scalatest/concurrent/PatienceConfiguration$Timeout;Lorg/scalatest/concurrent/PatienceConfiguration$Interval;Lorg/scalactic/source/Position;)Ljava/lang/Object;
   #74 = Utf8               Lorg/scalatest/concurrent/PatienceConfiguration$Timeout;
   #75 = Utf8               Lorg/scalatest/concurrent/PatienceConfiguration$Interval;
   #76 = Utf8               (Lorg/scalatest/concurrent/PatienceConfiguration$Timeout;Lorg/scalatest/concurrent/PatienceConfiguration$Interval;Lorg/scalactic/source/Position;)TT;
   #77 = Utf8               value
   #78 = NameAndType        #77:#50       // value:()Lorg/scalatest/time/Span;
   #79 = Methodref          #21.#78       // org/scalatest/concurrent/PatienceConfiguration$Timeout.value:()Lorg/scalatest/time/Span;
   #80 = Methodref          #16.#78       // org/scalatest/concurrent/PatienceConfiguration$Interval.value:()Lorg/scalatest/time/Span;
   #81 = Utf8               (Lorg/scalatest/concurrent/Futures$FutureConcept;Lorg/scalatest/concurrent/PatienceConfiguration$Timeout;Lorg/scalatest/concurrent/AbstractPatienceConfiguration$PatienceConfig;Lorg/scalactic/source/Position;)Ljava/lang/Object;
   #82 = Utf8               (Lorg/scalatest/concurrent/PatienceConfiguration$Timeout;Lorg/scalatest/concurrent/AbstractPatienceConfiguration$PatienceConfig;Lorg/scalactic/source/Position;)Ljava/lang/Object;
   #83 = NameAndType        #70:#82       // futureValue:(Lorg/scalatest/concurrent/PatienceConfiguration$Timeout;Lorg/scalatest/concurrent/AbstractPatienceConfiguration$PatienceConfig;Lorg/scalactic/source/Position;)Ljava/lang/Object;
   #84 = InterfaceMethodref #2.#83        // org/scalatest/concurrent/Futures$FutureConcept.futureValue:(Lorg/scalatest/concurrent/PatienceConfiguration$Timeout;Lorg/scalatest/concurrent/AbstractPatienceConfiguration$PatienceConfig;Lorg/scalactic/source/Position;)Ljava/lang/Object;
   #85 = Utf8               (Lorg/scalatest/concurrent/PatienceConfiguration$Timeout;Lorg/scalatest/concurrent/AbstractPatienceConfiguration$PatienceConfig;Lorg/scalactic/source/Position;)TT;
   #86 = Utf8               (Lorg/scalatest/concurrent/Futures$FutureConcept;Lorg/scalatest/concurrent/PatienceConfiguration$Interval;Lorg/scalatest/concurrent/AbstractPatienceConfiguration$PatienceConfig;Lorg/scalactic/source/Position;)Ljava/lang/Object;
   #87 = Utf8               (Lorg/scalatest/concurrent/PatienceConfiguration$Interval;Lorg/scalatest/concurrent/AbstractPatienceConfiguration$PatienceConfig;Lorg/scalactic/source/Position;)Ljava/lang/Object;
   #88 = NameAndType        #70:#87       // futureValue:(Lorg/scalatest/concurrent/PatienceConfiguration$Interval;Lorg/scalatest/concurrent/AbstractPatienceConfiguration$PatienceConfig;Lorg/scalactic/source/Position;)Ljava/lang/Object;
   #89 = InterfaceMethodref #2.#88        // org/scalatest/concurrent/Futures$FutureConcept.futureValue:(Lorg/scalatest/concurrent/PatienceConfiguration$Interval;Lorg/scalatest/concurrent/AbstractPatienceConfiguration$PatienceConfig;Lorg/scalactic/source/Position;)Ljava/lang/Object;
   #90 = Utf8               (Lorg/scalatest/concurrent/PatienceConfiguration$Interval;Lorg/scalatest/concurrent/AbstractPatienceConfiguration$PatienceConfig;Lorg/scalactic/source/Position;)TT;
   #91 = NameAndType        #32:#50       // timeout:()Lorg/scalatest/time/Span;
   #92 = Methodref          #8.#91        // org/scalatest/concurrent/AbstractPatienceConfiguration$PatienceConfig.timeout:()Lorg/scalatest/time/Span;
   #93 = Utf8               (Lorg/scalatest/concurrent/Futures$FutureConcept;Lorg/scalatest/concurrent/AbstractPatienceConfiguration$PatienceConfig;Lorg/scalactic/source/Position;)Ljava/lang/Object;
   #94 = Utf8               (Lorg/scalatest/concurrent/AbstractPatienceConfiguration$PatienceConfig;Lorg/scalactic/source/Position;)Ljava/lang/Object;
   #95 = NameAndType        #70:#94       // futureValue:(Lorg/scalatest/concurrent/AbstractPatienceConfiguration$PatienceConfig;Lorg/scalactic/source/Position;)Ljava/lang/Object;
   #96 = InterfaceMethodref #2.#95        // org/scalatest/concurrent/Futures$FutureConcept.futureValue:(Lorg/scalatest/concurrent/AbstractPatienceConfiguration$PatienceConfig;Lorg/scalactic/source/Position;)Ljava/lang/Object;
   #97 = Utf8               (Lorg/scalatest/concurrent/AbstractPatienceConfiguration$PatienceConfig;Lorg/scalactic/source/Position;)TT;
   #98 = Utf8               (Lorg/scalactic/source/Position;Lorg/scalatest/concurrent/AbstractPatienceConfiguration$PatienceConfig;)TT;
   #99 = Utf8               $init$
  #100 = Utf8               (Lorg/scalatest/concurrent/Futures$FutureConcept;)V
  #101 = Utf8               Signature
  #102 = Utf8               Code
  #103 = Utf8               LineNumberTable
  #104 = Utf8               LocalVariableTable
  #105 = Utf8               MethodParameters
  #106 = Utf8               StackMapTable
  #107 = Utf8               InnerClasses
  #108 = Utf8               SourceFile
  #109 = Utf8               ScalaInlineInfo
  #110 = Utf8               Scala
{
  public abstract scala.Option<scala.util.Either<java.lang.Throwable, T>> eitherValue();
    descriptor: ()Lscala/Option;
    flags: (0x0401) ACC_PUBLIC, ACC_ABSTRACT
    Signature: #25                          // ()Lscala/Option<Lscala/util/Either<Ljava/lang/Throwable;TT;>;>;

  public abstract boolean isExpired();
    descriptor: ()Z
    flags: (0x0401) ACC_PUBLIC, ACC_ABSTRACT

  public abstract boolean isCanceled();
    descriptor: ()Z
    flags: (0x0401) ACC_PUBLIC, ACC_ABSTRACT

  public static boolean isReadyWithin$(org.scalatest.concurrent.Futures$FutureConcept, org.scalatest.time.Span, org.scalatest.concurrent.AbstractPatienceConfiguration$PatienceConfig, org.scalactic.source.Position);
    descriptor: (Lorg/scalatest/concurrent/Futures$FutureConcept;Lorg/scalatest/time/Span;Lorg/scalatest/concurrent/AbstractPatienceConfiguration$PatienceConfig;Lorg/scalactic/source/Position;)Z
    flags: (0x1009) ACC_PUBLIC, ACC_STATIC, ACC_SYNTHETIC
    Code:
      stack=4, locals=4, args_size=4
         0: aload_0
         1: aload_1
         2: aload_2
         3: aload_3
         4: invokespecial #38                 // InterfaceMethod isReadyWithin:(Lorg/scalatest/time/Span;Lorg/scalatest/concurrent/AbstractPatienceConfiguration$PatienceConfig;Lorg/scalactic/source/Position;)Z
         7: ireturn
      LineNumberTable:
        line 306: 0
      LocalVariableTable:
        Start  Length  Slot  Name   Signature
            0       8     0 $this   Lorg/scalatest/concurrent/Futures$FutureConcept;
            0       8     1 timeout   Lorg/scalatest/time/Span;
            0       8     2 config   Lorg/scalatest/concurrent/AbstractPatienceConfiguration$PatienceConfig;
            0       8     3   pos   Lorg/scalactic/source/Position;
    MethodParameters:
      Name                           Flags
      $this                          final synthetic
      timeout                        final
      config                         final
      pos                            final

  public default boolean isReadyWithin(org.scalatest.time.Span, org.scalatest.concurrent.AbstractPatienceConfiguration$PatienceConfig, org.scalactic.source.Position);
    descriptor: (Lorg/scalatest/time/Span;Lorg/scalatest/concurrent/AbstractPatienceConfiguration$PatienceConfig;Lorg/scalactic/source/Position;)Z
    flags: (0x0001) ACC_PUBLIC
    Code:
      stack=7, locals=7, args_size=4
         0: aload_0
         1: aload_3
         2: new           #8                  // class org/scalatest/concurrent/AbstractPatienceConfiguration$PatienceConfig
         5: dup
         6: aload_0
         7: invokeinterface #48,  1           // InterfaceMethod org$scalatest$concurrent$Futures$FutureConcept$$$outer:()Lorg/scalatest/concurrent/Futures;
        12: aload_1
        13: aload_2
        14: invokevirtual #52                 // Method org/scalatest/concurrent/AbstractPatienceConfiguration$PatienceConfig.interval:()Lorg/scalatest/time/Span;
        17: invokespecial #56                 // Method org/scalatest/concurrent/AbstractPatienceConfiguration$PatienceConfig."<init>":(Lorg/scalatest/concurrent/AbstractPatienceConfiguration;Lorg/scalatest/time/Span;Lorg/scalatest/time/Span;)V
        20: invokeinterface #60,  3           // InterfaceMethod futureValueImpl:(Lorg/scalactic/source/Position;Lorg/scalatest/concurrent/AbstractPatienceConfiguration$PatienceConfig;)Ljava/lang/Object;
        25: pop
        26: iconst_1
        27: goto          61
        30: astore        5
        32: aload         5
        34: astore        6
        36: aload         6
        38: instanceof    #62                 // class org/scalatest/exceptions/TimeoutField
        41: ifeq          50
        44: iconst_0
        45: istore        4
        47: goto          56
        50: goto          53
        53: aload         5
        55: athrow
        56: iload         4
        58: goto          61
        61: ireturn
      Exception table:
         from    to  target type
             0    27    30   Class java/lang/Throwable
      StackMapTable: number_of_entries = 5
        frame_type = 94 /* same_locals_1_stack_item */
          stack = [ class java/lang/Throwable ]
        frame_type = 254 /* append */
          offset_delta = 19
          locals = [ top, class java/lang/Throwable, class java/lang/Throwable ]
        frame_type = 2 /* same */
        frame_type = 255 /* full_frame */
          offset_delta = 2
          locals = [ class org/scalatest/concurrent/Futures$FutureConcept, class org/scalatest/time/Span, class org/scalatest/concurrent/AbstractPatienceConfiguration$PatienceConfig, class org/scalactic/source/Position, int, class java/lang/Throwable, class java/lang/Throwable ]
          stack = []
        frame_type = 255 /* full_frame */
          offset_delta = 4
          locals = [ class org/scalatest/concurrent/Futures$FutureConcept, class org/scalatest/time/Span, class org/scalatest/concurrent/AbstractPatienceConfiguration$PatienceConfig, class org/scalactic/source/Position ]
          stack = [ int ]
      LineNumberTable:
        line 308: 0
        line 309: 26
        line 312: 32
        line 312: 36
        line 307: 53
      LocalVariableTable:
        Start  Length  Slot  Name   Signature
            0      62     0  this   Lorg/scalatest/concurrent/Futures$FutureConcept;
            0      62     1 timeout   Lorg/scalatest/time/Span;
            0      62     2 config   Lorg/scalatest/concurrent/AbstractPatienceConfiguration$PatienceConfig;
            0      62     3   pos   Lorg/scalactic/source/Position;
    MethodParameters:
      Name                           Flags
      timeout                        final
      config                         final
      pos                            final

  public static java.lang.Object futureValue$(org.scalatest.concurrent.Futures$FutureConcept, org.scalatest.concurrent.PatienceConfiguration$Timeout, org.scalatest.concurrent.PatienceConfiguration$Interval, org.scalactic.source.Position);
    descriptor: (Lorg/scalatest/concurrent/Futures$FutureConcept;Lorg/scalatest/concurrent/PatienceConfiguration$Timeout;Lorg/scalatest/concurrent/PatienceConfiguration$Interval;Lorg/scalactic/source/Position;)Ljava/lang/Object;
    flags: (0x1009) ACC_PUBLIC, ACC_STATIC, ACC_SYNTHETIC
    Code:
      stack=4, locals=4, args_size=4
         0: aload_0
         1: aload_1
         2: aload_2
         3: aload_3
         4: invokespecial #73                 // InterfaceMethod futureValue:(Lorg/scalatest/concurrent/PatienceConfiguration$Timeout;Lorg/scalatest/concurrent/PatienceConfiguration$Interval;Lorg/scalactic/source/Position;)Ljava/lang/Object;
         7: areturn
      LineNumberTable:
        line 352: 0
      LocalVariableTable:
        Start  Length  Slot  Name   Signature
            0       8     0 $this   Lorg/scalatest/concurrent/Futures$FutureConcept;
            0       8     1 timeout   Lorg/scalatest/concurrent/PatienceConfiguration$Timeout;
            0       8     2 interval   Lorg/scalatest/concurrent/PatienceConfiguration$Interval;
            0       8     3   pos   Lorg/scalactic/source/Position;
    MethodParameters:
      Name                           Flags
      $this                          final synthetic
      timeout                        final
      interval                       final
      pos                            final

  public default T futureValue(org.scalatest.concurrent.PatienceConfiguration$Timeout, org.scalatest.concurrent.PatienceConfiguration$Interval, org.scalactic.source.Position);
    descriptor: (Lorg/scalatest/concurrent/PatienceConfiguration$Timeout;Lorg/scalatest/concurrent/PatienceConfiguration$Interval;Lorg/scalactic/source/Position;)Ljava/lang/Object;
    flags: (0x0001) ACC_PUBLIC
    Code:
      stack=7, locals=4, args_size=4
         0: aload_0
         1: aload_3
         2: new           #8                  // class org/scalatest/concurrent/AbstractPatienceConfiguration$PatienceConfig
         5: dup
         6: aload_0
         7: invokeinterface #48,  1           // InterfaceMethod org$scalatest$concurrent$Futures$FutureConcept$$$outer:()Lorg/scalatest/concurrent/Futures;
        12: aload_1
        13: invokevirtual #79                 // Method org/scalatest/concurrent/PatienceConfiguration$Timeout.value:()Lorg/scalatest/time/Span;
        16: aload_2
        17: invokevirtual #80                 // Method org/scalatest/concurrent/PatienceConfiguration$Interval.value:()Lorg/scalatest/time/Span;
        20: invokespecial #56                 // Method org/scalatest/concurrent/AbstractPatienceConfiguration$PatienceConfig."<init>":(Lorg/scalatest/concurrent/AbstractPatienceConfiguration;Lorg/scalatest/time/Span;Lorg/scalatest/time/Span;)V
        23: invokeinterface #60,  3           // InterfaceMethod futureValueImpl:(Lorg/scalactic/source/Position;Lorg/scalatest/concurrent/AbstractPatienceConfiguration$PatienceConfig;)Ljava/lang/Object;
        28: areturn
      LineNumberTable:
        line 353: 0
      LocalVariableTable:
        Start  Length  Slot  Name   Signature
            0      29     0  this   Lorg/scalatest/concurrent/Futures$FutureConcept;
            0      29     1 timeout   Lorg/scalatest/concurrent/PatienceConfiguration$Timeout;
            0      29     2 interval   Lorg/scalatest/concurrent/PatienceConfiguration$Interval;
            0      29     3   pos   Lorg/scalactic/source/Position;
    Signature: #76                          // (Lorg/scalatest/concurrent/PatienceConfiguration$Timeout;Lorg/scalatest/concurrent/PatienceConfiguration$Interval;Lorg/scalactic/source/Position;)TT;
    MethodParameters:
      Name                           Flags
      timeout                        final
      interval                       final
      pos                            final

  public static java.lang.Object futureValue$(org.scalatest.concurrent.Futures$FutureConcept, org.scalatest.concurrent.PatienceConfiguration$Timeout, org.scalatest.concurrent.AbstractPatienceConfiguration$PatienceConfig, org.scalactic.source.Position);
    descriptor: (Lorg/scalatest/concurrent/Futures$FutureConcept;Lorg/scalatest/concurrent/PatienceConfiguration$Timeout;Lorg/scalatest/concurrent/AbstractPatienceConfiguration$PatienceConfig;Lorg/scalactic/source/Position;)Ljava/lang/Object;
    flags: (0x1009) ACC_PUBLIC, ACC_STATIC, ACC_SYNTHETIC
    Code:
      stack=4, locals=4, args_size=4
         0: aload_0
         1: aload_1
         2: aload_2
         3: aload_3
         4: invokespecial #84                 // InterfaceMethod futureValue:(Lorg/scalatest/concurrent/PatienceConfiguration$Timeout;Lorg/scalatest/concurrent/AbstractPatienceConfiguration$PatienceConfig;Lorg/scalactic/source/Position;)Ljava/lang/Object;
         7: areturn
      LineNumberTable:
        line 393: 0
      LocalVariableTable:
        Start  Length  Slot  Name   Signature
            0       8     0 $this   Lorg/scalatest/concurrent/Futures$FutureConcept;
            0       8     1 timeout   Lorg/scalatest/concurrent/PatienceConfiguration$Timeout;
            0       8     2 config   Lorg/scalatest/concurrent/AbstractPatienceConfiguration$PatienceConfig;
            0       8     3   pos   Lorg/scalactic/source/Position;
    MethodParameters:
      Name                           Flags
      $this                          final synthetic
      timeout                        final
      config                         final
      pos                            final

  public default T futureValue(org.scalatest.concurrent.PatienceConfiguration$Timeout, org.scalatest.concurrent.AbstractPatienceConfiguration$PatienceConfig, org.scalactic.source.Position);
    descriptor: (Lorg/scalatest/concurrent/PatienceConfiguration$Timeout;Lorg/scalatest/concurrent/AbstractPatienceConfiguration$PatienceConfig;Lorg/scalactic/source/Position;)Ljava/lang/Object;
    flags: (0x0001) ACC_PUBLIC
    Code:
      stack=7, locals=4, args_size=4
         0: aload_0
         1: aload_3
         2: new           #8                  // class org/scalatest/concurrent/AbstractPatienceConfiguration$PatienceConfig
         5: dup
         6: aload_0
         7: invokeinterface #48,  1           // InterfaceMethod org$scalatest$concurrent$Futures$FutureConcept$$$outer:()Lorg/scalatest/concurrent/Futures;
        12: aload_1
        13: invokevirtual #79                 // Method org/scalatest/concurrent/PatienceConfiguration$Timeout.value:()Lorg/scalatest/time/Span;
        16: aload_2
        17: invokevirtual #52                 // Method org/scalatest/concurrent/AbstractPatienceConfiguration$PatienceConfig.interval:()Lorg/scalatest/time/Span;
        20: invokespecial #56                 // Method org/scalatest/concurrent/AbstractPatienceConfiguration$PatienceConfig."<init>":(Lorg/scalatest/concurrent/AbstractPatienceConfiguration;Lorg/scalatest/time/Span;Lorg/scalatest/time/Span;)V
        23: invokeinterface #60,  3           // InterfaceMethod futureValueImpl:(Lorg/scalactic/source/Position;Lorg/scalatest/concurrent/AbstractPatienceConfiguration$PatienceConfig;)Ljava/lang/Object;
        28: areturn
      LineNumberTable:
        line 394: 0
      LocalVariableTable:
        Start  Length  Slot  Name   Signature
            0      29     0  this   Lorg/scalatest/concurrent/Futures$FutureConcept;
            0      29     1 timeout   Lorg/scalatest/concurrent/PatienceConfiguration$Timeout;
            0      29     2 config   Lorg/scalatest/concurrent/AbstractPatienceConfiguration$PatienceConfig;
            0      29     3   pos   Lorg/scalactic/source/Position;
    Signature: #85                          // (Lorg/scalatest/concurrent/PatienceConfiguration$Timeout;Lorg/scalatest/concurrent/AbstractPatienceConfiguration$PatienceConfig;Lorg/scalactic/source/Position;)TT;
    MethodParameters:
      Name                           Flags
      timeout                        final
      config                         final
      pos                            final

  public static java.lang.Object futureValue$(org.scalatest.concurrent.Futures$FutureConcept, org.scalatest.concurrent.PatienceConfiguration$Interval, org.scalatest.concurrent.AbstractPatienceConfiguration$PatienceConfig, org.scalactic.source.Position);
    descriptor: (Lorg/scalatest/concurrent/Futures$FutureConcept;Lorg/scalatest/concurrent/PatienceConfiguration$Interval;Lorg/scalatest/concurrent/AbstractPatienceConfiguration$PatienceConfig;Lorg/scalactic/source/Position;)Ljava/lang/Object;
    flags: (0x1009) ACC_PUBLIC, ACC_STATIC, ACC_SYNTHETIC
    Code:
      stack=4, locals=4, args_size=4
         0: aload_0
         1: aload_1
         2: aload_2
         3: aload_3
         4: invokespecial #89                 // InterfaceMethod futureValue:(Lorg/scalatest/concurrent/PatienceConfiguration$Interval;Lorg/scalatest/concurrent/AbstractPatienceConfiguration$PatienceConfig;Lorg/scalactic/source/Position;)Ljava/lang/Object;
         7: areturn
      LineNumberTable:
        line 434: 0
      LocalVariableTable:
        Start  Length  Slot  Name   Signature
            0       8     0 $this   Lorg/scalatest/concurrent/Futures$FutureConcept;
            0       8     1 interval   Lorg/scalatest/concurrent/PatienceConfiguration$Interval;
            0       8     2 config   Lorg/scalatest/concurrent/AbstractPatienceConfiguration$PatienceConfig;
            0       8     3   pos   Lorg/scalactic/source/Position;
    MethodParameters:
      Name                           Flags
      $this                          final synthetic
      interval                       final
      config                         final
      pos                            final

  public default T futureValue(org.scalatest.concurrent.PatienceConfiguration$Interval, org.scalatest.concurrent.AbstractPatienceConfiguration$PatienceConfig, org.scalactic.source.Position);
    descriptor: (Lorg/scalatest/concurrent/PatienceConfiguration$Interval;Lorg/scalatest/concurrent/AbstractPatienceConfiguration$PatienceConfig;Lorg/scalactic/source/Position;)Ljava/lang/Object;
    flags: (0x0001) ACC_PUBLIC
    Code:
      stack=7, locals=4, args_size=4
         0: aload_0
         1: aload_3
         2: new           #8                  // class org/scalatest/concurrent/AbstractPatienceConfiguration$PatienceConfig
         5: dup
         6: aload_0
         7: invokeinterface #48,  1           // InterfaceMethod org$scalatest$concurrent$Futures$FutureConcept$$$outer:()Lorg/scalatest/concurrent/Futures;
        12: aload_2
        13: invokevirtual #92                 // Method org/scalatest/concurrent/AbstractPatienceConfiguration$PatienceConfig.timeout:()Lorg/scalatest/time/Span;
        16: aload_1
        17: invokevirtual #80                 // Method org/scalatest/concurrent/PatienceConfiguration$Interval.value:()Lorg/scalatest/time/Span;
        20: invokespecial #56                 // Method org/scalatest/concurrent/AbstractPatienceConfiguration$PatienceConfig."<init>":(Lorg/scalatest/concurrent/AbstractPatienceConfiguration;Lorg/scalatest/time/Span;Lorg/scalatest/time/Span;)V
        23: invokeinterface #60,  3           // InterfaceMethod futureValueImpl:(Lorg/scalactic/source/Position;Lorg/scalatest/concurrent/AbstractPatienceConfiguration$PatienceConfig;)Ljava/lang/Object;
        28: areturn
      LineNumberTable:
        line 435: 0
      LocalVariableTable:
        Start  Length  Slot  Name   Signature
            0      29     0  this   Lorg/scalatest/concurrent/Futures$FutureConcept;
            0      29     1 interval   Lorg/scalatest/concurrent/PatienceConfiguration$Interval;
            0      29     2 config   Lorg/scalatest/concurrent/AbstractPatienceConfiguration$PatienceConfig;
            0      29     3   pos   Lorg/scalactic/source/Position;
    Signature: #90                          // (Lorg/scalatest/concurrent/PatienceConfiguration$Interval;Lorg/scalatest/concurrent/AbstractPatienceConfiguration$PatienceConfig;Lorg/scalactic/source/Position;)TT;
    MethodParameters:
      Name                           Flags
      interval                       final
      config                         final
      pos                            final

  public static java.lang.Object futureValue$(org.scalatest.concurrent.Futures$FutureConcept, org.scalatest.concurrent.AbstractPatienceConfiguration$PatienceConfig, org.scalactic.source.Position);
    descriptor: (Lorg/scalatest/concurrent/Futures$FutureConcept;Lorg/scalatest/concurrent/AbstractPatienceConfiguration$PatienceConfig;Lorg/scalactic/source/Position;)Ljava/lang/Object;
    flags: (0x1009) ACC_PUBLIC, ACC_STATIC, ACC_SYNTHETIC
    Code:
      stack=3, locals=3, args_size=3
         0: aload_0
         1: aload_1
         2: aload_2
         3: invokespecial #96                 // InterfaceMethod futureValue:(Lorg/scalatest/concurrent/AbstractPatienceConfiguration$PatienceConfig;Lorg/scalactic/source/Position;)Ljava/lang/Object;
         6: areturn
      LineNumberTable:
        line 475: 0
      LocalVariableTable:
        Start  Length  Slot  Name   Signature
            0       7     0 $this   Lorg/scalatest/concurrent/Futures$FutureConcept;
            0       7     1 config   Lorg/scalatest/concurrent/AbstractPatienceConfiguration$PatienceConfig;
            0       7     2   pos   Lorg/scalactic/source/Position;
    MethodParameters:
      Name                           Flags
      $this                          final synthetic
      config                         final
      pos                            final

  public default T futureValue(org.scalatest.concurrent.AbstractPatienceConfiguration$PatienceConfig, org.scalactic.source.Position);
    descriptor: (Lorg/scalatest/concurrent/AbstractPatienceConfiguration$PatienceConfig;Lorg/scalactic/source/Position;)Ljava/lang/Object;
    flags: (0x0001) ACC_PUBLIC
    Code:
      stack=3, locals=3, args_size=3
         0: aload_0
         1: aload_2
         2: aload_1
         3: invokeinterface #60,  3           // InterfaceMethod futureValueImpl:(Lorg/scalactic/source/Position;Lorg/scalatest/concurrent/AbstractPatienceConfiguration$PatienceConfig;)Ljava/lang/Object;
         8: areturn
      LineNumberTable:
        line 476: 0
      LocalVariableTable:
        Start  Length  Slot  Name   Signature
            0       9     0  this   Lorg/scalatest/concurrent/Futures$FutureConcept;
            0       9     1 config   Lorg/scalatest/concurrent/AbstractPatienceConfiguration$PatienceConfig;
            0       9     2   pos   Lorg/scalactic/source/Position;
    Signature: #97                          // (Lorg/scalatest/concurrent/AbstractPatienceConfiguration$PatienceConfig;Lorg/scalactic/source/Position;)TT;
    MethodParameters:
      Name                           Flags
      config                         final
      pos                            final

  public abstract T futureValueImpl(org.scalactic.source.Position, org.scalatest.concurrent.AbstractPatienceConfiguration$PatienceConfig);
    descriptor: (Lorg/scalactic/source/Position;Lorg/scalatest/concurrent/AbstractPatienceConfiguration$PatienceConfig;)Ljava/lang/Object;
    flags: (0x0401) ACC_PUBLIC, ACC_ABSTRACT
    Signature: #98                          // (Lorg/scalactic/source/Position;Lorg/scalatest/concurrent/AbstractPatienceConfiguration$PatienceConfig;)TT;
    MethodParameters:
      Name                           Flags
      pos                            final
      config                         final

  public abstract org.scalatest.concurrent.Futures org$scalatest$concurrent$Futures$FutureConcept$$$outer();
    descriptor: ()Lorg/scalatest/concurrent/Futures;
    flags: (0x1401) ACC_PUBLIC, ACC_ABSTRACT, ACC_SYNTHETIC

  public static void $init$(org.scalatest.concurrent.Futures$FutureConcept);
    descriptor: (Lorg/scalatest/concurrent/Futures$FutureConcept;)V
    flags: (0x0009) ACC_PUBLIC, ACC_STATIC
    Code:
      stack=0, locals=1, args_size=1
         0: return
      LineNumberTable:
        line 259: 0
      LocalVariableTable:
        Start  Length  Slot  Name   Signature
            0       1     0 $this   Lorg/scalatest/concurrent/Futures$FutureConcept;
    MethodParameters:
      Name                           Flags
      $this                          final synthetic
}
InnerClasses:
  public final #11= #8 of #10;            // PatienceConfig=class org/scalatest/concurrent/AbstractPatienceConfiguration$PatienceConfig of class org/scalatest/concurrent/AbstractPatienceConfiguration
  public #14= #2 of #13;                  // FutureConcept=class org/scalatest/concurrent/Futures$FutureConcept of class org/scalatest/concurrent/Futures
  public static final #19= #16 of #18;    // Interval=class org/scalatest/concurrent/PatienceConfiguration$Interval of class org/scalatest/concurrent/PatienceConfiguration
  public static final #22= #21 of #18;    // Timeout=class org/scalatest/concurrent/PatienceConfiguration$Timeout of class org/scalatest/concurrent/PatienceConfiguration
Signature: #3                           // <T:Ljava/lang/Object;>Ljava/lang/Object;
SourceFile: "Futures.scala"
  ScalaInlineInfo: length = 0x54 (unknown attribute)
   01 00 00 10 00 63 00 64 01 00 17 00 18 00 00 46
   00 5E 00 00 46 00 57 01 00 46 00 52 01 00 46 00
   47 01 00 44 00 5D 01 00 44 00 56 01 00 44 00 51
   01 00 44 00 45 01 00 39 00 3A 00 00 1C 00 1B 00
   00 1A 00 1B 00 00 23 00 24 01 00 1D 00 1E 01 00
   2D 00 2E 00
  Scala: length = 0x0 (unknown attribute)

