Classfile /Users/mw/Projects/slang-braindump/.jar/jar11/assemble/slang-braindump/assemble/content/org/scalatest/concurrent/PimpedThreadGroup$.class
  Last modified May 29, 2022; size 1420 bytes
  SHA-256 checksum 92952de3c2259c602a57d2530381481609b6c27adfa74c3dbe721d709624d133
  Compiled from "PimpedThreadGroup.scala"
public final class org.scalatest.concurrent.PimpedThreadGroup$
  minor version: 0
  major version: 52
  flags: (0x0031) ACC_PUBLIC, ACC_FINAL, ACC_SUPER
  this_class: #2                          // org/scalatest/concurrent/PimpedThreadGroup$
  super_class: #4                         // java/lang/Object
  interfaces: 0, fields: 1, methods: 5, attributes: 3
Constant pool:
   #1 = Utf8               org/scalatest/concurrent/PimpedThreadGroup$
   #2 = Class              #1             // org/scalatest/concurrent/PimpedThreadGroup$
   #3 = Utf8               java/lang/Object
   #4 = Class              #3             // java/lang/Object
   #5 = Utf8               PimpedThreadGroup.scala
   #6 = Utf8               MODULE$
   #7 = Utf8               Lorg/scalatest/concurrent/PimpedThreadGroup$;
   #8 = Utf8               <clinit>
   #9 = Utf8               ()V
  #10 = Utf8               <init>
  #11 = NameAndType        #10:#9         // "<init>":()V
  #12 = Methodref          #2.#11         // org/scalatest/concurrent/PimpedThreadGroup$."<init>":()V
  #13 = NameAndType        #6:#7          // MODULE$:Lorg/scalatest/concurrent/PimpedThreadGroup$;
  #14 = Fieldref           #2.#13         // org/scalatest/concurrent/PimpedThreadGroup$.MODULE$:Lorg/scalatest/concurrent/PimpedThreadGroup$;
  #15 = Utf8               ThreadGroupToList
  #16 = Utf8               (Ljava/lang/ThreadGroup;)Lscala/collection/immutable/List;
  #17 = Utf8               (Ljava/lang/ThreadGroup;)Lscala/collection/immutable/List<Ljava/lang/Thread;>;
  #18 = Utf8               tg
  #19 = Utf8               org/scalatest/concurrent/PimpedThreadGroup
  #20 = Class              #19            // org/scalatest/concurrent/PimpedThreadGroup
  #21 = Utf8               (Ljava/lang/ThreadGroup;)V
  #22 = NameAndType        #10:#21        // "<init>":(Ljava/lang/ThreadGroup;)V
  #23 = Methodref          #20.#22        // org/scalatest/concurrent/PimpedThreadGroup."<init>":(Ljava/lang/ThreadGroup;)V
  #24 = Utf8               getThreads
  #25 = Utf8               ()Lscala/collection/immutable/List;
  #26 = NameAndType        #24:#25        // getThreads:()Lscala/collection/immutable/List;
  #27 = Methodref          #20.#26        // org/scalatest/concurrent/PimpedThreadGroup.getThreads:()Lscala/collection/immutable/List;
  #28 = Utf8               this
  #29 = Utf8               Ljava/lang/ThreadGroup;
  #30 = Utf8               threadGroupToPimpedThreadGroup
  #31 = Utf8               (Ljava/lang/ThreadGroup;)Lorg/scalatest/concurrent/PimpedThreadGroup;
  #32 = Utf8               ()Lscala/collection/immutable/List<Ljava/lang/Thread;>;
  #33 = Utf8               java/lang/Thread
  #34 = Class              #33            // java/lang/Thread
  #35 = Utf8               currentThread
  #36 = Utf8               ()Ljava/lang/Thread;
  #37 = NameAndType        #35:#36        // currentThread:()Ljava/lang/Thread;
  #38 = Methodref          #34.#37        // java/lang/Thread.currentThread:()Ljava/lang/Thread;
  #39 = Utf8               getThreadGroup
  #40 = Utf8               ()Ljava/lang/ThreadGroup;
  #41 = NameAndType        #39:#40        // getThreadGroup:()Ljava/lang/ThreadGroup;
  #42 = Methodref          #34.#41        // java/lang/Thread.getThreadGroup:()Ljava/lang/ThreadGroup;
  #43 = NameAndType        #30:#31        // threadGroupToPimpedThreadGroup:(Ljava/lang/ThreadGroup;)Lorg/scalatest/concurrent/PimpedThreadGroup;
  #44 = Methodref          #2.#43         // org/scalatest/concurrent/PimpedThreadGroup$.threadGroupToPimpedThreadGroup:(Ljava/lang/ThreadGroup;)Lorg/scalatest/concurrent/PimpedThreadGroup;
  #45 = Methodref          #4.#11         // java/lang/Object."<init>":()V
  #46 = Utf8               Code
  #47 = Utf8               LineNumberTable
  #48 = Utf8               LocalVariableTable
  #49 = Utf8               Signature
  #50 = Utf8               MethodParameters
  #51 = Utf8               SourceFile
  #52 = Utf8               ScalaInlineInfo
  #53 = Utf8               Scala
{
  public static final org.scalatest.concurrent.PimpedThreadGroup$ MODULE$;
    descriptor: Lorg/scalatest/concurrent/PimpedThreadGroup$;
    flags: (0x0019) ACC_PUBLIC, ACC_STATIC, ACC_FINAL

  public static {};
    descriptor: ()V
    flags: (0x0009) ACC_PUBLIC, ACC_STATIC
    Code:
      stack=2, locals=0, args_size=0
         0: new           #2                  // class org/scalatest/concurrent/PimpedThreadGroup$
         3: dup
         4: invokespecial #12                 // Method "<init>":()V
         7: putstatic     #14                 // Field MODULE$:Lorg/scalatest/concurrent/PimpedThreadGroup$;
        10: return
      LineNumberTable:
        line 27: 0

  public scala.collection.immutable.List<java.lang.Thread> ThreadGroupToList(java.lang.ThreadGroup);
    descriptor: (Ljava/lang/ThreadGroup;)Lscala/collection/immutable/List;
    flags: (0x0001) ACC_PUBLIC
    Code:
      stack=3, locals=2, args_size=2
         0: new           #20                 // class org/scalatest/concurrent/PimpedThreadGroup
         3: dup
         4: aload_1
         5: invokespecial #23                 // Method org/scalatest/concurrent/PimpedThreadGroup."<init>":(Ljava/lang/ThreadGroup;)V
         8: invokevirtual #27                 // Method org/scalatest/concurrent/PimpedThreadGroup.getThreads:()Lscala/collection/immutable/List;
        11: areturn
      LineNumberTable:
        line 38: 0
      LocalVariableTable:
        Start  Length  Slot  Name   Signature
            0      12     0  this   Lorg/scalatest/concurrent/PimpedThreadGroup$;
            0      12     1    tg   Ljava/lang/ThreadGroup;
    Signature: #17                          // (Ljava/lang/ThreadGroup;)Lscala/collection/immutable/List<Ljava/lang/Thread;>;
    MethodParameters:
      Name                           Flags
      tg                             final

  public org.scalatest.concurrent.PimpedThreadGroup threadGroupToPimpedThreadGroup(java.lang.ThreadGroup);
    descriptor: (Ljava/lang/ThreadGroup;)Lorg/scalatest/concurrent/PimpedThreadGroup;
    flags: (0x0001) ACC_PUBLIC
    Code:
      stack=3, locals=2, args_size=2
         0: new           #20                 // class org/scalatest/concurrent/PimpedThreadGroup
         3: dup
         4: aload_1
         5: invokespecial #23                 // Method org/scalatest/concurrent/PimpedThreadGroup."<init>":(Ljava/lang/ThreadGroup;)V
         8: areturn
      LineNumberTable:
        line 44: 0
      LocalVariableTable:
        Start  Length  Slot  Name   Signature
            0       9     0  this   Lorg/scalatest/concurrent/PimpedThreadGroup$;
            0       9     1    tg   Ljava/lang/ThreadGroup;
    MethodParameters:
      Name                           Flags
      tg                             final

  public scala.collection.immutable.List<java.lang.Thread> getThreads();
    descriptor: ()Lscala/collection/immutable/List;
    flags: (0x0001) ACC_PUBLIC
    Code:
      stack=2, locals=1, args_size=1
         0: aload_0
         1: invokestatic  #38                 // Method java/lang/Thread.currentThread:()Ljava/lang/Thread;
         4: invokevirtual #42                 // Method java/lang/Thread.getThreadGroup:()Ljava/lang/ThreadGroup;
         7: invokevirtual #44                 // Method threadGroupToPimpedThreadGroup:(Ljava/lang/ThreadGroup;)Lorg/scalatest/concurrent/PimpedThreadGroup;
        10: invokevirtual #27                 // Method org/scalatest/concurrent/PimpedThreadGroup.getThreads:()Lscala/collection/immutable/List;
        13: areturn
      LineNumberTable:
        line 49: 0
      LocalVariableTable:
        Start  Length  Slot  Name   Signature
            0      14     0  this   Lorg/scalatest/concurrent/PimpedThreadGroup$;
    Signature: #32                          // ()Lscala/collection/immutable/List<Ljava/lang/Thread;>;

  private org.scalatest.concurrent.PimpedThreadGroup$();
    descriptor: ()V
    flags: (0x0002) ACC_PRIVATE
    Code:
      stack=1, locals=1, args_size=1
         0: aload_0
         1: invokespecial #45                 // Method java/lang/Object."<init>":()V
         4: return
      LineNumberTable:
        line 55: 0
        line 27: 4
      LocalVariableTable:
        Start  Length  Slot  Name   Signature
            0       5     0  this   Lorg/scalatest/concurrent/PimpedThreadGroup$;
}
SourceFile: "PimpedThreadGroup.scala"
  ScalaInlineInfo: length = 0x18 (unknown attribute)
   01 01 00 04 00 0A 00 09 01 00 0F 00 10 01 00 18
   00 19 01 00 1E 00 1F 01
  Scala: length = 0x0 (unknown attribute)

