Classfile /Users/mw/Projects/slang-braindump/.jar/jar11/assemble/slang-braindump/assemble/content/org/scalatest/concurrent/ScalaFutures$$anon$1.class
  Last modified May 29, 2022; size 11968 bytes
  SHA-256 checksum f6e4e19c419dc5a4fdeb2701b0ea7eb4c66bfd54921118bceadf0c94d467d6c0
  Compiled from "ScalaFutures.scala"
public final class org.scalatest.concurrent.ScalaFutures$$anon$1 extends java.lang.Object implements org.scalatest.concurrent.Futures$FutureConcept<T>
  minor version: 0
  major version: 52
  flags: (0x0031) ACC_PUBLIC, ACC_FINAL, ACC_SUPER
  this_class: #2                          // org/scalatest/concurrent/ScalaFutures$$anon$1
  super_class: #5                         // java/lang/Object
  interfaces: 1, fields: 2, methods: 17, attributes: 7
Constant pool:
    #1 = Utf8               org/scalatest/concurrent/ScalaFutures$$anon$1
    #2 = Class              #1            // org/scalatest/concurrent/ScalaFutures$$anon$1
    #3 = Utf8               Ljava/lang/Object;Lorg/scalatest/concurrent/Futures$FutureConcept<TT;>;
    #4 = Utf8               java/lang/Object
    #5 = Class              #4            // java/lang/Object
    #6 = Utf8               org/scalatest/concurrent/Futures$FutureConcept
    #7 = Class              #6            // org/scalatest/concurrent/Futures$FutureConcept
    #8 = Utf8               ScalaFutures.scala
    #9 = Utf8               org/scalatest/concurrent/ScalaFutures
   #10 = Class              #9            // org/scalatest/concurrent/ScalaFutures
   #11 = Utf8               convertScalaFuture
   #12 = Utf8               (Lscala/concurrent/Future;)Lorg/scalatest/concurrent/Futures$FutureConcept;
   #13 = NameAndType        #11:#12       // convertScalaFuture:(Lscala/concurrent/Future;)Lorg/scalatest/concurrent/Futures$FutureConcept;
   #14 = Utf8               java/lang/invoke/MethodHandles$Lookup
   #15 = Class              #14           // java/lang/invoke/MethodHandles$Lookup
   #16 = Utf8               java/lang/invoke/MethodHandles
   #17 = Class              #16           // java/lang/invoke/MethodHandles
   #18 = Utf8               Lookup
   #19 = Utf8               org/scalatest/concurrent/AbstractPatienceConfiguration$PatienceConfig
   #20 = Class              #19           // org/scalatest/concurrent/AbstractPatienceConfiguration$PatienceConfig
   #21 = Utf8               org/scalatest/concurrent/AbstractPatienceConfiguration
   #22 = Class              #21           // org/scalatest/concurrent/AbstractPatienceConfiguration
   #23 = Utf8               PatienceConfig
   #24 = Utf8               org/scalatest/concurrent/Futures
   #25 = Class              #24           // org/scalatest/concurrent/Futures
   #26 = Utf8               FutureConcept
   #27 = Utf8               org/scalatest/concurrent/PatienceConfiguration$Interval
   #28 = Class              #27           // org/scalatest/concurrent/PatienceConfiguration$Interval
   #29 = Utf8               org/scalatest/concurrent/PatienceConfiguration
   #30 = Class              #29           // org/scalatest/concurrent/PatienceConfiguration
   #31 = Utf8               Interval
   #32 = Utf8               org/scalatest/concurrent/PatienceConfiguration$Timeout
   #33 = Class              #32           // org/scalatest/concurrent/PatienceConfiguration$Timeout
   #34 = Utf8               Timeout
   #35 = Utf8               org/scalatest/concurrent/ScalaFutures$$anon$1$$anon$2
   #36 = Class              #35           // org/scalatest/concurrent/ScalaFutures$$anon$1$$anon$2
   #37 = Utf8               $outer
   #38 = Utf8               Lorg/scalatest/concurrent/ScalaFutures;
   #39 = Utf8               scalaFuture$1
   #40 = Utf8               Lscala/concurrent/Future;
   #41 = Utf8               isReadyWithin
   #42 = Utf8               (Lorg/scalatest/time/Span;Lorg/scalatest/concurrent/AbstractPatienceConfiguration$PatienceConfig;Lorg/scalactic/source/Position;)Z
   #43 = Utf8               timeout
   #44 = Utf8               config
   #45 = Utf8               pos
   #46 = Utf8               isReadyWithin$
   #47 = Utf8               (Lorg/scalatest/concurrent/Futures$FutureConcept;Lorg/scalatest/time/Span;Lorg/scalatest/concurrent/AbstractPatienceConfiguration$PatienceConfig;Lorg/scalactic/source/Position;)Z
   #48 = NameAndType        #46:#47       // isReadyWithin$:(Lorg/scalatest/concurrent/Futures$FutureConcept;Lorg/scalatest/time/Span;Lorg/scalatest/concurrent/AbstractPatienceConfiguration$PatienceConfig;Lorg/scalactic/source/Position;)Z
   #49 = InterfaceMethodref #7.#48        // org/scalatest/concurrent/Futures$FutureConcept.isReadyWithin$:(Lorg/scalatest/concurrent/Futures$FutureConcept;Lorg/scalatest/time/Span;Lorg/scalatest/concurrent/AbstractPatienceConfiguration$PatienceConfig;Lorg/scalactic/source/Position;)Z
   #50 = Utf8               this
   #51 = Utf8               Lorg/scalatest/concurrent/ScalaFutures$$anon$1;
   #52 = Utf8               Lorg/scalatest/time/Span;
   #53 = Utf8               Lorg/scalatest/concurrent/AbstractPatienceConfiguration$PatienceConfig;
   #54 = Utf8               Lorg/scalactic/source/Position;
   #55 = Utf8               futureValue
   #56 = Utf8               (Lorg/scalatest/concurrent/PatienceConfiguration$Timeout;Lorg/scalatest/concurrent/PatienceConfiguration$Interval;Lorg/scalactic/source/Position;)Ljava/lang/Object;
   #57 = Utf8               (Lorg/scalatest/concurrent/PatienceConfiguration$Timeout;Lorg/scalatest/concurrent/PatienceConfiguration$Interval;Lorg/scalactic/source/Position;)TT;
   #58 = Utf8               interval
   #59 = Utf8               futureValue$
   #60 = Utf8               (Lorg/scalatest/concurrent/Futures$FutureConcept;Lorg/scalatest/concurrent/PatienceConfiguration$Timeout;Lorg/scalatest/concurrent/PatienceConfiguration$Interval;Lorg/scalactic/source/Position;)Ljava/lang/Object;
   #61 = NameAndType        #59:#60       // futureValue$:(Lorg/scalatest/concurrent/Futures$FutureConcept;Lorg/scalatest/concurrent/PatienceConfiguration$Timeout;Lorg/scalatest/concurrent/PatienceConfiguration$Interval;Lorg/scalactic/source/Position;)Ljava/lang/Object;
   #62 = InterfaceMethodref #7.#61        // org/scalatest/concurrent/Futures$FutureConcept.futureValue$:(Lorg/scalatest/concurrent/Futures$FutureConcept;Lorg/scalatest/concurrent/PatienceConfiguration$Timeout;Lorg/scalatest/concurrent/PatienceConfiguration$Interval;Lorg/scalactic/source/Position;)Ljava/lang/Object;
   #63 = Utf8               Lorg/scalatest/concurrent/PatienceConfiguration$Timeout;
   #64 = Utf8               Lorg/scalatest/concurrent/PatienceConfiguration$Interval;
   #65 = Utf8               (Lorg/scalatest/concurrent/PatienceConfiguration$Timeout;Lorg/scalatest/concurrent/AbstractPatienceConfiguration$PatienceConfig;Lorg/scalactic/source/Position;)Ljava/lang/Object;
   #66 = Utf8               (Lorg/scalatest/concurrent/PatienceConfiguration$Timeout;Lorg/scalatest/concurrent/AbstractPatienceConfiguration$PatienceConfig;Lorg/scalactic/source/Position;)TT;
   #67 = Utf8               (Lorg/scalatest/concurrent/Futures$FutureConcept;Lorg/scalatest/concurrent/PatienceConfiguration$Timeout;Lorg/scalatest/concurrent/AbstractPatienceConfiguration$PatienceConfig;Lorg/scalactic/source/Position;)Ljava/lang/Object;
   #68 = NameAndType        #59:#67       // futureValue$:(Lorg/scalatest/concurrent/Futures$FutureConcept;Lorg/scalatest/concurrent/PatienceConfiguration$Timeout;Lorg/scalatest/concurrent/AbstractPatienceConfiguration$PatienceConfig;Lorg/scalactic/source/Position;)Ljava/lang/Object;
   #69 = InterfaceMethodref #7.#68        // org/scalatest/concurrent/Futures$FutureConcept.futureValue$:(Lorg/scalatest/concurrent/Futures$FutureConcept;Lorg/scalatest/concurrent/PatienceConfiguration$Timeout;Lorg/scalatest/concurrent/AbstractPatienceConfiguration$PatienceConfig;Lorg/scalactic/source/Position;)Ljava/lang/Object;
   #70 = Utf8               (Lorg/scalatest/concurrent/PatienceConfiguration$Interval;Lorg/scalatest/concurrent/AbstractPatienceConfiguration$PatienceConfig;Lorg/scalactic/source/Position;)Ljava/lang/Object;
   #71 = Utf8               (Lorg/scalatest/concurrent/PatienceConfiguration$Interval;Lorg/scalatest/concurrent/AbstractPatienceConfiguration$PatienceConfig;Lorg/scalactic/source/Position;)TT;
   #72 = Utf8               (Lorg/scalatest/concurrent/Futures$FutureConcept;Lorg/scalatest/concurrent/PatienceConfiguration$Interval;Lorg/scalatest/concurrent/AbstractPatienceConfiguration$PatienceConfig;Lorg/scalactic/source/Position;)Ljava/lang/Object;
   #73 = NameAndType        #59:#72       // futureValue$:(Lorg/scalatest/concurrent/Futures$FutureConcept;Lorg/scalatest/concurrent/PatienceConfiguration$Interval;Lorg/scalatest/concurrent/AbstractPatienceConfiguration$PatienceConfig;Lorg/scalactic/source/Position;)Ljava/lang/Object;
   #74 = InterfaceMethodref #7.#73        // org/scalatest/concurrent/Futures$FutureConcept.futureValue$:(Lorg/scalatest/concurrent/Futures$FutureConcept;Lorg/scalatest/concurrent/PatienceConfiguration$Interval;Lorg/scalatest/concurrent/AbstractPatienceConfiguration$PatienceConfig;Lorg/scalactic/source/Position;)Ljava/lang/Object;
   #75 = Utf8               (Lorg/scalatest/concurrent/AbstractPatienceConfiguration$PatienceConfig;Lorg/scalactic/source/Position;)Ljava/lang/Object;
   #76 = Utf8               (Lorg/scalatest/concurrent/AbstractPatienceConfiguration$PatienceConfig;Lorg/scalactic/source/Position;)TT;
   #77 = Utf8               (Lorg/scalatest/concurrent/Futures$FutureConcept;Lorg/scalatest/concurrent/AbstractPatienceConfiguration$PatienceConfig;Lorg/scalactic/source/Position;)Ljava/lang/Object;
   #78 = NameAndType        #59:#77       // futureValue$:(Lorg/scalatest/concurrent/Futures$FutureConcept;Lorg/scalatest/concurrent/AbstractPatienceConfiguration$PatienceConfig;Lorg/scalactic/source/Position;)Ljava/lang/Object;
   #79 = InterfaceMethodref #7.#78        // org/scalatest/concurrent/Futures$FutureConcept.futureValue$:(Lorg/scalatest/concurrent/Futures$FutureConcept;Lorg/scalatest/concurrent/AbstractPatienceConfiguration$PatienceConfig;Lorg/scalactic/source/Position;)Ljava/lang/Object;
   #80 = Utf8               eitherValue
   #81 = Utf8               ()Lscala/Option;
   #82 = Utf8               ()Lscala/Option<Lscala/util/Either<Ljava/lang/Throwable;TT;>;>;
   #83 = NameAndType        #39:#40       // scalaFuture$1:Lscala/concurrent/Future;
   #84 = Fieldref           #2.#83        // org/scalatest/concurrent/ScalaFutures$$anon$1.scalaFuture$1:Lscala/concurrent/Future;
   #85 = Utf8               scala/concurrent/Future
   #86 = Class              #85           // scala/concurrent/Future
   #87 = Utf8               value
   #88 = NameAndType        #87:#81       // value:()Lscala/Option;
   #89 = InterfaceMethodref #86.#88       // scala/concurrent/Future.value:()Lscala/Option;
   #90 = Utf8               (Ljava/lang/Object;)Ljava/lang/Object;
   #91 = MethodType         #90           //  (Ljava/lang/Object;)Ljava/lang/Object;
   #92 = Utf8               $anonfun$eitherValue$1
   #93 = Utf8               (Lscala/util/Try;)Lscala/util/Either;
   #94 = NameAndType        #92:#93       // $anonfun$eitherValue$1:(Lscala/util/Try;)Lscala/util/Either;
   #95 = Methodref          #2.#94        // org/scalatest/concurrent/ScalaFutures$$anon$1.$anonfun$eitherValue$1:(Lscala/util/Try;)Lscala/util/Either;
   #96 = MethodHandle       6:#95         // REF_invokeStatic org/scalatest/concurrent/ScalaFutures$$anon$1.$anonfun$eitherValue$1:(Lscala/util/Try;)Lscala/util/Either;
   #97 = MethodType         #93           //  (Lscala/util/Try;)Lscala/util/Either;
   #98 = Integer            5
   #99 = Integer            1
  #100 = Utf8               java/lang/invoke/LambdaMetafactory
  #101 = Class              #100          // java/lang/invoke/LambdaMetafactory
  #102 = Utf8               altMetafactory
  #103 = Utf8               (Ljava/lang/invoke/MethodHandles$Lookup;Ljava/lang/String;Ljava/lang/invoke/MethodType;[Ljava/lang/Object;)Ljava/lang/invoke/CallSite;
  #104 = NameAndType        #102:#103     // altMetafactory:(Ljava/lang/invoke/MethodHandles$Lookup;Ljava/lang/String;Ljava/lang/invoke/MethodType;[Ljava/lang/Object;)Ljava/lang/invoke/CallSite;
  #105 = Methodref          #101.#104     // java/lang/invoke/LambdaMetafactory.altMetafactory:(Ljava/lang/invoke/MethodHandles$Lookup;Ljava/lang/String;Ljava/lang/invoke/MethodType;[Ljava/lang/Object;)Ljava/lang/invoke/CallSite;
  #106 = MethodHandle       6:#105        // REF_invokeStatic java/lang/invoke/LambdaMetafactory.altMetafactory:(Ljava/lang/invoke/MethodHandles$Lookup;Ljava/lang/String;Ljava/lang/invoke/MethodType;[Ljava/lang/Object;)Ljava/lang/invoke/CallSite;
  #107 = Utf8               apply
  #108 = Utf8               ()Lscala/Function1;
  #109 = NameAndType        #107:#108     // apply:()Lscala/Function1;
  #110 = InvokeDynamic      #0:#109       // #0:apply:()Lscala/Function1;
  #111 = Utf8               scala/Option
  #112 = Class              #111          // scala/Option
  #113 = Utf8               map
  #114 = Utf8               (Lscala/Function1;)Lscala/Option;
  #115 = NameAndType        #113:#114     // map:(Lscala/Function1;)Lscala/Option;
  #116 = Methodref          #112.#115     // scala/Option.map:(Lscala/Function1;)Lscala/Option;
  #117 = Utf8               isExpired
  #118 = Utf8               ()Z
  #119 = Utf8               isCanceled
  #120 = Utf8               futureValueImpl
  #121 = Utf8               (Lorg/scalactic/source/Position;Lorg/scalatest/concurrent/AbstractPatienceConfiguration$PatienceConfig;)Ljava/lang/Object;
  #122 = Utf8               (Lorg/scalactic/source/Position;Lorg/scalatest/concurrent/AbstractPatienceConfiguration$PatienceConfig;)TT;
  #123 = Utf8               java/util/concurrent/TimeoutException
  #124 = Class              #123          // java/util/concurrent/TimeoutException
  #125 = Utf8               isCompleted
  #126 = NameAndType        #125:#118     // isCompleted:()Z
  #127 = InterfaceMethodref #86.#126      // scala/concurrent/Future.isCompleted:()Z
  #128 = Utf8               get
  #129 = Utf8               ()Ljava/lang/Object;
  #130 = NameAndType        #128:#129     // get:()Ljava/lang/Object;
  #131 = Methodref          #112.#130     // scala/Option.get:()Ljava/lang/Object;
  #132 = Utf8               scala/util/Try
  #133 = Class              #132          // scala/util/Try
  #134 = Utf8               $anonfun$futureValueImpl$1
  #135 = Utf8               (Ljava/lang/Object;)Lscala/util/Success;
  #136 = NameAndType        #134:#135     // $anonfun$futureValueImpl$1:(Ljava/lang/Object;)Lscala/util/Success;
  #137 = Methodref          #2.#136       // org/scalatest/concurrent/ScalaFutures$$anon$1.$anonfun$futureValueImpl$1:(Ljava/lang/Object;)Lscala/util/Success;
  #138 = MethodHandle       6:#137        // REF_invokeStatic org/scalatest/concurrent/ScalaFutures$$anon$1.$anonfun$futureValueImpl$1:(Ljava/lang/Object;)Lscala/util/Success;
  #139 = MethodType         #135          //  (Ljava/lang/Object;)Lscala/util/Success;
  #140 = InvokeDynamic      #1:#109       // #1:apply:()Lscala/Function1;
  #141 = Utf8               $anonfun$futureValueImpl$2
  #142 = Utf8               (Ljava/lang/Throwable;)Lscala/util/Success;
  #143 = NameAndType        #141:#142     // $anonfun$futureValueImpl$2:(Ljava/lang/Throwable;)Lscala/util/Success;
  #144 = Methodref          #2.#143       // org/scalatest/concurrent/ScalaFutures$$anon$1.$anonfun$futureValueImpl$2:(Ljava/lang/Throwable;)Lscala/util/Success;
  #145 = MethodHandle       6:#144        // REF_invokeStatic org/scalatest/concurrent/ScalaFutures$$anon$1.$anonfun$futureValueImpl$2:(Ljava/lang/Throwable;)Lscala/util/Success;
  #146 = MethodType         #142          //  (Ljava/lang/Throwable;)Lscala/util/Success;
  #147 = InvokeDynamic      #2:#109       // #2:apply:()Lscala/Function1;
  #148 = Utf8               transform
  #149 = Utf8               (Lscala/Function1;Lscala/Function1;)Lscala/util/Try;
  #150 = NameAndType        #148:#149     // transform:(Lscala/Function1;Lscala/Function1;)Lscala/util/Try;
  #151 = Methodref          #133.#150     // scala/util/Try.transform:(Lscala/Function1;Lscala/Function1;)Lscala/util/Try;
  #152 = Methodref          #133.#130     // scala/util/Try.get:()Ljava/lang/Object;
  #153 = Utf8               scala/util/Either
  #154 = Class              #153          // scala/util/Either
  #155 = NameAndType        #37:#38       // $outer:Lorg/scalatest/concurrent/ScalaFutures;
  #156 = Fieldref           #2.#155       // org/scalatest/concurrent/ScalaFutures$$anon$1.$outer:Lorg/scalatest/concurrent/ScalaFutures;
  #157 = Utf8               scala/concurrent/Await$
  #158 = Class              #157          // scala/concurrent/Await$
  #159 = Utf8               MODULE$
  #160 = Utf8               Lscala/concurrent/Await$;
  #161 = NameAndType        #159:#160     // MODULE$:Lscala/concurrent/Await$;
  #162 = Fieldref           #158.#161     // scala/concurrent/Await$.MODULE$:Lscala/concurrent/Await$;
  #163 = Utf8               scala/concurrent/duration/Duration$
  #164 = Class              #163          // scala/concurrent/duration/Duration$
  #165 = Utf8               Lscala/concurrent/duration/Duration$;
  #166 = NameAndType        #159:#165     // MODULE$:Lscala/concurrent/duration/Duration$;
  #167 = Fieldref           #164.#166     // scala/concurrent/duration/Duration$.MODULE$:Lscala/concurrent/duration/Duration$;
  #168 = Utf8               ()Lorg/scalatest/time/Span;
  #169 = NameAndType        #43:#168      // timeout:()Lorg/scalatest/time/Span;
  #170 = Methodref          #20.#169      // org/scalatest/concurrent/AbstractPatienceConfiguration$PatienceConfig.timeout:()Lorg/scalatest/time/Span;
  #171 = Utf8               org/scalatest/time/Span
  #172 = Class              #171          // org/scalatest/time/Span
  #173 = Utf8               totalNanos
  #174 = Utf8               ()J
  #175 = NameAndType        #173:#174     // totalNanos:()J
  #176 = Methodref          #172.#175     // org/scalatest/time/Span.totalNanos:()J
  #177 = Utf8               fromNanos
  #178 = Utf8               (J)Lscala/concurrent/duration/FiniteDuration;
  #179 = NameAndType        #177:#178     // fromNanos:(J)Lscala/concurrent/duration/FiniteDuration;
  #180 = Methodref          #164.#179     // scala/concurrent/duration/Duration$.fromNanos:(J)Lscala/concurrent/duration/FiniteDuration;
  #181 = Utf8               ready
  #182 = Utf8               (Lscala/concurrent/Awaitable;Lscala/concurrent/duration/Duration;)Lscala/concurrent/Awaitable;
  #183 = NameAndType        #181:#182     // ready:(Lscala/concurrent/Awaitable;Lscala/concurrent/duration/Duration;)Lscala/concurrent/Awaitable;
  #184 = Methodref          #158.#183     // scala/concurrent/Await$.ready:(Lscala/concurrent/Awaitable;Lscala/concurrent/duration/Duration;)Lscala/concurrent/Awaitable;
  #185 = InterfaceMethodref #10.#13       // org/scalatest/concurrent/ScalaFutures.convertScalaFuture:(Lscala/concurrent/Future;)Lorg/scalatest/concurrent/Futures$FutureConcept;
  #186 = NameAndType        #80:#81       // eitherValue:()Lscala/Option;
  #187 = InterfaceMethodref #7.#186       // org/scalatest/concurrent/Futures$FutureConcept.eitherValue:()Lscala/Option;
  #188 = Utf8               scala/util/Right
  #189 = Class              #188          // scala/util/Right
  #190 = NameAndType        #87:#129      // value:()Ljava/lang/Object;
  #191 = Methodref          #189.#190     // scala/util/Right.value:()Ljava/lang/Object;
  #192 = Utf8               scala/util/Left
  #193 = Class              #192          // scala/util/Left
  #194 = Methodref          #193.#190     // scala/util/Left.value:()Ljava/lang/Object;
  #195 = Utf8               java/lang/Throwable
  #196 = Class              #195          // java/lang/Throwable
  #197 = Utf8               org/scalatest/exceptions/TestPendingException
  #198 = Class              #197          // org/scalatest/exceptions/TestPendingException
  #199 = Utf8               org/scalatest/exceptions/TestCanceledException
  #200 = Class              #199          // org/scalatest/exceptions/TestCanceledException
  #201 = Utf8               org/scalatest/Suite$
  #202 = Class              #201          // org/scalatest/Suite$
  #203 = Utf8               Lorg/scalatest/Suite$;
  #204 = NameAndType        #159:#203     // MODULE$:Lorg/scalatest/Suite$;
  #205 = Fieldref           #202.#204     // org/scalatest/Suite$.MODULE$:Lorg/scalatest/Suite$;
  #206 = Utf8               anExceptionThatShouldCauseAnAbort
  #207 = Utf8               (Ljava/lang/Throwable;)Z
  #208 = NameAndType        #206:#207     // anExceptionThatShouldCauseAnAbort:(Ljava/lang/Throwable;)Z
  #209 = Methodref          #202.#208     // org/scalatest/Suite$.anExceptionThatShouldCauseAnAbort:(Ljava/lang/Throwable;)Z
  #210 = Utf8               java/util/concurrent/ExecutionException
  #211 = Class              #210          // java/util/concurrent/ExecutionException
  #212 = Utf8               getCause
  #213 = Utf8               ()Ljava/lang/Throwable;
  #214 = NameAndType        #212:#213     // getCause:()Ljava/lang/Throwable;
  #215 = Methodref          #211.#214     // java/util/concurrent/ExecutionException.getCause:()Ljava/lang/Throwable;
  #216 = Utf8               org/scalatest/exceptions/TestFailedException
  #217 = Class              #216          // org/scalatest/exceptions/TestFailedException
  #218 = Utf8               $anonfun$futureValueImpl$3
  #219 = Utf8               (Ljava/lang/Throwable;Lorg/scalatest/exceptions/StackDepthException;)Lscala/Some;
  #220 = NameAndType        #218:#219     // $anonfun$futureValueImpl$3:(Ljava/lang/Throwable;Lorg/scalatest/exceptions/StackDepthException;)Lscala/Some;
  #221 = Methodref          #2.#220       // org/scalatest/concurrent/ScalaFutures$$anon$1.$anonfun$futureValueImpl$3:(Ljava/lang/Throwable;Lorg/scalatest/exceptions/StackDepthException;)Lscala/Some;
  #222 = MethodHandle       6:#221        // REF_invokeStatic org/scalatest/concurrent/ScalaFutures$$anon$1.$anonfun$futureValueImpl$3:(Ljava/lang/Throwable;Lorg/scalatest/exceptions/StackDepthException;)Lscala/Some;
  #223 = Utf8               (Lorg/scalatest/exceptions/StackDepthException;)Lscala/Some;
  #224 = MethodType         #223          //  (Lorg/scalatest/exceptions/StackDepthException;)Lscala/Some;
  #225 = Utf8               (Ljava/lang/Throwable;)Lscala/Function1;
  #226 = NameAndType        #107:#225     // apply:(Ljava/lang/Throwable;)Lscala/Function1;
  #227 = InvokeDynamic      #3:#226       // #3:apply:(Ljava/lang/Throwable;)Lscala/Function1;
  #228 = Utf8               scala/Some
  #229 = Class              #228          // scala/Some
  #230 = Utf8               <init>
  #231 = Utf8               (Ljava/lang/Object;)V
  #232 = NameAndType        #230:#231     // "<init>":(Ljava/lang/Object;)V
  #233 = Methodref          #229.#232     // scala/Some."<init>":(Ljava/lang/Object;)V
  #234 = Utf8               (Lscala/Function1;Lscala/Option;Lorg/scalactic/source/Position;)V
  #235 = NameAndType        #230:#234     // "<init>":(Lscala/Function1;Lscala/Option;Lorg/scalactic/source/Position;)V
  #236 = Methodref          #217.#235     // org/scalatest/exceptions/TestFailedException."<init>":(Lscala/Function1;Lscala/Option;Lorg/scalactic/source/Position;)V
  #237 = Utf8               $anonfun$futureValueImpl$4
  #238 = NameAndType        #237:#219     // $anonfun$futureValueImpl$4:(Ljava/lang/Throwable;Lorg/scalatest/exceptions/StackDepthException;)Lscala/Some;
  #239 = Methodref          #2.#238       // org/scalatest/concurrent/ScalaFutures$$anon$1.$anonfun$futureValueImpl$4:(Ljava/lang/Throwable;Lorg/scalatest/exceptions/StackDepthException;)Lscala/Some;
  #240 = MethodHandle       6:#239        // REF_invokeStatic org/scalatest/concurrent/ScalaFutures$$anon$1.$anonfun$futureValueImpl$4:(Ljava/lang/Throwable;Lorg/scalatest/exceptions/StackDepthException;)Lscala/Some;
  #241 = InvokeDynamic      #4:#226       // #4:apply:(Ljava/lang/Throwable;)Lscala/Function1;
  #242 = Utf8               scala/MatchError
  #243 = Class              #242          // scala/MatchError
  #244 = Methodref          #243.#232     // scala/MatchError."<init>":(Ljava/lang/Object;)V
  #245 = Utf8               (Lorg/scalatest/concurrent/ScalaFutures$$anon$1;Lorg/scalatest/concurrent/AbstractPatienceConfiguration$PatienceConfig;Lorg/scalactic/source/Position;)V
  #246 = NameAndType        #230:#245     // "<init>":(Lorg/scalatest/concurrent/ScalaFutures$$anon$1;Lorg/scalatest/concurrent/AbstractPatienceConfiguration$PatienceConfig;Lorg/scalactic/source/Position;)V
  #247 = Methodref          #36.#246      // org/scalatest/concurrent/ScalaFutures$$anon$1$$anon$2."<init>":(Lorg/scalatest/concurrent/ScalaFutures$$anon$1;Lorg/scalatest/concurrent/AbstractPatienceConfiguration$PatienceConfig;Lorg/scalactic/source/Position;)V
  #248 = Utf8               v
  #249 = Utf8               Ljava/lang/Object;
  #250 = Utf8               tpe
  #251 = Utf8               Ljava/lang/Throwable;
  #252 = Utf8               tce
  #253 = Utf8               e
  #254 = Utf8               cause
  #255 = Utf8               ee
  #256 = Utf8               result
  #257 = Utf8               Lscala/util/Either;
  #258 = Utf8               Ljava/util/concurrent/TimeoutException;
  #259 = Utf8               org/scalactic/source/Position
  #260 = Class              #259          // org/scalactic/source/Position
  #261 = Utf8               org$scalatest$concurrent$Futures$FutureConcept$$$outer
  #262 = Utf8               ()Lorg/scalatest/concurrent/Futures;
  #263 = Utf8               x0$1
  #264 = Utf8               scala/util/Success
  #265 = Class              #264          // scala/util/Success
  #266 = Methodref          #265.#190     // scala/util/Success.value:()Ljava/lang/Object;
  #267 = Utf8               scala/package$
  #268 = Class              #267          // scala/package$
  #269 = Utf8               Lscala/package$;
  #270 = NameAndType        #159:#269     // MODULE$:Lscala/package$;
  #271 = Fieldref           #268.#270     // scala/package$.MODULE$:Lscala/package$;
  #272 = Utf8               Right
  #273 = Utf8               ()Lscala/util/Right$;
  #274 = NameAndType        #272:#273     // Right:()Lscala/util/Right$;
  #275 = Methodref          #268.#274     // scala/package$.Right:()Lscala/util/Right$;
  #276 = Utf8               scala/util/Right$
  #277 = Class              #276          // scala/util/Right$
  #278 = Utf8               (Ljava/lang/Object;)Lscala/util/Right;
  #279 = NameAndType        #107:#278     // apply:(Ljava/lang/Object;)Lscala/util/Right;
  #280 = Methodref          #277.#279     // scala/util/Right$.apply:(Ljava/lang/Object;)Lscala/util/Right;
  #281 = Utf8               scala/util/Failure
  #282 = Class              #281          // scala/util/Failure
  #283 = Utf8               exception
  #284 = NameAndType        #283:#213     // exception:()Ljava/lang/Throwable;
  #285 = Methodref          #282.#284     // scala/util/Failure.exception:()Ljava/lang/Throwable;
  #286 = Utf8               Left
  #287 = Utf8               ()Lscala/util/Left$;
  #288 = NameAndType        #286:#287     // Left:()Lscala/util/Left$;
  #289 = Methodref          #268.#288     // scala/package$.Left:()Lscala/util/Left$;
  #290 = Utf8               scala/util/Left$
  #291 = Class              #290          // scala/util/Left$
  #292 = Utf8               (Ljava/lang/Object;)Lscala/util/Left;
  #293 = NameAndType        #107:#292     // apply:(Ljava/lang/Object;)Lscala/util/Left;
  #294 = Methodref          #291.#293     // scala/util/Left$.apply:(Ljava/lang/Object;)Lscala/util/Left;
  #295 = Utf8               o
  #296 = Utf8               Lscala/util/Try;
  #297 = Utf8               s
  #298 = Methodref          #265.#232     // scala/util/Success."<init>":(Ljava/lang/Object;)V
  #299 = Utf8               f
  #300 = Utf8               cause$1
  #301 = Utf8               x$1
  #302 = Utf8               getMessage
  #303 = Utf8               ()Ljava/lang/String;
  #304 = NameAndType        #302:#303     // getMessage:()Ljava/lang/String;
  #305 = Methodref          #196.#304     // java/lang/Throwable.getMessage:()Ljava/lang/String;
  #306 = Utf8               org/scalatest/Resources$
  #307 = Class              #306          // org/scalatest/Resources$
  #308 = Utf8               Lorg/scalatest/Resources$;
  #309 = NameAndType        #159:#308     // MODULE$:Lorg/scalatest/Resources$;
  #310 = Fieldref           #307.#309     // org/scalatest/Resources$.MODULE$:Lorg/scalatest/Resources$;
  #311 = Utf8               getClass
  #312 = Utf8               ()Ljava/lang/Class;
  #313 = NameAndType        #311:#312     // getClass:()Ljava/lang/Class;
  #314 = Methodref          #196.#313     // java/lang/Throwable.getClass:()Ljava/lang/Class;
  #315 = Utf8               java/lang/Class
  #316 = Class              #315          // java/lang/Class
  #317 = Utf8               getName
  #318 = NameAndType        #317:#303     // getName:()Ljava/lang/String;
  #319 = Methodref          #316.#318     // java/lang/Class.getName:()Ljava/lang/String;
  #320 = Utf8               futureReturnedAnException
  #321 = Utf8               (Ljava/lang/Object;)Ljava/lang/String;
  #322 = NameAndType        #320:#321     // futureReturnedAnException:(Ljava/lang/Object;)Ljava/lang/String;
  #323 = Methodref          #307.#322     // org/scalatest/Resources$.futureReturnedAnException:(Ljava/lang/Object;)Ljava/lang/String;
  #324 = Utf8               futureReturnedAnExceptionWithMessage
  #325 = Utf8               (Ljava/lang/Object;Ljava/lang/Object;)Ljava/lang/String;
  #326 = NameAndType        #324:#325     // futureReturnedAnExceptionWithMessage:(Ljava/lang/Object;Ljava/lang/Object;)Ljava/lang/String;
  #327 = Methodref          #307.#326     // org/scalatest/Resources$.futureReturnedAnExceptionWithMessage:(Ljava/lang/Object;Ljava/lang/Object;)Ljava/lang/String;
  #328 = Utf8               Lorg/scalatest/exceptions/StackDepthException;
  #329 = Utf8               org/scalatest/exceptions/StackDepthException
  #330 = Class              #329          // org/scalatest/exceptions/StackDepthException
  #331 = Utf8               java/lang/String
  #332 = Class              #331          // java/lang/String
  #333 = Utf8               e$1
  #334 = Utf8               x$2
  #335 = Utf8               (Lorg/scalatest/concurrent/ScalaFutures;Lscala/concurrent/Future;)V
  #336 = Utf8               ()V
  #337 = NameAndType        #230:#336     // "<init>":()V
  #338 = Methodref          #5.#337       // java/lang/Object."<init>":()V
  #339 = Utf8               $init$
  #340 = Utf8               (Lorg/scalatest/concurrent/Futures$FutureConcept;)V
  #341 = NameAndType        #339:#340     // $init$:(Lorg/scalatest/concurrent/Futures$FutureConcept;)V
  #342 = InterfaceMethodref #7.#341       // org/scalatest/concurrent/Futures$FutureConcept.$init$:(Lorg/scalatest/concurrent/Futures$FutureConcept;)V
  #343 = Utf8               $deserializeLambda$
  #344 = Utf8               (Ljava/lang/invoke/SerializedLambda;)Ljava/lang/Object;
  #345 = Utf8               scala/runtime/LambdaDeserialize
  #346 = Class              #345          // scala/runtime/LambdaDeserialize
  #347 = Utf8               bootstrap
  #348 = Utf8               (Ljava/lang/invoke/MethodHandles$Lookup;Ljava/lang/String;Ljava/lang/invoke/MethodType;[Ljava/lang/invoke/MethodHandle;)Ljava/lang/invoke/CallSite;
  #349 = NameAndType        #347:#348     // bootstrap:(Ljava/lang/invoke/MethodHandles$Lookup;Ljava/lang/String;Ljava/lang/invoke/MethodType;[Ljava/lang/invoke/MethodHandle;)Ljava/lang/invoke/CallSite;
  #350 = Methodref          #346.#349     // scala/runtime/LambdaDeserialize.bootstrap:(Ljava/lang/invoke/MethodHandles$Lookup;Ljava/lang/String;Ljava/lang/invoke/MethodType;[Ljava/lang/invoke/MethodHandle;)Ljava/lang/invoke/CallSite;
  #351 = MethodHandle       6:#350        // REF_invokeStatic scala/runtime/LambdaDeserialize.bootstrap:(Ljava/lang/invoke/MethodHandles$Lookup;Ljava/lang/String;Ljava/lang/invoke/MethodType;[Ljava/lang/invoke/MethodHandle;)Ljava/lang/invoke/CallSite;
  #352 = Utf8               lambdaDeserialize
  #353 = NameAndType        #352:#344     // lambdaDeserialize:(Ljava/lang/invoke/SerializedLambda;)Ljava/lang/Object;
  #354 = InvokeDynamic      #5:#353       // #5:lambdaDeserialize:(Ljava/lang/invoke/SerializedLambda;)Ljava/lang/Object;
  #355 = Utf8               Code
  #356 = Utf8               LineNumberTable
  #357 = Utf8               LocalVariableTable
  #358 = Utf8               MethodParameters
  #359 = Utf8               Signature
  #360 = Utf8               StackMapTable
  #361 = Utf8               InnerClasses
  #362 = Utf8               EnclosingMethod
  #363 = Utf8               SourceFile
  #364 = Utf8               BootstrapMethods
  #365 = Utf8               ScalaInlineInfo
  #366 = Utf8               Scala
{
  private final org.scalatest.concurrent.ScalaFutures $outer;
    descriptor: Lorg/scalatest/concurrent/ScalaFutures;
    flags: (0x1012) ACC_PRIVATE, ACC_FINAL, ACC_SYNTHETIC

  private final scala.concurrent.Future scalaFuture$1;
    descriptor: Lscala/concurrent/Future;
    flags: (0x0012) ACC_PRIVATE, ACC_FINAL

  public final boolean isReadyWithin(org.scalatest.time.Span, org.scalatest.concurrent.AbstractPatienceConfiguration$PatienceConfig, org.scalactic.source.Position);
    descriptor: (Lorg/scalatest/time/Span;Lorg/scalatest/concurrent/AbstractPatienceConfiguration$PatienceConfig;Lorg/scalactic/source/Position;)Z
    flags: (0x0011) ACC_PUBLIC, ACC_FINAL
    Code:
      stack=4, locals=4, args_size=4
         0: aload_0
         1: aload_1
         2: aload_2
         3: aload_3
         4: invokestatic  #49                 // InterfaceMethod org/scalatest/concurrent/Futures$FutureConcept.isReadyWithin$:(Lorg/scalatest/concurrent/Futures$FutureConcept;Lorg/scalatest/time/Span;Lorg/scalatest/concurrent/AbstractPatienceConfiguration$PatienceConfig;Lorg/scalactic/source/Position;)Z
         7: ireturn
      LineNumberTable:
        line 281: 0
      LocalVariableTable:
        Start  Length  Slot  Name   Signature
            0       8     0  this   Lorg/scalatest/concurrent/ScalaFutures$$anon$1;
            0       8     1 timeout   Lorg/scalatest/time/Span;
            0       8     2 config   Lorg/scalatest/concurrent/AbstractPatienceConfiguration$PatienceConfig;
            0       8     3   pos   Lorg/scalactic/source/Position;
    MethodParameters:
      Name                           Flags
      timeout                        final
      config                         final
      pos                            final

  public final T futureValue(org.scalatest.concurrent.PatienceConfiguration$Timeout, org.scalatest.concurrent.PatienceConfiguration$Interval, org.scalactic.source.Position);
    descriptor: (Lorg/scalatest/concurrent/PatienceConfiguration$Timeout;Lorg/scalatest/concurrent/PatienceConfiguration$Interval;Lorg/scalactic/source/Position;)Ljava/lang/Object;
    flags: (0x0011) ACC_PUBLIC, ACC_FINAL
    Code:
      stack=4, locals=4, args_size=4
         0: aload_0
         1: aload_1
         2: aload_2
         3: aload_3
         4: invokestatic  #62                 // InterfaceMethod org/scalatest/concurrent/Futures$FutureConcept.futureValue$:(Lorg/scalatest/concurrent/Futures$FutureConcept;Lorg/scalatest/concurrent/PatienceConfiguration$Timeout;Lorg/scalatest/concurrent/PatienceConfiguration$Interval;Lorg/scalactic/source/Position;)Ljava/lang/Object;
         7: areturn
      LineNumberTable:
        line 281: 0
      LocalVariableTable:
        Start  Length  Slot  Name   Signature
            0       8     0  this   Lorg/scalatest/concurrent/ScalaFutures$$anon$1;
            0       8     1 timeout   Lorg/scalatest/concurrent/PatienceConfiguration$Timeout;
            0       8     2 interval   Lorg/scalatest/concurrent/PatienceConfiguration$Interval;
            0       8     3   pos   Lorg/scalactic/source/Position;
    Signature: #57                          // (Lorg/scalatest/concurrent/PatienceConfiguration$Timeout;Lorg/scalatest/concurrent/PatienceConfiguration$Interval;Lorg/scalactic/source/Position;)TT;
    MethodParameters:
      Name                           Flags
      timeout                        final
      interval                       final
      pos                            final

  public final T futureValue(org.scalatest.concurrent.PatienceConfiguration$Timeout, org.scalatest.concurrent.AbstractPatienceConfiguration$PatienceConfig, org.scalactic.source.Position);
    descriptor: (Lorg/scalatest/concurrent/PatienceConfiguration$Timeout;Lorg/scalatest/concurrent/AbstractPatienceConfiguration$PatienceConfig;Lorg/scalactic/source/Position;)Ljava/lang/Object;
    flags: (0x0011) ACC_PUBLIC, ACC_FINAL
    Code:
      stack=4, locals=4, args_size=4
         0: aload_0
         1: aload_1
         2: aload_2
         3: aload_3
         4: invokestatic  #69                 // InterfaceMethod org/scalatest/concurrent/Futures$FutureConcept.futureValue$:(Lorg/scalatest/concurrent/Futures$FutureConcept;Lorg/scalatest/concurrent/PatienceConfiguration$Timeout;Lorg/scalatest/concurrent/AbstractPatienceConfiguration$PatienceConfig;Lorg/scalactic/source/Position;)Ljava/lang/Object;
         7: areturn
      LineNumberTable:
        line 281: 0
      LocalVariableTable:
        Start  Length  Slot  Name   Signature
            0       8     0  this   Lorg/scalatest/concurrent/ScalaFutures$$anon$1;
            0       8     1 timeout   Lorg/scalatest/concurrent/PatienceConfiguration$Timeout;
            0       8     2 config   Lorg/scalatest/concurrent/AbstractPatienceConfiguration$PatienceConfig;
            0       8     3   pos   Lorg/scalactic/source/Position;
    Signature: #66                          // (Lorg/scalatest/concurrent/PatienceConfiguration$Timeout;Lorg/scalatest/concurrent/AbstractPatienceConfiguration$PatienceConfig;Lorg/scalactic/source/Position;)TT;
    MethodParameters:
      Name                           Flags
      timeout                        final
      config                         final
      pos                            final

  public final T futureValue(org.scalatest.concurrent.PatienceConfiguration$Interval, org.scalatest.concurrent.AbstractPatienceConfiguration$PatienceConfig, org.scalactic.source.Position);
    descriptor: (Lorg/scalatest/concurrent/PatienceConfiguration$Interval;Lorg/scalatest/concurrent/AbstractPatienceConfiguration$PatienceConfig;Lorg/scalactic/source/Position;)Ljava/lang/Object;
    flags: (0x0011) ACC_PUBLIC, ACC_FINAL
    Code:
      stack=4, locals=4, args_size=4
         0: aload_0
         1: aload_1
         2: aload_2
         3: aload_3
         4: invokestatic  #74                 // InterfaceMethod org/scalatest/concurrent/Futures$FutureConcept.futureValue$:(Lorg/scalatest/concurrent/Futures$FutureConcept;Lorg/scalatest/concurrent/PatienceConfiguration$Interval;Lorg/scalatest/concurrent/AbstractPatienceConfiguration$PatienceConfig;Lorg/scalactic/source/Position;)Ljava/lang/Object;
         7: areturn
      LineNumberTable:
        line 281: 0
      LocalVariableTable:
        Start  Length  Slot  Name   Signature
            0       8     0  this   Lorg/scalatest/concurrent/ScalaFutures$$anon$1;
            0       8     1 interval   Lorg/scalatest/concurrent/PatienceConfiguration$Interval;
            0       8     2 config   Lorg/scalatest/concurrent/AbstractPatienceConfiguration$PatienceConfig;
            0       8     3   pos   Lorg/scalactic/source/Position;
    Signature: #71                          // (Lorg/scalatest/concurrent/PatienceConfiguration$Interval;Lorg/scalatest/concurrent/AbstractPatienceConfiguration$PatienceConfig;Lorg/scalactic/source/Position;)TT;
    MethodParameters:
      Name                           Flags
      interval                       final
      config                         final
      pos                            final

  public T futureValue(org.scalatest.concurrent.AbstractPatienceConfiguration$PatienceConfig, org.scalactic.source.Position);
    descriptor: (Lorg/scalatest/concurrent/AbstractPatienceConfiguration$PatienceConfig;Lorg/scalactic/source/Position;)Ljava/lang/Object;
    flags: (0x0001) ACC_PUBLIC
    Code:
      stack=3, locals=3, args_size=3
         0: aload_0
         1: aload_1
         2: aload_2
         3: invokestatic  #79                 // InterfaceMethod org/scalatest/concurrent/Futures$FutureConcept.futureValue$:(Lorg/scalatest/concurrent/Futures$FutureConcept;Lorg/scalatest/concurrent/AbstractPatienceConfiguration$PatienceConfig;Lorg/scalactic/source/Position;)Ljava/lang/Object;
         6: areturn
      LineNumberTable:
        line 281: 0
      LocalVariableTable:
        Start  Length  Slot  Name   Signature
            0       7     0  this   Lorg/scalatest/concurrent/ScalaFutures$$anon$1;
            0       7     1 config   Lorg/scalatest/concurrent/AbstractPatienceConfiguration$PatienceConfig;
            0       7     2   pos   Lorg/scalactic/source/Position;
    Signature: #76                          // (Lorg/scalatest/concurrent/AbstractPatienceConfiguration$PatienceConfig;Lorg/scalactic/source/Position;)TT;
    MethodParameters:
      Name                           Flags
      config                         final
      pos                            final

  public scala.Option<scala.util.Either<java.lang.Throwable, T>> eitherValue();
    descriptor: ()Lscala/Option;
    flags: (0x0001) ACC_PUBLIC
    Code:
      stack=2, locals=1, args_size=1
         0: aload_0
         1: getfield      #84                 // Field scalaFuture$1:Lscala/concurrent/Future;
         4: invokeinterface #89,  1           // InterfaceMethod scala/concurrent/Future.value:()Lscala/Option;
         9: invokedynamic #110,  0            // InvokeDynamic #0:apply:()Lscala/Function1;
        14: invokevirtual #116                // Method scala/Option.map:(Lscala/Function1;)Lscala/Option;
        17: areturn
      LineNumberTable:
        line 283: 0
      LocalVariableTable:
        Start  Length  Slot  Name   Signature
            0      18     0  this   Lorg/scalatest/concurrent/ScalaFutures$$anon$1;
    Signature: #82                          // ()Lscala/Option<Lscala/util/Either<Ljava/lang/Throwable;TT;>;>;

  public boolean isExpired();
    descriptor: ()Z
    flags: (0x0001) ACC_PUBLIC
    Code:
      stack=1, locals=1, args_size=1
         0: iconst_0
         1: ireturn
      LineNumberTable:
        line 287: 0
      LocalVariableTable:
        Start  Length  Slot  Name   Signature
            0       2     0  this   Lorg/scalatest/concurrent/ScalaFutures$$anon$1;

  public boolean isCanceled();
    descriptor: ()Z
    flags: (0x0001) ACC_PUBLIC
    Code:
      stack=1, locals=1, args_size=1
         0: iconst_0
         1: ireturn
      LineNumberTable:
        line 288: 0
      LocalVariableTable:
        Start  Length  Slot  Name   Signature
            0       2     0  this   Lorg/scalatest/concurrent/ScalaFutures$$anon$1;

  public T futureValueImpl(org.scalactic.source.Position, org.scalatest.concurrent.AbstractPatienceConfiguration$PatienceConfig);
    descriptor: (Lorg/scalactic/source/Position;Lorg/scalatest/concurrent/AbstractPatienceConfiguration$PatienceConfig;)Ljava/lang/Object;
    flags: (0x0001) ACC_PUBLIC
    Code:
      stack=6, locals=24, args_size=3
         0: aload_0
         1: getfield      #84                 // Field scalaFuture$1:Lscala/concurrent/Future;
         4: invokeinterface #127,  1          // InterfaceMethod scala/concurrent/Future.isCompleted:()Z
         9: ifeq          49
        12: aload_0
        13: getfield      #84                 // Field scalaFuture$1:Lscala/concurrent/Future;
        16: invokeinterface #89,  1           // InterfaceMethod scala/concurrent/Future.value:()Lscala/Option;
        21: invokevirtual #131                // Method scala/Option.get:()Ljava/lang/Object;
        24: checkcast     #133                // class scala/util/Try
        27: invokedynamic #140,  0            // InvokeDynamic #1:apply:()Lscala/Function1;
        32: invokedynamic #147,  0            // InvokeDynamic #2:apply:()Lscala/Function1;
        37: invokevirtual #151                // Method scala/util/Try.transform:(Lscala/Function1;Lscala/Function1;)Lscala/util/Try;
        40: invokevirtual #152                // Method scala/util/Try.get:()Ljava/lang/Object;
        43: checkcast     #154                // class scala/util/Either
        46: goto          95
        49: aload_0
        50: getfield      #156                // Field $outer:Lorg/scalatest/concurrent/ScalaFutures;
        53: getstatic     #162                // Field scala/concurrent/Await$.MODULE$:Lscala/concurrent/Await$;
        56: aload_0
        57: getfield      #84                 // Field scalaFuture$1:Lscala/concurrent/Future;
        60: getstatic     #167                // Field scala/concurrent/duration/Duration$.MODULE$:Lscala/concurrent/duration/Duration$;
        63: aload_2
        64: invokevirtual #170                // Method org/scalatest/concurrent/AbstractPatienceConfiguration$PatienceConfig.timeout:()Lorg/scalatest/time/Span;
        67: invokevirtual #176                // Method org/scalatest/time/Span.totalNanos:()J
        70: invokevirtual #180                // Method scala/concurrent/duration/Duration$.fromNanos:(J)Lscala/concurrent/duration/FiniteDuration;
        73: invokevirtual #184                // Method scala/concurrent/Await$.ready:(Lscala/concurrent/Awaitable;Lscala/concurrent/duration/Duration;)Lscala/concurrent/Awaitable;
        76: checkcast     #86                 // class scala/concurrent/Future
        79: invokeinterface #185,  2          // InterfaceMethod org/scalatest/concurrent/ScalaFutures.convertScalaFuture:(Lscala/concurrent/Future;)Lorg/scalatest/concurrent/Futures$FutureConcept;
        84: invokeinterface #187,  1          // InterfaceMethod org/scalatest/concurrent/Futures$FutureConcept.eitherValue:()Lscala/Option;
        89: invokevirtual #131                // Method scala/Option.get:()Ljava/lang/Object;
        92: checkcast     #154                // class scala/util/Either
        95: astore        5
        97: iconst_0
        98: istore        6
       100: aconst_null
       101: astore        7
       103: aload         5
       105: astore        8
       107: aload         8
       109: instanceof    #189                // class scala/util/Right
       112: ifeq          135
       115: aload         8
       117: checkcast     #189                // class scala/util/Right
       120: astore        9
       122: aload         9
       124: invokevirtual #191                // Method scala/util/Right.value:()Ljava/lang/Object;
       127: astore        10
       129: aload         10
       131: astore_3
       132: goto          459
       135: goto          138
       138: aload         8
       140: instanceof    #193                // class scala/util/Left
       143: ifeq          187
       146: iconst_1
       147: istore        6
       149: aload         8
       151: checkcast     #193                // class scala/util/Left
       154: astore        7
       156: aload         7
       158: invokevirtual #194                // Method scala/util/Left.value:()Ljava/lang/Object;
       161: checkcast     #196                // class java/lang/Throwable
       164: astore        11
       166: aload         11
       168: instanceof    #198                // class org/scalatest/exceptions/TestPendingException
       171: ifeq          184
       174: aload         11
       176: checkcast     #198                // class org/scalatest/exceptions/TestPendingException
       179: astore        12
       181: aload         12
       183: athrow
       184: goto          190
       187: goto          190
       190: iload         6
       192: ifeq          226
       195: aload         7
       197: invokevirtual #194                // Method scala/util/Left.value:()Ljava/lang/Object;
       200: checkcast     #196                // class java/lang/Throwable
       203: astore        13
       205: aload         13
       207: instanceof    #200                // class org/scalatest/exceptions/TestCanceledException
       210: ifeq          223
       213: aload         13
       215: checkcast     #200                // class org/scalatest/exceptions/TestCanceledException
       218: astore        14
       220: aload         14
       222: athrow
       223: goto          229
       226: goto          229
       229: iload         6
       231: ifeq          261
       234: aload         7
       236: invokevirtual #194                // Method scala/util/Left.value:()Ljava/lang/Object;
       239: checkcast     #196                // class java/lang/Throwable
       242: astore        15
       244: getstatic     #205                // Field org/scalatest/Suite$.MODULE$:Lorg/scalatest/Suite$;
       247: aload         15
       249: invokevirtual #209                // Method org/scalatest/Suite$.anExceptionThatShouldCauseAnAbort:(Ljava/lang/Throwable;)Z
       252: ifeq          258
       255: aload         15
       257: athrow
       258: goto          264
       261: goto          264
       264: iload         6
       266: ifeq          403
       269: aload         7
       271: invokevirtual #194                // Method scala/util/Left.value:()Ljava/lang/Object;
       274: checkcast     #196                // class java/lang/Throwable
       277: astore        16
       279: aload         16
       281: instanceof    #211                // class java/util/concurrent/ExecutionException
       284: ifeq          400
       287: aload         16
       289: checkcast     #211                // class java/util/concurrent/ExecutionException
       292: astore        17
       294: aload         17
       296: invokevirtual #215                // Method java/util/concurrent/ExecutionException.getCause:()Ljava/lang/Throwable;
       299: ifnull        397
       302: aload         17
       304: invokevirtual #215                // Method java/util/concurrent/ExecutionException.getCause:()Ljava/lang/Throwable;
       307: astore        18
       309: aload         18
       311: astore        19
       313: aload         19
       315: instanceof    #198                // class org/scalatest/exceptions/TestPendingException
       318: ifeq          331
       321: aload         19
       323: checkcast     #198                // class org/scalatest/exceptions/TestPendingException
       326: astore        20
       328: aload         20
       330: athrow
       331: goto          334
       334: aload         19
       336: instanceof    #200                // class org/scalatest/exceptions/TestCanceledException
       339: ifeq          352
       342: aload         19
       344: checkcast     #200                // class org/scalatest/exceptions/TestCanceledException
       347: astore        21
       349: aload         21
       351: athrow
       352: goto          355
       355: getstatic     #205                // Field org/scalatest/Suite$.MODULE$:Lorg/scalatest/Suite$;
       358: aload         19
       360: invokevirtual #209                // Method org/scalatest/Suite$.anExceptionThatShouldCauseAnAbort:(Ljava/lang/Throwable;)Z
       363: ifeq          369
       366: aload         19
       368: athrow
       369: goto          372
       372: new           #217                // class org/scalatest/exceptions/TestFailedException
       375: dup
       376: aload         18
       378: invokedynamic #227,  0            // InvokeDynamic #3:apply:(Ljava/lang/Throwable;)Lscala/Function1;
       383: new           #229                // class scala/Some
       386: dup
       387: aload         18
       389: invokespecial #233                // Method scala/Some."<init>":(Ljava/lang/Object;)V
       392: aload_1
       393: invokespecial #236                // Method org/scalatest/exceptions/TestFailedException."<init>":(Lscala/Function1;Lscala/Option;Lorg/scalactic/source/Position;)V
       396: athrow
       397: goto          406
       400: goto          406
       403: goto          406
       406: iload         6
       408: ifeq          446
       411: aload         7
       413: invokevirtual #194                // Method scala/util/Left.value:()Ljava/lang/Object;
       416: checkcast     #196                // class java/lang/Throwable
       419: astore        22
       421: new           #217                // class org/scalatest/exceptions/TestFailedException
       424: dup
       425: aload         22
       427: invokedynamic #241,  0            // InvokeDynamic #4:apply:(Ljava/lang/Throwable;)Lscala/Function1;
       432: new           #229                // class scala/Some
       435: dup
       436: aload         22
       438: invokespecial #233                // Method scala/Some."<init>":(Ljava/lang/Object;)V
       441: aload_1
       442: invokespecial #236                // Method org/scalatest/exceptions/TestFailedException."<init>":(Lscala/Function1;Lscala/Option;Lorg/scalactic/source/Position;)V
       445: athrow
       446: goto          449
       449: new           #243                // class scala/MatchError
       452: dup
       453: aload         8
       455: invokespecial #244                // Method scala/MatchError."<init>":(Ljava/lang/Object;)V
       458: athrow
       459: aload_3
       460: goto          476
       463: astore        23
       465: new           #36                 // class org/scalatest/concurrent/ScalaFutures$$anon$1$$anon$2
       468: dup
       469: aload_0
       470: aload_2
       471: aload_1
       472: invokespecial #247                // Method org/scalatest/concurrent/ScalaFutures$$anon$1$$anon$2."<init>":(Lorg/scalatest/concurrent/ScalaFutures$$anon$1;Lorg/scalatest/concurrent/AbstractPatienceConfiguration$PatienceConfig;Lorg/scalactic/source/Position;)V
       475: athrow
       476: areturn
      Exception table:
         from    to  target type
             0   460   463   Class java/util/concurrent/TimeoutException
      StackMapTable: number_of_entries = 28
        frame_type = 49 /* same */
        frame_type = 109 /* same_locals_1_stack_item */
          stack = [ class scala/util/Either ]
        frame_type = 255 /* full_frame */
          offset_delta = 39
          locals = [ class org/scalatest/concurrent/ScalaFutures$$anon$1, class org/scalactic/source/Position, class org/scalatest/concurrent/AbstractPatienceConfiguration$PatienceConfig, top, top, class scala/util/Either, int, null, class scala/util/Either ]
          stack = []
        frame_type = 2 /* same */
        frame_type = 255 /* full_frame */
          offset_delta = 45
          locals = [ class org/scalatest/concurrent/ScalaFutures$$anon$1, class org/scalactic/source/Position, class org/scalatest/concurrent/AbstractPatienceConfiguration$PatienceConfig, top, top, class scala/util/Either, int, class scala/util/Left, class scala/util/Either, top, top, class java/lang/Throwable ]
          stack = []
        frame_type = 255 /* full_frame */
          offset_delta = 2
          locals = [ class org/scalatest/concurrent/ScalaFutures$$anon$1, class org/scalactic/source/Position, class org/scalatest/concurrent/AbstractPatienceConfiguration$PatienceConfig, top, top, class scala/util/Either, int, null, class scala/util/Either ]
          stack = []
        frame_type = 255 /* full_frame */
          offset_delta = 2
          locals = [ class org/scalatest/concurrent/ScalaFutures$$anon$1, class org/scalactic/source/Position, class org/scalatest/concurrent/AbstractPatienceConfiguration$PatienceConfig, top, top, class scala/util/Either, int, class scala/util/Left, class scala/util/Either ]
          stack = []
        frame_type = 255 /* full_frame */
          offset_delta = 32
          locals = [ class org/scalatest/concurrent/ScalaFutures$$anon$1, class org/scalactic/source/Position, class org/scalatest/concurrent/AbstractPatienceConfiguration$PatienceConfig, top, top, class scala/util/Either, int, class scala/util/Left, class scala/util/Either, top, top, top, top, class java/lang/Throwable ]
          stack = []
        frame_type = 255 /* full_frame */
          offset_delta = 2
          locals = [ class org/scalatest/concurrent/ScalaFutures$$anon$1, class org/scalactic/source/Position, class org/scalatest/concurrent/AbstractPatienceConfiguration$PatienceConfig, top, top, class scala/util/Either, int, class scala/util/Left, class scala/util/Either ]
          stack = []
        frame_type = 2 /* same */
        frame_type = 255 /* full_frame */
          offset_delta = 28
          locals = [ class org/scalatest/concurrent/ScalaFutures$$anon$1, class org/scalactic/source/Position, class org/scalatest/concurrent/AbstractPatienceConfiguration$PatienceConfig, top, top, class scala/util/Either, int, class scala/util/Left, class scala/util/Either, top, top, top, top, top, top, class java/lang/Throwable ]
          stack = []
        frame_type = 255 /* full_frame */
          offset_delta = 2
          locals = [ class org/scalatest/concurrent/ScalaFutures$$anon$1, class org/scalactic/source/Position, class org/scalatest/concurrent/AbstractPatienceConfiguration$PatienceConfig, top, top, class scala/util/Either, int, class scala/util/Left, class scala/util/Either ]
          stack = []
        frame_type = 2 /* same */
        frame_type = 255 /* full_frame */
          offset_delta = 66
          locals = [ class org/scalatest/concurrent/ScalaFutures$$anon$1, class org/scalactic/source/Position, class org/scalatest/concurrent/AbstractPatienceConfiguration$PatienceConfig, top, top, class scala/util/Either, int, class scala/util/Left, class scala/util/Either, top, top, top, top, top, top, top, class java/lang/Throwable, class java/util/concurrent/ExecutionException, class java/lang/Throwable, class java/lang/Throwable ]
          stack = []
        frame_type = 2 /* same */
        frame_type = 17 /* same */
        frame_type = 2 /* same */
        frame_type = 13 /* same */
        frame_type = 2 /* same */
        frame_type = 249 /* chop */
          offset_delta = 24
        frame_type = 250 /* chop */
          offset_delta = 2
        frame_type = 255 /* full_frame */
          offset_delta = 2
          locals = [ class org/scalatest/concurrent/ScalaFutures$$anon$1, class org/scalactic/source/Position, class org/scalatest/concurrent/AbstractPatienceConfiguration$PatienceConfig, top, top, class scala/util/Either, int, class scala/util/Left, class scala/util/Either ]
          stack = []
        frame_type = 2 /* same */
        frame_type = 39 /* same */
        frame_type = 2 /* same */
        frame_type = 255 /* full_frame */
          offset_delta = 9
          locals = [ class org/scalatest/concurrent/ScalaFutures$$anon$1, class org/scalactic/source/Position, class org/scalatest/concurrent/AbstractPatienceConfiguration$PatienceConfig, class java/lang/Object, top, class scala/util/Either, int, null, class scala/util/Either, class scala/util/Right, class java/lang/Object ]
          stack = []
        frame_type = 255 /* full_frame */
          offset_delta = 3
          locals = [ class org/scalatest/concurrent/ScalaFutures$$anon$1, class org/scalactic/source/Position, class org/scalatest/concurrent/AbstractPatienceConfiguration$PatienceConfig ]
          stack = [ class java/util/concurrent/TimeoutException ]
        frame_type = 255 /* full_frame */
          offset_delta = 12
          locals = [ class org/scalatest/concurrent/ScalaFutures$$anon$1, class org/scalactic/source/Position, class org/scalatest/concurrent/AbstractPatienceConfiguration$PatienceConfig, class java/lang/Object, top, class scala/util/Either, int, null, class scala/util/Either, class scala/util/Right, class java/lang/Object ]
          stack = [ class java/lang/Object ]
      LineNumberTable:
        line 294: 0
        line 295: 12
        line 297: 49
        line 301: 97
        line 302: 107
        line 303: 138
        line 304: 190
        line 305: 229
        line 306: 264
        line 307: 302
        line 308: 309
        line 309: 313
        line 310: 334
        line 311: 355
        line 308: 369
        line 313: 372
        line 314: 376
        line 320: 383
        line 321: 392
        line 313: 396
        line 306: 397
        line 324: 406
        line 325: 421
        line 326: 425
        line 332: 432
        line 333: 441
        line 325: 445
        line 324: 446
        line 301: 449
        line 339: 465
      LocalVariableTable:
        Start  Length  Slot  Name   Signature
          129       6    10     v   Ljava/lang/Object;
          166      21    11   tpe   Ljava/lang/Throwable;
          205      21    13   tce   Ljava/lang/Throwable;
          244      17    15     e   Ljava/lang/Throwable;
          309      88    18 cause   Ljava/lang/Throwable;
          279     124    16    ee   Ljava/lang/Throwable;
          421      25    22     e   Ljava/lang/Throwable;
           97     363     5 result   Lscala/util/Either;
          463      13    23     e   Ljava/util/concurrent/TimeoutException;
            0     477     0  this   Lorg/scalatest/concurrent/ScalaFutures$$anon$1;
            0     477     1   pos   Lorg/scalactic/source/Position;
            0     477     2 config   Lorg/scalatest/concurrent/AbstractPatienceConfiguration$PatienceConfig;
    Signature: #122                         // (Lorg/scalactic/source/Position;Lorg/scalatest/concurrent/AbstractPatienceConfiguration$PatienceConfig;)TT;
    MethodParameters:
      Name                           Flags
      pos                            final
      config                         final

  public org.scalatest.concurrent.Futures org$scalatest$concurrent$Futures$FutureConcept$$$outer();
    descriptor: ()Lorg/scalatest/concurrent/Futures;
    flags: (0x1001) ACC_PUBLIC, ACC_SYNTHETIC
    Code:
      stack=1, locals=1, args_size=1
         0: aload_0
         1: getfield      #156                // Field $outer:Lorg/scalatest/concurrent/ScalaFutures;
         4: areturn
      LineNumberTable:
        line 281: 0
      LocalVariableTable:
        Start  Length  Slot  Name   Signature
            0       5     0  this   Lorg/scalatest/concurrent/ScalaFutures$$anon$1;

  public static final scala.util.Either $anonfun$eitherValue$1(scala.util.Try);
    descriptor: (Lscala/util/Try;)Lscala/util/Either;
    flags: (0x1019) ACC_PUBLIC, ACC_STATIC, ACC_FINAL, ACC_SYNTHETIC
    Code:
      stack=3, locals=7, args_size=1
         0: aload_0
         1: astore_2
         2: aload_2
         3: instanceof    #265                // class scala/util/Success
         6: ifeq          35
         9: aload_2
        10: checkcast     #265                // class scala/util/Success
        13: astore_3
        14: aload_3
        15: invokevirtual #266                // Method scala/util/Success.value:()Ljava/lang/Object;
        18: astore        4
        20: getstatic     #271                // Field scala/package$.MODULE$:Lscala/package$;
        23: invokevirtual #275                // Method scala/package$.Right:()Lscala/util/Right$;
        26: aload         4
        28: invokevirtual #280                // Method scala/util/Right$.apply:(Ljava/lang/Object;)Lscala/util/Right;
        31: astore_1
        32: goto          85
        35: goto          38
        38: aload_2
        39: instanceof    #282                // class scala/util/Failure
        42: ifeq          73
        45: aload_2
        46: checkcast     #282                // class scala/util/Failure
        49: astore        5
        51: aload         5
        53: invokevirtual #285                // Method scala/util/Failure.exception:()Ljava/lang/Throwable;
        56: astore        6
        58: getstatic     #271                // Field scala/package$.MODULE$:Lscala/package$;
        61: invokevirtual #289                // Method scala/package$.Left:()Lscala/util/Left$;
        64: aload         6
        66: invokevirtual #294                // Method scala/util/Left$.apply:(Ljava/lang/Object;)Lscala/util/Left;
        69: astore_1
        70: goto          85
        73: goto          76
        76: new           #243                // class scala/MatchError
        79: dup
        80: aload_2
        81: invokespecial #244                // Method scala/MatchError."<init>":(Ljava/lang/Object;)V
        84: athrow
        85: aload_1
        86: areturn
      StackMapTable: number_of_entries = 5
        frame_type = 253 /* append */
          offset_delta = 35
          locals = [ top, class scala/util/Try ]
        frame_type = 2 /* same */
        frame_type = 34 /* same */
        frame_type = 2 /* same */
        frame_type = 255 /* full_frame */
          offset_delta = 8
          locals = [ class scala/util/Try, class scala/util/Either, class scala/util/Try ]
          stack = []
      LineNumberTable:
        line 283: 0
        line 284: 2
        line 285: 38
        line 283: 76
      LocalVariableTable:
        Start  Length  Slot  Name   Signature
           20      15     4     o   Ljava/lang/Object;
           58      15     6     e   Ljava/lang/Throwable;
            0      87     0  x0$1   Lscala/util/Try;
    MethodParameters:
      Name                           Flags
      x0$1                           final

  public static final scala.util.Success $anonfun$futureValueImpl$1(java.lang.Object);
    descriptor: (Ljava/lang/Object;)Lscala/util/Success;
    flags: (0x1019) ACC_PUBLIC, ACC_STATIC, ACC_FINAL, ACC_SYNTHETIC
    Code:
      stack=4, locals=1, args_size=1
         0: new           #265                // class scala/util/Success
         3: dup
         4: getstatic     #271                // Field scala/package$.MODULE$:Lscala/package$;
         7: invokevirtual #275                // Method scala/package$.Right:()Lscala/util/Right$;
        10: aload_0
        11: invokevirtual #280                // Method scala/util/Right$.apply:(Ljava/lang/Object;)Lscala/util/Right;
        14: invokespecial #298                // Method scala/util/Success."<init>":(Ljava/lang/Object;)V
        17: areturn
      LineNumberTable:
        line 295: 0
      LocalVariableTable:
        Start  Length  Slot  Name   Signature
            0      18     0     s   Ljava/lang/Object;
    MethodParameters:
      Name                           Flags
      s                              final

  public static final scala.util.Success $anonfun$futureValueImpl$2(java.lang.Throwable);
    descriptor: (Ljava/lang/Throwable;)Lscala/util/Success;
    flags: (0x1019) ACC_PUBLIC, ACC_STATIC, ACC_FINAL, ACC_SYNTHETIC
    Code:
      stack=4, locals=1, args_size=1
         0: new           #265                // class scala/util/Success
         3: dup
         4: getstatic     #271                // Field scala/package$.MODULE$:Lscala/package$;
         7: invokevirtual #289                // Method scala/package$.Left:()Lscala/util/Left$;
        10: aload_0
        11: invokevirtual #294                // Method scala/util/Left$.apply:(Ljava/lang/Object;)Lscala/util/Left;
        14: invokespecial #298                // Method scala/util/Success."<init>":(Ljava/lang/Object;)V
        17: areturn
      LineNumberTable:
        line 295: 0
      LocalVariableTable:
        Start  Length  Slot  Name   Signature
            0      18     0     f   Ljava/lang/Throwable;
    MethodParameters:
      Name                           Flags
      f                              final

  public static final scala.Some $anonfun$futureValueImpl$3(java.lang.Throwable, org.scalatest.exceptions.StackDepthException);
    descriptor: (Ljava/lang/Throwable;Lorg/scalatest/exceptions/StackDepthException;)Lscala/Some;
    flags: (0x1019) ACC_PUBLIC, ACC_STATIC, ACC_FINAL, ACC_SYNTHETIC
    Code:
      stack=5, locals=2, args_size=2
         0: new           #229                // class scala/Some
         3: dup
         4: aload_0
         5: invokevirtual #305                // Method java/lang/Throwable.getMessage:()Ljava/lang/String;
         8: ifnonnull     27
        11: getstatic     #310                // Field org/scalatest/Resources$.MODULE$:Lorg/scalatest/Resources$;
        14: aload_0
        15: invokevirtual #314                // Method java/lang/Throwable.getClass:()Ljava/lang/Class;
        18: invokevirtual #319                // Method java/lang/Class.getName:()Ljava/lang/String;
        21: invokevirtual #323                // Method org/scalatest/Resources$.futureReturnedAnException:(Ljava/lang/Object;)Ljava/lang/String;
        24: goto          44
        27: getstatic     #310                // Field org/scalatest/Resources$.MODULE$:Lorg/scalatest/Resources$;
        30: aload_0
        31: invokevirtual #314                // Method java/lang/Throwable.getClass:()Ljava/lang/Class;
        34: invokevirtual #319                // Method java/lang/Class.getName:()Ljava/lang/String;
        37: aload_0
        38: invokevirtual #305                // Method java/lang/Throwable.getMessage:()Ljava/lang/String;
        41: invokevirtual #327                // Method org/scalatest/Resources$.futureReturnedAnExceptionWithMessage:(Ljava/lang/Object;Ljava/lang/Object;)Ljava/lang/String;
        44: invokespecial #233                // Method scala/Some."<init>":(Ljava/lang/Object;)V
        47: areturn
      StackMapTable: number_of_entries = 2
        frame_type = 255 /* full_frame */
          offset_delta = 27
          locals = [ class java/lang/Throwable, class org/scalatest/exceptions/StackDepthException ]
          stack = [ uninitialized 0, uninitialized 0 ]
        frame_type = 255 /* full_frame */
          offset_delta = 16
          locals = [ class java/lang/Throwable, class org/scalatest/exceptions/StackDepthException ]
          stack = [ uninitialized 0, uninitialized 0, class java/lang/String ]
      LineNumberTable:
        line 314: 0
        line 315: 4
        line 316: 11
        line 318: 27
      LocalVariableTable:
        Start  Length  Slot  Name   Signature
            0      48     0 cause$1   Ljava/lang/Throwable;
            0      48     1   x$1   Lorg/scalatest/exceptions/StackDepthException;
    MethodParameters:
      Name                           Flags
      cause$1                        final
      x$1                            final

  public static final scala.Some $anonfun$futureValueImpl$4(java.lang.Throwable, org.scalatest.exceptions.StackDepthException);
    descriptor: (Ljava/lang/Throwable;Lorg/scalatest/exceptions/StackDepthException;)Lscala/Some;
    flags: (0x1019) ACC_PUBLIC, ACC_STATIC, ACC_FINAL, ACC_SYNTHETIC
    Code:
      stack=5, locals=2, args_size=2
         0: new           #229                // class scala/Some
         3: dup
         4: aload_0
         5: invokevirtual #305                // Method java/lang/Throwable.getMessage:()Ljava/lang/String;
         8: ifnonnull     27
        11: getstatic     #310                // Field org/scalatest/Resources$.MODULE$:Lorg/scalatest/Resources$;
        14: aload_0
        15: invokevirtual #314                // Method java/lang/Throwable.getClass:()Ljava/lang/Class;
        18: invokevirtual #319                // Method java/lang/Class.getName:()Ljava/lang/String;
        21: invokevirtual #323                // Method org/scalatest/Resources$.futureReturnedAnException:(Ljava/lang/Object;)Ljava/lang/String;
        24: goto          44
        27: getstatic     #310                // Field org/scalatest/Resources$.MODULE$:Lorg/scalatest/Resources$;
        30: aload_0
        31: invokevirtual #314                // Method java/lang/Throwable.getClass:()Ljava/lang/Class;
        34: invokevirtual #319                // Method java/lang/Class.getName:()Ljava/lang/String;
        37: aload_0
        38: invokevirtual #305                // Method java/lang/Throwable.getMessage:()Ljava/lang/String;
        41: invokevirtual #327                // Method org/scalatest/Resources$.futureReturnedAnExceptionWithMessage:(Ljava/lang/Object;Ljava/lang/Object;)Ljava/lang/String;
        44: invokespecial #233                // Method scala/Some."<init>":(Ljava/lang/Object;)V
        47: areturn
      StackMapTable: number_of_entries = 2
        frame_type = 255 /* full_frame */
          offset_delta = 27
          locals = [ class java/lang/Throwable, class org/scalatest/exceptions/StackDepthException ]
          stack = [ uninitialized 0, uninitialized 0 ]
        frame_type = 255 /* full_frame */
          offset_delta = 16
          locals = [ class java/lang/Throwable, class org/scalatest/exceptions/StackDepthException ]
          stack = [ uninitialized 0, uninitialized 0, class java/lang/String ]
      LineNumberTable:
        line 326: 0
        line 327: 4
        line 328: 11
        line 330: 27
      LocalVariableTable:
        Start  Length  Slot  Name   Signature
            0      48     0   e$1   Ljava/lang/Throwable;
            0      48     1   x$2   Lorg/scalatest/exceptions/StackDepthException;
    MethodParameters:
      Name                           Flags
      e$1                            final
      x$2                            final

  public org.scalatest.concurrent.ScalaFutures$$anon$1(org.scalatest.concurrent.ScalaFutures, scala.concurrent.Future);
    descriptor: (Lorg/scalatest/concurrent/ScalaFutures;Lscala/concurrent/Future;)V
    flags: (0x0001) ACC_PUBLIC
    Code:
      stack=2, locals=3, args_size=3
         0: aload_1
         1: ifnonnull     6
         4: aconst_null
         5: athrow
         6: aload_0
         7: aload_1
         8: putfield      #156                // Field $outer:Lorg/scalatest/concurrent/ScalaFutures;
        11: aload_0
        12: aload_2
        13: putfield      #84                 // Field scalaFuture$1:Lscala/concurrent/Future;
        16: aload_0
        17: invokespecial #338                // Method java/lang/Object."<init>":()V
        20: aload_0
        21: invokestatic  #342                // InterfaceMethod org/scalatest/concurrent/Futures$FutureConcept.$init$:(Lorg/scalatest/concurrent/Futures$FutureConcept;)V
        24: return
      StackMapTable: number_of_entries = 1
        frame_type = 6 /* same */
      LineNumberTable:
        line 281: 0
        line 280: 11
        line 281: 16
      LocalVariableTable:
        Start  Length  Slot  Name   Signature
            0      25     0  this   Lorg/scalatest/concurrent/ScalaFutures$$anon$1;
            0      25     1 $outer   Lorg/scalatest/concurrent/ScalaFutures;
            0      25     2 scalaFuture$1   Lscala/concurrent/Future;
    MethodParameters:
      Name                           Flags
      $outer                         final synthetic
      scalaFuture$1                  final

  private static java.lang.Object $deserializeLambda$(java.lang.invoke.SerializedLambda);
    descriptor: (Ljava/lang/invoke/SerializedLambda;)Ljava/lang/Object;
    flags: (0x100a) ACC_PRIVATE, ACC_STATIC, ACC_SYNTHETIC
    Code:
      stack=1, locals=1, args_size=1
         0: aload_0
         1: invokedynamic #354,  0            // InvokeDynamic #5:lambdaDeserialize:(Ljava/lang/invoke/SerializedLambda;)Ljava/lang/Object;
         6: areturn
}
InnerClasses:
  public static final #18= #15 of #17;    // Lookup=class java/lang/invoke/MethodHandles$Lookup of class java/lang/invoke/MethodHandles
  public final #23= #20 of #22;           // PatienceConfig=class org/scalatest/concurrent/AbstractPatienceConfiguration$PatienceConfig of class org/scalatest/concurrent/AbstractPatienceConfiguration
  public #26= #7 of #25;                  // FutureConcept=class org/scalatest/concurrent/Futures$FutureConcept of class org/scalatest/concurrent/Futures
  public static final #31= #28 of #30;    // Interval=class org/scalatest/concurrent/PatienceConfiguration$Interval of class org/scalatest/concurrent/PatienceConfiguration
  public static final #34= #33 of #30;    // Timeout=class org/scalatest/concurrent/PatienceConfiguration$Timeout of class org/scalatest/concurrent/PatienceConfiguration
  public final #2;                        // class org/scalatest/concurrent/ScalaFutures$$anon$1
  public final #36;                       // class org/scalatest/concurrent/ScalaFutures$$anon$1$$anon$2
EnclosingMethod: #10.#13                // org.scalatest.concurrent.ScalaFutures.convertScalaFuture
Signature: #3                           // Ljava/lang/Object;Lorg/scalatest/concurrent/Futures$FutureConcept<TT;>;
SourceFile: "ScalaFutures.scala"
BootstrapMethods:
  0: #106 REF_invokeStatic java/lang/invoke/LambdaMetafactory.altMetafactory:(Ljava/lang/invoke/MethodHandles$Lookup;Ljava/lang/String;Ljava/lang/invoke/MethodType;[Ljava/lang/Object;)Ljava/lang/invoke/CallSite;
    Method arguments:
      #91 (Ljava/lang/Object;)Ljava/lang/Object;
      #96 REF_invokeStatic org/scalatest/concurrent/ScalaFutures$$anon$1.$anonfun$eitherValue$1:(Lscala/util/Try;)Lscala/util/Either;
      #97 (Lscala/util/Try;)Lscala/util/Either;
      #98 5
      #99 1
      #97 (Lscala/util/Try;)Lscala/util/Either;
  1: #106 REF_invokeStatic java/lang/invoke/LambdaMetafactory.altMetafactory:(Ljava/lang/invoke/MethodHandles$Lookup;Ljava/lang/String;Ljava/lang/invoke/MethodType;[Ljava/lang/Object;)Ljava/lang/invoke/CallSite;
    Method arguments:
      #91 (Ljava/lang/Object;)Ljava/lang/Object;
      #138 REF_invokeStatic org/scalatest/concurrent/ScalaFutures$$anon$1.$anonfun$futureValueImpl$1:(Ljava/lang/Object;)Lscala/util/Success;
      #139 (Ljava/lang/Object;)Lscala/util/Success;
      #98 5
      #99 1
      #139 (Ljava/lang/Object;)Lscala/util/Success;
  2: #106 REF_invokeStatic java/lang/invoke/LambdaMetafactory.altMetafactory:(Ljava/lang/invoke/MethodHandles$Lookup;Ljava/lang/String;Ljava/lang/invoke/MethodType;[Ljava/lang/Object;)Ljava/lang/invoke/CallSite;
    Method arguments:
      #91 (Ljava/lang/Object;)Ljava/lang/Object;
      #145 REF_invokeStatic org/scalatest/concurrent/ScalaFutures$$anon$1.$anonfun$futureValueImpl$2:(Ljava/lang/Throwable;)Lscala/util/Success;
      #146 (Ljava/lang/Throwable;)Lscala/util/Success;
      #98 5
      #99 1
      #146 (Ljava/lang/Throwable;)Lscala/util/Success;
  3: #106 REF_invokeStatic java/lang/invoke/LambdaMetafactory.altMetafactory:(Ljava/lang/invoke/MethodHandles$Lookup;Ljava/lang/String;Ljava/lang/invoke/MethodType;[Ljava/lang/Object;)Ljava/lang/invoke/CallSite;
    Method arguments:
      #91 (Ljava/lang/Object;)Ljava/lang/Object;
      #222 REF_invokeStatic org/scalatest/concurrent/ScalaFutures$$anon$1.$anonfun$futureValueImpl$3:(Ljava/lang/Throwable;Lorg/scalatest/exceptions/StackDepthException;)Lscala/Some;
      #224 (Lorg/scalatest/exceptions/StackDepthException;)Lscala/Some;
      #98 5
      #99 1
      #224 (Lorg/scalatest/exceptions/StackDepthException;)Lscala/Some;
  4: #106 REF_invokeStatic java/lang/invoke/LambdaMetafactory.altMetafactory:(Ljava/lang/invoke/MethodHandles$Lookup;Ljava/lang/String;Ljava/lang/invoke/MethodType;[Ljava/lang/Object;)Ljava/lang/invoke/CallSite;
    Method arguments:
      #91 (Ljava/lang/Object;)Ljava/lang/Object;
      #240 REF_invokeStatic org/scalatest/concurrent/ScalaFutures$$anon$1.$anonfun$futureValueImpl$4:(Ljava/lang/Throwable;Lorg/scalatest/exceptions/StackDepthException;)Lscala/Some;
      #224 (Lorg/scalatest/exceptions/StackDepthException;)Lscala/Some;
      #98 5
      #99 1
      #224 (Lorg/scalatest/exceptions/StackDepthException;)Lscala/Some;
  5: #351 REF_invokeStatic scala/runtime/LambdaDeserialize.bootstrap:(Ljava/lang/invoke/MethodHandles$Lookup;Ljava/lang/String;Ljava/lang/invoke/MethodType;[Ljava/lang/invoke/MethodHandle;)Ljava/lang/invoke/CallSite;
    Method arguments:
      #96 REF_invokeStatic org/scalatest/concurrent/ScalaFutures$$anon$1.$anonfun$eitherValue$1:(Lscala/util/Try;)Lscala/util/Either;
      #138 REF_invokeStatic org/scalatest/concurrent/ScalaFutures$$anon$1.$anonfun$futureValueImpl$1:(Ljava/lang/Object;)Lscala/util/Success;
      #145 REF_invokeStatic org/scalatest/concurrent/ScalaFutures$$anon$1.$anonfun$futureValueImpl$2:(Ljava/lang/Throwable;)Lscala/util/Success;
      #222 REF_invokeStatic org/scalatest/concurrent/ScalaFutures$$anon$1.$anonfun$futureValueImpl$3:(Ljava/lang/Throwable;Lorg/scalatest/exceptions/StackDepthException;)Lscala/Some;
      #240 REF_invokeStatic org/scalatest/concurrent/ScalaFutures$$anon$1.$anonfun$futureValueImpl$4:(Ljava/lang/Throwable;Lorg/scalatest/exceptions/StackDepthException;)Lscala/Some;
  ScalaInlineInfo: length = 0x54 (unknown attribute)
   01 01 00 10 00 5C 00 5D 01 00 86 00 87 01 00 8D
   00 8E 01 00 DA 00 DB 01 00 ED 00 DB 01 00 E6 01
   4F 01 00 50 00 51 01 00 37 00 4B 01 00 37 00 46
   01 00 37 00 41 01 00 37 00 38 01 00 78 00 79 01
   00 77 00 76 01 00 75 00 76 01 00 29 00 2A 01 01
   05 01 06 01
  Scala: length = 0x0 (unknown attribute)

