Classfile /Users/mw/Projects/slang-braindump/.jar/jar11/assemble/slang-braindump/assemble/content/org/scalatest/concurrent/SelectorSignaler.class
  Last modified May 29, 2022; size 1315 bytes
  SHA-256 checksum 00e04eeabb3074b8a6285c55596a6ee3a416f4641d72cd70806017d1b953891c
  Compiled from "SelectorSignaler.scala"
public class org.scalatest.concurrent.SelectorSignaler implements org.scalatest.concurrent.Signaler
  minor version: 0
  major version: 52
  flags: (0x0021) ACC_PUBLIC, ACC_SUPER
  this_class: #2                          // org/scalatest/concurrent/SelectorSignaler
  super_class: #4                         // java/lang/Object
  interfaces: 1, fields: 1, methods: 2, attributes: 4
Constant pool:
   #1 = Utf8               org/scalatest/concurrent/SelectorSignaler
   #2 = Class              #1             // org/scalatest/concurrent/SelectorSignaler
   #3 = Utf8               java/lang/Object
   #4 = Class              #3             // java/lang/Object
   #5 = Utf8               org/scalatest/concurrent/Signaler
   #6 = Class              #5             // org/scalatest/concurrent/Signaler
   #7 = Utf8               SelectorSignaler.scala
   #8 = Utf8               Lscala/reflect/ScalaSignature;
   #9 = Utf8               bytes
  #10 = Utf8               \u0006\u0005u2A\u0001C\u0005\u0001!!A1\u0004\u0001B\u0001B\u0003%A\u0004C\u0003\'\u0001\u0011\u0005q\u0005C\u0003+\u0001\u0011\u00051fB\u00038\u0013!\u0005\u0001HB\u0003\t\u0013!\u0005\u0011\bC\u0003\'\u000b\u0011\u0005!\bC\u0003+\u000b\u0011\u00051H\u0001\tTK2,7\r^8s\'&<g.\u00197fe*\u0011!bC\u0001\u000bG>t7-\u001e:sK:$(B\u0001\u0007\u000e\u0003%\u00198-\u00197bi\u0016\u001cHOC\u0001\u000f\u0003\ry\'oZ\u0002\u0001\'\r\u0001\u0011c\u0006\t\u0003%Ui\u0011a\u0005\u0006\u0002)\u0005)1oY1mC&\u0011ac\u0005\u0002\u0007\u0003:L(+\u001a4\u0011\u0005aIR\"A\u0005\n\u0005iI!\u0001C*jO:\fG.\u001a:\u0002\u0011M,G.Z2u_J\u0004\"!\b\u0013\u000e\u0003yQ!a\b\u0011\u0002\u0011\rD\u0017M\u001c8fYNT!!\t\u0012\u0002\u00079LwNC\u0001$\u0003\u0011Q\u0017M^1\n\u0005\u0015r\"\u0001C*fY\u0016\u001cGo\u001c:\u0002\rqJg.\u001b;?)\tA\u0013\u0006\u0005\u0002\u0019\u0001!)1D\u0001a\u00019\u0005)\u0011\r\u001d9msR\u0011Af\f\t\u0003%5J!AL\n\u0003\tUs\u0017\u000e\u001e\u0005\u0006a\r\u0001\r!M\u0001\u000bi\u0016\u001cH\u000f\u00165sK\u0006$\u0007C\u0001\u001a6\u001b\u0005\u0019$B\u0001\u001b#\u0003\u0011a\u0017M\\4\n\u0005Y\u001a$A\u0002+ie\u0016\fG-\u0001\tTK2,7\r^8s\'&<g.\u00197feB\u0011\u0001$B\n\u0003\u000bE!\u0012\u0001\u000f\u000b\u0003QqBQaG\u0004A\u0002q\u0001
  #11 = Utf8               selector
  #12 = Utf8               Ljava/nio/channels/Selector;
  #13 = Utf8               apply
  #14 = Utf8               (Ljava/lang/Thread;)V
  #15 = Utf8               testThread
  #16 = NameAndType        #11:#12        // selector:Ljava/nio/channels/Selector;
  #17 = Fieldref           #2.#16         // org/scalatest/concurrent/SelectorSignaler.selector:Ljava/nio/channels/Selector;
  #18 = Utf8               java/nio/channels/Selector
  #19 = Class              #18            // java/nio/channels/Selector
  #20 = Utf8               wakeup
  #21 = Utf8               ()Ljava/nio/channels/Selector;
  #22 = NameAndType        #20:#21        // wakeup:()Ljava/nio/channels/Selector;
  #23 = Methodref          #19.#22        // java/nio/channels/Selector.wakeup:()Ljava/nio/channels/Selector;
  #24 = Utf8               this
  #25 = Utf8               Lorg/scalatest/concurrent/SelectorSignaler;
  #26 = Utf8               Ljava/lang/Thread;
  #27 = Utf8               <init>
  #28 = Utf8               (Ljava/nio/channels/Selector;)V
  #29 = Utf8               ()V
  #30 = NameAndType        #27:#29        // "<init>":()V
  #31 = Methodref          #4.#30         // java/lang/Object."<init>":()V
  #32 = Utf8               Code
  #33 = Utf8               LineNumberTable
  #34 = Utf8               LocalVariableTable
  #35 = Utf8               MethodParameters
  #36 = Utf8               SourceFile
  #37 = Utf8               RuntimeVisibleAnnotations
  #38 = Utf8               ScalaInlineInfo
  #39 = Utf8               ScalaSig
{
  private final java.nio.channels.Selector selector;
    descriptor: Ljava/nio/channels/Selector;
    flags: (0x0012) ACC_PRIVATE, ACC_FINAL

  public void apply(java.lang.Thread);
    descriptor: (Ljava/lang/Thread;)V
    flags: (0x0001) ACC_PUBLIC
    Code:
      stack=1, locals=2, args_size=2
         0: aload_0
         1: getfield      #17                 // Field selector:Ljava/nio/channels/Selector;
         4: invokevirtual #23                 // Method java/nio/channels/Selector.wakeup:()Ljava/nio/channels/Selector;
         7: pop
         8: return
      LineNumberTable:
        line 36: 0
      LocalVariableTable:
        Start  Length  Slot  Name   Signature
            0       9     0  this   Lorg/scalatest/concurrent/SelectorSignaler;
            0       9     1 testThread   Ljava/lang/Thread;
    MethodParameters:
      Name                           Flags
      testThread                     final

  public org.scalatest.concurrent.SelectorSignaler(java.nio.channels.Selector);
    descriptor: (Ljava/nio/channels/Selector;)V
    flags: (0x0001) ACC_PUBLIC
    Code:
      stack=2, locals=2, args_size=2
         0: aload_0
         1: aload_1
         2: putfield      #17                 // Field selector:Ljava/nio/channels/Selector;
         5: aload_0
         6: invokespecial #31                 // Method java/lang/Object."<init>":()V
         9: return
      LineNumberTable:
        line 28: 0
      LocalVariableTable:
        Start  Length  Slot  Name   Signature
            0      10     0  this   Lorg/scalatest/concurrent/SelectorSignaler;
            0      10     1 selector   Ljava/nio/channels/Selector;
    MethodParameters:
      Name                           Flags
      selector                       final
}
SourceFile: "SelectorSignaler.scala"
RuntimeVisibleAnnotations:
  0: #8(#9=s#10)
    scala.reflect.ScalaSignature(
      bytes="\u0006\u0005u2A\u0001C\u0005\u0001!!A1\u0004\u0001B\u0001B\u0003%A\u0004C\u0003\'\u0001\u0011\u0005q\u0005C\u0003+\u0001\u0011\u00051fB\u00038\u0013!\u0005\u0001HB\u0003\t\u0013!\u0005\u0011\bC\u0003\'\u000b\u0011\u0005!\bC\u0003+\u000b\u0011\u00051H\u0001\tTK2,7\r^8s\'&<g.\u00197fe*\u0011!bC\u0001\u000bG>t7-\u001e:sK:$(B\u0001\u0007\u000e\u0003%\u00198-\u00197bi\u0016\u001cHOC\u0001\u000f\u0003\ry\'oZ\u0002\u0001\'\r\u0001\u0011c\u0006\t\u0003%Ui\u0011a\u0005\u0006\u0002)\u0005)1oY1mC&\u0011ac\u0005\u0002\u0007\u0003:L(+\u001a4\u0011\u0005aIR\"A\u0005\n\u0005iI!\u0001C*jO:\fG.\u001a:\u0002\u0011M,G.Z2u_J\u0004\"!\b\u0013\u000e\u0003yQ!a\b\u0011\u0002\u0011\rD\u0017M\u001c8fYNT!!\t\u0012\u0002\u00079LwNC\u0001$\u0003\u0011Q\u0017M^1\n\u0005\u0015r\"\u0001C*fY\u0016\u001cGo\u001c:\u0002\rqJg.\u001b;?)\tA\u0013\u0006\u0005\u0002\u0019\u0001!)1D\u0001a\u00019\u0005)\u0011\r\u001d9msR\u0011Af\f\t\u0003%5J!AL\n\u0003\tUs\u0017\u000e\u001e\u0005\u0006a\r\u0001\r!M\u0001\u000bi\u0016\u001cH\u000f\u00165sK\u0006$\u0007C\u0001\u001a6\u001b\u0005\u0019$B\u0001\u001b#\u0003\u0011a\u0017M\\4\n\u0005Y\u001a$A\u0002+ie\u0016\fG-\u0001\tTK2,7\r^8s\'&<g.\u00197feB\u0011\u0001$B\n\u0003\u000bE!\u0012\u0001\u000f\u000b\u0003QqBQaG\u0004A\u0002q\u0001"
    )
  ScalaInlineInfo: length = 0xE (unknown attribute)
   01 00 00 02 00 1B 00 1C 00 00 0D 00 0E 00
  ScalaSig: length = 0x3 (unknown attribute)
   05 02 00
