Classfile /Users/mw/Projects/slang-braindump/.jar/jar11/assemble/slang-braindump/assemble/content/org/scalatest/concurrent/SerialExecutionContext.class
  Last modified May 29, 2022; size 2976 bytes
  SHA-256 checksum 9a6c37ffaf48112d1c846d4c6803378c672dd62e0565cd557527739929f9f6a3
  Compiled from "SerialExecutionContext.scala"
public class org.scalatest.concurrent.SerialExecutionContext implements scala.concurrent.ExecutionContext
  minor version: 0
  major version: 52
  flags: (0x0021) ACC_PUBLIC, ACC_SUPER
  this_class: #2                          // org/scalatest/concurrent/SerialExecutionContext
  super_class: #4                         // java/lang/Object
  interfaces: 1, fields: 1, methods: 7, attributes: 4
Constant pool:
    #1 = Utf8               org/scalatest/concurrent/SerialExecutionContext
    #2 = Class              #1            // org/scalatest/concurrent/SerialExecutionContext
    #3 = Utf8               java/lang/Object
    #4 = Class              #3            // java/lang/Object
    #5 = Utf8               scala/concurrent/ExecutionContext
    #6 = Class              #5            // scala/concurrent/ExecutionContext
    #7 = Utf8               SerialExecutionContext.scala
    #8 = Utf8               Lscala/reflect/ScalaSignature;
    #9 = Utf8               bytes
   #10 = Utf8               \u0006\u0005i3Q\u0001C\u0005\u0001\u0017=AQa\u0007\u0001\u0005\u0002uAq\u0001\t\u0001C\u0002\u00135\u0011\u0005\u0003\u0004/\u0001\u0001\u0006iA\t\u0005\u0006_\u0001!\t\u0001\r\u0005\u0006m\u0001!\ta\u000e\u0005\u0006\r\u0002!\ta\u0012\u0005\u0006!\u0002!I!\u0015\u0002\u0017\'\u0016\u0014\u0018.\u00197Fq\u0016\u001cW\u000f^5p]\u000e{g\u000e^3yi*\u0011!bC\u0001\u000bG>t7-\u001e:sK:$(B\u0001\u0007\u000e\u0003%\u00198-\u00197bi\u0016\u001cHOC\u0001\u000f\u0003\ry\'oZ\n\u0004\u0001A1\u0002CA\t\u0015\u001b\u0005\u0011\"\"A\n\u0002\u000bM\u001c\u0017\r\\1\n\u0005U\u0011\"AB!osJ+g\r\u0005\u0002\u001835\t\u0001D\u0003\u0002\u000b%%\u0011!\u0004\u0007\u0002\u0011\u000bb,7-\u001e;j_:\u001cuN\u001c;fqR\fa\u0001P5oSRt4\u0001\u0001\u000b\u0002=A\u0011q\u0004A\u0007\u0002\u0013\u0005)\u0011/^3vKV\t!\u0005E\u0002$I\u0019j\u0011aC\u0005\u0003K-\u00111\u0003T5oW\u0016$\'\t\\8dW&tw-U;fk\u0016\u0004\"a\n\u0017\u000e\u0003!R!!\u000b\u0016\u0002\t1\fgn\u001a\u0006\u0002W\u0005!!.\u0019<b\u0013\ti\u0003F\u0001\u0005Sk:t\u0017M\u00197f\u0003\u0019\tX/Z;fA\u00059Q\r_3dkR,GCA\u00195!\t\t\"\'\u0003\u00024%\t!QK\\5u\u0011\u0015)D\u00011\u0001\'\u0003!\u0011XO\u001c8bE2,\u0017!\u0004:fa>\u0014HOR1jYV\u0014X\r\u0006\u00022q!)\u0011(\u0002a\u0001u\u0005\tA\u000f\u0005\u0002<\u0007:\u0011A(\u0011\b\u0003{\u0001k\u0011A\u0010\u0006\u0003\u007fq\ta\u0001\u0010:p_Rt\u0014\"A\n\n\u0005\t\u0013\u0012a\u00029bG.\fw-Z\u0005\u0003\t\u0016\u0013\u0011\u0002\u00165s_^\f\'\r\\3\u000b\u0005\t\u0013\u0012A\u0002:v]:{w\u000f\u0006\u00022\u0011\")\u0011J\u0002a\u0001\u0015\u00061a-\u001e;ve\u0016\u00042aF&N\u0013\ta\u0005D\u0001\u0004GkR,(/\u001a\t\u0003G9K!aT\u0006\u0003\u000f=+HoY8nK\u0006I!/Z2Sk:tun\u001e\u000b\u0003cICQ!S\u0004A\u0002)C#a\u0002+\u0011\u0005UCV\"\u0001,\u000b\u0005]\u0013\u0012AC1o]>$\u0018\r^5p]&\u0011\u0011L\u0016\u0002\bi\u0006LGN]3d\u0001
   #11 = Utf8               queue
   #12 = Utf8               Lorg/scalatest/LinkedBlockingQueue;
   #13 = Utf8               Lorg/scalatest/LinkedBlockingQueue<Ljava/lang/Runnable;>;
   #14 = Utf8               prepare
   #15 = Utf8               ()Lscala/concurrent/ExecutionContext;
   #16 = Utf8               prepare$
   #17 = Utf8               (Lscala/concurrent/ExecutionContext;)Lscala/concurrent/ExecutionContext;
   #18 = NameAndType        #16:#17       // prepare$:(Lscala/concurrent/ExecutionContext;)Lscala/concurrent/ExecutionContext;
   #19 = InterfaceMethodref #6.#18        // scala/concurrent/ExecutionContext.prepare$:(Lscala/concurrent/ExecutionContext;)Lscala/concurrent/ExecutionContext;
   #20 = Utf8               this
   #21 = Utf8               Lorg/scalatest/concurrent/SerialExecutionContext;
   #22 = Utf8               ()Lorg/scalatest/LinkedBlockingQueue;
   #23 = Utf8               ()Lorg/scalatest/LinkedBlockingQueue<Ljava/lang/Runnable;>;
   #24 = NameAndType        #11:#12       // queue:Lorg/scalatest/LinkedBlockingQueue;
   #25 = Fieldref           #2.#24        // org/scalatest/concurrent/SerialExecutionContext.queue:Lorg/scalatest/LinkedBlockingQueue;
   #26 = Utf8               execute
   #27 = Utf8               (Ljava/lang/Runnable;)V
   #28 = Utf8               runnable
   #29 = NameAndType        #11:#22       // queue:()Lorg/scalatest/LinkedBlockingQueue;
   #30 = Methodref          #2.#29        // org/scalatest/concurrent/SerialExecutionContext.queue:()Lorg/scalatest/LinkedBlockingQueue;
   #31 = Utf8               org/scalatest/LinkedBlockingQueue
   #32 = Class              #31           // org/scalatest/LinkedBlockingQueue
   #33 = Utf8               put
   #34 = Utf8               (Ljava/lang/Object;)V
   #35 = NameAndType        #33:#34       // put:(Ljava/lang/Object;)V
   #36 = Methodref          #32.#35       // org/scalatest/LinkedBlockingQueue.put:(Ljava/lang/Object;)V
   #37 = Utf8               Ljava/lang/Runnable;
   #38 = Utf8               reportFailure
   #39 = Utf8               (Ljava/lang/Throwable;)V
   #40 = Utf8               t
   #41 = Utf8               java/lang/Throwable
   #42 = Class              #41           // java/lang/Throwable
   #43 = Utf8               printStackTrace
   #44 = Utf8               ()V
   #45 = NameAndType        #43:#44       // printStackTrace:()V
   #46 = Methodref          #42.#45       // java/lang/Throwable.printStackTrace:()V
   #47 = Utf8               Ljava/lang/Throwable;
   #48 = Utf8               runNow
   #49 = Utf8               (Lscala/concurrent/Future;)V
   #50 = Utf8               (Lscala/concurrent/Future<Lorg/scalatest/Outcome;>;)V
   #51 = Utf8               future
   #52 = Utf8               recRunNow
   #53 = NameAndType        #52:#49       // recRunNow:(Lscala/concurrent/Future;)V
   #54 = Methodref          #2.#53        // org/scalatest/concurrent/SerialExecutionContext.recRunNow:(Lscala/concurrent/Future;)V
   #55 = Utf8               Lscala/concurrent/Future;
   #56 = Utf8               scala/concurrent/Future
   #57 = Class              #56           // scala/concurrent/Future
   #58 = Utf8               isCompleted
   #59 = Utf8               ()Z
   #60 = NameAndType        #58:#59       // isCompleted:()Z
   #61 = InterfaceMethodref #57.#60       // scala/concurrent/Future.isCompleted:()Z
   #62 = Utf8               size
   #63 = Utf8               ()I
   #64 = NameAndType        #62:#63       // size:()I
   #65 = Methodref          #32.#64       // org/scalatest/LinkedBlockingQueue.size:()I
   #66 = Utf8               scala/runtime/BoxedUnit
   #67 = Class              #66           // scala/runtime/BoxedUnit
   #68 = Utf8               UNIT
   #69 = Utf8               Lscala/runtime/BoxedUnit;
   #70 = NameAndType        #68:#69       // UNIT:Lscala/runtime/BoxedUnit;
   #71 = Fieldref           #67.#70       // scala/runtime/BoxedUnit.UNIT:Lscala/runtime/BoxedUnit;
   #72 = Utf8               take
   #73 = Utf8               ()Ljava/lang/Object;
   #74 = NameAndType        #72:#73       // take:()Ljava/lang/Object;
   #75 = Methodref          #32.#74       // org/scalatest/LinkedBlockingQueue.take:()Ljava/lang/Object;
   #76 = Utf8               java/lang/Runnable
   #77 = Class              #76           // java/lang/Runnable
   #78 = Utf8               run
   #79 = NameAndType        #78:#44       // run:()V
   #80 = InterfaceMethodref #77.#79       // java/lang/Runnable.run:()V
   #81 = Utf8               task
   #82 = Utf8               <init>
   #83 = NameAndType        #82:#44       // "<init>":()V
   #84 = Methodref          #4.#83        // java/lang/Object."<init>":()V
   #85 = Utf8               $init$
   #86 = Utf8               (Lscala/concurrent/ExecutionContext;)V
   #87 = NameAndType        #85:#86       // $init$:(Lscala/concurrent/ExecutionContext;)V
   #88 = InterfaceMethodref #6.#87        // scala/concurrent/ExecutionContext.$init$:(Lscala/concurrent/ExecutionContext;)V
   #89 = Methodref          #32.#83       // org/scalatest/LinkedBlockingQueue."<init>":()V
   #90 = Utf8               Signature
   #91 = Utf8               Code
   #92 = Utf8               LineNumberTable
   #93 = Utf8               LocalVariableTable
   #94 = Utf8               Deprecated
   #95 = Utf8               MethodParameters
   #96 = Utf8               StackMapTable
   #97 = Utf8               SourceFile
   #98 = Utf8               RuntimeVisibleAnnotations
   #99 = Utf8               ScalaInlineInfo
  #100 = Utf8               ScalaSig
{
  private final org.scalatest.LinkedBlockingQueue<java.lang.Runnable> queue;
    descriptor: Lorg/scalatest/LinkedBlockingQueue;
    flags: (0x0012) ACC_PRIVATE, ACC_FINAL
    Signature: #13                          // Lorg/scalatest/LinkedBlockingQueue<Ljava/lang/Runnable;>;

  public scala.concurrent.ExecutionContext prepare();
    descriptor: ()Lscala/concurrent/ExecutionContext;
    flags: (0x0001) ACC_PUBLIC
    Code:
      stack=1, locals=1, args_size=1
         0: aload_0
         1: invokestatic  #19                 // InterfaceMethod scala/concurrent/ExecutionContext.prepare$:(Lscala/concurrent/ExecutionContext;)Lscala/concurrent/ExecutionContext;
         4: areturn
      LineNumberTable:
        line 32: 0
      LocalVariableTable:
        Start  Length  Slot  Name   Signature
            0       5     0  this   Lorg/scalatest/concurrent/SerialExecutionContext;
    Deprecated: true

  private final org.scalatest.LinkedBlockingQueue<java.lang.Runnable> queue();
    descriptor: ()Lorg/scalatest/LinkedBlockingQueue;
    flags: (0x0012) ACC_PRIVATE, ACC_FINAL
    Code:
      stack=1, locals=1, args_size=1
         0: aload_0
         1: getfield      #25                 // Field queue:Lorg/scalatest/LinkedBlockingQueue;
         4: areturn
      LineNumberTable:
        line 38: 0
      LocalVariableTable:
        Start  Length  Slot  Name   Signature
            0       5     0  this   Lorg/scalatest/concurrent/SerialExecutionContext;
    Signature: #23                          // ()Lorg/scalatest/LinkedBlockingQueue<Ljava/lang/Runnable;>;

  public void execute(java.lang.Runnable);
    descriptor: (Ljava/lang/Runnable;)V
    flags: (0x0001) ACC_PUBLIC
    Code:
      stack=2, locals=2, args_size=2
         0: aload_0
         1: invokespecial #30                 // Method queue:()Lorg/scalatest/LinkedBlockingQueue;
         4: aload_1
         5: invokevirtual #36                 // Method org/scalatest/LinkedBlockingQueue.put:(Ljava/lang/Object;)V
         8: return
      LineNumberTable:
        line 41: 0
      LocalVariableTable:
        Start  Length  Slot  Name   Signature
            0       9     0  this   Lorg/scalatest/concurrent/SerialExecutionContext;
            0       9     1 runnable   Ljava/lang/Runnable;
    MethodParameters:
      Name                           Flags
      runnable                       final

  public void reportFailure(java.lang.Throwable);
    descriptor: (Ljava/lang/Throwable;)V
    flags: (0x0001) ACC_PUBLIC
    Code:
      stack=1, locals=2, args_size=2
         0: aload_1
         1: invokevirtual #46                 // Method java/lang/Throwable.printStackTrace:()V
         4: return
      LineNumberTable:
        line 49: 0
      LocalVariableTable:
        Start  Length  Slot  Name   Signature
            0       5     0  this   Lorg/scalatest/concurrent/SerialExecutionContext;
            0       5     1     t   Ljava/lang/Throwable;
    MethodParameters:
      Name                           Flags
      t                              final

  public void runNow(scala.concurrent.Future<org.scalatest.Outcome>);
    descriptor: (Lscala/concurrent/Future;)V
    flags: (0x0001) ACC_PUBLIC
    Code:
      stack=2, locals=2, args_size=2
         0: aload_0
         1: aload_1
         2: invokespecial #54                 // Method recRunNow:(Lscala/concurrent/Future;)V
         5: return
      LineNumberTable:
        line 111: 0
      LocalVariableTable:
        Start  Length  Slot  Name   Signature
            0       6     0  this   Lorg/scalatest/concurrent/SerialExecutionContext;
            0       6     1 future   Lscala/concurrent/Future;
    Signature: #50                          // (Lscala/concurrent/Future<Lorg/scalatest/Outcome;>;)V
    MethodParameters:
      Name                           Flags
      future                         final

  private void recRunNow(scala.concurrent.Future<org.scalatest.Outcome>);
    descriptor: (Lscala/concurrent/Future;)V
    flags: (0x0002) ACC_PRIVATE
    Code:
      stack=2, locals=4, args_size=2
         0: aload_1
         1: invokeinterface #61,  1           // InterfaceMethod scala/concurrent/Future.isCompleted:()Z
         6: ifeq          26
         9: aload_0
        10: invokespecial #30                 // Method queue:()Lorg/scalatest/LinkedBlockingQueue;
        13: invokevirtual #65                 // Method org/scalatest/LinkedBlockingQueue.size:()I
        16: iconst_0
        17: if_icmpne     26
        20: getstatic     #71                 // Field scala/runtime/BoxedUnit.UNIT:Lscala/runtime/BoxedUnit;
        23: goto          48
        26: aload_0
        27: invokespecial #30                 // Method queue:()Lorg/scalatest/LinkedBlockingQueue;
        30: invokevirtual #75                 // Method org/scalatest/LinkedBlockingQueue.take:()Ljava/lang/Object;
        33: checkcast     #77                 // class java/lang/Runnable
        36: astore_3
        37: aload_3
        38: invokeinterface #80,  1           // InterfaceMethod java/lang/Runnable.run:()V
        43: aload_1
        44: astore_1
        45: goto          0
        48: pop
        49: return
      StackMapTable: number_of_entries = 3
        frame_type = 0 /* same */
        frame_type = 25 /* same */
        frame_type = 85 /* same_locals_1_stack_item */
          stack = [ class scala/runtime/BoxedUnit ]
      LineNumberTable:
        line 115: 0
        line 119: 26
        line 120: 37
        line 121: 43
        line 115: 49
      LocalVariableTable:
        Start  Length  Slot  Name   Signature
           37      11     3  task   Ljava/lang/Runnable;
            0      50     0  this   Lorg/scalatest/concurrent/SerialExecutionContext;
            0      50     1 future   Lscala/concurrent/Future;
    Signature: #50                          // (Lscala/concurrent/Future<Lorg/scalatest/Outcome;>;)V
    MethodParameters:
      Name                           Flags
      future                         final

  public org.scalatest.concurrent.SerialExecutionContext();
    descriptor: ()V
    flags: (0x0001) ACC_PUBLIC
    Code:
      stack=3, locals=1, args_size=1
         0: aload_0
         1: invokespecial #84                 // Method java/lang/Object."<init>":()V
         4: aload_0
         5: invokestatic  #88                 // InterfaceMethod scala/concurrent/ExecutionContext.$init$:(Lscala/concurrent/ExecutionContext;)V
         8: aload_0
         9: new           #32                 // class org/scalatest/LinkedBlockingQueue
        12: dup
        13: invokespecial #89                 // Method org/scalatest/LinkedBlockingQueue."<init>":()V
        16: putfield      #25                 // Field queue:Lorg/scalatest/LinkedBlockingQueue;
        19: return
      LineNumberTable:
        line 32: 0
        line 38: 8
        line 32: 19
      LocalVariableTable:
        Start  Length  Slot  Name   Signature
            0      20     0  this   Lorg/scalatest/concurrent/SerialExecutionContext;
}
SourceFile: "SerialExecutionContext.scala"
RuntimeVisibleAnnotations:
  0: #8(#9=s#10)
    scala.reflect.ScalaSignature(
      bytes="\u0006\u0005i3Q\u0001C\u0005\u0001\u0017=AQa\u0007\u0001\u0005\u0002uAq\u0001\t\u0001C\u0002\u00135\u0011\u0005\u0003\u0004/\u0001\u0001\u0006iA\t\u0005\u0006_\u0001!\t\u0001\r\u0005\u0006m\u0001!\ta\u000e\u0005\u0006\r\u0002!\ta\u0012\u0005\u0006!\u0002!I!\u0015\u0002\u0017\'\u0016\u0014\u0018.\u00197Fq\u0016\u001cW\u000f^5p]\u000e{g\u000e^3yi*\u0011!bC\u0001\u000bG>t7-\u001e:sK:$(B\u0001\u0007\u000e\u0003%\u00198-\u00197bi\u0016\u001cHOC\u0001\u000f\u0003\ry\'oZ\n\u0004\u0001A1\u0002CA\t\u0015\u001b\u0005\u0011\"\"A\n\u0002\u000bM\u001c\u0017\r\\1\n\u0005U\u0011\"AB!osJ+g\r\u0005\u0002\u001835\t\u0001D\u0003\u0002\u000b%%\u0011!\u0004\u0007\u0002\u0011\u000bb,7-\u001e;j_:\u001cuN\u001c;fqR\fa\u0001P5oSRt4\u0001\u0001\u000b\u0002=A\u0011q\u0004A\u0007\u0002\u0013\u0005)\u0011/^3vKV\t!\u0005E\u0002$I\u0019j\u0011aC\u0005\u0003K-\u00111\u0003T5oW\u0016$\'\t\\8dW&tw-U;fk\u0016\u0004\"a\n\u0017\u000e\u0003!R!!\u000b\u0016\u0002\t1\fgn\u001a\u0006\u0002W\u0005!!.\u0019<b\u0013\ti\u0003F\u0001\u0005Sk:t\u0017M\u00197f\u0003\u0019\tX/Z;fA\u00059Q\r_3dkR,GCA\u00195!\t\t\"\'\u0003\u00024%\t!QK\\5u\u0011\u0015)D\u00011\u0001\'\u0003!\u0011XO\u001c8bE2,\u0017!\u0004:fa>\u0014HOR1jYV\u0014X\r\u0006\u00022q!)\u0011(\u0002a\u0001u\u0005\tA\u000f\u0005\u0002<\u0007:\u0011A(\u0011\b\u0003{\u0001k\u0011A\u0010\u0006\u0003\u007fq\ta\u0001\u0010:p_Rt\u0014\"A\n\n\u0005\t\u0013\u0012a\u00029bG.\fw-Z\u0005\u0003\t\u0016\u0013\u0011\u0002\u00165s_^\f\'\r\\3\u000b\u0005\t\u0013\u0012A\u0002:v]:{w\u000f\u0006\u00022\u0011\")\u0011J\u0002a\u0001\u0015\u00061a-\u001e;ve\u0016\u00042aF&N\u0013\ta\u0005D\u0001\u0004GkR,(/\u001a\t\u0003G9K!aT\u0006\u0003\u000f=+HoY8nK\u0006I!/Z2Sk:tun\u001e\u000b\u0003cICQ!S\u0004A\u0002)C#a\u0002+\u0011\u0005UCV\"\u0001,\u000b\u0005]\u0013\u0012AC1o]>$\u0018\r^5p]&\u0011\u0011L\u0016\u0002\bi\u0006LGN]3d\u0001"
    )
  ScalaInlineInfo: length = 0x27 (unknown attribute)
   01 00 00 07 00 52 00 2C 00 00 1A 00 1B 00 00 0E
   00 0F 00 00 0B 00 16 01 00 34 00 31 01 00 26 00
   27 00 00 30 00 31 00
  ScalaSig: length = 0x3 (unknown attribute)
   05 02 00
