Classfile /Users/mw/Projects/slang-braindump/.jar/jar11/assemble/slang-braindump/assemble/content/org/scalatest/concurrent/Waiters$Waiter.class
  Last modified May 29, 2022; size 7301 bytes
  SHA-256 checksum 70ae93b8ab5903d37ebde3a98adb077766f9b0cedcc364568b023446644c6c68
  Compiled from "Waiters.scala"
public class org.scalatest.concurrent.Waiters$Waiter
  minor version: 0
  major version: 52
  flags: (0x0021) ACC_PUBLIC, ACC_SUPER
  this_class: #2                          // org/scalatest/concurrent/Waiters$Waiter
  super_class: #4                         // java/lang/Object
  interfaces: 0, fields: 4, methods: 19, attributes: 5
Constant pool:
    #1 = Utf8               org/scalatest/concurrent/Waiters$Waiter
    #2 = Class              #1            // org/scalatest/concurrent/Waiters$Waiter
    #3 = Utf8               java/lang/Object
    #4 = Class              #3            // java/lang/Object
    #5 = Utf8               Waiters.scala
    #6 = Utf8               java/lang/invoke/MethodHandles$Lookup
    #7 = Class              #6            // java/lang/invoke/MethodHandles$Lookup
    #8 = Utf8               java/lang/invoke/MethodHandles
    #9 = Class              #8            // java/lang/invoke/MethodHandles
   #10 = Utf8               Lookup
   #11 = Utf8               org/scalatest/concurrent/AbstractPatienceConfiguration$PatienceConfig
   #12 = Class              #11           // org/scalatest/concurrent/AbstractPatienceConfiguration$PatienceConfig
   #13 = Utf8               org/scalatest/concurrent/AbstractPatienceConfiguration
   #14 = Class              #13           // org/scalatest/concurrent/AbstractPatienceConfiguration
   #15 = Utf8               PatienceConfig
   #16 = Utf8               org/scalatest/concurrent/PatienceConfiguration$Timeout
   #17 = Class              #16           // org/scalatest/concurrent/PatienceConfiguration$Timeout
   #18 = Utf8               org/scalatest/concurrent/PatienceConfiguration
   #19 = Class              #18           // org/scalatest/concurrent/PatienceConfiguration
   #20 = Utf8               Timeout
   #21 = Utf8               org/scalatest/concurrent/Waiters$Dismissals
   #22 = Class              #21           // org/scalatest/concurrent/Waiters$Dismissals
   #23 = Utf8               org/scalatest/concurrent/Waiters
   #24 = Class              #23           // org/scalatest/concurrent/Waiters
   #25 = Utf8               Dismissals
   #26 = Utf8               Waiter
   #27 = Utf8               creatingThread
   #28 = Utf8               Ljava/lang/Thread;
   #29 = Utf8               dismissedCount
   #30 = Utf8               I
   #31 = Utf8               thrown
   #32 = Utf8               Lscala/Option;
   #33 = Utf8               Lscala/Option<Ljava/lang/Throwable;>;
   #34 = Utf8               $outer
   #35 = Utf8               Lorg/scalatest/concurrent/Waiters;
   #36 = Utf8               ()Ljava/lang/Thread;
   #37 = NameAndType        #27:#28       // creatingThread:Ljava/lang/Thread;
   #38 = Fieldref           #2.#37        // org/scalatest/concurrent/Waiters$Waiter.creatingThread:Ljava/lang/Thread;
   #39 = Utf8               this
   #40 = Utf8               Lorg/scalatest/concurrent/Waiters$Waiter;
   #41 = Utf8               ()I
   #42 = NameAndType        #29:#30       // dismissedCount:I
   #43 = Fieldref           #2.#42        // org/scalatest/concurrent/Waiters$Waiter.dismissedCount:I
   #44 = Utf8               dismissedCount_$eq
   #45 = Utf8               (I)V
   #46 = Utf8               x$1
   #47 = Utf8               ()Lscala/Option;
   #48 = Utf8               ()Lscala/Option<Ljava/lang/Throwable;>;
   #49 = NameAndType        #31:#32       // thrown:Lscala/Option;
   #50 = Fieldref           #2.#49        // org/scalatest/concurrent/Waiters$Waiter.thrown:Lscala/Option;
   #51 = Utf8               thrown_$eq
   #52 = Utf8               (Lscala/Option;)V
   #53 = Utf8               (Lscala/Option<Ljava/lang/Throwable;>;)V
   #54 = Utf8               setThrownIfEmpty
   #55 = Utf8               (Ljava/lang/Throwable;)V
   #56 = Utf8               t
   #57 = NameAndType        #31:#47       // thrown:()Lscala/Option;
   #58 = Methodref          #2.#57        // org/scalatest/concurrent/Waiters$Waiter.thrown:()Lscala/Option;
   #59 = Utf8               scala/Option
   #60 = Class              #59           // scala/Option
   #61 = Utf8               isEmpty
   #62 = Utf8               ()Z
   #63 = NameAndType        #61:#62       // isEmpty:()Z
   #64 = Methodref          #60.#63       // scala/Option.isEmpty:()Z
   #65 = Utf8               scala/Some
   #66 = Class              #65           // scala/Some
   #67 = Utf8               <init>
   #68 = Utf8               (Ljava/lang/Object;)V
   #69 = NameAndType        #67:#68       // "<init>":(Ljava/lang/Object;)V
   #70 = Methodref          #66.#69       // scala/Some."<init>":(Ljava/lang/Object;)V
   #71 = NameAndType        #51:#52       // thrown_$eq:(Lscala/Option;)V
   #72 = Methodref          #2.#71        // org/scalatest/concurrent/Waiters$Waiter.thrown_$eq:(Lscala/Option;)V
   #73 = Utf8               Ljava/lang/Throwable;
   #74 = Utf8               apply
   #75 = Utf8               (Lscala/Function0;)V
   #76 = Utf8               (Lscala/Function0<Lscala/runtime/BoxedUnit;>;)V
   #77 = Utf8               fun
   #78 = Utf8               java/lang/Throwable
   #79 = Class              #78           // java/lang/Throwable
   #80 = Utf8               scala/Function0
   #81 = Class              #80           // scala/Function0
   #82 = Utf8               apply$mcV$sp
   #83 = Utf8               ()V
   #84 = NameAndType        #82:#83       // apply$mcV$sp:()V
   #85 = InterfaceMethodref #81.#84       // scala/Function0.apply$mcV$sp:()V
   #86 = NameAndType        #54:#55       // setThrownIfEmpty:(Ljava/lang/Throwable;)V
   #87 = Methodref          #2.#86        // org/scalatest/concurrent/Waiters$Waiter.setThrownIfEmpty:(Ljava/lang/Throwable;)V
   #88 = Utf8               notifyAll
   #89 = NameAndType        #88:#83       // notifyAll:()V
   #90 = Methodref          #2.#89        // org/scalatest/concurrent/Waiters$Waiter.notifyAll:()V
   #91 = Utf8               Lscala/Function0;
   #92 = Utf8               awaitImpl
   #93 = Utf8               (Lorg/scalatest/time/Span;Lorg/scalactic/source/Position;I)V
   #94 = Utf8               timeout
   #95 = Utf8               pos
   #96 = Utf8               dismissals
   #97 = Utf8               java/lang/Thread
   #98 = Class              #97           // java/lang/Thread
   #99 = Utf8               currentThread
  #100 = NameAndType        #99:#36       // currentThread:()Ljava/lang/Thread;
  #101 = Methodref          #98.#100      // java/lang/Thread.currentThread:()Ljava/lang/Thread;
  #102 = NameAndType        #27:#36       // creatingThread:()Ljava/lang/Thread;
  #103 = Methodref          #2.#102       // org/scalatest/concurrent/Waiters$Waiter.creatingThread:()Ljava/lang/Thread;
  #104 = Utf8               equals
  #105 = Utf8               (Ljava/lang/Object;)Z
  #106 = NameAndType        #104:#105     // equals:(Ljava/lang/Object;)Z
  #107 = Methodref          #4.#106       // java/lang/Object.equals:(Ljava/lang/Object;)Z
  #108 = Utf8               org/scalatest/exceptions/NotAllowedException
  #109 = Class              #108          // org/scalatest/exceptions/NotAllowedException
  #110 = Utf8               org/scalatest/Resources$
  #111 = Class              #110          // org/scalatest/Resources$
  #112 = Utf8               MODULE$
  #113 = Utf8               Lorg/scalatest/Resources$;
  #114 = NameAndType        #112:#113     // MODULE$:Lorg/scalatest/Resources$;
  #115 = Fieldref           #111.#114     // org/scalatest/Resources$.MODULE$:Lorg/scalatest/Resources$;
  #116 = Utf8               awaitMustBeCalledOnCreatingThread
  #117 = Utf8               ()Ljava/lang/String;
  #118 = NameAndType        #116:#117     // awaitMustBeCalledOnCreatingThread:()Ljava/lang/String;
  #119 = Methodref          #111.#118     // org/scalatest/Resources$.awaitMustBeCalledOnCreatingThread:()Ljava/lang/String;
  #120 = Utf8               scala/None$
  #121 = Class              #120          // scala/None$
  #122 = Utf8               Lscala/None$;
  #123 = NameAndType        #112:#122     // MODULE$:Lscala/None$;
  #124 = Fieldref           #121.#123     // scala/None$.MODULE$:Lscala/None$;
  #125 = Utf8               (Ljava/lang/String;Lscala/Option;Lorg/scalactic/source/Position;)V
  #126 = NameAndType        #67:#125      // "<init>":(Ljava/lang/String;Lscala/Option;Lorg/scalactic/source/Position;)V
  #127 = Methodref          #109.#126     // org/scalatest/exceptions/NotAllowedException."<init>":(Ljava/lang/String;Lscala/Option;Lorg/scalactic/source/Position;)V
  #128 = Utf8               java/lang/System
  #129 = Class              #128          // java/lang/System
  #130 = Utf8               nanoTime
  #131 = Utf8               ()J
  #132 = NameAndType        #130:#131     // nanoTime:()J
  #133 = Methodref          #129.#132     // java/lang/System.nanoTime:()J
  #134 = Utf8               org/scalatest/time/Span
  #135 = Class              #134          // org/scalatest/time/Span
  #136 = Utf8               totalNanos
  #137 = NameAndType        #136:#131     // totalNanos:()J
  #138 = Methodref          #135.#137     // org/scalatest/time/Span.totalNanos:()J
  #139 = NameAndType        #29:#41       // dismissedCount:()I
  #140 = Methodref          #2.#139       // org/scalatest/concurrent/Waiters$Waiter.dismissedCount:()I
  #141 = Utf8               timedOut$1
  #142 = Utf8               (J)Z
  #143 = NameAndType        #141:#142     // timedOut$1:(J)Z
  #144 = Methodref          #2.#143       // org/scalatest/concurrent/Waiters$Waiter.timedOut$1:(J)Z
  #145 = Utf8               org/scalatest/time/Span$
  #146 = Class              #145          // org/scalatest/time/Span$
  #147 = Utf8               Lorg/scalatest/time/Span$;
  #148 = NameAndType        #112:#147     // MODULE$:Lorg/scalatest/time/Span$;
  #149 = Fieldref           #146.#148     // org/scalatest/time/Span$.MODULE$:Lorg/scalatest/time/Span$;
  #150 = Utf8               org/scalatest/time/Nanoseconds$
  #151 = Class              #150          // org/scalatest/time/Nanoseconds$
  #152 = Utf8               Lorg/scalatest/time/Nanoseconds$;
  #153 = NameAndType        #112:#152     // MODULE$:Lorg/scalatest/time/Nanoseconds$;
  #154 = Fieldref           #151.#153     // org/scalatest/time/Nanoseconds$.MODULE$:Lorg/scalatest/time/Nanoseconds$;
  #155 = Utf8               (JLorg/scalatest/time/Units;)Lorg/scalatest/time/Span;
  #156 = NameAndType        #74:#155      // apply:(JLorg/scalatest/time/Units;)Lorg/scalatest/time/Span;
  #157 = Methodref          #146.#156     // org/scalatest/time/Span$.apply:(JLorg/scalatest/time/Units;)Lorg/scalatest/time/Span;
  #158 = Utf8               Zero
  #159 = Utf8               ()Lorg/scalatest/time/Span;
  #160 = NameAndType        #158:#159     // Zero:()Lorg/scalatest/time/Span;
  #161 = Methodref          #146.#160     // org/scalatest/time/Span$.Zero:()Lorg/scalatest/time/Span;
  #162 = Utf8               millisPart
  #163 = NameAndType        #162:#131     // millisPart:()J
  #164 = Methodref          #135.#163     // org/scalatest/time/Span.millisPart:()J
  #165 = Utf8               nanosPart
  #166 = NameAndType        #165:#41      // nanosPart:()I
  #167 = Methodref          #135.#166     // org/scalatest/time/Span.nanosPart:()I
  #168 = Utf8               wait
  #169 = Utf8               (JI)V
  #170 = NameAndType        #168:#169     // wait:(JI)V
  #171 = Methodref          #2.#170       // org/scalatest/concurrent/Waiters$Waiter.wait:(JI)V
  #172 = Utf8               isDefined
  #173 = NameAndType        #172:#62      // isDefined:()Z
  #174 = Methodref          #60.#173      // scala/Option.isDefined:()Z
  #175 = Utf8               get
  #176 = Utf8               ()Ljava/lang/Object;
  #177 = NameAndType        #175:#176     // get:()Ljava/lang/Object;
  #178 = Methodref          #60.#177      // scala/Option.get:()Ljava/lang/Object;
  #179 = NameAndType        #44:#45       // dismissedCount_$eq:(I)V
  #180 = Methodref          #2.#179       // org/scalatest/concurrent/Waiters$Waiter.dismissedCount_$eq:(I)V
  #181 = Utf8               org/scalatest/exceptions/TestFailedException
  #182 = Class              #181          // org/scalatest/exceptions/TestFailedException
  #183 = Utf8               (Ljava/lang/Object;)Ljava/lang/Object;
  #184 = MethodType         #183          //  (Ljava/lang/Object;)Ljava/lang/Object;
  #185 = Utf8               $anonfun$awaitImpl$1
  #186 = Utf8               (Lorg/scalatest/exceptions/StackDepthException;)Lscala/Some;
  #187 = NameAndType        #185:#186     // $anonfun$awaitImpl$1:(Lorg/scalatest/exceptions/StackDepthException;)Lscala/Some;
  #188 = Methodref          #2.#187       // org/scalatest/concurrent/Waiters$Waiter.$anonfun$awaitImpl$1:(Lorg/scalatest/exceptions/StackDepthException;)Lscala/Some;
  #189 = MethodHandle       6:#188        // REF_invokeStatic org/scalatest/concurrent/Waiters$Waiter.$anonfun$awaitImpl$1:(Lorg/scalatest/exceptions/StackDepthException;)Lscala/Some;
  #190 = MethodType         #186          //  (Lorg/scalatest/exceptions/StackDepthException;)Lscala/Some;
  #191 = Integer            5
  #192 = Integer            1
  #193 = Utf8               java/lang/invoke/LambdaMetafactory
  #194 = Class              #193          // java/lang/invoke/LambdaMetafactory
  #195 = Utf8               altMetafactory
  #196 = Utf8               (Ljava/lang/invoke/MethodHandles$Lookup;Ljava/lang/String;Ljava/lang/invoke/MethodType;[Ljava/lang/Object;)Ljava/lang/invoke/CallSite;
  #197 = NameAndType        #195:#196     // altMetafactory:(Ljava/lang/invoke/MethodHandles$Lookup;Ljava/lang/String;Ljava/lang/invoke/MethodType;[Ljava/lang/Object;)Ljava/lang/invoke/CallSite;
  #198 = Methodref          #194.#197     // java/lang/invoke/LambdaMetafactory.altMetafactory:(Ljava/lang/invoke/MethodHandles$Lookup;Ljava/lang/String;Ljava/lang/invoke/MethodType;[Ljava/lang/Object;)Ljava/lang/invoke/CallSite;
  #199 = MethodHandle       6:#198        // REF_invokeStatic java/lang/invoke/LambdaMetafactory.altMetafactory:(Ljava/lang/invoke/MethodHandles$Lookup;Ljava/lang/String;Ljava/lang/invoke/MethodType;[Ljava/lang/Object;)Ljava/lang/invoke/CallSite;
  #200 = Utf8               ()Lscala/Function1;
  #201 = NameAndType        #74:#200      // apply:()Lscala/Function1;
  #202 = InvokeDynamic      #0:#201       // #0:apply:()Lscala/Function1;
  #203 = Utf8               (Lscala/Function1;Lscala/Option;Lorg/scalactic/source/Position;Lscala/Option;)V
  #204 = NameAndType        #67:#203      // "<init>":(Lscala/Function1;Lscala/Option;Lorg/scalactic/source/Position;Lscala/Option;)V
  #205 = Methodref          #182.#204     // org/scalatest/exceptions/TestFailedException."<init>":(Lscala/Function1;Lscala/Option;Lorg/scalactic/source/Position;Lscala/Option;)V
  #206 = Utf8               java/lang/Exception
  #207 = Class              #206          // java/lang/Exception
  #208 = Utf8               Should never happen: thrown was not defined; dismissedCount was not greater than dismissals; and timedOut was false
  #209 = String             #208          // Should never happen: thrown was not defined; dismissedCount was not greater than dismissals; and timedOut was false
  #210 = Utf8               (Ljava/lang/String;)V
  #211 = NameAndType        #67:#210      // "<init>":(Ljava/lang/String;)V
  #212 = Methodref          #207.#211     // java/lang/Exception."<init>":(Ljava/lang/String;)V
  #213 = Utf8               diff
  #214 = Utf8               J
  #215 = Utf8               timeLeft
  #216 = Utf8               Lorg/scalatest/time/Span;
  #217 = Utf8               startTime
  #218 = Utf8               endTime
  #219 = Utf8               Lorg/scalactic/source/Position;
  #220 = Utf8               org/scalactic/source/Position
  #221 = Class              #220          // org/scalactic/source/Position
  #222 = Utf8               await
  #223 = Utf8               (Lorg/scalatest/concurrent/AbstractPatienceConfiguration$PatienceConfig;Lorg/scalactic/source/Position;)V
  #224 = Utf8               config
  #225 = NameAndType        #94:#159      // timeout:()Lorg/scalatest/time/Span;
  #226 = Methodref          #12.#225      // org/scalatest/concurrent/AbstractPatienceConfiguration$PatienceConfig.timeout:()Lorg/scalatest/time/Span;
  #227 = Utf8               awaitImpl$default$3
  #228 = NameAndType        #227:#41      // awaitImpl$default$3:()I
  #229 = Methodref          #2.#228       // org/scalatest/concurrent/Waiters$Waiter.awaitImpl$default$3:()I
  #230 = NameAndType        #92:#93       // awaitImpl:(Lorg/scalatest/time/Span;Lorg/scalactic/source/Position;I)V
  #231 = Methodref          #2.#230       // org/scalatest/concurrent/Waiters$Waiter.awaitImpl:(Lorg/scalatest/time/Span;Lorg/scalactic/source/Position;I)V
  #232 = Utf8               Lorg/scalatest/concurrent/AbstractPatienceConfiguration$PatienceConfig;
  #233 = Utf8               (Lorg/scalatest/concurrent/PatienceConfiguration$Timeout;Lorg/scalactic/source/Position;)V
  #234 = Utf8               value
  #235 = NameAndType        #234:#159     // value:()Lorg/scalatest/time/Span;
  #236 = Methodref          #17.#235      // org/scalatest/concurrent/PatienceConfiguration$Timeout.value:()Lorg/scalatest/time/Span;
  #237 = Utf8               Lorg/scalatest/concurrent/PatienceConfiguration$Timeout;
  #238 = Utf8               (Lorg/scalatest/concurrent/Waiters$Dismissals;Lorg/scalatest/concurrent/AbstractPatienceConfiguration$PatienceConfig;Lorg/scalactic/source/Position;)V
  #239 = NameAndType        #234:#41      // value:()I
  #240 = Methodref          #22.#239      // org/scalatest/concurrent/Waiters$Dismissals.value:()I
  #241 = Utf8               Lorg/scalatest/concurrent/Waiters$Dismissals;
  #242 = Utf8               (Lorg/scalatest/concurrent/PatienceConfiguration$Timeout;Lorg/scalatest/concurrent/Waiters$Dismissals;Lorg/scalactic/source/Position;)V
  #243 = Utf8               dismiss
  #244 = Utf8               org$scalatest$concurrent$Waiters$Waiter$$$outer
  #245 = Utf8               ()Lorg/scalatest/concurrent/Waiters;
  #246 = NameAndType        #34:#35       // $outer:Lorg/scalatest/concurrent/Waiters;
  #247 = Fieldref           #2.#246       // org/scalatest/concurrent/Waiters$Waiter.$outer:Lorg/scalatest/concurrent/Waiters;
  #248 = Utf8               endTime$1
  #249 = Utf8               sde
  #250 = Utf8               awaitTimedOut
  #251 = NameAndType        #250:#117     // awaitTimedOut:()Ljava/lang/String;
  #252 = Methodref          #111.#251     // org/scalatest/Resources$.awaitTimedOut:()Ljava/lang/String;
  #253 = Utf8               Lorg/scalatest/exceptions/StackDepthException;
  #254 = Utf8               (Lorg/scalatest/concurrent/Waiters;)V
  #255 = NameAndType        #67:#83       // "<init>":()V
  #256 = Methodref          #4.#255       // java/lang/Object."<init>":()V
  #257 = Utf8               $deserializeLambda$
  #258 = Utf8               (Ljava/lang/invoke/SerializedLambda;)Ljava/lang/Object;
  #259 = Utf8               scala/runtime/LambdaDeserialize
  #260 = Class              #259          // scala/runtime/LambdaDeserialize
  #261 = Utf8               bootstrap
  #262 = Utf8               (Ljava/lang/invoke/MethodHandles$Lookup;Ljava/lang/String;Ljava/lang/invoke/MethodType;[Ljava/lang/invoke/MethodHandle;)Ljava/lang/invoke/CallSite;
  #263 = NameAndType        #261:#262     // bootstrap:(Ljava/lang/invoke/MethodHandles$Lookup;Ljava/lang/String;Ljava/lang/invoke/MethodType;[Ljava/lang/invoke/MethodHandle;)Ljava/lang/invoke/CallSite;
  #264 = Methodref          #260.#263     // scala/runtime/LambdaDeserialize.bootstrap:(Ljava/lang/invoke/MethodHandles$Lookup;Ljava/lang/String;Ljava/lang/invoke/MethodType;[Ljava/lang/invoke/MethodHandle;)Ljava/lang/invoke/CallSite;
  #265 = MethodHandle       6:#264        // REF_invokeStatic scala/runtime/LambdaDeserialize.bootstrap:(Ljava/lang/invoke/MethodHandles$Lookup;Ljava/lang/String;Ljava/lang/invoke/MethodType;[Ljava/lang/invoke/MethodHandle;)Ljava/lang/invoke/CallSite;
  #266 = Utf8               lambdaDeserialize
  #267 = NameAndType        #266:#258     // lambdaDeserialize:(Ljava/lang/invoke/SerializedLambda;)Ljava/lang/Object;
  #268 = InvokeDynamic      #1:#267       // #1:lambdaDeserialize:(Ljava/lang/invoke/SerializedLambda;)Ljava/lang/Object;
  #269 = Utf8               Signature
  #270 = Utf8               Code
  #271 = Utf8               LineNumberTable
  #272 = Utf8               LocalVariableTable
  #273 = Utf8               MethodParameters
  #274 = Utf8               StackMapTable
  #275 = Utf8               InnerClasses
  #276 = Utf8               SourceFile
  #277 = Utf8               BootstrapMethods
  #278 = Utf8               ScalaInlineInfo
  #279 = Utf8               Scala
{
  private final java.lang.Thread creatingThread;
    descriptor: Ljava/lang/Thread;
    flags: (0x0012) ACC_PRIVATE, ACC_FINAL

  private int dismissedCount;
    descriptor: I
    flags: (0x0002) ACC_PRIVATE

  private scala.Option<java.lang.Throwable> thrown;
    descriptor: Lscala/Option;
    flags: (0x0002) ACC_PRIVATE
    Signature: #33                          // Lscala/Option<Ljava/lang/Throwable;>;

  public final org.scalatest.concurrent.Waiters $outer;
    descriptor: Lorg/scalatest/concurrent/Waiters;
    flags: (0x1011) ACC_PUBLIC, ACC_FINAL, ACC_SYNTHETIC

  private final java.lang.Thread creatingThread();
    descriptor: ()Ljava/lang/Thread;
    flags: (0x0012) ACC_PRIVATE, ACC_FINAL
    Code:
      stack=1, locals=1, args_size=1
         0: aload_0
         1: getfield      #38                 // Field creatingThread:Ljava/lang/Thread;
         4: areturn
      LineNumberTable:
        line 311: 0
      LocalVariableTable:
        Start  Length  Slot  Name   Signature
            0       5     0  this   Lorg/scalatest/concurrent/Waiters$Waiter;

  private int dismissedCount();
    descriptor: ()I
    flags: (0x0002) ACC_PRIVATE
    Code:
      stack=1, locals=1, args_size=1
         0: aload_0
         1: getfield      #43                 // Field dismissedCount:I
         4: ireturn
      LineNumberTable:
        line 319: 0
      LocalVariableTable:
        Start  Length  Slot  Name   Signature
            0       5     0  this   Lorg/scalatest/concurrent/Waiters$Waiter;

  private void dismissedCount_$eq(int);
    descriptor: (I)V
    flags: (0x0002) ACC_PRIVATE
    Code:
      stack=2, locals=2, args_size=2
         0: aload_0
         1: iload_1
         2: putfield      #43                 // Field dismissedCount:I
         5: return
      LineNumberTable:
        line 319: 0
      LocalVariableTable:
        Start  Length  Slot  Name   Signature
            0       6     0  this   Lorg/scalatest/concurrent/Waiters$Waiter;
            0       6     1   x$1   I
    MethodParameters:
      Name                           Flags
      x$1                            final

  private scala.Option<java.lang.Throwable> thrown();
    descriptor: ()Lscala/Option;
    flags: (0x0002) ACC_PRIVATE
    Code:
      stack=1, locals=1, args_size=1
         0: aload_0
         1: getfield      #50                 // Field thrown:Lscala/Option;
         4: areturn
      LineNumberTable:
        line 320: 0
      LocalVariableTable:
        Start  Length  Slot  Name   Signature
            0       5     0  this   Lorg/scalatest/concurrent/Waiters$Waiter;
    Signature: #48                          // ()Lscala/Option<Ljava/lang/Throwable;>;

  private void thrown_$eq(scala.Option<java.lang.Throwable>);
    descriptor: (Lscala/Option;)V
    flags: (0x0002) ACC_PRIVATE
    Code:
      stack=2, locals=2, args_size=2
         0: aload_0
         1: aload_1
         2: putfield      #50                 // Field thrown:Lscala/Option;
         5: return
      LineNumberTable:
        line 320: 0
      LocalVariableTable:
        Start  Length  Slot  Name   Signature
            0       6     0  this   Lorg/scalatest/concurrent/Waiters$Waiter;
            0       6     1   x$1   Lscala/Option;
    Signature: #53                          // (Lscala/Option<Ljava/lang/Throwable;>;)V
    MethodParameters:
      Name                           Flags
      x$1                            final

  private synchronized void setThrownIfEmpty(java.lang.Throwable);
    descriptor: (Ljava/lang/Throwable;)V
    flags: (0x0022) ACC_PRIVATE, ACC_SYNCHRONIZED
    Code:
      stack=4, locals=2, args_size=2
         0: aload_0
         1: invokespecial #58                 // Method thrown:()Lscala/Option;
         4: invokevirtual #64                 // Method scala/Option.isEmpty:()Z
         7: ifeq          25
        10: aload_0
        11: new           #66                 // class scala/Some
        14: dup
        15: aload_1
        16: invokespecial #70                 // Method scala/Some."<init>":(Ljava/lang/Object;)V
        19: invokespecial #72                 // Method thrown_$eq:(Lscala/Option;)V
        22: goto          25
        25: return
      StackMapTable: number_of_entries = 1
        frame_type = 25 /* same */
      LineNumberTable:
        line 330: 0
      LocalVariableTable:
        Start  Length  Slot  Name   Signature
            0      26     0  this   Lorg/scalatest/concurrent/Waiters$Waiter;
            0      26     1     t   Ljava/lang/Throwable;
    MethodParameters:
      Name                           Flags
      t                              final

  public void apply(scala.Function0<scala.runtime.BoxedUnit>);
    descriptor: (Lscala/Function0;)V
    flags: (0x0001) ACC_PUBLIC
    Code:
      stack=2, locals=4, args_size=2
         0: aload_1
         1: invokeinterface #85,  1           // InterfaceMethod scala/Function0.apply$mcV$sp:()V
         6: goto          34
         9: astore_2
        10: aload_0
        11: aload_2
        12: invokespecial #87                 // Method setThrownIfEmpty:(Ljava/lang/Throwable;)V
        15: aload_0
        16: dup
        17: astore_3
        18: monitorenter
        19: aload_0
        20: invokevirtual #90                 // Method notifyAll:()V
        23: aload_3
        24: monitorexit
        25: goto          31
        28: aload_3
        29: monitorexit
        30: athrow
        31: goto          34
        34: return
      Exception table:
         from    to  target type
            19    23    28   any
             0     6     9   Class java/lang/Throwable
      StackMapTable: number_of_entries = 4
        frame_type = 73 /* same_locals_1_stack_item */
          stack = [ class java/lang/Throwable ]
        frame_type = 255 /* full_frame */
          offset_delta = 18
          locals = [ class org/scalatest/concurrent/Waiters$Waiter, class scala/Function0, class java/lang/Throwable, class org/scalatest/concurrent/Waiters$Waiter ]
          stack = [ class java/lang/Throwable ]
        frame_type = 2 /* same */
        frame_type = 249 /* chop */
          offset_delta = 2
      LineNumberTable:
        line 351: 0
        line 354: 10
        line 355: 15
        line 356: 19
        line 355: 31
      LocalVariableTable:
        Start  Length  Slot  Name   Signature
            9      22     2     t   Ljava/lang/Throwable;
            0      35     0  this   Lorg/scalatest/concurrent/Waiters$Waiter;
            0      35     1   fun   Lscala/Function0;
    Signature: #76                          // (Lscala/Function0<Lscala/runtime/BoxedUnit;>;)V
    MethodParameters:
      Name                           Flags
      fun                            final

  private void awaitImpl(org.scalatest.time.Span, org.scalactic.source.Position, int);
    descriptor: (Lorg/scalatest/time/Span;Lorg/scalactic/source/Position;I)V
    flags: (0x0002) ACC_PRIVATE
    Code:
      stack=6, locals=13, args_size=4
         0: invokestatic  #101                // Method java/lang/Thread.currentThread:()Ljava/lang/Thread;
         3: aload_0
         4: invokespecial #103                // Method creatingThread:()Ljava/lang/Thread;
         7: astore        4
         9: dup
        10: ifnonnull     22
        13: pop
        14: aload         4
        16: ifnull        48
        19: goto          30
        22: aload         4
        24: invokevirtual #107                // Method java/lang/Object.equals:(Ljava/lang/Object;)Z
        27: ifne          48
        30: new           #109                // class org/scalatest/exceptions/NotAllowedException
        33: dup
        34: getstatic     #115                // Field org/scalatest/Resources$.MODULE$:Lorg/scalatest/Resources$;
        37: invokevirtual #119                // Method org/scalatest/Resources$.awaitMustBeCalledOnCreatingThread:()Ljava/lang/String;
        40: getstatic     #124                // Field scala/None$.MODULE$:Lscala/None$;
        43: aload_2
        44: invokespecial #127                // Method org/scalatest/exceptions/NotAllowedException."<init>":(Ljava/lang/String;Lscala/Option;Lorg/scalactic/source/Position;)V
        47: athrow
        48: invokestatic  #133                // Method java/lang/System.nanoTime:()J
        51: lstore        5
        53: lload         5
        55: aload_1
        56: invokevirtual #138                // Method org/scalatest/time/Span.totalNanos:()J
        59: ladd
        60: lstore        7
        62: aload_0
        63: dup
        64: astore        9
        66: monitorenter
        67: aload_0
        68: invokespecial #140                // Method dismissedCount:()I
        71: iload_3
        72: if_icmpge     147
        75: lload         7
        77: invokestatic  #144                // Method timedOut$1:(J)Z
        80: ifne          147
        83: aload_0
        84: invokespecial #58                 // Method thrown:()Lscala/Option;
        87: invokevirtual #64                 // Method scala/Option.isEmpty:()Z
        90: ifeq          147
        93: lload         7
        95: invokestatic  #133                // Method java/lang/System.nanoTime:()J
        98: lsub
        99: lstore        11
       101: lload         11
       103: lconst_0
       104: lcmp
       105: ifle          122
       108: getstatic     #149                // Field org/scalatest/time/Span$.MODULE$:Lorg/scalatest/time/Span$;
       111: lload         11
       113: getstatic     #154                // Field org/scalatest/time/Nanoseconds$.MODULE$:Lorg/scalatest/time/Nanoseconds$;
       116: invokevirtual #157                // Method org/scalatest/time/Span$.apply:(JLorg/scalatest/time/Units;)Lorg/scalatest/time/Span;
       119: goto          128
       122: getstatic     #149                // Field org/scalatest/time/Span$.MODULE$:Lorg/scalatest/time/Span$;
       125: invokevirtual #161                // Method org/scalatest/time/Span$.Zero:()Lorg/scalatest/time/Span;
       128: astore        10
       130: aload_0
       131: aload         10
       133: invokevirtual #164                // Method org/scalatest/time/Span.millisPart:()J
       136: aload         10
       138: invokevirtual #167                // Method org/scalatest/time/Span.nanosPart:()I
       141: invokevirtual #171                // Method wait:(JI)V
       144: goto          67
       147: aload_0
       148: invokespecial #58                 // Method thrown:()Lscala/Option;
       151: invokevirtual #174                // Method scala/Option.isDefined:()Z
       154: ifeq          168
       157: aload_0
       158: invokespecial #58                 // Method thrown:()Lscala/Option;
       161: invokevirtual #178                // Method scala/Option.get:()Ljava/lang/Object;
       164: checkcast     #79                 // class java/lang/Throwable
       167: athrow
       168: aload_0
       169: invokespecial #140                // Method dismissedCount:()I
       172: iload_3
       173: if_icmplt     184
       176: aload_0
       177: iconst_0
       178: invokespecial #180                // Method dismissedCount_$eq:(I)V
       181: goto          222
       184: lload         7
       186: invokestatic  #144                // Method timedOut$1:(J)Z
       189: ifeq          212
       192: new           #182                // class org/scalatest/exceptions/TestFailedException
       195: dup
       196: invokedynamic #202,  0            // InvokeDynamic #0:apply:()Lscala/Function1;
       201: getstatic     #124                // Field scala/None$.MODULE$:Lscala/None$;
       204: aload_2
       205: getstatic     #124                // Field scala/None$.MODULE$:Lscala/None$;
       208: invokespecial #205                // Method org/scalatest/exceptions/TestFailedException."<init>":(Lscala/Function1;Lscala/Option;Lorg/scalactic/source/Position;Lscala/Option;)V
       211: athrow
       212: new           #207                // class java/lang/Exception
       215: dup
       216: ldc           #209                // String Should never happen: thrown was not defined; dismissedCount was not greater than dismissals; and timedOut was false
       218: invokespecial #212                // Method java/lang/Exception."<init>":(Ljava/lang/String;)V
       221: athrow
       222: aload         9
       224: monitorexit
       225: goto          232
       228: aload         9
       230: monitorexit
       231: athrow
       232: return
      Exception table:
         from    to  target type
            67   222   228   any
      StackMapTable: number_of_entries = 13
        frame_type = 255 /* full_frame */
          offset_delta = 22
          locals = [ class org/scalatest/concurrent/Waiters$Waiter, class org/scalatest/time/Span, class org/scalactic/source/Position, int, class java/lang/Thread ]
          stack = [ class java/lang/Thread ]
        frame_type = 7 /* same */
        frame_type = 17 /* same */
        frame_type = 254 /* append */
          offset_delta = 18
          locals = [ long, long, class org/scalatest/concurrent/Waiters$Waiter ]
        frame_type = 253 /* append */
          offset_delta = 54
          locals = [ top, long ]
        frame_type = 69 /* same_locals_1_stack_item */
          stack = [ class org/scalatest/time/Span ]
        frame_type = 249 /* chop */
          offset_delta = 18
        frame_type = 20 /* same */
        frame_type = 15 /* same */
        frame_type = 27 /* same */
        frame_type = 9 /* same */
        frame_type = 69 /* same_locals_1_stack_item */
          stack = [ class java/lang/Throwable ]
        frame_type = 3 /* same */
      LineNumberTable:
        line 383: 0
        line 384: 30
        line 386: 48
        line 387: 53
        line 389: 62
        line 390: 67
        line 392: 93
        line 393: 101
        line 395: 130
        line 390: 144
        line 401: 147
        line 402: 157
        line 403: 168
        line 404: 176
        line 405: 184
        line 406: 192
        line 407: 212
        line 389: 232
      LocalVariableTable:
        Start  Length  Slot  Name   Signature
          101      27    11  diff   J
          130      14    10 timeLeft   Lorg/scalatest/time/Span;
           53     179     5 startTime   J
           62     170     7 endTime   J
            0     233     0  this   Lorg/scalatest/concurrent/Waiters$Waiter;
            0     233     1 timeout   Lorg/scalatest/time/Span;
            0     233     2   pos   Lorg/scalactic/source/Position;
            0     233     3 dismissals   I
    MethodParameters:
      Name                           Flags
      timeout                        final
      pos                            final
      dismissals                     final

  public void await(org.scalatest.concurrent.AbstractPatienceConfiguration$PatienceConfig, org.scalactic.source.Position);
    descriptor: (Lorg/scalatest/concurrent/AbstractPatienceConfiguration$PatienceConfig;Lorg/scalactic/source/Position;)V
    flags: (0x0001) ACC_PUBLIC
    Code:
      stack=4, locals=3, args_size=3
         0: aload_0
         1: aload_1
         2: invokevirtual #226                // Method org/scalatest/concurrent/AbstractPatienceConfiguration$PatienceConfig.timeout:()Lorg/scalatest/time/Span;
         5: aload_2
         6: aload_0
         7: invokespecial #229                // Method awaitImpl$default$3:()I
        10: invokespecial #231                // Method awaitImpl:(Lorg/scalatest/time/Span;Lorg/scalactic/source/Position;I)V
        13: return
      LineNumberTable:
        line 440: 0
      LocalVariableTable:
        Start  Length  Slot  Name   Signature
            0      14     0  this   Lorg/scalatest/concurrent/Waiters$Waiter;
            0      14     1 config   Lorg/scalatest/concurrent/AbstractPatienceConfiguration$PatienceConfig;
            0      14     2   pos   Lorg/scalactic/source/Position;
    MethodParameters:
      Name                           Flags
      config                         final
      pos                            final

  public void await(org.scalatest.concurrent.PatienceConfiguration$Timeout, org.scalactic.source.Position);
    descriptor: (Lorg/scalatest/concurrent/PatienceConfiguration$Timeout;Lorg/scalactic/source/Position;)V
    flags: (0x0001) ACC_PUBLIC
    Code:
      stack=4, locals=3, args_size=3
         0: aload_0
         1: aload_1
         2: invokevirtual #236                // Method org/scalatest/concurrent/PatienceConfiguration$Timeout.value:()Lorg/scalatest/time/Span;
         5: aload_2
         6: aload_0
         7: invokespecial #229                // Method awaitImpl$default$3:()I
        10: invokespecial #231                // Method awaitImpl:(Lorg/scalatest/time/Span;Lorg/scalactic/source/Position;I)V
        13: return
      LineNumberTable:
        line 472: 0
      LocalVariableTable:
        Start  Length  Slot  Name   Signature
            0      14     0  this   Lorg/scalatest/concurrent/Waiters$Waiter;
            0      14     1 timeout   Lorg/scalatest/concurrent/PatienceConfiguration$Timeout;
            0      14     2   pos   Lorg/scalactic/source/Position;
    MethodParameters:
      Name                           Flags
      timeout                        final
      pos                            final

  public void await(org.scalatest.concurrent.Waiters$Dismissals, org.scalatest.concurrent.AbstractPatienceConfiguration$PatienceConfig, org.scalactic.source.Position);
    descriptor: (Lorg/scalatest/concurrent/Waiters$Dismissals;Lorg/scalatest/concurrent/AbstractPatienceConfiguration$PatienceConfig;Lorg/scalactic/source/Position;)V
    flags: (0x0001) ACC_PUBLIC
    Code:
      stack=4, locals=4, args_size=4
         0: aload_0
         1: aload_2
         2: invokevirtual #226                // Method org/scalatest/concurrent/AbstractPatienceConfiguration$PatienceConfig.timeout:()Lorg/scalatest/time/Span;
         5: aload_3
         6: aload_1
         7: invokevirtual #240                // Method org/scalatest/concurrent/Waiters$Dismissals.value:()I
        10: invokespecial #231                // Method awaitImpl:(Lorg/scalatest/time/Span;Lorg/scalactic/source/Position;I)V
        13: return
      LineNumberTable:
        line 506: 0
      LocalVariableTable:
        Start  Length  Slot  Name   Signature
            0      14     0  this   Lorg/scalatest/concurrent/Waiters$Waiter;
            0      14     1 dismissals   Lorg/scalatest/concurrent/Waiters$Dismissals;
            0      14     2 config   Lorg/scalatest/concurrent/AbstractPatienceConfiguration$PatienceConfig;
            0      14     3   pos   Lorg/scalactic/source/Position;
    MethodParameters:
      Name                           Flags
      dismissals                     final
      config                         final
      pos                            final

  public void await(org.scalatest.concurrent.PatienceConfiguration$Timeout, org.scalatest.concurrent.Waiters$Dismissals, org.scalactic.source.Position);
    descriptor: (Lorg/scalatest/concurrent/PatienceConfiguration$Timeout;Lorg/scalatest/concurrent/Waiters$Dismissals;Lorg/scalactic/source/Position;)V
    flags: (0x0001) ACC_PUBLIC
    Code:
      stack=4, locals=4, args_size=4
         0: aload_0
         1: aload_1
         2: invokevirtual #236                // Method org/scalatest/concurrent/PatienceConfiguration$Timeout.value:()Lorg/scalatest/time/Span;
         5: aload_3
         6: aload_2
         7: invokevirtual #240                // Method org/scalatest/concurrent/Waiters$Dismissals.value:()I
        10: invokespecial #231                // Method awaitImpl:(Lorg/scalatest/time/Span;Lorg/scalactic/source/Position;I)V
        13: return
      LineNumberTable:
        line 540: 0
      LocalVariableTable:
        Start  Length  Slot  Name   Signature
            0      14     0  this   Lorg/scalatest/concurrent/Waiters$Waiter;
            0      14     1 timeout   Lorg/scalatest/concurrent/PatienceConfiguration$Timeout;
            0      14     2 dismissals   Lorg/scalatest/concurrent/Waiters$Dismissals;
            0      14     3   pos   Lorg/scalactic/source/Position;
    MethodParameters:
      Name                           Flags
      timeout                        final
      dismissals                     final
      pos                            final

  private int awaitImpl$default$3();
    descriptor: ()I
    flags: (0x0002) ACC_PRIVATE
    Code:
      stack=1, locals=1, args_size=1
         0: iconst_1
         1: ireturn
      LineNumberTable:
        line 382: 0
      LocalVariableTable:
        Start  Length  Slot  Name   Signature
            0       2     0  this   Lorg/scalatest/concurrent/Waiters$Waiter;

  public synchronized void dismiss();
    descriptor: ()V
    flags: (0x0021) ACC_PUBLIC, ACC_SYNCHRONIZED
    Code:
      stack=3, locals=1, args_size=1
         0: aload_0
         1: aload_0
         2: invokespecial #140                // Method dismissedCount:()I
         5: iconst_1
         6: iadd
         7: invokespecial #180                // Method dismissedCount_$eq:(I)V
        10: aload_0
        11: invokevirtual #90                 // Method notifyAll:()V
        14: return
      LineNumberTable:
        line 557: 0
        line 558: 10
      LocalVariableTable:
        Start  Length  Slot  Name   Signature
            0      15     0  this   Lorg/scalatest/concurrent/Waiters$Waiter;

  public org.scalatest.concurrent.Waiters org$scalatest$concurrent$Waiters$Waiter$$$outer();
    descriptor: ()Lorg/scalatest/concurrent/Waiters;
    flags: (0x1001) ACC_PUBLIC, ACC_SYNTHETIC
    Code:
      stack=1, locals=1, args_size=1
         0: aload_0
         1: getfield      #247                // Field $outer:Lorg/scalatest/concurrent/Waiters;
         4: areturn
      LineNumberTable:
        line 309: 0
      LocalVariableTable:
        Start  Length  Slot  Name   Signature
            0       5     0  this   Lorg/scalatest/concurrent/Waiters$Waiter;

  private static final boolean timedOut$1(long);
    descriptor: (J)Z
    flags: (0x001a) ACC_PRIVATE, ACC_STATIC, ACC_FINAL
    Code:
      stack=4, locals=2, args_size=1
         0: lload_0
         1: invokestatic  #133                // Method java/lang/System.nanoTime:()J
         4: lcmp
         5: ifge          12
         8: iconst_1
         9: goto          13
        12: iconst_0
        13: ireturn
      StackMapTable: number_of_entries = 2
        frame_type = 12 /* same */
        frame_type = 64 /* same_locals_1_stack_item */
          stack = [ int ]
      LineNumberTable:
        line 388: 0
      LocalVariableTable:
        Start  Length  Slot  Name   Signature
            0      14     0 endTime$1   J
    MethodParameters:
      Name                           Flags
      endTime$1                      final

  public static final scala.Some $anonfun$awaitImpl$1(org.scalatest.exceptions.StackDepthException);
    descriptor: (Lorg/scalatest/exceptions/StackDepthException;)Lscala/Some;
    flags: (0x1019) ACC_PUBLIC, ACC_STATIC, ACC_FINAL, ACC_SYNTHETIC
    Code:
      stack=3, locals=1, args_size=1
         0: new           #66                 // class scala/Some
         3: dup
         4: getstatic     #115                // Field org/scalatest/Resources$.MODULE$:Lorg/scalatest/Resources$;
         7: invokevirtual #252                // Method org/scalatest/Resources$.awaitTimedOut:()Ljava/lang/String;
        10: invokespecial #70                 // Method scala/Some."<init>":(Ljava/lang/Object;)V
        13: areturn
      LineNumberTable:
        line 406: 0
      LocalVariableTable:
        Start  Length  Slot  Name   Signature
            0      14     0   sde   Lorg/scalatest/exceptions/StackDepthException;
    MethodParameters:
      Name                           Flags
      sde                            final

  public org.scalatest.concurrent.Waiters$Waiter(org.scalatest.concurrent.Waiters);
    descriptor: (Lorg/scalatest/concurrent/Waiters;)V
    flags: (0x0001) ACC_PUBLIC
    Code:
      stack=2, locals=2, args_size=2
         0: aload_1
         1: ifnonnull     6
         4: aconst_null
         5: athrow
         6: aload_0
         7: aload_1
         8: putfield      #247                // Field $outer:Lorg/scalatest/concurrent/Waiters;
        11: aload_0
        12: invokespecial #256                // Method java/lang/Object."<init>":()V
        15: aload_0
        16: invokestatic  #101                // Method java/lang/Thread.currentThread:()Ljava/lang/Thread;
        19: putfield      #38                 // Field creatingThread:Ljava/lang/Thread;
        22: aload_0
        23: iconst_0
        24: putfield      #43                 // Field dismissedCount:I
        27: aload_0
        28: getstatic     #124                // Field scala/None$.MODULE$:Lscala/None$;
        31: putfield      #50                 // Field thrown:Lscala/Option;
        34: return
      StackMapTable: number_of_entries = 1
        frame_type = 6 /* same */
      LineNumberTable:
        line 309: 0
        line 562: 11
        line 311: 15
        line 319: 22
        line 320: 27
        line 309: 34
      LocalVariableTable:
        Start  Length  Slot  Name   Signature
            0      35     0  this   Lorg/scalatest/concurrent/Waiters$Waiter;
            0      35     1 $outer   Lorg/scalatest/concurrent/Waiters;
    MethodParameters:
      Name                           Flags
      $outer                         final synthetic

  private static java.lang.Object $deserializeLambda$(java.lang.invoke.SerializedLambda);
    descriptor: (Ljava/lang/invoke/SerializedLambda;)Ljava/lang/Object;
    flags: (0x100a) ACC_PRIVATE, ACC_STATIC, ACC_SYNTHETIC
    Code:
      stack=1, locals=1, args_size=1
         0: aload_0
         1: invokedynamic #268,  0            // InvokeDynamic #1:lambdaDeserialize:(Ljava/lang/invoke/SerializedLambda;)Ljava/lang/Object;
         6: areturn
}
InnerClasses:
  public static final #10= #7 of #9;      // Lookup=class java/lang/invoke/MethodHandles$Lookup of class java/lang/invoke/MethodHandles
  public final #15= #12 of #14;           // PatienceConfig=class org/scalatest/concurrent/AbstractPatienceConfiguration$PatienceConfig of class org/scalatest/concurrent/AbstractPatienceConfiguration
  public static final #20= #17 of #19;    // Timeout=class org/scalatest/concurrent/PatienceConfiguration$Timeout of class org/scalatest/concurrent/PatienceConfiguration
  public final #25= #22 of #24;           // Dismissals=class org/scalatest/concurrent/Waiters$Dismissals of class org/scalatest/concurrent/Waiters
  public #26= #2 of #24;                  // Waiter=class org/scalatest/concurrent/Waiters$Waiter of class org/scalatest/concurrent/Waiters
SourceFile: "Waiters.scala"
BootstrapMethods:
  0: #199 REF_invokeStatic java/lang/invoke/LambdaMetafactory.altMetafactory:(Ljava/lang/invoke/MethodHandles$Lookup;Ljava/lang/String;Ljava/lang/invoke/MethodType;[Ljava/lang/Object;)Ljava/lang/invoke/CallSite;
    Method arguments:
      #184 (Ljava/lang/Object;)Ljava/lang/Object;
      #189 REF_invokeStatic org/scalatest/concurrent/Waiters$Waiter.$anonfun$awaitImpl$1:(Lorg/scalatest/exceptions/StackDepthException;)Lscala/Some;
      #190 (Lorg/scalatest/exceptions/StackDepthException;)Lscala/Some;
      #191 5
      #192 1
      #190 (Lorg/scalatest/exceptions/StackDepthException;)Lscala/Some;
  1: #265 REF_invokeStatic scala/runtime/LambdaDeserialize.bootstrap:(Ljava/lang/invoke/MethodHandles$Lookup;Ljava/lang/String;Ljava/lang/invoke/MethodType;[Ljava/lang/invoke/MethodHandle;)Ljava/lang/invoke/CallSite;
    Method arguments:
      #189 REF_invokeStatic org/scalatest/concurrent/Waiters$Waiter.$anonfun$awaitImpl$1:(Lorg/scalatest/exceptions/StackDepthException;)Lscala/Some;
  ScalaInlineInfo: length = 0x5E (unknown attribute)
   01 00 00 12 00 B9 00 BA 01 00 43 00 FE 00 00 4A
   00 4B 00 00 DE 00 DF 00 00 DE 00 E9 00 00 DE 00
   F2 00 00 DE 00 EE 00 00 5C 00 5D 01 00 E3 00 29
   01 00 1B 00 24 01 00 F3 00 53 00 00 1D 00 29 01
   00 2C 00 2D 01 00 F4 00 F5 00 00 36 00 37 01 00
   1F 00 2F 01 00 33 00 34 01 00 8D 00 8E 01
  Scala: length = 0x0 (unknown attribute)

