Classfile /Users/mw/Projects/slang-braindump/.jar/jar11/assemble/slang-braindump/assemble/content/com/fasterxml/jackson/databind/node/NodeSerialization.class
  Last modified May 29, 2022; size 3395 bytes
  SHA-256 checksum 01ce2935a6d087c720cd651952c8b4bd1536c1d4cee76aae4f9859a8c15a0bf9
  Compiled from "NodeSerialization.java"
class com.fasterxml.jackson.databind.node.NodeSerialization implements java.io.Serializable,java.io.Externalizable
  minor version: 0
  major version: 52
  flags: (0x0020) ACC_SUPER
  this_class: #13                         // com/fasterxml/jackson/databind/node/NodeSerialization
  super_class: #35                        // java/lang/Object
  interfaces: 2, fields: 3, methods: 7, attributes: 1
Constant pool:
    #1 = Methodref          #35.#92       // java/lang/Object."<init>":()V
    #2 = Fieldref           #13.#93       // com/fasterxml/jackson/databind/node/NodeSerialization.json:[B
    #3 = Methodref          #94.#95       // com/fasterxml/jackson/databind/node/InternalNodeMapper.bytesToNode:([B)Lcom/fasterxml/jackson/databind/JsonNode;
    #4 = Class              #96           // java/io/IOException
    #5 = Class              #97           // java/lang/IllegalArgumentException
    #6 = Class              #98           // java/lang/StringBuilder
    #7 = Methodref          #6.#92        // java/lang/StringBuilder."<init>":()V
    #8 = String             #99           // Failed to JDK deserialize `JsonNode` value:
    #9 = Methodref          #6.#100       // java/lang/StringBuilder.append:(Ljava/lang/String;)Ljava/lang/StringBuilder;
   #10 = Methodref          #4.#101       // java/io/IOException.getMessage:()Ljava/lang/String;
   #11 = Methodref          #6.#102       // java/lang/StringBuilder.toString:()Ljava/lang/String;
   #12 = Methodref          #5.#103       // java/lang/IllegalArgumentException."<init>":(Ljava/lang/String;Ljava/lang/Throwable;)V
   #13 = Class              #104          // com/fasterxml/jackson/databind/node/NodeSerialization
   #14 = Methodref          #94.#105      // com/fasterxml/jackson/databind/node/InternalNodeMapper.valueToBytes:(Ljava/lang/Object;)[B
   #15 = Methodref          #13.#106      // com/fasterxml/jackson/databind/node/NodeSerialization."<init>":([B)V
   #16 = String             #107          // Failed to JDK serialize `
   #17 = Methodref          #35.#108      // java/lang/Object.getClass:()Ljava/lang/Class;
   #18 = Methodref          #109.#110     // java/lang/Class.getSimpleName:()Ljava/lang/String;
   #19 = String             #111          // ` value:
   #20 = InterfaceMethodref #112.#113     // java/io/ObjectOutput.writeInt:(I)V
   #21 = InterfaceMethodref #112.#114     // java/io/ObjectOutput.write:([B)V
   #22 = InterfaceMethodref #115.#116     // java/io/ObjectInput.readInt:()I
   #23 = Methodref          #13.#117      // com/fasterxml/jackson/databind/node/NodeSerialization._read:(Ljava/io/ObjectInput;I)[B
   #24 = Integer            100000
   #25 = InterfaceMethodref #115.#118     // java/io/ObjectInput.readFully:([BII)V
   #26 = Class              #119          // com/fasterxml/jackson/core/util/ByteArrayBuilder
   #27 = Methodref          #26.#120      // com/fasterxml/jackson/core/util/ByteArrayBuilder."<init>":(I)V
   #28 = Methodref          #26.#121      // com/fasterxml/jackson/core/util/ByteArrayBuilder.resetAndGetFirstSegment:()[B
   #29 = Methodref          #122.#123     // java/lang/Math.min:(II)I
   #30 = Methodref          #26.#124      // com/fasterxml/jackson/core/util/ByteArrayBuilder.completeAndCoalesce:(I)[B
   #31 = Methodref          #26.#125      // com/fasterxml/jackson/core/util/ByteArrayBuilder.close:()V
   #32 = Class              #126          // java/lang/Throwable
   #33 = Methodref          #32.#127      // java/lang/Throwable.addSuppressed:(Ljava/lang/Throwable;)V
   #34 = Methodref          #26.#128      // com/fasterxml/jackson/core/util/ByteArrayBuilder.finishCurrentSegment:()[B
   #35 = Class              #129          // java/lang/Object
   #36 = Class              #130          // java/io/Serializable
   #37 = Class              #131          // java/io/Externalizable
   #38 = Utf8               LONGEST_EAGER_ALLOC
   #39 = Utf8               I
   #40 = Utf8               ConstantValue
   #41 = Utf8               serialVersionUID
   #42 = Utf8               J
   #43 = Long               1l
   #45 = Utf8               json
   #46 = Utf8               [B
   #47 = Utf8               <init>
   #48 = Utf8               ()V
   #49 = Utf8               Code
   #50 = Utf8               LineNumberTable
   #51 = Utf8               LocalVariableTable
   #52 = Utf8               this
   #53 = Utf8               Lcom/fasterxml/jackson/databind/node/NodeSerialization;
   #54 = Utf8               ([B)V
   #55 = Utf8               b
   #56 = Utf8               readResolve
   #57 = Utf8               ()Ljava/lang/Object;
   #58 = Utf8               e
   #59 = Utf8               Ljava/io/IOException;
   #60 = Utf8               StackMapTable
   #61 = Class              #96           // java/io/IOException
   #62 = Utf8               from
   #63 = Utf8               (Ljava/lang/Object;)Lcom/fasterxml/jackson/databind/node/NodeSerialization;
   #64 = Utf8               o
   #65 = Utf8               Ljava/lang/Object;
   #66 = Utf8               writeExternal
   #67 = Utf8               (Ljava/io/ObjectOutput;)V
   #68 = Utf8               out
   #69 = Utf8               Ljava/io/ObjectOutput;
   #70 = Utf8               Exceptions
   #71 = Utf8               readExternal
   #72 = Utf8               (Ljava/io/ObjectInput;)V
   #73 = Utf8               in
   #74 = Utf8               Ljava/io/ObjectInput;
   #75 = Utf8               len
   #76 = Utf8               _read
   #77 = Utf8               (Ljava/io/ObjectInput;I)[B
   #78 = Utf8               result
   #79 = Utf8               toRead
   #80 = Utf8               buffer
   #81 = Utf8               outOffset
   #82 = Utf8               bb
   #83 = Utf8               Lcom/fasterxml/jackson/core/util/ByteArrayBuilder;
   #84 = Utf8               expLen
   #85 = Class              #104          // com/fasterxml/jackson/databind/node/NodeSerialization
   #86 = Class              #132          // java/io/ObjectInput
   #87 = Class              #119          // com/fasterxml/jackson/core/util/ByteArrayBuilder
   #88 = Class              #126          // java/lang/Throwable
   #89 = Class              #46           // "[B"
   #90 = Utf8               SourceFile
   #91 = Utf8               NodeSerialization.java
   #92 = NameAndType        #47:#48       // "<init>":()V
   #93 = NameAndType        #45:#46       // json:[B
   #94 = Class              #133          // com/fasterxml/jackson/databind/node/InternalNodeMapper
   #95 = NameAndType        #134:#135     // bytesToNode:([B)Lcom/fasterxml/jackson/databind/JsonNode;
   #96 = Utf8               java/io/IOException
   #97 = Utf8               java/lang/IllegalArgumentException
   #98 = Utf8               java/lang/StringBuilder
   #99 = Utf8               Failed to JDK deserialize `JsonNode` value:
  #100 = NameAndType        #136:#137     // append:(Ljava/lang/String;)Ljava/lang/StringBuilder;
  #101 = NameAndType        #138:#139     // getMessage:()Ljava/lang/String;
  #102 = NameAndType        #140:#139     // toString:()Ljava/lang/String;
  #103 = NameAndType        #47:#141      // "<init>":(Ljava/lang/String;Ljava/lang/Throwable;)V
  #104 = Utf8               com/fasterxml/jackson/databind/node/NodeSerialization
  #105 = NameAndType        #142:#143     // valueToBytes:(Ljava/lang/Object;)[B
  #106 = NameAndType        #47:#54       // "<init>":([B)V
  #107 = Utf8               Failed to JDK serialize `
  #108 = NameAndType        #144:#145     // getClass:()Ljava/lang/Class;
  #109 = Class              #146          // java/lang/Class
  #110 = NameAndType        #147:#139     // getSimpleName:()Ljava/lang/String;
  #111 = Utf8               ` value:
  #112 = Class              #148          // java/io/ObjectOutput
  #113 = NameAndType        #149:#150     // writeInt:(I)V
  #114 = NameAndType        #151:#54      // write:([B)V
  #115 = Class              #132          // java/io/ObjectInput
  #116 = NameAndType        #152:#153     // readInt:()I
  #117 = NameAndType        #76:#77       // _read:(Ljava/io/ObjectInput;I)[B
  #118 = NameAndType        #154:#155     // readFully:([BII)V
  #119 = Utf8               com/fasterxml/jackson/core/util/ByteArrayBuilder
  #120 = NameAndType        #47:#150      // "<init>":(I)V
  #121 = NameAndType        #156:#157     // resetAndGetFirstSegment:()[B
  #122 = Class              #158          // java/lang/Math
  #123 = NameAndType        #159:#160     // min:(II)I
  #124 = NameAndType        #161:#162     // completeAndCoalesce:(I)[B
  #125 = NameAndType        #163:#48      // close:()V
  #126 = Utf8               java/lang/Throwable
  #127 = NameAndType        #164:#165     // addSuppressed:(Ljava/lang/Throwable;)V
  #128 = NameAndType        #166:#157     // finishCurrentSegment:()[B
  #129 = Utf8               java/lang/Object
  #130 = Utf8               java/io/Serializable
  #131 = Utf8               java/io/Externalizable
  #132 = Utf8               java/io/ObjectInput
  #133 = Utf8               com/fasterxml/jackson/databind/node/InternalNodeMapper
  #134 = Utf8               bytesToNode
  #135 = Utf8               ([B)Lcom/fasterxml/jackson/databind/JsonNode;
  #136 = Utf8               append
  #137 = Utf8               (Ljava/lang/String;)Ljava/lang/StringBuilder;
  #138 = Utf8               getMessage
  #139 = Utf8               ()Ljava/lang/String;
  #140 = Utf8               toString
  #141 = Utf8               (Ljava/lang/String;Ljava/lang/Throwable;)V
  #142 = Utf8               valueToBytes
  #143 = Utf8               (Ljava/lang/Object;)[B
  #144 = Utf8               getClass
  #145 = Utf8               ()Ljava/lang/Class;
  #146 = Utf8               java/lang/Class
  #147 = Utf8               getSimpleName
  #148 = Utf8               java/io/ObjectOutput
  #149 = Utf8               writeInt
  #150 = Utf8               (I)V
  #151 = Utf8               write
  #152 = Utf8               readInt
  #153 = Utf8               ()I
  #154 = Utf8               readFully
  #155 = Utf8               ([BII)V
  #156 = Utf8               resetAndGetFirstSegment
  #157 = Utf8               ()[B
  #158 = Utf8               java/lang/Math
  #159 = Utf8               min
  #160 = Utf8               (II)I
  #161 = Utf8               completeAndCoalesce
  #162 = Utf8               (I)[B
  #163 = Utf8               close
  #164 = Utf8               addSuppressed
  #165 = Utf8               (Ljava/lang/Throwable;)V
  #166 = Utf8               finishCurrentSegment
{
  protected static final int LONGEST_EAGER_ALLOC;
    descriptor: I
    flags: (0x001c) ACC_PROTECTED, ACC_STATIC, ACC_FINAL
    ConstantValue: int 100000

  private static final long serialVersionUID;
    descriptor: J
    flags: (0x001a) ACC_PRIVATE, ACC_STATIC, ACC_FINAL
    ConstantValue: long 1l

  public byte[] json;
    descriptor: [B
    flags: (0x0001) ACC_PUBLIC

  public com.fasterxml.jackson.databind.node.NodeSerialization();
    descriptor: ()V
    flags: (0x0001) ACC_PUBLIC
    Code:
      stack=1, locals=1, args_size=1
         0: aload_0
         1: invokespecial #1                  // Method java/lang/Object."<init>":()V
         4: return
      LineNumberTable:
        line 24: 0
      LocalVariableTable:
        Start  Length  Slot  Name   Signature
            0       5     0  this   Lcom/fasterxml/jackson/databind/node/NodeSerialization;

  public com.fasterxml.jackson.databind.node.NodeSerialization(byte[]);
    descriptor: ([B)V
    flags: (0x0001) ACC_PUBLIC
    Code:
      stack=2, locals=2, args_size=2
         0: aload_0
         1: invokespecial #1                  // Method java/lang/Object."<init>":()V
         4: aload_0
         5: aload_1
         6: putfield      #2                  // Field json:[B
         9: return
      LineNumberTable:
        line 26: 0
      LocalVariableTable:
        Start  Length  Slot  Name   Signature
            0      10     0  this   Lcom/fasterxml/jackson/databind/node/NodeSerialization;
            0      10     1     b   [B

  protected java.lang.Object readResolve();
    descriptor: ()Ljava/lang/Object;
    flags: (0x0004) ACC_PROTECTED
    Code:
      stack=4, locals=2, args_size=1
         0: aload_0
         1: getfield      #2                  // Field json:[B
         4: invokestatic  #3                  // Method com/fasterxml/jackson/databind/node/InternalNodeMapper.bytesToNode:([B)Lcom/fasterxml/jackson/databind/JsonNode;
         7: areturn
         8: astore_1
         9: new           #5                  // class java/lang/IllegalArgumentException
        12: dup
        13: new           #6                  // class java/lang/StringBuilder
        16: dup
        17: invokespecial #7                  // Method java/lang/StringBuilder."<init>":()V
        20: ldc           #8                  // String Failed to JDK deserialize `JsonNode` value:
        22: invokevirtual #9                  // Method java/lang/StringBuilder.append:(Ljava/lang/String;)Ljava/lang/StringBuilder;
        25: aload_1
        26: invokevirtual #10                 // Method java/io/IOException.getMessage:()Ljava/lang/String;
        29: invokevirtual #9                  // Method java/lang/StringBuilder.append:(Ljava/lang/String;)Ljava/lang/StringBuilder;
        32: invokevirtual #11                 // Method java/lang/StringBuilder.toString:()Ljava/lang/String;
        35: aload_1
        36: invokespecial #12                 // Method java/lang/IllegalArgumentException."<init>":(Ljava/lang/String;Ljava/lang/Throwable;)V
        39: athrow
      Exception table:
         from    to  target type
             0     7     8   Class java/io/IOException
      LineNumberTable:
        line 30: 0
        line 31: 8
        line 32: 9
      LocalVariableTable:
        Start  Length  Slot  Name   Signature
            9      31     1     e   Ljava/io/IOException;
            0      40     0  this   Lcom/fasterxml/jackson/databind/node/NodeSerialization;
      StackMapTable: number_of_entries = 1
        frame_type = 72 /* same_locals_1_stack_item */
          stack = [ class java/io/IOException ]

  public static com.fasterxml.jackson.databind.node.NodeSerialization from(java.lang.Object);
    descriptor: (Ljava/lang/Object;)Lcom/fasterxml/jackson/databind/node/NodeSerialization;
    flags: (0x0009) ACC_PUBLIC, ACC_STATIC
    Code:
      stack=4, locals=2, args_size=1
         0: new           #13                 // class com/fasterxml/jackson/databind/node/NodeSerialization
         3: dup
         4: aload_0
         5: invokestatic  #14                 // Method com/fasterxml/jackson/databind/node/InternalNodeMapper.valueToBytes:(Ljava/lang/Object;)[B
         8: invokespecial #15                 // Method "<init>":([B)V
        11: areturn
        12: astore_1
        13: new           #5                  // class java/lang/IllegalArgumentException
        16: dup
        17: new           #6                  // class java/lang/StringBuilder
        20: dup
        21: invokespecial #7                  // Method java/lang/StringBuilder."<init>":()V
        24: ldc           #16                 // String Failed to JDK serialize `
        26: invokevirtual #9                  // Method java/lang/StringBuilder.append:(Ljava/lang/String;)Ljava/lang/StringBuilder;
        29: aload_0
        30: invokevirtual #17                 // Method java/lang/Object.getClass:()Ljava/lang/Class;
        33: invokevirtual #18                 // Method java/lang/Class.getSimpleName:()Ljava/lang/String;
        36: invokevirtual #9                  // Method java/lang/StringBuilder.append:(Ljava/lang/String;)Ljava/lang/StringBuilder;
        39: ldc           #19                 // String ` value:
        41: invokevirtual #9                  // Method java/lang/StringBuilder.append:(Ljava/lang/String;)Ljava/lang/StringBuilder;
        44: aload_1
        45: invokevirtual #10                 // Method java/io/IOException.getMessage:()Ljava/lang/String;
        48: invokevirtual #9                  // Method java/lang/StringBuilder.append:(Ljava/lang/String;)Ljava/lang/StringBuilder;
        51: invokevirtual #11                 // Method java/lang/StringBuilder.toString:()Ljava/lang/String;
        54: aload_1
        55: invokespecial #12                 // Method java/lang/IllegalArgumentException."<init>":(Ljava/lang/String;Ljava/lang/Throwable;)V
        58: athrow
      Exception table:
         from    to  target type
             0    11    12   Class java/io/IOException
      LineNumberTable:
        line 38: 0
        line 39: 12
        line 40: 13
      LocalVariableTable:
        Start  Length  Slot  Name   Signature
           13      46     1     e   Ljava/io/IOException;
            0      59     0     o   Ljava/lang/Object;
      StackMapTable: number_of_entries = 1
        frame_type = 76 /* same_locals_1_stack_item */
          stack = [ class java/io/IOException ]

  public void writeExternal(java.io.ObjectOutput) throws java.io.IOException;
    descriptor: (Ljava/io/ObjectOutput;)V
    flags: (0x0001) ACC_PUBLIC
    Code:
      stack=2, locals=2, args_size=2
         0: aload_1
         1: aload_0
         2: getfield      #2                  // Field json:[B
         5: arraylength
         6: invokeinterface #20,  2           // InterfaceMethod java/io/ObjectOutput.writeInt:(I)V
        11: aload_1
        12: aload_0
        13: getfield      #2                  // Field json:[B
        16: invokeinterface #21,  2           // InterfaceMethod java/io/ObjectOutput.write:([B)V
        21: return
      LineNumberTable:
        line 46: 0
        line 47: 11
        line 48: 21
      LocalVariableTable:
        Start  Length  Slot  Name   Signature
            0      22     0  this   Lcom/fasterxml/jackson/databind/node/NodeSerialization;
            0      22     1   out   Ljava/io/ObjectOutput;
    Exceptions:
      throws java.io.IOException

  public void readExternal(java.io.ObjectInput) throws java.io.IOException;
    descriptor: (Ljava/io/ObjectInput;)V
    flags: (0x0001) ACC_PUBLIC
    Code:
      stack=4, locals=3, args_size=2
         0: aload_1
         1: invokeinterface #22,  1           // InterfaceMethod java/io/ObjectInput.readInt:()I
         6: istore_2
         7: aload_0
         8: aload_0
         9: aload_1
        10: iload_2
        11: invokespecial #23                 // Method _read:(Ljava/io/ObjectInput;I)[B
        14: putfield      #2                  // Field json:[B
        17: return
      LineNumberTable:
        line 52: 0
        line 53: 7
        line 54: 17
      LocalVariableTable:
        Start  Length  Slot  Name   Signature
            0      18     0  this   Lcom/fasterxml/jackson/databind/node/NodeSerialization;
            0      18     1    in   Ljava/io/ObjectInput;
            7      11     2   len   I
    Exceptions:
      throws java.io.IOException

  private byte[] _read(java.io.ObjectInput, int) throws java.io.IOException;
    descriptor: (Ljava/io/ObjectInput;I)[B
    flags: (0x0002) ACC_PRIVATE
    Code:
      stack=4, locals=12, args_size=3
         0: iload_2
         1: ldc           #24                 // int 100000
         3: if_icmpgt     21
         6: iload_2
         7: newarray       byte
         9: astore_3
        10: aload_1
        11: aload_3
        12: iconst_0
        13: iload_2
        14: invokeinterface #25,  4           // InterfaceMethod java/io/ObjectInput.readFully:([BII)V
        19: aload_3
        20: areturn
        21: new           #26                 // class com/fasterxml/jackson/core/util/ByteArrayBuilder
        24: dup
        25: ldc           #24                 // int 100000
        27: invokespecial #27                 // Method com/fasterxml/jackson/core/util/ByteArrayBuilder."<init>":(I)V
        30: astore_3
        31: aconst_null
        32: astore        4
        34: aload_3
        35: invokevirtual #28                 // Method com/fasterxml/jackson/core/util/ByteArrayBuilder.resetAndGetFirstSegment:()[B
        38: astore        5
        40: iconst_0
        41: istore        6
        43: aload         5
        45: arraylength
        46: iload         6
        48: isub
        49: iload_2
        50: invokestatic  #29                 // Method java/lang/Math.min:(II)I
        53: istore        7
        55: aload_1
        56: aload         5
        58: iconst_0
        59: iload         7
        61: invokeinterface #25,  4           // InterfaceMethod java/io/ObjectInput.readFully:([BII)V
        66: iload_2
        67: iload         7
        69: isub
        70: istore_2
        71: iload         6
        73: iload         7
        75: iadd
        76: istore        6
        78: iload_2
        79: ifne          125
        82: aload_3
        83: iload         6
        85: invokevirtual #30                 // Method com/fasterxml/jackson/core/util/ByteArrayBuilder.completeAndCoalesce:(I)[B
        88: astore        8
        90: aload_3
        91: ifnull        122
        94: aload         4
        96: ifnull        118
        99: aload_3
       100: invokevirtual #31                 // Method com/fasterxml/jackson/core/util/ByteArrayBuilder.close:()V
       103: goto          122
       106: astore        9
       108: aload         4
       110: aload         9
       112: invokevirtual #33                 // Method java/lang/Throwable.addSuppressed:(Ljava/lang/Throwable;)V
       115: goto          122
       118: aload_3
       119: invokevirtual #31                 // Method com/fasterxml/jackson/core/util/ByteArrayBuilder.close:()V
       122: aload         8
       124: areturn
       125: iload         6
       127: aload         5
       129: arraylength
       130: if_icmpne     142
       133: aload_3
       134: invokevirtual #34                 // Method com/fasterxml/jackson/core/util/ByteArrayBuilder.finishCurrentSegment:()[B
       137: astore        5
       139: iconst_0
       140: istore        6
       142: goto          43
       145: astore        5
       147: aload         5
       149: astore        4
       151: aload         5
       153: athrow
       154: astore        10
       156: aload_3
       157: ifnull        188
       160: aload         4
       162: ifnull        184
       165: aload_3
       166: invokevirtual #31                 // Method com/fasterxml/jackson/core/util/ByteArrayBuilder.close:()V
       169: goto          188
       172: astore        11
       174: aload         4
       176: aload         11
       178: invokevirtual #33                 // Method java/lang/Throwable.addSuppressed:(Ljava/lang/Throwable;)V
       181: goto          188
       184: aload_3
       185: invokevirtual #31                 // Method com/fasterxml/jackson/core/util/ByteArrayBuilder.close:()V
       188: aload         10
       190: athrow
      Exception table:
         from    to  target type
            99   103   106   Class java/lang/Throwable
            34    90   145   Class java/lang/Throwable
           125   145   145   Class java/lang/Throwable
            34    90   154   any
           165   169   172   Class java/lang/Throwable
           125   156   154   any
      LineNumberTable:
        line 58: 0
        line 59: 6
        line 60: 10
        line 61: 19
        line 65: 21
        line 66: 34
        line 67: 40
        line 69: 43
        line 70: 55
        line 71: 66
        line 72: 71
        line 74: 78
        line 75: 82
        line 83: 90
        line 75: 122
        line 78: 125
        line 79: 133
        line 80: 139
        line 82: 142
        line 65: 145
        line 83: 154
      LocalVariableTable:
        Start  Length  Slot  Name   Signature
           10      11     3 result   [B
           55      87     7 toRead   I
           40     105     5 buffer   [B
           43     102     6 outOffset   I
           31     160     3    bb   Lcom/fasterxml/jackson/core/util/ByteArrayBuilder;
            0     191     0  this   Lcom/fasterxml/jackson/databind/node/NodeSerialization;
            0     191     1    in   Ljava/io/ObjectInput;
            0     191     2 expLen   I
      StackMapTable: number_of_entries = 12
        frame_type = 21 /* same */
        frame_type = 255 /* full_frame */
          offset_delta = 21
          locals = [ class com/fasterxml/jackson/databind/node/NodeSerialization, class java/io/ObjectInput, int, class com/fasterxml/jackson/core/util/ByteArrayBuilder, class java/lang/Throwable, class "[B", int ]
          stack = []
        frame_type = 255 /* full_frame */
          offset_delta = 62
          locals = [ class com/fasterxml/jackson/databind/node/NodeSerialization, class java/io/ObjectInput, int, class com/fasterxml/jackson/core/util/ByteArrayBuilder, class java/lang/Throwable, class "[B", int, int, class "[B" ]
          stack = [ class java/lang/Throwable ]
        frame_type = 11 /* same */
        frame_type = 3 /* same */
        frame_type = 250 /* chop */
          offset_delta = 2
        frame_type = 250 /* chop */
          offset_delta = 16
        frame_type = 255 /* full_frame */
          offset_delta = 2
          locals = [ class com/fasterxml/jackson/databind/node/NodeSerialization, class java/io/ObjectInput, int, class com/fasterxml/jackson/core/util/ByteArrayBuilder, class java/lang/Throwable ]
          stack = [ class java/lang/Throwable ]
        frame_type = 72 /* same_locals_1_stack_item */
          stack = [ class java/lang/Throwable ]
        frame_type = 255 /* full_frame */
          offset_delta = 17
          locals = [ class com/fasterxml/jackson/databind/node/NodeSerialization, class java/io/ObjectInput, int, class com/fasterxml/jackson/core/util/ByteArrayBuilder, class java/lang/Throwable, top, top, top, top, top, class java/lang/Throwable ]
          stack = [ class java/lang/Throwable ]
        frame_type = 11 /* same */
        frame_type = 3 /* same */
    Exceptions:
      throws java.io.IOException
}
SourceFile: "NodeSerialization.java"
