Classfile /Users/mw/Projects/slang-braindump/.jar/jar8/assemble/slang-braindump/assemble/content/org/scalatest/matchers/must/Matchers$Collected.class
  Last modified May 29, 2022; size 1023 bytes
  SHA-256 checksum b8b8f74d50d536fcf74f41a2350410e0dfdefccccde9c3aca3e4c667345c9006
  Compiled from "Matchers.scala"
public class org.scalatest.matchers.must.Matchers$Collected implements java.io.Serializable
  minor version: 0
  major version: 52
  flags: (0x0021) ACC_PUBLIC, ACC_SUPER
  this_class: #2                          // org/scalatest/matchers/must/Matchers$Collected
  super_class: #4                         // java/lang/Object
  interfaces: 1, fields: 2, methods: 3, attributes: 4
Constant pool:
   #1 = Utf8               org/scalatest/matchers/must/Matchers$Collected
   #2 = Class              #1             // org/scalatest/matchers/must/Matchers$Collected
   #3 = Utf8               java/lang/Object
   #4 = Class              #3             // java/lang/Object
   #5 = Utf8               java/io/Serializable
   #6 = Class              #5             // java/io/Serializable
   #7 = Utf8               Matchers.scala
   #8 = Utf8               org/scalatest/matchers/must/Matchers
   #9 = Class              #8             // org/scalatest/matchers/must/Matchers
  #10 = Utf8               Collected
  #11 = Utf8               name
  #12 = Utf8               Ljava/lang/String;
  #13 = Utf8               $outer
  #14 = Utf8               Lorg/scalatest/matchers/must/Matchers;
  #15 = Utf8               toString
  #16 = Utf8               ()Ljava/lang/String;
  #17 = NameAndType        #11:#12        // name:Ljava/lang/String;
  #18 = Fieldref           #2.#17         // org/scalatest/matchers/must/Matchers$Collected.name:Ljava/lang/String;
  #19 = Utf8               this
  #20 = Utf8               Lorg/scalatest/matchers/must/Matchers$Collected;
  #21 = Utf8               org$scalatest$matchers$must$Matchers$Collected$$$outer
  #22 = Utf8               ()Lorg/scalatest/matchers/must/Matchers;
  #23 = NameAndType        #13:#14        // $outer:Lorg/scalatest/matchers/must/Matchers;
  #24 = Fieldref           #2.#23         // org/scalatest/matchers/must/Matchers$Collected.$outer:Lorg/scalatest/matchers/must/Matchers;
  #25 = Utf8               <init>
  #26 = Utf8               (Lorg/scalatest/matchers/must/Matchers;Ljava/lang/String;)V
  #27 = Utf8               ()V
  #28 = NameAndType        #25:#27        // "<init>":()V
  #29 = Methodref          #4.#28         // java/lang/Object."<init>":()V
  #30 = Utf8               Code
  #31 = Utf8               LineNumberTable
  #32 = Utf8               LocalVariableTable
  #33 = Utf8               StackMapTable
  #34 = Utf8               MethodParameters
  #35 = Utf8               InnerClasses
  #36 = Utf8               SourceFile
  #37 = Utf8               ScalaInlineInfo
  #38 = Utf8               Scala
{
  private final java.lang.String name;
    descriptor: Ljava/lang/String;
    flags: (0x0012) ACC_PRIVATE, ACC_FINAL

  public final org.scalatest.matchers.must.Matchers $outer;
    descriptor: Lorg/scalatest/matchers/must/Matchers;
    flags: (0x1011) ACC_PUBLIC, ACC_FINAL, ACC_SYNTHETIC

  public java.lang.String toString();
    descriptor: ()Ljava/lang/String;
    flags: (0x0001) ACC_PUBLIC
    Code:
      stack=1, locals=1, args_size=1
         0: aload_0
         1: getfield      #18                 // Field name:Ljava/lang/String;
         4: areturn
      LineNumberTable:
        line 3080: 0
      LocalVariableTable:
        Start  Length  Slot  Name   Signature
            0       5     0  this   Lorg/scalatest/matchers/must/Matchers$Collected;

  public org.scalatest.matchers.must.Matchers org$scalatest$matchers$must$Matchers$Collected$$$outer();
    descriptor: ()Lorg/scalatest/matchers/must/Matchers;
    flags: (0x1001) ACC_PUBLIC, ACC_SYNTHETIC
    Code:
      stack=1, locals=1, args_size=1
         0: aload_0
         1: getfield      #24                 // Field $outer:Lorg/scalatest/matchers/must/Matchers;
         4: areturn
      LineNumberTable:
        line 3079: 0
      LocalVariableTable:
        Start  Length  Slot  Name   Signature
            0       5     0  this   Lorg/scalatest/matchers/must/Matchers$Collected;

  public org.scalatest.matchers.must.Matchers$Collected(org.scalatest.matchers.must.Matchers, java.lang.String);
    descriptor: (Lorg/scalatest/matchers/must/Matchers;Ljava/lang/String;)V
    flags: (0x0001) ACC_PUBLIC
    Code:
      stack=2, locals=3, args_size=3
         0: aload_0
         1: aload_2
         2: putfield      #18                 // Field name:Ljava/lang/String;
         5: aload_1
         6: ifnonnull     11
         9: aconst_null
        10: athrow
        11: aload_0
        12: aload_1
        13: putfield      #24                 // Field $outer:Lorg/scalatest/matchers/must/Matchers;
        16: aload_0
        17: invokespecial #29                 // Method java/lang/Object."<init>":()V
        20: return
      StackMapTable: number_of_entries = 1
        frame_type = 11 /* same */
      LineNumberTable:
        line 3079: 0
      LocalVariableTable:
        Start  Length  Slot  Name   Signature
            0      21     0  this   Lorg/scalatest/matchers/must/Matchers$Collected;
            0      21     1 $outer   Lorg/scalatest/matchers/must/Matchers;
            0      21     2  name   Ljava/lang/String;
    MethodParameters:
      Name                           Flags
      $outer                         final synthetic
      name                           final
}
InnerClasses:
  public #10= #2 of #9;                   // Collected=class org/scalatest/matchers/must/Matchers$Collected of class org/scalatest/matchers/must/Matchers
SourceFile: "Matchers.scala"
  ScalaInlineInfo: length = 0x13 (unknown attribute)
   01 00 00 03 00 19 00 1A 00 00 15 00 16 00 00 0F
   00 10 00
  Scala: length = 0x0 (unknown attribute)

