Classfile /Users/mw/Projects/slang-braindump/.jar/jar8/assemble/slang-braindump/assemble/content/org/scalatest/matchers/must/Matchers$ResultOfHaveWordForExtent.class
  Last modified May 29, 2022; size 7812 bytes
  SHA-256 checksum 502c66b40c020b68fb4e3b207944d54ecd0dd05a10db0dcc94de88046ceca38d
  Compiled from "Matchers.scala"
public final class org.scalatest.matchers.must.Matchers$ResultOfHaveWordForExtent<A extends java.lang.Object> extends java.lang.Object
  minor version: 0
  major version: 52
  flags: (0x0031) ACC_PUBLIC, ACC_FINAL, ACC_SUPER
  this_class: #2                          // org/scalatest/matchers/must/Matchers$ResultOfHaveWordForExtent
  super_class: #5                         // java/lang/Object
  interfaces: 0, fields: 4, methods: 15, attributes: 6
Constant pool:
    #1 = Utf8               org/scalatest/matchers/must/Matchers$ResultOfHaveWordForExtent
    #2 = Class              #1            // org/scalatest/matchers/must/Matchers$ResultOfHaveWordForExtent
    #3 = Utf8               <A:Ljava/lang/Object;>Ljava/lang/Object;
    #4 = Utf8               java/lang/Object
    #5 = Class              #4            // java/lang/Object
    #6 = Utf8               Matchers.scala
    #7 = Utf8               java/lang/invoke/MethodHandles$Lookup
    #8 = Class              #7            // java/lang/invoke/MethodHandles$Lookup
    #9 = Utf8               java/lang/invoke/MethodHandles
   #10 = Class              #9            // java/lang/invoke/MethodHandles
   #11 = Utf8               Lookup
   #12 = Utf8               org/scalatest/matchers/must/Matchers
   #13 = Class              #12           // org/scalatest/matchers/must/Matchers
   #14 = Utf8               ResultOfHaveWordForExtent
   #15 = Utf8               left
   #16 = Utf8               Ljava/lang/Object;
   #17 = Utf8               TA;
   #18 = Utf8               mustBeTrue
   #19 = Utf8               Z
   #20 = Utf8               prettifier
   #21 = Utf8               Lorg/scalactic/Prettifier;
   #22 = Utf8               pos
   #23 = Utf8               Lorg/scalactic/source/Position;
   #24 = Utf8               length
   #25 = Utf8               (JLorg/scalatest/enablers/Length;)Lorg/scalatest/compatible/Assertion;
   #26 = Utf8               (JLorg/scalatest/enablers/Length<TA;>;)Lorg/scalatest/compatible/Assertion;
   #27 = Utf8               expectedLength
   #28 = Utf8               len
   #29 = NameAndType        #15:#16       // left:Ljava/lang/Object;
   #30 = Fieldref           #2.#29        // org/scalatest/matchers/must/Matchers$ResultOfHaveWordForExtent.left:Ljava/lang/Object;
   #31 = Utf8               org/scalatest/enablers/Length
   #32 = Class              #31           // org/scalatest/enablers/Length
   #33 = Utf8               lengthOf
   #34 = Utf8               (Ljava/lang/Object;)J
   #35 = NameAndType        #33:#34       // lengthOf:(Ljava/lang/Object;)J
   #36 = InterfaceMethodref #32.#35       // org/scalatest/enablers/Length.lengthOf:(Ljava/lang/Object;)J
   #37 = NameAndType        #18:#19       // mustBeTrue:Z
   #38 = Fieldref           #2.#37        // org/scalatest/matchers/must/Matchers$ResultOfHaveWordForExtent.mustBeTrue:Z
   #39 = Utf8               org/scalatest/matchers/MatchersHelper$
   #40 = Class              #39           // org/scalatest/matchers/MatchersHelper$
   #41 = Utf8               MODULE$
   #42 = Utf8               Lorg/scalatest/matchers/MatchersHelper$;
   #43 = NameAndType        #41:#42       // MODULE$:Lorg/scalatest/matchers/MatchersHelper$;
   #44 = Fieldref           #40.#43       // org/scalatest/matchers/MatchersHelper$.MODULE$:Lorg/scalatest/matchers/MatchersHelper$;
   #45 = Utf8               ()Ljava/lang/Object;
   #46 = MethodType         #45           //  ()Ljava/lang/Object;
   #47 = Utf8               $anonfun$length$1
   #48 = Utf8               (Lorg/scalatest/matchers/must/Matchers$ResultOfHaveWordForExtent;JJ)Ljava/lang/String;
   #49 = NameAndType        #47:#48       // $anonfun$length$1:(Lorg/scalatest/matchers/must/Matchers$ResultOfHaveWordForExtent;JJ)Ljava/lang/String;
   #50 = Methodref          #2.#49        // org/scalatest/matchers/must/Matchers$ResultOfHaveWordForExtent.$anonfun$length$1:(Lorg/scalatest/matchers/must/Matchers$ResultOfHaveWordForExtent;JJ)Ljava/lang/String;
   #51 = MethodHandle       6:#50         // REF_invokeStatic org/scalatest/matchers/must/Matchers$ResultOfHaveWordForExtent.$anonfun$length$1:(Lorg/scalatest/matchers/must/Matchers$ResultOfHaveWordForExtent;JJ)Ljava/lang/String;
   #52 = Utf8               ()Ljava/lang/String;
   #53 = MethodType         #52           //  ()Ljava/lang/String;
   #54 = Integer            5
   #55 = Integer            1
   #56 = Utf8               java/lang/invoke/LambdaMetafactory
   #57 = Class              #56           // java/lang/invoke/LambdaMetafactory
   #58 = Utf8               altMetafactory
   #59 = Utf8               (Ljava/lang/invoke/MethodHandles$Lookup;Ljava/lang/String;Ljava/lang/invoke/MethodType;[Ljava/lang/Object;)Ljava/lang/invoke/CallSite;
   #60 = NameAndType        #58:#59       // altMetafactory:(Ljava/lang/invoke/MethodHandles$Lookup;Ljava/lang/String;Ljava/lang/invoke/MethodType;[Ljava/lang/Object;)Ljava/lang/invoke/CallSite;
   #61 = Methodref          #57.#60       // java/lang/invoke/LambdaMetafactory.altMetafactory:(Ljava/lang/invoke/MethodHandles$Lookup;Ljava/lang/String;Ljava/lang/invoke/MethodType;[Ljava/lang/Object;)Ljava/lang/invoke/CallSite;
   #62 = MethodHandle       6:#61         // REF_invokeStatic java/lang/invoke/LambdaMetafactory.altMetafactory:(Ljava/lang/invoke/MethodHandles$Lookup;Ljava/lang/String;Ljava/lang/invoke/MethodType;[Ljava/lang/Object;)Ljava/lang/invoke/CallSite;
   #63 = Utf8               apply
   #64 = Utf8               (Lorg/scalatest/matchers/must/Matchers$ResultOfHaveWordForExtent;JJ)Lscala/Function0;
   #65 = NameAndType        #63:#64       // apply:(Lorg/scalatest/matchers/must/Matchers$ResultOfHaveWordForExtent;JJ)Lscala/Function0;
   #66 = InvokeDynamic      #0:#65        // #0:apply:(Lorg/scalatest/matchers/must/Matchers$ResultOfHaveWordForExtent;JJ)Lscala/Function0;
   #67 = Utf8               scala/None$
   #68 = Class              #67           // scala/None$
   #69 = Utf8               Lscala/None$;
   #70 = NameAndType        #41:#69       // MODULE$:Lscala/None$;
   #71 = Fieldref           #68.#70       // scala/None$.MODULE$:Lscala/None$;
   #72 = NameAndType        #22:#23       // pos:Lorg/scalactic/source/Position;
   #73 = Fieldref           #2.#72        // org/scalatest/matchers/must/Matchers$ResultOfHaveWordForExtent.pos:Lorg/scalactic/source/Position;
   #74 = Utf8               indicateFailure
   #75 = Utf8               (Lscala/Function0;Lscala/Option;Lorg/scalactic/source/Position;)Lorg/scalatest/compatible/Assertion;
   #76 = NameAndType        #74:#75       // indicateFailure:(Lscala/Function0;Lscala/Option;Lorg/scalactic/source/Position;)Lorg/scalatest/compatible/Assertion;
   #77 = Methodref          #40.#76       // org/scalatest/matchers/MatchersHelper$.indicateFailure:(Lscala/Function0;Lscala/Option;Lorg/scalactic/source/Position;)Lorg/scalatest/compatible/Assertion;
   #78 = Utf8               $anonfun$length$2
   #79 = Utf8               (Lorg/scalatest/matchers/must/Matchers$ResultOfHaveWordForExtent;J)Ljava/lang/String;
   #80 = NameAndType        #78:#79       // $anonfun$length$2:(Lorg/scalatest/matchers/must/Matchers$ResultOfHaveWordForExtent;J)Ljava/lang/String;
   #81 = Methodref          #2.#80        // org/scalatest/matchers/must/Matchers$ResultOfHaveWordForExtent.$anonfun$length$2:(Lorg/scalatest/matchers/must/Matchers$ResultOfHaveWordForExtent;J)Ljava/lang/String;
   #82 = MethodHandle       6:#81         // REF_invokeStatic org/scalatest/matchers/must/Matchers$ResultOfHaveWordForExtent.$anonfun$length$2:(Lorg/scalatest/matchers/must/Matchers$ResultOfHaveWordForExtent;J)Ljava/lang/String;
   #83 = Utf8               (Lorg/scalatest/matchers/must/Matchers$ResultOfHaveWordForExtent;J)Lscala/Function0;
   #84 = NameAndType        #63:#83       // apply:(Lorg/scalatest/matchers/must/Matchers$ResultOfHaveWordForExtent;J)Lscala/Function0;
   #85 = InvokeDynamic      #1:#84        // #1:apply:(Lorg/scalatest/matchers/must/Matchers$ResultOfHaveWordForExtent;J)Lscala/Function0;
   #86 = Utf8               $anonfun$length$3
   #87 = NameAndType        #86:#48       // $anonfun$length$3:(Lorg/scalatest/matchers/must/Matchers$ResultOfHaveWordForExtent;JJ)Ljava/lang/String;
   #88 = Methodref          #2.#87        // org/scalatest/matchers/must/Matchers$ResultOfHaveWordForExtent.$anonfun$length$3:(Lorg/scalatest/matchers/must/Matchers$ResultOfHaveWordForExtent;JJ)Ljava/lang/String;
   #89 = MethodHandle       6:#88         // REF_invokeStatic org/scalatest/matchers/must/Matchers$ResultOfHaveWordForExtent.$anonfun$length$3:(Lorg/scalatest/matchers/must/Matchers$ResultOfHaveWordForExtent;JJ)Ljava/lang/String;
   #90 = InvokeDynamic      #2:#65        // #2:apply:(Lorg/scalatest/matchers/must/Matchers$ResultOfHaveWordForExtent;JJ)Lscala/Function0;
   #91 = Utf8               indicateSuccess
   #92 = Utf8               (ZLscala/Function0;Lscala/Function0;)Lorg/scalatest/compatible/Assertion;
   #93 = NameAndType        #91:#92       // indicateSuccess:(ZLscala/Function0;Lscala/Function0;)Lorg/scalatest/compatible/Assertion;
   #94 = Methodref          #40.#93       // org/scalatest/matchers/MatchersHelper$.indicateSuccess:(ZLscala/Function0;Lscala/Function0;)Lorg/scalatest/compatible/Assertion;
   #95 = Utf8               leftLength
   #96 = Utf8               J
   #97 = Utf8               this
   #98 = Utf8               Lorg/scalatest/matchers/must/Matchers$ResultOfHaveWordForExtent;
   #99 = Utf8               Lorg/scalatest/enablers/Length;
  #100 = Utf8               org/scalatest/compatible/Assertion
  #101 = Class              #100          // org/scalatest/compatible/Assertion
  #102 = Utf8               size
  #103 = Utf8               (JLorg/scalatest/enablers/Size;)Lorg/scalatest/compatible/Assertion;
  #104 = Utf8               (JLorg/scalatest/enablers/Size<TA;>;)Lorg/scalatest/compatible/Assertion;
  #105 = Utf8               expectedSize
  #106 = Utf8               sz
  #107 = Utf8               org/scalatest/enablers/Size
  #108 = Class              #107          // org/scalatest/enablers/Size
  #109 = Utf8               sizeOf
  #110 = NameAndType        #109:#34      // sizeOf:(Ljava/lang/Object;)J
  #111 = InterfaceMethodref #108.#110     // org/scalatest/enablers/Size.sizeOf:(Ljava/lang/Object;)J
  #112 = Utf8               $anonfun$size$1
  #113 = NameAndType        #112:#48      // $anonfun$size$1:(Lorg/scalatest/matchers/must/Matchers$ResultOfHaveWordForExtent;JJ)Ljava/lang/String;
  #114 = Methodref          #2.#113       // org/scalatest/matchers/must/Matchers$ResultOfHaveWordForExtent.$anonfun$size$1:(Lorg/scalatest/matchers/must/Matchers$ResultOfHaveWordForExtent;JJ)Ljava/lang/String;
  #115 = MethodHandle       6:#114        // REF_invokeStatic org/scalatest/matchers/must/Matchers$ResultOfHaveWordForExtent.$anonfun$size$1:(Lorg/scalatest/matchers/must/Matchers$ResultOfHaveWordForExtent;JJ)Ljava/lang/String;
  #116 = InvokeDynamic      #3:#65        // #3:apply:(Lorg/scalatest/matchers/must/Matchers$ResultOfHaveWordForExtent;JJ)Lscala/Function0;
  #117 = Utf8               $anonfun$size$2
  #118 = NameAndType        #117:#79      // $anonfun$size$2:(Lorg/scalatest/matchers/must/Matchers$ResultOfHaveWordForExtent;J)Ljava/lang/String;
  #119 = Methodref          #2.#118       // org/scalatest/matchers/must/Matchers$ResultOfHaveWordForExtent.$anonfun$size$2:(Lorg/scalatest/matchers/must/Matchers$ResultOfHaveWordForExtent;J)Ljava/lang/String;
  #120 = MethodHandle       6:#119        // REF_invokeStatic org/scalatest/matchers/must/Matchers$ResultOfHaveWordForExtent.$anonfun$size$2:(Lorg/scalatest/matchers/must/Matchers$ResultOfHaveWordForExtent;J)Ljava/lang/String;
  #121 = InvokeDynamic      #4:#84        // #4:apply:(Lorg/scalatest/matchers/must/Matchers$ResultOfHaveWordForExtent;J)Lscala/Function0;
  #122 = Utf8               $anonfun$size$3
  #123 = NameAndType        #122:#48      // $anonfun$size$3:(Lorg/scalatest/matchers/must/Matchers$ResultOfHaveWordForExtent;JJ)Ljava/lang/String;
  #124 = Methodref          #2.#123       // org/scalatest/matchers/must/Matchers$ResultOfHaveWordForExtent.$anonfun$size$3:(Lorg/scalatest/matchers/must/Matchers$ResultOfHaveWordForExtent;JJ)Ljava/lang/String;
  #125 = MethodHandle       6:#124        // REF_invokeStatic org/scalatest/matchers/must/Matchers$ResultOfHaveWordForExtent.$anonfun$size$3:(Lorg/scalatest/matchers/must/Matchers$ResultOfHaveWordForExtent;JJ)Ljava/lang/String;
  #126 = InvokeDynamic      #5:#65        // #5:apply:(Lorg/scalatest/matchers/must/Matchers$ResultOfHaveWordForExtent;JJ)Lscala/Function0;
  #127 = Utf8               leftSize
  #128 = Utf8               Lorg/scalatest/enablers/Size;
  #129 = Utf8               message
  #130 = Utf8               (Ljava/lang/String;Lorg/scalatest/enablers/Messaging;)Lorg/scalatest/compatible/Assertion;
  #131 = Utf8               (Ljava/lang/String;Lorg/scalatest/enablers/Messaging<TA;>;)Lorg/scalatest/compatible/Assertion;
  #132 = Utf8               expectedMessage
  #133 = Utf8               messaging
  #134 = Utf8               org/scalatest/enablers/Messaging
  #135 = Class              #134          // org/scalatest/enablers/Messaging
  #136 = Utf8               messageOf
  #137 = Utf8               (Ljava/lang/Object;)Ljava/lang/String;
  #138 = NameAndType        #136:#137     // messageOf:(Ljava/lang/Object;)Ljava/lang/String;
  #139 = InterfaceMethodref #135.#138     // org/scalatest/enablers/Messaging.messageOf:(Ljava/lang/Object;)Ljava/lang/String;
  #140 = Utf8               equals
  #141 = Utf8               (Ljava/lang/Object;)Z
  #142 = NameAndType        #140:#141     // equals:(Ljava/lang/Object;)Z
  #143 = Methodref          #5.#142       // java/lang/Object.equals:(Ljava/lang/Object;)Z
  #144 = Utf8               $anonfun$message$1
  #145 = Utf8               (Lorg/scalatest/matchers/must/Matchers$ResultOfHaveWordForExtent;Ljava/lang/String;Ljava/lang/String;)Ljava/lang/String;
  #146 = NameAndType        #144:#145     // $anonfun$message$1:(Lorg/scalatest/matchers/must/Matchers$ResultOfHaveWordForExtent;Ljava/lang/String;Ljava/lang/String;)Ljava/lang/String;
  #147 = Methodref          #2.#146       // org/scalatest/matchers/must/Matchers$ResultOfHaveWordForExtent.$anonfun$message$1:(Lorg/scalatest/matchers/must/Matchers$ResultOfHaveWordForExtent;Ljava/lang/String;Ljava/lang/String;)Ljava/lang/String;
  #148 = MethodHandle       6:#147        // REF_invokeStatic org/scalatest/matchers/must/Matchers$ResultOfHaveWordForExtent.$anonfun$message$1:(Lorg/scalatest/matchers/must/Matchers$ResultOfHaveWordForExtent;Ljava/lang/String;Ljava/lang/String;)Ljava/lang/String;
  #149 = Utf8               (Lorg/scalatest/matchers/must/Matchers$ResultOfHaveWordForExtent;Ljava/lang/String;Ljava/lang/String;)Lscala/Function0;
  #150 = NameAndType        #63:#149      // apply:(Lorg/scalatest/matchers/must/Matchers$ResultOfHaveWordForExtent;Ljava/lang/String;Ljava/lang/String;)Lscala/Function0;
  #151 = InvokeDynamic      #6:#150       // #6:apply:(Lorg/scalatest/matchers/must/Matchers$ResultOfHaveWordForExtent;Ljava/lang/String;Ljava/lang/String;)Lscala/Function0;
  #152 = Utf8               $anonfun$message$2
  #153 = Utf8               (Lorg/scalatest/matchers/must/Matchers$ResultOfHaveWordForExtent;Ljava/lang/String;)Ljava/lang/String;
  #154 = NameAndType        #152:#153     // $anonfun$message$2:(Lorg/scalatest/matchers/must/Matchers$ResultOfHaveWordForExtent;Ljava/lang/String;)Ljava/lang/String;
  #155 = Methodref          #2.#154       // org/scalatest/matchers/must/Matchers$ResultOfHaveWordForExtent.$anonfun$message$2:(Lorg/scalatest/matchers/must/Matchers$ResultOfHaveWordForExtent;Ljava/lang/String;)Ljava/lang/String;
  #156 = MethodHandle       6:#155        // REF_invokeStatic org/scalatest/matchers/must/Matchers$ResultOfHaveWordForExtent.$anonfun$message$2:(Lorg/scalatest/matchers/must/Matchers$ResultOfHaveWordForExtent;Ljava/lang/String;)Ljava/lang/String;
  #157 = Utf8               (Lorg/scalatest/matchers/must/Matchers$ResultOfHaveWordForExtent;Ljava/lang/String;)Lscala/Function0;
  #158 = NameAndType        #63:#157      // apply:(Lorg/scalatest/matchers/must/Matchers$ResultOfHaveWordForExtent;Ljava/lang/String;)Lscala/Function0;
  #159 = InvokeDynamic      #7:#158       // #7:apply:(Lorg/scalatest/matchers/must/Matchers$ResultOfHaveWordForExtent;Ljava/lang/String;)Lscala/Function0;
  #160 = Utf8               $anonfun$message$3
  #161 = NameAndType        #160:#145     // $anonfun$message$3:(Lorg/scalatest/matchers/must/Matchers$ResultOfHaveWordForExtent;Ljava/lang/String;Ljava/lang/String;)Ljava/lang/String;
  #162 = Methodref          #2.#161       // org/scalatest/matchers/must/Matchers$ResultOfHaveWordForExtent.$anonfun$message$3:(Lorg/scalatest/matchers/must/Matchers$ResultOfHaveWordForExtent;Ljava/lang/String;Ljava/lang/String;)Ljava/lang/String;
  #163 = MethodHandle       6:#162        // REF_invokeStatic org/scalatest/matchers/must/Matchers$ResultOfHaveWordForExtent.$anonfun$message$3:(Lorg/scalatest/matchers/must/Matchers$ResultOfHaveWordForExtent;Ljava/lang/String;Ljava/lang/String;)Ljava/lang/String;
  #164 = InvokeDynamic      #8:#150       // #8:apply:(Lorg/scalatest/matchers/must/Matchers$ResultOfHaveWordForExtent;Ljava/lang/String;Ljava/lang/String;)Lscala/Function0;
  #165 = Utf8               actualMessage
  #166 = Utf8               Ljava/lang/String;
  #167 = Utf8               Lorg/scalatest/enablers/Messaging;
  #168 = Utf8               java/lang/String
  #169 = Class              #168          // java/lang/String
  #170 = Utf8               toString
  #171 = Utf8               java/lang/StringBuilder
  #172 = Class              #171          // java/lang/StringBuilder
  #173 = Integer            29
  #174 = Utf8               <init>
  #175 = Utf8               (I)V
  #176 = NameAndType        #174:#175     // "<init>":(I)V
  #177 = Methodref          #172.#176     // java/lang/StringBuilder."<init>":(I)V
  #178 = Utf8               ResultOfHaveWordForExtent(
  #179 = String             #178          // ResultOfHaveWordForExtent(
  #180 = Utf8               append
  #181 = Utf8               (Ljava/lang/String;)Ljava/lang/StringBuilder;
  #182 = NameAndType        #180:#181     // append:(Ljava/lang/String;)Ljava/lang/StringBuilder;
  #183 = Methodref          #172.#182     // java/lang/StringBuilder.append:(Ljava/lang/String;)Ljava/lang/StringBuilder;
  #184 = Utf8               org/scalactic/Prettifier$
  #185 = Class              #184          // org/scalactic/Prettifier$
  #186 = Utf8               Lorg/scalactic/Prettifier$;
  #187 = NameAndType        #41:#186      // MODULE$:Lorg/scalactic/Prettifier$;
  #188 = Fieldref           #185.#187     // org/scalactic/Prettifier$.MODULE$:Lorg/scalactic/Prettifier$;
  #189 = Utf8               default
  #190 = Utf8               ()Lorg/scalactic/Prettifier;
  #191 = NameAndType        #189:#190     // default:()Lorg/scalactic/Prettifier;
  #192 = Methodref          #185.#191     // org/scalactic/Prettifier$.default:()Lorg/scalactic/Prettifier;
  #193 = Utf8               org/scalactic/Prettifier
  #194 = Class              #193          // org/scalactic/Prettifier
  #195 = NameAndType        #63:#137      // apply:(Ljava/lang/Object;)Ljava/lang/String;
  #196 = InterfaceMethodref #194.#195     // org/scalactic/Prettifier.apply:(Ljava/lang/Object;)Ljava/lang/String;
  #197 = Utf8               ,
  #198 = String             #197          // ,
  #199 = Utf8               scala/runtime/BoxesRunTime
  #200 = Class              #199          // scala/runtime/BoxesRunTime
  #201 = Utf8               boxToBoolean
  #202 = Utf8               (Z)Ljava/lang/Boolean;
  #203 = NameAndType        #201:#202     // boxToBoolean:(Z)Ljava/lang/Boolean;
  #204 = Methodref          #200.#203     // scala/runtime/BoxesRunTime.boxToBoolean:(Z)Ljava/lang/Boolean;
  #205 = Utf8               )
  #206 = String             #205          // )
  #207 = NameAndType        #170:#52      // toString:()Ljava/lang/String;
  #208 = Methodref          #172.#207     // java/lang/StringBuilder.toString:()Ljava/lang/String;
  #209 = Utf8               $this
  #210 = Utf8               leftLength$1
  #211 = Utf8               expectedLength$1
  #212 = Utf8               org/scalatest/FailureMessages$
  #213 = Class              #212          // org/scalatest/FailureMessages$
  #214 = Utf8               Lorg/scalatest/FailureMessages$;
  #215 = NameAndType        #41:#214      // MODULE$:Lorg/scalatest/FailureMessages$;
  #216 = Fieldref           #213.#215     // org/scalatest/FailureMessages$.MODULE$:Lorg/scalatest/FailureMessages$;
  #217 = NameAndType        #20:#21       // prettifier:Lorg/scalactic/Prettifier;
  #218 = Fieldref           #2.#217       // org/scalatest/matchers/must/Matchers$ResultOfHaveWordForExtent.prettifier:Lorg/scalactic/Prettifier;
  #219 = Utf8               boxToLong
  #220 = Utf8               (J)Ljava/lang/Long;
  #221 = NameAndType        #219:#220     // boxToLong:(J)Ljava/lang/Long;
  #222 = Methodref          #200.#221     // scala/runtime/BoxesRunTime.boxToLong:(J)Ljava/lang/Long;
  #223 = Utf8               hadLengthInsteadOfExpectedLength
  #224 = Utf8               (Lorg/scalactic/Prettifier;Ljava/lang/Object;Ljava/lang/Object;Ljava/lang/Object;)Ljava/lang/String;
  #225 = NameAndType        #223:#224     // hadLengthInsteadOfExpectedLength:(Lorg/scalactic/Prettifier;Ljava/lang/Object;Ljava/lang/Object;Ljava/lang/Object;)Ljava/lang/String;
  #226 = Methodref          #213.#225     // org/scalatest/FailureMessages$.hadLengthInsteadOfExpectedLength:(Lorg/scalactic/Prettifier;Ljava/lang/Object;Ljava/lang/Object;Ljava/lang/Object;)Ljava/lang/String;
  #227 = Utf8               hadLength
  #228 = Utf8               (Lorg/scalactic/Prettifier;Ljava/lang/Object;Ljava/lang/Object;)Ljava/lang/String;
  #229 = NameAndType        #227:#228     // hadLength:(Lorg/scalactic/Prettifier;Ljava/lang/Object;Ljava/lang/Object;)Ljava/lang/String;
  #230 = Methodref          #213.#229     // org/scalatest/FailureMessages$.hadLength:(Lorg/scalactic/Prettifier;Ljava/lang/Object;Ljava/lang/Object;)Ljava/lang/String;
  #231 = Utf8               leftSize$1
  #232 = Utf8               expectedSize$1
  #233 = Utf8               hadSizeInsteadOfExpectedSize
  #234 = NameAndType        #233:#224     // hadSizeInsteadOfExpectedSize:(Lorg/scalactic/Prettifier;Ljava/lang/Object;Ljava/lang/Object;Ljava/lang/Object;)Ljava/lang/String;
  #235 = Methodref          #213.#234     // org/scalatest/FailureMessages$.hadSizeInsteadOfExpectedSize:(Lorg/scalactic/Prettifier;Ljava/lang/Object;Ljava/lang/Object;Ljava/lang/Object;)Ljava/lang/String;
  #236 = Utf8               hadSize
  #237 = NameAndType        #236:#228     // hadSize:(Lorg/scalactic/Prettifier;Ljava/lang/Object;Ljava/lang/Object;)Ljava/lang/String;
  #238 = Methodref          #213.#237     // org/scalatest/FailureMessages$.hadSize:(Lorg/scalactic/Prettifier;Ljava/lang/Object;Ljava/lang/Object;)Ljava/lang/String;
  #239 = Utf8               actualMessage$1
  #240 = Utf8               expectedMessage$1
  #241 = Utf8               hadMessageInsteadOfExpectedMessage
  #242 = NameAndType        #241:#224     // hadMessageInsteadOfExpectedMessage:(Lorg/scalactic/Prettifier;Ljava/lang/Object;Ljava/lang/Object;Ljava/lang/Object;)Ljava/lang/String;
  #243 = Methodref          #213.#242     // org/scalatest/FailureMessages$.hadMessageInsteadOfExpectedMessage:(Lorg/scalactic/Prettifier;Ljava/lang/Object;Ljava/lang/Object;Ljava/lang/Object;)Ljava/lang/String;
  #244 = Utf8               hadExpectedMessage
  #245 = NameAndType        #244:#228     // hadExpectedMessage:(Lorg/scalactic/Prettifier;Ljava/lang/Object;Ljava/lang/Object;)Ljava/lang/String;
  #246 = Methodref          #213.#245     // org/scalatest/FailureMessages$.hadExpectedMessage:(Lorg/scalactic/Prettifier;Ljava/lang/Object;Ljava/lang/Object;)Ljava/lang/String;
  #247 = Utf8               (Lorg/scalatest/matchers/must/Matchers;Ljava/lang/Object;ZLorg/scalactic/Prettifier;Lorg/scalactic/source/Position;)V
  #248 = Utf8               (TA;ZLorg/scalactic/Prettifier;Lorg/scalactic/source/Position;)V
  #249 = Utf8               $outer
  #250 = Utf8               ()V
  #251 = NameAndType        #174:#250     // "<init>":()V
  #252 = Methodref          #5.#251       // java/lang/Object."<init>":()V
  #253 = Utf8               Lorg/scalatest/matchers/must/Matchers;
  #254 = Utf8               $deserializeLambda$
  #255 = Utf8               (Ljava/lang/invoke/SerializedLambda;)Ljava/lang/Object;
  #256 = Utf8               scala/runtime/LambdaDeserialize
  #257 = Class              #256          // scala/runtime/LambdaDeserialize
  #258 = Utf8               bootstrap
  #259 = Utf8               (Ljava/lang/invoke/MethodHandles$Lookup;Ljava/lang/String;Ljava/lang/invoke/MethodType;[Ljava/lang/invoke/MethodHandle;)Ljava/lang/invoke/CallSite;
  #260 = NameAndType        #258:#259     // bootstrap:(Ljava/lang/invoke/MethodHandles$Lookup;Ljava/lang/String;Ljava/lang/invoke/MethodType;[Ljava/lang/invoke/MethodHandle;)Ljava/lang/invoke/CallSite;
  #261 = Methodref          #257.#260     // scala/runtime/LambdaDeserialize.bootstrap:(Ljava/lang/invoke/MethodHandles$Lookup;Ljava/lang/String;Ljava/lang/invoke/MethodType;[Ljava/lang/invoke/MethodHandle;)Ljava/lang/invoke/CallSite;
  #262 = MethodHandle       6:#261        // REF_invokeStatic scala/runtime/LambdaDeserialize.bootstrap:(Ljava/lang/invoke/MethodHandles$Lookup;Ljava/lang/String;Ljava/lang/invoke/MethodType;[Ljava/lang/invoke/MethodHandle;)Ljava/lang/invoke/CallSite;
  #263 = Utf8               lambdaDeserialize
  #264 = NameAndType        #263:#255     // lambdaDeserialize:(Ljava/lang/invoke/SerializedLambda;)Ljava/lang/Object;
  #265 = InvokeDynamic      #9:#264       // #9:lambdaDeserialize:(Ljava/lang/invoke/SerializedLambda;)Ljava/lang/Object;
  #266 = Utf8               Signature
  #267 = Utf8               Code
  #268 = Utf8               StackMapTable
  #269 = Utf8               LineNumberTable
  #270 = Utf8               LocalVariableTable
  #271 = Utf8               MethodParameters
  #272 = Utf8               InnerClasses
  #273 = Utf8               SourceFile
  #274 = Utf8               BootstrapMethods
  #275 = Utf8               ScalaInlineInfo
  #276 = Utf8               Scala
{
  private final A left;
    descriptor: Ljava/lang/Object;
    flags: (0x0012) ACC_PRIVATE, ACC_FINAL
    Signature: #17                          // TA;

  private final boolean mustBeTrue;
    descriptor: Z
    flags: (0x0012) ACC_PRIVATE, ACC_FINAL

  private final org.scalactic.Prettifier prettifier;
    descriptor: Lorg/scalactic/Prettifier;
    flags: (0x0012) ACC_PRIVATE, ACC_FINAL

  private final org.scalactic.source.Position pos;
    descriptor: Lorg/scalactic/source/Position;
    flags: (0x0012) ACC_PRIVATE, ACC_FINAL

  public org.scalatest.compatible.Assertion length(long, org.scalatest.enablers.Length<A>);
    descriptor: (JLorg/scalatest/enablers/Length;)Lorg/scalatest/compatible/Assertion;
    flags: (0x0001) ACC_PUBLIC
    Code:
      stack=8, locals=6, args_size=3
         0: aload_3
         1: aload_0
         2: getfield      #30                 // Field left:Ljava/lang/Object;
         5: invokeinterface #36,  2           // InterfaceMethod org/scalatest/enablers/Length.lengthOf:(Ljava/lang/Object;)J
        10: lstore        4
        12: lload         4
        14: lload_1
        15: lcmp
        16: ifne          23
        19: iconst_1
        20: goto          24
        23: iconst_0
        24: aload_0
        25: getfield      #38                 // Field mustBeTrue:Z
        28: if_icmpeq     56
        31: getstatic     #44                 // Field org/scalatest/matchers/MatchersHelper$.MODULE$:Lorg/scalatest/matchers/MatchersHelper$;
        34: aload_0
        35: lload         4
        37: lload_1
        38: invokedynamic #66,  0             // InvokeDynamic #0:apply:(Lorg/scalatest/matchers/must/Matchers$ResultOfHaveWordForExtent;JJ)Lscala/Function0;
        43: getstatic     #71                 // Field scala/None$.MODULE$:Lscala/None$;
        46: aload_0
        47: getfield      #73                 // Field pos:Lorg/scalactic/source/Position;
        50: invokevirtual #77                 // Method org/scalatest/matchers/MatchersHelper$.indicateFailure:(Lscala/Function0;Lscala/Option;Lorg/scalactic/source/Position;)Lorg/scalatest/compatible/Assertion;
        53: goto          82
        56: getstatic     #44                 // Field org/scalatest/matchers/MatchersHelper$.MODULE$:Lorg/scalatest/matchers/MatchersHelper$;
        59: aload_0
        60: getfield      #38                 // Field mustBeTrue:Z
        63: aload_0
        64: lload_1
        65: invokedynamic #85,  0             // InvokeDynamic #1:apply:(Lorg/scalatest/matchers/must/Matchers$ResultOfHaveWordForExtent;J)Lscala/Function0;
        70: aload_0
        71: lload         4
        73: lload_1
        74: invokedynamic #90,  0             // InvokeDynamic #2:apply:(Lorg/scalatest/matchers/must/Matchers$ResultOfHaveWordForExtent;JJ)Lscala/Function0;
        79: invokevirtual #94                 // Method org/scalatest/matchers/MatchersHelper$.indicateSuccess:(ZLscala/Function0;Lscala/Function0;)Lorg/scalatest/compatible/Assertion;
        82: areturn
      StackMapTable: number_of_entries = 4
        frame_type = 252 /* append */
          offset_delta = 23
          locals = [ long ]
        frame_type = 64 /* same_locals_1_stack_item */
          stack = [ int ]
        frame_type = 31 /* same */
        frame_type = 89 /* same_locals_1_stack_item */
          stack = [ class org/scalatest/compatible/Assertion ]
      LineNumberTable:
        line 2696: 0
        line 2697: 12
        line 2698: 31
        line 2699: 56
      LocalVariableTable:
        Start  Length  Slot  Name   Signature
           12      70     4 leftLength   J
            0      83     0  this   Lorg/scalatest/matchers/must/Matchers$ResultOfHaveWordForExtent;
            0      83     1 expectedLength   J
            0      83     3   len   Lorg/scalatest/enablers/Length;
    Signature: #26                          // (JLorg/scalatest/enablers/Length<TA;>;)Lorg/scalatest/compatible/Assertion;
    MethodParameters:
      Name                           Flags
      expectedLength                 final
      len                            final

  public org.scalatest.compatible.Assertion size(long, org.scalatest.enablers.Size<A>);
    descriptor: (JLorg/scalatest/enablers/Size;)Lorg/scalatest/compatible/Assertion;
    flags: (0x0001) ACC_PUBLIC
    Code:
      stack=8, locals=6, args_size=3
         0: aload_3
         1: aload_0
         2: getfield      #30                 // Field left:Ljava/lang/Object;
         5: invokeinterface #111,  2          // InterfaceMethod org/scalatest/enablers/Size.sizeOf:(Ljava/lang/Object;)J
        10: lstore        4
        12: lload         4
        14: lload_1
        15: lcmp
        16: ifne          23
        19: iconst_1
        20: goto          24
        23: iconst_0
        24: aload_0
        25: getfield      #38                 // Field mustBeTrue:Z
        28: if_icmpeq     56
        31: getstatic     #44                 // Field org/scalatest/matchers/MatchersHelper$.MODULE$:Lorg/scalatest/matchers/MatchersHelper$;
        34: aload_0
        35: lload         4
        37: lload_1
        38: invokedynamic #116,  0            // InvokeDynamic #3:apply:(Lorg/scalatest/matchers/must/Matchers$ResultOfHaveWordForExtent;JJ)Lscala/Function0;
        43: getstatic     #71                 // Field scala/None$.MODULE$:Lscala/None$;
        46: aload_0
        47: getfield      #73                 // Field pos:Lorg/scalactic/source/Position;
        50: invokevirtual #77                 // Method org/scalatest/matchers/MatchersHelper$.indicateFailure:(Lscala/Function0;Lscala/Option;Lorg/scalactic/source/Position;)Lorg/scalatest/compatible/Assertion;
        53: goto          82
        56: getstatic     #44                 // Field org/scalatest/matchers/MatchersHelper$.MODULE$:Lorg/scalatest/matchers/MatchersHelper$;
        59: aload_0
        60: getfield      #38                 // Field mustBeTrue:Z
        63: aload_0
        64: lload_1
        65: invokedynamic #121,  0            // InvokeDynamic #4:apply:(Lorg/scalatest/matchers/must/Matchers$ResultOfHaveWordForExtent;J)Lscala/Function0;
        70: aload_0
        71: lload         4
        73: lload_1
        74: invokedynamic #126,  0            // InvokeDynamic #5:apply:(Lorg/scalatest/matchers/must/Matchers$ResultOfHaveWordForExtent;JJ)Lscala/Function0;
        79: invokevirtual #94                 // Method org/scalatest/matchers/MatchersHelper$.indicateSuccess:(ZLscala/Function0;Lscala/Function0;)Lorg/scalatest/compatible/Assertion;
        82: areturn
      StackMapTable: number_of_entries = 4
        frame_type = 252 /* append */
          offset_delta = 23
          locals = [ long ]
        frame_type = 64 /* same_locals_1_stack_item */
          stack = [ int ]
        frame_type = 31 /* same */
        frame_type = 89 /* same_locals_1_stack_item */
          stack = [ class org/scalatest/compatible/Assertion ]
      LineNumberTable:
        line 2718: 0
        line 2719: 12
        line 2720: 31
        line 2721: 56
      LocalVariableTable:
        Start  Length  Slot  Name   Signature
           12      70     4 leftSize   J
            0      83     0  this   Lorg/scalatest/matchers/must/Matchers$ResultOfHaveWordForExtent;
            0      83     1 expectedSize   J
            0      83     3    sz   Lorg/scalatest/enablers/Size;
    Signature: #104                         // (JLorg/scalatest/enablers/Size<TA;>;)Lorg/scalatest/compatible/Assertion;
    MethodParameters:
      Name                           Flags
      expectedSize                   final
      sz                             final

  public org.scalatest.compatible.Assertion message(java.lang.String, org.scalatest.enablers.Messaging<A>);
    descriptor: (Ljava/lang/String;Lorg/scalatest/enablers/Messaging;)Lorg/scalatest/compatible/Assertion;
    flags: (0x0001) ACC_PUBLIC
    Code:
      stack=6, locals=5, args_size=3
         0: aload_2
         1: aload_0
         2: getfield      #30                 // Field left:Ljava/lang/Object;
         5: invokeinterface #139,  2          // InterfaceMethod org/scalatest/enablers/Messaging.messageOf:(Ljava/lang/Object;)Ljava/lang/String;
        10: astore_3
        11: aload_3
        12: aload_1
        13: astore        4
        15: dup
        16: ifnonnull     28
        19: pop
        20: aload         4
        22: ifnull        36
        25: goto          40
        28: aload         4
        30: invokevirtual #143                // Method java/lang/Object.equals:(Ljava/lang/Object;)Z
        33: ifeq          40
        36: iconst_1
        37: goto          41
        40: iconst_0
        41: aload_0
        42: getfield      #38                 // Field mustBeTrue:Z
        45: if_icmpeq     72
        48: getstatic     #44                 // Field org/scalatest/matchers/MatchersHelper$.MODULE$:Lorg/scalatest/matchers/MatchersHelper$;
        51: aload_0
        52: aload_3
        53: aload_1
        54: invokedynamic #151,  0            // InvokeDynamic #6:apply:(Lorg/scalatest/matchers/must/Matchers$ResultOfHaveWordForExtent;Ljava/lang/String;Ljava/lang/String;)Lscala/Function0;
        59: getstatic     #71                 // Field scala/None$.MODULE$:Lscala/None$;
        62: aload_0
        63: getfield      #73                 // Field pos:Lorg/scalactic/source/Position;
        66: invokevirtual #77                 // Method org/scalatest/matchers/MatchersHelper$.indicateFailure:(Lscala/Function0;Lscala/Option;Lorg/scalactic/source/Position;)Lorg/scalatest/compatible/Assertion;
        69: goto          97
        72: getstatic     #44                 // Field org/scalatest/matchers/MatchersHelper$.MODULE$:Lorg/scalatest/matchers/MatchersHelper$;
        75: aload_0
        76: getfield      #38                 // Field mustBeTrue:Z
        79: aload_0
        80: aload_1
        81: invokedynamic #159,  0            // InvokeDynamic #7:apply:(Lorg/scalatest/matchers/must/Matchers$ResultOfHaveWordForExtent;Ljava/lang/String;)Lscala/Function0;
        86: aload_0
        87: aload_3
        88: aload_1
        89: invokedynamic #164,  0            // InvokeDynamic #8:apply:(Lorg/scalatest/matchers/must/Matchers$ResultOfHaveWordForExtent;Ljava/lang/String;Ljava/lang/String;)Lscala/Function0;
        94: invokevirtual #94                 // Method org/scalatest/matchers/MatchersHelper$.indicateSuccess:(ZLscala/Function0;Lscala/Function0;)Lorg/scalatest/compatible/Assertion;
        97: areturn
      StackMapTable: number_of_entries = 6
        frame_type = 255 /* full_frame */
          offset_delta = 28
          locals = [ class org/scalatest/matchers/must/Matchers$ResultOfHaveWordForExtent, class java/lang/String, class org/scalatest/enablers/Messaging, class java/lang/String, class java/lang/String ]
          stack = [ class java/lang/String ]
        frame_type = 7 /* same */
        frame_type = 3 /* same */
        frame_type = 64 /* same_locals_1_stack_item */
          stack = [ int ]
        frame_type = 30 /* same */
        frame_type = 88 /* same_locals_1_stack_item */
          stack = [ class org/scalatest/compatible/Assertion ]
      LineNumberTable:
        line 2733: 0
        line 2734: 11
        line 2735: 48
        line 2736: 72
      LocalVariableTable:
        Start  Length  Slot  Name   Signature
           11      86     3 actualMessage   Ljava/lang/String;
            0      98     0  this   Lorg/scalatest/matchers/must/Matchers$ResultOfHaveWordForExtent;
            0      98     1 expectedMessage   Ljava/lang/String;
            0      98     2 messaging   Lorg/scalatest/enablers/Messaging;
    Signature: #131                         // (Ljava/lang/String;Lorg/scalatest/enablers/Messaging<TA;>;)Lorg/scalatest/compatible/Assertion;
    MethodParameters:
      Name                           Flags
      expectedMessage                final
      messaging                      final

  public java.lang.String toString();
    descriptor: ()Ljava/lang/String;
    flags: (0x0001) ACC_PUBLIC
    Code:
      stack=3, locals=1, args_size=1
         0: new           #172                // class java/lang/StringBuilder
         3: dup
         4: ldc           #173                // int 29
         6: invokespecial #177                // Method java/lang/StringBuilder."<init>":(I)V
         9: ldc           #179                // String ResultOfHaveWordForExtent(
        11: invokevirtual #183                // Method java/lang/StringBuilder.append:(Ljava/lang/String;)Ljava/lang/StringBuilder;
        14: getstatic     #188                // Field org/scalactic/Prettifier$.MODULE$:Lorg/scalactic/Prettifier$;
        17: invokevirtual #192                // Method org/scalactic/Prettifier$.default:()Lorg/scalactic/Prettifier;
        20: aload_0
        21: getfield      #30                 // Field left:Ljava/lang/Object;
        24: invokeinterface #196,  2          // InterfaceMethod org/scalactic/Prettifier.apply:(Ljava/lang/Object;)Ljava/lang/String;
        29: invokevirtual #183                // Method java/lang/StringBuilder.append:(Ljava/lang/String;)Ljava/lang/StringBuilder;
        32: ldc           #198                // String ,
        34: invokevirtual #183                // Method java/lang/StringBuilder.append:(Ljava/lang/String;)Ljava/lang/StringBuilder;
        37: getstatic     #188                // Field org/scalactic/Prettifier$.MODULE$:Lorg/scalactic/Prettifier$;
        40: invokevirtual #192                // Method org/scalactic/Prettifier$.default:()Lorg/scalactic/Prettifier;
        43: aload_0
        44: getfield      #38                 // Field mustBeTrue:Z
        47: invokestatic  #204                // Method scala/runtime/BoxesRunTime.boxToBoolean:(Z)Ljava/lang/Boolean;
        50: invokeinterface #196,  2          // InterfaceMethod org/scalactic/Prettifier.apply:(Ljava/lang/Object;)Ljava/lang/String;
        55: invokevirtual #183                // Method java/lang/StringBuilder.append:(Ljava/lang/String;)Ljava/lang/StringBuilder;
        58: ldc           #206                // String )
        60: invokevirtual #183                // Method java/lang/StringBuilder.append:(Ljava/lang/String;)Ljava/lang/StringBuilder;
        63: invokevirtual #208                // Method java/lang/StringBuilder.toString:()Ljava/lang/String;
        66: areturn
      LineNumberTable:
        line 2744: 0
      LocalVariableTable:
        Start  Length  Slot  Name   Signature
            0      67     0  this   Lorg/scalatest/matchers/must/Matchers$ResultOfHaveWordForExtent;

  public static final java.lang.String $anonfun$length$1(org.scalatest.matchers.must.Matchers$ResultOfHaveWordForExtent, long, long);
    descriptor: (Lorg/scalatest/matchers/must/Matchers$ResultOfHaveWordForExtent;JJ)Ljava/lang/String;
    flags: (0x1019) ACC_PUBLIC, ACC_STATIC, ACC_FINAL, ACC_SYNTHETIC
    Code:
      stack=6, locals=5, args_size=3
         0: aload_0
         1: getfield      #38                 // Field mustBeTrue:Z
         4: ifeq          32
         7: getstatic     #216                // Field org/scalatest/FailureMessages$.MODULE$:Lorg/scalatest/FailureMessages$;
        10: aload_0
        11: getfield      #218                // Field prettifier:Lorg/scalactic/Prettifier;
        14: aload_0
        15: getfield      #30                 // Field left:Ljava/lang/Object;
        18: lload_1
        19: invokestatic  #222                // Method scala/runtime/BoxesRunTime.boxToLong:(J)Ljava/lang/Long;
        22: lload_3
        23: invokestatic  #222                // Method scala/runtime/BoxesRunTime.boxToLong:(J)Ljava/lang/Long;
        26: invokevirtual #226                // Method org/scalatest/FailureMessages$.hadLengthInsteadOfExpectedLength:(Lorg/scalactic/Prettifier;Ljava/lang/Object;Ljava/lang/Object;Ljava/lang/Object;)Ljava/lang/String;
        29: goto          50
        32: getstatic     #216                // Field org/scalatest/FailureMessages$.MODULE$:Lorg/scalatest/FailureMessages$;
        35: aload_0
        36: getfield      #218                // Field prettifier:Lorg/scalactic/Prettifier;
        39: aload_0
        40: getfield      #30                 // Field left:Ljava/lang/Object;
        43: lload_3
        44: invokestatic  #222                // Method scala/runtime/BoxesRunTime.boxToLong:(J)Ljava/lang/Long;
        47: invokevirtual #230                // Method org/scalatest/FailureMessages$.hadLength:(Lorg/scalactic/Prettifier;Ljava/lang/Object;Ljava/lang/Object;)Ljava/lang/String;
        50: areturn
      StackMapTable: number_of_entries = 2
        frame_type = 32 /* same */
        frame_type = 81 /* same_locals_1_stack_item */
          stack = [ class java/lang/String ]
      LineNumberTable:
        line 2698: 0
      LocalVariableTable:
        Start  Length  Slot  Name   Signature
            0      51     0 $this   Lorg/scalatest/matchers/must/Matchers$ResultOfHaveWordForExtent;
            0      51     1 leftLength$1   J
            0      51     3 expectedLength$1   J
    MethodParameters:
      Name                           Flags
      $this                          final synthetic
      leftLength$1                   final
      expectedLength$1               final

  public static final java.lang.String $anonfun$length$2(org.scalatest.matchers.must.Matchers$ResultOfHaveWordForExtent, long);
    descriptor: (Lorg/scalatest/matchers/must/Matchers$ResultOfHaveWordForExtent;J)Ljava/lang/String;
    flags: (0x1019) ACC_PUBLIC, ACC_STATIC, ACC_FINAL, ACC_SYNTHETIC
    Code:
      stack=5, locals=3, args_size=2
         0: getstatic     #216                // Field org/scalatest/FailureMessages$.MODULE$:Lorg/scalatest/FailureMessages$;
         3: aload_0
         4: getfield      #218                // Field prettifier:Lorg/scalactic/Prettifier;
         7: aload_0
         8: getfield      #30                 // Field left:Ljava/lang/Object;
        11: lload_1
        12: invokestatic  #222                // Method scala/runtime/BoxesRunTime.boxToLong:(J)Ljava/lang/Long;
        15: invokevirtual #230                // Method org/scalatest/FailureMessages$.hadLength:(Lorg/scalactic/Prettifier;Ljava/lang/Object;Ljava/lang/Object;)Ljava/lang/String;
        18: areturn
      LineNumberTable:
        line 2699: 0
      LocalVariableTable:
        Start  Length  Slot  Name   Signature
            0      19     0 $this   Lorg/scalatest/matchers/must/Matchers$ResultOfHaveWordForExtent;
            0      19     1 expectedLength$1   J
    MethodParameters:
      Name                           Flags
      $this                          final synthetic
      expectedLength$1               final

  public static final java.lang.String $anonfun$length$3(org.scalatest.matchers.must.Matchers$ResultOfHaveWordForExtent, long, long);
    descriptor: (Lorg/scalatest/matchers/must/Matchers$ResultOfHaveWordForExtent;JJ)Ljava/lang/String;
    flags: (0x1019) ACC_PUBLIC, ACC_STATIC, ACC_FINAL, ACC_SYNTHETIC
    Code:
      stack=6, locals=5, args_size=3
         0: getstatic     #216                // Field org/scalatest/FailureMessages$.MODULE$:Lorg/scalatest/FailureMessages$;
         3: aload_0
         4: getfield      #218                // Field prettifier:Lorg/scalactic/Prettifier;
         7: aload_0
         8: getfield      #30                 // Field left:Ljava/lang/Object;
        11: lload_1
        12: invokestatic  #222                // Method scala/runtime/BoxesRunTime.boxToLong:(J)Ljava/lang/Long;
        15: lload_3
        16: invokestatic  #222                // Method scala/runtime/BoxesRunTime.boxToLong:(J)Ljava/lang/Long;
        19: invokevirtual #226                // Method org/scalatest/FailureMessages$.hadLengthInsteadOfExpectedLength:(Lorg/scalactic/Prettifier;Ljava/lang/Object;Ljava/lang/Object;Ljava/lang/Object;)Ljava/lang/String;
        22: areturn
      LineNumberTable:
        line 2699: 0
      LocalVariableTable:
        Start  Length  Slot  Name   Signature
            0      23     0 $this   Lorg/scalatest/matchers/must/Matchers$ResultOfHaveWordForExtent;
            0      23     1 leftLength$1   J
            0      23     3 expectedLength$1   J
    MethodParameters:
      Name                           Flags
      $this                          final synthetic
      leftLength$1                   final
      expectedLength$1               final

  public static final java.lang.String $anonfun$size$1(org.scalatest.matchers.must.Matchers$ResultOfHaveWordForExtent, long, long);
    descriptor: (Lorg/scalatest/matchers/must/Matchers$ResultOfHaveWordForExtent;JJ)Ljava/lang/String;
    flags: (0x1019) ACC_PUBLIC, ACC_STATIC, ACC_FINAL, ACC_SYNTHETIC
    Code:
      stack=6, locals=5, args_size=3
         0: aload_0
         1: getfield      #38                 // Field mustBeTrue:Z
         4: ifeq          32
         7: getstatic     #216                // Field org/scalatest/FailureMessages$.MODULE$:Lorg/scalatest/FailureMessages$;
        10: aload_0
        11: getfield      #218                // Field prettifier:Lorg/scalactic/Prettifier;
        14: aload_0
        15: getfield      #30                 // Field left:Ljava/lang/Object;
        18: lload_1
        19: invokestatic  #222                // Method scala/runtime/BoxesRunTime.boxToLong:(J)Ljava/lang/Long;
        22: lload_3
        23: invokestatic  #222                // Method scala/runtime/BoxesRunTime.boxToLong:(J)Ljava/lang/Long;
        26: invokevirtual #235                // Method org/scalatest/FailureMessages$.hadSizeInsteadOfExpectedSize:(Lorg/scalactic/Prettifier;Ljava/lang/Object;Ljava/lang/Object;Ljava/lang/Object;)Ljava/lang/String;
        29: goto          50
        32: getstatic     #216                // Field org/scalatest/FailureMessages$.MODULE$:Lorg/scalatest/FailureMessages$;
        35: aload_0
        36: getfield      #218                // Field prettifier:Lorg/scalactic/Prettifier;
        39: aload_0
        40: getfield      #30                 // Field left:Ljava/lang/Object;
        43: lload_3
        44: invokestatic  #222                // Method scala/runtime/BoxesRunTime.boxToLong:(J)Ljava/lang/Long;
        47: invokevirtual #238                // Method org/scalatest/FailureMessages$.hadSize:(Lorg/scalactic/Prettifier;Ljava/lang/Object;Ljava/lang/Object;)Ljava/lang/String;
        50: areturn
      StackMapTable: number_of_entries = 2
        frame_type = 32 /* same */
        frame_type = 81 /* same_locals_1_stack_item */
          stack = [ class java/lang/String ]
      LineNumberTable:
        line 2720: 0
      LocalVariableTable:
        Start  Length  Slot  Name   Signature
            0      51     0 $this   Lorg/scalatest/matchers/must/Matchers$ResultOfHaveWordForExtent;
            0      51     1 leftSize$1   J
            0      51     3 expectedSize$1   J
    MethodParameters:
      Name                           Flags
      $this                          final synthetic
      leftSize$1                     final
      expectedSize$1                 final

  public static final java.lang.String $anonfun$size$2(org.scalatest.matchers.must.Matchers$ResultOfHaveWordForExtent, long);
    descriptor: (Lorg/scalatest/matchers/must/Matchers$ResultOfHaveWordForExtent;J)Ljava/lang/String;
    flags: (0x1019) ACC_PUBLIC, ACC_STATIC, ACC_FINAL, ACC_SYNTHETIC
    Code:
      stack=5, locals=3, args_size=2
         0: getstatic     #216                // Field org/scalatest/FailureMessages$.MODULE$:Lorg/scalatest/FailureMessages$;
         3: aload_0
         4: getfield      #218                // Field prettifier:Lorg/scalactic/Prettifier;
         7: aload_0
         8: getfield      #30                 // Field left:Ljava/lang/Object;
        11: lload_1
        12: invokestatic  #222                // Method scala/runtime/BoxesRunTime.boxToLong:(J)Ljava/lang/Long;
        15: invokevirtual #238                // Method org/scalatest/FailureMessages$.hadSize:(Lorg/scalactic/Prettifier;Ljava/lang/Object;Ljava/lang/Object;)Ljava/lang/String;
        18: areturn
      LineNumberTable:
        line 2721: 0
      LocalVariableTable:
        Start  Length  Slot  Name   Signature
            0      19     0 $this   Lorg/scalatest/matchers/must/Matchers$ResultOfHaveWordForExtent;
            0      19     1 expectedSize$1   J
    MethodParameters:
      Name                           Flags
      $this                          final synthetic
      expectedSize$1                 final

  public static final java.lang.String $anonfun$size$3(org.scalatest.matchers.must.Matchers$ResultOfHaveWordForExtent, long, long);
    descriptor: (Lorg/scalatest/matchers/must/Matchers$ResultOfHaveWordForExtent;JJ)Ljava/lang/String;
    flags: (0x1019) ACC_PUBLIC, ACC_STATIC, ACC_FINAL, ACC_SYNTHETIC
    Code:
      stack=6, locals=5, args_size=3
         0: getstatic     #216                // Field org/scalatest/FailureMessages$.MODULE$:Lorg/scalatest/FailureMessages$;
         3: aload_0
         4: getfield      #218                // Field prettifier:Lorg/scalactic/Prettifier;
         7: aload_0
         8: getfield      #30                 // Field left:Ljava/lang/Object;
        11: lload_1
        12: invokestatic  #222                // Method scala/runtime/BoxesRunTime.boxToLong:(J)Ljava/lang/Long;
        15: lload_3
        16: invokestatic  #222                // Method scala/runtime/BoxesRunTime.boxToLong:(J)Ljava/lang/Long;
        19: invokevirtual #235                // Method org/scalatest/FailureMessages$.hadSizeInsteadOfExpectedSize:(Lorg/scalactic/Prettifier;Ljava/lang/Object;Ljava/lang/Object;Ljava/lang/Object;)Ljava/lang/String;
        22: areturn
      LineNumberTable:
        line 2721: 0
      LocalVariableTable:
        Start  Length  Slot  Name   Signature
            0      23     0 $this   Lorg/scalatest/matchers/must/Matchers$ResultOfHaveWordForExtent;
            0      23     1 leftSize$1   J
            0      23     3 expectedSize$1   J
    MethodParameters:
      Name                           Flags
      $this                          final synthetic
      leftSize$1                     final
      expectedSize$1                 final

  public static final java.lang.String $anonfun$message$1(org.scalatest.matchers.must.Matchers$ResultOfHaveWordForExtent, java.lang.String, java.lang.String);
    descriptor: (Lorg/scalatest/matchers/must/Matchers$ResultOfHaveWordForExtent;Ljava/lang/String;Ljava/lang/String;)Ljava/lang/String;
    flags: (0x1019) ACC_PUBLIC, ACC_STATIC, ACC_FINAL, ACC_SYNTHETIC
    Code:
      stack=5, locals=3, args_size=3
         0: aload_0
         1: getfield      #38                 // Field mustBeTrue:Z
         4: ifeq          26
         7: getstatic     #216                // Field org/scalatest/FailureMessages$.MODULE$:Lorg/scalatest/FailureMessages$;
        10: aload_0
        11: getfield      #218                // Field prettifier:Lorg/scalactic/Prettifier;
        14: aload_0
        15: getfield      #30                 // Field left:Ljava/lang/Object;
        18: aload_1
        19: aload_2
        20: invokevirtual #243                // Method org/scalatest/FailureMessages$.hadMessageInsteadOfExpectedMessage:(Lorg/scalactic/Prettifier;Ljava/lang/Object;Ljava/lang/Object;Ljava/lang/Object;)Ljava/lang/String;
        23: goto          41
        26: getstatic     #216                // Field org/scalatest/FailureMessages$.MODULE$:Lorg/scalatest/FailureMessages$;
        29: aload_0
        30: getfield      #218                // Field prettifier:Lorg/scalactic/Prettifier;
        33: aload_0
        34: getfield      #30                 // Field left:Ljava/lang/Object;
        37: aload_2
        38: invokevirtual #246                // Method org/scalatest/FailureMessages$.hadExpectedMessage:(Lorg/scalactic/Prettifier;Ljava/lang/Object;Ljava/lang/Object;)Ljava/lang/String;
        41: areturn
      StackMapTable: number_of_entries = 2
        frame_type = 26 /* same */
        frame_type = 78 /* same_locals_1_stack_item */
          stack = [ class java/lang/String ]
      LineNumberTable:
        line 2735: 0
      LocalVariableTable:
        Start  Length  Slot  Name   Signature
            0      42     0 $this   Lorg/scalatest/matchers/must/Matchers$ResultOfHaveWordForExtent;
            0      42     1 actualMessage$1   Ljava/lang/String;
            0      42     2 expectedMessage$1   Ljava/lang/String;
    MethodParameters:
      Name                           Flags
      $this                          final synthetic
      actualMessage$1                final
      expectedMessage$1              final

  public static final java.lang.String $anonfun$message$2(org.scalatest.matchers.must.Matchers$ResultOfHaveWordForExtent, java.lang.String);
    descriptor: (Lorg/scalatest/matchers/must/Matchers$ResultOfHaveWordForExtent;Ljava/lang/String;)Ljava/lang/String;
    flags: (0x1019) ACC_PUBLIC, ACC_STATIC, ACC_FINAL, ACC_SYNTHETIC
    Code:
      stack=4, locals=2, args_size=2
         0: getstatic     #216                // Field org/scalatest/FailureMessages$.MODULE$:Lorg/scalatest/FailureMessages$;
         3: aload_0
         4: getfield      #218                // Field prettifier:Lorg/scalactic/Prettifier;
         7: aload_0
         8: getfield      #30                 // Field left:Ljava/lang/Object;
        11: aload_1
        12: invokevirtual #246                // Method org/scalatest/FailureMessages$.hadExpectedMessage:(Lorg/scalactic/Prettifier;Ljava/lang/Object;Ljava/lang/Object;)Ljava/lang/String;
        15: areturn
      LineNumberTable:
        line 2736: 0
      LocalVariableTable:
        Start  Length  Slot  Name   Signature
            0      16     0 $this   Lorg/scalatest/matchers/must/Matchers$ResultOfHaveWordForExtent;
            0      16     1 expectedMessage$1   Ljava/lang/String;
    MethodParameters:
      Name                           Flags
      $this                          final synthetic
      expectedMessage$1              final

  public static final java.lang.String $anonfun$message$3(org.scalatest.matchers.must.Matchers$ResultOfHaveWordForExtent, java.lang.String, java.lang.String);
    descriptor: (Lorg/scalatest/matchers/must/Matchers$ResultOfHaveWordForExtent;Ljava/lang/String;Ljava/lang/String;)Ljava/lang/String;
    flags: (0x1019) ACC_PUBLIC, ACC_STATIC, ACC_FINAL, ACC_SYNTHETIC
    Code:
      stack=5, locals=3, args_size=3
         0: getstatic     #216                // Field org/scalatest/FailureMessages$.MODULE$:Lorg/scalatest/FailureMessages$;
         3: aload_0
         4: getfield      #218                // Field prettifier:Lorg/scalactic/Prettifier;
         7: aload_0
         8: getfield      #30                 // Field left:Ljava/lang/Object;
        11: aload_1
        12: aload_2
        13: invokevirtual #243                // Method org/scalatest/FailureMessages$.hadMessageInsteadOfExpectedMessage:(Lorg/scalactic/Prettifier;Ljava/lang/Object;Ljava/lang/Object;Ljava/lang/Object;)Ljava/lang/String;
        16: areturn
      LineNumberTable:
        line 2736: 0
      LocalVariableTable:
        Start  Length  Slot  Name   Signature
            0      17     0 $this   Lorg/scalatest/matchers/must/Matchers$ResultOfHaveWordForExtent;
            0      17     1 actualMessage$1   Ljava/lang/String;
            0      17     2 expectedMessage$1   Ljava/lang/String;
    MethodParameters:
      Name                           Flags
      $this                          final synthetic
      actualMessage$1                final
      expectedMessage$1              final

  public org.scalatest.matchers.must.Matchers$ResultOfHaveWordForExtent(A, boolean, org.scalactic.Prettifier, org.scalactic.source.Position);
    descriptor: (Lorg/scalatest/matchers/must/Matchers;Ljava/lang/Object;ZLorg/scalactic/Prettifier;Lorg/scalactic/source/Position;)V
    flags: (0x0001) ACC_PUBLIC
    Code:
      stack=2, locals=6, args_size=6
         0: aload_0
         1: aload_2
         2: putfield      #30                 // Field left:Ljava/lang/Object;
         5: aload_0
         6: iload_3
         7: putfield      #38                 // Field mustBeTrue:Z
        10: aload_0
        11: aload         4
        13: putfield      #218                // Field prettifier:Lorg/scalactic/Prettifier;
        16: aload_0
        17: aload         5
        19: putfield      #73                 // Field pos:Lorg/scalactic/source/Position;
        22: aload_0
        23: invokespecial #252                // Method java/lang/Object."<init>":()V
        26: return
      LineNumberTable:
        line 2678: 0
        line 2755: 22
        line 2678: 26
      LocalVariableTable:
        Start  Length  Slot  Name   Signature
            0      27     0  this   Lorg/scalatest/matchers/must/Matchers$ResultOfHaveWordForExtent;
            0      27     1 $outer   Lorg/scalatest/matchers/must/Matchers;
            0      27     2  left   Ljava/lang/Object;
            0      27     3 mustBeTrue   Z
            0      27     4 prettifier   Lorg/scalactic/Prettifier;
            0      27     5   pos   Lorg/scalactic/source/Position;
    Signature: #248                         // (TA;ZLorg/scalactic/Prettifier;Lorg/scalactic/source/Position;)V
    MethodParameters:
      Name                           Flags
      $outer                         final synthetic
      left                           final
      mustBeTrue                     final
      prettifier                     final
      pos                            final

  private static java.lang.Object $deserializeLambda$(java.lang.invoke.SerializedLambda);
    descriptor: (Ljava/lang/invoke/SerializedLambda;)Ljava/lang/Object;
    flags: (0x100a) ACC_PRIVATE, ACC_STATIC, ACC_SYNTHETIC
    Code:
      stack=1, locals=1, args_size=1
         0: aload_0
         1: invokedynamic #265,  0            // InvokeDynamic #9:lambdaDeserialize:(Ljava/lang/invoke/SerializedLambda;)Ljava/lang/Object;
         6: areturn
}
InnerClasses:
  public static final #11= #8 of #10;     // Lookup=class java/lang/invoke/MethodHandles$Lookup of class java/lang/invoke/MethodHandles
  public final #14= #2 of #13;            // ResultOfHaveWordForExtent=class org/scalatest/matchers/must/Matchers$ResultOfHaveWordForExtent of class org/scalatest/matchers/must/Matchers
Signature: #3                           // <A:Ljava/lang/Object;>Ljava/lang/Object;
SourceFile: "Matchers.scala"
BootstrapMethods:
  0: #62 REF_invokeStatic java/lang/invoke/LambdaMetafactory.altMetafactory:(Ljava/lang/invoke/MethodHandles$Lookup;Ljava/lang/String;Ljava/lang/invoke/MethodType;[Ljava/lang/Object;)Ljava/lang/invoke/CallSite;
    Method arguments:
      #46 ()Ljava/lang/Object;
      #51 REF_invokeStatic org/scalatest/matchers/must/Matchers$ResultOfHaveWordForExtent.$anonfun$length$1:(Lorg/scalatest/matchers/must/Matchers$ResultOfHaveWordForExtent;JJ)Ljava/lang/String;
      #53 ()Ljava/lang/String;
      #54 5
      #55 1
      #53 ()Ljava/lang/String;
  1: #62 REF_invokeStatic java/lang/invoke/LambdaMetafactory.altMetafactory:(Ljava/lang/invoke/MethodHandles$Lookup;Ljava/lang/String;Ljava/lang/invoke/MethodType;[Ljava/lang/Object;)Ljava/lang/invoke/CallSite;
    Method arguments:
      #46 ()Ljava/lang/Object;
      #82 REF_invokeStatic org/scalatest/matchers/must/Matchers$ResultOfHaveWordForExtent.$anonfun$length$2:(Lorg/scalatest/matchers/must/Matchers$ResultOfHaveWordForExtent;J)Ljava/lang/String;
      #53 ()Ljava/lang/String;
      #54 5
      #55 1
      #53 ()Ljava/lang/String;
  2: #62 REF_invokeStatic java/lang/invoke/LambdaMetafactory.altMetafactory:(Ljava/lang/invoke/MethodHandles$Lookup;Ljava/lang/String;Ljava/lang/invoke/MethodType;[Ljava/lang/Object;)Ljava/lang/invoke/CallSite;
    Method arguments:
      #46 ()Ljava/lang/Object;
      #89 REF_invokeStatic org/scalatest/matchers/must/Matchers$ResultOfHaveWordForExtent.$anonfun$length$3:(Lorg/scalatest/matchers/must/Matchers$ResultOfHaveWordForExtent;JJ)Ljava/lang/String;
      #53 ()Ljava/lang/String;
      #54 5
      #55 1
      #53 ()Ljava/lang/String;
  3: #62 REF_invokeStatic java/lang/invoke/LambdaMetafactory.altMetafactory:(Ljava/lang/invoke/MethodHandles$Lookup;Ljava/lang/String;Ljava/lang/invoke/MethodType;[Ljava/lang/Object;)Ljava/lang/invoke/CallSite;
    Method arguments:
      #46 ()Ljava/lang/Object;
      #115 REF_invokeStatic org/scalatest/matchers/must/Matchers$ResultOfHaveWordForExtent.$anonfun$size$1:(Lorg/scalatest/matchers/must/Matchers$ResultOfHaveWordForExtent;JJ)Ljava/lang/String;
      #53 ()Ljava/lang/String;
      #54 5
      #55 1
      #53 ()Ljava/lang/String;
  4: #62 REF_invokeStatic java/lang/invoke/LambdaMetafactory.altMetafactory:(Ljava/lang/invoke/MethodHandles$Lookup;Ljava/lang/String;Ljava/lang/invoke/MethodType;[Ljava/lang/Object;)Ljava/lang/invoke/CallSite;
    Method arguments:
      #46 ()Ljava/lang/Object;
      #120 REF_invokeStatic org/scalatest/matchers/must/Matchers$ResultOfHaveWordForExtent.$anonfun$size$2:(Lorg/scalatest/matchers/must/Matchers$ResultOfHaveWordForExtent;J)Ljava/lang/String;
      #53 ()Ljava/lang/String;
      #54 5
      #55 1
      #53 ()Ljava/lang/String;
  5: #62 REF_invokeStatic java/lang/invoke/LambdaMetafactory.altMetafactory:(Ljava/lang/invoke/MethodHandles$Lookup;Ljava/lang/String;Ljava/lang/invoke/MethodType;[Ljava/lang/Object;)Ljava/lang/invoke/CallSite;
    Method arguments:
      #46 ()Ljava/lang/Object;
      #125 REF_invokeStatic org/scalatest/matchers/must/Matchers$ResultOfHaveWordForExtent.$anonfun$size$3:(Lorg/scalatest/matchers/must/Matchers$ResultOfHaveWordForExtent;JJ)Ljava/lang/String;
      #53 ()Ljava/lang/String;
      #54 5
      #55 1
      #53 ()Ljava/lang/String;
  6: #62 REF_invokeStatic java/lang/invoke/LambdaMetafactory.altMetafactory:(Ljava/lang/invoke/MethodHandles$Lookup;Ljava/lang/String;Ljava/lang/invoke/MethodType;[Ljava/lang/Object;)Ljava/lang/invoke/CallSite;
    Method arguments:
      #46 ()Ljava/lang/Object;
      #148 REF_invokeStatic org/scalatest/matchers/must/Matchers$ResultOfHaveWordForExtent.$anonfun$message$1:(Lorg/scalatest/matchers/must/Matchers$ResultOfHaveWordForExtent;Ljava/lang/String;Ljava/lang/String;)Ljava/lang/String;
      #53 ()Ljava/lang/String;
      #54 5
      #55 1
      #53 ()Ljava/lang/String;
  7: #62 REF_invokeStatic java/lang/invoke/LambdaMetafactory.altMetafactory:(Ljava/lang/invoke/MethodHandles$Lookup;Ljava/lang/String;Ljava/lang/invoke/MethodType;[Ljava/lang/Object;)Ljava/lang/invoke/CallSite;
    Method arguments:
      #46 ()Ljava/lang/Object;
      #156 REF_invokeStatic org/scalatest/matchers/must/Matchers$ResultOfHaveWordForExtent.$anonfun$message$2:(Lorg/scalatest/matchers/must/Matchers$ResultOfHaveWordForExtent;Ljava/lang/String;)Ljava/lang/String;
      #53 ()Ljava/lang/String;
      #54 5
      #55 1
      #53 ()Ljava/lang/String;
  8: #62 REF_invokeStatic java/lang/invoke/LambdaMetafactory.altMetafactory:(Ljava/lang/invoke/MethodHandles$Lookup;Ljava/lang/String;Ljava/lang/invoke/MethodType;[Ljava/lang/Object;)Ljava/lang/invoke/CallSite;
    Method arguments:
      #46 ()Ljava/lang/Object;
      #163 REF_invokeStatic org/scalatest/matchers/must/Matchers$ResultOfHaveWordForExtent.$anonfun$message$3:(Lorg/scalatest/matchers/must/Matchers$ResultOfHaveWordForExtent;Ljava/lang/String;Ljava/lang/String;)Ljava/lang/String;
      #53 ()Ljava/lang/String;
      #54 5
      #55 1
      #53 ()Ljava/lang/String;
  9: #262 REF_invokeStatic scala/runtime/LambdaDeserialize.bootstrap:(Ljava/lang/invoke/MethodHandles$Lookup;Ljava/lang/String;Ljava/lang/invoke/MethodType;[Ljava/lang/invoke/MethodHandle;)Ljava/lang/invoke/CallSite;
    Method arguments:
      #51 REF_invokeStatic org/scalatest/matchers/must/Matchers$ResultOfHaveWordForExtent.$anonfun$length$1:(Lorg/scalatest/matchers/must/Matchers$ResultOfHaveWordForExtent;JJ)Ljava/lang/String;
      #82 REF_invokeStatic org/scalatest/matchers/must/Matchers$ResultOfHaveWordForExtent.$anonfun$length$2:(Lorg/scalatest/matchers/must/Matchers$ResultOfHaveWordForExtent;J)Ljava/lang/String;
      #89 REF_invokeStatic org/scalatest/matchers/must/Matchers$ResultOfHaveWordForExtent.$anonfun$length$3:(Lorg/scalatest/matchers/must/Matchers$ResultOfHaveWordForExtent;JJ)Ljava/lang/String;
      #148 REF_invokeStatic org/scalatest/matchers/must/Matchers$ResultOfHaveWordForExtent.$anonfun$message$1:(Lorg/scalatest/matchers/must/Matchers$ResultOfHaveWordForExtent;Ljava/lang/String;Ljava/lang/String;)Ljava/lang/String;
      #156 REF_invokeStatic org/scalatest/matchers/must/Matchers$ResultOfHaveWordForExtent.$anonfun$message$2:(Lorg/scalatest/matchers/must/Matchers$ResultOfHaveWordForExtent;Ljava/lang/String;)Ljava/lang/String;
      #163 REF_invokeStatic org/scalatest/matchers/must/Matchers$ResultOfHaveWordForExtent.$anonfun$message$3:(Lorg/scalatest/matchers/must/Matchers$ResultOfHaveWordForExtent;Ljava/lang/String;Ljava/lang/String;)Ljava/lang/String;
      #115 REF_invokeStatic org/scalatest/matchers/must/Matchers$ResultOfHaveWordForExtent.$anonfun$size$1:(Lorg/scalatest/matchers/must/Matchers$ResultOfHaveWordForExtent;JJ)Ljava/lang/String;
      #120 REF_invokeStatic org/scalatest/matchers/must/Matchers$ResultOfHaveWordForExtent.$anonfun$size$2:(Lorg/scalatest/matchers/must/Matchers$ResultOfHaveWordForExtent;J)Ljava/lang/String;
      #125 REF_invokeStatic org/scalatest/matchers/must/Matchers$ResultOfHaveWordForExtent.$anonfun$size$3:(Lorg/scalatest/matchers/must/Matchers$ResultOfHaveWordForExtent;JJ)Ljava/lang/String;
  ScalaInlineInfo: length = 0x4A (unknown attribute)
   01 01 00 0E 00 2F 00 30 01 00 4E 00 4F 01 00 56
   00 30 01 00 90 00 91 01 00 98 00 99 01 00 A0 00
   91 01 00 70 00 30 01 00 75 00 4F 01 00 7A 00 30
   01 00 AE 00 F7 01 00 18 00 19 01 00 81 00 82 01
   00 66 00 67 01 00 AA 00 34 01
  Scala: length = 0x0 (unknown attribute)

