Classfile /Users/mw/Projects/slang-braindump/.jar/jar11/assemble/slang-braindump/assemble/content/scala/collection/parallel/CollectionConverters.class
  Last modified May 29, 2022; size 30390 bytes
  SHA-256 checksum d5546d1543cdc7c4abcba81fd050eadeba6fad3e5d37ba8770c8860add26115a
  Compiled from "CollectionConverters.scala"
public final class scala.collection.parallel.CollectionConverters
  minor version: 0
  major version: 52
  flags: (0x0031) ACC_PUBLIC, ACC_FINAL, ACC_SUPER
  this_class: #2                          // scala/collection/parallel/CollectionConverters
  super_class: #4                         // java/lang/Object
  interfaces: 0, fields: 0, methods: 22, attributes: 4
Constant pool:
    #1 = Utf8               scala/collection/parallel/CollectionConverters
    #2 = Class              #1            // scala/collection/parallel/CollectionConverters
    #3 = Utf8               java/lang/Object
    #4 = Class              #3            // java/lang/Object
    #5 = Utf8               CollectionConverters.scala
    #6 = Utf8               Lscala/reflect/ScalaSignature;
    #7 = Utf8               bytes
    #8 = Utf8               \u0006\u00055%t\u0001\u0003BU\u0005WC\tA!/\u0007\u0011\tu&1\u0016E\u0001\u0005\u007fCqA!3\u0002\t\u0003\u0011YM\u0002\u0004\u0003N\u0006\u0019!q\u001a\u0005\u000f\u0005{\u001cA\u0011!A\u0003\u0006\u000b\u0007I\u0011\u0002B\u0000\u0011-\u00199a\u0001B\u0003\u0002\u0003\u0006Ia!\u0001\t\u000f\t%7\u0001\"\u0001\u0004\n!911C\u0002\u0005\u0002\t}\bbBB\u000b\u0007\u0011\u00053q\u0003\u0005\n\u00073\u0019\u0011\u0011!C!\u00077A\u0011ba\t\u0004\u0003\u0003%\te!\n\b\u0013\rE\u0012!!A\t\u0002\rMb!\u0003Bg\u0003\u0005\u0005\t\u0012AB\u001b\u0011\u001d\u0011I\r\u0004C\u0001\u0007oAqa!\u000f\r\t\u000b\u0019Y\u0004C\u0004\u0004L1!)a!\u0014\t\u0013\rmC\"!A\u0005\u0006\ru\u0003\"CB5\u0019\u0005\u0005IQAB6\u0011%\u0019\t$AA\u0001\n\u0007\u0019YH\u0002\u0004\u0004\n\u0006\u001911\u0012\u0005\u000f\u0007?\u001bB\u0011!A\u0003\u0006\u000b\u0007I\u0011BBQ\u0011-\u0019Yk\u0005B\u0003\u0002\u0003\u0006Iaa)\t\u000f\t%7\u0003\"\u0001\u0004.\"911C\n\u0005\u0002\r\u0005\u0006bBB\u000b\'\u0011\u000531\u0017\u0005\n\u00073\u0019\u0012\u0011!C!\u00077A\u0011ba\t\u0014\u0003\u0003%\te!.\b\u0013\re\u0016!!A\t\u0002\rmf!CBE\u0003\u0005\u0005\t\u0012AB_\u0011\u001d\u0011I\r\bC\u0001\u0007\u007fCqa!\u000f\u001d\t\u000b\u0019\t\rC\u0004\u0004Lq!)aa4\t\u0013\rmC$!A\u0005\u0006\ru\u0007\"CB59\u0005\u0005IQABu\u0011%\u0019I,AA\u0001\n\u0007\u0019IP\u0002\u0004\u0005\b\u0005\u0019A\u0011\u0002\u0005\u000f\t;\u0019C\u0011!A\u0003\u0006\u000b\u0007I\u0011\u0002C\u0010\u0011-!Ic\tB\u0003\u0002\u0003\u0006I\u0001\"\t\t\u000f\t%7\u0005\"\u0001\u0005,!911C\u0012\u0005\u0002\u0011}\u0001bBB\u000bG\u0011\u0005C\u0011\u0007\u0005\n\u00073\u0019\u0013\u0011!C!\u00077A\u0011ba\t$\u0003\u0003%\t\u0005b\r\b\u0013\u0011]\u0012!!A\t\u0002\u0011eb!\u0003C\u0004\u0003\u0005\u0005\t\u0012\u0001C\u001e\u0011\u001d\u0011I\r\fC\u0001\t{Aqa!\u000f-\t\u000b!y\u0004C\u0004\u0004L1\")\u0001\"\u0014\t\u0013\rmC&!A\u0005\u0006\u0011m\u0003\"CB5Y\u0005\u0005IQ\u0001C4\u0011%!9$AA\u0001\n\u0007!9\bC\u0004\u0005\u0006\u0006!\u0019\u0001b\"\u0007\r\u0011\r\u0016a\u0001CS\u00119!\u0019\f\u000eC\u0001\u0002\u000b\u0015)\u0019!C\u0005\tkC1\u0002b/5\u0005\u000b\u0005\t\u0015!\u0003\u00058\"9!\u0011\u001a\u001b\u0005\u0002\u0011u\u0006bBB\ni\u0011\u0005AQ\u0017\u0005\b\u0007+!D\u0011\tCb\u0011%\u0019I\u0002NA\u0001\n\u0003\u001aY\u0002C\u0005\u0004$Q\n\t\u0011\"\u0011\u0005F\u001eIA\u0011Z\u0001\u0002\u0002#\u0005A1\u001a\u0004\n\tG\u000b\u0011\u0011!E\u0001\t\u001bDqA!3>\t\u0003!y\rC\u0004\u0004:u\")\u0001\"5\t\u000f\r-S\b\"\u0002\u0005`\"I11L\u001f\u0002\u0002\u0013\u0015AQ\u001e\u0005\n\u0007Sj\u0014\u0011!C\u0003\tsD\u0011\u0002\"3\u0002\u0003\u0003%\u0019!\"\u0003\u0007\r\u0015]\u0011aAC\r\u00119)Y\u0003\u0012C\u0001\u0002\u000b\u0015)\u0019!C\u0005\u000b[A1\"\"\u000eE\u0005\u000b\u0005\t\u0015!\u0003\u00060!9!\u0011\u001a#\u0005\u0002\u0015]\u0002bBB\n\t\u0012\u0005QQ\u0006\u0005\b\u0007+!E\u0011IC\u001f\u0011%\u0019I\u0002RA\u0001\n\u0003\u001aY\u0002C\u0005\u0004$\u0011\u000b\t\u0011\"\u0011\u0006@\u001dIQ1I\u0001\u0002\u0002#\u0005QQ\t\u0004\n\u000b/\t\u0011\u0011!E\u0001\u000b\u000fBqA!3N\t\u0003)I\u0005C\u0004\u0004:5#)!b\u0013\t\u000f\r-S\n\"\u0002\u0006Z!I11L\'\u0002\u0002\u0013\u0015Qq\r\u0005\n\u0007Sj\u0015\u0011!C\u0003\u000bgB\u0011\"b\u0011\u0002\u0003\u0003%\u0019!b!\u0007\r\u0015E\u0015aACJ\u00119)y\n\u0016C\u0001\u0002\u000b\u0015)\u0019!C\u0005\u000bCC1\"\"+U\u0005\u000b\u0005\t\u0015!\u0003\u0006$\"9!\u0011\u001a+\u0005\u0002\u0015-\u0006bBB\n)\u0012\u0005Q\u0011\u0015\u0005\b\u0007+!F\u0011ICY\u0011%\u0019I\u0002VA\u0001\n\u0003\u001aY\u0002C\u0005\u0004$Q\u000b\t\u0011\"\u0011\u00064\u001eIQqW\u0001\u0002\u0002#\u0005Q\u0011\u0018\u0004\n\u000b#\u000b\u0011\u0011!E\u0001\u000bwCqA!3^\t\u0003)i\fC\u0004\u0004:u#)!b0\t\u000f\r-S\f\"\u0002\u0006N\"I11L/\u0002\u0002\u0013\u0015Q1\u001c\u0005\n\u0007Sj\u0016\u0011!C\u0003\u000bOD\u0011\"b.\u0002\u0003\u0003%\u0019!b>\u0007\r\u0019\u0015\u0011a\u0001D\u0004\u001191)\u0002\u001aC\u0001\u0002\u000b\u0015)\u0019!C\u0005\r/A1B\"\be\u0005\u000b\u0005\t\u0015!\u0003\u0007\u001a!9!\u0011\u001a3\u0005\u0002\u0019}\u0001bBB\nI\u0012\u0005aq\u0003\u0005\b\u0007+!G\u0011\tD\u0013\u0011%\u0019I\u0002ZA\u0001\n\u0003\u001aY\u0002C\u0005\u0004$\u0011\f\t\u0011\"\u0011\u0007(\u001dIa1F\u0001\u0002\u0002#\u0005aQ\u0006\u0004\n\r\u000b\t\u0011\u0011!E\u0001\r_AqA!3n\t\u00031\t\u0004C\u0004\u0004:5$)Ab\r\t\u000f\r-S\u000e\"\u0002\u0007B!I11L7\u0002\u0002\u0013\u0015aq\n\u0005\n\u0007Sj\u0017\u0011!C\u0003\r7B\u0011Bb\u000b\u0002\u0003\u0003%\u0019Ab\u001b\u0007\r\u0019e\u0014a\u0001D>\u001191)\t\u001eC\u0001\u0002\u000b\u0015)\u0019!C\u0005\r\u000fC1Bb$u\u0005\u000b\u0005\t\u0015!\u0003\u0007\n\"9!\u0011\u001a;\u0005\u0002\u0019E\u0005bBB\ni\u0012\u0005aq\u0011\u0005\b\u0007+!H\u0011\tDL\u0011%\u0019I\u0002^A\u0001\n\u0003\u001aY\u0002C\u0005\u0004$Q\f\t\u0011\"\u0011\u0007\u001a\u001eIaQT\u0001\u0002\u0002#\u0005aq\u0014\u0004\n\rs\n\u0011\u0011!E\u0001\rCCqA!3~\t\u00031\u0019\u000bC\u0004\u0004:u$)A\"*\t\u000f\r-S\u0010\"\u0002\u0007*\"I11L?\u0002\u0002\u0013\u0015aQ\u0016\u0005\n\u0007Sj\u0018\u0011!C\u0003\rcC\u0011B\"(\u0002\u0003\u0003%\u0019A\"/\u0007\r\u0019u\u0016a\u0001D`\u0011=1y-!\u0003\u0005\u0002\u0003\u0015)Q1A\u0005\n\u0019E\u0007\u0002\u0004Dm\u0003\u0013\u0011)\u0011!Q\u0001\n\u0019M\u0007\u0002\u0003Be\u0003\u0013!\tAb7\t\u0011\rM\u0011\u0011\u0002C\u0001\r#D\u0001b!\u0006\u0002\n\u0011\u0005c\u0011\u001d\u0005\u000b\u00073\tI!!A\u0005B\rm\u0001BCB\u0012\u0003\u0013\t\t\u0011\"\u0011\u0007d\u001eIaq]\u0001\u0002\u0002#\u0005a\u0011\u001e\u0004\n\r{\u000b\u0011\u0011!E\u0001\rWD\u0001B!3\u0002\u001c\u0011\u0005aQ\u001e\u0005\t\u0007s\tY\u0002\"\u0002\u0007p\"A11JA\u000e\t\u000b1i\u0010\u0003\u0006\u0004\\\u0005m\u0011\u0011!C\u0003\u000f\u0017A!b!\u001b\u0002\u001c\u0005\u0005IQAD\f\u0011%19/AA\u0001\n\u000799C\u0002\u0004\b6\u0005\u0019qq\u0007\u0005\u0010\u000f\u000f\nI\u0003\"A\u0001\u0006\u000b\u0015\r\u0011\"\u0003\bJ!aq\u0011KA\u0015\u0005\u000b\u0005\t\u0015!\u0003\bL!A!\u0011ZA\u0015\t\u00039\u0019\u0006\u0003\u0005\u0004\u0014\u0005%B\u0011AD%\u0011!\u0019)\"!\u000b\u0005B\u001de\u0003BCB\r\u0003S\t\t\u0011\"\u0011\u0004\u001c!Q11EA\u0015\u0003\u0003%\teb\u0017\b\u0013\u001d}\u0013!!A\t\u0002\u001d\u0005d!CD\u001b\u0003\u0005\u0005\t\u0012AD2\u0011!\u0011I-a\u000f\u0005\u0002\u001d\u0015\u0004\u0002CB\u001d\u0003w!)ab\u001a\t\u0011\r-\u00131\bC\u0003\u000fkB!ba\u0017\u0002<\u0005\u0005IQADB\u0011)\u0019I\'a\u000f\u0002\u0002\u0013\u0015qq\u0012\u0005\n\u000f?\n\u0011\u0011!C\u0002\u000f?3aa\",\u0002\u0007\u001d=\u0006bDD_\u0003\u0013\"\t\u0011!B\u0003\u0006\u0004%Iab0\t\u0019\u001d\u0015\u0017\u0011\nB\u0003\u0002\u0003\u0006Ia\"1\t\u0011\t%\u0017\u0011\nC\u0001\u000f\u000fD\u0001ba\u0005\u0002J\u0011\u0005qq\u0018\u0005\t\u0007+\tI\u0005\"\u0011\bN\"Q1\u0011DA%\u0003\u0003%\tea\u0007\t\u0015\r\r\u0012\u0011JA\u0001\n\u0003:ymB\u0005\bT\u0006\t\t\u0011#\u0001\bV\u001aIqQV\u0001\u0002\u0002#\u0005qq\u001b\u0005\t\u0005\u0013\fY\u0006\"\u0001\bZ\"A1\u0011HA.\t\u000b9Y\u000e\u0003\u0005\u0004L\u0005mCQADu\u0011)\u0019Y&a\u0017\u0002\u0002\u0013\u0015qq\u001f\u0005\u000b\u0007S\nY&!A\u0005\u0006!\r\u0001\"CDj\u0003\u0005\u0005I1\u0001E\n\r\u0019A\t#A\u0002\t$!y\u0001\u0012GA5\t\u0003\u0005)Q!b\u0001\n\u0013A\u0019\u0004\u0003\u0007\t:\u0005%$Q!A!\u0002\u0013A)\u0004\u0003\u0005\u0003J\u0006%D\u0011\u0001E\u001e\u0011!\u0019\u0019\"!\u001b\u0005\u0002!M\u0002\u0002CB\u000b\u0003S\"\t\u0005#\u0011\t\u0015\re\u0011\u0011NA\u0001\n\u0003\u001aY\u0002\u0003\u0006\u0004$\u0005%\u0014\u0011!C!\u0011\u0007:\u0011\u0002c\u0012\u0002\u0003\u0003E\t\u0001#\u0013\u0007\u0013!\u0005\u0012!!A\t\u0002!-\u0003\u0002\u0003Be\u0003w\"\t\u0001#\u0014\t\u0011\re\u00121\u0010C\u0003\u0011\u001fB\u0001ba\u0013\u0002|\u0011\u0015\u0001R\f\u0005\u000b\u00077\nY(!A\u0005\u0006!-\u0004BCB5\u0003w\n\t\u0011\"\u0002\tx!I\u0001rI\u0001\u0002\u0002\u0013\r\u0001r\u0011\u0004\u0007\u0011+\u000b1\u0001c&\t\u001f!\u001d\u0016\u0011\u0012C\u0001\u0002\u000b\u0015)\u0019!C\u0005\u0011SCA\u0002#-\u0002\n\n\u0015\t\u0011)A\u0005\u0011WC\u0001B!3\u0002\n\u0012\u0005\u00012\u0017\u0005\t\u0007\'\tI\t\"\u0001\t*\"A1QCAE\t\u0003BI\f\u0003\u0006\u0004\u001a\u0005%\u0015\u0011!C!\u00077A!ba\t\u0002\n\u0006\u0005I\u0011\tE^\u000f%Ay,AA\u0001\u0012\u0003A\tMB\u0005\t\u0016\u0006\t\t\u0011#\u0001\tD\"A!\u0011ZAN\t\u0003A)\r\u0003\u0005\u0004:\u0005mEQ\u0001Ed\u0011!\u0019Y%a\'\u0005\u0006!U\u0007BCB.\u00037\u000b\t\u0011\"\u0002\td\"Q1\u0011NAN\u0003\u0003%)\u0001c<\t\u0013!}\u0016!!A\u0005\u0004!}hABE\u0007\u0003\rIy\u0001C\b\n\u001e\u0005%F\u0011!A\u0003\u0006\u000b\u0007I\u0011BE\u0010\u00111I)#!+\u0003\u0006\u0003\u0005\u000b\u0011BE\u0011\u0011!\u0011I-!+\u0005\u0002%\u001d\u0002\u0002CB\n\u0003S#\t!c\b\t\u0011\rU\u0011\u0011\u0016C!\u0013[A!b!\u0007\u0002*\u0006\u0005I\u0011IB\u000e\u0011)\u0019\u0019#!+\u0002\u0002\u0013\u0005\u0013rF\u0004\n\u0013g\t\u0011\u0011!E\u0001\u0013k1\u0011\"#\u0004\u0002\u0003\u0003E\t!c\u000e\t\u0011\t%\u00171\u0018C\u0001\u0013sA\u0001b!\u000f\u0002<\u0012\u0015\u00112\b\u0005\t\u0007\u0017\nY\f\"\u0002\nJ!Q11LA^\u0003\u0003%)!c\u0016\t\u0015\r%\u00141XA\u0001\n\u000bI\u0019\u0007C\u0005\n4\u0005\t\t\u0011b\u0001\nt\u00191\u0011\u0012Q\u0001\u0004\u0013\u0007Cq\"#)\u0002J\u0012\u0005\tQ!BC\u0002\u0013%\u00112\u0015\u0005\r\u0013W\u000bIM!B\u0001B\u0003%\u0011R\u0015\u0005\t\u0005\u0013\fI\r\"\u0001\n.\"A11CAe\t\u0003I\u0019\u000b\u0003\u0005\u0004\u0016\u0005%G\u0011IEZ\u0011)\u0019I\"!3\u0002\u0002\u0013\u000531\u0004\u0005\u000b\u0007G\tI-!A\u0005B%Uv!CE]\u0003\u0005\u0005\t\u0012AE^\r%I\t)AA\u0001\u0012\u0003Ii\f\u0003\u0005\u0003J\u0006mG\u0011AE`\u0011!\u0019I$a7\u0005\u0006%\u0005\u0007\u0002CB&\u00037$)!c5\t\u0015\rm\u00131\\A\u0001\n\u000bI)\u000f\u0003\u0006\u0004j\u0005m\u0017\u0011!C\u0003\u0013kD\u0011\"#/\u0002\u0003\u0003%\u0019A#\u0003\u0007\r)m\u0011a\u0001F\u000f\u0011=Q\t$!;\u0005\u0002\u0003\u0015)Q1A\u0005\n)M\u0002\u0002\u0004F\u001d\u0003S\u0014)\u0011!Q\u0001\n)U\u0002\u0002\u0003Be\u0003S$\tAc\u000f\t\u0011\rM\u0011\u0011\u001eC\u0001\u0015gA\u0001b!\u0006\u0002j\u0012\u0005#\u0012\t\u0005\u000b\u00073\tI/!A\u0005B\rm\u0001BCB\u0012\u0003S\f\t\u0011\"\u0011\u000bD\u001dI!rI\u0001\u0002\u0002#\u0005!\u0012\n\u0004\n\u00157\t\u0011\u0011!E\u0001\u0015\u0017B\u0001B!3\u0002|\u0012\u0005!R\n\u0005\t\u0007s\tY\u0010\"\u0002\u000bP!A11JA~\t\u000bQ\t\u0007\u0003\u0006\u0004\\\u0005m\u0018\u0011!C\u0003\u0015gB!b!\u001b\u0002|\u0006\u0005IQ\u0001FB\u0011%Q9%AA\u0001\n\u0007Q9J\u0002\u0004\u000b*\u0006\u0019!2\u0016\u0005\u0010\u0015\u007f\u0013I\u0001\"A\u0001\u0006\u000b\u0015\r\u0011\"\u0003\u000bB\"a!r\u0019B\u0005\u0005\u000b\u0005\t\u0015!\u0003\u000bD\"A!\u0011\u001aB\u0005\t\u0003QI\r\u0003\u0005\u0004\u0014\t%A\u0011\u0001Fa\u0011!\u0019)B!\u0003\u0005B)=\u0007BCB\r\u0005\u0013\t\t\u0011\"\u0011\u0004\u001c!Q11\u0005B\u0005\u0003\u0003%\tE#5\b\u0013)U\u0017!!A\t\u0002)]g!\u0003FU\u0003\u0005\u0005\t\u0012\u0001Fm\u0011!\u0011IMa\u0007\u0005\u0002)m\u0007\u0002CB\u001d\u00057!)A#8\t\u0011\r-#1\u0004C\u0003\u0015_D!ba\u0017\u0003\u001c\u0005\u0005IQAF\u0001\u0011)\u0019IGa\u0007\u0002\u0002\u0013\u00151\u0012\u0003\u0005\n\u0015+\f\u0011\u0011!C\u0002\u0017K1aac\u000e\u0002\u0007-e\u0002bDF(\u0005S!\t\u0011!B\u0003\u0006\u0004%Ia#\u0015\t\u0019-e#\u0011\u0006B\u0003\u0002\u0003\u0006Iac\u0015\t\u0011\t%\'\u0011\u0006C\u0001\u00177B\u0001ba\u0005\u0003*\u0011\u00051\u0012\u000b\u0005\t\u0007+\u0011I\u0003\"\u0011\fb!Q1\u0011\u0004B\u0015\u0003\u0003%\tea\u0007\t\u0015\r\r\"\u0011FA\u0001\n\u0003Z\u0019gB\u0005\fh\u0005\t\t\u0011#\u0001\fj\u0019I1rG\u0001\u0002\u0002#\u000512\u000e\u0005\t\u0005\u0013\u0014Y\u0004\"\u0001\fn!A1\u0011\bB\u001e\t\u000bYy\u0007\u0003\u0005\u0004L\tmBQAFA\u0011)\u0019YFa\u000f\u0002\u0002\u0013\u001512\u0013\u0005\u000b\u0007S\u0012Y$!A\u0005\u0006-\r\u0006\"CF4\u0003\u0005\u0005I1AF\\\r\u0019YI-A\u0002\fL\"y1r\u001cB%\t\u0003\u0005)Q!b\u0001\n\u0013Y\t\u000f\u0003\u0007\fh\n%#Q!A!\u0002\u0013Y\u0019\u000f\u0003\u0005\u0003J\n%C\u0011AFu\u0011!\u0019\u0019B!\u0013\u0005\u0002-\u0005\b\u0002CB\u000b\u0005\u0013\"\tec<\t\u0015\re!\u0011JA\u0001\n\u0003\u001aY\u0002\u0003\u0006\u0004$\t%\u0013\u0011!C!\u0017c<\u0011b#>\u0002\u0003\u0003E\tac>\u0007\u0013-%\u0017!!A\t\u0002-e\b\u0002\u0003Be\u00057\"\tac?\t\u0011\re\"1\fC\u0003\u0017{D\u0001ba\u0013\u0003\\\u0011\u0015Ar\u0002\u0005\u000b\u00077\u0012Y&!A\u0005\u00061\u0005\u0002BCB5\u00057\n\t\u0011\"\u0002\r2!I1R_\u0001\u0002\u0002\u0013\rAR\t\u0004\u0007\u0019/\n1\u0001$\u0017\t\u001f1=$\u0011\u000eC\u0001\u0002\u000b\u0015)\u0019!C\u0005\u0019cBA\u0002d \u0003j\t\u0015\t\u0011)A\u0005\u0019gB\u0001B!3\u0003j\u0011\u0005A\u0012\u0011\u0005\t\u0007\'\u0011I\u0007\"\u0001\rr!A1Q\u0003B5\t\u0003b9\t\u0003\u0006\u0004\u001a\t%\u0014\u0011!C!\u00077A!ba\t\u0003j\u0005\u0005I\u0011\tGE\u000f%ai)AA\u0001\u0012\u0003ayIB\u0005\rX\u0005\t\t\u0011#\u0001\r\u0012\"A!\u0011\u001aB>\t\u0003a\u0019\n\u0003\u0005\u0004:\tmDQ\u0001GK\u0011!\u0019YEa\u001f\u0005\u00061\u001d\u0006BCB.\u0005w\n\t\u0011\"\u0002\r:\"Q1\u0011\u000eB>\u0003\u0003%)\u0001$3\t\u001315\u0015!!A\u0005\u00041ugA\u0002Gx\u0003\ra\t\u0010C\b\r~\n%E\u0011!A\u0003\u0006\u000b\u0007I\u0011\u0002G\u0000\u00111i9A!#\u0003\u0006\u0003\u0005\u000b\u0011BG\u0001\u0011!\u0011IM!#\u0005\u00025%\u0001\u0002CB\n\u0005\u0013#\t!$\u0005\t\u0011\rU!\u0011\u0012C!\u001b+A!b!\u0007\u0003\n\u0006\u0005I\u0011IB\u000e\u0011)\u0019\u0019C!#\u0002\u0002\u0013\u0005SrC\u0004\n\u001b7\t\u0011\u0011!E\u0001\u001b;1\u0011\u0002d<\u0002\u0003\u0003E\t!d\b\t\u0011\t%\'1\u0014C\u0001\u001bCA\u0001b!\u000f\u0003\u001c\u0012\u0015Q2\u0005\u0005\t\u0007\u0017\u0012Y\n\"\u0002\u000e2!Q11\fBN\u0003\u0003%)!d\u0010\t\u0015\r%$1TA\u0001\n\u000biY\u0005C\u0005\u000e\u001c\u0005\t\t\u0011b\u0001\u000e\\\u0005!2i\u001c7mK\u000e$\u0018n\u001c8D_:4XM\u001d;feNTAA!,\u00030\u0006A\u0001/\u0019:bY2,GN\u0003\u0003\u00032\nM\u0016AC2pY2,7\r^5p]*\u0011!QW\u0001\u0006g\u000e\fG.Y\u0002\u0001!\r\u0011Y,A\u0007\u0003\u0005W\u0013AcQ8mY\u0016\u001cG/[8o\u0007>tg/\u001a:uKJ\u001c8cA\u0001\u0003BB!!1\u0019Bc\u001b\t\u0011\u0019,\u0003\u0003\u0003H\nM&AB!osJ+g-\u0001\u0004=S:LGO\u0010\u000b\u0003\u0005s\u0013\u0001$\u0013;fe\u0006\u0014G.Z%t!\u0006\u0014\u0018\r\u001c7fY&T\u0018M\u00197f+\u0011\u0011\tN!:\u0014\u000b\r\u0011\u0019N!7\u0011\t\t\r\'Q[\u0005\u0005\u0005/\u0014\u0019L\u0001\u0004B]f4\u0016\r\u001c\t\t\u00057\u0014iN!9\u0003x6\u0011!qV\u0005\u0005\u0005?\u0014yK\u0001\u000bDkN$x.\u001c)be\u0006dG.\u001a7ju\u0006\u0014G.\u001a\t\u0005\u0005G\u0014)\u000f\u0004\u0001\u0005\u000f\t\u001d8A1\u0001\u0003j\n\t\u0011)\u0005\u0003\u0003l\nE\b\u0003\u0002Bb\u0005[LAAa<\u00034\n9aj\u001c;iS:<\u0007\u0003\u0002Bb\u0005gLAA!>\u00034\n\u0019\u0011I\\=\u0011\r\tm&\u0011 Bq\u0013\u0011\u0011YPa+\u0003\u0017A\u000b\'/\u0013;fe\u0006\u0014G.Z\u0001Ng\u000e\fG.\u0019\u0013d_2dWm\u0019;j_:$\u0003/\u0019:bY2,G\u000eJ\"pY2,7\r^5p]\u000e{gN^3si\u0016\u00148\u000fJ%uKJ\f\'\r\\3JgB\u000b\'/\u00197mK2L\'0\u00192mK\u0012\"3m\u001c7m+\t\u0019\t\u0001\u0005\u0004\u0003\\\u000e\r!\u0011]\u0005\u0005\u0007\u000b\u0011yK\u0001\u0005Ji\u0016\u0014\u0018M\u00197f\u00039\u001b8-\u00197bI\r|G\u000e\\3di&|g\u000e\n9be\u0006dG.\u001a7%\u0007>dG.Z2uS>t7i\u001c8wKJ$XM]:%\u0013R,\'/\u00192mK&\u001b\b+\u0019:bY2,G.\u001b>bE2,G\u0005J2pY2\u0004C\u0003BB\u0006\u0007\u001f\u0001Ra!\u0004\u0004\u0005Cl\u0011!\u0001\u0005\b\u0007#1\u0001\u0019AB\u0001\u0003\u0011\u0019w\u000e\u001c7\u0002\u0007M,\u0017/A\u0002qCJ,\"Aa>\u0002\u0011!\f7\u000f[\"pI\u0016$\"a!\b\u0011\t\t\r7qD\u0005\u0005\u0007C\u0011\u0019LA\u0002J]R\fa!Z9vC2\u001cH\u0003BB\u0014\u0007[\u0001BAa1\u0004*%!11\u0006BZ\u0005\u001d\u0011un\u001c7fC:D\u0011ba\f\u000b\u0003\u0003\u0005\rA!=\u0002\u0007a$\u0013\'\u0001\rJi\u0016\u0014\u0018M\u00197f\u0013N\u0004\u0016M]1mY\u0016d\u0017N_1cY\u0016\u00042a!\u0004\r\'\ra!\u0011\u0019\u000b\u0003\u0007g\tQb]3rI\u0015DH/\u001a8tS>tW\u0003BB\u001f\u0007\u0007\"Baa\u0010\u0004FA1!1\\B\u0002\u0007\u0003\u0002BAa9\u0004D\u00119!q\u001d\bC\u0002\t%\bbBB$\u001d\u0001\u00071\u0011J\u0001\u0006IQD\u0017n\u001d\t\u0006\u0007\u001b\u00191\u0011I\u0001\u000ea\u0006\u0014H%\u001a=uK:\u001c\u0018n\u001c8\u0016\t\r=3Q\u000b\u000b\u0005\u0007#\u001a9\u0006\u0005\u0004\u0003<\ne81\u000b\t\u0005\u0005G\u001c)\u0006B\u0004\u0003h>\u0011\rA!;\t\u000f\r\u001ds\u00021\u0001\u0004ZA)1QB\u0002\u0004T\u0005\u0011\u0002.Y:i\u0007>$W\rJ3yi\u0016t7/[8o+\u0011\u0019yfa\u001a\u0015\t\rm1\u0011\r\u0005\b\u0007\u000f\u0002\u0002\u0019AB2!\u0015\u0019iaAB3!\u0011\u0011\u0019oa\u001a\u0005\u000f\t\u001d\bC1\u0001\u0003j\u0006\u0001R-];bYN$S\r\u001f;f]NLwN\\\u000b\u0005\u0007[\u001aI\b\u0006\u0003\u0004p\rMD\u0003BB\u0014\u0007cB\u0011ba\f\u0012\u0003\u0003\u0005\rA!=\t\u000f\r\u001d\u0013\u00031\u0001\u0004vA)1QB\u0002\u0004xA!!1]B=\t\u001d\u00119/\u0005b\u0001\u0005S,Ba! \u0004\u0004R!1qPBC!\u0015\u0019iaABA!\u0011\u0011\u0019oa!\u0005\u000f\t\u001d(C1\u0001\u0003j\"91\u0011\u0003\nA\u0002\r\u001d\u0005C\u0002Bn\u0007\u0007\u0019\tIA\u0010NkR\f\'\r\\3Ji\u0016\u0014\u0018M\u00197f\u0013N\u0004\u0016M]1mY\u0016d\u0017N_1cY\u0016,Ba!$\u0004\u0014N)1Ca5\u0004\u0010BA!1\u001cBo\u0007#\u001b)\n\u0005\u0003\u0003d\u000eMEa\u0002Bt\'\t\u0007!\u0011\u001e\t\u0007\u0007/\u001bij!%\u000e\u0005\re%\u0002BBN\u0005W\u000bq!\\;uC\ndW-\u0003\u0003\u0003|\u000ee\u0015\u0001V:dC2\fGeY8mY\u0016\u001cG/[8oIA\f\'/\u00197mK2$3i\u001c7mK\u000e$\u0018n\u001c8D_:4XM\u001d;feN$S*\u001e;bE2,\u0017\n^3sC\ndW-S:QCJ\fG\u000e\\3mSj\f\'\r\\3%I\r|G\u000e\\\u000b\u0003\u0007G\u0003ba!*\u0004*\u000eEUBABT\u0015\u0011\u0019YJa,\n\t\r\u00151qU\u0001Vg\u000e\fG.\u0019\u0013d_2dWm\u0019;j_:$\u0003/\u0019:bY2,G\u000eJ\"pY2,7\r^5p]\u000e{gN^3si\u0016\u00148\u000fJ\'vi\u0006\u0014G.Z%uKJ\f\'\r\\3JgB\u000b\'/\u00197mK2L\'0\u00192mK\u0012\"3m\u001c7mAQ!1qVBY!\u0015\u0019iaEBI\u0011\u001d\u0019\tB\u0006a\u0001\u0007G+\"a!&\u0015\t\r\u001d2q\u0017\u0005\n\u0007_Q\u0012\u0011!a\u0001\u0005c\fq$T;uC\ndW-\u0013;fe\u0006\u0014G.Z%t!\u0006\u0014\u0018\r\u001c7fY&T\u0018M\u00197f!\r\u0019i\u0001H\n\u00049\t\u0005GCAB^+\u0011\u0019\u0019m!3\u0015\t\r\u001571\u001a\t\u0007\u0007K\u001bIka2\u0011\t\t\r8\u0011\u001a\u0003\b\u0005Ot\"\u0019\u0001Bu\u0011\u001d\u00199E\ba\u0001\u0007\u001b\u0004Ra!\u0004\u0014\u0007\u000f,Ba!5\u0004XR!11[Bm!\u0019\u00199j!(\u0004VB!!1]Bl\t\u001d\u00119o\bb\u0001\u0005SDqaa\u0012 \u0001\u0004\u0019Y\u000eE\u0003\u0004\u000eM\u0019).\u0006\u0003\u0004`\u000e\u001dH\u0003BB\u000e\u0007CDqaa\u0012!\u0001\u0004\u0019\u0019\u000fE\u0003\u0004\u000eM\u0019)\u000f\u0005\u0003\u0003d\u000e\u001dHa\u0002BtA\t\u0007!\u0011^\u000b\u0005\u0007W\u001c9\u0010\u0006\u0003\u0004n\u000eEH\u0003BB\u0014\u0007_D\u0011ba\f\"\u0003\u0003\u0005\rA!=\t\u000f\r\u001d\u0013\u00051\u0001\u0004tB)1QB\n\u0004vB!!1]B|\t\u001d\u00119/\tb\u0001\u0005S,Baa?\u0005\u0002Q!1Q C\u0002!\u0015\u0019iaEB\u0000!\u0011\u0011\u0019\u000f\"\u0001\u0005\u000f\t\u001d(E1\u0001\u0003j\"91\u0011\u0003\u0012A\u0002\u0011\u0015\u0001CBBS\u0007S\u001byPA\u0011J[6,H/\u00192mK&#XM]1cY\u0016L5\u000fU1sC2dW\r\\5{C\ndW-\u0006\u0003\u0005\f\u0011E1#B\u0012\u0003T\u00125\u0001\u0003\u0003Bn\u0005;$y\u0001b\u0005\u0011\t\t\rH\u0011\u0003\u0003\b\u0005O\u001c#\u0019\u0001Bu!\u0019!)\u0002b\u0007\u0005\u00105\u0011Aq\u0003\u0006\u0005\t3\u0011Y+A\u0005j[6,H/\u00192mK&!!1 C\f\u0003Y\u001b8-\u00197bI\r|G\u000e\\3di&|g\u000e\n9be\u0006dG.\u001a7%\u0007>dG.Z2uS>t7i\u001c8wKJ$XM]:%\u00136lW\u000f^1cY\u0016LE/\u001a:bE2,\u0017j\u001d)be\u0006dG.\u001a7ju\u0006\u0014G.\u001a\u0013%G>dG.\u0006\u0002\u0005\"A1A1\u0005C\u0014\t\u001fi!\u0001\"\n\u000b\t\u0011e!qV\u0005\u0005\u0007\u000b!)#A,tG\u0006d\u0017\rJ2pY2,7\r^5p]\u0012\u0002\u0018M]1mY\u0016dGeQ8mY\u0016\u001cG/[8o\u0007>tg/\u001a:uKJ\u001cH%S7nkR\f\'\r\\3Ji\u0016\u0014\u0018M\u00197f\u0013N\u0004\u0016M]1mY\u0016d\u0017N_1cY\u0016$CeY8mY\u0002\"B\u0001\"\f\u00050A)1QB\u0012\u0005\u0010!91\u0011\u0003\u0014A\u0002\u0011\u0005RC\u0001C\n)\u0011\u00199\u0003\"\u000e\t\u0013\r=\"&!AA\u0002\tE\u0018!I%n[V$\u0018M\u00197f\u0013R,\'/\u00192mK&\u001b\b+\u0019:bY2,G.\u001b>bE2,\u0007cAB\u0007YM\u0019AF!1\u0015\u0005\u0011eR\u0003\u0002C!\t\u000f\"B\u0001b\u0011\u0005JA1A1\u0005C\u0014\t\u000b\u0002BAa9\u0005H\u00119!q\u001d\u0018C\u0002\t%\bbBB$]\u0001\u0007A1\n\t\u0006\u0007\u001b\u0019CQI\u000b\u0005\t\u001f\")\u0006\u0006\u0003\u0005R\u0011]\u0003C\u0002C\u000b\t7!\u0019\u0006\u0005\u0003\u0003d\u0012UCa\u0002Bt_\t\u0007!\u0011\u001e\u0005\b\u0007\u000fz\u0003\u0019\u0001C-!\u0015\u0019ia\tC*+\u0011!i\u0006\"\u001a\u0015\t\rmAq\f\u0005\b\u0007\u000f\u0002\u0004\u0019\u0001C1!\u0015\u0019ia\tC2!\u0011\u0011\u0019\u000f\"\u001a\u0005\u000f\t\u001d\bG1\u0001\u0003jV!A\u0011\u000eC;)\u0011!Y\u0007b\u001c\u0015\t\r\u001dBQ\u000e\u0005\n\u0007_\t\u0014\u0011!a\u0001\u0005cDqaa\u00122\u0001\u0004!\t\bE\u0003\u0004\u000e\r\"\u0019\b\u0005\u0003\u0003d\u0012UDa\u0002Btc\t\u0007!\u0011^\u000b\u0005\ts\"y\b\u0006\u0003\u0005|\u0011\u0005\u0005#BB\u0007G\u0011u\u0004\u0003\u0002Br\t\u007f\"qAa:3\u0005\u0004\u0011I\u000fC\u0004\u0004\u0012I\u0002\r\u0001b!\u0011\r\u0011\rBq\u0005C?\u0003M\u0019X-]%t!\u0006\u0014\u0018\r\u001c7fY&T\u0018M\u00197f+\u0011!I\tb%\u0015\t\u0011-E1\u0014\t\t\u00057$i\t\"%\u0005\u0016&!Aq\u0012BX\u00059\u0001\u0016M]1mY\u0016d\u0017N_1cY\u0016\u0004BAa9\u0005\u0014\u00129!q]\u001aC\u0002\t%\bC\u0002B^\t/#\t*\u0003\u0003\u0005\u001a\n-&A\u0002)beN+\u0017\u000fC\u0004\u0004\u0012M\u0002\r\u0001\"(\u0011\r\tmGq\u0014CI\u0013\u0011!\tKa,\u0003\u0007M+\u0017O\u0001\u000eNkR\f\'\r\\3TKFL5\u000fU1sC2dW\r\\5{C\ndW-\u0006\u0003\u0005(\u001256#\u0002\u001b\u0003T\u0012%\u0006\u0003\u0003Bn\u0005;$Y\u000bb,\u0011\t\t\rHQ\u0016\u0003\b\u0005O$$\u0019\u0001Bu!\u0019\u00199\n\"-\u0005,&!A\u0011TBM\u0003=\u001b8-\u00197bI\r|G\u000e\\3di&|g\u000e\n9be\u0006dG.\u001a7%\u0007>dG.Z2uS>t7i\u001c8wKJ$XM]:%\u001bV$\u0018M\u00197f\'\u0016\f\u0018j\u001d)be\u0006dG.\u001a7ju\u0006\u0014G.\u001a\u0013%G>dG.\u0006\u0002\u00058B11Q\u0015C]\tWKA\u0001\")\u0004(\u0006\u00016oY1mC\u0012\u001aw\u000e\u001c7fGRLwN\u001c\u0013qCJ\fG\u000e\\3mI\r{G\u000e\\3di&|gnQ8om\u0016\u0014H/\u001a:tI5+H/\u00192mKN+\u0017/S:QCJ\fG\u000e\\3mSj\f\'\r\\3%I\r|G\u000e\u001c\u0011\u0015\t\u0011}F\u0011\u0019\t\u0006\u0007\u001b!D1\u0016\u0005\b\u0007#9\u0004\u0019\u0001C\\+\t!y\u000b\u0006\u0003\u0004(\u0011\u001d\u0007\"CB\u0018w\u0005\u0005\t\u0019\u0001By\u0003iiU\u000f^1cY\u0016\u001cV-]%t!\u0006\u0014\u0018\r\u001c7fY&T\u0018M\u00197f!\r\u0019i!P\n\u0004{\t\u0005GC\u0001Cf+\u0011!\u0019\u000e\"7\u0015\t\u0011UG1\u001c\t\u0007\u0007K#I\fb6\u0011\t\t\rH\u0011\u001c\u0003\b\u0005O|$\u0019\u0001Bu\u0011\u001d\u00199e\u0010a\u0001\t;\u0004Ra!\u00045\t/,B\u0001\"9\u0005hR!A1\u001dCu!\u0019\u00199\n\"-\u0005fB!!1\u001dCt\t\u001d\u00119\u000f\u0011b\u0001\u0005SDqaa\u0012A\u0001\u0004!Y\u000fE\u0003\u0004\u000eQ\")/\u0006\u0003\u0005p\u0012]H\u0003BB\u000e\tcDqaa\u0012B\u0001\u0004!\u0019\u0010E\u0003\u0004\u000eQ\")\u0010\u0005\u0003\u0003d\u0012]Ha\u0002Bt\u0003\n\u0007!\u0011^\u000b\u0005\tw,9\u0001\u0006\u0003\u0005~\u0016\u0005A\u0003BB\u0014\t\u007fD\u0011ba\fC\u0003\u0003\u0005\rA!=\t\u000f\r\u001d#\t1\u0001\u0006\u0004A)1Q\u0002\u001b\u0006\u0006A!!1]C\u0004\t\u001d\u00119O\u0011b\u0001\u0005S,B!b\u0003\u0006\u0012Q!QQBC\n!\u0015\u0019i\u0001NC\b!\u0011\u0011\u0019/\"\u0005\u0005\u000f\t\u001d8I1\u0001\u0003j\"91\u0011C\"A\u0002\u0015U\u0001CBBS\ts+yAA\u0010NkR\f\'\r\\3BeJ\f\u0017pU3r\u0013N\u0004\u0016M]1mY\u0016d\u0017N_1cY\u0016,B!b\u0007\u0006\"M)AIa5\u0006\u001eAA!1\u001cBo\u000b?))\u0003\u0005\u0003\u0003d\u0016\u0005BaBC\u0012\t\n\u0007!\u0011\u001e\u0002\u0002)B11qSC\u0014\u000b?IA!\"\u000b\u0004\u001a\nA\u0001+\u0019:BeJ\f\u00170\u0001+tG\u0006d\u0017\rJ2pY2,7\r^5p]\u0012\u0002\u0018M]1mY\u0016dGeQ8mY\u0016\u001cG/[8o\u0007>tg/\u001a:uKJ\u001cH%T;uC\ndW-\u0011:sCf\u001cV-]%t!\u0006\u0014\u0018\r\u001c7fY&T\u0018M\u00197fI\u0011\u001aw\u000e\u001c7\u0016\u0005\u0015=\u0002CBBS\u000bc)y\"\u0003\u0003\u00064\r\u001d&\u0001C!se\u0006L8+Z9\u0002+N\u001c\u0017\r\\1%G>dG.Z2uS>tG\u0005]1sC2dW\r\u001c\u0013D_2dWm\u0019;j_:\u001cuN\u001c<feR,\'o\u001d\u0013NkR\f\'\r\\3BeJ\f\u0017pU3r\u0013N\u0004\u0016M]1mY\u0016d\u0017N_1cY\u0016$CeY8mY\u0002\"B!\"\u000f\u0006<A)1Q\u0002#\u0006 !91\u0011C$A\u0002\u0015=RCAC\u0013)\u0011\u00199#\"\u0011\t\u0013\r=2*!AA\u0002\tE\u0018aH\'vi\u0006\u0014G.Z!se\u0006L8+Z9JgB\u000b\'/\u00197mK2L\'0\u00192mKB\u00191QB\'\u0014\u00075\u0013\t\r\u0006\u0002\u0006FU!QQJC*)\u0011)y%\"\u0016\u0011\r\r\u0015V\u0011GC)!\u0011\u0011\u0019/b\u0015\u0005\u000f\u0015\rrJ1\u0001\u0003j\"91qI(A\u0002\u0015]\u0003#BB\u0007\t\u0016ES\u0003BC.\u000bC\"B!\"\u0018\u0006dA11qSC\u0014\u000b?\u0002BAa9\u0006b\u00119Q1\u0005)C\u0002\t%\bbBB$!\u0002\u0007QQ\r\t\u0006\u0007\u001b!UqL\u000b\u0005\u000bS*\t\b\u0006\u0003\u0004\u001c\u0015-\u0004bBB$#\u0002\u0007QQ\u000e\t\u0006\u0007\u001b!Uq\u000e\t\u0005\u0005G,\t\bB\u0004\u0006$E\u0013\rA!;\u0016\t\u0015UT\u0011\u0011\u000b\u0005\u000bo*Y\b\u0006\u0003\u0004(\u0015e\u0004\"CB\u0018%\u0006\u0005\t\u0019\u0001By\u0011\u001d\u00199E\u0015a\u0001\u000b{\u0002Ra!\u0004E\u000b\u007f\u0002BAa9\u0006\u0002\u00129Q1\u0005*C\u0002\t%X\u0003BCC\u000b\u0017#B!b\"\u0006\u000eB)1Q\u0002#\u0006\nB!!1]CF\t\u001d)\u0019c\u0015b\u0001\u0005SDqa!\u0005T\u0001\u0004)y\t\u0005\u0004\u0004&\u0016ER\u0011\u0012\u0002#\u001bV$\u0018M\u00197f\u0003J\u0014\u0018-\u001f\"vM\u001a,\'/S:QCJ\fG\u000e\\3mSj\f\'\r\\3\u0016\t\u0015UU1T\n\u0006)\nMWq\u0013\t\t\u00057\u0014i.\"\'\u0006\u001eB!!1]CN\t\u001d)\u0019\u0003\u0016b\u0001\u0005S\u0004baa&\u0006(\u0015e\u0015aV:dC2\fGeY8mY\u0016\u001cG/[8oIA\f\'/\u00197mK2$3i\u001c7mK\u000e$\u0018n\u001c8D_:4XM\u001d;feN$S*\u001e;bE2,\u0017I\u001d:bs\n+hMZ3s\u0013N\u0004\u0016M]1mY\u0016d\u0017N_1cY\u0016$CeY8mYV\u0011Q1\u0015\t\u0007\u0007K+)+\"\'\n\t\u0015\u001d6q\u0015\u0002\f\u0003J\u0014\u0018-\u001f\"vM\u001a,\'/\u0001-tG\u0006d\u0017\rJ2pY2,7\r^5p]\u0012\u0002\u0018M]1mY\u0016dGeQ8mY\u0016\u001cG/[8o\u0007>tg/\u001a:uKJ\u001cH%T;uC\ndW-\u0011:sCf\u0014UO\u001a4fe&\u001b\b+\u0019:bY2,G.\u001b>bE2,G\u0005J2pY2\u0004C\u0003BCW\u000b_\u0003Ra!\u0004U\u000b3Cqa!\u0005X\u0001\u0004)\u0019+\u0006\u0002\u0006\u001eR!1qEC[\u0011%\u0019ycWA\u0001\u0002\u0004\u0011\t0\u0001\u0012NkR\f\'\r\\3BeJ\f\u0017PQ;gM\u0016\u0014\u0018j\u001d)be\u0006dG.\u001a7ju\u0006\u0014G.\u001a\t\u0004\u0007\u001bi6cA/\u0003BR\u0011Q\u0011X\u000b\u0005\u000b\u0003,9\r\u0006\u0003\u0006D\u0016%\u0007CBBS\u000bK+)\r\u0005\u0003\u0003d\u0016\u001dGaBC\u0012?\n\u0007!\u0011\u001e\u0005\b\u0007\u000fz\u0006\u0019ACf!\u0015\u0019i\u0001VCc+\u0011)y-\"6\u0015\t\u0015EWq\u001b\t\u0007\u0007/+9#b5\u0011\t\t\rXQ\u001b\u0003\b\u000bG\u0001\'\u0019\u0001Bu\u0011\u001d\u00199\u0005\u0019a\u0001\u000b3\u0004Ra!\u0004U\u000b\',B!\"8\u0006fR!11DCp\u0011\u001d\u00199%\u0019a\u0001\u000bC\u0004Ra!\u0004U\u000bG\u0004BAa9\u0006f\u00129Q1E1C\u0002\t%X\u0003BCu\u000bk$B!b;\u0006pR!1qECw\u0011%\u0019yCYA\u0001\u0002\u0004\u0011\t\u0010C\u0004\u0004H\t\u0004\r!\"=\u0011\u000b\r5A+b=\u0011\t\t\rXQ\u001f\u0003\b\u000bG\u0011\'\u0019\u0001Bu+\u0011)I0b@\u0015\t\u0015mh\u0011\u0001\t\u0006\u0007\u001b!VQ \t\u0005\u0005G,y\u0010B\u0004\u0006$\r\u0014\rA!;\t\u000f\rE1\r1\u0001\u0007\u0004A11QUCS\u000b{\u0014A$S7nkR\f\'\r\\3TKFL5\u000fU1sC2dW\r\\5{C\ndW-\u0006\u0003\u0007\n\u0019=1#\u00023\u0003T\u001a-\u0001\u0003\u0003Bn\u0005;4iA\"\u0005\u0011\t\t\rhq\u0002\u0003\b\u0005O$\'\u0019\u0001Bu!\u0019!)Bb\u0005\u0007\u000e%!A\u0011\u0014C\f\u0003E\u001b8-\u00197bI\r|G\u000e\\3di&|g\u000e\n9be\u0006dG.\u001a7%\u0007>dG.Z2uS>t7i\u001c8wKJ$XM]:%\u00136lW\u000f^1cY\u0016\u001cV-]%t!\u0006\u0014\u0018\r\u001c7fY&T\u0018M\u00197fI\u0011\u001aw\u000e\u001c7\u0016\u0005\u0019e\u0001C\u0002C\u0012\r71i!\u0003\u0003\u0005\"\u0012\u0015\u0012AU:dC2\fGeY8mY\u0016\u001cG/[8oIA\f\'/\u00197mK2$3i\u001c7mK\u000e$\u0018n\u001c8D_:4XM\u001d;feN$\u0013*\\7vi\u0006\u0014G.Z*fc&\u001b\b+\u0019:bY2,G.\u001b>bE2,G\u0005J2pY2\u0004C\u0003\u0002D\u0011\rG\u0001Ra!\u0004e\r\u001bAqa!\u0005h\u0001\u00041I\"\u0006\u0002\u0007\u0012Q!1q\u0005D\u0015\u0011%\u0019yc[A\u0001\u0002\u0004\u0011\t0\u0001\u000fJ[6,H/\u00192mKN+\u0017/S:QCJ\fG\u000e\\3mSj\f\'\r\\3\u0011\u0007\r5QnE\u0002n\u0005\u0003$\"A\"\f\u0016\t\u0019Ub1\b\u000b\u0005\ro1i\u0004\u0005\u0004\u0005$\u0019ma\u0011\b\t\u0005\u0005G4Y\u0004B\u0004\u0003h>\u0014\rA!;\t\u000f\r\u001ds\u000e1\u0001\u0007@A)1Q\u00023\u0007:U!a1\tD%)\u00111)Eb\u0013\u0011\r\u0011Ua1\u0003D$!\u0011\u0011\u0019O\"\u0013\u0005\u000f\t\u001d\bO1\u0001\u0003j\"91q\t9A\u0002\u00195\u0003#BB\u0007I\u001a\u001dS\u0003\u0002D)\r3\"Baa\u0007\u0007T!91qI9A\u0002\u0019U\u0003#BB\u0007I\u001a]\u0003\u0003\u0002Br\r3\"qAa:r\u0005\u0004\u0011I/\u0006\u0003\u0007^\u0019%D\u0003\u0002D0\rG\"Baa\n\u0007b!I1q\u0006:\u0002\u0002\u0003\u0007!\u0011\u001f\u0005\b\u0007\u000f\u0012\b\u0019\u0001D3!\u0015\u0019i\u0001\u001aD4!\u0011\u0011\u0019O\"\u001b\u0005\u000f\t\u001d(O1\u0001\u0003jV!aQ\u000eD:)\u00111yG\"\u001e\u0011\u000b\r5AM\"\u001d\u0011\t\t\rh1\u000f\u0003\b\u0005O\u001c(\u0019\u0001Bu\u0011\u001d\u0019\tb\u001da\u0001\ro\u0002b\u0001b\t\u0007\u001c\u0019E$!\u0006*b]\u001e,\u0017j\u001d)be\u0006dG.\u001a7ju\u0006\u0014G.Z\n\u0006i\nMgQ\u0010\t\t\u00057\u0014in!\b\u0007\u0000A!AQ\u0003DA\u0013\u00111\u0019\tb\u0006\u0003\u0011A\u000b\'OU1oO\u0016\f!j]2bY\u0006$3m\u001c7mK\u000e$\u0018n\u001c8%a\u0006\u0014\u0018\r\u001c7fY\u0012\u001au\u000e\u001c7fGRLwN\\\"p]Z,\'\u000f^3sg\u0012\u0012\u0016M\\4f\u0013N\u0004\u0016M]1mY\u0016d\u0017N_1cY\u0016$CeY8mYV\u0011a\u0011\u0012\t\u0005\tG1Y)\u0003\u0003\u0007\u000e\u0012\u0015\"!\u0002*b]\u001e,\u0017aS:dC2\fGeY8mY\u0016\u001cG/[8oIA\f\'/\u00197mK2$3i\u001c7mK\u000e$\u0018n\u001c8D_:4XM\u001d;feN$#+\u00198hK&\u001b\b+\u0019:bY2,G.\u001b>bE2,G\u0005J2pY2\u0004C\u0003\u0002DJ\r+\u00032a!\u0004u\u0011\u001d\u0019\tb\u001ea\u0001\r\u0013+\"Ab \u0015\t\r\u001db1\u0014\u0005\n\u0007_Y\u0018\u0011!a\u0001\u0005c\fQCU1oO\u0016L5\u000fU1sC2dW\r\\5{C\ndW\rE\u0002\u0004\u000eu\u001c2! Ba)\t1y\n\u0006\u0003\u0007\n\u001a\u001d\u0006bBB$\u007f\u0002\u0007a1\u0013\u000b\u0005\r\u007f2Y\u000b\u0003\u0005\u0004H\u0005\u0005\u0001\u0019\u0001DJ)\u0011\u0019YBb,\t\u0011\r\u001d\u00131\u0001a\u0001\r\'#BAb-\u00078R!1q\u0005D[\u0011)\u0019y#!\u0002\u0002\u0002\u0003\u0007!\u0011\u001f\u0005\t\u0007\u000f\n)\u00011\u0001\u0007\u0014R!a1\u0013D^\u0011!\u0019\t\"a\u0002A\u0002\u0019%%A\u0006,fGR|\'/S:QCJ\fG\u000e\\3mSj\f\'\r\\3\u0016\t\u0019\u0005gqY\n\u0007\u0003\u0013\u0011\u0019Nb1\u0011\u0011\tm\'Q\u001cDc\r\u0013\u0004BAa9\u0007H\u0012AQ1EA\u0005\u0005\u0004\u0011I\u000f\u0005\u0004\u0005\u0016\u0019-gQY\u0005\u0005\r\u001b$9BA\u0005QCJ4Vm\u0019;pe\u0006Y5oY1mC\u0012\u001aw\u000e\u001c7fGRLwN\u001c\u0013qCJ\fG\u000e\\3mI\r{G\u000e\\3di&|gnQ8om\u0016\u0014H/\u001a:tIY+7\r^8s\u0013N\u0004\u0016M]1mY\u0016d\u0017N_1cY\u0016$CeY8mYV\u0011a1\u001b\t\u0007\tG1)N\"2\n\t\u0019]GQ\u0005\u0002\u0007-\u0016\u001cGo\u001c:\u0002\u0019N\u001c\u0017\r\\1%G>dG.Z2uS>tG\u0005]1sC2dW\r\u001c\u0013D_2dWm\u0019;j_:\u001cuN\u001c<feR,\'o\u001d\u0013WK\u000e$xN]%t!\u0006\u0014\u0018\r\u001c7fY&T\u0018M\u00197fI\u0011\u001aw\u000e\u001c7!)\u00111iNb8\u0011\r\r5\u0011\u0011\u0002Dc\u0011!\u0019\t\"a\u0004A\u0002\u0019MWC\u0001De)\u0011\u00199C\":\t\u0015\r=\u0012qCA\u0001\u0002\u0004\u0011\t0\u0001\fWK\u000e$xN]%t!\u0006\u0014\u0018\r\u001c7fY&T\u0018M\u00197f!\u0011\u0019i!a\u0007\u0014\t\u0005m!\u0011\u0019\u000b\u0003\rS,BA\"=\u0007xR!a1\u001fD}!\u0019!\u0019C\"6\u0007vB!!1\u001dD|\t!)\u0019#a\bC\u0002\t%\b\u0002CB$\u0003?\u0001\rAb?\u0011\r\r5\u0011\u0011\u0002D{+\u00111yp\"\u0002\u0015\t\u001d\u0005qq\u0001\t\u0007\t+1Ymb\u0001\u0011\t\t\rxQ\u0001\u0003\t\u000bG\t\tC1\u0001\u0003j\"A1qIA\u0011\u0001\u00049I\u0001\u0005\u0004\u0004\u000e\u0005%q1A\u000b\u0005\u000f\u001b9)\u0002\u0006\u0003\u0004\u001c\u001d=\u0001\u0002CB$\u0003G\u0001\ra\"\u0005\u0011\r\r5\u0011\u0011BD\n!\u0011\u0011\u0019o\"\u0006\u0005\u0011\u0015\r\u00121\u0005b\u0001\u0005S,Ba\"\u0007\b&Q!q1DD\u0010)\u0011\u00199c\"\b\t\u0015\r=\u0012QEA\u0001\u0002\u0004\u0011\t\u0010\u0003\u0005\u0004H\u0005\u0015\u0002\u0019AD\u0011!\u0019\u0019i!!\u0003\b$A!!1]D\u0013\t!)\u0019#!\nC\u0002\t%X\u0003BD\u0015\u000f_!Bab\u000b\b2A11QBA\u0005\u000f[\u0001BAa9\b0\u0011AQ1EA\u0014\u0005\u0004\u0011I\u000f\u0003\u0005\u0004\u0012\u0005\u001d\u0002\u0019AD\u001a!\u0019!\u0019C\"6\b.\t\u00192+\u001a;JgB\u000b\'/\u00197mK2L\'0\u00192mKV!q\u0011HD \'\u0019\tICa5\b<AA!1\u001cBo\u000f{9\t\u0005\u0005\u0003\u0003d\u001e}B\u0001\u0003Bt\u0003S\u0011\rA!;\u0011\r\tmv1ID\u001f\u0013\u00119)Ea+\u0003\rA\u000b\'oU3u\u0003!\u001b8-\u00197bI\r|G\u000e\\3di&|g\u000e\n9be\u0006dG.\u001a7%\u0007>dG.Z2uS>t7i\u001c8wKJ$XM]:%\'\u0016$\u0018j\u001d)be\u0006dG.\u001a7ju\u0006\u0014G.\u001a\u0013%G>dG.\u0006\u0002\bLA1!1\\D\'\u000f{IAab\u0014\u00030\n\u00191+\u001a;\u0002\u0013N\u001c\u0017\r\\1%G>dG.Z2uS>tG\u0005]1sC2dW\r\u001c\u0013D_2dWm\u0019;j_:\u001cuN\u001c<feR,\'o\u001d\u0013TKRL5\u000fU1sC2dW\r\\5{C\ndW\r\n\u0013d_2d\u0007\u0005\u0006\u0003\bV\u001d]\u0003CBB\u0007\u0003S9i\u0004\u0003\u0005\u0004\u0012\u0005=\u0002\u0019AD&+\t9\t\u0005\u0006\u0003\u0004(\u001du\u0003BCB\u0018\u0003o\t\t\u00111\u0001\u0003r\u0006\u00192+\u001a;JgB\u000b\'/\u00197mK2L\'0\u00192mKB!1QBA\u001e\'\u0011\tYD!1\u0015\u0005\u001d\u0005T\u0003BD5\u000f_\"Bab\u001b\brA1!1\\D\'\u000f[\u0002BAa9\bp\u0011A!q]A \u0005\u0004\u0011I\u000f\u0003\u0005\u0004H\u0005}\u0002\u0019AD:!\u0019\u0019i!!\u000b\bnU!qqOD?)\u00119Ihb \u0011\r\tmv1ID>!\u0011\u0011\u0019o\" \u0005\u0011\t\u001d\u0018\u0011\tb\u0001\u0005SD\u0001ba\u0012\u0002B\u0001\u0007q\u0011\u0011\t\u0007\u0007\u001b\tIcb\u001f\u0016\t\u001d\u0015uQ\u0012\u000b\u0005\u0007799\t\u0003\u0005\u0004H\u0005\r\u0003\u0019ADE!\u0019\u0019i!!\u000b\b\fB!!1]DG\t!\u00119/a\u0011C\u0002\t%X\u0003BDI\u000f;#Bab%\b\u0018R!1qEDK\u0011)\u0019y#!\u0012\u0002\u0002\u0003\u0007!\u0011\u001f\u0005\t\u0007\u000f\n)\u00051\u0001\b\u001aB11QBA\u0015\u000f7\u0003BAa9\b\u001e\u0012A!q]A#\u0005\u0004\u0011I/\u0006\u0003\b\"\u001e\u001dF\u0003BDR\u000fS\u0003ba!\u0004\u0002*\u001d\u0015\u0006\u0003\u0002Br\u000fO#\u0001Ba:\u0002H\t\u0007!\u0011\u001e\u0005\t\u0007#\t9\u00051\u0001\b,B1!1\\D\'\u000fK\u0013A$S7nkR\f\'\r\\3TKRL5\u000fU1sC2dW\r\\5{C\ndW-\u0006\u0003\b2\u001e]6CBA%\u0005\'<\u0019\f\u0005\u0005\u0003\\\nuwQWD]!\u0011\u0011\u0019ob.\u0005\u0011\t\u001d\u0018\u0011\nb\u0001\u0005S\u0004b\u0001\"\u0006\b<\u001eU\u0016\u0002BD#\t/\t\u0011k]2bY\u0006$3m\u001c7mK\u000e$\u0018n\u001c8%a\u0006\u0014\u0018\r\u001c7fY\u0012\u001au\u000e\u001c7fGRLwN\\\"p]Z,\'\u000f^3sg\u0012JU.\\;uC\ndWmU3u\u0013N\u0004\u0016M]1mY\u0016d\u0017N_1cY\u0016$CeY8mYV\u0011q\u0011\u0019\t\u0007\tG9\u0019m\".\n\t\u001d=CQE\u0001Sg\u000e\fG.\u0019\u0013d_2dWm\u0019;j_:$\u0003/\u0019:bY2,G\u000eJ\"pY2,7\r^5p]\u000e{gN^3si\u0016\u00148\u000fJ%n[V$\u0018M\u00197f\'\u0016$\u0018j\u001d)be\u0006dG.\u001a7ju\u0006\u0014G.\u001a\u0013%G>dG\u000e\t\u000b\u0005\u000f\u0013<Y\r\u0005\u0004\u0004\u000e\u0005%sQ\u0017\u0005\t\u0007#\ty\u00051\u0001\bBV\u0011q\u0011\u0018\u000b\u0005\u0007O9\t\u000e\u0003\u0006\u00040\u0005]\u0013\u0011!a\u0001\u0005c\fA$S7nkR\f\'\r\\3TKRL5\u000fU1sC2dW\r\\5{C\ndW\r\u0005\u0003\u0004\u000e\u0005m3\u0003BA.\u0005\u0003$\"a\"6\u0016\t\u001duw1\u001d\u000b\u0005\u000f?<)\u000f\u0005\u0004\u0005$\u001d\rw\u0011\u001d\t\u0005\u0005G<\u0019\u000f\u0002\u0005\u0003h\u0006}#\u0019\u0001Bu\u0011!\u00199%a\u0018A\u0002\u001d\u001d\bCBB\u0007\u0003\u0013:\t/\u0006\u0003\bl\u001eEH\u0003BDw\u000fg\u0004b\u0001\"\u0006\b<\u001e=\b\u0003\u0002Br\u000fc$\u0001Ba:\u0002b\t\u0007!\u0011\u001e\u0005\t\u0007\u000f\n\t\u00071\u0001\bvB11QBA%\u000f_,Ba\"?\t\u0002Q!11DD~\u0011!\u00199%a\u0019A\u0002\u001du\bCBB\u0007\u0003\u0013:y\u0010\u0005\u0003\u0003d\"\u0005A\u0001\u0003Bt\u0003G\u0012\rA!;\u0016\t!\u0015\u0001\u0012\u0003\u000b\u0005\u0011\u000fAY\u0001\u0006\u0003\u0004(!%\u0001BCB\u0018\u0003K\n\t\u00111\u0001\u0003r\"A1qIA3\u0001\u0004Ai\u0001\u0005\u0004\u0004\u000e\u0005%\u0003r\u0002\t\u0005\u0005GD\t\u0002\u0002\u0005\u0003h\u0006\u0015$\u0019\u0001Bu+\u0011A)\u0002c\u0007\u0015\t!]\u0001R\u0004\t\u0007\u0007\u001b\tI\u0005#\u0007\u0011\t\t\r\b2\u0004\u0003\t\u0005O\f9G1\u0001\u0003j\"A1\u0011CA4\u0001\u0004Ay\u0002\u0005\u0004\u0005$\u001d\r\u0007\u0012\u0004\u0002\u001b\u001bV$\u0018M\u00197f\'\u0016$\u0018j\u001d)be\u0006dG.\u001a7ju\u0006\u0014G.Z\u000b\u0005\u0011KAYc\u0005\u0004\u0002j\tM\u0007r\u0005\t\t\u00057\u0014i\u000e#\u000b\t.A!!1\u001dE\u0016\t!\u00119/!\u001bC\u0002\t%\bCBBL\u0011_AI#\u0003\u0003\bF\re\u0015aT:dC2\fGeY8mY\u0016\u001cG/[8oIA\f\'/\u00197mK2$3i\u001c7mK\u000e$\u0018n\u001c8D_:4XM\u001d;feN$S*\u001e;bE2,7+\u001a;JgB\u000b\'/\u00197mK2L\'0\u00192mK\u0012\"3m\u001c7m+\tA)\u0004\u0005\u0004\u0004&\"]\u0002\u0012F\u0005\u0005\u000f\u001f\u001a9+\u0001)tG\u0006d\u0017\rJ2pY2,7\r^5p]\u0012\u0002\u0018M]1mY\u0016dGeQ8mY\u0016\u001cG/[8o\u0007>tg/\u001a:uKJ\u001cH%T;uC\ndWmU3u\u0013N\u0004\u0016M]1mY\u0016d\u0017N_1cY\u0016$CeY8mY\u0002\"B\u0001#\u0010\t@A11QBA5\u0011SA\u0001b!\u0005\u0002p\u0001\u0007\u0001RG\u000b\u0003\u0011[!Baa\n\tF!Q1qFA<\u0003\u0003\u0005\rA!=\u000255+H/\u00192mKN+G/S:QCJ\fG\u000e\\3mSj\f\'\r\\3\u0011\t\r5\u00111P\n\u0005\u0003w\u0012\t\r\u0006\u0002\tJU!\u0001\u0012\u000bE,)\u0011A\u0019\u0006#\u0017\u0011\r\r\u0015\u0006r\u0007E+!\u0011\u0011\u0019\u000fc\u0016\u0005\u0011\t\u001d\u0018q\u0010b\u0001\u0005SD\u0001ba\u0012\u0002\u0000\u0001\u0007\u00012\f\t\u0007\u0007\u001b\tI\u0007#\u0016\u0016\t!}\u0003R\r\u000b\u0005\u0011CB9\u0007\u0005\u0004\u0004\u0018\"=\u00022\r\t\u0005\u0005GD)\u0007\u0002\u0005\u0003h\u0006\u0005%\u0019\u0001Bu\u0011!\u00199%!!A\u0002!%\u0004CBB\u0007\u0003SB\u0019\'\u0006\u0003\tn!UD\u0003BB\u000e\u0011_B\u0001ba\u0012\u0002\u0004\u0002\u0007\u0001\u0012\u000f\t\u0007\u0007\u001b\tI\u0007c\u001d\u0011\t\t\r\bR\u000f\u0003\t\u0005O\f\u0019I1\u0001\u0003jV!\u0001\u0012\u0010EC)\u0011AY\bc \u0015\t\r\u001d\u0002R\u0010\u0005\u000b\u0007_\t))!AA\u0002\tE\b\u0002CB$\u0003\u000b\u0003\r\u0001#!\u0011\r\r5\u0011\u0011\u000eEB!\u0011\u0011\u0019\u000f#\"\u0005\u0011\t\u001d\u0018Q\u0011b\u0001\u0005S,B\u0001##\t\u0010R!\u00012\u0012EI!\u0019\u0019i!!\u001b\t\u000eB!!1\u001dEH\t!\u00119/a\"C\u0002\t%\b\u0002CB\t\u0003\u000f\u0003\r\u0001c%\u0011\r\r\u0015\u0006r\u0007EG\u0005yiU\u000f^1cY\u0016D\u0015m\u001d5TKRL5\u000fU1sC2dW\r\\5{C\ndW-\u0006\u0003\t\u001a\"}5CBAE\u0005\'DY\n\u0005\u0005\u0003\\\nu\u0007R\u0014EQ!\u0011\u0011\u0019\u000fc(\u0005\u0011\u0015\r\u0012\u0011\u0012b\u0001\u0005S\u0004baa&\t$\"u\u0015\u0002\u0002ES\u00073\u0013!\u0002U1s\u0011\u0006\u001c\bnU3u\u0003M\u001b8-\u00197bI\r|G\u000e\\3di&|g\u000e\n9be\u0006dG.\u001a7%\u0007>dG.Z2uS>t7i\u001c8wKJ$XM]:%\u001bV$\u0018M\u00197f\u0011\u0006\u001c\bnU3u\u0013N\u0004\u0016M]1mY\u0016d\u0017N_1cY\u0016$CeY8mYV\u0011\u00012\u0016\t\u0007\u0007KCi\u000b#(\n\t!=6q\u0015\u0002\b\u0011\u0006\u001c\bnU3u\u0003Q\u001b8-\u00197bI\r|G\u000e\\3di&|g\u000e\n9be\u0006dG.\u001a7%\u0007>dG.Z2uS>t7i\u001c8wKJ$XM]:%\u001bV$\u0018M\u00197f\u0011\u0006\u001c\bnU3u\u0013N\u0004\u0016M]1mY\u0016d\u0017N_1cY\u0016$CeY8mY\u0002\"B\u0001#.\t8B11QBAE\u0011;C\u0001b!\u0005\u0002\u0010\u0002\u0007\u00012V\u000b\u0003\u0011C#Baa\n\t>\"Q1qFAL\u0003\u0003\u0005\rA!=\u0002=5+H/\u00192mK\"\u000b7\u000f[*fi&\u001b\b+\u0019:bY2,G.\u001b>bE2,\u0007\u0003BB\u0007\u00037\u001bB!a\'\u0003BR\u0011\u0001\u0012Y\u000b\u0005\u0011\u0013Dy\r\u0006\u0003\tL\"E\u0007CBBS\u0011[Ci\r\u0005\u0003\u0003d\"=G\u0001CC\u0012\u0003?\u0013\rA!;\t\u0011\r\u001d\u0013q\u0014a\u0001\u0011\'\u0004ba!\u0004\u0002\n\"5W\u0003\u0002El\u0011;$B\u0001#7\t`B11q\u0013ER\u00117\u0004BAa9\t^\u0012AQ1EAQ\u0005\u0004\u0011I\u000f\u0003\u0005\u0004H\u0005\u0005\u0006\u0019\u0001Eq!\u0019\u0019i!!#\t\\V!\u0001R\u001dEw)\u0011\u0019Y\u0002c:\t\u0011\r\u001d\u00131\u0015a\u0001\u0011S\u0004ba!\u0004\u0002\n\"-\b\u0003\u0002Br\u0011[$\u0001\"b\t\u0002$\n\u0007!\u0011^\u000b\u0005\u0011cDi\u0010\u0006\u0003\tt\"]H\u0003BB\u0014\u0011kD!ba\f\u0002&\u0006\u0005\t\u0019\u0001By\u0011!\u00199%!*A\u0002!e\bCBB\u0007\u0003\u0013CY\u0010\u0005\u0003\u0003d\"uH\u0001CC\u0012\u0003K\u0013\rA!;\u0016\t%\u0005\u0011r\u0001\u000b\u0005\u0013\u0007II\u0001\u0005\u0004\u0004\u000e\u0005%\u0015R\u0001\t\u0005\u0005GL9\u0001\u0002\u0005\u0006$\u0005\u001d&\u0019\u0001Bu\u0011!\u0019\t\"a*A\u0002%-\u0001CBBS\u0011[K)A\u0001\u0011J[6,H/\u00192mK\"\u000b7\u000f[*fi&\u001b\b+\u0019:bY2,G.\u001b>bE2,W\u0003BE\t\u0013/\u0019b!!+\u0003T&M\u0001\u0003\u0003Bn\u0005;L)\"#\u0007\u0011\t\t\r\u0018r\u0003\u0003\t\u000bG\tIK1\u0001\u0003jB1AQCE\u000e\u0013+IA\u0001#*\u0005\u0018\u0005)6oY1mC\u0012\u001aw\u000e\u001c7fGRLwN\u001c\u0013qCJ\fG\u000e\\3mI\r{G\u000e\\3di&|gnQ8om\u0016\u0014H/\u001a:tI%kW.\u001e;bE2,\u0007*Y:i\'\u0016$\u0018j\u001d)be\u0006dG.\u001a7ju\u0006\u0014G.\u001a\u0013%G>dG.\u0006\u0002\n\"A1A1EE\u0012\u0013+IA\u0001c,\u0005&\u000516oY1mC\u0012\u001aw\u000e\u001c7fGRLwN\u001c\u0013qCJ\fG\u000e\\3mI\r{G\u000e\\3di&|gnQ8om\u0016\u0014H/\u001a:tI%kW.\u001e;bE2,\u0007*Y:i\'\u0016$\u0018j\u001d)be\u0006dG.\u001a7ju\u0006\u0014G.\u001a\u0013%G>dG\u000e\t\u000b\u0005\u0013SIY\u0003\u0005\u0004\u0004\u000e\u0005%\u0016R\u0003\u0005\t\u0007#\ty\u000b1\u0001\n\"U\u0011\u0011\u0012\u0004\u000b\u0005\u0007OI\t\u0004\u0003\u0006\u00040\u0005]\u0016\u0011!a\u0001\u0005c\f\u0001%S7nkR\f\'\r\\3ICND7+\u001a;JgB\u000b\'/\u00197mK2L\'0\u00192mKB!1QBA^\'\u0011\tYL!1\u0015\u0005%UR\u0003BE\u001f\u0013\u0007\"B!c\u0010\nFA1A1EE\u0012\u0013\u0003\u0002BAa9\nD\u0011AQ1EA`\u0005\u0004\u0011I\u000f\u0003\u0005\u0004H\u0005}\u0006\u0019AE$!\u0019\u0019i!!+\nBU!\u00112JE))\u0011Ii%c\u0015\u0011\r\u0011U\u00112DE(!\u0011\u0011\u0019/#\u0015\u0005\u0011\u0015\r\u0012\u0011\u0019b\u0001\u0005SD\u0001ba\u0012\u0002B\u0002\u0007\u0011R\u000b\t\u0007\u0007\u001b\tI+c\u0014\u0016\t%e\u0013\u0012\r\u000b\u0005\u00077IY\u0006\u0003\u0005\u0004H\u0005\r\u0007\u0019AE/!\u0019\u0019i!!+\n`A!!1]E1\t!)\u0019#a1C\u0002\t%X\u0003BE3\u0013c\"B!c\u001a\nlQ!1qEE5\u0011)\u0019y#!2\u0002\u0002\u0003\u0007!\u0011\u001f\u0005\t\u0007\u000f\n)\r1\u0001\nnA11QBAU\u0013_\u0002BAa9\nr\u0011AQ1EAc\u0005\u0004\u0011I/\u0006\u0003\nv%mD\u0003BE<\u0013{\u0002ba!\u0004\u0002*&e\u0004\u0003\u0002Br\u0013w\"\u0001\"b\t\u0002H\n\u0007!\u0011\u001e\u0005\t\u0007#\t9\r1\u0001\n\u0000A1A1EE\u0012\u0013s\u00121#T1q\u0013N\u0004\u0016M]1mY\u0016d\u0017N_1cY\u0016,b!#\"\n\u0012&]5CBAe\u0005\'L9\t\u0005\u0005\u0003\\\nu\u0017\u0012REN!!\u0011\u0019-c#\n\u0010&U\u0015\u0002BEG\u0005g\u0013a\u0001V;qY\u0016\u0014\u0004\u0003\u0002Br\u0013##\u0001\"c%\u0002J\n\u0007!\u0011\u001e\u0002\u0002\u0017B!!1]EL\t!II*!3C\u0002\t%(!\u0001,\u0011\u0011\tm\u0016RTEH\u0013+KA!c(\u0003,\n1\u0001+\u0019:NCB\f\u0001j]2bY\u0006$3m\u001c7mK\u000e$\u0018n\u001c8%a\u0006\u0014\u0018\r\u001c7fY\u0012\u001au\u000e\u001c7fGRLwN\\\"p]Z,\'\u000f^3sg\u0012j\u0015\r]%t!\u0006\u0014\u0018\r\u001c7fY&T\u0018M\u00197fI\u0011\u001aw\u000e\u001c7\u0016\u0005%\u0015\u0006\u0003\u0003Bn\u0013OKy)#&\n\t%%&q\u0016\u0002\u0004\u001b\u0006\u0004\u0018!S:dC2\fGeY8mY\u0016\u001cG/[8oIA\f\'/\u00197mK2$3i\u001c7mK\u000e$\u0018n\u001c8D_:4XM\u001d;feN$S*\u00199JgB\u000b\'/\u00197mK2L\'0\u00192mK\u0012\"3m\u001c7mAQ!\u0011rVEY!!\u0019i!!3\n\u0010&U\u0005\u0002CB\t\u0003\u001f\u0004\r!#*\u0016\u0005%mE\u0003BB\u0014\u0013oC!ba\f\u0002X\u0006\u0005\t\u0019\u0001By\u0003Mi\u0015\r]%t!\u0006\u0014\u0018\r\u001c7fY&T\u0018M\u00197f!\u0011\u0019i!a7\u0014\t\u0005m\'\u0011\u0019\u000b\u0003\u0013w+b!c1\nJ&5G\u0003BEc\u0013\u001f\u0004\u0002Ba7\n(&\u001d\u00172\u001a\t\u0005\u0005GLI\r\u0002\u0005\n\u0014\u0006}\'\u0019\u0001Bu!\u0011\u0011\u0019/#4\u0005\u0011%e\u0015q\u001cb\u0001\u0005SD\u0001ba\u0012\u0002`\u0002\u0007\u0011\u0012\u001b\t\t\u0007\u001b\tI-c2\nLV1\u0011R[En\u0013?$B!c6\nbBA!1XEO\u00133Li\u000e\u0005\u0003\u0003d&mG\u0001CEJ\u0003C\u0014\rA!;\u0011\t\t\r\u0018r\u001c\u0003\t\u00133\u000b\tO1\u0001\u0003j\"A1qIAq\u0001\u0004I\u0019\u000f\u0005\u0005\u0004\u000e\u0005%\u0017\u0012\\Eo+\u0019I9/c<\ntR!11DEu\u0011!\u00199%a9A\u0002%-\b\u0003CB\u0007\u0003\u0013Li/#=\u0011\t\t\r\u0018r\u001e\u0003\t\u0013\'\u000b\u0019O1\u0001\u0003jB!!1]Ez\t!II*a9C\u0002\t%XCBE|\u0015\u0007Q9\u0001\u0006\u0003\nz&uH\u0003BB\u0014\u0013wD!ba\f\u0002f\u0006\u0005\t\u0019\u0001By\u0011!\u00199%!:A\u0002%}\b\u0003CB\u0007\u0003\u0013T\tA#\u0002\u0011\t\t\r(2\u0001\u0003\t\u0013\'\u000b)O1\u0001\u0003jB!!1\u001dF\u0004\t!II*!:C\u0002\t%XC\u0002F\u0006\u0015#Q)\u0002\u0006\u0003\u000b\u000e)]\u0001\u0003CB\u0007\u0003\u0013TyAc\u0005\u0011\t\t\r(\u0012\u0003\u0003\t\u0013\'\u000b9O1\u0001\u0003jB!!1\u001dF\u000b\t!II*a:C\u0002\t%\b\u0002CB\t\u0003O\u0004\rA#\u0007\u0011\u0011\tm\u0017r\u0015F\b\u0015\'\u0011A$S7nkR\f\'\r\\3NCBL5\u000fU1sC2dW\r\\5{C\ndW-\u0006\u0004\u000b )\u001d\"2F\n\u0007\u0003S\u0014\u0019N#\t\u0011\u0011\tm\'Q\u001cF\u0012\u0015[\u0001\u0002Ba1\n\f*\u0015\"\u0012\u0006\t\u0005\u0005GT9\u0003\u0002\u0005\n\u0014\u0006%(\u0019\u0001Bu!\u0011\u0011\u0019Oc\u000b\u0005\u0011%e\u0015\u0011\u001eb\u0001\u0005S\u0004\u0002\u0002\"\u0006\u000b0)\u0015\"\u0012F\u0005\u0005\u0013?#9\"A)tG\u0006d\u0017\rJ2pY2,7\r^5p]\u0012\u0002\u0018M]1mY\u0016dGeQ8mY\u0016\u001cG/[8o\u0007>tg/\u001a:uKJ\u001cH%S7nkR\f\'\r\\3NCBL5\u000fU1sC2dW\r\\5{C\ndW\r\n\u0013d_2dWC\u0001F\u001b!!!\u0019Cc\u000e\u000b&)%\u0012\u0002BEU\tK\t!k]2bY\u0006$3m\u001c7mK\u000e$\u0018n\u001c8%a\u0006\u0014\u0018\r\u001c7fY\u0012\u001au\u000e\u001c7fGRLwN\\\"p]Z,\'\u000f^3sg\u0012JU.\\;uC\ndW-T1q\u0013N\u0004\u0016M]1mY\u0016d\u0017N_1cY\u0016$CeY8mY\u0002\"BA#\u0010\u000b@AA1QBAu\u0015KQI\u0003\u0003\u0005\u0004\u0012\u0005=\b\u0019\u0001F\u001b+\tQi\u0003\u0006\u0003\u0004()\u0015\u0003BCB\u0018\u0003o\f\t\u00111\u0001\u0003r\u0006a\u0012*\\7vi\u0006\u0014G.Z\'ba&\u001b\b+\u0019:bY2,G.\u001b>bE2,\u0007\u0003BB\u0007\u0003w\u001cB!a?\u0003BR\u0011!\u0012J\u000b\u0007\u0015#R9Fc\u0017\u0015\t)M#R\f\t\t\tGQ9D#\u0016\u000bZA!!1\u001dF,\t!I\u0019*a@C\u0002\t%\b\u0003\u0002Br\u00157\"\u0001\"#\'\u0002\u0000\n\u0007!\u0011\u001e\u0005\t\u0007\u000f\ny\u00101\u0001\u000b`AA1QBAu\u0015+RI&\u0006\u0004\u000bd)%$R\u000e\u000b\u0005\u0015KRy\u0007\u0005\u0005\u0005\u0016)=\"r\rF6!\u0011\u0011\u0019O#\u001b\u0005\u0011%M%\u0011\u0001b\u0001\u0005S\u0004BAa9\u000bn\u0011A\u0011\u0012\u0014B\u0001\u0005\u0004\u0011I\u000f\u0003\u0005\u0004H\t\u0005\u0001\u0019\u0001F9!!\u0019i!!;\u000bh)-TC\u0002F;\u0015{R\t\t\u0006\u0003\u0004\u001c)]\u0004\u0002CB$\u0005\u0007\u0001\rA#\u001f\u0011\u0011\r5\u0011\u0011\u001eF>\u0015\u007f\u0002BAa9\u000b~\u0011A\u00112\u0013B\u0002\u0005\u0004\u0011I\u000f\u0005\u0003\u0003d*\u0005E\u0001CEM\u0005\u0007\u0011\rA!;\u0016\r)\u0015%\u0012\u0013FK)\u0011Q9Ic#\u0015\t\r\u001d\"\u0012\u0012\u0005\u000b\u0007_\u0011)!!AA\u0002\tE\b\u0002CB$\u0005\u000b\u0001\rA#$\u0011\u0011\r5\u0011\u0011\u001eFH\u0015\'\u0003BAa9\u000b\u0012\u0012A\u00112\u0013B\u0003\u0005\u0004\u0011I\u000f\u0005\u0003\u0003d*UE\u0001CEM\u0005\u000b\u0011\rA!;\u0016\r)e%r\u0014FR)\u0011QYJ#*\u0011\u0011\r5\u0011\u0011\u001eFO\u0015C\u0003BAa9\u000b \u0012A\u00112\u0013B\u0004\u0005\u0004\u0011I\u000f\u0005\u0003\u0003d*\rF\u0001CEM\u0005\u000f\u0011\rA!;\t\u0011\rE!q\u0001a\u0001\u0015O\u0003\u0002\u0002b\t\u000b8)u%\u0012\u0015\u0002\u001b\u001bV$\u0018M\u00197f\u001b\u0006\u0004\u0018j\u001d)be\u0006dG.\u001a7ju\u0006\u0014G.Z\u000b\u0007\u0015[S)L#/\u0014\r\t%!1\u001bFX!!\u0011YN!8\u000b2*m\u0006\u0003\u0003Bb\u0013\u0017S\u0019Lc.\u0011\t\t\r(R\u0017\u0003\t\u0013\'\u0013IA1\u0001\u0003jB!!1\u001dF]\t!IIJ!\u0003C\u0002\t%\b\u0003CBL\u0015{S\u0019Lc.\n\t%}5\u0011T\u0001Pg\u000e\fG.\u0019\u0013d_2dWm\u0019;j_:$\u0003/\u0019:bY2,G\u000eJ\"pY2,7\r^5p]\u000e{gN^3si\u0016\u00148\u000fJ\'vi\u0006\u0014G.Z\'ba&\u001b\b+\u0019:bY2,G.\u001b>bE2,G\u0005J2pY2,\"Ac1\u0011\u0011\r\u0015&R\u0019FZ\u0015oKA!#+\u0004(\u0006\u00016oY1mC\u0012\u001aw\u000e\u001c7fGRLwN\u001c\u0013qCJ\fG\u000e\\3mI\r{G\u000e\\3di&|gnQ8om\u0016\u0014H/\u001a:tI5+H/\u00192mK6\u000b\u0007/S:QCJ\fG\u000e\\3mSj\f\'\r\\3%I\r|G\u000e\u001c\u0011\u0015\t)-\'R\u001a\t\t\u0007\u001b\u0011IAc-\u000b8\"A1\u0011\u0003B\b\u0001\u0004Q\u0019-\u0006\u0002\u000b<R!1q\u0005Fj\u0011)\u0019yCa\u0006\u0002\u0002\u0003\u0007!\u0011_\u0001\u001b\u001bV$\u0018M\u00197f\u001b\u0006\u0004\u0018j\u001d)be\u0006dG.\u001a7ju\u0006\u0014G.\u001a\t\u0005\u0007\u001b\u0011Yb\u0005\u0003\u0003\u001c\t\u0005GC\u0001Fl+\u0019QyN#:\u000bjR!!\u0012\u001dFv!!\u0019)K#2\u000bd*\u001d\b\u0003\u0002Br\u0015K$\u0001\"c%\u0003 \t\u0007!\u0011\u001e\t\u0005\u0005GTI\u000f\u0002\u0005\n\u001a\n}!\u0019\u0001Bu\u0011!\u00199Ea\bA\u0002)5\b\u0003CB\u0007\u0005\u0013Q\u0019Oc:\u0016\r)E(r\u001fF~)\u0011Q\u0019P#@\u0011\u0011\r]%R\u0018F{\u0015s\u0004BAa9\u000bx\u0012A\u00112\u0013B\u0011\u0005\u0004\u0011I\u000f\u0005\u0003\u0003d*mH\u0001CEM\u0005C\u0011\rA!;\t\u0011\r\u001d#\u0011\u0005a\u0001\u0015\u007f\u0004\u0002b!\u0004\u0003\n)U(\u0012`\u000b\u0007\u0017\u0007YYac\u0004\u0015\t\rm1R\u0001\u0005\t\u0007\u000f\u0012\u0019\u00031\u0001\f\bAA1Q\u0002B\u0005\u0017\u0013Yi\u0001\u0005\u0003\u0003d.-A\u0001CEJ\u0005G\u0011\rA!;\u0011\t\t\r8r\u0002\u0003\t\u00133\u0013\u0019C1\u0001\u0003jV112CF\u0010\u0017G!Ba#\u0006\f\u001aQ!1qEF\f\u0011)\u0019yC!\n\u0002\u0002\u0003\u0007!\u0011\u001f\u0005\t\u0007\u000f\u0012)\u00031\u0001\f\u001cAA1Q\u0002B\u0005\u0017;Y\t\u0003\u0005\u0003\u0003d.}A\u0001CEJ\u0005K\u0011\rA!;\u0011\t\t\r82\u0005\u0003\t\u00133\u0013)C1\u0001\u0003jV11rEF\u0017\u0017c!Ba#\u000b\f4AA1Q\u0002B\u0005\u0017WYy\u0003\u0005\u0003\u0003d.5B\u0001CEJ\u0005O\u0011\rA!;\u0011\t\t\r8\u0012\u0007\u0003\t\u00133\u00139C1\u0001\u0003j\"A1\u0011\u0003B\u0014\u0001\u0004Y)\u0004\u0005\u0005\u0004&*\u001572FF\u0018\u0005\u0001JU.\\;uC\ndW\rS1tQ6\u000b\u0007/S:QCJ\fG\u000e\\3mSj\f\'\r\\3\u0016\r-m22IF$\'\u0019\u0011ICa5\f>AA!1\u001cBo\u0017\u007fYI\u0005\u0005\u0005\u0003D&-5\u0012IF#!\u0011\u0011\u0019oc\u0011\u0005\u0011%M%\u0011\u0006b\u0001\u0005S\u0004BAa9\fH\u0011A\u0011\u0012\u0014B\u0015\u0005\u0004\u0011I\u000f\u0005\u0005\u0005\u0016--3\u0012IF#\u0013\u0011Yi\u0005b\u0006\u0003\u0015A\u000b\'\u000fS1tQ6\u000b\u0007/A+tG\u0006d\u0017\rJ2pY2,7\r^5p]\u0012\u0002\u0018M]1mY\u0016dGeQ8mY\u0016\u001cG/[8o\u0007>tg/\u001a:uKJ\u001cH%S7nkR\f\'\r\\3ICNDW*\u00199JgB\u000b\'/\u00197mK2L\'0\u00192mK\u0012\"3m\u001c7m+\tY\u0019\u0006\u0005\u0005\u0005$-U3\u0012IF#\u0013\u0011Y9\u0006\"\n\u0003\u000f!\u000b7\u000f[\'ba\u000616oY1mC\u0012\u001aw\u000e\u001c7fGRLwN\u001c\u0013qCJ\fG\u000e\\3mI\r{G\u000e\\3di&|gnQ8om\u0016\u0014H/\u001a:tI%kW.\u001e;bE2,\u0007*Y:i\u001b\u0006\u0004\u0018j\u001d)be\u0006dG.\u001a7ju\u0006\u0014G.\u001a\u0013%G>dG\u000e\t\u000b\u0005\u0017;Zy\u0006\u0005\u0005\u0004\u000e\t%2\u0012IF#\u0011!\u0019\tBa\fA\u0002-MSCAF%)\u0011\u00199c#\u001a\t\u0015\r=\"qGA\u0001\u0002\u0004\u0011\t0\u0001\u0011J[6,H/\u00192mK\"\u000b7\u000f[\'ba&\u001b\b+\u0019:bY2,G.\u001b>bE2,\u0007\u0003BB\u0007\u0005w\u0019BAa\u000f\u0003BR\u00111\u0012N\u000b\u0007\u0017cZ9hc\u001f\u0015\t-M4R\u0010\t\t\tGY)f#\u001e\fzA!!1]F<\t!I\u0019Ja\u0010C\u0002\t%\b\u0003\u0002Br\u0017w\"\u0001\"#\'\u0003@\t\u0007!\u0011\u001e\u0005\t\u0007\u000f\u0012y\u00041\u0001\f\u0000AA1Q\u0002B\u0015\u0017kZI(\u0006\u0004\f\u0004.%5R\u0012\u000b\u0005\u0017\u000b[y\t\u0005\u0005\u0005\u0016--3rQFF!\u0011\u0011\u0019o##\u0005\u0011%M%\u0011\tb\u0001\u0005S\u0004BAa9\f\u000e\u0012A\u0011\u0012\u0014B!\u0005\u0004\u0011I\u000f\u0003\u0005\u0004H\t\u0005\u0003\u0019AFI!!\u0019iA!\u000b\f\b.-UCBFK\u0017;[\t\u000b\u0006\u0003\u0004\u001c-]\u0005\u0002CB$\u0005\u0007\u0002\ra#\'\u0011\u0011\r5!\u0011FFN\u0017?\u0003BAa9\f\u001e\u0012A\u00112\u0013B\"\u0005\u0004\u0011I\u000f\u0005\u0003\u0003d.\u0005F\u0001CEM\u0005\u0007\u0012\rA!;\u0016\r-\u00156\u0012WF[)\u0011Y9kc+\u0015\t\r\u001d2\u0012\u0016\u0005\u000b\u0007_\u0011)%!AA\u0002\tE\b\u0002CB$\u0005\u000b\u0002\ra#,\u0011\u0011\r5!\u0011FFX\u0017g\u0003BAa9\f2\u0012A\u00112\u0013B#\u0005\u0004\u0011I\u000f\u0005\u0003\u0003d.UF\u0001CEM\u0005\u000b\u0012\rA!;\u0016\r-e6rXFb)\u0011YYl#2\u0011\u0011\r5!\u0011FF_\u0017\u0003\u0004BAa9\f@\u0012A\u00112\u0013B$\u0005\u0004\u0011I\u000f\u0005\u0003\u0003d.\rG\u0001CEM\u0005\u000f\u0012\rA!;\t\u0011\rE!q\ta\u0001\u0017\u000f\u0004\u0002\u0002b\t\fV-u6\u0012\u0019\u0002\u001f\u001bV$\u0018M\u00197f\u0011\u0006\u001c\b.T1q\u0013N\u0004\u0016M]1mY\u0016d\u0017N_1cY\u0016,ba#4\fV.e7C\u0002B%\u0005\'\\y\r\u0005\u0005\u0003\\\nu7\u0012[Fn!!\u0011\u0019-c#\fT.]\u0007\u0003\u0002Br\u0017+$\u0001\"c%\u0003J\t\u0007!\u0011\u001e\t\u0005\u0005G\\I\u000e\u0002\u0005\n\u001a\n%#\u0019\u0001Bu!!\u00199j#8\fT.]\u0017\u0002BF\'\u00073\u000b1k]2bY\u0006$3m\u001c7mK\u000e$\u0018n\u001c8%a\u0006\u0014\u0018\r\u001c7fY\u0012\u001au\u000e\u001c7fGRLwN\\\"p]Z,\'\u000f^3sg\u0012jU\u000f^1cY\u0016D\u0015m\u001d5NCBL5\u000fU1sC2dW\r\\5{C\ndW\r\n\u0013d_2dWCAFr!!\u0019)k#:\fT.]\u0017\u0002BF,\u0007O\u000bAk]2bY\u0006$3m\u001c7mK\u000e$\u0018n\u001c8%a\u0006\u0014\u0018\r\u001c7fY\u0012\u001au\u000e\u001c7fGRLwN\\\"p]Z,\'\u000f^3sg\u0012jU\u000f^1cY\u0016D\u0015m\u001d5NCBL5\u000fU1sC2dW\r\\5{C\ndW\r\n\u0013d_2d\u0007\u0005\u0006\u0003\fl.5\b\u0003CB\u0007\u0005\u0013Z\u0019nc6\t\u0011\rE!q\na\u0001\u0017G,\"ac7\u0015\t\r\u001d22\u001f\u0005\u000b\u0007_\u00119&!AA\u0002\tE\u0018AH\'vi\u0006\u0014G.\u001a%bg\"l\u0015\r]%t!\u0006\u0014\u0018\r\u001c7fY&T\u0018M\u00197f!\u0011\u0019iAa\u0017\u0014\t\tm#\u0011\u0019\u000b\u0003\u0017o,bac@\r\u00061%A\u0003\u0002G\u0001\u0019\u0017\u0001\u0002b!*\ff2\rAr\u0001\t\u0005\u0005Gd)\u0001\u0002\u0005\n\u0014\n}#\u0019\u0001Bu!\u0011\u0011\u0019\u000f$\u0003\u0005\u0011%e%q\fb\u0001\u0005SD\u0001ba\u0012\u0003`\u0001\u0007AR\u0002\t\t\u0007\u001b\u0011I\u0005d\u0001\r\bU1A\u0012\u0003G\f\u00197!B\u0001d\u0005\r\u001eAA1qSFo\u0019+aI\u0002\u0005\u0003\u0003d2]A\u0001CEJ\u0005C\u0012\rA!;\u0011\t\t\rH2\u0004\u0003\t\u00133\u0013\tG1\u0001\u0003j\"A1q\tB1\u0001\u0004ay\u0002\u0005\u0005\u0004\u000e\t%CR\u0003G\r+\u0019a\u0019\u0003d\u000b\r0Q!11\u0004G\u0013\u0011!\u00199Ea\u0019A\u00021\u001d\u0002\u0003CB\u0007\u0005\u0013bI\u0003$\f\u0011\t\t\rH2\u0006\u0003\t\u0013\'\u0013\u0019G1\u0001\u0003jB!!1\u001dG\u0018\t!IIJa\u0019C\u0002\t%XC\u0002G\u001a\u0019\u007fa\u0019\u0005\u0006\u0003\r61eB\u0003BB\u0014\u0019oA!ba\f\u0003f\u0005\u0005\t\u0019\u0001By\u0011!\u00199E!\u001aA\u00021m\u0002\u0003CB\u0007\u0005\u0013bi\u0004$\u0011\u0011\t\t\rHr\b\u0003\t\u0013\'\u0013)G1\u0001\u0003jB!!1\u001dG\"\t!IIJ!\u001aC\u0002\t%XC\u0002G$\u0019\u001bb\t\u0006\u0006\u0003\rJ1M\u0003\u0003CB\u0007\u0005\u0013bY\u0005d\u0014\u0011\t\t\rHR\n\u0003\t\u0013\'\u00139G1\u0001\u0003jB!!1\u001dG)\t!IIJa\u001aC\u0002\t%\b\u0002CB\t\u0005O\u0002\r\u0001$\u0016\u0011\u0011\r\u00156R\u001dG&\u0019\u001f\u0012\u0011eQ8oGV\u0014(/\u001a8u)JLW-T1q\u0013N\u0004\u0016M]1mY\u0016d\u0017N_1cY\u0016,b\u0001d\u0017\rd1\u001d4C\u0002B5\u0005\'di\u0006\u0005\u0005\u0003\\\nuGr\fG5!!\u0011\u0019-c#\rb1\u0015\u0004\u0003\u0002Br\u0019G\"\u0001\"c%\u0003j\t\u0007!\u0011\u001e\t\u0005\u0005Gd9\u0007\u0002\u0005\n\u001a\n%$\u0019\u0001Bu!!\u00199\nd\u001b\rb1\u0015\u0014\u0002\u0002G7\u00073\u0013!\u0002U1s)JLW-T1q\u0003Y\u001b8-\u00197bI\r|G\u000e\\3di&|g\u000e\n9be\u0006dG.\u001a7%\u0007>dG.Z2uS>t7i\u001c8wKJ$XM]:%\u0007>t7-\u001e:sK:$HK]5f\u001b\u0006\u0004\u0018j\u001d)be\u0006dG.\u001a7ju\u0006\u0014G.\u001a\u0013%G>dG.\u0006\u0002\rtAAAR\u000fG>\u0019Cb)\'\u0004\u0002\rx)!A\u0012\u0010BX\u0003)\u0019wN\\2veJ,g\u000e^\u0005\u0005\u0019{b9HA\u0004Ue&,W*\u00199\u0002/N\u001c\u0017\r\\1%G>dG.Z2uS>tG\u0005]1sC2dW\r\u001c\u0013D_2dWm\u0019;j_:\u001cuN\u001c<feR,\'o\u001d\u0013D_:\u001cWO\u001d:f]R$&/[3NCBL5\u000fU1sC2dW\r\\5{C\ndW\r\n\u0013d_2d\u0007\u0005\u0006\u0003\r\u00042\u0015\u0005\u0003CB\u0007\u0005Sb\t\u0007$\u001a\t\u0011\rE!q\u000ea\u0001\u0019g*\"\u0001$\u001b\u0015\t\r\u001dB2\u0012\u0005\u000b\u0007_\u00119(!AA\u0002\tE\u0018!I\"p]\u000e,(O]3oiR\u0013\u0018.Z\'ba&\u001b\b+\u0019:bY2,G.\u001b>bE2,\u0007\u0003BB\u0007\u0005w\u001aBAa\u001f\u0003BR\u0011ArR\u000b\u0007\u0019/ci\n$)\u0015\t1eE2\u0015\t\t\u0019kbY\bd\'\r B!!1\u001dGO\t!I\u0019Ja C\u0002\t%\b\u0003\u0002Br\u0019C#\u0001\"#\'\u0003\u0000\t\u0007!\u0011\u001e\u0005\t\u0007\u000f\u0012y\b1\u0001\r&BA1Q\u0002B5\u00197cy*\u0006\u0004\r*2=F2\u0017\u000b\u0005\u0019Wc)\f\u0005\u0005\u0004\u00182-DR\u0016GY!\u0011\u0011\u0019\u000fd,\u0005\u0011%M%\u0011\u0011b\u0001\u0005S\u0004BAa9\r4\u0012A\u0011\u0012\u0014BA\u0005\u0004\u0011I\u000f\u0003\u0005\u0004H\t\u0005\u0005\u0019\u0001G\\!!\u0019iA!\u001b\r.2EVC\u0002G^\u0019\u0007d9\r\u0006\u0003\u0004\u001c1u\u0006\u0002CB$\u0005\u0007\u0003\r\u0001d0\u0011\u0011\r5!\u0011\u000eGa\u0019\u000b\u0004BAa9\rD\u0012A\u00112\u0013BB\u0005\u0004\u0011I\u000f\u0005\u0003\u0003d2\u001dG\u0001CEM\u0005\u0007\u0013\rA!;\u0016\r1-Gr\u001bGn)\u0011ai\r$5\u0015\t\r\u001dBr\u001a\u0005\u000b\u0007_\u0011))!AA\u0002\tE\b\u0002CB$\u0005\u000b\u0003\r\u0001d5\u0011\u0011\r5!\u0011\u000eGk\u00193\u0004BAa9\rX\u0012A\u00112\u0013BC\u0005\u0004\u0011I\u000f\u0005\u0003\u0003d2mG\u0001CEM\u0005\u000b\u0013\rA!;\u0016\r1}GR\u001dGu)\u0011a\t\u000fd;\u0011\u0011\r5!\u0011\u000eGr\u0019O\u0004BAa9\rf\u0012A\u00112\u0013BD\u0005\u0004\u0011I\u000f\u0005\u0003\u0003d2%H\u0001CEM\u0005\u000f\u0013\rA!;\t\u0011\rE!q\u0011a\u0001\u0019[\u0004\u0002\u0002$\u001e\r|1\rHr\u001d\u0002\u0016\u0003J\u0014\u0018-_%t!\u0006\u0014\u0018\r\u001c7fY&T\u0018M\u00197f+\u0011a\u0019\u0010$?\u0014\r\t%%1\u001bG{!!\u0011YN!8\rx2m\b\u0003\u0002Br\u0019s$\u0001\"b\t\u0003\n\n\u0007!\u0011\u001e\t\u0007\u0007/+9\u0003d>\u0002\u000fN\u001c\u0017\r\\1%G>dG.Z2uS>tG\u0005]1sC2dW\r\u001c\u0013D_2dWm\u0019;j_:\u001cuN\u001c<feR,\'o\u001d\u0013BeJ\f\u00170S:QCJ\fG\u000e\\3mSj\f\'\r\\3%I\u0005,\"!$\u0001\u0011\r\t\rW2\u0001G|\u0013\u0011i)Aa-\u0003\u000b\u0005\u0013(/Y=\u0002\u0011N\u001c\u0017\r\\1%G>dG.Z2uS>tG\u0005]1sC2dW\r\u001c\u0013D_2dWm\u0019;j_:\u001cuN\u001c<feR,\'o\u001d\u0013BeJ\f\u00170S:QCJ\fG\u000e\\3mSj\f\'\r\\3%I\u0005\u0004C\u0003BG\u0006\u001b\u001b\u0001ba!\u0004\u0003\n2]\b\u0002CG\b\u0005\u001f\u0003\r!$\u0001\u0002\u0003\u0005,\"!d\u0005\u0011\r\r\u0015V\u0011\u0007G|+\taY\u0010\u0006\u0003\u0004(5e\u0001BCB\u0018\u0005/\u000b\t\u00111\u0001\u0003r\u0006)\u0012I\u001d:bs&\u001b\b+\u0019:bY2,G.\u001b>bE2,\u0007\u0003BB\u0007\u00057\u001bBAa\'\u0003BR\u0011QRD\u000b\u0005\u001bKiY\u0003\u0006\u0003\u000e(55\u0002CBBS\u000bciI\u0003\u0005\u0003\u0003d6-B\u0001CC\u0012\u0005?\u0013\rA!;\t\u0011\r\u001d#q\u0014a\u0001\u001b_\u0001ba!\u0004\u0003\n6%R\u0003BG\u001a\u001bs!B!$\u000e\u000e<A11qSC\u0014\u001bo\u0001BAa9\u000e:\u0011AQ1\u0005BQ\u0005\u0004\u0011I\u000f\u0003\u0005\u0004H\t\u0005\u0006\u0019AG\u001f!\u0019\u0019iA!#\u000e8U!Q\u0012IG%)\u0011\u0019Y\"d\u0011\t\u0011\r\u001d#1\u0015a\u0001\u001b\u000b\u0002ba!\u0004\u0003\n6\u001d\u0003\u0003\u0002Br\u001b\u0013\"\u0001\"b\t\u0003$\n\u0007!\u0011^\u000b\u0005\u001b\u001bjI\u0006\u0006\u0003\u000eP5MC\u0003BB\u0014\u001b#B!ba\f\u0003&\u0006\u0005\t\u0019\u0001By\u0011!\u00199E!*A\u00025U\u0003CBB\u0007\u0005\u0013k9\u0006\u0005\u0003\u0003d6eC\u0001CC\u0012\u0005K\u0013\rA!;\u0016\t5uS2\r\u000b\u0005\u001b?j)\u0007\u0005\u0004\u0004\u000e\t%U\u0012\r\t\u0005\u0005Gl\u0019\u0007\u0002\u0005\u0006$\t\u001d&\u0019\u0001Bu\u0011!iyAa*A\u00025\u001d\u0004C\u0002Bb\u001b\u0007i\t\u0007
    #9 = Utf8               scala/collection/parallel/CollectionConverters$ArrayIsParallelizable
   #10 = Class              #9            // scala/collection/parallel/CollectionConverters$ArrayIsParallelizable
   #11 = Utf8               ArrayIsParallelizable
   #12 = Utf8               scala/collection/parallel/CollectionConverters$ArrayIsParallelizable$
   #13 = Class              #12           // scala/collection/parallel/CollectionConverters$ArrayIsParallelizable$
   #14 = Utf8               ArrayIsParallelizable$
   #15 = Utf8               scala/collection/parallel/CollectionConverters$ConcurrentTrieMapIsParallelizable
   #16 = Class              #15           // scala/collection/parallel/CollectionConverters$ConcurrentTrieMapIsParallelizable
   #17 = Utf8               ConcurrentTrieMapIsParallelizable
   #18 = Utf8               scala/collection/parallel/CollectionConverters$ConcurrentTrieMapIsParallelizable$
   #19 = Class              #18           // scala/collection/parallel/CollectionConverters$ConcurrentTrieMapIsParallelizable$
   #20 = Utf8               ConcurrentTrieMapIsParallelizable$
   #21 = Utf8               scala/collection/parallel/CollectionConverters$ImmutableHashMapIsParallelizable
   #22 = Class              #21           // scala/collection/parallel/CollectionConverters$ImmutableHashMapIsParallelizable
   #23 = Utf8               ImmutableHashMapIsParallelizable
   #24 = Utf8               scala/collection/parallel/CollectionConverters$ImmutableHashMapIsParallelizable$
   #25 = Class              #24           // scala/collection/parallel/CollectionConverters$ImmutableHashMapIsParallelizable$
   #26 = Utf8               ImmutableHashMapIsParallelizable$
   #27 = Utf8               scala/collection/parallel/CollectionConverters$ImmutableHashSetIsParallelizable
   #28 = Class              #27           // scala/collection/parallel/CollectionConverters$ImmutableHashSetIsParallelizable
   #29 = Utf8               ImmutableHashSetIsParallelizable
   #30 = Utf8               scala/collection/parallel/CollectionConverters$ImmutableHashSetIsParallelizable$
   #31 = Class              #30           // scala/collection/parallel/CollectionConverters$ImmutableHashSetIsParallelizable$
   #32 = Utf8               ImmutableHashSetIsParallelizable$
   #33 = Utf8               scala/collection/parallel/CollectionConverters$ImmutableIterableIsParallelizable
   #34 = Class              #33           // scala/collection/parallel/CollectionConverters$ImmutableIterableIsParallelizable
   #35 = Utf8               ImmutableIterableIsParallelizable
   #36 = Utf8               scala/collection/parallel/CollectionConverters$ImmutableIterableIsParallelizable$
   #37 = Class              #36           // scala/collection/parallel/CollectionConverters$ImmutableIterableIsParallelizable$
   #38 = Utf8               ImmutableIterableIsParallelizable$
   #39 = Utf8               scala/collection/parallel/CollectionConverters$ImmutableMapIsParallelizable
   #40 = Class              #39           // scala/collection/parallel/CollectionConverters$ImmutableMapIsParallelizable
   #41 = Utf8               ImmutableMapIsParallelizable
   #42 = Utf8               scala/collection/parallel/CollectionConverters$ImmutableMapIsParallelizable$
   #43 = Class              #42           // scala/collection/parallel/CollectionConverters$ImmutableMapIsParallelizable$
   #44 = Utf8               ImmutableMapIsParallelizable$
   #45 = Utf8               scala/collection/parallel/CollectionConverters$ImmutableSeqIsParallelizable
   #46 = Class              #45           // scala/collection/parallel/CollectionConverters$ImmutableSeqIsParallelizable
   #47 = Utf8               ImmutableSeqIsParallelizable
   #48 = Utf8               scala/collection/parallel/CollectionConverters$ImmutableSeqIsParallelizable$
   #49 = Class              #48           // scala/collection/parallel/CollectionConverters$ImmutableSeqIsParallelizable$
   #50 = Utf8               ImmutableSeqIsParallelizable$
   #51 = Utf8               scala/collection/parallel/CollectionConverters$ImmutableSetIsParallelizable
   #52 = Class              #51           // scala/collection/parallel/CollectionConverters$ImmutableSetIsParallelizable
   #53 = Utf8               ImmutableSetIsParallelizable
   #54 = Utf8               scala/collection/parallel/CollectionConverters$ImmutableSetIsParallelizable$
   #55 = Class              #54           // scala/collection/parallel/CollectionConverters$ImmutableSetIsParallelizable$
   #56 = Utf8               ImmutableSetIsParallelizable$
   #57 = Utf8               scala/collection/parallel/CollectionConverters$IterableIsParallelizable
   #58 = Class              #57           // scala/collection/parallel/CollectionConverters$IterableIsParallelizable
   #59 = Utf8               IterableIsParallelizable
   #60 = Utf8               scala/collection/parallel/CollectionConverters$IterableIsParallelizable$
   #61 = Class              #60           // scala/collection/parallel/CollectionConverters$IterableIsParallelizable$
   #62 = Utf8               IterableIsParallelizable$
   #63 = Utf8               scala/collection/parallel/CollectionConverters$MapIsParallelizable
   #64 = Class              #63           // scala/collection/parallel/CollectionConverters$MapIsParallelizable
   #65 = Utf8               MapIsParallelizable
   #66 = Utf8               scala/collection/parallel/CollectionConverters$MapIsParallelizable$
   #67 = Class              #66           // scala/collection/parallel/CollectionConverters$MapIsParallelizable$
   #68 = Utf8               MapIsParallelizable$
   #69 = Utf8               scala/collection/parallel/CollectionConverters$MutableArrayBufferIsParallelizable
   #70 = Class              #69           // scala/collection/parallel/CollectionConverters$MutableArrayBufferIsParallelizable
   #71 = Utf8               MutableArrayBufferIsParallelizable
   #72 = Utf8               scala/collection/parallel/CollectionConverters$MutableArrayBufferIsParallelizable$
   #73 = Class              #72           // scala/collection/parallel/CollectionConverters$MutableArrayBufferIsParallelizable$
   #74 = Utf8               MutableArrayBufferIsParallelizable$
   #75 = Utf8               scala/collection/parallel/CollectionConverters$MutableArraySeqIsParallelizable
   #76 = Class              #75           // scala/collection/parallel/CollectionConverters$MutableArraySeqIsParallelizable
   #77 = Utf8               MutableArraySeqIsParallelizable
   #78 = Utf8               scala/collection/parallel/CollectionConverters$MutableArraySeqIsParallelizable$
   #79 = Class              #78           // scala/collection/parallel/CollectionConverters$MutableArraySeqIsParallelizable$
   #80 = Utf8               MutableArraySeqIsParallelizable$
   #81 = Utf8               scala/collection/parallel/CollectionConverters$MutableHashMapIsParallelizable
   #82 = Class              #81           // scala/collection/parallel/CollectionConverters$MutableHashMapIsParallelizable
   #83 = Utf8               MutableHashMapIsParallelizable
   #84 = Utf8               scala/collection/parallel/CollectionConverters$MutableHashMapIsParallelizable$
   #85 = Class              #84           // scala/collection/parallel/CollectionConverters$MutableHashMapIsParallelizable$
   #86 = Utf8               MutableHashMapIsParallelizable$
   #87 = Utf8               scala/collection/parallel/CollectionConverters$MutableHashSetIsParallelizable
   #88 = Class              #87           // scala/collection/parallel/CollectionConverters$MutableHashSetIsParallelizable
   #89 = Utf8               MutableHashSetIsParallelizable
   #90 = Utf8               scala/collection/parallel/CollectionConverters$MutableHashSetIsParallelizable$
   #91 = Class              #90           // scala/collection/parallel/CollectionConverters$MutableHashSetIsParallelizable$
   #92 = Utf8               MutableHashSetIsParallelizable$
   #93 = Utf8               scala/collection/parallel/CollectionConverters$MutableIterableIsParallelizable
   #94 = Class              #93           // scala/collection/parallel/CollectionConverters$MutableIterableIsParallelizable
   #95 = Utf8               MutableIterableIsParallelizable
   #96 = Utf8               scala/collection/parallel/CollectionConverters$MutableIterableIsParallelizable$
   #97 = Class              #96           // scala/collection/parallel/CollectionConverters$MutableIterableIsParallelizable$
   #98 = Utf8               MutableIterableIsParallelizable$
   #99 = Utf8               scala/collection/parallel/CollectionConverters$MutableMapIsParallelizable
  #100 = Class              #99           // scala/collection/parallel/CollectionConverters$MutableMapIsParallelizable
  #101 = Utf8               MutableMapIsParallelizable
  #102 = Utf8               scala/collection/parallel/CollectionConverters$MutableMapIsParallelizable$
  #103 = Class              #102          // scala/collection/parallel/CollectionConverters$MutableMapIsParallelizable$
  #104 = Utf8               MutableMapIsParallelizable$
  #105 = Utf8               scala/collection/parallel/CollectionConverters$MutableSeqIsParallelizable
  #106 = Class              #105          // scala/collection/parallel/CollectionConverters$MutableSeqIsParallelizable
  #107 = Utf8               MutableSeqIsParallelizable
  #108 = Utf8               scala/collection/parallel/CollectionConverters$MutableSeqIsParallelizable$
  #109 = Class              #108          // scala/collection/parallel/CollectionConverters$MutableSeqIsParallelizable$
  #110 = Utf8               MutableSeqIsParallelizable$
  #111 = Utf8               scala/collection/parallel/CollectionConverters$MutableSetIsParallelizable
  #112 = Class              #111          // scala/collection/parallel/CollectionConverters$MutableSetIsParallelizable
  #113 = Utf8               MutableSetIsParallelizable
  #114 = Utf8               scala/collection/parallel/CollectionConverters$MutableSetIsParallelizable$
  #115 = Class              #114          // scala/collection/parallel/CollectionConverters$MutableSetIsParallelizable$
  #116 = Utf8               MutableSetIsParallelizable$
  #117 = Utf8               scala/collection/parallel/CollectionConverters$RangeIsParallelizable
  #118 = Class              #117          // scala/collection/parallel/CollectionConverters$RangeIsParallelizable
  #119 = Utf8               RangeIsParallelizable
  #120 = Utf8               scala/collection/parallel/CollectionConverters$RangeIsParallelizable$
  #121 = Class              #120          // scala/collection/parallel/CollectionConverters$RangeIsParallelizable$
  #122 = Utf8               RangeIsParallelizable$
  #123 = Utf8               scala/collection/parallel/CollectionConverters$SetIsParallelizable
  #124 = Class              #123          // scala/collection/parallel/CollectionConverters$SetIsParallelizable
  #125 = Utf8               SetIsParallelizable
  #126 = Utf8               scala/collection/parallel/CollectionConverters$SetIsParallelizable$
  #127 = Class              #126          // scala/collection/parallel/CollectionConverters$SetIsParallelizable$
  #128 = Utf8               SetIsParallelizable$
  #129 = Utf8               scala/collection/parallel/CollectionConverters$VectorIsParallelizable
  #130 = Class              #129          // scala/collection/parallel/CollectionConverters$VectorIsParallelizable
  #131 = Utf8               VectorIsParallelizable
  #132 = Utf8               scala/collection/parallel/CollectionConverters$VectorIsParallelizable$
  #133 = Class              #132          // scala/collection/parallel/CollectionConverters$VectorIsParallelizable$
  #134 = Utf8               VectorIsParallelizable$
  #135 = Utf8               (Ljava/lang/Object;)Ljava/lang/Object;
  #136 = Utf8               a
  #137 = Utf8               scala/collection/parallel/CollectionConverters$
  #138 = Class              #137          // scala/collection/parallel/CollectionConverters$
  #139 = Utf8               MODULE$
  #140 = Utf8               Lscala/collection/parallel/CollectionConverters$;
  #141 = NameAndType        #139:#140     // MODULE$:Lscala/collection/parallel/CollectionConverters$;
  #142 = Fieldref           #138.#141     // scala/collection/parallel/CollectionConverters$.MODULE$:Lscala/collection/parallel/CollectionConverters$;
  #143 = NameAndType        #11:#135      // ArrayIsParallelizable:(Ljava/lang/Object;)Ljava/lang/Object;
  #144 = Methodref          #138.#143     // scala/collection/parallel/CollectionConverters$.ArrayIsParallelizable:(Ljava/lang/Object;)Ljava/lang/Object;
  #145 = Utf8               Ljava/lang/Object;
  #146 = Utf8               (Lscala/collection/concurrent/TrieMap;)Lscala/collection/concurrent/TrieMap;
  #147 = Utf8               coll
  #148 = NameAndType        #17:#146      // ConcurrentTrieMapIsParallelizable:(Lscala/collection/concurrent/TrieMap;)Lscala/collection/concurrent/TrieMap;
  #149 = Methodref          #138.#148     // scala/collection/parallel/CollectionConverters$.ConcurrentTrieMapIsParallelizable:(Lscala/collection/concurrent/TrieMap;)Lscala/collection/concurrent/TrieMap;
  #150 = Utf8               Lscala/collection/concurrent/TrieMap;
  #151 = Utf8               (Lscala/collection/mutable/HashMap;)Lscala/collection/mutable/HashMap;
  #152 = NameAndType        #83:#151      // MutableHashMapIsParallelizable:(Lscala/collection/mutable/HashMap;)Lscala/collection/mutable/HashMap;
  #153 = Methodref          #138.#152     // scala/collection/parallel/CollectionConverters$.MutableHashMapIsParallelizable:(Lscala/collection/mutable/HashMap;)Lscala/collection/mutable/HashMap;
  #154 = Utf8               Lscala/collection/mutable/HashMap;
  #155 = Utf8               (Lscala/collection/immutable/HashMap;)Lscala/collection/immutable/HashMap;
  #156 = NameAndType        #23:#155      // ImmutableHashMapIsParallelizable:(Lscala/collection/immutable/HashMap;)Lscala/collection/immutable/HashMap;
  #157 = Methodref          #138.#156     // scala/collection/parallel/CollectionConverters$.ImmutableHashMapIsParallelizable:(Lscala/collection/immutable/HashMap;)Lscala/collection/immutable/HashMap;
  #158 = Utf8               Lscala/collection/immutable/HashMap;
  #159 = Utf8               (Lscala/collection/mutable/Map;)Lscala/collection/mutable/Map;
  #160 = NameAndType        #101:#159     // MutableMapIsParallelizable:(Lscala/collection/mutable/Map;)Lscala/collection/mutable/Map;
  #161 = Methodref          #138.#160     // scala/collection/parallel/CollectionConverters$.MutableMapIsParallelizable:(Lscala/collection/mutable/Map;)Lscala/collection/mutable/Map;
  #162 = Utf8               Lscala/collection/mutable/Map;
  #163 = Utf8               (Lscala/collection/immutable/Map;)Lscala/collection/immutable/Map;
  #164 = NameAndType        #41:#163      // ImmutableMapIsParallelizable:(Lscala/collection/immutable/Map;)Lscala/collection/immutable/Map;
  #165 = Methodref          #138.#164     // scala/collection/parallel/CollectionConverters$.ImmutableMapIsParallelizable:(Lscala/collection/immutable/Map;)Lscala/collection/immutable/Map;
  #166 = Utf8               Lscala/collection/immutable/Map;
  #167 = Utf8               (Lscala/collection/Map;)Lscala/collection/Map;
  #168 = NameAndType        #65:#167      // MapIsParallelizable:(Lscala/collection/Map;)Lscala/collection/Map;
  #169 = Methodref          #138.#168     // scala/collection/parallel/CollectionConverters$.MapIsParallelizable:(Lscala/collection/Map;)Lscala/collection/Map;
  #170 = Utf8               Lscala/collection/Map;
  #171 = Utf8               (Lscala/collection/immutable/HashSet;)Lscala/collection/immutable/HashSet;
  #172 = NameAndType        #29:#171      // ImmutableHashSetIsParallelizable:(Lscala/collection/immutable/HashSet;)Lscala/collection/immutable/HashSet;
  #173 = Methodref          #138.#172     // scala/collection/parallel/CollectionConverters$.ImmutableHashSetIsParallelizable:(Lscala/collection/immutable/HashSet;)Lscala/collection/immutable/HashSet;
  #174 = Utf8               Lscala/collection/immutable/HashSet;
  #175 = Utf8               (Lscala/collection/mutable/HashSet;)Lscala/collection/mutable/HashSet;
  #176 = NameAndType        #89:#175      // MutableHashSetIsParallelizable:(Lscala/collection/mutable/HashSet;)Lscala/collection/mutable/HashSet;
  #177 = Methodref          #138.#176     // scala/collection/parallel/CollectionConverters$.MutableHashSetIsParallelizable:(Lscala/collection/mutable/HashSet;)Lscala/collection/mutable/HashSet;
  #178 = Utf8               Lscala/collection/mutable/HashSet;
  #179 = Utf8               (Lscala/collection/mutable/Set;)Lscala/collection/mutable/Set;
  #180 = NameAndType        #113:#179     // MutableSetIsParallelizable:(Lscala/collection/mutable/Set;)Lscala/collection/mutable/Set;
  #181 = Methodref          #138.#180     // scala/collection/parallel/CollectionConverters$.MutableSetIsParallelizable:(Lscala/collection/mutable/Set;)Lscala/collection/mutable/Set;
  #182 = Utf8               Lscala/collection/mutable/Set;
  #183 = Utf8               (Lscala/collection/immutable/Set;)Lscala/collection/immutable/Set;
  #184 = NameAndType        #53:#183      // ImmutableSetIsParallelizable:(Lscala/collection/immutable/Set;)Lscala/collection/immutable/Set;
  #185 = Methodref          #138.#184     // scala/collection/parallel/CollectionConverters$.ImmutableSetIsParallelizable:(Lscala/collection/immutable/Set;)Lscala/collection/immutable/Set;
  #186 = Utf8               Lscala/collection/immutable/Set;
  #187 = Utf8               (Lscala/collection/Set;)Lscala/collection/Set;
  #188 = NameAndType        #125:#187     // SetIsParallelizable:(Lscala/collection/Set;)Lscala/collection/Set;
  #189 = Methodref          #138.#188     // scala/collection/parallel/CollectionConverters$.SetIsParallelizable:(Lscala/collection/Set;)Lscala/collection/Set;
  #190 = Utf8               Lscala/collection/Set;
  #191 = Utf8               (Lscala/collection/immutable/Vector;)Lscala/collection/immutable/Vector;
  #192 = NameAndType        #131:#191     // VectorIsParallelizable:(Lscala/collection/immutable/Vector;)Lscala/collection/immutable/Vector;
  #193 = Methodref          #138.#192     // scala/collection/parallel/CollectionConverters$.VectorIsParallelizable:(Lscala/collection/immutable/Vector;)Lscala/collection/immutable/Vector;
  #194 = Utf8               Lscala/collection/immutable/Vector;
  #195 = Utf8               (Lscala/collection/immutable/Range;)Lscala/collection/immutable/Range;
  #196 = NameAndType        #119:#195     // RangeIsParallelizable:(Lscala/collection/immutable/Range;)Lscala/collection/immutable/Range;
  #197 = Methodref          #138.#196     // scala/collection/parallel/CollectionConverters$.RangeIsParallelizable:(Lscala/collection/immutable/Range;)Lscala/collection/immutable/Range;
  #198 = Utf8               Lscala/collection/immutable/Range;
  #199 = Utf8               (Lscala/collection/immutable/Seq;)Lscala/collection/immutable/Seq;
  #200 = NameAndType        #47:#199      // ImmutableSeqIsParallelizable:(Lscala/collection/immutable/Seq;)Lscala/collection/immutable/Seq;
  #201 = Methodref          #138.#200     // scala/collection/parallel/CollectionConverters$.ImmutableSeqIsParallelizable:(Lscala/collection/immutable/Seq;)Lscala/collection/immutable/Seq;
  #202 = Utf8               Lscala/collection/immutable/Seq;
  #203 = Utf8               (Lscala/collection/mutable/ArrayBuffer;)Lscala/collection/mutable/ArrayBuffer;
  #204 = NameAndType        #71:#203      // MutableArrayBufferIsParallelizable:(Lscala/collection/mutable/ArrayBuffer;)Lscala/collection/mutable/ArrayBuffer;
  #205 = Methodref          #138.#204     // scala/collection/parallel/CollectionConverters$.MutableArrayBufferIsParallelizable:(Lscala/collection/mutable/ArrayBuffer;)Lscala/collection/mutable/ArrayBuffer;
  #206 = Utf8               Lscala/collection/mutable/ArrayBuffer;
  #207 = Utf8               (Lscala/collection/mutable/ArraySeq;)Lscala/collection/mutable/ArraySeq;
  #208 = NameAndType        #77:#207      // MutableArraySeqIsParallelizable:(Lscala/collection/mutable/ArraySeq;)Lscala/collection/mutable/ArraySeq;
  #209 = Methodref          #138.#208     // scala/collection/parallel/CollectionConverters$.MutableArraySeqIsParallelizable:(Lscala/collection/mutable/ArraySeq;)Lscala/collection/mutable/ArraySeq;
  #210 = Utf8               Lscala/collection/mutable/ArraySeq;
  #211 = Utf8               (Lscala/collection/mutable/Seq;)Lscala/collection/mutable/Seq;
  #212 = NameAndType        #107:#211     // MutableSeqIsParallelizable:(Lscala/collection/mutable/Seq;)Lscala/collection/mutable/Seq;
  #213 = Methodref          #138.#212     // scala/collection/parallel/CollectionConverters$.MutableSeqIsParallelizable:(Lscala/collection/mutable/Seq;)Lscala/collection/mutable/Seq;
  #214 = Utf8               Lscala/collection/mutable/Seq;
  #215 = Utf8               seqIsParallelizable
  #216 = Utf8               (Lscala/collection/Seq;)Lscala/collection/Parallelizable;
  #217 = Utf8               <A:Ljava/lang/Object;>(Lscala/collection/Seq<TA;>;)Lscala/collection/Parallelizable<TA;Lscala/collection/parallel/ParSeq<TA;>;>;
  #218 = NameAndType        #215:#216     // seqIsParallelizable:(Lscala/collection/Seq;)Lscala/collection/Parallelizable;
  #219 = Methodref          #138.#218     // scala/collection/parallel/CollectionConverters$.seqIsParallelizable:(Lscala/collection/Seq;)Lscala/collection/Parallelizable;
  #220 = Utf8               Lscala/collection/Seq;
  #221 = Utf8               (Lscala/collection/immutable/Iterable;)Lscala/collection/immutable/Iterable;
  #222 = NameAndType        #35:#221      // ImmutableIterableIsParallelizable:(Lscala/collection/immutable/Iterable;)Lscala/collection/immutable/Iterable;
  #223 = Methodref          #138.#222     // scala/collection/parallel/CollectionConverters$.ImmutableIterableIsParallelizable:(Lscala/collection/immutable/Iterable;)Lscala/collection/immutable/Iterable;
  #224 = Utf8               Lscala/collection/immutable/Iterable;
  #225 = Utf8               (Lscala/collection/mutable/Iterable;)Lscala/collection/mutable/Iterable;
  #226 = NameAndType        #95:#225      // MutableIterableIsParallelizable:(Lscala/collection/mutable/Iterable;)Lscala/collection/mutable/Iterable;
  #227 = Methodref          #138.#226     // scala/collection/parallel/CollectionConverters$.MutableIterableIsParallelizable:(Lscala/collection/mutable/Iterable;)Lscala/collection/mutable/Iterable;
  #228 = Utf8               Lscala/collection/mutable/Iterable;
  #229 = Utf8               (Lscala/collection/Iterable;)Lscala/collection/Iterable;
  #230 = NameAndType        #59:#229      // IterableIsParallelizable:(Lscala/collection/Iterable;)Lscala/collection/Iterable;
  #231 = Methodref          #138.#230     // scala/collection/parallel/CollectionConverters$.IterableIsParallelizable:(Lscala/collection/Iterable;)Lscala/collection/Iterable;
  #232 = Utf8               Lscala/collection/Iterable;
  #233 = Utf8               Code
  #234 = Utf8               LocalVariableTable
  #235 = Utf8               MethodParameters
  #236 = Utf8               Signature
  #237 = Utf8               InnerClasses
  #238 = Utf8               SourceFile
  #239 = Utf8               RuntimeVisibleAnnotations
  #240 = Utf8               ScalaSig
{
  public static java.lang.Object ArrayIsParallelizable(java.lang.Object);
    descriptor: (Ljava/lang/Object;)Ljava/lang/Object;
    flags: (0x0009) ACC_PUBLIC, ACC_STATIC
    Code:
      stack=2, locals=1, args_size=1
         0: getstatic     #142                // Field scala/collection/parallel/CollectionConverters$.MODULE$:Lscala/collection/parallel/CollectionConverters$;
         3: aload_0
         4: invokevirtual #144                // Method scala/collection/parallel/CollectionConverters$.ArrayIsParallelizable:(Ljava/lang/Object;)Ljava/lang/Object;
         7: areturn
      LocalVariableTable:
        Start  Length  Slot  Name   Signature
            0       8     0     a   Ljava/lang/Object;
    MethodParameters:
      Name                           Flags
      a                              final

  public static scala.collection.concurrent.TrieMap ConcurrentTrieMapIsParallelizable(scala.collection.concurrent.TrieMap);
    descriptor: (Lscala/collection/concurrent/TrieMap;)Lscala/collection/concurrent/TrieMap;
    flags: (0x0009) ACC_PUBLIC, ACC_STATIC
    Code:
      stack=2, locals=1, args_size=1
         0: getstatic     #142                // Field scala/collection/parallel/CollectionConverters$.MODULE$:Lscala/collection/parallel/CollectionConverters$;
         3: aload_0
         4: invokevirtual #149                // Method scala/collection/parallel/CollectionConverters$.ConcurrentTrieMapIsParallelizable:(Lscala/collection/concurrent/TrieMap;)Lscala/collection/concurrent/TrieMap;
         7: areturn
      LocalVariableTable:
        Start  Length  Slot  Name   Signature
            0       8     0  coll   Lscala/collection/concurrent/TrieMap;
    MethodParameters:
      Name                           Flags
      coll                           final

  public static scala.collection.mutable.HashMap MutableHashMapIsParallelizable(scala.collection.mutable.HashMap);
    descriptor: (Lscala/collection/mutable/HashMap;)Lscala/collection/mutable/HashMap;
    flags: (0x0009) ACC_PUBLIC, ACC_STATIC
    Code:
      stack=2, locals=1, args_size=1
         0: getstatic     #142                // Field scala/collection/parallel/CollectionConverters$.MODULE$:Lscala/collection/parallel/CollectionConverters$;
         3: aload_0
         4: invokevirtual #153                // Method scala/collection/parallel/CollectionConverters$.MutableHashMapIsParallelizable:(Lscala/collection/mutable/HashMap;)Lscala/collection/mutable/HashMap;
         7: areturn
      LocalVariableTable:
        Start  Length  Slot  Name   Signature
            0       8     0  coll   Lscala/collection/mutable/HashMap;
    MethodParameters:
      Name                           Flags
      coll                           final

  public static scala.collection.immutable.HashMap ImmutableHashMapIsParallelizable(scala.collection.immutable.HashMap);
    descriptor: (Lscala/collection/immutable/HashMap;)Lscala/collection/immutable/HashMap;
    flags: (0x0009) ACC_PUBLIC, ACC_STATIC
    Code:
      stack=2, locals=1, args_size=1
         0: getstatic     #142                // Field scala/collection/parallel/CollectionConverters$.MODULE$:Lscala/collection/parallel/CollectionConverters$;
         3: aload_0
         4: invokevirtual #157                // Method scala/collection/parallel/CollectionConverters$.ImmutableHashMapIsParallelizable:(Lscala/collection/immutable/HashMap;)Lscala/collection/immutable/HashMap;
         7: areturn
      LocalVariableTable:
        Start  Length  Slot  Name   Signature
            0       8     0  coll   Lscala/collection/immutable/HashMap;
    MethodParameters:
      Name                           Flags
      coll                           final

  public static scala.collection.mutable.Map MutableMapIsParallelizable(scala.collection.mutable.Map);
    descriptor: (Lscala/collection/mutable/Map;)Lscala/collection/mutable/Map;
    flags: (0x0009) ACC_PUBLIC, ACC_STATIC
    Code:
      stack=2, locals=1, args_size=1
         0: getstatic     #142                // Field scala/collection/parallel/CollectionConverters$.MODULE$:Lscala/collection/parallel/CollectionConverters$;
         3: aload_0
         4: invokevirtual #161                // Method scala/collection/parallel/CollectionConverters$.MutableMapIsParallelizable:(Lscala/collection/mutable/Map;)Lscala/collection/mutable/Map;
         7: areturn
      LocalVariableTable:
        Start  Length  Slot  Name   Signature
            0       8     0  coll   Lscala/collection/mutable/Map;
    MethodParameters:
      Name                           Flags
      coll                           final

  public static scala.collection.immutable.Map ImmutableMapIsParallelizable(scala.collection.immutable.Map);
    descriptor: (Lscala/collection/immutable/Map;)Lscala/collection/immutable/Map;
    flags: (0x0009) ACC_PUBLIC, ACC_STATIC
    Code:
      stack=2, locals=1, args_size=1
         0: getstatic     #142                // Field scala/collection/parallel/CollectionConverters$.MODULE$:Lscala/collection/parallel/CollectionConverters$;
         3: aload_0
         4: invokevirtual #165                // Method scala/collection/parallel/CollectionConverters$.ImmutableMapIsParallelizable:(Lscala/collection/immutable/Map;)Lscala/collection/immutable/Map;
         7: areturn
      LocalVariableTable:
        Start  Length  Slot  Name   Signature
            0       8     0  coll   Lscala/collection/immutable/Map;
    MethodParameters:
      Name                           Flags
      coll                           final

  public static scala.collection.Map MapIsParallelizable(scala.collection.Map);
    descriptor: (Lscala/collection/Map;)Lscala/collection/Map;
    flags: (0x0009) ACC_PUBLIC, ACC_STATIC
    Code:
      stack=2, locals=1, args_size=1
         0: getstatic     #142                // Field scala/collection/parallel/CollectionConverters$.MODULE$:Lscala/collection/parallel/CollectionConverters$;
         3: aload_0
         4: invokevirtual #169                // Method scala/collection/parallel/CollectionConverters$.MapIsParallelizable:(Lscala/collection/Map;)Lscala/collection/Map;
         7: areturn
      LocalVariableTable:
        Start  Length  Slot  Name   Signature
            0       8     0  coll   Lscala/collection/Map;
    MethodParameters:
      Name                           Flags
      coll                           final

  public static scala.collection.immutable.HashSet ImmutableHashSetIsParallelizable(scala.collection.immutable.HashSet);
    descriptor: (Lscala/collection/immutable/HashSet;)Lscala/collection/immutable/HashSet;
    flags: (0x0009) ACC_PUBLIC, ACC_STATIC
    Code:
      stack=2, locals=1, args_size=1
         0: getstatic     #142                // Field scala/collection/parallel/CollectionConverters$.MODULE$:Lscala/collection/parallel/CollectionConverters$;
         3: aload_0
         4: invokevirtual #173                // Method scala/collection/parallel/CollectionConverters$.ImmutableHashSetIsParallelizable:(Lscala/collection/immutable/HashSet;)Lscala/collection/immutable/HashSet;
         7: areturn
      LocalVariableTable:
        Start  Length  Slot  Name   Signature
            0       8     0  coll   Lscala/collection/immutable/HashSet;
    MethodParameters:
      Name                           Flags
      coll                           final

  public static scala.collection.mutable.HashSet MutableHashSetIsParallelizable(scala.collection.mutable.HashSet);
    descriptor: (Lscala/collection/mutable/HashSet;)Lscala/collection/mutable/HashSet;
    flags: (0x0009) ACC_PUBLIC, ACC_STATIC
    Code:
      stack=2, locals=1, args_size=1
         0: getstatic     #142                // Field scala/collection/parallel/CollectionConverters$.MODULE$:Lscala/collection/parallel/CollectionConverters$;
         3: aload_0
         4: invokevirtual #177                // Method scala/collection/parallel/CollectionConverters$.MutableHashSetIsParallelizable:(Lscala/collection/mutable/HashSet;)Lscala/collection/mutable/HashSet;
         7: areturn
      LocalVariableTable:
        Start  Length  Slot  Name   Signature
            0       8     0  coll   Lscala/collection/mutable/HashSet;
    MethodParameters:
      Name                           Flags
      coll                           final

  public static scala.collection.mutable.Set MutableSetIsParallelizable(scala.collection.mutable.Set);
    descriptor: (Lscala/collection/mutable/Set;)Lscala/collection/mutable/Set;
    flags: (0x0009) ACC_PUBLIC, ACC_STATIC
    Code:
      stack=2, locals=1, args_size=1
         0: getstatic     #142                // Field scala/collection/parallel/CollectionConverters$.MODULE$:Lscala/collection/parallel/CollectionConverters$;
         3: aload_0
         4: invokevirtual #181                // Method scala/collection/parallel/CollectionConverters$.MutableSetIsParallelizable:(Lscala/collection/mutable/Set;)Lscala/collection/mutable/Set;
         7: areturn
      LocalVariableTable:
        Start  Length  Slot  Name   Signature
            0       8     0  coll   Lscala/collection/mutable/Set;
    MethodParameters:
      Name                           Flags
      coll                           final

  public static scala.collection.immutable.Set ImmutableSetIsParallelizable(scala.collection.immutable.Set);
    descriptor: (Lscala/collection/immutable/Set;)Lscala/collection/immutable/Set;
    flags: (0x0009) ACC_PUBLIC, ACC_STATIC
    Code:
      stack=2, locals=1, args_size=1
         0: getstatic     #142                // Field scala/collection/parallel/CollectionConverters$.MODULE$:Lscala/collection/parallel/CollectionConverters$;
         3: aload_0
         4: invokevirtual #185                // Method scala/collection/parallel/CollectionConverters$.ImmutableSetIsParallelizable:(Lscala/collection/immutable/Set;)Lscala/collection/immutable/Set;
         7: areturn
      LocalVariableTable:
        Start  Length  Slot  Name   Signature
            0       8     0  coll   Lscala/collection/immutable/Set;
    MethodParameters:
      Name                           Flags
      coll                           final

  public static scala.collection.Set SetIsParallelizable(scala.collection.Set);
    descriptor: (Lscala/collection/Set;)Lscala/collection/Set;
    flags: (0x0009) ACC_PUBLIC, ACC_STATIC
    Code:
      stack=2, locals=1, args_size=1
         0: getstatic     #142                // Field scala/collection/parallel/CollectionConverters$.MODULE$:Lscala/collection/parallel/CollectionConverters$;
         3: aload_0
         4: invokevirtual #189                // Method scala/collection/parallel/CollectionConverters$.SetIsParallelizable:(Lscala/collection/Set;)Lscala/collection/Set;
         7: areturn
      LocalVariableTable:
        Start  Length  Slot  Name   Signature
            0       8     0  coll   Lscala/collection/Set;
    MethodParameters:
      Name                           Flags
      coll                           final

  public static scala.collection.immutable.Vector VectorIsParallelizable(scala.collection.immutable.Vector);
    descriptor: (Lscala/collection/immutable/Vector;)Lscala/collection/immutable/Vector;
    flags: (0x0009) ACC_PUBLIC, ACC_STATIC
    Code:
      stack=2, locals=1, args_size=1
         0: getstatic     #142                // Field scala/collection/parallel/CollectionConverters$.MODULE$:Lscala/collection/parallel/CollectionConverters$;
         3: aload_0
         4: invokevirtual #193                // Method scala/collection/parallel/CollectionConverters$.VectorIsParallelizable:(Lscala/collection/immutable/Vector;)Lscala/collection/immutable/Vector;
         7: areturn
      LocalVariableTable:
        Start  Length  Slot  Name   Signature
            0       8     0  coll   Lscala/collection/immutable/Vector;
    MethodParameters:
      Name                           Flags
      coll                           final

  public static scala.collection.immutable.Range RangeIsParallelizable(scala.collection.immutable.Range);
    descriptor: (Lscala/collection/immutable/Range;)Lscala/collection/immutable/Range;
    flags: (0x0009) ACC_PUBLIC, ACC_STATIC
    Code:
      stack=2, locals=1, args_size=1
         0: getstatic     #142                // Field scala/collection/parallel/CollectionConverters$.MODULE$:Lscala/collection/parallel/CollectionConverters$;
         3: aload_0
         4: invokevirtual #197                // Method scala/collection/parallel/CollectionConverters$.RangeIsParallelizable:(Lscala/collection/immutable/Range;)Lscala/collection/immutable/Range;
         7: areturn
      LocalVariableTable:
        Start  Length  Slot  Name   Signature
            0       8     0  coll   Lscala/collection/immutable/Range;
    MethodParameters:
      Name                           Flags
      coll                           final

  public static scala.collection.immutable.Seq ImmutableSeqIsParallelizable(scala.collection.immutable.Seq);
    descriptor: (Lscala/collection/immutable/Seq;)Lscala/collection/immutable/Seq;
    flags: (0x0009) ACC_PUBLIC, ACC_STATIC
    Code:
      stack=2, locals=1, args_size=1
         0: getstatic     #142                // Field scala/collection/parallel/CollectionConverters$.MODULE$:Lscala/collection/parallel/CollectionConverters$;
         3: aload_0
         4: invokevirtual #201                // Method scala/collection/parallel/CollectionConverters$.ImmutableSeqIsParallelizable:(Lscala/collection/immutable/Seq;)Lscala/collection/immutable/Seq;
         7: areturn
      LocalVariableTable:
        Start  Length  Slot  Name   Signature
            0       8     0  coll   Lscala/collection/immutable/Seq;
    MethodParameters:
      Name                           Flags
      coll                           final

  public static scala.collection.mutable.ArrayBuffer MutableArrayBufferIsParallelizable(scala.collection.mutable.ArrayBuffer);
    descriptor: (Lscala/collection/mutable/ArrayBuffer;)Lscala/collection/mutable/ArrayBuffer;
    flags: (0x0009) ACC_PUBLIC, ACC_STATIC
    Code:
      stack=2, locals=1, args_size=1
         0: getstatic     #142                // Field scala/collection/parallel/CollectionConverters$.MODULE$:Lscala/collection/parallel/CollectionConverters$;
         3: aload_0
         4: invokevirtual #205                // Method scala/collection/parallel/CollectionConverters$.MutableArrayBufferIsParallelizable:(Lscala/collection/mutable/ArrayBuffer;)Lscala/collection/mutable/ArrayBuffer;
         7: areturn
      LocalVariableTable:
        Start  Length  Slot  Name   Signature
            0       8     0  coll   Lscala/collection/mutable/ArrayBuffer;
    MethodParameters:
      Name                           Flags
      coll                           final

  public static scala.collection.mutable.ArraySeq MutableArraySeqIsParallelizable(scala.collection.mutable.ArraySeq);
    descriptor: (Lscala/collection/mutable/ArraySeq;)Lscala/collection/mutable/ArraySeq;
    flags: (0x0009) ACC_PUBLIC, ACC_STATIC
    Code:
      stack=2, locals=1, args_size=1
         0: getstatic     #142                // Field scala/collection/parallel/CollectionConverters$.MODULE$:Lscala/collection/parallel/CollectionConverters$;
         3: aload_0
         4: invokevirtual #209                // Method scala/collection/parallel/CollectionConverters$.MutableArraySeqIsParallelizable:(Lscala/collection/mutable/ArraySeq;)Lscala/collection/mutable/ArraySeq;
         7: areturn
      LocalVariableTable:
        Start  Length  Slot  Name   Signature
            0       8     0  coll   Lscala/collection/mutable/ArraySeq;
    MethodParameters:
      Name                           Flags
      coll                           final

  public static scala.collection.mutable.Seq MutableSeqIsParallelizable(scala.collection.mutable.Seq);
    descriptor: (Lscala/collection/mutable/Seq;)Lscala/collection/mutable/Seq;
    flags: (0x0009) ACC_PUBLIC, ACC_STATIC
    Code:
      stack=2, locals=1, args_size=1
         0: getstatic     #142                // Field scala/collection/parallel/CollectionConverters$.MODULE$:Lscala/collection/parallel/CollectionConverters$;
         3: aload_0
         4: invokevirtual #213                // Method scala/collection/parallel/CollectionConverters$.MutableSeqIsParallelizable:(Lscala/collection/mutable/Seq;)Lscala/collection/mutable/Seq;
         7: areturn
      LocalVariableTable:
        Start  Length  Slot  Name   Signature
            0       8     0  coll   Lscala/collection/mutable/Seq;
    MethodParameters:
      Name                           Flags
      coll                           final

  public static <A extends java.lang.Object> scala.collection.Parallelizable<A, scala.collection.parallel.ParSeq<A>> seqIsParallelizable(scala.collection.Seq<A>);
    descriptor: (Lscala/collection/Seq;)Lscala/collection/Parallelizable;
    flags: (0x0009) ACC_PUBLIC, ACC_STATIC
    Code:
      stack=2, locals=1, args_size=1
         0: getstatic     #142                // Field scala/collection/parallel/CollectionConverters$.MODULE$:Lscala/collection/parallel/CollectionConverters$;
         3: aload_0
         4: invokevirtual #219                // Method scala/collection/parallel/CollectionConverters$.seqIsParallelizable:(Lscala/collection/Seq;)Lscala/collection/Parallelizable;
         7: areturn
      LocalVariableTable:
        Start  Length  Slot  Name   Signature
            0       8     0  coll   Lscala/collection/Seq;
    Signature: #217                         // <A:Ljava/lang/Object;>(Lscala/collection/Seq<TA;>;)Lscala/collection/Parallelizable<TA;Lscala/collection/parallel/ParSeq<TA;>;>;
    MethodParameters:
      Name                           Flags
      coll                           final

  public static scala.collection.immutable.Iterable ImmutableIterableIsParallelizable(scala.collection.immutable.Iterable);
    descriptor: (Lscala/collection/immutable/Iterable;)Lscala/collection/immutable/Iterable;
    flags: (0x0009) ACC_PUBLIC, ACC_STATIC
    Code:
      stack=2, locals=1, args_size=1
         0: getstatic     #142                // Field scala/collection/parallel/CollectionConverters$.MODULE$:Lscala/collection/parallel/CollectionConverters$;
         3: aload_0
         4: invokevirtual #223                // Method scala/collection/parallel/CollectionConverters$.ImmutableIterableIsParallelizable:(Lscala/collection/immutable/Iterable;)Lscala/collection/immutable/Iterable;
         7: areturn
      LocalVariableTable:
        Start  Length  Slot  Name   Signature
            0       8     0  coll   Lscala/collection/immutable/Iterable;
    MethodParameters:
      Name                           Flags
      coll                           final

  public static scala.collection.mutable.Iterable MutableIterableIsParallelizable(scala.collection.mutable.Iterable);
    descriptor: (Lscala/collection/mutable/Iterable;)Lscala/collection/mutable/Iterable;
    flags: (0x0009) ACC_PUBLIC, ACC_STATIC
    Code:
      stack=2, locals=1, args_size=1
         0: getstatic     #142                // Field scala/collection/parallel/CollectionConverters$.MODULE$:Lscala/collection/parallel/CollectionConverters$;
         3: aload_0
         4: invokevirtual #227                // Method scala/collection/parallel/CollectionConverters$.MutableIterableIsParallelizable:(Lscala/collection/mutable/Iterable;)Lscala/collection/mutable/Iterable;
         7: areturn
      LocalVariableTable:
        Start  Length  Slot  Name   Signature
            0       8     0  coll   Lscala/collection/mutable/Iterable;
    MethodParameters:
      Name                           Flags
      coll                           final

  public static scala.collection.Iterable IterableIsParallelizable(scala.collection.Iterable);
    descriptor: (Lscala/collection/Iterable;)Lscala/collection/Iterable;
    flags: (0x0009) ACC_PUBLIC, ACC_STATIC
    Code:
      stack=2, locals=1, args_size=1
         0: getstatic     #142                // Field scala/collection/parallel/CollectionConverters$.MODULE$:Lscala/collection/parallel/CollectionConverters$;
         3: aload_0
         4: invokevirtual #231                // Method scala/collection/parallel/CollectionConverters$.IterableIsParallelizable:(Lscala/collection/Iterable;)Lscala/collection/Iterable;
         7: areturn
      LocalVariableTable:
        Start  Length  Slot  Name   Signature
            0       8     0  coll   Lscala/collection/Iterable;
    MethodParameters:
      Name                           Flags
      coll                           final
}
InnerClasses:
  public static final #11= #10 of #2;     // ArrayIsParallelizable=class scala/collection/parallel/CollectionConverters$ArrayIsParallelizable of class scala/collection/parallel/CollectionConverters
  public static #14= #13 of #2;           // ArrayIsParallelizable$=class scala/collection/parallel/CollectionConverters$ArrayIsParallelizable$ of class scala/collection/parallel/CollectionConverters
  public static final #17= #16 of #2;     // ConcurrentTrieMapIsParallelizable=class scala/collection/parallel/CollectionConverters$ConcurrentTrieMapIsParallelizable of class scala/collection/parallel/CollectionConverters
  public static #20= #19 of #2;           // ConcurrentTrieMapIsParallelizable$=class scala/collection/parallel/CollectionConverters$ConcurrentTrieMapIsParallelizable$ of class scala/collection/parallel/CollectionConverters
  public static final #23= #22 of #2;     // ImmutableHashMapIsParallelizable=class scala/collection/parallel/CollectionConverters$ImmutableHashMapIsParallelizable of class scala/collection/parallel/CollectionConverters
  public static #26= #25 of #2;           // ImmutableHashMapIsParallelizable$=class scala/collection/parallel/CollectionConverters$ImmutableHashMapIsParallelizable$ of class scala/collection/parallel/CollectionConverters
  public static final #29= #28 of #2;     // ImmutableHashSetIsParallelizable=class scala/collection/parallel/CollectionConverters$ImmutableHashSetIsParallelizable of class scala/collection/parallel/CollectionConverters
  public static #32= #31 of #2;           // ImmutableHashSetIsParallelizable$=class scala/collection/parallel/CollectionConverters$ImmutableHashSetIsParallelizable$ of class scala/collection/parallel/CollectionConverters
  public static final #35= #34 of #2;     // ImmutableIterableIsParallelizable=class scala/collection/parallel/CollectionConverters$ImmutableIterableIsParallelizable of class scala/collection/parallel/CollectionConverters
  public static #38= #37 of #2;           // ImmutableIterableIsParallelizable$=class scala/collection/parallel/CollectionConverters$ImmutableIterableIsParallelizable$ of class scala/collection/parallel/CollectionConverters
  public static final #41= #40 of #2;     // ImmutableMapIsParallelizable=class scala/collection/parallel/CollectionConverters$ImmutableMapIsParallelizable of class scala/collection/parallel/CollectionConverters
  public static #44= #43 of #2;           // ImmutableMapIsParallelizable$=class scala/collection/parallel/CollectionConverters$ImmutableMapIsParallelizable$ of class scala/collection/parallel/CollectionConverters
  public static final #47= #46 of #2;     // ImmutableSeqIsParallelizable=class scala/collection/parallel/CollectionConverters$ImmutableSeqIsParallelizable of class scala/collection/parallel/CollectionConverters
  public static #50= #49 of #2;           // ImmutableSeqIsParallelizable$=class scala/collection/parallel/CollectionConverters$ImmutableSeqIsParallelizable$ of class scala/collection/parallel/CollectionConverters
  public static final #53= #52 of #2;     // ImmutableSetIsParallelizable=class scala/collection/parallel/CollectionConverters$ImmutableSetIsParallelizable of class scala/collection/parallel/CollectionConverters
  public static #56= #55 of #2;           // ImmutableSetIsParallelizable$=class scala/collection/parallel/CollectionConverters$ImmutableSetIsParallelizable$ of class scala/collection/parallel/CollectionConverters
  public static final #59= #58 of #2;     // IterableIsParallelizable=class scala/collection/parallel/CollectionConverters$IterableIsParallelizable of class scala/collection/parallel/CollectionConverters
  public static #62= #61 of #2;           // IterableIsParallelizable$=class scala/collection/parallel/CollectionConverters$IterableIsParallelizable$ of class scala/collection/parallel/CollectionConverters
  public static final #65= #64 of #2;     // MapIsParallelizable=class scala/collection/parallel/CollectionConverters$MapIsParallelizable of class scala/collection/parallel/CollectionConverters
  public static #68= #67 of #2;           // MapIsParallelizable$=class scala/collection/parallel/CollectionConverters$MapIsParallelizable$ of class scala/collection/parallel/CollectionConverters
  public static final #71= #70 of #2;     // MutableArrayBufferIsParallelizable=class scala/collection/parallel/CollectionConverters$MutableArrayBufferIsParallelizable of class scala/collection/parallel/CollectionConverters
  public static #74= #73 of #2;           // MutableArrayBufferIsParallelizable$=class scala/collection/parallel/CollectionConverters$MutableArrayBufferIsParallelizable$ of class scala/collection/parallel/CollectionConverters
  public static final #77= #76 of #2;     // MutableArraySeqIsParallelizable=class scala/collection/parallel/CollectionConverters$MutableArraySeqIsParallelizable of class scala/collection/parallel/CollectionConverters
  public static #80= #79 of #2;           // MutableArraySeqIsParallelizable$=class scala/collection/parallel/CollectionConverters$MutableArraySeqIsParallelizable$ of class scala/collection/parallel/CollectionConverters
  public static final #83= #82 of #2;     // MutableHashMapIsParallelizable=class scala/collection/parallel/CollectionConverters$MutableHashMapIsParallelizable of class scala/collection/parallel/CollectionConverters
  public static #86= #85 of #2;           // MutableHashMapIsParallelizable$=class scala/collection/parallel/CollectionConverters$MutableHashMapIsParallelizable$ of class scala/collection/parallel/CollectionConverters
  public static final #89= #88 of #2;     // MutableHashSetIsParallelizable=class scala/collection/parallel/CollectionConverters$MutableHashSetIsParallelizable of class scala/collection/parallel/CollectionConverters
  public static #92= #91 of #2;           // MutableHashSetIsParallelizable$=class scala/collection/parallel/CollectionConverters$MutableHashSetIsParallelizable$ of class scala/collection/parallel/CollectionConverters
  public static final #95= #94 of #2;     // MutableIterableIsParallelizable=class scala/collection/parallel/CollectionConverters$MutableIterableIsParallelizable of class scala/collection/parallel/CollectionConverters
  public static #98= #97 of #2;           // MutableIterableIsParallelizable$=class scala/collection/parallel/CollectionConverters$MutableIterableIsParallelizable$ of class scala/collection/parallel/CollectionConverters
  public static final #101= #100 of #2;   // MutableMapIsParallelizable=class scala/collection/parallel/CollectionConverters$MutableMapIsParallelizable of class scala/collection/parallel/CollectionConverters
  public static #104= #103 of #2;         // MutableMapIsParallelizable$=class scala/collection/parallel/CollectionConverters$MutableMapIsParallelizable$ of class scala/collection/parallel/CollectionConverters
  public static final #107= #106 of #2;   // MutableSeqIsParallelizable=class scala/collection/parallel/CollectionConverters$MutableSeqIsParallelizable of class scala/collection/parallel/CollectionConverters
  public static #110= #109 of #2;         // MutableSeqIsParallelizable$=class scala/collection/parallel/CollectionConverters$MutableSeqIsParallelizable$ of class scala/collection/parallel/CollectionConverters
  public static final #113= #112 of #2;   // MutableSetIsParallelizable=class scala/collection/parallel/CollectionConverters$MutableSetIsParallelizable of class scala/collection/parallel/CollectionConverters
  public static #116= #115 of #2;         // MutableSetIsParallelizable$=class scala/collection/parallel/CollectionConverters$MutableSetIsParallelizable$ of class scala/collection/parallel/CollectionConverters
  public static final #119= #118 of #2;   // RangeIsParallelizable=class scala/collection/parallel/CollectionConverters$RangeIsParallelizable of class scala/collection/parallel/CollectionConverters
  public static #122= #121 of #2;         // RangeIsParallelizable$=class scala/collection/parallel/CollectionConverters$RangeIsParallelizable$ of class scala/collection/parallel/CollectionConverters
  public static final #125= #124 of #2;   // SetIsParallelizable=class scala/collection/parallel/CollectionConverters$SetIsParallelizable of class scala/collection/parallel/CollectionConverters
  public static #128= #127 of #2;         // SetIsParallelizable$=class scala/collection/parallel/CollectionConverters$SetIsParallelizable$ of class scala/collection/parallel/CollectionConverters
  public static final #131= #130 of #2;   // VectorIsParallelizable=class scala/collection/parallel/CollectionConverters$VectorIsParallelizable of class scala/collection/parallel/CollectionConverters
  public static #134= #133 of #2;         // VectorIsParallelizable$=class scala/collection/parallel/CollectionConverters$VectorIsParallelizable$ of class scala/collection/parallel/CollectionConverters
SourceFile: "CollectionConverters.scala"
RuntimeVisibleAnnotations:
  0: #6(#7=s#8)
    scala.reflect.ScalaSignature(
      bytes="\u0006\u00055%t\u0001\u0003BU\u0005WC\tA!/\u0007\u0011\tu&1\u0016E\u0001\u0005\u007fCqA!3\u0002\t\u0003\u0011YM\u0002\u0004\u0003N\u0006\u0019!q\u001a\u0005\u000f\u0005{\u001cA\u0011!A\u0003\u0006\u000b\u0007I\u0011\u0002B\u0000\u0011-\u00199a\u0001B\u0003\u0002\u0003\u0006Ia!\u0001\t\u000f\t%7\u0001\"\u0001\u0004\n!911C\u0002\u0005\u0002\t}\bbBB\u000b\u0007\u0011\u00053q\u0003\u0005\n\u00073\u0019\u0011\u0011!C!\u00077A\u0011ba\t\u0004\u0003\u0003%\te!\n\b\u0013\rE\u0012!!A\t\u0002\rMb!\u0003Bg\u0003\u0005\u0005\t\u0012AB\u001b\u0011\u001d\u0011I\r\u0004C\u0001\u0007oAqa!\u000f\r\t\u000b\u0019Y\u0004C\u0004\u0004L1!)a!\u0014\t\u0013\rmC\"!A\u0005\u0006\ru\u0003\"CB5\u0019\u0005\u0005IQAB6\u0011%\u0019\t$AA\u0001\n\u0007\u0019YH\u0002\u0004\u0004\n\u0006\u001911\u0012\u0005\u000f\u0007?\u001bB\u0011!A\u0003\u0006\u000b\u0007I\u0011BBQ\u0011-\u0019Yk\u0005B\u0003\u0002\u0003\u0006Iaa)\t\u000f\t%7\u0003\"\u0001\u0004.\"911C\n\u0005\u0002\r\u0005\u0006bBB\u000b\'\u0011\u000531\u0017\u0005\n\u00073\u0019\u0012\u0011!C!\u00077A\u0011ba\t\u0014\u0003\u0003%\te!.\b\u0013\re\u0016!!A\t\u0002\rmf!CBE\u0003\u0005\u0005\t\u0012AB_\u0011\u001d\u0011I\r\bC\u0001\u0007\u007fCqa!\u000f\u001d\t\u000b\u0019\t\rC\u0004\u0004Lq!)aa4\t\u0013\rmC$!A\u0005\u0006\ru\u0007\"CB59\u0005\u0005IQABu\u0011%\u0019I,AA\u0001\n\u0007\u0019IP\u0002\u0004\u0005\b\u0005\u0019A\u0011\u0002\u0005\u000f\t;\u0019C\u0011!A\u0003\u0006\u000b\u0007I\u0011\u0002C\u0010\u0011-!Ic\tB\u0003\u0002\u0003\u0006I\u0001\"\t\t\u000f\t%7\u0005\"\u0001\u0005,!911C\u0012\u0005\u0002\u0011}\u0001bBB\u000bG\u0011\u0005C\u0011\u0007\u0005\n\u00073\u0019\u0013\u0011!C!\u00077A\u0011ba\t$\u0003\u0003%\t\u0005b\r\b\u0013\u0011]\u0012!!A\t\u0002\u0011eb!\u0003C\u0004\u0003\u0005\u0005\t\u0012\u0001C\u001e\u0011\u001d\u0011I\r\fC\u0001\t{Aqa!\u000f-\t\u000b!y\u0004C\u0004\u0004L1\")\u0001\"\u0014\t\u0013\rmC&!A\u0005\u0006\u0011m\u0003\"CB5Y\u0005\u0005IQ\u0001C4\u0011%!9$AA\u0001\n\u0007!9\bC\u0004\u0005\u0006\u0006!\u0019\u0001b\"\u0007\r\u0011\r\u0016a\u0001CS\u00119!\u0019\f\u000eC\u0001\u0002\u000b\u0015)\u0019!C\u0005\tkC1\u0002b/5\u0005\u000b\u0005\t\u0015!\u0003\u00058\"9!\u0011\u001a\u001b\u0005\u0002\u0011u\u0006bBB\ni\u0011\u0005AQ\u0017\u0005\b\u0007+!D\u0011\tCb\u0011%\u0019I\u0002NA\u0001\n\u0003\u001aY\u0002C\u0005\u0004$Q\n\t\u0011\"\u0011\u0005F\u001eIA\u0011Z\u0001\u0002\u0002#\u0005A1\u001a\u0004\n\tG\u000b\u0011\u0011!E\u0001\t\u001bDqA!3>\t\u0003!y\rC\u0004\u0004:u\")\u0001\"5\t\u000f\r-S\b\"\u0002\u0005`\"I11L\u001f\u0002\u0002\u0013\u0015AQ\u001e\u0005\n\u0007Sj\u0014\u0011!C\u0003\tsD\u0011\u0002\"3\u0002\u0003\u0003%\u0019!\"\u0003\u0007\r\u0015]\u0011aAC\r\u00119)Y\u0003\u0012C\u0001\u0002\u000b\u0015)\u0019!C\u0005\u000b[A1\"\"\u000eE\u0005\u000b\u0005\t\u0015!\u0003\u00060!9!\u0011\u001a#\u0005\u0002\u0015]\u0002bBB\n\t\u0012\u0005QQ\u0006\u0005\b\u0007+!E\u0011IC\u001f\u0011%\u0019I\u0002RA\u0001\n\u0003\u001aY\u0002C\u0005\u0004$\u0011\u000b\t\u0011\"\u0011\u0006@\u001dIQ1I\u0001\u0002\u0002#\u0005QQ\t\u0004\n\u000b/\t\u0011\u0011!E\u0001\u000b\u000fBqA!3N\t\u0003)I\u0005C\u0004\u0004:5#)!b\u0013\t\u000f\r-S\n\"\u0002\u0006Z!I11L\'\u0002\u0002\u0013\u0015Qq\r\u0005\n\u0007Sj\u0015\u0011!C\u0003\u000bgB\u0011\"b\u0011\u0002\u0003\u0003%\u0019!b!\u0007\r\u0015E\u0015aACJ\u00119)y\n\u0016C\u0001\u0002\u000b\u0015)\u0019!C\u0005\u000bCC1\"\"+U\u0005\u000b\u0005\t\u0015!\u0003\u0006$\"9!\u0011\u001a+\u0005\u0002\u0015-\u0006bBB\n)\u0012\u0005Q\u0011\u0015\u0005\b\u0007+!F\u0011ICY\u0011%\u0019I\u0002VA\u0001\n\u0003\u001aY\u0002C\u0005\u0004$Q\u000b\t\u0011\"\u0011\u00064\u001eIQqW\u0001\u0002\u0002#\u0005Q\u0011\u0018\u0004\n\u000b#\u000b\u0011\u0011!E\u0001\u000bwCqA!3^\t\u0003)i\fC\u0004\u0004:u#)!b0\t\u000f\r-S\f\"\u0002\u0006N\"I11L/\u0002\u0002\u0013\u0015Q1\u001c\u0005\n\u0007Sj\u0016\u0011!C\u0003\u000bOD\u0011\"b.\u0002\u0003\u0003%\u0019!b>\u0007\r\u0019\u0015\u0011a\u0001D\u0004\u001191)\u0002\u001aC\u0001\u0002\u000b\u0015)\u0019!C\u0005\r/A1B\"\be\u0005\u000b\u0005\t\u0015!\u0003\u0007\u001a!9!\u0011\u001a3\u0005\u0002\u0019}\u0001bBB\nI\u0012\u0005aq\u0003\u0005\b\u0007+!G\u0011\tD\u0013\u0011%\u0019I\u0002ZA\u0001\n\u0003\u001aY\u0002C\u0005\u0004$\u0011\f\t\u0011\"\u0011\u0007(\u001dIa1F\u0001\u0002\u0002#\u0005aQ\u0006\u0004\n\r\u000b\t\u0011\u0011!E\u0001\r_AqA!3n\t\u00031\t\u0004C\u0004\u0004:5$)Ab\r\t\u000f\r-S\u000e\"\u0002\u0007B!I11L7\u0002\u0002\u0013\u0015aq\n\u0005\n\u0007Sj\u0017\u0011!C\u0003\r7B\u0011Bb\u000b\u0002\u0003\u0003%\u0019Ab\u001b\u0007\r\u0019e\u0014a\u0001D>\u001191)\t\u001eC\u0001\u0002\u000b\u0015)\u0019!C\u0005\r\u000fC1Bb$u\u0005\u000b\u0005\t\u0015!\u0003\u0007\n\"9!\u0011\u001a;\u0005\u0002\u0019E\u0005bBB\ni\u0012\u0005aq\u0011\u0005\b\u0007+!H\u0011\tDL\u0011%\u0019I\u0002^A\u0001\n\u0003\u001aY\u0002C\u0005\u0004$Q\f\t\u0011\"\u0011\u0007\u001a\u001eIaQT\u0001\u0002\u0002#\u0005aq\u0014\u0004\n\rs\n\u0011\u0011!E\u0001\rCCqA!3~\t\u00031\u0019\u000bC\u0004\u0004:u$)A\"*\t\u000f\r-S\u0010\"\u0002\u0007*\"I11L?\u0002\u0002\u0013\u0015aQ\u0016\u0005\n\u0007Sj\u0018\u0011!C\u0003\rcC\u0011B\"(\u0002\u0003\u0003%\u0019A\"/\u0007\r\u0019u\u0016a\u0001D`\u0011=1y-!\u0003\u0005\u0002\u0003\u0015)Q1A\u0005\n\u0019E\u0007\u0002\u0004Dm\u0003\u0013\u0011)\u0011!Q\u0001\n\u0019M\u0007\u0002\u0003Be\u0003\u0013!\tAb7\t\u0011\rM\u0011\u0011\u0002C\u0001\r#D\u0001b!\u0006\u0002\n\u0011\u0005c\u0011\u001d\u0005\u000b\u00073\tI!!A\u0005B\rm\u0001BCB\u0012\u0003\u0013\t\t\u0011\"\u0011\u0007d\u001eIaq]\u0001\u0002\u0002#\u0005a\u0011\u001e\u0004\n\r{\u000b\u0011\u0011!E\u0001\rWD\u0001B!3\u0002\u001c\u0011\u0005aQ\u001e\u0005\t\u0007s\tY\u0002\"\u0002\u0007p\"A11JA\u000e\t\u000b1i\u0010\u0003\u0006\u0004\\\u0005m\u0011\u0011!C\u0003\u000f\u0017A!b!\u001b\u0002\u001c\u0005\u0005IQAD\f\u0011%19/AA\u0001\n\u000799C\u0002\u0004\b6\u0005\u0019qq\u0007\u0005\u0010\u000f\u000f\nI\u0003\"A\u0001\u0006\u000b\u0015\r\u0011\"\u0003\bJ!aq\u0011KA\u0015\u0005\u000b\u0005\t\u0015!\u0003\bL!A!\u0011ZA\u0015\t\u00039\u0019\u0006\u0003\u0005\u0004\u0014\u0005%B\u0011AD%\u0011!\u0019)\"!\u000b\u0005B\u001de\u0003BCB\r\u0003S\t\t\u0011\"\u0011\u0004\u001c!Q11EA\u0015\u0003\u0003%\teb\u0017\b\u0013\u001d}\u0013!!A\t\u0002\u001d\u0005d!CD\u001b\u0003\u0005\u0005\t\u0012AD2\u0011!\u0011I-a\u000f\u0005\u0002\u001d\u0015\u0004\u0002CB\u001d\u0003w!)ab\u001a\t\u0011\r-\u00131\bC\u0003\u000fkB!ba\u0017\u0002<\u0005\u0005IQADB\u0011)\u0019I\'a\u000f\u0002\u0002\u0013\u0015qq\u0012\u0005\n\u000f?\n\u0011\u0011!C\u0002\u000f?3aa\",\u0002\u0007\u001d=\u0006bDD_\u0003\u0013\"\t\u0011!B\u0003\u0006\u0004%Iab0\t\u0019\u001d\u0015\u0017\u0011\nB\u0003\u0002\u0003\u0006Ia\"1\t\u0011\t%\u0017\u0011\nC\u0001\u000f\u000fD\u0001ba\u0005\u0002J\u0011\u0005qq\u0018\u0005\t\u0007+\tI\u0005\"\u0011\bN\"Q1\u0011DA%\u0003\u0003%\tea\u0007\t\u0015\r\r\u0012\u0011JA\u0001\n\u0003:ymB\u0005\bT\u0006\t\t\u0011#\u0001\bV\u001aIqQV\u0001\u0002\u0002#\u0005qq\u001b\u0005\t\u0005\u0013\fY\u0006\"\u0001\bZ\"A1\u0011HA.\t\u000b9Y\u000e\u0003\u0005\u0004L\u0005mCQADu\u0011)\u0019Y&a\u0017\u0002\u0002\u0013\u0015qq\u001f\u0005\u000b\u0007S\nY&!A\u0005\u0006!\r\u0001\"CDj\u0003\u0005\u0005I1\u0001E\n\r\u0019A\t#A\u0002\t$!y\u0001\u0012GA5\t\u0003\u0005)Q!b\u0001\n\u0013A\u0019\u0004\u0003\u0007\t:\u0005%$Q!A!\u0002\u0013A)\u0004\u0003\u0005\u0003J\u0006%D\u0011\u0001E\u001e\u0011!\u0019\u0019\"!\u001b\u0005\u0002!M\u0002\u0002CB\u000b\u0003S\"\t\u0005#\u0011\t\u0015\re\u0011\u0011NA\u0001\n\u0003\u001aY\u0002\u0003\u0006\u0004$\u0005%\u0014\u0011!C!\u0011\u0007:\u0011\u0002c\u0012\u0002\u0003\u0003E\t\u0001#\u0013\u0007\u0013!\u0005\u0012!!A\t\u0002!-\u0003\u0002\u0003Be\u0003w\"\t\u0001#\u0014\t\u0011\re\u00121\u0010C\u0003\u0011\u001fB\u0001ba\u0013\u0002|\u0011\u0015\u0001R\f\u0005\u000b\u00077\nY(!A\u0005\u0006!-\u0004BCB5\u0003w\n\t\u0011\"\u0002\tx!I\u0001rI\u0001\u0002\u0002\u0013\r\u0001r\u0011\u0004\u0007\u0011+\u000b1\u0001c&\t\u001f!\u001d\u0016\u0011\u0012C\u0001\u0002\u000b\u0015)\u0019!C\u0005\u0011SCA\u0002#-\u0002\n\n\u0015\t\u0011)A\u0005\u0011WC\u0001B!3\u0002\n\u0012\u0005\u00012\u0017\u0005\t\u0007\'\tI\t\"\u0001\t*\"A1QCAE\t\u0003BI\f\u0003\u0006\u0004\u001a\u0005%\u0015\u0011!C!\u00077A!ba\t\u0002\n\u0006\u0005I\u0011\tE^\u000f%Ay,AA\u0001\u0012\u0003A\tMB\u0005\t\u0016\u0006\t\t\u0011#\u0001\tD\"A!\u0011ZAN\t\u0003A)\r\u0003\u0005\u0004:\u0005mEQ\u0001Ed\u0011!\u0019Y%a\'\u0005\u0006!U\u0007BCB.\u00037\u000b\t\u0011\"\u0002\td\"Q1\u0011NAN\u0003\u0003%)\u0001c<\t\u0013!}\u0016!!A\u0005\u0004!}hABE\u0007\u0003\rIy\u0001C\b\n\u001e\u0005%F\u0011!A\u0003\u0006\u000b\u0007I\u0011BE\u0010\u00111I)#!+\u0003\u0006\u0003\u0005\u000b\u0011BE\u0011\u0011!\u0011I-!+\u0005\u0002%\u001d\u0002\u0002CB\n\u0003S#\t!c\b\t\u0011\rU\u0011\u0011\u0016C!\u0013[A!b!\u0007\u0002*\u0006\u0005I\u0011IB\u000e\u0011)\u0019\u0019#!+\u0002\u0002\u0013\u0005\u0013rF\u0004\n\u0013g\t\u0011\u0011!E\u0001\u0013k1\u0011\"#\u0004\u0002\u0003\u0003E\t!c\u000e\t\u0011\t%\u00171\u0018C\u0001\u0013sA\u0001b!\u000f\u0002<\u0012\u0015\u00112\b\u0005\t\u0007\u0017\nY\f\"\u0002\nJ!Q11LA^\u0003\u0003%)!c\u0016\t\u0015\r%\u00141XA\u0001\n\u000bI\u0019\u0007C\u0005\n4\u0005\t\t\u0011b\u0001\nt\u00191\u0011\u0012Q\u0001\u0004\u0013\u0007Cq\"#)\u0002J\u0012\u0005\tQ!BC\u0002\u0013%\u00112\u0015\u0005\r\u0013W\u000bIM!B\u0001B\u0003%\u0011R\u0015\u0005\t\u0005\u0013\fI\r\"\u0001\n.\"A11CAe\t\u0003I\u0019\u000b\u0003\u0005\u0004\u0016\u0005%G\u0011IEZ\u0011)\u0019I\"!3\u0002\u0002\u0013\u000531\u0004\u0005\u000b\u0007G\tI-!A\u0005B%Uv!CE]\u0003\u0005\u0005\t\u0012AE^\r%I\t)AA\u0001\u0012\u0003Ii\f\u0003\u0005\u0003J\u0006mG\u0011AE`\u0011!\u0019I$a7\u0005\u0006%\u0005\u0007\u0002CB&\u00037$)!c5\t\u0015\rm\u00131\\A\u0001\n\u000bI)\u000f\u0003\u0006\u0004j\u0005m\u0017\u0011!C\u0003\u0013kD\u0011\"#/\u0002\u0003\u0003%\u0019A#\u0003\u0007\r)m\u0011a\u0001F\u000f\u0011=Q\t$!;\u0005\u0002\u0003\u0015)Q1A\u0005\n)M\u0002\u0002\u0004F\u001d\u0003S\u0014)\u0011!Q\u0001\n)U\u0002\u0002\u0003Be\u0003S$\tAc\u000f\t\u0011\rM\u0011\u0011\u001eC\u0001\u0015gA\u0001b!\u0006\u0002j\u0012\u0005#\u0012\t\u0005\u000b\u00073\tI/!A\u0005B\rm\u0001BCB\u0012\u0003S\f\t\u0011\"\u0011\u000bD\u001dI!rI\u0001\u0002\u0002#\u0005!\u0012\n\u0004\n\u00157\t\u0011\u0011!E\u0001\u0015\u0017B\u0001B!3\u0002|\u0012\u0005!R\n\u0005\t\u0007s\tY\u0010\"\u0002\u000bP!A11JA~\t\u000bQ\t\u0007\u0003\u0006\u0004\\\u0005m\u0018\u0011!C\u0003\u0015gB!b!\u001b\u0002|\u0006\u0005IQ\u0001FB\u0011%Q9%AA\u0001\n\u0007Q9J\u0002\u0004\u000b*\u0006\u0019!2\u0016\u0005\u0010\u0015\u007f\u0013I\u0001\"A\u0001\u0006\u000b\u0015\r\u0011\"\u0003\u000bB\"a!r\u0019B\u0005\u0005\u000b\u0005\t\u0015!\u0003\u000bD\"A!\u0011\u001aB\u0005\t\u0003QI\r\u0003\u0005\u0004\u0014\t%A\u0011\u0001Fa\u0011!\u0019)B!\u0003\u0005B)=\u0007BCB\r\u0005\u0013\t\t\u0011\"\u0011\u0004\u001c!Q11\u0005B\u0005\u0003\u0003%\tE#5\b\u0013)U\u0017!!A\t\u0002)]g!\u0003FU\u0003\u0005\u0005\t\u0012\u0001Fm\u0011!\u0011IMa\u0007\u0005\u0002)m\u0007\u0002CB\u001d\u00057!)A#8\t\u0011\r-#1\u0004C\u0003\u0015_D!ba\u0017\u0003\u001c\u0005\u0005IQAF\u0001\u0011)\u0019IGa\u0007\u0002\u0002\u0013\u00151\u0012\u0003\u0005\n\u0015+\f\u0011\u0011!C\u0002\u0017K1aac\u000e\u0002\u0007-e\u0002bDF(\u0005S!\t\u0011!B\u0003\u0006\u0004%Ia#\u0015\t\u0019-e#\u0011\u0006B\u0003\u0002\u0003\u0006Iac\u0015\t\u0011\t%\'\u0011\u0006C\u0001\u00177B\u0001ba\u0005\u0003*\u0011\u00051\u0012\u000b\u0005\t\u0007+\u0011I\u0003\"\u0011\fb!Q1\u0011\u0004B\u0015\u0003\u0003%\tea\u0007\t\u0015\r\r\"\u0011FA\u0001\n\u0003Z\u0019gB\u0005\fh\u0005\t\t\u0011#\u0001\fj\u0019I1rG\u0001\u0002\u0002#\u000512\u000e\u0005\t\u0005\u0013\u0014Y\u0004\"\u0001\fn!A1\u0011\bB\u001e\t\u000bYy\u0007\u0003\u0005\u0004L\tmBQAFA\u0011)\u0019YFa\u000f\u0002\u0002\u0013\u001512\u0013\u0005\u000b\u0007S\u0012Y$!A\u0005\u0006-\r\u0006\"CF4\u0003\u0005\u0005I1AF\\\r\u0019YI-A\u0002\fL\"y1r\u001cB%\t\u0003\u0005)Q!b\u0001\n\u0013Y\t\u000f\u0003\u0007\fh\n%#Q!A!\u0002\u0013Y\u0019\u000f\u0003\u0005\u0003J\n%C\u0011AFu\u0011!\u0019\u0019B!\u0013\u0005\u0002-\u0005\b\u0002CB\u000b\u0005\u0013\"\tec<\t\u0015\re!\u0011JA\u0001\n\u0003\u001aY\u0002\u0003\u0006\u0004$\t%\u0013\u0011!C!\u0017c<\u0011b#>\u0002\u0003\u0003E\tac>\u0007\u0013-%\u0017!!A\t\u0002-e\b\u0002\u0003Be\u00057\"\tac?\t\u0011\re\"1\fC\u0003\u0017{D\u0001ba\u0013\u0003\\\u0011\u0015Ar\u0002\u0005\u000b\u00077\u0012Y&!A\u0005\u00061\u0005\u0002BCB5\u00057\n\t\u0011\"\u0002\r2!I1R_\u0001\u0002\u0002\u0013\rAR\t\u0004\u0007\u0019/\n1\u0001$\u0017\t\u001f1=$\u0011\u000eC\u0001\u0002\u000b\u0015)\u0019!C\u0005\u0019cBA\u0002d \u0003j\t\u0015\t\u0011)A\u0005\u0019gB\u0001B!3\u0003j\u0011\u0005A\u0012\u0011\u0005\t\u0007\'\u0011I\u0007\"\u0001\rr!A1Q\u0003B5\t\u0003b9\t\u0003\u0006\u0004\u001a\t%\u0014\u0011!C!\u00077A!ba\t\u0003j\u0005\u0005I\u0011\tGE\u000f%ai)AA\u0001\u0012\u0003ayIB\u0005\rX\u0005\t\t\u0011#\u0001\r\u0012\"A!\u0011\u001aB>\t\u0003a\u0019\n\u0003\u0005\u0004:\tmDQ\u0001GK\u0011!\u0019YEa\u001f\u0005\u00061\u001d\u0006BCB.\u0005w\n\t\u0011\"\u0002\r:\"Q1\u0011\u000eB>\u0003\u0003%)\u0001$3\t\u001315\u0015!!A\u0005\u00041ugA\u0002Gx\u0003\ra\t\u0010C\b\r~\n%E\u0011!A\u0003\u0006\u000b\u0007I\u0011\u0002G\u0000\u00111i9A!#\u0003\u0006\u0003\u0005\u000b\u0011BG\u0001\u0011!\u0011IM!#\u0005\u00025%\u0001\u0002CB\n\u0005\u0013#\t!$\u0005\t\u0011\rU!\u0011\u0012C!\u001b+A!b!\u0007\u0003\n\u0006\u0005I\u0011IB\u000e\u0011)\u0019\u0019C!#\u0002\u0002\u0013\u0005SrC\u0004\n\u001b7\t\u0011\u0011!E\u0001\u001b;1\u0011\u0002d<\u0002\u0003\u0003E\t!d\b\t\u0011\t%\'1\u0014C\u0001\u001bCA\u0001b!\u000f\u0003\u001c\u0012\u0015Q2\u0005\u0005\t\u0007\u0017\u0012Y\n\"\u0002\u000e2!Q11\fBN\u0003\u0003%)!d\u0010\t\u0015\r%$1TA\u0001\n\u000biY\u0005C\u0005\u000e\u001c\u0005\t\t\u0011b\u0001\u000e\\\u0005!2i\u001c7mK\u000e$\u0018n\u001c8D_:4XM\u001d;feNTAA!,\u00030\u0006A\u0001/\u0019:bY2,GN\u0003\u0003\u00032\nM\u0016AC2pY2,7\r^5p]*\u0011!QW\u0001\u0006g\u000e\fG.Y\u0002\u0001!\r\u0011Y,A\u0007\u0003\u0005W\u0013AcQ8mY\u0016\u001cG/[8o\u0007>tg/\u001a:uKJ\u001c8cA\u0001\u0003BB!!1\u0019Bc\u001b\t\u0011\u0019,\u0003\u0003\u0003H\nM&AB!osJ+g-\u0001\u0004=S:LGO\u0010\u000b\u0003\u0005s\u0013\u0001$\u0013;fe\u0006\u0014G.Z%t!\u0006\u0014\u0018\r\u001c7fY&T\u0018M\u00197f+\u0011\u0011\tN!:\u0014\u000b\r\u0011\u0019N!7\u0011\t\t\r\'Q[\u0005\u0005\u0005/\u0014\u0019L\u0001\u0004B]f4\u0016\r\u001c\t\t\u00057\u0014iN!9\u0003x6\u0011!qV\u0005\u0005\u0005?\u0014yK\u0001\u000bDkN$x.\u001c)be\u0006dG.\u001a7ju\u0006\u0014G.\u001a\t\u0005\u0005G\u0014)\u000f\u0004\u0001\u0005\u000f\t\u001d8A1\u0001\u0003j\n\t\u0011)\u0005\u0003\u0003l\nE\b\u0003\u0002Bb\u0005[LAAa<\u00034\n9aj\u001c;iS:<\u0007\u0003\u0002Bb\u0005gLAA!>\u00034\n\u0019\u0011I\\=\u0011\r\tm&\u0011 Bq\u0013\u0011\u0011YPa+\u0003\u0017A\u000b\'/\u0013;fe\u0006\u0014G.Z\u0001Ng\u000e\fG.\u0019\u0013d_2dWm\u0019;j_:$\u0003/\u0019:bY2,G\u000eJ\"pY2,7\r^5p]\u000e{gN^3si\u0016\u00148\u000fJ%uKJ\f\'\r\\3JgB\u000b\'/\u00197mK2L\'0\u00192mK\u0012\"3m\u001c7m+\t\u0019\t\u0001\u0005\u0004\u0003\\\u000e\r!\u0011]\u0005\u0005\u0007\u000b\u0011yK\u0001\u0005Ji\u0016\u0014\u0018M\u00197f\u00039\u001b8-\u00197bI\r|G\u000e\\3di&|g\u000e\n9be\u0006dG.\u001a7%\u0007>dG.Z2uS>t7i\u001c8wKJ$XM]:%\u0013R,\'/\u00192mK&\u001b\b+\u0019:bY2,G.\u001b>bE2,G\u0005J2pY2\u0004C\u0003BB\u0006\u0007\u001f\u0001Ra!\u0004\u0004\u0005Cl\u0011!\u0001\u0005\b\u0007#1\u0001\u0019AB\u0001\u0003\u0011\u0019w\u000e\u001c7\u0002\u0007M,\u0017/A\u0002qCJ,\"Aa>\u0002\u0011!\f7\u000f[\"pI\u0016$\"a!\b\u0011\t\t\r7qD\u0005\u0005\u0007C\u0011\u0019LA\u0002J]R\fa!Z9vC2\u001cH\u0003BB\u0014\u0007[\u0001BAa1\u0004*%!11\u0006BZ\u0005\u001d\u0011un\u001c7fC:D\u0011ba\f\u000b\u0003\u0003\u0005\rA!=\u0002\u0007a$\u0013\'\u0001\rJi\u0016\u0014\u0018M\u00197f\u0013N\u0004\u0016M]1mY\u0016d\u0017N_1cY\u0016\u00042a!\u0004\r\'\ra!\u0011\u0019\u000b\u0003\u0007g\tQb]3rI\u0015DH/\u001a8tS>tW\u0003BB\u001f\u0007\u0007\"Baa\u0010\u0004FA1!1\\B\u0002\u0007\u0003\u0002BAa9\u0004D\u00119!q\u001d\bC\u0002\t%\bbBB$\u001d\u0001\u00071\u0011J\u0001\u0006IQD\u0017n\u001d\t\u0006\u0007\u001b\u00191\u0011I\u0001\u000ea\u0006\u0014H%\u001a=uK:\u001c\u0018n\u001c8\u0016\t\r=3Q\u000b\u000b\u0005\u0007#\u001a9\u0006\u0005\u0004\u0003<\ne81\u000b\t\u0005\u0005G\u001c)\u0006B\u0004\u0003h>\u0011\rA!;\t\u000f\r\u001ds\u00021\u0001\u0004ZA)1QB\u0002\u0004T\u0005\u0011\u0002.Y:i\u0007>$W\rJ3yi\u0016t7/[8o+\u0011\u0019yfa\u001a\u0015\t\rm1\u0011\r\u0005\b\u0007\u000f\u0002\u0002\u0019AB2!\u0015\u0019iaAB3!\u0011\u0011\u0019oa\u001a\u0005\u000f\t\u001d\bC1\u0001\u0003j\u0006\u0001R-];bYN$S\r\u001f;f]NLwN\\\u000b\u0005\u0007[\u001aI\b\u0006\u0003\u0004p\rMD\u0003BB\u0014\u0007cB\u0011ba\f\u0012\u0003\u0003\u0005\rA!=\t\u000f\r\u001d\u0013\u00031\u0001\u0004vA)1QB\u0002\u0004xA!!1]B=\t\u001d\u00119/\u0005b\u0001\u0005S,Ba! \u0004\u0004R!1qPBC!\u0015\u0019iaABA!\u0011\u0011\u0019oa!\u0005\u000f\t\u001d(C1\u0001\u0003j\"91\u0011\u0003\nA\u0002\r\u001d\u0005C\u0002Bn\u0007\u0007\u0019\tIA\u0010NkR\f\'\r\\3Ji\u0016\u0014\u0018M\u00197f\u0013N\u0004\u0016M]1mY\u0016d\u0017N_1cY\u0016,Ba!$\u0004\u0014N)1Ca5\u0004\u0010BA!1\u001cBo\u0007#\u001b)\n\u0005\u0003\u0003d\u000eMEa\u0002Bt\'\t\u0007!\u0011\u001e\t\u0007\u0007/\u001bij!%\u000e\u0005\re%\u0002BBN\u0005W\u000bq!\\;uC\ndW-\u0003\u0003\u0003|\u000ee\u0015\u0001V:dC2\fGeY8mY\u0016\u001cG/[8oIA\f\'/\u00197mK2$3i\u001c7mK\u000e$\u0018n\u001c8D_:4XM\u001d;feN$S*\u001e;bE2,\u0017\n^3sC\ndW-S:QCJ\fG\u000e\\3mSj\f\'\r\\3%I\r|G\u000e\\\u000b\u0003\u0007G\u0003ba!*\u0004*\u000eEUBABT\u0015\u0011\u0019YJa,\n\t\r\u00151qU\u0001Vg\u000e\fG.\u0019\u0013d_2dWm\u0019;j_:$\u0003/\u0019:bY2,G\u000eJ\"pY2,7\r^5p]\u000e{gN^3si\u0016\u00148\u000fJ\'vi\u0006\u0014G.Z%uKJ\f\'\r\\3JgB\u000b\'/\u00197mK2L\'0\u00192mK\u0012\"3m\u001c7mAQ!1qVBY!\u0015\u0019iaEBI\u0011\u001d\u0019\tB\u0006a\u0001\u0007G+\"a!&\u0015\t\r\u001d2q\u0017\u0005\n\u0007_Q\u0012\u0011!a\u0001\u0005c\fq$T;uC\ndW-\u0013;fe\u0006\u0014G.Z%t!\u0006\u0014\u0018\r\u001c7fY&T\u0018M\u00197f!\r\u0019i\u0001H\n\u00049\t\u0005GCAB^+\u0011\u0019\u0019m!3\u0015\t\r\u001571\u001a\t\u0007\u0007K\u001bIka2\u0011\t\t\r8\u0011\u001a\u0003\b\u0005Ot\"\u0019\u0001Bu\u0011\u001d\u00199E\ba\u0001\u0007\u001b\u0004Ra!\u0004\u0014\u0007\u000f,Ba!5\u0004XR!11[Bm!\u0019\u00199j!(\u0004VB!!1]Bl\t\u001d\u00119o\bb\u0001\u0005SDqaa\u0012 \u0001\u0004\u0019Y\u000eE\u0003\u0004\u000eM\u0019).\u0006\u0003\u0004`\u000e\u001dH\u0003BB\u000e\u0007CDqaa\u0012!\u0001\u0004\u0019\u0019\u000fE\u0003\u0004\u000eM\u0019)\u000f\u0005\u0003\u0003d\u000e\u001dHa\u0002BtA\t\u0007!\u0011^\u000b\u0005\u0007W\u001c9\u0010\u0006\u0003\u0004n\u000eEH\u0003BB\u0014\u0007_D\u0011ba\f\"\u0003\u0003\u0005\rA!=\t\u000f\r\u001d\u0013\u00051\u0001\u0004tB)1QB\n\u0004vB!!1]B|\t\u001d\u00119/\tb\u0001\u0005S,Baa?\u0005\u0002Q!1Q C\u0002!\u0015\u0019iaEB\u0000!\u0011\u0011\u0019\u000f\"\u0001\u0005\u000f\t\u001d(E1\u0001\u0003j\"91\u0011\u0003\u0012A\u0002\u0011\u0015\u0001CBBS\u0007S\u001byPA\u0011J[6,H/\u00192mK&#XM]1cY\u0016L5\u000fU1sC2dW\r\\5{C\ndW-\u0006\u0003\u0005\f\u0011E1#B\u0012\u0003T\u00125\u0001\u0003\u0003Bn\u0005;$y\u0001b\u0005\u0011\t\t\rH\u0011\u0003\u0003\b\u0005O\u001c#\u0019\u0001Bu!\u0019!)\u0002b\u0007\u0005\u00105\u0011Aq\u0003\u0006\u0005\t3\u0011Y+A\u0005j[6,H/\u00192mK&!!1 C\f\u0003Y\u001b8-\u00197bI\r|G\u000e\\3di&|g\u000e\n9be\u0006dG.\u001a7%\u0007>dG.Z2uS>t7i\u001c8wKJ$XM]:%\u00136lW\u000f^1cY\u0016LE/\u001a:bE2,\u0017j\u001d)be\u0006dG.\u001a7ju\u0006\u0014G.\u001a\u0013%G>dG.\u0006\u0002\u0005\"A1A1\u0005C\u0014\t\u001fi!\u0001\"\n\u000b\t\u0011e!qV\u0005\u0005\u0007\u000b!)#A,tG\u0006d\u0017\rJ2pY2,7\r^5p]\u0012\u0002\u0018M]1mY\u0016dGeQ8mY\u0016\u001cG/[8o\u0007>tg/\u001a:uKJ\u001cH%S7nkR\f\'\r\\3Ji\u0016\u0014\u0018M\u00197f\u0013N\u0004\u0016M]1mY\u0016d\u0017N_1cY\u0016$CeY8mY\u0002\"B\u0001\"\f\u00050A)1QB\u0012\u0005\u0010!91\u0011\u0003\u0014A\u0002\u0011\u0005RC\u0001C\n)\u0011\u00199\u0003\"\u000e\t\u0013\r=\"&!AA\u0002\tE\u0018!I%n[V$\u0018M\u00197f\u0013R,\'/\u00192mK&\u001b\b+\u0019:bY2,G.\u001b>bE2,\u0007cAB\u0007YM\u0019AF!1\u0015\u0005\u0011eR\u0003\u0002C!\t\u000f\"B\u0001b\u0011\u0005JA1A1\u0005C\u0014\t\u000b\u0002BAa9\u0005H\u00119!q\u001d\u0018C\u0002\t%\bbBB$]\u0001\u0007A1\n\t\u0006\u0007\u001b\u0019CQI\u000b\u0005\t\u001f\")\u0006\u0006\u0003\u0005R\u0011]\u0003C\u0002C\u000b\t7!\u0019\u0006\u0005\u0003\u0003d\u0012UCa\u0002Bt_\t\u0007!\u0011\u001e\u0005\b\u0007\u000fz\u0003\u0019\u0001C-!\u0015\u0019ia\tC*+\u0011!i\u0006\"\u001a\u0015\t\rmAq\f\u0005\b\u0007\u000f\u0002\u0004\u0019\u0001C1!\u0015\u0019ia\tC2!\u0011\u0011\u0019\u000f\"\u001a\u0005\u000f\t\u001d\bG1\u0001\u0003jV!A\u0011\u000eC;)\u0011!Y\u0007b\u001c\u0015\t\r\u001dBQ\u000e\u0005\n\u0007_\t\u0014\u0011!a\u0001\u0005cDqaa\u00122\u0001\u0004!\t\bE\u0003\u0004\u000e\r\"\u0019\b\u0005\u0003\u0003d\u0012UDa\u0002Btc\t\u0007!\u0011^\u000b\u0005\ts\"y\b\u0006\u0003\u0005|\u0011\u0005\u0005#BB\u0007G\u0011u\u0004\u0003\u0002Br\t\u007f\"qAa:3\u0005\u0004\u0011I\u000fC\u0004\u0004\u0012I\u0002\r\u0001b!\u0011\r\u0011\rBq\u0005C?\u0003M\u0019X-]%t!\u0006\u0014\u0018\r\u001c7fY&T\u0018M\u00197f+\u0011!I\tb%\u0015\t\u0011-E1\u0014\t\t\u00057$i\t\"%\u0005\u0016&!Aq\u0012BX\u00059\u0001\u0016M]1mY\u0016d\u0017N_1cY\u0016\u0004BAa9\u0005\u0014\u00129!q]\u001aC\u0002\t%\bC\u0002B^\t/#\t*\u0003\u0003\u0005\u001a\n-&A\u0002)beN+\u0017\u000fC\u0004\u0004\u0012M\u0002\r\u0001\"(\u0011\r\tmGq\u0014CI\u0013\u0011!\tKa,\u0003\u0007M+\u0017O\u0001\u000eNkR\f\'\r\\3TKFL5\u000fU1sC2dW\r\\5{C\ndW-\u0006\u0003\u0005(\u001256#\u0002\u001b\u0003T\u0012%\u0006\u0003\u0003Bn\u0005;$Y\u000bb,\u0011\t\t\rHQ\u0016\u0003\b\u0005O$$\u0019\u0001Bu!\u0019\u00199\n\"-\u0005,&!A\u0011TBM\u0003=\u001b8-\u00197bI\r|G\u000e\\3di&|g\u000e\n9be\u0006dG.\u001a7%\u0007>dG.Z2uS>t7i\u001c8wKJ$XM]:%\u001bV$\u0018M\u00197f\'\u0016\f\u0018j\u001d)be\u0006dG.\u001a7ju\u0006\u0014G.\u001a\u0013%G>dG.\u0006\u0002\u00058B11Q\u0015C]\tWKA\u0001\")\u0004(\u0006\u00016oY1mC\u0012\u001aw\u000e\u001c7fGRLwN\u001c\u0013qCJ\fG\u000e\\3mI\r{G\u000e\\3di&|gnQ8om\u0016\u0014H/\u001a:tI5+H/\u00192mKN+\u0017/S:QCJ\fG\u000e\\3mSj\f\'\r\\3%I\r|G\u000e\u001c\u0011\u0015\t\u0011}F\u0011\u0019\t\u0006\u0007\u001b!D1\u0016\u0005\b\u0007#9\u0004\u0019\u0001C\\+\t!y\u000b\u0006\u0003\u0004(\u0011\u001d\u0007\"CB\u0018w\u0005\u0005\t\u0019\u0001By\u0003iiU\u000f^1cY\u0016\u001cV-]%t!\u0006\u0014\u0018\r\u001c7fY&T\u0018M\u00197f!\r\u0019i!P\n\u0004{\t\u0005GC\u0001Cf+\u0011!\u0019\u000e\"7\u0015\t\u0011UG1\u001c\t\u0007\u0007K#I\fb6\u0011\t\t\rH\u0011\u001c\u0003\b\u0005O|$\u0019\u0001Bu\u0011\u001d\u00199e\u0010a\u0001\t;\u0004Ra!\u00045\t/,B\u0001\"9\u0005hR!A1\u001dCu!\u0019\u00199\n\"-\u0005fB!!1\u001dCt\t\u001d\u00119\u000f\u0011b\u0001\u0005SDqaa\u0012A\u0001\u0004!Y\u000fE\u0003\u0004\u000eQ\")/\u0006\u0003\u0005p\u0012]H\u0003BB\u000e\tcDqaa\u0012B\u0001\u0004!\u0019\u0010E\u0003\u0004\u000eQ\")\u0010\u0005\u0003\u0003d\u0012]Ha\u0002Bt\u0003\n\u0007!\u0011^\u000b\u0005\tw,9\u0001\u0006\u0003\u0005~\u0016\u0005A\u0003BB\u0014\t\u007fD\u0011ba\fC\u0003\u0003\u0005\rA!=\t\u000f\r\u001d#\t1\u0001\u0006\u0004A)1Q\u0002\u001b\u0006\u0006A!!1]C\u0004\t\u001d\u00119O\u0011b\u0001\u0005S,B!b\u0003\u0006\u0012Q!QQBC\n!\u0015\u0019i\u0001NC\b!\u0011\u0011\u0019/\"\u0005\u0005\u000f\t\u001d8I1\u0001\u0003j\"91\u0011C\"A\u0002\u0015U\u0001CBBS\ts+yAA\u0010NkR\f\'\r\\3BeJ\f\u0017pU3r\u0013N\u0004\u0016M]1mY\u0016d\u0017N_1cY\u0016,B!b\u0007\u0006\"M)AIa5\u0006\u001eAA!1\u001cBo\u000b?))\u0003\u0005\u0003\u0003d\u0016\u0005BaBC\u0012\t\n\u0007!\u0011\u001e\u0002\u0002)B11qSC\u0014\u000b?IA!\"\u000b\u0004\u001a\nA\u0001+\u0019:BeJ\f\u00170\u0001+tG\u0006d\u0017\rJ2pY2,7\r^5p]\u0012\u0002\u0018M]1mY\u0016dGeQ8mY\u0016\u001cG/[8o\u0007>tg/\u001a:uKJ\u001cH%T;uC\ndW-\u0011:sCf\u001cV-]%t!\u0006\u0014\u0018\r\u001c7fY&T\u0018M\u00197fI\u0011\u001aw\u000e\u001c7\u0016\u0005\u0015=\u0002CBBS\u000bc)y\"\u0003\u0003\u00064\r\u001d&\u0001C!se\u0006L8+Z9\u0002+N\u001c\u0017\r\\1%G>dG.Z2uS>tG\u0005]1sC2dW\r\u001c\u0013D_2dWm\u0019;j_:\u001cuN\u001c<feR,\'o\u001d\u0013NkR\f\'\r\\3BeJ\f\u0017pU3r\u0013N\u0004\u0016M]1mY\u0016d\u0017N_1cY\u0016$CeY8mY\u0002\"B!\"\u000f\u0006<A)1Q\u0002#\u0006 !91\u0011C$A\u0002\u0015=RCAC\u0013)\u0011\u00199#\"\u0011\t\u0013\r=2*!AA\u0002\tE\u0018aH\'vi\u0006\u0014G.Z!se\u0006L8+Z9JgB\u000b\'/\u00197mK2L\'0\u00192mKB\u00191QB\'\u0014\u00075\u0013\t\r\u0006\u0002\u0006FU!QQJC*)\u0011)y%\"\u0016\u0011\r\r\u0015V\u0011GC)!\u0011\u0011\u0019/b\u0015\u0005\u000f\u0015\rrJ1\u0001\u0003j\"91qI(A\u0002\u0015]\u0003#BB\u0007\t\u0016ES\u0003BC.\u000bC\"B!\"\u0018\u0006dA11qSC\u0014\u000b?\u0002BAa9\u0006b\u00119Q1\u0005)C\u0002\t%\bbBB$!\u0002\u0007QQ\r\t\u0006\u0007\u001b!UqL\u000b\u0005\u000bS*\t\b\u0006\u0003\u0004\u001c\u0015-\u0004bBB$#\u0002\u0007QQ\u000e\t\u0006\u0007\u001b!Uq\u000e\t\u0005\u0005G,\t\bB\u0004\u0006$E\u0013\rA!;\u0016\t\u0015UT\u0011\u0011\u000b\u0005\u000bo*Y\b\u0006\u0003\u0004(\u0015e\u0004\"CB\u0018%\u0006\u0005\t\u0019\u0001By\u0011\u001d\u00199E\u0015a\u0001\u000b{\u0002Ra!\u0004E\u000b\u007f\u0002BAa9\u0006\u0002\u00129Q1\u0005*C\u0002\t%X\u0003BCC\u000b\u0017#B!b\"\u0006\u000eB)1Q\u0002#\u0006\nB!!1]CF\t\u001d)\u0019c\u0015b\u0001\u0005SDqa!\u0005T\u0001\u0004)y\t\u0005\u0004\u0004&\u0016ER\u0011\u0012\u0002#\u001bV$\u0018M\u00197f\u0003J\u0014\u0018-\u001f\"vM\u001a,\'/S:QCJ\fG\u000e\\3mSj\f\'\r\\3\u0016\t\u0015UU1T\n\u0006)\nMWq\u0013\t\t\u00057\u0014i.\"\'\u0006\u001eB!!1]CN\t\u001d)\u0019\u0003\u0016b\u0001\u0005S\u0004baa&\u0006(\u0015e\u0015aV:dC2\fGeY8mY\u0016\u001cG/[8oIA\f\'/\u00197mK2$3i\u001c7mK\u000e$\u0018n\u001c8D_:4XM\u001d;feN$S*\u001e;bE2,\u0017I\u001d:bs\n+hMZ3s\u0013N\u0004\u0016M]1mY\u0016d\u0017N_1cY\u0016$CeY8mYV\u0011Q1\u0015\t\u0007\u0007K+)+\"\'\n\t\u0015\u001d6q\u0015\u0002\f\u0003J\u0014\u0018-\u001f\"vM\u001a,\'/\u0001-tG\u0006d\u0017\rJ2pY2,7\r^5p]\u0012\u0002\u0018M]1mY\u0016dGeQ8mY\u0016\u001cG/[8o\u0007>tg/\u001a:uKJ\u001cH%T;uC\ndW-\u0011:sCf\u0014UO\u001a4fe&\u001b\b+\u0019:bY2,G.\u001b>bE2,G\u0005J2pY2\u0004C\u0003BCW\u000b_\u0003Ra!\u0004U\u000b3Cqa!\u0005X\u0001\u0004)\u0019+\u0006\u0002\u0006\u001eR!1qEC[\u0011%\u0019ycWA\u0001\u0002\u0004\u0011\t0\u0001\u0012NkR\f\'\r\\3BeJ\f\u0017PQ;gM\u0016\u0014\u0018j\u001d)be\u0006dG.\u001a7ju\u0006\u0014G.\u001a\t\u0004\u0007\u001bi6cA/\u0003BR\u0011Q\u0011X\u000b\u0005\u000b\u0003,9\r\u0006\u0003\u0006D\u0016%\u0007CBBS\u000bK+)\r\u0005\u0003\u0003d\u0016\u001dGaBC\u0012?\n\u0007!\u0011\u001e\u0005\b\u0007\u000fz\u0006\u0019ACf!\u0015\u0019i\u0001VCc+\u0011)y-\"6\u0015\t\u0015EWq\u001b\t\u0007\u0007/+9#b5\u0011\t\t\rXQ\u001b\u0003\b\u000bG\u0001\'\u0019\u0001Bu\u0011\u001d\u00199\u0005\u0019a\u0001\u000b3\u0004Ra!\u0004U\u000b\',B!\"8\u0006fR!11DCp\u0011\u001d\u00199%\u0019a\u0001\u000bC\u0004Ra!\u0004U\u000bG\u0004BAa9\u0006f\u00129Q1E1C\u0002\t%X\u0003BCu\u000bk$B!b;\u0006pR!1qECw\u0011%\u0019yCYA\u0001\u0002\u0004\u0011\t\u0010C\u0004\u0004H\t\u0004\r!\"=\u0011\u000b\r5A+b=\u0011\t\t\rXQ\u001f\u0003\b\u000bG\u0011\'\u0019\u0001Bu+\u0011)I0b@\u0015\t\u0015mh\u0011\u0001\t\u0006\u0007\u001b!VQ \t\u0005\u0005G,y\u0010B\u0004\u0006$\r\u0014\rA!;\t\u000f\rE1\r1\u0001\u0007\u0004A11QUCS\u000b{\u0014A$S7nkR\f\'\r\\3TKFL5\u000fU1sC2dW\r\\5{C\ndW-\u0006\u0003\u0007\n\u0019=1#\u00023\u0003T\u001a-\u0001\u0003\u0003Bn\u0005;4iA\"\u0005\u0011\t\t\rhq\u0002\u0003\b\u0005O$\'\u0019\u0001Bu!\u0019!)Bb\u0005\u0007\u000e%!A\u0011\u0014C\f\u0003E\u001b8-\u00197bI\r|G\u000e\\3di&|g\u000e\n9be\u0006dG.\u001a7%\u0007>dG.Z2uS>t7i\u001c8wKJ$XM]:%\u00136lW\u000f^1cY\u0016\u001cV-]%t!\u0006\u0014\u0018\r\u001c7fY&T\u0018M\u00197fI\u0011\u001aw\u000e\u001c7\u0016\u0005\u0019e\u0001C\u0002C\u0012\r71i!\u0003\u0003\u0005\"\u0012\u0015\u0012AU:dC2\fGeY8mY\u0016\u001cG/[8oIA\f\'/\u00197mK2$3i\u001c7mK\u000e$\u0018n\u001c8D_:4XM\u001d;feN$\u0013*\\7vi\u0006\u0014G.Z*fc&\u001b\b+\u0019:bY2,G.\u001b>bE2,G\u0005J2pY2\u0004C\u0003\u0002D\u0011\rG\u0001Ra!\u0004e\r\u001bAqa!\u0005h\u0001\u00041I\"\u0006\u0002\u0007\u0012Q!1q\u0005D\u0015\u0011%\u0019yc[A\u0001\u0002\u0004\u0011\t0\u0001\u000fJ[6,H/\u00192mKN+\u0017/S:QCJ\fG\u000e\\3mSj\f\'\r\\3\u0011\u0007\r5QnE\u0002n\u0005\u0003$\"A\"\f\u0016\t\u0019Ub1\b\u000b\u0005\ro1i\u0004\u0005\u0004\u0005$\u0019ma\u0011\b\t\u0005\u0005G4Y\u0004B\u0004\u0003h>\u0014\rA!;\t\u000f\r\u001ds\u000e1\u0001\u0007@A)1Q\u00023\u0007:U!a1\tD%)\u00111)Eb\u0013\u0011\r\u0011Ua1\u0003D$!\u0011\u0011\u0019O\"\u0013\u0005\u000f\t\u001d\bO1\u0001\u0003j\"91q\t9A\u0002\u00195\u0003#BB\u0007I\u001a\u001dS\u0003\u0002D)\r3\"Baa\u0007\u0007T!91qI9A\u0002\u0019U\u0003#BB\u0007I\u001a]\u0003\u0003\u0002Br\r3\"qAa:r\u0005\u0004\u0011I/\u0006\u0003\u0007^\u0019%D\u0003\u0002D0\rG\"Baa\n\u0007b!I1q\u0006:\u0002\u0002\u0003\u0007!\u0011\u001f\u0005\b\u0007\u000f\u0012\b\u0019\u0001D3!\u0015\u0019i\u0001\u001aD4!\u0011\u0011\u0019O\"\u001b\u0005\u000f\t\u001d(O1\u0001\u0003jV!aQ\u000eD:)\u00111yG\"\u001e\u0011\u000b\r5AM\"\u001d\u0011\t\t\rh1\u000f\u0003\b\u0005O\u001c(\u0019\u0001Bu\u0011\u001d\u0019\tb\u001da\u0001\ro\u0002b\u0001b\t\u0007\u001c\u0019E$!\u0006*b]\u001e,\u0017j\u001d)be\u0006dG.\u001a7ju\u0006\u0014G.Z\n\u0006i\nMgQ\u0010\t\t\u00057\u0014in!\b\u0007\u0000A!AQ\u0003DA\u0013\u00111\u0019\tb\u0006\u0003\u0011A\u000b\'OU1oO\u0016\f!j]2bY\u0006$3m\u001c7mK\u000e$\u0018n\u001c8%a\u0006\u0014\u0018\r\u001c7fY\u0012\u001au\u000e\u001c7fGRLwN\\\"p]Z,\'\u000f^3sg\u0012\u0012\u0016M\\4f\u0013N\u0004\u0016M]1mY\u0016d\u0017N_1cY\u0016$CeY8mYV\u0011a\u0011\u0012\t\u0005\tG1Y)\u0003\u0003\u0007\u000e\u0012\u0015\"!\u0002*b]\u001e,\u0017aS:dC2\fGeY8mY\u0016\u001cG/[8oIA\f\'/\u00197mK2$3i\u001c7mK\u000e$\u0018n\u001c8D_:4XM\u001d;feN$#+\u00198hK&\u001b\b+\u0019:bY2,G.\u001b>bE2,G\u0005J2pY2\u0004C\u0003\u0002DJ\r+\u00032a!\u0004u\u0011\u001d\u0019\tb\u001ea\u0001\r\u0013+\"Ab \u0015\t\r\u001db1\u0014\u0005\n\u0007_Y\u0018\u0011!a\u0001\u0005c\fQCU1oO\u0016L5\u000fU1sC2dW\r\\5{C\ndW\rE\u0002\u0004\u000eu\u001c2! Ba)\t1y\n\u0006\u0003\u0007\n\u001a\u001d\u0006bBB$\u007f\u0002\u0007a1\u0013\u000b\u0005\r\u007f2Y\u000b\u0003\u0005\u0004H\u0005\u0005\u0001\u0019\u0001DJ)\u0011\u0019YBb,\t\u0011\r\u001d\u00131\u0001a\u0001\r\'#BAb-\u00078R!1q\u0005D[\u0011)\u0019y#!\u0002\u0002\u0002\u0003\u0007!\u0011\u001f\u0005\t\u0007\u000f\n)\u00011\u0001\u0007\u0014R!a1\u0013D^\u0011!\u0019\t\"a\u0002A\u0002\u0019%%A\u0006,fGR|\'/S:QCJ\fG\u000e\\3mSj\f\'\r\\3\u0016\t\u0019\u0005gqY\n\u0007\u0003\u0013\u0011\u0019Nb1\u0011\u0011\tm\'Q\u001cDc\r\u0013\u0004BAa9\u0007H\u0012AQ1EA\u0005\u0005\u0004\u0011I\u000f\u0005\u0004\u0005\u0016\u0019-gQY\u0005\u0005\r\u001b$9BA\u0005QCJ4Vm\u0019;pe\u0006Y5oY1mC\u0012\u001aw\u000e\u001c7fGRLwN\u001c\u0013qCJ\fG\u000e\\3mI\r{G\u000e\\3di&|gnQ8om\u0016\u0014H/\u001a:tIY+7\r^8s\u0013N\u0004\u0016M]1mY\u0016d\u0017N_1cY\u0016$CeY8mYV\u0011a1\u001b\t\u0007\tG1)N\"2\n\t\u0019]GQ\u0005\u0002\u0007-\u0016\u001cGo\u001c:\u0002\u0019N\u001c\u0017\r\\1%G>dG.Z2uS>tG\u0005]1sC2dW\r\u001c\u0013D_2dWm\u0019;j_:\u001cuN\u001c<feR,\'o\u001d\u0013WK\u000e$xN]%t!\u0006\u0014\u0018\r\u001c7fY&T\u0018M\u00197fI\u0011\u001aw\u000e\u001c7!)\u00111iNb8\u0011\r\r5\u0011\u0011\u0002Dc\u0011!\u0019\t\"a\u0004A\u0002\u0019MWC\u0001De)\u0011\u00199C\":\t\u0015\r=\u0012qCA\u0001\u0002\u0004\u0011\t0\u0001\fWK\u000e$xN]%t!\u0006\u0014\u0018\r\u001c7fY&T\u0018M\u00197f!\u0011\u0019i!a\u0007\u0014\t\u0005m!\u0011\u0019\u000b\u0003\rS,BA\"=\u0007xR!a1\u001fD}!\u0019!\u0019C\"6\u0007vB!!1\u001dD|\t!)\u0019#a\bC\u0002\t%\b\u0002CB$\u0003?\u0001\rAb?\u0011\r\r5\u0011\u0011\u0002D{+\u00111yp\"\u0002\u0015\t\u001d\u0005qq\u0001\t\u0007\t+1Ymb\u0001\u0011\t\t\rxQ\u0001\u0003\t\u000bG\t\tC1\u0001\u0003j\"A1qIA\u0011\u0001\u00049I\u0001\u0005\u0004\u0004\u000e\u0005%q1A\u000b\u0005\u000f\u001b9)\u0002\u0006\u0003\u0004\u001c\u001d=\u0001\u0002CB$\u0003G\u0001\ra\"\u0005\u0011\r\r5\u0011\u0011BD\n!\u0011\u0011\u0019o\"\u0006\u0005\u0011\u0015\r\u00121\u0005b\u0001\u0005S,Ba\"\u0007\b&Q!q1DD\u0010)\u0011\u00199c\"\b\t\u0015\r=\u0012QEA\u0001\u0002\u0004\u0011\t\u0010\u0003\u0005\u0004H\u0005\u0015\u0002\u0019AD\u0011!\u0019\u0019i!!\u0003\b$A!!1]D\u0013\t!)\u0019#!\nC\u0002\t%X\u0003BD\u0015\u000f_!Bab\u000b\b2A11QBA\u0005\u000f[\u0001BAa9\b0\u0011AQ1EA\u0014\u0005\u0004\u0011I\u000f\u0003\u0005\u0004\u0012\u0005\u001d\u0002\u0019AD\u001a!\u0019!\u0019C\"6\b.\t\u00192+\u001a;JgB\u000b\'/\u00197mK2L\'0\u00192mKV!q\u0011HD \'\u0019\tICa5\b<AA!1\u001cBo\u000f{9\t\u0005\u0005\u0003\u0003d\u001e}B\u0001\u0003Bt\u0003S\u0011\rA!;\u0011\r\tmv1ID\u001f\u0013\u00119)Ea+\u0003\rA\u000b\'oU3u\u0003!\u001b8-\u00197bI\r|G\u000e\\3di&|g\u000e\n9be\u0006dG.\u001a7%\u0007>dG.Z2uS>t7i\u001c8wKJ$XM]:%\'\u0016$\u0018j\u001d)be\u0006dG.\u001a7ju\u0006\u0014G.\u001a\u0013%G>dG.\u0006\u0002\bLA1!1\\D\'\u000f{IAab\u0014\u00030\n\u00191+\u001a;\u0002\u0013N\u001c\u0017\r\\1%G>dG.Z2uS>tG\u0005]1sC2dW\r\u001c\u0013D_2dWm\u0019;j_:\u001cuN\u001c<feR,\'o\u001d\u0013TKRL5\u000fU1sC2dW\r\\5{C\ndW\r\n\u0013d_2d\u0007\u0005\u0006\u0003\bV\u001d]\u0003CBB\u0007\u0003S9i\u0004\u0003\u0005\u0004\u0012\u0005=\u0002\u0019AD&+\t9\t\u0005\u0006\u0003\u0004(\u001du\u0003BCB\u0018\u0003o\t\t\u00111\u0001\u0003r\u0006\u00192+\u001a;JgB\u000b\'/\u00197mK2L\'0\u00192mKB!1QBA\u001e\'\u0011\tYD!1\u0015\u0005\u001d\u0005T\u0003BD5\u000f_\"Bab\u001b\brA1!1\\D\'\u000f[\u0002BAa9\bp\u0011A!q]A \u0005\u0004\u0011I\u000f\u0003\u0005\u0004H\u0005}\u0002\u0019AD:!\u0019\u0019i!!\u000b\bnU!qqOD?)\u00119Ihb \u0011\r\tmv1ID>!\u0011\u0011\u0019o\" \u0005\u0011\t\u001d\u0018\u0011\tb\u0001\u0005SD\u0001ba\u0012\u0002B\u0001\u0007q\u0011\u0011\t\u0007\u0007\u001b\tIcb\u001f\u0016\t\u001d\u0015uQ\u0012\u000b\u0005\u0007799\t\u0003\u0005\u0004H\u0005\r\u0003\u0019ADE!\u0019\u0019i!!\u000b\b\fB!!1]DG\t!\u00119/a\u0011C\u0002\t%X\u0003BDI\u000f;#Bab%\b\u0018R!1qEDK\u0011)\u0019y#!\u0012\u0002\u0002\u0003\u0007!\u0011\u001f\u0005\t\u0007\u000f\n)\u00051\u0001\b\u001aB11QBA\u0015\u000f7\u0003BAa9\b\u001e\u0012A!q]A#\u0005\u0004\u0011I/\u0006\u0003\b\"\u001e\u001dF\u0003BDR\u000fS\u0003ba!\u0004\u0002*\u001d\u0015\u0006\u0003\u0002Br\u000fO#\u0001Ba:\u0002H\t\u0007!\u0011\u001e\u0005\t\u0007#\t9\u00051\u0001\b,B1!1\\D\'\u000fK\u0013A$S7nkR\f\'\r\\3TKRL5\u000fU1sC2dW\r\\5{C\ndW-\u0006\u0003\b2\u001e]6CBA%\u0005\'<\u0019\f\u0005\u0005\u0003\\\nuwQWD]!\u0011\u0011\u0019ob.\u0005\u0011\t\u001d\u0018\u0011\nb\u0001\u0005S\u0004b\u0001\"\u0006\b<\u001eU\u0016\u0002BD#\t/\t\u0011k]2bY\u0006$3m\u001c7mK\u000e$\u0018n\u001c8%a\u0006\u0014\u0018\r\u001c7fY\u0012\u001au\u000e\u001c7fGRLwN\\\"p]Z,\'\u000f^3sg\u0012JU.\\;uC\ndWmU3u\u0013N\u0004\u0016M]1mY\u0016d\u0017N_1cY\u0016$CeY8mYV\u0011q\u0011\u0019\t\u0007\tG9\u0019m\".\n\t\u001d=CQE\u0001Sg\u000e\fG.\u0019\u0013d_2dWm\u0019;j_:$\u0003/\u0019:bY2,G\u000eJ\"pY2,7\r^5p]\u000e{gN^3si\u0016\u00148\u000fJ%n[V$\u0018M\u00197f\'\u0016$\u0018j\u001d)be\u0006dG.\u001a7ju\u0006\u0014G.\u001a\u0013%G>dG\u000e\t\u000b\u0005\u000f\u0013<Y\r\u0005\u0004\u0004\u000e\u0005%sQ\u0017\u0005\t\u0007#\ty\u00051\u0001\bBV\u0011q\u0011\u0018\u000b\u0005\u0007O9\t\u000e\u0003\u0006\u00040\u0005]\u0013\u0011!a\u0001\u0005c\fA$S7nkR\f\'\r\\3TKRL5\u000fU1sC2dW\r\\5{C\ndW\r\u0005\u0003\u0004\u000e\u0005m3\u0003BA.\u0005\u0003$\"a\"6\u0016\t\u001duw1\u001d\u000b\u0005\u000f?<)\u000f\u0005\u0004\u0005$\u001d\rw\u0011\u001d\t\u0005\u0005G<\u0019\u000f\u0002\u0005\u0003h\u0006}#\u0019\u0001Bu\u0011!\u00199%a\u0018A\u0002\u001d\u001d\bCBB\u0007\u0003\u0013:\t/\u0006\u0003\bl\u001eEH\u0003BDw\u000fg\u0004b\u0001\"\u0006\b<\u001e=\b\u0003\u0002Br\u000fc$\u0001Ba:\u0002b\t\u0007!\u0011\u001e\u0005\t\u0007\u000f\n\t\u00071\u0001\bvB11QBA%\u000f_,Ba\"?\t\u0002Q!11DD~\u0011!\u00199%a\u0019A\u0002\u001du\bCBB\u0007\u0003\u0013:y\u0010\u0005\u0003\u0003d\"\u0005A\u0001\u0003Bt\u0003G\u0012\rA!;\u0016\t!\u0015\u0001\u0012\u0003\u000b\u0005\u0011\u000fAY\u0001\u0006\u0003\u0004(!%\u0001BCB\u0018\u0003K\n\t\u00111\u0001\u0003r\"A1qIA3\u0001\u0004Ai\u0001\u0005\u0004\u0004\u000e\u0005%\u0003r\u0002\t\u0005\u0005GD\t\u0002\u0002\u0005\u0003h\u0006\u0015$\u0019\u0001Bu+\u0011A)\u0002c\u0007\u0015\t!]\u0001R\u0004\t\u0007\u0007\u001b\tI\u0005#\u0007\u0011\t\t\r\b2\u0004\u0003\t\u0005O\f9G1\u0001\u0003j\"A1\u0011CA4\u0001\u0004Ay\u0002\u0005\u0004\u0005$\u001d\r\u0007\u0012\u0004\u0002\u001b\u001bV$\u0018M\u00197f\'\u0016$\u0018j\u001d)be\u0006dG.\u001a7ju\u0006\u0014G.Z\u000b\u0005\u0011KAYc\u0005\u0004\u0002j\tM\u0007r\u0005\t\t\u00057\u0014i\u000e#\u000b\t.A!!1\u001dE\u0016\t!\u00119/!\u001bC\u0002\t%\bCBBL\u0011_AI#\u0003\u0003\bF\re\u0015aT:dC2\fGeY8mY\u0016\u001cG/[8oIA\f\'/\u00197mK2$3i\u001c7mK\u000e$\u0018n\u001c8D_:4XM\u001d;feN$S*\u001e;bE2,7+\u001a;JgB\u000b\'/\u00197mK2L\'0\u00192mK\u0012\"3m\u001c7m+\tA)\u0004\u0005\u0004\u0004&\"]\u0002\u0012F\u0005\u0005\u000f\u001f\u001a9+\u0001)tG\u0006d\u0017\rJ2pY2,7\r^5p]\u0012\u0002\u0018M]1mY\u0016dGeQ8mY\u0016\u001cG/[8o\u0007>tg/\u001a:uKJ\u001cH%T;uC\ndWmU3u\u0013N\u0004\u0016M]1mY\u0016d\u0017N_1cY\u0016$CeY8mY\u0002\"B\u0001#\u0010\t@A11QBA5\u0011SA\u0001b!\u0005\u0002p\u0001\u0007\u0001RG\u000b\u0003\u0011[!Baa\n\tF!Q1qFA<\u0003\u0003\u0005\rA!=\u000255+H/\u00192mKN+G/S:QCJ\fG\u000e\\3mSj\f\'\r\\3\u0011\t\r5\u00111P\n\u0005\u0003w\u0012\t\r\u0006\u0002\tJU!\u0001\u0012\u000bE,)\u0011A\u0019\u0006#\u0017\u0011\r\r\u0015\u0006r\u0007E+!\u0011\u0011\u0019\u000fc\u0016\u0005\u0011\t\u001d\u0018q\u0010b\u0001\u0005SD\u0001ba\u0012\u0002\u0000\u0001\u0007\u00012\f\t\u0007\u0007\u001b\tI\u0007#\u0016\u0016\t!}\u0003R\r\u000b\u0005\u0011CB9\u0007\u0005\u0004\u0004\u0018\"=\u00022\r\t\u0005\u0005GD)\u0007\u0002\u0005\u0003h\u0006\u0005%\u0019\u0001Bu\u0011!\u00199%!!A\u0002!%\u0004CBB\u0007\u0003SB\u0019\'\u0006\u0003\tn!UD\u0003BB\u000e\u0011_B\u0001ba\u0012\u0002\u0004\u0002\u0007\u0001\u0012\u000f\t\u0007\u0007\u001b\tI\u0007c\u001d\u0011\t\t\r\bR\u000f\u0003\t\u0005O\f\u0019I1\u0001\u0003jV!\u0001\u0012\u0010EC)\u0011AY\bc \u0015\t\r\u001d\u0002R\u0010\u0005\u000b\u0007_\t))!AA\u0002\tE\b\u0002CB$\u0003\u000b\u0003\r\u0001#!\u0011\r\r5\u0011\u0011\u000eEB!\u0011\u0011\u0019\u000f#\"\u0005\u0011\t\u001d\u0018Q\u0011b\u0001\u0005S,B\u0001##\t\u0010R!\u00012\u0012EI!\u0019\u0019i!!\u001b\t\u000eB!!1\u001dEH\t!\u00119/a\"C\u0002\t%\b\u0002CB\t\u0003\u000f\u0003\r\u0001c%\u0011\r\r\u0015\u0006r\u0007EG\u0005yiU\u000f^1cY\u0016D\u0015m\u001d5TKRL5\u000fU1sC2dW\r\\5{C\ndW-\u0006\u0003\t\u001a\"}5CBAE\u0005\'DY\n\u0005\u0005\u0003\\\nu\u0007R\u0014EQ!\u0011\u0011\u0019\u000fc(\u0005\u0011\u0015\r\u0012\u0011\u0012b\u0001\u0005S\u0004baa&\t$\"u\u0015\u0002\u0002ES\u00073\u0013!\u0002U1s\u0011\u0006\u001c\bnU3u\u0003M\u001b8-\u00197bI\r|G\u000e\\3di&|g\u000e\n9be\u0006dG.\u001a7%\u0007>dG.Z2uS>t7i\u001c8wKJ$XM]:%\u001bV$\u0018M\u00197f\u0011\u0006\u001c\bnU3u\u0013N\u0004\u0016M]1mY\u0016d\u0017N_1cY\u0016$CeY8mYV\u0011\u00012\u0016\t\u0007\u0007KCi\u000b#(\n\t!=6q\u0015\u0002\b\u0011\u0006\u001c\bnU3u\u0003Q\u001b8-\u00197bI\r|G\u000e\\3di&|g\u000e\n9be\u0006dG.\u001a7%\u0007>dG.Z2uS>t7i\u001c8wKJ$XM]:%\u001bV$\u0018M\u00197f\u0011\u0006\u001c\bnU3u\u0013N\u0004\u0016M]1mY\u0016d\u0017N_1cY\u0016$CeY8mY\u0002\"B\u0001#.\t8B11QBAE\u0011;C\u0001b!\u0005\u0002\u0010\u0002\u0007\u00012V\u000b\u0003\u0011C#Baa\n\t>\"Q1qFAL\u0003\u0003\u0005\rA!=\u0002=5+H/\u00192mK\"\u000b7\u000f[*fi&\u001b\b+\u0019:bY2,G.\u001b>bE2,\u0007\u0003BB\u0007\u00037\u001bB!a\'\u0003BR\u0011\u0001\u0012Y\u000b\u0005\u0011\u0013Dy\r\u0006\u0003\tL\"E\u0007CBBS\u0011[Ci\r\u0005\u0003\u0003d\"=G\u0001CC\u0012\u0003?\u0013\rA!;\t\u0011\r\u001d\u0013q\u0014a\u0001\u0011\'\u0004ba!\u0004\u0002\n\"5W\u0003\u0002El\u0011;$B\u0001#7\t`B11q\u0013ER\u00117\u0004BAa9\t^\u0012AQ1EAQ\u0005\u0004\u0011I\u000f\u0003\u0005\u0004H\u0005\u0005\u0006\u0019\u0001Eq!\u0019\u0019i!!#\t\\V!\u0001R\u001dEw)\u0011\u0019Y\u0002c:\t\u0011\r\u001d\u00131\u0015a\u0001\u0011S\u0004ba!\u0004\u0002\n\"-\b\u0003\u0002Br\u0011[$\u0001\"b\t\u0002$\n\u0007!\u0011^\u000b\u0005\u0011cDi\u0010\u0006\u0003\tt\"]H\u0003BB\u0014\u0011kD!ba\f\u0002&\u0006\u0005\t\u0019\u0001By\u0011!\u00199%!*A\u0002!e\bCBB\u0007\u0003\u0013CY\u0010\u0005\u0003\u0003d\"uH\u0001CC\u0012\u0003K\u0013\rA!;\u0016\t%\u0005\u0011r\u0001\u000b\u0005\u0013\u0007II\u0001\u0005\u0004\u0004\u000e\u0005%\u0015R\u0001\t\u0005\u0005GL9\u0001\u0002\u0005\u0006$\u0005\u001d&\u0019\u0001Bu\u0011!\u0019\t\"a*A\u0002%-\u0001CBBS\u0011[K)A\u0001\u0011J[6,H/\u00192mK\"\u000b7\u000f[*fi&\u001b\b+\u0019:bY2,G.\u001b>bE2,W\u0003BE\t\u0013/\u0019b!!+\u0003T&M\u0001\u0003\u0003Bn\u0005;L)\"#\u0007\u0011\t\t\r\u0018r\u0003\u0003\t\u000bG\tIK1\u0001\u0003jB1AQCE\u000e\u0013+IA\u0001#*\u0005\u0018\u0005)6oY1mC\u0012\u001aw\u000e\u001c7fGRLwN\u001c\u0013qCJ\fG\u000e\\3mI\r{G\u000e\\3di&|gnQ8om\u0016\u0014H/\u001a:tI%kW.\u001e;bE2,\u0007*Y:i\'\u0016$\u0018j\u001d)be\u0006dG.\u001a7ju\u0006\u0014G.\u001a\u0013%G>dG.\u0006\u0002\n\"A1A1EE\u0012\u0013+IA\u0001c,\u0005&\u000516oY1mC\u0012\u001aw\u000e\u001c7fGRLwN\u001c\u0013qCJ\fG\u000e\\3mI\r{G\u000e\\3di&|gnQ8om\u0016\u0014H/\u001a:tI%kW.\u001e;bE2,\u0007*Y:i\'\u0016$\u0018j\u001d)be\u0006dG.\u001a7ju\u0006\u0014G.\u001a\u0013%G>dG\u000e\t\u000b\u0005\u0013SIY\u0003\u0005\u0004\u0004\u000e\u0005%\u0016R\u0003\u0005\t\u0007#\ty\u000b1\u0001\n\"U\u0011\u0011\u0012\u0004\u000b\u0005\u0007OI\t\u0004\u0003\u0006\u00040\u0005]\u0016\u0011!a\u0001\u0005c\f\u0001%S7nkR\f\'\r\\3ICND7+\u001a;JgB\u000b\'/\u00197mK2L\'0\u00192mKB!1QBA^\'\u0011\tYL!1\u0015\u0005%UR\u0003BE\u001f\u0013\u0007\"B!c\u0010\nFA1A1EE\u0012\u0013\u0003\u0002BAa9\nD\u0011AQ1EA`\u0005\u0004\u0011I\u000f\u0003\u0005\u0004H\u0005}\u0006\u0019AE$!\u0019\u0019i!!+\nBU!\u00112JE))\u0011Ii%c\u0015\u0011\r\u0011U\u00112DE(!\u0011\u0011\u0019/#\u0015\u0005\u0011\u0015\r\u0012\u0011\u0019b\u0001\u0005SD\u0001ba\u0012\u0002B\u0002\u0007\u0011R\u000b\t\u0007\u0007\u001b\tI+c\u0014\u0016\t%e\u0013\u0012\r\u000b\u0005\u00077IY\u0006\u0003\u0005\u0004H\u0005\r\u0007\u0019AE/!\u0019\u0019i!!+\n`A!!1]E1\t!)\u0019#a1C\u0002\t%X\u0003BE3\u0013c\"B!c\u001a\nlQ!1qEE5\u0011)\u0019y#!2\u0002\u0002\u0003\u0007!\u0011\u001f\u0005\t\u0007\u000f\n)\r1\u0001\nnA11QBAU\u0013_\u0002BAa9\nr\u0011AQ1EAc\u0005\u0004\u0011I/\u0006\u0003\nv%mD\u0003BE<\u0013{\u0002ba!\u0004\u0002*&e\u0004\u0003\u0002Br\u0013w\"\u0001\"b\t\u0002H\n\u0007!\u0011\u001e\u0005\t\u0007#\t9\r1\u0001\n\u0000A1A1EE\u0012\u0013s\u00121#T1q\u0013N\u0004\u0016M]1mY\u0016d\u0017N_1cY\u0016,b!#\"\n\u0012&]5CBAe\u0005\'L9\t\u0005\u0005\u0003\\\nu\u0017\u0012REN!!\u0011\u0019-c#\n\u0010&U\u0015\u0002BEG\u0005g\u0013a\u0001V;qY\u0016\u0014\u0004\u0003\u0002Br\u0013##\u0001\"c%\u0002J\n\u0007!\u0011\u001e\u0002\u0002\u0017B!!1]EL\t!II*!3C\u0002\t%(!\u0001,\u0011\u0011\tm\u0016RTEH\u0013+KA!c(\u0003,\n1\u0001+\u0019:NCB\f\u0001j]2bY\u0006$3m\u001c7mK\u000e$\u0018n\u001c8%a\u0006\u0014\u0018\r\u001c7fY\u0012\u001au\u000e\u001c7fGRLwN\\\"p]Z,\'\u000f^3sg\u0012j\u0015\r]%t!\u0006\u0014\u0018\r\u001c7fY&T\u0018M\u00197fI\u0011\u001aw\u000e\u001c7\u0016\u0005%\u0015\u0006\u0003\u0003Bn\u0013OKy)#&\n\t%%&q\u0016\u0002\u0004\u001b\u0006\u0004\u0018!S:dC2\fGeY8mY\u0016\u001cG/[8oIA\f\'/\u00197mK2$3i\u001c7mK\u000e$\u0018n\u001c8D_:4XM\u001d;feN$S*\u00199JgB\u000b\'/\u00197mK2L\'0\u00192mK\u0012\"3m\u001c7mAQ!\u0011rVEY!!\u0019i!!3\n\u0010&U\u0005\u0002CB\t\u0003\u001f\u0004\r!#*\u0016\u0005%mE\u0003BB\u0014\u0013oC!ba\f\u0002X\u0006\u0005\t\u0019\u0001By\u0003Mi\u0015\r]%t!\u0006\u0014\u0018\r\u001c7fY&T\u0018M\u00197f!\u0011\u0019i!a7\u0014\t\u0005m\'\u0011\u0019\u000b\u0003\u0013w+b!c1\nJ&5G\u0003BEc\u0013\u001f\u0004\u0002Ba7\n(&\u001d\u00172\u001a\t\u0005\u0005GLI\r\u0002\u0005\n\u0014\u0006}\'\u0019\u0001Bu!\u0011\u0011\u0019/#4\u0005\u0011%e\u0015q\u001cb\u0001\u0005SD\u0001ba\u0012\u0002`\u0002\u0007\u0011\u0012\u001b\t\t\u0007\u001b\tI-c2\nLV1\u0011R[En\u0013?$B!c6\nbBA!1XEO\u00133Li\u000e\u0005\u0003\u0003d&mG\u0001CEJ\u0003C\u0014\rA!;\u0011\t\t\r\u0018r\u001c\u0003\t\u00133\u000b\tO1\u0001\u0003j\"A1qIAq\u0001\u0004I\u0019\u000f\u0005\u0005\u0004\u000e\u0005%\u0017\u0012\\Eo+\u0019I9/c<\ntR!11DEu\u0011!\u00199%a9A\u0002%-\b\u0003CB\u0007\u0003\u0013Li/#=\u0011\t\t\r\u0018r\u001e\u0003\t\u0013\'\u000b\u0019O1\u0001\u0003jB!!1]Ez\t!II*a9C\u0002\t%XCBE|\u0015\u0007Q9\u0001\u0006\u0003\nz&uH\u0003BB\u0014\u0013wD!ba\f\u0002f\u0006\u0005\t\u0019\u0001By\u0011!\u00199%!:A\u0002%}\b\u0003CB\u0007\u0003\u0013T\tA#\u0002\u0011\t\t\r(2\u0001\u0003\t\u0013\'\u000b)O1\u0001\u0003jB!!1\u001dF\u0004\t!II*!:C\u0002\t%XC\u0002F\u0006\u0015#Q)\u0002\u0006\u0003\u000b\u000e)]\u0001\u0003CB\u0007\u0003\u0013TyAc\u0005\u0011\t\t\r(\u0012\u0003\u0003\t\u0013\'\u000b9O1\u0001\u0003jB!!1\u001dF\u000b\t!II*a:C\u0002\t%\b\u0002CB\t\u0003O\u0004\rA#\u0007\u0011\u0011\tm\u0017r\u0015F\b\u0015\'\u0011A$S7nkR\f\'\r\\3NCBL5\u000fU1sC2dW\r\\5{C\ndW-\u0006\u0004\u000b )\u001d\"2F\n\u0007\u0003S\u0014\u0019N#\t\u0011\u0011\tm\'Q\u001cF\u0012\u0015[\u0001\u0002Ba1\n\f*\u0015\"\u0012\u0006\t\u0005\u0005GT9\u0003\u0002\u0005\n\u0014\u0006%(\u0019\u0001Bu!\u0011\u0011\u0019Oc\u000b\u0005\u0011%e\u0015\u0011\u001eb\u0001\u0005S\u0004\u0002\u0002\"\u0006\u000b0)\u0015\"\u0012F\u0005\u0005\u0013?#9\"A)tG\u0006d\u0017\rJ2pY2,7\r^5p]\u0012\u0002\u0018M]1mY\u0016dGeQ8mY\u0016\u001cG/[8o\u0007>tg/\u001a:uKJ\u001cH%S7nkR\f\'\r\\3NCBL5\u000fU1sC2dW\r\\5{C\ndW\r\n\u0013d_2dWC\u0001F\u001b!!!\u0019Cc\u000e\u000b&)%\u0012\u0002BEU\tK\t!k]2bY\u0006$3m\u001c7mK\u000e$\u0018n\u001c8%a\u0006\u0014\u0018\r\u001c7fY\u0012\u001au\u000e\u001c7fGRLwN\\\"p]Z,\'\u000f^3sg\u0012JU.\\;uC\ndW-T1q\u0013N\u0004\u0016M]1mY\u0016d\u0017N_1cY\u0016$CeY8mY\u0002\"BA#\u0010\u000b@AA1QBAu\u0015KQI\u0003\u0003\u0005\u0004\u0012\u0005=\b\u0019\u0001F\u001b+\tQi\u0003\u0006\u0003\u0004()\u0015\u0003BCB\u0018\u0003o\f\t\u00111\u0001\u0003r\u0006a\u0012*\\7vi\u0006\u0014G.Z\'ba&\u001b\b+\u0019:bY2,G.\u001b>bE2,\u0007\u0003BB\u0007\u0003w\u001cB!a?\u0003BR\u0011!\u0012J\u000b\u0007\u0015#R9Fc\u0017\u0015\t)M#R\f\t\t\tGQ9D#\u0016\u000bZA!!1\u001dF,\t!I\u0019*a@C\u0002\t%\b\u0003\u0002Br\u00157\"\u0001\"#\'\u0002\u0000\n\u0007!\u0011\u001e\u0005\t\u0007\u000f\ny\u00101\u0001\u000b`AA1QBAu\u0015+RI&\u0006\u0004\u000bd)%$R\u000e\u000b\u0005\u0015KRy\u0007\u0005\u0005\u0005\u0016)=\"r\rF6!\u0011\u0011\u0019O#\u001b\u0005\u0011%M%\u0011\u0001b\u0001\u0005S\u0004BAa9\u000bn\u0011A\u0011\u0012\u0014B\u0001\u0005\u0004\u0011I\u000f\u0003\u0005\u0004H\t\u0005\u0001\u0019\u0001F9!!\u0019i!!;\u000bh)-TC\u0002F;\u0015{R\t\t\u0006\u0003\u0004\u001c)]\u0004\u0002CB$\u0005\u0007\u0001\rA#\u001f\u0011\u0011\r5\u0011\u0011\u001eF>\u0015\u007f\u0002BAa9\u000b~\u0011A\u00112\u0013B\u0002\u0005\u0004\u0011I\u000f\u0005\u0003\u0003d*\u0005E\u0001CEM\u0005\u0007\u0011\rA!;\u0016\r)\u0015%\u0012\u0013FK)\u0011Q9Ic#\u0015\t\r\u001d\"\u0012\u0012\u0005\u000b\u0007_\u0011)!!AA\u0002\tE\b\u0002CB$\u0005\u000b\u0001\rA#$\u0011\u0011\r5\u0011\u0011\u001eFH\u0015\'\u0003BAa9\u000b\u0012\u0012A\u00112\u0013B\u0003\u0005\u0004\u0011I\u000f\u0005\u0003\u0003d*UE\u0001CEM\u0005\u000b\u0011\rA!;\u0016\r)e%r\u0014FR)\u0011QYJ#*\u0011\u0011\r5\u0011\u0011\u001eFO\u0015C\u0003BAa9\u000b \u0012A\u00112\u0013B\u0004\u0005\u0004\u0011I\u000f\u0005\u0003\u0003d*\rF\u0001CEM\u0005\u000f\u0011\rA!;\t\u0011\rE!q\u0001a\u0001\u0015O\u0003\u0002\u0002b\t\u000b8)u%\u0012\u0015\u0002\u001b\u001bV$\u0018M\u00197f\u001b\u0006\u0004\u0018j\u001d)be\u0006dG.\u001a7ju\u0006\u0014G.Z\u000b\u0007\u0015[S)L#/\u0014\r\t%!1\u001bFX!!\u0011YN!8\u000b2*m\u0006\u0003\u0003Bb\u0013\u0017S\u0019Lc.\u0011\t\t\r(R\u0017\u0003\t\u0013\'\u0013IA1\u0001\u0003jB!!1\u001dF]\t!IIJ!\u0003C\u0002\t%\b\u0003CBL\u0015{S\u0019Lc.\n\t%}5\u0011T\u0001Pg\u000e\fG.\u0019\u0013d_2dWm\u0019;j_:$\u0003/\u0019:bY2,G\u000eJ\"pY2,7\r^5p]\u000e{gN^3si\u0016\u00148\u000fJ\'vi\u0006\u0014G.Z\'ba&\u001b\b+\u0019:bY2,G.\u001b>bE2,G\u0005J2pY2,\"Ac1\u0011\u0011\r\u0015&R\u0019FZ\u0015oKA!#+\u0004(\u0006\u00016oY1mC\u0012\u001aw\u000e\u001c7fGRLwN\u001c\u0013qCJ\fG\u000e\\3mI\r{G\u000e\\3di&|gnQ8om\u0016\u0014H/\u001a:tI5+H/\u00192mK6\u000b\u0007/S:QCJ\fG\u000e\\3mSj\f\'\r\\3%I\r|G\u000e\u001c\u0011\u0015\t)-\'R\u001a\t\t\u0007\u001b\u0011IAc-\u000b8\"A1\u0011\u0003B\b\u0001\u0004Q\u0019-\u0006\u0002\u000b<R!1q\u0005Fj\u0011)\u0019yCa\u0006\u0002\u0002\u0003\u0007!\u0011_\u0001\u001b\u001bV$\u0018M\u00197f\u001b\u0006\u0004\u0018j\u001d)be\u0006dG.\u001a7ju\u0006\u0014G.\u001a\t\u0005\u0007\u001b\u0011Yb\u0005\u0003\u0003\u001c\t\u0005GC\u0001Fl+\u0019QyN#:\u000bjR!!\u0012\u001dFv!!\u0019)K#2\u000bd*\u001d\b\u0003\u0002Br\u0015K$\u0001\"c%\u0003 \t\u0007!\u0011\u001e\t\u0005\u0005GTI\u000f\u0002\u0005\n\u001a\n}!\u0019\u0001Bu\u0011!\u00199Ea\bA\u0002)5\b\u0003CB\u0007\u0005\u0013Q\u0019Oc:\u0016\r)E(r\u001fF~)\u0011Q\u0019P#@\u0011\u0011\r]%R\u0018F{\u0015s\u0004BAa9\u000bx\u0012A\u00112\u0013B\u0011\u0005\u0004\u0011I\u000f\u0005\u0003\u0003d*mH\u0001CEM\u0005C\u0011\rA!;\t\u0011\r\u001d#\u0011\u0005a\u0001\u0015\u007f\u0004\u0002b!\u0004\u0003\n)U(\u0012`\u000b\u0007\u0017\u0007YYac\u0004\u0015\t\rm1R\u0001\u0005\t\u0007\u000f\u0012\u0019\u00031\u0001\f\bAA1Q\u0002B\u0005\u0017\u0013Yi\u0001\u0005\u0003\u0003d.-A\u0001CEJ\u0005G\u0011\rA!;\u0011\t\t\r8r\u0002\u0003\t\u00133\u0013\u0019C1\u0001\u0003jV112CF\u0010\u0017G!Ba#\u0006\f\u001aQ!1qEF\f\u0011)\u0019yC!\n\u0002\u0002\u0003\u0007!\u0011\u001f\u0005\t\u0007\u000f\u0012)\u00031\u0001\f\u001cAA1Q\u0002B\u0005\u0017;Y\t\u0003\u0005\u0003\u0003d.}A\u0001CEJ\u0005K\u0011\rA!;\u0011\t\t\r82\u0005\u0003\t\u00133\u0013)C1\u0001\u0003jV11rEF\u0017\u0017c!Ba#\u000b\f4AA1Q\u0002B\u0005\u0017WYy\u0003\u0005\u0003\u0003d.5B\u0001CEJ\u0005O\u0011\rA!;\u0011\t\t\r8\u0012\u0007\u0003\t\u00133\u00139C1\u0001\u0003j\"A1\u0011\u0003B\u0014\u0001\u0004Y)\u0004\u0005\u0005\u0004&*\u001572FF\u0018\u0005\u0001JU.\\;uC\ndW\rS1tQ6\u000b\u0007/S:QCJ\fG\u000e\\3mSj\f\'\r\\3\u0016\r-m22IF$\'\u0019\u0011ICa5\f>AA!1\u001cBo\u0017\u007fYI\u0005\u0005\u0005\u0003D&-5\u0012IF#!\u0011\u0011\u0019oc\u0011\u0005\u0011%M%\u0011\u0006b\u0001\u0005S\u0004BAa9\fH\u0011A\u0011\u0012\u0014B\u0015\u0005\u0004\u0011I\u000f\u0005\u0005\u0005\u0016--3\u0012IF#\u0013\u0011Yi\u0005b\u0006\u0003\u0015A\u000b\'\u000fS1tQ6\u000b\u0007/A+tG\u0006d\u0017\rJ2pY2,7\r^5p]\u0012\u0002\u0018M]1mY\u0016dGeQ8mY\u0016\u001cG/[8o\u0007>tg/\u001a:uKJ\u001cH%S7nkR\f\'\r\\3ICNDW*\u00199JgB\u000b\'/\u00197mK2L\'0\u00192mK\u0012\"3m\u001c7m+\tY\u0019\u0006\u0005\u0005\u0005$-U3\u0012IF#\u0013\u0011Y9\u0006\"\n\u0003\u000f!\u000b7\u000f[\'ba\u000616oY1mC\u0012\u001aw\u000e\u001c7fGRLwN\u001c\u0013qCJ\fG\u000e\\3mI\r{G\u000e\\3di&|gnQ8om\u0016\u0014H/\u001a:tI%kW.\u001e;bE2,\u0007*Y:i\u001b\u0006\u0004\u0018j\u001d)be\u0006dG.\u001a7ju\u0006\u0014G.\u001a\u0013%G>dG\u000e\t\u000b\u0005\u0017;Zy\u0006\u0005\u0005\u0004\u000e\t%2\u0012IF#\u0011!\u0019\tBa\fA\u0002-MSCAF%)\u0011\u00199c#\u001a\t\u0015\r=\"qGA\u0001\u0002\u0004\u0011\t0\u0001\u0011J[6,H/\u00192mK\"\u000b7\u000f[\'ba&\u001b\b+\u0019:bY2,G.\u001b>bE2,\u0007\u0003BB\u0007\u0005w\u0019BAa\u000f\u0003BR\u00111\u0012N\u000b\u0007\u0017cZ9hc\u001f\u0015\t-M4R\u0010\t\t\tGY)f#\u001e\fzA!!1]F<\t!I\u0019Ja\u0010C\u0002\t%\b\u0003\u0002Br\u0017w\"\u0001\"#\'\u0003@\t\u0007!\u0011\u001e\u0005\t\u0007\u000f\u0012y\u00041\u0001\f\u0000AA1Q\u0002B\u0015\u0017kZI(\u0006\u0004\f\u0004.%5R\u0012\u000b\u0005\u0017\u000b[y\t\u0005\u0005\u0005\u0016--3rQFF!\u0011\u0011\u0019o##\u0005\u0011%M%\u0011\tb\u0001\u0005S\u0004BAa9\f\u000e\u0012A\u0011\u0012\u0014B!\u0005\u0004\u0011I\u000f\u0003\u0005\u0004H\t\u0005\u0003\u0019AFI!!\u0019iA!\u000b\f\b.-UCBFK\u0017;[\t\u000b\u0006\u0003\u0004\u001c-]\u0005\u0002CB$\u0005\u0007\u0002\ra#\'\u0011\u0011\r5!\u0011FFN\u0017?\u0003BAa9\f\u001e\u0012A\u00112\u0013B\"\u0005\u0004\u0011I\u000f\u0005\u0003\u0003d.\u0005F\u0001CEM\u0005\u0007\u0012\rA!;\u0016\r-\u00156\u0012WF[)\u0011Y9kc+\u0015\t\r\u001d2\u0012\u0016\u0005\u000b\u0007_\u0011)%!AA\u0002\tE\b\u0002CB$\u0005\u000b\u0002\ra#,\u0011\u0011\r5!\u0011FFX\u0017g\u0003BAa9\f2\u0012A\u00112\u0013B#\u0005\u0004\u0011I\u000f\u0005\u0003\u0003d.UF\u0001CEM\u0005\u000b\u0012\rA!;\u0016\r-e6rXFb)\u0011YYl#2\u0011\u0011\r5!\u0011FF_\u0017\u0003\u0004BAa9\f@\u0012A\u00112\u0013B$\u0005\u0004\u0011I\u000f\u0005\u0003\u0003d.\rG\u0001CEM\u0005\u000f\u0012\rA!;\t\u0011\rE!q\ta\u0001\u0017\u000f\u0004\u0002\u0002b\t\fV-u6\u0012\u0019\u0002\u001f\u001bV$\u0018M\u00197f\u0011\u0006\u001c\b.T1q\u0013N\u0004\u0016M]1mY\u0016d\u0017N_1cY\u0016,ba#4\fV.e7C\u0002B%\u0005\'\\y\r\u0005\u0005\u0003\\\nu7\u0012[Fn!!\u0011\u0019-c#\fT.]\u0007\u0003\u0002Br\u0017+$\u0001\"c%\u0003J\t\u0007!\u0011\u001e\t\u0005\u0005G\\I\u000e\u0002\u0005\n\u001a\n%#\u0019\u0001Bu!!\u00199j#8\fT.]\u0017\u0002BF\'\u00073\u000b1k]2bY\u0006$3m\u001c7mK\u000e$\u0018n\u001c8%a\u0006\u0014\u0018\r\u001c7fY\u0012\u001au\u000e\u001c7fGRLwN\\\"p]Z,\'\u000f^3sg\u0012jU\u000f^1cY\u0016D\u0015m\u001d5NCBL5\u000fU1sC2dW\r\\5{C\ndW\r\n\u0013d_2dWCAFr!!\u0019)k#:\fT.]\u0017\u0002BF,\u0007O\u000bAk]2bY\u0006$3m\u001c7mK\u000e$\u0018n\u001c8%a\u0006\u0014\u0018\r\u001c7fY\u0012\u001au\u000e\u001c7fGRLwN\\\"p]Z,\'\u000f^3sg\u0012jU\u000f^1cY\u0016D\u0015m\u001d5NCBL5\u000fU1sC2dW\r\\5{C\ndW\r\n\u0013d_2d\u0007\u0005\u0006\u0003\fl.5\b\u0003CB\u0007\u0005\u0013Z\u0019nc6\t\u0011\rE!q\na\u0001\u0017G,\"ac7\u0015\t\r\u001d22\u001f\u0005\u000b\u0007_\u00119&!AA\u0002\tE\u0018AH\'vi\u0006\u0014G.\u001a%bg\"l\u0015\r]%t!\u0006\u0014\u0018\r\u001c7fY&T\u0018M\u00197f!\u0011\u0019iAa\u0017\u0014\t\tm#\u0011\u0019\u000b\u0003\u0017o,bac@\r\u00061%A\u0003\u0002G\u0001\u0019\u0017\u0001\u0002b!*\ff2\rAr\u0001\t\u0005\u0005Gd)\u0001\u0002\u0005\n\u0014\n}#\u0019\u0001Bu!\u0011\u0011\u0019\u000f$\u0003\u0005\u0011%e%q\fb\u0001\u0005SD\u0001ba\u0012\u0003`\u0001\u0007AR\u0002\t\t\u0007\u001b\u0011I\u0005d\u0001\r\bU1A\u0012\u0003G\f\u00197!B\u0001d\u0005\r\u001eAA1qSFo\u0019+aI\u0002\u0005\u0003\u0003d2]A\u0001CEJ\u0005C\u0012\rA!;\u0011\t\t\rH2\u0004\u0003\t\u00133\u0013\tG1\u0001\u0003j\"A1q\tB1\u0001\u0004ay\u0002\u0005\u0005\u0004\u000e\t%CR\u0003G\r+\u0019a\u0019\u0003d\u000b\r0Q!11\u0004G\u0013\u0011!\u00199Ea\u0019A\u00021\u001d\u0002\u0003CB\u0007\u0005\u0013bI\u0003$\f\u0011\t\t\rH2\u0006\u0003\t\u0013\'\u0013\u0019G1\u0001\u0003jB!!1\u001dG\u0018\t!IIJa\u0019C\u0002\t%XC\u0002G\u001a\u0019\u007fa\u0019\u0005\u0006\u0003\r61eB\u0003BB\u0014\u0019oA!ba\f\u0003f\u0005\u0005\t\u0019\u0001By\u0011!\u00199E!\u001aA\u00021m\u0002\u0003CB\u0007\u0005\u0013bi\u0004$\u0011\u0011\t\t\rHr\b\u0003\t\u0013\'\u0013)G1\u0001\u0003jB!!1\u001dG\"\t!IIJ!\u001aC\u0002\t%XC\u0002G$\u0019\u001bb\t\u0006\u0006\u0003\rJ1M\u0003\u0003CB\u0007\u0005\u0013bY\u0005d\u0014\u0011\t\t\rHR\n\u0003\t\u0013\'\u00139G1\u0001\u0003jB!!1\u001dG)\t!IIJa\u001aC\u0002\t%\b\u0002CB\t\u0005O\u0002\r\u0001$\u0016\u0011\u0011\r\u00156R\u001dG&\u0019\u001f\u0012\u0011eQ8oGV\u0014(/\u001a8u)JLW-T1q\u0013N\u0004\u0016M]1mY\u0016d\u0017N_1cY\u0016,b\u0001d\u0017\rd1\u001d4C\u0002B5\u0005\'di\u0006\u0005\u0005\u0003\\\nuGr\fG5!!\u0011\u0019-c#\rb1\u0015\u0004\u0003\u0002Br\u0019G\"\u0001\"c%\u0003j\t\u0007!\u0011\u001e\t\u0005\u0005Gd9\u0007\u0002\u0005\n\u001a\n%$\u0019\u0001Bu!!\u00199\nd\u001b\rb1\u0015\u0014\u0002\u0002G7\u00073\u0013!\u0002U1s)JLW-T1q\u0003Y\u001b8-\u00197bI\r|G\u000e\\3di&|g\u000e\n9be\u0006dG.\u001a7%\u0007>dG.Z2uS>t7i\u001c8wKJ$XM]:%\u0007>t7-\u001e:sK:$HK]5f\u001b\u0006\u0004\u0018j\u001d)be\u0006dG.\u001a7ju\u0006\u0014G.\u001a\u0013%G>dG.\u0006\u0002\rtAAAR\u000fG>\u0019Cb)\'\u0004\u0002\rx)!A\u0012\u0010BX\u0003)\u0019wN\\2veJ,g\u000e^\u0005\u0005\u0019{b9HA\u0004Ue&,W*\u00199\u0002/N\u001c\u0017\r\\1%G>dG.Z2uS>tG\u0005]1sC2dW\r\u001c\u0013D_2dWm\u0019;j_:\u001cuN\u001c<feR,\'o\u001d\u0013D_:\u001cWO\u001d:f]R$&/[3NCBL5\u000fU1sC2dW\r\\5{C\ndW\r\n\u0013d_2d\u0007\u0005\u0006\u0003\r\u00042\u0015\u0005\u0003CB\u0007\u0005Sb\t\u0007$\u001a\t\u0011\rE!q\u000ea\u0001\u0019g*\"\u0001$\u001b\u0015\t\r\u001dB2\u0012\u0005\u000b\u0007_\u00119(!AA\u0002\tE\u0018!I\"p]\u000e,(O]3oiR\u0013\u0018.Z\'ba&\u001b\b+\u0019:bY2,G.\u001b>bE2,\u0007\u0003BB\u0007\u0005w\u001aBAa\u001f\u0003BR\u0011ArR\u000b\u0007\u0019/ci\n$)\u0015\t1eE2\u0015\t\t\u0019kbY\bd\'\r B!!1\u001dGO\t!I\u0019Ja C\u0002\t%\b\u0003\u0002Br\u0019C#\u0001\"#\'\u0003\u0000\t\u0007!\u0011\u001e\u0005\t\u0007\u000f\u0012y\b1\u0001\r&BA1Q\u0002B5\u00197cy*\u0006\u0004\r*2=F2\u0017\u000b\u0005\u0019Wc)\f\u0005\u0005\u0004\u00182-DR\u0016GY!\u0011\u0011\u0019\u000fd,\u0005\u0011%M%\u0011\u0011b\u0001\u0005S\u0004BAa9\r4\u0012A\u0011\u0012\u0014BA\u0005\u0004\u0011I\u000f\u0003\u0005\u0004H\t\u0005\u0005\u0019\u0001G\\!!\u0019iA!\u001b\r.2EVC\u0002G^\u0019\u0007d9\r\u0006\u0003\u0004\u001c1u\u0006\u0002CB$\u0005\u0007\u0003\r\u0001d0\u0011\u0011\r5!\u0011\u000eGa\u0019\u000b\u0004BAa9\rD\u0012A\u00112\u0013BB\u0005\u0004\u0011I\u000f\u0005\u0003\u0003d2\u001dG\u0001CEM\u0005\u0007\u0013\rA!;\u0016\r1-Gr\u001bGn)\u0011ai\r$5\u0015\t\r\u001dBr\u001a\u0005\u000b\u0007_\u0011))!AA\u0002\tE\b\u0002CB$\u0005\u000b\u0003\r\u0001d5\u0011\u0011\r5!\u0011\u000eGk\u00193\u0004BAa9\rX\u0012A\u00112\u0013BC\u0005\u0004\u0011I\u000f\u0005\u0003\u0003d2mG\u0001CEM\u0005\u000b\u0013\rA!;\u0016\r1}GR\u001dGu)\u0011a\t\u000fd;\u0011\u0011\r5!\u0011\u000eGr\u0019O\u0004BAa9\rf\u0012A\u00112\u0013BD\u0005\u0004\u0011I\u000f\u0005\u0003\u0003d2%H\u0001CEM\u0005\u000f\u0013\rA!;\t\u0011\rE!q\u0011a\u0001\u0019[\u0004\u0002\u0002$\u001e\r|1\rHr\u001d\u0002\u0016\u0003J\u0014\u0018-_%t!\u0006\u0014\u0018\r\u001c7fY&T\u0018M\u00197f+\u0011a\u0019\u0010$?\u0014\r\t%%1\u001bG{!!\u0011YN!8\rx2m\b\u0003\u0002Br\u0019s$\u0001\"b\t\u0003\n\n\u0007!\u0011\u001e\t\u0007\u0007/+9\u0003d>\u0002\u000fN\u001c\u0017\r\\1%G>dG.Z2uS>tG\u0005]1sC2dW\r\u001c\u0013D_2dWm\u0019;j_:\u001cuN\u001c<feR,\'o\u001d\u0013BeJ\f\u00170S:QCJ\fG\u000e\\3mSj\f\'\r\\3%I\u0005,\"!$\u0001\u0011\r\t\rW2\u0001G|\u0013\u0011i)Aa-\u0003\u000b\u0005\u0013(/Y=\u0002\u0011N\u001c\u0017\r\\1%G>dG.Z2uS>tG\u0005]1sC2dW\r\u001c\u0013D_2dWm\u0019;j_:\u001cuN\u001c<feR,\'o\u001d\u0013BeJ\f\u00170S:QCJ\fG\u000e\\3mSj\f\'\r\\3%I\u0005\u0004C\u0003BG\u0006\u001b\u001b\u0001ba!\u0004\u0003\n2]\b\u0002CG\b\u0005\u001f\u0003\r!$\u0001\u0002\u0003\u0005,\"!d\u0005\u0011\r\r\u0015V\u0011\u0007G|+\taY\u0010\u0006\u0003\u0004(5e\u0001BCB\u0018\u0005/\u000b\t\u00111\u0001\u0003r\u0006)\u0012I\u001d:bs&\u001b\b+\u0019:bY2,G.\u001b>bE2,\u0007\u0003BB\u0007\u00057\u001bBAa\'\u0003BR\u0011QRD\u000b\u0005\u001bKiY\u0003\u0006\u0003\u000e(55\u0002CBBS\u000bciI\u0003\u0005\u0003\u0003d6-B\u0001CC\u0012\u0005?\u0013\rA!;\t\u0011\r\u001d#q\u0014a\u0001\u001b_\u0001ba!\u0004\u0003\n6%R\u0003BG\u001a\u001bs!B!$\u000e\u000e<A11qSC\u0014\u001bo\u0001BAa9\u000e:\u0011AQ1\u0005BQ\u0005\u0004\u0011I\u000f\u0003\u0005\u0004H\t\u0005\u0006\u0019AG\u001f!\u0019\u0019iA!#\u000e8U!Q\u0012IG%)\u0011\u0019Y\"d\u0011\t\u0011\r\u001d#1\u0015a\u0001\u001b\u000b\u0002ba!\u0004\u0003\n6\u001d\u0003\u0003\u0002Br\u001b\u0013\"\u0001\"b\t\u0003$\n\u0007!\u0011^\u000b\u0005\u001b\u001bjI\u0006\u0006\u0003\u000eP5MC\u0003BB\u0014\u001b#B!ba\f\u0003&\u0006\u0005\t\u0019\u0001By\u0011!\u00199E!*A\u00025U\u0003CBB\u0007\u0005\u0013k9\u0006\u0005\u0003\u0003d6eC\u0001CC\u0012\u0005K\u0013\rA!;\u0016\t5uS2\r\u000b\u0005\u001b?j)\u0007\u0005\u0004\u0004\u000e\t%U\u0012\r\t\u0005\u0005Gl\u0019\u0007\u0002\u0005\u0006$\t\u001d&\u0019\u0001Bu\u0011!iyAa*A\u00025\u001d\u0004C\u0002Bb\u001b\u0007i\t\u0007"
    )
  ScalaSig: length = 0x3 (unknown attribute)
   05 02 00
