Classfile /Users/mw/Projects/slang-braindump/.jar/jar11/assemble/slang-braindump/assemble/content/scala/collection/parallel/ForkJoinTasks$.class
  Last modified May 29, 2022; size 963 bytes
  SHA-256 checksum b8ab3bfb337cacd392b54a7ab2472fe4fa604ecc7d1233e7ccc1ea35bbc4a7dd
  Compiled from "Tasks.scala"
public final class scala.collection.parallel.ForkJoinTasks$
  minor version: 0
  major version: 52
  flags: (0x0031) ACC_PUBLIC, ACC_FINAL, ACC_SUPER
  this_class: #2                          // scala/collection/parallel/ForkJoinTasks$
  super_class: #4                         // java/lang/Object
  interfaces: 0, fields: 3, methods: 4, attributes: 3
Constant pool:
   #1 = Utf8               scala/collection/parallel/ForkJoinTasks$
   #2 = Class              #1             // scala/collection/parallel/ForkJoinTasks$
   #3 = Utf8               java/lang/Object
   #4 = Class              #3             // java/lang/Object
   #5 = Utf8               Tasks.scala
   #6 = Utf8               MODULE$
   #7 = Utf8               Lscala/collection/parallel/ForkJoinTasks$;
   #8 = Utf8               defaultForkJoinPool
   #9 = Utf8               Ljava/util/concurrent/ForkJoinPool;
  #10 = Utf8               bitmap$0
  #11 = Utf8               Z
  #12 = Utf8               <clinit>
  #13 = Utf8               ()V
  #14 = Utf8               <init>
  #15 = NameAndType        #14:#13        // "<init>":()V
  #16 = Methodref          #2.#15         // scala/collection/parallel/ForkJoinTasks$."<init>":()V
  #17 = NameAndType        #6:#7          // MODULE$:Lscala/collection/parallel/ForkJoinTasks$;
  #18 = Fieldref           #2.#17         // scala/collection/parallel/ForkJoinTasks$.MODULE$:Lscala/collection/parallel/ForkJoinTasks$;
  #19 = Utf8               defaultForkJoinPool$lzycompute
  #20 = Utf8               ()Ljava/util/concurrent/ForkJoinPool;
  #21 = NameAndType        #10:#11        // bitmap$0:Z
  #22 = Fieldref           #2.#21         // scala/collection/parallel/ForkJoinTasks$.bitmap$0:Z
  #23 = Utf8               java/util/concurrent/ForkJoinPool
  #24 = Class              #23            // java/util/concurrent/ForkJoinPool
  #25 = Utf8               commonPool
  #26 = NameAndType        #25:#20        // commonPool:()Ljava/util/concurrent/ForkJoinPool;
  #27 = Methodref          #24.#26        // java/util/concurrent/ForkJoinPool.commonPool:()Ljava/util/concurrent/ForkJoinPool;
  #28 = NameAndType        #8:#9          // defaultForkJoinPool:Ljava/util/concurrent/ForkJoinPool;
  #29 = Fieldref           #2.#28         // scala/collection/parallel/ForkJoinTasks$.defaultForkJoinPool:Ljava/util/concurrent/ForkJoinPool;
  #30 = Utf8               this
  #31 = Utf8               java/lang/Throwable
  #32 = Class              #31            // java/lang/Throwable
  #33 = NameAndType        #19:#20        // defaultForkJoinPool$lzycompute:()Ljava/util/concurrent/ForkJoinPool;
  #34 = Methodref          #2.#33         // scala/collection/parallel/ForkJoinTasks$.defaultForkJoinPool$lzycompute:()Ljava/util/concurrent/ForkJoinPool;
  #35 = Methodref          #4.#15         // java/lang/Object."<init>":()V
  #36 = Utf8               Code
  #37 = Utf8               LineNumberTable
  #38 = Utf8               StackMapTable
  #39 = Utf8               LocalVariableTable
  #40 = Utf8               SourceFile
  #41 = Utf8               ScalaInlineInfo
  #42 = Utf8               Scala
{
  public static final scala.collection.parallel.ForkJoinTasks$ MODULE$;
    descriptor: Lscala/collection/parallel/ForkJoinTasks$;
    flags: (0x0019) ACC_PUBLIC, ACC_STATIC, ACC_FINAL

  private static java.util.concurrent.ForkJoinPool defaultForkJoinPool;
    descriptor: Ljava/util/concurrent/ForkJoinPool;
    flags: (0x000a) ACC_PRIVATE, ACC_STATIC

  private static volatile boolean bitmap$0;
    descriptor: Z
    flags: (0x004a) ACC_PRIVATE, ACC_STATIC, ACC_VOLATILE

  public static {};
    descriptor: ()V
    flags: (0x0009) ACC_PUBLIC, ACC_STATIC
    Code:
      stack=2, locals=0, args_size=0
         0: new           #2                  // class scala/collection/parallel/ForkJoinTasks$
         3: dup
         4: invokespecial #16                 // Method "<init>":()V
         7: putstatic     #18                 // Field MODULE$:Lscala/collection/parallel/ForkJoinTasks$;
        10: return
      LineNumberTable:
        line 296: 0

  private java.util.concurrent.ForkJoinPool defaultForkJoinPool$lzycompute();
    descriptor: ()Ljava/util/concurrent/ForkJoinPool;
    flags: (0x0002) ACC_PRIVATE
    Code:
      stack=2, locals=2, args_size=1
         0: aload_0
         1: dup
         2: astore_1
         3: monitorenter
         4: getstatic     #22                 // Field bitmap$0:Z
         7: ifne          20
        10: invokestatic  #27                 // Method java/util/concurrent/ForkJoinPool.commonPool:()Ljava/util/concurrent/ForkJoinPool;
        13: putstatic     #29                 // Field defaultForkJoinPool:Ljava/util/concurrent/ForkJoinPool;
        16: iconst_1
        17: putstatic     #22                 // Field bitmap$0:Z
        20: aload_1
        21: monitorexit
        22: goto          28
        25: aload_1
        26: monitorexit
        27: athrow
        28: getstatic     #29                 // Field defaultForkJoinPool:Ljava/util/concurrent/ForkJoinPool;
        31: areturn
      Exception table:
         from    to  target type
             4    20    25   any
      StackMapTable: number_of_entries = 3
        frame_type = 252 /* append */
          offset_delta = 20
          locals = [ class scala/collection/parallel/ForkJoinTasks$ ]
        frame_type = 68 /* same_locals_1_stack_item */
          stack = [ class java/lang/Throwable ]
        frame_type = 2 /* same */
      LineNumberTable:
        line 297: 0
      LocalVariableTable:
        Start  Length  Slot  Name   Signature
            0      32     0  this   Lscala/collection/parallel/ForkJoinTasks$;

  public java.util.concurrent.ForkJoinPool defaultForkJoinPool();
    descriptor: ()Ljava/util/concurrent/ForkJoinPool;
    flags: (0x0001) ACC_PUBLIC
    Code:
      stack=1, locals=1, args_size=1
         0: getstatic     #22                 // Field bitmap$0:Z
         3: ifne          13
         6: aload_0
         7: invokespecial #34                 // Method defaultForkJoinPool$lzycompute:()Ljava/util/concurrent/ForkJoinPool;
        10: goto          16
        13: getstatic     #29                 // Field defaultForkJoinPool:Ljava/util/concurrent/ForkJoinPool;
        16: areturn
      StackMapTable: number_of_entries = 2
        frame_type = 13 /* same */
        frame_type = 66 /* same_locals_1_stack_item */
          stack = [ class java/util/concurrent/ForkJoinPool ]
      LineNumberTable:
        line 297: 0
      LocalVariableTable:
        Start  Length  Slot  Name   Signature
            0      17     0  this   Lscala/collection/parallel/ForkJoinTasks$;

  private scala.collection.parallel.ForkJoinTasks$();
    descriptor: ()V
    flags: (0x0002) ACC_PRIVATE
    Code:
      stack=1, locals=1, args_size=1
         0: aload_0
         1: invokespecial #35                 // Method java/lang/Object."<init>":()V
         4: return
      LineNumberTable:
        line 302: 0
        line 296: 4
      LocalVariableTable:
        Start  Length  Slot  Name   Signature
            0       5     0  this   Lscala/collection/parallel/ForkJoinTasks$;
}
SourceFile: "Tasks.scala"
  ScalaInlineInfo: length = 0x13 (unknown attribute)
   01 01 00 03 00 0E 00 0D 01 00 08 00 14 01 00 13
   00 14 01
  Scala: length = 0x0 (unknown attribute)

