Classfile /Users/mw/Projects/slang-braindump/.jar/jar11/assemble/slang-braindump/assemble/content/scala/collection/parallel/FutureTasks$$anonfun$compute$1$1.class
  Last modified May 29, 2022; size 2889 bytes
  SHA-256 checksum b96a6334e5fc8b335a395f651999f59c44d427018a1046436ab46dc7920ec287
  Compiled from "Tasks.scala"
public final class scala.collection.parallel.FutureTasks$$anonfun$compute$1$1 extends scala.runtime.AbstractPartialFunction<scala.util.Try<scala.collection.parallel.Task<R, Tp>>, scala.runtime.BoxedUnit> implements java.io.Serializable
  minor version: 0
  major version: 52
  flags: (0x0031) ACC_PUBLIC, ACC_FINAL, ACC_SUPER
  this_class: #2                          // scala/collection/parallel/FutureTasks$$anonfun$compute$1$1
  super_class: #5                         // scala/runtime/AbstractPartialFunction
  interfaces: 1, fields: 2, methods: 5, attributes: 6
Constant pool:
    #1 = Utf8               scala/collection/parallel/FutureTasks$$anonfun$compute$1$1
    #2 = Class              #1            // scala/collection/parallel/FutureTasks$$anonfun$compute$1$1
    #3 = Utf8               Lscala/runtime/AbstractPartialFunction<Lscala/util/Try<Lscala/collection/parallel/Task<TR;TTp;>;>;Lscala/runtime/BoxedUnit;>;Ljava/io/Serializable;
    #4 = Utf8               scala/runtime/AbstractPartialFunction
    #5 = Class              #4            // scala/runtime/AbstractPartialFunction
    #6 = Utf8               java/io/Serializable
    #7 = Class              #6            // java/io/Serializable
    #8 = Utf8               Tasks.scala
    #9 = Utf8               scala/collection/parallel/FutureTasks
   #10 = Class              #9            // scala/collection/parallel/FutureTasks
   #11 = Utf8               compute$1
   #12 = Utf8               (Lscala/collection/parallel/Task;ILscala/concurrent/ExecutionContext;)Lscala/concurrent/Future;
   #13 = NameAndType        #11:#12       // compute$1:(Lscala/collection/parallel/Task;ILscala/concurrent/ExecutionContext;)Lscala/concurrent/Future;
   #14 = Utf8               serialVersionUID
   #15 = Utf8               J
   #16 = Long               0l
   #18 = Utf8               task$1
   #19 = Utf8               Lscala/collection/parallel/Task;
   #20 = Utf8               applyOrElse
   #21 = Utf8               (Lscala/util/Try;Lscala/Function1;)Ljava/lang/Object;
   #22 = Utf8               <A1:Lscala/util/Try<Lscala/collection/parallel/Task<TR;TTp;>;>;B1:Ljava/lang/Object;>(TA1;Lscala/Function1<TA1;TB1;>;)TB1;
   #23 = Utf8               x1
   #24 = Utf8               default
   #25 = Utf8               scala/util/Success
   #26 = Class              #25           // scala/util/Success
   #27 = Utf8               value
   #28 = Utf8               ()Ljava/lang/Object;
   #29 = NameAndType        #27:#28       // value:()Ljava/lang/Object;
   #30 = Methodref          #26.#29       // scala/util/Success.value:()Ljava/lang/Object;
   #31 = Utf8               scala/collection/parallel/Task
   #32 = Class              #31           // scala/collection/parallel/Task
   #33 = NameAndType        #18:#19       // task$1:Lscala/collection/parallel/Task;
   #34 = Fieldref           #2.#33        // scala/collection/parallel/FutureTasks$$anonfun$compute$1$1.task$1:Lscala/collection/parallel/Task;
   #35 = Utf8               throwable
   #36 = Utf8               ()Ljava/lang/Throwable;
   #37 = NameAndType        #35:#36       // throwable:()Ljava/lang/Throwable;
   #38 = InterfaceMethodref #32.#37       // scala/collection/parallel/Task.throwable:()Ljava/lang/Throwable;
   #39 = Utf8               throwable_$eq
   #40 = Utf8               (Ljava/lang/Throwable;)V
   #41 = NameAndType        #39:#40       // throwable_$eq:(Ljava/lang/Throwable;)V
   #42 = InterfaceMethodref #32.#41       // scala/collection/parallel/Task.throwable_$eq:(Ljava/lang/Throwable;)V
   #43 = Utf8               result
   #44 = NameAndType        #43:#28       // result:()Ljava/lang/Object;
   #45 = InterfaceMethodref #32.#44       // scala/collection/parallel/Task.result:()Ljava/lang/Object;
   #46 = Utf8               result_$eq
   #47 = Utf8               (Ljava/lang/Object;)V
   #48 = NameAndType        #46:#47       // result_$eq:(Ljava/lang/Object;)V
   #49 = InterfaceMethodref #32.#48       // scala/collection/parallel/Task.result_$eq:(Ljava/lang/Object;)V
   #50 = Utf8               scala/runtime/BoxedUnit
   #51 = Class              #50           // scala/runtime/BoxedUnit
   #52 = Utf8               UNIT
   #53 = Utf8               Lscala/runtime/BoxedUnit;
   #54 = NameAndType        #52:#53       // UNIT:Lscala/runtime/BoxedUnit;
   #55 = Fieldref           #51.#54       // scala/runtime/BoxedUnit.UNIT:Lscala/runtime/BoxedUnit;
   #56 = Utf8               scala/util/Failure
   #57 = Class              #56           // scala/util/Failure
   #58 = Utf8               exception
   #59 = NameAndType        #58:#36       // exception:()Ljava/lang/Throwable;
   #60 = Methodref          #57.#59       // scala/util/Failure.exception:()Ljava/lang/Throwable;
   #61 = Utf8               scala/Function1
   #62 = Class              #61           // scala/Function1
   #63 = Utf8               apply
   #64 = Utf8               (Ljava/lang/Object;)Ljava/lang/Object;
   #65 = NameAndType        #63:#64       // apply:(Ljava/lang/Object;)Ljava/lang/Object;
   #66 = InterfaceMethodref #62.#65       // scala/Function1.apply:(Ljava/lang/Object;)Ljava/lang/Object;
   #67 = Utf8               firstTask
   #68 = Utf8               Ljava/lang/Throwable;
   #69 = Utf8               this
   #70 = Utf8               Lscala/collection/parallel/FutureTasks$$anonfun$compute$1$1;
   #71 = Utf8               Lscala/util/Try;
   #72 = Utf8               Lscala/Function1;
   #73 = Utf8               scala/util/Try
   #74 = Class              #73           // scala/util/Try
   #75 = Utf8               java/lang/Object
   #76 = Class              #75           // java/lang/Object
   #77 = Utf8               isDefinedAt
   #78 = Utf8               (Lscala/util/Try;)Z
   #79 = Utf8               (Lscala/util/Try<Lscala/collection/parallel/Task<TR;TTp;>;>;)Z
   #80 = Utf8               (Ljava/lang/Object;)Z
   #81 = Utf8               x
   #82 = NameAndType        #77:#78       // isDefinedAt:(Lscala/util/Try;)Z
   #83 = Methodref          #2.#82        // scala/collection/parallel/FutureTasks$$anonfun$compute$1$1.isDefinedAt:(Lscala/util/Try;)Z
   #84 = Utf8               Ljava/lang/Object;
   #85 = Utf8               (Ljava/lang/Object;Lscala/Function1;)Ljava/lang/Object;
   #86 = NameAndType        #20:#21       // applyOrElse:(Lscala/util/Try;Lscala/Function1;)Ljava/lang/Object;
   #87 = Methodref          #2.#86        // scala/collection/parallel/FutureTasks$$anonfun$compute$1$1.applyOrElse:(Lscala/util/Try;Lscala/Function1;)Ljava/lang/Object;
   #88 = Utf8               <init>
   #89 = Utf8               (Lscala/collection/parallel/FutureTasks;Lscala/collection/parallel/Task;)V
   #90 = Utf8               $outer
   #91 = Utf8               ()V
   #92 = NameAndType        #88:#91       // "<init>":()V
   #93 = Methodref          #5.#92        // scala/runtime/AbstractPartialFunction."<init>":()V
   #94 = Utf8               Lscala/collection/parallel/FutureTasks;
   #95 = Utf8               ConstantValue
   #96 = Utf8               Code
   #97 = Utf8               StackMapTable
   #98 = Utf8               LineNumberTable
   #99 = Utf8               LocalVariableTable
  #100 = Utf8               Signature
  #101 = Utf8               MethodParameters
  #102 = Utf8               InnerClasses
  #103 = Utf8               EnclosingMethod
  #104 = Utf8               SourceFile
  #105 = Utf8               ScalaInlineInfo
  #106 = Utf8               Scala
{
  private static final long serialVersionUID;
    descriptor: J
    flags: (0x001a) ACC_PRIVATE, ACC_STATIC, ACC_FINAL
    ConstantValue: long 0l

  private final scala.collection.parallel.Task task$1;
    descriptor: Lscala/collection/parallel/Task;
    flags: (0x0012) ACC_PRIVATE, ACC_FINAL

  public final <A1 extends scala.util.Try<scala.collection.parallel.Task<R, Tp>>, B1 extends java.lang.Object> B1 applyOrElse(A1, scala.Function1<A1, B1>);
    descriptor: (Lscala/util/Try;Lscala/Function1;)Ljava/lang/Object;
    flags: (0x0011) ACC_PUBLIC, ACC_FINAL
    Code:
      stack=2, locals=9, args_size=3
         0: aload_1
         1: astore        4
         3: aload         4
         5: instanceof    #26                 // class scala/util/Success
         8: ifeq          67
        11: aload         4
        13: checkcast     #26                 // class scala/util/Success
        16: astore        5
        18: aload         5
        20: invokevirtual #30                 // Method scala/util/Success.value:()Ljava/lang/Object;
        23: checkcast     #32                 // class scala/collection/parallel/Task
        26: astore        6
        28: aload_0
        29: getfield      #34                 // Field task$1:Lscala/collection/parallel/Task;
        32: aload         6
        34: invokeinterface #38,  1           // InterfaceMethod scala/collection/parallel/Task.throwable:()Ljava/lang/Throwable;
        39: invokeinterface #42,  2           // InterfaceMethod scala/collection/parallel/Task.throwable_$eq:(Ljava/lang/Throwable;)V
        44: aload_0
        45: getfield      #34                 // Field task$1:Lscala/collection/parallel/Task;
        48: aload         6
        50: invokeinterface #45,  1           // InterfaceMethod scala/collection/parallel/Task.result:()Ljava/lang/Object;
        55: invokeinterface #49,  2           // InterfaceMethod scala/collection/parallel/Task.result_$eq:(Ljava/lang/Object;)V
        60: getstatic     #55                 // Field scala/runtime/BoxedUnit.UNIT:Lscala/runtime/BoxedUnit;
        63: astore_3
        64: goto          124
        67: goto          70
        70: aload         4
        72: instanceof    #57                 // class scala/util/Failure
        75: ifeq          110
        78: aload         4
        80: checkcast     #57                 // class scala/util/Failure
        83: astore        7
        85: aload         7
        87: invokevirtual #60                 // Method scala/util/Failure.exception:()Ljava/lang/Throwable;
        90: astore        8
        92: aload_0
        93: getfield      #34                 // Field task$1:Lscala/collection/parallel/Task;
        96: aload         8
        98: invokeinterface #42,  2           // InterfaceMethod scala/collection/parallel/Task.throwable_$eq:(Ljava/lang/Throwable;)V
       103: getstatic     #55                 // Field scala/runtime/BoxedUnit.UNIT:Lscala/runtime/BoxedUnit;
       106: astore_3
       107: goto          124
       110: goto          113
       113: aload_2
       114: aload_1
       115: invokeinterface #66,  2           // InterfaceMethod scala/Function1.apply:(Ljava/lang/Object;)Ljava/lang/Object;
       120: astore_3
       121: goto          124
       124: aload_3
       125: areturn
      StackMapTable: number_of_entries = 5
        frame_type = 253 /* append */
          offset_delta = 67
          locals = [ top, class scala/util/Try ]
        frame_type = 2 /* same */
        frame_type = 39 /* same */
        frame_type = 2 /* same */
        frame_type = 255 /* full_frame */
          offset_delta = 10
          locals = [ class scala/collection/parallel/FutureTasks$$anonfun$compute$1$1, class scala/util/Try, class scala/Function1, class java/lang/Object, class scala/util/Try ]
          stack = []
      LineNumberTable:
        line 344: 0
        line 345: 3
        line 346: 28
        line 347: 44
        line 345: 67
        line 348: 70
        line 349: 92
        line 348: 110
        line 344: 113
      LocalVariableTable:
        Start  Length  Slot  Name   Signature
           28      39     6 firstTask   Lscala/collection/parallel/Task;
           92      18     8 exception   Ljava/lang/Throwable;
            0     126     0  this   Lscala/collection/parallel/FutureTasks$$anonfun$compute$1$1;
            0     126     1    x1   Lscala/util/Try;
            0     126     2 default   Lscala/Function1;
    Signature: #22                          // <A1:Lscala/util/Try<Lscala/collection/parallel/Task<TR;TTp;>;>;B1:Ljava/lang/Object;>(TA1;Lscala/Function1<TA1;TB1;>;)TB1;
    MethodParameters:
      Name                           Flags
      x1                             final
      default                        final

  public final boolean isDefinedAt(scala.util.Try<scala.collection.parallel.Task<R, Tp>>);
    descriptor: (Lscala/util/Try;)Z
    flags: (0x0011) ACC_PUBLIC, ACC_FINAL
    Code:
      stack=1, locals=4, args_size=2
         0: aload_1
         1: astore_3
         2: aload_3
         3: instanceof    #26                 // class scala/util/Success
         6: ifeq          14
         9: iconst_1
        10: istore_2
        11: goto          37
        14: goto          17
        17: aload_3
        18: instanceof    #57                 // class scala/util/Failure
        21: ifeq          29
        24: iconst_1
        25: istore_2
        26: goto          37
        29: goto          32
        32: iconst_0
        33: istore_2
        34: goto          37
        37: iload_2
        38: ireturn
      StackMapTable: number_of_entries = 5
        frame_type = 253 /* append */
          offset_delta = 14
          locals = [ top, class scala/util/Try ]
        frame_type = 2 /* same */
        frame_type = 11 /* same */
        frame_type = 2 /* same */
        frame_type = 255 /* full_frame */
          offset_delta = 4
          locals = [ class scala/collection/parallel/FutureTasks$$anonfun$compute$1$1, class scala/util/Try, int, class scala/util/Try ]
          stack = []
      LineNumberTable:
        line 344: 0
        line 345: 2
        line 348: 17
        line 349: 24
        line 348: 29
        line 344: 32
      LocalVariableTable:
        Start  Length  Slot  Name   Signature
            0      39     0  this   Lscala/collection/parallel/FutureTasks$$anonfun$compute$1$1;
            0      39     1    x1   Lscala/util/Try;
    Signature: #79                          // (Lscala/util/Try<Lscala/collection/parallel/Task<TR;TTp;>;>;)Z
    MethodParameters:
      Name                           Flags
      x1                             final

  public final boolean isDefinedAt(java.lang.Object);
    descriptor: (Ljava/lang/Object;)Z
    flags: (0x1051) ACC_PUBLIC, ACC_FINAL, ACC_BRIDGE, ACC_SYNTHETIC
    Code:
      stack=2, locals=2, args_size=2
         0: aload_0
         1: aload_1
         2: checkcast     #74                 // class scala/util/Try
         5: invokevirtual #83                 // Method isDefinedAt:(Lscala/util/Try;)Z
         8: ireturn
      LineNumberTable:
        line 344: 0
      LocalVariableTable:
        Start  Length  Slot  Name   Signature
            0       9     0  this   Lscala/collection/parallel/FutureTasks$$anonfun$compute$1$1;
            0       9     1     x   Ljava/lang/Object;
    MethodParameters:
      Name                           Flags
      x                              final

  public final java.lang.Object applyOrElse(java.lang.Object, scala.Function1);
    descriptor: (Ljava/lang/Object;Lscala/Function1;)Ljava/lang/Object;
    flags: (0x1051) ACC_PUBLIC, ACC_FINAL, ACC_BRIDGE, ACC_SYNTHETIC
    Code:
      stack=3, locals=3, args_size=3
         0: aload_0
         1: aload_1
         2: checkcast     #74                 // class scala/util/Try
         5: aload_2
         6: invokevirtual #87                 // Method applyOrElse:(Lscala/util/Try;Lscala/Function1;)Ljava/lang/Object;
         9: areturn
      LineNumberTable:
        line 344: 0
      LocalVariableTable:
        Start  Length  Slot  Name   Signature
            0      10     0  this   Lscala/collection/parallel/FutureTasks$$anonfun$compute$1$1;
            0      10     1     x   Ljava/lang/Object;
            0      10     2 default   Lscala/Function1;
    MethodParameters:
      Name                           Flags
      x                              final
      default                        final

  public scala.collection.parallel.FutureTasks$$anonfun$compute$1$1(scala.collection.parallel.FutureTasks, scala.collection.parallel.Task);
    descriptor: (Lscala/collection/parallel/FutureTasks;Lscala/collection/parallel/Task;)V
    flags: (0x0001) ACC_PUBLIC
    Code:
      stack=2, locals=3, args_size=3
         0: aload_0
         1: aload_2
         2: putfield      #34                 // Field task$1:Lscala/collection/parallel/Task;
         5: aload_0
         6: invokespecial #93                 // Method scala/runtime/AbstractPartialFunction."<init>":()V
         9: return
      LineNumberTable:
        line 332: 0
        line 344: 5
      LocalVariableTable:
        Start  Length  Slot  Name   Signature
            0      10     0  this   Lscala/collection/parallel/FutureTasks$$anonfun$compute$1$1;
            0      10     1 $outer   Lscala/collection/parallel/FutureTasks;
            0      10     2 task$1   Lscala/collection/parallel/Task;
    MethodParameters:
      Name                           Flags
      $outer                         final synthetic
      task$1                         final
}
InnerClasses:
  public final #2;                        // class scala/collection/parallel/FutureTasks$$anonfun$compute$1$1
EnclosingMethod: #10.#13                // scala.collection.parallel.FutureTasks.compute$1
Signature: #3                           // Lscala/runtime/AbstractPartialFunction<Lscala/util/Try<Lscala/collection/parallel/Task<TR;TTp;>;>;Lscala/runtime/BoxedUnit;>;Ljava/io/Serializable;
SourceFile: "Tasks.scala"
  ScalaInlineInfo: length = 0x1D (unknown attribute)
   01 01 00 05 00 58 00 59 01 00 14 00 55 01 00 14
   00 15 01 00 4D 00 50 01 00 4D 00 4E 01
  Scala: length = 0x0 (unknown attribute)

