Classfile /Users/mw/Projects/slang-braindump/.jar/jar11/assemble/slang-braindump/assemble/content/scala/collection/parallel/package.class
  Last modified May 29, 2022; size 2826 bytes
  SHA-256 checksum 01c10d657721d3e0bf2f973b271f1fe555face6e1abdf6abf6c80a3c1ef0e306
  Compiled from "package.scala"
public final class scala.collection.parallel.package
  minor version: 0
  major version: 52
  flags: (0x0031) ACC_PUBLIC, ACC_FINAL, ACC_SUPER
  this_class: #2                          // scala/collection/parallel/package
  super_class: #4                         // java/lang/Object
  interfaces: 0, fields: 0, methods: 8, attributes: 4
Constant pool:
   #1 = Utf8               scala/collection/parallel/package
   #2 = Class              #1             // scala/collection/parallel/package
   #3 = Utf8               java/lang/Object
   #4 = Class              #3             // java/lang/Object
   #5 = Utf8               package.scala
   #6 = Utf8               Lscala/reflect/ScalaSignature;
   #7 = Utf8               bytes
   #8 = Utf8               \u0006\u0005\u0005\rq!B\u000b\u0017\u0011\u0003ib!B\u0010\u0017\u0011\u0003\u0001\u0003\"B\u0013\u0002\t\u00031\u0003bB\u0014\u0002\u0005\u0004%\t\u0001\u000b\u0005\u0007Y\u0005\u0001\u000b\u0011B\u0015\t\u000f5\n!\u0019!C\u0001Q!1a&\u0001Q\u0001\n%BqaL\u0001C\u0002\u0013\u0005\u0001\u0007\u0003\u00045\u0003\u0001\u0006I!\r\u0005\bk\u0005\u0011\r\u0011\"\u0001)\u0011\u00191\u0014\u0001)A\u0005S!)q\'\u0001C\u0001q!9Q(\u0001b\u0001\n\u0003q\u0004B\u0002\"\u0002A\u0003%q\bC\u0003D\u0003\u0011\u0005AI\u0002\u0003V\u0003\u00051\u0006\u0002\u0003*\u0010\u0005\u0003\u0005\u000b\u0011\u0002-\t\u0011m{!\u0011!Q\u0001\fqCQ!J\b\u0005\u0002\u0019DQ\u0001\\\b\u0005\u00025Dq\u0001^\u0001\u0002\u0002\u0013\rQ/A\u0004qC\u000e\\\u0017mZ3\u000b\u0005]A\u0012\u0001\u00039be\u0006dG.\u001a7\u000b\u0005eQ\u0012AC2pY2,7\r^5p]*\t1$A\u0003tG\u0006d\u0017m\u0001\u0001\u0011\u0005y\tQ\"\u0001\f\u0003\u000fA\f7m[1hKN\u0011\u0011!\t\t\u0003E\rj\u0011AG\u0005\u0003Ii\u0011a!\u00118z%\u00164\u0017A\u0002\u001fj]&$h\bF\u0001\u001e\u00031i\u0015JT0G\u001fJ{6i\u0014)Z+\u0005I\u0003C\u0001\u0012+\u0013\tY#DA\u0002J]R\fQ\"T%O?\u001a{%kX\"P!f\u0003\u0013AC\"I\u000b\u000e[uLU!U\u000b\u0006Y1\tS#D\u0017~\u0013\u0016\tV#!\u0003\u0015\u0019\u0016K\u0015+3+\u0005\t\u0004C\u0001\u00123\u0013\t\u0019$D\u0001\u0004E_V\u0014G.Z\u0001\u0007\'F\u0013FK\r\u0011\u0002\'\u00054\u0018-\u001b7bE2,\u0007K]8dKN\u001cxN]:\u0002)\u00054\u0018-\u001b7bE2,\u0007K]8dKN\u001cxN]:!\u0003E!\bN]3tQ>dGM\u0012:p[NK\'0\u001a\u000b\u0004SeZ\u0004\"\u0002\u001e\f\u0001\u0004I\u0013AA:{\u0011\u0015a4\u00021\u0001*\u0003A\u0001\u0018M]1mY\u0016d\u0017n]7MKZ,G.\u0001\neK\u001a\fW\u000f\u001c;UCN\\7+\u001e9q_J$X#A \u0011\u0005y\u0001\u0015BA!\u0017\u0005-!\u0016m]6TkB\u0004xN\u001d;\u0002\'\u0011,g-Y;miR\u000b7o[*vaB|\'\u000f\u001e\u0011\u0002\u001dM,G\u000fV1tWN+\b\u000f]8siV\u0011Q\t\u0013\u000b\u0004\rF\u001b\u0006CA$I\u0019\u0001!Q!\u0013\bC\u0002)\u0013AaQ8mYF\u00111J\u0014\t\u0003E1K!!\u0014\u000e\u0003\u000f9{G\u000f[5oOB\u0011!eT\u0005\u0003!j\u00111!\u00118z\u0011\u0015\u0011f\u00021\u0001G\u0003\u0005\u0019\u0007\"\u0002+\u000f\u0001\u0004y\u0014!\u0001;\u00033\r{G\u000e\\3di&|gn\u001d%bm\u0016$v\u000eU1s\u0003J\u0014\u0018-_\u000b\u0004/f#7CA\b\"!\t9\u0015\fB\u0003[\u001f\t\u0007!JA\u0001D\u0003\u0015\t7o\u0012;p!\u0011\u0011S\fW0\n\u0005yS\"!\u0003$v]\u000e$\u0018n\u001c82!\r\u0001\u0017mY\u0007\u00021%\u0011!\r\u0007\u0002\r\u0013R,\'/\u00192mK>s7-\u001a\t\u0003\u000f\u0012$Q!Z\bC\u0002)\u0013\u0011\u0001\u0016\u000b\u0003O.$\"\u0001\u001b6\u0011\t%|\u0001lY\u0007\u0002\u0003!)1L\u0005a\u00029\")!K\u0005a\u00011\u0006QAo\u001c)be\u0006\u0013(/Y=\u0016\u00039\u00042a\u001c:d\u001b\u0005\u0001(BA9\u0017\u0003\u001diW\u000f^1cY\u0016L!a\u001d9\u0003\u0011A\u000b\'/\u0011:sCf\f\u0011dQ8mY\u0016\u001cG/[8og\"\u000bg/\u001a+p!\u0006\u0014\u0018I\u001d:bsV\u0019aO\u001f?\u0015\u0007]\f\t\u0001\u0006\u0002y{B!\u0011nD=|!\t9%\u0010B\u0003[)\t\u0007!\n\u0005\u0002Hy\u0012)Q\r\u0006b\u0001\u0015\")1\f\u0006a\u0002}B!!%X=\u0000!\r\u0001\u0017m\u001f\u0005\u0006%R\u0001\r!\u001f
   #9 = Utf8               scala/collection/parallel/package$CollectionsHaveToParArray
  #10 = Class              #9             // scala/collection/parallel/package$CollectionsHaveToParArray
  #11 = Utf8               CollectionsHaveToParArray
  #12 = Utf8               (Ljava/lang/Object;Lscala/Function1;)Lscala/collection/parallel/package$CollectionsHaveToParArray;
  #13 = Utf8               <C:Ljava/lang/Object;T:Ljava/lang/Object;>(TC;Lscala/Function1<TC;Lscala/collection/IterableOnce<TT;>;>;)Lscala/collection/parallel/package$CollectionsHaveToParArray<TC;TT;>;
  #14 = Utf8               c
  #15 = Utf8               asGto
  #16 = Utf8               scala/collection/parallel/package$
  #17 = Class              #16            // scala/collection/parallel/package$
  #18 = Utf8               MODULE$
  #19 = Utf8               Lscala/collection/parallel/package$;
  #20 = NameAndType        #18:#19        // MODULE$:Lscala/collection/parallel/package$;
  #21 = Fieldref           #17.#20        // scala/collection/parallel/package$.MODULE$:Lscala/collection/parallel/package$;
  #22 = NameAndType        #11:#12        // CollectionsHaveToParArray:(Ljava/lang/Object;Lscala/Function1;)Lscala/collection/parallel/package$CollectionsHaveToParArray;
  #23 = Methodref          #17.#22        // scala/collection/parallel/package$.CollectionsHaveToParArray:(Ljava/lang/Object;Lscala/Function1;)Lscala/collection/parallel/package$CollectionsHaveToParArray;
  #24 = Utf8               Ljava/lang/Object;
  #25 = Utf8               Lscala/Function1;
  #26 = Utf8               setTaskSupport
  #27 = Utf8               (Ljava/lang/Object;Lscala/collection/parallel/TaskSupport;)Ljava/lang/Object;
  #28 = Utf8               <Coll:Ljava/lang/Object;>(TColl;Lscala/collection/parallel/TaskSupport;)TColl;
  #29 = Utf8               t
  #30 = NameAndType        #26:#27        // setTaskSupport:(Ljava/lang/Object;Lscala/collection/parallel/TaskSupport;)Ljava/lang/Object;
  #31 = Methodref          #17.#30        // scala/collection/parallel/package$.setTaskSupport:(Ljava/lang/Object;Lscala/collection/parallel/TaskSupport;)Ljava/lang/Object;
  #32 = Utf8               Lscala/collection/parallel/TaskSupport;
  #33 = Utf8               defaultTaskSupport
  #34 = Utf8               ()Lscala/collection/parallel/TaskSupport;
  #35 = NameAndType        #33:#34        // defaultTaskSupport:()Lscala/collection/parallel/TaskSupport;
  #36 = Methodref          #17.#35        // scala/collection/parallel/package$.defaultTaskSupport:()Lscala/collection/parallel/TaskSupport;
  #37 = Utf8               thresholdFromSize
  #38 = Utf8               (II)I
  #39 = Utf8               sz
  #40 = Utf8               parallelismLevel
  #41 = NameAndType        #37:#38        // thresholdFromSize:(II)I
  #42 = Methodref          #17.#41        // scala/collection/parallel/package$.thresholdFromSize:(II)I
  #43 = Utf8               I
  #44 = Utf8               availableProcessors
  #45 = Utf8               ()I
  #46 = NameAndType        #44:#45        // availableProcessors:()I
  #47 = Methodref          #17.#46        // scala/collection/parallel/package$.availableProcessors:()I
  #48 = Utf8               SQRT2
  #49 = Utf8               ()D
  #50 = NameAndType        #48:#49        // SQRT2:()D
  #51 = Methodref          #17.#50        // scala/collection/parallel/package$.SQRT2:()D
  #52 = Utf8               CHECK_RATE
  #53 = NameAndType        #52:#45        // CHECK_RATE:()I
  #54 = Methodref          #17.#53        // scala/collection/parallel/package$.CHECK_RATE:()I
  #55 = Utf8               MIN_FOR_COPY
  #56 = NameAndType        #55:#45        // MIN_FOR_COPY:()I
  #57 = Methodref          #17.#56        // scala/collection/parallel/package$.MIN_FOR_COPY:()I
  #58 = Utf8               Code
  #59 = Utf8               LocalVariableTable
  #60 = Utf8               Signature
  #61 = Utf8               MethodParameters
  #62 = Utf8               InnerClasses
  #63 = Utf8               SourceFile
  #64 = Utf8               RuntimeVisibleAnnotations
  #65 = Utf8               ScalaSig
{
  public static <C extends java.lang.Object, T extends java.lang.Object> scala.collection.parallel.package$CollectionsHaveToParArray<C, T> CollectionsHaveToParArray(C, scala.Function1<C, scala.collection.IterableOnce<T>>);
    descriptor: (Ljava/lang/Object;Lscala/Function1;)Lscala/collection/parallel/package$CollectionsHaveToParArray;
    flags: (0x0009) ACC_PUBLIC, ACC_STATIC
    Code:
      stack=3, locals=2, args_size=2
         0: getstatic     #21                 // Field scala/collection/parallel/package$.MODULE$:Lscala/collection/parallel/package$;
         3: aload_0
         4: aload_1
         5: invokevirtual #23                 // Method scala/collection/parallel/package$.CollectionsHaveToParArray:(Ljava/lang/Object;Lscala/Function1;)Lscala/collection/parallel/package$CollectionsHaveToParArray;
         8: areturn
      LocalVariableTable:
        Start  Length  Slot  Name   Signature
            0       9     0     c   Ljava/lang/Object;
            0       9     1 asGto   Lscala/Function1;
    Signature: #13                          // <C:Ljava/lang/Object;T:Ljava/lang/Object;>(TC;Lscala/Function1<TC;Lscala/collection/IterableOnce<TT;>;>;)Lscala/collection/parallel/package$CollectionsHaveToParArray<TC;TT;>;
    MethodParameters:
      Name                           Flags
      c                              final
      asGto                          final

  public static <Coll extends java.lang.Object> Coll setTaskSupport(Coll, scala.collection.parallel.TaskSupport);
    descriptor: (Ljava/lang/Object;Lscala/collection/parallel/TaskSupport;)Ljava/lang/Object;
    flags: (0x0009) ACC_PUBLIC, ACC_STATIC
    Code:
      stack=3, locals=2, args_size=2
         0: getstatic     #21                 // Field scala/collection/parallel/package$.MODULE$:Lscala/collection/parallel/package$;
         3: aload_0
         4: aload_1
         5: invokevirtual #31                 // Method scala/collection/parallel/package$.setTaskSupport:(Ljava/lang/Object;Lscala/collection/parallel/TaskSupport;)Ljava/lang/Object;
         8: areturn
      LocalVariableTable:
        Start  Length  Slot  Name   Signature
            0       9     0     c   Ljava/lang/Object;
            0       9     1     t   Lscala/collection/parallel/TaskSupport;
    Signature: #28                          // <Coll:Ljava/lang/Object;>(TColl;Lscala/collection/parallel/TaskSupport;)TColl;
    MethodParameters:
      Name                           Flags
      c                              final
      t                              final

  public static scala.collection.parallel.TaskSupport defaultTaskSupport();
    descriptor: ()Lscala/collection/parallel/TaskSupport;
    flags: (0x0009) ACC_PUBLIC, ACC_STATIC
    Code:
      stack=1, locals=0, args_size=0
         0: getstatic     #21                 // Field scala/collection/parallel/package$.MODULE$:Lscala/collection/parallel/package$;
         3: invokevirtual #36                 // Method scala/collection/parallel/package$.defaultTaskSupport:()Lscala/collection/parallel/TaskSupport;
         6: areturn

  public static int thresholdFromSize(int, int);
    descriptor: (II)I
    flags: (0x0009) ACC_PUBLIC, ACC_STATIC
    Code:
      stack=3, locals=2, args_size=2
         0: getstatic     #21                 // Field scala/collection/parallel/package$.MODULE$:Lscala/collection/parallel/package$;
         3: iload_0
         4: iload_1
         5: invokevirtual #42                 // Method scala/collection/parallel/package$.thresholdFromSize:(II)I
         8: ireturn
      LocalVariableTable:
        Start  Length  Slot  Name   Signature
            0       9     0    sz   I
            0       9     1 parallelismLevel   I
    MethodParameters:
      Name                           Flags
      sz                             final
      parallelismLevel               final

  public static int availableProcessors();
    descriptor: ()I
    flags: (0x0009) ACC_PUBLIC, ACC_STATIC
    Code:
      stack=1, locals=0, args_size=0
         0: getstatic     #21                 // Field scala/collection/parallel/package$.MODULE$:Lscala/collection/parallel/package$;
         3: invokevirtual #47                 // Method scala/collection/parallel/package$.availableProcessors:()I
         6: ireturn

  public static double SQRT2();
    descriptor: ()D
    flags: (0x0009) ACC_PUBLIC, ACC_STATIC
    Code:
      stack=2, locals=0, args_size=0
         0: getstatic     #21                 // Field scala/collection/parallel/package$.MODULE$:Lscala/collection/parallel/package$;
         3: invokevirtual #51                 // Method scala/collection/parallel/package$.SQRT2:()D
         6: dreturn

  public static int CHECK_RATE();
    descriptor: ()I
    flags: (0x0009) ACC_PUBLIC, ACC_STATIC
    Code:
      stack=1, locals=0, args_size=0
         0: getstatic     #21                 // Field scala/collection/parallel/package$.MODULE$:Lscala/collection/parallel/package$;
         3: invokevirtual #54                 // Method scala/collection/parallel/package$.CHECK_RATE:()I
         6: ireturn

  public static int MIN_FOR_COPY();
    descriptor: ()I
    flags: (0x0009) ACC_PUBLIC, ACC_STATIC
    Code:
      stack=1, locals=0, args_size=0
         0: getstatic     #21                 // Field scala/collection/parallel/package$.MODULE$:Lscala/collection/parallel/package$;
         3: invokevirtual #57                 // Method scala/collection/parallel/package$.MIN_FOR_COPY:()I
         6: ireturn
}
InnerClasses:
  public static #11= #10 of #2;           // CollectionsHaveToParArray=class scala/collection/parallel/package$CollectionsHaveToParArray of class scala/collection/parallel/package
SourceFile: "package.scala"
RuntimeVisibleAnnotations:
  0: #6(#7=s#8)
    scala.reflect.ScalaSignature(
      bytes="\u0006\u0005\u0005\rq!B\u000b\u0017\u0011\u0003ib!B\u0010\u0017\u0011\u0003\u0001\u0003\"B\u0013\u0002\t\u00031\u0003bB\u0014\u0002\u0005\u0004%\t\u0001\u000b\u0005\u0007Y\u0005\u0001\u000b\u0011B\u0015\t\u000f5\n!\u0019!C\u0001Q!1a&\u0001Q\u0001\n%BqaL\u0001C\u0002\u0013\u0005\u0001\u0007\u0003\u00045\u0003\u0001\u0006I!\r\u0005\bk\u0005\u0011\r\u0011\"\u0001)\u0011\u00191\u0014\u0001)A\u0005S!)q\'\u0001C\u0001q!9Q(\u0001b\u0001\n\u0003q\u0004B\u0002\"\u0002A\u0003%q\bC\u0003D\u0003\u0011\u0005AI\u0002\u0003V\u0003\u00051\u0006\u0002\u0003*\u0010\u0005\u0003\u0005\u000b\u0011\u0002-\t\u0011m{!\u0011!Q\u0001\fqCQ!J\b\u0005\u0002\u0019DQ\u0001\\\b\u0005\u00025Dq\u0001^\u0001\u0002\u0002\u0013\rQ/A\u0004qC\u000e\\\u0017mZ3\u000b\u0005]A\u0012\u0001\u00039be\u0006dG.\u001a7\u000b\u0005eQ\u0012AC2pY2,7\r^5p]*\t1$A\u0003tG\u0006d\u0017m\u0001\u0001\u0011\u0005y\tQ\"\u0001\f\u0003\u000fA\f7m[1hKN\u0011\u0011!\t\t\u0003E\rj\u0011AG\u0005\u0003Ii\u0011a!\u00118z%\u00164\u0017A\u0002\u001fj]&$h\bF\u0001\u001e\u00031i\u0015JT0G\u001fJ{6i\u0014)Z+\u0005I\u0003C\u0001\u0012+\u0013\tY#DA\u0002J]R\fQ\"T%O?\u001a{%kX\"P!f\u0003\u0013AC\"I\u000b\u000e[uLU!U\u000b\u0006Y1\tS#D\u0017~\u0013\u0016\tV#!\u0003\u0015\u0019\u0016K\u0015+3+\u0005\t\u0004C\u0001\u00123\u0013\t\u0019$D\u0001\u0004E_V\u0014G.Z\u0001\u0007\'F\u0013FK\r\u0011\u0002\'\u00054\u0018-\u001b7bE2,\u0007K]8dKN\u001cxN]:\u0002)\u00054\u0018-\u001b7bE2,\u0007K]8dKN\u001cxN]:!\u0003E!\bN]3tQ>dGM\u0012:p[NK\'0\u001a\u000b\u0004SeZ\u0004\"\u0002\u001e\f\u0001\u0004I\u0013AA:{\u0011\u0015a4\u00021\u0001*\u0003A\u0001\u0018M]1mY\u0016d\u0017n]7MKZ,G.\u0001\neK\u001a\fW\u000f\u001c;UCN\\7+\u001e9q_J$X#A \u0011\u0005y\u0001\u0015BA!\u0017\u0005-!\u0016m]6TkB\u0004xN\u001d;\u0002\'\u0011,g-Y;miR\u000b7o[*vaB|\'\u000f\u001e\u0011\u0002\u001dM,G\u000fV1tWN+\b\u000f]8siV\u0011Q\t\u0013\u000b\u0004\rF\u001b\u0006CA$I\u0019\u0001!Q!\u0013\bC\u0002)\u0013AaQ8mYF\u00111J\u0014\t\u0003E1K!!\u0014\u000e\u0003\u000f9{G\u000f[5oOB\u0011!eT\u0005\u0003!j\u00111!\u00118z\u0011\u0015\u0011f\u00021\u0001G\u0003\u0005\u0019\u0007\"\u0002+\u000f\u0001\u0004y\u0014!\u0001;\u00033\r{G\u000e\\3di&|gn\u001d%bm\u0016$v\u000eU1s\u0003J\u0014\u0018-_\u000b\u0004/f#7CA\b\"!\t9\u0015\fB\u0003[\u001f\t\u0007!JA\u0001D\u0003\u0015\t7o\u0012;p!\u0011\u0011S\fW0\n\u0005yS\"!\u0003$v]\u000e$\u0018n\u001c82!\r\u0001\u0017mY\u0007\u00021%\u0011!\r\u0007\u0002\r\u0013R,\'/\u00192mK>s7-\u001a\t\u0003\u000f\u0012$Q!Z\bC\u0002)\u0013\u0011\u0001\u0016\u000b\u0003O.$\"\u0001\u001b6\u0011\t%|\u0001lY\u0007\u0002\u0003!)1L\u0005a\u00029\")!K\u0005a\u00011\u0006QAo\u001c)be\u0006\u0013(/Y=\u0016\u00039\u00042a\u001c:d\u001b\u0005\u0001(BA9\u0017\u0003\u001diW\u000f^1cY\u0016L!a\u001d9\u0003\u0011A\u000b\'/\u0011:sCf\f\u0011dQ8mY\u0016\u001cG/[8og\"\u000bg/\u001a+p!\u0006\u0014\u0018I\u001d:bsV\u0019aO\u001f?\u0015\u0007]\f\t\u0001\u0006\u0002y{B!\u0011nD=|!\t9%\u0010B\u0003[)\t\u0007!\n\u0005\u0002Hy\u0012)Q\r\u0006b\u0001\u0015\")1\f\u0006a\u0002}B!!%X=\u0000!\r\u0001\u0017m\u001f\u0005\u0006%R\u0001\r!\u001f"
    )
  ScalaSig: length = 0x3 (unknown attribute)
   05 02 00
