Classfile /Users/mw/Projects/slang-braindump/.jar/jar11/assemble/slang-braindump/assemble/content/scala/collection/parallel/ParIterableLike$GroupBy.class
  Last modified May 29, 2022; size 8209 bytes
  SHA-256 checksum 3d961cbebe4d41d1aaf17fa398e6da3f7cb20efd86f1677af90af18ba19cfed8
  Compiled from "ParIterableLike.scala"
public class scala.collection.parallel.ParIterableLike$GroupBy<K extends java.lang.Object, U extends java.lang.Object> extends java.lang.Object implements scala.collection.parallel.ParIterableLike<T, CC, Repr, Sequential>.Transformer<scala.collection.parallel.immutable.HashMapCombiner<K, U>, scala.collection.parallel.ParIterableLike<T, CC, Repr, Sequential>.GroupBy<K, U>>
  minor version: 0
  major version: 52
  flags: (0x0021) ACC_PUBLIC, ACC_SUPER
  this_class: #2                          // scala/collection/parallel/ParIterableLike$GroupBy
  super_class: #5                         // java/lang/Object
  interfaces: 1, fields: 6, methods: 27, attributes: 5
Constant pool:
    #1 = Utf8               scala/collection/parallel/ParIterableLike$GroupBy
    #2 = Class              #1            // scala/collection/parallel/ParIterableLike$GroupBy
    #3 = Utf8               <K:Ljava/lang/Object;U:Ljava/lang/Object;>Ljava/lang/Object;Lscala/collection/parallel/ParIterableLike<TT;TCC;TRepr;TSequential;>.Transformer<Lscala/collection/parallel/immutable/HashMapCombiner<TK;TU;>;Lscala/collection/parallel/ParIterableLike<TT;TCC;TRepr;TSequential;>.GroupBy<TK;TU;>;>;
    #4 = Utf8               java/lang/Object
    #5 = Class              #4            // java/lang/Object
    #6 = Utf8               scala/collection/parallel/ParIterableLike$Transformer
    #7 = Class              #6            // scala/collection/parallel/ParIterableLike$Transformer
    #8 = Utf8               ParIterableLike.scala
    #9 = Utf8               scala/Predef$ArrowAssoc$
   #10 = Class              #9            // scala/Predef$ArrowAssoc$
   #11 = Utf8               scala/Predef
   #12 = Class              #11           // scala/Predef
   #13 = Utf8               ArrowAssoc$
   #14 = Utf8               scala/collection/parallel/ParIterableLike$Accessor
   #15 = Class              #14           // scala/collection/parallel/ParIterableLike$Accessor
   #16 = Utf8               scala/collection/parallel/ParIterableLike
   #17 = Class              #16           // scala/collection/parallel/ParIterableLike
   #18 = Utf8               Accessor
   #19 = Utf8               GroupBy
   #20 = Utf8               scala/collection/parallel/ParIterableLike$StrictSplitterCheckTask
   #21 = Class              #20           // scala/collection/parallel/ParIterableLike$StrictSplitterCheckTask
   #22 = Utf8               StrictSplitterCheckTask
   #23 = Utf8               Transformer
   #24 = Utf8               f
   #25 = Utf8               Lscala/Function1;
   #26 = Utf8               Lscala/Function1<TU;TK;>;
   #27 = Utf8               mcf
   #28 = Utf8               Lscala/Function0;
   #29 = Utf8               Lscala/Function0<Lscala/collection/parallel/immutable/HashMapCombiner<TK;TU;>;>;
   #30 = Utf8               pit
   #31 = Utf8               Lscala/collection/parallel/IterableSplitter;
   #32 = Utf8               Lscala/collection/parallel/IterableSplitter<TT;>;
   #33 = Utf8               result
   #34 = Utf8               Lscala/collection/parallel/immutable/HashMapCombiner;
   #35 = Utf8               Lscala/collection/parallel/immutable/HashMapCombiner<TK;TU;>;
   #36 = Utf8               throwable
   #37 = Utf8               Ljava/lang/Throwable;
   #38 = Utf8               $outer
   #39 = Utf8               Lscala/collection/parallel/ParIterableLike;
   #40 = Utf8               scala$collection$parallel$ParIterableLike$Accessor$$super$toString
   #41 = Utf8               ()Ljava/lang/String;
   #42 = Utf8               toString
   #43 = NameAndType        #42:#41       // toString:()Ljava/lang/String;
   #44 = Methodref          #5.#43        // java/lang/Object.toString:()Ljava/lang/String;
   #45 = Utf8               this
   #46 = Utf8               Lscala/collection/parallel/ParIterableLike$GroupBy;
   #47 = Utf8               shouldSplitFurther
   #48 = Utf8               ()Z
   #49 = Utf8               shouldSplitFurther$
   #50 = Utf8               (Lscala/collection/parallel/ParIterableLike$Accessor;)Z
   #51 = NameAndType        #49:#50       // shouldSplitFurther$:(Lscala/collection/parallel/ParIterableLike$Accessor;)Z
   #52 = InterfaceMethodref #15.#51       // scala/collection/parallel/ParIterableLike$Accessor.shouldSplitFurther$:(Lscala/collection/parallel/ParIterableLike$Accessor;)Z
   #53 = Utf8               split
   #54 = Utf8               ()Lscala/collection/immutable/Seq;
   #55 = Utf8               ()Lscala/collection/immutable/Seq<Lscala/collection/parallel/ParIterableLike<TT;TCC;TRepr;TSequential;>.Accessor<Lscala/collection/parallel/immutable/HashMapCombiner<TK;TU;>;Lscala/collection/parallel/ParIterableLike<TT;TCC;TRepr;TSequential;>.GroupBy<TK;TU;>;>;>;
   #56 = Utf8               split$
   #57 = Utf8               (Lscala/collection/parallel/ParIterableLike$Accessor;)Lscala/collection/immutable/Seq;
   #58 = NameAndType        #56:#57       // split$:(Lscala/collection/parallel/ParIterableLike$Accessor;)Lscala/collection/immutable/Seq;
   #59 = InterfaceMethodref #15.#58       // scala/collection/parallel/ParIterableLike$Accessor.split$:(Lscala/collection/parallel/ParIterableLike$Accessor;)Lscala/collection/immutable/Seq;
   #60 = Utf8               signalAbort
   #61 = Utf8               ()V
   #62 = Utf8               signalAbort$
   #63 = Utf8               (Lscala/collection/parallel/ParIterableLike$Accessor;)V
   #64 = NameAndType        #62:#63       // signalAbort$:(Lscala/collection/parallel/ParIterableLike$Accessor;)V
   #65 = InterfaceMethodref #15.#64       // scala/collection/parallel/ParIterableLike$Accessor.signalAbort$:(Lscala/collection/parallel/ParIterableLike$Accessor;)V
   #66 = Utf8               toString$
   #67 = Utf8               (Lscala/collection/parallel/ParIterableLike$Accessor;)Ljava/lang/String;
   #68 = NameAndType        #66:#67       // toString$:(Lscala/collection/parallel/ParIterableLike$Accessor;)Ljava/lang/String;
   #69 = InterfaceMethodref #15.#68       // scala/collection/parallel/ParIterableLike$Accessor.toString$:(Lscala/collection/parallel/ParIterableLike$Accessor;)Ljava/lang/String;
   #70 = Utf8               requiresStrictSplitters
   #71 = Utf8               requiresStrictSplitters$
   #72 = Utf8               (Lscala/collection/parallel/ParIterableLike$StrictSplitterCheckTask;)Z
   #73 = NameAndType        #71:#72       // requiresStrictSplitters$:(Lscala/collection/parallel/ParIterableLike$StrictSplitterCheckTask;)Z
   #74 = InterfaceMethodref #21.#73       // scala/collection/parallel/ParIterableLike$StrictSplitterCheckTask.requiresStrictSplitters$:(Lscala/collection/parallel/ParIterableLike$StrictSplitterCheckTask;)Z
   #75 = Utf8               repr
   #76 = Utf8               ()Ljava/lang/Object;
   #77 = Utf8               scala/collection/parallel/Task
   #78 = Class              #77           // scala/collection/parallel/Task
   #79 = Utf8               repr$
   #80 = Utf8               (Lscala/collection/parallel/Task;)Ljava/lang/Object;
   #81 = NameAndType        #79:#80       // repr$:(Lscala/collection/parallel/Task;)Ljava/lang/Object;
   #82 = InterfaceMethodref #78.#81       // scala/collection/parallel/Task.repr$:(Lscala/collection/parallel/Task;)Ljava/lang/Object;
   #83 = Utf8               forwardThrowable
   #84 = Utf8               forwardThrowable$
   #85 = Utf8               (Lscala/collection/parallel/Task;)V
   #86 = NameAndType        #84:#85       // forwardThrowable$:(Lscala/collection/parallel/Task;)V
   #87 = InterfaceMethodref #78.#86       // scala/collection/parallel/Task.forwardThrowable$:(Lscala/collection/parallel/Task;)V
   #88 = Utf8               tryLeaf
   #89 = Utf8               (Lscala/Option;)V
   #90 = Utf8               (Lscala/Option<Lscala/collection/parallel/immutable/HashMapCombiner<TK;TU;>;>;)V
   #91 = Utf8               lastres
   #92 = Utf8               tryLeaf$
   #93 = Utf8               (Lscala/collection/parallel/Task;Lscala/Option;)V
   #94 = NameAndType        #92:#93       // tryLeaf$:(Lscala/collection/parallel/Task;Lscala/Option;)V
   #95 = InterfaceMethodref #78.#94       // scala/collection/parallel/Task.tryLeaf$:(Lscala/collection/parallel/Task;Lscala/Option;)V
   #96 = Utf8               Lscala/Option;
   #97 = Utf8               tryMerge
   #98 = Utf8               (Ljava/lang/Object;)V
   #99 = Utf8               t
  #100 = Utf8               tryMerge$
  #101 = Utf8               (Lscala/collection/parallel/Task;Ljava/lang/Object;)V
  #102 = NameAndType        #100:#101     // tryMerge$:(Lscala/collection/parallel/Task;Ljava/lang/Object;)V
  #103 = InterfaceMethodref #78.#102      // scala/collection/parallel/Task.tryMerge$:(Lscala/collection/parallel/Task;Ljava/lang/Object;)V
  #104 = Utf8               Ljava/lang/Object;
  #105 = Utf8               mergeThrowables
  #106 = Utf8               (Lscala/collection/parallel/Task<**>;)V
  #107 = Utf8               that
  #108 = Utf8               mergeThrowables$
  #109 = Utf8               (Lscala/collection/parallel/Task;Lscala/collection/parallel/Task;)V
  #110 = NameAndType        #108:#109     // mergeThrowables$:(Lscala/collection/parallel/Task;Lscala/collection/parallel/Task;)V
  #111 = InterfaceMethodref #78.#110      // scala/collection/parallel/Task.mergeThrowables$:(Lscala/collection/parallel/Task;Lscala/collection/parallel/Task;)V
  #112 = Utf8               Lscala/collection/parallel/Task;
  #113 = Utf8               ()Ljava/lang/Throwable;
  #114 = NameAndType        #36:#37       // throwable:Ljava/lang/Throwable;
  #115 = Fieldref           #2.#114       // scala/collection/parallel/ParIterableLike$GroupBy.throwable:Ljava/lang/Throwable;
  #116 = Utf8               throwable_$eq
  #117 = Utf8               (Ljava/lang/Throwable;)V
  #118 = Utf8               x$1
  #119 = Utf8               ()Lscala/collection/parallel/IterableSplitter;
  #120 = Utf8               ()Lscala/collection/parallel/IterableSplitter<TT;>;
  #121 = NameAndType        #30:#31       // pit:Lscala/collection/parallel/IterableSplitter;
  #122 = Fieldref           #2.#121       // scala/collection/parallel/ParIterableLike$GroupBy.pit:Lscala/collection/parallel/IterableSplitter;
  #123 = Utf8               ()Lscala/collection/parallel/immutable/HashMapCombiner;
  #124 = Utf8               ()Lscala/collection/parallel/immutable/HashMapCombiner<TK;TU;>;
  #125 = NameAndType        #33:#34       // result:Lscala/collection/parallel/immutable/HashMapCombiner;
  #126 = Fieldref           #2.#125       // scala/collection/parallel/ParIterableLike$GroupBy.result:Lscala/collection/parallel/immutable/HashMapCombiner;
  #127 = Utf8               result_$eq
  #128 = Utf8               (Lscala/collection/parallel/immutable/HashMapCombiner;)V
  #129 = Utf8               (Lscala/collection/parallel/immutable/HashMapCombiner<TK;TU;>;)V
  #130 = Utf8               leaf
  #131 = Utf8               prev
  #132 = NameAndType        #27:#28       // mcf:Lscala/Function0;
  #133 = Fieldref           #2.#132       // scala/collection/parallel/ParIterableLike$GroupBy.mcf:Lscala/Function0;
  #134 = Utf8               scala/Function0
  #135 = Class              #134          // scala/Function0
  #136 = Utf8               apply
  #137 = NameAndType        #136:#76      // apply:()Ljava/lang/Object;
  #138 = InterfaceMethodref #135.#137     // scala/Function0.apply:()Ljava/lang/Object;
  #139 = Utf8               scala/collection/parallel/immutable/HashMapCombiner
  #140 = Class              #139          // scala/collection/parallel/immutable/HashMapCombiner
  #141 = NameAndType        #30:#119      // pit:()Lscala/collection/parallel/IterableSplitter;
  #142 = Methodref          #2.#141       // scala/collection/parallel/ParIterableLike$GroupBy.pit:()Lscala/collection/parallel/IterableSplitter;
  #143 = Utf8               scala/collection/parallel/IterableSplitter
  #144 = Class              #143          // scala/collection/parallel/IterableSplitter
  #145 = Utf8               hasNext
  #146 = NameAndType        #145:#48      // hasNext:()Z
  #147 = InterfaceMethodref #144.#146     // scala/collection/parallel/IterableSplitter.hasNext:()Z
  #148 = Utf8               next
  #149 = NameAndType        #148:#76      // next:()Ljava/lang/Object;
  #150 = InterfaceMethodref #144.#149     // scala/collection/parallel/IterableSplitter.next:()Ljava/lang/Object;
  #151 = Utf8               MODULE$
  #152 = Utf8               Lscala/Predef$ArrowAssoc$;
  #153 = NameAndType        #151:#152     // MODULE$:Lscala/Predef$ArrowAssoc$;
  #154 = Fieldref           #10.#153      // scala/Predef$ArrowAssoc$.MODULE$:Lscala/Predef$ArrowAssoc$;
  #155 = Utf8               scala/Predef$
  #156 = Class              #155          // scala/Predef$
  #157 = Utf8               Lscala/Predef$;
  #158 = NameAndType        #151:#157     // MODULE$:Lscala/Predef$;
  #159 = Fieldref           #156.#158     // scala/Predef$.MODULE$:Lscala/Predef$;
  #160 = NameAndType        #24:#25       // f:Lscala/Function1;
  #161 = Fieldref           #2.#160       // scala/collection/parallel/ParIterableLike$GroupBy.f:Lscala/Function1;
  #162 = Utf8               scala/Function1
  #163 = Class              #162          // scala/Function1
  #164 = Utf8               (Ljava/lang/Object;)Ljava/lang/Object;
  #165 = NameAndType        #136:#164     // apply:(Ljava/lang/Object;)Ljava/lang/Object;
  #166 = InterfaceMethodref #163.#165     // scala/Function1.apply:(Ljava/lang/Object;)Ljava/lang/Object;
  #167 = Utf8               ArrowAssoc
  #168 = NameAndType        #167:#164     // ArrowAssoc:(Ljava/lang/Object;)Ljava/lang/Object;
  #169 = Methodref          #156.#168     // scala/Predef$.ArrowAssoc:(Ljava/lang/Object;)Ljava/lang/Object;
  #170 = Utf8               $minus$greater$extension
  #171 = Utf8               (Ljava/lang/Object;Ljava/lang/Object;)Lscala/Tuple2;
  #172 = NameAndType        #170:#171     // $minus$greater$extension:(Ljava/lang/Object;Ljava/lang/Object;)Lscala/Tuple2;
  #173 = Methodref          #10.#172      // scala/Predef$ArrowAssoc$.$minus$greater$extension:(Ljava/lang/Object;Ljava/lang/Object;)Lscala/Tuple2;
  #174 = Utf8               $plus$eq
  #175 = Utf8               (Ljava/lang/Object;)Lscala/collection/mutable/Growable;
  #176 = NameAndType        #174:#175     // $plus$eq:(Ljava/lang/Object;)Lscala/collection/mutable/Growable;
  #177 = Methodref          #140.#176     // scala/collection/parallel/immutable/HashMapCombiner.$plus$eq:(Ljava/lang/Object;)Lscala/collection/mutable/Growable;
  #178 = NameAndType        #127:#128     // result_$eq:(Lscala/collection/parallel/immutable/HashMapCombiner;)V
  #179 = Methodref          #2.#178       // scala/collection/parallel/ParIterableLike$GroupBy.result_$eq:(Lscala/collection/parallel/immutable/HashMapCombiner;)V
  #180 = Utf8               elem
  #181 = Utf8               cb
  #182 = Utf8               newSubtask
  #183 = Utf8               (Lscala/collection/parallel/IterableSplitter;)Lscala/collection/parallel/ParIterableLike$GroupBy;
  #184 = Utf8               (Lscala/collection/parallel/IterableSplitter<TT;>;)Lscala/collection/parallel/ParIterableLike<TT;TCC;TRepr;TSequential;>.GroupBy<TK;TU;>;
  #185 = Utf8               p
  #186 = Utf8               scala$collection$parallel$ParIterableLike$GroupBy$$$outer
  #187 = Utf8               ()Lscala/collection/parallel/ParIterableLike;
  #188 = NameAndType        #186:#187     // scala$collection$parallel$ParIterableLike$GroupBy$$$outer:()Lscala/collection/parallel/ParIterableLike;
  #189 = Methodref          #2.#188       // scala/collection/parallel/ParIterableLike$GroupBy.scala$collection$parallel$ParIterableLike$GroupBy$$$outer:()Lscala/collection/parallel/ParIterableLike;
  #190 = Utf8               <init>
  #191 = Utf8               (Lscala/collection/parallel/ParIterableLike;Lscala/Function1;Lscala/Function0;Lscala/collection/parallel/IterableSplitter;)V
  #192 = NameAndType        #190:#191     // "<init>":(Lscala/collection/parallel/ParIterableLike;Lscala/Function1;Lscala/Function0;Lscala/collection/parallel/IterableSplitter;)V
  #193 = Methodref          #2.#192       // scala/collection/parallel/ParIterableLike$GroupBy."<init>":(Lscala/collection/parallel/ParIterableLike;Lscala/Function1;Lscala/Function0;Lscala/collection/parallel/IterableSplitter;)V
  #194 = Utf8               merge
  #195 = Utf8               (Lscala/collection/parallel/ParIterableLike$GroupBy;)V
  #196 = Utf8               (Lscala/collection/parallel/ParIterableLike<TT;TCC;TRepr;TSequential;>.GroupBy<TK;TU;>;)V
  #197 = NameAndType        #33:#123      // result:()Lscala/collection/parallel/immutable/HashMapCombiner;
  #198 = Methodref          #2.#197       // scala/collection/parallel/ParIterableLike$GroupBy.result:()Lscala/collection/parallel/immutable/HashMapCombiner;
  #199 = Utf8               combine
  #200 = Utf8               (Lscala/collection/parallel/Combiner;)Lscala/collection/parallel/Combiner;
  #201 = NameAndType        #199:#200     // combine:(Lscala/collection/parallel/Combiner;)Lscala/collection/parallel/Combiner;
  #202 = Methodref          #140.#201     // scala/collection/parallel/immutable/HashMapCombiner.combine:(Lscala/collection/parallel/Combiner;)Lscala/collection/parallel/Combiner;
  #203 = NameAndType        #38:#39       // $outer:Lscala/collection/parallel/ParIterableLike;
  #204 = Fieldref           #2.#203       // scala/collection/parallel/ParIterableLike$GroupBy.$outer:Lscala/collection/parallel/ParIterableLike;
  #205 = Utf8               scala$collection$parallel$ParIterableLike$Accessor$$$outer
  #206 = Utf8               scala$collection$parallel$ParIterableLike$StrictSplitterCheckTask$$$outer
  #207 = NameAndType        #194:#195     // merge:(Lscala/collection/parallel/ParIterableLike$GroupBy;)V
  #208 = Methodref          #2.#207       // scala/collection/parallel/ParIterableLike$GroupBy.merge:(Lscala/collection/parallel/ParIterableLike$GroupBy;)V
  #209 = Utf8               (Lscala/collection/parallel/IterableSplitter;)Lscala/collection/parallel/ParIterableLike$Accessor;
  #210 = NameAndType        #182:#183     // newSubtask:(Lscala/collection/parallel/IterableSplitter;)Lscala/collection/parallel/ParIterableLike$GroupBy;
  #211 = Methodref          #2.#210       // scala/collection/parallel/ParIterableLike$GroupBy.newSubtask:(Lscala/collection/parallel/IterableSplitter;)Lscala/collection/parallel/ParIterableLike$GroupBy;
  #212 = Utf8               (Lscala/Function1<TU;TK;>;Lscala/Function0<Lscala/collection/parallel/immutable/HashMapCombiner<TK;TU;>;>;Lscala/collection/parallel/IterableSplitter<TT;>;)V
  #213 = NameAndType        #190:#61      // "<init>":()V
  #214 = Methodref          #5.#213       // java/lang/Object."<init>":()V
  #215 = Utf8               $init$
  #216 = NameAndType        #215:#85      // $init$:(Lscala/collection/parallel/Task;)V
  #217 = InterfaceMethodref #78.#216      // scala/collection/parallel/Task.$init$:(Lscala/collection/parallel/Task;)V
  #218 = Utf8               (Lscala/collection/parallel/ParIterableLike$StrictSplitterCheckTask;)V
  #219 = NameAndType        #215:#218     // $init$:(Lscala/collection/parallel/ParIterableLike$StrictSplitterCheckTask;)V
  #220 = InterfaceMethodref #21.#219      // scala/collection/parallel/ParIterableLike$StrictSplitterCheckTask.$init$:(Lscala/collection/parallel/ParIterableLike$StrictSplitterCheckTask;)V
  #221 = NameAndType        #215:#63      // $init$:(Lscala/collection/parallel/ParIterableLike$Accessor;)V
  #222 = InterfaceMethodref #15.#221      // scala/collection/parallel/ParIterableLike$Accessor.$init$:(Lscala/collection/parallel/ParIterableLike$Accessor;)V
  #223 = Utf8               Signature
  #224 = Utf8               Code
  #225 = Utf8               LineNumberTable
  #226 = Utf8               LocalVariableTable
  #227 = Utf8               MethodParameters
  #228 = Utf8               StackMapTable
  #229 = Utf8               InnerClasses
  #230 = Utf8               SourceFile
  #231 = Utf8               ScalaInlineInfo
  #232 = Utf8               Scala
{
  private final scala.Function1<U, K> f;
    descriptor: Lscala/Function1;
    flags: (0x0012) ACC_PRIVATE, ACC_FINAL
    Signature: #26                          // Lscala/Function1<TU;TK;>;

  private final scala.Function0<scala.collection.parallel.immutable.HashMapCombiner<K, U>> mcf;
    descriptor: Lscala/Function0;
    flags: (0x0012) ACC_PRIVATE, ACC_FINAL
    Signature: #29                          // Lscala/Function0<Lscala/collection/parallel/immutable/HashMapCombiner<TK;TU;>;>;

  private final scala.collection.parallel.IterableSplitter<T> pit;
    descriptor: Lscala/collection/parallel/IterableSplitter;
    flags: (0x0012) ACC_PRIVATE, ACC_FINAL
    Signature: #32                          // Lscala/collection/parallel/IterableSplitter<TT;>;

  private volatile scala.collection.parallel.immutable.HashMapCombiner<K, U> result;
    descriptor: Lscala/collection/parallel/immutable/HashMapCombiner;
    flags: (0x0042) ACC_PRIVATE, ACC_VOLATILE
    Signature: #35                          // Lscala/collection/parallel/immutable/HashMapCombiner<TK;TU;>;

  private volatile java.lang.Throwable throwable;
    descriptor: Ljava/lang/Throwable;
    flags: (0x0042) ACC_PRIVATE, ACC_VOLATILE

  public final scala.collection.parallel.ParIterableLike $outer;
    descriptor: Lscala/collection/parallel/ParIterableLike;
    flags: (0x1011) ACC_PUBLIC, ACC_FINAL, ACC_SYNTHETIC

  public java.lang.String scala$collection$parallel$ParIterableLike$Accessor$$super$toString();
    descriptor: ()Ljava/lang/String;
    flags: (0x1001) ACC_PUBLIC, ACC_SYNTHETIC
    Code:
      stack=1, locals=1, args_size=1
         0: aload_0
         1: invokespecial #44                 // Method java/lang/Object.toString:()Ljava/lang/String;
         4: areturn
      LineNumberTable:
        line 1108: 0
      LocalVariableTable:
        Start  Length  Slot  Name   Signature
            0       5     0  this   Lscala/collection/parallel/ParIterableLike$GroupBy;

  public boolean shouldSplitFurther();
    descriptor: ()Z
    flags: (0x0001) ACC_PUBLIC
    Code:
      stack=1, locals=1, args_size=1
         0: aload_0
         1: invokestatic  #52                 // InterfaceMethod scala/collection/parallel/ParIterableLike$Accessor.shouldSplitFurther$:(Lscala/collection/parallel/ParIterableLike$Accessor;)Z
         4: ireturn
      LineNumberTable:
        line 1108: 0
      LocalVariableTable:
        Start  Length  Slot  Name   Signature
            0       5     0  this   Lscala/collection/parallel/ParIterableLike$GroupBy;

  public scala.collection.immutable.Seq<scala.collection.parallel.ParIterableLike<T, CC, Repr, Sequential>.Accessor<scala.collection.parallel.immutable.HashMapCombiner<K, U>, scala.collection.parallel.ParIterableLike<T, CC, Repr, Sequential>.GroupBy<K, U>>> split();
    descriptor: ()Lscala/collection/immutable/Seq;
    flags: (0x0001) ACC_PUBLIC
    Code:
      stack=1, locals=1, args_size=1
         0: aload_0
         1: invokestatic  #59                 // InterfaceMethod scala/collection/parallel/ParIterableLike$Accessor.split$:(Lscala/collection/parallel/ParIterableLike$Accessor;)Lscala/collection/immutable/Seq;
         4: areturn
      LineNumberTable:
        line 1108: 0
      LocalVariableTable:
        Start  Length  Slot  Name   Signature
            0       5     0  this   Lscala/collection/parallel/ParIterableLike$GroupBy;
    Signature: #55                          // ()Lscala/collection/immutable/Seq<Lscala/collection/parallel/ParIterableLike<TT;TCC;TRepr;TSequential;>.Accessor<Lscala/collection/parallel/immutable/HashMapCombiner<TK;TU;>;Lscala/collection/parallel/ParIterableLike<TT;TCC;TRepr;TSequential;>.GroupBy<TK;TU;>;>;>;

  public void signalAbort();
    descriptor: ()V
    flags: (0x0001) ACC_PUBLIC
    Code:
      stack=1, locals=1, args_size=1
         0: aload_0
         1: invokestatic  #65                 // InterfaceMethod scala/collection/parallel/ParIterableLike$Accessor.signalAbort$:(Lscala/collection/parallel/ParIterableLike$Accessor;)V
         4: return
      LineNumberTable:
        line 1108: 0
      LocalVariableTable:
        Start  Length  Slot  Name   Signature
            0       5     0  this   Lscala/collection/parallel/ParIterableLike$GroupBy;

  public java.lang.String toString();
    descriptor: ()Ljava/lang/String;
    flags: (0x0001) ACC_PUBLIC
    Code:
      stack=1, locals=1, args_size=1
         0: aload_0
         1: invokestatic  #69                 // InterfaceMethod scala/collection/parallel/ParIterableLike$Accessor.toString$:(Lscala/collection/parallel/ParIterableLike$Accessor;)Ljava/lang/String;
         4: areturn
      LineNumberTable:
        line 1108: 0
      LocalVariableTable:
        Start  Length  Slot  Name   Signature
            0       5     0  this   Lscala/collection/parallel/ParIterableLike$GroupBy;

  public boolean requiresStrictSplitters();
    descriptor: ()Z
    flags: (0x0001) ACC_PUBLIC
    Code:
      stack=1, locals=1, args_size=1
         0: aload_0
         1: invokestatic  #74                 // InterfaceMethod scala/collection/parallel/ParIterableLike$StrictSplitterCheckTask.requiresStrictSplitters$:(Lscala/collection/parallel/ParIterableLike$StrictSplitterCheckTask;)Z
         4: ireturn
      LineNumberTable:
        line 1108: 0
      LocalVariableTable:
        Start  Length  Slot  Name   Signature
            0       5     0  this   Lscala/collection/parallel/ParIterableLike$GroupBy;

  public java.lang.Object repr();
    descriptor: ()Ljava/lang/Object;
    flags: (0x0001) ACC_PUBLIC
    Code:
      stack=1, locals=1, args_size=1
         0: aload_0
         1: invokestatic  #82                 // InterfaceMethod scala/collection/parallel/Task.repr$:(Lscala/collection/parallel/Task;)Ljava/lang/Object;
         4: areturn
      LineNumberTable:
        line 1108: 0
      LocalVariableTable:
        Start  Length  Slot  Name   Signature
            0       5     0  this   Lscala/collection/parallel/ParIterableLike$GroupBy;

  public void forwardThrowable();
    descriptor: ()V
    flags: (0x0001) ACC_PUBLIC
    Code:
      stack=1, locals=1, args_size=1
         0: aload_0
         1: invokestatic  #87                 // InterfaceMethod scala/collection/parallel/Task.forwardThrowable$:(Lscala/collection/parallel/Task;)V
         4: return
      LineNumberTable:
        line 1108: 0
      LocalVariableTable:
        Start  Length  Slot  Name   Signature
            0       5     0  this   Lscala/collection/parallel/ParIterableLike$GroupBy;

  public void tryLeaf(scala.Option<scala.collection.parallel.immutable.HashMapCombiner<K, U>>);
    descriptor: (Lscala/Option;)V
    flags: (0x0001) ACC_PUBLIC
    Code:
      stack=2, locals=2, args_size=2
         0: aload_0
         1: aload_1
         2: invokestatic  #95                 // InterfaceMethod scala/collection/parallel/Task.tryLeaf$:(Lscala/collection/parallel/Task;Lscala/Option;)V
         5: return
      LineNumberTable:
        line 1108: 0
      LocalVariableTable:
        Start  Length  Slot  Name   Signature
            0       6     0  this   Lscala/collection/parallel/ParIterableLike$GroupBy;
            0       6     1 lastres   Lscala/Option;
    Signature: #90                          // (Lscala/Option<Lscala/collection/parallel/immutable/HashMapCombiner<TK;TU;>;>;)V
    MethodParameters:
      Name                           Flags
      lastres                        final

  public void tryMerge(java.lang.Object);
    descriptor: (Ljava/lang/Object;)V
    flags: (0x0001) ACC_PUBLIC
    Code:
      stack=2, locals=2, args_size=2
         0: aload_0
         1: aload_1
         2: invokestatic  #103                // InterfaceMethod scala/collection/parallel/Task.tryMerge$:(Lscala/collection/parallel/Task;Ljava/lang/Object;)V
         5: return
      LineNumberTable:
        line 1108: 0
      LocalVariableTable:
        Start  Length  Slot  Name   Signature
            0       6     0  this   Lscala/collection/parallel/ParIterableLike$GroupBy;
            0       6     1     t   Ljava/lang/Object;
    MethodParameters:
      Name                           Flags
      t                              final

  public void mergeThrowables(scala.collection.parallel.Task<?, ?>);
    descriptor: (Lscala/collection/parallel/Task;)V
    flags: (0x0001) ACC_PUBLIC
    Code:
      stack=2, locals=2, args_size=2
         0: aload_0
         1: aload_1
         2: invokestatic  #111                // InterfaceMethod scala/collection/parallel/Task.mergeThrowables$:(Lscala/collection/parallel/Task;Lscala/collection/parallel/Task;)V
         5: return
      LineNumberTable:
        line 1108: 0
      LocalVariableTable:
        Start  Length  Slot  Name   Signature
            0       6     0  this   Lscala/collection/parallel/ParIterableLike$GroupBy;
            0       6     1  that   Lscala/collection/parallel/Task;
    Signature: #106                         // (Lscala/collection/parallel/Task<**>;)V
    MethodParameters:
      Name                           Flags
      that                           final

  public java.lang.Throwable throwable();
    descriptor: ()Ljava/lang/Throwable;
    flags: (0x0001) ACC_PUBLIC
    Code:
      stack=1, locals=1, args_size=1
         0: aload_0
         1: getfield      #115                // Field throwable:Ljava/lang/Throwable;
         4: areturn
      LineNumberTable:
        line 1108: 0
      LocalVariableTable:
        Start  Length  Slot  Name   Signature
            0       5     0  this   Lscala/collection/parallel/ParIterableLike$GroupBy;

  public void throwable_$eq(java.lang.Throwable);
    descriptor: (Ljava/lang/Throwable;)V
    flags: (0x0001) ACC_PUBLIC
    Code:
      stack=2, locals=2, args_size=2
         0: aload_0
         1: aload_1
         2: putfield      #115                // Field throwable:Ljava/lang/Throwable;
         5: return
      LineNumberTable:
        line 1108: 0
      LocalVariableTable:
        Start  Length  Slot  Name   Signature
            0       6     0  this   Lscala/collection/parallel/ParIterableLike$GroupBy;
            0       6     1   x$1   Ljava/lang/Throwable;
    MethodParameters:
      Name                           Flags
      x$1                            final

  public scala.collection.parallel.IterableSplitter<T> pit();
    descriptor: ()Lscala/collection/parallel/IterableSplitter;
    flags: (0x0001) ACC_PUBLIC
    Code:
      stack=1, locals=1, args_size=1
         0: aload_0
         1: getfield      #122                // Field pit:Lscala/collection/parallel/IterableSplitter;
         4: areturn
      LineNumberTable:
        line 1111: 0
      LocalVariableTable:
        Start  Length  Slot  Name   Signature
            0       5     0  this   Lscala/collection/parallel/ParIterableLike$GroupBy;
    Signature: #120                         // ()Lscala/collection/parallel/IterableSplitter<TT;>;

  public scala.collection.parallel.immutable.HashMapCombiner<K, U> result();
    descriptor: ()Lscala/collection/parallel/immutable/HashMapCombiner;
    flags: (0x0001) ACC_PUBLIC
    Code:
      stack=1, locals=1, args_size=1
         0: aload_0
         1: getfield      #126                // Field result:Lscala/collection/parallel/immutable/HashMapCombiner;
         4: areturn
      LineNumberTable:
        line 1113: 0
      LocalVariableTable:
        Start  Length  Slot  Name   Signature
            0       5     0  this   Lscala/collection/parallel/ParIterableLike$GroupBy;
    Signature: #124                         // ()Lscala/collection/parallel/immutable/HashMapCombiner<TK;TU;>;

  public void result_$eq(scala.collection.parallel.immutable.HashMapCombiner<K, U>);
    descriptor: (Lscala/collection/parallel/immutable/HashMapCombiner;)V
    flags: (0x0001) ACC_PUBLIC
    Code:
      stack=2, locals=2, args_size=2
         0: aload_0
         1: aload_1
         2: putfield      #126                // Field result:Lscala/collection/parallel/immutable/HashMapCombiner;
         5: return
      LineNumberTable:
        line 1113: 0
      LocalVariableTable:
        Start  Length  Slot  Name   Signature
            0       6     0  this   Lscala/collection/parallel/ParIterableLike$GroupBy;
            0       6     1   x$1   Lscala/collection/parallel/immutable/HashMapCombiner;
    Signature: #129                         // (Lscala/collection/parallel/immutable/HashMapCombiner<TK;TU;>;)V
    MethodParameters:
      Name                           Flags
      x$1                            final

  public final void leaf(scala.Option<scala.collection.parallel.immutable.HashMapCombiner<K, U>>);
    descriptor: (Lscala/Option;)V
    flags: (0x0011) ACC_PUBLIC, ACC_FINAL
    Code:
      stack=5, locals=4, args_size=2
         0: aload_0
         1: getfield      #133                // Field mcf:Lscala/Function0;
         4: invokeinterface #138,  1          // InterfaceMethod scala/Function0.apply:()Ljava/lang/Object;
         9: checkcast     #140                // class scala/collection/parallel/immutable/HashMapCombiner
        12: astore_2
        13: aload_0
        14: invokevirtual #142                // Method pit:()Lscala/collection/parallel/IterableSplitter;
        17: invokeinterface #147,  1          // InterfaceMethod scala/collection/parallel/IterableSplitter.hasNext:()Z
        22: ifeq          66
        25: aload_0
        26: invokevirtual #142                // Method pit:()Lscala/collection/parallel/IterableSplitter;
        29: invokeinterface #150,  1          // InterfaceMethod scala/collection/parallel/IterableSplitter.next:()Ljava/lang/Object;
        34: astore_3
        35: aload_2
        36: getstatic     #154                // Field scala/Predef$ArrowAssoc$.MODULE$:Lscala/Predef$ArrowAssoc$;
        39: getstatic     #159                // Field scala/Predef$.MODULE$:Lscala/Predef$;
        42: aload_0
        43: getfield      #161                // Field f:Lscala/Function1;
        46: aload_3
        47: invokeinterface #166,  2          // InterfaceMethod scala/Function1.apply:(Ljava/lang/Object;)Ljava/lang/Object;
        52: invokevirtual #169                // Method scala/Predef$.ArrowAssoc:(Ljava/lang/Object;)Ljava/lang/Object;
        55: aload_3
        56: invokevirtual #173                // Method scala/Predef$ArrowAssoc$.$minus$greater$extension:(Ljava/lang/Object;Ljava/lang/Object;)Lscala/Tuple2;
        59: invokevirtual #177                // Method scala/collection/parallel/immutable/HashMapCombiner.$plus$eq:(Ljava/lang/Object;)Lscala/collection/mutable/Growable;
        62: pop
        63: goto          13
        66: aload_0
        67: aload_2
        68: invokevirtual #179                // Method result_$eq:(Lscala/collection/parallel/immutable/HashMapCombiner;)V
        71: return
      StackMapTable: number_of_entries = 2
        frame_type = 252 /* append */
          offset_delta = 13
          locals = [ class scala/collection/parallel/immutable/HashMapCombiner ]
        frame_type = 52 /* same */
      LineNumberTable:
        line 1116: 0
        line 1117: 13
        line 1118: 25
        line 1119: 35
        line 1117: 63
        line 1121: 66
      LocalVariableTable:
        Start  Length  Slot  Name   Signature
           35      28     3  elem   Ljava/lang/Object;
           13      58     2    cb   Lscala/collection/parallel/immutable/HashMapCombiner;
            0      72     0  this   Lscala/collection/parallel/ParIterableLike$GroupBy;
            0      72     1  prev   Lscala/Option;
    Signature: #90                          // (Lscala/Option<Lscala/collection/parallel/immutable/HashMapCombiner<TK;TU;>;>;)V
    MethodParameters:
      Name                           Flags
      prev                           final

  public scala.collection.parallel.ParIterableLike<T, CC, Repr, Sequential>.GroupBy<K, U> newSubtask(scala.collection.parallel.IterableSplitter<T>);
    descriptor: (Lscala/collection/parallel/IterableSplitter;)Lscala/collection/parallel/ParIterableLike$GroupBy;
    flags: (0x0001) ACC_PUBLIC
    Code:
      stack=6, locals=2, args_size=2
         0: new           #2                  // class scala/collection/parallel/ParIterableLike$GroupBy
         3: dup
         4: aload_0
         5: invokevirtual #189                // Method scala$collection$parallel$ParIterableLike$GroupBy$$$outer:()Lscala/collection/parallel/ParIterableLike;
         8: aload_0
         9: getfield      #161                // Field f:Lscala/Function1;
        12: aload_0
        13: getfield      #133                // Field mcf:Lscala/Function0;
        16: aload_1
        17: invokespecial #193                // Method "<init>":(Lscala/collection/parallel/ParIterableLike;Lscala/Function1;Lscala/Function0;Lscala/collection/parallel/IterableSplitter;)V
        20: areturn
      LineNumberTable:
        line 1123: 0
      LocalVariableTable:
        Start  Length  Slot  Name   Signature
            0      21     0  this   Lscala/collection/parallel/ParIterableLike$GroupBy;
            0      21     1     p   Lscala/collection/parallel/IterableSplitter;
    Signature: #184                         // (Lscala/collection/parallel/IterableSplitter<TT;>;)Lscala/collection/parallel/ParIterableLike<TT;TCC;TRepr;TSequential;>.GroupBy<TK;TU;>;
    MethodParameters:
      Name                           Flags
      p                              final

  public void merge(scala.collection.parallel.ParIterableLike<T, CC, Repr, Sequential>.GroupBy<K, U>);
    descriptor: (Lscala/collection/parallel/ParIterableLike$GroupBy;)V
    flags: (0x0001) ACC_PUBLIC
    Code:
      stack=3, locals=2, args_size=2
         0: aload_0
         1: aload_0
         2: invokevirtual #198                // Method result:()Lscala/collection/parallel/immutable/HashMapCombiner;
         5: aload_1
         6: invokevirtual #198                // Method result:()Lscala/collection/parallel/immutable/HashMapCombiner;
         9: invokevirtual #202                // Method scala/collection/parallel/immutable/HashMapCombiner.combine:(Lscala/collection/parallel/Combiner;)Lscala/collection/parallel/Combiner;
        12: checkcast     #140                // class scala/collection/parallel/immutable/HashMapCombiner
        15: invokevirtual #179                // Method result_$eq:(Lscala/collection/parallel/immutable/HashMapCombiner;)V
        18: return
      LineNumberTable:
        line 1127: 0
      LocalVariableTable:
        Start  Length  Slot  Name   Signature
            0      19     0  this   Lscala/collection/parallel/ParIterableLike$GroupBy;
            0      19     1  that   Lscala/collection/parallel/ParIterableLike$GroupBy;
    Signature: #196                         // (Lscala/collection/parallel/ParIterableLike<TT;TCC;TRepr;TSequential;>.GroupBy<TK;TU;>;)V
    MethodParameters:
      Name                           Flags
      that                           final

  public scala.collection.parallel.ParIterableLike scala$collection$parallel$ParIterableLike$GroupBy$$$outer();
    descriptor: ()Lscala/collection/parallel/ParIterableLike;
    flags: (0x1001) ACC_PUBLIC, ACC_SYNTHETIC
    Code:
      stack=1, locals=1, args_size=1
         0: aload_0
         1: getfield      #204                // Field $outer:Lscala/collection/parallel/ParIterableLike;
         4: areturn
      LineNumberTable:
        line 1108: 0
      LocalVariableTable:
        Start  Length  Slot  Name   Signature
            0       5     0  this   Lscala/collection/parallel/ParIterableLike$GroupBy;

  public scala.collection.parallel.ParIterableLike scala$collection$parallel$ParIterableLike$Accessor$$$outer();
    descriptor: ()Lscala/collection/parallel/ParIterableLike;
    flags: (0x1001) ACC_PUBLIC, ACC_SYNTHETIC
    Code:
      stack=1, locals=1, args_size=1
         0: aload_0
         1: invokevirtual #189                // Method scala$collection$parallel$ParIterableLike$GroupBy$$$outer:()Lscala/collection/parallel/ParIterableLike;
         4: areturn
      LineNumberTable:
        line 1108: 0
      LocalVariableTable:
        Start  Length  Slot  Name   Signature
            0       5     0  this   Lscala/collection/parallel/ParIterableLike$GroupBy;

  public scala.collection.parallel.ParIterableLike scala$collection$parallel$ParIterableLike$StrictSplitterCheckTask$$$outer();
    descriptor: ()Lscala/collection/parallel/ParIterableLike;
    flags: (0x1001) ACC_PUBLIC, ACC_SYNTHETIC
    Code:
      stack=1, locals=1, args_size=1
         0: aload_0
         1: invokevirtual #189                // Method scala$collection$parallel$ParIterableLike$GroupBy$$$outer:()Lscala/collection/parallel/ParIterableLike;
         4: areturn
      LineNumberTable:
        line 1108: 0
      LocalVariableTable:
        Start  Length  Slot  Name   Signature
            0       5     0  this   Lscala/collection/parallel/ParIterableLike$GroupBy;

  public void merge(java.lang.Object);
    descriptor: (Ljava/lang/Object;)V
    flags: (0x1041) ACC_PUBLIC, ACC_BRIDGE, ACC_SYNTHETIC
    Code:
      stack=2, locals=2, args_size=2
         0: aload_0
         1: aload_1
         2: checkcast     #2                  // class scala/collection/parallel/ParIterableLike$GroupBy
         5: invokevirtual #208                // Method merge:(Lscala/collection/parallel/ParIterableLike$GroupBy;)V
         8: return
      LineNumberTable:
        line 1108: 0
      LocalVariableTable:
        Start  Length  Slot  Name   Signature
            0       9     0  this   Lscala/collection/parallel/ParIterableLike$GroupBy;
            0       9     1  that   Ljava/lang/Object;
    MethodParameters:
      Name                           Flags
      that                           final

  public scala.collection.parallel.ParIterableLike$Accessor newSubtask(scala.collection.parallel.IterableSplitter);
    descriptor: (Lscala/collection/parallel/IterableSplitter;)Lscala/collection/parallel/ParIterableLike$Accessor;
    flags: (0x1041) ACC_PUBLIC, ACC_BRIDGE, ACC_SYNTHETIC
    Code:
      stack=2, locals=2, args_size=2
         0: aload_0
         1: aload_1
         2: invokevirtual #211                // Method newSubtask:(Lscala/collection/parallel/IterableSplitter;)Lscala/collection/parallel/ParIterableLike$GroupBy;
         5: areturn
      LineNumberTable:
        line 1108: 0
      LocalVariableTable:
        Start  Length  Slot  Name   Signature
            0       6     0  this   Lscala/collection/parallel/ParIterableLike$GroupBy;
            0       6     1     p   Lscala/collection/parallel/IterableSplitter;
    MethodParameters:
      Name                           Flags
      p                              final

  public void result_$eq(java.lang.Object);
    descriptor: (Ljava/lang/Object;)V
    flags: (0x1041) ACC_PUBLIC, ACC_BRIDGE, ACC_SYNTHETIC
    Code:
      stack=2, locals=2, args_size=2
         0: aload_0
         1: aload_1
         2: checkcast     #140                // class scala/collection/parallel/immutable/HashMapCombiner
         5: invokevirtual #179                // Method result_$eq:(Lscala/collection/parallel/immutable/HashMapCombiner;)V
         8: return
      LineNumberTable:
        line 1108: 0
      LocalVariableTable:
        Start  Length  Slot  Name   Signature
            0       9     0  this   Lscala/collection/parallel/ParIterableLike$GroupBy;
            0       9     1   x$1   Ljava/lang/Object;
    MethodParameters:
      Name                           Flags
      x$1                            final

  public java.lang.Object result();
    descriptor: ()Ljava/lang/Object;
    flags: (0x1041) ACC_PUBLIC, ACC_BRIDGE, ACC_SYNTHETIC
    Code:
      stack=1, locals=1, args_size=1
         0: aload_0
         1: invokevirtual #198                // Method result:()Lscala/collection/parallel/immutable/HashMapCombiner;
         4: areturn
      LineNumberTable:
        line 1108: 0
      LocalVariableTable:
        Start  Length  Slot  Name   Signature
            0       5     0  this   Lscala/collection/parallel/ParIterableLike$GroupBy;

  public scala.collection.parallel.ParIterableLike$GroupBy(scala.Function1<U, K>, scala.Function0<scala.collection.parallel.immutable.HashMapCombiner<K, U>>, scala.collection.parallel.IterableSplitter<T>);
    descriptor: (Lscala/collection/parallel/ParIterableLike;Lscala/Function1;Lscala/Function0;Lscala/collection/parallel/IterableSplitter;)V
    flags: (0x0001) ACC_PUBLIC
    Code:
      stack=2, locals=5, args_size=5
         0: aload_0
         1: aload_2
         2: putfield      #161                // Field f:Lscala/Function1;
         5: aload_0
         6: aload_3
         7: putfield      #133                // Field mcf:Lscala/Function0;
        10: aload_0
        11: aload         4
        13: putfield      #122                // Field pit:Lscala/collection/parallel/IterableSplitter;
        16: aload_1
        17: ifnonnull     22
        20: aconst_null
        21: athrow
        22: aload_0
        23: aload_1
        24: putfield      #204                // Field $outer:Lscala/collection/parallel/ParIterableLike;
        27: aload_0
        28: invokespecial #214                // Method java/lang/Object."<init>":()V
        31: aload_0
        32: invokestatic  #217                // InterfaceMethod scala/collection/parallel/Task.$init$:(Lscala/collection/parallel/Task;)V
        35: aload_0
        36: invokestatic  #220                // InterfaceMethod scala/collection/parallel/ParIterableLike$StrictSplitterCheckTask.$init$:(Lscala/collection/parallel/ParIterableLike$StrictSplitterCheckTask;)V
        39: aload_0
        40: invokestatic  #222                // InterfaceMethod scala/collection/parallel/ParIterableLike$Accessor.$init$:(Lscala/collection/parallel/ParIterableLike$Accessor;)V
        43: aload_0
        44: aconst_null
        45: putfield      #126                // Field result:Lscala/collection/parallel/immutable/HashMapCombiner;
        48: return
      StackMapTable: number_of_entries = 1
        frame_type = 22 /* same */
      LineNumberTable:
        line 1109: 0
        line 1110: 5
        line 1111: 10
        line 1108: 16
        line 1112: 27
        line 1113: 43
        line 1108: 48
      LocalVariableTable:
        Start  Length  Slot  Name   Signature
            0      49     0  this   Lscala/collection/parallel/ParIterableLike$GroupBy;
            0      49     1 $outer   Lscala/collection/parallel/ParIterableLike;
            0      49     2     f   Lscala/Function1;
            0      49     3   mcf   Lscala/Function0;
            0      49     4   pit   Lscala/collection/parallel/IterableSplitter;
    Signature: #212                         // (Lscala/Function1<TU;TK;>;Lscala/Function0<Lscala/collection/parallel/immutable/HashMapCombiner<TK;TU;>;>;Lscala/collection/parallel/IterableSplitter<TT;>;)V
    MethodParameters:
      Name                           Flags
      $outer                         final synthetic
      f                              final
      mcf                            final
      pit                            final
}
InnerClasses:
  public static #13= #10 of #12;          // ArrowAssoc$=class scala/Predef$ArrowAssoc$ of class scala/Predef
  public #18= #15 of #17;                 // Accessor=class scala/collection/parallel/ParIterableLike$Accessor of class scala/collection/parallel/ParIterableLike
  public #19= #2 of #17;                  // GroupBy=class scala/collection/parallel/ParIterableLike$GroupBy of class scala/collection/parallel/ParIterableLike
  public #22= #21 of #17;                 // StrictSplitterCheckTask=class scala/collection/parallel/ParIterableLike$StrictSplitterCheckTask of class scala/collection/parallel/ParIterableLike
  public #23= #7 of #17;                  // Transformer=class scala/collection/parallel/ParIterableLike$Transformer of class scala/collection/parallel/ParIterableLike
Signature: #3                           // <K:Ljava/lang/Object;U:Ljava/lang/Object;>Ljava/lang/Object;Lscala/collection/parallel/ParIterableLike<TT;TCC;TRepr;TSequential;>.Transformer<Lscala/collection/parallel/immutable/HashMapCombiner<TK;TU;>;Lscala/collection/parallel/ParIterableLike<TT;TCC;TRepr;TSequential;>.GroupBy<TK;TU;>;>;
SourceFile: "ParIterableLike.scala"
  ScalaInlineInfo: length = 0x8B (unknown attribute)
   01 00 00 1B 00 BE 00 BF 00 00 53 00 3D 00 00 82
   00 59 01 00 C2 00 62 00 00 C2 00 C3 00 00 69 00
   55 00 00 B6 00 D1 00 00 B6 00 B7 00 00 1E 00 77
   00 00 4B 00 4C 00 00 46 00 30 00 00 21 00 4C 00
   00 21 00 7B 00 00 7F 00 62 00 00 7F 00 80 00 00
   CD 00 BB 00 00 28 00 29 01 00 BA 00 BB 00 00 CE
   00 BB 00 00 2F 00 30 00 00 3C 00 3D 00 00 35 00
   36 00 00 24 00 71 00 00 74 00 75 00 00 2A 00 29
   00 00 58 00 59 00 00 61 00 62 00
  Scala: length = 0x0 (unknown attribute)

