Classfile /Users/mw/Projects/slang-braindump/.jar/jar11/assemble/slang-braindump/assemble/content/scala/collection/parallel/ParIterableLike$$anon$7$$anon$8.class
  Last modified May 29, 2022; size 2029 bytes
  SHA-256 checksum 93bf8ba60f1b246b06fb1095507db79c43ea99ea1d71d5653528ba4ada4159fc
  Compiled from "ParIterableLike.scala"
public final class scala.collection.parallel.ParIterableLike$$anon$7$$anon$8 extends java.lang.Object implements scala.collection.parallel.ParIterableLike<T, CC, Repr, Sequential>.BuilderOps<Elem, To>.Otherwise<Cmb>
  minor version: 0
  major version: 52
  flags: (0x0031) ACC_PUBLIC, ACC_FINAL, ACC_SUPER
  this_class: #2                          // scala/collection/parallel/ParIterableLike$$anon$7$$anon$8
  super_class: #5                         // java/lang/Object
  interfaces: 1, fields: 2, methods: 2, attributes: 6
Constant pool:
   #1 = Utf8               scala/collection/parallel/ParIterableLike$$anon$7$$anon$8
   #2 = Class              #1             // scala/collection/parallel/ParIterableLike$$anon$7$$anon$8
   #3 = Utf8               Ljava/lang/Object;Lscala/collection/parallel/ParIterableLike<TT;TCC;TRepr;TSequential;>.BuilderOps<TElem;TTo;>.Otherwise<TCmb;>;
   #4 = Utf8               java/lang/Object
   #5 = Class              #4             // java/lang/Object
   #6 = Utf8               scala/collection/parallel/ParIterableLike$BuilderOps$Otherwise
   #7 = Class              #6             // scala/collection/parallel/ParIterableLike$BuilderOps$Otherwise
   #8 = Utf8               ParIterableLike.scala
   #9 = Utf8               scala/collection/parallel/ParIterableLike$$anon$7
  #10 = Class              #9             // scala/collection/parallel/ParIterableLike$$anon$7
  #11 = Utf8               ifIs
  #12 = Utf8               (Lscala/Function1;)Lscala/collection/parallel/ParIterableLike$BuilderOps$Otherwise;
  #13 = NameAndType        #11:#12        // ifIs:(Lscala/Function1;)Lscala/collection/parallel/ParIterableLike$BuilderOps$Otherwise;
  #14 = Utf8               scala/collection/parallel/ParIterableLike$BuilderOps
  #15 = Class              #14            // scala/collection/parallel/ParIterableLike$BuilderOps
  #16 = Utf8               scala/collection/parallel/ParIterableLike
  #17 = Class              #16            // scala/collection/parallel/ParIterableLike
  #18 = Utf8               BuilderOps
  #19 = Utf8               Otherwise
  #20 = Utf8               $outer
  #21 = Utf8               Lscala/collection/parallel/ParIterableLike$$anon$7;
  #22 = Utf8               isbody$1
  #23 = Utf8               Lscala/Function1;
  #24 = Utf8               otherwise
  #25 = Utf8               (Lscala/Function0;Lscala/reflect/ClassTag;)V
  #26 = Utf8               (Lscala/Function0<Lscala/runtime/BoxedUnit;>;Lscala/reflect/ClassTag<TCmb;>;)V
  #27 = Utf8               notbody
  #28 = Utf8               t
  #29 = NameAndType        #20:#21        // $outer:Lscala/collection/parallel/ParIterableLike$$anon$7;
  #30 = Fieldref           #2.#29         // scala/collection/parallel/ParIterableLike$$anon$7$$anon$8.$outer:Lscala/collection/parallel/ParIterableLike$$anon$7;
  #31 = Utf8               cb$1
  #32 = Utf8               Lscala/collection/mutable/Builder;
  #33 = NameAndType        #31:#32        // cb$1:Lscala/collection/mutable/Builder;
  #34 = Fieldref           #10.#33        // scala/collection/parallel/ParIterableLike$$anon$7.cb$1:Lscala/collection/mutable/Builder;
  #35 = Utf8               getClass
  #36 = Utf8               ()Ljava/lang/Class;
  #37 = NameAndType        #35:#36        // getClass:()Ljava/lang/Class;
  #38 = Methodref          #5.#37         // java/lang/Object.getClass:()Ljava/lang/Class;
  #39 = Utf8               scala/reflect/ClassTag
  #40 = Class              #39            // scala/reflect/ClassTag
  #41 = Utf8               runtimeClass
  #42 = NameAndType        #41:#36        // runtimeClass:()Ljava/lang/Class;
  #43 = InterfaceMethodref #40.#42        // scala/reflect/ClassTag.runtimeClass:()Ljava/lang/Class;
  #44 = Utf8               equals
  #45 = Utf8               (Ljava/lang/Object;)Z
  #46 = NameAndType        #44:#45        // equals:(Ljava/lang/Object;)Z
  #47 = Methodref          #5.#46         // java/lang/Object.equals:(Ljava/lang/Object;)Z
  #48 = NameAndType        #22:#23        // isbody$1:Lscala/Function1;
  #49 = Fieldref           #2.#48         // scala/collection/parallel/ParIterableLike$$anon$7$$anon$8.isbody$1:Lscala/Function1;
  #50 = Utf8               scala/Function1
  #51 = Class              #50            // scala/Function1
  #52 = Utf8               apply
  #53 = Utf8               (Ljava/lang/Object;)Ljava/lang/Object;
  #54 = NameAndType        #52:#53        // apply:(Ljava/lang/Object;)Ljava/lang/Object;
  #55 = InterfaceMethodref #51.#54        // scala/Function1.apply:(Ljava/lang/Object;)Ljava/lang/Object;
  #56 = Utf8               scala/Function0
  #57 = Class              #56            // scala/Function0
  #58 = Utf8               apply$mcV$sp
  #59 = Utf8               ()V
  #60 = NameAndType        #58:#59        // apply$mcV$sp:()V
  #61 = InterfaceMethodref #57.#60        // scala/Function0.apply$mcV$sp:()V
  #62 = Utf8               this
  #63 = Utf8               Lscala/collection/parallel/ParIterableLike$$anon$7$$anon$8;
  #64 = Utf8               Lscala/Function0;
  #65 = Utf8               Lscala/reflect/ClassTag;
  #66 = Utf8               java/lang/Class
  #67 = Class              #66            // java/lang/Class
  #68 = Utf8               <init>
  #69 = Utf8               (Lscala/collection/parallel/ParIterableLike$$anon$7;Lscala/Function1;)V
  #70 = NameAndType        #68:#59        // "<init>":()V
  #71 = Methodref          #5.#70         // java/lang/Object."<init>":()V
  #72 = Utf8               Code
  #73 = Utf8               StackMapTable
  #74 = Utf8               LineNumberTable
  #75 = Utf8               LocalVariableTable
  #76 = Utf8               Signature
  #77 = Utf8               MethodParameters
  #78 = Utf8               InnerClasses
  #79 = Utf8               EnclosingMethod
  #80 = Utf8               SourceFile
  #81 = Utf8               ScalaInlineInfo
  #82 = Utf8               Scala
{
  private final scala.collection.parallel.ParIterableLike$$anon$7 $outer;
    descriptor: Lscala/collection/parallel/ParIterableLike$$anon$7;
    flags: (0x1012) ACC_PRIVATE, ACC_FINAL, ACC_SYNTHETIC

  private final scala.Function1 isbody$1;
    descriptor: Lscala/Function1;
    flags: (0x0012) ACC_PRIVATE, ACC_FINAL

  public void otherwise(scala.Function0<scala.runtime.BoxedUnit>, scala.reflect.ClassTag<Cmb>);
    descriptor: (Lscala/Function0;Lscala/reflect/ClassTag;)V
    flags: (0x0001) ACC_PUBLIC
    Code:
      stack=2, locals=4, args_size=3
         0: aload_0
         1: getfield      #30                 // Field $outer:Lscala/collection/parallel/ParIterableLike$$anon$7;
         4: getfield      #34                 // Field scala/collection/parallel/ParIterableLike$$anon$7.cb$1:Lscala/collection/mutable/Builder;
         7: invokevirtual #38                 // Method java/lang/Object.getClass:()Ljava/lang/Class;
        10: aload_2
        11: invokeinterface #43,  1           // InterfaceMethod scala/reflect/ClassTag.runtimeClass:()Ljava/lang/Class;
        16: astore_3
        17: dup
        18: ifnonnull     29
        21: pop
        22: aload_3
        23: ifnull        36
        26: goto          56
        29: aload_3
        30: invokevirtual #47                 // Method java/lang/Object.equals:(Ljava/lang/Object;)Z
        33: ifeq          56
        36: aload_0
        37: getfield      #49                 // Field isbody$1:Lscala/Function1;
        40: aload_0
        41: getfield      #30                 // Field $outer:Lscala/collection/parallel/ParIterableLike$$anon$7;
        44: getfield      #34                 // Field scala/collection/parallel/ParIterableLike$$anon$7.cb$1:Lscala/collection/mutable/Builder;
        47: invokeinterface #55,  2           // InterfaceMethod scala/Function1.apply:(Ljava/lang/Object;)Ljava/lang/Object;
        52: pop
        53: goto          62
        56: aload_1
        57: invokeinterface #61,  1           // InterfaceMethod scala/Function0.apply$mcV$sp:()V
        62: return
      StackMapTable: number_of_entries = 4
        frame_type = 255 /* full_frame */
          offset_delta = 29
          locals = [ class scala/collection/parallel/ParIterableLike$$anon$7$$anon$8, class scala/Function0, class scala/reflect/ClassTag, class java/lang/Class ]
          stack = [ class java/lang/Class ]
        frame_type = 6 /* same */
        frame_type = 19 /* same */
        frame_type = 5 /* same */
      LineNumberTable:
        line 328: 0
      LocalVariableTable:
        Start  Length  Slot  Name   Signature
            0      63     0  this   Lscala/collection/parallel/ParIterableLike$$anon$7$$anon$8;
            0      63     1 notbody   Lscala/Function0;
            0      63     2     t   Lscala/reflect/ClassTag;
    Signature: #26                          // (Lscala/Function0<Lscala/runtime/BoxedUnit;>;Lscala/reflect/ClassTag<TCmb;>;)V
    MethodParameters:
      Name                           Flags
      notbody                        final
      t                              final

  public scala.collection.parallel.ParIterableLike$$anon$7$$anon$8(scala.collection.parallel.ParIterableLike$$anon$7, scala.Function1);
    descriptor: (Lscala/collection/parallel/ParIterableLike$$anon$7;Lscala/Function1;)V
    flags: (0x0001) ACC_PUBLIC
    Code:
      stack=2, locals=3, args_size=3
         0: aload_1
         1: ifnonnull     6
         4: aconst_null
         5: athrow
         6: aload_0
         7: aload_1
         8: putfield      #30                 // Field $outer:Lscala/collection/parallel/ParIterableLike$$anon$7;
        11: aload_0
        12: aload_2
        13: putfield      #49                 // Field isbody$1:Lscala/Function1;
        16: aload_0
        17: invokespecial #71                 // Method java/lang/Object."<init>":()V
        20: return
      StackMapTable: number_of_entries = 1
        frame_type = 6 /* same */
      LineNumberTable:
        line 326: 0
      LocalVariableTable:
        Start  Length  Slot  Name   Signature
            0      21     0  this   Lscala/collection/parallel/ParIterableLike$$anon$7$$anon$8;
            0      21     1 $outer   Lscala/collection/parallel/ParIterableLike$$anon$7;
            0      21     2 isbody$1   Lscala/Function1;
    MethodParameters:
      Name                           Flags
      $outer                         final synthetic
      isbody$1                       final
}
InnerClasses:
  public final #10;                       // class scala/collection/parallel/ParIterableLike$$anon$7
  public final #2;                        // class scala/collection/parallel/ParIterableLike$$anon$7$$anon$8
  public #18= #15 of #17;                 // BuilderOps=class scala/collection/parallel/ParIterableLike$BuilderOps of class scala/collection/parallel/ParIterableLike
  public #19= #7 of #15;                  // Otherwise=class scala/collection/parallel/ParIterableLike$BuilderOps$Otherwise of class scala/collection/parallel/ParIterableLike$BuilderOps
EnclosingMethod: #10.#13                // scala.collection.parallel.ParIterableLike$$anon$7.ifIs
Signature: #3                           // Ljava/lang/Object;Lscala/collection/parallel/ParIterableLike<TT;TCC;TRepr;TSequential;>.BuilderOps<TElem;TTo;>.Otherwise<TCmb;>;
SourceFile: "ParIterableLike.scala"
  ScalaInlineInfo: length = 0xE (unknown attribute)
   01 01 00 02 00 44 00 45 01 00 18 00 19 01
  Scala: length = 0x0 (unknown attribute)

