Classfile /Users/mw/Projects/slang-braindump/.jar/jar11/assemble/slang-braindump/assemble/content/scala/collection/parallel/ParIterableLike$StrictSplitterCheckTask.class
  Last modified May 29, 2022; size 1562 bytes
  SHA-256 checksum 9d87ddcb7499dbe9b748f633c90111fc1efa99dd015725bf8fa52db59beec105
  Compiled from "ParIterableLike.scala"
public interface scala.collection.parallel.ParIterableLike$StrictSplitterCheckTask<R extends java.lang.Object, Tp extends java.lang.Object> extends scala.collection.parallel.Task<R, Tp>
  minor version: 0
  major version: 52
  flags: (0x0601) ACC_PUBLIC, ACC_INTERFACE, ACC_ABSTRACT
  this_class: #2                          // scala/collection/parallel/ParIterableLike$StrictSplitterCheckTask
  super_class: #5                         // java/lang/Object
  interfaces: 1, fields: 0, methods: 4, attributes: 5
Constant pool:
   #1 = Utf8               scala/collection/parallel/ParIterableLike$StrictSplitterCheckTask
   #2 = Class              #1             // scala/collection/parallel/ParIterableLike$StrictSplitterCheckTask
   #3 = Utf8               <R:Ljava/lang/Object;Tp:Ljava/lang/Object;>Ljava/lang/Object;Lscala/collection/parallel/Task<TR;TTp;>;
   #4 = Utf8               java/lang/Object
   #5 = Class              #4             // java/lang/Object
   #6 = Utf8               scala/collection/parallel/Task
   #7 = Class              #6             // scala/collection/parallel/Task
   #8 = Utf8               ParIterableLike.scala
   #9 = Utf8               scala/collection/parallel/ParIterableLike
  #10 = Class              #9             // scala/collection/parallel/ParIterableLike
  #11 = Utf8               StrictSplitterCheckTask
  #12 = Utf8               requiresStrictSplitters$
  #13 = Utf8               (Lscala/collection/parallel/ParIterableLike$StrictSplitterCheckTask;)Z
  #14 = Utf8               $this
  #15 = Utf8               requiresStrictSplitters
  #16 = Utf8               ()Z
  #17 = NameAndType        #15:#16        // requiresStrictSplitters:()Z
  #18 = InterfaceMethodref #2.#17         // scala/collection/parallel/ParIterableLike$StrictSplitterCheckTask.requiresStrictSplitters:()Z
  #19 = Utf8               Lscala/collection/parallel/ParIterableLike$StrictSplitterCheckTask;
  #20 = Utf8               this
  #21 = Utf8               scala$collection$parallel$ParIterableLike$StrictSplitterCheckTask$$$outer
  #22 = Utf8               ()Lscala/collection/parallel/ParIterableLike;
  #23 = Utf8               $init$
  #24 = Utf8               (Lscala/collection/parallel/ParIterableLike$StrictSplitterCheckTask;)V
  #25 = Utf8               (Lscala/collection/parallel/ParIterableLike<TT;TCC;TRepr;TSequential;>.StrictSplitterCheckTask;)V
  #26 = NameAndType        #21:#22        // scala$collection$parallel$ParIterableLike$StrictSplitterCheckTask$$$outer:()Lscala/collection/parallel/ParIterableLike;
  #27 = InterfaceMethodref #2.#26         // scala/collection/parallel/ParIterableLike$StrictSplitterCheckTask.scala$collection$parallel$ParIterableLike$StrictSplitterCheckTask$$$outer:()Lscala/collection/parallel/ParIterableLike;
  #28 = Utf8               isStrictSplitterCollection
  #29 = NameAndType        #28:#16        // isStrictSplitterCollection:()Z
  #30 = InterfaceMethodref #10.#29        // scala/collection/parallel/ParIterableLike.isStrictSplitterCollection:()Z
  #31 = Utf8               java/lang/UnsupportedOperationException
  #32 = Class              #31            // java/lang/UnsupportedOperationException
  #33 = Utf8               This collection does not provide strict splitters.
  #34 = String             #33            // This collection does not provide strict splitters.
  #35 = Utf8               <init>
  #36 = Utf8               (Ljava/lang/String;)V
  #37 = NameAndType        #35:#36        // "<init>":(Ljava/lang/String;)V
  #38 = Methodref          #32.#37        // java/lang/UnsupportedOperationException."<init>":(Ljava/lang/String;)V
  #39 = Utf8               Code
  #40 = Utf8               LineNumberTable
  #41 = Utf8               LocalVariableTable
  #42 = Utf8               MethodParameters
  #43 = Utf8               StackMapTable
  #44 = Utf8               Signature
  #45 = Utf8               InnerClasses
  #46 = Utf8               SourceFile
  #47 = Utf8               ScalaInlineInfo
  #48 = Utf8               Scala
{
  public static boolean requiresStrictSplitters$(scala.collection.parallel.ParIterableLike$StrictSplitterCheckTask);
    descriptor: (Lscala/collection/parallel/ParIterableLike$StrictSplitterCheckTask;)Z
    flags: (0x1009) ACC_PUBLIC, ACC_STATIC, ACC_SYNTHETIC
    Code:
      stack=1, locals=1, args_size=1
         0: aload_0
         1: invokespecial #18                 // InterfaceMethod requiresStrictSplitters:()Z
         4: ireturn
      LineNumberTable:
        line 853: 0
      LocalVariableTable:
        Start  Length  Slot  Name   Signature
            0       5     0 $this   Lscala/collection/parallel/ParIterableLike$StrictSplitterCheckTask;
    MethodParameters:
      Name                           Flags
      $this                          final synthetic

  public default boolean requiresStrictSplitters();
    descriptor: ()Z
    flags: (0x0001) ACC_PUBLIC
    Code:
      stack=1, locals=1, args_size=1
         0: iconst_0
         1: ireturn
      LineNumberTable:
        line 853: 0
      LocalVariableTable:
        Start  Length  Slot  Name   Signature
            0       2     0  this   Lscala/collection/parallel/ParIterableLike$StrictSplitterCheckTask;

  public abstract scala.collection.parallel.ParIterableLike scala$collection$parallel$ParIterableLike$StrictSplitterCheckTask$$$outer();
    descriptor: ()Lscala/collection/parallel/ParIterableLike;
    flags: (0x1401) ACC_PUBLIC, ACC_ABSTRACT, ACC_SYNTHETIC

  public static void $init$(scala.collection.parallel.ParIterableLike<T, CC, Repr, Sequential>.StrictSplitterCheckTask);
    descriptor: (Lscala/collection/parallel/ParIterableLike$StrictSplitterCheckTask;)V
    flags: (0x0009) ACC_PUBLIC, ACC_STATIC
    Code:
      stack=3, locals=1, args_size=1
         0: aload_0
         1: invokeinterface #18,  1           // InterfaceMethod requiresStrictSplitters:()Z
         6: ifeq          33
         9: aload_0
        10: invokeinterface #27,  1           // InterfaceMethod scala$collection$parallel$ParIterableLike$StrictSplitterCheckTask$$$outer:()Lscala/collection/parallel/ParIterableLike;
        15: invokeinterface #30,  1           // InterfaceMethod scala/collection/parallel/ParIterableLike.isStrictSplitterCollection:()Z
        20: ifne          33
        23: new           #32                 // class java/lang/UnsupportedOperationException
        26: dup
        27: ldc           #34                 // String This collection does not provide strict splitters.
        29: invokespecial #38                 // Method java/lang/UnsupportedOperationException."<init>":(Ljava/lang/String;)V
        32: athrow
        33: return
      StackMapTable: number_of_entries = 1
        frame_type = 33 /* same */
      LineNumberTable:
        line 854: 0
        line 855: 23
        line 852: 33
      LocalVariableTable:
        Start  Length  Slot  Name   Signature
            0      34     0 $this   Lscala/collection/parallel/ParIterableLike$StrictSplitterCheckTask;
    Signature: #25                          // (Lscala/collection/parallel/ParIterableLike<TT;TCC;TRepr;TSequential;>.StrictSplitterCheckTask;)V
    MethodParameters:
      Name                           Flags
      $this                          final synthetic
}
InnerClasses:
  public #11= #2 of #10;                  // StrictSplitterCheckTask=class scala/collection/parallel/ParIterableLike$StrictSplitterCheckTask of class scala/collection/parallel/ParIterableLike
Signature: #3                           // <R:Ljava/lang/Object;Tp:Ljava/lang/Object;>Ljava/lang/Object;Lscala/collection/parallel/Task<TR;TTp;>;
SourceFile: "ParIterableLike.scala"
  ScalaInlineInfo: length = 0x18 (unknown attribute)
   01 00 00 04 00 17 00 18 01 00 0F 00 10 00 00 0C
   00 0D 01 00 15 00 16 00
  Scala: length = 0x0 (unknown attribute)

