Classfile /Users/mw/Projects/slang-braindump/.jar/jar11/assemble/slang-braindump/assemble/content/scala/collection/parallel/ParIterableLike$$anon$10.class
  Last modified May 29, 2022; size 701 bytes
  SHA-256 checksum 618e338c9253614e1857bb09ef6526cd850fd136b059802084fb647e839520aa
  Compiled from "ParIterableLike.scala"
public final class scala.collection.parallel.ParIterableLike$$anon$10 extends scala.collection.generic.DefaultSignalling
  minor version: 0
  major version: 52
  flags: (0x0031) ACC_PUBLIC, ACC_FINAL, ACC_SUPER
  this_class: #2                          // scala/collection/parallel/ParIterableLike$$anon$10
  super_class: #4                         // scala/collection/generic/DefaultSignalling
  interfaces: 0, fields: 0, methods: 1, attributes: 5
Constant pool:
   #1 = Utf8               scala/collection/parallel/ParIterableLike$$anon$10
   #2 = Class              #1             // scala/collection/parallel/ParIterableLike$$anon$10
   #3 = Utf8               scala/collection/generic/DefaultSignalling
   #4 = Class              #3             // scala/collection/generic/DefaultSignalling
   #5 = Utf8               ParIterableLike.scala
   #6 = Utf8               scala/collection/parallel/ParIterableLike
   #7 = Class              #6             // scala/collection/parallel/ParIterableLike
   #8 = Utf8               exists
   #9 = Utf8               (Lscala/Function1;)Z
  #10 = NameAndType        #8:#9          // exists:(Lscala/Function1;)Z
  #11 = Utf8               <init>
  #12 = Utf8               (Lscala/collection/parallel/ParIterableLike;)V
  #13 = Utf8               $outer
  #14 = Utf8               ()V
  #15 = NameAndType        #11:#14        // "<init>":()V
  #16 = Methodref          #4.#15         // scala/collection/generic/DefaultSignalling."<init>":()V
  #17 = Utf8               this
  #18 = Utf8               Lscala/collection/parallel/ParIterableLike$$anon$10;
  #19 = Utf8               Lscala/collection/parallel/ParIterableLike;
  #20 = Utf8               Code
  #21 = Utf8               LineNumberTable
  #22 = Utf8               LocalVariableTable
  #23 = Utf8               MethodParameters
  #24 = Utf8               InnerClasses
  #25 = Utf8               EnclosingMethod
  #26 = Utf8               SourceFile
  #27 = Utf8               ScalaInlineInfo
  #28 = Utf8               Scala
{
  public scala.collection.parallel.ParIterableLike$$anon$10(scala.collection.parallel.ParIterableLike);
    descriptor: (Lscala/collection/parallel/ParIterableLike;)V
    flags: (0x0001) ACC_PUBLIC
    Code:
      stack=1, locals=2, args_size=2
         0: aload_0
         1: invokespecial #16                 // Method scala/collection/generic/DefaultSignalling."<init>":()V
         4: return
      LineNumberTable:
        line 522: 0
      LocalVariableTable:
        Start  Length  Slot  Name   Signature
            0       5     0  this   Lscala/collection/parallel/ParIterableLike$$anon$10;
            0       5     1 $outer   Lscala/collection/parallel/ParIterableLike;
    MethodParameters:
      Name                           Flags
      $outer                         final synthetic
}
InnerClasses:
  public final #2;                        // class scala/collection/parallel/ParIterableLike$$anon$10
EnclosingMethod: #7.#10                 // scala.collection.parallel.ParIterableLike.exists
SourceFile: "ParIterableLike.scala"
  ScalaInlineInfo: length = 0x9 (unknown attribute)
   01 01 00 01 00 0B 00 0C 01
  Scala: length = 0x0 (unknown attribute)

