Classfile /Users/mw/Projects/slang-braindump/.jar/jar11/assemble/slang-braindump/assemble/content/scala/collection/parallel/ParIterableLike$$anon$1$$anon$4.class
  Last modified May 29, 2022; size 2231 bytes
  SHA-256 checksum 9e7935fece655af8a743a0006bb9ac2cdbd5ef1e886d3c0b2e03ff92dd6120a5
  Compiled from "ParIterableLike.scala"
public final class scala.collection.parallel.ParIterableLike$$anon$1$$anon$4 extends scala.collection.parallel.ParIterableLike<T, CC, Repr, Sequential>.ParComposite<R, R2, R3, scala.collection.parallel.ParIterableLike<T, CC, Repr, Sequential>.StrictSplitterCheckTask<R, Tp>, scala.collection.parallel.ParIterableLike<T, CC, Repr, Sequential>.StrictSplitterCheckTask<R2, Tp2>>
  minor version: 0
  major version: 52
  flags: (0x0031) ACC_PUBLIC, ACC_FINAL, ACC_SUPER
  this_class: #2                          // scala/collection/parallel/ParIterableLike$$anon$1$$anon$4
  super_class: #5                         // scala/collection/parallel/ParIterableLike$ParComposite
  interfaces: 0, fields: 1, methods: 2, attributes: 6
Constant pool:
   #1 = Utf8               scala/collection/parallel/ParIterableLike$$anon$1$$anon$4
   #2 = Class              #1             // scala/collection/parallel/ParIterableLike$$anon$1$$anon$4
   #3 = Utf8               Lscala/collection/parallel/ParIterableLike<TT;TCC;TRepr;TSequential;>.ParComposite<TR;TR2;TR3;Lscala/collection/parallel/ParIterableLike<TT;TCC;TRepr;TSequential;>.StrictSplitterCheckTask<TR;TTp;>;Lscala/collection/parallel/ParIterableLike<TT;TCC;TRepr;TSequential;>.StrictSplitterCheckTask<TR2;TTp2;>;>;
   #4 = Utf8               scala/collection/parallel/ParIterableLike$ParComposite
   #5 = Class              #4             // scala/collection/parallel/ParIterableLike$ParComposite
   #6 = Utf8               ParIterableLike.scala
   #7 = Utf8               scala/collection/parallel/ParIterableLike$$anon$1
   #8 = Class              #7             // scala/collection/parallel/ParIterableLike$$anon$1
   #9 = Utf8               parallel
  #10 = Utf8               (Lscala/collection/parallel/ParIterableLike$StrictSplitterCheckTask;Lscala/Function2;)Lscala/collection/parallel/ParIterableLike$ParComposite;
  #11 = NameAndType        #9:#10         // parallel:(Lscala/collection/parallel/ParIterableLike$StrictSplitterCheckTask;Lscala/Function2;)Lscala/collection/parallel/ParIterableLike$ParComposite;
  #12 = Utf8               scala/collection/parallel/ParIterableLike
  #13 = Class              #12            // scala/collection/parallel/ParIterableLike
  #14 = Utf8               ParComposite
  #15 = Utf8               scala/collection/parallel/ParIterableLike$StrictSplitterCheckTask
  #16 = Class              #15            // scala/collection/parallel/ParIterableLike$StrictSplitterCheckTask
  #17 = Utf8               StrictSplitterCheckTask
  #18 = Utf8               resCombiner$2
  #19 = Utf8               Lscala/Function2;
  #20 = Utf8               combineResults
  #21 = Utf8               (Ljava/lang/Object;Ljava/lang/Object;)Ljava/lang/Object;
  #22 = Utf8               (TR;TR2;)TR3;
  #23 = Utf8               fr
  #24 = Utf8               sr
  #25 = NameAndType        #18:#19        // resCombiner$2:Lscala/Function2;
  #26 = Fieldref           #2.#25         // scala/collection/parallel/ParIterableLike$$anon$1$$anon$4.resCombiner$2:Lscala/Function2;
  #27 = Utf8               scala/Function2
  #28 = Class              #27            // scala/Function2
  #29 = Utf8               apply
  #30 = NameAndType        #29:#21        // apply:(Ljava/lang/Object;Ljava/lang/Object;)Ljava/lang/Object;
  #31 = InterfaceMethodref #28.#30        // scala/Function2.apply:(Ljava/lang/Object;Ljava/lang/Object;)Ljava/lang/Object;
  #32 = Utf8               this
  #33 = Utf8               Lscala/collection/parallel/ParIterableLike$$anon$1$$anon$4;
  #34 = Utf8               Ljava/lang/Object;
  #35 = Utf8               <init>
  #36 = Utf8               (Lscala/collection/parallel/ParIterableLike$$anon$1;Lscala/collection/parallel/ParIterableLike$StrictSplitterCheckTask;Lscala/Function2;)V
  #37 = Utf8               $outer
  #38 = Utf8               t2$2
  #39 = Utf8               scala$collection$parallel$ParIterableLike$$anon$$$outer
  #40 = Utf8               ()Lscala/collection/parallel/ParIterableLike;
  #41 = NameAndType        #39:#40        // scala$collection$parallel$ParIterableLike$$anon$$$outer:()Lscala/collection/parallel/ParIterableLike;
  #42 = Methodref          #8.#41         // scala/collection/parallel/ParIterableLike$$anon$1.scala$collection$parallel$ParIterableLike$$anon$$$outer:()Lscala/collection/parallel/ParIterableLike;
  #43 = Utf8               tsk$1
  #44 = Utf8               Lscala/collection/parallel/ParIterableLike$StrictSplitterCheckTask;
  #45 = NameAndType        #43:#44        // tsk$1:Lscala/collection/parallel/ParIterableLike$StrictSplitterCheckTask;
  #46 = Fieldref           #8.#45         // scala/collection/parallel/ParIterableLike$$anon$1.tsk$1:Lscala/collection/parallel/ParIterableLike$StrictSplitterCheckTask;
  #47 = Utf8               (Lscala/collection/parallel/ParIterableLike;Lscala/collection/parallel/ParIterableLike$StrictSplitterCheckTask;Lscala/collection/parallel/ParIterableLike$StrictSplitterCheckTask;)V
  #48 = NameAndType        #35:#47        // "<init>":(Lscala/collection/parallel/ParIterableLike;Lscala/collection/parallel/ParIterableLike$StrictSplitterCheckTask;Lscala/collection/parallel/ParIterableLike$StrictSplitterCheckTask;)V
  #49 = Methodref          #5.#48         // scala/collection/parallel/ParIterableLike$ParComposite."<init>":(Lscala/collection/parallel/ParIterableLike;Lscala/collection/parallel/ParIterableLike$StrictSplitterCheckTask;Lscala/collection/parallel/ParIterableLike$StrictSplitterCheckTask;)V
  #50 = Utf8               Lscala/collection/parallel/ParIterableLike$$anon$1;
  #51 = Utf8               Code
  #52 = Utf8               LineNumberTable
  #53 = Utf8               LocalVariableTable
  #54 = Utf8               Signature
  #55 = Utf8               MethodParameters
  #56 = Utf8               InnerClasses
  #57 = Utf8               EnclosingMethod
  #58 = Utf8               SourceFile
  #59 = Utf8               ScalaInlineInfo
  #60 = Utf8               Scala
{
  private final scala.Function2 resCombiner$2;
    descriptor: Lscala/Function2;
    flags: (0x0012) ACC_PRIVATE, ACC_FINAL

  public R3 combineResults(R, R2);
    descriptor: (Ljava/lang/Object;Ljava/lang/Object;)Ljava/lang/Object;
    flags: (0x0001) ACC_PUBLIC
    Code:
      stack=3, locals=3, args_size=3
         0: aload_0
         1: getfield      #26                 // Field resCombiner$2:Lscala/Function2;
         4: aload_1
         5: aload_2
         6: invokeinterface #31,  3           // InterfaceMethod scala/Function2.apply:(Ljava/lang/Object;Ljava/lang/Object;)Ljava/lang/Object;
        11: areturn
      LineNumberTable:
        line 308: 0
      LocalVariableTable:
        Start  Length  Slot  Name   Signature
            0      12     0  this   Lscala/collection/parallel/ParIterableLike$$anon$1$$anon$4;
            0      12     1    fr   Ljava/lang/Object;
            0      12     2    sr   Ljava/lang/Object;
    Signature: #22                          // (TR;TR2;)TR3;
    MethodParameters:
      Name                           Flags
      fr                             final
      sr                             final

  public scala.collection.parallel.ParIterableLike$$anon$1$$anon$4(scala.collection.parallel.ParIterableLike$$anon$1, scala.collection.parallel.ParIterableLike$StrictSplitterCheckTask, scala.Function2);
    descriptor: (Lscala/collection/parallel/ParIterableLike$$anon$1;Lscala/collection/parallel/ParIterableLike$StrictSplitterCheckTask;Lscala/Function2;)V
    flags: (0x0001) ACC_PUBLIC
    Code:
      stack=4, locals=4, args_size=4
         0: aload_0
         1: aload_3
         2: putfield      #26                 // Field resCombiner$2:Lscala/Function2;
         5: aload_0
         6: aload_1
         7: invokevirtual #42                 // Method scala/collection/parallel/ParIterableLike$$anon$1.scala$collection$parallel$ParIterableLike$$anon$$$outer:()Lscala/collection/parallel/ParIterableLike;
        10: aload_1
        11: getfield      #46                 // Field scala/collection/parallel/ParIterableLike$$anon$1.tsk$1:Lscala/collection/parallel/ParIterableLike$StrictSplitterCheckTask;
        14: aload_2
        15: invokespecial #49                 // Method scala/collection/parallel/ParIterableLike$ParComposite."<init>":(Lscala/collection/parallel/ParIterableLike;Lscala/collection/parallel/ParIterableLike$StrictSplitterCheckTask;Lscala/collection/parallel/ParIterableLike$StrictSplitterCheckTask;)V
        18: return
      LineNumberTable:
        line 307: 0
      LocalVariableTable:
        Start  Length  Slot  Name   Signature
            0      19     0  this   Lscala/collection/parallel/ParIterableLike$$anon$1$$anon$4;
            0      19     1 $outer   Lscala/collection/parallel/ParIterableLike$$anon$1;
            0      19     2  t2$2   Lscala/collection/parallel/ParIterableLike$StrictSplitterCheckTask;
            0      19     3 resCombiner$2   Lscala/Function2;
    MethodParameters:
      Name                           Flags
      $outer                         final synthetic
      t2$2                           final
      resCombiner$2                  final
}
InnerClasses:
  public final #8;                        // class scala/collection/parallel/ParIterableLike$$anon$1
  public final #2;                        // class scala/collection/parallel/ParIterableLike$$anon$1$$anon$4
  public abstract #14= #5 of #13;         // ParComposite=class scala/collection/parallel/ParIterableLike$ParComposite of class scala/collection/parallel/ParIterableLike
  public #17= #16 of #13;                 // StrictSplitterCheckTask=class scala/collection/parallel/ParIterableLike$StrictSplitterCheckTask of class scala/collection/parallel/ParIterableLike
EnclosingMethod: #8.#11                 // scala.collection.parallel.ParIterableLike$$anon$1.parallel
Signature: #3                           // Lscala/collection/parallel/ParIterableLike<TT;TCC;TRepr;TSequential;>.ParComposite<TR;TR2;TR3;Lscala/collection/parallel/ParIterableLike<TT;TCC;TRepr;TSequential;>.StrictSplitterCheckTask<TR;TTp;>;Lscala/collection/parallel/ParIterableLike<TT;TCC;TRepr;TSequential;>.StrictSplitterCheckTask<TR2;TTp2;>;>;
SourceFile: "ParIterableLike.scala"
  ScalaInlineInfo: length = 0xE (unknown attribute)
   01 01 00 02 00 23 00 24 01 00 14 00 15 01
  Scala: length = 0x0 (unknown attribute)

