Classfile /Users/mw/Projects/slang-braindump/.jar/jar11/assemble/slang-braindump/assemble/content/scala/collection/parallel/ParIterableLike$$anon$18.class
  Last modified May 29, 2022; size 2035 bytes
  SHA-256 checksum 217c8260140fa81949b2cba75b6f9b503d37517bf5aa25fb47002737e8941f4c
  Compiled from "ParIterableLike.scala"
public final class scala.collection.parallel.ParIterableLike$$anon$18 extends scala.collection.generic.DefaultSignalling implements scala.collection.generic.AtomicIndexFlag
  minor version: 0
  major version: 52
  flags: (0x0031) ACC_PUBLIC, ACC_FINAL, ACC_SUPER
  this_class: #2                          // scala/collection/parallel/ParIterableLike$$anon$18
  super_class: #4                         // scala/collection/generic/DefaultSignalling
  interfaces: 1, fields: 1, methods: 7, attributes: 5
Constant pool:
   #1 = Utf8               scala/collection/parallel/ParIterableLike$$anon$18
   #2 = Class              #1             // scala/collection/parallel/ParIterableLike$$anon$18
   #3 = Utf8               scala/collection/generic/DefaultSignalling
   #4 = Class              #3             // scala/collection/generic/DefaultSignalling
   #5 = Utf8               scala/collection/generic/AtomicIndexFlag
   #6 = Class              #5             // scala/collection/generic/AtomicIndexFlag
   #7 = Utf8               ParIterableLike.scala
   #8 = Utf8               scala/collection/parallel/ParIterableLike
   #9 = Class              #8             // scala/collection/parallel/ParIterableLike
  #10 = Utf8               dropWhile
  #11 = Utf8               (Lscala/Function1;)Lscala/collection/parallel/ParIterable;
  #12 = NameAndType        #10:#11        // dropWhile:(Lscala/Function1;)Lscala/collection/parallel/ParIterable;
  #13 = Utf8               scala$collection$generic$AtomicIndexFlag$$intflag
  #14 = Utf8               Ljava/util/concurrent/atomic/AtomicInteger;
  #15 = Utf8               indexFlag
  #16 = Utf8               ()I
  #17 = Utf8               indexFlag$
  #18 = Utf8               (Lscala/collection/generic/AtomicIndexFlag;)I
  #19 = NameAndType        #17:#18        // indexFlag$:(Lscala/collection/generic/AtomicIndexFlag;)I
  #20 = InterfaceMethodref #6.#19         // scala/collection/generic/AtomicIndexFlag.indexFlag$:(Lscala/collection/generic/AtomicIndexFlag;)I
  #21 = Utf8               this
  #22 = Utf8               Lscala/collection/parallel/ParIterableLike$$anon$18;
  #23 = Utf8               setIndexFlag
  #24 = Utf8               (I)V
  #25 = Utf8               f
  #26 = Utf8               setIndexFlag$
  #27 = Utf8               (Lscala/collection/generic/AtomicIndexFlag;I)V
  #28 = NameAndType        #26:#27        // setIndexFlag$:(Lscala/collection/generic/AtomicIndexFlag;I)V
  #29 = InterfaceMethodref #6.#28         // scala/collection/generic/AtomicIndexFlag.setIndexFlag$:(Lscala/collection/generic/AtomicIndexFlag;I)V
  #30 = Utf8               I
  #31 = Utf8               setIndexFlagIfGreater
  #32 = Utf8               setIndexFlagIfGreater$
  #33 = NameAndType        #32:#27        // setIndexFlagIfGreater$:(Lscala/collection/generic/AtomicIndexFlag;I)V
  #34 = InterfaceMethodref #6.#33         // scala/collection/generic/AtomicIndexFlag.setIndexFlagIfGreater$:(Lscala/collection/generic/AtomicIndexFlag;I)V
  #35 = Utf8               setIndexFlagIfLesser
  #36 = Utf8               setIndexFlagIfLesser$
  #37 = NameAndType        #36:#27        // setIndexFlagIfLesser$:(Lscala/collection/generic/AtomicIndexFlag;I)V
  #38 = InterfaceMethodref #6.#37         // scala/collection/generic/AtomicIndexFlag.setIndexFlagIfLesser$:(Lscala/collection/generic/AtomicIndexFlag;I)V
  #39 = Utf8               ()Ljava/util/concurrent/atomic/AtomicInteger;
  #40 = NameAndType        #13:#14        // scala$collection$generic$AtomicIndexFlag$$intflag:Ljava/util/concurrent/atomic/AtomicInteger;
  #41 = Fieldref           #2.#40         // scala/collection/parallel/ParIterableLike$$anon$18.scala$collection$generic$AtomicIndexFlag$$intflag:Ljava/util/concurrent/atomic/AtomicInteger;
  #42 = Utf8               scala$collection$generic$AtomicIndexFlag$_setter_$scala$collection$generic$AtomicIndexFlag$$intflag_$eq
  #43 = Utf8               (Ljava/util/concurrent/atomic/AtomicInteger;)V
  #44 = Utf8               x$1
  #45 = Utf8               <init>
  #46 = Utf8               (Lscala/collection/parallel/ParIterableLike;)V
  #47 = Utf8               $outer
  #48 = Utf8               ()V
  #49 = NameAndType        #45:#48        // "<init>":()V
  #50 = Methodref          #4.#49         // scala/collection/generic/DefaultSignalling."<init>":()V
  #51 = Utf8               $init$
  #52 = Utf8               (Lscala/collection/generic/AtomicIndexFlag;)V
  #53 = NameAndType        #51:#52        // $init$:(Lscala/collection/generic/AtomicIndexFlag;)V
  #54 = InterfaceMethodref #6.#53         // scala/collection/generic/AtomicIndexFlag.$init$:(Lscala/collection/generic/AtomicIndexFlag;)V
  #55 = Utf8               scala/runtime/Statics
  #56 = Class              #55            // scala/runtime/Statics
  #57 = Utf8               releaseFence
  #58 = NameAndType        #57:#48        // releaseFence:()V
  #59 = Methodref          #56.#58        // scala/runtime/Statics.releaseFence:()V
  #60 = Utf8               Lscala/collection/parallel/ParIterableLike;
  #61 = Utf8               Code
  #62 = Utf8               LineNumberTable
  #63 = Utf8               LocalVariableTable
  #64 = Utf8               MethodParameters
  #65 = Utf8               InnerClasses
  #66 = Utf8               EnclosingMethod
  #67 = Utf8               SourceFile
  #68 = Utf8               ScalaInlineInfo
  #69 = Utf8               Scala
{
  private java.util.concurrent.atomic.AtomicInteger scala$collection$generic$AtomicIndexFlag$$intflag;
    descriptor: Ljava/util/concurrent/atomic/AtomicInteger;
    flags: (0x0002) ACC_PRIVATE

  public int indexFlag();
    descriptor: ()I
    flags: (0x0001) ACC_PUBLIC
    Code:
      stack=1, locals=1, args_size=1
         0: aload_0
         1: invokestatic  #20                 // InterfaceMethod scala/collection/generic/AtomicIndexFlag.indexFlag$:(Lscala/collection/generic/AtomicIndexFlag;)I
         4: ireturn
      LineNumberTable:
        line 765: 0
      LocalVariableTable:
        Start  Length  Slot  Name   Signature
            0       5     0  this   Lscala/collection/parallel/ParIterableLike$$anon$18;

  public void setIndexFlag(int);
    descriptor: (I)V
    flags: (0x0001) ACC_PUBLIC
    Code:
      stack=2, locals=2, args_size=2
         0: aload_0
         1: iload_1
         2: invokestatic  #29                 // InterfaceMethod scala/collection/generic/AtomicIndexFlag.setIndexFlag$:(Lscala/collection/generic/AtomicIndexFlag;I)V
         5: return
      LineNumberTable:
        line 765: 0
      LocalVariableTable:
        Start  Length  Slot  Name   Signature
            0       6     0  this   Lscala/collection/parallel/ParIterableLike$$anon$18;
            0       6     1     f   I
    MethodParameters:
      Name                           Flags
      f                              final

  public void setIndexFlagIfGreater(int);
    descriptor: (I)V
    flags: (0x0001) ACC_PUBLIC
    Code:
      stack=2, locals=2, args_size=2
         0: aload_0
         1: iload_1
         2: invokestatic  #34                 // InterfaceMethod scala/collection/generic/AtomicIndexFlag.setIndexFlagIfGreater$:(Lscala/collection/generic/AtomicIndexFlag;I)V
         5: return
      LineNumberTable:
        line 765: 0
      LocalVariableTable:
        Start  Length  Slot  Name   Signature
            0       6     0  this   Lscala/collection/parallel/ParIterableLike$$anon$18;
            0       6     1     f   I
    MethodParameters:
      Name                           Flags
      f                              final

  public void setIndexFlagIfLesser(int);
    descriptor: (I)V
    flags: (0x0001) ACC_PUBLIC
    Code:
      stack=2, locals=2, args_size=2
         0: aload_0
         1: iload_1
         2: invokestatic  #38                 // InterfaceMethod scala/collection/generic/AtomicIndexFlag.setIndexFlagIfLesser$:(Lscala/collection/generic/AtomicIndexFlag;I)V
         5: return
      LineNumberTable:
        line 765: 0
      LocalVariableTable:
        Start  Length  Slot  Name   Signature
            0       6     0  this   Lscala/collection/parallel/ParIterableLike$$anon$18;
            0       6     1     f   I
    MethodParameters:
      Name                           Flags
      f                              final

  public java.util.concurrent.atomic.AtomicInteger scala$collection$generic$AtomicIndexFlag$$intflag();
    descriptor: ()Ljava/util/concurrent/atomic/AtomicInteger;
    flags: (0x0001) ACC_PUBLIC
    Code:
      stack=1, locals=1, args_size=1
         0: aload_0
         1: getfield      #41                 // Field scala$collection$generic$AtomicIndexFlag$$intflag:Ljava/util/concurrent/atomic/AtomicInteger;
         4: areturn
      LineNumberTable:
        line 765: 0
      LocalVariableTable:
        Start  Length  Slot  Name   Signature
            0       5     0  this   Lscala/collection/parallel/ParIterableLike$$anon$18;

  public final void scala$collection$generic$AtomicIndexFlag$_setter_$scala$collection$generic$AtomicIndexFlag$$intflag_$eq(java.util.concurrent.atomic.AtomicInteger);
    descriptor: (Ljava/util/concurrent/atomic/AtomicInteger;)V
    flags: (0x0011) ACC_PUBLIC, ACC_FINAL
    Code:
      stack=2, locals=2, args_size=2
         0: aload_0
         1: aload_1
         2: putfield      #41                 // Field scala$collection$generic$AtomicIndexFlag$$intflag:Ljava/util/concurrent/atomic/AtomicInteger;
         5: return
      LineNumberTable:
        line 765: 0
      LocalVariableTable:
        Start  Length  Slot  Name   Signature
            0       6     0  this   Lscala/collection/parallel/ParIterableLike$$anon$18;
            0       6     1   x$1   Ljava/util/concurrent/atomic/AtomicInteger;
    MethodParameters:
      Name                           Flags
      x$1                            final

  public scala.collection.parallel.ParIterableLike$$anon$18(scala.collection.parallel.ParIterableLike);
    descriptor: (Lscala/collection/parallel/ParIterableLike;)V
    flags: (0x0001) ACC_PUBLIC
    Code:
      stack=1, locals=2, args_size=2
         0: aload_0
         1: invokespecial #50                 // Method scala/collection/generic/DefaultSignalling."<init>":()V
         4: aload_0
         5: invokestatic  #54                 // InterfaceMethod scala/collection/generic/AtomicIndexFlag.$init$:(Lscala/collection/generic/AtomicIndexFlag;)V
         8: invokestatic  #59                 // Method scala/runtime/Statics.releaseFence:()V
        11: return
      LineNumberTable:
        line 765: 0
      LocalVariableTable:
        Start  Length  Slot  Name   Signature
            0      12     0  this   Lscala/collection/parallel/ParIterableLike$$anon$18;
            0      12     1 $outer   Lscala/collection/parallel/ParIterableLike;
    MethodParameters:
      Name                           Flags
      $outer                         final synthetic
}
InnerClasses:
  public final #2;                        // class scala/collection/parallel/ParIterableLike$$anon$18
EnclosingMethod: #9.#12                 // scala.collection.parallel.ParIterableLike.dropWhile
SourceFile: "ParIterableLike.scala"
  ScalaInlineInfo: length = 0x27 (unknown attribute)
   01 01 00 07 00 2D 00 2E 01 00 0F 00 10 01 00 0D
   00 27 01 00 2A 00 2B 01 00 17 00 18 01 00 1F 00
   18 01 00 23 00 18 01
  Scala: length = 0x0 (unknown attribute)

