Classfile /Users/mw/Projects/slang-braindump/.jar/jar11/assemble/slang-braindump/assemble/content/scala/collection/parallel/ParIterableLike$$anon$12.class
  Last modified May 29, 2022; size 1402 bytes
  SHA-256 checksum 4b87368908652dca62d6163f4b8dda632374569e1ef891311b11cdc9401e21d1
  Compiled from "ParIterableLike.scala"
public final class scala.collection.parallel.ParIterableLike$$anon$12 extends java.lang.Object implements scala.collection.parallel.CombinerFactory<T, Repr>
  minor version: 0
  major version: 52
  flags: (0x0031) ACC_PUBLIC, ACC_FINAL, ACC_SUPER
  this_class: #2                          // scala/collection/parallel/ParIterableLike$$anon$12
  super_class: #5                         // java/lang/Object
  interfaces: 1, fields: 1, methods: 4, attributes: 6
Constant pool:
   #1 = Utf8               scala/collection/parallel/ParIterableLike$$anon$12
   #2 = Class              #1             // scala/collection/parallel/ParIterableLike$$anon$12
   #3 = Utf8               Ljava/lang/Object;Lscala/collection/parallel/CombinerFactory<TT;TRepr;>;
   #4 = Utf8               java/lang/Object
   #5 = Class              #4             // java/lang/Object
   #6 = Utf8               scala/collection/parallel/CombinerFactory
   #7 = Class              #6             // scala/collection/parallel/CombinerFactory
   #8 = Utf8               ParIterableLike.scala
   #9 = Utf8               scala/collection/parallel/ParIterableLike
  #10 = Class              #9             // scala/collection/parallel/ParIterableLike
  #11 = Utf8               combinerFactory
  #12 = Utf8               ()Lscala/collection/parallel/CombinerFactory;
  #13 = NameAndType        #11:#12        // combinerFactory:()Lscala/collection/parallel/CombinerFactory;
  #14 = Utf8               shared
  #15 = Utf8               Lscala/collection/parallel/Combiner;
  #16 = Utf8               Lscala/collection/parallel/Combiner<TT;TRepr;>;
  #17 = Utf8               ()Lscala/collection/parallel/Combiner;
  #18 = Utf8               ()Lscala/collection/parallel/Combiner<TT;TRepr;>;
  #19 = NameAndType        #14:#15        // shared:Lscala/collection/parallel/Combiner;
  #20 = Fieldref           #2.#19         // scala/collection/parallel/ParIterableLike$$anon$12.shared:Lscala/collection/parallel/Combiner;
  #21 = Utf8               this
  #22 = Utf8               Lscala/collection/parallel/ParIterableLike$$anon$12;
  #23 = Utf8               apply
  #24 = NameAndType        #14:#17        // shared:()Lscala/collection/parallel/Combiner;
  #25 = Methodref          #2.#24         // scala/collection/parallel/ParIterableLike$$anon$12.shared:()Lscala/collection/parallel/Combiner;
  #26 = Utf8               doesShareCombiners
  #27 = Utf8               ()Z
  #28 = Utf8               <init>
  #29 = Utf8               (Lscala/collection/parallel/ParIterableLike;Lscala/collection/parallel/Combiner;)V
  #30 = Utf8               $outer
  #31 = Utf8               combiner$1
  #32 = Utf8               ()V
  #33 = NameAndType        #28:#32        // "<init>":()V
  #34 = Methodref          #5.#33         // java/lang/Object."<init>":()V
  #35 = Utf8               Lscala/collection/parallel/ParIterableLike;
  #36 = Utf8               Signature
  #37 = Utf8               Code
  #38 = Utf8               LineNumberTable
  #39 = Utf8               LocalVariableTable
  #40 = Utf8               MethodParameters
  #41 = Utf8               InnerClasses
  #42 = Utf8               EnclosingMethod
  #43 = Utf8               SourceFile
  #44 = Utf8               ScalaInlineInfo
  #45 = Utf8               Scala
{
  private final scala.collection.parallel.Combiner<T, Repr> shared;
    descriptor: Lscala/collection/parallel/Combiner;
    flags: (0x0012) ACC_PRIVATE, ACC_FINAL
    Signature: #16                          // Lscala/collection/parallel/Combiner<TT;TRepr;>;

  private scala.collection.parallel.Combiner<T, Repr> shared();
    descriptor: ()Lscala/collection/parallel/Combiner;
    flags: (0x0002) ACC_PRIVATE
    Code:
      stack=1, locals=1, args_size=1
         0: aload_0
         1: getfield      #20                 // Field shared:Lscala/collection/parallel/Combiner;
         4: areturn
      LineNumberTable:
        line 555: 0
      LocalVariableTable:
        Start  Length  Slot  Name   Signature
            0       5     0  this   Lscala/collection/parallel/ParIterableLike$$anon$12;
    Signature: #18                          // ()Lscala/collection/parallel/Combiner<TT;TRepr;>;

  public scala.collection.parallel.Combiner<T, Repr> apply();
    descriptor: ()Lscala/collection/parallel/Combiner;
    flags: (0x0001) ACC_PUBLIC
    Code:
      stack=1, locals=1, args_size=1
         0: aload_0
         1: invokespecial #25                 // Method shared:()Lscala/collection/parallel/Combiner;
         4: areturn
      LineNumberTable:
        line 556: 0
      LocalVariableTable:
        Start  Length  Slot  Name   Signature
            0       5     0  this   Lscala/collection/parallel/ParIterableLike$$anon$12;
    Signature: #18                          // ()Lscala/collection/parallel/Combiner<TT;TRepr;>;

  public boolean doesShareCombiners();
    descriptor: ()Z
    flags: (0x0001) ACC_PUBLIC
    Code:
      stack=1, locals=1, args_size=1
         0: iconst_1
         1: ireturn
      LineNumberTable:
        line 557: 0
      LocalVariableTable:
        Start  Length  Slot  Name   Signature
            0       2     0  this   Lscala/collection/parallel/ParIterableLike$$anon$12;

  public scala.collection.parallel.ParIterableLike$$anon$12(scala.collection.parallel.ParIterableLike, scala.collection.parallel.Combiner);
    descriptor: (Lscala/collection/parallel/ParIterableLike;Lscala/collection/parallel/Combiner;)V
    flags: (0x0001) ACC_PUBLIC
    Code:
      stack=2, locals=3, args_size=3
         0: aload_0
         1: invokespecial #34                 // Method java/lang/Object."<init>":()V
         4: aload_0
         5: aload_2
         6: putfield      #20                 // Field shared:Lscala/collection/parallel/Combiner;
         9: return
      LineNumberTable:
        line 554: 0
        line 555: 4
        line 554: 9
      LocalVariableTable:
        Start  Length  Slot  Name   Signature
            0      10     0  this   Lscala/collection/parallel/ParIterableLike$$anon$12;
            0      10     1 $outer   Lscala/collection/parallel/ParIterableLike;
            0      10     2 combiner$1   Lscala/collection/parallel/Combiner;
    MethodParameters:
      Name                           Flags
      $outer                         final synthetic
      combiner$1                     final
}
InnerClasses:
  public final #2;                        // class scala/collection/parallel/ParIterableLike$$anon$12
EnclosingMethod: #10.#13                // scala.collection.parallel.ParIterableLike.combinerFactory
Signature: #3                           // Ljava/lang/Object;Lscala/collection/parallel/CombinerFactory<TT;TRepr;>;
SourceFile: "ParIterableLike.scala"
  ScalaInlineInfo: length = 0x18 (unknown attribute)
   01 01 00 04 00 1C 00 1D 01 00 17 00 11 01 00 1A
   00 1B 01 00 0E 00 11 01
  Scala: length = 0x0 (unknown attribute)

