Classfile /Users/mw/Projects/slang-braindump/.jar/jar11/assemble/slang-braindump/assemble/content/scala/collection/parallel/ParMap$.class
  Last modified May 29, 2022; size 1893 bytes
  SHA-256 checksum ecdabf2966fbdbb31dcd04bb36fc11126851344d48e7500eaeed96d95e72b1e5
  Compiled from "ParMap.scala"
public final class scala.collection.parallel.ParMap$ extends scala.collection.generic.ParMapFactory<scala.collection.parallel.ParMap, scala.collection.Map>
  minor version: 0
  major version: 52
  flags: (0x0031) ACC_PUBLIC, ACC_FINAL, ACC_SUPER
  this_class: #2                          // scala/collection/parallel/ParMap$
  super_class: #5                         // scala/collection/generic/ParMapFactory
  interfaces: 0, fields: 1, methods: 5, attributes: 5
Constant pool:
   #1 = Utf8               scala/collection/parallel/ParMap$
   #2 = Class              #1             // scala/collection/parallel/ParMap$
   #3 = Utf8               Lscala/collection/generic/ParMapFactory<Lscala/collection/parallel/ParMap;Lscala/collection/Map;>;
   #4 = Utf8               scala/collection/generic/ParMapFactory
   #5 = Class              #4             // scala/collection/generic/ParMapFactory
   #6 = Utf8               ParMap.scala
   #7 = Utf8               scala/collection/generic/ParMapFactory$CanCombineFromMap
   #8 = Class              #7             // scala/collection/generic/ParMapFactory$CanCombineFromMap
   #9 = Utf8               CanCombineFromMap
  #10 = Utf8               MODULE$
  #11 = Utf8               Lscala/collection/parallel/ParMap$;
  #12 = Utf8               <clinit>
  #13 = Utf8               ()V
  #14 = Utf8               <init>
  #15 = NameAndType        #14:#13        // "<init>":()V
  #16 = Methodref          #2.#15         // scala/collection/parallel/ParMap$."<init>":()V
  #17 = NameAndType        #10:#11        // MODULE$:Lscala/collection/parallel/ParMap$;
  #18 = Fieldref           #2.#17         // scala/collection/parallel/ParMap$.MODULE$:Lscala/collection/parallel/ParMap$;
  #19 = Utf8               empty
  #20 = Utf8               ()Lscala/collection/parallel/ParMap;
  #21 = Utf8               <K:Ljava/lang/Object;V:Ljava/lang/Object;>()Lscala/collection/parallel/ParMap<TK;TV;>;
  #22 = Utf8               scala/collection/parallel/mutable/ParHashMap
  #23 = Class              #22            // scala/collection/parallel/mutable/ParHashMap
  #24 = Methodref          #23.#15        // scala/collection/parallel/mutable/ParHashMap."<init>":()V
  #25 = Utf8               this
  #26 = Utf8               newCombiner
  #27 = Utf8               ()Lscala/collection/parallel/Combiner;
  #28 = Utf8               <K:Ljava/lang/Object;V:Ljava/lang/Object;>()Lscala/collection/parallel/Combiner<Lscala/Tuple2<TK;TV;>;Lscala/collection/parallel/ParMap<TK;TV;>;>;
  #29 = Utf8               scala/collection/parallel/mutable/ParHashMapCombiner$
  #30 = Class              #29            // scala/collection/parallel/mutable/ParHashMapCombiner$
  #31 = Utf8               Lscala/collection/parallel/mutable/ParHashMapCombiner$;
  #32 = NameAndType        #10:#31        // MODULE$:Lscala/collection/parallel/mutable/ParHashMapCombiner$;
  #33 = Fieldref           #30.#32        // scala/collection/parallel/mutable/ParHashMapCombiner$.MODULE$:Lscala/collection/parallel/mutable/ParHashMapCombiner$;
  #34 = Utf8               apply
  #35 = Utf8               ()Lscala/collection/parallel/mutable/ParHashMapCombiner;
  #36 = NameAndType        #34:#35        // apply:()Lscala/collection/parallel/mutable/ParHashMapCombiner;
  #37 = Methodref          #30.#36        // scala/collection/parallel/mutable/ParHashMapCombiner$.apply:()Lscala/collection/parallel/mutable/ParHashMapCombiner;
  #38 = Utf8               canBuildFrom
  #39 = Utf8               ()Lscala/collection/generic/CanCombineFrom;
  #40 = Utf8               <FromK:Ljava/lang/Object;FromV:Ljava/lang/Object;K:Ljava/lang/Object;V:Ljava/lang/Object;>()Lscala/collection/generic/CanCombineFrom<Lscala/collection/parallel/ParMap<TFromK;TFromV;>;Lscala/Tuple2<TK;TV;>;Lscala/collection/parallel/ParMap<TK;TV;>;>;
  #41 = Utf8               (Lscala/collection/generic/ParMapFactory;)V
  #42 = NameAndType        #14:#41        // "<init>":(Lscala/collection/generic/ParMapFactory;)V
  #43 = Methodref          #8.#42         // scala/collection/generic/ParMapFactory$CanCombineFromMap."<init>":(Lscala/collection/generic/ParMapFactory;)V
  #44 = Methodref          #5.#15         // scala/collection/generic/ParMapFactory."<init>":()V
  #45 = Utf8               Code
  #46 = Utf8               LineNumberTable
  #47 = Utf8               LocalVariableTable
  #48 = Utf8               Signature
  #49 = Utf8               InnerClasses
  #50 = Utf8               SourceFile
  #51 = Utf8               ScalaInlineInfo
  #52 = Utf8               Scala
{
  public static final scala.collection.parallel.ParMap$ MODULE$;
    descriptor: Lscala/collection/parallel/ParMap$;
    flags: (0x0019) ACC_PUBLIC, ACC_STATIC, ACC_FINAL

  public static {};
    descriptor: ()V
    flags: (0x0009) ACC_PUBLIC, ACC_STATIC
    Code:
      stack=2, locals=0, args_size=0
         0: new           #2                  // class scala/collection/parallel/ParMap$
         3: dup
         4: invokespecial #16                 // Method "<init>":()V
         7: putstatic     #18                 // Field MODULE$:Lscala/collection/parallel/ParMap$;
        10: return
      LineNumberTable:
        line 48: 0

  public <K extends java.lang.Object, V extends java.lang.Object> scala.collection.parallel.ParMap<K, V> empty();
    descriptor: ()Lscala/collection/parallel/ParMap;
    flags: (0x0001) ACC_PUBLIC
    Code:
      stack=2, locals=1, args_size=1
         0: new           #23                 // class scala/collection/parallel/mutable/ParHashMap
         3: dup
         4: invokespecial #24                 // Method scala/collection/parallel/mutable/ParHashMap."<init>":()V
         7: areturn
      LineNumberTable:
        line 49: 0
      LocalVariableTable:
        Start  Length  Slot  Name   Signature
            0       8     0  this   Lscala/collection/parallel/ParMap$;
    Signature: #21                          // <K:Ljava/lang/Object;V:Ljava/lang/Object;>()Lscala/collection/parallel/ParMap<TK;TV;>;

  public <K extends java.lang.Object, V extends java.lang.Object> scala.collection.parallel.Combiner<scala.Tuple2<K, V>, scala.collection.parallel.ParMap<K, V>> newCombiner();
    descriptor: ()Lscala/collection/parallel/Combiner;
    flags: (0x0001) ACC_PUBLIC
    Code:
      stack=1, locals=1, args_size=1
         0: getstatic     #33                 // Field scala/collection/parallel/mutable/ParHashMapCombiner$.MODULE$:Lscala/collection/parallel/mutable/ParHashMapCombiner$;
         3: invokevirtual #37                 // Method scala/collection/parallel/mutable/ParHashMapCombiner$.apply:()Lscala/collection/parallel/mutable/ParHashMapCombiner;
         6: areturn
      LineNumberTable:
        line 51: 0
      LocalVariableTable:
        Start  Length  Slot  Name   Signature
            0       7     0  this   Lscala/collection/parallel/ParMap$;
    Signature: #28                          // <K:Ljava/lang/Object;V:Ljava/lang/Object;>()Lscala/collection/parallel/Combiner<Lscala/Tuple2<TK;TV;>;Lscala/collection/parallel/ParMap<TK;TV;>;>;

  public <FromK extends java.lang.Object, FromV extends java.lang.Object, K extends java.lang.Object, V extends java.lang.Object> scala.collection.generic.CanCombineFrom<scala.collection.parallel.ParMap<FromK, FromV>, scala.Tuple2<K, V>, scala.collection.parallel.ParMap<K, V>> canBuildFrom();
    descriptor: ()Lscala/collection/generic/CanCombineFrom;
    flags: (0x0001) ACC_PUBLIC
    Code:
      stack=3, locals=1, args_size=1
         0: new           #8                  // class scala/collection/generic/ParMapFactory$CanCombineFromMap
         3: dup
         4: aload_0
         5: invokespecial #43                 // Method scala/collection/generic/ParMapFactory$CanCombineFromMap."<init>":(Lscala/collection/generic/ParMapFactory;)V
         8: areturn
      LineNumberTable:
        line 53: 0
      LocalVariableTable:
        Start  Length  Slot  Name   Signature
            0       9     0  this   Lscala/collection/parallel/ParMap$;
    Signature: #40                          // <FromK:Ljava/lang/Object;FromV:Ljava/lang/Object;K:Ljava/lang/Object;V:Ljava/lang/Object;>()Lscala/collection/generic/CanCombineFrom<Lscala/collection/parallel/ParMap<TFromK;TFromV;>;Lscala/Tuple2<TK;TV;>;Lscala/collection/parallel/ParMap<TK;TV;>;>;

  private scala.collection.parallel.ParMap$();
    descriptor: ()V
    flags: (0x0002) ACC_PRIVATE
    Code:
      stack=1, locals=1, args_size=1
         0: aload_0
         1: invokespecial #44                 // Method scala/collection/generic/ParMapFactory."<init>":()V
         4: return
      LineNumberTable:
        line 48: 0
      LocalVariableTable:
        Start  Length  Slot  Name   Signature
            0       5     0  this   Lscala/collection/parallel/ParMap$;
}
InnerClasses:
  public #9= #8 of #5;                    // CanCombineFromMap=class scala/collection/generic/ParMapFactory$CanCombineFromMap of class scala/collection/generic/ParMapFactory
Signature: #3                           // Lscala/collection/generic/ParMapFactory<Lscala/collection/parallel/ParMap;Lscala/collection/Map;>;
SourceFile: "ParMap.scala"
  ScalaInlineInfo: length = 0x18 (unknown attribute)
   01 01 00 04 00 0E 00 0D 01 00 26 00 27 01 00 13
   00 14 01 00 1A 00 1B 01
  Scala: length = 0x0 (unknown attribute)

