Classfile /Users/mw/Projects/slang-braindump/.jar/jar11/assemble/slang-braindump/assemble/content/scala/collection/parallel/RemainsIterator.class
  Last modified May 29, 2022; size 1281 bytes
  SHA-256 checksum 8e87f0e4b84da737ebeb8fdea1be8fb0270e33a1d7a6e2a626aed723f63f2ef2
  Compiled from "RemainsIterator.scala"
public interface scala.collection.parallel.RemainsIterator<T extends java.lang.Object> extends scala.collection.Iterator<T>
  minor version: 0
  major version: 52
  flags: (0x0601) ACC_PUBLIC, ACC_INTERFACE, ACC_ABSTRACT
  this_class: #2                          // scala/collection/parallel/RemainsIterator
  super_class: #5                         // java/lang/Object
  interfaces: 1, fields: 0, methods: 4, attributes: 5
Constant pool:
   #1 = Utf8               scala/collection/parallel/RemainsIterator
   #2 = Class              #1             // scala/collection/parallel/RemainsIterator
   #3 = Utf8               <T:Ljava/lang/Object;>Ljava/lang/Object;Lscala/collection/Iterator<TT;>;
   #4 = Utf8               java/lang/Object
   #5 = Class              #4             // java/lang/Object
   #6 = Utf8               scala/collection/Iterator
   #7 = Class              #6             // scala/collection/Iterator
   #8 = Utf8               RemainsIterator.scala
   #9 = Utf8               Lscala/reflect/ScalaSignature;
  #10 = Utf8               bytes
  #11 = Utf8               \u0006\u0005M2\u0001\u0002B\u0003\u0011\u0002\u0007\u0005qa\u0003\u0005\u0006I\u0001!\t!\n\u0005\u0006S\u00011\tA\u000b\u0005\u0006]\u0001!\ta\f\u0002\u0010%\u0016l\u0017-\u001b8t\u0013R,\'/\u0019;pe*\u0011aaB\u0001\ta\u0006\u0014\u0018\r\u001c7fY*\u0011\u0001\"C\u0001\u000bG>dG.Z2uS>t\'\"\u0001\u0006\u0002\u000bM\u001c\u0017\r\\1\u0016\u00051Q2c\u0001\u0001\u000e#A\u0011abD\u0007\u0002\u0013%\u0011\u0001#\u0003\u0002\u0007\u0003:L(+\u001a4\u0011\u0007I)\u0002D\u0004\u0002\u000f\'%\u0011A#C\u0001\ba\u0006\u001c7.Y4f\u0013\t1rC\u0001\u0005Ji\u0016\u0014\u0018\r^8s\u0015\t!\u0012\u0002\u0005\u0002\u001a51\u0001AAB\u000e\u0001\t\u000b\u0007QDA\u0001U\u0007\u0001\t\"AH\u0011\u0011\u00059y\u0012B\u0001\u0011\n\u0005\u001dqu\u000e\u001e5j]\u001e\u0004\"A\u0004\u0012\n\u0005\rJ!aA!os\u00061A%\u001b8ji\u0012\"\u0012A\n\t\u0003\u001d\u001dJ!\u0001K\u0005\u0003\tUs\u0017\u000e^\u0001\ne\u0016l\u0017-\u001b8j]\u001e,\u0012a\u000b\t\u0003\u001d1J!!L\u0005\u0003\u0007%sG/\u0001\tjgJ+W.Y5oS:<7\t[3baV\t\u0001\u0007\u0005\u0002\u000fc%\u0011!\'\u0003\u0002\b\u0005>|G.Z1o\u0001
  #12 = Utf8               remaining
  #13 = Utf8               ()I
  #14 = Utf8               isRemainingCheap$
  #15 = Utf8               (Lscala/collection/parallel/RemainsIterator;)Z
  #16 = Utf8               $this
  #17 = Utf8               isRemainingCheap
  #18 = Utf8               ()Z
  #19 = NameAndType        #17:#18        // isRemainingCheap:()Z
  #20 = InterfaceMethodref #2.#19         // scala/collection/parallel/RemainsIterator.isRemainingCheap:()Z
  #21 = Utf8               Lscala/collection/parallel/RemainsIterator;
  #22 = Utf8               this
  #23 = Utf8               $init$
  #24 = Utf8               (Lscala/collection/parallel/RemainsIterator;)V
  #25 = Utf8               Code
  #26 = Utf8               LineNumberTable
  #27 = Utf8               LocalVariableTable
  #28 = Utf8               MethodParameters
  #29 = Utf8               Signature
  #30 = Utf8               SourceFile
  #31 = Utf8               RuntimeVisibleAnnotations
  #32 = Utf8               ScalaInlineInfo
  #33 = Utf8               ScalaSig
{
  public abstract int remaining();
    descriptor: ()I
    flags: (0x0401) ACC_PUBLIC, ACC_ABSTRACT

  public static boolean isRemainingCheap$(scala.collection.parallel.RemainsIterator);
    descriptor: (Lscala/collection/parallel/RemainsIterator;)Z
    flags: (0x1009) ACC_PUBLIC, ACC_STATIC, ACC_SYNTHETIC
    Code:
      stack=1, locals=1, args_size=1
         0: aload_0
         1: invokespecial #20                 // InterfaceMethod isRemainingCheap:()Z
         4: ireturn
      LineNumberTable:
        line 32: 0
      LocalVariableTable:
        Start  Length  Slot  Name   Signature
            0       5     0 $this   Lscala/collection/parallel/RemainsIterator;
    MethodParameters:
      Name                           Flags
      $this                          final synthetic

  public default boolean isRemainingCheap();
    descriptor: ()Z
    flags: (0x0001) ACC_PUBLIC
    Code:
      stack=1, locals=1, args_size=1
         0: iconst_1
         1: ireturn
      LineNumberTable:
        line 32: 0
      LocalVariableTable:
        Start  Length  Slot  Name   Signature
            0       2     0  this   Lscala/collection/parallel/RemainsIterator;

  public static void $init$(scala.collection.parallel.RemainsIterator);
    descriptor: (Lscala/collection/parallel/RemainsIterator;)V
    flags: (0x0009) ACC_PUBLIC, ACC_STATIC
    Code:
      stack=0, locals=1, args_size=1
         0: return
      LineNumberTable:
        line 23: 0
      LocalVariableTable:
        Start  Length  Slot  Name   Signature
            0       1     0 $this   Lscala/collection/parallel/RemainsIterator;
    MethodParameters:
      Name                           Flags
      $this                          final synthetic
}
Signature: #3                           // <T:Ljava/lang/Object;>Ljava/lang/Object;Lscala/collection/Iterator<TT;>;
SourceFile: "RemainsIterator.scala"
RuntimeVisibleAnnotations:
  0: #9(#10=s#11)
    scala.reflect.ScalaSignature(
      bytes="\u0006\u0005M2\u0001\u0002B\u0003\u0011\u0002\u0007\u0005qa\u0003\u0005\u0006I\u0001!\t!\n\u0005\u0006S\u00011\tA\u000b\u0005\u0006]\u0001!\ta\f\u0002\u0010%\u0016l\u0017-\u001b8t\u0013R,\'/\u0019;pe*\u0011aaB\u0001\ta\u0006\u0014\u0018\r\u001c7fY*\u0011\u0001\"C\u0001\u000bG>dG.Z2uS>t\'\"\u0001\u0006\u0002\u000bM\u001c\u0017\r\\1\u0016\u00051Q2c\u0001\u0001\u000e#A\u0011abD\u0007\u0002\u0013%\u0011\u0001#\u0003\u0002\u0007\u0003:L(+\u001a4\u0011\u0007I)\u0002D\u0004\u0002\u000f\'%\u0011A#C\u0001\ba\u0006\u001c7.Y4f\u0013\t1rC\u0001\u0005Ji\u0016\u0014\u0018\r^8s\u0015\t!\u0012\u0002\u0005\u0002\u001a51\u0001AAB\u000e\u0001\t\u000b\u0007QDA\u0001U\u0007\u0001\t\"AH\u0011\u0011\u00059y\u0012B\u0001\u0011\n\u0005\u001dqu\u000e\u001e5j]\u001e\u0004\"A\u0004\u0012\n\u0005\rJ!aA!os\u00061A%\u001b8ji\u0012\"\u0012A\n\t\u0003\u001d\u001dJ!\u0001K\u0005\u0003\tUs\u0017\u000e^\u0001\ne\u0016l\u0017-\u001b8j]\u001e,\u0012a\u000b\t\u0003\u001d1J!!L\u0005\u0003\u0007%sG/\u0001\tjgJ+W.Y5oS:<7\t[3baV\t\u0001\u0007\u0005\u0002\u000fc%\u0011!\'\u0003\u0002\b\u0005>|G.Z1o\u0001"
    )
  ScalaInlineInfo: length = 0x18 (unknown attribute)
   01 00 00 04 00 17 00 18 01 00 11 00 12 00 00 0E
   00 0F 01 00 0C 00 0D 00
  ScalaSig: length = 0x3 (unknown attribute)
   05 02 00
