Classfile /Users/mw/Projects/slang-braindump/.jar/jar11/assemble/slang-braindump/assemble/content/scala/collection/parallel/SeqSplitter$$anon$1.class
  Last modified May 29, 2022; size 1579 bytes
  SHA-256 checksum 8a602869a74d21603b6f5751c72806355dedcc3d5a0e8f51fc7beece7e747540
  Compiled from "RemainsIterator.scala"
public final class scala.collection.parallel.SeqSplitter$$anon$1 extends scala.collection.parallel.mutable.ParArray<T>.ParArrayIterator
  minor version: 0
  major version: 52
  flags: (0x0031) ACC_PUBLIC, ACC_FINAL, ACC_SUPER
  this_class: #2                          // scala/collection/parallel/SeqSplitter$$anon$1
  super_class: #5                         // scala/collection/parallel/mutable/ParArray$ParArrayIterator
  interfaces: 0, fields: 1, methods: 2, attributes: 6
Constant pool:
   #1 = Utf8               scala/collection/parallel/SeqSplitter$$anon$1
   #2 = Class              #1             // scala/collection/parallel/SeqSplitter$$anon$1
   #3 = Utf8               Lscala/collection/parallel/mutable/ParArray<TT;>.ParArrayIterator;
   #4 = Utf8               scala/collection/parallel/mutable/ParArray$ParArrayIterator
   #5 = Class              #4             // scala/collection/parallel/mutable/ParArray$ParArrayIterator
   #6 = Utf8               RemainsIterator.scala
   #7 = Utf8               scala/collection/parallel/SeqSplitter
   #8 = Class              #7             // scala/collection/parallel/SeqSplitter
   #9 = Utf8               reverse
  #10 = Utf8               ()Lscala/collection/parallel/SeqSplitter;
  #11 = NameAndType        #9:#10         // reverse:()Lscala/collection/parallel/SeqSplitter;
  #12 = Utf8               scala/collection/parallel/mutable/ParArray
  #13 = Class              #12            // scala/collection/parallel/mutable/ParArray
  #14 = Utf8               ParArrayIterator
  #15 = Utf8               scala/collection/parallel/mutable/ParArray$ParArrayIterator$
  #16 = Class              #15            // scala/collection/parallel/mutable/ParArray$ParArrayIterator$
  #17 = Utf8               ParArrayIterator$
  #18 = Utf8               $outer
  #19 = Utf8               Lscala/collection/parallel/SeqSplitter;
  #20 = Utf8               ()Lscala/collection/parallel/SeqSplitter<TT;>;
  #21 = NameAndType        #18:#19        // $outer:Lscala/collection/parallel/SeqSplitter;
  #22 = Fieldref           #2.#21         // scala/collection/parallel/SeqSplitter$$anon$1.$outer:Lscala/collection/parallel/SeqSplitter;
  #23 = Utf8               this
  #24 = Utf8               Lscala/collection/parallel/SeqSplitter$$anon$1;
  #25 = Utf8               <init>
  #26 = Utf8               (Lscala/collection/parallel/SeqSplitter;Lscala/collection/parallel/mutable/ParArray;)V
  #27 = Utf8               pa$1
  #28 = Utf8               ()Lscala/collection/parallel/mutable/ParArray$ParArrayIterator$;
  #29 = NameAndType        #14:#28        // ParArrayIterator:()Lscala/collection/parallel/mutable/ParArray$ParArrayIterator$;
  #30 = Methodref          #13.#29        // scala/collection/parallel/mutable/ParArray.ParArrayIterator:()Lscala/collection/parallel/mutable/ParArray$ParArrayIterator$;
  #31 = Utf8               $lessinit$greater$default$1
  #32 = Utf8               ()I
  #33 = NameAndType        #31:#32        // $lessinit$greater$default$1:()I
  #34 = Methodref          #16.#33        // scala/collection/parallel/mutable/ParArray$ParArrayIterator$.$lessinit$greater$default$1:()I
  #35 = Utf8               $lessinit$greater$default$2
  #36 = NameAndType        #35:#32        // $lessinit$greater$default$2:()I
  #37 = Methodref          #16.#36        // scala/collection/parallel/mutable/ParArray$ParArrayIterator$.$lessinit$greater$default$2:()I
  #38 = Utf8               $lessinit$greater$default$3
  #39 = Utf8               ()[Ljava/lang/Object;
  #40 = NameAndType        #38:#39        // $lessinit$greater$default$3:()[Ljava/lang/Object;
  #41 = Methodref          #16.#40        // scala/collection/parallel/mutable/ParArray$ParArrayIterator$.$lessinit$greater$default$3:()[Ljava/lang/Object;
  #42 = Utf8               (Lscala/collection/parallel/mutable/ParArray;II[Ljava/lang/Object;)V
  #43 = NameAndType        #25:#42        // "<init>":(Lscala/collection/parallel/mutable/ParArray;II[Ljava/lang/Object;)V
  #44 = Methodref          #5.#43         // scala/collection/parallel/mutable/ParArray$ParArrayIterator."<init>":(Lscala/collection/parallel/mutable/ParArray;II[Ljava/lang/Object;)V
  #45 = Utf8               Lscala/collection/parallel/mutable/ParArray;
  #46 = Utf8               Code
  #47 = Utf8               LineNumberTable
  #48 = Utf8               LocalVariableTable
  #49 = Utf8               Signature
  #50 = Utf8               StackMapTable
  #51 = Utf8               MethodParameters
  #52 = Utf8               InnerClasses
  #53 = Utf8               EnclosingMethod
  #54 = Utf8               SourceFile
  #55 = Utf8               ScalaInlineInfo
  #56 = Utf8               Scala
{
  private final scala.collection.parallel.SeqSplitter $outer;
    descriptor: Lscala/collection/parallel/SeqSplitter;
    flags: (0x1012) ACC_PRIVATE, ACC_FINAL, ACC_SYNTHETIC

  public scala.collection.parallel.SeqSplitter<T> reverse();
    descriptor: ()Lscala/collection/parallel/SeqSplitter;
    flags: (0x0001) ACC_PUBLIC
    Code:
      stack=1, locals=1, args_size=1
         0: aload_0
         1: getfield      #22                 // Field $outer:Lscala/collection/parallel/SeqSplitter;
         4: areturn
      LineNumberTable:
        line 649: 0
      LocalVariableTable:
        Start  Length  Slot  Name   Signature
            0       5     0  this   Lscala/collection/parallel/SeqSplitter$$anon$1;
    Signature: #20                          // ()Lscala/collection/parallel/SeqSplitter<TT;>;

  public scala.collection.parallel.SeqSplitter$$anon$1(scala.collection.parallel.SeqSplitter, scala.collection.parallel.mutable.ParArray);
    descriptor: (Lscala/collection/parallel/SeqSplitter;Lscala/collection/parallel/mutable/ParArray;)V
    flags: (0x0001) ACC_PUBLIC
    Code:
      stack=5, locals=3, args_size=3
         0: aload_1
         1: ifnonnull     6
         4: aconst_null
         5: athrow
         6: aload_0
         7: aload_1
         8: putfield      #22                 // Field $outer:Lscala/collection/parallel/SeqSplitter;
        11: aload_0
        12: aload_2
        13: aload_2
        14: invokevirtual #30                 // Method scala/collection/parallel/mutable/ParArray.ParArrayIterator:()Lscala/collection/parallel/mutable/ParArray$ParArrayIterator$;
        17: invokevirtual #34                 // Method scala/collection/parallel/mutable/ParArray$ParArrayIterator$.$lessinit$greater$default$1:()I
        20: aload_2
        21: invokevirtual #30                 // Method scala/collection/parallel/mutable/ParArray.ParArrayIterator:()Lscala/collection/parallel/mutable/ParArray$ParArrayIterator$;
        24: invokevirtual #37                 // Method scala/collection/parallel/mutable/ParArray$ParArrayIterator$.$lessinit$greater$default$2:()I
        27: aload_2
        28: invokevirtual #30                 // Method scala/collection/parallel/mutable/ParArray.ParArrayIterator:()Lscala/collection/parallel/mutable/ParArray$ParArrayIterator$;
        31: invokevirtual #41                 // Method scala/collection/parallel/mutable/ParArray$ParArrayIterator$.$lessinit$greater$default$3:()[Ljava/lang/Object;
        34: invokespecial #44                 // Method scala/collection/parallel/mutable/ParArray$ParArrayIterator."<init>":(Lscala/collection/parallel/mutable/ParArray;II[Ljava/lang/Object;)V
        37: return
      StackMapTable: number_of_entries = 1
        frame_type = 6 /* same */
      LineNumberTable:
        line 648: 0
      LocalVariableTable:
        Start  Length  Slot  Name   Signature
            0      38     0  this   Lscala/collection/parallel/SeqSplitter$$anon$1;
            0      38     1 $outer   Lscala/collection/parallel/SeqSplitter;
            0      38     2  pa$1   Lscala/collection/parallel/mutable/ParArray;
    MethodParameters:
      Name                           Flags
      $outer                         final synthetic
      pa$1                           final
}
InnerClasses:
  public final #2;                        // class scala/collection/parallel/SeqSplitter$$anon$1
  public #14= #5 of #13;                  // ParArrayIterator=class scala/collection/parallel/mutable/ParArray$ParArrayIterator of class scala/collection/parallel/mutable/ParArray
  public #17= #16 of #13;                 // ParArrayIterator$=class scala/collection/parallel/mutable/ParArray$ParArrayIterator$ of class scala/collection/parallel/mutable/ParArray
EnclosingMethod: #8.#11                 // scala.collection.parallel.SeqSplitter.reverse
Signature: #3                           // Lscala/collection/parallel/mutable/ParArray<TT;>.ParArrayIterator;
SourceFile: "RemainsIterator.scala"
  ScalaInlineInfo: length = 0xE (unknown attribute)
   01 01 00 02 00 19 00 1A 01 00 09 00 0A 01
  Scala: length = 0x0 (unknown attribute)

