Classfile /Users/mw/Projects/slang-braindump/.jar/jar11/assemble/slang-braindump/assemble/content/scala/collection/parallel/Task.class
  Last modified May 29, 2022; size 5821 bytes
  SHA-256 checksum d648b57e46c8acf927165ac09c10d6d3b17c2c2235b8b3450f24da675c6ff72f
  Compiled from "Tasks.scala"
public interface scala.collection.parallel.Task<R extends java.lang.Object, Tp extends java.lang.Object>
  minor version: 0
  major version: 52
  flags: (0x0601) ACC_PUBLIC, ACC_INTERFACE, ACC_ABSTRACT
  this_class: #2                          // scala/collection/parallel/Task
  super_class: #5                         // java/lang/Object
  interfaces: 0, fields: 0, methods: 25, attributes: 7
Constant pool:
    #1 = Utf8               scala/collection/parallel/Task
    #2 = Class              #1            // scala/collection/parallel/Task
    #3 = Utf8               <R:Ljava/lang/Object;Tp:Ljava/lang/Object;>Ljava/lang/Object;
    #4 = Utf8               java/lang/Object
    #5 = Class              #4            // java/lang/Object
    #6 = Utf8               Tasks.scala
    #7 = Utf8               Lscala/reflect/ScalaSignature;
    #8 = Utf8               bytes
    #9 = Utf8               \u0006\u0005\u0005\u0005aaB\t\u0013!\u0003\r\t!\u0007\u0005\u0006?\u0001!\t\u0001I\u0003\u0005I\u0001\u0001Q\u0005C\u00031\u0001\u0011\u0005\u0011\u0007C\u00036\u0001\u0019\u0005a\u0007C\u00049\u0001\u0001\u0007i\u0011\u0001\u001f\t\u000fu\u0002\u0001\u0019!D\u0001}!)\u0011\t\u0001D\u0001\u0005\"1a\t\u0001D\u0001%\u001dCa!\u0015\u0001\u0005\u0002I\u0011\u0006bB0\u0001\u0001\u0004%\t\u0001\u0019\u0005\bQ\u0002\u0001\r\u0011\"\u0001j\u0011\u0015Y\u0007\u0001\"\u0001!\u0011\u0019a\u0007\u0001\"\u0001\u0013[\"1\u0001\u000f\u0001C\u0001%EDa\u0001\u001e\u0001\u0005\u0002I)\bBB@\u0001\t\u0003\u0011\u0002E\u0001\u0003UCN\\\'BA\n\u0015\u0003!\u0001\u0018M]1mY\u0016d\'BA\u000b\u0017\u0003)\u0019w\u000e\u001c7fGRLwN\u001c\u0006\u0002/\u0005)1oY1mC\u000e\u0001Qc\u0001\u000e(gM\u0011\u0001a\u0007\t\u00039ui\u0011AF\u0005\u0003=Y\u0011a!\u00118z%\u00164\u0017A\u0002\u0013j]&$H\u0005F\u0001\"!\ta\"%\u0003\u0002$-\t!QK\\5u\u0005\u0019\u0011Vm];miB\u0011ae\n\u0007\u0001\t\u0015A\u0003A1\u0001*\u0005\u0005\u0011\u0016C\u0001\u0016.!\ta2&\u0003\u0002--\t9aj\u001c;iS:<\u0007C\u0001\u000f/\u0013\tycCA\u0002B]f\fAA]3qeV\t!\u0007\u0005\u0002\'g\u00111A\u0007\u0001CC\u0002%\u0012!\u0001\u00169\u0002\t1,\u0017M\u001a\u000b\u0003C]BQ\u0001\u000f\u0003A\u0002e\naA]3tk2$\bc\u0001\u000f;K%\u00111H\u0006\u0002\u0007\u001fB$\u0018n\u001c8\u0016\u0003\u0015\n!B]3tk2$x\fJ3r)\t\ts\bC\u0004A\r\u0005\u0005\t\u0019A\u0013\u0002\u0007a$\u0013\'\u0001\ntQ>,H\u000eZ*qY&$h)\u001e:uQ\u0016\u0014X#A\"\u0011\u0005q!\u0015BA#\u0017\u0005\u001d\u0011un\u001c7fC:\fQa\u001d9mSR,\u0012\u0001\u0013\t\u0004\u00132{eB\u0001\u000fK\u0013\tYe#A\u0004qC\u000e\\\u0017mZ3\n\u00055s%aA*fc*\u00111J\u0006\t\u0005!\u0002)#\'D\u0001\u0013\u0003\u0015iWM]4f)\t\t3\u000bC\u0003U\u0013\u0001\u0007Q+\u0001\u0003uQ\u0006$(F\u0001\u001aWW\u00059\u0006C\u0001-^\u001b\u0005I&B\u0001.\\\u0003%)hn\u00195fG.,GM\u0003\u0002]-\u0005Q\u0011M\u001c8pi\u0006$\u0018n\u001c8\n\u0005yK&!E;oG\",7m[3e-\u0006\u0014\u0018.\u00198dK\u0006IA\u000f\u001b:po\u0006\u0014G.Z\u000b\u0002CB\u0011\u0011JY\u0005\u0003G:\u0013\u0011\u0002\u00165s_^\f\'\r\\3)\u0005))\u0007C\u0001\u000fg\u0013\t9gC\u0001\u0005w_2\fG/\u001b7f\u00035!\bN]8xC\ndWm\u0018\u0013fcR\u0011\u0011E\u001b\u0005\b\u0001.\t\t\u00111\u0001b\u0003A1wN]<be\u0012$\u0006N]8xC\ndW-A\u0004uefdU-\u00194\u0015\u0005\u0005r\u0007\"B8\u000e\u0001\u0004I\u0014a\u00027bgR\u0014Xm]\u0001\tiJLX*\u001a:hKR\u0011\u0011E\u001d\u0005\u0006g:\u0001\r!V\u0001\u0002i\u0006yQ.\u001a:hKRC\'o\\<bE2,7\u000f\u0006\u0002\"m\")Ak\u0004a\u0001oB\u001a\u0001P_?\u0011\tA\u0003\u0011\u0010 \t\u0003Mi$\u0011b\u001f<\u0002\u0002\u0003\u0005)\u0011A\u0015\u0003\u0007}#\u0013\u0007\u0005\u0002\'{\u0012IaP^A\u0001\u0002\u0003\u0015\t!\u000b\u0002\u0004?\u0012\u0012\u0014aC:jO:\fG.\u00112peR\u0004
   #10 = Utf8               java/lang/invoke/MethodHandles$Lookup
   #11 = Class              #10           // java/lang/invoke/MethodHandles$Lookup
   #12 = Utf8               java/lang/invoke/MethodHandles
   #13 = Class              #12           // java/lang/invoke/MethodHandles
   #14 = Utf8               Lookup
   #15 = Utf8               scala/util/control/Breaks$TryBlock
   #16 = Class              #15           // scala/util/control/Breaks$TryBlock
   #17 = Utf8               scala/util/control/Breaks
   #18 = Class              #17           // scala/util/control/Breaks
   #19 = Utf8               TryBlock
   #20 = Utf8               repr$
   #21 = Utf8               (Lscala/collection/parallel/Task;)Ljava/lang/Object;
   #22 = Utf8               $this
   #23 = Utf8               repr
   #24 = Utf8               ()Ljava/lang/Object;
   #25 = NameAndType        #23:#24       // repr:()Ljava/lang/Object;
   #26 = InterfaceMethodref #2.#25        // scala/collection/parallel/Task.repr:()Ljava/lang/Object;
   #27 = Utf8               Lscala/collection/parallel/Task;
   #28 = Utf8               ()TTp;
   #29 = Utf8               this
   #30 = Utf8               leaf
   #31 = Utf8               (Lscala/Option;)V
   #32 = Utf8               (Lscala/Option<TR;>;)V
   #33 = Utf8               result
   #34 = Utf8               ()TR;
   #35 = Utf8               result_$eq
   #36 = Utf8               (Ljava/lang/Object;)V
   #37 = Utf8               (TR;)V
   #38 = Utf8               x$1
   #39 = Utf8               shouldSplitFurther
   #40 = Utf8               ()Z
   #41 = Utf8               split
   #42 = Utf8               ()Lscala/collection/immutable/Seq;
   #43 = Utf8               ()Lscala/collection/immutable/Seq<Lscala/collection/parallel/Task<TR;TTp;>;>;
   #44 = Utf8               merge$
   #45 = Utf8               (Lscala/collection/parallel/Task;Ljava/lang/Object;)V
   #46 = Utf8               that
   #47 = Utf8               merge
   #48 = NameAndType        #47:#36       // merge:(Ljava/lang/Object;)V
   #49 = InterfaceMethodref #2.#48        // scala/collection/parallel/Task.merge:(Ljava/lang/Object;)V
   #50 = Utf8               Ljava/lang/Object;
   #51 = Utf8               (TTp;)V
   #52 = Utf8               throwable
   #53 = Utf8               ()Ljava/lang/Throwable;
   #54 = Utf8               throwable_$eq
   #55 = Utf8               (Ljava/lang/Throwable;)V
   #56 = Utf8               forwardThrowable$
   #57 = Utf8               (Lscala/collection/parallel/Task;)V
   #58 = Utf8               forwardThrowable
   #59 = Utf8               ()V
   #60 = NameAndType        #58:#59       // forwardThrowable:()V
   #61 = InterfaceMethodref #2.#60        // scala/collection/parallel/Task.forwardThrowable:()V
   #62 = NameAndType        #52:#53       // throwable:()Ljava/lang/Throwable;
   #63 = InterfaceMethodref #2.#62        // scala/collection/parallel/Task.throwable:()Ljava/lang/Throwable;
   #64 = Utf8               tryLeaf$
   #65 = Utf8               (Lscala/collection/parallel/Task;Lscala/Option;)V
   #66 = Utf8               lastres
   #67 = Utf8               tryLeaf
   #68 = NameAndType        #67:#31       // tryLeaf:(Lscala/Option;)V
   #69 = InterfaceMethodref #2.#68        // scala/collection/parallel/Task.tryLeaf:(Lscala/Option;)V
   #70 = Utf8               Lscala/Option;
   #71 = Utf8               java/lang/Throwable
   #72 = Class              #71           // java/lang/Throwable
   #73 = Utf8               scala/util/control/Breaks$
   #74 = Class              #73           // scala/util/control/Breaks$
   #75 = Utf8               MODULE$
   #76 = Utf8               Lscala/util/control/Breaks$;
   #77 = NameAndType        #75:#76       // MODULE$:Lscala/util/control/Breaks$;
   #78 = Fieldref           #74.#77       // scala/util/control/Breaks$.MODULE$:Lscala/util/control/Breaks$;
   #79 = MethodType         #59           //  ()V
   #80 = Utf8               $anonfun$tryLeaf$1
   #81 = NameAndType        #80:#65       // $anonfun$tryLeaf$1:(Lscala/collection/parallel/Task;Lscala/Option;)V
   #82 = InterfaceMethodref #2.#81        // scala/collection/parallel/Task.$anonfun$tryLeaf$1:(Lscala/collection/parallel/Task;Lscala/Option;)V
   #83 = MethodHandle       6:#82         // REF_invokeStatic scala/collection/parallel/Task.$anonfun$tryLeaf$1:(Lscala/collection/parallel/Task;Lscala/Option;)V
   #84 = Integer            1
   #85 = Utf8               java/lang/invoke/LambdaMetafactory
   #86 = Class              #85           // java/lang/invoke/LambdaMetafactory
   #87 = Utf8               altMetafactory
   #88 = Utf8               (Ljava/lang/invoke/MethodHandles$Lookup;Ljava/lang/String;Ljava/lang/invoke/MethodType;[Ljava/lang/Object;)Ljava/lang/invoke/CallSite;
   #89 = NameAndType        #87:#88       // altMetafactory:(Ljava/lang/invoke/MethodHandles$Lookup;Ljava/lang/String;Ljava/lang/invoke/MethodType;[Ljava/lang/Object;)Ljava/lang/invoke/CallSite;
   #90 = Methodref          #86.#89       // java/lang/invoke/LambdaMetafactory.altMetafactory:(Ljava/lang/invoke/MethodHandles$Lookup;Ljava/lang/String;Ljava/lang/invoke/MethodType;[Ljava/lang/Object;)Ljava/lang/invoke/CallSite;
   #91 = MethodHandle       6:#90         // REF_invokeStatic java/lang/invoke/LambdaMetafactory.altMetafactory:(Ljava/lang/invoke/MethodHandles$Lookup;Ljava/lang/String;Ljava/lang/invoke/MethodType;[Ljava/lang/Object;)Ljava/lang/invoke/CallSite;
   #92 = Utf8               apply$mcV$sp
   #93 = Utf8               (Lscala/collection/parallel/Task;Lscala/Option;)Lscala/runtime/java8/JFunction0$mcV$sp;
   #94 = NameAndType        #92:#93       // apply$mcV$sp:(Lscala/collection/parallel/Task;Lscala/Option;)Lscala/runtime/java8/JFunction0$mcV$sp;
   #95 = InvokeDynamic      #0:#94        // #0:apply$mcV$sp:(Lscala/collection/parallel/Task;Lscala/Option;)Lscala/runtime/java8/JFunction0$mcV$sp;
   #96 = Utf8               tryBreakable
   #97 = Utf8               (Lscala/Function0;)Lscala/util/control/Breaks$TryBlock;
   #98 = NameAndType        #96:#97       // tryBreakable:(Lscala/Function0;)Lscala/util/control/Breaks$TryBlock;
   #99 = Methodref          #74.#98       // scala/util/control/Breaks$.tryBreakable:(Lscala/Function0;)Lscala/util/control/Breaks$TryBlock;
  #100 = Utf8               $anonfun$tryLeaf$2
  #101 = NameAndType        #100:#57      // $anonfun$tryLeaf$2:(Lscala/collection/parallel/Task;)V
  #102 = InterfaceMethodref #2.#101       // scala/collection/parallel/Task.$anonfun$tryLeaf$2:(Lscala/collection/parallel/Task;)V
  #103 = MethodHandle       6:#102        // REF_invokeStatic scala/collection/parallel/Task.$anonfun$tryLeaf$2:(Lscala/collection/parallel/Task;)V
  #104 = Utf8               (Lscala/collection/parallel/Task;)Lscala/runtime/java8/JFunction0$mcV$sp;
  #105 = NameAndType        #92:#104      // apply$mcV$sp:(Lscala/collection/parallel/Task;)Lscala/runtime/java8/JFunction0$mcV$sp;
  #106 = InvokeDynamic      #1:#105       // #1:apply$mcV$sp:(Lscala/collection/parallel/Task;)Lscala/runtime/java8/JFunction0$mcV$sp;
  #107 = Utf8               catchBreak
  #108 = Utf8               (Lscala/Function0;)Ljava/lang/Object;
  #109 = NameAndType        #107:#108     // catchBreak:(Lscala/Function0;)Ljava/lang/Object;
  #110 = InterfaceMethodref #16.#109      // scala/util/control/Breaks$TryBlock.catchBreak:(Lscala/Function0;)Ljava/lang/Object;
  #111 = NameAndType        #33:#24       // result:()Ljava/lang/Object;
  #112 = InterfaceMethodref #2.#111       // scala/collection/parallel/Task.result:()Ljava/lang/Object;
  #113 = NameAndType        #35:#36       // result_$eq:(Ljava/lang/Object;)V
  #114 = InterfaceMethodref #2.#113       // scala/collection/parallel/Task.result_$eq:(Ljava/lang/Object;)V
  #115 = NameAndType        #54:#55       // throwable_$eq:(Ljava/lang/Throwable;)V
  #116 = InterfaceMethodref #2.#115       // scala/collection/parallel/Task.throwable_$eq:(Ljava/lang/Throwable;)V
  #117 = Utf8               signalAbort
  #118 = NameAndType        #117:#59      // signalAbort:()V
  #119 = InterfaceMethodref #2.#118       // scala/collection/parallel/Task.signalAbort:()V
  #120 = Utf8               thr
  #121 = Utf8               Ljava/lang/Throwable;
  #122 = Utf8               tryMerge$
  #123 = Utf8               t
  #124 = Utf8               tryMerge
  #125 = NameAndType        #124:#36      // tryMerge:(Ljava/lang/Object;)V
  #126 = InterfaceMethodref #2.#125       // scala/collection/parallel/Task.tryMerge:(Ljava/lang/Object;)V
  #127 = Utf8               mergeThrowables
  #128 = NameAndType        #127:#57      // mergeThrowables:(Lscala/collection/parallel/Task;)V
  #129 = InterfaceMethodref #2.#128       // scala/collection/parallel/Task.mergeThrowables:(Lscala/collection/parallel/Task;)V
  #130 = Utf8               mergeThrowables$
  #131 = Utf8               (Lscala/collection/parallel/Task;Lscala/collection/parallel/Task;)V
  #132 = Utf8               (Lscala/collection/parallel/Task<**>;)V
  #133 = Utf8               addSuppressed
  #134 = NameAndType        #133:#55      // addSuppressed:(Ljava/lang/Throwable;)V
  #135 = Methodref          #72.#134      // java/lang/Throwable.addSuppressed:(Ljava/lang/Throwable;)V
  #136 = Utf8               signalAbort$
  #137 = Utf8               lastres$1
  #138 = NameAndType        #30:#31       // leaf:(Lscala/Option;)V
  #139 = InterfaceMethodref #2.#138       // scala/collection/parallel/Task.leaf:(Lscala/Option;)V
  #140 = Utf8               $init$
  #141 = Utf8               $deserializeLambda$
  #142 = Utf8               (Ljava/lang/invoke/SerializedLambda;)Ljava/lang/Object;
  #143 = Utf8               scala/runtime/LambdaDeserialize
  #144 = Class              #143          // scala/runtime/LambdaDeserialize
  #145 = Utf8               bootstrap
  #146 = Utf8               (Ljava/lang/invoke/MethodHandles$Lookup;Ljava/lang/String;Ljava/lang/invoke/MethodType;[Ljava/lang/invoke/MethodHandle;)Ljava/lang/invoke/CallSite;
  #147 = NameAndType        #145:#146     // bootstrap:(Ljava/lang/invoke/MethodHandles$Lookup;Ljava/lang/String;Ljava/lang/invoke/MethodType;[Ljava/lang/invoke/MethodHandle;)Ljava/lang/invoke/CallSite;
  #148 = Methodref          #144.#147     // scala/runtime/LambdaDeserialize.bootstrap:(Ljava/lang/invoke/MethodHandles$Lookup;Ljava/lang/String;Ljava/lang/invoke/MethodType;[Ljava/lang/invoke/MethodHandle;)Ljava/lang/invoke/CallSite;
  #149 = MethodHandle       6:#148        // REF_invokeStatic scala/runtime/LambdaDeserialize.bootstrap:(Ljava/lang/invoke/MethodHandles$Lookup;Ljava/lang/String;Ljava/lang/invoke/MethodType;[Ljava/lang/invoke/MethodHandle;)Ljava/lang/invoke/CallSite;
  #150 = Utf8               lambdaDeserialize
  #151 = NameAndType        #150:#142     // lambdaDeserialize:(Ljava/lang/invoke/SerializedLambda;)Ljava/lang/Object;
  #152 = InvokeDynamic      #2:#151       // #2:lambdaDeserialize:(Ljava/lang/invoke/SerializedLambda;)Ljava/lang/Object;
  #153 = Utf8               Code
  #154 = Utf8               LineNumberTable
  #155 = Utf8               LocalVariableTable
  #156 = Utf8               MethodParameters
  #157 = Utf8               Signature
  #158 = Utf8               StackMapTable
  #159 = Utf8               InnerClasses
  #160 = Utf8               SourceFile
  #161 = Utf8               RuntimeVisibleAnnotations
  #162 = Utf8               BootstrapMethods
  #163 = Utf8               ScalaInlineInfo
  #164 = Utf8               ScalaSig
{
  public static java.lang.Object repr$(scala.collection.parallel.Task);
    descriptor: (Lscala/collection/parallel/Task;)Ljava/lang/Object;
    flags: (0x1009) ACC_PUBLIC, ACC_STATIC, ACC_SYNTHETIC
    Code:
      stack=1, locals=1, args_size=1
         0: aload_0
         1: invokespecial #26                 // InterfaceMethod repr:()Ljava/lang/Object;
         4: areturn
      LineNumberTable:
        line 24: 0
      LocalVariableTable:
        Start  Length  Slot  Name   Signature
            0       5     0 $this   Lscala/collection/parallel/Task;
    MethodParameters:
      Name                           Flags
      $this                          final synthetic

  public default Tp repr();
    descriptor: ()Ljava/lang/Object;
    flags: (0x0001) ACC_PUBLIC
    Code:
      stack=1, locals=1, args_size=1
         0: aload_0
         1: areturn
      LineNumberTable:
        line 24: 0
      LocalVariableTable:
        Start  Length  Slot  Name   Signature
            0       2     0  this   Lscala/collection/parallel/Task;
    Signature: #28                          // ()TTp;

  public abstract void leaf(scala.Option<R>);
    descriptor: (Lscala/Option;)V
    flags: (0x0401) ACC_PUBLIC, ACC_ABSTRACT
    Signature: #32                          // (Lscala/Option<TR;>;)V
    MethodParameters:
      Name                           Flags
      result                         final

  public abstract R result();
    descriptor: ()Ljava/lang/Object;
    flags: (0x0401) ACC_PUBLIC, ACC_ABSTRACT
    Signature: #34                          // ()TR;

  public abstract void result_$eq(R);
    descriptor: (Ljava/lang/Object;)V
    flags: (0x0401) ACC_PUBLIC, ACC_ABSTRACT
    Signature: #37                          // (TR;)V
    MethodParameters:
      Name                           Flags
      x$1                            final

  public abstract boolean shouldSplitFurther();
    descriptor: ()Z
    flags: (0x0401) ACC_PUBLIC, ACC_ABSTRACT

  public abstract scala.collection.immutable.Seq<scala.collection.parallel.Task<R, Tp>> split();
    descriptor: ()Lscala/collection/immutable/Seq;
    flags: (0x0401) ACC_PUBLIC, ACC_ABSTRACT
    Signature: #43                          // ()Lscala/collection/immutable/Seq<Lscala/collection/parallel/Task<TR;TTp;>;>;

  public static void merge$(scala.collection.parallel.Task, java.lang.Object);
    descriptor: (Lscala/collection/parallel/Task;Ljava/lang/Object;)V
    flags: (0x1009) ACC_PUBLIC, ACC_STATIC, ACC_SYNTHETIC
    Code:
      stack=2, locals=2, args_size=2
         0: aload_0
         1: aload_1
         2: invokespecial #49                 // InterfaceMethod merge:(Ljava/lang/Object;)V
         5: return
      LineNumberTable:
        line 42: 0
      LocalVariableTable:
        Start  Length  Slot  Name   Signature
            0       6     0 $this   Lscala/collection/parallel/Task;
            0       6     1  that   Ljava/lang/Object;
    MethodParameters:
      Name                           Flags
      $this                          final synthetic
      that                           final

  public default void merge(Tp);
    descriptor: (Ljava/lang/Object;)V
    flags: (0x0001) ACC_PUBLIC
    Code:
      stack=0, locals=2, args_size=2
         0: return
      LineNumberTable:
        line 42: 0
      LocalVariableTable:
        Start  Length  Slot  Name   Signature
            0       1     0  this   Lscala/collection/parallel/Task;
            0       1     1  that   Ljava/lang/Object;
    Signature: #51                          // (TTp;)V
    MethodParameters:
      Name                           Flags
      that                           final

  public abstract java.lang.Throwable throwable();
    descriptor: ()Ljava/lang/Throwable;
    flags: (0x0401) ACC_PUBLIC, ACC_ABSTRACT

  public abstract void throwable_$eq(java.lang.Throwable);
    descriptor: (Ljava/lang/Throwable;)V
    flags: (0x0401) ACC_PUBLIC, ACC_ABSTRACT
    MethodParameters:
      Name                           Flags
      x$1                            final

  public static void forwardThrowable$(scala.collection.parallel.Task);
    descriptor: (Lscala/collection/parallel/Task;)V
    flags: (0x1009) ACC_PUBLIC, ACC_STATIC, ACC_SYNTHETIC
    Code:
      stack=1, locals=1, args_size=1
         0: aload_0
         1: invokespecial #61                 // InterfaceMethod forwardThrowable:()V
         4: return
      LineNumberTable:
        line 46: 0
      LocalVariableTable:
        Start  Length  Slot  Name   Signature
            0       5     0 $this   Lscala/collection/parallel/Task;
    MethodParameters:
      Name                           Flags
      $this                          final synthetic

  public default void forwardThrowable();
    descriptor: ()V
    flags: (0x0001) ACC_PUBLIC
    Code:
      stack=1, locals=1, args_size=1
         0: aload_0
         1: invokeinterface #63,  1           // InterfaceMethod throwable:()Ljava/lang/Throwable;
         6: ifnull        16
         9: aload_0
        10: invokeinterface #63,  1           // InterfaceMethod throwable:()Ljava/lang/Throwable;
        15: athrow
        16: return
      StackMapTable: number_of_entries = 1
        frame_type = 16 /* same */
      LineNumberTable:
        line 46: 0
      LocalVariableTable:
        Start  Length  Slot  Name   Signature
            0      17     0  this   Lscala/collection/parallel/Task;

  public static void tryLeaf$(scala.collection.parallel.Task, scala.Option);
    descriptor: (Lscala/collection/parallel/Task;Lscala/Option;)V
    flags: (0x1009) ACC_PUBLIC, ACC_STATIC, ACC_SYNTHETIC
    Code:
      stack=2, locals=2, args_size=2
         0: aload_0
         1: aload_1
         2: invokespecial #69                 // InterfaceMethod tryLeaf:(Lscala/Option;)V
         5: return
      LineNumberTable:
        line 49: 0
      LocalVariableTable:
        Start  Length  Slot  Name   Signature
            0       6     0 $this   Lscala/collection/parallel/Task;
            0       6     1 lastres   Lscala/Option;
    MethodParameters:
      Name                           Flags
      $this                          final synthetic
      lastres                        final

  public default void tryLeaf(scala.Option<R>);
    descriptor: (Lscala/Option;)V
    flags: (0x0001) ACC_PUBLIC
    Code:
      stack=3, locals=3, args_size=2
         0: getstatic     #78                 // Field scala/util/control/Breaks$.MODULE$:Lscala/util/control/Breaks$;
         3: aload_0
         4: aload_1
         5: invokedynamic #95,  0             // InvokeDynamic #0:apply$mcV$sp:(Lscala/collection/parallel/Task;Lscala/Option;)Lscala/runtime/java8/JFunction0$mcV$sp;
        10: invokevirtual #99                 // Method scala/util/control/Breaks$.tryBreakable:(Lscala/Function0;)Lscala/util/control/Breaks$TryBlock;
        13: aload_0
        14: invokedynamic #106,  0            // InvokeDynamic #1:apply$mcV$sp:(Lscala/collection/parallel/Task;)Lscala/runtime/java8/JFunction0$mcV$sp;
        19: invokeinterface #110,  2          // InterfaceMethod scala/util/control/Breaks$TryBlock.catchBreak:(Lscala/Function0;)Ljava/lang/Object;
        24: pop
        25: goto          57
        28: astore_2
        29: aload_0
        30: aload_0
        31: invokeinterface #112,  1          // InterfaceMethod result:()Ljava/lang/Object;
        36: invokeinterface #114,  2          // InterfaceMethod result_$eq:(Ljava/lang/Object;)V
        41: aload_0
        42: aload_2
        43: invokeinterface #116,  2          // InterfaceMethod throwable_$eq:(Ljava/lang/Throwable;)V
        48: aload_0
        49: invokeinterface #119,  1          // InterfaceMethod signalAbort:()V
        54: goto          57
        57: return
      Exception table:
         from    to  target type
             0    25    28   Class java/lang/Throwable
      StackMapTable: number_of_entries = 2
        frame_type = 92 /* same_locals_1_stack_item */
          stack = [ class java/lang/Throwable ]
        frame_type = 28 /* same */
      LineNumberTable:
        line 51: 0
        line 55: 13
        line 54: 25
        line 59: 29
        line 60: 41
        line 61: 48
      LocalVariableTable:
        Start  Length  Slot  Name   Signature
           28      26     2   thr   Ljava/lang/Throwable;
            0      58     0  this   Lscala/collection/parallel/Task;
            0      58     1 lastres   Lscala/Option;
    Signature: #32                          // (Lscala/Option<TR;>;)V
    MethodParameters:
      Name                           Flags
      lastres                        final

  public static void tryMerge$(scala.collection.parallel.Task, java.lang.Object);
    descriptor: (Lscala/collection/parallel/Task;Ljava/lang/Object;)V
    flags: (0x1009) ACC_PUBLIC, ACC_STATIC, ACC_SYNTHETIC
    Code:
      stack=2, locals=2, args_size=2
         0: aload_0
         1: aload_1
         2: invokespecial #126                // InterfaceMethod tryMerge:(Ljava/lang/Object;)V
         5: return
      LineNumberTable:
        line 65: 0
      LocalVariableTable:
        Start  Length  Slot  Name   Signature
            0       6     0 $this   Lscala/collection/parallel/Task;
            0       6     1     t   Ljava/lang/Object;
    MethodParameters:
      Name                           Flags
      $this                          final synthetic
      t                              final

  public default void tryMerge(Tp);
    descriptor: (Ljava/lang/Object;)V
    flags: (0x0001) ACC_PUBLIC
    Code:
      stack=2, locals=3, args_size=2
         0: aload_1
         1: checkcast     #2                  // class scala/collection/parallel/Task
         4: astore_2
         5: aload_0
         6: invokeinterface #63,  1           // InterfaceMethod throwable:()Ljava/lang/Throwable;
        11: ifnonnull     33
        14: aload_2
        15: invokeinterface #63,  1           // InterfaceMethod throwable:()Ljava/lang/Throwable;
        20: ifnonnull     33
        23: aload_0
        24: aload_1
        25: invokeinterface #49,  2           // InterfaceMethod merge:(Ljava/lang/Object;)V
        30: goto          33
        33: aload_0
        34: aload_2
        35: invokeinterface #129,  2          // InterfaceMethod mergeThrowables:(Lscala/collection/parallel/Task;)V
        40: return
      StackMapTable: number_of_entries = 1
        frame_type = 252 /* append */
          offset_delta = 33
          locals = [ class scala/collection/parallel/Task ]
      LineNumberTable:
        line 66: 0
        line 67: 5
        line 68: 33
      LocalVariableTable:
        Start  Length  Slot  Name   Signature
            5      35     2  that   Lscala/collection/parallel/Task;
            0      41     0  this   Lscala/collection/parallel/Task;
            0      41     1     t   Ljava/lang/Object;
    Signature: #51                          // (TTp;)V
    MethodParameters:
      Name                           Flags
      t                              final

  public static void mergeThrowables$(scala.collection.parallel.Task, scala.collection.parallel.Task);
    descriptor: (Lscala/collection/parallel/Task;Lscala/collection/parallel/Task;)V
    flags: (0x1009) ACC_PUBLIC, ACC_STATIC, ACC_SYNTHETIC
    Code:
      stack=2, locals=2, args_size=2
         0: aload_0
         1: aload_1
         2: invokespecial #129                // InterfaceMethod mergeThrowables:(Lscala/collection/parallel/Task;)V
         5: return
      LineNumberTable:
        line 71: 0
      LocalVariableTable:
        Start  Length  Slot  Name   Signature
            0       6     0 $this   Lscala/collection/parallel/Task;
            0       6     1  that   Lscala/collection/parallel/Task;
    MethodParameters:
      Name                           Flags
      $this                          final synthetic
      that                           final

  public default void mergeThrowables(scala.collection.parallel.Task<?, ?>);
    descriptor: (Lscala/collection/parallel/Task;)V
    flags: (0x0001) ACC_PUBLIC
    Code:
      stack=2, locals=2, args_size=2
         0: aload_0
         1: invokeinterface #63,  1           // InterfaceMethod throwable:()Ljava/lang/Throwable;
         6: ifnull        36
         9: aload_1
        10: invokeinterface #63,  1           // InterfaceMethod throwable:()Ljava/lang/Throwable;
        15: ifnull        36
        18: aload_0
        19: invokeinterface #63,  1           // InterfaceMethod throwable:()Ljava/lang/Throwable;
        24: aload_1
        25: invokeinterface #63,  1           // InterfaceMethod throwable:()Ljava/lang/Throwable;
        30: invokevirtual #135                // Method java/lang/Throwable.addSuppressed:(Ljava/lang/Throwable;)V
        33: goto          69
        36: aload_0
        37: invokeinterface #63,  1           // InterfaceMethod throwable:()Ljava/lang/Throwable;
        42: ifnonnull     69
        45: aload_1
        46: invokeinterface #63,  1           // InterfaceMethod throwable:()Ljava/lang/Throwable;
        51: ifnull        69
        54: aload_0
        55: aload_1
        56: invokeinterface #63,  1           // InterfaceMethod throwable:()Ljava/lang/Throwable;
        61: invokeinterface #116,  2          // InterfaceMethod throwable_$eq:(Ljava/lang/Throwable;)V
        66: goto          69
        69: return
      StackMapTable: number_of_entries = 2
        frame_type = 36 /* same */
        frame_type = 32 /* same */
      LineNumberTable:
        line 72: 0
        line 73: 18
        line 74: 36
        line 75: 54
        line 74: 69
      LocalVariableTable:
        Start  Length  Slot  Name   Signature
            0      70     0  this   Lscala/collection/parallel/Task;
            0      70     1  that   Lscala/collection/parallel/Task;
    Signature: #132                         // (Lscala/collection/parallel/Task<**>;)V
    MethodParameters:
      Name                           Flags
      that                           final

  public static void signalAbort$(scala.collection.parallel.Task);
    descriptor: (Lscala/collection/parallel/Task;)V
    flags: (0x1009) ACC_PUBLIC, ACC_STATIC, ACC_SYNTHETIC
    Code:
      stack=1, locals=1, args_size=1
         0: aload_0
         1: invokespecial #119                // InterfaceMethod signalAbort:()V
         4: return
      LineNumberTable:
        line 79: 0
      LocalVariableTable:
        Start  Length  Slot  Name   Signature
            0       5     0 $this   Lscala/collection/parallel/Task;
    MethodParameters:
      Name                           Flags
      $this                          final synthetic

  public default void signalAbort();
    descriptor: ()V
    flags: (0x0001) ACC_PUBLIC
    Code:
      stack=0, locals=1, args_size=1
         0: return
      LineNumberTable:
        line 79: 0
      LocalVariableTable:
        Start  Length  Slot  Name   Signature
            0       1     0  this   Lscala/collection/parallel/Task;

  public static void $anonfun$tryLeaf$1(scala.collection.parallel.Task, scala.Option);
    descriptor: (Lscala/collection/parallel/Task;Lscala/Option;)V
    flags: (0x1009) ACC_PUBLIC, ACC_STATIC, ACC_SYNTHETIC
    Code:
      stack=2, locals=2, args_size=2
         0: aload_0
         1: aload_1
         2: invokeinterface #139,  2          // InterfaceMethod leaf:(Lscala/Option;)V
         7: aload_0
         8: aload_0
         9: invokeinterface #112,  1          // InterfaceMethod result:()Ljava/lang/Object;
        14: invokeinterface #114,  2          // InterfaceMethod result_$eq:(Ljava/lang/Object;)V
        19: return
      LineNumberTable:
        line 52: 0
        line 53: 7
      LocalVariableTable:
        Start  Length  Slot  Name   Signature
            0      20     0 $this   Lscala/collection/parallel/Task;
            0      20     1 lastres$1   Lscala/Option;
    MethodParameters:
      Name                           Flags
      $this                          final synthetic
      lastres$1                      final

  public static void $anonfun$tryLeaf$2(scala.collection.parallel.Task);
    descriptor: (Lscala/collection/parallel/Task;)V
    flags: (0x1009) ACC_PUBLIC, ACC_STATIC, ACC_SYNTHETIC
    Code:
      stack=1, locals=1, args_size=1
         0: aload_0
         1: invokeinterface #119,  1          // InterfaceMethod signalAbort:()V
         6: return
      LineNumberTable:
        line 55: 0
      LocalVariableTable:
        Start  Length  Slot  Name   Signature
            0       7     0 $this   Lscala/collection/parallel/Task;
    MethodParameters:
      Name                           Flags
      $this                          final synthetic

  public static void $init$(scala.collection.parallel.Task);
    descriptor: (Lscala/collection/parallel/Task;)V
    flags: (0x0009) ACC_PUBLIC, ACC_STATIC
    Code:
      stack=2, locals=1, args_size=1
         0: aload_0
         1: aconst_null
         2: invokeinterface #116,  2          // InterfaceMethod throwable_$eq:(Ljava/lang/Throwable;)V
         7: return
      LineNumberTable:
        line 45: 0
        line 21: 7
      LocalVariableTable:
        Start  Length  Slot  Name   Signature
            0       8     0 $this   Lscala/collection/parallel/Task;
    MethodParameters:
      Name                           Flags
      $this                          final synthetic

  private static java.lang.Object $deserializeLambda$(java.lang.invoke.SerializedLambda);
    descriptor: (Ljava/lang/invoke/SerializedLambda;)Ljava/lang/Object;
    flags: (0x100a) ACC_PRIVATE, ACC_STATIC, ACC_SYNTHETIC
    Code:
      stack=1, locals=1, args_size=1
         0: aload_0
         1: invokedynamic #152,  0            // InvokeDynamic #2:lambdaDeserialize:(Ljava/lang/invoke/SerializedLambda;)Ljava/lang/Object;
         6: areturn
}
InnerClasses:
  public static final #14= #11 of #13;    // Lookup=class java/lang/invoke/MethodHandles$Lookup of class java/lang/invoke/MethodHandles
  public #19= #16 of #18;                 // TryBlock=class scala/util/control/Breaks$TryBlock of class scala/util/control/Breaks
Signature: #3                           // <R:Ljava/lang/Object;Tp:Ljava/lang/Object;>Ljava/lang/Object;
SourceFile: "Tasks.scala"
RuntimeVisibleAnnotations:
  0: #7(#8=s#9)
    scala.reflect.ScalaSignature(
      bytes="\u0006\u0005\u0005\u0005aaB\t\u0013!\u0003\r\t!\u0007\u0005\u0006?\u0001!\t\u0001I\u0003\u0005I\u0001\u0001Q\u0005C\u00031\u0001\u0011\u0005\u0011\u0007C\u00036\u0001\u0019\u0005a\u0007C\u00049\u0001\u0001\u0007i\u0011\u0001\u001f\t\u000fu\u0002\u0001\u0019!D\u0001}!)\u0011\t\u0001D\u0001\u0005\"1a\t\u0001D\u0001%\u001dCa!\u0015\u0001\u0005\u0002I\u0011\u0006bB0\u0001\u0001\u0004%\t\u0001\u0019\u0005\bQ\u0002\u0001\r\u0011\"\u0001j\u0011\u0015Y\u0007\u0001\"\u0001!\u0011\u0019a\u0007\u0001\"\u0001\u0013[\"1\u0001\u000f\u0001C\u0001%EDa\u0001\u001e\u0001\u0005\u0002I)\bBB@\u0001\t\u0003\u0011\u0002E\u0001\u0003UCN\\\'BA\n\u0015\u0003!\u0001\u0018M]1mY\u0016d\'BA\u000b\u0017\u0003)\u0019w\u000e\u001c7fGRLwN\u001c\u0006\u0002/\u0005)1oY1mC\u000e\u0001Qc\u0001\u000e(gM\u0011\u0001a\u0007\t\u00039ui\u0011AF\u0005\u0003=Y\u0011a!\u00118z%\u00164\u0017A\u0002\u0013j]&$H\u0005F\u0001\"!\ta\"%\u0003\u0002$-\t!QK\\5u\u0005\u0019\u0011Vm];miB\u0011ae\n\u0007\u0001\t\u0015A\u0003A1\u0001*\u0005\u0005\u0011\u0016C\u0001\u0016.!\ta2&\u0003\u0002--\t9aj\u001c;iS:<\u0007C\u0001\u000f/\u0013\tycCA\u0002B]f\fAA]3qeV\t!\u0007\u0005\u0002\'g\u00111A\u0007\u0001CC\u0002%\u0012!\u0001\u00169\u0002\t1,\u0017M\u001a\u000b\u0003C]BQ\u0001\u000f\u0003A\u0002e\naA]3tk2$\bc\u0001\u000f;K%\u00111H\u0006\u0002\u0007\u001fB$\u0018n\u001c8\u0016\u0003\u0015\n!B]3tk2$x\fJ3r)\t\ts\bC\u0004A\r\u0005\u0005\t\u0019A\u0013\u0002\u0007a$\u0013\'\u0001\ntQ>,H\u000eZ*qY&$h)\u001e:uQ\u0016\u0014X#A\"\u0011\u0005q!\u0015BA#\u0017\u0005\u001d\u0011un\u001c7fC:\fQa\u001d9mSR,\u0012\u0001\u0013\t\u0004\u00132{eB\u0001\u000fK\u0013\tYe#A\u0004qC\u000e\\\u0017mZ3\n\u00055s%aA*fc*\u00111J\u0006\t\u0005!\u0002)#\'D\u0001\u0013\u0003\u0015iWM]4f)\t\t3\u000bC\u0003U\u0013\u0001\u0007Q+\u0001\u0003uQ\u0006$(F\u0001\u001aWW\u00059\u0006C\u0001-^\u001b\u0005I&B\u0001.\\\u0003%)hn\u00195fG.,GM\u0003\u0002]-\u0005Q\u0011M\u001c8pi\u0006$\u0018n\u001c8\n\u0005yK&!E;oG\",7m[3e-\u0006\u0014\u0018.\u00198dK\u0006IA\u000f\u001b:po\u0006\u0014G.Z\u000b\u0002CB\u0011\u0011JY\u0005\u0003G:\u0013\u0011\u0002\u00165s_^\f\'\r\\3)\u0005))\u0007C\u0001\u000fg\u0013\t9gC\u0001\u0005w_2\fG/\u001b7f\u00035!\bN]8xC\ndWm\u0018\u0013fcR\u0011\u0011E\u001b\u0005\b\u0001.\t\t\u00111\u0001b\u0003A1wN]<be\u0012$\u0006N]8xC\ndW-A\u0004uefdU-\u00194\u0015\u0005\u0005r\u0007\"B8\u000e\u0001\u0004I\u0014a\u00027bgR\u0014Xm]\u0001\tiJLX*\u001a:hKR\u0011\u0011E\u001d\u0005\u0006g:\u0001\r!V\u0001\u0002i\u0006yQ.\u001a:hKRC\'o\\<bE2,7\u000f\u0006\u0002\"m\")Ak\u0004a\u0001oB\u001a\u0001P_?\u0011\tA\u0003\u0011\u0010 \t\u0003Mi$\u0011b\u001f<\u0002\u0002\u0003\u0005)\u0011A\u0015\u0003\u0007}#\u0013\u0007\u0005\u0002\'{\u0012IaP^A\u0001\u0002\u0003\u0015\t!\u000b\u0002\u0004?\u0012\u0012\u0014aC:jO:\fG.\u00112peR\u0004"
    )
BootstrapMethods:
  0: #91 REF_invokeStatic java/lang/invoke/LambdaMetafactory.altMetafactory:(Ljava/lang/invoke/MethodHandles$Lookup;Ljava/lang/String;Ljava/lang/invoke/MethodType;[Ljava/lang/Object;)Ljava/lang/invoke/CallSite;
    Method arguments:
      #79 ()V
      #83 REF_invokeStatic scala/collection/parallel/Task.$anonfun$tryLeaf$1:(Lscala/collection/parallel/Task;Lscala/Option;)V
      #79 ()V
      #84 1
  1: #91 REF_invokeStatic java/lang/invoke/LambdaMetafactory.altMetafactory:(Ljava/lang/invoke/MethodHandles$Lookup;Ljava/lang/String;Ljava/lang/invoke/MethodType;[Ljava/lang/Object;)Ljava/lang/invoke/CallSite;
    Method arguments:
      #79 ()V
      #103 REF_invokeStatic scala/collection/parallel/Task.$anonfun$tryLeaf$2:(Lscala/collection/parallel/Task;)V
      #79 ()V
      #84 1
  2: #149 REF_invokeStatic scala/runtime/LambdaDeserialize.bootstrap:(Ljava/lang/invoke/MethodHandles$Lookup;Ljava/lang/String;Ljava/lang/invoke/MethodType;[Ljava/lang/invoke/MethodHandle;)Ljava/lang/invoke/CallSite;
    Method arguments:
      #83 REF_invokeStatic scala/collection/parallel/Task.$anonfun$tryLeaf$1:(Lscala/collection/parallel/Task;Lscala/Option;)V
      #103 REF_invokeStatic scala/collection/parallel/Task.$anonfun$tryLeaf$2:(Lscala/collection/parallel/Task;)V
  ScalaInlineInfo: length = 0x7C (unknown attribute)
   01 00 00 18 00 50 00 41 01 00 64 00 39 01 00 8C
   00 39 01 00 3A 00 3B 00 00 38 00 39 01 00 1E 00
   1F 00 00 2F 00 24 00 00 2C 00 2D 01 00 7F 00 39
   00 00 82 00 83 01 00 17 00 18 00 00 14 00 15 01
   00 21 00 18 00 00 23 00 24 00 00 27 00 28 00 00
   75 00 3B 00 00 88 00 39 01 00 29 00 2A 00 00 34
   00 35 00 00 36 00 37 00 00 43 00 1F 00 00 40 00
   41 01 00 7C 00 24 00 00 7A 00 2D 01
  ScalaSig: length = 0x3 (unknown attribute)
   05 02 00
