Classfile /Users/mw/Projects/slang-braindump/.jar/jar8/assemble/slang-braindump/assemble/content/org/scalatest/concurrent/Conductors$Conductor$TestThread.class
  Last modified May 29, 2022; size 5040 bytes
  SHA-256 checksum 0a57e12f7589e16688bf74af950f09798e974ff0e7973ae75a7d0ca23b2089ec
  Compiled from "Conductors.scala"
public class org.scalatest.concurrent.Conductors$Conductor$TestThread extends java.lang.Thread implements scala.Product,java.io.Serializable
  minor version: 0
  major version: 52
  flags: (0x0021) ACC_PUBLIC, ACC_SUPER
  this_class: #2                          // org/scalatest/concurrent/Conductors$Conductor$TestThread
  super_class: #4                         // java/lang/Thread
  interfaces: 2, fields: 3, methods: 17, attributes: 4
Constant pool:
    #1 = Utf8               org/scalatest/concurrent/Conductors$Conductor$TestThread
    #2 = Class              #1            // org/scalatest/concurrent/Conductors$Conductor$TestThread
    #3 = Utf8               java/lang/Thread
    #4 = Class              #3            // java/lang/Thread
    #5 = Utf8               scala/Product
    #6 = Class              #5            // scala/Product
    #7 = Utf8               java/io/Serializable
    #8 = Class              #7            // java/io/Serializable
    #9 = Utf8               Conductors.scala
   #10 = Utf8               org/scalatest/concurrent/Conductors$Conductor
   #11 = Class              #10           // org/scalatest/concurrent/Conductors$Conductor
   #12 = Utf8               org/scalatest/concurrent/Conductors
   #13 = Class              #12           // org/scalatest/concurrent/Conductors
   #14 = Utf8               Conductor
   #15 = Utf8               TestThread
   #16 = Utf8               name
   #17 = Utf8               Ljava/lang/String;
   #18 = Utf8               f
   #19 = Utf8               Lscala/Function0;
   #20 = Utf8               Lscala/Function0<Lscala/runtime/BoxedUnit;>;
   #21 = Utf8               $outer
   #22 = Utf8               Lorg/scalatest/concurrent/Conductors$Conductor;
   #23 = Utf8               productElementNames
   #24 = Utf8               ()Lscala/collection/Iterator;
   #25 = Utf8               ()Lscala/collection/Iterator<Ljava/lang/String;>;
   #26 = Utf8               productElementNames$
   #27 = Utf8               (Lscala/Product;)Lscala/collection/Iterator;
   #28 = NameAndType        #26:#27       // productElementNames$:(Lscala/Product;)Lscala/collection/Iterator;
   #29 = InterfaceMethodref #6.#28        // scala/Product.productElementNames$:(Lscala/Product;)Lscala/collection/Iterator;
   #30 = Utf8               this
   #31 = Utf8               Lorg/scalatest/concurrent/Conductors$Conductor$TestThread;
   #32 = Utf8               ()Ljava/lang/String;
   #33 = NameAndType        #16:#17       // name:Ljava/lang/String;
   #34 = Fieldref           #2.#33        // org/scalatest/concurrent/Conductors$Conductor$TestThread.name:Ljava/lang/String;
   #35 = Utf8               ()Lscala/Function0;
   #36 = Utf8               ()Lscala/Function0<Lscala/runtime/BoxedUnit;>;
   #37 = NameAndType        #18:#19       // f:Lscala/Function0;
   #38 = Fieldref           #2.#37        // org/scalatest/concurrent/Conductors$Conductor$TestThread.f:Lscala/Function0;
   #39 = Utf8               run
   #40 = Utf8               ()V
   #41 = Utf8               java/lang/Throwable
   #42 = Class              #41           // java/lang/Throwable
   #43 = Utf8               org$scalatest$concurrent$Conductors$Conductor$TestThread$$$outer
   #44 = Utf8               ()Lorg/scalatest/concurrent/Conductors$Conductor;
   #45 = NameAndType        #43:#44       // org$scalatest$concurrent$Conductors$Conductor$TestThread$$$outer:()Lorg/scalatest/concurrent/Conductors$Conductor;
   #46 = Methodref          #2.#45        // org/scalatest/concurrent/Conductors$Conductor$TestThread.org$scalatest$concurrent$Conductors$Conductor$TestThread$$$outer:()Lorg/scalatest/concurrent/Conductors$Conductor;
   #47 = Utf8               org$scalatest$concurrent$Conductors$Conductor$$testThreadsStartingCounter
   #48 = Utf8               ()Lorg/scalatest/concurrent/TestThreadsStartingCounter;
   #49 = NameAndType        #47:#48       // org$scalatest$concurrent$Conductors$Conductor$$testThreadsStartingCounter:()Lorg/scalatest/concurrent/TestThreadsStartingCounter;
   #50 = Methodref          #11.#49       // org/scalatest/concurrent/Conductors$Conductor.org$scalatest$concurrent$Conductors$Conductor$$testThreadsStartingCounter:()Lorg/scalatest/concurrent/TestThreadsStartingCounter;
   #51 = Utf8               org/scalatest/concurrent/TestThreadsStartingCounter
   #52 = Class              #51           // org/scalatest/concurrent/TestThreadsStartingCounter
   #53 = Utf8               decrement
   #54 = NameAndType        #53:#40       // decrement:()V
   #55 = Methodref          #52.#54       // org/scalatest/concurrent/TestThreadsStartingCounter.decrement:()V
   #56 = Utf8               org$scalatest$concurrent$Conductors$Conductor$$greenLightForTestThreads
   #57 = Utf8               ()Lorg/scalatest/CountDownLatch;
   #58 = NameAndType        #56:#57       // org$scalatest$concurrent$Conductors$Conductor$$greenLightForTestThreads:()Lorg/scalatest/CountDownLatch;
   #59 = Methodref          #11.#58       // org/scalatest/concurrent/Conductors$Conductor.org$scalatest$concurrent$Conductors$Conductor$$greenLightForTestThreads:()Lorg/scalatest/CountDownLatch;
   #60 = Utf8               org/scalatest/CountDownLatch
   #61 = Class              #60           // org/scalatest/CountDownLatch
   #62 = Utf8               await
   #63 = NameAndType        #62:#40       // await:()V
   #64 = Methodref          #61.#63       // org/scalatest/CountDownLatch.await:()V
   #65 = NameAndType        #18:#35       // f:()Lscala/Function0;
   #66 = Methodref          #2.#65        // org/scalatest/concurrent/Conductors$Conductor$TestThread.f:()Lscala/Function0;
   #67 = Utf8               scala/Function0
   #68 = Class              #67           // scala/Function0
   #69 = Utf8               apply$mcV$sp
   #70 = NameAndType        #69:#40       // apply$mcV$sp:()V
   #71 = InterfaceMethodref #68.#70       // scala/Function0.apply$mcV$sp:()V
   #72 = Utf8               org$scalatest$concurrent$Conductors$Conductor$$firstExceptionThrown
   #73 = Utf8               ()Ljava/util/concurrent/ArrayBlockingQueue;
   #74 = NameAndType        #72:#73       // org$scalatest$concurrent$Conductors$Conductor$$firstExceptionThrown:()Ljava/util/concurrent/ArrayBlockingQueue;
   #75 = Methodref          #11.#74       // org/scalatest/concurrent/Conductors$Conductor.org$scalatest$concurrent$Conductors$Conductor$$firstExceptionThrown:()Ljava/util/concurrent/ArrayBlockingQueue;
   #76 = Utf8               java/util/concurrent/ArrayBlockingQueue
   #77 = Class              #76           // java/util/concurrent/ArrayBlockingQueue
   #78 = Utf8               isEmpty
   #79 = Utf8               ()Z
   #80 = NameAndType        #78:#79       // isEmpty:()Z
   #81 = Methodref          #77.#80       // java/util/concurrent/ArrayBlockingQueue.isEmpty:()Z
   #82 = Utf8               offer
   #83 = Utf8               (Ljava/lang/Object;)Z
   #84 = NameAndType        #82:#83       // offer:(Ljava/lang/Object;)Z
   #85 = Methodref          #77.#84       // java/util/concurrent/ArrayBlockingQueue.offer:(Ljava/lang/Object;)Z
   #86 = Utf8               t
   #87 = Utf8               Ljava/lang/Throwable;
   #88 = Utf8               copy
   #89 = Utf8               (Ljava/lang/String;Lscala/Function0;)Lorg/scalatest/concurrent/Conductors$Conductor$TestThread;
   #90 = Utf8               (Ljava/lang/String;Lscala/Function0<Lscala/runtime/BoxedUnit;>;)Lorg/scalatest/concurrent/Conductors$Conductor$TestThread;
   #91 = Utf8               <init>
   #92 = Utf8               (Lorg/scalatest/concurrent/Conductors$Conductor;Ljava/lang/String;Lscala/Function0;)V
   #93 = NameAndType        #91:#92       // "<init>":(Lorg/scalatest/concurrent/Conductors$Conductor;Ljava/lang/String;Lscala/Function0;)V
   #94 = Methodref          #2.#93        // org/scalatest/concurrent/Conductors$Conductor$TestThread."<init>":(Lorg/scalatest/concurrent/Conductors$Conductor;Ljava/lang/String;Lscala/Function0;)V
   #95 = Utf8               copy$default$1
   #96 = NameAndType        #16:#32       // name:()Ljava/lang/String;
   #97 = Methodref          #2.#96        // org/scalatest/concurrent/Conductors$Conductor$TestThread.name:()Ljava/lang/String;
   #98 = Utf8               copy$default$2
   #99 = Utf8               productPrefix
  #100 = String             #15           // TestThread
  #101 = Utf8               productArity
  #102 = Utf8               ()I
  #103 = Utf8               productElement
  #104 = Utf8               (I)Ljava/lang/Object;
  #105 = Utf8               x$1
  #106 = Utf8               scala/runtime/Statics
  #107 = Class              #106          // scala/runtime/Statics
  #108 = Utf8               ioobe
  #109 = NameAndType        #108:#104     // ioobe:(I)Ljava/lang/Object;
  #110 = Methodref          #107.#109     // scala/runtime/Statics.ioobe:(I)Ljava/lang/Object;
  #111 = Utf8               I
  #112 = Utf8               java/lang/Object
  #113 = Class              #112          // java/lang/Object
  #114 = Utf8               productIterator
  #115 = Utf8               ()Lscala/collection/Iterator<Ljava/lang/Object;>;
  #116 = Utf8               scala/runtime/ScalaRunTime$
  #117 = Class              #116          // scala/runtime/ScalaRunTime$
  #118 = Utf8               MODULE$
  #119 = Utf8               Lscala/runtime/ScalaRunTime$;
  #120 = NameAndType        #118:#119     // MODULE$:Lscala/runtime/ScalaRunTime$;
  #121 = Fieldref           #117.#120     // scala/runtime/ScalaRunTime$.MODULE$:Lscala/runtime/ScalaRunTime$;
  #122 = Utf8               typedProductIterator
  #123 = NameAndType        #122:#27      // typedProductIterator:(Lscala/Product;)Lscala/collection/Iterator;
  #124 = Methodref          #117.#123     // scala/runtime/ScalaRunTime$.typedProductIterator:(Lscala/Product;)Lscala/collection/Iterator;
  #125 = Utf8               canEqual
  #126 = Utf8               Ljava/lang/Object;
  #127 = Utf8               productElementName
  #128 = Utf8               (I)Ljava/lang/String;
  #129 = String             #16           // name
  #130 = String             #18           // f
  #131 = Utf8               java/lang/String
  #132 = Class              #131          // java/lang/String
  #133 = Utf8               hashCode
  #134 = Utf8               _hashCode
  #135 = Utf8               (Lscala/Product;)I
  #136 = NameAndType        #134:#135     // _hashCode:(Lscala/Product;)I
  #137 = Methodref          #117.#136     // scala/runtime/ScalaRunTime$._hashCode:(Lscala/Product;)I
  #138 = Utf8               equals
  #139 = NameAndType        #138:#83      // equals:(Ljava/lang/Object;)Z
  #140 = Methodref          #113.#139     // java/lang/Object.equals:(Ljava/lang/Object;)Z
  #141 = NameAndType        #125:#83      // canEqual:(Ljava/lang/Object;)Z
  #142 = Methodref          #2.#141       // org/scalatest/concurrent/Conductors$Conductor$TestThread.canEqual:(Ljava/lang/Object;)Z
  #143 = NameAndType        #21:#22       // $outer:Lorg/scalatest/concurrent/Conductors$Conductor;
  #144 = Fieldref           #2.#143       // org/scalatest/concurrent/Conductors$Conductor$TestThread.$outer:Lorg/scalatest/concurrent/Conductors$Conductor;
  #145 = Utf8               (Ljava/lang/String;Lscala/Function0<Lscala/runtime/BoxedUnit;>;)V
  #146 = Utf8               org$scalatest$concurrent$Conductors$Conductor$$threadGroup
  #147 = Utf8               ()Ljava/lang/ThreadGroup;
  #148 = NameAndType        #146:#147     // org$scalatest$concurrent$Conductors$Conductor$$threadGroup:()Ljava/lang/ThreadGroup;
  #149 = Methodref          #11.#148      // org/scalatest/concurrent/Conductors$Conductor.org$scalatest$concurrent$Conductors$Conductor$$threadGroup:()Ljava/lang/ThreadGroup;
  #150 = Utf8               (Ljava/lang/ThreadGroup;Ljava/lang/String;)V
  #151 = NameAndType        #91:#150      // "<init>":(Ljava/lang/ThreadGroup;Ljava/lang/String;)V
  #152 = Methodref          #4.#151       // java/lang/Thread."<init>":(Ljava/lang/ThreadGroup;Ljava/lang/String;)V
  #153 = Utf8               $init$
  #154 = Utf8               (Lscala/Product;)V
  #155 = NameAndType        #153:#154     // $init$:(Lscala/Product;)V
  #156 = InterfaceMethodref #6.#155       // scala/Product.$init$:(Lscala/Product;)V
  #157 = Utf8               increment
  #158 = NameAndType        #157:#40      // increment:()V
  #159 = Methodref          #52.#158      // org/scalatest/concurrent/TestThreadsStartingCounter.increment:()V
  #160 = Utf8               Signature
  #161 = Utf8               Code
  #162 = Utf8               LineNumberTable
  #163 = Utf8               LocalVariableTable
  #164 = Utf8               StackMapTable
  #165 = Utf8               MethodParameters
  #166 = Utf8               InnerClasses
  #167 = Utf8               SourceFile
  #168 = Utf8               ScalaInlineInfo
  #169 = Utf8               Scala
{
  private final java.lang.String name;
    descriptor: Ljava/lang/String;
    flags: (0x0012) ACC_PRIVATE, ACC_FINAL

  private final scala.Function0<scala.runtime.BoxedUnit> f;
    descriptor: Lscala/Function0;
    flags: (0x0012) ACC_PRIVATE, ACC_FINAL
    Signature: #20                          // Lscala/Function0<Lscala/runtime/BoxedUnit;>;

  public final org.scalatest.concurrent.Conductors$Conductor $outer;
    descriptor: Lorg/scalatest/concurrent/Conductors$Conductor;
    flags: (0x1011) ACC_PUBLIC, ACC_FINAL, ACC_SYNTHETIC

  public scala.collection.Iterator<java.lang.String> productElementNames();
    descriptor: ()Lscala/collection/Iterator;
    flags: (0x0001) ACC_PUBLIC
    Code:
      stack=1, locals=1, args_size=1
         0: aload_0
         1: invokestatic  #29                 // InterfaceMethod scala/Product.productElementNames$:(Lscala/Product;)Lscala/collection/Iterator;
         4: areturn
      LineNumberTable:
        line 563: 0
      LocalVariableTable:
        Start  Length  Slot  Name   Signature
            0       5     0  this   Lorg/scalatest/concurrent/Conductors$Conductor$TestThread;
    Signature: #25                          // ()Lscala/collection/Iterator<Ljava/lang/String;>;

  public java.lang.String name();
    descriptor: ()Ljava/lang/String;
    flags: (0x0001) ACC_PUBLIC
    Code:
      stack=1, locals=1, args_size=1
         0: aload_0
         1: getfield      #34                 // Field name:Ljava/lang/String;
         4: areturn
      LineNumberTable:
        line 563: 0
      LocalVariableTable:
        Start  Length  Slot  Name   Signature
            0       5     0  this   Lorg/scalatest/concurrent/Conductors$Conductor$TestThread;

  public scala.Function0<scala.runtime.BoxedUnit> f();
    descriptor: ()Lscala/Function0;
    flags: (0x0001) ACC_PUBLIC
    Code:
      stack=1, locals=1, args_size=1
         0: aload_0
         1: getfield      #38                 // Field f:Lscala/Function0;
         4: areturn
      LineNumberTable:
        line 563: 0
      LocalVariableTable:
        Start  Length  Slot  Name   Signature
            0       5     0  this   Lorg/scalatest/concurrent/Conductors$Conductor$TestThread;
    Signature: #36                          // ()Lscala/Function0<Lscala/runtime/BoxedUnit;>;

  public void run();
    descriptor: ()V
    flags: (0x0001) ACC_PUBLIC
    Code:
      stack=2, locals=2, args_size=1
         0: aload_0
         1: invokevirtual #46                 // Method org$scalatest$concurrent$Conductors$Conductor$TestThread$$$outer:()Lorg/scalatest/concurrent/Conductors$Conductor;
         4: invokevirtual #50                 // Method org/scalatest/concurrent/Conductors$Conductor.org$scalatest$concurrent$Conductors$Conductor$$testThreadsStartingCounter:()Lorg/scalatest/concurrent/TestThreadsStartingCounter;
         7: invokevirtual #55                 // Method org/scalatest/concurrent/TestThreadsStartingCounter.decrement:()V
        10: aload_0
        11: invokevirtual #46                 // Method org$scalatest$concurrent$Conductors$Conductor$TestThread$$$outer:()Lorg/scalatest/concurrent/Conductors$Conductor;
        14: invokevirtual #59                 // Method org/scalatest/concurrent/Conductors$Conductor.org$scalatest$concurrent$Conductors$Conductor$$greenLightForTestThreads:()Lorg/scalatest/CountDownLatch;
        17: invokevirtual #64                 // Method org/scalatest/CountDownLatch.await:()V
        20: aload_0
        21: invokevirtual #66                 // Method f:()Lscala/Function0;
        24: invokeinterface #71,  1           // InterfaceMethod scala/Function0.apply$mcV$sp:()V
        29: goto          64
        32: astore_1
        33: aload_0
        34: invokevirtual #46                 // Method org$scalatest$concurrent$Conductors$Conductor$TestThread$$$outer:()Lorg/scalatest/concurrent/Conductors$Conductor;
        37: invokevirtual #75                 // Method org/scalatest/concurrent/Conductors$Conductor.org$scalatest$concurrent$Conductors$Conductor$$firstExceptionThrown:()Ljava/util/concurrent/ArrayBlockingQueue;
        40: invokevirtual #81                 // Method java/util/concurrent/ArrayBlockingQueue.isEmpty:()Z
        43: ifeq          61
        46: aload_0
        47: invokevirtual #46                 // Method org$scalatest$concurrent$Conductors$Conductor$TestThread$$$outer:()Lorg/scalatest/concurrent/Conductors$Conductor;
        50: invokevirtual #75                 // Method org/scalatest/concurrent/Conductors$Conductor.org$scalatest$concurrent$Conductors$Conductor$$firstExceptionThrown:()Ljava/util/concurrent/ArrayBlockingQueue;
        53: aload_1
        54: invokevirtual #85                 // Method java/util/concurrent/ArrayBlockingQueue.offer:(Ljava/lang/Object;)Z
        57: pop
        58: goto          61
        61: goto          64
        64: return
      Exception table:
         from    to  target type
             0    29    32   Class java/lang/Throwable
      StackMapTable: number_of_entries = 3
        frame_type = 96 /* same_locals_1_stack_item */
          stack = [ class java/lang/Throwable ]
        frame_type = 252 /* append */
          offset_delta = 28
          locals = [ class java/lang/Throwable ]
        frame_type = 250 /* chop */
          offset_delta = 2
      LineNumberTable:
        line 571: 0
        line 574: 10
        line 577: 20
        line 580: 33
        line 591: 46
        line 580: 61
      LocalVariableTable:
        Start  Length  Slot  Name   Signature
           32      29     1     t   Ljava/lang/Throwable;
            0      65     0  this   Lorg/scalatest/concurrent/Conductors$Conductor$TestThread;

  public org.scalatest.concurrent.Conductors$Conductor$TestThread copy(java.lang.String, scala.Function0<scala.runtime.BoxedUnit>);
    descriptor: (Ljava/lang/String;Lscala/Function0;)Lorg/scalatest/concurrent/Conductors$Conductor$TestThread;
    flags: (0x0001) ACC_PUBLIC
    Code:
      stack=5, locals=3, args_size=3
         0: new           #2                  // class org/scalatest/concurrent/Conductors$Conductor$TestThread
         3: dup
         4: aload_0
         5: invokevirtual #46                 // Method org$scalatest$concurrent$Conductors$Conductor$TestThread$$$outer:()Lorg/scalatest/concurrent/Conductors$Conductor;
         8: aload_1
         9: aload_2
        10: invokespecial #94                 // Method "<init>":(Lorg/scalatest/concurrent/Conductors$Conductor;Ljava/lang/String;Lscala/Function0;)V
        13: areturn
      LineNumberTable:
        line 563: 0
      LocalVariableTable:
        Start  Length  Slot  Name   Signature
            0      14     0  this   Lorg/scalatest/concurrent/Conductors$Conductor$TestThread;
            0      14     1  name   Ljava/lang/String;
            0      14     2     f   Lscala/Function0;
    Signature: #90                          // (Ljava/lang/String;Lscala/Function0<Lscala/runtime/BoxedUnit;>;)Lorg/scalatest/concurrent/Conductors$Conductor$TestThread;
    MethodParameters:
      Name                           Flags
      name                           final
      f                              final

  public java.lang.String copy$default$1();
    descriptor: ()Ljava/lang/String;
    flags: (0x0001) ACC_PUBLIC
    Code:
      stack=1, locals=1, args_size=1
         0: aload_0
         1: invokevirtual #97                 // Method name:()Ljava/lang/String;
         4: areturn
      LineNumberTable:
        line 563: 0
      LocalVariableTable:
        Start  Length  Slot  Name   Signature
            0       5     0  this   Lorg/scalatest/concurrent/Conductors$Conductor$TestThread;

  public scala.Function0<scala.runtime.BoxedUnit> copy$default$2();
    descriptor: ()Lscala/Function0;
    flags: (0x0001) ACC_PUBLIC
    Code:
      stack=1, locals=1, args_size=1
         0: aload_0
         1: invokevirtual #66                 // Method f:()Lscala/Function0;
         4: areturn
      LineNumberTable:
        line 563: 0
      LocalVariableTable:
        Start  Length  Slot  Name   Signature
            0       5     0  this   Lorg/scalatest/concurrent/Conductors$Conductor$TestThread;
    Signature: #36                          // ()Lscala/Function0<Lscala/runtime/BoxedUnit;>;

  public java.lang.String productPrefix();
    descriptor: ()Ljava/lang/String;
    flags: (0x0001) ACC_PUBLIC
    Code:
      stack=1, locals=1, args_size=1
         0: ldc           #100                // String TestThread
         2: areturn
      LineNumberTable:
        line 563: 0
      LocalVariableTable:
        Start  Length  Slot  Name   Signature
            0       3     0  this   Lorg/scalatest/concurrent/Conductors$Conductor$TestThread;

  public int productArity();
    descriptor: ()I
    flags: (0x0001) ACC_PUBLIC
    Code:
      stack=1, locals=1, args_size=1
         0: iconst_2
         1: ireturn
      LineNumberTable:
        line 563: 0
      LocalVariableTable:
        Start  Length  Slot  Name   Signature
            0       2     0  this   Lorg/scalatest/concurrent/Conductors$Conductor$TestThread;

  public java.lang.Object productElement(int);
    descriptor: (I)Ljava/lang/Object;
    flags: (0x0001) ACC_PUBLIC
    Code:
      stack=1, locals=3, args_size=2
         0: iload_1
         1: istore_2
         2: iload_2
         3: tableswitch   { // 0 to 1
                       0: 24
                       1: 31
                 default: 38
            }
        24: aload_0
        25: invokevirtual #97                 // Method name:()Ljava/lang/String;
        28: goto          45
        31: aload_0
        32: invokevirtual #66                 // Method f:()Lscala/Function0;
        35: goto          45
        38: iload_1
        39: invokestatic  #110                // Method scala/runtime/Statics.ioobe:(I)Ljava/lang/Object;
        42: goto          45
        45: areturn
      StackMapTable: number_of_entries = 4
        frame_type = 252 /* append */
          offset_delta = 24
          locals = [ int ]
        frame_type = 6 /* same */
        frame_type = 6 /* same */
        frame_type = 70 /* same_locals_1_stack_item */
          stack = [ class java/lang/Object ]
      LineNumberTable:
        line 563: 0
      LocalVariableTable:
        Start  Length  Slot  Name   Signature
            0      46     0  this   Lorg/scalatest/concurrent/Conductors$Conductor$TestThread;
            0      46     1   x$1   I
    MethodParameters:
      Name                           Flags
      x$1                            final

  public scala.collection.Iterator<java.lang.Object> productIterator();
    descriptor: ()Lscala/collection/Iterator;
    flags: (0x0001) ACC_PUBLIC
    Code:
      stack=2, locals=1, args_size=1
         0: getstatic     #121                // Field scala/runtime/ScalaRunTime$.MODULE$:Lscala/runtime/ScalaRunTime$;
         3: aload_0
         4: invokevirtual #124                // Method scala/runtime/ScalaRunTime$.typedProductIterator:(Lscala/Product;)Lscala/collection/Iterator;
         7: areturn
      LineNumberTable:
        line 563: 0
      LocalVariableTable:
        Start  Length  Slot  Name   Signature
            0       8     0  this   Lorg/scalatest/concurrent/Conductors$Conductor$TestThread;
    Signature: #115                         // ()Lscala/collection/Iterator<Ljava/lang/Object;>;

  public boolean canEqual(java.lang.Object);
    descriptor: (Ljava/lang/Object;)Z
    flags: (0x0001) ACC_PUBLIC
    Code:
      stack=1, locals=2, args_size=2
         0: aload_1
         1: instanceof    #2                  // class org/scalatest/concurrent/Conductors$Conductor$TestThread
         4: ireturn
      LineNumberTable:
        line 563: 0
      LocalVariableTable:
        Start  Length  Slot  Name   Signature
            0       5     0  this   Lorg/scalatest/concurrent/Conductors$Conductor$TestThread;
            0       5     1   x$1   Ljava/lang/Object;
    MethodParameters:
      Name                           Flags
      x$1                            final

  public java.lang.String productElementName(int);
    descriptor: (I)Ljava/lang/String;
    flags: (0x0001) ACC_PUBLIC
    Code:
      stack=1, locals=3, args_size=2
         0: iload_1
         1: istore_2
         2: iload_2
         3: tableswitch   { // 0 to 1
                       0: 24
                       1: 29
                 default: 34
            }
        24: ldc           #129                // String name
        26: goto          44
        29: ldc           #130                // String f
        31: goto          44
        34: iload_1
        35: invokestatic  #110                // Method scala/runtime/Statics.ioobe:(I)Ljava/lang/Object;
        38: checkcast     #132                // class java/lang/String
        41: goto          44
        44: areturn
      StackMapTable: number_of_entries = 4
        frame_type = 252 /* append */
          offset_delta = 24
          locals = [ int ]
        frame_type = 4 /* same */
        frame_type = 4 /* same */
        frame_type = 73 /* same_locals_1_stack_item */
          stack = [ class java/lang/String ]
      LineNumberTable:
        line 563: 0
      LocalVariableTable:
        Start  Length  Slot  Name   Signature
            0      45     0  this   Lorg/scalatest/concurrent/Conductors$Conductor$TestThread;
            0      45     1   x$1   I
    MethodParameters:
      Name                           Flags
      x$1                            final

  public int hashCode();
    descriptor: ()I
    flags: (0x0001) ACC_PUBLIC
    Code:
      stack=2, locals=1, args_size=1
         0: getstatic     #121                // Field scala/runtime/ScalaRunTime$.MODULE$:Lscala/runtime/ScalaRunTime$;
         3: aload_0
         4: invokevirtual #137                // Method scala/runtime/ScalaRunTime$._hashCode:(Lscala/Product;)I
         7: ireturn
      LineNumberTable:
        line 563: 0
      LocalVariableTable:
        Start  Length  Slot  Name   Signature
            0       8     0  this   Lorg/scalatest/concurrent/Conductors$Conductor$TestThread;

  public boolean equals(java.lang.Object);
    descriptor: (Ljava/lang/Object;)Z
    flags: (0x0001) ACC_PUBLIC
    Code:
      stack=2, locals=7, args_size=2
         0: aload_0
         1: aload_1
         2: if_acmpeq     132
         5: aload_1
         6: astore_3
         7: aload_3
         8: instanceof    #2                  // class org/scalatest/concurrent/Conductors$Conductor$TestThread
        11: ifeq          33
        14: aload_3
        15: checkcast     #2                  // class org/scalatest/concurrent/Conductors$Conductor$TestThread
        18: invokevirtual #46                 // Method org$scalatest$concurrent$Conductors$Conductor$TestThread$$$outer:()Lorg/scalatest/concurrent/Conductors$Conductor;
        21: aload_0
        22: invokevirtual #46                 // Method org$scalatest$concurrent$Conductors$Conductor$TestThread$$$outer:()Lorg/scalatest/concurrent/Conductors$Conductor;
        25: if_acmpne     33
        28: iconst_1
        29: istore_2
        30: goto          41
        33: goto          36
        36: iconst_0
        37: istore_2
        38: goto          41
        41: iload_2
        42: ifeq          136
        45: aload_1
        46: checkcast     #2                  // class org/scalatest/concurrent/Conductors$Conductor$TestThread
        49: astore        4
        51: aload_0
        52: invokevirtual #97                 // Method name:()Ljava/lang/String;
        55: aload         4
        57: invokevirtual #97                 // Method name:()Ljava/lang/String;
        60: astore        5
        62: dup
        63: ifnonnull     75
        66: pop
        67: aload         5
        69: ifnull        83
        72: goto          128
        75: aload         5
        77: invokevirtual #140                // Method java/lang/Object.equals:(Ljava/lang/Object;)Z
        80: ifeq          128
        83: aload_0
        84: invokevirtual #66                 // Method f:()Lscala/Function0;
        87: aload         4
        89: invokevirtual #66                 // Method f:()Lscala/Function0;
        92: astore        6
        94: dup
        95: ifnonnull     107
        98: pop
        99: aload         6
       101: ifnull        115
       104: goto          128
       107: aload         6
       109: invokevirtual #140                // Method java/lang/Object.equals:(Ljava/lang/Object;)Z
       112: ifeq          128
       115: aload         4
       117: aload_0
       118: invokevirtual #142                // Method canEqual:(Ljava/lang/Object;)Z
       121: ifeq          128
       124: iconst_1
       125: goto          129
       128: iconst_0
       129: ifeq          136
       132: iconst_1
       133: goto          137
       136: iconst_0
       137: ireturn
      StackMapTable: number_of_entries = 12
        frame_type = 253 /* append */
          offset_delta = 33
          locals = [ top, class java/lang/Object ]
        frame_type = 2 /* same */
        frame_type = 255 /* full_frame */
          offset_delta = 4
          locals = [ class org/scalatest/concurrent/Conductors$Conductor$TestThread, class java/lang/Object, int, class java/lang/Object ]
          stack = []
        frame_type = 255 /* full_frame */
          offset_delta = 33
          locals = [ class org/scalatest/concurrent/Conductors$Conductor$TestThread, class java/lang/Object, int, class java/lang/Object, class org/scalatest/concurrent/Conductors$Conductor$TestThread, class java/lang/String ]
          stack = [ class java/lang/String ]
        frame_type = 7 /* same */
        frame_type = 255 /* full_frame */
          offset_delta = 23
          locals = [ class org/scalatest/concurrent/Conductors$Conductor$TestThread, class java/lang/Object, int, class java/lang/Object, class org/scalatest/concurrent/Conductors$Conductor$TestThread, class java/lang/String, class scala/Function0 ]
          stack = [ class scala/Function0 ]
        frame_type = 7 /* same */
        frame_type = 250 /* chop */
          offset_delta = 12
        frame_type = 64 /* same_locals_1_stack_item */
          stack = [ int ]
        frame_type = 255 /* full_frame */
          offset_delta = 2
          locals = [ class org/scalatest/concurrent/Conductors$Conductor$TestThread, class java/lang/Object ]
          stack = []
        frame_type = 253 /* append */
          offset_delta = 3
          locals = [ int, class java/lang/Object ]
        frame_type = 255 /* full_frame */
          offset_delta = 0
          locals = [ class org/scalatest/concurrent/Conductors$Conductor$TestThread, class java/lang/Object ]
          stack = [ int ]
      LineNumberTable:
        line 563: 0
      LocalVariableTable:
        Start  Length  Slot  Name   Signature
            0     138     0  this   Lorg/scalatest/concurrent/Conductors$Conductor$TestThread;
            0     138     1   x$1   Ljava/lang/Object;
    MethodParameters:
      Name                           Flags
      x$1                            final

  public org.scalatest.concurrent.Conductors$Conductor org$scalatest$concurrent$Conductors$Conductor$TestThread$$$outer();
    descriptor: ()Lorg/scalatest/concurrent/Conductors$Conductor;
    flags: (0x1001) ACC_PUBLIC, ACC_SYNTHETIC
    Code:
      stack=1, locals=1, args_size=1
         0: aload_0
         1: getfield      #144                // Field $outer:Lorg/scalatest/concurrent/Conductors$Conductor;
         4: areturn
      LineNumberTable:
        line 563: 0
      LocalVariableTable:
        Start  Length  Slot  Name   Signature
            0       5     0  this   Lorg/scalatest/concurrent/Conductors$Conductor$TestThread;

  public org.scalatest.concurrent.Conductors$Conductor$TestThread(java.lang.String, scala.Function0<scala.runtime.BoxedUnit>);
    descriptor: (Lorg/scalatest/concurrent/Conductors$Conductor;Ljava/lang/String;Lscala/Function0;)V
    flags: (0x0001) ACC_PUBLIC
    Code:
      stack=3, locals=4, args_size=4
         0: aload_0
         1: aload_2
         2: putfield      #34                 // Field name:Ljava/lang/String;
         5: aload_0
         6: aload_3
         7: putfield      #38                 // Field f:Lscala/Function0;
        10: aload_1
        11: ifnonnull     16
        14: aconst_null
        15: athrow
        16: aload_0
        17: aload_1
        18: putfield      #144                // Field $outer:Lorg/scalatest/concurrent/Conductors$Conductor;
        21: aload_0
        22: aload_1
        23: invokevirtual #149                // Method org/scalatest/concurrent/Conductors$Conductor.org$scalatest$concurrent$Conductors$Conductor$$threadGroup:()Ljava/lang/ThreadGroup;
        26: aload_2
        27: invokespecial #152                // Method java/lang/Thread."<init>":(Ljava/lang/ThreadGroup;Ljava/lang/String;)V
        30: aload_0
        31: invokestatic  #156                // InterfaceMethod scala/Product.$init$:(Lscala/Product;)V
        34: aload_1
        35: invokevirtual #50                 // Method org/scalatest/concurrent/Conductors$Conductor.org$scalatest$concurrent$Conductors$Conductor$$testThreadsStartingCounter:()Lorg/scalatest/concurrent/TestThreadsStartingCounter;
        38: invokevirtual #159                // Method org/scalatest/concurrent/TestThreadsStartingCounter.increment:()V
        41: return
      StackMapTable: number_of_entries = 1
        frame_type = 16 /* same */
      LineNumberTable:
        line 563: 0
        line 566: 34
        line 563: 41
      LocalVariableTable:
        Start  Length  Slot  Name   Signature
            0      42     0  this   Lorg/scalatest/concurrent/Conductors$Conductor$TestThread;
            0      42     1 $outer   Lorg/scalatest/concurrent/Conductors$Conductor;
            0      42     2  name   Ljava/lang/String;
            0      42     3     f   Lscala/Function0;
    Signature: #145                         // (Ljava/lang/String;Lscala/Function0<Lscala/runtime/BoxedUnit;>;)V
    MethodParameters:
      Name                           Flags
      $outer                         final synthetic
      name                           final
      f                              final
}
InnerClasses:
  public final #14= #11 of #13;           // Conductor=class org/scalatest/concurrent/Conductors$Conductor of class org/scalatest/concurrent/Conductors
  private #15= #2 of #11;                 // TestThread=class org/scalatest/concurrent/Conductors$Conductor$TestThread of class org/scalatest/concurrent/Conductors$Conductor
SourceFile: "Conductors.scala"
  ScalaInlineInfo: length = 0x59 (unknown attribute)
   01 00 00 11 00 5B 00 5C 00 00 7D 00 53 00 00 58
   00 59 00 00 5F 00 20 00 00 62 00 23 00 00 8A 00
   53 00 00 12 00 23 00 00 85 00 66 00 00 10 00 20
   00 00 2B 00 2C 00 00 65 00 66 00 00 67 00 68 00
   00 7F 00 80 00 00 17 00 18 00 00 72 00 18 00 00
   63 00 20 00 00 27 00 28 00
  Scala: length = 0x0 (unknown attribute)

