Classfile /Users/mw/Projects/slang-braindump/.jar/jar8/assemble/slang-braindump/assemble/content/org/scalatest/concurrent/Eventually.class
  Last modified May 29, 2022; size 6591 bytes
  SHA-256 checksum 010915d74e07f46a8cdcdcdd0039a4eb3fa6f222609fa8dc9342851b7f4fbae8
  Compiled from "Eventually.scala"
public interface org.scalatest.concurrent.Eventually extends org.scalatest.concurrent.PatienceConfiguration
  minor version: 0
  major version: 52
  flags: (0x0601) ACC_PUBLIC, ACC_INTERFACE, ACC_ABSTRACT
  this_class: #2                          // org/scalatest/concurrent/Eventually
  super_class: #4                         // java/lang/Object
  interfaces: 1, fields: 0, methods: 9, attributes: 5
Constant pool:
   #1 = Utf8               org/scalatest/concurrent/Eventually
   #2 = Class              #1             // org/scalatest/concurrent/Eventually
   #3 = Utf8               java/lang/Object
   #4 = Class              #3             // java/lang/Object
   #5 = Utf8               org/scalatest/concurrent/PatienceConfiguration
   #6 = Class              #5             // org/scalatest/concurrent/PatienceConfiguration
   #7 = Utf8               Eventually.scala
   #8 = Utf8               Lscala/reflect/ScalaSignature;
   #9 = Utf8               bytes
  #10 = Utf8               \u0006\u0005\u0005EaaB\u0005\u000b!\u0003\r\t!\u0005\u0005\u00069\u0001!\t!\b\u0005\u0006C\u0001!\tA\t\u0005\u0006C\u0001!\tA\u0016\u0005\u0006C\u0001!\tA\u001b\u0005\u0006C\u0001!\ta^\u0004\b\u0003\u000bQ\u0001\u0012AA\u0004\r\u0019I!\u0002#\u0001\u0002\n!9\u0011QB\u0004\u0005\u0002\u0005=!AC#wK:$X/\u00197ms*\u00111\u0002D\u0001\u000bG>t7-\u001e:sK:$(BA\u0007\u000f\u0003%\u00198-\u00197bi\u0016\u001cHOC\u0001\u0010\u0003\ry\'oZ\u0002\u0001\'\r\u0001!\u0003\u0007\t\u0003\'Yi\u0011\u0001\u0006\u0006\u0002+\u0005)1oY1mC&\u0011q\u0003\u0006\u0002\u0007\u0003:L(+\u001a4\u0011\u0005eQR\"\u0001\u0006\n\u0005mQ!!\u0006)bi&,gnY3D_:4\u0017nZ;sCRLwN\\\u0001\u0007I%t\u0017\u000e\u001e\u0013\u0015\u0003y\u0001\"aE\u0010\n\u0005\u0001\"\"\u0001B+oSR\f!\"\u001a<f]R,\u0018\r\u001c7z+\t\u0019\u0003\u0006F\u0002%\u0011F#\"!J\"\u0015\u0007\u0019\n\u0014\b\u0005\u0002(Q1\u0001A!B\u0015\u0003\u0005\u0004Q#!\u0001+\u0012\u0005-r\u0003CA\n-\u0013\tiCCA\u0004O_RD\u0017N\\4\u0011\u0005My\u0013B\u0001\u0019\u0015\u0005\r\te.\u001f\u0005\u0006e\t\u0001\u001daM\u0001\te\u0016$(/_5oOB\u0019Ag\u000e\u0014\u000e\u0003UR!A\u000e\u0007\u0002\u0011\u0015t\u0017M\u00197feNL!\u0001O\u001b\u0003\u0011I+GO]=j]\u001eDQA\u000f\u0002A\u0004m\n1\u0001]8t!\ta\u0014)D\u0001>\u0015\tqt(\u0001\u0004t_V\u00148-\u001a\u0006\u0003\u0001:\t\u0011b]2bY\u0006\u001cG/[2\n\u0005\tk$\u0001\u0003)pg&$\u0018n\u001c8\t\r\u0011\u0013A\u00111\u0001F\u0003\r1WO\u001c\t\u0004\'\u00193\u0013BA$\u0015\u0005!a$-\u001f8b[\u0016t\u0004\"B%\u0003\u0001\u0004Q\u0015a\u0002;j[\u0016|W\u000f\u001e\t\u0003\u0017:s!!\u0007\'\n\u00055S\u0011!\u0006)bi&,gnY3D_:4\u0017nZ;sCRLwN\\\u0005\u0003\u001fB\u0013q\u0001V5nK>,HO\u0003\u0002N\u0015!)!K\u0001a\u0001\'\u0006A\u0011N\u001c;feZ\fG\u000e\u0005\u0002L)&\u0011Q\u000b\u0015\u0002\t\u0013:$XM\u001d<bYV\u0011qk\u0017\u000b\u00031&$\"!W4\u0015\ticFM\u001a\t\u0003Om#Q!K\u0002C\u0002)BQ!X\u0002A\u0004y\u000baaY8oM&<\u0007CA0a\u001b\u0005\u0001\u0011BA1c\u00059\u0001\u0016\r^5f]\u000e,7i\u001c8gS\u001eL!a\u0019\u0006\u0003;\u0005\u00137\u000f\u001e:bGR\u0004\u0016\r^5f]\u000e,7i\u001c8gS\u001e,(/\u0019;j_:DQAM\u0002A\u0004\u0015\u00042\u0001N\u001c[\u0011\u0015Q4\u0001q\u0001<\u0011\u0019!5\u0001\"a\u0001QB\u00191C\u0012.\t\u000b%\u001b\u0001\u0019\u0001&\u0016\u0005-|GC\u00017w)\tiG\u000f\u0006\u0003oaF\u001c\bCA\u0014p\t\u0015ICA1\u0001+\u0011\u0015iF\u0001q\u0001_\u0011\u0015\u0011D\u0001q\u0001s!\r!tG\u001c\u0005\u0006u\u0011\u0001\u001da\u000f\u0005\u0007\t\u0012!\t\u0019A;\u0011\u0007M1e\u000eC\u0003S\t\u0001\u00071+\u0006\u0002ywR\u0019\u00110!\u0001\u0015\tidXp \t\u0003Om$Q!K\u0003C\u0002)BQ!X\u0003A\u0004yCQAM\u0003A\u0004y\u00042\u0001N\u001c{\u0011\u0015QT\u0001q\u0001<\u0011\u001d!U\u0001\"a\u0001\u0003\u0007\u00012a\u0005${\u0003))e/\u001a8uk\u0006dG.\u001f\t\u00033\u001d\u0019Ba\u0002\n\u0002\fA\u0011\u0011\u0004A\u0001\u0007y%t\u0017\u000e\u001e \u0015\u0005\u0005\u001d\u0001
  #11 = Utf8               org/scalatest/concurrent/AbstractPatienceConfiguration$PatienceConfig
  #12 = Class              #11            // org/scalatest/concurrent/AbstractPatienceConfiguration$PatienceConfig
  #13 = Utf8               org/scalatest/concurrent/AbstractPatienceConfiguration
  #14 = Class              #13            // org/scalatest/concurrent/AbstractPatienceConfiguration
  #15 = Utf8               PatienceConfig
  #16 = Utf8               org/scalatest/concurrent/PatienceConfiguration$Interval
  #17 = Class              #16            // org/scalatest/concurrent/PatienceConfiguration$Interval
  #18 = Utf8               Interval
  #19 = Utf8               org/scalatest/concurrent/PatienceConfiguration$Timeout
  #20 = Class              #19            // org/scalatest/concurrent/PatienceConfiguration$Timeout
  #21 = Utf8               Timeout
  #22 = Utf8               eventually$
  #23 = Utf8               (Lorg/scalatest/concurrent/Eventually;Lorg/scalatest/concurrent/PatienceConfiguration$Timeout;Lorg/scalatest/concurrent/PatienceConfiguration$Interval;Lscala/Function0;Lorg/scalatest/enablers/Retrying;Lorg/scalactic/source/Position;)Ljava/lang/Object;
  #24 = Utf8               $this
  #25 = Utf8               timeout
  #26 = Utf8               interval
  #27 = Utf8               fun
  #28 = Utf8               retrying
  #29 = Utf8               pos
  #30 = Utf8               eventually
  #31 = Utf8               (Lorg/scalatest/concurrent/PatienceConfiguration$Timeout;Lorg/scalatest/concurrent/PatienceConfiguration$Interval;Lscala/Function0;Lorg/scalatest/enablers/Retrying;Lorg/scalactic/source/Position;)Ljava/lang/Object;
  #32 = NameAndType        #30:#31        // eventually:(Lorg/scalatest/concurrent/PatienceConfiguration$Timeout;Lorg/scalatest/concurrent/PatienceConfiguration$Interval;Lscala/Function0;Lorg/scalatest/enablers/Retrying;Lorg/scalactic/source/Position;)Ljava/lang/Object;
  #33 = InterfaceMethodref #2.#32         // org/scalatest/concurrent/Eventually.eventually:(Lorg/scalatest/concurrent/PatienceConfiguration$Timeout;Lorg/scalatest/concurrent/PatienceConfiguration$Interval;Lscala/Function0;Lorg/scalatest/enablers/Retrying;Lorg/scalactic/source/Position;)Ljava/lang/Object;
  #34 = Utf8               Lorg/scalatest/concurrent/Eventually;
  #35 = Utf8               Lorg/scalatest/concurrent/PatienceConfiguration$Timeout;
  #36 = Utf8               Lorg/scalatest/concurrent/PatienceConfiguration$Interval;
  #37 = Utf8               Lscala/Function0;
  #38 = Utf8               Lorg/scalatest/enablers/Retrying;
  #39 = Utf8               Lorg/scalactic/source/Position;
  #40 = Utf8               <T:Ljava/lang/Object;>(Lorg/scalatest/concurrent/PatienceConfiguration$Timeout;Lorg/scalatest/concurrent/PatienceConfiguration$Interval;Lscala/Function0<TT;>;Lorg/scalatest/enablers/Retrying<TT;>;Lorg/scalactic/source/Position;)TT;
  #41 = Utf8               value
  #42 = Utf8               ()Lorg/scalatest/time/Span;
  #43 = NameAndType        #41:#42        // value:()Lorg/scalatest/time/Span;
  #44 = Methodref          #20.#43        // org/scalatest/concurrent/PatienceConfiguration$Timeout.value:()Lorg/scalatest/time/Span;
  #45 = Methodref          #17.#43        // org/scalatest/concurrent/PatienceConfiguration$Interval.value:()Lorg/scalatest/time/Span;
  #46 = Utf8               org/scalatest/enablers/Retrying
  #47 = Class              #46            // org/scalatest/enablers/Retrying
  #48 = Utf8               retry
  #49 = Utf8               (Lorg/scalatest/time/Span;Lorg/scalatest/time/Span;Lorg/scalactic/source/Position;Lscala/Function0;)Ljava/lang/Object;
  #50 = NameAndType        #48:#49        // retry:(Lorg/scalatest/time/Span;Lorg/scalatest/time/Span;Lorg/scalactic/source/Position;Lscala/Function0;)Ljava/lang/Object;
  #51 = InterfaceMethodref #47.#50        // org/scalatest/enablers/Retrying.retry:(Lorg/scalatest/time/Span;Lorg/scalatest/time/Span;Lorg/scalactic/source/Position;Lscala/Function0;)Ljava/lang/Object;
  #52 = Utf8               this
  #53 = Utf8               (Lorg/scalatest/concurrent/Eventually;Lorg/scalatest/concurrent/PatienceConfiguration$Timeout;Lscala/Function0;Lorg/scalatest/concurrent/AbstractPatienceConfiguration$PatienceConfig;Lorg/scalatest/enablers/Retrying;Lorg/scalactic/source/Position;)Ljava/lang/Object;
  #54 = Utf8               config
  #55 = Utf8               (Lorg/scalatest/concurrent/PatienceConfiguration$Timeout;Lscala/Function0;Lorg/scalatest/concurrent/AbstractPatienceConfiguration$PatienceConfig;Lorg/scalatest/enablers/Retrying;Lorg/scalactic/source/Position;)Ljava/lang/Object;
  #56 = NameAndType        #30:#55        // eventually:(Lorg/scalatest/concurrent/PatienceConfiguration$Timeout;Lscala/Function0;Lorg/scalatest/concurrent/AbstractPatienceConfiguration$PatienceConfig;Lorg/scalatest/enablers/Retrying;Lorg/scalactic/source/Position;)Ljava/lang/Object;
  #57 = InterfaceMethodref #2.#56         // org/scalatest/concurrent/Eventually.eventually:(Lorg/scalatest/concurrent/PatienceConfiguration$Timeout;Lscala/Function0;Lorg/scalatest/concurrent/AbstractPatienceConfiguration$PatienceConfig;Lorg/scalatest/enablers/Retrying;Lorg/scalactic/source/Position;)Ljava/lang/Object;
  #58 = Utf8               Lorg/scalatest/concurrent/AbstractPatienceConfiguration$PatienceConfig;
  #59 = Utf8               <T:Ljava/lang/Object;>(Lorg/scalatest/concurrent/PatienceConfiguration$Timeout;Lscala/Function0<TT;>;Lorg/scalatest/concurrent/AbstractPatienceConfiguration$PatienceConfig;Lorg/scalatest/enablers/Retrying<TT;>;Lorg/scalactic/source/Position;)TT;
  #60 = NameAndType        #26:#42        // interval:()Lorg/scalatest/time/Span;
  #61 = Methodref          #12.#60        // org/scalatest/concurrent/AbstractPatienceConfiguration$PatienceConfig.interval:()Lorg/scalatest/time/Span;
  #62 = Utf8               (Lorg/scalatest/concurrent/Eventually;Lorg/scalatest/concurrent/PatienceConfiguration$Interval;Lscala/Function0;Lorg/scalatest/concurrent/AbstractPatienceConfiguration$PatienceConfig;Lorg/scalatest/enablers/Retrying;Lorg/scalactic/source/Position;)Ljava/lang/Object;
  #63 = Utf8               (Lorg/scalatest/concurrent/PatienceConfiguration$Interval;Lscala/Function0;Lorg/scalatest/concurrent/AbstractPatienceConfiguration$PatienceConfig;Lorg/scalatest/enablers/Retrying;Lorg/scalactic/source/Position;)Ljava/lang/Object;
  #64 = NameAndType        #30:#63        // eventually:(Lorg/scalatest/concurrent/PatienceConfiguration$Interval;Lscala/Function0;Lorg/scalatest/concurrent/AbstractPatienceConfiguration$PatienceConfig;Lorg/scalatest/enablers/Retrying;Lorg/scalactic/source/Position;)Ljava/lang/Object;
  #65 = InterfaceMethodref #2.#64         // org/scalatest/concurrent/Eventually.eventually:(Lorg/scalatest/concurrent/PatienceConfiguration$Interval;Lscala/Function0;Lorg/scalatest/concurrent/AbstractPatienceConfiguration$PatienceConfig;Lorg/scalatest/enablers/Retrying;Lorg/scalactic/source/Position;)Ljava/lang/Object;
  #66 = Utf8               <T:Ljava/lang/Object;>(Lorg/scalatest/concurrent/PatienceConfiguration$Interval;Lscala/Function0<TT;>;Lorg/scalatest/concurrent/AbstractPatienceConfiguration$PatienceConfig;Lorg/scalatest/enablers/Retrying<TT;>;Lorg/scalactic/source/Position;)TT;
  #67 = NameAndType        #25:#42        // timeout:()Lorg/scalatest/time/Span;
  #68 = Methodref          #12.#67        // org/scalatest/concurrent/AbstractPatienceConfiguration$PatienceConfig.timeout:()Lorg/scalatest/time/Span;
  #69 = Utf8               (Lorg/scalatest/concurrent/Eventually;Lscala/Function0;Lorg/scalatest/concurrent/AbstractPatienceConfiguration$PatienceConfig;Lorg/scalatest/enablers/Retrying;Lorg/scalactic/source/Position;)Ljava/lang/Object;
  #70 = Utf8               (Lscala/Function0;Lorg/scalatest/concurrent/AbstractPatienceConfiguration$PatienceConfig;Lorg/scalatest/enablers/Retrying;Lorg/scalactic/source/Position;)Ljava/lang/Object;
  #71 = NameAndType        #30:#70        // eventually:(Lscala/Function0;Lorg/scalatest/concurrent/AbstractPatienceConfiguration$PatienceConfig;Lorg/scalatest/enablers/Retrying;Lorg/scalactic/source/Position;)Ljava/lang/Object;
  #72 = InterfaceMethodref #2.#71         // org/scalatest/concurrent/Eventually.eventually:(Lscala/Function0;Lorg/scalatest/concurrent/AbstractPatienceConfiguration$PatienceConfig;Lorg/scalatest/enablers/Retrying;Lorg/scalactic/source/Position;)Ljava/lang/Object;
  #73 = Utf8               <T:Ljava/lang/Object;>(Lscala/Function0<TT;>;Lorg/scalatest/concurrent/AbstractPatienceConfiguration$PatienceConfig;Lorg/scalatest/enablers/Retrying<TT;>;Lorg/scalactic/source/Position;)TT;
  #74 = Utf8               $init$
  #75 = Utf8               (Lorg/scalatest/concurrent/Eventually;)V
  #76 = Utf8               Code
  #77 = Utf8               LineNumberTable
  #78 = Utf8               LocalVariableTable
  #79 = Utf8               MethodParameters
  #80 = Utf8               Signature
  #81 = Utf8               InnerClasses
  #82 = Utf8               SourceFile
  #83 = Utf8               RuntimeVisibleAnnotations
  #84 = Utf8               ScalaInlineInfo
  #85 = Utf8               ScalaSig
{
  public static java.lang.Object eventually$(org.scalatest.concurrent.Eventually, org.scalatest.concurrent.PatienceConfiguration$Timeout, org.scalatest.concurrent.PatienceConfiguration$Interval, scala.Function0, org.scalatest.enablers.Retrying, org.scalactic.source.Position);
    descriptor: (Lorg/scalatest/concurrent/Eventually;Lorg/scalatest/concurrent/PatienceConfiguration$Timeout;Lorg/scalatest/concurrent/PatienceConfiguration$Interval;Lscala/Function0;Lorg/scalatest/enablers/Retrying;Lorg/scalactic/source/Position;)Ljava/lang/Object;
    flags: (0x1009) ACC_PUBLIC, ACC_STATIC, ACC_SYNTHETIC
    Code:
      stack=6, locals=6, args_size=6
         0: aload_0
         1: aload_1
         2: aload_2
         3: aload_3
         4: aload         4
         6: aload         5
         8: invokespecial #33                 // InterfaceMethod eventually:(Lorg/scalatest/concurrent/PatienceConfiguration$Timeout;Lorg/scalatest/concurrent/PatienceConfiguration$Interval;Lscala/Function0;Lorg/scalatest/enablers/Retrying;Lorg/scalactic/source/Position;)Ljava/lang/Object;
        11: areturn
      LineNumberTable:
        line 312: 0
      LocalVariableTable:
        Start  Length  Slot  Name   Signature
            0      12     0 $this   Lorg/scalatest/concurrent/Eventually;
            0      12     1 timeout   Lorg/scalatest/concurrent/PatienceConfiguration$Timeout;
            0      12     2 interval   Lorg/scalatest/concurrent/PatienceConfiguration$Interval;
            0      12     3   fun   Lscala/Function0;
            0      12     4 retrying   Lorg/scalatest/enablers/Retrying;
            0      12     5   pos   Lorg/scalactic/source/Position;
    MethodParameters:
      Name                           Flags
      $this                          final synthetic
      timeout                        final
      interval                       final
      fun                            final
      retrying                       final
      pos                            final

  public default <T extends java.lang.Object> T eventually(org.scalatest.concurrent.PatienceConfiguration$Timeout, org.scalatest.concurrent.PatienceConfiguration$Interval, scala.Function0<T>, org.scalatest.enablers.Retrying<T>, org.scalactic.source.Position);
    descriptor: (Lorg/scalatest/concurrent/PatienceConfiguration$Timeout;Lorg/scalatest/concurrent/PatienceConfiguration$Interval;Lscala/Function0;Lorg/scalatest/enablers/Retrying;Lorg/scalactic/source/Position;)Ljava/lang/Object;
    flags: (0x0001) ACC_PUBLIC
    Code:
      stack=5, locals=6, args_size=6
         0: aload         4
         2: aload_1
         3: invokevirtual #44                 // Method org/scalatest/concurrent/PatienceConfiguration$Timeout.value:()Lorg/scalatest/time/Span;
         6: aload_2
         7: invokevirtual #45                 // Method org/scalatest/concurrent/PatienceConfiguration$Interval.value:()Lorg/scalatest/time/Span;
        10: aload         5
        12: aload_3
        13: invokeinterface #51,  5           // InterfaceMethod org/scalatest/enablers/Retrying.retry:(Lorg/scalatest/time/Span;Lorg/scalatest/time/Span;Lorg/scalactic/source/Position;Lscala/Function0;)Ljava/lang/Object;
        18: areturn
      LineNumberTable:
        line 313: 0
      LocalVariableTable:
        Start  Length  Slot  Name   Signature
            0      19     0  this   Lorg/scalatest/concurrent/Eventually;
            0      19     1 timeout   Lorg/scalatest/concurrent/PatienceConfiguration$Timeout;
            0      19     2 interval   Lorg/scalatest/concurrent/PatienceConfiguration$Interval;
            0      19     3   fun   Lscala/Function0;
            0      19     4 retrying   Lorg/scalatest/enablers/Retrying;
            0      19     5   pos   Lorg/scalactic/source/Position;
    Signature: #40                          // <T:Ljava/lang/Object;>(Lorg/scalatest/concurrent/PatienceConfiguration$Timeout;Lorg/scalatest/concurrent/PatienceConfiguration$Interval;Lscala/Function0<TT;>;Lorg/scalatest/enablers/Retrying<TT;>;Lorg/scalactic/source/Position;)TT;
    MethodParameters:
      Name                           Flags
      timeout                        final
      interval                       final
      fun                            final
      retrying                       final
      pos                            final

  public static java.lang.Object eventually$(org.scalatest.concurrent.Eventually, org.scalatest.concurrent.PatienceConfiguration$Timeout, scala.Function0, org.scalatest.concurrent.AbstractPatienceConfiguration$PatienceConfig, org.scalatest.enablers.Retrying, org.scalactic.source.Position);
    descriptor: (Lorg/scalatest/concurrent/Eventually;Lorg/scalatest/concurrent/PatienceConfiguration$Timeout;Lscala/Function0;Lorg/scalatest/concurrent/AbstractPatienceConfiguration$PatienceConfig;Lorg/scalatest/enablers/Retrying;Lorg/scalactic/source/Position;)Ljava/lang/Object;
    flags: (0x1009) ACC_PUBLIC, ACC_STATIC, ACC_SYNTHETIC
    Code:
      stack=6, locals=6, args_size=6
         0: aload_0
         1: aload_1
         2: aload_2
         3: aload_3
         4: aload         4
         6: aload         5
         8: invokespecial #57                 // InterfaceMethod eventually:(Lorg/scalatest/concurrent/PatienceConfiguration$Timeout;Lscala/Function0;Lorg/scalatest/concurrent/AbstractPatienceConfiguration$PatienceConfig;Lorg/scalatest/enablers/Retrying;Lorg/scalactic/source/Position;)Ljava/lang/Object;
        11: areturn
      LineNumberTable:
        line 347: 0
      LocalVariableTable:
        Start  Length  Slot  Name   Signature
            0      12     0 $this   Lorg/scalatest/concurrent/Eventually;
            0      12     1 timeout   Lorg/scalatest/concurrent/PatienceConfiguration$Timeout;
            0      12     2   fun   Lscala/Function0;
            0      12     3 config   Lorg/scalatest/concurrent/AbstractPatienceConfiguration$PatienceConfig;
            0      12     4 retrying   Lorg/scalatest/enablers/Retrying;
            0      12     5   pos   Lorg/scalactic/source/Position;
    MethodParameters:
      Name                           Flags
      $this                          final synthetic
      timeout                        final
      fun                            final
      config                         final
      retrying                       final
      pos                            final

  public default <T extends java.lang.Object> T eventually(org.scalatest.concurrent.PatienceConfiguration$Timeout, scala.Function0<T>, org.scalatest.concurrent.AbstractPatienceConfiguration$PatienceConfig, org.scalatest.enablers.Retrying<T>, org.scalactic.source.Position);
    descriptor: (Lorg/scalatest/concurrent/PatienceConfiguration$Timeout;Lscala/Function0;Lorg/scalatest/concurrent/AbstractPatienceConfiguration$PatienceConfig;Lorg/scalatest/enablers/Retrying;Lorg/scalactic/source/Position;)Ljava/lang/Object;
    flags: (0x0001) ACC_PUBLIC
    Code:
      stack=5, locals=6, args_size=6
         0: aload         4
         2: aload_1
         3: invokevirtual #44                 // Method org/scalatest/concurrent/PatienceConfiguration$Timeout.value:()Lorg/scalatest/time/Span;
         6: aload_3
         7: invokevirtual #61                 // Method org/scalatest/concurrent/AbstractPatienceConfiguration$PatienceConfig.interval:()Lorg/scalatest/time/Span;
        10: aload         5
        12: aload_2
        13: invokeinterface #51,  5           // InterfaceMethod org/scalatest/enablers/Retrying.retry:(Lorg/scalatest/time/Span;Lorg/scalatest/time/Span;Lorg/scalactic/source/Position;Lscala/Function0;)Ljava/lang/Object;
        18: areturn
      LineNumberTable:
        line 348: 0
      LocalVariableTable:
        Start  Length  Slot  Name   Signature
            0      19     0  this   Lorg/scalatest/concurrent/Eventually;
            0      19     1 timeout   Lorg/scalatest/concurrent/PatienceConfiguration$Timeout;
            0      19     2   fun   Lscala/Function0;
            0      19     3 config   Lorg/scalatest/concurrent/AbstractPatienceConfiguration$PatienceConfig;
            0      19     4 retrying   Lorg/scalatest/enablers/Retrying;
            0      19     5   pos   Lorg/scalactic/source/Position;
    Signature: #59                          // <T:Ljava/lang/Object;>(Lorg/scalatest/concurrent/PatienceConfiguration$Timeout;Lscala/Function0<TT;>;Lorg/scalatest/concurrent/AbstractPatienceConfiguration$PatienceConfig;Lorg/scalatest/enablers/Retrying<TT;>;Lorg/scalactic/source/Position;)TT;
    MethodParameters:
      Name                           Flags
      timeout                        final
      fun                            final
      config                         final
      retrying                       final
      pos                            final

  public static java.lang.Object eventually$(org.scalatest.concurrent.Eventually, org.scalatest.concurrent.PatienceConfiguration$Interval, scala.Function0, org.scalatest.concurrent.AbstractPatienceConfiguration$PatienceConfig, org.scalatest.enablers.Retrying, org.scalactic.source.Position);
    descriptor: (Lorg/scalatest/concurrent/Eventually;Lorg/scalatest/concurrent/PatienceConfiguration$Interval;Lscala/Function0;Lorg/scalatest/concurrent/AbstractPatienceConfiguration$PatienceConfig;Lorg/scalatest/enablers/Retrying;Lorg/scalactic/source/Position;)Ljava/lang/Object;
    flags: (0x1009) ACC_PUBLIC, ACC_STATIC, ACC_SYNTHETIC
    Code:
      stack=6, locals=6, args_size=6
         0: aload_0
         1: aload_1
         2: aload_2
         3: aload_3
         4: aload         4
         6: aload         5
         8: invokespecial #65                 // InterfaceMethod eventually:(Lorg/scalatest/concurrent/PatienceConfiguration$Interval;Lscala/Function0;Lorg/scalatest/concurrent/AbstractPatienceConfiguration$PatienceConfig;Lorg/scalatest/enablers/Retrying;Lorg/scalactic/source/Position;)Ljava/lang/Object;
        11: areturn
      LineNumberTable:
        line 381: 0
      LocalVariableTable:
        Start  Length  Slot  Name   Signature
            0      12     0 $this   Lorg/scalatest/concurrent/Eventually;
            0      12     1 interval   Lorg/scalatest/concurrent/PatienceConfiguration$Interval;
            0      12     2   fun   Lscala/Function0;
            0      12     3 config   Lorg/scalatest/concurrent/AbstractPatienceConfiguration$PatienceConfig;
            0      12     4 retrying   Lorg/scalatest/enablers/Retrying;
            0      12     5   pos   Lorg/scalactic/source/Position;
    MethodParameters:
      Name                           Flags
      $this                          final synthetic
      interval                       final
      fun                            final
      config                         final
      retrying                       final
      pos                            final

  public default <T extends java.lang.Object> T eventually(org.scalatest.concurrent.PatienceConfiguration$Interval, scala.Function0<T>, org.scalatest.concurrent.AbstractPatienceConfiguration$PatienceConfig, org.scalatest.enablers.Retrying<T>, org.scalactic.source.Position);
    descriptor: (Lorg/scalatest/concurrent/PatienceConfiguration$Interval;Lscala/Function0;Lorg/scalatest/concurrent/AbstractPatienceConfiguration$PatienceConfig;Lorg/scalatest/enablers/Retrying;Lorg/scalactic/source/Position;)Ljava/lang/Object;
    flags: (0x0001) ACC_PUBLIC
    Code:
      stack=5, locals=6, args_size=6
         0: aload         4
         2: aload_3
         3: invokevirtual #68                 // Method org/scalatest/concurrent/AbstractPatienceConfiguration$PatienceConfig.timeout:()Lorg/scalatest/time/Span;
         6: aload_1
         7: invokevirtual #45                 // Method org/scalatest/concurrent/PatienceConfiguration$Interval.value:()Lorg/scalatest/time/Span;
        10: aload         5
        12: aload_2
        13: invokeinterface #51,  5           // InterfaceMethod org/scalatest/enablers/Retrying.retry:(Lorg/scalatest/time/Span;Lorg/scalatest/time/Span;Lorg/scalactic/source/Position;Lscala/Function0;)Ljava/lang/Object;
        18: areturn
      LineNumberTable:
        line 382: 0
      LocalVariableTable:
        Start  Length  Slot  Name   Signature
            0      19     0  this   Lorg/scalatest/concurrent/Eventually;
            0      19     1 interval   Lorg/scalatest/concurrent/PatienceConfiguration$Interval;
            0      19     2   fun   Lscala/Function0;
            0      19     3 config   Lorg/scalatest/concurrent/AbstractPatienceConfiguration$PatienceConfig;
            0      19     4 retrying   Lorg/scalatest/enablers/Retrying;
            0      19     5   pos   Lorg/scalactic/source/Position;
    Signature: #66                          // <T:Ljava/lang/Object;>(Lorg/scalatest/concurrent/PatienceConfiguration$Interval;Lscala/Function0<TT;>;Lorg/scalatest/concurrent/AbstractPatienceConfiguration$PatienceConfig;Lorg/scalatest/enablers/Retrying<TT;>;Lorg/scalactic/source/Position;)TT;
    MethodParameters:
      Name                           Flags
      interval                       final
      fun                            final
      config                         final
      retrying                       final
      pos                            final

  public static java.lang.Object eventually$(org.scalatest.concurrent.Eventually, scala.Function0, org.scalatest.concurrent.AbstractPatienceConfiguration$PatienceConfig, org.scalatest.enablers.Retrying, org.scalactic.source.Position);
    descriptor: (Lorg/scalatest/concurrent/Eventually;Lscala/Function0;Lorg/scalatest/concurrent/AbstractPatienceConfiguration$PatienceConfig;Lorg/scalatest/enablers/Retrying;Lorg/scalactic/source/Position;)Ljava/lang/Object;
    flags: (0x1009) ACC_PUBLIC, ACC_STATIC, ACC_SYNTHETIC
    Code:
      stack=5, locals=5, args_size=5
         0: aload_0
         1: aload_1
         2: aload_2
         3: aload_3
         4: aload         4
         6: invokespecial #72                 // InterfaceMethod eventually:(Lscala/Function0;Lorg/scalatest/concurrent/AbstractPatienceConfiguration$PatienceConfig;Lorg/scalatest/enablers/Retrying;Lorg/scalactic/source/Position;)Ljava/lang/Object;
         9: areturn
      LineNumberTable:
        line 414: 0
      LocalVariableTable:
        Start  Length  Slot  Name   Signature
            0      10     0 $this   Lorg/scalatest/concurrent/Eventually;
            0      10     1   fun   Lscala/Function0;
            0      10     2 config   Lorg/scalatest/concurrent/AbstractPatienceConfiguration$PatienceConfig;
            0      10     3 retrying   Lorg/scalatest/enablers/Retrying;
            0      10     4   pos   Lorg/scalactic/source/Position;
    MethodParameters:
      Name                           Flags
      $this                          final synthetic
      fun                            final
      config                         final
      retrying                       final
      pos                            final

  public default <T extends java.lang.Object> T eventually(scala.Function0<T>, org.scalatest.concurrent.AbstractPatienceConfiguration$PatienceConfig, org.scalatest.enablers.Retrying<T>, org.scalactic.source.Position);
    descriptor: (Lscala/Function0;Lorg/scalatest/concurrent/AbstractPatienceConfiguration$PatienceConfig;Lorg/scalatest/enablers/Retrying;Lorg/scalactic/source/Position;)Ljava/lang/Object;
    flags: (0x0001) ACC_PUBLIC
    Code:
      stack=5, locals=5, args_size=5
         0: aload_3
         1: aload_2
         2: invokevirtual #68                 // Method org/scalatest/concurrent/AbstractPatienceConfiguration$PatienceConfig.timeout:()Lorg/scalatest/time/Span;
         5: aload_2
         6: invokevirtual #61                 // Method org/scalatest/concurrent/AbstractPatienceConfiguration$PatienceConfig.interval:()Lorg/scalatest/time/Span;
         9: aload         4
        11: aload_1
        12: invokeinterface #51,  5           // InterfaceMethod org/scalatest/enablers/Retrying.retry:(Lorg/scalatest/time/Span;Lorg/scalatest/time/Span;Lorg/scalactic/source/Position;Lscala/Function0;)Ljava/lang/Object;
        17: areturn
      LineNumberTable:
        line 415: 0
      LocalVariableTable:
        Start  Length  Slot  Name   Signature
            0      18     0  this   Lorg/scalatest/concurrent/Eventually;
            0      18     1   fun   Lscala/Function0;
            0      18     2 config   Lorg/scalatest/concurrent/AbstractPatienceConfiguration$PatienceConfig;
            0      18     3 retrying   Lorg/scalatest/enablers/Retrying;
            0      18     4   pos   Lorg/scalactic/source/Position;
    Signature: #73                          // <T:Ljava/lang/Object;>(Lscala/Function0<TT;>;Lorg/scalatest/concurrent/AbstractPatienceConfiguration$PatienceConfig;Lorg/scalatest/enablers/Retrying<TT;>;Lorg/scalactic/source/Position;)TT;
    MethodParameters:
      Name                           Flags
      fun                            final
      config                         final
      retrying                       final
      pos                            final

  public static void $init$(org.scalatest.concurrent.Eventually);
    descriptor: (Lorg/scalatest/concurrent/Eventually;)V
    flags: (0x0009) ACC_PUBLIC, ACC_STATIC
    Code:
      stack=0, locals=1, args_size=1
         0: return
      LineNumberTable:
        line 281: 0
      LocalVariableTable:
        Start  Length  Slot  Name   Signature
            0       1     0 $this   Lorg/scalatest/concurrent/Eventually;
    MethodParameters:
      Name                           Flags
      $this                          final synthetic
}
InnerClasses:
  public final #15= #12 of #14;           // PatienceConfig=class org/scalatest/concurrent/AbstractPatienceConfiguration$PatienceConfig of class org/scalatest/concurrent/AbstractPatienceConfiguration
  public static final #18= #17 of #6;     // Interval=class org/scalatest/concurrent/PatienceConfiguration$Interval of class org/scalatest/concurrent/PatienceConfiguration
  public static final #21= #20 of #6;     // Timeout=class org/scalatest/concurrent/PatienceConfiguration$Timeout of class org/scalatest/concurrent/PatienceConfiguration
SourceFile: "Eventually.scala"
RuntimeVisibleAnnotations:
  0: #8(#9=s#10)
    scala.reflect.ScalaSignature(
      bytes="\u0006\u0005\u0005EaaB\u0005\u000b!\u0003\r\t!\u0005\u0005\u00069\u0001!\t!\b\u0005\u0006C\u0001!\tA\t\u0005\u0006C\u0001!\tA\u0016\u0005\u0006C\u0001!\tA\u001b\u0005\u0006C\u0001!\ta^\u0004\b\u0003\u000bQ\u0001\u0012AA\u0004\r\u0019I!\u0002#\u0001\u0002\n!9\u0011QB\u0004\u0005\u0002\u0005=!AC#wK:$X/\u00197ms*\u00111\u0002D\u0001\u000bG>t7-\u001e:sK:$(BA\u0007\u000f\u0003%\u00198-\u00197bi\u0016\u001cHOC\u0001\u0010\u0003\ry\'oZ\u0002\u0001\'\r\u0001!\u0003\u0007\t\u0003\'Yi\u0011\u0001\u0006\u0006\u0002+\u0005)1oY1mC&\u0011q\u0003\u0006\u0002\u0007\u0003:L(+\u001a4\u0011\u0005eQR\"\u0001\u0006\n\u0005mQ!!\u0006)bi&,gnY3D_:4\u0017nZ;sCRLwN\\\u0001\u0007I%t\u0017\u000e\u001e\u0013\u0015\u0003y\u0001\"aE\u0010\n\u0005\u0001\"\"\u0001B+oSR\f!\"\u001a<f]R,\u0018\r\u001c7z+\t\u0019\u0003\u0006F\u0002%\u0011F#\"!J\"\u0015\u0007\u0019\n\u0014\b\u0005\u0002(Q1\u0001A!B\u0015\u0003\u0005\u0004Q#!\u0001+\u0012\u0005-r\u0003CA\n-\u0013\tiCCA\u0004O_RD\u0017N\\4\u0011\u0005My\u0013B\u0001\u0019\u0015\u0005\r\te.\u001f\u0005\u0006e\t\u0001\u001daM\u0001\te\u0016$(/_5oOB\u0019Ag\u000e\u0014\u000e\u0003UR!A\u000e\u0007\u0002\u0011\u0015t\u0017M\u00197feNL!\u0001O\u001b\u0003\u0011I+GO]=j]\u001eDQA\u000f\u0002A\u0004m\n1\u0001]8t!\ta\u0014)D\u0001>\u0015\tqt(\u0001\u0004t_V\u00148-\u001a\u0006\u0003\u0001:\t\u0011b]2bY\u0006\u001cG/[2\n\u0005\tk$\u0001\u0003)pg&$\u0018n\u001c8\t\r\u0011\u0013A\u00111\u0001F\u0003\r1WO\u001c\t\u0004\'\u00193\u0013BA$\u0015\u0005!a$-\u001f8b[\u0016t\u0004\"B%\u0003\u0001\u0004Q\u0015a\u0002;j[\u0016|W\u000f\u001e\t\u0003\u0017:s!!\u0007\'\n\u00055S\u0011!\u0006)bi&,gnY3D_:4\u0017nZ;sCRLwN\\\u0005\u0003\u001fB\u0013q\u0001V5nK>,HO\u0003\u0002N\u0015!)!K\u0001a\u0001\'\u0006A\u0011N\u001c;feZ\fG\u000e\u0005\u0002L)&\u0011Q\u000b\u0015\u0002\t\u0013:$XM\u001d<bYV\u0011qk\u0017\u000b\u00031&$\"!W4\u0015\ticFM\u001a\t\u0003Om#Q!K\u0002C\u0002)BQ!X\u0002A\u0004y\u000baaY8oM&<\u0007CA0a\u001b\u0005\u0001\u0011BA1c\u00059\u0001\u0016\r^5f]\u000e,7i\u001c8gS\u001eL!a\u0019\u0006\u0003;\u0005\u00137\u000f\u001e:bGR\u0004\u0016\r^5f]\u000e,7i\u001c8gS\u001e,(/\u0019;j_:DQAM\u0002A\u0004\u0015\u00042\u0001N\u001c[\u0011\u0015Q4\u0001q\u0001<\u0011\u0019!5\u0001\"a\u0001QB\u00191C\u0012.\t\u000b%\u001b\u0001\u0019\u0001&\u0016\u0005-|GC\u00017w)\tiG\u000f\u0006\u0003oaF\u001c\bCA\u0014p\t\u0015ICA1\u0001+\u0011\u0015iF\u0001q\u0001_\u0011\u0015\u0011D\u0001q\u0001s!\r!tG\u001c\u0005\u0006u\u0011\u0001\u001da\u000f\u0005\u0007\t\u0012!\t\u0019A;\u0011\u0007M1e\u000eC\u0003S\t\u0001\u00071+\u0006\u0002ywR\u0019\u00110!\u0001\u0015\tidXp \t\u0003Om$Q!K\u0003C\u0002)BQ!X\u0003A\u0004yCQAM\u0003A\u0004y\u00042\u0001N\u001c{\u0011\u0015QT\u0001q\u0001<\u0011\u001d!U\u0001\"a\u0001\u0003\u0007\u00012a\u0005${\u0003))e/\u001a8uk\u0006dG.\u001f\t\u00033\u001d\u0019Ba\u0002\n\u0002\fA\u0011\u0011\u0004A\u0001\u0007y%t\u0017\u000e\u001e \u0015\u0005\u0005\u001d\u0001"
    )
  ScalaInlineInfo: length = 0x31 (unknown attribute)
   01 00 00 09 00 4A 00 4B 01 00 1E 00 3F 00 00 1E
   00 1F 00 00 1E 00 37 00 00 1E 00 46 00 00 16 00
   3E 01 00 16 00 17 01 00 16 00 35 01 00 16 00 45
   01
  ScalaSig: length = 0x3 (unknown attribute)
   05 02 00
