Classfile /Users/mw/Projects/slang-braindump/.jar/jar8/assemble/slang-braindump/assemble/content/org/scalatest/concurrent/JavaFutures$$anon$1$$anon$2$$anonfun$$lessinit$greater$1.class
  Last modified May 29, 2022; size 2588 bytes
  SHA-256 checksum 5a194dd0101fa92eb91c7cfa74bb8d12ea01ac97dea19c0edc9fc82b3c4db468
  Compiled from "JavaFutures.scala"
public final class org.scalatest.concurrent.JavaFutures$$anon$1$$anon$2$$anonfun$$lessinit$greater$1 extends scala.runtime.AbstractFunction1<org.scalatest.exceptions.StackDepthException, scala.Some<java.lang.String>> implements java.io.Serializable
  minor version: 0
  major version: 52
  flags: (0x0031) ACC_PUBLIC, ACC_FINAL, ACC_SUPER
  this_class: #2                          // org/scalatest/concurrent/JavaFutures$$anon$1$$anon$2$$anonfun$$lessinit$greater$1
  super_class: #5                         // scala/runtime/AbstractFunction1
  interfaces: 1, fields: 2, methods: 3, attributes: 6
Constant pool:
   #1 = Utf8               org/scalatest/concurrent/JavaFutures$$anon$1$$anon$2$$anonfun$$lessinit$greater$1
   #2 = Class              #1             // org/scalatest/concurrent/JavaFutures$$anon$1$$anon$2$$anonfun$$lessinit$greater$1
   #3 = Utf8               Lscala/runtime/AbstractFunction1<Lorg/scalatest/exceptions/StackDepthException;Lscala/Some<Ljava/lang/String;>;>;Ljava/io/Serializable;
   #4 = Utf8               scala/runtime/AbstractFunction1
   #5 = Class              #4             // scala/runtime/AbstractFunction1
   #6 = Utf8               java/io/Serializable
   #7 = Class              #6             // java/io/Serializable
   #8 = Utf8               JavaFutures.scala
   #9 = Utf8               org/scalatest/concurrent/JavaFutures$$anon$1$$anon$2
  #10 = Class              #9             // org/scalatest/concurrent/JavaFutures$$anon$1$$anon$2
  #11 = Utf8               <init>
  #12 = Utf8               (Lorg/scalatest/concurrent/JavaFutures$$anon$1;Lorg/scalatest/concurrent/AbstractPatienceConfiguration$PatienceConfig;Lorg/scalactic/source/Position;)V
  #13 = NameAndType        #11:#12        // "<init>":(Lorg/scalatest/concurrent/JavaFutures$$anon$1;Lorg/scalatest/concurrent/AbstractPatienceConfiguration$PatienceConfig;Lorg/scalactic/source/Position;)V
  #14 = Utf8               org/scalatest/concurrent/AbstractPatienceConfiguration$PatienceConfig
  #15 = Class              #14            // org/scalatest/concurrent/AbstractPatienceConfiguration$PatienceConfig
  #16 = Utf8               org/scalatest/concurrent/AbstractPatienceConfiguration
  #17 = Class              #16            // org/scalatest/concurrent/AbstractPatienceConfiguration
  #18 = Utf8               PatienceConfig
  #19 = Utf8               org/scalatest/concurrent/JavaFutures$$anon$1
  #20 = Class              #19            // org/scalatest/concurrent/JavaFutures$$anon$1
  #21 = Utf8               serialVersionUID
  #22 = Utf8               J
  #23 = Long               0l
  #25 = Utf8               config$1
  #26 = Utf8               Lorg/scalatest/concurrent/AbstractPatienceConfiguration$PatienceConfig;
  #27 = Utf8               apply
  #28 = Utf8               (Lorg/scalatest/exceptions/StackDepthException;)Lscala/Some;
  #29 = Utf8               (Lorg/scalatest/exceptions/StackDepthException;)Lscala/Some<Ljava/lang/String;>;
  #30 = Utf8               x$2
  #31 = Utf8               scala/Some
  #32 = Class              #31            // scala/Some
  #33 = Utf8               org/scalatest/Resources$
  #34 = Class              #33            // org/scalatest/Resources$
  #35 = Utf8               MODULE$
  #36 = Utf8               Lorg/scalatest/Resources$;
  #37 = NameAndType        #35:#36        // MODULE$:Lorg/scalatest/Resources$;
  #38 = Fieldref           #34.#37        // org/scalatest/Resources$.MODULE$:Lorg/scalatest/Resources$;
  #39 = Utf8               scala/Tuple2
  #40 = Class              #39            // scala/Tuple2
  #41 = Utf8               scala/runtime/BoxesRunTime
  #42 = Class              #41            // scala/runtime/BoxesRunTime
  #43 = Utf8               boxToInteger
  #44 = Utf8               (I)Ljava/lang/Integer;
  #45 = NameAndType        #43:#44        // boxToInteger:(I)Ljava/lang/Integer;
  #46 = Methodref          #42.#45        // scala/runtime/BoxesRunTime.boxToInteger:(I)Ljava/lang/Integer;
  #47 = NameAndType        #25:#26        // config$1:Lorg/scalatest/concurrent/AbstractPatienceConfiguration$PatienceConfig;
  #48 = Fieldref           #2.#47         // org/scalatest/concurrent/JavaFutures$$anon$1$$anon$2$$anonfun$$lessinit$greater$1.config$1:Lorg/scalatest/concurrent/AbstractPatienceConfiguration$PatienceConfig;
  #49 = Utf8               interval
  #50 = Utf8               ()Lorg/scalatest/time/Span;
  #51 = NameAndType        #49:#50        // interval:()Lorg/scalatest/time/Span;
  #52 = Methodref          #15.#51        // org/scalatest/concurrent/AbstractPatienceConfiguration$PatienceConfig.interval:()Lorg/scalatest/time/Span;
  #53 = Utf8               org/scalatest/time/Span
  #54 = Class              #53            // org/scalatest/time/Span
  #55 = Utf8               prettyString
  #56 = Utf8               ()Ljava/lang/String;
  #57 = NameAndType        #55:#56        // prettyString:()Ljava/lang/String;
  #58 = Methodref          #54.#57        // org/scalatest/time/Span.prettyString:()Ljava/lang/String;
  #59 = Utf8               (Ljava/lang/Object;Ljava/lang/Object;)V
  #60 = NameAndType        #11:#59        // "<init>":(Ljava/lang/Object;Ljava/lang/Object;)V
  #61 = Methodref          #40.#60        // scala/Tuple2."<init>":(Ljava/lang/Object;Ljava/lang/Object;)V
  #62 = Utf8               wasNeverReady
  #63 = Utf8               (Ljava/lang/Object;)Ljava/lang/String;
  #64 = NameAndType        #62:#63        // wasNeverReady:(Ljava/lang/Object;)Ljava/lang/String;
  #65 = Methodref          #34.#64        // org/scalatest/Resources$.wasNeverReady:(Ljava/lang/Object;)Ljava/lang/String;
  #66 = Utf8               (Ljava/lang/Object;)V
  #67 = NameAndType        #11:#66        // "<init>":(Ljava/lang/Object;)V
  #68 = Methodref          #32.#67        // scala/Some."<init>":(Ljava/lang/Object;)V
  #69 = Utf8               this
  #70 = Utf8               Lorg/scalatest/concurrent/JavaFutures$$anon$1$$anon$2$$anonfun$$lessinit$greater$1;
  #71 = Utf8               Lorg/scalatest/exceptions/StackDepthException;
  #72 = Utf8               (Ljava/lang/Object;)Ljava/lang/Object;
  #73 = Utf8               v1
  #74 = Utf8               org/scalatest/exceptions/StackDepthException
  #75 = Class              #74            // org/scalatest/exceptions/StackDepthException
  #76 = NameAndType        #27:#28        // apply:(Lorg/scalatest/exceptions/StackDepthException;)Lscala/Some;
  #77 = Methodref          #2.#76         // org/scalatest/concurrent/JavaFutures$$anon$1$$anon$2$$anonfun$$lessinit$greater$1.apply:(Lorg/scalatest/exceptions/StackDepthException;)Lscala/Some;
  #78 = Utf8               Ljava/lang/Object;
  #79 = Utf8               (Lorg/scalatest/concurrent/JavaFutures$$anon$1;Lorg/scalatest/concurrent/AbstractPatienceConfiguration$PatienceConfig;)V
  #80 = Utf8               $outer
  #81 = Utf8               ()V
  #82 = NameAndType        #11:#81        // "<init>":()V
  #83 = Methodref          #5.#82         // scala/runtime/AbstractFunction1."<init>":()V
  #84 = Utf8               Lorg/scalatest/concurrent/JavaFutures$$anon$1;
  #85 = Utf8               ConstantValue
  #86 = Utf8               Code
  #87 = Utf8               LineNumberTable
  #88 = Utf8               LocalVariableTable
  #89 = Utf8               Signature
  #90 = Utf8               MethodParameters
  #91 = Utf8               InnerClasses
  #92 = Utf8               EnclosingMethod
  #93 = Utf8               SourceFile
  #94 = Utf8               ScalaInlineInfo
  #95 = Utf8               Scala
{
  private static final long serialVersionUID;
    descriptor: J
    flags: (0x001a) ACC_PRIVATE, ACC_STATIC, ACC_FINAL
    ConstantValue: long 0l

  private final org.scalatest.concurrent.AbstractPatienceConfiguration$PatienceConfig config$1;
    descriptor: Lorg/scalatest/concurrent/AbstractPatienceConfiguration$PatienceConfig;
    flags: (0x0012) ACC_PRIVATE, ACC_FINAL

  public final scala.Some<java.lang.String> apply(org.scalatest.exceptions.StackDepthException);
    descriptor: (Lorg/scalatest/exceptions/StackDepthException;)Lscala/Some;
    flags: (0x0011) ACC_PUBLIC, ACC_FINAL
    Code:
      stack=7, locals=2, args_size=2
         0: new           #32                 // class scala/Some
         3: dup
         4: getstatic     #38                 // Field org/scalatest/Resources$.MODULE$:Lorg/scalatest/Resources$;
         7: new           #40                 // class scala/Tuple2
        10: dup
        11: iconst_1
        12: invokestatic  #46                 // Method scala/runtime/BoxesRunTime.boxToInteger:(I)Ljava/lang/Integer;
        15: aload_0
        16: getfield      #48                 // Field config$1:Lorg/scalatest/concurrent/AbstractPatienceConfiguration$PatienceConfig;
        19: invokevirtual #52                 // Method org/scalatest/concurrent/AbstractPatienceConfiguration$PatienceConfig.interval:()Lorg/scalatest/time/Span;
        22: invokevirtual #58                 // Method org/scalatest/time/Span.prettyString:()Ljava/lang/String;
        25: invokespecial #61                 // Method scala/Tuple2."<init>":(Ljava/lang/Object;Ljava/lang/Object;)V
        28: invokevirtual #65                 // Method org/scalatest/Resources$.wasNeverReady:(Ljava/lang/Object;)Ljava/lang/String;
        31: invokespecial #68                 // Method scala/Some."<init>":(Ljava/lang/Object;)V
        34: areturn
      LineNumberTable:
        line 100: 0
      LocalVariableTable:
        Start  Length  Slot  Name   Signature
            0      35     0  this   Lorg/scalatest/concurrent/JavaFutures$$anon$1$$anon$2$$anonfun$$lessinit$greater$1;
            0      35     1   x$2   Lorg/scalatest/exceptions/StackDepthException;
    Signature: #29                          // (Lorg/scalatest/exceptions/StackDepthException;)Lscala/Some<Ljava/lang/String;>;
    MethodParameters:
      Name                           Flags
      x$2                            final

  public final java.lang.Object apply(java.lang.Object);
    descriptor: (Ljava/lang/Object;)Ljava/lang/Object;
    flags: (0x1051) ACC_PUBLIC, ACC_FINAL, ACC_BRIDGE, ACC_SYNTHETIC
    Code:
      stack=2, locals=2, args_size=2
         0: aload_0
         1: aload_1
         2: checkcast     #75                 // class org/scalatest/exceptions/StackDepthException
         5: invokevirtual #77                 // Method apply:(Lorg/scalatest/exceptions/StackDepthException;)Lscala/Some;
         8: areturn
      LineNumberTable:
        line 100: 0
      LocalVariableTable:
        Start  Length  Slot  Name   Signature
            0       9     0  this   Lorg/scalatest/concurrent/JavaFutures$$anon$1$$anon$2$$anonfun$$lessinit$greater$1;
            0       9     1    v1   Ljava/lang/Object;
    MethodParameters:
      Name                           Flags
      v1                             final

  public org.scalatest.concurrent.JavaFutures$$anon$1$$anon$2$$anonfun$$lessinit$greater$1(org.scalatest.concurrent.JavaFutures$$anon$1, org.scalatest.concurrent.AbstractPatienceConfiguration$PatienceConfig);
    descriptor: (Lorg/scalatest/concurrent/JavaFutures$$anon$1;Lorg/scalatest/concurrent/AbstractPatienceConfiguration$PatienceConfig;)V
    flags: (0x0001) ACC_PUBLIC
    Code:
      stack=2, locals=3, args_size=3
         0: aload_0
         1: aload_2
         2: putfield      #48                 // Field config$1:Lorg/scalatest/concurrent/AbstractPatienceConfiguration$PatienceConfig;
         5: aload_0
         6: invokespecial #83                 // Method scala/runtime/AbstractFunction1."<init>":()V
         9: return
      LineNumberTable:
        line 81: 0
        line 100: 5
      LocalVariableTable:
        Start  Length  Slot  Name   Signature
            0      10     0  this   Lorg/scalatest/concurrent/JavaFutures$$anon$1$$anon$2$$anonfun$$lessinit$greater$1;
            0      10     1 $outer   Lorg/scalatest/concurrent/JavaFutures$$anon$1;
            0      10     2 config$1   Lorg/scalatest/concurrent/AbstractPatienceConfiguration$PatienceConfig;
    MethodParameters:
      Name                           Flags
      $outer                         final synthetic
      config$1                       final
}
InnerClasses:
  public final #18= #15 of #17;           // PatienceConfig=class org/scalatest/concurrent/AbstractPatienceConfiguration$PatienceConfig of class org/scalatest/concurrent/AbstractPatienceConfiguration
  public final #20;                       // class org/scalatest/concurrent/JavaFutures$$anon$1
  public final #10;                       // class org/scalatest/concurrent/JavaFutures$$anon$1$$anon$2
  public final #2;                        // class org/scalatest/concurrent/JavaFutures$$anon$1$$anon$2$$anonfun$$lessinit$greater$1
EnclosingMethod: #10.#13                // org.scalatest.concurrent.JavaFutures$$anon$1$$anon$2.<init>
Signature: #3                           // Lscala/runtime/AbstractFunction1<Lorg/scalatest/exceptions/StackDepthException;Lscala/Some<Ljava/lang/String;>;>;Ljava/io/Serializable;
SourceFile: "JavaFutures.scala"
  ScalaInlineInfo: length = 0x13 (unknown attribute)
   01 01 00 03 00 0B 00 4F 01 00 1B 00 48 01 00 1B
   00 1C 01
  Scala: length = 0x0 (unknown attribute)

