Classfile /Users/mw/Projects/slang-braindump/.jar/jar8/assemble/slang-braindump/assemble/content/org/scalatest/concurrent/ScaledTimeSpans.class
  Last modified May 29, 2022; size 1618 bytes
  SHA-256 checksum b9a509d0f333c18131b130ff248d2f1c30fce4fe7348dde463ff481cc1403e38
  Compiled from "ScaledTimeSpans.scala"
public interface org.scalatest.concurrent.ScaledTimeSpans
  minor version: 0
  major version: 52
  flags: (0x0601) ACC_PUBLIC, ACC_INTERFACE, ACC_ABSTRACT
  this_class: #2                          // org/scalatest/concurrent/ScaledTimeSpans
  super_class: #4                         // java/lang/Object
  interfaces: 0, fields: 0, methods: 5, attributes: 4
Constant pool:
   #1 = Utf8               org/scalatest/concurrent/ScaledTimeSpans
   #2 = Class              #1             // org/scalatest/concurrent/ScaledTimeSpans
   #3 = Utf8               java/lang/Object
   #4 = Class              #3             // java/lang/Object
   #5 = Utf8               ScaledTimeSpans.scala
   #6 = Utf8               Lscala/reflect/ScalaSignature;
   #7 = Utf8               bytes
   #8 = Utf8               \u0006\u0005\u001d2q\u0001B\u0003\u0011\u0002\u0007\u0005A\u0002C\u0003\u0014\u0001\u0011\u0005A\u0003C\u0003\u0019\u0001\u0011\u0015\u0011\u0004C\u0003#\u0001\u0011\u00051EA\bTG\u0006dW\r\u001a+j[\u0016\u001c\u0006/\u00198t\u0015\t1q!\u0001\u0006d_:\u001cWO\u001d:f]RT!\u0001C\u0005\u0002\u0013M\u001c\u0017\r\\1uKN$(\"\u0001\u0006\u0002\u0007=\u0014xm\u0001\u0001\u0014\u0005\u0001i\u0001C\u0001\b\u0012\u001b\u0005y!\"\u0001\t\u0002\u000bM\u001c\u0017\r\\1\n\u0005Iy!AB!osJ+g-\u0001\u0004%S:LG\u000f\n\u000b\u0002+A\u0011aBF\u0005\u0003/=\u0011A!\u00168ji\u000611oY1mK\u0012$\"A\u0007\u0011\u0011\u0005mqR\"\u0001\u000f\u000b\u0005u9\u0011\u0001\u0002;j[\u0016L!a\b\u000f\u0003\tM\u0003\u0018M\u001c\u0005\u0006C\t\u0001\rAG\u0001\u0005gB\fg.A\bta\u0006t7kY1mK\u001a\u000b7\r^8s+\u0005!\u0003C\u0001\b&\u0013\t1sB\u0001\u0004E_V\u0014G.\u001a
   #9 = Utf8               scaled$
  #10 = Utf8               (Lorg/scalatest/concurrent/ScaledTimeSpans;Lorg/scalatest/time/Span;)Lorg/scalatest/time/Span;
  #11 = Utf8               $this
  #12 = Utf8               span
  #13 = Utf8               scaled
  #14 = Utf8               (Lorg/scalatest/time/Span;)Lorg/scalatest/time/Span;
  #15 = NameAndType        #13:#14        // scaled:(Lorg/scalatest/time/Span;)Lorg/scalatest/time/Span;
  #16 = InterfaceMethodref #2.#15         // org/scalatest/concurrent/ScaledTimeSpans.scaled:(Lorg/scalatest/time/Span;)Lorg/scalatest/time/Span;
  #17 = Utf8               Lorg/scalatest/concurrent/ScaledTimeSpans;
  #18 = Utf8               Lorg/scalatest/time/Span;
  #19 = Utf8               spanScaleFactor
  #20 = Utf8               ()D
  #21 = NameAndType        #19:#20        // spanScaleFactor:()D
  #22 = InterfaceMethodref #2.#21         // org/scalatest/concurrent/ScaledTimeSpans.spanScaleFactor:()D
  #23 = Utf8               org/scalatest/time/Span
  #24 = Class              #23            // org/scalatest/time/Span
  #25 = Utf8               scaledBy
  #26 = Utf8               (D)Lorg/scalatest/time/Span;
  #27 = NameAndType        #25:#26        // scaledBy:(D)Lorg/scalatest/time/Span;
  #28 = Methodref          #24.#27        // org/scalatest/time/Span.scaledBy:(D)Lorg/scalatest/time/Span;
  #29 = Utf8               this
  #30 = Utf8               spanScaleFactor$
  #31 = Utf8               (Lorg/scalatest/concurrent/ScaledTimeSpans;)D
  #32 = Utf8               org/scalatest/tools/Runner$
  #33 = Class              #32            // org/scalatest/tools/Runner$
  #34 = Utf8               MODULE$
  #35 = Utf8               Lorg/scalatest/tools/Runner$;
  #36 = NameAndType        #34:#35        // MODULE$:Lorg/scalatest/tools/Runner$;
  #37 = Fieldref           #33.#36        // org/scalatest/tools/Runner$.MODULE$:Lorg/scalatest/tools/Runner$;
  #38 = Methodref          #33.#21        // org/scalatest/tools/Runner$.spanScaleFactor:()D
  #39 = Utf8               $init$
  #40 = Utf8               (Lorg/scalatest/concurrent/ScaledTimeSpans;)V
  #41 = Utf8               Code
  #42 = Utf8               LineNumberTable
  #43 = Utf8               LocalVariableTable
  #44 = Utf8               MethodParameters
  #45 = Utf8               SourceFile
  #46 = Utf8               RuntimeVisibleAnnotations
  #47 = Utf8               ScalaInlineInfo
  #48 = Utf8               ScalaSig
{
  public static org.scalatest.time.Span scaled$(org.scalatest.concurrent.ScaledTimeSpans, org.scalatest.time.Span);
    descriptor: (Lorg/scalatest/concurrent/ScaledTimeSpans;Lorg/scalatest/time/Span;)Lorg/scalatest/time/Span;
    flags: (0x1009) ACC_PUBLIC, ACC_STATIC, ACC_SYNTHETIC
    Code:
      stack=2, locals=2, args_size=2
         0: aload_0
         1: aload_1
         2: invokespecial #16                 // InterfaceMethod scaled:(Lorg/scalatest/time/Span;)Lorg/scalatest/time/Span;
         5: areturn
      LineNumberTable:
        line 185: 0
      LocalVariableTable:
        Start  Length  Slot  Name   Signature
            0       6     0 $this   Lorg/scalatest/concurrent/ScaledTimeSpans;
            0       6     1  span   Lorg/scalatest/time/Span;
    MethodParameters:
      Name                           Flags
      $this                          final synthetic
      span                           final

  public default org.scalatest.time.Span scaled(org.scalatest.time.Span);
    descriptor: (Lorg/scalatest/time/Span;)Lorg/scalatest/time/Span;
    flags: (0x0001) ACC_PUBLIC
    Code:
      stack=3, locals=2, args_size=2
         0: aload_1
         1: aload_0
         2: invokeinterface #22,  1           // InterfaceMethod spanScaleFactor:()D
         7: invokevirtual #28                 // Method org/scalatest/time/Span.scaledBy:(D)Lorg/scalatest/time/Span;
        10: areturn
      LineNumberTable:
        line 185: 0
      LocalVariableTable:
        Start  Length  Slot  Name   Signature
            0      11     0  this   Lorg/scalatest/concurrent/ScaledTimeSpans;
            0      11     1  span   Lorg/scalatest/time/Span;
    MethodParameters:
      Name                           Flags
      span                           final

  public static double spanScaleFactor$(org.scalatest.concurrent.ScaledTimeSpans);
    descriptor: (Lorg/scalatest/concurrent/ScaledTimeSpans;)D
    flags: (0x1009) ACC_PUBLIC, ACC_STATIC, ACC_SYNTHETIC
    Code:
      stack=2, locals=1, args_size=1
         0: aload_0
         1: invokespecial #22                 // InterfaceMethod spanScaleFactor:()D
         4: dreturn
      LineNumberTable:
        line 196: 0
      LocalVariableTable:
        Start  Length  Slot  Name   Signature
            0       5     0 $this   Lorg/scalatest/concurrent/ScaledTimeSpans;
    MethodParameters:
      Name                           Flags
      $this                          final synthetic

  public default double spanScaleFactor();
    descriptor: ()D
    flags: (0x0001) ACC_PUBLIC
    Code:
      stack=2, locals=1, args_size=1
         0: getstatic     #37                 // Field org/scalatest/tools/Runner$.MODULE$:Lorg/scalatest/tools/Runner$;
         3: invokevirtual #38                 // Method org/scalatest/tools/Runner$.spanScaleFactor:()D
         6: dreturn
      LineNumberTable:
        line 198: 0
      LocalVariableTable:
        Start  Length  Slot  Name   Signature
            0       7     0  this   Lorg/scalatest/concurrent/ScaledTimeSpans;

  public static void $init$(org.scalatest.concurrent.ScaledTimeSpans);
    descriptor: (Lorg/scalatest/concurrent/ScaledTimeSpans;)V
    flags: (0x0009) ACC_PUBLIC, ACC_STATIC
    Code:
      stack=0, locals=1, args_size=1
         0: return
      LineNumberTable:
        line 161: 0
      LocalVariableTable:
        Start  Length  Slot  Name   Signature
            0       1     0 $this   Lorg/scalatest/concurrent/ScaledTimeSpans;
    MethodParameters:
      Name                           Flags
      $this                          final synthetic
}
SourceFile: "ScaledTimeSpans.scala"
RuntimeVisibleAnnotations:
  0: #6(#7=s#8)
    scala.reflect.ScalaSignature(
      bytes="\u0006\u0005\u001d2q\u0001B\u0003\u0011\u0002\u0007\u0005A\u0002C\u0003\u0014\u0001\u0011\u0005A\u0003C\u0003\u0019\u0001\u0011\u0015\u0011\u0004C\u0003#\u0001\u0011\u00051EA\bTG\u0006dW\r\u001a+j[\u0016\u001c\u0006/\u00198t\u0015\t1q!\u0001\u0006d_:\u001cWO\u001d:f]RT!\u0001C\u0005\u0002\u0013M\u001c\u0017\r\\1uKN$(\"\u0001\u0006\u0002\u0007=\u0014xm\u0001\u0001\u0014\u0005\u0001i\u0001C\u0001\b\u0012\u001b\u0005y!\"\u0001\t\u0002\u000bM\u001c\u0017\r\\1\n\u0005Iy!AB!osJ+g-\u0001\u0004%S:LG\u000f\n\u000b\u0002+A\u0011aBF\u0005\u0003/=\u0011A!\u00168ji\u000611oY1mK\u0012$\"A\u0007\u0011\u0011\u0005mqR\"\u0001\u000f\u000b\u0005u9\u0011\u0001\u0002;j[\u0016L!a\b\u000f\u0003\tM\u0003\u0018M\u001c\u0005\u0006C\t\u0001\rAG\u0001\u0005gB\fg.A\bta\u0006t7kY1mK\u001a\u000b7\r^8s+\u0005!\u0003C\u0001\b&\u0013\t1sB\u0001\u0004E_V\u0014G.\u001a"
    )
  ScalaInlineInfo: length = 0x1D (unknown attribute)
   01 00 00 05 00 27 00 28 01 00 0D 00 0E 01 00 09
   00 0A 01 00 13 00 14 00 00 1E 00 1F 01
  ScalaSig: length = 0x3 (unknown attribute)
   05 02 00
