Classfile /Users/mw/Projects/slang-braindump/.jar/jar8/assemble/slang-braindump/assemble/content/org/scalatest/concurrent/Signaler$$anon$1.class
  Last modified May 29, 2022; size 915 bytes
  SHA-256 checksum da403ec34d5d086977c4468ef4da9f5d21ac7342db2fcfbd088413db2c698c87
  Compiled from "Signaler.scala"
public final class org.scalatest.concurrent.Signaler$$anon$1 implements org.scalatest.concurrent.Signaler
  minor version: 0
  major version: 52
  flags: (0x0031) ACC_PUBLIC, ACC_FINAL, ACC_SUPER
  this_class: #2                          // org/scalatest/concurrent/Signaler$$anon$1
  super_class: #4                         // java/lang/Object
  interfaces: 1, fields: 1, methods: 2, attributes: 5
Constant pool:
   #1 = Utf8               org/scalatest/concurrent/Signaler$$anon$1
   #2 = Class              #1             // org/scalatest/concurrent/Signaler$$anon$1
   #3 = Utf8               java/lang/Object
   #4 = Class              #3             // java/lang/Object
   #5 = Utf8               org/scalatest/concurrent/Signaler
   #6 = Class              #5             // org/scalatest/concurrent/Signaler
   #7 = Utf8               Signaler.scala
   #8 = Utf8               org/scalatest/concurrent/Signaler$
   #9 = Class              #8             // org/scalatest/concurrent/Signaler$
  #10 = Utf8               apply
  #11 = Utf8               (Lscala/Function1;)Lorg/scalatest/concurrent/Signaler;
  #12 = NameAndType        #10:#11        // apply:(Lscala/Function1;)Lorg/scalatest/concurrent/Signaler;
  #13 = Utf8               fun$1
  #14 = Utf8               Lscala/Function1;
  #15 = Utf8               (Ljava/lang/Thread;)V
  #16 = Utf8               testThread
  #17 = NameAndType        #13:#14        // fun$1:Lscala/Function1;
  #18 = Fieldref           #2.#17         // org/scalatest/concurrent/Signaler$$anon$1.fun$1:Lscala/Function1;
  #19 = Utf8               scala/Function1
  #20 = Class              #19            // scala/Function1
  #21 = Utf8               (Ljava/lang/Object;)Ljava/lang/Object;
  #22 = NameAndType        #10:#21        // apply:(Ljava/lang/Object;)Ljava/lang/Object;
  #23 = InterfaceMethodref #20.#22        // scala/Function1.apply:(Ljava/lang/Object;)Ljava/lang/Object;
  #24 = Utf8               this
  #25 = Utf8               Lorg/scalatest/concurrent/Signaler$$anon$1;
  #26 = Utf8               Ljava/lang/Thread;
  #27 = Utf8               <init>
  #28 = Utf8               (Lscala/Function1;)V
  #29 = Utf8               ()V
  #30 = NameAndType        #27:#29        // "<init>":()V
  #31 = Methodref          #4.#30         // java/lang/Object."<init>":()V
  #32 = Utf8               Code
  #33 = Utf8               LineNumberTable
  #34 = Utf8               LocalVariableTable
  #35 = Utf8               MethodParameters
  #36 = Utf8               InnerClasses
  #37 = Utf8               EnclosingMethod
  #38 = Utf8               SourceFile
  #39 = Utf8               ScalaInlineInfo
  #40 = Utf8               Scala
{
  private final scala.Function1 fun$1;
    descriptor: Lscala/Function1;
    flags: (0x0012) ACC_PRIVATE, ACC_FINAL

  public void apply(java.lang.Thread);
    descriptor: (Ljava/lang/Thread;)V
    flags: (0x0001) ACC_PUBLIC
    Code:
      stack=2, locals=2, args_size=2
         0: aload_0
         1: getfield      #18                 // Field fun$1:Lscala/Function1;
         4: aload_1
         5: invokeinterface #23,  2           // InterfaceMethod scala/Function1.apply:(Ljava/lang/Object;)Ljava/lang/Object;
        10: pop
        11: return
      LineNumberTable:
        line 58: 0
      LocalVariableTable:
        Start  Length  Slot  Name   Signature
            0      12     0  this   Lorg/scalatest/concurrent/Signaler$$anon$1;
            0      12     1 testThread   Ljava/lang/Thread;
    MethodParameters:
      Name                           Flags
      testThread                     final

  public org.scalatest.concurrent.Signaler$$anon$1(scala.Function1);
    descriptor: (Lscala/Function1;)V
    flags: (0x0001) ACC_PUBLIC
    Code:
      stack=2, locals=2, args_size=2
         0: aload_0
         1: aload_1
         2: putfield      #18                 // Field fun$1:Lscala/Function1;
         5: aload_0
         6: invokespecial #31                 // Method java/lang/Object."<init>":()V
         9: return
      LineNumberTable:
        line 56: 0
        line 57: 5
      LocalVariableTable:
        Start  Length  Slot  Name   Signature
            0      10     0  this   Lorg/scalatest/concurrent/Signaler$$anon$1;
            0      10     1 fun$1   Lscala/Function1;
    MethodParameters:
      Name                           Flags
      fun$1                          final
}
InnerClasses:
  public final #2;                        // class org/scalatest/concurrent/Signaler$$anon$1
EnclosingMethod: #9.#12                 // org.scalatest.concurrent.Signaler$.apply
SourceFile: "Signaler.scala"
  ScalaInlineInfo: length = 0xE (unknown attribute)
   01 01 00 02 00 1B 00 1C 01 00 0A 00 0F 01
  Scala: length = 0x0 (unknown attribute)

