Classfile /Users/mw/Projects/slang-braindump/.jar/jar8/assemble/slang-braindump/assemble/content/org/scalatest/concurrent/SocketSignaler.class
  Last modified May 29, 2022; size 1214 bytes
  SHA-256 checksum ff32ea500dcae3970fd8a602b7d55e566a53b2344b2a5f7ac3480c125c119fb5
  Compiled from "SocketSignaler.scala"
public class org.scalatest.concurrent.SocketSignaler implements org.scalatest.concurrent.Signaler
  minor version: 0
  major version: 52
  flags: (0x0021) ACC_PUBLIC, ACC_SUPER
  this_class: #2                          // org/scalatest/concurrent/SocketSignaler
  super_class: #4                         // java/lang/Object
  interfaces: 1, fields: 1, methods: 2, attributes: 4
Constant pool:
   #1 = Utf8               org/scalatest/concurrent/SocketSignaler
   #2 = Class              #1             // org/scalatest/concurrent/SocketSignaler
   #3 = Utf8               java/lang/Object
   #4 = Class              #3             // java/lang/Object
   #5 = Utf8               org/scalatest/concurrent/Signaler
   #6 = Class              #5             // org/scalatest/concurrent/Signaler
   #7 = Utf8               SocketSignaler.scala
   #8 = Utf8               Lscala/reflect/ScalaSignature;
   #9 = Utf8               bytes
  #10 = Utf8               \u0006\u0005m2A\u0001C\u0005\u0001!!A1\u0004\u0001B\u0001B\u0003%A\u0004C\u0003%\u0001\u0011\u0005Q\u0005C\u0003)\u0001\u0011\u0005\u0011fB\u00036\u0013!\u0005aGB\u0003\t\u0013!\u0005q\u0007C\u0003%\u000b\u0011\u0005\u0001\bC\u0003)\u000b\u0011\u0005\u0011H\u0001\bT_\u000e\\W\r^*jO:\fG.\u001a:\u000b\u0005)Y\u0011AC2p]\u000e,(O]3oi*\u0011A\"D\u0001\ng\u000e\fG.\u0019;fgRT\u0011AD\u0001\u0004_J<7\u0001A\n\u0004\u0001E9\u0002C\u0001\n\u0016\u001b\u0005\u0019\"\"\u0001\u000b\u0002\u000bM\u001c\u0017\r\\1\n\u0005Y\u0019\"AB!osJ+g\r\u0005\u0002\u001935\t\u0011\"\u0003\u0002\u001b\u0013\tA1+[4oC2,\'/\u0001\u0004t_\u000e\\W\r\u001e\t\u0003;\tj\u0011A\b\u0006\u0003?\u0001\n1A\\3u\u0015\u0005\t\u0013\u0001\u00026bm\u0006L!a\t\u0010\u0003\rM{7m[3u\u0003\u0019a\u0014N\\5u}Q\u0011ae\n\t\u00031\u0001AQa\u0007\u0002A\u0002q\tQ!\u00199qYf$\"AK\u0017\u0011\u0005IY\u0013B\u0001\u0017\u0014\u0005\u0011)f.\u001b;\t\u000b9\u001a\u0001\u0019A\u0018\u0002\u0015Q,7\u000f\u001e+ie\u0016\fG\r\u0005\u00021g5\t\u0011G\u0003\u00023A\u0005!A.\u00198h\u0013\t!\u0014G\u0001\u0004UQJ,\u0017\rZ\u0001\u000f\'>\u001c7.\u001a;TS\u001et\u0017\r\\3s!\tARa\u0005\u0002\u0006#Q\ta\u0007\u0006\u0002\'u!)1d\u0002a\u00019\u0001
  #11 = Utf8               socket
  #12 = Utf8               Ljava/net/Socket;
  #13 = Utf8               apply
  #14 = Utf8               (Ljava/lang/Thread;)V
  #15 = Utf8               testThread
  #16 = NameAndType        #11:#12        // socket:Ljava/net/Socket;
  #17 = Fieldref           #2.#16         // org/scalatest/concurrent/SocketSignaler.socket:Ljava/net/Socket;
  #18 = Utf8               java/net/Socket
  #19 = Class              #18            // java/net/Socket
  #20 = Utf8               close
  #21 = Utf8               ()V
  #22 = NameAndType        #20:#21        // close:()V
  #23 = Methodref          #19.#22        // java/net/Socket.close:()V
  #24 = Utf8               this
  #25 = Utf8               Lorg/scalatest/concurrent/SocketSignaler;
  #26 = Utf8               Ljava/lang/Thread;
  #27 = Utf8               <init>
  #28 = Utf8               (Ljava/net/Socket;)V
  #29 = NameAndType        #27:#21        // "<init>":()V
  #30 = Methodref          #4.#29         // java/lang/Object."<init>":()V
  #31 = Utf8               Code
  #32 = Utf8               LineNumberTable
  #33 = Utf8               LocalVariableTable
  #34 = Utf8               MethodParameters
  #35 = Utf8               SourceFile
  #36 = Utf8               RuntimeVisibleAnnotations
  #37 = Utf8               ScalaInlineInfo
  #38 = Utf8               ScalaSig
{
  private final java.net.Socket socket;
    descriptor: Ljava/net/Socket;
    flags: (0x0012) ACC_PRIVATE, ACC_FINAL

  public void apply(java.lang.Thread);
    descriptor: (Ljava/lang/Thread;)V
    flags: (0x0001) ACC_PUBLIC
    Code:
      stack=1, locals=2, args_size=2
         0: aload_0
         1: getfield      #17                 // Field socket:Ljava/net/Socket;
         4: invokevirtual #23                 // Method java/net/Socket.close:()V
         7: return
      LineNumberTable:
        line 37: 0
      LocalVariableTable:
        Start  Length  Slot  Name   Signature
            0       8     0  this   Lorg/scalatest/concurrent/SocketSignaler;
            0       8     1 testThread   Ljava/lang/Thread;
    MethodParameters:
      Name                           Flags
      testThread                     final

  public org.scalatest.concurrent.SocketSignaler(java.net.Socket);
    descriptor: (Ljava/net/Socket;)V
    flags: (0x0001) ACC_PUBLIC
    Code:
      stack=2, locals=2, args_size=2
         0: aload_0
         1: aload_1
         2: putfield      #17                 // Field socket:Ljava/net/Socket;
         5: aload_0
         6: invokespecial #30                 // Method java/lang/Object."<init>":()V
         9: return
      LineNumberTable:
        line 29: 0
      LocalVariableTable:
        Start  Length  Slot  Name   Signature
            0      10     0  this   Lorg/scalatest/concurrent/SocketSignaler;
            0      10     1 socket   Ljava/net/Socket;
    MethodParameters:
      Name                           Flags
      socket                         final
}
SourceFile: "SocketSignaler.scala"
RuntimeVisibleAnnotations:
  0: #8(#9=s#10)
    scala.reflect.ScalaSignature(
      bytes="\u0006\u0005m2A\u0001C\u0005\u0001!!A1\u0004\u0001B\u0001B\u0003%A\u0004C\u0003%\u0001\u0011\u0005Q\u0005C\u0003)\u0001\u0011\u0005\u0011fB\u00036\u0013!\u0005aGB\u0003\t\u0013!\u0005q\u0007C\u0003%\u000b\u0011\u0005\u0001\bC\u0003)\u000b\u0011\u0005\u0011H\u0001\bT_\u000e\\W\r^*jO:\fG.\u001a:\u000b\u0005)Y\u0011AC2p]\u000e,(O]3oi*\u0011A\"D\u0001\ng\u000e\fG.\u0019;fgRT\u0011AD\u0001\u0004_J<7\u0001A\n\u0004\u0001E9\u0002C\u0001\n\u0016\u001b\u0005\u0019\"\"\u0001\u000b\u0002\u000bM\u001c\u0017\r\\1\n\u0005Y\u0019\"AB!osJ+g\r\u0005\u0002\u001935\t\u0011\"\u0003\u0002\u001b\u0013\tA1+[4oC2,\'/\u0001\u0004t_\u000e\\W\r\u001e\t\u0003;\tj\u0011A\b\u0006\u0003?\u0001\n1A\\3u\u0015\u0005\t\u0013\u0001\u00026bm\u0006L!a\t\u0010\u0003\rM{7m[3u\u0003\u0019a\u0014N\\5u}Q\u0011ae\n\t\u00031\u0001AQa\u0007\u0002A\u0002q\tQ!\u00199qYf$\"AK\u0017\u0011\u0005IY\u0013B\u0001\u0017\u0014\u0005\u0011)f.\u001b;\t\u000b9\u001a\u0001\u0019A\u0018\u0002\u0015Q,7\u000f\u001e+ie\u0016\fG\r\u0005\u00021g5\t\u0011G\u0003\u00023A\u0005!A.\u00198h\u0013\t!\u0014G\u0001\u0004UQJ,\u0017\rZ\u0001\u000f\'>\u001c7.\u001a;TS\u001et\u0017\r\\3s!\tARa\u0005\u0002\u0006#Q\ta\u0007\u0006\u0002\'u!)1d\u0002a\u00019\u0001"
    )
  ScalaInlineInfo: length = 0xE (unknown attribute)
   01 00 00 02 00 1B 00 1C 00 00 0D 00 0E 00
  ScalaSig: length = 0x3 (unknown attribute)
   05 02 00
