Classfile /Users/mw/Projects/slang-braindump/.jar/jar11/assemble/slang-braindump/assemble/content/com/fasterxml/jackson/databind/deser/BuilderBasedDeserializer.class
  Last modified May 29, 2022; size 26173 bytes
  SHA-256 checksum 862a26aed991f4c9b847df16bebeb901ef585b99bd7278f9448e3d2f20ccf06e
  Compiled from "BuilderBasedDeserializer.java"
public class com.fasterxml.jackson.databind.deser.BuilderBasedDeserializer extends com.fasterxml.jackson.databind.deser.BeanDeserializerBase
  minor version: 0
  major version: 52
  flags: (0x0021) ACC_PUBLIC, ACC_SUPER
  this_class: #27                         // com/fasterxml/jackson/databind/deser/BuilderBasedDeserializer
  super_class: #144                       // com/fasterxml/jackson/databind/deser/BeanDeserializerBase
  interfaces: 0, fields: 3, methods: 32, attributes: 2
Constant pool:
    #1 = Methodref          #27.#308      // com/fasterxml/jackson/databind/deser/BuilderBasedDeserializer."<init>":(Lcom/fasterxml/jackson/databind/deser/BeanDeserializerBuilder;Lcom/fasterxml/jackson/databind/BeanDescription;Lcom/fasterxml/jackson/databind/JavaType;Lcom/fasterxml/jackson/databind/deser/impl/BeanPropertyMap;Ljava/util/Map;Ljava/util/Set;ZLjava/util/Set;Z)V
    #2 = Methodref          #144.#309     // com/fasterxml/jackson/databind/deser/BeanDeserializerBase."<init>":(Lcom/fasterxml/jackson/databind/deser/BeanDeserializerBuilder;Lcom/fasterxml/jackson/databind/BeanDescription;Lcom/fasterxml/jackson/databind/deser/impl/BeanPropertyMap;Ljava/util/Map;Ljava/util/Set;ZLjava/util/Set;Z)V
    #3 = Fieldref           #27.#310      // com/fasterxml/jackson/databind/deser/BuilderBasedDeserializer._targetType:Lcom/fasterxml/jackson/databind/JavaType;
    #4 = Methodref          #311.#312     // com/fasterxml/jackson/databind/deser/BeanDeserializerBuilder.getBuildMethod:()Lcom/fasterxml/jackson/databind/introspect/AnnotatedMethod;
    #5 = Fieldref           #27.#313      // com/fasterxml/jackson/databind/deser/BuilderBasedDeserializer._buildMethod:Lcom/fasterxml/jackson/databind/introspect/AnnotatedMethod;
    #6 = Fieldref           #27.#314      // com/fasterxml/jackson/databind/deser/BuilderBasedDeserializer._objectIdReader:Lcom/fasterxml/jackson/databind/deser/impl/ObjectIdReader;
    #7 = Class              #315          // java/lang/IllegalArgumentException
    #8 = Class              #316          // java/lang/StringBuilder
    #9 = Methodref          #8.#317       // java/lang/StringBuilder."<init>":()V
   #10 = String             #318          // Cannot use Object Id with Builder-based deserialization (type
   #11 = Methodref          #8.#319       // java/lang/StringBuilder.append:(Ljava/lang/String;)Ljava/lang/StringBuilder;
   #12 = Methodref          #320.#321     // com/fasterxml/jackson/databind/BeanDescription.getType:()Lcom/fasterxml/jackson/databind/JavaType;
   #13 = Methodref          #8.#322       // java/lang/StringBuilder.append:(Ljava/lang/Object;)Ljava/lang/StringBuilder;
   #14 = String             #323          // )
   #15 = Methodref          #8.#324       // java/lang/StringBuilder.toString:()Ljava/lang/String;
   #16 = Methodref          #7.#325       // java/lang/IllegalArgumentException."<init>":(Ljava/lang/String;)V
   #17 = Methodref          #27.#326      // com/fasterxml/jackson/databind/deser/BuilderBasedDeserializer."<init>":(Lcom/fasterxml/jackson/databind/deser/BeanDeserializerBuilder;Lcom/fasterxml/jackson/databind/BeanDescription;Lcom/fasterxml/jackson/databind/JavaType;Lcom/fasterxml/jackson/databind/deser/impl/BeanPropertyMap;Ljava/util/Map;Ljava/util/Set;ZZ)V
   #18 = Fieldref           #27.#327      // com/fasterxml/jackson/databind/deser/BuilderBasedDeserializer._ignoreAllUnknown:Z
   #19 = Methodref          #27.#328      // com/fasterxml/jackson/databind/deser/BuilderBasedDeserializer."<init>":(Lcom/fasterxml/jackson/databind/deser/BuilderBasedDeserializer;Z)V
   #20 = Methodref          #144.#329     // com/fasterxml/jackson/databind/deser/BeanDeserializerBase."<init>":(Lcom/fasterxml/jackson/databind/deser/BeanDeserializerBase;Z)V
   #21 = Methodref          #144.#330     // com/fasterxml/jackson/databind/deser/BeanDeserializerBase."<init>":(Lcom/fasterxml/jackson/databind/deser/BeanDeserializerBase;Lcom/fasterxml/jackson/databind/util/NameTransformer;)V
   #22 = Methodref          #144.#331     // com/fasterxml/jackson/databind/deser/BeanDeserializerBase."<init>":(Lcom/fasterxml/jackson/databind/deser/BeanDeserializerBase;Lcom/fasterxml/jackson/databind/deser/impl/ObjectIdReader;)V
   #23 = Fieldref           #27.#332      // com/fasterxml/jackson/databind/deser/BuilderBasedDeserializer._includableProps:Ljava/util/Set;
   #24 = Methodref          #27.#333      // com/fasterxml/jackson/databind/deser/BuilderBasedDeserializer."<init>":(Lcom/fasterxml/jackson/databind/deser/BuilderBasedDeserializer;Ljava/util/Set;Ljava/util/Set;)V
   #25 = Methodref          #144.#334     // com/fasterxml/jackson/databind/deser/BeanDeserializerBase."<init>":(Lcom/fasterxml/jackson/databind/deser/BeanDeserializerBase;Ljava/util/Set;Ljava/util/Set;)V
   #26 = Methodref          #144.#335     // com/fasterxml/jackson/databind/deser/BeanDeserializerBase."<init>":(Lcom/fasterxml/jackson/databind/deser/BeanDeserializerBase;Lcom/fasterxml/jackson/databind/deser/impl/BeanPropertyMap;)V
   #27 = Class              #336          // com/fasterxml/jackson/databind/deser/BuilderBasedDeserializer
   #28 = Methodref          #27.#337      // com/fasterxml/jackson/databind/deser/BuilderBasedDeserializer."<init>":(Lcom/fasterxml/jackson/databind/deser/BuilderBasedDeserializer;Lcom/fasterxml/jackson/databind/util/NameTransformer;)V
   #29 = Methodref          #27.#338      // com/fasterxml/jackson/databind/deser/BuilderBasedDeserializer."<init>":(Lcom/fasterxml/jackson/databind/deser/BuilderBasedDeserializer;Lcom/fasterxml/jackson/databind/deser/impl/ObjectIdReader;)V
   #30 = Methodref          #27.#339      // com/fasterxml/jackson/databind/deser/BuilderBasedDeserializer."<init>":(Lcom/fasterxml/jackson/databind/deser/BuilderBasedDeserializer;Lcom/fasterxml/jackson/databind/deser/impl/BeanPropertyMap;)V
   #31 = Fieldref           #27.#340      // com/fasterxml/jackson/databind/deser/BuilderBasedDeserializer._beanProperties:Lcom/fasterxml/jackson/databind/deser/impl/BeanPropertyMap;
   #32 = Methodref          #341.#342     // com/fasterxml/jackson/databind/deser/impl/BeanPropertyMap.getPropertiesInInsertionOrder:()[Lcom/fasterxml/jackson/databind/deser/SettableBeanProperty;
   #33 = Class              #343          // com/fasterxml/jackson/databind/deser/impl/BeanAsArrayBuilderDeserializer
   #34 = Methodref          #33.#344      // com/fasterxml/jackson/databind/deser/impl/BeanAsArrayBuilderDeserializer."<init>":(Lcom/fasterxml/jackson/databind/deser/BeanDeserializerBase;Lcom/fasterxml/jackson/databind/JavaType;[Lcom/fasterxml/jackson/databind/deser/SettableBeanProperty;Lcom/fasterxml/jackson/databind/introspect/AnnotatedMethod;)V
   #35 = Fieldref           #345.#346     // java/lang/Boolean.FALSE:Ljava/lang/Boolean;
   #36 = Methodref          #347.#348     // com/fasterxml/jackson/databind/introspect/AnnotatedMethod.getMember:()Ljava/lang/reflect/Method;
   #37 = Class              #349          // "[Ljava/lang/Object;"
   #38 = Methodref          #350.#351     // java/lang/reflect/Method.invoke:(Ljava/lang/Object;[Ljava/lang/Object;)Ljava/lang/Object;
   #39 = Class              #352          // java/lang/Exception
   #40 = Methodref          #27.#353      // com/fasterxml/jackson/databind/deser/BuilderBasedDeserializer.wrapInstantiationProblem:(Ljava/lang/Throwable;Lcom/fasterxml/jackson/databind/DeserializationContext;)Ljava/lang/Object;
   #41 = Methodref          #354.#355     // com/fasterxml/jackson/core/JsonParser.isExpectedStartObjectToken:()Z
   #42 = Methodref          #354.#356     // com/fasterxml/jackson/core/JsonParser.nextToken:()Lcom/fasterxml/jackson/core/JsonToken;
   #43 = Fieldref           #27.#357      // com/fasterxml/jackson/databind/deser/BuilderBasedDeserializer._vanillaProcessing:Z
   #44 = Methodref          #27.#358      // com/fasterxml/jackson/databind/deser/BuilderBasedDeserializer.vanillaDeserialize:(Lcom/fasterxml/jackson/core/JsonParser;Lcom/fasterxml/jackson/databind/DeserializationContext;Lcom/fasterxml/jackson/core/JsonToken;)Ljava/lang/Object;
   #45 = Methodref          #27.#359      // com/fasterxml/jackson/databind/deser/BuilderBasedDeserializer.finishBuild:(Lcom/fasterxml/jackson/databind/DeserializationContext;Ljava/lang/Object;)Ljava/lang/Object;
   #46 = Methodref          #27.#360      // com/fasterxml/jackson/databind/deser/BuilderBasedDeserializer.deserializeFromObject:(Lcom/fasterxml/jackson/core/JsonParser;Lcom/fasterxml/jackson/databind/DeserializationContext;)Ljava/lang/Object;
   #47 = Methodref          #354.#361     // com/fasterxml/jackson/core/JsonParser.currentTokenId:()I
   #48 = Methodref          #27.#362      // com/fasterxml/jackson/databind/deser/BuilderBasedDeserializer.deserializeFromString:(Lcom/fasterxml/jackson/core/JsonParser;Lcom/fasterxml/jackson/databind/DeserializationContext;)Ljava/lang/Object;
   #49 = Methodref          #27.#363      // com/fasterxml/jackson/databind/deser/BuilderBasedDeserializer.deserializeFromNumber:(Lcom/fasterxml/jackson/core/JsonParser;Lcom/fasterxml/jackson/databind/DeserializationContext;)Ljava/lang/Object;
   #50 = Methodref          #27.#364      // com/fasterxml/jackson/databind/deser/BuilderBasedDeserializer.deserializeFromDouble:(Lcom/fasterxml/jackson/core/JsonParser;Lcom/fasterxml/jackson/databind/DeserializationContext;)Ljava/lang/Object;
   #51 = Methodref          #354.#365     // com/fasterxml/jackson/core/JsonParser.getEmbeddedObject:()Ljava/lang/Object;
   #52 = Methodref          #27.#366      // com/fasterxml/jackson/databind/deser/BuilderBasedDeserializer.deserializeFromBoolean:(Lcom/fasterxml/jackson/core/JsonParser;Lcom/fasterxml/jackson/databind/DeserializationContext;)Ljava/lang/Object;
   #53 = Methodref          #27.#367      // com/fasterxml/jackson/databind/deser/BuilderBasedDeserializer._deserializeFromArray:(Lcom/fasterxml/jackson/core/JsonParser;Lcom/fasterxml/jackson/databind/DeserializationContext;)Ljava/lang/Object;
   #54 = Methodref          #27.#368      // com/fasterxml/jackson/databind/deser/BuilderBasedDeserializer.getValueType:(Lcom/fasterxml/jackson/databind/DeserializationContext;)Lcom/fasterxml/jackson/databind/JavaType;
   #55 = Methodref          #369.#370     // com/fasterxml/jackson/databind/DeserializationContext.handleUnexpectedToken:(Lcom/fasterxml/jackson/databind/JavaType;Lcom/fasterxml/jackson/core/JsonParser;)Ljava/lang/Object;
   #56 = Methodref          #27.#371      // com/fasterxml/jackson/databind/deser/BuilderBasedDeserializer.handledType:()Ljava/lang/Class;
   #57 = Methodref          #60.#372      // java/lang/Object.getClass:()Ljava/lang/Class;
   #58 = Methodref          #373.#374     // java/lang/Class.isAssignableFrom:(Ljava/lang/Class;)Z
   #59 = String             #375          // Deserialization of %s by passing existing Builder (%s) instance not supported
   #60 = Class              #376          // java/lang/Object
   #61 = Methodref          #373.#377     // java/lang/Class.getName:()Ljava/lang/String;
   #62 = Methodref          #378.#379     // java/lang/String.format:(Ljava/lang/String;[Ljava/lang/Object;)Ljava/lang/String;
   #63 = Methodref          #369.#380     // com/fasterxml/jackson/databind/DeserializationContext.reportBadDefinition:(Lcom/fasterxml/jackson/databind/JavaType;Ljava/lang/String;)Ljava/lang/Object;
   #64 = String             #381          // Deserialization of %s by passing existing instance (of %s) not supported
   #65 = Fieldref           #27.#382      // com/fasterxml/jackson/databind/deser/BuilderBasedDeserializer._valueInstantiator:Lcom/fasterxml/jackson/databind/deser/ValueInstantiator;
   #66 = Methodref          #383.#384     // com/fasterxml/jackson/databind/deser/ValueInstantiator.createUsingDefault:(Lcom/fasterxml/jackson/databind/DeserializationContext;)Ljava/lang/Object;
   #67 = Methodref          #354.#385     // com/fasterxml/jackson/core/JsonParser.currentToken:()Lcom/fasterxml/jackson/core/JsonToken;
   #68 = Fieldref           #386.#387     // com/fasterxml/jackson/core/JsonToken.FIELD_NAME:Lcom/fasterxml/jackson/core/JsonToken;
   #69 = Methodref          #354.#388     // com/fasterxml/jackson/core/JsonParser.currentName:()Ljava/lang/String;
   #70 = Methodref          #341.#389     // com/fasterxml/jackson/databind/deser/impl/BeanPropertyMap.find:(Ljava/lang/String;)Lcom/fasterxml/jackson/databind/deser/SettableBeanProperty;
   #71 = Methodref          #390.#391     // com/fasterxml/jackson/databind/deser/SettableBeanProperty.deserializeSetAndReturn:(Lcom/fasterxml/jackson/core/JsonParser;Lcom/fasterxml/jackson/databind/DeserializationContext;Ljava/lang/Object;)Ljava/lang/Object;
   #72 = Methodref          #27.#392      // com/fasterxml/jackson/databind/deser/BuilderBasedDeserializer.wrapAndThrow:(Ljava/lang/Throwable;Ljava/lang/Object;Ljava/lang/String;Lcom/fasterxml/jackson/databind/DeserializationContext;)V
   #73 = Methodref          #27.#393      // com/fasterxml/jackson/databind/deser/BuilderBasedDeserializer.handleUnknownVanilla:(Lcom/fasterxml/jackson/core/JsonParser;Lcom/fasterxml/jackson/databind/DeserializationContext;Ljava/lang/Object;Ljava/lang/String;)V
   #74 = Fieldref           #27.#394      // com/fasterxml/jackson/databind/deser/BuilderBasedDeserializer._nonStandardCreation:Z
   #75 = Fieldref           #27.#395      // com/fasterxml/jackson/databind/deser/BuilderBasedDeserializer._unwrappedPropertyHandler:Lcom/fasterxml/jackson/databind/deser/impl/UnwrappedPropertyHandler;
   #76 = Methodref          #27.#396      // com/fasterxml/jackson/databind/deser/BuilderBasedDeserializer.deserializeWithUnwrapped:(Lcom/fasterxml/jackson/core/JsonParser;Lcom/fasterxml/jackson/databind/DeserializationContext;)Ljava/lang/Object;
   #77 = Fieldref           #27.#397      // com/fasterxml/jackson/databind/deser/BuilderBasedDeserializer._externalTypeIdHandler:Lcom/fasterxml/jackson/databind/deser/impl/ExternalTypeHandler;
   #78 = Methodref          #27.#398      // com/fasterxml/jackson/databind/deser/BuilderBasedDeserializer.deserializeWithExternalTypeId:(Lcom/fasterxml/jackson/core/JsonParser;Lcom/fasterxml/jackson/databind/DeserializationContext;)Ljava/lang/Object;
   #79 = Methodref          #27.#399      // com/fasterxml/jackson/databind/deser/BuilderBasedDeserializer.deserializeFromObjectUsingNonDefault:(Lcom/fasterxml/jackson/core/JsonParser;Lcom/fasterxml/jackson/databind/DeserializationContext;)Ljava/lang/Object;
   #80 = Fieldref           #27.#400      // com/fasterxml/jackson/databind/deser/BuilderBasedDeserializer._injectables:[Lcom/fasterxml/jackson/databind/deser/impl/ValueInjector;
   #81 = Methodref          #27.#401      // com/fasterxml/jackson/databind/deser/BuilderBasedDeserializer.injectValues:(Lcom/fasterxml/jackson/databind/DeserializationContext;Ljava/lang/Object;)V
   #82 = Fieldref           #27.#402      // com/fasterxml/jackson/databind/deser/BuilderBasedDeserializer._needViewProcesing:Z
   #83 = Methodref          #369.#403     // com/fasterxml/jackson/databind/DeserializationContext.getActiveView:()Ljava/lang/Class;
   #84 = Methodref          #27.#404      // com/fasterxml/jackson/databind/deser/BuilderBasedDeserializer.deserializeWithView:(Lcom/fasterxml/jackson/core/JsonParser;Lcom/fasterxml/jackson/databind/DeserializationContext;Ljava/lang/Object;Ljava/lang/Class;)Ljava/lang/Object;
   #85 = Fieldref           #27.#405      // com/fasterxml/jackson/databind/deser/BuilderBasedDeserializer._propertyBasedCreator:Lcom/fasterxml/jackson/databind/deser/impl/PropertyBasedCreator;
   #86 = Methodref          #406.#407     // com/fasterxml/jackson/databind/deser/impl/PropertyBasedCreator.startBuilding:(Lcom/fasterxml/jackson/core/JsonParser;Lcom/fasterxml/jackson/databind/DeserializationContext;Lcom/fasterxml/jackson/databind/deser/impl/ObjectIdReader;)Lcom/fasterxml/jackson/databind/deser/impl/PropertyValueBuffer;
   #87 = Methodref          #406.#408     // com/fasterxml/jackson/databind/deser/impl/PropertyBasedCreator.findCreatorProperty:(Ljava/lang/String;)Lcom/fasterxml/jackson/databind/deser/SettableBeanProperty;
   #88 = Methodref          #409.#410     // com/fasterxml/jackson/databind/deser/impl/PropertyValueBuffer.readIdProperty:(Ljava/lang/String;)Z
   #89 = Methodref          #390.#411     // com/fasterxml/jackson/databind/deser/SettableBeanProperty.visibleInView:(Ljava/lang/Class;)Z
   #90 = Methodref          #354.#412     // com/fasterxml/jackson/core/JsonParser.skipChildren:()Lcom/fasterxml/jackson/core/JsonParser;
   #91 = Methodref          #390.#413     // com/fasterxml/jackson/databind/deser/SettableBeanProperty.deserialize:(Lcom/fasterxml/jackson/core/JsonParser;Lcom/fasterxml/jackson/databind/DeserializationContext;)Ljava/lang/Object;
   #92 = Methodref          #409.#414     // com/fasterxml/jackson/databind/deser/impl/PropertyValueBuffer.assignParameter:(Lcom/fasterxml/jackson/databind/deser/SettableBeanProperty;Ljava/lang/Object;)Z
   #93 = Methodref          #406.#415     // com/fasterxml/jackson/databind/deser/impl/PropertyBasedCreator.build:(Lcom/fasterxml/jackson/databind/DeserializationContext;Lcom/fasterxml/jackson/databind/deser/impl/PropertyValueBuffer;)Ljava/lang/Object;
   #94 = Fieldref           #27.#416      // com/fasterxml/jackson/databind/deser/BuilderBasedDeserializer._beanType:Lcom/fasterxml/jackson/databind/JavaType;
   #95 = Methodref          #417.#418     // com/fasterxml/jackson/databind/JavaType.getRawClass:()Ljava/lang/Class;
   #96 = Methodref          #27.#419      // com/fasterxml/jackson/databind/deser/BuilderBasedDeserializer.handlePolymorphic:(Lcom/fasterxml/jackson/core/JsonParser;Lcom/fasterxml/jackson/databind/DeserializationContext;Ljava/lang/Object;Lcom/fasterxml/jackson/databind/util/TokenBuffer;)Ljava/lang/Object;
   #97 = Methodref          #27.#420      // com/fasterxml/jackson/databind/deser/BuilderBasedDeserializer.handleUnknownProperties:(Lcom/fasterxml/jackson/databind/DeserializationContext;Ljava/lang/Object;Lcom/fasterxml/jackson/databind/util/TokenBuffer;)Ljava/lang/Object;
   #98 = Methodref          #27.#421      // com/fasterxml/jackson/databind/deser/BuilderBasedDeserializer._deserialize:(Lcom/fasterxml/jackson/core/JsonParser;Lcom/fasterxml/jackson/databind/DeserializationContext;Ljava/lang/Object;)Ljava/lang/Object;
   #99 = Methodref          #409.#422     // com/fasterxml/jackson/databind/deser/impl/PropertyValueBuffer.bufferProperty:(Lcom/fasterxml/jackson/databind/deser/SettableBeanProperty;Ljava/lang/Object;)V
  #100 = Fieldref           #27.#423      // com/fasterxml/jackson/databind/deser/BuilderBasedDeserializer._ignorableProps:Ljava/util/Set;
  #101 = Methodref          #424.#425     // com/fasterxml/jackson/databind/util/IgnorePropertiesUtil.shouldIgnore:(Ljava/lang/Object;Ljava/util/Collection;Ljava/util/Collection;)Z
  #102 = Methodref          #27.#426      // com/fasterxml/jackson/databind/deser/BuilderBasedDeserializer.handleIgnoredProperty:(Lcom/fasterxml/jackson/core/JsonParser;Lcom/fasterxml/jackson/databind/DeserializationContext;Ljava/lang/Object;Ljava/lang/String;)V
  #103 = Fieldref           #27.#427      // com/fasterxml/jackson/databind/deser/BuilderBasedDeserializer._anySetter:Lcom/fasterxml/jackson/databind/deser/SettableAnyProperty;
  #104 = Methodref          #428.#413     // com/fasterxml/jackson/databind/deser/SettableAnyProperty.deserialize:(Lcom/fasterxml/jackson/core/JsonParser;Lcom/fasterxml/jackson/databind/DeserializationContext;)Ljava/lang/Object;
  #105 = Methodref          #409.#429     // com/fasterxml/jackson/databind/deser/impl/PropertyValueBuffer.bufferAnyProperty:(Lcom/fasterxml/jackson/databind/deser/SettableAnyProperty;Ljava/lang/String;Ljava/lang/Object;)V
  #106 = Methodref          #369.#430     // com/fasterxml/jackson/databind/DeserializationContext.bufferForInputBuffering:(Lcom/fasterxml/jackson/core/JsonParser;)Lcom/fasterxml/jackson/databind/util/TokenBuffer;
  #107 = Methodref          #431.#432     // com/fasterxml/jackson/databind/util/TokenBuffer.writeFieldName:(Ljava/lang/String;)V
  #108 = Methodref          #431.#433     // com/fasterxml/jackson/databind/util/TokenBuffer.copyCurrentStructure:(Lcom/fasterxml/jackson/core/JsonParser;)V
  #109 = Fieldref           #386.#434     // com/fasterxml/jackson/core/JsonToken.START_OBJECT:Lcom/fasterxml/jackson/core/JsonToken;
  #110 = Methodref          #354.#435     // com/fasterxml/jackson/core/JsonParser.hasToken:(Lcom/fasterxml/jackson/core/JsonToken;)Z
  #111 = Methodref          #431.#436     // com/fasterxml/jackson/databind/util/TokenBuffer.writeStartObject:()V
  #112 = Methodref          #27.#437      // com/fasterxml/jackson/databind/deser/BuilderBasedDeserializer.deserializeWithUnwrapped:(Lcom/fasterxml/jackson/core/JsonParser;Lcom/fasterxml/jackson/databind/DeserializationContext;Ljava/lang/Object;Lcom/fasterxml/jackson/databind/util/TokenBuffer;)Ljava/lang/Object;
  #113 = Methodref          #27.#438      // com/fasterxml/jackson/databind/deser/BuilderBasedDeserializer.deserializeWithExternalTypeId:(Lcom/fasterxml/jackson/core/JsonParser;Lcom/fasterxml/jackson/databind/DeserializationContext;Ljava/lang/Object;)Ljava/lang/Object;
  #114 = Fieldref           #27.#439      // com/fasterxml/jackson/databind/deser/BuilderBasedDeserializer._arrayDelegateDeserializer:Lcom/fasterxml/jackson/databind/JsonDeserializer;
  #115 = Fieldref           #27.#440      // com/fasterxml/jackson/databind/deser/BuilderBasedDeserializer._delegateDeserializer:Lcom/fasterxml/jackson/databind/JsonDeserializer;
  #116 = Methodref          #441.#413     // com/fasterxml/jackson/databind/JsonDeserializer.deserialize:(Lcom/fasterxml/jackson/core/JsonParser;Lcom/fasterxml/jackson/databind/DeserializationContext;)Ljava/lang/Object;
  #117 = Methodref          #383.#442     // com/fasterxml/jackson/databind/deser/ValueInstantiator.createUsingArrayDelegate:(Lcom/fasterxml/jackson/databind/DeserializationContext;Ljava/lang/Object;)Ljava/lang/Object;
  #118 = Methodref          #27.#443      // com/fasterxml/jackson/databind/deser/BuilderBasedDeserializer._findCoercionFromEmptyArray:(Lcom/fasterxml/jackson/databind/DeserializationContext;)Lcom/fasterxml/jackson/databind/cfg/CoercionAction;
  #119 = Fieldref           #444.#445     // com/fasterxml/jackson/databind/DeserializationFeature.UNWRAP_SINGLE_VALUE_ARRAYS:Lcom/fasterxml/jackson/databind/DeserializationFeature;
  #120 = Methodref          #369.#446     // com/fasterxml/jackson/databind/DeserializationContext.isEnabled:(Lcom/fasterxml/jackson/databind/DeserializationFeature;)Z
  #121 = Fieldref           #447.#448     // com/fasterxml/jackson/databind/cfg/CoercionAction.Fail:Lcom/fasterxml/jackson/databind/cfg/CoercionAction;
  #122 = Fieldref           #386.#449     // com/fasterxml/jackson/core/JsonToken.END_ARRAY:Lcom/fasterxml/jackson/core/JsonToken;
  #123 = Fieldref           #145.#450     // com/fasterxml/jackson/databind/deser/BuilderBasedDeserializer$1.$SwitchMap$com$fasterxml$jackson$databind$cfg$CoercionAction:[I
  #124 = Methodref          #447.#451     // com/fasterxml/jackson/databind/cfg/CoercionAction.ordinal:()I
  #125 = Methodref          #27.#452      // com/fasterxml/jackson/databind/deser/BuilderBasedDeserializer.getEmptyValue:(Lcom/fasterxml/jackson/databind/DeserializationContext;)Ljava/lang/Object;
  #126 = Methodref          #27.#453      // com/fasterxml/jackson/databind/deser/BuilderBasedDeserializer.getNullValue:(Lcom/fasterxml/jackson/databind/DeserializationContext;)Ljava/lang/Object;
  #127 = Fieldref           #386.#454     // com/fasterxml/jackson/core/JsonToken.START_ARRAY:Lcom/fasterxml/jackson/core/JsonToken;
  #128 = Methodref          #369.#455     // com/fasterxml/jackson/databind/DeserializationContext.handleUnexpectedToken:(Lcom/fasterxml/jackson/databind/JavaType;Lcom/fasterxml/jackson/core/JsonToken;Lcom/fasterxml/jackson/core/JsonParser;Ljava/lang/String;[Ljava/lang/Object;)Ljava/lang/Object;
  #129 = Methodref          #27.#413      // com/fasterxml/jackson/databind/deser/BuilderBasedDeserializer.deserialize:(Lcom/fasterxml/jackson/core/JsonParser;Lcom/fasterxml/jackson/databind/DeserializationContext;)Ljava/lang/Object;
  #130 = Methodref          #27.#456      // com/fasterxml/jackson/databind/deser/BuilderBasedDeserializer.handleMissingEndArrayForSingle:(Lcom/fasterxml/jackson/core/JsonParser;Lcom/fasterxml/jackson/databind/DeserializationContext;)V
  #131 = Methodref          #383.#457     // com/fasterxml/jackson/databind/deser/ValueInstantiator.createUsingDelegate:(Lcom/fasterxml/jackson/databind/DeserializationContext;Ljava/lang/Object;)Ljava/lang/Object;
  #132 = Methodref          #27.#458      // com/fasterxml/jackson/databind/deser/BuilderBasedDeserializer.deserializeUsingPropertyBasedWithUnwrapped:(Lcom/fasterxml/jackson/core/JsonParser;Lcom/fasterxml/jackson/databind/DeserializationContext;)Ljava/lang/Object;
  #133 = Methodref          #428.#459     // com/fasterxml/jackson/databind/deser/SettableAnyProperty.deserializeAndSet:(Lcom/fasterxml/jackson/core/JsonParser;Lcom/fasterxml/jackson/databind/DeserializationContext;Ljava/lang/Object;Ljava/lang/String;)V
  #134 = Methodref          #431.#460     // com/fasterxml/jackson/databind/util/TokenBuffer.writeEndObject:()V
  #135 = Methodref          #461.#462     // com/fasterxml/jackson/databind/deser/impl/UnwrappedPropertyHandler.processUnwrapped:(Lcom/fasterxml/jackson/core/JsonParser;Lcom/fasterxml/jackson/databind/DeserializationContext;Ljava/lang/Object;Lcom/fasterxml/jackson/databind/util/TokenBuffer;)Ljava/lang/Object;
  #136 = Methodref          #27.#463      // com/fasterxml/jackson/databind/deser/BuilderBasedDeserializer.deserializeUsingPropertyBasedWithExternalTypeId:(Lcom/fasterxml/jackson/core/JsonParser;Lcom/fasterxml/jackson/databind/DeserializationContext;)Ljava/lang/Object;
  #137 = Methodref          #464.#465     // com/fasterxml/jackson/databind/deser/impl/ExternalTypeHandler.start:()Lcom/fasterxml/jackson/databind/deser/impl/ExternalTypeHandler;
  #138 = Methodref          #386.#466     // com/fasterxml/jackson/core/JsonToken.isScalarValue:()Z
  #139 = Methodref          #464.#467     // com/fasterxml/jackson/databind/deser/impl/ExternalTypeHandler.handleTypePropertyValue:(Lcom/fasterxml/jackson/core/JsonParser;Lcom/fasterxml/jackson/databind/DeserializationContext;Ljava/lang/String;Ljava/lang/Object;)Z
  #140 = Methodref          #464.#468     // com/fasterxml/jackson/databind/deser/impl/ExternalTypeHandler.handlePropertyValue:(Lcom/fasterxml/jackson/core/JsonParser;Lcom/fasterxml/jackson/databind/DeserializationContext;Ljava/lang/String;Ljava/lang/Object;)Z
  #141 = Methodref          #27.#469      // com/fasterxml/jackson/databind/deser/BuilderBasedDeserializer.handleUnknownProperty:(Lcom/fasterxml/jackson/core/JsonParser;Lcom/fasterxml/jackson/databind/DeserializationContext;Ljava/lang/Object;Ljava/lang/String;)V
  #142 = Methodref          #464.#470     // com/fasterxml/jackson/databind/deser/impl/ExternalTypeHandler.complete:(Lcom/fasterxml/jackson/core/JsonParser;Lcom/fasterxml/jackson/databind/DeserializationContext;Ljava/lang/Object;)Ljava/lang/Object;
  #143 = String             #471          // Deserialization (of %s) with Builder, External type id, @JsonCreator not yet implemented
  #144 = Class              #472          // com/fasterxml/jackson/databind/deser/BeanDeserializerBase
  #145 = Class              #473          // com/fasterxml/jackson/databind/deser/BuilderBasedDeserializer$1
  #146 = Utf8               InnerClasses
  #147 = Utf8               serialVersionUID
  #148 = Utf8               J
  #149 = Utf8               ConstantValue
  #150 = Long               1l
  #152 = Utf8               _buildMethod
  #153 = Utf8               Lcom/fasterxml/jackson/databind/introspect/AnnotatedMethod;
  #154 = Utf8               _targetType
  #155 = Utf8               Lcom/fasterxml/jackson/databind/JavaType;
  #156 = Utf8               <init>
  #157 = Utf8               (Lcom/fasterxml/jackson/databind/deser/BeanDeserializerBuilder;Lcom/fasterxml/jackson/databind/BeanDescription;Lcom/fasterxml/jackson/databind/JavaType;Lcom/fasterxml/jackson/databind/deser/impl/BeanPropertyMap;Ljava/util/Map;Ljava/util/Set;ZZ)V
  #158 = Utf8               Code
  #159 = Utf8               LineNumberTable
  #160 = Utf8               LocalVariableTable
  #161 = Utf8               this
  #162 = Utf8               Lcom/fasterxml/jackson/databind/deser/BuilderBasedDeserializer;
  #163 = Utf8               builder
  #164 = Utf8               Lcom/fasterxml/jackson/databind/deser/BeanDeserializerBuilder;
  #165 = Utf8               beanDesc
  #166 = Utf8               Lcom/fasterxml/jackson/databind/BeanDescription;
  #167 = Utf8               targetType
  #168 = Utf8               properties
  #169 = Utf8               Lcom/fasterxml/jackson/databind/deser/impl/BeanPropertyMap;
  #170 = Utf8               backRefs
  #171 = Utf8               Ljava/util/Map;
  #172 = Utf8               ignorableProps
  #173 = Utf8               Ljava/util/Set;
  #174 = Utf8               ignoreAllUnknown
  #175 = Utf8               Z
  #176 = Utf8               hasViews
  #177 = Utf8               LocalVariableTypeTable
  #178 = Utf8               Ljava/util/Map<Ljava/lang/String;Lcom/fasterxml/jackson/databind/deser/SettableBeanProperty;>;
  #179 = Utf8               Ljava/util/Set<Ljava/lang/String;>;
  #180 = Utf8               Signature
  #181 = Utf8               (Lcom/fasterxml/jackson/databind/deser/BeanDeserializerBuilder;Lcom/fasterxml/jackson/databind/BeanDescription;Lcom/fasterxml/jackson/databind/JavaType;Lcom/fasterxml/jackson/databind/deser/impl/BeanPropertyMap;Ljava/util/Map<Ljava/lang/String;Lcom/fasterxml/jackson/databind/deser/SettableBeanProperty;>;Ljava/util/Set<Ljava/lang/String;>;ZZ)V
  #182 = Utf8               (Lcom/fasterxml/jackson/databind/deser/BeanDeserializerBuilder;Lcom/fasterxml/jackson/databind/BeanDescription;Lcom/fasterxml/jackson/databind/JavaType;Lcom/fasterxml/jackson/databind/deser/impl/BeanPropertyMap;Ljava/util/Map;Ljava/util/Set;ZLjava/util/Set;Z)V
  #183 = Utf8               includableProps
  #184 = Utf8               StackMapTable
  #185 = Class              #336          // com/fasterxml/jackson/databind/deser/BuilderBasedDeserializer
  #186 = Class              #474          // com/fasterxml/jackson/databind/deser/BeanDeserializerBuilder
  #187 = Class              #475          // com/fasterxml/jackson/databind/BeanDescription
  #188 = Class              #476          // com/fasterxml/jackson/databind/JavaType
  #189 = Class              #477          // com/fasterxml/jackson/databind/deser/impl/BeanPropertyMap
  #190 = Class              #478          // java/util/Map
  #191 = Class              #479          // java/util/Set
  #192 = Utf8               (Lcom/fasterxml/jackson/databind/deser/BeanDeserializerBuilder;Lcom/fasterxml/jackson/databind/BeanDescription;Lcom/fasterxml/jackson/databind/JavaType;Lcom/fasterxml/jackson/databind/deser/impl/BeanPropertyMap;Ljava/util/Map<Ljava/lang/String;Lcom/fasterxml/jackson/databind/deser/SettableBeanProperty;>;Ljava/util/Set<Ljava/lang/String;>;ZLjava/util/Set<Ljava/lang/String;>;Z)V
  #193 = Utf8               (Lcom/fasterxml/jackson/databind/deser/BeanDeserializerBuilder;Lcom/fasterxml/jackson/databind/BeanDescription;Lcom/fasterxml/jackson/databind/deser/impl/BeanPropertyMap;Ljava/util/Map;Ljava/util/Set;ZZ)V
  #194 = Utf8               Deprecated
  #195 = Utf8               (Lcom/fasterxml/jackson/databind/deser/BeanDeserializerBuilder;Lcom/fasterxml/jackson/databind/BeanDescription;Lcom/fasterxml/jackson/databind/deser/impl/BeanPropertyMap;Ljava/util/Map<Ljava/lang/String;Lcom/fasterxml/jackson/databind/deser/SettableBeanProperty;>;Ljava/util/Set<Ljava/lang/String;>;ZZ)V
  #196 = Utf8               RuntimeVisibleAnnotations
  #197 = Utf8               Ljava/lang/Deprecated;
  #198 = Utf8               (Lcom/fasterxml/jackson/databind/deser/BuilderBasedDeserializer;)V
  #199 = Utf8               src
  #200 = Utf8               (Lcom/fasterxml/jackson/databind/deser/BuilderBasedDeserializer;Z)V
  #201 = Utf8               (Lcom/fasterxml/jackson/databind/deser/BuilderBasedDeserializer;Lcom/fasterxml/jackson/databind/util/NameTransformer;)V
  #202 = Utf8               unwrapper
  #203 = Utf8               Lcom/fasterxml/jackson/databind/util/NameTransformer;
  #204 = Utf8               (Lcom/fasterxml/jackson/databind/deser/BuilderBasedDeserializer;Lcom/fasterxml/jackson/databind/deser/impl/ObjectIdReader;)V
  #205 = Utf8               oir
  #206 = Utf8               Lcom/fasterxml/jackson/databind/deser/impl/ObjectIdReader;
  #207 = Utf8               (Lcom/fasterxml/jackson/databind/deser/BuilderBasedDeserializer;Ljava/util/Set;)V
  #208 = Utf8               (Lcom/fasterxml/jackson/databind/deser/BuilderBasedDeserializer;Ljava/util/Set<Ljava/lang/String;>;)V
  #209 = Utf8               (Lcom/fasterxml/jackson/databind/deser/BuilderBasedDeserializer;Ljava/util/Set;Ljava/util/Set;)V
  #210 = Utf8               (Lcom/fasterxml/jackson/databind/deser/BuilderBasedDeserializer;Ljava/util/Set<Ljava/lang/String;>;Ljava/util/Set<Ljava/lang/String;>;)V
  #211 = Utf8               (Lcom/fasterxml/jackson/databind/deser/BuilderBasedDeserializer;Lcom/fasterxml/jackson/databind/deser/impl/BeanPropertyMap;)V
  #212 = Utf8               props
  #213 = Utf8               unwrappingDeserializer
  #214 = Utf8               (Lcom/fasterxml/jackson/databind/util/NameTransformer;)Lcom/fasterxml/jackson/databind/JsonDeserializer;
  #215 = Utf8               (Lcom/fasterxml/jackson/databind/util/NameTransformer;)Lcom/fasterxml/jackson/databind/JsonDeserializer<Ljava/lang/Object;>;
  #216 = Utf8               withObjectIdReader
  #217 = Utf8               (Lcom/fasterxml/jackson/databind/deser/impl/ObjectIdReader;)Lcom/fasterxml/jackson/databind/deser/BeanDeserializerBase;
  #218 = Utf8               withByNameInclusion
  #219 = Utf8               (Ljava/util/Set;Ljava/util/Set;)Lcom/fasterxml/jackson/databind/deser/BeanDeserializerBase;
  #220 = Utf8               (Ljava/util/Set<Ljava/lang/String;>;Ljava/util/Set<Ljava/lang/String;>;)Lcom/fasterxml/jackson/databind/deser/BeanDeserializerBase;
  #221 = Utf8               withIgnoreAllUnknown
  #222 = Utf8               (Z)Lcom/fasterxml/jackson/databind/deser/BeanDeserializerBase;
  #223 = Utf8               ignoreUnknown
  #224 = Utf8               withBeanProperties
  #225 = Utf8               (Lcom/fasterxml/jackson/databind/deser/impl/BeanPropertyMap;)Lcom/fasterxml/jackson/databind/deser/BeanDeserializerBase;
  #226 = Utf8               asArrayDeserializer
  #227 = Utf8               ()Lcom/fasterxml/jackson/databind/deser/BeanDeserializerBase;
  #228 = Utf8               [Lcom/fasterxml/jackson/databind/deser/SettableBeanProperty;
  #229 = Utf8               supportsUpdate
  #230 = Utf8               (Lcom/fasterxml/jackson/databind/DeserializationConfig;)Ljava/lang/Boolean;
  #231 = Utf8               config
  #232 = Utf8               Lcom/fasterxml/jackson/databind/DeserializationConfig;
  #233 = Utf8               finishBuild
  #234 = Utf8               (Lcom/fasterxml/jackson/databind/DeserializationContext;Ljava/lang/Object;)Ljava/lang/Object;
  #235 = Utf8               e
  #236 = Utf8               Ljava/lang/Exception;
  #237 = Utf8               ctxt
  #238 = Utf8               Lcom/fasterxml/jackson/databind/DeserializationContext;
  #239 = Utf8               Ljava/lang/Object;
  #240 = Class              #352          // java/lang/Exception
  #241 = Utf8               Exceptions
  #242 = Class              #480          // java/io/IOException
  #243 = Utf8               deserialize
  #244 = Utf8               (Lcom/fasterxml/jackson/core/JsonParser;Lcom/fasterxml/jackson/databind/DeserializationContext;)Ljava/lang/Object;
  #245 = Utf8               t
  #246 = Utf8               Lcom/fasterxml/jackson/core/JsonToken;
  #247 = Utf8               p
  #248 = Utf8               Lcom/fasterxml/jackson/core/JsonParser;
  #249 = Class              #481          // com/fasterxml/jackson/core/JsonToken
  #250 = Utf8               (Lcom/fasterxml/jackson/core/JsonParser;Lcom/fasterxml/jackson/databind/DeserializationContext;Ljava/lang/Object;)Ljava/lang/Object;
  #251 = Utf8               value
  #252 = Utf8               valueType
  #253 = Utf8               builderRawType
  #254 = Utf8               Ljava/lang/Class;
  #255 = Utf8               instRawType
  #256 = Utf8               Ljava/lang/Class<*>;
  #257 = Class              #482          // java/lang/Class
  #258 = Utf8               vanillaDeserialize
  #259 = Utf8               (Lcom/fasterxml/jackson/core/JsonParser;Lcom/fasterxml/jackson/databind/DeserializationContext;Lcom/fasterxml/jackson/core/JsonToken;)Ljava/lang/Object;
  #260 = Utf8               propName
  #261 = Utf8               Ljava/lang/String;
  #262 = Utf8               prop
  #263 = Utf8               Lcom/fasterxml/jackson/databind/deser/SettableBeanProperty;
  #264 = Utf8               bean
  #265 = Class              #376          // java/lang/Object
  #266 = Class              #483          // com/fasterxml/jackson/core/JsonParser
  #267 = Class              #484          // com/fasterxml/jackson/databind/DeserializationContext
  #268 = Class              #485          // java/lang/String
  #269 = Class              #486          // com/fasterxml/jackson/databind/deser/SettableBeanProperty
  #270 = Utf8               deserializeFromObject
  #271 = Utf8               view
  #272 = Utf8               _deserializeUsingPropertyBased
  #273 = Utf8               creatorProp
  #274 = Utf8               creator
  #275 = Utf8               Lcom/fasterxml/jackson/databind/deser/impl/PropertyBasedCreator;
  #276 = Utf8               buffer
  #277 = Utf8               Lcom/fasterxml/jackson/databind/deser/impl/PropertyValueBuffer;
  #278 = Utf8               activeView
  #279 = Utf8               unknown
  #280 = Utf8               Lcom/fasterxml/jackson/databind/util/TokenBuffer;
  #281 = Class              #487          // com/fasterxml/jackson/databind/deser/impl/PropertyBasedCreator
  #282 = Class              #488          // com/fasterxml/jackson/databind/deser/impl/PropertyValueBuffer
  #283 = Class              #489          // com/fasterxml/jackson/databind/util/TokenBuffer
  #284 = Utf8               _deserialize
  #285 = Utf8               tokens
  #286 = Utf8               _deserializeFromArray
  #287 = Utf8               delegateDeser
  #288 = Utf8               Lcom/fasterxml/jackson/databind/JsonDeserializer;
  #289 = Utf8               act
  #290 = Utf8               Lcom/fasterxml/jackson/databind/cfg/CoercionAction;
  #291 = Utf8               unwrap
  #292 = Utf8               Lcom/fasterxml/jackson/databind/JsonDeserializer<Ljava/lang/Object;>;
  #293 = Class              #490          // com/fasterxml/jackson/databind/JsonDeserializer
  #294 = Class              #491          // com/fasterxml/jackson/databind/cfg/CoercionAction
  #295 = Utf8               deserializeWithView
  #296 = Utf8               (Lcom/fasterxml/jackson/core/JsonParser;Lcom/fasterxml/jackson/databind/DeserializationContext;Ljava/lang/Object;Ljava/lang/Class;)Ljava/lang/Object;
  #297 = Utf8               (Lcom/fasterxml/jackson/core/JsonParser;Lcom/fasterxml/jackson/databind/DeserializationContext;Ljava/lang/Object;Ljava/lang/Class<*>;)Ljava/lang/Object;
  #298 = Utf8               deserializeWithUnwrapped
  #299 = Utf8               deserializeUsingPropertyBasedWithUnwrapped
  #300 = Utf8               (Lcom/fasterxml/jackson/core/JsonParser;Lcom/fasterxml/jackson/databind/DeserializationContext;Ljava/lang/Object;Lcom/fasterxml/jackson/databind/util/TokenBuffer;)Ljava/lang/Object;
  #301 = Utf8               deserializeWithExternalTypeId
  #302 = Utf8               ext
  #303 = Utf8               Lcom/fasterxml/jackson/databind/deser/impl/ExternalTypeHandler;
  #304 = Class              #492          // com/fasterxml/jackson/databind/deser/impl/ExternalTypeHandler
  #305 = Utf8               deserializeUsingPropertyBasedWithExternalTypeId
  #306 = Utf8               SourceFile
  #307 = Utf8               BuilderBasedDeserializer.java
  #308 = NameAndType        #156:#182     // "<init>":(Lcom/fasterxml/jackson/databind/deser/BeanDeserializerBuilder;Lcom/fasterxml/jackson/databind/BeanDescription;Lcom/fasterxml/jackson/databind/JavaType;Lcom/fasterxml/jackson/databind/deser/impl/BeanPropertyMap;Ljava/util/Map;Ljava/util/Set;ZLjava/util/Set;Z)V
  #309 = NameAndType        #156:#493     // "<init>":(Lcom/fasterxml/jackson/databind/deser/BeanDeserializerBuilder;Lcom/fasterxml/jackson/databind/BeanDescription;Lcom/fasterxml/jackson/databind/deser/impl/BeanPropertyMap;Ljava/util/Map;Ljava/util/Set;ZLjava/util/Set;Z)V
  #310 = NameAndType        #154:#155     // _targetType:Lcom/fasterxml/jackson/databind/JavaType;
  #311 = Class              #474          // com/fasterxml/jackson/databind/deser/BeanDeserializerBuilder
  #312 = NameAndType        #494:#495     // getBuildMethod:()Lcom/fasterxml/jackson/databind/introspect/AnnotatedMethod;
  #313 = NameAndType        #152:#153     // _buildMethod:Lcom/fasterxml/jackson/databind/introspect/AnnotatedMethod;
  #314 = NameAndType        #496:#206     // _objectIdReader:Lcom/fasterxml/jackson/databind/deser/impl/ObjectIdReader;
  #315 = Utf8               java/lang/IllegalArgumentException
  #316 = Utf8               java/lang/StringBuilder
  #317 = NameAndType        #156:#497     // "<init>":()V
  #318 = Utf8               Cannot use Object Id with Builder-based deserialization (type
  #319 = NameAndType        #498:#499     // append:(Ljava/lang/String;)Ljava/lang/StringBuilder;
  #320 = Class              #475          // com/fasterxml/jackson/databind/BeanDescription
  #321 = NameAndType        #500:#501     // getType:()Lcom/fasterxml/jackson/databind/JavaType;
  #322 = NameAndType        #498:#502     // append:(Ljava/lang/Object;)Ljava/lang/StringBuilder;
  #323 = Utf8               )
  #324 = NameAndType        #503:#504     // toString:()Ljava/lang/String;
  #325 = NameAndType        #156:#505     // "<init>":(Ljava/lang/String;)V
  #326 = NameAndType        #156:#157     // "<init>":(Lcom/fasterxml/jackson/databind/deser/BeanDeserializerBuilder;Lcom/fasterxml/jackson/databind/BeanDescription;Lcom/fasterxml/jackson/databind/JavaType;Lcom/fasterxml/jackson/databind/deser/impl/BeanPropertyMap;Ljava/util/Map;Ljava/util/Set;ZZ)V
  #327 = NameAndType        #506:#175     // _ignoreAllUnknown:Z
  #328 = NameAndType        #156:#200     // "<init>":(Lcom/fasterxml/jackson/databind/deser/BuilderBasedDeserializer;Z)V
  #329 = NameAndType        #156:#507     // "<init>":(Lcom/fasterxml/jackson/databind/deser/BeanDeserializerBase;Z)V
  #330 = NameAndType        #156:#508     // "<init>":(Lcom/fasterxml/jackson/databind/deser/BeanDeserializerBase;Lcom/fasterxml/jackson/databind/util/NameTransformer;)V
  #331 = NameAndType        #156:#509     // "<init>":(Lcom/fasterxml/jackson/databind/deser/BeanDeserializerBase;Lcom/fasterxml/jackson/databind/deser/impl/ObjectIdReader;)V
  #332 = NameAndType        #510:#173     // _includableProps:Ljava/util/Set;
  #333 = NameAndType        #156:#209     // "<init>":(Lcom/fasterxml/jackson/databind/deser/BuilderBasedDeserializer;Ljava/util/Set;Ljava/util/Set;)V
  #334 = NameAndType        #156:#511     // "<init>":(Lcom/fasterxml/jackson/databind/deser/BeanDeserializerBase;Ljava/util/Set;Ljava/util/Set;)V
  #335 = NameAndType        #156:#512     // "<init>":(Lcom/fasterxml/jackson/databind/deser/BeanDeserializerBase;Lcom/fasterxml/jackson/databind/deser/impl/BeanPropertyMap;)V
  #336 = Utf8               com/fasterxml/jackson/databind/deser/BuilderBasedDeserializer
  #337 = NameAndType        #156:#201     // "<init>":(Lcom/fasterxml/jackson/databind/deser/BuilderBasedDeserializer;Lcom/fasterxml/jackson/databind/util/NameTransformer;)V
  #338 = NameAndType        #156:#204     // "<init>":(Lcom/fasterxml/jackson/databind/deser/BuilderBasedDeserializer;Lcom/fasterxml/jackson/databind/deser/impl/ObjectIdReader;)V
  #339 = NameAndType        #156:#211     // "<init>":(Lcom/fasterxml/jackson/databind/deser/BuilderBasedDeserializer;Lcom/fasterxml/jackson/databind/deser/impl/BeanPropertyMap;)V
  #340 = NameAndType        #513:#169     // _beanProperties:Lcom/fasterxml/jackson/databind/deser/impl/BeanPropertyMap;
  #341 = Class              #477          // com/fasterxml/jackson/databind/deser/impl/BeanPropertyMap
  #342 = NameAndType        #514:#515     // getPropertiesInInsertionOrder:()[Lcom/fasterxml/jackson/databind/deser/SettableBeanProperty;
  #343 = Utf8               com/fasterxml/jackson/databind/deser/impl/BeanAsArrayBuilderDeserializer
  #344 = NameAndType        #156:#516     // "<init>":(Lcom/fasterxml/jackson/databind/deser/BeanDeserializerBase;Lcom/fasterxml/jackson/databind/JavaType;[Lcom/fasterxml/jackson/databind/deser/SettableBeanProperty;Lcom/fasterxml/jackson/databind/introspect/AnnotatedMethod;)V
  #345 = Class              #517          // java/lang/Boolean
  #346 = NameAndType        #518:#519     // FALSE:Ljava/lang/Boolean;
  #347 = Class              #520          // com/fasterxml/jackson/databind/introspect/AnnotatedMethod
  #348 = NameAndType        #521:#522     // getMember:()Ljava/lang/reflect/Method;
  #349 = Utf8               [Ljava/lang/Object;
  #350 = Class              #523          // java/lang/reflect/Method
  #351 = NameAndType        #524:#525     // invoke:(Ljava/lang/Object;[Ljava/lang/Object;)Ljava/lang/Object;
  #352 = Utf8               java/lang/Exception
  #353 = NameAndType        #526:#527     // wrapInstantiationProblem:(Ljava/lang/Throwable;Lcom/fasterxml/jackson/databind/DeserializationContext;)Ljava/lang/Object;
  #354 = Class              #483          // com/fasterxml/jackson/core/JsonParser
  #355 = NameAndType        #528:#529     // isExpectedStartObjectToken:()Z
  #356 = NameAndType        #530:#531     // nextToken:()Lcom/fasterxml/jackson/core/JsonToken;
  #357 = NameAndType        #532:#175     // _vanillaProcessing:Z
  #358 = NameAndType        #258:#259     // vanillaDeserialize:(Lcom/fasterxml/jackson/core/JsonParser;Lcom/fasterxml/jackson/databind/DeserializationContext;Lcom/fasterxml/jackson/core/JsonToken;)Ljava/lang/Object;
  #359 = NameAndType        #233:#234     // finishBuild:(Lcom/fasterxml/jackson/databind/DeserializationContext;Ljava/lang/Object;)Ljava/lang/Object;
  #360 = NameAndType        #270:#244     // deserializeFromObject:(Lcom/fasterxml/jackson/core/JsonParser;Lcom/fasterxml/jackson/databind/DeserializationContext;)Ljava/lang/Object;
  #361 = NameAndType        #533:#534     // currentTokenId:()I
  #362 = NameAndType        #535:#244     // deserializeFromString:(Lcom/fasterxml/jackson/core/JsonParser;Lcom/fasterxml/jackson/databind/DeserializationContext;)Ljava/lang/Object;
  #363 = NameAndType        #536:#244     // deserializeFromNumber:(Lcom/fasterxml/jackson/core/JsonParser;Lcom/fasterxml/jackson/databind/DeserializationContext;)Ljava/lang/Object;
  #364 = NameAndType        #537:#244     // deserializeFromDouble:(Lcom/fasterxml/jackson/core/JsonParser;Lcom/fasterxml/jackson/databind/DeserializationContext;)Ljava/lang/Object;
  #365 = NameAndType        #538:#539     // getEmbeddedObject:()Ljava/lang/Object;
  #366 = NameAndType        #540:#244     // deserializeFromBoolean:(Lcom/fasterxml/jackson/core/JsonParser;Lcom/fasterxml/jackson/databind/DeserializationContext;)Ljava/lang/Object;
  #367 = NameAndType        #286:#244     // _deserializeFromArray:(Lcom/fasterxml/jackson/core/JsonParser;Lcom/fasterxml/jackson/databind/DeserializationContext;)Ljava/lang/Object;
  #368 = NameAndType        #541:#542     // getValueType:(Lcom/fasterxml/jackson/databind/DeserializationContext;)Lcom/fasterxml/jackson/databind/JavaType;
  #369 = Class              #484          // com/fasterxml/jackson/databind/DeserializationContext
  #370 = NameAndType        #543:#544     // handleUnexpectedToken:(Lcom/fasterxml/jackson/databind/JavaType;Lcom/fasterxml/jackson/core/JsonParser;)Ljava/lang/Object;
  #371 = NameAndType        #545:#546     // handledType:()Ljava/lang/Class;
  #372 = NameAndType        #547:#546     // getClass:()Ljava/lang/Class;
  #373 = Class              #482          // java/lang/Class
  #374 = NameAndType        #548:#549     // isAssignableFrom:(Ljava/lang/Class;)Z
  #375 = Utf8               Deserialization of %s by passing existing Builder (%s) instance not supported
  #376 = Utf8               java/lang/Object
  #377 = NameAndType        #550:#504     // getName:()Ljava/lang/String;
  #378 = Class              #485          // java/lang/String
  #379 = NameAndType        #551:#552     // format:(Ljava/lang/String;[Ljava/lang/Object;)Ljava/lang/String;
  #380 = NameAndType        #553:#554     // reportBadDefinition:(Lcom/fasterxml/jackson/databind/JavaType;Ljava/lang/String;)Ljava/lang/Object;
  #381 = Utf8               Deserialization of %s by passing existing instance (of %s) not supported
  #382 = NameAndType        #555:#556     // _valueInstantiator:Lcom/fasterxml/jackson/databind/deser/ValueInstantiator;
  #383 = Class              #557          // com/fasterxml/jackson/databind/deser/ValueInstantiator
  #384 = NameAndType        #558:#559     // createUsingDefault:(Lcom/fasterxml/jackson/databind/DeserializationContext;)Ljava/lang/Object;
  #385 = NameAndType        #560:#531     // currentToken:()Lcom/fasterxml/jackson/core/JsonToken;
  #386 = Class              #481          // com/fasterxml/jackson/core/JsonToken
  #387 = NameAndType        #561:#246     // FIELD_NAME:Lcom/fasterxml/jackson/core/JsonToken;
  #388 = NameAndType        #562:#504     // currentName:()Ljava/lang/String;
  #389 = NameAndType        #563:#564     // find:(Ljava/lang/String;)Lcom/fasterxml/jackson/databind/deser/SettableBeanProperty;
  #390 = Class              #486          // com/fasterxml/jackson/databind/deser/SettableBeanProperty
  #391 = NameAndType        #565:#250     // deserializeSetAndReturn:(Lcom/fasterxml/jackson/core/JsonParser;Lcom/fasterxml/jackson/databind/DeserializationContext;Ljava/lang/Object;)Ljava/lang/Object;
  #392 = NameAndType        #566:#567     // wrapAndThrow:(Ljava/lang/Throwable;Ljava/lang/Object;Ljava/lang/String;Lcom/fasterxml/jackson/databind/DeserializationContext;)V
  #393 = NameAndType        #568:#569     // handleUnknownVanilla:(Lcom/fasterxml/jackson/core/JsonParser;Lcom/fasterxml/jackson/databind/DeserializationContext;Ljava/lang/Object;Ljava/lang/String;)V
  #394 = NameAndType        #570:#175     // _nonStandardCreation:Z
  #395 = NameAndType        #571:#572     // _unwrappedPropertyHandler:Lcom/fasterxml/jackson/databind/deser/impl/UnwrappedPropertyHandler;
  #396 = NameAndType        #298:#244     // deserializeWithUnwrapped:(Lcom/fasterxml/jackson/core/JsonParser;Lcom/fasterxml/jackson/databind/DeserializationContext;)Ljava/lang/Object;
  #397 = NameAndType        #573:#303     // _externalTypeIdHandler:Lcom/fasterxml/jackson/databind/deser/impl/ExternalTypeHandler;
  #398 = NameAndType        #301:#244     // deserializeWithExternalTypeId:(Lcom/fasterxml/jackson/core/JsonParser;Lcom/fasterxml/jackson/databind/DeserializationContext;)Ljava/lang/Object;
  #399 = NameAndType        #574:#244     // deserializeFromObjectUsingNonDefault:(Lcom/fasterxml/jackson/core/JsonParser;Lcom/fasterxml/jackson/databind/DeserializationContext;)Ljava/lang/Object;
  #400 = NameAndType        #575:#576     // _injectables:[Lcom/fasterxml/jackson/databind/deser/impl/ValueInjector;
  #401 = NameAndType        #577:#578     // injectValues:(Lcom/fasterxml/jackson/databind/DeserializationContext;Ljava/lang/Object;)V
  #402 = NameAndType        #579:#175     // _needViewProcesing:Z
  #403 = NameAndType        #580:#546     // getActiveView:()Ljava/lang/Class;
  #404 = NameAndType        #295:#296     // deserializeWithView:(Lcom/fasterxml/jackson/core/JsonParser;Lcom/fasterxml/jackson/databind/DeserializationContext;Ljava/lang/Object;Ljava/lang/Class;)Ljava/lang/Object;
  #405 = NameAndType        #581:#275     // _propertyBasedCreator:Lcom/fasterxml/jackson/databind/deser/impl/PropertyBasedCreator;
  #406 = Class              #487          // com/fasterxml/jackson/databind/deser/impl/PropertyBasedCreator
  #407 = NameAndType        #582:#583     // startBuilding:(Lcom/fasterxml/jackson/core/JsonParser;Lcom/fasterxml/jackson/databind/DeserializationContext;Lcom/fasterxml/jackson/databind/deser/impl/ObjectIdReader;)Lcom/fasterxml/jackson/databind/deser/impl/PropertyValueBuffer;
  #408 = NameAndType        #584:#564     // findCreatorProperty:(Ljava/lang/String;)Lcom/fasterxml/jackson/databind/deser/SettableBeanProperty;
  #409 = Class              #488          // com/fasterxml/jackson/databind/deser/impl/PropertyValueBuffer
  #410 = NameAndType        #585:#586     // readIdProperty:(Ljava/lang/String;)Z
  #411 = NameAndType        #587:#549     // visibleInView:(Ljava/lang/Class;)Z
  #412 = NameAndType        #588:#589     // skipChildren:()Lcom/fasterxml/jackson/core/JsonParser;
  #413 = NameAndType        #243:#244     // deserialize:(Lcom/fasterxml/jackson/core/JsonParser;Lcom/fasterxml/jackson/databind/DeserializationContext;)Ljava/lang/Object;
  #414 = NameAndType        #590:#591     // assignParameter:(Lcom/fasterxml/jackson/databind/deser/SettableBeanProperty;Ljava/lang/Object;)Z
  #415 = NameAndType        #592:#593     // build:(Lcom/fasterxml/jackson/databind/DeserializationContext;Lcom/fasterxml/jackson/databind/deser/impl/PropertyValueBuffer;)Ljava/lang/Object;
  #416 = NameAndType        #594:#155     // _beanType:Lcom/fasterxml/jackson/databind/JavaType;
  #417 = Class              #476          // com/fasterxml/jackson/databind/JavaType
  #418 = NameAndType        #595:#546     // getRawClass:()Ljava/lang/Class;
  #419 = NameAndType        #596:#300     // handlePolymorphic:(Lcom/fasterxml/jackson/core/JsonParser;Lcom/fasterxml/jackson/databind/DeserializationContext;Ljava/lang/Object;Lcom/fasterxml/jackson/databind/util/TokenBuffer;)Ljava/lang/Object;
  #420 = NameAndType        #597:#598     // handleUnknownProperties:(Lcom/fasterxml/jackson/databind/DeserializationContext;Ljava/lang/Object;Lcom/fasterxml/jackson/databind/util/TokenBuffer;)Ljava/lang/Object;
  #421 = NameAndType        #284:#250     // _deserialize:(Lcom/fasterxml/jackson/core/JsonParser;Lcom/fasterxml/jackson/databind/DeserializationContext;Ljava/lang/Object;)Ljava/lang/Object;
  #422 = NameAndType        #599:#600     // bufferProperty:(Lcom/fasterxml/jackson/databind/deser/SettableBeanProperty;Ljava/lang/Object;)V
  #423 = NameAndType        #601:#173     // _ignorableProps:Ljava/util/Set;
  #424 = Class              #602          // com/fasterxml/jackson/databind/util/IgnorePropertiesUtil
  #425 = NameAndType        #603:#604     // shouldIgnore:(Ljava/lang/Object;Ljava/util/Collection;Ljava/util/Collection;)Z
  #426 = NameAndType        #605:#569     // handleIgnoredProperty:(Lcom/fasterxml/jackson/core/JsonParser;Lcom/fasterxml/jackson/databind/DeserializationContext;Ljava/lang/Object;Ljava/lang/String;)V
  #427 = NameAndType        #606:#607     // _anySetter:Lcom/fasterxml/jackson/databind/deser/SettableAnyProperty;
  #428 = Class              #608          // com/fasterxml/jackson/databind/deser/SettableAnyProperty
  #429 = NameAndType        #609:#610     // bufferAnyProperty:(Lcom/fasterxml/jackson/databind/deser/SettableAnyProperty;Ljava/lang/String;Ljava/lang/Object;)V
  #430 = NameAndType        #611:#612     // bufferForInputBuffering:(Lcom/fasterxml/jackson/core/JsonParser;)Lcom/fasterxml/jackson/databind/util/TokenBuffer;
  #431 = Class              #489          // com/fasterxml/jackson/databind/util/TokenBuffer
  #432 = NameAndType        #613:#505     // writeFieldName:(Ljava/lang/String;)V
  #433 = NameAndType        #614:#615     // copyCurrentStructure:(Lcom/fasterxml/jackson/core/JsonParser;)V
  #434 = NameAndType        #616:#246     // START_OBJECT:Lcom/fasterxml/jackson/core/JsonToken;
  #435 = NameAndType        #617:#618     // hasToken:(Lcom/fasterxml/jackson/core/JsonToken;)Z
  #436 = NameAndType        #619:#497     // writeStartObject:()V
  #437 = NameAndType        #298:#300     // deserializeWithUnwrapped:(Lcom/fasterxml/jackson/core/JsonParser;Lcom/fasterxml/jackson/databind/DeserializationContext;Ljava/lang/Object;Lcom/fasterxml/jackson/databind/util/TokenBuffer;)Ljava/lang/Object;
  #438 = NameAndType        #301:#250     // deserializeWithExternalTypeId:(Lcom/fasterxml/jackson/core/JsonParser;Lcom/fasterxml/jackson/databind/DeserializationContext;Ljava/lang/Object;)Ljava/lang/Object;
  #439 = NameAndType        #620:#288     // _arrayDelegateDeserializer:Lcom/fasterxml/jackson/databind/JsonDeserializer;
  #440 = NameAndType        #621:#288     // _delegateDeserializer:Lcom/fasterxml/jackson/databind/JsonDeserializer;
  #441 = Class              #490          // com/fasterxml/jackson/databind/JsonDeserializer
  #442 = NameAndType        #622:#234     // createUsingArrayDelegate:(Lcom/fasterxml/jackson/databind/DeserializationContext;Ljava/lang/Object;)Ljava/lang/Object;
  #443 = NameAndType        #623:#624     // _findCoercionFromEmptyArray:(Lcom/fasterxml/jackson/databind/DeserializationContext;)Lcom/fasterxml/jackson/databind/cfg/CoercionAction;
  #444 = Class              #625          // com/fasterxml/jackson/databind/DeserializationFeature
  #445 = NameAndType        #626:#627     // UNWRAP_SINGLE_VALUE_ARRAYS:Lcom/fasterxml/jackson/databind/DeserializationFeature;
  #446 = NameAndType        #628:#629     // isEnabled:(Lcom/fasterxml/jackson/databind/DeserializationFeature;)Z
  #447 = Class              #491          // com/fasterxml/jackson/databind/cfg/CoercionAction
  #448 = NameAndType        #630:#290     // Fail:Lcom/fasterxml/jackson/databind/cfg/CoercionAction;
  #449 = NameAndType        #631:#246     // END_ARRAY:Lcom/fasterxml/jackson/core/JsonToken;
  #450 = NameAndType        #632:#633     // $SwitchMap$com$fasterxml$jackson$databind$cfg$CoercionAction:[I
  #451 = NameAndType        #634:#534     // ordinal:()I
  #452 = NameAndType        #635:#559     // getEmptyValue:(Lcom/fasterxml/jackson/databind/DeserializationContext;)Ljava/lang/Object;
  #453 = NameAndType        #636:#559     // getNullValue:(Lcom/fasterxml/jackson/databind/DeserializationContext;)Ljava/lang/Object;
  #454 = NameAndType        #637:#246     // START_ARRAY:Lcom/fasterxml/jackson/core/JsonToken;
  #455 = NameAndType        #543:#638     // handleUnexpectedToken:(Lcom/fasterxml/jackson/databind/JavaType;Lcom/fasterxml/jackson/core/JsonToken;Lcom/fasterxml/jackson/core/JsonParser;Ljava/lang/String;[Ljava/lang/Object;)Ljava/lang/Object;
  #456 = NameAndType        #639:#640     // handleMissingEndArrayForSingle:(Lcom/fasterxml/jackson/core/JsonParser;Lcom/fasterxml/jackson/databind/DeserializationContext;)V
  #457 = NameAndType        #641:#234     // createUsingDelegate:(Lcom/fasterxml/jackson/databind/DeserializationContext;Ljava/lang/Object;)Ljava/lang/Object;
  #458 = NameAndType        #299:#244     // deserializeUsingPropertyBasedWithUnwrapped:(Lcom/fasterxml/jackson/core/JsonParser;Lcom/fasterxml/jackson/databind/DeserializationContext;)Ljava/lang/Object;
  #459 = NameAndType        #642:#569     // deserializeAndSet:(Lcom/fasterxml/jackson/core/JsonParser;Lcom/fasterxml/jackson/databind/DeserializationContext;Ljava/lang/Object;Ljava/lang/String;)V
  #460 = NameAndType        #643:#497     // writeEndObject:()V
  #461 = Class              #644          // com/fasterxml/jackson/databind/deser/impl/UnwrappedPropertyHandler
  #462 = NameAndType        #645:#300     // processUnwrapped:(Lcom/fasterxml/jackson/core/JsonParser;Lcom/fasterxml/jackson/databind/DeserializationContext;Ljava/lang/Object;Lcom/fasterxml/jackson/databind/util/TokenBuffer;)Ljava/lang/Object;
  #463 = NameAndType        #305:#244     // deserializeUsingPropertyBasedWithExternalTypeId:(Lcom/fasterxml/jackson/core/JsonParser;Lcom/fasterxml/jackson/databind/DeserializationContext;)Ljava/lang/Object;
  #464 = Class              #492          // com/fasterxml/jackson/databind/deser/impl/ExternalTypeHandler
  #465 = NameAndType        #646:#647     // start:()Lcom/fasterxml/jackson/databind/deser/impl/ExternalTypeHandler;
  #466 = NameAndType        #648:#529     // isScalarValue:()Z
  #467 = NameAndType        #649:#650     // handleTypePropertyValue:(Lcom/fasterxml/jackson/core/JsonParser;Lcom/fasterxml/jackson/databind/DeserializationContext;Ljava/lang/String;Ljava/lang/Object;)Z
  #468 = NameAndType        #651:#650     // handlePropertyValue:(Lcom/fasterxml/jackson/core/JsonParser;Lcom/fasterxml/jackson/databind/DeserializationContext;Ljava/lang/String;Ljava/lang/Object;)Z
  #469 = NameAndType        #652:#569     // handleUnknownProperty:(Lcom/fasterxml/jackson/core/JsonParser;Lcom/fasterxml/jackson/databind/DeserializationContext;Ljava/lang/Object;Ljava/lang/String;)V
  #470 = NameAndType        #653:#250     // complete:(Lcom/fasterxml/jackson/core/JsonParser;Lcom/fasterxml/jackson/databind/DeserializationContext;Ljava/lang/Object;)Ljava/lang/Object;
  #471 = Utf8               Deserialization (of %s) with Builder, External type id, @JsonCreator not yet implemented
  #472 = Utf8               com/fasterxml/jackson/databind/deser/BeanDeserializerBase
  #473 = Utf8               com/fasterxml/jackson/databind/deser/BuilderBasedDeserializer$1
  #474 = Utf8               com/fasterxml/jackson/databind/deser/BeanDeserializerBuilder
  #475 = Utf8               com/fasterxml/jackson/databind/BeanDescription
  #476 = Utf8               com/fasterxml/jackson/databind/JavaType
  #477 = Utf8               com/fasterxml/jackson/databind/deser/impl/BeanPropertyMap
  #478 = Utf8               java/util/Map
  #479 = Utf8               java/util/Set
  #480 = Utf8               java/io/IOException
  #481 = Utf8               com/fasterxml/jackson/core/JsonToken
  #482 = Utf8               java/lang/Class
  #483 = Utf8               com/fasterxml/jackson/core/JsonParser
  #484 = Utf8               com/fasterxml/jackson/databind/DeserializationContext
  #485 = Utf8               java/lang/String
  #486 = Utf8               com/fasterxml/jackson/databind/deser/SettableBeanProperty
  #487 = Utf8               com/fasterxml/jackson/databind/deser/impl/PropertyBasedCreator
  #488 = Utf8               com/fasterxml/jackson/databind/deser/impl/PropertyValueBuffer
  #489 = Utf8               com/fasterxml/jackson/databind/util/TokenBuffer
  #490 = Utf8               com/fasterxml/jackson/databind/JsonDeserializer
  #491 = Utf8               com/fasterxml/jackson/databind/cfg/CoercionAction
  #492 = Utf8               com/fasterxml/jackson/databind/deser/impl/ExternalTypeHandler
  #493 = Utf8               (Lcom/fasterxml/jackson/databind/deser/BeanDeserializerBuilder;Lcom/fasterxml/jackson/databind/BeanDescription;Lcom/fasterxml/jackson/databind/deser/impl/BeanPropertyMap;Ljava/util/Map;Ljava/util/Set;ZLjava/util/Set;Z)V
  #494 = Utf8               getBuildMethod
  #495 = Utf8               ()Lcom/fasterxml/jackson/databind/introspect/AnnotatedMethod;
  #496 = Utf8               _objectIdReader
  #497 = Utf8               ()V
  #498 = Utf8               append
  #499 = Utf8               (Ljava/lang/String;)Ljava/lang/StringBuilder;
  #500 = Utf8               getType
  #501 = Utf8               ()Lcom/fasterxml/jackson/databind/JavaType;
  #502 = Utf8               (Ljava/lang/Object;)Ljava/lang/StringBuilder;
  #503 = Utf8               toString
  #504 = Utf8               ()Ljava/lang/String;
  #505 = Utf8               (Ljava/lang/String;)V
  #506 = Utf8               _ignoreAllUnknown
  #507 = Utf8               (Lcom/fasterxml/jackson/databind/deser/BeanDeserializerBase;Z)V
  #508 = Utf8               (Lcom/fasterxml/jackson/databind/deser/BeanDeserializerBase;Lcom/fasterxml/jackson/databind/util/NameTransformer;)V
  #509 = Utf8               (Lcom/fasterxml/jackson/databind/deser/BeanDeserializerBase;Lcom/fasterxml/jackson/databind/deser/impl/ObjectIdReader;)V
  #510 = Utf8               _includableProps
  #511 = Utf8               (Lcom/fasterxml/jackson/databind/deser/BeanDeserializerBase;Ljava/util/Set;Ljava/util/Set;)V
  #512 = Utf8               (Lcom/fasterxml/jackson/databind/deser/BeanDeserializerBase;Lcom/fasterxml/jackson/databind/deser/impl/BeanPropertyMap;)V
  #513 = Utf8               _beanProperties
  #514 = Utf8               getPropertiesInInsertionOrder
  #515 = Utf8               ()[Lcom/fasterxml/jackson/databind/deser/SettableBeanProperty;
  #516 = Utf8               (Lcom/fasterxml/jackson/databind/deser/BeanDeserializerBase;Lcom/fasterxml/jackson/databind/JavaType;[Lcom/fasterxml/jackson/databind/deser/SettableBeanProperty;Lcom/fasterxml/jackson/databind/introspect/AnnotatedMethod;)V
  #517 = Utf8               java/lang/Boolean
  #518 = Utf8               FALSE
  #519 = Utf8               Ljava/lang/Boolean;
  #520 = Utf8               com/fasterxml/jackson/databind/introspect/AnnotatedMethod
  #521 = Utf8               getMember
  #522 = Utf8               ()Ljava/lang/reflect/Method;
  #523 = Utf8               java/lang/reflect/Method
  #524 = Utf8               invoke
  #525 = Utf8               (Ljava/lang/Object;[Ljava/lang/Object;)Ljava/lang/Object;
  #526 = Utf8               wrapInstantiationProblem
  #527 = Utf8               (Ljava/lang/Throwable;Lcom/fasterxml/jackson/databind/DeserializationContext;)Ljava/lang/Object;
  #528 = Utf8               isExpectedStartObjectToken
  #529 = Utf8               ()Z
  #530 = Utf8               nextToken
  #531 = Utf8               ()Lcom/fasterxml/jackson/core/JsonToken;
  #532 = Utf8               _vanillaProcessing
  #533 = Utf8               currentTokenId
  #534 = Utf8               ()I
  #535 = Utf8               deserializeFromString
  #536 = Utf8               deserializeFromNumber
  #537 = Utf8               deserializeFromDouble
  #538 = Utf8               getEmbeddedObject
  #539 = Utf8               ()Ljava/lang/Object;
  #540 = Utf8               deserializeFromBoolean
  #541 = Utf8               getValueType
  #542 = Utf8               (Lcom/fasterxml/jackson/databind/DeserializationContext;)Lcom/fasterxml/jackson/databind/JavaType;
  #543 = Utf8               handleUnexpectedToken
  #544 = Utf8               (Lcom/fasterxml/jackson/databind/JavaType;Lcom/fasterxml/jackson/core/JsonParser;)Ljava/lang/Object;
  #545 = Utf8               handledType
  #546 = Utf8               ()Ljava/lang/Class;
  #547 = Utf8               getClass
  #548 = Utf8               isAssignableFrom
  #549 = Utf8               (Ljava/lang/Class;)Z
  #550 = Utf8               getName
  #551 = Utf8               format
  #552 = Utf8               (Ljava/lang/String;[Ljava/lang/Object;)Ljava/lang/String;
  #553 = Utf8               reportBadDefinition
  #554 = Utf8               (Lcom/fasterxml/jackson/databind/JavaType;Ljava/lang/String;)Ljava/lang/Object;
  #555 = Utf8               _valueInstantiator
  #556 = Utf8               Lcom/fasterxml/jackson/databind/deser/ValueInstantiator;
  #557 = Utf8               com/fasterxml/jackson/databind/deser/ValueInstantiator
  #558 = Utf8               createUsingDefault
  #559 = Utf8               (Lcom/fasterxml/jackson/databind/DeserializationContext;)Ljava/lang/Object;
  #560 = Utf8               currentToken
  #561 = Utf8               FIELD_NAME
  #562 = Utf8               currentName
  #563 = Utf8               find
  #564 = Utf8               (Ljava/lang/String;)Lcom/fasterxml/jackson/databind/deser/SettableBeanProperty;
  #565 = Utf8               deserializeSetAndReturn
  #566 = Utf8               wrapAndThrow
  #567 = Utf8               (Ljava/lang/Throwable;Ljava/lang/Object;Ljava/lang/String;Lcom/fasterxml/jackson/databind/DeserializationContext;)V
  #568 = Utf8               handleUnknownVanilla
  #569 = Utf8               (Lcom/fasterxml/jackson/core/JsonParser;Lcom/fasterxml/jackson/databind/DeserializationContext;Ljava/lang/Object;Ljava/lang/String;)V
  #570 = Utf8               _nonStandardCreation
  #571 = Utf8               _unwrappedPropertyHandler
  #572 = Utf8               Lcom/fasterxml/jackson/databind/deser/impl/UnwrappedPropertyHandler;
  #573 = Utf8               _externalTypeIdHandler
  #574 = Utf8               deserializeFromObjectUsingNonDefault
  #575 = Utf8               _injectables
  #576 = Utf8               [Lcom/fasterxml/jackson/databind/deser/impl/ValueInjector;
  #577 = Utf8               injectValues
  #578 = Utf8               (Lcom/fasterxml/jackson/databind/DeserializationContext;Ljava/lang/Object;)V
  #579 = Utf8               _needViewProcesing
  #580 = Utf8               getActiveView
  #581 = Utf8               _propertyBasedCreator
  #582 = Utf8               startBuilding
  #583 = Utf8               (Lcom/fasterxml/jackson/core/JsonParser;Lcom/fasterxml/jackson/databind/DeserializationContext;Lcom/fasterxml/jackson/databind/deser/impl/ObjectIdReader;)Lcom/fasterxml/jackson/databind/deser/impl/PropertyValueBuffer;
  #584 = Utf8               findCreatorProperty
  #585 = Utf8               readIdProperty
  #586 = Utf8               (Ljava/lang/String;)Z
  #587 = Utf8               visibleInView
  #588 = Utf8               skipChildren
  #589 = Utf8               ()Lcom/fasterxml/jackson/core/JsonParser;
  #590 = Utf8               assignParameter
  #591 = Utf8               (Lcom/fasterxml/jackson/databind/deser/SettableBeanProperty;Ljava/lang/Object;)Z
  #592 = Utf8               build
  #593 = Utf8               (Lcom/fasterxml/jackson/databind/DeserializationContext;Lcom/fasterxml/jackson/databind/deser/impl/PropertyValueBuffer;)Ljava/lang/Object;
  #594 = Utf8               _beanType
  #595 = Utf8               getRawClass
  #596 = Utf8               handlePolymorphic
  #597 = Utf8               handleUnknownProperties
  #598 = Utf8               (Lcom/fasterxml/jackson/databind/DeserializationContext;Ljava/lang/Object;Lcom/fasterxml/jackson/databind/util/TokenBuffer;)Ljava/lang/Object;
  #599 = Utf8               bufferProperty
  #600 = Utf8               (Lcom/fasterxml/jackson/databind/deser/SettableBeanProperty;Ljava/lang/Object;)V
  #601 = Utf8               _ignorableProps
  #602 = Utf8               com/fasterxml/jackson/databind/util/IgnorePropertiesUtil
  #603 = Utf8               shouldIgnore
  #604 = Utf8               (Ljava/lang/Object;Ljava/util/Collection;Ljava/util/Collection;)Z
  #605 = Utf8               handleIgnoredProperty
  #606 = Utf8               _anySetter
  #607 = Utf8               Lcom/fasterxml/jackson/databind/deser/SettableAnyProperty;
  #608 = Utf8               com/fasterxml/jackson/databind/deser/SettableAnyProperty
  #609 = Utf8               bufferAnyProperty
  #610 = Utf8               (Lcom/fasterxml/jackson/databind/deser/SettableAnyProperty;Ljava/lang/String;Ljava/lang/Object;)V
  #611 = Utf8               bufferForInputBuffering
  #612 = Utf8               (Lcom/fasterxml/jackson/core/JsonParser;)Lcom/fasterxml/jackson/databind/util/TokenBuffer;
  #613 = Utf8               writeFieldName
  #614 = Utf8               copyCurrentStructure
  #615 = Utf8               (Lcom/fasterxml/jackson/core/JsonParser;)V
  #616 = Utf8               START_OBJECT
  #617 = Utf8               hasToken
  #618 = Utf8               (Lcom/fasterxml/jackson/core/JsonToken;)Z
  #619 = Utf8               writeStartObject
  #620 = Utf8               _arrayDelegateDeserializer
  #621 = Utf8               _delegateDeserializer
  #622 = Utf8               createUsingArrayDelegate
  #623 = Utf8               _findCoercionFromEmptyArray
  #624 = Utf8               (Lcom/fasterxml/jackson/databind/DeserializationContext;)Lcom/fasterxml/jackson/databind/cfg/CoercionAction;
  #625 = Utf8               com/fasterxml/jackson/databind/DeserializationFeature
  #626 = Utf8               UNWRAP_SINGLE_VALUE_ARRAYS
  #627 = Utf8               Lcom/fasterxml/jackson/databind/DeserializationFeature;
  #628 = Utf8               isEnabled
  #629 = Utf8               (Lcom/fasterxml/jackson/databind/DeserializationFeature;)Z
  #630 = Utf8               Fail
  #631 = Utf8               END_ARRAY
  #632 = Utf8               $SwitchMap$com$fasterxml$jackson$databind$cfg$CoercionAction
  #633 = Utf8               [I
  #634 = Utf8               ordinal
  #635 = Utf8               getEmptyValue
  #636 = Utf8               getNullValue
  #637 = Utf8               START_ARRAY
  #638 = Utf8               (Lcom/fasterxml/jackson/databind/JavaType;Lcom/fasterxml/jackson/core/JsonToken;Lcom/fasterxml/jackson/core/JsonParser;Ljava/lang/String;[Ljava/lang/Object;)Ljava/lang/Object;
  #639 = Utf8               handleMissingEndArrayForSingle
  #640 = Utf8               (Lcom/fasterxml/jackson/core/JsonParser;Lcom/fasterxml/jackson/databind/DeserializationContext;)V
  #641 = Utf8               createUsingDelegate
  #642 = Utf8               deserializeAndSet
  #643 = Utf8               writeEndObject
  #644 = Utf8               com/fasterxml/jackson/databind/deser/impl/UnwrappedPropertyHandler
  #645 = Utf8               processUnwrapped
  #646 = Utf8               start
  #647 = Utf8               ()Lcom/fasterxml/jackson/databind/deser/impl/ExternalTypeHandler;
  #648 = Utf8               isScalarValue
  #649 = Utf8               handleTypePropertyValue
  #650 = Utf8               (Lcom/fasterxml/jackson/core/JsonParser;Lcom/fasterxml/jackson/databind/DeserializationContext;Ljava/lang/String;Ljava/lang/Object;)Z
  #651 = Utf8               handlePropertyValue
  #652 = Utf8               handleUnknownProperty
  #653 = Utf8               complete
{
  private static final long serialVersionUID;
    descriptor: J
    flags: (0x001a) ACC_PRIVATE, ACC_STATIC, ACC_FINAL
    ConstantValue: long 1l

  protected final com.fasterxml.jackson.databind.introspect.AnnotatedMethod _buildMethod;
    descriptor: Lcom/fasterxml/jackson/databind/introspect/AnnotatedMethod;
    flags: (0x0014) ACC_PROTECTED, ACC_FINAL

  protected final com.fasterxml.jackson.databind.JavaType _targetType;
    descriptor: Lcom/fasterxml/jackson/databind/JavaType;
    flags: (0x0014) ACC_PROTECTED, ACC_FINAL

  public com.fasterxml.jackson.databind.deser.BuilderBasedDeserializer(com.fasterxml.jackson.databind.deser.BeanDeserializerBuilder, com.fasterxml.jackson.databind.BeanDescription, com.fasterxml.jackson.databind.JavaType, com.fasterxml.jackson.databind.deser.impl.BeanPropertyMap, java.util.Map<java.lang.String, com.fasterxml.jackson.databind.deser.SettableBeanProperty>, java.util.Set<java.lang.String>, boolean, boolean);
    descriptor: (Lcom/fasterxml/jackson/databind/deser/BeanDeserializerBuilder;Lcom/fasterxml/jackson/databind/BeanDescription;Lcom/fasterxml/jackson/databind/JavaType;Lcom/fasterxml/jackson/databind/deser/impl/BeanPropertyMap;Ljava/util/Map;Ljava/util/Set;ZZ)V
    flags: (0x0001) ACC_PUBLIC
    Code:
      stack=10, locals=9, args_size=9
         0: aload_0
         1: aload_1
         2: aload_2
         3: aload_3
         4: aload         4
         6: aload         5
         8: aload         6
        10: iload         7
        12: aconst_null
        13: iload         8
        15: invokespecial #1                  // Method "<init>":(Lcom/fasterxml/jackson/databind/deser/BeanDeserializerBuilder;Lcom/fasterxml/jackson/databind/BeanDescription;Lcom/fasterxml/jackson/databind/JavaType;Lcom/fasterxml/jackson/databind/deser/impl/BeanPropertyMap;Ljava/util/Map;Ljava/util/Set;ZLjava/util/Set;Z)V
        18: return
      LineNumberTable:
        line 55: 0
        line 56: 18
      LocalVariableTable:
        Start  Length  Slot  Name   Signature
            0      19     0  this   Lcom/fasterxml/jackson/databind/deser/BuilderBasedDeserializer;
            0      19     1 builder   Lcom/fasterxml/jackson/databind/deser/BeanDeserializerBuilder;
            0      19     2 beanDesc   Lcom/fasterxml/jackson/databind/BeanDescription;
            0      19     3 targetType   Lcom/fasterxml/jackson/databind/JavaType;
            0      19     4 properties   Lcom/fasterxml/jackson/databind/deser/impl/BeanPropertyMap;
            0      19     5 backRefs   Ljava/util/Map;
            0      19     6 ignorableProps   Ljava/util/Set;
            0      19     7 ignoreAllUnknown   Z
            0      19     8 hasViews   Z
      LocalVariableTypeTable:
        Start  Length  Slot  Name   Signature
            0      19     5 backRefs   Ljava/util/Map<Ljava/lang/String;Lcom/fasterxml/jackson/databind/deser/SettableBeanProperty;>;
            0      19     6 ignorableProps   Ljava/util/Set<Ljava/lang/String;>;
    Signature: #181                         // (Lcom/fasterxml/jackson/databind/deser/BeanDeserializerBuilder;Lcom/fasterxml/jackson/databind/BeanDescription;Lcom/fasterxml/jackson/databind/JavaType;Lcom/fasterxml/jackson/databind/deser/impl/BeanPropertyMap;Ljava/util/Map<Ljava/lang/String;Lcom/fasterxml/jackson/databind/deser/SettableBeanProperty;>;Ljava/util/Set<Ljava/lang/String;>;ZZ)V

  public com.fasterxml.jackson.databind.deser.BuilderBasedDeserializer(com.fasterxml.jackson.databind.deser.BeanDeserializerBuilder, com.fasterxml.jackson.databind.BeanDescription, com.fasterxml.jackson.databind.JavaType, com.fasterxml.jackson.databind.deser.impl.BeanPropertyMap, java.util.Map<java.lang.String, com.fasterxml.jackson.databind.deser.SettableBeanProperty>, java.util.Set<java.lang.String>, boolean, java.util.Set<java.lang.String>, boolean);
    descriptor: (Lcom/fasterxml/jackson/databind/deser/BeanDeserializerBuilder;Lcom/fasterxml/jackson/databind/BeanDescription;Lcom/fasterxml/jackson/databind/JavaType;Lcom/fasterxml/jackson/databind/deser/impl/BeanPropertyMap;Ljava/util/Map;Ljava/util/Set;ZLjava/util/Set;Z)V
    flags: (0x0001) ACC_PUBLIC
    Code:
      stack=9, locals=10, args_size=10
         0: aload_0
         1: aload_1
         2: aload_2
         3: aload         4
         5: aload         5
         7: aload         6
         9: iload         7
        11: aload         8
        13: iload         9
        15: invokespecial #2                  // Method com/fasterxml/jackson/databind/deser/BeanDeserializerBase."<init>":(Lcom/fasterxml/jackson/databind/deser/BeanDeserializerBuilder;Lcom/fasterxml/jackson/databind/BeanDescription;Lcom/fasterxml/jackson/databind/deser/impl/BeanPropertyMap;Ljava/util/Map;Ljava/util/Set;ZLjava/util/Set;Z)V
        18: aload_0
        19: aload_3
        20: putfield      #3                  // Field _targetType:Lcom/fasterxml/jackson/databind/JavaType;
        23: aload_0
        24: aload_1
        25: invokevirtual #4                  // Method com/fasterxml/jackson/databind/deser/BeanDeserializerBuilder.getBuildMethod:()Lcom/fasterxml/jackson/databind/introspect/AnnotatedMethod;
        28: putfield      #5                  // Field _buildMethod:Lcom/fasterxml/jackson/databind/introspect/AnnotatedMethod;
        31: aload_0
        32: getfield      #6                  // Field _objectIdReader:Lcom/fasterxml/jackson/databind/deser/impl/ObjectIdReader;
        35: ifnull        73
        38: new           #7                  // class java/lang/IllegalArgumentException
        41: dup
        42: new           #8                  // class java/lang/StringBuilder
        45: dup
        46: invokespecial #9                  // Method java/lang/StringBuilder."<init>":()V
        49: ldc           #10                 // String Cannot use Object Id with Builder-based deserialization (type
        51: invokevirtual #11                 // Method java/lang/StringBuilder.append:(Ljava/lang/String;)Ljava/lang/StringBuilder;
        54: aload_2
        55: invokevirtual #12                 // Method com/fasterxml/jackson/databind/BeanDescription.getType:()Lcom/fasterxml/jackson/databind/JavaType;
        58: invokevirtual #13                 // Method java/lang/StringBuilder.append:(Ljava/lang/Object;)Ljava/lang/StringBuilder;
        61: ldc           #14                 // String )
        63: invokevirtual #11                 // Method java/lang/StringBuilder.append:(Ljava/lang/String;)Ljava/lang/StringBuilder;
        66: invokevirtual #15                 // Method java/lang/StringBuilder.toString:()Ljava/lang/String;
        69: invokespecial #16                 // Method java/lang/IllegalArgumentException."<init>":(Ljava/lang/String;)V
        72: athrow
        73: return
      LineNumberTable:
        line 67: 0
        line 69: 18
        line 70: 23
        line 72: 31
        line 73: 38
        line 74: 55
        line 76: 73
      LocalVariableTable:
        Start  Length  Slot  Name   Signature
            0      74     0  this   Lcom/fasterxml/jackson/databind/deser/BuilderBasedDeserializer;
            0      74     1 builder   Lcom/fasterxml/jackson/databind/deser/BeanDeserializerBuilder;
            0      74     2 beanDesc   Lcom/fasterxml/jackson/databind/BeanDescription;
            0      74     3 targetType   Lcom/fasterxml/jackson/databind/JavaType;
            0      74     4 properties   Lcom/fasterxml/jackson/databind/deser/impl/BeanPropertyMap;
            0      74     5 backRefs   Ljava/util/Map;
            0      74     6 ignorableProps   Ljava/util/Set;
            0      74     7 ignoreAllUnknown   Z
            0      74     8 includableProps   Ljava/util/Set;
            0      74     9 hasViews   Z
      LocalVariableTypeTable:
        Start  Length  Slot  Name   Signature
            0      74     5 backRefs   Ljava/util/Map<Ljava/lang/String;Lcom/fasterxml/jackson/databind/deser/SettableBeanProperty;>;
            0      74     6 ignorableProps   Ljava/util/Set<Ljava/lang/String;>;
            0      74     8 includableProps   Ljava/util/Set<Ljava/lang/String;>;
      StackMapTable: number_of_entries = 1
        frame_type = 255 /* full_frame */
          offset_delta = 73
          locals = [ class com/fasterxml/jackson/databind/deser/BuilderBasedDeserializer, class com/fasterxml/jackson/databind/deser/BeanDeserializerBuilder, class com/fasterxml/jackson/databind/BeanDescription, class com/fasterxml/jackson/databind/JavaType, class com/fasterxml/jackson/databind/deser/impl/BeanPropertyMap, class java/util/Map, class java/util/Set, int, class java/util/Set, int ]
          stack = []
    Signature: #192                         // (Lcom/fasterxml/jackson/databind/deser/BeanDeserializerBuilder;Lcom/fasterxml/jackson/databind/BeanDescription;Lcom/fasterxml/jackson/databind/JavaType;Lcom/fasterxml/jackson/databind/deser/impl/BeanPropertyMap;Ljava/util/Map<Ljava/lang/String;Lcom/fasterxml/jackson/databind/deser/SettableBeanProperty;>;Ljava/util/Set<Ljava/lang/String;>;ZLjava/util/Set<Ljava/lang/String;>;Z)V

  public com.fasterxml.jackson.databind.deser.BuilderBasedDeserializer(com.fasterxml.jackson.databind.deser.BeanDeserializerBuilder, com.fasterxml.jackson.databind.BeanDescription, com.fasterxml.jackson.databind.deser.impl.BeanPropertyMap, java.util.Map<java.lang.String, com.fasterxml.jackson.databind.deser.SettableBeanProperty>, java.util.Set<java.lang.String>, boolean, boolean);
    descriptor: (Lcom/fasterxml/jackson/databind/deser/BeanDeserializerBuilder;Lcom/fasterxml/jackson/databind/BeanDescription;Lcom/fasterxml/jackson/databind/deser/impl/BeanPropertyMap;Ljava/util/Map;Ljava/util/Set;ZZ)V
    flags: (0x0001) ACC_PUBLIC
    Code:
      stack=9, locals=8, args_size=8
         0: aload_0
         1: aload_1
         2: aload_2
         3: aload_2
         4: invokevirtual #12                 // Method com/fasterxml/jackson/databind/BeanDescription.getType:()Lcom/fasterxml/jackson/databind/JavaType;
         7: aload_3
         8: aload         4
        10: aload         5
        12: iload         6
        14: iload         7
        16: invokespecial #17                 // Method "<init>":(Lcom/fasterxml/jackson/databind/deser/BeanDeserializerBuilder;Lcom/fasterxml/jackson/databind/BeanDescription;Lcom/fasterxml/jackson/databind/JavaType;Lcom/fasterxml/jackson/databind/deser/impl/BeanPropertyMap;Ljava/util/Map;Ljava/util/Set;ZZ)V
        19: return
      LineNumberTable:
        line 88: 0
        line 89: 4
        line 88: 16
        line 91: 19
      LocalVariableTable:
        Start  Length  Slot  Name   Signature
            0      20     0  this   Lcom/fasterxml/jackson/databind/deser/BuilderBasedDeserializer;
            0      20     1 builder   Lcom/fasterxml/jackson/databind/deser/BeanDeserializerBuilder;
            0      20     2 beanDesc   Lcom/fasterxml/jackson/databind/BeanDescription;
            0      20     3 properties   Lcom/fasterxml/jackson/databind/deser/impl/BeanPropertyMap;
            0      20     4 backRefs   Ljava/util/Map;
            0      20     5 ignorableProps   Ljava/util/Set;
            0      20     6 ignoreAllUnknown   Z
            0      20     7 hasViews   Z
      LocalVariableTypeTable:
        Start  Length  Slot  Name   Signature
            0      20     4 backRefs   Ljava/util/Map<Ljava/lang/String;Lcom/fasterxml/jackson/databind/deser/SettableBeanProperty;>;
            0      20     5 ignorableProps   Ljava/util/Set<Ljava/lang/String;>;
    Deprecated: true
    Signature: #195                         // (Lcom/fasterxml/jackson/databind/deser/BeanDeserializerBuilder;Lcom/fasterxml/jackson/databind/BeanDescription;Lcom/fasterxml/jackson/databind/deser/impl/BeanPropertyMap;Ljava/util/Map<Ljava/lang/String;Lcom/fasterxml/jackson/databind/deser/SettableBeanProperty;>;Ljava/util/Set<Ljava/lang/String;>;ZZ)V
    RuntimeVisibleAnnotations:
      0: #197()
        java.lang.Deprecated

  protected com.fasterxml.jackson.databind.deser.BuilderBasedDeserializer(com.fasterxml.jackson.databind.deser.BuilderBasedDeserializer);
    descriptor: (Lcom/fasterxml/jackson/databind/deser/BuilderBasedDeserializer;)V
    flags: (0x0004) ACC_PROTECTED
    Code:
      stack=3, locals=2, args_size=2
         0: aload_0
         1: aload_1
         2: aload_1
         3: getfield      #18                 // Field _ignoreAllUnknown:Z
         6: invokespecial #19                 // Method "<init>":(Lcom/fasterxml/jackson/databind/deser/BuilderBasedDeserializer;Z)V
         9: return
      LineNumberTable:
        line 99: 0
        line 100: 9
      LocalVariableTable:
        Start  Length  Slot  Name   Signature
            0      10     0  this   Lcom/fasterxml/jackson/databind/deser/BuilderBasedDeserializer;
            0      10     1   src   Lcom/fasterxml/jackson/databind/deser/BuilderBasedDeserializer;

  protected com.fasterxml.jackson.databind.deser.BuilderBasedDeserializer(com.fasterxml.jackson.databind.deser.BuilderBasedDeserializer, boolean);
    descriptor: (Lcom/fasterxml/jackson/databind/deser/BuilderBasedDeserializer;Z)V
    flags: (0x0004) ACC_PROTECTED
    Code:
      stack=3, locals=3, args_size=3
         0: aload_0
         1: aload_1
         2: iload_2
         3: invokespecial #20                 // Method com/fasterxml/jackson/databind/deser/BeanDeserializerBase."<init>":(Lcom/fasterxml/jackson/databind/deser/BeanDeserializerBase;Z)V
         6: aload_0
         7: aload_1
         8: getfield      #5                  // Field _buildMethod:Lcom/fasterxml/jackson/databind/introspect/AnnotatedMethod;
        11: putfield      #5                  // Field _buildMethod:Lcom/fasterxml/jackson/databind/introspect/AnnotatedMethod;
        14: aload_0
        15: aload_1
        16: getfield      #3                  // Field _targetType:Lcom/fasterxml/jackson/databind/JavaType;
        19: putfield      #3                  // Field _targetType:Lcom/fasterxml/jackson/databind/JavaType;
        22: return
      LineNumberTable:
        line 104: 0
        line 105: 6
        line 106: 14
        line 107: 22
      LocalVariableTable:
        Start  Length  Slot  Name   Signature
            0      23     0  this   Lcom/fasterxml/jackson/databind/deser/BuilderBasedDeserializer;
            0      23     1   src   Lcom/fasterxml/jackson/databind/deser/BuilderBasedDeserializer;
            0      23     2 ignoreAllUnknown   Z

  protected com.fasterxml.jackson.databind.deser.BuilderBasedDeserializer(com.fasterxml.jackson.databind.deser.BuilderBasedDeserializer, com.fasterxml.jackson.databind.util.NameTransformer);
    descriptor: (Lcom/fasterxml/jackson/databind/deser/BuilderBasedDeserializer;Lcom/fasterxml/jackson/databind/util/NameTransformer;)V
    flags: (0x0004) ACC_PROTECTED
    Code:
      stack=3, locals=3, args_size=3
         0: aload_0
         1: aload_1
         2: aload_2
         3: invokespecial #21                 // Method com/fasterxml/jackson/databind/deser/BeanDeserializerBase."<init>":(Lcom/fasterxml/jackson/databind/deser/BeanDeserializerBase;Lcom/fasterxml/jackson/databind/util/NameTransformer;)V
         6: aload_0
         7: aload_1
         8: getfield      #5                  // Field _buildMethod:Lcom/fasterxml/jackson/databind/introspect/AnnotatedMethod;
        11: putfield      #5                  // Field _buildMethod:Lcom/fasterxml/jackson/databind/introspect/AnnotatedMethod;
        14: aload_0
        15: aload_1
        16: getfield      #3                  // Field _targetType:Lcom/fasterxml/jackson/databind/JavaType;
        19: putfield      #3                  // Field _targetType:Lcom/fasterxml/jackson/databind/JavaType;
        22: return
      LineNumberTable:
        line 110: 0
        line 111: 6
        line 112: 14
        line 113: 22
      LocalVariableTable:
        Start  Length  Slot  Name   Signature
            0      23     0  this   Lcom/fasterxml/jackson/databind/deser/BuilderBasedDeserializer;
            0      23     1   src   Lcom/fasterxml/jackson/databind/deser/BuilderBasedDeserializer;
            0      23     2 unwrapper   Lcom/fasterxml/jackson/databind/util/NameTransformer;

  public com.fasterxml.jackson.databind.deser.BuilderBasedDeserializer(com.fasterxml.jackson.databind.deser.BuilderBasedDeserializer, com.fasterxml.jackson.databind.deser.impl.ObjectIdReader);
    descriptor: (Lcom/fasterxml/jackson/databind/deser/BuilderBasedDeserializer;Lcom/fasterxml/jackson/databind/deser/impl/ObjectIdReader;)V
    flags: (0x0001) ACC_PUBLIC
    Code:
      stack=3, locals=3, args_size=3
         0: aload_0
         1: aload_1
         2: aload_2
         3: invokespecial #22                 // Method com/fasterxml/jackson/databind/deser/BeanDeserializerBase."<init>":(Lcom/fasterxml/jackson/databind/deser/BeanDeserializerBase;Lcom/fasterxml/jackson/databind/deser/impl/ObjectIdReader;)V
         6: aload_0
         7: aload_1
         8: getfield      #5                  // Field _buildMethod:Lcom/fasterxml/jackson/databind/introspect/AnnotatedMethod;
        11: putfield      #5                  // Field _buildMethod:Lcom/fasterxml/jackson/databind/introspect/AnnotatedMethod;
        14: aload_0
        15: aload_1
        16: getfield      #3                  // Field _targetType:Lcom/fasterxml/jackson/databind/JavaType;
        19: putfield      #3                  // Field _targetType:Lcom/fasterxml/jackson/databind/JavaType;
        22: return
      LineNumberTable:
        line 116: 0
        line 117: 6
        line 118: 14
        line 119: 22
      LocalVariableTable:
        Start  Length  Slot  Name   Signature
            0      23     0  this   Lcom/fasterxml/jackson/databind/deser/BuilderBasedDeserializer;
            0      23     1   src   Lcom/fasterxml/jackson/databind/deser/BuilderBasedDeserializer;
            0      23     2   oir   Lcom/fasterxml/jackson/databind/deser/impl/ObjectIdReader;

  public com.fasterxml.jackson.databind.deser.BuilderBasedDeserializer(com.fasterxml.jackson.databind.deser.BuilderBasedDeserializer, java.util.Set<java.lang.String>);
    descriptor: (Lcom/fasterxml/jackson/databind/deser/BuilderBasedDeserializer;Ljava/util/Set;)V
    flags: (0x0001) ACC_PUBLIC
    Code:
      stack=4, locals=3, args_size=3
         0: aload_0
         1: aload_1
         2: aload_2
         3: aload_1
         4: getfield      #23                 // Field _includableProps:Ljava/util/Set;
         7: invokespecial #24                 // Method "<init>":(Lcom/fasterxml/jackson/databind/deser/BuilderBasedDeserializer;Ljava/util/Set;Ljava/util/Set;)V
        10: return
      LineNumberTable:
        line 122: 0
        line 123: 10
      LocalVariableTable:
        Start  Length  Slot  Name   Signature
            0      11     0  this   Lcom/fasterxml/jackson/databind/deser/BuilderBasedDeserializer;
            0      11     1   src   Lcom/fasterxml/jackson/databind/deser/BuilderBasedDeserializer;
            0      11     2 ignorableProps   Ljava/util/Set;
      LocalVariableTypeTable:
        Start  Length  Slot  Name   Signature
            0      11     2 ignorableProps   Ljava/util/Set<Ljava/lang/String;>;
    Signature: #208                         // (Lcom/fasterxml/jackson/databind/deser/BuilderBasedDeserializer;Ljava/util/Set<Ljava/lang/String;>;)V

  public com.fasterxml.jackson.databind.deser.BuilderBasedDeserializer(com.fasterxml.jackson.databind.deser.BuilderBasedDeserializer, java.util.Set<java.lang.String>, java.util.Set<java.lang.String>);
    descriptor: (Lcom/fasterxml/jackson/databind/deser/BuilderBasedDeserializer;Ljava/util/Set;Ljava/util/Set;)V
    flags: (0x0001) ACC_PUBLIC
    Code:
      stack=4, locals=4, args_size=4
         0: aload_0
         1: aload_1
         2: aload_2
         3: aload_3
         4: invokespecial #25                 // Method com/fasterxml/jackson/databind/deser/BeanDeserializerBase."<init>":(Lcom/fasterxml/jackson/databind/deser/BeanDeserializerBase;Ljava/util/Set;Ljava/util/Set;)V
         7: aload_0
         8: aload_1
         9: getfield      #5                  // Field _buildMethod:Lcom/fasterxml/jackson/databind/introspect/AnnotatedMethod;
        12: putfield      #5                  // Field _buildMethod:Lcom/fasterxml/jackson/databind/introspect/AnnotatedMethod;
        15: aload_0
        16: aload_1
        17: getfield      #3                  // Field _targetType:Lcom/fasterxml/jackson/databind/JavaType;
        20: putfield      #3                  // Field _targetType:Lcom/fasterxml/jackson/databind/JavaType;
        23: return
      LineNumberTable:
        line 126: 0
        line 127: 7
        line 128: 15
        line 129: 23
      LocalVariableTable:
        Start  Length  Slot  Name   Signature
            0      24     0  this   Lcom/fasterxml/jackson/databind/deser/BuilderBasedDeserializer;
            0      24     1   src   Lcom/fasterxml/jackson/databind/deser/BuilderBasedDeserializer;
            0      24     2 ignorableProps   Ljava/util/Set;
            0      24     3 includableProps   Ljava/util/Set;
      LocalVariableTypeTable:
        Start  Length  Slot  Name   Signature
            0      24     2 ignorableProps   Ljava/util/Set<Ljava/lang/String;>;
            0      24     3 includableProps   Ljava/util/Set<Ljava/lang/String;>;
    Signature: #210                         // (Lcom/fasterxml/jackson/databind/deser/BuilderBasedDeserializer;Ljava/util/Set<Ljava/lang/String;>;Ljava/util/Set<Ljava/lang/String;>;)V

  public com.fasterxml.jackson.databind.deser.BuilderBasedDeserializer(com.fasterxml.jackson.databind.deser.BuilderBasedDeserializer, com.fasterxml.jackson.databind.deser.impl.BeanPropertyMap);
    descriptor: (Lcom/fasterxml/jackson/databind/deser/BuilderBasedDeserializer;Lcom/fasterxml/jackson/databind/deser/impl/BeanPropertyMap;)V
    flags: (0x0001) ACC_PUBLIC
    Code:
      stack=3, locals=3, args_size=3
         0: aload_0
         1: aload_1
         2: aload_2
         3: invokespecial #26                 // Method com/fasterxml/jackson/databind/deser/BeanDeserializerBase."<init>":(Lcom/fasterxml/jackson/databind/deser/BeanDeserializerBase;Lcom/fasterxml/jackson/databind/deser/impl/BeanPropertyMap;)V
         6: aload_0
         7: aload_1
         8: getfield      #5                  // Field _buildMethod:Lcom/fasterxml/jackson/databind/introspect/AnnotatedMethod;
        11: putfield      #5                  // Field _buildMethod:Lcom/fasterxml/jackson/databind/introspect/AnnotatedMethod;
        14: aload_0
        15: aload_1
        16: getfield      #3                  // Field _targetType:Lcom/fasterxml/jackson/databind/JavaType;
        19: putfield      #3                  // Field _targetType:Lcom/fasterxml/jackson/databind/JavaType;
        22: return
      LineNumberTable:
        line 132: 0
        line 133: 6
        line 134: 14
        line 135: 22
      LocalVariableTable:
        Start  Length  Slot  Name   Signature
            0      23     0  this   Lcom/fasterxml/jackson/databind/deser/BuilderBasedDeserializer;
            0      23     1   src   Lcom/fasterxml/jackson/databind/deser/BuilderBasedDeserializer;
            0      23     2 props   Lcom/fasterxml/jackson/databind/deser/impl/BeanPropertyMap;

  public com.fasterxml.jackson.databind.JsonDeserializer<java.lang.Object> unwrappingDeserializer(com.fasterxml.jackson.databind.util.NameTransformer);
    descriptor: (Lcom/fasterxml/jackson/databind/util/NameTransformer;)Lcom/fasterxml/jackson/databind/JsonDeserializer;
    flags: (0x0001) ACC_PUBLIC
    Code:
      stack=4, locals=2, args_size=2
         0: new           #27                 // class com/fasterxml/jackson/databind/deser/BuilderBasedDeserializer
         3: dup
         4: aload_0
         5: aload_1
         6: invokespecial #28                 // Method "<init>":(Lcom/fasterxml/jackson/databind/deser/BuilderBasedDeserializer;Lcom/fasterxml/jackson/databind/util/NameTransformer;)V
         9: areturn
      LineNumberTable:
        line 144: 0
      LocalVariableTable:
        Start  Length  Slot  Name   Signature
            0      10     0  this   Lcom/fasterxml/jackson/databind/deser/BuilderBasedDeserializer;
            0      10     1 unwrapper   Lcom/fasterxml/jackson/databind/util/NameTransformer;
    Signature: #215                         // (Lcom/fasterxml/jackson/databind/util/NameTransformer;)Lcom/fasterxml/jackson/databind/JsonDeserializer<Ljava/lang/Object;>;

  public com.fasterxml.jackson.databind.deser.BeanDeserializerBase withObjectIdReader(com.fasterxml.jackson.databind.deser.impl.ObjectIdReader);
    descriptor: (Lcom/fasterxml/jackson/databind/deser/impl/ObjectIdReader;)Lcom/fasterxml/jackson/databind/deser/BeanDeserializerBase;
    flags: (0x0001) ACC_PUBLIC
    Code:
      stack=4, locals=2, args_size=2
         0: new           #27                 // class com/fasterxml/jackson/databind/deser/BuilderBasedDeserializer
         3: dup
         4: aload_0
         5: aload_1
         6: invokespecial #29                 // Method "<init>":(Lcom/fasterxml/jackson/databind/deser/BuilderBasedDeserializer;Lcom/fasterxml/jackson/databind/deser/impl/ObjectIdReader;)V
         9: areturn
      LineNumberTable:
        line 149: 0
      LocalVariableTable:
        Start  Length  Slot  Name   Signature
            0      10     0  this   Lcom/fasterxml/jackson/databind/deser/BuilderBasedDeserializer;
            0      10     1   oir   Lcom/fasterxml/jackson/databind/deser/impl/ObjectIdReader;

  public com.fasterxml.jackson.databind.deser.BeanDeserializerBase withByNameInclusion(java.util.Set<java.lang.String>, java.util.Set<java.lang.String>);
    descriptor: (Ljava/util/Set;Ljava/util/Set;)Lcom/fasterxml/jackson/databind/deser/BeanDeserializerBase;
    flags: (0x0001) ACC_PUBLIC
    Code:
      stack=5, locals=3, args_size=3
         0: new           #27                 // class com/fasterxml/jackson/databind/deser/BuilderBasedDeserializer
         3: dup
         4: aload_0
         5: aload_1
         6: aload_2
         7: invokespecial #24                 // Method "<init>":(Lcom/fasterxml/jackson/databind/deser/BuilderBasedDeserializer;Ljava/util/Set;Ljava/util/Set;)V
        10: areturn
      LineNumberTable:
        line 155: 0
      LocalVariableTable:
        Start  Length  Slot  Name   Signature
            0      11     0  this   Lcom/fasterxml/jackson/databind/deser/BuilderBasedDeserializer;
            0      11     1 ignorableProps   Ljava/util/Set;
            0      11     2 includableProps   Ljava/util/Set;
      LocalVariableTypeTable:
        Start  Length  Slot  Name   Signature
            0      11     1 ignorableProps   Ljava/util/Set<Ljava/lang/String;>;
            0      11     2 includableProps   Ljava/util/Set<Ljava/lang/String;>;
    Signature: #220                         // (Ljava/util/Set<Ljava/lang/String;>;Ljava/util/Set<Ljava/lang/String;>;)Lcom/fasterxml/jackson/databind/deser/BeanDeserializerBase;

  public com.fasterxml.jackson.databind.deser.BeanDeserializerBase withIgnoreAllUnknown(boolean);
    descriptor: (Z)Lcom/fasterxml/jackson/databind/deser/BeanDeserializerBase;
    flags: (0x0001) ACC_PUBLIC
    Code:
      stack=4, locals=2, args_size=2
         0: new           #27                 // class com/fasterxml/jackson/databind/deser/BuilderBasedDeserializer
         3: dup
         4: aload_0
         5: iload_1
         6: invokespecial #19                 // Method "<init>":(Lcom/fasterxml/jackson/databind/deser/BuilderBasedDeserializer;Z)V
         9: areturn
      LineNumberTable:
        line 160: 0
      LocalVariableTable:
        Start  Length  Slot  Name   Signature
            0      10     0  this   Lcom/fasterxml/jackson/databind/deser/BuilderBasedDeserializer;
            0      10     1 ignoreUnknown   Z

  public com.fasterxml.jackson.databind.deser.BeanDeserializerBase withBeanProperties(com.fasterxml.jackson.databind.deser.impl.BeanPropertyMap);
    descriptor: (Lcom/fasterxml/jackson/databind/deser/impl/BeanPropertyMap;)Lcom/fasterxml/jackson/databind/deser/BeanDeserializerBase;
    flags: (0x0001) ACC_PUBLIC
    Code:
      stack=4, locals=2, args_size=2
         0: new           #27                 // class com/fasterxml/jackson/databind/deser/BuilderBasedDeserializer
         3: dup
         4: aload_0
         5: aload_1
         6: invokespecial #30                 // Method "<init>":(Lcom/fasterxml/jackson/databind/deser/BuilderBasedDeserializer;Lcom/fasterxml/jackson/databind/deser/impl/BeanPropertyMap;)V
         9: areturn
      LineNumberTable:
        line 165: 0
      LocalVariableTable:
        Start  Length  Slot  Name   Signature
            0      10     0  this   Lcom/fasterxml/jackson/databind/deser/BuilderBasedDeserializer;
            0      10     1 props   Lcom/fasterxml/jackson/databind/deser/impl/BeanPropertyMap;

  protected com.fasterxml.jackson.databind.deser.BeanDeserializerBase asArrayDeserializer();
    descriptor: ()Lcom/fasterxml/jackson/databind/deser/BeanDeserializerBase;
    flags: (0x0004) ACC_PROTECTED
    Code:
      stack=6, locals=2, args_size=1
         0: aload_0
         1: getfield      #31                 // Field _beanProperties:Lcom/fasterxml/jackson/databind/deser/impl/BeanPropertyMap;
         4: invokevirtual #32                 // Method com/fasterxml/jackson/databind/deser/impl/BeanPropertyMap.getPropertiesInInsertionOrder:()[Lcom/fasterxml/jackson/databind/deser/SettableBeanProperty;
         7: astore_1
         8: new           #33                 // class com/fasterxml/jackson/databind/deser/impl/BeanAsArrayBuilderDeserializer
        11: dup
        12: aload_0
        13: aload_0
        14: getfield      #3                  // Field _targetType:Lcom/fasterxml/jackson/databind/JavaType;
        17: aload_1
        18: aload_0
        19: getfield      #5                  // Field _buildMethod:Lcom/fasterxml/jackson/databind/introspect/AnnotatedMethod;
        22: invokespecial #34                 // Method com/fasterxml/jackson/databind/deser/impl/BeanAsArrayBuilderDeserializer."<init>":(Lcom/fasterxml/jackson/databind/deser/BeanDeserializerBase;Lcom/fasterxml/jackson/databind/JavaType;[Lcom/fasterxml/jackson/databind/deser/SettableBeanProperty;Lcom/fasterxml/jackson/databind/introspect/AnnotatedMethod;)V
        25: areturn
      LineNumberTable:
        line 170: 0
        line 171: 8
      LocalVariableTable:
        Start  Length  Slot  Name   Signature
            0      26     0  this   Lcom/fasterxml/jackson/databind/deser/BuilderBasedDeserializer;
            8      18     1 props   [Lcom/fasterxml/jackson/databind/deser/SettableBeanProperty;

  public java.lang.Boolean supportsUpdate(com.fasterxml.jackson.databind.DeserializationConfig);
    descriptor: (Lcom/fasterxml/jackson/databind/DeserializationConfig;)Ljava/lang/Boolean;
    flags: (0x0001) ACC_PUBLIC
    Code:
      stack=1, locals=2, args_size=2
         0: getstatic     #35                 // Field java/lang/Boolean.FALSE:Ljava/lang/Boolean;
         3: areturn
      LineNumberTable:
        line 183: 0
      LocalVariableTable:
        Start  Length  Slot  Name   Signature
            0       4     0  this   Lcom/fasterxml/jackson/databind/deser/BuilderBasedDeserializer;
            0       4     1 config   Lcom/fasterxml/jackson/databind/DeserializationConfig;

  protected java.lang.Object finishBuild(com.fasterxml.jackson.databind.DeserializationContext, java.lang.Object) throws java.io.IOException;
    descriptor: (Lcom/fasterxml/jackson/databind/DeserializationContext;Ljava/lang/Object;)Ljava/lang/Object;
    flags: (0x0004) ACC_PROTECTED
    Code:
      stack=3, locals=4, args_size=3
         0: aconst_null
         1: aload_0
         2: getfield      #5                  // Field _buildMethod:Lcom/fasterxml/jackson/databind/introspect/AnnotatedMethod;
         5: if_acmpne     10
         8: aload_2
         9: areturn
        10: aload_0
        11: getfield      #5                  // Field _buildMethod:Lcom/fasterxml/jackson/databind/introspect/AnnotatedMethod;
        14: invokevirtual #36                 // Method com/fasterxml/jackson/databind/introspect/AnnotatedMethod.getMember:()Ljava/lang/reflect/Method;
        17: aload_2
        18: aconst_null
        19: checkcast     #37                 // class "[Ljava/lang/Object;"
        22: invokevirtual #38                 // Method java/lang/reflect/Method.invoke:(Ljava/lang/Object;[Ljava/lang/Object;)Ljava/lang/Object;
        25: areturn
        26: astore_3
        27: aload_0
        28: aload_3
        29: aload_1
        30: invokevirtual #40                 // Method wrapInstantiationProblem:(Ljava/lang/Throwable;Lcom/fasterxml/jackson/databind/DeserializationContext;)Ljava/lang/Object;
        33: areturn
      Exception table:
         from    to  target type
            10    25    26   Class java/lang/Exception
      LineNumberTable:
        line 196: 0
        line 197: 8
        line 200: 10
        line 201: 26
        line 202: 27
      LocalVariableTable:
        Start  Length  Slot  Name   Signature
           27       7     3     e   Ljava/lang/Exception;
            0      34     0  this   Lcom/fasterxml/jackson/databind/deser/BuilderBasedDeserializer;
            0      34     1  ctxt   Lcom/fasterxml/jackson/databind/DeserializationContext;
            0      34     2 builder   Ljava/lang/Object;
      StackMapTable: number_of_entries = 2
        frame_type = 10 /* same */
        frame_type = 79 /* same_locals_1_stack_item */
          stack = [ class java/lang/Exception ]
    Exceptions:
      throws java.io.IOException

  public java.lang.Object deserialize(com.fasterxml.jackson.core.JsonParser, com.fasterxml.jackson.databind.DeserializationContext) throws java.io.IOException;
    descriptor: (Lcom/fasterxml/jackson/core/JsonParser;Lcom/fasterxml/jackson/databind/DeserializationContext;)Ljava/lang/Object;
    flags: (0x0001) ACC_PUBLIC
    Code:
      stack=6, locals=4, args_size=3
         0: aload_1
         1: invokevirtual #41                 // Method com/fasterxml/jackson/core/JsonParser.isExpectedStartObjectToken:()Z
         4: ifeq          44
         7: aload_1
         8: invokevirtual #42                 // Method com/fasterxml/jackson/core/JsonParser.nextToken:()Lcom/fasterxml/jackson/core/JsonToken;
        11: astore_3
        12: aload_0
        13: getfield      #43                 // Field _vanillaProcessing:Z
        16: ifeq          32
        19: aload_0
        20: aload_2
        21: aload_0
        22: aload_1
        23: aload_2
        24: aload_3
        25: invokespecial #44                 // Method vanillaDeserialize:(Lcom/fasterxml/jackson/core/JsonParser;Lcom/fasterxml/jackson/databind/DeserializationContext;Lcom/fasterxml/jackson/core/JsonToken;)Ljava/lang/Object;
        28: invokevirtual #45                 // Method finishBuild:(Lcom/fasterxml/jackson/databind/DeserializationContext;Ljava/lang/Object;)Ljava/lang/Object;
        31: areturn
        32: aload_0
        33: aload_2
        34: aload_0
        35: aload_1
        36: aload_2
        37: invokevirtual #46                 // Method deserializeFromObject:(Lcom/fasterxml/jackson/core/JsonParser;Lcom/fasterxml/jackson/databind/DeserializationContext;)Ljava/lang/Object;
        40: invokevirtual #45                 // Method finishBuild:(Lcom/fasterxml/jackson/databind/DeserializationContext;Ljava/lang/Object;)Ljava/lang/Object;
        43: areturn
        44: aload_1
        45: invokevirtual #47                 // Method com/fasterxml/jackson/core/JsonParser.currentTokenId:()I
        48: tableswitch   { // 2 to 12
                       2: 168
                       3: 161
                       4: 180
                       5: 168
                       6: 108
                       7: 120
                       8: 132
                       9: 149
                      10: 149
                      11: 180
                      12: 144
                 default: 180
            }
       108: aload_0
       109: aload_2
       110: aload_0
       111: aload_1
       112: aload_2
       113: invokevirtual #48                 // Method deserializeFromString:(Lcom/fasterxml/jackson/core/JsonParser;Lcom/fasterxml/jackson/databind/DeserializationContext;)Ljava/lang/Object;
       116: invokevirtual #45                 // Method finishBuild:(Lcom/fasterxml/jackson/databind/DeserializationContext;Ljava/lang/Object;)Ljava/lang/Object;
       119: areturn
       120: aload_0
       121: aload_2
       122: aload_0
       123: aload_1
       124: aload_2
       125: invokevirtual #49                 // Method deserializeFromNumber:(Lcom/fasterxml/jackson/core/JsonParser;Lcom/fasterxml/jackson/databind/DeserializationContext;)Ljava/lang/Object;
       128: invokevirtual #45                 // Method finishBuild:(Lcom/fasterxml/jackson/databind/DeserializationContext;Ljava/lang/Object;)Ljava/lang/Object;
       131: areturn
       132: aload_0
       133: aload_2
       134: aload_0
       135: aload_1
       136: aload_2
       137: invokevirtual #50                 // Method deserializeFromDouble:(Lcom/fasterxml/jackson/core/JsonParser;Lcom/fasterxml/jackson/databind/DeserializationContext;)Ljava/lang/Object;
       140: invokevirtual #45                 // Method finishBuild:(Lcom/fasterxml/jackson/databind/DeserializationContext;Ljava/lang/Object;)Ljava/lang/Object;
       143: areturn
       144: aload_1
       145: invokevirtual #51                 // Method com/fasterxml/jackson/core/JsonParser.getEmbeddedObject:()Ljava/lang/Object;
       148: areturn
       149: aload_0
       150: aload_2
       151: aload_0
       152: aload_1
       153: aload_2
       154: invokevirtual #52                 // Method deserializeFromBoolean:(Lcom/fasterxml/jackson/core/JsonParser;Lcom/fasterxml/jackson/databind/DeserializationContext;)Ljava/lang/Object;
       157: invokevirtual #45                 // Method finishBuild:(Lcom/fasterxml/jackson/databind/DeserializationContext;Ljava/lang/Object;)Ljava/lang/Object;
       160: areturn
       161: aload_0
       162: aload_1
       163: aload_2
       164: invokevirtual #53                 // Method _deserializeFromArray:(Lcom/fasterxml/jackson/core/JsonParser;Lcom/fasterxml/jackson/databind/DeserializationContext;)Ljava/lang/Object;
       167: areturn
       168: aload_0
       169: aload_2
       170: aload_0
       171: aload_1
       172: aload_2
       173: invokevirtual #46                 // Method deserializeFromObject:(Lcom/fasterxml/jackson/core/JsonParser;Lcom/fasterxml/jackson/databind/DeserializationContext;)Ljava/lang/Object;
       176: invokevirtual #45                 // Method finishBuild:(Lcom/fasterxml/jackson/databind/DeserializationContext;Ljava/lang/Object;)Ljava/lang/Object;
       179: areturn
       180: aload_2
       181: aload_0
       182: aload_2
       183: invokevirtual #54                 // Method getValueType:(Lcom/fasterxml/jackson/databind/DeserializationContext;)Lcom/fasterxml/jackson/databind/JavaType;
       186: aload_1
       187: invokevirtual #55                 // Method com/fasterxml/jackson/databind/DeserializationContext.handleUnexpectedToken:(Lcom/fasterxml/jackson/databind/JavaType;Lcom/fasterxml/jackson/core/JsonParser;)Ljava/lang/Object;
       190: areturn
      LineNumberTable:
        line 214: 0
        line 215: 7
        line 216: 12
        line 217: 19
        line 219: 32
        line 222: 44
        line 224: 108
        line 226: 120
        line 228: 132
        line 230: 144
        line 233: 149
        line 237: 161
        line 240: 168
        line 243: 180
      LocalVariableTable:
        Start  Length  Slot  Name   Signature
           12      32     3     t   Lcom/fasterxml/jackson/core/JsonToken;
            0     191     0  this   Lcom/fasterxml/jackson/databind/deser/BuilderBasedDeserializer;
            0     191     1     p   Lcom/fasterxml/jackson/core/JsonParser;
            0     191     2  ctxt   Lcom/fasterxml/jackson/databind/DeserializationContext;
      StackMapTable: number_of_entries = 10
        frame_type = 252 /* append */
          offset_delta = 32
          locals = [ class com/fasterxml/jackson/core/JsonToken ]
        frame_type = 250 /* chop */
          offset_delta = 11
        frame_type = 63 /* same */
        frame_type = 11 /* same */
        frame_type = 11 /* same */
        frame_type = 11 /* same */
        frame_type = 4 /* same */
        frame_type = 11 /* same */
        frame_type = 6 /* same */
        frame_type = 11 /* same */
    Exceptions:
      throws java.io.IOException

  public java.lang.Object deserialize(com.fasterxml.jackson.core.JsonParser, com.fasterxml.jackson.databind.DeserializationContext, java.lang.Object) throws java.io.IOException;
    descriptor: (Lcom/fasterxml/jackson/core/JsonParser;Lcom/fasterxml/jackson/databind/DeserializationContext;Ljava/lang/Object;)Ljava/lang/Object;
    flags: (0x0001) ACC_PUBLIC
    Code:
      stack=7, locals=7, args_size=4
         0: aload_0
         1: getfield      #3                  // Field _targetType:Lcom/fasterxml/jackson/databind/JavaType;
         4: astore        4
         6: aload_0
         7: invokevirtual #56                 // Method handledType:()Ljava/lang/Class;
        10: astore        5
        12: aload_3
        13: invokevirtual #57                 // Method java/lang/Object.getClass:()Ljava/lang/Class;
        16: astore        6
        18: aload         5
        20: aload         6
        22: invokevirtual #58                 // Method java/lang/Class.isAssignableFrom:(Ljava/lang/Class;)Z
        25: ifeq          57
        28: aload_2
        29: aload         4
        31: ldc           #59                 // String Deserialization of %s by passing existing Builder (%s) instance not supported
        33: iconst_2
        34: anewarray     #60                 // class java/lang/Object
        37: dup
        38: iconst_0
        39: aload         4
        41: aastore
        42: dup
        43: iconst_1
        44: aload         5
        46: invokevirtual #61                 // Method java/lang/Class.getName:()Ljava/lang/String;
        49: aastore
        50: invokestatic  #62                 // Method java/lang/String.format:(Ljava/lang/String;[Ljava/lang/Object;)Ljava/lang/String;
        53: invokevirtual #63                 // Method com/fasterxml/jackson/databind/DeserializationContext.reportBadDefinition:(Lcom/fasterxml/jackson/databind/JavaType;Ljava/lang/String;)Ljava/lang/Object;
        56: areturn
        57: aload_2
        58: aload         4
        60: ldc           #64                 // String Deserialization of %s by passing existing instance (of %s) not supported
        62: iconst_2
        63: anewarray     #60                 // class java/lang/Object
        66: dup
        67: iconst_0
        68: aload         4
        70: aastore
        71: dup
        72: iconst_1
        73: aload         6
        75: invokevirtual #61                 // Method java/lang/Class.getName:()Ljava/lang/String;
        78: aastore
        79: invokestatic  #62                 // Method java/lang/String.format:(Ljava/lang/String;[Ljava/lang/Object;)Ljava/lang/String;
        82: invokevirtual #63                 // Method com/fasterxml/jackson/databind/DeserializationContext.reportBadDefinition:(Lcom/fasterxml/jackson/databind/JavaType;Ljava/lang/String;)Ljava/lang/Object;
        85: areturn
      LineNumberTable:
        line 257: 0
        line 259: 6
        line 260: 12
        line 261: 18
        line 262: 28
        line 264: 46
        line 262: 50
        line 266: 57
        line 268: 75
        line 266: 79
      LocalVariableTable:
        Start  Length  Slot  Name   Signature
            0      86     0  this   Lcom/fasterxml/jackson/databind/deser/BuilderBasedDeserializer;
            0      86     1     p   Lcom/fasterxml/jackson/core/JsonParser;
            0      86     2  ctxt   Lcom/fasterxml/jackson/databind/DeserializationContext;
            0      86     3 value   Ljava/lang/Object;
            6      80     4 valueType   Lcom/fasterxml/jackson/databind/JavaType;
           12      74     5 builderRawType   Ljava/lang/Class;
           18      68     6 instRawType   Ljava/lang/Class;
      LocalVariableTypeTable:
        Start  Length  Slot  Name   Signature
           12      74     5 builderRawType   Ljava/lang/Class<*>;
           18      68     6 instRawType   Ljava/lang/Class<*>;
      StackMapTable: number_of_entries = 1
        frame_type = 254 /* append */
          offset_delta = 57
          locals = [ class com/fasterxml/jackson/databind/JavaType, class java/lang/Class, class java/lang/Class ]
    Exceptions:
      throws java.io.IOException

  private final java.lang.Object vanillaDeserialize(com.fasterxml.jackson.core.JsonParser, com.fasterxml.jackson.databind.DeserializationContext, com.fasterxml.jackson.core.JsonToken) throws java.io.IOException;
    descriptor: (Lcom/fasterxml/jackson/core/JsonParser;Lcom/fasterxml/jackson/databind/DeserializationContext;Lcom/fasterxml/jackson/core/JsonToken;)Ljava/lang/Object;
    flags: (0x0012) ACC_PRIVATE, ACC_FINAL
    Code:
      stack=5, locals=8, args_size=4
         0: aload_0
         1: getfield      #65                 // Field _valueInstantiator:Lcom/fasterxml/jackson/databind/deser/ValueInstantiator;
         4: aload_2
         5: invokevirtual #66                 // Method com/fasterxml/jackson/databind/deser/ValueInstantiator.createUsingDefault:(Lcom/fasterxml/jackson/databind/DeserializationContext;)Ljava/lang/Object;
         8: astore        4
        10: aload_1
        11: invokevirtual #67                 // Method com/fasterxml/jackson/core/JsonParser.currentToken:()Lcom/fasterxml/jackson/core/JsonToken;
        14: getstatic     #68                 // Field com/fasterxml/jackson/core/JsonToken.FIELD_NAME:Lcom/fasterxml/jackson/core/JsonToken;
        17: if_acmpne     95
        20: aload_1
        21: invokevirtual #69                 // Method com/fasterxml/jackson/core/JsonParser.currentName:()Ljava/lang/String;
        24: astore        5
        26: aload_1
        27: invokevirtual #42                 // Method com/fasterxml/jackson/core/JsonParser.nextToken:()Lcom/fasterxml/jackson/core/JsonToken;
        30: pop
        31: aload_0
        32: getfield      #31                 // Field _beanProperties:Lcom/fasterxml/jackson/databind/deser/impl/BeanPropertyMap;
        35: aload         5
        37: invokevirtual #70                 // Method com/fasterxml/jackson/databind/deser/impl/BeanPropertyMap.find:(Ljava/lang/String;)Lcom/fasterxml/jackson/databind/deser/SettableBeanProperty;
        40: astore        6
        42: aload         6
        44: ifnull        77
        47: aload         6
        49: aload_1
        50: aload_2
        51: aload         4
        53: invokevirtual #71                 // Method com/fasterxml/jackson/databind/deser/SettableBeanProperty.deserializeSetAndReturn:(Lcom/fasterxml/jackson/core/JsonParser;Lcom/fasterxml/jackson/databind/DeserializationContext;Ljava/lang/Object;)Ljava/lang/Object;
        56: astore        4
        58: goto          87
        61: astore        7
        63: aload_0
        64: aload         7
        66: aload         4
        68: aload         5
        70: aload_2
        71: invokevirtual #72                 // Method wrapAndThrow:(Ljava/lang/Throwable;Ljava/lang/Object;Ljava/lang/String;Lcom/fasterxml/jackson/databind/DeserializationContext;)V
        74: goto          87
        77: aload_0
        78: aload_1
        79: aload_2
        80: aload         4
        82: aload         5
        84: invokevirtual #73                 // Method handleUnknownVanilla:(Lcom/fasterxml/jackson/core/JsonParser;Lcom/fasterxml/jackson/databind/DeserializationContext;Ljava/lang/Object;Ljava/lang/String;)V
        87: aload_1
        88: invokevirtual #42                 // Method com/fasterxml/jackson/core/JsonParser.nextToken:()Lcom/fasterxml/jackson/core/JsonToken;
        91: pop
        92: goto          10
        95: aload         4
        97: areturn
      Exception table:
         from    to  target type
            47    58    61   Class java/lang/Exception
      LineNumberTable:
        line 285: 0
        line 286: 10
        line 287: 20
        line 289: 26
        line 290: 31
        line 291: 42
        line 293: 47
        line 296: 58
        line 294: 61
        line 295: 63
        line 296: 74
        line 298: 77
        line 286: 87
        line 301: 95
      LocalVariableTable:
        Start  Length  Slot  Name   Signature
           63      11     7     e   Ljava/lang/Exception;
           26      61     5 propName   Ljava/lang/String;
           42      45     6  prop   Lcom/fasterxml/jackson/databind/deser/SettableBeanProperty;
            0      98     0  this   Lcom/fasterxml/jackson/databind/deser/BuilderBasedDeserializer;
            0      98     1     p   Lcom/fasterxml/jackson/core/JsonParser;
            0      98     2  ctxt   Lcom/fasterxml/jackson/databind/DeserializationContext;
            0      98     3     t   Lcom/fasterxml/jackson/core/JsonToken;
           10      88     4  bean   Ljava/lang/Object;
      StackMapTable: number_of_entries = 5
        frame_type = 252 /* append */
          offset_delta = 10
          locals = [ class java/lang/Object ]
        frame_type = 255 /* full_frame */
          offset_delta = 50
          locals = [ class com/fasterxml/jackson/databind/deser/BuilderBasedDeserializer, class com/fasterxml/jackson/core/JsonParser, class com/fasterxml/jackson/databind/DeserializationContext, class com/fasterxml/jackson/core/JsonToken, class java/lang/Object, class java/lang/String, class com/fasterxml/jackson/databind/deser/SettableBeanProperty ]
          stack = [ class java/lang/Exception ]
        frame_type = 15 /* same */
        frame_type = 249 /* chop */
          offset_delta = 9
        frame_type = 7 /* same */
    Exceptions:
      throws java.io.IOException

  public java.lang.Object deserializeFromObject(com.fasterxml.jackson.core.JsonParser, com.fasterxml.jackson.databind.DeserializationContext) throws java.io.IOException;
    descriptor: (Lcom/fasterxml/jackson/core/JsonParser;Lcom/fasterxml/jackson/databind/DeserializationContext;)Ljava/lang/Object;
    flags: (0x0001) ACC_PUBLIC
    Code:
      stack=5, locals=7, args_size=3
         0: aload_0
         1: getfield      #74                 // Field _nonStandardCreation:Z
         4: ifeq          42
         7: aload_0
         8: getfield      #75                 // Field _unwrappedPropertyHandler:Lcom/fasterxml/jackson/databind/deser/impl/UnwrappedPropertyHandler;
        11: ifnull        21
        14: aload_0
        15: aload_1
        16: aload_2
        17: invokevirtual #76                 // Method deserializeWithUnwrapped:(Lcom/fasterxml/jackson/core/JsonParser;Lcom/fasterxml/jackson/databind/DeserializationContext;)Ljava/lang/Object;
        20: areturn
        21: aload_0
        22: getfield      #77                 // Field _externalTypeIdHandler:Lcom/fasterxml/jackson/databind/deser/impl/ExternalTypeHandler;
        25: ifnull        35
        28: aload_0
        29: aload_1
        30: aload_2
        31: invokevirtual #78                 // Method deserializeWithExternalTypeId:(Lcom/fasterxml/jackson/core/JsonParser;Lcom/fasterxml/jackson/databind/DeserializationContext;)Ljava/lang/Object;
        34: areturn
        35: aload_0
        36: aload_1
        37: aload_2
        38: invokevirtual #79                 // Method deserializeFromObjectUsingNonDefault:(Lcom/fasterxml/jackson/core/JsonParser;Lcom/fasterxml/jackson/databind/DeserializationContext;)Ljava/lang/Object;
        41: areturn
        42: aload_0
        43: getfield      #65                 // Field _valueInstantiator:Lcom/fasterxml/jackson/databind/deser/ValueInstantiator;
        46: aload_2
        47: invokevirtual #66                 // Method com/fasterxml/jackson/databind/deser/ValueInstantiator.createUsingDefault:(Lcom/fasterxml/jackson/databind/DeserializationContext;)Ljava/lang/Object;
        50: astore_3
        51: aload_0
        52: getfield      #80                 // Field _injectables:[Lcom/fasterxml/jackson/databind/deser/impl/ValueInjector;
        55: ifnull        64
        58: aload_0
        59: aload_2
        60: aload_3
        61: invokevirtual #81                 // Method injectValues:(Lcom/fasterxml/jackson/databind/DeserializationContext;Ljava/lang/Object;)V
        64: aload_0
        65: getfield      #82                 // Field _needViewProcesing:Z
        68: ifeq          92
        71: aload_2
        72: invokevirtual #83                 // Method com/fasterxml/jackson/databind/DeserializationContext.getActiveView:()Ljava/lang/Class;
        75: astore        4
        77: aload         4
        79: ifnull        92
        82: aload_0
        83: aload_1
        84: aload_2
        85: aload_3
        86: aload         4
        88: invokevirtual #84                 // Method deserializeWithView:(Lcom/fasterxml/jackson/core/JsonParser;Lcom/fasterxml/jackson/databind/DeserializationContext;Ljava/lang/Object;Ljava/lang/Class;)Ljava/lang/Object;
        91: areturn
        92: aload_1
        93: invokevirtual #67                 // Method com/fasterxml/jackson/core/JsonParser.currentToken:()Lcom/fasterxml/jackson/core/JsonToken;
        96: getstatic     #68                 // Field com/fasterxml/jackson/core/JsonToken.FIELD_NAME:Lcom/fasterxml/jackson/core/JsonToken;
        99: if_acmpne     173
       102: aload_1
       103: invokevirtual #69                 // Method com/fasterxml/jackson/core/JsonParser.currentName:()Ljava/lang/String;
       106: astore        4
       108: aload_1
       109: invokevirtual #42                 // Method com/fasterxml/jackson/core/JsonParser.nextToken:()Lcom/fasterxml/jackson/core/JsonToken;
       112: pop
       113: aload_0
       114: getfield      #31                 // Field _beanProperties:Lcom/fasterxml/jackson/databind/deser/impl/BeanPropertyMap;
       117: aload         4
       119: invokevirtual #70                 // Method com/fasterxml/jackson/databind/deser/impl/BeanPropertyMap.find:(Ljava/lang/String;)Lcom/fasterxml/jackson/databind/deser/SettableBeanProperty;
       122: astore        5
       124: aload         5
       126: ifnull        156
       129: aload         5
       131: aload_1
       132: aload_2
       133: aload_3
       134: invokevirtual #71                 // Method com/fasterxml/jackson/databind/deser/SettableBeanProperty.deserializeSetAndReturn:(Lcom/fasterxml/jackson/core/JsonParser;Lcom/fasterxml/jackson/databind/DeserializationContext;Ljava/lang/Object;)Ljava/lang/Object;
       137: astore_3
       138: goto          165
       141: astore        6
       143: aload_0
       144: aload         6
       146: aload_3
       147: aload         4
       149: aload_2
       150: invokevirtual #72                 // Method wrapAndThrow:(Ljava/lang/Throwable;Ljava/lang/Object;Ljava/lang/String;Lcom/fasterxml/jackson/databind/DeserializationContext;)V
       153: goto          165
       156: aload_0
       157: aload_1
       158: aload_2
       159: aload_3
       160: aload         4
       162: invokevirtual #73                 // Method handleUnknownVanilla:(Lcom/fasterxml/jackson/core/JsonParser;Lcom/fasterxml/jackson/databind/DeserializationContext;Ljava/lang/Object;Ljava/lang/String;)V
       165: aload_1
       166: invokevirtual #42                 // Method com/fasterxml/jackson/core/JsonParser.nextToken:()Lcom/fasterxml/jackson/core/JsonToken;
       169: pop
       170: goto          92
       173: aload_3
       174: areturn
      Exception table:
         from    to  target type
           129   138   141   Class java/lang/Exception
      LineNumberTable:
        line 312: 0
        line 313: 7
        line 314: 14
        line 316: 21
        line 317: 28
        line 319: 35
        line 321: 42
        line 322: 51
        line 323: 58
        line 325: 64
        line 326: 71
        line 327: 77
        line 328: 82
        line 331: 92
        line 332: 102
        line 334: 108
        line 335: 113
        line 336: 124
        line 338: 129
        line 341: 138
        line 339: 141
        line 340: 143
        line 342: 153
        line 344: 156
        line 331: 165
        line 346: 173
      LocalVariableTable:
        Start  Length  Slot  Name   Signature
           77      15     4  view   Ljava/lang/Class;
          143      10     6     e   Ljava/lang/Exception;
          108      57     4 propName   Ljava/lang/String;
          124      41     5  prop   Lcom/fasterxml/jackson/databind/deser/SettableBeanProperty;
            0     175     0  this   Lcom/fasterxml/jackson/databind/deser/BuilderBasedDeserializer;
            0     175     1     p   Lcom/fasterxml/jackson/core/JsonParser;
            0     175     2  ctxt   Lcom/fasterxml/jackson/databind/DeserializationContext;
           51     124     3  bean   Ljava/lang/Object;
      LocalVariableTypeTable:
        Start  Length  Slot  Name   Signature
           77      15     4  view   Ljava/lang/Class<*>;
      StackMapTable: number_of_entries = 9
        frame_type = 21 /* same */
        frame_type = 13 /* same */
        frame_type = 6 /* same */
        frame_type = 252 /* append */
          offset_delta = 21
          locals = [ class java/lang/Object ]
        frame_type = 27 /* same */
        frame_type = 255 /* full_frame */
          offset_delta = 48
          locals = [ class com/fasterxml/jackson/databind/deser/BuilderBasedDeserializer, class com/fasterxml/jackson/core/JsonParser, class com/fasterxml/jackson/databind/DeserializationContext, class java/lang/Object, class java/lang/String, class com/fasterxml/jackson/databind/deser/SettableBeanProperty ]
          stack = [ class java/lang/Exception ]
        frame_type = 14 /* same */
        frame_type = 249 /* chop */
          offset_delta = 8
        frame_type = 7 /* same */
    Exceptions:
      throws java.io.IOException

  protected java.lang.Object _deserializeUsingPropertyBased(com.fasterxml.jackson.core.JsonParser, com.fasterxml.jackson.databind.DeserializationContext) throws java.io.IOException;
    descriptor: (Lcom/fasterxml/jackson/core/JsonParser;Lcom/fasterxml/jackson/databind/DeserializationContext;)Ljava/lang/Object;
    flags: (0x0004) ACC_PROTECTED
    Code:
      stack=6, locals=12, args_size=3
         0: aload_0
         1: getfield      #85                 // Field _propertyBasedCreator:Lcom/fasterxml/jackson/databind/deser/impl/PropertyBasedCreator;
         4: astore_3
         5: aload_3
         6: aload_1
         7: aload_2
         8: aload_0
         9: getfield      #6                  // Field _objectIdReader:Lcom/fasterxml/jackson/databind/deser/impl/ObjectIdReader;
        12: invokevirtual #86                 // Method com/fasterxml/jackson/databind/deser/impl/PropertyBasedCreator.startBuilding:(Lcom/fasterxml/jackson/core/JsonParser;Lcom/fasterxml/jackson/databind/DeserializationContext;Lcom/fasterxml/jackson/databind/deser/impl/ObjectIdReader;)Lcom/fasterxml/jackson/databind/deser/impl/PropertyValueBuffer;
        15: astore        4
        17: aload_0
        18: getfield      #82                 // Field _needViewProcesing:Z
        21: ifeq          31
        24: aload_2
        25: invokevirtual #83                 // Method com/fasterxml/jackson/databind/DeserializationContext.getActiveView:()Ljava/lang/Class;
        28: goto          32
        31: aconst_null
        32: astore        5
        34: aconst_null
        35: astore        6
        37: aload_1
        38: invokevirtual #67                 // Method com/fasterxml/jackson/core/JsonParser.currentToken:()Lcom/fasterxml/jackson/core/JsonToken;
        41: astore        7
        43: aload         7
        45: getstatic     #68                 // Field com/fasterxml/jackson/core/JsonToken.FIELD_NAME:Lcom/fasterxml/jackson/core/JsonToken;
        48: if_acmpne     350
        51: aload_1
        52: invokevirtual #69                 // Method com/fasterxml/jackson/core/JsonParser.currentName:()Ljava/lang/String;
        55: astore        8
        57: aload_1
        58: invokevirtual #42                 // Method com/fasterxml/jackson/core/JsonParser.nextToken:()Lcom/fasterxml/jackson/core/JsonToken;
        61: pop
        62: aload_3
        63: aload         8
        65: invokevirtual #87                 // Method com/fasterxml/jackson/databind/deser/impl/PropertyBasedCreator.findCreatorProperty:(Ljava/lang/String;)Lcom/fasterxml/jackson/databind/deser/SettableBeanProperty;
        68: astore        9
        70: aload         4
        72: aload         8
        74: invokevirtual #88                 // Method com/fasterxml/jackson/databind/deser/impl/PropertyValueBuffer.readIdProperty:(Ljava/lang/String;)Z
        77: ifeq          88
        80: aload         9
        82: ifnonnull     88
        85: goto          341
        88: aload         9
        90: ifnull        222
        93: aload         5
        95: ifnull        116
        98: aload         9
       100: aload         5
       102: invokevirtual #89                 // Method com/fasterxml/jackson/databind/deser/SettableBeanProperty.visibleInView:(Ljava/lang/Class;)Z
       105: ifne          116
       108: aload_1
       109: invokevirtual #90                 // Method com/fasterxml/jackson/core/JsonParser.skipChildren:()Lcom/fasterxml/jackson/core/JsonParser;
       112: pop
       113: goto          341
       116: aload         4
       118: aload         9
       120: aload         9
       122: aload_1
       123: aload_2
       124: invokevirtual #91                 // Method com/fasterxml/jackson/databind/deser/SettableBeanProperty.deserialize:(Lcom/fasterxml/jackson/core/JsonParser;Lcom/fasterxml/jackson/databind/DeserializationContext;)Ljava/lang/Object;
       127: invokevirtual #92                 // Method com/fasterxml/jackson/databind/deser/impl/PropertyValueBuffer.assignParameter:(Lcom/fasterxml/jackson/databind/deser/SettableBeanProperty;Ljava/lang/Object;)Z
       130: ifeq          341
       133: aload_1
       134: invokevirtual #42                 // Method com/fasterxml/jackson/core/JsonParser.nextToken:()Lcom/fasterxml/jackson/core/JsonToken;
       137: pop
       138: aload_3
       139: aload_2
       140: aload         4
       142: invokevirtual #93                 // Method com/fasterxml/jackson/databind/deser/impl/PropertyBasedCreator.build:(Lcom/fasterxml/jackson/databind/DeserializationContext;Lcom/fasterxml/jackson/databind/deser/impl/PropertyValueBuffer;)Ljava/lang/Object;
       145: astore        10
       147: goto          171
       150: astore        11
       152: aload_0
       153: aload         11
       155: aload_0
       156: getfield      #94                 // Field _beanType:Lcom/fasterxml/jackson/databind/JavaType;
       159: invokevirtual #95                 // Method com/fasterxml/jackson/databind/JavaType.getRawClass:()Ljava/lang/Class;
       162: aload         8
       164: aload_2
       165: invokevirtual #72                 // Method wrapAndThrow:(Ljava/lang/Throwable;Ljava/lang/Object;Ljava/lang/String;Lcom/fasterxml/jackson/databind/DeserializationContext;)V
       168: goto          341
       171: aload         10
       173: invokevirtual #57                 // Method java/lang/Object.getClass:()Ljava/lang/Class;
       176: aload_0
       177: getfield      #94                 // Field _beanType:Lcom/fasterxml/jackson/databind/JavaType;
       180: invokevirtual #95                 // Method com/fasterxml/jackson/databind/JavaType.getRawClass:()Ljava/lang/Class;
       183: if_acmpeq     197
       186: aload_0
       187: aload_1
       188: aload_2
       189: aload         10
       191: aload         6
       193: invokevirtual #96                 // Method handlePolymorphic:(Lcom/fasterxml/jackson/core/JsonParser;Lcom/fasterxml/jackson/databind/DeserializationContext;Ljava/lang/Object;Lcom/fasterxml/jackson/databind/util/TokenBuffer;)Ljava/lang/Object;
       196: areturn
       197: aload         6
       199: ifnull        213
       202: aload_0
       203: aload_2
       204: aload         10
       206: aload         6
       208: invokevirtual #97                 // Method handleUnknownProperties:(Lcom/fasterxml/jackson/databind/DeserializationContext;Ljava/lang/Object;Lcom/fasterxml/jackson/databind/util/TokenBuffer;)Ljava/lang/Object;
       211: astore        10
       213: aload_0
       214: aload_1
       215: aload_2
       216: aload         10
       218: invokevirtual #98                 // Method _deserialize:(Lcom/fasterxml/jackson/core/JsonParser;Lcom/fasterxml/jackson/databind/DeserializationContext;Ljava/lang/Object;)Ljava/lang/Object;
       221: areturn
       222: aload_0
       223: getfield      #31                 // Field _beanProperties:Lcom/fasterxml/jackson/databind/deser/impl/BeanPropertyMap;
       226: aload         8
       228: invokevirtual #70                 // Method com/fasterxml/jackson/databind/deser/impl/BeanPropertyMap.find:(Ljava/lang/String;)Lcom/fasterxml/jackson/databind/deser/SettableBeanProperty;
       231: astore        10
       233: aload         10
       235: ifnull        255
       238: aload         4
       240: aload         10
       242: aload         10
       244: aload_1
       245: aload_2
       246: invokevirtual #91                 // Method com/fasterxml/jackson/databind/deser/SettableBeanProperty.deserialize:(Lcom/fasterxml/jackson/core/JsonParser;Lcom/fasterxml/jackson/databind/DeserializationContext;)Ljava/lang/Object;
       249: invokevirtual #99                 // Method com/fasterxml/jackson/databind/deser/impl/PropertyValueBuffer.bufferProperty:(Lcom/fasterxml/jackson/databind/deser/SettableBeanProperty;Ljava/lang/Object;)V
       252: goto          341
       255: aload         8
       257: aload_0
       258: getfield      #100                // Field _ignorableProps:Ljava/util/Set;
       261: aload_0
       262: getfield      #23                 // Field _includableProps:Ljava/util/Set;
       265: invokestatic  #101                // Method com/fasterxml/jackson/databind/util/IgnorePropertiesUtil.shouldIgnore:(Ljava/lang/Object;Ljava/util/Collection;Ljava/util/Collection;)Z
       268: ifeq          286
       271: aload_0
       272: aload_1
       273: aload_2
       274: aload_0
       275: invokevirtual #56                 // Method handledType:()Ljava/lang/Class;
       278: aload         8
       280: invokevirtual #102                // Method handleIgnoredProperty:(Lcom/fasterxml/jackson/core/JsonParser;Lcom/fasterxml/jackson/databind/DeserializationContext;Ljava/lang/Object;Ljava/lang/String;)V
       283: goto          341
       286: aload_0
       287: getfield      #103                // Field _anySetter:Lcom/fasterxml/jackson/databind/deser/SettableAnyProperty;
       290: ifnull        316
       293: aload         4
       295: aload_0
       296: getfield      #103                // Field _anySetter:Lcom/fasterxml/jackson/databind/deser/SettableAnyProperty;
       299: aload         8
       301: aload_0
       302: getfield      #103                // Field _anySetter:Lcom/fasterxml/jackson/databind/deser/SettableAnyProperty;
       305: aload_1
       306: aload_2
       307: invokevirtual #104                // Method com/fasterxml/jackson/databind/deser/SettableAnyProperty.deserialize:(Lcom/fasterxml/jackson/core/JsonParser;Lcom/fasterxml/jackson/databind/DeserializationContext;)Ljava/lang/Object;
       310: invokevirtual #105                // Method com/fasterxml/jackson/databind/deser/impl/PropertyValueBuffer.bufferAnyProperty:(Lcom/fasterxml/jackson/databind/deser/SettableAnyProperty;Ljava/lang/String;Ljava/lang/Object;)V
       313: goto          341
       316: aload         6
       318: ifnonnull     328
       321: aload_2
       322: aload_1
       323: invokevirtual #106                // Method com/fasterxml/jackson/databind/DeserializationContext.bufferForInputBuffering:(Lcom/fasterxml/jackson/core/JsonParser;)Lcom/fasterxml/jackson/databind/util/TokenBuffer;
       326: astore        6
       328: aload         6
       330: aload         8
       332: invokevirtual #107                // Method com/fasterxml/jackson/databind/util/TokenBuffer.writeFieldName:(Ljava/lang/String;)V
       335: aload         6
       337: aload_1
       338: invokevirtual #108                // Method com/fasterxml/jackson/databind/util/TokenBuffer.copyCurrentStructure:(Lcom/fasterxml/jackson/core/JsonParser;)V
       341: aload_1
       342: invokevirtual #42                 // Method com/fasterxml/jackson/core/JsonParser.nextToken:()Lcom/fasterxml/jackson/core/JsonToken;
       345: astore        7
       347: goto          43
       350: aload_3
       351: aload_2
       352: aload         4
       354: invokevirtual #93                 // Method com/fasterxml/jackson/databind/deser/impl/PropertyBasedCreator.build:(Lcom/fasterxml/jackson/databind/DeserializationContext;Lcom/fasterxml/jackson/databind/deser/impl/PropertyValueBuffer;)Ljava/lang/Object;
       357: astore        8
       359: goto          373
       362: astore        9
       364: aload_0
       365: aload         9
       367: aload_2
       368: invokevirtual #40                 // Method wrapInstantiationProblem:(Ljava/lang/Throwable;Lcom/fasterxml/jackson/databind/DeserializationContext;)Ljava/lang/Object;
       371: astore        8
       373: aload         6
       375: ifnull        414
       378: aload         8
       380: invokevirtual #57                 // Method java/lang/Object.getClass:()Ljava/lang/Class;
       383: aload_0
       384: getfield      #94                 // Field _beanType:Lcom/fasterxml/jackson/databind/JavaType;
       387: invokevirtual #95                 // Method com/fasterxml/jackson/databind/JavaType.getRawClass:()Ljava/lang/Class;
       390: if_acmpeq     404
       393: aload_0
       394: aconst_null
       395: aload_2
       396: aload         8
       398: aload         6
       400: invokevirtual #96                 // Method handlePolymorphic:(Lcom/fasterxml/jackson/core/JsonParser;Lcom/fasterxml/jackson/databind/DeserializationContext;Ljava/lang/Object;Lcom/fasterxml/jackson/databind/util/TokenBuffer;)Ljava/lang/Object;
       403: areturn
       404: aload_0
       405: aload_2
       406: aload         8
       408: aload         6
       410: invokevirtual #97                 // Method handleUnknownProperties:(Lcom/fasterxml/jackson/databind/DeserializationContext;Ljava/lang/Object;Lcom/fasterxml/jackson/databind/util/TokenBuffer;)Ljava/lang/Object;
       413: areturn
       414: aload         8
       416: areturn
      Exception table:
         from    to  target type
           138   147   150   Class java/lang/Exception
           350   359   362   Class java/lang/Exception
      LineNumberTable:
        line 364: 0
        line 365: 5
        line 366: 17
        line 369: 34
        line 371: 37
        line 372: 43
        line 373: 51
        line 374: 57
        line 376: 62
        line 378: 70
        line 379: 85
        line 381: 88
        line 382: 93
        line 383: 108
        line 384: 113
        line 387: 116
        line 388: 133
        line 391: 138
        line 395: 147
        line 392: 150
        line 393: 152
        line 394: 168
        line 397: 171
        line 398: 186
        line 400: 197
        line 401: 202
        line 404: 213
        line 409: 222
        line 410: 233
        line 411: 238
        line 412: 252
        line 416: 255
        line 417: 271
        line 418: 283
        line 421: 286
        line 422: 293
        line 423: 313
        line 426: 316
        line 427: 321
        line 429: 328
        line 430: 335
        line 372: 341
        line 436: 350
        line 439: 359
        line 437: 362
        line 438: 364
        line 440: 373
        line 442: 378
        line 443: 393
        line 446: 404
        line 448: 414
      LocalVariableTable:
        Start  Length  Slot  Name   Signature
          147       3    10 builder   Ljava/lang/Object;
          152      19    11     e   Ljava/lang/Exception;
          171      51    10 builder   Ljava/lang/Object;
           57     284     8 propName   Ljava/lang/String;
           70     271     9 creatorProp   Lcom/fasterxml/jackson/databind/deser/SettableBeanProperty;
          233     108    10  prop   Lcom/fasterxml/jackson/databind/deser/SettableBeanProperty;
          359       3     8 builder   Ljava/lang/Object;
          364       9     9     e   Ljava/lang/Exception;
            0     417     0  this   Lcom/fasterxml/jackson/databind/deser/BuilderBasedDeserializer;
            0     417     1     p   Lcom/fasterxml/jackson/core/JsonParser;
            0     417     2  ctxt   Lcom/fasterxml/jackson/databind/DeserializationContext;
            5     412     3 creator   Lcom/fasterxml/jackson/databind/deser/impl/PropertyBasedCreator;
           17     400     4 buffer   Lcom/fasterxml/jackson/databind/deser/impl/PropertyValueBuffer;
           34     383     5 activeView   Ljava/lang/Class;
           37     380     6 unknown   Lcom/fasterxml/jackson/databind/util/TokenBuffer;
           43     374     7     t   Lcom/fasterxml/jackson/core/JsonToken;
          373      44     8 builder   Ljava/lang/Object;
      LocalVariableTypeTable:
        Start  Length  Slot  Name   Signature
           34     383     5 activeView   Ljava/lang/Class<*>;
      StackMapTable: number_of_entries = 20
        frame_type = 253 /* append */
          offset_delta = 31
          locals = [ class com/fasterxml/jackson/databind/deser/impl/PropertyBasedCreator, class com/fasterxml/jackson/databind/deser/impl/PropertyValueBuffer ]
        frame_type = 64 /* same_locals_1_stack_item */
          stack = [ class java/lang/Class ]
        frame_type = 254 /* append */
          offset_delta = 10
          locals = [ class java/lang/Class, class com/fasterxml/jackson/databind/util/TokenBuffer, class com/fasterxml/jackson/core/JsonToken ]
        frame_type = 253 /* append */
          offset_delta = 44
          locals = [ class java/lang/String, class com/fasterxml/jackson/databind/deser/SettableBeanProperty ]
        frame_type = 27 /* same */
        frame_type = 97 /* same_locals_1_stack_item */
          stack = [ class java/lang/Exception ]
        frame_type = 252 /* append */
          offset_delta = 20
          locals = [ class java/lang/Object ]
        frame_type = 25 /* same */
        frame_type = 15 /* same */
        frame_type = 250 /* chop */
          offset_delta = 8
        frame_type = 252 /* append */
          offset_delta = 32
          locals = [ class com/fasterxml/jackson/databind/deser/SettableBeanProperty ]
        frame_type = 30 /* same */
        frame_type = 29 /* same */
        frame_type = 11 /* same */
        frame_type = 248 /* chop */
          offset_delta = 12
        frame_type = 8 /* same */
        frame_type = 75 /* same_locals_1_stack_item */
          stack = [ class java/lang/Exception ]
        frame_type = 252 /* append */
          offset_delta = 10
          locals = [ class java/lang/Object ]
        frame_type = 30 /* same */
        frame_type = 9 /* same */
    Exceptions:
      throws java.io.IOException

  protected final java.lang.Object _deserialize(com.fasterxml.jackson.core.JsonParser, com.fasterxml.jackson.databind.DeserializationContext, java.lang.Object) throws java.io.IOException;
    descriptor: (Lcom/fasterxml/jackson/core/JsonParser;Lcom/fasterxml/jackson/databind/DeserializationContext;Ljava/lang/Object;)Ljava/lang/Object;
    flags: (0x0014) ACC_PROTECTED, ACC_FINAL
    Code:
      stack=5, locals=8, args_size=4
         0: aload_0
         1: getfield      #80                 // Field _injectables:[Lcom/fasterxml/jackson/databind/deser/impl/ValueInjector;
         4: ifnull        13
         7: aload_0
         8: aload_2
         9: aload_3
        10: invokevirtual #81                 // Method injectValues:(Lcom/fasterxml/jackson/databind/DeserializationContext;Ljava/lang/Object;)V
        13: aload_0
        14: getfield      #75                 // Field _unwrappedPropertyHandler:Lcom/fasterxml/jackson/databind/deser/impl/UnwrappedPropertyHandler;
        17: ifnull        57
        20: aload_1
        21: getstatic     #109                // Field com/fasterxml/jackson/core/JsonToken.START_OBJECT:Lcom/fasterxml/jackson/core/JsonToken;
        24: invokevirtual #110                // Method com/fasterxml/jackson/core/JsonParser.hasToken:(Lcom/fasterxml/jackson/core/JsonToken;)Z
        27: ifeq          35
        30: aload_1
        31: invokevirtual #42                 // Method com/fasterxml/jackson/core/JsonParser.nextToken:()Lcom/fasterxml/jackson/core/JsonToken;
        34: pop
        35: aload_2
        36: aload_1
        37: invokevirtual #106                // Method com/fasterxml/jackson/databind/DeserializationContext.bufferForInputBuffering:(Lcom/fasterxml/jackson/core/JsonParser;)Lcom/fasterxml/jackson/databind/util/TokenBuffer;
        40: astore        4
        42: aload         4
        44: invokevirtual #111                // Method com/fasterxml/jackson/databind/util/TokenBuffer.writeStartObject:()V
        47: aload_0
        48: aload_1
        49: aload_2
        50: aload_3
        51: aload         4
        53: invokevirtual #112                // Method deserializeWithUnwrapped:(Lcom/fasterxml/jackson/core/JsonParser;Lcom/fasterxml/jackson/databind/DeserializationContext;Ljava/lang/Object;Lcom/fasterxml/jackson/databind/util/TokenBuffer;)Ljava/lang/Object;
        56: areturn
        57: aload_0
        58: getfield      #77                 // Field _externalTypeIdHandler:Lcom/fasterxml/jackson/databind/deser/impl/ExternalTypeHandler;
        61: ifnull        72
        64: aload_0
        65: aload_1
        66: aload_2
        67: aload_3
        68: invokevirtual #113                // Method deserializeWithExternalTypeId:(Lcom/fasterxml/jackson/core/JsonParser;Lcom/fasterxml/jackson/databind/DeserializationContext;Ljava/lang/Object;)Ljava/lang/Object;
        71: areturn
        72: aload_0
        73: getfield      #82                 // Field _needViewProcesing:Z
        76: ifeq          100
        79: aload_2
        80: invokevirtual #83                 // Method com/fasterxml/jackson/databind/DeserializationContext.getActiveView:()Ljava/lang/Class;
        83: astore        4
        85: aload         4
        87: ifnull        100
        90: aload_0
        91: aload_1
        92: aload_2
        93: aload_3
        94: aload         4
        96: invokevirtual #84                 // Method deserializeWithView:(Lcom/fasterxml/jackson/core/JsonParser;Lcom/fasterxml/jackson/databind/DeserializationContext;Ljava/lang/Object;Ljava/lang/Class;)Ljava/lang/Object;
        99: areturn
       100: aload_1
       101: invokevirtual #67                 // Method com/fasterxml/jackson/core/JsonParser.currentToken:()Lcom/fasterxml/jackson/core/JsonToken;
       104: astore        4
       106: aload         4
       108: getstatic     #109                // Field com/fasterxml/jackson/core/JsonToken.START_OBJECT:Lcom/fasterxml/jackson/core/JsonToken;
       111: if_acmpne     120
       114: aload_1
       115: invokevirtual #42                 // Method com/fasterxml/jackson/core/JsonParser.nextToken:()Lcom/fasterxml/jackson/core/JsonToken;
       118: astore        4
       120: aload         4
       122: getstatic     #68                 // Field com/fasterxml/jackson/core/JsonToken.FIELD_NAME:Lcom/fasterxml/jackson/core/JsonToken;
       125: if_acmpne     200
       128: aload_1
       129: invokevirtual #69                 // Method com/fasterxml/jackson/core/JsonParser.currentName:()Ljava/lang/String;
       132: astore        5
       134: aload_1
       135: invokevirtual #42                 // Method com/fasterxml/jackson/core/JsonParser.nextToken:()Lcom/fasterxml/jackson/core/JsonToken;
       138: pop
       139: aload_0
       140: getfield      #31                 // Field _beanProperties:Lcom/fasterxml/jackson/databind/deser/impl/BeanPropertyMap;
       143: aload         5
       145: invokevirtual #70                 // Method com/fasterxml/jackson/databind/deser/impl/BeanPropertyMap.find:(Ljava/lang/String;)Lcom/fasterxml/jackson/databind/deser/SettableBeanProperty;
       148: astore        6
       150: aload         6
       152: ifnull        182
       155: aload         6
       157: aload_1
       158: aload_2
       159: aload_3
       160: invokevirtual #71                 // Method com/fasterxml/jackson/databind/deser/SettableBeanProperty.deserializeSetAndReturn:(Lcom/fasterxml/jackson/core/JsonParser;Lcom/fasterxml/jackson/databind/DeserializationContext;Ljava/lang/Object;)Ljava/lang/Object;
       163: astore_3
       164: goto          191
       167: astore        7
       169: aload_0
       170: aload         7
       172: aload_3
       173: aload         5
       175: aload_2
       176: invokevirtual #72                 // Method wrapAndThrow:(Ljava/lang/Throwable;Ljava/lang/Object;Ljava/lang/String;Lcom/fasterxml/jackson/databind/DeserializationContext;)V
       179: goto          191
       182: aload_0
       183: aload_1
       184: aload_2
       185: aload_3
       186: aload         5
       188: invokevirtual #73                 // Method handleUnknownVanilla:(Lcom/fasterxml/jackson/core/JsonParser;Lcom/fasterxml/jackson/databind/DeserializationContext;Ljava/lang/Object;Ljava/lang/String;)V
       191: aload_1
       192: invokevirtual #42                 // Method com/fasterxml/jackson/core/JsonParser.nextToken:()Lcom/fasterxml/jackson/core/JsonToken;
       195: astore        4
       197: goto          120
       200: aload_3
       201: areturn
      Exception table:
         from    to  target type
           155   164   167   Class java/lang/Exception
      LineNumberTable:
        line 454: 0
        line 455: 7
        line 457: 13
        line 458: 20
        line 459: 30
        line 461: 35
        line 462: 42
        line 463: 47
        line 465: 57
        line 466: 64
        line 468: 72
        line 469: 79
        line 470: 85
        line 471: 90
        line 474: 100
        line 476: 106
        line 477: 114
        line 479: 120
        line 480: 128
        line 482: 134
        line 483: 139
        line 485: 150
        line 487: 155
        line 490: 164
        line 488: 167
        line 489: 169
        line 491: 179
        line 493: 182
        line 479: 191
        line 495: 200
      LocalVariableTable:
        Start  Length  Slot  Name   Signature
           42      15     4 tokens   Lcom/fasterxml/jackson/databind/util/TokenBuffer;
           85      15     4  view   Ljava/lang/Class;
          169      10     7     e   Ljava/lang/Exception;
          134      57     5 propName   Ljava/lang/String;
          150      41     6  prop   Lcom/fasterxml/jackson/databind/deser/SettableBeanProperty;
            0     202     0  this   Lcom/fasterxml/jackson/databind/deser/BuilderBasedDeserializer;
            0     202     1     p   Lcom/fasterxml/jackson/core/JsonParser;
            0     202     2  ctxt   Lcom/fasterxml/jackson/databind/DeserializationContext;
            0     202     3 builder   Ljava/lang/Object;
          106      96     4     t   Lcom/fasterxml/jackson/core/JsonToken;
      LocalVariableTypeTable:
        Start  Length  Slot  Name   Signature
           85      15     4  view   Ljava/lang/Class<*>;
      StackMapTable: number_of_entries = 10
        frame_type = 13 /* same */
        frame_type = 21 /* same */
        frame_type = 21 /* same */
        frame_type = 14 /* same */
        frame_type = 27 /* same */
        frame_type = 252 /* append */
          offset_delta = 19
          locals = [ class com/fasterxml/jackson/core/JsonToken ]
        frame_type = 255 /* full_frame */
          offset_delta = 46
          locals = [ class com/fasterxml/jackson/databind/deser/BuilderBasedDeserializer, class com/fasterxml/jackson/core/JsonParser, class com/fasterxml/jackson/databind/DeserializationContext, class java/lang/Object, class com/fasterxml/jackson/core/JsonToken, class java/lang/String, class com/fasterxml/jackson/databind/deser/SettableBeanProperty ]
          stack = [ class java/lang/Exception ]
        frame_type = 14 /* same */
        frame_type = 249 /* chop */
          offset_delta = 8
        frame_type = 8 /* same */
    Exceptions:
      throws java.io.IOException

  protected java.lang.Object _deserializeFromArray(com.fasterxml.jackson.core.JsonParser, com.fasterxml.jackson.databind.DeserializationContext) throws java.io.IOException;
    descriptor: (Lcom/fasterxml/jackson/core/JsonParser;Lcom/fasterxml/jackson/databind/DeserializationContext;)Ljava/lang/Object;
    flags: (0x0004) ACC_PROTECTED
    Code:
      stack=6, locals=8, args_size=3
         0: aload_0
         1: getfield      #114                // Field _arrayDelegateDeserializer:Lcom/fasterxml/jackson/databind/JsonDeserializer;
         4: astore_3
         5: aload_3
         6: ifnonnull     18
         9: aload_0
        10: getfield      #115                // Field _delegateDeserializer:Lcom/fasterxml/jackson/databind/JsonDeserializer;
        13: dup
        14: astore_3
        15: ifnull        56
        18: aload_0
        19: getfield      #65                 // Field _valueInstantiator:Lcom/fasterxml/jackson/databind/deser/ValueInstantiator;
        22: aload_2
        23: aload_3
        24: aload_1
        25: aload_2
        26: invokevirtual #116                // Method com/fasterxml/jackson/databind/JsonDeserializer.deserialize:(Lcom/fasterxml/jackson/core/JsonParser;Lcom/fasterxml/jackson/databind/DeserializationContext;)Ljava/lang/Object;
        29: invokevirtual #117                // Method com/fasterxml/jackson/databind/deser/ValueInstantiator.createUsingArrayDelegate:(Lcom/fasterxml/jackson/databind/DeserializationContext;Ljava/lang/Object;)Ljava/lang/Object;
        32: astore        4
        34: aload_0
        35: getfield      #80                 // Field _injectables:[Lcom/fasterxml/jackson/databind/deser/impl/ValueInjector;
        38: ifnull        48
        41: aload_0
        42: aload_2
        43: aload         4
        45: invokevirtual #81                 // Method injectValues:(Lcom/fasterxml/jackson/databind/DeserializationContext;Ljava/lang/Object;)V
        48: aload_0
        49: aload_2
        50: aload         4
        52: invokevirtual #45                 // Method finishBuild:(Lcom/fasterxml/jackson/databind/DeserializationContext;Ljava/lang/Object;)Ljava/lang/Object;
        55: areturn
        56: aload_0
        57: aload_2
        58: invokevirtual #118                // Method _findCoercionFromEmptyArray:(Lcom/fasterxml/jackson/databind/DeserializationContext;)Lcom/fasterxml/jackson/databind/cfg/CoercionAction;
        61: astore        4
        63: aload_2
        64: getstatic     #119                // Field com/fasterxml/jackson/databind/DeserializationFeature.UNWRAP_SINGLE_VALUE_ARRAYS:Lcom/fasterxml/jackson/databind/DeserializationFeature;
        67: invokevirtual #120                // Method com/fasterxml/jackson/databind/DeserializationContext.isEnabled:(Lcom/fasterxml/jackson/databind/DeserializationFeature;)Z
        70: istore        5
        72: iload         5
        74: ifne          85
        77: aload         4
        79: getstatic     #121                // Field com/fasterxml/jackson/databind/cfg/CoercionAction.Fail:Lcom/fasterxml/jackson/databind/cfg/CoercionAction;
        82: if_acmpeq     199
        85: aload_1
        86: invokevirtual #42                 // Method com/fasterxml/jackson/core/JsonParser.nextToken:()Lcom/fasterxml/jackson/core/JsonToken;
        89: astore        6
        91: aload         6
        93: getstatic     #122                // Field com/fasterxml/jackson/core/JsonToken.END_ARRAY:Lcom/fasterxml/jackson/core/JsonToken;
        96: if_acmpne     167
        99: getstatic     #123                // Field com/fasterxml/jackson/databind/deser/BuilderBasedDeserializer$1.$SwitchMap$com$fasterxml$jackson$databind$cfg$CoercionAction:[I
       102: aload         4
       104: invokevirtual #124                // Method com/fasterxml/jackson/databind/cfg/CoercionAction.ordinal:()I
       107: iaload
       108: tableswitch   { // 1 to 3
                       1: 136
                       2: 142
                       3: 142
                 default: 148
            }
       136: aload_0
       137: aload_2
       138: invokevirtual #125                // Method getEmptyValue:(Lcom/fasterxml/jackson/databind/DeserializationContext;)Ljava/lang/Object;
       141: areturn
       142: aload_0
       143: aload_2
       144: invokevirtual #126                // Method getNullValue:(Lcom/fasterxml/jackson/databind/DeserializationContext;)Ljava/lang/Object;
       147: areturn
       148: aload_2
       149: aload_0
       150: aload_2
       151: invokevirtual #54                 // Method getValueType:(Lcom/fasterxml/jackson/databind/DeserializationContext;)Lcom/fasterxml/jackson/databind/JavaType;
       154: getstatic     #127                // Field com/fasterxml/jackson/core/JsonToken.START_ARRAY:Lcom/fasterxml/jackson/core/JsonToken;
       157: aload_1
       158: aconst_null
       159: iconst_0
       160: anewarray     #60                 // class java/lang/Object
       163: invokevirtual #128                // Method com/fasterxml/jackson/databind/DeserializationContext.handleUnexpectedToken:(Lcom/fasterxml/jackson/databind/JavaType;Lcom/fasterxml/jackson/core/JsonToken;Lcom/fasterxml/jackson/core/JsonParser;Ljava/lang/String;[Ljava/lang/Object;)Ljava/lang/Object;
       166: areturn
       167: iload         5
       169: ifeq          199
       172: aload_0
       173: aload_1
       174: aload_2
       175: invokevirtual #129                // Method deserialize:(Lcom/fasterxml/jackson/core/JsonParser;Lcom/fasterxml/jackson/databind/DeserializationContext;)Ljava/lang/Object;
       178: astore        7
       180: aload_1
       181: invokevirtual #42                 // Method com/fasterxml/jackson/core/JsonParser.nextToken:()Lcom/fasterxml/jackson/core/JsonToken;
       184: getstatic     #122                // Field com/fasterxml/jackson/core/JsonToken.END_ARRAY:Lcom/fasterxml/jackson/core/JsonToken;
       187: if_acmpeq     196
       190: aload_0
       191: aload_1
       192: aload_2
       193: invokevirtual #130                // Method handleMissingEndArrayForSingle:(Lcom/fasterxml/jackson/core/JsonParser;Lcom/fasterxml/jackson/databind/DeserializationContext;)V
       196: aload         7
       198: areturn
       199: aload_2
       200: aload_0
       201: aload_2
       202: invokevirtual #54                 // Method getValueType:(Lcom/fasterxml/jackson/databind/DeserializationContext;)Lcom/fasterxml/jackson/databind/JavaType;
       205: aload_1
       206: invokevirtual #55                 // Method com/fasterxml/jackson/databind/DeserializationContext.handleUnexpectedToken:(Lcom/fasterxml/jackson/databind/JavaType;Lcom/fasterxml/jackson/core/JsonParser;)Ljava/lang/Object;
       209: areturn
      LineNumberTable:
        line 502: 0
        line 504: 5
        line 505: 18
        line 506: 26
        line 505: 29
        line 507: 34
        line 508: 41
        line 510: 48
        line 512: 56
        line 513: 63
        line 515: 72
        line 516: 85
        line 517: 91
        line 518: 99
        line 520: 136
        line 523: 142
        line 526: 148
        line 528: 167
        line 529: 172
        line 530: 180
        line 531: 190
        line 533: 196
        line 536: 199
      LocalVariableTable:
        Start  Length  Slot  Name   Signature
           34      22     4 builder   Ljava/lang/Object;
          180      19     7 value   Ljava/lang/Object;
           91     108     6     t   Lcom/fasterxml/jackson/core/JsonToken;
            0     210     0  this   Lcom/fasterxml/jackson/databind/deser/BuilderBasedDeserializer;
            0     210     1     p   Lcom/fasterxml/jackson/core/JsonParser;
            0     210     2  ctxt   Lcom/fasterxml/jackson/databind/DeserializationContext;
            5     205     3 delegateDeser   Lcom/fasterxml/jackson/databind/JsonDeserializer;
           63     147     4   act   Lcom/fasterxml/jackson/databind/cfg/CoercionAction;
           72     138     5 unwrap   Z
      LocalVariableTypeTable:
        Start  Length  Slot  Name   Signature
            5     205     3 delegateDeser   Lcom/fasterxml/jackson/databind/JsonDeserializer<Ljava/lang/Object;>;
      StackMapTable: number_of_entries = 10
        frame_type = 252 /* append */
          offset_delta = 18
          locals = [ class com/fasterxml/jackson/databind/JsonDeserializer ]
        frame_type = 252 /* append */
          offset_delta = 29
          locals = [ class java/lang/Object ]
        frame_type = 250 /* chop */
          offset_delta = 7
        frame_type = 253 /* append */
          offset_delta = 28
          locals = [ class com/fasterxml/jackson/databind/cfg/CoercionAction, int ]
        frame_type = 252 /* append */
          offset_delta = 50
          locals = [ class com/fasterxml/jackson/core/JsonToken ]
        frame_type = 5 /* same */
        frame_type = 5 /* same */
        frame_type = 18 /* same */
        frame_type = 252 /* append */
          offset_delta = 28
          locals = [ class java/lang/Object ]
        frame_type = 249 /* chop */
          offset_delta = 2
    Exceptions:
      throws java.io.IOException

  protected final java.lang.Object deserializeWithView(com.fasterxml.jackson.core.JsonParser, com.fasterxml.jackson.databind.DeserializationContext, java.lang.Object, java.lang.Class<?>) throws java.io.IOException;
    descriptor: (Lcom/fasterxml/jackson/core/JsonParser;Lcom/fasterxml/jackson/databind/DeserializationContext;Ljava/lang/Object;Ljava/lang/Class;)Ljava/lang/Object;
    flags: (0x0014) ACC_PROTECTED, ACC_FINAL
    Code:
      stack=5, locals=9, args_size=5
         0: aload_1
         1: invokevirtual #67                 // Method com/fasterxml/jackson/core/JsonParser.currentToken:()Lcom/fasterxml/jackson/core/JsonToken;
         4: astore        5
         6: aload         5
         8: getstatic     #68                 // Field com/fasterxml/jackson/core/JsonToken.FIELD_NAME:Lcom/fasterxml/jackson/core/JsonToken;
        11: if_acmpne     104
        14: aload_1
        15: invokevirtual #69                 // Method com/fasterxml/jackson/core/JsonParser.currentName:()Ljava/lang/String;
        18: astore        6
        20: aload_1
        21: invokevirtual #42                 // Method com/fasterxml/jackson/core/JsonParser.nextToken:()Lcom/fasterxml/jackson/core/JsonToken;
        24: pop
        25: aload_0
        26: getfield      #31                 // Field _beanProperties:Lcom/fasterxml/jackson/databind/deser/impl/BeanPropertyMap;
        29: aload         6
        31: invokevirtual #70                 // Method com/fasterxml/jackson/databind/deser/impl/BeanPropertyMap.find:(Ljava/lang/String;)Lcom/fasterxml/jackson/databind/deser/SettableBeanProperty;
        34: astore        7
        36: aload         7
        38: ifnull        86
        41: aload         7
        43: aload         4
        45: invokevirtual #89                 // Method com/fasterxml/jackson/databind/deser/SettableBeanProperty.visibleInView:(Ljava/lang/Class;)Z
        48: ifne          59
        51: aload_1
        52: invokevirtual #90                 // Method com/fasterxml/jackson/core/JsonParser.skipChildren:()Lcom/fasterxml/jackson/core/JsonParser;
        55: pop
        56: goto          95
        59: aload         7
        61: aload_1
        62: aload_2
        63: aload_3
        64: invokevirtual #71                 // Method com/fasterxml/jackson/databind/deser/SettableBeanProperty.deserializeSetAndReturn:(Lcom/fasterxml/jackson/core/JsonParser;Lcom/fasterxml/jackson/databind/DeserializationContext;Ljava/lang/Object;)Ljava/lang/Object;
        67: astore_3
        68: goto          95
        71: astore        8
        73: aload_0
        74: aload         8
        76: aload_3
        77: aload         6
        79: aload_2
        80: invokevirtual #72                 // Method wrapAndThrow:(Ljava/lang/Throwable;Ljava/lang/Object;Ljava/lang/String;Lcom/fasterxml/jackson/databind/DeserializationContext;)V
        83: goto          95
        86: aload_0
        87: aload_1
        88: aload_2
        89: aload_3
        90: aload         6
        92: invokevirtual #73                 // Method handleUnknownVanilla:(Lcom/fasterxml/jackson/core/JsonParser;Lcom/fasterxml/jackson/databind/DeserializationContext;Ljava/lang/Object;Ljava/lang/String;)V
        95: aload_1
        96: invokevirtual #42                 // Method com/fasterxml/jackson/core/JsonParser.nextToken:()Lcom/fasterxml/jackson/core/JsonToken;
        99: astore        5
       101: goto          6
       104: aload_3
       105: areturn
      Exception table:
         from    to  target type
            59    68    71   Class java/lang/Exception
      LineNumberTable:
        line 549: 0
        line 550: 6
        line 551: 14
        line 553: 20
        line 554: 25
        line 555: 36
        line 556: 41
        line 557: 51
        line 558: 56
        line 561: 59
        line 564: 68
        line 562: 71
        line 563: 73
        line 565: 83
        line 567: 86
        line 550: 95
        line 569: 104
      LocalVariableTable:
        Start  Length  Slot  Name   Signature
           73      10     8     e   Ljava/lang/Exception;
           20      75     6 propName   Ljava/lang/String;
           36      59     7  prop   Lcom/fasterxml/jackson/databind/deser/SettableBeanProperty;
            0     106     0  this   Lcom/fasterxml/jackson/databind/deser/BuilderBasedDeserializer;
            0     106     1     p   Lcom/fasterxml/jackson/core/JsonParser;
            0     106     2  ctxt   Lcom/fasterxml/jackson/databind/DeserializationContext;
            0     106     3  bean   Ljava/lang/Object;
            0     106     4 activeView   Ljava/lang/Class;
            6     100     5     t   Lcom/fasterxml/jackson/core/JsonToken;
      LocalVariableTypeTable:
        Start  Length  Slot  Name   Signature
            0     106     4 activeView   Ljava/lang/Class<*>;
      StackMapTable: number_of_entries = 6
        frame_type = 252 /* append */
          offset_delta = 6
          locals = [ class com/fasterxml/jackson/core/JsonToken ]
        frame_type = 253 /* append */
          offset_delta = 52
          locals = [ class java/lang/String, class com/fasterxml/jackson/databind/deser/SettableBeanProperty ]
        frame_type = 75 /* same_locals_1_stack_item */
          stack = [ class java/lang/Exception ]
        frame_type = 14 /* same */
        frame_type = 249 /* chop */
          offset_delta = 8
        frame_type = 8 /* same */
    Exceptions:
      throws java.io.IOException
    Signature: #297                         // (Lcom/fasterxml/jackson/core/JsonParser;Lcom/fasterxml/jackson/databind/DeserializationContext;Ljava/lang/Object;Ljava/lang/Class<*>;)Ljava/lang/Object;

  protected java.lang.Object deserializeWithUnwrapped(com.fasterxml.jackson.core.JsonParser, com.fasterxml.jackson.databind.DeserializationContext) throws java.io.IOException;
    descriptor: (Lcom/fasterxml/jackson/core/JsonParser;Lcom/fasterxml/jackson/databind/DeserializationContext;)Ljava/lang/Object;
    flags: (0x0004) ACC_PROTECTED
    Code:
      stack=5, locals=9, args_size=3
         0: aload_0
         1: getfield      #115                // Field _delegateDeserializer:Lcom/fasterxml/jackson/databind/JsonDeserializer;
         4: ifnull        25
         7: aload_0
         8: getfield      #65                 // Field _valueInstantiator:Lcom/fasterxml/jackson/databind/deser/ValueInstantiator;
        11: aload_2
        12: aload_0
        13: getfield      #115                // Field _delegateDeserializer:Lcom/fasterxml/jackson/databind/JsonDeserializer;
        16: aload_1
        17: aload_2
        18: invokevirtual #116                // Method com/fasterxml/jackson/databind/JsonDeserializer.deserialize:(Lcom/fasterxml/jackson/core/JsonParser;Lcom/fasterxml/jackson/databind/DeserializationContext;)Ljava/lang/Object;
        21: invokevirtual #131                // Method com/fasterxml/jackson/databind/deser/ValueInstantiator.createUsingDelegate:(Lcom/fasterxml/jackson/databind/DeserializationContext;Ljava/lang/Object;)Ljava/lang/Object;
        24: areturn
        25: aload_0
        26: getfield      #85                 // Field _propertyBasedCreator:Lcom/fasterxml/jackson/databind/deser/impl/PropertyBasedCreator;
        29: ifnull        39
        32: aload_0
        33: aload_1
        34: aload_2
        35: invokevirtual #132                // Method deserializeUsingPropertyBasedWithUnwrapped:(Lcom/fasterxml/jackson/core/JsonParser;Lcom/fasterxml/jackson/databind/DeserializationContext;)Ljava/lang/Object;
        38: areturn
        39: aload_2
        40: aload_1
        41: invokevirtual #106                // Method com/fasterxml/jackson/databind/DeserializationContext.bufferForInputBuffering:(Lcom/fasterxml/jackson/core/JsonParser;)Lcom/fasterxml/jackson/databind/util/TokenBuffer;
        44: astore_3
        45: aload_3
        46: invokevirtual #111                // Method com/fasterxml/jackson/databind/util/TokenBuffer.writeStartObject:()V
        49: aload_0
        50: getfield      #65                 // Field _valueInstantiator:Lcom/fasterxml/jackson/databind/deser/ValueInstantiator;
        53: aload_2
        54: invokevirtual #66                 // Method com/fasterxml/jackson/databind/deser/ValueInstantiator.createUsingDefault:(Lcom/fasterxml/jackson/databind/DeserializationContext;)Ljava/lang/Object;
        57: astore        4
        59: aload_0
        60: getfield      #80                 // Field _injectables:[Lcom/fasterxml/jackson/databind/deser/impl/ValueInjector;
        63: ifnull        73
        66: aload_0
        67: aload_2
        68: aload         4
        70: invokevirtual #81                 // Method injectValues:(Lcom/fasterxml/jackson/databind/DeserializationContext;Ljava/lang/Object;)V
        73: aload_0
        74: getfield      #82                 // Field _needViewProcesing:Z
        77: ifeq          87
        80: aload_2
        81: invokevirtual #83                 // Method com/fasterxml/jackson/databind/DeserializationContext.getActiveView:()Ljava/lang/Class;
        84: goto          88
        87: aconst_null
        88: astore        5
        90: aload_1
        91: invokevirtual #67                 // Method com/fasterxml/jackson/core/JsonParser.currentToken:()Lcom/fasterxml/jackson/core/JsonToken;
        94: getstatic     #68                 // Field com/fasterxml/jackson/core/JsonToken.FIELD_NAME:Lcom/fasterxml/jackson/core/JsonToken;
        97: if_acmpne     267
       100: aload_1
       101: invokevirtual #69                 // Method com/fasterxml/jackson/core/JsonParser.currentName:()Ljava/lang/String;
       104: astore        6
       106: aload_1
       107: invokevirtual #42                 // Method com/fasterxml/jackson/core/JsonParser.nextToken:()Lcom/fasterxml/jackson/core/JsonToken;
       110: pop
       111: aload_0
       112: getfield      #31                 // Field _beanProperties:Lcom/fasterxml/jackson/databind/deser/impl/BeanPropertyMap;
       115: aload         6
       117: invokevirtual #70                 // Method com/fasterxml/jackson/databind/deser/impl/BeanPropertyMap.find:(Ljava/lang/String;)Lcom/fasterxml/jackson/databind/deser/SettableBeanProperty;
       120: astore        7
       122: aload         7
       124: ifnull        180
       127: aload         5
       129: ifnull        150
       132: aload         7
       134: aload         5
       136: invokevirtual #89                 // Method com/fasterxml/jackson/databind/deser/SettableBeanProperty.visibleInView:(Ljava/lang/Class;)Z
       139: ifne          150
       142: aload_1
       143: invokevirtual #90                 // Method com/fasterxml/jackson/core/JsonParser.skipChildren:()Lcom/fasterxml/jackson/core/JsonParser;
       146: pop
       147: goto          259
       150: aload         7
       152: aload_1
       153: aload_2
       154: aload         4
       156: invokevirtual #71                 // Method com/fasterxml/jackson/databind/deser/SettableBeanProperty.deserializeSetAndReturn:(Lcom/fasterxml/jackson/core/JsonParser;Lcom/fasterxml/jackson/databind/DeserializationContext;Ljava/lang/Object;)Ljava/lang/Object;
       159: astore        4
       161: goto          259
       164: astore        8
       166: aload_0
       167: aload         8
       169: aload         4
       171: aload         6
       173: aload_2
       174: invokevirtual #72                 // Method wrapAndThrow:(Ljava/lang/Throwable;Ljava/lang/Object;Ljava/lang/String;Lcom/fasterxml/jackson/databind/DeserializationContext;)V
       177: goto          259
       180: aload         6
       182: aload_0
       183: getfield      #100                // Field _ignorableProps:Ljava/util/Set;
       186: aload_0
       187: getfield      #23                 // Field _includableProps:Ljava/util/Set;
       190: invokestatic  #101                // Method com/fasterxml/jackson/databind/util/IgnorePropertiesUtil.shouldIgnore:(Ljava/lang/Object;Ljava/util/Collection;Ljava/util/Collection;)Z
       193: ifeq          209
       196: aload_0
       197: aload_1
       198: aload_2
       199: aload         4
       201: aload         6
       203: invokevirtual #102                // Method handleIgnoredProperty:(Lcom/fasterxml/jackson/core/JsonParser;Lcom/fasterxml/jackson/databind/DeserializationContext;Ljava/lang/Object;Ljava/lang/String;)V
       206: goto          259
       209: aload_3
       210: aload         6
       212: invokevirtual #107                // Method com/fasterxml/jackson/databind/util/TokenBuffer.writeFieldName:(Ljava/lang/String;)V
       215: aload_3
       216: aload_1
       217: invokevirtual #108                // Method com/fasterxml/jackson/databind/util/TokenBuffer.copyCurrentStructure:(Lcom/fasterxml/jackson/core/JsonParser;)V
       220: aload_0
       221: getfield      #103                // Field _anySetter:Lcom/fasterxml/jackson/databind/deser/SettableAnyProperty;
       224: ifnull        259
       227: aload_0
       228: getfield      #103                // Field _anySetter:Lcom/fasterxml/jackson/databind/deser/SettableAnyProperty;
       231: aload_1
       232: aload_2
       233: aload         4
       235: aload         6
       237: invokevirtual #133                // Method com/fasterxml/jackson/databind/deser/SettableAnyProperty.deserializeAndSet:(Lcom/fasterxml/jackson/core/JsonParser;Lcom/fasterxml/jackson/databind/DeserializationContext;Ljava/lang/Object;Ljava/lang/String;)V
       240: goto          259
       243: astore        8
       245: aload_0
       246: aload         8
       248: aload         4
       250: aload         6
       252: aload_2
       253: invokevirtual #72                 // Method wrapAndThrow:(Ljava/lang/Throwable;Ljava/lang/Object;Ljava/lang/String;Lcom/fasterxml/jackson/databind/DeserializationContext;)V
       256: goto          259
       259: aload_1
       260: invokevirtual #42                 // Method com/fasterxml/jackson/core/JsonParser.nextToken:()Lcom/fasterxml/jackson/core/JsonToken;
       263: pop
       264: goto          90
       267: aload_3
       268: invokevirtual #134                // Method com/fasterxml/jackson/databind/util/TokenBuffer.writeEndObject:()V
       271: aload_0
       272: getfield      #75                 // Field _unwrappedPropertyHandler:Lcom/fasterxml/jackson/databind/deser/impl/UnwrappedPropertyHandler;
       275: aload_1
       276: aload_2
       277: aload         4
       279: aload_3
       280: invokevirtual #135                // Method com/fasterxml/jackson/databind/deser/impl/UnwrappedPropertyHandler.processUnwrapped:(Lcom/fasterxml/jackson/core/JsonParser;Lcom/fasterxml/jackson/databind/DeserializationContext;Ljava/lang/Object;Lcom/fasterxml/jackson/databind/util/TokenBuffer;)Ljava/lang/Object;
       283: areturn
      Exception table:
         from    to  target type
           150   161   164   Class java/lang/Exception
           227   240   243   Class java/lang/Exception
      LineNumberTable:
        line 586: 0
        line 587: 7
        line 589: 25
        line 590: 32
        line 592: 39
        line 593: 45
        line 594: 49
        line 596: 59
        line 597: 66
        line 600: 73
        line 601: 90
        line 602: 100
        line 603: 106
        line 604: 111
        line 605: 122
        line 606: 127
        line 607: 142
        line 608: 147
        line 611: 150
        line 614: 161
        line 612: 164
        line 613: 166
        line 615: 177
        line 618: 180
        line 619: 196
        line 620: 206
        line 623: 209
        line 624: 215
        line 626: 220
        line 628: 227
        line 631: 240
        line 629: 243
        line 630: 245
        line 632: 256
        line 601: 259
        line 635: 267
        line 636: 271
      LocalVariableTable:
        Start  Length  Slot  Name   Signature
          166      11     8     e   Ljava/lang/Exception;
          245      11     8     e   Ljava/lang/Exception;
          106     153     6 propName   Ljava/lang/String;
          122     137     7  prop   Lcom/fasterxml/jackson/databind/deser/SettableBeanProperty;
            0     284     0  this   Lcom/fasterxml/jackson/databind/deser/BuilderBasedDeserializer;
            0     284     1     p   Lcom/fasterxml/jackson/core/JsonParser;
            0     284     2  ctxt   Lcom/fasterxml/jackson/databind/DeserializationContext;
           45     239     3 tokens   Lcom/fasterxml/jackson/databind/util/TokenBuffer;
           59     225     4  bean   Ljava/lang/Object;
           90     194     5 activeView   Ljava/lang/Class;
      LocalVariableTypeTable:
        Start  Length  Slot  Name   Signature
           90     194     5 activeView   Ljava/lang/Class<*>;
      StackMapTable: number_of_entries = 13
        frame_type = 25 /* same */
        frame_type = 13 /* same */
        frame_type = 253 /* append */
          offset_delta = 33
          locals = [ class com/fasterxml/jackson/databind/util/TokenBuffer, class java/lang/Object ]
        frame_type = 13 /* same */
        frame_type = 64 /* same_locals_1_stack_item */
          stack = [ class java/lang/Class ]
        frame_type = 252 /* append */
          offset_delta = 1
          locals = [ class java/lang/Class ]
        frame_type = 253 /* append */
          offset_delta = 59
          locals = [ class java/lang/String, class com/fasterxml/jackson/databind/deser/SettableBeanProperty ]
        frame_type = 77 /* same_locals_1_stack_item */
          stack = [ class java/lang/Exception ]
        frame_type = 15 /* same */
        frame_type = 28 /* same */
        frame_type = 97 /* same_locals_1_stack_item */
          stack = [ class java/lang/Exception ]
        frame_type = 249 /* chop */
          offset_delta = 15
        frame_type = 7 /* same */
    Exceptions:
      throws java.io.IOException

  protected java.lang.Object deserializeUsingPropertyBasedWithUnwrapped(com.fasterxml.jackson.core.JsonParser, com.fasterxml.jackson.databind.DeserializationContext) throws java.io.IOException;
    descriptor: (Lcom/fasterxml/jackson/core/JsonParser;Lcom/fasterxml/jackson/databind/DeserializationContext;)Ljava/lang/Object;
    flags: (0x0004) ACC_PROTECTED
    Code:
      stack=6, locals=11, args_size=3
         0: aload_0
         1: getfield      #85                 // Field _propertyBasedCreator:Lcom/fasterxml/jackson/databind/deser/impl/PropertyBasedCreator;
         4: astore_3
         5: aload_3
         6: aload_1
         7: aload_2
         8: aload_0
         9: getfield      #6                  // Field _objectIdReader:Lcom/fasterxml/jackson/databind/deser/impl/ObjectIdReader;
        12: invokevirtual #86                 // Method com/fasterxml/jackson/databind/deser/impl/PropertyBasedCreator.startBuilding:(Lcom/fasterxml/jackson/core/JsonParser;Lcom/fasterxml/jackson/databind/DeserializationContext;Lcom/fasterxml/jackson/databind/deser/impl/ObjectIdReader;)Lcom/fasterxml/jackson/databind/deser/impl/PropertyValueBuffer;
        15: astore        4
        17: aload_2
        18: aload_1
        19: invokevirtual #106                // Method com/fasterxml/jackson/databind/DeserializationContext.bufferForInputBuffering:(Lcom/fasterxml/jackson/core/JsonParser;)Lcom/fasterxml/jackson/databind/util/TokenBuffer;
        22: astore        5
        24: aload         5
        26: invokevirtual #111                // Method com/fasterxml/jackson/databind/util/TokenBuffer.writeStartObject:()V
        29: aconst_null
        30: astore        6
        32: aload_1
        33: invokevirtual #67                 // Method com/fasterxml/jackson/core/JsonParser.currentToken:()Lcom/fasterxml/jackson/core/JsonToken;
        36: astore        7
        38: aload         7
        40: getstatic     #68                 // Field com/fasterxml/jackson/core/JsonToken.FIELD_NAME:Lcom/fasterxml/jackson/core/JsonToken;
        43: if_acmpne     294
        46: aload_1
        47: invokevirtual #69                 // Method com/fasterxml/jackson/core/JsonParser.currentName:()Ljava/lang/String;
        50: astore        8
        52: aload_1
        53: invokevirtual #42                 // Method com/fasterxml/jackson/core/JsonParser.nextToken:()Lcom/fasterxml/jackson/core/JsonToken;
        56: pop
        57: aload_3
        58: aload         8
        60: invokevirtual #87                 // Method com/fasterxml/jackson/databind/deser/impl/PropertyBasedCreator.findCreatorProperty:(Ljava/lang/String;)Lcom/fasterxml/jackson/databind/deser/SettableBeanProperty;
        63: astore        9
        65: aload         4
        67: aload         8
        69: invokevirtual #88                 // Method com/fasterxml/jackson/databind/deser/impl/PropertyValueBuffer.readIdProperty:(Ljava/lang/String;)Z
        72: ifeq          83
        75: aload         9
        77: ifnonnull     83
        80: goto          285
        83: aload         9
        85: ifnull        181
        88: aload         4
        90: aload         9
        92: aload         9
        94: aload_1
        95: aload_2
        96: invokevirtual #91                 // Method com/fasterxml/jackson/databind/deser/SettableBeanProperty.deserialize:(Lcom/fasterxml/jackson/core/JsonParser;Lcom/fasterxml/jackson/databind/DeserializationContext;)Ljava/lang/Object;
        99: invokevirtual #92                 // Method com/fasterxml/jackson/databind/deser/impl/PropertyValueBuffer.assignParameter:(Lcom/fasterxml/jackson/databind/deser/SettableBeanProperty;Ljava/lang/Object;)Z
       102: ifeq          285
       105: aload_1
       106: invokevirtual #42                 // Method com/fasterxml/jackson/core/JsonParser.nextToken:()Lcom/fasterxml/jackson/core/JsonToken;
       109: astore        7
       111: aload_3
       112: aload_2
       113: aload         4
       115: invokevirtual #93                 // Method com/fasterxml/jackson/databind/deser/impl/PropertyBasedCreator.build:(Lcom/fasterxml/jackson/databind/DeserializationContext;Lcom/fasterxml/jackson/databind/deser/impl/PropertyValueBuffer;)Ljava/lang/Object;
       118: astore        6
       120: goto          144
       123: astore        10
       125: aload_0
       126: aload         10
       128: aload_0
       129: getfield      #94                 // Field _beanType:Lcom/fasterxml/jackson/databind/JavaType;
       132: invokevirtual #95                 // Method com/fasterxml/jackson/databind/JavaType.getRawClass:()Ljava/lang/Class;
       135: aload         8
       137: aload_2
       138: invokevirtual #72                 // Method wrapAndThrow:(Ljava/lang/Throwable;Ljava/lang/Object;Ljava/lang/String;Lcom/fasterxml/jackson/databind/DeserializationContext;)V
       141: goto          285
       144: aload         6
       146: invokevirtual #57                 // Method java/lang/Object.getClass:()Ljava/lang/Class;
       149: aload_0
       150: getfield      #94                 // Field _beanType:Lcom/fasterxml/jackson/databind/JavaType;
       153: invokevirtual #95                 // Method com/fasterxml/jackson/databind/JavaType.getRawClass:()Ljava/lang/Class;
       156: if_acmpeq     170
       159: aload_0
       160: aload_1
       161: aload_2
       162: aload         6
       164: aload         5
       166: invokevirtual #96                 // Method handlePolymorphic:(Lcom/fasterxml/jackson/core/JsonParser;Lcom/fasterxml/jackson/databind/DeserializationContext;Ljava/lang/Object;Lcom/fasterxml/jackson/databind/util/TokenBuffer;)Ljava/lang/Object;
       169: areturn
       170: aload_0
       171: aload_1
       172: aload_2
       173: aload         6
       175: aload         5
       177: invokevirtual #112                // Method deserializeWithUnwrapped:(Lcom/fasterxml/jackson/core/JsonParser;Lcom/fasterxml/jackson/databind/DeserializationContext;Ljava/lang/Object;Lcom/fasterxml/jackson/databind/util/TokenBuffer;)Ljava/lang/Object;
       180: areturn
       181: aload_0
       182: getfield      #31                 // Field _beanProperties:Lcom/fasterxml/jackson/databind/deser/impl/BeanPropertyMap;
       185: aload         8
       187: invokevirtual #70                 // Method com/fasterxml/jackson/databind/deser/impl/BeanPropertyMap.find:(Ljava/lang/String;)Lcom/fasterxml/jackson/databind/deser/SettableBeanProperty;
       190: astore        10
       192: aload         10
       194: ifnull        214
       197: aload         4
       199: aload         10
       201: aload         10
       203: aload_1
       204: aload_2
       205: invokevirtual #91                 // Method com/fasterxml/jackson/databind/deser/SettableBeanProperty.deserialize:(Lcom/fasterxml/jackson/core/JsonParser;Lcom/fasterxml/jackson/databind/DeserializationContext;)Ljava/lang/Object;
       208: invokevirtual #99                 // Method com/fasterxml/jackson/databind/deser/impl/PropertyValueBuffer.bufferProperty:(Lcom/fasterxml/jackson/databind/deser/SettableBeanProperty;Ljava/lang/Object;)V
       211: goto          285
       214: aload         8
       216: aload_0
       217: getfield      #100                // Field _ignorableProps:Ljava/util/Set;
       220: aload_0
       221: getfield      #23                 // Field _includableProps:Ljava/util/Set;
       224: invokestatic  #101                // Method com/fasterxml/jackson/databind/util/IgnorePropertiesUtil.shouldIgnore:(Ljava/lang/Object;Ljava/util/Collection;Ljava/util/Collection;)Z
       227: ifeq          245
       230: aload_0
       231: aload_1
       232: aload_2
       233: aload_0
       234: invokevirtual #56                 // Method handledType:()Ljava/lang/Class;
       237: aload         8
       239: invokevirtual #102                // Method handleIgnoredProperty:(Lcom/fasterxml/jackson/core/JsonParser;Lcom/fasterxml/jackson/databind/DeserializationContext;Ljava/lang/Object;Ljava/lang/String;)V
       242: goto          285
       245: aload         5
       247: aload         8
       249: invokevirtual #107                // Method com/fasterxml/jackson/databind/util/TokenBuffer.writeFieldName:(Ljava/lang/String;)V
       252: aload         5
       254: aload_1
       255: invokevirtual #108                // Method com/fasterxml/jackson/databind/util/TokenBuffer.copyCurrentStructure:(Lcom/fasterxml/jackson/core/JsonParser;)V
       258: aload_0
       259: getfield      #103                // Field _anySetter:Lcom/fasterxml/jackson/databind/deser/SettableAnyProperty;
       262: ifnull        285
       265: aload         4
       267: aload_0
       268: getfield      #103                // Field _anySetter:Lcom/fasterxml/jackson/databind/deser/SettableAnyProperty;
       271: aload         8
       273: aload_0
       274: getfield      #103                // Field _anySetter:Lcom/fasterxml/jackson/databind/deser/SettableAnyProperty;
       277: aload_1
       278: aload_2
       279: invokevirtual #104                // Method com/fasterxml/jackson/databind/deser/SettableAnyProperty.deserialize:(Lcom/fasterxml/jackson/core/JsonParser;Lcom/fasterxml/jackson/databind/DeserializationContext;)Ljava/lang/Object;
       282: invokevirtual #105                // Method com/fasterxml/jackson/databind/deser/impl/PropertyValueBuffer.bufferAnyProperty:(Lcom/fasterxml/jackson/databind/deser/SettableAnyProperty;Ljava/lang/String;Ljava/lang/Object;)V
       285: aload_1
       286: invokevirtual #42                 // Method com/fasterxml/jackson/core/JsonParser.nextToken:()Lcom/fasterxml/jackson/core/JsonToken;
       289: astore        7
       291: goto          38
       294: aload         5
       296: invokevirtual #134                // Method com/fasterxml/jackson/databind/util/TokenBuffer.writeEndObject:()V
       299: aload         6
       301: ifnonnull     326
       304: aload_3
       305: aload_2
       306: aload         4
       308: invokevirtual #93                 // Method com/fasterxml/jackson/databind/deser/impl/PropertyBasedCreator.build:(Lcom/fasterxml/jackson/databind/DeserializationContext;Lcom/fasterxml/jackson/databind/deser/impl/PropertyValueBuffer;)Ljava/lang/Object;
       311: astore        6
       313: goto          326
       316: astore        8
       318: aload_0
       319: aload         8
       321: aload_2
       322: invokevirtual #40                 // Method wrapInstantiationProblem:(Ljava/lang/Throwable;Lcom/fasterxml/jackson/databind/DeserializationContext;)Ljava/lang/Object;
       325: areturn
       326: aload_0
       327: getfield      #75                 // Field _unwrappedPropertyHandler:Lcom/fasterxml/jackson/databind/deser/impl/UnwrappedPropertyHandler;
       330: aload_1
       331: aload_2
       332: aload         6
       334: aload         5
       336: invokevirtual #135                // Method com/fasterxml/jackson/databind/deser/impl/UnwrappedPropertyHandler.processUnwrapped:(Lcom/fasterxml/jackson/core/JsonParser;Lcom/fasterxml/jackson/databind/DeserializationContext;Ljava/lang/Object;Lcom/fasterxml/jackson/databind/util/TokenBuffer;)Ljava/lang/Object;
       339: areturn
      Exception table:
         from    to  target type
           111   120   123   Class java/lang/Exception
           304   313   316   Class java/lang/Exception
      LineNumberTable:
        line 644: 0
        line 645: 5
        line 647: 17
        line 648: 24
        line 649: 29
        line 651: 32
        line 652: 38
        line 653: 46
        line 654: 52
        line 656: 57
        line 658: 65
        line 659: 80
        line 661: 83
        line 663: 88
        line 664: 105
        line 666: 111
        line 670: 120
        line 667: 123
        line 668: 125
        line 669: 141
        line 671: 144
        line 672: 159
        line 674: 170
        line 679: 181
        line 680: 192
        line 681: 197
        line 682: 211
        line 684: 214
        line 685: 230
        line 686: 242
        line 688: 245
        line 689: 252
        line 691: 258
        line 692: 265
        line 652: 285
        line 695: 294
        line 698: 299
        line 700: 304
        line 703: 313
        line 701: 316
        line 702: 318
        line 705: 326
      LocalVariableTable:
        Start  Length  Slot  Name   Signature
          125      19    10     e   Ljava/lang/Exception;
           52     233     8 propName   Ljava/lang/String;
           65     220     9 creatorProp   Lcom/fasterxml/jackson/databind/deser/SettableBeanProperty;
          192      93    10  prop   Lcom/fasterxml/jackson/databind/deser/SettableBeanProperty;
          318       8     8     e   Ljava/lang/Exception;
            0     340     0  this   Lcom/fasterxml/jackson/databind/deser/BuilderBasedDeserializer;
            0     340     1     p   Lcom/fasterxml/jackson/core/JsonParser;
            0     340     2  ctxt   Lcom/fasterxml/jackson/databind/DeserializationContext;
            5     335     3 creator   Lcom/fasterxml/jackson/databind/deser/impl/PropertyBasedCreator;
           17     323     4 buffer   Lcom/fasterxml/jackson/databind/deser/impl/PropertyValueBuffer;
           24     316     5 tokens   Lcom/fasterxml/jackson/databind/util/TokenBuffer;
           32     308     6 builder   Ljava/lang/Object;
           38     302     7     t   Lcom/fasterxml/jackson/core/JsonToken;
      StackMapTable: number_of_entries = 12
        frame_type = 255 /* full_frame */
          offset_delta = 38
          locals = [ class com/fasterxml/jackson/databind/deser/BuilderBasedDeserializer, class com/fasterxml/jackson/core/JsonParser, class com/fasterxml/jackson/databind/DeserializationContext, class com/fasterxml/jackson/databind/deser/impl/PropertyBasedCreator, class com/fasterxml/jackson/databind/deser/impl/PropertyValueBuffer, class com/fasterxml/jackson/databind/util/TokenBuffer, class java/lang/Object, class com/fasterxml/jackson/core/JsonToken ]
          stack = []
        frame_type = 253 /* append */
          offset_delta = 44
          locals = [ class java/lang/String, class com/fasterxml/jackson/databind/deser/SettableBeanProperty ]
        frame_type = 103 /* same_locals_1_stack_item */
          stack = [ class java/lang/Exception ]
        frame_type = 20 /* same */
        frame_type = 25 /* same */
        frame_type = 10 /* same */
        frame_type = 252 /* append */
          offset_delta = 32
          locals = [ class com/fasterxml/jackson/databind/deser/SettableBeanProperty ]
        frame_type = 30 /* same */
        frame_type = 248 /* chop */
          offset_delta = 39
        frame_type = 8 /* same */
        frame_type = 85 /* same_locals_1_stack_item */
          stack = [ class java/lang/Exception ]
        frame_type = 9 /* same */
    Exceptions:
      throws java.io.IOException

  protected java.lang.Object deserializeWithUnwrapped(com.fasterxml.jackson.core.JsonParser, com.fasterxml.jackson.databind.DeserializationContext, java.lang.Object, com.fasterxml.jackson.databind.util.TokenBuffer) throws java.io.IOException;
    descriptor: (Lcom/fasterxml/jackson/core/JsonParser;Lcom/fasterxml/jackson/databind/DeserializationContext;Ljava/lang/Object;Lcom/fasterxml/jackson/databind/util/TokenBuffer;)Ljava/lang/Object;
    flags: (0x0004) ACC_PROTECTED
    Code:
      stack=5, locals=10, args_size=5
         0: aload_0
         1: getfield      #82                 // Field _needViewProcesing:Z
         4: ifeq          14
         7: aload_2
         8: invokevirtual #83                 // Method com/fasterxml/jackson/databind/DeserializationContext.getActiveView:()Ljava/lang/Class;
        11: goto          15
        14: aconst_null
        15: astore        5
        17: aload_1
        18: invokevirtual #67                 // Method com/fasterxml/jackson/core/JsonParser.currentToken:()Lcom/fasterxml/jackson/core/JsonToken;
        21: astore        6
        23: aload         6
        25: getstatic     #68                 // Field com/fasterxml/jackson/core/JsonToken.FIELD_NAME:Lcom/fasterxml/jackson/core/JsonToken;
        28: if_acmpne     177
        31: aload_1
        32: invokevirtual #69                 // Method com/fasterxml/jackson/core/JsonParser.currentName:()Ljava/lang/String;
        35: astore        7
        37: aload_0
        38: getfield      #31                 // Field _beanProperties:Lcom/fasterxml/jackson/databind/deser/impl/BeanPropertyMap;
        41: aload         7
        43: invokevirtual #70                 // Method com/fasterxml/jackson/databind/deser/impl/BeanPropertyMap.find:(Ljava/lang/String;)Lcom/fasterxml/jackson/databind/deser/SettableBeanProperty;
        46: astore        8
        48: aload_1
        49: invokevirtual #42                 // Method com/fasterxml/jackson/core/JsonParser.nextToken:()Lcom/fasterxml/jackson/core/JsonToken;
        52: pop
        53: aload         8
        55: ifnull        108
        58: aload         5
        60: ifnull        81
        63: aload         8
        65: aload         5
        67: invokevirtual #89                 // Method com/fasterxml/jackson/databind/deser/SettableBeanProperty.visibleInView:(Ljava/lang/Class;)Z
        70: ifne          81
        73: aload_1
        74: invokevirtual #90                 // Method com/fasterxml/jackson/core/JsonParser.skipChildren:()Lcom/fasterxml/jackson/core/JsonParser;
        77: pop
        78: goto          168
        81: aload         8
        83: aload_1
        84: aload_2
        85: aload_3
        86: invokevirtual #71                 // Method com/fasterxml/jackson/databind/deser/SettableBeanProperty.deserializeSetAndReturn:(Lcom/fasterxml/jackson/core/JsonParser;Lcom/fasterxml/jackson/databind/DeserializationContext;Ljava/lang/Object;)Ljava/lang/Object;
        89: astore_3
        90: goto          168
        93: astore        9
        95: aload_0
        96: aload         9
        98: aload_3
        99: aload         7
       101: aload_2
       102: invokevirtual #72                 // Method wrapAndThrow:(Ljava/lang/Throwable;Ljava/lang/Object;Ljava/lang/String;Lcom/fasterxml/jackson/databind/DeserializationContext;)V
       105: goto          168
       108: aload         7
       110: aload_0
       111: getfield      #100                // Field _ignorableProps:Ljava/util/Set;
       114: aload_0
       115: getfield      #23                 // Field _includableProps:Ljava/util/Set;
       118: invokestatic  #101                // Method com/fasterxml/jackson/databind/util/IgnorePropertiesUtil.shouldIgnore:(Ljava/lang/Object;Ljava/util/Collection;Ljava/util/Collection;)Z
       121: ifeq          136
       124: aload_0
       125: aload_1
       126: aload_2
       127: aload_3
       128: aload         7
       130: invokevirtual #102                // Method handleIgnoredProperty:(Lcom/fasterxml/jackson/core/JsonParser;Lcom/fasterxml/jackson/databind/DeserializationContext;Ljava/lang/Object;Ljava/lang/String;)V
       133: goto          168
       136: aload         4
       138: aload         7
       140: invokevirtual #107                // Method com/fasterxml/jackson/databind/util/TokenBuffer.writeFieldName:(Ljava/lang/String;)V
       143: aload         4
       145: aload_1
       146: invokevirtual #108                // Method com/fasterxml/jackson/databind/util/TokenBuffer.copyCurrentStructure:(Lcom/fasterxml/jackson/core/JsonParser;)V
       149: aload_0
       150: getfield      #103                // Field _anySetter:Lcom/fasterxml/jackson/databind/deser/SettableAnyProperty;
       153: ifnull        168
       156: aload_0
       157: getfield      #103                // Field _anySetter:Lcom/fasterxml/jackson/databind/deser/SettableAnyProperty;
       160: aload_1
       161: aload_2
       162: aload_3
       163: aload         7
       165: invokevirtual #133                // Method com/fasterxml/jackson/databind/deser/SettableAnyProperty.deserializeAndSet:(Lcom/fasterxml/jackson/core/JsonParser;Lcom/fasterxml/jackson/databind/DeserializationContext;Ljava/lang/Object;Ljava/lang/String;)V
       168: aload_1
       169: invokevirtual #42                 // Method com/fasterxml/jackson/core/JsonParser.nextToken:()Lcom/fasterxml/jackson/core/JsonToken;
       172: astore        6
       174: goto          23
       177: aload         4
       179: invokevirtual #134                // Method com/fasterxml/jackson/databind/util/TokenBuffer.writeEndObject:()V
       182: aload_0
       183: getfield      #75                 // Field _unwrappedPropertyHandler:Lcom/fasterxml/jackson/databind/deser/impl/UnwrappedPropertyHandler;
       186: aload_1
       187: aload_2
       188: aload_3
       189: aload         4
       191: invokevirtual #135                // Method com/fasterxml/jackson/databind/deser/impl/UnwrappedPropertyHandler.processUnwrapped:(Lcom/fasterxml/jackson/core/JsonParser;Lcom/fasterxml/jackson/databind/DeserializationContext;Ljava/lang/Object;Lcom/fasterxml/jackson/databind/util/TokenBuffer;)Ljava/lang/Object;
       194: areturn
      Exception table:
         from    to  target type
            81    90    93   Class java/lang/Exception
      LineNumberTable:
        line 712: 0
        line 713: 17
        line 714: 31
        line 715: 37
        line 716: 48
        line 717: 53
        line 718: 58
        line 719: 73
        line 720: 78
        line 723: 81
        line 726: 90
        line 724: 93
        line 725: 95
        line 727: 105
        line 729: 108
        line 730: 124
        line 731: 133
        line 734: 136
        line 735: 143
        line 737: 149
        line 738: 156
        line 713: 168
        line 741: 177
        line 742: 182
      LocalVariableTable:
        Start  Length  Slot  Name   Signature
           95      10     9     e   Ljava/lang/Exception;
           37     131     7 propName   Ljava/lang/String;
           48     120     8  prop   Lcom/fasterxml/jackson/databind/deser/SettableBeanProperty;
           23     154     6     t   Lcom/fasterxml/jackson/core/JsonToken;
            0     195     0  this   Lcom/fasterxml/jackson/databind/deser/BuilderBasedDeserializer;
            0     195     1     p   Lcom/fasterxml/jackson/core/JsonParser;
            0     195     2  ctxt   Lcom/fasterxml/jackson/databind/DeserializationContext;
            0     195     3 builder   Ljava/lang/Object;
            0     195     4 tokens   Lcom/fasterxml/jackson/databind/util/TokenBuffer;
           17     178     5 activeView   Ljava/lang/Class;
      LocalVariableTypeTable:
        Start  Length  Slot  Name   Signature
           17     178     5 activeView   Ljava/lang/Class<*>;
      StackMapTable: number_of_entries = 9
        frame_type = 14 /* same */
        frame_type = 64 /* same_locals_1_stack_item */
          stack = [ class java/lang/Class ]
        frame_type = 253 /* append */
          offset_delta = 7
          locals = [ class java/lang/Class, class com/fasterxml/jackson/core/JsonToken ]
        frame_type = 253 /* append */
          offset_delta = 57
          locals = [ class java/lang/String, class com/fasterxml/jackson/databind/deser/SettableBeanProperty ]
        frame_type = 75 /* same_locals_1_stack_item */
          stack = [ class java/lang/Exception ]
        frame_type = 14 /* same */
        frame_type = 27 /* same */
        frame_type = 249 /* chop */
          offset_delta = 31
        frame_type = 250 /* chop */
          offset_delta = 8
    Exceptions:
      throws java.io.IOException

  protected java.lang.Object deserializeWithExternalTypeId(com.fasterxml.jackson.core.JsonParser, com.fasterxml.jackson.databind.DeserializationContext) throws java.io.IOException;
    descriptor: (Lcom/fasterxml/jackson/core/JsonParser;Lcom/fasterxml/jackson/databind/DeserializationContext;)Ljava/lang/Object;
    flags: (0x0004) ACC_PROTECTED
    Code:
      stack=5, locals=3, args_size=3
         0: aload_0
         1: getfield      #85                 // Field _propertyBasedCreator:Lcom/fasterxml/jackson/databind/deser/impl/PropertyBasedCreator;
         4: ifnull        14
         7: aload_0
         8: aload_1
         9: aload_2
        10: invokevirtual #136                // Method deserializeUsingPropertyBasedWithExternalTypeId:(Lcom/fasterxml/jackson/core/JsonParser;Lcom/fasterxml/jackson/databind/DeserializationContext;)Ljava/lang/Object;
        13: areturn
        14: aload_0
        15: aload_1
        16: aload_2
        17: aload_0
        18: getfield      #65                 // Field _valueInstantiator:Lcom/fasterxml/jackson/databind/deser/ValueInstantiator;
        21: aload_2
        22: invokevirtual #66                 // Method com/fasterxml/jackson/databind/deser/ValueInstantiator.createUsingDefault:(Lcom/fasterxml/jackson/databind/DeserializationContext;)Ljava/lang/Object;
        25: invokevirtual #113                // Method deserializeWithExternalTypeId:(Lcom/fasterxml/jackson/core/JsonParser;Lcom/fasterxml/jackson/databind/DeserializationContext;Ljava/lang/Object;)Ljava/lang/Object;
        28: areturn
      LineNumberTable:
        line 755: 0
        line 756: 7
        line 758: 14
      LocalVariableTable:
        Start  Length  Slot  Name   Signature
            0      29     0  this   Lcom/fasterxml/jackson/databind/deser/BuilderBasedDeserializer;
            0      29     1     p   Lcom/fasterxml/jackson/core/JsonParser;
            0      29     2  ctxt   Lcom/fasterxml/jackson/databind/DeserializationContext;
      StackMapTable: number_of_entries = 1
        frame_type = 14 /* same */
    Exceptions:
      throws java.io.IOException

  protected java.lang.Object deserializeWithExternalTypeId(com.fasterxml.jackson.core.JsonParser, com.fasterxml.jackson.databind.DeserializationContext, java.lang.Object) throws java.io.IOException;
    descriptor: (Lcom/fasterxml/jackson/core/JsonParser;Lcom/fasterxml/jackson/databind/DeserializationContext;Ljava/lang/Object;)Ljava/lang/Object;
    flags: (0x0004) ACC_PROTECTED
    Code:
      stack=5, locals=10, args_size=4
         0: aload_0
         1: getfield      #82                 // Field _needViewProcesing:Z
         4: ifeq          14
         7: aload_2
         8: invokevirtual #83                 // Method com/fasterxml/jackson/databind/DeserializationContext.getActiveView:()Ljava/lang/Class;
        11: goto          15
        14: aconst_null
        15: astore        4
        17: aload_0
        18: getfield      #77                 // Field _externalTypeIdHandler:Lcom/fasterxml/jackson/databind/deser/impl/ExternalTypeHandler;
        21: invokevirtual #137                // Method com/fasterxml/jackson/databind/deser/impl/ExternalTypeHandler.start:()Lcom/fasterxml/jackson/databind/deser/impl/ExternalTypeHandler;
        24: astore        5
        26: aload_1
        27: invokevirtual #67                 // Method com/fasterxml/jackson/core/JsonParser.currentToken:()Lcom/fasterxml/jackson/core/JsonToken;
        30: astore        6
        32: aload         6
        34: getstatic     #68                 // Field com/fasterxml/jackson/core/JsonToken.FIELD_NAME:Lcom/fasterxml/jackson/core/JsonToken;
        37: if_acmpne     236
        40: aload_1
        41: invokevirtual #69                 // Method com/fasterxml/jackson/core/JsonParser.currentName:()Ljava/lang/String;
        44: astore        7
        46: aload_1
        47: invokevirtual #42                 // Method com/fasterxml/jackson/core/JsonParser.nextToken:()Lcom/fasterxml/jackson/core/JsonToken;
        50: astore        6
        52: aload_0
        53: getfield      #31                 // Field _beanProperties:Lcom/fasterxml/jackson/databind/deser/impl/BeanPropertyMap;
        56: aload         7
        58: invokevirtual #70                 // Method com/fasterxml/jackson/databind/deser/impl/BeanPropertyMap.find:(Ljava/lang/String;)Lcom/fasterxml/jackson/databind/deser/SettableBeanProperty;
        61: astore        8
        63: aload         8
        65: ifnull        137
        68: aload         6
        70: invokevirtual #138                // Method com/fasterxml/jackson/core/JsonToken.isScalarValue:()Z
        73: ifeq          87
        76: aload         5
        78: aload_1
        79: aload_2
        80: aload         7
        82: aload_3
        83: invokevirtual #139                // Method com/fasterxml/jackson/databind/deser/impl/ExternalTypeHandler.handleTypePropertyValue:(Lcom/fasterxml/jackson/core/JsonParser;Lcom/fasterxml/jackson/databind/DeserializationContext;Ljava/lang/String;Ljava/lang/Object;)Z
        86: pop
        87: aload         4
        89: ifnull        110
        92: aload         8
        94: aload         4
        96: invokevirtual #89                 // Method com/fasterxml/jackson/databind/deser/SettableBeanProperty.visibleInView:(Ljava/lang/Class;)Z
        99: ifne          110
       102: aload_1
       103: invokevirtual #90                 // Method com/fasterxml/jackson/core/JsonParser.skipChildren:()Lcom/fasterxml/jackson/core/JsonParser;
       106: pop
       107: goto          227
       110: aload         8
       112: aload_1
       113: aload_2
       114: aload_3
       115: invokevirtual #71                 // Method com/fasterxml/jackson/databind/deser/SettableBeanProperty.deserializeSetAndReturn:(Lcom/fasterxml/jackson/core/JsonParser;Lcom/fasterxml/jackson/databind/DeserializationContext;Ljava/lang/Object;)Ljava/lang/Object;
       118: astore_3
       119: goto          227
       122: astore        9
       124: aload_0
       125: aload         9
       127: aload_3
       128: aload         7
       130: aload_2
       131: invokevirtual #72                 // Method wrapAndThrow:(Ljava/lang/Throwable;Ljava/lang/Object;Ljava/lang/String;Lcom/fasterxml/jackson/databind/DeserializationContext;)V
       134: goto          227
       137: aload         7
       139: aload_0
       140: getfield      #100                // Field _ignorableProps:Ljava/util/Set;
       143: aload_0
       144: getfield      #23                 // Field _includableProps:Ljava/util/Set;
       147: invokestatic  #101                // Method com/fasterxml/jackson/databind/util/IgnorePropertiesUtil.shouldIgnore:(Ljava/lang/Object;Ljava/util/Collection;Ljava/util/Collection;)Z
       150: ifeq          165
       153: aload_0
       154: aload_1
       155: aload_2
       156: aload_3
       157: aload         7
       159: invokevirtual #102                // Method handleIgnoredProperty:(Lcom/fasterxml/jackson/core/JsonParser;Lcom/fasterxml/jackson/databind/DeserializationContext;Ljava/lang/Object;Ljava/lang/String;)V
       162: goto          227
       165: aload         5
       167: aload_1
       168: aload_2
       169: aload         7
       171: aload_3
       172: invokevirtual #140                // Method com/fasterxml/jackson/databind/deser/impl/ExternalTypeHandler.handlePropertyValue:(Lcom/fasterxml/jackson/core/JsonParser;Lcom/fasterxml/jackson/databind/DeserializationContext;Ljava/lang/String;Ljava/lang/Object;)Z
       175: ifeq          181
       178: goto          227
       181: aload_0
       182: getfield      #103                // Field _anySetter:Lcom/fasterxml/jackson/databind/deser/SettableAnyProperty;
       185: ifnull        218
       188: aload_0
       189: getfield      #103                // Field _anySetter:Lcom/fasterxml/jackson/databind/deser/SettableAnyProperty;
       192: aload_1
       193: aload_2
       194: aload_3
       195: aload         7
       197: invokevirtual #133                // Method com/fasterxml/jackson/databind/deser/SettableAnyProperty.deserializeAndSet:(Lcom/fasterxml/jackson/core/JsonParser;Lcom/fasterxml/jackson/databind/DeserializationContext;Ljava/lang/Object;Ljava/lang/String;)V
       200: goto          227
       203: astore        9
       205: aload_0
       206: aload         9
       208: aload_3
       209: aload         7
       211: aload_2
       212: invokevirtual #72                 // Method wrapAndThrow:(Ljava/lang/Throwable;Ljava/lang/Object;Ljava/lang/String;Lcom/fasterxml/jackson/databind/DeserializationContext;)V
       215: goto          227
       218: aload_0
       219: aload_1
       220: aload_2
       221: aload_3
       222: aload         7
       224: invokevirtual #141                // Method handleUnknownProperty:(Lcom/fasterxml/jackson/core/JsonParser;Lcom/fasterxml/jackson/databind/DeserializationContext;Ljava/lang/Object;Ljava/lang/String;)V
       227: aload_1
       228: invokevirtual #42                 // Method com/fasterxml/jackson/core/JsonParser.nextToken:()Lcom/fasterxml/jackson/core/JsonToken;
       231: astore        6
       233: goto          32
       236: aload         5
       238: aload_1
       239: aload_2
       240: aload_3
       241: invokevirtual #142                // Method com/fasterxml/jackson/databind/deser/impl/ExternalTypeHandler.complete:(Lcom/fasterxml/jackson/core/JsonParser;Lcom/fasterxml/jackson/databind/DeserializationContext;Ljava/lang/Object;)Ljava/lang/Object;
       244: areturn
      Exception table:
         from    to  target type
           110   119   122   Class java/lang/Exception
           188   200   203   Class java/lang/Exception
      LineNumberTable:
        line 765: 0
        line 766: 17
        line 768: 26
        line 769: 40
        line 770: 46
        line 771: 52
        line 772: 63
        line 774: 68
        line 775: 76
        line 777: 87
        line 778: 102
        line 779: 107
        line 782: 110
        line 785: 119
        line 783: 122
        line 784: 124
        line 786: 134
        line 789: 137
        line 790: 153
        line 791: 162
        line 794: 165
        line 795: 178
        line 798: 181
        line 800: 188
        line 803: 200
        line 801: 203
        line 802: 205
        line 804: 215
        line 807: 218
        line 768: 227
        line 811: 236
      LocalVariableTable:
        Start  Length  Slot  Name   Signature
          124      10     9     e   Ljava/lang/Exception;
          205      10     9     e   Ljava/lang/Exception;
           46     181     7 propName   Ljava/lang/String;
           63     164     8  prop   Lcom/fasterxml/jackson/databind/deser/SettableBeanProperty;
           32     204     6     t   Lcom/fasterxml/jackson/core/JsonToken;
            0     245     0  this   Lcom/fasterxml/jackson/databind/deser/BuilderBasedDeserializer;
            0     245     1     p   Lcom/fasterxml/jackson/core/JsonParser;
            0     245     2  ctxt   Lcom/fasterxml/jackson/databind/DeserializationContext;
            0     245     3  bean   Ljava/lang/Object;
           17     228     4 activeView   Ljava/lang/Class;
           26     219     5   ext   Lcom/fasterxml/jackson/databind/deser/impl/ExternalTypeHandler;
      LocalVariableTypeTable:
        Start  Length  Slot  Name   Signature
           17     228     4 activeView   Ljava/lang/Class<*>;
      StackMapTable: number_of_entries = 13
        frame_type = 14 /* same */
        frame_type = 64 /* same_locals_1_stack_item */
          stack = [ class java/lang/Class ]
        frame_type = 254 /* append */
          offset_delta = 16
          locals = [ class java/lang/Class, class com/fasterxml/jackson/databind/deser/impl/ExternalTypeHandler, class com/fasterxml/jackson/core/JsonToken ]
        frame_type = 253 /* append */
          offset_delta = 54
          locals = [ class java/lang/String, class com/fasterxml/jackson/databind/deser/SettableBeanProperty ]
        frame_type = 22 /* same */
        frame_type = 75 /* same_locals_1_stack_item */
          stack = [ class java/lang/Exception ]
        frame_type = 14 /* same */
        frame_type = 27 /* same */
        frame_type = 15 /* same */
        frame_type = 85 /* same_locals_1_stack_item */
          stack = [ class java/lang/Exception ]
        frame_type = 14 /* same */
        frame_type = 249 /* chop */
          offset_delta = 8
        frame_type = 250 /* chop */
          offset_delta = 8
    Exceptions:
      throws java.io.IOException

  protected java.lang.Object deserializeUsingPropertyBasedWithExternalTypeId(com.fasterxml.jackson.core.JsonParser, com.fasterxml.jackson.databind.DeserializationContext) throws java.io.IOException;
    descriptor: (Lcom/fasterxml/jackson/core/JsonParser;Lcom/fasterxml/jackson/databind/DeserializationContext;)Ljava/lang/Object;
    flags: (0x0004) ACC_PROTECTED
    Code:
      stack=7, locals=4, args_size=3
         0: aload_0
         1: getfield      #3                  // Field _targetType:Lcom/fasterxml/jackson/databind/JavaType;
         4: astore_3
         5: aload_2
         6: aload_3
         7: ldc           #143                // String Deserialization (of %s) with Builder, External type id, @JsonCreator not yet implemented
         9: iconst_1
        10: anewarray     #60                 // class java/lang/Object
        13: dup
        14: iconst_0
        15: aload_3
        16: aastore
        17: invokestatic  #62                 // Method java/lang/String.format:(Ljava/lang/String;[Ljava/lang/Object;)Ljava/lang/String;
        20: invokevirtual #63                 // Method com/fasterxml/jackson/databind/DeserializationContext.reportBadDefinition:(Lcom/fasterxml/jackson/databind/JavaType;Ljava/lang/String;)Ljava/lang/Object;
        23: areturn
      LineNumberTable:
        line 819: 0
        line 820: 5
      LocalVariableTable:
        Start  Length  Slot  Name   Signature
            0      24     0  this   Lcom/fasterxml/jackson/databind/deser/BuilderBasedDeserializer;
            0      24     1     p   Lcom/fasterxml/jackson/core/JsonParser;
            0      24     2  ctxt   Lcom/fasterxml/jackson/databind/DeserializationContext;
            5      19     3     t   Lcom/fasterxml/jackson/databind/JavaType;
    Exceptions:
      throws java.io.IOException
}
SourceFile: "BuilderBasedDeserializer.java"
InnerClasses:
  static #145;                            // class com/fasterxml/jackson/databind/deser/BuilderBasedDeserializer$1
