Classfile /Users/mw/Projects/slang-braindump/.jar/jar8/assemble/slang-braindump/assemble/content/org/sireum/Asm_Ext.class
  Last modified May 29, 2022; size 2644 bytes
  SHA-256 checksum 6ff3a36e0fbecb942e9d5ba409ced9cf9ca68b4a0a0b31ef6439b2e86f9d5276
  Compiled from "Asm_Ext.scala"
public final class org.sireum.Asm_Ext
  minor version: 0
  major version: 52
  flags: (0x0031) ACC_PUBLIC, ACC_FINAL, ACC_SUPER
  this_class: #2                          // org/sireum/Asm_Ext
  super_class: #4                         // java/lang/Object
  interfaces: 0, fields: 0, methods: 4, attributes: 4
Constant pool:
   #1 = Utf8               org/sireum/Asm_Ext
   #2 = Class              #1             // org/sireum/Asm_Ext
   #3 = Utf8               java/lang/Object
   #4 = Class              #3             // java/lang/Object
   #5 = Utf8               Asm_Ext.scala
   #6 = Utf8               Lscala/reflect/ScalaSignature;
   #7 = Utf8               bytes
   #8 = Utf8               \u0006\u0005\u0005Mu!B\u0015+\u0011\u0003yc!B\u0019+\u0011\u0003\u0011\u0004\"B\u001d\u0002\t\u0003Q\u0004bB\u001e\u0002\u0005\u0004%\t\u0001\u0010\u0005\u0007\u0001\u0006\u0001\u000b\u0011B\u001f\t\u000b\u0005\u000bA\u0011\u0001\"\t\u000b=\u000bA\u0011\u0001)\t\u000bI\u000bA\u0011A*\b\u000bU\u000b\u0001\u0012\u0001,\u0007\u000ba\u000b\u0001\u0012A-\t\u000beJA\u0011\u0001.\u0007\tmK\u0001\u0001\u0018\u0005\tK.\u0011\t\u0011)A\u0005;\")\u0011h\u0003C\u0001M\")!n\u0003C!W\u001a!A.\u0003\u0001n\u0011!\txB!A!\u0002\u0013\u0011\b\"B\u001d\u0010\t\u0003)\b\"\u0002=\u0010\t\u0003JxaBA\u000f\u0003!\u0005\u0011q\u0004\u0004\b\u0003C\t\u0001\u0012AA\u0012\u0011\u0019ID\u0003\"\u0001\u0002&\u0019)1\f\u0006\u0001\u0002(!AQM\u0006B\u0001B\u0003%Q\f\u0003\u0004:-\u0011\u0005\u0011\u0011\u0006\u0005\b\u0003c1B\u0011IA\u001a\r\u0015aG\u0003AA&\u0011!\t(D!A!\u0002\u0013\u0011\bBB\u001d\u001b\t\u0003\ti\u0005\u0003\u0004y5\u0011\u0005\u00131K\u0004\b\u0003?\n\u0001\u0012AA1\r\u001d\t\u0019\'\u0001E\u0001\u0003KBa!O\u0010\u0005\u0002\u0005\u001dd!B. \u0001\u0005%\u0004\u0002C3\"\u0005\u0003\u0005\u000b\u0011B/\t\re\nC\u0011AA6\u0011\u001d\t\t$\tC!\u0003g2Q\u0001\\\u0010\u0001\u0003\u007fB\u0001\"]\u0013\u0003\u0002\u0003\u0006IA\u001d\u0005\u0007s\u0015\"\t!!!\t\ra,C\u0011IAD\u0003\u001d\t5/\\0FqRT!a\u000b\u0017\u0002\rML\'/Z;n\u0015\u0005i\u0013aA8sO\u000e\u0001\u0001C\u0001\u0019\u0002\u001b\u0005Q#aB!t[~+\u0005\u0010^\n\u0003\u0003M\u0002\"\u0001N\u001c\u000e\u0003UR\u0011AN\u0001\u0006g\u000e\fG.Y\u0005\u0003qU\u0012a!\u00118z%\u00164\u0017A\u0002\u001fj]&$h\bF\u00010\u0003\r\t\u0007/[\u000b\u0002{A\u0011AGP\u0005\u0003\u007fU\u00121!\u00138u\u0003\u0011\t\u0007/\u001b\u0011\u0002\u001d\u0015\u0014\u0018m]3O_:t\u0015\r^5wKR\u00111I\u0012\t\u0003i\u0011K!!R\u001b\u0003\tUs\u0017\u000e\u001e\u0005\u0006\u000f\u0016\u0001\r\u0001S\u0001\u0005a\u0006$\b\u000e\u0005\u0002J\u0019:\u0011\u0001GS\u0005\u0003\u0017*\n!aT:\n\u00055s%\u0001\u0002)bi\"T!a\u0013\u0016\u0002\'I,wO]5uKJ+G.Z1tK\u001a+gnY3\u0015\u0005\r\u000b\u0006\"B$\u0007\u0001\u0004A\u0015!\u0007:foJLG/Z*fiN+7-\u001e:jifl\u0015M\\1hKJ$\"a\u0011+\t\u000b\u001d;\u0001\u0019\u0001%\u0002\u0019I+G.Z1tK\u001a+gnY3\u0011\u0005]KQ\"A\u0001\u0003\u0019I+G.Z1tK\u001a+gnY3\u0014\u0005%\u0019D#\u0001,\u0003\u001153\u0016n]5u_J\u001c\"aC/\u0011\u0005y\u001bW\"A0\u000b\u0005\u0001\f\u0017aA1t[*\u0011!\rL\u0001\n_\nTWm\u0019;xK\nL!\u0001Z0\u0003\u001b5+G\u000f[8e-&\u001c\u0018\u000e^8s\u0003\u001d1\u0018n]5u_J$\"aZ5\u0011\u0005!\\Q\"A\u0005\t\u000b\u0015l\u0001\u0019A/\u0002\u0013YL7/\u001b;D_\u0012,G#A\"\u0003\u0011\r3\u0016n]5u_J\u001c\"a\u00048\u0011\u0005y{\u0017B\u00019`\u00051\u0019E.Y:t-&\u001c\u0018\u000e^8s\u0003\t\u0019w\u000f\u0005\u0002_g&\u0011Ao\u0018\u0002\f\u00072\f7o],sSR,\'\u000f\u0006\u0002woB\u0011\u0001n\u0004\u0005\u0006cF\u0001\rA]\u0001\fm&\u001c\u0018\u000e^\'fi\"|G\rF\u0005^ur\fY!a\u0004\u0002\u0014!)1P\u0005a\u0001{\u00051\u0011mY2fgNDQ! \nA\u0002y\fAA\\1nKB\u0019q0!\u0002\u000f\u0007Q\n\t!C\u0002\u0002\u0004U\na\u0001\u0015:fI\u00164\u0017\u0002BA\u0004\u0003\u0013\u0011aa\u0015;sS:<\'bAA\u0002k!1\u0011Q\u0002\nA\u0002y\f!\u0002Z3tGJL\u0007\u000f^8s\u0011\u0019\t\tB\u0005a\u0001}\u0006I1/[4oCR,(/\u001a\u0005\b\u0003+\u0011\u0002\u0019AA\f\u0003))\u0007pY3qi&|gn\u001d\t\u0005i\u0005ea0C\u0002\u0002\u001cU\u0012Q!\u0011:sCf\fqbU3dkJLG/_\'b]\u0006<WM\u001d\t\u0003/R\u0011qbU3dkJLG/_\'b]\u0006<WM]\n\u0003)M\"\"!a\b\u0014\u0005YiF\u0003BA\u0016\u0003_\u00012!!\f\u0017\u001b\u0005!\u0002\"B3\u0019\u0001\u0004i\u0016a\u0004<jg&$X*\u001a;i_\u0012Len\u001d8\u0015\u0017\r\u000b)$!\u000f\u0002>\u0005}\u0012\u0011\t\u0005\u0007\u0003oI\u0002\u0019A\u001f\u0002\r=\u00048m\u001c3f\u0011\u0019\tY$\u0007a\u0001}\u0006)qn\u001e8fe\")Q0\u0007a\u0001}\"1\u0011QB\rA\u0002yDq!a\u0011\u001a\u0001\u0004\t)%A\u0006jg&sG/\u001a:gC\u000e,\u0007c\u0001\u001b\u0002H%\u0019\u0011\u0011J\u001b\u0003\u000f\t{w\u000e\\3b]N\u0011!D\u001c\u000b\u0005\u0003\u001f\n\t\u0006E\u0002\u0002.iAQ!\u001d\u000fA\u0002I$2\"XA+\u0003/\nI&a\u0017\u0002^!)10\ba\u0001{!)Q0\ba\u0001}\"1\u0011QB\u000fA\u0002yDa!!\u0005\u001e\u0001\u0004q\bbBA\u000b;\u0001\u0007\u0011qC\u0001\u000b\u001d\u0006$\u0018N^3Vi&d\u0007CA, \u0005)q\u0015\r^5wKV#\u0018\u000e\\\n\u0003?M\"\"!!\u0019\u0014\u0005\u0005jF\u0003BA7\u0003c\u00022!a\u001c\"\u001b\u0005y\u0002\"B3$\u0001\u0004iFcC\"\u0002v\u0005]\u0014\u0011PA>\u0003{Ba!a\u000e%\u0001\u0004i\u0004BBA\u001eI\u0001\u0007a\u0010C\u0003~I\u0001\u0007a\u0010\u0003\u0004\u0002\u000e\u0011\u0002\rA \u0005\b\u0003\u0007\"\u0003\u0019AA#\'\t)c\u000e\u0006\u0003\u0002\u0004\u0006\u0015\u0005cAA8K!)\u0011o\na\u0001eRYQ,!#\u0002\f\u00065\u0015qRAI\u0011\u0015Y\b\u00061\u0001>\u0011\u0015i\b\u00061\u0001\u007f\u0011\u0019\ti\u0001\u000ba\u0001}\"1\u0011\u0011\u0003\u0015A\u0002yDq!!\u0006)\u0001\u0004\t9\u0002
   #9 = Utf8               org/sireum/Asm_Ext$NativeUtil$
  #10 = Class              #9             // org/sireum/Asm_Ext$NativeUtil$
  #11 = Utf8               NativeUtil$
  #12 = Utf8               org/sireum/Asm_Ext$ReleaseFence$
  #13 = Class              #12            // org/sireum/Asm_Ext$ReleaseFence$
  #14 = Utf8               ReleaseFence$
  #15 = Utf8               org/sireum/Asm_Ext$SecurityManager$
  #16 = Class              #15            // org/sireum/Asm_Ext$SecurityManager$
  #17 = Utf8               SecurityManager$
  #18 = Utf8               org/sireum/Os$Path
  #19 = Class              #18            // org/sireum/Os$Path
  #20 = Utf8               org/sireum/Os
  #21 = Class              #20            // org/sireum/Os
  #22 = Utf8               Path
  #23 = Utf8               rewriteSetSecurityManager
  #24 = Utf8               (Lorg/sireum/Os$Path;)V
  #25 = Utf8               path
  #26 = Utf8               org/sireum/Asm_Ext$
  #27 = Class              #26            // org/sireum/Asm_Ext$
  #28 = Utf8               MODULE$
  #29 = Utf8               Lorg/sireum/Asm_Ext$;
  #30 = NameAndType        #28:#29        // MODULE$:Lorg/sireum/Asm_Ext$;
  #31 = Fieldref           #27.#30        // org/sireum/Asm_Ext$.MODULE$:Lorg/sireum/Asm_Ext$;
  #32 = NameAndType        #23:#24        // rewriteSetSecurityManager:(Lorg/sireum/Os$Path;)V
  #33 = Methodref          #27.#32        // org/sireum/Asm_Ext$.rewriteSetSecurityManager:(Lorg/sireum/Os$Path;)V
  #34 = Utf8               Lorg/sireum/Os$Path;
  #35 = Utf8               rewriteReleaseFence
  #36 = NameAndType        #35:#24        // rewriteReleaseFence:(Lorg/sireum/Os$Path;)V
  #37 = Methodref          #27.#36        // org/sireum/Asm_Ext$.rewriteReleaseFence:(Lorg/sireum/Os$Path;)V
  #38 = Utf8               eraseNonNative
  #39 = NameAndType        #38:#24        // eraseNonNative:(Lorg/sireum/Os$Path;)V
  #40 = Methodref          #27.#39        // org/sireum/Asm_Ext$.eraseNonNative:(Lorg/sireum/Os$Path;)V
  #41 = Utf8               api
  #42 = Utf8               ()I
  #43 = NameAndType        #41:#42        // api:()I
  #44 = Methodref          #27.#43        // org/sireum/Asm_Ext$.api:()I
  #45 = Utf8               Code
  #46 = Utf8               LocalVariableTable
  #47 = Utf8               MethodParameters
  #48 = Utf8               InnerClasses
  #49 = Utf8               SourceFile
  #50 = Utf8               RuntimeVisibleAnnotations
  #51 = Utf8               ScalaSig
{
  public static void rewriteSetSecurityManager(org.sireum.Os$Path);
    descriptor: (Lorg/sireum/Os$Path;)V
    flags: (0x0009) ACC_PUBLIC, ACC_STATIC
    Code:
      stack=2, locals=1, args_size=1
         0: getstatic     #31                 // Field org/sireum/Asm_Ext$.MODULE$:Lorg/sireum/Asm_Ext$;
         3: aload_0
         4: invokevirtual #33                 // Method org/sireum/Asm_Ext$.rewriteSetSecurityManager:(Lorg/sireum/Os$Path;)V
         7: return
      LocalVariableTable:
        Start  Length  Slot  Name   Signature
            0       8     0  path   Lorg/sireum/Os$Path;
    MethodParameters:
      Name                           Flags
      path                           final

  public static void rewriteReleaseFence(org.sireum.Os$Path);
    descriptor: (Lorg/sireum/Os$Path;)V
    flags: (0x0009) ACC_PUBLIC, ACC_STATIC
    Code:
      stack=2, locals=1, args_size=1
         0: getstatic     #31                 // Field org/sireum/Asm_Ext$.MODULE$:Lorg/sireum/Asm_Ext$;
         3: aload_0
         4: invokevirtual #37                 // Method org/sireum/Asm_Ext$.rewriteReleaseFence:(Lorg/sireum/Os$Path;)V
         7: return
      LocalVariableTable:
        Start  Length  Slot  Name   Signature
            0       8     0  path   Lorg/sireum/Os$Path;
    MethodParameters:
      Name                           Flags
      path                           final

  public static void eraseNonNative(org.sireum.Os$Path);
    descriptor: (Lorg/sireum/Os$Path;)V
    flags: (0x0009) ACC_PUBLIC, ACC_STATIC
    Code:
      stack=2, locals=1, args_size=1
         0: getstatic     #31                 // Field org/sireum/Asm_Ext$.MODULE$:Lorg/sireum/Asm_Ext$;
         3: aload_0
         4: invokevirtual #40                 // Method org/sireum/Asm_Ext$.eraseNonNative:(Lorg/sireum/Os$Path;)V
         7: return
      LocalVariableTable:
        Start  Length  Slot  Name   Signature
            0       8     0  path   Lorg/sireum/Os$Path;
    MethodParameters:
      Name                           Flags
      path                           final

  public static int api();
    descriptor: ()I
    flags: (0x0009) ACC_PUBLIC, ACC_STATIC
    Code:
      stack=1, locals=0, args_size=0
         0: getstatic     #31                 // Field org/sireum/Asm_Ext$.MODULE$:Lorg/sireum/Asm_Ext$;
         3: invokevirtual #44                 // Method org/sireum/Asm_Ext$.api:()I
         6: ireturn
}
InnerClasses:
  public static #11= #10 of #2;           // NativeUtil$=class org/sireum/Asm_Ext$NativeUtil$ of class org/sireum/Asm_Ext
  public static #14= #13 of #2;           // ReleaseFence$=class org/sireum/Asm_Ext$ReleaseFence$ of class org/sireum/Asm_Ext
  public static #17= #16 of #2;           // SecurityManager$=class org/sireum/Asm_Ext$SecurityManager$ of class org/sireum/Asm_Ext
  public static #22= #19 of #21;          // Path=class org/sireum/Os$Path of class org/sireum/Os
SourceFile: "Asm_Ext.scala"
RuntimeVisibleAnnotations:
  0: #6(#7=s#8)
    scala.reflect.ScalaSignature(
      bytes="\u0006\u0005\u0005Mu!B\u0015+\u0011\u0003yc!B\u0019+\u0011\u0003\u0011\u0004\"B\u001d\u0002\t\u0003Q\u0004bB\u001e\u0002\u0005\u0004%\t\u0001\u0010\u0005\u0007\u0001\u0006\u0001\u000b\u0011B\u001f\t\u000b\u0005\u000bA\u0011\u0001\"\t\u000b=\u000bA\u0011\u0001)\t\u000bI\u000bA\u0011A*\b\u000bU\u000b\u0001\u0012\u0001,\u0007\u000ba\u000b\u0001\u0012A-\t\u000beJA\u0011\u0001.\u0007\tmK\u0001\u0001\u0018\u0005\tK.\u0011\t\u0011)A\u0005;\")\u0011h\u0003C\u0001M\")!n\u0003C!W\u001a!A.\u0003\u0001n\u0011!\txB!A!\u0002\u0013\u0011\b\"B\u001d\u0010\t\u0003)\b\"\u0002=\u0010\t\u0003JxaBA\u000f\u0003!\u0005\u0011q\u0004\u0004\b\u0003C\t\u0001\u0012AA\u0012\u0011\u0019ID\u0003\"\u0001\u0002&\u0019)1\f\u0006\u0001\u0002(!AQM\u0006B\u0001B\u0003%Q\f\u0003\u0004:-\u0011\u0005\u0011\u0011\u0006\u0005\b\u0003c1B\u0011IA\u001a\r\u0015aG\u0003AA&\u0011!\t(D!A!\u0002\u0013\u0011\bBB\u001d\u001b\t\u0003\ti\u0005\u0003\u0004y5\u0011\u0005\u00131K\u0004\b\u0003?\n\u0001\u0012AA1\r\u001d\t\u0019\'\u0001E\u0001\u0003KBa!O\u0010\u0005\u0002\u0005\u001dd!B. \u0001\u0005%\u0004\u0002C3\"\u0005\u0003\u0005\u000b\u0011B/\t\re\nC\u0011AA6\u0011\u001d\t\t$\tC!\u0003g2Q\u0001\\\u0010\u0001\u0003\u007fB\u0001\"]\u0013\u0003\u0002\u0003\u0006IA\u001d\u0005\u0007s\u0015\"\t!!!\t\ra,C\u0011IAD\u0003\u001d\t5/\\0FqRT!a\u000b\u0017\u0002\rML\'/Z;n\u0015\u0005i\u0013aA8sO\u000e\u0001\u0001C\u0001\u0019\u0002\u001b\u0005Q#aB!t[~+\u0005\u0010^\n\u0003\u0003M\u0002\"\u0001N\u001c\u000e\u0003UR\u0011AN\u0001\u0006g\u000e\fG.Y\u0005\u0003qU\u0012a!\u00118z%\u00164\u0017A\u0002\u001fj]&$h\bF\u00010\u0003\r\t\u0007/[\u000b\u0002{A\u0011AGP\u0005\u0003\u007fU\u00121!\u00138u\u0003\u0011\t\u0007/\u001b\u0011\u0002\u001d\u0015\u0014\u0018m]3O_:t\u0015\r^5wKR\u00111I\u0012\t\u0003i\u0011K!!R\u001b\u0003\tUs\u0017\u000e\u001e\u0005\u0006\u000f\u0016\u0001\r\u0001S\u0001\u0005a\u0006$\b\u000e\u0005\u0002J\u0019:\u0011\u0001GS\u0005\u0003\u0017*\n!aT:\n\u00055s%\u0001\u0002)bi\"T!a\u0013\u0016\u0002\'I,wO]5uKJ+G.Z1tK\u001a+gnY3\u0015\u0005\r\u000b\u0006\"B$\u0007\u0001\u0004A\u0015!\u0007:foJLG/Z*fiN+7-\u001e:jifl\u0015M\\1hKJ$\"a\u0011+\t\u000b\u001d;\u0001\u0019\u0001%\u0002\u0019I+G.Z1tK\u001a+gnY3\u0011\u0005]KQ\"A\u0001\u0003\u0019I+G.Z1tK\u001a+gnY3\u0014\u0005%\u0019D#\u0001,\u0003\u001153\u0016n]5u_J\u001c\"aC/\u0011\u0005y\u001bW\"A0\u000b\u0005\u0001\f\u0017aA1t[*\u0011!\rL\u0001\n_\nTWm\u0019;xK\nL!\u0001Z0\u0003\u001b5+G\u000f[8e-&\u001c\u0018\u000e^8s\u0003\u001d1\u0018n]5u_J$\"aZ5\u0011\u0005!\\Q\"A\u0005\t\u000b\u0015l\u0001\u0019A/\u0002\u0013YL7/\u001b;D_\u0012,G#A\"\u0003\u0011\r3\u0016n]5u_J\u001c\"a\u00048\u0011\u0005y{\u0017B\u00019`\u00051\u0019E.Y:t-&\u001c\u0018\u000e^8s\u0003\t\u0019w\u000f\u0005\u0002_g&\u0011Ao\u0018\u0002\f\u00072\f7o],sSR,\'\u000f\u0006\u0002woB\u0011\u0001n\u0004\u0005\u0006cF\u0001\rA]\u0001\fm&\u001c\u0018\u000e^\'fi\"|G\rF\u0005^ur\fY!a\u0004\u0002\u0014!)1P\u0005a\u0001{\u00051\u0011mY2fgNDQ! \nA\u0002y\fAA\\1nKB\u0019q0!\u0002\u000f\u0007Q\n\t!C\u0002\u0002\u0004U\na\u0001\u0015:fI\u00164\u0017\u0002BA\u0004\u0003\u0013\u0011aa\u0015;sS:<\'bAA\u0002k!1\u0011Q\u0002\nA\u0002y\f!\u0002Z3tGJL\u0007\u000f^8s\u0011\u0019\t\tB\u0005a\u0001}\u0006I1/[4oCR,(/\u001a\u0005\b\u0003+\u0011\u0002\u0019AA\f\u0003))\u0007pY3qi&|gn\u001d\t\u0005i\u0005ea0C\u0002\u0002\u001cU\u0012Q!\u0011:sCf\fqbU3dkJLG/_\'b]\u0006<WM\u001d\t\u0003/R\u0011qbU3dkJLG/_\'b]\u0006<WM]\n\u0003)M\"\"!a\b\u0014\u0005YiF\u0003BA\u0016\u0003_\u00012!!\f\u0017\u001b\u0005!\u0002\"B3\u0019\u0001\u0004i\u0016a\u0004<jg&$X*\u001a;i_\u0012Len\u001d8\u0015\u0017\r\u000b)$!\u000f\u0002>\u0005}\u0012\u0011\t\u0005\u0007\u0003oI\u0002\u0019A\u001f\u0002\r=\u00048m\u001c3f\u0011\u0019\tY$\u0007a\u0001}\u0006)qn\u001e8fe\")Q0\u0007a\u0001}\"1\u0011QB\rA\u0002yDq!a\u0011\u001a\u0001\u0004\t)%A\u0006jg&sG/\u001a:gC\u000e,\u0007c\u0001\u001b\u0002H%\u0019\u0011\u0011J\u001b\u0003\u000f\t{w\u000e\\3b]N\u0011!D\u001c\u000b\u0005\u0003\u001f\n\t\u0006E\u0002\u0002.iAQ!\u001d\u000fA\u0002I$2\"XA+\u0003/\nI&a\u0017\u0002^!)10\ba\u0001{!)Q0\ba\u0001}\"1\u0011QB\u000fA\u0002yDa!!\u0005\u001e\u0001\u0004q\bbBA\u000b;\u0001\u0007\u0011qC\u0001\u000b\u001d\u0006$\u0018N^3Vi&d\u0007CA, \u0005)q\u0015\r^5wKV#\u0018\u000e\\\n\u0003?M\"\"!!\u0019\u0014\u0005\u0005jF\u0003BA7\u0003c\u00022!a\u001c\"\u001b\u0005y\u0002\"B3$\u0001\u0004iFcC\"\u0002v\u0005]\u0014\u0011PA>\u0003{Ba!a\u000e%\u0001\u0004i\u0004BBA\u001eI\u0001\u0007a\u0010C\u0003~I\u0001\u0007a\u0010\u0003\u0004\u0002\u000e\u0011\u0002\rA \u0005\b\u0003\u0007\"\u0003\u0019AA#\'\t)c\u000e\u0006\u0003\u0002\u0004\u0006\u0015\u0005cAA8K!)\u0011o\na\u0001eRYQ,!#\u0002\f\u00065\u0015qRAI\u0011\u0015Y\b\u00061\u0001>\u0011\u0015i\b\u00061\u0001\u007f\u0011\u0019\ti\u0001\u000ba\u0001}\"1\u0011\u0011\u0003\u0015A\u0002yDq!!\u0006)\u0001\u0004\t9\u0002"
    )
  ScalaSig: length = 0x3 (unknown attribute)
   05 02 00
