Classfile /Users/mw/Projects/slang-braindump/.jar/jar8/assemble/slang-braindump/assemble/content/org/sireum/Asm_Ext$ReleaseFence$CVisitor.class
  Last modified May 29, 2022; size 1559 bytes
  SHA-256 checksum dbdadfea07fa64a6b3acf1ed5dc451a00211ab57e4402dd703438ddddd1acfc6
  Compiled from "Asm_Ext.scala"
public class org.sireum.Asm_Ext$ReleaseFence$CVisitor extends org.objectweb.asm.ClassVisitor
  minor version: 0
  major version: 52
  flags: (0x0021) ACC_PUBLIC, ACC_SUPER
  this_class: #2                          // org/sireum/Asm_Ext$ReleaseFence$CVisitor
  super_class: #4                         // org/objectweb/asm/ClassVisitor
  interfaces: 0, fields: 0, methods: 2, attributes: 4
Constant pool:
   #1 = Utf8               org/sireum/Asm_Ext$ReleaseFence$CVisitor
   #2 = Class              #1             // org/sireum/Asm_Ext$ReleaseFence$CVisitor
   #3 = Utf8               org/objectweb/asm/ClassVisitor
   #4 = Class              #3             // org/objectweb/asm/ClassVisitor
   #5 = Utf8               Asm_Ext.scala
   #6 = Utf8               org/sireum/Asm_Ext$ReleaseFence$
   #7 = Class              #6             // org/sireum/Asm_Ext$ReleaseFence$
   #8 = Utf8               org/sireum/Asm_Ext
   #9 = Class              #8             // org/sireum/Asm_Ext
  #10 = Utf8               ReleaseFence$
  #11 = Utf8               CVisitor
  #12 = Utf8               org/sireum/Asm_Ext$ReleaseFence$MVisitor
  #13 = Class              #12            // org/sireum/Asm_Ext$ReleaseFence$MVisitor
  #14 = Utf8               MVisitor
  #15 = Utf8               visitMethod
  #16 = Utf8               (ILjava/lang/String;Ljava/lang/String;Ljava/lang/String;[Ljava/lang/String;)Lorg/objectweb/asm/MethodVisitor;
  #17 = Utf8               access
  #18 = Utf8               name
  #19 = Utf8               descriptor
  #20 = Utf8               signature
  #21 = Utf8               exceptions
  #22 = NameAndType        #15:#16        // visitMethod:(ILjava/lang/String;Ljava/lang/String;Ljava/lang/String;[Ljava/lang/String;)Lorg/objectweb/asm/MethodVisitor;
  #23 = Methodref          #4.#22         // org/objectweb/asm/ClassVisitor.visitMethod:(ILjava/lang/String;Ljava/lang/String;Ljava/lang/String;[Ljava/lang/String;)Lorg/objectweb/asm/MethodVisitor;
  #24 = Utf8               releaseFence
  #25 = String             #24            // releaseFence
  #26 = Utf8               java/lang/Object
  #27 = Class              #26            // java/lang/Object
  #28 = Utf8               equals
  #29 = Utf8               (Ljava/lang/Object;)Z
  #30 = NameAndType        #28:#29        // equals:(Ljava/lang/Object;)Z
  #31 = Methodref          #27.#30        // java/lang/Object.equals:(Ljava/lang/Object;)Z
  #32 = Utf8               <init>
  #33 = Utf8               (Lorg/objectweb/asm/MethodVisitor;)V
  #34 = NameAndType        #32:#33        // "<init>":(Lorg/objectweb/asm/MethodVisitor;)V
  #35 = Methodref          #13.#34        // org/sireum/Asm_Ext$ReleaseFence$MVisitor."<init>":(Lorg/objectweb/asm/MethodVisitor;)V
  #36 = Utf8               visitor
  #37 = Utf8               Lorg/objectweb/asm/MethodVisitor;
  #38 = Utf8               this
  #39 = Utf8               Lorg/sireum/Asm_Ext$ReleaseFence$CVisitor;
  #40 = Utf8               I
  #41 = Utf8               Ljava/lang/String;
  #42 = Utf8               [Ljava/lang/String;
  #43 = Utf8               java/lang/String
  #44 = Class              #43            // java/lang/String
  #45 = Class              #42            // "[Ljava/lang/String;"
  #46 = Utf8               org/objectweb/asm/MethodVisitor
  #47 = Class              #46            // org/objectweb/asm/MethodVisitor
  #48 = Utf8               (Lorg/objectweb/asm/ClassWriter;)V
  #49 = Utf8               cw
  #50 = Utf8               org/sireum/Asm_Ext$
  #51 = Class              #50            // org/sireum/Asm_Ext$
  #52 = Utf8               MODULE$
  #53 = Utf8               Lorg/sireum/Asm_Ext$;
  #54 = NameAndType        #52:#53        // MODULE$:Lorg/sireum/Asm_Ext$;
  #55 = Fieldref           #51.#54        // org/sireum/Asm_Ext$.MODULE$:Lorg/sireum/Asm_Ext$;
  #56 = Utf8               api
  #57 = Utf8               ()I
  #58 = NameAndType        #56:#57        // api:()I
  #59 = Methodref          #51.#58        // org/sireum/Asm_Ext$.api:()I
  #60 = Utf8               (ILorg/objectweb/asm/ClassVisitor;)V
  #61 = NameAndType        #32:#60        // "<init>":(ILorg/objectweb/asm/ClassVisitor;)V
  #62 = Methodref          #4.#61         // org/objectweb/asm/ClassVisitor."<init>":(ILorg/objectweb/asm/ClassVisitor;)V
  #63 = Utf8               Lorg/objectweb/asm/ClassWriter;
  #64 = Utf8               Code
  #65 = Utf8               StackMapTable
  #66 = Utf8               LineNumberTable
  #67 = Utf8               LocalVariableTable
  #68 = Utf8               MethodParameters
  #69 = Utf8               InnerClasses
  #70 = Utf8               SourceFile
  #71 = Utf8               ScalaInlineInfo
  #72 = Utf8               Scala
{
  public org.objectweb.asm.MethodVisitor visitMethod(int, java.lang.String, java.lang.String, java.lang.String, java.lang.String[]);
    descriptor: (ILjava/lang/String;Ljava/lang/String;Ljava/lang/String;[Ljava/lang/String;)Lorg/objectweb/asm/MethodVisitor;
    flags: (0x0001) ACC_PUBLIC
    Code:
      stack=6, locals=8, args_size=6
         0: aload_0
         1: iload_1
         2: aload_2
         3: aload_3
         4: aload         4
         6: aload         5
         8: invokespecial #23                 // Method org/objectweb/asm/ClassVisitor.visitMethod:(ILjava/lang/String;Ljava/lang/String;Ljava/lang/String;[Ljava/lang/String;)Lorg/objectweb/asm/MethodVisitor;
        11: astore        6
        13: aload_2
        14: ldc           #25                 // String releaseFence
        16: astore        7
        18: dup
        19: ifnonnull     31
        22: pop
        23: aload         7
        25: ifnull        39
        28: goto          51
        31: aload         7
        33: invokevirtual #31                 // Method java/lang/Object.equals:(Ljava/lang/Object;)Z
        36: ifeq          51
        39: new           #13                 // class org/sireum/Asm_Ext$ReleaseFence$MVisitor
        42: dup
        43: aload         6
        45: invokespecial #35                 // Method org/sireum/Asm_Ext$ReleaseFence$MVisitor."<init>":(Lorg/objectweb/asm/MethodVisitor;)V
        48: goto          53
        51: aload         6
        53: areturn
      StackMapTable: number_of_entries = 4
        frame_type = 255 /* full_frame */
          offset_delta = 31
          locals = [ class org/sireum/Asm_Ext$ReleaseFence$CVisitor, int, class java/lang/String, class java/lang/String, class java/lang/String, class "[Ljava/lang/String;", class org/objectweb/asm/MethodVisitor, class java/lang/String ]
          stack = [ class java/lang/String ]
        frame_type = 7 /* same */
        frame_type = 11 /* same */
        frame_type = 65 /* same_locals_1_stack_item */
          stack = [ class org/objectweb/asm/MethodVisitor ]
      LineNumberTable:
        line 135: 0
        line 136: 13
      LocalVariableTable:
        Start  Length  Slot  Name   Signature
           13      41     6 visitor   Lorg/objectweb/asm/MethodVisitor;
            0      54     0  this   Lorg/sireum/Asm_Ext$ReleaseFence$CVisitor;
            0      54     1 access   I
            0      54     2  name   Ljava/lang/String;
            0      54     3 descriptor   Ljava/lang/String;
            0      54     4 signature   Ljava/lang/String;
            0      54     5 exceptions   [Ljava/lang/String;
    MethodParameters:
      Name                           Flags
      access                         final
      name                           final
      descriptor                     final
      signature                      final
      exceptions                     final

  public org.sireum.Asm_Ext$ReleaseFence$CVisitor(org.objectweb.asm.ClassWriter);
    descriptor: (Lorg/objectweb/asm/ClassWriter;)V
    flags: (0x0001) ACC_PUBLIC
    Code:
      stack=3, locals=2, args_size=2
         0: aload_0
         1: getstatic     #55                 // Field org/sireum/Asm_Ext$.MODULE$:Lorg/sireum/Asm_Ext$;
         4: invokevirtual #59                 // Method org/sireum/Asm_Ext$.api:()I
         7: aload_1
         8: invokespecial #62                 // Method org/objectweb/asm/ClassVisitor."<init>":(ILorg/objectweb/asm/ClassVisitor;)V
        11: return
      LineNumberTable:
        line 132: 0
      LocalVariableTable:
        Start  Length  Slot  Name   Signature
            0      12     0  this   Lorg/sireum/Asm_Ext$ReleaseFence$CVisitor;
            0      12     1    cw   Lorg/objectweb/asm/ClassWriter;
    MethodParameters:
      Name                           Flags
      cw                             final
}
InnerClasses:
  public static #10= #7 of #9;            // ReleaseFence$=class org/sireum/Asm_Ext$ReleaseFence$ of class org/sireum/Asm_Ext
  public static #11= #2 of #7;            // CVisitor=class org/sireum/Asm_Ext$ReleaseFence$CVisitor of class org/sireum/Asm_Ext$ReleaseFence$
  public static #14= #13 of #7;           // MVisitor=class org/sireum/Asm_Ext$ReleaseFence$MVisitor of class org/sireum/Asm_Ext$ReleaseFence$
SourceFile: "Asm_Ext.scala"
  ScalaInlineInfo: length = 0xE (unknown attribute)
   01 00 00 02 00 20 00 30 00 00 0F 00 10 00
  Scala: length = 0x0 (unknown attribute)

