Classfile /Users/mw/Projects/slang-braindump/.jar/jar8/assemble/slang-braindump/assemble/content/org/sireum/CircularQueue$NoDrop$.class
  Last modified May 29, 2022; size 4124 bytes
  SHA-256 checksum b91a5853a98aa8f59d76247d43397eae51bf01001c52036599b44df8e0e2c7ce
  Compiled from "CircularQueue.scala"
public class org.sireum.CircularQueue$NoDrop$
  minor version: 0
  major version: 52
  flags: (0x0021) ACC_PUBLIC, ACC_SUPER
  this_class: #2                          // org/sireum/CircularQueue$NoDrop$
  super_class: #4                         // java/lang/Object
  interfaces: 0, fields: 1, methods: 6, attributes: 4
Constant pool:
    #1 = Utf8               org/sireum/CircularQueue$NoDrop$
    #2 = Class              #1            // org/sireum/CircularQueue$NoDrop$
    #3 = Utf8               java/lang/Object
    #4 = Class              #3            // java/lang/Object
    #5 = Utf8               CircularQueue.scala
    #6 = Utf8               org/sireum/CircularQueue$NoDrop
    #7 = Class              #6            // org/sireum/CircularQueue$NoDrop
    #8 = Utf8               org/sireum/CircularQueue
    #9 = Class              #8            // org/sireum/CircularQueue
   #10 = Utf8               NoDrop
   #11 = Utf8               NoDrop$
   #12 = Utf8               MODULE$
   #13 = Utf8               Lorg/sireum/CircularQueue$NoDrop$;
   #14 = Utf8               <clinit>
   #15 = Utf8               ()V
   #16 = Utf8               <init>
   #17 = NameAndType        #16:#15       // "<init>":()V
   #18 = Methodref          #2.#17        // org/sireum/CircularQueue$NoDrop$."<init>":()V
   #19 = NameAndType        #12:#13       // MODULE$:Lorg/sireum/CircularQueue$NoDrop$;
   #20 = Fieldref           #2.#19        // org/sireum/CircularQueue$NoDrop$.MODULE$:Lorg/sireum/CircularQueue$NoDrop$;
   #21 = Utf8               create
   #22 = Utf8               (Lorg/sireum/Z;Ljava/lang/Object;Z)Lorg/sireum/CircularQueue$NoDrop;
   #23 = Utf8               <E:Ljava/lang/Object;>(Lorg/sireum/Z;TE;Z)Lorg/sireum/CircularQueue$NoDrop<TE;>;
   #24 = Utf8               max
   #25 = Utf8               default
   #26 = Utf8               scrub
   #27 = Utf8               scala/runtime/BoxedUnit
   #28 = Class              #27           // scala/runtime/BoxedUnit
   #29 = Utf8               UNIT
   #30 = Utf8               Lscala/runtime/BoxedUnit;
   #31 = NameAndType        #29:#30       // UNIT:Lscala/runtime/BoxedUnit;
   #32 = Fieldref           #28.#31       // scala/runtime/BoxedUnit.UNIT:Lscala/runtime/BoxedUnit;
   #33 = Utf8               org/sireum/helper$
   #34 = Class              #33           // org/sireum/helper$
   #35 = Utf8               Lorg/sireum/helper$;
   #36 = NameAndType        #12:#35       // MODULE$:Lorg/sireum/helper$;
   #37 = Fieldref           #34.#36       // org/sireum/helper$.MODULE$:Lorg/sireum/helper$;
   #38 = Utf8               org/sireum/MS$
   #39 = Class              #38           // org/sireum/MS$
   #40 = Utf8               Lorg/sireum/MS$;
   #41 = NameAndType        #12:#40       // MODULE$:Lorg/sireum/MS$;
   #42 = Fieldref           #39.#41       // org/sireum/MS$.MODULE$:Lorg/sireum/MS$;
   #43 = Utf8               org/sireum/Z$
   #44 = Class              #43           // org/sireum/Z$
   #45 = Utf8               Lorg/sireum/Z$;
   #46 = NameAndType        #12:#45       // MODULE$:Lorg/sireum/Z$;
   #47 = Fieldref           #44.#46       // org/sireum/Z$.MODULE$:Lorg/sireum/Z$;
   #48 = Utf8               apply
   #49 = Utf8               (I)Lorg/sireum/Z;
   #50 = NameAndType        #48:#49       // apply:(I)Lorg/sireum/Z;
   #51 = Methodref          #44.#50       // org/sireum/Z$.apply:(I)Lorg/sireum/Z;
   #52 = Utf8               org/sireum/Z
   #53 = Class              #52           // org/sireum/Z
   #54 = Utf8               $plus
   #55 = Utf8               (Lorg/sireum/Z;)Lorg/sireum/Z;
   #56 = NameAndType        #54:#55       // $plus:(Lorg/sireum/Z;)Lorg/sireum/Z;
   #57 = InterfaceMethodref #53.#56       // org/sireum/Z.$plus:(Lorg/sireum/Z;)Lorg/sireum/Z;
   #58 = Utf8               org/sireum/package$
   #59 = Class              #58           // org/sireum/package$
   #60 = Utf8               Lorg/sireum/package$;
   #61 = NameAndType        #12:#60       // MODULE$:Lorg/sireum/package$;
   #62 = Fieldref           #59.#61       // org/sireum/package$.MODULE$:Lorg/sireum/package$;
   #63 = Utf8               $ZCompanion
   #64 = Utf8               ()Lorg/sireum/$ZCompanion;
   #65 = NameAndType        #63:#64       // $ZCompanion:()Lorg/sireum/$ZCompanion;
   #66 = Methodref          #59.#65       // org/sireum/package$.$ZCompanion:()Lorg/sireum/$ZCompanion;
   #67 = Utf8               (Lorg/sireum/Z;Ljava/lang/Object;Lorg/sireum/$ZCompanion;)Lorg/sireum/MS;
   #68 = NameAndType        #21:#67       // create:(Lorg/sireum/Z;Ljava/lang/Object;Lorg/sireum/$ZCompanion;)Lorg/sireum/MS;
   #69 = Methodref          #39.#68       // org/sireum/MS$.create:(Lorg/sireum/Z;Ljava/lang/Object;Lorg/sireum/$ZCompanion;)Lorg/sireum/MS;
   #70 = Utf8               (Lorg/sireum/Z;Ljava/lang/Object;ZLorg/sireum/MS;Lorg/sireum/Z;Lorg/sireum/Z;Lorg/sireum/Z;)Lorg/sireum/CircularQueue$NoDrop;
   #71 = NameAndType        #48:#70       // apply:(Lorg/sireum/Z;Ljava/lang/Object;ZLorg/sireum/MS;Lorg/sireum/Z;Lorg/sireum/Z;Lorg/sireum/Z;)Lorg/sireum/CircularQueue$NoDrop;
   #72 = Methodref          #2.#71        // org/sireum/CircularQueue$NoDrop$.apply:(Lorg/sireum/Z;Ljava/lang/Object;ZLorg/sireum/MS;Lorg/sireum/Z;Lorg/sireum/Z;Lorg/sireum/Z;)Lorg/sireum/CircularQueue$NoDrop;
   #73 = Utf8               retMut
   #74 = Utf8               (Lorg/sireum/$internal/MutableMarker;)Ljava/lang/Object;
   #75 = NameAndType        #73:#74       // retMut:(Lorg/sireum/$internal/MutableMarker;)Ljava/lang/Object;
   #76 = Methodref          #34.#75       // org/sireum/helper$.retMut:(Lorg/sireum/$internal/MutableMarker;)Ljava/lang/Object;
   #77 = Utf8               this
   #78 = Utf8               Lorg/sireum/Z;
   #79 = Utf8               Ljava/lang/Object;
   #80 = Utf8               Z
   #81 = Utf8               additionalCreateEnsures
   #82 = Utf8               (Lorg/sireum/CircularQueue$NoDrop;)Z
   #83 = Utf8               <E:Ljava/lang/Object;>(Lorg/sireum/CircularQueue$NoDrop<TE;>;)Z
   #84 = Utf8               res
   #85 = Utf8               org/sireum/B$
   #86 = Class              #85           // org/sireum/B$
   #87 = Utf8               Lorg/sireum/B$;
   #88 = NameAndType        #12:#87       // MODULE$:Lorg/sireum/B$;
   #89 = Fieldref           #86.#88       // org/sireum/B$.MODULE$:Lorg/sireum/B$;
   #90 = Utf8               front
   #91 = Utf8               ()Lorg/sireum/Z;
   #92 = NameAndType        #90:#91       // front:()Lorg/sireum/Z;
   #93 = Methodref          #7.#92        // org/sireum/CircularQueue$NoDrop.front:()Lorg/sireum/Z;
   #94 = Utf8               equals
   #95 = Utf8               (Ljava/lang/Object;)Z
   #96 = NameAndType        #94:#95       // equals:(Ljava/lang/Object;)Z
   #97 = Methodref          #4.#96        // java/lang/Object.equals:(Ljava/lang/Object;)Z
   #98 = Utf8               rear
   #99 = NameAndType        #98:#91       // rear:()Lorg/sireum/Z;
  #100 = Methodref          #7.#99        // org/sireum/CircularQueue$NoDrop.rear:()Lorg/sireum/Z;
  #101 = Utf8               numOfElements
  #102 = NameAndType        #101:#91      // numOfElements:()Lorg/sireum/Z;
  #103 = Methodref          #7.#102       // org/sireum/CircularQueue$NoDrop.numOfElements:()Lorg/sireum/Z;
  #104 = Utf8               org/sireum/ContractUtil$
  #105 = Class              #104          // org/sireum/ContractUtil$
  #106 = Utf8               Lorg/sireum/ContractUtil$;
  #107 = NameAndType        #12:#106      // MODULE$:Lorg/sireum/ContractUtil$;
  #108 = Fieldref           #105.#107     // org/sireum/ContractUtil$.MODULE$:Lorg/sireum/ContractUtil$;
  #109 = Utf8               queue
  #110 = Utf8               ()Lorg/sireum/MS;
  #111 = NameAndType        #109:#110     // queue:()Lorg/sireum/MS;
  #112 = Methodref          #7.#111       // org/sireum/CircularQueue$NoDrop.queue:()Lorg/sireum/MS;
  #113 = Utf8               ()Ljava/lang/Object;
  #114 = NameAndType        #25:#113      // default:()Ljava/lang/Object;
  #115 = Methodref          #7.#114       // org/sireum/CircularQueue$NoDrop.default:()Ljava/lang/Object;
  #116 = Utf8               isAllMS
  #117 = Utf8               (Lorg/sireum/MS;Ljava/lang/Object;)Z
  #118 = NameAndType        #116:#117     // isAllMS:(Lorg/sireum/MS;Ljava/lang/Object;)Z
  #119 = Methodref          #105.#118     // org/sireum/ContractUtil$.isAllMS:(Lorg/sireum/MS;Ljava/lang/Object;)Z
  #120 = Utf8               $4B
  #121 = Utf8               (Z)Z
  #122 = NameAndType        #120:#121     // $4B:(Z)Z
  #123 = Methodref          #86.#122      // org/sireum/B$.$4B:(Z)Z
  #124 = NameAndType        #48:#121      // apply:(Z)Z
  #125 = Methodref          #86.#124      // org/sireum/B$.apply:(Z)Z
  #126 = Utf8               Lorg/sireum/CircularQueue$NoDrop;
  #127 = Utf8               <E:Ljava/lang/Object;>(Lorg/sireum/Z;TE;ZLorg/sireum/MS<Lorg/sireum/Z;TE;>;Lorg/sireum/Z;Lorg/sireum/Z;Lorg/sireum/Z;)Lorg/sireum/CircularQueue$NoDrop<TE;>;
  #128 = Utf8               (Lorg/sireum/Z;Ljava/lang/Object;ZLorg/sireum/MS;Lorg/sireum/Z;Lorg/sireum/Z;Lorg/sireum/Z;)V
  #129 = NameAndType        #16:#128      // "<init>":(Lorg/sireum/Z;Ljava/lang/Object;ZLorg/sireum/MS;Lorg/sireum/Z;Lorg/sireum/Z;Lorg/sireum/Z;)V
  #130 = Methodref          #7.#129       // org/sireum/CircularQueue$NoDrop."<init>":(Lorg/sireum/Z;Ljava/lang/Object;ZLorg/sireum/MS;Lorg/sireum/Z;Lorg/sireum/Z;Lorg/sireum/Z;)V
  #131 = Utf8               Lorg/sireum/MS;
  #132 = Utf8               unapply
  #133 = Utf8               (Lorg/sireum/CircularQueue$NoDrop;)Lscala/Some;
  #134 = Utf8               <E:Ljava/lang/Object;>(Lorg/sireum/CircularQueue$NoDrop<TE;>;)Lscala/Some<Lscala/Tuple7<Lorg/sireum/Z;TE;Lorg/sireum/B;Lorg/sireum/MS<Lorg/sireum/Z;TE;>;Lorg/sireum/Z;Lorg/sireum/Z;Lorg/sireum/Z;>;>;
  #135 = Utf8               o
  #136 = Utf8               scala/Some
  #137 = Class              #136          // scala/Some
  #138 = Utf8               scala/Tuple7
  #139 = Class              #138          // scala/Tuple7
  #140 = NameAndType        #24:#91       // max:()Lorg/sireum/Z;
  #141 = Methodref          #7.#140       // org/sireum/CircularQueue$NoDrop.max:()Lorg/sireum/Z;
  #142 = Utf8               clone
  #143 = Utf8               (Ljava/lang/Object;)Ljava/lang/Object;
  #144 = NameAndType        #142:#143     // clone:(Ljava/lang/Object;)Ljava/lang/Object;
  #145 = Methodref          #34.#144      // org/sireum/helper$.clone:(Ljava/lang/Object;)Ljava/lang/Object;
  #146 = Utf8               org/sireum/B
  #147 = Class              #146          // org/sireum/B
  #148 = Utf8               ()Z
  #149 = NameAndType        #26:#148      // scrub:()Z
  #150 = Methodref          #7.#149       // org/sireum/CircularQueue$NoDrop.scrub:()Z
  #151 = Utf8               (Z)V
  #152 = NameAndType        #16:#151      // "<init>":(Z)V
  #153 = Methodref          #147.#152     // org/sireum/B."<init>":(Z)V
  #154 = Utf8               (Ljava/lang/Object;Ljava/lang/Object;Ljava/lang/Object;Ljava/lang/Object;Ljava/lang/Object;Ljava/lang/Object;Ljava/lang/Object;)V
  #155 = NameAndType        #16:#154      // "<init>":(Ljava/lang/Object;Ljava/lang/Object;Ljava/lang/Object;Ljava/lang/Object;Ljava/lang/Object;Ljava/lang/Object;Ljava/lang/Object;)V
  #156 = Methodref          #139.#155     // scala/Tuple7."<init>":(Ljava/lang/Object;Ljava/lang/Object;Ljava/lang/Object;Ljava/lang/Object;Ljava/lang/Object;Ljava/lang/Object;Ljava/lang/Object;)V
  #157 = Utf8               (Ljava/lang/Object;)V
  #158 = NameAndType        #16:#157      // "<init>":(Ljava/lang/Object;)V
  #159 = Methodref          #137.#158     // scala/Some."<init>":(Ljava/lang/Object;)V
  #160 = Methodref          #4.#17        // java/lang/Object."<init>":()V
  #161 = Utf8               Code
  #162 = Utf8               LineNumberTable
  #163 = Utf8               LocalVariableTable
  #164 = Utf8               Signature
  #165 = Utf8               MethodParameters
  #166 = Utf8               StackMapTable
  #167 = Utf8               InnerClasses
  #168 = Utf8               SourceFile
  #169 = Utf8               ScalaInlineInfo
  #170 = Utf8               Scala
{
  public static final org.sireum.CircularQueue$NoDrop$ MODULE$;
    descriptor: Lorg/sireum/CircularQueue$NoDrop$;
    flags: (0x0019) ACC_PUBLIC, ACC_STATIC, ACC_FINAL

  public static {};
    descriptor: ()V
    flags: (0x0009) ACC_PUBLIC, ACC_STATIC
    Code:
      stack=2, locals=0, args_size=0
         0: new           #2                  // class org/sireum/CircularQueue$NoDrop$
         3: dup
         4: invokespecial #18                 // Method "<init>":()V
         7: putstatic     #20                 // Field MODULE$:Lorg/sireum/CircularQueue$NoDrop$;
        10: return
      LineNumberTable:
        line 128: 0

  public <E extends java.lang.Object> org.sireum.CircularQueue$NoDrop<E> create(org.sireum.Z, E, boolean);
    descriptor: (Lorg/sireum/Z;Ljava/lang/Object;Z)Lorg/sireum/CircularQueue$NoDrop;
    flags: (0x0001) ACC_PUBLIC
    Code:
      stack=10, locals=4, args_size=4
         0: getstatic     #32                 // Field scala/runtime/BoxedUnit.UNIT:Lscala/runtime/BoxedUnit;
         3: pop
         4: getstatic     #37                 // Field org/sireum/helper$.MODULE$:Lorg/sireum/helper$;
         7: aload_0
         8: aload_1
         9: aload_2
        10: iload_3
        11: getstatic     #42                 // Field org/sireum/MS$.MODULE$:Lorg/sireum/MS$;
        14: aload_1
        15: getstatic     #47                 // Field org/sireum/Z$.MODULE$:Lorg/sireum/Z$;
        18: iconst_1
        19: invokevirtual #51                 // Method org/sireum/Z$.apply:(I)Lorg/sireum/Z;
        22: invokeinterface #57,  2           // InterfaceMethod org/sireum/Z.$plus:(Lorg/sireum/Z;)Lorg/sireum/Z;
        27: aload_2
        28: getstatic     #62                 // Field org/sireum/package$.MODULE$:Lorg/sireum/package$;
        31: invokevirtual #66                 // Method org/sireum/package$.$ZCompanion:()Lorg/sireum/$ZCompanion;
        34: invokevirtual #69                 // Method org/sireum/MS$.create:(Lorg/sireum/Z;Ljava/lang/Object;Lorg/sireum/$ZCompanion;)Lorg/sireum/MS;
        37: getstatic     #47                 // Field org/sireum/Z$.MODULE$:Lorg/sireum/Z$;
        40: iconst_0
        41: invokevirtual #51                 // Method org/sireum/Z$.apply:(I)Lorg/sireum/Z;
        44: getstatic     #47                 // Field org/sireum/Z$.MODULE$:Lorg/sireum/Z$;
        47: iconst_0
        48: invokevirtual #51                 // Method org/sireum/Z$.apply:(I)Lorg/sireum/Z;
        51: getstatic     #47                 // Field org/sireum/Z$.MODULE$:Lorg/sireum/Z$;
        54: iconst_0
        55: invokevirtual #51                 // Method org/sireum/Z$.apply:(I)Lorg/sireum/Z;
        58: invokevirtual #72                 // Method apply:(Lorg/sireum/Z;Ljava/lang/Object;ZLorg/sireum/MS;Lorg/sireum/Z;Lorg/sireum/Z;Lorg/sireum/Z;)Lorg/sireum/CircularQueue$NoDrop;
        61: invokevirtual #76                 // Method org/sireum/helper$.retMut:(Lorg/sireum/$internal/MutableMarker;)Ljava/lang/Object;
        64: checkcast     #7                  // class org/sireum/CircularQueue$NoDrop
        67: areturn
      LineNumberTable:
        line 131: 0
        line 139: 4
      LocalVariableTable:
        Start  Length  Slot  Name   Signature
            0      68     0  this   Lorg/sireum/CircularQueue$NoDrop$;
            0      68     1   max   Lorg/sireum/Z;
            0      68     2 default   Ljava/lang/Object;
            0      68     3 scrub   Z
    Signature: #23                          // <E:Ljava/lang/Object;>(Lorg/sireum/Z;TE;Z)Lorg/sireum/CircularQueue$NoDrop<TE;>;
    MethodParameters:
      Name                           Flags
      max                            final
      default                        final
      scrub                          final

  public <E extends java.lang.Object> boolean additionalCreateEnsures(org.sireum.CircularQueue$NoDrop<E>);
    descriptor: (Lorg/sireum/CircularQueue$NoDrop;)Z
    flags: (0x0001) ACC_PUBLIC
    Code:
      stack=6, locals=5, args_size=2
         0: getstatic     #89                 // Field org/sireum/B$.MODULE$:Lorg/sireum/B$;
         3: aload_1
         4: invokevirtual #93                 // Method org/sireum/CircularQueue$NoDrop.front:()Lorg/sireum/Z;
         7: getstatic     #47                 // Field org/sireum/Z$.MODULE$:Lorg/sireum/Z$;
        10: iconst_0
        11: invokevirtual #51                 // Method org/sireum/Z$.apply:(I)Lorg/sireum/Z;
        14: astore_2
        15: dup
        16: ifnonnull     27
        19: pop
        20: aload_2
        21: ifnull        34
        24: goto          38
        27: aload_2
        28: invokevirtual #97                 // Method java/lang/Object.equals:(Ljava/lang/Object;)Z
        31: ifeq          38
        34: iconst_1
        35: goto          39
        38: iconst_0
        39: aload_1
        40: invokevirtual #100                // Method org/sireum/CircularQueue$NoDrop.rear:()Lorg/sireum/Z;
        43: getstatic     #47                 // Field org/sireum/Z$.MODULE$:Lorg/sireum/Z$;
        46: iconst_0
        47: invokevirtual #51                 // Method org/sireum/Z$.apply:(I)Lorg/sireum/Z;
        50: astore_3
        51: dup
        52: ifnonnull     63
        55: pop
        56: aload_3
        57: ifnull        70
        60: goto          74
        63: aload_3
        64: invokevirtual #97                 // Method java/lang/Object.equals:(Ljava/lang/Object;)Z
        67: ifeq          74
        70: iconst_1
        71: goto          75
        74: iconst_0
        75: iand
        76: aload_1
        77: invokevirtual #103                // Method org/sireum/CircularQueue$NoDrop.numOfElements:()Lorg/sireum/Z;
        80: getstatic     #47                 // Field org/sireum/Z$.MODULE$:Lorg/sireum/Z$;
        83: iconst_0
        84: invokevirtual #51                 // Method org/sireum/Z$.apply:(I)Lorg/sireum/Z;
        87: astore        4
        89: dup
        90: ifnonnull     102
        93: pop
        94: aload         4
        96: ifnull        110
        99: goto          114
       102: aload         4
       104: invokevirtual #97                 // Method java/lang/Object.equals:(Ljava/lang/Object;)Z
       107: ifeq          114
       110: iconst_1
       111: goto          115
       114: iconst_0
       115: iand
       116: getstatic     #89                 // Field org/sireum/B$.MODULE$:Lorg/sireum/B$;
       119: getstatic     #108                // Field org/sireum/ContractUtil$.MODULE$:Lorg/sireum/ContractUtil$;
       122: aload_1
       123: invokevirtual #112                // Method org/sireum/CircularQueue$NoDrop.queue:()Lorg/sireum/MS;
       126: aload_1
       127: invokevirtual #115                // Method org/sireum/CircularQueue$NoDrop.default:()Ljava/lang/Object;
       130: invokevirtual #119                // Method org/sireum/ContractUtil$.isAllMS:(Lorg/sireum/MS;Ljava/lang/Object;)Z
       133: invokevirtual #123                // Method org/sireum/B$.$4B:(Z)Z
       136: iand
       137: invokevirtual #125                // Method org/sireum/B$.apply:(Z)Z
       140: ireturn
      StackMapTable: number_of_entries = 12
        frame_type = 255 /* full_frame */
          offset_delta = 27
          locals = [ class org/sireum/CircularQueue$NoDrop$, class org/sireum/CircularQueue$NoDrop, class org/sireum/Z ]
          stack = [ class org/sireum/B$, class org/sireum/Z ]
        frame_type = 70 /* same_locals_1_stack_item */
          stack = [ class org/sireum/B$ ]
        frame_type = 67 /* same_locals_1_stack_item */
          stack = [ class org/sireum/B$ ]
        frame_type = 255 /* full_frame */
          offset_delta = 0
          locals = [ class org/sireum/CircularQueue$NoDrop$, class org/sireum/CircularQueue$NoDrop, class org/sireum/Z ]
          stack = [ class org/sireum/B$, int ]
        frame_type = 255 /* full_frame */
          offset_delta = 23
          locals = [ class org/sireum/CircularQueue$NoDrop$, class org/sireum/CircularQueue$NoDrop, class org/sireum/Z, class org/sireum/Z ]
          stack = [ class org/sireum/B$, int, class org/sireum/Z ]
        frame_type = 255 /* full_frame */
          offset_delta = 6
          locals = [ class org/sireum/CircularQueue$NoDrop$, class org/sireum/CircularQueue$NoDrop, class org/sireum/Z, class org/sireum/Z ]
          stack = [ class org/sireum/B$, int ]
        frame_type = 255 /* full_frame */
          offset_delta = 3
          locals = [ class org/sireum/CircularQueue$NoDrop$, class org/sireum/CircularQueue$NoDrop, class org/sireum/Z, class org/sireum/Z ]
          stack = [ class org/sireum/B$, int ]
        frame_type = 255 /* full_frame */
          offset_delta = 0
          locals = [ class org/sireum/CircularQueue$NoDrop$, class org/sireum/CircularQueue$NoDrop, class org/sireum/Z, class org/sireum/Z ]
          stack = [ class org/sireum/B$, int, int ]
        frame_type = 255 /* full_frame */
          offset_delta = 26
          locals = [ class org/sireum/CircularQueue$NoDrop$, class org/sireum/CircularQueue$NoDrop, class org/sireum/Z, class org/sireum/Z, class org/sireum/Z ]
          stack = [ class org/sireum/B$, int, class org/sireum/Z ]
        frame_type = 255 /* full_frame */
          offset_delta = 7
          locals = [ class org/sireum/CircularQueue$NoDrop$, class org/sireum/CircularQueue$NoDrop, class org/sireum/Z, class org/sireum/Z, class org/sireum/Z ]
          stack = [ class org/sireum/B$, int ]
        frame_type = 255 /* full_frame */
          offset_delta = 3
          locals = [ class org/sireum/CircularQueue$NoDrop$, class org/sireum/CircularQueue$NoDrop, class org/sireum/Z, class org/sireum/Z, class org/sireum/Z ]
          stack = [ class org/sireum/B$, int ]
        frame_type = 255 /* full_frame */
          offset_delta = 0
          locals = [ class org/sireum/CircularQueue$NoDrop$, class org/sireum/CircularQueue$NoDrop, class org/sireum/Z, class org/sireum/Z, class org/sireum/Z ]
          stack = [ class org/sireum/B$, int, int ]
      LineNumberTable:
        line 145: 0
        line 143: 3
        line 144: 39
        line 145: 76
        line 146: 116
        line 145: 137
      LocalVariableTable:
        Start  Length  Slot  Name   Signature
            0     141     0  this   Lorg/sireum/CircularQueue$NoDrop$;
            0     141     1   res   Lorg/sireum/CircularQueue$NoDrop;
    Signature: #83                          // <E:Ljava/lang/Object;>(Lorg/sireum/CircularQueue$NoDrop<TE;>;)Z
    MethodParameters:
      Name                           Flags
      res                            final

  public <E extends java.lang.Object> org.sireum.CircularQueue$NoDrop<E> apply(org.sireum.Z, E, boolean, org.sireum.MS<org.sireum.Z, E>, org.sireum.Z, org.sireum.Z, org.sireum.Z);
    descriptor: (Lorg/sireum/Z;Ljava/lang/Object;ZLorg/sireum/MS;Lorg/sireum/Z;Lorg/sireum/Z;Lorg/sireum/Z;)Lorg/sireum/CircularQueue$NoDrop;
    flags: (0x0001) ACC_PUBLIC
    Code:
      stack=9, locals=8, args_size=8
         0: new           #7                  // class org/sireum/CircularQueue$NoDrop
         3: dup
         4: aload_1
         5: aload_2
         6: iload_3
         7: aload         4
         9: aload         5
        11: aload         6
        13: aload         7
        15: invokespecial #130                // Method org/sireum/CircularQueue$NoDrop."<init>":(Lorg/sireum/Z;Ljava/lang/Object;ZLorg/sireum/MS;Lorg/sireum/Z;Lorg/sireum/Z;Lorg/sireum/Z;)V
        18: areturn
      LineNumberTable:
        line 128: 0
      LocalVariableTable:
        Start  Length  Slot  Name   Signature
            0      19     0  this   Lorg/sireum/CircularQueue$NoDrop$;
            0      19     1   max   Lorg/sireum/Z;
            0      19     2 default   Ljava/lang/Object;
            0      19     3 scrub   Z
            0      19     4 queue   Lorg/sireum/MS;
            0      19     5 front   Lorg/sireum/Z;
            0      19     6  rear   Lorg/sireum/Z;
            0      19     7 numOfElements   Lorg/sireum/Z;
    Signature: #127                         // <E:Ljava/lang/Object;>(Lorg/sireum/Z;TE;ZLorg/sireum/MS<Lorg/sireum/Z;TE;>;Lorg/sireum/Z;Lorg/sireum/Z;Lorg/sireum/Z;)Lorg/sireum/CircularQueue$NoDrop<TE;>;
    MethodParameters:
      Name                           Flags
      max                            final
      default                        final
      scrub                          final
      queue                          final
      front                          final
      rear                           final
      numOfElements                  final

  public <E extends java.lang.Object> scala.Some<scala.Tuple7<org.sireum.Z, E, org.sireum.B, org.sireum.MS<org.sireum.Z, E>, org.sireum.Z, org.sireum.Z, org.sireum.Z>> unapply(org.sireum.CircularQueue$NoDrop<E>);
    descriptor: (Lorg/sireum/CircularQueue$NoDrop;)Lscala/Some;
    flags: (0x0001) ACC_PUBLIC
    Code:
      stack=12, locals=2, args_size=2
         0: new           #137                // class scala/Some
         3: dup
         4: new           #139                // class scala/Tuple7
         7: dup
         8: getstatic     #37                 // Field org/sireum/helper$.MODULE$:Lorg/sireum/helper$;
        11: aload_1
        12: invokevirtual #141                // Method org/sireum/CircularQueue$NoDrop.max:()Lorg/sireum/Z;
        15: invokevirtual #145                // Method org/sireum/helper$.clone:(Ljava/lang/Object;)Ljava/lang/Object;
        18: getstatic     #37                 // Field org/sireum/helper$.MODULE$:Lorg/sireum/helper$;
        21: aload_1
        22: invokevirtual #115                // Method org/sireum/CircularQueue$NoDrop.default:()Ljava/lang/Object;
        25: invokevirtual #145                // Method org/sireum/helper$.clone:(Ljava/lang/Object;)Ljava/lang/Object;
        28: getstatic     #37                 // Field org/sireum/helper$.MODULE$:Lorg/sireum/helper$;
        31: new           #147                // class org/sireum/B
        34: dup
        35: aload_1
        36: invokevirtual #150                // Method org/sireum/CircularQueue$NoDrop.scrub:()Z
        39: invokespecial #153                // Method org/sireum/B."<init>":(Z)V
        42: invokevirtual #145                // Method org/sireum/helper$.clone:(Ljava/lang/Object;)Ljava/lang/Object;
        45: getstatic     #37                 // Field org/sireum/helper$.MODULE$:Lorg/sireum/helper$;
        48: aload_1
        49: invokevirtual #112                // Method org/sireum/CircularQueue$NoDrop.queue:()Lorg/sireum/MS;
        52: invokevirtual #145                // Method org/sireum/helper$.clone:(Ljava/lang/Object;)Ljava/lang/Object;
        55: getstatic     #37                 // Field org/sireum/helper$.MODULE$:Lorg/sireum/helper$;
        58: aload_1
        59: invokevirtual #93                 // Method org/sireum/CircularQueue$NoDrop.front:()Lorg/sireum/Z;
        62: invokevirtual #145                // Method org/sireum/helper$.clone:(Ljava/lang/Object;)Ljava/lang/Object;
        65: getstatic     #37                 // Field org/sireum/helper$.MODULE$:Lorg/sireum/helper$;
        68: aload_1
        69: invokevirtual #100                // Method org/sireum/CircularQueue$NoDrop.rear:()Lorg/sireum/Z;
        72: invokevirtual #145                // Method org/sireum/helper$.clone:(Ljava/lang/Object;)Ljava/lang/Object;
        75: getstatic     #37                 // Field org/sireum/helper$.MODULE$:Lorg/sireum/helper$;
        78: aload_1
        79: invokevirtual #103                // Method org/sireum/CircularQueue$NoDrop.numOfElements:()Lorg/sireum/Z;
        82: invokevirtual #145                // Method org/sireum/helper$.clone:(Ljava/lang/Object;)Ljava/lang/Object;
        85: invokespecial #156                // Method scala/Tuple7."<init>":(Ljava/lang/Object;Ljava/lang/Object;Ljava/lang/Object;Ljava/lang/Object;Ljava/lang/Object;Ljava/lang/Object;Ljava/lang/Object;)V
        88: invokespecial #159                // Method scala/Some."<init>":(Ljava/lang/Object;)V
        91: areturn
      LineNumberTable:
        line 128: 0
      LocalVariableTable:
        Start  Length  Slot  Name   Signature
            0      92     0  this   Lorg/sireum/CircularQueue$NoDrop$;
            0      92     1     o   Lorg/sireum/CircularQueue$NoDrop;
    Signature: #134                         // <E:Ljava/lang/Object;>(Lorg/sireum/CircularQueue$NoDrop<TE;>;)Lscala/Some<Lscala/Tuple7<Lorg/sireum/Z;TE;Lorg/sireum/B;Lorg/sireum/MS<Lorg/sireum/Z;TE;>;Lorg/sireum/Z;Lorg/sireum/Z;Lorg/sireum/Z;>;>;
    MethodParameters:
      Name                           Flags
      o                              final

  public org.sireum.CircularQueue$NoDrop$();
    descriptor: ()V
    flags: (0x0001) ACC_PUBLIC
    Code:
      stack=1, locals=1, args_size=1
         0: aload_0
         1: invokespecial #160                // Method java/lang/Object."<init>":()V
         4: return
      LineNumberTable:
        line 128: 0
      LocalVariableTable:
        Start  Length  Slot  Name   Signature
            0       5     0  this   Lorg/sireum/CircularQueue$NoDrop$;
}
InnerClasses:
  public static final #10= #7 of #9;      // NoDrop=class org/sireum/CircularQueue$NoDrop of class org/sireum/CircularQueue
  public static #11= #2 of #9;            // NoDrop$=class org/sireum/CircularQueue$NoDrop$ of class org/sireum/CircularQueue
SourceFile: "CircularQueue.scala"
  ScalaInlineInfo: length = 0x1D (unknown attribute)
   01 01 00 05 00 10 00 0F 01 00 51 00 52 01 00 30
   00 46 01 00 15 00 16 01 00 84 00 85 01
  Scala: length = 0x0 (unknown attribute)

