Classfile /Users/mw/Projects/slang-braindump/.jar/jar8/assemble/slang-braindump/assemble/content/org/sireum/CircularQueue$DropFront.class
  Last modified May 29, 2022; size 14239 bytes
  SHA-256 checksum d601d28e1b0644052e49a122a0c1dcca87950fcd8dc046256ed2f688c506f7f7
  Compiled from "CircularQueue.scala"
public final class org.sireum.CircularQueue$DropFront<E extends java.lang.Object> extends java.lang.Object implements org.sireum.CircularQueue<E>
  minor version: 0
  major version: 52
  flags: (0x0031) ACC_PUBLIC, ACC_FINAL, ACC_SUPER
  this_class: #2                          // org/sireum/CircularQueue$DropFront
  super_class: #5                         // java/lang/Object
  interfaces: 1, fields: 9, methods: 61, attributes: 6
Constant pool:
    #1 = Utf8               org/sireum/CircularQueue$DropFront
    #2 = Class              #1            // org/sireum/CircularQueue$DropFront
    #3 = Utf8               <E:Ljava/lang/Object;>Ljava/lang/Object;Lorg/sireum/CircularQueue<TE;>;
    #4 = Utf8               java/lang/Object
    #5 = Class              #4            // java/lang/Object
    #6 = Utf8               org/sireum/CircularQueue
    #7 = Class              #6            // org/sireum/CircularQueue
    #8 = Utf8               CircularQueue.scala
    #9 = Utf8               java/lang/invoke/MethodHandles$Lookup
   #10 = Class              #9            // java/lang/invoke/MethodHandles$Lookup
   #11 = Utf8               java/lang/invoke/MethodHandles
   #12 = Class              #11           // java/lang/invoke/MethodHandles
   #13 = Utf8               Lookup
   #14 = Utf8               org/sireum/$internal/PackageTrait$MSZ$
   #15 = Class              #14           // org/sireum/$internal/PackageTrait$MSZ$
   #16 = Utf8               org/sireum/$internal/PackageTrait
   #17 = Class              #16           // org/sireum/$internal/PackageTrait
   #18 = Utf8               MSZ$
   #19 = Utf8               DropFront
   #20 = Utf8               org/sireum/CircularQueue$Policy$
   #21 = Class              #20           // org/sireum/CircularQueue$Policy$
   #22 = Utf8               Policy$
   #23 = Utf8               org/sireum/CircularQueue$Policy$DropFront$
   #24 = Class              #23           // org/sireum/CircularQueue$Policy$DropFront$
   #25 = Utf8               DropFront$
   #26 = Utf8               org/sireum/CircularQueue$Policy$Type
   #27 = Class              #26           // org/sireum/CircularQueue$Policy$Type
   #28 = Utf8               Type
   #29 = Utf8               org/sireum/contract$Contract$
   #30 = Class              #29           // org/sireum/contract$Contract$
   #31 = Utf8               org/sireum/contract
   #32 = Class              #31           // org/sireum/contract
   #33 = Utf8               Contract$
   #34 = Utf8               org/sireum/contract$Contract$Invariant
   #35 = Class              #34           // org/sireum/contract$Contract$Invariant
   #36 = Utf8               Invariant
   #37 = Utf8               _max
   #38 = Utf8               Lorg/sireum/Z;
   #39 = Utf8               _default
   #40 = Utf8               Ljava/lang/Object;
   #41 = Utf8               TE;
   #42 = Utf8               _scrub
   #43 = Utf8               Z
   #44 = Utf8               _queue
   #45 = Utf8               Lorg/sireum/MS;
   #46 = Utf8               Lorg/sireum/MS<Lorg/sireum/Z;TE;>;
   #47 = Utf8               _front
   #48 = Utf8               _rear
   #49 = Utf8               _numOfElements
   #50 = Utf8               rep
   #51 = Utf8               org$sireum$RecordSig$$$isOwned
   #52 = Utf8               repInv
   #53 = Utf8               ()Lorg/sireum/contract$Contract$Invariant;
   #54 = Utf8               repInv$
   #55 = Utf8               (Lorg/sireum/CircularQueue;)Lorg/sireum/contract$Contract$Invariant;
   #56 = NameAndType        #54:#55       // repInv$:(Lorg/sireum/CircularQueue;)Lorg/sireum/contract$Contract$Invariant;
   #57 = InterfaceMethodref #7.#56        // org/sireum/CircularQueue.repInv$:(Lorg/sireum/CircularQueue;)Lorg/sireum/contract$Contract$Invariant;
   #58 = Utf8               this
   #59 = Utf8               Lorg/sireum/CircularQueue$DropFront;
   #60 = Utf8               $owned
   #61 = Utf8               ()Z
   #62 = Utf8               org/sireum/RecordSig
   #63 = Class              #62           // org/sireum/RecordSig
   #64 = Utf8               $owned$
   #65 = Utf8               (Lorg/sireum/RecordSig;)Z
   #66 = NameAndType        #64:#65       // $owned$:(Lorg/sireum/RecordSig;)Z
   #67 = InterfaceMethodref #63.#66       // org/sireum/RecordSig.$owned$:(Lorg/sireum/RecordSig;)Z
   #68 = Utf8               $owned_$eq
   #69 = Utf8               (Z)Lorg/sireum/RecordSig;
   #70 = Utf8               b
   #71 = Utf8               $owned_$eq$
   #72 = Utf8               (Lorg/sireum/RecordSig;Z)Lorg/sireum/RecordSig;
   #73 = NameAndType        #71:#72       // $owned_$eq$:(Lorg/sireum/RecordSig;Z)Lorg/sireum/RecordSig;
   #74 = InterfaceMethodref #63.#73       // org/sireum/RecordSig.$owned_$eq$:(Lorg/sireum/RecordSig;Z)Lorg/sireum/RecordSig;
   #75 = Utf8               hash
   #76 = Utf8               ()Lorg/sireum/Z;
   #77 = Utf8               hash$
   #78 = Utf8               (Lorg/sireum/RecordSig;)Lorg/sireum/Z;
   #79 = NameAndType        #77:#78       // hash$:(Lorg/sireum/RecordSig;)Lorg/sireum/Z;
   #80 = InterfaceMethodref #63.#79       // org/sireum/RecordSig.hash$:(Lorg/sireum/RecordSig;)Lorg/sireum/Z;
   #81 = Utf8               $cannotMixImmutableAndMutable
   #82 = Utf8               ()Lscala/runtime/Nothing$;
   #83 = Utf8               org/sireum/Mutable
   #84 = Class              #83           // org/sireum/Mutable
   #85 = Utf8               $cannotMixImmutableAndMutable$
   #86 = Utf8               (Lorg/sireum/Mutable;)Lscala/runtime/Nothing$;
   #87 = NameAndType        #85:#86       // $cannotMixImmutableAndMutable$:(Lorg/sireum/Mutable;)Lscala/runtime/Nothing$;
   #88 = InterfaceMethodref #84.#87       // org/sireum/Mutable.$cannotMixImmutableAndMutable$:(Lorg/sireum/Mutable;)Lscala/runtime/Nothing$;
   #89 = Utf8               $hasEquals
   #90 = Utf8               $hasEquals$
   #91 = Utf8               (Lorg/sireum/Mutable;)Z
   #92 = NameAndType        #90:#91       // $hasEquals$:(Lorg/sireum/Mutable;)Z
   #93 = InterfaceMethodref #84.#92       // org/sireum/Mutable.$hasEquals$:(Lorg/sireum/Mutable;)Z
   #94 = Utf8               $hasString
   #95 = Utf8               $hasString$
   #96 = NameAndType        #95:#91       // $hasString$:(Lorg/sireum/Mutable;)Z
   #97 = InterfaceMethodref #84.#96       // org/sireum/Mutable.$hasString$:(Lorg/sireum/Mutable;)Z
   #98 = Utf8               ()Lorg/sireum/MS;
   #99 = Utf8               ()Lorg/sireum/MS<Lorg/sireum/Z;TE;>;
  #100 = NameAndType        #50:#45       // rep:Lorg/sireum/MS;
  #101 = Fieldref           #2.#100       // org/sireum/CircularQueue$DropFront.rep:Lorg/sireum/MS;
  #102 = Utf8               rep_$eq
  #103 = Utf8               (Lorg/sireum/MS;)V
  #104 = Utf8               (Lorg/sireum/MS<Lorg/sireum/Z;TE;>;)V
  #105 = Utf8               x$1
  #106 = NameAndType        #51:#43       // org$sireum$RecordSig$$$isOwned:Z
  #107 = Fieldref           #2.#106       // org/sireum/CircularQueue$DropFront.org$sireum$RecordSig$$$isOwned:Z
  #108 = Utf8               org$sireum$RecordSig$$$isOwned_$eq
  #109 = Utf8               (Z)V
  #110 = Utf8               max
  #111 = NameAndType        #37:#38       // _max:Lorg/sireum/Z;
  #112 = Fieldref           #2.#111       // org/sireum/CircularQueue$DropFront._max:Lorg/sireum/Z;
  #113 = Utf8               getMax
  #114 = Utf8               default
  #115 = Utf8               ()Ljava/lang/Object;
  #116 = Utf8               ()TE;
  #117 = NameAndType        #39:#40       // _default:Ljava/lang/Object;
  #118 = Fieldref           #2.#117       // org/sireum/CircularQueue$DropFront._default:Ljava/lang/Object;
  #119 = Utf8               getDefault
  #120 = Utf8               scrub
  #121 = NameAndType        #42:#43       // _scrub:Z
  #122 = Fieldref           #2.#121       // org/sireum/CircularQueue$DropFront._scrub:Z
  #123 = Utf8               getScrub
  #124 = Utf8               queue
  #125 = NameAndType        #44:#45       // _queue:Lorg/sireum/MS;
  #126 = Fieldref           #2.#125       // org/sireum/CircularQueue$DropFront._queue:Lorg/sireum/MS;
  #127 = Utf8               getQueue
  #128 = Utf8               front
  #129 = NameAndType        #47:#38       // _front:Lorg/sireum/Z;
  #130 = Fieldref           #2.#129       // org/sireum/CircularQueue$DropFront._front:Lorg/sireum/Z;
  #131 = Utf8               getFront
  #132 = Utf8               front_$eq
  #133 = Utf8               (Lorg/sireum/Z;)Lorg/sireum/CircularQueue$DropFront;
  #134 = Utf8               (Lorg/sireum/Z;)Lorg/sireum/CircularQueue$DropFront<TE;>;
  #135 = Utf8               setFront
  #136 = Utf8               rear
  #137 = NameAndType        #48:#38       // _rear:Lorg/sireum/Z;
  #138 = Fieldref           #2.#137       // org/sireum/CircularQueue$DropFront._rear:Lorg/sireum/Z;
  #139 = Utf8               getRear
  #140 = Utf8               rear_$eq
  #141 = Utf8               setRear
  #142 = Utf8               numOfElements
  #143 = NameAndType        #49:#38       // _numOfElements:Lorg/sireum/Z;
  #144 = Fieldref           #2.#143       // org/sireum/CircularQueue$DropFront._numOfElements:Lorg/sireum/Z;
  #145 = Utf8               getNumOfElements
  #146 = Utf8               numOfElements_$eq
  #147 = Utf8               setNumOfElements
  #148 = Utf8               toString
  #149 = Utf8               ()Ljava/lang/String;
  #150 = Utf8               string$
  #151 = Utf8               (Lorg/sireum/CircularQueue;)Ljava/lang/String;
  #152 = NameAndType        #150:#151     // string$:(Lorg/sireum/CircularQueue;)Ljava/lang/String;
  #153 = InterfaceMethodref #7.#152       // org/sireum/CircularQueue.string$:(Lorg/sireum/CircularQueue;)Ljava/lang/String;
  #154 = Utf8               string
  #155 = Utf8               hashCode
  #156 = Utf8               ()I
  #157 = NameAndType        #89:#61       // $hasEquals:()Z
  #158 = Methodref          #2.#157       // org/sireum/CircularQueue$DropFront.$hasEquals:()Z
  #159 = NameAndType        #155:#156     // hashCode:()I
  #160 = Methodref          #5.#159       // java/lang/Object.hashCode:()I
  #161 = Utf8               scala/package$
  #162 = Class              #161          // scala/package$
  #163 = Utf8               MODULE$
  #164 = Utf8               Lscala/package$;
  #165 = NameAndType        #163:#164     // MODULE$:Lscala/package$;
  #166 = Fieldref           #162.#165     // scala/package$.MODULE$:Lscala/package$;
  #167 = Utf8               Seq
  #168 = Utf8               ()Lscala/collection/immutable/Seq$;
  #169 = NameAndType        #167:#168     // Seq:()Lscala/collection/immutable/Seq$;
  #170 = Methodref          #162.#169     // scala/package$.Seq:()Lscala/collection/immutable/Seq$;
  #171 = Utf8               scala/runtime/ScalaRunTime$
  #172 = Class              #171          // scala/runtime/ScalaRunTime$
  #173 = Utf8               Lscala/runtime/ScalaRunTime$;
  #174 = NameAndType        #163:#173     // MODULE$:Lscala/runtime/ScalaRunTime$;
  #175 = Fieldref           #172.#174     // scala/runtime/ScalaRunTime$.MODULE$:Lscala/runtime/ScalaRunTime$;
  #176 = Utf8               getClass
  #177 = Utf8               ()Ljava/lang/Class;
  #178 = NameAndType        #176:#177     // getClass:()Ljava/lang/Class;
  #179 = Methodref          #2.#178       // org/sireum/CircularQueue$DropFront.getClass:()Ljava/lang/Class;
  #180 = Utf8               java/lang/Class
  #181 = Class              #180          // java/lang/Class
  #182 = Utf8               getName
  #183 = NameAndType        #182:#149     // getName:()Ljava/lang/String;
  #184 = Methodref          #181.#183     // java/lang/Class.getName:()Ljava/lang/String;
  #185 = NameAndType        #110:#76      // max:()Lorg/sireum/Z;
  #186 = Methodref          #2.#185       // org/sireum/CircularQueue$DropFront.max:()Lorg/sireum/Z;
  #187 = NameAndType        #114:#115     // default:()Ljava/lang/Object;
  #188 = Methodref          #2.#187       // org/sireum/CircularQueue$DropFront.default:()Ljava/lang/Object;
  #189 = Utf8               org/sireum/B
  #190 = Class              #189          // org/sireum/B
  #191 = NameAndType        #120:#61      // scrub:()Z
  #192 = Methodref          #2.#191       // org/sireum/CircularQueue$DropFront.scrub:()Z
  #193 = Utf8               <init>
  #194 = NameAndType        #193:#109     // "<init>":(Z)V
  #195 = Methodref          #190.#194     // org/sireum/B."<init>":(Z)V
  #196 = NameAndType        #124:#98      // queue:()Lorg/sireum/MS;
  #197 = Methodref          #2.#196       // org/sireum/CircularQueue$DropFront.queue:()Lorg/sireum/MS;
  #198 = NameAndType        #128:#76      // front:()Lorg/sireum/Z;
  #199 = Methodref          #2.#198       // org/sireum/CircularQueue$DropFront.front:()Lorg/sireum/Z;
  #200 = NameAndType        #136:#76      // rear:()Lorg/sireum/Z;
  #201 = Methodref          #2.#200       // org/sireum/CircularQueue$DropFront.rear:()Lorg/sireum/Z;
  #202 = NameAndType        #142:#76      // numOfElements:()Lorg/sireum/Z;
  #203 = Methodref          #2.#202       // org/sireum/CircularQueue$DropFront.numOfElements:()Lorg/sireum/Z;
  #204 = Utf8               genericWrapArray
  #205 = Utf8               (Ljava/lang/Object;)Lscala/collection/immutable/ArraySeq;
  #206 = NameAndType        #204:#205     // genericWrapArray:(Ljava/lang/Object;)Lscala/collection/immutable/ArraySeq;
  #207 = Methodref          #172.#206     // scala/runtime/ScalaRunTime$.genericWrapArray:(Ljava/lang/Object;)Lscala/collection/immutable/ArraySeq;
  #208 = Utf8               scala/collection/immutable/Seq$
  #209 = Class              #208          // scala/collection/immutable/Seq$
  #210 = Utf8               apply
  #211 = Utf8               (Lscala/collection/immutable/Seq;)Lscala/collection/SeqOps;
  #212 = NameAndType        #210:#211     // apply:(Lscala/collection/immutable/Seq;)Lscala/collection/SeqOps;
  #213 = Methodref          #209.#212     // scala/collection/immutable/Seq$.apply:(Lscala/collection/immutable/Seq;)Lscala/collection/SeqOps;
  #214 = Utf8               scala/collection/Seq
  #215 = Class              #214          // scala/collection/Seq
  #216 = InterfaceMethodref #215.#159     // scala/collection/Seq.hashCode:()I
  #217 = Utf8               equals
  #218 = Utf8               (Ljava/lang/Object;)Z
  #219 = Utf8               o
  #220 = NameAndType        #217:#218     // equals:(Ljava/lang/Object;)Z
  #221 = Methodref          #5.#220       // java/lang/Object.equals:(Ljava/lang/Object;)Z
  #222 = Methodref          #2.#159       // org/sireum/CircularQueue$DropFront.hashCode:()I
  #223 = Utf8               scala/runtime/BoxesRunTime
  #224 = Class              #223          // scala/runtime/BoxesRunTime
  #225 = Utf8               (Ljava/lang/Object;Ljava/lang/Object;)Z
  #226 = NameAndType        #217:#225     // equals:(Ljava/lang/Object;Ljava/lang/Object;)Z
  #227 = Methodref          #224.#226     // scala/runtime/BoxesRunTime.equals:(Ljava/lang/Object;Ljava/lang/Object;)Z
  #228 = Utf8               org/sireum/Z
  #229 = Class              #228          // org/sireum/Z
  #230 = Utf8               org/sireum/MS
  #231 = Class              #230          // org/sireum/MS
  #232 = Utf8               (Lorg/sireum/Z;Ljava/lang/Object;ZLorg/sireum/MS;Lorg/sireum/Z;Lorg/sireum/Z;Lorg/sireum/Z;)Lorg/sireum/CircularQueue$DropFront;
  #233 = Utf8               (Lorg/sireum/Z;TE;ZLorg/sireum/MS<Lorg/sireum/Z;TE;>;Lorg/sireum/Z;Lorg/sireum/Z;Lorg/sireum/Z;)Lorg/sireum/CircularQueue$DropFront<TE;>;
  #234 = Utf8               org/sireum/helper$
  #235 = Class              #234          // org/sireum/helper$
  #236 = Utf8               Lorg/sireum/helper$;
  #237 = NameAndType        #163:#236     // MODULE$:Lorg/sireum/helper$;
  #238 = Fieldref           #235.#237     // org/sireum/helper$.MODULE$:Lorg/sireum/helper$;
  #239 = Utf8               assignMut
  #240 = Utf8               (Lorg/sireum/$internal/MutableMarker;)Ljava/lang/Object;
  #241 = NameAndType        #239:#240     // assignMut:(Lorg/sireum/$internal/MutableMarker;)Ljava/lang/Object;
  #242 = Methodref          #235.#241     // org/sireum/helper$.assignMut:(Lorg/sireum/$internal/MutableMarker;)Ljava/lang/Object;
  #243 = Utf8               (Lorg/sireum/Z;Ljava/lang/Object;ZLorg/sireum/MS;Lorg/sireum/Z;Lorg/sireum/Z;Lorg/sireum/Z;)V
  #244 = NameAndType        #193:#243     // "<init>":(Lorg/sireum/Z;Ljava/lang/Object;ZLorg/sireum/MS;Lorg/sireum/Z;Lorg/sireum/Z;Lorg/sireum/Z;)V
  #245 = Methodref          #2.#244       // org/sireum/CircularQueue$DropFront."<init>":(Lorg/sireum/Z;Ljava/lang/Object;ZLorg/sireum/MS;Lorg/sireum/Z;Lorg/sireum/Z;Lorg/sireum/Z;)V
  #246 = Utf8               apply$default$1
  #247 = Utf8               apply$default$2
  #248 = Utf8               apply$default$3
  #249 = Utf8               apply$default$4
  #250 = Utf8               apply$default$5
  #251 = Utf8               apply$default$6
  #252 = Utf8               apply$default$7
  #253 = Utf8               $content
  #254 = Utf8               ()Lscala/collection/immutable/Seq;
  #255 = Utf8               ()Lscala/collection/immutable/Seq<Lscala/Tuple2<Ljava/lang/String;Ljava/lang/Object;>;>;
  #256 = Utf8               scala/Tuple2
  #257 = Class              #256          // scala/Tuple2
  #258 = Utf8               type
  #259 = String             #258          // type
  #260 = Utf8               List
  #261 = Utf8               ()Lscala/collection/immutable/List$;
  #262 = NameAndType        #260:#261     // List:()Lscala/collection/immutable/List$;
  #263 = Methodref          #162.#262     // scala/package$.List:()Lscala/collection/immutable/List$;
  #264 = Utf8               java/lang/String
  #265 = Class              #264          // java/lang/String
  #266 = Utf8               org
  #267 = String             #266          // org
  #268 = Utf8               sireum
  #269 = String             #268          // sireum
  #270 = String             #19           // DropFront
  #271 = Utf8               [Ljava/lang/Object;
  #272 = Class              #271          // "[Ljava/lang/Object;"
  #273 = Utf8               wrapRefArray
  #274 = Utf8               ([Ljava/lang/Object;)Lscala/collection/immutable/ArraySeq;
  #275 = NameAndType        #273:#274     // wrapRefArray:([Ljava/lang/Object;)Lscala/collection/immutable/ArraySeq;
  #276 = Methodref          #172.#275     // scala/runtime/ScalaRunTime$.wrapRefArray:([Ljava/lang/Object;)Lscala/collection/immutable/ArraySeq;
  #277 = Utf8               scala/collection/immutable/List$
  #278 = Class              #277          // scala/collection/immutable/List$
  #279 = Utf8               (Lscala/collection/immutable/Seq;)Ljava/lang/Object;
  #280 = NameAndType        #210:#279     // apply:(Lscala/collection/immutable/Seq;)Ljava/lang/Object;
  #281 = Methodref          #278.#280     // scala/collection/immutable/List$.apply:(Lscala/collection/immutable/Seq;)Ljava/lang/Object;
  #282 = Utf8               (Ljava/lang/Object;Ljava/lang/Object;)V
  #283 = NameAndType        #193:#282     // "<init>":(Ljava/lang/Object;Ljava/lang/Object;)V
  #284 = Methodref          #257.#283     // scala/Tuple2."<init>":(Ljava/lang/Object;Ljava/lang/Object;)V
  #285 = String             #110          // max
  #286 = String             #114          // default
  #287 = String             #120          // scrub
  #288 = String             #124          // queue
  #289 = String             #128          // front
  #290 = String             #136          // rear
  #291 = String             #142          // numOfElements
  #292 = Utf8               scala/collection/immutable/Seq
  #293 = Class              #292          // scala/collection/immutable/Seq
  #294 = Utf8               $clone
  #295 = Utf8               ()Lorg/sireum/CircularQueue$DropFront;
  #296 = Utf8               ()Lorg/sireum/CircularQueue$DropFront<TE;>;
  #297 = Utf8               cloneAssign
  #298 = Utf8               (Ljava/lang/Object;)Ljava/lang/Object;
  #299 = NameAndType        #297:#298     // cloneAssign:(Ljava/lang/Object;)Ljava/lang/Object;
  #300 = Methodref          #235.#299     // org/sireum/helper$.cloneAssign:(Ljava/lang/Object;)Ljava/lang/Object;
  #301 = Utf8               value
  #302 = NameAndType        #301:#61      // value:()Z
  #303 = Methodref          #190.#302     // org/sireum/B.value:()Z
  #304 = Utf8               r
  #305 = Utf8               invariant
  #306 = Utf8               org/sireum/package$
  #307 = Class              #306          // org/sireum/package$
  #308 = Utf8               Lorg/sireum/package$;
  #309 = NameAndType        #163:#308     // MODULE$:Lorg/sireum/package$;
  #310 = Fieldref           #307.#309     // org/sireum/package$.MODULE$:Lorg/sireum/package$;
  #311 = Utf8               org/sireum/CircularQueue$
  #312 = Class              #311          // org/sireum/CircularQueue$
  #313 = Utf8               Lorg/sireum/CircularQueue$;
  #314 = NameAndType        #163:#313     // MODULE$:Lorg/sireum/CircularQueue$;
  #315 = Fieldref           #312.#314     // org/sireum/CircularQueue$.MODULE$:Lorg/sireum/CircularQueue$;
  #316 = Utf8               inv
  #317 = Utf8               (Lorg/sireum/Z;Ljava/lang/Object;ZLorg/sireum/MS;Lorg/sireum/Z;Lorg/sireum/Z;Lorg/sireum/Z;)Z
  #318 = NameAndType        #316:#317     // inv:(Lorg/sireum/Z;Ljava/lang/Object;ZLorg/sireum/MS;Lorg/sireum/Z;Lorg/sireum/Z;Lorg/sireum/Z;)Z
  #319 = Methodref          #312.#318     // org/sireum/CircularQueue$.inv:(Lorg/sireum/Z;Ljava/lang/Object;ZLorg/sireum/MS;Lorg/sireum/Z;Lorg/sireum/Z;Lorg/sireum/Z;)Z
  #320 = Utf8               (Lscala/collection/immutable/Seq;)Lorg/sireum/contract$Contract$Invariant;
  #321 = NameAndType        #36:#320      // Invariant:(Lscala/collection/immutable/Seq;)Lorg/sireum/contract$Contract$Invariant;
  #322 = Methodref          #307.#321     // org/sireum/package$.Invariant:(Lscala/collection/immutable/Seq;)Lorg/sireum/contract$Contract$Invariant;
  #323 = Utf8               policy
  #324 = Utf8               ()Lorg/sireum/CircularQueue$Policy$Type;
  #325 = Utf8               Lorg/sireum/CircularQueue$Policy$DropFront$;
  #326 = NameAndType        #163:#325     // MODULE$:Lorg/sireum/CircularQueue$Policy$DropFront$;
  #327 = Fieldref           #24.#326      // org/sireum/CircularQueue$Policy$DropFront$.MODULE$:Lorg/sireum/CircularQueue$Policy$DropFront$;
  #328 = Utf8               size
  #329 = Utf8               scala/runtime/BoxedUnit
  #330 = Class              #329          // scala/runtime/BoxedUnit
  #331 = Utf8               UNIT
  #332 = Utf8               Lscala/runtime/BoxedUnit;
  #333 = NameAndType        #331:#332     // UNIT:Lscala/runtime/BoxedUnit;
  #334 = Fieldref           #330.#333     // scala/runtime/BoxedUnit.UNIT:Lscala/runtime/BoxedUnit;
  #335 = Utf8               isEmpty
  #336 = Utf8               org/sireum/B$
  #337 = Class              #336          // org/sireum/B$
  #338 = Utf8               Lorg/sireum/B$;
  #339 = NameAndType        #163:#338     // MODULE$:Lorg/sireum/B$;
  #340 = Fieldref           #337.#339     // org/sireum/B$.MODULE$:Lorg/sireum/B$;
  #341 = Utf8               org/sireum/Z$
  #342 = Class              #341          // org/sireum/Z$
  #343 = Utf8               Lorg/sireum/Z$;
  #344 = NameAndType        #163:#343     // MODULE$:Lorg/sireum/Z$;
  #345 = Fieldref           #342.#344     // org/sireum/Z$.MODULE$:Lorg/sireum/Z$;
  #346 = Utf8               (I)Lorg/sireum/Z;
  #347 = NameAndType        #210:#346     // apply:(I)Lorg/sireum/Z;
  #348 = Methodref          #342.#347     // org/sireum/Z$.apply:(I)Lorg/sireum/Z;
  #349 = Utf8               (Z)Z
  #350 = NameAndType        #210:#349     // apply:(Z)Z
  #351 = Methodref          #337.#350     // org/sireum/B$.apply:(Z)Z
  #352 = Utf8               nonEmpty
  #353 = NameAndType        #335:#61      // isEmpty:()Z
  #354 = Methodref          #2.#353       // org/sireum/CircularQueue$DropFront.isEmpty:()Z
  #355 = Utf8               unary_$bang$extension
  #356 = NameAndType        #355:#349     // unary_$bang$extension:(Z)Z
  #357 = Methodref          #337.#356     // org/sireum/B$.unary_$bang$extension:(Z)Z
  #358 = Utf8               isFull
  #359 = Utf8               enqueue
  #360 = Utf8               (Ljava/lang/Object;)V
  #361 = Utf8               (TE;)V
  #362 = Utf8               element
  #363 = NameAndType        #358:#61      // isFull:()Z
  #364 = Methodref          #2.#363       // org/sireum/CircularQueue$DropFront.isFull:()Z
  #365 = Utf8               $4B
  #366 = NameAndType        #365:#349     // $4B:(Z)Z
  #367 = Methodref          #337.#366     // org/sireum/B$.$4B:(Z)Z
  #368 = Utf8               dequeue
  #369 = NameAndType        #368:#115     // dequeue:()Ljava/lang/Object;
  #370 = Methodref          #2.#369       // org/sireum/CircularQueue$DropFront.dequeue:()Ljava/lang/Object;
  #371 = Utf8               update
  #372 = NameAndType        #371:#282     // update:(Ljava/lang/Object;Ljava/lang/Object;)V
  #373 = Methodref          #231.#372     // org/sireum/MS.update:(Ljava/lang/Object;Ljava/lang/Object;)V
  #374 = Utf8               org/sireum/ContractUtil$
  #375 = Class              #374          // org/sireum/ContractUtil$
  #376 = Utf8               Lorg/sireum/ContractUtil$;
  #377 = NameAndType        #163:#376     // MODULE$:Lorg/sireum/ContractUtil$;
  #378 = Fieldref           #375.#377     // org/sireum/ContractUtil$.MODULE$:Lorg/sireum/ContractUtil$;
  #379 = Utf8               $plus
  #380 = Utf8               (Lorg/sireum/Z;)Lorg/sireum/Z;
  #381 = NameAndType        #379:#380     // $plus:(Lorg/sireum/Z;)Lorg/sireum/Z;
  #382 = InterfaceMethodref #229.#381     // org/sireum/Z.$plus:(Lorg/sireum/Z;)Lorg/sireum/Z;
  #383 = NameAndType        #328:#76      // size:()Lorg/sireum/Z;
  #384 = Methodref          #231.#383     // org/sireum/MS.size:()Lorg/sireum/Z;
  #385 = Utf8               modPos
  #386 = Utf8               (Lorg/sireum/Z;Lorg/sireum/Z;)Lorg/sireum/Z;
  #387 = NameAndType        #385:#386     // modPos:(Lorg/sireum/Z;Lorg/sireum/Z;)Lorg/sireum/Z;
  #388 = Methodref          #375.#387     // org/sireum/ContractUtil$.modPos:(Lorg/sireum/Z;Lorg/sireum/Z;)Lorg/sireum/Z;
  #389 = NameAndType        #140:#133     // rear_$eq:(Lorg/sireum/Z;)Lorg/sireum/CircularQueue$DropFront;
  #390 = Methodref          #2.#389       // org/sireum/CircularQueue$DropFront.rear_$eq:(Lorg/sireum/Z;)Lorg/sireum/CircularQueue$DropFront;
  #391 = NameAndType        #146:#133     // numOfElements_$eq:(Lorg/sireum/Z;)Lorg/sireum/CircularQueue$DropFront;
  #392 = Methodref          #2.#391       // org/sireum/CircularQueue$DropFront.numOfElements_$eq:(Lorg/sireum/Z;)Lorg/sireum/CircularQueue$DropFront;
  #393 = NameAndType        #210:#298     // apply:(Ljava/lang/Object;)Ljava/lang/Object;
  #394 = Methodref          #231.#393     // org/sireum/MS.apply:(Ljava/lang/Object;)Ljava/lang/Object;
  #395 = NameAndType        #132:#133     // front_$eq:(Lorg/sireum/Z;)Lorg/sireum/CircularQueue$DropFront;
  #396 = Methodref          #2.#395       // org/sireum/CircularQueue$DropFront.front_$eq:(Lorg/sireum/Z;)Lorg/sireum/CircularQueue$DropFront;
  #397 = Utf8               $minus
  #398 = NameAndType        #397:#380     // $minus:(Lorg/sireum/Z;)Lorg/sireum/Z;
  #399 = InterfaceMethodref #229.#398     // org/sireum/Z.$minus:(Lorg/sireum/Z;)Lorg/sireum/Z;
  #400 = Utf8               elements
  #401 = Utf8               MSZ
  #402 = Utf8               ()Lorg/sireum/$internal/PackageTrait$MSZ$;
  #403 = NameAndType        #401:#402     // MSZ:()Lorg/sireum/$internal/PackageTrait$MSZ$;
  #404 = Methodref          #307.#403     // org/sireum/package$.MSZ:()Lorg/sireum/$internal/PackageTrait$MSZ$;
  #405 = Utf8               create
  #406 = Utf8               (Lorg/sireum/Z;Ljava/lang/Object;)Lorg/sireum/MS;
  #407 = NameAndType        #405:#406     // create:(Lorg/sireum/Z;Ljava/lang/Object;)Lorg/sireum/MS;
  #408 = Methodref          #15.#407      // org/sireum/$internal/PackageTrait$MSZ$.create:(Lorg/sireum/Z;Ljava/lang/Object;)Lorg/sireum/MS;
  #409 = Utf8               until
  #410 = Utf8               (Lorg/sireum/ZLike;)Lorg/sireum/ZRange;
  #411 = NameAndType        #409:#410     // until:(Lorg/sireum/ZLike;)Lorg/sireum/ZRange;
  #412 = InterfaceMethodref #229.#411     // org/sireum/Z.until:(Lorg/sireum/ZLike;)Lorg/sireum/ZRange;
  #413 = MethodType         #298          //  (Ljava/lang/Object;)Ljava/lang/Object;
  #414 = Utf8               $anonfun$elements$2$adapted
  #415 = Utf8               (Lorg/sireum/CircularQueue$DropFront;Lorg/sireum/MS;Lorg/sireum/Z;)Ljava/lang/Object;
  #416 = NameAndType        #414:#415     // $anonfun$elements$2$adapted:(Lorg/sireum/CircularQueue$DropFront;Lorg/sireum/MS;Lorg/sireum/Z;)Ljava/lang/Object;
  #417 = Methodref          #2.#416       // org/sireum/CircularQueue$DropFront.$anonfun$elements$2$adapted:(Lorg/sireum/CircularQueue$DropFront;Lorg/sireum/MS;Lorg/sireum/Z;)Ljava/lang/Object;
  #418 = MethodHandle       6:#417        // REF_invokeStatic org/sireum/CircularQueue$DropFront.$anonfun$elements$2$adapted:(Lorg/sireum/CircularQueue$DropFront;Lorg/sireum/MS;Lorg/sireum/Z;)Ljava/lang/Object;
  #419 = Utf8               (Lorg/sireum/Z;)Ljava/lang/Object;
  #420 = MethodType         #419          //  (Lorg/sireum/Z;)Ljava/lang/Object;
  #421 = Integer            5
  #422 = Integer            1
  #423 = Utf8               java/lang/invoke/LambdaMetafactory
  #424 = Class              #423          // java/lang/invoke/LambdaMetafactory
  #425 = Utf8               altMetafactory
  #426 = Utf8               (Ljava/lang/invoke/MethodHandles$Lookup;Ljava/lang/String;Ljava/lang/invoke/MethodType;[Ljava/lang/Object;)Ljava/lang/invoke/CallSite;
  #427 = NameAndType        #425:#426     // altMetafactory:(Ljava/lang/invoke/MethodHandles$Lookup;Ljava/lang/String;Ljava/lang/invoke/MethodType;[Ljava/lang/Object;)Ljava/lang/invoke/CallSite;
  #428 = Methodref          #424.#427     // java/lang/invoke/LambdaMetafactory.altMetafactory:(Ljava/lang/invoke/MethodHandles$Lookup;Ljava/lang/String;Ljava/lang/invoke/MethodType;[Ljava/lang/Object;)Ljava/lang/invoke/CallSite;
  #429 = MethodHandle       6:#428        // REF_invokeStatic java/lang/invoke/LambdaMetafactory.altMetafactory:(Ljava/lang/invoke/MethodHandles$Lookup;Ljava/lang/String;Ljava/lang/invoke/MethodType;[Ljava/lang/Object;)Ljava/lang/invoke/CallSite;
  #430 = Utf8               (Lorg/sireum/CircularQueue$DropFront;Lorg/sireum/MS;)Lscala/Function1;
  #431 = NameAndType        #210:#430     // apply:(Lorg/sireum/CircularQueue$DropFront;Lorg/sireum/MS;)Lscala/Function1;
  #432 = InvokeDynamic      #0:#431       // #0:apply:(Lorg/sireum/CircularQueue$DropFront;Lorg/sireum/MS;)Lscala/Function1;
  #433 = Utf8               org/sireum/ZRange
  #434 = Class              #433          // org/sireum/ZRange
  #435 = Utf8               foreach
  #436 = Utf8               (Lscala/Function1;)V
  #437 = NameAndType        #435:#436     // foreach:(Lscala/Function1;)V
  #438 = Methodref          #434.#437     // org/sireum/ZRange.foreach:(Lscala/Function1;)V
  #439 = Utf8               retMut
  #440 = NameAndType        #439:#240     // retMut:(Lorg/sireum/$internal/MutableMarker;)Ljava/lang/Object;
  #441 = Methodref          #235.#440     // org/sireum/helper$.retMut:(Lorg/sireum/$internal/MutableMarker;)Ljava/lang/Object;
  #442 = Utf8               (Z)Lorg/sireum/$internal/MutableMarker;
  #443 = NameAndType        #68:#69       // $owned_$eq:(Z)Lorg/sireum/RecordSig;
  #444 = Methodref          #2.#443       // org/sireum/CircularQueue$DropFront.$owned_$eq:(Z)Lorg/sireum/RecordSig;
  #445 = NameAndType        #294:#295     // $clone:()Lorg/sireum/CircularQueue$DropFront;
  #446 = Methodref          #2.#445       // org/sireum/CircularQueue$DropFront.$clone:()Lorg/sireum/CircularQueue$DropFront;
  #447 = Utf8               ()Lorg/sireum/$internal/MutableMarker;
  #448 = Utf8               $anonfun$elements$2
  #449 = Utf8               (Lorg/sireum/CircularQueue$DropFront;Lorg/sireum/MS;Lorg/sireum/Z;)V
  #450 = Utf8               $this
  #451 = Utf8               r$2
  #452 = Utf8               i
  #453 = Utf8               (Lorg/sireum/Z;TE;ZLorg/sireum/MS<Lorg/sireum/Z;TE;>;Lorg/sireum/Z;Lorg/sireum/Z;Lorg/sireum/Z;)V
  #454 = Utf8               __max
  #455 = Utf8               __default
  #456 = Utf8               __scrub
  #457 = Utf8               __queue
  #458 = Utf8               __front
  #459 = Utf8               __rear
  #460 = Utf8               __numOfElements
  #461 = Utf8               ()V
  #462 = NameAndType        #193:#461     // "<init>":()V
  #463 = Methodref          #5.#462       // java/lang/Object."<init>":()V
  #464 = Utf8               $init$
  #465 = Utf8               (Lorg/sireum/Mutable;)V
  #466 = NameAndType        #464:#465     // $init$:(Lorg/sireum/Mutable;)V
  #467 = InterfaceMethodref #84.#466      // org/sireum/Mutable.$init$:(Lorg/sireum/Mutable;)V
  #468 = Utf8               (Lorg/sireum/RecordSig;)V
  #469 = NameAndType        #464:#468     // $init$:(Lorg/sireum/RecordSig;)V
  #470 = InterfaceMethodref #63.#469      // org/sireum/RecordSig.$init$:(Lorg/sireum/RecordSig;)V
  #471 = Utf8               (Lorg/sireum/CircularQueue;)V
  #472 = NameAndType        #464:#471     // $init$:(Lorg/sireum/CircularQueue;)V
  #473 = InterfaceMethodref #7.#472       // org/sireum/CircularQueue.$init$:(Lorg/sireum/CircularQueue;)V
  #474 = NameAndType        #448:#449     // $anonfun$elements$2:(Lorg/sireum/CircularQueue$DropFront;Lorg/sireum/MS;Lorg/sireum/Z;)V
  #475 = Methodref          #2.#474       // org/sireum/CircularQueue$DropFront.$anonfun$elements$2:(Lorg/sireum/CircularQueue$DropFront;Lorg/sireum/MS;Lorg/sireum/Z;)V
  #476 = Utf8               $deserializeLambda$
  #477 = Utf8               (Ljava/lang/invoke/SerializedLambda;)Ljava/lang/Object;
  #478 = Utf8               scala/runtime/LambdaDeserialize
  #479 = Class              #478          // scala/runtime/LambdaDeserialize
  #480 = Utf8               bootstrap
  #481 = Utf8               (Ljava/lang/invoke/MethodHandles$Lookup;Ljava/lang/String;Ljava/lang/invoke/MethodType;[Ljava/lang/invoke/MethodHandle;)Ljava/lang/invoke/CallSite;
  #482 = NameAndType        #480:#481     // bootstrap:(Ljava/lang/invoke/MethodHandles$Lookup;Ljava/lang/String;Ljava/lang/invoke/MethodType;[Ljava/lang/invoke/MethodHandle;)Ljava/lang/invoke/CallSite;
  #483 = Methodref          #479.#482     // scala/runtime/LambdaDeserialize.bootstrap:(Ljava/lang/invoke/MethodHandles$Lookup;Ljava/lang/String;Ljava/lang/invoke/MethodType;[Ljava/lang/invoke/MethodHandle;)Ljava/lang/invoke/CallSite;
  #484 = MethodHandle       6:#483        // REF_invokeStatic scala/runtime/LambdaDeserialize.bootstrap:(Ljava/lang/invoke/MethodHandles$Lookup;Ljava/lang/String;Ljava/lang/invoke/MethodType;[Ljava/lang/invoke/MethodHandle;)Ljava/lang/invoke/CallSite;
  #485 = Utf8               lambdaDeserialize
  #486 = NameAndType        #485:#477     // lambdaDeserialize:(Ljava/lang/invoke/SerializedLambda;)Ljava/lang/Object;
  #487 = InvokeDynamic      #1:#486       // #1:lambdaDeserialize:(Ljava/lang/invoke/SerializedLambda;)Ljava/lang/Object;
  #488 = Utf8               Signature
  #489 = Utf8               Code
  #490 = Utf8               LineNumberTable
  #491 = Utf8               LocalVariableTable
  #492 = Utf8               MethodParameters
  #493 = Utf8               StackMapTable
  #494 = Utf8               InnerClasses
  #495 = Utf8               SourceFile
  #496 = Utf8               BootstrapMethods
  #497 = Utf8               ScalaInlineInfo
  #498 = Utf8               Scala
{
  private org.sireum.Z _max;
    descriptor: Lorg/sireum/Z;
    flags: (0x0002) ACC_PRIVATE

  private E _default;
    descriptor: Ljava/lang/Object;
    flags: (0x0002) ACC_PRIVATE
    Signature: #41                          // TE;

  private boolean _scrub;
    descriptor: Z
    flags: (0x0002) ACC_PRIVATE

  private org.sireum.MS<org.sireum.Z, E> _queue;
    descriptor: Lorg/sireum/MS;
    flags: (0x0002) ACC_PRIVATE
    Signature: #46                          // Lorg/sireum/MS<Lorg/sireum/Z;TE;>;

  private org.sireum.Z _front;
    descriptor: Lorg/sireum/Z;
    flags: (0x0002) ACC_PRIVATE

  private org.sireum.Z _rear;
    descriptor: Lorg/sireum/Z;
    flags: (0x0002) ACC_PRIVATE

  private org.sireum.Z _numOfElements;
    descriptor: Lorg/sireum/Z;
    flags: (0x0002) ACC_PRIVATE

  private org.sireum.MS<org.sireum.Z, E> rep;
    descriptor: Lorg/sireum/MS;
    flags: (0x0002) ACC_PRIVATE
    Signature: #46                          // Lorg/sireum/MS<Lorg/sireum/Z;TE;>;

  private boolean org$sireum$RecordSig$$$isOwned;
    descriptor: Z
    flags: (0x0002) ACC_PRIVATE

  public org.sireum.contract$Contract$Invariant repInv();
    descriptor: ()Lorg/sireum/contract$Contract$Invariant;
    flags: (0x0001) ACC_PUBLIC
    Code:
      stack=1, locals=1, args_size=1
         0: aload_0
         1: invokestatic  #57                 // InterfaceMethod org/sireum/CircularQueue.repInv$:(Lorg/sireum/CircularQueue;)Lorg/sireum/contract$Contract$Invariant;
         4: areturn
      LineNumberTable:
        line 262: 0
      LocalVariableTable:
        Start  Length  Slot  Name   Signature
            0       5     0  this   Lorg/sireum/CircularQueue$DropFront;

  public final boolean $owned();
    descriptor: ()Z
    flags: (0x0011) ACC_PUBLIC, ACC_FINAL
    Code:
      stack=1, locals=1, args_size=1
         0: aload_0
         1: invokestatic  #67                 // InterfaceMethod org/sireum/RecordSig.$owned$:(Lorg/sireum/RecordSig;)Z
         4: ireturn
      LineNumberTable:
        line 262: 0
      LocalVariableTable:
        Start  Length  Slot  Name   Signature
            0       5     0  this   Lorg/sireum/CircularQueue$DropFront;

  public final org.sireum.RecordSig $owned_$eq(boolean);
    descriptor: (Z)Lorg/sireum/RecordSig;
    flags: (0x0011) ACC_PUBLIC, ACC_FINAL
    Code:
      stack=2, locals=2, args_size=2
         0: aload_0
         1: iload_1
         2: invokestatic  #74                 // InterfaceMethod org/sireum/RecordSig.$owned_$eq$:(Lorg/sireum/RecordSig;Z)Lorg/sireum/RecordSig;
         5: areturn
      LineNumberTable:
        line 262: 0
      LocalVariableTable:
        Start  Length  Slot  Name   Signature
            0       6     0  this   Lorg/sireum/CircularQueue$DropFront;
            0       6     1     b   Z
    MethodParameters:
      Name                           Flags
      b                              final

  public org.sireum.Z hash();
    descriptor: ()Lorg/sireum/Z;
    flags: (0x0001) ACC_PUBLIC
    Code:
      stack=1, locals=1, args_size=1
         0: aload_0
         1: invokestatic  #80                 // InterfaceMethod org/sireum/RecordSig.hash$:(Lorg/sireum/RecordSig;)Lorg/sireum/Z;
         4: areturn
      LineNumberTable:
        line 262: 0
      LocalVariableTable:
        Start  Length  Slot  Name   Signature
            0       5     0  this   Lorg/sireum/CircularQueue$DropFront;

  public final scala.runtime.Nothing$ $cannotMixImmutableAndMutable();
    descriptor: ()Lscala/runtime/Nothing$;
    flags: (0x0011) ACC_PUBLIC, ACC_FINAL
    Code:
      stack=1, locals=1, args_size=1
         0: aload_0
         1: invokestatic  #88                 // InterfaceMethod org/sireum/Mutable.$cannotMixImmutableAndMutable$:(Lorg/sireum/Mutable;)Lscala/runtime/Nothing$;
         4: areturn
      LineNumberTable:
        line 262: 0
      LocalVariableTable:
        Start  Length  Slot  Name   Signature
            0       5     0  this   Lorg/sireum/CircularQueue$DropFront;

  public boolean $hasEquals();
    descriptor: ()Z
    flags: (0x0001) ACC_PUBLIC
    Code:
      stack=1, locals=1, args_size=1
         0: aload_0
         1: invokestatic  #93                 // InterfaceMethod org/sireum/Mutable.$hasEquals$:(Lorg/sireum/Mutable;)Z
         4: ireturn
      LineNumberTable:
        line 262: 0
      LocalVariableTable:
        Start  Length  Slot  Name   Signature
            0       5     0  this   Lorg/sireum/CircularQueue$DropFront;

  public boolean $hasString();
    descriptor: ()Z
    flags: (0x0001) ACC_PUBLIC
    Code:
      stack=1, locals=1, args_size=1
         0: aload_0
         1: invokestatic  #97                 // InterfaceMethod org/sireum/Mutable.$hasString$:(Lorg/sireum/Mutable;)Z
         4: ireturn
      LineNumberTable:
        line 262: 0
      LocalVariableTable:
        Start  Length  Slot  Name   Signature
            0       5     0  this   Lorg/sireum/CircularQueue$DropFront;

  public org.sireum.MS<org.sireum.Z, E> rep();
    descriptor: ()Lorg/sireum/MS;
    flags: (0x0001) ACC_PUBLIC
    Code:
      stack=1, locals=1, args_size=1
         0: aload_0
         1: getfield      #101                // Field rep:Lorg/sireum/MS;
         4: areturn
      LineNumberTable:
        line 262: 0
      LocalVariableTable:
        Start  Length  Slot  Name   Signature
            0       5     0  this   Lorg/sireum/CircularQueue$DropFront;
    Signature: #99                          // ()Lorg/sireum/MS<Lorg/sireum/Z;TE;>;

  public void rep_$eq(org.sireum.MS<org.sireum.Z, E>);
    descriptor: (Lorg/sireum/MS;)V
    flags: (0x0001) ACC_PUBLIC
    Code:
      stack=2, locals=2, args_size=2
         0: aload_0
         1: aload_1
         2: putfield      #101                // Field rep:Lorg/sireum/MS;
         5: return
      LineNumberTable:
        line 262: 0
      LocalVariableTable:
        Start  Length  Slot  Name   Signature
            0       6     0  this   Lorg/sireum/CircularQueue$DropFront;
            0       6     1   x$1   Lorg/sireum/MS;
    Signature: #104                         // (Lorg/sireum/MS<Lorg/sireum/Z;TE;>;)V
    MethodParameters:
      Name                           Flags
      x$1                            final

  public boolean org$sireum$RecordSig$$$isOwned();
    descriptor: ()Z
    flags: (0x0001) ACC_PUBLIC
    Code:
      stack=1, locals=1, args_size=1
         0: aload_0
         1: getfield      #107                // Field org$sireum$RecordSig$$$isOwned:Z
         4: ireturn
      LineNumberTable:
        line 262: 0
      LocalVariableTable:
        Start  Length  Slot  Name   Signature
            0       5     0  this   Lorg/sireum/CircularQueue$DropFront;

  public void org$sireum$RecordSig$$$isOwned_$eq(boolean);
    descriptor: (Z)V
    flags: (0x0001) ACC_PUBLIC
    Code:
      stack=2, locals=2, args_size=2
         0: aload_0
         1: iload_1
         2: putfield      #107                // Field org$sireum$RecordSig$$$isOwned:Z
         5: return
      LineNumberTable:
        line 262: 0
      LocalVariableTable:
        Start  Length  Slot  Name   Signature
            0       6     0  this   Lorg/sireum/CircularQueue$DropFront;
            0       6     1   x$1   Z
    MethodParameters:
      Name                           Flags
      x$1                            final

  public org.sireum.Z max();
    descriptor: ()Lorg/sireum/Z;
    flags: (0x0001) ACC_PUBLIC
    Code:
      stack=1, locals=1, args_size=1
         0: aload_0
         1: getfield      #112                // Field _max:Lorg/sireum/Z;
         4: areturn
      LineNumberTable:
        line 262: 0
      LocalVariableTable:
        Start  Length  Slot  Name   Signature
            0       5     0  this   Lorg/sireum/CircularQueue$DropFront;

  public org.sireum.Z getMax();
    descriptor: ()Lorg/sireum/Z;
    flags: (0x0001) ACC_PUBLIC
    Code:
      stack=1, locals=1, args_size=1
         0: aload_0
         1: getfield      #112                // Field _max:Lorg/sireum/Z;
         4: areturn
      LineNumberTable:
        line 262: 0
      LocalVariableTable:
        Start  Length  Slot  Name   Signature
            0       5     0  this   Lorg/sireum/CircularQueue$DropFront;

  public E default();
    descriptor: ()Ljava/lang/Object;
    flags: (0x0001) ACC_PUBLIC
    Code:
      stack=1, locals=1, args_size=1
         0: aload_0
         1: getfield      #118                // Field _default:Ljava/lang/Object;
         4: areturn
      LineNumberTable:
        line 262: 0
      LocalVariableTable:
        Start  Length  Slot  Name   Signature
            0       5     0  this   Lorg/sireum/CircularQueue$DropFront;
    Signature: #116                         // ()TE;

  public E getDefault();
    descriptor: ()Ljava/lang/Object;
    flags: (0x0001) ACC_PUBLIC
    Code:
      stack=1, locals=1, args_size=1
         0: aload_0
         1: getfield      #118                // Field _default:Ljava/lang/Object;
         4: areturn
      LineNumberTable:
        line 262: 0
      LocalVariableTable:
        Start  Length  Slot  Name   Signature
            0       5     0  this   Lorg/sireum/CircularQueue$DropFront;
    Signature: #116                         // ()TE;

  public boolean scrub();
    descriptor: ()Z
    flags: (0x0001) ACC_PUBLIC
    Code:
      stack=1, locals=1, args_size=1
         0: aload_0
         1: getfield      #122                // Field _scrub:Z
         4: ireturn
      LineNumberTable:
        line 262: 0
      LocalVariableTable:
        Start  Length  Slot  Name   Signature
            0       5     0  this   Lorg/sireum/CircularQueue$DropFront;

  public boolean getScrub();
    descriptor: ()Z
    flags: (0x0001) ACC_PUBLIC
    Code:
      stack=1, locals=1, args_size=1
         0: aload_0
         1: getfield      #122                // Field _scrub:Z
         4: ireturn
      LineNumberTable:
        line 262: 0
      LocalVariableTable:
        Start  Length  Slot  Name   Signature
            0       5     0  this   Lorg/sireum/CircularQueue$DropFront;

  public org.sireum.MS<org.sireum.Z, E> queue();
    descriptor: ()Lorg/sireum/MS;
    flags: (0x0001) ACC_PUBLIC
    Code:
      stack=1, locals=1, args_size=1
         0: aload_0
         1: getfield      #126                // Field _queue:Lorg/sireum/MS;
         4: areturn
      LineNumberTable:
        line 262: 0
      LocalVariableTable:
        Start  Length  Slot  Name   Signature
            0       5     0  this   Lorg/sireum/CircularQueue$DropFront;
    Signature: #99                          // ()Lorg/sireum/MS<Lorg/sireum/Z;TE;>;

  public org.sireum.MS<org.sireum.Z, E> getQueue();
    descriptor: ()Lorg/sireum/MS;
    flags: (0x0001) ACC_PUBLIC
    Code:
      stack=1, locals=1, args_size=1
         0: aload_0
         1: getfield      #126                // Field _queue:Lorg/sireum/MS;
         4: areturn
      LineNumberTable:
        line 262: 0
      LocalVariableTable:
        Start  Length  Slot  Name   Signature
            0       5     0  this   Lorg/sireum/CircularQueue$DropFront;
    Signature: #99                          // ()Lorg/sireum/MS<Lorg/sireum/Z;TE;>;

  public org.sireum.Z front();
    descriptor: ()Lorg/sireum/Z;
    flags: (0x0001) ACC_PUBLIC
    Code:
      stack=1, locals=1, args_size=1
         0: aload_0
         1: getfield      #130                // Field _front:Lorg/sireum/Z;
         4: areturn
      LineNumberTable:
        line 262: 0
      LocalVariableTable:
        Start  Length  Slot  Name   Signature
            0       5     0  this   Lorg/sireum/CircularQueue$DropFront;

  public org.sireum.Z getFront();
    descriptor: ()Lorg/sireum/Z;
    flags: (0x0001) ACC_PUBLIC
    Code:
      stack=1, locals=1, args_size=1
         0: aload_0
         1: getfield      #130                // Field _front:Lorg/sireum/Z;
         4: areturn
      LineNumberTable:
        line 262: 0
      LocalVariableTable:
        Start  Length  Slot  Name   Signature
            0       5     0  this   Lorg/sireum/CircularQueue$DropFront;

  public org.sireum.CircularQueue$DropFront<E> front_$eq(org.sireum.Z);
    descriptor: (Lorg/sireum/Z;)Lorg/sireum/CircularQueue$DropFront;
    flags: (0x0001) ACC_PUBLIC
    Code:
      stack=2, locals=2, args_size=2
         0: aload_0
         1: aload_1
         2: putfield      #130                // Field _front:Lorg/sireum/Z;
         5: aload_0
         6: areturn
      LineNumberTable:
        line 262: 0
      LocalVariableTable:
        Start  Length  Slot  Name   Signature
            0       7     0  this   Lorg/sireum/CircularQueue$DropFront;
            0       7     1 front   Lorg/sireum/Z;
    Signature: #134                         // (Lorg/sireum/Z;)Lorg/sireum/CircularQueue$DropFront<TE;>;
    MethodParameters:
      Name                           Flags
      front                          final

  public org.sireum.CircularQueue$DropFront<E> setFront(org.sireum.Z);
    descriptor: (Lorg/sireum/Z;)Lorg/sireum/CircularQueue$DropFront;
    flags: (0x0001) ACC_PUBLIC
    Code:
      stack=2, locals=2, args_size=2
         0: aload_0
         1: aload_1
         2: putfield      #130                // Field _front:Lorg/sireum/Z;
         5: aload_0
         6: areturn
      LineNumberTable:
        line 262: 0
      LocalVariableTable:
        Start  Length  Slot  Name   Signature
            0       7     0  this   Lorg/sireum/CircularQueue$DropFront;
            0       7     1 front   Lorg/sireum/Z;
    Signature: #134                         // (Lorg/sireum/Z;)Lorg/sireum/CircularQueue$DropFront<TE;>;
    MethodParameters:
      Name                           Flags
      front                          final

  public org.sireum.Z rear();
    descriptor: ()Lorg/sireum/Z;
    flags: (0x0001) ACC_PUBLIC
    Code:
      stack=1, locals=1, args_size=1
         0: aload_0
         1: getfield      #138                // Field _rear:Lorg/sireum/Z;
         4: areturn
      LineNumberTable:
        line 262: 0
      LocalVariableTable:
        Start  Length  Slot  Name   Signature
            0       5     0  this   Lorg/sireum/CircularQueue$DropFront;

  public org.sireum.Z getRear();
    descriptor: ()Lorg/sireum/Z;
    flags: (0x0001) ACC_PUBLIC
    Code:
      stack=1, locals=1, args_size=1
         0: aload_0
         1: getfield      #138                // Field _rear:Lorg/sireum/Z;
         4: areturn
      LineNumberTable:
        line 262: 0
      LocalVariableTable:
        Start  Length  Slot  Name   Signature
            0       5     0  this   Lorg/sireum/CircularQueue$DropFront;

  public org.sireum.CircularQueue$DropFront<E> rear_$eq(org.sireum.Z);
    descriptor: (Lorg/sireum/Z;)Lorg/sireum/CircularQueue$DropFront;
    flags: (0x0001) ACC_PUBLIC
    Code:
      stack=2, locals=2, args_size=2
         0: aload_0
         1: aload_1
         2: putfield      #138                // Field _rear:Lorg/sireum/Z;
         5: aload_0
         6: areturn
      LineNumberTable:
        line 262: 0
      LocalVariableTable:
        Start  Length  Slot  Name   Signature
            0       7     0  this   Lorg/sireum/CircularQueue$DropFront;
            0       7     1  rear   Lorg/sireum/Z;
    Signature: #134                         // (Lorg/sireum/Z;)Lorg/sireum/CircularQueue$DropFront<TE;>;
    MethodParameters:
      Name                           Flags
      rear                           final

  public org.sireum.CircularQueue$DropFront<E> setRear(org.sireum.Z);
    descriptor: (Lorg/sireum/Z;)Lorg/sireum/CircularQueue$DropFront;
    flags: (0x0001) ACC_PUBLIC
    Code:
      stack=2, locals=2, args_size=2
         0: aload_0
         1: aload_1
         2: putfield      #138                // Field _rear:Lorg/sireum/Z;
         5: aload_0
         6: areturn
      LineNumberTable:
        line 262: 0
      LocalVariableTable:
        Start  Length  Slot  Name   Signature
            0       7     0  this   Lorg/sireum/CircularQueue$DropFront;
            0       7     1  rear   Lorg/sireum/Z;
    Signature: #134                         // (Lorg/sireum/Z;)Lorg/sireum/CircularQueue$DropFront<TE;>;
    MethodParameters:
      Name                           Flags
      rear                           final

  public org.sireum.Z numOfElements();
    descriptor: ()Lorg/sireum/Z;
    flags: (0x0001) ACC_PUBLIC
    Code:
      stack=1, locals=1, args_size=1
         0: aload_0
         1: getfield      #144                // Field _numOfElements:Lorg/sireum/Z;
         4: areturn
      LineNumberTable:
        line 262: 0
      LocalVariableTable:
        Start  Length  Slot  Name   Signature
            0       5     0  this   Lorg/sireum/CircularQueue$DropFront;

  public org.sireum.Z getNumOfElements();
    descriptor: ()Lorg/sireum/Z;
    flags: (0x0001) ACC_PUBLIC
    Code:
      stack=1, locals=1, args_size=1
         0: aload_0
         1: getfield      #144                // Field _numOfElements:Lorg/sireum/Z;
         4: areturn
      LineNumberTable:
        line 262: 0
      LocalVariableTable:
        Start  Length  Slot  Name   Signature
            0       5     0  this   Lorg/sireum/CircularQueue$DropFront;

  public org.sireum.CircularQueue$DropFront<E> numOfElements_$eq(org.sireum.Z);
    descriptor: (Lorg/sireum/Z;)Lorg/sireum/CircularQueue$DropFront;
    flags: (0x0001) ACC_PUBLIC
    Code:
      stack=2, locals=2, args_size=2
         0: aload_0
         1: aload_1
         2: putfield      #144                // Field _numOfElements:Lorg/sireum/Z;
         5: aload_0
         6: areturn
      LineNumberTable:
        line 262: 0
      LocalVariableTable:
        Start  Length  Slot  Name   Signature
            0       7     0  this   Lorg/sireum/CircularQueue$DropFront;
            0       7     1 numOfElements   Lorg/sireum/Z;
    Signature: #134                         // (Lorg/sireum/Z;)Lorg/sireum/CircularQueue$DropFront<TE;>;
    MethodParameters:
      Name                           Flags
      numOfElements                  final

  public org.sireum.CircularQueue$DropFront<E> setNumOfElements(org.sireum.Z);
    descriptor: (Lorg/sireum/Z;)Lorg/sireum/CircularQueue$DropFront;
    flags: (0x0001) ACC_PUBLIC
    Code:
      stack=2, locals=2, args_size=2
         0: aload_0
         1: aload_1
         2: putfield      #144                // Field _numOfElements:Lorg/sireum/Z;
         5: aload_0
         6: areturn
      LineNumberTable:
        line 262: 0
      LocalVariableTable:
        Start  Length  Slot  Name   Signature
            0       7     0  this   Lorg/sireum/CircularQueue$DropFront;
            0       7     1 numOfElements   Lorg/sireum/Z;
    Signature: #134                         // (Lorg/sireum/Z;)Lorg/sireum/CircularQueue$DropFront<TE;>;
    MethodParameters:
      Name                           Flags
      numOfElements                  final

  public java.lang.String toString();
    descriptor: ()Ljava/lang/String;
    flags: (0x0001) ACC_PUBLIC
    Code:
      stack=1, locals=1, args_size=1
         0: aload_0
         1: invokestatic  #153                // InterfaceMethod org/sireum/CircularQueue.string$:(Lorg/sireum/CircularQueue;)Ljava/lang/String;
         4: areturn
      LineNumberTable:
        line 262: 0
      LocalVariableTable:
        Start  Length  Slot  Name   Signature
            0       5     0  this   Lorg/sireum/CircularQueue$DropFront;

  public java.lang.String string();
    descriptor: ()Ljava/lang/String;
    flags: (0x0001) ACC_PUBLIC
    Code:
      stack=1, locals=1, args_size=1
         0: aload_0
         1: invokestatic  #153                // InterfaceMethod org/sireum/CircularQueue.string$:(Lorg/sireum/CircularQueue;)Ljava/lang/String;
         4: areturn
      LineNumberTable:
        line 262: 0
      LocalVariableTable:
        Start  Length  Slot  Name   Signature
            0       5     0  this   Lorg/sireum/CircularQueue$DropFront;

  public int hashCode();
    descriptor: ()I
    flags: (0x0001) ACC_PUBLIC
    Code:
      stack=8, locals=1, args_size=1
         0: aload_0
         1: invokevirtual #158                // Method $hasEquals:()Z
         4: ifeq          14
         7: aload_0
         8: invokespecial #160                // Method java/lang/Object.hashCode:()I
        11: goto          110
        14: getstatic     #166                // Field scala/package$.MODULE$:Lscala/package$;
        17: invokevirtual #170                // Method scala/package$.Seq:()Lscala/collection/immutable/Seq$;
        20: getstatic     #175                // Field scala/runtime/ScalaRunTime$.MODULE$:Lscala/runtime/ScalaRunTime$;
        23: bipush        8
        25: anewarray     #5                  // class java/lang/Object
        28: dup
        29: iconst_0
        30: aload_0
        31: invokevirtual #179                // Method getClass:()Ljava/lang/Class;
        34: invokevirtual #184                // Method java/lang/Class.getName:()Ljava/lang/String;
        37: aastore
        38: dup
        39: iconst_1
        40: aload_0
        41: invokevirtual #186                // Method max:()Lorg/sireum/Z;
        44: aastore
        45: dup
        46: iconst_2
        47: aload_0
        48: invokevirtual #188                // Method default:()Ljava/lang/Object;
        51: aastore
        52: dup
        53: iconst_3
        54: new           #190                // class org/sireum/B
        57: dup
        58: aload_0
        59: invokevirtual #192                // Method scrub:()Z
        62: invokespecial #195                // Method org/sireum/B."<init>":(Z)V
        65: aastore
        66: dup
        67: iconst_4
        68: aload_0
        69: invokevirtual #197                // Method queue:()Lorg/sireum/MS;
        72: aastore
        73: dup
        74: iconst_5
        75: aload_0
        76: invokevirtual #199                // Method front:()Lorg/sireum/Z;
        79: aastore
        80: dup
        81: bipush        6
        83: aload_0
        84: invokevirtual #201                // Method rear:()Lorg/sireum/Z;
        87: aastore
        88: dup
        89: bipush        7
        91: aload_0
        92: invokevirtual #203                // Method numOfElements:()Lorg/sireum/Z;
        95: aastore
        96: invokevirtual #207                // Method scala/runtime/ScalaRunTime$.genericWrapArray:(Ljava/lang/Object;)Lscala/collection/immutable/ArraySeq;
        99: invokevirtual #213                // Method scala/collection/immutable/Seq$.apply:(Lscala/collection/immutable/Seq;)Lscala/collection/SeqOps;
       102: checkcast     #215                // class scala/collection/Seq
       105: invokeinterface #216,  1          // InterfaceMethod scala/collection/Seq.hashCode:()I
       110: ireturn
      StackMapTable: number_of_entries = 2
        frame_type = 14 /* same */
        frame_type = 247 /* same_locals_1_stack_item_frame_extended */
          offset_delta = 95
          stack = [ int ]
      LineNumberTable:
        line 262: 0
      LocalVariableTable:
        Start  Length  Slot  Name   Signature
            0     111     0  this   Lorg/sireum/CircularQueue$DropFront;

  public boolean equals(java.lang.Object);
    descriptor: (Ljava/lang/Object;)Z
    flags: (0x0001) ACC_PUBLIC
    Code:
      stack=2, locals=10, args_size=2
         0: aload_0
         1: invokevirtual #158                // Method $hasEquals:()Z
         4: ifeq          15
         7: aload_0
         8: aload_1
         9: invokespecial #221                // Method java/lang/Object.equals:(Ljava/lang/Object;)Z
        12: goto          260
        15: aload_0
        16: aload_1
        17: if_acmpne     24
        20: iconst_1
        21: goto          260
        24: aload_1
        25: astore_3
        26: aload_3
        27: instanceof    #2                  // class org/sireum/CircularQueue$DropFront
        30: ifeq          251
        33: aload_3
        34: checkcast     #2                  // class org/sireum/CircularQueue$DropFront
        37: astore        4
        39: aload_0
        40: invokevirtual #222                // Method hashCode:()I
        43: aload         4
        45: invokevirtual #222                // Method hashCode:()I
        48: if_icmpeq     55
        51: iconst_0
        52: goto          247
        55: aload_0
        56: invokevirtual #186                // Method max:()Lorg/sireum/Z;
        59: aload         4
        61: invokevirtual #186                // Method max:()Lorg/sireum/Z;
        64: astore        5
        66: dup
        67: ifnonnull     79
        70: pop
        71: aload         5
        73: ifnull        87
        76: goto          246
        79: aload         5
        81: invokevirtual #221                // Method java/lang/Object.equals:(Ljava/lang/Object;)Z
        84: ifeq          246
        87: aload_0
        88: invokevirtual #188                // Method default:()Ljava/lang/Object;
        91: aload         4
        93: invokevirtual #188                // Method default:()Ljava/lang/Object;
        96: invokestatic  #227                // Method scala/runtime/BoxesRunTime.equals:(Ljava/lang/Object;Ljava/lang/Object;)Z
        99: ifeq          246
       102: aload_0
       103: invokevirtual #192                // Method scrub:()Z
       106: aload         4
       108: invokevirtual #192                // Method scrub:()Z
       111: if_icmpne     246
       114: aload_0
       115: invokevirtual #197                // Method queue:()Lorg/sireum/MS;
       118: aload         4
       120: invokevirtual #197                // Method queue:()Lorg/sireum/MS;
       123: astore        6
       125: dup
       126: ifnonnull     138
       129: pop
       130: aload         6
       132: ifnull        146
       135: goto          246
       138: aload         6
       140: invokevirtual #221                // Method java/lang/Object.equals:(Ljava/lang/Object;)Z
       143: ifeq          246
       146: aload_0
       147: invokevirtual #199                // Method front:()Lorg/sireum/Z;
       150: aload         4
       152: invokevirtual #199                // Method front:()Lorg/sireum/Z;
       155: astore        7
       157: dup
       158: ifnonnull     170
       161: pop
       162: aload         7
       164: ifnull        178
       167: goto          246
       170: aload         7
       172: invokevirtual #221                // Method java/lang/Object.equals:(Ljava/lang/Object;)Z
       175: ifeq          246
       178: aload_0
       179: invokevirtual #201                // Method rear:()Lorg/sireum/Z;
       182: aload         4
       184: invokevirtual #201                // Method rear:()Lorg/sireum/Z;
       187: astore        8
       189: dup
       190: ifnonnull     202
       193: pop
       194: aload         8
       196: ifnull        210
       199: goto          246
       202: aload         8
       204: invokevirtual #221                // Method java/lang/Object.equals:(Ljava/lang/Object;)Z
       207: ifeq          246
       210: aload_0
       211: invokevirtual #203                // Method numOfElements:()Lorg/sireum/Z;
       214: aload         4
       216: invokevirtual #203                // Method numOfElements:()Lorg/sireum/Z;
       219: astore        9
       221: dup
       222: ifnonnull     234
       225: pop
       226: aload         9
       228: ifnull        242
       231: goto          246
       234: aload         9
       236: invokevirtual #221                // Method java/lang/Object.equals:(Ljava/lang/Object;)Z
       239: ifeq          246
       242: iconst_1
       243: goto          247
       246: iconst_0
       247: istore_2
       248: goto          259
       251: goto          254
       254: iconst_0
       255: istore_2
       256: goto          259
       259: iload_2
       260: ireturn
      StackMapTable: number_of_entries = 19
        frame_type = 15 /* same */
        frame_type = 8 /* same */
        frame_type = 254 /* append */
          offset_delta = 30
          locals = [ top, class java/lang/Object, class org/sireum/CircularQueue$DropFront ]
        frame_type = 255 /* full_frame */
          offset_delta = 23
          locals = [ class org/sireum/CircularQueue$DropFront, class java/lang/Object, top, class java/lang/Object, class org/sireum/CircularQueue$DropFront, class org/sireum/Z ]
          stack = [ class org/sireum/Z ]
        frame_type = 7 /* same */
        frame_type = 255 /* full_frame */
          offset_delta = 50
          locals = [ class org/sireum/CircularQueue$DropFront, class java/lang/Object, top, class java/lang/Object, class org/sireum/CircularQueue$DropFront, class org/sireum/Z, class org/sireum/MS ]
          stack = [ class org/sireum/MS ]
        frame_type = 7 /* same */
        frame_type = 255 /* full_frame */
          offset_delta = 23
          locals = [ class org/sireum/CircularQueue$DropFront, class java/lang/Object, top, class java/lang/Object, class org/sireum/CircularQueue$DropFront, class org/sireum/Z, class org/sireum/MS, class org/sireum/Z ]
          stack = [ class org/sireum/Z ]
        frame_type = 7 /* same */
        frame_type = 255 /* full_frame */
          offset_delta = 23
          locals = [ class org/sireum/CircularQueue$DropFront, class java/lang/Object, top, class java/lang/Object, class org/sireum/CircularQueue$DropFront, class org/sireum/Z, class org/sireum/MS, class org/sireum/Z, class org/sireum/Z ]
          stack = [ class org/sireum/Z ]
        frame_type = 7 /* same */
        frame_type = 255 /* full_frame */
          offset_delta = 23
          locals = [ class org/sireum/CircularQueue$DropFront, class java/lang/Object, top, class java/lang/Object, class org/sireum/CircularQueue$DropFront, class org/sireum/Z, class org/sireum/MS, class org/sireum/Z, class org/sireum/Z, class org/sireum/Z ]
          stack = [ class org/sireum/Z ]
        frame_type = 7 /* same */
        frame_type = 255 /* full_frame */
          offset_delta = 3
          locals = [ class org/sireum/CircularQueue$DropFront, class java/lang/Object, top, class java/lang/Object, class org/sireum/CircularQueue$DropFront, class org/sireum/Z ]
          stack = []
        frame_type = 255 /* full_frame */
          offset_delta = 0
          locals = [ class org/sireum/CircularQueue$DropFront, class java/lang/Object, top, class java/lang/Object, class org/sireum/CircularQueue$DropFront ]
          stack = [ int ]
        frame_type = 250 /* chop */
          offset_delta = 3
        frame_type = 2 /* same */
        frame_type = 255 /* full_frame */
          offset_delta = 4
          locals = [ class org/sireum/CircularQueue$DropFront, class java/lang/Object, int, class java/lang/Object ]
          stack = []
        frame_type = 255 /* full_frame */
          offset_delta = 0
          locals = [ class org/sireum/CircularQueue$DropFront, class java/lang/Object ]
          stack = [ int ]
      LineNumberTable:
        line 262: 0
      LocalVariableTable:
        Start  Length  Slot  Name   Signature
            0     261     0  this   Lorg/sireum/CircularQueue$DropFront;
            0     261     1     o   Ljava/lang/Object;
    MethodParameters:
      Name                           Flags
      o                              final

  public org.sireum.CircularQueue$DropFront<E> apply(org.sireum.Z, E, boolean, org.sireum.MS<org.sireum.Z, E>, org.sireum.Z, org.sireum.Z, org.sireum.Z);
    descriptor: (Lorg/sireum/Z;Ljava/lang/Object;ZLorg/sireum/MS;Lorg/sireum/Z;Lorg/sireum/Z;Lorg/sireum/Z;)Lorg/sireum/CircularQueue$DropFront;
    flags: (0x0001) ACC_PUBLIC
    Code:
      stack=9, locals=8, args_size=8
         0: new           #2                  // class org/sireum/CircularQueue$DropFront
         3: dup
         4: aload_1
         5: aload_2
         6: iload_3
         7: getstatic     #238                // Field org/sireum/helper$.MODULE$:Lorg/sireum/helper$;
        10: aload         4
        12: invokevirtual #242                // Method org/sireum/helper$.assignMut:(Lorg/sireum/$internal/MutableMarker;)Ljava/lang/Object;
        15: checkcast     #231                // class org/sireum/MS
        18: aload         5
        20: aload         6
        22: aload         7
        24: invokespecial #245                // Method "<init>":(Lorg/sireum/Z;Ljava/lang/Object;ZLorg/sireum/MS;Lorg/sireum/Z;Lorg/sireum/Z;Lorg/sireum/Z;)V
        27: areturn
      LineNumberTable:
        line 262: 0
      LocalVariableTable:
        Start  Length  Slot  Name   Signature
            0      28     0  this   Lorg/sireum/CircularQueue$DropFront;
            0      28     1   max   Lorg/sireum/Z;
            0      28     2 default   Ljava/lang/Object;
            0      28     3 scrub   Z
            0      28     4 queue   Lorg/sireum/MS;
            0      28     5 front   Lorg/sireum/Z;
            0      28     6  rear   Lorg/sireum/Z;
            0      28     7 numOfElements   Lorg/sireum/Z;
    Signature: #233                         // (Lorg/sireum/Z;TE;ZLorg/sireum/MS<Lorg/sireum/Z;TE;>;Lorg/sireum/Z;Lorg/sireum/Z;Lorg/sireum/Z;)Lorg/sireum/CircularQueue$DropFront<TE;>;
    MethodParameters:
      Name                           Flags
      max                            final
      default                        final
      scrub                          final
      queue                          final
      front                          final
      rear                           final
      numOfElements                  final

  public org.sireum.Z apply$default$1();
    descriptor: ()Lorg/sireum/Z;
    flags: (0x0001) ACC_PUBLIC
    Code:
      stack=1, locals=1, args_size=1
         0: aload_0
         1: invokevirtual #186                // Method max:()Lorg/sireum/Z;
         4: areturn
      LineNumberTable:
        line 262: 0
      LocalVariableTable:
        Start  Length  Slot  Name   Signature
            0       5     0  this   Lorg/sireum/CircularQueue$DropFront;

  public E apply$default$2();
    descriptor: ()Ljava/lang/Object;
    flags: (0x0001) ACC_PUBLIC
    Code:
      stack=1, locals=1, args_size=1
         0: aload_0
         1: invokevirtual #188                // Method default:()Ljava/lang/Object;
         4: areturn
      LineNumberTable:
        line 262: 0
      LocalVariableTable:
        Start  Length  Slot  Name   Signature
            0       5     0  this   Lorg/sireum/CircularQueue$DropFront;
    Signature: #116                         // ()TE;

  public boolean apply$default$3();
    descriptor: ()Z
    flags: (0x0001) ACC_PUBLIC
    Code:
      stack=1, locals=1, args_size=1
         0: aload_0
         1: invokevirtual #192                // Method scrub:()Z
         4: ireturn
      LineNumberTable:
        line 262: 0
      LocalVariableTable:
        Start  Length  Slot  Name   Signature
            0       5     0  this   Lorg/sireum/CircularQueue$DropFront;

  public org.sireum.MS<org.sireum.Z, E> apply$default$4();
    descriptor: ()Lorg/sireum/MS;
    flags: (0x0001) ACC_PUBLIC
    Code:
      stack=1, locals=1, args_size=1
         0: aload_0
         1: invokevirtual #197                // Method queue:()Lorg/sireum/MS;
         4: areturn
      LineNumberTable:
        line 262: 0
      LocalVariableTable:
        Start  Length  Slot  Name   Signature
            0       5     0  this   Lorg/sireum/CircularQueue$DropFront;
    Signature: #99                          // ()Lorg/sireum/MS<Lorg/sireum/Z;TE;>;

  public org.sireum.Z apply$default$5();
    descriptor: ()Lorg/sireum/Z;
    flags: (0x0001) ACC_PUBLIC
    Code:
      stack=1, locals=1, args_size=1
         0: aload_0
         1: invokevirtual #199                // Method front:()Lorg/sireum/Z;
         4: areturn
      LineNumberTable:
        line 262: 0
      LocalVariableTable:
        Start  Length  Slot  Name   Signature
            0       5     0  this   Lorg/sireum/CircularQueue$DropFront;

  public org.sireum.Z apply$default$6();
    descriptor: ()Lorg/sireum/Z;
    flags: (0x0001) ACC_PUBLIC
    Code:
      stack=1, locals=1, args_size=1
         0: aload_0
         1: invokevirtual #201                // Method rear:()Lorg/sireum/Z;
         4: areturn
      LineNumberTable:
        line 262: 0
      LocalVariableTable:
        Start  Length  Slot  Name   Signature
            0       5     0  this   Lorg/sireum/CircularQueue$DropFront;

  public org.sireum.Z apply$default$7();
    descriptor: ()Lorg/sireum/Z;
    flags: (0x0001) ACC_PUBLIC
    Code:
      stack=1, locals=1, args_size=1
         0: aload_0
         1: invokevirtual #203                // Method numOfElements:()Lorg/sireum/Z;
         4: areturn
      LineNumberTable:
        line 262: 0
      LocalVariableTable:
        Start  Length  Slot  Name   Signature
            0       5     0  this   Lorg/sireum/CircularQueue$DropFront;

  public scala.collection.immutable.Seq<scala.Tuple2<java.lang.String, java.lang.Object>> $content();
    descriptor: ()Lscala/collection/immutable/Seq;
    flags: (0x0001) ACC_PUBLIC
    Code:
      stack=14, locals=1, args_size=1
         0: getstatic     #166                // Field scala/package$.MODULE$:Lscala/package$;
         3: invokevirtual #170                // Method scala/package$.Seq:()Lscala/collection/immutable/Seq$;
         6: getstatic     #175                // Field scala/runtime/ScalaRunTime$.MODULE$:Lscala/runtime/ScalaRunTime$;
         9: bipush        8
        11: anewarray     #257                // class scala/Tuple2
        14: dup
        15: iconst_0
        16: new           #257                // class scala/Tuple2
        19: dup
        20: ldc_w         #259                // String type
        23: getstatic     #166                // Field scala/package$.MODULE$:Lscala/package$;
        26: invokevirtual #263                // Method scala/package$.List:()Lscala/collection/immutable/List$;
        29: getstatic     #175                // Field scala/runtime/ScalaRunTime$.MODULE$:Lscala/runtime/ScalaRunTime$;
        32: iconst_3
        33: anewarray     #265                // class java/lang/String
        36: dup
        37: iconst_0
        38: ldc_w         #267                // String org
        41: aastore
        42: dup
        43: iconst_1
        44: ldc_w         #269                // String sireum
        47: aastore
        48: dup
        49: iconst_2
        50: ldc_w         #270                // String DropFront
        53: aastore
        54: checkcast     #272                // class "[Ljava/lang/Object;"
        57: invokevirtual #276                // Method scala/runtime/ScalaRunTime$.wrapRefArray:([Ljava/lang/Object;)Lscala/collection/immutable/ArraySeq;
        60: invokevirtual #281                // Method scala/collection/immutable/List$.apply:(Lscala/collection/immutable/Seq;)Ljava/lang/Object;
        63: invokespecial #284                // Method scala/Tuple2."<init>":(Ljava/lang/Object;Ljava/lang/Object;)V
        66: aastore
        67: dup
        68: iconst_1
        69: new           #257                // class scala/Tuple2
        72: dup
        73: ldc_w         #285                // String max
        76: aload_0
        77: invokevirtual #186                // Method max:()Lorg/sireum/Z;
        80: invokespecial #284                // Method scala/Tuple2."<init>":(Ljava/lang/Object;Ljava/lang/Object;)V
        83: aastore
        84: dup
        85: iconst_2
        86: new           #257                // class scala/Tuple2
        89: dup
        90: ldc_w         #286                // String default
        93: aload_0
        94: invokevirtual #188                // Method default:()Ljava/lang/Object;
        97: invokespecial #284                // Method scala/Tuple2."<init>":(Ljava/lang/Object;Ljava/lang/Object;)V
       100: aastore
       101: dup
       102: iconst_3
       103: new           #257                // class scala/Tuple2
       106: dup
       107: ldc_w         #287                // String scrub
       110: new           #190                // class org/sireum/B
       113: dup
       114: aload_0
       115: invokevirtual #192                // Method scrub:()Z
       118: invokespecial #195                // Method org/sireum/B."<init>":(Z)V
       121: invokespecial #284                // Method scala/Tuple2."<init>":(Ljava/lang/Object;Ljava/lang/Object;)V
       124: aastore
       125: dup
       126: iconst_4
       127: new           #257                // class scala/Tuple2
       130: dup
       131: ldc_w         #288                // String queue
       134: aload_0
       135: invokevirtual #197                // Method queue:()Lorg/sireum/MS;
       138: invokespecial #284                // Method scala/Tuple2."<init>":(Ljava/lang/Object;Ljava/lang/Object;)V
       141: aastore
       142: dup
       143: iconst_5
       144: new           #257                // class scala/Tuple2
       147: dup
       148: ldc_w         #289                // String front
       151: aload_0
       152: invokevirtual #199                // Method front:()Lorg/sireum/Z;
       155: invokespecial #284                // Method scala/Tuple2."<init>":(Ljava/lang/Object;Ljava/lang/Object;)V
       158: aastore
       159: dup
       160: bipush        6
       162: new           #257                // class scala/Tuple2
       165: dup
       166: ldc_w         #290                // String rear
       169: aload_0
       170: invokevirtual #201                // Method rear:()Lorg/sireum/Z;
       173: invokespecial #284                // Method scala/Tuple2."<init>":(Ljava/lang/Object;Ljava/lang/Object;)V
       176: aastore
       177: dup
       178: bipush        7
       180: new           #257                // class scala/Tuple2
       183: dup
       184: ldc_w         #291                // String numOfElements
       187: aload_0
       188: invokevirtual #203                // Method numOfElements:()Lorg/sireum/Z;
       191: invokespecial #284                // Method scala/Tuple2."<init>":(Ljava/lang/Object;Ljava/lang/Object;)V
       194: aastore
       195: checkcast     #272                // class "[Ljava/lang/Object;"
       198: invokevirtual #276                // Method scala/runtime/ScalaRunTime$.wrapRefArray:([Ljava/lang/Object;)Lscala/collection/immutable/ArraySeq;
       201: invokevirtual #213                // Method scala/collection/immutable/Seq$.apply:(Lscala/collection/immutable/Seq;)Lscala/collection/SeqOps;
       204: checkcast     #293                // class scala/collection/immutable/Seq
       207: areturn
      LineNumberTable:
        line 262: 0
      LocalVariableTable:
        Start  Length  Slot  Name   Signature
            0     208     0  this   Lorg/sireum/CircularQueue$DropFront;
    Signature: #255                         // ()Lscala/collection/immutable/Seq<Lscala/Tuple2<Ljava/lang/String;Ljava/lang/Object;>;>;

  public org.sireum.CircularQueue$DropFront<E> $clone();
    descriptor: ()Lorg/sireum/CircularQueue$DropFront;
    flags: (0x0001) ACC_PUBLIC
    Code:
      stack=10, locals=2, args_size=1
         0: new           #2                  // class org/sireum/CircularQueue$DropFront
         3: dup
         4: getstatic     #238                // Field org/sireum/helper$.MODULE$:Lorg/sireum/helper$;
         7: aload_0
         8: invokevirtual #186                // Method max:()Lorg/sireum/Z;
        11: invokevirtual #300                // Method org/sireum/helper$.cloneAssign:(Ljava/lang/Object;)Ljava/lang/Object;
        14: checkcast     #229                // class org/sireum/Z
        17: getstatic     #238                // Field org/sireum/helper$.MODULE$:Lorg/sireum/helper$;
        20: aload_0
        21: invokevirtual #188                // Method default:()Ljava/lang/Object;
        24: invokevirtual #300                // Method org/sireum/helper$.cloneAssign:(Ljava/lang/Object;)Ljava/lang/Object;
        27: getstatic     #238                // Field org/sireum/helper$.MODULE$:Lorg/sireum/helper$;
        30: new           #190                // class org/sireum/B
        33: dup
        34: aload_0
        35: invokevirtual #192                // Method scrub:()Z
        38: invokespecial #195                // Method org/sireum/B."<init>":(Z)V
        41: invokevirtual #300                // Method org/sireum/helper$.cloneAssign:(Ljava/lang/Object;)Ljava/lang/Object;
        44: checkcast     #190                // class org/sireum/B
        47: invokevirtual #303                // Method org/sireum/B.value:()Z
        50: getstatic     #238                // Field org/sireum/helper$.MODULE$:Lorg/sireum/helper$;
        53: aload_0
        54: invokevirtual #197                // Method queue:()Lorg/sireum/MS;
        57: invokevirtual #300                // Method org/sireum/helper$.cloneAssign:(Ljava/lang/Object;)Ljava/lang/Object;
        60: checkcast     #231                // class org/sireum/MS
        63: getstatic     #238                // Field org/sireum/helper$.MODULE$:Lorg/sireum/helper$;
        66: aload_0
        67: invokevirtual #199                // Method front:()Lorg/sireum/Z;
        70: invokevirtual #300                // Method org/sireum/helper$.cloneAssign:(Ljava/lang/Object;)Ljava/lang/Object;
        73: checkcast     #229                // class org/sireum/Z
        76: getstatic     #238                // Field org/sireum/helper$.MODULE$:Lorg/sireum/helper$;
        79: aload_0
        80: invokevirtual #201                // Method rear:()Lorg/sireum/Z;
        83: invokevirtual #300                // Method org/sireum/helper$.cloneAssign:(Ljava/lang/Object;)Ljava/lang/Object;
        86: checkcast     #229                // class org/sireum/Z
        89: getstatic     #238                // Field org/sireum/helper$.MODULE$:Lorg/sireum/helper$;
        92: aload_0
        93: invokevirtual #203                // Method numOfElements:()Lorg/sireum/Z;
        96: invokevirtual #300                // Method org/sireum/helper$.cloneAssign:(Ljava/lang/Object;)Ljava/lang/Object;
        99: checkcast     #229                // class org/sireum/Z
       102: invokespecial #245                // Method "<init>":(Lorg/sireum/Z;Ljava/lang/Object;ZLorg/sireum/MS;Lorg/sireum/Z;Lorg/sireum/Z;Lorg/sireum/Z;)V
       105: astore_1
       106: aload_1
       107: areturn
      LineNumberTable:
        line 262: 0
      LocalVariableTable:
        Start  Length  Slot  Name   Signature
          106       1     1     r   Lorg/sireum/CircularQueue$DropFront;
            0     108     0  this   Lorg/sireum/CircularQueue$DropFront;
    Signature: #296                         // ()Lorg/sireum/CircularQueue$DropFront<TE;>;

  public org.sireum.contract$Contract$Invariant invariant();
    descriptor: ()Lorg/sireum/contract$Contract$Invariant;
    flags: (0x0001) ACC_PUBLIC
    Code:
      stack=15, locals=1, args_size=1
         0: getstatic     #310                // Field org/sireum/package$.MODULE$:Lorg/sireum/package$;
         3: getstatic     #175                // Field scala/runtime/ScalaRunTime$.MODULE$:Lscala/runtime/ScalaRunTime$;
         6: iconst_1
         7: anewarray     #190                // class org/sireum/B
        10: dup
        11: iconst_0
        12: new           #190                // class org/sireum/B
        15: dup
        16: getstatic     #315                // Field org/sireum/CircularQueue$.MODULE$:Lorg/sireum/CircularQueue$;
        19: aload_0
        20: invokevirtual #186                // Method max:()Lorg/sireum/Z;
        23: aload_0
        24: invokevirtual #188                // Method default:()Ljava/lang/Object;
        27: aload_0
        28: invokevirtual #192                // Method scrub:()Z
        31: aload_0
        32: invokevirtual #197                // Method queue:()Lorg/sireum/MS;
        35: aload_0
        36: invokevirtual #199                // Method front:()Lorg/sireum/Z;
        39: aload_0
        40: invokevirtual #201                // Method rear:()Lorg/sireum/Z;
        43: aload_0
        44: invokevirtual #203                // Method numOfElements:()Lorg/sireum/Z;
        47: invokevirtual #319                // Method org/sireum/CircularQueue$.inv:(Lorg/sireum/Z;Ljava/lang/Object;ZLorg/sireum/MS;Lorg/sireum/Z;Lorg/sireum/Z;Lorg/sireum/Z;)Z
        50: invokespecial #195                // Method org/sireum/B."<init>":(Z)V
        53: aastore
        54: invokevirtual #207                // Method scala/runtime/ScalaRunTime$.genericWrapArray:(Ljava/lang/Object;)Lscala/collection/immutable/ArraySeq;
        57: invokevirtual #322                // Method org/sireum/package$.Invariant:(Lscala/collection/immutable/Seq;)Lorg/sireum/contract$Contract$Invariant;
        60: areturn
      LineNumberTable:
        line 270: 0
        line 271: 12
      LocalVariableTable:
        Start  Length  Slot  Name   Signature
            0      61     0  this   Lorg/sireum/CircularQueue$DropFront;

  public org.sireum.CircularQueue$Policy$Type policy();
    descriptor: ()Lorg/sireum/CircularQueue$Policy$Type;
    flags: (0x0001) ACC_PUBLIC
    Code:
      stack=1, locals=1, args_size=1
         0: getstatic     #327                // Field org/sireum/CircularQueue$Policy$DropFront$.MODULE$:Lorg/sireum/CircularQueue$Policy$DropFront$;
         3: areturn
      LineNumberTable:
        line 280: 0
      LocalVariableTable:
        Start  Length  Slot  Name   Signature
            0       4     0  this   Lorg/sireum/CircularQueue$DropFront;

  public org.sireum.Z size();
    descriptor: ()Lorg/sireum/Z;
    flags: (0x0001) ACC_PUBLIC
    Code:
      stack=1, locals=1, args_size=1
         0: getstatic     #334                // Field scala/runtime/BoxedUnit.UNIT:Lscala/runtime/BoxedUnit;
         3: pop
         4: aload_0
         5: invokevirtual #203                // Method numOfElements:()Lorg/sireum/Z;
         8: areturn
      LineNumberTable:
        line 283: 0
        line 285: 4
      LocalVariableTable:
        Start  Length  Slot  Name   Signature
            0       9     0  this   Lorg/sireum/CircularQueue$DropFront;

  public boolean isEmpty();
    descriptor: ()Z
    flags: (0x0001) ACC_PUBLIC
    Code:
      stack=4, locals=2, args_size=1
         0: getstatic     #334                // Field scala/runtime/BoxedUnit.UNIT:Lscala/runtime/BoxedUnit;
         3: pop
         4: getstatic     #340                // Field org/sireum/B$.MODULE$:Lorg/sireum/B$;
         7: aload_0
         8: invokevirtual #203                // Method numOfElements:()Lorg/sireum/Z;
        11: getstatic     #345                // Field org/sireum/Z$.MODULE$:Lorg/sireum/Z$;
        14: iconst_0
        15: invokevirtual #348                // Method org/sireum/Z$.apply:(I)Lorg/sireum/Z;
        18: astore_1
        19: dup
        20: ifnonnull     31
        23: pop
        24: aload_1
        25: ifnull        38
        28: goto          42
        31: aload_1
        32: invokevirtual #221                // Method java/lang/Object.equals:(Ljava/lang/Object;)Z
        35: ifeq          42
        38: iconst_1
        39: goto          43
        42: iconst_0
        43: invokevirtual #351                // Method org/sireum/B$.apply:(Z)Z
        46: ireturn
      StackMapTable: number_of_entries = 4
        frame_type = 255 /* full_frame */
          offset_delta = 31
          locals = [ class org/sireum/CircularQueue$DropFront, class org/sireum/Z ]
          stack = [ class org/sireum/B$, class org/sireum/Z ]
        frame_type = 70 /* same_locals_1_stack_item */
          stack = [ class org/sireum/B$ ]
        frame_type = 67 /* same_locals_1_stack_item */
          stack = [ class org/sireum/B$ ]
        frame_type = 255 /* full_frame */
          offset_delta = 0
          locals = [ class org/sireum/CircularQueue$DropFront, class org/sireum/Z ]
          stack = [ class org/sireum/B$, int ]
      LineNumberTable:
        line 289: 0
        line 291: 4
      LocalVariableTable:
        Start  Length  Slot  Name   Signature
            0      47     0  this   Lorg/sireum/CircularQueue$DropFront;

  public boolean nonEmpty();
    descriptor: ()Z
    flags: (0x0001) ACC_PUBLIC
    Code:
      stack=2, locals=1, args_size=1
         0: getstatic     #334                // Field scala/runtime/BoxedUnit.UNIT:Lscala/runtime/BoxedUnit;
         3: pop
         4: getstatic     #340                // Field org/sireum/B$.MODULE$:Lorg/sireum/B$;
         7: aload_0
         8: invokevirtual #354                // Method isEmpty:()Z
        11: invokevirtual #357                // Method org/sireum/B$.unary_$bang$extension:(Z)Z
        14: ireturn
      LineNumberTable:
        line 295: 0
        line 297: 4
      LocalVariableTable:
        Start  Length  Slot  Name   Signature
            0      15     0  this   Lorg/sireum/CircularQueue$DropFront;

  public boolean isFull();
    descriptor: ()Z
    flags: (0x0001) ACC_PUBLIC
    Code:
      stack=3, locals=2, args_size=1
         0: getstatic     #334                // Field scala/runtime/BoxedUnit.UNIT:Lscala/runtime/BoxedUnit;
         3: pop
         4: getstatic     #340                // Field org/sireum/B$.MODULE$:Lorg/sireum/B$;
         7: aload_0
         8: invokevirtual #203                // Method numOfElements:()Lorg/sireum/Z;
        11: aload_0
        12: invokevirtual #186                // Method max:()Lorg/sireum/Z;
        15: astore_1
        16: dup
        17: ifnonnull     28
        20: pop
        21: aload_1
        22: ifnull        35
        25: goto          39
        28: aload_1
        29: invokevirtual #221                // Method java/lang/Object.equals:(Ljava/lang/Object;)Z
        32: ifeq          39
        35: iconst_1
        36: goto          40
        39: iconst_0
        40: invokevirtual #351                // Method org/sireum/B$.apply:(Z)Z
        43: ireturn
      StackMapTable: number_of_entries = 4
        frame_type = 255 /* full_frame */
          offset_delta = 28
          locals = [ class org/sireum/CircularQueue$DropFront, class org/sireum/Z ]
          stack = [ class org/sireum/B$, class org/sireum/Z ]
        frame_type = 70 /* same_locals_1_stack_item */
          stack = [ class org/sireum/B$ ]
        frame_type = 67 /* same_locals_1_stack_item */
          stack = [ class org/sireum/B$ ]
        frame_type = 255 /* full_frame */
          offset_delta = 0
          locals = [ class org/sireum/CircularQueue$DropFront, class org/sireum/Z ]
          stack = [ class org/sireum/B$, int ]
      LineNumberTable:
        line 301: 0
        line 303: 4
      LocalVariableTable:
        Start  Length  Slot  Name   Signature
            0      44     0  this   Lorg/sireum/CircularQueue$DropFront;

  public void enqueue(E);
    descriptor: (Ljava/lang/Object;)V
    flags: (0x0001) ACC_PUBLIC
    Code:
      stack=5, locals=2, args_size=2
         0: getstatic     #334                // Field scala/runtime/BoxedUnit.UNIT:Lscala/runtime/BoxedUnit;
         3: pop
         4: getstatic     #340                // Field org/sireum/B$.MODULE$:Lorg/sireum/B$;
         7: aload_0
         8: invokevirtual #364                // Method isFull:()Z
        11: invokevirtual #367                // Method org/sireum/B$.$4B:(Z)Z
        14: ifeq          24
        17: aload_0
        18: invokevirtual #370                // Method dequeue:()Ljava/lang/Object;
        21: goto          27
        24: getstatic     #334                // Field scala/runtime/BoxedUnit.UNIT:Lscala/runtime/BoxedUnit;
        27: pop
        28: aload_0
        29: invokevirtual #197                // Method queue:()Lorg/sireum/MS;
        32: aload_0
        33: invokevirtual #201                // Method rear:()Lorg/sireum/Z;
        36: aload_1
        37: invokevirtual #373                // Method org/sireum/MS.update:(Ljava/lang/Object;Ljava/lang/Object;)V
        40: aload_0
        41: getstatic     #378                // Field org/sireum/ContractUtil$.MODULE$:Lorg/sireum/ContractUtil$;
        44: aload_0
        45: invokevirtual #201                // Method rear:()Lorg/sireum/Z;
        48: getstatic     #345                // Field org/sireum/Z$.MODULE$:Lorg/sireum/Z$;
        51: iconst_1
        52: invokevirtual #348                // Method org/sireum/Z$.apply:(I)Lorg/sireum/Z;
        55: invokeinterface #382,  2          // InterfaceMethod org/sireum/Z.$plus:(Lorg/sireum/Z;)Lorg/sireum/Z;
        60: aload_0
        61: invokevirtual #197                // Method queue:()Lorg/sireum/MS;
        64: invokevirtual #384                // Method org/sireum/MS.size:()Lorg/sireum/Z;
        67: invokevirtual #388                // Method org/sireum/ContractUtil$.modPos:(Lorg/sireum/Z;Lorg/sireum/Z;)Lorg/sireum/Z;
        70: invokevirtual #390                // Method rear_$eq:(Lorg/sireum/Z;)Lorg/sireum/CircularQueue$DropFront;
        73: pop
        74: aload_0
        75: aload_0
        76: invokevirtual #203                // Method numOfElements:()Lorg/sireum/Z;
        79: getstatic     #345                // Field org/sireum/Z$.MODULE$:Lorg/sireum/Z$;
        82: iconst_1
        83: invokevirtual #348                // Method org/sireum/Z$.apply:(I)Lorg/sireum/Z;
        86: invokeinterface #382,  2          // InterfaceMethod org/sireum/Z.$plus:(Lorg/sireum/Z;)Lorg/sireum/Z;
        91: invokevirtual #392                // Method numOfElements_$eq:(Lorg/sireum/Z;)Lorg/sireum/CircularQueue$DropFront;
        94: pop
        95: return
      StackMapTable: number_of_entries = 2
        frame_type = 24 /* same */
        frame_type = 66 /* same_locals_1_stack_item */
          stack = [ class java/lang/Object ]
      LineNumberTable:
        line 307: 0
        line 318: 4
        line 319: 17
        line 318: 24
        line 321: 28
        line 322: 40
        line 323: 74
      LocalVariableTable:
        Start  Length  Slot  Name   Signature
            0      96     0  this   Lorg/sireum/CircularQueue$DropFront;
            0      96     1 element   Ljava/lang/Object;
    Signature: #361                         // (TE;)V
    MethodParameters:
      Name                           Flags
      element                        final

  public E dequeue();
    descriptor: ()Ljava/lang/Object;
    flags: (0x0001) ACC_PUBLIC
    Code:
      stack=5, locals=2, args_size=1
         0: getstatic     #334                // Field scala/runtime/BoxedUnit.UNIT:Lscala/runtime/BoxedUnit;
         3: pop
         4: aload_0
         5: invokevirtual #197                // Method queue:()Lorg/sireum/MS;
         8: aload_0
         9: invokevirtual #199                // Method front:()Lorg/sireum/Z;
        12: invokevirtual #394                // Method org/sireum/MS.apply:(Ljava/lang/Object;)Ljava/lang/Object;
        15: astore_1
        16: getstatic     #340                // Field org/sireum/B$.MODULE$:Lorg/sireum/B$;
        19: aload_0
        20: invokevirtual #192                // Method scrub:()Z
        23: invokevirtual #367                // Method org/sireum/B$.$4B:(Z)Z
        26: ifeq          47
        29: aload_0
        30: invokevirtual #197                // Method queue:()Lorg/sireum/MS;
        33: aload_0
        34: invokevirtual #199                // Method front:()Lorg/sireum/Z;
        37: aload_0
        38: invokevirtual #188                // Method default:()Ljava/lang/Object;
        41: invokevirtual #373                // Method org/sireum/MS.update:(Ljava/lang/Object;Ljava/lang/Object;)V
        44: goto          47
        47: aload_0
        48: getstatic     #378                // Field org/sireum/ContractUtil$.MODULE$:Lorg/sireum/ContractUtil$;
        51: aload_0
        52: invokevirtual #199                // Method front:()Lorg/sireum/Z;
        55: getstatic     #345                // Field org/sireum/Z$.MODULE$:Lorg/sireum/Z$;
        58: iconst_1
        59: invokevirtual #348                // Method org/sireum/Z$.apply:(I)Lorg/sireum/Z;
        62: invokeinterface #382,  2          // InterfaceMethod org/sireum/Z.$plus:(Lorg/sireum/Z;)Lorg/sireum/Z;
        67: aload_0
        68: invokevirtual #197                // Method queue:()Lorg/sireum/MS;
        71: invokevirtual #384                // Method org/sireum/MS.size:()Lorg/sireum/Z;
        74: invokevirtual #388                // Method org/sireum/ContractUtil$.modPos:(Lorg/sireum/Z;Lorg/sireum/Z;)Lorg/sireum/Z;
        77: invokevirtual #396                // Method front_$eq:(Lorg/sireum/Z;)Lorg/sireum/CircularQueue$DropFront;
        80: pop
        81: aload_0
        82: aload_0
        83: invokevirtual #203                // Method numOfElements:()Lorg/sireum/Z;
        86: getstatic     #345                // Field org/sireum/Z$.MODULE$:Lorg/sireum/Z$;
        89: iconst_1
        90: invokevirtual #348                // Method org/sireum/Z$.apply:(I)Lorg/sireum/Z;
        93: invokeinterface #399,  2          // InterfaceMethod org/sireum/Z.$minus:(Lorg/sireum/Z;)Lorg/sireum/Z;
        98: invokevirtual #392                // Method numOfElements_$eq:(Lorg/sireum/Z;)Lorg/sireum/CircularQueue$DropFront;
       101: pop
       102: aload_1
       103: areturn
      StackMapTable: number_of_entries = 1
        frame_type = 252 /* append */
          offset_delta = 47
          locals = [ class java/lang/Object ]
      LineNumberTable:
        line 327: 0
        line 337: 4
        line 338: 16
        line 339: 29
        line 341: 47
        line 342: 81
        line 343: 102
      LocalVariableTable:
        Start  Length  Slot  Name   Signature
           16      88     1     r   Ljava/lang/Object;
            0     104     0  this   Lorg/sireum/CircularQueue$DropFront;
    Signature: #116                         // ()TE;

  public org.sireum.MS<org.sireum.Z, E> elements();
    descriptor: ()Lorg/sireum/MS;
    flags: (0x0001) ACC_PUBLIC
    Code:
      stack=4, locals=2, args_size=1
         0: getstatic     #334                // Field scala/runtime/BoxedUnit.UNIT:Lscala/runtime/BoxedUnit;
         3: pop
         4: getstatic     #238                // Field org/sireum/helper$.MODULE$:Lorg/sireum/helper$;
         7: getstatic     #310                // Field org/sireum/package$.MODULE$:Lorg/sireum/package$;
        10: invokevirtual #404                // Method org/sireum/package$.MSZ:()Lorg/sireum/$internal/PackageTrait$MSZ$;
        13: aload_0
        14: invokevirtual #203                // Method numOfElements:()Lorg/sireum/Z;
        17: aload_0
        18: invokevirtual #188                // Method default:()Ljava/lang/Object;
        21: invokevirtual #408                // Method org/sireum/$internal/PackageTrait$MSZ$.create:(Lorg/sireum/Z;Ljava/lang/Object;)Lorg/sireum/MS;
        24: invokevirtual #242                // Method org/sireum/helper$.assignMut:(Lorg/sireum/$internal/MutableMarker;)Ljava/lang/Object;
        27: checkcast     #231                // class org/sireum/MS
        30: astore_1
        31: getstatic     #345                // Field org/sireum/Z$.MODULE$:Lorg/sireum/Z$;
        34: iconst_0
        35: invokevirtual #348                // Method org/sireum/Z$.apply:(I)Lorg/sireum/Z;
        38: aload_0
        39: invokevirtual #203                // Method numOfElements:()Lorg/sireum/Z;
        42: invokeinterface #412,  2          // InterfaceMethod org/sireum/Z.until:(Lorg/sireum/ZLike;)Lorg/sireum/ZRange;
        47: aload_0
        48: aload_1
        49: invokedynamic #432,  0            // InvokeDynamic #0:apply:(Lorg/sireum/CircularQueue$DropFront;Lorg/sireum/MS;)Lscala/Function1;
        54: invokevirtual #438                // Method org/sireum/ZRange.foreach:(Lscala/Function1;)V
        57: getstatic     #238                // Field org/sireum/helper$.MODULE$:Lorg/sireum/helper$;
        60: aload_1
        61: invokevirtual #441                // Method org/sireum/helper$.retMut:(Lorg/sireum/$internal/MutableMarker;)Ljava/lang/Object;
        64: checkcast     #231                // class org/sireum/MS
        67: areturn
      LineNumberTable:
        line 347: 0
        line 349: 4
        line 350: 31
        line 353: 57
      LocalVariableTable:
        Start  Length  Slot  Name   Signature
           31      37     1     r   Lorg/sireum/MS;
            0      68     0  this   Lorg/sireum/CircularQueue$DropFront;
    Signature: #99                          // ()Lorg/sireum/MS<Lorg/sireum/Z;TE;>;

  public final org.sireum.$internal.MutableMarker $owned_$eq(boolean);
    descriptor: (Z)Lorg/sireum/$internal/MutableMarker;
    flags: (0x1051) ACC_PUBLIC, ACC_FINAL, ACC_BRIDGE, ACC_SYNTHETIC
    Code:
      stack=2, locals=2, args_size=2
         0: aload_0
         1: iload_1
         2: invokevirtual #444                // Method $owned_$eq:(Z)Lorg/sireum/RecordSig;
         5: areturn
      LineNumberTable:
        line 262: 0
      LocalVariableTable:
        Start  Length  Slot  Name   Signature
            0       6     0  this   Lorg/sireum/CircularQueue$DropFront;
            0       6     1     b   Z
    MethodParameters:
      Name                           Flags
      b                              final

  public java.lang.Object $clone();
    descriptor: ()Ljava/lang/Object;
    flags: (0x1041) ACC_PUBLIC, ACC_BRIDGE, ACC_SYNTHETIC
    Code:
      stack=1, locals=1, args_size=1
         0: aload_0
         1: invokevirtual #446                // Method $clone:()Lorg/sireum/CircularQueue$DropFront;
         4: areturn
      LineNumberTable:
        line 262: 0
      LocalVariableTable:
        Start  Length  Slot  Name   Signature
            0       5     0  this   Lorg/sireum/CircularQueue$DropFront;

  public org.sireum.$internal.MutableMarker $clone();
    descriptor: ()Lorg/sireum/$internal/MutableMarker;
    flags: (0x1041) ACC_PUBLIC, ACC_BRIDGE, ACC_SYNTHETIC
    Code:
      stack=1, locals=1, args_size=1
         0: aload_0
         1: invokevirtual #446                // Method $clone:()Lorg/sireum/CircularQueue$DropFront;
         4: areturn
      LineNumberTable:
        line 262: 0
      LocalVariableTable:
        Start  Length  Slot  Name   Signature
            0       5     0  this   Lorg/sireum/CircularQueue$DropFront;

  public static final void $anonfun$elements$2(org.sireum.CircularQueue$DropFront, org.sireum.MS, org.sireum.Z);
    descriptor: (Lorg/sireum/CircularQueue$DropFront;Lorg/sireum/MS;Lorg/sireum/Z;)V
    flags: (0x1019) ACC_PUBLIC, ACC_STATIC, ACC_FINAL, ACC_SYNTHETIC
    Code:
      stack=6, locals=3, args_size=3
         0: aload_1
         1: aload_2
         2: aload_0
         3: invokevirtual #197                // Method queue:()Lorg/sireum/MS;
         6: getstatic     #378                // Field org/sireum/ContractUtil$.MODULE$:Lorg/sireum/ContractUtil$;
         9: aload_0
        10: invokevirtual #199                // Method front:()Lorg/sireum/Z;
        13: aload_2
        14: invokeinterface #382,  2          // InterfaceMethod org/sireum/Z.$plus:(Lorg/sireum/Z;)Lorg/sireum/Z;
        19: aload_0
        20: invokevirtual #197                // Method queue:()Lorg/sireum/MS;
        23: invokevirtual #384                // Method org/sireum/MS.size:()Lorg/sireum/Z;
        26: invokevirtual #388                // Method org/sireum/ContractUtil$.modPos:(Lorg/sireum/Z;Lorg/sireum/Z;)Lorg/sireum/Z;
        29: invokevirtual #394                // Method org/sireum/MS.apply:(Ljava/lang/Object;)Ljava/lang/Object;
        32: invokevirtual #373                // Method org/sireum/MS.update:(Ljava/lang/Object;Ljava/lang/Object;)V
        35: return
      LineNumberTable:
        line 351: 0
      LocalVariableTable:
        Start  Length  Slot  Name   Signature
            0      36     0 $this   Lorg/sireum/CircularQueue$DropFront;
            0      36     1   r$2   Lorg/sireum/MS;
            0      36     2     i   Lorg/sireum/Z;
    MethodParameters:
      Name                           Flags
      $this                          final synthetic
      r$2                            final
      i                              final

  public org.sireum.CircularQueue$DropFront(org.sireum.Z, E, boolean, org.sireum.MS<org.sireum.Z, E>, org.sireum.Z, org.sireum.Z, org.sireum.Z);
    descriptor: (Lorg/sireum/Z;Ljava/lang/Object;ZLorg/sireum/MS;Lorg/sireum/Z;Lorg/sireum/Z;Lorg/sireum/Z;)V
    flags: (0x0001) ACC_PUBLIC
    Code:
      stack=2, locals=8, args_size=8
         0: aload_0
         1: invokespecial #463                // Method java/lang/Object."<init>":()V
         4: aload_0
         5: invokestatic  #467                // InterfaceMethod org/sireum/Mutable.$init$:(Lorg/sireum/Mutable;)V
         8: aload_0
         9: invokestatic  #470                // InterfaceMethod org/sireum/RecordSig.$init$:(Lorg/sireum/RecordSig;)V
        12: aload_0
        13: invokestatic  #473                // InterfaceMethod org/sireum/CircularQueue.$init$:(Lorg/sireum/CircularQueue;)V
        16: aload_0
        17: aload_1
        18: putfield      #112                // Field _max:Lorg/sireum/Z;
        21: aload_0
        22: aload_2
        23: putfield      #118                // Field _default:Ljava/lang/Object;
        26: aload_0
        27: iload_3
        28: putfield      #122                // Field _scrub:Z
        31: aload_0
        32: aload         4
        34: putfield      #126                // Field _queue:Lorg/sireum/MS;
        37: aload_0
        38: aload         5
        40: putfield      #130                // Field _front:Lorg/sireum/Z;
        43: aload_0
        44: aload         6
        46: putfield      #138                // Field _rear:Lorg/sireum/Z;
        49: aload_0
        50: aload         7
        52: putfield      #144                // Field _numOfElements:Lorg/sireum/Z;
        55: getstatic     #334                // Field scala/runtime/BoxedUnit.UNIT:Lscala/runtime/BoxedUnit;
        58: pop
        59: return
      LineNumberTable:
        line 268: 0
        line 262: 16
        line 274: 55
        line 262: 59
      LocalVariableTable:
        Start  Length  Slot  Name   Signature
            0      60     0  this   Lorg/sireum/CircularQueue$DropFront;
            0      60     1 __max   Lorg/sireum/Z;
            0      60     2 __default   Ljava/lang/Object;
            0      60     3 __scrub   Z
            0      60     4 __queue   Lorg/sireum/MS;
            0      60     5 __front   Lorg/sireum/Z;
            0      60     6 __rear   Lorg/sireum/Z;
            0      60     7 __numOfElements   Lorg/sireum/Z;
    Signature: #453                         // (Lorg/sireum/Z;TE;ZLorg/sireum/MS<Lorg/sireum/Z;TE;>;Lorg/sireum/Z;Lorg/sireum/Z;Lorg/sireum/Z;)V
    MethodParameters:
      Name                           Flags
      __max                          final
      __default                      final
      __scrub                        final
      __queue                        final
      __front                        final
      __rear                         final
      __numOfElements                final

  public static final java.lang.Object $anonfun$elements$2$adapted(org.sireum.CircularQueue$DropFront, org.sireum.MS, org.sireum.Z);
    descriptor: (Lorg/sireum/CircularQueue$DropFront;Lorg/sireum/MS;Lorg/sireum/Z;)Ljava/lang/Object;
    flags: (0x1019) ACC_PUBLIC, ACC_STATIC, ACC_FINAL, ACC_SYNTHETIC
    Code:
      stack=3, locals=3, args_size=3
         0: aload_0
         1: aload_1
         2: aload_2
         3: invokestatic  #475                // Method $anonfun$elements$2:(Lorg/sireum/CircularQueue$DropFront;Lorg/sireum/MS;Lorg/sireum/Z;)V
         6: getstatic     #334                // Field scala/runtime/BoxedUnit.UNIT:Lscala/runtime/BoxedUnit;
         9: areturn
      LineNumberTable:
        line 350: 0
      LocalVariableTable:
        Start  Length  Slot  Name   Signature
            0      10     0 $this   Lorg/sireum/CircularQueue$DropFront;
            0      10     1   r$2   Lorg/sireum/MS;
            0      10     2     i   Lorg/sireum/Z;
    MethodParameters:
      Name                           Flags
      $this                          final
      r$2                            final
      i                              final

  private static java.lang.Object $deserializeLambda$(java.lang.invoke.SerializedLambda);
    descriptor: (Ljava/lang/invoke/SerializedLambda;)Ljava/lang/Object;
    flags: (0x100a) ACC_PRIVATE, ACC_STATIC, ACC_SYNTHETIC
    Code:
      stack=1, locals=1, args_size=1
         0: aload_0
         1: invokedynamic #487,  0            // InvokeDynamic #1:lambdaDeserialize:(Ljava/lang/invoke/SerializedLambda;)Ljava/lang/Object;
         6: areturn
}
InnerClasses:
  public static final #13= #10 of #12;    // Lookup=class java/lang/invoke/MethodHandles$Lookup of class java/lang/invoke/MethodHandles
  public #18= #15 of #17;                 // MSZ$=class org/sireum/$internal/PackageTrait$MSZ$ of class org/sireum/$internal/PackageTrait
  public static final #19= #2 of #7;      // DropFront=class org/sireum/CircularQueue$DropFront of class org/sireum/CircularQueue
  public static #22= #21 of #7;           // Policy$=class org/sireum/CircularQueue$Policy$ of class org/sireum/CircularQueue
  public static final #25= #24 of #21;    // DropFront$=class org/sireum/CircularQueue$Policy$DropFront$ of class org/sireum/CircularQueue$Policy$
  public static #28= #27 of #21;          // Type=class org/sireum/CircularQueue$Policy$Type of class org/sireum/CircularQueue$Policy$
  public #33= #30 of #32;                 // Contract$=class org/sireum/contract$Contract$ of class org/sireum/contract
  public #36= #35 of #30;                 // Invariant=class org/sireum/contract$Contract$Invariant of class org/sireum/contract$Contract$
Signature: #3                           // <E:Ljava/lang/Object;>Ljava/lang/Object;Lorg/sireum/CircularQueue<TE;>;
SourceFile: "CircularQueue.scala"
BootstrapMethods:
  0: #429 REF_invokeStatic java/lang/invoke/LambdaMetafactory.altMetafactory:(Ljava/lang/invoke/MethodHandles$Lookup;Ljava/lang/String;Ljava/lang/invoke/MethodType;[Ljava/lang/Object;)Ljava/lang/invoke/CallSite;
    Method arguments:
      #413 (Ljava/lang/Object;)Ljava/lang/Object;
      #418 REF_invokeStatic org/sireum/CircularQueue$DropFront.$anonfun$elements$2$adapted:(Lorg/sireum/CircularQueue$DropFront;Lorg/sireum/MS;Lorg/sireum/Z;)Ljava/lang/Object;
      #420 (Lorg/sireum/Z;)Ljava/lang/Object;
      #421 5
      #422 1
      #420 (Lorg/sireum/Z;)Ljava/lang/Object;
  1: #484 REF_invokeStatic scala/runtime/LambdaDeserialize.bootstrap:(Ljava/lang/invoke/MethodHandles$Lookup;Ljava/lang/String;Ljava/lang/invoke/MethodType;[Ljava/lang/invoke/MethodHandle;)Ljava/lang/invoke/CallSite;
    Method arguments:
      #418 REF_invokeStatic org/sireum/CircularQueue$DropFront.$anonfun$elements$2$adapted:(Lorg/sireum/CircularQueue$DropFront;Lorg/sireum/MS;Lorg/sireum/Z;)Ljava/lang/Object;
  ScalaInlineInfo: length = 0x130 (unknown attribute)
   01 01 00 3C 01 C0 01 C1 01 01 9E 01 9F 01 00 51
   00 52 01 01 26 00 73 01 01 26 01 BF 01 01 26 01
   27 01 00 FD 00 FE 01 00 59 00 3D 01 00 5E 00 3D
   01 00 3C 00 3D 01 00 44 01 BA 01 00 44 00 45 01
   00 C1 00 F3 01 00 D2 00 E8 01 00 F6 00 4C 01 00
   F7 00 73 01 00 F8 00 3D 01 00 F9 00 62 01 00 FA
   00 4C 01 00 FB 00 4C 01 00 FC 00 4C 01 00 72 00
   73 01 01 70 00 73 01 01 90 00 62 01 01 67 01 68
   01 00 D9 00 DA 01 00 80 00 4C 01 00 84 00 85 01
   00 77 00 73 01 00 83 00 4C 01 00 71 00 4C 01 00
   91 00 4C 01 00 7F 00 62 01 00 8B 00 4C 01 00 7B
   00 3D 01 00 4B 00 4C 01 00 9B 00 9C 01 01 31 00
   35 01 01 4F 00 3D 01 01 66 00 3D 01 00 6E 00 4C
   01 01 60 00 3D 01 00 8E 00 4C 01 00 92 00 85 01
   00 33 00 3D 01 00 6C 00 6D 01 01 43 01 44 01 00
   7C 00 62 01 00 88 00 4C 01 00 8C 00 85 01 00 32
   00 62 01 00 34 00 35 01 00 66 00 67 01 00 78 00
   3D 01 00 87 00 85 01 00 93 00 85 01 00 8D 00 85
   01 01 48 00 4C 01 00 9A 00 95 01 00 94 00 95 01

  Scala: length = 0x0 (unknown attribute)

