Classfile /Users/mw/Projects/slang-braindump/.jar/jar8/assemble/slang-braindump/assemble/content/org/sireum/DiffMatchPatch$LinesToCharsResult.class
  Last modified May 29, 2022; size 673 bytes
  SHA-256 checksum 7b6e31c662871e1ff0dfe5d863a58e69933e6da5ed2f9607ff807aaffd1cce26
  Compiled from "DiffMatchPatch.java"
public class org.sireum.DiffMatchPatch$LinesToCharsResult
  minor version: 0
  major version: 52
  flags: (0x0021) ACC_PUBLIC, ACC_SUPER
  this_class: #8                          // org/sireum/DiffMatchPatch$LinesToCharsResult
  super_class: #2                         // java/lang/Object
  interfaces: 0, fields: 3, methods: 1, attributes: 2
Constant pool:
   #1 = Methodref          #2.#3          // java/lang/Object."<init>":()V
   #2 = Class              #4             // java/lang/Object
   #3 = NameAndType        #5:#6          // "<init>":()V
   #4 = Utf8               java/lang/Object
   #5 = Utf8               <init>
   #6 = Utf8               ()V
   #7 = Fieldref           #8.#9          // org/sireum/DiffMatchPatch$LinesToCharsResult.chars1:Ljava/lang/String;
   #8 = Class              #10            // org/sireum/DiffMatchPatch$LinesToCharsResult
   #9 = NameAndType        #11:#12        // chars1:Ljava/lang/String;
  #10 = Utf8               org/sireum/DiffMatchPatch$LinesToCharsResult
  #11 = Utf8               chars1
  #12 = Utf8               Ljava/lang/String;
  #13 = Fieldref           #8.#14         // org/sireum/DiffMatchPatch$LinesToCharsResult.chars2:Ljava/lang/String;
  #14 = NameAndType        #15:#12        // chars2:Ljava/lang/String;
  #15 = Utf8               chars2
  #16 = Fieldref           #8.#17         // org/sireum/DiffMatchPatch$LinesToCharsResult.lineArray:Ljava/util/List;
  #17 = NameAndType        #18:#19        // lineArray:Ljava/util/List;
  #18 = Utf8               lineArray
  #19 = Utf8               Ljava/util/List;
  #20 = Utf8               Signature
  #21 = Utf8               Ljava/util/List<Ljava/lang/String;>;
  #22 = Utf8               (Ljava/lang/String;Ljava/lang/String;Ljava/util/List;)V
  #23 = Utf8               Code
  #24 = Utf8               LineNumberTable
  #25 = Utf8               (Ljava/lang/String;Ljava/lang/String;Ljava/util/List<Ljava/lang/String;>;)V
  #26 = Utf8               SourceFile
  #27 = Utf8               DiffMatchPatch.java
  #28 = Utf8               InnerClasses
  #29 = Class              #30            // org/sireum/DiffMatchPatch
  #30 = Utf8               org/sireum/DiffMatchPatch
  #31 = Utf8               LinesToCharsResult
{
  protected java.lang.String chars1;
    descriptor: Ljava/lang/String;
    flags: (0x0004) ACC_PROTECTED

  protected java.lang.String chars2;
    descriptor: Ljava/lang/String;
    flags: (0x0004) ACC_PROTECTED

  protected java.util.List<java.lang.String> lineArray;
    descriptor: Ljava/util/List;
    flags: (0x0004) ACC_PROTECTED
    Signature: #21                          // Ljava/util/List<Ljava/lang/String;>;

  protected org.sireum.DiffMatchPatch$LinesToCharsResult(java.lang.String, java.lang.String, java.util.List<java.lang.String>);
    descriptor: (Ljava/lang/String;Ljava/lang/String;Ljava/util/List;)V
    flags: (0x0004) ACC_PROTECTED
    Code:
      stack=2, locals=4, args_size=4
         0: aload_0
         1: invokespecial #1                  // Method java/lang/Object."<init>":()V
         4: aload_0
         5: aload_1
         6: putfield      #7                  // Field chars1:Ljava/lang/String;
         9: aload_0
        10: aload_2
        11: putfield      #13                 // Field chars2:Ljava/lang/String;
        14: aload_0
        15: aload_3
        16: putfield      #16                 // Field lineArray:Ljava/util/List;
        19: return
      LineNumberTable:
        line 99: 0
        line 100: 4
        line 101: 9
        line 102: 14
        line 103: 19
    Signature: #25                          // (Ljava/lang/String;Ljava/lang/String;Ljava/util/List<Ljava/lang/String;>;)V
}
SourceFile: "DiffMatchPatch.java"
InnerClasses:
  protected static #31= #8 of #29;        // LinesToCharsResult=class org/sireum/DiffMatchPatch$LinesToCharsResult of class org/sireum/DiffMatchPatch
