Classfile /Users/mw/Projects/slang-braindump/.jar/jar8/assemble/slang-braindump/assemble/content/org/sireum/Hash.class
  Last modified May 29, 2022; size 1178 bytes
  SHA-256 checksum a615e29df032dcb52892f9c7141de570c5f5baae87abca2d91503c61d713571f
  Compiled from "Hash.scala"
public final class org.sireum.Hash
  minor version: 0
  major version: 52
  flags: (0x0031) ACC_PUBLIC, ACC_FINAL, ACC_SUPER
  this_class: #2                          // org/sireum/Hash
  super_class: #4                         // java/lang/Object
  interfaces: 0, fields: 0, methods: 3, attributes: 3
Constant pool:
   #1 = Utf8               org/sireum/Hash
   #2 = Class              #1             // org/sireum/Hash
   #3 = Utf8               java/lang/Object
   #4 = Class              #3             // java/lang/Object
   #5 = Utf8               Hash.scala
   #6 = Utf8               Lscala/reflect/ScalaSignature;
   #7 = Utf8               bytes
   #8 = Utf8               \u0006\u0005\u0011;QAB\u0004\t\u000211QAD\u0004\t\u0002=AQAF\u0001\u0005\u0002]AQ\u0001G\u0001\u0005\u0002eAQAM\u0001\u0005\u0002MBQAO\u0001\u0005\u0002m\nA\u0001S1tQ*\u0011\u0001\"C\u0001\u0007g&\u0014X-^7\u000b\u0003)\t1a\u001c:h\u0007\u0001\u0001\"!D\u0001\u000e\u0003\u001d\u0011A\u0001S1tQN\u0011\u0011\u0001\u0005\t\u0003#Qi\u0011A\u0005\u0006\u0002\'\u0005)1oY1mC&\u0011QC\u0005\u0002\u0007\u0003:L(+\u001a4\u0002\rqJg.\u001b;?)\u0005a\u0011\u0001C7ve6,(oM1\u0015\u0007iiB\u0006\u0005\u0002\u000e7%\u0011Ad\u0002\u0002\u0004+N\u0012\u0004\"\u0002\u0010\u0004\u0001\u0004y\u0012\u0001\u00023bi\u0006\u00042\u0001I\u0012*\u001d\ti\u0011%\u0003\u0002#\u000f\u00059\u0001/Y2lC\u001e,\u0017B\u0001\u0013&\u0005\rI5KW\u0005\u0003M\u001d\u0012A\u0002U1dW\u0006<W\r\u0016:bSRT!\u0001K\u0004\u0002\u0013\u0011Jg\u000e^3s]\u0006d\u0007CA\u0007+\u0013\tYsA\u0001\u0002Vq!)Qf\u0001a\u00015\u0005!1/Z3eQ\t\u0019q\u0006\u0005\u0002\u000ea%\u0011\u0011g\u0002\u0002\u0005aV\u0014X-A\u0003uc!\f\u0007\u0007F\u00025oa\u0002\"!D\u001b\n\u0005Y:!aA+7i!)a\u0004\u0002a\u0001?!)Q\u0006\u0002a\u0001i!\u0012AaL\u0001\u0005iFB\u0017\r\u0006\u00035y\u0005\u0013\u0005\"B\u001f\u0006\u0001\u0004q\u0014aB5t\r&\u00148\u000f\u001e\t\u0003\u001b}J!\u0001Q\u0004\u0003\u0003\tCQAH\u0003A\u0002}AQ!L\u0003A\u0002QB#!B\u0018
   #9 = Utf8               t1ha
  #10 = Utf8               (ZLorg/sireum/IS;J)J
  #11 = Utf8               isFirst
  #12 = Utf8               data
  #13 = Utf8               seed
  #14 = Utf8               org/sireum/Hash$
  #15 = Class              #14            // org/sireum/Hash$
  #16 = Utf8               MODULE$
  #17 = Utf8               Lorg/sireum/Hash$;
  #18 = NameAndType        #16:#17        // MODULE$:Lorg/sireum/Hash$;
  #19 = Fieldref           #15.#18        // org/sireum/Hash$.MODULE$:Lorg/sireum/Hash$;
  #20 = NameAndType        #9:#10         // t1ha:(ZLorg/sireum/IS;J)J
  #21 = Methodref          #15.#20        // org/sireum/Hash$.t1ha:(ZLorg/sireum/IS;J)J
  #22 = Utf8               Z
  #23 = Utf8               Lorg/sireum/IS;
  #24 = Utf8               J
  #25 = Utf8               t1ha0
  #26 = Utf8               (Lorg/sireum/IS;J)J
  #27 = NameAndType        #25:#26        // t1ha0:(Lorg/sireum/IS;J)J
  #28 = Methodref          #15.#27        // org/sireum/Hash$.t1ha0:(Lorg/sireum/IS;J)J
  #29 = Utf8               murmur3a
  #30 = Utf8               (Lorg/sireum/IS;I)I
  #31 = NameAndType        #29:#30        // murmur3a:(Lorg/sireum/IS;I)I
  #32 = Methodref          #15.#31        // org/sireum/Hash$.murmur3a:(Lorg/sireum/IS;I)I
  #33 = Utf8               I
  #34 = Utf8               Code
  #35 = Utf8               LocalVariableTable
  #36 = Utf8               MethodParameters
  #37 = Utf8               SourceFile
  #38 = Utf8               RuntimeVisibleAnnotations
  #39 = Utf8               ScalaSig
{
  public static long t1ha(boolean, org.sireum.IS, long);
    descriptor: (ZLorg/sireum/IS;J)J
    flags: (0x0009) ACC_PUBLIC, ACC_STATIC
    Code:
      stack=5, locals=4, args_size=3
         0: getstatic     #19                 // Field org/sireum/Hash$.MODULE$:Lorg/sireum/Hash$;
         3: iload_0
         4: aload_1
         5: lload_2
         6: invokevirtual #21                 // Method org/sireum/Hash$.t1ha:(ZLorg/sireum/IS;J)J
         9: lreturn
      LocalVariableTable:
        Start  Length  Slot  Name   Signature
            0      10     0 isFirst   Z
            0      10     1  data   Lorg/sireum/IS;
            0      10     2  seed   J
    MethodParameters:
      Name                           Flags
      isFirst                        final
      data                           final
      seed                           final

  public static long t1ha0(org.sireum.IS, long);
    descriptor: (Lorg/sireum/IS;J)J
    flags: (0x0009) ACC_PUBLIC, ACC_STATIC
    Code:
      stack=4, locals=3, args_size=2
         0: getstatic     #19                 // Field org/sireum/Hash$.MODULE$:Lorg/sireum/Hash$;
         3: aload_0
         4: lload_1
         5: invokevirtual #28                 // Method org/sireum/Hash$.t1ha0:(Lorg/sireum/IS;J)J
         8: lreturn
      LocalVariableTable:
        Start  Length  Slot  Name   Signature
            0       9     0  data   Lorg/sireum/IS;
            0       9     1  seed   J
    MethodParameters:
      Name                           Flags
      data                           final
      seed                           final

  public static int murmur3a(org.sireum.IS, int);
    descriptor: (Lorg/sireum/IS;I)I
    flags: (0x0009) ACC_PUBLIC, ACC_STATIC
    Code:
      stack=3, locals=2, args_size=2
         0: getstatic     #19                 // Field org/sireum/Hash$.MODULE$:Lorg/sireum/Hash$;
         3: aload_0
         4: iload_1
         5: invokevirtual #32                 // Method org/sireum/Hash$.murmur3a:(Lorg/sireum/IS;I)I
         8: ireturn
      LocalVariableTable:
        Start  Length  Slot  Name   Signature
            0       9     0  data   Lorg/sireum/IS;
            0       9     1  seed   I
    MethodParameters:
      Name                           Flags
      data                           final
      seed                           final
}
SourceFile: "Hash.scala"
RuntimeVisibleAnnotations:
  0: #6(#7=s#8)
    scala.reflect.ScalaSignature(
      bytes="\u0006\u0005\u0011;QAB\u0004\t\u000211QAD\u0004\t\u0002=AQAF\u0001\u0005\u0002]AQ\u0001G\u0001\u0005\u0002eAQAM\u0001\u0005\u0002MBQAO\u0001\u0005\u0002m\nA\u0001S1tQ*\u0011\u0001\"C\u0001\u0007g&\u0014X-^7\u000b\u0003)\t1a\u001c:h\u0007\u0001\u0001\"!D\u0001\u000e\u0003\u001d\u0011A\u0001S1tQN\u0011\u0011\u0001\u0005\t\u0003#Qi\u0011A\u0005\u0006\u0002\'\u0005)1oY1mC&\u0011QC\u0005\u0002\u0007\u0003:L(+\u001a4\u0002\rqJg.\u001b;?)\u0005a\u0011\u0001C7ve6,(oM1\u0015\u0007iiB\u0006\u0005\u0002\u000e7%\u0011Ad\u0002\u0002\u0004+N\u0012\u0004\"\u0002\u0010\u0004\u0001\u0004y\u0012\u0001\u00023bi\u0006\u00042\u0001I\u0012*\u001d\ti\u0011%\u0003\u0002#\u000f\u00059\u0001/Y2lC\u001e,\u0017B\u0001\u0013&\u0005\rI5KW\u0005\u0003M\u001d\u0012A\u0002U1dW\u0006<W\r\u0016:bSRT!\u0001K\u0004\u0002\u0013\u0011Jg\u000e^3s]\u0006d\u0007CA\u0007+\u0013\tYsA\u0001\u0002Vq!)Qf\u0001a\u00015\u0005!1/Z3eQ\t\u0019q\u0006\u0005\u0002\u000ea%\u0011\u0011g\u0002\u0002\u0005aV\u0014X-A\u0003uc!\f\u0007\u0007F\u00025oa\u0002\"!D\u001b\n\u0005Y:!aA+7i!)a\u0004\u0002a\u0001?!)Q\u0006\u0002a\u0001i!\u0012AaL\u0001\u0005iFB\u0017\r\u0006\u00035y\u0005\u0013\u0005\"B\u001f\u0006\u0001\u0004q\u0014aB5t\r&\u00148\u000f\u001e\t\u0003\u001b}J!\u0001Q\u0004\u0003\u0003\tCQAH\u0003A\u0002}AQ!L\u0003A\u0002QB#!B\u0018"
    )
  ScalaSig: length = 0x3 (unknown attribute)
   05 02 00
