Classfile /Users/mw/Projects/slang-braindump/.jar/jar8/assemble/slang-braindump/assemble/content/org/sireum/Indexable.class
  Last modified May 29, 2022; size 4112 bytes
  SHA-256 checksum 49a41dedad4b707ec4e3d37965ea49f8102db2243c4841577f2a10eb2b296abf
  Compiled from "Indexable.scala"
public interface org.sireum.Indexable<T extends java.lang.Object> extends org.sireum.Immutable
  minor version: 0
  major version: 52
  flags: (0x0601) ACC_PUBLIC, ACC_INTERFACE, ACC_ABSTRACT
  this_class: #2                          // org/sireum/Indexable
  super_class: #5                         // java/lang/Object
  interfaces: 1, fields: 0, methods: 4, attributes: 6
Constant pool:
   #1 = Utf8               org/sireum/Indexable
   #2 = Class              #1             // org/sireum/Indexable
   #3 = Utf8               <T:Ljava/lang/Object;>Ljava/lang/Object;Lorg/sireum/Immutable;
   #4 = Utf8               java/lang/Object
   #5 = Class              #4             // java/lang/Object
   #6 = Utf8               org/sireum/Immutable
   #7 = Class              #6             // org/sireum/Immutable
   #8 = Utf8               Indexable.scala
   #9 = Utf8               Lscala/reflect/ScalaSignature;
  #10 = Utf8               bytes
  #11 = Utf8               \u0006\u0005\t\rfa\u0002\u001d:!\u0003\r\nA\u0010\u0005\u0006\u0015\u00021\ta\u0013\u0005\u0006A\u00021\t!Y\u0004\u0006WfB\t\u0001\u001c\u0004\u0006qeB\t!\u001c\u0005\u0006]\u0012!\ta\u001c\u0004\ba\u0012\u0001\n1%\u0001r\u0011\u00151hA\"\u0001x\u000f\u001d\ty\u0001\u0002E\u0001\u0003#1q!!\u0006\u0005\u0011\u0003\t9\u0002\u0003\u0004o\u0013\u0011\u0005\u0011\u0011\u0004\u0005\b\u00037IA\u0011AA\u000f\u0011\u001d\tI/\u0003C\u0001\u0003W4a!!\u0006\u0005\u0005\u0005\r\u0002BCA\u001a\u001b\t\u0005\t\u0015!\u0003\u00026!1a.\u0004C\u0001\u0003\u0013B\u0001\"a\u0014\u000eA\u0003%\u0011Q\u0007\u0005\b\u0003#jA\u0011AA*\u0011\u001d\t)&\u0004C\u0001\u0003\'Bq!a\u0016\u000e\t\u0003\nI\u0006C\u0004\u0002l5!\t%!\u001c\t\u0015\u0005MT\u0002#b\u0001\n\u0003\n)\bC\u0004\u0002~5!\t%a \t\u000f\u0005mQ\u0002\"\u0001\u0002\f\"I\u0011qR\u0007\u0012\u0002\u0013\u0005\u0011\u0011\u0013\u0005\u000b\u0003Ok\u0001R1A\u0005B\u0005%\u0006B\u0002&\u000e\t\u0003\n9\r\u0003\u0004a\u001b\u0011\u0005\u00131[\u0004\b\u0003\u007f$\u0001\u0012\u0001B\u0001\r\u001d\u0011\u0019\u0001\u0002E\u0001\u0005\u000bAaA\\\u000f\u0005\u0002\t\u001d\u0001bBA\u000e;\u0011\u0005!\u0011\u0002\u0005\b\u0003SlB\u0011\u0001B6\r\u0019\u0011\u0019\u0001\u0002\u0002\u0003\u0010!Q\u00111G\u0011\u0003\u0002\u0003\u0006IAa\u0007\t\u0015\tu\u0011E!A!\u0002\u0013\u0011y\u0002\u0003\u0004oC\u0011\u0005!Q\u0005\u0005\t\u0003\u001f\n\u0003\u0015!\u0003\u0003\u001c!9\u0011\u0011K\u0011\u0005\u0002\t5\u0002bBA+C\u0011\u0005!Q\u0006\u0005\t\u0005_\t\u0003\u0015!\u0003\u0003 !9!\u0011G\u0011\u0005\u0002\tM\u0002b\u0002B\u001bC\u0011\u0005!1\u0007\u0005\b\u0003/\nC\u0011IA-\u0011\u001d\tY\'\tC!\u0003[B!\"a\u001d\"\u0011\u000b\u0007I\u0011IA;\u0011\u001d\ti(\tC!\u0005oAq!a\u0007\"\t\u0003\u0011Y\u0004C\u0005\u0002\u0010\u0006\n\n\u0011\"\u0001\u0003B!I!QI\u0011\u0012\u0002\u0013\u0005!q\t\u0005\u000b\u0003O\u000b\u0003R1A\u0005B\u0005%\u0006B\u0002&\"\t\u0003\u0012Y\u0005\u0003\u0004aC\u0011\u0005#\u0011\u000b\u0005\u0007m\u0006\"\tAa\u0016\t\u000f\tuD\u0001\"\u0001\u0003\u0000!9!q\u0012\u0003\u0005\u0002\tE%!C%oI\u0016D\u0018M\u00197f\u0015\tQ4(\u0001\u0004tSJ,W/\u001c\u0006\u0002y\u0005\u0019qN]4\u0004\u0001U\u0011qHT\n\u0004\u0001\u00013\u0005CA!E\u001b\u0005\u0011%\"A\"\u0002\u000bM\u001c\u0017\r\\1\n\u0005\u0015\u0013%AB!osJ+g\r\u0005\u0002H\u00116\t\u0011(\u0003\u0002Js\tI\u0011*\\7vi\u0006\u0014G.Z\u0001\u0003CR$\"\u0001T,\u0011\u00055sE\u0002\u0001\u0003\u0006\u001f\u0002\u0011\r\u0001\u0015\u0002\u0002)F\u0011\u0011\u000b\u0016\t\u0003\u0003JK!a\u0015\"\u0003\u000f9{G\u000f[5oOB\u0011\u0011)V\u0005\u0003-\n\u00131!\u00118z\u0011\u0015A\u0016\u00011\u0001Z\u0003\u0005I\u0007CA$[\u0013\tY\u0016HA\u0001[Q\t\tQ\f\u0005\u0002H=&\u0011q,\u000f\u0002\u0005aV\u0014X-A\u0002iCN$\"AY3\u0011\u0005\u001d\u001b\u0017B\u00013:\u0005\u0005\u0011\u0005\"\u0002-\u0003\u0001\u0004I\u0006F\u0001\u0002^Q\t\u0001\u0001\u000e\u0005\u0002HS&\u0011!.\u000f\u0002\u0004g&<\u0017!C%oI\u0016D\u0018M\u00197f!\t9Ea\u0005\u0002\u0005\u0001\u00061A(\u001b8jiz\"\u0012\u0001\u001c\u0002\u0004!>\u001cXC\u0001:v\'\u00111\u0001i\u001d$\u0011\u0007\u001d\u0003A\u000f\u0005\u0002Nk\u0012)qJ\u0002b\u0001!\u00061\u0001o\\:PaR$R\u0001_A\u0002\u0003\u000f\u00012aR=|\u0013\tQ\u0018H\u0001\u0004PaRLwN\u001c\t\u0003y~l\u0011! \u0006\u0003}f\nq!\\3tg\u0006<W-C\u0002\u0002\u0002u\u0014\u0001\u0002U8tSRLwN\u001c\u0005\u0007\u0003\u000b9\u0001\u0019A-\u0002\r=4gm]3u\u0011\u0019\tIa\u0002a\u00013\u00061A.\u001a8hi\"D#aB/)\u0005\u0019A\u0017aA%tuB\u0019\u00111C\u0005\u000e\u0003\u0011\u00111!S:{\'\tI\u0001\t\u0006\u0002\u0002\u0012\u0005)\u0011\r\u001d9msV!\u0011qDAr)\u0011\t\t#!:\u0011\u000b\u0005MQ\"!9\u0016\t\u0005\u0015\u00121F\n\u0007\u001b\u0001\u000b9#!\f\u0011\t\u001d\u0003\u0011\u0011\u0006\t\u0004\u001b\u0006-B!B(\u000e\u0005\u0004\u0001\u0006cA$\u00020%\u0019\u0011\u0011G\u001d\u0003\u0017\u0011\u000bG/\u0019;za\u0016\u001c\u0016nZ\u0001\u0005?~K7\u000f\u0005\u0004\u00028\u0005u\u0012\u0011\u0006\b\u0004\u000f\u0006e\u0012bAA\u001es\u00059\u0001/Y2lC\u001e,\u0017\u0002BA \u0003\u0003\u00121!S*[\u0013\u0011\t\u0019%!\u0012\u0003\u0019A\u000b7m[1hKR\u0013\u0018-\u001b;\u000b\u0007\u0005\u001d\u0013(A\u0005%S:$XM\u001d8bYR!\u00111JA\'!\u0015\t\u0019\"DA\u0015\u0011\u001d\t\u0019d\u0004a\u0001\u0003k\t1aX5t\u0003\tI7/\u0006\u0002\u00026\u0005)q-\u001a;Jg\u0006AAo\\*ue&tw\r\u0006\u0002\u0002\\A!\u0011QLA4\u001b\t\tyF\u0003\u0003\u0002b\u0005\r\u0014\u0001\u00027b]\u001eT!!!\u001a\u0002\t)\fg/Y\u0005\u0005\u0003S\nyF\u0001\u0004TiJLgnZ\u0001\u0007gR\u0014\u0018N\\4\u0016\u0005\u0005=\u0004cA$\u0002r%\u0019\u0011\u0011N\u001d\u0002\u0011!\f7\u000f[\"pI\u0016,\"!a\u001e\u0011\u0007\u0005\u000bI(C\u0002\u0002|\t\u00131!\u00138u\u0003\u0019)\u0017/^1mgR!\u0011\u0011QAD!\r\t\u00151Q\u0005\u0004\u0003\u000b\u0013%a\u0002\"p_2,\u0017M\u001c\u0005\u0007\u0003\u00133\u0002\u0019\u0001+\u0002\u0003=$B!a\u0013\u0002\u000e\"I\u0011\u0011K\f\u0011\u0002\u0003\u0007\u0011QG\u0001\u0010CB\u0004H.\u001f\u0013eK\u001a\fW\u000f\u001c;%cU\u0011\u00111\u0013\u0016\u0005\u0003k\t)j\u000b\u0002\u0002\u0018B!\u0011\u0011TAR\u001b\t\tYJ\u0003\u0003\u0002\u001e\u0006}\u0015!C;oG\",7m[3e\u0015\r\t\tKQ\u0001\u000bC:tw\u000e^1uS>t\u0017\u0002BAS\u00037\u0013\u0011#\u001e8dQ\u0016\u001c7.\u001a3WCJL\u0017M\\2f\u0003!!3m\u001c8uK:$XCAAV!\u0019\ti+a/\u0002B:!\u0011qVA]\u001d\u0011\t\t,a.\u000e\u0005\u0005M&bAA[{\u00051AH]8pizJ\u0011aQ\u0005\u0004\u0003w\u0011\u0015\u0002BA_\u0003\u007f\u00131aU3r\u0015\r\tYD\u0011\t\u0007\u0003\u0006\r\u00171\f+\n\u0007\u0005\u0015\'I\u0001\u0004UkBdWM\r\u000b\u0005\u0003S\tI\rC\u0003Y5\u0001\u0007\u0011\fK\u0002\u001b\u0003\u001b\u00042aRAh\u0013\r\t\t.\u000f\u0002\u000bgR\u0014\u0018n\u0019;qkJ,Gc\u00012\u0002V\")\u0001l\u0007a\u00013\"\u001a1$!4)\u00075\tY\u000eE\u0002H\u0003;L1!a8:\u0005!!\u0017\r^1usB,\u0007cA\'\u0002d\u0012)qj\u0003b\u0001!\"9\u0011\u0011K\u0006A\u0002\u0005\u001d\bCBA\u001c\u0003{\t\t/A\u0004v]\u0006\u0004\b\u000f\\=\u0016\t\u00055\u0018\u0011 \u000b\u0005\u0003_\fY\u0010E\u0003B\u0003c\f)0C\u0002\u0002t\n\u0013AaU8nKB1\u0011qGA\u001f\u0003o\u00042!TA}\t\u0015yEB1\u0001Q\u0011\u001d\tI\t\u0004a\u0001\u0003{\u0004R!a\u0005\u000e\u0003o\f!\"S:{\t>\u001c\u0017J\u001c4p!\r\t\u0019\"\b\u0002\u000b\u0013NTHi\\2J]\u001a|7CA\u000fA)\t\u0011\t!\u0006\u0003\u0003\f\t\rDC\u0002B\u0007\u0005K\u0012I\u0007E\u0003\u0002\u0014\u0005\u0012\t\'\u0006\u0003\u0003\u0012\te1CB\u0011A\u0005\'\ti\u0003E\u0003\u0003\u0016\u0019\u00119B\u0004\u0002H\u0007A\u0019QJ!\u0007\u0005\u000b=\u000b#\u0019\u0001)\u0011\r\u0005]\u0012Q\bB\f\u0003\u0019yv,\u001b8g_B\u0019AP!\t\n\u0007\t\rRPA\u0004E_\u000eLeNZ8\u0015\r\t\u001d\"\u0011\u0006B\u0016!\u0015\t\u0019\"\tB\f\u0011\u001d\t\u0019\u0004\na\u0001\u00057AqA!\b%\u0001\u0004\u0011y\"\u0006\u0002\u0003\u001c\u0005)q,\u001b8g_\u0006!\u0011N\u001c4p+\t\u0011y\"A\u0004hKRLeNZ8\u0015\t\u0005\u0005%\u0011\b\u0005\u0007\u0003\u0013s\u0003\u0019\u0001+\u0015\r\t\u001d\"Q\bB \u0011%\t\tf\fI\u0001\u0002\u0004\u0011Y\u0002C\u0005\u00032=\u0002\n\u00111\u0001\u0003 U\u0011!1\t\u0016\u0005\u00057\t)*A\bbaBd\u0017\u0010\n3fM\u0006,H\u000e\u001e\u00133+\t\u0011IE\u000b\u0003\u0003 \u0005UE\u0003\u0002B\f\u0005\u001bBQ\u0001W\u001aA\u0002eC3aMAg)\r\u0011\'1\u000b\u0005\u00061R\u0002\r!\u0017\u0015\u0004i\u00055G#\u0002=\u0003Z\tm\u0003BBA\u0003k\u0001\u0007\u0011\f\u0003\u0004\u0002\nU\u0002\r!\u0017\u0015\u0004k\u00055\u0007fA\u0011\u0002\\B\u0019QJa\u0019\u0005\u000b={\"\u0019\u0001)\t\u000f\u0005Es\u00041\u0001\u0003hA1\u0011qGA\u001f\u0005CBqA!\r \u0001\u0004\u0011y\"\u0006\u0003\u0003n\t]D\u0003\u0002B8\u0005s\u0002R!QAy\u0005c\u0002r!QAb\u0005g\u0012y\u0002\u0005\u0004\u00028\u0005u\"Q\u000f\t\u0004\u001b\n]D!B(!\u0005\u0004\u0001\u0006bBAEA\u0001\u0007!1\u0010\t\u0006\u0003\'\t#QO\u0001\bMJ|W.S:{+\u0011\u0011\tIa\"\u0015\t\t\r%\u0011\u0012\t\u0005\u000f\u0002\u0011)\tE\u0002N\u0005\u000f#Qa\u0014\u001cC\u0002ACq!!\u00157\u0001\u0004\u0011Y\t\u0005\u0004\u00028\u0005u\"Q\u0011\u0015\u0004m\u00055\u0017A\u00044s_6L5O\u001f#pG&sgm\\\u000b\u0005\u0005\'\u0013I\n\u0006\u0004\u0003\u0016\nm%q\u0014\t\u0006\u0005+1!q\u0013\t\u0004\u001b\neE!B(8\u0005\u0004\u0001\u0006bBA)o\u0001\u0007!Q\u0014\t\u0007\u0003o\tiDa&\t\u000f\tEr\u00071\u0001\u0003 !\u001aq\'!4
  #12 = Utf8               org/sireum/Indexable$Isz
  #13 = Class              #12            // org/sireum/Indexable$Isz
  #14 = Utf8               Isz
  #15 = Utf8               org/sireum/Indexable$Isz$
  #16 = Class              #15            // org/sireum/Indexable$Isz$
  #17 = Utf8               Isz$
  #18 = Utf8               org/sireum/Indexable$IszDocInfo
  #19 = Class              #18            // org/sireum/Indexable$IszDocInfo
  #20 = Utf8               IszDocInfo
  #21 = Utf8               org/sireum/Indexable$IszDocInfo$
  #22 = Class              #21            // org/sireum/Indexable$IszDocInfo$
  #23 = Utf8               IszDocInfo$
  #24 = Utf8               org/sireum/Indexable$Pos
  #25 = Class              #24            // org/sireum/Indexable$Pos
  #26 = Utf8               Pos
  #27 = Utf8               fromIszDocInfo
  #28 = Utf8               (Lorg/sireum/IS;Lorg/sireum/message/DocInfo;)Lorg/sireum/Indexable$Pos;
  #29 = Utf8               <T:Ljava/lang/Object;>(Lorg/sireum/IS<Lorg/sireum/Z;TT;>;Lorg/sireum/message/DocInfo;)Lorg/sireum/Indexable$Pos<TT;>;
  #30 = Utf8               is
  #31 = Utf8               info
  #32 = Utf8               org/sireum/Indexable$
  #33 = Class              #32            // org/sireum/Indexable$
  #34 = Utf8               MODULE$
  #35 = Utf8               Lorg/sireum/Indexable$;
  #36 = NameAndType        #34:#35        // MODULE$:Lorg/sireum/Indexable$;
  #37 = Fieldref           #33.#36        // org/sireum/Indexable$.MODULE$:Lorg/sireum/Indexable$;
  #38 = NameAndType        #27:#28        // fromIszDocInfo:(Lorg/sireum/IS;Lorg/sireum/message/DocInfo;)Lorg/sireum/Indexable$Pos;
  #39 = Methodref          #33.#38        // org/sireum/Indexable$.fromIszDocInfo:(Lorg/sireum/IS;Lorg/sireum/message/DocInfo;)Lorg/sireum/Indexable$Pos;
  #40 = Utf8               Lorg/sireum/IS;
  #41 = Utf8               Lorg/sireum/message/DocInfo;
  #42 = Utf8               fromIsz
  #43 = Utf8               (Lorg/sireum/IS;)Lorg/sireum/Indexable;
  #44 = Utf8               <T:Ljava/lang/Object;>(Lorg/sireum/IS<Lorg/sireum/Z;TT;>;)Lorg/sireum/Indexable<TT;>;
  #45 = NameAndType        #42:#43        // fromIsz:(Lorg/sireum/IS;)Lorg/sireum/Indexable;
  #46 = Methodref          #33.#45        // org/sireum/Indexable$.fromIsz:(Lorg/sireum/IS;)Lorg/sireum/Indexable;
  #47 = Utf8               at
  #48 = Utf8               (Lorg/sireum/Z;)Ljava/lang/Object;
  #49 = Utf8               (Lorg/sireum/Z;)TT;
  #50 = Utf8               i
  #51 = Utf8               has
  #52 = Utf8               (Lorg/sireum/Z;)Z
  #53 = Utf8               Code
  #54 = Utf8               LocalVariableTable
  #55 = Utf8               Signature
  #56 = Utf8               MethodParameters
  #57 = Utf8               InnerClasses
  #58 = Utf8               SourceFile
  #59 = Utf8               RuntimeVisibleAnnotations
  #60 = Utf8               ScalaInlineInfo
  #61 = Utf8               ScalaSig
{
  public static <T extends java.lang.Object> org.sireum.Indexable$Pos<T> fromIszDocInfo(org.sireum.IS<org.sireum.Z, T>, org.sireum.message.DocInfo);
    descriptor: (Lorg/sireum/IS;Lorg/sireum/message/DocInfo;)Lorg/sireum/Indexable$Pos;
    flags: (0x0009) ACC_PUBLIC, ACC_STATIC
    Code:
      stack=3, locals=2, args_size=2
         0: getstatic     #37                 // Field org/sireum/Indexable$.MODULE$:Lorg/sireum/Indexable$;
         3: aload_0
         4: aload_1
         5: invokevirtual #39                 // Method org/sireum/Indexable$.fromIszDocInfo:(Lorg/sireum/IS;Lorg/sireum/message/DocInfo;)Lorg/sireum/Indexable$Pos;
         8: areturn
      LocalVariableTable:
        Start  Length  Slot  Name   Signature
            0       9     0    is   Lorg/sireum/IS;
            0       9     1  info   Lorg/sireum/message/DocInfo;
    Signature: #29                          // <T:Ljava/lang/Object;>(Lorg/sireum/IS<Lorg/sireum/Z;TT;>;Lorg/sireum/message/DocInfo;)Lorg/sireum/Indexable$Pos<TT;>;
    MethodParameters:
      Name                           Flags
      is                             final
      info                           final

  public static <T extends java.lang.Object> org.sireum.Indexable<T> fromIsz(org.sireum.IS<org.sireum.Z, T>);
    descriptor: (Lorg/sireum/IS;)Lorg/sireum/Indexable;
    flags: (0x0009) ACC_PUBLIC, ACC_STATIC
    Code:
      stack=2, locals=1, args_size=1
         0: getstatic     #37                 // Field org/sireum/Indexable$.MODULE$:Lorg/sireum/Indexable$;
         3: aload_0
         4: invokevirtual #46                 // Method org/sireum/Indexable$.fromIsz:(Lorg/sireum/IS;)Lorg/sireum/Indexable;
         7: areturn
      LocalVariableTable:
        Start  Length  Slot  Name   Signature
            0       8     0    is   Lorg/sireum/IS;
    Signature: #44                          // <T:Ljava/lang/Object;>(Lorg/sireum/IS<Lorg/sireum/Z;TT;>;)Lorg/sireum/Indexable<TT;>;
    MethodParameters:
      Name                           Flags
      is                             final

  public abstract T at(org.sireum.Z);
    descriptor: (Lorg/sireum/Z;)Ljava/lang/Object;
    flags: (0x0401) ACC_PUBLIC, ACC_ABSTRACT
    Signature: #49                          // (Lorg/sireum/Z;)TT;
    MethodParameters:
      Name                           Flags
      i                              final

  public abstract boolean has(org.sireum.Z);
    descriptor: (Lorg/sireum/Z;)Z
    flags: (0x0401) ACC_PUBLIC, ACC_ABSTRACT
    MethodParameters:
      Name                           Flags
      i                              final
}
InnerClasses:
  public static final #14= #13 of #2;     // Isz=class org/sireum/Indexable$Isz of class org/sireum/Indexable
  public static #17= #16 of #2;           // Isz$=class org/sireum/Indexable$Isz$ of class org/sireum/Indexable
  public static final #20= #19 of #2;     // IszDocInfo=class org/sireum/Indexable$IszDocInfo of class org/sireum/Indexable
  public static #23= #22 of #2;           // IszDocInfo$=class org/sireum/Indexable$IszDocInfo$ of class org/sireum/Indexable
  public static #26= #25 of #2;           // Pos=class org/sireum/Indexable$Pos of class org/sireum/Indexable
Signature: #3                           // <T:Ljava/lang/Object;>Ljava/lang/Object;Lorg/sireum/Immutable;
SourceFile: "Indexable.scala"
RuntimeVisibleAnnotations:
  0: #9(#10=s#11)
    scala.reflect.ScalaSignature(
      bytes="\u0006\u0005\t\rfa\u0002\u001d:!\u0003\r\nA\u0010\u0005\u0006\u0015\u00021\ta\u0013\u0005\u0006A\u00021\t!Y\u0004\u0006WfB\t\u0001\u001c\u0004\u0006qeB\t!\u001c\u0005\u0006]\u0012!\ta\u001c\u0004\ba\u0012\u0001\n1%\u0001r\u0011\u00151hA\"\u0001x\u000f\u001d\ty\u0001\u0002E\u0001\u0003#1q!!\u0006\u0005\u0011\u0003\t9\u0002\u0003\u0004o\u0013\u0011\u0005\u0011\u0011\u0004\u0005\b\u00037IA\u0011AA\u000f\u0011\u001d\tI/\u0003C\u0001\u0003W4a!!\u0006\u0005\u0005\u0005\r\u0002BCA\u001a\u001b\t\u0005\t\u0015!\u0003\u00026!1a.\u0004C\u0001\u0003\u0013B\u0001\"a\u0014\u000eA\u0003%\u0011Q\u0007\u0005\b\u0003#jA\u0011AA*\u0011\u001d\t)&\u0004C\u0001\u0003\'Bq!a\u0016\u000e\t\u0003\nI\u0006C\u0004\u0002l5!\t%!\u001c\t\u0015\u0005MT\u0002#b\u0001\n\u0003\n)\bC\u0004\u0002~5!\t%a \t\u000f\u0005mQ\u0002\"\u0001\u0002\f\"I\u0011qR\u0007\u0012\u0002\u0013\u0005\u0011\u0011\u0013\u0005\u000b\u0003Ok\u0001R1A\u0005B\u0005%\u0006B\u0002&\u000e\t\u0003\n9\r\u0003\u0004a\u001b\u0011\u0005\u00131[\u0004\b\u0003\u007f$\u0001\u0012\u0001B\u0001\r\u001d\u0011\u0019\u0001\u0002E\u0001\u0005\u000bAaA\\\u000f\u0005\u0002\t\u001d\u0001bBA\u000e;\u0011\u0005!\u0011\u0002\u0005\b\u0003SlB\u0011\u0001B6\r\u0019\u0011\u0019\u0001\u0002\u0002\u0003\u0010!Q\u00111G\u0011\u0003\u0002\u0003\u0006IAa\u0007\t\u0015\tu\u0011E!A!\u0002\u0013\u0011y\u0002\u0003\u0004oC\u0011\u0005!Q\u0005\u0005\t\u0003\u001f\n\u0003\u0015!\u0003\u0003\u001c!9\u0011\u0011K\u0011\u0005\u0002\t5\u0002bBA+C\u0011\u0005!Q\u0006\u0005\t\u0005_\t\u0003\u0015!\u0003\u0003 !9!\u0011G\u0011\u0005\u0002\tM\u0002b\u0002B\u001bC\u0011\u0005!1\u0007\u0005\b\u0003/\nC\u0011IA-\u0011\u001d\tY\'\tC!\u0003[B!\"a\u001d\"\u0011\u000b\u0007I\u0011IA;\u0011\u001d\ti(\tC!\u0005oAq!a\u0007\"\t\u0003\u0011Y\u0004C\u0005\u0002\u0010\u0006\n\n\u0011\"\u0001\u0003B!I!QI\u0011\u0012\u0002\u0013\u0005!q\t\u0005\u000b\u0003O\u000b\u0003R1A\u0005B\u0005%\u0006B\u0002&\"\t\u0003\u0012Y\u0005\u0003\u0004aC\u0011\u0005#\u0011\u000b\u0005\u0007m\u0006\"\tAa\u0016\t\u000f\tuD\u0001\"\u0001\u0003\u0000!9!q\u0012\u0003\u0005\u0002\tE%!C%oI\u0016D\u0018M\u00197f\u0015\tQ4(\u0001\u0004tSJ,W/\u001c\u0006\u0002y\u0005\u0019qN]4\u0004\u0001U\u0011qHT\n\u0004\u0001\u00013\u0005CA!E\u001b\u0005\u0011%\"A\"\u0002\u000bM\u001c\u0017\r\\1\n\u0005\u0015\u0013%AB!osJ+g\r\u0005\u0002H\u00116\t\u0011(\u0003\u0002Js\tI\u0011*\\7vi\u0006\u0014G.Z\u0001\u0003CR$\"\u0001T,\u0011\u00055sE\u0002\u0001\u0003\u0006\u001f\u0002\u0011\r\u0001\u0015\u0002\u0002)F\u0011\u0011\u000b\u0016\t\u0003\u0003JK!a\u0015\"\u0003\u000f9{G\u000f[5oOB\u0011\u0011)V\u0005\u0003-\n\u00131!\u00118z\u0011\u0015A\u0016\u00011\u0001Z\u0003\u0005I\u0007CA$[\u0013\tY\u0016HA\u0001[Q\t\tQ\f\u0005\u0002H=&\u0011q,\u000f\u0002\u0005aV\u0014X-A\u0002iCN$\"AY3\u0011\u0005\u001d\u001b\u0017B\u00013:\u0005\u0005\u0011\u0005\"\u0002-\u0003\u0001\u0004I\u0006F\u0001\u0002^Q\t\u0001\u0001\u000e\u0005\u0002HS&\u0011!.\u000f\u0002\u0004g&<\u0017!C%oI\u0016D\u0018M\u00197f!\t9Ea\u0005\u0002\u0005\u0001\u00061A(\u001b8jiz\"\u0012\u0001\u001c\u0002\u0004!>\u001cXC\u0001:v\'\u00111\u0001i\u001d$\u0011\u0007\u001d\u0003A\u000f\u0005\u0002Nk\u0012)qJ\u0002b\u0001!\u00061\u0001o\\:PaR$R\u0001_A\u0002\u0003\u000f\u00012aR=|\u0013\tQ\u0018H\u0001\u0004PaRLwN\u001c\t\u0003y~l\u0011! \u0006\u0003}f\nq!\\3tg\u0006<W-C\u0002\u0002\u0002u\u0014\u0001\u0002U8tSRLwN\u001c\u0005\u0007\u0003\u000b9\u0001\u0019A-\u0002\r=4gm]3u\u0011\u0019\tIa\u0002a\u00013\u00061A.\u001a8hi\"D#aB/)\u0005\u0019A\u0017aA%tuB\u0019\u00111C\u0005\u000e\u0003\u0011\u00111!S:{\'\tI\u0001\t\u0006\u0002\u0002\u0012\u0005)\u0011\r\u001d9msV!\u0011qDAr)\u0011\t\t#!:\u0011\u000b\u0005MQ\"!9\u0016\t\u0005\u0015\u00121F\n\u0007\u001b\u0001\u000b9#!\f\u0011\t\u001d\u0003\u0011\u0011\u0006\t\u0004\u001b\u0006-B!B(\u000e\u0005\u0004\u0001\u0006cA$\u00020%\u0019\u0011\u0011G\u001d\u0003\u0017\u0011\u000bG/\u0019;za\u0016\u001c\u0016nZ\u0001\u0005?~K7\u000f\u0005\u0004\u00028\u0005u\u0012\u0011\u0006\b\u0004\u000f\u0006e\u0012bAA\u001es\u00059\u0001/Y2lC\u001e,\u0017\u0002BA \u0003\u0003\u00121!S*[\u0013\u0011\t\u0019%!\u0012\u0003\u0019A\u000b7m[1hKR\u0013\u0018-\u001b;\u000b\u0007\u0005\u001d\u0013(A\u0005%S:$XM\u001d8bYR!\u00111JA\'!\u0015\t\u0019\"DA\u0015\u0011\u001d\t\u0019d\u0004a\u0001\u0003k\t1aX5t\u0003\tI7/\u0006\u0002\u00026\u0005)q-\u001a;Jg\u0006AAo\\*ue&tw\r\u0006\u0002\u0002\\A!\u0011QLA4\u001b\t\tyF\u0003\u0003\u0002b\u0005\r\u0014\u0001\u00027b]\u001eT!!!\u001a\u0002\t)\fg/Y\u0005\u0005\u0003S\nyF\u0001\u0004TiJLgnZ\u0001\u0007gR\u0014\u0018N\\4\u0016\u0005\u0005=\u0004cA$\u0002r%\u0019\u0011\u0011N\u001d\u0002\u0011!\f7\u000f[\"pI\u0016,\"!a\u001e\u0011\u0007\u0005\u000bI(C\u0002\u0002|\t\u00131!\u00138u\u0003\u0019)\u0017/^1mgR!\u0011\u0011QAD!\r\t\u00151Q\u0005\u0004\u0003\u000b\u0013%a\u0002\"p_2,\u0017M\u001c\u0005\u0007\u0003\u00133\u0002\u0019\u0001+\u0002\u0003=$B!a\u0013\u0002\u000e\"I\u0011\u0011K\f\u0011\u0002\u0003\u0007\u0011QG\u0001\u0010CB\u0004H.\u001f\u0013eK\u001a\fW\u000f\u001c;%cU\u0011\u00111\u0013\u0016\u0005\u0003k\t)j\u000b\u0002\u0002\u0018B!\u0011\u0011TAR\u001b\t\tYJ\u0003\u0003\u0002\u001e\u0006}\u0015!C;oG\",7m[3e\u0015\r\t\tKQ\u0001\u000bC:tw\u000e^1uS>t\u0017\u0002BAS\u00037\u0013\u0011#\u001e8dQ\u0016\u001c7.\u001a3WCJL\u0017M\\2f\u0003!!3m\u001c8uK:$XCAAV!\u0019\ti+a/\u0002B:!\u0011qVA]\u001d\u0011\t\t,a.\u000e\u0005\u0005M&bAA[{\u00051AH]8pizJ\u0011aQ\u0005\u0004\u0003w\u0011\u0015\u0002BA_\u0003\u007f\u00131aU3r\u0015\r\tYD\u0011\t\u0007\u0003\u0006\r\u00171\f+\n\u0007\u0005\u0015\'I\u0001\u0004UkBdWM\r\u000b\u0005\u0003S\tI\rC\u0003Y5\u0001\u0007\u0011\fK\u0002\u001b\u0003\u001b\u00042aRAh\u0013\r\t\t.\u000f\u0002\u000bgR\u0014\u0018n\u0019;qkJ,Gc\u00012\u0002V\")\u0001l\u0007a\u00013\"\u001a1$!4)\u00075\tY\u000eE\u0002H\u0003;L1!a8:\u0005!!\u0017\r^1usB,\u0007cA\'\u0002d\u0012)qj\u0003b\u0001!\"9\u0011\u0011K\u0006A\u0002\u0005\u001d\bCBA\u001c\u0003{\t\t/A\u0004v]\u0006\u0004\b\u000f\\=\u0016\t\u00055\u0018\u0011 \u000b\u0005\u0003_\fY\u0010E\u0003B\u0003c\f)0C\u0002\u0002t\n\u0013AaU8nKB1\u0011qGA\u001f\u0003o\u00042!TA}\t\u0015yEB1\u0001Q\u0011\u001d\tI\t\u0004a\u0001\u0003{\u0004R!a\u0005\u000e\u0003o\f!\"S:{\t>\u001c\u0017J\u001c4p!\r\t\u0019\"\b\u0002\u000b\u0013NTHi\\2J]\u001a|7CA\u000fA)\t\u0011\t!\u0006\u0003\u0003\f\t\rDC\u0002B\u0007\u0005K\u0012I\u0007E\u0003\u0002\u0014\u0005\u0012\t\'\u0006\u0003\u0003\u0012\te1CB\u0011A\u0005\'\ti\u0003E\u0003\u0003\u0016\u0019\u00119B\u0004\u0002H\u0007A\u0019QJ!\u0007\u0005\u000b=\u000b#\u0019\u0001)\u0011\r\u0005]\u0012Q\bB\f\u0003\u0019yv,\u001b8g_B\u0019AP!\t\n\u0007\t\rRPA\u0004E_\u000eLeNZ8\u0015\r\t\u001d\"\u0011\u0006B\u0016!\u0015\t\u0019\"\tB\f\u0011\u001d\t\u0019\u0004\na\u0001\u00057AqA!\b%\u0001\u0004\u0011y\"\u0006\u0002\u0003\u001c\u0005)q,\u001b8g_\u0006!\u0011N\u001c4p+\t\u0011y\"A\u0004hKRLeNZ8\u0015\t\u0005\u0005%\u0011\b\u0005\u0007\u0003\u0013s\u0003\u0019\u0001+\u0015\r\t\u001d\"Q\bB \u0011%\t\tf\fI\u0001\u0002\u0004\u0011Y\u0002C\u0005\u00032=\u0002\n\u00111\u0001\u0003 U\u0011!1\t\u0016\u0005\u00057\t)*A\bbaBd\u0017\u0010\n3fM\u0006,H\u000e\u001e\u00133+\t\u0011IE\u000b\u0003\u0003 \u0005UE\u0003\u0002B\f\u0005\u001bBQ\u0001W\u001aA\u0002eC3aMAg)\r\u0011\'1\u000b\u0005\u00061R\u0002\r!\u0017\u0015\u0004i\u00055G#\u0002=\u0003Z\tm\u0003BBA\u0003k\u0001\u0007\u0011\f\u0003\u0004\u0002\nU\u0002\r!\u0017\u0015\u0004k\u00055\u0007fA\u0011\u0002\\B\u0019QJa\u0019\u0005\u000b={\"\u0019\u0001)\t\u000f\u0005Es\u00041\u0001\u0003hA1\u0011qGA\u001f\u0005CBqA!\r \u0001\u0004\u0011y\"\u0006\u0003\u0003n\t]D\u0003\u0002B8\u0005s\u0002R!QAy\u0005c\u0002r!QAb\u0005g\u0012y\u0002\u0005\u0004\u00028\u0005u\"Q\u000f\t\u0004\u001b\n]D!B(!\u0005\u0004\u0001\u0006bBAEA\u0001\u0007!1\u0010\t\u0006\u0003\'\t#QO\u0001\bMJ|W.S:{+\u0011\u0011\tIa\"\u0015\t\t\r%\u0011\u0012\t\u0005\u000f\u0002\u0011)\tE\u0002N\u0005\u000f#Qa\u0014\u001cC\u0002ACq!!\u00157\u0001\u0004\u0011Y\t\u0005\u0004\u00028\u0005u\"Q\u0011\u0015\u0004m\u00055\u0017A\u00044s_6L5O\u001f#pG&sgm\\\u000b\u0005\u0005\'\u0013I\n\u0006\u0004\u0003\u0016\nm%q\u0014\t\u0006\u0005+1!q\u0013\t\u0004\u001b\neE!B(8\u0005\u0004\u0001\u0006bBA)o\u0001\u0007!Q\u0014\t\u0007\u0003o\tiDa&\t\u000f\tEr\u00071\u0001\u0003 !\u001aq\'!4"
    )
  ScalaInlineInfo: length = 0xE (unknown attribute)
   01 00 00 02 00 2F 00 30 00 00 33 00 34 00
  ScalaSig: length = 0x3 (unknown attribute)
   05 02 00
