Classfile /Users/mw/Projects/slang-braindump/.jar/jar8/assemble/slang-braindump/assemble/content/org/sireum/Jen$Internal$Sliced$.class
  Last modified May 29, 2022; size 1639 bytes
  SHA-256 checksum f02676506ba327b7f9ffe403c584fece0a80f110719538f7e0df7a099f3d2d3e
  Compiled from "Jen.scala"
public class org.sireum.Jen$Internal$Sliced$
  minor version: 0
  major version: 52
  flags: (0x0021) ACC_PUBLIC, ACC_SUPER
  this_class: #2                          // org/sireum/Jen$Internal$Sliced$
  super_class: #4                         // java/lang/Object
  interfaces: 0, fields: 1, methods: 4, attributes: 4
Constant pool:
   #1 = Utf8               org/sireum/Jen$Internal$Sliced$
   #2 = Class              #1             // org/sireum/Jen$Internal$Sliced$
   #3 = Utf8               java/lang/Object
   #4 = Class              #3             // java/lang/Object
   #5 = Utf8               Jen.scala
   #6 = Utf8               org/sireum/Jen$Internal$
   #7 = Class              #6             // org/sireum/Jen$Internal$
   #8 = Utf8               org/sireum/Jen
   #9 = Class              #8             // org/sireum/Jen
  #10 = Utf8               Internal$
  #11 = Utf8               org/sireum/Jen$Internal$Sliced
  #12 = Class              #11            // org/sireum/Jen$Internal$Sliced
  #13 = Utf8               Sliced
  #14 = Utf8               Sliced$
  #15 = Utf8               MODULE$
  #16 = Utf8               Lorg/sireum/Jen$Internal$Sliced$;
  #17 = Utf8               <clinit>
  #18 = Utf8               ()V
  #19 = Utf8               <init>
  #20 = NameAndType        #19:#18        // "<init>":()V
  #21 = Methodref          #2.#20         // org/sireum/Jen$Internal$Sliced$."<init>":()V
  #22 = NameAndType        #15:#16        // MODULE$:Lorg/sireum/Jen$Internal$Sliced$;
  #23 = Fieldref           #2.#22         // org/sireum/Jen$Internal$Sliced$.MODULE$:Lorg/sireum/Jen$Internal$Sliced$;
  #24 = Utf8               apply
  #25 = Utf8               (Lorg/sireum/Jen;Lorg/sireum/Z;Lorg/sireum/Z;)Lorg/sireum/Jen$Internal$Sliced;
  #26 = Utf8               <T:Ljava/lang/Object;>(Lorg/sireum/Jen<TT;>;Lorg/sireum/Z;Lorg/sireum/Z;)Lorg/sireum/Jen$Internal$Sliced<TT;>;
  #27 = Utf8               gen
  #28 = Utf8               start
  #29 = Utf8               end
  #30 = Utf8               (Lorg/sireum/Jen;Lorg/sireum/Z;Lorg/sireum/Z;)V
  #31 = NameAndType        #19:#30        // "<init>":(Lorg/sireum/Jen;Lorg/sireum/Z;Lorg/sireum/Z;)V
  #32 = Methodref          #12.#31        // org/sireum/Jen$Internal$Sliced."<init>":(Lorg/sireum/Jen;Lorg/sireum/Z;Lorg/sireum/Z;)V
  #33 = Utf8               this
  #34 = Utf8               Lorg/sireum/Jen;
  #35 = Utf8               Lorg/sireum/Z;
  #36 = Utf8               unapply
  #37 = Utf8               (Lorg/sireum/Jen$Internal$Sliced;)Lscala/Some;
  #38 = Utf8               <T:Ljava/lang/Object;>(Lorg/sireum/Jen$Internal$Sliced<TT;>;)Lscala/Some<Lscala/Tuple3<Lorg/sireum/Jen<TT;>;Lorg/sireum/Z;Lorg/sireum/Z;>;>;
  #39 = Utf8               o
  #40 = Utf8               scala/Some
  #41 = Class              #40            // scala/Some
  #42 = Utf8               scala/Tuple3
  #43 = Class              #42            // scala/Tuple3
  #44 = Utf8               ()Lorg/sireum/Jen;
  #45 = NameAndType        #27:#44        // gen:()Lorg/sireum/Jen;
  #46 = Methodref          #12.#45        // org/sireum/Jen$Internal$Sliced.gen:()Lorg/sireum/Jen;
  #47 = Utf8               ()Lorg/sireum/Z;
  #48 = NameAndType        #28:#47        // start:()Lorg/sireum/Z;
  #49 = Methodref          #12.#48        // org/sireum/Jen$Internal$Sliced.start:()Lorg/sireum/Z;
  #50 = NameAndType        #29:#47        // end:()Lorg/sireum/Z;
  #51 = Methodref          #12.#50        // org/sireum/Jen$Internal$Sliced.end:()Lorg/sireum/Z;
  #52 = Utf8               (Ljava/lang/Object;Ljava/lang/Object;Ljava/lang/Object;)V
  #53 = NameAndType        #19:#52        // "<init>":(Ljava/lang/Object;Ljava/lang/Object;Ljava/lang/Object;)V
  #54 = Methodref          #43.#53        // scala/Tuple3."<init>":(Ljava/lang/Object;Ljava/lang/Object;Ljava/lang/Object;)V
  #55 = Utf8               (Ljava/lang/Object;)V
  #56 = NameAndType        #19:#55        // "<init>":(Ljava/lang/Object;)V
  #57 = Methodref          #41.#56        // scala/Some."<init>":(Ljava/lang/Object;)V
  #58 = Utf8               Lorg/sireum/Jen$Internal$Sliced;
  #59 = Methodref          #4.#20         // java/lang/Object."<init>":()V
  #60 = Utf8               Code
  #61 = Utf8               LineNumberTable
  #62 = Utf8               LocalVariableTable
  #63 = Utf8               Signature
  #64 = Utf8               MethodParameters
  #65 = Utf8               InnerClasses
  #66 = Utf8               SourceFile
  #67 = Utf8               ScalaInlineInfo
  #68 = Utf8               Scala
{
  public static final org.sireum.Jen$Internal$Sliced$ MODULE$;
    descriptor: Lorg/sireum/Jen$Internal$Sliced$;
    flags: (0x0019) ACC_PUBLIC, ACC_STATIC, ACC_FINAL

  public static {};
    descriptor: ()V
    flags: (0x0009) ACC_PUBLIC, ACC_STATIC
    Code:
      stack=2, locals=0, args_size=0
         0: new           #2                  // class org/sireum/Jen$Internal$Sliced$
         3: dup
         4: invokespecial #21                 // Method "<init>":()V
         7: putstatic     #23                 // Field MODULE$:Lorg/sireum/Jen$Internal$Sliced$;
        10: return
      LineNumberTable:
        line 360: 0

  public <T extends java.lang.Object> org.sireum.Jen$Internal$Sliced<T> apply(org.sireum.Jen<T>, org.sireum.Z, org.sireum.Z);
    descriptor: (Lorg/sireum/Jen;Lorg/sireum/Z;Lorg/sireum/Z;)Lorg/sireum/Jen$Internal$Sliced;
    flags: (0x0001) ACC_PUBLIC
    Code:
      stack=5, locals=4, args_size=4
         0: new           #12                 // class org/sireum/Jen$Internal$Sliced
         3: dup
         4: aload_1
         5: aload_2
         6: aload_3
         7: invokespecial #32                 // Method org/sireum/Jen$Internal$Sliced."<init>":(Lorg/sireum/Jen;Lorg/sireum/Z;Lorg/sireum/Z;)V
        10: areturn
      LineNumberTable:
        line 360: 0
      LocalVariableTable:
        Start  Length  Slot  Name   Signature
            0      11     0  this   Lorg/sireum/Jen$Internal$Sliced$;
            0      11     1   gen   Lorg/sireum/Jen;
            0      11     2 start   Lorg/sireum/Z;
            0      11     3   end   Lorg/sireum/Z;
    Signature: #26                          // <T:Ljava/lang/Object;>(Lorg/sireum/Jen<TT;>;Lorg/sireum/Z;Lorg/sireum/Z;)Lorg/sireum/Jen$Internal$Sliced<TT;>;
    MethodParameters:
      Name                           Flags
      gen                            final
      start                          final
      end                            final

  public <T extends java.lang.Object> scala.Some<scala.Tuple3<org.sireum.Jen<T>, org.sireum.Z, org.sireum.Z>> unapply(org.sireum.Jen$Internal$Sliced<T>);
    descriptor: (Lorg/sireum/Jen$Internal$Sliced;)Lscala/Some;
    flags: (0x0001) ACC_PUBLIC
    Code:
      stack=7, locals=2, args_size=2
         0: new           #41                 // class scala/Some
         3: dup
         4: new           #43                 // class scala/Tuple3
         7: dup
         8: aload_1
         9: invokevirtual #46                 // Method org/sireum/Jen$Internal$Sliced.gen:()Lorg/sireum/Jen;
        12: aload_1
        13: invokevirtual #49                 // Method org/sireum/Jen$Internal$Sliced.start:()Lorg/sireum/Z;
        16: aload_1
        17: invokevirtual #51                 // Method org/sireum/Jen$Internal$Sliced.end:()Lorg/sireum/Z;
        20: invokespecial #54                 // Method scala/Tuple3."<init>":(Ljava/lang/Object;Ljava/lang/Object;Ljava/lang/Object;)V
        23: invokespecial #57                 // Method scala/Some."<init>":(Ljava/lang/Object;)V
        26: areturn
      LineNumberTable:
        line 360: 0
      LocalVariableTable:
        Start  Length  Slot  Name   Signature
            0      27     0  this   Lorg/sireum/Jen$Internal$Sliced$;
            0      27     1     o   Lorg/sireum/Jen$Internal$Sliced;
    Signature: #38                          // <T:Ljava/lang/Object;>(Lorg/sireum/Jen$Internal$Sliced<TT;>;)Lscala/Some<Lscala/Tuple3<Lorg/sireum/Jen<TT;>;Lorg/sireum/Z;Lorg/sireum/Z;>;>;
    MethodParameters:
      Name                           Flags
      o                              final

  public org.sireum.Jen$Internal$Sliced$();
    descriptor: ()V
    flags: (0x0001) ACC_PUBLIC
    Code:
      stack=1, locals=1, args_size=1
         0: aload_0
         1: invokespecial #59                 // Method java/lang/Object."<init>":()V
         4: return
      LineNumberTable:
        line 360: 0
      LocalVariableTable:
        Start  Length  Slot  Name   Signature
            0       5     0  this   Lorg/sireum/Jen$Internal$Sliced$;
}
InnerClasses:
  public static #10= #7 of #9;            // Internal$=class org/sireum/Jen$Internal$ of class org/sireum/Jen
  public static final #13= #12 of #7;     // Sliced=class org/sireum/Jen$Internal$Sliced of class org/sireum/Jen$Internal$
  public static #14= #2 of #7;            // Sliced$=class org/sireum/Jen$Internal$Sliced$ of class org/sireum/Jen$Internal$
SourceFile: "Jen.scala"
  ScalaInlineInfo: length = 0x13 (unknown attribute)
   01 01 00 03 00 13 00 12 01 00 18 00 19 01 00 24
   00 25 01
  Scala: length = 0x0 (unknown attribute)

