Classfile /Users/mw/Projects/slang-braindump/.jar/jar8/assemble/slang-braindump/assemble/content/org/sireum/Jen$Internal$MapImpl$.class
  Last modified May 29, 2022; size 1368 bytes
  SHA-256 checksum d4d903e633e4a1fd9bec2feac2f2387924e556ed36a57972b3a1ad2a311e633a
  Compiled from "Jen.scala"
public class org.sireum.Jen$Internal$MapImpl$
  minor version: 0
  major version: 52
  flags: (0x0021) ACC_PUBLIC, ACC_SUPER
  this_class: #2                          // org/sireum/Jen$Internal$MapImpl$
  super_class: #4                         // java/lang/Object
  interfaces: 0, fields: 1, methods: 4, attributes: 4
Constant pool:
   #1 = Utf8               org/sireum/Jen$Internal$MapImpl$
   #2 = Class              #1             // org/sireum/Jen$Internal$MapImpl$
   #3 = Utf8               java/lang/Object
   #4 = Class              #3             // java/lang/Object
   #5 = Utf8               Jen.scala
   #6 = Utf8               org/sireum/Jen$Internal$
   #7 = Class              #6             // org/sireum/Jen$Internal$
   #8 = Utf8               org/sireum/Jen
   #9 = Class              #8             // org/sireum/Jen
  #10 = Utf8               Internal$
  #11 = Utf8               org/sireum/Jen$Internal$MapImpl
  #12 = Class              #11            // org/sireum/Jen$Internal$MapImpl
  #13 = Utf8               MapImpl
  #14 = Utf8               MapImpl$
  #15 = Utf8               MODULE$
  #16 = Utf8               Lorg/sireum/Jen$Internal$MapImpl$;
  #17 = Utf8               <clinit>
  #18 = Utf8               ()V
  #19 = Utf8               <init>
  #20 = NameAndType        #19:#18        // "<init>":()V
  #21 = Methodref          #2.#20         // org/sireum/Jen$Internal$MapImpl$."<init>":()V
  #22 = NameAndType        #15:#16        // MODULE$:Lorg/sireum/Jen$Internal$MapImpl$;
  #23 = Fieldref           #2.#22         // org/sireum/Jen$Internal$MapImpl$.MODULE$:Lorg/sireum/Jen$Internal$MapImpl$;
  #24 = Utf8               apply
  #25 = Utf8               (Lorg/sireum/Map;)Lorg/sireum/Jen$Internal$MapImpl;
  #26 = Utf8               <K:Ljava/lang/Object;T:Ljava/lang/Object;>(Lorg/sireum/Map<TK;TT;>;)Lorg/sireum/Jen$Internal$MapImpl<TK;TT;>;
  #27 = Utf8               m
  #28 = Utf8               (Lorg/sireum/Map;)V
  #29 = NameAndType        #19:#28        // "<init>":(Lorg/sireum/Map;)V
  #30 = Methodref          #12.#29        // org/sireum/Jen$Internal$MapImpl."<init>":(Lorg/sireum/Map;)V
  #31 = Utf8               this
  #32 = Utf8               Lorg/sireum/Map;
  #33 = Utf8               unapply
  #34 = Utf8               (Lorg/sireum/Jen$Internal$MapImpl;)Lscala/Some;
  #35 = Utf8               <K:Ljava/lang/Object;T:Ljava/lang/Object;>(Lorg/sireum/Jen$Internal$MapImpl<TK;TT;>;)Lscala/Some<Lorg/sireum/Map<TK;TT;>;>;
  #36 = Utf8               o
  #37 = Utf8               scala/Some
  #38 = Class              #37            // scala/Some
  #39 = Utf8               ()Lorg/sireum/Map;
  #40 = NameAndType        #27:#39        // m:()Lorg/sireum/Map;
  #41 = Methodref          #12.#40        // org/sireum/Jen$Internal$MapImpl.m:()Lorg/sireum/Map;
  #42 = Utf8               (Ljava/lang/Object;)V
  #43 = NameAndType        #19:#42        // "<init>":(Ljava/lang/Object;)V
  #44 = Methodref          #38.#43        // scala/Some."<init>":(Ljava/lang/Object;)V
  #45 = Utf8               Lorg/sireum/Jen$Internal$MapImpl;
  #46 = Methodref          #4.#20         // java/lang/Object."<init>":()V
  #47 = Utf8               Code
  #48 = Utf8               LineNumberTable
  #49 = Utf8               LocalVariableTable
  #50 = Utf8               Signature
  #51 = Utf8               MethodParameters
  #52 = Utf8               InnerClasses
  #53 = Utf8               SourceFile
  #54 = Utf8               ScalaInlineInfo
  #55 = Utf8               Scala
{
  public static final org.sireum.Jen$Internal$MapImpl$ MODULE$;
    descriptor: Lorg/sireum/Jen$Internal$MapImpl$;
    flags: (0x0019) ACC_PUBLIC, ACC_STATIC, ACC_FINAL

  public static {};
    descriptor: ()V
    flags: (0x0009) ACC_PUBLIC, ACC_STATIC
    Code:
      stack=2, locals=0, args_size=0
         0: new           #2                  // class org/sireum/Jen$Internal$MapImpl$
         3: dup
         4: invokespecial #21                 // Method "<init>":()V
         7: putstatic     #23                 // Field MODULE$:Lorg/sireum/Jen$Internal$MapImpl$;
        10: return
      LineNumberTable:
        line 264: 0

  public <K extends java.lang.Object, T extends java.lang.Object> org.sireum.Jen$Internal$MapImpl<K, T> apply(org.sireum.Map<K, T>);
    descriptor: (Lorg/sireum/Map;)Lorg/sireum/Jen$Internal$MapImpl;
    flags: (0x0001) ACC_PUBLIC
    Code:
      stack=3, locals=2, args_size=2
         0: new           #12                 // class org/sireum/Jen$Internal$MapImpl
         3: dup
         4: aload_1
         5: invokespecial #30                 // Method org/sireum/Jen$Internal$MapImpl."<init>":(Lorg/sireum/Map;)V
         8: areturn
      LineNumberTable:
        line 264: 0
      LocalVariableTable:
        Start  Length  Slot  Name   Signature
            0       9     0  this   Lorg/sireum/Jen$Internal$MapImpl$;
            0       9     1     m   Lorg/sireum/Map;
    Signature: #26                          // <K:Ljava/lang/Object;T:Ljava/lang/Object;>(Lorg/sireum/Map<TK;TT;>;)Lorg/sireum/Jen$Internal$MapImpl<TK;TT;>;
    MethodParameters:
      Name                           Flags
      m                              final

  public <K extends java.lang.Object, T extends java.lang.Object> scala.Some<org.sireum.Map<K, T>> unapply(org.sireum.Jen$Internal$MapImpl<K, T>);
    descriptor: (Lorg/sireum/Jen$Internal$MapImpl;)Lscala/Some;
    flags: (0x0001) ACC_PUBLIC
    Code:
      stack=3, locals=2, args_size=2
         0: new           #38                 // class scala/Some
         3: dup
         4: aload_1
         5: invokevirtual #41                 // Method org/sireum/Jen$Internal$MapImpl.m:()Lorg/sireum/Map;
         8: invokespecial #44                 // Method scala/Some."<init>":(Ljava/lang/Object;)V
        11: areturn
      LineNumberTable:
        line 264: 0
      LocalVariableTable:
        Start  Length  Slot  Name   Signature
            0      12     0  this   Lorg/sireum/Jen$Internal$MapImpl$;
            0      12     1     o   Lorg/sireum/Jen$Internal$MapImpl;
    Signature: #35                          // <K:Ljava/lang/Object;T:Ljava/lang/Object;>(Lorg/sireum/Jen$Internal$MapImpl<TK;TT;>;)Lscala/Some<Lorg/sireum/Map<TK;TT;>;>;
    MethodParameters:
      Name                           Flags
      o                              final

  public org.sireum.Jen$Internal$MapImpl$();
    descriptor: ()V
    flags: (0x0001) ACC_PUBLIC
    Code:
      stack=1, locals=1, args_size=1
         0: aload_0
         1: invokespecial #46                 // Method java/lang/Object."<init>":()V
         4: return
      LineNumberTable:
        line 264: 0
      LocalVariableTable:
        Start  Length  Slot  Name   Signature
            0       5     0  this   Lorg/sireum/Jen$Internal$MapImpl$;
}
InnerClasses:
  public static #10= #7 of #9;            // Internal$=class org/sireum/Jen$Internal$ of class org/sireum/Jen
  public static final #13= #12 of #7;     // MapImpl=class org/sireum/Jen$Internal$MapImpl of class org/sireum/Jen$Internal$
  public static #14= #2 of #7;            // MapImpl$=class org/sireum/Jen$Internal$MapImpl$ of class org/sireum/Jen$Internal$
SourceFile: "Jen.scala"
  ScalaInlineInfo: length = 0x13 (unknown attribute)
   01 01 00 03 00 13 00 12 01 00 18 00 19 01 00 21
   00 22 01
  Scala: length = 0x0 (unknown attribute)

