Classfile /Users/mw/Projects/slang-braindump/.jar/jar8/assemble/slang-braindump/assemble/content/org/sireum/Json$Fun$.class
  Last modified May 29, 2022; size 31928 bytes
  SHA-256 checksum 7eb637ec6893c52a4fd5103d0bbdc7ef985ef4efa9b200d99a1e0ccddab22459
  Compiled from "Json.scala"
public class org.sireum.Json$Fun$
  minor version: 0
  major version: 52
  flags: (0x0021) ACC_PUBLIC, ACC_SUPER
  this_class: #2                          // org/sireum/Json$Fun$
  super_class: #4                         // java/lang/Object
  interfaces: 0, fields: 1, methods: 94, attributes: 4
Constant pool:
    #1 = Utf8               org/sireum/Json$Fun$
    #2 = Class              #1            // org/sireum/Json$Fun$
    #3 = Utf8               java/lang/Object
    #4 = Class              #3            // java/lang/Object
    #5 = Utf8               Json.scala
    #6 = Utf8               org/sireum/Json
    #7 = Class              #6            // org/sireum/Json
    #8 = Utf8               Fun$
    #9 = Utf8               org/sireum/Json$Parser
   #10 = Class              #9            // org/sireum/Json$Parser
   #11 = Utf8               Parser
   #12 = Utf8               MODULE$
   #13 = Utf8               Lorg/sireum/Json$Fun$;
   #14 = Utf8               <clinit>
   #15 = Utf8               ()V
   #16 = Utf8               <init>
   #17 = NameAndType        #16:#15       // "<init>":()V
   #18 = Methodref          #2.#17        // org/sireum/Json$Fun$."<init>":()V
   #19 = NameAndType        #12:#13       // MODULE$:Lorg/sireum/Json$Fun$;
   #20 = Fieldref           #2.#19        // org/sireum/Json$Fun$.MODULE$:Lorg/sireum/Json$Fun$;
   #21 = Utf8               printPure0
   #22 = Utf8               (Lscala/Function0;)Ljava/lang/String;
   #23 = Utf8               <R:Ljava/lang/Object;>(Lscala/Function0<TR;>;)Ljava/lang/String;
   #24 = Utf8               f
   #25 = Utf8               org/sireum/JsonFun_Ext$
   #26 = Class              #25           // org/sireum/JsonFun_Ext$
   #27 = Utf8               Lorg/sireum/JsonFun_Ext$;
   #28 = NameAndType        #12:#27       // MODULE$:Lorg/sireum/JsonFun_Ext$;
   #29 = Fieldref           #26.#28       // org/sireum/JsonFun_Ext$.MODULE$:Lorg/sireum/JsonFun_Ext$;
   #30 = NameAndType        #21:#22       // printPure0:(Lscala/Function0;)Ljava/lang/String;
   #31 = Methodref          #26.#30       // org/sireum/JsonFun_Ext$.printPure0:(Lscala/Function0;)Ljava/lang/String;
   #32 = Utf8               this
   #33 = Utf8               Lscala/Function0;
   #34 = Utf8               parsePure0
   #35 = Utf8               (Lorg/sireum/Json$Parser;Ljava/lang/String;)Lscala/Function0;
   #36 = Utf8               <R:Ljava/lang/Object;>(Lorg/sireum/Json$Parser;Ljava/lang/String;)Lscala/Function0<TR;>;
   #37 = Utf8               parser
   #38 = NameAndType        #34:#35       // parsePure0:(Lorg/sireum/Json$Parser;Ljava/lang/String;)Lscala/Function0;
   #39 = Methodref          #26.#38       // org/sireum/JsonFun_Ext$.parsePure0:(Lorg/sireum/Json$Parser;Ljava/lang/String;)Lscala/Function0;
   #40 = Utf8               Lorg/sireum/Json$Parser;
   #41 = Utf8               Ljava/lang/String;
   #42 = Utf8               print0
   #43 = NameAndType        #42:#22       // print0:(Lscala/Function0;)Ljava/lang/String;
   #44 = Methodref          #26.#43       // org/sireum/JsonFun_Ext$.print0:(Lscala/Function0;)Ljava/lang/String;
   #45 = Utf8               parse0
   #46 = NameAndType        #45:#35       // parse0:(Lorg/sireum/Json$Parser;Ljava/lang/String;)Lscala/Function0;
   #47 = Methodref          #26.#46       // org/sireum/JsonFun_Ext$.parse0:(Lorg/sireum/Json$Parser;Ljava/lang/String;)Lscala/Function0;
   #48 = Utf8               printPure1
   #49 = Utf8               (Lscala/Function1;)Ljava/lang/String;
   #50 = Utf8               <T1:Ljava/lang/Object;R:Ljava/lang/Object;>(Lscala/Function1<TT1;TR;>;)Ljava/lang/String;
   #51 = NameAndType        #48:#49       // printPure1:(Lscala/Function1;)Ljava/lang/String;
   #52 = Methodref          #26.#51       // org/sireum/JsonFun_Ext$.printPure1:(Lscala/Function1;)Ljava/lang/String;
   #53 = Utf8               Lscala/Function1;
   #54 = Utf8               parsePure1
   #55 = Utf8               (Lorg/sireum/Json$Parser;Ljava/lang/String;)Lscala/Function1;
   #56 = Utf8               <T1:Ljava/lang/Object;R:Ljava/lang/Object;>(Lorg/sireum/Json$Parser;Ljava/lang/String;)Lscala/Function1<TT1;TR;>;
   #57 = NameAndType        #54:#55       // parsePure1:(Lorg/sireum/Json$Parser;Ljava/lang/String;)Lscala/Function1;
   #58 = Methodref          #26.#57       // org/sireum/JsonFun_Ext$.parsePure1:(Lorg/sireum/Json$Parser;Ljava/lang/String;)Lscala/Function1;
   #59 = Utf8               print1
   #60 = NameAndType        #59:#49       // print1:(Lscala/Function1;)Ljava/lang/String;
   #61 = Methodref          #26.#60       // org/sireum/JsonFun_Ext$.print1:(Lscala/Function1;)Ljava/lang/String;
   #62 = Utf8               parse1
   #63 = NameAndType        #62:#55       // parse1:(Lorg/sireum/Json$Parser;Ljava/lang/String;)Lscala/Function1;
   #64 = Methodref          #26.#63       // org/sireum/JsonFun_Ext$.parse1:(Lorg/sireum/Json$Parser;Ljava/lang/String;)Lscala/Function1;
   #65 = Utf8               printPure2
   #66 = Utf8               (Lscala/Function2;)Ljava/lang/String;
   #67 = Utf8               <T1:Ljava/lang/Object;T2:Ljava/lang/Object;R:Ljava/lang/Object;>(Lscala/Function2<TT1;TT2;TR;>;)Ljava/lang/String;
   #68 = NameAndType        #65:#66       // printPure2:(Lscala/Function2;)Ljava/lang/String;
   #69 = Methodref          #26.#68       // org/sireum/JsonFun_Ext$.printPure2:(Lscala/Function2;)Ljava/lang/String;
   #70 = Utf8               Lscala/Function2;
   #71 = Utf8               parsePure2
   #72 = Utf8               (Lorg/sireum/Json$Parser;Ljava/lang/String;)Lscala/Function2;
   #73 = Utf8               <T1:Ljava/lang/Object;T2:Ljava/lang/Object;R:Ljava/lang/Object;>(Lorg/sireum/Json$Parser;Ljava/lang/String;)Lscala/Function2<TT1;TT2;TR;>;
   #74 = NameAndType        #71:#72       // parsePure2:(Lorg/sireum/Json$Parser;Ljava/lang/String;)Lscala/Function2;
   #75 = Methodref          #26.#74       // org/sireum/JsonFun_Ext$.parsePure2:(Lorg/sireum/Json$Parser;Ljava/lang/String;)Lscala/Function2;
   #76 = Utf8               print2
   #77 = NameAndType        #76:#66       // print2:(Lscala/Function2;)Ljava/lang/String;
   #78 = Methodref          #26.#77       // org/sireum/JsonFun_Ext$.print2:(Lscala/Function2;)Ljava/lang/String;
   #79 = Utf8               parse2
   #80 = NameAndType        #79:#72       // parse2:(Lorg/sireum/Json$Parser;Ljava/lang/String;)Lscala/Function2;
   #81 = Methodref          #26.#80       // org/sireum/JsonFun_Ext$.parse2:(Lorg/sireum/Json$Parser;Ljava/lang/String;)Lscala/Function2;
   #82 = Utf8               printPure3
   #83 = Utf8               (Lscala/Function3;)Ljava/lang/String;
   #84 = Utf8               <T1:Ljava/lang/Object;T2:Ljava/lang/Object;T3:Ljava/lang/Object;R:Ljava/lang/Object;>(Lscala/Function3<TT1;TT2;TT3;TR;>;)Ljava/lang/String;
   #85 = NameAndType        #82:#83       // printPure3:(Lscala/Function3;)Ljava/lang/String;
   #86 = Methodref          #26.#85       // org/sireum/JsonFun_Ext$.printPure3:(Lscala/Function3;)Ljava/lang/String;
   #87 = Utf8               Lscala/Function3;
   #88 = Utf8               parsePure3
   #89 = Utf8               (Lorg/sireum/Json$Parser;Ljava/lang/String;)Lscala/Function3;
   #90 = Utf8               <T1:Ljava/lang/Object;T2:Ljava/lang/Object;T3:Ljava/lang/Object;R:Ljava/lang/Object;>(Lorg/sireum/Json$Parser;Ljava/lang/String;)Lscala/Function3<TT1;TT2;TT3;TR;>;
   #91 = NameAndType        #88:#89       // parsePure3:(Lorg/sireum/Json$Parser;Ljava/lang/String;)Lscala/Function3;
   #92 = Methodref          #26.#91       // org/sireum/JsonFun_Ext$.parsePure3:(Lorg/sireum/Json$Parser;Ljava/lang/String;)Lscala/Function3;
   #93 = Utf8               print3
   #94 = NameAndType        #93:#83       // print3:(Lscala/Function3;)Ljava/lang/String;
   #95 = Methodref          #26.#94       // org/sireum/JsonFun_Ext$.print3:(Lscala/Function3;)Ljava/lang/String;
   #96 = Utf8               parse3
   #97 = NameAndType        #96:#89       // parse3:(Lorg/sireum/Json$Parser;Ljava/lang/String;)Lscala/Function3;
   #98 = Methodref          #26.#97       // org/sireum/JsonFun_Ext$.parse3:(Lorg/sireum/Json$Parser;Ljava/lang/String;)Lscala/Function3;
   #99 = Utf8               printPure4
  #100 = Utf8               (Lscala/Function4;)Ljava/lang/String;
  #101 = Utf8               <T1:Ljava/lang/Object;T2:Ljava/lang/Object;T3:Ljava/lang/Object;T4:Ljava/lang/Object;R:Ljava/lang/Object;>(Lscala/Function4<TT1;TT2;TT3;TT4;TR;>;)Ljava/lang/String;
  #102 = NameAndType        #99:#100      // printPure4:(Lscala/Function4;)Ljava/lang/String;
  #103 = Methodref          #26.#102      // org/sireum/JsonFun_Ext$.printPure4:(Lscala/Function4;)Ljava/lang/String;
  #104 = Utf8               Lscala/Function4;
  #105 = Utf8               parsePure4
  #106 = Utf8               (Lorg/sireum/Json$Parser;Ljava/lang/String;)Lscala/Function4;
  #107 = Utf8               <T1:Ljava/lang/Object;T2:Ljava/lang/Object;T3:Ljava/lang/Object;T4:Ljava/lang/Object;R:Ljava/lang/Object;>(Lorg/sireum/Json$Parser;Ljava/lang/String;)Lscala/Function4<TT1;TT2;TT3;TT4;TR;>;
  #108 = NameAndType        #105:#106     // parsePure4:(Lorg/sireum/Json$Parser;Ljava/lang/String;)Lscala/Function4;
  #109 = Methodref          #26.#108      // org/sireum/JsonFun_Ext$.parsePure4:(Lorg/sireum/Json$Parser;Ljava/lang/String;)Lscala/Function4;
  #110 = Utf8               print4
  #111 = NameAndType        #110:#100     // print4:(Lscala/Function4;)Ljava/lang/String;
  #112 = Methodref          #26.#111      // org/sireum/JsonFun_Ext$.print4:(Lscala/Function4;)Ljava/lang/String;
  #113 = Utf8               parse4
  #114 = NameAndType        #113:#106     // parse4:(Lorg/sireum/Json$Parser;Ljava/lang/String;)Lscala/Function4;
  #115 = Methodref          #26.#114      // org/sireum/JsonFun_Ext$.parse4:(Lorg/sireum/Json$Parser;Ljava/lang/String;)Lscala/Function4;
  #116 = Utf8               printPure5
  #117 = Utf8               (Lscala/Function5;)Ljava/lang/String;
  #118 = Utf8               <T1:Ljava/lang/Object;T2:Ljava/lang/Object;T3:Ljava/lang/Object;T4:Ljava/lang/Object;T5:Ljava/lang/Object;R:Ljava/lang/Object;>(Lscala/Function5<TT1;TT2;TT3;TT4;TT5;TR;>;)Ljava/lang/String;
  #119 = NameAndType        #116:#117     // printPure5:(Lscala/Function5;)Ljava/lang/String;
  #120 = Methodref          #26.#119      // org/sireum/JsonFun_Ext$.printPure5:(Lscala/Function5;)Ljava/lang/String;
  #121 = Utf8               Lscala/Function5;
  #122 = Utf8               parsePure5
  #123 = Utf8               (Lorg/sireum/Json$Parser;Ljava/lang/String;)Lscala/Function5;
  #124 = Utf8               <T1:Ljava/lang/Object;T2:Ljava/lang/Object;T3:Ljava/lang/Object;T4:Ljava/lang/Object;T5:Ljava/lang/Object;R:Ljava/lang/Object;>(Lorg/sireum/Json$Parser;Ljava/lang/String;)Lscala/Function5<TT1;TT2;TT3;TT4;TT5;TR;>;
  #125 = NameAndType        #122:#123     // parsePure5:(Lorg/sireum/Json$Parser;Ljava/lang/String;)Lscala/Function5;
  #126 = Methodref          #26.#125      // org/sireum/JsonFun_Ext$.parsePure5:(Lorg/sireum/Json$Parser;Ljava/lang/String;)Lscala/Function5;
  #127 = Utf8               print5
  #128 = NameAndType        #127:#117     // print5:(Lscala/Function5;)Ljava/lang/String;
  #129 = Methodref          #26.#128      // org/sireum/JsonFun_Ext$.print5:(Lscala/Function5;)Ljava/lang/String;
  #130 = Utf8               parse5
  #131 = NameAndType        #130:#123     // parse5:(Lorg/sireum/Json$Parser;Ljava/lang/String;)Lscala/Function5;
  #132 = Methodref          #26.#131      // org/sireum/JsonFun_Ext$.parse5:(Lorg/sireum/Json$Parser;Ljava/lang/String;)Lscala/Function5;
  #133 = Utf8               printPure6
  #134 = Utf8               (Lscala/Function6;)Ljava/lang/String;
  #135 = Utf8               <T1:Ljava/lang/Object;T2:Ljava/lang/Object;T3:Ljava/lang/Object;T4:Ljava/lang/Object;T5:Ljava/lang/Object;T6:Ljava/lang/Object;R:Ljava/lang/Object;>(Lscala/Function6<TT1;TT2;TT3;TT4;TT5;TT6;TR;>;)Ljava/lang/String;
  #136 = NameAndType        #133:#134     // printPure6:(Lscala/Function6;)Ljava/lang/String;
  #137 = Methodref          #26.#136      // org/sireum/JsonFun_Ext$.printPure6:(Lscala/Function6;)Ljava/lang/String;
  #138 = Utf8               Lscala/Function6;
  #139 = Utf8               parsePure6
  #140 = Utf8               (Lorg/sireum/Json$Parser;Ljava/lang/String;)Lscala/Function6;
  #141 = Utf8               <T1:Ljava/lang/Object;T2:Ljava/lang/Object;T3:Ljava/lang/Object;T4:Ljava/lang/Object;T5:Ljava/lang/Object;T6:Ljava/lang/Object;R:Ljava/lang/Object;>(Lorg/sireum/Json$Parser;Ljava/lang/String;)Lscala/Function6<TT1;TT2;TT3;TT4;TT5;TT6;TR;>;
  #142 = NameAndType        #139:#140     // parsePure6:(Lorg/sireum/Json$Parser;Ljava/lang/String;)Lscala/Function6;
  #143 = Methodref          #26.#142      // org/sireum/JsonFun_Ext$.parsePure6:(Lorg/sireum/Json$Parser;Ljava/lang/String;)Lscala/Function6;
  #144 = Utf8               print6
  #145 = NameAndType        #144:#134     // print6:(Lscala/Function6;)Ljava/lang/String;
  #146 = Methodref          #26.#145      // org/sireum/JsonFun_Ext$.print6:(Lscala/Function6;)Ljava/lang/String;
  #147 = Utf8               parse6
  #148 = NameAndType        #147:#140     // parse6:(Lorg/sireum/Json$Parser;Ljava/lang/String;)Lscala/Function6;
  #149 = Methodref          #26.#148      // org/sireum/JsonFun_Ext$.parse6:(Lorg/sireum/Json$Parser;Ljava/lang/String;)Lscala/Function6;
  #150 = Utf8               printPure7
  #151 = Utf8               (Lscala/Function7;)Ljava/lang/String;
  #152 = Utf8               <T1:Ljava/lang/Object;T2:Ljava/lang/Object;T3:Ljava/lang/Object;T4:Ljava/lang/Object;T5:Ljava/lang/Object;T6:Ljava/lang/Object;T7:Ljava/lang/Object;R:Ljava/lang/Object;>(Lscala/Function7<TT1;TT2;TT3;TT4;TT5;TT6;TT7;TR;>;)Ljava/lang/String;
  #153 = NameAndType        #150:#151     // printPure7:(Lscala/Function7;)Ljava/lang/String;
  #154 = Methodref          #26.#153      // org/sireum/JsonFun_Ext$.printPure7:(Lscala/Function7;)Ljava/lang/String;
  #155 = Utf8               Lscala/Function7;
  #156 = Utf8               parsePure7
  #157 = Utf8               (Lorg/sireum/Json$Parser;Ljava/lang/String;)Lscala/Function7;
  #158 = Utf8               <T1:Ljava/lang/Object;T2:Ljava/lang/Object;T3:Ljava/lang/Object;T4:Ljava/lang/Object;T5:Ljava/lang/Object;T6:Ljava/lang/Object;T7:Ljava/lang/Object;R:Ljava/lang/Object;>(Lorg/sireum/Json$Parser;Ljava/lang/String;)Lscala/Function7<TT1;TT2;TT3;TT4;TT5;TT6;TT7;TR;>;
  #159 = NameAndType        #156:#157     // parsePure7:(Lorg/sireum/Json$Parser;Ljava/lang/String;)Lscala/Function7;
  #160 = Methodref          #26.#159      // org/sireum/JsonFun_Ext$.parsePure7:(Lorg/sireum/Json$Parser;Ljava/lang/String;)Lscala/Function7;
  #161 = Utf8               print7
  #162 = NameAndType        #161:#151     // print7:(Lscala/Function7;)Ljava/lang/String;
  #163 = Methodref          #26.#162      // org/sireum/JsonFun_Ext$.print7:(Lscala/Function7;)Ljava/lang/String;
  #164 = Utf8               parse7
  #165 = NameAndType        #164:#157     // parse7:(Lorg/sireum/Json$Parser;Ljava/lang/String;)Lscala/Function7;
  #166 = Methodref          #26.#165      // org/sireum/JsonFun_Ext$.parse7:(Lorg/sireum/Json$Parser;Ljava/lang/String;)Lscala/Function7;
  #167 = Utf8               printPure8
  #168 = Utf8               (Lscala/Function8;)Ljava/lang/String;
  #169 = Utf8               <T1:Ljava/lang/Object;T2:Ljava/lang/Object;T3:Ljava/lang/Object;T4:Ljava/lang/Object;T5:Ljava/lang/Object;T6:Ljava/lang/Object;T7:Ljava/lang/Object;T8:Ljava/lang/Object;R:Ljava/lang/Object;>(Lscala/Function8<TT1;TT2;TT3;TT4;TT5;TT6;TT7;TT8;TR;>;)Ljava/lang/String;
  #170 = NameAndType        #167:#168     // printPure8:(Lscala/Function8;)Ljava/lang/String;
  #171 = Methodref          #26.#170      // org/sireum/JsonFun_Ext$.printPure8:(Lscala/Function8;)Ljava/lang/String;
  #172 = Utf8               Lscala/Function8;
  #173 = Utf8               parsePure8
  #174 = Utf8               (Lorg/sireum/Json$Parser;Ljava/lang/String;)Lscala/Function8;
  #175 = Utf8               <T1:Ljava/lang/Object;T2:Ljava/lang/Object;T3:Ljava/lang/Object;T4:Ljava/lang/Object;T5:Ljava/lang/Object;T6:Ljava/lang/Object;T7:Ljava/lang/Object;T8:Ljava/lang/Object;R:Ljava/lang/Object;>(Lorg/sireum/Json$Parser;Ljava/lang/String;)Lscala/Function8<TT1;TT2;TT3;TT4;TT5;TT6;TT7;TT8;TR;>;
  #176 = NameAndType        #173:#174     // parsePure8:(Lorg/sireum/Json$Parser;Ljava/lang/String;)Lscala/Function8;
  #177 = Methodref          #26.#176      // org/sireum/JsonFun_Ext$.parsePure8:(Lorg/sireum/Json$Parser;Ljava/lang/String;)Lscala/Function8;
  #178 = Utf8               print8
  #179 = NameAndType        #178:#168     // print8:(Lscala/Function8;)Ljava/lang/String;
  #180 = Methodref          #26.#179      // org/sireum/JsonFun_Ext$.print8:(Lscala/Function8;)Ljava/lang/String;
  #181 = Utf8               parse8
  #182 = NameAndType        #181:#174     // parse8:(Lorg/sireum/Json$Parser;Ljava/lang/String;)Lscala/Function8;
  #183 = Methodref          #26.#182      // org/sireum/JsonFun_Ext$.parse8:(Lorg/sireum/Json$Parser;Ljava/lang/String;)Lscala/Function8;
  #184 = Utf8               printPure9
  #185 = Utf8               (Lscala/Function9;)Ljava/lang/String;
  #186 = Utf8               <T1:Ljava/lang/Object;T2:Ljava/lang/Object;T3:Ljava/lang/Object;T4:Ljava/lang/Object;T5:Ljava/lang/Object;T6:Ljava/lang/Object;T7:Ljava/lang/Object;T8:Ljava/lang/Object;T9:Ljava/lang/Object;R:Ljava/lang/Object;>(Lscala/Function9<TT1;TT2;TT3;TT4;TT5;TT6;TT7;TT8;TT9;TR;>;)Ljava/lang/String;
  #187 = NameAndType        #184:#185     // printPure9:(Lscala/Function9;)Ljava/lang/String;
  #188 = Methodref          #26.#187      // org/sireum/JsonFun_Ext$.printPure9:(Lscala/Function9;)Ljava/lang/String;
  #189 = Utf8               Lscala/Function9;
  #190 = Utf8               parsePure9
  #191 = Utf8               (Lorg/sireum/Json$Parser;Ljava/lang/String;)Lscala/Function9;
  #192 = Utf8               <T1:Ljava/lang/Object;T2:Ljava/lang/Object;T3:Ljava/lang/Object;T4:Ljava/lang/Object;T5:Ljava/lang/Object;T6:Ljava/lang/Object;T7:Ljava/lang/Object;T8:Ljava/lang/Object;T9:Ljava/lang/Object;R:Ljava/lang/Object;>(Lorg/sireum/Json$Parser;Ljava/lang/String;)Lscala/Function9<TT1;TT2;TT3;TT4;TT5;TT6;TT7;TT8;TT9;TR;>;
  #193 = NameAndType        #190:#191     // parsePure9:(Lorg/sireum/Json$Parser;Ljava/lang/String;)Lscala/Function9;
  #194 = Methodref          #26.#193      // org/sireum/JsonFun_Ext$.parsePure9:(Lorg/sireum/Json$Parser;Ljava/lang/String;)Lscala/Function9;
  #195 = Utf8               print9
  #196 = NameAndType        #195:#185     // print9:(Lscala/Function9;)Ljava/lang/String;
  #197 = Methodref          #26.#196      // org/sireum/JsonFun_Ext$.print9:(Lscala/Function9;)Ljava/lang/String;
  #198 = Utf8               parse9
  #199 = NameAndType        #198:#191     // parse9:(Lorg/sireum/Json$Parser;Ljava/lang/String;)Lscala/Function9;
  #200 = Methodref          #26.#199      // org/sireum/JsonFun_Ext$.parse9:(Lorg/sireum/Json$Parser;Ljava/lang/String;)Lscala/Function9;
  #201 = Utf8               printPure10
  #202 = Utf8               (Lscala/Function10;)Ljava/lang/String;
  #203 = Utf8               <T1:Ljava/lang/Object;T2:Ljava/lang/Object;T3:Ljava/lang/Object;T4:Ljava/lang/Object;T5:Ljava/lang/Object;T6:Ljava/lang/Object;T7:Ljava/lang/Object;T8:Ljava/lang/Object;T9:Ljava/lang/Object;T10:Ljava/lang/Object;R:Ljava/lang/Object;>(Lscala/Function10<TT1;TT2;TT3;TT4;TT5;TT6;TT7;TT8;TT9;TT10;TR;>;)Ljava/lang/String;
  #204 = NameAndType        #201:#202     // printPure10:(Lscala/Function10;)Ljava/lang/String;
  #205 = Methodref          #26.#204      // org/sireum/JsonFun_Ext$.printPure10:(Lscala/Function10;)Ljava/lang/String;
  #206 = Utf8               Lscala/Function10;
  #207 = Utf8               parsePure10
  #208 = Utf8               (Lorg/sireum/Json$Parser;Ljava/lang/String;)Lscala/Function10;
  #209 = Utf8               <T1:Ljava/lang/Object;T2:Ljava/lang/Object;T3:Ljava/lang/Object;T4:Ljava/lang/Object;T5:Ljava/lang/Object;T6:Ljava/lang/Object;T7:Ljava/lang/Object;T8:Ljava/lang/Object;T9:Ljava/lang/Object;T10:Ljava/lang/Object;R:Ljava/lang/Object;>(Lorg/sireum/Json$Parser;Ljava/lang/String;)Lscala/Function10<TT1;TT2;TT3;TT4;TT5;TT6;TT7;TT8;TT9;TT10;TR;>;
  #210 = NameAndType        #207:#208     // parsePure10:(Lorg/sireum/Json$Parser;Ljava/lang/String;)Lscala/Function10;
  #211 = Methodref          #26.#210      // org/sireum/JsonFun_Ext$.parsePure10:(Lorg/sireum/Json$Parser;Ljava/lang/String;)Lscala/Function10;
  #212 = Utf8               print10
  #213 = NameAndType        #212:#202     // print10:(Lscala/Function10;)Ljava/lang/String;
  #214 = Methodref          #26.#213      // org/sireum/JsonFun_Ext$.print10:(Lscala/Function10;)Ljava/lang/String;
  #215 = Utf8               parse10
  #216 = NameAndType        #215:#208     // parse10:(Lorg/sireum/Json$Parser;Ljava/lang/String;)Lscala/Function10;
  #217 = Methodref          #26.#216      // org/sireum/JsonFun_Ext$.parse10:(Lorg/sireum/Json$Parser;Ljava/lang/String;)Lscala/Function10;
  #218 = Utf8               printPure11
  #219 = Utf8               (Lscala/Function11;)Ljava/lang/String;
  #220 = Utf8               <T1:Ljava/lang/Object;T2:Ljava/lang/Object;T3:Ljava/lang/Object;T4:Ljava/lang/Object;T5:Ljava/lang/Object;T6:Ljava/lang/Object;T7:Ljava/lang/Object;T8:Ljava/lang/Object;T9:Ljava/lang/Object;T10:Ljava/lang/Object;T11:Ljava/lang/Object;R:Ljava/lang/Object;>(Lscala/Function11<TT1;TT2;TT3;TT4;TT5;TT6;TT7;TT8;TT9;TT10;TT11;TR;>;)Ljava/lang/String;
  #221 = NameAndType        #218:#219     // printPure11:(Lscala/Function11;)Ljava/lang/String;
  #222 = Methodref          #26.#221      // org/sireum/JsonFun_Ext$.printPure11:(Lscala/Function11;)Ljava/lang/String;
  #223 = Utf8               Lscala/Function11;
  #224 = Utf8               parsePure11
  #225 = Utf8               (Lorg/sireum/Json$Parser;Ljava/lang/String;)Lscala/Function11;
  #226 = Utf8               <T1:Ljava/lang/Object;T2:Ljava/lang/Object;T3:Ljava/lang/Object;T4:Ljava/lang/Object;T5:Ljava/lang/Object;T6:Ljava/lang/Object;T7:Ljava/lang/Object;T8:Ljava/lang/Object;T9:Ljava/lang/Object;T10:Ljava/lang/Object;T11:Ljava/lang/Object;R:Ljava/lang/Object;>(Lorg/sireum/Json$Parser;Ljava/lang/String;)Lscala/Function11<TT1;TT2;TT3;TT4;TT5;TT6;TT7;TT8;TT9;TT10;TT11;TR;>;
  #227 = NameAndType        #224:#225     // parsePure11:(Lorg/sireum/Json$Parser;Ljava/lang/String;)Lscala/Function11;
  #228 = Methodref          #26.#227      // org/sireum/JsonFun_Ext$.parsePure11:(Lorg/sireum/Json$Parser;Ljava/lang/String;)Lscala/Function11;
  #229 = Utf8               print11
  #230 = NameAndType        #229:#219     // print11:(Lscala/Function11;)Ljava/lang/String;
  #231 = Methodref          #26.#230      // org/sireum/JsonFun_Ext$.print11:(Lscala/Function11;)Ljava/lang/String;
  #232 = Utf8               parse11
  #233 = NameAndType        #232:#225     // parse11:(Lorg/sireum/Json$Parser;Ljava/lang/String;)Lscala/Function11;
  #234 = Methodref          #26.#233      // org/sireum/JsonFun_Ext$.parse11:(Lorg/sireum/Json$Parser;Ljava/lang/String;)Lscala/Function11;
  #235 = Utf8               printPure12
  #236 = Utf8               (Lscala/Function12;)Ljava/lang/String;
  #237 = Utf8               <T1:Ljava/lang/Object;T2:Ljava/lang/Object;T3:Ljava/lang/Object;T4:Ljava/lang/Object;T5:Ljava/lang/Object;T6:Ljava/lang/Object;T7:Ljava/lang/Object;T8:Ljava/lang/Object;T9:Ljava/lang/Object;T10:Ljava/lang/Object;T11:Ljava/lang/Object;T12:Ljava/lang/Object;R:Ljava/lang/Object;>(Lscala/Function12<TT1;TT2;TT3;TT4;TT5;TT6;TT7;TT8;TT9;TT10;TT11;TT12;TR;>;)Ljava/lang/String;
  #238 = NameAndType        #235:#236     // printPure12:(Lscala/Function12;)Ljava/lang/String;
  #239 = Methodref          #26.#238      // org/sireum/JsonFun_Ext$.printPure12:(Lscala/Function12;)Ljava/lang/String;
  #240 = Utf8               Lscala/Function12;
  #241 = Utf8               parsePure12
  #242 = Utf8               (Lorg/sireum/Json$Parser;Ljava/lang/String;)Lscala/Function12;
  #243 = Utf8               <T1:Ljava/lang/Object;T2:Ljava/lang/Object;T3:Ljava/lang/Object;T4:Ljava/lang/Object;T5:Ljava/lang/Object;T6:Ljava/lang/Object;T7:Ljava/lang/Object;T8:Ljava/lang/Object;T9:Ljava/lang/Object;T10:Ljava/lang/Object;T11:Ljava/lang/Object;T12:Ljava/lang/Object;R:Ljava/lang/Object;>(Lorg/sireum/Json$Parser;Ljava/lang/String;)Lscala/Function12<TT1;TT2;TT3;TT4;TT5;TT6;TT7;TT8;TT9;TT10;TT11;TT12;TR;>;
  #244 = NameAndType        #241:#242     // parsePure12:(Lorg/sireum/Json$Parser;Ljava/lang/String;)Lscala/Function12;
  #245 = Methodref          #26.#244      // org/sireum/JsonFun_Ext$.parsePure12:(Lorg/sireum/Json$Parser;Ljava/lang/String;)Lscala/Function12;
  #246 = Utf8               print12
  #247 = NameAndType        #246:#236     // print12:(Lscala/Function12;)Ljava/lang/String;
  #248 = Methodref          #26.#247      // org/sireum/JsonFun_Ext$.print12:(Lscala/Function12;)Ljava/lang/String;
  #249 = Utf8               parse12
  #250 = NameAndType        #249:#242     // parse12:(Lorg/sireum/Json$Parser;Ljava/lang/String;)Lscala/Function12;
  #251 = Methodref          #26.#250      // org/sireum/JsonFun_Ext$.parse12:(Lorg/sireum/Json$Parser;Ljava/lang/String;)Lscala/Function12;
  #252 = Utf8               printPure13
  #253 = Utf8               (Lscala/Function13;)Ljava/lang/String;
  #254 = Utf8               <T1:Ljava/lang/Object;T2:Ljava/lang/Object;T3:Ljava/lang/Object;T4:Ljava/lang/Object;T5:Ljava/lang/Object;T6:Ljava/lang/Object;T7:Ljava/lang/Object;T8:Ljava/lang/Object;T9:Ljava/lang/Object;T10:Ljava/lang/Object;T11:Ljava/lang/Object;T12:Ljava/lang/Object;T13:Ljava/lang/Object;R:Ljava/lang/Object;>(Lscala/Function13<TT1;TT2;TT3;TT4;TT5;TT6;TT7;TT8;TT9;TT10;TT11;TT12;TT13;TR;>;)Ljava/lang/String;
  #255 = NameAndType        #252:#253     // printPure13:(Lscala/Function13;)Ljava/lang/String;
  #256 = Methodref          #26.#255      // org/sireum/JsonFun_Ext$.printPure13:(Lscala/Function13;)Ljava/lang/String;
  #257 = Utf8               Lscala/Function13;
  #258 = Utf8               parsePure13
  #259 = Utf8               (Lorg/sireum/Json$Parser;Ljava/lang/String;)Lscala/Function13;
  #260 = Utf8               <T1:Ljava/lang/Object;T2:Ljava/lang/Object;T3:Ljava/lang/Object;T4:Ljava/lang/Object;T5:Ljava/lang/Object;T6:Ljava/lang/Object;T7:Ljava/lang/Object;T8:Ljava/lang/Object;T9:Ljava/lang/Object;T10:Ljava/lang/Object;T11:Ljava/lang/Object;T12:Ljava/lang/Object;T13:Ljava/lang/Object;R:Ljava/lang/Object;>(Lorg/sireum/Json$Parser;Ljava/lang/String;)Lscala/Function13<TT1;TT2;TT3;TT4;TT5;TT6;TT7;TT8;TT9;TT10;TT11;TT12;TT13;TR;>;
  #261 = NameAndType        #258:#259     // parsePure13:(Lorg/sireum/Json$Parser;Ljava/lang/String;)Lscala/Function13;
  #262 = Methodref          #26.#261      // org/sireum/JsonFun_Ext$.parsePure13:(Lorg/sireum/Json$Parser;Ljava/lang/String;)Lscala/Function13;
  #263 = Utf8               print13
  #264 = NameAndType        #263:#253     // print13:(Lscala/Function13;)Ljava/lang/String;
  #265 = Methodref          #26.#264      // org/sireum/JsonFun_Ext$.print13:(Lscala/Function13;)Ljava/lang/String;
  #266 = Utf8               parse13
  #267 = NameAndType        #266:#259     // parse13:(Lorg/sireum/Json$Parser;Ljava/lang/String;)Lscala/Function13;
  #268 = Methodref          #26.#267      // org/sireum/JsonFun_Ext$.parse13:(Lorg/sireum/Json$Parser;Ljava/lang/String;)Lscala/Function13;
  #269 = Utf8               printPure14
  #270 = Utf8               (Lscala/Function14;)Ljava/lang/String;
  #271 = Utf8               <T1:Ljava/lang/Object;T2:Ljava/lang/Object;T3:Ljava/lang/Object;T4:Ljava/lang/Object;T5:Ljava/lang/Object;T6:Ljava/lang/Object;T7:Ljava/lang/Object;T8:Ljava/lang/Object;T9:Ljava/lang/Object;T10:Ljava/lang/Object;T11:Ljava/lang/Object;T12:Ljava/lang/Object;T13:Ljava/lang/Object;T14:Ljava/lang/Object;R:Ljava/lang/Object;>(Lscala/Function14<TT1;TT2;TT3;TT4;TT5;TT6;TT7;TT8;TT9;TT10;TT11;TT12;TT13;TT14;TR;>;)Ljava/lang/String;
  #272 = NameAndType        #269:#270     // printPure14:(Lscala/Function14;)Ljava/lang/String;
  #273 = Methodref          #26.#272      // org/sireum/JsonFun_Ext$.printPure14:(Lscala/Function14;)Ljava/lang/String;
  #274 = Utf8               Lscala/Function14;
  #275 = Utf8               parsePure14
  #276 = Utf8               (Lorg/sireum/Json$Parser;Ljava/lang/String;)Lscala/Function14;
  #277 = Utf8               <T1:Ljava/lang/Object;T2:Ljava/lang/Object;T3:Ljava/lang/Object;T4:Ljava/lang/Object;T5:Ljava/lang/Object;T6:Ljava/lang/Object;T7:Ljava/lang/Object;T8:Ljava/lang/Object;T9:Ljava/lang/Object;T10:Ljava/lang/Object;T11:Ljava/lang/Object;T12:Ljava/lang/Object;T13:Ljava/lang/Object;T14:Ljava/lang/Object;R:Ljava/lang/Object;>(Lorg/sireum/Json$Parser;Ljava/lang/String;)Lscala/Function14<TT1;TT2;TT3;TT4;TT5;TT6;TT7;TT8;TT9;TT10;TT11;TT12;TT13;TT14;TR;>;
  #278 = NameAndType        #275:#276     // parsePure14:(Lorg/sireum/Json$Parser;Ljava/lang/String;)Lscala/Function14;
  #279 = Methodref          #26.#278      // org/sireum/JsonFun_Ext$.parsePure14:(Lorg/sireum/Json$Parser;Ljava/lang/String;)Lscala/Function14;
  #280 = Utf8               print14
  #281 = NameAndType        #280:#270     // print14:(Lscala/Function14;)Ljava/lang/String;
  #282 = Methodref          #26.#281      // org/sireum/JsonFun_Ext$.print14:(Lscala/Function14;)Ljava/lang/String;
  #283 = Utf8               parse14
  #284 = NameAndType        #283:#276     // parse14:(Lorg/sireum/Json$Parser;Ljava/lang/String;)Lscala/Function14;
  #285 = Methodref          #26.#284      // org/sireum/JsonFun_Ext$.parse14:(Lorg/sireum/Json$Parser;Ljava/lang/String;)Lscala/Function14;
  #286 = Utf8               printPure15
  #287 = Utf8               (Lscala/Function15;)Ljava/lang/String;
  #288 = Utf8               <T1:Ljava/lang/Object;T2:Ljava/lang/Object;T3:Ljava/lang/Object;T4:Ljava/lang/Object;T5:Ljava/lang/Object;T6:Ljava/lang/Object;T7:Ljava/lang/Object;T8:Ljava/lang/Object;T9:Ljava/lang/Object;T10:Ljava/lang/Object;T11:Ljava/lang/Object;T12:Ljava/lang/Object;T13:Ljava/lang/Object;T14:Ljava/lang/Object;T15:Ljava/lang/Object;R:Ljava/lang/Object;>(Lscala/Function15<TT1;TT2;TT3;TT4;TT5;TT6;TT7;TT8;TT9;TT10;TT11;TT12;TT13;TT14;TT15;TR;>;)Ljava/lang/String;
  #289 = NameAndType        #286:#287     // printPure15:(Lscala/Function15;)Ljava/lang/String;
  #290 = Methodref          #26.#289      // org/sireum/JsonFun_Ext$.printPure15:(Lscala/Function15;)Ljava/lang/String;
  #291 = Utf8               Lscala/Function15;
  #292 = Utf8               parsePure15
  #293 = Utf8               (Lorg/sireum/Json$Parser;Ljava/lang/String;)Lscala/Function15;
  #294 = Utf8               <T1:Ljava/lang/Object;T2:Ljava/lang/Object;T3:Ljava/lang/Object;T4:Ljava/lang/Object;T5:Ljava/lang/Object;T6:Ljava/lang/Object;T7:Ljava/lang/Object;T8:Ljava/lang/Object;T9:Ljava/lang/Object;T10:Ljava/lang/Object;T11:Ljava/lang/Object;T12:Ljava/lang/Object;T13:Ljava/lang/Object;T14:Ljava/lang/Object;T15:Ljava/lang/Object;R:Ljava/lang/Object;>(Lorg/sireum/Json$Parser;Ljava/lang/String;)Lscala/Function15<TT1;TT2;TT3;TT4;TT5;TT6;TT7;TT8;TT9;TT10;TT11;TT12;TT13;TT14;TT15;TR;>;
  #295 = NameAndType        #292:#293     // parsePure15:(Lorg/sireum/Json$Parser;Ljava/lang/String;)Lscala/Function15;
  #296 = Methodref          #26.#295      // org/sireum/JsonFun_Ext$.parsePure15:(Lorg/sireum/Json$Parser;Ljava/lang/String;)Lscala/Function15;
  #297 = Utf8               print15
  #298 = NameAndType        #297:#287     // print15:(Lscala/Function15;)Ljava/lang/String;
  #299 = Methodref          #26.#298      // org/sireum/JsonFun_Ext$.print15:(Lscala/Function15;)Ljava/lang/String;
  #300 = Utf8               parse15
  #301 = NameAndType        #300:#293     // parse15:(Lorg/sireum/Json$Parser;Ljava/lang/String;)Lscala/Function15;
  #302 = Methodref          #26.#301      // org/sireum/JsonFun_Ext$.parse15:(Lorg/sireum/Json$Parser;Ljava/lang/String;)Lscala/Function15;
  #303 = Utf8               printPure16
  #304 = Utf8               (Lscala/Function16;)Ljava/lang/String;
  #305 = Utf8               <T1:Ljava/lang/Object;T2:Ljava/lang/Object;T3:Ljava/lang/Object;T4:Ljava/lang/Object;T5:Ljava/lang/Object;T6:Ljava/lang/Object;T7:Ljava/lang/Object;T8:Ljava/lang/Object;T9:Ljava/lang/Object;T10:Ljava/lang/Object;T11:Ljava/lang/Object;T12:Ljava/lang/Object;T13:Ljava/lang/Object;T14:Ljava/lang/Object;T15:Ljava/lang/Object;T16:Ljava/lang/Object;R:Ljava/lang/Object;>(Lscala/Function16<TT1;TT2;TT3;TT4;TT5;TT6;TT7;TT8;TT9;TT10;TT11;TT12;TT13;TT14;TT15;TT16;TR;>;)Ljava/lang/String;
  #306 = NameAndType        #303:#304     // printPure16:(Lscala/Function16;)Ljava/lang/String;
  #307 = Methodref          #26.#306      // org/sireum/JsonFun_Ext$.printPure16:(Lscala/Function16;)Ljava/lang/String;
  #308 = Utf8               Lscala/Function16;
  #309 = Utf8               parsePure16
  #310 = Utf8               (Lorg/sireum/Json$Parser;Ljava/lang/String;)Lscala/Function16;
  #311 = Utf8               <T1:Ljava/lang/Object;T2:Ljava/lang/Object;T3:Ljava/lang/Object;T4:Ljava/lang/Object;T5:Ljava/lang/Object;T6:Ljava/lang/Object;T7:Ljava/lang/Object;T8:Ljava/lang/Object;T9:Ljava/lang/Object;T10:Ljava/lang/Object;T11:Ljava/lang/Object;T12:Ljava/lang/Object;T13:Ljava/lang/Object;T14:Ljava/lang/Object;T15:Ljava/lang/Object;T16:Ljava/lang/Object;R:Ljava/lang/Object;>(Lorg/sireum/Json$Parser;Ljava/lang/String;)Lscala/Function16<TT1;TT2;TT3;TT4;TT5;TT6;TT7;TT8;TT9;TT10;TT11;TT12;TT13;TT14;TT15;TT16;TR;>;
  #312 = NameAndType        #309:#310     // parsePure16:(Lorg/sireum/Json$Parser;Ljava/lang/String;)Lscala/Function16;
  #313 = Methodref          #26.#312      // org/sireum/JsonFun_Ext$.parsePure16:(Lorg/sireum/Json$Parser;Ljava/lang/String;)Lscala/Function16;
  #314 = Utf8               print16
  #315 = NameAndType        #314:#304     // print16:(Lscala/Function16;)Ljava/lang/String;
  #316 = Methodref          #26.#315      // org/sireum/JsonFun_Ext$.print16:(Lscala/Function16;)Ljava/lang/String;
  #317 = Utf8               parse16
  #318 = NameAndType        #317:#310     // parse16:(Lorg/sireum/Json$Parser;Ljava/lang/String;)Lscala/Function16;
  #319 = Methodref          #26.#318      // org/sireum/JsonFun_Ext$.parse16:(Lorg/sireum/Json$Parser;Ljava/lang/String;)Lscala/Function16;
  #320 = Utf8               printPure17
  #321 = Utf8               (Lscala/Function17;)Ljava/lang/String;
  #322 = Utf8               <T1:Ljava/lang/Object;T2:Ljava/lang/Object;T3:Ljava/lang/Object;T4:Ljava/lang/Object;T5:Ljava/lang/Object;T6:Ljava/lang/Object;T7:Ljava/lang/Object;T8:Ljava/lang/Object;T9:Ljava/lang/Object;T10:Ljava/lang/Object;T11:Ljava/lang/Object;T12:Ljava/lang/Object;T13:Ljava/lang/Object;T14:Ljava/lang/Object;T15:Ljava/lang/Object;T16:Ljava/lang/Object;T17:Ljava/lang/Object;R:Ljava/lang/Object;>(Lscala/Function17<TT1;TT2;TT3;TT4;TT5;TT6;TT7;TT8;TT9;TT10;TT11;TT12;TT13;TT14;TT15;TT16;TT17;TR;>;)Ljava/lang/String;
  #323 = NameAndType        #320:#321     // printPure17:(Lscala/Function17;)Ljava/lang/String;
  #324 = Methodref          #26.#323      // org/sireum/JsonFun_Ext$.printPure17:(Lscala/Function17;)Ljava/lang/String;
  #325 = Utf8               Lscala/Function17;
  #326 = Utf8               parsePure17
  #327 = Utf8               (Lorg/sireum/Json$Parser;Ljava/lang/String;)Lscala/Function17;
  #328 = Utf8               <T1:Ljava/lang/Object;T2:Ljava/lang/Object;T3:Ljava/lang/Object;T4:Ljava/lang/Object;T5:Ljava/lang/Object;T6:Ljava/lang/Object;T7:Ljava/lang/Object;T8:Ljava/lang/Object;T9:Ljava/lang/Object;T10:Ljava/lang/Object;T11:Ljava/lang/Object;T12:Ljava/lang/Object;T13:Ljava/lang/Object;T14:Ljava/lang/Object;T15:Ljava/lang/Object;T16:Ljava/lang/Object;T17:Ljava/lang/Object;R:Ljava/lang/Object;>(Lorg/sireum/Json$Parser;Ljava/lang/String;)Lscala/Function17<TT1;TT2;TT3;TT4;TT5;TT6;TT7;TT8;TT9;TT10;TT11;TT12;TT13;TT14;TT15;TT16;TT17;TR;>;
  #329 = NameAndType        #326:#327     // parsePure17:(Lorg/sireum/Json$Parser;Ljava/lang/String;)Lscala/Function17;
  #330 = Methodref          #26.#329      // org/sireum/JsonFun_Ext$.parsePure17:(Lorg/sireum/Json$Parser;Ljava/lang/String;)Lscala/Function17;
  #331 = Utf8               print17
  #332 = NameAndType        #331:#321     // print17:(Lscala/Function17;)Ljava/lang/String;
  #333 = Methodref          #26.#332      // org/sireum/JsonFun_Ext$.print17:(Lscala/Function17;)Ljava/lang/String;
  #334 = Utf8               parse17
  #335 = NameAndType        #334:#327     // parse17:(Lorg/sireum/Json$Parser;Ljava/lang/String;)Lscala/Function17;
  #336 = Methodref          #26.#335      // org/sireum/JsonFun_Ext$.parse17:(Lorg/sireum/Json$Parser;Ljava/lang/String;)Lscala/Function17;
  #337 = Utf8               printPure18
  #338 = Utf8               (Lscala/Function18;)Ljava/lang/String;
  #339 = Utf8               <T1:Ljava/lang/Object;T2:Ljava/lang/Object;T3:Ljava/lang/Object;T4:Ljava/lang/Object;T5:Ljava/lang/Object;T6:Ljava/lang/Object;T7:Ljava/lang/Object;T8:Ljava/lang/Object;T9:Ljava/lang/Object;T10:Ljava/lang/Object;T11:Ljava/lang/Object;T12:Ljava/lang/Object;T13:Ljava/lang/Object;T14:Ljava/lang/Object;T15:Ljava/lang/Object;T16:Ljava/lang/Object;T17:Ljava/lang/Object;T18:Ljava/lang/Object;R:Ljava/lang/Object;>(Lscala/Function18<TT1;TT2;TT3;TT4;TT5;TT6;TT7;TT8;TT9;TT10;TT11;TT12;TT13;TT14;TT15;TT16;TT17;TT18;TR;>;)Ljava/lang/String;
  #340 = NameAndType        #337:#338     // printPure18:(Lscala/Function18;)Ljava/lang/String;
  #341 = Methodref          #26.#340      // org/sireum/JsonFun_Ext$.printPure18:(Lscala/Function18;)Ljava/lang/String;
  #342 = Utf8               Lscala/Function18;
  #343 = Utf8               parsePure18
  #344 = Utf8               (Lorg/sireum/Json$Parser;Ljava/lang/String;)Lscala/Function18;
  #345 = Utf8               <T1:Ljava/lang/Object;T2:Ljava/lang/Object;T3:Ljava/lang/Object;T4:Ljava/lang/Object;T5:Ljava/lang/Object;T6:Ljava/lang/Object;T7:Ljava/lang/Object;T8:Ljava/lang/Object;T9:Ljava/lang/Object;T10:Ljava/lang/Object;T11:Ljava/lang/Object;T12:Ljava/lang/Object;T13:Ljava/lang/Object;T14:Ljava/lang/Object;T15:Ljava/lang/Object;T16:Ljava/lang/Object;T17:Ljava/lang/Object;T18:Ljava/lang/Object;R:Ljava/lang/Object;>(Lorg/sireum/Json$Parser;Ljava/lang/String;)Lscala/Function18<TT1;TT2;TT3;TT4;TT5;TT6;TT7;TT8;TT9;TT10;TT11;TT12;TT13;TT14;TT15;TT16;TT17;TT18;TR;>;
  #346 = NameAndType        #343:#344     // parsePure18:(Lorg/sireum/Json$Parser;Ljava/lang/String;)Lscala/Function18;
  #347 = Methodref          #26.#346      // org/sireum/JsonFun_Ext$.parsePure18:(Lorg/sireum/Json$Parser;Ljava/lang/String;)Lscala/Function18;
  #348 = Utf8               print18
  #349 = NameAndType        #348:#338     // print18:(Lscala/Function18;)Ljava/lang/String;
  #350 = Methodref          #26.#349      // org/sireum/JsonFun_Ext$.print18:(Lscala/Function18;)Ljava/lang/String;
  #351 = Utf8               parse18
  #352 = NameAndType        #351:#344     // parse18:(Lorg/sireum/Json$Parser;Ljava/lang/String;)Lscala/Function18;
  #353 = Methodref          #26.#352      // org/sireum/JsonFun_Ext$.parse18:(Lorg/sireum/Json$Parser;Ljava/lang/String;)Lscala/Function18;
  #354 = Utf8               printPure19
  #355 = Utf8               (Lscala/Function19;)Ljava/lang/String;
  #356 = Utf8               <T1:Ljava/lang/Object;T2:Ljava/lang/Object;T3:Ljava/lang/Object;T4:Ljava/lang/Object;T5:Ljava/lang/Object;T6:Ljava/lang/Object;T7:Ljava/lang/Object;T8:Ljava/lang/Object;T9:Ljava/lang/Object;T10:Ljava/lang/Object;T11:Ljava/lang/Object;T12:Ljava/lang/Object;T13:Ljava/lang/Object;T14:Ljava/lang/Object;T15:Ljava/lang/Object;T16:Ljava/lang/Object;T17:Ljava/lang/Object;T18:Ljava/lang/Object;T19:Ljava/lang/Object;R:Ljava/lang/Object;>(Lscala/Function19<TT1;TT2;TT3;TT4;TT5;TT6;TT7;TT8;TT9;TT10;TT11;TT12;TT13;TT14;TT15;TT16;TT17;TT18;TT19;TR;>;)Ljava/lang/String;
  #357 = NameAndType        #354:#355     // printPure19:(Lscala/Function19;)Ljava/lang/String;
  #358 = Methodref          #26.#357      // org/sireum/JsonFun_Ext$.printPure19:(Lscala/Function19;)Ljava/lang/String;
  #359 = Utf8               Lscala/Function19;
  #360 = Utf8               parsePure19
  #361 = Utf8               (Lorg/sireum/Json$Parser;Ljava/lang/String;)Lscala/Function19;
  #362 = Utf8               <T1:Ljava/lang/Object;T2:Ljava/lang/Object;T3:Ljava/lang/Object;T4:Ljava/lang/Object;T5:Ljava/lang/Object;T6:Ljava/lang/Object;T7:Ljava/lang/Object;T8:Ljava/lang/Object;T9:Ljava/lang/Object;T10:Ljava/lang/Object;T11:Ljava/lang/Object;T12:Ljava/lang/Object;T13:Ljava/lang/Object;T14:Ljava/lang/Object;T15:Ljava/lang/Object;T16:Ljava/lang/Object;T17:Ljava/lang/Object;T18:Ljava/lang/Object;T19:Ljava/lang/Object;R:Ljava/lang/Object;>(Lorg/sireum/Json$Parser;Ljava/lang/String;)Lscala/Function19<TT1;TT2;TT3;TT4;TT5;TT6;TT7;TT8;TT9;TT10;TT11;TT12;TT13;TT14;TT15;TT16;TT17;TT18;TT19;TR;>;
  #363 = NameAndType        #360:#361     // parsePure19:(Lorg/sireum/Json$Parser;Ljava/lang/String;)Lscala/Function19;
  #364 = Methodref          #26.#363      // org/sireum/JsonFun_Ext$.parsePure19:(Lorg/sireum/Json$Parser;Ljava/lang/String;)Lscala/Function19;
  #365 = Utf8               print19
  #366 = NameAndType        #365:#355     // print19:(Lscala/Function19;)Ljava/lang/String;
  #367 = Methodref          #26.#366      // org/sireum/JsonFun_Ext$.print19:(Lscala/Function19;)Ljava/lang/String;
  #368 = Utf8               parse19
  #369 = NameAndType        #368:#361     // parse19:(Lorg/sireum/Json$Parser;Ljava/lang/String;)Lscala/Function19;
  #370 = Methodref          #26.#369      // org/sireum/JsonFun_Ext$.parse19:(Lorg/sireum/Json$Parser;Ljava/lang/String;)Lscala/Function19;
  #371 = Utf8               printPure20
  #372 = Utf8               (Lscala/Function20;)Ljava/lang/String;
  #373 = Utf8               <T1:Ljava/lang/Object;T2:Ljava/lang/Object;T3:Ljava/lang/Object;T4:Ljava/lang/Object;T5:Ljava/lang/Object;T6:Ljava/lang/Object;T7:Ljava/lang/Object;T8:Ljava/lang/Object;T9:Ljava/lang/Object;T10:Ljava/lang/Object;T11:Ljava/lang/Object;T12:Ljava/lang/Object;T13:Ljava/lang/Object;T14:Ljava/lang/Object;T15:Ljava/lang/Object;T16:Ljava/lang/Object;T17:Ljava/lang/Object;T18:Ljava/lang/Object;T19:Ljava/lang/Object;T20:Ljava/lang/Object;R:Ljava/lang/Object;>(Lscala/Function20<TT1;TT2;TT3;TT4;TT5;TT6;TT7;TT8;TT9;TT10;TT11;TT12;TT13;TT14;TT15;TT16;TT17;TT18;TT19;TT20;TR;>;)Ljava/lang/String;
  #374 = NameAndType        #371:#372     // printPure20:(Lscala/Function20;)Ljava/lang/String;
  #375 = Methodref          #26.#374      // org/sireum/JsonFun_Ext$.printPure20:(Lscala/Function20;)Ljava/lang/String;
  #376 = Utf8               Lscala/Function20;
  #377 = Utf8               parsePure20
  #378 = Utf8               (Lorg/sireum/Json$Parser;Ljava/lang/String;)Lscala/Function20;
  #379 = Utf8               <T1:Ljava/lang/Object;T2:Ljava/lang/Object;T3:Ljava/lang/Object;T4:Ljava/lang/Object;T5:Ljava/lang/Object;T6:Ljava/lang/Object;T7:Ljava/lang/Object;T8:Ljava/lang/Object;T9:Ljava/lang/Object;T10:Ljava/lang/Object;T11:Ljava/lang/Object;T12:Ljava/lang/Object;T13:Ljava/lang/Object;T14:Ljava/lang/Object;T15:Ljava/lang/Object;T16:Ljava/lang/Object;T17:Ljava/lang/Object;T18:Ljava/lang/Object;T19:Ljava/lang/Object;T20:Ljava/lang/Object;R:Ljava/lang/Object;>(Lorg/sireum/Json$Parser;Ljava/lang/String;)Lscala/Function20<TT1;TT2;TT3;TT4;TT5;TT6;TT7;TT8;TT9;TT10;TT11;TT12;TT13;TT14;TT15;TT16;TT17;TT18;TT19;TT20;TR;>;
  #380 = NameAndType        #377:#378     // parsePure20:(Lorg/sireum/Json$Parser;Ljava/lang/String;)Lscala/Function20;
  #381 = Methodref          #26.#380      // org/sireum/JsonFun_Ext$.parsePure20:(Lorg/sireum/Json$Parser;Ljava/lang/String;)Lscala/Function20;
  #382 = Utf8               print20
  #383 = NameAndType        #382:#372     // print20:(Lscala/Function20;)Ljava/lang/String;
  #384 = Methodref          #26.#383      // org/sireum/JsonFun_Ext$.print20:(Lscala/Function20;)Ljava/lang/String;
  #385 = Utf8               parse20
  #386 = NameAndType        #385:#378     // parse20:(Lorg/sireum/Json$Parser;Ljava/lang/String;)Lscala/Function20;
  #387 = Methodref          #26.#386      // org/sireum/JsonFun_Ext$.parse20:(Lorg/sireum/Json$Parser;Ljava/lang/String;)Lscala/Function20;
  #388 = Utf8               printPure21
  #389 = Utf8               (Lscala/Function21;)Ljava/lang/String;
  #390 = Utf8               <T1:Ljava/lang/Object;T2:Ljava/lang/Object;T3:Ljava/lang/Object;T4:Ljava/lang/Object;T5:Ljava/lang/Object;T6:Ljava/lang/Object;T7:Ljava/lang/Object;T8:Ljava/lang/Object;T9:Ljava/lang/Object;T10:Ljava/lang/Object;T11:Ljava/lang/Object;T12:Ljava/lang/Object;T13:Ljava/lang/Object;T14:Ljava/lang/Object;T15:Ljava/lang/Object;T16:Ljava/lang/Object;T17:Ljava/lang/Object;T18:Ljava/lang/Object;T19:Ljava/lang/Object;T20:Ljava/lang/Object;T21:Ljava/lang/Object;R:Ljava/lang/Object;>(Lscala/Function21<TT1;TT2;TT3;TT4;TT5;TT6;TT7;TT8;TT9;TT10;TT11;TT12;TT13;TT14;TT15;TT16;TT17;TT18;TT19;TT20;TT21;TR;>;)Ljava/lang/String;
  #391 = NameAndType        #388:#389     // printPure21:(Lscala/Function21;)Ljava/lang/String;
  #392 = Methodref          #26.#391      // org/sireum/JsonFun_Ext$.printPure21:(Lscala/Function21;)Ljava/lang/String;
  #393 = Utf8               Lscala/Function21;
  #394 = Utf8               parsePure21
  #395 = Utf8               (Lorg/sireum/Json$Parser;Ljava/lang/String;)Lscala/Function21;
  #396 = Utf8               <T1:Ljava/lang/Object;T2:Ljava/lang/Object;T3:Ljava/lang/Object;T4:Ljava/lang/Object;T5:Ljava/lang/Object;T6:Ljava/lang/Object;T7:Ljava/lang/Object;T8:Ljava/lang/Object;T9:Ljava/lang/Object;T10:Ljava/lang/Object;T11:Ljava/lang/Object;T12:Ljava/lang/Object;T13:Ljava/lang/Object;T14:Ljava/lang/Object;T15:Ljava/lang/Object;T16:Ljava/lang/Object;T17:Ljava/lang/Object;T18:Ljava/lang/Object;T19:Ljava/lang/Object;T20:Ljava/lang/Object;T21:Ljava/lang/Object;R:Ljava/lang/Object;>(Lorg/sireum/Json$Parser;Ljava/lang/String;)Lscala/Function21<TT1;TT2;TT3;TT4;TT5;TT6;TT7;TT8;TT9;TT10;TT11;TT12;TT13;TT14;TT15;TT16;TT17;TT18;TT19;TT20;TT21;TR;>;
  #397 = NameAndType        #394:#395     // parsePure21:(Lorg/sireum/Json$Parser;Ljava/lang/String;)Lscala/Function21;
  #398 = Methodref          #26.#397      // org/sireum/JsonFun_Ext$.parsePure21:(Lorg/sireum/Json$Parser;Ljava/lang/String;)Lscala/Function21;
  #399 = Utf8               print21
  #400 = NameAndType        #399:#389     // print21:(Lscala/Function21;)Ljava/lang/String;
  #401 = Methodref          #26.#400      // org/sireum/JsonFun_Ext$.print21:(Lscala/Function21;)Ljava/lang/String;
  #402 = Utf8               parse21
  #403 = NameAndType        #402:#395     // parse21:(Lorg/sireum/Json$Parser;Ljava/lang/String;)Lscala/Function21;
  #404 = Methodref          #26.#403      // org/sireum/JsonFun_Ext$.parse21:(Lorg/sireum/Json$Parser;Ljava/lang/String;)Lscala/Function21;
  #405 = Utf8               printPure22
  #406 = Utf8               (Lscala/Function22;)Ljava/lang/String;
  #407 = Utf8               <T1:Ljava/lang/Object;T2:Ljava/lang/Object;T3:Ljava/lang/Object;T4:Ljava/lang/Object;T5:Ljava/lang/Object;T6:Ljava/lang/Object;T7:Ljava/lang/Object;T8:Ljava/lang/Object;T9:Ljava/lang/Object;T10:Ljava/lang/Object;T11:Ljava/lang/Object;T12:Ljava/lang/Object;T13:Ljava/lang/Object;T14:Ljava/lang/Object;T15:Ljava/lang/Object;T16:Ljava/lang/Object;T17:Ljava/lang/Object;T18:Ljava/lang/Object;T19:Ljava/lang/Object;T20:Ljava/lang/Object;T21:Ljava/lang/Object;T22:Ljava/lang/Object;R:Ljava/lang/Object;>(Lscala/Function22<TT1;TT2;TT3;TT4;TT5;TT6;TT7;TT8;TT9;TT10;TT11;TT12;TT13;TT14;TT15;TT16;TT17;TT18;TT19;TT20;TT21;TT22;TR;>;)Ljava/lang/String;
  #408 = NameAndType        #405:#406     // printPure22:(Lscala/Function22;)Ljava/lang/String;
  #409 = Methodref          #26.#408      // org/sireum/JsonFun_Ext$.printPure22:(Lscala/Function22;)Ljava/lang/String;
  #410 = Utf8               Lscala/Function22;
  #411 = Utf8               parsePure22
  #412 = Utf8               (Lorg/sireum/Json$Parser;Ljava/lang/String;)Lscala/Function22;
  #413 = Utf8               <T1:Ljava/lang/Object;T2:Ljava/lang/Object;T3:Ljava/lang/Object;T4:Ljava/lang/Object;T5:Ljava/lang/Object;T6:Ljava/lang/Object;T7:Ljava/lang/Object;T8:Ljava/lang/Object;T9:Ljava/lang/Object;T10:Ljava/lang/Object;T11:Ljava/lang/Object;T12:Ljava/lang/Object;T13:Ljava/lang/Object;T14:Ljava/lang/Object;T15:Ljava/lang/Object;T16:Ljava/lang/Object;T17:Ljava/lang/Object;T18:Ljava/lang/Object;T19:Ljava/lang/Object;T20:Ljava/lang/Object;T21:Ljava/lang/Object;T22:Ljava/lang/Object;R:Ljava/lang/Object;>(Lorg/sireum/Json$Parser;Ljava/lang/String;)Lscala/Function22<TT1;TT2;TT3;TT4;TT5;TT6;TT7;TT8;TT9;TT10;TT11;TT12;TT13;TT14;TT15;TT16;TT17;TT18;TT19;TT20;TT21;TT22;TR;>;
  #414 = NameAndType        #411:#412     // parsePure22:(Lorg/sireum/Json$Parser;Ljava/lang/String;)Lscala/Function22;
  #415 = Methodref          #26.#414      // org/sireum/JsonFun_Ext$.parsePure22:(Lorg/sireum/Json$Parser;Ljava/lang/String;)Lscala/Function22;
  #416 = Utf8               print22
  #417 = NameAndType        #416:#406     // print22:(Lscala/Function22;)Ljava/lang/String;
  #418 = Methodref          #26.#417      // org/sireum/JsonFun_Ext$.print22:(Lscala/Function22;)Ljava/lang/String;
  #419 = Utf8               parse22
  #420 = NameAndType        #419:#412     // parse22:(Lorg/sireum/Json$Parser;Ljava/lang/String;)Lscala/Function22;
  #421 = Methodref          #26.#420      // org/sireum/JsonFun_Ext$.parse22:(Lorg/sireum/Json$Parser;Ljava/lang/String;)Lscala/Function22;
  #422 = Methodref          #4.#17        // java/lang/Object."<init>":()V
  #423 = Utf8               Code
  #424 = Utf8               LineNumberTable
  #425 = Utf8               LocalVariableTable
  #426 = Utf8               Signature
  #427 = Utf8               MethodParameters
  #428 = Utf8               InnerClasses
  #429 = Utf8               SourceFile
  #430 = Utf8               ScalaInlineInfo
  #431 = Utf8               Scala
{
  public static final org.sireum.Json$Fun$ MODULE$;
    descriptor: Lorg/sireum/Json$Fun$;
    flags: (0x0019) ACC_PUBLIC, ACC_STATIC, ACC_FINAL

  public static {};
    descriptor: ()V
    flags: (0x0009) ACC_PUBLIC, ACC_STATIC
    Code:
      stack=2, locals=0, args_size=0
         0: new           #2                  // class org/sireum/Json$Fun$
         3: dup
         4: invokespecial #18                 // Method "<init>":()V
         7: putstatic     #20                 // Field MODULE$:Lorg/sireum/Json$Fun$;
        10: return
      LineNumberTable:
        line 2411: 0

  public <R extends java.lang.Object> java.lang.String printPure0(scala.Function0<R>);
    descriptor: (Lscala/Function0;)Ljava/lang/String;
    flags: (0x0001) ACC_PUBLIC
    Code:
      stack=2, locals=2, args_size=2
         0: getstatic     #29                 // Field org/sireum/JsonFun_Ext$.MODULE$:Lorg/sireum/JsonFun_Ext$;
         3: aload_1
         4: invokevirtual #31                 // Method org/sireum/JsonFun_Ext$.printPure0:(Lscala/Function0;)Ljava/lang/String;
         7: areturn
      LineNumberTable:
        line 2412: 0
      LocalVariableTable:
        Start  Length  Slot  Name   Signature
            0       8     0  this   Lorg/sireum/Json$Fun$;
            0       8     1     f   Lscala/Function0;
    Signature: #23                          // <R:Ljava/lang/Object;>(Lscala/Function0<TR;>;)Ljava/lang/String;
    MethodParameters:
      Name                           Flags
      f                              final

  public <R extends java.lang.Object> scala.Function0<R> parsePure0(org.sireum.Json$Parser, java.lang.String);
    descriptor: (Lorg/sireum/Json$Parser;Ljava/lang/String;)Lscala/Function0;
    flags: (0x0001) ACC_PUBLIC
    Code:
      stack=3, locals=3, args_size=3
         0: getstatic     #29                 // Field org/sireum/JsonFun_Ext$.MODULE$:Lorg/sireum/JsonFun_Ext$;
         3: aload_1
         4: aload_2
         5: invokevirtual #39                 // Method org/sireum/JsonFun_Ext$.parsePure0:(Lorg/sireum/Json$Parser;Ljava/lang/String;)Lscala/Function0;
         8: areturn
      LineNumberTable:
        line 2413: 0
      LocalVariableTable:
        Start  Length  Slot  Name   Signature
            0       9     0  this   Lorg/sireum/Json$Fun$;
            0       9     1 parser   Lorg/sireum/Json$Parser;
            0       9     2     f   Ljava/lang/String;
    Signature: #36                          // <R:Ljava/lang/Object;>(Lorg/sireum/Json$Parser;Ljava/lang/String;)Lscala/Function0<TR;>;
    MethodParameters:
      Name                           Flags
      parser                         final
      f                              final

  public <R extends java.lang.Object> java.lang.String print0(scala.Function0<R>);
    descriptor: (Lscala/Function0;)Ljava/lang/String;
    flags: (0x0001) ACC_PUBLIC
    Code:
      stack=2, locals=2, args_size=2
         0: getstatic     #29                 // Field org/sireum/JsonFun_Ext$.MODULE$:Lorg/sireum/JsonFun_Ext$;
         3: aload_1
         4: invokevirtual #44                 // Method org/sireum/JsonFun_Ext$.print0:(Lscala/Function0;)Ljava/lang/String;
         7: areturn
      LineNumberTable:
        line 2415: 0
      LocalVariableTable:
        Start  Length  Slot  Name   Signature
            0       8     0  this   Lorg/sireum/Json$Fun$;
            0       8     1     f   Lscala/Function0;
    Signature: #23                          // <R:Ljava/lang/Object;>(Lscala/Function0<TR;>;)Ljava/lang/String;
    MethodParameters:
      Name                           Flags
      f                              final

  public <R extends java.lang.Object> scala.Function0<R> parse0(org.sireum.Json$Parser, java.lang.String);
    descriptor: (Lorg/sireum/Json$Parser;Ljava/lang/String;)Lscala/Function0;
    flags: (0x0001) ACC_PUBLIC
    Code:
      stack=3, locals=3, args_size=3
         0: getstatic     #29                 // Field org/sireum/JsonFun_Ext$.MODULE$:Lorg/sireum/JsonFun_Ext$;
         3: aload_1
         4: aload_2
         5: invokevirtual #47                 // Method org/sireum/JsonFun_Ext$.parse0:(Lorg/sireum/Json$Parser;Ljava/lang/String;)Lscala/Function0;
         8: areturn
      LineNumberTable:
        line 2416: 0
      LocalVariableTable:
        Start  Length  Slot  Name   Signature
            0       9     0  this   Lorg/sireum/Json$Fun$;
            0       9     1 parser   Lorg/sireum/Json$Parser;
            0       9     2     f   Ljava/lang/String;
    Signature: #36                          // <R:Ljava/lang/Object;>(Lorg/sireum/Json$Parser;Ljava/lang/String;)Lscala/Function0<TR;>;
    MethodParameters:
      Name                           Flags
      parser                         final
      f                              final

  public <T1 extends java.lang.Object, R extends java.lang.Object> java.lang.String printPure1(scala.Function1<T1, R>);
    descriptor: (Lscala/Function1;)Ljava/lang/String;
    flags: (0x0001) ACC_PUBLIC
    Code:
      stack=2, locals=2, args_size=2
         0: getstatic     #29                 // Field org/sireum/JsonFun_Ext$.MODULE$:Lorg/sireum/JsonFun_Ext$;
         3: aload_1
         4: invokevirtual #52                 // Method org/sireum/JsonFun_Ext$.printPure1:(Lscala/Function1;)Ljava/lang/String;
         7: areturn
      LineNumberTable:
        line 2418: 0
      LocalVariableTable:
        Start  Length  Slot  Name   Signature
            0       8     0  this   Lorg/sireum/Json$Fun$;
            0       8     1     f   Lscala/Function1;
    Signature: #50                          // <T1:Ljava/lang/Object;R:Ljava/lang/Object;>(Lscala/Function1<TT1;TR;>;)Ljava/lang/String;
    MethodParameters:
      Name                           Flags
      f                              final

  public <T1 extends java.lang.Object, R extends java.lang.Object> scala.Function1<T1, R> parsePure1(org.sireum.Json$Parser, java.lang.String);
    descriptor: (Lorg/sireum/Json$Parser;Ljava/lang/String;)Lscala/Function1;
    flags: (0x0001) ACC_PUBLIC
    Code:
      stack=3, locals=3, args_size=3
         0: getstatic     #29                 // Field org/sireum/JsonFun_Ext$.MODULE$:Lorg/sireum/JsonFun_Ext$;
         3: aload_1
         4: aload_2
         5: invokevirtual #58                 // Method org/sireum/JsonFun_Ext$.parsePure1:(Lorg/sireum/Json$Parser;Ljava/lang/String;)Lscala/Function1;
         8: areturn
      LineNumberTable:
        line 2419: 0
      LocalVariableTable:
        Start  Length  Slot  Name   Signature
            0       9     0  this   Lorg/sireum/Json$Fun$;
            0       9     1 parser   Lorg/sireum/Json$Parser;
            0       9     2     f   Ljava/lang/String;
    Signature: #56                          // <T1:Ljava/lang/Object;R:Ljava/lang/Object;>(Lorg/sireum/Json$Parser;Ljava/lang/String;)Lscala/Function1<TT1;TR;>;
    MethodParameters:
      Name                           Flags
      parser                         final
      f                              final

  public <T1 extends java.lang.Object, R extends java.lang.Object> java.lang.String print1(scala.Function1<T1, R>);
    descriptor: (Lscala/Function1;)Ljava/lang/String;
    flags: (0x0001) ACC_PUBLIC
    Code:
      stack=2, locals=2, args_size=2
         0: getstatic     #29                 // Field org/sireum/JsonFun_Ext$.MODULE$:Lorg/sireum/JsonFun_Ext$;
         3: aload_1
         4: invokevirtual #61                 // Method org/sireum/JsonFun_Ext$.print1:(Lscala/Function1;)Ljava/lang/String;
         7: areturn
      LineNumberTable:
        line 2421: 0
      LocalVariableTable:
        Start  Length  Slot  Name   Signature
            0       8     0  this   Lorg/sireum/Json$Fun$;
            0       8     1     f   Lscala/Function1;
    Signature: #50                          // <T1:Ljava/lang/Object;R:Ljava/lang/Object;>(Lscala/Function1<TT1;TR;>;)Ljava/lang/String;
    MethodParameters:
      Name                           Flags
      f                              final

  public <T1 extends java.lang.Object, R extends java.lang.Object> scala.Function1<T1, R> parse1(org.sireum.Json$Parser, java.lang.String);
    descriptor: (Lorg/sireum/Json$Parser;Ljava/lang/String;)Lscala/Function1;
    flags: (0x0001) ACC_PUBLIC
    Code:
      stack=3, locals=3, args_size=3
         0: getstatic     #29                 // Field org/sireum/JsonFun_Ext$.MODULE$:Lorg/sireum/JsonFun_Ext$;
         3: aload_1
         4: aload_2
         5: invokevirtual #64                 // Method org/sireum/JsonFun_Ext$.parse1:(Lorg/sireum/Json$Parser;Ljava/lang/String;)Lscala/Function1;
         8: areturn
      LineNumberTable:
        line 2422: 0
      LocalVariableTable:
        Start  Length  Slot  Name   Signature
            0       9     0  this   Lorg/sireum/Json$Fun$;
            0       9     1 parser   Lorg/sireum/Json$Parser;
            0       9     2     f   Ljava/lang/String;
    Signature: #56                          // <T1:Ljava/lang/Object;R:Ljava/lang/Object;>(Lorg/sireum/Json$Parser;Ljava/lang/String;)Lscala/Function1<TT1;TR;>;
    MethodParameters:
      Name                           Flags
      parser                         final
      f                              final

  public <T1 extends java.lang.Object, T2 extends java.lang.Object, R extends java.lang.Object> java.lang.String printPure2(scala.Function2<T1, T2, R>);
    descriptor: (Lscala/Function2;)Ljava/lang/String;
    flags: (0x0001) ACC_PUBLIC
    Code:
      stack=2, locals=2, args_size=2
         0: getstatic     #29                 // Field org/sireum/JsonFun_Ext$.MODULE$:Lorg/sireum/JsonFun_Ext$;
         3: aload_1
         4: invokevirtual #69                 // Method org/sireum/JsonFun_Ext$.printPure2:(Lscala/Function2;)Ljava/lang/String;
         7: areturn
      LineNumberTable:
        line 2423: 0
      LocalVariableTable:
        Start  Length  Slot  Name   Signature
            0       8     0  this   Lorg/sireum/Json$Fun$;
            0       8     1     f   Lscala/Function2;
    Signature: #67                          // <T1:Ljava/lang/Object;T2:Ljava/lang/Object;R:Ljava/lang/Object;>(Lscala/Function2<TT1;TT2;TR;>;)Ljava/lang/String;
    MethodParameters:
      Name                           Flags
      f                              final

  public <T1 extends java.lang.Object, T2 extends java.lang.Object, R extends java.lang.Object> scala.Function2<T1, T2, R> parsePure2(org.sireum.Json$Parser, java.lang.String);
    descriptor: (Lorg/sireum/Json$Parser;Ljava/lang/String;)Lscala/Function2;
    flags: (0x0001) ACC_PUBLIC
    Code:
      stack=3, locals=3, args_size=3
         0: getstatic     #29                 // Field org/sireum/JsonFun_Ext$.MODULE$:Lorg/sireum/JsonFun_Ext$;
         3: aload_1
         4: aload_2
         5: invokevirtual #75                 // Method org/sireum/JsonFun_Ext$.parsePure2:(Lorg/sireum/Json$Parser;Ljava/lang/String;)Lscala/Function2;
         8: areturn
      LineNumberTable:
        line 2424: 0
      LocalVariableTable:
        Start  Length  Slot  Name   Signature
            0       9     0  this   Lorg/sireum/Json$Fun$;
            0       9     1 parser   Lorg/sireum/Json$Parser;
            0       9     2     f   Ljava/lang/String;
    Signature: #73                          // <T1:Ljava/lang/Object;T2:Ljava/lang/Object;R:Ljava/lang/Object;>(Lorg/sireum/Json$Parser;Ljava/lang/String;)Lscala/Function2<TT1;TT2;TR;>;
    MethodParameters:
      Name                           Flags
      parser                         final
      f                              final

  public <T1 extends java.lang.Object, T2 extends java.lang.Object, R extends java.lang.Object> java.lang.String print2(scala.Function2<T1, T2, R>);
    descriptor: (Lscala/Function2;)Ljava/lang/String;
    flags: (0x0001) ACC_PUBLIC
    Code:
      stack=2, locals=2, args_size=2
         0: getstatic     #29                 // Field org/sireum/JsonFun_Ext$.MODULE$:Lorg/sireum/JsonFun_Ext$;
         3: aload_1
         4: invokevirtual #78                 // Method org/sireum/JsonFun_Ext$.print2:(Lscala/Function2;)Ljava/lang/String;
         7: areturn
      LineNumberTable:
        line 2426: 0
      LocalVariableTable:
        Start  Length  Slot  Name   Signature
            0       8     0  this   Lorg/sireum/Json$Fun$;
            0       8     1     f   Lscala/Function2;
    Signature: #67                          // <T1:Ljava/lang/Object;T2:Ljava/lang/Object;R:Ljava/lang/Object;>(Lscala/Function2<TT1;TT2;TR;>;)Ljava/lang/String;
    MethodParameters:
      Name                           Flags
      f                              final

  public <T1 extends java.lang.Object, T2 extends java.lang.Object, R extends java.lang.Object> scala.Function2<T1, T2, R> parse2(org.sireum.Json$Parser, java.lang.String);
    descriptor: (Lorg/sireum/Json$Parser;Ljava/lang/String;)Lscala/Function2;
    flags: (0x0001) ACC_PUBLIC
    Code:
      stack=3, locals=3, args_size=3
         0: getstatic     #29                 // Field org/sireum/JsonFun_Ext$.MODULE$:Lorg/sireum/JsonFun_Ext$;
         3: aload_1
         4: aload_2
         5: invokevirtual #81                 // Method org/sireum/JsonFun_Ext$.parse2:(Lorg/sireum/Json$Parser;Ljava/lang/String;)Lscala/Function2;
         8: areturn
      LineNumberTable:
        line 2427: 0
      LocalVariableTable:
        Start  Length  Slot  Name   Signature
            0       9     0  this   Lorg/sireum/Json$Fun$;
            0       9     1 parser   Lorg/sireum/Json$Parser;
            0       9     2     f   Ljava/lang/String;
    Signature: #73                          // <T1:Ljava/lang/Object;T2:Ljava/lang/Object;R:Ljava/lang/Object;>(Lorg/sireum/Json$Parser;Ljava/lang/String;)Lscala/Function2<TT1;TT2;TR;>;
    MethodParameters:
      Name                           Flags
      parser                         final
      f                              final

  public <T1 extends java.lang.Object, T2 extends java.lang.Object, T3 extends java.lang.Object, R extends java.lang.Object> java.lang.String printPure3(scala.Function3<T1, T2, T3, R>);
    descriptor: (Lscala/Function3;)Ljava/lang/String;
    flags: (0x0001) ACC_PUBLIC
    Code:
      stack=2, locals=2, args_size=2
         0: getstatic     #29                 // Field org/sireum/JsonFun_Ext$.MODULE$:Lorg/sireum/JsonFun_Ext$;
         3: aload_1
         4: invokevirtual #86                 // Method org/sireum/JsonFun_Ext$.printPure3:(Lscala/Function3;)Ljava/lang/String;
         7: areturn
      LineNumberTable:
        line 2429: 0
      LocalVariableTable:
        Start  Length  Slot  Name   Signature
            0       8     0  this   Lorg/sireum/Json$Fun$;
            0       8     1     f   Lscala/Function3;
    Signature: #84                          // <T1:Ljava/lang/Object;T2:Ljava/lang/Object;T3:Ljava/lang/Object;R:Ljava/lang/Object;>(Lscala/Function3<TT1;TT2;TT3;TR;>;)Ljava/lang/String;
    MethodParameters:
      Name                           Flags
      f                              final

  public <T1 extends java.lang.Object, T2 extends java.lang.Object, T3 extends java.lang.Object, R extends java.lang.Object> scala.Function3<T1, T2, T3, R> parsePure3(org.sireum.Json$Parser, java.lang.String);
    descriptor: (Lorg/sireum/Json$Parser;Ljava/lang/String;)Lscala/Function3;
    flags: (0x0001) ACC_PUBLIC
    Code:
      stack=3, locals=3, args_size=3
         0: getstatic     #29                 // Field org/sireum/JsonFun_Ext$.MODULE$:Lorg/sireum/JsonFun_Ext$;
         3: aload_1
         4: aload_2
         5: invokevirtual #92                 // Method org/sireum/JsonFun_Ext$.parsePure3:(Lorg/sireum/Json$Parser;Ljava/lang/String;)Lscala/Function3;
         8: areturn
      LineNumberTable:
        line 2430: 0
      LocalVariableTable:
        Start  Length  Slot  Name   Signature
            0       9     0  this   Lorg/sireum/Json$Fun$;
            0       9     1 parser   Lorg/sireum/Json$Parser;
            0       9     2     f   Ljava/lang/String;
    Signature: #90                          // <T1:Ljava/lang/Object;T2:Ljava/lang/Object;T3:Ljava/lang/Object;R:Ljava/lang/Object;>(Lorg/sireum/Json$Parser;Ljava/lang/String;)Lscala/Function3<TT1;TT2;TT3;TR;>;
    MethodParameters:
      Name                           Flags
      parser                         final
      f                              final

  public <T1 extends java.lang.Object, T2 extends java.lang.Object, T3 extends java.lang.Object, R extends java.lang.Object> java.lang.String print3(scala.Function3<T1, T2, T3, R>);
    descriptor: (Lscala/Function3;)Ljava/lang/String;
    flags: (0x0001) ACC_PUBLIC
    Code:
      stack=2, locals=2, args_size=2
         0: getstatic     #29                 // Field org/sireum/JsonFun_Ext$.MODULE$:Lorg/sireum/JsonFun_Ext$;
         3: aload_1
         4: invokevirtual #95                 // Method org/sireum/JsonFun_Ext$.print3:(Lscala/Function3;)Ljava/lang/String;
         7: areturn
      LineNumberTable:
        line 2432: 0
      LocalVariableTable:
        Start  Length  Slot  Name   Signature
            0       8     0  this   Lorg/sireum/Json$Fun$;
            0       8     1     f   Lscala/Function3;
    Signature: #84                          // <T1:Ljava/lang/Object;T2:Ljava/lang/Object;T3:Ljava/lang/Object;R:Ljava/lang/Object;>(Lscala/Function3<TT1;TT2;TT3;TR;>;)Ljava/lang/String;
    MethodParameters:
      Name                           Flags
      f                              final

  public <T1 extends java.lang.Object, T2 extends java.lang.Object, T3 extends java.lang.Object, R extends java.lang.Object> scala.Function3<T1, T2, T3, R> parse3(org.sireum.Json$Parser, java.lang.String);
    descriptor: (Lorg/sireum/Json$Parser;Ljava/lang/String;)Lscala/Function3;
    flags: (0x0001) ACC_PUBLIC
    Code:
      stack=3, locals=3, args_size=3
         0: getstatic     #29                 // Field org/sireum/JsonFun_Ext$.MODULE$:Lorg/sireum/JsonFun_Ext$;
         3: aload_1
         4: aload_2
         5: invokevirtual #98                 // Method org/sireum/JsonFun_Ext$.parse3:(Lorg/sireum/Json$Parser;Ljava/lang/String;)Lscala/Function3;
         8: areturn
      LineNumberTable:
        line 2433: 0
      LocalVariableTable:
        Start  Length  Slot  Name   Signature
            0       9     0  this   Lorg/sireum/Json$Fun$;
            0       9     1 parser   Lorg/sireum/Json$Parser;
            0       9     2     f   Ljava/lang/String;
    Signature: #90                          // <T1:Ljava/lang/Object;T2:Ljava/lang/Object;T3:Ljava/lang/Object;R:Ljava/lang/Object;>(Lorg/sireum/Json$Parser;Ljava/lang/String;)Lscala/Function3<TT1;TT2;TT3;TR;>;
    MethodParameters:
      Name                           Flags
      parser                         final
      f                              final

  public <T1 extends java.lang.Object, T2 extends java.lang.Object, T3 extends java.lang.Object, T4 extends java.lang.Object, R extends java.lang.Object> java.lang.String printPure4(scala.Function4<T1, T2, T3, T4, R>);
    descriptor: (Lscala/Function4;)Ljava/lang/String;
    flags: (0x0001) ACC_PUBLIC
    Code:
      stack=2, locals=2, args_size=2
         0: getstatic     #29                 // Field org/sireum/JsonFun_Ext$.MODULE$:Lorg/sireum/JsonFun_Ext$;
         3: aload_1
         4: invokevirtual #103                // Method org/sireum/JsonFun_Ext$.printPure4:(Lscala/Function4;)Ljava/lang/String;
         7: areturn
      LineNumberTable:
        line 2435: 0
      LocalVariableTable:
        Start  Length  Slot  Name   Signature
            0       8     0  this   Lorg/sireum/Json$Fun$;
            0       8     1     f   Lscala/Function4;
    Signature: #101                         // <T1:Ljava/lang/Object;T2:Ljava/lang/Object;T3:Ljava/lang/Object;T4:Ljava/lang/Object;R:Ljava/lang/Object;>(Lscala/Function4<TT1;TT2;TT3;TT4;TR;>;)Ljava/lang/String;
    MethodParameters:
      Name                           Flags
      f                              final

  public <T1 extends java.lang.Object, T2 extends java.lang.Object, T3 extends java.lang.Object, T4 extends java.lang.Object, R extends java.lang.Object> scala.Function4<T1, T2, T3, T4, R> parsePure4(org.sireum.Json$Parser, java.lang.String);
    descriptor: (Lorg/sireum/Json$Parser;Ljava/lang/String;)Lscala/Function4;
    flags: (0x0001) ACC_PUBLIC
    Code:
      stack=3, locals=3, args_size=3
         0: getstatic     #29                 // Field org/sireum/JsonFun_Ext$.MODULE$:Lorg/sireum/JsonFun_Ext$;
         3: aload_1
         4: aload_2
         5: invokevirtual #109                // Method org/sireum/JsonFun_Ext$.parsePure4:(Lorg/sireum/Json$Parser;Ljava/lang/String;)Lscala/Function4;
         8: areturn
      LineNumberTable:
        line 2436: 0
      LocalVariableTable:
        Start  Length  Slot  Name   Signature
            0       9     0  this   Lorg/sireum/Json$Fun$;
            0       9     1 parser   Lorg/sireum/Json$Parser;
            0       9     2     f   Ljava/lang/String;
    Signature: #107                         // <T1:Ljava/lang/Object;T2:Ljava/lang/Object;T3:Ljava/lang/Object;T4:Ljava/lang/Object;R:Ljava/lang/Object;>(Lorg/sireum/Json$Parser;Ljava/lang/String;)Lscala/Function4<TT1;TT2;TT3;TT4;TR;>;
    MethodParameters:
      Name                           Flags
      parser                         final
      f                              final

  public <T1 extends java.lang.Object, T2 extends java.lang.Object, T3 extends java.lang.Object, T4 extends java.lang.Object, R extends java.lang.Object> java.lang.String print4(scala.Function4<T1, T2, T3, T4, R>);
    descriptor: (Lscala/Function4;)Ljava/lang/String;
    flags: (0x0001) ACC_PUBLIC
    Code:
      stack=2, locals=2, args_size=2
         0: getstatic     #29                 // Field org/sireum/JsonFun_Ext$.MODULE$:Lorg/sireum/JsonFun_Ext$;
         3: aload_1
         4: invokevirtual #112                // Method org/sireum/JsonFun_Ext$.print4:(Lscala/Function4;)Ljava/lang/String;
         7: areturn
      LineNumberTable:
        line 2438: 0
      LocalVariableTable:
        Start  Length  Slot  Name   Signature
            0       8     0  this   Lorg/sireum/Json$Fun$;
            0       8     1     f   Lscala/Function4;
    Signature: #101                         // <T1:Ljava/lang/Object;T2:Ljava/lang/Object;T3:Ljava/lang/Object;T4:Ljava/lang/Object;R:Ljava/lang/Object;>(Lscala/Function4<TT1;TT2;TT3;TT4;TR;>;)Ljava/lang/String;
    MethodParameters:
      Name                           Flags
      f                              final

  public <T1 extends java.lang.Object, T2 extends java.lang.Object, T3 extends java.lang.Object, T4 extends java.lang.Object, R extends java.lang.Object> scala.Function4<T1, T2, T3, T4, R> parse4(org.sireum.Json$Parser, java.lang.String);
    descriptor: (Lorg/sireum/Json$Parser;Ljava/lang/String;)Lscala/Function4;
    flags: (0x0001) ACC_PUBLIC
    Code:
      stack=3, locals=3, args_size=3
         0: getstatic     #29                 // Field org/sireum/JsonFun_Ext$.MODULE$:Lorg/sireum/JsonFun_Ext$;
         3: aload_1
         4: aload_2
         5: invokevirtual #115                // Method org/sireum/JsonFun_Ext$.parse4:(Lorg/sireum/Json$Parser;Ljava/lang/String;)Lscala/Function4;
         8: areturn
      LineNumberTable:
        line 2439: 0
      LocalVariableTable:
        Start  Length  Slot  Name   Signature
            0       9     0  this   Lorg/sireum/Json$Fun$;
            0       9     1 parser   Lorg/sireum/Json$Parser;
            0       9     2     f   Ljava/lang/String;
    Signature: #107                         // <T1:Ljava/lang/Object;T2:Ljava/lang/Object;T3:Ljava/lang/Object;T4:Ljava/lang/Object;R:Ljava/lang/Object;>(Lorg/sireum/Json$Parser;Ljava/lang/String;)Lscala/Function4<TT1;TT2;TT3;TT4;TR;>;
    MethodParameters:
      Name                           Flags
      parser                         final
      f                              final

  public <T1 extends java.lang.Object, T2 extends java.lang.Object, T3 extends java.lang.Object, T4 extends java.lang.Object, T5 extends java.lang.Object, R extends java.lang.Object> java.lang.String printPure5(scala.Function5<T1, T2, T3, T4, T5, R>);
    descriptor: (Lscala/Function5;)Ljava/lang/String;
    flags: (0x0001) ACC_PUBLIC
    Code:
      stack=2, locals=2, args_size=2
         0: getstatic     #29                 // Field org/sireum/JsonFun_Ext$.MODULE$:Lorg/sireum/JsonFun_Ext$;
         3: aload_1
         4: invokevirtual #120                // Method org/sireum/JsonFun_Ext$.printPure5:(Lscala/Function5;)Ljava/lang/String;
         7: areturn
      LineNumberTable:
        line 2441: 0
      LocalVariableTable:
        Start  Length  Slot  Name   Signature
            0       8     0  this   Lorg/sireum/Json$Fun$;
            0       8     1     f   Lscala/Function5;
    Signature: #118                         // <T1:Ljava/lang/Object;T2:Ljava/lang/Object;T3:Ljava/lang/Object;T4:Ljava/lang/Object;T5:Ljava/lang/Object;R:Ljava/lang/Object;>(Lscala/Function5<TT1;TT2;TT3;TT4;TT5;TR;>;)Ljava/lang/String;
    MethodParameters:
      Name                           Flags
      f                              final

  public <T1 extends java.lang.Object, T2 extends java.lang.Object, T3 extends java.lang.Object, T4 extends java.lang.Object, T5 extends java.lang.Object, R extends java.lang.Object> scala.Function5<T1, T2, T3, T4, T5, R> parsePure5(org.sireum.Json$Parser, java.lang.String);
    descriptor: (Lorg/sireum/Json$Parser;Ljava/lang/String;)Lscala/Function5;
    flags: (0x0001) ACC_PUBLIC
    Code:
      stack=3, locals=3, args_size=3
         0: getstatic     #29                 // Field org/sireum/JsonFun_Ext$.MODULE$:Lorg/sireum/JsonFun_Ext$;
         3: aload_1
         4: aload_2
         5: invokevirtual #126                // Method org/sireum/JsonFun_Ext$.parsePure5:(Lorg/sireum/Json$Parser;Ljava/lang/String;)Lscala/Function5;
         8: areturn
      LineNumberTable:
        line 2442: 0
      LocalVariableTable:
        Start  Length  Slot  Name   Signature
            0       9     0  this   Lorg/sireum/Json$Fun$;
            0       9     1 parser   Lorg/sireum/Json$Parser;
            0       9     2     f   Ljava/lang/String;
    Signature: #124                         // <T1:Ljava/lang/Object;T2:Ljava/lang/Object;T3:Ljava/lang/Object;T4:Ljava/lang/Object;T5:Ljava/lang/Object;R:Ljava/lang/Object;>(Lorg/sireum/Json$Parser;Ljava/lang/String;)Lscala/Function5<TT1;TT2;TT3;TT4;TT5;TR;>;
    MethodParameters:
      Name                           Flags
      parser                         final
      f                              final

  public <T1 extends java.lang.Object, T2 extends java.lang.Object, T3 extends java.lang.Object, T4 extends java.lang.Object, T5 extends java.lang.Object, R extends java.lang.Object> java.lang.String print5(scala.Function5<T1, T2, T3, T4, T5, R>);
    descriptor: (Lscala/Function5;)Ljava/lang/String;
    flags: (0x0001) ACC_PUBLIC
    Code:
      stack=2, locals=2, args_size=2
         0: getstatic     #29                 // Field org/sireum/JsonFun_Ext$.MODULE$:Lorg/sireum/JsonFun_Ext$;
         3: aload_1
         4: invokevirtual #129                // Method org/sireum/JsonFun_Ext$.print5:(Lscala/Function5;)Ljava/lang/String;
         7: areturn
      LineNumberTable:
        line 2444: 0
      LocalVariableTable:
        Start  Length  Slot  Name   Signature
            0       8     0  this   Lorg/sireum/Json$Fun$;
            0       8     1     f   Lscala/Function5;
    Signature: #118                         // <T1:Ljava/lang/Object;T2:Ljava/lang/Object;T3:Ljava/lang/Object;T4:Ljava/lang/Object;T5:Ljava/lang/Object;R:Ljava/lang/Object;>(Lscala/Function5<TT1;TT2;TT3;TT4;TT5;TR;>;)Ljava/lang/String;
    MethodParameters:
      Name                           Flags
      f                              final

  public <T1 extends java.lang.Object, T2 extends java.lang.Object, T3 extends java.lang.Object, T4 extends java.lang.Object, T5 extends java.lang.Object, R extends java.lang.Object> scala.Function5<T1, T2, T3, T4, T5, R> parse5(org.sireum.Json$Parser, java.lang.String);
    descriptor: (Lorg/sireum/Json$Parser;Ljava/lang/String;)Lscala/Function5;
    flags: (0x0001) ACC_PUBLIC
    Code:
      stack=3, locals=3, args_size=3
         0: getstatic     #29                 // Field org/sireum/JsonFun_Ext$.MODULE$:Lorg/sireum/JsonFun_Ext$;
         3: aload_1
         4: aload_2
         5: invokevirtual #132                // Method org/sireum/JsonFun_Ext$.parse5:(Lorg/sireum/Json$Parser;Ljava/lang/String;)Lscala/Function5;
         8: areturn
      LineNumberTable:
        line 2445: 0
      LocalVariableTable:
        Start  Length  Slot  Name   Signature
            0       9     0  this   Lorg/sireum/Json$Fun$;
            0       9     1 parser   Lorg/sireum/Json$Parser;
            0       9     2     f   Ljava/lang/String;
    Signature: #124                         // <T1:Ljava/lang/Object;T2:Ljava/lang/Object;T3:Ljava/lang/Object;T4:Ljava/lang/Object;T5:Ljava/lang/Object;R:Ljava/lang/Object;>(Lorg/sireum/Json$Parser;Ljava/lang/String;)Lscala/Function5<TT1;TT2;TT3;TT4;TT5;TR;>;
    MethodParameters:
      Name                           Flags
      parser                         final
      f                              final

  public <T1 extends java.lang.Object, T2 extends java.lang.Object, T3 extends java.lang.Object, T4 extends java.lang.Object, T5 extends java.lang.Object, T6 extends java.lang.Object, R extends java.lang.Object> java.lang.String printPure6(scala.Function6<T1, T2, T3, T4, T5, T6, R>);
    descriptor: (Lscala/Function6;)Ljava/lang/String;
    flags: (0x0001) ACC_PUBLIC
    Code:
      stack=2, locals=2, args_size=2
         0: getstatic     #29                 // Field org/sireum/JsonFun_Ext$.MODULE$:Lorg/sireum/JsonFun_Ext$;
         3: aload_1
         4: invokevirtual #137                // Method org/sireum/JsonFun_Ext$.printPure6:(Lscala/Function6;)Ljava/lang/String;
         7: areturn
      LineNumberTable:
        line 2447: 0
      LocalVariableTable:
        Start  Length  Slot  Name   Signature
            0       8     0  this   Lorg/sireum/Json$Fun$;
            0       8     1     f   Lscala/Function6;
    Signature: #135                         // <T1:Ljava/lang/Object;T2:Ljava/lang/Object;T3:Ljava/lang/Object;T4:Ljava/lang/Object;T5:Ljava/lang/Object;T6:Ljava/lang/Object;R:Ljava/lang/Object;>(Lscala/Function6<TT1;TT2;TT3;TT4;TT5;TT6;TR;>;)Ljava/lang/String;
    MethodParameters:
      Name                           Flags
      f                              final

  public <T1 extends java.lang.Object, T2 extends java.lang.Object, T3 extends java.lang.Object, T4 extends java.lang.Object, T5 extends java.lang.Object, T6 extends java.lang.Object, R extends java.lang.Object> scala.Function6<T1, T2, T3, T4, T5, T6, R> parsePure6(org.sireum.Json$Parser, java.lang.String);
    descriptor: (Lorg/sireum/Json$Parser;Ljava/lang/String;)Lscala/Function6;
    flags: (0x0001) ACC_PUBLIC
    Code:
      stack=3, locals=3, args_size=3
         0: getstatic     #29                 // Field org/sireum/JsonFun_Ext$.MODULE$:Lorg/sireum/JsonFun_Ext$;
         3: aload_1
         4: aload_2
         5: invokevirtual #143                // Method org/sireum/JsonFun_Ext$.parsePure6:(Lorg/sireum/Json$Parser;Ljava/lang/String;)Lscala/Function6;
         8: areturn
      LineNumberTable:
        line 2448: 0
      LocalVariableTable:
        Start  Length  Slot  Name   Signature
            0       9     0  this   Lorg/sireum/Json$Fun$;
            0       9     1 parser   Lorg/sireum/Json$Parser;
            0       9     2     f   Ljava/lang/String;
    Signature: #141                         // <T1:Ljava/lang/Object;T2:Ljava/lang/Object;T3:Ljava/lang/Object;T4:Ljava/lang/Object;T5:Ljava/lang/Object;T6:Ljava/lang/Object;R:Ljava/lang/Object;>(Lorg/sireum/Json$Parser;Ljava/lang/String;)Lscala/Function6<TT1;TT2;TT3;TT4;TT5;TT6;TR;>;
    MethodParameters:
      Name                           Flags
      parser                         final
      f                              final

  public <T1 extends java.lang.Object, T2 extends java.lang.Object, T3 extends java.lang.Object, T4 extends java.lang.Object, T5 extends java.lang.Object, T6 extends java.lang.Object, R extends java.lang.Object> java.lang.String print6(scala.Function6<T1, T2, T3, T4, T5, T6, R>);
    descriptor: (Lscala/Function6;)Ljava/lang/String;
    flags: (0x0001) ACC_PUBLIC
    Code:
      stack=2, locals=2, args_size=2
         0: getstatic     #29                 // Field org/sireum/JsonFun_Ext$.MODULE$:Lorg/sireum/JsonFun_Ext$;
         3: aload_1
         4: invokevirtual #146                // Method org/sireum/JsonFun_Ext$.print6:(Lscala/Function6;)Ljava/lang/String;
         7: areturn
      LineNumberTable:
        line 2450: 0
      LocalVariableTable:
        Start  Length  Slot  Name   Signature
            0       8     0  this   Lorg/sireum/Json$Fun$;
            0       8     1     f   Lscala/Function6;
    Signature: #135                         // <T1:Ljava/lang/Object;T2:Ljava/lang/Object;T3:Ljava/lang/Object;T4:Ljava/lang/Object;T5:Ljava/lang/Object;T6:Ljava/lang/Object;R:Ljava/lang/Object;>(Lscala/Function6<TT1;TT2;TT3;TT4;TT5;TT6;TR;>;)Ljava/lang/String;
    MethodParameters:
      Name                           Flags
      f                              final

  public <T1 extends java.lang.Object, T2 extends java.lang.Object, T3 extends java.lang.Object, T4 extends java.lang.Object, T5 extends java.lang.Object, T6 extends java.lang.Object, R extends java.lang.Object> scala.Function6<T1, T2, T3, T4, T5, T6, R> parse6(org.sireum.Json$Parser, java.lang.String);
    descriptor: (Lorg/sireum/Json$Parser;Ljava/lang/String;)Lscala/Function6;
    flags: (0x0001) ACC_PUBLIC
    Code:
      stack=3, locals=3, args_size=3
         0: getstatic     #29                 // Field org/sireum/JsonFun_Ext$.MODULE$:Lorg/sireum/JsonFun_Ext$;
         3: aload_1
         4: aload_2
         5: invokevirtual #149                // Method org/sireum/JsonFun_Ext$.parse6:(Lorg/sireum/Json$Parser;Ljava/lang/String;)Lscala/Function6;
         8: areturn
      LineNumberTable:
        line 2451: 0
      LocalVariableTable:
        Start  Length  Slot  Name   Signature
            0       9     0  this   Lorg/sireum/Json$Fun$;
            0       9     1 parser   Lorg/sireum/Json$Parser;
            0       9     2     f   Ljava/lang/String;
    Signature: #141                         // <T1:Ljava/lang/Object;T2:Ljava/lang/Object;T3:Ljava/lang/Object;T4:Ljava/lang/Object;T5:Ljava/lang/Object;T6:Ljava/lang/Object;R:Ljava/lang/Object;>(Lorg/sireum/Json$Parser;Ljava/lang/String;)Lscala/Function6<TT1;TT2;TT3;TT4;TT5;TT6;TR;>;
    MethodParameters:
      Name                           Flags
      parser                         final
      f                              final

  public <T1 extends java.lang.Object, T2 extends java.lang.Object, T3 extends java.lang.Object, T4 extends java.lang.Object, T5 extends java.lang.Object, T6 extends java.lang.Object, T7 extends java.lang.Object, R extends java.lang.Object> java.lang.String printPure7(scala.Function7<T1, T2, T3, T4, T5, T6, T7, R>);
    descriptor: (Lscala/Function7;)Ljava/lang/String;
    flags: (0x0001) ACC_PUBLIC
    Code:
      stack=2, locals=2, args_size=2
         0: getstatic     #29                 // Field org/sireum/JsonFun_Ext$.MODULE$:Lorg/sireum/JsonFun_Ext$;
         3: aload_1
         4: invokevirtual #154                // Method org/sireum/JsonFun_Ext$.printPure7:(Lscala/Function7;)Ljava/lang/String;
         7: areturn
      LineNumberTable:
        line 2453: 0
      LocalVariableTable:
        Start  Length  Slot  Name   Signature
            0       8     0  this   Lorg/sireum/Json$Fun$;
            0       8     1     f   Lscala/Function7;
    Signature: #152                         // <T1:Ljava/lang/Object;T2:Ljava/lang/Object;T3:Ljava/lang/Object;T4:Ljava/lang/Object;T5:Ljava/lang/Object;T6:Ljava/lang/Object;T7:Ljava/lang/Object;R:Ljava/lang/Object;>(Lscala/Function7<TT1;TT2;TT3;TT4;TT5;TT6;TT7;TR;>;)Ljava/lang/String;
    MethodParameters:
      Name                           Flags
      f                              final

  public <T1 extends java.lang.Object, T2 extends java.lang.Object, T3 extends java.lang.Object, T4 extends java.lang.Object, T5 extends java.lang.Object, T6 extends java.lang.Object, T7 extends java.lang.Object, R extends java.lang.Object> scala.Function7<T1, T2, T3, T4, T5, T6, T7, R> parsePure7(org.sireum.Json$Parser, java.lang.String);
    descriptor: (Lorg/sireum/Json$Parser;Ljava/lang/String;)Lscala/Function7;
    flags: (0x0001) ACC_PUBLIC
    Code:
      stack=3, locals=3, args_size=3
         0: getstatic     #29                 // Field org/sireum/JsonFun_Ext$.MODULE$:Lorg/sireum/JsonFun_Ext$;
         3: aload_1
         4: aload_2
         5: invokevirtual #160                // Method org/sireum/JsonFun_Ext$.parsePure7:(Lorg/sireum/Json$Parser;Ljava/lang/String;)Lscala/Function7;
         8: areturn
      LineNumberTable:
        line 2454: 0
      LocalVariableTable:
        Start  Length  Slot  Name   Signature
            0       9     0  this   Lorg/sireum/Json$Fun$;
            0       9     1 parser   Lorg/sireum/Json$Parser;
            0       9     2     f   Ljava/lang/String;
    Signature: #158                         // <T1:Ljava/lang/Object;T2:Ljava/lang/Object;T3:Ljava/lang/Object;T4:Ljava/lang/Object;T5:Ljava/lang/Object;T6:Ljava/lang/Object;T7:Ljava/lang/Object;R:Ljava/lang/Object;>(Lorg/sireum/Json$Parser;Ljava/lang/String;)Lscala/Function7<TT1;TT2;TT3;TT4;TT5;TT6;TT7;TR;>;
    MethodParameters:
      Name                           Flags
      parser                         final
      f                              final

  public <T1 extends java.lang.Object, T2 extends java.lang.Object, T3 extends java.lang.Object, T4 extends java.lang.Object, T5 extends java.lang.Object, T6 extends java.lang.Object, T7 extends java.lang.Object, R extends java.lang.Object> java.lang.String print7(scala.Function7<T1, T2, T3, T4, T5, T6, T7, R>);
    descriptor: (Lscala/Function7;)Ljava/lang/String;
    flags: (0x0001) ACC_PUBLIC
    Code:
      stack=2, locals=2, args_size=2
         0: getstatic     #29                 // Field org/sireum/JsonFun_Ext$.MODULE$:Lorg/sireum/JsonFun_Ext$;
         3: aload_1
         4: invokevirtual #163                // Method org/sireum/JsonFun_Ext$.print7:(Lscala/Function7;)Ljava/lang/String;
         7: areturn
      LineNumberTable:
        line 2456: 0
      LocalVariableTable:
        Start  Length  Slot  Name   Signature
            0       8     0  this   Lorg/sireum/Json$Fun$;
            0       8     1     f   Lscala/Function7;
    Signature: #152                         // <T1:Ljava/lang/Object;T2:Ljava/lang/Object;T3:Ljava/lang/Object;T4:Ljava/lang/Object;T5:Ljava/lang/Object;T6:Ljava/lang/Object;T7:Ljava/lang/Object;R:Ljava/lang/Object;>(Lscala/Function7<TT1;TT2;TT3;TT4;TT5;TT6;TT7;TR;>;)Ljava/lang/String;
    MethodParameters:
      Name                           Flags
      f                              final

  public <T1 extends java.lang.Object, T2 extends java.lang.Object, T3 extends java.lang.Object, T4 extends java.lang.Object, T5 extends java.lang.Object, T6 extends java.lang.Object, T7 extends java.lang.Object, R extends java.lang.Object> scala.Function7<T1, T2, T3, T4, T5, T6, T7, R> parse7(org.sireum.Json$Parser, java.lang.String);
    descriptor: (Lorg/sireum/Json$Parser;Ljava/lang/String;)Lscala/Function7;
    flags: (0x0001) ACC_PUBLIC
    Code:
      stack=3, locals=3, args_size=3
         0: getstatic     #29                 // Field org/sireum/JsonFun_Ext$.MODULE$:Lorg/sireum/JsonFun_Ext$;
         3: aload_1
         4: aload_2
         5: invokevirtual #166                // Method org/sireum/JsonFun_Ext$.parse7:(Lorg/sireum/Json$Parser;Ljava/lang/String;)Lscala/Function7;
         8: areturn
      LineNumberTable:
        line 2457: 0
      LocalVariableTable:
        Start  Length  Slot  Name   Signature
            0       9     0  this   Lorg/sireum/Json$Fun$;
            0       9     1 parser   Lorg/sireum/Json$Parser;
            0       9     2     f   Ljava/lang/String;
    Signature: #158                         // <T1:Ljava/lang/Object;T2:Ljava/lang/Object;T3:Ljava/lang/Object;T4:Ljava/lang/Object;T5:Ljava/lang/Object;T6:Ljava/lang/Object;T7:Ljava/lang/Object;R:Ljava/lang/Object;>(Lorg/sireum/Json$Parser;Ljava/lang/String;)Lscala/Function7<TT1;TT2;TT3;TT4;TT5;TT6;TT7;TR;>;
    MethodParameters:
      Name                           Flags
      parser                         final
      f                              final

  public <T1 extends java.lang.Object, T2 extends java.lang.Object, T3 extends java.lang.Object, T4 extends java.lang.Object, T5 extends java.lang.Object, T6 extends java.lang.Object, T7 extends java.lang.Object, T8 extends java.lang.Object, R extends java.lang.Object> java.lang.String printPure8(scala.Function8<T1, T2, T3, T4, T5, T6, T7, T8, R>);
    descriptor: (Lscala/Function8;)Ljava/lang/String;
    flags: (0x0001) ACC_PUBLIC
    Code:
      stack=2, locals=2, args_size=2
         0: getstatic     #29                 // Field org/sireum/JsonFun_Ext$.MODULE$:Lorg/sireum/JsonFun_Ext$;
         3: aload_1
         4: invokevirtual #171                // Method org/sireum/JsonFun_Ext$.printPure8:(Lscala/Function8;)Ljava/lang/String;
         7: areturn
      LineNumberTable:
        line 2459: 0
      LocalVariableTable:
        Start  Length  Slot  Name   Signature
            0       8     0  this   Lorg/sireum/Json$Fun$;
            0       8     1     f   Lscala/Function8;
    Signature: #169                         // <T1:Ljava/lang/Object;T2:Ljava/lang/Object;T3:Ljava/lang/Object;T4:Ljava/lang/Object;T5:Ljava/lang/Object;T6:Ljava/lang/Object;T7:Ljava/lang/Object;T8:Ljava/lang/Object;R:Ljava/lang/Object;>(Lscala/Function8<TT1;TT2;TT3;TT4;TT5;TT6;TT7;TT8;TR;>;)Ljava/lang/String;
    MethodParameters:
      Name                           Flags
      f                              final

  public <T1 extends java.lang.Object, T2 extends java.lang.Object, T3 extends java.lang.Object, T4 extends java.lang.Object, T5 extends java.lang.Object, T6 extends java.lang.Object, T7 extends java.lang.Object, T8 extends java.lang.Object, R extends java.lang.Object> scala.Function8<T1, T2, T3, T4, T5, T6, T7, T8, R> parsePure8(org.sireum.Json$Parser, java.lang.String);
    descriptor: (Lorg/sireum/Json$Parser;Ljava/lang/String;)Lscala/Function8;
    flags: (0x0001) ACC_PUBLIC
    Code:
      stack=3, locals=3, args_size=3
         0: getstatic     #29                 // Field org/sireum/JsonFun_Ext$.MODULE$:Lorg/sireum/JsonFun_Ext$;
         3: aload_1
         4: aload_2
         5: invokevirtual #177                // Method org/sireum/JsonFun_Ext$.parsePure8:(Lorg/sireum/Json$Parser;Ljava/lang/String;)Lscala/Function8;
         8: areturn
      LineNumberTable:
        line 2460: 0
      LocalVariableTable:
        Start  Length  Slot  Name   Signature
            0       9     0  this   Lorg/sireum/Json$Fun$;
            0       9     1 parser   Lorg/sireum/Json$Parser;
            0       9     2     f   Ljava/lang/String;
    Signature: #175                         // <T1:Ljava/lang/Object;T2:Ljava/lang/Object;T3:Ljava/lang/Object;T4:Ljava/lang/Object;T5:Ljava/lang/Object;T6:Ljava/lang/Object;T7:Ljava/lang/Object;T8:Ljava/lang/Object;R:Ljava/lang/Object;>(Lorg/sireum/Json$Parser;Ljava/lang/String;)Lscala/Function8<TT1;TT2;TT3;TT4;TT5;TT6;TT7;TT8;TR;>;
    MethodParameters:
      Name                           Flags
      parser                         final
      f                              final

  public <T1 extends java.lang.Object, T2 extends java.lang.Object, T3 extends java.lang.Object, T4 extends java.lang.Object, T5 extends java.lang.Object, T6 extends java.lang.Object, T7 extends java.lang.Object, T8 extends java.lang.Object, R extends java.lang.Object> java.lang.String print8(scala.Function8<T1, T2, T3, T4, T5, T6, T7, T8, R>);
    descriptor: (Lscala/Function8;)Ljava/lang/String;
    flags: (0x0001) ACC_PUBLIC
    Code:
      stack=2, locals=2, args_size=2
         0: getstatic     #29                 // Field org/sireum/JsonFun_Ext$.MODULE$:Lorg/sireum/JsonFun_Ext$;
         3: aload_1
         4: invokevirtual #180                // Method org/sireum/JsonFun_Ext$.print8:(Lscala/Function8;)Ljava/lang/String;
         7: areturn
      LineNumberTable:
        line 2462: 0
      LocalVariableTable:
        Start  Length  Slot  Name   Signature
            0       8     0  this   Lorg/sireum/Json$Fun$;
            0       8     1     f   Lscala/Function8;
    Signature: #169                         // <T1:Ljava/lang/Object;T2:Ljava/lang/Object;T3:Ljava/lang/Object;T4:Ljava/lang/Object;T5:Ljava/lang/Object;T6:Ljava/lang/Object;T7:Ljava/lang/Object;T8:Ljava/lang/Object;R:Ljava/lang/Object;>(Lscala/Function8<TT1;TT2;TT3;TT4;TT5;TT6;TT7;TT8;TR;>;)Ljava/lang/String;
    MethodParameters:
      Name                           Flags
      f                              final

  public <T1 extends java.lang.Object, T2 extends java.lang.Object, T3 extends java.lang.Object, T4 extends java.lang.Object, T5 extends java.lang.Object, T6 extends java.lang.Object, T7 extends java.lang.Object, T8 extends java.lang.Object, R extends java.lang.Object> scala.Function8<T1, T2, T3, T4, T5, T6, T7, T8, R> parse8(org.sireum.Json$Parser, java.lang.String);
    descriptor: (Lorg/sireum/Json$Parser;Ljava/lang/String;)Lscala/Function8;
    flags: (0x0001) ACC_PUBLIC
    Code:
      stack=3, locals=3, args_size=3
         0: getstatic     #29                 // Field org/sireum/JsonFun_Ext$.MODULE$:Lorg/sireum/JsonFun_Ext$;
         3: aload_1
         4: aload_2
         5: invokevirtual #183                // Method org/sireum/JsonFun_Ext$.parse8:(Lorg/sireum/Json$Parser;Ljava/lang/String;)Lscala/Function8;
         8: areturn
      LineNumberTable:
        line 2463: 0
      LocalVariableTable:
        Start  Length  Slot  Name   Signature
            0       9     0  this   Lorg/sireum/Json$Fun$;
            0       9     1 parser   Lorg/sireum/Json$Parser;
            0       9     2     f   Ljava/lang/String;
    Signature: #175                         // <T1:Ljava/lang/Object;T2:Ljava/lang/Object;T3:Ljava/lang/Object;T4:Ljava/lang/Object;T5:Ljava/lang/Object;T6:Ljava/lang/Object;T7:Ljava/lang/Object;T8:Ljava/lang/Object;R:Ljava/lang/Object;>(Lorg/sireum/Json$Parser;Ljava/lang/String;)Lscala/Function8<TT1;TT2;TT3;TT4;TT5;TT6;TT7;TT8;TR;>;
    MethodParameters:
      Name                           Flags
      parser                         final
      f                              final

  public <T1 extends java.lang.Object, T2 extends java.lang.Object, T3 extends java.lang.Object, T4 extends java.lang.Object, T5 extends java.lang.Object, T6 extends java.lang.Object, T7 extends java.lang.Object, T8 extends java.lang.Object, T9 extends java.lang.Object, R extends java.lang.Object> java.lang.String printPure9(scala.Function9<T1, T2, T3, T4, T5, T6, T7, T8, T9, R>);
    descriptor: (Lscala/Function9;)Ljava/lang/String;
    flags: (0x0001) ACC_PUBLIC
    Code:
      stack=2, locals=2, args_size=2
         0: getstatic     #29                 // Field org/sireum/JsonFun_Ext$.MODULE$:Lorg/sireum/JsonFun_Ext$;
         3: aload_1
         4: invokevirtual #188                // Method org/sireum/JsonFun_Ext$.printPure9:(Lscala/Function9;)Ljava/lang/String;
         7: areturn
      LineNumberTable:
        line 2465: 0
      LocalVariableTable:
        Start  Length  Slot  Name   Signature
            0       8     0  this   Lorg/sireum/Json$Fun$;
            0       8     1     f   Lscala/Function9;
    Signature: #186                         // <T1:Ljava/lang/Object;T2:Ljava/lang/Object;T3:Ljava/lang/Object;T4:Ljava/lang/Object;T5:Ljava/lang/Object;T6:Ljava/lang/Object;T7:Ljava/lang/Object;T8:Ljava/lang/Object;T9:Ljava/lang/Object;R:Ljava/lang/Object;>(Lscala/Function9<TT1;TT2;TT3;TT4;TT5;TT6;TT7;TT8;TT9;TR;>;)Ljava/lang/String;
    MethodParameters:
      Name                           Flags
      f                              final

  public <T1 extends java.lang.Object, T2 extends java.lang.Object, T3 extends java.lang.Object, T4 extends java.lang.Object, T5 extends java.lang.Object, T6 extends java.lang.Object, T7 extends java.lang.Object, T8 extends java.lang.Object, T9 extends java.lang.Object, R extends java.lang.Object> scala.Function9<T1, T2, T3, T4, T5, T6, T7, T8, T9, R> parsePure9(org.sireum.Json$Parser, java.lang.String);
    descriptor: (Lorg/sireum/Json$Parser;Ljava/lang/String;)Lscala/Function9;
    flags: (0x0001) ACC_PUBLIC
    Code:
      stack=3, locals=3, args_size=3
         0: getstatic     #29                 // Field org/sireum/JsonFun_Ext$.MODULE$:Lorg/sireum/JsonFun_Ext$;
         3: aload_1
         4: aload_2
         5: invokevirtual #194                // Method org/sireum/JsonFun_Ext$.parsePure9:(Lorg/sireum/Json$Parser;Ljava/lang/String;)Lscala/Function9;
         8: areturn
      LineNumberTable:
        line 2466: 0
      LocalVariableTable:
        Start  Length  Slot  Name   Signature
            0       9     0  this   Lorg/sireum/Json$Fun$;
            0       9     1 parser   Lorg/sireum/Json$Parser;
            0       9     2     f   Ljava/lang/String;
    Signature: #192                         // <T1:Ljava/lang/Object;T2:Ljava/lang/Object;T3:Ljava/lang/Object;T4:Ljava/lang/Object;T5:Ljava/lang/Object;T6:Ljava/lang/Object;T7:Ljava/lang/Object;T8:Ljava/lang/Object;T9:Ljava/lang/Object;R:Ljava/lang/Object;>(Lorg/sireum/Json$Parser;Ljava/lang/String;)Lscala/Function9<TT1;TT2;TT3;TT4;TT5;TT6;TT7;TT8;TT9;TR;>;
    MethodParameters:
      Name                           Flags
      parser                         final
      f                              final

  public <T1 extends java.lang.Object, T2 extends java.lang.Object, T3 extends java.lang.Object, T4 extends java.lang.Object, T5 extends java.lang.Object, T6 extends java.lang.Object, T7 extends java.lang.Object, T8 extends java.lang.Object, T9 extends java.lang.Object, R extends java.lang.Object> java.lang.String print9(scala.Function9<T1, T2, T3, T4, T5, T6, T7, T8, T9, R>);
    descriptor: (Lscala/Function9;)Ljava/lang/String;
    flags: (0x0001) ACC_PUBLIC
    Code:
      stack=2, locals=2, args_size=2
         0: getstatic     #29                 // Field org/sireum/JsonFun_Ext$.MODULE$:Lorg/sireum/JsonFun_Ext$;
         3: aload_1
         4: invokevirtual #197                // Method org/sireum/JsonFun_Ext$.print9:(Lscala/Function9;)Ljava/lang/String;
         7: areturn
      LineNumberTable:
        line 2468: 0
      LocalVariableTable:
        Start  Length  Slot  Name   Signature
            0       8     0  this   Lorg/sireum/Json$Fun$;
            0       8     1     f   Lscala/Function9;
    Signature: #186                         // <T1:Ljava/lang/Object;T2:Ljava/lang/Object;T3:Ljava/lang/Object;T4:Ljava/lang/Object;T5:Ljava/lang/Object;T6:Ljava/lang/Object;T7:Ljava/lang/Object;T8:Ljava/lang/Object;T9:Ljava/lang/Object;R:Ljava/lang/Object;>(Lscala/Function9<TT1;TT2;TT3;TT4;TT5;TT6;TT7;TT8;TT9;TR;>;)Ljava/lang/String;
    MethodParameters:
      Name                           Flags
      f                              final

  public <T1 extends java.lang.Object, T2 extends java.lang.Object, T3 extends java.lang.Object, T4 extends java.lang.Object, T5 extends java.lang.Object, T6 extends java.lang.Object, T7 extends java.lang.Object, T8 extends java.lang.Object, T9 extends java.lang.Object, R extends java.lang.Object> scala.Function9<T1, T2, T3, T4, T5, T6, T7, T8, T9, R> parse9(org.sireum.Json$Parser, java.lang.String);
    descriptor: (Lorg/sireum/Json$Parser;Ljava/lang/String;)Lscala/Function9;
    flags: (0x0001) ACC_PUBLIC
    Code:
      stack=3, locals=3, args_size=3
         0: getstatic     #29                 // Field org/sireum/JsonFun_Ext$.MODULE$:Lorg/sireum/JsonFun_Ext$;
         3: aload_1
         4: aload_2
         5: invokevirtual #200                // Method org/sireum/JsonFun_Ext$.parse9:(Lorg/sireum/Json$Parser;Ljava/lang/String;)Lscala/Function9;
         8: areturn
      LineNumberTable:
        line 2469: 0
      LocalVariableTable:
        Start  Length  Slot  Name   Signature
            0       9     0  this   Lorg/sireum/Json$Fun$;
            0       9     1 parser   Lorg/sireum/Json$Parser;
            0       9     2     f   Ljava/lang/String;
    Signature: #192                         // <T1:Ljava/lang/Object;T2:Ljava/lang/Object;T3:Ljava/lang/Object;T4:Ljava/lang/Object;T5:Ljava/lang/Object;T6:Ljava/lang/Object;T7:Ljava/lang/Object;T8:Ljava/lang/Object;T9:Ljava/lang/Object;R:Ljava/lang/Object;>(Lorg/sireum/Json$Parser;Ljava/lang/String;)Lscala/Function9<TT1;TT2;TT3;TT4;TT5;TT6;TT7;TT8;TT9;TR;>;
    MethodParameters:
      Name                           Flags
      parser                         final
      f                              final

  public <T1 extends java.lang.Object, T2 extends java.lang.Object, T3 extends java.lang.Object, T4 extends java.lang.Object, T5 extends java.lang.Object, T6 extends java.lang.Object, T7 extends java.lang.Object, T8 extends java.lang.Object, T9 extends java.lang.Object, T10 extends java.lang.Object, R extends java.lang.Object> java.lang.String printPure10(scala.Function10<T1, T2, T3, T4, T5, T6, T7, T8, T9, T10, R>);
    descriptor: (Lscala/Function10;)Ljava/lang/String;
    flags: (0x0001) ACC_PUBLIC
    Code:
      stack=2, locals=2, args_size=2
         0: getstatic     #29                 // Field org/sireum/JsonFun_Ext$.MODULE$:Lorg/sireum/JsonFun_Ext$;
         3: aload_1
         4: invokevirtual #205                // Method org/sireum/JsonFun_Ext$.printPure10:(Lscala/Function10;)Ljava/lang/String;
         7: areturn
      LineNumberTable:
        line 2471: 0
      LocalVariableTable:
        Start  Length  Slot  Name   Signature
            0       8     0  this   Lorg/sireum/Json$Fun$;
            0       8     1     f   Lscala/Function10;
    Signature: #203                         // <T1:Ljava/lang/Object;T2:Ljava/lang/Object;T3:Ljava/lang/Object;T4:Ljava/lang/Object;T5:Ljava/lang/Object;T6:Ljava/lang/Object;T7:Ljava/lang/Object;T8:Ljava/lang/Object;T9:Ljava/lang/Object;T10:Ljava/lang/Object;R:Ljava/lang/Object;>(Lscala/Function10<TT1;TT2;TT3;TT4;TT5;TT6;TT7;TT8;TT9;TT10;TR;>;)Ljava/lang/String;
    MethodParameters:
      Name                           Flags
      f                              final

  public <T1 extends java.lang.Object, T2 extends java.lang.Object, T3 extends java.lang.Object, T4 extends java.lang.Object, T5 extends java.lang.Object, T6 extends java.lang.Object, T7 extends java.lang.Object, T8 extends java.lang.Object, T9 extends java.lang.Object, T10 extends java.lang.Object, R extends java.lang.Object> scala.Function10<T1, T2, T3, T4, T5, T6, T7, T8, T9, T10, R> parsePure10(org.sireum.Json$Parser, java.lang.String);
    descriptor: (Lorg/sireum/Json$Parser;Ljava/lang/String;)Lscala/Function10;
    flags: (0x0001) ACC_PUBLIC
    Code:
      stack=3, locals=3, args_size=3
         0: getstatic     #29                 // Field org/sireum/JsonFun_Ext$.MODULE$:Lorg/sireum/JsonFun_Ext$;
         3: aload_1
         4: aload_2
         5: invokevirtual #211                // Method org/sireum/JsonFun_Ext$.parsePure10:(Lorg/sireum/Json$Parser;Ljava/lang/String;)Lscala/Function10;
         8: areturn
      LineNumberTable:
        line 2472: 0
      LocalVariableTable:
        Start  Length  Slot  Name   Signature
            0       9     0  this   Lorg/sireum/Json$Fun$;
            0       9     1 parser   Lorg/sireum/Json$Parser;
            0       9     2     f   Ljava/lang/String;
    Signature: #209                         // <T1:Ljava/lang/Object;T2:Ljava/lang/Object;T3:Ljava/lang/Object;T4:Ljava/lang/Object;T5:Ljava/lang/Object;T6:Ljava/lang/Object;T7:Ljava/lang/Object;T8:Ljava/lang/Object;T9:Ljava/lang/Object;T10:Ljava/lang/Object;R:Ljava/lang/Object;>(Lorg/sireum/Json$Parser;Ljava/lang/String;)Lscala/Function10<TT1;TT2;TT3;TT4;TT5;TT6;TT7;TT8;TT9;TT10;TR;>;
    MethodParameters:
      Name                           Flags
      parser                         final
      f                              final

  public <T1 extends java.lang.Object, T2 extends java.lang.Object, T3 extends java.lang.Object, T4 extends java.lang.Object, T5 extends java.lang.Object, T6 extends java.lang.Object, T7 extends java.lang.Object, T8 extends java.lang.Object, T9 extends java.lang.Object, T10 extends java.lang.Object, R extends java.lang.Object> java.lang.String print10(scala.Function10<T1, T2, T3, T4, T5, T6, T7, T8, T9, T10, R>);
    descriptor: (Lscala/Function10;)Ljava/lang/String;
    flags: (0x0001) ACC_PUBLIC
    Code:
      stack=2, locals=2, args_size=2
         0: getstatic     #29                 // Field org/sireum/JsonFun_Ext$.MODULE$:Lorg/sireum/JsonFun_Ext$;
         3: aload_1
         4: invokevirtual #214                // Method org/sireum/JsonFun_Ext$.print10:(Lscala/Function10;)Ljava/lang/String;
         7: areturn
      LineNumberTable:
        line 2474: 0
      LocalVariableTable:
        Start  Length  Slot  Name   Signature
            0       8     0  this   Lorg/sireum/Json$Fun$;
            0       8     1     f   Lscala/Function10;
    Signature: #203                         // <T1:Ljava/lang/Object;T2:Ljava/lang/Object;T3:Ljava/lang/Object;T4:Ljava/lang/Object;T5:Ljava/lang/Object;T6:Ljava/lang/Object;T7:Ljava/lang/Object;T8:Ljava/lang/Object;T9:Ljava/lang/Object;T10:Ljava/lang/Object;R:Ljava/lang/Object;>(Lscala/Function10<TT1;TT2;TT3;TT4;TT5;TT6;TT7;TT8;TT9;TT10;TR;>;)Ljava/lang/String;
    MethodParameters:
      Name                           Flags
      f                              final

  public <T1 extends java.lang.Object, T2 extends java.lang.Object, T3 extends java.lang.Object, T4 extends java.lang.Object, T5 extends java.lang.Object, T6 extends java.lang.Object, T7 extends java.lang.Object, T8 extends java.lang.Object, T9 extends java.lang.Object, T10 extends java.lang.Object, R extends java.lang.Object> scala.Function10<T1, T2, T3, T4, T5, T6, T7, T8, T9, T10, R> parse10(org.sireum.Json$Parser, java.lang.String);
    descriptor: (Lorg/sireum/Json$Parser;Ljava/lang/String;)Lscala/Function10;
    flags: (0x0001) ACC_PUBLIC
    Code:
      stack=3, locals=3, args_size=3
         0: getstatic     #29                 // Field org/sireum/JsonFun_Ext$.MODULE$:Lorg/sireum/JsonFun_Ext$;
         3: aload_1
         4: aload_2
         5: invokevirtual #217                // Method org/sireum/JsonFun_Ext$.parse10:(Lorg/sireum/Json$Parser;Ljava/lang/String;)Lscala/Function10;
         8: areturn
      LineNumberTable:
        line 2475: 0
      LocalVariableTable:
        Start  Length  Slot  Name   Signature
            0       9     0  this   Lorg/sireum/Json$Fun$;
            0       9     1 parser   Lorg/sireum/Json$Parser;
            0       9     2     f   Ljava/lang/String;
    Signature: #209                         // <T1:Ljava/lang/Object;T2:Ljava/lang/Object;T3:Ljava/lang/Object;T4:Ljava/lang/Object;T5:Ljava/lang/Object;T6:Ljava/lang/Object;T7:Ljava/lang/Object;T8:Ljava/lang/Object;T9:Ljava/lang/Object;T10:Ljava/lang/Object;R:Ljava/lang/Object;>(Lorg/sireum/Json$Parser;Ljava/lang/String;)Lscala/Function10<TT1;TT2;TT3;TT4;TT5;TT6;TT7;TT8;TT9;TT10;TR;>;
    MethodParameters:
      Name                           Flags
      parser                         final
      f                              final

  public <T1 extends java.lang.Object, T2 extends java.lang.Object, T3 extends java.lang.Object, T4 extends java.lang.Object, T5 extends java.lang.Object, T6 extends java.lang.Object, T7 extends java.lang.Object, T8 extends java.lang.Object, T9 extends java.lang.Object, T10 extends java.lang.Object, T11 extends java.lang.Object, R extends java.lang.Object> java.lang.String printPure11(scala.Function11<T1, T2, T3, T4, T5, T6, T7, T8, T9, T10, T11, R>);
    descriptor: (Lscala/Function11;)Ljava/lang/String;
    flags: (0x0001) ACC_PUBLIC
    Code:
      stack=2, locals=2, args_size=2
         0: getstatic     #29                 // Field org/sireum/JsonFun_Ext$.MODULE$:Lorg/sireum/JsonFun_Ext$;
         3: aload_1
         4: invokevirtual #222                // Method org/sireum/JsonFun_Ext$.printPure11:(Lscala/Function11;)Ljava/lang/String;
         7: areturn
      LineNumberTable:
        line 2477: 0
      LocalVariableTable:
        Start  Length  Slot  Name   Signature
            0       8     0  this   Lorg/sireum/Json$Fun$;
            0       8     1     f   Lscala/Function11;
    Signature: #220                         // <T1:Ljava/lang/Object;T2:Ljava/lang/Object;T3:Ljava/lang/Object;T4:Ljava/lang/Object;T5:Ljava/lang/Object;T6:Ljava/lang/Object;T7:Ljava/lang/Object;T8:Ljava/lang/Object;T9:Ljava/lang/Object;T10:Ljava/lang/Object;T11:Ljava/lang/Object;R:Ljava/lang/Object;>(Lscala/Function11<TT1;TT2;TT3;TT4;TT5;TT6;TT7;TT8;TT9;TT10;TT11;TR;>;)Ljava/lang/String;
    MethodParameters:
      Name                           Flags
      f                              final

  public <T1 extends java.lang.Object, T2 extends java.lang.Object, T3 extends java.lang.Object, T4 extends java.lang.Object, T5 extends java.lang.Object, T6 extends java.lang.Object, T7 extends java.lang.Object, T8 extends java.lang.Object, T9 extends java.lang.Object, T10 extends java.lang.Object, T11 extends java.lang.Object, R extends java.lang.Object> scala.Function11<T1, T2, T3, T4, T5, T6, T7, T8, T9, T10, T11, R> parsePure11(org.sireum.Json$Parser, java.lang.String);
    descriptor: (Lorg/sireum/Json$Parser;Ljava/lang/String;)Lscala/Function11;
    flags: (0x0001) ACC_PUBLIC
    Code:
      stack=3, locals=3, args_size=3
         0: getstatic     #29                 // Field org/sireum/JsonFun_Ext$.MODULE$:Lorg/sireum/JsonFun_Ext$;
         3: aload_1
         4: aload_2
         5: invokevirtual #228                // Method org/sireum/JsonFun_Ext$.parsePure11:(Lorg/sireum/Json$Parser;Ljava/lang/String;)Lscala/Function11;
         8: areturn
      LineNumberTable:
        line 2478: 0
      LocalVariableTable:
        Start  Length  Slot  Name   Signature
            0       9     0  this   Lorg/sireum/Json$Fun$;
            0       9     1 parser   Lorg/sireum/Json$Parser;
            0       9     2     f   Ljava/lang/String;
    Signature: #226                         // <T1:Ljava/lang/Object;T2:Ljava/lang/Object;T3:Ljava/lang/Object;T4:Ljava/lang/Object;T5:Ljava/lang/Object;T6:Ljava/lang/Object;T7:Ljava/lang/Object;T8:Ljava/lang/Object;T9:Ljava/lang/Object;T10:Ljava/lang/Object;T11:Ljava/lang/Object;R:Ljava/lang/Object;>(Lorg/sireum/Json$Parser;Ljava/lang/String;)Lscala/Function11<TT1;TT2;TT3;TT4;TT5;TT6;TT7;TT8;TT9;TT10;TT11;TR;>;
    MethodParameters:
      Name                           Flags
      parser                         final
      f                              final

  public <T1 extends java.lang.Object, T2 extends java.lang.Object, T3 extends java.lang.Object, T4 extends java.lang.Object, T5 extends java.lang.Object, T6 extends java.lang.Object, T7 extends java.lang.Object, T8 extends java.lang.Object, T9 extends java.lang.Object, T10 extends java.lang.Object, T11 extends java.lang.Object, R extends java.lang.Object> java.lang.String print11(scala.Function11<T1, T2, T3, T4, T5, T6, T7, T8, T9, T10, T11, R>);
    descriptor: (Lscala/Function11;)Ljava/lang/String;
    flags: (0x0001) ACC_PUBLIC
    Code:
      stack=2, locals=2, args_size=2
         0: getstatic     #29                 // Field org/sireum/JsonFun_Ext$.MODULE$:Lorg/sireum/JsonFun_Ext$;
         3: aload_1
         4: invokevirtual #231                // Method org/sireum/JsonFun_Ext$.print11:(Lscala/Function11;)Ljava/lang/String;
         7: areturn
      LineNumberTable:
        line 2480: 0
      LocalVariableTable:
        Start  Length  Slot  Name   Signature
            0       8     0  this   Lorg/sireum/Json$Fun$;
            0       8     1     f   Lscala/Function11;
    Signature: #220                         // <T1:Ljava/lang/Object;T2:Ljava/lang/Object;T3:Ljava/lang/Object;T4:Ljava/lang/Object;T5:Ljava/lang/Object;T6:Ljava/lang/Object;T7:Ljava/lang/Object;T8:Ljava/lang/Object;T9:Ljava/lang/Object;T10:Ljava/lang/Object;T11:Ljava/lang/Object;R:Ljava/lang/Object;>(Lscala/Function11<TT1;TT2;TT3;TT4;TT5;TT6;TT7;TT8;TT9;TT10;TT11;TR;>;)Ljava/lang/String;
    MethodParameters:
      Name                           Flags
      f                              final

  public <T1 extends java.lang.Object, T2 extends java.lang.Object, T3 extends java.lang.Object, T4 extends java.lang.Object, T5 extends java.lang.Object, T6 extends java.lang.Object, T7 extends java.lang.Object, T8 extends java.lang.Object, T9 extends java.lang.Object, T10 extends java.lang.Object, T11 extends java.lang.Object, R extends java.lang.Object> scala.Function11<T1, T2, T3, T4, T5, T6, T7, T8, T9, T10, T11, R> parse11(org.sireum.Json$Parser, java.lang.String);
    descriptor: (Lorg/sireum/Json$Parser;Ljava/lang/String;)Lscala/Function11;
    flags: (0x0001) ACC_PUBLIC
    Code:
      stack=3, locals=3, args_size=3
         0: getstatic     #29                 // Field org/sireum/JsonFun_Ext$.MODULE$:Lorg/sireum/JsonFun_Ext$;
         3: aload_1
         4: aload_2
         5: invokevirtual #234                // Method org/sireum/JsonFun_Ext$.parse11:(Lorg/sireum/Json$Parser;Ljava/lang/String;)Lscala/Function11;
         8: areturn
      LineNumberTable:
        line 2481: 0
      LocalVariableTable:
        Start  Length  Slot  Name   Signature
            0       9     0  this   Lorg/sireum/Json$Fun$;
            0       9     1 parser   Lorg/sireum/Json$Parser;
            0       9     2     f   Ljava/lang/String;
    Signature: #226                         // <T1:Ljava/lang/Object;T2:Ljava/lang/Object;T3:Ljava/lang/Object;T4:Ljava/lang/Object;T5:Ljava/lang/Object;T6:Ljava/lang/Object;T7:Ljava/lang/Object;T8:Ljava/lang/Object;T9:Ljava/lang/Object;T10:Ljava/lang/Object;T11:Ljava/lang/Object;R:Ljava/lang/Object;>(Lorg/sireum/Json$Parser;Ljava/lang/String;)Lscala/Function11<TT1;TT2;TT3;TT4;TT5;TT6;TT7;TT8;TT9;TT10;TT11;TR;>;
    MethodParameters:
      Name                           Flags
      parser                         final
      f                              final

  public <T1 extends java.lang.Object, T2 extends java.lang.Object, T3 extends java.lang.Object, T4 extends java.lang.Object, T5 extends java.lang.Object, T6 extends java.lang.Object, T7 extends java.lang.Object, T8 extends java.lang.Object, T9 extends java.lang.Object, T10 extends java.lang.Object, T11 extends java.lang.Object, T12 extends java.lang.Object, R extends java.lang.Object> java.lang.String printPure12(scala.Function12<T1, T2, T3, T4, T5, T6, T7, T8, T9, T10, T11, T12, R>);
    descriptor: (Lscala/Function12;)Ljava/lang/String;
    flags: (0x0001) ACC_PUBLIC
    Code:
      stack=2, locals=2, args_size=2
         0: getstatic     #29                 // Field org/sireum/JsonFun_Ext$.MODULE$:Lorg/sireum/JsonFun_Ext$;
         3: aload_1
         4: invokevirtual #239                // Method org/sireum/JsonFun_Ext$.printPure12:(Lscala/Function12;)Ljava/lang/String;
         7: areturn
      LineNumberTable:
        line 2483: 0
      LocalVariableTable:
        Start  Length  Slot  Name   Signature
            0       8     0  this   Lorg/sireum/Json$Fun$;
            0       8     1     f   Lscala/Function12;
    Signature: #237                         // <T1:Ljava/lang/Object;T2:Ljava/lang/Object;T3:Ljava/lang/Object;T4:Ljava/lang/Object;T5:Ljava/lang/Object;T6:Ljava/lang/Object;T7:Ljava/lang/Object;T8:Ljava/lang/Object;T9:Ljava/lang/Object;T10:Ljava/lang/Object;T11:Ljava/lang/Object;T12:Ljava/lang/Object;R:Ljava/lang/Object;>(Lscala/Function12<TT1;TT2;TT3;TT4;TT5;TT6;TT7;TT8;TT9;TT10;TT11;TT12;TR;>;)Ljava/lang/String;
    MethodParameters:
      Name                           Flags
      f                              final

  public <T1 extends java.lang.Object, T2 extends java.lang.Object, T3 extends java.lang.Object, T4 extends java.lang.Object, T5 extends java.lang.Object, T6 extends java.lang.Object, T7 extends java.lang.Object, T8 extends java.lang.Object, T9 extends java.lang.Object, T10 extends java.lang.Object, T11 extends java.lang.Object, T12 extends java.lang.Object, R extends java.lang.Object> scala.Function12<T1, T2, T3, T4, T5, T6, T7, T8, T9, T10, T11, T12, R> parsePure12(org.sireum.Json$Parser, java.lang.String);
    descriptor: (Lorg/sireum/Json$Parser;Ljava/lang/String;)Lscala/Function12;
    flags: (0x0001) ACC_PUBLIC
    Code:
      stack=3, locals=3, args_size=3
         0: getstatic     #29                 // Field org/sireum/JsonFun_Ext$.MODULE$:Lorg/sireum/JsonFun_Ext$;
         3: aload_1
         4: aload_2
         5: invokevirtual #245                // Method org/sireum/JsonFun_Ext$.parsePure12:(Lorg/sireum/Json$Parser;Ljava/lang/String;)Lscala/Function12;
         8: areturn
      LineNumberTable:
        line 2484: 0
      LocalVariableTable:
        Start  Length  Slot  Name   Signature
            0       9     0  this   Lorg/sireum/Json$Fun$;
            0       9     1 parser   Lorg/sireum/Json$Parser;
            0       9     2     f   Ljava/lang/String;
    Signature: #243                         // <T1:Ljava/lang/Object;T2:Ljava/lang/Object;T3:Ljava/lang/Object;T4:Ljava/lang/Object;T5:Ljava/lang/Object;T6:Ljava/lang/Object;T7:Ljava/lang/Object;T8:Ljava/lang/Object;T9:Ljava/lang/Object;T10:Ljava/lang/Object;T11:Ljava/lang/Object;T12:Ljava/lang/Object;R:Ljava/lang/Object;>(Lorg/sireum/Json$Parser;Ljava/lang/String;)Lscala/Function12<TT1;TT2;TT3;TT4;TT5;TT6;TT7;TT8;TT9;TT10;TT11;TT12;TR;>;
    MethodParameters:
      Name                           Flags
      parser                         final
      f                              final

  public <T1 extends java.lang.Object, T2 extends java.lang.Object, T3 extends java.lang.Object, T4 extends java.lang.Object, T5 extends java.lang.Object, T6 extends java.lang.Object, T7 extends java.lang.Object, T8 extends java.lang.Object, T9 extends java.lang.Object, T10 extends java.lang.Object, T11 extends java.lang.Object, T12 extends java.lang.Object, R extends java.lang.Object> java.lang.String print12(scala.Function12<T1, T2, T3, T4, T5, T6, T7, T8, T9, T10, T11, T12, R>);
    descriptor: (Lscala/Function12;)Ljava/lang/String;
    flags: (0x0001) ACC_PUBLIC
    Code:
      stack=2, locals=2, args_size=2
         0: getstatic     #29                 // Field org/sireum/JsonFun_Ext$.MODULE$:Lorg/sireum/JsonFun_Ext$;
         3: aload_1
         4: invokevirtual #248                // Method org/sireum/JsonFun_Ext$.print12:(Lscala/Function12;)Ljava/lang/String;
         7: areturn
      LineNumberTable:
        line 2486: 0
      LocalVariableTable:
        Start  Length  Slot  Name   Signature
            0       8     0  this   Lorg/sireum/Json$Fun$;
            0       8     1     f   Lscala/Function12;
    Signature: #237                         // <T1:Ljava/lang/Object;T2:Ljava/lang/Object;T3:Ljava/lang/Object;T4:Ljava/lang/Object;T5:Ljava/lang/Object;T6:Ljava/lang/Object;T7:Ljava/lang/Object;T8:Ljava/lang/Object;T9:Ljava/lang/Object;T10:Ljava/lang/Object;T11:Ljava/lang/Object;T12:Ljava/lang/Object;R:Ljava/lang/Object;>(Lscala/Function12<TT1;TT2;TT3;TT4;TT5;TT6;TT7;TT8;TT9;TT10;TT11;TT12;TR;>;)Ljava/lang/String;
    MethodParameters:
      Name                           Flags
      f                              final

  public <T1 extends java.lang.Object, T2 extends java.lang.Object, T3 extends java.lang.Object, T4 extends java.lang.Object, T5 extends java.lang.Object, T6 extends java.lang.Object, T7 extends java.lang.Object, T8 extends java.lang.Object, T9 extends java.lang.Object, T10 extends java.lang.Object, T11 extends java.lang.Object, T12 extends java.lang.Object, R extends java.lang.Object> scala.Function12<T1, T2, T3, T4, T5, T6, T7, T8, T9, T10, T11, T12, R> parse12(org.sireum.Json$Parser, java.lang.String);
    descriptor: (Lorg/sireum/Json$Parser;Ljava/lang/String;)Lscala/Function12;
    flags: (0x0001) ACC_PUBLIC
    Code:
      stack=3, locals=3, args_size=3
         0: getstatic     #29                 // Field org/sireum/JsonFun_Ext$.MODULE$:Lorg/sireum/JsonFun_Ext$;
         3: aload_1
         4: aload_2
         5: invokevirtual #251                // Method org/sireum/JsonFun_Ext$.parse12:(Lorg/sireum/Json$Parser;Ljava/lang/String;)Lscala/Function12;
         8: areturn
      LineNumberTable:
        line 2487: 0
      LocalVariableTable:
        Start  Length  Slot  Name   Signature
            0       9     0  this   Lorg/sireum/Json$Fun$;
            0       9     1 parser   Lorg/sireum/Json$Parser;
            0       9     2     f   Ljava/lang/String;
    Signature: #243                         // <T1:Ljava/lang/Object;T2:Ljava/lang/Object;T3:Ljava/lang/Object;T4:Ljava/lang/Object;T5:Ljava/lang/Object;T6:Ljava/lang/Object;T7:Ljava/lang/Object;T8:Ljava/lang/Object;T9:Ljava/lang/Object;T10:Ljava/lang/Object;T11:Ljava/lang/Object;T12:Ljava/lang/Object;R:Ljava/lang/Object;>(Lorg/sireum/Json$Parser;Ljava/lang/String;)Lscala/Function12<TT1;TT2;TT3;TT4;TT5;TT6;TT7;TT8;TT9;TT10;TT11;TT12;TR;>;
    MethodParameters:
      Name                           Flags
      parser                         final
      f                              final

  public <T1 extends java.lang.Object, T2 extends java.lang.Object, T3 extends java.lang.Object, T4 extends java.lang.Object, T5 extends java.lang.Object, T6 extends java.lang.Object, T7 extends java.lang.Object, T8 extends java.lang.Object, T9 extends java.lang.Object, T10 extends java.lang.Object, T11 extends java.lang.Object, T12 extends java.lang.Object, T13 extends java.lang.Object, R extends java.lang.Object> java.lang.String printPure13(scala.Function13<T1, T2, T3, T4, T5, T6, T7, T8, T9, T10, T11, T12, T13, R>);
    descriptor: (Lscala/Function13;)Ljava/lang/String;
    flags: (0x0001) ACC_PUBLIC
    Code:
      stack=2, locals=2, args_size=2
         0: getstatic     #29                 // Field org/sireum/JsonFun_Ext$.MODULE$:Lorg/sireum/JsonFun_Ext$;
         3: aload_1
         4: invokevirtual #256                // Method org/sireum/JsonFun_Ext$.printPure13:(Lscala/Function13;)Ljava/lang/String;
         7: areturn
      LineNumberTable:
        line 2489: 0
      LocalVariableTable:
        Start  Length  Slot  Name   Signature
            0       8     0  this   Lorg/sireum/Json$Fun$;
            0       8     1     f   Lscala/Function13;
    Signature: #254                         // <T1:Ljava/lang/Object;T2:Ljava/lang/Object;T3:Ljava/lang/Object;T4:Ljava/lang/Object;T5:Ljava/lang/Object;T6:Ljava/lang/Object;T7:Ljava/lang/Object;T8:Ljava/lang/Object;T9:Ljava/lang/Object;T10:Ljava/lang/Object;T11:Ljava/lang/Object;T12:Ljava/lang/Object;T13:Ljava/lang/Object;R:Ljava/lang/Object;>(Lscala/Function13<TT1;TT2;TT3;TT4;TT5;TT6;TT7;TT8;TT9;TT10;TT11;TT12;TT13;TR;>;)Ljava/lang/String;
    MethodParameters:
      Name                           Flags
      f                              final

  public <T1 extends java.lang.Object, T2 extends java.lang.Object, T3 extends java.lang.Object, T4 extends java.lang.Object, T5 extends java.lang.Object, T6 extends java.lang.Object, T7 extends java.lang.Object, T8 extends java.lang.Object, T9 extends java.lang.Object, T10 extends java.lang.Object, T11 extends java.lang.Object, T12 extends java.lang.Object, T13 extends java.lang.Object, R extends java.lang.Object> scala.Function13<T1, T2, T3, T4, T5, T6, T7, T8, T9, T10, T11, T12, T13, R> parsePure13(org.sireum.Json$Parser, java.lang.String);
    descriptor: (Lorg/sireum/Json$Parser;Ljava/lang/String;)Lscala/Function13;
    flags: (0x0001) ACC_PUBLIC
    Code:
      stack=3, locals=3, args_size=3
         0: getstatic     #29                 // Field org/sireum/JsonFun_Ext$.MODULE$:Lorg/sireum/JsonFun_Ext$;
         3: aload_1
         4: aload_2
         5: invokevirtual #262                // Method org/sireum/JsonFun_Ext$.parsePure13:(Lorg/sireum/Json$Parser;Ljava/lang/String;)Lscala/Function13;
         8: areturn
      LineNumberTable:
        line 2490: 0
      LocalVariableTable:
        Start  Length  Slot  Name   Signature
            0       9     0  this   Lorg/sireum/Json$Fun$;
            0       9     1 parser   Lorg/sireum/Json$Parser;
            0       9     2     f   Ljava/lang/String;
    Signature: #260                         // <T1:Ljava/lang/Object;T2:Ljava/lang/Object;T3:Ljava/lang/Object;T4:Ljava/lang/Object;T5:Ljava/lang/Object;T6:Ljava/lang/Object;T7:Ljava/lang/Object;T8:Ljava/lang/Object;T9:Ljava/lang/Object;T10:Ljava/lang/Object;T11:Ljava/lang/Object;T12:Ljava/lang/Object;T13:Ljava/lang/Object;R:Ljava/lang/Object;>(Lorg/sireum/Json$Parser;Ljava/lang/String;)Lscala/Function13<TT1;TT2;TT3;TT4;TT5;TT6;TT7;TT8;TT9;TT10;TT11;TT12;TT13;TR;>;
    MethodParameters:
      Name                           Flags
      parser                         final
      f                              final

  public <T1 extends java.lang.Object, T2 extends java.lang.Object, T3 extends java.lang.Object, T4 extends java.lang.Object, T5 extends java.lang.Object, T6 extends java.lang.Object, T7 extends java.lang.Object, T8 extends java.lang.Object, T9 extends java.lang.Object, T10 extends java.lang.Object, T11 extends java.lang.Object, T12 extends java.lang.Object, T13 extends java.lang.Object, R extends java.lang.Object> java.lang.String print13(scala.Function13<T1, T2, T3, T4, T5, T6, T7, T8, T9, T10, T11, T12, T13, R>);
    descriptor: (Lscala/Function13;)Ljava/lang/String;
    flags: (0x0001) ACC_PUBLIC
    Code:
      stack=2, locals=2, args_size=2
         0: getstatic     #29                 // Field org/sireum/JsonFun_Ext$.MODULE$:Lorg/sireum/JsonFun_Ext$;
         3: aload_1
         4: invokevirtual #265                // Method org/sireum/JsonFun_Ext$.print13:(Lscala/Function13;)Ljava/lang/String;
         7: areturn
      LineNumberTable:
        line 2492: 0
      LocalVariableTable:
        Start  Length  Slot  Name   Signature
            0       8     0  this   Lorg/sireum/Json$Fun$;
            0       8     1     f   Lscala/Function13;
    Signature: #254                         // <T1:Ljava/lang/Object;T2:Ljava/lang/Object;T3:Ljava/lang/Object;T4:Ljava/lang/Object;T5:Ljava/lang/Object;T6:Ljava/lang/Object;T7:Ljava/lang/Object;T8:Ljava/lang/Object;T9:Ljava/lang/Object;T10:Ljava/lang/Object;T11:Ljava/lang/Object;T12:Ljava/lang/Object;T13:Ljava/lang/Object;R:Ljava/lang/Object;>(Lscala/Function13<TT1;TT2;TT3;TT4;TT5;TT6;TT7;TT8;TT9;TT10;TT11;TT12;TT13;TR;>;)Ljava/lang/String;
    MethodParameters:
      Name                           Flags
      f                              final

  public <T1 extends java.lang.Object, T2 extends java.lang.Object, T3 extends java.lang.Object, T4 extends java.lang.Object, T5 extends java.lang.Object, T6 extends java.lang.Object, T7 extends java.lang.Object, T8 extends java.lang.Object, T9 extends java.lang.Object, T10 extends java.lang.Object, T11 extends java.lang.Object, T12 extends java.lang.Object, T13 extends java.lang.Object, R extends java.lang.Object> scala.Function13<T1, T2, T3, T4, T5, T6, T7, T8, T9, T10, T11, T12, T13, R> parse13(org.sireum.Json$Parser, java.lang.String);
    descriptor: (Lorg/sireum/Json$Parser;Ljava/lang/String;)Lscala/Function13;
    flags: (0x0001) ACC_PUBLIC
    Code:
      stack=3, locals=3, args_size=3
         0: getstatic     #29                 // Field org/sireum/JsonFun_Ext$.MODULE$:Lorg/sireum/JsonFun_Ext$;
         3: aload_1
         4: aload_2
         5: invokevirtual #268                // Method org/sireum/JsonFun_Ext$.parse13:(Lorg/sireum/Json$Parser;Ljava/lang/String;)Lscala/Function13;
         8: areturn
      LineNumberTable:
        line 2493: 0
      LocalVariableTable:
        Start  Length  Slot  Name   Signature
            0       9     0  this   Lorg/sireum/Json$Fun$;
            0       9     1 parser   Lorg/sireum/Json$Parser;
            0       9     2     f   Ljava/lang/String;
    Signature: #260                         // <T1:Ljava/lang/Object;T2:Ljava/lang/Object;T3:Ljava/lang/Object;T4:Ljava/lang/Object;T5:Ljava/lang/Object;T6:Ljava/lang/Object;T7:Ljava/lang/Object;T8:Ljava/lang/Object;T9:Ljava/lang/Object;T10:Ljava/lang/Object;T11:Ljava/lang/Object;T12:Ljava/lang/Object;T13:Ljava/lang/Object;R:Ljava/lang/Object;>(Lorg/sireum/Json$Parser;Ljava/lang/String;)Lscala/Function13<TT1;TT2;TT3;TT4;TT5;TT6;TT7;TT8;TT9;TT10;TT11;TT12;TT13;TR;>;
    MethodParameters:
      Name                           Flags
      parser                         final
      f                              final

  public <T1 extends java.lang.Object, T2 extends java.lang.Object, T3 extends java.lang.Object, T4 extends java.lang.Object, T5 extends java.lang.Object, T6 extends java.lang.Object, T7 extends java.lang.Object, T8 extends java.lang.Object, T9 extends java.lang.Object, T10 extends java.lang.Object, T11 extends java.lang.Object, T12 extends java.lang.Object, T13 extends java.lang.Object, T14 extends java.lang.Object, R extends java.lang.Object> java.lang.String printPure14(scala.Function14<T1, T2, T3, T4, T5, T6, T7, T8, T9, T10, T11, T12, T13, T14, R>);
    descriptor: (Lscala/Function14;)Ljava/lang/String;
    flags: (0x0001) ACC_PUBLIC
    Code:
      stack=2, locals=2, args_size=2
         0: getstatic     #29                 // Field org/sireum/JsonFun_Ext$.MODULE$:Lorg/sireum/JsonFun_Ext$;
         3: aload_1
         4: invokevirtual #273                // Method org/sireum/JsonFun_Ext$.printPure14:(Lscala/Function14;)Ljava/lang/String;
         7: areturn
      LineNumberTable:
        line 2495: 0
      LocalVariableTable:
        Start  Length  Slot  Name   Signature
            0       8     0  this   Lorg/sireum/Json$Fun$;
            0       8     1     f   Lscala/Function14;
    Signature: #271                         // <T1:Ljava/lang/Object;T2:Ljava/lang/Object;T3:Ljava/lang/Object;T4:Ljava/lang/Object;T5:Ljava/lang/Object;T6:Ljava/lang/Object;T7:Ljava/lang/Object;T8:Ljava/lang/Object;T9:Ljava/lang/Object;T10:Ljava/lang/Object;T11:Ljava/lang/Object;T12:Ljava/lang/Object;T13:Ljava/lang/Object;T14:Ljava/lang/Object;R:Ljava/lang/Object;>(Lscala/Function14<TT1;TT2;TT3;TT4;TT5;TT6;TT7;TT8;TT9;TT10;TT11;TT12;TT13;TT14;TR;>;)Ljava/lang/String;
    MethodParameters:
      Name                           Flags
      f                              final

  public <T1 extends java.lang.Object, T2 extends java.lang.Object, T3 extends java.lang.Object, T4 extends java.lang.Object, T5 extends java.lang.Object, T6 extends java.lang.Object, T7 extends java.lang.Object, T8 extends java.lang.Object, T9 extends java.lang.Object, T10 extends java.lang.Object, T11 extends java.lang.Object, T12 extends java.lang.Object, T13 extends java.lang.Object, T14 extends java.lang.Object, R extends java.lang.Object> scala.Function14<T1, T2, T3, T4, T5, T6, T7, T8, T9, T10, T11, T12, T13, T14, R> parsePure14(org.sireum.Json$Parser, java.lang.String);
    descriptor: (Lorg/sireum/Json$Parser;Ljava/lang/String;)Lscala/Function14;
    flags: (0x0001) ACC_PUBLIC
    Code:
      stack=3, locals=3, args_size=3
         0: getstatic     #29                 // Field org/sireum/JsonFun_Ext$.MODULE$:Lorg/sireum/JsonFun_Ext$;
         3: aload_1
         4: aload_2
         5: invokevirtual #279                // Method org/sireum/JsonFun_Ext$.parsePure14:(Lorg/sireum/Json$Parser;Ljava/lang/String;)Lscala/Function14;
         8: areturn
      LineNumberTable:
        line 2496: 0
      LocalVariableTable:
        Start  Length  Slot  Name   Signature
            0       9     0  this   Lorg/sireum/Json$Fun$;
            0       9     1 parser   Lorg/sireum/Json$Parser;
            0       9     2     f   Ljava/lang/String;
    Signature: #277                         // <T1:Ljava/lang/Object;T2:Ljava/lang/Object;T3:Ljava/lang/Object;T4:Ljava/lang/Object;T5:Ljava/lang/Object;T6:Ljava/lang/Object;T7:Ljava/lang/Object;T8:Ljava/lang/Object;T9:Ljava/lang/Object;T10:Ljava/lang/Object;T11:Ljava/lang/Object;T12:Ljava/lang/Object;T13:Ljava/lang/Object;T14:Ljava/lang/Object;R:Ljava/lang/Object;>(Lorg/sireum/Json$Parser;Ljava/lang/String;)Lscala/Function14<TT1;TT2;TT3;TT4;TT5;TT6;TT7;TT8;TT9;TT10;TT11;TT12;TT13;TT14;TR;>;
    MethodParameters:
      Name                           Flags
      parser                         final
      f                              final

  public <T1 extends java.lang.Object, T2 extends java.lang.Object, T3 extends java.lang.Object, T4 extends java.lang.Object, T5 extends java.lang.Object, T6 extends java.lang.Object, T7 extends java.lang.Object, T8 extends java.lang.Object, T9 extends java.lang.Object, T10 extends java.lang.Object, T11 extends java.lang.Object, T12 extends java.lang.Object, T13 extends java.lang.Object, T14 extends java.lang.Object, R extends java.lang.Object> java.lang.String print14(scala.Function14<T1, T2, T3, T4, T5, T6, T7, T8, T9, T10, T11, T12, T13, T14, R>);
    descriptor: (Lscala/Function14;)Ljava/lang/String;
    flags: (0x0001) ACC_PUBLIC
    Code:
      stack=2, locals=2, args_size=2
         0: getstatic     #29                 // Field org/sireum/JsonFun_Ext$.MODULE$:Lorg/sireum/JsonFun_Ext$;
         3: aload_1
         4: invokevirtual #282                // Method org/sireum/JsonFun_Ext$.print14:(Lscala/Function14;)Ljava/lang/String;
         7: areturn
      LineNumberTable:
        line 2498: 0
      LocalVariableTable:
        Start  Length  Slot  Name   Signature
            0       8     0  this   Lorg/sireum/Json$Fun$;
            0       8     1     f   Lscala/Function14;
    Signature: #271                         // <T1:Ljava/lang/Object;T2:Ljava/lang/Object;T3:Ljava/lang/Object;T4:Ljava/lang/Object;T5:Ljava/lang/Object;T6:Ljava/lang/Object;T7:Ljava/lang/Object;T8:Ljava/lang/Object;T9:Ljava/lang/Object;T10:Ljava/lang/Object;T11:Ljava/lang/Object;T12:Ljava/lang/Object;T13:Ljava/lang/Object;T14:Ljava/lang/Object;R:Ljava/lang/Object;>(Lscala/Function14<TT1;TT2;TT3;TT4;TT5;TT6;TT7;TT8;TT9;TT10;TT11;TT12;TT13;TT14;TR;>;)Ljava/lang/String;
    MethodParameters:
      Name                           Flags
      f                              final

  public <T1 extends java.lang.Object, T2 extends java.lang.Object, T3 extends java.lang.Object, T4 extends java.lang.Object, T5 extends java.lang.Object, T6 extends java.lang.Object, T7 extends java.lang.Object, T8 extends java.lang.Object, T9 extends java.lang.Object, T10 extends java.lang.Object, T11 extends java.lang.Object, T12 extends java.lang.Object, T13 extends java.lang.Object, T14 extends java.lang.Object, R extends java.lang.Object> scala.Function14<T1, T2, T3, T4, T5, T6, T7, T8, T9, T10, T11, T12, T13, T14, R> parse14(org.sireum.Json$Parser, java.lang.String);
    descriptor: (Lorg/sireum/Json$Parser;Ljava/lang/String;)Lscala/Function14;
    flags: (0x0001) ACC_PUBLIC
    Code:
      stack=3, locals=3, args_size=3
         0: getstatic     #29                 // Field org/sireum/JsonFun_Ext$.MODULE$:Lorg/sireum/JsonFun_Ext$;
         3: aload_1
         4: aload_2
         5: invokevirtual #285                // Method org/sireum/JsonFun_Ext$.parse14:(Lorg/sireum/Json$Parser;Ljava/lang/String;)Lscala/Function14;
         8: areturn
      LineNumberTable:
        line 2499: 0
      LocalVariableTable:
        Start  Length  Slot  Name   Signature
            0       9     0  this   Lorg/sireum/Json$Fun$;
            0       9     1 parser   Lorg/sireum/Json$Parser;
            0       9     2     f   Ljava/lang/String;
    Signature: #277                         // <T1:Ljava/lang/Object;T2:Ljava/lang/Object;T3:Ljava/lang/Object;T4:Ljava/lang/Object;T5:Ljava/lang/Object;T6:Ljava/lang/Object;T7:Ljava/lang/Object;T8:Ljava/lang/Object;T9:Ljava/lang/Object;T10:Ljava/lang/Object;T11:Ljava/lang/Object;T12:Ljava/lang/Object;T13:Ljava/lang/Object;T14:Ljava/lang/Object;R:Ljava/lang/Object;>(Lorg/sireum/Json$Parser;Ljava/lang/String;)Lscala/Function14<TT1;TT2;TT3;TT4;TT5;TT6;TT7;TT8;TT9;TT10;TT11;TT12;TT13;TT14;TR;>;
    MethodParameters:
      Name                           Flags
      parser                         final
      f                              final

  public <T1 extends java.lang.Object, T2 extends java.lang.Object, T3 extends java.lang.Object, T4 extends java.lang.Object, T5 extends java.lang.Object, T6 extends java.lang.Object, T7 extends java.lang.Object, T8 extends java.lang.Object, T9 extends java.lang.Object, T10 extends java.lang.Object, T11 extends java.lang.Object, T12 extends java.lang.Object, T13 extends java.lang.Object, T14 extends java.lang.Object, T15 extends java.lang.Object, R extends java.lang.Object> java.lang.String printPure15(scala.Function15<T1, T2, T3, T4, T5, T6, T7, T8, T9, T10, T11, T12, T13, T14, T15, R>);
    descriptor: (Lscala/Function15;)Ljava/lang/String;
    flags: (0x0001) ACC_PUBLIC
    Code:
      stack=2, locals=2, args_size=2
         0: getstatic     #29                 // Field org/sireum/JsonFun_Ext$.MODULE$:Lorg/sireum/JsonFun_Ext$;
         3: aload_1
         4: invokevirtual #290                // Method org/sireum/JsonFun_Ext$.printPure15:(Lscala/Function15;)Ljava/lang/String;
         7: areturn
      LineNumberTable:
        line 2501: 0
      LocalVariableTable:
        Start  Length  Slot  Name   Signature
            0       8     0  this   Lorg/sireum/Json$Fun$;
            0       8     1     f   Lscala/Function15;
    Signature: #288                         // <T1:Ljava/lang/Object;T2:Ljava/lang/Object;T3:Ljava/lang/Object;T4:Ljava/lang/Object;T5:Ljava/lang/Object;T6:Ljava/lang/Object;T7:Ljava/lang/Object;T8:Ljava/lang/Object;T9:Ljava/lang/Object;T10:Ljava/lang/Object;T11:Ljava/lang/Object;T12:Ljava/lang/Object;T13:Ljava/lang/Object;T14:Ljava/lang/Object;T15:Ljava/lang/Object;R:Ljava/lang/Object;>(Lscala/Function15<TT1;TT2;TT3;TT4;TT5;TT6;TT7;TT8;TT9;TT10;TT11;TT12;TT13;TT14;TT15;TR;>;)Ljava/lang/String;
    MethodParameters:
      Name                           Flags
      f                              final

  public <T1 extends java.lang.Object, T2 extends java.lang.Object, T3 extends java.lang.Object, T4 extends java.lang.Object, T5 extends java.lang.Object, T6 extends java.lang.Object, T7 extends java.lang.Object, T8 extends java.lang.Object, T9 extends java.lang.Object, T10 extends java.lang.Object, T11 extends java.lang.Object, T12 extends java.lang.Object, T13 extends java.lang.Object, T14 extends java.lang.Object, T15 extends java.lang.Object, R extends java.lang.Object> scala.Function15<T1, T2, T3, T4, T5, T6, T7, T8, T9, T10, T11, T12, T13, T14, T15, R> parsePure15(org.sireum.Json$Parser, java.lang.String);
    descriptor: (Lorg/sireum/Json$Parser;Ljava/lang/String;)Lscala/Function15;
    flags: (0x0001) ACC_PUBLIC
    Code:
      stack=3, locals=3, args_size=3
         0: getstatic     #29                 // Field org/sireum/JsonFun_Ext$.MODULE$:Lorg/sireum/JsonFun_Ext$;
         3: aload_1
         4: aload_2
         5: invokevirtual #296                // Method org/sireum/JsonFun_Ext$.parsePure15:(Lorg/sireum/Json$Parser;Ljava/lang/String;)Lscala/Function15;
         8: areturn
      LineNumberTable:
        line 2502: 0
      LocalVariableTable:
        Start  Length  Slot  Name   Signature
            0       9     0  this   Lorg/sireum/Json$Fun$;
            0       9     1 parser   Lorg/sireum/Json$Parser;
            0       9     2     f   Ljava/lang/String;
    Signature: #294                         // <T1:Ljava/lang/Object;T2:Ljava/lang/Object;T3:Ljava/lang/Object;T4:Ljava/lang/Object;T5:Ljava/lang/Object;T6:Ljava/lang/Object;T7:Ljava/lang/Object;T8:Ljava/lang/Object;T9:Ljava/lang/Object;T10:Ljava/lang/Object;T11:Ljava/lang/Object;T12:Ljava/lang/Object;T13:Ljava/lang/Object;T14:Ljava/lang/Object;T15:Ljava/lang/Object;R:Ljava/lang/Object;>(Lorg/sireum/Json$Parser;Ljava/lang/String;)Lscala/Function15<TT1;TT2;TT3;TT4;TT5;TT6;TT7;TT8;TT9;TT10;TT11;TT12;TT13;TT14;TT15;TR;>;
    MethodParameters:
      Name                           Flags
      parser                         final
      f                              final

  public <T1 extends java.lang.Object, T2 extends java.lang.Object, T3 extends java.lang.Object, T4 extends java.lang.Object, T5 extends java.lang.Object, T6 extends java.lang.Object, T7 extends java.lang.Object, T8 extends java.lang.Object, T9 extends java.lang.Object, T10 extends java.lang.Object, T11 extends java.lang.Object, T12 extends java.lang.Object, T13 extends java.lang.Object, T14 extends java.lang.Object, T15 extends java.lang.Object, R extends java.lang.Object> java.lang.String print15(scala.Function15<T1, T2, T3, T4, T5, T6, T7, T8, T9, T10, T11, T12, T13, T14, T15, R>);
    descriptor: (Lscala/Function15;)Ljava/lang/String;
    flags: (0x0001) ACC_PUBLIC
    Code:
      stack=2, locals=2, args_size=2
         0: getstatic     #29                 // Field org/sireum/JsonFun_Ext$.MODULE$:Lorg/sireum/JsonFun_Ext$;
         3: aload_1
         4: invokevirtual #299                // Method org/sireum/JsonFun_Ext$.print15:(Lscala/Function15;)Ljava/lang/String;
         7: areturn
      LineNumberTable:
        line 2504: 0
      LocalVariableTable:
        Start  Length  Slot  Name   Signature
            0       8     0  this   Lorg/sireum/Json$Fun$;
            0       8     1     f   Lscala/Function15;
    Signature: #288                         // <T1:Ljava/lang/Object;T2:Ljava/lang/Object;T3:Ljava/lang/Object;T4:Ljava/lang/Object;T5:Ljava/lang/Object;T6:Ljava/lang/Object;T7:Ljava/lang/Object;T8:Ljava/lang/Object;T9:Ljava/lang/Object;T10:Ljava/lang/Object;T11:Ljava/lang/Object;T12:Ljava/lang/Object;T13:Ljava/lang/Object;T14:Ljava/lang/Object;T15:Ljava/lang/Object;R:Ljava/lang/Object;>(Lscala/Function15<TT1;TT2;TT3;TT4;TT5;TT6;TT7;TT8;TT9;TT10;TT11;TT12;TT13;TT14;TT15;TR;>;)Ljava/lang/String;
    MethodParameters:
      Name                           Flags
      f                              final

  public <T1 extends java.lang.Object, T2 extends java.lang.Object, T3 extends java.lang.Object, T4 extends java.lang.Object, T5 extends java.lang.Object, T6 extends java.lang.Object, T7 extends java.lang.Object, T8 extends java.lang.Object, T9 extends java.lang.Object, T10 extends java.lang.Object, T11 extends java.lang.Object, T12 extends java.lang.Object, T13 extends java.lang.Object, T14 extends java.lang.Object, T15 extends java.lang.Object, R extends java.lang.Object> scala.Function15<T1, T2, T3, T4, T5, T6, T7, T8, T9, T10, T11, T12, T13, T14, T15, R> parse15(org.sireum.Json$Parser, java.lang.String);
    descriptor: (Lorg/sireum/Json$Parser;Ljava/lang/String;)Lscala/Function15;
    flags: (0x0001) ACC_PUBLIC
    Code:
      stack=3, locals=3, args_size=3
         0: getstatic     #29                 // Field org/sireum/JsonFun_Ext$.MODULE$:Lorg/sireum/JsonFun_Ext$;
         3: aload_1
         4: aload_2
         5: invokevirtual #302                // Method org/sireum/JsonFun_Ext$.parse15:(Lorg/sireum/Json$Parser;Ljava/lang/String;)Lscala/Function15;
         8: areturn
      LineNumberTable:
        line 2505: 0
      LocalVariableTable:
        Start  Length  Slot  Name   Signature
            0       9     0  this   Lorg/sireum/Json$Fun$;
            0       9     1 parser   Lorg/sireum/Json$Parser;
            0       9     2     f   Ljava/lang/String;
    Signature: #294                         // <T1:Ljava/lang/Object;T2:Ljava/lang/Object;T3:Ljava/lang/Object;T4:Ljava/lang/Object;T5:Ljava/lang/Object;T6:Ljava/lang/Object;T7:Ljava/lang/Object;T8:Ljava/lang/Object;T9:Ljava/lang/Object;T10:Ljava/lang/Object;T11:Ljava/lang/Object;T12:Ljava/lang/Object;T13:Ljava/lang/Object;T14:Ljava/lang/Object;T15:Ljava/lang/Object;R:Ljava/lang/Object;>(Lorg/sireum/Json$Parser;Ljava/lang/String;)Lscala/Function15<TT1;TT2;TT3;TT4;TT5;TT6;TT7;TT8;TT9;TT10;TT11;TT12;TT13;TT14;TT15;TR;>;
    MethodParameters:
      Name                           Flags
      parser                         final
      f                              final

  public <T1 extends java.lang.Object, T2 extends java.lang.Object, T3 extends java.lang.Object, T4 extends java.lang.Object, T5 extends java.lang.Object, T6 extends java.lang.Object, T7 extends java.lang.Object, T8 extends java.lang.Object, T9 extends java.lang.Object, T10 extends java.lang.Object, T11 extends java.lang.Object, T12 extends java.lang.Object, T13 extends java.lang.Object, T14 extends java.lang.Object, T15 extends java.lang.Object, T16 extends java.lang.Object, R extends java.lang.Object> java.lang.String printPure16(scala.Function16<T1, T2, T3, T4, T5, T6, T7, T8, T9, T10, T11, T12, T13, T14, T15, T16, R>);
    descriptor: (Lscala/Function16;)Ljava/lang/String;
    flags: (0x0001) ACC_PUBLIC
    Code:
      stack=2, locals=2, args_size=2
         0: getstatic     #29                 // Field org/sireum/JsonFun_Ext$.MODULE$:Lorg/sireum/JsonFun_Ext$;
         3: aload_1
         4: invokevirtual #307                // Method org/sireum/JsonFun_Ext$.printPure16:(Lscala/Function16;)Ljava/lang/String;
         7: areturn
      LineNumberTable:
        line 2507: 0
      LocalVariableTable:
        Start  Length  Slot  Name   Signature
            0       8     0  this   Lorg/sireum/Json$Fun$;
            0       8     1     f   Lscala/Function16;
    Signature: #305                         // <T1:Ljava/lang/Object;T2:Ljava/lang/Object;T3:Ljava/lang/Object;T4:Ljava/lang/Object;T5:Ljava/lang/Object;T6:Ljava/lang/Object;T7:Ljava/lang/Object;T8:Ljava/lang/Object;T9:Ljava/lang/Object;T10:Ljava/lang/Object;T11:Ljava/lang/Object;T12:Ljava/lang/Object;T13:Ljava/lang/Object;T14:Ljava/lang/Object;T15:Ljava/lang/Object;T16:Ljava/lang/Object;R:Ljava/lang/Object;>(Lscala/Function16<TT1;TT2;TT3;TT4;TT5;TT6;TT7;TT8;TT9;TT10;TT11;TT12;TT13;TT14;TT15;TT16;TR;>;)Ljava/lang/String;
    MethodParameters:
      Name                           Flags
      f                              final

  public <T1 extends java.lang.Object, T2 extends java.lang.Object, T3 extends java.lang.Object, T4 extends java.lang.Object, T5 extends java.lang.Object, T6 extends java.lang.Object, T7 extends java.lang.Object, T8 extends java.lang.Object, T9 extends java.lang.Object, T10 extends java.lang.Object, T11 extends java.lang.Object, T12 extends java.lang.Object, T13 extends java.lang.Object, T14 extends java.lang.Object, T15 extends java.lang.Object, T16 extends java.lang.Object, R extends java.lang.Object> scala.Function16<T1, T2, T3, T4, T5, T6, T7, T8, T9, T10, T11, T12, T13, T14, T15, T16, R> parsePure16(org.sireum.Json$Parser, java.lang.String);
    descriptor: (Lorg/sireum/Json$Parser;Ljava/lang/String;)Lscala/Function16;
    flags: (0x0001) ACC_PUBLIC
    Code:
      stack=3, locals=3, args_size=3
         0: getstatic     #29                 // Field org/sireum/JsonFun_Ext$.MODULE$:Lorg/sireum/JsonFun_Ext$;
         3: aload_1
         4: aload_2
         5: invokevirtual #313                // Method org/sireum/JsonFun_Ext$.parsePure16:(Lorg/sireum/Json$Parser;Ljava/lang/String;)Lscala/Function16;
         8: areturn
      LineNumberTable:
        line 2508: 0
      LocalVariableTable:
        Start  Length  Slot  Name   Signature
            0       9     0  this   Lorg/sireum/Json$Fun$;
            0       9     1 parser   Lorg/sireum/Json$Parser;
            0       9     2     f   Ljava/lang/String;
    Signature: #311                         // <T1:Ljava/lang/Object;T2:Ljava/lang/Object;T3:Ljava/lang/Object;T4:Ljava/lang/Object;T5:Ljava/lang/Object;T6:Ljava/lang/Object;T7:Ljava/lang/Object;T8:Ljava/lang/Object;T9:Ljava/lang/Object;T10:Ljava/lang/Object;T11:Ljava/lang/Object;T12:Ljava/lang/Object;T13:Ljava/lang/Object;T14:Ljava/lang/Object;T15:Ljava/lang/Object;T16:Ljava/lang/Object;R:Ljava/lang/Object;>(Lorg/sireum/Json$Parser;Ljava/lang/String;)Lscala/Function16<TT1;TT2;TT3;TT4;TT5;TT6;TT7;TT8;TT9;TT10;TT11;TT12;TT13;TT14;TT15;TT16;TR;>;
    MethodParameters:
      Name                           Flags
      parser                         final
      f                              final

  public <T1 extends java.lang.Object, T2 extends java.lang.Object, T3 extends java.lang.Object, T4 extends java.lang.Object, T5 extends java.lang.Object, T6 extends java.lang.Object, T7 extends java.lang.Object, T8 extends java.lang.Object, T9 extends java.lang.Object, T10 extends java.lang.Object, T11 extends java.lang.Object, T12 extends java.lang.Object, T13 extends java.lang.Object, T14 extends java.lang.Object, T15 extends java.lang.Object, T16 extends java.lang.Object, R extends java.lang.Object> java.lang.String print16(scala.Function16<T1, T2, T3, T4, T5, T6, T7, T8, T9, T10, T11, T12, T13, T14, T15, T16, R>);
    descriptor: (Lscala/Function16;)Ljava/lang/String;
    flags: (0x0001) ACC_PUBLIC
    Code:
      stack=2, locals=2, args_size=2
         0: getstatic     #29                 // Field org/sireum/JsonFun_Ext$.MODULE$:Lorg/sireum/JsonFun_Ext$;
         3: aload_1
         4: invokevirtual #316                // Method org/sireum/JsonFun_Ext$.print16:(Lscala/Function16;)Ljava/lang/String;
         7: areturn
      LineNumberTable:
        line 2510: 0
      LocalVariableTable:
        Start  Length  Slot  Name   Signature
            0       8     0  this   Lorg/sireum/Json$Fun$;
            0       8     1     f   Lscala/Function16;
    Signature: #305                         // <T1:Ljava/lang/Object;T2:Ljava/lang/Object;T3:Ljava/lang/Object;T4:Ljava/lang/Object;T5:Ljava/lang/Object;T6:Ljava/lang/Object;T7:Ljava/lang/Object;T8:Ljava/lang/Object;T9:Ljava/lang/Object;T10:Ljava/lang/Object;T11:Ljava/lang/Object;T12:Ljava/lang/Object;T13:Ljava/lang/Object;T14:Ljava/lang/Object;T15:Ljava/lang/Object;T16:Ljava/lang/Object;R:Ljava/lang/Object;>(Lscala/Function16<TT1;TT2;TT3;TT4;TT5;TT6;TT7;TT8;TT9;TT10;TT11;TT12;TT13;TT14;TT15;TT16;TR;>;)Ljava/lang/String;
    MethodParameters:
      Name                           Flags
      f                              final

  public <T1 extends java.lang.Object, T2 extends java.lang.Object, T3 extends java.lang.Object, T4 extends java.lang.Object, T5 extends java.lang.Object, T6 extends java.lang.Object, T7 extends java.lang.Object, T8 extends java.lang.Object, T9 extends java.lang.Object, T10 extends java.lang.Object, T11 extends java.lang.Object, T12 extends java.lang.Object, T13 extends java.lang.Object, T14 extends java.lang.Object, T15 extends java.lang.Object, T16 extends java.lang.Object, R extends java.lang.Object> scala.Function16<T1, T2, T3, T4, T5, T6, T7, T8, T9, T10, T11, T12, T13, T14, T15, T16, R> parse16(org.sireum.Json$Parser, java.lang.String);
    descriptor: (Lorg/sireum/Json$Parser;Ljava/lang/String;)Lscala/Function16;
    flags: (0x0001) ACC_PUBLIC
    Code:
      stack=3, locals=3, args_size=3
         0: getstatic     #29                 // Field org/sireum/JsonFun_Ext$.MODULE$:Lorg/sireum/JsonFun_Ext$;
         3: aload_1
         4: aload_2
         5: invokevirtual #319                // Method org/sireum/JsonFun_Ext$.parse16:(Lorg/sireum/Json$Parser;Ljava/lang/String;)Lscala/Function16;
         8: areturn
      LineNumberTable:
        line 2511: 0
      LocalVariableTable:
        Start  Length  Slot  Name   Signature
            0       9     0  this   Lorg/sireum/Json$Fun$;
            0       9     1 parser   Lorg/sireum/Json$Parser;
            0       9     2     f   Ljava/lang/String;
    Signature: #311                         // <T1:Ljava/lang/Object;T2:Ljava/lang/Object;T3:Ljava/lang/Object;T4:Ljava/lang/Object;T5:Ljava/lang/Object;T6:Ljava/lang/Object;T7:Ljava/lang/Object;T8:Ljava/lang/Object;T9:Ljava/lang/Object;T10:Ljava/lang/Object;T11:Ljava/lang/Object;T12:Ljava/lang/Object;T13:Ljava/lang/Object;T14:Ljava/lang/Object;T15:Ljava/lang/Object;T16:Ljava/lang/Object;R:Ljava/lang/Object;>(Lorg/sireum/Json$Parser;Ljava/lang/String;)Lscala/Function16<TT1;TT2;TT3;TT4;TT5;TT6;TT7;TT8;TT9;TT10;TT11;TT12;TT13;TT14;TT15;TT16;TR;>;
    MethodParameters:
      Name                           Flags
      parser                         final
      f                              final

  public <T1 extends java.lang.Object, T2 extends java.lang.Object, T3 extends java.lang.Object, T4 extends java.lang.Object, T5 extends java.lang.Object, T6 extends java.lang.Object, T7 extends java.lang.Object, T8 extends java.lang.Object, T9 extends java.lang.Object, T10 extends java.lang.Object, T11 extends java.lang.Object, T12 extends java.lang.Object, T13 extends java.lang.Object, T14 extends java.lang.Object, T15 extends java.lang.Object, T16 extends java.lang.Object, T17 extends java.lang.Object, R extends java.lang.Object> java.lang.String printPure17(scala.Function17<T1, T2, T3, T4, T5, T6, T7, T8, T9, T10, T11, T12, T13, T14, T15, T16, T17, R>);
    descriptor: (Lscala/Function17;)Ljava/lang/String;
    flags: (0x0001) ACC_PUBLIC
    Code:
      stack=2, locals=2, args_size=2
         0: getstatic     #29                 // Field org/sireum/JsonFun_Ext$.MODULE$:Lorg/sireum/JsonFun_Ext$;
         3: aload_1
         4: invokevirtual #324                // Method org/sireum/JsonFun_Ext$.printPure17:(Lscala/Function17;)Ljava/lang/String;
         7: areturn
      LineNumberTable:
        line 2513: 0
      LocalVariableTable:
        Start  Length  Slot  Name   Signature
            0       8     0  this   Lorg/sireum/Json$Fun$;
            0       8     1     f   Lscala/Function17;
    Signature: #322                         // <T1:Ljava/lang/Object;T2:Ljava/lang/Object;T3:Ljava/lang/Object;T4:Ljava/lang/Object;T5:Ljava/lang/Object;T6:Ljava/lang/Object;T7:Ljava/lang/Object;T8:Ljava/lang/Object;T9:Ljava/lang/Object;T10:Ljava/lang/Object;T11:Ljava/lang/Object;T12:Ljava/lang/Object;T13:Ljava/lang/Object;T14:Ljava/lang/Object;T15:Ljava/lang/Object;T16:Ljava/lang/Object;T17:Ljava/lang/Object;R:Ljava/lang/Object;>(Lscala/Function17<TT1;TT2;TT3;TT4;TT5;TT6;TT7;TT8;TT9;TT10;TT11;TT12;TT13;TT14;TT15;TT16;TT17;TR;>;)Ljava/lang/String;
    MethodParameters:
      Name                           Flags
      f                              final

  public <T1 extends java.lang.Object, T2 extends java.lang.Object, T3 extends java.lang.Object, T4 extends java.lang.Object, T5 extends java.lang.Object, T6 extends java.lang.Object, T7 extends java.lang.Object, T8 extends java.lang.Object, T9 extends java.lang.Object, T10 extends java.lang.Object, T11 extends java.lang.Object, T12 extends java.lang.Object, T13 extends java.lang.Object, T14 extends java.lang.Object, T15 extends java.lang.Object, T16 extends java.lang.Object, T17 extends java.lang.Object, R extends java.lang.Object> scala.Function17<T1, T2, T3, T4, T5, T6, T7, T8, T9, T10, T11, T12, T13, T14, T15, T16, T17, R> parsePure17(org.sireum.Json$Parser, java.lang.String);
    descriptor: (Lorg/sireum/Json$Parser;Ljava/lang/String;)Lscala/Function17;
    flags: (0x0001) ACC_PUBLIC
    Code:
      stack=3, locals=3, args_size=3
         0: getstatic     #29                 // Field org/sireum/JsonFun_Ext$.MODULE$:Lorg/sireum/JsonFun_Ext$;
         3: aload_1
         4: aload_2
         5: invokevirtual #330                // Method org/sireum/JsonFun_Ext$.parsePure17:(Lorg/sireum/Json$Parser;Ljava/lang/String;)Lscala/Function17;
         8: areturn
      LineNumberTable:
        line 2514: 0
      LocalVariableTable:
        Start  Length  Slot  Name   Signature
            0       9     0  this   Lorg/sireum/Json$Fun$;
            0       9     1 parser   Lorg/sireum/Json$Parser;
            0       9     2     f   Ljava/lang/String;
    Signature: #328                         // <T1:Ljava/lang/Object;T2:Ljava/lang/Object;T3:Ljava/lang/Object;T4:Ljava/lang/Object;T5:Ljava/lang/Object;T6:Ljava/lang/Object;T7:Ljava/lang/Object;T8:Ljava/lang/Object;T9:Ljava/lang/Object;T10:Ljava/lang/Object;T11:Ljava/lang/Object;T12:Ljava/lang/Object;T13:Ljava/lang/Object;T14:Ljava/lang/Object;T15:Ljava/lang/Object;T16:Ljava/lang/Object;T17:Ljava/lang/Object;R:Ljava/lang/Object;>(Lorg/sireum/Json$Parser;Ljava/lang/String;)Lscala/Function17<TT1;TT2;TT3;TT4;TT5;TT6;TT7;TT8;TT9;TT10;TT11;TT12;TT13;TT14;TT15;TT16;TT17;TR;>;
    MethodParameters:
      Name                           Flags
      parser                         final
      f                              final

  public <T1 extends java.lang.Object, T2 extends java.lang.Object, T3 extends java.lang.Object, T4 extends java.lang.Object, T5 extends java.lang.Object, T6 extends java.lang.Object, T7 extends java.lang.Object, T8 extends java.lang.Object, T9 extends java.lang.Object, T10 extends java.lang.Object, T11 extends java.lang.Object, T12 extends java.lang.Object, T13 extends java.lang.Object, T14 extends java.lang.Object, T15 extends java.lang.Object, T16 extends java.lang.Object, T17 extends java.lang.Object, R extends java.lang.Object> java.lang.String print17(scala.Function17<T1, T2, T3, T4, T5, T6, T7, T8, T9, T10, T11, T12, T13, T14, T15, T16, T17, R>);
    descriptor: (Lscala/Function17;)Ljava/lang/String;
    flags: (0x0001) ACC_PUBLIC
    Code:
      stack=2, locals=2, args_size=2
         0: getstatic     #29                 // Field org/sireum/JsonFun_Ext$.MODULE$:Lorg/sireum/JsonFun_Ext$;
         3: aload_1
         4: invokevirtual #333                // Method org/sireum/JsonFun_Ext$.print17:(Lscala/Function17;)Ljava/lang/String;
         7: areturn
      LineNumberTable:
        line 2516: 0
      LocalVariableTable:
        Start  Length  Slot  Name   Signature
            0       8     0  this   Lorg/sireum/Json$Fun$;
            0       8     1     f   Lscala/Function17;
    Signature: #322                         // <T1:Ljava/lang/Object;T2:Ljava/lang/Object;T3:Ljava/lang/Object;T4:Ljava/lang/Object;T5:Ljava/lang/Object;T6:Ljava/lang/Object;T7:Ljava/lang/Object;T8:Ljava/lang/Object;T9:Ljava/lang/Object;T10:Ljava/lang/Object;T11:Ljava/lang/Object;T12:Ljava/lang/Object;T13:Ljava/lang/Object;T14:Ljava/lang/Object;T15:Ljava/lang/Object;T16:Ljava/lang/Object;T17:Ljava/lang/Object;R:Ljava/lang/Object;>(Lscala/Function17<TT1;TT2;TT3;TT4;TT5;TT6;TT7;TT8;TT9;TT10;TT11;TT12;TT13;TT14;TT15;TT16;TT17;TR;>;)Ljava/lang/String;
    MethodParameters:
      Name                           Flags
      f                              final

  public <T1 extends java.lang.Object, T2 extends java.lang.Object, T3 extends java.lang.Object, T4 extends java.lang.Object, T5 extends java.lang.Object, T6 extends java.lang.Object, T7 extends java.lang.Object, T8 extends java.lang.Object, T9 extends java.lang.Object, T10 extends java.lang.Object, T11 extends java.lang.Object, T12 extends java.lang.Object, T13 extends java.lang.Object, T14 extends java.lang.Object, T15 extends java.lang.Object, T16 extends java.lang.Object, T17 extends java.lang.Object, R extends java.lang.Object> scala.Function17<T1, T2, T3, T4, T5, T6, T7, T8, T9, T10, T11, T12, T13, T14, T15, T16, T17, R> parse17(org.sireum.Json$Parser, java.lang.String);
    descriptor: (Lorg/sireum/Json$Parser;Ljava/lang/String;)Lscala/Function17;
    flags: (0x0001) ACC_PUBLIC
    Code:
      stack=3, locals=3, args_size=3
         0: getstatic     #29                 // Field org/sireum/JsonFun_Ext$.MODULE$:Lorg/sireum/JsonFun_Ext$;
         3: aload_1
         4: aload_2
         5: invokevirtual #336                // Method org/sireum/JsonFun_Ext$.parse17:(Lorg/sireum/Json$Parser;Ljava/lang/String;)Lscala/Function17;
         8: areturn
      LineNumberTable:
        line 2517: 0
      LocalVariableTable:
        Start  Length  Slot  Name   Signature
            0       9     0  this   Lorg/sireum/Json$Fun$;
            0       9     1 parser   Lorg/sireum/Json$Parser;
            0       9     2     f   Ljava/lang/String;
    Signature: #328                         // <T1:Ljava/lang/Object;T2:Ljava/lang/Object;T3:Ljava/lang/Object;T4:Ljava/lang/Object;T5:Ljava/lang/Object;T6:Ljava/lang/Object;T7:Ljava/lang/Object;T8:Ljava/lang/Object;T9:Ljava/lang/Object;T10:Ljava/lang/Object;T11:Ljava/lang/Object;T12:Ljava/lang/Object;T13:Ljava/lang/Object;T14:Ljava/lang/Object;T15:Ljava/lang/Object;T16:Ljava/lang/Object;T17:Ljava/lang/Object;R:Ljava/lang/Object;>(Lorg/sireum/Json$Parser;Ljava/lang/String;)Lscala/Function17<TT1;TT2;TT3;TT4;TT5;TT6;TT7;TT8;TT9;TT10;TT11;TT12;TT13;TT14;TT15;TT16;TT17;TR;>;
    MethodParameters:
      Name                           Flags
      parser                         final
      f                              final

  public <T1 extends java.lang.Object, T2 extends java.lang.Object, T3 extends java.lang.Object, T4 extends java.lang.Object, T5 extends java.lang.Object, T6 extends java.lang.Object, T7 extends java.lang.Object, T8 extends java.lang.Object, T9 extends java.lang.Object, T10 extends java.lang.Object, T11 extends java.lang.Object, T12 extends java.lang.Object, T13 extends java.lang.Object, T14 extends java.lang.Object, T15 extends java.lang.Object, T16 extends java.lang.Object, T17 extends java.lang.Object, T18 extends java.lang.Object, R extends java.lang.Object> java.lang.String printPure18(scala.Function18<T1, T2, T3, T4, T5, T6, T7, T8, T9, T10, T11, T12, T13, T14, T15, T16, T17, T18, R>);
    descriptor: (Lscala/Function18;)Ljava/lang/String;
    flags: (0x0001) ACC_PUBLIC
    Code:
      stack=2, locals=2, args_size=2
         0: getstatic     #29                 // Field org/sireum/JsonFun_Ext$.MODULE$:Lorg/sireum/JsonFun_Ext$;
         3: aload_1
         4: invokevirtual #341                // Method org/sireum/JsonFun_Ext$.printPure18:(Lscala/Function18;)Ljava/lang/String;
         7: areturn
      LineNumberTable:
        line 2519: 0
      LocalVariableTable:
        Start  Length  Slot  Name   Signature
            0       8     0  this   Lorg/sireum/Json$Fun$;
            0       8     1     f   Lscala/Function18;
    Signature: #339                         // <T1:Ljava/lang/Object;T2:Ljava/lang/Object;T3:Ljava/lang/Object;T4:Ljava/lang/Object;T5:Ljava/lang/Object;T6:Ljava/lang/Object;T7:Ljava/lang/Object;T8:Ljava/lang/Object;T9:Ljava/lang/Object;T10:Ljava/lang/Object;T11:Ljava/lang/Object;T12:Ljava/lang/Object;T13:Ljava/lang/Object;T14:Ljava/lang/Object;T15:Ljava/lang/Object;T16:Ljava/lang/Object;T17:Ljava/lang/Object;T18:Ljava/lang/Object;R:Ljava/lang/Object;>(Lscala/Function18<TT1;TT2;TT3;TT4;TT5;TT6;TT7;TT8;TT9;TT10;TT11;TT12;TT13;TT14;TT15;TT16;TT17;TT18;TR;>;)Ljava/lang/String;
    MethodParameters:
      Name                           Flags
      f                              final

  public <T1 extends java.lang.Object, T2 extends java.lang.Object, T3 extends java.lang.Object, T4 extends java.lang.Object, T5 extends java.lang.Object, T6 extends java.lang.Object, T7 extends java.lang.Object, T8 extends java.lang.Object, T9 extends java.lang.Object, T10 extends java.lang.Object, T11 extends java.lang.Object, T12 extends java.lang.Object, T13 extends java.lang.Object, T14 extends java.lang.Object, T15 extends java.lang.Object, T16 extends java.lang.Object, T17 extends java.lang.Object, T18 extends java.lang.Object, R extends java.lang.Object> scala.Function18<T1, T2, T3, T4, T5, T6, T7, T8, T9, T10, T11, T12, T13, T14, T15, T16, T17, T18, R> parsePure18(org.sireum.Json$Parser, java.lang.String);
    descriptor: (Lorg/sireum/Json$Parser;Ljava/lang/String;)Lscala/Function18;
    flags: (0x0001) ACC_PUBLIC
    Code:
      stack=3, locals=3, args_size=3
         0: getstatic     #29                 // Field org/sireum/JsonFun_Ext$.MODULE$:Lorg/sireum/JsonFun_Ext$;
         3: aload_1
         4: aload_2
         5: invokevirtual #347                // Method org/sireum/JsonFun_Ext$.parsePure18:(Lorg/sireum/Json$Parser;Ljava/lang/String;)Lscala/Function18;
         8: areturn
      LineNumberTable:
        line 2520: 0
      LocalVariableTable:
        Start  Length  Slot  Name   Signature
            0       9     0  this   Lorg/sireum/Json$Fun$;
            0       9     1 parser   Lorg/sireum/Json$Parser;
            0       9     2     f   Ljava/lang/String;
    Signature: #345                         // <T1:Ljava/lang/Object;T2:Ljava/lang/Object;T3:Ljava/lang/Object;T4:Ljava/lang/Object;T5:Ljava/lang/Object;T6:Ljava/lang/Object;T7:Ljava/lang/Object;T8:Ljava/lang/Object;T9:Ljava/lang/Object;T10:Ljava/lang/Object;T11:Ljava/lang/Object;T12:Ljava/lang/Object;T13:Ljava/lang/Object;T14:Ljava/lang/Object;T15:Ljava/lang/Object;T16:Ljava/lang/Object;T17:Ljava/lang/Object;T18:Ljava/lang/Object;R:Ljava/lang/Object;>(Lorg/sireum/Json$Parser;Ljava/lang/String;)Lscala/Function18<TT1;TT2;TT3;TT4;TT5;TT6;TT7;TT8;TT9;TT10;TT11;TT12;TT13;TT14;TT15;TT16;TT17;TT18;TR;>;
    MethodParameters:
      Name                           Flags
      parser                         final
      f                              final

  public <T1 extends java.lang.Object, T2 extends java.lang.Object, T3 extends java.lang.Object, T4 extends java.lang.Object, T5 extends java.lang.Object, T6 extends java.lang.Object, T7 extends java.lang.Object, T8 extends java.lang.Object, T9 extends java.lang.Object, T10 extends java.lang.Object, T11 extends java.lang.Object, T12 extends java.lang.Object, T13 extends java.lang.Object, T14 extends java.lang.Object, T15 extends java.lang.Object, T16 extends java.lang.Object, T17 extends java.lang.Object, T18 extends java.lang.Object, R extends java.lang.Object> java.lang.String print18(scala.Function18<T1, T2, T3, T4, T5, T6, T7, T8, T9, T10, T11, T12, T13, T14, T15, T16, T17, T18, R>);
    descriptor: (Lscala/Function18;)Ljava/lang/String;
    flags: (0x0001) ACC_PUBLIC
    Code:
      stack=2, locals=2, args_size=2
         0: getstatic     #29                 // Field org/sireum/JsonFun_Ext$.MODULE$:Lorg/sireum/JsonFun_Ext$;
         3: aload_1
         4: invokevirtual #350                // Method org/sireum/JsonFun_Ext$.print18:(Lscala/Function18;)Ljava/lang/String;
         7: areturn
      LineNumberTable:
        line 2522: 0
      LocalVariableTable:
        Start  Length  Slot  Name   Signature
            0       8     0  this   Lorg/sireum/Json$Fun$;
            0       8     1     f   Lscala/Function18;
    Signature: #339                         // <T1:Ljava/lang/Object;T2:Ljava/lang/Object;T3:Ljava/lang/Object;T4:Ljava/lang/Object;T5:Ljava/lang/Object;T6:Ljava/lang/Object;T7:Ljava/lang/Object;T8:Ljava/lang/Object;T9:Ljava/lang/Object;T10:Ljava/lang/Object;T11:Ljava/lang/Object;T12:Ljava/lang/Object;T13:Ljava/lang/Object;T14:Ljava/lang/Object;T15:Ljava/lang/Object;T16:Ljava/lang/Object;T17:Ljava/lang/Object;T18:Ljava/lang/Object;R:Ljava/lang/Object;>(Lscala/Function18<TT1;TT2;TT3;TT4;TT5;TT6;TT7;TT8;TT9;TT10;TT11;TT12;TT13;TT14;TT15;TT16;TT17;TT18;TR;>;)Ljava/lang/String;
    MethodParameters:
      Name                           Flags
      f                              final

  public <T1 extends java.lang.Object, T2 extends java.lang.Object, T3 extends java.lang.Object, T4 extends java.lang.Object, T5 extends java.lang.Object, T6 extends java.lang.Object, T7 extends java.lang.Object, T8 extends java.lang.Object, T9 extends java.lang.Object, T10 extends java.lang.Object, T11 extends java.lang.Object, T12 extends java.lang.Object, T13 extends java.lang.Object, T14 extends java.lang.Object, T15 extends java.lang.Object, T16 extends java.lang.Object, T17 extends java.lang.Object, T18 extends java.lang.Object, R extends java.lang.Object> scala.Function18<T1, T2, T3, T4, T5, T6, T7, T8, T9, T10, T11, T12, T13, T14, T15, T16, T17, T18, R> parse18(org.sireum.Json$Parser, java.lang.String);
    descriptor: (Lorg/sireum/Json$Parser;Ljava/lang/String;)Lscala/Function18;
    flags: (0x0001) ACC_PUBLIC
    Code:
      stack=3, locals=3, args_size=3
         0: getstatic     #29                 // Field org/sireum/JsonFun_Ext$.MODULE$:Lorg/sireum/JsonFun_Ext$;
         3: aload_1
         4: aload_2
         5: invokevirtual #353                // Method org/sireum/JsonFun_Ext$.parse18:(Lorg/sireum/Json$Parser;Ljava/lang/String;)Lscala/Function18;
         8: areturn
      LineNumberTable:
        line 2523: 0
      LocalVariableTable:
        Start  Length  Slot  Name   Signature
            0       9     0  this   Lorg/sireum/Json$Fun$;
            0       9     1 parser   Lorg/sireum/Json$Parser;
            0       9     2     f   Ljava/lang/String;
    Signature: #345                         // <T1:Ljava/lang/Object;T2:Ljava/lang/Object;T3:Ljava/lang/Object;T4:Ljava/lang/Object;T5:Ljava/lang/Object;T6:Ljava/lang/Object;T7:Ljava/lang/Object;T8:Ljava/lang/Object;T9:Ljava/lang/Object;T10:Ljava/lang/Object;T11:Ljava/lang/Object;T12:Ljava/lang/Object;T13:Ljava/lang/Object;T14:Ljava/lang/Object;T15:Ljava/lang/Object;T16:Ljava/lang/Object;T17:Ljava/lang/Object;T18:Ljava/lang/Object;R:Ljava/lang/Object;>(Lorg/sireum/Json$Parser;Ljava/lang/String;)Lscala/Function18<TT1;TT2;TT3;TT4;TT5;TT6;TT7;TT8;TT9;TT10;TT11;TT12;TT13;TT14;TT15;TT16;TT17;TT18;TR;>;
    MethodParameters:
      Name                           Flags
      parser                         final
      f                              final

  public <T1 extends java.lang.Object, T2 extends java.lang.Object, T3 extends java.lang.Object, T4 extends java.lang.Object, T5 extends java.lang.Object, T6 extends java.lang.Object, T7 extends java.lang.Object, T8 extends java.lang.Object, T9 extends java.lang.Object, T10 extends java.lang.Object, T11 extends java.lang.Object, T12 extends java.lang.Object, T13 extends java.lang.Object, T14 extends java.lang.Object, T15 extends java.lang.Object, T16 extends java.lang.Object, T17 extends java.lang.Object, T18 extends java.lang.Object, T19 extends java.lang.Object, R extends java.lang.Object> java.lang.String printPure19(scala.Function19<T1, T2, T3, T4, T5, T6, T7, T8, T9, T10, T11, T12, T13, T14, T15, T16, T17, T18, T19, R>);
    descriptor: (Lscala/Function19;)Ljava/lang/String;
    flags: (0x0001) ACC_PUBLIC
    Code:
      stack=2, locals=2, args_size=2
         0: getstatic     #29                 // Field org/sireum/JsonFun_Ext$.MODULE$:Lorg/sireum/JsonFun_Ext$;
         3: aload_1
         4: invokevirtual #358                // Method org/sireum/JsonFun_Ext$.printPure19:(Lscala/Function19;)Ljava/lang/String;
         7: areturn
      LineNumberTable:
        line 2525: 0
      LocalVariableTable:
        Start  Length  Slot  Name   Signature
            0       8     0  this   Lorg/sireum/Json$Fun$;
            0       8     1     f   Lscala/Function19;
    Signature: #356                         // <T1:Ljava/lang/Object;T2:Ljava/lang/Object;T3:Ljava/lang/Object;T4:Ljava/lang/Object;T5:Ljava/lang/Object;T6:Ljava/lang/Object;T7:Ljava/lang/Object;T8:Ljava/lang/Object;T9:Ljava/lang/Object;T10:Ljava/lang/Object;T11:Ljava/lang/Object;T12:Ljava/lang/Object;T13:Ljava/lang/Object;T14:Ljava/lang/Object;T15:Ljava/lang/Object;T16:Ljava/lang/Object;T17:Ljava/lang/Object;T18:Ljava/lang/Object;T19:Ljava/lang/Object;R:Ljava/lang/Object;>(Lscala/Function19<TT1;TT2;TT3;TT4;TT5;TT6;TT7;TT8;TT9;TT10;TT11;TT12;TT13;TT14;TT15;TT16;TT17;TT18;TT19;TR;>;)Ljava/lang/String;
    MethodParameters:
      Name                           Flags
      f                              final

  public <T1 extends java.lang.Object, T2 extends java.lang.Object, T3 extends java.lang.Object, T4 extends java.lang.Object, T5 extends java.lang.Object, T6 extends java.lang.Object, T7 extends java.lang.Object, T8 extends java.lang.Object, T9 extends java.lang.Object, T10 extends java.lang.Object, T11 extends java.lang.Object, T12 extends java.lang.Object, T13 extends java.lang.Object, T14 extends java.lang.Object, T15 extends java.lang.Object, T16 extends java.lang.Object, T17 extends java.lang.Object, T18 extends java.lang.Object, T19 extends java.lang.Object, R extends java.lang.Object> scala.Function19<T1, T2, T3, T4, T5, T6, T7, T8, T9, T10, T11, T12, T13, T14, T15, T16, T17, T18, T19, R> parsePure19(org.sireum.Json$Parser, java.lang.String);
    descriptor: (Lorg/sireum/Json$Parser;Ljava/lang/String;)Lscala/Function19;
    flags: (0x0001) ACC_PUBLIC
    Code:
      stack=3, locals=3, args_size=3
         0: getstatic     #29                 // Field org/sireum/JsonFun_Ext$.MODULE$:Lorg/sireum/JsonFun_Ext$;
         3: aload_1
         4: aload_2
         5: invokevirtual #364                // Method org/sireum/JsonFun_Ext$.parsePure19:(Lorg/sireum/Json$Parser;Ljava/lang/String;)Lscala/Function19;
         8: areturn
      LineNumberTable:
        line 2526: 0
      LocalVariableTable:
        Start  Length  Slot  Name   Signature
            0       9     0  this   Lorg/sireum/Json$Fun$;
            0       9     1 parser   Lorg/sireum/Json$Parser;
            0       9     2     f   Ljava/lang/String;
    Signature: #362                         // <T1:Ljava/lang/Object;T2:Ljava/lang/Object;T3:Ljava/lang/Object;T4:Ljava/lang/Object;T5:Ljava/lang/Object;T6:Ljava/lang/Object;T7:Ljava/lang/Object;T8:Ljava/lang/Object;T9:Ljava/lang/Object;T10:Ljava/lang/Object;T11:Ljava/lang/Object;T12:Ljava/lang/Object;T13:Ljava/lang/Object;T14:Ljava/lang/Object;T15:Ljava/lang/Object;T16:Ljava/lang/Object;T17:Ljava/lang/Object;T18:Ljava/lang/Object;T19:Ljava/lang/Object;R:Ljava/lang/Object;>(Lorg/sireum/Json$Parser;Ljava/lang/String;)Lscala/Function19<TT1;TT2;TT3;TT4;TT5;TT6;TT7;TT8;TT9;TT10;TT11;TT12;TT13;TT14;TT15;TT16;TT17;TT18;TT19;TR;>;
    MethodParameters:
      Name                           Flags
      parser                         final
      f                              final

  public <T1 extends java.lang.Object, T2 extends java.lang.Object, T3 extends java.lang.Object, T4 extends java.lang.Object, T5 extends java.lang.Object, T6 extends java.lang.Object, T7 extends java.lang.Object, T8 extends java.lang.Object, T9 extends java.lang.Object, T10 extends java.lang.Object, T11 extends java.lang.Object, T12 extends java.lang.Object, T13 extends java.lang.Object, T14 extends java.lang.Object, T15 extends java.lang.Object, T16 extends java.lang.Object, T17 extends java.lang.Object, T18 extends java.lang.Object, T19 extends java.lang.Object, R extends java.lang.Object> java.lang.String print19(scala.Function19<T1, T2, T3, T4, T5, T6, T7, T8, T9, T10, T11, T12, T13, T14, T15, T16, T17, T18, T19, R>);
    descriptor: (Lscala/Function19;)Ljava/lang/String;
    flags: (0x0001) ACC_PUBLIC
    Code:
      stack=2, locals=2, args_size=2
         0: getstatic     #29                 // Field org/sireum/JsonFun_Ext$.MODULE$:Lorg/sireum/JsonFun_Ext$;
         3: aload_1
         4: invokevirtual #367                // Method org/sireum/JsonFun_Ext$.print19:(Lscala/Function19;)Ljava/lang/String;
         7: areturn
      LineNumberTable:
        line 2528: 0
      LocalVariableTable:
        Start  Length  Slot  Name   Signature
            0       8     0  this   Lorg/sireum/Json$Fun$;
            0       8     1     f   Lscala/Function19;
    Signature: #356                         // <T1:Ljava/lang/Object;T2:Ljava/lang/Object;T3:Ljava/lang/Object;T4:Ljava/lang/Object;T5:Ljava/lang/Object;T6:Ljava/lang/Object;T7:Ljava/lang/Object;T8:Ljava/lang/Object;T9:Ljava/lang/Object;T10:Ljava/lang/Object;T11:Ljava/lang/Object;T12:Ljava/lang/Object;T13:Ljava/lang/Object;T14:Ljava/lang/Object;T15:Ljava/lang/Object;T16:Ljava/lang/Object;T17:Ljava/lang/Object;T18:Ljava/lang/Object;T19:Ljava/lang/Object;R:Ljava/lang/Object;>(Lscala/Function19<TT1;TT2;TT3;TT4;TT5;TT6;TT7;TT8;TT9;TT10;TT11;TT12;TT13;TT14;TT15;TT16;TT17;TT18;TT19;TR;>;)Ljava/lang/String;
    MethodParameters:
      Name                           Flags
      f                              final

  public <T1 extends java.lang.Object, T2 extends java.lang.Object, T3 extends java.lang.Object, T4 extends java.lang.Object, T5 extends java.lang.Object, T6 extends java.lang.Object, T7 extends java.lang.Object, T8 extends java.lang.Object, T9 extends java.lang.Object, T10 extends java.lang.Object, T11 extends java.lang.Object, T12 extends java.lang.Object, T13 extends java.lang.Object, T14 extends java.lang.Object, T15 extends java.lang.Object, T16 extends java.lang.Object, T17 extends java.lang.Object, T18 extends java.lang.Object, T19 extends java.lang.Object, R extends java.lang.Object> scala.Function19<T1, T2, T3, T4, T5, T6, T7, T8, T9, T10, T11, T12, T13, T14, T15, T16, T17, T18, T19, R> parse19(org.sireum.Json$Parser, java.lang.String);
    descriptor: (Lorg/sireum/Json$Parser;Ljava/lang/String;)Lscala/Function19;
    flags: (0x0001) ACC_PUBLIC
    Code:
      stack=3, locals=3, args_size=3
         0: getstatic     #29                 // Field org/sireum/JsonFun_Ext$.MODULE$:Lorg/sireum/JsonFun_Ext$;
         3: aload_1
         4: aload_2
         5: invokevirtual #370                // Method org/sireum/JsonFun_Ext$.parse19:(Lorg/sireum/Json$Parser;Ljava/lang/String;)Lscala/Function19;
         8: areturn
      LineNumberTable:
        line 2529: 0
      LocalVariableTable:
        Start  Length  Slot  Name   Signature
            0       9     0  this   Lorg/sireum/Json$Fun$;
            0       9     1 parser   Lorg/sireum/Json$Parser;
            0       9     2     f   Ljava/lang/String;
    Signature: #362                         // <T1:Ljava/lang/Object;T2:Ljava/lang/Object;T3:Ljava/lang/Object;T4:Ljava/lang/Object;T5:Ljava/lang/Object;T6:Ljava/lang/Object;T7:Ljava/lang/Object;T8:Ljava/lang/Object;T9:Ljava/lang/Object;T10:Ljava/lang/Object;T11:Ljava/lang/Object;T12:Ljava/lang/Object;T13:Ljava/lang/Object;T14:Ljava/lang/Object;T15:Ljava/lang/Object;T16:Ljava/lang/Object;T17:Ljava/lang/Object;T18:Ljava/lang/Object;T19:Ljava/lang/Object;R:Ljava/lang/Object;>(Lorg/sireum/Json$Parser;Ljava/lang/String;)Lscala/Function19<TT1;TT2;TT3;TT4;TT5;TT6;TT7;TT8;TT9;TT10;TT11;TT12;TT13;TT14;TT15;TT16;TT17;TT18;TT19;TR;>;
    MethodParameters:
      Name                           Flags
      parser                         final
      f                              final

  public <T1 extends java.lang.Object, T2 extends java.lang.Object, T3 extends java.lang.Object, T4 extends java.lang.Object, T5 extends java.lang.Object, T6 extends java.lang.Object, T7 extends java.lang.Object, T8 extends java.lang.Object, T9 extends java.lang.Object, T10 extends java.lang.Object, T11 extends java.lang.Object, T12 extends java.lang.Object, T13 extends java.lang.Object, T14 extends java.lang.Object, T15 extends java.lang.Object, T16 extends java.lang.Object, T17 extends java.lang.Object, T18 extends java.lang.Object, T19 extends java.lang.Object, T20 extends java.lang.Object, R extends java.lang.Object> java.lang.String printPure20(scala.Function20<T1, T2, T3, T4, T5, T6, T7, T8, T9, T10, T11, T12, T13, T14, T15, T16, T17, T18, T19, T20, R>);
    descriptor: (Lscala/Function20;)Ljava/lang/String;
    flags: (0x0001) ACC_PUBLIC
    Code:
      stack=2, locals=2, args_size=2
         0: getstatic     #29                 // Field org/sireum/JsonFun_Ext$.MODULE$:Lorg/sireum/JsonFun_Ext$;
         3: aload_1
         4: invokevirtual #375                // Method org/sireum/JsonFun_Ext$.printPure20:(Lscala/Function20;)Ljava/lang/String;
         7: areturn
      LineNumberTable:
        line 2531: 0
      LocalVariableTable:
        Start  Length  Slot  Name   Signature
            0       8     0  this   Lorg/sireum/Json$Fun$;
            0       8     1     f   Lscala/Function20;
    Signature: #373                         // <T1:Ljava/lang/Object;T2:Ljava/lang/Object;T3:Ljava/lang/Object;T4:Ljava/lang/Object;T5:Ljava/lang/Object;T6:Ljava/lang/Object;T7:Ljava/lang/Object;T8:Ljava/lang/Object;T9:Ljava/lang/Object;T10:Ljava/lang/Object;T11:Ljava/lang/Object;T12:Ljava/lang/Object;T13:Ljava/lang/Object;T14:Ljava/lang/Object;T15:Ljava/lang/Object;T16:Ljava/lang/Object;T17:Ljava/lang/Object;T18:Ljava/lang/Object;T19:Ljava/lang/Object;T20:Ljava/lang/Object;R:Ljava/lang/Object;>(Lscala/Function20<TT1;TT2;TT3;TT4;TT5;TT6;TT7;TT8;TT9;TT10;TT11;TT12;TT13;TT14;TT15;TT16;TT17;TT18;TT19;TT20;TR;>;)Ljava/lang/String;
    MethodParameters:
      Name                           Flags
      f                              final

  public <T1 extends java.lang.Object, T2 extends java.lang.Object, T3 extends java.lang.Object, T4 extends java.lang.Object, T5 extends java.lang.Object, T6 extends java.lang.Object, T7 extends java.lang.Object, T8 extends java.lang.Object, T9 extends java.lang.Object, T10 extends java.lang.Object, T11 extends java.lang.Object, T12 extends java.lang.Object, T13 extends java.lang.Object, T14 extends java.lang.Object, T15 extends java.lang.Object, T16 extends java.lang.Object, T17 extends java.lang.Object, T18 extends java.lang.Object, T19 extends java.lang.Object, T20 extends java.lang.Object, R extends java.lang.Object> scala.Function20<T1, T2, T3, T4, T5, T6, T7, T8, T9, T10, T11, T12, T13, T14, T15, T16, T17, T18, T19, T20, R> parsePure20(org.sireum.Json$Parser, java.lang.String);
    descriptor: (Lorg/sireum/Json$Parser;Ljava/lang/String;)Lscala/Function20;
    flags: (0x0001) ACC_PUBLIC
    Code:
      stack=3, locals=3, args_size=3
         0: getstatic     #29                 // Field org/sireum/JsonFun_Ext$.MODULE$:Lorg/sireum/JsonFun_Ext$;
         3: aload_1
         4: aload_2
         5: invokevirtual #381                // Method org/sireum/JsonFun_Ext$.parsePure20:(Lorg/sireum/Json$Parser;Ljava/lang/String;)Lscala/Function20;
         8: areturn
      LineNumberTable:
        line 2532: 0
      LocalVariableTable:
        Start  Length  Slot  Name   Signature
            0       9     0  this   Lorg/sireum/Json$Fun$;
            0       9     1 parser   Lorg/sireum/Json$Parser;
            0       9     2     f   Ljava/lang/String;
    Signature: #379                         // <T1:Ljava/lang/Object;T2:Ljava/lang/Object;T3:Ljava/lang/Object;T4:Ljava/lang/Object;T5:Ljava/lang/Object;T6:Ljava/lang/Object;T7:Ljava/lang/Object;T8:Ljava/lang/Object;T9:Ljava/lang/Object;T10:Ljava/lang/Object;T11:Ljava/lang/Object;T12:Ljava/lang/Object;T13:Ljava/lang/Object;T14:Ljava/lang/Object;T15:Ljava/lang/Object;T16:Ljava/lang/Object;T17:Ljava/lang/Object;T18:Ljava/lang/Object;T19:Ljava/lang/Object;T20:Ljava/lang/Object;R:Ljava/lang/Object;>(Lorg/sireum/Json$Parser;Ljava/lang/String;)Lscala/Function20<TT1;TT2;TT3;TT4;TT5;TT6;TT7;TT8;TT9;TT10;TT11;TT12;TT13;TT14;TT15;TT16;TT17;TT18;TT19;TT20;TR;>;
    MethodParameters:
      Name                           Flags
      parser                         final
      f                              final

  public <T1 extends java.lang.Object, T2 extends java.lang.Object, T3 extends java.lang.Object, T4 extends java.lang.Object, T5 extends java.lang.Object, T6 extends java.lang.Object, T7 extends java.lang.Object, T8 extends java.lang.Object, T9 extends java.lang.Object, T10 extends java.lang.Object, T11 extends java.lang.Object, T12 extends java.lang.Object, T13 extends java.lang.Object, T14 extends java.lang.Object, T15 extends java.lang.Object, T16 extends java.lang.Object, T17 extends java.lang.Object, T18 extends java.lang.Object, T19 extends java.lang.Object, T20 extends java.lang.Object, R extends java.lang.Object> java.lang.String print20(scala.Function20<T1, T2, T3, T4, T5, T6, T7, T8, T9, T10, T11, T12, T13, T14, T15, T16, T17, T18, T19, T20, R>);
    descriptor: (Lscala/Function20;)Ljava/lang/String;
    flags: (0x0001) ACC_PUBLIC
    Code:
      stack=2, locals=2, args_size=2
         0: getstatic     #29                 // Field org/sireum/JsonFun_Ext$.MODULE$:Lorg/sireum/JsonFun_Ext$;
         3: aload_1
         4: invokevirtual #384                // Method org/sireum/JsonFun_Ext$.print20:(Lscala/Function20;)Ljava/lang/String;
         7: areturn
      LineNumberTable:
        line 2534: 0
      LocalVariableTable:
        Start  Length  Slot  Name   Signature
            0       8     0  this   Lorg/sireum/Json$Fun$;
            0       8     1     f   Lscala/Function20;
    Signature: #373                         // <T1:Ljava/lang/Object;T2:Ljava/lang/Object;T3:Ljava/lang/Object;T4:Ljava/lang/Object;T5:Ljava/lang/Object;T6:Ljava/lang/Object;T7:Ljava/lang/Object;T8:Ljava/lang/Object;T9:Ljava/lang/Object;T10:Ljava/lang/Object;T11:Ljava/lang/Object;T12:Ljava/lang/Object;T13:Ljava/lang/Object;T14:Ljava/lang/Object;T15:Ljava/lang/Object;T16:Ljava/lang/Object;T17:Ljava/lang/Object;T18:Ljava/lang/Object;T19:Ljava/lang/Object;T20:Ljava/lang/Object;R:Ljava/lang/Object;>(Lscala/Function20<TT1;TT2;TT3;TT4;TT5;TT6;TT7;TT8;TT9;TT10;TT11;TT12;TT13;TT14;TT15;TT16;TT17;TT18;TT19;TT20;TR;>;)Ljava/lang/String;
    MethodParameters:
      Name                           Flags
      f                              final

  public <T1 extends java.lang.Object, T2 extends java.lang.Object, T3 extends java.lang.Object, T4 extends java.lang.Object, T5 extends java.lang.Object, T6 extends java.lang.Object, T7 extends java.lang.Object, T8 extends java.lang.Object, T9 extends java.lang.Object, T10 extends java.lang.Object, T11 extends java.lang.Object, T12 extends java.lang.Object, T13 extends java.lang.Object, T14 extends java.lang.Object, T15 extends java.lang.Object, T16 extends java.lang.Object, T17 extends java.lang.Object, T18 extends java.lang.Object, T19 extends java.lang.Object, T20 extends java.lang.Object, R extends java.lang.Object> scala.Function20<T1, T2, T3, T4, T5, T6, T7, T8, T9, T10, T11, T12, T13, T14, T15, T16, T17, T18, T19, T20, R> parse20(org.sireum.Json$Parser, java.lang.String);
    descriptor: (Lorg/sireum/Json$Parser;Ljava/lang/String;)Lscala/Function20;
    flags: (0x0001) ACC_PUBLIC
    Code:
      stack=3, locals=3, args_size=3
         0: getstatic     #29                 // Field org/sireum/JsonFun_Ext$.MODULE$:Lorg/sireum/JsonFun_Ext$;
         3: aload_1
         4: aload_2
         5: invokevirtual #387                // Method org/sireum/JsonFun_Ext$.parse20:(Lorg/sireum/Json$Parser;Ljava/lang/String;)Lscala/Function20;
         8: areturn
      LineNumberTable:
        line 2535: 0
      LocalVariableTable:
        Start  Length  Slot  Name   Signature
            0       9     0  this   Lorg/sireum/Json$Fun$;
            0       9     1 parser   Lorg/sireum/Json$Parser;
            0       9     2     f   Ljava/lang/String;
    Signature: #379                         // <T1:Ljava/lang/Object;T2:Ljava/lang/Object;T3:Ljava/lang/Object;T4:Ljava/lang/Object;T5:Ljava/lang/Object;T6:Ljava/lang/Object;T7:Ljava/lang/Object;T8:Ljava/lang/Object;T9:Ljava/lang/Object;T10:Ljava/lang/Object;T11:Ljava/lang/Object;T12:Ljava/lang/Object;T13:Ljava/lang/Object;T14:Ljava/lang/Object;T15:Ljava/lang/Object;T16:Ljava/lang/Object;T17:Ljava/lang/Object;T18:Ljava/lang/Object;T19:Ljava/lang/Object;T20:Ljava/lang/Object;R:Ljava/lang/Object;>(Lorg/sireum/Json$Parser;Ljava/lang/String;)Lscala/Function20<TT1;TT2;TT3;TT4;TT5;TT6;TT7;TT8;TT9;TT10;TT11;TT12;TT13;TT14;TT15;TT16;TT17;TT18;TT19;TT20;TR;>;
    MethodParameters:
      Name                           Flags
      parser                         final
      f                              final

  public <T1 extends java.lang.Object, T2 extends java.lang.Object, T3 extends java.lang.Object, T4 extends java.lang.Object, T5 extends java.lang.Object, T6 extends java.lang.Object, T7 extends java.lang.Object, T8 extends java.lang.Object, T9 extends java.lang.Object, T10 extends java.lang.Object, T11 extends java.lang.Object, T12 extends java.lang.Object, T13 extends java.lang.Object, T14 extends java.lang.Object, T15 extends java.lang.Object, T16 extends java.lang.Object, T17 extends java.lang.Object, T18 extends java.lang.Object, T19 extends java.lang.Object, T20 extends java.lang.Object, T21 extends java.lang.Object, R extends java.lang.Object> java.lang.String printPure21(scala.Function21<T1, T2, T3, T4, T5, T6, T7, T8, T9, T10, T11, T12, T13, T14, T15, T16, T17, T18, T19, T20, T21, R>);
    descriptor: (Lscala/Function21;)Ljava/lang/String;
    flags: (0x0001) ACC_PUBLIC
    Code:
      stack=2, locals=2, args_size=2
         0: getstatic     #29                 // Field org/sireum/JsonFun_Ext$.MODULE$:Lorg/sireum/JsonFun_Ext$;
         3: aload_1
         4: invokevirtual #392                // Method org/sireum/JsonFun_Ext$.printPure21:(Lscala/Function21;)Ljava/lang/String;
         7: areturn
      LineNumberTable:
        line 2537: 0
      LocalVariableTable:
        Start  Length  Slot  Name   Signature
            0       8     0  this   Lorg/sireum/Json$Fun$;
            0       8     1     f   Lscala/Function21;
    Signature: #390                         // <T1:Ljava/lang/Object;T2:Ljava/lang/Object;T3:Ljava/lang/Object;T4:Ljava/lang/Object;T5:Ljava/lang/Object;T6:Ljava/lang/Object;T7:Ljava/lang/Object;T8:Ljava/lang/Object;T9:Ljava/lang/Object;T10:Ljava/lang/Object;T11:Ljava/lang/Object;T12:Ljava/lang/Object;T13:Ljava/lang/Object;T14:Ljava/lang/Object;T15:Ljava/lang/Object;T16:Ljava/lang/Object;T17:Ljava/lang/Object;T18:Ljava/lang/Object;T19:Ljava/lang/Object;T20:Ljava/lang/Object;T21:Ljava/lang/Object;R:Ljava/lang/Object;>(Lscala/Function21<TT1;TT2;TT3;TT4;TT5;TT6;TT7;TT8;TT9;TT10;TT11;TT12;TT13;TT14;TT15;TT16;TT17;TT18;TT19;TT20;TT21;TR;>;)Ljava/lang/String;
    MethodParameters:
      Name                           Flags
      f                              final

  public <T1 extends java.lang.Object, T2 extends java.lang.Object, T3 extends java.lang.Object, T4 extends java.lang.Object, T5 extends java.lang.Object, T6 extends java.lang.Object, T7 extends java.lang.Object, T8 extends java.lang.Object, T9 extends java.lang.Object, T10 extends java.lang.Object, T11 extends java.lang.Object, T12 extends java.lang.Object, T13 extends java.lang.Object, T14 extends java.lang.Object, T15 extends java.lang.Object, T16 extends java.lang.Object, T17 extends java.lang.Object, T18 extends java.lang.Object, T19 extends java.lang.Object, T20 extends java.lang.Object, T21 extends java.lang.Object, R extends java.lang.Object> scala.Function21<T1, T2, T3, T4, T5, T6, T7, T8, T9, T10, T11, T12, T13, T14, T15, T16, T17, T18, T19, T20, T21, R> parsePure21(org.sireum.Json$Parser, java.lang.String);
    descriptor: (Lorg/sireum/Json$Parser;Ljava/lang/String;)Lscala/Function21;
    flags: (0x0001) ACC_PUBLIC
    Code:
      stack=3, locals=3, args_size=3
         0: getstatic     #29                 // Field org/sireum/JsonFun_Ext$.MODULE$:Lorg/sireum/JsonFun_Ext$;
         3: aload_1
         4: aload_2
         5: invokevirtual #398                // Method org/sireum/JsonFun_Ext$.parsePure21:(Lorg/sireum/Json$Parser;Ljava/lang/String;)Lscala/Function21;
         8: areturn
      LineNumberTable:
        line 2538: 0
      LocalVariableTable:
        Start  Length  Slot  Name   Signature
            0       9     0  this   Lorg/sireum/Json$Fun$;
            0       9     1 parser   Lorg/sireum/Json$Parser;
            0       9     2     f   Ljava/lang/String;
    Signature: #396                         // <T1:Ljava/lang/Object;T2:Ljava/lang/Object;T3:Ljava/lang/Object;T4:Ljava/lang/Object;T5:Ljava/lang/Object;T6:Ljava/lang/Object;T7:Ljava/lang/Object;T8:Ljava/lang/Object;T9:Ljava/lang/Object;T10:Ljava/lang/Object;T11:Ljava/lang/Object;T12:Ljava/lang/Object;T13:Ljava/lang/Object;T14:Ljava/lang/Object;T15:Ljava/lang/Object;T16:Ljava/lang/Object;T17:Ljava/lang/Object;T18:Ljava/lang/Object;T19:Ljava/lang/Object;T20:Ljava/lang/Object;T21:Ljava/lang/Object;R:Ljava/lang/Object;>(Lorg/sireum/Json$Parser;Ljava/lang/String;)Lscala/Function21<TT1;TT2;TT3;TT4;TT5;TT6;TT7;TT8;TT9;TT10;TT11;TT12;TT13;TT14;TT15;TT16;TT17;TT18;TT19;TT20;TT21;TR;>;
    MethodParameters:
      Name                           Flags
      parser                         final
      f                              final

  public <T1 extends java.lang.Object, T2 extends java.lang.Object, T3 extends java.lang.Object, T4 extends java.lang.Object, T5 extends java.lang.Object, T6 extends java.lang.Object, T7 extends java.lang.Object, T8 extends java.lang.Object, T9 extends java.lang.Object, T10 extends java.lang.Object, T11 extends java.lang.Object, T12 extends java.lang.Object, T13 extends java.lang.Object, T14 extends java.lang.Object, T15 extends java.lang.Object, T16 extends java.lang.Object, T17 extends java.lang.Object, T18 extends java.lang.Object, T19 extends java.lang.Object, T20 extends java.lang.Object, T21 extends java.lang.Object, R extends java.lang.Object> java.lang.String print21(scala.Function21<T1, T2, T3, T4, T5, T6, T7, T8, T9, T10, T11, T12, T13, T14, T15, T16, T17, T18, T19, T20, T21, R>);
    descriptor: (Lscala/Function21;)Ljava/lang/String;
    flags: (0x0001) ACC_PUBLIC
    Code:
      stack=2, locals=2, args_size=2
         0: getstatic     #29                 // Field org/sireum/JsonFun_Ext$.MODULE$:Lorg/sireum/JsonFun_Ext$;
         3: aload_1
         4: invokevirtual #401                // Method org/sireum/JsonFun_Ext$.print21:(Lscala/Function21;)Ljava/lang/String;
         7: areturn
      LineNumberTable:
        line 2540: 0
      LocalVariableTable:
        Start  Length  Slot  Name   Signature
            0       8     0  this   Lorg/sireum/Json$Fun$;
            0       8     1     f   Lscala/Function21;
    Signature: #390                         // <T1:Ljava/lang/Object;T2:Ljava/lang/Object;T3:Ljava/lang/Object;T4:Ljava/lang/Object;T5:Ljava/lang/Object;T6:Ljava/lang/Object;T7:Ljava/lang/Object;T8:Ljava/lang/Object;T9:Ljava/lang/Object;T10:Ljava/lang/Object;T11:Ljava/lang/Object;T12:Ljava/lang/Object;T13:Ljava/lang/Object;T14:Ljava/lang/Object;T15:Ljava/lang/Object;T16:Ljava/lang/Object;T17:Ljava/lang/Object;T18:Ljava/lang/Object;T19:Ljava/lang/Object;T20:Ljava/lang/Object;T21:Ljava/lang/Object;R:Ljava/lang/Object;>(Lscala/Function21<TT1;TT2;TT3;TT4;TT5;TT6;TT7;TT8;TT9;TT10;TT11;TT12;TT13;TT14;TT15;TT16;TT17;TT18;TT19;TT20;TT21;TR;>;)Ljava/lang/String;
    MethodParameters:
      Name                           Flags
      f                              final

  public <T1 extends java.lang.Object, T2 extends java.lang.Object, T3 extends java.lang.Object, T4 extends java.lang.Object, T5 extends java.lang.Object, T6 extends java.lang.Object, T7 extends java.lang.Object, T8 extends java.lang.Object, T9 extends java.lang.Object, T10 extends java.lang.Object, T11 extends java.lang.Object, T12 extends java.lang.Object, T13 extends java.lang.Object, T14 extends java.lang.Object, T15 extends java.lang.Object, T16 extends java.lang.Object, T17 extends java.lang.Object, T18 extends java.lang.Object, T19 extends java.lang.Object, T20 extends java.lang.Object, T21 extends java.lang.Object, R extends java.lang.Object> scala.Function21<T1, T2, T3, T4, T5, T6, T7, T8, T9, T10, T11, T12, T13, T14, T15, T16, T17, T18, T19, T20, T21, R> parse21(org.sireum.Json$Parser, java.lang.String);
    descriptor: (Lorg/sireum/Json$Parser;Ljava/lang/String;)Lscala/Function21;
    flags: (0x0001) ACC_PUBLIC
    Code:
      stack=3, locals=3, args_size=3
         0: getstatic     #29                 // Field org/sireum/JsonFun_Ext$.MODULE$:Lorg/sireum/JsonFun_Ext$;
         3: aload_1
         4: aload_2
         5: invokevirtual #404                // Method org/sireum/JsonFun_Ext$.parse21:(Lorg/sireum/Json$Parser;Ljava/lang/String;)Lscala/Function21;
         8: areturn
      LineNumberTable:
        line 2541: 0
      LocalVariableTable:
        Start  Length  Slot  Name   Signature
            0       9     0  this   Lorg/sireum/Json$Fun$;
            0       9     1 parser   Lorg/sireum/Json$Parser;
            0       9     2     f   Ljava/lang/String;
    Signature: #396                         // <T1:Ljava/lang/Object;T2:Ljava/lang/Object;T3:Ljava/lang/Object;T4:Ljava/lang/Object;T5:Ljava/lang/Object;T6:Ljava/lang/Object;T7:Ljava/lang/Object;T8:Ljava/lang/Object;T9:Ljava/lang/Object;T10:Ljava/lang/Object;T11:Ljava/lang/Object;T12:Ljava/lang/Object;T13:Ljava/lang/Object;T14:Ljava/lang/Object;T15:Ljava/lang/Object;T16:Ljava/lang/Object;T17:Ljava/lang/Object;T18:Ljava/lang/Object;T19:Ljava/lang/Object;T20:Ljava/lang/Object;T21:Ljava/lang/Object;R:Ljava/lang/Object;>(Lorg/sireum/Json$Parser;Ljava/lang/String;)Lscala/Function21<TT1;TT2;TT3;TT4;TT5;TT6;TT7;TT8;TT9;TT10;TT11;TT12;TT13;TT14;TT15;TT16;TT17;TT18;TT19;TT20;TT21;TR;>;
    MethodParameters:
      Name                           Flags
      parser                         final
      f                              final

  public <T1 extends java.lang.Object, T2 extends java.lang.Object, T3 extends java.lang.Object, T4 extends java.lang.Object, T5 extends java.lang.Object, T6 extends java.lang.Object, T7 extends java.lang.Object, T8 extends java.lang.Object, T9 extends java.lang.Object, T10 extends java.lang.Object, T11 extends java.lang.Object, T12 extends java.lang.Object, T13 extends java.lang.Object, T14 extends java.lang.Object, T15 extends java.lang.Object, T16 extends java.lang.Object, T17 extends java.lang.Object, T18 extends java.lang.Object, T19 extends java.lang.Object, T20 extends java.lang.Object, T21 extends java.lang.Object, T22 extends java.lang.Object, R extends java.lang.Object> java.lang.String printPure22(scala.Function22<T1, T2, T3, T4, T5, T6, T7, T8, T9, T10, T11, T12, T13, T14, T15, T16, T17, T18, T19, T20, T21, T22, R>);
    descriptor: (Lscala/Function22;)Ljava/lang/String;
    flags: (0x0001) ACC_PUBLIC
    Code:
      stack=2, locals=2, args_size=2
         0: getstatic     #29                 // Field org/sireum/JsonFun_Ext$.MODULE$:Lorg/sireum/JsonFun_Ext$;
         3: aload_1
         4: invokevirtual #409                // Method org/sireum/JsonFun_Ext$.printPure22:(Lscala/Function22;)Ljava/lang/String;
         7: areturn
      LineNumberTable:
        line 2543: 0
      LocalVariableTable:
        Start  Length  Slot  Name   Signature
            0       8     0  this   Lorg/sireum/Json$Fun$;
            0       8     1     f   Lscala/Function22;
    Signature: #407                         // <T1:Ljava/lang/Object;T2:Ljava/lang/Object;T3:Ljava/lang/Object;T4:Ljava/lang/Object;T5:Ljava/lang/Object;T6:Ljava/lang/Object;T7:Ljava/lang/Object;T8:Ljava/lang/Object;T9:Ljava/lang/Object;T10:Ljava/lang/Object;T11:Ljava/lang/Object;T12:Ljava/lang/Object;T13:Ljava/lang/Object;T14:Ljava/lang/Object;T15:Ljava/lang/Object;T16:Ljava/lang/Object;T17:Ljava/lang/Object;T18:Ljava/lang/Object;T19:Ljava/lang/Object;T20:Ljava/lang/Object;T21:Ljava/lang/Object;T22:Ljava/lang/Object;R:Ljava/lang/Object;>(Lscala/Function22<TT1;TT2;TT3;TT4;TT5;TT6;TT7;TT8;TT9;TT10;TT11;TT12;TT13;TT14;TT15;TT16;TT17;TT18;TT19;TT20;TT21;TT22;TR;>;)Ljava/lang/String;
    MethodParameters:
      Name                           Flags
      f                              final

  public <T1 extends java.lang.Object, T2 extends java.lang.Object, T3 extends java.lang.Object, T4 extends java.lang.Object, T5 extends java.lang.Object, T6 extends java.lang.Object, T7 extends java.lang.Object, T8 extends java.lang.Object, T9 extends java.lang.Object, T10 extends java.lang.Object, T11 extends java.lang.Object, T12 extends java.lang.Object, T13 extends java.lang.Object, T14 extends java.lang.Object, T15 extends java.lang.Object, T16 extends java.lang.Object, T17 extends java.lang.Object, T18 extends java.lang.Object, T19 extends java.lang.Object, T20 extends java.lang.Object, T21 extends java.lang.Object, T22 extends java.lang.Object, R extends java.lang.Object> scala.Function22<T1, T2, T3, T4, T5, T6, T7, T8, T9, T10, T11, T12, T13, T14, T15, T16, T17, T18, T19, T20, T21, T22, R> parsePure22(org.sireum.Json$Parser, java.lang.String);
    descriptor: (Lorg/sireum/Json$Parser;Ljava/lang/String;)Lscala/Function22;
    flags: (0x0001) ACC_PUBLIC
    Code:
      stack=3, locals=3, args_size=3
         0: getstatic     #29                 // Field org/sireum/JsonFun_Ext$.MODULE$:Lorg/sireum/JsonFun_Ext$;
         3: aload_1
         4: aload_2
         5: invokevirtual #415                // Method org/sireum/JsonFun_Ext$.parsePure22:(Lorg/sireum/Json$Parser;Ljava/lang/String;)Lscala/Function22;
         8: areturn
      LineNumberTable:
        line 2544: 0
      LocalVariableTable:
        Start  Length  Slot  Name   Signature
            0       9     0  this   Lorg/sireum/Json$Fun$;
            0       9     1 parser   Lorg/sireum/Json$Parser;
            0       9     2     f   Ljava/lang/String;
    Signature: #413                         // <T1:Ljava/lang/Object;T2:Ljava/lang/Object;T3:Ljava/lang/Object;T4:Ljava/lang/Object;T5:Ljava/lang/Object;T6:Ljava/lang/Object;T7:Ljava/lang/Object;T8:Ljava/lang/Object;T9:Ljava/lang/Object;T10:Ljava/lang/Object;T11:Ljava/lang/Object;T12:Ljava/lang/Object;T13:Ljava/lang/Object;T14:Ljava/lang/Object;T15:Ljava/lang/Object;T16:Ljava/lang/Object;T17:Ljava/lang/Object;T18:Ljava/lang/Object;T19:Ljava/lang/Object;T20:Ljava/lang/Object;T21:Ljava/lang/Object;T22:Ljava/lang/Object;R:Ljava/lang/Object;>(Lorg/sireum/Json$Parser;Ljava/lang/String;)Lscala/Function22<TT1;TT2;TT3;TT4;TT5;TT6;TT7;TT8;TT9;TT10;TT11;TT12;TT13;TT14;TT15;TT16;TT17;TT18;TT19;TT20;TT21;TT22;TR;>;
    MethodParameters:
      Name                           Flags
      parser                         final
      f                              final

  public <T1 extends java.lang.Object, T2 extends java.lang.Object, T3 extends java.lang.Object, T4 extends java.lang.Object, T5 extends java.lang.Object, T6 extends java.lang.Object, T7 extends java.lang.Object, T8 extends java.lang.Object, T9 extends java.lang.Object, T10 extends java.lang.Object, T11 extends java.lang.Object, T12 extends java.lang.Object, T13 extends java.lang.Object, T14 extends java.lang.Object, T15 extends java.lang.Object, T16 extends java.lang.Object, T17 extends java.lang.Object, T18 extends java.lang.Object, T19 extends java.lang.Object, T20 extends java.lang.Object, T21 extends java.lang.Object, T22 extends java.lang.Object, R extends java.lang.Object> java.lang.String print22(scala.Function22<T1, T2, T3, T4, T5, T6, T7, T8, T9, T10, T11, T12, T13, T14, T15, T16, T17, T18, T19, T20, T21, T22, R>);
    descriptor: (Lscala/Function22;)Ljava/lang/String;
    flags: (0x0001) ACC_PUBLIC
    Code:
      stack=2, locals=2, args_size=2
         0: getstatic     #29                 // Field org/sireum/JsonFun_Ext$.MODULE$:Lorg/sireum/JsonFun_Ext$;
         3: aload_1
         4: invokevirtual #418                // Method org/sireum/JsonFun_Ext$.print22:(Lscala/Function22;)Ljava/lang/String;
         7: areturn
      LineNumberTable:
        line 2546: 0
      LocalVariableTable:
        Start  Length  Slot  Name   Signature
            0       8     0  this   Lorg/sireum/Json$Fun$;
            0       8     1     f   Lscala/Function22;
    Signature: #407                         // <T1:Ljava/lang/Object;T2:Ljava/lang/Object;T3:Ljava/lang/Object;T4:Ljava/lang/Object;T5:Ljava/lang/Object;T6:Ljava/lang/Object;T7:Ljava/lang/Object;T8:Ljava/lang/Object;T9:Ljava/lang/Object;T10:Ljava/lang/Object;T11:Ljava/lang/Object;T12:Ljava/lang/Object;T13:Ljava/lang/Object;T14:Ljava/lang/Object;T15:Ljava/lang/Object;T16:Ljava/lang/Object;T17:Ljava/lang/Object;T18:Ljava/lang/Object;T19:Ljava/lang/Object;T20:Ljava/lang/Object;T21:Ljava/lang/Object;T22:Ljava/lang/Object;R:Ljava/lang/Object;>(Lscala/Function22<TT1;TT2;TT3;TT4;TT5;TT6;TT7;TT8;TT9;TT10;TT11;TT12;TT13;TT14;TT15;TT16;TT17;TT18;TT19;TT20;TT21;TT22;TR;>;)Ljava/lang/String;
    MethodParameters:
      Name                           Flags
      f                              final

  public <T1 extends java.lang.Object, T2 extends java.lang.Object, T3 extends java.lang.Object, T4 extends java.lang.Object, T5 extends java.lang.Object, T6 extends java.lang.Object, T7 extends java.lang.Object, T8 extends java.lang.Object, T9 extends java.lang.Object, T10 extends java.lang.Object, T11 extends java.lang.Object, T12 extends java.lang.Object, T13 extends java.lang.Object, T14 extends java.lang.Object, T15 extends java.lang.Object, T16 extends java.lang.Object, T17 extends java.lang.Object, T18 extends java.lang.Object, T19 extends java.lang.Object, T20 extends java.lang.Object, T21 extends java.lang.Object, T22 extends java.lang.Object, R extends java.lang.Object> scala.Function22<T1, T2, T3, T4, T5, T6, T7, T8, T9, T10, T11, T12, T13, T14, T15, T16, T17, T18, T19, T20, T21, T22, R> parse22(org.sireum.Json$Parser, java.lang.String);
    descriptor: (Lorg/sireum/Json$Parser;Ljava/lang/String;)Lscala/Function22;
    flags: (0x0001) ACC_PUBLIC
    Code:
      stack=3, locals=3, args_size=3
         0: getstatic     #29                 // Field org/sireum/JsonFun_Ext$.MODULE$:Lorg/sireum/JsonFun_Ext$;
         3: aload_1
         4: aload_2
         5: invokevirtual #421                // Method org/sireum/JsonFun_Ext$.parse22:(Lorg/sireum/Json$Parser;Ljava/lang/String;)Lscala/Function22;
         8: areturn
      LineNumberTable:
        line 2547: 0
      LocalVariableTable:
        Start  Length  Slot  Name   Signature
            0       9     0  this   Lorg/sireum/Json$Fun$;
            0       9     1 parser   Lorg/sireum/Json$Parser;
            0       9     2     f   Ljava/lang/String;
    Signature: #413                         // <T1:Ljava/lang/Object;T2:Ljava/lang/Object;T3:Ljava/lang/Object;T4:Ljava/lang/Object;T5:Ljava/lang/Object;T6:Ljava/lang/Object;T7:Ljava/lang/Object;T8:Ljava/lang/Object;T9:Ljava/lang/Object;T10:Ljava/lang/Object;T11:Ljava/lang/Object;T12:Ljava/lang/Object;T13:Ljava/lang/Object;T14:Ljava/lang/Object;T15:Ljava/lang/Object;T16:Ljava/lang/Object;T17:Ljava/lang/Object;T18:Ljava/lang/Object;T19:Ljava/lang/Object;T20:Ljava/lang/Object;T21:Ljava/lang/Object;T22:Ljava/lang/Object;R:Ljava/lang/Object;>(Lorg/sireum/Json$Parser;Ljava/lang/String;)Lscala/Function22<TT1;TT2;TT3;TT4;TT5;TT6;TT7;TT8;TT9;TT10;TT11;TT12;TT13;TT14;TT15;TT16;TT17;TT18;TT19;TT20;TT21;TT22;TR;>;
    MethodParameters:
      Name                           Flags
      parser                         final
      f                              final

  public org.sireum.Json$Fun$();
    descriptor: ()V
    flags: (0x0001) ACC_PUBLIC
    Code:
      stack=1, locals=1, args_size=1
         0: aload_0
         1: invokespecial #422                // Method java/lang/Object."<init>":()V
         4: return
      LineNumberTable:
        line 2411: 0
      LocalVariableTable:
        Start  Length  Slot  Name   Signature
            0       5     0  this   Lorg/sireum/Json$Fun$;
}
InnerClasses:
  public static #8= #2 of #7;             // Fun$=class org/sireum/Json$Fun$ of class org/sireum/Json
  public static final #11= #10 of #7;     // Parser=class org/sireum/Json$Parser of class org/sireum/Json
SourceFile: "Json.scala"
  ScalaInlineInfo: length = 0x1D5 (unknown attribute)
   01 01 00 5D 00 10 00 0F 01 00 2D 00 23 01 00 3E
   00 37 01 00 D7 00 D0 01 00 E8 00 E1 01 00 F9 00
   F2 01 01 0A 01 03 01 01 1B 01 14 01 01 2C 01 25
   01 01 3D 01 36 01 01 4E 01 47 01 01 5F 01 58 01
   01 70 01 69 01 00 4F 00 48 01 01 81 01 7A 01 01
   92 01 8B 01 01 A3 01 9C 01 00 60 00 59 01 00 71
   00 6A 01 00 82 00 7B 01 00 93 00 8C 01 00 A4 00
   9D 01 00 B5 00 AE 01 00 C6 00 BF 01 00 22 00 23
   01 00 36 00 37 01 00 CF 00 D0 01 00 E0 00 E1 01
   00 F1 00 F2 01 01 02 01 03 01 01 13 01 14 01 01
   24 01 25 01 01 35 01 36 01 01 46 01 47 01 01 57
   01 58 01 01 68 01 69 01 00 47 00 48 01 01 79 01
   7A 01 01 8A 01 8B 01 01 9B 01 9C 01 00 58 00 59
   01 00 69 00 6A 01 00 7A 00 7B 01 00 8B 00 8C 01
   00 9C 00 9D 01 00 AD 00 AE 01 00 BE 00 BF 01 00
   2A 00 16 01 00 3B 00 31 01 00 D4 00 CA 01 00 E5
   00 DB 01 00 F6 00 EC 01 01 07 00 FD 01 01 18 01
   0E 01 01 29 01 1F 01 01 3A 01 30 01 01 4B 01 41
   01 01 5C 01 52 01 01 6D 01 63 01 00 4C 00 42 01
   01 7E 01 74 01 01 8F 01 85 01 01 A0 01 96 01 00
   5D 00 53 01 00 6E 00 64 01 00 7F 00 75 01 00 90
   00 86 01 00 A1 00 97 01 00 B2 00 A8 01 00 C3 00
   B9 01 00 15 00 16 01 00 30 00 31 01 00 C9 00 CA
   01 00 DA 00 DB 01 00 EB 00 EC 01 00 FC 00 FD 01
   01 0D 01 0E 01 01 1E 01 1F 01 01 2F 01 30 01 01
   40 01 41 01 01 51 01 52 01 01 62 01 63 01 00 41
   00 42 01 01 73 01 74 01 01 84 01 85 01 01 95 01
   96 01 00 52 00 53 01 00 63 00 64 01 00 74 00 75
   01 00 85 00 86 01 00 96 00 97 01 00 A7 00 A8 01
   00 B8 00 B9 01
  Scala: length = 0x0 (unknown attribute)

