Classfile /Users/mw/Projects/slang-braindump/.jar/jar8/assemble/slang-braindump/assemble/content/org/sireum/justification$natded$.class
  Last modified May 29, 2022; size 632 bytes
  SHA-256 checksum bd8c588c8874e97a89c929f044b061b150e44d2c033f633563473751d2adeac2
  Compiled from "justification.scala"
public class org.sireum.justification$natded$
  minor version: 0
  major version: 52
  flags: (0x0021) ACC_PUBLIC, ACC_SUPER
  this_class: #2                          // org/sireum/justification$natded$
  super_class: #4                         // java/lang/Object
  interfaces: 0, fields: 1, methods: 2, attributes: 4
Constant pool:
   #1 = Utf8               org/sireum/justification$natded$
   #2 = Class              #1             // org/sireum/justification$natded$
   #3 = Utf8               java/lang/Object
   #4 = Class              #3             // java/lang/Object
   #5 = Utf8               justification.scala
   #6 = Utf8               org/sireum/justification
   #7 = Class              #6             // org/sireum/justification
   #8 = Utf8               natded$
   #9 = Utf8               org/sireum/justification$natded$pred$
  #10 = Class              #9             // org/sireum/justification$natded$pred$
  #11 = Utf8               pred$
  #12 = Utf8               org/sireum/justification$natded$prop$
  #13 = Class              #12            // org/sireum/justification$natded$prop$
  #14 = Utf8               prop$
  #15 = Utf8               MODULE$
  #16 = Utf8               Lorg/sireum/justification$natded$;
  #17 = Utf8               <clinit>
  #18 = Utf8               ()V
  #19 = Utf8               <init>
  #20 = NameAndType        #19:#18        // "<init>":()V
  #21 = Methodref          #2.#20         // org/sireum/justification$natded$."<init>":()V
  #22 = NameAndType        #15:#16        // MODULE$:Lorg/sireum/justification$natded$;
  #23 = Fieldref           #2.#22         // org/sireum/justification$natded$.MODULE$:Lorg/sireum/justification$natded$;
  #24 = Methodref          #4.#20         // java/lang/Object."<init>":()V
  #25 = Utf8               this
  #26 = Utf8               Code
  #27 = Utf8               LineNumberTable
  #28 = Utf8               LocalVariableTable
  #29 = Utf8               InnerClasses
  #30 = Utf8               SourceFile
  #31 = Utf8               ScalaInlineInfo
  #32 = Utf8               Scala
{
  public static final org.sireum.justification$natded$ MODULE$;
    descriptor: Lorg/sireum/justification$natded$;
    flags: (0x0019) ACC_PUBLIC, ACC_STATIC, ACC_FINAL

  public static {};
    descriptor: ()V
    flags: (0x0009) ACC_PUBLIC, ACC_STATIC
    Code:
      stack=2, locals=0, args_size=0
         0: new           #2                  // class org/sireum/justification$natded$
         3: dup
         4: invokespecial #21                 // Method "<init>":()V
         7: putstatic     #23                 // Field MODULE$:Lorg/sireum/justification$natded$;
        10: return
      LineNumberTable:
        line 36: 0

  public org.sireum.justification$natded$();
    descriptor: ()V
    flags: (0x0001) ACC_PUBLIC
    Code:
      stack=1, locals=1, args_size=1
         0: aload_0
         1: invokespecial #24                 // Method java/lang/Object."<init>":()V
         4: return
      LineNumberTable:
        line 36: 0
      LocalVariableTable:
        Start  Length  Slot  Name   Signature
            0       5     0  this   Lorg/sireum/justification$natded$;
}
InnerClasses:
  public static #8= #2 of #7;             // natded$=class org/sireum/justification$natded$ of class org/sireum/justification
  public static #11= #10 of #2;           // pred$=class org/sireum/justification$natded$pred$ of class org/sireum/justification$natded$
  public static #14= #13 of #2;           // prop$=class org/sireum/justification$natded$prop$ of class org/sireum/justification$natded$
SourceFile: "justification.scala"
  ScalaInlineInfo: length = 0x9 (unknown attribute)
   01 01 00 01 00 13 00 12 01
  Scala: length = 0x0 (unknown attribute)

