Classfile /Users/mw/Projects/slang-braindump/.jar/jar8/assemble/slang-braindump/assemble/content/org/sireum/MBox17.class
  Last modified May 29, 2022; size 27008 bytes
  SHA-256 checksum 9352b1239833119069483843cf8ffcccffcc64f35184a7bd8563a34d0bc6a00a
  Compiled from "MBox.scala"
public final class org.sireum.MBox17<T1 extends java.lang.Object, T2 extends java.lang.Object, T3 extends java.lang.Object, T4 extends java.lang.Object, T5 extends java.lang.Object, T6 extends java.lang.Object, T7 extends java.lang.Object, T8 extends java.lang.Object, T9 extends java.lang.Object, T10 extends java.lang.Object, T11 extends java.lang.Object, T12 extends java.lang.Object, T13 extends java.lang.Object, T14 extends java.lang.Object, T15 extends java.lang.Object, T16 extends java.lang.Object, T17 extends java.lang.Object> extends java.lang.Object implements org.sireum.RecordSig
  minor version: 0
  major version: 52
  flags: (0x0031) ACC_PUBLIC, ACC_FINAL, ACC_SUPER
  this_class: #2                          // org/sireum/MBox17
  super_class: #5                         // java/lang/Object
  interfaces: 1, fields: 18, methods: 105, attributes: 5
Constant pool:
    #1 = Utf8               org/sireum/MBox17
    #2 = Class              #1            // org/sireum/MBox17
    #3 = Utf8               <T1:Ljava/lang/Object;T2:Ljava/lang/Object;T3:Ljava/lang/Object;T4:Ljava/lang/Object;T5:Ljava/lang/Object;T6:Ljava/lang/Object;T7:Ljava/lang/Object;T8:Ljava/lang/Object;T9:Ljava/lang/Object;T10:Ljava/lang/Object;T11:Ljava/lang/Object;T12:Ljava/lang/Object;T13:Ljava/lang/Object;T14:Ljava/lang/Object;T15:Ljava/lang/Object;T16:Ljava/lang/Object;T17:Ljava/lang/Object;>Ljava/lang/Object;Lorg/sireum/RecordSig;
    #4 = Utf8               java/lang/Object
    #5 = Class              #4            // java/lang/Object
    #6 = Utf8               org/sireum/RecordSig
    #7 = Class              #6            // org/sireum/RecordSig
    #8 = Utf8               MBox.scala
    #9 = Utf8               Lscala/reflect/ScalaSignature;
   #10 = Utf8               bytes
   #11 = Utf8               \u0006\u0005\u0015Mq\u0001CA\u0006\u0003\u001bA\t!a\u0006\u0007\u0011\u0005m\u0011Q\u0002E\u0001\u0003;Aq!a\u000b\u0002\t\u0003\ti\u0003C\u0004\u00020\u0005!\t!!\r\t\u000f\u0011e\u0016\u0001\"\u0001\u0005<\u001a9\u00111DA\u0007\u0005\u0005]\u0002BCA!\u000b\t\u0005\t\u0015!\u0003\u0002D!Q\u0011\u0011L\u0003\u0003\u0002\u0003\u0006I!a\u0017\t\u0015\u0005\u0005TA!A!\u0002\u0013\t\u0019\u0007\u0003\u0006\u0002j\u0015\u0011\t\u0011)A\u0005\u0003WB!\"!\u001d\u0006\u0005\u0003\u0005\u000b\u0011BA:\u0011)\tI(\u0002B\u0001B\u0003%\u00111\u0010\u0005\u000b\u0003\u0003+!\u0011!Q\u0001\n\u0005\r\u0005BCAE\u000b\t\u0005\t\u0015!\u0003\u0002\f\"Q\u0011\u0011S\u0003\u0003\u0002\u0003\u0006I!a%\t\u0015\u0005eUA!A!\u0002\u0013\tY\n\u0003\u0006\u0002\"\u0016\u0011\t\u0011)A\u0005\u0003GC!\"!+\u0006\u0005\u0003\u0005\u000b\u0011BAV\u0011)\t\t,\u0002B\u0001B\u0003%\u00111\u0017\u0005\u000b\u0003s+!\u0011!Q\u0001\n\u0005m\u0006BCAa\u000b\t\u0005\t\u0015!\u0003\u0002D\"Q\u0011\u0011Z\u0003\u0003\u0002\u0003\u0006I!a3\t\u0015\u0005EWA!A!\u0002\u0013\t\u0019\u000eC\u0004\u0002,\u0015!\t!!7\t\u0011\u0005}X\u0001)Q\u0005\u0003\u0007BqA!\u0001\u0006\t\u0003\u0011\u0019\u0001C\u0004\u0003\u0006\u0015!\tAa\u0001\t\u000f\t\u001dQ\u0001\"\u0001\u0003\n!9!qB\u0003\u0005\u0002\tE\u0001\u0002\u0003B\u000b\u000b\u0001\u0006K!a\u0017\t\u000f\t]Q\u0001\"\u0001\u0003\u001a!9!1D\u0003\u0005\u0002\te\u0001b\u0002B\u000f\u000b\u0011\u0005!q\u0004\u0005\b\u0005G)A\u0011\u0001B\u0013\u0011!\u0011I#\u0002Q!\n\u0005\r\u0004b\u0002B\u0016\u000b\u0011\u0005!Q\u0006\u0005\b\u0005_)A\u0011\u0001B\u0017\u0011\u001d\u0011\t$\u0002C\u0001\u0005gAqAa\u000e\u0006\t\u0003\u0011I\u0004\u0003\u0005\u0003>\u0015\u0001\u000b\u0015BA6\u0011\u001d\u0011y$\u0002C\u0001\u0005\u0003BqAa\u0011\u0006\t\u0003\u0011\t\u0005C\u0004\u0003F\u0015!\tAa\u0012\t\u000f\t-S\u0001\"\u0001\u0003N!A!\u0011K\u0003!B\u0013\t\u0019\bC\u0004\u0003T\u0015!\tA!\u0016\t\u000f\t]S\u0001\"\u0001\u0003V!9!\u0011L\u0003\u0005\u0002\tm\u0003b\u0002B0\u000b\u0011\u0005!\u0011\r\u0005\t\u0005K*\u0001\u0015)\u0003\u0002|!9!qM\u0003\u0005\u0002\t%\u0004b\u0002B6\u000b\u0011\u0005!\u0011\u000e\u0005\b\u0005[*A\u0011\u0001B8\u0011\u001d\u0011\u0019(\u0002C\u0001\u0005kB\u0001B!\u001f\u0006A\u0003&\u00111\u0011\u0005\b\u0005w*A\u0011\u0001B?\u0011\u001d\u0011y(\u0002C\u0001\u0005{BqA!!\u0006\t\u0003\u0011\u0019\tC\u0004\u0003\b\u0016!\tA!#\t\u0011\t5U\u0001)Q\u0005\u0003\u0017CqAa$\u0006\t\u0003\u0011\t\nC\u0004\u0003\u0014\u0016!\tA!%\t\u000f\tUU\u0001\"\u0001\u0003\u0018\"9!1T\u0003\u0005\u0002\tu\u0005\u0002\u0003BQ\u000b\u0001\u0006K!a%\t\u000f\t\rV\u0001\"\u0001\u0003&\"9!qU\u0003\u0005\u0002\t\u0015\u0006b\u0002BU\u000b\u0011\u0005!1\u0016\u0005\b\u0005_+A\u0011\u0001BY\u0011!\u0011),\u0002Q!\n\u0005m\u0005b\u0002B\\\u000b\u0011\u0005!\u0011\u0018\u0005\b\u0005w+A\u0011\u0001B]\u0011\u001d\u0011i,\u0002C\u0001\u0005\u007fCqAa1\u0006\t\u0003\u0011)\r\u0003\u0005\u0003J\u0016\u0001\u000b\u0015BAR\u0011\u001d\u0011Y-\u0002C\u0001\u0005\u001bDqAa4\u0006\t\u0003\u0011i\rC\u0004\u0003R\u0016!\tAa5\t\u000f\t]W\u0001\"\u0001\u0003Z\"A!Q\\\u0003!B\u0013\tY\u000bC\u0004\u0003`\u0016!\tA!9\t\u000f\t\rX\u0001\"\u0001\u0003b\"9!Q]\u0003\u0005\u0002\t\u001d\bb\u0002Bv\u000b\u0011\u0005!Q\u001e\u0005\t\u0005c,\u0001\u0015)\u0003\u00024\"9!1_\u0003\u0005\u0002\tU\bb\u0002B|\u000b\u0011\u0005!Q\u001f\u0005\b\u0005s,A\u0011\u0001B~\u0011\u001d\u0011y0\u0002C\u0001\u0007\u0003A\u0001b!\u0002\u0006A\u0003&\u00111\u0018\u0005\b\u0007\u000f)A\u0011AB\u0005\u0011\u001d\u0019Y!\u0002C\u0001\u0007\u0013Aqa!\u0004\u0006\t\u0003\u0019y\u0001C\u0004\u0004\u0014\u0015!\ta!\u0006\t\u0011\reQ\u0001)Q\u0005\u0003\u0007Dqaa\u0007\u0006\t\u0003\u0019i\u0002C\u0004\u0004 \u0015!\ta!\b\t\u000f\r\u0005R\u0001\"\u0001\u0004$!91qE\u0003\u0005\u0002\r%\u0002\u0002CB\u0017\u000b\u0001\u0006K!a3\t\u000f\r=R\u0001\"\u0001\u00042!911G\u0003\u0005\u0002\rE\u0002bBB\u001b\u000b\u0011\u00051q\u0007\u0005\b\u0007w)A\u0011AB\u001f\u0011!\u0019\t%\u0002Q!\n\u0005M\u0007bBB\"\u000b\u0011\u00051Q\t\u0005\b\u0007\u000f*A\u0011AB#\u0011\u001d\u0019I%\u0002C\u0001\u0007\u0017Bqaa\u0014\u0006\t\u0003\u0019\t\u0006C\u0004\u0004V\u0015!\tea\u0016\t\u000f\r%T\u0001\"\u0011\u0004l!91\u0011O\u0003\u0005B\rM\u0004bBB>\u000b\u0011\u00053Q\u0010\u0005\b\u0003_)A\u0011ABE\u0011%\u0019i+BI\u0001\n\u0003\u0019y\u000bC\u0005\u0004F\u0016\t\n\u0011\"\u0001\u0004H\"I11Z\u0003\u0012\u0002\u0013\u00051Q\u001a\u0005\n\u0007#,\u0011\u0013!C\u0001\u0007\'D\u0011ba6\u0006#\u0003%\ta!7\t\u0013\ruW!%A\u0005\u0002\r}\u0007\"CBr\u000bE\u0005I\u0011ABs\u0011%\u0019I/BI\u0001\n\u0003\u0019Y\u000fC\u0005\u0004p\u0016\t\n\u0011\"\u0001\u0004r\"I1Q_\u0003\u0012\u0002\u0013\u00051q\u001f\u0005\n\u0007w,\u0011\u0013!C\u0001\u0007{D\u0011\u0002\"\u0001\u0006#\u0003%\t\u0001b\u0001\t\u0013\u0011\u001dQ!%A\u0005\u0002\u0011%\u0001\"\u0003C\u0007\u000bE\u0005I\u0011\u0001C\b\u0011%!\u0019\"BI\u0001\n\u0003!)\u0002C\u0005\u0005\u001a\u0015\t\n\u0011\"\u0001\u0005\u001c!IAqD\u0003\u0012\u0002\u0013\u0005A\u0011\u0005\u0005\b\tK)A\u0011\tC\u0014\u0011\u001d!9%\u0002C!\t\u0013\na!\u0014\"pqF:$\u0002BA\b\u0003#\taa]5sKVl\'BAA\n\u0003\ry\'oZ\u0002\u0001!\r\tI\"A\u0007\u0003\u0003\u001b\u0011a!\u0014\"pqF:4cA\u0001\u0002 A!\u0011\u0011EA\u0014\u001b\t\t\u0019C\u0003\u0002\u0002&\u0005)1oY1mC&!\u0011\u0011FA\u0012\u0005\u0019\te.\u001f*fM\u00061A(\u001b8jiz\"\"!a\u0006\u0002\u000b\u0005\u0004\b\u000f\\=\u0016I\u0005MBQ\u000bC-\t;\"\t\u0007\"\u001a\u0005j\u00115D\u0011\u000fC;\ts\"i\b\"!\u0005\u0006\u0012%EQ\u0012CI\t+#B%!\u000e\u0005\u0018\u0012eE1\u0014CO\t?#\t\u000bb)\u0005&\u0012\u001dF\u0011\u0016CV\t[#y\u000b\"-\u00054\u0012UFq\u0017\t&\u00033)A1\u000bC,\t7\"y\u0006b\u0019\u0005h\u0011-Dq\u000eC:\to\"Y\bb \u0005\u0004\u0012\u001dE1\u0012CH\t\'+B%!\u000f\u0002H\u0005u\u0013QMA7\u0003k\ni(!\"\u0002\u000e\u0006U\u0015QTAS\u0003[\u000b),!0\u0002F\u00065\u0017Q[\n\u0006\u000b\u0005}\u00111\b\t\u0005\u00033\ti$\u0003\u0003\u0002@\u00055!!\u0003*fG>\u0014HmU5h\u0003!yvL^1mk\u0016\f\u0004\u0003BA#\u0003\u000fb\u0001\u0001B\u0004\u0002J\u0015\u0011\r!a\u0013\u0003\u0005Q\u000b\u0014\u0003BA\'\u0003\'\u0002B!!\t\u0002P%!\u0011\u0011KA\u0012\u0005\u001dqu\u000e\u001e5j]\u001e\u0004B!!\t\u0002V%!\u0011qKA\u0012\u0005\r\te._\u0001\t?~3\u0018\r\\;feA!\u0011QIA/\t\u001d\ty&\u0002b\u0001\u0003\u0017\u0012!\u0001\u0016\u001a\u0002\u0011}{f/\u00197vKN\u0002B!!\u0012\u0002f\u00119\u0011qM\u0003C\u0002\u0005-#A\u0001+4\u0003!yvL^1mk\u0016$\u0004\u0003BA#\u0003[\"q!a\u001c\u0006\u0005\u0004\tYE\u0001\u0002Ui\u0005Aql\u0018<bYV,W\u0007\u0005\u0003\u0002F\u0005UDaBA<\u000b\t\u0007\u00111\n\u0002\u0003)V\n\u0001bX0wC2,XM\u000e\t\u0005\u0003\u000b\ni\bB\u0004\u0002\u0000\u0015\u0011\r!a\u0013\u0003\u0005Q3\u0014\u0001C0`m\u0006dW/Z\u001c\u0011\t\u0005\u0015\u0013Q\u0011\u0003\b\u0003\u000f+!\u0019AA&\u0005\t!v\'\u0001\u0005`?Z\fG.^39!\u0011\t)%!$\u0005\u000f\u0005=UA1\u0001\u0002L\t\u0011A\u000bO\u0001\t?~3\u0018\r\\;fsA!\u0011QIAK\t\u001d\t9*\u0002b\u0001\u0003\u0017\u0012!\u0001V\u001d\u0002\u0013}{f/\u00197vKF\u0002\u0004\u0003BA#\u0003;#q!a(\u0006\u0005\u0004\tYEA\u0002UcA\n\u0011bX0wC2,X-M\u0019\u0011\t\u0005\u0015\u0013Q\u0015\u0003\b\u0003O+!\u0019AA&\u0005\r!\u0016\'M\u0001\n?~3\u0018\r\\;fcI\u0002B!!\u0012\u0002.\u00129\u0011qV\u0003C\u0002\u0005-#a\u0001+2e\u0005Iql\u0018<bYV,\u0017g\r\t\u0005\u0003\u000b\n)\fB\u0004\u00028\u0016\u0011\r!a\u0013\u0003\u0007Q\u000b4\'A\u0005`?Z\fG.^32iA!\u0011QIA_\t\u001d\ty,\u0002b\u0001\u0003\u0017\u00121\u0001V\u00195\u0003%yvL^1mk\u0016\fT\u0007\u0005\u0003\u0002F\u0005\u0015GaBAd\u000b\t\u0007\u00111\n\u0002\u0004)F*\u0014!C0`m\u0006dW/Z\u00197!\u0011\t)%!4\u0005\u000f\u0005=WA1\u0001\u0002L\t\u0019A+\r\u001c\u0002\u0013}{f/\u00197vKF:\u0004\u0003BA#\u0003+$q!a6\u0006\u0005\u0004\tYEA\u0002Uc]\"B%a7\u0002^\u0006}\u0017\u0011]Ar\u0003K\f9/!;\u0002l\u00065\u0018q^Ay\u0003g\f)0a>\u0002z\u0006m\u0018Q \t&\u00033)\u00111IA.\u0003G\nY\'a\u001d\u0002|\u0005\r\u00151RAJ\u00037\u000b\u0019+a+\u00024\u0006m\u00161YAf\u0003\'Dq!!\u0011\u0018\u0001\u0004\t\u0019\u0005C\u0004\u0002Z]\u0001\r!a\u0017\t\u000f\u0005\u0005t\u00031\u0001\u0002d!9\u0011\u0011N\fA\u0002\u0005-\u0004bBA9/\u0001\u0007\u00111\u000f\u0005\b\u0003s:\u0002\u0019AA>\u0011\u001d\t\ti\u0006a\u0001\u0003\u0007Cq!!#\u0018\u0001\u0004\tY\tC\u0004\u0002\u0012^\u0001\r!a%\t\u000f\u0005eu\u00031\u0001\u0002\u001c\"9\u0011\u0011U\fA\u0002\u0005\r\u0006bBAU/\u0001\u0007\u00111\u0016\u0005\b\u0003c;\u0002\u0019AAZ\u0011\u001d\tIl\u0006a\u0001\u0003wCq!!1\u0018\u0001\u0004\t\u0019\rC\u0004\u0002J^\u0001\r!a3\t\u000f\u0005Ew\u00031\u0001\u0002T\u00069qL^1mk\u0016\f\u0014A\u0002<bYV,\u0017\'\u0006\u0002\u0002D\u0005Iq-\u001a;WC2,X-M\u0001\u000bm\u0006dW/Z\u0019`I\u0015\fH\u0003\u0002B\u0006\u0005\u001bi\u0011!\u0002\u0005\b\u0005\u0003Y\u0002\u0019AA\"\u0003%\u0019X\r\u001e,bYV,\u0017\u0007\u0006\u0003\u0003\f\tM\u0001b\u0002B\u00019\u0001\u0007\u00111I\u0001\b?Z\fG.^33\u0003\u00191\u0018\r\\;feU\u0011\u00111L\u0001\nO\u0016$h+\u00197vKJ\n!B^1mk\u0016\u0014t\fJ3r)\u0011\u0011YA!\t\t\u000f\t]\u0001\u00051\u0001\u0002\\\u0005I1/\u001a;WC2,XM\r\u000b\u0005\u0005\u0017\u00119\u0003C\u0004\u0003\u0018\u0005\u0002\r!a\u0017\u0002\u000f}3\u0018\r\\;fg\u00051a/\u00197vKN*\"!a\u0019\u0002\u0013\u001d,GOV1mk\u0016\u001c\u0014A\u0003<bYV,7g\u0018\u0013fcR!!1\u0002B\u001b\u0011\u001d\u0011Y#\na\u0001\u0003G\n\u0011b]3u-\u0006dW/Z\u001a\u0015\t\t-!1\b\u0005\b\u0005W1\u0003\u0019AA2\u0003\u001dyf/\u00197vKR\naA^1mk\u0016$TCAA6\u0003%9W\r\u001e,bYV,G\'\u0001\u0006wC2,X\rN0%KF$BAa\u0003\u0003J!9!q\b\u0016A\u0002\u0005-\u0014!C:fiZ\u000bG.^35)\u0011\u0011YAa\u0014\t\u000f\t}2\u00061\u0001\u0002l\u00059qL^1mk\u0016,\u0014A\u0002<bYV,W\'\u0006\u0002\u0002t\u0005Iq-\u001a;WC2,X-N\u0001\u000bm\u0006dW/Z\u001b`I\u0015\fH\u0003\u0002B\u0006\u0005;BqAa\u00150\u0001\u0004\t\u0019(A\u0005tKR4\u0016\r\\;fkQ!!1\u0002B2\u0011\u001d\u0011\u0019\u0006\ra\u0001\u0003g\nqa\u0018<bYV,g\'\u0001\u0004wC2,XMN\u000b\u0003\u0003w\n\u0011bZ3u-\u0006dW/\u001a\u001c\u0002\u0015Y\fG.^37?\u0012*\u0017\u000f\u0006\u0003\u0003\f\tE\u0004b\u0002B4i\u0001\u0007\u00111P\u0001\ng\u0016$h+\u00197vKZ\"BAa\u0003\u0003x!9!qM\u001bA\u0002\u0005m\u0014aB0wC2,XmN\u0001\u0007m\u0006dW/Z\u001c\u0016\u0005\u0005\r\u0015!C4fiZ\u000bG.^38\u0003)1\u0018\r\\;fo}#S-\u001d\u000b\u0005\u0005\u0017\u0011)\tC\u0004\u0003|e\u0002\r!a!\u0002\u0013M,GOV1mk\u0016<D\u0003\u0002B\u0006\u0005\u0017CqAa\u001f;\u0001\u0004\t\u0019)A\u0004`m\u0006dW/\u001a\u001d\u0002\rY\fG.^39+\t\tY)A\u0005hKR4\u0016\r\\;fq\u0005Qa/\u00197vKbzF%Z9\u0015\t\t-!\u0011\u0014\u0005\b\u0005\u001fs\u0004\u0019AAF\u0003%\u0019X\r\u001e,bYV,\u0007\b\u0006\u0003\u0003\f\t}\u0005b\u0002BH\u007f\u0001\u0007\u00111R\u0001\b?Z\fG.^3:\u0003\u00191\u0018\r\\;fsU\u0011\u00111S\u0001\nO\u0016$h+\u00197vKf\n!B^1mk\u0016Lt\fJ3r)\u0011\u0011YA!,\t\u000f\t\r6\t1\u0001\u0002\u0014\u0006I1/\u001a;WC2,X-\u000f\u000b\u0005\u0005\u0017\u0011\u0019\fC\u0004\u0003$\u0012\u0003\r!a%\u0002\u0011}3\u0018\r\\;fcA\nqA^1mk\u0016\f\u0004\'\u0006\u0002\u0002\u001c\u0006Qq-\u001a;WC2,X-\r\u0019\u0002\u0017Y\fG.^32a}#S-\u001d\u000b\u0005\u0005\u0017\u0011\t\rC\u0004\u00038\"\u0003\r!a\'\u0002\u0015M,GOV1mk\u0016\f\u0004\u0007\u0006\u0003\u0003\f\t\u001d\u0007b\u0002B\\\u0013\u0002\u0007\u00111T\u0001\t?Z\fG.^32c\u00059a/\u00197vKF\nTCAAR\u0003)9W\r\u001e,bYV,\u0017\'M\u0001\fm\u0006dW/Z\u00192?\u0012*\u0017\u000f\u0006\u0003\u0003\f\tU\u0007b\u0002Bf\u001b\u0002\u0007\u00111U\u0001\u000bg\u0016$h+\u00197vKF\nD\u0003\u0002B\u0006\u00057DqAa3O\u0001\u0004\t\u0019+\u0001\u0005`m\u0006dW/Z\u00193\u0003\u001d1\u0018\r\\;fcI*\"!a+\u0002\u0015\u001d,GOV1mk\u0016\f$\'A\u0006wC2,X-\r\u001a`I\u0015\fH\u0003\u0002B\u0006\u0005SDqAa8S\u0001\u0004\tY+\u0001\u0006tKR4\u0016\r\\;fcI\"BAa\u0003\u0003p\"9!q\\*A\u0002\u0005-\u0016\u0001C0wC2,X-M\u001a\u0002\u000fY\fG.^32gU\u0011\u00111W\u0001\u000bO\u0016$h+\u00197vKF\u001a\u0014a\u0003<bYV,\u0017gM0%KF$BAa\u0003\u0003~\"9!1_,A\u0002\u0005M\u0016AC:fiZ\u000bG.^32gQ!!1BB\u0002\u0011\u001d\u0011\u0019\u0010\u0017a\u0001\u0003g\u000b\u0001b\u0018<bYV,\u0017\u0007N\u0001\bm\u0006dW/Z\u00195+\t\tY,\u0001\u0006hKR4\u0016\r\\;fcQ\n1B^1mk\u0016\fDg\u0018\u0013fcR!!1BB\t\u0011\u001d\u00199\u0001\u0018a\u0001\u0003w\u000b!b]3u-\u0006dW/Z\u00195)\u0011\u0011Yaa\u0006\t\u000f\r\u001dQ\f1\u0001\u0002<\u0006AqL^1mk\u0016\fT\'A\u0004wC2,X-M\u001b\u0016\u0005\u0005\r\u0017AC4fiZ\u000bG.^32k\u0005Ya/\u00197vKF*t\fJ3r)\u0011\u0011Ya!\n\t\u000f\rm\u0011\r1\u0001\u0002D\u0006Q1/\u001a;WC2,X-M\u001b\u0015\t\t-11\u0006\u0005\b\u00077\u0011\u0007\u0019AAb\u0003!yf/\u00197vKF2\u0014a\u0002<bYV,\u0017GN\u000b\u0003\u0003\u0017\f!bZ3u-\u0006dW/Z\u00197\u0003-1\u0018\r\\;fcYzF%Z9\u0015\t\t-1\u0011\b\u0005\b\u0007_1\u0007\u0019AAf\u0003)\u0019X\r\u001e,bYV,\u0017G\u000e\u000b\u0005\u0005\u0017\u0019y\u0004C\u0004\u00040\u001d\u0004\r!a3\u0002\u0011}3\u0018\r\\;fc]\nqA^1mk\u0016\ft\'\u0006\u0002\u0002T\u0006Qq-\u001a;WC2,X-M\u001c\u0002\u0017Y\fG.^32o}#S-\u001d\u000b\u0005\u0005\u0017\u0019i\u0005C\u0004\u0004D-\u0004\r!a5\u0002\u0015M,GOV1mk\u0016\ft\u0007\u0006\u0003\u0003\f\rM\u0003bBB\"Y\u0002\u0007\u00111[\u0001\ti>\u001cFO]5oOR\u00111\u0011\f\t\u0005\u00077\u001a)\'\u0004\u0002\u0004^)!1qLB1\u0003\u0011a\u0017M\\4\u000b\u0005\r\r\u0014\u0001\u00026bm\u0006LAaa\u001a\u0004^\t11\u000b\u001e:j]\u001e\faa\u001d;sS:<WCAB7!\u0011\tIba\u001c\n\t\r\u001d\u0014QB\u0001\tQ\u0006\u001c\bnQ8eKR\u00111Q\u000f\t\u0005\u0003C\u00199(\u0003\u0003\u0004z\u0005\r\"aA%oi\u00061Q-];bYN$Baa \u0004\u0006B!\u0011\u0011EBA\u0013\u0011\u0019\u0019)a\t\u0003\u000f\t{w\u000e\\3b]\"91q\u00119A\u0002\u0005M\u0013!A8\u0015I\u0005m71RBG\u0007\u001f\u001b\tja%\u0004\u0016\u000e]5\u0011TBN\u0007;\u001byj!)\u0004$\u000e\u00156qUBU\u0007WC\u0011B!\u0001r!\u0003\u0005\r!a\u0011\t\u0013\t]\u0011\u000f%AA\u0002\u0005m\u0003\"\u0003B\u0016cB\u0005\t\u0019AA2\u0011%\u0011y$\u001dI\u0001\u0002\u0004\tY\u0007C\u0005\u0003TE\u0004\n\u00111\u0001\u0002t!I!qM9\u0011\u0002\u0003\u0007\u00111\u0010\u0005\n\u0005w\n\b\u0013!a\u0001\u0003\u0007C\u0011Ba$r!\u0003\u0005\r!a#\t\u0013\t\r\u0016\u000f%AA\u0002\u0005M\u0005\"\u0003B\\cB\u0005\t\u0019AAN\u0011%\u0011Y-\u001dI\u0001\u0002\u0004\t\u0019\u000bC\u0005\u0003`F\u0004\n\u00111\u0001\u0002,\"I!1_9\u0011\u0002\u0003\u0007\u00111\u0017\u0005\n\u0007\u000f\t\b\u0013!a\u0001\u0003wC\u0011ba\u0007r!\u0003\u0005\r!a1\t\u0013\r=\u0012\u000f%AA\u0002\u0005-\u0007\"CB\"cB\u0005\t\u0019AAj\u0003=\t\u0007\u000f\u001d7zI\u0011,g-Y;mi\u0012\nTCABYU\u0011\t\u0019ea-,\u0005\rU\u0006\u0003BB\\\u0007\u0003l!a!/\u000b\t\rm6QX\u0001\nk:\u001c\u0007.Z2lK\u0012TAaa0\u0002$\u0005Q\u0011M\u001c8pi\u0006$\u0018n\u001c8\n\t\r\r7\u0011\u0018\u0002\u0012k:\u001c\u0007.Z2lK\u00124\u0016M]5b]\u000e,\u0017aD1qa2LH\u0005Z3gCVdG\u000f\n\u001a\u0016\u0005\r%\'\u0006BA.\u0007g\u000bq\"\u00199qYf$C-\u001a4bk2$HeM\u000b\u0003\u0007\u001fTC!a\u0019\u00044\u0006y\u0011\r\u001d9ms\u0012\"WMZ1vYR$C\'\u0006\u0002\u0004V*\"\u00111NBZ\u0003=\t\u0007\u000f\u001d7zI\u0011,g-Y;mi\u0012*TCABnU\u0011\t\u0019ha-\u0002\u001f\u0005\u0004\b\u000f\\=%I\u00164\u0017-\u001e7uIY*\"a!9+\t\u0005m41W\u0001\u0010CB\u0004H.\u001f\u0013eK\u001a\fW\u000f\u001c;%oU\u00111q\u001d\u0016\u0005\u0003\u0007\u001b\u0019,A\bbaBd\u0017\u0010\n3fM\u0006,H\u000e\u001e\u00139+\t\u0019iO\u000b\u0003\u0002\f\u000eM\u0016aD1qa2LH\u0005Z3gCVdG\u000fJ\u001d\u0016\u0005\rM(\u0006BAJ\u0007g\u000b\u0001#\u00199qYf$C-\u001a4bk2$H%\r\u0019\u0016\u0005\re(\u0006BAN\u0007g\u000b\u0001#\u00199qYf$C-\u001a4bk2$H%M\u0019\u0016\u0005\r}(\u0006BAR\u0007g\u000b\u0001#\u00199qYf$C-\u001a4bk2$H%\r\u001a\u0016\u0005\u0011\u0015!\u0006BAV\u0007g\u000b\u0001#\u00199qYf$C-\u001a4bk2$H%M\u001a\u0016\u0005\u0011-!\u0006BAZ\u0007g\u000b\u0001#\u00199qYf$C-\u001a4bk2$H%\r\u001b\u0016\u0005\u0011E!\u0006BA^\u0007g\u000b\u0001#\u00199qYf$C-\u001a4bk2$H%M\u001b\u0016\u0005\u0011]!\u0006BAb\u0007g\u000b\u0001#\u00199qYf$C-\u001a4bk2$H%\r\u001c\u0016\u0005\u0011u!\u0006BAf\u0007g\u000b\u0001#\u00199qYf$C-\u001a4bk2$H%M\u001c\u0016\u0005\u0011\r\"\u0006BAj\u0007g\u000b\u0001\u0002J2p]R,g\u000e^\u000b\u0003\tS\u0001b\u0001b\u000b\u0005<\u0011\u0005c\u0002\u0002C\u0017\toqA\u0001b\f\u000565\u0011A\u0011\u0007\u0006\u0005\tg\t)\"\u0001\u0004=e>|GOP\u0005\u0003\u0003KIA\u0001\"\u000f\u0002$\u00059\u0001/Y2lC\u001e,\u0017\u0002\u0002C\u001f\t\u007f\u00111aU3r\u0015\u0011!I$a\t\u0011\u0011\u0005\u0005B1IB-\u0003\'JA\u0001\"\u0012\u0002$\t1A+\u001e9mKJ\na\u0001J2m_:,WCAAnQ\r)AQ\n\t\u0005\u00033!y%\u0003\u0003\u0005R\u00055!A\u0002:fG>\u0014H\r\u0005\u0003\u0002F\u0011UCaBA%\u0007\t\u0007\u00111\n\t\u0005\u0003\u000b\"I\u0006B\u0004\u0002`\r\u0011\r!a\u0013\u0011\t\u0005\u0015CQ\f\u0003\b\u0003O\u001a!\u0019AA&!\u0011\t)\u0005\"\u0019\u0005\u000f\u0005=4A1\u0001\u0002LA!\u0011Q\tC3\t\u001d\t9h\u0001b\u0001\u0003\u0017\u0002B!!\u0012\u0005j\u00119\u0011qP\u0002C\u0002\u0005-\u0003\u0003BA#\t[\"q!a\"\u0004\u0005\u0004\tY\u0005\u0005\u0003\u0002F\u0011EDaBAH\u0007\t\u0007\u00111\n\t\u0005\u0003\u000b\")\bB\u0004\u0002\u0018\u000e\u0011\r!a\u0013\u0011\t\u0005\u0015C\u0011\u0010\u0003\b\u0003?\u001b!\u0019AA&!\u0011\t)\u0005\" \u0005\u000f\u0005\u001d6A1\u0001\u0002LA!\u0011Q\tCA\t\u001d\tyk\u0001b\u0001\u0003\u0017\u0002B!!\u0012\u0005\u0006\u00129\u0011qW\u0002C\u0002\u0005-\u0003\u0003BA#\t\u0013#q!a0\u0004\u0005\u0004\tY\u0005\u0005\u0003\u0002F\u00115EaBAd\u0007\t\u0007\u00111\n\t\u0005\u0003\u000b\"\t\nB\u0004\u0002P\u000e\u0011\r!a\u0013\u0011\t\u0005\u0015CQ\u0013\u0003\b\u0003/\u001c!\u0019AA&\u0011\u001d\u0011\ta\u0001a\u0001\t\'BqAa\u0006\u0004\u0001\u0004!9\u0006C\u0004\u0003,\r\u0001\r\u0001b\u0017\t\u000f\t}2\u00011\u0001\u0005`!9!1K\u0002A\u0002\u0011\r\u0004b\u0002B4\u0007\u0001\u0007Aq\r\u0005\b\u0005w\u001a\u0001\u0019\u0001C6\u0011\u001d\u0011yi\u0001a\u0001\t_BqAa)\u0004\u0001\u0004!\u0019\bC\u0004\u00038\u000e\u0001\r\u0001b\u001e\t\u000f\t-7\u00011\u0001\u0005|!9!q\\\u0002A\u0002\u0011}\u0004b\u0002Bz\u0007\u0001\u0007A1\u0011\u0005\b\u0007\u000f\u0019\u0001\u0019\u0001CD\u0011\u001d\u0019Yb\u0001a\u0001\t\u0017Cqaa\f\u0004\u0001\u0004!y\tC\u0004\u0004D\r\u0001\r\u0001b%\u0002\u000fUt\u0017\r\u001d9msV!CQ\u0018Cg\t#$)\u000e\"7\u0005^\u0012\u0005HQ\u001dCu\t[$\t\u0010\">\u0005z\u0012uX\u0011AC\u0003\u000b\u0013)i\u0001\u0006\u0003\u0005@\u0016=\u0001CBA\u0011\t\u0003$)-\u0003\u0003\u0005D\u0006\r\"\u0001B*p[\u0016\u0004b%!\t\u0005H\u0012-Gq\u001aCj\t/$Y\u000eb8\u0005d\u0012\u001dH1\u001eCx\tg$9\u0010b?\u0005\u0000\u0016\rQqAC\u0006\u0013\u0011!I-a\t\u0003\u000fQ+\b\u000f\\32oA!\u0011Q\tCg\t\u001d\tI\u0005\u0002b\u0001\u0003\u0017\u0002B!!\u0012\u0005R\u00129\u0011q\f\u0003C\u0002\u0005-\u0003\u0003BA#\t+$q!a\u001a\u0005\u0005\u0004\tY\u0005\u0005\u0003\u0002F\u0011eGaBA8\t\t\u0007\u00111\n\t\u0005\u0003\u000b\"i\u000eB\u0004\u0002x\u0011\u0011\r!a\u0013\u0011\t\u0005\u0015C\u0011\u001d\u0003\b\u0003\u007f\"!\u0019AA&!\u0011\t)\u0005\":\u0005\u000f\u0005\u001dEA1\u0001\u0002LA!\u0011Q\tCu\t\u001d\ty\t\u0002b\u0001\u0003\u0017\u0002B!!\u0012\u0005n\u00129\u0011q\u0013\u0003C\u0002\u0005-\u0003\u0003BA#\tc$q!a(\u0005\u0005\u0004\tY\u0005\u0005\u0003\u0002F\u0011UHaBAT\t\t\u0007\u00111\n\t\u0005\u0003\u000b\"I\u0010B\u0004\u00020\u0012\u0011\r!a\u0013\u0011\t\u0005\u0015CQ \u0003\b\u0003o#!\u0019AA&!\u0011\t)%\"\u0001\u0005\u000f\u0005}FA1\u0001\u0002LA!\u0011QIC\u0003\t\u001d\t9\r\u0002b\u0001\u0003\u0017\u0002B!!\u0012\u0006\n\u00119\u0011q\u001a\u0003C\u0002\u0005-\u0003\u0003BA#\u000b\u001b!q!a6\u0005\u0005\u0004\tY\u0005C\u0004\u0004\b\u0012\u0001\r!\"\u0005\u0011K\u0005eQ\u0001b3\u0005P\u0012MGq\u001bCn\t?$\u0019\u000fb:\u0005l\u0012=H1\u001fC|\tw$y0b\u0001\u0006\b\u0015-\u0001
   #12 = Utf8               _value1
   #13 = Utf8               Ljava/lang/Object;
   #14 = Utf8               TT1;
   #15 = Utf8               _value2
   #16 = Utf8               TT2;
   #17 = Utf8               _value3
   #18 = Utf8               TT3;
   #19 = Utf8               _value4
   #20 = Utf8               TT4;
   #21 = Utf8               _value5
   #22 = Utf8               TT5;
   #23 = Utf8               _value6
   #24 = Utf8               TT6;
   #25 = Utf8               _value7
   #26 = Utf8               TT7;
   #27 = Utf8               _value8
   #28 = Utf8               TT8;
   #29 = Utf8               _value9
   #30 = Utf8               TT9;
   #31 = Utf8               _value10
   #32 = Utf8               TT10;
   #33 = Utf8               _value11
   #34 = Utf8               TT11;
   #35 = Utf8               _value12
   #36 = Utf8               TT12;
   #37 = Utf8               _value13
   #38 = Utf8               TT13;
   #39 = Utf8               _value14
   #40 = Utf8               TT14;
   #41 = Utf8               _value15
   #42 = Utf8               TT15;
   #43 = Utf8               _value16
   #44 = Utf8               TT16;
   #45 = Utf8               _value17
   #46 = Utf8               TT17;
   #47 = Utf8               org$sireum$RecordSig$$$isOwned
   #48 = Utf8               Z
   #49 = Utf8               unapply
   #50 = Utf8               (Lorg/sireum/MBox17;)Lscala/Some;
   #51 = Utf8               <T1:Ljava/lang/Object;T2:Ljava/lang/Object;T3:Ljava/lang/Object;T4:Ljava/lang/Object;T5:Ljava/lang/Object;T6:Ljava/lang/Object;T7:Ljava/lang/Object;T8:Ljava/lang/Object;T9:Ljava/lang/Object;T10:Ljava/lang/Object;T11:Ljava/lang/Object;T12:Ljava/lang/Object;T13:Ljava/lang/Object;T14:Ljava/lang/Object;T15:Ljava/lang/Object;T16:Ljava/lang/Object;T17:Ljava/lang/Object;>(Lorg/sireum/MBox17<TT1;TT2;TT3;TT4;TT5;TT6;TT7;TT8;TT9;TT10;TT11;TT12;TT13;TT14;TT15;TT16;TT17;>;)Lscala/Some<Lscala/Tuple17<TT1;TT2;TT3;TT4;TT5;TT6;TT7;TT8;TT9;TT10;TT11;TT12;TT13;TT14;TT15;TT16;TT17;>;>;
   #52 = Utf8               o
   #53 = Utf8               org/sireum/MBox17$
   #54 = Class              #53           // org/sireum/MBox17$
   #55 = Utf8               MODULE$
   #56 = Utf8               Lorg/sireum/MBox17$;
   #57 = NameAndType        #55:#56       // MODULE$:Lorg/sireum/MBox17$;
   #58 = Fieldref           #54.#57       // org/sireum/MBox17$.MODULE$:Lorg/sireum/MBox17$;
   #59 = NameAndType        #49:#50       // unapply:(Lorg/sireum/MBox17;)Lscala/Some;
   #60 = Methodref          #54.#59       // org/sireum/MBox17$.unapply:(Lorg/sireum/MBox17;)Lscala/Some;
   #61 = Utf8               Lorg/sireum/MBox17;
   #62 = Utf8               $owned
   #63 = Utf8               ()Z
   #64 = Utf8               $owned$
   #65 = Utf8               (Lorg/sireum/RecordSig;)Z
   #66 = NameAndType        #64:#65       // $owned$:(Lorg/sireum/RecordSig;)Z
   #67 = InterfaceMethodref #7.#66        // org/sireum/RecordSig.$owned$:(Lorg/sireum/RecordSig;)Z
   #68 = Utf8               this
   #69 = Utf8               $owned_$eq
   #70 = Utf8               (Z)Lorg/sireum/RecordSig;
   #71 = Utf8               b
   #72 = Utf8               $owned_$eq$
   #73 = Utf8               (Lorg/sireum/RecordSig;Z)Lorg/sireum/RecordSig;
   #74 = NameAndType        #72:#73       // $owned_$eq$:(Lorg/sireum/RecordSig;Z)Lorg/sireum/RecordSig;
   #75 = InterfaceMethodref #7.#74        // org/sireum/RecordSig.$owned_$eq$:(Lorg/sireum/RecordSig;Z)Lorg/sireum/RecordSig;
   #76 = Utf8               hash
   #77 = Utf8               ()Lorg/sireum/Z;
   #78 = Utf8               hash$
   #79 = Utf8               (Lorg/sireum/RecordSig;)Lorg/sireum/Z;
   #80 = NameAndType        #78:#79       // hash$:(Lorg/sireum/RecordSig;)Lorg/sireum/Z;
   #81 = InterfaceMethodref #7.#80        // org/sireum/RecordSig.hash$:(Lorg/sireum/RecordSig;)Lorg/sireum/Z;
   #82 = Utf8               $cannotMixImmutableAndMutable
   #83 = Utf8               ()Lscala/runtime/Nothing$;
   #84 = Utf8               org/sireum/Mutable
   #85 = Class              #84           // org/sireum/Mutable
   #86 = Utf8               $cannotMixImmutableAndMutable$
   #87 = Utf8               (Lorg/sireum/Mutable;)Lscala/runtime/Nothing$;
   #88 = NameAndType        #86:#87       // $cannotMixImmutableAndMutable$:(Lorg/sireum/Mutable;)Lscala/runtime/Nothing$;
   #89 = InterfaceMethodref #85.#88       // org/sireum/Mutable.$cannotMixImmutableAndMutable$:(Lorg/sireum/Mutable;)Lscala/runtime/Nothing$;
   #90 = Utf8               $hasEquals
   #91 = Utf8               $hasEquals$
   #92 = Utf8               (Lorg/sireum/Mutable;)Z
   #93 = NameAndType        #91:#92       // $hasEquals$:(Lorg/sireum/Mutable;)Z
   #94 = InterfaceMethodref #85.#93       // org/sireum/Mutable.$hasEquals$:(Lorg/sireum/Mutable;)Z
   #95 = Utf8               $hasString
   #96 = Utf8               $hasString$
   #97 = NameAndType        #96:#92       // $hasString$:(Lorg/sireum/Mutable;)Z
   #98 = InterfaceMethodref #85.#97       // org/sireum/Mutable.$hasString$:(Lorg/sireum/Mutable;)Z
   #99 = NameAndType        #47:#48       // org$sireum$RecordSig$$$isOwned:Z
  #100 = Fieldref           #2.#99        // org/sireum/MBox17.org$sireum$RecordSig$$$isOwned:Z
  #101 = Utf8               org$sireum$RecordSig$$$isOwned_$eq
  #102 = Utf8               (Z)V
  #103 = Utf8               x$1
  #104 = Utf8               value1
  #105 = Utf8               ()Ljava/lang/Object;
  #106 = Utf8               ()TT1;
  #107 = NameAndType        #12:#13       // _value1:Ljava/lang/Object;
  #108 = Fieldref           #2.#107       // org/sireum/MBox17._value1:Ljava/lang/Object;
  #109 = Utf8               getValue1
  #110 = Utf8               value1_$eq
  #111 = Utf8               (Ljava/lang/Object;)Lorg/sireum/MBox17;
  #112 = Utf8               (TT1;)Lorg/sireum/MBox17<TT1;TT2;TT3;TT4;TT5;TT6;TT7;TT8;TT9;TT10;TT11;TT12;TT13;TT14;TT15;TT16;TT17;>;
  #113 = Utf8               setValue1
  #114 = Utf8               value2
  #115 = Utf8               ()TT2;
  #116 = NameAndType        #15:#13       // _value2:Ljava/lang/Object;
  #117 = Fieldref           #2.#116       // org/sireum/MBox17._value2:Ljava/lang/Object;
  #118 = Utf8               getValue2
  #119 = Utf8               value2_$eq
  #120 = Utf8               (TT2;)Lorg/sireum/MBox17<TT1;TT2;TT3;TT4;TT5;TT6;TT7;TT8;TT9;TT10;TT11;TT12;TT13;TT14;TT15;TT16;TT17;>;
  #121 = Utf8               setValue2
  #122 = Utf8               value3
  #123 = Utf8               ()TT3;
  #124 = NameAndType        #17:#13       // _value3:Ljava/lang/Object;
  #125 = Fieldref           #2.#124       // org/sireum/MBox17._value3:Ljava/lang/Object;
  #126 = Utf8               getValue3
  #127 = Utf8               value3_$eq
  #128 = Utf8               (TT3;)Lorg/sireum/MBox17<TT1;TT2;TT3;TT4;TT5;TT6;TT7;TT8;TT9;TT10;TT11;TT12;TT13;TT14;TT15;TT16;TT17;>;
  #129 = Utf8               setValue3
  #130 = Utf8               value4
  #131 = Utf8               ()TT4;
  #132 = NameAndType        #19:#13       // _value4:Ljava/lang/Object;
  #133 = Fieldref           #2.#132       // org/sireum/MBox17._value4:Ljava/lang/Object;
  #134 = Utf8               getValue4
  #135 = Utf8               value4_$eq
  #136 = Utf8               (TT4;)Lorg/sireum/MBox17<TT1;TT2;TT3;TT4;TT5;TT6;TT7;TT8;TT9;TT10;TT11;TT12;TT13;TT14;TT15;TT16;TT17;>;
  #137 = Utf8               setValue4
  #138 = Utf8               value5
  #139 = Utf8               ()TT5;
  #140 = NameAndType        #21:#13       // _value5:Ljava/lang/Object;
  #141 = Fieldref           #2.#140       // org/sireum/MBox17._value5:Ljava/lang/Object;
  #142 = Utf8               getValue5
  #143 = Utf8               value5_$eq
  #144 = Utf8               (TT5;)Lorg/sireum/MBox17<TT1;TT2;TT3;TT4;TT5;TT6;TT7;TT8;TT9;TT10;TT11;TT12;TT13;TT14;TT15;TT16;TT17;>;
  #145 = Utf8               setValue5
  #146 = Utf8               value6
  #147 = Utf8               ()TT6;
  #148 = NameAndType        #23:#13       // _value6:Ljava/lang/Object;
  #149 = Fieldref           #2.#148       // org/sireum/MBox17._value6:Ljava/lang/Object;
  #150 = Utf8               getValue6
  #151 = Utf8               value6_$eq
  #152 = Utf8               (TT6;)Lorg/sireum/MBox17<TT1;TT2;TT3;TT4;TT5;TT6;TT7;TT8;TT9;TT10;TT11;TT12;TT13;TT14;TT15;TT16;TT17;>;
  #153 = Utf8               setValue6
  #154 = Utf8               value7
  #155 = Utf8               ()TT7;
  #156 = NameAndType        #25:#13       // _value7:Ljava/lang/Object;
  #157 = Fieldref           #2.#156       // org/sireum/MBox17._value7:Ljava/lang/Object;
  #158 = Utf8               getValue7
  #159 = Utf8               value7_$eq
  #160 = Utf8               (TT7;)Lorg/sireum/MBox17<TT1;TT2;TT3;TT4;TT5;TT6;TT7;TT8;TT9;TT10;TT11;TT12;TT13;TT14;TT15;TT16;TT17;>;
  #161 = Utf8               setValue7
  #162 = Utf8               value8
  #163 = Utf8               ()TT8;
  #164 = NameAndType        #27:#13       // _value8:Ljava/lang/Object;
  #165 = Fieldref           #2.#164       // org/sireum/MBox17._value8:Ljava/lang/Object;
  #166 = Utf8               getValue8
  #167 = Utf8               value8_$eq
  #168 = Utf8               (TT8;)Lorg/sireum/MBox17<TT1;TT2;TT3;TT4;TT5;TT6;TT7;TT8;TT9;TT10;TT11;TT12;TT13;TT14;TT15;TT16;TT17;>;
  #169 = Utf8               setValue8
  #170 = Utf8               value9
  #171 = Utf8               ()TT9;
  #172 = NameAndType        #29:#13       // _value9:Ljava/lang/Object;
  #173 = Fieldref           #2.#172       // org/sireum/MBox17._value9:Ljava/lang/Object;
  #174 = Utf8               getValue9
  #175 = Utf8               value9_$eq
  #176 = Utf8               (TT9;)Lorg/sireum/MBox17<TT1;TT2;TT3;TT4;TT5;TT6;TT7;TT8;TT9;TT10;TT11;TT12;TT13;TT14;TT15;TT16;TT17;>;
  #177 = Utf8               setValue9
  #178 = Utf8               value10
  #179 = Utf8               ()TT10;
  #180 = NameAndType        #31:#13       // _value10:Ljava/lang/Object;
  #181 = Fieldref           #2.#180       // org/sireum/MBox17._value10:Ljava/lang/Object;
  #182 = Utf8               getValue10
  #183 = Utf8               value10_$eq
  #184 = Utf8               (TT10;)Lorg/sireum/MBox17<TT1;TT2;TT3;TT4;TT5;TT6;TT7;TT8;TT9;TT10;TT11;TT12;TT13;TT14;TT15;TT16;TT17;>;
  #185 = Utf8               setValue10
  #186 = Utf8               value11
  #187 = Utf8               ()TT11;
  #188 = NameAndType        #33:#13       // _value11:Ljava/lang/Object;
  #189 = Fieldref           #2.#188       // org/sireum/MBox17._value11:Ljava/lang/Object;
  #190 = Utf8               getValue11
  #191 = Utf8               value11_$eq
  #192 = Utf8               (TT11;)Lorg/sireum/MBox17<TT1;TT2;TT3;TT4;TT5;TT6;TT7;TT8;TT9;TT10;TT11;TT12;TT13;TT14;TT15;TT16;TT17;>;
  #193 = Utf8               setValue11
  #194 = Utf8               value12
  #195 = Utf8               ()TT12;
  #196 = NameAndType        #35:#13       // _value12:Ljava/lang/Object;
  #197 = Fieldref           #2.#196       // org/sireum/MBox17._value12:Ljava/lang/Object;
  #198 = Utf8               getValue12
  #199 = Utf8               value12_$eq
  #200 = Utf8               (TT12;)Lorg/sireum/MBox17<TT1;TT2;TT3;TT4;TT5;TT6;TT7;TT8;TT9;TT10;TT11;TT12;TT13;TT14;TT15;TT16;TT17;>;
  #201 = Utf8               setValue12
  #202 = Utf8               value13
  #203 = Utf8               ()TT13;
  #204 = NameAndType        #37:#13       // _value13:Ljava/lang/Object;
  #205 = Fieldref           #2.#204       // org/sireum/MBox17._value13:Ljava/lang/Object;
  #206 = Utf8               getValue13
  #207 = Utf8               value13_$eq
  #208 = Utf8               (TT13;)Lorg/sireum/MBox17<TT1;TT2;TT3;TT4;TT5;TT6;TT7;TT8;TT9;TT10;TT11;TT12;TT13;TT14;TT15;TT16;TT17;>;
  #209 = Utf8               setValue13
  #210 = Utf8               value14
  #211 = Utf8               ()TT14;
  #212 = NameAndType        #39:#13       // _value14:Ljava/lang/Object;
  #213 = Fieldref           #2.#212       // org/sireum/MBox17._value14:Ljava/lang/Object;
  #214 = Utf8               getValue14
  #215 = Utf8               value14_$eq
  #216 = Utf8               (TT14;)Lorg/sireum/MBox17<TT1;TT2;TT3;TT4;TT5;TT6;TT7;TT8;TT9;TT10;TT11;TT12;TT13;TT14;TT15;TT16;TT17;>;
  #217 = Utf8               setValue14
  #218 = Utf8               value15
  #219 = Utf8               ()TT15;
  #220 = NameAndType        #41:#13       // _value15:Ljava/lang/Object;
  #221 = Fieldref           #2.#220       // org/sireum/MBox17._value15:Ljava/lang/Object;
  #222 = Utf8               getValue15
  #223 = Utf8               value15_$eq
  #224 = Utf8               (TT15;)Lorg/sireum/MBox17<TT1;TT2;TT3;TT4;TT5;TT6;TT7;TT8;TT9;TT10;TT11;TT12;TT13;TT14;TT15;TT16;TT17;>;
  #225 = Utf8               setValue15
  #226 = Utf8               value16
  #227 = Utf8               ()TT16;
  #228 = NameAndType        #43:#13       // _value16:Ljava/lang/Object;
  #229 = Fieldref           #2.#228       // org/sireum/MBox17._value16:Ljava/lang/Object;
  #230 = Utf8               getValue16
  #231 = Utf8               value16_$eq
  #232 = Utf8               (TT16;)Lorg/sireum/MBox17<TT1;TT2;TT3;TT4;TT5;TT6;TT7;TT8;TT9;TT10;TT11;TT12;TT13;TT14;TT15;TT16;TT17;>;
  #233 = Utf8               setValue16
  #234 = Utf8               value17
  #235 = Utf8               ()TT17;
  #236 = NameAndType        #45:#13       // _value17:Ljava/lang/Object;
  #237 = Fieldref           #2.#236       // org/sireum/MBox17._value17:Ljava/lang/Object;
  #238 = Utf8               getValue17
  #239 = Utf8               value17_$eq
  #240 = Utf8               (TT17;)Lorg/sireum/MBox17<TT1;TT2;TT3;TT4;TT5;TT6;TT7;TT8;TT9;TT10;TT11;TT12;TT13;TT14;TT15;TT16;TT17;>;
  #241 = Utf8               setValue17
  #242 = Utf8               toString
  #243 = Utf8               ()Ljava/lang/String;
  #244 = NameAndType        #95:#63       // $hasString:()Z
  #245 = Methodref          #2.#244       // org/sireum/MBox17.$hasString:()Z
  #246 = Utf8               string$
  #247 = Utf8               (Lorg/sireum/RecordSig;)Ljava/lang/String;
  #248 = NameAndType        #246:#247     // string$:(Lorg/sireum/RecordSig;)Ljava/lang/String;
  #249 = InterfaceMethodref #7.#248       // org/sireum/RecordSig.string$:(Lorg/sireum/RecordSig;)Ljava/lang/String;
  #250 = Utf8               java/lang/StringBuilder
  #251 = Class              #250          // java/lang/StringBuilder
  #252 = Utf8               <init>
  #253 = Utf8               ()V
  #254 = NameAndType        #252:#253     // "<init>":()V
  #255 = Methodref          #251.#254     // java/lang/StringBuilder."<init>":()V
  #256 = Utf8               MBox17
  #257 = String             #256          // MBox17
  #258 = Utf8               append
  #259 = Utf8               (Ljava/lang/String;)Ljava/lang/StringBuilder;
  #260 = NameAndType        #258:#259     // append:(Ljava/lang/String;)Ljava/lang/StringBuilder;
  #261 = Methodref          #251.#260     // java/lang/StringBuilder.append:(Ljava/lang/String;)Ljava/lang/StringBuilder;
  #262 = Utf8               (C)Ljava/lang/StringBuilder;
  #263 = NameAndType        #258:#262     // append:(C)Ljava/lang/StringBuilder;
  #264 = Methodref          #251.#263     // java/lang/StringBuilder.append:(C)Ljava/lang/StringBuilder;
  #265 = Utf8               org/sireum/String$
  #266 = Class              #265          // org/sireum/String$
  #267 = Utf8               Lorg/sireum/String$;
  #268 = NameAndType        #55:#267      // MODULE$:Lorg/sireum/String$;
  #269 = Fieldref           #266.#268     // org/sireum/String$.MODULE$:Lorg/sireum/String$;
  #270 = NameAndType        #104:#105     // value1:()Ljava/lang/Object;
  #271 = Methodref          #2.#270       // org/sireum/MBox17.value1:()Ljava/lang/Object;
  #272 = Utf8               escape
  #273 = Utf8               (Ljava/lang/Object;)Ljava/lang/String;
  #274 = NameAndType        #272:#273     // escape:(Ljava/lang/Object;)Ljava/lang/String;
  #275 = Methodref          #266.#274     // org/sireum/String$.escape:(Ljava/lang/Object;)Ljava/lang/String;
  #276 = Utf8               ,
  #277 = String             #276          // ,
  #278 = NameAndType        #114:#105     // value2:()Ljava/lang/Object;
  #279 = Methodref          #2.#278       // org/sireum/MBox17.value2:()Ljava/lang/Object;
  #280 = NameAndType        #122:#105     // value3:()Ljava/lang/Object;
  #281 = Methodref          #2.#280       // org/sireum/MBox17.value3:()Ljava/lang/Object;
  #282 = NameAndType        #130:#105     // value4:()Ljava/lang/Object;
  #283 = Methodref          #2.#282       // org/sireum/MBox17.value4:()Ljava/lang/Object;
  #284 = NameAndType        #138:#105     // value5:()Ljava/lang/Object;
  #285 = Methodref          #2.#284       // org/sireum/MBox17.value5:()Ljava/lang/Object;
  #286 = NameAndType        #146:#105     // value6:()Ljava/lang/Object;
  #287 = Methodref          #2.#286       // org/sireum/MBox17.value6:()Ljava/lang/Object;
  #288 = NameAndType        #154:#105     // value7:()Ljava/lang/Object;
  #289 = Methodref          #2.#288       // org/sireum/MBox17.value7:()Ljava/lang/Object;
  #290 = NameAndType        #162:#105     // value8:()Ljava/lang/Object;
  #291 = Methodref          #2.#290       // org/sireum/MBox17.value8:()Ljava/lang/Object;
  #292 = NameAndType        #170:#105     // value9:()Ljava/lang/Object;
  #293 = Methodref          #2.#292       // org/sireum/MBox17.value9:()Ljava/lang/Object;
  #294 = NameAndType        #178:#105     // value10:()Ljava/lang/Object;
  #295 = Methodref          #2.#294       // org/sireum/MBox17.value10:()Ljava/lang/Object;
  #296 = NameAndType        #186:#105     // value11:()Ljava/lang/Object;
  #297 = Methodref          #2.#296       // org/sireum/MBox17.value11:()Ljava/lang/Object;
  #298 = NameAndType        #194:#105     // value12:()Ljava/lang/Object;
  #299 = Methodref          #2.#298       // org/sireum/MBox17.value12:()Ljava/lang/Object;
  #300 = NameAndType        #202:#105     // value13:()Ljava/lang/Object;
  #301 = Methodref          #2.#300       // org/sireum/MBox17.value13:()Ljava/lang/Object;
  #302 = NameAndType        #210:#105     // value14:()Ljava/lang/Object;
  #303 = Methodref          #2.#302       // org/sireum/MBox17.value14:()Ljava/lang/Object;
  #304 = NameAndType        #218:#105     // value15:()Ljava/lang/Object;
  #305 = Methodref          #2.#304       // org/sireum/MBox17.value15:()Ljava/lang/Object;
  #306 = NameAndType        #226:#105     // value16:()Ljava/lang/Object;
  #307 = Methodref          #2.#306       // org/sireum/MBox17.value16:()Ljava/lang/Object;
  #308 = NameAndType        #234:#105     // value17:()Ljava/lang/Object;
  #309 = Methodref          #2.#308       // org/sireum/MBox17.value17:()Ljava/lang/Object;
  #310 = NameAndType        #242:#243     // toString:()Ljava/lang/String;
  #311 = Methodref          #251.#310     // java/lang/StringBuilder.toString:()Ljava/lang/String;
  #312 = Utf8               sb
  #313 = Utf8               Ljava/lang/StringBuilder;
  #314 = Utf8               java/lang/String
  #315 = Class              #314          // java/lang/String
  #316 = Utf8               string
  #317 = Methodref          #2.#310       // org/sireum/MBox17.toString:()Ljava/lang/String;
  #318 = Utf8               apply
  #319 = Utf8               (Ljava/lang/String;)Ljava/lang/String;
  #320 = NameAndType        #318:#319     // apply:(Ljava/lang/String;)Ljava/lang/String;
  #321 = Methodref          #266.#320     // org/sireum/String$.apply:(Ljava/lang/String;)Ljava/lang/String;
  #322 = Utf8               hashCode
  #323 = Utf8               ()I
  #324 = NameAndType        #90:#63       // $hasEquals:()Z
  #325 = Methodref          #2.#324       // org/sireum/MBox17.$hasEquals:()Z
  #326 = NameAndType        #322:#323     // hashCode:()I
  #327 = Methodref          #5.#326       // java/lang/Object.hashCode:()I
  #328 = Utf8               scala/package$
  #329 = Class              #328          // scala/package$
  #330 = Utf8               Lscala/package$;
  #331 = NameAndType        #55:#330      // MODULE$:Lscala/package$;
  #332 = Fieldref           #329.#331     // scala/package$.MODULE$:Lscala/package$;
  #333 = Utf8               Seq
  #334 = Utf8               ()Lscala/collection/immutable/Seq$;
  #335 = NameAndType        #333:#334     // Seq:()Lscala/collection/immutable/Seq$;
  #336 = Methodref          #329.#335     // scala/package$.Seq:()Lscala/collection/immutable/Seq$;
  #337 = Utf8               scala/runtime/ScalaRunTime$
  #338 = Class              #337          // scala/runtime/ScalaRunTime$
  #339 = Utf8               Lscala/runtime/ScalaRunTime$;
  #340 = NameAndType        #55:#339      // MODULE$:Lscala/runtime/ScalaRunTime$;
  #341 = Fieldref           #338.#340     // scala/runtime/ScalaRunTime$.MODULE$:Lscala/runtime/ScalaRunTime$;
  #342 = Utf8               getClass
  #343 = Utf8               ()Ljava/lang/Class;
  #344 = NameAndType        #342:#343     // getClass:()Ljava/lang/Class;
  #345 = Methodref          #2.#344       // org/sireum/MBox17.getClass:()Ljava/lang/Class;
  #346 = Utf8               java/lang/Class
  #347 = Class              #346          // java/lang/Class
  #348 = Utf8               getName
  #349 = NameAndType        #348:#243     // getName:()Ljava/lang/String;
  #350 = Methodref          #347.#349     // java/lang/Class.getName:()Ljava/lang/String;
  #351 = Utf8               genericWrapArray
  #352 = Utf8               (Ljava/lang/Object;)Lscala/collection/immutable/ArraySeq;
  #353 = NameAndType        #351:#352     // genericWrapArray:(Ljava/lang/Object;)Lscala/collection/immutable/ArraySeq;
  #354 = Methodref          #338.#353     // scala/runtime/ScalaRunTime$.genericWrapArray:(Ljava/lang/Object;)Lscala/collection/immutable/ArraySeq;
  #355 = Utf8               scala/collection/immutable/Seq$
  #356 = Class              #355          // scala/collection/immutable/Seq$
  #357 = Utf8               (Lscala/collection/immutable/Seq;)Lscala/collection/SeqOps;
  #358 = NameAndType        #318:#357     // apply:(Lscala/collection/immutable/Seq;)Lscala/collection/SeqOps;
  #359 = Methodref          #356.#358     // scala/collection/immutable/Seq$.apply:(Lscala/collection/immutable/Seq;)Lscala/collection/SeqOps;
  #360 = Utf8               scala/collection/Seq
  #361 = Class              #360          // scala/collection/Seq
  #362 = InterfaceMethodref #361.#326     // scala/collection/Seq.hashCode:()I
  #363 = Utf8               equals
  #364 = Utf8               (Ljava/lang/Object;)Z
  #365 = NameAndType        #363:#364     // equals:(Ljava/lang/Object;)Z
  #366 = Methodref          #5.#365       // java/lang/Object.equals:(Ljava/lang/Object;)Z
  #367 = Methodref          #2.#326       // org/sireum/MBox17.hashCode:()I
  #368 = Utf8               scala/runtime/BoxesRunTime
  #369 = Class              #368          // scala/runtime/BoxesRunTime
  #370 = Utf8               (Ljava/lang/Object;Ljava/lang/Object;)Z
  #371 = NameAndType        #363:#370     // equals:(Ljava/lang/Object;Ljava/lang/Object;)Z
  #372 = Methodref          #369.#371     // scala/runtime/BoxesRunTime.equals:(Ljava/lang/Object;Ljava/lang/Object;)Z
  #373 = Utf8               (Ljava/lang/Object;Ljava/lang/Object;Ljava/lang/Object;Ljava/lang/Object;Ljava/lang/Object;Ljava/lang/Object;Ljava/lang/Object;Ljava/lang/Object;Ljava/lang/Object;Ljava/lang/Object;Ljava/lang/Object;Ljava/lang/Object;Ljava/lang/Object;Ljava/lang/Object;Ljava/lang/Object;Ljava/lang/Object;Ljava/lang/Object;)Lorg/sireum/MBox17;
  #374 = Utf8               (TT1;TT2;TT3;TT4;TT5;TT6;TT7;TT8;TT9;TT10;TT11;TT12;TT13;TT14;TT15;TT16;TT17;)Lorg/sireum/MBox17<TT1;TT2;TT3;TT4;TT5;TT6;TT7;TT8;TT9;TT10;TT11;TT12;TT13;TT14;TT15;TT16;TT17;>;
  #375 = Utf8               (Ljava/lang/Object;Ljava/lang/Object;Ljava/lang/Object;Ljava/lang/Object;Ljava/lang/Object;Ljava/lang/Object;Ljava/lang/Object;Ljava/lang/Object;Ljava/lang/Object;Ljava/lang/Object;Ljava/lang/Object;Ljava/lang/Object;Ljava/lang/Object;Ljava/lang/Object;Ljava/lang/Object;Ljava/lang/Object;Ljava/lang/Object;)V
  #376 = NameAndType        #252:#375     // "<init>":(Ljava/lang/Object;Ljava/lang/Object;Ljava/lang/Object;Ljava/lang/Object;Ljava/lang/Object;Ljava/lang/Object;Ljava/lang/Object;Ljava/lang/Object;Ljava/lang/Object;Ljava/lang/Object;Ljava/lang/Object;Ljava/lang/Object;Ljava/lang/Object;Ljava/lang/Object;Ljava/lang/Object;Ljava/lang/Object;Ljava/lang/Object;)V
  #377 = Methodref          #2.#376       // org/sireum/MBox17."<init>":(Ljava/lang/Object;Ljava/lang/Object;Ljava/lang/Object;Ljava/lang/Object;Ljava/lang/Object;Ljava/lang/Object;Ljava/lang/Object;Ljava/lang/Object;Ljava/lang/Object;Ljava/lang/Object;Ljava/lang/Object;Ljava/lang/Object;Ljava/lang/Object;Ljava/lang/Object;Ljava/lang/Object;Ljava/lang/Object;Ljava/lang/Object;)V
  #378 = Utf8               apply$default$1
  #379 = Utf8               apply$default$2
  #380 = Utf8               apply$default$3
  #381 = Utf8               apply$default$4
  #382 = Utf8               apply$default$5
  #383 = Utf8               apply$default$6
  #384 = Utf8               apply$default$7
  #385 = Utf8               apply$default$8
  #386 = Utf8               apply$default$9
  #387 = Utf8               apply$default$10
  #388 = Utf8               apply$default$11
  #389 = Utf8               apply$default$12
  #390 = Utf8               apply$default$13
  #391 = Utf8               apply$default$14
  #392 = Utf8               apply$default$15
  #393 = Utf8               apply$default$16
  #394 = Utf8               apply$default$17
  #395 = Utf8               $content
  #396 = Utf8               ()Lscala/collection/immutable/Seq;
  #397 = Utf8               ()Lscala/collection/immutable/Seq<Lscala/Tuple2<Ljava/lang/String;Ljava/lang/Object;>;>;
  #398 = Utf8               scala/Tuple2
  #399 = Class              #398          // scala/Tuple2
  #400 = Utf8               type
  #401 = String             #400          // type
  #402 = Utf8               List
  #403 = Utf8               ()Lscala/collection/immutable/List$;
  #404 = NameAndType        #402:#403     // List:()Lscala/collection/immutable/List$;
  #405 = Methodref          #329.#404     // scala/package$.List:()Lscala/collection/immutable/List$;
  #406 = Utf8               org
  #407 = String             #406          // org
  #408 = Utf8               sireum
  #409 = String             #408          // sireum
  #410 = Utf8               [Ljava/lang/Object;
  #411 = Class              #410          // "[Ljava/lang/Object;"
  #412 = Utf8               wrapRefArray
  #413 = Utf8               ([Ljava/lang/Object;)Lscala/collection/immutable/ArraySeq;
  #414 = NameAndType        #412:#413     // wrapRefArray:([Ljava/lang/Object;)Lscala/collection/immutable/ArraySeq;
  #415 = Methodref          #338.#414     // scala/runtime/ScalaRunTime$.wrapRefArray:([Ljava/lang/Object;)Lscala/collection/immutable/ArraySeq;
  #416 = Utf8               scala/collection/immutable/List$
  #417 = Class              #416          // scala/collection/immutable/List$
  #418 = Utf8               (Lscala/collection/immutable/Seq;)Ljava/lang/Object;
  #419 = NameAndType        #318:#418     // apply:(Lscala/collection/immutable/Seq;)Ljava/lang/Object;
  #420 = Methodref          #417.#419     // scala/collection/immutable/List$.apply:(Lscala/collection/immutable/Seq;)Ljava/lang/Object;
  #421 = Utf8               (Ljava/lang/Object;Ljava/lang/Object;)V
  #422 = NameAndType        #252:#421     // "<init>":(Ljava/lang/Object;Ljava/lang/Object;)V
  #423 = Methodref          #399.#422     // scala/Tuple2."<init>":(Ljava/lang/Object;Ljava/lang/Object;)V
  #424 = String             #104          // value1
  #425 = String             #114          // value2
  #426 = String             #122          // value3
  #427 = String             #130          // value4
  #428 = String             #138          // value5
  #429 = String             #146          // value6
  #430 = String             #154          // value7
  #431 = String             #162          // value8
  #432 = String             #170          // value9
  #433 = String             #178          // value10
  #434 = String             #186          // value11
  #435 = String             #194          // value12
  #436 = String             #202          // value13
  #437 = String             #210          // value14
  #438 = String             #218          // value15
  #439 = String             #226          // value16
  #440 = String             #234          // value17
  #441 = Utf8               scala/collection/immutable/Seq
  #442 = Class              #441          // scala/collection/immutable/Seq
  #443 = Utf8               $clone
  #444 = Utf8               ()Lorg/sireum/MBox17;
  #445 = Utf8               ()Lorg/sireum/MBox17<TT1;TT2;TT3;TT4;TT5;TT6;TT7;TT8;TT9;TT10;TT11;TT12;TT13;TT14;TT15;TT16;TT17;>;
  #446 = Utf8               org/sireum/helper$
  #447 = Class              #446          // org/sireum/helper$
  #448 = Utf8               Lorg/sireum/helper$;
  #449 = NameAndType        #55:#448      // MODULE$:Lorg/sireum/helper$;
  #450 = Fieldref           #447.#449     // org/sireum/helper$.MODULE$:Lorg/sireum/helper$;
  #451 = Utf8               cloneAssign
  #452 = Utf8               (Ljava/lang/Object;)Ljava/lang/Object;
  #453 = NameAndType        #451:#452     // cloneAssign:(Ljava/lang/Object;)Ljava/lang/Object;
  #454 = Methodref          #447.#453     // org/sireum/helper$.cloneAssign:(Ljava/lang/Object;)Ljava/lang/Object;
  #455 = Utf8               r
  #456 = Utf8               (Z)Lorg/sireum/$internal/MutableMarker;
  #457 = NameAndType        #69:#70       // $owned_$eq:(Z)Lorg/sireum/RecordSig;
  #458 = Methodref          #2.#457       // org/sireum/MBox17.$owned_$eq:(Z)Lorg/sireum/RecordSig;
  #459 = NameAndType        #443:#444     // $clone:()Lorg/sireum/MBox17;
  #460 = Methodref          #2.#459       // org/sireum/MBox17.$clone:()Lorg/sireum/MBox17;
  #461 = Utf8               ()Lorg/sireum/$internal/MutableMarker;
  #462 = Utf8               (TT1;TT2;TT3;TT4;TT5;TT6;TT7;TT8;TT9;TT10;TT11;TT12;TT13;TT14;TT15;TT16;TT17;)V
  #463 = Utf8               __value1
  #464 = Utf8               __value2
  #465 = Utf8               __value3
  #466 = Utf8               __value4
  #467 = Utf8               __value5
  #468 = Utf8               __value6
  #469 = Utf8               __value7
  #470 = Utf8               __value8
  #471 = Utf8               __value9
  #472 = Utf8               __value10
  #473 = Utf8               __value11
  #474 = Utf8               __value12
  #475 = Utf8               __value13
  #476 = Utf8               __value14
  #477 = Utf8               __value15
  #478 = Utf8               __value16
  #479 = Utf8               __value17
  #480 = Methodref          #5.#254       // java/lang/Object."<init>":()V
  #481 = Utf8               $init$
  #482 = Utf8               (Lorg/sireum/Mutable;)V
  #483 = NameAndType        #481:#482     // $init$:(Lorg/sireum/Mutable;)V
  #484 = InterfaceMethodref #85.#483      // org/sireum/Mutable.$init$:(Lorg/sireum/Mutable;)V
  #485 = Utf8               (Lorg/sireum/RecordSig;)V
  #486 = NameAndType        #481:#485     // $init$:(Lorg/sireum/RecordSig;)V
  #487 = InterfaceMethodref #7.#486       // org/sireum/RecordSig.$init$:(Lorg/sireum/RecordSig;)V
  #488 = Utf8               Signature
  #489 = Utf8               Code
  #490 = Utf8               LocalVariableTable
  #491 = Utf8               MethodParameters
  #492 = Utf8               LineNumberTable
  #493 = Utf8               StackMapTable
  #494 = Utf8               SourceFile
  #495 = Utf8               RuntimeVisibleAnnotations
  #496 = Utf8               ScalaInlineInfo
  #497 = Utf8               ScalaSig
{
  private T1 _value1;
    descriptor: Ljava/lang/Object;
    flags: (0x0002) ACC_PRIVATE
    Signature: #14                          // TT1;

  private T2 _value2;
    descriptor: Ljava/lang/Object;
    flags: (0x0002) ACC_PRIVATE
    Signature: #16                          // TT2;

  private T3 _value3;
    descriptor: Ljava/lang/Object;
    flags: (0x0002) ACC_PRIVATE
    Signature: #18                          // TT3;

  private T4 _value4;
    descriptor: Ljava/lang/Object;
    flags: (0x0002) ACC_PRIVATE
    Signature: #20                          // TT4;

  private T5 _value5;
    descriptor: Ljava/lang/Object;
    flags: (0x0002) ACC_PRIVATE
    Signature: #22                          // TT5;

  private T6 _value6;
    descriptor: Ljava/lang/Object;
    flags: (0x0002) ACC_PRIVATE
    Signature: #24                          // TT6;

  private T7 _value7;
    descriptor: Ljava/lang/Object;
    flags: (0x0002) ACC_PRIVATE
    Signature: #26                          // TT7;

  private T8 _value8;
    descriptor: Ljava/lang/Object;
    flags: (0x0002) ACC_PRIVATE
    Signature: #28                          // TT8;

  private T9 _value9;
    descriptor: Ljava/lang/Object;
    flags: (0x0002) ACC_PRIVATE
    Signature: #30                          // TT9;

  private T10 _value10;
    descriptor: Ljava/lang/Object;
    flags: (0x0002) ACC_PRIVATE
    Signature: #32                          // TT10;

  private T11 _value11;
    descriptor: Ljava/lang/Object;
    flags: (0x0002) ACC_PRIVATE
    Signature: #34                          // TT11;

  private T12 _value12;
    descriptor: Ljava/lang/Object;
    flags: (0x0002) ACC_PRIVATE
    Signature: #36                          // TT12;

  private T13 _value13;
    descriptor: Ljava/lang/Object;
    flags: (0x0002) ACC_PRIVATE
    Signature: #38                          // TT13;

  private T14 _value14;
    descriptor: Ljava/lang/Object;
    flags: (0x0002) ACC_PRIVATE
    Signature: #40                          // TT14;

  private T15 _value15;
    descriptor: Ljava/lang/Object;
    flags: (0x0002) ACC_PRIVATE
    Signature: #42                          // TT15;

  private T16 _value16;
    descriptor: Ljava/lang/Object;
    flags: (0x0002) ACC_PRIVATE
    Signature: #44                          // TT16;

  private T17 _value17;
    descriptor: Ljava/lang/Object;
    flags: (0x0002) ACC_PRIVATE
    Signature: #46                          // TT17;

  private boolean org$sireum$RecordSig$$$isOwned;
    descriptor: Z
    flags: (0x0002) ACC_PRIVATE

  public static <T1 extends java.lang.Object, T2 extends java.lang.Object, T3 extends java.lang.Object, T4 extends java.lang.Object, T5 extends java.lang.Object, T6 extends java.lang.Object, T7 extends java.lang.Object, T8 extends java.lang.Object, T9 extends java.lang.Object, T10 extends java.lang.Object, T11 extends java.lang.Object, T12 extends java.lang.Object, T13 extends java.lang.Object, T14 extends java.lang.Object, T15 extends java.lang.Object, T16 extends java.lang.Object, T17 extends java.lang.Object> scala.Some<scala.Tuple17<T1, T2, T3, T4, T5, T6, T7, T8, T9, T10, T11, T12, T13, T14, T15, T16, T17>> unapply(org.sireum.MBox17<T1, T2, T3, T4, T5, T6, T7, T8, T9, T10, T11, T12, T13, T14, T15, T16, T17>);
    descriptor: (Lorg/sireum/MBox17;)Lscala/Some;
    flags: (0x0009) ACC_PUBLIC, ACC_STATIC
    Code:
      stack=2, locals=1, args_size=1
         0: getstatic     #58                 // Field org/sireum/MBox17$.MODULE$:Lorg/sireum/MBox17$;
         3: aload_0
         4: invokevirtual #60                 // Method org/sireum/MBox17$.unapply:(Lorg/sireum/MBox17;)Lscala/Some;
         7: areturn
      LocalVariableTable:
        Start  Length  Slot  Name   Signature
            0       8     0     o   Lorg/sireum/MBox17;
    Signature: #51                          // <T1:Ljava/lang/Object;T2:Ljava/lang/Object;T3:Ljava/lang/Object;T4:Ljava/lang/Object;T5:Ljava/lang/Object;T6:Ljava/lang/Object;T7:Ljava/lang/Object;T8:Ljava/lang/Object;T9:Ljava/lang/Object;T10:Ljava/lang/Object;T11:Ljava/lang/Object;T12:Ljava/lang/Object;T13:Ljava/lang/Object;T14:Ljava/lang/Object;T15:Ljava/lang/Object;T16:Ljava/lang/Object;T17:Ljava/lang/Object;>(Lorg/sireum/MBox17<TT1;TT2;TT3;TT4;TT5;TT6;TT7;TT8;TT9;TT10;TT11;TT12;TT13;TT14;TT15;TT16;TT17;>;)Lscala/Some<Lscala/Tuple17<TT1;TT2;TT3;TT4;TT5;TT6;TT7;TT8;TT9;TT10;TT11;TT12;TT13;TT14;TT15;TT16;TT17;>;>;
    MethodParameters:
      Name                           Flags
      o                              final

  public final boolean $owned();
    descriptor: ()Z
    flags: (0x0011) ACC_PUBLIC, ACC_FINAL
    Code:
      stack=1, locals=1, args_size=1
         0: aload_0
         1: invokestatic  #67                 // InterfaceMethod org/sireum/RecordSig.$owned$:(Lorg/sireum/RecordSig;)Z
         4: ireturn
      LineNumberTable:
        line 61: 0
      LocalVariableTable:
        Start  Length  Slot  Name   Signature
            0       5     0  this   Lorg/sireum/MBox17;

  public final org.sireum.RecordSig $owned_$eq(boolean);
    descriptor: (Z)Lorg/sireum/RecordSig;
    flags: (0x0011) ACC_PUBLIC, ACC_FINAL
    Code:
      stack=2, locals=2, args_size=2
         0: aload_0
         1: iload_1
         2: invokestatic  #75                 // InterfaceMethod org/sireum/RecordSig.$owned_$eq$:(Lorg/sireum/RecordSig;Z)Lorg/sireum/RecordSig;
         5: areturn
      LineNumberTable:
        line 61: 0
      LocalVariableTable:
        Start  Length  Slot  Name   Signature
            0       6     0  this   Lorg/sireum/MBox17;
            0       6     1     b   Z
    MethodParameters:
      Name                           Flags
      b                              final

  public org.sireum.Z hash();
    descriptor: ()Lorg/sireum/Z;
    flags: (0x0001) ACC_PUBLIC
    Code:
      stack=1, locals=1, args_size=1
         0: aload_0
         1: invokestatic  #81                 // InterfaceMethod org/sireum/RecordSig.hash$:(Lorg/sireum/RecordSig;)Lorg/sireum/Z;
         4: areturn
      LineNumberTable:
        line 61: 0
      LocalVariableTable:
        Start  Length  Slot  Name   Signature
            0       5     0  this   Lorg/sireum/MBox17;

  public final scala.runtime.Nothing$ $cannotMixImmutableAndMutable();
    descriptor: ()Lscala/runtime/Nothing$;
    flags: (0x0011) ACC_PUBLIC, ACC_FINAL
    Code:
      stack=1, locals=1, args_size=1
         0: aload_0
         1: invokestatic  #89                 // InterfaceMethod org/sireum/Mutable.$cannotMixImmutableAndMutable$:(Lorg/sireum/Mutable;)Lscala/runtime/Nothing$;
         4: areturn
      LineNumberTable:
        line 61: 0
      LocalVariableTable:
        Start  Length  Slot  Name   Signature
            0       5     0  this   Lorg/sireum/MBox17;

  public boolean $hasEquals();
    descriptor: ()Z
    flags: (0x0001) ACC_PUBLIC
    Code:
      stack=1, locals=1, args_size=1
         0: aload_0
         1: invokestatic  #94                 // InterfaceMethod org/sireum/Mutable.$hasEquals$:(Lorg/sireum/Mutable;)Z
         4: ireturn
      LineNumberTable:
        line 61: 0
      LocalVariableTable:
        Start  Length  Slot  Name   Signature
            0       5     0  this   Lorg/sireum/MBox17;

  public boolean $hasString();
    descriptor: ()Z
    flags: (0x0001) ACC_PUBLIC
    Code:
      stack=1, locals=1, args_size=1
         0: aload_0
         1: invokestatic  #98                 // InterfaceMethod org/sireum/Mutable.$hasString$:(Lorg/sireum/Mutable;)Z
         4: ireturn
      LineNumberTable:
        line 61: 0
      LocalVariableTable:
        Start  Length  Slot  Name   Signature
            0       5     0  this   Lorg/sireum/MBox17;

  public boolean org$sireum$RecordSig$$$isOwned();
    descriptor: ()Z
    flags: (0x0001) ACC_PUBLIC
    Code:
      stack=1, locals=1, args_size=1
         0: aload_0
         1: getfield      #100                // Field org$sireum$RecordSig$$$isOwned:Z
         4: ireturn
      LineNumberTable:
        line 61: 0
      LocalVariableTable:
        Start  Length  Slot  Name   Signature
            0       5     0  this   Lorg/sireum/MBox17;

  public void org$sireum$RecordSig$$$isOwned_$eq(boolean);
    descriptor: (Z)V
    flags: (0x0001) ACC_PUBLIC
    Code:
      stack=2, locals=2, args_size=2
         0: aload_0
         1: iload_1
         2: putfield      #100                // Field org$sireum$RecordSig$$$isOwned:Z
         5: return
      LineNumberTable:
        line 61: 0
      LocalVariableTable:
        Start  Length  Slot  Name   Signature
            0       6     0  this   Lorg/sireum/MBox17;
            0       6     1   x$1   Z
    MethodParameters:
      Name                           Flags
      x$1                            final

  public T1 value1();
    descriptor: ()Ljava/lang/Object;
    flags: (0x0001) ACC_PUBLIC
    Code:
      stack=1, locals=1, args_size=1
         0: aload_0
         1: getfield      #108                // Field _value1:Ljava/lang/Object;
         4: areturn
      LineNumberTable:
        line 61: 0
      LocalVariableTable:
        Start  Length  Slot  Name   Signature
            0       5     0  this   Lorg/sireum/MBox17;
    Signature: #106                         // ()TT1;

  public T1 getValue1();
    descriptor: ()Ljava/lang/Object;
    flags: (0x0001) ACC_PUBLIC
    Code:
      stack=1, locals=1, args_size=1
         0: aload_0
         1: getfield      #108                // Field _value1:Ljava/lang/Object;
         4: areturn
      LineNumberTable:
        line 61: 0
      LocalVariableTable:
        Start  Length  Slot  Name   Signature
            0       5     0  this   Lorg/sireum/MBox17;
    Signature: #106                         // ()TT1;

  public org.sireum.MBox17<T1, T2, T3, T4, T5, T6, T7, T8, T9, T10, T11, T12, T13, T14, T15, T16, T17> value1_$eq(T1);
    descriptor: (Ljava/lang/Object;)Lorg/sireum/MBox17;
    flags: (0x0001) ACC_PUBLIC
    Code:
      stack=2, locals=2, args_size=2
         0: aload_0
         1: aload_1
         2: putfield      #108                // Field _value1:Ljava/lang/Object;
         5: aload_0
         6: areturn
      LineNumberTable:
        line 61: 0
      LocalVariableTable:
        Start  Length  Slot  Name   Signature
            0       7     0  this   Lorg/sireum/MBox17;
            0       7     1 value1   Ljava/lang/Object;
    Signature: #112                         // (TT1;)Lorg/sireum/MBox17<TT1;TT2;TT3;TT4;TT5;TT6;TT7;TT8;TT9;TT10;TT11;TT12;TT13;TT14;TT15;TT16;TT17;>;
    MethodParameters:
      Name                           Flags
      value1                         final

  public org.sireum.MBox17<T1, T2, T3, T4, T5, T6, T7, T8, T9, T10, T11, T12, T13, T14, T15, T16, T17> setValue1(T1);
    descriptor: (Ljava/lang/Object;)Lorg/sireum/MBox17;
    flags: (0x0001) ACC_PUBLIC
    Code:
      stack=2, locals=2, args_size=2
         0: aload_0
         1: aload_1
         2: putfield      #108                // Field _value1:Ljava/lang/Object;
         5: aload_0
         6: areturn
      LineNumberTable:
        line 61: 0
      LocalVariableTable:
        Start  Length  Slot  Name   Signature
            0       7     0  this   Lorg/sireum/MBox17;
            0       7     1 value1   Ljava/lang/Object;
    Signature: #112                         // (TT1;)Lorg/sireum/MBox17<TT1;TT2;TT3;TT4;TT5;TT6;TT7;TT8;TT9;TT10;TT11;TT12;TT13;TT14;TT15;TT16;TT17;>;
    MethodParameters:
      Name                           Flags
      value1                         final

  public T2 value2();
    descriptor: ()Ljava/lang/Object;
    flags: (0x0001) ACC_PUBLIC
    Code:
      stack=1, locals=1, args_size=1
         0: aload_0
         1: getfield      #117                // Field _value2:Ljava/lang/Object;
         4: areturn
      LineNumberTable:
        line 61: 0
      LocalVariableTable:
        Start  Length  Slot  Name   Signature
            0       5     0  this   Lorg/sireum/MBox17;
    Signature: #115                         // ()TT2;

  public T2 getValue2();
    descriptor: ()Ljava/lang/Object;
    flags: (0x0001) ACC_PUBLIC
    Code:
      stack=1, locals=1, args_size=1
         0: aload_0
         1: getfield      #117                // Field _value2:Ljava/lang/Object;
         4: areturn
      LineNumberTable:
        line 61: 0
      LocalVariableTable:
        Start  Length  Slot  Name   Signature
            0       5     0  this   Lorg/sireum/MBox17;
    Signature: #115                         // ()TT2;

  public org.sireum.MBox17<T1, T2, T3, T4, T5, T6, T7, T8, T9, T10, T11, T12, T13, T14, T15, T16, T17> value2_$eq(T2);
    descriptor: (Ljava/lang/Object;)Lorg/sireum/MBox17;
    flags: (0x0001) ACC_PUBLIC
    Code:
      stack=2, locals=2, args_size=2
         0: aload_0
         1: aload_1
         2: putfield      #117                // Field _value2:Ljava/lang/Object;
         5: aload_0
         6: areturn
      LineNumberTable:
        line 61: 0
      LocalVariableTable:
        Start  Length  Slot  Name   Signature
            0       7     0  this   Lorg/sireum/MBox17;
            0       7     1 value2   Ljava/lang/Object;
    Signature: #120                         // (TT2;)Lorg/sireum/MBox17<TT1;TT2;TT3;TT4;TT5;TT6;TT7;TT8;TT9;TT10;TT11;TT12;TT13;TT14;TT15;TT16;TT17;>;
    MethodParameters:
      Name                           Flags
      value2                         final

  public org.sireum.MBox17<T1, T2, T3, T4, T5, T6, T7, T8, T9, T10, T11, T12, T13, T14, T15, T16, T17> setValue2(T2);
    descriptor: (Ljava/lang/Object;)Lorg/sireum/MBox17;
    flags: (0x0001) ACC_PUBLIC
    Code:
      stack=2, locals=2, args_size=2
         0: aload_0
         1: aload_1
         2: putfield      #117                // Field _value2:Ljava/lang/Object;
         5: aload_0
         6: areturn
      LineNumberTable:
        line 61: 0
      LocalVariableTable:
        Start  Length  Slot  Name   Signature
            0       7     0  this   Lorg/sireum/MBox17;
            0       7     1 value2   Ljava/lang/Object;
    Signature: #120                         // (TT2;)Lorg/sireum/MBox17<TT1;TT2;TT3;TT4;TT5;TT6;TT7;TT8;TT9;TT10;TT11;TT12;TT13;TT14;TT15;TT16;TT17;>;
    MethodParameters:
      Name                           Flags
      value2                         final

  public T3 value3();
    descriptor: ()Ljava/lang/Object;
    flags: (0x0001) ACC_PUBLIC
    Code:
      stack=1, locals=1, args_size=1
         0: aload_0
         1: getfield      #125                // Field _value3:Ljava/lang/Object;
         4: areturn
      LineNumberTable:
        line 61: 0
      LocalVariableTable:
        Start  Length  Slot  Name   Signature
            0       5     0  this   Lorg/sireum/MBox17;
    Signature: #123                         // ()TT3;

  public T3 getValue3();
    descriptor: ()Ljava/lang/Object;
    flags: (0x0001) ACC_PUBLIC
    Code:
      stack=1, locals=1, args_size=1
         0: aload_0
         1: getfield      #125                // Field _value3:Ljava/lang/Object;
         4: areturn
      LineNumberTable:
        line 61: 0
      LocalVariableTable:
        Start  Length  Slot  Name   Signature
            0       5     0  this   Lorg/sireum/MBox17;
    Signature: #123                         // ()TT3;

  public org.sireum.MBox17<T1, T2, T3, T4, T5, T6, T7, T8, T9, T10, T11, T12, T13, T14, T15, T16, T17> value3_$eq(T3);
    descriptor: (Ljava/lang/Object;)Lorg/sireum/MBox17;
    flags: (0x0001) ACC_PUBLIC
    Code:
      stack=2, locals=2, args_size=2
         0: aload_0
         1: aload_1
         2: putfield      #125                // Field _value3:Ljava/lang/Object;
         5: aload_0
         6: areturn
      LineNumberTable:
        line 61: 0
      LocalVariableTable:
        Start  Length  Slot  Name   Signature
            0       7     0  this   Lorg/sireum/MBox17;
            0       7     1 value3   Ljava/lang/Object;
    Signature: #128                         // (TT3;)Lorg/sireum/MBox17<TT1;TT2;TT3;TT4;TT5;TT6;TT7;TT8;TT9;TT10;TT11;TT12;TT13;TT14;TT15;TT16;TT17;>;
    MethodParameters:
      Name                           Flags
      value3                         final

  public org.sireum.MBox17<T1, T2, T3, T4, T5, T6, T7, T8, T9, T10, T11, T12, T13, T14, T15, T16, T17> setValue3(T3);
    descriptor: (Ljava/lang/Object;)Lorg/sireum/MBox17;
    flags: (0x0001) ACC_PUBLIC
    Code:
      stack=2, locals=2, args_size=2
         0: aload_0
         1: aload_1
         2: putfield      #125                // Field _value3:Ljava/lang/Object;
         5: aload_0
         6: areturn
      LineNumberTable:
        line 61: 0
      LocalVariableTable:
        Start  Length  Slot  Name   Signature
            0       7     0  this   Lorg/sireum/MBox17;
            0       7     1 value3   Ljava/lang/Object;
    Signature: #128                         // (TT3;)Lorg/sireum/MBox17<TT1;TT2;TT3;TT4;TT5;TT6;TT7;TT8;TT9;TT10;TT11;TT12;TT13;TT14;TT15;TT16;TT17;>;
    MethodParameters:
      Name                           Flags
      value3                         final

  public T4 value4();
    descriptor: ()Ljava/lang/Object;
    flags: (0x0001) ACC_PUBLIC
    Code:
      stack=1, locals=1, args_size=1
         0: aload_0
         1: getfield      #133                // Field _value4:Ljava/lang/Object;
         4: areturn
      LineNumberTable:
        line 61: 0
      LocalVariableTable:
        Start  Length  Slot  Name   Signature
            0       5     0  this   Lorg/sireum/MBox17;
    Signature: #131                         // ()TT4;

  public T4 getValue4();
    descriptor: ()Ljava/lang/Object;
    flags: (0x0001) ACC_PUBLIC
    Code:
      stack=1, locals=1, args_size=1
         0: aload_0
         1: getfield      #133                // Field _value4:Ljava/lang/Object;
         4: areturn
      LineNumberTable:
        line 61: 0
      LocalVariableTable:
        Start  Length  Slot  Name   Signature
            0       5     0  this   Lorg/sireum/MBox17;
    Signature: #131                         // ()TT4;

  public org.sireum.MBox17<T1, T2, T3, T4, T5, T6, T7, T8, T9, T10, T11, T12, T13, T14, T15, T16, T17> value4_$eq(T4);
    descriptor: (Ljava/lang/Object;)Lorg/sireum/MBox17;
    flags: (0x0001) ACC_PUBLIC
    Code:
      stack=2, locals=2, args_size=2
         0: aload_0
         1: aload_1
         2: putfield      #133                // Field _value4:Ljava/lang/Object;
         5: aload_0
         6: areturn
      LineNumberTable:
        line 61: 0
      LocalVariableTable:
        Start  Length  Slot  Name   Signature
            0       7     0  this   Lorg/sireum/MBox17;
            0       7     1 value4   Ljava/lang/Object;
    Signature: #136                         // (TT4;)Lorg/sireum/MBox17<TT1;TT2;TT3;TT4;TT5;TT6;TT7;TT8;TT9;TT10;TT11;TT12;TT13;TT14;TT15;TT16;TT17;>;
    MethodParameters:
      Name                           Flags
      value4                         final

  public org.sireum.MBox17<T1, T2, T3, T4, T5, T6, T7, T8, T9, T10, T11, T12, T13, T14, T15, T16, T17> setValue4(T4);
    descriptor: (Ljava/lang/Object;)Lorg/sireum/MBox17;
    flags: (0x0001) ACC_PUBLIC
    Code:
      stack=2, locals=2, args_size=2
         0: aload_0
         1: aload_1
         2: putfield      #133                // Field _value4:Ljava/lang/Object;
         5: aload_0
         6: areturn
      LineNumberTable:
        line 61: 0
      LocalVariableTable:
        Start  Length  Slot  Name   Signature
            0       7     0  this   Lorg/sireum/MBox17;
            0       7     1 value4   Ljava/lang/Object;
    Signature: #136                         // (TT4;)Lorg/sireum/MBox17<TT1;TT2;TT3;TT4;TT5;TT6;TT7;TT8;TT9;TT10;TT11;TT12;TT13;TT14;TT15;TT16;TT17;>;
    MethodParameters:
      Name                           Flags
      value4                         final

  public T5 value5();
    descriptor: ()Ljava/lang/Object;
    flags: (0x0001) ACC_PUBLIC
    Code:
      stack=1, locals=1, args_size=1
         0: aload_0
         1: getfield      #141                // Field _value5:Ljava/lang/Object;
         4: areturn
      LineNumberTable:
        line 61: 0
      LocalVariableTable:
        Start  Length  Slot  Name   Signature
            0       5     0  this   Lorg/sireum/MBox17;
    Signature: #139                         // ()TT5;

  public T5 getValue5();
    descriptor: ()Ljava/lang/Object;
    flags: (0x0001) ACC_PUBLIC
    Code:
      stack=1, locals=1, args_size=1
         0: aload_0
         1: getfield      #141                // Field _value5:Ljava/lang/Object;
         4: areturn
      LineNumberTable:
        line 61: 0
      LocalVariableTable:
        Start  Length  Slot  Name   Signature
            0       5     0  this   Lorg/sireum/MBox17;
    Signature: #139                         // ()TT5;

  public org.sireum.MBox17<T1, T2, T3, T4, T5, T6, T7, T8, T9, T10, T11, T12, T13, T14, T15, T16, T17> value5_$eq(T5);
    descriptor: (Ljava/lang/Object;)Lorg/sireum/MBox17;
    flags: (0x0001) ACC_PUBLIC
    Code:
      stack=2, locals=2, args_size=2
         0: aload_0
         1: aload_1
         2: putfield      #141                // Field _value5:Ljava/lang/Object;
         5: aload_0
         6: areturn
      LineNumberTable:
        line 61: 0
      LocalVariableTable:
        Start  Length  Slot  Name   Signature
            0       7     0  this   Lorg/sireum/MBox17;
            0       7     1 value5   Ljava/lang/Object;
    Signature: #144                         // (TT5;)Lorg/sireum/MBox17<TT1;TT2;TT3;TT4;TT5;TT6;TT7;TT8;TT9;TT10;TT11;TT12;TT13;TT14;TT15;TT16;TT17;>;
    MethodParameters:
      Name                           Flags
      value5                         final

  public org.sireum.MBox17<T1, T2, T3, T4, T5, T6, T7, T8, T9, T10, T11, T12, T13, T14, T15, T16, T17> setValue5(T5);
    descriptor: (Ljava/lang/Object;)Lorg/sireum/MBox17;
    flags: (0x0001) ACC_PUBLIC
    Code:
      stack=2, locals=2, args_size=2
         0: aload_0
         1: aload_1
         2: putfield      #141                // Field _value5:Ljava/lang/Object;
         5: aload_0
         6: areturn
      LineNumberTable:
        line 61: 0
      LocalVariableTable:
        Start  Length  Slot  Name   Signature
            0       7     0  this   Lorg/sireum/MBox17;
            0       7     1 value5   Ljava/lang/Object;
    Signature: #144                         // (TT5;)Lorg/sireum/MBox17<TT1;TT2;TT3;TT4;TT5;TT6;TT7;TT8;TT9;TT10;TT11;TT12;TT13;TT14;TT15;TT16;TT17;>;
    MethodParameters:
      Name                           Flags
      value5                         final

  public T6 value6();
    descriptor: ()Ljava/lang/Object;
    flags: (0x0001) ACC_PUBLIC
    Code:
      stack=1, locals=1, args_size=1
         0: aload_0
         1: getfield      #149                // Field _value6:Ljava/lang/Object;
         4: areturn
      LineNumberTable:
        line 61: 0
      LocalVariableTable:
        Start  Length  Slot  Name   Signature
            0       5     0  this   Lorg/sireum/MBox17;
    Signature: #147                         // ()TT6;

  public T6 getValue6();
    descriptor: ()Ljava/lang/Object;
    flags: (0x0001) ACC_PUBLIC
    Code:
      stack=1, locals=1, args_size=1
         0: aload_0
         1: getfield      #149                // Field _value6:Ljava/lang/Object;
         4: areturn
      LineNumberTable:
        line 61: 0
      LocalVariableTable:
        Start  Length  Slot  Name   Signature
            0       5     0  this   Lorg/sireum/MBox17;
    Signature: #147                         // ()TT6;

  public org.sireum.MBox17<T1, T2, T3, T4, T5, T6, T7, T8, T9, T10, T11, T12, T13, T14, T15, T16, T17> value6_$eq(T6);
    descriptor: (Ljava/lang/Object;)Lorg/sireum/MBox17;
    flags: (0x0001) ACC_PUBLIC
    Code:
      stack=2, locals=2, args_size=2
         0: aload_0
         1: aload_1
         2: putfield      #149                // Field _value6:Ljava/lang/Object;
         5: aload_0
         6: areturn
      LineNumberTable:
        line 61: 0
      LocalVariableTable:
        Start  Length  Slot  Name   Signature
            0       7     0  this   Lorg/sireum/MBox17;
            0       7     1 value6   Ljava/lang/Object;
    Signature: #152                         // (TT6;)Lorg/sireum/MBox17<TT1;TT2;TT3;TT4;TT5;TT6;TT7;TT8;TT9;TT10;TT11;TT12;TT13;TT14;TT15;TT16;TT17;>;
    MethodParameters:
      Name                           Flags
      value6                         final

  public org.sireum.MBox17<T1, T2, T3, T4, T5, T6, T7, T8, T9, T10, T11, T12, T13, T14, T15, T16, T17> setValue6(T6);
    descriptor: (Ljava/lang/Object;)Lorg/sireum/MBox17;
    flags: (0x0001) ACC_PUBLIC
    Code:
      stack=2, locals=2, args_size=2
         0: aload_0
         1: aload_1
         2: putfield      #149                // Field _value6:Ljava/lang/Object;
         5: aload_0
         6: areturn
      LineNumberTable:
        line 61: 0
      LocalVariableTable:
        Start  Length  Slot  Name   Signature
            0       7     0  this   Lorg/sireum/MBox17;
            0       7     1 value6   Ljava/lang/Object;
    Signature: #152                         // (TT6;)Lorg/sireum/MBox17<TT1;TT2;TT3;TT4;TT5;TT6;TT7;TT8;TT9;TT10;TT11;TT12;TT13;TT14;TT15;TT16;TT17;>;
    MethodParameters:
      Name                           Flags
      value6                         final

  public T7 value7();
    descriptor: ()Ljava/lang/Object;
    flags: (0x0001) ACC_PUBLIC
    Code:
      stack=1, locals=1, args_size=1
         0: aload_0
         1: getfield      #157                // Field _value7:Ljava/lang/Object;
         4: areturn
      LineNumberTable:
        line 61: 0
      LocalVariableTable:
        Start  Length  Slot  Name   Signature
            0       5     0  this   Lorg/sireum/MBox17;
    Signature: #155                         // ()TT7;

  public T7 getValue7();
    descriptor: ()Ljava/lang/Object;
    flags: (0x0001) ACC_PUBLIC
    Code:
      stack=1, locals=1, args_size=1
         0: aload_0
         1: getfield      #157                // Field _value7:Ljava/lang/Object;
         4: areturn
      LineNumberTable:
        line 61: 0
      LocalVariableTable:
        Start  Length  Slot  Name   Signature
            0       5     0  this   Lorg/sireum/MBox17;
    Signature: #155                         // ()TT7;

  public org.sireum.MBox17<T1, T2, T3, T4, T5, T6, T7, T8, T9, T10, T11, T12, T13, T14, T15, T16, T17> value7_$eq(T7);
    descriptor: (Ljava/lang/Object;)Lorg/sireum/MBox17;
    flags: (0x0001) ACC_PUBLIC
    Code:
      stack=2, locals=2, args_size=2
         0: aload_0
         1: aload_1
         2: putfield      #157                // Field _value7:Ljava/lang/Object;
         5: aload_0
         6: areturn
      LineNumberTable:
        line 61: 0
      LocalVariableTable:
        Start  Length  Slot  Name   Signature
            0       7     0  this   Lorg/sireum/MBox17;
            0       7     1 value7   Ljava/lang/Object;
    Signature: #160                         // (TT7;)Lorg/sireum/MBox17<TT1;TT2;TT3;TT4;TT5;TT6;TT7;TT8;TT9;TT10;TT11;TT12;TT13;TT14;TT15;TT16;TT17;>;
    MethodParameters:
      Name                           Flags
      value7                         final

  public org.sireum.MBox17<T1, T2, T3, T4, T5, T6, T7, T8, T9, T10, T11, T12, T13, T14, T15, T16, T17> setValue7(T7);
    descriptor: (Ljava/lang/Object;)Lorg/sireum/MBox17;
    flags: (0x0001) ACC_PUBLIC
    Code:
      stack=2, locals=2, args_size=2
         0: aload_0
         1: aload_1
         2: putfield      #157                // Field _value7:Ljava/lang/Object;
         5: aload_0
         6: areturn
      LineNumberTable:
        line 61: 0
      LocalVariableTable:
        Start  Length  Slot  Name   Signature
            0       7     0  this   Lorg/sireum/MBox17;
            0       7     1 value7   Ljava/lang/Object;
    Signature: #160                         // (TT7;)Lorg/sireum/MBox17<TT1;TT2;TT3;TT4;TT5;TT6;TT7;TT8;TT9;TT10;TT11;TT12;TT13;TT14;TT15;TT16;TT17;>;
    MethodParameters:
      Name                           Flags
      value7                         final

  public T8 value8();
    descriptor: ()Ljava/lang/Object;
    flags: (0x0001) ACC_PUBLIC
    Code:
      stack=1, locals=1, args_size=1
         0: aload_0
         1: getfield      #165                // Field _value8:Ljava/lang/Object;
         4: areturn
      LineNumberTable:
        line 61: 0
      LocalVariableTable:
        Start  Length  Slot  Name   Signature
            0       5     0  this   Lorg/sireum/MBox17;
    Signature: #163                         // ()TT8;

  public T8 getValue8();
    descriptor: ()Ljava/lang/Object;
    flags: (0x0001) ACC_PUBLIC
    Code:
      stack=1, locals=1, args_size=1
         0: aload_0
         1: getfield      #165                // Field _value8:Ljava/lang/Object;
         4: areturn
      LineNumberTable:
        line 61: 0
      LocalVariableTable:
        Start  Length  Slot  Name   Signature
            0       5     0  this   Lorg/sireum/MBox17;
    Signature: #163                         // ()TT8;

  public org.sireum.MBox17<T1, T2, T3, T4, T5, T6, T7, T8, T9, T10, T11, T12, T13, T14, T15, T16, T17> value8_$eq(T8);
    descriptor: (Ljava/lang/Object;)Lorg/sireum/MBox17;
    flags: (0x0001) ACC_PUBLIC
    Code:
      stack=2, locals=2, args_size=2
         0: aload_0
         1: aload_1
         2: putfield      #165                // Field _value8:Ljava/lang/Object;
         5: aload_0
         6: areturn
      LineNumberTable:
        line 61: 0
      LocalVariableTable:
        Start  Length  Slot  Name   Signature
            0       7     0  this   Lorg/sireum/MBox17;
            0       7     1 value8   Ljava/lang/Object;
    Signature: #168                         // (TT8;)Lorg/sireum/MBox17<TT1;TT2;TT3;TT4;TT5;TT6;TT7;TT8;TT9;TT10;TT11;TT12;TT13;TT14;TT15;TT16;TT17;>;
    MethodParameters:
      Name                           Flags
      value8                         final

  public org.sireum.MBox17<T1, T2, T3, T4, T5, T6, T7, T8, T9, T10, T11, T12, T13, T14, T15, T16, T17> setValue8(T8);
    descriptor: (Ljava/lang/Object;)Lorg/sireum/MBox17;
    flags: (0x0001) ACC_PUBLIC
    Code:
      stack=2, locals=2, args_size=2
         0: aload_0
         1: aload_1
         2: putfield      #165                // Field _value8:Ljava/lang/Object;
         5: aload_0
         6: areturn
      LineNumberTable:
        line 61: 0
      LocalVariableTable:
        Start  Length  Slot  Name   Signature
            0       7     0  this   Lorg/sireum/MBox17;
            0       7     1 value8   Ljava/lang/Object;
    Signature: #168                         // (TT8;)Lorg/sireum/MBox17<TT1;TT2;TT3;TT4;TT5;TT6;TT7;TT8;TT9;TT10;TT11;TT12;TT13;TT14;TT15;TT16;TT17;>;
    MethodParameters:
      Name                           Flags
      value8                         final

  public T9 value9();
    descriptor: ()Ljava/lang/Object;
    flags: (0x0001) ACC_PUBLIC
    Code:
      stack=1, locals=1, args_size=1
         0: aload_0
         1: getfield      #173                // Field _value9:Ljava/lang/Object;
         4: areturn
      LineNumberTable:
        line 61: 0
      LocalVariableTable:
        Start  Length  Slot  Name   Signature
            0       5     0  this   Lorg/sireum/MBox17;
    Signature: #171                         // ()TT9;

  public T9 getValue9();
    descriptor: ()Ljava/lang/Object;
    flags: (0x0001) ACC_PUBLIC
    Code:
      stack=1, locals=1, args_size=1
         0: aload_0
         1: getfield      #173                // Field _value9:Ljava/lang/Object;
         4: areturn
      LineNumberTable:
        line 61: 0
      LocalVariableTable:
        Start  Length  Slot  Name   Signature
            0       5     0  this   Lorg/sireum/MBox17;
    Signature: #171                         // ()TT9;

  public org.sireum.MBox17<T1, T2, T3, T4, T5, T6, T7, T8, T9, T10, T11, T12, T13, T14, T15, T16, T17> value9_$eq(T9);
    descriptor: (Ljava/lang/Object;)Lorg/sireum/MBox17;
    flags: (0x0001) ACC_PUBLIC
    Code:
      stack=2, locals=2, args_size=2
         0: aload_0
         1: aload_1
         2: putfield      #173                // Field _value9:Ljava/lang/Object;
         5: aload_0
         6: areturn
      LineNumberTable:
        line 61: 0
      LocalVariableTable:
        Start  Length  Slot  Name   Signature
            0       7     0  this   Lorg/sireum/MBox17;
            0       7     1 value9   Ljava/lang/Object;
    Signature: #176                         // (TT9;)Lorg/sireum/MBox17<TT1;TT2;TT3;TT4;TT5;TT6;TT7;TT8;TT9;TT10;TT11;TT12;TT13;TT14;TT15;TT16;TT17;>;
    MethodParameters:
      Name                           Flags
      value9                         final

  public org.sireum.MBox17<T1, T2, T3, T4, T5, T6, T7, T8, T9, T10, T11, T12, T13, T14, T15, T16, T17> setValue9(T9);
    descriptor: (Ljava/lang/Object;)Lorg/sireum/MBox17;
    flags: (0x0001) ACC_PUBLIC
    Code:
      stack=2, locals=2, args_size=2
         0: aload_0
         1: aload_1
         2: putfield      #173                // Field _value9:Ljava/lang/Object;
         5: aload_0
         6: areturn
      LineNumberTable:
        line 61: 0
      LocalVariableTable:
        Start  Length  Slot  Name   Signature
            0       7     0  this   Lorg/sireum/MBox17;
            0       7     1 value9   Ljava/lang/Object;
    Signature: #176                         // (TT9;)Lorg/sireum/MBox17<TT1;TT2;TT3;TT4;TT5;TT6;TT7;TT8;TT9;TT10;TT11;TT12;TT13;TT14;TT15;TT16;TT17;>;
    MethodParameters:
      Name                           Flags
      value9                         final

  public T10 value10();
    descriptor: ()Ljava/lang/Object;
    flags: (0x0001) ACC_PUBLIC
    Code:
      stack=1, locals=1, args_size=1
         0: aload_0
         1: getfield      #181                // Field _value10:Ljava/lang/Object;
         4: areturn
      LineNumberTable:
        line 61: 0
      LocalVariableTable:
        Start  Length  Slot  Name   Signature
            0       5     0  this   Lorg/sireum/MBox17;
    Signature: #179                         // ()TT10;

  public T10 getValue10();
    descriptor: ()Ljava/lang/Object;
    flags: (0x0001) ACC_PUBLIC
    Code:
      stack=1, locals=1, args_size=1
         0: aload_0
         1: getfield      #181                // Field _value10:Ljava/lang/Object;
         4: areturn
      LineNumberTable:
        line 61: 0
      LocalVariableTable:
        Start  Length  Slot  Name   Signature
            0       5     0  this   Lorg/sireum/MBox17;
    Signature: #179                         // ()TT10;

  public org.sireum.MBox17<T1, T2, T3, T4, T5, T6, T7, T8, T9, T10, T11, T12, T13, T14, T15, T16, T17> value10_$eq(T10);
    descriptor: (Ljava/lang/Object;)Lorg/sireum/MBox17;
    flags: (0x0001) ACC_PUBLIC
    Code:
      stack=2, locals=2, args_size=2
         0: aload_0
         1: aload_1
         2: putfield      #181                // Field _value10:Ljava/lang/Object;
         5: aload_0
         6: areturn
      LineNumberTable:
        line 61: 0
      LocalVariableTable:
        Start  Length  Slot  Name   Signature
            0       7     0  this   Lorg/sireum/MBox17;
            0       7     1 value10   Ljava/lang/Object;
    Signature: #184                         // (TT10;)Lorg/sireum/MBox17<TT1;TT2;TT3;TT4;TT5;TT6;TT7;TT8;TT9;TT10;TT11;TT12;TT13;TT14;TT15;TT16;TT17;>;
    MethodParameters:
      Name                           Flags
      value10                        final

  public org.sireum.MBox17<T1, T2, T3, T4, T5, T6, T7, T8, T9, T10, T11, T12, T13, T14, T15, T16, T17> setValue10(T10);
    descriptor: (Ljava/lang/Object;)Lorg/sireum/MBox17;
    flags: (0x0001) ACC_PUBLIC
    Code:
      stack=2, locals=2, args_size=2
         0: aload_0
         1: aload_1
         2: putfield      #181                // Field _value10:Ljava/lang/Object;
         5: aload_0
         6: areturn
      LineNumberTable:
        line 61: 0
      LocalVariableTable:
        Start  Length  Slot  Name   Signature
            0       7     0  this   Lorg/sireum/MBox17;
            0       7     1 value10   Ljava/lang/Object;
    Signature: #184                         // (TT10;)Lorg/sireum/MBox17<TT1;TT2;TT3;TT4;TT5;TT6;TT7;TT8;TT9;TT10;TT11;TT12;TT13;TT14;TT15;TT16;TT17;>;
    MethodParameters:
      Name                           Flags
      value10                        final

  public T11 value11();
    descriptor: ()Ljava/lang/Object;
    flags: (0x0001) ACC_PUBLIC
    Code:
      stack=1, locals=1, args_size=1
         0: aload_0
         1: getfield      #189                // Field _value11:Ljava/lang/Object;
         4: areturn
      LineNumberTable:
        line 61: 0
      LocalVariableTable:
        Start  Length  Slot  Name   Signature
            0       5     0  this   Lorg/sireum/MBox17;
    Signature: #187                         // ()TT11;

  public T11 getValue11();
    descriptor: ()Ljava/lang/Object;
    flags: (0x0001) ACC_PUBLIC
    Code:
      stack=1, locals=1, args_size=1
         0: aload_0
         1: getfield      #189                // Field _value11:Ljava/lang/Object;
         4: areturn
      LineNumberTable:
        line 61: 0
      LocalVariableTable:
        Start  Length  Slot  Name   Signature
            0       5     0  this   Lorg/sireum/MBox17;
    Signature: #187                         // ()TT11;

  public org.sireum.MBox17<T1, T2, T3, T4, T5, T6, T7, T8, T9, T10, T11, T12, T13, T14, T15, T16, T17> value11_$eq(T11);
    descriptor: (Ljava/lang/Object;)Lorg/sireum/MBox17;
    flags: (0x0001) ACC_PUBLIC
    Code:
      stack=2, locals=2, args_size=2
         0: aload_0
         1: aload_1
         2: putfield      #189                // Field _value11:Ljava/lang/Object;
         5: aload_0
         6: areturn
      LineNumberTable:
        line 61: 0
      LocalVariableTable:
        Start  Length  Slot  Name   Signature
            0       7     0  this   Lorg/sireum/MBox17;
            0       7     1 value11   Ljava/lang/Object;
    Signature: #192                         // (TT11;)Lorg/sireum/MBox17<TT1;TT2;TT3;TT4;TT5;TT6;TT7;TT8;TT9;TT10;TT11;TT12;TT13;TT14;TT15;TT16;TT17;>;
    MethodParameters:
      Name                           Flags
      value11                        final

  public org.sireum.MBox17<T1, T2, T3, T4, T5, T6, T7, T8, T9, T10, T11, T12, T13, T14, T15, T16, T17> setValue11(T11);
    descriptor: (Ljava/lang/Object;)Lorg/sireum/MBox17;
    flags: (0x0001) ACC_PUBLIC
    Code:
      stack=2, locals=2, args_size=2
         0: aload_0
         1: aload_1
         2: putfield      #189                // Field _value11:Ljava/lang/Object;
         5: aload_0
         6: areturn
      LineNumberTable:
        line 61: 0
      LocalVariableTable:
        Start  Length  Slot  Name   Signature
            0       7     0  this   Lorg/sireum/MBox17;
            0       7     1 value11   Ljava/lang/Object;
    Signature: #192                         // (TT11;)Lorg/sireum/MBox17<TT1;TT2;TT3;TT4;TT5;TT6;TT7;TT8;TT9;TT10;TT11;TT12;TT13;TT14;TT15;TT16;TT17;>;
    MethodParameters:
      Name                           Flags
      value11                        final

  public T12 value12();
    descriptor: ()Ljava/lang/Object;
    flags: (0x0001) ACC_PUBLIC
    Code:
      stack=1, locals=1, args_size=1
         0: aload_0
         1: getfield      #197                // Field _value12:Ljava/lang/Object;
         4: areturn
      LineNumberTable:
        line 61: 0
      LocalVariableTable:
        Start  Length  Slot  Name   Signature
            0       5     0  this   Lorg/sireum/MBox17;
    Signature: #195                         // ()TT12;

  public T12 getValue12();
    descriptor: ()Ljava/lang/Object;
    flags: (0x0001) ACC_PUBLIC
    Code:
      stack=1, locals=1, args_size=1
         0: aload_0
         1: getfield      #197                // Field _value12:Ljava/lang/Object;
         4: areturn
      LineNumberTable:
        line 61: 0
      LocalVariableTable:
        Start  Length  Slot  Name   Signature
            0       5     0  this   Lorg/sireum/MBox17;
    Signature: #195                         // ()TT12;

  public org.sireum.MBox17<T1, T2, T3, T4, T5, T6, T7, T8, T9, T10, T11, T12, T13, T14, T15, T16, T17> value12_$eq(T12);
    descriptor: (Ljava/lang/Object;)Lorg/sireum/MBox17;
    flags: (0x0001) ACC_PUBLIC
    Code:
      stack=2, locals=2, args_size=2
         0: aload_0
         1: aload_1
         2: putfield      #197                // Field _value12:Ljava/lang/Object;
         5: aload_0
         6: areturn
      LineNumberTable:
        line 61: 0
      LocalVariableTable:
        Start  Length  Slot  Name   Signature
            0       7     0  this   Lorg/sireum/MBox17;
            0       7     1 value12   Ljava/lang/Object;
    Signature: #200                         // (TT12;)Lorg/sireum/MBox17<TT1;TT2;TT3;TT4;TT5;TT6;TT7;TT8;TT9;TT10;TT11;TT12;TT13;TT14;TT15;TT16;TT17;>;
    MethodParameters:
      Name                           Flags
      value12                        final

  public org.sireum.MBox17<T1, T2, T3, T4, T5, T6, T7, T8, T9, T10, T11, T12, T13, T14, T15, T16, T17> setValue12(T12);
    descriptor: (Ljava/lang/Object;)Lorg/sireum/MBox17;
    flags: (0x0001) ACC_PUBLIC
    Code:
      stack=2, locals=2, args_size=2
         0: aload_0
         1: aload_1
         2: putfield      #197                // Field _value12:Ljava/lang/Object;
         5: aload_0
         6: areturn
      LineNumberTable:
        line 61: 0
      LocalVariableTable:
        Start  Length  Slot  Name   Signature
            0       7     0  this   Lorg/sireum/MBox17;
            0       7     1 value12   Ljava/lang/Object;
    Signature: #200                         // (TT12;)Lorg/sireum/MBox17<TT1;TT2;TT3;TT4;TT5;TT6;TT7;TT8;TT9;TT10;TT11;TT12;TT13;TT14;TT15;TT16;TT17;>;
    MethodParameters:
      Name                           Flags
      value12                        final

  public T13 value13();
    descriptor: ()Ljava/lang/Object;
    flags: (0x0001) ACC_PUBLIC
    Code:
      stack=1, locals=1, args_size=1
         0: aload_0
         1: getfield      #205                // Field _value13:Ljava/lang/Object;
         4: areturn
      LineNumberTable:
        line 61: 0
      LocalVariableTable:
        Start  Length  Slot  Name   Signature
            0       5     0  this   Lorg/sireum/MBox17;
    Signature: #203                         // ()TT13;

  public T13 getValue13();
    descriptor: ()Ljava/lang/Object;
    flags: (0x0001) ACC_PUBLIC
    Code:
      stack=1, locals=1, args_size=1
         0: aload_0
         1: getfield      #205                // Field _value13:Ljava/lang/Object;
         4: areturn
      LineNumberTable:
        line 61: 0
      LocalVariableTable:
        Start  Length  Slot  Name   Signature
            0       5     0  this   Lorg/sireum/MBox17;
    Signature: #203                         // ()TT13;

  public org.sireum.MBox17<T1, T2, T3, T4, T5, T6, T7, T8, T9, T10, T11, T12, T13, T14, T15, T16, T17> value13_$eq(T13);
    descriptor: (Ljava/lang/Object;)Lorg/sireum/MBox17;
    flags: (0x0001) ACC_PUBLIC
    Code:
      stack=2, locals=2, args_size=2
         0: aload_0
         1: aload_1
         2: putfield      #205                // Field _value13:Ljava/lang/Object;
         5: aload_0
         6: areturn
      LineNumberTable:
        line 61: 0
      LocalVariableTable:
        Start  Length  Slot  Name   Signature
            0       7     0  this   Lorg/sireum/MBox17;
            0       7     1 value13   Ljava/lang/Object;
    Signature: #208                         // (TT13;)Lorg/sireum/MBox17<TT1;TT2;TT3;TT4;TT5;TT6;TT7;TT8;TT9;TT10;TT11;TT12;TT13;TT14;TT15;TT16;TT17;>;
    MethodParameters:
      Name                           Flags
      value13                        final

  public org.sireum.MBox17<T1, T2, T3, T4, T5, T6, T7, T8, T9, T10, T11, T12, T13, T14, T15, T16, T17> setValue13(T13);
    descriptor: (Ljava/lang/Object;)Lorg/sireum/MBox17;
    flags: (0x0001) ACC_PUBLIC
    Code:
      stack=2, locals=2, args_size=2
         0: aload_0
         1: aload_1
         2: putfield      #205                // Field _value13:Ljava/lang/Object;
         5: aload_0
         6: areturn
      LineNumberTable:
        line 61: 0
      LocalVariableTable:
        Start  Length  Slot  Name   Signature
            0       7     0  this   Lorg/sireum/MBox17;
            0       7     1 value13   Ljava/lang/Object;
    Signature: #208                         // (TT13;)Lorg/sireum/MBox17<TT1;TT2;TT3;TT4;TT5;TT6;TT7;TT8;TT9;TT10;TT11;TT12;TT13;TT14;TT15;TT16;TT17;>;
    MethodParameters:
      Name                           Flags
      value13                        final

  public T14 value14();
    descriptor: ()Ljava/lang/Object;
    flags: (0x0001) ACC_PUBLIC
    Code:
      stack=1, locals=1, args_size=1
         0: aload_0
         1: getfield      #213                // Field _value14:Ljava/lang/Object;
         4: areturn
      LineNumberTable:
        line 61: 0
      LocalVariableTable:
        Start  Length  Slot  Name   Signature
            0       5     0  this   Lorg/sireum/MBox17;
    Signature: #211                         // ()TT14;

  public T14 getValue14();
    descriptor: ()Ljava/lang/Object;
    flags: (0x0001) ACC_PUBLIC
    Code:
      stack=1, locals=1, args_size=1
         0: aload_0
         1: getfield      #213                // Field _value14:Ljava/lang/Object;
         4: areturn
      LineNumberTable:
        line 61: 0
      LocalVariableTable:
        Start  Length  Slot  Name   Signature
            0       5     0  this   Lorg/sireum/MBox17;
    Signature: #211                         // ()TT14;

  public org.sireum.MBox17<T1, T2, T3, T4, T5, T6, T7, T8, T9, T10, T11, T12, T13, T14, T15, T16, T17> value14_$eq(T14);
    descriptor: (Ljava/lang/Object;)Lorg/sireum/MBox17;
    flags: (0x0001) ACC_PUBLIC
    Code:
      stack=2, locals=2, args_size=2
         0: aload_0
         1: aload_1
         2: putfield      #213                // Field _value14:Ljava/lang/Object;
         5: aload_0
         6: areturn
      LineNumberTable:
        line 61: 0
      LocalVariableTable:
        Start  Length  Slot  Name   Signature
            0       7     0  this   Lorg/sireum/MBox17;
            0       7     1 value14   Ljava/lang/Object;
    Signature: #216                         // (TT14;)Lorg/sireum/MBox17<TT1;TT2;TT3;TT4;TT5;TT6;TT7;TT8;TT9;TT10;TT11;TT12;TT13;TT14;TT15;TT16;TT17;>;
    MethodParameters:
      Name                           Flags
      value14                        final

  public org.sireum.MBox17<T1, T2, T3, T4, T5, T6, T7, T8, T9, T10, T11, T12, T13, T14, T15, T16, T17> setValue14(T14);
    descriptor: (Ljava/lang/Object;)Lorg/sireum/MBox17;
    flags: (0x0001) ACC_PUBLIC
    Code:
      stack=2, locals=2, args_size=2
         0: aload_0
         1: aload_1
         2: putfield      #213                // Field _value14:Ljava/lang/Object;
         5: aload_0
         6: areturn
      LineNumberTable:
        line 61: 0
      LocalVariableTable:
        Start  Length  Slot  Name   Signature
            0       7     0  this   Lorg/sireum/MBox17;
            0       7     1 value14   Ljava/lang/Object;
    Signature: #216                         // (TT14;)Lorg/sireum/MBox17<TT1;TT2;TT3;TT4;TT5;TT6;TT7;TT8;TT9;TT10;TT11;TT12;TT13;TT14;TT15;TT16;TT17;>;
    MethodParameters:
      Name                           Flags
      value14                        final

  public T15 value15();
    descriptor: ()Ljava/lang/Object;
    flags: (0x0001) ACC_PUBLIC
    Code:
      stack=1, locals=1, args_size=1
         0: aload_0
         1: getfield      #221                // Field _value15:Ljava/lang/Object;
         4: areturn
      LineNumberTable:
        line 61: 0
      LocalVariableTable:
        Start  Length  Slot  Name   Signature
            0       5     0  this   Lorg/sireum/MBox17;
    Signature: #219                         // ()TT15;

  public T15 getValue15();
    descriptor: ()Ljava/lang/Object;
    flags: (0x0001) ACC_PUBLIC
    Code:
      stack=1, locals=1, args_size=1
         0: aload_0
         1: getfield      #221                // Field _value15:Ljava/lang/Object;
         4: areturn
      LineNumberTable:
        line 61: 0
      LocalVariableTable:
        Start  Length  Slot  Name   Signature
            0       5     0  this   Lorg/sireum/MBox17;
    Signature: #219                         // ()TT15;

  public org.sireum.MBox17<T1, T2, T3, T4, T5, T6, T7, T8, T9, T10, T11, T12, T13, T14, T15, T16, T17> value15_$eq(T15);
    descriptor: (Ljava/lang/Object;)Lorg/sireum/MBox17;
    flags: (0x0001) ACC_PUBLIC
    Code:
      stack=2, locals=2, args_size=2
         0: aload_0
         1: aload_1
         2: putfield      #221                // Field _value15:Ljava/lang/Object;
         5: aload_0
         6: areturn
      LineNumberTable:
        line 61: 0
      LocalVariableTable:
        Start  Length  Slot  Name   Signature
            0       7     0  this   Lorg/sireum/MBox17;
            0       7     1 value15   Ljava/lang/Object;
    Signature: #224                         // (TT15;)Lorg/sireum/MBox17<TT1;TT2;TT3;TT4;TT5;TT6;TT7;TT8;TT9;TT10;TT11;TT12;TT13;TT14;TT15;TT16;TT17;>;
    MethodParameters:
      Name                           Flags
      value15                        final

  public org.sireum.MBox17<T1, T2, T3, T4, T5, T6, T7, T8, T9, T10, T11, T12, T13, T14, T15, T16, T17> setValue15(T15);
    descriptor: (Ljava/lang/Object;)Lorg/sireum/MBox17;
    flags: (0x0001) ACC_PUBLIC
    Code:
      stack=2, locals=2, args_size=2
         0: aload_0
         1: aload_1
         2: putfield      #221                // Field _value15:Ljava/lang/Object;
         5: aload_0
         6: areturn
      LineNumberTable:
        line 61: 0
      LocalVariableTable:
        Start  Length  Slot  Name   Signature
            0       7     0  this   Lorg/sireum/MBox17;
            0       7     1 value15   Ljava/lang/Object;
    Signature: #224                         // (TT15;)Lorg/sireum/MBox17<TT1;TT2;TT3;TT4;TT5;TT6;TT7;TT8;TT9;TT10;TT11;TT12;TT13;TT14;TT15;TT16;TT17;>;
    MethodParameters:
      Name                           Flags
      value15                        final

  public T16 value16();
    descriptor: ()Ljava/lang/Object;
    flags: (0x0001) ACC_PUBLIC
    Code:
      stack=1, locals=1, args_size=1
         0: aload_0
         1: getfield      #229                // Field _value16:Ljava/lang/Object;
         4: areturn
      LineNumberTable:
        line 61: 0
      LocalVariableTable:
        Start  Length  Slot  Name   Signature
            0       5     0  this   Lorg/sireum/MBox17;
    Signature: #227                         // ()TT16;

  public T16 getValue16();
    descriptor: ()Ljava/lang/Object;
    flags: (0x0001) ACC_PUBLIC
    Code:
      stack=1, locals=1, args_size=1
         0: aload_0
         1: getfield      #229                // Field _value16:Ljava/lang/Object;
         4: areturn
      LineNumberTable:
        line 61: 0
      LocalVariableTable:
        Start  Length  Slot  Name   Signature
            0       5     0  this   Lorg/sireum/MBox17;
    Signature: #227                         // ()TT16;

  public org.sireum.MBox17<T1, T2, T3, T4, T5, T6, T7, T8, T9, T10, T11, T12, T13, T14, T15, T16, T17> value16_$eq(T16);
    descriptor: (Ljava/lang/Object;)Lorg/sireum/MBox17;
    flags: (0x0001) ACC_PUBLIC
    Code:
      stack=2, locals=2, args_size=2
         0: aload_0
         1: aload_1
         2: putfield      #229                // Field _value16:Ljava/lang/Object;
         5: aload_0
         6: areturn
      LineNumberTable:
        line 61: 0
      LocalVariableTable:
        Start  Length  Slot  Name   Signature
            0       7     0  this   Lorg/sireum/MBox17;
            0       7     1 value16   Ljava/lang/Object;
    Signature: #232                         // (TT16;)Lorg/sireum/MBox17<TT1;TT2;TT3;TT4;TT5;TT6;TT7;TT8;TT9;TT10;TT11;TT12;TT13;TT14;TT15;TT16;TT17;>;
    MethodParameters:
      Name                           Flags
      value16                        final

  public org.sireum.MBox17<T1, T2, T3, T4, T5, T6, T7, T8, T9, T10, T11, T12, T13, T14, T15, T16, T17> setValue16(T16);
    descriptor: (Ljava/lang/Object;)Lorg/sireum/MBox17;
    flags: (0x0001) ACC_PUBLIC
    Code:
      stack=2, locals=2, args_size=2
         0: aload_0
         1: aload_1
         2: putfield      #229                // Field _value16:Ljava/lang/Object;
         5: aload_0
         6: areturn
      LineNumberTable:
        line 61: 0
      LocalVariableTable:
        Start  Length  Slot  Name   Signature
            0       7     0  this   Lorg/sireum/MBox17;
            0       7     1 value16   Ljava/lang/Object;
    Signature: #232                         // (TT16;)Lorg/sireum/MBox17<TT1;TT2;TT3;TT4;TT5;TT6;TT7;TT8;TT9;TT10;TT11;TT12;TT13;TT14;TT15;TT16;TT17;>;
    MethodParameters:
      Name                           Flags
      value16                        final

  public T17 value17();
    descriptor: ()Ljava/lang/Object;
    flags: (0x0001) ACC_PUBLIC
    Code:
      stack=1, locals=1, args_size=1
         0: aload_0
         1: getfield      #237                // Field _value17:Ljava/lang/Object;
         4: areturn
      LineNumberTable:
        line 61: 0
      LocalVariableTable:
        Start  Length  Slot  Name   Signature
            0       5     0  this   Lorg/sireum/MBox17;
    Signature: #235                         // ()TT17;

  public T17 getValue17();
    descriptor: ()Ljava/lang/Object;
    flags: (0x0001) ACC_PUBLIC
    Code:
      stack=1, locals=1, args_size=1
         0: aload_0
         1: getfield      #237                // Field _value17:Ljava/lang/Object;
         4: areturn
      LineNumberTable:
        line 61: 0
      LocalVariableTable:
        Start  Length  Slot  Name   Signature
            0       5     0  this   Lorg/sireum/MBox17;
    Signature: #235                         // ()TT17;

  public org.sireum.MBox17<T1, T2, T3, T4, T5, T6, T7, T8, T9, T10, T11, T12, T13, T14, T15, T16, T17> value17_$eq(T17);
    descriptor: (Ljava/lang/Object;)Lorg/sireum/MBox17;
    flags: (0x0001) ACC_PUBLIC
    Code:
      stack=2, locals=2, args_size=2
         0: aload_0
         1: aload_1
         2: putfield      #237                // Field _value17:Ljava/lang/Object;
         5: aload_0
         6: areturn
      LineNumberTable:
        line 61: 0
      LocalVariableTable:
        Start  Length  Slot  Name   Signature
            0       7     0  this   Lorg/sireum/MBox17;
            0       7     1 value17   Ljava/lang/Object;
    Signature: #240                         // (TT17;)Lorg/sireum/MBox17<TT1;TT2;TT3;TT4;TT5;TT6;TT7;TT8;TT9;TT10;TT11;TT12;TT13;TT14;TT15;TT16;TT17;>;
    MethodParameters:
      Name                           Flags
      value17                        final

  public org.sireum.MBox17<T1, T2, T3, T4, T5, T6, T7, T8, T9, T10, T11, T12, T13, T14, T15, T16, T17> setValue17(T17);
    descriptor: (Ljava/lang/Object;)Lorg/sireum/MBox17;
    flags: (0x0001) ACC_PUBLIC
    Code:
      stack=2, locals=2, args_size=2
         0: aload_0
         1: aload_1
         2: putfield      #237                // Field _value17:Ljava/lang/Object;
         5: aload_0
         6: areturn
      LineNumberTable:
        line 61: 0
      LocalVariableTable:
        Start  Length  Slot  Name   Signature
            0       7     0  this   Lorg/sireum/MBox17;
            0       7     1 value17   Ljava/lang/Object;
    Signature: #240                         // (TT17;)Lorg/sireum/MBox17<TT1;TT2;TT3;TT4;TT5;TT6;TT7;TT8;TT9;TT10;TT11;TT12;TT13;TT14;TT15;TT16;TT17;>;
    MethodParameters:
      Name                           Flags
      value17                        final

  public java.lang.String toString();
    descriptor: ()Ljava/lang/String;
    flags: (0x0001) ACC_PUBLIC
    Code:
      stack=3, locals=2, args_size=1
         0: aload_0
         1: invokevirtual #245                // Method $hasString:()Z
         4: ifeq          14
         7: aload_0
         8: invokestatic  #249                // InterfaceMethod org/sireum/RecordSig.string$:(Lorg/sireum/RecordSig;)Ljava/lang/String;
        11: goto          431
        14: new           #251                // class java/lang/StringBuilder
        17: dup
        18: invokespecial #255                // Method java/lang/StringBuilder."<init>":()V
        21: astore_1
        22: aload_1
        23: ldc_w         #257                // String MBox17
        26: invokevirtual #261                // Method java/lang/StringBuilder.append:(Ljava/lang/String;)Ljava/lang/StringBuilder;
        29: pop
        30: aload_1
        31: bipush        40
        33: invokevirtual #264                // Method java/lang/StringBuilder.append:(C)Ljava/lang/StringBuilder;
        36: pop
        37: aload_1
        38: getstatic     #269                // Field org/sireum/String$.MODULE$:Lorg/sireum/String$;
        41: aload_0
        42: invokevirtual #271                // Method value1:()Ljava/lang/Object;
        45: invokevirtual #275                // Method org/sireum/String$.escape:(Ljava/lang/Object;)Ljava/lang/String;
        48: invokevirtual #261                // Method java/lang/StringBuilder.append:(Ljava/lang/String;)Ljava/lang/StringBuilder;
        51: pop
        52: aload_1
        53: ldc_w         #277                // String ,
        56: invokevirtual #261                // Method java/lang/StringBuilder.append:(Ljava/lang/String;)Ljava/lang/StringBuilder;
        59: pop
        60: aload_1
        61: getstatic     #269                // Field org/sireum/String$.MODULE$:Lorg/sireum/String$;
        64: aload_0
        65: invokevirtual #279                // Method value2:()Ljava/lang/Object;
        68: invokevirtual #275                // Method org/sireum/String$.escape:(Ljava/lang/Object;)Ljava/lang/String;
        71: invokevirtual #261                // Method java/lang/StringBuilder.append:(Ljava/lang/String;)Ljava/lang/StringBuilder;
        74: pop
        75: aload_1
        76: ldc_w         #277                // String ,
        79: invokevirtual #261                // Method java/lang/StringBuilder.append:(Ljava/lang/String;)Ljava/lang/StringBuilder;
        82: pop
        83: aload_1
        84: getstatic     #269                // Field org/sireum/String$.MODULE$:Lorg/sireum/String$;
        87: aload_0
        88: invokevirtual #281                // Method value3:()Ljava/lang/Object;
        91: invokevirtual #275                // Method org/sireum/String$.escape:(Ljava/lang/Object;)Ljava/lang/String;
        94: invokevirtual #261                // Method java/lang/StringBuilder.append:(Ljava/lang/String;)Ljava/lang/StringBuilder;
        97: pop
        98: aload_1
        99: ldc_w         #277                // String ,
       102: invokevirtual #261                // Method java/lang/StringBuilder.append:(Ljava/lang/String;)Ljava/lang/StringBuilder;
       105: pop
       106: aload_1
       107: getstatic     #269                // Field org/sireum/String$.MODULE$:Lorg/sireum/String$;
       110: aload_0
       111: invokevirtual #283                // Method value4:()Ljava/lang/Object;
       114: invokevirtual #275                // Method org/sireum/String$.escape:(Ljava/lang/Object;)Ljava/lang/String;
       117: invokevirtual #261                // Method java/lang/StringBuilder.append:(Ljava/lang/String;)Ljava/lang/StringBuilder;
       120: pop
       121: aload_1
       122: ldc_w         #277                // String ,
       125: invokevirtual #261                // Method java/lang/StringBuilder.append:(Ljava/lang/String;)Ljava/lang/StringBuilder;
       128: pop
       129: aload_1
       130: getstatic     #269                // Field org/sireum/String$.MODULE$:Lorg/sireum/String$;
       133: aload_0
       134: invokevirtual #285                // Method value5:()Ljava/lang/Object;
       137: invokevirtual #275                // Method org/sireum/String$.escape:(Ljava/lang/Object;)Ljava/lang/String;
       140: invokevirtual #261                // Method java/lang/StringBuilder.append:(Ljava/lang/String;)Ljava/lang/StringBuilder;
       143: pop
       144: aload_1
       145: ldc_w         #277                // String ,
       148: invokevirtual #261                // Method java/lang/StringBuilder.append:(Ljava/lang/String;)Ljava/lang/StringBuilder;
       151: pop
       152: aload_1
       153: getstatic     #269                // Field org/sireum/String$.MODULE$:Lorg/sireum/String$;
       156: aload_0
       157: invokevirtual #287                // Method value6:()Ljava/lang/Object;
       160: invokevirtual #275                // Method org/sireum/String$.escape:(Ljava/lang/Object;)Ljava/lang/String;
       163: invokevirtual #261                // Method java/lang/StringBuilder.append:(Ljava/lang/String;)Ljava/lang/StringBuilder;
       166: pop
       167: aload_1
       168: ldc_w         #277                // String ,
       171: invokevirtual #261                // Method java/lang/StringBuilder.append:(Ljava/lang/String;)Ljava/lang/StringBuilder;
       174: pop
       175: aload_1
       176: getstatic     #269                // Field org/sireum/String$.MODULE$:Lorg/sireum/String$;
       179: aload_0
       180: invokevirtual #289                // Method value7:()Ljava/lang/Object;
       183: invokevirtual #275                // Method org/sireum/String$.escape:(Ljava/lang/Object;)Ljava/lang/String;
       186: invokevirtual #261                // Method java/lang/StringBuilder.append:(Ljava/lang/String;)Ljava/lang/StringBuilder;
       189: pop
       190: aload_1
       191: ldc_w         #277                // String ,
       194: invokevirtual #261                // Method java/lang/StringBuilder.append:(Ljava/lang/String;)Ljava/lang/StringBuilder;
       197: pop
       198: aload_1
       199: getstatic     #269                // Field org/sireum/String$.MODULE$:Lorg/sireum/String$;
       202: aload_0
       203: invokevirtual #291                // Method value8:()Ljava/lang/Object;
       206: invokevirtual #275                // Method org/sireum/String$.escape:(Ljava/lang/Object;)Ljava/lang/String;
       209: invokevirtual #261                // Method java/lang/StringBuilder.append:(Ljava/lang/String;)Ljava/lang/StringBuilder;
       212: pop
       213: aload_1
       214: ldc_w         #277                // String ,
       217: invokevirtual #261                // Method java/lang/StringBuilder.append:(Ljava/lang/String;)Ljava/lang/StringBuilder;
       220: pop
       221: aload_1
       222: getstatic     #269                // Field org/sireum/String$.MODULE$:Lorg/sireum/String$;
       225: aload_0
       226: invokevirtual #293                // Method value9:()Ljava/lang/Object;
       229: invokevirtual #275                // Method org/sireum/String$.escape:(Ljava/lang/Object;)Ljava/lang/String;
       232: invokevirtual #261                // Method java/lang/StringBuilder.append:(Ljava/lang/String;)Ljava/lang/StringBuilder;
       235: pop
       236: aload_1
       237: ldc_w         #277                // String ,
       240: invokevirtual #261                // Method java/lang/StringBuilder.append:(Ljava/lang/String;)Ljava/lang/StringBuilder;
       243: pop
       244: aload_1
       245: getstatic     #269                // Field org/sireum/String$.MODULE$:Lorg/sireum/String$;
       248: aload_0
       249: invokevirtual #295                // Method value10:()Ljava/lang/Object;
       252: invokevirtual #275                // Method org/sireum/String$.escape:(Ljava/lang/Object;)Ljava/lang/String;
       255: invokevirtual #261                // Method java/lang/StringBuilder.append:(Ljava/lang/String;)Ljava/lang/StringBuilder;
       258: pop
       259: aload_1
       260: ldc_w         #277                // String ,
       263: invokevirtual #261                // Method java/lang/StringBuilder.append:(Ljava/lang/String;)Ljava/lang/StringBuilder;
       266: pop
       267: aload_1
       268: getstatic     #269                // Field org/sireum/String$.MODULE$:Lorg/sireum/String$;
       271: aload_0
       272: invokevirtual #297                // Method value11:()Ljava/lang/Object;
       275: invokevirtual #275                // Method org/sireum/String$.escape:(Ljava/lang/Object;)Ljava/lang/String;
       278: invokevirtual #261                // Method java/lang/StringBuilder.append:(Ljava/lang/String;)Ljava/lang/StringBuilder;
       281: pop
       282: aload_1
       283: ldc_w         #277                // String ,
       286: invokevirtual #261                // Method java/lang/StringBuilder.append:(Ljava/lang/String;)Ljava/lang/StringBuilder;
       289: pop
       290: aload_1
       291: getstatic     #269                // Field org/sireum/String$.MODULE$:Lorg/sireum/String$;
       294: aload_0
       295: invokevirtual #299                // Method value12:()Ljava/lang/Object;
       298: invokevirtual #275                // Method org/sireum/String$.escape:(Ljava/lang/Object;)Ljava/lang/String;
       301: invokevirtual #261                // Method java/lang/StringBuilder.append:(Ljava/lang/String;)Ljava/lang/StringBuilder;
       304: pop
       305: aload_1
       306: ldc_w         #277                // String ,
       309: invokevirtual #261                // Method java/lang/StringBuilder.append:(Ljava/lang/String;)Ljava/lang/StringBuilder;
       312: pop
       313: aload_1
       314: getstatic     #269                // Field org/sireum/String$.MODULE$:Lorg/sireum/String$;
       317: aload_0
       318: invokevirtual #301                // Method value13:()Ljava/lang/Object;
       321: invokevirtual #275                // Method org/sireum/String$.escape:(Ljava/lang/Object;)Ljava/lang/String;
       324: invokevirtual #261                // Method java/lang/StringBuilder.append:(Ljava/lang/String;)Ljava/lang/StringBuilder;
       327: pop
       328: aload_1
       329: ldc_w         #277                // String ,
       332: invokevirtual #261                // Method java/lang/StringBuilder.append:(Ljava/lang/String;)Ljava/lang/StringBuilder;
       335: pop
       336: aload_1
       337: getstatic     #269                // Field org/sireum/String$.MODULE$:Lorg/sireum/String$;
       340: aload_0
       341: invokevirtual #303                // Method value14:()Ljava/lang/Object;
       344: invokevirtual #275                // Method org/sireum/String$.escape:(Ljava/lang/Object;)Ljava/lang/String;
       347: invokevirtual #261                // Method java/lang/StringBuilder.append:(Ljava/lang/String;)Ljava/lang/StringBuilder;
       350: pop
       351: aload_1
       352: ldc_w         #277                // String ,
       355: invokevirtual #261                // Method java/lang/StringBuilder.append:(Ljava/lang/String;)Ljava/lang/StringBuilder;
       358: pop
       359: aload_1
       360: getstatic     #269                // Field org/sireum/String$.MODULE$:Lorg/sireum/String$;
       363: aload_0
       364: invokevirtual #305                // Method value15:()Ljava/lang/Object;
       367: invokevirtual #275                // Method org/sireum/String$.escape:(Ljava/lang/Object;)Ljava/lang/String;
       370: invokevirtual #261                // Method java/lang/StringBuilder.append:(Ljava/lang/String;)Ljava/lang/StringBuilder;
       373: pop
       374: aload_1
       375: ldc_w         #277                // String ,
       378: invokevirtual #261                // Method java/lang/StringBuilder.append:(Ljava/lang/String;)Ljava/lang/StringBuilder;
       381: pop
       382: aload_1
       383: getstatic     #269                // Field org/sireum/String$.MODULE$:Lorg/sireum/String$;
       386: aload_0
       387: invokevirtual #307                // Method value16:()Ljava/lang/Object;
       390: invokevirtual #275                // Method org/sireum/String$.escape:(Ljava/lang/Object;)Ljava/lang/String;
       393: invokevirtual #261                // Method java/lang/StringBuilder.append:(Ljava/lang/String;)Ljava/lang/StringBuilder;
       396: pop
       397: aload_1
       398: ldc_w         #277                // String ,
       401: invokevirtual #261                // Method java/lang/StringBuilder.append:(Ljava/lang/String;)Ljava/lang/StringBuilder;
       404: pop
       405: aload_1
       406: getstatic     #269                // Field org/sireum/String$.MODULE$:Lorg/sireum/String$;
       409: aload_0
       410: invokevirtual #309                // Method value17:()Ljava/lang/Object;
       413: invokevirtual #275                // Method org/sireum/String$.escape:(Ljava/lang/Object;)Ljava/lang/String;
       416: invokevirtual #261                // Method java/lang/StringBuilder.append:(Ljava/lang/String;)Ljava/lang/StringBuilder;
       419: pop
       420: aload_1
       421: bipush        41
       423: invokevirtual #264                // Method java/lang/StringBuilder.append:(C)Ljava/lang/StringBuilder;
       426: pop
       427: aload_1
       428: invokevirtual #311                // Method java/lang/StringBuilder.toString:()Ljava/lang/String;
       431: areturn
      StackMapTable: number_of_entries = 2
        frame_type = 14 /* same */
        frame_type = 247 /* same_locals_1_stack_item_frame_extended */
          offset_delta = 416
          stack = [ class java/lang/String ]
      LineNumberTable:
        line 61: 0
      LocalVariableTable:
        Start  Length  Slot  Name   Signature
           22     409     1    sb   Ljava/lang/StringBuilder;
            0     432     0  this   Lorg/sireum/MBox17;

  public java.lang.String string();
    descriptor: ()Ljava/lang/String;
    flags: (0x0001) ACC_PUBLIC
    Code:
      stack=2, locals=1, args_size=1
         0: aload_0
         1: invokevirtual #245                // Method $hasString:()Z
         4: ifeq          14
         7: aload_0
         8: invokestatic  #249                // InterfaceMethod org/sireum/RecordSig.string$:(Lorg/sireum/RecordSig;)Ljava/lang/String;
        11: goto          24
        14: getstatic     #269                // Field org/sireum/String$.MODULE$:Lorg/sireum/String$;
        17: aload_0
        18: invokevirtual #317                // Method toString:()Ljava/lang/String;
        21: invokevirtual #321                // Method org/sireum/String$.apply:(Ljava/lang/String;)Ljava/lang/String;
        24: areturn
      StackMapTable: number_of_entries = 2
        frame_type = 14 /* same */
        frame_type = 73 /* same_locals_1_stack_item */
          stack = [ class java/lang/String ]
      LineNumberTable:
        line 61: 0
      LocalVariableTable:
        Start  Length  Slot  Name   Signature
            0      25     0  this   Lorg/sireum/MBox17;

  public int hashCode();
    descriptor: ()I
    flags: (0x0001) ACC_PUBLIC
    Code:
      stack=6, locals=1, args_size=1
         0: aload_0
         1: invokevirtual #325                // Method $hasEquals:()Z
         4: ifeq          14
         7: aload_0
         8: invokespecial #327                // Method java/lang/Object.hashCode:()I
        11: goto          183
        14: getstatic     #332                // Field scala/package$.MODULE$:Lscala/package$;
        17: invokevirtual #336                // Method scala/package$.Seq:()Lscala/collection/immutable/Seq$;
        20: getstatic     #341                // Field scala/runtime/ScalaRunTime$.MODULE$:Lscala/runtime/ScalaRunTime$;
        23: bipush        18
        25: anewarray     #5                  // class java/lang/Object
        28: dup
        29: iconst_0
        30: aload_0
        31: invokevirtual #345                // Method getClass:()Ljava/lang/Class;
        34: invokevirtual #350                // Method java/lang/Class.getName:()Ljava/lang/String;
        37: aastore
        38: dup
        39: iconst_1
        40: aload_0
        41: invokevirtual #271                // Method value1:()Ljava/lang/Object;
        44: aastore
        45: dup
        46: iconst_2
        47: aload_0
        48: invokevirtual #279                // Method value2:()Ljava/lang/Object;
        51: aastore
        52: dup
        53: iconst_3
        54: aload_0
        55: invokevirtual #281                // Method value3:()Ljava/lang/Object;
        58: aastore
        59: dup
        60: iconst_4
        61: aload_0
        62: invokevirtual #283                // Method value4:()Ljava/lang/Object;
        65: aastore
        66: dup
        67: iconst_5
        68: aload_0
        69: invokevirtual #285                // Method value5:()Ljava/lang/Object;
        72: aastore
        73: dup
        74: bipush        6
        76: aload_0
        77: invokevirtual #287                // Method value6:()Ljava/lang/Object;
        80: aastore
        81: dup
        82: bipush        7
        84: aload_0
        85: invokevirtual #289                // Method value7:()Ljava/lang/Object;
        88: aastore
        89: dup
        90: bipush        8
        92: aload_0
        93: invokevirtual #291                // Method value8:()Ljava/lang/Object;
        96: aastore
        97: dup
        98: bipush        9
       100: aload_0
       101: invokevirtual #293                // Method value9:()Ljava/lang/Object;
       104: aastore
       105: dup
       106: bipush        10
       108: aload_0
       109: invokevirtual #295                // Method value10:()Ljava/lang/Object;
       112: aastore
       113: dup
       114: bipush        11
       116: aload_0
       117: invokevirtual #297                // Method value11:()Ljava/lang/Object;
       120: aastore
       121: dup
       122: bipush        12
       124: aload_0
       125: invokevirtual #299                // Method value12:()Ljava/lang/Object;
       128: aastore
       129: dup
       130: bipush        13
       132: aload_0
       133: invokevirtual #301                // Method value13:()Ljava/lang/Object;
       136: aastore
       137: dup
       138: bipush        14
       140: aload_0
       141: invokevirtual #303                // Method value14:()Ljava/lang/Object;
       144: aastore
       145: dup
       146: bipush        15
       148: aload_0
       149: invokevirtual #305                // Method value15:()Ljava/lang/Object;
       152: aastore
       153: dup
       154: bipush        16
       156: aload_0
       157: invokevirtual #307                // Method value16:()Ljava/lang/Object;
       160: aastore
       161: dup
       162: bipush        17
       164: aload_0
       165: invokevirtual #309                // Method value17:()Ljava/lang/Object;
       168: aastore
       169: invokevirtual #354                // Method scala/runtime/ScalaRunTime$.genericWrapArray:(Ljava/lang/Object;)Lscala/collection/immutable/ArraySeq;
       172: invokevirtual #359                // Method scala/collection/immutable/Seq$.apply:(Lscala/collection/immutable/Seq;)Lscala/collection/SeqOps;
       175: checkcast     #361                // class scala/collection/Seq
       178: invokeinterface #362,  1          // InterfaceMethod scala/collection/Seq.hashCode:()I
       183: ireturn
      StackMapTable: number_of_entries = 2
        frame_type = 14 /* same */
        frame_type = 247 /* same_locals_1_stack_item_frame_extended */
          offset_delta = 168
          stack = [ int ]
      LineNumberTable:
        line 61: 0
      LocalVariableTable:
        Start  Length  Slot  Name   Signature
            0     184     0  this   Lorg/sireum/MBox17;

  public boolean equals(java.lang.Object);
    descriptor: (Ljava/lang/Object;)Z
    flags: (0x0001) ACC_PUBLIC
    Code:
      stack=2, locals=5, args_size=2
         0: aload_0
         1: invokevirtual #325                // Method $hasEquals:()Z
         4: ifeq          15
         7: aload_0
         8: aload_1
         9: invokespecial #366                // Method java/lang/Object.equals:(Ljava/lang/Object;)Z
        12: goto          328
        15: aload_0
        16: aload_1
        17: if_acmpne     24
        20: iconst_1
        21: goto          328
        24: aload_1
        25: astore_3
        26: aload_3
        27: instanceof    #2                  // class org/sireum/MBox17
        30: ifeq          319
        33: aload_3
        34: checkcast     #2                  // class org/sireum/MBox17
        37: astore        4
        39: aload_0
        40: invokevirtual #367                // Method hashCode:()I
        43: aload         4
        45: invokevirtual #367                // Method hashCode:()I
        48: if_icmpeq     55
        51: iconst_0
        52: goto          315
        55: aload_0
        56: invokevirtual #271                // Method value1:()Ljava/lang/Object;
        59: aload         4
        61: invokevirtual #271                // Method value1:()Ljava/lang/Object;
        64: invokestatic  #372                // Method scala/runtime/BoxesRunTime.equals:(Ljava/lang/Object;Ljava/lang/Object;)Z
        67: ifeq          314
        70: aload_0
        71: invokevirtual #279                // Method value2:()Ljava/lang/Object;
        74: aload         4
        76: invokevirtual #279                // Method value2:()Ljava/lang/Object;
        79: invokestatic  #372                // Method scala/runtime/BoxesRunTime.equals:(Ljava/lang/Object;Ljava/lang/Object;)Z
        82: ifeq          314
        85: aload_0
        86: invokevirtual #281                // Method value3:()Ljava/lang/Object;
        89: aload         4
        91: invokevirtual #281                // Method value3:()Ljava/lang/Object;
        94: invokestatic  #372                // Method scala/runtime/BoxesRunTime.equals:(Ljava/lang/Object;Ljava/lang/Object;)Z
        97: ifeq          314
       100: aload_0
       101: invokevirtual #283                // Method value4:()Ljava/lang/Object;
       104: aload         4
       106: invokevirtual #283                // Method value4:()Ljava/lang/Object;
       109: invokestatic  #372                // Method scala/runtime/BoxesRunTime.equals:(Ljava/lang/Object;Ljava/lang/Object;)Z
       112: ifeq          314
       115: aload_0
       116: invokevirtual #285                // Method value5:()Ljava/lang/Object;
       119: aload         4
       121: invokevirtual #285                // Method value5:()Ljava/lang/Object;
       124: invokestatic  #372                // Method scala/runtime/BoxesRunTime.equals:(Ljava/lang/Object;Ljava/lang/Object;)Z
       127: ifeq          314
       130: aload_0
       131: invokevirtual #287                // Method value6:()Ljava/lang/Object;
       134: aload         4
       136: invokevirtual #287                // Method value6:()Ljava/lang/Object;
       139: invokestatic  #372                // Method scala/runtime/BoxesRunTime.equals:(Ljava/lang/Object;Ljava/lang/Object;)Z
       142: ifeq          314
       145: aload_0
       146: invokevirtual #289                // Method value7:()Ljava/lang/Object;
       149: aload         4
       151: invokevirtual #289                // Method value7:()Ljava/lang/Object;
       154: invokestatic  #372                // Method scala/runtime/BoxesRunTime.equals:(Ljava/lang/Object;Ljava/lang/Object;)Z
       157: ifeq          314
       160: aload_0
       161: invokevirtual #291                // Method value8:()Ljava/lang/Object;
       164: aload         4
       166: invokevirtual #291                // Method value8:()Ljava/lang/Object;
       169: invokestatic  #372                // Method scala/runtime/BoxesRunTime.equals:(Ljava/lang/Object;Ljava/lang/Object;)Z
       172: ifeq          314
       175: aload_0
       176: invokevirtual #293                // Method value9:()Ljava/lang/Object;
       179: aload         4
       181: invokevirtual #293                // Method value9:()Ljava/lang/Object;
       184: invokestatic  #372                // Method scala/runtime/BoxesRunTime.equals:(Ljava/lang/Object;Ljava/lang/Object;)Z
       187: ifeq          314
       190: aload_0
       191: invokevirtual #295                // Method value10:()Ljava/lang/Object;
       194: aload         4
       196: invokevirtual #295                // Method value10:()Ljava/lang/Object;
       199: invokestatic  #372                // Method scala/runtime/BoxesRunTime.equals:(Ljava/lang/Object;Ljava/lang/Object;)Z
       202: ifeq          314
       205: aload_0
       206: invokevirtual #297                // Method value11:()Ljava/lang/Object;
       209: aload         4
       211: invokevirtual #297                // Method value11:()Ljava/lang/Object;
       214: invokestatic  #372                // Method scala/runtime/BoxesRunTime.equals:(Ljava/lang/Object;Ljava/lang/Object;)Z
       217: ifeq          314
       220: aload_0
       221: invokevirtual #299                // Method value12:()Ljava/lang/Object;
       224: aload         4
       226: invokevirtual #299                // Method value12:()Ljava/lang/Object;
       229: invokestatic  #372                // Method scala/runtime/BoxesRunTime.equals:(Ljava/lang/Object;Ljava/lang/Object;)Z
       232: ifeq          314
       235: aload_0
       236: invokevirtual #301                // Method value13:()Ljava/lang/Object;
       239: aload         4
       241: invokevirtual #301                // Method value13:()Ljava/lang/Object;
       244: invokestatic  #372                // Method scala/runtime/BoxesRunTime.equals:(Ljava/lang/Object;Ljava/lang/Object;)Z
       247: ifeq          314
       250: aload_0
       251: invokevirtual #303                // Method value14:()Ljava/lang/Object;
       254: aload         4
       256: invokevirtual #303                // Method value14:()Ljava/lang/Object;
       259: invokestatic  #372                // Method scala/runtime/BoxesRunTime.equals:(Ljava/lang/Object;Ljava/lang/Object;)Z
       262: ifeq          314
       265: aload_0
       266: invokevirtual #305                // Method value15:()Ljava/lang/Object;
       269: aload         4
       271: invokevirtual #305                // Method value15:()Ljava/lang/Object;
       274: invokestatic  #372                // Method scala/runtime/BoxesRunTime.equals:(Ljava/lang/Object;Ljava/lang/Object;)Z
       277: ifeq          314
       280: aload_0
       281: invokevirtual #307                // Method value16:()Ljava/lang/Object;
       284: aload         4
       286: invokevirtual #307                // Method value16:()Ljava/lang/Object;
       289: invokestatic  #372                // Method scala/runtime/BoxesRunTime.equals:(Ljava/lang/Object;Ljava/lang/Object;)Z
       292: ifeq          314
       295: aload_0
       296: invokevirtual #309                // Method value17:()Ljava/lang/Object;
       299: aload         4
       301: invokevirtual #309                // Method value17:()Ljava/lang/Object;
       304: invokestatic  #372                // Method scala/runtime/BoxesRunTime.equals:(Ljava/lang/Object;Ljava/lang/Object;)Z
       307: ifeq          314
       310: iconst_1
       311: goto          315
       314: iconst_0
       315: istore_2
       316: goto          327
       319: goto          322
       322: iconst_0
       323: istore_2
       324: goto          327
       327: iload_2
       328: ireturn
      StackMapTable: number_of_entries = 9
        frame_type = 15 /* same */
        frame_type = 8 /* same */
        frame_type = 254 /* append */
          offset_delta = 30
          locals = [ top, class java/lang/Object, class org/sireum/MBox17 ]
        frame_type = 251 /* same_frame_extended */
          offset_delta = 258
        frame_type = 64 /* same_locals_1_stack_item */
          stack = [ int ]
        frame_type = 250 /* chop */
          offset_delta = 3
        frame_type = 2 /* same */
        frame_type = 255 /* full_frame */
          offset_delta = 4
          locals = [ class org/sireum/MBox17, class java/lang/Object, int, class java/lang/Object ]
          stack = []
        frame_type = 255 /* full_frame */
          offset_delta = 0
          locals = [ class org/sireum/MBox17, class java/lang/Object ]
          stack = [ int ]
      LineNumberTable:
        line 61: 0
      LocalVariableTable:
        Start  Length  Slot  Name   Signature
            0     329     0  this   Lorg/sireum/MBox17;
            0     329     1     o   Ljava/lang/Object;
    MethodParameters:
      Name                           Flags
      o                              final

  public org.sireum.MBox17<T1, T2, T3, T4, T5, T6, T7, T8, T9, T10, T11, T12, T13, T14, T15, T16, T17> apply(T1, T2, T3, T4, T5, T6, T7, T8, T9, T10, T11, T12, T13, T14, T15, T16, T17);
    descriptor: (Ljava/lang/Object;Ljava/lang/Object;Ljava/lang/Object;Ljava/lang/Object;Ljava/lang/Object;Ljava/lang/Object;Ljava/lang/Object;Ljava/lang/Object;Ljava/lang/Object;Ljava/lang/Object;Ljava/lang/Object;Ljava/lang/Object;Ljava/lang/Object;Ljava/lang/Object;Ljava/lang/Object;Ljava/lang/Object;Ljava/lang/Object;)Lorg/sireum/MBox17;
    flags: (0x0001) ACC_PUBLIC
    Code:
      stack=19, locals=18, args_size=18
         0: new           #2                  // class org/sireum/MBox17
         3: dup
         4: aload_1
         5: aload_2
         6: aload_3
         7: aload         4
         9: aload         5
        11: aload         6
        13: aload         7
        15: aload         8
        17: aload         9
        19: aload         10
        21: aload         11
        23: aload         12
        25: aload         13
        27: aload         14
        29: aload         15
        31: aload         16
        33: aload         17
        35: invokespecial #377                // Method "<init>":(Ljava/lang/Object;Ljava/lang/Object;Ljava/lang/Object;Ljava/lang/Object;Ljava/lang/Object;Ljava/lang/Object;Ljava/lang/Object;Ljava/lang/Object;Ljava/lang/Object;Ljava/lang/Object;Ljava/lang/Object;Ljava/lang/Object;Ljava/lang/Object;Ljava/lang/Object;Ljava/lang/Object;Ljava/lang/Object;Ljava/lang/Object;)V
        38: areturn
      LineNumberTable:
        line 61: 0
      LocalVariableTable:
        Start  Length  Slot  Name   Signature
            0      39     0  this   Lorg/sireum/MBox17;
            0      39     1 value1   Ljava/lang/Object;
            0      39     2 value2   Ljava/lang/Object;
            0      39     3 value3   Ljava/lang/Object;
            0      39     4 value4   Ljava/lang/Object;
            0      39     5 value5   Ljava/lang/Object;
            0      39     6 value6   Ljava/lang/Object;
            0      39     7 value7   Ljava/lang/Object;
            0      39     8 value8   Ljava/lang/Object;
            0      39     9 value9   Ljava/lang/Object;
            0      39    10 value10   Ljava/lang/Object;
            0      39    11 value11   Ljava/lang/Object;
            0      39    12 value12   Ljava/lang/Object;
            0      39    13 value13   Ljava/lang/Object;
            0      39    14 value14   Ljava/lang/Object;
            0      39    15 value15   Ljava/lang/Object;
            0      39    16 value16   Ljava/lang/Object;
            0      39    17 value17   Ljava/lang/Object;
    Signature: #374                         // (TT1;TT2;TT3;TT4;TT5;TT6;TT7;TT8;TT9;TT10;TT11;TT12;TT13;TT14;TT15;TT16;TT17;)Lorg/sireum/MBox17<TT1;TT2;TT3;TT4;TT5;TT6;TT7;TT8;TT9;TT10;TT11;TT12;TT13;TT14;TT15;TT16;TT17;>;
    MethodParameters:
      Name                           Flags
      value1                         final
      value2                         final
      value3                         final
      value4                         final
      value5                         final
      value6                         final
      value7                         final
      value8                         final
      value9                         final
      value10                        final
      value11                        final
      value12                        final
      value13                        final
      value14                        final
      value15                        final
      value16                        final
      value17                        final

  public T1 apply$default$1();
    descriptor: ()Ljava/lang/Object;
    flags: (0x0001) ACC_PUBLIC
    Code:
      stack=1, locals=1, args_size=1
         0: aload_0
         1: invokevirtual #271                // Method value1:()Ljava/lang/Object;
         4: areturn
      LineNumberTable:
        line 61: 0
      LocalVariableTable:
        Start  Length  Slot  Name   Signature
            0       5     0  this   Lorg/sireum/MBox17;
    Signature: #106                         // ()TT1;

  public T2 apply$default$2();
    descriptor: ()Ljava/lang/Object;
    flags: (0x0001) ACC_PUBLIC
    Code:
      stack=1, locals=1, args_size=1
         0: aload_0
         1: invokevirtual #279                // Method value2:()Ljava/lang/Object;
         4: areturn
      LineNumberTable:
        line 61: 0
      LocalVariableTable:
        Start  Length  Slot  Name   Signature
            0       5     0  this   Lorg/sireum/MBox17;
    Signature: #115                         // ()TT2;

  public T3 apply$default$3();
    descriptor: ()Ljava/lang/Object;
    flags: (0x0001) ACC_PUBLIC
    Code:
      stack=1, locals=1, args_size=1
         0: aload_0
         1: invokevirtual #281                // Method value3:()Ljava/lang/Object;
         4: areturn
      LineNumberTable:
        line 61: 0
      LocalVariableTable:
        Start  Length  Slot  Name   Signature
            0       5     0  this   Lorg/sireum/MBox17;
    Signature: #123                         // ()TT3;

  public T4 apply$default$4();
    descriptor: ()Ljava/lang/Object;
    flags: (0x0001) ACC_PUBLIC
    Code:
      stack=1, locals=1, args_size=1
         0: aload_0
         1: invokevirtual #283                // Method value4:()Ljava/lang/Object;
         4: areturn
      LineNumberTable:
        line 61: 0
      LocalVariableTable:
        Start  Length  Slot  Name   Signature
            0       5     0  this   Lorg/sireum/MBox17;
    Signature: #131                         // ()TT4;

  public T5 apply$default$5();
    descriptor: ()Ljava/lang/Object;
    flags: (0x0001) ACC_PUBLIC
    Code:
      stack=1, locals=1, args_size=1
         0: aload_0
         1: invokevirtual #285                // Method value5:()Ljava/lang/Object;
         4: areturn
      LineNumberTable:
        line 61: 0
      LocalVariableTable:
        Start  Length  Slot  Name   Signature
            0       5     0  this   Lorg/sireum/MBox17;
    Signature: #139                         // ()TT5;

  public T6 apply$default$6();
    descriptor: ()Ljava/lang/Object;
    flags: (0x0001) ACC_PUBLIC
    Code:
      stack=1, locals=1, args_size=1
         0: aload_0
         1: invokevirtual #287                // Method value6:()Ljava/lang/Object;
         4: areturn
      LineNumberTable:
        line 61: 0
      LocalVariableTable:
        Start  Length  Slot  Name   Signature
            0       5     0  this   Lorg/sireum/MBox17;
    Signature: #147                         // ()TT6;

  public T7 apply$default$7();
    descriptor: ()Ljava/lang/Object;
    flags: (0x0001) ACC_PUBLIC
    Code:
      stack=1, locals=1, args_size=1
         0: aload_0
         1: invokevirtual #289                // Method value7:()Ljava/lang/Object;
         4: areturn
      LineNumberTable:
        line 61: 0
      LocalVariableTable:
        Start  Length  Slot  Name   Signature
            0       5     0  this   Lorg/sireum/MBox17;
    Signature: #155                         // ()TT7;

  public T8 apply$default$8();
    descriptor: ()Ljava/lang/Object;
    flags: (0x0001) ACC_PUBLIC
    Code:
      stack=1, locals=1, args_size=1
         0: aload_0
         1: invokevirtual #291                // Method value8:()Ljava/lang/Object;
         4: areturn
      LineNumberTable:
        line 61: 0
      LocalVariableTable:
        Start  Length  Slot  Name   Signature
            0       5     0  this   Lorg/sireum/MBox17;
    Signature: #163                         // ()TT8;

  public T9 apply$default$9();
    descriptor: ()Ljava/lang/Object;
    flags: (0x0001) ACC_PUBLIC
    Code:
      stack=1, locals=1, args_size=1
         0: aload_0
         1: invokevirtual #293                // Method value9:()Ljava/lang/Object;
         4: areturn
      LineNumberTable:
        line 61: 0
      LocalVariableTable:
        Start  Length  Slot  Name   Signature
            0       5     0  this   Lorg/sireum/MBox17;
    Signature: #171                         // ()TT9;

  public T10 apply$default$10();
    descriptor: ()Ljava/lang/Object;
    flags: (0x0001) ACC_PUBLIC
    Code:
      stack=1, locals=1, args_size=1
         0: aload_0
         1: invokevirtual #295                // Method value10:()Ljava/lang/Object;
         4: areturn
      LineNumberTable:
        line 61: 0
      LocalVariableTable:
        Start  Length  Slot  Name   Signature
            0       5     0  this   Lorg/sireum/MBox17;
    Signature: #179                         // ()TT10;

  public T11 apply$default$11();
    descriptor: ()Ljava/lang/Object;
    flags: (0x0001) ACC_PUBLIC
    Code:
      stack=1, locals=1, args_size=1
         0: aload_0
         1: invokevirtual #297                // Method value11:()Ljava/lang/Object;
         4: areturn
      LineNumberTable:
        line 61: 0
      LocalVariableTable:
        Start  Length  Slot  Name   Signature
            0       5     0  this   Lorg/sireum/MBox17;
    Signature: #187                         // ()TT11;

  public T12 apply$default$12();
    descriptor: ()Ljava/lang/Object;
    flags: (0x0001) ACC_PUBLIC
    Code:
      stack=1, locals=1, args_size=1
         0: aload_0
         1: invokevirtual #299                // Method value12:()Ljava/lang/Object;
         4: areturn
      LineNumberTable:
        line 61: 0
      LocalVariableTable:
        Start  Length  Slot  Name   Signature
            0       5     0  this   Lorg/sireum/MBox17;
    Signature: #195                         // ()TT12;

  public T13 apply$default$13();
    descriptor: ()Ljava/lang/Object;
    flags: (0x0001) ACC_PUBLIC
    Code:
      stack=1, locals=1, args_size=1
         0: aload_0
         1: invokevirtual #301                // Method value13:()Ljava/lang/Object;
         4: areturn
      LineNumberTable:
        line 61: 0
      LocalVariableTable:
        Start  Length  Slot  Name   Signature
            0       5     0  this   Lorg/sireum/MBox17;
    Signature: #203                         // ()TT13;

  public T14 apply$default$14();
    descriptor: ()Ljava/lang/Object;
    flags: (0x0001) ACC_PUBLIC
    Code:
      stack=1, locals=1, args_size=1
         0: aload_0
         1: invokevirtual #303                // Method value14:()Ljava/lang/Object;
         4: areturn
      LineNumberTable:
        line 61: 0
      LocalVariableTable:
        Start  Length  Slot  Name   Signature
            0       5     0  this   Lorg/sireum/MBox17;
    Signature: #211                         // ()TT14;

  public T15 apply$default$15();
    descriptor: ()Ljava/lang/Object;
    flags: (0x0001) ACC_PUBLIC
    Code:
      stack=1, locals=1, args_size=1
         0: aload_0
         1: invokevirtual #305                // Method value15:()Ljava/lang/Object;
         4: areturn
      LineNumberTable:
        line 61: 0
      LocalVariableTable:
        Start  Length  Slot  Name   Signature
            0       5     0  this   Lorg/sireum/MBox17;
    Signature: #219                         // ()TT15;

  public T16 apply$default$16();
    descriptor: ()Ljava/lang/Object;
    flags: (0x0001) ACC_PUBLIC
    Code:
      stack=1, locals=1, args_size=1
         0: aload_0
         1: invokevirtual #307                // Method value16:()Ljava/lang/Object;
         4: areturn
      LineNumberTable:
        line 61: 0
      LocalVariableTable:
        Start  Length  Slot  Name   Signature
            0       5     0  this   Lorg/sireum/MBox17;
    Signature: #227                         // ()TT16;

  public T17 apply$default$17();
    descriptor: ()Ljava/lang/Object;
    flags: (0x0001) ACC_PUBLIC
    Code:
      stack=1, locals=1, args_size=1
         0: aload_0
         1: invokevirtual #309                // Method value17:()Ljava/lang/Object;
         4: areturn
      LineNumberTable:
        line 61: 0
      LocalVariableTable:
        Start  Length  Slot  Name   Signature
            0       5     0  this   Lorg/sireum/MBox17;
    Signature: #235                         // ()TT17;

  public scala.collection.immutable.Seq<scala.Tuple2<java.lang.String, java.lang.Object>> $content();
    descriptor: ()Lscala/collection/immutable/Seq;
    flags: (0x0001) ACC_PUBLIC
    Code:
      stack=14, locals=1, args_size=1
         0: getstatic     #332                // Field scala/package$.MODULE$:Lscala/package$;
         3: invokevirtual #336                // Method scala/package$.Seq:()Lscala/collection/immutable/Seq$;
         6: getstatic     #341                // Field scala/runtime/ScalaRunTime$.MODULE$:Lscala/runtime/ScalaRunTime$;
         9: bipush        18
        11: anewarray     #399                // class scala/Tuple2
        14: dup
        15: iconst_0
        16: new           #399                // class scala/Tuple2
        19: dup
        20: ldc_w         #401                // String type
        23: getstatic     #332                // Field scala/package$.MODULE$:Lscala/package$;
        26: invokevirtual #405                // Method scala/package$.List:()Lscala/collection/immutable/List$;
        29: getstatic     #341                // Field scala/runtime/ScalaRunTime$.MODULE$:Lscala/runtime/ScalaRunTime$;
        32: iconst_3
        33: anewarray     #315                // class java/lang/String
        36: dup
        37: iconst_0
        38: ldc_w         #407                // String org
        41: aastore
        42: dup
        43: iconst_1
        44: ldc_w         #409                // String sireum
        47: aastore
        48: dup
        49: iconst_2
        50: ldc_w         #257                // String MBox17
        53: aastore
        54: checkcast     #411                // class "[Ljava/lang/Object;"
        57: invokevirtual #415                // Method scala/runtime/ScalaRunTime$.wrapRefArray:([Ljava/lang/Object;)Lscala/collection/immutable/ArraySeq;
        60: invokevirtual #420                // Method scala/collection/immutable/List$.apply:(Lscala/collection/immutable/Seq;)Ljava/lang/Object;
        63: invokespecial #423                // Method scala/Tuple2."<init>":(Ljava/lang/Object;Ljava/lang/Object;)V
        66: aastore
        67: dup
        68: iconst_1
        69: new           #399                // class scala/Tuple2
        72: dup
        73: ldc_w         #424                // String value1
        76: aload_0
        77: invokevirtual #271                // Method value1:()Ljava/lang/Object;
        80: invokespecial #423                // Method scala/Tuple2."<init>":(Ljava/lang/Object;Ljava/lang/Object;)V
        83: aastore
        84: dup
        85: iconst_2
        86: new           #399                // class scala/Tuple2
        89: dup
        90: ldc_w         #425                // String value2
        93: aload_0
        94: invokevirtual #279                // Method value2:()Ljava/lang/Object;
        97: invokespecial #423                // Method scala/Tuple2."<init>":(Ljava/lang/Object;Ljava/lang/Object;)V
       100: aastore
       101: dup
       102: iconst_3
       103: new           #399                // class scala/Tuple2
       106: dup
       107: ldc_w         #426                // String value3
       110: aload_0
       111: invokevirtual #281                // Method value3:()Ljava/lang/Object;
       114: invokespecial #423                // Method scala/Tuple2."<init>":(Ljava/lang/Object;Ljava/lang/Object;)V
       117: aastore
       118: dup
       119: iconst_4
       120: new           #399                // class scala/Tuple2
       123: dup
       124: ldc_w         #427                // String value4
       127: aload_0
       128: invokevirtual #283                // Method value4:()Ljava/lang/Object;
       131: invokespecial #423                // Method scala/Tuple2."<init>":(Ljava/lang/Object;Ljava/lang/Object;)V
       134: aastore
       135: dup
       136: iconst_5
       137: new           #399                // class scala/Tuple2
       140: dup
       141: ldc_w         #428                // String value5
       144: aload_0
       145: invokevirtual #285                // Method value5:()Ljava/lang/Object;
       148: invokespecial #423                // Method scala/Tuple2."<init>":(Ljava/lang/Object;Ljava/lang/Object;)V
       151: aastore
       152: dup
       153: bipush        6
       155: new           #399                // class scala/Tuple2
       158: dup
       159: ldc_w         #429                // String value6
       162: aload_0
       163: invokevirtual #287                // Method value6:()Ljava/lang/Object;
       166: invokespecial #423                // Method scala/Tuple2."<init>":(Ljava/lang/Object;Ljava/lang/Object;)V
       169: aastore
       170: dup
       171: bipush        7
       173: new           #399                // class scala/Tuple2
       176: dup
       177: ldc_w         #430                // String value7
       180: aload_0
       181: invokevirtual #289                // Method value7:()Ljava/lang/Object;
       184: invokespecial #423                // Method scala/Tuple2."<init>":(Ljava/lang/Object;Ljava/lang/Object;)V
       187: aastore
       188: dup
       189: bipush        8
       191: new           #399                // class scala/Tuple2
       194: dup
       195: ldc_w         #431                // String value8
       198: aload_0
       199: invokevirtual #291                // Method value8:()Ljava/lang/Object;
       202: invokespecial #423                // Method scala/Tuple2."<init>":(Ljava/lang/Object;Ljava/lang/Object;)V
       205: aastore
       206: dup
       207: bipush        9
       209: new           #399                // class scala/Tuple2
       212: dup
       213: ldc_w         #432                // String value9
       216: aload_0
       217: invokevirtual #293                // Method value9:()Ljava/lang/Object;
       220: invokespecial #423                // Method scala/Tuple2."<init>":(Ljava/lang/Object;Ljava/lang/Object;)V
       223: aastore
       224: dup
       225: bipush        10
       227: new           #399                // class scala/Tuple2
       230: dup
       231: ldc_w         #433                // String value10
       234: aload_0
       235: invokevirtual #295                // Method value10:()Ljava/lang/Object;
       238: invokespecial #423                // Method scala/Tuple2."<init>":(Ljava/lang/Object;Ljava/lang/Object;)V
       241: aastore
       242: dup
       243: bipush        11
       245: new           #399                // class scala/Tuple2
       248: dup
       249: ldc_w         #434                // String value11
       252: aload_0
       253: invokevirtual #297                // Method value11:()Ljava/lang/Object;
       256: invokespecial #423                // Method scala/Tuple2."<init>":(Ljava/lang/Object;Ljava/lang/Object;)V
       259: aastore
       260: dup
       261: bipush        12
       263: new           #399                // class scala/Tuple2
       266: dup
       267: ldc_w         #435                // String value12
       270: aload_0
       271: invokevirtual #299                // Method value12:()Ljava/lang/Object;
       274: invokespecial #423                // Method scala/Tuple2."<init>":(Ljava/lang/Object;Ljava/lang/Object;)V
       277: aastore
       278: dup
       279: bipush        13
       281: new           #399                // class scala/Tuple2
       284: dup
       285: ldc_w         #436                // String value13
       288: aload_0
       289: invokevirtual #301                // Method value13:()Ljava/lang/Object;
       292: invokespecial #423                // Method scala/Tuple2."<init>":(Ljava/lang/Object;Ljava/lang/Object;)V
       295: aastore
       296: dup
       297: bipush        14
       299: new           #399                // class scala/Tuple2
       302: dup
       303: ldc_w         #437                // String value14
       306: aload_0
       307: invokevirtual #303                // Method value14:()Ljava/lang/Object;
       310: invokespecial #423                // Method scala/Tuple2."<init>":(Ljava/lang/Object;Ljava/lang/Object;)V
       313: aastore
       314: dup
       315: bipush        15
       317: new           #399                // class scala/Tuple2
       320: dup
       321: ldc_w         #438                // String value15
       324: aload_0
       325: invokevirtual #305                // Method value15:()Ljava/lang/Object;
       328: invokespecial #423                // Method scala/Tuple2."<init>":(Ljava/lang/Object;Ljava/lang/Object;)V
       331: aastore
       332: dup
       333: bipush        16
       335: new           #399                // class scala/Tuple2
       338: dup
       339: ldc_w         #439                // String value16
       342: aload_0
       343: invokevirtual #307                // Method value16:()Ljava/lang/Object;
       346: invokespecial #423                // Method scala/Tuple2."<init>":(Ljava/lang/Object;Ljava/lang/Object;)V
       349: aastore
       350: dup
       351: bipush        17
       353: new           #399                // class scala/Tuple2
       356: dup
       357: ldc_w         #440                // String value17
       360: aload_0
       361: invokevirtual #309                // Method value17:()Ljava/lang/Object;
       364: invokespecial #423                // Method scala/Tuple2."<init>":(Ljava/lang/Object;Ljava/lang/Object;)V
       367: aastore
       368: checkcast     #411                // class "[Ljava/lang/Object;"
       371: invokevirtual #415                // Method scala/runtime/ScalaRunTime$.wrapRefArray:([Ljava/lang/Object;)Lscala/collection/immutable/ArraySeq;
       374: invokevirtual #359                // Method scala/collection/immutable/Seq$.apply:(Lscala/collection/immutable/Seq;)Lscala/collection/SeqOps;
       377: checkcast     #442                // class scala/collection/immutable/Seq
       380: areturn
      LineNumberTable:
        line 61: 0
      LocalVariableTable:
        Start  Length  Slot  Name   Signature
            0     381     0  this   Lorg/sireum/MBox17;
    Signature: #397                         // ()Lscala/collection/immutable/Seq<Lscala/Tuple2<Ljava/lang/String;Ljava/lang/Object;>;>;

  public org.sireum.MBox17<T1, T2, T3, T4, T5, T6, T7, T8, T9, T10, T11, T12, T13, T14, T15, T16, T17> $clone();
    descriptor: ()Lorg/sireum/MBox17;
    flags: (0x0001) ACC_PUBLIC
    Code:
      stack=20, locals=2, args_size=1
         0: new           #2                  // class org/sireum/MBox17
         3: dup
         4: getstatic     #450                // Field org/sireum/helper$.MODULE$:Lorg/sireum/helper$;
         7: aload_0
         8: invokevirtual #271                // Method value1:()Ljava/lang/Object;
        11: invokevirtual #454                // Method org/sireum/helper$.cloneAssign:(Ljava/lang/Object;)Ljava/lang/Object;
        14: getstatic     #450                // Field org/sireum/helper$.MODULE$:Lorg/sireum/helper$;
        17: aload_0
        18: invokevirtual #279                // Method value2:()Ljava/lang/Object;
        21: invokevirtual #454                // Method org/sireum/helper$.cloneAssign:(Ljava/lang/Object;)Ljava/lang/Object;
        24: getstatic     #450                // Field org/sireum/helper$.MODULE$:Lorg/sireum/helper$;
        27: aload_0
        28: invokevirtual #281                // Method value3:()Ljava/lang/Object;
        31: invokevirtual #454                // Method org/sireum/helper$.cloneAssign:(Ljava/lang/Object;)Ljava/lang/Object;
        34: getstatic     #450                // Field org/sireum/helper$.MODULE$:Lorg/sireum/helper$;
        37: aload_0
        38: invokevirtual #283                // Method value4:()Ljava/lang/Object;
        41: invokevirtual #454                // Method org/sireum/helper$.cloneAssign:(Ljava/lang/Object;)Ljava/lang/Object;
        44: getstatic     #450                // Field org/sireum/helper$.MODULE$:Lorg/sireum/helper$;
        47: aload_0
        48: invokevirtual #285                // Method value5:()Ljava/lang/Object;
        51: invokevirtual #454                // Method org/sireum/helper$.cloneAssign:(Ljava/lang/Object;)Ljava/lang/Object;
        54: getstatic     #450                // Field org/sireum/helper$.MODULE$:Lorg/sireum/helper$;
        57: aload_0
        58: invokevirtual #287                // Method value6:()Ljava/lang/Object;
        61: invokevirtual #454                // Method org/sireum/helper$.cloneAssign:(Ljava/lang/Object;)Ljava/lang/Object;
        64: getstatic     #450                // Field org/sireum/helper$.MODULE$:Lorg/sireum/helper$;
        67: aload_0
        68: invokevirtual #289                // Method value7:()Ljava/lang/Object;
        71: invokevirtual #454                // Method org/sireum/helper$.cloneAssign:(Ljava/lang/Object;)Ljava/lang/Object;
        74: getstatic     #450                // Field org/sireum/helper$.MODULE$:Lorg/sireum/helper$;
        77: aload_0
        78: invokevirtual #291                // Method value8:()Ljava/lang/Object;
        81: invokevirtual #454                // Method org/sireum/helper$.cloneAssign:(Ljava/lang/Object;)Ljava/lang/Object;
        84: getstatic     #450                // Field org/sireum/helper$.MODULE$:Lorg/sireum/helper$;
        87: aload_0
        88: invokevirtual #293                // Method value9:()Ljava/lang/Object;
        91: invokevirtual #454                // Method org/sireum/helper$.cloneAssign:(Ljava/lang/Object;)Ljava/lang/Object;
        94: getstatic     #450                // Field org/sireum/helper$.MODULE$:Lorg/sireum/helper$;
        97: aload_0
        98: invokevirtual #295                // Method value10:()Ljava/lang/Object;
       101: invokevirtual #454                // Method org/sireum/helper$.cloneAssign:(Ljava/lang/Object;)Ljava/lang/Object;
       104: getstatic     #450                // Field org/sireum/helper$.MODULE$:Lorg/sireum/helper$;
       107: aload_0
       108: invokevirtual #297                // Method value11:()Ljava/lang/Object;
       111: invokevirtual #454                // Method org/sireum/helper$.cloneAssign:(Ljava/lang/Object;)Ljava/lang/Object;
       114: getstatic     #450                // Field org/sireum/helper$.MODULE$:Lorg/sireum/helper$;
       117: aload_0
       118: invokevirtual #299                // Method value12:()Ljava/lang/Object;
       121: invokevirtual #454                // Method org/sireum/helper$.cloneAssign:(Ljava/lang/Object;)Ljava/lang/Object;
       124: getstatic     #450                // Field org/sireum/helper$.MODULE$:Lorg/sireum/helper$;
       127: aload_0
       128: invokevirtual #301                // Method value13:()Ljava/lang/Object;
       131: invokevirtual #454                // Method org/sireum/helper$.cloneAssign:(Ljava/lang/Object;)Ljava/lang/Object;
       134: getstatic     #450                // Field org/sireum/helper$.MODULE$:Lorg/sireum/helper$;
       137: aload_0
       138: invokevirtual #303                // Method value14:()Ljava/lang/Object;
       141: invokevirtual #454                // Method org/sireum/helper$.cloneAssign:(Ljava/lang/Object;)Ljava/lang/Object;
       144: getstatic     #450                // Field org/sireum/helper$.MODULE$:Lorg/sireum/helper$;
       147: aload_0
       148: invokevirtual #305                // Method value15:()Ljava/lang/Object;
       151: invokevirtual #454                // Method org/sireum/helper$.cloneAssign:(Ljava/lang/Object;)Ljava/lang/Object;
       154: getstatic     #450                // Field org/sireum/helper$.MODULE$:Lorg/sireum/helper$;
       157: aload_0
       158: invokevirtual #307                // Method value16:()Ljava/lang/Object;
       161: invokevirtual #454                // Method org/sireum/helper$.cloneAssign:(Ljava/lang/Object;)Ljava/lang/Object;
       164: getstatic     #450                // Field org/sireum/helper$.MODULE$:Lorg/sireum/helper$;
       167: aload_0
       168: invokevirtual #309                // Method value17:()Ljava/lang/Object;
       171: invokevirtual #454                // Method org/sireum/helper$.cloneAssign:(Ljava/lang/Object;)Ljava/lang/Object;
       174: invokespecial #377                // Method "<init>":(Ljava/lang/Object;Ljava/lang/Object;Ljava/lang/Object;Ljava/lang/Object;Ljava/lang/Object;Ljava/lang/Object;Ljava/lang/Object;Ljava/lang/Object;Ljava/lang/Object;Ljava/lang/Object;Ljava/lang/Object;Ljava/lang/Object;Ljava/lang/Object;Ljava/lang/Object;Ljava/lang/Object;Ljava/lang/Object;Ljava/lang/Object;)V
       177: astore_1
       178: aload_1
       179: areturn
      LineNumberTable:
        line 61: 0
      LocalVariableTable:
        Start  Length  Slot  Name   Signature
          178       1     1     r   Lorg/sireum/MBox17;
            0     180     0  this   Lorg/sireum/MBox17;
    Signature: #445                         // ()Lorg/sireum/MBox17<TT1;TT2;TT3;TT4;TT5;TT6;TT7;TT8;TT9;TT10;TT11;TT12;TT13;TT14;TT15;TT16;TT17;>;

  public final org.sireum.$internal.MutableMarker $owned_$eq(boolean);
    descriptor: (Z)Lorg/sireum/$internal/MutableMarker;
    flags: (0x1051) ACC_PUBLIC, ACC_FINAL, ACC_BRIDGE, ACC_SYNTHETIC
    Code:
      stack=2, locals=2, args_size=2
         0: aload_0
         1: iload_1
         2: invokevirtual #458                // Method $owned_$eq:(Z)Lorg/sireum/RecordSig;
         5: areturn
      LineNumberTable:
        line 61: 0
      LocalVariableTable:
        Start  Length  Slot  Name   Signature
            0       6     0  this   Lorg/sireum/MBox17;
            0       6     1     b   Z
    MethodParameters:
      Name                           Flags
      b                              final

  public java.lang.Object $clone();
    descriptor: ()Ljava/lang/Object;
    flags: (0x1041) ACC_PUBLIC, ACC_BRIDGE, ACC_SYNTHETIC
    Code:
      stack=1, locals=1, args_size=1
         0: aload_0
         1: invokevirtual #460                // Method $clone:()Lorg/sireum/MBox17;
         4: areturn
      LineNumberTable:
        line 61: 0
      LocalVariableTable:
        Start  Length  Slot  Name   Signature
            0       5     0  this   Lorg/sireum/MBox17;

  public org.sireum.$internal.MutableMarker $clone();
    descriptor: ()Lorg/sireum/$internal/MutableMarker;
    flags: (0x1041) ACC_PUBLIC, ACC_BRIDGE, ACC_SYNTHETIC
    Code:
      stack=1, locals=1, args_size=1
         0: aload_0
         1: invokevirtual #460                // Method $clone:()Lorg/sireum/MBox17;
         4: areturn
      LineNumberTable:
        line 61: 0
      LocalVariableTable:
        Start  Length  Slot  Name   Signature
            0       5     0  this   Lorg/sireum/MBox17;

  public org.sireum.MBox17(T1, T2, T3, T4, T5, T6, T7, T8, T9, T10, T11, T12, T13, T14, T15, T16, T17);
    descriptor: (Ljava/lang/Object;Ljava/lang/Object;Ljava/lang/Object;Ljava/lang/Object;Ljava/lang/Object;Ljava/lang/Object;Ljava/lang/Object;Ljava/lang/Object;Ljava/lang/Object;Ljava/lang/Object;Ljava/lang/Object;Ljava/lang/Object;Ljava/lang/Object;Ljava/lang/Object;Ljava/lang/Object;Ljava/lang/Object;Ljava/lang/Object;)V
    flags: (0x0001) ACC_PUBLIC
    Code:
      stack=2, locals=18, args_size=18
         0: aload_0
         1: invokespecial #480                // Method java/lang/Object."<init>":()V
         4: aload_0
         5: invokestatic  #484                // InterfaceMethod org/sireum/Mutable.$init$:(Lorg/sireum/Mutable;)V
         8: aload_0
         9: invokestatic  #487                // InterfaceMethod org/sireum/RecordSig.$init$:(Lorg/sireum/RecordSig;)V
        12: aload_0
        13: aload_1
        14: putfield      #108                // Field _value1:Ljava/lang/Object;
        17: aload_0
        18: aload_2
        19: putfield      #117                // Field _value2:Ljava/lang/Object;
        22: aload_0
        23: aload_3
        24: putfield      #125                // Field _value3:Ljava/lang/Object;
        27: aload_0
        28: aload         4
        30: putfield      #133                // Field _value4:Ljava/lang/Object;
        33: aload_0
        34: aload         5
        36: putfield      #141                // Field _value5:Ljava/lang/Object;
        39: aload_0
        40: aload         6
        42: putfield      #149                // Field _value6:Ljava/lang/Object;
        45: aload_0
        46: aload         7
        48: putfield      #157                // Field _value7:Ljava/lang/Object;
        51: aload_0
        52: aload         8
        54: putfield      #165                // Field _value8:Ljava/lang/Object;
        57: aload_0
        58: aload         9
        60: putfield      #173                // Field _value9:Ljava/lang/Object;
        63: aload_0
        64: aload         10
        66: putfield      #181                // Field _value10:Ljava/lang/Object;
        69: aload_0
        70: aload         11
        72: putfield      #189                // Field _value11:Ljava/lang/Object;
        75: aload_0
        76: aload         12
        78: putfield      #197                // Field _value12:Ljava/lang/Object;
        81: aload_0
        82: aload         13
        84: putfield      #205                // Field _value13:Ljava/lang/Object;
        87: aload_0
        88: aload         14
        90: putfield      #213                // Field _value14:Ljava/lang/Object;
        93: aload_0
        94: aload         15
        96: putfield      #221                // Field _value15:Ljava/lang/Object;
        99: aload_0
       100: aload         16
       102: putfield      #229                // Field _value16:Ljava/lang/Object;
       105: aload_0
       106: aload         17
       108: putfield      #237                // Field _value17:Ljava/lang/Object;
       111: return
      LineNumberTable:
        line 61: 0
      LocalVariableTable:
        Start  Length  Slot  Name   Signature
            0     112     0  this   Lorg/sireum/MBox17;
            0     112     1 __value1   Ljava/lang/Object;
            0     112     2 __value2   Ljava/lang/Object;
            0     112     3 __value3   Ljava/lang/Object;
            0     112     4 __value4   Ljava/lang/Object;
            0     112     5 __value5   Ljava/lang/Object;
            0     112     6 __value6   Ljava/lang/Object;
            0     112     7 __value7   Ljava/lang/Object;
            0     112     8 __value8   Ljava/lang/Object;
            0     112     9 __value9   Ljava/lang/Object;
            0     112    10 __value10   Ljava/lang/Object;
            0     112    11 __value11   Ljava/lang/Object;
            0     112    12 __value12   Ljava/lang/Object;
            0     112    13 __value13   Ljava/lang/Object;
            0     112    14 __value14   Ljava/lang/Object;
            0     112    15 __value15   Ljava/lang/Object;
            0     112    16 __value16   Ljava/lang/Object;
            0     112    17 __value17   Ljava/lang/Object;
    Signature: #462                         // (TT1;TT2;TT3;TT4;TT5;TT6;TT7;TT8;TT9;TT10;TT11;TT12;TT13;TT14;TT15;TT16;TT17;)V
    MethodParameters:
      Name                           Flags
      __value1                       final
      __value2                       final
      __value3                       final
      __value4                       final
      __value5                       final
      __value6                       final
      __value7                       final
      __value8                       final
      __value9                       final
      __value10                      final
      __value11                      final
      __value12                      final
      __value13                      final
      __value14                      final
      __value15                      final
      __value16                      final
      __value17                      final
}
Signature: #3                           // <T1:Ljava/lang/Object;T2:Ljava/lang/Object;T3:Ljava/lang/Object;T4:Ljava/lang/Object;T5:Ljava/lang/Object;T6:Ljava/lang/Object;T7:Ljava/lang/Object;T8:Ljava/lang/Object;T9:Ljava/lang/Object;T10:Ljava/lang/Object;T11:Ljava/lang/Object;T12:Ljava/lang/Object;T13:Ljava/lang/Object;T14:Ljava/lang/Object;T15:Ljava/lang/Object;T16:Ljava/lang/Object;T17:Ljava/lang/Object;>Ljava/lang/Object;Lorg/sireum/RecordSig;
SourceFile: "MBox.scala"
RuntimeVisibleAnnotations:
  0: #9(#10=s#11)
    scala.reflect.ScalaSignature(
      bytes="\u0006\u0005\u0015Mq\u0001CA\u0006\u0003\u001bA\t!a\u0006\u0007\u0011\u0005m\u0011Q\u0002E\u0001\u0003;Aq!a\u000b\u0002\t\u0003\ti\u0003C\u0004\u00020\u0005!\t!!\r\t\u000f\u0011e\u0016\u0001\"\u0001\u0005<\u001a9\u00111DA\u0007\u0005\u0005]\u0002BCA!\u000b\t\u0005\t\u0015!\u0003\u0002D!Q\u0011\u0011L\u0003\u0003\u0002\u0003\u0006I!a\u0017\t\u0015\u0005\u0005TA!A!\u0002\u0013\t\u0019\u0007\u0003\u0006\u0002j\u0015\u0011\t\u0011)A\u0005\u0003WB!\"!\u001d\u0006\u0005\u0003\u0005\u000b\u0011BA:\u0011)\tI(\u0002B\u0001B\u0003%\u00111\u0010\u0005\u000b\u0003\u0003+!\u0011!Q\u0001\n\u0005\r\u0005BCAE\u000b\t\u0005\t\u0015!\u0003\u0002\f\"Q\u0011\u0011S\u0003\u0003\u0002\u0003\u0006I!a%\t\u0015\u0005eUA!A!\u0002\u0013\tY\n\u0003\u0006\u0002\"\u0016\u0011\t\u0011)A\u0005\u0003GC!\"!+\u0006\u0005\u0003\u0005\u000b\u0011BAV\u0011)\t\t,\u0002B\u0001B\u0003%\u00111\u0017\u0005\u000b\u0003s+!\u0011!Q\u0001\n\u0005m\u0006BCAa\u000b\t\u0005\t\u0015!\u0003\u0002D\"Q\u0011\u0011Z\u0003\u0003\u0002\u0003\u0006I!a3\t\u0015\u0005EWA!A!\u0002\u0013\t\u0019\u000eC\u0004\u0002,\u0015!\t!!7\t\u0011\u0005}X\u0001)Q\u0005\u0003\u0007BqA!\u0001\u0006\t\u0003\u0011\u0019\u0001C\u0004\u0003\u0006\u0015!\tAa\u0001\t\u000f\t\u001dQ\u0001\"\u0001\u0003\n!9!qB\u0003\u0005\u0002\tE\u0001\u0002\u0003B\u000b\u000b\u0001\u0006K!a\u0017\t\u000f\t]Q\u0001\"\u0001\u0003\u001a!9!1D\u0003\u0005\u0002\te\u0001b\u0002B\u000f\u000b\u0011\u0005!q\u0004\u0005\b\u0005G)A\u0011\u0001B\u0013\u0011!\u0011I#\u0002Q!\n\u0005\r\u0004b\u0002B\u0016\u000b\u0011\u0005!Q\u0006\u0005\b\u0005_)A\u0011\u0001B\u0017\u0011\u001d\u0011\t$\u0002C\u0001\u0005gAqAa\u000e\u0006\t\u0003\u0011I\u0004\u0003\u0005\u0003>\u0015\u0001\u000b\u0015BA6\u0011\u001d\u0011y$\u0002C\u0001\u0005\u0003BqAa\u0011\u0006\t\u0003\u0011\t\u0005C\u0004\u0003F\u0015!\tAa\u0012\t\u000f\t-S\u0001\"\u0001\u0003N!A!\u0011K\u0003!B\u0013\t\u0019\bC\u0004\u0003T\u0015!\tA!\u0016\t\u000f\t]S\u0001\"\u0001\u0003V!9!\u0011L\u0003\u0005\u0002\tm\u0003b\u0002B0\u000b\u0011\u0005!\u0011\r\u0005\t\u0005K*\u0001\u0015)\u0003\u0002|!9!qM\u0003\u0005\u0002\t%\u0004b\u0002B6\u000b\u0011\u0005!\u0011\u000e\u0005\b\u0005[*A\u0011\u0001B8\u0011\u001d\u0011\u0019(\u0002C\u0001\u0005kB\u0001B!\u001f\u0006A\u0003&\u00111\u0011\u0005\b\u0005w*A\u0011\u0001B?\u0011\u001d\u0011y(\u0002C\u0001\u0005{BqA!!\u0006\t\u0003\u0011\u0019\tC\u0004\u0003\b\u0016!\tA!#\t\u0011\t5U\u0001)Q\u0005\u0003\u0017CqAa$\u0006\t\u0003\u0011\t\nC\u0004\u0003\u0014\u0016!\tA!%\t\u000f\tUU\u0001\"\u0001\u0003\u0018\"9!1T\u0003\u0005\u0002\tu\u0005\u0002\u0003BQ\u000b\u0001\u0006K!a%\t\u000f\t\rV\u0001\"\u0001\u0003&\"9!qU\u0003\u0005\u0002\t\u0015\u0006b\u0002BU\u000b\u0011\u0005!1\u0016\u0005\b\u0005_+A\u0011\u0001BY\u0011!\u0011),\u0002Q!\n\u0005m\u0005b\u0002B\\\u000b\u0011\u0005!\u0011\u0018\u0005\b\u0005w+A\u0011\u0001B]\u0011\u001d\u0011i,\u0002C\u0001\u0005\u007fCqAa1\u0006\t\u0003\u0011)\r\u0003\u0005\u0003J\u0016\u0001\u000b\u0015BAR\u0011\u001d\u0011Y-\u0002C\u0001\u0005\u001bDqAa4\u0006\t\u0003\u0011i\rC\u0004\u0003R\u0016!\tAa5\t\u000f\t]W\u0001\"\u0001\u0003Z\"A!Q\\\u0003!B\u0013\tY\u000bC\u0004\u0003`\u0016!\tA!9\t\u000f\t\rX\u0001\"\u0001\u0003b\"9!Q]\u0003\u0005\u0002\t\u001d\bb\u0002Bv\u000b\u0011\u0005!Q\u001e\u0005\t\u0005c,\u0001\u0015)\u0003\u00024\"9!1_\u0003\u0005\u0002\tU\bb\u0002B|\u000b\u0011\u0005!Q\u001f\u0005\b\u0005s,A\u0011\u0001B~\u0011\u001d\u0011y0\u0002C\u0001\u0007\u0003A\u0001b!\u0002\u0006A\u0003&\u00111\u0018\u0005\b\u0007\u000f)A\u0011AB\u0005\u0011\u001d\u0019Y!\u0002C\u0001\u0007\u0013Aqa!\u0004\u0006\t\u0003\u0019y\u0001C\u0004\u0004\u0014\u0015!\ta!\u0006\t\u0011\reQ\u0001)Q\u0005\u0003\u0007Dqaa\u0007\u0006\t\u0003\u0019i\u0002C\u0004\u0004 \u0015!\ta!\b\t\u000f\r\u0005R\u0001\"\u0001\u0004$!91qE\u0003\u0005\u0002\r%\u0002\u0002CB\u0017\u000b\u0001\u0006K!a3\t\u000f\r=R\u0001\"\u0001\u00042!911G\u0003\u0005\u0002\rE\u0002bBB\u001b\u000b\u0011\u00051q\u0007\u0005\b\u0007w)A\u0011AB\u001f\u0011!\u0019\t%\u0002Q!\n\u0005M\u0007bBB\"\u000b\u0011\u00051Q\t\u0005\b\u0007\u000f*A\u0011AB#\u0011\u001d\u0019I%\u0002C\u0001\u0007\u0017Bqaa\u0014\u0006\t\u0003\u0019\t\u0006C\u0004\u0004V\u0015!\tea\u0016\t\u000f\r%T\u0001\"\u0011\u0004l!91\u0011O\u0003\u0005B\rM\u0004bBB>\u000b\u0011\u00053Q\u0010\u0005\b\u0003_)A\u0011ABE\u0011%\u0019i+BI\u0001\n\u0003\u0019y\u000bC\u0005\u0004F\u0016\t\n\u0011\"\u0001\u0004H\"I11Z\u0003\u0012\u0002\u0013\u00051Q\u001a\u0005\n\u0007#,\u0011\u0013!C\u0001\u0007\'D\u0011ba6\u0006#\u0003%\ta!7\t\u0013\ruW!%A\u0005\u0002\r}\u0007\"CBr\u000bE\u0005I\u0011ABs\u0011%\u0019I/BI\u0001\n\u0003\u0019Y\u000fC\u0005\u0004p\u0016\t\n\u0011\"\u0001\u0004r\"I1Q_\u0003\u0012\u0002\u0013\u00051q\u001f\u0005\n\u0007w,\u0011\u0013!C\u0001\u0007{D\u0011\u0002\"\u0001\u0006#\u0003%\t\u0001b\u0001\t\u0013\u0011\u001dQ!%A\u0005\u0002\u0011%\u0001\"\u0003C\u0007\u000bE\u0005I\u0011\u0001C\b\u0011%!\u0019\"BI\u0001\n\u0003!)\u0002C\u0005\u0005\u001a\u0015\t\n\u0011\"\u0001\u0005\u001c!IAqD\u0003\u0012\u0002\u0013\u0005A\u0011\u0005\u0005\b\tK)A\u0011\tC\u0014\u0011\u001d!9%\u0002C!\t\u0013\na!\u0014\"pqF:$\u0002BA\b\u0003#\taa]5sKVl\'BAA\n\u0003\ry\'oZ\u0002\u0001!\r\tI\"A\u0007\u0003\u0003\u001b\u0011a!\u0014\"pqF:4cA\u0001\u0002 A!\u0011\u0011EA\u0014\u001b\t\t\u0019C\u0003\u0002\u0002&\u0005)1oY1mC&!\u0011\u0011FA\u0012\u0005\u0019\te.\u001f*fM\u00061A(\u001b8jiz\"\"!a\u0006\u0002\u000b\u0005\u0004\b\u000f\\=\u0016I\u0005MBQ\u000bC-\t;\"\t\u0007\"\u001a\u0005j\u00115D\u0011\u000fC;\ts\"i\b\"!\u0005\u0006\u0012%EQ\u0012CI\t+#B%!\u000e\u0005\u0018\u0012eE1\u0014CO\t?#\t\u000bb)\u0005&\u0012\u001dF\u0011\u0016CV\t[#y\u000b\"-\u00054\u0012UFq\u0017\t&\u00033)A1\u000bC,\t7\"y\u0006b\u0019\u0005h\u0011-Dq\u000eC:\to\"Y\bb \u0005\u0004\u0012\u001dE1\u0012CH\t\'+B%!\u000f\u0002H\u0005u\u0013QMA7\u0003k\ni(!\"\u0002\u000e\u0006U\u0015QTAS\u0003[\u000b),!0\u0002F\u00065\u0017Q[\n\u0006\u000b\u0005}\u00111\b\t\u0005\u00033\ti$\u0003\u0003\u0002@\u00055!!\u0003*fG>\u0014HmU5h\u0003!yvL^1mk\u0016\f\u0004\u0003BA#\u0003\u000fb\u0001\u0001B\u0004\u0002J\u0015\u0011\r!a\u0013\u0003\u0005Q\u000b\u0014\u0003BA\'\u0003\'\u0002B!!\t\u0002P%!\u0011\u0011KA\u0012\u0005\u001dqu\u000e\u001e5j]\u001e\u0004B!!\t\u0002V%!\u0011qKA\u0012\u0005\r\te._\u0001\t?~3\u0018\r\\;feA!\u0011QIA/\t\u001d\ty&\u0002b\u0001\u0003\u0017\u0012!\u0001\u0016\u001a\u0002\u0011}{f/\u00197vKN\u0002B!!\u0012\u0002f\u00119\u0011qM\u0003C\u0002\u0005-#A\u0001+4\u0003!yvL^1mk\u0016$\u0004\u0003BA#\u0003[\"q!a\u001c\u0006\u0005\u0004\tYE\u0001\u0002Ui\u0005Aql\u0018<bYV,W\u0007\u0005\u0003\u0002F\u0005UDaBA<\u000b\t\u0007\u00111\n\u0002\u0003)V\n\u0001bX0wC2,XM\u000e\t\u0005\u0003\u000b\ni\bB\u0004\u0002\u0000\u0015\u0011\r!a\u0013\u0003\u0005Q3\u0014\u0001C0`m\u0006dW/Z\u001c\u0011\t\u0005\u0015\u0013Q\u0011\u0003\b\u0003\u000f+!\u0019AA&\u0005\t!v\'\u0001\u0005`?Z\fG.^39!\u0011\t)%!$\u0005\u000f\u0005=UA1\u0001\u0002L\t\u0011A\u000bO\u0001\t?~3\u0018\r\\;fsA!\u0011QIAK\t\u001d\t9*\u0002b\u0001\u0003\u0017\u0012!\u0001V\u001d\u0002\u0013}{f/\u00197vKF\u0002\u0004\u0003BA#\u0003;#q!a(\u0006\u0005\u0004\tYEA\u0002UcA\n\u0011bX0wC2,X-M\u0019\u0011\t\u0005\u0015\u0013Q\u0015\u0003\b\u0003O+!\u0019AA&\u0005\r!\u0016\'M\u0001\n?~3\u0018\r\\;fcI\u0002B!!\u0012\u0002.\u00129\u0011qV\u0003C\u0002\u0005-#a\u0001+2e\u0005Iql\u0018<bYV,\u0017g\r\t\u0005\u0003\u000b\n)\fB\u0004\u00028\u0016\u0011\r!a\u0013\u0003\u0007Q\u000b4\'A\u0005`?Z\fG.^32iA!\u0011QIA_\t\u001d\ty,\u0002b\u0001\u0003\u0017\u00121\u0001V\u00195\u0003%yvL^1mk\u0016\fT\u0007\u0005\u0003\u0002F\u0005\u0015GaBAd\u000b\t\u0007\u00111\n\u0002\u0004)F*\u0014!C0`m\u0006dW/Z\u00197!\u0011\t)%!4\u0005\u000f\u0005=WA1\u0001\u0002L\t\u0019A+\r\u001c\u0002\u0013}{f/\u00197vKF:\u0004\u0003BA#\u0003+$q!a6\u0006\u0005\u0004\tYEA\u0002Uc]\"B%a7\u0002^\u0006}\u0017\u0011]Ar\u0003K\f9/!;\u0002l\u00065\u0018q^Ay\u0003g\f)0a>\u0002z\u0006m\u0018Q \t&\u00033)\u00111IA.\u0003G\nY\'a\u001d\u0002|\u0005\r\u00151RAJ\u00037\u000b\u0019+a+\u00024\u0006m\u00161YAf\u0003\'Dq!!\u0011\u0018\u0001\u0004\t\u0019\u0005C\u0004\u0002Z]\u0001\r!a\u0017\t\u000f\u0005\u0005t\u00031\u0001\u0002d!9\u0011\u0011N\fA\u0002\u0005-\u0004bBA9/\u0001\u0007\u00111\u000f\u0005\b\u0003s:\u0002\u0019AA>\u0011\u001d\t\ti\u0006a\u0001\u0003\u0007Cq!!#\u0018\u0001\u0004\tY\tC\u0004\u0002\u0012^\u0001\r!a%\t\u000f\u0005eu\u00031\u0001\u0002\u001c\"9\u0011\u0011U\fA\u0002\u0005\r\u0006bBAU/\u0001\u0007\u00111\u0016\u0005\b\u0003c;\u0002\u0019AAZ\u0011\u001d\tIl\u0006a\u0001\u0003wCq!!1\u0018\u0001\u0004\t\u0019\rC\u0004\u0002J^\u0001\r!a3\t\u000f\u0005Ew\u00031\u0001\u0002T\u00069qL^1mk\u0016\f\u0014A\u0002<bYV,\u0017\'\u0006\u0002\u0002D\u0005Iq-\u001a;WC2,X-M\u0001\u000bm\u0006dW/Z\u0019`I\u0015\fH\u0003\u0002B\u0006\u0005\u001bi\u0011!\u0002\u0005\b\u0005\u0003Y\u0002\u0019AA\"\u0003%\u0019X\r\u001e,bYV,\u0017\u0007\u0006\u0003\u0003\f\tM\u0001b\u0002B\u00019\u0001\u0007\u00111I\u0001\b?Z\fG.^33\u0003\u00191\u0018\r\\;feU\u0011\u00111L\u0001\nO\u0016$h+\u00197vKJ\n!B^1mk\u0016\u0014t\fJ3r)\u0011\u0011YA!\t\t\u000f\t]\u0001\u00051\u0001\u0002\\\u0005I1/\u001a;WC2,XM\r\u000b\u0005\u0005\u0017\u00119\u0003C\u0004\u0003\u0018\u0005\u0002\r!a\u0017\u0002\u000f}3\u0018\r\\;fg\u00051a/\u00197vKN*\"!a\u0019\u0002\u0013\u001d,GOV1mk\u0016\u001c\u0014A\u0003<bYV,7g\u0018\u0013fcR!!1\u0002B\u001b\u0011\u001d\u0011Y#\na\u0001\u0003G\n\u0011b]3u-\u0006dW/Z\u001a\u0015\t\t-!1\b\u0005\b\u0005W1\u0003\u0019AA2\u0003\u001dyf/\u00197vKR\naA^1mk\u0016$TCAA6\u0003%9W\r\u001e,bYV,G\'\u0001\u0006wC2,X\rN0%KF$BAa\u0003\u0003J!9!q\b\u0016A\u0002\u0005-\u0014!C:fiZ\u000bG.^35)\u0011\u0011YAa\u0014\t\u000f\t}2\u00061\u0001\u0002l\u00059qL^1mk\u0016,\u0014A\u0002<bYV,W\'\u0006\u0002\u0002t\u0005Iq-\u001a;WC2,X-N\u0001\u000bm\u0006dW/Z\u001b`I\u0015\fH\u0003\u0002B\u0006\u0005;BqAa\u00150\u0001\u0004\t\u0019(A\u0005tKR4\u0016\r\\;fkQ!!1\u0002B2\u0011\u001d\u0011\u0019\u0006\ra\u0001\u0003g\nqa\u0018<bYV,g\'\u0001\u0004wC2,XMN\u000b\u0003\u0003w\n\u0011bZ3u-\u0006dW/\u001a\u001c\u0002\u0015Y\fG.^37?\u0012*\u0017\u000f\u0006\u0003\u0003\f\tE\u0004b\u0002B4i\u0001\u0007\u00111P\u0001\ng\u0016$h+\u00197vKZ\"BAa\u0003\u0003x!9!qM\u001bA\u0002\u0005m\u0014aB0wC2,XmN\u0001\u0007m\u0006dW/Z\u001c\u0016\u0005\u0005\r\u0015!C4fiZ\u000bG.^38\u0003)1\u0018\r\\;fo}#S-\u001d\u000b\u0005\u0005\u0017\u0011)\tC\u0004\u0003|e\u0002\r!a!\u0002\u0013M,GOV1mk\u0016<D\u0003\u0002B\u0006\u0005\u0017CqAa\u001f;\u0001\u0004\t\u0019)A\u0004`m\u0006dW/\u001a\u001d\u0002\rY\fG.^39+\t\tY)A\u0005hKR4\u0016\r\\;fq\u0005Qa/\u00197vKbzF%Z9\u0015\t\t-!\u0011\u0014\u0005\b\u0005\u001fs\u0004\u0019AAF\u0003%\u0019X\r\u001e,bYV,\u0007\b\u0006\u0003\u0003\f\t}\u0005b\u0002BH\u007f\u0001\u0007\u00111R\u0001\b?Z\fG.^3:\u0003\u00191\u0018\r\\;fsU\u0011\u00111S\u0001\nO\u0016$h+\u00197vKf\n!B^1mk\u0016Lt\fJ3r)\u0011\u0011YA!,\t\u000f\t\r6\t1\u0001\u0002\u0014\u0006I1/\u001a;WC2,X-\u000f\u000b\u0005\u0005\u0017\u0011\u0019\fC\u0004\u0003$\u0012\u0003\r!a%\u0002\u0011}3\u0018\r\\;fcA\nqA^1mk\u0016\f\u0004\'\u0006\u0002\u0002\u001c\u0006Qq-\u001a;WC2,X-\r\u0019\u0002\u0017Y\fG.^32a}#S-\u001d\u000b\u0005\u0005\u0017\u0011\t\rC\u0004\u00038\"\u0003\r!a\'\u0002\u0015M,GOV1mk\u0016\f\u0004\u0007\u0006\u0003\u0003\f\t\u001d\u0007b\u0002B\\\u0013\u0002\u0007\u00111T\u0001\t?Z\fG.^32c\u00059a/\u00197vKF\nTCAAR\u0003)9W\r\u001e,bYV,\u0017\'M\u0001\fm\u0006dW/Z\u00192?\u0012*\u0017\u000f\u0006\u0003\u0003\f\tU\u0007b\u0002Bf\u001b\u0002\u0007\u00111U\u0001\u000bg\u0016$h+\u00197vKF\nD\u0003\u0002B\u0006\u00057DqAa3O\u0001\u0004\t\u0019+\u0001\u0005`m\u0006dW/Z\u00193\u0003\u001d1\u0018\r\\;fcI*\"!a+\u0002\u0015\u001d,GOV1mk\u0016\f$\'A\u0006wC2,X-\r\u001a`I\u0015\fH\u0003\u0002B\u0006\u0005SDqAa8S\u0001\u0004\tY+\u0001\u0006tKR4\u0016\r\\;fcI\"BAa\u0003\u0003p\"9!q\\*A\u0002\u0005-\u0016\u0001C0wC2,X-M\u001a\u0002\u000fY\fG.^32gU\u0011\u00111W\u0001\u000bO\u0016$h+\u00197vKF\u001a\u0014a\u0003<bYV,\u0017gM0%KF$BAa\u0003\u0003~\"9!1_,A\u0002\u0005M\u0016AC:fiZ\u000bG.^32gQ!!1BB\u0002\u0011\u001d\u0011\u0019\u0010\u0017a\u0001\u0003g\u000b\u0001b\u0018<bYV,\u0017\u0007N\u0001\bm\u0006dW/Z\u00195+\t\tY,\u0001\u0006hKR4\u0016\r\\;fcQ\n1B^1mk\u0016\fDg\u0018\u0013fcR!!1BB\t\u0011\u001d\u00199\u0001\u0018a\u0001\u0003w\u000b!b]3u-\u0006dW/Z\u00195)\u0011\u0011Yaa\u0006\t\u000f\r\u001dQ\f1\u0001\u0002<\u0006AqL^1mk\u0016\fT\'A\u0004wC2,X-M\u001b\u0016\u0005\u0005\r\u0017AC4fiZ\u000bG.^32k\u0005Ya/\u00197vKF*t\fJ3r)\u0011\u0011Ya!\n\t\u000f\rm\u0011\r1\u0001\u0002D\u0006Q1/\u001a;WC2,X-M\u001b\u0015\t\t-11\u0006\u0005\b\u00077\u0011\u0007\u0019AAb\u0003!yf/\u00197vKF2\u0014a\u0002<bYV,\u0017GN\u000b\u0003\u0003\u0017\f!bZ3u-\u0006dW/Z\u00197\u0003-1\u0018\r\\;fcYzF%Z9\u0015\t\t-1\u0011\b\u0005\b\u0007_1\u0007\u0019AAf\u0003)\u0019X\r\u001e,bYV,\u0017G\u000e\u000b\u0005\u0005\u0017\u0019y\u0004C\u0004\u00040\u001d\u0004\r!a3\u0002\u0011}3\u0018\r\\;fc]\nqA^1mk\u0016\ft\'\u0006\u0002\u0002T\u0006Qq-\u001a;WC2,X-M\u001c\u0002\u0017Y\fG.^32o}#S-\u001d\u000b\u0005\u0005\u0017\u0019i\u0005C\u0004\u0004D-\u0004\r!a5\u0002\u0015M,GOV1mk\u0016\ft\u0007\u0006\u0003\u0003\f\rM\u0003bBB\"Y\u0002\u0007\u00111[\u0001\ti>\u001cFO]5oOR\u00111\u0011\f\t\u0005\u00077\u001a)\'\u0004\u0002\u0004^)!1qLB1\u0003\u0011a\u0017M\\4\u000b\u0005\r\r\u0014\u0001\u00026bm\u0006LAaa\u001a\u0004^\t11\u000b\u001e:j]\u001e\faa\u001d;sS:<WCAB7!\u0011\tIba\u001c\n\t\r\u001d\u0014QB\u0001\tQ\u0006\u001c\bnQ8eKR\u00111Q\u000f\t\u0005\u0003C\u00199(\u0003\u0003\u0004z\u0005\r\"aA%oi\u00061Q-];bYN$Baa \u0004\u0006B!\u0011\u0011EBA\u0013\u0011\u0019\u0019)a\t\u0003\u000f\t{w\u000e\\3b]\"91q\u00119A\u0002\u0005M\u0013!A8\u0015I\u0005m71RBG\u0007\u001f\u001b\tja%\u0004\u0016\u000e]5\u0011TBN\u0007;\u001byj!)\u0004$\u000e\u00156qUBU\u0007WC\u0011B!\u0001r!\u0003\u0005\r!a\u0011\t\u0013\t]\u0011\u000f%AA\u0002\u0005m\u0003\"\u0003B\u0016cB\u0005\t\u0019AA2\u0011%\u0011y$\u001dI\u0001\u0002\u0004\tY\u0007C\u0005\u0003TE\u0004\n\u00111\u0001\u0002t!I!qM9\u0011\u0002\u0003\u0007\u00111\u0010\u0005\n\u0005w\n\b\u0013!a\u0001\u0003\u0007C\u0011Ba$r!\u0003\u0005\r!a#\t\u0013\t\r\u0016\u000f%AA\u0002\u0005M\u0005\"\u0003B\\cB\u0005\t\u0019AAN\u0011%\u0011Y-\u001dI\u0001\u0002\u0004\t\u0019\u000bC\u0005\u0003`F\u0004\n\u00111\u0001\u0002,\"I!1_9\u0011\u0002\u0003\u0007\u00111\u0017\u0005\n\u0007\u000f\t\b\u0013!a\u0001\u0003wC\u0011ba\u0007r!\u0003\u0005\r!a1\t\u0013\r=\u0012\u000f%AA\u0002\u0005-\u0007\"CB\"cB\u0005\t\u0019AAj\u0003=\t\u0007\u000f\u001d7zI\u0011,g-Y;mi\u0012\nTCABYU\u0011\t\u0019ea-,\u0005\rU\u0006\u0003BB\\\u0007\u0003l!a!/\u000b\t\rm6QX\u0001\nk:\u001c\u0007.Z2lK\u0012TAaa0\u0002$\u0005Q\u0011M\u001c8pi\u0006$\u0018n\u001c8\n\t\r\r7\u0011\u0018\u0002\u0012k:\u001c\u0007.Z2lK\u00124\u0016M]5b]\u000e,\u0017aD1qa2LH\u0005Z3gCVdG\u000f\n\u001a\u0016\u0005\r%\'\u0006BA.\u0007g\u000bq\"\u00199qYf$C-\u001a4bk2$HeM\u000b\u0003\u0007\u001fTC!a\u0019\u00044\u0006y\u0011\r\u001d9ms\u0012\"WMZ1vYR$C\'\u0006\u0002\u0004V*\"\u00111NBZ\u0003=\t\u0007\u000f\u001d7zI\u0011,g-Y;mi\u0012*TCABnU\u0011\t\u0019ha-\u0002\u001f\u0005\u0004\b\u000f\\=%I\u00164\u0017-\u001e7uIY*\"a!9+\t\u0005m41W\u0001\u0010CB\u0004H.\u001f\u0013eK\u001a\fW\u000f\u001c;%oU\u00111q\u001d\u0016\u0005\u0003\u0007\u001b\u0019,A\bbaBd\u0017\u0010\n3fM\u0006,H\u000e\u001e\u00139+\t\u0019iO\u000b\u0003\u0002\f\u000eM\u0016aD1qa2LH\u0005Z3gCVdG\u000fJ\u001d\u0016\u0005\rM(\u0006BAJ\u0007g\u000b\u0001#\u00199qYf$C-\u001a4bk2$H%\r\u0019\u0016\u0005\re(\u0006BAN\u0007g\u000b\u0001#\u00199qYf$C-\u001a4bk2$H%M\u0019\u0016\u0005\r}(\u0006BAR\u0007g\u000b\u0001#\u00199qYf$C-\u001a4bk2$H%\r\u001a\u0016\u0005\u0011\u0015!\u0006BAV\u0007g\u000b\u0001#\u00199qYf$C-\u001a4bk2$H%M\u001a\u0016\u0005\u0011-!\u0006BAZ\u0007g\u000b\u0001#\u00199qYf$C-\u001a4bk2$H%\r\u001b\u0016\u0005\u0011E!\u0006BA^\u0007g\u000b\u0001#\u00199qYf$C-\u001a4bk2$H%M\u001b\u0016\u0005\u0011]!\u0006BAb\u0007g\u000b\u0001#\u00199qYf$C-\u001a4bk2$H%\r\u001c\u0016\u0005\u0011u!\u0006BAf\u0007g\u000b\u0001#\u00199qYf$C-\u001a4bk2$H%M\u001c\u0016\u0005\u0011\r\"\u0006BAj\u0007g\u000b\u0001\u0002J2p]R,g\u000e^\u000b\u0003\tS\u0001b\u0001b\u000b\u0005<\u0011\u0005c\u0002\u0002C\u0017\toqA\u0001b\f\u000565\u0011A\u0011\u0007\u0006\u0005\tg\t)\"\u0001\u0004=e>|GOP\u0005\u0003\u0003KIA\u0001\"\u000f\u0002$\u00059\u0001/Y2lC\u001e,\u0017\u0002\u0002C\u001f\t\u007f\u00111aU3r\u0015\u0011!I$a\t\u0011\u0011\u0005\u0005B1IB-\u0003\'JA\u0001\"\u0012\u0002$\t1A+\u001e9mKJ\na\u0001J2m_:,WCAAnQ\r)AQ\n\t\u0005\u00033!y%\u0003\u0003\u0005R\u00055!A\u0002:fG>\u0014H\r\u0005\u0003\u0002F\u0011UCaBA%\u0007\t\u0007\u00111\n\t\u0005\u0003\u000b\"I\u0006B\u0004\u0002`\r\u0011\r!a\u0013\u0011\t\u0005\u0015CQ\f\u0003\b\u0003O\u001a!\u0019AA&!\u0011\t)\u0005\"\u0019\u0005\u000f\u0005=4A1\u0001\u0002LA!\u0011Q\tC3\t\u001d\t9h\u0001b\u0001\u0003\u0017\u0002B!!\u0012\u0005j\u00119\u0011qP\u0002C\u0002\u0005-\u0003\u0003BA#\t[\"q!a\"\u0004\u0005\u0004\tY\u0005\u0005\u0003\u0002F\u0011EDaBAH\u0007\t\u0007\u00111\n\t\u0005\u0003\u000b\")\bB\u0004\u0002\u0018\u000e\u0011\r!a\u0013\u0011\t\u0005\u0015C\u0011\u0010\u0003\b\u0003?\u001b!\u0019AA&!\u0011\t)\u0005\" \u0005\u000f\u0005\u001d6A1\u0001\u0002LA!\u0011Q\tCA\t\u001d\tyk\u0001b\u0001\u0003\u0017\u0002B!!\u0012\u0005\u0006\u00129\u0011qW\u0002C\u0002\u0005-\u0003\u0003BA#\t\u0013#q!a0\u0004\u0005\u0004\tY\u0005\u0005\u0003\u0002F\u00115EaBAd\u0007\t\u0007\u00111\n\t\u0005\u0003\u000b\"\t\nB\u0004\u0002P\u000e\u0011\r!a\u0013\u0011\t\u0005\u0015CQ\u0013\u0003\b\u0003/\u001c!\u0019AA&\u0011\u001d\u0011\ta\u0001a\u0001\t\'BqAa\u0006\u0004\u0001\u0004!9\u0006C\u0004\u0003,\r\u0001\r\u0001b\u0017\t\u000f\t}2\u00011\u0001\u0005`!9!1K\u0002A\u0002\u0011\r\u0004b\u0002B4\u0007\u0001\u0007Aq\r\u0005\b\u0005w\u001a\u0001\u0019\u0001C6\u0011\u001d\u0011yi\u0001a\u0001\t_BqAa)\u0004\u0001\u0004!\u0019\bC\u0004\u00038\u000e\u0001\r\u0001b\u001e\t\u000f\t-7\u00011\u0001\u0005|!9!q\\\u0002A\u0002\u0011}\u0004b\u0002Bz\u0007\u0001\u0007A1\u0011\u0005\b\u0007\u000f\u0019\u0001\u0019\u0001CD\u0011\u001d\u0019Yb\u0001a\u0001\t\u0017Cqaa\f\u0004\u0001\u0004!y\tC\u0004\u0004D\r\u0001\r\u0001b%\u0002\u000fUt\u0017\r\u001d9msV!CQ\u0018Cg\t#$)\u000e\"7\u0005^\u0012\u0005HQ\u001dCu\t[$\t\u0010\">\u0005z\u0012uX\u0011AC\u0003\u000b\u0013)i\u0001\u0006\u0003\u0005@\u0016=\u0001CBA\u0011\t\u0003$)-\u0003\u0003\u0005D\u0006\r\"\u0001B*p[\u0016\u0004b%!\t\u0005H\u0012-Gq\u001aCj\t/$Y\u000eb8\u0005d\u0012\u001dH1\u001eCx\tg$9\u0010b?\u0005\u0000\u0016\rQqAC\u0006\u0013\u0011!I-a\t\u0003\u000fQ+\b\u000f\\32oA!\u0011Q\tCg\t\u001d\tI\u0005\u0002b\u0001\u0003\u0017\u0002B!!\u0012\u0005R\u00129\u0011q\f\u0003C\u0002\u0005-\u0003\u0003BA#\t+$q!a\u001a\u0005\u0005\u0004\tY\u0005\u0005\u0003\u0002F\u0011eGaBA8\t\t\u0007\u00111\n\t\u0005\u0003\u000b\"i\u000eB\u0004\u0002x\u0011\u0011\r!a\u0013\u0011\t\u0005\u0015C\u0011\u001d\u0003\b\u0003\u007f\"!\u0019AA&!\u0011\t)\u0005\":\u0005\u000f\u0005\u001dEA1\u0001\u0002LA!\u0011Q\tCu\t\u001d\ty\t\u0002b\u0001\u0003\u0017\u0002B!!\u0012\u0005n\u00129\u0011q\u0013\u0003C\u0002\u0005-\u0003\u0003BA#\tc$q!a(\u0005\u0005\u0004\tY\u0005\u0005\u0003\u0002F\u0011UHaBAT\t\t\u0007\u00111\n\t\u0005\u0003\u000b\"I\u0010B\u0004\u00020\u0012\u0011\r!a\u0013\u0011\t\u0005\u0015CQ \u0003\b\u0003o#!\u0019AA&!\u0011\t)%\"\u0001\u0005\u000f\u0005}FA1\u0001\u0002LA!\u0011QIC\u0003\t\u001d\t9\r\u0002b\u0001\u0003\u0017\u0002B!!\u0012\u0006\n\u00119\u0011q\u001a\u0003C\u0002\u0005-\u0003\u0003BA#\u000b\u001b!q!a6\u0005\u0005\u0004\tY\u0005C\u0004\u0004\b\u0012\u0001\r!\"\u0005\u0011K\u0005eQ\u0001b3\u0005P\u0012MGq\u001bCn\t?$\u0019\u000fb:\u0005l\u0012=H1\u001fC|\tw$y0b\u0001\u0006\b\u0015-\u0001"
    )
  ScalaInlineInfo: length = 0x20C (unknown attribute)
   01 01 00 68 00 52 00 53 01 01 BB 00 69 01 01 BB
   01 CD 01 01 BB 01 BC 01 01 8B 01 8C 01 00 5A 00
   3F 01 00 5F 00 3F 01 00 3E 00 3F 01 00 45 01 C8
   01 00 45 00 46 01 00 FC 01 77 01 01 3E 01 75 01
   01 7A 00 69 01 01 83 00 69 01 01 84 00 69 01 01
   85 00 69 01 01 86 00 69 01 01 87 00 69 01 01 88
   00 69 01 01 89 00 69 01 01 8A 00 69 01 01 7B 00
   69 01 01 7C 00 69 01 01 7D 00 69 01 01 7E 00 69
   01 01 7F 00 69 01 01 80 00 69 01 01 81 00 69 01
   01 82 00 69 01 01 6B 01 6C 01 00 6D 00 69 01 00
   B6 00 69 01 00 BE 00 69 01 00 C6 00 69 01 00 CE
   00 69 01 00 D6 00 69 01 00 DE 00 69 01 00 E6 00
   69 01 00 EE 00 69 01 00 76 00 69 01 00 7E 00 69
   01 00 86 00 69 01 00 8E 00 69 01 00 96 00 69 01
   00 9E 00 69 01 00 A6 00 69 01 00 AE 00 69 01 00
   4C 00 4D 01 01 42 01 43 01 00 2F 00 3F 01 00 65
   00 66 01 00 71 00 6F 01 00 B9 00 6F 01 00 C1 00
   6F 01 00 C9 00 6F 01 00 D1 00 6F 01 00 D9 00 6F
   01 00 E1 00 6F 01 00 E9 00 6F 01 00 F1 00 6F 01
   00 79 00 6F 01 00 81 00 6F 01 00 89 00 6F 01 00
   91 00 6F 01 00 99 00 6F 01 00 A1 00 6F 01 00 A9
   00 6F 01 00 B1 00 6F 01 01 3C 00 F3 01 00 F2 00
   F3 01 00 68 00 69 01 00 B2 00 69 01 00 B7 00 6F
   01 00 BA 00 69 01 00 BF 00 6F 01 00 C2 00 69 01
   00 C7 00 6F 01 00 CA 00 69 01 00 CF 00 6F 01 00
   D2 00 69 01 00 D7 00 6F 01 00 DA 00 69 01 00 DF
   00 6F 01 00 E2 00 69 01 00 E7 00 6F 01 00 EA 00
   69 01 00 EF 00 6F 01 00 6E 00 6F 01 00 72 00 69
   01 00 77 00 6F 01 00 7A 00 69 01 00 7F 00 6F 01
   00 82 00 69 01 00 87 00 6F 01 00 8A 00 69 01 00
   8F 00 6F 01 00 92 00 69 01 00 97 00 6F 01 00 9A
   00 69 01 00 9F 00 6F 01 00 A2 00 69 01 00 A7 00
   6F 01 00 AA 00 69 01 00 AF 00 6F 01
  ScalaSig: length = 0x3 (unknown attribute)
   05 02 00
