Classfile /Users/mw/Projects/slang-braindump/.jar/jar8/assemble/slang-braindump/assemble/content/org/sireum/MBox7.class
  Last modified May 29, 2022; size 14117 bytes
  SHA-256 checksum 0209eb7376069044fa1a2ce65f322980f543f572377f63c32f4fce5fc77450a4
  Compiled from "MBox.scala"
public final class org.sireum.MBox7<T1 extends java.lang.Object, T2 extends java.lang.Object, T3 extends java.lang.Object, T4 extends java.lang.Object, T5 extends java.lang.Object, T6 extends java.lang.Object, T7 extends java.lang.Object> extends java.lang.Object implements org.sireum.RecordSig
  minor version: 0
  major version: 52
  flags: (0x0031) ACC_PUBLIC, ACC_FINAL, ACC_SUPER
  this_class: #2                          // org/sireum/MBox7
  super_class: #5                         // java/lang/Object
  interfaces: 1, fields: 8, methods: 55, attributes: 5
Constant pool:
    #1 = Utf8               org/sireum/MBox7
    #2 = Class              #1            // org/sireum/MBox7
    #3 = Utf8               <T1:Ljava/lang/Object;T2:Ljava/lang/Object;T3:Ljava/lang/Object;T4:Ljava/lang/Object;T5:Ljava/lang/Object;T6:Ljava/lang/Object;T7:Ljava/lang/Object;>Ljava/lang/Object;Lorg/sireum/RecordSig;
    #4 = Utf8               java/lang/Object
    #5 = Class              #4            // java/lang/Object
    #6 = Utf8               org/sireum/RecordSig
    #7 = Class              #6            // org/sireum/RecordSig
    #8 = Utf8               MBox.scala
    #9 = Utf8               Lscala/reflect/ScalaSignature;
   #10 = Utf8               bytes
   #11 = Utf8               \u0006\u0005\t\u001dv!B A\u0011\u0003)e!B$A\u0011\u0003A\u0005\"B(\u0002\t\u0003\u0001\u0006\"B)\u0002\t\u0003\u0011\u0006b\u0002B;\u0003\u0011\u0005!q\u000f\u0004\u0005\u000f\u0002\u0013Q\u000b\u0003\u0005[\u000b\t\u0005\t\u0015!\u0003\\\u0011!1WA!A!\u0002\u00139\u0007\u0002\u00036\u0006\u0005\u0003\u0005\u000b\u0011B6\t\u00119,!\u0011!Q\u0001\n=D\u0001B]\u0003\u0003\u0002\u0003\u0006Ia\u001d\u0005\tm\u0016\u0011\t\u0011)A\u0005o\"A!0\u0002B\u0001B\u0003%1\u0010C\u0003P\u000b\u0011\u0005a\u0010C\u0004\u0002\u0010\u0015\u0001\u000b\u0015B.\t\u000f\u0005EQ\u0001\"\u0001\u0002\u0014!9\u0011QC\u0003\u0005\u0002\u0005M\u0001bBA\f\u000b\u0011\u0005\u0011\u0011\u0004\u0005\b\u0003?)A\u0011AA\u0011\u0011\u001d\t)#\u0002Q!\n\u001dDq!a\n\u0006\t\u0003\tI\u0003C\u0004\u0002,\u0015!\t!!\u000b\t\u000f\u00055R\u0001\"\u0001\u00020!9\u00111G\u0003\u0005\u0002\u0005U\u0002bBA\u001d\u000b\u0001\u0006Ka\u001b\u0005\b\u0003w)A\u0011AA\u001f\u0011\u001d\ty$\u0002C\u0001\u0003{Aq!!\u0011\u0006\t\u0003\t\u0019\u0005C\u0004\u0002H\u0015!\t!!\u0013\t\u000f\u00055S\u0001)Q\u0005_\"9\u0011qJ\u0003\u0005\u0002\u0005E\u0003bBA*\u000b\u0011\u0005\u0011\u0011\u000b\u0005\b\u0003+*A\u0011AA,\u0011\u001d\tY&\u0002C\u0001\u0003;Bq!!\u0019\u0006A\u0003&1\u000fC\u0004\u0002d\u0015!\t!!\u001a\t\u000f\u0005\u001dT\u0001\"\u0001\u0002f!9\u0011\u0011N\u0003\u0005\u0002\u0005-\u0004bBA8\u000b\u0011\u0005\u0011\u0011\u000f\u0005\b\u0003k*\u0001\u0015)\u0003x\u0011\u001d\t9(\u0002C\u0001\u0003sBq!a\u001f\u0006\t\u0003\tI\bC\u0004\u0002~\u0015!\t!a \t\u000f\u0005\rU\u0001\"\u0001\u0002\u0006\"9\u0011\u0011R\u0003!B\u0013Y\bbBAF\u000b\u0011\u0005\u0011Q\u0012\u0005\b\u0003\u001f+A\u0011AAG\u0011\u001d\t\t*\u0002C\u0001\u0003\'Cq!a&\u0006\t\u0003\tI\nC\u0004\u0002\u001e\u0016!\t%a(\t\u000f\u0005EV\u0001\"\u0011\u00024\"9\u0011\u0011X\u0003\u0005B\u0005m\u0006bBAb\u000b\u0011\u0005\u0013Q\u0019\u0005\u0007#\u0016!\t!!5\t\u0013\u0005\u0005X!%A\u0005\u0002\u0005\r\b\"CA}\u000bE\u0005I\u0011AA~\u0011%\ty0BI\u0001\n\u0003\u0011\t\u0001C\u0005\u0003\u0006\u0015\t\n\u0011\"\u0001\u0003\b!I!1B\u0003\u0012\u0002\u0013\u0005!Q\u0002\u0005\n\u0005#)\u0011\u0013!C\u0001\u0005\'A\u0011Ba\u0006\u0006#\u0003%\tA!\u0007\t\u000f\tuQ\u0001\"\u0011\u0003 !9!qH\u0003\u0005B\t\u0005\u0013!B\'C_b<$BA!C\u0003\u0019\u0019\u0018N]3v[*\t1)A\u0002pe\u001e\u001c\u0001\u0001\u0005\u0002G\u00035\t\u0001IA\u0003N\u0005>Dxg\u0005\u0002\u0002\u0013B\u0011!*T\u0007\u0002\u0017*\tA*A\u0003tG\u0006d\u0017-\u0003\u0002O\u0017\n1\u0011I\\=SK\u001a\fa\u0001P5oSRtD#A#\u0002\u000b\u0005\u0004\b\u000f\\=\u0016\u001fM\u0013iE!\u0015\u0003V\te#Q\fB1\u0005K\"r\u0002\u0016B4\u0005S\u0012YG!\u001c\u0003p\tE$1\u000f\t\u0011\r\u0016\u0011YEa\u0014\u0003T\t]#1\fB0\u0005G*\u0002BV/iYB$\b\u0010`\n\u0004\u000b%;\u0006C\u0001$Y\u0013\tI\u0006IA\u0005SK\u000e|\'\u000fZ*jO\u0006Aql\u0018<bYV,\u0017\u0007\u0005\u0002];2\u0001A!\u00020\u0006\u0005\u0004y&A\u0001+2#\t\u00017\r\u0005\u0002KC&\u0011!m\u0013\u0002\b\u001d>$\b.\u001b8h!\tQE-\u0003\u0002f\u0017\n\u0019\u0011I\\=\u0002\u0011}{f/\u00197vKJ\u0002\"\u0001\u00185\u0005\u000b%,!\u0019A0\u0003\u0005Q\u0013\u0014\u0001C0`m\u0006dW/Z\u001a\u0011\u0005qcG!B7\u0006\u0005\u0004y&A\u0001+4\u0003!yvL^1mk\u0016$\u0004C\u0001/q\t\u0015\tXA1\u0001`\u0005\t!F\'\u0001\u0005`?Z\fG.^36!\taF\u000fB\u0003v\u000b\t\u0007qL\u0001\u0002Uk\u0005Aql\u0018<bYV,g\u0007\u0005\u0002]q\u0012)\u00110\u0002b\u0001?\n\u0011AKN\u0001\t?~3\u0018\r\\;foA\u0011A\f \u0003\u0006{\u0016\u0011\ra\u0018\u0002\u0003)^\"rb`A\u0001\u0003\u0007\t)!a\u0002\u0002\n\u0005-\u0011Q\u0002\t\n\r\u0016Yvm[8tonDQAW\u0007A\u0002mCQAZ\u0007A\u0002\u001dDQA[\u0007A\u0002-DQA\\\u0007A\u0002=DQA]\u0007A\u0002MDQA^\u0007A\u0002]DQA_\u0007A\u0002m\fqa\u0018<bYV,\u0017\'\u0001\u0004wC2,X-M\u000b\u00027\u0006Iq-\u001a;WC2,X-M\u0001\u000bm\u0006dW/Z\u0019`I\u0015\fH\u0003BA\u000e\u0003;i\u0011!\u0002\u0005\u0007\u0003#\t\u0002\u0019A.\u0002\u0013M,GOV1mk\u0016\fD\u0003BA\u000e\u0003GAa!!\u0005\u0013\u0001\u0004Y\u0016aB0wC2,XMM\u0001\u0007m\u0006dW/\u001a\u001a\u0016\u0003\u001d\f\u0011bZ3u-\u0006dW/\u001a\u001a\u0002\u0015Y\fG.^33?\u0012*\u0017\u000f\u0006\u0003\u0002\u001c\u0005E\u0002BBA\u0014-\u0001\u0007q-A\u0005tKR4\u0016\r\\;feQ!\u00111DA\u001c\u0011\u0019\t9c\u0006a\u0001O\u00069qL^1mk\u0016\u001c\u0014A\u0002<bYV,7\'F\u0001l\u0003%9W\r\u001e,bYV,7\'\u0001\u0006wC2,XmM0%KF$B!a\u0007\u0002F!1\u00111H\u000eA\u0002-\f\u0011b]3u-\u0006dW/Z\u001a\u0015\t\u0005m\u00111\n\u0005\u0007\u0003wa\u0002\u0019A6\u0002\u000f}3\u0018\r\\;fi\u00051a/\u00197vKR*\u0012a\\\u0001\nO\u0016$h+\u00197vKR\n!B^1mk\u0016$t\fJ3r)\u0011\tY\"!\u0017\t\r\u0005=\u0003\u00051\u0001p\u0003%\u0019X\r\u001e,bYV,G\u0007\u0006\u0003\u0002\u001c\u0005}\u0003BBA(C\u0001\u0007q.A\u0004`m\u0006dW/Z\u001b\u0002\rY\fG.^36+\u0005\u0019\u0018!C4fiZ\u000bG.^36\u0003)1\u0018\r\\;fk}#S-\u001d\u000b\u0005\u00037\ti\u0007\u0003\u0004\u0002d\u0015\u0002\ra]\u0001\ng\u0016$h+\u00197vKV\"B!a\u0007\u0002t!1\u00111\r\u0014A\u0002M\fqa\u0018<bYV,g\'\u0001\u0004wC2,XMN\u000b\u0002o\u0006Iq-\u001a;WC2,XMN\u0001\u000bm\u0006dW/\u001a\u001c`I\u0015\fH\u0003BA\u000e\u0003\u0003Ca!a\u001e+\u0001\u00049\u0018!C:fiZ\u000bG.^37)\u0011\tY\"a\"\t\r\u0005]4\u00061\u0001x\u0003\u001dyf/\u00197vK^\naA^1mk\u0016<T#A>\u0002\u0013\u001d,GOV1mk\u0016<\u0014A\u0003<bYV,wg\u0018\u0013fcR!\u00111DAK\u0011\u0019\tYi\fa\u0001w\u0006I1/\u001a;WC2,Xm\u000e\u000b\u0005\u00037\tY\n\u0003\u0004\u0002\fB\u0002\ra_\u0001\ti>\u001cFO]5oOR\u0011\u0011\u0011\u0015\t\u0005\u0003G\u000bi+\u0004\u0002\u0002&*!\u0011qUAU\u0003\u0011a\u0017M\\4\u000b\u0005\u0005-\u0016\u0001\u00026bm\u0006LA!a,\u0002&\n11\u000b\u001e:j]\u001e\faa\u001d;sS:<WCAA[!\r1\u0015qW\u0005\u0004\u0003_\u0003\u0015\u0001\u00035bg\"\u001cu\u000eZ3\u0015\u0005\u0005u\u0006c\u0001&\u0002@&\u0019\u0011\u0011Y&\u0003\u0007%sG/\u0001\u0004fcV\fGn\u001d\u000b\u0005\u0003\u000f\fi\rE\u0002K\u0003\u0013L1!a3L\u0005\u001d\u0011un\u001c7fC:Da!a45\u0001\u0004\u0019\u0017!A8\u0015\u001f}\f\u0019.!6\u0002X\u0006e\u00171\\Ao\u0003?D\u0001\"!\u00056!\u0003\u0005\ra\u0017\u0005\t\u0003O)\u0004\u0013!a\u0001O\"A\u00111H\u001b\u0011\u0002\u0003\u00071\u000e\u0003\u0005\u0002PU\u0002\n\u00111\u0001p\u0011!\t\u0019\'\u000eI\u0001\u0002\u0004\u0019\b\u0002CA<kA\u0005\t\u0019A<\t\u0011\u0005-U\u0007%AA\u0002m\fq\"\u00199qYf$C-\u001a4bk2$H%M\u000b\u0003\u0003KT3aWAtW\t\tI\u000f\u0005\u0003\u0002l\u0006UXBAAw\u0015\u0011\ty/!=\u0002\u0013Ut7\r[3dW\u0016$\'bAAz\u0017\u0006Q\u0011M\u001c8pi\u0006$\u0018n\u001c8\n\t\u0005]\u0018Q\u001e\u0002\u0012k:\u001c\u0007.Z2lK\u00124\u0016M]5b]\u000e,\u0017aD1qa2LH\u0005Z3gCVdG\u000f\n\u001a\u0016\u0005\u0005u(fA4\u0002h\u0006y\u0011\r\u001d9ms\u0012\"WMZ1vYR$3\'\u0006\u0002\u0003\u0004)\u001a1.a:\u0002\u001f\u0005\u0004\b\u000f\\=%I\u00164\u0017-\u001e7uIQ*\"A!\u0003+\u0007=\f9/A\bbaBd\u0017\u0010\n3fM\u0006,H\u000e\u001e\u00136+\t\u0011yAK\u0002t\u0003O\fq\"\u00199qYf$C-\u001a4bk2$HEN\u000b\u0003\u0005+Q3a^At\u0003=\t\u0007\u000f\u001d7zI\u0011,g-Y;mi\u0012:TC\u0001B\u000eU\rY\u0018q]\u0001\tI\r|g\u000e^3oiV\u0011!\u0011\u0005\t\u0007\u0005G\u0011\u0019D!\u000f\u000f\t\t\u0015\"q\u0006\b\u0005\u0005O\u0011i#\u0004\u0002\u0003*)\u0019!1\u0006#\u0002\rq\u0012xn\u001c;?\u0013\u0005a\u0015b\u0001B\u0019\u0017\u00069\u0001/Y2lC\u001e,\u0017\u0002\u0002B\u001b\u0005o\u00111aU3r\u0015\r\u0011\td\u0013\t\u0007\u0015\nm\u0012\u0011U2\n\u0007\tu2J\u0001\u0004UkBdWMM\u0001\u0007I\rdwN\\3\u0016\u0003}D3!\u0002B#!\r1%qI\u0005\u0004\u0005\u0013\u0002%A\u0002:fG>\u0014H\rE\u0002]\u0005\u001b\"QAX\u0002C\u0002}\u00032\u0001\u0018B)\t\u0015I7A1\u0001`!\ra&Q\u000b\u0003\u0006[\u000e\u0011\ra\u0018\t\u00049\neC!B9\u0004\u0005\u0004y\u0006c\u0001/\u0003^\u0011)Qo\u0001b\u0001?B\u0019AL!\u0019\u0005\u000be\u001c!\u0019A0\u0011\u0007q\u0013)\u0007B\u0003~\u0007\t\u0007q\fC\u0004\u0002\u0012\r\u0001\rAa\u0013\t\u000f\u0005\u001d2\u00011\u0001\u0003P!9\u00111H\u0002A\u0002\tM\u0003bBA(\u0007\u0001\u0007!q\u000b\u0005\b\u0003G\u001a\u0001\u0019\u0001B.\u0011\u001d\t9h\u0001a\u0001\u0005?Bq!a#\u0004\u0001\u0004\u0011\u0019\'A\u0004v]\u0006\u0004\b\u000f\\=\u0016!\te$\u0011\u0012BG\u0005#\u0013)J!\'\u0003\u001e\n\u0005F\u0003\u0002B>\u0005G\u0003RA\u0013B?\u0005\u0003K1Aa L\u0005\u0011\u0019v.\\3\u0011#)\u0013\u0019Ia\"\u0003\f\n=%1\u0013BL\u00057\u0013y*C\u0002\u0003\u0006.\u0013a\u0001V;qY\u0016<\u0004c\u0001/\u0003\n\u0012)a\f\u0002b\u0001?B\u0019AL!$\u0005\u000b%$!\u0019A0\u0011\u0007q\u0013\t\nB\u0003n\t\t\u0007q\fE\u0002]\u0005+#Q!\u001d\u0003C\u0002}\u00032\u0001\u0018BM\t\u0015)HA1\u0001`!\ra&Q\u0014\u0003\u0006s\u0012\u0011\ra\u0018\t\u00049\n\u0005F!B?\u0005\u0005\u0004y\u0006bBAh\t\u0001\u0007!Q\u0015\t\u0011\r\u0016\u00119Ia#\u0003\u0010\nM%q\u0013BN\u0005?\u0003
   #12 = Utf8               _value1
   #13 = Utf8               Ljava/lang/Object;
   #14 = Utf8               TT1;
   #15 = Utf8               _value2
   #16 = Utf8               TT2;
   #17 = Utf8               _value3
   #18 = Utf8               TT3;
   #19 = Utf8               _value4
   #20 = Utf8               TT4;
   #21 = Utf8               _value5
   #22 = Utf8               TT5;
   #23 = Utf8               _value6
   #24 = Utf8               TT6;
   #25 = Utf8               _value7
   #26 = Utf8               TT7;
   #27 = Utf8               org$sireum$RecordSig$$$isOwned
   #28 = Utf8               Z
   #29 = Utf8               unapply
   #30 = Utf8               (Lorg/sireum/MBox7;)Lscala/Some;
   #31 = Utf8               <T1:Ljava/lang/Object;T2:Ljava/lang/Object;T3:Ljava/lang/Object;T4:Ljava/lang/Object;T5:Ljava/lang/Object;T6:Ljava/lang/Object;T7:Ljava/lang/Object;>(Lorg/sireum/MBox7<TT1;TT2;TT3;TT4;TT5;TT6;TT7;>;)Lscala/Some<Lscala/Tuple7<TT1;TT2;TT3;TT4;TT5;TT6;TT7;>;>;
   #32 = Utf8               o
   #33 = Utf8               org/sireum/MBox7$
   #34 = Class              #33           // org/sireum/MBox7$
   #35 = Utf8               MODULE$
   #36 = Utf8               Lorg/sireum/MBox7$;
   #37 = NameAndType        #35:#36       // MODULE$:Lorg/sireum/MBox7$;
   #38 = Fieldref           #34.#37       // org/sireum/MBox7$.MODULE$:Lorg/sireum/MBox7$;
   #39 = NameAndType        #29:#30       // unapply:(Lorg/sireum/MBox7;)Lscala/Some;
   #40 = Methodref          #34.#39       // org/sireum/MBox7$.unapply:(Lorg/sireum/MBox7;)Lscala/Some;
   #41 = Utf8               Lorg/sireum/MBox7;
   #42 = Utf8               $owned
   #43 = Utf8               ()Z
   #44 = Utf8               $owned$
   #45 = Utf8               (Lorg/sireum/RecordSig;)Z
   #46 = NameAndType        #44:#45       // $owned$:(Lorg/sireum/RecordSig;)Z
   #47 = InterfaceMethodref #7.#46        // org/sireum/RecordSig.$owned$:(Lorg/sireum/RecordSig;)Z
   #48 = Utf8               this
   #49 = Utf8               $owned_$eq
   #50 = Utf8               (Z)Lorg/sireum/RecordSig;
   #51 = Utf8               b
   #52 = Utf8               $owned_$eq$
   #53 = Utf8               (Lorg/sireum/RecordSig;Z)Lorg/sireum/RecordSig;
   #54 = NameAndType        #52:#53       // $owned_$eq$:(Lorg/sireum/RecordSig;Z)Lorg/sireum/RecordSig;
   #55 = InterfaceMethodref #7.#54        // org/sireum/RecordSig.$owned_$eq$:(Lorg/sireum/RecordSig;Z)Lorg/sireum/RecordSig;
   #56 = Utf8               hash
   #57 = Utf8               ()Lorg/sireum/Z;
   #58 = Utf8               hash$
   #59 = Utf8               (Lorg/sireum/RecordSig;)Lorg/sireum/Z;
   #60 = NameAndType        #58:#59       // hash$:(Lorg/sireum/RecordSig;)Lorg/sireum/Z;
   #61 = InterfaceMethodref #7.#60        // org/sireum/RecordSig.hash$:(Lorg/sireum/RecordSig;)Lorg/sireum/Z;
   #62 = Utf8               $cannotMixImmutableAndMutable
   #63 = Utf8               ()Lscala/runtime/Nothing$;
   #64 = Utf8               org/sireum/Mutable
   #65 = Class              #64           // org/sireum/Mutable
   #66 = Utf8               $cannotMixImmutableAndMutable$
   #67 = Utf8               (Lorg/sireum/Mutable;)Lscala/runtime/Nothing$;
   #68 = NameAndType        #66:#67       // $cannotMixImmutableAndMutable$:(Lorg/sireum/Mutable;)Lscala/runtime/Nothing$;
   #69 = InterfaceMethodref #65.#68       // org/sireum/Mutable.$cannotMixImmutableAndMutable$:(Lorg/sireum/Mutable;)Lscala/runtime/Nothing$;
   #70 = Utf8               $hasEquals
   #71 = Utf8               $hasEquals$
   #72 = Utf8               (Lorg/sireum/Mutable;)Z
   #73 = NameAndType        #71:#72       // $hasEquals$:(Lorg/sireum/Mutable;)Z
   #74 = InterfaceMethodref #65.#73       // org/sireum/Mutable.$hasEquals$:(Lorg/sireum/Mutable;)Z
   #75 = Utf8               $hasString
   #76 = Utf8               $hasString$
   #77 = NameAndType        #76:#72       // $hasString$:(Lorg/sireum/Mutable;)Z
   #78 = InterfaceMethodref #65.#77       // org/sireum/Mutable.$hasString$:(Lorg/sireum/Mutable;)Z
   #79 = NameAndType        #27:#28       // org$sireum$RecordSig$$$isOwned:Z
   #80 = Fieldref           #2.#79        // org/sireum/MBox7.org$sireum$RecordSig$$$isOwned:Z
   #81 = Utf8               org$sireum$RecordSig$$$isOwned_$eq
   #82 = Utf8               (Z)V
   #83 = Utf8               x$1
   #84 = Utf8               value1
   #85 = Utf8               ()Ljava/lang/Object;
   #86 = Utf8               ()TT1;
   #87 = NameAndType        #12:#13       // _value1:Ljava/lang/Object;
   #88 = Fieldref           #2.#87        // org/sireum/MBox7._value1:Ljava/lang/Object;
   #89 = Utf8               getValue1
   #90 = Utf8               value1_$eq
   #91 = Utf8               (Ljava/lang/Object;)Lorg/sireum/MBox7;
   #92 = Utf8               (TT1;)Lorg/sireum/MBox7<TT1;TT2;TT3;TT4;TT5;TT6;TT7;>;
   #93 = Utf8               setValue1
   #94 = Utf8               value2
   #95 = Utf8               ()TT2;
   #96 = NameAndType        #15:#13       // _value2:Ljava/lang/Object;
   #97 = Fieldref           #2.#96        // org/sireum/MBox7._value2:Ljava/lang/Object;
   #98 = Utf8               getValue2
   #99 = Utf8               value2_$eq
  #100 = Utf8               (TT2;)Lorg/sireum/MBox7<TT1;TT2;TT3;TT4;TT5;TT6;TT7;>;
  #101 = Utf8               setValue2
  #102 = Utf8               value3
  #103 = Utf8               ()TT3;
  #104 = NameAndType        #17:#13       // _value3:Ljava/lang/Object;
  #105 = Fieldref           #2.#104       // org/sireum/MBox7._value3:Ljava/lang/Object;
  #106 = Utf8               getValue3
  #107 = Utf8               value3_$eq
  #108 = Utf8               (TT3;)Lorg/sireum/MBox7<TT1;TT2;TT3;TT4;TT5;TT6;TT7;>;
  #109 = Utf8               setValue3
  #110 = Utf8               value4
  #111 = Utf8               ()TT4;
  #112 = NameAndType        #19:#13       // _value4:Ljava/lang/Object;
  #113 = Fieldref           #2.#112       // org/sireum/MBox7._value4:Ljava/lang/Object;
  #114 = Utf8               getValue4
  #115 = Utf8               value4_$eq
  #116 = Utf8               (TT4;)Lorg/sireum/MBox7<TT1;TT2;TT3;TT4;TT5;TT6;TT7;>;
  #117 = Utf8               setValue4
  #118 = Utf8               value5
  #119 = Utf8               ()TT5;
  #120 = NameAndType        #21:#13       // _value5:Ljava/lang/Object;
  #121 = Fieldref           #2.#120       // org/sireum/MBox7._value5:Ljava/lang/Object;
  #122 = Utf8               getValue5
  #123 = Utf8               value5_$eq
  #124 = Utf8               (TT5;)Lorg/sireum/MBox7<TT1;TT2;TT3;TT4;TT5;TT6;TT7;>;
  #125 = Utf8               setValue5
  #126 = Utf8               value6
  #127 = Utf8               ()TT6;
  #128 = NameAndType        #23:#13       // _value6:Ljava/lang/Object;
  #129 = Fieldref           #2.#128       // org/sireum/MBox7._value6:Ljava/lang/Object;
  #130 = Utf8               getValue6
  #131 = Utf8               value6_$eq
  #132 = Utf8               (TT6;)Lorg/sireum/MBox7<TT1;TT2;TT3;TT4;TT5;TT6;TT7;>;
  #133 = Utf8               setValue6
  #134 = Utf8               value7
  #135 = Utf8               ()TT7;
  #136 = NameAndType        #25:#13       // _value7:Ljava/lang/Object;
  #137 = Fieldref           #2.#136       // org/sireum/MBox7._value7:Ljava/lang/Object;
  #138 = Utf8               getValue7
  #139 = Utf8               value7_$eq
  #140 = Utf8               (TT7;)Lorg/sireum/MBox7<TT1;TT2;TT3;TT4;TT5;TT6;TT7;>;
  #141 = Utf8               setValue7
  #142 = Utf8               toString
  #143 = Utf8               ()Ljava/lang/String;
  #144 = NameAndType        #75:#43       // $hasString:()Z
  #145 = Methodref          #2.#144       // org/sireum/MBox7.$hasString:()Z
  #146 = Utf8               string$
  #147 = Utf8               (Lorg/sireum/RecordSig;)Ljava/lang/String;
  #148 = NameAndType        #146:#147     // string$:(Lorg/sireum/RecordSig;)Ljava/lang/String;
  #149 = InterfaceMethodref #7.#148       // org/sireum/RecordSig.string$:(Lorg/sireum/RecordSig;)Ljava/lang/String;
  #150 = Utf8               java/lang/StringBuilder
  #151 = Class              #150          // java/lang/StringBuilder
  #152 = Utf8               <init>
  #153 = Utf8               ()V
  #154 = NameAndType        #152:#153     // "<init>":()V
  #155 = Methodref          #151.#154     // java/lang/StringBuilder."<init>":()V
  #156 = Utf8               MBox7
  #157 = String             #156          // MBox7
  #158 = Utf8               append
  #159 = Utf8               (Ljava/lang/String;)Ljava/lang/StringBuilder;
  #160 = NameAndType        #158:#159     // append:(Ljava/lang/String;)Ljava/lang/StringBuilder;
  #161 = Methodref          #151.#160     // java/lang/StringBuilder.append:(Ljava/lang/String;)Ljava/lang/StringBuilder;
  #162 = Utf8               (C)Ljava/lang/StringBuilder;
  #163 = NameAndType        #158:#162     // append:(C)Ljava/lang/StringBuilder;
  #164 = Methodref          #151.#163     // java/lang/StringBuilder.append:(C)Ljava/lang/StringBuilder;
  #165 = Utf8               org/sireum/String$
  #166 = Class              #165          // org/sireum/String$
  #167 = Utf8               Lorg/sireum/String$;
  #168 = NameAndType        #35:#167      // MODULE$:Lorg/sireum/String$;
  #169 = Fieldref           #166.#168     // org/sireum/String$.MODULE$:Lorg/sireum/String$;
  #170 = NameAndType        #84:#85       // value1:()Ljava/lang/Object;
  #171 = Methodref          #2.#170       // org/sireum/MBox7.value1:()Ljava/lang/Object;
  #172 = Utf8               escape
  #173 = Utf8               (Ljava/lang/Object;)Ljava/lang/String;
  #174 = NameAndType        #172:#173     // escape:(Ljava/lang/Object;)Ljava/lang/String;
  #175 = Methodref          #166.#174     // org/sireum/String$.escape:(Ljava/lang/Object;)Ljava/lang/String;
  #176 = Utf8               ,
  #177 = String             #176          // ,
  #178 = NameAndType        #94:#85       // value2:()Ljava/lang/Object;
  #179 = Methodref          #2.#178       // org/sireum/MBox7.value2:()Ljava/lang/Object;
  #180 = NameAndType        #102:#85      // value3:()Ljava/lang/Object;
  #181 = Methodref          #2.#180       // org/sireum/MBox7.value3:()Ljava/lang/Object;
  #182 = NameAndType        #110:#85      // value4:()Ljava/lang/Object;
  #183 = Methodref          #2.#182       // org/sireum/MBox7.value4:()Ljava/lang/Object;
  #184 = NameAndType        #118:#85      // value5:()Ljava/lang/Object;
  #185 = Methodref          #2.#184       // org/sireum/MBox7.value5:()Ljava/lang/Object;
  #186 = NameAndType        #126:#85      // value6:()Ljava/lang/Object;
  #187 = Methodref          #2.#186       // org/sireum/MBox7.value6:()Ljava/lang/Object;
  #188 = NameAndType        #134:#85      // value7:()Ljava/lang/Object;
  #189 = Methodref          #2.#188       // org/sireum/MBox7.value7:()Ljava/lang/Object;
  #190 = NameAndType        #142:#143     // toString:()Ljava/lang/String;
  #191 = Methodref          #151.#190     // java/lang/StringBuilder.toString:()Ljava/lang/String;
  #192 = Utf8               sb
  #193 = Utf8               Ljava/lang/StringBuilder;
  #194 = Utf8               java/lang/String
  #195 = Class              #194          // java/lang/String
  #196 = Utf8               string
  #197 = Methodref          #2.#190       // org/sireum/MBox7.toString:()Ljava/lang/String;
  #198 = Utf8               apply
  #199 = Utf8               (Ljava/lang/String;)Ljava/lang/String;
  #200 = NameAndType        #198:#199     // apply:(Ljava/lang/String;)Ljava/lang/String;
  #201 = Methodref          #166.#200     // org/sireum/String$.apply:(Ljava/lang/String;)Ljava/lang/String;
  #202 = Utf8               hashCode
  #203 = Utf8               ()I
  #204 = NameAndType        #70:#43       // $hasEquals:()Z
  #205 = Methodref          #2.#204       // org/sireum/MBox7.$hasEquals:()Z
  #206 = NameAndType        #202:#203     // hashCode:()I
  #207 = Methodref          #5.#206       // java/lang/Object.hashCode:()I
  #208 = Utf8               scala/package$
  #209 = Class              #208          // scala/package$
  #210 = Utf8               Lscala/package$;
  #211 = NameAndType        #35:#210      // MODULE$:Lscala/package$;
  #212 = Fieldref           #209.#211     // scala/package$.MODULE$:Lscala/package$;
  #213 = Utf8               Seq
  #214 = Utf8               ()Lscala/collection/immutable/Seq$;
  #215 = NameAndType        #213:#214     // Seq:()Lscala/collection/immutable/Seq$;
  #216 = Methodref          #209.#215     // scala/package$.Seq:()Lscala/collection/immutable/Seq$;
  #217 = Utf8               scala/runtime/ScalaRunTime$
  #218 = Class              #217          // scala/runtime/ScalaRunTime$
  #219 = Utf8               Lscala/runtime/ScalaRunTime$;
  #220 = NameAndType        #35:#219      // MODULE$:Lscala/runtime/ScalaRunTime$;
  #221 = Fieldref           #218.#220     // scala/runtime/ScalaRunTime$.MODULE$:Lscala/runtime/ScalaRunTime$;
  #222 = Utf8               getClass
  #223 = Utf8               ()Ljava/lang/Class;
  #224 = NameAndType        #222:#223     // getClass:()Ljava/lang/Class;
  #225 = Methodref          #2.#224       // org/sireum/MBox7.getClass:()Ljava/lang/Class;
  #226 = Utf8               java/lang/Class
  #227 = Class              #226          // java/lang/Class
  #228 = Utf8               getName
  #229 = NameAndType        #228:#143     // getName:()Ljava/lang/String;
  #230 = Methodref          #227.#229     // java/lang/Class.getName:()Ljava/lang/String;
  #231 = Utf8               genericWrapArray
  #232 = Utf8               (Ljava/lang/Object;)Lscala/collection/immutable/ArraySeq;
  #233 = NameAndType        #231:#232     // genericWrapArray:(Ljava/lang/Object;)Lscala/collection/immutable/ArraySeq;
  #234 = Methodref          #218.#233     // scala/runtime/ScalaRunTime$.genericWrapArray:(Ljava/lang/Object;)Lscala/collection/immutable/ArraySeq;
  #235 = Utf8               scala/collection/immutable/Seq$
  #236 = Class              #235          // scala/collection/immutable/Seq$
  #237 = Utf8               (Lscala/collection/immutable/Seq;)Lscala/collection/SeqOps;
  #238 = NameAndType        #198:#237     // apply:(Lscala/collection/immutable/Seq;)Lscala/collection/SeqOps;
  #239 = Methodref          #236.#238     // scala/collection/immutable/Seq$.apply:(Lscala/collection/immutable/Seq;)Lscala/collection/SeqOps;
  #240 = Utf8               scala/collection/Seq
  #241 = Class              #240          // scala/collection/Seq
  #242 = InterfaceMethodref #241.#206     // scala/collection/Seq.hashCode:()I
  #243 = Utf8               equals
  #244 = Utf8               (Ljava/lang/Object;)Z
  #245 = NameAndType        #243:#244     // equals:(Ljava/lang/Object;)Z
  #246 = Methodref          #5.#245       // java/lang/Object.equals:(Ljava/lang/Object;)Z
  #247 = Methodref          #2.#206       // org/sireum/MBox7.hashCode:()I
  #248 = Utf8               scala/runtime/BoxesRunTime
  #249 = Class              #248          // scala/runtime/BoxesRunTime
  #250 = Utf8               (Ljava/lang/Object;Ljava/lang/Object;)Z
  #251 = NameAndType        #243:#250     // equals:(Ljava/lang/Object;Ljava/lang/Object;)Z
  #252 = Methodref          #249.#251     // scala/runtime/BoxesRunTime.equals:(Ljava/lang/Object;Ljava/lang/Object;)Z
  #253 = Utf8               (Ljava/lang/Object;Ljava/lang/Object;Ljava/lang/Object;Ljava/lang/Object;Ljava/lang/Object;Ljava/lang/Object;Ljava/lang/Object;)Lorg/sireum/MBox7;
  #254 = Utf8               (TT1;TT2;TT3;TT4;TT5;TT6;TT7;)Lorg/sireum/MBox7<TT1;TT2;TT3;TT4;TT5;TT6;TT7;>;
  #255 = Utf8               (Ljava/lang/Object;Ljava/lang/Object;Ljava/lang/Object;Ljava/lang/Object;Ljava/lang/Object;Ljava/lang/Object;Ljava/lang/Object;)V
  #256 = NameAndType        #152:#255     // "<init>":(Ljava/lang/Object;Ljava/lang/Object;Ljava/lang/Object;Ljava/lang/Object;Ljava/lang/Object;Ljava/lang/Object;Ljava/lang/Object;)V
  #257 = Methodref          #2.#256       // org/sireum/MBox7."<init>":(Ljava/lang/Object;Ljava/lang/Object;Ljava/lang/Object;Ljava/lang/Object;Ljava/lang/Object;Ljava/lang/Object;Ljava/lang/Object;)V
  #258 = Utf8               apply$default$1
  #259 = Utf8               apply$default$2
  #260 = Utf8               apply$default$3
  #261 = Utf8               apply$default$4
  #262 = Utf8               apply$default$5
  #263 = Utf8               apply$default$6
  #264 = Utf8               apply$default$7
  #265 = Utf8               $content
  #266 = Utf8               ()Lscala/collection/immutable/Seq;
  #267 = Utf8               ()Lscala/collection/immutable/Seq<Lscala/Tuple2<Ljava/lang/String;Ljava/lang/Object;>;>;
  #268 = Utf8               scala/Tuple2
  #269 = Class              #268          // scala/Tuple2
  #270 = Utf8               type
  #271 = String             #270          // type
  #272 = Utf8               List
  #273 = Utf8               ()Lscala/collection/immutable/List$;
  #274 = NameAndType        #272:#273     // List:()Lscala/collection/immutable/List$;
  #275 = Methodref          #209.#274     // scala/package$.List:()Lscala/collection/immutable/List$;
  #276 = Utf8               org
  #277 = String             #276          // org
  #278 = Utf8               sireum
  #279 = String             #278          // sireum
  #280 = Utf8               [Ljava/lang/Object;
  #281 = Class              #280          // "[Ljava/lang/Object;"
  #282 = Utf8               wrapRefArray
  #283 = Utf8               ([Ljava/lang/Object;)Lscala/collection/immutable/ArraySeq;
  #284 = NameAndType        #282:#283     // wrapRefArray:([Ljava/lang/Object;)Lscala/collection/immutable/ArraySeq;
  #285 = Methodref          #218.#284     // scala/runtime/ScalaRunTime$.wrapRefArray:([Ljava/lang/Object;)Lscala/collection/immutable/ArraySeq;
  #286 = Utf8               scala/collection/immutable/List$
  #287 = Class              #286          // scala/collection/immutable/List$
  #288 = Utf8               (Lscala/collection/immutable/Seq;)Ljava/lang/Object;
  #289 = NameAndType        #198:#288     // apply:(Lscala/collection/immutable/Seq;)Ljava/lang/Object;
  #290 = Methodref          #287.#289     // scala/collection/immutable/List$.apply:(Lscala/collection/immutable/Seq;)Ljava/lang/Object;
  #291 = Utf8               (Ljava/lang/Object;Ljava/lang/Object;)V
  #292 = NameAndType        #152:#291     // "<init>":(Ljava/lang/Object;Ljava/lang/Object;)V
  #293 = Methodref          #269.#292     // scala/Tuple2."<init>":(Ljava/lang/Object;Ljava/lang/Object;)V
  #294 = String             #84           // value1
  #295 = String             #94           // value2
  #296 = String             #102          // value3
  #297 = String             #110          // value4
  #298 = String             #118          // value5
  #299 = String             #126          // value6
  #300 = String             #134          // value7
  #301 = Utf8               scala/collection/immutable/Seq
  #302 = Class              #301          // scala/collection/immutable/Seq
  #303 = Utf8               $clone
  #304 = Utf8               ()Lorg/sireum/MBox7;
  #305 = Utf8               ()Lorg/sireum/MBox7<TT1;TT2;TT3;TT4;TT5;TT6;TT7;>;
  #306 = Utf8               org/sireum/helper$
  #307 = Class              #306          // org/sireum/helper$
  #308 = Utf8               Lorg/sireum/helper$;
  #309 = NameAndType        #35:#308      // MODULE$:Lorg/sireum/helper$;
  #310 = Fieldref           #307.#309     // org/sireum/helper$.MODULE$:Lorg/sireum/helper$;
  #311 = Utf8               cloneAssign
  #312 = Utf8               (Ljava/lang/Object;)Ljava/lang/Object;
  #313 = NameAndType        #311:#312     // cloneAssign:(Ljava/lang/Object;)Ljava/lang/Object;
  #314 = Methodref          #307.#313     // org/sireum/helper$.cloneAssign:(Ljava/lang/Object;)Ljava/lang/Object;
  #315 = Utf8               r
  #316 = Utf8               (Z)Lorg/sireum/$internal/MutableMarker;
  #317 = NameAndType        #49:#50       // $owned_$eq:(Z)Lorg/sireum/RecordSig;
  #318 = Methodref          #2.#317       // org/sireum/MBox7.$owned_$eq:(Z)Lorg/sireum/RecordSig;
  #319 = NameAndType        #303:#304     // $clone:()Lorg/sireum/MBox7;
  #320 = Methodref          #2.#319       // org/sireum/MBox7.$clone:()Lorg/sireum/MBox7;
  #321 = Utf8               ()Lorg/sireum/$internal/MutableMarker;
  #322 = Utf8               (TT1;TT2;TT3;TT4;TT5;TT6;TT7;)V
  #323 = Utf8               __value1
  #324 = Utf8               __value2
  #325 = Utf8               __value3
  #326 = Utf8               __value4
  #327 = Utf8               __value5
  #328 = Utf8               __value6
  #329 = Utf8               __value7
  #330 = Methodref          #5.#154       // java/lang/Object."<init>":()V
  #331 = Utf8               $init$
  #332 = Utf8               (Lorg/sireum/Mutable;)V
  #333 = NameAndType        #331:#332     // $init$:(Lorg/sireum/Mutable;)V
  #334 = InterfaceMethodref #65.#333      // org/sireum/Mutable.$init$:(Lorg/sireum/Mutable;)V
  #335 = Utf8               (Lorg/sireum/RecordSig;)V
  #336 = NameAndType        #331:#335     // $init$:(Lorg/sireum/RecordSig;)V
  #337 = InterfaceMethodref #7.#336       // org/sireum/RecordSig.$init$:(Lorg/sireum/RecordSig;)V
  #338 = Utf8               Signature
  #339 = Utf8               Code
  #340 = Utf8               LocalVariableTable
  #341 = Utf8               MethodParameters
  #342 = Utf8               LineNumberTable
  #343 = Utf8               StackMapTable
  #344 = Utf8               SourceFile
  #345 = Utf8               RuntimeVisibleAnnotations
  #346 = Utf8               ScalaInlineInfo
  #347 = Utf8               ScalaSig
{
  private T1 _value1;
    descriptor: Ljava/lang/Object;
    flags: (0x0002) ACC_PRIVATE
    Signature: #14                          // TT1;

  private T2 _value2;
    descriptor: Ljava/lang/Object;
    flags: (0x0002) ACC_PRIVATE
    Signature: #16                          // TT2;

  private T3 _value3;
    descriptor: Ljava/lang/Object;
    flags: (0x0002) ACC_PRIVATE
    Signature: #18                          // TT3;

  private T4 _value4;
    descriptor: Ljava/lang/Object;
    flags: (0x0002) ACC_PRIVATE
    Signature: #20                          // TT4;

  private T5 _value5;
    descriptor: Ljava/lang/Object;
    flags: (0x0002) ACC_PRIVATE
    Signature: #22                          // TT5;

  private T6 _value6;
    descriptor: Ljava/lang/Object;
    flags: (0x0002) ACC_PRIVATE
    Signature: #24                          // TT6;

  private T7 _value7;
    descriptor: Ljava/lang/Object;
    flags: (0x0002) ACC_PRIVATE
    Signature: #26                          // TT7;

  private boolean org$sireum$RecordSig$$$isOwned;
    descriptor: Z
    flags: (0x0002) ACC_PRIVATE

  public static <T1 extends java.lang.Object, T2 extends java.lang.Object, T3 extends java.lang.Object, T4 extends java.lang.Object, T5 extends java.lang.Object, T6 extends java.lang.Object, T7 extends java.lang.Object> scala.Some<scala.Tuple7<T1, T2, T3, T4, T5, T6, T7>> unapply(org.sireum.MBox7<T1, T2, T3, T4, T5, T6, T7>);
    descriptor: (Lorg/sireum/MBox7;)Lscala/Some;
    flags: (0x0009) ACC_PUBLIC, ACC_STATIC
    Code:
      stack=2, locals=1, args_size=1
         0: getstatic     #38                 // Field org/sireum/MBox7$.MODULE$:Lorg/sireum/MBox7$;
         3: aload_0
         4: invokevirtual #40                 // Method org/sireum/MBox7$.unapply:(Lorg/sireum/MBox7;)Lscala/Some;
         7: areturn
      LocalVariableTable:
        Start  Length  Slot  Name   Signature
            0       8     0     o   Lorg/sireum/MBox7;
    Signature: #31                          // <T1:Ljava/lang/Object;T2:Ljava/lang/Object;T3:Ljava/lang/Object;T4:Ljava/lang/Object;T5:Ljava/lang/Object;T6:Ljava/lang/Object;T7:Ljava/lang/Object;>(Lorg/sireum/MBox7<TT1;TT2;TT3;TT4;TT5;TT6;TT7;>;)Lscala/Some<Lscala/Tuple7<TT1;TT2;TT3;TT4;TT5;TT6;TT7;>;>;
    MethodParameters:
      Name                           Flags
      o                              final

  public final boolean $owned();
    descriptor: ()Z
    flags: (0x0011) ACC_PUBLIC, ACC_FINAL
    Code:
      stack=1, locals=1, args_size=1
         0: aload_0
         1: invokestatic  #47                 // InterfaceMethod org/sireum/RecordSig.$owned$:(Lorg/sireum/RecordSig;)Z
         4: ireturn
      LineNumberTable:
        line 41: 0
      LocalVariableTable:
        Start  Length  Slot  Name   Signature
            0       5     0  this   Lorg/sireum/MBox7;

  public final org.sireum.RecordSig $owned_$eq(boolean);
    descriptor: (Z)Lorg/sireum/RecordSig;
    flags: (0x0011) ACC_PUBLIC, ACC_FINAL
    Code:
      stack=2, locals=2, args_size=2
         0: aload_0
         1: iload_1
         2: invokestatic  #55                 // InterfaceMethod org/sireum/RecordSig.$owned_$eq$:(Lorg/sireum/RecordSig;Z)Lorg/sireum/RecordSig;
         5: areturn
      LineNumberTable:
        line 41: 0
      LocalVariableTable:
        Start  Length  Slot  Name   Signature
            0       6     0  this   Lorg/sireum/MBox7;
            0       6     1     b   Z
    MethodParameters:
      Name                           Flags
      b                              final

  public org.sireum.Z hash();
    descriptor: ()Lorg/sireum/Z;
    flags: (0x0001) ACC_PUBLIC
    Code:
      stack=1, locals=1, args_size=1
         0: aload_0
         1: invokestatic  #61                 // InterfaceMethod org/sireum/RecordSig.hash$:(Lorg/sireum/RecordSig;)Lorg/sireum/Z;
         4: areturn
      LineNumberTable:
        line 41: 0
      LocalVariableTable:
        Start  Length  Slot  Name   Signature
            0       5     0  this   Lorg/sireum/MBox7;

  public final scala.runtime.Nothing$ $cannotMixImmutableAndMutable();
    descriptor: ()Lscala/runtime/Nothing$;
    flags: (0x0011) ACC_PUBLIC, ACC_FINAL
    Code:
      stack=1, locals=1, args_size=1
         0: aload_0
         1: invokestatic  #69                 // InterfaceMethod org/sireum/Mutable.$cannotMixImmutableAndMutable$:(Lorg/sireum/Mutable;)Lscala/runtime/Nothing$;
         4: areturn
      LineNumberTable:
        line 41: 0
      LocalVariableTable:
        Start  Length  Slot  Name   Signature
            0       5     0  this   Lorg/sireum/MBox7;

  public boolean $hasEquals();
    descriptor: ()Z
    flags: (0x0001) ACC_PUBLIC
    Code:
      stack=1, locals=1, args_size=1
         0: aload_0
         1: invokestatic  #74                 // InterfaceMethod org/sireum/Mutable.$hasEquals$:(Lorg/sireum/Mutable;)Z
         4: ireturn
      LineNumberTable:
        line 41: 0
      LocalVariableTable:
        Start  Length  Slot  Name   Signature
            0       5     0  this   Lorg/sireum/MBox7;

  public boolean $hasString();
    descriptor: ()Z
    flags: (0x0001) ACC_PUBLIC
    Code:
      stack=1, locals=1, args_size=1
         0: aload_0
         1: invokestatic  #78                 // InterfaceMethod org/sireum/Mutable.$hasString$:(Lorg/sireum/Mutable;)Z
         4: ireturn
      LineNumberTable:
        line 41: 0
      LocalVariableTable:
        Start  Length  Slot  Name   Signature
            0       5     0  this   Lorg/sireum/MBox7;

  public boolean org$sireum$RecordSig$$$isOwned();
    descriptor: ()Z
    flags: (0x0001) ACC_PUBLIC
    Code:
      stack=1, locals=1, args_size=1
         0: aload_0
         1: getfield      #80                 // Field org$sireum$RecordSig$$$isOwned:Z
         4: ireturn
      LineNumberTable:
        line 41: 0
      LocalVariableTable:
        Start  Length  Slot  Name   Signature
            0       5     0  this   Lorg/sireum/MBox7;

  public void org$sireum$RecordSig$$$isOwned_$eq(boolean);
    descriptor: (Z)V
    flags: (0x0001) ACC_PUBLIC
    Code:
      stack=2, locals=2, args_size=2
         0: aload_0
         1: iload_1
         2: putfield      #80                 // Field org$sireum$RecordSig$$$isOwned:Z
         5: return
      LineNumberTable:
        line 41: 0
      LocalVariableTable:
        Start  Length  Slot  Name   Signature
            0       6     0  this   Lorg/sireum/MBox7;
            0       6     1   x$1   Z
    MethodParameters:
      Name                           Flags
      x$1                            final

  public T1 value1();
    descriptor: ()Ljava/lang/Object;
    flags: (0x0001) ACC_PUBLIC
    Code:
      stack=1, locals=1, args_size=1
         0: aload_0
         1: getfield      #88                 // Field _value1:Ljava/lang/Object;
         4: areturn
      LineNumberTable:
        line 41: 0
      LocalVariableTable:
        Start  Length  Slot  Name   Signature
            0       5     0  this   Lorg/sireum/MBox7;
    Signature: #86                          // ()TT1;

  public T1 getValue1();
    descriptor: ()Ljava/lang/Object;
    flags: (0x0001) ACC_PUBLIC
    Code:
      stack=1, locals=1, args_size=1
         0: aload_0
         1: getfield      #88                 // Field _value1:Ljava/lang/Object;
         4: areturn
      LineNumberTable:
        line 41: 0
      LocalVariableTable:
        Start  Length  Slot  Name   Signature
            0       5     0  this   Lorg/sireum/MBox7;
    Signature: #86                          // ()TT1;

  public org.sireum.MBox7<T1, T2, T3, T4, T5, T6, T7> value1_$eq(T1);
    descriptor: (Ljava/lang/Object;)Lorg/sireum/MBox7;
    flags: (0x0001) ACC_PUBLIC
    Code:
      stack=2, locals=2, args_size=2
         0: aload_0
         1: aload_1
         2: putfield      #88                 // Field _value1:Ljava/lang/Object;
         5: aload_0
         6: areturn
      LineNumberTable:
        line 41: 0
      LocalVariableTable:
        Start  Length  Slot  Name   Signature
            0       7     0  this   Lorg/sireum/MBox7;
            0       7     1 value1   Ljava/lang/Object;
    Signature: #92                          // (TT1;)Lorg/sireum/MBox7<TT1;TT2;TT3;TT4;TT5;TT6;TT7;>;
    MethodParameters:
      Name                           Flags
      value1                         final

  public org.sireum.MBox7<T1, T2, T3, T4, T5, T6, T7> setValue1(T1);
    descriptor: (Ljava/lang/Object;)Lorg/sireum/MBox7;
    flags: (0x0001) ACC_PUBLIC
    Code:
      stack=2, locals=2, args_size=2
         0: aload_0
         1: aload_1
         2: putfield      #88                 // Field _value1:Ljava/lang/Object;
         5: aload_0
         6: areturn
      LineNumberTable:
        line 41: 0
      LocalVariableTable:
        Start  Length  Slot  Name   Signature
            0       7     0  this   Lorg/sireum/MBox7;
            0       7     1 value1   Ljava/lang/Object;
    Signature: #92                          // (TT1;)Lorg/sireum/MBox7<TT1;TT2;TT3;TT4;TT5;TT6;TT7;>;
    MethodParameters:
      Name                           Flags
      value1                         final

  public T2 value2();
    descriptor: ()Ljava/lang/Object;
    flags: (0x0001) ACC_PUBLIC
    Code:
      stack=1, locals=1, args_size=1
         0: aload_0
         1: getfield      #97                 // Field _value2:Ljava/lang/Object;
         4: areturn
      LineNumberTable:
        line 41: 0
      LocalVariableTable:
        Start  Length  Slot  Name   Signature
            0       5     0  this   Lorg/sireum/MBox7;
    Signature: #95                          // ()TT2;

  public T2 getValue2();
    descriptor: ()Ljava/lang/Object;
    flags: (0x0001) ACC_PUBLIC
    Code:
      stack=1, locals=1, args_size=1
         0: aload_0
         1: getfield      #97                 // Field _value2:Ljava/lang/Object;
         4: areturn
      LineNumberTable:
        line 41: 0
      LocalVariableTable:
        Start  Length  Slot  Name   Signature
            0       5     0  this   Lorg/sireum/MBox7;
    Signature: #95                          // ()TT2;

  public org.sireum.MBox7<T1, T2, T3, T4, T5, T6, T7> value2_$eq(T2);
    descriptor: (Ljava/lang/Object;)Lorg/sireum/MBox7;
    flags: (0x0001) ACC_PUBLIC
    Code:
      stack=2, locals=2, args_size=2
         0: aload_0
         1: aload_1
         2: putfield      #97                 // Field _value2:Ljava/lang/Object;
         5: aload_0
         6: areturn
      LineNumberTable:
        line 41: 0
      LocalVariableTable:
        Start  Length  Slot  Name   Signature
            0       7     0  this   Lorg/sireum/MBox7;
            0       7     1 value2   Ljava/lang/Object;
    Signature: #100                         // (TT2;)Lorg/sireum/MBox7<TT1;TT2;TT3;TT4;TT5;TT6;TT7;>;
    MethodParameters:
      Name                           Flags
      value2                         final

  public org.sireum.MBox7<T1, T2, T3, T4, T5, T6, T7> setValue2(T2);
    descriptor: (Ljava/lang/Object;)Lorg/sireum/MBox7;
    flags: (0x0001) ACC_PUBLIC
    Code:
      stack=2, locals=2, args_size=2
         0: aload_0
         1: aload_1
         2: putfield      #97                 // Field _value2:Ljava/lang/Object;
         5: aload_0
         6: areturn
      LineNumberTable:
        line 41: 0
      LocalVariableTable:
        Start  Length  Slot  Name   Signature
            0       7     0  this   Lorg/sireum/MBox7;
            0       7     1 value2   Ljava/lang/Object;
    Signature: #100                         // (TT2;)Lorg/sireum/MBox7<TT1;TT2;TT3;TT4;TT5;TT6;TT7;>;
    MethodParameters:
      Name                           Flags
      value2                         final

  public T3 value3();
    descriptor: ()Ljava/lang/Object;
    flags: (0x0001) ACC_PUBLIC
    Code:
      stack=1, locals=1, args_size=1
         0: aload_0
         1: getfield      #105                // Field _value3:Ljava/lang/Object;
         4: areturn
      LineNumberTable:
        line 41: 0
      LocalVariableTable:
        Start  Length  Slot  Name   Signature
            0       5     0  this   Lorg/sireum/MBox7;
    Signature: #103                         // ()TT3;

  public T3 getValue3();
    descriptor: ()Ljava/lang/Object;
    flags: (0x0001) ACC_PUBLIC
    Code:
      stack=1, locals=1, args_size=1
         0: aload_0
         1: getfield      #105                // Field _value3:Ljava/lang/Object;
         4: areturn
      LineNumberTable:
        line 41: 0
      LocalVariableTable:
        Start  Length  Slot  Name   Signature
            0       5     0  this   Lorg/sireum/MBox7;
    Signature: #103                         // ()TT3;

  public org.sireum.MBox7<T1, T2, T3, T4, T5, T6, T7> value3_$eq(T3);
    descriptor: (Ljava/lang/Object;)Lorg/sireum/MBox7;
    flags: (0x0001) ACC_PUBLIC
    Code:
      stack=2, locals=2, args_size=2
         0: aload_0
         1: aload_1
         2: putfield      #105                // Field _value3:Ljava/lang/Object;
         5: aload_0
         6: areturn
      LineNumberTable:
        line 41: 0
      LocalVariableTable:
        Start  Length  Slot  Name   Signature
            0       7     0  this   Lorg/sireum/MBox7;
            0       7     1 value3   Ljava/lang/Object;
    Signature: #108                         // (TT3;)Lorg/sireum/MBox7<TT1;TT2;TT3;TT4;TT5;TT6;TT7;>;
    MethodParameters:
      Name                           Flags
      value3                         final

  public org.sireum.MBox7<T1, T2, T3, T4, T5, T6, T7> setValue3(T3);
    descriptor: (Ljava/lang/Object;)Lorg/sireum/MBox7;
    flags: (0x0001) ACC_PUBLIC
    Code:
      stack=2, locals=2, args_size=2
         0: aload_0
         1: aload_1
         2: putfield      #105                // Field _value3:Ljava/lang/Object;
         5: aload_0
         6: areturn
      LineNumberTable:
        line 41: 0
      LocalVariableTable:
        Start  Length  Slot  Name   Signature
            0       7     0  this   Lorg/sireum/MBox7;
            0       7     1 value3   Ljava/lang/Object;
    Signature: #108                         // (TT3;)Lorg/sireum/MBox7<TT1;TT2;TT3;TT4;TT5;TT6;TT7;>;
    MethodParameters:
      Name                           Flags
      value3                         final

  public T4 value4();
    descriptor: ()Ljava/lang/Object;
    flags: (0x0001) ACC_PUBLIC
    Code:
      stack=1, locals=1, args_size=1
         0: aload_0
         1: getfield      #113                // Field _value4:Ljava/lang/Object;
         4: areturn
      LineNumberTable:
        line 41: 0
      LocalVariableTable:
        Start  Length  Slot  Name   Signature
            0       5     0  this   Lorg/sireum/MBox7;
    Signature: #111                         // ()TT4;

  public T4 getValue4();
    descriptor: ()Ljava/lang/Object;
    flags: (0x0001) ACC_PUBLIC
    Code:
      stack=1, locals=1, args_size=1
         0: aload_0
         1: getfield      #113                // Field _value4:Ljava/lang/Object;
         4: areturn
      LineNumberTable:
        line 41: 0
      LocalVariableTable:
        Start  Length  Slot  Name   Signature
            0       5     0  this   Lorg/sireum/MBox7;
    Signature: #111                         // ()TT4;

  public org.sireum.MBox7<T1, T2, T3, T4, T5, T6, T7> value4_$eq(T4);
    descriptor: (Ljava/lang/Object;)Lorg/sireum/MBox7;
    flags: (0x0001) ACC_PUBLIC
    Code:
      stack=2, locals=2, args_size=2
         0: aload_0
         1: aload_1
         2: putfield      #113                // Field _value4:Ljava/lang/Object;
         5: aload_0
         6: areturn
      LineNumberTable:
        line 41: 0
      LocalVariableTable:
        Start  Length  Slot  Name   Signature
            0       7     0  this   Lorg/sireum/MBox7;
            0       7     1 value4   Ljava/lang/Object;
    Signature: #116                         // (TT4;)Lorg/sireum/MBox7<TT1;TT2;TT3;TT4;TT5;TT6;TT7;>;
    MethodParameters:
      Name                           Flags
      value4                         final

  public org.sireum.MBox7<T1, T2, T3, T4, T5, T6, T7> setValue4(T4);
    descriptor: (Ljava/lang/Object;)Lorg/sireum/MBox7;
    flags: (0x0001) ACC_PUBLIC
    Code:
      stack=2, locals=2, args_size=2
         0: aload_0
         1: aload_1
         2: putfield      #113                // Field _value4:Ljava/lang/Object;
         5: aload_0
         6: areturn
      LineNumberTable:
        line 41: 0
      LocalVariableTable:
        Start  Length  Slot  Name   Signature
            0       7     0  this   Lorg/sireum/MBox7;
            0       7     1 value4   Ljava/lang/Object;
    Signature: #116                         // (TT4;)Lorg/sireum/MBox7<TT1;TT2;TT3;TT4;TT5;TT6;TT7;>;
    MethodParameters:
      Name                           Flags
      value4                         final

  public T5 value5();
    descriptor: ()Ljava/lang/Object;
    flags: (0x0001) ACC_PUBLIC
    Code:
      stack=1, locals=1, args_size=1
         0: aload_0
         1: getfield      #121                // Field _value5:Ljava/lang/Object;
         4: areturn
      LineNumberTable:
        line 41: 0
      LocalVariableTable:
        Start  Length  Slot  Name   Signature
            0       5     0  this   Lorg/sireum/MBox7;
    Signature: #119                         // ()TT5;

  public T5 getValue5();
    descriptor: ()Ljava/lang/Object;
    flags: (0x0001) ACC_PUBLIC
    Code:
      stack=1, locals=1, args_size=1
         0: aload_0
         1: getfield      #121                // Field _value5:Ljava/lang/Object;
         4: areturn
      LineNumberTable:
        line 41: 0
      LocalVariableTable:
        Start  Length  Slot  Name   Signature
            0       5     0  this   Lorg/sireum/MBox7;
    Signature: #119                         // ()TT5;

  public org.sireum.MBox7<T1, T2, T3, T4, T5, T6, T7> value5_$eq(T5);
    descriptor: (Ljava/lang/Object;)Lorg/sireum/MBox7;
    flags: (0x0001) ACC_PUBLIC
    Code:
      stack=2, locals=2, args_size=2
         0: aload_0
         1: aload_1
         2: putfield      #121                // Field _value5:Ljava/lang/Object;
         5: aload_0
         6: areturn
      LineNumberTable:
        line 41: 0
      LocalVariableTable:
        Start  Length  Slot  Name   Signature
            0       7     0  this   Lorg/sireum/MBox7;
            0       7     1 value5   Ljava/lang/Object;
    Signature: #124                         // (TT5;)Lorg/sireum/MBox7<TT1;TT2;TT3;TT4;TT5;TT6;TT7;>;
    MethodParameters:
      Name                           Flags
      value5                         final

  public org.sireum.MBox7<T1, T2, T3, T4, T5, T6, T7> setValue5(T5);
    descriptor: (Ljava/lang/Object;)Lorg/sireum/MBox7;
    flags: (0x0001) ACC_PUBLIC
    Code:
      stack=2, locals=2, args_size=2
         0: aload_0
         1: aload_1
         2: putfield      #121                // Field _value5:Ljava/lang/Object;
         5: aload_0
         6: areturn
      LineNumberTable:
        line 41: 0
      LocalVariableTable:
        Start  Length  Slot  Name   Signature
            0       7     0  this   Lorg/sireum/MBox7;
            0       7     1 value5   Ljava/lang/Object;
    Signature: #124                         // (TT5;)Lorg/sireum/MBox7<TT1;TT2;TT3;TT4;TT5;TT6;TT7;>;
    MethodParameters:
      Name                           Flags
      value5                         final

  public T6 value6();
    descriptor: ()Ljava/lang/Object;
    flags: (0x0001) ACC_PUBLIC
    Code:
      stack=1, locals=1, args_size=1
         0: aload_0
         1: getfield      #129                // Field _value6:Ljava/lang/Object;
         4: areturn
      LineNumberTable:
        line 41: 0
      LocalVariableTable:
        Start  Length  Slot  Name   Signature
            0       5     0  this   Lorg/sireum/MBox7;
    Signature: #127                         // ()TT6;

  public T6 getValue6();
    descriptor: ()Ljava/lang/Object;
    flags: (0x0001) ACC_PUBLIC
    Code:
      stack=1, locals=1, args_size=1
         0: aload_0
         1: getfield      #129                // Field _value6:Ljava/lang/Object;
         4: areturn
      LineNumberTable:
        line 41: 0
      LocalVariableTable:
        Start  Length  Slot  Name   Signature
            0       5     0  this   Lorg/sireum/MBox7;
    Signature: #127                         // ()TT6;

  public org.sireum.MBox7<T1, T2, T3, T4, T5, T6, T7> value6_$eq(T6);
    descriptor: (Ljava/lang/Object;)Lorg/sireum/MBox7;
    flags: (0x0001) ACC_PUBLIC
    Code:
      stack=2, locals=2, args_size=2
         0: aload_0
         1: aload_1
         2: putfield      #129                // Field _value6:Ljava/lang/Object;
         5: aload_0
         6: areturn
      LineNumberTable:
        line 41: 0
      LocalVariableTable:
        Start  Length  Slot  Name   Signature
            0       7     0  this   Lorg/sireum/MBox7;
            0       7     1 value6   Ljava/lang/Object;
    Signature: #132                         // (TT6;)Lorg/sireum/MBox7<TT1;TT2;TT3;TT4;TT5;TT6;TT7;>;
    MethodParameters:
      Name                           Flags
      value6                         final

  public org.sireum.MBox7<T1, T2, T3, T4, T5, T6, T7> setValue6(T6);
    descriptor: (Ljava/lang/Object;)Lorg/sireum/MBox7;
    flags: (0x0001) ACC_PUBLIC
    Code:
      stack=2, locals=2, args_size=2
         0: aload_0
         1: aload_1
         2: putfield      #129                // Field _value6:Ljava/lang/Object;
         5: aload_0
         6: areturn
      LineNumberTable:
        line 41: 0
      LocalVariableTable:
        Start  Length  Slot  Name   Signature
            0       7     0  this   Lorg/sireum/MBox7;
            0       7     1 value6   Ljava/lang/Object;
    Signature: #132                         // (TT6;)Lorg/sireum/MBox7<TT1;TT2;TT3;TT4;TT5;TT6;TT7;>;
    MethodParameters:
      Name                           Flags
      value6                         final

  public T7 value7();
    descriptor: ()Ljava/lang/Object;
    flags: (0x0001) ACC_PUBLIC
    Code:
      stack=1, locals=1, args_size=1
         0: aload_0
         1: getfield      #137                // Field _value7:Ljava/lang/Object;
         4: areturn
      LineNumberTable:
        line 41: 0
      LocalVariableTable:
        Start  Length  Slot  Name   Signature
            0       5     0  this   Lorg/sireum/MBox7;
    Signature: #135                         // ()TT7;

  public T7 getValue7();
    descriptor: ()Ljava/lang/Object;
    flags: (0x0001) ACC_PUBLIC
    Code:
      stack=1, locals=1, args_size=1
         0: aload_0
         1: getfield      #137                // Field _value7:Ljava/lang/Object;
         4: areturn
      LineNumberTable:
        line 41: 0
      LocalVariableTable:
        Start  Length  Slot  Name   Signature
            0       5     0  this   Lorg/sireum/MBox7;
    Signature: #135                         // ()TT7;

  public org.sireum.MBox7<T1, T2, T3, T4, T5, T6, T7> value7_$eq(T7);
    descriptor: (Ljava/lang/Object;)Lorg/sireum/MBox7;
    flags: (0x0001) ACC_PUBLIC
    Code:
      stack=2, locals=2, args_size=2
         0: aload_0
         1: aload_1
         2: putfield      #137                // Field _value7:Ljava/lang/Object;
         5: aload_0
         6: areturn
      LineNumberTable:
        line 41: 0
      LocalVariableTable:
        Start  Length  Slot  Name   Signature
            0       7     0  this   Lorg/sireum/MBox7;
            0       7     1 value7   Ljava/lang/Object;
    Signature: #140                         // (TT7;)Lorg/sireum/MBox7<TT1;TT2;TT3;TT4;TT5;TT6;TT7;>;
    MethodParameters:
      Name                           Flags
      value7                         final

  public org.sireum.MBox7<T1, T2, T3, T4, T5, T6, T7> setValue7(T7);
    descriptor: (Ljava/lang/Object;)Lorg/sireum/MBox7;
    flags: (0x0001) ACC_PUBLIC
    Code:
      stack=2, locals=2, args_size=2
         0: aload_0
         1: aload_1
         2: putfield      #137                // Field _value7:Ljava/lang/Object;
         5: aload_0
         6: areturn
      LineNumberTable:
        line 41: 0
      LocalVariableTable:
        Start  Length  Slot  Name   Signature
            0       7     0  this   Lorg/sireum/MBox7;
            0       7     1 value7   Ljava/lang/Object;
    Signature: #140                         // (TT7;)Lorg/sireum/MBox7<TT1;TT2;TT3;TT4;TT5;TT6;TT7;>;
    MethodParameters:
      Name                           Flags
      value7                         final

  public java.lang.String toString();
    descriptor: ()Ljava/lang/String;
    flags: (0x0001) ACC_PUBLIC
    Code:
      stack=3, locals=2, args_size=1
         0: aload_0
         1: invokevirtual #145                // Method $hasString:()Z
         4: ifeq          14
         7: aload_0
         8: invokestatic  #149                // InterfaceMethod org/sireum/RecordSig.string$:(Lorg/sireum/RecordSig;)Ljava/lang/String;
        11: goto          194
        14: new           #151                // class java/lang/StringBuilder
        17: dup
        18: invokespecial #155                // Method java/lang/StringBuilder."<init>":()V
        21: astore_1
        22: aload_1
        23: ldc           #157                // String MBox7
        25: invokevirtual #161                // Method java/lang/StringBuilder.append:(Ljava/lang/String;)Ljava/lang/StringBuilder;
        28: pop
        29: aload_1
        30: bipush        40
        32: invokevirtual #164                // Method java/lang/StringBuilder.append:(C)Ljava/lang/StringBuilder;
        35: pop
        36: aload_1
        37: getstatic     #169                // Field org/sireum/String$.MODULE$:Lorg/sireum/String$;
        40: aload_0
        41: invokevirtual #171                // Method value1:()Ljava/lang/Object;
        44: invokevirtual #175                // Method org/sireum/String$.escape:(Ljava/lang/Object;)Ljava/lang/String;
        47: invokevirtual #161                // Method java/lang/StringBuilder.append:(Ljava/lang/String;)Ljava/lang/StringBuilder;
        50: pop
        51: aload_1
        52: ldc           #177                // String ,
        54: invokevirtual #161                // Method java/lang/StringBuilder.append:(Ljava/lang/String;)Ljava/lang/StringBuilder;
        57: pop
        58: aload_1
        59: getstatic     #169                // Field org/sireum/String$.MODULE$:Lorg/sireum/String$;
        62: aload_0
        63: invokevirtual #179                // Method value2:()Ljava/lang/Object;
        66: invokevirtual #175                // Method org/sireum/String$.escape:(Ljava/lang/Object;)Ljava/lang/String;
        69: invokevirtual #161                // Method java/lang/StringBuilder.append:(Ljava/lang/String;)Ljava/lang/StringBuilder;
        72: pop
        73: aload_1
        74: ldc           #177                // String ,
        76: invokevirtual #161                // Method java/lang/StringBuilder.append:(Ljava/lang/String;)Ljava/lang/StringBuilder;
        79: pop
        80: aload_1
        81: getstatic     #169                // Field org/sireum/String$.MODULE$:Lorg/sireum/String$;
        84: aload_0
        85: invokevirtual #181                // Method value3:()Ljava/lang/Object;
        88: invokevirtual #175                // Method org/sireum/String$.escape:(Ljava/lang/Object;)Ljava/lang/String;
        91: invokevirtual #161                // Method java/lang/StringBuilder.append:(Ljava/lang/String;)Ljava/lang/StringBuilder;
        94: pop
        95: aload_1
        96: ldc           #177                // String ,
        98: invokevirtual #161                // Method java/lang/StringBuilder.append:(Ljava/lang/String;)Ljava/lang/StringBuilder;
       101: pop
       102: aload_1
       103: getstatic     #169                // Field org/sireum/String$.MODULE$:Lorg/sireum/String$;
       106: aload_0
       107: invokevirtual #183                // Method value4:()Ljava/lang/Object;
       110: invokevirtual #175                // Method org/sireum/String$.escape:(Ljava/lang/Object;)Ljava/lang/String;
       113: invokevirtual #161                // Method java/lang/StringBuilder.append:(Ljava/lang/String;)Ljava/lang/StringBuilder;
       116: pop
       117: aload_1
       118: ldc           #177                // String ,
       120: invokevirtual #161                // Method java/lang/StringBuilder.append:(Ljava/lang/String;)Ljava/lang/StringBuilder;
       123: pop
       124: aload_1
       125: getstatic     #169                // Field org/sireum/String$.MODULE$:Lorg/sireum/String$;
       128: aload_0
       129: invokevirtual #185                // Method value5:()Ljava/lang/Object;
       132: invokevirtual #175                // Method org/sireum/String$.escape:(Ljava/lang/Object;)Ljava/lang/String;
       135: invokevirtual #161                // Method java/lang/StringBuilder.append:(Ljava/lang/String;)Ljava/lang/StringBuilder;
       138: pop
       139: aload_1
       140: ldc           #177                // String ,
       142: invokevirtual #161                // Method java/lang/StringBuilder.append:(Ljava/lang/String;)Ljava/lang/StringBuilder;
       145: pop
       146: aload_1
       147: getstatic     #169                // Field org/sireum/String$.MODULE$:Lorg/sireum/String$;
       150: aload_0
       151: invokevirtual #187                // Method value6:()Ljava/lang/Object;
       154: invokevirtual #175                // Method org/sireum/String$.escape:(Ljava/lang/Object;)Ljava/lang/String;
       157: invokevirtual #161                // Method java/lang/StringBuilder.append:(Ljava/lang/String;)Ljava/lang/StringBuilder;
       160: pop
       161: aload_1
       162: ldc           #177                // String ,
       164: invokevirtual #161                // Method java/lang/StringBuilder.append:(Ljava/lang/String;)Ljava/lang/StringBuilder;
       167: pop
       168: aload_1
       169: getstatic     #169                // Field org/sireum/String$.MODULE$:Lorg/sireum/String$;
       172: aload_0
       173: invokevirtual #189                // Method value7:()Ljava/lang/Object;
       176: invokevirtual #175                // Method org/sireum/String$.escape:(Ljava/lang/Object;)Ljava/lang/String;
       179: invokevirtual #161                // Method java/lang/StringBuilder.append:(Ljava/lang/String;)Ljava/lang/StringBuilder;
       182: pop
       183: aload_1
       184: bipush        41
       186: invokevirtual #164                // Method java/lang/StringBuilder.append:(C)Ljava/lang/StringBuilder;
       189: pop
       190: aload_1
       191: invokevirtual #191                // Method java/lang/StringBuilder.toString:()Ljava/lang/String;
       194: areturn
      StackMapTable: number_of_entries = 2
        frame_type = 14 /* same */
        frame_type = 247 /* same_locals_1_stack_item_frame_extended */
          offset_delta = 179
          stack = [ class java/lang/String ]
      LineNumberTable:
        line 41: 0
      LocalVariableTable:
        Start  Length  Slot  Name   Signature
           22     172     1    sb   Ljava/lang/StringBuilder;
            0     195     0  this   Lorg/sireum/MBox7;

  public java.lang.String string();
    descriptor: ()Ljava/lang/String;
    flags: (0x0001) ACC_PUBLIC
    Code:
      stack=2, locals=1, args_size=1
         0: aload_0
         1: invokevirtual #145                // Method $hasString:()Z
         4: ifeq          14
         7: aload_0
         8: invokestatic  #149                // InterfaceMethod org/sireum/RecordSig.string$:(Lorg/sireum/RecordSig;)Ljava/lang/String;
        11: goto          24
        14: getstatic     #169                // Field org/sireum/String$.MODULE$:Lorg/sireum/String$;
        17: aload_0
        18: invokevirtual #197                // Method toString:()Ljava/lang/String;
        21: invokevirtual #201                // Method org/sireum/String$.apply:(Ljava/lang/String;)Ljava/lang/String;
        24: areturn
      StackMapTable: number_of_entries = 2
        frame_type = 14 /* same */
        frame_type = 73 /* same_locals_1_stack_item */
          stack = [ class java/lang/String ]
      LineNumberTable:
        line 41: 0
      LocalVariableTable:
        Start  Length  Slot  Name   Signature
            0      25     0  this   Lorg/sireum/MBox7;

  public int hashCode();
    descriptor: ()I
    flags: (0x0001) ACC_PUBLIC
    Code:
      stack=6, locals=1, args_size=1
         0: aload_0
         1: invokevirtual #205                // Method $hasEquals:()Z
         4: ifeq          14
         7: aload_0
         8: invokespecial #207                // Method java/lang/Object.hashCode:()I
        11: goto          103
        14: getstatic     #212                // Field scala/package$.MODULE$:Lscala/package$;
        17: invokevirtual #216                // Method scala/package$.Seq:()Lscala/collection/immutable/Seq$;
        20: getstatic     #221                // Field scala/runtime/ScalaRunTime$.MODULE$:Lscala/runtime/ScalaRunTime$;
        23: bipush        8
        25: anewarray     #5                  // class java/lang/Object
        28: dup
        29: iconst_0
        30: aload_0
        31: invokevirtual #225                // Method getClass:()Ljava/lang/Class;
        34: invokevirtual #230                // Method java/lang/Class.getName:()Ljava/lang/String;
        37: aastore
        38: dup
        39: iconst_1
        40: aload_0
        41: invokevirtual #171                // Method value1:()Ljava/lang/Object;
        44: aastore
        45: dup
        46: iconst_2
        47: aload_0
        48: invokevirtual #179                // Method value2:()Ljava/lang/Object;
        51: aastore
        52: dup
        53: iconst_3
        54: aload_0
        55: invokevirtual #181                // Method value3:()Ljava/lang/Object;
        58: aastore
        59: dup
        60: iconst_4
        61: aload_0
        62: invokevirtual #183                // Method value4:()Ljava/lang/Object;
        65: aastore
        66: dup
        67: iconst_5
        68: aload_0
        69: invokevirtual #185                // Method value5:()Ljava/lang/Object;
        72: aastore
        73: dup
        74: bipush        6
        76: aload_0
        77: invokevirtual #187                // Method value6:()Ljava/lang/Object;
        80: aastore
        81: dup
        82: bipush        7
        84: aload_0
        85: invokevirtual #189                // Method value7:()Ljava/lang/Object;
        88: aastore
        89: invokevirtual #234                // Method scala/runtime/ScalaRunTime$.genericWrapArray:(Ljava/lang/Object;)Lscala/collection/immutable/ArraySeq;
        92: invokevirtual #239                // Method scala/collection/immutable/Seq$.apply:(Lscala/collection/immutable/Seq;)Lscala/collection/SeqOps;
        95: checkcast     #241                // class scala/collection/Seq
        98: invokeinterface #242,  1          // InterfaceMethod scala/collection/Seq.hashCode:()I
       103: ireturn
      StackMapTable: number_of_entries = 2
        frame_type = 14 /* same */
        frame_type = 247 /* same_locals_1_stack_item_frame_extended */
          offset_delta = 88
          stack = [ int ]
      LineNumberTable:
        line 41: 0
      LocalVariableTable:
        Start  Length  Slot  Name   Signature
            0     104     0  this   Lorg/sireum/MBox7;

  public boolean equals(java.lang.Object);
    descriptor: (Ljava/lang/Object;)Z
    flags: (0x0001) ACC_PUBLIC
    Code:
      stack=2, locals=5, args_size=2
         0: aload_0
         1: invokevirtual #205                // Method $hasEquals:()Z
         4: ifeq          15
         7: aload_0
         8: aload_1
         9: invokespecial #246                // Method java/lang/Object.equals:(Ljava/lang/Object;)Z
        12: goto          178
        15: aload_0
        16: aload_1
        17: if_acmpne     24
        20: iconst_1
        21: goto          178
        24: aload_1
        25: astore_3
        26: aload_3
        27: instanceof    #2                  // class org/sireum/MBox7
        30: ifeq          169
        33: aload_3
        34: checkcast     #2                  // class org/sireum/MBox7
        37: astore        4
        39: aload_0
        40: invokevirtual #247                // Method hashCode:()I
        43: aload         4
        45: invokevirtual #247                // Method hashCode:()I
        48: if_icmpeq     55
        51: iconst_0
        52: goto          165
        55: aload_0
        56: invokevirtual #171                // Method value1:()Ljava/lang/Object;
        59: aload         4
        61: invokevirtual #171                // Method value1:()Ljava/lang/Object;
        64: invokestatic  #252                // Method scala/runtime/BoxesRunTime.equals:(Ljava/lang/Object;Ljava/lang/Object;)Z
        67: ifeq          164
        70: aload_0
        71: invokevirtual #179                // Method value2:()Ljava/lang/Object;
        74: aload         4
        76: invokevirtual #179                // Method value2:()Ljava/lang/Object;
        79: invokestatic  #252                // Method scala/runtime/BoxesRunTime.equals:(Ljava/lang/Object;Ljava/lang/Object;)Z
        82: ifeq          164
        85: aload_0
        86: invokevirtual #181                // Method value3:()Ljava/lang/Object;
        89: aload         4
        91: invokevirtual #181                // Method value3:()Ljava/lang/Object;
        94: invokestatic  #252                // Method scala/runtime/BoxesRunTime.equals:(Ljava/lang/Object;Ljava/lang/Object;)Z
        97: ifeq          164
       100: aload_0
       101: invokevirtual #183                // Method value4:()Ljava/lang/Object;
       104: aload         4
       106: invokevirtual #183                // Method value4:()Ljava/lang/Object;
       109: invokestatic  #252                // Method scala/runtime/BoxesRunTime.equals:(Ljava/lang/Object;Ljava/lang/Object;)Z
       112: ifeq          164
       115: aload_0
       116: invokevirtual #185                // Method value5:()Ljava/lang/Object;
       119: aload         4
       121: invokevirtual #185                // Method value5:()Ljava/lang/Object;
       124: invokestatic  #252                // Method scala/runtime/BoxesRunTime.equals:(Ljava/lang/Object;Ljava/lang/Object;)Z
       127: ifeq          164
       130: aload_0
       131: invokevirtual #187                // Method value6:()Ljava/lang/Object;
       134: aload         4
       136: invokevirtual #187                // Method value6:()Ljava/lang/Object;
       139: invokestatic  #252                // Method scala/runtime/BoxesRunTime.equals:(Ljava/lang/Object;Ljava/lang/Object;)Z
       142: ifeq          164
       145: aload_0
       146: invokevirtual #189                // Method value7:()Ljava/lang/Object;
       149: aload         4
       151: invokevirtual #189                // Method value7:()Ljava/lang/Object;
       154: invokestatic  #252                // Method scala/runtime/BoxesRunTime.equals:(Ljava/lang/Object;Ljava/lang/Object;)Z
       157: ifeq          164
       160: iconst_1
       161: goto          165
       164: iconst_0
       165: istore_2
       166: goto          177
       169: goto          172
       172: iconst_0
       173: istore_2
       174: goto          177
       177: iload_2
       178: ireturn
      StackMapTable: number_of_entries = 9
        frame_type = 15 /* same */
        frame_type = 8 /* same */
        frame_type = 254 /* append */
          offset_delta = 30
          locals = [ top, class java/lang/Object, class org/sireum/MBox7 ]
        frame_type = 251 /* same_frame_extended */
          offset_delta = 108
        frame_type = 64 /* same_locals_1_stack_item */
          stack = [ int ]
        frame_type = 250 /* chop */
          offset_delta = 3
        frame_type = 2 /* same */
        frame_type = 255 /* full_frame */
          offset_delta = 4
          locals = [ class org/sireum/MBox7, class java/lang/Object, int, class java/lang/Object ]
          stack = []
        frame_type = 255 /* full_frame */
          offset_delta = 0
          locals = [ class org/sireum/MBox7, class java/lang/Object ]
          stack = [ int ]
      LineNumberTable:
        line 41: 0
      LocalVariableTable:
        Start  Length  Slot  Name   Signature
            0     179     0  this   Lorg/sireum/MBox7;
            0     179     1     o   Ljava/lang/Object;
    MethodParameters:
      Name                           Flags
      o                              final

  public org.sireum.MBox7<T1, T2, T3, T4, T5, T6, T7> apply(T1, T2, T3, T4, T5, T6, T7);
    descriptor: (Ljava/lang/Object;Ljava/lang/Object;Ljava/lang/Object;Ljava/lang/Object;Ljava/lang/Object;Ljava/lang/Object;Ljava/lang/Object;)Lorg/sireum/MBox7;
    flags: (0x0001) ACC_PUBLIC
    Code:
      stack=9, locals=8, args_size=8
         0: new           #2                  // class org/sireum/MBox7
         3: dup
         4: aload_1
         5: aload_2
         6: aload_3
         7: aload         4
         9: aload         5
        11: aload         6
        13: aload         7
        15: invokespecial #257                // Method "<init>":(Ljava/lang/Object;Ljava/lang/Object;Ljava/lang/Object;Ljava/lang/Object;Ljava/lang/Object;Ljava/lang/Object;Ljava/lang/Object;)V
        18: areturn
      LineNumberTable:
        line 41: 0
      LocalVariableTable:
        Start  Length  Slot  Name   Signature
            0      19     0  this   Lorg/sireum/MBox7;
            0      19     1 value1   Ljava/lang/Object;
            0      19     2 value2   Ljava/lang/Object;
            0      19     3 value3   Ljava/lang/Object;
            0      19     4 value4   Ljava/lang/Object;
            0      19     5 value5   Ljava/lang/Object;
            0      19     6 value6   Ljava/lang/Object;
            0      19     7 value7   Ljava/lang/Object;
    Signature: #254                         // (TT1;TT2;TT3;TT4;TT5;TT6;TT7;)Lorg/sireum/MBox7<TT1;TT2;TT3;TT4;TT5;TT6;TT7;>;
    MethodParameters:
      Name                           Flags
      value1                         final
      value2                         final
      value3                         final
      value4                         final
      value5                         final
      value6                         final
      value7                         final

  public T1 apply$default$1();
    descriptor: ()Ljava/lang/Object;
    flags: (0x0001) ACC_PUBLIC
    Code:
      stack=1, locals=1, args_size=1
         0: aload_0
         1: invokevirtual #171                // Method value1:()Ljava/lang/Object;
         4: areturn
      LineNumberTable:
        line 41: 0
      LocalVariableTable:
        Start  Length  Slot  Name   Signature
            0       5     0  this   Lorg/sireum/MBox7;
    Signature: #86                          // ()TT1;

  public T2 apply$default$2();
    descriptor: ()Ljava/lang/Object;
    flags: (0x0001) ACC_PUBLIC
    Code:
      stack=1, locals=1, args_size=1
         0: aload_0
         1: invokevirtual #179                // Method value2:()Ljava/lang/Object;
         4: areturn
      LineNumberTable:
        line 41: 0
      LocalVariableTable:
        Start  Length  Slot  Name   Signature
            0       5     0  this   Lorg/sireum/MBox7;
    Signature: #95                          // ()TT2;

  public T3 apply$default$3();
    descriptor: ()Ljava/lang/Object;
    flags: (0x0001) ACC_PUBLIC
    Code:
      stack=1, locals=1, args_size=1
         0: aload_0
         1: invokevirtual #181                // Method value3:()Ljava/lang/Object;
         4: areturn
      LineNumberTable:
        line 41: 0
      LocalVariableTable:
        Start  Length  Slot  Name   Signature
            0       5     0  this   Lorg/sireum/MBox7;
    Signature: #103                         // ()TT3;

  public T4 apply$default$4();
    descriptor: ()Ljava/lang/Object;
    flags: (0x0001) ACC_PUBLIC
    Code:
      stack=1, locals=1, args_size=1
         0: aload_0
         1: invokevirtual #183                // Method value4:()Ljava/lang/Object;
         4: areturn
      LineNumberTable:
        line 41: 0
      LocalVariableTable:
        Start  Length  Slot  Name   Signature
            0       5     0  this   Lorg/sireum/MBox7;
    Signature: #111                         // ()TT4;

  public T5 apply$default$5();
    descriptor: ()Ljava/lang/Object;
    flags: (0x0001) ACC_PUBLIC
    Code:
      stack=1, locals=1, args_size=1
         0: aload_0
         1: invokevirtual #185                // Method value5:()Ljava/lang/Object;
         4: areturn
      LineNumberTable:
        line 41: 0
      LocalVariableTable:
        Start  Length  Slot  Name   Signature
            0       5     0  this   Lorg/sireum/MBox7;
    Signature: #119                         // ()TT5;

  public T6 apply$default$6();
    descriptor: ()Ljava/lang/Object;
    flags: (0x0001) ACC_PUBLIC
    Code:
      stack=1, locals=1, args_size=1
         0: aload_0
         1: invokevirtual #187                // Method value6:()Ljava/lang/Object;
         4: areturn
      LineNumberTable:
        line 41: 0
      LocalVariableTable:
        Start  Length  Slot  Name   Signature
            0       5     0  this   Lorg/sireum/MBox7;
    Signature: #127                         // ()TT6;

  public T7 apply$default$7();
    descriptor: ()Ljava/lang/Object;
    flags: (0x0001) ACC_PUBLIC
    Code:
      stack=1, locals=1, args_size=1
         0: aload_0
         1: invokevirtual #189                // Method value7:()Ljava/lang/Object;
         4: areturn
      LineNumberTable:
        line 41: 0
      LocalVariableTable:
        Start  Length  Slot  Name   Signature
            0       5     0  this   Lorg/sireum/MBox7;
    Signature: #135                         // ()TT7;

  public scala.collection.immutable.Seq<scala.Tuple2<java.lang.String, java.lang.Object>> $content();
    descriptor: ()Lscala/collection/immutable/Seq;
    flags: (0x0001) ACC_PUBLIC
    Code:
      stack=14, locals=1, args_size=1
         0: getstatic     #212                // Field scala/package$.MODULE$:Lscala/package$;
         3: invokevirtual #216                // Method scala/package$.Seq:()Lscala/collection/immutable/Seq$;
         6: getstatic     #221                // Field scala/runtime/ScalaRunTime$.MODULE$:Lscala/runtime/ScalaRunTime$;
         9: bipush        8
        11: anewarray     #269                // class scala/Tuple2
        14: dup
        15: iconst_0
        16: new           #269                // class scala/Tuple2
        19: dup
        20: ldc_w         #271                // String type
        23: getstatic     #212                // Field scala/package$.MODULE$:Lscala/package$;
        26: invokevirtual #275                // Method scala/package$.List:()Lscala/collection/immutable/List$;
        29: getstatic     #221                // Field scala/runtime/ScalaRunTime$.MODULE$:Lscala/runtime/ScalaRunTime$;
        32: iconst_3
        33: anewarray     #195                // class java/lang/String
        36: dup
        37: iconst_0
        38: ldc_w         #277                // String org
        41: aastore
        42: dup
        43: iconst_1
        44: ldc_w         #279                // String sireum
        47: aastore
        48: dup
        49: iconst_2
        50: ldc           #157                // String MBox7
        52: aastore
        53: checkcast     #281                // class "[Ljava/lang/Object;"
        56: invokevirtual #285                // Method scala/runtime/ScalaRunTime$.wrapRefArray:([Ljava/lang/Object;)Lscala/collection/immutable/ArraySeq;
        59: invokevirtual #290                // Method scala/collection/immutable/List$.apply:(Lscala/collection/immutable/Seq;)Ljava/lang/Object;
        62: invokespecial #293                // Method scala/Tuple2."<init>":(Ljava/lang/Object;Ljava/lang/Object;)V
        65: aastore
        66: dup
        67: iconst_1
        68: new           #269                // class scala/Tuple2
        71: dup
        72: ldc_w         #294                // String value1
        75: aload_0
        76: invokevirtual #171                // Method value1:()Ljava/lang/Object;
        79: invokespecial #293                // Method scala/Tuple2."<init>":(Ljava/lang/Object;Ljava/lang/Object;)V
        82: aastore
        83: dup
        84: iconst_2
        85: new           #269                // class scala/Tuple2
        88: dup
        89: ldc_w         #295                // String value2
        92: aload_0
        93: invokevirtual #179                // Method value2:()Ljava/lang/Object;
        96: invokespecial #293                // Method scala/Tuple2."<init>":(Ljava/lang/Object;Ljava/lang/Object;)V
        99: aastore
       100: dup
       101: iconst_3
       102: new           #269                // class scala/Tuple2
       105: dup
       106: ldc_w         #296                // String value3
       109: aload_0
       110: invokevirtual #181                // Method value3:()Ljava/lang/Object;
       113: invokespecial #293                // Method scala/Tuple2."<init>":(Ljava/lang/Object;Ljava/lang/Object;)V
       116: aastore
       117: dup
       118: iconst_4
       119: new           #269                // class scala/Tuple2
       122: dup
       123: ldc_w         #297                // String value4
       126: aload_0
       127: invokevirtual #183                // Method value4:()Ljava/lang/Object;
       130: invokespecial #293                // Method scala/Tuple2."<init>":(Ljava/lang/Object;Ljava/lang/Object;)V
       133: aastore
       134: dup
       135: iconst_5
       136: new           #269                // class scala/Tuple2
       139: dup
       140: ldc_w         #298                // String value5
       143: aload_0
       144: invokevirtual #185                // Method value5:()Ljava/lang/Object;
       147: invokespecial #293                // Method scala/Tuple2."<init>":(Ljava/lang/Object;Ljava/lang/Object;)V
       150: aastore
       151: dup
       152: bipush        6
       154: new           #269                // class scala/Tuple2
       157: dup
       158: ldc_w         #299                // String value6
       161: aload_0
       162: invokevirtual #187                // Method value6:()Ljava/lang/Object;
       165: invokespecial #293                // Method scala/Tuple2."<init>":(Ljava/lang/Object;Ljava/lang/Object;)V
       168: aastore
       169: dup
       170: bipush        7
       172: new           #269                // class scala/Tuple2
       175: dup
       176: ldc_w         #300                // String value7
       179: aload_0
       180: invokevirtual #189                // Method value7:()Ljava/lang/Object;
       183: invokespecial #293                // Method scala/Tuple2."<init>":(Ljava/lang/Object;Ljava/lang/Object;)V
       186: aastore
       187: checkcast     #281                // class "[Ljava/lang/Object;"
       190: invokevirtual #285                // Method scala/runtime/ScalaRunTime$.wrapRefArray:([Ljava/lang/Object;)Lscala/collection/immutable/ArraySeq;
       193: invokevirtual #239                // Method scala/collection/immutable/Seq$.apply:(Lscala/collection/immutable/Seq;)Lscala/collection/SeqOps;
       196: checkcast     #302                // class scala/collection/immutable/Seq
       199: areturn
      LineNumberTable:
        line 41: 0
      LocalVariableTable:
        Start  Length  Slot  Name   Signature
            0     200     0  this   Lorg/sireum/MBox7;
    Signature: #267                         // ()Lscala/collection/immutable/Seq<Lscala/Tuple2<Ljava/lang/String;Ljava/lang/Object;>;>;

  public org.sireum.MBox7<T1, T2, T3, T4, T5, T6, T7> $clone();
    descriptor: ()Lorg/sireum/MBox7;
    flags: (0x0001) ACC_PUBLIC
    Code:
      stack=10, locals=2, args_size=1
         0: new           #2                  // class org/sireum/MBox7
         3: dup
         4: getstatic     #310                // Field org/sireum/helper$.MODULE$:Lorg/sireum/helper$;
         7: aload_0
         8: invokevirtual #171                // Method value1:()Ljava/lang/Object;
        11: invokevirtual #314                // Method org/sireum/helper$.cloneAssign:(Ljava/lang/Object;)Ljava/lang/Object;
        14: getstatic     #310                // Field org/sireum/helper$.MODULE$:Lorg/sireum/helper$;
        17: aload_0
        18: invokevirtual #179                // Method value2:()Ljava/lang/Object;
        21: invokevirtual #314                // Method org/sireum/helper$.cloneAssign:(Ljava/lang/Object;)Ljava/lang/Object;
        24: getstatic     #310                // Field org/sireum/helper$.MODULE$:Lorg/sireum/helper$;
        27: aload_0
        28: invokevirtual #181                // Method value3:()Ljava/lang/Object;
        31: invokevirtual #314                // Method org/sireum/helper$.cloneAssign:(Ljava/lang/Object;)Ljava/lang/Object;
        34: getstatic     #310                // Field org/sireum/helper$.MODULE$:Lorg/sireum/helper$;
        37: aload_0
        38: invokevirtual #183                // Method value4:()Ljava/lang/Object;
        41: invokevirtual #314                // Method org/sireum/helper$.cloneAssign:(Ljava/lang/Object;)Ljava/lang/Object;
        44: getstatic     #310                // Field org/sireum/helper$.MODULE$:Lorg/sireum/helper$;
        47: aload_0
        48: invokevirtual #185                // Method value5:()Ljava/lang/Object;
        51: invokevirtual #314                // Method org/sireum/helper$.cloneAssign:(Ljava/lang/Object;)Ljava/lang/Object;
        54: getstatic     #310                // Field org/sireum/helper$.MODULE$:Lorg/sireum/helper$;
        57: aload_0
        58: invokevirtual #187                // Method value6:()Ljava/lang/Object;
        61: invokevirtual #314                // Method org/sireum/helper$.cloneAssign:(Ljava/lang/Object;)Ljava/lang/Object;
        64: getstatic     #310                // Field org/sireum/helper$.MODULE$:Lorg/sireum/helper$;
        67: aload_0
        68: invokevirtual #189                // Method value7:()Ljava/lang/Object;
        71: invokevirtual #314                // Method org/sireum/helper$.cloneAssign:(Ljava/lang/Object;)Ljava/lang/Object;
        74: invokespecial #257                // Method "<init>":(Ljava/lang/Object;Ljava/lang/Object;Ljava/lang/Object;Ljava/lang/Object;Ljava/lang/Object;Ljava/lang/Object;Ljava/lang/Object;)V
        77: astore_1
        78: aload_1
        79: areturn
      LineNumberTable:
        line 41: 0
      LocalVariableTable:
        Start  Length  Slot  Name   Signature
           78       1     1     r   Lorg/sireum/MBox7;
            0      80     0  this   Lorg/sireum/MBox7;
    Signature: #305                         // ()Lorg/sireum/MBox7<TT1;TT2;TT3;TT4;TT5;TT6;TT7;>;

  public final org.sireum.$internal.MutableMarker $owned_$eq(boolean);
    descriptor: (Z)Lorg/sireum/$internal/MutableMarker;
    flags: (0x1051) ACC_PUBLIC, ACC_FINAL, ACC_BRIDGE, ACC_SYNTHETIC
    Code:
      stack=2, locals=2, args_size=2
         0: aload_0
         1: iload_1
         2: invokevirtual #318                // Method $owned_$eq:(Z)Lorg/sireum/RecordSig;
         5: areturn
      LineNumberTable:
        line 41: 0
      LocalVariableTable:
        Start  Length  Slot  Name   Signature
            0       6     0  this   Lorg/sireum/MBox7;
            0       6     1     b   Z
    MethodParameters:
      Name                           Flags
      b                              final

  public java.lang.Object $clone();
    descriptor: ()Ljava/lang/Object;
    flags: (0x1041) ACC_PUBLIC, ACC_BRIDGE, ACC_SYNTHETIC
    Code:
      stack=1, locals=1, args_size=1
         0: aload_0
         1: invokevirtual #320                // Method $clone:()Lorg/sireum/MBox7;
         4: areturn
      LineNumberTable:
        line 41: 0
      LocalVariableTable:
        Start  Length  Slot  Name   Signature
            0       5     0  this   Lorg/sireum/MBox7;

  public org.sireum.$internal.MutableMarker $clone();
    descriptor: ()Lorg/sireum/$internal/MutableMarker;
    flags: (0x1041) ACC_PUBLIC, ACC_BRIDGE, ACC_SYNTHETIC
    Code:
      stack=1, locals=1, args_size=1
         0: aload_0
         1: invokevirtual #320                // Method $clone:()Lorg/sireum/MBox7;
         4: areturn
      LineNumberTable:
        line 41: 0
      LocalVariableTable:
        Start  Length  Slot  Name   Signature
            0       5     0  this   Lorg/sireum/MBox7;

  public org.sireum.MBox7(T1, T2, T3, T4, T5, T6, T7);
    descriptor: (Ljava/lang/Object;Ljava/lang/Object;Ljava/lang/Object;Ljava/lang/Object;Ljava/lang/Object;Ljava/lang/Object;Ljava/lang/Object;)V
    flags: (0x0001) ACC_PUBLIC
    Code:
      stack=2, locals=8, args_size=8
         0: aload_0
         1: invokespecial #330                // Method java/lang/Object."<init>":()V
         4: aload_0
         5: invokestatic  #334                // InterfaceMethod org/sireum/Mutable.$init$:(Lorg/sireum/Mutable;)V
         8: aload_0
         9: invokestatic  #337                // InterfaceMethod org/sireum/RecordSig.$init$:(Lorg/sireum/RecordSig;)V
        12: aload_0
        13: aload_1
        14: putfield      #88                 // Field _value1:Ljava/lang/Object;
        17: aload_0
        18: aload_2
        19: putfield      #97                 // Field _value2:Ljava/lang/Object;
        22: aload_0
        23: aload_3
        24: putfield      #105                // Field _value3:Ljava/lang/Object;
        27: aload_0
        28: aload         4
        30: putfield      #113                // Field _value4:Ljava/lang/Object;
        33: aload_0
        34: aload         5
        36: putfield      #121                // Field _value5:Ljava/lang/Object;
        39: aload_0
        40: aload         6
        42: putfield      #129                // Field _value6:Ljava/lang/Object;
        45: aload_0
        46: aload         7
        48: putfield      #137                // Field _value7:Ljava/lang/Object;
        51: return
      LineNumberTable:
        line 41: 0
      LocalVariableTable:
        Start  Length  Slot  Name   Signature
            0      52     0  this   Lorg/sireum/MBox7;
            0      52     1 __value1   Ljava/lang/Object;
            0      52     2 __value2   Ljava/lang/Object;
            0      52     3 __value3   Ljava/lang/Object;
            0      52     4 __value4   Ljava/lang/Object;
            0      52     5 __value5   Ljava/lang/Object;
            0      52     6 __value6   Ljava/lang/Object;
            0      52     7 __value7   Ljava/lang/Object;
    Signature: #322                         // (TT1;TT2;TT3;TT4;TT5;TT6;TT7;)V
    MethodParameters:
      Name                           Flags
      __value1                       final
      __value2                       final
      __value3                       final
      __value4                       final
      __value5                       final
      __value6                       final
      __value7                       final
}
Signature: #3                           // <T1:Ljava/lang/Object;T2:Ljava/lang/Object;T3:Ljava/lang/Object;T4:Ljava/lang/Object;T5:Ljava/lang/Object;T6:Ljava/lang/Object;T7:Ljava/lang/Object;>Ljava/lang/Object;Lorg/sireum/RecordSig;
SourceFile: "MBox.scala"
RuntimeVisibleAnnotations:
  0: #9(#10=s#11)
    scala.reflect.ScalaSignature(
      bytes="\u0006\u0005\t\u001dv!B A\u0011\u0003)e!B$A\u0011\u0003A\u0005\"B(\u0002\t\u0003\u0001\u0006\"B)\u0002\t\u0003\u0011\u0006b\u0002B;\u0003\u0011\u0005!q\u000f\u0004\u0005\u000f\u0002\u0013Q\u000b\u0003\u0005[\u000b\t\u0005\t\u0015!\u0003\\\u0011!1WA!A!\u0002\u00139\u0007\u0002\u00036\u0006\u0005\u0003\u0005\u000b\u0011B6\t\u00119,!\u0011!Q\u0001\n=D\u0001B]\u0003\u0003\u0002\u0003\u0006Ia\u001d\u0005\tm\u0016\u0011\t\u0011)A\u0005o\"A!0\u0002B\u0001B\u0003%1\u0010C\u0003P\u000b\u0011\u0005a\u0010C\u0004\u0002\u0010\u0015\u0001\u000b\u0015B.\t\u000f\u0005EQ\u0001\"\u0001\u0002\u0014!9\u0011QC\u0003\u0005\u0002\u0005M\u0001bBA\f\u000b\u0011\u0005\u0011\u0011\u0004\u0005\b\u0003?)A\u0011AA\u0011\u0011\u001d\t)#\u0002Q!\n\u001dDq!a\n\u0006\t\u0003\tI\u0003C\u0004\u0002,\u0015!\t!!\u000b\t\u000f\u00055R\u0001\"\u0001\u00020!9\u00111G\u0003\u0005\u0002\u0005U\u0002bBA\u001d\u000b\u0001\u0006Ka\u001b\u0005\b\u0003w)A\u0011AA\u001f\u0011\u001d\ty$\u0002C\u0001\u0003{Aq!!\u0011\u0006\t\u0003\t\u0019\u0005C\u0004\u0002H\u0015!\t!!\u0013\t\u000f\u00055S\u0001)Q\u0005_\"9\u0011qJ\u0003\u0005\u0002\u0005E\u0003bBA*\u000b\u0011\u0005\u0011\u0011\u000b\u0005\b\u0003+*A\u0011AA,\u0011\u001d\tY&\u0002C\u0001\u0003;Bq!!\u0019\u0006A\u0003&1\u000fC\u0004\u0002d\u0015!\t!!\u001a\t\u000f\u0005\u001dT\u0001\"\u0001\u0002f!9\u0011\u0011N\u0003\u0005\u0002\u0005-\u0004bBA8\u000b\u0011\u0005\u0011\u0011\u000f\u0005\b\u0003k*\u0001\u0015)\u0003x\u0011\u001d\t9(\u0002C\u0001\u0003sBq!a\u001f\u0006\t\u0003\tI\bC\u0004\u0002~\u0015!\t!a \t\u000f\u0005\rU\u0001\"\u0001\u0002\u0006\"9\u0011\u0011R\u0003!B\u0013Y\bbBAF\u000b\u0011\u0005\u0011Q\u0012\u0005\b\u0003\u001f+A\u0011AAG\u0011\u001d\t\t*\u0002C\u0001\u0003\'Cq!a&\u0006\t\u0003\tI\nC\u0004\u0002\u001e\u0016!\t%a(\t\u000f\u0005EV\u0001\"\u0011\u00024\"9\u0011\u0011X\u0003\u0005B\u0005m\u0006bBAb\u000b\u0011\u0005\u0013Q\u0019\u0005\u0007#\u0016!\t!!5\t\u0013\u0005\u0005X!%A\u0005\u0002\u0005\r\b\"CA}\u000bE\u0005I\u0011AA~\u0011%\ty0BI\u0001\n\u0003\u0011\t\u0001C\u0005\u0003\u0006\u0015\t\n\u0011\"\u0001\u0003\b!I!1B\u0003\u0012\u0002\u0013\u0005!Q\u0002\u0005\n\u0005#)\u0011\u0013!C\u0001\u0005\'A\u0011Ba\u0006\u0006#\u0003%\tA!\u0007\t\u000f\tuQ\u0001\"\u0011\u0003 !9!qH\u0003\u0005B\t\u0005\u0013!B\'C_b<$BA!C\u0003\u0019\u0019\u0018N]3v[*\t1)A\u0002pe\u001e\u001c\u0001\u0001\u0005\u0002G\u00035\t\u0001IA\u0003N\u0005>Dxg\u0005\u0002\u0002\u0013B\u0011!*T\u0007\u0002\u0017*\tA*A\u0003tG\u0006d\u0017-\u0003\u0002O\u0017\n1\u0011I\\=SK\u001a\fa\u0001P5oSRtD#A#\u0002\u000b\u0005\u0004\b\u000f\\=\u0016\u001fM\u0013iE!\u0015\u0003V\te#Q\fB1\u0005K\"r\u0002\u0016B4\u0005S\u0012YG!\u001c\u0003p\tE$1\u000f\t\u0011\r\u0016\u0011YEa\u0014\u0003T\t]#1\fB0\u0005G*\u0002BV/iYB$\b\u0010`\n\u0004\u000b%;\u0006C\u0001$Y\u0013\tI\u0006IA\u0005SK\u000e|\'\u000fZ*jO\u0006Aql\u0018<bYV,\u0017\u0007\u0005\u0002];2\u0001A!\u00020\u0006\u0005\u0004y&A\u0001+2#\t\u00017\r\u0005\u0002KC&\u0011!m\u0013\u0002\b\u001d>$\b.\u001b8h!\tQE-\u0003\u0002f\u0017\n\u0019\u0011I\\=\u0002\u0011}{f/\u00197vKJ\u0002\"\u0001\u00185\u0005\u000b%,!\u0019A0\u0003\u0005Q\u0013\u0014\u0001C0`m\u0006dW/Z\u001a\u0011\u0005qcG!B7\u0006\u0005\u0004y&A\u0001+4\u0003!yvL^1mk\u0016$\u0004C\u0001/q\t\u0015\tXA1\u0001`\u0005\t!F\'\u0001\u0005`?Z\fG.^36!\taF\u000fB\u0003v\u000b\t\u0007qL\u0001\u0002Uk\u0005Aql\u0018<bYV,g\u0007\u0005\u0002]q\u0012)\u00110\u0002b\u0001?\n\u0011AKN\u0001\t?~3\u0018\r\\;foA\u0011A\f \u0003\u0006{\u0016\u0011\ra\u0018\u0002\u0003)^\"rb`A\u0001\u0003\u0007\t)!a\u0002\u0002\n\u0005-\u0011Q\u0002\t\n\r\u0016Yvm[8tonDQAW\u0007A\u0002mCQAZ\u0007A\u0002\u001dDQA[\u0007A\u0002-DQA\\\u0007A\u0002=DQA]\u0007A\u0002MDQA^\u0007A\u0002]DQA_\u0007A\u0002m\fqa\u0018<bYV,\u0017\'\u0001\u0004wC2,X-M\u000b\u00027\u0006Iq-\u001a;WC2,X-M\u0001\u000bm\u0006dW/Z\u0019`I\u0015\fH\u0003BA\u000e\u0003;i\u0011!\u0002\u0005\u0007\u0003#\t\u0002\u0019A.\u0002\u0013M,GOV1mk\u0016\fD\u0003BA\u000e\u0003GAa!!\u0005\u0013\u0001\u0004Y\u0016aB0wC2,XMM\u0001\u0007m\u0006dW/\u001a\u001a\u0016\u0003\u001d\f\u0011bZ3u-\u0006dW/\u001a\u001a\u0002\u0015Y\fG.^33?\u0012*\u0017\u000f\u0006\u0003\u0002\u001c\u0005E\u0002BBA\u0014-\u0001\u0007q-A\u0005tKR4\u0016\r\\;feQ!\u00111DA\u001c\u0011\u0019\t9c\u0006a\u0001O\u00069qL^1mk\u0016\u001c\u0014A\u0002<bYV,7\'F\u0001l\u0003%9W\r\u001e,bYV,7\'\u0001\u0006wC2,XmM0%KF$B!a\u0007\u0002F!1\u00111H\u000eA\u0002-\f\u0011b]3u-\u0006dW/Z\u001a\u0015\t\u0005m\u00111\n\u0005\u0007\u0003wa\u0002\u0019A6\u0002\u000f}3\u0018\r\\;fi\u00051a/\u00197vKR*\u0012a\\\u0001\nO\u0016$h+\u00197vKR\n!B^1mk\u0016$t\fJ3r)\u0011\tY\"!\u0017\t\r\u0005=\u0003\u00051\u0001p\u0003%\u0019X\r\u001e,bYV,G\u0007\u0006\u0003\u0002\u001c\u0005}\u0003BBA(C\u0001\u0007q.A\u0004`m\u0006dW/Z\u001b\u0002\rY\fG.^36+\u0005\u0019\u0018!C4fiZ\u000bG.^36\u0003)1\u0018\r\\;fk}#S-\u001d\u000b\u0005\u00037\ti\u0007\u0003\u0004\u0002d\u0015\u0002\ra]\u0001\ng\u0016$h+\u00197vKV\"B!a\u0007\u0002t!1\u00111\r\u0014A\u0002M\fqa\u0018<bYV,g\'\u0001\u0004wC2,XMN\u000b\u0002o\u0006Iq-\u001a;WC2,XMN\u0001\u000bm\u0006dW/\u001a\u001c`I\u0015\fH\u0003BA\u000e\u0003\u0003Ca!a\u001e+\u0001\u00049\u0018!C:fiZ\u000bG.^37)\u0011\tY\"a\"\t\r\u0005]4\u00061\u0001x\u0003\u001dyf/\u00197vK^\naA^1mk\u0016<T#A>\u0002\u0013\u001d,GOV1mk\u0016<\u0014A\u0003<bYV,wg\u0018\u0013fcR!\u00111DAK\u0011\u0019\tYi\fa\u0001w\u0006I1/\u001a;WC2,Xm\u000e\u000b\u0005\u00037\tY\n\u0003\u0004\u0002\fB\u0002\ra_\u0001\ti>\u001cFO]5oOR\u0011\u0011\u0011\u0015\t\u0005\u0003G\u000bi+\u0004\u0002\u0002&*!\u0011qUAU\u0003\u0011a\u0017M\\4\u000b\u0005\u0005-\u0016\u0001\u00026bm\u0006LA!a,\u0002&\n11\u000b\u001e:j]\u001e\faa\u001d;sS:<WCAA[!\r1\u0015qW\u0005\u0004\u0003_\u0003\u0015\u0001\u00035bg\"\u001cu\u000eZ3\u0015\u0005\u0005u\u0006c\u0001&\u0002@&\u0019\u0011\u0011Y&\u0003\u0007%sG/\u0001\u0004fcV\fGn\u001d\u000b\u0005\u0003\u000f\fi\rE\u0002K\u0003\u0013L1!a3L\u0005\u001d\u0011un\u001c7fC:Da!a45\u0001\u0004\u0019\u0017!A8\u0015\u001f}\f\u0019.!6\u0002X\u0006e\u00171\\Ao\u0003?D\u0001\"!\u00056!\u0003\u0005\ra\u0017\u0005\t\u0003O)\u0004\u0013!a\u0001O\"A\u00111H\u001b\u0011\u0002\u0003\u00071\u000e\u0003\u0005\u0002PU\u0002\n\u00111\u0001p\u0011!\t\u0019\'\u000eI\u0001\u0002\u0004\u0019\b\u0002CA<kA\u0005\t\u0019A<\t\u0011\u0005-U\u0007%AA\u0002m\fq\"\u00199qYf$C-\u001a4bk2$H%M\u000b\u0003\u0003KT3aWAtW\t\tI\u000f\u0005\u0003\u0002l\u0006UXBAAw\u0015\u0011\ty/!=\u0002\u0013Ut7\r[3dW\u0016$\'bAAz\u0017\u0006Q\u0011M\u001c8pi\u0006$\u0018n\u001c8\n\t\u0005]\u0018Q\u001e\u0002\u0012k:\u001c\u0007.Z2lK\u00124\u0016M]5b]\u000e,\u0017aD1qa2LH\u0005Z3gCVdG\u000f\n\u001a\u0016\u0005\u0005u(fA4\u0002h\u0006y\u0011\r\u001d9ms\u0012\"WMZ1vYR$3\'\u0006\u0002\u0003\u0004)\u001a1.a:\u0002\u001f\u0005\u0004\b\u000f\\=%I\u00164\u0017-\u001e7uIQ*\"A!\u0003+\u0007=\f9/A\bbaBd\u0017\u0010\n3fM\u0006,H\u000e\u001e\u00136+\t\u0011yAK\u0002t\u0003O\fq\"\u00199qYf$C-\u001a4bk2$HEN\u000b\u0003\u0005+Q3a^At\u0003=\t\u0007\u000f\u001d7zI\u0011,g-Y;mi\u0012:TC\u0001B\u000eU\rY\u0018q]\u0001\tI\r|g\u000e^3oiV\u0011!\u0011\u0005\t\u0007\u0005G\u0011\u0019D!\u000f\u000f\t\t\u0015\"q\u0006\b\u0005\u0005O\u0011i#\u0004\u0002\u0003*)\u0019!1\u0006#\u0002\rq\u0012xn\u001c;?\u0013\u0005a\u0015b\u0001B\u0019\u0017\u00069\u0001/Y2lC\u001e,\u0017\u0002\u0002B\u001b\u0005o\u00111aU3r\u0015\r\u0011\td\u0013\t\u0007\u0015\nm\u0012\u0011U2\n\u0007\tu2J\u0001\u0004UkBdWMM\u0001\u0007I\rdwN\\3\u0016\u0003}D3!\u0002B#!\r1%qI\u0005\u0004\u0005\u0013\u0002%A\u0002:fG>\u0014H\rE\u0002]\u0005\u001b\"QAX\u0002C\u0002}\u00032\u0001\u0018B)\t\u0015I7A1\u0001`!\ra&Q\u000b\u0003\u0006[\u000e\u0011\ra\u0018\t\u00049\neC!B9\u0004\u0005\u0004y\u0006c\u0001/\u0003^\u0011)Qo\u0001b\u0001?B\u0019AL!\u0019\u0005\u000be\u001c!\u0019A0\u0011\u0007q\u0013)\u0007B\u0003~\u0007\t\u0007q\fC\u0004\u0002\u0012\r\u0001\rAa\u0013\t\u000f\u0005\u001d2\u00011\u0001\u0003P!9\u00111H\u0002A\u0002\tM\u0003bBA(\u0007\u0001\u0007!q\u000b\u0005\b\u0003G\u001a\u0001\u0019\u0001B.\u0011\u001d\t9h\u0001a\u0001\u0005?Bq!a#\u0004\u0001\u0004\u0011\u0019\'A\u0004v]\u0006\u0004\b\u000f\\=\u0016!\te$\u0011\u0012BG\u0005#\u0013)J!\'\u0003\u001e\n\u0005F\u0003\u0002B>\u0005G\u0003RA\u0013B?\u0005\u0003K1Aa L\u0005\u0011\u0019v.\\3\u0011#)\u0013\u0019Ia\"\u0003\f\n=%1\u0013BL\u00057\u0013y*C\u0002\u0003\u0006.\u0013a\u0001V;qY\u0016<\u0004c\u0001/\u0003\n\u0012)a\f\u0002b\u0001?B\u0019AL!$\u0005\u000b%$!\u0019A0\u0011\u0007q\u0013\t\nB\u0003n\t\t\u0007q\fE\u0002]\u0005+#Q!\u001d\u0003C\u0002}\u00032\u0001\u0018BM\t\u0015)HA1\u0001`!\ra&Q\u0014\u0003\u0006s\u0012\u0011\ra\u0018\t\u00049\n\u0005F!B?\u0005\u0005\u0004y\u0006bBAh\t\u0001\u0007!Q\u0015\t\u0011\r\u0016\u00119Ia#\u0003\u0010\nM%q\u0013BN\u0005?\u0003"
    )
  ScalaInlineInfo: length = 0x112 (unknown attribute)
   01 01 00 36 00 3E 00 3F 01 01 2F 00 55 01 01 2F
   01 41 01 01 2F 01 30 01 01 09 01 0A 01 00 46 00
   2B 01 00 4B 00 2B 01 00 2A 00 2B 01 00 31 01 3C
   01 00 31 00 32 01 00 98 00 FF 01 00 C6 00 FD 01
   01 02 00 55 01 01 03 00 55 01 01 04 00 55 01 01
   05 00 55 01 01 06 00 55 01 01 07 00 55 01 01 08
   00 55 01 00 F3 00 F4 01 00 59 00 55 01 00 62 00
   55 01 00 6A 00 55 01 00 72 00 55 01 00 7A 00 55
   01 00 82 00 55 01 00 8A 00 55 01 00 38 00 39 01
   00 CA 00 CB 01 00 1B 00 2B 01 00 51 00 52 01 00
   5D 00 5B 01 00 65 00 5B 01 00 6D 00 5B 01 00 75
   00 5B 01 00 7D 00 5B 01 00 85 00 5B 01 00 8D 00
   5B 01 00 C4 00 8F 01 00 8E 00 8F 01 00 54 00 55
   01 00 5A 00 5B 01 00 5E 00 55 01 00 63 00 5B 01
   00 66 00 55 01 00 6B 00 5B 01 00 6E 00 55 01 00
   73 00 5B 01 00 76 00 55 01 00 7B 00 5B 01 00 7E
   00 55 01 00 83 00 5B 01 00 86 00 55 01 00 8B 00
   5B 01
  ScalaSig: length = 0x3 (unknown attribute)
   05 02 00
