Classfile /Users/mw/Projects/slang-braindump/.jar/jar8/assemble/slang-braindump/assemble/content/org/sireum/MBox16.class
  Last modified May 29, 2022; size 25687 bytes
  SHA-256 checksum a8365736f071de3d4e1568a49cb8c83e3477a38e2f7bc570e9dc07efc466492e
  Compiled from "MBox.scala"
public final class org.sireum.MBox16<T1 extends java.lang.Object, T2 extends java.lang.Object, T3 extends java.lang.Object, T4 extends java.lang.Object, T5 extends java.lang.Object, T6 extends java.lang.Object, T7 extends java.lang.Object, T8 extends java.lang.Object, T9 extends java.lang.Object, T10 extends java.lang.Object, T11 extends java.lang.Object, T12 extends java.lang.Object, T13 extends java.lang.Object, T14 extends java.lang.Object, T15 extends java.lang.Object, T16 extends java.lang.Object> extends java.lang.Object implements org.sireum.RecordSig
  minor version: 0
  major version: 52
  flags: (0x0031) ACC_PUBLIC, ACC_FINAL, ACC_SUPER
  this_class: #2                          // org/sireum/MBox16
  super_class: #5                         // java/lang/Object
  interfaces: 1, fields: 17, methods: 100, attributes: 5
Constant pool:
    #1 = Utf8               org/sireum/MBox16
    #2 = Class              #1            // org/sireum/MBox16
    #3 = Utf8               <T1:Ljava/lang/Object;T2:Ljava/lang/Object;T3:Ljava/lang/Object;T4:Ljava/lang/Object;T5:Ljava/lang/Object;T6:Ljava/lang/Object;T7:Ljava/lang/Object;T8:Ljava/lang/Object;T9:Ljava/lang/Object;T10:Ljava/lang/Object;T11:Ljava/lang/Object;T12:Ljava/lang/Object;T13:Ljava/lang/Object;T14:Ljava/lang/Object;T15:Ljava/lang/Object;T16:Ljava/lang/Object;>Ljava/lang/Object;Lorg/sireum/RecordSig;
    #4 = Utf8               java/lang/Object
    #5 = Class              #4            // java/lang/Object
    #6 = Utf8               org/sireum/RecordSig
    #7 = Class              #6            // org/sireum/RecordSig
    #8 = Utf8               MBox.scala
    #9 = Utf8               Lscala/reflect/ScalaSignature;
   #10 = Utf8               bytes
   #11 = Utf8               \u0006\u0005\u0011UwA\u0002@\u0000\u0011\u0003\tIAB\u0004\u0002\u000e}D\t!a\u0004\t\u000f\u0005u\u0011\u0001\"\u0001\u0002 !9\u0011\u0011E\u0001\u0005\u0002\u0005\r\u0002b\u0002C@\u0003\u0011\u0005A\u0011\u0011\u0004\u0007\u0003\u001by(!!\u000b\t\u0015\u0005MRA!A!\u0002\u0013\t)\u0004\u0003\u0006\u0002L\u0015\u0011\t\u0011)A\u0005\u0003\u001bB!\"a\u0015\u0006\u0005\u0003\u0005\u000b\u0011BA+\u0011)\tY&\u0002B\u0001B\u0003%\u0011Q\f\u0005\u000b\u0003G*!\u0011!Q\u0001\n\u0005\u0015\u0004BCA6\u000b\t\u0005\t\u0015!\u0003\u0002n!Q\u00111O\u0003\u0003\u0002\u0003\u0006I!!\u001e\t\u0015\u0005mTA!A!\u0002\u0013\ti\b\u0003\u0006\u0002\u0004\u0016\u0011\t\u0011)A\u0005\u0003\u000bC!\"a#\u0006\u0005\u0003\u0005\u000b\u0011BAG\u0011)\t\u0019*\u0002B\u0001B\u0003%\u0011Q\u0013\u0005\u000b\u00037+!\u0011!Q\u0001\n\u0005u\u0005BCAR\u000b\t\u0005\t\u0015!\u0003\u0002&\"Q\u00111V\u0003\u0003\u0002\u0003\u0006I!!,\t\u0015\u0005MVA!A!\u0002\u0013\t)\f\u0003\u0006\u0002<\u0016\u0011\t\u0011)A\u0005\u0003{Cq!!\b\u0006\t\u0003\t\u0019\r\u0003\u0005\u0002h\u0016\u0001\u000b\u0015BA\u001b\u0011\u001d\tI/\u0002C\u0001\u0003WDq!!<\u0006\t\u0003\tY\u000fC\u0004\u0002p\u0016!\t!!=\t\u000f\u0005]X\u0001\"\u0001\u0002z\"A\u0011Q`\u0003!B\u0013\ti\u0005C\u0004\u0002\u0000\u0016!\tA!\u0001\t\u000f\t\rQ\u0001\"\u0001\u0003\u0002!9!QA\u0003\u0005\u0002\t\u001d\u0001b\u0002B\u0006\u000b\u0011\u0005!Q\u0002\u0005\t\u0005#)\u0001\u0015)\u0003\u0002V!9!1C\u0003\u0005\u0002\tU\u0001b\u0002B\f\u000b\u0011\u0005!Q\u0003\u0005\b\u00053)A\u0011\u0001B\u000e\u0011\u001d\u0011y\"\u0002C\u0001\u0005CA\u0001B!\n\u0006A\u0003&\u0011Q\f\u0005\b\u0005O)A\u0011\u0001B\u0015\u0011\u001d\u0011Y#\u0002C\u0001\u0005SAqA!\f\u0006\t\u0003\u0011y\u0003C\u0004\u00034\u0015!\tA!\u000e\t\u0011\teR\u0001)Q\u0005\u0003KBqAa\u000f\u0006\t\u0003\u0011i\u0004C\u0004\u0003@\u0015!\tA!\u0010\t\u000f\t\u0005S\u0001\"\u0001\u0003D!9!qI\u0003\u0005\u0002\t%\u0003\u0002\u0003B\'\u000b\u0001\u0006K!!\u001c\t\u000f\t=S\u0001\"\u0001\u0003R!9!1K\u0003\u0005\u0002\tE\u0003b\u0002B+\u000b\u0011\u0005!q\u000b\u0005\b\u00057*A\u0011\u0001B/\u0011!\u0011\t\'\u0002Q!\n\u0005U\u0004b\u0002B2\u000b\u0011\u0005!Q\r\u0005\b\u0005O*A\u0011\u0001B3\u0011\u001d\u0011I\'\u0002C\u0001\u0005WBqAa\u001c\u0006\t\u0003\u0011\t\b\u0003\u0005\u0003v\u0015\u0001\u000b\u0015BA?\u0011\u001d\u00119(\u0002C\u0001\u0005sBqAa\u001f\u0006\t\u0003\u0011I\bC\u0004\u0003~\u0015!\tAa \t\u000f\t\rU\u0001\"\u0001\u0003\u0006\"A!\u0011R\u0003!B\u0013\t)\tC\u0004\u0003\f\u0016!\tA!$\t\u000f\t=U\u0001\"\u0001\u0003\u000e\"9!\u0011S\u0003\u0005\u0002\tM\u0005b\u0002BL\u000b\u0011\u0005!\u0011\u0014\u0005\t\u0005;+\u0001\u0015)\u0003\u0002\u000e\"9!qT\u0003\u0005\u0002\t\u0005\u0006b\u0002BR\u000b\u0011\u0005!\u0011\u0015\u0005\b\u0005K+A\u0011\u0001BT\u0011\u001d\u0011Y+\u0002C\u0001\u0005[C\u0001B!-\u0006A\u0003&\u0011Q\u0013\u0005\b\u0005g+A\u0011\u0001B[\u0011\u001d\u00119,\u0002C\u0001\u0005kCqA!/\u0006\t\u0003\u0011Y\fC\u0004\u0003@\u0016!\tA!1\t\u0011\t\u0015W\u0001)Q\u0005\u0003;CqAa2\u0006\t\u0003\u0011I\rC\u0004\u0003L\u0016!\tA!3\t\u000f\t5W\u0001\"\u0001\u0003P\"9!1[\u0003\u0005\u0002\tU\u0007\u0002\u0003Bm\u000b\u0001\u0006K!!*\t\u000f\tmW\u0001\"\u0001\u0003^\"9!q\\\u0003\u0005\u0002\tu\u0007b\u0002Bq\u000b\u0011\u0005!1\u001d\u0005\b\u0005O,A\u0011\u0001Bu\u0011!\u0011i/\u0002Q!\n\u00055\u0006b\u0002Bx\u000b\u0011\u0005!\u0011\u001f\u0005\b\u0005g,A\u0011\u0001By\u0011\u001d\u0011)0\u0002C\u0001\u0005oDqAa?\u0006\t\u0003\u0011i\u0010\u0003\u0005\u0004\u0002\u0015\u0001\u000b\u0015BA[\u0011\u001d\u0019\u0019!\u0002C\u0001\u0007\u000bAqaa\u0002\u0006\t\u0003\u0019)\u0001C\u0004\u0004\n\u0015!\taa\u0003\t\u000f\r=Q\u0001\"\u0001\u0004\u0012!A1QC\u0003!B\u0013\ti\fC\u0004\u0004\u0018\u0015!\ta!\u0007\t\u000f\rmQ\u0001\"\u0001\u0004\u001a!91QD\u0003\u0005\u0002\r}\u0001bBB\u0012\u000b\u0011\u00051Q\u0005\u0005\b\u0007S)A\u0011IB\u0016\u0011\u001d\u0019i$\u0002C!\u0007\u007fAqa!\u0012\u0006\t\u0003\u001a9\u0005C\u0004\u0004P\u0015!\te!\u0015\t\u000f\u0005\u0005R\u0001\"\u0001\u0004^!I1qP\u0003\u0012\u0002\u0013\u00051\u0011\u0011\u0005\n\u0007/+\u0011\u0013!C\u0001\u00073C\u0011b!(\u0006#\u0003%\taa(\t\u0013\r\rV!%A\u0005\u0002\r\u0015\u0006\"CBU\u000bE\u0005I\u0011ABV\u0011%\u0019y+BI\u0001\n\u0003\u0019\t\fC\u0005\u00046\u0016\t\n\u0011\"\u0001\u00048\"I11X\u0003\u0012\u0002\u0013\u00051Q\u0018\u0005\n\u0007\u0003,\u0011\u0013!C\u0001\u0007\u0007D\u0011ba2\u0006#\u0003%\ta!3\t\u0013\r5W!%A\u0005\u0002\r=\u0007\"CBj\u000bE\u0005I\u0011ABk\u0011%\u0019I.BI\u0001\n\u0003\u0019Y\u000eC\u0005\u0004`\u0016\t\n\u0011\"\u0001\u0004b\"I1Q]\u0003\u0012\u0002\u0013\u00051q\u001d\u0005\n\u0007W,\u0011\u0013!C\u0001\u0007[Dqa!=\u0006\t\u0003\u001a\u0019\u0010C\u0004\u0005\u0014\u0015!\t\u0005\"\u0006\u0002\r5\u0013u\u000e_\u00197\u0015\u0011\t\t!a\u0001\u0002\rML\'/Z;n\u0015\t\t)!A\u0002pe\u001e\u001c\u0001\u0001E\u0002\u0002\f\u0005i\u0011a \u0002\u0007\u001b\n{\u00070\r\u001c\u0014\u0007\u0005\t\t\u0002\u0005\u0003\u0002\u0014\u0005eQBAA\u000b\u0015\t\t9\"A\u0003tG\u0006d\u0017-\u0003\u0003\u0002\u001c\u0005U!AB!osJ+g-\u0001\u0004=S:LGO\u0010\u000b\u0003\u0003\u0013\tQ!\u00199qYf,\"%!\n\u0005\"\u0011\u0015B\u0011\u0006C\u0017\tc!)\u0004\"\u000f\u0005>\u0011\u0005CQ\tC%\t\u001b\"\t\u0006\"\u0016\u0005Z\u0011uCCIA\u0014\t?\"\t\u0007b\u0019\u0005f\u0011\u001dD\u0011\u000eC6\t[\"y\u0007\"\u001d\u0005t\u0011UDq\u000fC=\tw\"i\bE\u0012\u0002\f\u0015!y\u0002b\t\u0005(\u0011-Bq\u0006C\u001a\to!Y\u0004b\u0010\u0005D\u0011\u001dC1\nC(\t\'\"9\u0006b\u0017\u0016E\u0005-\u0012\u0011HA(\u0003/\ny&a\u001a\u0002p\u0005]\u0014qPAD\u0003\u001f\u000b9*a(\u0002(\u0006=\u0016qWA`\'\u0015)\u0011\u0011CA\u0017!\u0011\tY!a\f\n\u0007\u0005ErPA\u0005SK\u000e|\'\u000fZ*jO\u0006Aql\u0018<bYV,\u0017\u0007\u0005\u0003\u00028\u0005eB\u0002\u0001\u0003\b\u0003w)!\u0019AA\u001f\u0005\t!\u0016\'\u0005\u0003\u0002@\u0005\u0015\u0003\u0003BA\n\u0003\u0003JA!a\u0011\u0002\u0016\t9aj\u001c;iS:<\u0007\u0003BA\n\u0003\u000fJA!!\u0013\u0002\u0016\t\u0019\u0011I\\=\u0002\u0011}{f/\u00197vKJ\u0002B!a\u000e\u0002P\u00119\u0011\u0011K\u0003C\u0002\u0005u\"A\u0001+3\u0003!yvL^1mk\u0016\u001c\u0004\u0003BA\u001c\u0003/\"q!!\u0017\u0006\u0005\u0004\tiD\u0001\u0002Ug\u0005Aql\u0018<bYV,G\u0007\u0005\u0003\u00028\u0005}CaBA1\u000b\t\u0007\u0011Q\b\u0002\u0003)R\n\u0001bX0wC2,X-\u000e\t\u0005\u0003o\t9\u0007B\u0004\u0002j\u0015\u0011\r!!\u0010\u0003\u0005Q+\u0014\u0001C0`m\u0006dW/\u001a\u001c\u0011\t\u0005]\u0012q\u000e\u0003\b\u0003c*!\u0019AA\u001f\u0005\t!f\'\u0001\u0005`?Z\fG.^38!\u0011\t9$a\u001e\u0005\u000f\u0005eTA1\u0001\u0002>\t\u0011AkN\u0001\t?~3\u0018\r\\;fqA!\u0011qGA@\t\u001d\t\t)\u0002b\u0001\u0003{\u0011!\u0001\u0016\u001d\u0002\u0011}{f/\u00197vKf\u0002B!a\u000e\u0002\b\u00129\u0011\u0011R\u0003C\u0002\u0005u\"A\u0001+:\u0003%yvL^1mk\u0016\f\u0004\u0007\u0005\u0003\u00028\u0005=EaBAI\u000b\t\u0007\u0011Q\b\u0002\u0004)F\u0002\u0014!C0`m\u0006dW/Z\u00192!\u0011\t9$a&\u0005\u000f\u0005eUA1\u0001\u0002>\t\u0019A+M\u0019\u0002\u0013}{f/\u00197vKF\u0012\u0004\u0003BA\u001c\u0003?#q!!)\u0006\u0005\u0004\tiDA\u0002UcI\n\u0011bX0wC2,X-M\u001a\u0011\t\u0005]\u0012q\u0015\u0003\b\u0003S+!\u0019AA\u001f\u0005\r!\u0016gM\u0001\n?~3\u0018\r\\;fcQ\u0002B!a\u000e\u00020\u00129\u0011\u0011W\u0003C\u0002\u0005u\"a\u0001+2i\u0005Iql\u0018<bYV,\u0017\'\u000e\t\u0005\u0003o\t9\fB\u0004\u0002:\u0016\u0011\r!!\u0010\u0003\u0007Q\u000bT\'A\u0005`?Z\fG.^32mA!\u0011qGA`\t\u001d\t\t-\u0002b\u0001\u0003{\u00111\u0001V\u00197)\t\n)-a2\u0002J\u0006-\u0017QZAh\u0003#\f\u0019.!6\u0002X\u0006e\u00171\\Ao\u0003?\f\t/a9\u0002fB\u0019\u00131B\u0003\u00026\u00055\u0013QKA/\u0003K\ni\'!\u001e\u0002~\u0005\u0015\u0015QRAK\u0003;\u000b)+!,\u00026\u0006u\u0006bBA\u001a-\u0001\u0007\u0011Q\u0007\u0005\b\u0003\u00172\u0002\u0019AA\'\u0011\u001d\t\u0019F\u0006a\u0001\u0003+Bq!a\u0017\u0017\u0001\u0004\ti\u0006C\u0004\u0002dY\u0001\r!!\u001a\t\u000f\u0005-d\u00031\u0001\u0002n!9\u00111\u000f\fA\u0002\u0005U\u0004bBA>-\u0001\u0007\u0011Q\u0010\u0005\b\u0003\u00073\u0002\u0019AAC\u0011\u001d\tYI\u0006a\u0001\u0003\u001bCq!a%\u0017\u0001\u0004\t)\nC\u0004\u0002\u001cZ\u0001\r!!(\t\u000f\u0005\rf\u00031\u0001\u0002&\"9\u00111\u0016\fA\u0002\u00055\u0006bBAZ-\u0001\u0007\u0011Q\u0017\u0005\b\u0003w3\u0002\u0019AA_\u0003\u001dyf/\u00197vKF\naA^1mk\u0016\fTCAA\u001b\u0003%9W\r\u001e,bYV,\u0017\'\u0001\u0006wC2,X-M0%KF$B!a=\u0002v6\tQ\u0001C\u0004\u0002jj\u0001\r!!\u000e\u0002\u0013M,GOV1mk\u0016\fD\u0003BAz\u0003wDq!!;\u001c\u0001\u0004\t)$A\u0004`m\u0006dW/\u001a\u001a\u0002\rY\fG.^33+\t\ti%A\u0005hKR4\u0016\r\\;fe\u0005Qa/\u00197vKJzF%Z9\u0015\t\u0005M(\u0011\u0002\u0005\b\u0003\u007f|\u0002\u0019AA\'\u0003%\u0019X\r\u001e,bYV,\'\u0007\u0006\u0003\u0002t\n=\u0001bBA\u0000A\u0001\u0007\u0011QJ\u0001\b?Z\fG.^34\u0003\u00191\u0018\r\\;fgU\u0011\u0011QK\u0001\nO\u0016$h+\u00197vKN\n!B^1mk\u0016\u001ct\fJ3r)\u0011\t\u0019P!\b\t\u000f\tMA\u00051\u0001\u0002V\u0005I1/\u001a;WC2,Xm\r\u000b\u0005\u0003g\u0014\u0019\u0003C\u0004\u0003\u0014\u0015\u0002\r!!\u0016\u0002\u000f}3\u0018\r\\;fi\u00051a/\u00197vKR*\"!!\u0018\u0002\u0013\u001d,GOV1mk\u0016$\u0014A\u0003<bYV,Gg\u0018\u0013fcR!\u00111\u001fB\u0019\u0011\u001d\u00119#\u000ba\u0001\u0003;\n\u0011b]3u-\u0006dW/\u001a\u001b\u0015\t\u0005M(q\u0007\u0005\b\u0005OQ\u0003\u0019AA/\u0003\u001dyf/\u00197vKV\naA^1mk\u0016,TCAA3\u0003%9W\r\u001e,bYV,W\'\u0001\u0006wC2,X-N0%KF$B!a=\u0003F!9!1\b\u0018A\u0002\u0005\u0015\u0014!C:fiZ\u000bG.^36)\u0011\t\u0019Pa\u0013\t\u000f\tmr\u00061\u0001\u0002f\u00059qL^1mk\u00164\u0014A\u0002<bYV,g\'\u0006\u0002\u0002n\u0005Iq-\u001a;WC2,XMN\u0001\u000bm\u0006dW/\u001a\u001c`I\u0015\fH\u0003BAz\u00053BqAa\u00144\u0001\u0004\ti\'A\u0005tKR4\u0016\r\\;fmQ!\u00111\u001fB0\u0011\u001d\u0011y\u0005\u000ea\u0001\u0003[\nqa\u0018<bYV,w\'\u0001\u0004wC2,XmN\u000b\u0003\u0003k\n\u0011bZ3u-\u0006dW/Z\u001c\u0002\u0015Y\fG.^38?\u0012*\u0017\u000f\u0006\u0003\u0002t\n5\u0004b\u0002B2q\u0001\u0007\u0011QO\u0001\ng\u0016$h+\u00197vK^\"B!a=\u0003t!9!1M\u001dA\u0002\u0005U\u0014aB0wC2,X\rO\u0001\u0007m\u0006dW/\u001a\u001d\u0016\u0005\u0005u\u0014!C4fiZ\u000bG.^39\u0003)1\u0018\r\\;fq}#S-\u001d\u000b\u0005\u0003g\u0014\t\tC\u0004\u0003xu\u0002\r!! \u0002\u0013M,GOV1mk\u0016DD\u0003BAz\u0005\u000fCqAa\u001e?\u0001\u0004\ti(A\u0004`m\u0006dW/Z\u001d\u0002\rY\fG.^3:+\t\t))A\u0005hKR4\u0016\r\\;fs\u0005Qa/\u00197vKfzF%Z9\u0015\t\u0005M(Q\u0013\u0005\b\u0005\u0017\u0013\u0005\u0019AAC\u0003%\u0019X\r\u001e,bYV,\u0017\b\u0006\u0003\u0002t\nm\u0005b\u0002BF\u0007\u0002\u0007\u0011QQ\u0001\t?Z\fG.^32a\u00059a/\u00197vKF\u0002TCAAG\u0003)9W\r\u001e,bYV,\u0017\u0007M\u0001\fm\u0006dW/Z\u00191?\u0012*\u0017\u000f\u0006\u0003\u0002t\n%\u0006b\u0002BP\u000f\u0002\u0007\u0011QR\u0001\u000bg\u0016$h+\u00197vKF\u0002D\u0003BAz\u0005_CqAa(I\u0001\u0004\ti)\u0001\u0005`m\u0006dW/Z\u00192\u0003\u001d1\u0018\r\\;fcE*\"!!&\u0002\u0015\u001d,GOV1mk\u0016\f\u0014\'A\u0006wC2,X-M\u0019`I\u0015\fH\u0003BAz\u0005{CqAa-M\u0001\u0004\t)*\u0001\u0006tKR4\u0016\r\\;fcE\"B!a=\u0003D\"9!1W\'A\u0002\u0005U\u0015\u0001C0wC2,X-\r\u001a\u0002\u000fY\fG.^32eU\u0011\u0011QT\u0001\u000bO\u0016$h+\u00197vKF\u0012\u0014a\u0003<bYV,\u0017GM0%KF$B!a=\u0003R\"9!qY)A\u0002\u0005u\u0015AC:fiZ\u000bG.^32eQ!\u00111\u001fBl\u0011\u001d\u00119M\u0015a\u0001\u0003;\u000b\u0001b\u0018<bYV,\u0017gM\u0001\bm\u0006dW/Z\u00194+\t\t)+\u0001\u0006hKR4\u0016\r\\;fcM\n1B^1mk\u0016\f4g\u0018\u0013fcR!\u00111\u001fBs\u0011\u001d\u0011YN\u0016a\u0001\u0003K\u000b!b]3u-\u0006dW/Z\u00194)\u0011\t\u0019Pa;\t\u000f\tmw\u000b1\u0001\u0002&\u0006AqL^1mk\u0016\fD\'A\u0004wC2,X-\r\u001b\u0016\u0005\u00055\u0016AC4fiZ\u000bG.^32i\u0005Ya/\u00197vKF\"t\fJ3r)\u0011\t\u0019P!?\t\u000f\t=8\f1\u0001\u0002.\u0006Q1/\u001a;WC2,X-\r\u001b\u0015\t\u0005M(q \u0005\b\u0005_d\u0006\u0019AAW\u0003!yf/\u00197vKF*\u0014a\u0002<bYV,\u0017\'N\u000b\u0003\u0003k\u000b!bZ3u-\u0006dW/Z\u00196\u0003-1\u0018\r\\;fcUzF%Z9\u0015\t\u0005M8Q\u0002\u0005\b\u0007\u0007\u0001\u0007\u0019AA[\u0003)\u0019X\r\u001e,bYV,\u0017\'\u000e\u000b\u0005\u0003g\u001c\u0019\u0002C\u0004\u0004\u0004\u0005\u0004\r!!.\u0002\u0011}3\u0018\r\\;fcY\nqA^1mk\u0016\fd\'\u0006\u0002\u0002>\u0006Qq-\u001a;WC2,X-\r\u001c\u0002\u0017Y\fG.^32m}#S-\u001d\u000b\u0005\u0003g\u001c\t\u0003C\u0004\u0004\u0018\u0015\u0004\r!!0\u0002\u0015M,GOV1mk\u0016\fd\u0007\u0006\u0003\u0002t\u000e\u001d\u0002bBB\fM\u0002\u0007\u0011QX\u0001\ti>\u001cFO]5oOR\u00111Q\u0006\t\u0005\u0007_\u0019I$\u0004\u0002\u00042)!11GB\u001b\u0003\u0011a\u0017M\\4\u000b\u0005\r]\u0012\u0001\u00026bm\u0006LAaa\u000f\u00042\t11\u000b\u001e:j]\u001e\faa\u001d;sS:<WCAB!!\u0011\tYaa\u0011\n\u0007\rmr0\u0001\u0005iCND7i\u001c3f)\t\u0019I\u0005\u0005\u0003\u0002\u0014\r-\u0013\u0002BB\'\u0003+\u00111!\u00138u\u0003\u0019)\u0017/^1mgR!11KB-!\u0011\t\u0019b!\u0016\n\t\r]\u0013Q\u0003\u0002\b\u0005>|G.Z1o\u0011\u001d\u0019YF\u001ba\u0001\u0003\u000b\n\u0011a\u001c\u000b#\u0003\u000b\u001cyf!\u0019\u0004d\r\u00154qMB5\u0007W\u001aiga\u001c\u0004r\rM4QOB<\u0007s\u001aYh! \t\u0013\u0005%8\u000e%AA\u0002\u0005U\u0002\"CA\u0000WB\u0005\t\u0019AA\'\u0011%\u0011\u0019b\u001bI\u0001\u0002\u0004\t)\u0006C\u0005\u0003(-\u0004\n\u00111\u0001\u0002^!I!1H6\u0011\u0002\u0003\u0007\u0011Q\r\u0005\n\u0005\u001fZ\u0007\u0013!a\u0001\u0003[B\u0011Ba\u0019l!\u0003\u0005\r!!\u001e\t\u0013\t]4\u000e%AA\u0002\u0005u\u0004\"\u0003BFWB\u0005\t\u0019AAC\u0011%\u0011yj\u001bI\u0001\u0002\u0004\ti\tC\u0005\u00034.\u0004\n\u00111\u0001\u0002\u0016\"I!qY6\u0011\u0002\u0003\u0007\u0011Q\u0014\u0005\n\u00057\\\u0007\u0013!a\u0001\u0003KC\u0011Ba<l!\u0003\u0005\r!!,\t\u0013\r\r1\u000e%AA\u0002\u0005U\u0006\"CB\fWB\u0005\t\u0019AA_\u0003=\t\u0007\u000f\u001d7zI\u0011,g-Y;mi\u0012\nTCABBU\u0011\t)d!\",\u0005\r\u001d\u0005\u0003BBE\u0007\'k!aa#\u000b\t\r55qR\u0001\nk:\u001c\u0007.Z2lK\u0012TAa!%\u0002\u0016\u0005Q\u0011M\u001c8pi\u0006$\u0018n\u001c8\n\t\rU51\u0012\u0002\u0012k:\u001c\u0007.Z2lK\u00124\u0016M]5b]\u000e,\u0017aD1qa2LH\u0005Z3gCVdG\u000f\n\u001a\u0016\u0005\rm%\u0006BA\'\u0007\u000b\u000bq\"\u00199qYf$C-\u001a4bk2$HeM\u000b\u0003\u0007CSC!!\u0016\u0004\u0006\u0006y\u0011\r\u001d9ms\u0012\"WMZ1vYR$C\'\u0006\u0002\u0004(*\"\u0011QLBC\u0003=\t\u0007\u000f\u001d7zI\u0011,g-Y;mi\u0012*TCABWU\u0011\t)g!\"\u0002\u001f\u0005\u0004\b\u000f\\=%I\u00164\u0017-\u001e7uIY*\"aa-+\t\u000554QQ\u0001\u0010CB\u0004H.\u001f\u0013eK\u001a\fW\u000f\u001c;%oU\u00111\u0011\u0018\u0016\u0005\u0003k\u001a))A\bbaBd\u0017\u0010\n3fM\u0006,H\u000e\u001e\u00139+\t\u0019yL\u000b\u0003\u0002~\r\u0015\u0015aD1qa2LH\u0005Z3gCVdG\u000fJ\u001d\u0016\u0005\r\u0015\'\u0006BAC\u0007\u000b\u000b\u0001#\u00199qYf$C-\u001a4bk2$H%\r\u0019\u0016\u0005\r-\'\u0006BAG\u0007\u000b\u000b\u0001#\u00199qYf$C-\u001a4bk2$H%M\u0019\u0016\u0005\rE\'\u0006BAK\u0007\u000b\u000b\u0001#\u00199qYf$C-\u001a4bk2$H%\r\u001a\u0016\u0005\r]\'\u0006BAO\u0007\u000b\u000b\u0001#\u00199qYf$C-\u001a4bk2$H%M\u001a\u0016\u0005\ru\'\u0006BAS\u0007\u000b\u000b\u0001#\u00199qYf$C-\u001a4bk2$H%\r\u001b\u0016\u0005\r\r(\u0006BAW\u0007\u000b\u000b\u0001#\u00199qYf$C-\u001a4bk2$H%M\u001b\u0016\u0005\r%(\u0006BA[\u0007\u000b\u000b\u0001#\u00199qYf$C-\u001a4bk2$H%\r\u001c\u0016\u0005\r=(\u0006BA_\u0007\u000b\u000b\u0001\u0002J2p]R,g\u000e^\u000b\u0003\u0007k\u0004baa>\u0005\b\u00115a\u0002BB}\t\u0007qAaa?\u0005\u00025\u00111Q \u0006\u0005\u0007\u007f\f9!\u0001\u0004=e>|GOP\u0005\u0003\u0003/IA\u0001\"\u0002\u0002\u0016\u00059\u0001/Y2lC\u001e,\u0017\u0002\u0002C\u0005\t\u0017\u00111aU3r\u0015\u0011!)!!\u0006\u0011\u0011\u0005MAqBB\u0017\u0003\u000bJA\u0001\"\u0005\u0002\u0016\t1A+\u001e9mKJ\na\u0001J2m_:,WCAAcQ\r)A\u0011\u0004\t\u0005\u0003\u0017!Y\"C\u0002\u0005\u001e}\u0014aA]3d_J$\u0007\u0003BA\u001c\tC!q!a\u000f\u0004\u0005\u0004\ti\u0004\u0005\u0003\u00028\u0011\u0015BaBA)\u0007\t\u0007\u0011Q\b\t\u0005\u0003o!I\u0003B\u0004\u0002Z\r\u0011\r!!\u0010\u0011\t\u0005]BQ\u0006\u0003\b\u0003C\u001a!\u0019AA\u001f!\u0011\t9\u0004\"\r\u0005\u000f\u0005%4A1\u0001\u0002>A!\u0011q\u0007C\u001b\t\u001d\t\th\u0001b\u0001\u0003{\u0001B!a\u000e\u0005:\u00119\u0011\u0011P\u0002C\u0002\u0005u\u0002\u0003BA\u001c\t{!q!!!\u0004\u0005\u0004\ti\u0004\u0005\u0003\u00028\u0011\u0005CaBAE\u0007\t\u0007\u0011Q\b\t\u0005\u0003o!)\u0005B\u0004\u0002\u0012\u000e\u0011\r!!\u0010\u0011\t\u0005]B\u0011\n\u0003\b\u00033\u001b!\u0019AA\u001f!\u0011\t9\u0004\"\u0014\u0005\u000f\u0005\u00056A1\u0001\u0002>A!\u0011q\u0007C)\t\u001d\tIk\u0001b\u0001\u0003{\u0001B!a\u000e\u0005V\u00119\u0011\u0011W\u0002C\u0002\u0005u\u0002\u0003BA\u001c\t3\"q!!/\u0004\u0005\u0004\ti\u0004\u0005\u0003\u00028\u0011uCaBAa\u0007\t\u0007\u0011Q\b\u0005\b\u0003S\u001c\u0001\u0019\u0001C\u0010\u0011\u001d\typ\u0001a\u0001\tGAqAa\u0005\u0004\u0001\u0004!9\u0003C\u0004\u0003(\r\u0001\r\u0001b\u000b\t\u000f\tm2\u00011\u0001\u00050!9!qJ\u0002A\u0002\u0011M\u0002b\u0002B2\u0007\u0001\u0007Aq\u0007\u0005\b\u0005o\u001a\u0001\u0019\u0001C\u001e\u0011\u001d\u0011Yi\u0001a\u0001\t\u007fAqAa(\u0004\u0001\u0004!\u0019\u0005C\u0004\u00034\u000e\u0001\r\u0001b\u0012\t\u000f\t\u001d7\u00011\u0001\u0005L!9!1\\\u0002A\u0002\u0011=\u0003b\u0002Bx\u0007\u0001\u0007A1\u000b\u0005\b\u0007\u0007\u0019\u0001\u0019\u0001C,\u0011\u001d\u00199b\u0001a\u0001\t7\nq!\u001e8baBd\u00170\u0006\u0012\u0005\u0004\u0012MEq\u0013CN\t?#\u0019\u000bb*\u0005,\u0012=F1\u0017C\\\tw#y\fb1\u0005H\u0012-Gq\u001a\u000b\u0005\t\u000b#\t\u000e\u0005\u0004\u0002\u0014\u0011\u001dE1R\u0005\u0005\t\u0013\u000b)B\u0001\u0003T_6,\u0007\u0003JA\n\t\u001b#\t\n\"&\u0005\u001a\u0012uE\u0011\u0015CS\tS#i\u000b\"-\u00056\u0012eFQ\u0018Ca\t\u000b$I\r\"4\n\t\u0011=\u0015Q\u0003\u0002\b)V\u0004H.Z\u00197!\u0011\t9\u0004b%\u0005\u000f\u0005mBA1\u0001\u0002>A!\u0011q\u0007CL\t\u001d\t\t\u0006\u0002b\u0001\u0003{\u0001B!a\u000e\u0005\u001c\u00129\u0011\u0011\f\u0003C\u0002\u0005u\u0002\u0003BA\u001c\t?#q!!\u0019\u0005\u0005\u0004\ti\u0004\u0005\u0003\u00028\u0011\rFaBA5\t\t\u0007\u0011Q\b\t\u0005\u0003o!9\u000bB\u0004\u0002r\u0011\u0011\r!!\u0010\u0011\t\u0005]B1\u0016\u0003\b\u0003s\"!\u0019AA\u001f!\u0011\t9\u0004b,\u0005\u000f\u0005\u0005EA1\u0001\u0002>A!\u0011q\u0007CZ\t\u001d\tI\t\u0002b\u0001\u0003{\u0001B!a\u000e\u00058\u00129\u0011\u0011\u0013\u0003C\u0002\u0005u\u0002\u0003BA\u001c\tw#q!!\'\u0005\u0005\u0004\ti\u0004\u0005\u0003\u00028\u0011}FaBAQ\t\t\u0007\u0011Q\b\t\u0005\u0003o!\u0019\rB\u0004\u0002*\u0012\u0011\r!!\u0010\u0011\t\u0005]Bq\u0019\u0003\b\u0003c#!\u0019AA\u001f!\u0011\t9\u0004b3\u0005\u000f\u0005eFA1\u0001\u0002>A!\u0011q\u0007Ch\t\u001d\t\t\r\u0002b\u0001\u0003{Aqaa\u0017\u0005\u0001\u0004!\u0019\u000eE\u0012\u0002\f\u0015!\t\n\"&\u0005\u001a\u0012uE\u0011\u0015CS\tS#i\u000b\"-\u00056\u0012eFQ\u0018Ca\t\u000b$I\r\"4
   #12 = Utf8               _value1
   #13 = Utf8               Ljava/lang/Object;
   #14 = Utf8               TT1;
   #15 = Utf8               _value2
   #16 = Utf8               TT2;
   #17 = Utf8               _value3
   #18 = Utf8               TT3;
   #19 = Utf8               _value4
   #20 = Utf8               TT4;
   #21 = Utf8               _value5
   #22 = Utf8               TT5;
   #23 = Utf8               _value6
   #24 = Utf8               TT6;
   #25 = Utf8               _value7
   #26 = Utf8               TT7;
   #27 = Utf8               _value8
   #28 = Utf8               TT8;
   #29 = Utf8               _value9
   #30 = Utf8               TT9;
   #31 = Utf8               _value10
   #32 = Utf8               TT10;
   #33 = Utf8               _value11
   #34 = Utf8               TT11;
   #35 = Utf8               _value12
   #36 = Utf8               TT12;
   #37 = Utf8               _value13
   #38 = Utf8               TT13;
   #39 = Utf8               _value14
   #40 = Utf8               TT14;
   #41 = Utf8               _value15
   #42 = Utf8               TT15;
   #43 = Utf8               _value16
   #44 = Utf8               TT16;
   #45 = Utf8               org$sireum$RecordSig$$$isOwned
   #46 = Utf8               Z
   #47 = Utf8               unapply
   #48 = Utf8               (Lorg/sireum/MBox16;)Lscala/Some;
   #49 = Utf8               <T1:Ljava/lang/Object;T2:Ljava/lang/Object;T3:Ljava/lang/Object;T4:Ljava/lang/Object;T5:Ljava/lang/Object;T6:Ljava/lang/Object;T7:Ljava/lang/Object;T8:Ljava/lang/Object;T9:Ljava/lang/Object;T10:Ljava/lang/Object;T11:Ljava/lang/Object;T12:Ljava/lang/Object;T13:Ljava/lang/Object;T14:Ljava/lang/Object;T15:Ljava/lang/Object;T16:Ljava/lang/Object;>(Lorg/sireum/MBox16<TT1;TT2;TT3;TT4;TT5;TT6;TT7;TT8;TT9;TT10;TT11;TT12;TT13;TT14;TT15;TT16;>;)Lscala/Some<Lscala/Tuple16<TT1;TT2;TT3;TT4;TT5;TT6;TT7;TT8;TT9;TT10;TT11;TT12;TT13;TT14;TT15;TT16;>;>;
   #50 = Utf8               o
   #51 = Utf8               org/sireum/MBox16$
   #52 = Class              #51           // org/sireum/MBox16$
   #53 = Utf8               MODULE$
   #54 = Utf8               Lorg/sireum/MBox16$;
   #55 = NameAndType        #53:#54       // MODULE$:Lorg/sireum/MBox16$;
   #56 = Fieldref           #52.#55       // org/sireum/MBox16$.MODULE$:Lorg/sireum/MBox16$;
   #57 = NameAndType        #47:#48       // unapply:(Lorg/sireum/MBox16;)Lscala/Some;
   #58 = Methodref          #52.#57       // org/sireum/MBox16$.unapply:(Lorg/sireum/MBox16;)Lscala/Some;
   #59 = Utf8               Lorg/sireum/MBox16;
   #60 = Utf8               $owned
   #61 = Utf8               ()Z
   #62 = Utf8               $owned$
   #63 = Utf8               (Lorg/sireum/RecordSig;)Z
   #64 = NameAndType        #62:#63       // $owned$:(Lorg/sireum/RecordSig;)Z
   #65 = InterfaceMethodref #7.#64        // org/sireum/RecordSig.$owned$:(Lorg/sireum/RecordSig;)Z
   #66 = Utf8               this
   #67 = Utf8               $owned_$eq
   #68 = Utf8               (Z)Lorg/sireum/RecordSig;
   #69 = Utf8               b
   #70 = Utf8               $owned_$eq$
   #71 = Utf8               (Lorg/sireum/RecordSig;Z)Lorg/sireum/RecordSig;
   #72 = NameAndType        #70:#71       // $owned_$eq$:(Lorg/sireum/RecordSig;Z)Lorg/sireum/RecordSig;
   #73 = InterfaceMethodref #7.#72        // org/sireum/RecordSig.$owned_$eq$:(Lorg/sireum/RecordSig;Z)Lorg/sireum/RecordSig;
   #74 = Utf8               hash
   #75 = Utf8               ()Lorg/sireum/Z;
   #76 = Utf8               hash$
   #77 = Utf8               (Lorg/sireum/RecordSig;)Lorg/sireum/Z;
   #78 = NameAndType        #76:#77       // hash$:(Lorg/sireum/RecordSig;)Lorg/sireum/Z;
   #79 = InterfaceMethodref #7.#78        // org/sireum/RecordSig.hash$:(Lorg/sireum/RecordSig;)Lorg/sireum/Z;
   #80 = Utf8               $cannotMixImmutableAndMutable
   #81 = Utf8               ()Lscala/runtime/Nothing$;
   #82 = Utf8               org/sireum/Mutable
   #83 = Class              #82           // org/sireum/Mutable
   #84 = Utf8               $cannotMixImmutableAndMutable$
   #85 = Utf8               (Lorg/sireum/Mutable;)Lscala/runtime/Nothing$;
   #86 = NameAndType        #84:#85       // $cannotMixImmutableAndMutable$:(Lorg/sireum/Mutable;)Lscala/runtime/Nothing$;
   #87 = InterfaceMethodref #83.#86       // org/sireum/Mutable.$cannotMixImmutableAndMutable$:(Lorg/sireum/Mutable;)Lscala/runtime/Nothing$;
   #88 = Utf8               $hasEquals
   #89 = Utf8               $hasEquals$
   #90 = Utf8               (Lorg/sireum/Mutable;)Z
   #91 = NameAndType        #89:#90       // $hasEquals$:(Lorg/sireum/Mutable;)Z
   #92 = InterfaceMethodref #83.#91       // org/sireum/Mutable.$hasEquals$:(Lorg/sireum/Mutable;)Z
   #93 = Utf8               $hasString
   #94 = Utf8               $hasString$
   #95 = NameAndType        #94:#90       // $hasString$:(Lorg/sireum/Mutable;)Z
   #96 = InterfaceMethodref #83.#95       // org/sireum/Mutable.$hasString$:(Lorg/sireum/Mutable;)Z
   #97 = NameAndType        #45:#46       // org$sireum$RecordSig$$$isOwned:Z
   #98 = Fieldref           #2.#97        // org/sireum/MBox16.org$sireum$RecordSig$$$isOwned:Z
   #99 = Utf8               org$sireum$RecordSig$$$isOwned_$eq
  #100 = Utf8               (Z)V
  #101 = Utf8               x$1
  #102 = Utf8               value1
  #103 = Utf8               ()Ljava/lang/Object;
  #104 = Utf8               ()TT1;
  #105 = NameAndType        #12:#13       // _value1:Ljava/lang/Object;
  #106 = Fieldref           #2.#105       // org/sireum/MBox16._value1:Ljava/lang/Object;
  #107 = Utf8               getValue1
  #108 = Utf8               value1_$eq
  #109 = Utf8               (Ljava/lang/Object;)Lorg/sireum/MBox16;
  #110 = Utf8               (TT1;)Lorg/sireum/MBox16<TT1;TT2;TT3;TT4;TT5;TT6;TT7;TT8;TT9;TT10;TT11;TT12;TT13;TT14;TT15;TT16;>;
  #111 = Utf8               setValue1
  #112 = Utf8               value2
  #113 = Utf8               ()TT2;
  #114 = NameAndType        #15:#13       // _value2:Ljava/lang/Object;
  #115 = Fieldref           #2.#114       // org/sireum/MBox16._value2:Ljava/lang/Object;
  #116 = Utf8               getValue2
  #117 = Utf8               value2_$eq
  #118 = Utf8               (TT2;)Lorg/sireum/MBox16<TT1;TT2;TT3;TT4;TT5;TT6;TT7;TT8;TT9;TT10;TT11;TT12;TT13;TT14;TT15;TT16;>;
  #119 = Utf8               setValue2
  #120 = Utf8               value3
  #121 = Utf8               ()TT3;
  #122 = NameAndType        #17:#13       // _value3:Ljava/lang/Object;
  #123 = Fieldref           #2.#122       // org/sireum/MBox16._value3:Ljava/lang/Object;
  #124 = Utf8               getValue3
  #125 = Utf8               value3_$eq
  #126 = Utf8               (TT3;)Lorg/sireum/MBox16<TT1;TT2;TT3;TT4;TT5;TT6;TT7;TT8;TT9;TT10;TT11;TT12;TT13;TT14;TT15;TT16;>;
  #127 = Utf8               setValue3
  #128 = Utf8               value4
  #129 = Utf8               ()TT4;
  #130 = NameAndType        #19:#13       // _value4:Ljava/lang/Object;
  #131 = Fieldref           #2.#130       // org/sireum/MBox16._value4:Ljava/lang/Object;
  #132 = Utf8               getValue4
  #133 = Utf8               value4_$eq
  #134 = Utf8               (TT4;)Lorg/sireum/MBox16<TT1;TT2;TT3;TT4;TT5;TT6;TT7;TT8;TT9;TT10;TT11;TT12;TT13;TT14;TT15;TT16;>;
  #135 = Utf8               setValue4
  #136 = Utf8               value5
  #137 = Utf8               ()TT5;
  #138 = NameAndType        #21:#13       // _value5:Ljava/lang/Object;
  #139 = Fieldref           #2.#138       // org/sireum/MBox16._value5:Ljava/lang/Object;
  #140 = Utf8               getValue5
  #141 = Utf8               value5_$eq
  #142 = Utf8               (TT5;)Lorg/sireum/MBox16<TT1;TT2;TT3;TT4;TT5;TT6;TT7;TT8;TT9;TT10;TT11;TT12;TT13;TT14;TT15;TT16;>;
  #143 = Utf8               setValue5
  #144 = Utf8               value6
  #145 = Utf8               ()TT6;
  #146 = NameAndType        #23:#13       // _value6:Ljava/lang/Object;
  #147 = Fieldref           #2.#146       // org/sireum/MBox16._value6:Ljava/lang/Object;
  #148 = Utf8               getValue6
  #149 = Utf8               value6_$eq
  #150 = Utf8               (TT6;)Lorg/sireum/MBox16<TT1;TT2;TT3;TT4;TT5;TT6;TT7;TT8;TT9;TT10;TT11;TT12;TT13;TT14;TT15;TT16;>;
  #151 = Utf8               setValue6
  #152 = Utf8               value7
  #153 = Utf8               ()TT7;
  #154 = NameAndType        #25:#13       // _value7:Ljava/lang/Object;
  #155 = Fieldref           #2.#154       // org/sireum/MBox16._value7:Ljava/lang/Object;
  #156 = Utf8               getValue7
  #157 = Utf8               value7_$eq
  #158 = Utf8               (TT7;)Lorg/sireum/MBox16<TT1;TT2;TT3;TT4;TT5;TT6;TT7;TT8;TT9;TT10;TT11;TT12;TT13;TT14;TT15;TT16;>;
  #159 = Utf8               setValue7
  #160 = Utf8               value8
  #161 = Utf8               ()TT8;
  #162 = NameAndType        #27:#13       // _value8:Ljava/lang/Object;
  #163 = Fieldref           #2.#162       // org/sireum/MBox16._value8:Ljava/lang/Object;
  #164 = Utf8               getValue8
  #165 = Utf8               value8_$eq
  #166 = Utf8               (TT8;)Lorg/sireum/MBox16<TT1;TT2;TT3;TT4;TT5;TT6;TT7;TT8;TT9;TT10;TT11;TT12;TT13;TT14;TT15;TT16;>;
  #167 = Utf8               setValue8
  #168 = Utf8               value9
  #169 = Utf8               ()TT9;
  #170 = NameAndType        #29:#13       // _value9:Ljava/lang/Object;
  #171 = Fieldref           #2.#170       // org/sireum/MBox16._value9:Ljava/lang/Object;
  #172 = Utf8               getValue9
  #173 = Utf8               value9_$eq
  #174 = Utf8               (TT9;)Lorg/sireum/MBox16<TT1;TT2;TT3;TT4;TT5;TT6;TT7;TT8;TT9;TT10;TT11;TT12;TT13;TT14;TT15;TT16;>;
  #175 = Utf8               setValue9
  #176 = Utf8               value10
  #177 = Utf8               ()TT10;
  #178 = NameAndType        #31:#13       // _value10:Ljava/lang/Object;
  #179 = Fieldref           #2.#178       // org/sireum/MBox16._value10:Ljava/lang/Object;
  #180 = Utf8               getValue10
  #181 = Utf8               value10_$eq
  #182 = Utf8               (TT10;)Lorg/sireum/MBox16<TT1;TT2;TT3;TT4;TT5;TT6;TT7;TT8;TT9;TT10;TT11;TT12;TT13;TT14;TT15;TT16;>;
  #183 = Utf8               setValue10
  #184 = Utf8               value11
  #185 = Utf8               ()TT11;
  #186 = NameAndType        #33:#13       // _value11:Ljava/lang/Object;
  #187 = Fieldref           #2.#186       // org/sireum/MBox16._value11:Ljava/lang/Object;
  #188 = Utf8               getValue11
  #189 = Utf8               value11_$eq
  #190 = Utf8               (TT11;)Lorg/sireum/MBox16<TT1;TT2;TT3;TT4;TT5;TT6;TT7;TT8;TT9;TT10;TT11;TT12;TT13;TT14;TT15;TT16;>;
  #191 = Utf8               setValue11
  #192 = Utf8               value12
  #193 = Utf8               ()TT12;
  #194 = NameAndType        #35:#13       // _value12:Ljava/lang/Object;
  #195 = Fieldref           #2.#194       // org/sireum/MBox16._value12:Ljava/lang/Object;
  #196 = Utf8               getValue12
  #197 = Utf8               value12_$eq
  #198 = Utf8               (TT12;)Lorg/sireum/MBox16<TT1;TT2;TT3;TT4;TT5;TT6;TT7;TT8;TT9;TT10;TT11;TT12;TT13;TT14;TT15;TT16;>;
  #199 = Utf8               setValue12
  #200 = Utf8               value13
  #201 = Utf8               ()TT13;
  #202 = NameAndType        #37:#13       // _value13:Ljava/lang/Object;
  #203 = Fieldref           #2.#202       // org/sireum/MBox16._value13:Ljava/lang/Object;
  #204 = Utf8               getValue13
  #205 = Utf8               value13_$eq
  #206 = Utf8               (TT13;)Lorg/sireum/MBox16<TT1;TT2;TT3;TT4;TT5;TT6;TT7;TT8;TT9;TT10;TT11;TT12;TT13;TT14;TT15;TT16;>;
  #207 = Utf8               setValue13
  #208 = Utf8               value14
  #209 = Utf8               ()TT14;
  #210 = NameAndType        #39:#13       // _value14:Ljava/lang/Object;
  #211 = Fieldref           #2.#210       // org/sireum/MBox16._value14:Ljava/lang/Object;
  #212 = Utf8               getValue14
  #213 = Utf8               value14_$eq
  #214 = Utf8               (TT14;)Lorg/sireum/MBox16<TT1;TT2;TT3;TT4;TT5;TT6;TT7;TT8;TT9;TT10;TT11;TT12;TT13;TT14;TT15;TT16;>;
  #215 = Utf8               setValue14
  #216 = Utf8               value15
  #217 = Utf8               ()TT15;
  #218 = NameAndType        #41:#13       // _value15:Ljava/lang/Object;
  #219 = Fieldref           #2.#218       // org/sireum/MBox16._value15:Ljava/lang/Object;
  #220 = Utf8               getValue15
  #221 = Utf8               value15_$eq
  #222 = Utf8               (TT15;)Lorg/sireum/MBox16<TT1;TT2;TT3;TT4;TT5;TT6;TT7;TT8;TT9;TT10;TT11;TT12;TT13;TT14;TT15;TT16;>;
  #223 = Utf8               setValue15
  #224 = Utf8               value16
  #225 = Utf8               ()TT16;
  #226 = NameAndType        #43:#13       // _value16:Ljava/lang/Object;
  #227 = Fieldref           #2.#226       // org/sireum/MBox16._value16:Ljava/lang/Object;
  #228 = Utf8               getValue16
  #229 = Utf8               value16_$eq
  #230 = Utf8               (TT16;)Lorg/sireum/MBox16<TT1;TT2;TT3;TT4;TT5;TT6;TT7;TT8;TT9;TT10;TT11;TT12;TT13;TT14;TT15;TT16;>;
  #231 = Utf8               setValue16
  #232 = Utf8               toString
  #233 = Utf8               ()Ljava/lang/String;
  #234 = NameAndType        #93:#61       // $hasString:()Z
  #235 = Methodref          #2.#234       // org/sireum/MBox16.$hasString:()Z
  #236 = Utf8               string$
  #237 = Utf8               (Lorg/sireum/RecordSig;)Ljava/lang/String;
  #238 = NameAndType        #236:#237     // string$:(Lorg/sireum/RecordSig;)Ljava/lang/String;
  #239 = InterfaceMethodref #7.#238       // org/sireum/RecordSig.string$:(Lorg/sireum/RecordSig;)Ljava/lang/String;
  #240 = Utf8               java/lang/StringBuilder
  #241 = Class              #240          // java/lang/StringBuilder
  #242 = Utf8               <init>
  #243 = Utf8               ()V
  #244 = NameAndType        #242:#243     // "<init>":()V
  #245 = Methodref          #241.#244     // java/lang/StringBuilder."<init>":()V
  #246 = Utf8               MBox16
  #247 = String             #246          // MBox16
  #248 = Utf8               append
  #249 = Utf8               (Ljava/lang/String;)Ljava/lang/StringBuilder;
  #250 = NameAndType        #248:#249     // append:(Ljava/lang/String;)Ljava/lang/StringBuilder;
  #251 = Methodref          #241.#250     // java/lang/StringBuilder.append:(Ljava/lang/String;)Ljava/lang/StringBuilder;
  #252 = Utf8               (C)Ljava/lang/StringBuilder;
  #253 = NameAndType        #248:#252     // append:(C)Ljava/lang/StringBuilder;
  #254 = Methodref          #241.#253     // java/lang/StringBuilder.append:(C)Ljava/lang/StringBuilder;
  #255 = Utf8               org/sireum/String$
  #256 = Class              #255          // org/sireum/String$
  #257 = Utf8               Lorg/sireum/String$;
  #258 = NameAndType        #53:#257      // MODULE$:Lorg/sireum/String$;
  #259 = Fieldref           #256.#258     // org/sireum/String$.MODULE$:Lorg/sireum/String$;
  #260 = NameAndType        #102:#103     // value1:()Ljava/lang/Object;
  #261 = Methodref          #2.#260       // org/sireum/MBox16.value1:()Ljava/lang/Object;
  #262 = Utf8               escape
  #263 = Utf8               (Ljava/lang/Object;)Ljava/lang/String;
  #264 = NameAndType        #262:#263     // escape:(Ljava/lang/Object;)Ljava/lang/String;
  #265 = Methodref          #256.#264     // org/sireum/String$.escape:(Ljava/lang/Object;)Ljava/lang/String;
  #266 = Utf8               ,
  #267 = String             #266          // ,
  #268 = NameAndType        #112:#103     // value2:()Ljava/lang/Object;
  #269 = Methodref          #2.#268       // org/sireum/MBox16.value2:()Ljava/lang/Object;
  #270 = NameAndType        #120:#103     // value3:()Ljava/lang/Object;
  #271 = Methodref          #2.#270       // org/sireum/MBox16.value3:()Ljava/lang/Object;
  #272 = NameAndType        #128:#103     // value4:()Ljava/lang/Object;
  #273 = Methodref          #2.#272       // org/sireum/MBox16.value4:()Ljava/lang/Object;
  #274 = NameAndType        #136:#103     // value5:()Ljava/lang/Object;
  #275 = Methodref          #2.#274       // org/sireum/MBox16.value5:()Ljava/lang/Object;
  #276 = NameAndType        #144:#103     // value6:()Ljava/lang/Object;
  #277 = Methodref          #2.#276       // org/sireum/MBox16.value6:()Ljava/lang/Object;
  #278 = NameAndType        #152:#103     // value7:()Ljava/lang/Object;
  #279 = Methodref          #2.#278       // org/sireum/MBox16.value7:()Ljava/lang/Object;
  #280 = NameAndType        #160:#103     // value8:()Ljava/lang/Object;
  #281 = Methodref          #2.#280       // org/sireum/MBox16.value8:()Ljava/lang/Object;
  #282 = NameAndType        #168:#103     // value9:()Ljava/lang/Object;
  #283 = Methodref          #2.#282       // org/sireum/MBox16.value9:()Ljava/lang/Object;
  #284 = NameAndType        #176:#103     // value10:()Ljava/lang/Object;
  #285 = Methodref          #2.#284       // org/sireum/MBox16.value10:()Ljava/lang/Object;
  #286 = NameAndType        #184:#103     // value11:()Ljava/lang/Object;
  #287 = Methodref          #2.#286       // org/sireum/MBox16.value11:()Ljava/lang/Object;
  #288 = NameAndType        #192:#103     // value12:()Ljava/lang/Object;
  #289 = Methodref          #2.#288       // org/sireum/MBox16.value12:()Ljava/lang/Object;
  #290 = NameAndType        #200:#103     // value13:()Ljava/lang/Object;
  #291 = Methodref          #2.#290       // org/sireum/MBox16.value13:()Ljava/lang/Object;
  #292 = NameAndType        #208:#103     // value14:()Ljava/lang/Object;
  #293 = Methodref          #2.#292       // org/sireum/MBox16.value14:()Ljava/lang/Object;
  #294 = NameAndType        #216:#103     // value15:()Ljava/lang/Object;
  #295 = Methodref          #2.#294       // org/sireum/MBox16.value15:()Ljava/lang/Object;
  #296 = NameAndType        #224:#103     // value16:()Ljava/lang/Object;
  #297 = Methodref          #2.#296       // org/sireum/MBox16.value16:()Ljava/lang/Object;
  #298 = NameAndType        #232:#233     // toString:()Ljava/lang/String;
  #299 = Methodref          #241.#298     // java/lang/StringBuilder.toString:()Ljava/lang/String;
  #300 = Utf8               sb
  #301 = Utf8               Ljava/lang/StringBuilder;
  #302 = Utf8               java/lang/String
  #303 = Class              #302          // java/lang/String
  #304 = Utf8               string
  #305 = Methodref          #2.#298       // org/sireum/MBox16.toString:()Ljava/lang/String;
  #306 = Utf8               apply
  #307 = Utf8               (Ljava/lang/String;)Ljava/lang/String;
  #308 = NameAndType        #306:#307     // apply:(Ljava/lang/String;)Ljava/lang/String;
  #309 = Methodref          #256.#308     // org/sireum/String$.apply:(Ljava/lang/String;)Ljava/lang/String;
  #310 = Utf8               hashCode
  #311 = Utf8               ()I
  #312 = NameAndType        #88:#61       // $hasEquals:()Z
  #313 = Methodref          #2.#312       // org/sireum/MBox16.$hasEquals:()Z
  #314 = NameAndType        #310:#311     // hashCode:()I
  #315 = Methodref          #5.#314       // java/lang/Object.hashCode:()I
  #316 = Utf8               scala/package$
  #317 = Class              #316          // scala/package$
  #318 = Utf8               Lscala/package$;
  #319 = NameAndType        #53:#318      // MODULE$:Lscala/package$;
  #320 = Fieldref           #317.#319     // scala/package$.MODULE$:Lscala/package$;
  #321 = Utf8               Seq
  #322 = Utf8               ()Lscala/collection/immutable/Seq$;
  #323 = NameAndType        #321:#322     // Seq:()Lscala/collection/immutable/Seq$;
  #324 = Methodref          #317.#323     // scala/package$.Seq:()Lscala/collection/immutable/Seq$;
  #325 = Utf8               scala/runtime/ScalaRunTime$
  #326 = Class              #325          // scala/runtime/ScalaRunTime$
  #327 = Utf8               Lscala/runtime/ScalaRunTime$;
  #328 = NameAndType        #53:#327      // MODULE$:Lscala/runtime/ScalaRunTime$;
  #329 = Fieldref           #326.#328     // scala/runtime/ScalaRunTime$.MODULE$:Lscala/runtime/ScalaRunTime$;
  #330 = Utf8               getClass
  #331 = Utf8               ()Ljava/lang/Class;
  #332 = NameAndType        #330:#331     // getClass:()Ljava/lang/Class;
  #333 = Methodref          #2.#332       // org/sireum/MBox16.getClass:()Ljava/lang/Class;
  #334 = Utf8               java/lang/Class
  #335 = Class              #334          // java/lang/Class
  #336 = Utf8               getName
  #337 = NameAndType        #336:#233     // getName:()Ljava/lang/String;
  #338 = Methodref          #335.#337     // java/lang/Class.getName:()Ljava/lang/String;
  #339 = Utf8               genericWrapArray
  #340 = Utf8               (Ljava/lang/Object;)Lscala/collection/immutable/ArraySeq;
  #341 = NameAndType        #339:#340     // genericWrapArray:(Ljava/lang/Object;)Lscala/collection/immutable/ArraySeq;
  #342 = Methodref          #326.#341     // scala/runtime/ScalaRunTime$.genericWrapArray:(Ljava/lang/Object;)Lscala/collection/immutable/ArraySeq;
  #343 = Utf8               scala/collection/immutable/Seq$
  #344 = Class              #343          // scala/collection/immutable/Seq$
  #345 = Utf8               (Lscala/collection/immutable/Seq;)Lscala/collection/SeqOps;
  #346 = NameAndType        #306:#345     // apply:(Lscala/collection/immutable/Seq;)Lscala/collection/SeqOps;
  #347 = Methodref          #344.#346     // scala/collection/immutable/Seq$.apply:(Lscala/collection/immutable/Seq;)Lscala/collection/SeqOps;
  #348 = Utf8               scala/collection/Seq
  #349 = Class              #348          // scala/collection/Seq
  #350 = InterfaceMethodref #349.#314     // scala/collection/Seq.hashCode:()I
  #351 = Utf8               equals
  #352 = Utf8               (Ljava/lang/Object;)Z
  #353 = NameAndType        #351:#352     // equals:(Ljava/lang/Object;)Z
  #354 = Methodref          #5.#353       // java/lang/Object.equals:(Ljava/lang/Object;)Z
  #355 = Methodref          #2.#314       // org/sireum/MBox16.hashCode:()I
  #356 = Utf8               scala/runtime/BoxesRunTime
  #357 = Class              #356          // scala/runtime/BoxesRunTime
  #358 = Utf8               (Ljava/lang/Object;Ljava/lang/Object;)Z
  #359 = NameAndType        #351:#358     // equals:(Ljava/lang/Object;Ljava/lang/Object;)Z
  #360 = Methodref          #357.#359     // scala/runtime/BoxesRunTime.equals:(Ljava/lang/Object;Ljava/lang/Object;)Z
  #361 = Utf8               (Ljava/lang/Object;Ljava/lang/Object;Ljava/lang/Object;Ljava/lang/Object;Ljava/lang/Object;Ljava/lang/Object;Ljava/lang/Object;Ljava/lang/Object;Ljava/lang/Object;Ljava/lang/Object;Ljava/lang/Object;Ljava/lang/Object;Ljava/lang/Object;Ljava/lang/Object;Ljava/lang/Object;Ljava/lang/Object;)Lorg/sireum/MBox16;
  #362 = Utf8               (TT1;TT2;TT3;TT4;TT5;TT6;TT7;TT8;TT9;TT10;TT11;TT12;TT13;TT14;TT15;TT16;)Lorg/sireum/MBox16<TT1;TT2;TT3;TT4;TT5;TT6;TT7;TT8;TT9;TT10;TT11;TT12;TT13;TT14;TT15;TT16;>;
  #363 = Utf8               (Ljava/lang/Object;Ljava/lang/Object;Ljava/lang/Object;Ljava/lang/Object;Ljava/lang/Object;Ljava/lang/Object;Ljava/lang/Object;Ljava/lang/Object;Ljava/lang/Object;Ljava/lang/Object;Ljava/lang/Object;Ljava/lang/Object;Ljava/lang/Object;Ljava/lang/Object;Ljava/lang/Object;Ljava/lang/Object;)V
  #364 = NameAndType        #242:#363     // "<init>":(Ljava/lang/Object;Ljava/lang/Object;Ljava/lang/Object;Ljava/lang/Object;Ljava/lang/Object;Ljava/lang/Object;Ljava/lang/Object;Ljava/lang/Object;Ljava/lang/Object;Ljava/lang/Object;Ljava/lang/Object;Ljava/lang/Object;Ljava/lang/Object;Ljava/lang/Object;Ljava/lang/Object;Ljava/lang/Object;)V
  #365 = Methodref          #2.#364       // org/sireum/MBox16."<init>":(Ljava/lang/Object;Ljava/lang/Object;Ljava/lang/Object;Ljava/lang/Object;Ljava/lang/Object;Ljava/lang/Object;Ljava/lang/Object;Ljava/lang/Object;Ljava/lang/Object;Ljava/lang/Object;Ljava/lang/Object;Ljava/lang/Object;Ljava/lang/Object;Ljava/lang/Object;Ljava/lang/Object;Ljava/lang/Object;)V
  #366 = Utf8               apply$default$1
  #367 = Utf8               apply$default$2
  #368 = Utf8               apply$default$3
  #369 = Utf8               apply$default$4
  #370 = Utf8               apply$default$5
  #371 = Utf8               apply$default$6
  #372 = Utf8               apply$default$7
  #373 = Utf8               apply$default$8
  #374 = Utf8               apply$default$9
  #375 = Utf8               apply$default$10
  #376 = Utf8               apply$default$11
  #377 = Utf8               apply$default$12
  #378 = Utf8               apply$default$13
  #379 = Utf8               apply$default$14
  #380 = Utf8               apply$default$15
  #381 = Utf8               apply$default$16
  #382 = Utf8               $content
  #383 = Utf8               ()Lscala/collection/immutable/Seq;
  #384 = Utf8               ()Lscala/collection/immutable/Seq<Lscala/Tuple2<Ljava/lang/String;Ljava/lang/Object;>;>;
  #385 = Utf8               scala/Tuple2
  #386 = Class              #385          // scala/Tuple2
  #387 = Utf8               type
  #388 = String             #387          // type
  #389 = Utf8               List
  #390 = Utf8               ()Lscala/collection/immutable/List$;
  #391 = NameAndType        #389:#390     // List:()Lscala/collection/immutable/List$;
  #392 = Methodref          #317.#391     // scala/package$.List:()Lscala/collection/immutable/List$;
  #393 = Utf8               org
  #394 = String             #393          // org
  #395 = Utf8               sireum
  #396 = String             #395          // sireum
  #397 = Utf8               [Ljava/lang/Object;
  #398 = Class              #397          // "[Ljava/lang/Object;"
  #399 = Utf8               wrapRefArray
  #400 = Utf8               ([Ljava/lang/Object;)Lscala/collection/immutable/ArraySeq;
  #401 = NameAndType        #399:#400     // wrapRefArray:([Ljava/lang/Object;)Lscala/collection/immutable/ArraySeq;
  #402 = Methodref          #326.#401     // scala/runtime/ScalaRunTime$.wrapRefArray:([Ljava/lang/Object;)Lscala/collection/immutable/ArraySeq;
  #403 = Utf8               scala/collection/immutable/List$
  #404 = Class              #403          // scala/collection/immutable/List$
  #405 = Utf8               (Lscala/collection/immutable/Seq;)Ljava/lang/Object;
  #406 = NameAndType        #306:#405     // apply:(Lscala/collection/immutable/Seq;)Ljava/lang/Object;
  #407 = Methodref          #404.#406     // scala/collection/immutable/List$.apply:(Lscala/collection/immutable/Seq;)Ljava/lang/Object;
  #408 = Utf8               (Ljava/lang/Object;Ljava/lang/Object;)V
  #409 = NameAndType        #242:#408     // "<init>":(Ljava/lang/Object;Ljava/lang/Object;)V
  #410 = Methodref          #386.#409     // scala/Tuple2."<init>":(Ljava/lang/Object;Ljava/lang/Object;)V
  #411 = String             #102          // value1
  #412 = String             #112          // value2
  #413 = String             #120          // value3
  #414 = String             #128          // value4
  #415 = String             #136          // value5
  #416 = String             #144          // value6
  #417 = String             #152          // value7
  #418 = String             #160          // value8
  #419 = String             #168          // value9
  #420 = String             #176          // value10
  #421 = String             #184          // value11
  #422 = String             #192          // value12
  #423 = String             #200          // value13
  #424 = String             #208          // value14
  #425 = String             #216          // value15
  #426 = String             #224          // value16
  #427 = Utf8               scala/collection/immutable/Seq
  #428 = Class              #427          // scala/collection/immutable/Seq
  #429 = Utf8               $clone
  #430 = Utf8               ()Lorg/sireum/MBox16;
  #431 = Utf8               ()Lorg/sireum/MBox16<TT1;TT2;TT3;TT4;TT5;TT6;TT7;TT8;TT9;TT10;TT11;TT12;TT13;TT14;TT15;TT16;>;
  #432 = Utf8               org/sireum/helper$
  #433 = Class              #432          // org/sireum/helper$
  #434 = Utf8               Lorg/sireum/helper$;
  #435 = NameAndType        #53:#434      // MODULE$:Lorg/sireum/helper$;
  #436 = Fieldref           #433.#435     // org/sireum/helper$.MODULE$:Lorg/sireum/helper$;
  #437 = Utf8               cloneAssign
  #438 = Utf8               (Ljava/lang/Object;)Ljava/lang/Object;
  #439 = NameAndType        #437:#438     // cloneAssign:(Ljava/lang/Object;)Ljava/lang/Object;
  #440 = Methodref          #433.#439     // org/sireum/helper$.cloneAssign:(Ljava/lang/Object;)Ljava/lang/Object;
  #441 = Utf8               r
  #442 = Utf8               (Z)Lorg/sireum/$internal/MutableMarker;
  #443 = NameAndType        #67:#68       // $owned_$eq:(Z)Lorg/sireum/RecordSig;
  #444 = Methodref          #2.#443       // org/sireum/MBox16.$owned_$eq:(Z)Lorg/sireum/RecordSig;
  #445 = NameAndType        #429:#430     // $clone:()Lorg/sireum/MBox16;
  #446 = Methodref          #2.#445       // org/sireum/MBox16.$clone:()Lorg/sireum/MBox16;
  #447 = Utf8               ()Lorg/sireum/$internal/MutableMarker;
  #448 = Utf8               (TT1;TT2;TT3;TT4;TT5;TT6;TT7;TT8;TT9;TT10;TT11;TT12;TT13;TT14;TT15;TT16;)V
  #449 = Utf8               __value1
  #450 = Utf8               __value2
  #451 = Utf8               __value3
  #452 = Utf8               __value4
  #453 = Utf8               __value5
  #454 = Utf8               __value6
  #455 = Utf8               __value7
  #456 = Utf8               __value8
  #457 = Utf8               __value9
  #458 = Utf8               __value10
  #459 = Utf8               __value11
  #460 = Utf8               __value12
  #461 = Utf8               __value13
  #462 = Utf8               __value14
  #463 = Utf8               __value15
  #464 = Utf8               __value16
  #465 = Methodref          #5.#244       // java/lang/Object."<init>":()V
  #466 = Utf8               $init$
  #467 = Utf8               (Lorg/sireum/Mutable;)V
  #468 = NameAndType        #466:#467     // $init$:(Lorg/sireum/Mutable;)V
  #469 = InterfaceMethodref #83.#468      // org/sireum/Mutable.$init$:(Lorg/sireum/Mutable;)V
  #470 = Utf8               (Lorg/sireum/RecordSig;)V
  #471 = NameAndType        #466:#470     // $init$:(Lorg/sireum/RecordSig;)V
  #472 = InterfaceMethodref #7.#471       // org/sireum/RecordSig.$init$:(Lorg/sireum/RecordSig;)V
  #473 = Utf8               Signature
  #474 = Utf8               Code
  #475 = Utf8               LocalVariableTable
  #476 = Utf8               MethodParameters
  #477 = Utf8               LineNumberTable
  #478 = Utf8               StackMapTable
  #479 = Utf8               SourceFile
  #480 = Utf8               RuntimeVisibleAnnotations
  #481 = Utf8               ScalaInlineInfo
  #482 = Utf8               ScalaSig
{
  private T1 _value1;
    descriptor: Ljava/lang/Object;
    flags: (0x0002) ACC_PRIVATE
    Signature: #14                          // TT1;

  private T2 _value2;
    descriptor: Ljava/lang/Object;
    flags: (0x0002) ACC_PRIVATE
    Signature: #16                          // TT2;

  private T3 _value3;
    descriptor: Ljava/lang/Object;
    flags: (0x0002) ACC_PRIVATE
    Signature: #18                          // TT3;

  private T4 _value4;
    descriptor: Ljava/lang/Object;
    flags: (0x0002) ACC_PRIVATE
    Signature: #20                          // TT4;

  private T5 _value5;
    descriptor: Ljava/lang/Object;
    flags: (0x0002) ACC_PRIVATE
    Signature: #22                          // TT5;

  private T6 _value6;
    descriptor: Ljava/lang/Object;
    flags: (0x0002) ACC_PRIVATE
    Signature: #24                          // TT6;

  private T7 _value7;
    descriptor: Ljava/lang/Object;
    flags: (0x0002) ACC_PRIVATE
    Signature: #26                          // TT7;

  private T8 _value8;
    descriptor: Ljava/lang/Object;
    flags: (0x0002) ACC_PRIVATE
    Signature: #28                          // TT8;

  private T9 _value9;
    descriptor: Ljava/lang/Object;
    flags: (0x0002) ACC_PRIVATE
    Signature: #30                          // TT9;

  private T10 _value10;
    descriptor: Ljava/lang/Object;
    flags: (0x0002) ACC_PRIVATE
    Signature: #32                          // TT10;

  private T11 _value11;
    descriptor: Ljava/lang/Object;
    flags: (0x0002) ACC_PRIVATE
    Signature: #34                          // TT11;

  private T12 _value12;
    descriptor: Ljava/lang/Object;
    flags: (0x0002) ACC_PRIVATE
    Signature: #36                          // TT12;

  private T13 _value13;
    descriptor: Ljava/lang/Object;
    flags: (0x0002) ACC_PRIVATE
    Signature: #38                          // TT13;

  private T14 _value14;
    descriptor: Ljava/lang/Object;
    flags: (0x0002) ACC_PRIVATE
    Signature: #40                          // TT14;

  private T15 _value15;
    descriptor: Ljava/lang/Object;
    flags: (0x0002) ACC_PRIVATE
    Signature: #42                          // TT15;

  private T16 _value16;
    descriptor: Ljava/lang/Object;
    flags: (0x0002) ACC_PRIVATE
    Signature: #44                          // TT16;

  private boolean org$sireum$RecordSig$$$isOwned;
    descriptor: Z
    flags: (0x0002) ACC_PRIVATE

  public static <T1 extends java.lang.Object, T2 extends java.lang.Object, T3 extends java.lang.Object, T4 extends java.lang.Object, T5 extends java.lang.Object, T6 extends java.lang.Object, T7 extends java.lang.Object, T8 extends java.lang.Object, T9 extends java.lang.Object, T10 extends java.lang.Object, T11 extends java.lang.Object, T12 extends java.lang.Object, T13 extends java.lang.Object, T14 extends java.lang.Object, T15 extends java.lang.Object, T16 extends java.lang.Object> scala.Some<scala.Tuple16<T1, T2, T3, T4, T5, T6, T7, T8, T9, T10, T11, T12, T13, T14, T15, T16>> unapply(org.sireum.MBox16<T1, T2, T3, T4, T5, T6, T7, T8, T9, T10, T11, T12, T13, T14, T15, T16>);
    descriptor: (Lorg/sireum/MBox16;)Lscala/Some;
    flags: (0x0009) ACC_PUBLIC, ACC_STATIC
    Code:
      stack=2, locals=1, args_size=1
         0: getstatic     #56                 // Field org/sireum/MBox16$.MODULE$:Lorg/sireum/MBox16$;
         3: aload_0
         4: invokevirtual #58                 // Method org/sireum/MBox16$.unapply:(Lorg/sireum/MBox16;)Lscala/Some;
         7: areturn
      LocalVariableTable:
        Start  Length  Slot  Name   Signature
            0       8     0     o   Lorg/sireum/MBox16;
    Signature: #49                          // <T1:Ljava/lang/Object;T2:Ljava/lang/Object;T3:Ljava/lang/Object;T4:Ljava/lang/Object;T5:Ljava/lang/Object;T6:Ljava/lang/Object;T7:Ljava/lang/Object;T8:Ljava/lang/Object;T9:Ljava/lang/Object;T10:Ljava/lang/Object;T11:Ljava/lang/Object;T12:Ljava/lang/Object;T13:Ljava/lang/Object;T14:Ljava/lang/Object;T15:Ljava/lang/Object;T16:Ljava/lang/Object;>(Lorg/sireum/MBox16<TT1;TT2;TT3;TT4;TT5;TT6;TT7;TT8;TT9;TT10;TT11;TT12;TT13;TT14;TT15;TT16;>;)Lscala/Some<Lscala/Tuple16<TT1;TT2;TT3;TT4;TT5;TT6;TT7;TT8;TT9;TT10;TT11;TT12;TT13;TT14;TT15;TT16;>;>;
    MethodParameters:
      Name                           Flags
      o                              final

  public final boolean $owned();
    descriptor: ()Z
    flags: (0x0011) ACC_PUBLIC, ACC_FINAL
    Code:
      stack=1, locals=1, args_size=1
         0: aload_0
         1: invokestatic  #65                 // InterfaceMethod org/sireum/RecordSig.$owned$:(Lorg/sireum/RecordSig;)Z
         4: ireturn
      LineNumberTable:
        line 59: 0
      LocalVariableTable:
        Start  Length  Slot  Name   Signature
            0       5     0  this   Lorg/sireum/MBox16;

  public final org.sireum.RecordSig $owned_$eq(boolean);
    descriptor: (Z)Lorg/sireum/RecordSig;
    flags: (0x0011) ACC_PUBLIC, ACC_FINAL
    Code:
      stack=2, locals=2, args_size=2
         0: aload_0
         1: iload_1
         2: invokestatic  #73                 // InterfaceMethod org/sireum/RecordSig.$owned_$eq$:(Lorg/sireum/RecordSig;Z)Lorg/sireum/RecordSig;
         5: areturn
      LineNumberTable:
        line 59: 0
      LocalVariableTable:
        Start  Length  Slot  Name   Signature
            0       6     0  this   Lorg/sireum/MBox16;
            0       6     1     b   Z
    MethodParameters:
      Name                           Flags
      b                              final

  public org.sireum.Z hash();
    descriptor: ()Lorg/sireum/Z;
    flags: (0x0001) ACC_PUBLIC
    Code:
      stack=1, locals=1, args_size=1
         0: aload_0
         1: invokestatic  #79                 // InterfaceMethod org/sireum/RecordSig.hash$:(Lorg/sireum/RecordSig;)Lorg/sireum/Z;
         4: areturn
      LineNumberTable:
        line 59: 0
      LocalVariableTable:
        Start  Length  Slot  Name   Signature
            0       5     0  this   Lorg/sireum/MBox16;

  public final scala.runtime.Nothing$ $cannotMixImmutableAndMutable();
    descriptor: ()Lscala/runtime/Nothing$;
    flags: (0x0011) ACC_PUBLIC, ACC_FINAL
    Code:
      stack=1, locals=1, args_size=1
         0: aload_0
         1: invokestatic  #87                 // InterfaceMethod org/sireum/Mutable.$cannotMixImmutableAndMutable$:(Lorg/sireum/Mutable;)Lscala/runtime/Nothing$;
         4: areturn
      LineNumberTable:
        line 59: 0
      LocalVariableTable:
        Start  Length  Slot  Name   Signature
            0       5     0  this   Lorg/sireum/MBox16;

  public boolean $hasEquals();
    descriptor: ()Z
    flags: (0x0001) ACC_PUBLIC
    Code:
      stack=1, locals=1, args_size=1
         0: aload_0
         1: invokestatic  #92                 // InterfaceMethod org/sireum/Mutable.$hasEquals$:(Lorg/sireum/Mutable;)Z
         4: ireturn
      LineNumberTable:
        line 59: 0
      LocalVariableTable:
        Start  Length  Slot  Name   Signature
            0       5     0  this   Lorg/sireum/MBox16;

  public boolean $hasString();
    descriptor: ()Z
    flags: (0x0001) ACC_PUBLIC
    Code:
      stack=1, locals=1, args_size=1
         0: aload_0
         1: invokestatic  #96                 // InterfaceMethod org/sireum/Mutable.$hasString$:(Lorg/sireum/Mutable;)Z
         4: ireturn
      LineNumberTable:
        line 59: 0
      LocalVariableTable:
        Start  Length  Slot  Name   Signature
            0       5     0  this   Lorg/sireum/MBox16;

  public boolean org$sireum$RecordSig$$$isOwned();
    descriptor: ()Z
    flags: (0x0001) ACC_PUBLIC
    Code:
      stack=1, locals=1, args_size=1
         0: aload_0
         1: getfield      #98                 // Field org$sireum$RecordSig$$$isOwned:Z
         4: ireturn
      LineNumberTable:
        line 59: 0
      LocalVariableTable:
        Start  Length  Slot  Name   Signature
            0       5     0  this   Lorg/sireum/MBox16;

  public void org$sireum$RecordSig$$$isOwned_$eq(boolean);
    descriptor: (Z)V
    flags: (0x0001) ACC_PUBLIC
    Code:
      stack=2, locals=2, args_size=2
         0: aload_0
         1: iload_1
         2: putfield      #98                 // Field org$sireum$RecordSig$$$isOwned:Z
         5: return
      LineNumberTable:
        line 59: 0
      LocalVariableTable:
        Start  Length  Slot  Name   Signature
            0       6     0  this   Lorg/sireum/MBox16;
            0       6     1   x$1   Z
    MethodParameters:
      Name                           Flags
      x$1                            final

  public T1 value1();
    descriptor: ()Ljava/lang/Object;
    flags: (0x0001) ACC_PUBLIC
    Code:
      stack=1, locals=1, args_size=1
         0: aload_0
         1: getfield      #106                // Field _value1:Ljava/lang/Object;
         4: areturn
      LineNumberTable:
        line 59: 0
      LocalVariableTable:
        Start  Length  Slot  Name   Signature
            0       5     0  this   Lorg/sireum/MBox16;
    Signature: #104                         // ()TT1;

  public T1 getValue1();
    descriptor: ()Ljava/lang/Object;
    flags: (0x0001) ACC_PUBLIC
    Code:
      stack=1, locals=1, args_size=1
         0: aload_0
         1: getfield      #106                // Field _value1:Ljava/lang/Object;
         4: areturn
      LineNumberTable:
        line 59: 0
      LocalVariableTable:
        Start  Length  Slot  Name   Signature
            0       5     0  this   Lorg/sireum/MBox16;
    Signature: #104                         // ()TT1;

  public org.sireum.MBox16<T1, T2, T3, T4, T5, T6, T7, T8, T9, T10, T11, T12, T13, T14, T15, T16> value1_$eq(T1);
    descriptor: (Ljava/lang/Object;)Lorg/sireum/MBox16;
    flags: (0x0001) ACC_PUBLIC
    Code:
      stack=2, locals=2, args_size=2
         0: aload_0
         1: aload_1
         2: putfield      #106                // Field _value1:Ljava/lang/Object;
         5: aload_0
         6: areturn
      LineNumberTable:
        line 59: 0
      LocalVariableTable:
        Start  Length  Slot  Name   Signature
            0       7     0  this   Lorg/sireum/MBox16;
            0       7     1 value1   Ljava/lang/Object;
    Signature: #110                         // (TT1;)Lorg/sireum/MBox16<TT1;TT2;TT3;TT4;TT5;TT6;TT7;TT8;TT9;TT10;TT11;TT12;TT13;TT14;TT15;TT16;>;
    MethodParameters:
      Name                           Flags
      value1                         final

  public org.sireum.MBox16<T1, T2, T3, T4, T5, T6, T7, T8, T9, T10, T11, T12, T13, T14, T15, T16> setValue1(T1);
    descriptor: (Ljava/lang/Object;)Lorg/sireum/MBox16;
    flags: (0x0001) ACC_PUBLIC
    Code:
      stack=2, locals=2, args_size=2
         0: aload_0
         1: aload_1
         2: putfield      #106                // Field _value1:Ljava/lang/Object;
         5: aload_0
         6: areturn
      LineNumberTable:
        line 59: 0
      LocalVariableTable:
        Start  Length  Slot  Name   Signature
            0       7     0  this   Lorg/sireum/MBox16;
            0       7     1 value1   Ljava/lang/Object;
    Signature: #110                         // (TT1;)Lorg/sireum/MBox16<TT1;TT2;TT3;TT4;TT5;TT6;TT7;TT8;TT9;TT10;TT11;TT12;TT13;TT14;TT15;TT16;>;
    MethodParameters:
      Name                           Flags
      value1                         final

  public T2 value2();
    descriptor: ()Ljava/lang/Object;
    flags: (0x0001) ACC_PUBLIC
    Code:
      stack=1, locals=1, args_size=1
         0: aload_0
         1: getfield      #115                // Field _value2:Ljava/lang/Object;
         4: areturn
      LineNumberTable:
        line 59: 0
      LocalVariableTable:
        Start  Length  Slot  Name   Signature
            0       5     0  this   Lorg/sireum/MBox16;
    Signature: #113                         // ()TT2;

  public T2 getValue2();
    descriptor: ()Ljava/lang/Object;
    flags: (0x0001) ACC_PUBLIC
    Code:
      stack=1, locals=1, args_size=1
         0: aload_0
         1: getfield      #115                // Field _value2:Ljava/lang/Object;
         4: areturn
      LineNumberTable:
        line 59: 0
      LocalVariableTable:
        Start  Length  Slot  Name   Signature
            0       5     0  this   Lorg/sireum/MBox16;
    Signature: #113                         // ()TT2;

  public org.sireum.MBox16<T1, T2, T3, T4, T5, T6, T7, T8, T9, T10, T11, T12, T13, T14, T15, T16> value2_$eq(T2);
    descriptor: (Ljava/lang/Object;)Lorg/sireum/MBox16;
    flags: (0x0001) ACC_PUBLIC
    Code:
      stack=2, locals=2, args_size=2
         0: aload_0
         1: aload_1
         2: putfield      #115                // Field _value2:Ljava/lang/Object;
         5: aload_0
         6: areturn
      LineNumberTable:
        line 59: 0
      LocalVariableTable:
        Start  Length  Slot  Name   Signature
            0       7     0  this   Lorg/sireum/MBox16;
            0       7     1 value2   Ljava/lang/Object;
    Signature: #118                         // (TT2;)Lorg/sireum/MBox16<TT1;TT2;TT3;TT4;TT5;TT6;TT7;TT8;TT9;TT10;TT11;TT12;TT13;TT14;TT15;TT16;>;
    MethodParameters:
      Name                           Flags
      value2                         final

  public org.sireum.MBox16<T1, T2, T3, T4, T5, T6, T7, T8, T9, T10, T11, T12, T13, T14, T15, T16> setValue2(T2);
    descriptor: (Ljava/lang/Object;)Lorg/sireum/MBox16;
    flags: (0x0001) ACC_PUBLIC
    Code:
      stack=2, locals=2, args_size=2
         0: aload_0
         1: aload_1
         2: putfield      #115                // Field _value2:Ljava/lang/Object;
         5: aload_0
         6: areturn
      LineNumberTable:
        line 59: 0
      LocalVariableTable:
        Start  Length  Slot  Name   Signature
            0       7     0  this   Lorg/sireum/MBox16;
            0       7     1 value2   Ljava/lang/Object;
    Signature: #118                         // (TT2;)Lorg/sireum/MBox16<TT1;TT2;TT3;TT4;TT5;TT6;TT7;TT8;TT9;TT10;TT11;TT12;TT13;TT14;TT15;TT16;>;
    MethodParameters:
      Name                           Flags
      value2                         final

  public T3 value3();
    descriptor: ()Ljava/lang/Object;
    flags: (0x0001) ACC_PUBLIC
    Code:
      stack=1, locals=1, args_size=1
         0: aload_0
         1: getfield      #123                // Field _value3:Ljava/lang/Object;
         4: areturn
      LineNumberTable:
        line 59: 0
      LocalVariableTable:
        Start  Length  Slot  Name   Signature
            0       5     0  this   Lorg/sireum/MBox16;
    Signature: #121                         // ()TT3;

  public T3 getValue3();
    descriptor: ()Ljava/lang/Object;
    flags: (0x0001) ACC_PUBLIC
    Code:
      stack=1, locals=1, args_size=1
         0: aload_0
         1: getfield      #123                // Field _value3:Ljava/lang/Object;
         4: areturn
      LineNumberTable:
        line 59: 0
      LocalVariableTable:
        Start  Length  Slot  Name   Signature
            0       5     0  this   Lorg/sireum/MBox16;
    Signature: #121                         // ()TT3;

  public org.sireum.MBox16<T1, T2, T3, T4, T5, T6, T7, T8, T9, T10, T11, T12, T13, T14, T15, T16> value3_$eq(T3);
    descriptor: (Ljava/lang/Object;)Lorg/sireum/MBox16;
    flags: (0x0001) ACC_PUBLIC
    Code:
      stack=2, locals=2, args_size=2
         0: aload_0
         1: aload_1
         2: putfield      #123                // Field _value3:Ljava/lang/Object;
         5: aload_0
         6: areturn
      LineNumberTable:
        line 59: 0
      LocalVariableTable:
        Start  Length  Slot  Name   Signature
            0       7     0  this   Lorg/sireum/MBox16;
            0       7     1 value3   Ljava/lang/Object;
    Signature: #126                         // (TT3;)Lorg/sireum/MBox16<TT1;TT2;TT3;TT4;TT5;TT6;TT7;TT8;TT9;TT10;TT11;TT12;TT13;TT14;TT15;TT16;>;
    MethodParameters:
      Name                           Flags
      value3                         final

  public org.sireum.MBox16<T1, T2, T3, T4, T5, T6, T7, T8, T9, T10, T11, T12, T13, T14, T15, T16> setValue3(T3);
    descriptor: (Ljava/lang/Object;)Lorg/sireum/MBox16;
    flags: (0x0001) ACC_PUBLIC
    Code:
      stack=2, locals=2, args_size=2
         0: aload_0
         1: aload_1
         2: putfield      #123                // Field _value3:Ljava/lang/Object;
         5: aload_0
         6: areturn
      LineNumberTable:
        line 59: 0
      LocalVariableTable:
        Start  Length  Slot  Name   Signature
            0       7     0  this   Lorg/sireum/MBox16;
            0       7     1 value3   Ljava/lang/Object;
    Signature: #126                         // (TT3;)Lorg/sireum/MBox16<TT1;TT2;TT3;TT4;TT5;TT6;TT7;TT8;TT9;TT10;TT11;TT12;TT13;TT14;TT15;TT16;>;
    MethodParameters:
      Name                           Flags
      value3                         final

  public T4 value4();
    descriptor: ()Ljava/lang/Object;
    flags: (0x0001) ACC_PUBLIC
    Code:
      stack=1, locals=1, args_size=1
         0: aload_0
         1: getfield      #131                // Field _value4:Ljava/lang/Object;
         4: areturn
      LineNumberTable:
        line 59: 0
      LocalVariableTable:
        Start  Length  Slot  Name   Signature
            0       5     0  this   Lorg/sireum/MBox16;
    Signature: #129                         // ()TT4;

  public T4 getValue4();
    descriptor: ()Ljava/lang/Object;
    flags: (0x0001) ACC_PUBLIC
    Code:
      stack=1, locals=1, args_size=1
         0: aload_0
         1: getfield      #131                // Field _value4:Ljava/lang/Object;
         4: areturn
      LineNumberTable:
        line 59: 0
      LocalVariableTable:
        Start  Length  Slot  Name   Signature
            0       5     0  this   Lorg/sireum/MBox16;
    Signature: #129                         // ()TT4;

  public org.sireum.MBox16<T1, T2, T3, T4, T5, T6, T7, T8, T9, T10, T11, T12, T13, T14, T15, T16> value4_$eq(T4);
    descriptor: (Ljava/lang/Object;)Lorg/sireum/MBox16;
    flags: (0x0001) ACC_PUBLIC
    Code:
      stack=2, locals=2, args_size=2
         0: aload_0
         1: aload_1
         2: putfield      #131                // Field _value4:Ljava/lang/Object;
         5: aload_0
         6: areturn
      LineNumberTable:
        line 59: 0
      LocalVariableTable:
        Start  Length  Slot  Name   Signature
            0       7     0  this   Lorg/sireum/MBox16;
            0       7     1 value4   Ljava/lang/Object;
    Signature: #134                         // (TT4;)Lorg/sireum/MBox16<TT1;TT2;TT3;TT4;TT5;TT6;TT7;TT8;TT9;TT10;TT11;TT12;TT13;TT14;TT15;TT16;>;
    MethodParameters:
      Name                           Flags
      value4                         final

  public org.sireum.MBox16<T1, T2, T3, T4, T5, T6, T7, T8, T9, T10, T11, T12, T13, T14, T15, T16> setValue4(T4);
    descriptor: (Ljava/lang/Object;)Lorg/sireum/MBox16;
    flags: (0x0001) ACC_PUBLIC
    Code:
      stack=2, locals=2, args_size=2
         0: aload_0
         1: aload_1
         2: putfield      #131                // Field _value4:Ljava/lang/Object;
         5: aload_0
         6: areturn
      LineNumberTable:
        line 59: 0
      LocalVariableTable:
        Start  Length  Slot  Name   Signature
            0       7     0  this   Lorg/sireum/MBox16;
            0       7     1 value4   Ljava/lang/Object;
    Signature: #134                         // (TT4;)Lorg/sireum/MBox16<TT1;TT2;TT3;TT4;TT5;TT6;TT7;TT8;TT9;TT10;TT11;TT12;TT13;TT14;TT15;TT16;>;
    MethodParameters:
      Name                           Flags
      value4                         final

  public T5 value5();
    descriptor: ()Ljava/lang/Object;
    flags: (0x0001) ACC_PUBLIC
    Code:
      stack=1, locals=1, args_size=1
         0: aload_0
         1: getfield      #139                // Field _value5:Ljava/lang/Object;
         4: areturn
      LineNumberTable:
        line 59: 0
      LocalVariableTable:
        Start  Length  Slot  Name   Signature
            0       5     0  this   Lorg/sireum/MBox16;
    Signature: #137                         // ()TT5;

  public T5 getValue5();
    descriptor: ()Ljava/lang/Object;
    flags: (0x0001) ACC_PUBLIC
    Code:
      stack=1, locals=1, args_size=1
         0: aload_0
         1: getfield      #139                // Field _value5:Ljava/lang/Object;
         4: areturn
      LineNumberTable:
        line 59: 0
      LocalVariableTable:
        Start  Length  Slot  Name   Signature
            0       5     0  this   Lorg/sireum/MBox16;
    Signature: #137                         // ()TT5;

  public org.sireum.MBox16<T1, T2, T3, T4, T5, T6, T7, T8, T9, T10, T11, T12, T13, T14, T15, T16> value5_$eq(T5);
    descriptor: (Ljava/lang/Object;)Lorg/sireum/MBox16;
    flags: (0x0001) ACC_PUBLIC
    Code:
      stack=2, locals=2, args_size=2
         0: aload_0
         1: aload_1
         2: putfield      #139                // Field _value5:Ljava/lang/Object;
         5: aload_0
         6: areturn
      LineNumberTable:
        line 59: 0
      LocalVariableTable:
        Start  Length  Slot  Name   Signature
            0       7     0  this   Lorg/sireum/MBox16;
            0       7     1 value5   Ljava/lang/Object;
    Signature: #142                         // (TT5;)Lorg/sireum/MBox16<TT1;TT2;TT3;TT4;TT5;TT6;TT7;TT8;TT9;TT10;TT11;TT12;TT13;TT14;TT15;TT16;>;
    MethodParameters:
      Name                           Flags
      value5                         final

  public org.sireum.MBox16<T1, T2, T3, T4, T5, T6, T7, T8, T9, T10, T11, T12, T13, T14, T15, T16> setValue5(T5);
    descriptor: (Ljava/lang/Object;)Lorg/sireum/MBox16;
    flags: (0x0001) ACC_PUBLIC
    Code:
      stack=2, locals=2, args_size=2
         0: aload_0
         1: aload_1
         2: putfield      #139                // Field _value5:Ljava/lang/Object;
         5: aload_0
         6: areturn
      LineNumberTable:
        line 59: 0
      LocalVariableTable:
        Start  Length  Slot  Name   Signature
            0       7     0  this   Lorg/sireum/MBox16;
            0       7     1 value5   Ljava/lang/Object;
    Signature: #142                         // (TT5;)Lorg/sireum/MBox16<TT1;TT2;TT3;TT4;TT5;TT6;TT7;TT8;TT9;TT10;TT11;TT12;TT13;TT14;TT15;TT16;>;
    MethodParameters:
      Name                           Flags
      value5                         final

  public T6 value6();
    descriptor: ()Ljava/lang/Object;
    flags: (0x0001) ACC_PUBLIC
    Code:
      stack=1, locals=1, args_size=1
         0: aload_0
         1: getfield      #147                // Field _value6:Ljava/lang/Object;
         4: areturn
      LineNumberTable:
        line 59: 0
      LocalVariableTable:
        Start  Length  Slot  Name   Signature
            0       5     0  this   Lorg/sireum/MBox16;
    Signature: #145                         // ()TT6;

  public T6 getValue6();
    descriptor: ()Ljava/lang/Object;
    flags: (0x0001) ACC_PUBLIC
    Code:
      stack=1, locals=1, args_size=1
         0: aload_0
         1: getfield      #147                // Field _value6:Ljava/lang/Object;
         4: areturn
      LineNumberTable:
        line 59: 0
      LocalVariableTable:
        Start  Length  Slot  Name   Signature
            0       5     0  this   Lorg/sireum/MBox16;
    Signature: #145                         // ()TT6;

  public org.sireum.MBox16<T1, T2, T3, T4, T5, T6, T7, T8, T9, T10, T11, T12, T13, T14, T15, T16> value6_$eq(T6);
    descriptor: (Ljava/lang/Object;)Lorg/sireum/MBox16;
    flags: (0x0001) ACC_PUBLIC
    Code:
      stack=2, locals=2, args_size=2
         0: aload_0
         1: aload_1
         2: putfield      #147                // Field _value6:Ljava/lang/Object;
         5: aload_0
         6: areturn
      LineNumberTable:
        line 59: 0
      LocalVariableTable:
        Start  Length  Slot  Name   Signature
            0       7     0  this   Lorg/sireum/MBox16;
            0       7     1 value6   Ljava/lang/Object;
    Signature: #150                         // (TT6;)Lorg/sireum/MBox16<TT1;TT2;TT3;TT4;TT5;TT6;TT7;TT8;TT9;TT10;TT11;TT12;TT13;TT14;TT15;TT16;>;
    MethodParameters:
      Name                           Flags
      value6                         final

  public org.sireum.MBox16<T1, T2, T3, T4, T5, T6, T7, T8, T9, T10, T11, T12, T13, T14, T15, T16> setValue6(T6);
    descriptor: (Ljava/lang/Object;)Lorg/sireum/MBox16;
    flags: (0x0001) ACC_PUBLIC
    Code:
      stack=2, locals=2, args_size=2
         0: aload_0
         1: aload_1
         2: putfield      #147                // Field _value6:Ljava/lang/Object;
         5: aload_0
         6: areturn
      LineNumberTable:
        line 59: 0
      LocalVariableTable:
        Start  Length  Slot  Name   Signature
            0       7     0  this   Lorg/sireum/MBox16;
            0       7     1 value6   Ljava/lang/Object;
    Signature: #150                         // (TT6;)Lorg/sireum/MBox16<TT1;TT2;TT3;TT4;TT5;TT6;TT7;TT8;TT9;TT10;TT11;TT12;TT13;TT14;TT15;TT16;>;
    MethodParameters:
      Name                           Flags
      value6                         final

  public T7 value7();
    descriptor: ()Ljava/lang/Object;
    flags: (0x0001) ACC_PUBLIC
    Code:
      stack=1, locals=1, args_size=1
         0: aload_0
         1: getfield      #155                // Field _value7:Ljava/lang/Object;
         4: areturn
      LineNumberTable:
        line 59: 0
      LocalVariableTable:
        Start  Length  Slot  Name   Signature
            0       5     0  this   Lorg/sireum/MBox16;
    Signature: #153                         // ()TT7;

  public T7 getValue7();
    descriptor: ()Ljava/lang/Object;
    flags: (0x0001) ACC_PUBLIC
    Code:
      stack=1, locals=1, args_size=1
         0: aload_0
         1: getfield      #155                // Field _value7:Ljava/lang/Object;
         4: areturn
      LineNumberTable:
        line 59: 0
      LocalVariableTable:
        Start  Length  Slot  Name   Signature
            0       5     0  this   Lorg/sireum/MBox16;
    Signature: #153                         // ()TT7;

  public org.sireum.MBox16<T1, T2, T3, T4, T5, T6, T7, T8, T9, T10, T11, T12, T13, T14, T15, T16> value7_$eq(T7);
    descriptor: (Ljava/lang/Object;)Lorg/sireum/MBox16;
    flags: (0x0001) ACC_PUBLIC
    Code:
      stack=2, locals=2, args_size=2
         0: aload_0
         1: aload_1
         2: putfield      #155                // Field _value7:Ljava/lang/Object;
         5: aload_0
         6: areturn
      LineNumberTable:
        line 59: 0
      LocalVariableTable:
        Start  Length  Slot  Name   Signature
            0       7     0  this   Lorg/sireum/MBox16;
            0       7     1 value7   Ljava/lang/Object;
    Signature: #158                         // (TT7;)Lorg/sireum/MBox16<TT1;TT2;TT3;TT4;TT5;TT6;TT7;TT8;TT9;TT10;TT11;TT12;TT13;TT14;TT15;TT16;>;
    MethodParameters:
      Name                           Flags
      value7                         final

  public org.sireum.MBox16<T1, T2, T3, T4, T5, T6, T7, T8, T9, T10, T11, T12, T13, T14, T15, T16> setValue7(T7);
    descriptor: (Ljava/lang/Object;)Lorg/sireum/MBox16;
    flags: (0x0001) ACC_PUBLIC
    Code:
      stack=2, locals=2, args_size=2
         0: aload_0
         1: aload_1
         2: putfield      #155                // Field _value7:Ljava/lang/Object;
         5: aload_0
         6: areturn
      LineNumberTable:
        line 59: 0
      LocalVariableTable:
        Start  Length  Slot  Name   Signature
            0       7     0  this   Lorg/sireum/MBox16;
            0       7     1 value7   Ljava/lang/Object;
    Signature: #158                         // (TT7;)Lorg/sireum/MBox16<TT1;TT2;TT3;TT4;TT5;TT6;TT7;TT8;TT9;TT10;TT11;TT12;TT13;TT14;TT15;TT16;>;
    MethodParameters:
      Name                           Flags
      value7                         final

  public T8 value8();
    descriptor: ()Ljava/lang/Object;
    flags: (0x0001) ACC_PUBLIC
    Code:
      stack=1, locals=1, args_size=1
         0: aload_0
         1: getfield      #163                // Field _value8:Ljava/lang/Object;
         4: areturn
      LineNumberTable:
        line 59: 0
      LocalVariableTable:
        Start  Length  Slot  Name   Signature
            0       5     0  this   Lorg/sireum/MBox16;
    Signature: #161                         // ()TT8;

  public T8 getValue8();
    descriptor: ()Ljava/lang/Object;
    flags: (0x0001) ACC_PUBLIC
    Code:
      stack=1, locals=1, args_size=1
         0: aload_0
         1: getfield      #163                // Field _value8:Ljava/lang/Object;
         4: areturn
      LineNumberTable:
        line 59: 0
      LocalVariableTable:
        Start  Length  Slot  Name   Signature
            0       5     0  this   Lorg/sireum/MBox16;
    Signature: #161                         // ()TT8;

  public org.sireum.MBox16<T1, T2, T3, T4, T5, T6, T7, T8, T9, T10, T11, T12, T13, T14, T15, T16> value8_$eq(T8);
    descriptor: (Ljava/lang/Object;)Lorg/sireum/MBox16;
    flags: (0x0001) ACC_PUBLIC
    Code:
      stack=2, locals=2, args_size=2
         0: aload_0
         1: aload_1
         2: putfield      #163                // Field _value8:Ljava/lang/Object;
         5: aload_0
         6: areturn
      LineNumberTable:
        line 59: 0
      LocalVariableTable:
        Start  Length  Slot  Name   Signature
            0       7     0  this   Lorg/sireum/MBox16;
            0       7     1 value8   Ljava/lang/Object;
    Signature: #166                         // (TT8;)Lorg/sireum/MBox16<TT1;TT2;TT3;TT4;TT5;TT6;TT7;TT8;TT9;TT10;TT11;TT12;TT13;TT14;TT15;TT16;>;
    MethodParameters:
      Name                           Flags
      value8                         final

  public org.sireum.MBox16<T1, T2, T3, T4, T5, T6, T7, T8, T9, T10, T11, T12, T13, T14, T15, T16> setValue8(T8);
    descriptor: (Ljava/lang/Object;)Lorg/sireum/MBox16;
    flags: (0x0001) ACC_PUBLIC
    Code:
      stack=2, locals=2, args_size=2
         0: aload_0
         1: aload_1
         2: putfield      #163                // Field _value8:Ljava/lang/Object;
         5: aload_0
         6: areturn
      LineNumberTable:
        line 59: 0
      LocalVariableTable:
        Start  Length  Slot  Name   Signature
            0       7     0  this   Lorg/sireum/MBox16;
            0       7     1 value8   Ljava/lang/Object;
    Signature: #166                         // (TT8;)Lorg/sireum/MBox16<TT1;TT2;TT3;TT4;TT5;TT6;TT7;TT8;TT9;TT10;TT11;TT12;TT13;TT14;TT15;TT16;>;
    MethodParameters:
      Name                           Flags
      value8                         final

  public T9 value9();
    descriptor: ()Ljava/lang/Object;
    flags: (0x0001) ACC_PUBLIC
    Code:
      stack=1, locals=1, args_size=1
         0: aload_0
         1: getfield      #171                // Field _value9:Ljava/lang/Object;
         4: areturn
      LineNumberTable:
        line 59: 0
      LocalVariableTable:
        Start  Length  Slot  Name   Signature
            0       5     0  this   Lorg/sireum/MBox16;
    Signature: #169                         // ()TT9;

  public T9 getValue9();
    descriptor: ()Ljava/lang/Object;
    flags: (0x0001) ACC_PUBLIC
    Code:
      stack=1, locals=1, args_size=1
         0: aload_0
         1: getfield      #171                // Field _value9:Ljava/lang/Object;
         4: areturn
      LineNumberTable:
        line 59: 0
      LocalVariableTable:
        Start  Length  Slot  Name   Signature
            0       5     0  this   Lorg/sireum/MBox16;
    Signature: #169                         // ()TT9;

  public org.sireum.MBox16<T1, T2, T3, T4, T5, T6, T7, T8, T9, T10, T11, T12, T13, T14, T15, T16> value9_$eq(T9);
    descriptor: (Ljava/lang/Object;)Lorg/sireum/MBox16;
    flags: (0x0001) ACC_PUBLIC
    Code:
      stack=2, locals=2, args_size=2
         0: aload_0
         1: aload_1
         2: putfield      #171                // Field _value9:Ljava/lang/Object;
         5: aload_0
         6: areturn
      LineNumberTable:
        line 59: 0
      LocalVariableTable:
        Start  Length  Slot  Name   Signature
            0       7     0  this   Lorg/sireum/MBox16;
            0       7     1 value9   Ljava/lang/Object;
    Signature: #174                         // (TT9;)Lorg/sireum/MBox16<TT1;TT2;TT3;TT4;TT5;TT6;TT7;TT8;TT9;TT10;TT11;TT12;TT13;TT14;TT15;TT16;>;
    MethodParameters:
      Name                           Flags
      value9                         final

  public org.sireum.MBox16<T1, T2, T3, T4, T5, T6, T7, T8, T9, T10, T11, T12, T13, T14, T15, T16> setValue9(T9);
    descriptor: (Ljava/lang/Object;)Lorg/sireum/MBox16;
    flags: (0x0001) ACC_PUBLIC
    Code:
      stack=2, locals=2, args_size=2
         0: aload_0
         1: aload_1
         2: putfield      #171                // Field _value9:Ljava/lang/Object;
         5: aload_0
         6: areturn
      LineNumberTable:
        line 59: 0
      LocalVariableTable:
        Start  Length  Slot  Name   Signature
            0       7     0  this   Lorg/sireum/MBox16;
            0       7     1 value9   Ljava/lang/Object;
    Signature: #174                         // (TT9;)Lorg/sireum/MBox16<TT1;TT2;TT3;TT4;TT5;TT6;TT7;TT8;TT9;TT10;TT11;TT12;TT13;TT14;TT15;TT16;>;
    MethodParameters:
      Name                           Flags
      value9                         final

  public T10 value10();
    descriptor: ()Ljava/lang/Object;
    flags: (0x0001) ACC_PUBLIC
    Code:
      stack=1, locals=1, args_size=1
         0: aload_0
         1: getfield      #179                // Field _value10:Ljava/lang/Object;
         4: areturn
      LineNumberTable:
        line 59: 0
      LocalVariableTable:
        Start  Length  Slot  Name   Signature
            0       5     0  this   Lorg/sireum/MBox16;
    Signature: #177                         // ()TT10;

  public T10 getValue10();
    descriptor: ()Ljava/lang/Object;
    flags: (0x0001) ACC_PUBLIC
    Code:
      stack=1, locals=1, args_size=1
         0: aload_0
         1: getfield      #179                // Field _value10:Ljava/lang/Object;
         4: areturn
      LineNumberTable:
        line 59: 0
      LocalVariableTable:
        Start  Length  Slot  Name   Signature
            0       5     0  this   Lorg/sireum/MBox16;
    Signature: #177                         // ()TT10;

  public org.sireum.MBox16<T1, T2, T3, T4, T5, T6, T7, T8, T9, T10, T11, T12, T13, T14, T15, T16> value10_$eq(T10);
    descriptor: (Ljava/lang/Object;)Lorg/sireum/MBox16;
    flags: (0x0001) ACC_PUBLIC
    Code:
      stack=2, locals=2, args_size=2
         0: aload_0
         1: aload_1
         2: putfield      #179                // Field _value10:Ljava/lang/Object;
         5: aload_0
         6: areturn
      LineNumberTable:
        line 59: 0
      LocalVariableTable:
        Start  Length  Slot  Name   Signature
            0       7     0  this   Lorg/sireum/MBox16;
            0       7     1 value10   Ljava/lang/Object;
    Signature: #182                         // (TT10;)Lorg/sireum/MBox16<TT1;TT2;TT3;TT4;TT5;TT6;TT7;TT8;TT9;TT10;TT11;TT12;TT13;TT14;TT15;TT16;>;
    MethodParameters:
      Name                           Flags
      value10                        final

  public org.sireum.MBox16<T1, T2, T3, T4, T5, T6, T7, T8, T9, T10, T11, T12, T13, T14, T15, T16> setValue10(T10);
    descriptor: (Ljava/lang/Object;)Lorg/sireum/MBox16;
    flags: (0x0001) ACC_PUBLIC
    Code:
      stack=2, locals=2, args_size=2
         0: aload_0
         1: aload_1
         2: putfield      #179                // Field _value10:Ljava/lang/Object;
         5: aload_0
         6: areturn
      LineNumberTable:
        line 59: 0
      LocalVariableTable:
        Start  Length  Slot  Name   Signature
            0       7     0  this   Lorg/sireum/MBox16;
            0       7     1 value10   Ljava/lang/Object;
    Signature: #182                         // (TT10;)Lorg/sireum/MBox16<TT1;TT2;TT3;TT4;TT5;TT6;TT7;TT8;TT9;TT10;TT11;TT12;TT13;TT14;TT15;TT16;>;
    MethodParameters:
      Name                           Flags
      value10                        final

  public T11 value11();
    descriptor: ()Ljava/lang/Object;
    flags: (0x0001) ACC_PUBLIC
    Code:
      stack=1, locals=1, args_size=1
         0: aload_0
         1: getfield      #187                // Field _value11:Ljava/lang/Object;
         4: areturn
      LineNumberTable:
        line 59: 0
      LocalVariableTable:
        Start  Length  Slot  Name   Signature
            0       5     0  this   Lorg/sireum/MBox16;
    Signature: #185                         // ()TT11;

  public T11 getValue11();
    descriptor: ()Ljava/lang/Object;
    flags: (0x0001) ACC_PUBLIC
    Code:
      stack=1, locals=1, args_size=1
         0: aload_0
         1: getfield      #187                // Field _value11:Ljava/lang/Object;
         4: areturn
      LineNumberTable:
        line 59: 0
      LocalVariableTable:
        Start  Length  Slot  Name   Signature
            0       5     0  this   Lorg/sireum/MBox16;
    Signature: #185                         // ()TT11;

  public org.sireum.MBox16<T1, T2, T3, T4, T5, T6, T7, T8, T9, T10, T11, T12, T13, T14, T15, T16> value11_$eq(T11);
    descriptor: (Ljava/lang/Object;)Lorg/sireum/MBox16;
    flags: (0x0001) ACC_PUBLIC
    Code:
      stack=2, locals=2, args_size=2
         0: aload_0
         1: aload_1
         2: putfield      #187                // Field _value11:Ljava/lang/Object;
         5: aload_0
         6: areturn
      LineNumberTable:
        line 59: 0
      LocalVariableTable:
        Start  Length  Slot  Name   Signature
            0       7     0  this   Lorg/sireum/MBox16;
            0       7     1 value11   Ljava/lang/Object;
    Signature: #190                         // (TT11;)Lorg/sireum/MBox16<TT1;TT2;TT3;TT4;TT5;TT6;TT7;TT8;TT9;TT10;TT11;TT12;TT13;TT14;TT15;TT16;>;
    MethodParameters:
      Name                           Flags
      value11                        final

  public org.sireum.MBox16<T1, T2, T3, T4, T5, T6, T7, T8, T9, T10, T11, T12, T13, T14, T15, T16> setValue11(T11);
    descriptor: (Ljava/lang/Object;)Lorg/sireum/MBox16;
    flags: (0x0001) ACC_PUBLIC
    Code:
      stack=2, locals=2, args_size=2
         0: aload_0
         1: aload_1
         2: putfield      #187                // Field _value11:Ljava/lang/Object;
         5: aload_0
         6: areturn
      LineNumberTable:
        line 59: 0
      LocalVariableTable:
        Start  Length  Slot  Name   Signature
            0       7     0  this   Lorg/sireum/MBox16;
            0       7     1 value11   Ljava/lang/Object;
    Signature: #190                         // (TT11;)Lorg/sireum/MBox16<TT1;TT2;TT3;TT4;TT5;TT6;TT7;TT8;TT9;TT10;TT11;TT12;TT13;TT14;TT15;TT16;>;
    MethodParameters:
      Name                           Flags
      value11                        final

  public T12 value12();
    descriptor: ()Ljava/lang/Object;
    flags: (0x0001) ACC_PUBLIC
    Code:
      stack=1, locals=1, args_size=1
         0: aload_0
         1: getfield      #195                // Field _value12:Ljava/lang/Object;
         4: areturn
      LineNumberTable:
        line 59: 0
      LocalVariableTable:
        Start  Length  Slot  Name   Signature
            0       5     0  this   Lorg/sireum/MBox16;
    Signature: #193                         // ()TT12;

  public T12 getValue12();
    descriptor: ()Ljava/lang/Object;
    flags: (0x0001) ACC_PUBLIC
    Code:
      stack=1, locals=1, args_size=1
         0: aload_0
         1: getfield      #195                // Field _value12:Ljava/lang/Object;
         4: areturn
      LineNumberTable:
        line 59: 0
      LocalVariableTable:
        Start  Length  Slot  Name   Signature
            0       5     0  this   Lorg/sireum/MBox16;
    Signature: #193                         // ()TT12;

  public org.sireum.MBox16<T1, T2, T3, T4, T5, T6, T7, T8, T9, T10, T11, T12, T13, T14, T15, T16> value12_$eq(T12);
    descriptor: (Ljava/lang/Object;)Lorg/sireum/MBox16;
    flags: (0x0001) ACC_PUBLIC
    Code:
      stack=2, locals=2, args_size=2
         0: aload_0
         1: aload_1
         2: putfield      #195                // Field _value12:Ljava/lang/Object;
         5: aload_0
         6: areturn
      LineNumberTable:
        line 59: 0
      LocalVariableTable:
        Start  Length  Slot  Name   Signature
            0       7     0  this   Lorg/sireum/MBox16;
            0       7     1 value12   Ljava/lang/Object;
    Signature: #198                         // (TT12;)Lorg/sireum/MBox16<TT1;TT2;TT3;TT4;TT5;TT6;TT7;TT8;TT9;TT10;TT11;TT12;TT13;TT14;TT15;TT16;>;
    MethodParameters:
      Name                           Flags
      value12                        final

  public org.sireum.MBox16<T1, T2, T3, T4, T5, T6, T7, T8, T9, T10, T11, T12, T13, T14, T15, T16> setValue12(T12);
    descriptor: (Ljava/lang/Object;)Lorg/sireum/MBox16;
    flags: (0x0001) ACC_PUBLIC
    Code:
      stack=2, locals=2, args_size=2
         0: aload_0
         1: aload_1
         2: putfield      #195                // Field _value12:Ljava/lang/Object;
         5: aload_0
         6: areturn
      LineNumberTable:
        line 59: 0
      LocalVariableTable:
        Start  Length  Slot  Name   Signature
            0       7     0  this   Lorg/sireum/MBox16;
            0       7     1 value12   Ljava/lang/Object;
    Signature: #198                         // (TT12;)Lorg/sireum/MBox16<TT1;TT2;TT3;TT4;TT5;TT6;TT7;TT8;TT9;TT10;TT11;TT12;TT13;TT14;TT15;TT16;>;
    MethodParameters:
      Name                           Flags
      value12                        final

  public T13 value13();
    descriptor: ()Ljava/lang/Object;
    flags: (0x0001) ACC_PUBLIC
    Code:
      stack=1, locals=1, args_size=1
         0: aload_0
         1: getfield      #203                // Field _value13:Ljava/lang/Object;
         4: areturn
      LineNumberTable:
        line 59: 0
      LocalVariableTable:
        Start  Length  Slot  Name   Signature
            0       5     0  this   Lorg/sireum/MBox16;
    Signature: #201                         // ()TT13;

  public T13 getValue13();
    descriptor: ()Ljava/lang/Object;
    flags: (0x0001) ACC_PUBLIC
    Code:
      stack=1, locals=1, args_size=1
         0: aload_0
         1: getfield      #203                // Field _value13:Ljava/lang/Object;
         4: areturn
      LineNumberTable:
        line 59: 0
      LocalVariableTable:
        Start  Length  Slot  Name   Signature
            0       5     0  this   Lorg/sireum/MBox16;
    Signature: #201                         // ()TT13;

  public org.sireum.MBox16<T1, T2, T3, T4, T5, T6, T7, T8, T9, T10, T11, T12, T13, T14, T15, T16> value13_$eq(T13);
    descriptor: (Ljava/lang/Object;)Lorg/sireum/MBox16;
    flags: (0x0001) ACC_PUBLIC
    Code:
      stack=2, locals=2, args_size=2
         0: aload_0
         1: aload_1
         2: putfield      #203                // Field _value13:Ljava/lang/Object;
         5: aload_0
         6: areturn
      LineNumberTable:
        line 59: 0
      LocalVariableTable:
        Start  Length  Slot  Name   Signature
            0       7     0  this   Lorg/sireum/MBox16;
            0       7     1 value13   Ljava/lang/Object;
    Signature: #206                         // (TT13;)Lorg/sireum/MBox16<TT1;TT2;TT3;TT4;TT5;TT6;TT7;TT8;TT9;TT10;TT11;TT12;TT13;TT14;TT15;TT16;>;
    MethodParameters:
      Name                           Flags
      value13                        final

  public org.sireum.MBox16<T1, T2, T3, T4, T5, T6, T7, T8, T9, T10, T11, T12, T13, T14, T15, T16> setValue13(T13);
    descriptor: (Ljava/lang/Object;)Lorg/sireum/MBox16;
    flags: (0x0001) ACC_PUBLIC
    Code:
      stack=2, locals=2, args_size=2
         0: aload_0
         1: aload_1
         2: putfield      #203                // Field _value13:Ljava/lang/Object;
         5: aload_0
         6: areturn
      LineNumberTable:
        line 59: 0
      LocalVariableTable:
        Start  Length  Slot  Name   Signature
            0       7     0  this   Lorg/sireum/MBox16;
            0       7     1 value13   Ljava/lang/Object;
    Signature: #206                         // (TT13;)Lorg/sireum/MBox16<TT1;TT2;TT3;TT4;TT5;TT6;TT7;TT8;TT9;TT10;TT11;TT12;TT13;TT14;TT15;TT16;>;
    MethodParameters:
      Name                           Flags
      value13                        final

  public T14 value14();
    descriptor: ()Ljava/lang/Object;
    flags: (0x0001) ACC_PUBLIC
    Code:
      stack=1, locals=1, args_size=1
         0: aload_0
         1: getfield      #211                // Field _value14:Ljava/lang/Object;
         4: areturn
      LineNumberTable:
        line 59: 0
      LocalVariableTable:
        Start  Length  Slot  Name   Signature
            0       5     0  this   Lorg/sireum/MBox16;
    Signature: #209                         // ()TT14;

  public T14 getValue14();
    descriptor: ()Ljava/lang/Object;
    flags: (0x0001) ACC_PUBLIC
    Code:
      stack=1, locals=1, args_size=1
         0: aload_0
         1: getfield      #211                // Field _value14:Ljava/lang/Object;
         4: areturn
      LineNumberTable:
        line 59: 0
      LocalVariableTable:
        Start  Length  Slot  Name   Signature
            0       5     0  this   Lorg/sireum/MBox16;
    Signature: #209                         // ()TT14;

  public org.sireum.MBox16<T1, T2, T3, T4, T5, T6, T7, T8, T9, T10, T11, T12, T13, T14, T15, T16> value14_$eq(T14);
    descriptor: (Ljava/lang/Object;)Lorg/sireum/MBox16;
    flags: (0x0001) ACC_PUBLIC
    Code:
      stack=2, locals=2, args_size=2
         0: aload_0
         1: aload_1
         2: putfield      #211                // Field _value14:Ljava/lang/Object;
         5: aload_0
         6: areturn
      LineNumberTable:
        line 59: 0
      LocalVariableTable:
        Start  Length  Slot  Name   Signature
            0       7     0  this   Lorg/sireum/MBox16;
            0       7     1 value14   Ljava/lang/Object;
    Signature: #214                         // (TT14;)Lorg/sireum/MBox16<TT1;TT2;TT3;TT4;TT5;TT6;TT7;TT8;TT9;TT10;TT11;TT12;TT13;TT14;TT15;TT16;>;
    MethodParameters:
      Name                           Flags
      value14                        final

  public org.sireum.MBox16<T1, T2, T3, T4, T5, T6, T7, T8, T9, T10, T11, T12, T13, T14, T15, T16> setValue14(T14);
    descriptor: (Ljava/lang/Object;)Lorg/sireum/MBox16;
    flags: (0x0001) ACC_PUBLIC
    Code:
      stack=2, locals=2, args_size=2
         0: aload_0
         1: aload_1
         2: putfield      #211                // Field _value14:Ljava/lang/Object;
         5: aload_0
         6: areturn
      LineNumberTable:
        line 59: 0
      LocalVariableTable:
        Start  Length  Slot  Name   Signature
            0       7     0  this   Lorg/sireum/MBox16;
            0       7     1 value14   Ljava/lang/Object;
    Signature: #214                         // (TT14;)Lorg/sireum/MBox16<TT1;TT2;TT3;TT4;TT5;TT6;TT7;TT8;TT9;TT10;TT11;TT12;TT13;TT14;TT15;TT16;>;
    MethodParameters:
      Name                           Flags
      value14                        final

  public T15 value15();
    descriptor: ()Ljava/lang/Object;
    flags: (0x0001) ACC_PUBLIC
    Code:
      stack=1, locals=1, args_size=1
         0: aload_0
         1: getfield      #219                // Field _value15:Ljava/lang/Object;
         4: areturn
      LineNumberTable:
        line 59: 0
      LocalVariableTable:
        Start  Length  Slot  Name   Signature
            0       5     0  this   Lorg/sireum/MBox16;
    Signature: #217                         // ()TT15;

  public T15 getValue15();
    descriptor: ()Ljava/lang/Object;
    flags: (0x0001) ACC_PUBLIC
    Code:
      stack=1, locals=1, args_size=1
         0: aload_0
         1: getfield      #219                // Field _value15:Ljava/lang/Object;
         4: areturn
      LineNumberTable:
        line 59: 0
      LocalVariableTable:
        Start  Length  Slot  Name   Signature
            0       5     0  this   Lorg/sireum/MBox16;
    Signature: #217                         // ()TT15;

  public org.sireum.MBox16<T1, T2, T3, T4, T5, T6, T7, T8, T9, T10, T11, T12, T13, T14, T15, T16> value15_$eq(T15);
    descriptor: (Ljava/lang/Object;)Lorg/sireum/MBox16;
    flags: (0x0001) ACC_PUBLIC
    Code:
      stack=2, locals=2, args_size=2
         0: aload_0
         1: aload_1
         2: putfield      #219                // Field _value15:Ljava/lang/Object;
         5: aload_0
         6: areturn
      LineNumberTable:
        line 59: 0
      LocalVariableTable:
        Start  Length  Slot  Name   Signature
            0       7     0  this   Lorg/sireum/MBox16;
            0       7     1 value15   Ljava/lang/Object;
    Signature: #222                         // (TT15;)Lorg/sireum/MBox16<TT1;TT2;TT3;TT4;TT5;TT6;TT7;TT8;TT9;TT10;TT11;TT12;TT13;TT14;TT15;TT16;>;
    MethodParameters:
      Name                           Flags
      value15                        final

  public org.sireum.MBox16<T1, T2, T3, T4, T5, T6, T7, T8, T9, T10, T11, T12, T13, T14, T15, T16> setValue15(T15);
    descriptor: (Ljava/lang/Object;)Lorg/sireum/MBox16;
    flags: (0x0001) ACC_PUBLIC
    Code:
      stack=2, locals=2, args_size=2
         0: aload_0
         1: aload_1
         2: putfield      #219                // Field _value15:Ljava/lang/Object;
         5: aload_0
         6: areturn
      LineNumberTable:
        line 59: 0
      LocalVariableTable:
        Start  Length  Slot  Name   Signature
            0       7     0  this   Lorg/sireum/MBox16;
            0       7     1 value15   Ljava/lang/Object;
    Signature: #222                         // (TT15;)Lorg/sireum/MBox16<TT1;TT2;TT3;TT4;TT5;TT6;TT7;TT8;TT9;TT10;TT11;TT12;TT13;TT14;TT15;TT16;>;
    MethodParameters:
      Name                           Flags
      value15                        final

  public T16 value16();
    descriptor: ()Ljava/lang/Object;
    flags: (0x0001) ACC_PUBLIC
    Code:
      stack=1, locals=1, args_size=1
         0: aload_0
         1: getfield      #227                // Field _value16:Ljava/lang/Object;
         4: areturn
      LineNumberTable:
        line 59: 0
      LocalVariableTable:
        Start  Length  Slot  Name   Signature
            0       5     0  this   Lorg/sireum/MBox16;
    Signature: #225                         // ()TT16;

  public T16 getValue16();
    descriptor: ()Ljava/lang/Object;
    flags: (0x0001) ACC_PUBLIC
    Code:
      stack=1, locals=1, args_size=1
         0: aload_0
         1: getfield      #227                // Field _value16:Ljava/lang/Object;
         4: areturn
      LineNumberTable:
        line 59: 0
      LocalVariableTable:
        Start  Length  Slot  Name   Signature
            0       5     0  this   Lorg/sireum/MBox16;
    Signature: #225                         // ()TT16;

  public org.sireum.MBox16<T1, T2, T3, T4, T5, T6, T7, T8, T9, T10, T11, T12, T13, T14, T15, T16> value16_$eq(T16);
    descriptor: (Ljava/lang/Object;)Lorg/sireum/MBox16;
    flags: (0x0001) ACC_PUBLIC
    Code:
      stack=2, locals=2, args_size=2
         0: aload_0
         1: aload_1
         2: putfield      #227                // Field _value16:Ljava/lang/Object;
         5: aload_0
         6: areturn
      LineNumberTable:
        line 59: 0
      LocalVariableTable:
        Start  Length  Slot  Name   Signature
            0       7     0  this   Lorg/sireum/MBox16;
            0       7     1 value16   Ljava/lang/Object;
    Signature: #230                         // (TT16;)Lorg/sireum/MBox16<TT1;TT2;TT3;TT4;TT5;TT6;TT7;TT8;TT9;TT10;TT11;TT12;TT13;TT14;TT15;TT16;>;
    MethodParameters:
      Name                           Flags
      value16                        final

  public org.sireum.MBox16<T1, T2, T3, T4, T5, T6, T7, T8, T9, T10, T11, T12, T13, T14, T15, T16> setValue16(T16);
    descriptor: (Ljava/lang/Object;)Lorg/sireum/MBox16;
    flags: (0x0001) ACC_PUBLIC
    Code:
      stack=2, locals=2, args_size=2
         0: aload_0
         1: aload_1
         2: putfield      #227                // Field _value16:Ljava/lang/Object;
         5: aload_0
         6: areturn
      LineNumberTable:
        line 59: 0
      LocalVariableTable:
        Start  Length  Slot  Name   Signature
            0       7     0  this   Lorg/sireum/MBox16;
            0       7     1 value16   Ljava/lang/Object;
    Signature: #230                         // (TT16;)Lorg/sireum/MBox16<TT1;TT2;TT3;TT4;TT5;TT6;TT7;TT8;TT9;TT10;TT11;TT12;TT13;TT14;TT15;TT16;>;
    MethodParameters:
      Name                           Flags
      value16                        final

  public java.lang.String toString();
    descriptor: ()Ljava/lang/String;
    flags: (0x0001) ACC_PUBLIC
    Code:
      stack=3, locals=2, args_size=1
         0: aload_0
         1: invokevirtual #235                // Method $hasString:()Z
         4: ifeq          14
         7: aload_0
         8: invokestatic  #239                // InterfaceMethod org/sireum/RecordSig.string$:(Lorg/sireum/RecordSig;)Ljava/lang/String;
        11: goto          407
        14: new           #241                // class java/lang/StringBuilder
        17: dup
        18: invokespecial #245                // Method java/lang/StringBuilder."<init>":()V
        21: astore_1
        22: aload_1
        23: ldc           #247                // String MBox16
        25: invokevirtual #251                // Method java/lang/StringBuilder.append:(Ljava/lang/String;)Ljava/lang/StringBuilder;
        28: pop
        29: aload_1
        30: bipush        40
        32: invokevirtual #254                // Method java/lang/StringBuilder.append:(C)Ljava/lang/StringBuilder;
        35: pop
        36: aload_1
        37: getstatic     #259                // Field org/sireum/String$.MODULE$:Lorg/sireum/String$;
        40: aload_0
        41: invokevirtual #261                // Method value1:()Ljava/lang/Object;
        44: invokevirtual #265                // Method org/sireum/String$.escape:(Ljava/lang/Object;)Ljava/lang/String;
        47: invokevirtual #251                // Method java/lang/StringBuilder.append:(Ljava/lang/String;)Ljava/lang/StringBuilder;
        50: pop
        51: aload_1
        52: ldc_w         #267                // String ,
        55: invokevirtual #251                // Method java/lang/StringBuilder.append:(Ljava/lang/String;)Ljava/lang/StringBuilder;
        58: pop
        59: aload_1
        60: getstatic     #259                // Field org/sireum/String$.MODULE$:Lorg/sireum/String$;
        63: aload_0
        64: invokevirtual #269                // Method value2:()Ljava/lang/Object;
        67: invokevirtual #265                // Method org/sireum/String$.escape:(Ljava/lang/Object;)Ljava/lang/String;
        70: invokevirtual #251                // Method java/lang/StringBuilder.append:(Ljava/lang/String;)Ljava/lang/StringBuilder;
        73: pop
        74: aload_1
        75: ldc_w         #267                // String ,
        78: invokevirtual #251                // Method java/lang/StringBuilder.append:(Ljava/lang/String;)Ljava/lang/StringBuilder;
        81: pop
        82: aload_1
        83: getstatic     #259                // Field org/sireum/String$.MODULE$:Lorg/sireum/String$;
        86: aload_0
        87: invokevirtual #271                // Method value3:()Ljava/lang/Object;
        90: invokevirtual #265                // Method org/sireum/String$.escape:(Ljava/lang/Object;)Ljava/lang/String;
        93: invokevirtual #251                // Method java/lang/StringBuilder.append:(Ljava/lang/String;)Ljava/lang/StringBuilder;
        96: pop
        97: aload_1
        98: ldc_w         #267                // String ,
       101: invokevirtual #251                // Method java/lang/StringBuilder.append:(Ljava/lang/String;)Ljava/lang/StringBuilder;
       104: pop
       105: aload_1
       106: getstatic     #259                // Field org/sireum/String$.MODULE$:Lorg/sireum/String$;
       109: aload_0
       110: invokevirtual #273                // Method value4:()Ljava/lang/Object;
       113: invokevirtual #265                // Method org/sireum/String$.escape:(Ljava/lang/Object;)Ljava/lang/String;
       116: invokevirtual #251                // Method java/lang/StringBuilder.append:(Ljava/lang/String;)Ljava/lang/StringBuilder;
       119: pop
       120: aload_1
       121: ldc_w         #267                // String ,
       124: invokevirtual #251                // Method java/lang/StringBuilder.append:(Ljava/lang/String;)Ljava/lang/StringBuilder;
       127: pop
       128: aload_1
       129: getstatic     #259                // Field org/sireum/String$.MODULE$:Lorg/sireum/String$;
       132: aload_0
       133: invokevirtual #275                // Method value5:()Ljava/lang/Object;
       136: invokevirtual #265                // Method org/sireum/String$.escape:(Ljava/lang/Object;)Ljava/lang/String;
       139: invokevirtual #251                // Method java/lang/StringBuilder.append:(Ljava/lang/String;)Ljava/lang/StringBuilder;
       142: pop
       143: aload_1
       144: ldc_w         #267                // String ,
       147: invokevirtual #251                // Method java/lang/StringBuilder.append:(Ljava/lang/String;)Ljava/lang/StringBuilder;
       150: pop
       151: aload_1
       152: getstatic     #259                // Field org/sireum/String$.MODULE$:Lorg/sireum/String$;
       155: aload_0
       156: invokevirtual #277                // Method value6:()Ljava/lang/Object;
       159: invokevirtual #265                // Method org/sireum/String$.escape:(Ljava/lang/Object;)Ljava/lang/String;
       162: invokevirtual #251                // Method java/lang/StringBuilder.append:(Ljava/lang/String;)Ljava/lang/StringBuilder;
       165: pop
       166: aload_1
       167: ldc_w         #267                // String ,
       170: invokevirtual #251                // Method java/lang/StringBuilder.append:(Ljava/lang/String;)Ljava/lang/StringBuilder;
       173: pop
       174: aload_1
       175: getstatic     #259                // Field org/sireum/String$.MODULE$:Lorg/sireum/String$;
       178: aload_0
       179: invokevirtual #279                // Method value7:()Ljava/lang/Object;
       182: invokevirtual #265                // Method org/sireum/String$.escape:(Ljava/lang/Object;)Ljava/lang/String;
       185: invokevirtual #251                // Method java/lang/StringBuilder.append:(Ljava/lang/String;)Ljava/lang/StringBuilder;
       188: pop
       189: aload_1
       190: ldc_w         #267                // String ,
       193: invokevirtual #251                // Method java/lang/StringBuilder.append:(Ljava/lang/String;)Ljava/lang/StringBuilder;
       196: pop
       197: aload_1
       198: getstatic     #259                // Field org/sireum/String$.MODULE$:Lorg/sireum/String$;
       201: aload_0
       202: invokevirtual #281                // Method value8:()Ljava/lang/Object;
       205: invokevirtual #265                // Method org/sireum/String$.escape:(Ljava/lang/Object;)Ljava/lang/String;
       208: invokevirtual #251                // Method java/lang/StringBuilder.append:(Ljava/lang/String;)Ljava/lang/StringBuilder;
       211: pop
       212: aload_1
       213: ldc_w         #267                // String ,
       216: invokevirtual #251                // Method java/lang/StringBuilder.append:(Ljava/lang/String;)Ljava/lang/StringBuilder;
       219: pop
       220: aload_1
       221: getstatic     #259                // Field org/sireum/String$.MODULE$:Lorg/sireum/String$;
       224: aload_0
       225: invokevirtual #283                // Method value9:()Ljava/lang/Object;
       228: invokevirtual #265                // Method org/sireum/String$.escape:(Ljava/lang/Object;)Ljava/lang/String;
       231: invokevirtual #251                // Method java/lang/StringBuilder.append:(Ljava/lang/String;)Ljava/lang/StringBuilder;
       234: pop
       235: aload_1
       236: ldc_w         #267                // String ,
       239: invokevirtual #251                // Method java/lang/StringBuilder.append:(Ljava/lang/String;)Ljava/lang/StringBuilder;
       242: pop
       243: aload_1
       244: getstatic     #259                // Field org/sireum/String$.MODULE$:Lorg/sireum/String$;
       247: aload_0
       248: invokevirtual #285                // Method value10:()Ljava/lang/Object;
       251: invokevirtual #265                // Method org/sireum/String$.escape:(Ljava/lang/Object;)Ljava/lang/String;
       254: invokevirtual #251                // Method java/lang/StringBuilder.append:(Ljava/lang/String;)Ljava/lang/StringBuilder;
       257: pop
       258: aload_1
       259: ldc_w         #267                // String ,
       262: invokevirtual #251                // Method java/lang/StringBuilder.append:(Ljava/lang/String;)Ljava/lang/StringBuilder;
       265: pop
       266: aload_1
       267: getstatic     #259                // Field org/sireum/String$.MODULE$:Lorg/sireum/String$;
       270: aload_0
       271: invokevirtual #287                // Method value11:()Ljava/lang/Object;
       274: invokevirtual #265                // Method org/sireum/String$.escape:(Ljava/lang/Object;)Ljava/lang/String;
       277: invokevirtual #251                // Method java/lang/StringBuilder.append:(Ljava/lang/String;)Ljava/lang/StringBuilder;
       280: pop
       281: aload_1
       282: ldc_w         #267                // String ,
       285: invokevirtual #251                // Method java/lang/StringBuilder.append:(Ljava/lang/String;)Ljava/lang/StringBuilder;
       288: pop
       289: aload_1
       290: getstatic     #259                // Field org/sireum/String$.MODULE$:Lorg/sireum/String$;
       293: aload_0
       294: invokevirtual #289                // Method value12:()Ljava/lang/Object;
       297: invokevirtual #265                // Method org/sireum/String$.escape:(Ljava/lang/Object;)Ljava/lang/String;
       300: invokevirtual #251                // Method java/lang/StringBuilder.append:(Ljava/lang/String;)Ljava/lang/StringBuilder;
       303: pop
       304: aload_1
       305: ldc_w         #267                // String ,
       308: invokevirtual #251                // Method java/lang/StringBuilder.append:(Ljava/lang/String;)Ljava/lang/StringBuilder;
       311: pop
       312: aload_1
       313: getstatic     #259                // Field org/sireum/String$.MODULE$:Lorg/sireum/String$;
       316: aload_0
       317: invokevirtual #291                // Method value13:()Ljava/lang/Object;
       320: invokevirtual #265                // Method org/sireum/String$.escape:(Ljava/lang/Object;)Ljava/lang/String;
       323: invokevirtual #251                // Method java/lang/StringBuilder.append:(Ljava/lang/String;)Ljava/lang/StringBuilder;
       326: pop
       327: aload_1
       328: ldc_w         #267                // String ,
       331: invokevirtual #251                // Method java/lang/StringBuilder.append:(Ljava/lang/String;)Ljava/lang/StringBuilder;
       334: pop
       335: aload_1
       336: getstatic     #259                // Field org/sireum/String$.MODULE$:Lorg/sireum/String$;
       339: aload_0
       340: invokevirtual #293                // Method value14:()Ljava/lang/Object;
       343: invokevirtual #265                // Method org/sireum/String$.escape:(Ljava/lang/Object;)Ljava/lang/String;
       346: invokevirtual #251                // Method java/lang/StringBuilder.append:(Ljava/lang/String;)Ljava/lang/StringBuilder;
       349: pop
       350: aload_1
       351: ldc_w         #267                // String ,
       354: invokevirtual #251                // Method java/lang/StringBuilder.append:(Ljava/lang/String;)Ljava/lang/StringBuilder;
       357: pop
       358: aload_1
       359: getstatic     #259                // Field org/sireum/String$.MODULE$:Lorg/sireum/String$;
       362: aload_0
       363: invokevirtual #295                // Method value15:()Ljava/lang/Object;
       366: invokevirtual #265                // Method org/sireum/String$.escape:(Ljava/lang/Object;)Ljava/lang/String;
       369: invokevirtual #251                // Method java/lang/StringBuilder.append:(Ljava/lang/String;)Ljava/lang/StringBuilder;
       372: pop
       373: aload_1
       374: ldc_w         #267                // String ,
       377: invokevirtual #251                // Method java/lang/StringBuilder.append:(Ljava/lang/String;)Ljava/lang/StringBuilder;
       380: pop
       381: aload_1
       382: getstatic     #259                // Field org/sireum/String$.MODULE$:Lorg/sireum/String$;
       385: aload_0
       386: invokevirtual #297                // Method value16:()Ljava/lang/Object;
       389: invokevirtual #265                // Method org/sireum/String$.escape:(Ljava/lang/Object;)Ljava/lang/String;
       392: invokevirtual #251                // Method java/lang/StringBuilder.append:(Ljava/lang/String;)Ljava/lang/StringBuilder;
       395: pop
       396: aload_1
       397: bipush        41
       399: invokevirtual #254                // Method java/lang/StringBuilder.append:(C)Ljava/lang/StringBuilder;
       402: pop
       403: aload_1
       404: invokevirtual #299                // Method java/lang/StringBuilder.toString:()Ljava/lang/String;
       407: areturn
      StackMapTable: number_of_entries = 2
        frame_type = 14 /* same */
        frame_type = 247 /* same_locals_1_stack_item_frame_extended */
          offset_delta = 392
          stack = [ class java/lang/String ]
      LineNumberTable:
        line 59: 0
      LocalVariableTable:
        Start  Length  Slot  Name   Signature
           22     385     1    sb   Ljava/lang/StringBuilder;
            0     408     0  this   Lorg/sireum/MBox16;

  public java.lang.String string();
    descriptor: ()Ljava/lang/String;
    flags: (0x0001) ACC_PUBLIC
    Code:
      stack=2, locals=1, args_size=1
         0: aload_0
         1: invokevirtual #235                // Method $hasString:()Z
         4: ifeq          14
         7: aload_0
         8: invokestatic  #239                // InterfaceMethod org/sireum/RecordSig.string$:(Lorg/sireum/RecordSig;)Ljava/lang/String;
        11: goto          24
        14: getstatic     #259                // Field org/sireum/String$.MODULE$:Lorg/sireum/String$;
        17: aload_0
        18: invokevirtual #305                // Method toString:()Ljava/lang/String;
        21: invokevirtual #309                // Method org/sireum/String$.apply:(Ljava/lang/String;)Ljava/lang/String;
        24: areturn
      StackMapTable: number_of_entries = 2
        frame_type = 14 /* same */
        frame_type = 73 /* same_locals_1_stack_item */
          stack = [ class java/lang/String ]
      LineNumberTable:
        line 59: 0
      LocalVariableTable:
        Start  Length  Slot  Name   Signature
            0      25     0  this   Lorg/sireum/MBox16;

  public int hashCode();
    descriptor: ()I
    flags: (0x0001) ACC_PUBLIC
    Code:
      stack=6, locals=1, args_size=1
         0: aload_0
         1: invokevirtual #313                // Method $hasEquals:()Z
         4: ifeq          14
         7: aload_0
         8: invokespecial #315                // Method java/lang/Object.hashCode:()I
        11: goto          175
        14: getstatic     #320                // Field scala/package$.MODULE$:Lscala/package$;
        17: invokevirtual #324                // Method scala/package$.Seq:()Lscala/collection/immutable/Seq$;
        20: getstatic     #329                // Field scala/runtime/ScalaRunTime$.MODULE$:Lscala/runtime/ScalaRunTime$;
        23: bipush        17
        25: anewarray     #5                  // class java/lang/Object
        28: dup
        29: iconst_0
        30: aload_0
        31: invokevirtual #333                // Method getClass:()Ljava/lang/Class;
        34: invokevirtual #338                // Method java/lang/Class.getName:()Ljava/lang/String;
        37: aastore
        38: dup
        39: iconst_1
        40: aload_0
        41: invokevirtual #261                // Method value1:()Ljava/lang/Object;
        44: aastore
        45: dup
        46: iconst_2
        47: aload_0
        48: invokevirtual #269                // Method value2:()Ljava/lang/Object;
        51: aastore
        52: dup
        53: iconst_3
        54: aload_0
        55: invokevirtual #271                // Method value3:()Ljava/lang/Object;
        58: aastore
        59: dup
        60: iconst_4
        61: aload_0
        62: invokevirtual #273                // Method value4:()Ljava/lang/Object;
        65: aastore
        66: dup
        67: iconst_5
        68: aload_0
        69: invokevirtual #275                // Method value5:()Ljava/lang/Object;
        72: aastore
        73: dup
        74: bipush        6
        76: aload_0
        77: invokevirtual #277                // Method value6:()Ljava/lang/Object;
        80: aastore
        81: dup
        82: bipush        7
        84: aload_0
        85: invokevirtual #279                // Method value7:()Ljava/lang/Object;
        88: aastore
        89: dup
        90: bipush        8
        92: aload_0
        93: invokevirtual #281                // Method value8:()Ljava/lang/Object;
        96: aastore
        97: dup
        98: bipush        9
       100: aload_0
       101: invokevirtual #283                // Method value9:()Ljava/lang/Object;
       104: aastore
       105: dup
       106: bipush        10
       108: aload_0
       109: invokevirtual #285                // Method value10:()Ljava/lang/Object;
       112: aastore
       113: dup
       114: bipush        11
       116: aload_0
       117: invokevirtual #287                // Method value11:()Ljava/lang/Object;
       120: aastore
       121: dup
       122: bipush        12
       124: aload_0
       125: invokevirtual #289                // Method value12:()Ljava/lang/Object;
       128: aastore
       129: dup
       130: bipush        13
       132: aload_0
       133: invokevirtual #291                // Method value13:()Ljava/lang/Object;
       136: aastore
       137: dup
       138: bipush        14
       140: aload_0
       141: invokevirtual #293                // Method value14:()Ljava/lang/Object;
       144: aastore
       145: dup
       146: bipush        15
       148: aload_0
       149: invokevirtual #295                // Method value15:()Ljava/lang/Object;
       152: aastore
       153: dup
       154: bipush        16
       156: aload_0
       157: invokevirtual #297                // Method value16:()Ljava/lang/Object;
       160: aastore
       161: invokevirtual #342                // Method scala/runtime/ScalaRunTime$.genericWrapArray:(Ljava/lang/Object;)Lscala/collection/immutable/ArraySeq;
       164: invokevirtual #347                // Method scala/collection/immutable/Seq$.apply:(Lscala/collection/immutable/Seq;)Lscala/collection/SeqOps;
       167: checkcast     #349                // class scala/collection/Seq
       170: invokeinterface #350,  1          // InterfaceMethod scala/collection/Seq.hashCode:()I
       175: ireturn
      StackMapTable: number_of_entries = 2
        frame_type = 14 /* same */
        frame_type = 247 /* same_locals_1_stack_item_frame_extended */
          offset_delta = 160
          stack = [ int ]
      LineNumberTable:
        line 59: 0
      LocalVariableTable:
        Start  Length  Slot  Name   Signature
            0     176     0  this   Lorg/sireum/MBox16;

  public boolean equals(java.lang.Object);
    descriptor: (Ljava/lang/Object;)Z
    flags: (0x0001) ACC_PUBLIC
    Code:
      stack=2, locals=5, args_size=2
         0: aload_0
         1: invokevirtual #313                // Method $hasEquals:()Z
         4: ifeq          15
         7: aload_0
         8: aload_1
         9: invokespecial #354                // Method java/lang/Object.equals:(Ljava/lang/Object;)Z
        12: goto          313
        15: aload_0
        16: aload_1
        17: if_acmpne     24
        20: iconst_1
        21: goto          313
        24: aload_1
        25: astore_3
        26: aload_3
        27: instanceof    #2                  // class org/sireum/MBox16
        30: ifeq          304
        33: aload_3
        34: checkcast     #2                  // class org/sireum/MBox16
        37: astore        4
        39: aload_0
        40: invokevirtual #355                // Method hashCode:()I
        43: aload         4
        45: invokevirtual #355                // Method hashCode:()I
        48: if_icmpeq     55
        51: iconst_0
        52: goto          300
        55: aload_0
        56: invokevirtual #261                // Method value1:()Ljava/lang/Object;
        59: aload         4
        61: invokevirtual #261                // Method value1:()Ljava/lang/Object;
        64: invokestatic  #360                // Method scala/runtime/BoxesRunTime.equals:(Ljava/lang/Object;Ljava/lang/Object;)Z
        67: ifeq          299
        70: aload_0
        71: invokevirtual #269                // Method value2:()Ljava/lang/Object;
        74: aload         4
        76: invokevirtual #269                // Method value2:()Ljava/lang/Object;
        79: invokestatic  #360                // Method scala/runtime/BoxesRunTime.equals:(Ljava/lang/Object;Ljava/lang/Object;)Z
        82: ifeq          299
        85: aload_0
        86: invokevirtual #271                // Method value3:()Ljava/lang/Object;
        89: aload         4
        91: invokevirtual #271                // Method value3:()Ljava/lang/Object;
        94: invokestatic  #360                // Method scala/runtime/BoxesRunTime.equals:(Ljava/lang/Object;Ljava/lang/Object;)Z
        97: ifeq          299
       100: aload_0
       101: invokevirtual #273                // Method value4:()Ljava/lang/Object;
       104: aload         4
       106: invokevirtual #273                // Method value4:()Ljava/lang/Object;
       109: invokestatic  #360                // Method scala/runtime/BoxesRunTime.equals:(Ljava/lang/Object;Ljava/lang/Object;)Z
       112: ifeq          299
       115: aload_0
       116: invokevirtual #275                // Method value5:()Ljava/lang/Object;
       119: aload         4
       121: invokevirtual #275                // Method value5:()Ljava/lang/Object;
       124: invokestatic  #360                // Method scala/runtime/BoxesRunTime.equals:(Ljava/lang/Object;Ljava/lang/Object;)Z
       127: ifeq          299
       130: aload_0
       131: invokevirtual #277                // Method value6:()Ljava/lang/Object;
       134: aload         4
       136: invokevirtual #277                // Method value6:()Ljava/lang/Object;
       139: invokestatic  #360                // Method scala/runtime/BoxesRunTime.equals:(Ljava/lang/Object;Ljava/lang/Object;)Z
       142: ifeq          299
       145: aload_0
       146: invokevirtual #279                // Method value7:()Ljava/lang/Object;
       149: aload         4
       151: invokevirtual #279                // Method value7:()Ljava/lang/Object;
       154: invokestatic  #360                // Method scala/runtime/BoxesRunTime.equals:(Ljava/lang/Object;Ljava/lang/Object;)Z
       157: ifeq          299
       160: aload_0
       161: invokevirtual #281                // Method value8:()Ljava/lang/Object;
       164: aload         4
       166: invokevirtual #281                // Method value8:()Ljava/lang/Object;
       169: invokestatic  #360                // Method scala/runtime/BoxesRunTime.equals:(Ljava/lang/Object;Ljava/lang/Object;)Z
       172: ifeq          299
       175: aload_0
       176: invokevirtual #283                // Method value9:()Ljava/lang/Object;
       179: aload         4
       181: invokevirtual #283                // Method value9:()Ljava/lang/Object;
       184: invokestatic  #360                // Method scala/runtime/BoxesRunTime.equals:(Ljava/lang/Object;Ljava/lang/Object;)Z
       187: ifeq          299
       190: aload_0
       191: invokevirtual #285                // Method value10:()Ljava/lang/Object;
       194: aload         4
       196: invokevirtual #285                // Method value10:()Ljava/lang/Object;
       199: invokestatic  #360                // Method scala/runtime/BoxesRunTime.equals:(Ljava/lang/Object;Ljava/lang/Object;)Z
       202: ifeq          299
       205: aload_0
       206: invokevirtual #287                // Method value11:()Ljava/lang/Object;
       209: aload         4
       211: invokevirtual #287                // Method value11:()Ljava/lang/Object;
       214: invokestatic  #360                // Method scala/runtime/BoxesRunTime.equals:(Ljava/lang/Object;Ljava/lang/Object;)Z
       217: ifeq          299
       220: aload_0
       221: invokevirtual #289                // Method value12:()Ljava/lang/Object;
       224: aload         4
       226: invokevirtual #289                // Method value12:()Ljava/lang/Object;
       229: invokestatic  #360                // Method scala/runtime/BoxesRunTime.equals:(Ljava/lang/Object;Ljava/lang/Object;)Z
       232: ifeq          299
       235: aload_0
       236: invokevirtual #291                // Method value13:()Ljava/lang/Object;
       239: aload         4
       241: invokevirtual #291                // Method value13:()Ljava/lang/Object;
       244: invokestatic  #360                // Method scala/runtime/BoxesRunTime.equals:(Ljava/lang/Object;Ljava/lang/Object;)Z
       247: ifeq          299
       250: aload_0
       251: invokevirtual #293                // Method value14:()Ljava/lang/Object;
       254: aload         4
       256: invokevirtual #293                // Method value14:()Ljava/lang/Object;
       259: invokestatic  #360                // Method scala/runtime/BoxesRunTime.equals:(Ljava/lang/Object;Ljava/lang/Object;)Z
       262: ifeq          299
       265: aload_0
       266: invokevirtual #295                // Method value15:()Ljava/lang/Object;
       269: aload         4
       271: invokevirtual #295                // Method value15:()Ljava/lang/Object;
       274: invokestatic  #360                // Method scala/runtime/BoxesRunTime.equals:(Ljava/lang/Object;Ljava/lang/Object;)Z
       277: ifeq          299
       280: aload_0
       281: invokevirtual #297                // Method value16:()Ljava/lang/Object;
       284: aload         4
       286: invokevirtual #297                // Method value16:()Ljava/lang/Object;
       289: invokestatic  #360                // Method scala/runtime/BoxesRunTime.equals:(Ljava/lang/Object;Ljava/lang/Object;)Z
       292: ifeq          299
       295: iconst_1
       296: goto          300
       299: iconst_0
       300: istore_2
       301: goto          312
       304: goto          307
       307: iconst_0
       308: istore_2
       309: goto          312
       312: iload_2
       313: ireturn
      StackMapTable: number_of_entries = 9
        frame_type = 15 /* same */
        frame_type = 8 /* same */
        frame_type = 254 /* append */
          offset_delta = 30
          locals = [ top, class java/lang/Object, class org/sireum/MBox16 ]
        frame_type = 251 /* same_frame_extended */
          offset_delta = 243
        frame_type = 64 /* same_locals_1_stack_item */
          stack = [ int ]
        frame_type = 250 /* chop */
          offset_delta = 3
        frame_type = 2 /* same */
        frame_type = 255 /* full_frame */
          offset_delta = 4
          locals = [ class org/sireum/MBox16, class java/lang/Object, int, class java/lang/Object ]
          stack = []
        frame_type = 255 /* full_frame */
          offset_delta = 0
          locals = [ class org/sireum/MBox16, class java/lang/Object ]
          stack = [ int ]
      LineNumberTable:
        line 59: 0
      LocalVariableTable:
        Start  Length  Slot  Name   Signature
            0     314     0  this   Lorg/sireum/MBox16;
            0     314     1     o   Ljava/lang/Object;
    MethodParameters:
      Name                           Flags
      o                              final

  public org.sireum.MBox16<T1, T2, T3, T4, T5, T6, T7, T8, T9, T10, T11, T12, T13, T14, T15, T16> apply(T1, T2, T3, T4, T5, T6, T7, T8, T9, T10, T11, T12, T13, T14, T15, T16);
    descriptor: (Ljava/lang/Object;Ljava/lang/Object;Ljava/lang/Object;Ljava/lang/Object;Ljava/lang/Object;Ljava/lang/Object;Ljava/lang/Object;Ljava/lang/Object;Ljava/lang/Object;Ljava/lang/Object;Ljava/lang/Object;Ljava/lang/Object;Ljava/lang/Object;Ljava/lang/Object;Ljava/lang/Object;Ljava/lang/Object;)Lorg/sireum/MBox16;
    flags: (0x0001) ACC_PUBLIC
    Code:
      stack=18, locals=17, args_size=17
         0: new           #2                  // class org/sireum/MBox16
         3: dup
         4: aload_1
         5: aload_2
         6: aload_3
         7: aload         4
         9: aload         5
        11: aload         6
        13: aload         7
        15: aload         8
        17: aload         9
        19: aload         10
        21: aload         11
        23: aload         12
        25: aload         13
        27: aload         14
        29: aload         15
        31: aload         16
        33: invokespecial #365                // Method "<init>":(Ljava/lang/Object;Ljava/lang/Object;Ljava/lang/Object;Ljava/lang/Object;Ljava/lang/Object;Ljava/lang/Object;Ljava/lang/Object;Ljava/lang/Object;Ljava/lang/Object;Ljava/lang/Object;Ljava/lang/Object;Ljava/lang/Object;Ljava/lang/Object;Ljava/lang/Object;Ljava/lang/Object;Ljava/lang/Object;)V
        36: areturn
      LineNumberTable:
        line 59: 0
      LocalVariableTable:
        Start  Length  Slot  Name   Signature
            0      37     0  this   Lorg/sireum/MBox16;
            0      37     1 value1   Ljava/lang/Object;
            0      37     2 value2   Ljava/lang/Object;
            0      37     3 value3   Ljava/lang/Object;
            0      37     4 value4   Ljava/lang/Object;
            0      37     5 value5   Ljava/lang/Object;
            0      37     6 value6   Ljava/lang/Object;
            0      37     7 value7   Ljava/lang/Object;
            0      37     8 value8   Ljava/lang/Object;
            0      37     9 value9   Ljava/lang/Object;
            0      37    10 value10   Ljava/lang/Object;
            0      37    11 value11   Ljava/lang/Object;
            0      37    12 value12   Ljava/lang/Object;
            0      37    13 value13   Ljava/lang/Object;
            0      37    14 value14   Ljava/lang/Object;
            0      37    15 value15   Ljava/lang/Object;
            0      37    16 value16   Ljava/lang/Object;
    Signature: #362                         // (TT1;TT2;TT3;TT4;TT5;TT6;TT7;TT8;TT9;TT10;TT11;TT12;TT13;TT14;TT15;TT16;)Lorg/sireum/MBox16<TT1;TT2;TT3;TT4;TT5;TT6;TT7;TT8;TT9;TT10;TT11;TT12;TT13;TT14;TT15;TT16;>;
    MethodParameters:
      Name                           Flags
      value1                         final
      value2                         final
      value3                         final
      value4                         final
      value5                         final
      value6                         final
      value7                         final
      value8                         final
      value9                         final
      value10                        final
      value11                        final
      value12                        final
      value13                        final
      value14                        final
      value15                        final
      value16                        final

  public T1 apply$default$1();
    descriptor: ()Ljava/lang/Object;
    flags: (0x0001) ACC_PUBLIC
    Code:
      stack=1, locals=1, args_size=1
         0: aload_0
         1: invokevirtual #261                // Method value1:()Ljava/lang/Object;
         4: areturn
      LineNumberTable:
        line 59: 0
      LocalVariableTable:
        Start  Length  Slot  Name   Signature
            0       5     0  this   Lorg/sireum/MBox16;
    Signature: #104                         // ()TT1;

  public T2 apply$default$2();
    descriptor: ()Ljava/lang/Object;
    flags: (0x0001) ACC_PUBLIC
    Code:
      stack=1, locals=1, args_size=1
         0: aload_0
         1: invokevirtual #269                // Method value2:()Ljava/lang/Object;
         4: areturn
      LineNumberTable:
        line 59: 0
      LocalVariableTable:
        Start  Length  Slot  Name   Signature
            0       5     0  this   Lorg/sireum/MBox16;
    Signature: #113                         // ()TT2;

  public T3 apply$default$3();
    descriptor: ()Ljava/lang/Object;
    flags: (0x0001) ACC_PUBLIC
    Code:
      stack=1, locals=1, args_size=1
         0: aload_0
         1: invokevirtual #271                // Method value3:()Ljava/lang/Object;
         4: areturn
      LineNumberTable:
        line 59: 0
      LocalVariableTable:
        Start  Length  Slot  Name   Signature
            0       5     0  this   Lorg/sireum/MBox16;
    Signature: #121                         // ()TT3;

  public T4 apply$default$4();
    descriptor: ()Ljava/lang/Object;
    flags: (0x0001) ACC_PUBLIC
    Code:
      stack=1, locals=1, args_size=1
         0: aload_0
         1: invokevirtual #273                // Method value4:()Ljava/lang/Object;
         4: areturn
      LineNumberTable:
        line 59: 0
      LocalVariableTable:
        Start  Length  Slot  Name   Signature
            0       5     0  this   Lorg/sireum/MBox16;
    Signature: #129                         // ()TT4;

  public T5 apply$default$5();
    descriptor: ()Ljava/lang/Object;
    flags: (0x0001) ACC_PUBLIC
    Code:
      stack=1, locals=1, args_size=1
         0: aload_0
         1: invokevirtual #275                // Method value5:()Ljava/lang/Object;
         4: areturn
      LineNumberTable:
        line 59: 0
      LocalVariableTable:
        Start  Length  Slot  Name   Signature
            0       5     0  this   Lorg/sireum/MBox16;
    Signature: #137                         // ()TT5;

  public T6 apply$default$6();
    descriptor: ()Ljava/lang/Object;
    flags: (0x0001) ACC_PUBLIC
    Code:
      stack=1, locals=1, args_size=1
         0: aload_0
         1: invokevirtual #277                // Method value6:()Ljava/lang/Object;
         4: areturn
      LineNumberTable:
        line 59: 0
      LocalVariableTable:
        Start  Length  Slot  Name   Signature
            0       5     0  this   Lorg/sireum/MBox16;
    Signature: #145                         // ()TT6;

  public T7 apply$default$7();
    descriptor: ()Ljava/lang/Object;
    flags: (0x0001) ACC_PUBLIC
    Code:
      stack=1, locals=1, args_size=1
         0: aload_0
         1: invokevirtual #279                // Method value7:()Ljava/lang/Object;
         4: areturn
      LineNumberTable:
        line 59: 0
      LocalVariableTable:
        Start  Length  Slot  Name   Signature
            0       5     0  this   Lorg/sireum/MBox16;
    Signature: #153                         // ()TT7;

  public T8 apply$default$8();
    descriptor: ()Ljava/lang/Object;
    flags: (0x0001) ACC_PUBLIC
    Code:
      stack=1, locals=1, args_size=1
         0: aload_0
         1: invokevirtual #281                // Method value8:()Ljava/lang/Object;
         4: areturn
      LineNumberTable:
        line 59: 0
      LocalVariableTable:
        Start  Length  Slot  Name   Signature
            0       5     0  this   Lorg/sireum/MBox16;
    Signature: #161                         // ()TT8;

  public T9 apply$default$9();
    descriptor: ()Ljava/lang/Object;
    flags: (0x0001) ACC_PUBLIC
    Code:
      stack=1, locals=1, args_size=1
         0: aload_0
         1: invokevirtual #283                // Method value9:()Ljava/lang/Object;
         4: areturn
      LineNumberTable:
        line 59: 0
      LocalVariableTable:
        Start  Length  Slot  Name   Signature
            0       5     0  this   Lorg/sireum/MBox16;
    Signature: #169                         // ()TT9;

  public T10 apply$default$10();
    descriptor: ()Ljava/lang/Object;
    flags: (0x0001) ACC_PUBLIC
    Code:
      stack=1, locals=1, args_size=1
         0: aload_0
         1: invokevirtual #285                // Method value10:()Ljava/lang/Object;
         4: areturn
      LineNumberTable:
        line 59: 0
      LocalVariableTable:
        Start  Length  Slot  Name   Signature
            0       5     0  this   Lorg/sireum/MBox16;
    Signature: #177                         // ()TT10;

  public T11 apply$default$11();
    descriptor: ()Ljava/lang/Object;
    flags: (0x0001) ACC_PUBLIC
    Code:
      stack=1, locals=1, args_size=1
         0: aload_0
         1: invokevirtual #287                // Method value11:()Ljava/lang/Object;
         4: areturn
      LineNumberTable:
        line 59: 0
      LocalVariableTable:
        Start  Length  Slot  Name   Signature
            0       5     0  this   Lorg/sireum/MBox16;
    Signature: #185                         // ()TT11;

  public T12 apply$default$12();
    descriptor: ()Ljava/lang/Object;
    flags: (0x0001) ACC_PUBLIC
    Code:
      stack=1, locals=1, args_size=1
         0: aload_0
         1: invokevirtual #289                // Method value12:()Ljava/lang/Object;
         4: areturn
      LineNumberTable:
        line 59: 0
      LocalVariableTable:
        Start  Length  Slot  Name   Signature
            0       5     0  this   Lorg/sireum/MBox16;
    Signature: #193                         // ()TT12;

  public T13 apply$default$13();
    descriptor: ()Ljava/lang/Object;
    flags: (0x0001) ACC_PUBLIC
    Code:
      stack=1, locals=1, args_size=1
         0: aload_0
         1: invokevirtual #291                // Method value13:()Ljava/lang/Object;
         4: areturn
      LineNumberTable:
        line 59: 0
      LocalVariableTable:
        Start  Length  Slot  Name   Signature
            0       5     0  this   Lorg/sireum/MBox16;
    Signature: #201                         // ()TT13;

  public T14 apply$default$14();
    descriptor: ()Ljava/lang/Object;
    flags: (0x0001) ACC_PUBLIC
    Code:
      stack=1, locals=1, args_size=1
         0: aload_0
         1: invokevirtual #293                // Method value14:()Ljava/lang/Object;
         4: areturn
      LineNumberTable:
        line 59: 0
      LocalVariableTable:
        Start  Length  Slot  Name   Signature
            0       5     0  this   Lorg/sireum/MBox16;
    Signature: #209                         // ()TT14;

  public T15 apply$default$15();
    descriptor: ()Ljava/lang/Object;
    flags: (0x0001) ACC_PUBLIC
    Code:
      stack=1, locals=1, args_size=1
         0: aload_0
         1: invokevirtual #295                // Method value15:()Ljava/lang/Object;
         4: areturn
      LineNumberTable:
        line 59: 0
      LocalVariableTable:
        Start  Length  Slot  Name   Signature
            0       5     0  this   Lorg/sireum/MBox16;
    Signature: #217                         // ()TT15;

  public T16 apply$default$16();
    descriptor: ()Ljava/lang/Object;
    flags: (0x0001) ACC_PUBLIC
    Code:
      stack=1, locals=1, args_size=1
         0: aload_0
         1: invokevirtual #297                // Method value16:()Ljava/lang/Object;
         4: areturn
      LineNumberTable:
        line 59: 0
      LocalVariableTable:
        Start  Length  Slot  Name   Signature
            0       5     0  this   Lorg/sireum/MBox16;
    Signature: #225                         // ()TT16;

  public scala.collection.immutable.Seq<scala.Tuple2<java.lang.String, java.lang.Object>> $content();
    descriptor: ()Lscala/collection/immutable/Seq;
    flags: (0x0001) ACC_PUBLIC
    Code:
      stack=14, locals=1, args_size=1
         0: getstatic     #320                // Field scala/package$.MODULE$:Lscala/package$;
         3: invokevirtual #324                // Method scala/package$.Seq:()Lscala/collection/immutable/Seq$;
         6: getstatic     #329                // Field scala/runtime/ScalaRunTime$.MODULE$:Lscala/runtime/ScalaRunTime$;
         9: bipush        17
        11: anewarray     #386                // class scala/Tuple2
        14: dup
        15: iconst_0
        16: new           #386                // class scala/Tuple2
        19: dup
        20: ldc_w         #388                // String type
        23: getstatic     #320                // Field scala/package$.MODULE$:Lscala/package$;
        26: invokevirtual #392                // Method scala/package$.List:()Lscala/collection/immutable/List$;
        29: getstatic     #329                // Field scala/runtime/ScalaRunTime$.MODULE$:Lscala/runtime/ScalaRunTime$;
        32: iconst_3
        33: anewarray     #303                // class java/lang/String
        36: dup
        37: iconst_0
        38: ldc_w         #394                // String org
        41: aastore
        42: dup
        43: iconst_1
        44: ldc_w         #396                // String sireum
        47: aastore
        48: dup
        49: iconst_2
        50: ldc           #247                // String MBox16
        52: aastore
        53: checkcast     #398                // class "[Ljava/lang/Object;"
        56: invokevirtual #402                // Method scala/runtime/ScalaRunTime$.wrapRefArray:([Ljava/lang/Object;)Lscala/collection/immutable/ArraySeq;
        59: invokevirtual #407                // Method scala/collection/immutable/List$.apply:(Lscala/collection/immutable/Seq;)Ljava/lang/Object;
        62: invokespecial #410                // Method scala/Tuple2."<init>":(Ljava/lang/Object;Ljava/lang/Object;)V
        65: aastore
        66: dup
        67: iconst_1
        68: new           #386                // class scala/Tuple2
        71: dup
        72: ldc_w         #411                // String value1
        75: aload_0
        76: invokevirtual #261                // Method value1:()Ljava/lang/Object;
        79: invokespecial #410                // Method scala/Tuple2."<init>":(Ljava/lang/Object;Ljava/lang/Object;)V
        82: aastore
        83: dup
        84: iconst_2
        85: new           #386                // class scala/Tuple2
        88: dup
        89: ldc_w         #412                // String value2
        92: aload_0
        93: invokevirtual #269                // Method value2:()Ljava/lang/Object;
        96: invokespecial #410                // Method scala/Tuple2."<init>":(Ljava/lang/Object;Ljava/lang/Object;)V
        99: aastore
       100: dup
       101: iconst_3
       102: new           #386                // class scala/Tuple2
       105: dup
       106: ldc_w         #413                // String value3
       109: aload_0
       110: invokevirtual #271                // Method value3:()Ljava/lang/Object;
       113: invokespecial #410                // Method scala/Tuple2."<init>":(Ljava/lang/Object;Ljava/lang/Object;)V
       116: aastore
       117: dup
       118: iconst_4
       119: new           #386                // class scala/Tuple2
       122: dup
       123: ldc_w         #414                // String value4
       126: aload_0
       127: invokevirtual #273                // Method value4:()Ljava/lang/Object;
       130: invokespecial #410                // Method scala/Tuple2."<init>":(Ljava/lang/Object;Ljava/lang/Object;)V
       133: aastore
       134: dup
       135: iconst_5
       136: new           #386                // class scala/Tuple2
       139: dup
       140: ldc_w         #415                // String value5
       143: aload_0
       144: invokevirtual #275                // Method value5:()Ljava/lang/Object;
       147: invokespecial #410                // Method scala/Tuple2."<init>":(Ljava/lang/Object;Ljava/lang/Object;)V
       150: aastore
       151: dup
       152: bipush        6
       154: new           #386                // class scala/Tuple2
       157: dup
       158: ldc_w         #416                // String value6
       161: aload_0
       162: invokevirtual #277                // Method value6:()Ljava/lang/Object;
       165: invokespecial #410                // Method scala/Tuple2."<init>":(Ljava/lang/Object;Ljava/lang/Object;)V
       168: aastore
       169: dup
       170: bipush        7
       172: new           #386                // class scala/Tuple2
       175: dup
       176: ldc_w         #417                // String value7
       179: aload_0
       180: invokevirtual #279                // Method value7:()Ljava/lang/Object;
       183: invokespecial #410                // Method scala/Tuple2."<init>":(Ljava/lang/Object;Ljava/lang/Object;)V
       186: aastore
       187: dup
       188: bipush        8
       190: new           #386                // class scala/Tuple2
       193: dup
       194: ldc_w         #418                // String value8
       197: aload_0
       198: invokevirtual #281                // Method value8:()Ljava/lang/Object;
       201: invokespecial #410                // Method scala/Tuple2."<init>":(Ljava/lang/Object;Ljava/lang/Object;)V
       204: aastore
       205: dup
       206: bipush        9
       208: new           #386                // class scala/Tuple2
       211: dup
       212: ldc_w         #419                // String value9
       215: aload_0
       216: invokevirtual #283                // Method value9:()Ljava/lang/Object;
       219: invokespecial #410                // Method scala/Tuple2."<init>":(Ljava/lang/Object;Ljava/lang/Object;)V
       222: aastore
       223: dup
       224: bipush        10
       226: new           #386                // class scala/Tuple2
       229: dup
       230: ldc_w         #420                // String value10
       233: aload_0
       234: invokevirtual #285                // Method value10:()Ljava/lang/Object;
       237: invokespecial #410                // Method scala/Tuple2."<init>":(Ljava/lang/Object;Ljava/lang/Object;)V
       240: aastore
       241: dup
       242: bipush        11
       244: new           #386                // class scala/Tuple2
       247: dup
       248: ldc_w         #421                // String value11
       251: aload_0
       252: invokevirtual #287                // Method value11:()Ljava/lang/Object;
       255: invokespecial #410                // Method scala/Tuple2."<init>":(Ljava/lang/Object;Ljava/lang/Object;)V
       258: aastore
       259: dup
       260: bipush        12
       262: new           #386                // class scala/Tuple2
       265: dup
       266: ldc_w         #422                // String value12
       269: aload_0
       270: invokevirtual #289                // Method value12:()Ljava/lang/Object;
       273: invokespecial #410                // Method scala/Tuple2."<init>":(Ljava/lang/Object;Ljava/lang/Object;)V
       276: aastore
       277: dup
       278: bipush        13
       280: new           #386                // class scala/Tuple2
       283: dup
       284: ldc_w         #423                // String value13
       287: aload_0
       288: invokevirtual #291                // Method value13:()Ljava/lang/Object;
       291: invokespecial #410                // Method scala/Tuple2."<init>":(Ljava/lang/Object;Ljava/lang/Object;)V
       294: aastore
       295: dup
       296: bipush        14
       298: new           #386                // class scala/Tuple2
       301: dup
       302: ldc_w         #424                // String value14
       305: aload_0
       306: invokevirtual #293                // Method value14:()Ljava/lang/Object;
       309: invokespecial #410                // Method scala/Tuple2."<init>":(Ljava/lang/Object;Ljava/lang/Object;)V
       312: aastore
       313: dup
       314: bipush        15
       316: new           #386                // class scala/Tuple2
       319: dup
       320: ldc_w         #425                // String value15
       323: aload_0
       324: invokevirtual #295                // Method value15:()Ljava/lang/Object;
       327: invokespecial #410                // Method scala/Tuple2."<init>":(Ljava/lang/Object;Ljava/lang/Object;)V
       330: aastore
       331: dup
       332: bipush        16
       334: new           #386                // class scala/Tuple2
       337: dup
       338: ldc_w         #426                // String value16
       341: aload_0
       342: invokevirtual #297                // Method value16:()Ljava/lang/Object;
       345: invokespecial #410                // Method scala/Tuple2."<init>":(Ljava/lang/Object;Ljava/lang/Object;)V
       348: aastore
       349: checkcast     #398                // class "[Ljava/lang/Object;"
       352: invokevirtual #402                // Method scala/runtime/ScalaRunTime$.wrapRefArray:([Ljava/lang/Object;)Lscala/collection/immutable/ArraySeq;
       355: invokevirtual #347                // Method scala/collection/immutable/Seq$.apply:(Lscala/collection/immutable/Seq;)Lscala/collection/SeqOps;
       358: checkcast     #428                // class scala/collection/immutable/Seq
       361: areturn
      LineNumberTable:
        line 59: 0
      LocalVariableTable:
        Start  Length  Slot  Name   Signature
            0     362     0  this   Lorg/sireum/MBox16;
    Signature: #384                         // ()Lscala/collection/immutable/Seq<Lscala/Tuple2<Ljava/lang/String;Ljava/lang/Object;>;>;

  public org.sireum.MBox16<T1, T2, T3, T4, T5, T6, T7, T8, T9, T10, T11, T12, T13, T14, T15, T16> $clone();
    descriptor: ()Lorg/sireum/MBox16;
    flags: (0x0001) ACC_PUBLIC
    Code:
      stack=19, locals=2, args_size=1
         0: new           #2                  // class org/sireum/MBox16
         3: dup
         4: getstatic     #436                // Field org/sireum/helper$.MODULE$:Lorg/sireum/helper$;
         7: aload_0
         8: invokevirtual #261                // Method value1:()Ljava/lang/Object;
        11: invokevirtual #440                // Method org/sireum/helper$.cloneAssign:(Ljava/lang/Object;)Ljava/lang/Object;
        14: getstatic     #436                // Field org/sireum/helper$.MODULE$:Lorg/sireum/helper$;
        17: aload_0
        18: invokevirtual #269                // Method value2:()Ljava/lang/Object;
        21: invokevirtual #440                // Method org/sireum/helper$.cloneAssign:(Ljava/lang/Object;)Ljava/lang/Object;
        24: getstatic     #436                // Field org/sireum/helper$.MODULE$:Lorg/sireum/helper$;
        27: aload_0
        28: invokevirtual #271                // Method value3:()Ljava/lang/Object;
        31: invokevirtual #440                // Method org/sireum/helper$.cloneAssign:(Ljava/lang/Object;)Ljava/lang/Object;
        34: getstatic     #436                // Field org/sireum/helper$.MODULE$:Lorg/sireum/helper$;
        37: aload_0
        38: invokevirtual #273                // Method value4:()Ljava/lang/Object;
        41: invokevirtual #440                // Method org/sireum/helper$.cloneAssign:(Ljava/lang/Object;)Ljava/lang/Object;
        44: getstatic     #436                // Field org/sireum/helper$.MODULE$:Lorg/sireum/helper$;
        47: aload_0
        48: invokevirtual #275                // Method value5:()Ljava/lang/Object;
        51: invokevirtual #440                // Method org/sireum/helper$.cloneAssign:(Ljava/lang/Object;)Ljava/lang/Object;
        54: getstatic     #436                // Field org/sireum/helper$.MODULE$:Lorg/sireum/helper$;
        57: aload_0
        58: invokevirtual #277                // Method value6:()Ljava/lang/Object;
        61: invokevirtual #440                // Method org/sireum/helper$.cloneAssign:(Ljava/lang/Object;)Ljava/lang/Object;
        64: getstatic     #436                // Field org/sireum/helper$.MODULE$:Lorg/sireum/helper$;
        67: aload_0
        68: invokevirtual #279                // Method value7:()Ljava/lang/Object;
        71: invokevirtual #440                // Method org/sireum/helper$.cloneAssign:(Ljava/lang/Object;)Ljava/lang/Object;
        74: getstatic     #436                // Field org/sireum/helper$.MODULE$:Lorg/sireum/helper$;
        77: aload_0
        78: invokevirtual #281                // Method value8:()Ljava/lang/Object;
        81: invokevirtual #440                // Method org/sireum/helper$.cloneAssign:(Ljava/lang/Object;)Ljava/lang/Object;
        84: getstatic     #436                // Field org/sireum/helper$.MODULE$:Lorg/sireum/helper$;
        87: aload_0
        88: invokevirtual #283                // Method value9:()Ljava/lang/Object;
        91: invokevirtual #440                // Method org/sireum/helper$.cloneAssign:(Ljava/lang/Object;)Ljava/lang/Object;
        94: getstatic     #436                // Field org/sireum/helper$.MODULE$:Lorg/sireum/helper$;
        97: aload_0
        98: invokevirtual #285                // Method value10:()Ljava/lang/Object;
       101: invokevirtual #440                // Method org/sireum/helper$.cloneAssign:(Ljava/lang/Object;)Ljava/lang/Object;
       104: getstatic     #436                // Field org/sireum/helper$.MODULE$:Lorg/sireum/helper$;
       107: aload_0
       108: invokevirtual #287                // Method value11:()Ljava/lang/Object;
       111: invokevirtual #440                // Method org/sireum/helper$.cloneAssign:(Ljava/lang/Object;)Ljava/lang/Object;
       114: getstatic     #436                // Field org/sireum/helper$.MODULE$:Lorg/sireum/helper$;
       117: aload_0
       118: invokevirtual #289                // Method value12:()Ljava/lang/Object;
       121: invokevirtual #440                // Method org/sireum/helper$.cloneAssign:(Ljava/lang/Object;)Ljava/lang/Object;
       124: getstatic     #436                // Field org/sireum/helper$.MODULE$:Lorg/sireum/helper$;
       127: aload_0
       128: invokevirtual #291                // Method value13:()Ljava/lang/Object;
       131: invokevirtual #440                // Method org/sireum/helper$.cloneAssign:(Ljava/lang/Object;)Ljava/lang/Object;
       134: getstatic     #436                // Field org/sireum/helper$.MODULE$:Lorg/sireum/helper$;
       137: aload_0
       138: invokevirtual #293                // Method value14:()Ljava/lang/Object;
       141: invokevirtual #440                // Method org/sireum/helper$.cloneAssign:(Ljava/lang/Object;)Ljava/lang/Object;
       144: getstatic     #436                // Field org/sireum/helper$.MODULE$:Lorg/sireum/helper$;
       147: aload_0
       148: invokevirtual #295                // Method value15:()Ljava/lang/Object;
       151: invokevirtual #440                // Method org/sireum/helper$.cloneAssign:(Ljava/lang/Object;)Ljava/lang/Object;
       154: getstatic     #436                // Field org/sireum/helper$.MODULE$:Lorg/sireum/helper$;
       157: aload_0
       158: invokevirtual #297                // Method value16:()Ljava/lang/Object;
       161: invokevirtual #440                // Method org/sireum/helper$.cloneAssign:(Ljava/lang/Object;)Ljava/lang/Object;
       164: invokespecial #365                // Method "<init>":(Ljava/lang/Object;Ljava/lang/Object;Ljava/lang/Object;Ljava/lang/Object;Ljava/lang/Object;Ljava/lang/Object;Ljava/lang/Object;Ljava/lang/Object;Ljava/lang/Object;Ljava/lang/Object;Ljava/lang/Object;Ljava/lang/Object;Ljava/lang/Object;Ljava/lang/Object;Ljava/lang/Object;Ljava/lang/Object;)V
       167: astore_1
       168: aload_1
       169: areturn
      LineNumberTable:
        line 59: 0
      LocalVariableTable:
        Start  Length  Slot  Name   Signature
          168       1     1     r   Lorg/sireum/MBox16;
            0     170     0  this   Lorg/sireum/MBox16;
    Signature: #431                         // ()Lorg/sireum/MBox16<TT1;TT2;TT3;TT4;TT5;TT6;TT7;TT8;TT9;TT10;TT11;TT12;TT13;TT14;TT15;TT16;>;

  public final org.sireum.$internal.MutableMarker $owned_$eq(boolean);
    descriptor: (Z)Lorg/sireum/$internal/MutableMarker;
    flags: (0x1051) ACC_PUBLIC, ACC_FINAL, ACC_BRIDGE, ACC_SYNTHETIC
    Code:
      stack=2, locals=2, args_size=2
         0: aload_0
         1: iload_1
         2: invokevirtual #444                // Method $owned_$eq:(Z)Lorg/sireum/RecordSig;
         5: areturn
      LineNumberTable:
        line 59: 0
      LocalVariableTable:
        Start  Length  Slot  Name   Signature
            0       6     0  this   Lorg/sireum/MBox16;
            0       6     1     b   Z
    MethodParameters:
      Name                           Flags
      b                              final

  public java.lang.Object $clone();
    descriptor: ()Ljava/lang/Object;
    flags: (0x1041) ACC_PUBLIC, ACC_BRIDGE, ACC_SYNTHETIC
    Code:
      stack=1, locals=1, args_size=1
         0: aload_0
         1: invokevirtual #446                // Method $clone:()Lorg/sireum/MBox16;
         4: areturn
      LineNumberTable:
        line 59: 0
      LocalVariableTable:
        Start  Length  Slot  Name   Signature
            0       5     0  this   Lorg/sireum/MBox16;

  public org.sireum.$internal.MutableMarker $clone();
    descriptor: ()Lorg/sireum/$internal/MutableMarker;
    flags: (0x1041) ACC_PUBLIC, ACC_BRIDGE, ACC_SYNTHETIC
    Code:
      stack=1, locals=1, args_size=1
         0: aload_0
         1: invokevirtual #446                // Method $clone:()Lorg/sireum/MBox16;
         4: areturn
      LineNumberTable:
        line 59: 0
      LocalVariableTable:
        Start  Length  Slot  Name   Signature
            0       5     0  this   Lorg/sireum/MBox16;

  public org.sireum.MBox16(T1, T2, T3, T4, T5, T6, T7, T8, T9, T10, T11, T12, T13, T14, T15, T16);
    descriptor: (Ljava/lang/Object;Ljava/lang/Object;Ljava/lang/Object;Ljava/lang/Object;Ljava/lang/Object;Ljava/lang/Object;Ljava/lang/Object;Ljava/lang/Object;Ljava/lang/Object;Ljava/lang/Object;Ljava/lang/Object;Ljava/lang/Object;Ljava/lang/Object;Ljava/lang/Object;Ljava/lang/Object;Ljava/lang/Object;)V
    flags: (0x0001) ACC_PUBLIC
    Code:
      stack=2, locals=17, args_size=17
         0: aload_0
         1: invokespecial #465                // Method java/lang/Object."<init>":()V
         4: aload_0
         5: invokestatic  #469                // InterfaceMethod org/sireum/Mutable.$init$:(Lorg/sireum/Mutable;)V
         8: aload_0
         9: invokestatic  #472                // InterfaceMethod org/sireum/RecordSig.$init$:(Lorg/sireum/RecordSig;)V
        12: aload_0
        13: aload_1
        14: putfield      #106                // Field _value1:Ljava/lang/Object;
        17: aload_0
        18: aload_2
        19: putfield      #115                // Field _value2:Ljava/lang/Object;
        22: aload_0
        23: aload_3
        24: putfield      #123                // Field _value3:Ljava/lang/Object;
        27: aload_0
        28: aload         4
        30: putfield      #131                // Field _value4:Ljava/lang/Object;
        33: aload_0
        34: aload         5
        36: putfield      #139                // Field _value5:Ljava/lang/Object;
        39: aload_0
        40: aload         6
        42: putfield      #147                // Field _value6:Ljava/lang/Object;
        45: aload_0
        46: aload         7
        48: putfield      #155                // Field _value7:Ljava/lang/Object;
        51: aload_0
        52: aload         8
        54: putfield      #163                // Field _value8:Ljava/lang/Object;
        57: aload_0
        58: aload         9
        60: putfield      #171                // Field _value9:Ljava/lang/Object;
        63: aload_0
        64: aload         10
        66: putfield      #179                // Field _value10:Ljava/lang/Object;
        69: aload_0
        70: aload         11
        72: putfield      #187                // Field _value11:Ljava/lang/Object;
        75: aload_0
        76: aload         12
        78: putfield      #195                // Field _value12:Ljava/lang/Object;
        81: aload_0
        82: aload         13
        84: putfield      #203                // Field _value13:Ljava/lang/Object;
        87: aload_0
        88: aload         14
        90: putfield      #211                // Field _value14:Ljava/lang/Object;
        93: aload_0
        94: aload         15
        96: putfield      #219                // Field _value15:Ljava/lang/Object;
        99: aload_0
       100: aload         16
       102: putfield      #227                // Field _value16:Ljava/lang/Object;
       105: return
      LineNumberTable:
        line 59: 0
      LocalVariableTable:
        Start  Length  Slot  Name   Signature
            0     106     0  this   Lorg/sireum/MBox16;
            0     106     1 __value1   Ljava/lang/Object;
            0     106     2 __value2   Ljava/lang/Object;
            0     106     3 __value3   Ljava/lang/Object;
            0     106     4 __value4   Ljava/lang/Object;
            0     106     5 __value5   Ljava/lang/Object;
            0     106     6 __value6   Ljava/lang/Object;
            0     106     7 __value7   Ljava/lang/Object;
            0     106     8 __value8   Ljava/lang/Object;
            0     106     9 __value9   Ljava/lang/Object;
            0     106    10 __value10   Ljava/lang/Object;
            0     106    11 __value11   Ljava/lang/Object;
            0     106    12 __value12   Ljava/lang/Object;
            0     106    13 __value13   Ljava/lang/Object;
            0     106    14 __value14   Ljava/lang/Object;
            0     106    15 __value15   Ljava/lang/Object;
            0     106    16 __value16   Ljava/lang/Object;
    Signature: #448                         // (TT1;TT2;TT3;TT4;TT5;TT6;TT7;TT8;TT9;TT10;TT11;TT12;TT13;TT14;TT15;TT16;)V
    MethodParameters:
      Name                           Flags
      __value1                       final
      __value2                       final
      __value3                       final
      __value4                       final
      __value5                       final
      __value6                       final
      __value7                       final
      __value8                       final
      __value9                       final
      __value10                      final
      __value11                      final
      __value12                      final
      __value13                      final
      __value14                      final
      __value15                      final
      __value16                      final
}
Signature: #3                           // <T1:Ljava/lang/Object;T2:Ljava/lang/Object;T3:Ljava/lang/Object;T4:Ljava/lang/Object;T5:Ljava/lang/Object;T6:Ljava/lang/Object;T7:Ljava/lang/Object;T8:Ljava/lang/Object;T9:Ljava/lang/Object;T10:Ljava/lang/Object;T11:Ljava/lang/Object;T12:Ljava/lang/Object;T13:Ljava/lang/Object;T14:Ljava/lang/Object;T15:Ljava/lang/Object;T16:Ljava/lang/Object;>Ljava/lang/Object;Lorg/sireum/RecordSig;
SourceFile: "MBox.scala"
RuntimeVisibleAnnotations:
  0: #9(#10=s#11)
    scala.reflect.ScalaSignature(
      bytes="\u0006\u0005\u0011UwA\u0002@\u0000\u0011\u0003\tIAB\u0004\u0002\u000e}D\t!a\u0004\t\u000f\u0005u\u0011\u0001\"\u0001\u0002 !9\u0011\u0011E\u0001\u0005\u0002\u0005\r\u0002b\u0002C@\u0003\u0011\u0005A\u0011\u0011\u0004\u0007\u0003\u001by(!!\u000b\t\u0015\u0005MRA!A!\u0002\u0013\t)\u0004\u0003\u0006\u0002L\u0015\u0011\t\u0011)A\u0005\u0003\u001bB!\"a\u0015\u0006\u0005\u0003\u0005\u000b\u0011BA+\u0011)\tY&\u0002B\u0001B\u0003%\u0011Q\f\u0005\u000b\u0003G*!\u0011!Q\u0001\n\u0005\u0015\u0004BCA6\u000b\t\u0005\t\u0015!\u0003\u0002n!Q\u00111O\u0003\u0003\u0002\u0003\u0006I!!\u001e\t\u0015\u0005mTA!A!\u0002\u0013\ti\b\u0003\u0006\u0002\u0004\u0016\u0011\t\u0011)A\u0005\u0003\u000bC!\"a#\u0006\u0005\u0003\u0005\u000b\u0011BAG\u0011)\t\u0019*\u0002B\u0001B\u0003%\u0011Q\u0013\u0005\u000b\u00037+!\u0011!Q\u0001\n\u0005u\u0005BCAR\u000b\t\u0005\t\u0015!\u0003\u0002&\"Q\u00111V\u0003\u0003\u0002\u0003\u0006I!!,\t\u0015\u0005MVA!A!\u0002\u0013\t)\f\u0003\u0006\u0002<\u0016\u0011\t\u0011)A\u0005\u0003{Cq!!\b\u0006\t\u0003\t\u0019\r\u0003\u0005\u0002h\u0016\u0001\u000b\u0015BA\u001b\u0011\u001d\tI/\u0002C\u0001\u0003WDq!!<\u0006\t\u0003\tY\u000fC\u0004\u0002p\u0016!\t!!=\t\u000f\u0005]X\u0001\"\u0001\u0002z\"A\u0011Q`\u0003!B\u0013\ti\u0005C\u0004\u0002\u0000\u0016!\tA!\u0001\t\u000f\t\rQ\u0001\"\u0001\u0003\u0002!9!QA\u0003\u0005\u0002\t\u001d\u0001b\u0002B\u0006\u000b\u0011\u0005!Q\u0002\u0005\t\u0005#)\u0001\u0015)\u0003\u0002V!9!1C\u0003\u0005\u0002\tU\u0001b\u0002B\f\u000b\u0011\u0005!Q\u0003\u0005\b\u00053)A\u0011\u0001B\u000e\u0011\u001d\u0011y\"\u0002C\u0001\u0005CA\u0001B!\n\u0006A\u0003&\u0011Q\f\u0005\b\u0005O)A\u0011\u0001B\u0015\u0011\u001d\u0011Y#\u0002C\u0001\u0005SAqA!\f\u0006\t\u0003\u0011y\u0003C\u0004\u00034\u0015!\tA!\u000e\t\u0011\teR\u0001)Q\u0005\u0003KBqAa\u000f\u0006\t\u0003\u0011i\u0004C\u0004\u0003@\u0015!\tA!\u0010\t\u000f\t\u0005S\u0001\"\u0001\u0003D!9!qI\u0003\u0005\u0002\t%\u0003\u0002\u0003B\'\u000b\u0001\u0006K!!\u001c\t\u000f\t=S\u0001\"\u0001\u0003R!9!1K\u0003\u0005\u0002\tE\u0003b\u0002B+\u000b\u0011\u0005!q\u000b\u0005\b\u00057*A\u0011\u0001B/\u0011!\u0011\t\'\u0002Q!\n\u0005U\u0004b\u0002B2\u000b\u0011\u0005!Q\r\u0005\b\u0005O*A\u0011\u0001B3\u0011\u001d\u0011I\'\u0002C\u0001\u0005WBqAa\u001c\u0006\t\u0003\u0011\t\b\u0003\u0005\u0003v\u0015\u0001\u000b\u0015BA?\u0011\u001d\u00119(\u0002C\u0001\u0005sBqAa\u001f\u0006\t\u0003\u0011I\bC\u0004\u0003~\u0015!\tAa \t\u000f\t\rU\u0001\"\u0001\u0003\u0006\"A!\u0011R\u0003!B\u0013\t)\tC\u0004\u0003\f\u0016!\tA!$\t\u000f\t=U\u0001\"\u0001\u0003\u000e\"9!\u0011S\u0003\u0005\u0002\tM\u0005b\u0002BL\u000b\u0011\u0005!\u0011\u0014\u0005\t\u0005;+\u0001\u0015)\u0003\u0002\u000e\"9!qT\u0003\u0005\u0002\t\u0005\u0006b\u0002BR\u000b\u0011\u0005!\u0011\u0015\u0005\b\u0005K+A\u0011\u0001BT\u0011\u001d\u0011Y+\u0002C\u0001\u0005[C\u0001B!-\u0006A\u0003&\u0011Q\u0013\u0005\b\u0005g+A\u0011\u0001B[\u0011\u001d\u00119,\u0002C\u0001\u0005kCqA!/\u0006\t\u0003\u0011Y\fC\u0004\u0003@\u0016!\tA!1\t\u0011\t\u0015W\u0001)Q\u0005\u0003;CqAa2\u0006\t\u0003\u0011I\rC\u0004\u0003L\u0016!\tA!3\t\u000f\t5W\u0001\"\u0001\u0003P\"9!1[\u0003\u0005\u0002\tU\u0007\u0002\u0003Bm\u000b\u0001\u0006K!!*\t\u000f\tmW\u0001\"\u0001\u0003^\"9!q\\\u0003\u0005\u0002\tu\u0007b\u0002Bq\u000b\u0011\u0005!1\u001d\u0005\b\u0005O,A\u0011\u0001Bu\u0011!\u0011i/\u0002Q!\n\u00055\u0006b\u0002Bx\u000b\u0011\u0005!\u0011\u001f\u0005\b\u0005g,A\u0011\u0001By\u0011\u001d\u0011)0\u0002C\u0001\u0005oDqAa?\u0006\t\u0003\u0011i\u0010\u0003\u0005\u0004\u0002\u0015\u0001\u000b\u0015BA[\u0011\u001d\u0019\u0019!\u0002C\u0001\u0007\u000bAqaa\u0002\u0006\t\u0003\u0019)\u0001C\u0004\u0004\n\u0015!\taa\u0003\t\u000f\r=Q\u0001\"\u0001\u0004\u0012!A1QC\u0003!B\u0013\ti\fC\u0004\u0004\u0018\u0015!\ta!\u0007\t\u000f\rmQ\u0001\"\u0001\u0004\u001a!91QD\u0003\u0005\u0002\r}\u0001bBB\u0012\u000b\u0011\u00051Q\u0005\u0005\b\u0007S)A\u0011IB\u0016\u0011\u001d\u0019i$\u0002C!\u0007\u007fAqa!\u0012\u0006\t\u0003\u001a9\u0005C\u0004\u0004P\u0015!\te!\u0015\t\u000f\u0005\u0005R\u0001\"\u0001\u0004^!I1qP\u0003\u0012\u0002\u0013\u00051\u0011\u0011\u0005\n\u0007/+\u0011\u0013!C\u0001\u00073C\u0011b!(\u0006#\u0003%\taa(\t\u0013\r\rV!%A\u0005\u0002\r\u0015\u0006\"CBU\u000bE\u0005I\u0011ABV\u0011%\u0019y+BI\u0001\n\u0003\u0019\t\fC\u0005\u00046\u0016\t\n\u0011\"\u0001\u00048\"I11X\u0003\u0012\u0002\u0013\u00051Q\u0018\u0005\n\u0007\u0003,\u0011\u0013!C\u0001\u0007\u0007D\u0011ba2\u0006#\u0003%\ta!3\t\u0013\r5W!%A\u0005\u0002\r=\u0007\"CBj\u000bE\u0005I\u0011ABk\u0011%\u0019I.BI\u0001\n\u0003\u0019Y\u000eC\u0005\u0004`\u0016\t\n\u0011\"\u0001\u0004b\"I1Q]\u0003\u0012\u0002\u0013\u00051q\u001d\u0005\n\u0007W,\u0011\u0013!C\u0001\u0007[Dqa!=\u0006\t\u0003\u001a\u0019\u0010C\u0004\u0005\u0014\u0015!\t\u0005\"\u0006\u0002\r5\u0013u\u000e_\u00197\u0015\u0011\t\t!a\u0001\u0002\rML\'/Z;n\u0015\t\t)!A\u0002pe\u001e\u001c\u0001\u0001E\u0002\u0002\f\u0005i\u0011a \u0002\u0007\u001b\n{\u00070\r\u001c\u0014\u0007\u0005\t\t\u0002\u0005\u0003\u0002\u0014\u0005eQBAA\u000b\u0015\t\t9\"A\u0003tG\u0006d\u0017-\u0003\u0003\u0002\u001c\u0005U!AB!osJ+g-\u0001\u0004=S:LGO\u0010\u000b\u0003\u0003\u0013\tQ!\u00199qYf,\"%!\n\u0005\"\u0011\u0015B\u0011\u0006C\u0017\tc!)\u0004\"\u000f\u0005>\u0011\u0005CQ\tC%\t\u001b\"\t\u0006\"\u0016\u0005Z\u0011uCCIA\u0014\t?\"\t\u0007b\u0019\u0005f\u0011\u001dD\u0011\u000eC6\t[\"y\u0007\"\u001d\u0005t\u0011UDq\u000fC=\tw\"i\bE\u0012\u0002\f\u0015!y\u0002b\t\u0005(\u0011-Bq\u0006C\u001a\to!Y\u0004b\u0010\u0005D\u0011\u001dC1\nC(\t\'\"9\u0006b\u0017\u0016E\u0005-\u0012\u0011HA(\u0003/\ny&a\u001a\u0002p\u0005]\u0014qPAD\u0003\u001f\u000b9*a(\u0002(\u0006=\u0016qWA`\'\u0015)\u0011\u0011CA\u0017!\u0011\tY!a\f\n\u0007\u0005ErPA\u0005SK\u000e|\'\u000fZ*jO\u0006Aql\u0018<bYV,\u0017\u0007\u0005\u0003\u00028\u0005eB\u0002\u0001\u0003\b\u0003w)!\u0019AA\u001f\u0005\t!\u0016\'\u0005\u0003\u0002@\u0005\u0015\u0003\u0003BA\n\u0003\u0003JA!a\u0011\u0002\u0016\t9aj\u001c;iS:<\u0007\u0003BA\n\u0003\u000fJA!!\u0013\u0002\u0016\t\u0019\u0011I\\=\u0002\u0011}{f/\u00197vKJ\u0002B!a\u000e\u0002P\u00119\u0011\u0011K\u0003C\u0002\u0005u\"A\u0001+3\u0003!yvL^1mk\u0016\u001c\u0004\u0003BA\u001c\u0003/\"q!!\u0017\u0006\u0005\u0004\tiD\u0001\u0002Ug\u0005Aql\u0018<bYV,G\u0007\u0005\u0003\u00028\u0005}CaBA1\u000b\t\u0007\u0011Q\b\u0002\u0003)R\n\u0001bX0wC2,X-\u000e\t\u0005\u0003o\t9\u0007B\u0004\u0002j\u0015\u0011\r!!\u0010\u0003\u0005Q+\u0014\u0001C0`m\u0006dW/\u001a\u001c\u0011\t\u0005]\u0012q\u000e\u0003\b\u0003c*!\u0019AA\u001f\u0005\t!f\'\u0001\u0005`?Z\fG.^38!\u0011\t9$a\u001e\u0005\u000f\u0005eTA1\u0001\u0002>\t\u0011AkN\u0001\t?~3\u0018\r\\;fqA!\u0011qGA@\t\u001d\t\t)\u0002b\u0001\u0003{\u0011!\u0001\u0016\u001d\u0002\u0011}{f/\u00197vKf\u0002B!a\u000e\u0002\b\u00129\u0011\u0011R\u0003C\u0002\u0005u\"A\u0001+:\u0003%yvL^1mk\u0016\f\u0004\u0007\u0005\u0003\u00028\u0005=EaBAI\u000b\t\u0007\u0011Q\b\u0002\u0004)F\u0002\u0014!C0`m\u0006dW/Z\u00192!\u0011\t9$a&\u0005\u000f\u0005eUA1\u0001\u0002>\t\u0019A+M\u0019\u0002\u0013}{f/\u00197vKF\u0012\u0004\u0003BA\u001c\u0003?#q!!)\u0006\u0005\u0004\tiDA\u0002UcI\n\u0011bX0wC2,X-M\u001a\u0011\t\u0005]\u0012q\u0015\u0003\b\u0003S+!\u0019AA\u001f\u0005\r!\u0016gM\u0001\n?~3\u0018\r\\;fcQ\u0002B!a\u000e\u00020\u00129\u0011\u0011W\u0003C\u0002\u0005u\"a\u0001+2i\u0005Iql\u0018<bYV,\u0017\'\u000e\t\u0005\u0003o\t9\fB\u0004\u0002:\u0016\u0011\r!!\u0010\u0003\u0007Q\u000bT\'A\u0005`?Z\fG.^32mA!\u0011qGA`\t\u001d\t\t-\u0002b\u0001\u0003{\u00111\u0001V\u00197)\t\n)-a2\u0002J\u0006-\u0017QZAh\u0003#\f\u0019.!6\u0002X\u0006e\u00171\\Ao\u0003?\f\t/a9\u0002fB\u0019\u00131B\u0003\u00026\u00055\u0013QKA/\u0003K\ni\'!\u001e\u0002~\u0005\u0015\u0015QRAK\u0003;\u000b)+!,\u00026\u0006u\u0006bBA\u001a-\u0001\u0007\u0011Q\u0007\u0005\b\u0003\u00172\u0002\u0019AA\'\u0011\u001d\t\u0019F\u0006a\u0001\u0003+Bq!a\u0017\u0017\u0001\u0004\ti\u0006C\u0004\u0002dY\u0001\r!!\u001a\t\u000f\u0005-d\u00031\u0001\u0002n!9\u00111\u000f\fA\u0002\u0005U\u0004bBA>-\u0001\u0007\u0011Q\u0010\u0005\b\u0003\u00073\u0002\u0019AAC\u0011\u001d\tYI\u0006a\u0001\u0003\u001bCq!a%\u0017\u0001\u0004\t)\nC\u0004\u0002\u001cZ\u0001\r!!(\t\u000f\u0005\rf\u00031\u0001\u0002&\"9\u00111\u0016\fA\u0002\u00055\u0006bBAZ-\u0001\u0007\u0011Q\u0017\u0005\b\u0003w3\u0002\u0019AA_\u0003\u001dyf/\u00197vKF\naA^1mk\u0016\fTCAA\u001b\u0003%9W\r\u001e,bYV,\u0017\'\u0001\u0006wC2,X-M0%KF$B!a=\u0002v6\tQ\u0001C\u0004\u0002jj\u0001\r!!\u000e\u0002\u0013M,GOV1mk\u0016\fD\u0003BAz\u0003wDq!!;\u001c\u0001\u0004\t)$A\u0004`m\u0006dW/\u001a\u001a\u0002\rY\fG.^33+\t\ti%A\u0005hKR4\u0016\r\\;fe\u0005Qa/\u00197vKJzF%Z9\u0015\t\u0005M(\u0011\u0002\u0005\b\u0003\u007f|\u0002\u0019AA\'\u0003%\u0019X\r\u001e,bYV,\'\u0007\u0006\u0003\u0002t\n=\u0001bBA\u0000A\u0001\u0007\u0011QJ\u0001\b?Z\fG.^34\u0003\u00191\u0018\r\\;fgU\u0011\u0011QK\u0001\nO\u0016$h+\u00197vKN\n!B^1mk\u0016\u001ct\fJ3r)\u0011\t\u0019P!\b\t\u000f\tMA\u00051\u0001\u0002V\u0005I1/\u001a;WC2,Xm\r\u000b\u0005\u0003g\u0014\u0019\u0003C\u0004\u0003\u0014\u0015\u0002\r!!\u0016\u0002\u000f}3\u0018\r\\;fi\u00051a/\u00197vKR*\"!!\u0018\u0002\u0013\u001d,GOV1mk\u0016$\u0014A\u0003<bYV,Gg\u0018\u0013fcR!\u00111\u001fB\u0019\u0011\u001d\u00119#\u000ba\u0001\u0003;\n\u0011b]3u-\u0006dW/\u001a\u001b\u0015\t\u0005M(q\u0007\u0005\b\u0005OQ\u0003\u0019AA/\u0003\u001dyf/\u00197vKV\naA^1mk\u0016,TCAA3\u0003%9W\r\u001e,bYV,W\'\u0001\u0006wC2,X-N0%KF$B!a=\u0003F!9!1\b\u0018A\u0002\u0005\u0015\u0014!C:fiZ\u000bG.^36)\u0011\t\u0019Pa\u0013\t\u000f\tmr\u00061\u0001\u0002f\u00059qL^1mk\u00164\u0014A\u0002<bYV,g\'\u0006\u0002\u0002n\u0005Iq-\u001a;WC2,XMN\u0001\u000bm\u0006dW/\u001a\u001c`I\u0015\fH\u0003BAz\u00053BqAa\u00144\u0001\u0004\ti\'A\u0005tKR4\u0016\r\\;fmQ!\u00111\u001fB0\u0011\u001d\u0011y\u0005\u000ea\u0001\u0003[\nqa\u0018<bYV,w\'\u0001\u0004wC2,XmN\u000b\u0003\u0003k\n\u0011bZ3u-\u0006dW/Z\u001c\u0002\u0015Y\fG.^38?\u0012*\u0017\u000f\u0006\u0003\u0002t\n5\u0004b\u0002B2q\u0001\u0007\u0011QO\u0001\ng\u0016$h+\u00197vK^\"B!a=\u0003t!9!1M\u001dA\u0002\u0005U\u0014aB0wC2,X\rO\u0001\u0007m\u0006dW/\u001a\u001d\u0016\u0005\u0005u\u0014!C4fiZ\u000bG.^39\u0003)1\u0018\r\\;fq}#S-\u001d\u000b\u0005\u0003g\u0014\t\tC\u0004\u0003xu\u0002\r!! \u0002\u0013M,GOV1mk\u0016DD\u0003BAz\u0005\u000fCqAa\u001e?\u0001\u0004\ti(A\u0004`m\u0006dW/Z\u001d\u0002\rY\fG.^3:+\t\t))A\u0005hKR4\u0016\r\\;fs\u0005Qa/\u00197vKfzF%Z9\u0015\t\u0005M(Q\u0013\u0005\b\u0005\u0017\u0013\u0005\u0019AAC\u0003%\u0019X\r\u001e,bYV,\u0017\b\u0006\u0003\u0002t\nm\u0005b\u0002BF\u0007\u0002\u0007\u0011QQ\u0001\t?Z\fG.^32a\u00059a/\u00197vKF\u0002TCAAG\u0003)9W\r\u001e,bYV,\u0017\u0007M\u0001\fm\u0006dW/Z\u00191?\u0012*\u0017\u000f\u0006\u0003\u0002t\n%\u0006b\u0002BP\u000f\u0002\u0007\u0011QR\u0001\u000bg\u0016$h+\u00197vKF\u0002D\u0003BAz\u0005_CqAa(I\u0001\u0004\ti)\u0001\u0005`m\u0006dW/Z\u00192\u0003\u001d1\u0018\r\\;fcE*\"!!&\u0002\u0015\u001d,GOV1mk\u0016\f\u0014\'A\u0006wC2,X-M\u0019`I\u0015\fH\u0003BAz\u0005{CqAa-M\u0001\u0004\t)*\u0001\u0006tKR4\u0016\r\\;fcE\"B!a=\u0003D\"9!1W\'A\u0002\u0005U\u0015\u0001C0wC2,X-\r\u001a\u0002\u000fY\fG.^32eU\u0011\u0011QT\u0001\u000bO\u0016$h+\u00197vKF\u0012\u0014a\u0003<bYV,\u0017GM0%KF$B!a=\u0003R\"9!qY)A\u0002\u0005u\u0015AC:fiZ\u000bG.^32eQ!\u00111\u001fBl\u0011\u001d\u00119M\u0015a\u0001\u0003;\u000b\u0001b\u0018<bYV,\u0017gM\u0001\bm\u0006dW/Z\u00194+\t\t)+\u0001\u0006hKR4\u0016\r\\;fcM\n1B^1mk\u0016\f4g\u0018\u0013fcR!\u00111\u001fBs\u0011\u001d\u0011YN\u0016a\u0001\u0003K\u000b!b]3u-\u0006dW/Z\u00194)\u0011\t\u0019Pa;\t\u000f\tmw\u000b1\u0001\u0002&\u0006AqL^1mk\u0016\fD\'A\u0004wC2,X-\r\u001b\u0016\u0005\u00055\u0016AC4fiZ\u000bG.^32i\u0005Ya/\u00197vKF\"t\fJ3r)\u0011\t\u0019P!?\t\u000f\t=8\f1\u0001\u0002.\u0006Q1/\u001a;WC2,X-\r\u001b\u0015\t\u0005M(q \u0005\b\u0005_d\u0006\u0019AAW\u0003!yf/\u00197vKF*\u0014a\u0002<bYV,\u0017\'N\u000b\u0003\u0003k\u000b!bZ3u-\u0006dW/Z\u00196\u0003-1\u0018\r\\;fcUzF%Z9\u0015\t\u0005M8Q\u0002\u0005\b\u0007\u0007\u0001\u0007\u0019AA[\u0003)\u0019X\r\u001e,bYV,\u0017\'\u000e\u000b\u0005\u0003g\u001c\u0019\u0002C\u0004\u0004\u0004\u0005\u0004\r!!.\u0002\u0011}3\u0018\r\\;fcY\nqA^1mk\u0016\fd\'\u0006\u0002\u0002>\u0006Qq-\u001a;WC2,X-\r\u001c\u0002\u0017Y\fG.^32m}#S-\u001d\u000b\u0005\u0003g\u001c\t\u0003C\u0004\u0004\u0018\u0015\u0004\r!!0\u0002\u0015M,GOV1mk\u0016\fd\u0007\u0006\u0003\u0002t\u000e\u001d\u0002bBB\fM\u0002\u0007\u0011QX\u0001\ti>\u001cFO]5oOR\u00111Q\u0006\t\u0005\u0007_\u0019I$\u0004\u0002\u00042)!11GB\u001b\u0003\u0011a\u0017M\\4\u000b\u0005\r]\u0012\u0001\u00026bm\u0006LAaa\u000f\u00042\t11\u000b\u001e:j]\u001e\faa\u001d;sS:<WCAB!!\u0011\tYaa\u0011\n\u0007\rmr0\u0001\u0005iCND7i\u001c3f)\t\u0019I\u0005\u0005\u0003\u0002\u0014\r-\u0013\u0002BB\'\u0003+\u00111!\u00138u\u0003\u0019)\u0017/^1mgR!11KB-!\u0011\t\u0019b!\u0016\n\t\r]\u0013Q\u0003\u0002\b\u0005>|G.Z1o\u0011\u001d\u0019YF\u001ba\u0001\u0003\u000b\n\u0011a\u001c\u000b#\u0003\u000b\u001cyf!\u0019\u0004d\r\u00154qMB5\u0007W\u001aiga\u001c\u0004r\rM4QOB<\u0007s\u001aYh! \t\u0013\u0005%8\u000e%AA\u0002\u0005U\u0002\"CA\u0000WB\u0005\t\u0019AA\'\u0011%\u0011\u0019b\u001bI\u0001\u0002\u0004\t)\u0006C\u0005\u0003(-\u0004\n\u00111\u0001\u0002^!I!1H6\u0011\u0002\u0003\u0007\u0011Q\r\u0005\n\u0005\u001fZ\u0007\u0013!a\u0001\u0003[B\u0011Ba\u0019l!\u0003\u0005\r!!\u001e\t\u0013\t]4\u000e%AA\u0002\u0005u\u0004\"\u0003BFWB\u0005\t\u0019AAC\u0011%\u0011yj\u001bI\u0001\u0002\u0004\ti\tC\u0005\u00034.\u0004\n\u00111\u0001\u0002\u0016\"I!qY6\u0011\u0002\u0003\u0007\u0011Q\u0014\u0005\n\u00057\\\u0007\u0013!a\u0001\u0003KC\u0011Ba<l!\u0003\u0005\r!!,\t\u0013\r\r1\u000e%AA\u0002\u0005U\u0006\"CB\fWB\u0005\t\u0019AA_\u0003=\t\u0007\u000f\u001d7zI\u0011,g-Y;mi\u0012\nTCABBU\u0011\t)d!\",\u0005\r\u001d\u0005\u0003BBE\u0007\'k!aa#\u000b\t\r55qR\u0001\nk:\u001c\u0007.Z2lK\u0012TAa!%\u0002\u0016\u0005Q\u0011M\u001c8pi\u0006$\u0018n\u001c8\n\t\rU51\u0012\u0002\u0012k:\u001c\u0007.Z2lK\u00124\u0016M]5b]\u000e,\u0017aD1qa2LH\u0005Z3gCVdG\u000f\n\u001a\u0016\u0005\rm%\u0006BA\'\u0007\u000b\u000bq\"\u00199qYf$C-\u001a4bk2$HeM\u000b\u0003\u0007CSC!!\u0016\u0004\u0006\u0006y\u0011\r\u001d9ms\u0012\"WMZ1vYR$C\'\u0006\u0002\u0004(*\"\u0011QLBC\u0003=\t\u0007\u000f\u001d7zI\u0011,g-Y;mi\u0012*TCABWU\u0011\t)g!\"\u0002\u001f\u0005\u0004\b\u000f\\=%I\u00164\u0017-\u001e7uIY*\"aa-+\t\u000554QQ\u0001\u0010CB\u0004H.\u001f\u0013eK\u001a\fW\u000f\u001c;%oU\u00111\u0011\u0018\u0016\u0005\u0003k\u001a))A\bbaBd\u0017\u0010\n3fM\u0006,H\u000e\u001e\u00139+\t\u0019yL\u000b\u0003\u0002~\r\u0015\u0015aD1qa2LH\u0005Z3gCVdG\u000fJ\u001d\u0016\u0005\r\u0015\'\u0006BAC\u0007\u000b\u000b\u0001#\u00199qYf$C-\u001a4bk2$H%\r\u0019\u0016\u0005\r-\'\u0006BAG\u0007\u000b\u000b\u0001#\u00199qYf$C-\u001a4bk2$H%M\u0019\u0016\u0005\rE\'\u0006BAK\u0007\u000b\u000b\u0001#\u00199qYf$C-\u001a4bk2$H%\r\u001a\u0016\u0005\r]\'\u0006BAO\u0007\u000b\u000b\u0001#\u00199qYf$C-\u001a4bk2$H%M\u001a\u0016\u0005\ru\'\u0006BAS\u0007\u000b\u000b\u0001#\u00199qYf$C-\u001a4bk2$H%\r\u001b\u0016\u0005\r\r(\u0006BAW\u0007\u000b\u000b\u0001#\u00199qYf$C-\u001a4bk2$H%M\u001b\u0016\u0005\r%(\u0006BA[\u0007\u000b\u000b\u0001#\u00199qYf$C-\u001a4bk2$H%\r\u001c\u0016\u0005\r=(\u0006BA_\u0007\u000b\u000b\u0001\u0002J2p]R,g\u000e^\u000b\u0003\u0007k\u0004baa>\u0005\b\u00115a\u0002BB}\t\u0007qAaa?\u0005\u00025\u00111Q \u0006\u0005\u0007\u007f\f9!\u0001\u0004=e>|GOP\u0005\u0003\u0003/IA\u0001\"\u0002\u0002\u0016\u00059\u0001/Y2lC\u001e,\u0017\u0002\u0002C\u0005\t\u0017\u00111aU3r\u0015\u0011!)!!\u0006\u0011\u0011\u0005MAqBB\u0017\u0003\u000bJA\u0001\"\u0005\u0002\u0016\t1A+\u001e9mKJ\na\u0001J2m_:,WCAAcQ\r)A\u0011\u0004\t\u0005\u0003\u0017!Y\"C\u0002\u0005\u001e}\u0014aA]3d_J$\u0007\u0003BA\u001c\tC!q!a\u000f\u0004\u0005\u0004\ti\u0004\u0005\u0003\u00028\u0011\u0015BaBA)\u0007\t\u0007\u0011Q\b\t\u0005\u0003o!I\u0003B\u0004\u0002Z\r\u0011\r!!\u0010\u0011\t\u0005]BQ\u0006\u0003\b\u0003C\u001a!\u0019AA\u001f!\u0011\t9\u0004\"\r\u0005\u000f\u0005%4A1\u0001\u0002>A!\u0011q\u0007C\u001b\t\u001d\t\th\u0001b\u0001\u0003{\u0001B!a\u000e\u0005:\u00119\u0011\u0011P\u0002C\u0002\u0005u\u0002\u0003BA\u001c\t{!q!!!\u0004\u0005\u0004\ti\u0004\u0005\u0003\u00028\u0011\u0005CaBAE\u0007\t\u0007\u0011Q\b\t\u0005\u0003o!)\u0005B\u0004\u0002\u0012\u000e\u0011\r!!\u0010\u0011\t\u0005]B\u0011\n\u0003\b\u00033\u001b!\u0019AA\u001f!\u0011\t9\u0004\"\u0014\u0005\u000f\u0005\u00056A1\u0001\u0002>A!\u0011q\u0007C)\t\u001d\tIk\u0001b\u0001\u0003{\u0001B!a\u000e\u0005V\u00119\u0011\u0011W\u0002C\u0002\u0005u\u0002\u0003BA\u001c\t3\"q!!/\u0004\u0005\u0004\ti\u0004\u0005\u0003\u00028\u0011uCaBAa\u0007\t\u0007\u0011Q\b\u0005\b\u0003S\u001c\u0001\u0019\u0001C\u0010\u0011\u001d\typ\u0001a\u0001\tGAqAa\u0005\u0004\u0001\u0004!9\u0003C\u0004\u0003(\r\u0001\r\u0001b\u000b\t\u000f\tm2\u00011\u0001\u00050!9!qJ\u0002A\u0002\u0011M\u0002b\u0002B2\u0007\u0001\u0007Aq\u0007\u0005\b\u0005o\u001a\u0001\u0019\u0001C\u001e\u0011\u001d\u0011Yi\u0001a\u0001\t\u007fAqAa(\u0004\u0001\u0004!\u0019\u0005C\u0004\u00034\u000e\u0001\r\u0001b\u0012\t\u000f\t\u001d7\u00011\u0001\u0005L!9!1\\\u0002A\u0002\u0011=\u0003b\u0002Bx\u0007\u0001\u0007A1\u000b\u0005\b\u0007\u0007\u0019\u0001\u0019\u0001C,\u0011\u001d\u00199b\u0001a\u0001\t7\nq!\u001e8baBd\u00170\u0006\u0012\u0005\u0004\u0012MEq\u0013CN\t?#\u0019\u000bb*\u0005,\u0012=F1\u0017C\\\tw#y\fb1\u0005H\u0012-Gq\u001a\u000b\u0005\t\u000b#\t\u000e\u0005\u0004\u0002\u0014\u0011\u001dE1R\u0005\u0005\t\u0013\u000b)B\u0001\u0003T_6,\u0007\u0003JA\n\t\u001b#\t\n\"&\u0005\u001a\u0012uE\u0011\u0015CS\tS#i\u000b\"-\u00056\u0012eFQ\u0018Ca\t\u000b$I\r\"4\n\t\u0011=\u0015Q\u0003\u0002\b)V\u0004H.Z\u00197!\u0011\t9\u0004b%\u0005\u000f\u0005mBA1\u0001\u0002>A!\u0011q\u0007CL\t\u001d\t\t\u0006\u0002b\u0001\u0003{\u0001B!a\u000e\u0005\u001c\u00129\u0011\u0011\f\u0003C\u0002\u0005u\u0002\u0003BA\u001c\t?#q!!\u0019\u0005\u0005\u0004\ti\u0004\u0005\u0003\u00028\u0011\rFaBA5\t\t\u0007\u0011Q\b\t\u0005\u0003o!9\u000bB\u0004\u0002r\u0011\u0011\r!!\u0010\u0011\t\u0005]B1\u0016\u0003\b\u0003s\"!\u0019AA\u001f!\u0011\t9\u0004b,\u0005\u000f\u0005\u0005EA1\u0001\u0002>A!\u0011q\u0007CZ\t\u001d\tI\t\u0002b\u0001\u0003{\u0001B!a\u000e\u00058\u00129\u0011\u0011\u0013\u0003C\u0002\u0005u\u0002\u0003BA\u001c\tw#q!!\'\u0005\u0005\u0004\ti\u0004\u0005\u0003\u00028\u0011}FaBAQ\t\t\u0007\u0011Q\b\t\u0005\u0003o!\u0019\rB\u0004\u0002*\u0012\u0011\r!!\u0010\u0011\t\u0005]Bq\u0019\u0003\b\u0003c#!\u0019AA\u001f!\u0011\t9\u0004b3\u0005\u000f\u0005eFA1\u0001\u0002>A!\u0011q\u0007Ch\t\u001d\t\t\r\u0002b\u0001\u0003{Aqaa\u0017\u0005\u0001\u0004!\u0019\u000eE\u0012\u0002\f\u0015!\t\n\"&\u0005\u001a\u0012uE\u0011\u0015CS\tS#i\u000b\"-\u00056\u0012eFQ\u0018Ca\t\u000b$I\r\"4"
    )
  ScalaInlineInfo: length = 0x1F3 (unknown attribute)
   01 01 00 63 00 50 00 51 01 01 AD 00 67 01 01 AD
   01 BF 01 01 AD 01 AE 01 01 7E 01 7F 01 00 58 00
   3D 01 00 5D 00 3D 01 00 3C 00 3D 01 00 43 01 BA
   01 00 43 00 44 01 00 F2 01 6B 01 01 32 01 69 01
   01 6E 00 67 01 01 77 00 67 01 01 78 00 67 01 01
   79 00 67 01 01 7A 00 67 01 01 7B 00 67 01 01 7C
   00 67 01 01 7D 00 67 01 01 6F 00 67 01 01 70 00
   67 01 01 71 00 67 01 01 72 00 67 01 01 73 00 67
   01 01 74 00 67 01 01 75 00 67 01 01 76 00 67 01
   01 5F 01 60 01 00 6B 00 67 01 00 B4 00 67 01 00
   BC 00 67 01 00 C4 00 67 01 00 CC 00 67 01 00 D4
   00 67 01 00 DC 00 67 01 00 E4 00 67 01 00 74 00
   67 01 00 7C 00 67 01 00 84 00 67 01 00 8C 00 67
   01 00 94 00 67 01 00 9C 00 67 01 00 A4 00 67 01
   00 AC 00 67 01 00 4A 00 4B 01 01 36 01 37 01 00
   2D 00 3D 01 00 63 00 64 01 00 6F 00 6D 01 00 B7
   00 6D 01 00 BF 00 6D 01 00 C7 00 6D 01 00 CF 00
   6D 01 00 D7 00 6D 01 00 DF 00 6D 01 00 E7 00 6D
   01 00 77 00 6D 01 00 7F 00 6D 01 00 87 00 6D 01
   00 8F 00 6D 01 00 97 00 6D 01 00 9F 00 6D 01 00
   A7 00 6D 01 00 AF 00 6D 01 01 30 00 E9 01 00 E8
   00 E9 01 00 66 00 67 01 00 B0 00 67 01 00 B5 00
   6D 01 00 B8 00 67 01 00 BD 00 6D 01 00 C0 00 67
   01 00 C5 00 6D 01 00 C8 00 67 01 00 CD 00 6D 01
   00 D0 00 67 01 00 D5 00 6D 01 00 D8 00 67 01 00
   DD 00 6D 01 00 E0 00 67 01 00 E5 00 6D 01 00 6C
   00 6D 01 00 70 00 67 01 00 75 00 6D 01 00 78 00
   67 01 00 7D 00 6D 01 00 80 00 67 01 00 85 00 6D
   01 00 88 00 67 01 00 8D 00 6D 01 00 90 00 67 01
   00 95 00 6D 01 00 98 00 67 01 00 9D 00 6D 01 00
   A0 00 67 01 00 A5 00 6D 01 00 A8 00 67 01 00 AD
   00 6D 01
  ScalaSig: length = 0x3 (unknown attribute)
   05 02 00
