Classfile /Users/mw/Projects/slang-braindump/.jar/jar8/assemble/slang-braindump/assemble/content/org/sireum/MBox21.class
  Last modified May 29, 2022; size 32383 bytes
  SHA-256 checksum 8a94c59a40d417c0821577fa98e057a0ceaa66ed1e9489fe1913e68b3d7edd6a
  Compiled from "MBox.scala"
public final class org.sireum.MBox21<T1 extends java.lang.Object, T2 extends java.lang.Object, T3 extends java.lang.Object, T4 extends java.lang.Object, T5 extends java.lang.Object, T6 extends java.lang.Object, T7 extends java.lang.Object, T8 extends java.lang.Object, T9 extends java.lang.Object, T10 extends java.lang.Object, T11 extends java.lang.Object, T12 extends java.lang.Object, T13 extends java.lang.Object, T14 extends java.lang.Object, T15 extends java.lang.Object, T16 extends java.lang.Object, T17 extends java.lang.Object, T18 extends java.lang.Object, T19 extends java.lang.Object, T20 extends java.lang.Object, T21 extends java.lang.Object> extends java.lang.Object implements org.sireum.RecordSig
  minor version: 0
  major version: 52
  flags: (0x0031) ACC_PUBLIC, ACC_FINAL, ACC_SUPER
  this_class: #2                          // org/sireum/MBox21
  super_class: #5                         // java/lang/Object
  interfaces: 1, fields: 22, methods: 125, attributes: 5
Constant pool:
    #1 = Utf8               org/sireum/MBox21
    #2 = Class              #1            // org/sireum/MBox21
    #3 = Utf8               <T1:Ljava/lang/Object;T2:Ljava/lang/Object;T3:Ljava/lang/Object;T4:Ljava/lang/Object;T5:Ljava/lang/Object;T6:Ljava/lang/Object;T7:Ljava/lang/Object;T8:Ljava/lang/Object;T9:Ljava/lang/Object;T10:Ljava/lang/Object;T11:Ljava/lang/Object;T12:Ljava/lang/Object;T13:Ljava/lang/Object;T14:Ljava/lang/Object;T15:Ljava/lang/Object;T16:Ljava/lang/Object;T17:Ljava/lang/Object;T18:Ljava/lang/Object;T19:Ljava/lang/Object;T20:Ljava/lang/Object;T21:Ljava/lang/Object;>Ljava/lang/Object;Lorg/sireum/RecordSig;
    #4 = Utf8               java/lang/Object
    #5 = Class              #4            // java/lang/Object
    #6 = Utf8               org/sireum/RecordSig
    #7 = Class              #6            // org/sireum/RecordSig
    #8 = Utf8               MBox.scala
    #9 = Utf8               Lscala/reflect/ScalaSignature;
   #10 = Utf8               bytes
   #11 = Utf8               \u0006\u0005\u0019-q\u0001CA\"\u0003\u000bB\t!a\u0014\u0007\u0011\u0005M\u0013Q\tE\u0001\u0003+Bq!a\u0019\u0002\t\u0003\t)\u0007C\u0004\u0002h\u0005!\t!!\u001b\t\u000f\u0015\u0005\u0016\u0001\"\u0001\u0006$\u001a9\u00111KA#\u0005\u0005=\u0004BCA=\u000b\t\u0005\t\u0015!\u0003\u0002|!Q\u0011\u0011S\u0003\u0003\u0002\u0003\u0006I!a%\t\u0015\u0005eUA!A!\u0002\u0013\tY\n\u0003\u0006\u0002\"\u0016\u0011\t\u0011)A\u0005\u0003GC!\"!+\u0006\u0005\u0003\u0005\u000b\u0011BAV\u0011)\t\t,\u0002B\u0001B\u0003%\u00111\u0017\u0005\u000b\u0003s+!\u0011!Q\u0001\n\u0005m\u0006BCAa\u000b\t\u0005\t\u0015!\u0003\u0002D\"Q\u0011\u0011Z\u0003\u0003\u0002\u0003\u0006I!a3\t\u0015\u0005EWA!A!\u0002\u0013\t\u0019\u000e\u0003\u0006\u0002Z\u0016\u0011\t\u0011)A\u0005\u00037D!\"!9\u0006\u0005\u0003\u0005\u000b\u0011BAr\u0011)\tI/\u0002B\u0001B\u0003%\u00111\u001e\u0005\u000b\u0003c,!\u0011!Q\u0001\n\u0005M\bBCA}\u000b\t\u0005\t\u0015!\u0003\u0002|\"Q!\u0011A\u0003\u0003\u0002\u0003\u0006IAa\u0001\t\u0015\t%QA!A!\u0002\u0013\u0011Y\u0001\u0003\u0006\u0003\u0012\u0015\u0011\t\u0011)A\u0005\u0005\'A!B!\u0007\u0006\u0005\u0003\u0005\u000b\u0011\u0002B\u000e\u0011)\u0011\t#\u0002B\u0001B\u0003%!1\u0005\u0005\u000b\u0005S)!\u0011!Q\u0001\n\t-\u0002bBA2\u000b\u0011\u0005!\u0011\u0007\u0005\t\u0005?*\u0001\u0015)\u0003\u0002|!9!\u0011M\u0003\u0005\u0002\t\r\u0004b\u0002B3\u000b\u0011\u0005!1\r\u0005\b\u0005O*A\u0011\u0001B5\u0011\u001d\u0011y\'\u0002C\u0001\u0005cB\u0001B!\u001e\u0006A\u0003&\u00111\u0013\u0005\b\u0005o*A\u0011\u0001B=\u0011\u001d\u0011Y(\u0002C\u0001\u0005sBqA! \u0006\t\u0003\u0011y\bC\u0004\u0003\u0004\u0016!\tA!\"\t\u0011\t%U\u0001)Q\u0005\u00037CqAa#\u0006\t\u0003\u0011i\tC\u0004\u0003\u0010\u0016!\tA!$\t\u000f\tEU\u0001\"\u0001\u0003\u0014\"9!qS\u0003\u0005\u0002\te\u0005\u0002\u0003BO\u000b\u0001\u0006K!a)\t\u000f\t}U\u0001\"\u0001\u0003\"\"9!1U\u0003\u0005\u0002\t\u0005\u0006b\u0002BS\u000b\u0011\u0005!q\u0015\u0005\b\u0005W+A\u0011\u0001BW\u0011!\u0011\t,\u0002Q!\n\u0005-\u0006b\u0002BZ\u000b\u0011\u0005!Q\u0017\u0005\b\u0005o+A\u0011\u0001B[\u0011\u001d\u0011I,\u0002C\u0001\u0005wCqAa0\u0006\t\u0003\u0011\t\r\u0003\u0005\u0003F\u0016\u0001\u000b\u0015BAZ\u0011\u001d\u00119-\u0002C\u0001\u0005\u0013DqAa3\u0006\t\u0003\u0011I\rC\u0004\u0003N\u0016!\tAa4\t\u000f\tMW\u0001\"\u0001\u0003V\"A!\u0011\\\u0003!B\u0013\tY\fC\u0004\u0003\\\u0016!\tA!8\t\u000f\t}W\u0001\"\u0001\u0003^\"9!\u0011]\u0003\u0005\u0002\t\r\bb\u0002Bt\u000b\u0011\u0005!\u0011\u001e\u0005\t\u0005[,\u0001\u0015)\u0003\u0002D\"9!q^\u0003\u0005\u0002\tE\bb\u0002Bz\u000b\u0011\u0005!\u0011\u001f\u0005\b\u0005k,A\u0011\u0001B|\u0011\u001d\u0011Y0\u0002C\u0001\u0005{D\u0001b!\u0001\u0006A\u0003&\u00111\u001a\u0005\b\u0007\u0007)A\u0011AB\u0003\u0011\u001d\u00199!\u0002C\u0001\u0007\u000bAqa!\u0003\u0006\t\u0003\u0019Y\u0001C\u0004\u0004\u0010\u0015!\ta!\u0005\t\u0011\rUQ\u0001)Q\u0005\u0003\'Dqaa\u0006\u0006\t\u0003\u0019I\u0002C\u0004\u0004\u001c\u0015!\ta!\u0007\t\u000f\ruQ\u0001\"\u0001\u0004 !911E\u0003\u0005\u0002\r\u0015\u0002\u0002CB\u0015\u000b\u0001\u0006K!a7\t\u000f\r-R\u0001\"\u0001\u0004.!91qF\u0003\u0005\u0002\r5\u0002bBB\u0019\u000b\u0011\u000511\u0007\u0005\b\u0007o)A\u0011AB\u001d\u0011!\u0019i$\u0002Q!\n\u0005\r\bbBB \u000b\u0011\u00051\u0011\t\u0005\b\u0007\u0007*A\u0011AB!\u0011\u001d\u0019)%\u0002C\u0001\u0007\u000fBqaa\u0013\u0006\t\u0003\u0019i\u0005\u0003\u0005\u0004R\u0015\u0001\u000b\u0015BAv\u0011\u001d\u0019\u0019&\u0002C\u0001\u0007+Bqaa\u0016\u0006\t\u0003\u0019)\u0006C\u0004\u0004Z\u0015!\taa\u0017\t\u000f\r}S\u0001\"\u0001\u0004b!A1QM\u0003!B\u0013\t\u0019\u0010C\u0004\u0004h\u0015!\ta!\u001b\t\u000f\r-T\u0001\"\u0001\u0004j!91QN\u0003\u0005\u0002\r=\u0004bBB:\u000b\u0011\u00051Q\u000f\u0005\t\u0007s*\u0001\u0015)\u0003\u0002|\"911P\u0003\u0005\u0002\ru\u0004bBB@\u000b\u0011\u00051Q\u0010\u0005\b\u0007\u0003+A\u0011ABB\u0011\u001d\u00199)\u0002C\u0001\u0007\u0013C\u0001b!$\u0006A\u0003&!1\u0001\u0005\b\u0007\u001f+A\u0011ABI\u0011\u001d\u0019\u0019*\u0002C\u0001\u0007#Cqa!&\u0006\t\u0003\u00199\nC\u0004\u0004\u001c\u0016!\ta!(\t\u0011\r\u0005V\u0001)Q\u0005\u0005\u0017Aqaa)\u0006\t\u0003\u0019)\u000bC\u0004\u0004(\u0016!\ta!*\t\u000f\r%V\u0001\"\u0001\u0004,\"91qV\u0003\u0005\u0002\rE\u0006\u0002CB[\u000b\u0001\u0006KAa\u0005\t\u000f\r]V\u0001\"\u0001\u0004:\"911X\u0003\u0005\u0002\re\u0006bBB_\u000b\u0011\u00051q\u0018\u0005\b\u0007\u0007,A\u0011ABc\u0011!\u0019I-\u0002Q!\n\tm\u0001bBBf\u000b\u0011\u00051Q\u001a\u0005\b\u0007\u001f,A\u0011ABg\u0011\u001d\u0019\t.\u0002C\u0001\u0007\'Dqaa6\u0006\t\u0003\u0019I\u000e\u0003\u0005\u0004^\u0016\u0001\u000b\u0015\u0002B\u0012\u0011\u001d\u0019y.\u0002C\u0001\u0007CDqaa9\u0006\t\u0003\u0019\t\u000fC\u0004\u0004f\u0016!\taa:\t\u000f\r-X\u0001\"\u0001\u0004n\"A1\u0011_\u0003!B\u0013\u0011Y\u0003C\u0004\u0004t\u0016!\ta!>\t\u000f\r]X\u0001\"\u0001\u0004v\"91\u0011`\u0003\u0005\u0002\rm\bbBB\u0000\u000b\u0011\u0005A\u0011\u0001\u0005\b\t\u000b)A\u0011\tC\u0004\u0011\u001d!I\"\u0002C!\t7Aq\u0001\"\t\u0006\t\u0003\"\u0019\u0003C\u0004\u0005,\u0015!\t\u0005\"\f\t\u000f\u0005\u001dT\u0001\"\u0001\u0005:!IAQM\u0003\u0012\u0002\u0013\u0005Aq\r\u0005\n\t{*\u0011\u0013!C\u0001\t\u007fB\u0011\u0002b!\u0006#\u0003%\t\u0001\"\"\t\u0013\u0011%U!%A\u0005\u0002\u0011-\u0005\"\u0003CH\u000bE\u0005I\u0011\u0001CI\u0011%!)*BI\u0001\n\u0003!9\nC\u0005\u0005\u001c\u0016\t\n\u0011\"\u0001\u0005\u001e\"IA\u0011U\u0003\u0012\u0002\u0013\u0005A1\u0015\u0005\n\tO+\u0011\u0013!C\u0001\tSC\u0011\u0002\",\u0006#\u0003%\t\u0001b,\t\u0013\u0011MV!%A\u0005\u0002\u0011U\u0006\"\u0003C]\u000bE\u0005I\u0011\u0001C^\u0011%!y,BI\u0001\n\u0003!\t\rC\u0005\u0005F\u0016\t\n\u0011\"\u0001\u0005H\"IA1Z\u0003\u0012\u0002\u0013\u0005AQ\u001a\u0005\n\t#,\u0011\u0013!C\u0001\t\'D\u0011\u0002b6\u0006#\u0003%\t\u0001\"7\t\u0013\u0011uW!%A\u0005\u0002\u0011}\u0007\"\u0003Cr\u000bE\u0005I\u0011\u0001Cs\u0011%!I/BI\u0001\n\u0003!Y\u000fC\u0005\u0005p\u0016\t\n\u0011\"\u0001\u0005r\"9AQ_\u0003\u0005B\u0011]\bbBC\f\u000b\u0011\u0005S\u0011D\u0001\u0007\u001b\n{\u0007PM\u0019\u000b\t\u0005\u001d\u0013\u0011J\u0001\u0007g&\u0014X-^7\u000b\u0005\u0005-\u0013aA8sO\u000e\u0001\u0001cAA)\u00035\u0011\u0011Q\t\u0002\u0007\u001b\n{\u0007PM\u0019\u0014\u0007\u0005\t9\u0006\u0005\u0003\u0002Z\u0005}SBAA.\u0015\t\ti&A\u0003tG\u0006d\u0017-\u0003\u0003\u0002b\u0005m#AB!osJ+g-\u0001\u0004=S:LGO\u0010\u000b\u0003\u0003\u001f\nQ!\u00199qYf,B&a\u001b\u0006&\u0015%RQFC\u0019\u000bk)I$\"\u0010\u0006B\u0015\u0015S\u0011JC\'\u000b#*)&\"\u0017\u0006^\u0015\u0005TQMC5\u000b[*\t(\"\u001e\u0015Y\u00055TqOC=\u000bw*i(b \u0006\u0002\u0016\rUQQCD\u000b\u0013+Y)\"$\u0006\u0010\u0016EU1SCK\u000b/+I*b\'\u0006\u001e\u0016}\u0005#LA)\u000b\u0015\rRqEC\u0016\u000b_)\u0019$b\u000e\u0006<\u0015}R1IC$\u000b\u0017*y%b\u0015\u0006X\u0015mSqLC2\u000bO*Y\'b\u001c\u0006tUa\u0013\u0011OA@\u0003+\u000bi*!*\u0002.\u0006U\u0016QXAc\u0003\u001b\f).!8\u0002f\u00065\u0018Q_A\u007f\u0005\u000b\u0011iA!\u0006\u0003\u001e\t\u0015\"QF\n\u0006\u000b\u0005]\u00131\u000f\t\u0005\u0003#\n)(\u0003\u0003\u0002x\u0005\u0015#!\u0003*fG>\u0014HmU5h\u0003!yvL^1mk\u0016\f\u0004\u0003BA?\u0003\u007fb\u0001\u0001B\u0004\u0002\u0002\u0016\u0011\r!a!\u0003\u0005Q\u000b\u0014\u0003BAC\u0003\u0017\u0003B!!\u0017\u0002\b&!\u0011\u0011RA.\u0005\u001dqu\u000e\u001e5j]\u001e\u0004B!!\u0017\u0002\u000e&!\u0011qRA.\u0005\r\te._\u0001\t?~3\u0018\r\\;feA!\u0011QPAK\t\u001d\t9*\u0002b\u0001\u0003\u0007\u0013!\u0001\u0016\u001a\u0002\u0011}{f/\u00197vKN\u0002B!! \u0002\u001e\u00129\u0011qT\u0003C\u0002\u0005\r%A\u0001+4\u0003!yvL^1mk\u0016$\u0004\u0003BA?\u0003K#q!a*\u0006\u0005\u0004\t\u0019I\u0001\u0002Ui\u0005Aql\u0018<bYV,W\u0007\u0005\u0003\u0002~\u00055FaBAX\u000b\t\u0007\u00111\u0011\u0002\u0003)V\n\u0001bX0wC2,XM\u000e\t\u0005\u0003{\n)\fB\u0004\u00028\u0016\u0011\r!a!\u0003\u0005Q3\u0014\u0001C0`m\u0006dW/Z\u001c\u0011\t\u0005u\u0014Q\u0018\u0003\b\u0003\u007f+!\u0019AAB\u0005\t!v\'\u0001\u0005`?Z\fG.^39!\u0011\ti(!2\u0005\u000f\u0005\u001dWA1\u0001\u0002\u0004\n\u0011A\u000bO\u0001\t?~3\u0018\r\\;fsA!\u0011QPAg\t\u001d\ty-\u0002b\u0001\u0003\u0007\u0013!\u0001V\u001d\u0002\u0013}{f/\u00197vKF\u0002\u0004\u0003BA?\u0003+$q!a6\u0006\u0005\u0004\t\u0019IA\u0002UcA\n\u0011bX0wC2,X-M\u0019\u0011\t\u0005u\u0014Q\u001c\u0003\b\u0003?,!\u0019AAB\u0005\r!\u0016\'M\u0001\n?~3\u0018\r\\;fcI\u0002B!! \u0002f\u00129\u0011q]\u0003C\u0002\u0005\r%a\u0001+2e\u0005Iql\u0018<bYV,\u0017g\r\t\u0005\u0003{\ni\u000fB\u0004\u0002p\u0016\u0011\r!a!\u0003\u0007Q\u000b4\'A\u0005`?Z\fG.^32iA!\u0011QPA{\t\u001d\t90\u0002b\u0001\u0003\u0007\u00131\u0001V\u00195\u0003%yvL^1mk\u0016\fT\u0007\u0005\u0003\u0002~\u0005uHaBA\u0000\u000b\t\u0007\u00111\u0011\u0002\u0004)F*\u0014!C0`m\u0006dW/Z\u00197!\u0011\tiH!\u0002\u0005\u000f\t\u001dQA1\u0001\u0002\u0004\n\u0019A+\r\u001c\u0002\u0013}{f/\u00197vKF:\u0004\u0003BA?\u0005\u001b!qAa\u0004\u0006\u0005\u0004\t\u0019IA\u0002Uc]\n\u0011bX0wC2,X-\r\u001d\u0011\t\u0005u$Q\u0003\u0003\b\u0005/)!\u0019AAB\u0005\r!\u0016\u0007O\u0001\n?~3\u0018\r\\;fce\u0002B!! \u0003\u001e\u00119!qD\u0003C\u0002\u0005\r%a\u0001+2s\u0005Iql\u0018<bYV,\'\u0007\r\t\u0005\u0003{\u0012)\u0003B\u0004\u0003(\u0015\u0011\r!a!\u0003\u0007Q\u0013\u0004\'A\u0005`?Z\fG.^33cA!\u0011Q\u0010B\u0017\t\u001d\u0011y#\u0002b\u0001\u0003\u0007\u00131\u0001\u0016\u001a2)1\u0012\u0019D!\u000e\u00038\te\"1\bB\u001f\u0005\u007f\u0011\tEa\u0011\u0003F\t\u001d#\u0011\nB&\u0005\u001b\u0012yE!\u0015\u0003T\tU#q\u000bB-\u00057\u0012i\u0006E\u0017\u0002R\u0015\tY(a%\u0002\u001c\u0006\r\u00161VAZ\u0003w\u000b\u0019-a3\u0002T\u0006m\u00171]Av\u0003g\fYPa\u0001\u0003\f\tM!1\u0004B\u0012\u0005WAq!!\u001f\u001c\u0001\u0004\tY\bC\u0004\u0002\u0012n\u0001\r!a%\t\u000f\u0005e5\u00041\u0001\u0002\u001c\"9\u0011\u0011U\u000eA\u0002\u0005\r\u0006bBAU7\u0001\u0007\u00111\u0016\u0005\b\u0003c[\u0002\u0019AAZ\u0011\u001d\tIl\u0007a\u0001\u0003wCq!!1\u001c\u0001\u0004\t\u0019\rC\u0004\u0002Jn\u0001\r!a3\t\u000f\u0005E7\u00041\u0001\u0002T\"9\u0011\u0011\\\u000eA\u0002\u0005m\u0007bBAq7\u0001\u0007\u00111\u001d\u0005\b\u0003S\\\u0002\u0019AAv\u0011\u001d\t\tp\u0007a\u0001\u0003gDq!!?\u001c\u0001\u0004\tY\u0010C\u0004\u0003\u0002m\u0001\rAa\u0001\t\u000f\t%1\u00041\u0001\u0003\f!9!\u0011C\u000eA\u0002\tM\u0001b\u0002B\r7\u0001\u0007!1\u0004\u0005\b\u0005CY\u0002\u0019\u0001B\u0012\u0011\u001d\u0011Ic\u0007a\u0001\u0005W\tqa\u0018<bYV,\u0017\'\u0001\u0004wC2,X-M\u000b\u0003\u0003w\n\u0011bZ3u-\u0006dW/Z\u0019\u0002\u0015Y\fG.^32?\u0012*\u0017\u000f\u0006\u0003\u0003l\t5T\"A\u0003\t\u000f\t\u0005t\u00041\u0001\u0002|\u0005I1/\u001a;WC2,X-\r\u000b\u0005\u0005W\u0012\u0019\bC\u0004\u0003b\u0001\u0002\r!a\u001f\u0002\u000f}3\u0018\r\\;fe\u00051a/\u00197vKJ*\"!a%\u0002\u0013\u001d,GOV1mk\u0016\u0014\u0014A\u0003<bYV,\'g\u0018\u0013fcR!!1\u000eBA\u0011\u001d\u00119\b\na\u0001\u0003\'\u000b\u0011b]3u-\u0006dW/\u001a\u001a\u0015\t\t-$q\u0011\u0005\b\u0005o*\u0003\u0019AAJ\u0003\u001dyf/\u00197vKN\naA^1mk\u0016\u001cTCAAN\u0003%9W\r\u001e,bYV,7\'\u0001\u0006wC2,XmM0%KF$BAa\u001b\u0003\u0016\"9!1R\u0015A\u0002\u0005m\u0015!C:fiZ\u000bG.^34)\u0011\u0011YGa\'\t\u000f\t-%\u00061\u0001\u0002\u001c\u00069qL^1mk\u0016$\u0014A\u0002<bYV,G\'\u0006\u0002\u0002$\u0006Iq-\u001a;WC2,X\rN\u0001\u000bm\u0006dW/\u001a\u001b`I\u0015\fH\u0003\u0002B6\u0005SCqAa(/\u0001\u0004\t\u0019+A\u0005tKR4\u0016\r\\;fiQ!!1\u000eBX\u0011\u001d\u0011yj\fa\u0001\u0003G\u000bqa\u0018<bYV,W\'\u0001\u0004wC2,X-N\u000b\u0003\u0003W\u000b\u0011bZ3u-\u0006dW/Z\u001b\u0002\u0015Y\fG.^36?\u0012*\u0017\u000f\u0006\u0003\u0003l\tu\u0006b\u0002BZg\u0001\u0007\u00111V\u0001\ng\u0016$h+\u00197vKV\"BAa\u001b\u0003D\"9!1\u0017\u001bA\u0002\u0005-\u0016aB0wC2,XMN\u0001\u0007m\u0006dW/\u001a\u001c\u0016\u0005\u0005M\u0016!C4fiZ\u000bG.^37\u0003)1\u0018\r\\;fm}#S-\u001d\u000b\u0005\u0005W\u0012\t\u000eC\u0004\u0003Hb\u0002\r!a-\u0002\u0013M,GOV1mk\u00164D\u0003\u0002B6\u0005/DqAa2:\u0001\u0004\t\u0019,A\u0004`m\u0006dW/Z\u001c\u0002\rY\fG.^38+\t\tY,A\u0005hKR4\u0016\r\\;fo\u0005Qa/\u00197vK^zF%Z9\u0015\t\t-$Q\u001d\u0005\b\u00057l\u0004\u0019AA^\u0003%\u0019X\r\u001e,bYV,w\u0007\u0006\u0003\u0003l\t-\bb\u0002Bn}\u0001\u0007\u00111X\u0001\b?Z\fG.^39\u0003\u00191\u0018\r\\;fqU\u0011\u00111Y\u0001\nO\u0016$h+\u00197vKb\n!B^1mk\u0016Dt\fJ3r)\u0011\u0011YG!?\t\u000f\t=(\t1\u0001\u0002D\u0006I1/\u001a;WC2,X\r\u000f\u000b\u0005\u0005W\u0012y\u0010C\u0004\u0003p\u000e\u0003\r!a1\u0002\u000f}3\u0018\r\\;fs\u00051a/\u00197vKf*\"!a3\u0002\u0013\u001d,GOV1mk\u0016L\u0014A\u0003<bYV,\u0017h\u0018\u0013fcR!!1NB\u0007\u0011\u001d\u0019\u0019a\u0012a\u0001\u0003\u0017\f\u0011b]3u-\u0006dW/Z\u001d\u0015\t\t-41\u0003\u0005\b\u0007\u0007A\u0005\u0019AAf\u0003!yf/\u00197vKF\u0002\u0014a\u0002<bYV,\u0017\u0007M\u000b\u0003\u0003\'\f!bZ3u-\u0006dW/Z\u00191\u0003-1\u0018\r\\;fcAzF%Z9\u0015\t\t-4\u0011\u0005\u0005\b\u0007/a\u0005\u0019AAj\u0003)\u0019X\r\u001e,bYV,\u0017\u0007\r\u000b\u0005\u0005W\u001a9\u0003C\u0004\u0004\u00185\u0003\r!a5\u0002\u0011}3\u0018\r\\;fcE\nqA^1mk\u0016\f\u0014\'\u0006\u0002\u0002\\\u0006Qq-\u001a;WC2,X-M\u0019\u0002\u0017Y\fG.^32c}#S-\u001d\u000b\u0005\u0005W\u001a)\u0004C\u0004\u0004,E\u0003\r!a7\u0002\u0015M,GOV1mk\u0016\f\u0014\u0007\u0006\u0003\u0003l\rm\u0002bBB\u0016%\u0002\u0007\u00111\\\u0001\t?Z\fG.^32e\u00059a/\u00197vKF\u0012TCAAr\u0003)9W\r\u001e,bYV,\u0017GM\u0001\fm\u0006dW/Z\u00193?\u0012*\u0017\u000f\u0006\u0003\u0003l\r%\u0003bBB -\u0002\u0007\u00111]\u0001\u000bg\u0016$h+\u00197vKF\u0012D\u0003\u0002B6\u0007\u001fBqaa\u0010X\u0001\u0004\t\u0019/\u0001\u0005`m\u0006dW/Z\u00194\u0003\u001d1\u0018\r\\;fcM*\"!a;\u0002\u0015\u001d,GOV1mk\u0016\f4\'A\u0006wC2,X-M\u001a`I\u0015\fH\u0003\u0002B6\u0007;Bqaa\u0015\\\u0001\u0004\tY/\u0001\u0006tKR4\u0016\r\\;fcM\"BAa\u001b\u0004d!911\u000b/A\u0002\u0005-\u0018\u0001C0wC2,X-\r\u001b\u0002\u000fY\fG.^32iU\u0011\u00111_\u0001\u000bO\u0016$h+\u00197vKF\"\u0014a\u0003<bYV,\u0017\u0007N0%KF$BAa\u001b\u0004r!91q\r1A\u0002\u0005M\u0018AC:fiZ\u000bG.^32iQ!!1NB<\u0011\u001d\u00199\'\u0019a\u0001\u0003g\f\u0001b\u0018<bYV,\u0017\'N\u0001\bm\u0006dW/Z\u00196+\t\tY0\u0001\u0006hKR4\u0016\r\\;fcU\n1B^1mk\u0016\fTg\u0018\u0013fcR!!1NBC\u0011\u001d\u0019Y(\u001aa\u0001\u0003w\f!b]3u-\u0006dW/Z\u00196)\u0011\u0011Yga#\t\u000f\rmd\r1\u0001\u0002|\u0006AqL^1mk\u0016\fd\'A\u0004wC2,X-\r\u001c\u0016\u0005\t\r\u0011AC4fiZ\u000bG.^32m\u0005Ya/\u00197vKF2t\fJ3r)\u0011\u0011Yg!\'\t\u000f\r=%\u000e1\u0001\u0003\u0004\u0005Q1/\u001a;WC2,X-\r\u001c\u0015\t\t-4q\u0014\u0005\b\u0007\u001f[\u0007\u0019\u0001B\u0002\u0003!yf/\u00197vKF:\u0014a\u0002<bYV,\u0017gN\u000b\u0003\u0005\u0017\t!bZ3u-\u0006dW/Z\u00198\u0003-1\u0018\r\\;fc]zF%Z9\u0015\t\t-4Q\u0016\u0005\b\u0007G{\u0007\u0019\u0001B\u0006\u0003)\u0019X\r\u001e,bYV,\u0017g\u000e\u000b\u0005\u0005W\u001a\u0019\fC\u0004\u0004$B\u0004\rAa\u0003\u0002\u0011}3\u0018\r\\;fca\nqA^1mk\u0016\f\u0004(\u0006\u0002\u0003\u0014\u0005Qq-\u001a;WC2,X-\r\u001d\u0002\u0017Y\fG.^32q}#S-\u001d\u000b\u0005\u0005W\u001a\t\rC\u0004\u00048R\u0004\rAa\u0005\u0002\u0015M,GOV1mk\u0016\f\u0004\b\u0006\u0003\u0003l\r\u001d\u0007bBB\\k\u0002\u0007!1C\u0001\t?Z\fG.^32s\u00059a/\u00197vKFJTC\u0001B\u000e\u0003)9W\r\u001e,bYV,\u0017\'O\u0001\fm\u0006dW/Z\u0019:?\u0012*\u0017\u000f\u0006\u0003\u0003l\rU\u0007bBBfs\u0002\u0007!1D\u0001\u000bg\u0016$h+\u00197vKFJD\u0003\u0002B6\u00077Dqaa3{\u0001\u0004\u0011Y\"\u0001\u0005`m\u0006dW/\u001a\u001a1\u0003\u001d1\u0018\r\\;feA*\"Aa\t\u0002\u0015\u001d,GOV1mk\u0016\u0014\u0004\'A\u0006wC2,XM\r\u0019`I\u0015\fH\u0003\u0002B6\u0007SDqaa8\u007f\u0001\u0004\u0011\u0019#\u0001\u0006tKR4\u0016\r\\;feA\"BAa\u001b\u0004p\"91q\\@A\u0002\t\r\u0012\u0001C0wC2,XMM\u0019\u0002\u000fY\fG.^33cU\u0011!1F\u0001\u000bO\u0016$h+\u00197vKJ\n\u0014a\u0003<bYV,\'\'M0%KF$BAa\u001b\u0004~\"A11_A\u0004\u0001\u0004\u0011Y#\u0001\u0006tKR4\u0016\r\\;feE\"BAa\u001b\u0005\u0004!A11_A\u0005\u0001\u0004\u0011Y#\u0001\u0005u_N#(/\u001b8h)\t!I\u0001\u0005\u0003\u0005\f\u0011UQB\u0001C\u0007\u0015\u0011!y\u0001\"\u0005\u0002\t1\fgn\u001a\u0006\u0003\t\'\tAA[1wC&!Aq\u0003C\u0007\u0005\u0019\u0019FO]5oO\u000611\u000f\u001e:j]\u001e,\"\u0001\"\b\u0011\t\u0005ECqD\u0005\u0005\t/\t)%\u0001\u0005iCND7i\u001c3f)\t!)\u0003\u0005\u0003\u0002Z\u0011\u001d\u0012\u0002\u0002C\u0015\u00037\u00121!\u00138u\u0003\u0019)\u0017/^1mgR!Aq\u0006C\u001b!\u0011\tI\u0006\"\r\n\t\u0011M\u00121\f\u0002\b\u0005>|G.Z1o\u0011!!9$!\u0005A\u0002\u0005-\u0015!A8\u0015Y\tMB1\bC\u001f\t\u007f!\t\u0005b\u0011\u0005F\u0011\u001dC\u0011\nC&\t\u001b\"y\u0005\"\u0015\u0005T\u0011UCq\u000bC-\t7\"i\u0006b\u0018\u0005b\u0011\r\u0004B\u0003B1\u0003\'\u0001\n\u00111\u0001\u0002|!Q!qOA\n!\u0003\u0005\r!a%\t\u0015\t-\u00151\u0003I\u0001\u0002\u0004\tY\n\u0003\u0006\u0003 \u0006M\u0001\u0013!a\u0001\u0003GC!Ba-\u0002\u0014A\u0005\t\u0019AAV\u0011)\u00119-a\u0005\u0011\u0002\u0003\u0007\u00111\u0017\u0005\u000b\u00057\f\u0019\u0002%AA\u0002\u0005m\u0006B\u0003Bx\u0003\'\u0001\n\u00111\u0001\u0002D\"Q11AA\n!\u0003\u0005\r!a3\t\u0015\r]\u00111\u0003I\u0001\u0002\u0004\t\u0019\u000e\u0003\u0006\u0004,\u0005M\u0001\u0013!a\u0001\u00037D!ba\u0010\u0002\u0014A\u0005\t\u0019AAr\u0011)\u0019\u0019&a\u0005\u0011\u0002\u0003\u0007\u00111\u001e\u0005\u000b\u0007O\n\u0019\u0002%AA\u0002\u0005M\bBCB>\u0003\'\u0001\n\u00111\u0001\u0002|\"Q1qRA\n!\u0003\u0005\rAa\u0001\t\u0015\r\r\u00161\u0003I\u0001\u0002\u0004\u0011Y\u0001\u0003\u0006\u00048\u0006M\u0001\u0013!a\u0001\u0005\'A!ba3\u0002\u0014A\u0005\t\u0019\u0001B\u000e\u0011)\u0019y.a\u0005\u0011\u0002\u0003\u0007!1\u0005\u0005\u000b\u0007g\f\u0019\u0002%AA\u0002\t-\u0012aD1qa2LH\u0005Z3gCVdG\u000fJ\u0019\u0016\u0005\u0011%$\u0006BA>\tWZ#\u0001\"\u001c\u0011\t\u0011=D\u0011P\u0007\u0003\tcRA\u0001b\u001d\u0005v\u0005IQO\\2iK\u000e\\W\r\u001a\u0006\u0005\to\nY&\u0001\u0006b]:|G/\u0019;j_:LA\u0001b\u001f\u0005r\t\tRO\\2iK\u000e\\W\r\u001a,be&\fgnY3\u0002\u001f\u0005\u0004\b\u000f\\=%I\u00164\u0017-\u001e7uII*\"\u0001\"!+\t\u0005ME1N\u0001\u0010CB\u0004H.\u001f\u0013eK\u001a\fW\u000f\u001c;%gU\u0011Aq\u0011\u0016\u0005\u00037#Y\'A\bbaBd\u0017\u0010\n3fM\u0006,H\u000e\u001e\u00135+\t!iI\u000b\u0003\u0002$\u0012-\u0014aD1qa2LH\u0005Z3gCVdG\u000fJ\u001b\u0016\u0005\u0011M%\u0006BAV\tW\nq\"\u00199qYf$C-\u001a4bk2$HEN\u000b\u0003\t3SC!a-\u0005l\u0005y\u0011\r\u001d9ms\u0012\"WMZ1vYR$s\'\u0006\u0002\u0005 *\"\u00111\u0018C6\u0003=\t\u0007\u000f\u001d7zI\u0011,g-Y;mi\u0012BTC\u0001CSU\u0011\t\u0019\rb\u001b\u0002\u001f\u0005\u0004\b\u000f\\=%I\u00164\u0017-\u001e7uIe*\"\u0001b++\t\u0005-G1N\u0001\u0011CB\u0004H.\u001f\u0013eK\u001a\fW\u000f\u001c;%cA*\"\u0001\"-+\t\u0005MG1N\u0001\u0011CB\u0004H.\u001f\u0013eK\u001a\fW\u000f\u001c;%cE*\"\u0001b.+\t\u0005mG1N\u0001\u0011CB\u0004H.\u001f\u0013eK\u001a\fW\u000f\u001c;%cI*\"\u0001\"0+\t\u0005\rH1N\u0001\u0011CB\u0004H.\u001f\u0013eK\u001a\fW\u000f\u001c;%cM*\"\u0001b1+\t\u0005-H1N\u0001\u0011CB\u0004H.\u001f\u0013eK\u001a\fW\u000f\u001c;%cQ*\"\u0001\"3+\t\u0005MH1N\u0001\u0011CB\u0004H.\u001f\u0013eK\u001a\fW\u000f\u001c;%cU*\"\u0001b4+\t\u0005mH1N\u0001\u0011CB\u0004H.\u001f\u0013eK\u001a\fW\u000f\u001c;%cY*\"\u0001\"6+\t\t\rA1N\u0001\u0011CB\u0004H.\u001f\u0013eK\u001a\fW\u000f\u001c;%c]*\"\u0001b7+\t\t-A1N\u0001\u0011CB\u0004H.\u001f\u0013eK\u001a\fW\u000f\u001c;%ca*\"\u0001\"9+\t\tMA1N\u0001\u0011CB\u0004H.\u001f\u0013eK\u001a\fW\u000f\u001c;%ce*\"\u0001b:+\t\tmA1N\u0001\u0011CB\u0004H.\u001f\u0013eK\u001a\fW\u000f\u001c;%eA*\"\u0001\"<+\t\t\rB1N\u0001\u0011CB\u0004H.\u001f\u0013eK\u001a\fW\u000f\u001c;%eE*\"\u0001b=+\t\t-B1N\u0001\tI\r|g\u000e^3oiV\u0011A\u0011 \t\u0007\tw,Y!\"\u0005\u000f\t\u0011uXq\u0001\b\u0005\t\u007f,)!\u0004\u0002\u0006\u0002)!Q1AA\'\u0003\u0019a$o\\8u}%\u0011\u0011QL\u0005\u0005\u000b\u0013\tY&A\u0004qC\u000e\\\u0017mZ3\n\t\u00155Qq\u0002\u0002\u0004\'\u0016\f(\u0002BC\u0005\u00037\u0002\u0002\"!\u0017\u0006\u0014\u0011%\u00111R\u0005\u0005\u000b+\tYF\u0001\u0004UkBdWMM\u0001\u0007I\rdwN\\3\u0016\u0005\tM\u0002fA\u0003\u0006\u001eA!\u0011\u0011KC\u0010\u0013\u0011)\t#!\u0012\u0003\rI,7m\u001c:e!\u0011\ti(\"\n\u0005\u000f\u0005\u00055A1\u0001\u0002\u0004B!\u0011QPC\u0015\t\u001d\t9j\u0001b\u0001\u0003\u0007\u0003B!! \u0006.\u00119\u0011qT\u0002C\u0002\u0005\r\u0005\u0003BA?\u000bc!q!a*\u0004\u0005\u0004\t\u0019\t\u0005\u0003\u0002~\u0015UBaBAX\u0007\t\u0007\u00111\u0011\t\u0005\u0003{*I\u0004B\u0004\u00028\u000e\u0011\r!a!\u0011\t\u0005uTQ\b\u0003\b\u0003\u007f\u001b!\u0019AAB!\u0011\ti(\"\u0011\u0005\u000f\u0005\u001d7A1\u0001\u0002\u0004B!\u0011QPC#\t\u001d\tym\u0001b\u0001\u0003\u0007\u0003B!! \u0006J\u00119\u0011q[\u0002C\u0002\u0005\r\u0005\u0003BA?\u000b\u001b\"q!a8\u0004\u0005\u0004\t\u0019\t\u0005\u0003\u0002~\u0015ECaBAt\u0007\t\u0007\u00111\u0011\t\u0005\u0003{*)\u0006B\u0004\u0002p\u000e\u0011\r!a!\u0011\t\u0005uT\u0011\f\u0003\b\u0003o\u001c!\u0019AAB!\u0011\ti(\"\u0018\u0005\u000f\u0005}8A1\u0001\u0002\u0004B!\u0011QPC1\t\u001d\u00119a\u0001b\u0001\u0003\u0007\u0003B!! \u0006f\u00119!qB\u0002C\u0002\u0005\r\u0005\u0003BA?\u000bS\"qAa\u0006\u0004\u0005\u0004\t\u0019\t\u0005\u0003\u0002~\u00155Da\u0002B\u0010\u0007\t\u0007\u00111\u0011\t\u0005\u0003{*\t\bB\u0004\u0003(\r\u0011\r!a!\u0011\t\u0005uTQ\u000f\u0003\b\u0005_\u0019!\u0019AAB\u0011\u001d\u0011\tg\u0001a\u0001\u000bGAqAa\u001e\u0004\u0001\u0004)9\u0003C\u0004\u0003\f\u000e\u0001\r!b\u000b\t\u000f\t}5\u00011\u0001\u00060!9!1W\u0002A\u0002\u0015M\u0002b\u0002Bd\u0007\u0001\u0007Qq\u0007\u0005\b\u00057\u001c\u0001\u0019AC\u001e\u0011\u001d\u0011yo\u0001a\u0001\u000b\u007fAqaa\u0001\u0004\u0001\u0004)\u0019\u0005C\u0004\u0004\u0018\r\u0001\r!b\u0012\t\u000f\r-2\u00011\u0001\u0006L!91qH\u0002A\u0002\u0015=\u0003bBB*\u0007\u0001\u0007Q1\u000b\u0005\b\u0007O\u001a\u0001\u0019AC,\u0011\u001d\u0019Yh\u0001a\u0001\u000b7Bqaa$\u0004\u0001\u0004)y\u0006C\u0004\u0004$\u000e\u0001\r!b\u0019\t\u000f\r]6\u00011\u0001\u0006h!911Z\u0002A\u0002\u0015-\u0004bBBp\u0007\u0001\u0007Qq\u000e\u0005\b\u0007g\u001c\u0001\u0019AC:\u0003\u001d)h.\u00199qYf,B&\"*\u00066\u0016eVQXCa\u000b\u000b,I-\"4\u0006R\u0016UW\u0011\\Co\u000bC,)/\";\u0006n\u0016EXQ_C}\u000b{4\tA\"\u0002\u0015\t\u0015\u001dfq\u0001\t\u0007\u00033*I+\",\n\t\u0015-\u00161\f\u0002\u0005\'>lW\r\u0005\u0018\u0002Z\u0015=V1WC\\\u000bw+y,b1\u0006H\u0016-WqZCj\u000b/,Y.b8\u0006d\u0016\u001dX1^Cx\u000bg,90b?\u0006\u0000\u001a\r\u0011\u0002BCY\u00037\u0012q\u0001V;qY\u0016\u0014\u0014\u0007\u0005\u0003\u0002~\u0015UFaBAA\t\t\u0007\u00111\u0011\t\u0005\u0003{*I\fB\u0004\u0002\u0018\u0012\u0011\r!a!\u0011\t\u0005uTQ\u0018\u0003\b\u0003?#!\u0019AAB!\u0011\ti(\"1\u0005\u000f\u0005\u001dFA1\u0001\u0002\u0004B!\u0011QPCc\t\u001d\ty\u000b\u0002b\u0001\u0003\u0007\u0003B!! \u0006J\u00129\u0011q\u0017\u0003C\u0002\u0005\r\u0005\u0003BA?\u000b\u001b$q!a0\u0005\u0005\u0004\t\u0019\t\u0005\u0003\u0002~\u0015EGaBAd\t\t\u0007\u00111\u0011\t\u0005\u0003{*)\u000eB\u0004\u0002P\u0012\u0011\r!a!\u0011\t\u0005uT\u0011\u001c\u0003\b\u0003/$!\u0019AAB!\u0011\ti(\"8\u0005\u000f\u0005}GA1\u0001\u0002\u0004B!\u0011QPCq\t\u001d\t9\u000f\u0002b\u0001\u0003\u0007\u0003B!! \u0006f\u00129\u0011q\u001e\u0003C\u0002\u0005\r\u0005\u0003BA?\u000bS$q!a>\u0005\u0005\u0004\t\u0019\t\u0005\u0003\u0002~\u00155HaBA\u0000\t\t\u0007\u00111\u0011\t\u0005\u0003{*\t\u0010B\u0004\u0003\b\u0011\u0011\r!a!\u0011\t\u0005uTQ\u001f\u0003\b\u0005\u001f!!\u0019AAB!\u0011\ti(\"?\u0005\u000f\t]AA1\u0001\u0002\u0004B!\u0011QPC\u007f\t\u001d\u0011y\u0002\u0002b\u0001\u0003\u0007\u0003B!! \u0007\u0002\u00119!q\u0005\u0003C\u0002\u0005\r\u0005\u0003BA?\r\u000b!qAa\f\u0005\u0005\u0004\t\u0019\tC\u0004\u00058\u0011\u0001\rA\"\u0003\u0011[\u0005ES!b-\u00068\u0016mVqXCb\u000b\u000f,Y-b4\u0006T\u0016]W1\\Cp\u000bG,9/b;\u0006p\u0016MXq_C~\u000b\u007f4\u0019\u0001
   #12 = Utf8               _value1
   #13 = Utf8               Ljava/lang/Object;
   #14 = Utf8               TT1;
   #15 = Utf8               _value2
   #16 = Utf8               TT2;
   #17 = Utf8               _value3
   #18 = Utf8               TT3;
   #19 = Utf8               _value4
   #20 = Utf8               TT4;
   #21 = Utf8               _value5
   #22 = Utf8               TT5;
   #23 = Utf8               _value6
   #24 = Utf8               TT6;
   #25 = Utf8               _value7
   #26 = Utf8               TT7;
   #27 = Utf8               _value8
   #28 = Utf8               TT8;
   #29 = Utf8               _value9
   #30 = Utf8               TT9;
   #31 = Utf8               _value10
   #32 = Utf8               TT10;
   #33 = Utf8               _value11
   #34 = Utf8               TT11;
   #35 = Utf8               _value12
   #36 = Utf8               TT12;
   #37 = Utf8               _value13
   #38 = Utf8               TT13;
   #39 = Utf8               _value14
   #40 = Utf8               TT14;
   #41 = Utf8               _value15
   #42 = Utf8               TT15;
   #43 = Utf8               _value16
   #44 = Utf8               TT16;
   #45 = Utf8               _value17
   #46 = Utf8               TT17;
   #47 = Utf8               _value18
   #48 = Utf8               TT18;
   #49 = Utf8               _value19
   #50 = Utf8               TT19;
   #51 = Utf8               _value20
   #52 = Utf8               TT20;
   #53 = Utf8               _value21
   #54 = Utf8               TT21;
   #55 = Utf8               org$sireum$RecordSig$$$isOwned
   #56 = Utf8               Z
   #57 = Utf8               unapply
   #58 = Utf8               (Lorg/sireum/MBox21;)Lscala/Some;
   #59 = Utf8               <T1:Ljava/lang/Object;T2:Ljava/lang/Object;T3:Ljava/lang/Object;T4:Ljava/lang/Object;T5:Ljava/lang/Object;T6:Ljava/lang/Object;T7:Ljava/lang/Object;T8:Ljava/lang/Object;T9:Ljava/lang/Object;T10:Ljava/lang/Object;T11:Ljava/lang/Object;T12:Ljava/lang/Object;T13:Ljava/lang/Object;T14:Ljava/lang/Object;T15:Ljava/lang/Object;T16:Ljava/lang/Object;T17:Ljava/lang/Object;T18:Ljava/lang/Object;T19:Ljava/lang/Object;T20:Ljava/lang/Object;T21:Ljava/lang/Object;>(Lorg/sireum/MBox21<TT1;TT2;TT3;TT4;TT5;TT6;TT7;TT8;TT9;TT10;TT11;TT12;TT13;TT14;TT15;TT16;TT17;TT18;TT19;TT20;TT21;>;)Lscala/Some<Lscala/Tuple21<TT1;TT2;TT3;TT4;TT5;TT6;TT7;TT8;TT9;TT10;TT11;TT12;TT13;TT14;TT15;TT16;TT17;TT18;TT19;TT20;TT21;>;>;
   #60 = Utf8               o
   #61 = Utf8               org/sireum/MBox21$
   #62 = Class              #61           // org/sireum/MBox21$
   #63 = Utf8               MODULE$
   #64 = Utf8               Lorg/sireum/MBox21$;
   #65 = NameAndType        #63:#64       // MODULE$:Lorg/sireum/MBox21$;
   #66 = Fieldref           #62.#65       // org/sireum/MBox21$.MODULE$:Lorg/sireum/MBox21$;
   #67 = NameAndType        #57:#58       // unapply:(Lorg/sireum/MBox21;)Lscala/Some;
   #68 = Methodref          #62.#67       // org/sireum/MBox21$.unapply:(Lorg/sireum/MBox21;)Lscala/Some;
   #69 = Utf8               Lorg/sireum/MBox21;
   #70 = Utf8               $owned
   #71 = Utf8               ()Z
   #72 = Utf8               $owned$
   #73 = Utf8               (Lorg/sireum/RecordSig;)Z
   #74 = NameAndType        #72:#73       // $owned$:(Lorg/sireum/RecordSig;)Z
   #75 = InterfaceMethodref #7.#74        // org/sireum/RecordSig.$owned$:(Lorg/sireum/RecordSig;)Z
   #76 = Utf8               this
   #77 = Utf8               $owned_$eq
   #78 = Utf8               (Z)Lorg/sireum/RecordSig;
   #79 = Utf8               b
   #80 = Utf8               $owned_$eq$
   #81 = Utf8               (Lorg/sireum/RecordSig;Z)Lorg/sireum/RecordSig;
   #82 = NameAndType        #80:#81       // $owned_$eq$:(Lorg/sireum/RecordSig;Z)Lorg/sireum/RecordSig;
   #83 = InterfaceMethodref #7.#82        // org/sireum/RecordSig.$owned_$eq$:(Lorg/sireum/RecordSig;Z)Lorg/sireum/RecordSig;
   #84 = Utf8               hash
   #85 = Utf8               ()Lorg/sireum/Z;
   #86 = Utf8               hash$
   #87 = Utf8               (Lorg/sireum/RecordSig;)Lorg/sireum/Z;
   #88 = NameAndType        #86:#87       // hash$:(Lorg/sireum/RecordSig;)Lorg/sireum/Z;
   #89 = InterfaceMethodref #7.#88        // org/sireum/RecordSig.hash$:(Lorg/sireum/RecordSig;)Lorg/sireum/Z;
   #90 = Utf8               $cannotMixImmutableAndMutable
   #91 = Utf8               ()Lscala/runtime/Nothing$;
   #92 = Utf8               org/sireum/Mutable
   #93 = Class              #92           // org/sireum/Mutable
   #94 = Utf8               $cannotMixImmutableAndMutable$
   #95 = Utf8               (Lorg/sireum/Mutable;)Lscala/runtime/Nothing$;
   #96 = NameAndType        #94:#95       // $cannotMixImmutableAndMutable$:(Lorg/sireum/Mutable;)Lscala/runtime/Nothing$;
   #97 = InterfaceMethodref #93.#96       // org/sireum/Mutable.$cannotMixImmutableAndMutable$:(Lorg/sireum/Mutable;)Lscala/runtime/Nothing$;
   #98 = Utf8               $hasEquals
   #99 = Utf8               $hasEquals$
  #100 = Utf8               (Lorg/sireum/Mutable;)Z
  #101 = NameAndType        #99:#100      // $hasEquals$:(Lorg/sireum/Mutable;)Z
  #102 = InterfaceMethodref #93.#101      // org/sireum/Mutable.$hasEquals$:(Lorg/sireum/Mutable;)Z
  #103 = Utf8               $hasString
  #104 = Utf8               $hasString$
  #105 = NameAndType        #104:#100     // $hasString$:(Lorg/sireum/Mutable;)Z
  #106 = InterfaceMethodref #93.#105      // org/sireum/Mutable.$hasString$:(Lorg/sireum/Mutable;)Z
  #107 = NameAndType        #55:#56       // org$sireum$RecordSig$$$isOwned:Z
  #108 = Fieldref           #2.#107       // org/sireum/MBox21.org$sireum$RecordSig$$$isOwned:Z
  #109 = Utf8               org$sireum$RecordSig$$$isOwned_$eq
  #110 = Utf8               (Z)V
  #111 = Utf8               x$1
  #112 = Utf8               value1
  #113 = Utf8               ()Ljava/lang/Object;
  #114 = Utf8               ()TT1;
  #115 = NameAndType        #12:#13       // _value1:Ljava/lang/Object;
  #116 = Fieldref           #2.#115       // org/sireum/MBox21._value1:Ljava/lang/Object;
  #117 = Utf8               getValue1
  #118 = Utf8               value1_$eq
  #119 = Utf8               (Ljava/lang/Object;)Lorg/sireum/MBox21;
  #120 = Utf8               (TT1;)Lorg/sireum/MBox21<TT1;TT2;TT3;TT4;TT5;TT6;TT7;TT8;TT9;TT10;TT11;TT12;TT13;TT14;TT15;TT16;TT17;TT18;TT19;TT20;TT21;>;
  #121 = Utf8               setValue1
  #122 = Utf8               value2
  #123 = Utf8               ()TT2;
  #124 = NameAndType        #15:#13       // _value2:Ljava/lang/Object;
  #125 = Fieldref           #2.#124       // org/sireum/MBox21._value2:Ljava/lang/Object;
  #126 = Utf8               getValue2
  #127 = Utf8               value2_$eq
  #128 = Utf8               (TT2;)Lorg/sireum/MBox21<TT1;TT2;TT3;TT4;TT5;TT6;TT7;TT8;TT9;TT10;TT11;TT12;TT13;TT14;TT15;TT16;TT17;TT18;TT19;TT20;TT21;>;
  #129 = Utf8               setValue2
  #130 = Utf8               value3
  #131 = Utf8               ()TT3;
  #132 = NameAndType        #17:#13       // _value3:Ljava/lang/Object;
  #133 = Fieldref           #2.#132       // org/sireum/MBox21._value3:Ljava/lang/Object;
  #134 = Utf8               getValue3
  #135 = Utf8               value3_$eq
  #136 = Utf8               (TT3;)Lorg/sireum/MBox21<TT1;TT2;TT3;TT4;TT5;TT6;TT7;TT8;TT9;TT10;TT11;TT12;TT13;TT14;TT15;TT16;TT17;TT18;TT19;TT20;TT21;>;
  #137 = Utf8               setValue3
  #138 = Utf8               value4
  #139 = Utf8               ()TT4;
  #140 = NameAndType        #19:#13       // _value4:Ljava/lang/Object;
  #141 = Fieldref           #2.#140       // org/sireum/MBox21._value4:Ljava/lang/Object;
  #142 = Utf8               getValue4
  #143 = Utf8               value4_$eq
  #144 = Utf8               (TT4;)Lorg/sireum/MBox21<TT1;TT2;TT3;TT4;TT5;TT6;TT7;TT8;TT9;TT10;TT11;TT12;TT13;TT14;TT15;TT16;TT17;TT18;TT19;TT20;TT21;>;
  #145 = Utf8               setValue4
  #146 = Utf8               value5
  #147 = Utf8               ()TT5;
  #148 = NameAndType        #21:#13       // _value5:Ljava/lang/Object;
  #149 = Fieldref           #2.#148       // org/sireum/MBox21._value5:Ljava/lang/Object;
  #150 = Utf8               getValue5
  #151 = Utf8               value5_$eq
  #152 = Utf8               (TT5;)Lorg/sireum/MBox21<TT1;TT2;TT3;TT4;TT5;TT6;TT7;TT8;TT9;TT10;TT11;TT12;TT13;TT14;TT15;TT16;TT17;TT18;TT19;TT20;TT21;>;
  #153 = Utf8               setValue5
  #154 = Utf8               value6
  #155 = Utf8               ()TT6;
  #156 = NameAndType        #23:#13       // _value6:Ljava/lang/Object;
  #157 = Fieldref           #2.#156       // org/sireum/MBox21._value6:Ljava/lang/Object;
  #158 = Utf8               getValue6
  #159 = Utf8               value6_$eq
  #160 = Utf8               (TT6;)Lorg/sireum/MBox21<TT1;TT2;TT3;TT4;TT5;TT6;TT7;TT8;TT9;TT10;TT11;TT12;TT13;TT14;TT15;TT16;TT17;TT18;TT19;TT20;TT21;>;
  #161 = Utf8               setValue6
  #162 = Utf8               value7
  #163 = Utf8               ()TT7;
  #164 = NameAndType        #25:#13       // _value7:Ljava/lang/Object;
  #165 = Fieldref           #2.#164       // org/sireum/MBox21._value7:Ljava/lang/Object;
  #166 = Utf8               getValue7
  #167 = Utf8               value7_$eq
  #168 = Utf8               (TT7;)Lorg/sireum/MBox21<TT1;TT2;TT3;TT4;TT5;TT6;TT7;TT8;TT9;TT10;TT11;TT12;TT13;TT14;TT15;TT16;TT17;TT18;TT19;TT20;TT21;>;
  #169 = Utf8               setValue7
  #170 = Utf8               value8
  #171 = Utf8               ()TT8;
  #172 = NameAndType        #27:#13       // _value8:Ljava/lang/Object;
  #173 = Fieldref           #2.#172       // org/sireum/MBox21._value8:Ljava/lang/Object;
  #174 = Utf8               getValue8
  #175 = Utf8               value8_$eq
  #176 = Utf8               (TT8;)Lorg/sireum/MBox21<TT1;TT2;TT3;TT4;TT5;TT6;TT7;TT8;TT9;TT10;TT11;TT12;TT13;TT14;TT15;TT16;TT17;TT18;TT19;TT20;TT21;>;
  #177 = Utf8               setValue8
  #178 = Utf8               value9
  #179 = Utf8               ()TT9;
  #180 = NameAndType        #29:#13       // _value9:Ljava/lang/Object;
  #181 = Fieldref           #2.#180       // org/sireum/MBox21._value9:Ljava/lang/Object;
  #182 = Utf8               getValue9
  #183 = Utf8               value9_$eq
  #184 = Utf8               (TT9;)Lorg/sireum/MBox21<TT1;TT2;TT3;TT4;TT5;TT6;TT7;TT8;TT9;TT10;TT11;TT12;TT13;TT14;TT15;TT16;TT17;TT18;TT19;TT20;TT21;>;
  #185 = Utf8               setValue9
  #186 = Utf8               value10
  #187 = Utf8               ()TT10;
  #188 = NameAndType        #31:#13       // _value10:Ljava/lang/Object;
  #189 = Fieldref           #2.#188       // org/sireum/MBox21._value10:Ljava/lang/Object;
  #190 = Utf8               getValue10
  #191 = Utf8               value10_$eq
  #192 = Utf8               (TT10;)Lorg/sireum/MBox21<TT1;TT2;TT3;TT4;TT5;TT6;TT7;TT8;TT9;TT10;TT11;TT12;TT13;TT14;TT15;TT16;TT17;TT18;TT19;TT20;TT21;>;
  #193 = Utf8               setValue10
  #194 = Utf8               value11
  #195 = Utf8               ()TT11;
  #196 = NameAndType        #33:#13       // _value11:Ljava/lang/Object;
  #197 = Fieldref           #2.#196       // org/sireum/MBox21._value11:Ljava/lang/Object;
  #198 = Utf8               getValue11
  #199 = Utf8               value11_$eq
  #200 = Utf8               (TT11;)Lorg/sireum/MBox21<TT1;TT2;TT3;TT4;TT5;TT6;TT7;TT8;TT9;TT10;TT11;TT12;TT13;TT14;TT15;TT16;TT17;TT18;TT19;TT20;TT21;>;
  #201 = Utf8               setValue11
  #202 = Utf8               value12
  #203 = Utf8               ()TT12;
  #204 = NameAndType        #35:#13       // _value12:Ljava/lang/Object;
  #205 = Fieldref           #2.#204       // org/sireum/MBox21._value12:Ljava/lang/Object;
  #206 = Utf8               getValue12
  #207 = Utf8               value12_$eq
  #208 = Utf8               (TT12;)Lorg/sireum/MBox21<TT1;TT2;TT3;TT4;TT5;TT6;TT7;TT8;TT9;TT10;TT11;TT12;TT13;TT14;TT15;TT16;TT17;TT18;TT19;TT20;TT21;>;
  #209 = Utf8               setValue12
  #210 = Utf8               value13
  #211 = Utf8               ()TT13;
  #212 = NameAndType        #37:#13       // _value13:Ljava/lang/Object;
  #213 = Fieldref           #2.#212       // org/sireum/MBox21._value13:Ljava/lang/Object;
  #214 = Utf8               getValue13
  #215 = Utf8               value13_$eq
  #216 = Utf8               (TT13;)Lorg/sireum/MBox21<TT1;TT2;TT3;TT4;TT5;TT6;TT7;TT8;TT9;TT10;TT11;TT12;TT13;TT14;TT15;TT16;TT17;TT18;TT19;TT20;TT21;>;
  #217 = Utf8               setValue13
  #218 = Utf8               value14
  #219 = Utf8               ()TT14;
  #220 = NameAndType        #39:#13       // _value14:Ljava/lang/Object;
  #221 = Fieldref           #2.#220       // org/sireum/MBox21._value14:Ljava/lang/Object;
  #222 = Utf8               getValue14
  #223 = Utf8               value14_$eq
  #224 = Utf8               (TT14;)Lorg/sireum/MBox21<TT1;TT2;TT3;TT4;TT5;TT6;TT7;TT8;TT9;TT10;TT11;TT12;TT13;TT14;TT15;TT16;TT17;TT18;TT19;TT20;TT21;>;
  #225 = Utf8               setValue14
  #226 = Utf8               value15
  #227 = Utf8               ()TT15;
  #228 = NameAndType        #41:#13       // _value15:Ljava/lang/Object;
  #229 = Fieldref           #2.#228       // org/sireum/MBox21._value15:Ljava/lang/Object;
  #230 = Utf8               getValue15
  #231 = Utf8               value15_$eq
  #232 = Utf8               (TT15;)Lorg/sireum/MBox21<TT1;TT2;TT3;TT4;TT5;TT6;TT7;TT8;TT9;TT10;TT11;TT12;TT13;TT14;TT15;TT16;TT17;TT18;TT19;TT20;TT21;>;
  #233 = Utf8               setValue15
  #234 = Utf8               value16
  #235 = Utf8               ()TT16;
  #236 = NameAndType        #43:#13       // _value16:Ljava/lang/Object;
  #237 = Fieldref           #2.#236       // org/sireum/MBox21._value16:Ljava/lang/Object;
  #238 = Utf8               getValue16
  #239 = Utf8               value16_$eq
  #240 = Utf8               (TT16;)Lorg/sireum/MBox21<TT1;TT2;TT3;TT4;TT5;TT6;TT7;TT8;TT9;TT10;TT11;TT12;TT13;TT14;TT15;TT16;TT17;TT18;TT19;TT20;TT21;>;
  #241 = Utf8               setValue16
  #242 = Utf8               value17
  #243 = Utf8               ()TT17;
  #244 = NameAndType        #45:#13       // _value17:Ljava/lang/Object;
  #245 = Fieldref           #2.#244       // org/sireum/MBox21._value17:Ljava/lang/Object;
  #246 = Utf8               getValue17
  #247 = Utf8               value17_$eq
  #248 = Utf8               (TT17;)Lorg/sireum/MBox21<TT1;TT2;TT3;TT4;TT5;TT6;TT7;TT8;TT9;TT10;TT11;TT12;TT13;TT14;TT15;TT16;TT17;TT18;TT19;TT20;TT21;>;
  #249 = Utf8               setValue17
  #250 = Utf8               value18
  #251 = Utf8               ()TT18;
  #252 = NameAndType        #47:#13       // _value18:Ljava/lang/Object;
  #253 = Fieldref           #2.#252       // org/sireum/MBox21._value18:Ljava/lang/Object;
  #254 = Utf8               getValue18
  #255 = Utf8               value18_$eq
  #256 = Utf8               (TT18;)Lorg/sireum/MBox21<TT1;TT2;TT3;TT4;TT5;TT6;TT7;TT8;TT9;TT10;TT11;TT12;TT13;TT14;TT15;TT16;TT17;TT18;TT19;TT20;TT21;>;
  #257 = Utf8               setValue18
  #258 = Utf8               value19
  #259 = Utf8               ()TT19;
  #260 = NameAndType        #49:#13       // _value19:Ljava/lang/Object;
  #261 = Fieldref           #2.#260       // org/sireum/MBox21._value19:Ljava/lang/Object;
  #262 = Utf8               getValue19
  #263 = Utf8               value19_$eq
  #264 = Utf8               (TT19;)Lorg/sireum/MBox21<TT1;TT2;TT3;TT4;TT5;TT6;TT7;TT8;TT9;TT10;TT11;TT12;TT13;TT14;TT15;TT16;TT17;TT18;TT19;TT20;TT21;>;
  #265 = Utf8               setValue19
  #266 = Utf8               value20
  #267 = Utf8               ()TT20;
  #268 = NameAndType        #51:#13       // _value20:Ljava/lang/Object;
  #269 = Fieldref           #2.#268       // org/sireum/MBox21._value20:Ljava/lang/Object;
  #270 = Utf8               getValue20
  #271 = Utf8               value20_$eq
  #272 = Utf8               (TT20;)Lorg/sireum/MBox21<TT1;TT2;TT3;TT4;TT5;TT6;TT7;TT8;TT9;TT10;TT11;TT12;TT13;TT14;TT15;TT16;TT17;TT18;TT19;TT20;TT21;>;
  #273 = Utf8               setValue20
  #274 = Utf8               value21
  #275 = Utf8               ()TT21;
  #276 = NameAndType        #53:#13       // _value21:Ljava/lang/Object;
  #277 = Fieldref           #2.#276       // org/sireum/MBox21._value21:Ljava/lang/Object;
  #278 = Utf8               getValue21
  #279 = Utf8               value21_$eq
  #280 = Utf8               (TT21;)Lorg/sireum/MBox21<TT1;TT2;TT3;TT4;TT5;TT6;TT7;TT8;TT9;TT10;TT11;TT12;TT13;TT14;TT15;TT16;TT17;TT18;TT19;TT20;TT21;>;
  #281 = Utf8               setValue21
  #282 = Utf8               toString
  #283 = Utf8               ()Ljava/lang/String;
  #284 = NameAndType        #103:#71      // $hasString:()Z
  #285 = Methodref          #2.#284       // org/sireum/MBox21.$hasString:()Z
  #286 = Utf8               string$
  #287 = Utf8               (Lorg/sireum/RecordSig;)Ljava/lang/String;
  #288 = NameAndType        #286:#287     // string$:(Lorg/sireum/RecordSig;)Ljava/lang/String;
  #289 = InterfaceMethodref #7.#288       // org/sireum/RecordSig.string$:(Lorg/sireum/RecordSig;)Ljava/lang/String;
  #290 = Utf8               java/lang/StringBuilder
  #291 = Class              #290          // java/lang/StringBuilder
  #292 = Utf8               <init>
  #293 = Utf8               ()V
  #294 = NameAndType        #292:#293     // "<init>":()V
  #295 = Methodref          #291.#294     // java/lang/StringBuilder."<init>":()V
  #296 = Utf8               MBox21
  #297 = String             #296          // MBox21
  #298 = Utf8               append
  #299 = Utf8               (Ljava/lang/String;)Ljava/lang/StringBuilder;
  #300 = NameAndType        #298:#299     // append:(Ljava/lang/String;)Ljava/lang/StringBuilder;
  #301 = Methodref          #291.#300     // java/lang/StringBuilder.append:(Ljava/lang/String;)Ljava/lang/StringBuilder;
  #302 = Utf8               (C)Ljava/lang/StringBuilder;
  #303 = NameAndType        #298:#302     // append:(C)Ljava/lang/StringBuilder;
  #304 = Methodref          #291.#303     // java/lang/StringBuilder.append:(C)Ljava/lang/StringBuilder;
  #305 = Utf8               org/sireum/String$
  #306 = Class              #305          // org/sireum/String$
  #307 = Utf8               Lorg/sireum/String$;
  #308 = NameAndType        #63:#307      // MODULE$:Lorg/sireum/String$;
  #309 = Fieldref           #306.#308     // org/sireum/String$.MODULE$:Lorg/sireum/String$;
  #310 = NameAndType        #112:#113     // value1:()Ljava/lang/Object;
  #311 = Methodref          #2.#310       // org/sireum/MBox21.value1:()Ljava/lang/Object;
  #312 = Utf8               escape
  #313 = Utf8               (Ljava/lang/Object;)Ljava/lang/String;
  #314 = NameAndType        #312:#313     // escape:(Ljava/lang/Object;)Ljava/lang/String;
  #315 = Methodref          #306.#314     // org/sireum/String$.escape:(Ljava/lang/Object;)Ljava/lang/String;
  #316 = Utf8               ,
  #317 = String             #316          // ,
  #318 = NameAndType        #122:#113     // value2:()Ljava/lang/Object;
  #319 = Methodref          #2.#318       // org/sireum/MBox21.value2:()Ljava/lang/Object;
  #320 = NameAndType        #130:#113     // value3:()Ljava/lang/Object;
  #321 = Methodref          #2.#320       // org/sireum/MBox21.value3:()Ljava/lang/Object;
  #322 = NameAndType        #138:#113     // value4:()Ljava/lang/Object;
  #323 = Methodref          #2.#322       // org/sireum/MBox21.value4:()Ljava/lang/Object;
  #324 = NameAndType        #146:#113     // value5:()Ljava/lang/Object;
  #325 = Methodref          #2.#324       // org/sireum/MBox21.value5:()Ljava/lang/Object;
  #326 = NameAndType        #154:#113     // value6:()Ljava/lang/Object;
  #327 = Methodref          #2.#326       // org/sireum/MBox21.value6:()Ljava/lang/Object;
  #328 = NameAndType        #162:#113     // value7:()Ljava/lang/Object;
  #329 = Methodref          #2.#328       // org/sireum/MBox21.value7:()Ljava/lang/Object;
  #330 = NameAndType        #170:#113     // value8:()Ljava/lang/Object;
  #331 = Methodref          #2.#330       // org/sireum/MBox21.value8:()Ljava/lang/Object;
  #332 = NameAndType        #178:#113     // value9:()Ljava/lang/Object;
  #333 = Methodref          #2.#332       // org/sireum/MBox21.value9:()Ljava/lang/Object;
  #334 = NameAndType        #186:#113     // value10:()Ljava/lang/Object;
  #335 = Methodref          #2.#334       // org/sireum/MBox21.value10:()Ljava/lang/Object;
  #336 = NameAndType        #194:#113     // value11:()Ljava/lang/Object;
  #337 = Methodref          #2.#336       // org/sireum/MBox21.value11:()Ljava/lang/Object;
  #338 = NameAndType        #202:#113     // value12:()Ljava/lang/Object;
  #339 = Methodref          #2.#338       // org/sireum/MBox21.value12:()Ljava/lang/Object;
  #340 = NameAndType        #210:#113     // value13:()Ljava/lang/Object;
  #341 = Methodref          #2.#340       // org/sireum/MBox21.value13:()Ljava/lang/Object;
  #342 = NameAndType        #218:#113     // value14:()Ljava/lang/Object;
  #343 = Methodref          #2.#342       // org/sireum/MBox21.value14:()Ljava/lang/Object;
  #344 = NameAndType        #226:#113     // value15:()Ljava/lang/Object;
  #345 = Methodref          #2.#344       // org/sireum/MBox21.value15:()Ljava/lang/Object;
  #346 = NameAndType        #234:#113     // value16:()Ljava/lang/Object;
  #347 = Methodref          #2.#346       // org/sireum/MBox21.value16:()Ljava/lang/Object;
  #348 = NameAndType        #242:#113     // value17:()Ljava/lang/Object;
  #349 = Methodref          #2.#348       // org/sireum/MBox21.value17:()Ljava/lang/Object;
  #350 = NameAndType        #250:#113     // value18:()Ljava/lang/Object;
  #351 = Methodref          #2.#350       // org/sireum/MBox21.value18:()Ljava/lang/Object;
  #352 = NameAndType        #258:#113     // value19:()Ljava/lang/Object;
  #353 = Methodref          #2.#352       // org/sireum/MBox21.value19:()Ljava/lang/Object;
  #354 = NameAndType        #266:#113     // value20:()Ljava/lang/Object;
  #355 = Methodref          #2.#354       // org/sireum/MBox21.value20:()Ljava/lang/Object;
  #356 = NameAndType        #274:#113     // value21:()Ljava/lang/Object;
  #357 = Methodref          #2.#356       // org/sireum/MBox21.value21:()Ljava/lang/Object;
  #358 = NameAndType        #282:#283     // toString:()Ljava/lang/String;
  #359 = Methodref          #291.#358     // java/lang/StringBuilder.toString:()Ljava/lang/String;
  #360 = Utf8               sb
  #361 = Utf8               Ljava/lang/StringBuilder;
  #362 = Utf8               java/lang/String
  #363 = Class              #362          // java/lang/String
  #364 = Utf8               string
  #365 = Methodref          #2.#358       // org/sireum/MBox21.toString:()Ljava/lang/String;
  #366 = Utf8               apply
  #367 = Utf8               (Ljava/lang/String;)Ljava/lang/String;
  #368 = NameAndType        #366:#367     // apply:(Ljava/lang/String;)Ljava/lang/String;
  #369 = Methodref          #306.#368     // org/sireum/String$.apply:(Ljava/lang/String;)Ljava/lang/String;
  #370 = Utf8               hashCode
  #371 = Utf8               ()I
  #372 = NameAndType        #98:#71       // $hasEquals:()Z
  #373 = Methodref          #2.#372       // org/sireum/MBox21.$hasEquals:()Z
  #374 = NameAndType        #370:#371     // hashCode:()I
  #375 = Methodref          #5.#374       // java/lang/Object.hashCode:()I
  #376 = Utf8               scala/package$
  #377 = Class              #376          // scala/package$
  #378 = Utf8               Lscala/package$;
  #379 = NameAndType        #63:#378      // MODULE$:Lscala/package$;
  #380 = Fieldref           #377.#379     // scala/package$.MODULE$:Lscala/package$;
  #381 = Utf8               Seq
  #382 = Utf8               ()Lscala/collection/immutable/Seq$;
  #383 = NameAndType        #381:#382     // Seq:()Lscala/collection/immutable/Seq$;
  #384 = Methodref          #377.#383     // scala/package$.Seq:()Lscala/collection/immutable/Seq$;
  #385 = Utf8               scala/runtime/ScalaRunTime$
  #386 = Class              #385          // scala/runtime/ScalaRunTime$
  #387 = Utf8               Lscala/runtime/ScalaRunTime$;
  #388 = NameAndType        #63:#387      // MODULE$:Lscala/runtime/ScalaRunTime$;
  #389 = Fieldref           #386.#388     // scala/runtime/ScalaRunTime$.MODULE$:Lscala/runtime/ScalaRunTime$;
  #390 = Utf8               getClass
  #391 = Utf8               ()Ljava/lang/Class;
  #392 = NameAndType        #390:#391     // getClass:()Ljava/lang/Class;
  #393 = Methodref          #2.#392       // org/sireum/MBox21.getClass:()Ljava/lang/Class;
  #394 = Utf8               java/lang/Class
  #395 = Class              #394          // java/lang/Class
  #396 = Utf8               getName
  #397 = NameAndType        #396:#283     // getName:()Ljava/lang/String;
  #398 = Methodref          #395.#397     // java/lang/Class.getName:()Ljava/lang/String;
  #399 = Utf8               genericWrapArray
  #400 = Utf8               (Ljava/lang/Object;)Lscala/collection/immutable/ArraySeq;
  #401 = NameAndType        #399:#400     // genericWrapArray:(Ljava/lang/Object;)Lscala/collection/immutable/ArraySeq;
  #402 = Methodref          #386.#401     // scala/runtime/ScalaRunTime$.genericWrapArray:(Ljava/lang/Object;)Lscala/collection/immutable/ArraySeq;
  #403 = Utf8               scala/collection/immutable/Seq$
  #404 = Class              #403          // scala/collection/immutable/Seq$
  #405 = Utf8               (Lscala/collection/immutable/Seq;)Lscala/collection/SeqOps;
  #406 = NameAndType        #366:#405     // apply:(Lscala/collection/immutable/Seq;)Lscala/collection/SeqOps;
  #407 = Methodref          #404.#406     // scala/collection/immutable/Seq$.apply:(Lscala/collection/immutable/Seq;)Lscala/collection/SeqOps;
  #408 = Utf8               scala/collection/Seq
  #409 = Class              #408          // scala/collection/Seq
  #410 = InterfaceMethodref #409.#374     // scala/collection/Seq.hashCode:()I
  #411 = Utf8               equals
  #412 = Utf8               (Ljava/lang/Object;)Z
  #413 = NameAndType        #411:#412     // equals:(Ljava/lang/Object;)Z
  #414 = Methodref          #5.#413       // java/lang/Object.equals:(Ljava/lang/Object;)Z
  #415 = Methodref          #2.#374       // org/sireum/MBox21.hashCode:()I
  #416 = Utf8               scala/runtime/BoxesRunTime
  #417 = Class              #416          // scala/runtime/BoxesRunTime
  #418 = Utf8               (Ljava/lang/Object;Ljava/lang/Object;)Z
  #419 = NameAndType        #411:#418     // equals:(Ljava/lang/Object;Ljava/lang/Object;)Z
  #420 = Methodref          #417.#419     // scala/runtime/BoxesRunTime.equals:(Ljava/lang/Object;Ljava/lang/Object;)Z
  #421 = Utf8               (Ljava/lang/Object;Ljava/lang/Object;Ljava/lang/Object;Ljava/lang/Object;Ljava/lang/Object;Ljava/lang/Object;Ljava/lang/Object;Ljava/lang/Object;Ljava/lang/Object;Ljava/lang/Object;Ljava/lang/Object;Ljava/lang/Object;Ljava/lang/Object;Ljava/lang/Object;Ljava/lang/Object;Ljava/lang/Object;Ljava/lang/Object;Ljava/lang/Object;Ljava/lang/Object;Ljava/lang/Object;Ljava/lang/Object;)Lorg/sireum/MBox21;
  #422 = Utf8               (TT1;TT2;TT3;TT4;TT5;TT6;TT7;TT8;TT9;TT10;TT11;TT12;TT13;TT14;TT15;TT16;TT17;TT18;TT19;TT20;TT21;)Lorg/sireum/MBox21<TT1;TT2;TT3;TT4;TT5;TT6;TT7;TT8;TT9;TT10;TT11;TT12;TT13;TT14;TT15;TT16;TT17;TT18;TT19;TT20;TT21;>;
  #423 = Utf8               (Ljava/lang/Object;Ljava/lang/Object;Ljava/lang/Object;Ljava/lang/Object;Ljava/lang/Object;Ljava/lang/Object;Ljava/lang/Object;Ljava/lang/Object;Ljava/lang/Object;Ljava/lang/Object;Ljava/lang/Object;Ljava/lang/Object;Ljava/lang/Object;Ljava/lang/Object;Ljava/lang/Object;Ljava/lang/Object;Ljava/lang/Object;Ljava/lang/Object;Ljava/lang/Object;Ljava/lang/Object;Ljava/lang/Object;)V
  #424 = NameAndType        #292:#423     // "<init>":(Ljava/lang/Object;Ljava/lang/Object;Ljava/lang/Object;Ljava/lang/Object;Ljava/lang/Object;Ljava/lang/Object;Ljava/lang/Object;Ljava/lang/Object;Ljava/lang/Object;Ljava/lang/Object;Ljava/lang/Object;Ljava/lang/Object;Ljava/lang/Object;Ljava/lang/Object;Ljava/lang/Object;Ljava/lang/Object;Ljava/lang/Object;Ljava/lang/Object;Ljava/lang/Object;Ljava/lang/Object;Ljava/lang/Object;)V
  #425 = Methodref          #2.#424       // org/sireum/MBox21."<init>":(Ljava/lang/Object;Ljava/lang/Object;Ljava/lang/Object;Ljava/lang/Object;Ljava/lang/Object;Ljava/lang/Object;Ljava/lang/Object;Ljava/lang/Object;Ljava/lang/Object;Ljava/lang/Object;Ljava/lang/Object;Ljava/lang/Object;Ljava/lang/Object;Ljava/lang/Object;Ljava/lang/Object;Ljava/lang/Object;Ljava/lang/Object;Ljava/lang/Object;Ljava/lang/Object;Ljava/lang/Object;Ljava/lang/Object;)V
  #426 = Utf8               apply$default$1
  #427 = Utf8               apply$default$2
  #428 = Utf8               apply$default$3
  #429 = Utf8               apply$default$4
  #430 = Utf8               apply$default$5
  #431 = Utf8               apply$default$6
  #432 = Utf8               apply$default$7
  #433 = Utf8               apply$default$8
  #434 = Utf8               apply$default$9
  #435 = Utf8               apply$default$10
  #436 = Utf8               apply$default$11
  #437 = Utf8               apply$default$12
  #438 = Utf8               apply$default$13
  #439 = Utf8               apply$default$14
  #440 = Utf8               apply$default$15
  #441 = Utf8               apply$default$16
  #442 = Utf8               apply$default$17
  #443 = Utf8               apply$default$18
  #444 = Utf8               apply$default$19
  #445 = Utf8               apply$default$20
  #446 = Utf8               apply$default$21
  #447 = Utf8               $content
  #448 = Utf8               ()Lscala/collection/immutable/Seq;
  #449 = Utf8               ()Lscala/collection/immutable/Seq<Lscala/Tuple2<Ljava/lang/String;Ljava/lang/Object;>;>;
  #450 = Utf8               scala/Tuple2
  #451 = Class              #450          // scala/Tuple2
  #452 = Utf8               type
  #453 = String             #452          // type
  #454 = Utf8               List
  #455 = Utf8               ()Lscala/collection/immutable/List$;
  #456 = NameAndType        #454:#455     // List:()Lscala/collection/immutable/List$;
  #457 = Methodref          #377.#456     // scala/package$.List:()Lscala/collection/immutable/List$;
  #458 = Utf8               org
  #459 = String             #458          // org
  #460 = Utf8               sireum
  #461 = String             #460          // sireum
  #462 = Utf8               [Ljava/lang/Object;
  #463 = Class              #462          // "[Ljava/lang/Object;"
  #464 = Utf8               wrapRefArray
  #465 = Utf8               ([Ljava/lang/Object;)Lscala/collection/immutable/ArraySeq;
  #466 = NameAndType        #464:#465     // wrapRefArray:([Ljava/lang/Object;)Lscala/collection/immutable/ArraySeq;
  #467 = Methodref          #386.#466     // scala/runtime/ScalaRunTime$.wrapRefArray:([Ljava/lang/Object;)Lscala/collection/immutable/ArraySeq;
  #468 = Utf8               scala/collection/immutable/List$
  #469 = Class              #468          // scala/collection/immutable/List$
  #470 = Utf8               (Lscala/collection/immutable/Seq;)Ljava/lang/Object;
  #471 = NameAndType        #366:#470     // apply:(Lscala/collection/immutable/Seq;)Ljava/lang/Object;
  #472 = Methodref          #469.#471     // scala/collection/immutable/List$.apply:(Lscala/collection/immutable/Seq;)Ljava/lang/Object;
  #473 = Utf8               (Ljava/lang/Object;Ljava/lang/Object;)V
  #474 = NameAndType        #292:#473     // "<init>":(Ljava/lang/Object;Ljava/lang/Object;)V
  #475 = Methodref          #451.#474     // scala/Tuple2."<init>":(Ljava/lang/Object;Ljava/lang/Object;)V
  #476 = String             #112          // value1
  #477 = String             #122          // value2
  #478 = String             #130          // value3
  #479 = String             #138          // value4
  #480 = String             #146          // value5
  #481 = String             #154          // value6
  #482 = String             #162          // value7
  #483 = String             #170          // value8
  #484 = String             #178          // value9
  #485 = String             #186          // value10
  #486 = String             #194          // value11
  #487 = String             #202          // value12
  #488 = String             #210          // value13
  #489 = String             #218          // value14
  #490 = String             #226          // value15
  #491 = String             #234          // value16
  #492 = String             #242          // value17
  #493 = String             #250          // value18
  #494 = String             #258          // value19
  #495 = String             #266          // value20
  #496 = String             #274          // value21
  #497 = Utf8               scala/collection/immutable/Seq
  #498 = Class              #497          // scala/collection/immutable/Seq
  #499 = Utf8               $clone
  #500 = Utf8               ()Lorg/sireum/MBox21;
  #501 = Utf8               ()Lorg/sireum/MBox21<TT1;TT2;TT3;TT4;TT5;TT6;TT7;TT8;TT9;TT10;TT11;TT12;TT13;TT14;TT15;TT16;TT17;TT18;TT19;TT20;TT21;>;
  #502 = Utf8               org/sireum/helper$
  #503 = Class              #502          // org/sireum/helper$
  #504 = Utf8               Lorg/sireum/helper$;
  #505 = NameAndType        #63:#504      // MODULE$:Lorg/sireum/helper$;
  #506 = Fieldref           #503.#505     // org/sireum/helper$.MODULE$:Lorg/sireum/helper$;
  #507 = Utf8               cloneAssign
  #508 = Utf8               (Ljava/lang/Object;)Ljava/lang/Object;
  #509 = NameAndType        #507:#508     // cloneAssign:(Ljava/lang/Object;)Ljava/lang/Object;
  #510 = Methodref          #503.#509     // org/sireum/helper$.cloneAssign:(Ljava/lang/Object;)Ljava/lang/Object;
  #511 = Utf8               r
  #512 = Utf8               (Z)Lorg/sireum/$internal/MutableMarker;
  #513 = NameAndType        #77:#78       // $owned_$eq:(Z)Lorg/sireum/RecordSig;
  #514 = Methodref          #2.#513       // org/sireum/MBox21.$owned_$eq:(Z)Lorg/sireum/RecordSig;
  #515 = NameAndType        #499:#500     // $clone:()Lorg/sireum/MBox21;
  #516 = Methodref          #2.#515       // org/sireum/MBox21.$clone:()Lorg/sireum/MBox21;
  #517 = Utf8               ()Lorg/sireum/$internal/MutableMarker;
  #518 = Utf8               (TT1;TT2;TT3;TT4;TT5;TT6;TT7;TT8;TT9;TT10;TT11;TT12;TT13;TT14;TT15;TT16;TT17;TT18;TT19;TT20;TT21;)V
  #519 = Utf8               __value1
  #520 = Utf8               __value2
  #521 = Utf8               __value3
  #522 = Utf8               __value4
  #523 = Utf8               __value5
  #524 = Utf8               __value6
  #525 = Utf8               __value7
  #526 = Utf8               __value8
  #527 = Utf8               __value9
  #528 = Utf8               __value10
  #529 = Utf8               __value11
  #530 = Utf8               __value12
  #531 = Utf8               __value13
  #532 = Utf8               __value14
  #533 = Utf8               __value15
  #534 = Utf8               __value16
  #535 = Utf8               __value17
  #536 = Utf8               __value18
  #537 = Utf8               __value19
  #538 = Utf8               __value20
  #539 = Utf8               __value21
  #540 = Methodref          #5.#294       // java/lang/Object."<init>":()V
  #541 = Utf8               $init$
  #542 = Utf8               (Lorg/sireum/Mutable;)V
  #543 = NameAndType        #541:#542     // $init$:(Lorg/sireum/Mutable;)V
  #544 = InterfaceMethodref #93.#543      // org/sireum/Mutable.$init$:(Lorg/sireum/Mutable;)V
  #545 = Utf8               (Lorg/sireum/RecordSig;)V
  #546 = NameAndType        #541:#545     // $init$:(Lorg/sireum/RecordSig;)V
  #547 = InterfaceMethodref #7.#546       // org/sireum/RecordSig.$init$:(Lorg/sireum/RecordSig;)V
  #548 = Utf8               Signature
  #549 = Utf8               Code
  #550 = Utf8               LocalVariableTable
  #551 = Utf8               MethodParameters
  #552 = Utf8               LineNumberTable
  #553 = Utf8               StackMapTable
  #554 = Utf8               SourceFile
  #555 = Utf8               RuntimeVisibleAnnotations
  #556 = Utf8               ScalaInlineInfo
  #557 = Utf8               ScalaSig
{
  private T1 _value1;
    descriptor: Ljava/lang/Object;
    flags: (0x0002) ACC_PRIVATE
    Signature: #14                          // TT1;

  private T2 _value2;
    descriptor: Ljava/lang/Object;
    flags: (0x0002) ACC_PRIVATE
    Signature: #16                          // TT2;

  private T3 _value3;
    descriptor: Ljava/lang/Object;
    flags: (0x0002) ACC_PRIVATE
    Signature: #18                          // TT3;

  private T4 _value4;
    descriptor: Ljava/lang/Object;
    flags: (0x0002) ACC_PRIVATE
    Signature: #20                          // TT4;

  private T5 _value5;
    descriptor: Ljava/lang/Object;
    flags: (0x0002) ACC_PRIVATE
    Signature: #22                          // TT5;

  private T6 _value6;
    descriptor: Ljava/lang/Object;
    flags: (0x0002) ACC_PRIVATE
    Signature: #24                          // TT6;

  private T7 _value7;
    descriptor: Ljava/lang/Object;
    flags: (0x0002) ACC_PRIVATE
    Signature: #26                          // TT7;

  private T8 _value8;
    descriptor: Ljava/lang/Object;
    flags: (0x0002) ACC_PRIVATE
    Signature: #28                          // TT8;

  private T9 _value9;
    descriptor: Ljava/lang/Object;
    flags: (0x0002) ACC_PRIVATE
    Signature: #30                          // TT9;

  private T10 _value10;
    descriptor: Ljava/lang/Object;
    flags: (0x0002) ACC_PRIVATE
    Signature: #32                          // TT10;

  private T11 _value11;
    descriptor: Ljava/lang/Object;
    flags: (0x0002) ACC_PRIVATE
    Signature: #34                          // TT11;

  private T12 _value12;
    descriptor: Ljava/lang/Object;
    flags: (0x0002) ACC_PRIVATE
    Signature: #36                          // TT12;

  private T13 _value13;
    descriptor: Ljava/lang/Object;
    flags: (0x0002) ACC_PRIVATE
    Signature: #38                          // TT13;

  private T14 _value14;
    descriptor: Ljava/lang/Object;
    flags: (0x0002) ACC_PRIVATE
    Signature: #40                          // TT14;

  private T15 _value15;
    descriptor: Ljava/lang/Object;
    flags: (0x0002) ACC_PRIVATE
    Signature: #42                          // TT15;

  private T16 _value16;
    descriptor: Ljava/lang/Object;
    flags: (0x0002) ACC_PRIVATE
    Signature: #44                          // TT16;

  private T17 _value17;
    descriptor: Ljava/lang/Object;
    flags: (0x0002) ACC_PRIVATE
    Signature: #46                          // TT17;

  private T18 _value18;
    descriptor: Ljava/lang/Object;
    flags: (0x0002) ACC_PRIVATE
    Signature: #48                          // TT18;

  private T19 _value19;
    descriptor: Ljava/lang/Object;
    flags: (0x0002) ACC_PRIVATE
    Signature: #50                          // TT19;

  private T20 _value20;
    descriptor: Ljava/lang/Object;
    flags: (0x0002) ACC_PRIVATE
    Signature: #52                          // TT20;

  private T21 _value21;
    descriptor: Ljava/lang/Object;
    flags: (0x0002) ACC_PRIVATE
    Signature: #54                          // TT21;

  private boolean org$sireum$RecordSig$$$isOwned;
    descriptor: Z
    flags: (0x0002) ACC_PRIVATE

  public static <T1 extends java.lang.Object, T2 extends java.lang.Object, T3 extends java.lang.Object, T4 extends java.lang.Object, T5 extends java.lang.Object, T6 extends java.lang.Object, T7 extends java.lang.Object, T8 extends java.lang.Object, T9 extends java.lang.Object, T10 extends java.lang.Object, T11 extends java.lang.Object, T12 extends java.lang.Object, T13 extends java.lang.Object, T14 extends java.lang.Object, T15 extends java.lang.Object, T16 extends java.lang.Object, T17 extends java.lang.Object, T18 extends java.lang.Object, T19 extends java.lang.Object, T20 extends java.lang.Object, T21 extends java.lang.Object> scala.Some<scala.Tuple21<T1, T2, T3, T4, T5, T6, T7, T8, T9, T10, T11, T12, T13, T14, T15, T16, T17, T18, T19, T20, T21>> unapply(org.sireum.MBox21<T1, T2, T3, T4, T5, T6, T7, T8, T9, T10, T11, T12, T13, T14, T15, T16, T17, T18, T19, T20, T21>);
    descriptor: (Lorg/sireum/MBox21;)Lscala/Some;
    flags: (0x0009) ACC_PUBLIC, ACC_STATIC
    Code:
      stack=2, locals=1, args_size=1
         0: getstatic     #66                 // Field org/sireum/MBox21$.MODULE$:Lorg/sireum/MBox21$;
         3: aload_0
         4: invokevirtual #68                 // Method org/sireum/MBox21$.unapply:(Lorg/sireum/MBox21;)Lscala/Some;
         7: areturn
      LocalVariableTable:
        Start  Length  Slot  Name   Signature
            0       8     0     o   Lorg/sireum/MBox21;
    Signature: #59                          // <T1:Ljava/lang/Object;T2:Ljava/lang/Object;T3:Ljava/lang/Object;T4:Ljava/lang/Object;T5:Ljava/lang/Object;T6:Ljava/lang/Object;T7:Ljava/lang/Object;T8:Ljava/lang/Object;T9:Ljava/lang/Object;T10:Ljava/lang/Object;T11:Ljava/lang/Object;T12:Ljava/lang/Object;T13:Ljava/lang/Object;T14:Ljava/lang/Object;T15:Ljava/lang/Object;T16:Ljava/lang/Object;T17:Ljava/lang/Object;T18:Ljava/lang/Object;T19:Ljava/lang/Object;T20:Ljava/lang/Object;T21:Ljava/lang/Object;>(Lorg/sireum/MBox21<TT1;TT2;TT3;TT4;TT5;TT6;TT7;TT8;TT9;TT10;TT11;TT12;TT13;TT14;TT15;TT16;TT17;TT18;TT19;TT20;TT21;>;)Lscala/Some<Lscala/Tuple21<TT1;TT2;TT3;TT4;TT5;TT6;TT7;TT8;TT9;TT10;TT11;TT12;TT13;TT14;TT15;TT16;TT17;TT18;TT19;TT20;TT21;>;>;
    MethodParameters:
      Name                           Flags
      o                              final

  public final boolean $owned();
    descriptor: ()Z
    flags: (0x0011) ACC_PUBLIC, ACC_FINAL
    Code:
      stack=1, locals=1, args_size=1
         0: aload_0
         1: invokestatic  #75                 // InterfaceMethod org/sireum/RecordSig.$owned$:(Lorg/sireum/RecordSig;)Z
         4: ireturn
      LineNumberTable:
        line 69: 0
      LocalVariableTable:
        Start  Length  Slot  Name   Signature
            0       5     0  this   Lorg/sireum/MBox21;

  public final org.sireum.RecordSig $owned_$eq(boolean);
    descriptor: (Z)Lorg/sireum/RecordSig;
    flags: (0x0011) ACC_PUBLIC, ACC_FINAL
    Code:
      stack=2, locals=2, args_size=2
         0: aload_0
         1: iload_1
         2: invokestatic  #83                 // InterfaceMethod org/sireum/RecordSig.$owned_$eq$:(Lorg/sireum/RecordSig;Z)Lorg/sireum/RecordSig;
         5: areturn
      LineNumberTable:
        line 69: 0
      LocalVariableTable:
        Start  Length  Slot  Name   Signature
            0       6     0  this   Lorg/sireum/MBox21;
            0       6     1     b   Z
    MethodParameters:
      Name                           Flags
      b                              final

  public org.sireum.Z hash();
    descriptor: ()Lorg/sireum/Z;
    flags: (0x0001) ACC_PUBLIC
    Code:
      stack=1, locals=1, args_size=1
         0: aload_0
         1: invokestatic  #89                 // InterfaceMethod org/sireum/RecordSig.hash$:(Lorg/sireum/RecordSig;)Lorg/sireum/Z;
         4: areturn
      LineNumberTable:
        line 69: 0
      LocalVariableTable:
        Start  Length  Slot  Name   Signature
            0       5     0  this   Lorg/sireum/MBox21;

  public final scala.runtime.Nothing$ $cannotMixImmutableAndMutable();
    descriptor: ()Lscala/runtime/Nothing$;
    flags: (0x0011) ACC_PUBLIC, ACC_FINAL
    Code:
      stack=1, locals=1, args_size=1
         0: aload_0
         1: invokestatic  #97                 // InterfaceMethod org/sireum/Mutable.$cannotMixImmutableAndMutable$:(Lorg/sireum/Mutable;)Lscala/runtime/Nothing$;
         4: areturn
      LineNumberTable:
        line 69: 0
      LocalVariableTable:
        Start  Length  Slot  Name   Signature
            0       5     0  this   Lorg/sireum/MBox21;

  public boolean $hasEquals();
    descriptor: ()Z
    flags: (0x0001) ACC_PUBLIC
    Code:
      stack=1, locals=1, args_size=1
         0: aload_0
         1: invokestatic  #102                // InterfaceMethod org/sireum/Mutable.$hasEquals$:(Lorg/sireum/Mutable;)Z
         4: ireturn
      LineNumberTable:
        line 69: 0
      LocalVariableTable:
        Start  Length  Slot  Name   Signature
            0       5     0  this   Lorg/sireum/MBox21;

  public boolean $hasString();
    descriptor: ()Z
    flags: (0x0001) ACC_PUBLIC
    Code:
      stack=1, locals=1, args_size=1
         0: aload_0
         1: invokestatic  #106                // InterfaceMethod org/sireum/Mutable.$hasString$:(Lorg/sireum/Mutable;)Z
         4: ireturn
      LineNumberTable:
        line 69: 0
      LocalVariableTable:
        Start  Length  Slot  Name   Signature
            0       5     0  this   Lorg/sireum/MBox21;

  public boolean org$sireum$RecordSig$$$isOwned();
    descriptor: ()Z
    flags: (0x0001) ACC_PUBLIC
    Code:
      stack=1, locals=1, args_size=1
         0: aload_0
         1: getfield      #108                // Field org$sireum$RecordSig$$$isOwned:Z
         4: ireturn
      LineNumberTable:
        line 69: 0
      LocalVariableTable:
        Start  Length  Slot  Name   Signature
            0       5     0  this   Lorg/sireum/MBox21;

  public void org$sireum$RecordSig$$$isOwned_$eq(boolean);
    descriptor: (Z)V
    flags: (0x0001) ACC_PUBLIC
    Code:
      stack=2, locals=2, args_size=2
         0: aload_0
         1: iload_1
         2: putfield      #108                // Field org$sireum$RecordSig$$$isOwned:Z
         5: return
      LineNumberTable:
        line 69: 0
      LocalVariableTable:
        Start  Length  Slot  Name   Signature
            0       6     0  this   Lorg/sireum/MBox21;
            0       6     1   x$1   Z
    MethodParameters:
      Name                           Flags
      x$1                            final

  public T1 value1();
    descriptor: ()Ljava/lang/Object;
    flags: (0x0001) ACC_PUBLIC
    Code:
      stack=1, locals=1, args_size=1
         0: aload_0
         1: getfield      #116                // Field _value1:Ljava/lang/Object;
         4: areturn
      LineNumberTable:
        line 69: 0
      LocalVariableTable:
        Start  Length  Slot  Name   Signature
            0       5     0  this   Lorg/sireum/MBox21;
    Signature: #114                         // ()TT1;

  public T1 getValue1();
    descriptor: ()Ljava/lang/Object;
    flags: (0x0001) ACC_PUBLIC
    Code:
      stack=1, locals=1, args_size=1
         0: aload_0
         1: getfield      #116                // Field _value1:Ljava/lang/Object;
         4: areturn
      LineNumberTable:
        line 69: 0
      LocalVariableTable:
        Start  Length  Slot  Name   Signature
            0       5     0  this   Lorg/sireum/MBox21;
    Signature: #114                         // ()TT1;

  public org.sireum.MBox21<T1, T2, T3, T4, T5, T6, T7, T8, T9, T10, T11, T12, T13, T14, T15, T16, T17, T18, T19, T20, T21> value1_$eq(T1);
    descriptor: (Ljava/lang/Object;)Lorg/sireum/MBox21;
    flags: (0x0001) ACC_PUBLIC
    Code:
      stack=2, locals=2, args_size=2
         0: aload_0
         1: aload_1
         2: putfield      #116                // Field _value1:Ljava/lang/Object;
         5: aload_0
         6: areturn
      LineNumberTable:
        line 69: 0
      LocalVariableTable:
        Start  Length  Slot  Name   Signature
            0       7     0  this   Lorg/sireum/MBox21;
            0       7     1 value1   Ljava/lang/Object;
    Signature: #120                         // (TT1;)Lorg/sireum/MBox21<TT1;TT2;TT3;TT4;TT5;TT6;TT7;TT8;TT9;TT10;TT11;TT12;TT13;TT14;TT15;TT16;TT17;TT18;TT19;TT20;TT21;>;
    MethodParameters:
      Name                           Flags
      value1                         final

  public org.sireum.MBox21<T1, T2, T3, T4, T5, T6, T7, T8, T9, T10, T11, T12, T13, T14, T15, T16, T17, T18, T19, T20, T21> setValue1(T1);
    descriptor: (Ljava/lang/Object;)Lorg/sireum/MBox21;
    flags: (0x0001) ACC_PUBLIC
    Code:
      stack=2, locals=2, args_size=2
         0: aload_0
         1: aload_1
         2: putfield      #116                // Field _value1:Ljava/lang/Object;
         5: aload_0
         6: areturn
      LineNumberTable:
        line 69: 0
      LocalVariableTable:
        Start  Length  Slot  Name   Signature
            0       7     0  this   Lorg/sireum/MBox21;
            0       7     1 value1   Ljava/lang/Object;
    Signature: #120                         // (TT1;)Lorg/sireum/MBox21<TT1;TT2;TT3;TT4;TT5;TT6;TT7;TT8;TT9;TT10;TT11;TT12;TT13;TT14;TT15;TT16;TT17;TT18;TT19;TT20;TT21;>;
    MethodParameters:
      Name                           Flags
      value1                         final

  public T2 value2();
    descriptor: ()Ljava/lang/Object;
    flags: (0x0001) ACC_PUBLIC
    Code:
      stack=1, locals=1, args_size=1
         0: aload_0
         1: getfield      #125                // Field _value2:Ljava/lang/Object;
         4: areturn
      LineNumberTable:
        line 69: 0
      LocalVariableTable:
        Start  Length  Slot  Name   Signature
            0       5     0  this   Lorg/sireum/MBox21;
    Signature: #123                         // ()TT2;

  public T2 getValue2();
    descriptor: ()Ljava/lang/Object;
    flags: (0x0001) ACC_PUBLIC
    Code:
      stack=1, locals=1, args_size=1
         0: aload_0
         1: getfield      #125                // Field _value2:Ljava/lang/Object;
         4: areturn
      LineNumberTable:
        line 69: 0
      LocalVariableTable:
        Start  Length  Slot  Name   Signature
            0       5     0  this   Lorg/sireum/MBox21;
    Signature: #123                         // ()TT2;

  public org.sireum.MBox21<T1, T2, T3, T4, T5, T6, T7, T8, T9, T10, T11, T12, T13, T14, T15, T16, T17, T18, T19, T20, T21> value2_$eq(T2);
    descriptor: (Ljava/lang/Object;)Lorg/sireum/MBox21;
    flags: (0x0001) ACC_PUBLIC
    Code:
      stack=2, locals=2, args_size=2
         0: aload_0
         1: aload_1
         2: putfield      #125                // Field _value2:Ljava/lang/Object;
         5: aload_0
         6: areturn
      LineNumberTable:
        line 69: 0
      LocalVariableTable:
        Start  Length  Slot  Name   Signature
            0       7     0  this   Lorg/sireum/MBox21;
            0       7     1 value2   Ljava/lang/Object;
    Signature: #128                         // (TT2;)Lorg/sireum/MBox21<TT1;TT2;TT3;TT4;TT5;TT6;TT7;TT8;TT9;TT10;TT11;TT12;TT13;TT14;TT15;TT16;TT17;TT18;TT19;TT20;TT21;>;
    MethodParameters:
      Name                           Flags
      value2                         final

  public org.sireum.MBox21<T1, T2, T3, T4, T5, T6, T7, T8, T9, T10, T11, T12, T13, T14, T15, T16, T17, T18, T19, T20, T21> setValue2(T2);
    descriptor: (Ljava/lang/Object;)Lorg/sireum/MBox21;
    flags: (0x0001) ACC_PUBLIC
    Code:
      stack=2, locals=2, args_size=2
         0: aload_0
         1: aload_1
         2: putfield      #125                // Field _value2:Ljava/lang/Object;
         5: aload_0
         6: areturn
      LineNumberTable:
        line 69: 0
      LocalVariableTable:
        Start  Length  Slot  Name   Signature
            0       7     0  this   Lorg/sireum/MBox21;
            0       7     1 value2   Ljava/lang/Object;
    Signature: #128                         // (TT2;)Lorg/sireum/MBox21<TT1;TT2;TT3;TT4;TT5;TT6;TT7;TT8;TT9;TT10;TT11;TT12;TT13;TT14;TT15;TT16;TT17;TT18;TT19;TT20;TT21;>;
    MethodParameters:
      Name                           Flags
      value2                         final

  public T3 value3();
    descriptor: ()Ljava/lang/Object;
    flags: (0x0001) ACC_PUBLIC
    Code:
      stack=1, locals=1, args_size=1
         0: aload_0
         1: getfield      #133                // Field _value3:Ljava/lang/Object;
         4: areturn
      LineNumberTable:
        line 69: 0
      LocalVariableTable:
        Start  Length  Slot  Name   Signature
            0       5     0  this   Lorg/sireum/MBox21;
    Signature: #131                         // ()TT3;

  public T3 getValue3();
    descriptor: ()Ljava/lang/Object;
    flags: (0x0001) ACC_PUBLIC
    Code:
      stack=1, locals=1, args_size=1
         0: aload_0
         1: getfield      #133                // Field _value3:Ljava/lang/Object;
         4: areturn
      LineNumberTable:
        line 69: 0
      LocalVariableTable:
        Start  Length  Slot  Name   Signature
            0       5     0  this   Lorg/sireum/MBox21;
    Signature: #131                         // ()TT3;

  public org.sireum.MBox21<T1, T2, T3, T4, T5, T6, T7, T8, T9, T10, T11, T12, T13, T14, T15, T16, T17, T18, T19, T20, T21> value3_$eq(T3);
    descriptor: (Ljava/lang/Object;)Lorg/sireum/MBox21;
    flags: (0x0001) ACC_PUBLIC
    Code:
      stack=2, locals=2, args_size=2
         0: aload_0
         1: aload_1
         2: putfield      #133                // Field _value3:Ljava/lang/Object;
         5: aload_0
         6: areturn
      LineNumberTable:
        line 69: 0
      LocalVariableTable:
        Start  Length  Slot  Name   Signature
            0       7     0  this   Lorg/sireum/MBox21;
            0       7     1 value3   Ljava/lang/Object;
    Signature: #136                         // (TT3;)Lorg/sireum/MBox21<TT1;TT2;TT3;TT4;TT5;TT6;TT7;TT8;TT9;TT10;TT11;TT12;TT13;TT14;TT15;TT16;TT17;TT18;TT19;TT20;TT21;>;
    MethodParameters:
      Name                           Flags
      value3                         final

  public org.sireum.MBox21<T1, T2, T3, T4, T5, T6, T7, T8, T9, T10, T11, T12, T13, T14, T15, T16, T17, T18, T19, T20, T21> setValue3(T3);
    descriptor: (Ljava/lang/Object;)Lorg/sireum/MBox21;
    flags: (0x0001) ACC_PUBLIC
    Code:
      stack=2, locals=2, args_size=2
         0: aload_0
         1: aload_1
         2: putfield      #133                // Field _value3:Ljava/lang/Object;
         5: aload_0
         6: areturn
      LineNumberTable:
        line 69: 0
      LocalVariableTable:
        Start  Length  Slot  Name   Signature
            0       7     0  this   Lorg/sireum/MBox21;
            0       7     1 value3   Ljava/lang/Object;
    Signature: #136                         // (TT3;)Lorg/sireum/MBox21<TT1;TT2;TT3;TT4;TT5;TT6;TT7;TT8;TT9;TT10;TT11;TT12;TT13;TT14;TT15;TT16;TT17;TT18;TT19;TT20;TT21;>;
    MethodParameters:
      Name                           Flags
      value3                         final

  public T4 value4();
    descriptor: ()Ljava/lang/Object;
    flags: (0x0001) ACC_PUBLIC
    Code:
      stack=1, locals=1, args_size=1
         0: aload_0
         1: getfield      #141                // Field _value4:Ljava/lang/Object;
         4: areturn
      LineNumberTable:
        line 69: 0
      LocalVariableTable:
        Start  Length  Slot  Name   Signature
            0       5     0  this   Lorg/sireum/MBox21;
    Signature: #139                         // ()TT4;

  public T4 getValue4();
    descriptor: ()Ljava/lang/Object;
    flags: (0x0001) ACC_PUBLIC
    Code:
      stack=1, locals=1, args_size=1
         0: aload_0
         1: getfield      #141                // Field _value4:Ljava/lang/Object;
         4: areturn
      LineNumberTable:
        line 69: 0
      LocalVariableTable:
        Start  Length  Slot  Name   Signature
            0       5     0  this   Lorg/sireum/MBox21;
    Signature: #139                         // ()TT4;

  public org.sireum.MBox21<T1, T2, T3, T4, T5, T6, T7, T8, T9, T10, T11, T12, T13, T14, T15, T16, T17, T18, T19, T20, T21> value4_$eq(T4);
    descriptor: (Ljava/lang/Object;)Lorg/sireum/MBox21;
    flags: (0x0001) ACC_PUBLIC
    Code:
      stack=2, locals=2, args_size=2
         0: aload_0
         1: aload_1
         2: putfield      #141                // Field _value4:Ljava/lang/Object;
         5: aload_0
         6: areturn
      LineNumberTable:
        line 69: 0
      LocalVariableTable:
        Start  Length  Slot  Name   Signature
            0       7     0  this   Lorg/sireum/MBox21;
            0       7     1 value4   Ljava/lang/Object;
    Signature: #144                         // (TT4;)Lorg/sireum/MBox21<TT1;TT2;TT3;TT4;TT5;TT6;TT7;TT8;TT9;TT10;TT11;TT12;TT13;TT14;TT15;TT16;TT17;TT18;TT19;TT20;TT21;>;
    MethodParameters:
      Name                           Flags
      value4                         final

  public org.sireum.MBox21<T1, T2, T3, T4, T5, T6, T7, T8, T9, T10, T11, T12, T13, T14, T15, T16, T17, T18, T19, T20, T21> setValue4(T4);
    descriptor: (Ljava/lang/Object;)Lorg/sireum/MBox21;
    flags: (0x0001) ACC_PUBLIC
    Code:
      stack=2, locals=2, args_size=2
         0: aload_0
         1: aload_1
         2: putfield      #141                // Field _value4:Ljava/lang/Object;
         5: aload_0
         6: areturn
      LineNumberTable:
        line 69: 0
      LocalVariableTable:
        Start  Length  Slot  Name   Signature
            0       7     0  this   Lorg/sireum/MBox21;
            0       7     1 value4   Ljava/lang/Object;
    Signature: #144                         // (TT4;)Lorg/sireum/MBox21<TT1;TT2;TT3;TT4;TT5;TT6;TT7;TT8;TT9;TT10;TT11;TT12;TT13;TT14;TT15;TT16;TT17;TT18;TT19;TT20;TT21;>;
    MethodParameters:
      Name                           Flags
      value4                         final

  public T5 value5();
    descriptor: ()Ljava/lang/Object;
    flags: (0x0001) ACC_PUBLIC
    Code:
      stack=1, locals=1, args_size=1
         0: aload_0
         1: getfield      #149                // Field _value5:Ljava/lang/Object;
         4: areturn
      LineNumberTable:
        line 69: 0
      LocalVariableTable:
        Start  Length  Slot  Name   Signature
            0       5     0  this   Lorg/sireum/MBox21;
    Signature: #147                         // ()TT5;

  public T5 getValue5();
    descriptor: ()Ljava/lang/Object;
    flags: (0x0001) ACC_PUBLIC
    Code:
      stack=1, locals=1, args_size=1
         0: aload_0
         1: getfield      #149                // Field _value5:Ljava/lang/Object;
         4: areturn
      LineNumberTable:
        line 69: 0
      LocalVariableTable:
        Start  Length  Slot  Name   Signature
            0       5     0  this   Lorg/sireum/MBox21;
    Signature: #147                         // ()TT5;

  public org.sireum.MBox21<T1, T2, T3, T4, T5, T6, T7, T8, T9, T10, T11, T12, T13, T14, T15, T16, T17, T18, T19, T20, T21> value5_$eq(T5);
    descriptor: (Ljava/lang/Object;)Lorg/sireum/MBox21;
    flags: (0x0001) ACC_PUBLIC
    Code:
      stack=2, locals=2, args_size=2
         0: aload_0
         1: aload_1
         2: putfield      #149                // Field _value5:Ljava/lang/Object;
         5: aload_0
         6: areturn
      LineNumberTable:
        line 69: 0
      LocalVariableTable:
        Start  Length  Slot  Name   Signature
            0       7     0  this   Lorg/sireum/MBox21;
            0       7     1 value5   Ljava/lang/Object;
    Signature: #152                         // (TT5;)Lorg/sireum/MBox21<TT1;TT2;TT3;TT4;TT5;TT6;TT7;TT8;TT9;TT10;TT11;TT12;TT13;TT14;TT15;TT16;TT17;TT18;TT19;TT20;TT21;>;
    MethodParameters:
      Name                           Flags
      value5                         final

  public org.sireum.MBox21<T1, T2, T3, T4, T5, T6, T7, T8, T9, T10, T11, T12, T13, T14, T15, T16, T17, T18, T19, T20, T21> setValue5(T5);
    descriptor: (Ljava/lang/Object;)Lorg/sireum/MBox21;
    flags: (0x0001) ACC_PUBLIC
    Code:
      stack=2, locals=2, args_size=2
         0: aload_0
         1: aload_1
         2: putfield      #149                // Field _value5:Ljava/lang/Object;
         5: aload_0
         6: areturn
      LineNumberTable:
        line 69: 0
      LocalVariableTable:
        Start  Length  Slot  Name   Signature
            0       7     0  this   Lorg/sireum/MBox21;
            0       7     1 value5   Ljava/lang/Object;
    Signature: #152                         // (TT5;)Lorg/sireum/MBox21<TT1;TT2;TT3;TT4;TT5;TT6;TT7;TT8;TT9;TT10;TT11;TT12;TT13;TT14;TT15;TT16;TT17;TT18;TT19;TT20;TT21;>;
    MethodParameters:
      Name                           Flags
      value5                         final

  public T6 value6();
    descriptor: ()Ljava/lang/Object;
    flags: (0x0001) ACC_PUBLIC
    Code:
      stack=1, locals=1, args_size=1
         0: aload_0
         1: getfield      #157                // Field _value6:Ljava/lang/Object;
         4: areturn
      LineNumberTable:
        line 69: 0
      LocalVariableTable:
        Start  Length  Slot  Name   Signature
            0       5     0  this   Lorg/sireum/MBox21;
    Signature: #155                         // ()TT6;

  public T6 getValue6();
    descriptor: ()Ljava/lang/Object;
    flags: (0x0001) ACC_PUBLIC
    Code:
      stack=1, locals=1, args_size=1
         0: aload_0
         1: getfield      #157                // Field _value6:Ljava/lang/Object;
         4: areturn
      LineNumberTable:
        line 69: 0
      LocalVariableTable:
        Start  Length  Slot  Name   Signature
            0       5     0  this   Lorg/sireum/MBox21;
    Signature: #155                         // ()TT6;

  public org.sireum.MBox21<T1, T2, T3, T4, T5, T6, T7, T8, T9, T10, T11, T12, T13, T14, T15, T16, T17, T18, T19, T20, T21> value6_$eq(T6);
    descriptor: (Ljava/lang/Object;)Lorg/sireum/MBox21;
    flags: (0x0001) ACC_PUBLIC
    Code:
      stack=2, locals=2, args_size=2
         0: aload_0
         1: aload_1
         2: putfield      #157                // Field _value6:Ljava/lang/Object;
         5: aload_0
         6: areturn
      LineNumberTable:
        line 69: 0
      LocalVariableTable:
        Start  Length  Slot  Name   Signature
            0       7     0  this   Lorg/sireum/MBox21;
            0       7     1 value6   Ljava/lang/Object;
    Signature: #160                         // (TT6;)Lorg/sireum/MBox21<TT1;TT2;TT3;TT4;TT5;TT6;TT7;TT8;TT9;TT10;TT11;TT12;TT13;TT14;TT15;TT16;TT17;TT18;TT19;TT20;TT21;>;
    MethodParameters:
      Name                           Flags
      value6                         final

  public org.sireum.MBox21<T1, T2, T3, T4, T5, T6, T7, T8, T9, T10, T11, T12, T13, T14, T15, T16, T17, T18, T19, T20, T21> setValue6(T6);
    descriptor: (Ljava/lang/Object;)Lorg/sireum/MBox21;
    flags: (0x0001) ACC_PUBLIC
    Code:
      stack=2, locals=2, args_size=2
         0: aload_0
         1: aload_1
         2: putfield      #157                // Field _value6:Ljava/lang/Object;
         5: aload_0
         6: areturn
      LineNumberTable:
        line 69: 0
      LocalVariableTable:
        Start  Length  Slot  Name   Signature
            0       7     0  this   Lorg/sireum/MBox21;
            0       7     1 value6   Ljava/lang/Object;
    Signature: #160                         // (TT6;)Lorg/sireum/MBox21<TT1;TT2;TT3;TT4;TT5;TT6;TT7;TT8;TT9;TT10;TT11;TT12;TT13;TT14;TT15;TT16;TT17;TT18;TT19;TT20;TT21;>;
    MethodParameters:
      Name                           Flags
      value6                         final

  public T7 value7();
    descriptor: ()Ljava/lang/Object;
    flags: (0x0001) ACC_PUBLIC
    Code:
      stack=1, locals=1, args_size=1
         0: aload_0
         1: getfield      #165                // Field _value7:Ljava/lang/Object;
         4: areturn
      LineNumberTable:
        line 69: 0
      LocalVariableTable:
        Start  Length  Slot  Name   Signature
            0       5     0  this   Lorg/sireum/MBox21;
    Signature: #163                         // ()TT7;

  public T7 getValue7();
    descriptor: ()Ljava/lang/Object;
    flags: (0x0001) ACC_PUBLIC
    Code:
      stack=1, locals=1, args_size=1
         0: aload_0
         1: getfield      #165                // Field _value7:Ljava/lang/Object;
         4: areturn
      LineNumberTable:
        line 69: 0
      LocalVariableTable:
        Start  Length  Slot  Name   Signature
            0       5     0  this   Lorg/sireum/MBox21;
    Signature: #163                         // ()TT7;

  public org.sireum.MBox21<T1, T2, T3, T4, T5, T6, T7, T8, T9, T10, T11, T12, T13, T14, T15, T16, T17, T18, T19, T20, T21> value7_$eq(T7);
    descriptor: (Ljava/lang/Object;)Lorg/sireum/MBox21;
    flags: (0x0001) ACC_PUBLIC
    Code:
      stack=2, locals=2, args_size=2
         0: aload_0
         1: aload_1
         2: putfield      #165                // Field _value7:Ljava/lang/Object;
         5: aload_0
         6: areturn
      LineNumberTable:
        line 69: 0
      LocalVariableTable:
        Start  Length  Slot  Name   Signature
            0       7     0  this   Lorg/sireum/MBox21;
            0       7     1 value7   Ljava/lang/Object;
    Signature: #168                         // (TT7;)Lorg/sireum/MBox21<TT1;TT2;TT3;TT4;TT5;TT6;TT7;TT8;TT9;TT10;TT11;TT12;TT13;TT14;TT15;TT16;TT17;TT18;TT19;TT20;TT21;>;
    MethodParameters:
      Name                           Flags
      value7                         final

  public org.sireum.MBox21<T1, T2, T3, T4, T5, T6, T7, T8, T9, T10, T11, T12, T13, T14, T15, T16, T17, T18, T19, T20, T21> setValue7(T7);
    descriptor: (Ljava/lang/Object;)Lorg/sireum/MBox21;
    flags: (0x0001) ACC_PUBLIC
    Code:
      stack=2, locals=2, args_size=2
         0: aload_0
         1: aload_1
         2: putfield      #165                // Field _value7:Ljava/lang/Object;
         5: aload_0
         6: areturn
      LineNumberTable:
        line 69: 0
      LocalVariableTable:
        Start  Length  Slot  Name   Signature
            0       7     0  this   Lorg/sireum/MBox21;
            0       7     1 value7   Ljava/lang/Object;
    Signature: #168                         // (TT7;)Lorg/sireum/MBox21<TT1;TT2;TT3;TT4;TT5;TT6;TT7;TT8;TT9;TT10;TT11;TT12;TT13;TT14;TT15;TT16;TT17;TT18;TT19;TT20;TT21;>;
    MethodParameters:
      Name                           Flags
      value7                         final

  public T8 value8();
    descriptor: ()Ljava/lang/Object;
    flags: (0x0001) ACC_PUBLIC
    Code:
      stack=1, locals=1, args_size=1
         0: aload_0
         1: getfield      #173                // Field _value8:Ljava/lang/Object;
         4: areturn
      LineNumberTable:
        line 69: 0
      LocalVariableTable:
        Start  Length  Slot  Name   Signature
            0       5     0  this   Lorg/sireum/MBox21;
    Signature: #171                         // ()TT8;

  public T8 getValue8();
    descriptor: ()Ljava/lang/Object;
    flags: (0x0001) ACC_PUBLIC
    Code:
      stack=1, locals=1, args_size=1
         0: aload_0
         1: getfield      #173                // Field _value8:Ljava/lang/Object;
         4: areturn
      LineNumberTable:
        line 69: 0
      LocalVariableTable:
        Start  Length  Slot  Name   Signature
            0       5     0  this   Lorg/sireum/MBox21;
    Signature: #171                         // ()TT8;

  public org.sireum.MBox21<T1, T2, T3, T4, T5, T6, T7, T8, T9, T10, T11, T12, T13, T14, T15, T16, T17, T18, T19, T20, T21> value8_$eq(T8);
    descriptor: (Ljava/lang/Object;)Lorg/sireum/MBox21;
    flags: (0x0001) ACC_PUBLIC
    Code:
      stack=2, locals=2, args_size=2
         0: aload_0
         1: aload_1
         2: putfield      #173                // Field _value8:Ljava/lang/Object;
         5: aload_0
         6: areturn
      LineNumberTable:
        line 69: 0
      LocalVariableTable:
        Start  Length  Slot  Name   Signature
            0       7     0  this   Lorg/sireum/MBox21;
            0       7     1 value8   Ljava/lang/Object;
    Signature: #176                         // (TT8;)Lorg/sireum/MBox21<TT1;TT2;TT3;TT4;TT5;TT6;TT7;TT8;TT9;TT10;TT11;TT12;TT13;TT14;TT15;TT16;TT17;TT18;TT19;TT20;TT21;>;
    MethodParameters:
      Name                           Flags
      value8                         final

  public org.sireum.MBox21<T1, T2, T3, T4, T5, T6, T7, T8, T9, T10, T11, T12, T13, T14, T15, T16, T17, T18, T19, T20, T21> setValue8(T8);
    descriptor: (Ljava/lang/Object;)Lorg/sireum/MBox21;
    flags: (0x0001) ACC_PUBLIC
    Code:
      stack=2, locals=2, args_size=2
         0: aload_0
         1: aload_1
         2: putfield      #173                // Field _value8:Ljava/lang/Object;
         5: aload_0
         6: areturn
      LineNumberTable:
        line 69: 0
      LocalVariableTable:
        Start  Length  Slot  Name   Signature
            0       7     0  this   Lorg/sireum/MBox21;
            0       7     1 value8   Ljava/lang/Object;
    Signature: #176                         // (TT8;)Lorg/sireum/MBox21<TT1;TT2;TT3;TT4;TT5;TT6;TT7;TT8;TT9;TT10;TT11;TT12;TT13;TT14;TT15;TT16;TT17;TT18;TT19;TT20;TT21;>;
    MethodParameters:
      Name                           Flags
      value8                         final

  public T9 value9();
    descriptor: ()Ljava/lang/Object;
    flags: (0x0001) ACC_PUBLIC
    Code:
      stack=1, locals=1, args_size=1
         0: aload_0
         1: getfield      #181                // Field _value9:Ljava/lang/Object;
         4: areturn
      LineNumberTable:
        line 69: 0
      LocalVariableTable:
        Start  Length  Slot  Name   Signature
            0       5     0  this   Lorg/sireum/MBox21;
    Signature: #179                         // ()TT9;

  public T9 getValue9();
    descriptor: ()Ljava/lang/Object;
    flags: (0x0001) ACC_PUBLIC
    Code:
      stack=1, locals=1, args_size=1
         0: aload_0
         1: getfield      #181                // Field _value9:Ljava/lang/Object;
         4: areturn
      LineNumberTable:
        line 69: 0
      LocalVariableTable:
        Start  Length  Slot  Name   Signature
            0       5     0  this   Lorg/sireum/MBox21;
    Signature: #179                         // ()TT9;

  public org.sireum.MBox21<T1, T2, T3, T4, T5, T6, T7, T8, T9, T10, T11, T12, T13, T14, T15, T16, T17, T18, T19, T20, T21> value9_$eq(T9);
    descriptor: (Ljava/lang/Object;)Lorg/sireum/MBox21;
    flags: (0x0001) ACC_PUBLIC
    Code:
      stack=2, locals=2, args_size=2
         0: aload_0
         1: aload_1
         2: putfield      #181                // Field _value9:Ljava/lang/Object;
         5: aload_0
         6: areturn
      LineNumberTable:
        line 69: 0
      LocalVariableTable:
        Start  Length  Slot  Name   Signature
            0       7     0  this   Lorg/sireum/MBox21;
            0       7     1 value9   Ljava/lang/Object;
    Signature: #184                         // (TT9;)Lorg/sireum/MBox21<TT1;TT2;TT3;TT4;TT5;TT6;TT7;TT8;TT9;TT10;TT11;TT12;TT13;TT14;TT15;TT16;TT17;TT18;TT19;TT20;TT21;>;
    MethodParameters:
      Name                           Flags
      value9                         final

  public org.sireum.MBox21<T1, T2, T3, T4, T5, T6, T7, T8, T9, T10, T11, T12, T13, T14, T15, T16, T17, T18, T19, T20, T21> setValue9(T9);
    descriptor: (Ljava/lang/Object;)Lorg/sireum/MBox21;
    flags: (0x0001) ACC_PUBLIC
    Code:
      stack=2, locals=2, args_size=2
         0: aload_0
         1: aload_1
         2: putfield      #181                // Field _value9:Ljava/lang/Object;
         5: aload_0
         6: areturn
      LineNumberTable:
        line 69: 0
      LocalVariableTable:
        Start  Length  Slot  Name   Signature
            0       7     0  this   Lorg/sireum/MBox21;
            0       7     1 value9   Ljava/lang/Object;
    Signature: #184                         // (TT9;)Lorg/sireum/MBox21<TT1;TT2;TT3;TT4;TT5;TT6;TT7;TT8;TT9;TT10;TT11;TT12;TT13;TT14;TT15;TT16;TT17;TT18;TT19;TT20;TT21;>;
    MethodParameters:
      Name                           Flags
      value9                         final

  public T10 value10();
    descriptor: ()Ljava/lang/Object;
    flags: (0x0001) ACC_PUBLIC
    Code:
      stack=1, locals=1, args_size=1
         0: aload_0
         1: getfield      #189                // Field _value10:Ljava/lang/Object;
         4: areturn
      LineNumberTable:
        line 69: 0
      LocalVariableTable:
        Start  Length  Slot  Name   Signature
            0       5     0  this   Lorg/sireum/MBox21;
    Signature: #187                         // ()TT10;

  public T10 getValue10();
    descriptor: ()Ljava/lang/Object;
    flags: (0x0001) ACC_PUBLIC
    Code:
      stack=1, locals=1, args_size=1
         0: aload_0
         1: getfield      #189                // Field _value10:Ljava/lang/Object;
         4: areturn
      LineNumberTable:
        line 69: 0
      LocalVariableTable:
        Start  Length  Slot  Name   Signature
            0       5     0  this   Lorg/sireum/MBox21;
    Signature: #187                         // ()TT10;

  public org.sireum.MBox21<T1, T2, T3, T4, T5, T6, T7, T8, T9, T10, T11, T12, T13, T14, T15, T16, T17, T18, T19, T20, T21> value10_$eq(T10);
    descriptor: (Ljava/lang/Object;)Lorg/sireum/MBox21;
    flags: (0x0001) ACC_PUBLIC
    Code:
      stack=2, locals=2, args_size=2
         0: aload_0
         1: aload_1
         2: putfield      #189                // Field _value10:Ljava/lang/Object;
         5: aload_0
         6: areturn
      LineNumberTable:
        line 69: 0
      LocalVariableTable:
        Start  Length  Slot  Name   Signature
            0       7     0  this   Lorg/sireum/MBox21;
            0       7     1 value10   Ljava/lang/Object;
    Signature: #192                         // (TT10;)Lorg/sireum/MBox21<TT1;TT2;TT3;TT4;TT5;TT6;TT7;TT8;TT9;TT10;TT11;TT12;TT13;TT14;TT15;TT16;TT17;TT18;TT19;TT20;TT21;>;
    MethodParameters:
      Name                           Flags
      value10                        final

  public org.sireum.MBox21<T1, T2, T3, T4, T5, T6, T7, T8, T9, T10, T11, T12, T13, T14, T15, T16, T17, T18, T19, T20, T21> setValue10(T10);
    descriptor: (Ljava/lang/Object;)Lorg/sireum/MBox21;
    flags: (0x0001) ACC_PUBLIC
    Code:
      stack=2, locals=2, args_size=2
         0: aload_0
         1: aload_1
         2: putfield      #189                // Field _value10:Ljava/lang/Object;
         5: aload_0
         6: areturn
      LineNumberTable:
        line 69: 0
      LocalVariableTable:
        Start  Length  Slot  Name   Signature
            0       7     0  this   Lorg/sireum/MBox21;
            0       7     1 value10   Ljava/lang/Object;
    Signature: #192                         // (TT10;)Lorg/sireum/MBox21<TT1;TT2;TT3;TT4;TT5;TT6;TT7;TT8;TT9;TT10;TT11;TT12;TT13;TT14;TT15;TT16;TT17;TT18;TT19;TT20;TT21;>;
    MethodParameters:
      Name                           Flags
      value10                        final

  public T11 value11();
    descriptor: ()Ljava/lang/Object;
    flags: (0x0001) ACC_PUBLIC
    Code:
      stack=1, locals=1, args_size=1
         0: aload_0
         1: getfield      #197                // Field _value11:Ljava/lang/Object;
         4: areturn
      LineNumberTable:
        line 69: 0
      LocalVariableTable:
        Start  Length  Slot  Name   Signature
            0       5     0  this   Lorg/sireum/MBox21;
    Signature: #195                         // ()TT11;

  public T11 getValue11();
    descriptor: ()Ljava/lang/Object;
    flags: (0x0001) ACC_PUBLIC
    Code:
      stack=1, locals=1, args_size=1
         0: aload_0
         1: getfield      #197                // Field _value11:Ljava/lang/Object;
         4: areturn
      LineNumberTable:
        line 69: 0
      LocalVariableTable:
        Start  Length  Slot  Name   Signature
            0       5     0  this   Lorg/sireum/MBox21;
    Signature: #195                         // ()TT11;

  public org.sireum.MBox21<T1, T2, T3, T4, T5, T6, T7, T8, T9, T10, T11, T12, T13, T14, T15, T16, T17, T18, T19, T20, T21> value11_$eq(T11);
    descriptor: (Ljava/lang/Object;)Lorg/sireum/MBox21;
    flags: (0x0001) ACC_PUBLIC
    Code:
      stack=2, locals=2, args_size=2
         0: aload_0
         1: aload_1
         2: putfield      #197                // Field _value11:Ljava/lang/Object;
         5: aload_0
         6: areturn
      LineNumberTable:
        line 69: 0
      LocalVariableTable:
        Start  Length  Slot  Name   Signature
            0       7     0  this   Lorg/sireum/MBox21;
            0       7     1 value11   Ljava/lang/Object;
    Signature: #200                         // (TT11;)Lorg/sireum/MBox21<TT1;TT2;TT3;TT4;TT5;TT6;TT7;TT8;TT9;TT10;TT11;TT12;TT13;TT14;TT15;TT16;TT17;TT18;TT19;TT20;TT21;>;
    MethodParameters:
      Name                           Flags
      value11                        final

  public org.sireum.MBox21<T1, T2, T3, T4, T5, T6, T7, T8, T9, T10, T11, T12, T13, T14, T15, T16, T17, T18, T19, T20, T21> setValue11(T11);
    descriptor: (Ljava/lang/Object;)Lorg/sireum/MBox21;
    flags: (0x0001) ACC_PUBLIC
    Code:
      stack=2, locals=2, args_size=2
         0: aload_0
         1: aload_1
         2: putfield      #197                // Field _value11:Ljava/lang/Object;
         5: aload_0
         6: areturn
      LineNumberTable:
        line 69: 0
      LocalVariableTable:
        Start  Length  Slot  Name   Signature
            0       7     0  this   Lorg/sireum/MBox21;
            0       7     1 value11   Ljava/lang/Object;
    Signature: #200                         // (TT11;)Lorg/sireum/MBox21<TT1;TT2;TT3;TT4;TT5;TT6;TT7;TT8;TT9;TT10;TT11;TT12;TT13;TT14;TT15;TT16;TT17;TT18;TT19;TT20;TT21;>;
    MethodParameters:
      Name                           Flags
      value11                        final

  public T12 value12();
    descriptor: ()Ljava/lang/Object;
    flags: (0x0001) ACC_PUBLIC
    Code:
      stack=1, locals=1, args_size=1
         0: aload_0
         1: getfield      #205                // Field _value12:Ljava/lang/Object;
         4: areturn
      LineNumberTable:
        line 69: 0
      LocalVariableTable:
        Start  Length  Slot  Name   Signature
            0       5     0  this   Lorg/sireum/MBox21;
    Signature: #203                         // ()TT12;

  public T12 getValue12();
    descriptor: ()Ljava/lang/Object;
    flags: (0x0001) ACC_PUBLIC
    Code:
      stack=1, locals=1, args_size=1
         0: aload_0
         1: getfield      #205                // Field _value12:Ljava/lang/Object;
         4: areturn
      LineNumberTable:
        line 69: 0
      LocalVariableTable:
        Start  Length  Slot  Name   Signature
            0       5     0  this   Lorg/sireum/MBox21;
    Signature: #203                         // ()TT12;

  public org.sireum.MBox21<T1, T2, T3, T4, T5, T6, T7, T8, T9, T10, T11, T12, T13, T14, T15, T16, T17, T18, T19, T20, T21> value12_$eq(T12);
    descriptor: (Ljava/lang/Object;)Lorg/sireum/MBox21;
    flags: (0x0001) ACC_PUBLIC
    Code:
      stack=2, locals=2, args_size=2
         0: aload_0
         1: aload_1
         2: putfield      #205                // Field _value12:Ljava/lang/Object;
         5: aload_0
         6: areturn
      LineNumberTable:
        line 69: 0
      LocalVariableTable:
        Start  Length  Slot  Name   Signature
            0       7     0  this   Lorg/sireum/MBox21;
            0       7     1 value12   Ljava/lang/Object;
    Signature: #208                         // (TT12;)Lorg/sireum/MBox21<TT1;TT2;TT3;TT4;TT5;TT6;TT7;TT8;TT9;TT10;TT11;TT12;TT13;TT14;TT15;TT16;TT17;TT18;TT19;TT20;TT21;>;
    MethodParameters:
      Name                           Flags
      value12                        final

  public org.sireum.MBox21<T1, T2, T3, T4, T5, T6, T7, T8, T9, T10, T11, T12, T13, T14, T15, T16, T17, T18, T19, T20, T21> setValue12(T12);
    descriptor: (Ljava/lang/Object;)Lorg/sireum/MBox21;
    flags: (0x0001) ACC_PUBLIC
    Code:
      stack=2, locals=2, args_size=2
         0: aload_0
         1: aload_1
         2: putfield      #205                // Field _value12:Ljava/lang/Object;
         5: aload_0
         6: areturn
      LineNumberTable:
        line 69: 0
      LocalVariableTable:
        Start  Length  Slot  Name   Signature
            0       7     0  this   Lorg/sireum/MBox21;
            0       7     1 value12   Ljava/lang/Object;
    Signature: #208                         // (TT12;)Lorg/sireum/MBox21<TT1;TT2;TT3;TT4;TT5;TT6;TT7;TT8;TT9;TT10;TT11;TT12;TT13;TT14;TT15;TT16;TT17;TT18;TT19;TT20;TT21;>;
    MethodParameters:
      Name                           Flags
      value12                        final

  public T13 value13();
    descriptor: ()Ljava/lang/Object;
    flags: (0x0001) ACC_PUBLIC
    Code:
      stack=1, locals=1, args_size=1
         0: aload_0
         1: getfield      #213                // Field _value13:Ljava/lang/Object;
         4: areturn
      LineNumberTable:
        line 69: 0
      LocalVariableTable:
        Start  Length  Slot  Name   Signature
            0       5     0  this   Lorg/sireum/MBox21;
    Signature: #211                         // ()TT13;

  public T13 getValue13();
    descriptor: ()Ljava/lang/Object;
    flags: (0x0001) ACC_PUBLIC
    Code:
      stack=1, locals=1, args_size=1
         0: aload_0
         1: getfield      #213                // Field _value13:Ljava/lang/Object;
         4: areturn
      LineNumberTable:
        line 69: 0
      LocalVariableTable:
        Start  Length  Slot  Name   Signature
            0       5     0  this   Lorg/sireum/MBox21;
    Signature: #211                         // ()TT13;

  public org.sireum.MBox21<T1, T2, T3, T4, T5, T6, T7, T8, T9, T10, T11, T12, T13, T14, T15, T16, T17, T18, T19, T20, T21> value13_$eq(T13);
    descriptor: (Ljava/lang/Object;)Lorg/sireum/MBox21;
    flags: (0x0001) ACC_PUBLIC
    Code:
      stack=2, locals=2, args_size=2
         0: aload_0
         1: aload_1
         2: putfield      #213                // Field _value13:Ljava/lang/Object;
         5: aload_0
         6: areturn
      LineNumberTable:
        line 69: 0
      LocalVariableTable:
        Start  Length  Slot  Name   Signature
            0       7     0  this   Lorg/sireum/MBox21;
            0       7     1 value13   Ljava/lang/Object;
    Signature: #216                         // (TT13;)Lorg/sireum/MBox21<TT1;TT2;TT3;TT4;TT5;TT6;TT7;TT8;TT9;TT10;TT11;TT12;TT13;TT14;TT15;TT16;TT17;TT18;TT19;TT20;TT21;>;
    MethodParameters:
      Name                           Flags
      value13                        final

  public org.sireum.MBox21<T1, T2, T3, T4, T5, T6, T7, T8, T9, T10, T11, T12, T13, T14, T15, T16, T17, T18, T19, T20, T21> setValue13(T13);
    descriptor: (Ljava/lang/Object;)Lorg/sireum/MBox21;
    flags: (0x0001) ACC_PUBLIC
    Code:
      stack=2, locals=2, args_size=2
         0: aload_0
         1: aload_1
         2: putfield      #213                // Field _value13:Ljava/lang/Object;
         5: aload_0
         6: areturn
      LineNumberTable:
        line 69: 0
      LocalVariableTable:
        Start  Length  Slot  Name   Signature
            0       7     0  this   Lorg/sireum/MBox21;
            0       7     1 value13   Ljava/lang/Object;
    Signature: #216                         // (TT13;)Lorg/sireum/MBox21<TT1;TT2;TT3;TT4;TT5;TT6;TT7;TT8;TT9;TT10;TT11;TT12;TT13;TT14;TT15;TT16;TT17;TT18;TT19;TT20;TT21;>;
    MethodParameters:
      Name                           Flags
      value13                        final

  public T14 value14();
    descriptor: ()Ljava/lang/Object;
    flags: (0x0001) ACC_PUBLIC
    Code:
      stack=1, locals=1, args_size=1
         0: aload_0
         1: getfield      #221                // Field _value14:Ljava/lang/Object;
         4: areturn
      LineNumberTable:
        line 69: 0
      LocalVariableTable:
        Start  Length  Slot  Name   Signature
            0       5     0  this   Lorg/sireum/MBox21;
    Signature: #219                         // ()TT14;

  public T14 getValue14();
    descriptor: ()Ljava/lang/Object;
    flags: (0x0001) ACC_PUBLIC
    Code:
      stack=1, locals=1, args_size=1
         0: aload_0
         1: getfield      #221                // Field _value14:Ljava/lang/Object;
         4: areturn
      LineNumberTable:
        line 69: 0
      LocalVariableTable:
        Start  Length  Slot  Name   Signature
            0       5     0  this   Lorg/sireum/MBox21;
    Signature: #219                         // ()TT14;

  public org.sireum.MBox21<T1, T2, T3, T4, T5, T6, T7, T8, T9, T10, T11, T12, T13, T14, T15, T16, T17, T18, T19, T20, T21> value14_$eq(T14);
    descriptor: (Ljava/lang/Object;)Lorg/sireum/MBox21;
    flags: (0x0001) ACC_PUBLIC
    Code:
      stack=2, locals=2, args_size=2
         0: aload_0
         1: aload_1
         2: putfield      #221                // Field _value14:Ljava/lang/Object;
         5: aload_0
         6: areturn
      LineNumberTable:
        line 69: 0
      LocalVariableTable:
        Start  Length  Slot  Name   Signature
            0       7     0  this   Lorg/sireum/MBox21;
            0       7     1 value14   Ljava/lang/Object;
    Signature: #224                         // (TT14;)Lorg/sireum/MBox21<TT1;TT2;TT3;TT4;TT5;TT6;TT7;TT8;TT9;TT10;TT11;TT12;TT13;TT14;TT15;TT16;TT17;TT18;TT19;TT20;TT21;>;
    MethodParameters:
      Name                           Flags
      value14                        final

  public org.sireum.MBox21<T1, T2, T3, T4, T5, T6, T7, T8, T9, T10, T11, T12, T13, T14, T15, T16, T17, T18, T19, T20, T21> setValue14(T14);
    descriptor: (Ljava/lang/Object;)Lorg/sireum/MBox21;
    flags: (0x0001) ACC_PUBLIC
    Code:
      stack=2, locals=2, args_size=2
         0: aload_0
         1: aload_1
         2: putfield      #221                // Field _value14:Ljava/lang/Object;
         5: aload_0
         6: areturn
      LineNumberTable:
        line 69: 0
      LocalVariableTable:
        Start  Length  Slot  Name   Signature
            0       7     0  this   Lorg/sireum/MBox21;
            0       7     1 value14   Ljava/lang/Object;
    Signature: #224                         // (TT14;)Lorg/sireum/MBox21<TT1;TT2;TT3;TT4;TT5;TT6;TT7;TT8;TT9;TT10;TT11;TT12;TT13;TT14;TT15;TT16;TT17;TT18;TT19;TT20;TT21;>;
    MethodParameters:
      Name                           Flags
      value14                        final

  public T15 value15();
    descriptor: ()Ljava/lang/Object;
    flags: (0x0001) ACC_PUBLIC
    Code:
      stack=1, locals=1, args_size=1
         0: aload_0
         1: getfield      #229                // Field _value15:Ljava/lang/Object;
         4: areturn
      LineNumberTable:
        line 69: 0
      LocalVariableTable:
        Start  Length  Slot  Name   Signature
            0       5     0  this   Lorg/sireum/MBox21;
    Signature: #227                         // ()TT15;

  public T15 getValue15();
    descriptor: ()Ljava/lang/Object;
    flags: (0x0001) ACC_PUBLIC
    Code:
      stack=1, locals=1, args_size=1
         0: aload_0
         1: getfield      #229                // Field _value15:Ljava/lang/Object;
         4: areturn
      LineNumberTable:
        line 69: 0
      LocalVariableTable:
        Start  Length  Slot  Name   Signature
            0       5     0  this   Lorg/sireum/MBox21;
    Signature: #227                         // ()TT15;

  public org.sireum.MBox21<T1, T2, T3, T4, T5, T6, T7, T8, T9, T10, T11, T12, T13, T14, T15, T16, T17, T18, T19, T20, T21> value15_$eq(T15);
    descriptor: (Ljava/lang/Object;)Lorg/sireum/MBox21;
    flags: (0x0001) ACC_PUBLIC
    Code:
      stack=2, locals=2, args_size=2
         0: aload_0
         1: aload_1
         2: putfield      #229                // Field _value15:Ljava/lang/Object;
         5: aload_0
         6: areturn
      LineNumberTable:
        line 69: 0
      LocalVariableTable:
        Start  Length  Slot  Name   Signature
            0       7     0  this   Lorg/sireum/MBox21;
            0       7     1 value15   Ljava/lang/Object;
    Signature: #232                         // (TT15;)Lorg/sireum/MBox21<TT1;TT2;TT3;TT4;TT5;TT6;TT7;TT8;TT9;TT10;TT11;TT12;TT13;TT14;TT15;TT16;TT17;TT18;TT19;TT20;TT21;>;
    MethodParameters:
      Name                           Flags
      value15                        final

  public org.sireum.MBox21<T1, T2, T3, T4, T5, T6, T7, T8, T9, T10, T11, T12, T13, T14, T15, T16, T17, T18, T19, T20, T21> setValue15(T15);
    descriptor: (Ljava/lang/Object;)Lorg/sireum/MBox21;
    flags: (0x0001) ACC_PUBLIC
    Code:
      stack=2, locals=2, args_size=2
         0: aload_0
         1: aload_1
         2: putfield      #229                // Field _value15:Ljava/lang/Object;
         5: aload_0
         6: areturn
      LineNumberTable:
        line 69: 0
      LocalVariableTable:
        Start  Length  Slot  Name   Signature
            0       7     0  this   Lorg/sireum/MBox21;
            0       7     1 value15   Ljava/lang/Object;
    Signature: #232                         // (TT15;)Lorg/sireum/MBox21<TT1;TT2;TT3;TT4;TT5;TT6;TT7;TT8;TT9;TT10;TT11;TT12;TT13;TT14;TT15;TT16;TT17;TT18;TT19;TT20;TT21;>;
    MethodParameters:
      Name                           Flags
      value15                        final

  public T16 value16();
    descriptor: ()Ljava/lang/Object;
    flags: (0x0001) ACC_PUBLIC
    Code:
      stack=1, locals=1, args_size=1
         0: aload_0
         1: getfield      #237                // Field _value16:Ljava/lang/Object;
         4: areturn
      LineNumberTable:
        line 69: 0
      LocalVariableTable:
        Start  Length  Slot  Name   Signature
            0       5     0  this   Lorg/sireum/MBox21;
    Signature: #235                         // ()TT16;

  public T16 getValue16();
    descriptor: ()Ljava/lang/Object;
    flags: (0x0001) ACC_PUBLIC
    Code:
      stack=1, locals=1, args_size=1
         0: aload_0
         1: getfield      #237                // Field _value16:Ljava/lang/Object;
         4: areturn
      LineNumberTable:
        line 69: 0
      LocalVariableTable:
        Start  Length  Slot  Name   Signature
            0       5     0  this   Lorg/sireum/MBox21;
    Signature: #235                         // ()TT16;

  public org.sireum.MBox21<T1, T2, T3, T4, T5, T6, T7, T8, T9, T10, T11, T12, T13, T14, T15, T16, T17, T18, T19, T20, T21> value16_$eq(T16);
    descriptor: (Ljava/lang/Object;)Lorg/sireum/MBox21;
    flags: (0x0001) ACC_PUBLIC
    Code:
      stack=2, locals=2, args_size=2
         0: aload_0
         1: aload_1
         2: putfield      #237                // Field _value16:Ljava/lang/Object;
         5: aload_0
         6: areturn
      LineNumberTable:
        line 69: 0
      LocalVariableTable:
        Start  Length  Slot  Name   Signature
            0       7     0  this   Lorg/sireum/MBox21;
            0       7     1 value16   Ljava/lang/Object;
    Signature: #240                         // (TT16;)Lorg/sireum/MBox21<TT1;TT2;TT3;TT4;TT5;TT6;TT7;TT8;TT9;TT10;TT11;TT12;TT13;TT14;TT15;TT16;TT17;TT18;TT19;TT20;TT21;>;
    MethodParameters:
      Name                           Flags
      value16                        final

  public org.sireum.MBox21<T1, T2, T3, T4, T5, T6, T7, T8, T9, T10, T11, T12, T13, T14, T15, T16, T17, T18, T19, T20, T21> setValue16(T16);
    descriptor: (Ljava/lang/Object;)Lorg/sireum/MBox21;
    flags: (0x0001) ACC_PUBLIC
    Code:
      stack=2, locals=2, args_size=2
         0: aload_0
         1: aload_1
         2: putfield      #237                // Field _value16:Ljava/lang/Object;
         5: aload_0
         6: areturn
      LineNumberTable:
        line 69: 0
      LocalVariableTable:
        Start  Length  Slot  Name   Signature
            0       7     0  this   Lorg/sireum/MBox21;
            0       7     1 value16   Ljava/lang/Object;
    Signature: #240                         // (TT16;)Lorg/sireum/MBox21<TT1;TT2;TT3;TT4;TT5;TT6;TT7;TT8;TT9;TT10;TT11;TT12;TT13;TT14;TT15;TT16;TT17;TT18;TT19;TT20;TT21;>;
    MethodParameters:
      Name                           Flags
      value16                        final

  public T17 value17();
    descriptor: ()Ljava/lang/Object;
    flags: (0x0001) ACC_PUBLIC
    Code:
      stack=1, locals=1, args_size=1
         0: aload_0
         1: getfield      #245                // Field _value17:Ljava/lang/Object;
         4: areturn
      LineNumberTable:
        line 69: 0
      LocalVariableTable:
        Start  Length  Slot  Name   Signature
            0       5     0  this   Lorg/sireum/MBox21;
    Signature: #243                         // ()TT17;

  public T17 getValue17();
    descriptor: ()Ljava/lang/Object;
    flags: (0x0001) ACC_PUBLIC
    Code:
      stack=1, locals=1, args_size=1
         0: aload_0
         1: getfield      #245                // Field _value17:Ljava/lang/Object;
         4: areturn
      LineNumberTable:
        line 69: 0
      LocalVariableTable:
        Start  Length  Slot  Name   Signature
            0       5     0  this   Lorg/sireum/MBox21;
    Signature: #243                         // ()TT17;

  public org.sireum.MBox21<T1, T2, T3, T4, T5, T6, T7, T8, T9, T10, T11, T12, T13, T14, T15, T16, T17, T18, T19, T20, T21> value17_$eq(T17);
    descriptor: (Ljava/lang/Object;)Lorg/sireum/MBox21;
    flags: (0x0001) ACC_PUBLIC
    Code:
      stack=2, locals=2, args_size=2
         0: aload_0
         1: aload_1
         2: putfield      #245                // Field _value17:Ljava/lang/Object;
         5: aload_0
         6: areturn
      LineNumberTable:
        line 69: 0
      LocalVariableTable:
        Start  Length  Slot  Name   Signature
            0       7     0  this   Lorg/sireum/MBox21;
            0       7     1 value17   Ljava/lang/Object;
    Signature: #248                         // (TT17;)Lorg/sireum/MBox21<TT1;TT2;TT3;TT4;TT5;TT6;TT7;TT8;TT9;TT10;TT11;TT12;TT13;TT14;TT15;TT16;TT17;TT18;TT19;TT20;TT21;>;
    MethodParameters:
      Name                           Flags
      value17                        final

  public org.sireum.MBox21<T1, T2, T3, T4, T5, T6, T7, T8, T9, T10, T11, T12, T13, T14, T15, T16, T17, T18, T19, T20, T21> setValue17(T17);
    descriptor: (Ljava/lang/Object;)Lorg/sireum/MBox21;
    flags: (0x0001) ACC_PUBLIC
    Code:
      stack=2, locals=2, args_size=2
         0: aload_0
         1: aload_1
         2: putfield      #245                // Field _value17:Ljava/lang/Object;
         5: aload_0
         6: areturn
      LineNumberTable:
        line 69: 0
      LocalVariableTable:
        Start  Length  Slot  Name   Signature
            0       7     0  this   Lorg/sireum/MBox21;
            0       7     1 value17   Ljava/lang/Object;
    Signature: #248                         // (TT17;)Lorg/sireum/MBox21<TT1;TT2;TT3;TT4;TT5;TT6;TT7;TT8;TT9;TT10;TT11;TT12;TT13;TT14;TT15;TT16;TT17;TT18;TT19;TT20;TT21;>;
    MethodParameters:
      Name                           Flags
      value17                        final

  public T18 value18();
    descriptor: ()Ljava/lang/Object;
    flags: (0x0001) ACC_PUBLIC
    Code:
      stack=1, locals=1, args_size=1
         0: aload_0
         1: getfield      #253                // Field _value18:Ljava/lang/Object;
         4: areturn
      LineNumberTable:
        line 69: 0
      LocalVariableTable:
        Start  Length  Slot  Name   Signature
            0       5     0  this   Lorg/sireum/MBox21;
    Signature: #251                         // ()TT18;

  public T18 getValue18();
    descriptor: ()Ljava/lang/Object;
    flags: (0x0001) ACC_PUBLIC
    Code:
      stack=1, locals=1, args_size=1
         0: aload_0
         1: getfield      #253                // Field _value18:Ljava/lang/Object;
         4: areturn
      LineNumberTable:
        line 69: 0
      LocalVariableTable:
        Start  Length  Slot  Name   Signature
            0       5     0  this   Lorg/sireum/MBox21;
    Signature: #251                         // ()TT18;

  public org.sireum.MBox21<T1, T2, T3, T4, T5, T6, T7, T8, T9, T10, T11, T12, T13, T14, T15, T16, T17, T18, T19, T20, T21> value18_$eq(T18);
    descriptor: (Ljava/lang/Object;)Lorg/sireum/MBox21;
    flags: (0x0001) ACC_PUBLIC
    Code:
      stack=2, locals=2, args_size=2
         0: aload_0
         1: aload_1
         2: putfield      #253                // Field _value18:Ljava/lang/Object;
         5: aload_0
         6: areturn
      LineNumberTable:
        line 69: 0
      LocalVariableTable:
        Start  Length  Slot  Name   Signature
            0       7     0  this   Lorg/sireum/MBox21;
            0       7     1 value18   Ljava/lang/Object;
    Signature: #256                         // (TT18;)Lorg/sireum/MBox21<TT1;TT2;TT3;TT4;TT5;TT6;TT7;TT8;TT9;TT10;TT11;TT12;TT13;TT14;TT15;TT16;TT17;TT18;TT19;TT20;TT21;>;
    MethodParameters:
      Name                           Flags
      value18                        final

  public org.sireum.MBox21<T1, T2, T3, T4, T5, T6, T7, T8, T9, T10, T11, T12, T13, T14, T15, T16, T17, T18, T19, T20, T21> setValue18(T18);
    descriptor: (Ljava/lang/Object;)Lorg/sireum/MBox21;
    flags: (0x0001) ACC_PUBLIC
    Code:
      stack=2, locals=2, args_size=2
         0: aload_0
         1: aload_1
         2: putfield      #253                // Field _value18:Ljava/lang/Object;
         5: aload_0
         6: areturn
      LineNumberTable:
        line 69: 0
      LocalVariableTable:
        Start  Length  Slot  Name   Signature
            0       7     0  this   Lorg/sireum/MBox21;
            0       7     1 value18   Ljava/lang/Object;
    Signature: #256                         // (TT18;)Lorg/sireum/MBox21<TT1;TT2;TT3;TT4;TT5;TT6;TT7;TT8;TT9;TT10;TT11;TT12;TT13;TT14;TT15;TT16;TT17;TT18;TT19;TT20;TT21;>;
    MethodParameters:
      Name                           Flags
      value18                        final

  public T19 value19();
    descriptor: ()Ljava/lang/Object;
    flags: (0x0001) ACC_PUBLIC
    Code:
      stack=1, locals=1, args_size=1
         0: aload_0
         1: getfield      #261                // Field _value19:Ljava/lang/Object;
         4: areturn
      LineNumberTable:
        line 69: 0
      LocalVariableTable:
        Start  Length  Slot  Name   Signature
            0       5     0  this   Lorg/sireum/MBox21;
    Signature: #259                         // ()TT19;

  public T19 getValue19();
    descriptor: ()Ljava/lang/Object;
    flags: (0x0001) ACC_PUBLIC
    Code:
      stack=1, locals=1, args_size=1
         0: aload_0
         1: getfield      #261                // Field _value19:Ljava/lang/Object;
         4: areturn
      LineNumberTable:
        line 69: 0
      LocalVariableTable:
        Start  Length  Slot  Name   Signature
            0       5     0  this   Lorg/sireum/MBox21;
    Signature: #259                         // ()TT19;

  public org.sireum.MBox21<T1, T2, T3, T4, T5, T6, T7, T8, T9, T10, T11, T12, T13, T14, T15, T16, T17, T18, T19, T20, T21> value19_$eq(T19);
    descriptor: (Ljava/lang/Object;)Lorg/sireum/MBox21;
    flags: (0x0001) ACC_PUBLIC
    Code:
      stack=2, locals=2, args_size=2
         0: aload_0
         1: aload_1
         2: putfield      #261                // Field _value19:Ljava/lang/Object;
         5: aload_0
         6: areturn
      LineNumberTable:
        line 69: 0
      LocalVariableTable:
        Start  Length  Slot  Name   Signature
            0       7     0  this   Lorg/sireum/MBox21;
            0       7     1 value19   Ljava/lang/Object;
    Signature: #264                         // (TT19;)Lorg/sireum/MBox21<TT1;TT2;TT3;TT4;TT5;TT6;TT7;TT8;TT9;TT10;TT11;TT12;TT13;TT14;TT15;TT16;TT17;TT18;TT19;TT20;TT21;>;
    MethodParameters:
      Name                           Flags
      value19                        final

  public org.sireum.MBox21<T1, T2, T3, T4, T5, T6, T7, T8, T9, T10, T11, T12, T13, T14, T15, T16, T17, T18, T19, T20, T21> setValue19(T19);
    descriptor: (Ljava/lang/Object;)Lorg/sireum/MBox21;
    flags: (0x0001) ACC_PUBLIC
    Code:
      stack=2, locals=2, args_size=2
         0: aload_0
         1: aload_1
         2: putfield      #261                // Field _value19:Ljava/lang/Object;
         5: aload_0
         6: areturn
      LineNumberTable:
        line 69: 0
      LocalVariableTable:
        Start  Length  Slot  Name   Signature
            0       7     0  this   Lorg/sireum/MBox21;
            0       7     1 value19   Ljava/lang/Object;
    Signature: #264                         // (TT19;)Lorg/sireum/MBox21<TT1;TT2;TT3;TT4;TT5;TT6;TT7;TT8;TT9;TT10;TT11;TT12;TT13;TT14;TT15;TT16;TT17;TT18;TT19;TT20;TT21;>;
    MethodParameters:
      Name                           Flags
      value19                        final

  public T20 value20();
    descriptor: ()Ljava/lang/Object;
    flags: (0x0001) ACC_PUBLIC
    Code:
      stack=1, locals=1, args_size=1
         0: aload_0
         1: getfield      #269                // Field _value20:Ljava/lang/Object;
         4: areturn
      LineNumberTable:
        line 69: 0
      LocalVariableTable:
        Start  Length  Slot  Name   Signature
            0       5     0  this   Lorg/sireum/MBox21;
    Signature: #267                         // ()TT20;

  public T20 getValue20();
    descriptor: ()Ljava/lang/Object;
    flags: (0x0001) ACC_PUBLIC
    Code:
      stack=1, locals=1, args_size=1
         0: aload_0
         1: getfield      #269                // Field _value20:Ljava/lang/Object;
         4: areturn
      LineNumberTable:
        line 69: 0
      LocalVariableTable:
        Start  Length  Slot  Name   Signature
            0       5     0  this   Lorg/sireum/MBox21;
    Signature: #267                         // ()TT20;

  public org.sireum.MBox21<T1, T2, T3, T4, T5, T6, T7, T8, T9, T10, T11, T12, T13, T14, T15, T16, T17, T18, T19, T20, T21> value20_$eq(T20);
    descriptor: (Ljava/lang/Object;)Lorg/sireum/MBox21;
    flags: (0x0001) ACC_PUBLIC
    Code:
      stack=2, locals=2, args_size=2
         0: aload_0
         1: aload_1
         2: putfield      #269                // Field _value20:Ljava/lang/Object;
         5: aload_0
         6: areturn
      LineNumberTable:
        line 69: 0
      LocalVariableTable:
        Start  Length  Slot  Name   Signature
            0       7     0  this   Lorg/sireum/MBox21;
            0       7     1 value20   Ljava/lang/Object;
    Signature: #272                         // (TT20;)Lorg/sireum/MBox21<TT1;TT2;TT3;TT4;TT5;TT6;TT7;TT8;TT9;TT10;TT11;TT12;TT13;TT14;TT15;TT16;TT17;TT18;TT19;TT20;TT21;>;
    MethodParameters:
      Name                           Flags
      value20                        final

  public org.sireum.MBox21<T1, T2, T3, T4, T5, T6, T7, T8, T9, T10, T11, T12, T13, T14, T15, T16, T17, T18, T19, T20, T21> setValue20(T20);
    descriptor: (Ljava/lang/Object;)Lorg/sireum/MBox21;
    flags: (0x0001) ACC_PUBLIC
    Code:
      stack=2, locals=2, args_size=2
         0: aload_0
         1: aload_1
         2: putfield      #269                // Field _value20:Ljava/lang/Object;
         5: aload_0
         6: areturn
      LineNumberTable:
        line 69: 0
      LocalVariableTable:
        Start  Length  Slot  Name   Signature
            0       7     0  this   Lorg/sireum/MBox21;
            0       7     1 value20   Ljava/lang/Object;
    Signature: #272                         // (TT20;)Lorg/sireum/MBox21<TT1;TT2;TT3;TT4;TT5;TT6;TT7;TT8;TT9;TT10;TT11;TT12;TT13;TT14;TT15;TT16;TT17;TT18;TT19;TT20;TT21;>;
    MethodParameters:
      Name                           Flags
      value20                        final

  public T21 value21();
    descriptor: ()Ljava/lang/Object;
    flags: (0x0001) ACC_PUBLIC
    Code:
      stack=1, locals=1, args_size=1
         0: aload_0
         1: getfield      #277                // Field _value21:Ljava/lang/Object;
         4: areturn
      LineNumberTable:
        line 69: 0
      LocalVariableTable:
        Start  Length  Slot  Name   Signature
            0       5     0  this   Lorg/sireum/MBox21;
    Signature: #275                         // ()TT21;

  public T21 getValue21();
    descriptor: ()Ljava/lang/Object;
    flags: (0x0001) ACC_PUBLIC
    Code:
      stack=1, locals=1, args_size=1
         0: aload_0
         1: getfield      #277                // Field _value21:Ljava/lang/Object;
         4: areturn
      LineNumberTable:
        line 69: 0
      LocalVariableTable:
        Start  Length  Slot  Name   Signature
            0       5     0  this   Lorg/sireum/MBox21;
    Signature: #275                         // ()TT21;

  public org.sireum.MBox21<T1, T2, T3, T4, T5, T6, T7, T8, T9, T10, T11, T12, T13, T14, T15, T16, T17, T18, T19, T20, T21> value21_$eq(T21);
    descriptor: (Ljava/lang/Object;)Lorg/sireum/MBox21;
    flags: (0x0001) ACC_PUBLIC
    Code:
      stack=2, locals=2, args_size=2
         0: aload_0
         1: aload_1
         2: putfield      #277                // Field _value21:Ljava/lang/Object;
         5: aload_0
         6: areturn
      LineNumberTable:
        line 69: 0
      LocalVariableTable:
        Start  Length  Slot  Name   Signature
            0       7     0  this   Lorg/sireum/MBox21;
            0       7     1 value21   Ljava/lang/Object;
    Signature: #280                         // (TT21;)Lorg/sireum/MBox21<TT1;TT2;TT3;TT4;TT5;TT6;TT7;TT8;TT9;TT10;TT11;TT12;TT13;TT14;TT15;TT16;TT17;TT18;TT19;TT20;TT21;>;
    MethodParameters:
      Name                           Flags
      value21                        final

  public org.sireum.MBox21<T1, T2, T3, T4, T5, T6, T7, T8, T9, T10, T11, T12, T13, T14, T15, T16, T17, T18, T19, T20, T21> setValue21(T21);
    descriptor: (Ljava/lang/Object;)Lorg/sireum/MBox21;
    flags: (0x0001) ACC_PUBLIC
    Code:
      stack=2, locals=2, args_size=2
         0: aload_0
         1: aload_1
         2: putfield      #277                // Field _value21:Ljava/lang/Object;
         5: aload_0
         6: areturn
      LineNumberTable:
        line 69: 0
      LocalVariableTable:
        Start  Length  Slot  Name   Signature
            0       7     0  this   Lorg/sireum/MBox21;
            0       7     1 value21   Ljava/lang/Object;
    Signature: #280                         // (TT21;)Lorg/sireum/MBox21<TT1;TT2;TT3;TT4;TT5;TT6;TT7;TT8;TT9;TT10;TT11;TT12;TT13;TT14;TT15;TT16;TT17;TT18;TT19;TT20;TT21;>;
    MethodParameters:
      Name                           Flags
      value21                        final

  public java.lang.String toString();
    descriptor: ()Ljava/lang/String;
    flags: (0x0001) ACC_PUBLIC
    Code:
      stack=3, locals=2, args_size=1
         0: aload_0
         1: invokevirtual #285                // Method $hasString:()Z
         4: ifeq          14
         7: aload_0
         8: invokestatic  #289                // InterfaceMethod org/sireum/RecordSig.string$:(Lorg/sireum/RecordSig;)Ljava/lang/String;
        11: goto          523
        14: new           #291                // class java/lang/StringBuilder
        17: dup
        18: invokespecial #295                // Method java/lang/StringBuilder."<init>":()V
        21: astore_1
        22: aload_1
        23: ldc_w         #297                // String MBox21
        26: invokevirtual #301                // Method java/lang/StringBuilder.append:(Ljava/lang/String;)Ljava/lang/StringBuilder;
        29: pop
        30: aload_1
        31: bipush        40
        33: invokevirtual #304                // Method java/lang/StringBuilder.append:(C)Ljava/lang/StringBuilder;
        36: pop
        37: aload_1
        38: getstatic     #309                // Field org/sireum/String$.MODULE$:Lorg/sireum/String$;
        41: aload_0
        42: invokevirtual #311                // Method value1:()Ljava/lang/Object;
        45: invokevirtual #315                // Method org/sireum/String$.escape:(Ljava/lang/Object;)Ljava/lang/String;
        48: invokevirtual #301                // Method java/lang/StringBuilder.append:(Ljava/lang/String;)Ljava/lang/StringBuilder;
        51: pop
        52: aload_1
        53: ldc_w         #317                // String ,
        56: invokevirtual #301                // Method java/lang/StringBuilder.append:(Ljava/lang/String;)Ljava/lang/StringBuilder;
        59: pop
        60: aload_1
        61: getstatic     #309                // Field org/sireum/String$.MODULE$:Lorg/sireum/String$;
        64: aload_0
        65: invokevirtual #319                // Method value2:()Ljava/lang/Object;
        68: invokevirtual #315                // Method org/sireum/String$.escape:(Ljava/lang/Object;)Ljava/lang/String;
        71: invokevirtual #301                // Method java/lang/StringBuilder.append:(Ljava/lang/String;)Ljava/lang/StringBuilder;
        74: pop
        75: aload_1
        76: ldc_w         #317                // String ,
        79: invokevirtual #301                // Method java/lang/StringBuilder.append:(Ljava/lang/String;)Ljava/lang/StringBuilder;
        82: pop
        83: aload_1
        84: getstatic     #309                // Field org/sireum/String$.MODULE$:Lorg/sireum/String$;
        87: aload_0
        88: invokevirtual #321                // Method value3:()Ljava/lang/Object;
        91: invokevirtual #315                // Method org/sireum/String$.escape:(Ljava/lang/Object;)Ljava/lang/String;
        94: invokevirtual #301                // Method java/lang/StringBuilder.append:(Ljava/lang/String;)Ljava/lang/StringBuilder;
        97: pop
        98: aload_1
        99: ldc_w         #317                // String ,
       102: invokevirtual #301                // Method java/lang/StringBuilder.append:(Ljava/lang/String;)Ljava/lang/StringBuilder;
       105: pop
       106: aload_1
       107: getstatic     #309                // Field org/sireum/String$.MODULE$:Lorg/sireum/String$;
       110: aload_0
       111: invokevirtual #323                // Method value4:()Ljava/lang/Object;
       114: invokevirtual #315                // Method org/sireum/String$.escape:(Ljava/lang/Object;)Ljava/lang/String;
       117: invokevirtual #301                // Method java/lang/StringBuilder.append:(Ljava/lang/String;)Ljava/lang/StringBuilder;
       120: pop
       121: aload_1
       122: ldc_w         #317                // String ,
       125: invokevirtual #301                // Method java/lang/StringBuilder.append:(Ljava/lang/String;)Ljava/lang/StringBuilder;
       128: pop
       129: aload_1
       130: getstatic     #309                // Field org/sireum/String$.MODULE$:Lorg/sireum/String$;
       133: aload_0
       134: invokevirtual #325                // Method value5:()Ljava/lang/Object;
       137: invokevirtual #315                // Method org/sireum/String$.escape:(Ljava/lang/Object;)Ljava/lang/String;
       140: invokevirtual #301                // Method java/lang/StringBuilder.append:(Ljava/lang/String;)Ljava/lang/StringBuilder;
       143: pop
       144: aload_1
       145: ldc_w         #317                // String ,
       148: invokevirtual #301                // Method java/lang/StringBuilder.append:(Ljava/lang/String;)Ljava/lang/StringBuilder;
       151: pop
       152: aload_1
       153: getstatic     #309                // Field org/sireum/String$.MODULE$:Lorg/sireum/String$;
       156: aload_0
       157: invokevirtual #327                // Method value6:()Ljava/lang/Object;
       160: invokevirtual #315                // Method org/sireum/String$.escape:(Ljava/lang/Object;)Ljava/lang/String;
       163: invokevirtual #301                // Method java/lang/StringBuilder.append:(Ljava/lang/String;)Ljava/lang/StringBuilder;
       166: pop
       167: aload_1
       168: ldc_w         #317                // String ,
       171: invokevirtual #301                // Method java/lang/StringBuilder.append:(Ljava/lang/String;)Ljava/lang/StringBuilder;
       174: pop
       175: aload_1
       176: getstatic     #309                // Field org/sireum/String$.MODULE$:Lorg/sireum/String$;
       179: aload_0
       180: invokevirtual #329                // Method value7:()Ljava/lang/Object;
       183: invokevirtual #315                // Method org/sireum/String$.escape:(Ljava/lang/Object;)Ljava/lang/String;
       186: invokevirtual #301                // Method java/lang/StringBuilder.append:(Ljava/lang/String;)Ljava/lang/StringBuilder;
       189: pop
       190: aload_1
       191: ldc_w         #317                // String ,
       194: invokevirtual #301                // Method java/lang/StringBuilder.append:(Ljava/lang/String;)Ljava/lang/StringBuilder;
       197: pop
       198: aload_1
       199: getstatic     #309                // Field org/sireum/String$.MODULE$:Lorg/sireum/String$;
       202: aload_0
       203: invokevirtual #331                // Method value8:()Ljava/lang/Object;
       206: invokevirtual #315                // Method org/sireum/String$.escape:(Ljava/lang/Object;)Ljava/lang/String;
       209: invokevirtual #301                // Method java/lang/StringBuilder.append:(Ljava/lang/String;)Ljava/lang/StringBuilder;
       212: pop
       213: aload_1
       214: ldc_w         #317                // String ,
       217: invokevirtual #301                // Method java/lang/StringBuilder.append:(Ljava/lang/String;)Ljava/lang/StringBuilder;
       220: pop
       221: aload_1
       222: getstatic     #309                // Field org/sireum/String$.MODULE$:Lorg/sireum/String$;
       225: aload_0
       226: invokevirtual #333                // Method value9:()Ljava/lang/Object;
       229: invokevirtual #315                // Method org/sireum/String$.escape:(Ljava/lang/Object;)Ljava/lang/String;
       232: invokevirtual #301                // Method java/lang/StringBuilder.append:(Ljava/lang/String;)Ljava/lang/StringBuilder;
       235: pop
       236: aload_1
       237: ldc_w         #317                // String ,
       240: invokevirtual #301                // Method java/lang/StringBuilder.append:(Ljava/lang/String;)Ljava/lang/StringBuilder;
       243: pop
       244: aload_1
       245: getstatic     #309                // Field org/sireum/String$.MODULE$:Lorg/sireum/String$;
       248: aload_0
       249: invokevirtual #335                // Method value10:()Ljava/lang/Object;
       252: invokevirtual #315                // Method org/sireum/String$.escape:(Ljava/lang/Object;)Ljava/lang/String;
       255: invokevirtual #301                // Method java/lang/StringBuilder.append:(Ljava/lang/String;)Ljava/lang/StringBuilder;
       258: pop
       259: aload_1
       260: ldc_w         #317                // String ,
       263: invokevirtual #301                // Method java/lang/StringBuilder.append:(Ljava/lang/String;)Ljava/lang/StringBuilder;
       266: pop
       267: aload_1
       268: getstatic     #309                // Field org/sireum/String$.MODULE$:Lorg/sireum/String$;
       271: aload_0
       272: invokevirtual #337                // Method value11:()Ljava/lang/Object;
       275: invokevirtual #315                // Method org/sireum/String$.escape:(Ljava/lang/Object;)Ljava/lang/String;
       278: invokevirtual #301                // Method java/lang/StringBuilder.append:(Ljava/lang/String;)Ljava/lang/StringBuilder;
       281: pop
       282: aload_1
       283: ldc_w         #317                // String ,
       286: invokevirtual #301                // Method java/lang/StringBuilder.append:(Ljava/lang/String;)Ljava/lang/StringBuilder;
       289: pop
       290: aload_1
       291: getstatic     #309                // Field org/sireum/String$.MODULE$:Lorg/sireum/String$;
       294: aload_0
       295: invokevirtual #339                // Method value12:()Ljava/lang/Object;
       298: invokevirtual #315                // Method org/sireum/String$.escape:(Ljava/lang/Object;)Ljava/lang/String;
       301: invokevirtual #301                // Method java/lang/StringBuilder.append:(Ljava/lang/String;)Ljava/lang/StringBuilder;
       304: pop
       305: aload_1
       306: ldc_w         #317                // String ,
       309: invokevirtual #301                // Method java/lang/StringBuilder.append:(Ljava/lang/String;)Ljava/lang/StringBuilder;
       312: pop
       313: aload_1
       314: getstatic     #309                // Field org/sireum/String$.MODULE$:Lorg/sireum/String$;
       317: aload_0
       318: invokevirtual #341                // Method value13:()Ljava/lang/Object;
       321: invokevirtual #315                // Method org/sireum/String$.escape:(Ljava/lang/Object;)Ljava/lang/String;
       324: invokevirtual #301                // Method java/lang/StringBuilder.append:(Ljava/lang/String;)Ljava/lang/StringBuilder;
       327: pop
       328: aload_1
       329: ldc_w         #317                // String ,
       332: invokevirtual #301                // Method java/lang/StringBuilder.append:(Ljava/lang/String;)Ljava/lang/StringBuilder;
       335: pop
       336: aload_1
       337: getstatic     #309                // Field org/sireum/String$.MODULE$:Lorg/sireum/String$;
       340: aload_0
       341: invokevirtual #343                // Method value14:()Ljava/lang/Object;
       344: invokevirtual #315                // Method org/sireum/String$.escape:(Ljava/lang/Object;)Ljava/lang/String;
       347: invokevirtual #301                // Method java/lang/StringBuilder.append:(Ljava/lang/String;)Ljava/lang/StringBuilder;
       350: pop
       351: aload_1
       352: ldc_w         #317                // String ,
       355: invokevirtual #301                // Method java/lang/StringBuilder.append:(Ljava/lang/String;)Ljava/lang/StringBuilder;
       358: pop
       359: aload_1
       360: getstatic     #309                // Field org/sireum/String$.MODULE$:Lorg/sireum/String$;
       363: aload_0
       364: invokevirtual #345                // Method value15:()Ljava/lang/Object;
       367: invokevirtual #315                // Method org/sireum/String$.escape:(Ljava/lang/Object;)Ljava/lang/String;
       370: invokevirtual #301                // Method java/lang/StringBuilder.append:(Ljava/lang/String;)Ljava/lang/StringBuilder;
       373: pop
       374: aload_1
       375: ldc_w         #317                // String ,
       378: invokevirtual #301                // Method java/lang/StringBuilder.append:(Ljava/lang/String;)Ljava/lang/StringBuilder;
       381: pop
       382: aload_1
       383: getstatic     #309                // Field org/sireum/String$.MODULE$:Lorg/sireum/String$;
       386: aload_0
       387: invokevirtual #347                // Method value16:()Ljava/lang/Object;
       390: invokevirtual #315                // Method org/sireum/String$.escape:(Ljava/lang/Object;)Ljava/lang/String;
       393: invokevirtual #301                // Method java/lang/StringBuilder.append:(Ljava/lang/String;)Ljava/lang/StringBuilder;
       396: pop
       397: aload_1
       398: ldc_w         #317                // String ,
       401: invokevirtual #301                // Method java/lang/StringBuilder.append:(Ljava/lang/String;)Ljava/lang/StringBuilder;
       404: pop
       405: aload_1
       406: getstatic     #309                // Field org/sireum/String$.MODULE$:Lorg/sireum/String$;
       409: aload_0
       410: invokevirtual #349                // Method value17:()Ljava/lang/Object;
       413: invokevirtual #315                // Method org/sireum/String$.escape:(Ljava/lang/Object;)Ljava/lang/String;
       416: invokevirtual #301                // Method java/lang/StringBuilder.append:(Ljava/lang/String;)Ljava/lang/StringBuilder;
       419: pop
       420: aload_1
       421: ldc_w         #317                // String ,
       424: invokevirtual #301                // Method java/lang/StringBuilder.append:(Ljava/lang/String;)Ljava/lang/StringBuilder;
       427: pop
       428: aload_1
       429: getstatic     #309                // Field org/sireum/String$.MODULE$:Lorg/sireum/String$;
       432: aload_0
       433: invokevirtual #351                // Method value18:()Ljava/lang/Object;
       436: invokevirtual #315                // Method org/sireum/String$.escape:(Ljava/lang/Object;)Ljava/lang/String;
       439: invokevirtual #301                // Method java/lang/StringBuilder.append:(Ljava/lang/String;)Ljava/lang/StringBuilder;
       442: pop
       443: aload_1
       444: ldc_w         #317                // String ,
       447: invokevirtual #301                // Method java/lang/StringBuilder.append:(Ljava/lang/String;)Ljava/lang/StringBuilder;
       450: pop
       451: aload_1
       452: getstatic     #309                // Field org/sireum/String$.MODULE$:Lorg/sireum/String$;
       455: aload_0
       456: invokevirtual #353                // Method value19:()Ljava/lang/Object;
       459: invokevirtual #315                // Method org/sireum/String$.escape:(Ljava/lang/Object;)Ljava/lang/String;
       462: invokevirtual #301                // Method java/lang/StringBuilder.append:(Ljava/lang/String;)Ljava/lang/StringBuilder;
       465: pop
       466: aload_1
       467: ldc_w         #317                // String ,
       470: invokevirtual #301                // Method java/lang/StringBuilder.append:(Ljava/lang/String;)Ljava/lang/StringBuilder;
       473: pop
       474: aload_1
       475: getstatic     #309                // Field org/sireum/String$.MODULE$:Lorg/sireum/String$;
       478: aload_0
       479: invokevirtual #355                // Method value20:()Ljava/lang/Object;
       482: invokevirtual #315                // Method org/sireum/String$.escape:(Ljava/lang/Object;)Ljava/lang/String;
       485: invokevirtual #301                // Method java/lang/StringBuilder.append:(Ljava/lang/String;)Ljava/lang/StringBuilder;
       488: pop
       489: aload_1
       490: ldc_w         #317                // String ,
       493: invokevirtual #301                // Method java/lang/StringBuilder.append:(Ljava/lang/String;)Ljava/lang/StringBuilder;
       496: pop
       497: aload_1
       498: getstatic     #309                // Field org/sireum/String$.MODULE$:Lorg/sireum/String$;
       501: aload_0
       502: invokevirtual #357                // Method value21:()Ljava/lang/Object;
       505: invokevirtual #315                // Method org/sireum/String$.escape:(Ljava/lang/Object;)Ljava/lang/String;
       508: invokevirtual #301                // Method java/lang/StringBuilder.append:(Ljava/lang/String;)Ljava/lang/StringBuilder;
       511: pop
       512: aload_1
       513: bipush        41
       515: invokevirtual #304                // Method java/lang/StringBuilder.append:(C)Ljava/lang/StringBuilder;
       518: pop
       519: aload_1
       520: invokevirtual #359                // Method java/lang/StringBuilder.toString:()Ljava/lang/String;
       523: areturn
      StackMapTable: number_of_entries = 2
        frame_type = 14 /* same */
        frame_type = 247 /* same_locals_1_stack_item_frame_extended */
          offset_delta = 508
          stack = [ class java/lang/String ]
      LineNumberTable:
        line 69: 0
      LocalVariableTable:
        Start  Length  Slot  Name   Signature
           22     501     1    sb   Ljava/lang/StringBuilder;
            0     524     0  this   Lorg/sireum/MBox21;

  public java.lang.String string();
    descriptor: ()Ljava/lang/String;
    flags: (0x0001) ACC_PUBLIC
    Code:
      stack=2, locals=1, args_size=1
         0: aload_0
         1: invokevirtual #285                // Method $hasString:()Z
         4: ifeq          14
         7: aload_0
         8: invokestatic  #289                // InterfaceMethod org/sireum/RecordSig.string$:(Lorg/sireum/RecordSig;)Ljava/lang/String;
        11: goto          24
        14: getstatic     #309                // Field org/sireum/String$.MODULE$:Lorg/sireum/String$;
        17: aload_0
        18: invokevirtual #365                // Method toString:()Ljava/lang/String;
        21: invokevirtual #369                // Method org/sireum/String$.apply:(Ljava/lang/String;)Ljava/lang/String;
        24: areturn
      StackMapTable: number_of_entries = 2
        frame_type = 14 /* same */
        frame_type = 73 /* same_locals_1_stack_item */
          stack = [ class java/lang/String ]
      LineNumberTable:
        line 69: 0
      LocalVariableTable:
        Start  Length  Slot  Name   Signature
            0      25     0  this   Lorg/sireum/MBox21;

  public int hashCode();
    descriptor: ()I
    flags: (0x0001) ACC_PUBLIC
    Code:
      stack=6, locals=1, args_size=1
         0: aload_0
         1: invokevirtual #373                // Method $hasEquals:()Z
         4: ifeq          14
         7: aload_0
         8: invokespecial #375                // Method java/lang/Object.hashCode:()I
        11: goto          215
        14: getstatic     #380                // Field scala/package$.MODULE$:Lscala/package$;
        17: invokevirtual #384                // Method scala/package$.Seq:()Lscala/collection/immutable/Seq$;
        20: getstatic     #389                // Field scala/runtime/ScalaRunTime$.MODULE$:Lscala/runtime/ScalaRunTime$;
        23: bipush        22
        25: anewarray     #5                  // class java/lang/Object
        28: dup
        29: iconst_0
        30: aload_0
        31: invokevirtual #393                // Method getClass:()Ljava/lang/Class;
        34: invokevirtual #398                // Method java/lang/Class.getName:()Ljava/lang/String;
        37: aastore
        38: dup
        39: iconst_1
        40: aload_0
        41: invokevirtual #311                // Method value1:()Ljava/lang/Object;
        44: aastore
        45: dup
        46: iconst_2
        47: aload_0
        48: invokevirtual #319                // Method value2:()Ljava/lang/Object;
        51: aastore
        52: dup
        53: iconst_3
        54: aload_0
        55: invokevirtual #321                // Method value3:()Ljava/lang/Object;
        58: aastore
        59: dup
        60: iconst_4
        61: aload_0
        62: invokevirtual #323                // Method value4:()Ljava/lang/Object;
        65: aastore
        66: dup
        67: iconst_5
        68: aload_0
        69: invokevirtual #325                // Method value5:()Ljava/lang/Object;
        72: aastore
        73: dup
        74: bipush        6
        76: aload_0
        77: invokevirtual #327                // Method value6:()Ljava/lang/Object;
        80: aastore
        81: dup
        82: bipush        7
        84: aload_0
        85: invokevirtual #329                // Method value7:()Ljava/lang/Object;
        88: aastore
        89: dup
        90: bipush        8
        92: aload_0
        93: invokevirtual #331                // Method value8:()Ljava/lang/Object;
        96: aastore
        97: dup
        98: bipush        9
       100: aload_0
       101: invokevirtual #333                // Method value9:()Ljava/lang/Object;
       104: aastore
       105: dup
       106: bipush        10
       108: aload_0
       109: invokevirtual #335                // Method value10:()Ljava/lang/Object;
       112: aastore
       113: dup
       114: bipush        11
       116: aload_0
       117: invokevirtual #337                // Method value11:()Ljava/lang/Object;
       120: aastore
       121: dup
       122: bipush        12
       124: aload_0
       125: invokevirtual #339                // Method value12:()Ljava/lang/Object;
       128: aastore
       129: dup
       130: bipush        13
       132: aload_0
       133: invokevirtual #341                // Method value13:()Ljava/lang/Object;
       136: aastore
       137: dup
       138: bipush        14
       140: aload_0
       141: invokevirtual #343                // Method value14:()Ljava/lang/Object;
       144: aastore
       145: dup
       146: bipush        15
       148: aload_0
       149: invokevirtual #345                // Method value15:()Ljava/lang/Object;
       152: aastore
       153: dup
       154: bipush        16
       156: aload_0
       157: invokevirtual #347                // Method value16:()Ljava/lang/Object;
       160: aastore
       161: dup
       162: bipush        17
       164: aload_0
       165: invokevirtual #349                // Method value17:()Ljava/lang/Object;
       168: aastore
       169: dup
       170: bipush        18
       172: aload_0
       173: invokevirtual #351                // Method value18:()Ljava/lang/Object;
       176: aastore
       177: dup
       178: bipush        19
       180: aload_0
       181: invokevirtual #353                // Method value19:()Ljava/lang/Object;
       184: aastore
       185: dup
       186: bipush        20
       188: aload_0
       189: invokevirtual #355                // Method value20:()Ljava/lang/Object;
       192: aastore
       193: dup
       194: bipush        21
       196: aload_0
       197: invokevirtual #357                // Method value21:()Ljava/lang/Object;
       200: aastore
       201: invokevirtual #402                // Method scala/runtime/ScalaRunTime$.genericWrapArray:(Ljava/lang/Object;)Lscala/collection/immutable/ArraySeq;
       204: invokevirtual #407                // Method scala/collection/immutable/Seq$.apply:(Lscala/collection/immutable/Seq;)Lscala/collection/SeqOps;
       207: checkcast     #409                // class scala/collection/Seq
       210: invokeinterface #410,  1          // InterfaceMethod scala/collection/Seq.hashCode:()I
       215: ireturn
      StackMapTable: number_of_entries = 2
        frame_type = 14 /* same */
        frame_type = 247 /* same_locals_1_stack_item_frame_extended */
          offset_delta = 200
          stack = [ int ]
      LineNumberTable:
        line 69: 0
      LocalVariableTable:
        Start  Length  Slot  Name   Signature
            0     216     0  this   Lorg/sireum/MBox21;

  public boolean equals(java.lang.Object);
    descriptor: (Ljava/lang/Object;)Z
    flags: (0x0001) ACC_PUBLIC
    Code:
      stack=2, locals=5, args_size=2
         0: aload_0
         1: invokevirtual #373                // Method $hasEquals:()Z
         4: ifeq          15
         7: aload_0
         8: aload_1
         9: invokespecial #414                // Method java/lang/Object.equals:(Ljava/lang/Object;)Z
        12: goto          388
        15: aload_0
        16: aload_1
        17: if_acmpne     24
        20: iconst_1
        21: goto          388
        24: aload_1
        25: astore_3
        26: aload_3
        27: instanceof    #2                  // class org/sireum/MBox21
        30: ifeq          379
        33: aload_3
        34: checkcast     #2                  // class org/sireum/MBox21
        37: astore        4
        39: aload_0
        40: invokevirtual #415                // Method hashCode:()I
        43: aload         4
        45: invokevirtual #415                // Method hashCode:()I
        48: if_icmpeq     55
        51: iconst_0
        52: goto          375
        55: aload_0
        56: invokevirtual #311                // Method value1:()Ljava/lang/Object;
        59: aload         4
        61: invokevirtual #311                // Method value1:()Ljava/lang/Object;
        64: invokestatic  #420                // Method scala/runtime/BoxesRunTime.equals:(Ljava/lang/Object;Ljava/lang/Object;)Z
        67: ifeq          374
        70: aload_0
        71: invokevirtual #319                // Method value2:()Ljava/lang/Object;
        74: aload         4
        76: invokevirtual #319                // Method value2:()Ljava/lang/Object;
        79: invokestatic  #420                // Method scala/runtime/BoxesRunTime.equals:(Ljava/lang/Object;Ljava/lang/Object;)Z
        82: ifeq          374
        85: aload_0
        86: invokevirtual #321                // Method value3:()Ljava/lang/Object;
        89: aload         4
        91: invokevirtual #321                // Method value3:()Ljava/lang/Object;
        94: invokestatic  #420                // Method scala/runtime/BoxesRunTime.equals:(Ljava/lang/Object;Ljava/lang/Object;)Z
        97: ifeq          374
       100: aload_0
       101: invokevirtual #323                // Method value4:()Ljava/lang/Object;
       104: aload         4
       106: invokevirtual #323                // Method value4:()Ljava/lang/Object;
       109: invokestatic  #420                // Method scala/runtime/BoxesRunTime.equals:(Ljava/lang/Object;Ljava/lang/Object;)Z
       112: ifeq          374
       115: aload_0
       116: invokevirtual #325                // Method value5:()Ljava/lang/Object;
       119: aload         4
       121: invokevirtual #325                // Method value5:()Ljava/lang/Object;
       124: invokestatic  #420                // Method scala/runtime/BoxesRunTime.equals:(Ljava/lang/Object;Ljava/lang/Object;)Z
       127: ifeq          374
       130: aload_0
       131: invokevirtual #327                // Method value6:()Ljava/lang/Object;
       134: aload         4
       136: invokevirtual #327                // Method value6:()Ljava/lang/Object;
       139: invokestatic  #420                // Method scala/runtime/BoxesRunTime.equals:(Ljava/lang/Object;Ljava/lang/Object;)Z
       142: ifeq          374
       145: aload_0
       146: invokevirtual #329                // Method value7:()Ljava/lang/Object;
       149: aload         4
       151: invokevirtual #329                // Method value7:()Ljava/lang/Object;
       154: invokestatic  #420                // Method scala/runtime/BoxesRunTime.equals:(Ljava/lang/Object;Ljava/lang/Object;)Z
       157: ifeq          374
       160: aload_0
       161: invokevirtual #331                // Method value8:()Ljava/lang/Object;
       164: aload         4
       166: invokevirtual #331                // Method value8:()Ljava/lang/Object;
       169: invokestatic  #420                // Method scala/runtime/BoxesRunTime.equals:(Ljava/lang/Object;Ljava/lang/Object;)Z
       172: ifeq          374
       175: aload_0
       176: invokevirtual #333                // Method value9:()Ljava/lang/Object;
       179: aload         4
       181: invokevirtual #333                // Method value9:()Ljava/lang/Object;
       184: invokestatic  #420                // Method scala/runtime/BoxesRunTime.equals:(Ljava/lang/Object;Ljava/lang/Object;)Z
       187: ifeq          374
       190: aload_0
       191: invokevirtual #335                // Method value10:()Ljava/lang/Object;
       194: aload         4
       196: invokevirtual #335                // Method value10:()Ljava/lang/Object;
       199: invokestatic  #420                // Method scala/runtime/BoxesRunTime.equals:(Ljava/lang/Object;Ljava/lang/Object;)Z
       202: ifeq          374
       205: aload_0
       206: invokevirtual #337                // Method value11:()Ljava/lang/Object;
       209: aload         4
       211: invokevirtual #337                // Method value11:()Ljava/lang/Object;
       214: invokestatic  #420                // Method scala/runtime/BoxesRunTime.equals:(Ljava/lang/Object;Ljava/lang/Object;)Z
       217: ifeq          374
       220: aload_0
       221: invokevirtual #339                // Method value12:()Ljava/lang/Object;
       224: aload         4
       226: invokevirtual #339                // Method value12:()Ljava/lang/Object;
       229: invokestatic  #420                // Method scala/runtime/BoxesRunTime.equals:(Ljava/lang/Object;Ljava/lang/Object;)Z
       232: ifeq          374
       235: aload_0
       236: invokevirtual #341                // Method value13:()Ljava/lang/Object;
       239: aload         4
       241: invokevirtual #341                // Method value13:()Ljava/lang/Object;
       244: invokestatic  #420                // Method scala/runtime/BoxesRunTime.equals:(Ljava/lang/Object;Ljava/lang/Object;)Z
       247: ifeq          374
       250: aload_0
       251: invokevirtual #343                // Method value14:()Ljava/lang/Object;
       254: aload         4
       256: invokevirtual #343                // Method value14:()Ljava/lang/Object;
       259: invokestatic  #420                // Method scala/runtime/BoxesRunTime.equals:(Ljava/lang/Object;Ljava/lang/Object;)Z
       262: ifeq          374
       265: aload_0
       266: invokevirtual #345                // Method value15:()Ljava/lang/Object;
       269: aload         4
       271: invokevirtual #345                // Method value15:()Ljava/lang/Object;
       274: invokestatic  #420                // Method scala/runtime/BoxesRunTime.equals:(Ljava/lang/Object;Ljava/lang/Object;)Z
       277: ifeq          374
       280: aload_0
       281: invokevirtual #347                // Method value16:()Ljava/lang/Object;
       284: aload         4
       286: invokevirtual #347                // Method value16:()Ljava/lang/Object;
       289: invokestatic  #420                // Method scala/runtime/BoxesRunTime.equals:(Ljava/lang/Object;Ljava/lang/Object;)Z
       292: ifeq          374
       295: aload_0
       296: invokevirtual #349                // Method value17:()Ljava/lang/Object;
       299: aload         4
       301: invokevirtual #349                // Method value17:()Ljava/lang/Object;
       304: invokestatic  #420                // Method scala/runtime/BoxesRunTime.equals:(Ljava/lang/Object;Ljava/lang/Object;)Z
       307: ifeq          374
       310: aload_0
       311: invokevirtual #351                // Method value18:()Ljava/lang/Object;
       314: aload         4
       316: invokevirtual #351                // Method value18:()Ljava/lang/Object;
       319: invokestatic  #420                // Method scala/runtime/BoxesRunTime.equals:(Ljava/lang/Object;Ljava/lang/Object;)Z
       322: ifeq          374
       325: aload_0
       326: invokevirtual #353                // Method value19:()Ljava/lang/Object;
       329: aload         4
       331: invokevirtual #353                // Method value19:()Ljava/lang/Object;
       334: invokestatic  #420                // Method scala/runtime/BoxesRunTime.equals:(Ljava/lang/Object;Ljava/lang/Object;)Z
       337: ifeq          374
       340: aload_0
       341: invokevirtual #355                // Method value20:()Ljava/lang/Object;
       344: aload         4
       346: invokevirtual #355                // Method value20:()Ljava/lang/Object;
       349: invokestatic  #420                // Method scala/runtime/BoxesRunTime.equals:(Ljava/lang/Object;Ljava/lang/Object;)Z
       352: ifeq          374
       355: aload_0
       356: invokevirtual #357                // Method value21:()Ljava/lang/Object;
       359: aload         4
       361: invokevirtual #357                // Method value21:()Ljava/lang/Object;
       364: invokestatic  #420                // Method scala/runtime/BoxesRunTime.equals:(Ljava/lang/Object;Ljava/lang/Object;)Z
       367: ifeq          374
       370: iconst_1
       371: goto          375
       374: iconst_0
       375: istore_2
       376: goto          387
       379: goto          382
       382: iconst_0
       383: istore_2
       384: goto          387
       387: iload_2
       388: ireturn
      StackMapTable: number_of_entries = 9
        frame_type = 15 /* same */
        frame_type = 8 /* same */
        frame_type = 254 /* append */
          offset_delta = 30
          locals = [ top, class java/lang/Object, class org/sireum/MBox21 ]
        frame_type = 251 /* same_frame_extended */
          offset_delta = 318
        frame_type = 64 /* same_locals_1_stack_item */
          stack = [ int ]
        frame_type = 250 /* chop */
          offset_delta = 3
        frame_type = 2 /* same */
        frame_type = 255 /* full_frame */
          offset_delta = 4
          locals = [ class org/sireum/MBox21, class java/lang/Object, int, class java/lang/Object ]
          stack = []
        frame_type = 255 /* full_frame */
          offset_delta = 0
          locals = [ class org/sireum/MBox21, class java/lang/Object ]
          stack = [ int ]
      LineNumberTable:
        line 69: 0
      LocalVariableTable:
        Start  Length  Slot  Name   Signature
            0     389     0  this   Lorg/sireum/MBox21;
            0     389     1     o   Ljava/lang/Object;
    MethodParameters:
      Name                           Flags
      o                              final

  public org.sireum.MBox21<T1, T2, T3, T4, T5, T6, T7, T8, T9, T10, T11, T12, T13, T14, T15, T16, T17, T18, T19, T20, T21> apply(T1, T2, T3, T4, T5, T6, T7, T8, T9, T10, T11, T12, T13, T14, T15, T16, T17, T18, T19, T20, T21);
    descriptor: (Ljava/lang/Object;Ljava/lang/Object;Ljava/lang/Object;Ljava/lang/Object;Ljava/lang/Object;Ljava/lang/Object;Ljava/lang/Object;Ljava/lang/Object;Ljava/lang/Object;Ljava/lang/Object;Ljava/lang/Object;Ljava/lang/Object;Ljava/lang/Object;Ljava/lang/Object;Ljava/lang/Object;Ljava/lang/Object;Ljava/lang/Object;Ljava/lang/Object;Ljava/lang/Object;Ljava/lang/Object;Ljava/lang/Object;)Lorg/sireum/MBox21;
    flags: (0x0001) ACC_PUBLIC
    Code:
      stack=23, locals=22, args_size=22
         0: new           #2                  // class org/sireum/MBox21
         3: dup
         4: aload_1
         5: aload_2
         6: aload_3
         7: aload         4
         9: aload         5
        11: aload         6
        13: aload         7
        15: aload         8
        17: aload         9
        19: aload         10
        21: aload         11
        23: aload         12
        25: aload         13
        27: aload         14
        29: aload         15
        31: aload         16
        33: aload         17
        35: aload         18
        37: aload         19
        39: aload         20
        41: aload         21
        43: invokespecial #425                // Method "<init>":(Ljava/lang/Object;Ljava/lang/Object;Ljava/lang/Object;Ljava/lang/Object;Ljava/lang/Object;Ljava/lang/Object;Ljava/lang/Object;Ljava/lang/Object;Ljava/lang/Object;Ljava/lang/Object;Ljava/lang/Object;Ljava/lang/Object;Ljava/lang/Object;Ljava/lang/Object;Ljava/lang/Object;Ljava/lang/Object;Ljava/lang/Object;Ljava/lang/Object;Ljava/lang/Object;Ljava/lang/Object;Ljava/lang/Object;)V
        46: areturn
      LineNumberTable:
        line 69: 0
      LocalVariableTable:
        Start  Length  Slot  Name   Signature
            0      47     0  this   Lorg/sireum/MBox21;
            0      47     1 value1   Ljava/lang/Object;
            0      47     2 value2   Ljava/lang/Object;
            0      47     3 value3   Ljava/lang/Object;
            0      47     4 value4   Ljava/lang/Object;
            0      47     5 value5   Ljava/lang/Object;
            0      47     6 value6   Ljava/lang/Object;
            0      47     7 value7   Ljava/lang/Object;
            0      47     8 value8   Ljava/lang/Object;
            0      47     9 value9   Ljava/lang/Object;
            0      47    10 value10   Ljava/lang/Object;
            0      47    11 value11   Ljava/lang/Object;
            0      47    12 value12   Ljava/lang/Object;
            0      47    13 value13   Ljava/lang/Object;
            0      47    14 value14   Ljava/lang/Object;
            0      47    15 value15   Ljava/lang/Object;
            0      47    16 value16   Ljava/lang/Object;
            0      47    17 value17   Ljava/lang/Object;
            0      47    18 value18   Ljava/lang/Object;
            0      47    19 value19   Ljava/lang/Object;
            0      47    20 value20   Ljava/lang/Object;
            0      47    21 value21   Ljava/lang/Object;
    Signature: #422                         // (TT1;TT2;TT3;TT4;TT5;TT6;TT7;TT8;TT9;TT10;TT11;TT12;TT13;TT14;TT15;TT16;TT17;TT18;TT19;TT20;TT21;)Lorg/sireum/MBox21<TT1;TT2;TT3;TT4;TT5;TT6;TT7;TT8;TT9;TT10;TT11;TT12;TT13;TT14;TT15;TT16;TT17;TT18;TT19;TT20;TT21;>;
    MethodParameters:
      Name                           Flags
      value1                         final
      value2                         final
      value3                         final
      value4                         final
      value5                         final
      value6                         final
      value7                         final
      value8                         final
      value9                         final
      value10                        final
      value11                        final
      value12                        final
      value13                        final
      value14                        final
      value15                        final
      value16                        final
      value17                        final
      value18                        final
      value19                        final
      value20                        final
      value21                        final

  public T1 apply$default$1();
    descriptor: ()Ljava/lang/Object;
    flags: (0x0001) ACC_PUBLIC
    Code:
      stack=1, locals=1, args_size=1
         0: aload_0
         1: invokevirtual #311                // Method value1:()Ljava/lang/Object;
         4: areturn
      LineNumberTable:
        line 69: 0
      LocalVariableTable:
        Start  Length  Slot  Name   Signature
            0       5     0  this   Lorg/sireum/MBox21;
    Signature: #114                         // ()TT1;

  public T2 apply$default$2();
    descriptor: ()Ljava/lang/Object;
    flags: (0x0001) ACC_PUBLIC
    Code:
      stack=1, locals=1, args_size=1
         0: aload_0
         1: invokevirtual #319                // Method value2:()Ljava/lang/Object;
         4: areturn
      LineNumberTable:
        line 69: 0
      LocalVariableTable:
        Start  Length  Slot  Name   Signature
            0       5     0  this   Lorg/sireum/MBox21;
    Signature: #123                         // ()TT2;

  public T3 apply$default$3();
    descriptor: ()Ljava/lang/Object;
    flags: (0x0001) ACC_PUBLIC
    Code:
      stack=1, locals=1, args_size=1
         0: aload_0
         1: invokevirtual #321                // Method value3:()Ljava/lang/Object;
         4: areturn
      LineNumberTable:
        line 69: 0
      LocalVariableTable:
        Start  Length  Slot  Name   Signature
            0       5     0  this   Lorg/sireum/MBox21;
    Signature: #131                         // ()TT3;

  public T4 apply$default$4();
    descriptor: ()Ljava/lang/Object;
    flags: (0x0001) ACC_PUBLIC
    Code:
      stack=1, locals=1, args_size=1
         0: aload_0
         1: invokevirtual #323                // Method value4:()Ljava/lang/Object;
         4: areturn
      LineNumberTable:
        line 69: 0
      LocalVariableTable:
        Start  Length  Slot  Name   Signature
            0       5     0  this   Lorg/sireum/MBox21;
    Signature: #139                         // ()TT4;

  public T5 apply$default$5();
    descriptor: ()Ljava/lang/Object;
    flags: (0x0001) ACC_PUBLIC
    Code:
      stack=1, locals=1, args_size=1
         0: aload_0
         1: invokevirtual #325                // Method value5:()Ljava/lang/Object;
         4: areturn
      LineNumberTable:
        line 69: 0
      LocalVariableTable:
        Start  Length  Slot  Name   Signature
            0       5     0  this   Lorg/sireum/MBox21;
    Signature: #147                         // ()TT5;

  public T6 apply$default$6();
    descriptor: ()Ljava/lang/Object;
    flags: (0x0001) ACC_PUBLIC
    Code:
      stack=1, locals=1, args_size=1
         0: aload_0
         1: invokevirtual #327                // Method value6:()Ljava/lang/Object;
         4: areturn
      LineNumberTable:
        line 69: 0
      LocalVariableTable:
        Start  Length  Slot  Name   Signature
            0       5     0  this   Lorg/sireum/MBox21;
    Signature: #155                         // ()TT6;

  public T7 apply$default$7();
    descriptor: ()Ljava/lang/Object;
    flags: (0x0001) ACC_PUBLIC
    Code:
      stack=1, locals=1, args_size=1
         0: aload_0
         1: invokevirtual #329                // Method value7:()Ljava/lang/Object;
         4: areturn
      LineNumberTable:
        line 69: 0
      LocalVariableTable:
        Start  Length  Slot  Name   Signature
            0       5     0  this   Lorg/sireum/MBox21;
    Signature: #163                         // ()TT7;

  public T8 apply$default$8();
    descriptor: ()Ljava/lang/Object;
    flags: (0x0001) ACC_PUBLIC
    Code:
      stack=1, locals=1, args_size=1
         0: aload_0
         1: invokevirtual #331                // Method value8:()Ljava/lang/Object;
         4: areturn
      LineNumberTable:
        line 69: 0
      LocalVariableTable:
        Start  Length  Slot  Name   Signature
            0       5     0  this   Lorg/sireum/MBox21;
    Signature: #171                         // ()TT8;

  public T9 apply$default$9();
    descriptor: ()Ljava/lang/Object;
    flags: (0x0001) ACC_PUBLIC
    Code:
      stack=1, locals=1, args_size=1
         0: aload_0
         1: invokevirtual #333                // Method value9:()Ljava/lang/Object;
         4: areturn
      LineNumberTable:
        line 69: 0
      LocalVariableTable:
        Start  Length  Slot  Name   Signature
            0       5     0  this   Lorg/sireum/MBox21;
    Signature: #179                         // ()TT9;

  public T10 apply$default$10();
    descriptor: ()Ljava/lang/Object;
    flags: (0x0001) ACC_PUBLIC
    Code:
      stack=1, locals=1, args_size=1
         0: aload_0
         1: invokevirtual #335                // Method value10:()Ljava/lang/Object;
         4: areturn
      LineNumberTable:
        line 69: 0
      LocalVariableTable:
        Start  Length  Slot  Name   Signature
            0       5     0  this   Lorg/sireum/MBox21;
    Signature: #187                         // ()TT10;

  public T11 apply$default$11();
    descriptor: ()Ljava/lang/Object;
    flags: (0x0001) ACC_PUBLIC
    Code:
      stack=1, locals=1, args_size=1
         0: aload_0
         1: invokevirtual #337                // Method value11:()Ljava/lang/Object;
         4: areturn
      LineNumberTable:
        line 69: 0
      LocalVariableTable:
        Start  Length  Slot  Name   Signature
            0       5     0  this   Lorg/sireum/MBox21;
    Signature: #195                         // ()TT11;

  public T12 apply$default$12();
    descriptor: ()Ljava/lang/Object;
    flags: (0x0001) ACC_PUBLIC
    Code:
      stack=1, locals=1, args_size=1
         0: aload_0
         1: invokevirtual #339                // Method value12:()Ljava/lang/Object;
         4: areturn
      LineNumberTable:
        line 69: 0
      LocalVariableTable:
        Start  Length  Slot  Name   Signature
            0       5     0  this   Lorg/sireum/MBox21;
    Signature: #203                         // ()TT12;

  public T13 apply$default$13();
    descriptor: ()Ljava/lang/Object;
    flags: (0x0001) ACC_PUBLIC
    Code:
      stack=1, locals=1, args_size=1
         0: aload_0
         1: invokevirtual #341                // Method value13:()Ljava/lang/Object;
         4: areturn
      LineNumberTable:
        line 69: 0
      LocalVariableTable:
        Start  Length  Slot  Name   Signature
            0       5     0  this   Lorg/sireum/MBox21;
    Signature: #211                         // ()TT13;

  public T14 apply$default$14();
    descriptor: ()Ljava/lang/Object;
    flags: (0x0001) ACC_PUBLIC
    Code:
      stack=1, locals=1, args_size=1
         0: aload_0
         1: invokevirtual #343                // Method value14:()Ljava/lang/Object;
         4: areturn
      LineNumberTable:
        line 69: 0
      LocalVariableTable:
        Start  Length  Slot  Name   Signature
            0       5     0  this   Lorg/sireum/MBox21;
    Signature: #219                         // ()TT14;

  public T15 apply$default$15();
    descriptor: ()Ljava/lang/Object;
    flags: (0x0001) ACC_PUBLIC
    Code:
      stack=1, locals=1, args_size=1
         0: aload_0
         1: invokevirtual #345                // Method value15:()Ljava/lang/Object;
         4: areturn
      LineNumberTable:
        line 69: 0
      LocalVariableTable:
        Start  Length  Slot  Name   Signature
            0       5     0  this   Lorg/sireum/MBox21;
    Signature: #227                         // ()TT15;

  public T16 apply$default$16();
    descriptor: ()Ljava/lang/Object;
    flags: (0x0001) ACC_PUBLIC
    Code:
      stack=1, locals=1, args_size=1
         0: aload_0
         1: invokevirtual #347                // Method value16:()Ljava/lang/Object;
         4: areturn
      LineNumberTable:
        line 69: 0
      LocalVariableTable:
        Start  Length  Slot  Name   Signature
            0       5     0  this   Lorg/sireum/MBox21;
    Signature: #235                         // ()TT16;

  public T17 apply$default$17();
    descriptor: ()Ljava/lang/Object;
    flags: (0x0001) ACC_PUBLIC
    Code:
      stack=1, locals=1, args_size=1
         0: aload_0
         1: invokevirtual #349                // Method value17:()Ljava/lang/Object;
         4: areturn
      LineNumberTable:
        line 69: 0
      LocalVariableTable:
        Start  Length  Slot  Name   Signature
            0       5     0  this   Lorg/sireum/MBox21;
    Signature: #243                         // ()TT17;

  public T18 apply$default$18();
    descriptor: ()Ljava/lang/Object;
    flags: (0x0001) ACC_PUBLIC
    Code:
      stack=1, locals=1, args_size=1
         0: aload_0
         1: invokevirtual #351                // Method value18:()Ljava/lang/Object;
         4: areturn
      LineNumberTable:
        line 69: 0
      LocalVariableTable:
        Start  Length  Slot  Name   Signature
            0       5     0  this   Lorg/sireum/MBox21;
    Signature: #251                         // ()TT18;

  public T19 apply$default$19();
    descriptor: ()Ljava/lang/Object;
    flags: (0x0001) ACC_PUBLIC
    Code:
      stack=1, locals=1, args_size=1
         0: aload_0
         1: invokevirtual #353                // Method value19:()Ljava/lang/Object;
         4: areturn
      LineNumberTable:
        line 69: 0
      LocalVariableTable:
        Start  Length  Slot  Name   Signature
            0       5     0  this   Lorg/sireum/MBox21;
    Signature: #259                         // ()TT19;

  public T20 apply$default$20();
    descriptor: ()Ljava/lang/Object;
    flags: (0x0001) ACC_PUBLIC
    Code:
      stack=1, locals=1, args_size=1
         0: aload_0
         1: invokevirtual #355                // Method value20:()Ljava/lang/Object;
         4: areturn
      LineNumberTable:
        line 69: 0
      LocalVariableTable:
        Start  Length  Slot  Name   Signature
            0       5     0  this   Lorg/sireum/MBox21;
    Signature: #267                         // ()TT20;

  public T21 apply$default$21();
    descriptor: ()Ljava/lang/Object;
    flags: (0x0001) ACC_PUBLIC
    Code:
      stack=1, locals=1, args_size=1
         0: aload_0
         1: invokevirtual #357                // Method value21:()Ljava/lang/Object;
         4: areturn
      LineNumberTable:
        line 69: 0
      LocalVariableTable:
        Start  Length  Slot  Name   Signature
            0       5     0  this   Lorg/sireum/MBox21;
    Signature: #275                         // ()TT21;

  public scala.collection.immutable.Seq<scala.Tuple2<java.lang.String, java.lang.Object>> $content();
    descriptor: ()Lscala/collection/immutable/Seq;
    flags: (0x0001) ACC_PUBLIC
    Code:
      stack=14, locals=1, args_size=1
         0: getstatic     #380                // Field scala/package$.MODULE$:Lscala/package$;
         3: invokevirtual #384                // Method scala/package$.Seq:()Lscala/collection/immutable/Seq$;
         6: getstatic     #389                // Field scala/runtime/ScalaRunTime$.MODULE$:Lscala/runtime/ScalaRunTime$;
         9: bipush        22
        11: anewarray     #451                // class scala/Tuple2
        14: dup
        15: iconst_0
        16: new           #451                // class scala/Tuple2
        19: dup
        20: ldc_w         #453                // String type
        23: getstatic     #380                // Field scala/package$.MODULE$:Lscala/package$;
        26: invokevirtual #457                // Method scala/package$.List:()Lscala/collection/immutable/List$;
        29: getstatic     #389                // Field scala/runtime/ScalaRunTime$.MODULE$:Lscala/runtime/ScalaRunTime$;
        32: iconst_3
        33: anewarray     #363                // class java/lang/String
        36: dup
        37: iconst_0
        38: ldc_w         #459                // String org
        41: aastore
        42: dup
        43: iconst_1
        44: ldc_w         #461                // String sireum
        47: aastore
        48: dup
        49: iconst_2
        50: ldc_w         #297                // String MBox21
        53: aastore
        54: checkcast     #463                // class "[Ljava/lang/Object;"
        57: invokevirtual #467                // Method scala/runtime/ScalaRunTime$.wrapRefArray:([Ljava/lang/Object;)Lscala/collection/immutable/ArraySeq;
        60: invokevirtual #472                // Method scala/collection/immutable/List$.apply:(Lscala/collection/immutable/Seq;)Ljava/lang/Object;
        63: invokespecial #475                // Method scala/Tuple2."<init>":(Ljava/lang/Object;Ljava/lang/Object;)V
        66: aastore
        67: dup
        68: iconst_1
        69: new           #451                // class scala/Tuple2
        72: dup
        73: ldc_w         #476                // String value1
        76: aload_0
        77: invokevirtual #311                // Method value1:()Ljava/lang/Object;
        80: invokespecial #475                // Method scala/Tuple2."<init>":(Ljava/lang/Object;Ljava/lang/Object;)V
        83: aastore
        84: dup
        85: iconst_2
        86: new           #451                // class scala/Tuple2
        89: dup
        90: ldc_w         #477                // String value2
        93: aload_0
        94: invokevirtual #319                // Method value2:()Ljava/lang/Object;
        97: invokespecial #475                // Method scala/Tuple2."<init>":(Ljava/lang/Object;Ljava/lang/Object;)V
       100: aastore
       101: dup
       102: iconst_3
       103: new           #451                // class scala/Tuple2
       106: dup
       107: ldc_w         #478                // String value3
       110: aload_0
       111: invokevirtual #321                // Method value3:()Ljava/lang/Object;
       114: invokespecial #475                // Method scala/Tuple2."<init>":(Ljava/lang/Object;Ljava/lang/Object;)V
       117: aastore
       118: dup
       119: iconst_4
       120: new           #451                // class scala/Tuple2
       123: dup
       124: ldc_w         #479                // String value4
       127: aload_0
       128: invokevirtual #323                // Method value4:()Ljava/lang/Object;
       131: invokespecial #475                // Method scala/Tuple2."<init>":(Ljava/lang/Object;Ljava/lang/Object;)V
       134: aastore
       135: dup
       136: iconst_5
       137: new           #451                // class scala/Tuple2
       140: dup
       141: ldc_w         #480                // String value5
       144: aload_0
       145: invokevirtual #325                // Method value5:()Ljava/lang/Object;
       148: invokespecial #475                // Method scala/Tuple2."<init>":(Ljava/lang/Object;Ljava/lang/Object;)V
       151: aastore
       152: dup
       153: bipush        6
       155: new           #451                // class scala/Tuple2
       158: dup
       159: ldc_w         #481                // String value6
       162: aload_0
       163: invokevirtual #327                // Method value6:()Ljava/lang/Object;
       166: invokespecial #475                // Method scala/Tuple2."<init>":(Ljava/lang/Object;Ljava/lang/Object;)V
       169: aastore
       170: dup
       171: bipush        7
       173: new           #451                // class scala/Tuple2
       176: dup
       177: ldc_w         #482                // String value7
       180: aload_0
       181: invokevirtual #329                // Method value7:()Ljava/lang/Object;
       184: invokespecial #475                // Method scala/Tuple2."<init>":(Ljava/lang/Object;Ljava/lang/Object;)V
       187: aastore
       188: dup
       189: bipush        8
       191: new           #451                // class scala/Tuple2
       194: dup
       195: ldc_w         #483                // String value8
       198: aload_0
       199: invokevirtual #331                // Method value8:()Ljava/lang/Object;
       202: invokespecial #475                // Method scala/Tuple2."<init>":(Ljava/lang/Object;Ljava/lang/Object;)V
       205: aastore
       206: dup
       207: bipush        9
       209: new           #451                // class scala/Tuple2
       212: dup
       213: ldc_w         #484                // String value9
       216: aload_0
       217: invokevirtual #333                // Method value9:()Ljava/lang/Object;
       220: invokespecial #475                // Method scala/Tuple2."<init>":(Ljava/lang/Object;Ljava/lang/Object;)V
       223: aastore
       224: dup
       225: bipush        10
       227: new           #451                // class scala/Tuple2
       230: dup
       231: ldc_w         #485                // String value10
       234: aload_0
       235: invokevirtual #335                // Method value10:()Ljava/lang/Object;
       238: invokespecial #475                // Method scala/Tuple2."<init>":(Ljava/lang/Object;Ljava/lang/Object;)V
       241: aastore
       242: dup
       243: bipush        11
       245: new           #451                // class scala/Tuple2
       248: dup
       249: ldc_w         #486                // String value11
       252: aload_0
       253: invokevirtual #337                // Method value11:()Ljava/lang/Object;
       256: invokespecial #475                // Method scala/Tuple2."<init>":(Ljava/lang/Object;Ljava/lang/Object;)V
       259: aastore
       260: dup
       261: bipush        12
       263: new           #451                // class scala/Tuple2
       266: dup
       267: ldc_w         #487                // String value12
       270: aload_0
       271: invokevirtual #339                // Method value12:()Ljava/lang/Object;
       274: invokespecial #475                // Method scala/Tuple2."<init>":(Ljava/lang/Object;Ljava/lang/Object;)V
       277: aastore
       278: dup
       279: bipush        13
       281: new           #451                // class scala/Tuple2
       284: dup
       285: ldc_w         #488                // String value13
       288: aload_0
       289: invokevirtual #341                // Method value13:()Ljava/lang/Object;
       292: invokespecial #475                // Method scala/Tuple2."<init>":(Ljava/lang/Object;Ljava/lang/Object;)V
       295: aastore
       296: dup
       297: bipush        14
       299: new           #451                // class scala/Tuple2
       302: dup
       303: ldc_w         #489                // String value14
       306: aload_0
       307: invokevirtual #343                // Method value14:()Ljava/lang/Object;
       310: invokespecial #475                // Method scala/Tuple2."<init>":(Ljava/lang/Object;Ljava/lang/Object;)V
       313: aastore
       314: dup
       315: bipush        15
       317: new           #451                // class scala/Tuple2
       320: dup
       321: ldc_w         #490                // String value15
       324: aload_0
       325: invokevirtual #345                // Method value15:()Ljava/lang/Object;
       328: invokespecial #475                // Method scala/Tuple2."<init>":(Ljava/lang/Object;Ljava/lang/Object;)V
       331: aastore
       332: dup
       333: bipush        16
       335: new           #451                // class scala/Tuple2
       338: dup
       339: ldc_w         #491                // String value16
       342: aload_0
       343: invokevirtual #347                // Method value16:()Ljava/lang/Object;
       346: invokespecial #475                // Method scala/Tuple2."<init>":(Ljava/lang/Object;Ljava/lang/Object;)V
       349: aastore
       350: dup
       351: bipush        17
       353: new           #451                // class scala/Tuple2
       356: dup
       357: ldc_w         #492                // String value17
       360: aload_0
       361: invokevirtual #349                // Method value17:()Ljava/lang/Object;
       364: invokespecial #475                // Method scala/Tuple2."<init>":(Ljava/lang/Object;Ljava/lang/Object;)V
       367: aastore
       368: dup
       369: bipush        18
       371: new           #451                // class scala/Tuple2
       374: dup
       375: ldc_w         #493                // String value18
       378: aload_0
       379: invokevirtual #351                // Method value18:()Ljava/lang/Object;
       382: invokespecial #475                // Method scala/Tuple2."<init>":(Ljava/lang/Object;Ljava/lang/Object;)V
       385: aastore
       386: dup
       387: bipush        19
       389: new           #451                // class scala/Tuple2
       392: dup
       393: ldc_w         #494                // String value19
       396: aload_0
       397: invokevirtual #353                // Method value19:()Ljava/lang/Object;
       400: invokespecial #475                // Method scala/Tuple2."<init>":(Ljava/lang/Object;Ljava/lang/Object;)V
       403: aastore
       404: dup
       405: bipush        20
       407: new           #451                // class scala/Tuple2
       410: dup
       411: ldc_w         #495                // String value20
       414: aload_0
       415: invokevirtual #355                // Method value20:()Ljava/lang/Object;
       418: invokespecial #475                // Method scala/Tuple2."<init>":(Ljava/lang/Object;Ljava/lang/Object;)V
       421: aastore
       422: dup
       423: bipush        21
       425: new           #451                // class scala/Tuple2
       428: dup
       429: ldc_w         #496                // String value21
       432: aload_0
       433: invokevirtual #357                // Method value21:()Ljava/lang/Object;
       436: invokespecial #475                // Method scala/Tuple2."<init>":(Ljava/lang/Object;Ljava/lang/Object;)V
       439: aastore
       440: checkcast     #463                // class "[Ljava/lang/Object;"
       443: invokevirtual #467                // Method scala/runtime/ScalaRunTime$.wrapRefArray:([Ljava/lang/Object;)Lscala/collection/immutable/ArraySeq;
       446: invokevirtual #407                // Method scala/collection/immutable/Seq$.apply:(Lscala/collection/immutable/Seq;)Lscala/collection/SeqOps;
       449: checkcast     #498                // class scala/collection/immutable/Seq
       452: areturn
      LineNumberTable:
        line 69: 0
      LocalVariableTable:
        Start  Length  Slot  Name   Signature
            0     453     0  this   Lorg/sireum/MBox21;
    Signature: #449                         // ()Lscala/collection/immutable/Seq<Lscala/Tuple2<Ljava/lang/String;Ljava/lang/Object;>;>;

  public org.sireum.MBox21<T1, T2, T3, T4, T5, T6, T7, T8, T9, T10, T11, T12, T13, T14, T15, T16, T17, T18, T19, T20, T21> $clone();
    descriptor: ()Lorg/sireum/MBox21;
    flags: (0x0001) ACC_PUBLIC
    Code:
      stack=24, locals=2, args_size=1
         0: new           #2                  // class org/sireum/MBox21
         3: dup
         4: getstatic     #506                // Field org/sireum/helper$.MODULE$:Lorg/sireum/helper$;
         7: aload_0
         8: invokevirtual #311                // Method value1:()Ljava/lang/Object;
        11: invokevirtual #510                // Method org/sireum/helper$.cloneAssign:(Ljava/lang/Object;)Ljava/lang/Object;
        14: getstatic     #506                // Field org/sireum/helper$.MODULE$:Lorg/sireum/helper$;
        17: aload_0
        18: invokevirtual #319                // Method value2:()Ljava/lang/Object;
        21: invokevirtual #510                // Method org/sireum/helper$.cloneAssign:(Ljava/lang/Object;)Ljava/lang/Object;
        24: getstatic     #506                // Field org/sireum/helper$.MODULE$:Lorg/sireum/helper$;
        27: aload_0
        28: invokevirtual #321                // Method value3:()Ljava/lang/Object;
        31: invokevirtual #510                // Method org/sireum/helper$.cloneAssign:(Ljava/lang/Object;)Ljava/lang/Object;
        34: getstatic     #506                // Field org/sireum/helper$.MODULE$:Lorg/sireum/helper$;
        37: aload_0
        38: invokevirtual #323                // Method value4:()Ljava/lang/Object;
        41: invokevirtual #510                // Method org/sireum/helper$.cloneAssign:(Ljava/lang/Object;)Ljava/lang/Object;
        44: getstatic     #506                // Field org/sireum/helper$.MODULE$:Lorg/sireum/helper$;
        47: aload_0
        48: invokevirtual #325                // Method value5:()Ljava/lang/Object;
        51: invokevirtual #510                // Method org/sireum/helper$.cloneAssign:(Ljava/lang/Object;)Ljava/lang/Object;
        54: getstatic     #506                // Field org/sireum/helper$.MODULE$:Lorg/sireum/helper$;
        57: aload_0
        58: invokevirtual #327                // Method value6:()Ljava/lang/Object;
        61: invokevirtual #510                // Method org/sireum/helper$.cloneAssign:(Ljava/lang/Object;)Ljava/lang/Object;
        64: getstatic     #506                // Field org/sireum/helper$.MODULE$:Lorg/sireum/helper$;
        67: aload_0
        68: invokevirtual #329                // Method value7:()Ljava/lang/Object;
        71: invokevirtual #510                // Method org/sireum/helper$.cloneAssign:(Ljava/lang/Object;)Ljava/lang/Object;
        74: getstatic     #506                // Field org/sireum/helper$.MODULE$:Lorg/sireum/helper$;
        77: aload_0
        78: invokevirtual #331                // Method value8:()Ljava/lang/Object;
        81: invokevirtual #510                // Method org/sireum/helper$.cloneAssign:(Ljava/lang/Object;)Ljava/lang/Object;
        84: getstatic     #506                // Field org/sireum/helper$.MODULE$:Lorg/sireum/helper$;
        87: aload_0
        88: invokevirtual #333                // Method value9:()Ljava/lang/Object;
        91: invokevirtual #510                // Method org/sireum/helper$.cloneAssign:(Ljava/lang/Object;)Ljava/lang/Object;
        94: getstatic     #506                // Field org/sireum/helper$.MODULE$:Lorg/sireum/helper$;
        97: aload_0
        98: invokevirtual #335                // Method value10:()Ljava/lang/Object;
       101: invokevirtual #510                // Method org/sireum/helper$.cloneAssign:(Ljava/lang/Object;)Ljava/lang/Object;
       104: getstatic     #506                // Field org/sireum/helper$.MODULE$:Lorg/sireum/helper$;
       107: aload_0
       108: invokevirtual #337                // Method value11:()Ljava/lang/Object;
       111: invokevirtual #510                // Method org/sireum/helper$.cloneAssign:(Ljava/lang/Object;)Ljava/lang/Object;
       114: getstatic     #506                // Field org/sireum/helper$.MODULE$:Lorg/sireum/helper$;
       117: aload_0
       118: invokevirtual #339                // Method value12:()Ljava/lang/Object;
       121: invokevirtual #510                // Method org/sireum/helper$.cloneAssign:(Ljava/lang/Object;)Ljava/lang/Object;
       124: getstatic     #506                // Field org/sireum/helper$.MODULE$:Lorg/sireum/helper$;
       127: aload_0
       128: invokevirtual #341                // Method value13:()Ljava/lang/Object;
       131: invokevirtual #510                // Method org/sireum/helper$.cloneAssign:(Ljava/lang/Object;)Ljava/lang/Object;
       134: getstatic     #506                // Field org/sireum/helper$.MODULE$:Lorg/sireum/helper$;
       137: aload_0
       138: invokevirtual #343                // Method value14:()Ljava/lang/Object;
       141: invokevirtual #510                // Method org/sireum/helper$.cloneAssign:(Ljava/lang/Object;)Ljava/lang/Object;
       144: getstatic     #506                // Field org/sireum/helper$.MODULE$:Lorg/sireum/helper$;
       147: aload_0
       148: invokevirtual #345                // Method value15:()Ljava/lang/Object;
       151: invokevirtual #510                // Method org/sireum/helper$.cloneAssign:(Ljava/lang/Object;)Ljava/lang/Object;
       154: getstatic     #506                // Field org/sireum/helper$.MODULE$:Lorg/sireum/helper$;
       157: aload_0
       158: invokevirtual #347                // Method value16:()Ljava/lang/Object;
       161: invokevirtual #510                // Method org/sireum/helper$.cloneAssign:(Ljava/lang/Object;)Ljava/lang/Object;
       164: getstatic     #506                // Field org/sireum/helper$.MODULE$:Lorg/sireum/helper$;
       167: aload_0
       168: invokevirtual #349                // Method value17:()Ljava/lang/Object;
       171: invokevirtual #510                // Method org/sireum/helper$.cloneAssign:(Ljava/lang/Object;)Ljava/lang/Object;
       174: getstatic     #506                // Field org/sireum/helper$.MODULE$:Lorg/sireum/helper$;
       177: aload_0
       178: invokevirtual #351                // Method value18:()Ljava/lang/Object;
       181: invokevirtual #510                // Method org/sireum/helper$.cloneAssign:(Ljava/lang/Object;)Ljava/lang/Object;
       184: getstatic     #506                // Field org/sireum/helper$.MODULE$:Lorg/sireum/helper$;
       187: aload_0
       188: invokevirtual #353                // Method value19:()Ljava/lang/Object;
       191: invokevirtual #510                // Method org/sireum/helper$.cloneAssign:(Ljava/lang/Object;)Ljava/lang/Object;
       194: getstatic     #506                // Field org/sireum/helper$.MODULE$:Lorg/sireum/helper$;
       197: aload_0
       198: invokevirtual #355                // Method value20:()Ljava/lang/Object;
       201: invokevirtual #510                // Method org/sireum/helper$.cloneAssign:(Ljava/lang/Object;)Ljava/lang/Object;
       204: getstatic     #506                // Field org/sireum/helper$.MODULE$:Lorg/sireum/helper$;
       207: aload_0
       208: invokevirtual #357                // Method value21:()Ljava/lang/Object;
       211: invokevirtual #510                // Method org/sireum/helper$.cloneAssign:(Ljava/lang/Object;)Ljava/lang/Object;
       214: invokespecial #425                // Method "<init>":(Ljava/lang/Object;Ljava/lang/Object;Ljava/lang/Object;Ljava/lang/Object;Ljava/lang/Object;Ljava/lang/Object;Ljava/lang/Object;Ljava/lang/Object;Ljava/lang/Object;Ljava/lang/Object;Ljava/lang/Object;Ljava/lang/Object;Ljava/lang/Object;Ljava/lang/Object;Ljava/lang/Object;Ljava/lang/Object;Ljava/lang/Object;Ljava/lang/Object;Ljava/lang/Object;Ljava/lang/Object;Ljava/lang/Object;)V
       217: astore_1
       218: aload_1
       219: areturn
      LineNumberTable:
        line 69: 0
      LocalVariableTable:
        Start  Length  Slot  Name   Signature
          218       1     1     r   Lorg/sireum/MBox21;
            0     220     0  this   Lorg/sireum/MBox21;
    Signature: #501                         // ()Lorg/sireum/MBox21<TT1;TT2;TT3;TT4;TT5;TT6;TT7;TT8;TT9;TT10;TT11;TT12;TT13;TT14;TT15;TT16;TT17;TT18;TT19;TT20;TT21;>;

  public final org.sireum.$internal.MutableMarker $owned_$eq(boolean);
    descriptor: (Z)Lorg/sireum/$internal/MutableMarker;
    flags: (0x1051) ACC_PUBLIC, ACC_FINAL, ACC_BRIDGE, ACC_SYNTHETIC
    Code:
      stack=2, locals=2, args_size=2
         0: aload_0
         1: iload_1
         2: invokevirtual #514                // Method $owned_$eq:(Z)Lorg/sireum/RecordSig;
         5: areturn
      LineNumberTable:
        line 69: 0
      LocalVariableTable:
        Start  Length  Slot  Name   Signature
            0       6     0  this   Lorg/sireum/MBox21;
            0       6     1     b   Z
    MethodParameters:
      Name                           Flags
      b                              final

  public java.lang.Object $clone();
    descriptor: ()Ljava/lang/Object;
    flags: (0x1041) ACC_PUBLIC, ACC_BRIDGE, ACC_SYNTHETIC
    Code:
      stack=1, locals=1, args_size=1
         0: aload_0
         1: invokevirtual #516                // Method $clone:()Lorg/sireum/MBox21;
         4: areturn
      LineNumberTable:
        line 69: 0
      LocalVariableTable:
        Start  Length  Slot  Name   Signature
            0       5     0  this   Lorg/sireum/MBox21;

  public org.sireum.$internal.MutableMarker $clone();
    descriptor: ()Lorg/sireum/$internal/MutableMarker;
    flags: (0x1041) ACC_PUBLIC, ACC_BRIDGE, ACC_SYNTHETIC
    Code:
      stack=1, locals=1, args_size=1
         0: aload_0
         1: invokevirtual #516                // Method $clone:()Lorg/sireum/MBox21;
         4: areturn
      LineNumberTable:
        line 69: 0
      LocalVariableTable:
        Start  Length  Slot  Name   Signature
            0       5     0  this   Lorg/sireum/MBox21;

  public org.sireum.MBox21(T1, T2, T3, T4, T5, T6, T7, T8, T9, T10, T11, T12, T13, T14, T15, T16, T17, T18, T19, T20, T21);
    descriptor: (Ljava/lang/Object;Ljava/lang/Object;Ljava/lang/Object;Ljava/lang/Object;Ljava/lang/Object;Ljava/lang/Object;Ljava/lang/Object;Ljava/lang/Object;Ljava/lang/Object;Ljava/lang/Object;Ljava/lang/Object;Ljava/lang/Object;Ljava/lang/Object;Ljava/lang/Object;Ljava/lang/Object;Ljava/lang/Object;Ljava/lang/Object;Ljava/lang/Object;Ljava/lang/Object;Ljava/lang/Object;Ljava/lang/Object;)V
    flags: (0x0001) ACC_PUBLIC
    Code:
      stack=2, locals=22, args_size=22
         0: aload_0
         1: invokespecial #540                // Method java/lang/Object."<init>":()V
         4: aload_0
         5: invokestatic  #544                // InterfaceMethod org/sireum/Mutable.$init$:(Lorg/sireum/Mutable;)V
         8: aload_0
         9: invokestatic  #547                // InterfaceMethod org/sireum/RecordSig.$init$:(Lorg/sireum/RecordSig;)V
        12: aload_0
        13: aload_1
        14: putfield      #116                // Field _value1:Ljava/lang/Object;
        17: aload_0
        18: aload_2
        19: putfield      #125                // Field _value2:Ljava/lang/Object;
        22: aload_0
        23: aload_3
        24: putfield      #133                // Field _value3:Ljava/lang/Object;
        27: aload_0
        28: aload         4
        30: putfield      #141                // Field _value4:Ljava/lang/Object;
        33: aload_0
        34: aload         5
        36: putfield      #149                // Field _value5:Ljava/lang/Object;
        39: aload_0
        40: aload         6
        42: putfield      #157                // Field _value6:Ljava/lang/Object;
        45: aload_0
        46: aload         7
        48: putfield      #165                // Field _value7:Ljava/lang/Object;
        51: aload_0
        52: aload         8
        54: putfield      #173                // Field _value8:Ljava/lang/Object;
        57: aload_0
        58: aload         9
        60: putfield      #181                // Field _value9:Ljava/lang/Object;
        63: aload_0
        64: aload         10
        66: putfield      #189                // Field _value10:Ljava/lang/Object;
        69: aload_0
        70: aload         11
        72: putfield      #197                // Field _value11:Ljava/lang/Object;
        75: aload_0
        76: aload         12
        78: putfield      #205                // Field _value12:Ljava/lang/Object;
        81: aload_0
        82: aload         13
        84: putfield      #213                // Field _value13:Ljava/lang/Object;
        87: aload_0
        88: aload         14
        90: putfield      #221                // Field _value14:Ljava/lang/Object;
        93: aload_0
        94: aload         15
        96: putfield      #229                // Field _value15:Ljava/lang/Object;
        99: aload_0
       100: aload         16
       102: putfield      #237                // Field _value16:Ljava/lang/Object;
       105: aload_0
       106: aload         17
       108: putfield      #245                // Field _value17:Ljava/lang/Object;
       111: aload_0
       112: aload         18
       114: putfield      #253                // Field _value18:Ljava/lang/Object;
       117: aload_0
       118: aload         19
       120: putfield      #261                // Field _value19:Ljava/lang/Object;
       123: aload_0
       124: aload         20
       126: putfield      #269                // Field _value20:Ljava/lang/Object;
       129: aload_0
       130: aload         21
       132: putfield      #277                // Field _value21:Ljava/lang/Object;
       135: return
      LineNumberTable:
        line 69: 0
      LocalVariableTable:
        Start  Length  Slot  Name   Signature
            0     136     0  this   Lorg/sireum/MBox21;
            0     136     1 __value1   Ljava/lang/Object;
            0     136     2 __value2   Ljava/lang/Object;
            0     136     3 __value3   Ljava/lang/Object;
            0     136     4 __value4   Ljava/lang/Object;
            0     136     5 __value5   Ljava/lang/Object;
            0     136     6 __value6   Ljava/lang/Object;
            0     136     7 __value7   Ljava/lang/Object;
            0     136     8 __value8   Ljava/lang/Object;
            0     136     9 __value9   Ljava/lang/Object;
            0     136    10 __value10   Ljava/lang/Object;
            0     136    11 __value11   Ljava/lang/Object;
            0     136    12 __value12   Ljava/lang/Object;
            0     136    13 __value13   Ljava/lang/Object;
            0     136    14 __value14   Ljava/lang/Object;
            0     136    15 __value15   Ljava/lang/Object;
            0     136    16 __value16   Ljava/lang/Object;
            0     136    17 __value17   Ljava/lang/Object;
            0     136    18 __value18   Ljava/lang/Object;
            0     136    19 __value19   Ljava/lang/Object;
            0     136    20 __value20   Ljava/lang/Object;
            0     136    21 __value21   Ljava/lang/Object;
    Signature: #518                         // (TT1;TT2;TT3;TT4;TT5;TT6;TT7;TT8;TT9;TT10;TT11;TT12;TT13;TT14;TT15;TT16;TT17;TT18;TT19;TT20;TT21;)V
    MethodParameters:
      Name                           Flags
      __value1                       final
      __value2                       final
      __value3                       final
      __value4                       final
      __value5                       final
      __value6                       final
      __value7                       final
      __value8                       final
      __value9                       final
      __value10                      final
      __value11                      final
      __value12                      final
      __value13                      final
      __value14                      final
      __value15                      final
      __value16                      final
      __value17                      final
      __value18                      final
      __value19                      final
      __value20                      final
      __value21                      final
}
Signature: #3                           // <T1:Ljava/lang/Object;T2:Ljava/lang/Object;T3:Ljava/lang/Object;T4:Ljava/lang/Object;T5:Ljava/lang/Object;T6:Ljava/lang/Object;T7:Ljava/lang/Object;T8:Ljava/lang/Object;T9:Ljava/lang/Object;T10:Ljava/lang/Object;T11:Ljava/lang/Object;T12:Ljava/lang/Object;T13:Ljava/lang/Object;T14:Ljava/lang/Object;T15:Ljava/lang/Object;T16:Ljava/lang/Object;T17:Ljava/lang/Object;T18:Ljava/lang/Object;T19:Ljava/lang/Object;T20:Ljava/lang/Object;T21:Ljava/lang/Object;>Ljava/lang/Object;Lorg/sireum/RecordSig;
SourceFile: "MBox.scala"
RuntimeVisibleAnnotations:
  0: #9(#10=s#11)
    scala.reflect.ScalaSignature(
      bytes="\u0006\u0005\u0019-q\u0001CA\"\u0003\u000bB\t!a\u0014\u0007\u0011\u0005M\u0013Q\tE\u0001\u0003+Bq!a\u0019\u0002\t\u0003\t)\u0007C\u0004\u0002h\u0005!\t!!\u001b\t\u000f\u0015\u0005\u0016\u0001\"\u0001\u0006$\u001a9\u00111KA#\u0005\u0005=\u0004BCA=\u000b\t\u0005\t\u0015!\u0003\u0002|!Q\u0011\u0011S\u0003\u0003\u0002\u0003\u0006I!a%\t\u0015\u0005eUA!A!\u0002\u0013\tY\n\u0003\u0006\u0002\"\u0016\u0011\t\u0011)A\u0005\u0003GC!\"!+\u0006\u0005\u0003\u0005\u000b\u0011BAV\u0011)\t\t,\u0002B\u0001B\u0003%\u00111\u0017\u0005\u000b\u0003s+!\u0011!Q\u0001\n\u0005m\u0006BCAa\u000b\t\u0005\t\u0015!\u0003\u0002D\"Q\u0011\u0011Z\u0003\u0003\u0002\u0003\u0006I!a3\t\u0015\u0005EWA!A!\u0002\u0013\t\u0019\u000e\u0003\u0006\u0002Z\u0016\u0011\t\u0011)A\u0005\u00037D!\"!9\u0006\u0005\u0003\u0005\u000b\u0011BAr\u0011)\tI/\u0002B\u0001B\u0003%\u00111\u001e\u0005\u000b\u0003c,!\u0011!Q\u0001\n\u0005M\bBCA}\u000b\t\u0005\t\u0015!\u0003\u0002|\"Q!\u0011A\u0003\u0003\u0002\u0003\u0006IAa\u0001\t\u0015\t%QA!A!\u0002\u0013\u0011Y\u0001\u0003\u0006\u0003\u0012\u0015\u0011\t\u0011)A\u0005\u0005\'A!B!\u0007\u0006\u0005\u0003\u0005\u000b\u0011\u0002B\u000e\u0011)\u0011\t#\u0002B\u0001B\u0003%!1\u0005\u0005\u000b\u0005S)!\u0011!Q\u0001\n\t-\u0002bBA2\u000b\u0011\u0005!\u0011\u0007\u0005\t\u0005?*\u0001\u0015)\u0003\u0002|!9!\u0011M\u0003\u0005\u0002\t\r\u0004b\u0002B3\u000b\u0011\u0005!1\r\u0005\b\u0005O*A\u0011\u0001B5\u0011\u001d\u0011y\'\u0002C\u0001\u0005cB\u0001B!\u001e\u0006A\u0003&\u00111\u0013\u0005\b\u0005o*A\u0011\u0001B=\u0011\u001d\u0011Y(\u0002C\u0001\u0005sBqA! \u0006\t\u0003\u0011y\bC\u0004\u0003\u0004\u0016!\tA!\"\t\u0011\t%U\u0001)Q\u0005\u00037CqAa#\u0006\t\u0003\u0011i\tC\u0004\u0003\u0010\u0016!\tA!$\t\u000f\tEU\u0001\"\u0001\u0003\u0014\"9!qS\u0003\u0005\u0002\te\u0005\u0002\u0003BO\u000b\u0001\u0006K!a)\t\u000f\t}U\u0001\"\u0001\u0003\"\"9!1U\u0003\u0005\u0002\t\u0005\u0006b\u0002BS\u000b\u0011\u0005!q\u0015\u0005\b\u0005W+A\u0011\u0001BW\u0011!\u0011\t,\u0002Q!\n\u0005-\u0006b\u0002BZ\u000b\u0011\u0005!Q\u0017\u0005\b\u0005o+A\u0011\u0001B[\u0011\u001d\u0011I,\u0002C\u0001\u0005wCqAa0\u0006\t\u0003\u0011\t\r\u0003\u0005\u0003F\u0016\u0001\u000b\u0015BAZ\u0011\u001d\u00119-\u0002C\u0001\u0005\u0013DqAa3\u0006\t\u0003\u0011I\rC\u0004\u0003N\u0016!\tAa4\t\u000f\tMW\u0001\"\u0001\u0003V\"A!\u0011\\\u0003!B\u0013\tY\fC\u0004\u0003\\\u0016!\tA!8\t\u000f\t}W\u0001\"\u0001\u0003^\"9!\u0011]\u0003\u0005\u0002\t\r\bb\u0002Bt\u000b\u0011\u0005!\u0011\u001e\u0005\t\u0005[,\u0001\u0015)\u0003\u0002D\"9!q^\u0003\u0005\u0002\tE\bb\u0002Bz\u000b\u0011\u0005!\u0011\u001f\u0005\b\u0005k,A\u0011\u0001B|\u0011\u001d\u0011Y0\u0002C\u0001\u0005{D\u0001b!\u0001\u0006A\u0003&\u00111\u001a\u0005\b\u0007\u0007)A\u0011AB\u0003\u0011\u001d\u00199!\u0002C\u0001\u0007\u000bAqa!\u0003\u0006\t\u0003\u0019Y\u0001C\u0004\u0004\u0010\u0015!\ta!\u0005\t\u0011\rUQ\u0001)Q\u0005\u0003\'Dqaa\u0006\u0006\t\u0003\u0019I\u0002C\u0004\u0004\u001c\u0015!\ta!\u0007\t\u000f\ruQ\u0001\"\u0001\u0004 !911E\u0003\u0005\u0002\r\u0015\u0002\u0002CB\u0015\u000b\u0001\u0006K!a7\t\u000f\r-R\u0001\"\u0001\u0004.!91qF\u0003\u0005\u0002\r5\u0002bBB\u0019\u000b\u0011\u000511\u0007\u0005\b\u0007o)A\u0011AB\u001d\u0011!\u0019i$\u0002Q!\n\u0005\r\bbBB \u000b\u0011\u00051\u0011\t\u0005\b\u0007\u0007*A\u0011AB!\u0011\u001d\u0019)%\u0002C\u0001\u0007\u000fBqaa\u0013\u0006\t\u0003\u0019i\u0005\u0003\u0005\u0004R\u0015\u0001\u000b\u0015BAv\u0011\u001d\u0019\u0019&\u0002C\u0001\u0007+Bqaa\u0016\u0006\t\u0003\u0019)\u0006C\u0004\u0004Z\u0015!\taa\u0017\t\u000f\r}S\u0001\"\u0001\u0004b!A1QM\u0003!B\u0013\t\u0019\u0010C\u0004\u0004h\u0015!\ta!\u001b\t\u000f\r-T\u0001\"\u0001\u0004j!91QN\u0003\u0005\u0002\r=\u0004bBB:\u000b\u0011\u00051Q\u000f\u0005\t\u0007s*\u0001\u0015)\u0003\u0002|\"911P\u0003\u0005\u0002\ru\u0004bBB@\u000b\u0011\u00051Q\u0010\u0005\b\u0007\u0003+A\u0011ABB\u0011\u001d\u00199)\u0002C\u0001\u0007\u0013C\u0001b!$\u0006A\u0003&!1\u0001\u0005\b\u0007\u001f+A\u0011ABI\u0011\u001d\u0019\u0019*\u0002C\u0001\u0007#Cqa!&\u0006\t\u0003\u00199\nC\u0004\u0004\u001c\u0016!\ta!(\t\u0011\r\u0005V\u0001)Q\u0005\u0005\u0017Aqaa)\u0006\t\u0003\u0019)\u000bC\u0004\u0004(\u0016!\ta!*\t\u000f\r%V\u0001\"\u0001\u0004,\"91qV\u0003\u0005\u0002\rE\u0006\u0002CB[\u000b\u0001\u0006KAa\u0005\t\u000f\r]V\u0001\"\u0001\u0004:\"911X\u0003\u0005\u0002\re\u0006bBB_\u000b\u0011\u00051q\u0018\u0005\b\u0007\u0007,A\u0011ABc\u0011!\u0019I-\u0002Q!\n\tm\u0001bBBf\u000b\u0011\u00051Q\u001a\u0005\b\u0007\u001f,A\u0011ABg\u0011\u001d\u0019\t.\u0002C\u0001\u0007\'Dqaa6\u0006\t\u0003\u0019I\u000e\u0003\u0005\u0004^\u0016\u0001\u000b\u0015\u0002B\u0012\u0011\u001d\u0019y.\u0002C\u0001\u0007CDqaa9\u0006\t\u0003\u0019\t\u000fC\u0004\u0004f\u0016!\taa:\t\u000f\r-X\u0001\"\u0001\u0004n\"A1\u0011_\u0003!B\u0013\u0011Y\u0003C\u0004\u0004t\u0016!\ta!>\t\u000f\r]X\u0001\"\u0001\u0004v\"91\u0011`\u0003\u0005\u0002\rm\bbBB\u0000\u000b\u0011\u0005A\u0011\u0001\u0005\b\t\u000b)A\u0011\tC\u0004\u0011\u001d!I\"\u0002C!\t7Aq\u0001\"\t\u0006\t\u0003\"\u0019\u0003C\u0004\u0005,\u0015!\t\u0005\"\f\t\u000f\u0005\u001dT\u0001\"\u0001\u0005:!IAQM\u0003\u0012\u0002\u0013\u0005Aq\r\u0005\n\t{*\u0011\u0013!C\u0001\t\u007fB\u0011\u0002b!\u0006#\u0003%\t\u0001\"\"\t\u0013\u0011%U!%A\u0005\u0002\u0011-\u0005\"\u0003CH\u000bE\u0005I\u0011\u0001CI\u0011%!)*BI\u0001\n\u0003!9\nC\u0005\u0005\u001c\u0016\t\n\u0011\"\u0001\u0005\u001e\"IA\u0011U\u0003\u0012\u0002\u0013\u0005A1\u0015\u0005\n\tO+\u0011\u0013!C\u0001\tSC\u0011\u0002\",\u0006#\u0003%\t\u0001b,\t\u0013\u0011MV!%A\u0005\u0002\u0011U\u0006\"\u0003C]\u000bE\u0005I\u0011\u0001C^\u0011%!y,BI\u0001\n\u0003!\t\rC\u0005\u0005F\u0016\t\n\u0011\"\u0001\u0005H\"IA1Z\u0003\u0012\u0002\u0013\u0005AQ\u001a\u0005\n\t#,\u0011\u0013!C\u0001\t\'D\u0011\u0002b6\u0006#\u0003%\t\u0001\"7\t\u0013\u0011uW!%A\u0005\u0002\u0011}\u0007\"\u0003Cr\u000bE\u0005I\u0011\u0001Cs\u0011%!I/BI\u0001\n\u0003!Y\u000fC\u0005\u0005p\u0016\t\n\u0011\"\u0001\u0005r\"9AQ_\u0003\u0005B\u0011]\bbBC\f\u000b\u0011\u0005S\u0011D\u0001\u0007\u001b\n{\u0007PM\u0019\u000b\t\u0005\u001d\u0013\u0011J\u0001\u0007g&\u0014X-^7\u000b\u0005\u0005-\u0013aA8sO\u000e\u0001\u0001cAA)\u00035\u0011\u0011Q\t\u0002\u0007\u001b\n{\u0007PM\u0019\u0014\u0007\u0005\t9\u0006\u0005\u0003\u0002Z\u0005}SBAA.\u0015\t\ti&A\u0003tG\u0006d\u0017-\u0003\u0003\u0002b\u0005m#AB!osJ+g-\u0001\u0004=S:LGO\u0010\u000b\u0003\u0003\u001f\nQ!\u00199qYf,B&a\u001b\u0006&\u0015%RQFC\u0019\u000bk)I$\"\u0010\u0006B\u0015\u0015S\u0011JC\'\u000b#*)&\"\u0017\u0006^\u0015\u0005TQMC5\u000b[*\t(\"\u001e\u0015Y\u00055TqOC=\u000bw*i(b \u0006\u0002\u0016\rUQQCD\u000b\u0013+Y)\"$\u0006\u0010\u0016EU1SCK\u000b/+I*b\'\u0006\u001e\u0016}\u0005#LA)\u000b\u0015\rRqEC\u0016\u000b_)\u0019$b\u000e\u0006<\u0015}R1IC$\u000b\u0017*y%b\u0015\u0006X\u0015mSqLC2\u000bO*Y\'b\u001c\u0006tUa\u0013\u0011OA@\u0003+\u000bi*!*\u0002.\u0006U\u0016QXAc\u0003\u001b\f).!8\u0002f\u00065\u0018Q_A\u007f\u0005\u000b\u0011iA!\u0006\u0003\u001e\t\u0015\"QF\n\u0006\u000b\u0005]\u00131\u000f\t\u0005\u0003#\n)(\u0003\u0003\u0002x\u0005\u0015#!\u0003*fG>\u0014HmU5h\u0003!yvL^1mk\u0016\f\u0004\u0003BA?\u0003\u007fb\u0001\u0001B\u0004\u0002\u0002\u0016\u0011\r!a!\u0003\u0005Q\u000b\u0014\u0003BAC\u0003\u0017\u0003B!!\u0017\u0002\b&!\u0011\u0011RA.\u0005\u001dqu\u000e\u001e5j]\u001e\u0004B!!\u0017\u0002\u000e&!\u0011qRA.\u0005\r\te._\u0001\t?~3\u0018\r\\;feA!\u0011QPAK\t\u001d\t9*\u0002b\u0001\u0003\u0007\u0013!\u0001\u0016\u001a\u0002\u0011}{f/\u00197vKN\u0002B!! \u0002\u001e\u00129\u0011qT\u0003C\u0002\u0005\r%A\u0001+4\u0003!yvL^1mk\u0016$\u0004\u0003BA?\u0003K#q!a*\u0006\u0005\u0004\t\u0019I\u0001\u0002Ui\u0005Aql\u0018<bYV,W\u0007\u0005\u0003\u0002~\u00055FaBAX\u000b\t\u0007\u00111\u0011\u0002\u0003)V\n\u0001bX0wC2,XM\u000e\t\u0005\u0003{\n)\fB\u0004\u00028\u0016\u0011\r!a!\u0003\u0005Q3\u0014\u0001C0`m\u0006dW/Z\u001c\u0011\t\u0005u\u0014Q\u0018\u0003\b\u0003\u007f+!\u0019AAB\u0005\t!v\'\u0001\u0005`?Z\fG.^39!\u0011\ti(!2\u0005\u000f\u0005\u001dWA1\u0001\u0002\u0004\n\u0011A\u000bO\u0001\t?~3\u0018\r\\;fsA!\u0011QPAg\t\u001d\ty-\u0002b\u0001\u0003\u0007\u0013!\u0001V\u001d\u0002\u0013}{f/\u00197vKF\u0002\u0004\u0003BA?\u0003+$q!a6\u0006\u0005\u0004\t\u0019IA\u0002UcA\n\u0011bX0wC2,X-M\u0019\u0011\t\u0005u\u0014Q\u001c\u0003\b\u0003?,!\u0019AAB\u0005\r!\u0016\'M\u0001\n?~3\u0018\r\\;fcI\u0002B!! \u0002f\u00129\u0011q]\u0003C\u0002\u0005\r%a\u0001+2e\u0005Iql\u0018<bYV,\u0017g\r\t\u0005\u0003{\ni\u000fB\u0004\u0002p\u0016\u0011\r!a!\u0003\u0007Q\u000b4\'A\u0005`?Z\fG.^32iA!\u0011QPA{\t\u001d\t90\u0002b\u0001\u0003\u0007\u00131\u0001V\u00195\u0003%yvL^1mk\u0016\fT\u0007\u0005\u0003\u0002~\u0005uHaBA\u0000\u000b\t\u0007\u00111\u0011\u0002\u0004)F*\u0014!C0`m\u0006dW/Z\u00197!\u0011\tiH!\u0002\u0005\u000f\t\u001dQA1\u0001\u0002\u0004\n\u0019A+\r\u001c\u0002\u0013}{f/\u00197vKF:\u0004\u0003BA?\u0005\u001b!qAa\u0004\u0006\u0005\u0004\t\u0019IA\u0002Uc]\n\u0011bX0wC2,X-\r\u001d\u0011\t\u0005u$Q\u0003\u0003\b\u0005/)!\u0019AAB\u0005\r!\u0016\u0007O\u0001\n?~3\u0018\r\\;fce\u0002B!! \u0003\u001e\u00119!qD\u0003C\u0002\u0005\r%a\u0001+2s\u0005Iql\u0018<bYV,\'\u0007\r\t\u0005\u0003{\u0012)\u0003B\u0004\u0003(\u0015\u0011\r!a!\u0003\u0007Q\u0013\u0004\'A\u0005`?Z\fG.^33cA!\u0011Q\u0010B\u0017\t\u001d\u0011y#\u0002b\u0001\u0003\u0007\u00131\u0001\u0016\u001a2)1\u0012\u0019D!\u000e\u00038\te\"1\bB\u001f\u0005\u007f\u0011\tEa\u0011\u0003F\t\u001d#\u0011\nB&\u0005\u001b\u0012yE!\u0015\u0003T\tU#q\u000bB-\u00057\u0012i\u0006E\u0017\u0002R\u0015\tY(a%\u0002\u001c\u0006\r\u00161VAZ\u0003w\u000b\u0019-a3\u0002T\u0006m\u00171]Av\u0003g\fYPa\u0001\u0003\f\tM!1\u0004B\u0012\u0005WAq!!\u001f\u001c\u0001\u0004\tY\bC\u0004\u0002\u0012n\u0001\r!a%\t\u000f\u0005e5\u00041\u0001\u0002\u001c\"9\u0011\u0011U\u000eA\u0002\u0005\r\u0006bBAU7\u0001\u0007\u00111\u0016\u0005\b\u0003c[\u0002\u0019AAZ\u0011\u001d\tIl\u0007a\u0001\u0003wCq!!1\u001c\u0001\u0004\t\u0019\rC\u0004\u0002Jn\u0001\r!a3\t\u000f\u0005E7\u00041\u0001\u0002T\"9\u0011\u0011\\\u000eA\u0002\u0005m\u0007bBAq7\u0001\u0007\u00111\u001d\u0005\b\u0003S\\\u0002\u0019AAv\u0011\u001d\t\tp\u0007a\u0001\u0003gDq!!?\u001c\u0001\u0004\tY\u0010C\u0004\u0003\u0002m\u0001\rAa\u0001\t\u000f\t%1\u00041\u0001\u0003\f!9!\u0011C\u000eA\u0002\tM\u0001b\u0002B\r7\u0001\u0007!1\u0004\u0005\b\u0005CY\u0002\u0019\u0001B\u0012\u0011\u001d\u0011Ic\u0007a\u0001\u0005W\tqa\u0018<bYV,\u0017\'\u0001\u0004wC2,X-M\u000b\u0003\u0003w\n\u0011bZ3u-\u0006dW/Z\u0019\u0002\u0015Y\fG.^32?\u0012*\u0017\u000f\u0006\u0003\u0003l\t5T\"A\u0003\t\u000f\t\u0005t\u00041\u0001\u0002|\u0005I1/\u001a;WC2,X-\r\u000b\u0005\u0005W\u0012\u0019\bC\u0004\u0003b\u0001\u0002\r!a\u001f\u0002\u000f}3\u0018\r\\;fe\u00051a/\u00197vKJ*\"!a%\u0002\u0013\u001d,GOV1mk\u0016\u0014\u0014A\u0003<bYV,\'g\u0018\u0013fcR!!1\u000eBA\u0011\u001d\u00119\b\na\u0001\u0003\'\u000b\u0011b]3u-\u0006dW/\u001a\u001a\u0015\t\t-$q\u0011\u0005\b\u0005o*\u0003\u0019AAJ\u0003\u001dyf/\u00197vKN\naA^1mk\u0016\u001cTCAAN\u0003%9W\r\u001e,bYV,7\'\u0001\u0006wC2,XmM0%KF$BAa\u001b\u0003\u0016\"9!1R\u0015A\u0002\u0005m\u0015!C:fiZ\u000bG.^34)\u0011\u0011YGa\'\t\u000f\t-%\u00061\u0001\u0002\u001c\u00069qL^1mk\u0016$\u0014A\u0002<bYV,G\'\u0006\u0002\u0002$\u0006Iq-\u001a;WC2,X\rN\u0001\u000bm\u0006dW/\u001a\u001b`I\u0015\fH\u0003\u0002B6\u0005SCqAa(/\u0001\u0004\t\u0019+A\u0005tKR4\u0016\r\\;fiQ!!1\u000eBX\u0011\u001d\u0011yj\fa\u0001\u0003G\u000bqa\u0018<bYV,W\'\u0001\u0004wC2,X-N\u000b\u0003\u0003W\u000b\u0011bZ3u-\u0006dW/Z\u001b\u0002\u0015Y\fG.^36?\u0012*\u0017\u000f\u0006\u0003\u0003l\tu\u0006b\u0002BZg\u0001\u0007\u00111V\u0001\ng\u0016$h+\u00197vKV\"BAa\u001b\u0003D\"9!1\u0017\u001bA\u0002\u0005-\u0016aB0wC2,XMN\u0001\u0007m\u0006dW/\u001a\u001c\u0016\u0005\u0005M\u0016!C4fiZ\u000bG.^37\u0003)1\u0018\r\\;fm}#S-\u001d\u000b\u0005\u0005W\u0012\t\u000eC\u0004\u0003Hb\u0002\r!a-\u0002\u0013M,GOV1mk\u00164D\u0003\u0002B6\u0005/DqAa2:\u0001\u0004\t\u0019,A\u0004`m\u0006dW/Z\u001c\u0002\rY\fG.^38+\t\tY,A\u0005hKR4\u0016\r\\;fo\u0005Qa/\u00197vK^zF%Z9\u0015\t\t-$Q\u001d\u0005\b\u00057l\u0004\u0019AA^\u0003%\u0019X\r\u001e,bYV,w\u0007\u0006\u0003\u0003l\t-\bb\u0002Bn}\u0001\u0007\u00111X\u0001\b?Z\fG.^39\u0003\u00191\u0018\r\\;fqU\u0011\u00111Y\u0001\nO\u0016$h+\u00197vKb\n!B^1mk\u0016Dt\fJ3r)\u0011\u0011YG!?\t\u000f\t=(\t1\u0001\u0002D\u0006I1/\u001a;WC2,X\r\u000f\u000b\u0005\u0005W\u0012y\u0010C\u0004\u0003p\u000e\u0003\r!a1\u0002\u000f}3\u0018\r\\;fs\u00051a/\u00197vKf*\"!a3\u0002\u0013\u001d,GOV1mk\u0016L\u0014A\u0003<bYV,\u0017h\u0018\u0013fcR!!1NB\u0007\u0011\u001d\u0019\u0019a\u0012a\u0001\u0003\u0017\f\u0011b]3u-\u0006dW/Z\u001d\u0015\t\t-41\u0003\u0005\b\u0007\u0007A\u0005\u0019AAf\u0003!yf/\u00197vKF\u0002\u0014a\u0002<bYV,\u0017\u0007M\u000b\u0003\u0003\'\f!bZ3u-\u0006dW/Z\u00191\u0003-1\u0018\r\\;fcAzF%Z9\u0015\t\t-4\u0011\u0005\u0005\b\u0007/a\u0005\u0019AAj\u0003)\u0019X\r\u001e,bYV,\u0017\u0007\r\u000b\u0005\u0005W\u001a9\u0003C\u0004\u0004\u00185\u0003\r!a5\u0002\u0011}3\u0018\r\\;fcE\nqA^1mk\u0016\f\u0014\'\u0006\u0002\u0002\\\u0006Qq-\u001a;WC2,X-M\u0019\u0002\u0017Y\fG.^32c}#S-\u001d\u000b\u0005\u0005W\u001a)\u0004C\u0004\u0004,E\u0003\r!a7\u0002\u0015M,GOV1mk\u0016\f\u0014\u0007\u0006\u0003\u0003l\rm\u0002bBB\u0016%\u0002\u0007\u00111\\\u0001\t?Z\fG.^32e\u00059a/\u00197vKF\u0012TCAAr\u0003)9W\r\u001e,bYV,\u0017GM\u0001\fm\u0006dW/Z\u00193?\u0012*\u0017\u000f\u0006\u0003\u0003l\r%\u0003bBB -\u0002\u0007\u00111]\u0001\u000bg\u0016$h+\u00197vKF\u0012D\u0003\u0002B6\u0007\u001fBqaa\u0010X\u0001\u0004\t\u0019/\u0001\u0005`m\u0006dW/Z\u00194\u0003\u001d1\u0018\r\\;fcM*\"!a;\u0002\u0015\u001d,GOV1mk\u0016\f4\'A\u0006wC2,X-M\u001a`I\u0015\fH\u0003\u0002B6\u0007;Bqaa\u0015\\\u0001\u0004\tY/\u0001\u0006tKR4\u0016\r\\;fcM\"BAa\u001b\u0004d!911\u000b/A\u0002\u0005-\u0018\u0001C0wC2,X-\r\u001b\u0002\u000fY\fG.^32iU\u0011\u00111_\u0001\u000bO\u0016$h+\u00197vKF\"\u0014a\u0003<bYV,\u0017\u0007N0%KF$BAa\u001b\u0004r!91q\r1A\u0002\u0005M\u0018AC:fiZ\u000bG.^32iQ!!1NB<\u0011\u001d\u00199\'\u0019a\u0001\u0003g\f\u0001b\u0018<bYV,\u0017\'N\u0001\bm\u0006dW/Z\u00196+\t\tY0\u0001\u0006hKR4\u0016\r\\;fcU\n1B^1mk\u0016\fTg\u0018\u0013fcR!!1NBC\u0011\u001d\u0019Y(\u001aa\u0001\u0003w\f!b]3u-\u0006dW/Z\u00196)\u0011\u0011Yga#\t\u000f\rmd\r1\u0001\u0002|\u0006AqL^1mk\u0016\fd\'A\u0004wC2,X-\r\u001c\u0016\u0005\t\r\u0011AC4fiZ\u000bG.^32m\u0005Ya/\u00197vKF2t\fJ3r)\u0011\u0011Yg!\'\t\u000f\r=%\u000e1\u0001\u0003\u0004\u0005Q1/\u001a;WC2,X-\r\u001c\u0015\t\t-4q\u0014\u0005\b\u0007\u001f[\u0007\u0019\u0001B\u0002\u0003!yf/\u00197vKF:\u0014a\u0002<bYV,\u0017gN\u000b\u0003\u0005\u0017\t!bZ3u-\u0006dW/Z\u00198\u0003-1\u0018\r\\;fc]zF%Z9\u0015\t\t-4Q\u0016\u0005\b\u0007G{\u0007\u0019\u0001B\u0006\u0003)\u0019X\r\u001e,bYV,\u0017g\u000e\u000b\u0005\u0005W\u001a\u0019\fC\u0004\u0004$B\u0004\rAa\u0003\u0002\u0011}3\u0018\r\\;fca\nqA^1mk\u0016\f\u0004(\u0006\u0002\u0003\u0014\u0005Qq-\u001a;WC2,X-\r\u001d\u0002\u0017Y\fG.^32q}#S-\u001d\u000b\u0005\u0005W\u001a\t\rC\u0004\u00048R\u0004\rAa\u0005\u0002\u0015M,GOV1mk\u0016\f\u0004\b\u0006\u0003\u0003l\r\u001d\u0007bBB\\k\u0002\u0007!1C\u0001\t?Z\fG.^32s\u00059a/\u00197vKFJTC\u0001B\u000e\u0003)9W\r\u001e,bYV,\u0017\'O\u0001\fm\u0006dW/Z\u0019:?\u0012*\u0017\u000f\u0006\u0003\u0003l\rU\u0007bBBfs\u0002\u0007!1D\u0001\u000bg\u0016$h+\u00197vKFJD\u0003\u0002B6\u00077Dqaa3{\u0001\u0004\u0011Y\"\u0001\u0005`m\u0006dW/\u001a\u001a1\u0003\u001d1\u0018\r\\;feA*\"Aa\t\u0002\u0015\u001d,GOV1mk\u0016\u0014\u0004\'A\u0006wC2,XM\r\u0019`I\u0015\fH\u0003\u0002B6\u0007SDqaa8\u007f\u0001\u0004\u0011\u0019#\u0001\u0006tKR4\u0016\r\\;feA\"BAa\u001b\u0004p\"91q\\@A\u0002\t\r\u0012\u0001C0wC2,XMM\u0019\u0002\u000fY\fG.^33cU\u0011!1F\u0001\u000bO\u0016$h+\u00197vKJ\n\u0014a\u0003<bYV,\'\'M0%KF$BAa\u001b\u0004~\"A11_A\u0004\u0001\u0004\u0011Y#\u0001\u0006tKR4\u0016\r\\;feE\"BAa\u001b\u0005\u0004!A11_A\u0005\u0001\u0004\u0011Y#\u0001\u0005u_N#(/\u001b8h)\t!I\u0001\u0005\u0003\u0005\f\u0011UQB\u0001C\u0007\u0015\u0011!y\u0001\"\u0005\u0002\t1\fgn\u001a\u0006\u0003\t\'\tAA[1wC&!Aq\u0003C\u0007\u0005\u0019\u0019FO]5oO\u000611\u000f\u001e:j]\u001e,\"\u0001\"\b\u0011\t\u0005ECqD\u0005\u0005\t/\t)%\u0001\u0005iCND7i\u001c3f)\t!)\u0003\u0005\u0003\u0002Z\u0011\u001d\u0012\u0002\u0002C\u0015\u00037\u00121!\u00138u\u0003\u0019)\u0017/^1mgR!Aq\u0006C\u001b!\u0011\tI\u0006\"\r\n\t\u0011M\u00121\f\u0002\b\u0005>|G.Z1o\u0011!!9$!\u0005A\u0002\u0005-\u0015!A8\u0015Y\tMB1\bC\u001f\t\u007f!\t\u0005b\u0011\u0005F\u0011\u001dC\u0011\nC&\t\u001b\"y\u0005\"\u0015\u0005T\u0011UCq\u000bC-\t7\"i\u0006b\u0018\u0005b\u0011\r\u0004B\u0003B1\u0003\'\u0001\n\u00111\u0001\u0002|!Q!qOA\n!\u0003\u0005\r!a%\t\u0015\t-\u00151\u0003I\u0001\u0002\u0004\tY\n\u0003\u0006\u0003 \u0006M\u0001\u0013!a\u0001\u0003GC!Ba-\u0002\u0014A\u0005\t\u0019AAV\u0011)\u00119-a\u0005\u0011\u0002\u0003\u0007\u00111\u0017\u0005\u000b\u00057\f\u0019\u0002%AA\u0002\u0005m\u0006B\u0003Bx\u0003\'\u0001\n\u00111\u0001\u0002D\"Q11AA\n!\u0003\u0005\r!a3\t\u0015\r]\u00111\u0003I\u0001\u0002\u0004\t\u0019\u000e\u0003\u0006\u0004,\u0005M\u0001\u0013!a\u0001\u00037D!ba\u0010\u0002\u0014A\u0005\t\u0019AAr\u0011)\u0019\u0019&a\u0005\u0011\u0002\u0003\u0007\u00111\u001e\u0005\u000b\u0007O\n\u0019\u0002%AA\u0002\u0005M\bBCB>\u0003\'\u0001\n\u00111\u0001\u0002|\"Q1qRA\n!\u0003\u0005\rAa\u0001\t\u0015\r\r\u00161\u0003I\u0001\u0002\u0004\u0011Y\u0001\u0003\u0006\u00048\u0006M\u0001\u0013!a\u0001\u0005\'A!ba3\u0002\u0014A\u0005\t\u0019\u0001B\u000e\u0011)\u0019y.a\u0005\u0011\u0002\u0003\u0007!1\u0005\u0005\u000b\u0007g\f\u0019\u0002%AA\u0002\t-\u0012aD1qa2LH\u0005Z3gCVdG\u000fJ\u0019\u0016\u0005\u0011%$\u0006BA>\tWZ#\u0001\"\u001c\u0011\t\u0011=D\u0011P\u0007\u0003\tcRA\u0001b\u001d\u0005v\u0005IQO\\2iK\u000e\\W\r\u001a\u0006\u0005\to\nY&\u0001\u0006b]:|G/\u0019;j_:LA\u0001b\u001f\u0005r\t\tRO\\2iK\u000e\\W\r\u001a,be&\fgnY3\u0002\u001f\u0005\u0004\b\u000f\\=%I\u00164\u0017-\u001e7uII*\"\u0001\"!+\t\u0005ME1N\u0001\u0010CB\u0004H.\u001f\u0013eK\u001a\fW\u000f\u001c;%gU\u0011Aq\u0011\u0016\u0005\u00037#Y\'A\bbaBd\u0017\u0010\n3fM\u0006,H\u000e\u001e\u00135+\t!iI\u000b\u0003\u0002$\u0012-\u0014aD1qa2LH\u0005Z3gCVdG\u000fJ\u001b\u0016\u0005\u0011M%\u0006BAV\tW\nq\"\u00199qYf$C-\u001a4bk2$HEN\u000b\u0003\t3SC!a-\u0005l\u0005y\u0011\r\u001d9ms\u0012\"WMZ1vYR$s\'\u0006\u0002\u0005 *\"\u00111\u0018C6\u0003=\t\u0007\u000f\u001d7zI\u0011,g-Y;mi\u0012BTC\u0001CSU\u0011\t\u0019\rb\u001b\u0002\u001f\u0005\u0004\b\u000f\\=%I\u00164\u0017-\u001e7uIe*\"\u0001b++\t\u0005-G1N\u0001\u0011CB\u0004H.\u001f\u0013eK\u001a\fW\u000f\u001c;%cA*\"\u0001\"-+\t\u0005MG1N\u0001\u0011CB\u0004H.\u001f\u0013eK\u001a\fW\u000f\u001c;%cE*\"\u0001b.+\t\u0005mG1N\u0001\u0011CB\u0004H.\u001f\u0013eK\u001a\fW\u000f\u001c;%cI*\"\u0001\"0+\t\u0005\rH1N\u0001\u0011CB\u0004H.\u001f\u0013eK\u001a\fW\u000f\u001c;%cM*\"\u0001b1+\t\u0005-H1N\u0001\u0011CB\u0004H.\u001f\u0013eK\u001a\fW\u000f\u001c;%cQ*\"\u0001\"3+\t\u0005MH1N\u0001\u0011CB\u0004H.\u001f\u0013eK\u001a\fW\u000f\u001c;%cU*\"\u0001b4+\t\u0005mH1N\u0001\u0011CB\u0004H.\u001f\u0013eK\u001a\fW\u000f\u001c;%cY*\"\u0001\"6+\t\t\rA1N\u0001\u0011CB\u0004H.\u001f\u0013eK\u001a\fW\u000f\u001c;%c]*\"\u0001b7+\t\t-A1N\u0001\u0011CB\u0004H.\u001f\u0013eK\u001a\fW\u000f\u001c;%ca*\"\u0001\"9+\t\tMA1N\u0001\u0011CB\u0004H.\u001f\u0013eK\u001a\fW\u000f\u001c;%ce*\"\u0001b:+\t\tmA1N\u0001\u0011CB\u0004H.\u001f\u0013eK\u001a\fW\u000f\u001c;%eA*\"\u0001\"<+\t\t\rB1N\u0001\u0011CB\u0004H.\u001f\u0013eK\u001a\fW\u000f\u001c;%eE*\"\u0001b=+\t\t-B1N\u0001\tI\r|g\u000e^3oiV\u0011A\u0011 \t\u0007\tw,Y!\"\u0005\u000f\t\u0011uXq\u0001\b\u0005\t\u007f,)!\u0004\u0002\u0006\u0002)!Q1AA\'\u0003\u0019a$o\\8u}%\u0011\u0011QL\u0005\u0005\u000b\u0013\tY&A\u0004qC\u000e\\\u0017mZ3\n\t\u00155Qq\u0002\u0002\u0004\'\u0016\f(\u0002BC\u0005\u00037\u0002\u0002\"!\u0017\u0006\u0014\u0011%\u00111R\u0005\u0005\u000b+\tYF\u0001\u0004UkBdWMM\u0001\u0007I\rdwN\\3\u0016\u0005\tM\u0002fA\u0003\u0006\u001eA!\u0011\u0011KC\u0010\u0013\u0011)\t#!\u0012\u0003\rI,7m\u001c:e!\u0011\ti(\"\n\u0005\u000f\u0005\u00055A1\u0001\u0002\u0004B!\u0011QPC\u0015\t\u001d\t9j\u0001b\u0001\u0003\u0007\u0003B!! \u0006.\u00119\u0011qT\u0002C\u0002\u0005\r\u0005\u0003BA?\u000bc!q!a*\u0004\u0005\u0004\t\u0019\t\u0005\u0003\u0002~\u0015UBaBAX\u0007\t\u0007\u00111\u0011\t\u0005\u0003{*I\u0004B\u0004\u00028\u000e\u0011\r!a!\u0011\t\u0005uTQ\b\u0003\b\u0003\u007f\u001b!\u0019AAB!\u0011\ti(\"\u0011\u0005\u000f\u0005\u001d7A1\u0001\u0002\u0004B!\u0011QPC#\t\u001d\tym\u0001b\u0001\u0003\u0007\u0003B!! \u0006J\u00119\u0011q[\u0002C\u0002\u0005\r\u0005\u0003BA?\u000b\u001b\"q!a8\u0004\u0005\u0004\t\u0019\t\u0005\u0003\u0002~\u0015ECaBAt\u0007\t\u0007\u00111\u0011\t\u0005\u0003{*)\u0006B\u0004\u0002p\u000e\u0011\r!a!\u0011\t\u0005uT\u0011\f\u0003\b\u0003o\u001c!\u0019AAB!\u0011\ti(\"\u0018\u0005\u000f\u0005}8A1\u0001\u0002\u0004B!\u0011QPC1\t\u001d\u00119a\u0001b\u0001\u0003\u0007\u0003B!! \u0006f\u00119!qB\u0002C\u0002\u0005\r\u0005\u0003BA?\u000bS\"qAa\u0006\u0004\u0005\u0004\t\u0019\t\u0005\u0003\u0002~\u00155Da\u0002B\u0010\u0007\t\u0007\u00111\u0011\t\u0005\u0003{*\t\bB\u0004\u0003(\r\u0011\r!a!\u0011\t\u0005uTQ\u000f\u0003\b\u0005_\u0019!\u0019AAB\u0011\u001d\u0011\tg\u0001a\u0001\u000bGAqAa\u001e\u0004\u0001\u0004)9\u0003C\u0004\u0003\f\u000e\u0001\r!b\u000b\t\u000f\t}5\u00011\u0001\u00060!9!1W\u0002A\u0002\u0015M\u0002b\u0002Bd\u0007\u0001\u0007Qq\u0007\u0005\b\u00057\u001c\u0001\u0019AC\u001e\u0011\u001d\u0011yo\u0001a\u0001\u000b\u007fAqaa\u0001\u0004\u0001\u0004)\u0019\u0005C\u0004\u0004\u0018\r\u0001\r!b\u0012\t\u000f\r-2\u00011\u0001\u0006L!91qH\u0002A\u0002\u0015=\u0003bBB*\u0007\u0001\u0007Q1\u000b\u0005\b\u0007O\u001a\u0001\u0019AC,\u0011\u001d\u0019Yh\u0001a\u0001\u000b7Bqaa$\u0004\u0001\u0004)y\u0006C\u0004\u0004$\u000e\u0001\r!b\u0019\t\u000f\r]6\u00011\u0001\u0006h!911Z\u0002A\u0002\u0015-\u0004bBBp\u0007\u0001\u0007Qq\u000e\u0005\b\u0007g\u001c\u0001\u0019AC:\u0003\u001d)h.\u00199qYf,B&\"*\u00066\u0016eVQXCa\u000b\u000b,I-\"4\u0006R\u0016UW\u0011\\Co\u000bC,)/\";\u0006n\u0016EXQ_C}\u000b{4\tA\"\u0002\u0015\t\u0015\u001dfq\u0001\t\u0007\u00033*I+\",\n\t\u0015-\u00161\f\u0002\u0005\'>lW\r\u0005\u0018\u0002Z\u0015=V1WC\\\u000bw+y,b1\u0006H\u0016-WqZCj\u000b/,Y.b8\u0006d\u0016\u001dX1^Cx\u000bg,90b?\u0006\u0000\u001a\r\u0011\u0002BCY\u00037\u0012q\u0001V;qY\u0016\u0014\u0014\u0007\u0005\u0003\u0002~\u0015UFaBAA\t\t\u0007\u00111\u0011\t\u0005\u0003{*I\fB\u0004\u0002\u0018\u0012\u0011\r!a!\u0011\t\u0005uTQ\u0018\u0003\b\u0003?#!\u0019AAB!\u0011\ti(\"1\u0005\u000f\u0005\u001dFA1\u0001\u0002\u0004B!\u0011QPCc\t\u001d\ty\u000b\u0002b\u0001\u0003\u0007\u0003B!! \u0006J\u00129\u0011q\u0017\u0003C\u0002\u0005\r\u0005\u0003BA?\u000b\u001b$q!a0\u0005\u0005\u0004\t\u0019\t\u0005\u0003\u0002~\u0015EGaBAd\t\t\u0007\u00111\u0011\t\u0005\u0003{*)\u000eB\u0004\u0002P\u0012\u0011\r!a!\u0011\t\u0005uT\u0011\u001c\u0003\b\u0003/$!\u0019AAB!\u0011\ti(\"8\u0005\u000f\u0005}GA1\u0001\u0002\u0004B!\u0011QPCq\t\u001d\t9\u000f\u0002b\u0001\u0003\u0007\u0003B!! \u0006f\u00129\u0011q\u001e\u0003C\u0002\u0005\r\u0005\u0003BA?\u000bS$q!a>\u0005\u0005\u0004\t\u0019\t\u0005\u0003\u0002~\u00155HaBA\u0000\t\t\u0007\u00111\u0011\t\u0005\u0003{*\t\u0010B\u0004\u0003\b\u0011\u0011\r!a!\u0011\t\u0005uTQ\u001f\u0003\b\u0005\u001f!!\u0019AAB!\u0011\ti(\"?\u0005\u000f\t]AA1\u0001\u0002\u0004B!\u0011QPC\u007f\t\u001d\u0011y\u0002\u0002b\u0001\u0003\u0007\u0003B!! \u0007\u0002\u00119!q\u0005\u0003C\u0002\u0005\r\u0005\u0003BA?\r\u000b!qAa\f\u0005\u0005\u0004\t\u0019\tC\u0004\u00058\u0011\u0001\rA\"\u0003\u0011[\u0005ES!b-\u00068\u0016mVqXCb\u000b\u000f,Y-b4\u0006T\u0016]W1\\Cp\u000bG,9/b;\u0006p\u0016MXq_C~\u000b\u007f4\u0019\u0001"
    )
  ScalaInlineInfo: length = 0x270 (unknown attribute)
   01 01 00 7C 00 5A 00 5B 01 01 F3 00 71 01 01 F3
   02 05 01 01 F3 01 F4 01 01 BF 01 C0 01 00 62 00
   47 01 00 67 00 47 01 00 46 00 47 01 00 4D 02 00
   01 00 4D 00 4E 01 01 24 01 A7 01 01 6E 01 A5 01
   01 AA 00 71 01 01 B3 00 71 01 01 B4 00 71 01 01
   B5 00 71 01 01 B6 00 71 01 01 B7 00 71 01 01 B8
   00 71 01 01 B9 00 71 01 01 BA 00 71 01 01 BB 00
   71 01 01 BC 00 71 01 01 AB 00 71 01 01 BD 00 71
   01 01 BE 00 71 01 01 AC 00 71 01 01 AD 00 71 01
   01 AE 00 71 01 01 AF 00 71 01 01 B0 00 71 01 01
   B1 00 71 01 01 B2 00 71 01 01 9B 01 9C 01 00 75
   00 71 01 00 BE 00 71 01 00 C6 00 71 01 00 CE 00
   71 01 00 D6 00 71 01 00 DE 00 71 01 00 E6 00 71
   01 00 EE 00 71 01 00 F6 00 71 01 00 FE 00 71 01
   01 06 00 71 01 00 7E 00 71 01 01 0E 00 71 01 01
   16 00 71 01 00 86 00 71 01 00 8E 00 71 01 00 96
   00 71 01 00 9E 00 71 01 00 A6 00 71 01 00 AE 00
   71 01 00 B6 00 71 01 00 54 00 55 01 01 72 01 73
   01 00 37 00 47 01 00 6D 00 6E 01 00 79 00 77 01
   00 C1 00 77 01 00 C9 00 77 01 00 D1 00 77 01 00
   D9 00 77 01 00 E1 00 77 01 00 E9 00 77 01 00 F1
   00 77 01 00 F9 00 77 01 01 01 00 77 01 01 09 00
   77 01 00 81 00 77 01 01 11 00 77 01 01 19 00 77
   01 00 89 00 77 01 00 91 00 77 01 00 99 00 77 01
   00 A1 00 77 01 00 A9 00 77 01 00 B1 00 77 01 00
   B9 00 77 01 01 6C 01 1B 01 01 1A 01 1B 01 00 70
   00 71 01 00 BA 00 71 01 00 BF 00 77 01 00 C2 00
   71 01 00 C7 00 77 01 00 CA 00 71 01 00 CF 00 77
   01 00 D2 00 71 01 00 D7 00 77 01 00 DA 00 71 01
   00 DF 00 77 01 00 E2 00 71 01 00 E7 00 77 01 00
   EA 00 71 01 00 EF 00 77 01 00 F2 00 71 01 00 F7
   00 77 01 00 FA 00 71 01 00 FF 00 77 01 01 02 00
   71 01 01 07 00 77 01 00 76 00 77 01 00 7A 00 71
   01 01 0A 00 71 01 01 0F 00 77 01 01 12 00 71 01
   01 17 00 77 01 00 7F 00 77 01 00 82 00 71 01 00
   87 00 77 01 00 8A 00 71 01 00 8F 00 77 01 00 92
   00 71 01 00 97 00 77 01 00 9A 00 71 01 00 9F 00
   77 01 00 A2 00 71 01 00 A7 00 77 01 00 AA 00 71
   01 00 AF 00 77 01 00 B2 00 71 01 00 B7 00 77 01

  ScalaSig: length = 0x3 (unknown attribute)
   05 02 00
