Classfile /Users/mw/Projects/slang-braindump/.jar/jar8/assemble/slang-braindump/assemble/content/org/sireum/MJen$Internal$.class
  Last modified May 29, 2022; size 2132 bytes
  SHA-256 checksum 1fe7f9ad255e209666144c6fbec521ace01d13c79c491a165484aeda29c3dab0
  Compiled from "MJen.scala"
public class org.sireum.MJen$Internal$
  minor version: 0
  major version: 52
  flags: (0x0021) ACC_PUBLIC, ACC_SUPER
  this_class: #2                          // org/sireum/MJen$Internal$
  super_class: #4                         // java/lang/Object
  interfaces: 0, fields: 1, methods: 2, attributes: 4
Constant pool:
    #1 = Utf8               org/sireum/MJen$Internal$
    #2 = Class              #1            // org/sireum/MJen$Internal$
    #3 = Utf8               java/lang/Object
    #4 = Class              #3            // java/lang/Object
    #5 = Utf8               MJen.scala
    #6 = Utf8               org/sireum/MJen
    #7 = Class              #6            // org/sireum/MJen
    #8 = Utf8               Internal$
    #9 = Utf8               org/sireum/MJen$Internal$Concat
   #10 = Class              #9            // org/sireum/MJen$Internal$Concat
   #11 = Utf8               Concat
   #12 = Utf8               org/sireum/MJen$Internal$Concat$
   #13 = Class              #12           // org/sireum/MJen$Internal$Concat$
   #14 = Utf8               Concat$
   #15 = Utf8               org/sireum/MJen$Internal$DropWhile
   #16 = Class              #15           // org/sireum/MJen$Internal$DropWhile
   #17 = Utf8               DropWhile
   #18 = Utf8               org/sireum/MJen$Internal$DropWhile$
   #19 = Class              #18           // org/sireum/MJen$Internal$DropWhile$
   #20 = Utf8               DropWhile$
   #21 = Utf8               org/sireum/MJen$Internal$Filtered
   #22 = Class              #21           // org/sireum/MJen$Internal$Filtered
   #23 = Utf8               Filtered
   #24 = Utf8               org/sireum/MJen$Internal$Filtered$
   #25 = Class              #24           // org/sireum/MJen$Internal$Filtered$
   #26 = Utf8               Filtered$
   #27 = Utf8               org/sireum/MJen$Internal$FlatMapped
   #28 = Class              #27           // org/sireum/MJen$Internal$FlatMapped
   #29 = Utf8               FlatMapped
   #30 = Utf8               org/sireum/MJen$Internal$FlatMapped$
   #31 = Class              #30           // org/sireum/MJen$Internal$FlatMapped$
   #32 = Utf8               FlatMapped$
   #33 = Utf8               org/sireum/MJen$Internal$HashMapImpl
   #34 = Class              #33           // org/sireum/MJen$Internal$HashMapImpl
   #35 = Utf8               HashMapImpl
   #36 = Utf8               org/sireum/MJen$Internal$HashMapImpl$
   #37 = Class              #36           // org/sireum/MJen$Internal$HashMapImpl$
   #38 = Utf8               HashMapImpl$
   #39 = Utf8               org/sireum/MJen$Internal$ISImpl
   #40 = Class              #39           // org/sireum/MJen$Internal$ISImpl
   #41 = Utf8               ISImpl
   #42 = Utf8               org/sireum/MJen$Internal$ISImpl$
   #43 = Class              #42           // org/sireum/MJen$Internal$ISImpl$
   #44 = Utf8               ISImpl$
   #45 = Utf8               org/sireum/MJen$Internal$MSImpl
   #46 = Class              #45           // org/sireum/MJen$Internal$MSImpl
   #47 = Utf8               MSImpl
   #48 = Utf8               org/sireum/MJen$Internal$MSImpl$
   #49 = Class              #48           // org/sireum/MJen$Internal$MSImpl$
   #50 = Utf8               MSImpl$
   #51 = Utf8               org/sireum/MJen$Internal$MapImpl
   #52 = Class              #51           // org/sireum/MJen$Internal$MapImpl
   #53 = Utf8               MapImpl
   #54 = Utf8               org/sireum/MJen$Internal$MapImpl$
   #55 = Class              #54           // org/sireum/MJen$Internal$MapImpl$
   #56 = Utf8               MapImpl$
   #57 = Utf8               org/sireum/MJen$Internal$Mapped
   #58 = Class              #57           // org/sireum/MJen$Internal$Mapped
   #59 = Utf8               Mapped
   #60 = Utf8               org/sireum/MJen$Internal$Mapped$
   #61 = Class              #60           // org/sireum/MJen$Internal$Mapped$
   #62 = Utf8               Mapped$
   #63 = Utf8               org/sireum/MJen$Internal$Product
   #64 = Class              #63           // org/sireum/MJen$Internal$Product
   #65 = Utf8               Product
   #66 = Utf8               org/sireum/MJen$Internal$Product$
   #67 = Class              #66           // org/sireum/MJen$Internal$Product$
   #68 = Utf8               Product$
   #69 = Utf8               org/sireum/MJen$Internal$Sliced
   #70 = Class              #69           // org/sireum/MJen$Internal$Sliced
   #71 = Utf8               Sliced
   #72 = Utf8               org/sireum/MJen$Internal$Sliced$
   #73 = Class              #72           // org/sireum/MJen$Internal$Sliced$
   #74 = Utf8               Sliced$
   #75 = Utf8               org/sireum/MJen$Internal$TakeWhile
   #76 = Class              #75           // org/sireum/MJen$Internal$TakeWhile
   #77 = Utf8               TakeWhile
   #78 = Utf8               org/sireum/MJen$Internal$TakeWhile$
   #79 = Class              #78           // org/sireum/MJen$Internal$TakeWhile$
   #80 = Utf8               TakeWhile$
   #81 = Utf8               org/sireum/MJen$Internal$ZipWithIndexed
   #82 = Class              #81           // org/sireum/MJen$Internal$ZipWithIndexed
   #83 = Utf8               ZipWithIndexed
   #84 = Utf8               org/sireum/MJen$Internal$ZipWithIndexed$
   #85 = Class              #84           // org/sireum/MJen$Internal$ZipWithIndexed$
   #86 = Utf8               ZipWithIndexed$
   #87 = Utf8               org/sireum/MJen$Internal$Zipped
   #88 = Class              #87           // org/sireum/MJen$Internal$Zipped
   #89 = Utf8               Zipped
   #90 = Utf8               org/sireum/MJen$Internal$Zipped$
   #91 = Class              #90           // org/sireum/MJen$Internal$Zipped$
   #92 = Utf8               Zipped$
   #93 = Utf8               MODULE$
   #94 = Utf8               Lorg/sireum/MJen$Internal$;
   #95 = Utf8               <clinit>
   #96 = Utf8               ()V
   #97 = Utf8               <init>
   #98 = NameAndType        #97:#96       // "<init>":()V
   #99 = Methodref          #2.#98        // org/sireum/MJen$Internal$."<init>":()V
  #100 = NameAndType        #93:#94       // MODULE$:Lorg/sireum/MJen$Internal$;
  #101 = Fieldref           #2.#100       // org/sireum/MJen$Internal$.MODULE$:Lorg/sireum/MJen$Internal$;
  #102 = Methodref          #4.#98        // java/lang/Object."<init>":()V
  #103 = Utf8               this
  #104 = Utf8               Code
  #105 = Utf8               LineNumberTable
  #106 = Utf8               LocalVariableTable
  #107 = Utf8               InnerClasses
  #108 = Utf8               SourceFile
  #109 = Utf8               ScalaInlineInfo
  #110 = Utf8               Scala
{
  public static final org.sireum.MJen$Internal$ MODULE$;
    descriptor: Lorg/sireum/MJen$Internal$;
    flags: (0x0019) ACC_PUBLIC, ACC_STATIC, ACC_FINAL

  public static {};
    descriptor: ()V
    flags: (0x0009) ACC_PUBLIC, ACC_STATIC
    Code:
      stack=2, locals=0, args_size=0
         0: new           #2                  // class org/sireum/MJen$Internal$
         3: dup
         4: invokespecial #99                 // Method "<init>":()V
         7: putstatic     #101                // Field MODULE$:Lorg/sireum/MJen$Internal$;
        10: return
      LineNumberTable:
        line 229: 0

  public org.sireum.MJen$Internal$();
    descriptor: ()V
    flags: (0x0001) ACC_PUBLIC
    Code:
      stack=1, locals=1, args_size=1
         0: aload_0
         1: invokespecial #102                // Method java/lang/Object."<init>":()V
         4: return
      LineNumberTable:
        line 229: 0
      LocalVariableTable:
        Start  Length  Slot  Name   Signature
            0       5     0  this   Lorg/sireum/MJen$Internal$;
}
InnerClasses:
  public static #8= #2 of #7;             // Internal$=class org/sireum/MJen$Internal$ of class org/sireum/MJen
  public static final #11= #10 of #2;     // Concat=class org/sireum/MJen$Internal$Concat of class org/sireum/MJen$Internal$
  public static #14= #13 of #2;           // Concat$=class org/sireum/MJen$Internal$Concat$ of class org/sireum/MJen$Internal$
  public static final #17= #16 of #2;     // DropWhile=class org/sireum/MJen$Internal$DropWhile of class org/sireum/MJen$Internal$
  public static #20= #19 of #2;           // DropWhile$=class org/sireum/MJen$Internal$DropWhile$ of class org/sireum/MJen$Internal$
  public static final #23= #22 of #2;     // Filtered=class org/sireum/MJen$Internal$Filtered of class org/sireum/MJen$Internal$
  public static #26= #25 of #2;           // Filtered$=class org/sireum/MJen$Internal$Filtered$ of class org/sireum/MJen$Internal$
  public static final #29= #28 of #2;     // FlatMapped=class org/sireum/MJen$Internal$FlatMapped of class org/sireum/MJen$Internal$
  public static #32= #31 of #2;           // FlatMapped$=class org/sireum/MJen$Internal$FlatMapped$ of class org/sireum/MJen$Internal$
  public static final #35= #34 of #2;     // HashMapImpl=class org/sireum/MJen$Internal$HashMapImpl of class org/sireum/MJen$Internal$
  public static #38= #37 of #2;           // HashMapImpl$=class org/sireum/MJen$Internal$HashMapImpl$ of class org/sireum/MJen$Internal$
  public static final #41= #40 of #2;     // ISImpl=class org/sireum/MJen$Internal$ISImpl of class org/sireum/MJen$Internal$
  public static #44= #43 of #2;           // ISImpl$=class org/sireum/MJen$Internal$ISImpl$ of class org/sireum/MJen$Internal$
  public static final #47= #46 of #2;     // MSImpl=class org/sireum/MJen$Internal$MSImpl of class org/sireum/MJen$Internal$
  public static #50= #49 of #2;           // MSImpl$=class org/sireum/MJen$Internal$MSImpl$ of class org/sireum/MJen$Internal$
  public static final #53= #52 of #2;     // MapImpl=class org/sireum/MJen$Internal$MapImpl of class org/sireum/MJen$Internal$
  public static #56= #55 of #2;           // MapImpl$=class org/sireum/MJen$Internal$MapImpl$ of class org/sireum/MJen$Internal$
  public static final #59= #58 of #2;     // Mapped=class org/sireum/MJen$Internal$Mapped of class org/sireum/MJen$Internal$
  public static #62= #61 of #2;           // Mapped$=class org/sireum/MJen$Internal$Mapped$ of class org/sireum/MJen$Internal$
  public static final #65= #64 of #2;     // Product=class org/sireum/MJen$Internal$Product of class org/sireum/MJen$Internal$
  public static #68= #67 of #2;           // Product$=class org/sireum/MJen$Internal$Product$ of class org/sireum/MJen$Internal$
  public static final #71= #70 of #2;     // Sliced=class org/sireum/MJen$Internal$Sliced of class org/sireum/MJen$Internal$
  public static #74= #73 of #2;           // Sliced$=class org/sireum/MJen$Internal$Sliced$ of class org/sireum/MJen$Internal$
  public static final #77= #76 of #2;     // TakeWhile=class org/sireum/MJen$Internal$TakeWhile of class org/sireum/MJen$Internal$
  public static #80= #79 of #2;           // TakeWhile$=class org/sireum/MJen$Internal$TakeWhile$ of class org/sireum/MJen$Internal$
  public static final #83= #82 of #2;     // ZipWithIndexed=class org/sireum/MJen$Internal$ZipWithIndexed of class org/sireum/MJen$Internal$
  public static #86= #85 of #2;           // ZipWithIndexed$=class org/sireum/MJen$Internal$ZipWithIndexed$ of class org/sireum/MJen$Internal$
  public static final #89= #88 of #2;     // Zipped=class org/sireum/MJen$Internal$Zipped of class org/sireum/MJen$Internal$
  public static #92= #91 of #2;           // Zipped$=class org/sireum/MJen$Internal$Zipped$ of class org/sireum/MJen$Internal$
SourceFile: "MJen.scala"
  ScalaInlineInfo: length = 0x9 (unknown attribute)
   01 01 00 01 00 61 00 60 01
  Scala: length = 0x0 (unknown attribute)

