Classfile /Users/mw/Projects/slang-braindump/.jar/jar8/assemble/slang-braindump/assemble/content/org/sireum/MS$$anon$1.class
  Last modified May 29, 2022; size 1268 bytes
  SHA-256 checksum 7b21c63733ec8aef6d719986f274c31374ffcfa18b80f385fa03c443da7be39e
  Compiled from "MS.scala"
public final class org.sireum.MS$$anon$1 extends java.lang.Object implements org.sireum.ZRange$CondIncDec<I>
  minor version: 0
  major version: 52
  flags: (0x0031) ACC_PUBLIC, ACC_FINAL, ACC_SUPER
  this_class: #2                          // org/sireum/MS$$anon$1
  super_class: #5                         // java/lang/Object
  interfaces: 1, fields: 0, methods: 4, attributes: 6
Constant pool:
   #1 = Utf8               org/sireum/MS$$anon$1
   #2 = Class              #1             // org/sireum/MS$$anon$1
   #3 = Utf8               Ljava/lang/Object;Lorg/sireum/ZRange$CondIncDec<TI;>;
   #4 = Utf8               java/lang/Object
   #5 = Class              #4             // java/lang/Object
   #6 = Utf8               org/sireum/ZRange$CondIncDec
   #7 = Class              #6             // org/sireum/ZRange$CondIncDec
   #8 = Utf8               MS.scala
   #9 = Utf8               org/sireum/MS
  #10 = Class              #9             // org/sireum/MS
  #11 = Utf8               indices
  #12 = Utf8               ()Lorg/sireum/ZRange;
  #13 = NameAndType        #11:#12        // indices:()Lorg/sireum/ZRange;
  #14 = Utf8               org/sireum/ZRange
  #15 = Class              #14            // org/sireum/ZRange
  #16 = Utf8               CondIncDec
  #17 = Utf8               cond
  #18 = Utf8               (Ljava/lang/Object;)Z
  #19 = Utf8               (TI;)Z
  #20 = Utf8               i
  #21 = Utf8               org/sireum/package$
  #22 = Class              #21            // org/sireum/package$
  #23 = Utf8               MODULE$
  #24 = Utf8               Lorg/sireum/package$;
  #25 = NameAndType        #23:#24        // MODULE$:Lorg/sireum/package$;
  #26 = Fieldref           #22.#25        // org/sireum/package$.MODULE$:Lorg/sireum/package$;
  #27 = Utf8               T
  #28 = Utf8               ()Z
  #29 = NameAndType        #27:#28        // T:()Z
  #30 = Methodref          #22.#29        // org/sireum/package$.T:()Z
  #31 = Utf8               this
  #32 = Utf8               Lorg/sireum/MS$$anon$1;
  #33 = Utf8               Ljava/lang/Object;
  #34 = Utf8               increase
  #35 = Utf8               (Ljava/lang/Object;)Ljava/lang/Object;
  #36 = Utf8               (TI;)TI;
  #37 = Utf8               org/sireum/ZLike
  #38 = Class              #37            // org/sireum/ZLike
  #39 = Utf8               ()Lorg/sireum/ZLike;
  #40 = NameAndType        #34:#39        // increase:()Lorg/sireum/ZLike;
  #41 = InterfaceMethodref #38.#40        // org/sireum/ZLike.increase:()Lorg/sireum/ZLike;
  #42 = Utf8               decrease
  #43 = NameAndType        #42:#39        // decrease:()Lorg/sireum/ZLike;
  #44 = InterfaceMethodref #38.#43        // org/sireum/ZLike.decrease:()Lorg/sireum/ZLike;
  #45 = Utf8               <init>
  #46 = Utf8               (Lorg/sireum/MS;)V
  #47 = Utf8               $outer
  #48 = Utf8               ()V
  #49 = NameAndType        #45:#48        // "<init>":()V
  #50 = Methodref          #5.#49         // java/lang/Object."<init>":()V
  #51 = Utf8               Lorg/sireum/MS;
  #52 = Utf8               Code
  #53 = Utf8               LineNumberTable
  #54 = Utf8               LocalVariableTable
  #55 = Utf8               Signature
  #56 = Utf8               MethodParameters
  #57 = Utf8               InnerClasses
  #58 = Utf8               EnclosingMethod
  #59 = Utf8               SourceFile
  #60 = Utf8               ScalaInlineInfo
  #61 = Utf8               Scala
{
  public boolean cond(I);
    descriptor: (Ljava/lang/Object;)Z
    flags: (0x0001) ACC_PUBLIC
    Code:
      stack=1, locals=2, args_size=2
         0: getstatic     #26                 // Field org/sireum/package$.MODULE$:Lorg/sireum/package$;
         3: invokevirtual #30                 // Method org/sireum/package$.T:()Z
         6: ireturn
      LineNumberTable:
        line 226: 0
      LocalVariableTable:
        Start  Length  Slot  Name   Signature
            0       7     0  this   Lorg/sireum/MS$$anon$1;
            0       7     1     i   Ljava/lang/Object;
    Signature: #19                          // (TI;)Z
    MethodParameters:
      Name                           Flags
      i                              final

  public I increase(I);
    descriptor: (Ljava/lang/Object;)Ljava/lang/Object;
    flags: (0x0001) ACC_PUBLIC
    Code:
      stack=1, locals=2, args_size=2
         0: aload_1
         1: checkcast     #38                 // class org/sireum/ZLike
         4: invokeinterface #41,  1           // InterfaceMethod org/sireum/ZLike.increase:()Lorg/sireum/ZLike;
         9: areturn
      LineNumberTable:
        line 227: 0
      LocalVariableTable:
        Start  Length  Slot  Name   Signature
            0      10     0  this   Lorg/sireum/MS$$anon$1;
            0      10     1     i   Ljava/lang/Object;
    Signature: #36                          // (TI;)TI;
    MethodParameters:
      Name                           Flags
      i                              final

  public I decrease(I);
    descriptor: (Ljava/lang/Object;)Ljava/lang/Object;
    flags: (0x0001) ACC_PUBLIC
    Code:
      stack=1, locals=2, args_size=2
         0: aload_1
         1: checkcast     #38                 // class org/sireum/ZLike
         4: invokeinterface #44,  1           // InterfaceMethod org/sireum/ZLike.decrease:()Lorg/sireum/ZLike;
         9: areturn
      LineNumberTable:
        line 228: 0
      LocalVariableTable:
        Start  Length  Slot  Name   Signature
            0      10     0  this   Lorg/sireum/MS$$anon$1;
            0      10     1     i   Ljava/lang/Object;
    Signature: #36                          // (TI;)TI;
    MethodParameters:
      Name                           Flags
      i                              final

  public org.sireum.MS$$anon$1(org.sireum.MS);
    descriptor: (Lorg/sireum/MS;)V
    flags: (0x0001) ACC_PUBLIC
    Code:
      stack=1, locals=2, args_size=2
         0: aload_0
         1: invokespecial #50                 // Method java/lang/Object."<init>":()V
         4: return
      LineNumberTable:
        line 225: 0
      LocalVariableTable:
        Start  Length  Slot  Name   Signature
            0       5     0  this   Lorg/sireum/MS$$anon$1;
            0       5     1 $outer   Lorg/sireum/MS;
    MethodParameters:
      Name                           Flags
      $outer                         final synthetic
}
InnerClasses:
  public final #2;                        // class org/sireum/MS$$anon$1
  public static #16= #7 of #15;           // CondIncDec=class org/sireum/ZRange$CondIncDec of class org/sireum/ZRange
EnclosingMethod: #10.#13                // org.sireum.MS.indices
Signature: #3                           // Ljava/lang/Object;Lorg/sireum/ZRange$CondIncDec<TI;>;
SourceFile: "MS.scala"
  ScalaInlineInfo: length = 0x18 (unknown attribute)
   01 01 00 04 00 2D 00 2E 01 00 11 00 12 01 00 2A
   00 23 01 00 22 00 23 01
  Scala: length = 0x0 (unknown attribute)

