Classfile /Users/mw/Projects/slang-braindump/.jar/jar8/assemble/slang-braindump/assemble/content/org/sireum/MS$WithFilter.class
  Last modified May 29, 2022; size 7829 bytes
  SHA-256 checksum 977bb82bce2d546d8aa563f71bb3842f4e846879cea5a692932a2753a3978683
  Compiled from "MS.scala"
public class org.sireum.MS$WithFilter<I extends java.lang.Object, V extends java.lang.Object> extends java.lang.Object
  minor version: 0
  major version: 52
  flags: (0x0021) ACC_PUBLIC, ACC_SUPER
  this_class: #2                          // org/sireum/MS$WithFilter
  super_class: #5                         // java/lang/Object
  interfaces: 0, fields: 2, methods: 14, attributes: 6
Constant pool:
    #1 = Utf8               org/sireum/MS$WithFilter
    #2 = Class              #1            // org/sireum/MS$WithFilter
    #3 = Utf8               <I:Ljava/lang/Object;V:Ljava/lang/Object;>Ljava/lang/Object;
    #4 = Utf8               java/lang/Object
    #5 = Class              #4            // java/lang/Object
    #6 = Utf8               MS.scala
    #7 = Utf8               java/lang/invoke/MethodHandles$Lookup
    #8 = Class              #7            // java/lang/invoke/MethodHandles$Lookup
    #9 = Utf8               java/lang/invoke/MethodHandles
   #10 = Class              #9            // java/lang/invoke/MethodHandles
   #11 = Utf8               Lookup
   #12 = Utf8               org/sireum/MS
   #13 = Class              #12           // org/sireum/MS
   #14 = Utf8               WithFilter
   #15 = Utf8               org/sireum/Z$MP$
   #16 = Class              #15           // org/sireum/Z$MP$
   #17 = Utf8               org/sireum/Z
   #18 = Class              #17           // org/sireum/Z
   #19 = Utf8               MP$
   #20 = Utf8               ms
   #21 = Utf8               Lorg/sireum/MS;
   #22 = Utf8               Lorg/sireum/MS<TI;TV;>;
   #23 = Utf8               p
   #24 = Utf8               Lscala/Function1;
   #25 = Utf8               Lscala/Function1<TV;Lorg/sireum/B;>;
   #26 = Utf8               foreach
   #27 = Utf8               (Lscala/Function1;)V
   #28 = Utf8               <U:Ljava/lang/Object;>(Lscala/Function1<TV;TU;>;)V
   #29 = Utf8               f
   #30 = Utf8               MODULE$
   #31 = Utf8               Lorg/sireum/Z$MP$;
   #32 = NameAndType        #30:#31       // MODULE$:Lorg/sireum/Z$MP$;
   #33 = Fieldref           #16.#32       // org/sireum/Z$MP$.MODULE$:Lorg/sireum/Z$MP$;
   #34 = Utf8               zero
   #35 = Utf8               ()Lorg/sireum/Z;
   #36 = NameAndType        #34:#35       // zero:()Lorg/sireum/Z;
   #37 = Methodref          #16.#36       // org/sireum/Z$MP$.zero:()Lorg/sireum/Z;
   #38 = Utf8               org/sireum/B$
   #39 = Class              #38           // org/sireum/B$
   #40 = Utf8               Lorg/sireum/B$;
   #41 = NameAndType        #30:#40       // MODULE$:Lorg/sireum/B$;
   #42 = Fieldref           #39.#41       // org/sireum/B$.MODULE$:Lorg/sireum/B$;
   #43 = NameAndType        #20:#21       // ms:Lorg/sireum/MS;
   #44 = Fieldref           #2.#43        // org/sireum/MS$WithFilter.ms:Lorg/sireum/MS;
   #45 = Utf8               length
   #46 = NameAndType        #45:#35       // length:()Lorg/sireum/Z;
   #47 = Methodref          #13.#46       // org/sireum/MS.length:()Lorg/sireum/Z;
   #48 = Utf8               $less
   #49 = Utf8               (Lorg/sireum/Z;)Z
   #50 = NameAndType        #48:#49       // $less:(Lorg/sireum/Z;)Z
   #51 = InterfaceMethodref #18.#50       // org/sireum/Z.$less:(Lorg/sireum/Z;)Z
   #52 = Utf8               $4B
   #53 = Utf8               (Z)Z
   #54 = NameAndType        #52:#53       // $4B:(Z)Z
   #55 = Methodref          #39.#54       // org/sireum/B$.$4B:(Z)Z
   #56 = Utf8               boxer
   #57 = Utf8               ()Lorg/sireum/$internal/Boxer;
   #58 = NameAndType        #56:#57       // boxer:()Lorg/sireum/$internal/Boxer;
   #59 = Methodref          #13.#58       // org/sireum/MS.boxer:()Lorg/sireum/$internal/Boxer;
   #60 = Utf8               data
   #61 = Utf8               ()Ljava/lang/Object;
   #62 = NameAndType        #60:#61       // data:()Ljava/lang/Object;
   #63 = Methodref          #13.#62       // org/sireum/MS.data:()Ljava/lang/Object;
   #64 = Utf8               org/sireum/$internal/Boxer
   #65 = Class              #64           // org/sireum/$internal/Boxer
   #66 = Utf8               lookup
   #67 = Utf8               (Ljava/lang/Object;Lorg/sireum/Z;)Ljava/lang/Object;
   #68 = NameAndType        #66:#67       // lookup:(Ljava/lang/Object;Lorg/sireum/Z;)Ljava/lang/Object;
   #69 = InterfaceMethodref #65.#68       // org/sireum/$internal/Boxer.lookup:(Ljava/lang/Object;Lorg/sireum/Z;)Ljava/lang/Object;
   #70 = NameAndType        #23:#24       // p:Lscala/Function1;
   #71 = Fieldref           #2.#70        // org/sireum/MS$WithFilter.p:Lscala/Function1;
   #72 = Utf8               scala/Function1
   #73 = Class              #72           // scala/Function1
   #74 = Utf8               apply
   #75 = Utf8               (Ljava/lang/Object;)Ljava/lang/Object;
   #76 = NameAndType        #74:#75       // apply:(Ljava/lang/Object;)Ljava/lang/Object;
   #77 = InterfaceMethodref #73.#76       // scala/Function1.apply:(Ljava/lang/Object;)Ljava/lang/Object;
   #78 = Utf8               org/sireum/B
   #79 = Class              #78           // org/sireum/B
   #80 = Utf8               value
   #81 = Utf8               ()Z
   #82 = NameAndType        #80:#81       // value:()Z
   #83 = Methodref          #79.#82       // org/sireum/B.value:()Z
   #84 = Utf8               scala/runtime/BoxedUnit
   #85 = Class              #84           // scala/runtime/BoxedUnit
   #86 = Utf8               UNIT
   #87 = Utf8               Lscala/runtime/BoxedUnit;
   #88 = NameAndType        #86:#87       // UNIT:Lscala/runtime/BoxedUnit;
   #89 = Fieldref           #85.#88       // scala/runtime/BoxedUnit.UNIT:Lscala/runtime/BoxedUnit;
   #90 = Utf8               increase
   #91 = NameAndType        #90:#35       // increase:()Lorg/sireum/Z;
   #92 = InterfaceMethodref #18.#91       // org/sireum/Z.increase:()Lorg/sireum/Z;
   #93 = Utf8               v
   #94 = Utf8               Ljava/lang/Object;
   #95 = Utf8               i
   #96 = Utf8               Lorg/sireum/Z;
   #97 = Utf8               this
   #98 = Utf8               Lorg/sireum/MS$WithFilter;
   #99 = Utf8               map
  #100 = Utf8               (Lscala/Function1;)Lorg/sireum/MS;
  #101 = Utf8               <V2:Ljava/lang/Object;>(Lscala/Function1<TV;TV2;>;)Lorg/sireum/MS<TI;TV2;>;
  #102 = Utf8               isEmpty
  #103 = NameAndType        #102:#81      // isEmpty:()Z
  #104 = Methodref          #13.#103      // org/sireum/MS.isEmpty:()Z
  #105 = Utf8               org/sireum/MS$
  #106 = Class              #105          // org/sireum/MS$
  #107 = Utf8               Lorg/sireum/MS$;
  #108 = NameAndType        #30:#107      // MODULE$:Lorg/sireum/MS$;
  #109 = Fieldref           #106.#108     // org/sireum/MS$.MODULE$:Lorg/sireum/MS$;
  #110 = Utf8               scala/collection/immutable/Nil$
  #111 = Class              #110          // scala/collection/immutable/Nil$
  #112 = Utf8               Lscala/collection/immutable/Nil$;
  #113 = NameAndType        #30:#112      // MODULE$:Lscala/collection/immutable/Nil$;
  #114 = Fieldref           #111.#113     // scala/collection/immutable/Nil$.MODULE$:Lscala/collection/immutable/Nil$;
  #115 = Utf8               companion
  #116 = Utf8               ()Lorg/sireum/$ZCompanion;
  #117 = NameAndType        #115:#116     // companion:()Lorg/sireum/$ZCompanion;
  #118 = Methodref          #13.#117      // org/sireum/MS.companion:()Lorg/sireum/$ZCompanion;
  #119 = Utf8               (Lscala/collection/immutable/Seq;Lorg/sireum/$ZCompanion;)Lorg/sireum/MS;
  #120 = NameAndType        #74:#119      // apply:(Lscala/collection/immutable/Seq;Lorg/sireum/$ZCompanion;)Lorg/sireum/MS;
  #121 = Methodref          #106.#120     // org/sireum/MS$.apply:(Lscala/collection/immutable/Seq;Lorg/sireum/$ZCompanion;)Lorg/sireum/MS;
  #122 = Utf8               scala/Array$
  #123 = Class              #122          // scala/Array$
  #124 = Utf8               Lscala/Array$;
  #125 = NameAndType        #30:#124      // MODULE$:Lscala/Array$;
  #126 = Fieldref           #123.#125     // scala/Array$.MODULE$:Lscala/Array$;
  #127 = Utf8               scala/reflect/ClassTag$
  #128 = Class              #127          // scala/reflect/ClassTag$
  #129 = Utf8               Lscala/reflect/ClassTag$;
  #130 = NameAndType        #30:#129      // MODULE$:Lscala/reflect/ClassTag$;
  #131 = Fieldref           #128.#130     // scala/reflect/ClassTag$.MODULE$:Lscala/reflect/ClassTag$;
  #132 = Utf8               Nothing
  #133 = Utf8               ()Lscala/reflect/ClassTag;
  #134 = NameAndType        #132:#133     // Nothing:()Lscala/reflect/ClassTag;
  #135 = Methodref          #128.#134     // scala/reflect/ClassTag$.Nothing:()Lscala/reflect/ClassTag;
  #136 = Utf8               (Lscala/collection/immutable/Seq;Lscala/reflect/ClassTag;)Ljava/lang/Object;
  #137 = NameAndType        #74:#136      // apply:(Lscala/collection/immutable/Seq;Lscala/reflect/ClassTag;)Ljava/lang/Object;
  #138 = Methodref          #123.#137     // scala/Array$.apply:(Lscala/collection/immutable/Seq;Lscala/reflect/ClassTag;)Ljava/lang/Object;
  #139 = Utf8               org/sireum/$internal/Boxer$
  #140 = Class              #139          // org/sireum/$internal/Boxer$
  #141 = Utf8               Lorg/sireum/$internal/Boxer$;
  #142 = NameAndType        #30:#141      // MODULE$:Lorg/sireum/$internal/Boxer$;
  #143 = Fieldref           #140.#142     // org/sireum/$internal/Boxer$.MODULE$:Lorg/sireum/$internal/Boxer$;
  #144 = Utf8               (Ljava/lang/Object;)Lorg/sireum/$internal/Boxer;
  #145 = NameAndType        #56:#144      // boxer:(Ljava/lang/Object;)Lorg/sireum/$internal/Boxer;
  #146 = Methodref          #140.#145     // org/sireum/$internal/Boxer$.boxer:(Ljava/lang/Object;)Lorg/sireum/$internal/Boxer;
  #147 = Utf8               create
  #148 = Utf8               (Lorg/sireum/Z;)Ljava/lang/Object;
  #149 = NameAndType        #147:#148     // create:(Lorg/sireum/Z;)Ljava/lang/Object;
  #150 = InterfaceMethodref #65.#149      // org/sireum/$internal/Boxer.create:(Lorg/sireum/Z;)Ljava/lang/Object;
  #151 = Utf8               org/sireum/helper$
  #152 = Class              #151          // org/sireum/helper$
  #153 = Utf8               Lorg/sireum/helper$;
  #154 = NameAndType        #30:#153      // MODULE$:Lorg/sireum/helper$;
  #155 = Fieldref           #152.#154     // org/sireum/helper$.MODULE$:Lorg/sireum/helper$;
  #156 = Utf8               assign
  #157 = NameAndType        #156:#75      // assign:(Ljava/lang/Object;)Ljava/lang/Object;
  #158 = Methodref          #152.#157     // org/sireum/helper$.assign:(Ljava/lang/Object;)Ljava/lang/Object;
  #159 = Utf8               store
  #160 = Utf8               (Ljava/lang/Object;Lorg/sireum/Z;Ljava/lang/Object;)V
  #161 = NameAndType        #159:#160     // store:(Ljava/lang/Object;Lorg/sireum/Z;Ljava/lang/Object;)V
  #162 = InterfaceMethodref #65.#161      // org/sireum/$internal/Boxer.store:(Ljava/lang/Object;Lorg/sireum/Z;Ljava/lang/Object;)V
  #163 = Utf8               org/sireum/$internal/IdentityBoxer$
  #164 = Class              #163          // org/sireum/$internal/IdentityBoxer$
  #165 = Utf8               Lorg/sireum/$internal/IdentityBoxer$;
  #166 = NameAndType        #30:#165      // MODULE$:Lorg/sireum/$internal/IdentityBoxer$;
  #167 = Fieldref           #164.#166     // org/sireum/$internal/IdentityBoxer$.MODULE$:Lorg/sireum/$internal/IdentityBoxer$;
  #168 = Utf8               (Lorg/sireum/$ZCompanion;Ljava/lang/Object;Lorg/sireum/Z;Lorg/sireum/$internal/Boxer;)Lorg/sireum/MS;
  #169 = NameAndType        #74:#168      // apply:(Lorg/sireum/$ZCompanion;Ljava/lang/Object;Lorg/sireum/Z;Lorg/sireum/$internal/Boxer;)Lorg/sireum/MS;
  #170 = Methodref          #106.#169     // org/sireum/MS$.apply:(Lorg/sireum/$ZCompanion;Ljava/lang/Object;Lorg/sireum/Z;Lorg/sireum/$internal/Boxer;)Lorg/sireum/MS;
  #171 = Utf8               v2
  #172 = Utf8               a
  #173 = Utf8               boxer2
  #174 = Utf8               Lorg/sireum/$internal/Boxer;
  #175 = Utf8               j
  #176 = Utf8               org/sireum/$ZCompanion
  #177 = Class              #176          // org/sireum/$ZCompanion
  #178 = Utf8               flatMap
  #179 = Utf8               <V2:Ljava/lang/Object;>(Lscala/Function1<TV;Lorg/sireum/MS<TI;TV2;>;>;)Lorg/sireum/MS<TI;TV2;>;
  #180 = Utf8               elements
  #181 = Utf8               ()Lscala/collection/immutable/Seq;
  #182 = NameAndType        #180:#181     // elements:()Lscala/collection/immutable/Seq;
  #183 = Methodref          #13.#182      // org/sireum/MS.elements:()Lscala/collection/immutable/Seq;
  #184 = Utf8               scala/collection/immutable/Seq
  #185 = Class              #184          // scala/collection/immutable/Seq
  #186 = Utf8               head
  #187 = NameAndType        #186:#61      // head:()Ljava/lang/Object;
  #188 = InterfaceMethodref #185.#187     // scala/collection/immutable/Seq.head:()Ljava/lang/Object;
  #189 = Utf8               scala/runtime/ObjectRef
  #190 = Class              #189          // scala/runtime/ObjectRef
  #191 = Utf8               (Ljava/lang/Object;)Lscala/runtime/ObjectRef;
  #192 = NameAndType        #147:#191     // create:(Ljava/lang/Object;)Lscala/runtime/ObjectRef;
  #193 = Methodref          #190.#192     // scala/runtime/ObjectRef.create:(Ljava/lang/Object;)Lscala/runtime/ObjectRef;
  #194 = Utf8               tail
  #195 = NameAndType        #194:#61      // tail:()Ljava/lang/Object;
  #196 = InterfaceMethodref #185.#195     // scala/collection/immutable/Seq.tail:()Ljava/lang/Object;
  #197 = Utf8               scala/collection/IterableOps
  #198 = Class              #197          // scala/collection/IterableOps
  #199 = MethodType         #75           //  (Ljava/lang/Object;)Ljava/lang/Object;
  #200 = Utf8               $anonfun$flatMap$1$adapted
  #201 = Utf8               (Lorg/sireum/MS$WithFilter;Ljava/lang/Object;)Ljava/lang/Object;
  #202 = NameAndType        #200:#201     // $anonfun$flatMap$1$adapted:(Lorg/sireum/MS$WithFilter;Ljava/lang/Object;)Ljava/lang/Object;
  #203 = Methodref          #2.#202       // org/sireum/MS$WithFilter.$anonfun$flatMap$1$adapted:(Lorg/sireum/MS$WithFilter;Ljava/lang/Object;)Ljava/lang/Object;
  #204 = MethodHandle       6:#203        // REF_invokeStatic org/sireum/MS$WithFilter.$anonfun$flatMap$1$adapted:(Lorg/sireum/MS$WithFilter;Ljava/lang/Object;)Ljava/lang/Object;
  #205 = Integer            1
  #206 = Utf8               java/lang/invoke/LambdaMetafactory
  #207 = Class              #206          // java/lang/invoke/LambdaMetafactory
  #208 = Utf8               altMetafactory
  #209 = Utf8               (Ljava/lang/invoke/MethodHandles$Lookup;Ljava/lang/String;Ljava/lang/invoke/MethodType;[Ljava/lang/Object;)Ljava/lang/invoke/CallSite;
  #210 = NameAndType        #208:#209     // altMetafactory:(Ljava/lang/invoke/MethodHandles$Lookup;Ljava/lang/String;Ljava/lang/invoke/MethodType;[Ljava/lang/Object;)Ljava/lang/invoke/CallSite;
  #211 = Methodref          #207.#210     // java/lang/invoke/LambdaMetafactory.altMetafactory:(Ljava/lang/invoke/MethodHandles$Lookup;Ljava/lang/String;Ljava/lang/invoke/MethodType;[Ljava/lang/Object;)Ljava/lang/invoke/CallSite;
  #212 = MethodHandle       6:#211        // REF_invokeStatic java/lang/invoke/LambdaMetafactory.altMetafactory:(Ljava/lang/invoke/MethodHandles$Lookup;Ljava/lang/String;Ljava/lang/invoke/MethodType;[Ljava/lang/Object;)Ljava/lang/invoke/CallSite;
  #213 = Utf8               (Lorg/sireum/MS$WithFilter;)Lscala/Function1;
  #214 = NameAndType        #74:#213      // apply:(Lorg/sireum/MS$WithFilter;)Lscala/Function1;
  #215 = InvokeDynamic      #0:#214       // #0:apply:(Lorg/sireum/MS$WithFilter;)Lscala/Function1;
  #216 = Utf8               withFilter
  #217 = Utf8               (Lscala/Function1;)Lscala/collection/WithFilter;
  #218 = NameAndType        #216:#217     // withFilter:(Lscala/Function1;)Lscala/collection/WithFilter;
  #219 = InterfaceMethodref #198.#218     // scala/collection/IterableOps.withFilter:(Lscala/Function1;)Lscala/collection/WithFilter;
  #220 = Utf8               $anonfun$flatMap$2$adapted
  #221 = Utf8               (Lscala/runtime/ObjectRef;Lscala/Function1;Ljava/lang/Object;)Ljava/lang/Object;
  #222 = NameAndType        #220:#221     // $anonfun$flatMap$2$adapted:(Lscala/runtime/ObjectRef;Lscala/Function1;Ljava/lang/Object;)Ljava/lang/Object;
  #223 = Methodref          #2.#222       // org/sireum/MS$WithFilter.$anonfun$flatMap$2$adapted:(Lscala/runtime/ObjectRef;Lscala/Function1;Ljava/lang/Object;)Ljava/lang/Object;
  #224 = MethodHandle       6:#223        // REF_invokeStatic org/sireum/MS$WithFilter.$anonfun$flatMap$2$adapted:(Lscala/runtime/ObjectRef;Lscala/Function1;Ljava/lang/Object;)Ljava/lang/Object;
  #225 = Utf8               (Lscala/runtime/ObjectRef;Lscala/Function1;)Lscala/Function1;
  #226 = NameAndType        #74:#225      // apply:(Lscala/runtime/ObjectRef;Lscala/Function1;)Lscala/Function1;
  #227 = InvokeDynamic      #1:#226       // #1:apply:(Lscala/runtime/ObjectRef;Lscala/Function1;)Lscala/Function1;
  #228 = Utf8               scala/collection/WithFilter
  #229 = Class              #228          // scala/collection/WithFilter
  #230 = NameAndType        #26:#27       // foreach:(Lscala/Function1;)V
  #231 = Methodref          #229.#230     // scala/collection/WithFilter.foreach:(Lscala/Function1;)V
  #232 = Utf8               elem
  #233 = NameAndType        #232:#94      // elem:Ljava/lang/Object;
  #234 = Fieldref           #190.#233     // scala/runtime/ObjectRef.elem:Ljava/lang/Object;
  #235 = Utf8               es
  #236 = Utf8               Lscala/collection/immutable/Seq;
  #237 = Utf8               r
  #238 = Utf8               Lscala/runtime/ObjectRef;
  #239 = Utf8               (Lscala/Function1;)Lorg/sireum/MS$WithFilter;
  #240 = Utf8               (Lscala/Function1<TV;Lorg/sireum/B;>;)Lorg/sireum/MS$WithFilter<TI;TV;>;
  #241 = Utf8               p2
  #242 = Utf8               $anonfun$withFilter$1$adapted
  #243 = Utf8               (Lorg/sireum/MS$WithFilter;Lscala/Function1;Ljava/lang/Object;)Ljava/lang/Object;
  #244 = NameAndType        #242:#243     // $anonfun$withFilter$1$adapted:(Lorg/sireum/MS$WithFilter;Lscala/Function1;Ljava/lang/Object;)Ljava/lang/Object;
  #245 = Methodref          #2.#244       // org/sireum/MS$WithFilter.$anonfun$withFilter$1$adapted:(Lorg/sireum/MS$WithFilter;Lscala/Function1;Ljava/lang/Object;)Ljava/lang/Object;
  #246 = MethodHandle       6:#245        // REF_invokeStatic org/sireum/MS$WithFilter.$anonfun$withFilter$1$adapted:(Lorg/sireum/MS$WithFilter;Lscala/Function1;Ljava/lang/Object;)Ljava/lang/Object;
  #247 = Utf8               (Lorg/sireum/MS$WithFilter;Lscala/Function1;)Lscala/Function1;
  #248 = NameAndType        #74:#247      // apply:(Lorg/sireum/MS$WithFilter;Lscala/Function1;)Lscala/Function1;
  #249 = InvokeDynamic      #2:#248       // #2:apply:(Lorg/sireum/MS$WithFilter;Lscala/Function1;)Lscala/Function1;
  #250 = Utf8               <init>
  #251 = Utf8               (Lorg/sireum/MS;Lscala/Function1;)V
  #252 = NameAndType        #250:#251     // "<init>":(Lorg/sireum/MS;Lscala/Function1;)V
  #253 = Methodref          #2.#252       // org/sireum/MS$WithFilter."<init>":(Lorg/sireum/MS;Lscala/Function1;)V
  #254 = Utf8               $anonfun$flatMap$1
  #255 = Utf8               (Lorg/sireum/MS$WithFilter;Ljava/lang/Object;)Z
  #256 = Utf8               $this
  #257 = Utf8               e
  #258 = Utf8               $anonfun$flatMap$2
  #259 = Utf8               (Lscala/runtime/ObjectRef;Lscala/Function1;Ljava/lang/Object;)V
  #260 = Utf8               r$1
  #261 = Utf8               f$1
  #262 = Utf8               $plus$plus
  #263 = Utf8               (Lorg/sireum/MS;)Lorg/sireum/MS;
  #264 = NameAndType        #262:#263     // $plus$plus:(Lorg/sireum/MS;)Lorg/sireum/MS;
  #265 = Methodref          #13.#264      // org/sireum/MS.$plus$plus:(Lorg/sireum/MS;)Lorg/sireum/MS;
  #266 = Utf8               $anonfun$withFilter$2
  #267 = Utf8               (Lscala/Function1;Ljava/lang/Object;)Z
  #268 = Utf8               p2$1
  #269 = Utf8               v$1
  #270 = Utf8               $anonfun$withFilter$1
  #271 = Utf8               (Lorg/sireum/MS$WithFilter;Lscala/Function1;Ljava/lang/Object;)Z
  #272 = MethodType         #61           //  ()Ljava/lang/Object;
  #273 = Utf8               $anonfun$withFilter$2$adapted
  #274 = Utf8               (Lscala/Function1;Ljava/lang/Object;)Ljava/lang/Object;
  #275 = NameAndType        #273:#274     // $anonfun$withFilter$2$adapted:(Lscala/Function1;Ljava/lang/Object;)Ljava/lang/Object;
  #276 = Methodref          #2.#275       // org/sireum/MS$WithFilter.$anonfun$withFilter$2$adapted:(Lscala/Function1;Ljava/lang/Object;)Ljava/lang/Object;
  #277 = MethodHandle       6:#276        // REF_invokeStatic org/sireum/MS$WithFilter.$anonfun$withFilter$2$adapted:(Lscala/Function1;Ljava/lang/Object;)Ljava/lang/Object;
  #278 = Utf8               (Lscala/Function1;Ljava/lang/Object;)Lscala/Function0;
  #279 = NameAndType        #74:#278      // apply:(Lscala/Function1;Ljava/lang/Object;)Lscala/Function0;
  #280 = InvokeDynamic      #3:#279       // #3:apply:(Lscala/Function1;Ljava/lang/Object;)Lscala/Function0;
  #281 = Utf8               $amp$amp$extension
  #282 = Utf8               (ZLscala/Function0;)Z
  #283 = NameAndType        #281:#282     // $amp$amp$extension:(ZLscala/Function0;)Z
  #284 = Methodref          #39.#283      // org/sireum/B$.$amp$amp$extension:(ZLscala/Function0;)Z
  #285 = Utf8               (Lorg/sireum/MS<TI;TV;>;Lscala/Function1<TV;Lorg/sireum/B;>;)V
  #286 = Utf8               ()V
  #287 = NameAndType        #250:#286     // "<init>":()V
  #288 = Methodref          #5.#287       // java/lang/Object."<init>":()V
  #289 = NameAndType        #254:#255     // $anonfun$flatMap$1:(Lorg/sireum/MS$WithFilter;Ljava/lang/Object;)Z
  #290 = Methodref          #2.#289       // org/sireum/MS$WithFilter.$anonfun$flatMap$1:(Lorg/sireum/MS$WithFilter;Ljava/lang/Object;)Z
  #291 = Utf8               scala/runtime/BoxesRunTime
  #292 = Class              #291          // scala/runtime/BoxesRunTime
  #293 = Utf8               boxToBoolean
  #294 = Utf8               (Z)Ljava/lang/Boolean;
  #295 = NameAndType        #293:#294     // boxToBoolean:(Z)Ljava/lang/Boolean;
  #296 = Methodref          #292.#295     // scala/runtime/BoxesRunTime.boxToBoolean:(Z)Ljava/lang/Boolean;
  #297 = NameAndType        #258:#259     // $anonfun$flatMap$2:(Lscala/runtime/ObjectRef;Lscala/Function1;Ljava/lang/Object;)V
  #298 = Methodref          #2.#297       // org/sireum/MS$WithFilter.$anonfun$flatMap$2:(Lscala/runtime/ObjectRef;Lscala/Function1;Ljava/lang/Object;)V
  #299 = NameAndType        #270:#271     // $anonfun$withFilter$1:(Lorg/sireum/MS$WithFilter;Lscala/Function1;Ljava/lang/Object;)Z
  #300 = Methodref          #2.#299       // org/sireum/MS$WithFilter.$anonfun$withFilter$1:(Lorg/sireum/MS$WithFilter;Lscala/Function1;Ljava/lang/Object;)Z
  #301 = Utf8               (Z)V
  #302 = NameAndType        #250:#301     // "<init>":(Z)V
  #303 = Methodref          #79.#302      // org/sireum/B."<init>":(Z)V
  #304 = NameAndType        #266:#267     // $anonfun$withFilter$2:(Lscala/Function1;Ljava/lang/Object;)Z
  #305 = Methodref          #2.#304       // org/sireum/MS$WithFilter.$anonfun$withFilter$2:(Lscala/Function1;Ljava/lang/Object;)Z
  #306 = Utf8               $deserializeLambda$
  #307 = Utf8               (Ljava/lang/invoke/SerializedLambda;)Ljava/lang/Object;
  #308 = Utf8               scala/runtime/LambdaDeserialize
  #309 = Class              #308          // scala/runtime/LambdaDeserialize
  #310 = Utf8               bootstrap
  #311 = Utf8               (Ljava/lang/invoke/MethodHandles$Lookup;Ljava/lang/String;Ljava/lang/invoke/MethodType;[Ljava/lang/invoke/MethodHandle;)Ljava/lang/invoke/CallSite;
  #312 = NameAndType        #310:#311     // bootstrap:(Ljava/lang/invoke/MethodHandles$Lookup;Ljava/lang/String;Ljava/lang/invoke/MethodType;[Ljava/lang/invoke/MethodHandle;)Ljava/lang/invoke/CallSite;
  #313 = Methodref          #309.#312     // scala/runtime/LambdaDeserialize.bootstrap:(Ljava/lang/invoke/MethodHandles$Lookup;Ljava/lang/String;Ljava/lang/invoke/MethodType;[Ljava/lang/invoke/MethodHandle;)Ljava/lang/invoke/CallSite;
  #314 = MethodHandle       6:#313        // REF_invokeStatic scala/runtime/LambdaDeserialize.bootstrap:(Ljava/lang/invoke/MethodHandles$Lookup;Ljava/lang/String;Ljava/lang/invoke/MethodType;[Ljava/lang/invoke/MethodHandle;)Ljava/lang/invoke/CallSite;
  #315 = Utf8               lambdaDeserialize
  #316 = NameAndType        #315:#307     // lambdaDeserialize:(Ljava/lang/invoke/SerializedLambda;)Ljava/lang/Object;
  #317 = InvokeDynamic      #4:#316       // #4:lambdaDeserialize:(Ljava/lang/invoke/SerializedLambda;)Ljava/lang/Object;
  #318 = Utf8               Signature
  #319 = Utf8               Code
  #320 = Utf8               StackMapTable
  #321 = Utf8               LineNumberTable
  #322 = Utf8               LocalVariableTable
  #323 = Utf8               MethodParameters
  #324 = Utf8               InnerClasses
  #325 = Utf8               SourceFile
  #326 = Utf8               BootstrapMethods
  #327 = Utf8               ScalaInlineInfo
  #328 = Utf8               Scala
{
  private final org.sireum.MS<I, V> ms;
    descriptor: Lorg/sireum/MS;
    flags: (0x0012) ACC_PRIVATE, ACC_FINAL
    Signature: #22                          // Lorg/sireum/MS<TI;TV;>;

  private final scala.Function1<V, org.sireum.B> p;
    descriptor: Lscala/Function1;
    flags: (0x0012) ACC_PRIVATE, ACC_FINAL
    Signature: #25                          // Lscala/Function1<TV;Lorg/sireum/B;>;

  public <U extends java.lang.Object> void foreach(scala.Function1<V, U>);
    descriptor: (Lscala/Function1;)V
    flags: (0x0001) ACC_PUBLIC
    Code:
      stack=3, locals=4, args_size=2
         0: getstatic     #33                 // Field org/sireum/Z$MP$.MODULE$:Lorg/sireum/Z$MP$;
         3: invokevirtual #37                 // Method org/sireum/Z$MP$.zero:()Lorg/sireum/Z;
         6: astore_2
         7: getstatic     #42                 // Field org/sireum/B$.MODULE$:Lorg/sireum/B$;
        10: aload_2
        11: aload_0
        12: getfield      #44                 // Field ms:Lorg/sireum/MS;
        15: invokevirtual #47                 // Method org/sireum/MS.length:()Lorg/sireum/Z;
        18: invokeinterface #51,  2           // InterfaceMethod org/sireum/Z.$less:(Lorg/sireum/Z;)Z
        23: invokevirtual #55                 // Method org/sireum/B$.$4B:(Z)Z
        26: ifeq          99
        29: aload_0
        30: getfield      #44                 // Field ms:Lorg/sireum/MS;
        33: invokevirtual #59                 // Method org/sireum/MS.boxer:()Lorg/sireum/$internal/Boxer;
        36: aload_0
        37: getfield      #44                 // Field ms:Lorg/sireum/MS;
        40: invokevirtual #63                 // Method org/sireum/MS.data:()Ljava/lang/Object;
        43: aload_2
        44: invokeinterface #69,  3           // InterfaceMethod org/sireum/$internal/Boxer.lookup:(Ljava/lang/Object;Lorg/sireum/Z;)Ljava/lang/Object;
        49: astore_3
        50: getstatic     #42                 // Field org/sireum/B$.MODULE$:Lorg/sireum/B$;
        53: aload_0
        54: getfield      #71                 // Field p:Lscala/Function1;
        57: aload_3
        58: invokeinterface #77,  2           // InterfaceMethod scala/Function1.apply:(Ljava/lang/Object;)Ljava/lang/Object;
        63: checkcast     #79                 // class org/sireum/B
        66: invokevirtual #83                 // Method org/sireum/B.value:()Z
        69: invokevirtual #55                 // Method org/sireum/B$.$4B:(Z)Z
        72: ifeq          85
        75: aload_1
        76: aload_3
        77: invokeinterface #77,  2           // InterfaceMethod scala/Function1.apply:(Ljava/lang/Object;)Ljava/lang/Object;
        82: goto          88
        85: getstatic     #89                 // Field scala/runtime/BoxedUnit.UNIT:Lscala/runtime/BoxedUnit;
        88: pop
        89: aload_2
        90: invokeinterface #92,  1           // InterfaceMethod org/sireum/Z.increase:()Lorg/sireum/Z;
        95: astore_2
        96: goto          7
        99: return
      StackMapTable: number_of_entries = 4
        frame_type = 252 /* append */
          offset_delta = 7
          locals = [ class org/sireum/Z ]
        frame_type = 252 /* append */
          offset_delta = 77
          locals = [ class java/lang/Object ]
        frame_type = 66 /* same_locals_1_stack_item */
          stack = [ class java/lang/Object ]
        frame_type = 250 /* chop */
          offset_delta = 10
      LineNumberTable:
        line 34: 0
        line 35: 7
        line 36: 29
        line 37: 50
        line 38: 75
        line 37: 85
        line 40: 89
        line 35: 96
      LocalVariableTable:
        Start  Length  Slot  Name   Signature
           50      46     3     v   Ljava/lang/Object;
            7      92     2     i   Lorg/sireum/Z;
            0     100     0  this   Lorg/sireum/MS$WithFilter;
            0     100     1     f   Lscala/Function1;
    Signature: #28                          // <U:Ljava/lang/Object;>(Lscala/Function1<TV;TU;>;)V
    MethodParameters:
      Name                           Flags
      f                              final

  public <V2 extends java.lang.Object> org.sireum.MS<I, V2> map(scala.Function1<V, V2>);
    descriptor: (Lscala/Function1;)Lorg/sireum/MS;
    flags: (0x0001) ACC_PUBLIC
    Code:
      stack=5, locals=8, args_size=2
         0: getstatic     #42                 // Field org/sireum/B$.MODULE$:Lorg/sireum/B$;
         3: aload_0
         4: getfield      #44                 // Field ms:Lorg/sireum/MS;
         7: invokevirtual #104                // Method org/sireum/MS.isEmpty:()Z
        10: invokevirtual #55                 // Method org/sireum/B$.$4B:(Z)Z
        13: ifeq          35
        16: getstatic     #109                // Field org/sireum/MS$.MODULE$:Lorg/sireum/MS$;
        19: getstatic     #114                // Field scala/collection/immutable/Nil$.MODULE$:Lscala/collection/immutable/Nil$;
        22: aload_0
        23: getfield      #44                 // Field ms:Lorg/sireum/MS;
        26: invokevirtual #118                // Method org/sireum/MS.companion:()Lorg/sireum/$ZCompanion;
        29: invokevirtual #121                // Method org/sireum/MS$.apply:(Lscala/collection/immutable/Seq;Lorg/sireum/$ZCompanion;)Lorg/sireum/MS;
        32: goto          249
        35: getstatic     #126                // Field scala/Array$.MODULE$:Lscala/Array$;
        38: getstatic     #114                // Field scala/collection/immutable/Nil$.MODULE$:Lscala/collection/immutable/Nil$;
        41: getstatic     #131                // Field scala/reflect/ClassTag$.MODULE$:Lscala/reflect/ClassTag$;
        44: invokevirtual #135                // Method scala/reflect/ClassTag$.Nothing:()Lscala/reflect/ClassTag;
        47: invokevirtual #138                // Method scala/Array$.apply:(Lscala/collection/immutable/Seq;Lscala/reflect/ClassTag;)Ljava/lang/Object;
        50: astore_2
        51: aconst_null
        52: astore_3
        53: getstatic     #33                 // Field org/sireum/Z$MP$.MODULE$:Lorg/sireum/Z$MP$;
        56: invokevirtual #37                 // Method org/sireum/Z$MP$.zero:()Lorg/sireum/Z;
        59: astore        4
        61: getstatic     #33                 // Field org/sireum/Z$MP$.MODULE$:Lorg/sireum/Z$MP$;
        64: invokevirtual #37                 // Method org/sireum/Z$MP$.zero:()Lorg/sireum/Z;
        67: astore        5
        69: getstatic     #42                 // Field org/sireum/B$.MODULE$:Lorg/sireum/B$;
        72: aload         4
        74: aload_0
        75: getfield      #44                 // Field ms:Lorg/sireum/MS;
        78: invokevirtual #47                 // Method org/sireum/MS.length:()Lorg/sireum/Z;
        81: invokeinterface #51,  2           // InterfaceMethod org/sireum/Z.$less:(Lorg/sireum/Z;)Z
        86: invokevirtual #55                 // Method org/sireum/B$.$4B:(Z)Z
        89: ifeq          222
        92: aload_0
        93: getfield      #44                 // Field ms:Lorg/sireum/MS;
        96: invokevirtual #59                 // Method org/sireum/MS.boxer:()Lorg/sireum/$internal/Boxer;
        99: aload_0
       100: getfield      #44                 // Field ms:Lorg/sireum/MS;
       103: invokevirtual #63                 // Method org/sireum/MS.data:()Ljava/lang/Object;
       106: aload         4
       108: invokeinterface #69,  3           // InterfaceMethod org/sireum/$internal/Boxer.lookup:(Ljava/lang/Object;Lorg/sireum/Z;)Ljava/lang/Object;
       113: astore        6
       115: getstatic     #42                 // Field org/sireum/B$.MODULE$:Lorg/sireum/B$;
       118: aload_0
       119: getfield      #71                 // Field p:Lscala/Function1;
       122: aload         6
       124: invokeinterface #77,  2           // InterfaceMethod scala/Function1.apply:(Ljava/lang/Object;)Ljava/lang/Object;
       129: checkcast     #79                 // class org/sireum/B
       132: invokevirtual #83                 // Method org/sireum/B.value:()Z
       135: invokevirtual #55                 // Method org/sireum/B$.$4B:(Z)Z
       138: ifeq          210
       141: aload_1
       142: aload         6
       144: invokeinterface #77,  2           // InterfaceMethod scala/Function1.apply:(Ljava/lang/Object;)Ljava/lang/Object;
       149: astore        7
       151: aload_3
       152: ifnonnull     181
       155: getstatic     #143                // Field org/sireum/$internal/Boxer$.MODULE$:Lorg/sireum/$internal/Boxer$;
       158: aload         7
       160: invokevirtual #146                // Method org/sireum/$internal/Boxer$.boxer:(Ljava/lang/Object;)Lorg/sireum/$internal/Boxer;
       163: astore_3
       164: aload_3
       165: aload_0
       166: getfield      #44                 // Field ms:Lorg/sireum/MS;
       169: invokevirtual #47                 // Method org/sireum/MS.length:()Lorg/sireum/Z;
       172: invokeinterface #150,  2          // InterfaceMethod org/sireum/$internal/Boxer.create:(Lorg/sireum/Z;)Ljava/lang/Object;
       177: astore_2
       178: goto          181
       181: aload_3
       182: aload_2
       183: aload         5
       185: getstatic     #155                // Field org/sireum/helper$.MODULE$:Lorg/sireum/helper$;
       188: aload         7
       190: invokevirtual #158                // Method org/sireum/helper$.assign:(Ljava/lang/Object;)Ljava/lang/Object;
       193: invokeinterface #162,  4          // InterfaceMethod org/sireum/$internal/Boxer.store:(Ljava/lang/Object;Lorg/sireum/Z;Ljava/lang/Object;)V
       198: aload         5
       200: invokeinterface #92,  1           // InterfaceMethod org/sireum/Z.increase:()Lorg/sireum/Z;
       205: astore        5
       207: goto          210
       210: aload         4
       212: invokeinterface #92,  1           // InterfaceMethod org/sireum/Z.increase:()Lorg/sireum/Z;
       217: astore        4
       219: goto          69
       222: getstatic     #109                // Field org/sireum/MS$.MODULE$:Lorg/sireum/MS$;
       225: aload_0
       226: getfield      #44                 // Field ms:Lorg/sireum/MS;
       229: invokevirtual #118                // Method org/sireum/MS.companion:()Lorg/sireum/$ZCompanion;
       232: aload_2
       233: aload         5
       235: aload_3
       236: ifnonnull     245
       239: getstatic     #167                // Field org/sireum/$internal/IdentityBoxer$.MODULE$:Lorg/sireum/$internal/IdentityBoxer$;
       242: goto          246
       245: aload_3
       246: invokevirtual #170                // Method org/sireum/MS$.apply:(Lorg/sireum/$ZCompanion;Ljava/lang/Object;Lorg/sireum/Z;Lorg/sireum/$internal/Boxer;)Lorg/sireum/MS;
       249: areturn
      StackMapTable: number_of_entries = 8
        frame_type = 35 /* same */
        frame_type = 255 /* full_frame */
          offset_delta = 33
          locals = [ class org/sireum/MS$WithFilter, class scala/Function1, class java/lang/Object, class org/sireum/$internal/Boxer, class org/sireum/Z, class org/sireum/Z ]
          stack = []
        frame_type = 253 /* append */
          offset_delta = 111
          locals = [ class java/lang/Object, class java/lang/Object ]
        frame_type = 250 /* chop */
          offset_delta = 28
        frame_type = 250 /* chop */
          offset_delta = 11
        frame_type = 255 /* full_frame */
          offset_delta = 22
          locals = [ class org/sireum/MS$WithFilter, class scala/Function1, class java/lang/Object, class org/sireum/$internal/Boxer, class org/sireum/Z, class org/sireum/Z ]
          stack = [ class org/sireum/MS$, class org/sireum/$ZCompanion, class java/lang/Object, class org/sireum/Z ]
        frame_type = 255 /* full_frame */
          offset_delta = 0
          locals = [ class org/sireum/MS$WithFilter, class scala/Function1, class java/lang/Object, class org/sireum/$internal/Boxer, class org/sireum/Z, class org/sireum/Z ]
          stack = [ class org/sireum/MS$, class org/sireum/$ZCompanion, class java/lang/Object, class org/sireum/Z, class org/sireum/$internal/Boxer ]
        frame_type = 255 /* full_frame */
          offset_delta = 2
          locals = [ class org/sireum/MS$WithFilter, class scala/Function1 ]
          stack = [ class org/sireum/MS ]
      LineNumberTable:
        line 45: 0
        line 47: 35
        line 48: 51
        line 49: 53
        line 50: 61
        line 51: 69
        line 52: 92
        line 53: 115
        line 54: 141
        line 55: 151
        line 56: 155
        line 57: 164
        line 59: 181
        line 60: 198
        line 62: 210
        line 51: 219
        line 64: 222
      LocalVariableTable:
        Start  Length  Slot  Name   Signature
          151      56     7    v2   Ljava/lang/Object;
          115     104     6     v   Ljava/lang/Object;
           51     198     2     a   Ljava/lang/Object;
           53     196     3 boxer2   Lorg/sireum/$internal/Boxer;
           61     188     4     i   Lorg/sireum/Z;
           69     180     5     j   Lorg/sireum/Z;
            0     250     0  this   Lorg/sireum/MS$WithFilter;
            0     250     1     f   Lscala/Function1;
    Signature: #101                         // <V2:Ljava/lang/Object;>(Lscala/Function1<TV;TV2;>;)Lorg/sireum/MS<TI;TV2;>;
    MethodParameters:
      Name                           Flags
      f                              final

  public <V2 extends java.lang.Object> org.sireum.MS<I, V2> flatMap(scala.Function1<V, org.sireum.MS<I, V2>>);
    descriptor: (Lscala/Function1;)Lorg/sireum/MS;
    flags: (0x0001) ACC_PUBLIC
    Code:
      stack=3, locals=4, args_size=2
         0: getstatic     #42                 // Field org/sireum/B$.MODULE$:Lorg/sireum/B$;
         3: aload_0
         4: getfield      #44                 // Field ms:Lorg/sireum/MS;
         7: invokevirtual #104                // Method org/sireum/MS.isEmpty:()Z
        10: invokevirtual #55                 // Method org/sireum/B$.$4B:(Z)Z
        13: ifeq          35
        16: getstatic     #109                // Field org/sireum/MS$.MODULE$:Lorg/sireum/MS$;
        19: getstatic     #114                // Field scala/collection/immutable/Nil$.MODULE$:Lscala/collection/immutable/Nil$;
        22: aload_0
        23: getfield      #44                 // Field ms:Lorg/sireum/MS;
        26: invokevirtual #118                // Method org/sireum/MS.companion:()Lorg/sireum/$ZCompanion;
        29: invokevirtual #121                // Method org/sireum/MS$.apply:(Lscala/collection/immutable/Seq;Lorg/sireum/$ZCompanion;)Lorg/sireum/MS;
        32: goto          99
        35: aload_0
        36: getfield      #44                 // Field ms:Lorg/sireum/MS;
        39: invokevirtual #183                // Method org/sireum/MS.elements:()Lscala/collection/immutable/Seq;
        42: astore_2
        43: aload_1
        44: aload_2
        45: invokeinterface #188,  1          // InterfaceMethod scala/collection/immutable/Seq.head:()Ljava/lang/Object;
        50: invokeinterface #77,  2           // InterfaceMethod scala/Function1.apply:(Ljava/lang/Object;)Ljava/lang/Object;
        55: checkcast     #13                 // class org/sireum/MS
        58: invokestatic  #193                // Method scala/runtime/ObjectRef.create:(Ljava/lang/Object;)Lscala/runtime/ObjectRef;
        61: astore_3
        62: aload_2
        63: invokeinterface #196,  1          // InterfaceMethod scala/collection/immutable/Seq.tail:()Ljava/lang/Object;
        68: checkcast     #198                // class scala/collection/IterableOps
        71: aload_0
        72: invokedynamic #215,  0            // InvokeDynamic #0:apply:(Lorg/sireum/MS$WithFilter;)Lscala/Function1;
        77: invokeinterface #219,  2          // InterfaceMethod scala/collection/IterableOps.withFilter:(Lscala/Function1;)Lscala/collection/WithFilter;
        82: aload_3
        83: aload_1
        84: invokedynamic #227,  0            // InvokeDynamic #1:apply:(Lscala/runtime/ObjectRef;Lscala/Function1;)Lscala/Function1;
        89: invokevirtual #231                // Method scala/collection/WithFilter.foreach:(Lscala/Function1;)V
        92: aload_3
        93: getfield      #234                // Field scala/runtime/ObjectRef.elem:Ljava/lang/Object;
        96: checkcast     #13                 // class org/sireum/MS
        99: areturn
      StackMapTable: number_of_entries = 2
        frame_type = 35 /* same */
        frame_type = 247 /* same_locals_1_stack_item_frame_extended */
          offset_delta = 63
          stack = [ class org/sireum/MS ]
      LineNumberTable:
        line 68: 0
        line 70: 35
        line 71: 43
        line 72: 62
        line 75: 92
      LocalVariableTable:
        Start  Length  Slot  Name   Signature
           43      56     2    es   Lscala/collection/immutable/Seq;
           62      37     3     r   Lscala/runtime/ObjectRef;
            0     100     0  this   Lorg/sireum/MS$WithFilter;
            0     100     1     f   Lscala/Function1;
    Signature: #179                         // <V2:Ljava/lang/Object;>(Lscala/Function1<TV;Lorg/sireum/MS<TI;TV2;>;>;)Lorg/sireum/MS<TI;TV2;>;
    MethodParameters:
      Name                           Flags
      f                              final

  public org.sireum.MS$WithFilter<I, V> withFilter(scala.Function1<V, org.sireum.B>);
    descriptor: (Lscala/Function1;)Lorg/sireum/MS$WithFilter;
    flags: (0x0001) ACC_PUBLIC
    Code:
      stack=5, locals=2, args_size=2
         0: new           #2                  // class org/sireum/MS$WithFilter
         3: dup
         4: aload_0
         5: getfield      #44                 // Field ms:Lorg/sireum/MS;
         8: aload_0
         9: aload_1
        10: invokedynamic #249,  0            // InvokeDynamic #2:apply:(Lorg/sireum/MS$WithFilter;Lscala/Function1;)Lscala/Function1;
        15: invokespecial #253                // Method "<init>":(Lorg/sireum/MS;Lscala/Function1;)V
        18: areturn
      LineNumberTable:
        line 78: 0
      LocalVariableTable:
        Start  Length  Slot  Name   Signature
            0      19     0  this   Lorg/sireum/MS$WithFilter;
            0      19     1    p2   Lscala/Function1;
    Signature: #240                         // (Lscala/Function1<TV;Lorg/sireum/B;>;)Lorg/sireum/MS$WithFilter<TI;TV;>;
    MethodParameters:
      Name                           Flags
      p2                             final

  public static final boolean $anonfun$flatMap$1(org.sireum.MS$WithFilter, java.lang.Object);
    descriptor: (Lorg/sireum/MS$WithFilter;Ljava/lang/Object;)Z
    flags: (0x1019) ACC_PUBLIC, ACC_STATIC, ACC_FINAL, ACC_SYNTHETIC
    Code:
      stack=3, locals=2, args_size=2
         0: getstatic     #42                 // Field org/sireum/B$.MODULE$:Lorg/sireum/B$;
         3: aload_0
         4: getfield      #71                 // Field p:Lscala/Function1;
         7: aload_1
         8: invokeinterface #77,  2           // InterfaceMethod scala/Function1.apply:(Ljava/lang/Object;)Ljava/lang/Object;
        13: checkcast     #79                 // class org/sireum/B
        16: invokevirtual #83                 // Method org/sireum/B.value:()Z
        19: invokevirtual #55                 // Method org/sireum/B$.$4B:(Z)Z
        22: ireturn
      LineNumberTable:
        line 72: 0
      LocalVariableTable:
        Start  Length  Slot  Name   Signature
            0      23     0 $this   Lorg/sireum/MS$WithFilter;
            0      23     1     e   Ljava/lang/Object;
    MethodParameters:
      Name                           Flags
      $this                          final synthetic
      e                              final

  public static final void $anonfun$flatMap$2(scala.runtime.ObjectRef, scala.Function1, java.lang.Object);
    descriptor: (Lscala/runtime/ObjectRef;Lscala/Function1;Ljava/lang/Object;)V
    flags: (0x1019) ACC_PUBLIC, ACC_STATIC, ACC_FINAL, ACC_SYNTHETIC
    Code:
      stack=4, locals=3, args_size=3
         0: aload_0
         1: aload_0
         2: getfield      #234                // Field scala/runtime/ObjectRef.elem:Ljava/lang/Object;
         5: checkcast     #13                 // class org/sireum/MS
         8: aload_1
         9: aload_2
        10: invokeinterface #77,  2           // InterfaceMethod scala/Function1.apply:(Ljava/lang/Object;)Ljava/lang/Object;
        15: checkcast     #13                 // class org/sireum/MS
        18: invokevirtual #265                // Method org/sireum/MS.$plus$plus:(Lorg/sireum/MS;)Lorg/sireum/MS;
        21: putfield      #234                // Field scala/runtime/ObjectRef.elem:Ljava/lang/Object;
        24: return
      LineNumberTable:
        line 73: 0
      LocalVariableTable:
        Start  Length  Slot  Name   Signature
            0      25     0   r$1   Lscala/runtime/ObjectRef;
            0      25     1   f$1   Lscala/Function1;
            0      25     2     e   Ljava/lang/Object;
    MethodParameters:
      Name                           Flags
      r$1                            final
      f$1                            final
      e                              final

  public static final boolean $anonfun$withFilter$2(scala.Function1, java.lang.Object);
    descriptor: (Lscala/Function1;Ljava/lang/Object;)Z
    flags: (0x1019) ACC_PUBLIC, ACC_STATIC, ACC_FINAL, ACC_SYNTHETIC
    Code:
      stack=2, locals=2, args_size=2
         0: aload_0
         1: aload_1
         2: invokeinterface #77,  2           // InterfaceMethod scala/Function1.apply:(Ljava/lang/Object;)Ljava/lang/Object;
         7: checkcast     #79                 // class org/sireum/B
        10: invokevirtual #83                 // Method org/sireum/B.value:()Z
        13: ireturn
      LineNumberTable:
        line 78: 0
      LocalVariableTable:
        Start  Length  Slot  Name   Signature
            0      14     0  p2$1   Lscala/Function1;
            0      14     1   v$1   Ljava/lang/Object;
    MethodParameters:
      Name                           Flags
      p2$1                           final
      v$1                            final

  public static final boolean $anonfun$withFilter$1(org.sireum.MS$WithFilter, scala.Function1, java.lang.Object);
    descriptor: (Lorg/sireum/MS$WithFilter;Lscala/Function1;Ljava/lang/Object;)Z
    flags: (0x1019) ACC_PUBLIC, ACC_STATIC, ACC_FINAL, ACC_SYNTHETIC
    Code:
      stack=4, locals=3, args_size=3
         0: getstatic     #42                 // Field org/sireum/B$.MODULE$:Lorg/sireum/B$;
         3: aload_0
         4: getfield      #71                 // Field p:Lscala/Function1;
         7: aload_2
         8: invokeinterface #77,  2           // InterfaceMethod scala/Function1.apply:(Ljava/lang/Object;)Ljava/lang/Object;
        13: checkcast     #79                 // class org/sireum/B
        16: invokevirtual #83                 // Method org/sireum/B.value:()Z
        19: aload_1
        20: aload_2
        21: invokedynamic #280,  0            // InvokeDynamic #3:apply:(Lscala/Function1;Ljava/lang/Object;)Lscala/Function0;
        26: invokevirtual #284                // Method org/sireum/B$.$amp$amp$extension:(ZLscala/Function0;)Z
        29: ireturn
      LineNumberTable:
        line 78: 3
      LocalVariableTable:
        Start  Length  Slot  Name   Signature
            0      30     0 $this   Lorg/sireum/MS$WithFilter;
            0      30     1  p2$1   Lscala/Function1;
            0      30     2     v   Ljava/lang/Object;
    MethodParameters:
      Name                           Flags
      $this                          final synthetic
      p2$1                           final
      v                              final

  public org.sireum.MS$WithFilter(org.sireum.MS<I, V>, scala.Function1<V, org.sireum.B>);
    descriptor: (Lorg/sireum/MS;Lscala/Function1;)V
    flags: (0x0001) ACC_PUBLIC
    Code:
      stack=2, locals=3, args_size=3
         0: aload_0
         1: aload_1
         2: putfield      #44                 // Field ms:Lorg/sireum/MS;
         5: aload_0
         6: aload_2
         7: putfield      #71                 // Field p:Lscala/Function1;
        10: aload_0
        11: invokespecial #288                // Method java/lang/Object."<init>":()V
        14: return
      LineNumberTable:
        line 32: 0
      LocalVariableTable:
        Start  Length  Slot  Name   Signature
            0      15     0  this   Lorg/sireum/MS$WithFilter;
            0      15     1    ms   Lorg/sireum/MS;
            0      15     2     p   Lscala/Function1;
    Signature: #285                         // (Lorg/sireum/MS<TI;TV;>;Lscala/Function1<TV;Lorg/sireum/B;>;)V
    MethodParameters:
      Name                           Flags
      ms                             final
      p                              final

  public static final java.lang.Object $anonfun$flatMap$1$adapted(org.sireum.MS$WithFilter, java.lang.Object);
    descriptor: (Lorg/sireum/MS$WithFilter;Ljava/lang/Object;)Ljava/lang/Object;
    flags: (0x1019) ACC_PUBLIC, ACC_STATIC, ACC_FINAL, ACC_SYNTHETIC
    Code:
      stack=2, locals=2, args_size=2
         0: aload_0
         1: aload_1
         2: invokestatic  #290                // Method $anonfun$flatMap$1:(Lorg/sireum/MS$WithFilter;Ljava/lang/Object;)Z
         5: invokestatic  #296                // Method scala/runtime/BoxesRunTime.boxToBoolean:(Z)Ljava/lang/Boolean;
         8: areturn
      LineNumberTable:
        line 72: 0
      LocalVariableTable:
        Start  Length  Slot  Name   Signature
            0       9     0 $this   Lorg/sireum/MS$WithFilter;
            0       9     1     e   Ljava/lang/Object;
    MethodParameters:
      Name                           Flags
      $this                          final
      e                              final

  public static final java.lang.Object $anonfun$flatMap$2$adapted(scala.runtime.ObjectRef, scala.Function1, java.lang.Object);
    descriptor: (Lscala/runtime/ObjectRef;Lscala/Function1;Ljava/lang/Object;)Ljava/lang/Object;
    flags: (0x1019) ACC_PUBLIC, ACC_STATIC, ACC_FINAL, ACC_SYNTHETIC
    Code:
      stack=3, locals=3, args_size=3
         0: aload_0
         1: aload_1
         2: aload_2
         3: invokestatic  #298                // Method $anonfun$flatMap$2:(Lscala/runtime/ObjectRef;Lscala/Function1;Ljava/lang/Object;)V
         6: getstatic     #89                 // Field scala/runtime/BoxedUnit.UNIT:Lscala/runtime/BoxedUnit;
         9: areturn
      LineNumberTable:
        line 72: 0
      LocalVariableTable:
        Start  Length  Slot  Name   Signature
            0      10     0   r$1   Lscala/runtime/ObjectRef;
            0      10     1   f$1   Lscala/Function1;
            0      10     2     e   Ljava/lang/Object;
    MethodParameters:
      Name                           Flags
      r$1                            final
      f$1                            final
      e                              final

  public static final java.lang.Object $anonfun$withFilter$1$adapted(org.sireum.MS$WithFilter, scala.Function1, java.lang.Object);
    descriptor: (Lorg/sireum/MS$WithFilter;Lscala/Function1;Ljava/lang/Object;)Ljava/lang/Object;
    flags: (0x1019) ACC_PUBLIC, ACC_STATIC, ACC_FINAL, ACC_SYNTHETIC
    Code:
      stack=5, locals=3, args_size=3
         0: new           #79                 // class org/sireum/B
         3: dup
         4: aload_0
         5: aload_1
         6: aload_2
         7: invokestatic  #300                // Method $anonfun$withFilter$1:(Lorg/sireum/MS$WithFilter;Lscala/Function1;Ljava/lang/Object;)Z
        10: invokespecial #303                // Method org/sireum/B."<init>":(Z)V
        13: areturn
      LineNumberTable:
        line 78: 0
      LocalVariableTable:
        Start  Length  Slot  Name   Signature
            0      14     0 $this   Lorg/sireum/MS$WithFilter;
            0      14     1  p2$1   Lscala/Function1;
            0      14     2     v   Ljava/lang/Object;
    MethodParameters:
      Name                           Flags
      $this                          final
      p2$1                           final
      v                              final

  public static final java.lang.Object $anonfun$withFilter$2$adapted(scala.Function1, java.lang.Object);
    descriptor: (Lscala/Function1;Ljava/lang/Object;)Ljava/lang/Object;
    flags: (0x1019) ACC_PUBLIC, ACC_STATIC, ACC_FINAL, ACC_SYNTHETIC
    Code:
      stack=4, locals=2, args_size=2
         0: new           #79                 // class org/sireum/B
         3: dup
         4: aload_0
         5: aload_1
         6: invokestatic  #305                // Method $anonfun$withFilter$2:(Lscala/Function1;Ljava/lang/Object;)Z
         9: invokespecial #303                // Method org/sireum/B."<init>":(Z)V
        12: areturn
      LineNumberTable:
        line 78: 0
      LocalVariableTable:
        Start  Length  Slot  Name   Signature
            0      13     0  p2$1   Lscala/Function1;
            0      13     1   v$1   Ljava/lang/Object;
    MethodParameters:
      Name                           Flags
      p2$1                           final
      v$1                            final

  private static java.lang.Object $deserializeLambda$(java.lang.invoke.SerializedLambda);
    descriptor: (Ljava/lang/invoke/SerializedLambda;)Ljava/lang/Object;
    flags: (0x100a) ACC_PRIVATE, ACC_STATIC, ACC_SYNTHETIC
    Code:
      stack=1, locals=1, args_size=1
         0: aload_0
         1: invokedynamic #317,  0            // InvokeDynamic #4:lambdaDeserialize:(Ljava/lang/invoke/SerializedLambda;)Ljava/lang/Object;
         6: areturn
}
InnerClasses:
  public static final #11= #8 of #10;     // Lookup=class java/lang/invoke/MethodHandles$Lookup of class java/lang/invoke/MethodHandles
  public static #14= #2 of #13;           // WithFilter=class org/sireum/MS$WithFilter of class org/sireum/MS
  public static #19= #16 of #18;          // MP$=class org/sireum/Z$MP$ of class org/sireum/Z
Signature: #3                           // <I:Ljava/lang/Object;V:Ljava/lang/Object;>Ljava/lang/Object;
SourceFile: "MS.scala"
BootstrapMethods:
  0: #212 REF_invokeStatic java/lang/invoke/LambdaMetafactory.altMetafactory:(Ljava/lang/invoke/MethodHandles$Lookup;Ljava/lang/String;Ljava/lang/invoke/MethodType;[Ljava/lang/Object;)Ljava/lang/invoke/CallSite;
    Method arguments:
      #199 (Ljava/lang/Object;)Ljava/lang/Object;
      #204 REF_invokeStatic org/sireum/MS$WithFilter.$anonfun$flatMap$1$adapted:(Lorg/sireum/MS$WithFilter;Ljava/lang/Object;)Ljava/lang/Object;
      #199 (Ljava/lang/Object;)Ljava/lang/Object;
      #205 1
  1: #212 REF_invokeStatic java/lang/invoke/LambdaMetafactory.altMetafactory:(Ljava/lang/invoke/MethodHandles$Lookup;Ljava/lang/String;Ljava/lang/invoke/MethodType;[Ljava/lang/Object;)Ljava/lang/invoke/CallSite;
    Method arguments:
      #199 (Ljava/lang/Object;)Ljava/lang/Object;
      #224 REF_invokeStatic org/sireum/MS$WithFilter.$anonfun$flatMap$2$adapted:(Lscala/runtime/ObjectRef;Lscala/Function1;Ljava/lang/Object;)Ljava/lang/Object;
      #199 (Ljava/lang/Object;)Ljava/lang/Object;
      #205 1
  2: #212 REF_invokeStatic java/lang/invoke/LambdaMetafactory.altMetafactory:(Ljava/lang/invoke/MethodHandles$Lookup;Ljava/lang/String;Ljava/lang/invoke/MethodType;[Ljava/lang/Object;)Ljava/lang/invoke/CallSite;
    Method arguments:
      #199 (Ljava/lang/Object;)Ljava/lang/Object;
      #246 REF_invokeStatic org/sireum/MS$WithFilter.$anonfun$withFilter$1$adapted:(Lorg/sireum/MS$WithFilter;Lscala/Function1;Ljava/lang/Object;)Ljava/lang/Object;
      #199 (Ljava/lang/Object;)Ljava/lang/Object;
      #205 1
  3: #212 REF_invokeStatic java/lang/invoke/LambdaMetafactory.altMetafactory:(Ljava/lang/invoke/MethodHandles$Lookup;Ljava/lang/String;Ljava/lang/invoke/MethodType;[Ljava/lang/Object;)Ljava/lang/invoke/CallSite;
    Method arguments:
      #272 ()Ljava/lang/Object;
      #277 REF_invokeStatic org/sireum/MS$WithFilter.$anonfun$withFilter$2$adapted:(Lscala/Function1;Ljava/lang/Object;)Ljava/lang/Object;
      #272 ()Ljava/lang/Object;
      #205 1
  4: #314 REF_invokeStatic scala/runtime/LambdaDeserialize.bootstrap:(Ljava/lang/invoke/MethodHandles$Lookup;Ljava/lang/String;Ljava/lang/invoke/MethodType;[Ljava/lang/invoke/MethodHandle;)Ljava/lang/invoke/CallSite;
    Method arguments:
      #204 REF_invokeStatic org/sireum/MS$WithFilter.$anonfun$flatMap$1$adapted:(Lorg/sireum/MS$WithFilter;Ljava/lang/Object;)Ljava/lang/Object;
      #224 REF_invokeStatic org/sireum/MS$WithFilter.$anonfun$flatMap$2$adapted:(Lscala/runtime/ObjectRef;Lscala/Function1;Ljava/lang/Object;)Ljava/lang/Object;
      #246 REF_invokeStatic org/sireum/MS$WithFilter.$anonfun$withFilter$1$adapted:(Lorg/sireum/MS$WithFilter;Lscala/Function1;Ljava/lang/Object;)Ljava/lang/Object;
      #277 REF_invokeStatic org/sireum/MS$WithFilter.$anonfun$withFilter$2$adapted:(Lscala/Function1;Ljava/lang/Object;)Ljava/lang/Object;
  ScalaInlineInfo: length = 0x45 (unknown attribute)
   01 00 00 0D 00 FE 00 FF 01 00 C8 00 C9 01 01 02
   01 03 01 00 DC 00 DD 01 01 0E 01 0F 01 00 F2 00
   F3 01 01 0A 01 0B 01 01 11 01 12 01 00 FA 00 FB
   00 00 B2 00 64 00 00 1A 00 1B 00 00 63 00 64 00
   00 D8 00 EF 00
  Scala: length = 0x0 (unknown attribute)

