Classfile /Users/mw/Projects/slang-braindump/.jar/jar8/assemble/slang-braindump/assemble/content/org/sireum/Option.class
  Last modified May 29, 2022; size 3077 bytes
  SHA-256 checksum a135d384ec7e1ce8facbd45cbee8678ae4d975a6d105fd05e4c91f518c4c002d
  Compiled from "Option.scala"
public interface org.sireum.Option<T extends java.lang.Object> extends org.sireum.DatatypeSig
  minor version: 0
  major version: 52
  flags: (0x0601) ACC_PUBLIC, ACC_INTERFACE, ACC_ABSTRACT
  this_class: #2                          // org/sireum/Option
  super_class: #5                         // java/lang/Object
  interfaces: 1, fields: 0, methods: 14, attributes: 5
Constant pool:
   #1 = Utf8               org/sireum/Option
   #2 = Class              #1             // org/sireum/Option
   #3 = Utf8               <T:Ljava/lang/Object;>Ljava/lang/Object;Lorg/sireum/DatatypeSig;
   #4 = Utf8               java/lang/Object
   #5 = Class              #4             // java/lang/Object
   #6 = Utf8               org/sireum/DatatypeSig
   #7 = Class              #6             // org/sireum/DatatypeSig
   #8 = Utf8               Option.scala
   #9 = Utf8               Lscala/reflect/ScalaSignature;
  #10 = Utf8               bytes
  #11 = Utf8               \u0006\u0005\u0005=s!\u0002\n\u0014\u0011\u0003Ab!\u0002\u000e\u0014\u0011\u0003Y\u0002\"\u0002\u0012\u0002\t\u0003\u0019\u0003\"\u0002\u0013\u0002\t\u0003)\u0003bBA!\u0003\u0011\u0005\u00111\t\u0004\b5M\u0001\n1!\t)\u0011\u0015iS\u0001\"\u0001/\u0011\u0015\u0011T\u0001\"\u00014\u0011\u0015YT\u0001\"\u00014\u0011\u0015iT\u0001\"\u0001?\u0011\u00159V\u0001\"\u0001Y\u0011\u0015\tW\u0001\"\u0001c\u0011\u00159W\u0001\"\u0001i\u0011\u0015YW\u0001\"\u0001m\u0011\u0015qW\u0001\"\u0001p\u0011\u00151X\u0001\"\u0001x\u0011\u0015QX\u0001\"\u0001|\u0011\u001d\ty!\u0002D\u0001\u0003#\taa\u00149uS>t\'B\u0001\u000b\u0016\u0003\u0019\u0019\u0018N]3v[*\ta#A\u0002pe\u001e\u001c\u0001\u0001\u0005\u0002\u001a\u00035\t1C\u0001\u0004PaRLwN\\\n\u0003\u0003q\u0001\"!\b\u0011\u000e\u0003yQ\u0011aH\u0001\u0006g\u000e\fG.Y\u0005\u0003Cy\u0011a!\u00118z%\u00164\u0017A\u0002\u001fj]&$h\bF\u0001\u0019\u0003\u0011\u0019x.\\3\u0016\u0007\u0019\n\u0019\u0004F\u0002(\u0003k\u0001B!G\u0003\u00022U\u0011\u0011FU\n\u0004\u000bqQ\u0003CA\r,\u0013\ta3CA\u0006ECR\fG/\u001f9f\'&<\u0017A\u0002\u0013j]&$H\u0005F\u00010!\ti\u0002\'\u0003\u00022=\t!QK\\5u\u0003\u001dI7/R7qif,\u0012\u0001\u000e\t\u00033UJ!AN\n\u0003\u0003\tC#a\u0002\u001d\u0011\u0005eI\u0014B\u0001\u001e\u0014\u0005\u0011\u0001XO]3\u0002\u00119|g.R7qifD#\u0001\u0003\u001d\u0002\u00075\f\u0007/\u0006\u0002@\u0007R\u0011\u0001\t\u0014\t\u00043\u0015\t\u0005C\u0001\"D\u0019\u0001!Q\u0001R\u0005C\u0002\u0015\u0013!\u0001\u0016\u001a\u0012\u0005\u0019K\u0005CA\u000fH\u0013\tAeDA\u0004O_RD\u0017N\\4\u0011\u0005uQ\u0015BA&\u001f\u0005\r\te.\u001f\u0005\u0006\u001b&\u0001\rAT\u0001\u0002MB!QdT)U\u0013\t\u0001fDA\u0005Gk:\u001cG/[8ocA\u0011!I\u0015\u0003\u0006\'\u0016\u0011\r!\u0012\u0002\u0002)*\u0012\u0011)V\u0016\u0002q!\u0012\u0011\u0002O\u0001\bM2\fG/T1q+\tIF\f\u0006\u0002[;B\u0019\u0011$B.\u0011\u0005\tcF!\u0002#\u000b\u0005\u0004)\u0005\"B\'\u000b\u0001\u0004q\u0006\u0003B\u000fP#~S#AW+)\u0005)A\u0014A\u00024pe\u0006dG\u000e\u0006\u00025G\")Qj\u0003a\u0001IB!QdT)fU\t!T\u000b\u000b\u0002\fq\u00051Q\r_5tiN$\"\u0001N5\t\u000b5c\u0001\u0019\u00013)\u00051A\u0014aA4fiV\t\u0011\u000b\u000b\u0002\u000eq\u0005Iq-\u001a;Pe\u0016c7/\u001a\u000b\u0003#BDa!\u001d\b\u0005\u0002\u0004\u0011\u0018a\u00023fM\u0006,H\u000e\u001e\t\u0004;M\f\u0016B\u0001;\u001f\u0005!a$-\u001f8b[\u0016t\u0004F\u0001\b9\u000399W\r^(s\u000b2\u001cX-R1hKJ$\"!\u0015=\t\u000bE|\u0001\u0019A))\u0005=A\u0014\u0001\u0002;p\u0013N+\u0012\u0001 \t\u0005{\u0006\u0005\u0011K\u0004\u0002\u001a}&\u0011qpE\u0001\ba\u0006\u001c7.Y4f\u0013\u0011\t\u0019!!\u0002\u0003\u0007%\u001b&,\u0003\u0003\u0002\b\u0005%!\u0001\u0004)bG.\fw-\u001a+sC&$(bAA\u0006\'\u0005IA%\u001b8uKJt\u0017\r\u001c\u0015\u0003!a\nqAZ8sK\u0006\u001c\u0007.\u0006\u0003\u0002\u0014\u0005mAcA\u0018\u0002\u0016!1Q*\u0005a\u0001\u0003/\u0001R!H(R\u00033\u00012AQA\u000e\t\u0019\ti\"\u0005b\u0001\u000b\n\ta+K\u0003\u0006\u0003C\t)#C\u0002\u0002$M\u0011AAT8oK&\u0019\u0011qE\n\u0003\tM{W.\u001a\u0015\u0004\u000b\u0005-\u0002cA\r\u0002.%\u0019\u0011qF\n\u0003\u0011\u0011\fG/\u0019;za\u0016\u00042AQA\u001a\t\u0015\u00196A1\u0001F\u0011\u001d\t9d\u0001a\u0001\u0003c\tQA^1mk\u0016D3aAA\u001e!\rI\u0012QH\u0005\u0004\u0003\u007f\u0019\"AC:ue&\u001cG\u000f];sK\u0006!an\u001c8f+\u0011\t)%a\u0013\u0015\u0005\u0005\u001d\u0003\u0003B\r\u0006\u0003\u0013\u00022AQA&\t\u0015\u0019FA1\u0001FQ\r!\u00111\b
  #12 = Utf8               none
  #13 = Utf8               ()Lorg/sireum/Option;
  #14 = Utf8               <T:Ljava/lang/Object;>()Lorg/sireum/Option<TT;>;
  #15 = Utf8               org/sireum/Option$
  #16 = Class              #15            // org/sireum/Option$
  #17 = Utf8               MODULE$
  #18 = Utf8               Lorg/sireum/Option$;
  #19 = NameAndType        #17:#18        // MODULE$:Lorg/sireum/Option$;
  #20 = Fieldref           #16.#19        // org/sireum/Option$.MODULE$:Lorg/sireum/Option$;
  #21 = NameAndType        #12:#13        // none:()Lorg/sireum/Option;
  #22 = Methodref          #16.#21        // org/sireum/Option$.none:()Lorg/sireum/Option;
  #23 = Utf8               some
  #24 = Utf8               (Ljava/lang/Object;)Lorg/sireum/Option;
  #25 = Utf8               <T:Ljava/lang/Object;>(TT;)Lorg/sireum/Option<TT;>;
  #26 = Utf8               value
  #27 = NameAndType        #23:#24        // some:(Ljava/lang/Object;)Lorg/sireum/Option;
  #28 = Methodref          #16.#27        // org/sireum/Option$.some:(Ljava/lang/Object;)Lorg/sireum/Option;
  #29 = Utf8               Ljava/lang/Object;
  #30 = Utf8               isEmpty
  #31 = Utf8               ()Z
  #32 = Utf8               nonEmpty
  #33 = Utf8               map
  #34 = Utf8               (Lscala/Function1;)Lorg/sireum/Option;
  #35 = Utf8               <T2:Ljava/lang/Object;>(Lscala/Function1<TT;TT2;>;)Lorg/sireum/Option<TT2;>;
  #36 = Utf8               f
  #37 = Utf8               flatMap
  #38 = Utf8               <T2:Ljava/lang/Object;>(Lscala/Function1<TT;Lorg/sireum/Option<TT2;>;>;)Lorg/sireum/Option<TT2;>;
  #39 = Utf8               forall
  #40 = Utf8               (Lscala/Function1;)Z
  #41 = Utf8               (Lscala/Function1<TT;Lorg/sireum/B;>;)Z
  #42 = Utf8               exists
  #43 = Utf8               get
  #44 = Utf8               ()Ljava/lang/Object;
  #45 = Utf8               ()TT;
  #46 = Utf8               getOrElse
  #47 = Utf8               (Lscala/Function0;)Ljava/lang/Object;
  #48 = Utf8               (Lscala/Function0<TT;>;)TT;
  #49 = Utf8               default
  #50 = Utf8               getOrElseEager
  #51 = Utf8               (Ljava/lang/Object;)Ljava/lang/Object;
  #52 = Utf8               (TT;)TT;
  #53 = Utf8               toIS
  #54 = Utf8               ()Lorg/sireum/IS;
  #55 = Utf8               ()Lorg/sireum/IS<Lorg/sireum/Z;TT;>;
  #56 = Utf8               foreach
  #57 = Utf8               (Lscala/Function1;)V
  #58 = Utf8               <V:Ljava/lang/Object;>(Lscala/Function1<TT;TV;>;)V
  #59 = Utf8               $init$
  #60 = Utf8               (Lorg/sireum/Option;)V
  #61 = Utf8               $this
  #62 = Utf8               Lorg/sireum/Option;
  #63 = Utf8               Code
  #64 = Utf8               Signature
  #65 = Utf8               LocalVariableTable
  #66 = Utf8               MethodParameters
  #67 = Utf8               LineNumberTable
  #68 = Utf8               SourceFile
  #69 = Utf8               RuntimeVisibleAnnotations
  #70 = Utf8               ScalaInlineInfo
  #71 = Utf8               ScalaSig
{
  public static <T extends java.lang.Object> org.sireum.Option<T> none();
    descriptor: ()Lorg/sireum/Option;
    flags: (0x0009) ACC_PUBLIC, ACC_STATIC
    Code:
      stack=1, locals=0, args_size=0
         0: getstatic     #20                 // Field org/sireum/Option$.MODULE$:Lorg/sireum/Option$;
         3: invokevirtual #22                 // Method org/sireum/Option$.none:()Lorg/sireum/Option;
         6: areturn
    Signature: #14                          // <T:Ljava/lang/Object;>()Lorg/sireum/Option<TT;>;

  public static <T extends java.lang.Object> org.sireum.Option<T> some(T);
    descriptor: (Ljava/lang/Object;)Lorg/sireum/Option;
    flags: (0x0009) ACC_PUBLIC, ACC_STATIC
    Code:
      stack=2, locals=1, args_size=1
         0: getstatic     #20                 // Field org/sireum/Option$.MODULE$:Lorg/sireum/Option$;
         3: aload_0
         4: invokevirtual #28                 // Method org/sireum/Option$.some:(Ljava/lang/Object;)Lorg/sireum/Option;
         7: areturn
      LocalVariableTable:
        Start  Length  Slot  Name   Signature
            0       8     0 value   Ljava/lang/Object;
    Signature: #25                          // <T:Ljava/lang/Object;>(TT;)Lorg/sireum/Option<TT;>;
    MethodParameters:
      Name                           Flags
      value                          final

  public abstract boolean isEmpty();
    descriptor: ()Z
    flags: (0x0401) ACC_PUBLIC, ACC_ABSTRACT

  public abstract boolean nonEmpty();
    descriptor: ()Z
    flags: (0x0401) ACC_PUBLIC, ACC_ABSTRACT

  public abstract <T2 extends java.lang.Object> org.sireum.Option<T2> map(scala.Function1<T, T2>);
    descriptor: (Lscala/Function1;)Lorg/sireum/Option;
    flags: (0x0401) ACC_PUBLIC, ACC_ABSTRACT
    Signature: #35                          // <T2:Ljava/lang/Object;>(Lscala/Function1<TT;TT2;>;)Lorg/sireum/Option<TT2;>;
    MethodParameters:
      Name                           Flags
      f                              final

  public abstract <T2 extends java.lang.Object> org.sireum.Option<T2> flatMap(scala.Function1<T, org.sireum.Option<T2>>);
    descriptor: (Lscala/Function1;)Lorg/sireum/Option;
    flags: (0x0401) ACC_PUBLIC, ACC_ABSTRACT
    Signature: #38                          // <T2:Ljava/lang/Object;>(Lscala/Function1<TT;Lorg/sireum/Option<TT2;>;>;)Lorg/sireum/Option<TT2;>;
    MethodParameters:
      Name                           Flags
      f                              final

  public abstract boolean forall(scala.Function1<T, org.sireum.B>);
    descriptor: (Lscala/Function1;)Z
    flags: (0x0401) ACC_PUBLIC, ACC_ABSTRACT
    Signature: #41                          // (Lscala/Function1<TT;Lorg/sireum/B;>;)Z
    MethodParameters:
      Name                           Flags
      f                              final

  public abstract boolean exists(scala.Function1<T, org.sireum.B>);
    descriptor: (Lscala/Function1;)Z
    flags: (0x0401) ACC_PUBLIC, ACC_ABSTRACT
    Signature: #41                          // (Lscala/Function1<TT;Lorg/sireum/B;>;)Z
    MethodParameters:
      Name                           Flags
      f                              final

  public abstract T get();
    descriptor: ()Ljava/lang/Object;
    flags: (0x0401) ACC_PUBLIC, ACC_ABSTRACT
    Signature: #45                          // ()TT;

  public abstract T getOrElse(scala.Function0<T>);
    descriptor: (Lscala/Function0;)Ljava/lang/Object;
    flags: (0x0401) ACC_PUBLIC, ACC_ABSTRACT
    Signature: #48                          // (Lscala/Function0<TT;>;)TT;
    MethodParameters:
      Name                           Flags
      default                        final

  public abstract T getOrElseEager(T);
    descriptor: (Ljava/lang/Object;)Ljava/lang/Object;
    flags: (0x0401) ACC_PUBLIC, ACC_ABSTRACT
    Signature: #52                          // (TT;)TT;
    MethodParameters:
      Name                           Flags
      default                        final

  public abstract org.sireum.IS<org.sireum.Z, T> toIS();
    descriptor: ()Lorg/sireum/IS;
    flags: (0x0401) ACC_PUBLIC, ACC_ABSTRACT
    Signature: #55                          // ()Lorg/sireum/IS<Lorg/sireum/Z;TT;>;

  public abstract <V extends java.lang.Object> void foreach(scala.Function1<T, V>);
    descriptor: (Lscala/Function1;)V
    flags: (0x0401) ACC_PUBLIC, ACC_ABSTRACT
    Signature: #58                          // <V:Ljava/lang/Object;>(Lscala/Function1<TT;TV;>;)V
    MethodParameters:
      Name                           Flags
      f                              final

  public static void $init$(org.sireum.Option);
    descriptor: (Lorg/sireum/Option;)V
    flags: (0x0009) ACC_PUBLIC, ACC_STATIC
    Code:
      stack=0, locals=1, args_size=1
         0: return
      LineNumberTable:
        line 36: 0
      LocalVariableTable:
        Start  Length  Slot  Name   Signature
            0       1     0 $this   Lorg/sireum/Option;
    MethodParameters:
      Name                           Flags
      $this                          final synthetic
}
Signature: #3                           // <T:Ljava/lang/Object;>Ljava/lang/Object;Lorg/sireum/DatatypeSig;
SourceFile: "Option.scala"
RuntimeVisibleAnnotations:
  0: #9(#10=s#11)
    scala.reflect.ScalaSignature(
      bytes="\u0006\u0005\u0005=s!\u0002\n\u0014\u0011\u0003Ab!\u0002\u000e\u0014\u0011\u0003Y\u0002\"\u0002\u0012\u0002\t\u0003\u0019\u0003\"\u0002\u0013\u0002\t\u0003)\u0003bBA!\u0003\u0011\u0005\u00111\t\u0004\b5M\u0001\n1!\t)\u0011\u0015iS\u0001\"\u0001/\u0011\u0015\u0011T\u0001\"\u00014\u0011\u0015YT\u0001\"\u00014\u0011\u0015iT\u0001\"\u0001?\u0011\u00159V\u0001\"\u0001Y\u0011\u0015\tW\u0001\"\u0001c\u0011\u00159W\u0001\"\u0001i\u0011\u0015YW\u0001\"\u0001m\u0011\u0015qW\u0001\"\u0001p\u0011\u00151X\u0001\"\u0001x\u0011\u0015QX\u0001\"\u0001|\u0011\u001d\ty!\u0002D\u0001\u0003#\taa\u00149uS>t\'B\u0001\u000b\u0016\u0003\u0019\u0019\u0018N]3v[*\ta#A\u0002pe\u001e\u001c\u0001\u0001\u0005\u0002\u001a\u00035\t1C\u0001\u0004PaRLwN\\\n\u0003\u0003q\u0001\"!\b\u0011\u000e\u0003yQ\u0011aH\u0001\u0006g\u000e\fG.Y\u0005\u0003Cy\u0011a!\u00118z%\u00164\u0017A\u0002\u001fj]&$h\bF\u0001\u0019\u0003\u0011\u0019x.\\3\u0016\u0007\u0019\n\u0019\u0004F\u0002(\u0003k\u0001B!G\u0003\u00022U\u0011\u0011FU\n\u0004\u000bqQ\u0003CA\r,\u0013\ta3CA\u0006ECR\fG/\u001f9f\'&<\u0017A\u0002\u0013j]&$H\u0005F\u00010!\ti\u0002\'\u0003\u00022=\t!QK\\5u\u0003\u001dI7/R7qif,\u0012\u0001\u000e\t\u00033UJ!AN\n\u0003\u0003\tC#a\u0002\u001d\u0011\u0005eI\u0014B\u0001\u001e\u0014\u0005\u0011\u0001XO]3\u0002\u00119|g.R7qifD#\u0001\u0003\u001d\u0002\u00075\f\u0007/\u0006\u0002@\u0007R\u0011\u0001\t\u0014\t\u00043\u0015\t\u0005C\u0001\"D\u0019\u0001!Q\u0001R\u0005C\u0002\u0015\u0013!\u0001\u0016\u001a\u0012\u0005\u0019K\u0005CA\u000fH\u0013\tAeDA\u0004O_RD\u0017N\\4\u0011\u0005uQ\u0015BA&\u001f\u0005\r\te.\u001f\u0005\u0006\u001b&\u0001\rAT\u0001\u0002MB!QdT)U\u0013\t\u0001fDA\u0005Gk:\u001cG/[8ocA\u0011!I\u0015\u0003\u0006\'\u0016\u0011\r!\u0012\u0002\u0002)*\u0012\u0011)V\u0016\u0002q!\u0012\u0011\u0002O\u0001\bM2\fG/T1q+\tIF\f\u0006\u0002[;B\u0019\u0011$B.\u0011\u0005\tcF!\u0002#\u000b\u0005\u0004)\u0005\"B\'\u000b\u0001\u0004q\u0006\u0003B\u000fP#~S#AW+)\u0005)A\u0014A\u00024pe\u0006dG\u000e\u0006\u00025G\")Qj\u0003a\u0001IB!QdT)fU\t!T\u000b\u000b\u0002\fq\u00051Q\r_5tiN$\"\u0001N5\t\u000b5c\u0001\u0019\u00013)\u00051A\u0014aA4fiV\t\u0011\u000b\u000b\u0002\u000eq\u0005Iq-\u001a;Pe\u0016c7/\u001a\u000b\u0003#BDa!\u001d\b\u0005\u0002\u0004\u0011\u0018a\u00023fM\u0006,H\u000e\u001e\t\u0004;M\f\u0016B\u0001;\u001f\u0005!a$-\u001f8b[\u0016t\u0004F\u0001\b9\u000399W\r^(s\u000b2\u001cX-R1hKJ$\"!\u0015=\t\u000bE|\u0001\u0019A))\u0005=A\u0014\u0001\u0002;p\u0013N+\u0012\u0001 \t\u0005{\u0006\u0005\u0011K\u0004\u0002\u001a}&\u0011qpE\u0001\ba\u0006\u001c7.Y4f\u0013\u0011\t\u0019!!\u0002\u0003\u0007%\u001b&,\u0003\u0003\u0002\b\u0005%!\u0001\u0004)bG.\fw-\u001a+sC&$(bAA\u0006\'\u0005IA%\u001b8uKJt\u0017\r\u001c\u0015\u0003!a\nqAZ8sK\u0006\u001c\u0007.\u0006\u0003\u0002\u0014\u0005mAcA\u0018\u0002\u0016!1Q*\u0005a\u0001\u0003/\u0001R!H(R\u00033\u00012AQA\u000e\t\u0019\ti\"\u0005b\u0001\u000b\n\ta+K\u0003\u0006\u0003C\t)#C\u0002\u0002$M\u0011AAT8oK&\u0019\u0011qE\n\u0003\tM{W.\u001a\u0015\u0004\u000b\u0005-\u0002cA\r\u0002.%\u0019\u0011qF\n\u0003\u0011\u0011\fG/\u0019;za\u0016\u00042AQA\u001a\t\u0015\u00196A1\u0001F\u0011\u001d\t9d\u0001a\u0001\u0003c\tQA^1mk\u0016D3aAA\u001e!\rI\u0012QH\u0005\u0004\u0003\u007f\u0019\"AC:ue&\u001cG\u000f];sK\u0006!an\u001c8f+\u0011\t)%a\u0013\u0015\u0005\u0005\u001d\u0003\u0003B\r\u0006\u0003\u0013\u00022AQA&\t\u0015\u0019FA1\u0001FQ\r!\u00111\b"
    )
  ScalaInlineInfo: length = 0x40 (unknown attribute)
   01 00 00 0C 00 3B 00 3C 01 00 2A 00 28 00 00 25
   00 22 00 00 27 00 28 00 00 38 00 39 00 00 2B 00
   2C 00 00 2E 00 2F 00 00 32 00 33 00 00 1E 00 1F
   00 00 21 00 22 00 00 20 00 1F 00 00 35 00 36 00

  ScalaSig: length = 0x3 (unknown attribute)
   05 02 00
