Classfile /Users/mw/Projects/slang-braindump/.jar/jar8/assemble/slang-braindump/assemble/content/org/sireum/package$$Char2C$.class
  Last modified May 29, 2022; size 5885 bytes
  SHA-256 checksum 3908ed94e44ef467922cac2c2266db755444fb265268d1f8e6a6ca2e62749b5d
  Compiled from "package.scala"
public class org.sireum.package$$Char2C$
  minor version: 0
  major version: 52
  flags: (0x0021) ACC_PUBLIC, ACC_SUPER
  this_class: #2                          // org/sireum/package$$Char2C$
  super_class: #4                         // java/lang/Object
  interfaces: 0, fields: 1, methods: 25, attributes: 4
Constant pool:
    #1 = Utf8               org/sireum/package$$Char2C$
    #2 = Class              #1            // org/sireum/package$$Char2C$
    #3 = Utf8               java/lang/Object
    #4 = Class              #3            // java/lang/Object
    #5 = Utf8               package.scala
    #6 = Utf8               org/sireum/package$$Char2C
    #7 = Class              #6            // org/sireum/package$$Char2C
    #8 = Utf8               org/sireum/package
    #9 = Class              #8            // org/sireum/package
   #10 = Utf8               $Char2C
   #11 = Utf8               $Char2C$
   #12 = Utf8               org/sireum/package$Any2HashString$
   #13 = Class              #12           // org/sireum/package$Any2HashString$
   #14 = Utf8               Any2HashString$
   #15 = Utf8               MODULE$
   #16 = Utf8               Lorg/sireum/package$$Char2C$;
   #17 = Utf8               <clinit>
   #18 = Utf8               ()V
   #19 = Utf8               <init>
   #20 = NameAndType        #19:#18       // "<init>":()V
   #21 = Methodref          #2.#20        // org/sireum/package$$Char2C$."<init>":()V
   #22 = NameAndType        #15:#16       // MODULE$:Lorg/sireum/package$$Char2C$;
   #23 = Fieldref           #2.#22        // org/sireum/package$$Char2C$.MODULE$:Lorg/sireum/package$$Char2C$;
   #24 = Utf8               hash$extension
   #25 = Utf8               (C)Lorg/sireum/Z;
   #26 = Utf8               $this
   #27 = Utf8               Lorg/sireum/package$Any2HashString$;
   #28 = NameAndType        #15:#27       // MODULE$:Lorg/sireum/package$Any2HashString$;
   #29 = Fieldref           #13.#28       // org/sireum/package$Any2HashString$.MODULE$:Lorg/sireum/package$Any2HashString$;
   #30 = Utf8               org/sireum/package$
   #31 = Class              #30           // org/sireum/package$
   #32 = Utf8               Lorg/sireum/package$;
   #33 = NameAndType        #15:#32       // MODULE$:Lorg/sireum/package$;
   #34 = Fieldref           #31.#33       // org/sireum/package$.MODULE$:Lorg/sireum/package$;
   #35 = Utf8               org/sireum/C
   #36 = Class              #35           // org/sireum/C
   #37 = Utf8               org/sireum/C$
   #38 = Class              #37           // org/sireum/C$
   #39 = Utf8               Lorg/sireum/C$;
   #40 = NameAndType        #15:#39       // MODULE$:Lorg/sireum/C$;
   #41 = Fieldref           #38.#40       // org/sireum/C$.MODULE$:Lorg/sireum/C$;
   #42 = Utf8               apply
   #43 = Utf8               (C)I
   #44 = NameAndType        #42:#43       // apply:(C)I
   #45 = Methodref          #38.#44       // org/sireum/C$.apply:(C)I
   #46 = Utf8               (I)V
   #47 = NameAndType        #19:#46       // "<init>":(I)V
   #48 = Methodref          #36.#47       // org/sireum/C."<init>":(I)V
   #49 = Utf8               Any2HashString
   #50 = Utf8               (Ljava/lang/Object;)Ljava/lang/Object;
   #51 = NameAndType        #49:#50       // Any2HashString:(Ljava/lang/Object;)Ljava/lang/Object;
   #52 = Methodref          #31.#51       // org/sireum/package$.Any2HashString:(Ljava/lang/Object;)Ljava/lang/Object;
   #53 = Utf8               (Ljava/lang/Object;)Lorg/sireum/Z;
   #54 = NameAndType        #24:#53       // hash$extension:(Ljava/lang/Object;)Lorg/sireum/Z;
   #55 = Methodref          #13.#54       // org/sireum/package$Any2HashString$.hash$extension:(Ljava/lang/Object;)Lorg/sireum/Z;
   #56 = Utf8               this
   #57 = Utf8               C
   #58 = Utf8               string$extension
   #59 = Utf8               (C)Ljava/lang/String;
   #60 = Utf8               (I)Ljava/lang/String;
   #61 = NameAndType        #58:#60       // string$extension:(I)Ljava/lang/String;
   #62 = Methodref          #38.#61       // org/sireum/C$.string$extension:(I)Ljava/lang/String;
   #63 = Utf8               $less$extension
   #64 = Utf8               (CI)Z
   #65 = Utf8               other
   #66 = Utf8               (II)Z
   #67 = NameAndType        #63:#66       // $less$extension:(II)Z
   #68 = Methodref          #38.#67       // org/sireum/C$.$less$extension:(II)Z
   #69 = Utf8               I
   #70 = Utf8               $less$eq$extension
   #71 = NameAndType        #70:#66       // $less$eq$extension:(II)Z
   #72 = Methodref          #38.#71       // org/sireum/C$.$less$eq$extension:(II)Z
   #73 = Utf8               $greater$extension
   #74 = NameAndType        #73:#66       // $greater$extension:(II)Z
   #75 = Methodref          #38.#74       // org/sireum/C$.$greater$extension:(II)Z
   #76 = Utf8               $greater$eq$extension
   #77 = NameAndType        #76:#66       // $greater$eq$extension:(II)Z
   #78 = Methodref          #38.#77       // org/sireum/C$.$greater$eq$extension:(II)Z
   #79 = Utf8               $eq$eq$eq$extension
   #80 = Utf8               org/sireum/B$
   #81 = Class              #80           // org/sireum/B$
   #82 = Utf8               Lorg/sireum/B$;
   #83 = NameAndType        #15:#82       // MODULE$:Lorg/sireum/B$;
   #84 = Fieldref           #81.#83       // org/sireum/B$.MODULE$:Lorg/sireum/B$;
   #85 = Utf8               (Z)Z
   #86 = NameAndType        #42:#85       // apply:(Z)Z
   #87 = Methodref          #81.#86       // org/sireum/B$.apply:(Z)Z
   #88 = Utf8               $eq$bang$eq$extension
   #89 = Utf8               $greater$greater$greater$extension
   #90 = Utf8               (CI)I
   #91 = Utf8               (II)I
   #92 = NameAndType        #89:#91       // $greater$greater$greater$extension:(II)I
   #93 = Methodref          #38.#92       // org/sireum/C$.$greater$greater$greater$extension:(II)I
   #94 = Utf8               $less$less$extension
   #95 = NameAndType        #94:#91       // $less$less$extension:(II)I
   #96 = Methodref          #38.#95       // org/sireum/C$.$less$less$extension:(II)I
   #97 = Utf8               $amp$extension
   #98 = NameAndType        #97:#91       // $amp$extension:(II)I
   #99 = Methodref          #38.#98       // org/sireum/C$.$amp$extension:(II)I
  #100 = Utf8               $bar$extension
  #101 = NameAndType        #100:#91      // $bar$extension:(II)I
  #102 = Methodref          #38.#101      // org/sireum/C$.$bar$extension:(II)I
  #103 = Utf8               $bar$up$extension
  #104 = NameAndType        #103:#91      // $bar$up$extension:(II)I
  #105 = Methodref          #38.#104      // org/sireum/C$.$bar$up$extension:(II)I
  #106 = Utf8               $tilde$greater$extension
  #107 = Utf8               (CZ)Lscala/Tuple2;
  #108 = Utf8               (CZ)Lscala/Tuple2<Lorg/sireum/C;Lorg/sireum/B;>;
  #109 = Utf8               o
  #110 = Utf8               scala/Tuple2
  #111 = Class              #110          // scala/Tuple2
  #112 = Utf8               org/sireum/B
  #113 = Class              #112          // org/sireum/B
  #114 = Utf8               (Z)V
  #115 = NameAndType        #19:#114      // "<init>":(Z)V
  #116 = Methodref          #113.#115     // org/sireum/B."<init>":(Z)V
  #117 = Utf8               (Ljava/lang/Object;Ljava/lang/Object;)V
  #118 = NameAndType        #19:#117      // "<init>":(Ljava/lang/Object;Ljava/lang/Object;)V
  #119 = Methodref          #111.#118     // scala/Tuple2."<init>":(Ljava/lang/Object;Ljava/lang/Object;)V
  #120 = Utf8               Z
  #121 = Utf8               (CC)Lscala/Tuple2;
  #122 = Utf8               (CC)Lscala/Tuple2<Lorg/sireum/C;Lorg/sireum/C;>;
  #123 = Utf8               (CI)Lscala/Tuple2;
  #124 = Utf8               (CI)Lscala/Tuple2<Lorg/sireum/C;Lorg/sireum/Z;>;
  #125 = Utf8               org/sireum/Z$
  #126 = Class              #125          // org/sireum/Z$
  #127 = Utf8               Lorg/sireum/Z$;
  #128 = NameAndType        #15:#127      // MODULE$:Lorg/sireum/Z$;
  #129 = Fieldref           #126.#128     // org/sireum/Z$.MODULE$:Lorg/sireum/Z$;
  #130 = Utf8               (I)Lorg/sireum/Z;
  #131 = NameAndType        #42:#130      // apply:(I)Lorg/sireum/Z;
  #132 = Methodref          #126.#131     // org/sireum/Z$.apply:(I)Lorg/sireum/Z;
  #133 = Utf8               (CJ)Lscala/Tuple2;
  #134 = Utf8               (CJ)Lscala/Tuple2<Lorg/sireum/C;Lorg/sireum/Z;>;
  #135 = Utf8               (J)Lorg/sireum/Z;
  #136 = NameAndType        #42:#135      // apply:(J)Lorg/sireum/Z;
  #137 = Methodref          #126.#136     // org/sireum/Z$.apply:(J)Lorg/sireum/Z;
  #138 = Utf8               J
  #139 = Utf8               (CF)Lscala/Tuple2;
  #140 = Utf8               (CF)Lscala/Tuple2<Lorg/sireum/C;Lorg/sireum/F32;>;
  #141 = Utf8               org/sireum/F32
  #142 = Class              #141          // org/sireum/F32
  #143 = Utf8               org/sireum/F32$
  #144 = Class              #143          // org/sireum/F32$
  #145 = Utf8               Lorg/sireum/F32$;
  #146 = NameAndType        #15:#145      // MODULE$:Lorg/sireum/F32$;
  #147 = Fieldref           #144.#146     // org/sireum/F32$.MODULE$:Lorg/sireum/F32$;
  #148 = Utf8               (F)F
  #149 = NameAndType        #42:#148      // apply:(F)F
  #150 = Methodref          #144.#149     // org/sireum/F32$.apply:(F)F
  #151 = Utf8               (F)V
  #152 = NameAndType        #19:#151      // "<init>":(F)V
  #153 = Methodref          #142.#152     // org/sireum/F32."<init>":(F)V
  #154 = Utf8               F
  #155 = Utf8               (CD)Lscala/Tuple2;
  #156 = Utf8               (CD)Lscala/Tuple2<Lorg/sireum/C;Lorg/sireum/F64;>;
  #157 = Utf8               org/sireum/F64
  #158 = Class              #157          // org/sireum/F64
  #159 = Utf8               org/sireum/F64$
  #160 = Class              #159          // org/sireum/F64$
  #161 = Utf8               Lorg/sireum/F64$;
  #162 = NameAndType        #15:#161      // MODULE$:Lorg/sireum/F64$;
  #163 = Fieldref           #160.#162     // org/sireum/F64$.MODULE$:Lorg/sireum/F64$;
  #164 = Utf8               (D)D
  #165 = NameAndType        #42:#164      // apply:(D)D
  #166 = Methodref          #160.#165     // org/sireum/F64$.apply:(D)D
  #167 = Utf8               (D)V
  #168 = NameAndType        #19:#167      // "<init>":(D)V
  #169 = Methodref          #158.#168     // org/sireum/F64."<init>":(D)V
  #170 = Utf8               D
  #171 = Utf8               (CLjava/lang/String;)Lscala/Tuple2;
  #172 = Utf8               (CLjava/lang/String;)Lscala/Tuple2<Lorg/sireum/C;Lorg/sireum/String;>;
  #173 = Utf8               org/sireum/String
  #174 = Class              #173          // org/sireum/String
  #175 = Utf8               org/sireum/String$
  #176 = Class              #175          // org/sireum/String$
  #177 = Utf8               Lorg/sireum/String$;
  #178 = NameAndType        #15:#177      // MODULE$:Lorg/sireum/String$;
  #179 = Fieldref           #176.#178     // org/sireum/String$.MODULE$:Lorg/sireum/String$;
  #180 = Utf8               (Ljava/lang/String;)Ljava/lang/String;
  #181 = NameAndType        #42:#180      // apply:(Ljava/lang/String;)Ljava/lang/String;
  #182 = Methodref          #176.#181     // org/sireum/String$.apply:(Ljava/lang/String;)Ljava/lang/String;
  #183 = Utf8               (Ljava/lang/String;)V
  #184 = NameAndType        #19:#183      // "<init>":(Ljava/lang/String;)V
  #185 = Methodref          #174.#184     // org/sireum/String."<init>":(Ljava/lang/String;)V
  #186 = Utf8               Ljava/lang/String;
  #187 = Utf8               (CLjava/lang/Object;)Lscala/Tuple2;
  #188 = Utf8               <T:Ljava/lang/Object;>(CTT;)Lscala/Tuple2<Lorg/sireum/C;TT;>;
  #189 = Utf8               Ljava/lang/Object;
  #190 = Utf8               hashCode$extension
  #191 = Utf8               java/lang/Character
  #192 = Class              #191          // java/lang/Character
  #193 = Utf8               hashCode
  #194 = NameAndType        #193:#43      // hashCode:(C)I
  #195 = Methodref          #192.#194     // java/lang/Character.hashCode:(C)I
  #196 = Utf8               equals$extension
  #197 = Utf8               (CLjava/lang/Object;)Z
  #198 = Utf8               x$1
  #199 = Utf8               _value
  #200 = Utf8               ()C
  #201 = NameAndType        #199:#200     // _value:()C
  #202 = Methodref          #7.#201       // org/sireum/package$$Char2C._value:()C
  #203 = Methodref          #4.#20        // java/lang/Object."<init>":()V
  #204 = Utf8               Code
  #205 = Utf8               LineNumberTable
  #206 = Utf8               LocalVariableTable
  #207 = Utf8               MethodParameters
  #208 = Utf8               StackMapTable
  #209 = Utf8               Signature
  #210 = Utf8               InnerClasses
  #211 = Utf8               SourceFile
  #212 = Utf8               ScalaInlineInfo
  #213 = Utf8               Scala
{
  public static final org.sireum.package$$Char2C$ MODULE$;
    descriptor: Lorg/sireum/package$$Char2C$;
    flags: (0x0019) ACC_PUBLIC, ACC_STATIC, ACC_FINAL

  public static {};
    descriptor: ()V
    flags: (0x0009) ACC_PUBLIC, ACC_STATIC
    Code:
      stack=2, locals=0, args_size=0
         0: new           #2                  // class org/sireum/package$$Char2C$
         3: dup
         4: invokespecial #21                 // Method "<init>":()V
         7: putstatic     #23                 // Field MODULE$:Lorg/sireum/package$$Char2C$;
        10: return
      LineNumberTable:
        line 164: 0

  public final org.sireum.Z hash$extension(char);
    descriptor: (C)Lorg/sireum/Z;
    flags: (0x0011) ACC_PUBLIC, ACC_FINAL
    Code:
      stack=6, locals=2, args_size=2
         0: getstatic     #29                 // Field org/sireum/package$Any2HashString$.MODULE$:Lorg/sireum/package$Any2HashString$;
         3: getstatic     #34                 // Field org/sireum/package$.MODULE$:Lorg/sireum/package$;
         6: new           #36                 // class org/sireum/C
         9: dup
        10: getstatic     #41                 // Field org/sireum/C$.MODULE$:Lorg/sireum/C$;
        13: iload_1
        14: invokevirtual #45                 // Method org/sireum/C$.apply:(C)I
        17: invokespecial #48                 // Method org/sireum/C."<init>":(I)V
        20: invokevirtual #52                 // Method org/sireum/package$.Any2HashString:(Ljava/lang/Object;)Ljava/lang/Object;
        23: invokevirtual #55                 // Method org/sireum/package$Any2HashString$.hash$extension:(Ljava/lang/Object;)Lorg/sireum/Z;
        26: areturn
      LineNumberTable:
        line 166: 3
      LocalVariableTable:
        Start  Length  Slot  Name   Signature
            0      27     0  this   Lorg/sireum/package$$Char2C$;
            0      27     1 $this   C
    MethodParameters:
      Name                           Flags
      $this                          final

  public final java.lang.String string$extension(char);
    descriptor: (C)Ljava/lang/String;
    flags: (0x0011) ACC_PUBLIC, ACC_FINAL
    Code:
      stack=3, locals=2, args_size=2
         0: getstatic     #41                 // Field org/sireum/C$.MODULE$:Lorg/sireum/C$;
         3: getstatic     #41                 // Field org/sireum/C$.MODULE$:Lorg/sireum/C$;
         6: iload_1
         7: invokevirtual #45                 // Method org/sireum/C$.apply:(C)I
        10: invokevirtual #62                 // Method org/sireum/C$.string$extension:(I)Ljava/lang/String;
        13: areturn
      LineNumberTable:
        line 168: 3
      LocalVariableTable:
        Start  Length  Slot  Name   Signature
            0      14     0  this   Lorg/sireum/package$$Char2C$;
            0      14     1 $this   C
    MethodParameters:
      Name                           Flags
      $this                          final

  public final boolean $less$extension(char, int);
    descriptor: (CI)Z
    flags: (0x0011) ACC_PUBLIC, ACC_FINAL
    Code:
      stack=3, locals=3, args_size=3
         0: getstatic     #41                 // Field org/sireum/C$.MODULE$:Lorg/sireum/C$;
         3: getstatic     #41                 // Field org/sireum/C$.MODULE$:Lorg/sireum/C$;
         6: iload_1
         7: invokevirtual #45                 // Method org/sireum/C$.apply:(C)I
        10: iload_2
        11: invokevirtual #68                 // Method org/sireum/C$.$less$extension:(II)Z
        14: ireturn
      LineNumberTable:
        line 170: 3
      LocalVariableTable:
        Start  Length  Slot  Name   Signature
            0      15     0  this   Lorg/sireum/package$$Char2C$;
            0      15     1 $this   C
            0      15     2 other   I
    MethodParameters:
      Name                           Flags
      $this                          final
      other                          final

  public final boolean $less$eq$extension(char, int);
    descriptor: (CI)Z
    flags: (0x0011) ACC_PUBLIC, ACC_FINAL
    Code:
      stack=3, locals=3, args_size=3
         0: getstatic     #41                 // Field org/sireum/C$.MODULE$:Lorg/sireum/C$;
         3: getstatic     #41                 // Field org/sireum/C$.MODULE$:Lorg/sireum/C$;
         6: iload_1
         7: invokevirtual #45                 // Method org/sireum/C$.apply:(C)I
        10: iload_2
        11: invokevirtual #72                 // Method org/sireum/C$.$less$eq$extension:(II)Z
        14: ireturn
      LineNumberTable:
        line 172: 3
      LocalVariableTable:
        Start  Length  Slot  Name   Signature
            0      15     0  this   Lorg/sireum/package$$Char2C$;
            0      15     1 $this   C
            0      15     2 other   I
    MethodParameters:
      Name                           Flags
      $this                          final
      other                          final

  public final boolean $greater$extension(char, int);
    descriptor: (CI)Z
    flags: (0x0011) ACC_PUBLIC, ACC_FINAL
    Code:
      stack=3, locals=3, args_size=3
         0: getstatic     #41                 // Field org/sireum/C$.MODULE$:Lorg/sireum/C$;
         3: getstatic     #41                 // Field org/sireum/C$.MODULE$:Lorg/sireum/C$;
         6: iload_1
         7: invokevirtual #45                 // Method org/sireum/C$.apply:(C)I
        10: iload_2
        11: invokevirtual #75                 // Method org/sireum/C$.$greater$extension:(II)Z
        14: ireturn
      LineNumberTable:
        line 174: 3
      LocalVariableTable:
        Start  Length  Slot  Name   Signature
            0      15     0  this   Lorg/sireum/package$$Char2C$;
            0      15     1 $this   C
            0      15     2 other   I
    MethodParameters:
      Name                           Flags
      $this                          final
      other                          final

  public final boolean $greater$eq$extension(char, int);
    descriptor: (CI)Z
    flags: (0x0011) ACC_PUBLIC, ACC_FINAL
    Code:
      stack=3, locals=3, args_size=3
         0: getstatic     #41                 // Field org/sireum/C$.MODULE$:Lorg/sireum/C$;
         3: getstatic     #41                 // Field org/sireum/C$.MODULE$:Lorg/sireum/C$;
         6: iload_1
         7: invokevirtual #45                 // Method org/sireum/C$.apply:(C)I
        10: iload_2
        11: invokevirtual #78                 // Method org/sireum/C$.$greater$eq$extension:(II)Z
        14: ireturn
      LineNumberTable:
        line 176: 3
      LocalVariableTable:
        Start  Length  Slot  Name   Signature
            0      15     0  this   Lorg/sireum/package$$Char2C$;
            0      15     1 $this   C
            0      15     2 other   I
    MethodParameters:
      Name                           Flags
      $this                          final
      other                          final

  public final boolean $eq$eq$eq$extension(char, int);
    descriptor: (CI)Z
    flags: (0x0011) ACC_PUBLIC, ACC_FINAL
    Code:
      stack=3, locals=3, args_size=3
         0: getstatic     #84                 // Field org/sireum/B$.MODULE$:Lorg/sireum/B$;
         3: iload_1
         4: iload_2
         5: if_icmpne     12
         8: iconst_1
         9: goto          13
        12: iconst_0
        13: invokevirtual #87                 // Method org/sireum/B$.apply:(Z)Z
        16: ireturn
      StackMapTable: number_of_entries = 2
        frame_type = 76 /* same_locals_1_stack_item */
          stack = [ class org/sireum/B$ ]
        frame_type = 255 /* full_frame */
          offset_delta = 0
          locals = [ class org/sireum/package$$Char2C$, int, int ]
          stack = [ class org/sireum/B$, int ]
      LineNumberTable:
        line 178: 0
      LocalVariableTable:
        Start  Length  Slot  Name   Signature
            0      17     0  this   Lorg/sireum/package$$Char2C$;
            0      17     1 $this   C
            0      17     2 other   I
    MethodParameters:
      Name                           Flags
      $this                          final
      other                          final

  public final boolean $eq$bang$eq$extension(char, int);
    descriptor: (CI)Z
    flags: (0x0011) ACC_PUBLIC, ACC_FINAL
    Code:
      stack=3, locals=3, args_size=3
         0: getstatic     #84                 // Field org/sireum/B$.MODULE$:Lorg/sireum/B$;
         3: iload_1
         4: iload_2
         5: if_icmpeq     12
         8: iconst_1
         9: goto          13
        12: iconst_0
        13: invokevirtual #87                 // Method org/sireum/B$.apply:(Z)Z
        16: ireturn
      StackMapTable: number_of_entries = 2
        frame_type = 76 /* same_locals_1_stack_item */
          stack = [ class org/sireum/B$ ]
        frame_type = 255 /* full_frame */
          offset_delta = 0
          locals = [ class org/sireum/package$$Char2C$, int, int ]
          stack = [ class org/sireum/B$, int ]
      LineNumberTable:
        line 180: 0
      LocalVariableTable:
        Start  Length  Slot  Name   Signature
            0      17     0  this   Lorg/sireum/package$$Char2C$;
            0      17     1 $this   C
            0      17     2 other   I
    MethodParameters:
      Name                           Flags
      $this                          final
      other                          final

  public final int $greater$greater$greater$extension(char, int);
    descriptor: (CI)I
    flags: (0x0011) ACC_PUBLIC, ACC_FINAL
    Code:
      stack=3, locals=3, args_size=3
         0: getstatic     #41                 // Field org/sireum/C$.MODULE$:Lorg/sireum/C$;
         3: getstatic     #41                 // Field org/sireum/C$.MODULE$:Lorg/sireum/C$;
         6: iload_1
         7: invokevirtual #45                 // Method org/sireum/C$.apply:(C)I
        10: iload_2
        11: invokevirtual #93                 // Method org/sireum/C$.$greater$greater$greater$extension:(II)I
        14: ireturn
      LineNumberTable:
        line 182: 3
      LocalVariableTable:
        Start  Length  Slot  Name   Signature
            0      15     0  this   Lorg/sireum/package$$Char2C$;
            0      15     1 $this   C
            0      15     2 other   I
    MethodParameters:
      Name                           Flags
      $this                          final
      other                          final

  public final int $less$less$extension(char, int);
    descriptor: (CI)I
    flags: (0x0011) ACC_PUBLIC, ACC_FINAL
    Code:
      stack=3, locals=3, args_size=3
         0: getstatic     #41                 // Field org/sireum/C$.MODULE$:Lorg/sireum/C$;
         3: getstatic     #41                 // Field org/sireum/C$.MODULE$:Lorg/sireum/C$;
         6: iload_1
         7: invokevirtual #45                 // Method org/sireum/C$.apply:(C)I
        10: iload_2
        11: invokevirtual #96                 // Method org/sireum/C$.$less$less$extension:(II)I
        14: ireturn
      LineNumberTable:
        line 184: 3
      LocalVariableTable:
        Start  Length  Slot  Name   Signature
            0      15     0  this   Lorg/sireum/package$$Char2C$;
            0      15     1 $this   C
            0      15     2 other   I
    MethodParameters:
      Name                           Flags
      $this                          final
      other                          final

  public final int $amp$extension(char, int);
    descriptor: (CI)I
    flags: (0x0011) ACC_PUBLIC, ACC_FINAL
    Code:
      stack=3, locals=3, args_size=3
         0: getstatic     #41                 // Field org/sireum/C$.MODULE$:Lorg/sireum/C$;
         3: getstatic     #41                 // Field org/sireum/C$.MODULE$:Lorg/sireum/C$;
         6: iload_1
         7: invokevirtual #45                 // Method org/sireum/C$.apply:(C)I
        10: iload_2
        11: invokevirtual #99                 // Method org/sireum/C$.$amp$extension:(II)I
        14: ireturn
      LineNumberTable:
        line 186: 3
      LocalVariableTable:
        Start  Length  Slot  Name   Signature
            0      15     0  this   Lorg/sireum/package$$Char2C$;
            0      15     1 $this   C
            0      15     2 other   I
    MethodParameters:
      Name                           Flags
      $this                          final
      other                          final

  public final int $bar$extension(char, int);
    descriptor: (CI)I
    flags: (0x0011) ACC_PUBLIC, ACC_FINAL
    Code:
      stack=3, locals=3, args_size=3
         0: getstatic     #41                 // Field org/sireum/C$.MODULE$:Lorg/sireum/C$;
         3: getstatic     #41                 // Field org/sireum/C$.MODULE$:Lorg/sireum/C$;
         6: iload_1
         7: invokevirtual #45                 // Method org/sireum/C$.apply:(C)I
        10: iload_2
        11: invokevirtual #102                // Method org/sireum/C$.$bar$extension:(II)I
        14: ireturn
      LineNumberTable:
        line 188: 3
      LocalVariableTable:
        Start  Length  Slot  Name   Signature
            0      15     0  this   Lorg/sireum/package$$Char2C$;
            0      15     1 $this   C
            0      15     2 other   I
    MethodParameters:
      Name                           Flags
      $this                          final
      other                          final

  public final int $bar$up$extension(char, int);
    descriptor: (CI)I
    flags: (0x0011) ACC_PUBLIC, ACC_FINAL
    Code:
      stack=3, locals=3, args_size=3
         0: getstatic     #41                 // Field org/sireum/C$.MODULE$:Lorg/sireum/C$;
         3: getstatic     #41                 // Field org/sireum/C$.MODULE$:Lorg/sireum/C$;
         6: iload_1
         7: invokevirtual #45                 // Method org/sireum/C$.apply:(C)I
        10: iload_2
        11: invokevirtual #105                // Method org/sireum/C$.$bar$up$extension:(II)I
        14: ireturn
      LineNumberTable:
        line 190: 3
      LocalVariableTable:
        Start  Length  Slot  Name   Signature
            0      15     0  this   Lorg/sireum/package$$Char2C$;
            0      15     1 $this   C
            0      15     2 other   I
    MethodParameters:
      Name                           Flags
      $this                          final
      other                          final

  public final scala.Tuple2<org.sireum.C, org.sireum.B> $tilde$greater$extension(char, boolean);
    descriptor: (CZ)Lscala/Tuple2;
    flags: (0x0011) ACC_PUBLIC, ACC_FINAL
    Code:
      stack=7, locals=3, args_size=3
         0: new           #111                // class scala/Tuple2
         3: dup
         4: new           #36                 // class org/sireum/C
         7: dup
         8: getstatic     #41                 // Field org/sireum/C$.MODULE$:Lorg/sireum/C$;
        11: iload_1
        12: invokevirtual #45                 // Method org/sireum/C$.apply:(C)I
        15: invokespecial #48                 // Method org/sireum/C."<init>":(I)V
        18: new           #113                // class org/sireum/B
        21: dup
        22: getstatic     #84                 // Field org/sireum/B$.MODULE$:Lorg/sireum/B$;
        25: iload_2
        26: invokevirtual #87                 // Method org/sireum/B$.apply:(Z)Z
        29: invokespecial #116                // Method org/sireum/B."<init>":(Z)V
        32: invokespecial #119                // Method scala/Tuple2."<init>":(Ljava/lang/Object;Ljava/lang/Object;)V
        35: areturn
      LineNumberTable:
        line 192: 0
      LocalVariableTable:
        Start  Length  Slot  Name   Signature
            0      36     0  this   Lorg/sireum/package$$Char2C$;
            0      36     1 $this   C
            0      36     2     o   Z
    Signature: #108                         // (CZ)Lscala/Tuple2<Lorg/sireum/C;Lorg/sireum/B;>;
    MethodParameters:
      Name                           Flags
      $this                          final
      o                              final

  public final scala.Tuple2<org.sireum.C, org.sireum.C> $tilde$greater$extension(char, char);
    descriptor: (CC)Lscala/Tuple2;
    flags: (0x0011) ACC_PUBLIC, ACC_FINAL
    Code:
      stack=7, locals=3, args_size=3
         0: new           #111                // class scala/Tuple2
         3: dup
         4: new           #36                 // class org/sireum/C
         7: dup
         8: getstatic     #41                 // Field org/sireum/C$.MODULE$:Lorg/sireum/C$;
        11: iload_1
        12: invokevirtual #45                 // Method org/sireum/C$.apply:(C)I
        15: invokespecial #48                 // Method org/sireum/C."<init>":(I)V
        18: new           #36                 // class org/sireum/C
        21: dup
        22: getstatic     #41                 // Field org/sireum/C$.MODULE$:Lorg/sireum/C$;
        25: iload_2
        26: invokevirtual #45                 // Method org/sireum/C$.apply:(C)I
        29: invokespecial #48                 // Method org/sireum/C."<init>":(I)V
        32: invokespecial #119                // Method scala/Tuple2."<init>":(Ljava/lang/Object;Ljava/lang/Object;)V
        35: areturn
      LineNumberTable:
        line 194: 0
      LocalVariableTable:
        Start  Length  Slot  Name   Signature
            0      36     0  this   Lorg/sireum/package$$Char2C$;
            0      36     1 $this   C
            0      36     2     o   C
    Signature: #122                         // (CC)Lscala/Tuple2<Lorg/sireum/C;Lorg/sireum/C;>;
    MethodParameters:
      Name                           Flags
      $this                          final
      o                              final

  public final scala.Tuple2<org.sireum.C, org.sireum.Z> $tilde$greater$extension(char, int);
    descriptor: (CI)Lscala/Tuple2;
    flags: (0x0011) ACC_PUBLIC, ACC_FINAL
    Code:
      stack=6, locals=3, args_size=3
         0: new           #111                // class scala/Tuple2
         3: dup
         4: new           #36                 // class org/sireum/C
         7: dup
         8: getstatic     #41                 // Field org/sireum/C$.MODULE$:Lorg/sireum/C$;
        11: iload_1
        12: invokevirtual #45                 // Method org/sireum/C$.apply:(C)I
        15: invokespecial #48                 // Method org/sireum/C."<init>":(I)V
        18: getstatic     #129                // Field org/sireum/Z$.MODULE$:Lorg/sireum/Z$;
        21: iload_2
        22: invokevirtual #132                // Method org/sireum/Z$.apply:(I)Lorg/sireum/Z;
        25: invokespecial #119                // Method scala/Tuple2."<init>":(Ljava/lang/Object;Ljava/lang/Object;)V
        28: areturn
      LineNumberTable:
        line 196: 0
      LocalVariableTable:
        Start  Length  Slot  Name   Signature
            0      29     0  this   Lorg/sireum/package$$Char2C$;
            0      29     1 $this   C
            0      29     2     o   I
    Signature: #124                         // (CI)Lscala/Tuple2<Lorg/sireum/C;Lorg/sireum/Z;>;
    MethodParameters:
      Name                           Flags
      $this                          final
      o                              final

  public final scala.Tuple2<org.sireum.C, org.sireum.Z> $tilde$greater$extension(char, long);
    descriptor: (CJ)Lscala/Tuple2;
    flags: (0x0011) ACC_PUBLIC, ACC_FINAL
    Code:
      stack=6, locals=4, args_size=3
         0: new           #111                // class scala/Tuple2
         3: dup
         4: new           #36                 // class org/sireum/C
         7: dup
         8: getstatic     #41                 // Field org/sireum/C$.MODULE$:Lorg/sireum/C$;
        11: iload_1
        12: invokevirtual #45                 // Method org/sireum/C$.apply:(C)I
        15: invokespecial #48                 // Method org/sireum/C."<init>":(I)V
        18: getstatic     #129                // Field org/sireum/Z$.MODULE$:Lorg/sireum/Z$;
        21: lload_2
        22: invokevirtual #137                // Method org/sireum/Z$.apply:(J)Lorg/sireum/Z;
        25: invokespecial #119                // Method scala/Tuple2."<init>":(Ljava/lang/Object;Ljava/lang/Object;)V
        28: areturn
      LineNumberTable:
        line 198: 0
      LocalVariableTable:
        Start  Length  Slot  Name   Signature
            0      29     0  this   Lorg/sireum/package$$Char2C$;
            0      29     1 $this   C
            0      29     2     o   J
    Signature: #134                         // (CJ)Lscala/Tuple2<Lorg/sireum/C;Lorg/sireum/Z;>;
    MethodParameters:
      Name                           Flags
      $this                          final
      o                              final

  public final scala.Tuple2<org.sireum.C, org.sireum.F32> $tilde$greater$extension(char, float);
    descriptor: (CF)Lscala/Tuple2;
    flags: (0x0011) ACC_PUBLIC, ACC_FINAL
    Code:
      stack=7, locals=3, args_size=3
         0: new           #111                // class scala/Tuple2
         3: dup
         4: new           #36                 // class org/sireum/C
         7: dup
         8: getstatic     #41                 // Field org/sireum/C$.MODULE$:Lorg/sireum/C$;
        11: iload_1
        12: invokevirtual #45                 // Method org/sireum/C$.apply:(C)I
        15: invokespecial #48                 // Method org/sireum/C."<init>":(I)V
        18: new           #142                // class org/sireum/F32
        21: dup
        22: getstatic     #147                // Field org/sireum/F32$.MODULE$:Lorg/sireum/F32$;
        25: fload_2
        26: invokevirtual #150                // Method org/sireum/F32$.apply:(F)F
        29: invokespecial #153                // Method org/sireum/F32."<init>":(F)V
        32: invokespecial #119                // Method scala/Tuple2."<init>":(Ljava/lang/Object;Ljava/lang/Object;)V
        35: areturn
      LineNumberTable:
        line 200: 0
      LocalVariableTable:
        Start  Length  Slot  Name   Signature
            0      36     0  this   Lorg/sireum/package$$Char2C$;
            0      36     1 $this   C
            0      36     2     o   F
    Signature: #140                         // (CF)Lscala/Tuple2<Lorg/sireum/C;Lorg/sireum/F32;>;
    MethodParameters:
      Name                           Flags
      $this                          final
      o                              final

  public final scala.Tuple2<org.sireum.C, org.sireum.F64> $tilde$greater$extension(char, double);
    descriptor: (CD)Lscala/Tuple2;
    flags: (0x0011) ACC_PUBLIC, ACC_FINAL
    Code:
      stack=8, locals=4, args_size=3
         0: new           #111                // class scala/Tuple2
         3: dup
         4: new           #36                 // class org/sireum/C
         7: dup
         8: getstatic     #41                 // Field org/sireum/C$.MODULE$:Lorg/sireum/C$;
        11: iload_1
        12: invokevirtual #45                 // Method org/sireum/C$.apply:(C)I
        15: invokespecial #48                 // Method org/sireum/C."<init>":(I)V
        18: new           #158                // class org/sireum/F64
        21: dup
        22: getstatic     #163                // Field org/sireum/F64$.MODULE$:Lorg/sireum/F64$;
        25: dload_2
        26: invokevirtual #166                // Method org/sireum/F64$.apply:(D)D
        29: invokespecial #169                // Method org/sireum/F64."<init>":(D)V
        32: invokespecial #119                // Method scala/Tuple2."<init>":(Ljava/lang/Object;Ljava/lang/Object;)V
        35: areturn
      LineNumberTable:
        line 202: 0
      LocalVariableTable:
        Start  Length  Slot  Name   Signature
            0      36     0  this   Lorg/sireum/package$$Char2C$;
            0      36     1 $this   C
            0      36     2     o   D
    Signature: #156                         // (CD)Lscala/Tuple2<Lorg/sireum/C;Lorg/sireum/F64;>;
    MethodParameters:
      Name                           Flags
      $this                          final
      o                              final

  public final scala.Tuple2<org.sireum.C, org.sireum.String> $tilde$greater$extension(char, java.lang.String);
    descriptor: (CLjava/lang/String;)Lscala/Tuple2;
    flags: (0x0011) ACC_PUBLIC, ACC_FINAL
    Code:
      stack=7, locals=3, args_size=3
         0: new           #111                // class scala/Tuple2
         3: dup
         4: new           #36                 // class org/sireum/C
         7: dup
         8: getstatic     #41                 // Field org/sireum/C$.MODULE$:Lorg/sireum/C$;
        11: iload_1
        12: invokevirtual #45                 // Method org/sireum/C$.apply:(C)I
        15: invokespecial #48                 // Method org/sireum/C."<init>":(I)V
        18: new           #174                // class org/sireum/String
        21: dup
        22: getstatic     #179                // Field org/sireum/String$.MODULE$:Lorg/sireum/String$;
        25: aload_2
        26: invokevirtual #182                // Method org/sireum/String$.apply:(Ljava/lang/String;)Ljava/lang/String;
        29: invokespecial #185                // Method org/sireum/String."<init>":(Ljava/lang/String;)V
        32: invokespecial #119                // Method scala/Tuple2."<init>":(Ljava/lang/Object;Ljava/lang/Object;)V
        35: areturn
      LineNumberTable:
        line 204: 0
      LocalVariableTable:
        Start  Length  Slot  Name   Signature
            0      36     0  this   Lorg/sireum/package$$Char2C$;
            0      36     1 $this   C
            0      36     2     o   Ljava/lang/String;
    Signature: #172                         // (CLjava/lang/String;)Lscala/Tuple2<Lorg/sireum/C;Lorg/sireum/String;>;
    MethodParameters:
      Name                           Flags
      $this                          final
      o                              final

  public final <T extends java.lang.Object> scala.Tuple2<org.sireum.C, T> $tilde$greater$extension(char, T);
    descriptor: (CLjava/lang/Object;)Lscala/Tuple2;
    flags: (0x0011) ACC_PUBLIC, ACC_FINAL
    Code:
      stack=6, locals=3, args_size=3
         0: new           #111                // class scala/Tuple2
         3: dup
         4: new           #36                 // class org/sireum/C
         7: dup
         8: getstatic     #41                 // Field org/sireum/C$.MODULE$:Lorg/sireum/C$;
        11: iload_1
        12: invokevirtual #45                 // Method org/sireum/C$.apply:(C)I
        15: invokespecial #48                 // Method org/sireum/C."<init>":(I)V
        18: aload_2
        19: invokespecial #119                // Method scala/Tuple2."<init>":(Ljava/lang/Object;Ljava/lang/Object;)V
        22: areturn
      LineNumberTable:
        line 206: 0
      LocalVariableTable:
        Start  Length  Slot  Name   Signature
            0      23     0  this   Lorg/sireum/package$$Char2C$;
            0      23     1 $this   C
            0      23     2     o   Ljava/lang/Object;
    Signature: #188                         // <T:Ljava/lang/Object;>(CTT;)Lscala/Tuple2<Lorg/sireum/C;TT;>;
    MethodParameters:
      Name                           Flags
      $this                          final
      o                              final

  public final int hashCode$extension(char);
    descriptor: (C)I
    flags: (0x0011) ACC_PUBLIC, ACC_FINAL
    Code:
      stack=1, locals=2, args_size=2
         0: iload_1
         1: invokestatic  #195                // Method java/lang/Character.hashCode:(C)I
         4: ireturn
      LineNumberTable:
        line 164: 0
      LocalVariableTable:
        Start  Length  Slot  Name   Signature
            0       5     0  this   Lorg/sireum/package$$Char2C$;
            0       5     1 $this   C
    MethodParameters:
      Name                           Flags
      $this                          final

  public final boolean equals$extension(char, java.lang.Object);
    descriptor: (CLjava/lang/Object;)Z
    flags: (0x0011) ACC_PUBLIC, ACC_FINAL
    Code:
      stack=2, locals=6, args_size=3
         0: aload_2
         1: astore        4
         3: aload         4
         5: instanceof    #7                  // class org/sireum/package$$Char2C
         8: ifeq          16
        11: iconst_1
        12: istore_3
        13: goto          24
        16: goto          19
        19: iconst_0
        20: istore_3
        21: goto          24
        24: iload_3
        25: ifeq          55
        28: aload_2
        29: checkcast     #7                  // class org/sireum/package$$Char2C
        32: invokevirtual #202                // Method org/sireum/package$$Char2C._value:()C
        35: istore        5
        37: iload_1
        38: iload         5
        40: if_icmpne     47
        43: iconst_1
        44: goto          48
        47: iconst_0
        48: ifeq          55
        51: iconst_1
        52: goto          56
        55: iconst_0
        56: ireturn
      StackMapTable: number_of_entries = 7
        frame_type = 253 /* append */
          offset_delta = 16
          locals = [ top, class java/lang/Object ]
        frame_type = 2 /* same */
        frame_type = 255 /* full_frame */
          offset_delta = 4
          locals = [ class org/sireum/package$$Char2C$, int, class java/lang/Object, int, class java/lang/Object ]
          stack = []
        frame_type = 252 /* append */
          offset_delta = 22
          locals = [ int ]
        frame_type = 64 /* same_locals_1_stack_item */
          stack = [ int ]
        frame_type = 250 /* chop */
          offset_delta = 6
        frame_type = 64 /* same_locals_1_stack_item */
          stack = [ int ]
      LineNumberTable:
        line 164: 0
      LocalVariableTable:
        Start  Length  Slot  Name   Signature
            0      57     0  this   Lorg/sireum/package$$Char2C$;
            0      57     1 $this   C
            0      57     2   x$1   Ljava/lang/Object;
    MethodParameters:
      Name                           Flags
      $this                          final
      x$1                            final

  public org.sireum.package$$Char2C$();
    descriptor: ()V
    flags: (0x0001) ACC_PUBLIC
    Code:
      stack=1, locals=1, args_size=1
         0: aload_0
         1: invokespecial #203                // Method java/lang/Object."<init>":()V
         4: return
      LineNumberTable:
        line 164: 0
      LocalVariableTable:
        Start  Length  Slot  Name   Signature
            0       5     0  this   Lorg/sireum/package$$Char2C$;
}
InnerClasses:
  public static final #10= #7 of #9;      // $Char2C=class org/sireum/package$$Char2C of class org/sireum/package
  public static #11= #2 of #9;            // $Char2C$=class org/sireum/package$$Char2C$ of class org/sireum/package
  public static #14= #13 of #9;           // Any2HashString$=class org/sireum/package$Any2HashString$ of class org/sireum/package
SourceFile: "package.scala"
  ScalaInlineInfo: length = 0x7C (unknown attribute)
   01 01 00 18 00 61 00 5A 05 00 64 00 5A 05 00 67
   00 5A 05 00 58 00 40 05 00 4F 00 40 05 00 4C 00
   40 05 00 49 00 40 05 00 59 00 5A 05 00 46 00 40
   05 00 3F 00 40 05 00 5E 00 5A 05 00 6A 00 79 05
   00 6A 00 9B 05 00 6A 00 8B 05 00 6A 00 7B 05 00
   6A 00 85 05 00 6A 00 BB 05 00 6A 00 AB 05 00 6A
   00 6B 05 00 13 00 12 01 00 C4 00 C5 01 00 18 00
   19 05 00 BE 00 2B 01 00 3A 00 3B 05
  Scala: length = 0x0 (unknown attribute)

