Classfile /Users/mw/Projects/slang-braindump/.jar/jar8/assemble/slang-braindump/assemble/content/org/sireum/package$$PredefString2String$.class
  Last modified May 29, 2022; size 6664 bytes
  SHA-256 checksum 83aab0de586b4a188be7eae10b471a4ab8649c3b1b30cb98ddccd03e15f3deb9
  Compiled from "package.scala"
public class org.sireum.package$$PredefString2String$
  minor version: 0
  major version: 52
  flags: (0x0021) ACC_PUBLIC, ACC_SUPER
  this_class: #2                          // org/sireum/package$$PredefString2String$
  super_class: #4                         // java/lang/Object
  interfaces: 0, fields: 1, methods: 23, attributes: 4
Constant pool:
    #1 = Utf8               org/sireum/package$$PredefString2String$
    #2 = Class              #1            // org/sireum/package$$PredefString2String$
    #3 = Utf8               java/lang/Object
    #4 = Class              #3            // java/lang/Object
    #5 = Utf8               package.scala
    #6 = Utf8               org/sireum/package$$PredefString2String
    #7 = Class              #6            // org/sireum/package$$PredefString2String
    #8 = Utf8               org/sireum/package
    #9 = Class              #8            // org/sireum/package
   #10 = Utf8               $PredefString2String
   #11 = Utf8               $PredefString2String$
   #12 = Utf8               org/sireum/package$Any2HashString$
   #13 = Class              #12           // org/sireum/package$Any2HashString$
   #14 = Utf8               Any2HashString$
   #15 = Utf8               MODULE$
   #16 = Utf8               Lorg/sireum/package$$PredefString2String$;
   #17 = Utf8               <clinit>
   #18 = Utf8               ()V
   #19 = Utf8               <init>
   #20 = NameAndType        #19:#18       // "<init>":()V
   #21 = Methodref          #2.#20        // org/sireum/package$$PredefString2String$."<init>":()V
   #22 = NameAndType        #15:#16       // MODULE$:Lorg/sireum/package$$PredefString2String$;
   #23 = Fieldref           #2.#22        // org/sireum/package$$PredefString2String$.MODULE$:Lorg/sireum/package$$PredefString2String$;
   #24 = Utf8               apply$extension
   #25 = Utf8               (Ljava/lang/String;Ljava/lang/Object;)Lscala/runtime/Nothing$;
   #26 = Utf8               $this
   #27 = Utf8               arg
   #28 = Utf8               org/sireum/package$
   #29 = Class              #28           // org/sireum/package$
   #30 = Utf8               Lorg/sireum/package$;
   #31 = NameAndType        #15:#30       // MODULE$:Lorg/sireum/package$;
   #32 = Fieldref           #29.#31       // org/sireum/package$.MODULE$:Lorg/sireum/package$;
   #33 = Utf8
   #34 = String             #33           //
   #35 = Utf8               halt
   #36 = Utf8               (Ljava/lang/Object;)Lscala/runtime/Nothing$;
   #37 = NameAndType        #35:#36       // halt:(Ljava/lang/Object;)Lscala/runtime/Nothing$;
   #38 = Methodref          #29.#37       // org/sireum/package$.halt:(Ljava/lang/Object;)Lscala/runtime/Nothing$;
   #39 = Utf8               this
   #40 = Utf8               Ljava/lang/String;
   #41 = Utf8               Ljava/lang/Object;
   #42 = Utf8               (Ljava/lang/String;Z)Lscala/runtime/Nothing$;
   #43 = Utf8               Z
   #44 = Utf8               (Ljava/lang/String;B)Lscala/runtime/Nothing$;
   #45 = Utf8               B
   #46 = Utf8               (Ljava/lang/String;S)Lscala/runtime/Nothing$;
   #47 = Utf8               S
   #48 = Utf8               (Ljava/lang/String;C)Lscala/runtime/Nothing$;
   #49 = Utf8               C
   #50 = Utf8               (Ljava/lang/String;Ljava/lang/Object;Ljava/lang/Object;Lscala/collection/immutable/Seq;)Lscala/runtime/Nothing$;
   #51 = Utf8               (Ljava/lang/String;Ljava/lang/Object;Ljava/lang/Object;Lscala/collection/immutable/Seq<Ljava/lang/Object;>;)Lscala/runtime/Nothing$;
   #52 = Utf8               arg0
   #53 = Utf8               arg1
   #54 = Utf8               args
   #55 = Utf8               Lscala/collection/immutable/Seq;
   #56 = Utf8               hash$extension
   #57 = Utf8               (Ljava/lang/String;)Lorg/sireum/Z;
   #58 = Utf8               Lorg/sireum/package$Any2HashString$;
   #59 = NameAndType        #15:#58       // MODULE$:Lorg/sireum/package$Any2HashString$;
   #60 = Fieldref           #13.#59       // org/sireum/package$Any2HashString$.MODULE$:Lorg/sireum/package$Any2HashString$;
   #61 = Utf8               org/sireum/String
   #62 = Class              #61           // org/sireum/String
   #63 = Utf8               org/sireum/String$
   #64 = Class              #63           // org/sireum/String$
   #65 = Utf8               Lorg/sireum/String$;
   #66 = NameAndType        #15:#65       // MODULE$:Lorg/sireum/String$;
   #67 = Fieldref           #64.#66       // org/sireum/String$.MODULE$:Lorg/sireum/String$;
   #68 = Utf8               apply
   #69 = Utf8               (Ljava/lang/String;)Ljava/lang/String;
   #70 = NameAndType        #68:#69       // apply:(Ljava/lang/String;)Ljava/lang/String;
   #71 = Methodref          #64.#70       // org/sireum/String$.apply:(Ljava/lang/String;)Ljava/lang/String;
   #72 = Utf8               (Ljava/lang/String;)V
   #73 = NameAndType        #19:#72       // "<init>":(Ljava/lang/String;)V
   #74 = Methodref          #62.#73       // org/sireum/String."<init>":(Ljava/lang/String;)V
   #75 = Utf8               Any2HashString
   #76 = Utf8               (Ljava/lang/Object;)Ljava/lang/Object;
   #77 = NameAndType        #75:#76       // Any2HashString:(Ljava/lang/Object;)Ljava/lang/Object;
   #78 = Methodref          #29.#77       // org/sireum/package$.Any2HashString:(Ljava/lang/Object;)Ljava/lang/Object;
   #79 = Utf8               (Ljava/lang/Object;)Lorg/sireum/Z;
   #80 = NameAndType        #56:#79       // hash$extension:(Ljava/lang/Object;)Lorg/sireum/Z;
   #81 = Methodref          #13.#80       // org/sireum/package$Any2HashString$.hash$extension:(Ljava/lang/Object;)Lorg/sireum/Z;
   #82 = Utf8               string$extension
   #83 = Utf8               size$extension
   #84 = NameAndType        #83:#57       // size$extension:(Ljava/lang/String;)Lorg/sireum/Z;
   #85 = Methodref          #64.#84       // org/sireum/String$.size$extension:(Ljava/lang/String;)Lorg/sireum/Z;
   #86 = Utf8               $eq$eq$eq$extension
   #87 = Utf8               (Ljava/lang/String;Ljava/lang/String;)Z
   #88 = Utf8               other
   #89 = Utf8               org/sireum/B$
   #90 = Class              #89           // org/sireum/B$
   #91 = Utf8               Lorg/sireum/B$;
   #92 = NameAndType        #15:#91       // MODULE$:Lorg/sireum/B$;
   #93 = Fieldref           #90.#92       // org/sireum/B$.MODULE$:Lorg/sireum/B$;
   #94 = Utf8               equals
   #95 = Utf8               (Ljava/lang/Object;)Z
   #96 = NameAndType        #94:#95       // equals:(Ljava/lang/Object;)Z
   #97 = Methodref          #4.#96        // java/lang/Object.equals:(Ljava/lang/Object;)Z
   #98 = Utf8               (Z)Z
   #99 = NameAndType        #68:#98       // apply:(Z)Z
  #100 = Methodref          #90.#99       // org/sireum/B$.apply:(Z)Z
  #101 = Utf8               java/lang/String
  #102 = Class              #101          // java/lang/String
  #103 = Utf8               $eq$bang$eq$extension
  #104 = Utf8               $tilde$greater$extension
  #105 = Utf8               (Ljava/lang/String;Z)Lscala/Tuple2;
  #106 = Utf8               (Ljava/lang/String;Z)Lscala/Tuple2<Lorg/sireum/String;Lorg/sireum/B;>;
  #107 = Utf8               o
  #108 = Utf8               scala/Tuple2
  #109 = Class              #108          // scala/Tuple2
  #110 = Utf8               org/sireum/B
  #111 = Class              #110          // org/sireum/B
  #112 = Utf8               (Z)V
  #113 = NameAndType        #19:#112      // "<init>":(Z)V
  #114 = Methodref          #111.#113     // org/sireum/B."<init>":(Z)V
  #115 = Utf8               (Ljava/lang/Object;Ljava/lang/Object;)V
  #116 = NameAndType        #19:#115      // "<init>":(Ljava/lang/Object;Ljava/lang/Object;)V
  #117 = Methodref          #109.#116     // scala/Tuple2."<init>":(Ljava/lang/Object;Ljava/lang/Object;)V
  #118 = Utf8               (Ljava/lang/String;C)Lscala/Tuple2;
  #119 = Utf8               (Ljava/lang/String;C)Lscala/Tuple2<Lorg/sireum/String;Lorg/sireum/C;>;
  #120 = Utf8               org/sireum/C
  #121 = Class              #120          // org/sireum/C
  #122 = Utf8               org/sireum/C$
  #123 = Class              #122          // org/sireum/C$
  #124 = Utf8               Lorg/sireum/C$;
  #125 = NameAndType        #15:#124      // MODULE$:Lorg/sireum/C$;
  #126 = Fieldref           #123.#125     // org/sireum/C$.MODULE$:Lorg/sireum/C$;
  #127 = Utf8               (C)I
  #128 = NameAndType        #68:#127      // apply:(C)I
  #129 = Methodref          #123.#128     // org/sireum/C$.apply:(C)I
  #130 = Utf8               (I)V
  #131 = NameAndType        #19:#130      // "<init>":(I)V
  #132 = Methodref          #121.#131     // org/sireum/C."<init>":(I)V
  #133 = Utf8               (Ljava/lang/String;I)Lscala/Tuple2;
  #134 = Utf8               (Ljava/lang/String;I)Lscala/Tuple2<Lorg/sireum/String;Lorg/sireum/Z;>;
  #135 = Utf8               org/sireum/Z$
  #136 = Class              #135          // org/sireum/Z$
  #137 = Utf8               Lorg/sireum/Z$;
  #138 = NameAndType        #15:#137      // MODULE$:Lorg/sireum/Z$;
  #139 = Fieldref           #136.#138     // org/sireum/Z$.MODULE$:Lorg/sireum/Z$;
  #140 = Utf8               (I)Lorg/sireum/Z;
  #141 = NameAndType        #68:#140      // apply:(I)Lorg/sireum/Z;
  #142 = Methodref          #136.#141     // org/sireum/Z$.apply:(I)Lorg/sireum/Z;
  #143 = Utf8               I
  #144 = Utf8               (Ljava/lang/String;J)Lscala/Tuple2;
  #145 = Utf8               (Ljava/lang/String;J)Lscala/Tuple2<Lorg/sireum/String;Lorg/sireum/Z;>;
  #146 = Utf8               (J)Lorg/sireum/Z;
  #147 = NameAndType        #68:#146      // apply:(J)Lorg/sireum/Z;
  #148 = Methodref          #136.#147     // org/sireum/Z$.apply:(J)Lorg/sireum/Z;
  #149 = Utf8               J
  #150 = Utf8               (Ljava/lang/String;F)Lscala/Tuple2;
  #151 = Utf8               (Ljava/lang/String;F)Lscala/Tuple2<Lorg/sireum/String;Lorg/sireum/F32;>;
  #152 = Utf8               org/sireum/F32
  #153 = Class              #152          // org/sireum/F32
  #154 = Utf8               org/sireum/F32$
  #155 = Class              #154          // org/sireum/F32$
  #156 = Utf8               Lorg/sireum/F32$;
  #157 = NameAndType        #15:#156      // MODULE$:Lorg/sireum/F32$;
  #158 = Fieldref           #155.#157     // org/sireum/F32$.MODULE$:Lorg/sireum/F32$;
  #159 = Utf8               (F)F
  #160 = NameAndType        #68:#159      // apply:(F)F
  #161 = Methodref          #155.#160     // org/sireum/F32$.apply:(F)F
  #162 = Utf8               (F)V
  #163 = NameAndType        #19:#162      // "<init>":(F)V
  #164 = Methodref          #153.#163     // org/sireum/F32."<init>":(F)V
  #165 = Utf8               F
  #166 = Utf8               (Ljava/lang/String;D)Lscala/Tuple2;
  #167 = Utf8               (Ljava/lang/String;D)Lscala/Tuple2<Lorg/sireum/String;Lorg/sireum/F64;>;
  #168 = Utf8               org/sireum/F64
  #169 = Class              #168          // org/sireum/F64
  #170 = Utf8               org/sireum/F64$
  #171 = Class              #170          // org/sireum/F64$
  #172 = Utf8               Lorg/sireum/F64$;
  #173 = NameAndType        #15:#172      // MODULE$:Lorg/sireum/F64$;
  #174 = Fieldref           #171.#173     // org/sireum/F64$.MODULE$:Lorg/sireum/F64$;
  #175 = Utf8               (D)D
  #176 = NameAndType        #68:#175      // apply:(D)D
  #177 = Methodref          #171.#176     // org/sireum/F64$.apply:(D)D
  #178 = Utf8               (D)V
  #179 = NameAndType        #19:#178      // "<init>":(D)V
  #180 = Methodref          #169.#179     // org/sireum/F64."<init>":(D)V
  #181 = Utf8               D
  #182 = Utf8               (Ljava/lang/String;Ljava/lang/String;)Lscala/Tuple2;
  #183 = Utf8               (Ljava/lang/String;Ljava/lang/String;)Lscala/Tuple2<Lorg/sireum/String;Lorg/sireum/String;>;
  #184 = Utf8               (Ljava/lang/String;Ljava/lang/Object;)Lscala/Tuple2;
  #185 = Utf8               <T:Ljava/lang/Object;>(Ljava/lang/String;TT;)Lscala/Tuple2<Lorg/sireum/String;TT;>;
  #186 = Utf8               hashCode$extension
  #187 = Utf8               (Ljava/lang/String;)I
  #188 = Utf8               hashCode
  #189 = Utf8               ()I
  #190 = NameAndType        #188:#189     // hashCode:()I
  #191 = Methodref          #102.#190     // java/lang/String.hashCode:()I
  #192 = Utf8               equals$extension
  #193 = Utf8               (Ljava/lang/String;Ljava/lang/Object;)Z
  #194 = Utf8               x$1
  #195 = Utf8               _value
  #196 = Utf8               ()Ljava/lang/String;
  #197 = NameAndType        #195:#196     // _value:()Ljava/lang/String;
  #198 = Methodref          #7.#197       // org/sireum/package$$PredefString2String._value:()Ljava/lang/String;
  #199 = Methodref          #4.#20        // java/lang/Object."<init>":()V
  #200 = Utf8               Code
  #201 = Utf8               LineNumberTable
  #202 = Utf8               LocalVariableTable
  #203 = Utf8               MethodParameters
  #204 = Utf8               Signature
  #205 = Utf8               StackMapTable
  #206 = Utf8               InnerClasses
  #207 = Utf8               SourceFile
  #208 = Utf8               ScalaInlineInfo
  #209 = Utf8               Scala
{
  public static final org.sireum.package$$PredefString2String$ MODULE$;
    descriptor: Lorg/sireum/package$$PredefString2String$;
    flags: (0x0019) ACC_PUBLIC, ACC_STATIC, ACC_FINAL

  public static {};
    descriptor: ()V
    flags: (0x0009) ACC_PUBLIC, ACC_STATIC
    Code:
      stack=2, locals=0, args_size=0
         0: new           #2                  // class org/sireum/package$$PredefString2String$
         3: dup
         4: invokespecial #21                 // Method "<init>":()V
         7: putstatic     #23                 // Field MODULE$:Lorg/sireum/package$$PredefString2String$;
        10: return
      LineNumberTable:
        line 405: 0

  public final scala.runtime.Nothing$ apply$extension(java.lang.String, java.lang.Object);
    descriptor: (Ljava/lang/String;Ljava/lang/Object;)Lscala/runtime/Nothing$;
    flags: (0x0011) ACC_PUBLIC, ACC_FINAL
    Code:
      stack=2, locals=3, args_size=3
         0: getstatic     #32                 // Field org/sireum/package$.MODULE$:Lorg/sireum/package$;
         3: ldc           #34                 // String
         5: invokevirtual #38                 // Method org/sireum/package$.halt:(Ljava/lang/Object;)Lscala/runtime/Nothing$;
         8: areturn
      LineNumberTable:
        line 407: 0
      LocalVariableTable:
        Start  Length  Slot  Name   Signature
            0       9     0  this   Lorg/sireum/package$$PredefString2String$;
            0       9     1 $this   Ljava/lang/String;
            0       9     2   arg   Ljava/lang/Object;
    MethodParameters:
      Name                           Flags
      $this                          final
      arg                            final

  public final scala.runtime.Nothing$ apply$extension(java.lang.String, boolean);
    descriptor: (Ljava/lang/String;Z)Lscala/runtime/Nothing$;
    flags: (0x0011) ACC_PUBLIC, ACC_FINAL
    Code:
      stack=2, locals=3, args_size=3
         0: getstatic     #32                 // Field org/sireum/package$.MODULE$:Lorg/sireum/package$;
         3: ldc           #34                 // String
         5: invokevirtual #38                 // Method org/sireum/package$.halt:(Ljava/lang/Object;)Lscala/runtime/Nothing$;
         8: areturn
      LineNumberTable:
        line 409: 0
      LocalVariableTable:
        Start  Length  Slot  Name   Signature
            0       9     0  this   Lorg/sireum/package$$PredefString2String$;
            0       9     1 $this   Ljava/lang/String;
            0       9     2   arg   Z
    MethodParameters:
      Name                           Flags
      $this                          final
      arg                            final

  public final scala.runtime.Nothing$ apply$extension(java.lang.String, byte);
    descriptor: (Ljava/lang/String;B)Lscala/runtime/Nothing$;
    flags: (0x0011) ACC_PUBLIC, ACC_FINAL
    Code:
      stack=2, locals=3, args_size=3
         0: getstatic     #32                 // Field org/sireum/package$.MODULE$:Lorg/sireum/package$;
         3: ldc           #34                 // String
         5: invokevirtual #38                 // Method org/sireum/package$.halt:(Ljava/lang/Object;)Lscala/runtime/Nothing$;
         8: areturn
      LineNumberTable:
        line 411: 0
      LocalVariableTable:
        Start  Length  Slot  Name   Signature
            0       9     0  this   Lorg/sireum/package$$PredefString2String$;
            0       9     1 $this   Ljava/lang/String;
            0       9     2   arg   B
    MethodParameters:
      Name                           Flags
      $this                          final
      arg                            final

  public final scala.runtime.Nothing$ apply$extension(java.lang.String, short);
    descriptor: (Ljava/lang/String;S)Lscala/runtime/Nothing$;
    flags: (0x0011) ACC_PUBLIC, ACC_FINAL
    Code:
      stack=2, locals=3, args_size=3
         0: getstatic     #32                 // Field org/sireum/package$.MODULE$:Lorg/sireum/package$;
         3: ldc           #34                 // String
         5: invokevirtual #38                 // Method org/sireum/package$.halt:(Ljava/lang/Object;)Lscala/runtime/Nothing$;
         8: areturn
      LineNumberTable:
        line 413: 0
      LocalVariableTable:
        Start  Length  Slot  Name   Signature
            0       9     0  this   Lorg/sireum/package$$PredefString2String$;
            0       9     1 $this   Ljava/lang/String;
            0       9     2   arg   S
    MethodParameters:
      Name                           Flags
      $this                          final
      arg                            final

  public final scala.runtime.Nothing$ apply$extension(java.lang.String, char);
    descriptor: (Ljava/lang/String;C)Lscala/runtime/Nothing$;
    flags: (0x0011) ACC_PUBLIC, ACC_FINAL
    Code:
      stack=2, locals=3, args_size=3
         0: getstatic     #32                 // Field org/sireum/package$.MODULE$:Lorg/sireum/package$;
         3: ldc           #34                 // String
         5: invokevirtual #38                 // Method org/sireum/package$.halt:(Ljava/lang/Object;)Lscala/runtime/Nothing$;
         8: areturn
      LineNumberTable:
        line 415: 0
      LocalVariableTable:
        Start  Length  Slot  Name   Signature
            0       9     0  this   Lorg/sireum/package$$PredefString2String$;
            0       9     1 $this   Ljava/lang/String;
            0       9     2   arg   C
    MethodParameters:
      Name                           Flags
      $this                          final
      arg                            final

  public final scala.runtime.Nothing$ apply$extension(java.lang.String, java.lang.Object, java.lang.Object, scala.collection.immutable.Seq<java.lang.Object>);
    descriptor: (Ljava/lang/String;Ljava/lang/Object;Ljava/lang/Object;Lscala/collection/immutable/Seq;)Lscala/runtime/Nothing$;
    flags: (0x0011) ACC_PUBLIC, ACC_FINAL
    Code:
      stack=2, locals=5, args_size=5
         0: getstatic     #32                 // Field org/sireum/package$.MODULE$:Lorg/sireum/package$;
         3: ldc           #34                 // String
         5: invokevirtual #38                 // Method org/sireum/package$.halt:(Ljava/lang/Object;)Lscala/runtime/Nothing$;
         8: areturn
      LineNumberTable:
        line 417: 0
      LocalVariableTable:
        Start  Length  Slot  Name   Signature
            0       9     0  this   Lorg/sireum/package$$PredefString2String$;
            0       9     1 $this   Ljava/lang/String;
            0       9     2  arg0   Ljava/lang/Object;
            0       9     3  arg1   Ljava/lang/Object;
            0       9     4  args   Lscala/collection/immutable/Seq;
    Signature: #51                          // (Ljava/lang/String;Ljava/lang/Object;Ljava/lang/Object;Lscala/collection/immutable/Seq<Ljava/lang/Object;>;)Lscala/runtime/Nothing$;
    MethodParameters:
      Name                           Flags
      $this                          final
      arg0                           final
      arg1                           final
      args                           final

  public final org.sireum.Z hash$extension(java.lang.String);
    descriptor: (Ljava/lang/String;)Lorg/sireum/Z;
    flags: (0x0011) ACC_PUBLIC, ACC_FINAL
    Code:
      stack=6, locals=2, args_size=2
         0: getstatic     #60                 // Field org/sireum/package$Any2HashString$.MODULE$:Lorg/sireum/package$Any2HashString$;
         3: getstatic     #32                 // Field org/sireum/package$.MODULE$:Lorg/sireum/package$;
         6: new           #62                 // class org/sireum/String
         9: dup
        10: getstatic     #67                 // Field org/sireum/String$.MODULE$:Lorg/sireum/String$;
        13: aload_1
        14: invokevirtual #71                 // Method org/sireum/String$.apply:(Ljava/lang/String;)Ljava/lang/String;
        17: invokespecial #74                 // Method org/sireum/String."<init>":(Ljava/lang/String;)V
        20: invokevirtual #78                 // Method org/sireum/package$.Any2HashString:(Ljava/lang/Object;)Ljava/lang/Object;
        23: invokevirtual #81                 // Method org/sireum/package$Any2HashString$.hash$extension:(Ljava/lang/Object;)Lorg/sireum/Z;
        26: areturn
      LineNumberTable:
        line 419: 3
      LocalVariableTable:
        Start  Length  Slot  Name   Signature
            0      27     0  this   Lorg/sireum/package$$PredefString2String$;
            0      27     1 $this   Ljava/lang/String;
    MethodParameters:
      Name                           Flags
      $this                          final

  public final java.lang.String string$extension(java.lang.String);
    descriptor: (Ljava/lang/String;)Ljava/lang/String;
    flags: (0x0011) ACC_PUBLIC, ACC_FINAL
    Code:
      stack=2, locals=2, args_size=2
         0: getstatic     #67                 // Field org/sireum/String$.MODULE$:Lorg/sireum/String$;
         3: aload_1
         4: invokevirtual #71                 // Method org/sireum/String$.apply:(Ljava/lang/String;)Ljava/lang/String;
         7: areturn
      LineNumberTable:
        line 421: 0
      LocalVariableTable:
        Start  Length  Slot  Name   Signature
            0       8     0  this   Lorg/sireum/package$$PredefString2String$;
            0       8     1 $this   Ljava/lang/String;
    MethodParameters:
      Name                           Flags
      $this                          final

  public final org.sireum.Z size$extension(java.lang.String);
    descriptor: (Ljava/lang/String;)Lorg/sireum/Z;
    flags: (0x0011) ACC_PUBLIC, ACC_FINAL
    Code:
      stack=3, locals=2, args_size=2
         0: getstatic     #67                 // Field org/sireum/String$.MODULE$:Lorg/sireum/String$;
         3: getstatic     #67                 // Field org/sireum/String$.MODULE$:Lorg/sireum/String$;
         6: aload_1
         7: invokevirtual #71                 // Method org/sireum/String$.apply:(Ljava/lang/String;)Ljava/lang/String;
        10: invokevirtual #85                 // Method org/sireum/String$.size$extension:(Ljava/lang/String;)Lorg/sireum/Z;
        13: areturn
      LineNumberTable:
        line 423: 3
      LocalVariableTable:
        Start  Length  Slot  Name   Signature
            0      14     0  this   Lorg/sireum/package$$PredefString2String$;
            0      14     1 $this   Ljava/lang/String;
    MethodParameters:
      Name                           Flags
      $this                          final

  public final boolean $eq$eq$eq$extension(java.lang.String, java.lang.String);
    descriptor: (Ljava/lang/String;Ljava/lang/String;)Z
    flags: (0x0011) ACC_PUBLIC, ACC_FINAL
    Code:
      stack=3, locals=4, args_size=3
         0: getstatic     #93                 // Field org/sireum/B$.MODULE$:Lorg/sireum/B$;
         3: aload_1
         4: aload_2
         5: astore_3
         6: dup
         7: ifnonnull     18
        10: pop
        11: aload_3
        12: ifnull        25
        15: goto          29
        18: aload_3
        19: invokevirtual #97                 // Method java/lang/Object.equals:(Ljava/lang/Object;)Z
        22: ifeq          29
        25: iconst_1
        26: goto          30
        29: iconst_0
        30: invokevirtual #100                // Method org/sireum/B$.apply:(Z)Z
        33: ireturn
      StackMapTable: number_of_entries = 4
        frame_type = 255 /* full_frame */
          offset_delta = 18
          locals = [ class org/sireum/package$$PredefString2String$, class java/lang/String, class java/lang/String, class java/lang/String ]
          stack = [ class org/sireum/B$, class java/lang/String ]
        frame_type = 70 /* same_locals_1_stack_item */
          stack = [ class org/sireum/B$ ]
        frame_type = 67 /* same_locals_1_stack_item */
          stack = [ class org/sireum/B$ ]
        frame_type = 255 /* full_frame */
          offset_delta = 0
          locals = [ class org/sireum/package$$PredefString2String$, class java/lang/String, class java/lang/String, class java/lang/String ]
          stack = [ class org/sireum/B$, int ]
      LineNumberTable:
        line 425: 0
      LocalVariableTable:
        Start  Length  Slot  Name   Signature
            0      34     0  this   Lorg/sireum/package$$PredefString2String$;
            0      34     1 $this   Ljava/lang/String;
            0      34     2 other   Ljava/lang/String;
    MethodParameters:
      Name                           Flags
      $this                          final
      other                          final

  public final boolean $eq$bang$eq$extension(java.lang.String, java.lang.String);
    descriptor: (Ljava/lang/String;Ljava/lang/String;)Z
    flags: (0x0011) ACC_PUBLIC, ACC_FINAL
    Code:
      stack=3, locals=4, args_size=3
         0: getstatic     #93                 // Field org/sireum/B$.MODULE$:Lorg/sireum/B$;
         3: aload_1
         4: aload_2
         5: astore_3
         6: dup
         7: ifnonnull     18
        10: pop
        11: aload_3
        12: ifnull        29
        15: goto          25
        18: aload_3
        19: invokevirtual #97                 // Method java/lang/Object.equals:(Ljava/lang/Object;)Z
        22: ifne          29
        25: iconst_1
        26: goto          30
        29: iconst_0
        30: invokevirtual #100                // Method org/sireum/B$.apply:(Z)Z
        33: ireturn
      StackMapTable: number_of_entries = 4
        frame_type = 255 /* full_frame */
          offset_delta = 18
          locals = [ class org/sireum/package$$PredefString2String$, class java/lang/String, class java/lang/String, class java/lang/String ]
          stack = [ class org/sireum/B$, class java/lang/String ]
        frame_type = 70 /* same_locals_1_stack_item */
          stack = [ class org/sireum/B$ ]
        frame_type = 67 /* same_locals_1_stack_item */
          stack = [ class org/sireum/B$ ]
        frame_type = 255 /* full_frame */
          offset_delta = 0
          locals = [ class org/sireum/package$$PredefString2String$, class java/lang/String, class java/lang/String, class java/lang/String ]
          stack = [ class org/sireum/B$, int ]
      LineNumberTable:
        line 427: 0
      LocalVariableTable:
        Start  Length  Slot  Name   Signature
            0      34     0  this   Lorg/sireum/package$$PredefString2String$;
            0      34     1 $this   Ljava/lang/String;
            0      34     2 other   Ljava/lang/String;
    MethodParameters:
      Name                           Flags
      $this                          final
      other                          final

  public final scala.Tuple2<org.sireum.String, org.sireum.B> $tilde$greater$extension(java.lang.String, boolean);
    descriptor: (Ljava/lang/String;Z)Lscala/Tuple2;
    flags: (0x0011) ACC_PUBLIC, ACC_FINAL
    Code:
      stack=7, locals=3, args_size=3
         0: new           #109                // class scala/Tuple2
         3: dup
         4: new           #62                 // class org/sireum/String
         7: dup
         8: getstatic     #67                 // Field org/sireum/String$.MODULE$:Lorg/sireum/String$;
        11: aload_1
        12: invokevirtual #71                 // Method org/sireum/String$.apply:(Ljava/lang/String;)Ljava/lang/String;
        15: invokespecial #74                 // Method org/sireum/String."<init>":(Ljava/lang/String;)V
        18: new           #111                // class org/sireum/B
        21: dup
        22: getstatic     #93                 // Field org/sireum/B$.MODULE$:Lorg/sireum/B$;
        25: iload_2
        26: invokevirtual #100                // Method org/sireum/B$.apply:(Z)Z
        29: invokespecial #114                // Method org/sireum/B."<init>":(Z)V
        32: invokespecial #117                // Method scala/Tuple2."<init>":(Ljava/lang/Object;Ljava/lang/Object;)V
        35: areturn
      LineNumberTable:
        line 429: 0
      LocalVariableTable:
        Start  Length  Slot  Name   Signature
            0      36     0  this   Lorg/sireum/package$$PredefString2String$;
            0      36     1 $this   Ljava/lang/String;
            0      36     2     o   Z
    Signature: #106                         // (Ljava/lang/String;Z)Lscala/Tuple2<Lorg/sireum/String;Lorg/sireum/B;>;
    MethodParameters:
      Name                           Flags
      $this                          final
      o                              final

  public final scala.Tuple2<org.sireum.String, org.sireum.C> $tilde$greater$extension(java.lang.String, char);
    descriptor: (Ljava/lang/String;C)Lscala/Tuple2;
    flags: (0x0011) ACC_PUBLIC, ACC_FINAL
    Code:
      stack=7, locals=3, args_size=3
         0: new           #109                // class scala/Tuple2
         3: dup
         4: new           #62                 // class org/sireum/String
         7: dup
         8: getstatic     #67                 // Field org/sireum/String$.MODULE$:Lorg/sireum/String$;
        11: aload_1
        12: invokevirtual #71                 // Method org/sireum/String$.apply:(Ljava/lang/String;)Ljava/lang/String;
        15: invokespecial #74                 // Method org/sireum/String."<init>":(Ljava/lang/String;)V
        18: new           #121                // class org/sireum/C
        21: dup
        22: getstatic     #126                // Field org/sireum/C$.MODULE$:Lorg/sireum/C$;
        25: iload_2
        26: invokevirtual #129                // Method org/sireum/C$.apply:(C)I
        29: invokespecial #132                // Method org/sireum/C."<init>":(I)V
        32: invokespecial #117                // Method scala/Tuple2."<init>":(Ljava/lang/Object;Ljava/lang/Object;)V
        35: areturn
      LineNumberTable:
        line 431: 0
      LocalVariableTable:
        Start  Length  Slot  Name   Signature
            0      36     0  this   Lorg/sireum/package$$PredefString2String$;
            0      36     1 $this   Ljava/lang/String;
            0      36     2     o   C
    Signature: #119                         // (Ljava/lang/String;C)Lscala/Tuple2<Lorg/sireum/String;Lorg/sireum/C;>;
    MethodParameters:
      Name                           Flags
      $this                          final
      o                              final

  public final scala.Tuple2<org.sireum.String, org.sireum.Z> $tilde$greater$extension(java.lang.String, int);
    descriptor: (Ljava/lang/String;I)Lscala/Tuple2;
    flags: (0x0011) ACC_PUBLIC, ACC_FINAL
    Code:
      stack=6, locals=3, args_size=3
         0: new           #109                // class scala/Tuple2
         3: dup
         4: new           #62                 // class org/sireum/String
         7: dup
         8: getstatic     #67                 // Field org/sireum/String$.MODULE$:Lorg/sireum/String$;
        11: aload_1
        12: invokevirtual #71                 // Method org/sireum/String$.apply:(Ljava/lang/String;)Ljava/lang/String;
        15: invokespecial #74                 // Method org/sireum/String."<init>":(Ljava/lang/String;)V
        18: getstatic     #139                // Field org/sireum/Z$.MODULE$:Lorg/sireum/Z$;
        21: iload_2
        22: invokevirtual #142                // Method org/sireum/Z$.apply:(I)Lorg/sireum/Z;
        25: invokespecial #117                // Method scala/Tuple2."<init>":(Ljava/lang/Object;Ljava/lang/Object;)V
        28: areturn
      LineNumberTable:
        line 433: 0
      LocalVariableTable:
        Start  Length  Slot  Name   Signature
            0      29     0  this   Lorg/sireum/package$$PredefString2String$;
            0      29     1 $this   Ljava/lang/String;
            0      29     2     o   I
    Signature: #134                         // (Ljava/lang/String;I)Lscala/Tuple2<Lorg/sireum/String;Lorg/sireum/Z;>;
    MethodParameters:
      Name                           Flags
      $this                          final
      o                              final

  public final scala.Tuple2<org.sireum.String, org.sireum.Z> $tilde$greater$extension(java.lang.String, long);
    descriptor: (Ljava/lang/String;J)Lscala/Tuple2;
    flags: (0x0011) ACC_PUBLIC, ACC_FINAL
    Code:
      stack=6, locals=4, args_size=3
         0: new           #109                // class scala/Tuple2
         3: dup
         4: new           #62                 // class org/sireum/String
         7: dup
         8: getstatic     #67                 // Field org/sireum/String$.MODULE$:Lorg/sireum/String$;
        11: aload_1
        12: invokevirtual #71                 // Method org/sireum/String$.apply:(Ljava/lang/String;)Ljava/lang/String;
        15: invokespecial #74                 // Method org/sireum/String."<init>":(Ljava/lang/String;)V
        18: getstatic     #139                // Field org/sireum/Z$.MODULE$:Lorg/sireum/Z$;
        21: lload_2
        22: invokevirtual #148                // Method org/sireum/Z$.apply:(J)Lorg/sireum/Z;
        25: invokespecial #117                // Method scala/Tuple2."<init>":(Ljava/lang/Object;Ljava/lang/Object;)V
        28: areturn
      LineNumberTable:
        line 435: 0
      LocalVariableTable:
        Start  Length  Slot  Name   Signature
            0      29     0  this   Lorg/sireum/package$$PredefString2String$;
            0      29     1 $this   Ljava/lang/String;
            0      29     2     o   J
    Signature: #145                         // (Ljava/lang/String;J)Lscala/Tuple2<Lorg/sireum/String;Lorg/sireum/Z;>;
    MethodParameters:
      Name                           Flags
      $this                          final
      o                              final

  public final scala.Tuple2<org.sireum.String, org.sireum.F32> $tilde$greater$extension(java.lang.String, float);
    descriptor: (Ljava/lang/String;F)Lscala/Tuple2;
    flags: (0x0011) ACC_PUBLIC, ACC_FINAL
    Code:
      stack=7, locals=3, args_size=3
         0: new           #109                // class scala/Tuple2
         3: dup
         4: new           #62                 // class org/sireum/String
         7: dup
         8: getstatic     #67                 // Field org/sireum/String$.MODULE$:Lorg/sireum/String$;
        11: aload_1
        12: invokevirtual #71                 // Method org/sireum/String$.apply:(Ljava/lang/String;)Ljava/lang/String;
        15: invokespecial #74                 // Method org/sireum/String."<init>":(Ljava/lang/String;)V
        18: new           #153                // class org/sireum/F32
        21: dup
        22: getstatic     #158                // Field org/sireum/F32$.MODULE$:Lorg/sireum/F32$;
        25: fload_2
        26: invokevirtual #161                // Method org/sireum/F32$.apply:(F)F
        29: invokespecial #164                // Method org/sireum/F32."<init>":(F)V
        32: invokespecial #117                // Method scala/Tuple2."<init>":(Ljava/lang/Object;Ljava/lang/Object;)V
        35: areturn
      LineNumberTable:
        line 437: 0
      LocalVariableTable:
        Start  Length  Slot  Name   Signature
            0      36     0  this   Lorg/sireum/package$$PredefString2String$;
            0      36     1 $this   Ljava/lang/String;
            0      36     2     o   F
    Signature: #151                         // (Ljava/lang/String;F)Lscala/Tuple2<Lorg/sireum/String;Lorg/sireum/F32;>;
    MethodParameters:
      Name                           Flags
      $this                          final
      o                              final

  public final scala.Tuple2<org.sireum.String, org.sireum.F64> $tilde$greater$extension(java.lang.String, double);
    descriptor: (Ljava/lang/String;D)Lscala/Tuple2;
    flags: (0x0011) ACC_PUBLIC, ACC_FINAL
    Code:
      stack=8, locals=4, args_size=3
         0: new           #109                // class scala/Tuple2
         3: dup
         4: new           #62                 // class org/sireum/String
         7: dup
         8: getstatic     #67                 // Field org/sireum/String$.MODULE$:Lorg/sireum/String$;
        11: aload_1
        12: invokevirtual #71                 // Method org/sireum/String$.apply:(Ljava/lang/String;)Ljava/lang/String;
        15: invokespecial #74                 // Method org/sireum/String."<init>":(Ljava/lang/String;)V
        18: new           #169                // class org/sireum/F64
        21: dup
        22: getstatic     #174                // Field org/sireum/F64$.MODULE$:Lorg/sireum/F64$;
        25: dload_2
        26: invokevirtual #177                // Method org/sireum/F64$.apply:(D)D
        29: invokespecial #180                // Method org/sireum/F64."<init>":(D)V
        32: invokespecial #117                // Method scala/Tuple2."<init>":(Ljava/lang/Object;Ljava/lang/Object;)V
        35: areturn
      LineNumberTable:
        line 439: 0
      LocalVariableTable:
        Start  Length  Slot  Name   Signature
            0      36     0  this   Lorg/sireum/package$$PredefString2String$;
            0      36     1 $this   Ljava/lang/String;
            0      36     2     o   D
    Signature: #167                         // (Ljava/lang/String;D)Lscala/Tuple2<Lorg/sireum/String;Lorg/sireum/F64;>;
    MethodParameters:
      Name                           Flags
      $this                          final
      o                              final

  public final scala.Tuple2<org.sireum.String, org.sireum.String> $tilde$greater$extension(java.lang.String, java.lang.String);
    descriptor: (Ljava/lang/String;Ljava/lang/String;)Lscala/Tuple2;
    flags: (0x0011) ACC_PUBLIC, ACC_FINAL
    Code:
      stack=7, locals=3, args_size=3
         0: new           #109                // class scala/Tuple2
         3: dup
         4: new           #62                 // class org/sireum/String
         7: dup
         8: getstatic     #67                 // Field org/sireum/String$.MODULE$:Lorg/sireum/String$;
        11: aload_1
        12: invokevirtual #71                 // Method org/sireum/String$.apply:(Ljava/lang/String;)Ljava/lang/String;
        15: invokespecial #74                 // Method org/sireum/String."<init>":(Ljava/lang/String;)V
        18: new           #62                 // class org/sireum/String
        21: dup
        22: getstatic     #67                 // Field org/sireum/String$.MODULE$:Lorg/sireum/String$;
        25: aload_2
        26: invokevirtual #71                 // Method org/sireum/String$.apply:(Ljava/lang/String;)Ljava/lang/String;
        29: invokespecial #74                 // Method org/sireum/String."<init>":(Ljava/lang/String;)V
        32: invokespecial #117                // Method scala/Tuple2."<init>":(Ljava/lang/Object;Ljava/lang/Object;)V
        35: areturn
      LineNumberTable:
        line 441: 0
      LocalVariableTable:
        Start  Length  Slot  Name   Signature
            0      36     0  this   Lorg/sireum/package$$PredefString2String$;
            0      36     1 $this   Ljava/lang/String;
            0      36     2     o   Ljava/lang/String;
    Signature: #183                         // (Ljava/lang/String;Ljava/lang/String;)Lscala/Tuple2<Lorg/sireum/String;Lorg/sireum/String;>;
    MethodParameters:
      Name                           Flags
      $this                          final
      o                              final

  public final <T extends java.lang.Object> scala.Tuple2<org.sireum.String, T> $tilde$greater$extension(java.lang.String, T);
    descriptor: (Ljava/lang/String;Ljava/lang/Object;)Lscala/Tuple2;
    flags: (0x0011) ACC_PUBLIC, ACC_FINAL
    Code:
      stack=6, locals=3, args_size=3
         0: new           #109                // class scala/Tuple2
         3: dup
         4: new           #62                 // class org/sireum/String
         7: dup
         8: getstatic     #67                 // Field org/sireum/String$.MODULE$:Lorg/sireum/String$;
        11: aload_1
        12: invokevirtual #71                 // Method org/sireum/String$.apply:(Ljava/lang/String;)Ljava/lang/String;
        15: invokespecial #74                 // Method org/sireum/String."<init>":(Ljava/lang/String;)V
        18: aload_2
        19: invokespecial #117                // Method scala/Tuple2."<init>":(Ljava/lang/Object;Ljava/lang/Object;)V
        22: areturn
      LineNumberTable:
        line 443: 0
      LocalVariableTable:
        Start  Length  Slot  Name   Signature
            0      23     0  this   Lorg/sireum/package$$PredefString2String$;
            0      23     1 $this   Ljava/lang/String;
            0      23     2     o   Ljava/lang/Object;
    Signature: #185                         // <T:Ljava/lang/Object;>(Ljava/lang/String;TT;)Lscala/Tuple2<Lorg/sireum/String;TT;>;
    MethodParameters:
      Name                           Flags
      $this                          final
      o                              final

  public final int hashCode$extension(java.lang.String);
    descriptor: (Ljava/lang/String;)I
    flags: (0x0011) ACC_PUBLIC, ACC_FINAL
    Code:
      stack=1, locals=2, args_size=2
         0: aload_1
         1: invokevirtual #191                // Method java/lang/String.hashCode:()I
         4: ireturn
      LineNumberTable:
        line 405: 0
      LocalVariableTable:
        Start  Length  Slot  Name   Signature
            0       5     0  this   Lorg/sireum/package$$PredefString2String$;
            0       5     1 $this   Ljava/lang/String;
    MethodParameters:
      Name                           Flags
      $this                          final

  public final boolean equals$extension(java.lang.String, java.lang.Object);
    descriptor: (Ljava/lang/String;Ljava/lang/Object;)Z
    flags: (0x0011) ACC_PUBLIC, ACC_FINAL
    Code:
      stack=2, locals=7, args_size=3
         0: aload_2
         1: astore        4
         3: aload         4
         5: instanceof    #7                  // class org/sireum/package$$PredefString2String
         8: ifeq          16
        11: iconst_1
        12: istore_3
        13: goto          24
        16: goto          19
        19: iconst_0
        20: istore_3
        21: goto          24
        24: iload_3
        25: ifeq          83
        28: aload_2
        29: ifnonnull     36
        32: aconst_null
        33: goto          43
        36: aload_2
        37: checkcast     #7                  // class org/sireum/package$$PredefString2String
        40: invokevirtual #198                // Method org/sireum/package$$PredefString2String._value:()Ljava/lang/String;
        43: astore        5
        45: aload_1
        46: aload         5
        48: astore        6
        50: dup
        51: ifnonnull     63
        54: pop
        55: aload         6
        57: ifnull        71
        60: goto          75
        63: aload         6
        65: invokevirtual #97                 // Method java/lang/Object.equals:(Ljava/lang/Object;)Z
        68: ifeq          75
        71: iconst_1
        72: goto          76
        75: iconst_0
        76: ifeq          83
        79: iconst_1
        80: goto          84
        83: iconst_0
        84: ireturn
      StackMapTable: number_of_entries = 11
        frame_type = 253 /* append */
          offset_delta = 16
          locals = [ top, class java/lang/Object ]
        frame_type = 2 /* same */
        frame_type = 255 /* full_frame */
          offset_delta = 4
          locals = [ class org/sireum/package$$PredefString2String$, class java/lang/String, class java/lang/Object, int, class java/lang/Object ]
          stack = []
        frame_type = 11 /* same */
        frame_type = 70 /* same_locals_1_stack_item */
          stack = [ class java/lang/String ]
        frame_type = 255 /* full_frame */
          offset_delta = 19
          locals = [ class org/sireum/package$$PredefString2String$, class java/lang/String, class java/lang/Object, int, class java/lang/Object, class java/lang/String, class java/lang/String ]
          stack = [ class java/lang/String ]
        frame_type = 7 /* same */
        frame_type = 3 /* same */
        frame_type = 64 /* same_locals_1_stack_item */
          stack = [ int ]
        frame_type = 249 /* chop */
          offset_delta = 6
        frame_type = 64 /* same_locals_1_stack_item */
          stack = [ int ]
      LineNumberTable:
        line 405: 0
      LocalVariableTable:
        Start  Length  Slot  Name   Signature
            0      85     0  this   Lorg/sireum/package$$PredefString2String$;
            0      85     1 $this   Ljava/lang/String;
            0      85     2   x$1   Ljava/lang/Object;
    MethodParameters:
      Name                           Flags
      $this                          final
      x$1                            final

  public org.sireum.package$$PredefString2String$();
    descriptor: ()V
    flags: (0x0001) ACC_PUBLIC
    Code:
      stack=1, locals=1, args_size=1
         0: aload_0
         1: invokespecial #199                // Method java/lang/Object."<init>":()V
         4: return
      LineNumberTable:
        line 405: 0
      LocalVariableTable:
        Start  Length  Slot  Name   Signature
            0       5     0  this   Lorg/sireum/package$$PredefString2String$;
}
InnerClasses:
  public static final #10= #7 of #9;      // $PredefString2String=class org/sireum/package$$PredefString2String of class org/sireum/package
  public static #11= #2 of #9;            // $PredefString2String$=class org/sireum/package$$PredefString2String$ of class org/sireum/package
  public static #14= #13 of #9;           // Any2HashString$=class org/sireum/package$Any2HashString$ of class org/sireum/package
SourceFile: "package.scala"
  ScalaInlineInfo: length = 0x72 (unknown attribute)
   01 01 00 16 00 67 00 57 05 00 56 00 57 05 00 68
   00 76 05 00 68 00 A6 05 00 68 00 96 05 00 68 00
   85 05 00 68 00 90 05 00 68 00 B8 05 00 68 00 B6
   05 00 68 00 69 05 00 13 00 12 01 00 18 00 2C 05
   00 18 00 30 05 00 18 00 19 05 00 18 00 32 05 00
   18 00 2E 05 00 18 00 2A 05 00 C0 00 C1 01 00 38
   00 39 05 00 BA 00 BB 01 00 53 00 39 05 00 52 00
   45 05
  Scala: length = 0x0 (unknown attribute)

