Classfile /Users/mw/Projects/slang-braindump/.jar/jar8/assemble/slang-braindump/assemble/content/org/sireum/package$.class
  Last modified May 29, 2022; size 49995 bytes
  SHA-256 checksum 5684ddc0e45ad2b257699f80a8d8646daaccc53811a756eaa0499e6c1560ac39
  Compiled from "package.scala"
public final class org.sireum.package$ implements org.sireum.$internal.PackageTrait,org.sireum.contract
  minor version: 0
  major version: 52
  flags: (0x0031) ACC_PUBLIC, ACC_FINAL, ACC_SUPER
  this_class: #2                          // org/sireum/package$
  super_class: #4                         // java/lang/Object
  interfaces: 2, fields: 13, methods: 134, attributes: 4
Constant pool:
    #1 = Utf8               org/sireum/package$
    #2 = Class              #1            // org/sireum/package$
    #3 = Utf8               java/lang/Object
    #4 = Class              #3            // java/lang/Object
    #5 = Utf8               org/sireum/$internal/PackageTrait
    #6 = Class              #5            // org/sireum/$internal/PackageTrait
    #7 = Utf8               org/sireum/contract
    #8 = Class              #7            // org/sireum/contract
    #9 = Utf8               package.scala
   #10 = Utf8               org/sireum/$internal/PackageTrait$ISZ$
   #11 = Class              #10           // org/sireum/$internal/PackageTrait$ISZ$
   #12 = Utf8               ISZ$
   #13 = Utf8               org/sireum/$internal/PackageTrait$MSZ$
   #14 = Class              #13           // org/sireum/$internal/PackageTrait$MSZ$
   #15 = Utf8               MSZ$
   #16 = Utf8               org/sireum/$internal/PackageTrait$ZS$
   #17 = Class              #16           // org/sireum/$internal/PackageTrait$ZS$
   #18 = Utf8               ZS$
   #19 = Utf8               org/sireum/contract$$u2200$
   #20 = Class              #19           // org/sireum/contract$$u2200$
   #21 = Utf8               $u2200$
   #22 = Utf8               org/sireum/contract$$u2203$
   #23 = Class              #22           // org/sireum/contract$$u2203$
   #24 = Utf8               $u2203$
   #25 = Utf8               org/sireum/contract$All$
   #26 = Class              #25           // org/sireum/contract$All$
   #27 = Utf8               All$
   #28 = Utf8               org/sireum/contract$Contract$
   #29 = Class              #28           // org/sireum/contract$Contract$
   #30 = Utf8               Contract$
   #31 = Utf8               org/sireum/contract$Contract$Assert
   #32 = Class              #31           // org/sireum/contract$Contract$Assert
   #33 = Utf8               Assert
   #34 = Utf8               org/sireum/contract$Contract$Assume
   #35 = Class              #34           // org/sireum/contract$Contract$Assume
   #36 = Utf8               Assume
   #37 = Utf8               org/sireum/contract$Contract$Case
   #38 = Class              #37           // org/sireum/contract$Contract$Case
   #39 = Utf8               Case
   #40 = Utf8               org/sireum/contract$Contract$DataRefinement
   #41 = Class              #40           // org/sireum/contract$Contract$DataRefinement
   #42 = Utf8               DataRefinement
   #43 = Utf8               org/sireum/contract$Contract$Ensures
   #44 = Class              #43           // org/sireum/contract$Contract$Ensures
   #45 = Utf8               Ensures
   #46 = Utf8               org/sireum/contract$Contract$Fact
   #47 = Class              #46           // org/sireum/contract$Contract$Fact
   #48 = Utf8               Fact
   #49 = Utf8               org/sireum/contract$Contract$Invariant
   #50 = Class              #49           // org/sireum/contract$Contract$Invariant
   #51 = Utf8               Invariant
   #52 = Utf8               org/sireum/contract$Contract$Justification
   #53 = Class              #52           // org/sireum/contract$Contract$Justification
   #54 = Utf8               Justification
   #55 = Utf8               org/sireum/contract$Contract$Lemma
   #56 = Class              #55           // org/sireum/contract$Contract$Lemma
   #57 = Utf8               Lemma
   #58 = Utf8               org/sireum/contract$Contract$Let
   #59 = Class              #58           // org/sireum/contract$Contract$Let
   #60 = Utf8               Let
   #61 = Utf8               org/sireum/contract$Contract$MaxIt
   #62 = Class              #61           // org/sireum/contract$Contract$MaxIt
   #63 = Utf8               MaxIt
   #64 = Utf8               org/sireum/contract$Contract$Modifies
   #65 = Class              #64           // org/sireum/contract$Contract$Modifies
   #66 = Utf8               Modifies
   #67 = Utf8               org/sireum/contract$Contract$Proof
   #68 = Class              #67           // org/sireum/contract$Contract$Proof
   #69 = Utf8               Proof
   #70 = Utf8               org/sireum/contract$Contract$ProofStep
   #71 = Class              #70           // org/sireum/contract$Contract$ProofStep
   #72 = Utf8               ProofStep
   #73 = Utf8               org/sireum/contract$Contract$Reads
   #74 = Class              #73           // org/sireum/contract$Contract$Reads
   #75 = Utf8               Reads
   #76 = Utf8               org/sireum/contract$Contract$Requires
   #77 = Class              #76           // org/sireum/contract$Contract$Requires
   #78 = Utf8               Requires
   #79 = Utf8               org/sireum/contract$Contract$Sequent
   #80 = Class              #79           // org/sireum/contract$Contract$Sequent
   #81 = Utf8               Sequent
   #82 = Utf8               org/sireum/contract$Contract$SequentBuilder
   #83 = Class              #82           // org/sireum/contract$Contract$SequentBuilder
   #84 = Utf8               SequentBuilder
   #85 = Utf8               org/sireum/contract$Contract$StateCont
   #86 = Class              #85           // org/sireum/contract$Contract$StateCont
   #87 = Utf8               StateCont
   #88 = Utf8               org/sireum/contract$Contract$StepBuilder
   #89 = Class              #88           // org/sireum/contract$Contract$StepBuilder
   #90 = Utf8               StepBuilder
   #91 = Utf8               org/sireum/contract$Contract$SubProof
   #92 = Class              #91           // org/sireum/contract$Contract$SubProof
   #93 = Utf8               SubProof
   #94 = Utf8               org/sireum/contract$Contract$Theorem
   #95 = Class              #94           // org/sireum/contract$Contract$Theorem
   #96 = Utf8               Theorem
   #97 = Utf8               org/sireum/contract$Exists$
   #98 = Class              #97           // org/sireum/contract$Exists$
   #99 = Utf8               Exists$
  #100 = Utf8               org/sireum/contract$Spec$
  #101 = Class              #100          // org/sireum/contract$Spec$
  #102 = Utf8               Spec$
  #103 = Utf8               org/sireum/package$$Slang
  #104 = Class              #103          // org/sireum/package$$Slang
  #105 = Utf8               org/sireum/package
  #106 = Class              #105          // org/sireum/package
  #107 = Utf8               $Slang
  #108 = Utf8               MODULE$
  #109 = Utf8               Lorg/sireum/package$;
  #110 = Utf8               Spec$module
  #111 = Utf8               Lorg/sireum/contract$Spec$;
  #112 = Utf8               Contract$module
  #113 = Utf8               Lorg/sireum/contract$Contract$;
  #114 = Utf8               All$module
  #115 = Utf8               Lorg/sireum/contract$All$;
  #116 = Utf8               $u2200$module
  #117 = Utf8               Lorg/sireum/contract$$u2200$;
  #118 = Utf8               Exists$module
  #119 = Utf8               Lorg/sireum/contract$Exists$;
  #120 = Utf8               $u2203$module
  #121 = Utf8               Lorg/sireum/contract$$u2203$;
  #122 = Utf8               ISZ$module
  #123 = Utf8               Lorg/sireum/$internal/PackageTrait$ISZ$;
  #124 = Utf8               MSZ$module
  #125 = Utf8               Lorg/sireum/$internal/PackageTrait$MSZ$;
  #126 = Utf8               ZS$module
  #127 = Utf8               Lorg/sireum/$internal/PackageTrait$ZS$;
  #128 = Utf8               T
  #129 = Utf8               Z
  #130 = Utf8               F
  #131 = Utf8               $ZCompanion
  #132 = Utf8               Lorg/sireum/$ZCompanion;
  #133 = Utf8               Lorg/sireum/$ZCompanion<Lorg/sireum/Z;>;
  #134 = Utf8               <clinit>
  #135 = Utf8               ()V
  #136 = Utf8               <init>
  #137 = NameAndType        #136:#135     // "<init>":()V
  #138 = Methodref          #2.#137       // org/sireum/package$."<init>":()V
  #139 = NameAndType        #108:#109     // MODULE$:Lorg/sireum/package$;
  #140 = Fieldref           #2.#139       // org/sireum/package$.MODULE$:Lorg/sireum/package$;
  #141 = Utf8               $init$
  #142 = Utf8               (Lorg/sireum/$internal/PackageTrait;)V
  #143 = NameAndType        #141:#142     // $init$:(Lorg/sireum/$internal/PackageTrait;)V
  #144 = InterfaceMethodref #6.#143       // org/sireum/$internal/PackageTrait.$init$:(Lorg/sireum/$internal/PackageTrait;)V
  #145 = Utf8               (Lorg/sireum/contract;)V
  #146 = NameAndType        #141:#145     // $init$:(Lorg/sireum/contract;)V
  #147 = InterfaceMethodref #8.#146       // org/sireum/contract.$init$:(Lorg/sireum/contract;)V
  #148 = Utf8               (Lorg/sireum/Z;)Lorg/sireum/contract$Contract$MaxIt;
  #149 = Utf8               num
  #150 = Utf8               MaxIt$
  #151 = Utf8               (Lorg/sireum/contract;Lorg/sireum/Z;)Lorg/sireum/contract$Contract$MaxIt;
  #152 = NameAndType        #150:#151     // MaxIt$:(Lorg/sireum/contract;Lorg/sireum/Z;)Lorg/sireum/contract$Contract$MaxIt;
  #153 = InterfaceMethodref #8.#152       // org/sireum/contract.MaxIt$:(Lorg/sireum/contract;Lorg/sireum/Z;)Lorg/sireum/contract$Contract$MaxIt;
  #154 = Utf8               this
  #155 = Utf8               Lorg/sireum/Z;
  #156 = Utf8               (Lscala/collection/immutable/Seq;)Lorg/sireum/contract$Contract$Reads;
  #157 = Utf8               (Lscala/collection/immutable/Seq<Ljava/lang/Object;>;)Lorg/sireum/contract$Contract$Reads;
  #158 = Utf8               accesses
  #159 = Utf8               Reads$
  #160 = Utf8               (Lorg/sireum/contract;Lscala/collection/immutable/Seq;)Lorg/sireum/contract$Contract$Reads;
  #161 = NameAndType        #159:#160     // Reads$:(Lorg/sireum/contract;Lscala/collection/immutable/Seq;)Lorg/sireum/contract$Contract$Reads;
  #162 = InterfaceMethodref #8.#161       // org/sireum/contract.Reads$:(Lorg/sireum/contract;Lscala/collection/immutable/Seq;)Lorg/sireum/contract$Contract$Reads;
  #163 = Utf8               Lscala/collection/immutable/Seq;
  #164 = Utf8               (Lscala/collection/immutable/Seq;)Lorg/sireum/contract$Contract$Requires;
  #165 = Utf8               (Lscala/collection/immutable/Seq<Lorg/sireum/B;>;)Lorg/sireum/contract$Contract$Requires;
  #166 = Utf8               claims
  #167 = Utf8               Requires$
  #168 = Utf8               (Lorg/sireum/contract;Lscala/collection/immutable/Seq;)Lorg/sireum/contract$Contract$Requires;
  #169 = NameAndType        #167:#168     // Requires$:(Lorg/sireum/contract;Lscala/collection/immutable/Seq;)Lorg/sireum/contract$Contract$Requires;
  #170 = InterfaceMethodref #8.#169       // org/sireum/contract.Requires$:(Lorg/sireum/contract;Lscala/collection/immutable/Seq;)Lorg/sireum/contract$Contract$Requires;
  #171 = Utf8               (Lscala/collection/immutable/Seq;)Lorg/sireum/contract$Contract$Modifies;
  #172 = Utf8               (Lscala/collection/immutable/Seq<Ljava/lang/Object;>;)Lorg/sireum/contract$Contract$Modifies;
  #173 = Utf8               Modifies$
  #174 = Utf8               (Lorg/sireum/contract;Lscala/collection/immutable/Seq;)Lorg/sireum/contract$Contract$Modifies;
  #175 = NameAndType        #173:#174     // Modifies$:(Lorg/sireum/contract;Lscala/collection/immutable/Seq;)Lorg/sireum/contract$Contract$Modifies;
  #176 = InterfaceMethodref #8.#175       // org/sireum/contract.Modifies$:(Lorg/sireum/contract;Lscala/collection/immutable/Seq;)Lorg/sireum/contract$Contract$Modifies;
  #177 = Utf8               (Lscala/collection/immutable/Seq;)Lorg/sireum/contract$Contract$Ensures;
  #178 = Utf8               (Lscala/collection/immutable/Seq<Lorg/sireum/B;>;)Lorg/sireum/contract$Contract$Ensures;
  #179 = Utf8               Ensures$
  #180 = Utf8               (Lorg/sireum/contract;Lscala/collection/immutable/Seq;)Lorg/sireum/contract$Contract$Ensures;
  #181 = NameAndType        #179:#180     // Ensures$:(Lorg/sireum/contract;Lscala/collection/immutable/Seq;)Lorg/sireum/contract$Contract$Ensures;
  #182 = InterfaceMethodref #8.#181       // org/sireum/contract.Ensures$:(Lorg/sireum/contract;Lscala/collection/immutable/Seq;)Lorg/sireum/contract$Contract$Ensures;
  #183 = Utf8               (Lscala/collection/immutable/Seq;)Lorg/sireum/contract$Contract$Invariant;
  #184 = Utf8               (Lscala/collection/immutable/Seq<Lorg/sireum/B;>;)Lorg/sireum/contract$Contract$Invariant;
  #185 = Utf8               Invariant$
  #186 = Utf8               (Lorg/sireum/contract;Lscala/collection/immutable/Seq;)Lorg/sireum/contract$Contract$Invariant;
  #187 = NameAndType        #185:#186     // Invariant$:(Lorg/sireum/contract;Lscala/collection/immutable/Seq;)Lorg/sireum/contract$Contract$Invariant;
  #188 = InterfaceMethodref #8.#187       // org/sireum/contract.Invariant$:(Lorg/sireum/contract;Lscala/collection/immutable/Seq;)Lorg/sireum/contract$Contract$Invariant;
  #189 = Utf8               (Ljava/lang/String;Lscala/collection/immutable/Seq;)Lorg/sireum/contract$Contract$Invariant;
  #190 = Utf8               (Ljava/lang/String;Lscala/collection/immutable/Seq<Lorg/sireum/B;>;)Lorg/sireum/contract$Contract$Invariant;
  #191 = Utf8               desc
  #192 = Utf8               (Lorg/sireum/contract;Ljava/lang/String;Lscala/collection/immutable/Seq;)Lorg/sireum/contract$Contract$Invariant;
  #193 = NameAndType        #185:#192     // Invariant$:(Lorg/sireum/contract;Ljava/lang/String;Lscala/collection/immutable/Seq;)Lorg/sireum/contract$Contract$Invariant;
  #194 = InterfaceMethodref #8.#193       // org/sireum/contract.Invariant$:(Lorg/sireum/contract;Ljava/lang/String;Lscala/collection/immutable/Seq;)Lorg/sireum/contract$Contract$Invariant;
  #195 = Utf8               Ljava/lang/String;
  #196 = Utf8               (Ljava/lang/Object;Lscala/collection/immutable/Seq;Lscala/collection/immutable/Seq;)Lorg/sireum/contract$Contract$DataRefinement;
  #197 = Utf8               (Ljava/lang/Object;Lscala/collection/immutable/Seq<Ljava/lang/Object;>;Lscala/collection/immutable/Seq<Lorg/sireum/B;>;)Lorg/sireum/contract$Contract$DataRefinement;
  #198 = Utf8               rep
  #199 = Utf8               refs
  #200 = Utf8               DataRefinement$
  #201 = Utf8               (Lorg/sireum/contract;Ljava/lang/Object;Lscala/collection/immutable/Seq;Lscala/collection/immutable/Seq;)Lorg/sireum/contract$Contract$DataRefinement;
  #202 = NameAndType        #200:#201     // DataRefinement$:(Lorg/sireum/contract;Ljava/lang/Object;Lscala/collection/immutable/Seq;Lscala/collection/immutable/Seq;)Lorg/sireum/contract$Contract$DataRefinement;
  #203 = InterfaceMethodref #8.#202       // org/sireum/contract.DataRefinement$:(Lorg/sireum/contract;Ljava/lang/Object;Lscala/collection/immutable/Seq;Lscala/collection/immutable/Seq;)Lorg/sireum/contract$Contract$DataRefinement;
  #204 = Utf8               Ljava/lang/Object;
  #205 = Utf8               (Lorg/sireum/contract$Contract$Requires;)Lorg/sireum/contract$Contract$Case;
  #206 = Utf8               requires
  #207 = Utf8               Case$
  #208 = Utf8               (Lorg/sireum/contract;Lorg/sireum/contract$Contract$Requires;)Lorg/sireum/contract$Contract$Case;
  #209 = NameAndType        #207:#208     // Case$:(Lorg/sireum/contract;Lorg/sireum/contract$Contract$Requires;)Lorg/sireum/contract$Contract$Case;
  #210 = InterfaceMethodref #8.#209       // org/sireum/contract.Case$:(Lorg/sireum/contract;Lorg/sireum/contract$Contract$Requires;)Lorg/sireum/contract$Contract$Case;
  #211 = Utf8               Lorg/sireum/contract$Contract$Requires;
  #212 = Utf8               (Lorg/sireum/contract$Contract$Ensures;)Lorg/sireum/contract$Contract$Case;
  #213 = Utf8               ensures
  #214 = Utf8               (Lorg/sireum/contract;Lorg/sireum/contract$Contract$Ensures;)Lorg/sireum/contract$Contract$Case;
  #215 = NameAndType        #207:#214     // Case$:(Lorg/sireum/contract;Lorg/sireum/contract$Contract$Ensures;)Lorg/sireum/contract$Contract$Case;
  #216 = InterfaceMethodref #8.#215       // org/sireum/contract.Case$:(Lorg/sireum/contract;Lorg/sireum/contract$Contract$Ensures;)Lorg/sireum/contract$Contract$Case;
  #217 = Utf8               Lorg/sireum/contract$Contract$Ensures;
  #218 = Utf8               (Lorg/sireum/contract$Contract$Requires;Lorg/sireum/contract$Contract$Ensures;)Lorg/sireum/contract$Contract$Case;
  #219 = Utf8               (Lorg/sireum/contract;Lorg/sireum/contract$Contract$Requires;Lorg/sireum/contract$Contract$Ensures;)Lorg/sireum/contract$Contract$Case;
  #220 = NameAndType        #207:#219     // Case$:(Lorg/sireum/contract;Lorg/sireum/contract$Contract$Requires;Lorg/sireum/contract$Contract$Ensures;)Lorg/sireum/contract$Contract$Case;
  #221 = InterfaceMethodref #8.#220       // org/sireum/contract.Case$:(Lorg/sireum/contract;Lorg/sireum/contract$Contract$Requires;Lorg/sireum/contract$Contract$Ensures;)Lorg/sireum/contract$Contract$Case;
  #222 = Utf8               (Ljava/lang/String;Lorg/sireum/contract$Contract$Requires;)Lorg/sireum/contract$Contract$Case;
  #223 = Utf8               name
  #224 = Utf8               (Lorg/sireum/contract;Ljava/lang/String;Lorg/sireum/contract$Contract$Requires;)Lorg/sireum/contract$Contract$Case;
  #225 = NameAndType        #207:#224     // Case$:(Lorg/sireum/contract;Ljava/lang/String;Lorg/sireum/contract$Contract$Requires;)Lorg/sireum/contract$Contract$Case;
  #226 = InterfaceMethodref #8.#225       // org/sireum/contract.Case$:(Lorg/sireum/contract;Ljava/lang/String;Lorg/sireum/contract$Contract$Requires;)Lorg/sireum/contract$Contract$Case;
  #227 = Utf8               (Ljava/lang/String;Lorg/sireum/contract$Contract$Ensures;)Lorg/sireum/contract$Contract$Case;
  #228 = Utf8               (Lorg/sireum/contract;Ljava/lang/String;Lorg/sireum/contract$Contract$Ensures;)Lorg/sireum/contract$Contract$Case;
  #229 = NameAndType        #207:#228     // Case$:(Lorg/sireum/contract;Ljava/lang/String;Lorg/sireum/contract$Contract$Ensures;)Lorg/sireum/contract$Contract$Case;
  #230 = InterfaceMethodref #8.#229       // org/sireum/contract.Case$:(Lorg/sireum/contract;Ljava/lang/String;Lorg/sireum/contract$Contract$Ensures;)Lorg/sireum/contract$Contract$Case;
  #231 = Utf8               (Ljava/lang/String;Lorg/sireum/contract$Contract$Requires;Lorg/sireum/contract$Contract$Ensures;)Lorg/sireum/contract$Contract$Case;
  #232 = Utf8               (Lorg/sireum/contract;Ljava/lang/String;Lorg/sireum/contract$Contract$Requires;Lorg/sireum/contract$Contract$Ensures;)Lorg/sireum/contract$Contract$Case;
  #233 = NameAndType        #207:#232     // Case$:(Lorg/sireum/contract;Ljava/lang/String;Lorg/sireum/contract$Contract$Requires;Lorg/sireum/contract$Contract$Ensures;)Lorg/sireum/contract$Contract$Case;
  #234 = InterfaceMethodref #8.#233       // org/sireum/contract.Case$:(Lorg/sireum/contract;Ljava/lang/String;Lorg/sireum/contract$Contract$Requires;Lorg/sireum/contract$Contract$Ensures;)Lorg/sireum/contract$Contract$Case;
  #235 = Utf8               (Lscala/collection/immutable/Seq;)Lorg/sireum/contract$Contract$Fact;
  #236 = Utf8               (Lscala/collection/immutable/Seq<Lorg/sireum/B;>;)Lorg/sireum/contract$Contract$Fact;
  #237 = Utf8               Fact$
  #238 = Utf8               (Lorg/sireum/contract;Lscala/collection/immutable/Seq;)Lorg/sireum/contract$Contract$Fact;
  #239 = NameAndType        #237:#238     // Fact$:(Lorg/sireum/contract;Lscala/collection/immutable/Seq;)Lorg/sireum/contract$Contract$Fact;
  #240 = InterfaceMethodref #8.#239       // org/sireum/contract.Fact$:(Lorg/sireum/contract;Lscala/collection/immutable/Seq;)Lorg/sireum/contract$Contract$Fact;
  #241 = Utf8               (Ljava/lang/String;Lscala/collection/immutable/Seq;)Lorg/sireum/contract$Contract$Fact;
  #242 = Utf8               (Ljava/lang/String;Lscala/collection/immutable/Seq<Lorg/sireum/B;>;)Lorg/sireum/contract$Contract$Fact;
  #243 = Utf8               (Lorg/sireum/contract;Ljava/lang/String;Lscala/collection/immutable/Seq;)Lorg/sireum/contract$Contract$Fact;
  #244 = NameAndType        #237:#243     // Fact$:(Lorg/sireum/contract;Ljava/lang/String;Lscala/collection/immutable/Seq;)Lorg/sireum/contract$Contract$Fact;
  #245 = InterfaceMethodref #8.#244       // org/sireum/contract.Fact$:(Lorg/sireum/contract;Ljava/lang/String;Lscala/collection/immutable/Seq;)Lorg/sireum/contract$Contract$Fact;
  #246 = Utf8               (ZLorg/sireum/contract$Contract$Proof;)Lorg/sireum/contract$Contract$Lemma;
  #247 = Utf8               claim
  #248 = Utf8               proof
  #249 = Utf8               Lemma$
  #250 = Utf8               (Lorg/sireum/contract;ZLorg/sireum/contract$Contract$Proof;)Lorg/sireum/contract$Contract$Lemma;
  #251 = NameAndType        #249:#250     // Lemma$:(Lorg/sireum/contract;ZLorg/sireum/contract$Contract$Proof;)Lorg/sireum/contract$Contract$Lemma;
  #252 = InterfaceMethodref #8.#251       // org/sireum/contract.Lemma$:(Lorg/sireum/contract;ZLorg/sireum/contract$Contract$Proof;)Lorg/sireum/contract$Contract$Lemma;
  #253 = Utf8               Lorg/sireum/contract$Contract$Proof;
  #254 = Utf8               (Ljava/lang/String;ZLorg/sireum/contract$Contract$Proof;)Lorg/sireum/contract$Contract$Lemma;
  #255 = Utf8               (Lorg/sireum/contract;Ljava/lang/String;ZLorg/sireum/contract$Contract$Proof;)Lorg/sireum/contract$Contract$Lemma;
  #256 = NameAndType        #249:#255     // Lemma$:(Lorg/sireum/contract;Ljava/lang/String;ZLorg/sireum/contract$Contract$Proof;)Lorg/sireum/contract$Contract$Lemma;
  #257 = InterfaceMethodref #8.#256       // org/sireum/contract.Lemma$:(Lorg/sireum/contract;Ljava/lang/String;ZLorg/sireum/contract$Contract$Proof;)Lorg/sireum/contract$Contract$Lemma;
  #258 = Utf8               (ZLorg/sireum/contract$Contract$Proof;)Lorg/sireum/contract$Contract$Theorem;
  #259 = Utf8               Theorem$
  #260 = Utf8               (Lorg/sireum/contract;ZLorg/sireum/contract$Contract$Proof;)Lorg/sireum/contract$Contract$Theorem;
  #261 = NameAndType        #259:#260     // Theorem$:(Lorg/sireum/contract;ZLorg/sireum/contract$Contract$Proof;)Lorg/sireum/contract$Contract$Theorem;
  #262 = InterfaceMethodref #8.#261       // org/sireum/contract.Theorem$:(Lorg/sireum/contract;ZLorg/sireum/contract$Contract$Proof;)Lorg/sireum/contract$Contract$Theorem;
  #263 = Utf8               (Ljava/lang/String;ZLorg/sireum/contract$Contract$Proof;)Lorg/sireum/contract$Contract$Theorem;
  #264 = Utf8               (Lorg/sireum/contract;Ljava/lang/String;ZLorg/sireum/contract$Contract$Proof;)Lorg/sireum/contract$Contract$Theorem;
  #265 = NameAndType        #259:#264     // Theorem$:(Lorg/sireum/contract;Ljava/lang/String;ZLorg/sireum/contract$Contract$Proof;)Lorg/sireum/contract$Contract$Theorem;
  #266 = InterfaceMethodref #8.#265       // org/sireum/contract.Theorem$:(Lorg/sireum/contract;Ljava/lang/String;ZLorg/sireum/contract$Contract$Proof;)Lorg/sireum/contract$Contract$Theorem;
  #267 = Utf8               (Lscala/collection/immutable/Seq;)Lorg/sireum/contract$Contract$Proof;
  #268 = Utf8               (Lscala/collection/immutable/Seq<Lorg/sireum/contract$Contract$ProofStep;>;)Lorg/sireum/contract$Contract$Proof;
  #269 = Utf8               steps
  #270 = Utf8               Proof$
  #271 = Utf8               (Lorg/sireum/contract;Lscala/collection/immutable/Seq;)Lorg/sireum/contract$Contract$Proof;
  #272 = NameAndType        #270:#271     // Proof$:(Lorg/sireum/contract;Lscala/collection/immutable/Seq;)Lorg/sireum/contract$Contract$Proof;
  #273 = InterfaceMethodref #8.#272       // org/sireum/contract.Proof$:(Lorg/sireum/contract;Lscala/collection/immutable/Seq;)Lorg/sireum/contract$Contract$Proof;
  #274 = Utf8               Step
  #275 = Utf8               (IZ)Lorg/sireum/contract$Contract$ProofStep;
  #276 = Utf8               no
  #277 = Utf8               Step$
  #278 = Utf8               (Lorg/sireum/contract;IZ)Lorg/sireum/contract$Contract$ProofStep;
  #279 = NameAndType        #277:#278     // Step$:(Lorg/sireum/contract;IZ)Lorg/sireum/contract$Contract$ProofStep;
  #280 = InterfaceMethodref #8.#279       // org/sireum/contract.Step$:(Lorg/sireum/contract;IZ)Lorg/sireum/contract$Contract$ProofStep;
  #281 = Utf8               I
  #282 = Utf8               (IZLorg/sireum/contract$Contract$Justification;)Lorg/sireum/contract$Contract$ProofStep;
  #283 = Utf8               just
  #284 = Utf8               (Lorg/sireum/contract;IZLorg/sireum/contract$Contract$Justification;)Lorg/sireum/contract$Contract$ProofStep;
  #285 = NameAndType        #277:#284     // Step$:(Lorg/sireum/contract;IZLorg/sireum/contract$Contract$Justification;)Lorg/sireum/contract$Contract$ProofStep;
  #286 = InterfaceMethodref #8.#285       // org/sireum/contract.Step$:(Lorg/sireum/contract;IZLorg/sireum/contract$Contract$Justification;)Lorg/sireum/contract$Contract$ProofStep;
  #287 = Utf8               Lorg/sireum/contract$Contract$Justification;
  #288 = Utf8               (Lscala/collection/immutable/Seq;)Lorg/sireum/contract$Contract$SubProof;
  #289 = Utf8               (Lscala/collection/immutable/Seq<Lorg/sireum/contract$Contract$ProofStep;>;)Lorg/sireum/contract$Contract$SubProof;
  #290 = Utf8               SubProof$
  #291 = Utf8               (Lorg/sireum/contract;Lscala/collection/immutable/Seq;)Lorg/sireum/contract$Contract$SubProof;
  #292 = NameAndType        #290:#291     // SubProof$:(Lorg/sireum/contract;Lscala/collection/immutable/Seq;)Lorg/sireum/contract$Contract$SubProof;
  #293 = InterfaceMethodref #8.#292       // org/sireum/contract.SubProof$:(Lorg/sireum/contract;Lscala/collection/immutable/Seq;)Lorg/sireum/contract$Contract$SubProof;
  #294 = Utf8               (Z)Lorg/sireum/contract$Contract$Assume;
  #295 = Utf8               Assume$
  #296 = Utf8               (Lorg/sireum/contract;Z)Lorg/sireum/contract$Contract$Assume;
  #297 = NameAndType        #295:#296     // Assume$:(Lorg/sireum/contract;Z)Lorg/sireum/contract$Contract$Assume;
  #298 = InterfaceMethodref #8.#297       // org/sireum/contract.Assume$:(Lorg/sireum/contract;Z)Lorg/sireum/contract$Contract$Assume;
  #299 = Utf8               (ZLorg/sireum/contract$Contract$SubProof;)Lorg/sireum/contract$Contract$Assert;
  #300 = Utf8               subProof
  #301 = Utf8               Assert$
  #302 = Utf8               (Lorg/sireum/contract;ZLorg/sireum/contract$Contract$SubProof;)Lorg/sireum/contract$Contract$Assert;
  #303 = NameAndType        #301:#302     // Assert$:(Lorg/sireum/contract;ZLorg/sireum/contract$Contract$SubProof;)Lorg/sireum/contract$Contract$Assert;
  #304 = InterfaceMethodref #8.#303       // org/sireum/contract.Assert$:(Lorg/sireum/contract;ZLorg/sireum/contract$Contract$SubProof;)Lorg/sireum/contract$Contract$Assert;
  #305 = Utf8               Lorg/sireum/contract$Contract$SubProof;
  #306 = Utf8               StructuralInduction
  #307 = Utf8               (Lorg/sireum/contract$Contract$SubProof;)Lorg/sireum/contract$Contract$Justification;
  #308 = Utf8               StructuralInduction$
  #309 = Utf8               (Lorg/sireum/contract;Lorg/sireum/contract$Contract$SubProof;)Lorg/sireum/contract$Contract$Justification;
  #310 = NameAndType        #308:#309     // StructuralInduction$:(Lorg/sireum/contract;Lorg/sireum/contract$Contract$SubProof;)Lorg/sireum/contract$Contract$Justification;
  #311 = InterfaceMethodref #8.#310       // org/sireum/contract.StructuralInduction$:(Lorg/sireum/contract;Lorg/sireum/contract$Contract$SubProof;)Lorg/sireum/contract$Contract$Justification;
  #312 = Utf8               (Lscala/Function1;)Lorg/sireum/contract$Contract$Let;
  #313 = Utf8               <T:Ljava/lang/Object;>(Lscala/Function1<TT;Lorg/sireum/contract$Contract$SubProof;>;)Lorg/sireum/contract$Contract$Let;
  #314 = Utf8               body
  #315 = Utf8               Let$
  #316 = Utf8               (Lorg/sireum/contract;Lscala/Function1;)Lorg/sireum/contract$Contract$Let;
  #317 = NameAndType        #315:#316     // Let$:(Lorg/sireum/contract;Lscala/Function1;)Lorg/sireum/contract$Contract$Let;
  #318 = InterfaceMethodref #8.#317       // org/sireum/contract.Let$:(Lorg/sireum/contract;Lscala/Function1;)Lorg/sireum/contract$Contract$Let;
  #319 = Utf8               Lscala/Function1;
  #320 = Utf8               (Lscala/Function2;)Lorg/sireum/contract$Contract$Let;
  #321 = Utf8               <T1:Ljava/lang/Object;T2:Ljava/lang/Object;>(Lscala/Function2<TT1;TT2;Lorg/sireum/contract$Contract$SubProof;>;)Lorg/sireum/contract$Contract$Let;
  #322 = Utf8               (Lorg/sireum/contract;Lscala/Function2;)Lorg/sireum/contract$Contract$Let;
  #323 = NameAndType        #315:#322     // Let$:(Lorg/sireum/contract;Lscala/Function2;)Lorg/sireum/contract$Contract$Let;
  #324 = InterfaceMethodref #8.#323       // org/sireum/contract.Let$:(Lorg/sireum/contract;Lscala/Function2;)Lorg/sireum/contract$Contract$Let;
  #325 = Utf8               Lscala/Function2;
  #326 = Utf8               (Lscala/Function3;)Lorg/sireum/contract$Contract$Let;
  #327 = Utf8               <T1:Ljava/lang/Object;T2:Ljava/lang/Object;T3:Ljava/lang/Object;>(Lscala/Function3<TT1;TT2;TT3;Lorg/sireum/contract$Contract$SubProof;>;)Lorg/sireum/contract$Contract$Let;
  #328 = Utf8               (Lorg/sireum/contract;Lscala/Function3;)Lorg/sireum/contract$Contract$Let;
  #329 = NameAndType        #315:#328     // Let$:(Lorg/sireum/contract;Lscala/Function3;)Lorg/sireum/contract$Contract$Let;
  #330 = InterfaceMethodref #8.#329       // org/sireum/contract.Let$:(Lorg/sireum/contract;Lscala/Function3;)Lorg/sireum/contract$Contract$Let;
  #331 = Utf8               Lscala/Function3;
  #332 = Utf8               (Lscala/Function4;)Lorg/sireum/contract$Contract$Let;
  #333 = Utf8               <T1:Ljava/lang/Object;T2:Ljava/lang/Object;T3:Ljava/lang/Object;T4:Ljava/lang/Object;>(Lscala/Function4<TT1;TT2;TT3;TT4;Lorg/sireum/contract$Contract$SubProof;>;)Lorg/sireum/contract$Contract$Let;
  #334 = Utf8               (Lorg/sireum/contract;Lscala/Function4;)Lorg/sireum/contract$Contract$Let;
  #335 = NameAndType        #315:#334     // Let$:(Lorg/sireum/contract;Lscala/Function4;)Lorg/sireum/contract$Contract$Let;
  #336 = InterfaceMethodref #8.#335       // org/sireum/contract.Let$:(Lorg/sireum/contract;Lscala/Function4;)Lorg/sireum/contract$Contract$Let;
  #337 = Utf8               Lscala/Function4;
  #338 = Utf8               (Lscala/Function5;)Lorg/sireum/contract$Contract$Let;
  #339 = Utf8               <T1:Ljava/lang/Object;T2:Ljava/lang/Object;T3:Ljava/lang/Object;T4:Ljava/lang/Object;T5:Ljava/lang/Object;>(Lscala/Function5<TT1;TT2;TT3;TT4;TT5;Lorg/sireum/contract$Contract$SubProof;>;)Lorg/sireum/contract$Contract$Let;
  #340 = Utf8               (Lorg/sireum/contract;Lscala/Function5;)Lorg/sireum/contract$Contract$Let;
  #341 = NameAndType        #315:#340     // Let$:(Lorg/sireum/contract;Lscala/Function5;)Lorg/sireum/contract$Contract$Let;
  #342 = InterfaceMethodref #8.#341       // org/sireum/contract.Let$:(Lorg/sireum/contract;Lscala/Function5;)Lorg/sireum/contract$Contract$Let;
  #343 = Utf8               Lscala/Function5;
  #344 = Utf8               (Lscala/Function6;)Lorg/sireum/contract$Contract$Let;
  #345 = Utf8               <T1:Ljava/lang/Object;T2:Ljava/lang/Object;T3:Ljava/lang/Object;T4:Ljava/lang/Object;T5:Ljava/lang/Object;T6:Ljava/lang/Object;>(Lscala/Function6<TT1;TT2;TT3;TT4;TT5;TT6;Lorg/sireum/contract$Contract$SubProof;>;)Lorg/sireum/contract$Contract$Let;
  #346 = Utf8               (Lorg/sireum/contract;Lscala/Function6;)Lorg/sireum/contract$Contract$Let;
  #347 = NameAndType        #315:#346     // Let$:(Lorg/sireum/contract;Lscala/Function6;)Lorg/sireum/contract$Contract$Let;
  #348 = InterfaceMethodref #8.#347       // org/sireum/contract.Let$:(Lorg/sireum/contract;Lscala/Function6;)Lorg/sireum/contract$Contract$Let;
  #349 = Utf8               Lscala/Function6;
  #350 = Utf8               (Lscala/Function7;)Lorg/sireum/contract$Contract$Let;
  #351 = Utf8               <T1:Ljava/lang/Object;T2:Ljava/lang/Object;T3:Ljava/lang/Object;T4:Ljava/lang/Object;T5:Ljava/lang/Object;T6:Ljava/lang/Object;T7:Ljava/lang/Object;>(Lscala/Function7<TT1;TT2;TT3;TT4;TT5;TT6;TT7;Lorg/sireum/contract$Contract$SubProof;>;)Lorg/sireum/contract$Contract$Let;
  #352 = Utf8               (Lorg/sireum/contract;Lscala/Function7;)Lorg/sireum/contract$Contract$Let;
  #353 = NameAndType        #315:#352     // Let$:(Lorg/sireum/contract;Lscala/Function7;)Lorg/sireum/contract$Contract$Let;
  #354 = InterfaceMethodref #8.#353       // org/sireum/contract.Let$:(Lorg/sireum/contract;Lscala/Function7;)Lorg/sireum/contract$Contract$Let;
  #355 = Utf8               Lscala/Function7;
  #356 = Utf8               (Lscala/Function8;)Lorg/sireum/contract$Contract$Let;
  #357 = Utf8               <T1:Ljava/lang/Object;T2:Ljava/lang/Object;T3:Ljava/lang/Object;T4:Ljava/lang/Object;T5:Ljava/lang/Object;T6:Ljava/lang/Object;T7:Ljava/lang/Object;T8:Ljava/lang/Object;>(Lscala/Function8<TT1;TT2;TT3;TT4;TT5;TT6;TT7;TT8;Lorg/sireum/contract$Contract$SubProof;>;)Lorg/sireum/contract$Contract$Let;
  #358 = Utf8               (Lorg/sireum/contract;Lscala/Function8;)Lorg/sireum/contract$Contract$Let;
  #359 = NameAndType        #315:#358     // Let$:(Lorg/sireum/contract;Lscala/Function8;)Lorg/sireum/contract$Contract$Let;
  #360 = InterfaceMethodref #8.#359       // org/sireum/contract.Let$:(Lorg/sireum/contract;Lscala/Function8;)Lorg/sireum/contract$Contract$Let;
  #361 = Utf8               Lscala/Function8;
  #362 = Utf8               (Lscala/Function9;)Lorg/sireum/contract$Contract$Let;
  #363 = Utf8               <T1:Ljava/lang/Object;T2:Ljava/lang/Object;T3:Ljava/lang/Object;T4:Ljava/lang/Object;T5:Ljava/lang/Object;T6:Ljava/lang/Object;T7:Ljava/lang/Object;T8:Ljava/lang/Object;T9:Ljava/lang/Object;>(Lscala/Function9<TT1;TT2;TT3;TT4;TT5;TT6;TT7;TT8;TT9;Lorg/sireum/contract$Contract$SubProof;>;)Lorg/sireum/contract$Contract$Let;
  #364 = Utf8               (Lorg/sireum/contract;Lscala/Function9;)Lorg/sireum/contract$Contract$Let;
  #365 = NameAndType        #315:#364     // Let$:(Lorg/sireum/contract;Lscala/Function9;)Lorg/sireum/contract$Contract$Let;
  #366 = InterfaceMethodref #8.#365       // org/sireum/contract.Let$:(Lorg/sireum/contract;Lscala/Function9;)Lorg/sireum/contract$Contract$Let;
  #367 = Utf8               Lscala/Function9;
  #368 = Utf8               (Lscala/Function10;)Lorg/sireum/contract$Contract$Let;
  #369 = Utf8               <T1:Ljava/lang/Object;T2:Ljava/lang/Object;T3:Ljava/lang/Object;T4:Ljava/lang/Object;T5:Ljava/lang/Object;T6:Ljava/lang/Object;T7:Ljava/lang/Object;T8:Ljava/lang/Object;T9:Ljava/lang/Object;T10:Ljava/lang/Object;>(Lscala/Function10<TT1;TT2;TT3;TT4;TT5;TT6;TT7;TT8;TT9;TT10;Lorg/sireum/contract$Contract$SubProof;>;)Lorg/sireum/contract$Contract$Let;
  #370 = Utf8               (Lorg/sireum/contract;Lscala/Function10;)Lorg/sireum/contract$Contract$Let;
  #371 = NameAndType        #315:#370     // Let$:(Lorg/sireum/contract;Lscala/Function10;)Lorg/sireum/contract$Contract$Let;
  #372 = InterfaceMethodref #8.#371       // org/sireum/contract.Let$:(Lorg/sireum/contract;Lscala/Function10;)Lorg/sireum/contract$Contract$Let;
  #373 = Utf8               Lscala/Function10;
  #374 = Utf8               (Lscala/Function11;)Lorg/sireum/contract$Contract$Let;
  #375 = Utf8               <T1:Ljava/lang/Object;T2:Ljava/lang/Object;T3:Ljava/lang/Object;T4:Ljava/lang/Object;T5:Ljava/lang/Object;T6:Ljava/lang/Object;T7:Ljava/lang/Object;T8:Ljava/lang/Object;T9:Ljava/lang/Object;T10:Ljava/lang/Object;T11:Ljava/lang/Object;>(Lscala/Function11<TT1;TT2;TT3;TT4;TT5;TT6;TT7;TT8;TT9;TT10;TT11;Lorg/sireum/contract$Contract$SubProof;>;)Lorg/sireum/contract$Contract$Let;
  #376 = Utf8               (Lorg/sireum/contract;Lscala/Function11;)Lorg/sireum/contract$Contract$Let;
  #377 = NameAndType        #315:#376     // Let$:(Lorg/sireum/contract;Lscala/Function11;)Lorg/sireum/contract$Contract$Let;
  #378 = InterfaceMethodref #8.#377       // org/sireum/contract.Let$:(Lorg/sireum/contract;Lscala/Function11;)Lorg/sireum/contract$Contract$Let;
  #379 = Utf8               Lscala/Function11;
  #380 = Utf8               (Lscala/Function12;)Lorg/sireum/contract$Contract$Let;
  #381 = Utf8               <T1:Ljava/lang/Object;T2:Ljava/lang/Object;T3:Ljava/lang/Object;T4:Ljava/lang/Object;T5:Ljava/lang/Object;T6:Ljava/lang/Object;T7:Ljava/lang/Object;T8:Ljava/lang/Object;T9:Ljava/lang/Object;T10:Ljava/lang/Object;T11:Ljava/lang/Object;T12:Ljava/lang/Object;>(Lscala/Function12<TT1;TT2;TT3;TT4;TT5;TT6;TT7;TT8;TT9;TT10;TT11;TT12;Lorg/sireum/contract$Contract$SubProof;>;)Lorg/sireum/contract$Contract$Let;
  #382 = Utf8               (Lorg/sireum/contract;Lscala/Function12;)Lorg/sireum/contract$Contract$Let;
  #383 = NameAndType        #315:#382     // Let$:(Lorg/sireum/contract;Lscala/Function12;)Lorg/sireum/contract$Contract$Let;
  #384 = InterfaceMethodref #8.#383       // org/sireum/contract.Let$:(Lorg/sireum/contract;Lscala/Function12;)Lorg/sireum/contract$Contract$Let;
  #385 = Utf8               Lscala/Function12;
  #386 = Utf8               (Lscala/Function13;)Lorg/sireum/contract$Contract$Let;
  #387 = Utf8               <T1:Ljava/lang/Object;T2:Ljava/lang/Object;T3:Ljava/lang/Object;T4:Ljava/lang/Object;T5:Ljava/lang/Object;T6:Ljava/lang/Object;T7:Ljava/lang/Object;T8:Ljava/lang/Object;T9:Ljava/lang/Object;T10:Ljava/lang/Object;T11:Ljava/lang/Object;T12:Ljava/lang/Object;T13:Ljava/lang/Object;>(Lscala/Function13<TT1;TT2;TT3;TT4;TT5;TT6;TT7;TT8;TT9;TT10;TT11;TT12;TT13;Lorg/sireum/contract$Contract$SubProof;>;)Lorg/sireum/contract$Contract$Let;
  #388 = Utf8               (Lorg/sireum/contract;Lscala/Function13;)Lorg/sireum/contract$Contract$Let;
  #389 = NameAndType        #315:#388     // Let$:(Lorg/sireum/contract;Lscala/Function13;)Lorg/sireum/contract$Contract$Let;
  #390 = InterfaceMethodref #8.#389       // org/sireum/contract.Let$:(Lorg/sireum/contract;Lscala/Function13;)Lorg/sireum/contract$Contract$Let;
  #391 = Utf8               Lscala/Function13;
  #392 = Utf8               (Lscala/Function14;)Lorg/sireum/contract$Contract$Let;
  #393 = Utf8               <T1:Ljava/lang/Object;T2:Ljava/lang/Object;T3:Ljava/lang/Object;T4:Ljava/lang/Object;T5:Ljava/lang/Object;T6:Ljava/lang/Object;T7:Ljava/lang/Object;T8:Ljava/lang/Object;T9:Ljava/lang/Object;T10:Ljava/lang/Object;T11:Ljava/lang/Object;T12:Ljava/lang/Object;T13:Ljava/lang/Object;T14:Ljava/lang/Object;>(Lscala/Function14<TT1;TT2;TT3;TT4;TT5;TT6;TT7;TT8;TT9;TT10;TT11;TT12;TT13;TT14;Lorg/sireum/contract$Contract$SubProof;>;)Lorg/sireum/contract$Contract$Let;
  #394 = Utf8               (Lorg/sireum/contract;Lscala/Function14;)Lorg/sireum/contract$Contract$Let;
  #395 = NameAndType        #315:#394     // Let$:(Lorg/sireum/contract;Lscala/Function14;)Lorg/sireum/contract$Contract$Let;
  #396 = InterfaceMethodref #8.#395       // org/sireum/contract.Let$:(Lorg/sireum/contract;Lscala/Function14;)Lorg/sireum/contract$Contract$Let;
  #397 = Utf8               Lscala/Function14;
  #398 = Utf8               (Lscala/Function15;)Lorg/sireum/contract$Contract$Let;
  #399 = Utf8               <T1:Ljava/lang/Object;T2:Ljava/lang/Object;T3:Ljava/lang/Object;T4:Ljava/lang/Object;T5:Ljava/lang/Object;T6:Ljava/lang/Object;T7:Ljava/lang/Object;T8:Ljava/lang/Object;T9:Ljava/lang/Object;T10:Ljava/lang/Object;T11:Ljava/lang/Object;T12:Ljava/lang/Object;T13:Ljava/lang/Object;T14:Ljava/lang/Object;T15:Ljava/lang/Object;>(Lscala/Function15<TT1;TT2;TT3;TT4;TT5;TT6;TT7;TT8;TT9;TT10;TT11;TT12;TT13;TT14;TT15;Lorg/sireum/contract$Contract$SubProof;>;)Lorg/sireum/contract$Contract$Let;
  #400 = Utf8               (Lorg/sireum/contract;Lscala/Function15;)Lorg/sireum/contract$Contract$Let;
  #401 = NameAndType        #315:#400     // Let$:(Lorg/sireum/contract;Lscala/Function15;)Lorg/sireum/contract$Contract$Let;
  #402 = InterfaceMethodref #8.#401       // org/sireum/contract.Let$:(Lorg/sireum/contract;Lscala/Function15;)Lorg/sireum/contract$Contract$Let;
  #403 = Utf8               Lscala/Function15;
  #404 = Utf8               (Lscala/Function16;)Lorg/sireum/contract$Contract$Let;
  #405 = Utf8               <T1:Ljava/lang/Object;T2:Ljava/lang/Object;T3:Ljava/lang/Object;T4:Ljava/lang/Object;T5:Ljava/lang/Object;T6:Ljava/lang/Object;T7:Ljava/lang/Object;T8:Ljava/lang/Object;T9:Ljava/lang/Object;T10:Ljava/lang/Object;T11:Ljava/lang/Object;T12:Ljava/lang/Object;T13:Ljava/lang/Object;T14:Ljava/lang/Object;T15:Ljava/lang/Object;T16:Ljava/lang/Object;>(Lscala/Function16<TT1;TT2;TT3;TT4;TT5;TT6;TT7;TT8;TT9;TT10;TT11;TT12;TT13;TT14;TT15;TT16;Lorg/sireum/contract$Contract$SubProof;>;)Lorg/sireum/contract$Contract$Let;
  #406 = Utf8               (Lorg/sireum/contract;Lscala/Function16;)Lorg/sireum/contract$Contract$Let;
  #407 = NameAndType        #315:#406     // Let$:(Lorg/sireum/contract;Lscala/Function16;)Lorg/sireum/contract$Contract$Let;
  #408 = InterfaceMethodref #8.#407       // org/sireum/contract.Let$:(Lorg/sireum/contract;Lscala/Function16;)Lorg/sireum/contract$Contract$Let;
  #409 = Utf8               Lscala/Function16;
  #410 = Utf8               (Lscala/Function17;)Lorg/sireum/contract$Contract$Let;
  #411 = Utf8               <T1:Ljava/lang/Object;T2:Ljava/lang/Object;T3:Ljava/lang/Object;T4:Ljava/lang/Object;T5:Ljava/lang/Object;T6:Ljava/lang/Object;T7:Ljava/lang/Object;T8:Ljava/lang/Object;T9:Ljava/lang/Object;T10:Ljava/lang/Object;T11:Ljava/lang/Object;T12:Ljava/lang/Object;T13:Ljava/lang/Object;T14:Ljava/lang/Object;T15:Ljava/lang/Object;T16:Ljava/lang/Object;T17:Ljava/lang/Object;>(Lscala/Function17<TT1;TT2;TT3;TT4;TT5;TT6;TT7;TT8;TT9;TT10;TT11;TT12;TT13;TT14;TT15;TT16;TT17;Lorg/sireum/contract$Contract$SubProof;>;)Lorg/sireum/contract$Contract$Let;
  #412 = Utf8               (Lorg/sireum/contract;Lscala/Function17;)Lorg/sireum/contract$Contract$Let;
  #413 = NameAndType        #315:#412     // Let$:(Lorg/sireum/contract;Lscala/Function17;)Lorg/sireum/contract$Contract$Let;
  #414 = InterfaceMethodref #8.#413       // org/sireum/contract.Let$:(Lorg/sireum/contract;Lscala/Function17;)Lorg/sireum/contract$Contract$Let;
  #415 = Utf8               Lscala/Function17;
  #416 = Utf8               (Lscala/Function18;)Lorg/sireum/contract$Contract$Let;
  #417 = Utf8               <T1:Ljava/lang/Object;T2:Ljava/lang/Object;T3:Ljava/lang/Object;T4:Ljava/lang/Object;T5:Ljava/lang/Object;T6:Ljava/lang/Object;T7:Ljava/lang/Object;T8:Ljava/lang/Object;T9:Ljava/lang/Object;T10:Ljava/lang/Object;T11:Ljava/lang/Object;T12:Ljava/lang/Object;T13:Ljava/lang/Object;T14:Ljava/lang/Object;T15:Ljava/lang/Object;T16:Ljava/lang/Object;T17:Ljava/lang/Object;T18:Ljava/lang/Object;>(Lscala/Function18<TT1;TT2;TT3;TT4;TT5;TT6;TT7;TT8;TT9;TT10;TT11;TT12;TT13;TT14;TT15;TT16;TT17;TT18;Lorg/sireum/contract$Contract$SubProof;>;)Lorg/sireum/contract$Contract$Let;
  #418 = Utf8               (Lorg/sireum/contract;Lscala/Function18;)Lorg/sireum/contract$Contract$Let;
  #419 = NameAndType        #315:#418     // Let$:(Lorg/sireum/contract;Lscala/Function18;)Lorg/sireum/contract$Contract$Let;
  #420 = InterfaceMethodref #8.#419       // org/sireum/contract.Let$:(Lorg/sireum/contract;Lscala/Function18;)Lorg/sireum/contract$Contract$Let;
  #421 = Utf8               Lscala/Function18;
  #422 = Utf8               (Lscala/Function19;)Lorg/sireum/contract$Contract$Let;
  #423 = Utf8               <T1:Ljava/lang/Object;T2:Ljava/lang/Object;T3:Ljava/lang/Object;T4:Ljava/lang/Object;T5:Ljava/lang/Object;T6:Ljava/lang/Object;T7:Ljava/lang/Object;T8:Ljava/lang/Object;T9:Ljava/lang/Object;T10:Ljava/lang/Object;T11:Ljava/lang/Object;T12:Ljava/lang/Object;T13:Ljava/lang/Object;T14:Ljava/lang/Object;T15:Ljava/lang/Object;T16:Ljava/lang/Object;T17:Ljava/lang/Object;T18:Ljava/lang/Object;T19:Ljava/lang/Object;>(Lscala/Function19<TT1;TT2;TT3;TT4;TT5;TT6;TT7;TT8;TT9;TT10;TT11;TT12;TT13;TT14;TT15;TT16;TT17;TT18;TT19;Lorg/sireum/contract$Contract$SubProof;>;)Lorg/sireum/contract$Contract$Let;
  #424 = Utf8               (Lorg/sireum/contract;Lscala/Function19;)Lorg/sireum/contract$Contract$Let;
  #425 = NameAndType        #315:#424     // Let$:(Lorg/sireum/contract;Lscala/Function19;)Lorg/sireum/contract$Contract$Let;
  #426 = InterfaceMethodref #8.#425       // org/sireum/contract.Let$:(Lorg/sireum/contract;Lscala/Function19;)Lorg/sireum/contract$Contract$Let;
  #427 = Utf8               Lscala/Function19;
  #428 = Utf8               (Lscala/Function20;)Lorg/sireum/contract$Contract$Let;
  #429 = Utf8               <T1:Ljava/lang/Object;T2:Ljava/lang/Object;T3:Ljava/lang/Object;T4:Ljava/lang/Object;T5:Ljava/lang/Object;T6:Ljava/lang/Object;T7:Ljava/lang/Object;T8:Ljava/lang/Object;T9:Ljava/lang/Object;T10:Ljava/lang/Object;T11:Ljava/lang/Object;T12:Ljava/lang/Object;T13:Ljava/lang/Object;T14:Ljava/lang/Object;T15:Ljava/lang/Object;T16:Ljava/lang/Object;T17:Ljava/lang/Object;T18:Ljava/lang/Object;T19:Ljava/lang/Object;T20:Ljava/lang/Object;>(Lscala/Function20<TT1;TT2;TT3;TT4;TT5;TT6;TT7;TT8;TT9;TT10;TT11;TT12;TT13;TT14;TT15;TT16;TT17;TT18;TT19;TT20;Lorg/sireum/contract$Contract$SubProof;>;)Lorg/sireum/contract$Contract$Let;
  #430 = Utf8               (Lorg/sireum/contract;Lscala/Function20;)Lorg/sireum/contract$Contract$Let;
  #431 = NameAndType        #315:#430     // Let$:(Lorg/sireum/contract;Lscala/Function20;)Lorg/sireum/contract$Contract$Let;
  #432 = InterfaceMethodref #8.#431       // org/sireum/contract.Let$:(Lorg/sireum/contract;Lscala/Function20;)Lorg/sireum/contract$Contract$Let;
  #433 = Utf8               Lscala/Function20;
  #434 = Utf8               (Lscala/Function21;)Lorg/sireum/contract$Contract$Let;
  #435 = Utf8               <T1:Ljava/lang/Object;T2:Ljava/lang/Object;T3:Ljava/lang/Object;T4:Ljava/lang/Object;T5:Ljava/lang/Object;T6:Ljava/lang/Object;T7:Ljava/lang/Object;T8:Ljava/lang/Object;T9:Ljava/lang/Object;T10:Ljava/lang/Object;T11:Ljava/lang/Object;T12:Ljava/lang/Object;T13:Ljava/lang/Object;T14:Ljava/lang/Object;T15:Ljava/lang/Object;T16:Ljava/lang/Object;T17:Ljava/lang/Object;T18:Ljava/lang/Object;T19:Ljava/lang/Object;T20:Ljava/lang/Object;T21:Ljava/lang/Object;>(Lscala/Function21<TT1;TT2;TT3;TT4;TT5;TT6;TT7;TT8;TT9;TT10;TT11;TT12;TT13;TT14;TT15;TT16;TT17;TT18;TT19;TT20;TT21;Lorg/sireum/contract$Contract$SubProof;>;)Lorg/sireum/contract$Contract$Let;
  #436 = Utf8               (Lorg/sireum/contract;Lscala/Function21;)Lorg/sireum/contract$Contract$Let;
  #437 = NameAndType        #315:#436     // Let$:(Lorg/sireum/contract;Lscala/Function21;)Lorg/sireum/contract$Contract$Let;
  #438 = InterfaceMethodref #8.#437       // org/sireum/contract.Let$:(Lorg/sireum/contract;Lscala/Function21;)Lorg/sireum/contract$Contract$Let;
  #439 = Utf8               Lscala/Function21;
  #440 = Utf8               (Lscala/Function22;)Lorg/sireum/contract$Contract$Let;
  #441 = Utf8               <T1:Ljava/lang/Object;T2:Ljava/lang/Object;T3:Ljava/lang/Object;T4:Ljava/lang/Object;T5:Ljava/lang/Object;T6:Ljava/lang/Object;T7:Ljava/lang/Object;T8:Ljava/lang/Object;T9:Ljava/lang/Object;T10:Ljava/lang/Object;T11:Ljava/lang/Object;T12:Ljava/lang/Object;T13:Ljava/lang/Object;T14:Ljava/lang/Object;T15:Ljava/lang/Object;T16:Ljava/lang/Object;T17:Ljava/lang/Object;T18:Ljava/lang/Object;T19:Ljava/lang/Object;T20:Ljava/lang/Object;T21:Ljava/lang/Object;T22:Ljava/lang/Object;>(Lscala/Function22<TT1;TT2;TT3;TT4;TT5;TT6;TT7;TT8;TT9;TT10;TT11;TT12;TT13;TT14;TT15;TT16;TT17;TT18;TT19;TT20;TT21;TT22;Lorg/sireum/contract$Contract$SubProof;>;)Lorg/sireum/contract$Contract$Let;
  #442 = Utf8               (Lorg/sireum/contract;Lscala/Function22;)Lorg/sireum/contract$Contract$Let;
  #443 = NameAndType        #315:#442     // Let$:(Lorg/sireum/contract;Lscala/Function22;)Lorg/sireum/contract$Contract$Let;
  #444 = InterfaceMethodref #8.#443       // org/sireum/contract.Let$:(Lorg/sireum/contract;Lscala/Function22;)Lorg/sireum/contract$Contract$Let;
  #445 = Utf8               Lscala/Function22;
  #446 = Utf8               In
  #447 = Utf8               (Ljava/lang/Object;)Ljava/lang/Object;
  #448 = Utf8               <T:Ljava/lang/Object;>(TT;)TT;
  #449 = Utf8               v
  #450 = Utf8               In$
  #451 = Utf8               (Lorg/sireum/contract;Ljava/lang/Object;)Ljava/lang/Object;
  #452 = NameAndType        #450:#451     // In$:(Lorg/sireum/contract;Ljava/lang/Object;)Ljava/lang/Object;
  #453 = InterfaceMethodref #8.#452       // org/sireum/contract.In$:(Lorg/sireum/contract;Ljava/lang/Object;)Ljava/lang/Object;
  #454 = Utf8               Old
  #455 = Utf8               Old$
  #456 = NameAndType        #455:#451     // Old$:(Lorg/sireum/contract;Ljava/lang/Object;)Ljava/lang/Object;
  #457 = InterfaceMethodref #8.#456       // org/sireum/contract.Old$:(Lorg/sireum/contract;Ljava/lang/Object;)Ljava/lang/Object;
  #458 = Utf8               At
  #459 = Utf8               (Ljava/lang/String;Ljava/lang/Object;)Ljava/lang/Object;
  #460 = Utf8               <T:Ljava/lang/Object;>(Ljava/lang/String;TT;)TT;
  #461 = Utf8               label
  #462 = Utf8               At$
  #463 = Utf8               (Lorg/sireum/contract;Ljava/lang/String;Ljava/lang/Object;)Ljava/lang/Object;
  #464 = NameAndType        #462:#463     // At$:(Lorg/sireum/contract;Ljava/lang/String;Ljava/lang/Object;)Ljava/lang/Object;
  #465 = InterfaceMethodref #8.#464       // org/sireum/contract.At$:(Lorg/sireum/contract;Ljava/lang/String;Ljava/lang/Object;)Ljava/lang/Object;
  #466 = Utf8               (Lorg/sireum/Z;Ljava/lang/Object;)Ljava/lang/Object;
  #467 = Utf8               <T:Ljava/lang/Object;>(Lorg/sireum/Z;TT;)TT;
  #468 = Utf8               n
  #469 = Utf8               (Lorg/sireum/contract;Lorg/sireum/Z;Ljava/lang/Object;)Ljava/lang/Object;
  #470 = NameAndType        #462:#469     // At$:(Lorg/sireum/contract;Lorg/sireum/Z;Ljava/lang/Object;)Ljava/lang/Object;
  #471 = InterfaceMethodref #8.#470       // org/sireum/contract.At$:(Lorg/sireum/contract;Lorg/sireum/Z;Ljava/lang/Object;)Ljava/lang/Object;
  #472 = Utf8               Res
  #473 = Utf8               ()Ljava/lang/Object;
  #474 = Utf8               <T:Ljava/lang/Object;>()TT;
  #475 = Utf8               Res$
  #476 = Utf8               (Lorg/sireum/contract;)Ljava/lang/Object;
  #477 = NameAndType        #475:#476     // Res$:(Lorg/sireum/contract;)Ljava/lang/Object;
  #478 = InterfaceMethodref #8.#477       // org/sireum/contract.Res$:(Lorg/sireum/contract;)Ljava/lang/Object;
  #479 = Utf8               Idx
  #480 = Utf8               (Ljava/lang/Object;)Lorg/sireum/ZLike;
  #481 = Utf8               <T::Lorg/sireum/ZLike<TT;>;>(Ljava/lang/Object;)TT;
  #482 = Utf8               Idx$
  #483 = Utf8               (Lorg/sireum/contract;Ljava/lang/Object;)Lorg/sireum/ZLike;
  #484 = NameAndType        #482:#483     // Idx$:(Lorg/sireum/contract;Ljava/lang/Object;)Lorg/sireum/ZLike;
  #485 = InterfaceMethodref #8.#484       // org/sireum/contract.Idx$:(Lorg/sireum/contract;Ljava/lang/Object;)Lorg/sireum/ZLike;
  #486 = Utf8               $bar$minus
  #487 = Utf8               (Z)Lorg/sireum/contract$Contract$Sequent;
  #488 = Utf8               conclusion
  #489 = Utf8               $bar$minus$
  #490 = Utf8               (Lorg/sireum/contract;Z)Lorg/sireum/contract$Contract$Sequent;
  #491 = NameAndType        #489:#490     // $bar$minus$:(Lorg/sireum/contract;Z)Lorg/sireum/contract$Contract$Sequent;
  #492 = InterfaceMethodref #8.#491       // org/sireum/contract.$bar$minus$:(Lorg/sireum/contract;Z)Lorg/sireum/contract$Contract$Sequent;
  #493 = Utf8               $u22A2
  #494 = Utf8               $u22A2$
  #495 = NameAndType        #494:#490     // $u22A2$:(Lorg/sireum/contract;Z)Lorg/sireum/contract$Contract$Sequent;
  #496 = InterfaceMethodref #8.#495       // org/sireum/contract.$u22A2$:(Lorg/sireum/contract;Z)Lorg/sireum/contract$Contract$Sequent;
  #497 = Utf8               $toStepBuilder
  #498 = Utf8               (I)Lorg/sireum/contract$Contract$StepBuilder;
  #499 = Utf8               stepNo
  #500 = Utf8               $toStepBuilder$
  #501 = Utf8               (Lorg/sireum/contract;I)Lorg/sireum/contract$Contract$StepBuilder;
  #502 = NameAndType        #500:#501     // $toStepBuilder$:(Lorg/sireum/contract;I)Lorg/sireum/contract$Contract$StepBuilder;
  #503 = InterfaceMethodref #8.#502       // org/sireum/contract.$toStepBuilder$:(Lorg/sireum/contract;I)Lorg/sireum/contract$Contract$StepBuilder;
  #504 = Utf8               (Lorg/sireum/Z;)Lorg/sireum/contract$Contract$StepBuilder;
  #505 = Utf8               (Lorg/sireum/contract;Lorg/sireum/Z;)Lorg/sireum/contract$Contract$StepBuilder;
  #506 = NameAndType        #500:#505     // $toStepBuilder$:(Lorg/sireum/contract;Lorg/sireum/Z;)Lorg/sireum/contract$Contract$StepBuilder;
  #507 = InterfaceMethodref #8.#506       // org/sireum/contract.$toStepBuilder$:(Lorg/sireum/contract;Lorg/sireum/Z;)Lorg/sireum/contract$Contract$StepBuilder;
  #508 = Utf8               $toJustification
  #509 = Utf8               (Ljava/lang/String;)Lorg/sireum/contract$Contract$Justification;
  #510 = Utf8               $toJustification$
  #511 = Utf8               (Lorg/sireum/contract;Ljava/lang/String;)Lorg/sireum/contract$Contract$Justification;
  #512 = NameAndType        #510:#511     // $toJustification$:(Lorg/sireum/contract;Ljava/lang/String;)Lorg/sireum/contract$Contract$Justification;
  #513 = InterfaceMethodref #8.#512       // org/sireum/contract.$toJustification$:(Lorg/sireum/contract;Ljava/lang/String;)Lorg/sireum/contract$Contract$Justification;
  #514 = Utf8               $toB
  #515 = Utf8               (Lorg/sireum/contract$Contract$StateCont;)Z
  #516 = Utf8               state
  #517 = Utf8               $toB$
  #518 = Utf8               (Lorg/sireum/contract;Lorg/sireum/contract$Contract$StateCont;)Z
  #519 = NameAndType        #517:#518     // $toB$:(Lorg/sireum/contract;Lorg/sireum/contract$Contract$StateCont;)Z
  #520 = InterfaceMethodref #8.#519       // org/sireum/contract.$toB$:(Lorg/sireum/contract;Lorg/sireum/contract$Contract$StateCont;)Z
  #521 = Utf8               Lorg/sireum/contract$Contract$StateCont;
  #522 = Utf8               $toSequent
  #523 = Utf8               (Z)Lorg/sireum/contract$Contract$SequentBuilder;
  #524 = Utf8               bs
  #525 = Utf8               $toSequent$
  #526 = Utf8               (Lorg/sireum/contract;Z)Lorg/sireum/contract$Contract$SequentBuilder;
  #527 = NameAndType        #525:#526     // $toSequent$:(Lorg/sireum/contract;Z)Lorg/sireum/contract$Contract$SequentBuilder;
  #528 = InterfaceMethodref #8.#527       // org/sireum/contract.$toSequent$:(Lorg/sireum/contract;Z)Lorg/sireum/contract$Contract$SequentBuilder;
  #529 = Utf8               (Lscala/Tuple2;)Lorg/sireum/contract$Contract$SequentBuilder;
  #530 = Utf8               (Lscala/Tuple2<Lorg/sireum/B;Lorg/sireum/B;>;)Lorg/sireum/contract$Contract$SequentBuilder;
  #531 = Utf8               (Lorg/sireum/contract;Lscala/Tuple2;)Lorg/sireum/contract$Contract$SequentBuilder;
  #532 = NameAndType        #525:#531     // $toSequent$:(Lorg/sireum/contract;Lscala/Tuple2;)Lorg/sireum/contract$Contract$SequentBuilder;
  #533 = InterfaceMethodref #8.#532       // org/sireum/contract.$toSequent$:(Lorg/sireum/contract;Lscala/Tuple2;)Lorg/sireum/contract$Contract$SequentBuilder;
  #534 = Utf8               Lscala/Tuple2;
  #535 = Utf8               (Lscala/Tuple3;)Lorg/sireum/contract$Contract$SequentBuilder;
  #536 = Utf8               (Lscala/Tuple3<Lorg/sireum/B;Lorg/sireum/B;Lorg/sireum/B;>;)Lorg/sireum/contract$Contract$SequentBuilder;
  #537 = Utf8               (Lorg/sireum/contract;Lscala/Tuple3;)Lorg/sireum/contract$Contract$SequentBuilder;
  #538 = NameAndType        #525:#537     // $toSequent$:(Lorg/sireum/contract;Lscala/Tuple3;)Lorg/sireum/contract$Contract$SequentBuilder;
  #539 = InterfaceMethodref #8.#538       // org/sireum/contract.$toSequent$:(Lorg/sireum/contract;Lscala/Tuple3;)Lorg/sireum/contract$Contract$SequentBuilder;
  #540 = Utf8               Lscala/Tuple3;
  #541 = Utf8               (Lscala/Tuple4;)Lorg/sireum/contract$Contract$SequentBuilder;
  #542 = Utf8               (Lscala/Tuple4<Lorg/sireum/B;Lorg/sireum/B;Lorg/sireum/B;Lorg/sireum/B;>;)Lorg/sireum/contract$Contract$SequentBuilder;
  #543 = Utf8               (Lorg/sireum/contract;Lscala/Tuple4;)Lorg/sireum/contract$Contract$SequentBuilder;
  #544 = NameAndType        #525:#543     // $toSequent$:(Lorg/sireum/contract;Lscala/Tuple4;)Lorg/sireum/contract$Contract$SequentBuilder;
  #545 = InterfaceMethodref #8.#544       // org/sireum/contract.$toSequent$:(Lorg/sireum/contract;Lscala/Tuple4;)Lorg/sireum/contract$Contract$SequentBuilder;
  #546 = Utf8               Lscala/Tuple4;
  #547 = Utf8               (Lscala/Tuple5;)Lorg/sireum/contract$Contract$SequentBuilder;
  #548 = Utf8               (Lscala/Tuple5<Lorg/sireum/B;Lorg/sireum/B;Lorg/sireum/B;Lorg/sireum/B;Lorg/sireum/B;>;)Lorg/sireum/contract$Contract$SequentBuilder;
  #549 = Utf8               (Lorg/sireum/contract;Lscala/Tuple5;)Lorg/sireum/contract$Contract$SequentBuilder;
  #550 = NameAndType        #525:#549     // $toSequent$:(Lorg/sireum/contract;Lscala/Tuple5;)Lorg/sireum/contract$Contract$SequentBuilder;
  #551 = InterfaceMethodref #8.#550       // org/sireum/contract.$toSequent$:(Lorg/sireum/contract;Lscala/Tuple5;)Lorg/sireum/contract$Contract$SequentBuilder;
  #552 = Utf8               Lscala/Tuple5;
  #553 = Utf8               (Lscala/Tuple6;)Lorg/sireum/contract$Contract$SequentBuilder;
  #554 = Utf8               (Lscala/Tuple6<Lorg/sireum/B;Lorg/sireum/B;Lorg/sireum/B;Lorg/sireum/B;Lorg/sireum/B;Lorg/sireum/B;>;)Lorg/sireum/contract$Contract$SequentBuilder;
  #555 = Utf8               (Lorg/sireum/contract;Lscala/Tuple6;)Lorg/sireum/contract$Contract$SequentBuilder;
  #556 = NameAndType        #525:#555     // $toSequent$:(Lorg/sireum/contract;Lscala/Tuple6;)Lorg/sireum/contract$Contract$SequentBuilder;
  #557 = InterfaceMethodref #8.#556       // org/sireum/contract.$toSequent$:(Lorg/sireum/contract;Lscala/Tuple6;)Lorg/sireum/contract$Contract$SequentBuilder;
  #558 = Utf8               Lscala/Tuple6;
  #559 = Utf8               (Lscala/Tuple7;)Lorg/sireum/contract$Contract$SequentBuilder;
  #560 = Utf8               (Lscala/Tuple7<Lorg/sireum/B;Lorg/sireum/B;Lorg/sireum/B;Lorg/sireum/B;Lorg/sireum/B;Lorg/sireum/B;Lorg/sireum/B;>;)Lorg/sireum/contract$Contract$SequentBuilder;
  #561 = Utf8               (Lorg/sireum/contract;Lscala/Tuple7;)Lorg/sireum/contract$Contract$SequentBuilder;
  #562 = NameAndType        #525:#561     // $toSequent$:(Lorg/sireum/contract;Lscala/Tuple7;)Lorg/sireum/contract$Contract$SequentBuilder;
  #563 = InterfaceMethodref #8.#562       // org/sireum/contract.$toSequent$:(Lorg/sireum/contract;Lscala/Tuple7;)Lorg/sireum/contract$Contract$SequentBuilder;
  #564 = Utf8               Lscala/Tuple7;
  #565 = Utf8               (Lscala/Tuple8;)Lorg/sireum/contract$Contract$SequentBuilder;
  #566 = Utf8               (Lscala/Tuple8<Lorg/sireum/B;Lorg/sireum/B;Lorg/sireum/B;Lorg/sireum/B;Lorg/sireum/B;Lorg/sireum/B;Lorg/sireum/B;Lorg/sireum/B;>;)Lorg/sireum/contract$Contract$SequentBuilder;
  #567 = Utf8               (Lorg/sireum/contract;Lscala/Tuple8;)Lorg/sireum/contract$Contract$SequentBuilder;
  #568 = NameAndType        #525:#567     // $toSequent$:(Lorg/sireum/contract;Lscala/Tuple8;)Lorg/sireum/contract$Contract$SequentBuilder;
  #569 = InterfaceMethodref #8.#568       // org/sireum/contract.$toSequent$:(Lorg/sireum/contract;Lscala/Tuple8;)Lorg/sireum/contract$Contract$SequentBuilder;
  #570 = Utf8               Lscala/Tuple8;
  #571 = Utf8               (Lscala/Tuple9;)Lorg/sireum/contract$Contract$SequentBuilder;
  #572 = Utf8               (Lscala/Tuple9<Lorg/sireum/B;Lorg/sireum/B;Lorg/sireum/B;Lorg/sireum/B;Lorg/sireum/B;Lorg/sireum/B;Lorg/sireum/B;Lorg/sireum/B;Lorg/sireum/B;>;)Lorg/sireum/contract$Contract$SequentBuilder;
  #573 = Utf8               (Lorg/sireum/contract;Lscala/Tuple9;)Lorg/sireum/contract$Contract$SequentBuilder;
  #574 = NameAndType        #525:#573     // $toSequent$:(Lorg/sireum/contract;Lscala/Tuple9;)Lorg/sireum/contract$Contract$SequentBuilder;
  #575 = InterfaceMethodref #8.#574       // org/sireum/contract.$toSequent$:(Lorg/sireum/contract;Lscala/Tuple9;)Lorg/sireum/contract$Contract$SequentBuilder;
  #576 = Utf8               Lscala/Tuple9;
  #577 = Utf8               (Lscala/Tuple10;)Lorg/sireum/contract$Contract$SequentBuilder;
  #578 = Utf8               (Lscala/Tuple10<Lorg/sireum/B;Lorg/sireum/B;Lorg/sireum/B;Lorg/sireum/B;Lorg/sireum/B;Lorg/sireum/B;Lorg/sireum/B;Lorg/sireum/B;Lorg/sireum/B;Lorg/sireum/B;>;)Lorg/sireum/contract$Contract$SequentBuilder;
  #579 = Utf8               (Lorg/sireum/contract;Lscala/Tuple10;)Lorg/sireum/contract$Contract$SequentBuilder;
  #580 = NameAndType        #525:#579     // $toSequent$:(Lorg/sireum/contract;Lscala/Tuple10;)Lorg/sireum/contract$Contract$SequentBuilder;
  #581 = InterfaceMethodref #8.#580       // org/sireum/contract.$toSequent$:(Lorg/sireum/contract;Lscala/Tuple10;)Lorg/sireum/contract$Contract$SequentBuilder;
  #582 = Utf8               Lscala/Tuple10;
  #583 = Utf8               (Lscala/Tuple11;)Lorg/sireum/contract$Contract$SequentBuilder;
  #584 = Utf8               (Lscala/Tuple11<Lorg/sireum/B;Lorg/sireum/B;Lorg/sireum/B;Lorg/sireum/B;Lorg/sireum/B;Lorg/sireum/B;Lorg/sireum/B;Lorg/sireum/B;Lorg/sireum/B;Lorg/sireum/B;Lorg/sireum/B;>;)Lorg/sireum/contract$Contract$SequentBuilder;
  #585 = Utf8               (Lorg/sireum/contract;Lscala/Tuple11;)Lorg/sireum/contract$Contract$SequentBuilder;
  #586 = NameAndType        #525:#585     // $toSequent$:(Lorg/sireum/contract;Lscala/Tuple11;)Lorg/sireum/contract$Contract$SequentBuilder;
  #587 = InterfaceMethodref #8.#586       // org/sireum/contract.$toSequent$:(Lorg/sireum/contract;Lscala/Tuple11;)Lorg/sireum/contract$Contract$SequentBuilder;
  #588 = Utf8               Lscala/Tuple11;
  #589 = Utf8               (Lscala/Tuple12;)Lorg/sireum/contract$Contract$SequentBuilder;
  #590 = Utf8               (Lscala/Tuple12<Lorg/sireum/B;Lorg/sireum/B;Lorg/sireum/B;Lorg/sireum/B;Lorg/sireum/B;Lorg/sireum/B;Lorg/sireum/B;Lorg/sireum/B;Lorg/sireum/B;Lorg/sireum/B;Lorg/sireum/B;Lorg/sireum/B;>;)Lorg/sireum/contract$Contract$SequentBuilder;
  #591 = Utf8               (Lorg/sireum/contract;Lscala/Tuple12;)Lorg/sireum/contract$Contract$SequentBuilder;
  #592 = NameAndType        #525:#591     // $toSequent$:(Lorg/sireum/contract;Lscala/Tuple12;)Lorg/sireum/contract$Contract$SequentBuilder;
  #593 = InterfaceMethodref #8.#592       // org/sireum/contract.$toSequent$:(Lorg/sireum/contract;Lscala/Tuple12;)Lorg/sireum/contract$Contract$SequentBuilder;
  #594 = Utf8               Lscala/Tuple12;
  #595 = Utf8               (Lscala/Tuple13;)Lorg/sireum/contract$Contract$SequentBuilder;
  #596 = Utf8               (Lscala/Tuple13<Lorg/sireum/B;Lorg/sireum/B;Lorg/sireum/B;Lorg/sireum/B;Lorg/sireum/B;Lorg/sireum/B;Lorg/sireum/B;Lorg/sireum/B;Lorg/sireum/B;Lorg/sireum/B;Lorg/sireum/B;Lorg/sireum/B;Lorg/sireum/B;>;)Lorg/sireum/contract$Contract$SequentBuilder;
  #597 = Utf8               (Lorg/sireum/contract;Lscala/Tuple13;)Lorg/sireum/contract$Contract$SequentBuilder;
  #598 = NameAndType        #525:#597     // $toSequent$:(Lorg/sireum/contract;Lscala/Tuple13;)Lorg/sireum/contract$Contract$SequentBuilder;
  #599 = InterfaceMethodref #8.#598       // org/sireum/contract.$toSequent$:(Lorg/sireum/contract;Lscala/Tuple13;)Lorg/sireum/contract$Contract$SequentBuilder;
  #600 = Utf8               Lscala/Tuple13;
  #601 = Utf8               (Lscala/Tuple14;)Lorg/sireum/contract$Contract$SequentBuilder;
  #602 = Utf8               (Lscala/Tuple14<Lorg/sireum/B;Lorg/sireum/B;Lorg/sireum/B;Lorg/sireum/B;Lorg/sireum/B;Lorg/sireum/B;Lorg/sireum/B;Lorg/sireum/B;Lorg/sireum/B;Lorg/sireum/B;Lorg/sireum/B;Lorg/sireum/B;Lorg/sireum/B;Lorg/sireum/B;>;)Lorg/sireum/contract$Contract$SequentBuilder;
  #603 = Utf8               (Lorg/sireum/contract;Lscala/Tuple14;)Lorg/sireum/contract$Contract$SequentBuilder;
  #604 = NameAndType        #525:#603     // $toSequent$:(Lorg/sireum/contract;Lscala/Tuple14;)Lorg/sireum/contract$Contract$SequentBuilder;
  #605 = InterfaceMethodref #8.#604       // org/sireum/contract.$toSequent$:(Lorg/sireum/contract;Lscala/Tuple14;)Lorg/sireum/contract$Contract$SequentBuilder;
  #606 = Utf8               Lscala/Tuple14;
  #607 = Utf8               (Lscala/Tuple15;)Lorg/sireum/contract$Contract$SequentBuilder;
  #608 = Utf8               (Lscala/Tuple15<Lorg/sireum/B;Lorg/sireum/B;Lorg/sireum/B;Lorg/sireum/B;Lorg/sireum/B;Lorg/sireum/B;Lorg/sireum/B;Lorg/sireum/B;Lorg/sireum/B;Lorg/sireum/B;Lorg/sireum/B;Lorg/sireum/B;Lorg/sireum/B;Lorg/sireum/B;Lorg/sireum/B;>;)Lorg/sireum/contract$Contract$SequentBuilder;
  #609 = Utf8               (Lorg/sireum/contract;Lscala/Tuple15;)Lorg/sireum/contract$Contract$SequentBuilder;
  #610 = NameAndType        #525:#609     // $toSequent$:(Lorg/sireum/contract;Lscala/Tuple15;)Lorg/sireum/contract$Contract$SequentBuilder;
  #611 = InterfaceMethodref #8.#610       // org/sireum/contract.$toSequent$:(Lorg/sireum/contract;Lscala/Tuple15;)Lorg/sireum/contract$Contract$SequentBuilder;
  #612 = Utf8               Lscala/Tuple15;
  #613 = Utf8               (Lscala/Tuple16;)Lorg/sireum/contract$Contract$SequentBuilder;
  #614 = Utf8               (Lscala/Tuple16<Lorg/sireum/B;Lorg/sireum/B;Lorg/sireum/B;Lorg/sireum/B;Lorg/sireum/B;Lorg/sireum/B;Lorg/sireum/B;Lorg/sireum/B;Lorg/sireum/B;Lorg/sireum/B;Lorg/sireum/B;Lorg/sireum/B;Lorg/sireum/B;Lorg/sireum/B;Lorg/sireum/B;Lorg/sireum/B;>;)Lorg/sireum/contract$Contract$SequentBuilder;
  #615 = Utf8               (Lorg/sireum/contract;Lscala/Tuple16;)Lorg/sireum/contract$Contract$SequentBuilder;
  #616 = NameAndType        #525:#615     // $toSequent$:(Lorg/sireum/contract;Lscala/Tuple16;)Lorg/sireum/contract$Contract$SequentBuilder;
  #617 = InterfaceMethodref #8.#616       // org/sireum/contract.$toSequent$:(Lorg/sireum/contract;Lscala/Tuple16;)Lorg/sireum/contract$Contract$SequentBuilder;
  #618 = Utf8               Lscala/Tuple16;
  #619 = Utf8               (Lscala/Tuple17;)Lorg/sireum/contract$Contract$SequentBuilder;
  #620 = Utf8               (Lscala/Tuple17<Lorg/sireum/B;Lorg/sireum/B;Lorg/sireum/B;Lorg/sireum/B;Lorg/sireum/B;Lorg/sireum/B;Lorg/sireum/B;Lorg/sireum/B;Lorg/sireum/B;Lorg/sireum/B;Lorg/sireum/B;Lorg/sireum/B;Lorg/sireum/B;Lorg/sireum/B;Lorg/sireum/B;Lorg/sireum/B;Lorg/sireum/B;>;)Lorg/sireum/contract$Contract$SequentBuilder;
  #621 = Utf8               (Lorg/sireum/contract;Lscala/Tuple17;)Lorg/sireum/contract$Contract$SequentBuilder;
  #622 = NameAndType        #525:#621     // $toSequent$:(Lorg/sireum/contract;Lscala/Tuple17;)Lorg/sireum/contract$Contract$SequentBuilder;
  #623 = InterfaceMethodref #8.#622       // org/sireum/contract.$toSequent$:(Lorg/sireum/contract;Lscala/Tuple17;)Lorg/sireum/contract$Contract$SequentBuilder;
  #624 = Utf8               Lscala/Tuple17;
  #625 = Utf8               (Lscala/Tuple18;)Lorg/sireum/contract$Contract$SequentBuilder;
  #626 = Utf8               (Lscala/Tuple18<Lorg/sireum/B;Lorg/sireum/B;Lorg/sireum/B;Lorg/sireum/B;Lorg/sireum/B;Lorg/sireum/B;Lorg/sireum/B;Lorg/sireum/B;Lorg/sireum/B;Lorg/sireum/B;Lorg/sireum/B;Lorg/sireum/B;Lorg/sireum/B;Lorg/sireum/B;Lorg/sireum/B;Lorg/sireum/B;Lorg/sireum/B;Lorg/sireum/B;>;)Lorg/sireum/contract$Contract$SequentBuilder;
  #627 = Utf8               (Lorg/sireum/contract;Lscala/Tuple18;)Lorg/sireum/contract$Contract$SequentBuilder;
  #628 = NameAndType        #525:#627     // $toSequent$:(Lorg/sireum/contract;Lscala/Tuple18;)Lorg/sireum/contract$Contract$SequentBuilder;
  #629 = InterfaceMethodref #8.#628       // org/sireum/contract.$toSequent$:(Lorg/sireum/contract;Lscala/Tuple18;)Lorg/sireum/contract$Contract$SequentBuilder;
  #630 = Utf8               Lscala/Tuple18;
  #631 = Utf8               (Lscala/Tuple19;)Lorg/sireum/contract$Contract$SequentBuilder;
  #632 = Utf8               (Lscala/Tuple19<Lorg/sireum/B;Lorg/sireum/B;Lorg/sireum/B;Lorg/sireum/B;Lorg/sireum/B;Lorg/sireum/B;Lorg/sireum/B;Lorg/sireum/B;Lorg/sireum/B;Lorg/sireum/B;Lorg/sireum/B;Lorg/sireum/B;Lorg/sireum/B;Lorg/sireum/B;Lorg/sireum/B;Lorg/sireum/B;Lorg/sireum/B;Lorg/sireum/B;Lorg/sireum/B;>;)Lorg/sireum/contract$Contract$SequentBuilder;
  #633 = Utf8               (Lorg/sireum/contract;Lscala/Tuple19;)Lorg/sireum/contract$Contract$SequentBuilder;
  #634 = NameAndType        #525:#633     // $toSequent$:(Lorg/sireum/contract;Lscala/Tuple19;)Lorg/sireum/contract$Contract$SequentBuilder;
  #635 = InterfaceMethodref #8.#634       // org/sireum/contract.$toSequent$:(Lorg/sireum/contract;Lscala/Tuple19;)Lorg/sireum/contract$Contract$SequentBuilder;
  #636 = Utf8               Lscala/Tuple19;
  #637 = Utf8               (Lscala/Tuple20;)Lorg/sireum/contract$Contract$SequentBuilder;
  #638 = Utf8               (Lscala/Tuple20<Lorg/sireum/B;Lorg/sireum/B;Lorg/sireum/B;Lorg/sireum/B;Lorg/sireum/B;Lorg/sireum/B;Lorg/sireum/B;Lorg/sireum/B;Lorg/sireum/B;Lorg/sireum/B;Lorg/sireum/B;Lorg/sireum/B;Lorg/sireum/B;Lorg/sireum/B;Lorg/sireum/B;Lorg/sireum/B;Lorg/sireum/B;Lorg/sireum/B;Lorg/sireum/B;Lorg/sireum/B;>;)Lorg/sireum/contract$Contract$SequentBuilder;
  #639 = Utf8               (Lorg/sireum/contract;Lscala/Tuple20;)Lorg/sireum/contract$Contract$SequentBuilder;
  #640 = NameAndType        #525:#639     // $toSequent$:(Lorg/sireum/contract;Lscala/Tuple20;)Lorg/sireum/contract$Contract$SequentBuilder;
  #641 = InterfaceMethodref #8.#640       // org/sireum/contract.$toSequent$:(Lorg/sireum/contract;Lscala/Tuple20;)Lorg/sireum/contract$Contract$SequentBuilder;
  #642 = Utf8               Lscala/Tuple20;
  #643 = Utf8               (Lscala/Tuple21;)Lorg/sireum/contract$Contract$SequentBuilder;
  #644 = Utf8               (Lscala/Tuple21<Lorg/sireum/B;Lorg/sireum/B;Lorg/sireum/B;Lorg/sireum/B;Lorg/sireum/B;Lorg/sireum/B;Lorg/sireum/B;Lorg/sireum/B;Lorg/sireum/B;Lorg/sireum/B;Lorg/sireum/B;Lorg/sireum/B;Lorg/sireum/B;Lorg/sireum/B;Lorg/sireum/B;Lorg/sireum/B;Lorg/sireum/B;Lorg/sireum/B;Lorg/sireum/B;Lorg/sireum/B;Lorg/sireum/B;>;)Lorg/sireum/contract$Contract$SequentBuilder;
  #645 = Utf8               (Lorg/sireum/contract;Lscala/Tuple21;)Lorg/sireum/contract$Contract$SequentBuilder;
  #646 = NameAndType        #525:#645     // $toSequent$:(Lorg/sireum/contract;Lscala/Tuple21;)Lorg/sireum/contract$Contract$SequentBuilder;
  #647 = InterfaceMethodref #8.#646       // org/sireum/contract.$toSequent$:(Lorg/sireum/contract;Lscala/Tuple21;)Lorg/sireum/contract$Contract$SequentBuilder;
  #648 = Utf8               Lscala/Tuple21;
  #649 = Utf8               (Lscala/Tuple22;)Lorg/sireum/contract$Contract$SequentBuilder;
  #650 = Utf8               (Lscala/Tuple22<Lorg/sireum/B;Lorg/sireum/B;Lorg/sireum/B;Lorg/sireum/B;Lorg/sireum/B;Lorg/sireum/B;Lorg/sireum/B;Lorg/sireum/B;Lorg/sireum/B;Lorg/sireum/B;Lorg/sireum/B;Lorg/sireum/B;Lorg/sireum/B;Lorg/sireum/B;Lorg/sireum/B;Lorg/sireum/B;Lorg/sireum/B;Lorg/sireum/B;Lorg/sireum/B;Lorg/sireum/B;Lorg/sireum/B;Lorg/sireum/B;>;)Lorg/sireum/contract$Contract$SequentBuilder;
  #651 = Utf8               (Lorg/sireum/contract;Lscala/Tuple22;)Lorg/sireum/contract$Contract$SequentBuilder;
  #652 = NameAndType        #525:#651     // $toSequent$:(Lorg/sireum/contract;Lscala/Tuple22;)Lorg/sireum/contract$Contract$SequentBuilder;
  #653 = InterfaceMethodref #8.#652       // org/sireum/contract.$toSequent$:(Lorg/sireum/contract;Lscala/Tuple22;)Lorg/sireum/contract$Contract$SequentBuilder;
  #654 = Utf8               Lscala/Tuple22;
  #655 = Utf8               randomInt
  #656 = Utf8               ()Lorg/sireum/Z;
  #657 = Utf8               randomInt$
  #658 = Utf8               (Lorg/sireum/$internal/PackageTrait;)Lorg/sireum/Z;
  #659 = NameAndType        #657:#658     // randomInt$:(Lorg/sireum/$internal/PackageTrait;)Lorg/sireum/Z;
  #660 = InterfaceMethodref #6.#659       // org/sireum/$internal/PackageTrait.randomInt$:(Lorg/sireum/$internal/PackageTrait;)Lorg/sireum/Z;
  #661 = Utf8               seqIndexValidSize
  #662 = Utf8               (Lorg/sireum/Z;)Z
  #663 = Utf8               <I:Ljava/lang/Object;>(Lorg/sireum/Z;)Z
  #664 = Utf8               size
  #665 = Utf8               seqIndexValidSize$
  #666 = Utf8               (Lorg/sireum/$internal/PackageTrait;Lorg/sireum/Z;)Z
  #667 = NameAndType        #665:#666     // seqIndexValidSize$:(Lorg/sireum/$internal/PackageTrait;Lorg/sireum/Z;)Z
  #668 = InterfaceMethodref #6.#667       // org/sireum/$internal/PackageTrait.seqIndexValidSize$:(Lorg/sireum/$internal/PackageTrait;Lorg/sireum/Z;)Z
  #669 = Utf8               promptInt
  #670 = Utf8               (Ljava/lang/String;)Lorg/sireum/Z;
  #671 = Utf8               msg
  #672 = Utf8               promptInt$
  #673 = Utf8               (Lorg/sireum/$internal/PackageTrait;Ljava/lang/String;)Lorg/sireum/Z;
  #674 = NameAndType        #672:#673     // promptInt$:(Lorg/sireum/$internal/PackageTrait;Ljava/lang/String;)Lorg/sireum/Z;
  #675 = InterfaceMethodref #6.#674       // org/sireum/$internal/PackageTrait.promptInt$:(Lorg/sireum/$internal/PackageTrait;Ljava/lang/String;)Lorg/sireum/Z;
  #676 = Utf8               readInt
  #677 = Utf8               readInt$
  #678 = NameAndType        #677:#658     // readInt$:(Lorg/sireum/$internal/PackageTrait;)Lorg/sireum/Z;
  #679 = InterfaceMethodref #6.#678       // org/sireum/$internal/PackageTrait.readInt$:(Lorg/sireum/$internal/PackageTrait;)Lorg/sireum/Z;
  #680 = Utf8               halt
  #681 = Utf8               (Ljava/lang/Object;)Lscala/runtime/Nothing$;
  #682 = Utf8               halt$
  #683 = Utf8               (Lorg/sireum/$internal/PackageTrait;Ljava/lang/Object;)Lscala/runtime/Nothing$;
  #684 = NameAndType        #682:#683     // halt$:(Lorg/sireum/$internal/PackageTrait;Ljava/lang/Object;)Lscala/runtime/Nothing$;
  #685 = InterfaceMethodref #6.#684       // org/sireum/$internal/PackageTrait.halt$:(Lorg/sireum/$internal/PackageTrait;Ljava/lang/Object;)Lscala/runtime/Nothing$;
  #686 = Utf8               cprintln
  #687 = Utf8               (ZLscala/collection/immutable/Seq;)V
  #688 = Utf8               (ZLscala/collection/immutable/Seq<Ljava/lang/Object;>;)V
  #689 = Utf8               isErr
  #690 = Utf8               as
  #691 = Utf8               cprintln$
  #692 = Utf8               (Lorg/sireum/$internal/PackageTrait;ZLscala/collection/immutable/Seq;)V
  #693 = NameAndType        #691:#692     // cprintln$:(Lorg/sireum/$internal/PackageTrait;ZLscala/collection/immutable/Seq;)V
  #694 = InterfaceMethodref #6.#693       // org/sireum/$internal/PackageTrait.cprintln$:(Lorg/sireum/$internal/PackageTrait;ZLscala/collection/immutable/Seq;)V
  #695 = Utf8               cprint
  #696 = Utf8               cprint$
  #697 = NameAndType        #696:#692     // cprint$:(Lorg/sireum/$internal/PackageTrait;ZLscala/collection/immutable/Seq;)V
  #698 = InterfaceMethodref #6.#697       // org/sireum/$internal/PackageTrait.cprint$:(Lorg/sireum/$internal/PackageTrait;ZLscala/collection/immutable/Seq;)V
  #699 = Utf8               println
  #700 = Utf8               (Lscala/collection/immutable/Seq;)V
  #701 = Utf8               (Lscala/collection/immutable/Seq<Ljava/lang/Object;>;)V
  #702 = Utf8               println$
  #703 = Utf8               (Lorg/sireum/$internal/PackageTrait;Lscala/collection/immutable/Seq;)V
  #704 = NameAndType        #702:#703     // println$:(Lorg/sireum/$internal/PackageTrait;Lscala/collection/immutable/Seq;)V
  #705 = InterfaceMethodref #6.#704       // org/sireum/$internal/PackageTrait.println$:(Lorg/sireum/$internal/PackageTrait;Lscala/collection/immutable/Seq;)V
  #706 = Utf8               print
  #707 = Utf8               print$
  #708 = NameAndType        #707:#703     // print$:(Lorg/sireum/$internal/PackageTrait;Lscala/collection/immutable/Seq;)V
  #709 = InterfaceMethodref #6.#708       // org/sireum/$internal/PackageTrait.print$:(Lorg/sireum/$internal/PackageTrait;Lscala/collection/immutable/Seq;)V
  #710 = Utf8               eprintln
  #711 = Utf8               eprintln$
  #712 = NameAndType        #711:#703     // eprintln$:(Lorg/sireum/$internal/PackageTrait;Lscala/collection/immutable/Seq;)V
  #713 = InterfaceMethodref #6.#712       // org/sireum/$internal/PackageTrait.eprintln$:(Lorg/sireum/$internal/PackageTrait;Lscala/collection/immutable/Seq;)V
  #714 = Utf8               eprint
  #715 = Utf8               eprint$
  #716 = NameAndType        #715:#703     // eprint$:(Lorg/sireum/$internal/PackageTrait;Lscala/collection/immutable/Seq;)V
  #717 = InterfaceMethodref #6.#716       // org/sireum/$internal/PackageTrait.eprint$:(Lorg/sireum/$internal/PackageTrait;Lscala/collection/immutable/Seq;)V
  #718 = Utf8               $2BigIntOpt
  #719 = Utf8               (I)Lscala/Option;
  #720 = Utf8               (I)Lscala/Option<Lscala/math/BigInt;>;
  #721 = Utf8               $2BigIntOpt$
  #722 = Utf8               (Lorg/sireum/$internal/PackageTrait;I)Lscala/Option;
  #723 = NameAndType        #721:#722     // $2BigIntOpt$:(Lorg/sireum/$internal/PackageTrait;I)Lscala/Option;
  #724 = InterfaceMethodref #6.#723       // org/sireum/$internal/PackageTrait.$2BigIntOpt$:(Lorg/sireum/$internal/PackageTrait;I)Lscala/Option;
  #725 = Utf8               (J)Lscala/Option;
  #726 = Utf8               (J)Lscala/Option<Lscala/math/BigInt;>;
  #727 = Utf8               (Lorg/sireum/$internal/PackageTrait;J)Lscala/Option;
  #728 = NameAndType        #721:#727     // $2BigIntOpt$:(Lorg/sireum/$internal/PackageTrait;J)Lscala/Option;
  #729 = InterfaceMethodref #6.#728       // org/sireum/$internal/PackageTrait.$2BigIntOpt$:(Lorg/sireum/$internal/PackageTrait;J)Lscala/Option;
  #730 = Utf8               J
  #731 = Utf8               (Lorg/sireum/Z;)Lscala/Option;
  #732 = Utf8               (Lorg/sireum/Z;)Lscala/Option<Lscala/math/BigInt;>;
  #733 = Utf8               (Lorg/sireum/$internal/PackageTrait;Lorg/sireum/Z;)Lscala/Option;
  #734 = NameAndType        #721:#733     // $2BigIntOpt$:(Lorg/sireum/$internal/PackageTrait;Lorg/sireum/Z;)Lscala/Option;
  #735 = InterfaceMethodref #6.#734       // org/sireum/$internal/PackageTrait.$2BigIntOpt$:(Lorg/sireum/$internal/PackageTrait;Lorg/sireum/Z;)Lscala/Option;
  #736 = Utf8               $2IS
  #737 = Utf8               (Lorg/sireum/ZRange;)Lorg/sireum/IS;
  #738 = Utf8               <I:Ljava/lang/Object;>(Lorg/sireum/ZRange<TI;>;)Lorg/sireum/IS<Lorg/sireum/Z;TI;>;
  #739 = Utf8               zr
  #740 = Utf8               $2IS$
  #741 = Utf8               (Lorg/sireum/$internal/PackageTrait;Lorg/sireum/ZRange;)Lorg/sireum/IS;
  #742 = NameAndType        #740:#741     // $2IS$:(Lorg/sireum/$internal/PackageTrait;Lorg/sireum/ZRange;)Lorg/sireum/IS;
  #743 = InterfaceMethodref #6.#742       // org/sireum/$internal/PackageTrait.$2IS$:(Lorg/sireum/$internal/PackageTrait;Lorg/sireum/ZRange;)Lorg/sireum/IS;
  #744 = Utf8               Lorg/sireum/ZRange;
  #745 = Utf8               Spec
  #746 = Utf8               ()Lorg/sireum/contract$Spec$;
  #747 = NameAndType        #110:#111     // Spec$module:Lorg/sireum/contract$Spec$;
  #748 = Fieldref           #2.#747       // org/sireum/package$.Spec$module:Lorg/sireum/contract$Spec$;
  #749 = Utf8               Spec$lzycompute$1
  #750 = NameAndType        #749:#135     // Spec$lzycompute$1:()V
  #751 = Methodref          #2.#750       // org/sireum/package$.Spec$lzycompute$1:()V
  #752 = Utf8               Contract
  #753 = Utf8               ()Lorg/sireum/contract$Contract$;
  #754 = NameAndType        #112:#113     // Contract$module:Lorg/sireum/contract$Contract$;
  #755 = Fieldref           #2.#754       // org/sireum/package$.Contract$module:Lorg/sireum/contract$Contract$;
  #756 = Utf8               Contract$lzycompute$1
  #757 = NameAndType        #756:#135     // Contract$lzycompute$1:()V
  #758 = Methodref          #2.#757       // org/sireum/package$.Contract$lzycompute$1:()V
  #759 = Utf8               All
  #760 = Utf8               ()Lorg/sireum/contract$All$;
  #761 = NameAndType        #114:#115     // All$module:Lorg/sireum/contract$All$;
  #762 = Fieldref           #2.#761       // org/sireum/package$.All$module:Lorg/sireum/contract$All$;
  #763 = Utf8               All$lzycompute$1
  #764 = NameAndType        #763:#135     // All$lzycompute$1:()V
  #765 = Methodref          #2.#764       // org/sireum/package$.All$lzycompute$1:()V
  #766 = Utf8               $u2200
  #767 = Utf8               ()Lorg/sireum/contract$$u2200$;
  #768 = NameAndType        #116:#117     // $u2200$module:Lorg/sireum/contract$$u2200$;
  #769 = Fieldref           #2.#768       // org/sireum/package$.$u2200$module:Lorg/sireum/contract$$u2200$;
  #770 = Utf8               $u2200$lzycompute$1
  #771 = NameAndType        #770:#135     // $u2200$lzycompute$1:()V
  #772 = Methodref          #2.#771       // org/sireum/package$.$u2200$lzycompute$1:()V
  #773 = Utf8               Exists
  #774 = Utf8               ()Lorg/sireum/contract$Exists$;
  #775 = NameAndType        #118:#119     // Exists$module:Lorg/sireum/contract$Exists$;
  #776 = Fieldref           #2.#775       // org/sireum/package$.Exists$module:Lorg/sireum/contract$Exists$;
  #777 = Utf8               Exists$lzycompute$1
  #778 = NameAndType        #777:#135     // Exists$lzycompute$1:()V
  #779 = Methodref          #2.#778       // org/sireum/package$.Exists$lzycompute$1:()V
  #780 = Utf8               $u2203
  #781 = Utf8               ()Lorg/sireum/contract$$u2203$;
  #782 = NameAndType        #120:#121     // $u2203$module:Lorg/sireum/contract$$u2203$;
  #783 = Fieldref           #2.#782       // org/sireum/package$.$u2203$module:Lorg/sireum/contract$$u2203$;
  #784 = Utf8               $u2203$lzycompute$1
  #785 = NameAndType        #784:#135     // $u2203$lzycompute$1:()V
  #786 = Methodref          #2.#785       // org/sireum/package$.$u2203$lzycompute$1:()V
  #787 = Utf8               ISZ
  #788 = Utf8               ()Lorg/sireum/$internal/PackageTrait$ISZ$;
  #789 = NameAndType        #122:#123     // ISZ$module:Lorg/sireum/$internal/PackageTrait$ISZ$;
  #790 = Fieldref           #2.#789       // org/sireum/package$.ISZ$module:Lorg/sireum/$internal/PackageTrait$ISZ$;
  #791 = Utf8               ISZ$lzycompute$1
  #792 = NameAndType        #791:#135     // ISZ$lzycompute$1:()V
  #793 = Methodref          #2.#792       // org/sireum/package$.ISZ$lzycompute$1:()V
  #794 = Utf8               MSZ
  #795 = Utf8               ()Lorg/sireum/$internal/PackageTrait$MSZ$;
  #796 = NameAndType        #124:#125     // MSZ$module:Lorg/sireum/$internal/PackageTrait$MSZ$;
  #797 = Fieldref           #2.#796       // org/sireum/package$.MSZ$module:Lorg/sireum/$internal/PackageTrait$MSZ$;
  #798 = Utf8               MSZ$lzycompute$1
  #799 = NameAndType        #798:#135     // MSZ$lzycompute$1:()V
  #800 = Methodref          #2.#799       // org/sireum/package$.MSZ$lzycompute$1:()V
  #801 = Utf8               ZS
  #802 = Utf8               ()Lorg/sireum/$internal/PackageTrait$ZS$;
  #803 = NameAndType        #126:#127     // ZS$module:Lorg/sireum/$internal/PackageTrait$ZS$;
  #804 = Fieldref           #2.#803       // org/sireum/package$.ZS$module:Lorg/sireum/$internal/PackageTrait$ZS$;
  #805 = Utf8               ZS$lzycompute$1
  #806 = NameAndType        #805:#135     // ZS$lzycompute$1:()V
  #807 = Methodref          #2.#806       // org/sireum/package$.ZS$lzycompute$1:()V
  #808 = Utf8               ()Z
  #809 = NameAndType        #128:#129     // T:Z
  #810 = Fieldref           #2.#809       // org/sireum/package$.T:Z
  #811 = NameAndType        #130:#129     // F:Z
  #812 = Fieldref           #2.#811       // org/sireum/package$.F:Z
  #813 = Utf8               ()Lorg/sireum/$ZCompanion;
  #814 = Utf8               ()Lorg/sireum/$ZCompanion<Lorg/sireum/Z;>;
  #815 = NameAndType        #131:#132     // $ZCompanion:Lorg/sireum/$ZCompanion;
  #816 = Fieldref           #2.#815       // org/sireum/package$.$ZCompanion:Lorg/sireum/$ZCompanion;
  #817 = Utf8               org$sireum$$internal$PackageTrait$_setter_$T_$eq
  #818 = Utf8               (Z)V
  #819 = Utf8               x$1
  #820 = Utf8               org$sireum$$internal$PackageTrait$_setter_$F_$eq
  #821 = Utf8               org$sireum$$internal$PackageTrait$_setter_$$ZCompanion_$eq
  #822 = Utf8               (Lorg/sireum/$ZCompanion;)V
  #823 = Utf8               (Lorg/sireum/$ZCompanion<Lorg/sireum/Z;>;)V
  #824 = Utf8               $Arrow
  #825 = Utf8               <T1:Ljava/lang/Object;>(TT1;)TT1;
  #826 = Utf8               _t1
  #827 = Utf8               (Lscala/StringContext;)Lorg/sireum/package$$Slang;
  #828 = Utf8               $sc
  #829 = Utf8               (Lscala/StringContext;)V
  #830 = NameAndType        #136:#829     // "<init>":(Lscala/StringContext;)V
  #831 = Methodref          #104.#830     // org/sireum/package$$Slang."<init>":(Lscala/StringContext;)V
  #832 = Utf8               Lscala/StringContext;
  #833 = Utf8               Any2HashString
  #834 = Utf8               _o
  #835 = Utf8               $Boolean2B
  #836 = Utf8               (Z)Z
  #837 = Utf8               _value
  #838 = Utf8               $Char2C
  #839 = Utf8               (C)C
  #840 = Utf8               C
  #841 = Utf8               $Int2Z
  #842 = Utf8               (I)I
  #843 = Utf8               $Long2Z
  #844 = Utf8               (J)J
  #845 = Utf8               $Float2F32
  #846 = Utf8               (F)F
  #847 = Utf8               $Double2F64
  #848 = Utf8               (D)D
  #849 = Utf8               D
  #850 = Utf8               $PredefString2String
  #851 = Utf8               (Ljava/lang/String;)Ljava/lang/String;
  #852 = NameAndType        #136:#145     // "<init>":(Lorg/sireum/contract;)V
  #853 = Methodref          #101.#852     // org/sireum/contract$Spec$."<init>":(Lorg/sireum/contract;)V
  #854 = Utf8               java/lang/Throwable
  #855 = Class              #854          // java/lang/Throwable
  #856 = Methodref          #29.#852      // org/sireum/contract$Contract$."<init>":(Lorg/sireum/contract;)V
  #857 = Methodref          #26.#852      // org/sireum/contract$All$."<init>":(Lorg/sireum/contract;)V
  #858 = Methodref          #20.#852      // org/sireum/contract$$u2200$."<init>":(Lorg/sireum/contract;)V
  #859 = Methodref          #98.#852      // org/sireum/contract$Exists$."<init>":(Lorg/sireum/contract;)V
  #860 = Methodref          #23.#852      // org/sireum/contract$$u2203$."<init>":(Lorg/sireum/contract;)V
  #861 = NameAndType        #136:#142     // "<init>":(Lorg/sireum/$internal/PackageTrait;)V
  #862 = Methodref          #11.#861      // org/sireum/$internal/PackageTrait$ISZ$."<init>":(Lorg/sireum/$internal/PackageTrait;)V
  #863 = Methodref          #14.#861      // org/sireum/$internal/PackageTrait$MSZ$."<init>":(Lorg/sireum/$internal/PackageTrait;)V
  #864 = Methodref          #17.#861      // org/sireum/$internal/PackageTrait$ZS$."<init>":(Lorg/sireum/$internal/PackageTrait;)V
  #865 = Methodref          #4.#137       // java/lang/Object."<init>":()V
  #866 = Utf8               Signature
  #867 = Utf8               Code
  #868 = Utf8               LineNumberTable
  #869 = Utf8               LocalVariableTable
  #870 = Utf8               MethodParameters
  #871 = Utf8               StackMapTable
  #872 = Utf8               InnerClasses
  #873 = Utf8               SourceFile
  #874 = Utf8               ScalaInlineInfo
  #875 = Utf8               $
  #876 = Utf8               Deduce
  #877 = Utf8               (Ljava/lang/String;Lorg/sireum/contract$Contract$Sequent;Lscala/collection/immutable/Seq;)V
  #878 = Utf8               (Lorg/sireum/contract$Contract$ProofStep;Lscala/collection/immutable/Seq;)V
  #879 = Utf8               (Lorg/sireum/contract$Contract$Sequent;Lscala/collection/immutable/Seq;)V
  #880 = Utf8               (Lorg/sireum/contract$Contract$MaxIt;Lorg/sireum/contract$Contract$Modifies;Lscala/collection/immutable/Seq;)V
  #881 = Utf8               (Lorg/sireum/contract$Contract$MaxIt;Lscala/collection/immutable/Seq;)V
  #882 = Utf8               (Lorg/sireum/contract$Contract$Modifies;Lscala/collection/immutable/Seq;)V
  #883 = Utf8               Scala
{
  public static final org.sireum.package$ MODULE$;
    descriptor: Lorg/sireum/package$;
    flags: (0x0019) ACC_PUBLIC, ACC_STATIC, ACC_FINAL

  private static volatile org.sireum.contract$Spec$ Spec$module;
    descriptor: Lorg/sireum/contract$Spec$;
    flags: (0x004a) ACC_PRIVATE, ACC_STATIC, ACC_VOLATILE

  private static volatile org.sireum.contract$Contract$ Contract$module;
    descriptor: Lorg/sireum/contract$Contract$;
    flags: (0x004a) ACC_PRIVATE, ACC_STATIC, ACC_VOLATILE

  private static volatile org.sireum.contract$All$ All$module;
    descriptor: Lorg/sireum/contract$All$;
    flags: (0x004a) ACC_PRIVATE, ACC_STATIC, ACC_VOLATILE

  private static volatile org.sireum.contract$$u2200$ $u2200$module;
    descriptor: Lorg/sireum/contract$$u2200$;
    flags: (0x004a) ACC_PRIVATE, ACC_STATIC, ACC_VOLATILE

  private static volatile org.sireum.contract$Exists$ Exists$module;
    descriptor: Lorg/sireum/contract$Exists$;
    flags: (0x004a) ACC_PRIVATE, ACC_STATIC, ACC_VOLATILE

  private static volatile org.sireum.contract$$u2203$ $u2203$module;
    descriptor: Lorg/sireum/contract$$u2203$;
    flags: (0x004a) ACC_PRIVATE, ACC_STATIC, ACC_VOLATILE

  private static volatile org.sireum.$internal.PackageTrait$ISZ$ ISZ$module;
    descriptor: Lorg/sireum/$internal/PackageTrait$ISZ$;
    flags: (0x004a) ACC_PRIVATE, ACC_STATIC, ACC_VOLATILE

  private static volatile org.sireum.$internal.PackageTrait$MSZ$ MSZ$module;
    descriptor: Lorg/sireum/$internal/PackageTrait$MSZ$;
    flags: (0x004a) ACC_PRIVATE, ACC_STATIC, ACC_VOLATILE

  private static volatile org.sireum.$internal.PackageTrait$ZS$ ZS$module;
    descriptor: Lorg/sireum/$internal/PackageTrait$ZS$;
    flags: (0x004a) ACC_PRIVATE, ACC_STATIC, ACC_VOLATILE

  private static boolean T;
    descriptor: Z
    flags: (0x000a) ACC_PRIVATE, ACC_STATIC

  private static boolean F;
    descriptor: Z
    flags: (0x000a) ACC_PRIVATE, ACC_STATIC

  private static org.sireum.$ZCompanion<org.sireum.Z> $ZCompanion;
    descriptor: Lorg/sireum/$ZCompanion;
    flags: (0x000a) ACC_PRIVATE, ACC_STATIC
    Signature: #133                         // Lorg/sireum/$ZCompanion<Lorg/sireum/Z;>;

  public static {};
    descriptor: ()V
    flags: (0x0009) ACC_PUBLIC, ACC_STATIC
    Code:
      stack=2, locals=0, args_size=0
         0: new           #2                  // class org/sireum/package$
         3: dup
         4: invokespecial #138                // Method "<init>":()V
         7: putstatic     #140                // Field MODULE$:Lorg/sireum/package$;
        10: getstatic     #140                // Field MODULE$:Lorg/sireum/package$;
        13: invokestatic  #144                // InterfaceMethod org/sireum/$internal/PackageTrait.$init$:(Lorg/sireum/$internal/PackageTrait;)V
        16: getstatic     #140                // Field MODULE$:Lorg/sireum/package$;
        19: invokestatic  #147                // InterfaceMethod org/sireum/contract.$init$:(Lorg/sireum/contract;)V
        22: return
      LineNumberTable:
        line 28: 0

  public org.sireum.contract$Contract$MaxIt MaxIt(org.sireum.Z);
    descriptor: (Lorg/sireum/Z;)Lorg/sireum/contract$Contract$MaxIt;
    flags: (0x0001) ACC_PUBLIC
    Code:
      stack=2, locals=2, args_size=2
         0: aload_0
         1: aload_1
         2: invokestatic  #153                // InterfaceMethod org/sireum/contract.MaxIt$:(Lorg/sireum/contract;Lorg/sireum/Z;)Lorg/sireum/contract$Contract$MaxIt;
         5: areturn
      LineNumberTable:
        line 28: 0
      LocalVariableTable:
        Start  Length  Slot  Name   Signature
            0       6     0  this   Lorg/sireum/package$;
            0       6     1   num   Lorg/sireum/Z;
    MethodParameters:
      Name                           Flags
      num                            final

  public org.sireum.contract$Contract$Reads Reads(scala.collection.immutable.Seq<java.lang.Object>);
    descriptor: (Lscala/collection/immutable/Seq;)Lorg/sireum/contract$Contract$Reads;
    flags: (0x0001) ACC_PUBLIC
    Code:
      stack=2, locals=2, args_size=2
         0: aload_0
         1: aload_1
         2: invokestatic  #162                // InterfaceMethod org/sireum/contract.Reads$:(Lorg/sireum/contract;Lscala/collection/immutable/Seq;)Lorg/sireum/contract$Contract$Reads;
         5: areturn
      LineNumberTable:
        line 28: 0
      LocalVariableTable:
        Start  Length  Slot  Name   Signature
            0       6     0  this   Lorg/sireum/package$;
            0       6     1 accesses   Lscala/collection/immutable/Seq;
    Signature: #157                         // (Lscala/collection/immutable/Seq<Ljava/lang/Object;>;)Lorg/sireum/contract$Contract$Reads;
    MethodParameters:
      Name                           Flags
      accesses                       final

  public org.sireum.contract$Contract$Requires Requires(scala.collection.immutable.Seq<org.sireum.B>);
    descriptor: (Lscala/collection/immutable/Seq;)Lorg/sireum/contract$Contract$Requires;
    flags: (0x0001) ACC_PUBLIC
    Code:
      stack=2, locals=2, args_size=2
         0: aload_0
         1: aload_1
         2: invokestatic  #170                // InterfaceMethod org/sireum/contract.Requires$:(Lorg/sireum/contract;Lscala/collection/immutable/Seq;)Lorg/sireum/contract$Contract$Requires;
         5: areturn
      LineNumberTable:
        line 28: 0
      LocalVariableTable:
        Start  Length  Slot  Name   Signature
            0       6     0  this   Lorg/sireum/package$;
            0       6     1 claims   Lscala/collection/immutable/Seq;
    Signature: #165                         // (Lscala/collection/immutable/Seq<Lorg/sireum/B;>;)Lorg/sireum/contract$Contract$Requires;
    MethodParameters:
      Name                           Flags
      claims                         final

  public org.sireum.contract$Contract$Modifies Modifies(scala.collection.immutable.Seq<java.lang.Object>);
    descriptor: (Lscala/collection/immutable/Seq;)Lorg/sireum/contract$Contract$Modifies;
    flags: (0x0001) ACC_PUBLIC
    Code:
      stack=2, locals=2, args_size=2
         0: aload_0
         1: aload_1
         2: invokestatic  #176                // InterfaceMethod org/sireum/contract.Modifies$:(Lorg/sireum/contract;Lscala/collection/immutable/Seq;)Lorg/sireum/contract$Contract$Modifies;
         5: areturn
      LineNumberTable:
        line 28: 0
      LocalVariableTable:
        Start  Length  Slot  Name   Signature
            0       6     0  this   Lorg/sireum/package$;
            0       6     1 accesses   Lscala/collection/immutable/Seq;
    Signature: #172                         // (Lscala/collection/immutable/Seq<Ljava/lang/Object;>;)Lorg/sireum/contract$Contract$Modifies;
    MethodParameters:
      Name                           Flags
      accesses                       final

  public org.sireum.contract$Contract$Ensures Ensures(scala.collection.immutable.Seq<org.sireum.B>);
    descriptor: (Lscala/collection/immutable/Seq;)Lorg/sireum/contract$Contract$Ensures;
    flags: (0x0001) ACC_PUBLIC
    Code:
      stack=2, locals=2, args_size=2
         0: aload_0
         1: aload_1
         2: invokestatic  #182                // InterfaceMethod org/sireum/contract.Ensures$:(Lorg/sireum/contract;Lscala/collection/immutable/Seq;)Lorg/sireum/contract$Contract$Ensures;
         5: areturn
      LineNumberTable:
        line 28: 0
      LocalVariableTable:
        Start  Length  Slot  Name   Signature
            0       6     0  this   Lorg/sireum/package$;
            0       6     1 claims   Lscala/collection/immutable/Seq;
    Signature: #178                         // (Lscala/collection/immutable/Seq<Lorg/sireum/B;>;)Lorg/sireum/contract$Contract$Ensures;
    MethodParameters:
      Name                           Flags
      claims                         final

  public org.sireum.contract$Contract$Invariant Invariant(scala.collection.immutable.Seq<org.sireum.B>);
    descriptor: (Lscala/collection/immutable/Seq;)Lorg/sireum/contract$Contract$Invariant;
    flags: (0x0001) ACC_PUBLIC
    Code:
      stack=2, locals=2, args_size=2
         0: aload_0
         1: aload_1
         2: invokestatic  #188                // InterfaceMethod org/sireum/contract.Invariant$:(Lorg/sireum/contract;Lscala/collection/immutable/Seq;)Lorg/sireum/contract$Contract$Invariant;
         5: areturn
      LineNumberTable:
        line 28: 0
      LocalVariableTable:
        Start  Length  Slot  Name   Signature
            0       6     0  this   Lorg/sireum/package$;
            0       6     1 claims   Lscala/collection/immutable/Seq;
    Signature: #184                         // (Lscala/collection/immutable/Seq<Lorg/sireum/B;>;)Lorg/sireum/contract$Contract$Invariant;
    MethodParameters:
      Name                           Flags
      claims                         final

  public org.sireum.contract$Contract$Invariant Invariant(java.lang.String, scala.collection.immutable.Seq<org.sireum.B>);
    descriptor: (Ljava/lang/String;Lscala/collection/immutable/Seq;)Lorg/sireum/contract$Contract$Invariant;
    flags: (0x0001) ACC_PUBLIC
    Code:
      stack=3, locals=3, args_size=3
         0: aload_0
         1: aload_1
         2: aload_2
         3: invokestatic  #194                // InterfaceMethod org/sireum/contract.Invariant$:(Lorg/sireum/contract;Ljava/lang/String;Lscala/collection/immutable/Seq;)Lorg/sireum/contract$Contract$Invariant;
         6: areturn
      LineNumberTable:
        line 28: 0
      LocalVariableTable:
        Start  Length  Slot  Name   Signature
            0       7     0  this   Lorg/sireum/package$;
            0       7     1  desc   Ljava/lang/String;
            0       7     2 claims   Lscala/collection/immutable/Seq;
    Signature: #190                         // (Ljava/lang/String;Lscala/collection/immutable/Seq<Lorg/sireum/B;>;)Lorg/sireum/contract$Contract$Invariant;
    MethodParameters:
      Name                           Flags
      desc                           final
      claims                         final

  public org.sireum.contract$Contract$DataRefinement DataRefinement(java.lang.Object, scala.collection.immutable.Seq<java.lang.Object>, scala.collection.immutable.Seq<org.sireum.B>);
    descriptor: (Ljava/lang/Object;Lscala/collection/immutable/Seq;Lscala/collection/immutable/Seq;)Lorg/sireum/contract$Contract$DataRefinement;
    flags: (0x0001) ACC_PUBLIC
    Code:
      stack=4, locals=4, args_size=4
         0: aload_0
         1: aload_1
         2: aload_2
         3: aload_3
         4: invokestatic  #203                // InterfaceMethod org/sireum/contract.DataRefinement$:(Lorg/sireum/contract;Ljava/lang/Object;Lscala/collection/immutable/Seq;Lscala/collection/immutable/Seq;)Lorg/sireum/contract$Contract$DataRefinement;
         7: areturn
      LineNumberTable:
        line 28: 0
      LocalVariableTable:
        Start  Length  Slot  Name   Signature
            0       8     0  this   Lorg/sireum/package$;
            0       8     1   rep   Ljava/lang/Object;
            0       8     2  refs   Lscala/collection/immutable/Seq;
            0       8     3 claims   Lscala/collection/immutable/Seq;
    Signature: #197                         // (Ljava/lang/Object;Lscala/collection/immutable/Seq<Ljava/lang/Object;>;Lscala/collection/immutable/Seq<Lorg/sireum/B;>;)Lorg/sireum/contract$Contract$DataRefinement;
    MethodParameters:
      Name                           Flags
      rep                            final
      refs                           final
      claims                         final

  public org.sireum.contract$Contract$Case Case(org.sireum.contract$Contract$Requires);
    descriptor: (Lorg/sireum/contract$Contract$Requires;)Lorg/sireum/contract$Contract$Case;
    flags: (0x0001) ACC_PUBLIC
    Code:
      stack=2, locals=2, args_size=2
         0: aload_0
         1: aload_1
         2: invokestatic  #210                // InterfaceMethod org/sireum/contract.Case$:(Lorg/sireum/contract;Lorg/sireum/contract$Contract$Requires;)Lorg/sireum/contract$Contract$Case;
         5: areturn
      LineNumberTable:
        line 28: 0
      LocalVariableTable:
        Start  Length  Slot  Name   Signature
            0       6     0  this   Lorg/sireum/package$;
            0       6     1 requires   Lorg/sireum/contract$Contract$Requires;
    MethodParameters:
      Name                           Flags
      requires                       final

  public org.sireum.contract$Contract$Case Case(org.sireum.contract$Contract$Ensures);
    descriptor: (Lorg/sireum/contract$Contract$Ensures;)Lorg/sireum/contract$Contract$Case;
    flags: (0x0001) ACC_PUBLIC
    Code:
      stack=2, locals=2, args_size=2
         0: aload_0
         1: aload_1
         2: invokestatic  #216                // InterfaceMethod org/sireum/contract.Case$:(Lorg/sireum/contract;Lorg/sireum/contract$Contract$Ensures;)Lorg/sireum/contract$Contract$Case;
         5: areturn
      LineNumberTable:
        line 28: 0
      LocalVariableTable:
        Start  Length  Slot  Name   Signature
            0       6     0  this   Lorg/sireum/package$;
            0       6     1 ensures   Lorg/sireum/contract$Contract$Ensures;
    MethodParameters:
      Name                           Flags
      ensures                        final

  public org.sireum.contract$Contract$Case Case(org.sireum.contract$Contract$Requires, org.sireum.contract$Contract$Ensures);
    descriptor: (Lorg/sireum/contract$Contract$Requires;Lorg/sireum/contract$Contract$Ensures;)Lorg/sireum/contract$Contract$Case;
    flags: (0x0001) ACC_PUBLIC
    Code:
      stack=3, locals=3, args_size=3
         0: aload_0
         1: aload_1
         2: aload_2
         3: invokestatic  #221                // InterfaceMethod org/sireum/contract.Case$:(Lorg/sireum/contract;Lorg/sireum/contract$Contract$Requires;Lorg/sireum/contract$Contract$Ensures;)Lorg/sireum/contract$Contract$Case;
         6: areturn
      LineNumberTable:
        line 28: 0
      LocalVariableTable:
        Start  Length  Slot  Name   Signature
            0       7     0  this   Lorg/sireum/package$;
            0       7     1 requires   Lorg/sireum/contract$Contract$Requires;
            0       7     2 ensures   Lorg/sireum/contract$Contract$Ensures;
    MethodParameters:
      Name                           Flags
      requires                       final
      ensures                        final

  public org.sireum.contract$Contract$Case Case(java.lang.String, org.sireum.contract$Contract$Requires);
    descriptor: (Ljava/lang/String;Lorg/sireum/contract$Contract$Requires;)Lorg/sireum/contract$Contract$Case;
    flags: (0x0001) ACC_PUBLIC
    Code:
      stack=3, locals=3, args_size=3
         0: aload_0
         1: aload_1
         2: aload_2
         3: invokestatic  #226                // InterfaceMethod org/sireum/contract.Case$:(Lorg/sireum/contract;Ljava/lang/String;Lorg/sireum/contract$Contract$Requires;)Lorg/sireum/contract$Contract$Case;
         6: areturn
      LineNumberTable:
        line 28: 0
      LocalVariableTable:
        Start  Length  Slot  Name   Signature
            0       7     0  this   Lorg/sireum/package$;
            0       7     1  name   Ljava/lang/String;
            0       7     2 requires   Lorg/sireum/contract$Contract$Requires;
    MethodParameters:
      Name                           Flags
      name                           final
      requires                       final

  public org.sireum.contract$Contract$Case Case(java.lang.String, org.sireum.contract$Contract$Ensures);
    descriptor: (Ljava/lang/String;Lorg/sireum/contract$Contract$Ensures;)Lorg/sireum/contract$Contract$Case;
    flags: (0x0001) ACC_PUBLIC
    Code:
      stack=3, locals=3, args_size=3
         0: aload_0
         1: aload_1
         2: aload_2
         3: invokestatic  #230                // InterfaceMethod org/sireum/contract.Case$:(Lorg/sireum/contract;Ljava/lang/String;Lorg/sireum/contract$Contract$Ensures;)Lorg/sireum/contract$Contract$Case;
         6: areturn
      LineNumberTable:
        line 28: 0
      LocalVariableTable:
        Start  Length  Slot  Name   Signature
            0       7     0  this   Lorg/sireum/package$;
            0       7     1  name   Ljava/lang/String;
            0       7     2 ensures   Lorg/sireum/contract$Contract$Ensures;
    MethodParameters:
      Name                           Flags
      name                           final
      ensures                        final

  public org.sireum.contract$Contract$Case Case(java.lang.String, org.sireum.contract$Contract$Requires, org.sireum.contract$Contract$Ensures);
    descriptor: (Ljava/lang/String;Lorg/sireum/contract$Contract$Requires;Lorg/sireum/contract$Contract$Ensures;)Lorg/sireum/contract$Contract$Case;
    flags: (0x0001) ACC_PUBLIC
    Code:
      stack=4, locals=4, args_size=4
         0: aload_0
         1: aload_1
         2: aload_2
         3: aload_3
         4: invokestatic  #234                // InterfaceMethod org/sireum/contract.Case$:(Lorg/sireum/contract;Ljava/lang/String;Lorg/sireum/contract$Contract$Requires;Lorg/sireum/contract$Contract$Ensures;)Lorg/sireum/contract$Contract$Case;
         7: areturn
      LineNumberTable:
        line 28: 0
      LocalVariableTable:
        Start  Length  Slot  Name   Signature
            0       8     0  this   Lorg/sireum/package$;
            0       8     1  name   Ljava/lang/String;
            0       8     2 requires   Lorg/sireum/contract$Contract$Requires;
            0       8     3 ensures   Lorg/sireum/contract$Contract$Ensures;
    MethodParameters:
      Name                           Flags
      name                           final
      requires                       final
      ensures                        final

  public org.sireum.contract$Contract$Fact Fact(scala.collection.immutable.Seq<org.sireum.B>);
    descriptor: (Lscala/collection/immutable/Seq;)Lorg/sireum/contract$Contract$Fact;
    flags: (0x0001) ACC_PUBLIC
    Code:
      stack=2, locals=2, args_size=2
         0: aload_0
         1: aload_1
         2: invokestatic  #240                // InterfaceMethod org/sireum/contract.Fact$:(Lorg/sireum/contract;Lscala/collection/immutable/Seq;)Lorg/sireum/contract$Contract$Fact;
         5: areturn
      LineNumberTable:
        line 28: 0
      LocalVariableTable:
        Start  Length  Slot  Name   Signature
            0       6     0  this   Lorg/sireum/package$;
            0       6     1 claims   Lscala/collection/immutable/Seq;
    Signature: #236                         // (Lscala/collection/immutable/Seq<Lorg/sireum/B;>;)Lorg/sireum/contract$Contract$Fact;
    MethodParameters:
      Name                           Flags
      claims                         final

  public org.sireum.contract$Contract$Fact Fact(java.lang.String, scala.collection.immutable.Seq<org.sireum.B>);
    descriptor: (Ljava/lang/String;Lscala/collection/immutable/Seq;)Lorg/sireum/contract$Contract$Fact;
    flags: (0x0001) ACC_PUBLIC
    Code:
      stack=3, locals=3, args_size=3
         0: aload_0
         1: aload_1
         2: aload_2
         3: invokestatic  #245                // InterfaceMethod org/sireum/contract.Fact$:(Lorg/sireum/contract;Ljava/lang/String;Lscala/collection/immutable/Seq;)Lorg/sireum/contract$Contract$Fact;
         6: areturn
      LineNumberTable:
        line 28: 0
      LocalVariableTable:
        Start  Length  Slot  Name   Signature
            0       7     0  this   Lorg/sireum/package$;
            0       7     1  desc   Ljava/lang/String;
            0       7     2 claims   Lscala/collection/immutable/Seq;
    Signature: #242                         // (Ljava/lang/String;Lscala/collection/immutable/Seq<Lorg/sireum/B;>;)Lorg/sireum/contract$Contract$Fact;
    MethodParameters:
      Name                           Flags
      desc                           final
      claims                         final

  public org.sireum.contract$Contract$Lemma Lemma(boolean, org.sireum.contract$Contract$Proof);
    descriptor: (ZLorg/sireum/contract$Contract$Proof;)Lorg/sireum/contract$Contract$Lemma;
    flags: (0x0001) ACC_PUBLIC
    Code:
      stack=3, locals=3, args_size=3
         0: aload_0
         1: iload_1
         2: aload_2
         3: invokestatic  #252                // InterfaceMethod org/sireum/contract.Lemma$:(Lorg/sireum/contract;ZLorg/sireum/contract$Contract$Proof;)Lorg/sireum/contract$Contract$Lemma;
         6: areturn
      LineNumberTable:
        line 28: 0
      LocalVariableTable:
        Start  Length  Slot  Name   Signature
            0       7     0  this   Lorg/sireum/package$;
            0       7     1 claim   Z
            0       7     2 proof   Lorg/sireum/contract$Contract$Proof;
    MethodParameters:
      Name                           Flags
      claim                          final
      proof                          final

  public org.sireum.contract$Contract$Lemma Lemma(java.lang.String, boolean, org.sireum.contract$Contract$Proof);
    descriptor: (Ljava/lang/String;ZLorg/sireum/contract$Contract$Proof;)Lorg/sireum/contract$Contract$Lemma;
    flags: (0x0001) ACC_PUBLIC
    Code:
      stack=4, locals=4, args_size=4
         0: aload_0
         1: aload_1
         2: iload_2
         3: aload_3
         4: invokestatic  #257                // InterfaceMethod org/sireum/contract.Lemma$:(Lorg/sireum/contract;Ljava/lang/String;ZLorg/sireum/contract$Contract$Proof;)Lorg/sireum/contract$Contract$Lemma;
         7: areturn
      LineNumberTable:
        line 28: 0
      LocalVariableTable:
        Start  Length  Slot  Name   Signature
            0       8     0  this   Lorg/sireum/package$;
            0       8     1  desc   Ljava/lang/String;
            0       8     2 claim   Z
            0       8     3 proof   Lorg/sireum/contract$Contract$Proof;
    MethodParameters:
      Name                           Flags
      desc                           final
      claim                          final
      proof                          final

  public org.sireum.contract$Contract$Theorem Theorem(boolean, org.sireum.contract$Contract$Proof);
    descriptor: (ZLorg/sireum/contract$Contract$Proof;)Lorg/sireum/contract$Contract$Theorem;
    flags: (0x0001) ACC_PUBLIC
    Code:
      stack=3, locals=3, args_size=3
         0: aload_0
         1: iload_1
         2: aload_2
         3: invokestatic  #262                // InterfaceMethod org/sireum/contract.Theorem$:(Lorg/sireum/contract;ZLorg/sireum/contract$Contract$Proof;)Lorg/sireum/contract$Contract$Theorem;
         6: areturn
      LineNumberTable:
        line 28: 0
      LocalVariableTable:
        Start  Length  Slot  Name   Signature
            0       7     0  this   Lorg/sireum/package$;
            0       7     1 claim   Z
            0       7     2 proof   Lorg/sireum/contract$Contract$Proof;
    MethodParameters:
      Name                           Flags
      claim                          final
      proof                          final

  public org.sireum.contract$Contract$Theorem Theorem(java.lang.String, boolean, org.sireum.contract$Contract$Proof);
    descriptor: (Ljava/lang/String;ZLorg/sireum/contract$Contract$Proof;)Lorg/sireum/contract$Contract$Theorem;
    flags: (0x0001) ACC_PUBLIC
    Code:
      stack=4, locals=4, args_size=4
         0: aload_0
         1: aload_1
         2: iload_2
         3: aload_3
         4: invokestatic  #266                // InterfaceMethod org/sireum/contract.Theorem$:(Lorg/sireum/contract;Ljava/lang/String;ZLorg/sireum/contract$Contract$Proof;)Lorg/sireum/contract$Contract$Theorem;
         7: areturn
      LineNumberTable:
        line 28: 0
      LocalVariableTable:
        Start  Length  Slot  Name   Signature
            0       8     0  this   Lorg/sireum/package$;
            0       8     1  desc   Ljava/lang/String;
            0       8     2 claim   Z
            0       8     3 proof   Lorg/sireum/contract$Contract$Proof;
    MethodParameters:
      Name                           Flags
      desc                           final
      claim                          final
      proof                          final

  public org.sireum.contract$Contract$Proof Proof(scala.collection.immutable.Seq<org.sireum.contract$Contract$ProofStep>);
    descriptor: (Lscala/collection/immutable/Seq;)Lorg/sireum/contract$Contract$Proof;
    flags: (0x0001) ACC_PUBLIC
    Code:
      stack=2, locals=2, args_size=2
         0: aload_0
         1: aload_1
         2: invokestatic  #273                // InterfaceMethod org/sireum/contract.Proof$:(Lorg/sireum/contract;Lscala/collection/immutable/Seq;)Lorg/sireum/contract$Contract$Proof;
         5: areturn
      LineNumberTable:
        line 28: 0
      LocalVariableTable:
        Start  Length  Slot  Name   Signature
            0       6     0  this   Lorg/sireum/package$;
            0       6     1 steps   Lscala/collection/immutable/Seq;
    Signature: #268                         // (Lscala/collection/immutable/Seq<Lorg/sireum/contract$Contract$ProofStep;>;)Lorg/sireum/contract$Contract$Proof;
    MethodParameters:
      Name                           Flags
      steps                          final

  public org.sireum.contract$Contract$ProofStep Step(int, boolean);
    descriptor: (IZ)Lorg/sireum/contract$Contract$ProofStep;
    flags: (0x0001) ACC_PUBLIC
    Code:
      stack=3, locals=3, args_size=3
         0: aload_0
         1: iload_1
         2: iload_2
         3: invokestatic  #280                // InterfaceMethod org/sireum/contract.Step$:(Lorg/sireum/contract;IZ)Lorg/sireum/contract$Contract$ProofStep;
         6: areturn
      LineNumberTable:
        line 28: 0
      LocalVariableTable:
        Start  Length  Slot  Name   Signature
            0       7     0  this   Lorg/sireum/package$;
            0       7     1    no   I
            0       7     2 claim   Z
    MethodParameters:
      Name                           Flags
      no                             final
      claim                          final

  public org.sireum.contract$Contract$ProofStep Step(int, boolean, org.sireum.contract$Contract$Justification);
    descriptor: (IZLorg/sireum/contract$Contract$Justification;)Lorg/sireum/contract$Contract$ProofStep;
    flags: (0x0001) ACC_PUBLIC
    Code:
      stack=4, locals=4, args_size=4
         0: aload_0
         1: iload_1
         2: iload_2
         3: aload_3
         4: invokestatic  #286                // InterfaceMethod org/sireum/contract.Step$:(Lorg/sireum/contract;IZLorg/sireum/contract$Contract$Justification;)Lorg/sireum/contract$Contract$ProofStep;
         7: areturn
      LineNumberTable:
        line 28: 0
      LocalVariableTable:
        Start  Length  Slot  Name   Signature
            0       8     0  this   Lorg/sireum/package$;
            0       8     1    no   I
            0       8     2 claim   Z
            0       8     3  just   Lorg/sireum/contract$Contract$Justification;
    MethodParameters:
      Name                           Flags
      no                             final
      claim                          final
      just                           final

  public org.sireum.contract$Contract$SubProof SubProof(scala.collection.immutable.Seq<org.sireum.contract$Contract$ProofStep>);
    descriptor: (Lscala/collection/immutable/Seq;)Lorg/sireum/contract$Contract$SubProof;
    flags: (0x0001) ACC_PUBLIC
    Code:
      stack=2, locals=2, args_size=2
         0: aload_0
         1: aload_1
         2: invokestatic  #293                // InterfaceMethod org/sireum/contract.SubProof$:(Lorg/sireum/contract;Lscala/collection/immutable/Seq;)Lorg/sireum/contract$Contract$SubProof;
         5: areturn
      LineNumberTable:
        line 28: 0
      LocalVariableTable:
        Start  Length  Slot  Name   Signature
            0       6     0  this   Lorg/sireum/package$;
            0       6     1 steps   Lscala/collection/immutable/Seq;
    Signature: #289                         // (Lscala/collection/immutable/Seq<Lorg/sireum/contract$Contract$ProofStep;>;)Lorg/sireum/contract$Contract$SubProof;
    MethodParameters:
      Name                           Flags
      steps                          final

  public org.sireum.contract$Contract$Assume Assume(boolean);
    descriptor: (Z)Lorg/sireum/contract$Contract$Assume;
    flags: (0x0001) ACC_PUBLIC
    Code:
      stack=2, locals=2, args_size=2
         0: aload_0
         1: iload_1
         2: invokestatic  #298                // InterfaceMethod org/sireum/contract.Assume$:(Lorg/sireum/contract;Z)Lorg/sireum/contract$Contract$Assume;
         5: areturn
      LineNumberTable:
        line 28: 0
      LocalVariableTable:
        Start  Length  Slot  Name   Signature
            0       6     0  this   Lorg/sireum/package$;
            0       6     1 claim   Z
    MethodParameters:
      Name                           Flags
      claim                          final

  public org.sireum.contract$Contract$Assert Assert(boolean, org.sireum.contract$Contract$SubProof);
    descriptor: (ZLorg/sireum/contract$Contract$SubProof;)Lorg/sireum/contract$Contract$Assert;
    flags: (0x0001) ACC_PUBLIC
    Code:
      stack=3, locals=3, args_size=3
         0: aload_0
         1: iload_1
         2: aload_2
         3: invokestatic  #304                // InterfaceMethod org/sireum/contract.Assert$:(Lorg/sireum/contract;ZLorg/sireum/contract$Contract$SubProof;)Lorg/sireum/contract$Contract$Assert;
         6: areturn
      LineNumberTable:
        line 28: 0
      LocalVariableTable:
        Start  Length  Slot  Name   Signature
            0       7     0  this   Lorg/sireum/package$;
            0       7     1 claim   Z
            0       7     2 subProof   Lorg/sireum/contract$Contract$SubProof;
    MethodParameters:
      Name                           Flags
      claim                          final
      subProof                       final

  public org.sireum.contract$Contract$Justification StructuralInduction(org.sireum.contract$Contract$SubProof);
    descriptor: (Lorg/sireum/contract$Contract$SubProof;)Lorg/sireum/contract$Contract$Justification;
    flags: (0x0001) ACC_PUBLIC
    Code:
      stack=2, locals=2, args_size=2
         0: aload_0
         1: aload_1
         2: invokestatic  #311                // InterfaceMethod org/sireum/contract.StructuralInduction$:(Lorg/sireum/contract;Lorg/sireum/contract$Contract$SubProof;)Lorg/sireum/contract$Contract$Justification;
         5: areturn
      LineNumberTable:
        line 28: 0
      LocalVariableTable:
        Start  Length  Slot  Name   Signature
            0       6     0  this   Lorg/sireum/package$;
            0       6     1 subProof   Lorg/sireum/contract$Contract$SubProof;
    MethodParameters:
      Name                           Flags
      subProof                       final

  public <T extends java.lang.Object> org.sireum.contract$Contract$Let Let(scala.Function1<T, org.sireum.contract$Contract$SubProof>);
    descriptor: (Lscala/Function1;)Lorg/sireum/contract$Contract$Let;
    flags: (0x0001) ACC_PUBLIC
    Code:
      stack=2, locals=2, args_size=2
         0: aload_0
         1: aload_1
         2: invokestatic  #318                // InterfaceMethod org/sireum/contract.Let$:(Lorg/sireum/contract;Lscala/Function1;)Lorg/sireum/contract$Contract$Let;
         5: areturn
      LineNumberTable:
        line 28: 0
      LocalVariableTable:
        Start  Length  Slot  Name   Signature
            0       6     0  this   Lorg/sireum/package$;
            0       6     1  body   Lscala/Function1;
    Signature: #313                         // <T:Ljava/lang/Object;>(Lscala/Function1<TT;Lorg/sireum/contract$Contract$SubProof;>;)Lorg/sireum/contract$Contract$Let;
    MethodParameters:
      Name                           Flags
      body                           final

  public <T1 extends java.lang.Object, T2 extends java.lang.Object> org.sireum.contract$Contract$Let Let(scala.Function2<T1, T2, org.sireum.contract$Contract$SubProof>);
    descriptor: (Lscala/Function2;)Lorg/sireum/contract$Contract$Let;
    flags: (0x0001) ACC_PUBLIC
    Code:
      stack=2, locals=2, args_size=2
         0: aload_0
         1: aload_1
         2: invokestatic  #324                // InterfaceMethod org/sireum/contract.Let$:(Lorg/sireum/contract;Lscala/Function2;)Lorg/sireum/contract$Contract$Let;
         5: areturn
      LineNumberTable:
        line 28: 0
      LocalVariableTable:
        Start  Length  Slot  Name   Signature
            0       6     0  this   Lorg/sireum/package$;
            0       6     1  body   Lscala/Function2;
    Signature: #321                         // <T1:Ljava/lang/Object;T2:Ljava/lang/Object;>(Lscala/Function2<TT1;TT2;Lorg/sireum/contract$Contract$SubProof;>;)Lorg/sireum/contract$Contract$Let;
    MethodParameters:
      Name                           Flags
      body                           final

  public <T1 extends java.lang.Object, T2 extends java.lang.Object, T3 extends java.lang.Object> org.sireum.contract$Contract$Let Let(scala.Function3<T1, T2, T3, org.sireum.contract$Contract$SubProof>);
    descriptor: (Lscala/Function3;)Lorg/sireum/contract$Contract$Let;
    flags: (0x0001) ACC_PUBLIC
    Code:
      stack=2, locals=2, args_size=2
         0: aload_0
         1: aload_1
         2: invokestatic  #330                // InterfaceMethod org/sireum/contract.Let$:(Lorg/sireum/contract;Lscala/Function3;)Lorg/sireum/contract$Contract$Let;
         5: areturn
      LineNumberTable:
        line 28: 0
      LocalVariableTable:
        Start  Length  Slot  Name   Signature
            0       6     0  this   Lorg/sireum/package$;
            0       6     1  body   Lscala/Function3;
    Signature: #327                         // <T1:Ljava/lang/Object;T2:Ljava/lang/Object;T3:Ljava/lang/Object;>(Lscala/Function3<TT1;TT2;TT3;Lorg/sireum/contract$Contract$SubProof;>;)Lorg/sireum/contract$Contract$Let;
    MethodParameters:
      Name                           Flags
      body                           final

  public <T1 extends java.lang.Object, T2 extends java.lang.Object, T3 extends java.lang.Object, T4 extends java.lang.Object> org.sireum.contract$Contract$Let Let(scala.Function4<T1, T2, T3, T4, org.sireum.contract$Contract$SubProof>);
    descriptor: (Lscala/Function4;)Lorg/sireum/contract$Contract$Let;
    flags: (0x0001) ACC_PUBLIC
    Code:
      stack=2, locals=2, args_size=2
         0: aload_0
         1: aload_1
         2: invokestatic  #336                // InterfaceMethod org/sireum/contract.Let$:(Lorg/sireum/contract;Lscala/Function4;)Lorg/sireum/contract$Contract$Let;
         5: areturn
      LineNumberTable:
        line 28: 0
      LocalVariableTable:
        Start  Length  Slot  Name   Signature
            0       6     0  this   Lorg/sireum/package$;
            0       6     1  body   Lscala/Function4;
    Signature: #333                         // <T1:Ljava/lang/Object;T2:Ljava/lang/Object;T3:Ljava/lang/Object;T4:Ljava/lang/Object;>(Lscala/Function4<TT1;TT2;TT3;TT4;Lorg/sireum/contract$Contract$SubProof;>;)Lorg/sireum/contract$Contract$Let;
    MethodParameters:
      Name                           Flags
      body                           final

  public <T1 extends java.lang.Object, T2 extends java.lang.Object, T3 extends java.lang.Object, T4 extends java.lang.Object, T5 extends java.lang.Object> org.sireum.contract$Contract$Let Let(scala.Function5<T1, T2, T3, T4, T5, org.sireum.contract$Contract$SubProof>);
    descriptor: (Lscala/Function5;)Lorg/sireum/contract$Contract$Let;
    flags: (0x0001) ACC_PUBLIC
    Code:
      stack=2, locals=2, args_size=2
         0: aload_0
         1: aload_1
         2: invokestatic  #342                // InterfaceMethod org/sireum/contract.Let$:(Lorg/sireum/contract;Lscala/Function5;)Lorg/sireum/contract$Contract$Let;
         5: areturn
      LineNumberTable:
        line 28: 0
      LocalVariableTable:
        Start  Length  Slot  Name   Signature
            0       6     0  this   Lorg/sireum/package$;
            0       6     1  body   Lscala/Function5;
    Signature: #339                         // <T1:Ljava/lang/Object;T2:Ljava/lang/Object;T3:Ljava/lang/Object;T4:Ljava/lang/Object;T5:Ljava/lang/Object;>(Lscala/Function5<TT1;TT2;TT3;TT4;TT5;Lorg/sireum/contract$Contract$SubProof;>;)Lorg/sireum/contract$Contract$Let;
    MethodParameters:
      Name                           Flags
      body                           final

  public <T1 extends java.lang.Object, T2 extends java.lang.Object, T3 extends java.lang.Object, T4 extends java.lang.Object, T5 extends java.lang.Object, T6 extends java.lang.Object> org.sireum.contract$Contract$Let Let(scala.Function6<T1, T2, T3, T4, T5, T6, org.sireum.contract$Contract$SubProof>);
    descriptor: (Lscala/Function6;)Lorg/sireum/contract$Contract$Let;
    flags: (0x0001) ACC_PUBLIC
    Code:
      stack=2, locals=2, args_size=2
         0: aload_0
         1: aload_1
         2: invokestatic  #348                // InterfaceMethod org/sireum/contract.Let$:(Lorg/sireum/contract;Lscala/Function6;)Lorg/sireum/contract$Contract$Let;
         5: areturn
      LineNumberTable:
        line 28: 0
      LocalVariableTable:
        Start  Length  Slot  Name   Signature
            0       6     0  this   Lorg/sireum/package$;
            0       6     1  body   Lscala/Function6;
    Signature: #345                         // <T1:Ljava/lang/Object;T2:Ljava/lang/Object;T3:Ljava/lang/Object;T4:Ljava/lang/Object;T5:Ljava/lang/Object;T6:Ljava/lang/Object;>(Lscala/Function6<TT1;TT2;TT3;TT4;TT5;TT6;Lorg/sireum/contract$Contract$SubProof;>;)Lorg/sireum/contract$Contract$Let;
    MethodParameters:
      Name                           Flags
      body                           final

  public <T1 extends java.lang.Object, T2 extends java.lang.Object, T3 extends java.lang.Object, T4 extends java.lang.Object, T5 extends java.lang.Object, T6 extends java.lang.Object, T7 extends java.lang.Object> org.sireum.contract$Contract$Let Let(scala.Function7<T1, T2, T3, T4, T5, T6, T7, org.sireum.contract$Contract$SubProof>);
    descriptor: (Lscala/Function7;)Lorg/sireum/contract$Contract$Let;
    flags: (0x0001) ACC_PUBLIC
    Code:
      stack=2, locals=2, args_size=2
         0: aload_0
         1: aload_1
         2: invokestatic  #354                // InterfaceMethod org/sireum/contract.Let$:(Lorg/sireum/contract;Lscala/Function7;)Lorg/sireum/contract$Contract$Let;
         5: areturn
      LineNumberTable:
        line 28: 0
      LocalVariableTable:
        Start  Length  Slot  Name   Signature
            0       6     0  this   Lorg/sireum/package$;
            0       6     1  body   Lscala/Function7;
    Signature: #351                         // <T1:Ljava/lang/Object;T2:Ljava/lang/Object;T3:Ljava/lang/Object;T4:Ljava/lang/Object;T5:Ljava/lang/Object;T6:Ljava/lang/Object;T7:Ljava/lang/Object;>(Lscala/Function7<TT1;TT2;TT3;TT4;TT5;TT6;TT7;Lorg/sireum/contract$Contract$SubProof;>;)Lorg/sireum/contract$Contract$Let;
    MethodParameters:
      Name                           Flags
      body                           final

  public <T1 extends java.lang.Object, T2 extends java.lang.Object, T3 extends java.lang.Object, T4 extends java.lang.Object, T5 extends java.lang.Object, T6 extends java.lang.Object, T7 extends java.lang.Object, T8 extends java.lang.Object> org.sireum.contract$Contract$Let Let(scala.Function8<T1, T2, T3, T4, T5, T6, T7, T8, org.sireum.contract$Contract$SubProof>);
    descriptor: (Lscala/Function8;)Lorg/sireum/contract$Contract$Let;
    flags: (0x0001) ACC_PUBLIC
    Code:
      stack=2, locals=2, args_size=2
         0: aload_0
         1: aload_1
         2: invokestatic  #360                // InterfaceMethod org/sireum/contract.Let$:(Lorg/sireum/contract;Lscala/Function8;)Lorg/sireum/contract$Contract$Let;
         5: areturn
      LineNumberTable:
        line 28: 0
      LocalVariableTable:
        Start  Length  Slot  Name   Signature
            0       6     0  this   Lorg/sireum/package$;
            0       6     1  body   Lscala/Function8;
    Signature: #357                         // <T1:Ljava/lang/Object;T2:Ljava/lang/Object;T3:Ljava/lang/Object;T4:Ljava/lang/Object;T5:Ljava/lang/Object;T6:Ljava/lang/Object;T7:Ljava/lang/Object;T8:Ljava/lang/Object;>(Lscala/Function8<TT1;TT2;TT3;TT4;TT5;TT6;TT7;TT8;Lorg/sireum/contract$Contract$SubProof;>;)Lorg/sireum/contract$Contract$Let;
    MethodParameters:
      Name                           Flags
      body                           final

  public <T1 extends java.lang.Object, T2 extends java.lang.Object, T3 extends java.lang.Object, T4 extends java.lang.Object, T5 extends java.lang.Object, T6 extends java.lang.Object, T7 extends java.lang.Object, T8 extends java.lang.Object, T9 extends java.lang.Object> org.sireum.contract$Contract$Let Let(scala.Function9<T1, T2, T3, T4, T5, T6, T7, T8, T9, org.sireum.contract$Contract$SubProof>);
    descriptor: (Lscala/Function9;)Lorg/sireum/contract$Contract$Let;
    flags: (0x0001) ACC_PUBLIC
    Code:
      stack=2, locals=2, args_size=2
         0: aload_0
         1: aload_1
         2: invokestatic  #366                // InterfaceMethod org/sireum/contract.Let$:(Lorg/sireum/contract;Lscala/Function9;)Lorg/sireum/contract$Contract$Let;
         5: areturn
      LineNumberTable:
        line 28: 0
      LocalVariableTable:
        Start  Length  Slot  Name   Signature
            0       6     0  this   Lorg/sireum/package$;
            0       6     1  body   Lscala/Function9;
    Signature: #363                         // <T1:Ljava/lang/Object;T2:Ljava/lang/Object;T3:Ljava/lang/Object;T4:Ljava/lang/Object;T5:Ljava/lang/Object;T6:Ljava/lang/Object;T7:Ljava/lang/Object;T8:Ljava/lang/Object;T9:Ljava/lang/Object;>(Lscala/Function9<TT1;TT2;TT3;TT4;TT5;TT6;TT7;TT8;TT9;Lorg/sireum/contract$Contract$SubProof;>;)Lorg/sireum/contract$Contract$Let;
    MethodParameters:
      Name                           Flags
      body                           final

  public <T1 extends java.lang.Object, T2 extends java.lang.Object, T3 extends java.lang.Object, T4 extends java.lang.Object, T5 extends java.lang.Object, T6 extends java.lang.Object, T7 extends java.lang.Object, T8 extends java.lang.Object, T9 extends java.lang.Object, T10 extends java.lang.Object> org.sireum.contract$Contract$Let Let(scala.Function10<T1, T2, T3, T4, T5, T6, T7, T8, T9, T10, org.sireum.contract$Contract$SubProof>);
    descriptor: (Lscala/Function10;)Lorg/sireum/contract$Contract$Let;
    flags: (0x0001) ACC_PUBLIC
    Code:
      stack=2, locals=2, args_size=2
         0: aload_0
         1: aload_1
         2: invokestatic  #372                // InterfaceMethod org/sireum/contract.Let$:(Lorg/sireum/contract;Lscala/Function10;)Lorg/sireum/contract$Contract$Let;
         5: areturn
      LineNumberTable:
        line 28: 0
      LocalVariableTable:
        Start  Length  Slot  Name   Signature
            0       6     0  this   Lorg/sireum/package$;
            0       6     1  body   Lscala/Function10;
    Signature: #369                         // <T1:Ljava/lang/Object;T2:Ljava/lang/Object;T3:Ljava/lang/Object;T4:Ljava/lang/Object;T5:Ljava/lang/Object;T6:Ljava/lang/Object;T7:Ljava/lang/Object;T8:Ljava/lang/Object;T9:Ljava/lang/Object;T10:Ljava/lang/Object;>(Lscala/Function10<TT1;TT2;TT3;TT4;TT5;TT6;TT7;TT8;TT9;TT10;Lorg/sireum/contract$Contract$SubProof;>;)Lorg/sireum/contract$Contract$Let;
    MethodParameters:
      Name                           Flags
      body                           final

  public <T1 extends java.lang.Object, T2 extends java.lang.Object, T3 extends java.lang.Object, T4 extends java.lang.Object, T5 extends java.lang.Object, T6 extends java.lang.Object, T7 extends java.lang.Object, T8 extends java.lang.Object, T9 extends java.lang.Object, T10 extends java.lang.Object, T11 extends java.lang.Object> org.sireum.contract$Contract$Let Let(scala.Function11<T1, T2, T3, T4, T5, T6, T7, T8, T9, T10, T11, org.sireum.contract$Contract$SubProof>);
    descriptor: (Lscala/Function11;)Lorg/sireum/contract$Contract$Let;
    flags: (0x0001) ACC_PUBLIC
    Code:
      stack=2, locals=2, args_size=2
         0: aload_0
         1: aload_1
         2: invokestatic  #378                // InterfaceMethod org/sireum/contract.Let$:(Lorg/sireum/contract;Lscala/Function11;)Lorg/sireum/contract$Contract$Let;
         5: areturn
      LineNumberTable:
        line 28: 0
      LocalVariableTable:
        Start  Length  Slot  Name   Signature
            0       6     0  this   Lorg/sireum/package$;
            0       6     1  body   Lscala/Function11;
    Signature: #375                         // <T1:Ljava/lang/Object;T2:Ljava/lang/Object;T3:Ljava/lang/Object;T4:Ljava/lang/Object;T5:Ljava/lang/Object;T6:Ljava/lang/Object;T7:Ljava/lang/Object;T8:Ljava/lang/Object;T9:Ljava/lang/Object;T10:Ljava/lang/Object;T11:Ljava/lang/Object;>(Lscala/Function11<TT1;TT2;TT3;TT4;TT5;TT6;TT7;TT8;TT9;TT10;TT11;Lorg/sireum/contract$Contract$SubProof;>;)Lorg/sireum/contract$Contract$Let;
    MethodParameters:
      Name                           Flags
      body                           final

  public <T1 extends java.lang.Object, T2 extends java.lang.Object, T3 extends java.lang.Object, T4 extends java.lang.Object, T5 extends java.lang.Object, T6 extends java.lang.Object, T7 extends java.lang.Object, T8 extends java.lang.Object, T9 extends java.lang.Object, T10 extends java.lang.Object, T11 extends java.lang.Object, T12 extends java.lang.Object> org.sireum.contract$Contract$Let Let(scala.Function12<T1, T2, T3, T4, T5, T6, T7, T8, T9, T10, T11, T12, org.sireum.contract$Contract$SubProof>);
    descriptor: (Lscala/Function12;)Lorg/sireum/contract$Contract$Let;
    flags: (0x0001) ACC_PUBLIC
    Code:
      stack=2, locals=2, args_size=2
         0: aload_0
         1: aload_1
         2: invokestatic  #384                // InterfaceMethod org/sireum/contract.Let$:(Lorg/sireum/contract;Lscala/Function12;)Lorg/sireum/contract$Contract$Let;
         5: areturn
      LineNumberTable:
        line 28: 0
      LocalVariableTable:
        Start  Length  Slot  Name   Signature
            0       6     0  this   Lorg/sireum/package$;
            0       6     1  body   Lscala/Function12;
    Signature: #381                         // <T1:Ljava/lang/Object;T2:Ljava/lang/Object;T3:Ljava/lang/Object;T4:Ljava/lang/Object;T5:Ljava/lang/Object;T6:Ljava/lang/Object;T7:Ljava/lang/Object;T8:Ljava/lang/Object;T9:Ljava/lang/Object;T10:Ljava/lang/Object;T11:Ljava/lang/Object;T12:Ljava/lang/Object;>(Lscala/Function12<TT1;TT2;TT3;TT4;TT5;TT6;TT7;TT8;TT9;TT10;TT11;TT12;Lorg/sireum/contract$Contract$SubProof;>;)Lorg/sireum/contract$Contract$Let;
    MethodParameters:
      Name                           Flags
      body                           final

  public <T1 extends java.lang.Object, T2 extends java.lang.Object, T3 extends java.lang.Object, T4 extends java.lang.Object, T5 extends java.lang.Object, T6 extends java.lang.Object, T7 extends java.lang.Object, T8 extends java.lang.Object, T9 extends java.lang.Object, T10 extends java.lang.Object, T11 extends java.lang.Object, T12 extends java.lang.Object, T13 extends java.lang.Object> org.sireum.contract$Contract$Let Let(scala.Function13<T1, T2, T3, T4, T5, T6, T7, T8, T9, T10, T11, T12, T13, org.sireum.contract$Contract$SubProof>);
    descriptor: (Lscala/Function13;)Lorg/sireum/contract$Contract$Let;
    flags: (0x0001) ACC_PUBLIC
    Code:
      stack=2, locals=2, args_size=2
         0: aload_0
         1: aload_1
         2: invokestatic  #390                // InterfaceMethod org/sireum/contract.Let$:(Lorg/sireum/contract;Lscala/Function13;)Lorg/sireum/contract$Contract$Let;
         5: areturn
      LineNumberTable:
        line 28: 0
      LocalVariableTable:
        Start  Length  Slot  Name   Signature
            0       6     0  this   Lorg/sireum/package$;
            0       6     1  body   Lscala/Function13;
    Signature: #387                         // <T1:Ljava/lang/Object;T2:Ljava/lang/Object;T3:Ljava/lang/Object;T4:Ljava/lang/Object;T5:Ljava/lang/Object;T6:Ljava/lang/Object;T7:Ljava/lang/Object;T8:Ljava/lang/Object;T9:Ljava/lang/Object;T10:Ljava/lang/Object;T11:Ljava/lang/Object;T12:Ljava/lang/Object;T13:Ljava/lang/Object;>(Lscala/Function13<TT1;TT2;TT3;TT4;TT5;TT6;TT7;TT8;TT9;TT10;TT11;TT12;TT13;Lorg/sireum/contract$Contract$SubProof;>;)Lorg/sireum/contract$Contract$Let;
    MethodParameters:
      Name                           Flags
      body                           final

  public <T1 extends java.lang.Object, T2 extends java.lang.Object, T3 extends java.lang.Object, T4 extends java.lang.Object, T5 extends java.lang.Object, T6 extends java.lang.Object, T7 extends java.lang.Object, T8 extends java.lang.Object, T9 extends java.lang.Object, T10 extends java.lang.Object, T11 extends java.lang.Object, T12 extends java.lang.Object, T13 extends java.lang.Object, T14 extends java.lang.Object> org.sireum.contract$Contract$Let Let(scala.Function14<T1, T2, T3, T4, T5, T6, T7, T8, T9, T10, T11, T12, T13, T14, org.sireum.contract$Contract$SubProof>);
    descriptor: (Lscala/Function14;)Lorg/sireum/contract$Contract$Let;
    flags: (0x0001) ACC_PUBLIC
    Code:
      stack=2, locals=2, args_size=2
         0: aload_0
         1: aload_1
         2: invokestatic  #396                // InterfaceMethod org/sireum/contract.Let$:(Lorg/sireum/contract;Lscala/Function14;)Lorg/sireum/contract$Contract$Let;
         5: areturn
      LineNumberTable:
        line 28: 0
      LocalVariableTable:
        Start  Length  Slot  Name   Signature
            0       6     0  this   Lorg/sireum/package$;
            0       6     1  body   Lscala/Function14;
    Signature: #393                         // <T1:Ljava/lang/Object;T2:Ljava/lang/Object;T3:Ljava/lang/Object;T4:Ljava/lang/Object;T5:Ljava/lang/Object;T6:Ljava/lang/Object;T7:Ljava/lang/Object;T8:Ljava/lang/Object;T9:Ljava/lang/Object;T10:Ljava/lang/Object;T11:Ljava/lang/Object;T12:Ljava/lang/Object;T13:Ljava/lang/Object;T14:Ljava/lang/Object;>(Lscala/Function14<TT1;TT2;TT3;TT4;TT5;TT6;TT7;TT8;TT9;TT10;TT11;TT12;TT13;TT14;Lorg/sireum/contract$Contract$SubProof;>;)Lorg/sireum/contract$Contract$Let;
    MethodParameters:
      Name                           Flags
      body                           final

  public <T1 extends java.lang.Object, T2 extends java.lang.Object, T3 extends java.lang.Object, T4 extends java.lang.Object, T5 extends java.lang.Object, T6 extends java.lang.Object, T7 extends java.lang.Object, T8 extends java.lang.Object, T9 extends java.lang.Object, T10 extends java.lang.Object, T11 extends java.lang.Object, T12 extends java.lang.Object, T13 extends java.lang.Object, T14 extends java.lang.Object, T15 extends java.lang.Object> org.sireum.contract$Contract$Let Let(scala.Function15<T1, T2, T3, T4, T5, T6, T7, T8, T9, T10, T11, T12, T13, T14, T15, org.sireum.contract$Contract$SubProof>);
    descriptor: (Lscala/Function15;)Lorg/sireum/contract$Contract$Let;
    flags: (0x0001) ACC_PUBLIC
    Code:
      stack=2, locals=2, args_size=2
         0: aload_0
         1: aload_1
         2: invokestatic  #402                // InterfaceMethod org/sireum/contract.Let$:(Lorg/sireum/contract;Lscala/Function15;)Lorg/sireum/contract$Contract$Let;
         5: areturn
      LineNumberTable:
        line 28: 0
      LocalVariableTable:
        Start  Length  Slot  Name   Signature
            0       6     0  this   Lorg/sireum/package$;
            0       6     1  body   Lscala/Function15;
    Signature: #399                         // <T1:Ljava/lang/Object;T2:Ljava/lang/Object;T3:Ljava/lang/Object;T4:Ljava/lang/Object;T5:Ljava/lang/Object;T6:Ljava/lang/Object;T7:Ljava/lang/Object;T8:Ljava/lang/Object;T9:Ljava/lang/Object;T10:Ljava/lang/Object;T11:Ljava/lang/Object;T12:Ljava/lang/Object;T13:Ljava/lang/Object;T14:Ljava/lang/Object;T15:Ljava/lang/Object;>(Lscala/Function15<TT1;TT2;TT3;TT4;TT5;TT6;TT7;TT8;TT9;TT10;TT11;TT12;TT13;TT14;TT15;Lorg/sireum/contract$Contract$SubProof;>;)Lorg/sireum/contract$Contract$Let;
    MethodParameters:
      Name                           Flags
      body                           final

  public <T1 extends java.lang.Object, T2 extends java.lang.Object, T3 extends java.lang.Object, T4 extends java.lang.Object, T5 extends java.lang.Object, T6 extends java.lang.Object, T7 extends java.lang.Object, T8 extends java.lang.Object, T9 extends java.lang.Object, T10 extends java.lang.Object, T11 extends java.lang.Object, T12 extends java.lang.Object, T13 extends java.lang.Object, T14 extends java.lang.Object, T15 extends java.lang.Object, T16 extends java.lang.Object> org.sireum.contract$Contract$Let Let(scala.Function16<T1, T2, T3, T4, T5, T6, T7, T8, T9, T10, T11, T12, T13, T14, T15, T16, org.sireum.contract$Contract$SubProof>);
    descriptor: (Lscala/Function16;)Lorg/sireum/contract$Contract$Let;
    flags: (0x0001) ACC_PUBLIC
    Code:
      stack=2, locals=2, args_size=2
         0: aload_0
         1: aload_1
         2: invokestatic  #408                // InterfaceMethod org/sireum/contract.Let$:(Lorg/sireum/contract;Lscala/Function16;)Lorg/sireum/contract$Contract$Let;
         5: areturn
      LineNumberTable:
        line 28: 0
      LocalVariableTable:
        Start  Length  Slot  Name   Signature
            0       6     0  this   Lorg/sireum/package$;
            0       6     1  body   Lscala/Function16;
    Signature: #405                         // <T1:Ljava/lang/Object;T2:Ljava/lang/Object;T3:Ljava/lang/Object;T4:Ljava/lang/Object;T5:Ljava/lang/Object;T6:Ljava/lang/Object;T7:Ljava/lang/Object;T8:Ljava/lang/Object;T9:Ljava/lang/Object;T10:Ljava/lang/Object;T11:Ljava/lang/Object;T12:Ljava/lang/Object;T13:Ljava/lang/Object;T14:Ljava/lang/Object;T15:Ljava/lang/Object;T16:Ljava/lang/Object;>(Lscala/Function16<TT1;TT2;TT3;TT4;TT5;TT6;TT7;TT8;TT9;TT10;TT11;TT12;TT13;TT14;TT15;TT16;Lorg/sireum/contract$Contract$SubProof;>;)Lorg/sireum/contract$Contract$Let;
    MethodParameters:
      Name                           Flags
      body                           final

  public <T1 extends java.lang.Object, T2 extends java.lang.Object, T3 extends java.lang.Object, T4 extends java.lang.Object, T5 extends java.lang.Object, T6 extends java.lang.Object, T7 extends java.lang.Object, T8 extends java.lang.Object, T9 extends java.lang.Object, T10 extends java.lang.Object, T11 extends java.lang.Object, T12 extends java.lang.Object, T13 extends java.lang.Object, T14 extends java.lang.Object, T15 extends java.lang.Object, T16 extends java.lang.Object, T17 extends java.lang.Object> org.sireum.contract$Contract$Let Let(scala.Function17<T1, T2, T3, T4, T5, T6, T7, T8, T9, T10, T11, T12, T13, T14, T15, T16, T17, org.sireum.contract$Contract$SubProof>);
    descriptor: (Lscala/Function17;)Lorg/sireum/contract$Contract$Let;
    flags: (0x0001) ACC_PUBLIC
    Code:
      stack=2, locals=2, args_size=2
         0: aload_0
         1: aload_1
         2: invokestatic  #414                // InterfaceMethod org/sireum/contract.Let$:(Lorg/sireum/contract;Lscala/Function17;)Lorg/sireum/contract$Contract$Let;
         5: areturn
      LineNumberTable:
        line 28: 0
      LocalVariableTable:
        Start  Length  Slot  Name   Signature
            0       6     0  this   Lorg/sireum/package$;
            0       6     1  body   Lscala/Function17;
    Signature: #411                         // <T1:Ljava/lang/Object;T2:Ljava/lang/Object;T3:Ljava/lang/Object;T4:Ljava/lang/Object;T5:Ljava/lang/Object;T6:Ljava/lang/Object;T7:Ljava/lang/Object;T8:Ljava/lang/Object;T9:Ljava/lang/Object;T10:Ljava/lang/Object;T11:Ljava/lang/Object;T12:Ljava/lang/Object;T13:Ljava/lang/Object;T14:Ljava/lang/Object;T15:Ljava/lang/Object;T16:Ljava/lang/Object;T17:Ljava/lang/Object;>(Lscala/Function17<TT1;TT2;TT3;TT4;TT5;TT6;TT7;TT8;TT9;TT10;TT11;TT12;TT13;TT14;TT15;TT16;TT17;Lorg/sireum/contract$Contract$SubProof;>;)Lorg/sireum/contract$Contract$Let;
    MethodParameters:
      Name                           Flags
      body                           final

  public <T1 extends java.lang.Object, T2 extends java.lang.Object, T3 extends java.lang.Object, T4 extends java.lang.Object, T5 extends java.lang.Object, T6 extends java.lang.Object, T7 extends java.lang.Object, T8 extends java.lang.Object, T9 extends java.lang.Object, T10 extends java.lang.Object, T11 extends java.lang.Object, T12 extends java.lang.Object, T13 extends java.lang.Object, T14 extends java.lang.Object, T15 extends java.lang.Object, T16 extends java.lang.Object, T17 extends java.lang.Object, T18 extends java.lang.Object> org.sireum.contract$Contract$Let Let(scala.Function18<T1, T2, T3, T4, T5, T6, T7, T8, T9, T10, T11, T12, T13, T14, T15, T16, T17, T18, org.sireum.contract$Contract$SubProof>);
    descriptor: (Lscala/Function18;)Lorg/sireum/contract$Contract$Let;
    flags: (0x0001) ACC_PUBLIC
    Code:
      stack=2, locals=2, args_size=2
         0: aload_0
         1: aload_1
         2: invokestatic  #420                // InterfaceMethod org/sireum/contract.Let$:(Lorg/sireum/contract;Lscala/Function18;)Lorg/sireum/contract$Contract$Let;
         5: areturn
      LineNumberTable:
        line 28: 0
      LocalVariableTable:
        Start  Length  Slot  Name   Signature
            0       6     0  this   Lorg/sireum/package$;
            0       6     1  body   Lscala/Function18;
    Signature: #417                         // <T1:Ljava/lang/Object;T2:Ljava/lang/Object;T3:Ljava/lang/Object;T4:Ljava/lang/Object;T5:Ljava/lang/Object;T6:Ljava/lang/Object;T7:Ljava/lang/Object;T8:Ljava/lang/Object;T9:Ljava/lang/Object;T10:Ljava/lang/Object;T11:Ljava/lang/Object;T12:Ljava/lang/Object;T13:Ljava/lang/Object;T14:Ljava/lang/Object;T15:Ljava/lang/Object;T16:Ljava/lang/Object;T17:Ljava/lang/Object;T18:Ljava/lang/Object;>(Lscala/Function18<TT1;TT2;TT3;TT4;TT5;TT6;TT7;TT8;TT9;TT10;TT11;TT12;TT13;TT14;TT15;TT16;TT17;TT18;Lorg/sireum/contract$Contract$SubProof;>;)Lorg/sireum/contract$Contract$Let;
    MethodParameters:
      Name                           Flags
      body                           final

  public <T1 extends java.lang.Object, T2 extends java.lang.Object, T3 extends java.lang.Object, T4 extends java.lang.Object, T5 extends java.lang.Object, T6 extends java.lang.Object, T7 extends java.lang.Object, T8 extends java.lang.Object, T9 extends java.lang.Object, T10 extends java.lang.Object, T11 extends java.lang.Object, T12 extends java.lang.Object, T13 extends java.lang.Object, T14 extends java.lang.Object, T15 extends java.lang.Object, T16 extends java.lang.Object, T17 extends java.lang.Object, T18 extends java.lang.Object, T19 extends java.lang.Object> org.sireum.contract$Contract$Let Let(scala.Function19<T1, T2, T3, T4, T5, T6, T7, T8, T9, T10, T11, T12, T13, T14, T15, T16, T17, T18, T19, org.sireum.contract$Contract$SubProof>);
    descriptor: (Lscala/Function19;)Lorg/sireum/contract$Contract$Let;
    flags: (0x0001) ACC_PUBLIC
    Code:
      stack=2, locals=2, args_size=2
         0: aload_0
         1: aload_1
         2: invokestatic  #426                // InterfaceMethod org/sireum/contract.Let$:(Lorg/sireum/contract;Lscala/Function19;)Lorg/sireum/contract$Contract$Let;
         5: areturn
      LineNumberTable:
        line 28: 0
      LocalVariableTable:
        Start  Length  Slot  Name   Signature
            0       6     0  this   Lorg/sireum/package$;
            0       6     1  body   Lscala/Function19;
    Signature: #423                         // <T1:Ljava/lang/Object;T2:Ljava/lang/Object;T3:Ljava/lang/Object;T4:Ljava/lang/Object;T5:Ljava/lang/Object;T6:Ljava/lang/Object;T7:Ljava/lang/Object;T8:Ljava/lang/Object;T9:Ljava/lang/Object;T10:Ljava/lang/Object;T11:Ljava/lang/Object;T12:Ljava/lang/Object;T13:Ljava/lang/Object;T14:Ljava/lang/Object;T15:Ljava/lang/Object;T16:Ljava/lang/Object;T17:Ljava/lang/Object;T18:Ljava/lang/Object;T19:Ljava/lang/Object;>(Lscala/Function19<TT1;TT2;TT3;TT4;TT5;TT6;TT7;TT8;TT9;TT10;TT11;TT12;TT13;TT14;TT15;TT16;TT17;TT18;TT19;Lorg/sireum/contract$Contract$SubProof;>;)Lorg/sireum/contract$Contract$Let;
    MethodParameters:
      Name                           Flags
      body                           final

  public <T1 extends java.lang.Object, T2 extends java.lang.Object, T3 extends java.lang.Object, T4 extends java.lang.Object, T5 extends java.lang.Object, T6 extends java.lang.Object, T7 extends java.lang.Object, T8 extends java.lang.Object, T9 extends java.lang.Object, T10 extends java.lang.Object, T11 extends java.lang.Object, T12 extends java.lang.Object, T13 extends java.lang.Object, T14 extends java.lang.Object, T15 extends java.lang.Object, T16 extends java.lang.Object, T17 extends java.lang.Object, T18 extends java.lang.Object, T19 extends java.lang.Object, T20 extends java.lang.Object> org.sireum.contract$Contract$Let Let(scala.Function20<T1, T2, T3, T4, T5, T6, T7, T8, T9, T10, T11, T12, T13, T14, T15, T16, T17, T18, T19, T20, org.sireum.contract$Contract$SubProof>);
    descriptor: (Lscala/Function20;)Lorg/sireum/contract$Contract$Let;
    flags: (0x0001) ACC_PUBLIC
    Code:
      stack=2, locals=2, args_size=2
         0: aload_0
         1: aload_1
         2: invokestatic  #432                // InterfaceMethod org/sireum/contract.Let$:(Lorg/sireum/contract;Lscala/Function20;)Lorg/sireum/contract$Contract$Let;
         5: areturn
      LineNumberTable:
        line 28: 0
      LocalVariableTable:
        Start  Length  Slot  Name   Signature
            0       6     0  this   Lorg/sireum/package$;
            0       6     1  body   Lscala/Function20;
    Signature: #429                         // <T1:Ljava/lang/Object;T2:Ljava/lang/Object;T3:Ljava/lang/Object;T4:Ljava/lang/Object;T5:Ljava/lang/Object;T6:Ljava/lang/Object;T7:Ljava/lang/Object;T8:Ljava/lang/Object;T9:Ljava/lang/Object;T10:Ljava/lang/Object;T11:Ljava/lang/Object;T12:Ljava/lang/Object;T13:Ljava/lang/Object;T14:Ljava/lang/Object;T15:Ljava/lang/Object;T16:Ljava/lang/Object;T17:Ljava/lang/Object;T18:Ljava/lang/Object;T19:Ljava/lang/Object;T20:Ljava/lang/Object;>(Lscala/Function20<TT1;TT2;TT3;TT4;TT5;TT6;TT7;TT8;TT9;TT10;TT11;TT12;TT13;TT14;TT15;TT16;TT17;TT18;TT19;TT20;Lorg/sireum/contract$Contract$SubProof;>;)Lorg/sireum/contract$Contract$Let;
    MethodParameters:
      Name                           Flags
      body                           final

  public <T1 extends java.lang.Object, T2 extends java.lang.Object, T3 extends java.lang.Object, T4 extends java.lang.Object, T5 extends java.lang.Object, T6 extends java.lang.Object, T7 extends java.lang.Object, T8 extends java.lang.Object, T9 extends java.lang.Object, T10 extends java.lang.Object, T11 extends java.lang.Object, T12 extends java.lang.Object, T13 extends java.lang.Object, T14 extends java.lang.Object, T15 extends java.lang.Object, T16 extends java.lang.Object, T17 extends java.lang.Object, T18 extends java.lang.Object, T19 extends java.lang.Object, T20 extends java.lang.Object, T21 extends java.lang.Object> org.sireum.contract$Contract$Let Let(scala.Function21<T1, T2, T3, T4, T5, T6, T7, T8, T9, T10, T11, T12, T13, T14, T15, T16, T17, T18, T19, T20, T21, org.sireum.contract$Contract$SubProof>);
    descriptor: (Lscala/Function21;)Lorg/sireum/contract$Contract$Let;
    flags: (0x0001) ACC_PUBLIC
    Code:
      stack=2, locals=2, args_size=2
         0: aload_0
         1: aload_1
         2: invokestatic  #438                // InterfaceMethod org/sireum/contract.Let$:(Lorg/sireum/contract;Lscala/Function21;)Lorg/sireum/contract$Contract$Let;
         5: areturn
      LineNumberTable:
        line 28: 0
      LocalVariableTable:
        Start  Length  Slot  Name   Signature
            0       6     0  this   Lorg/sireum/package$;
            0       6     1  body   Lscala/Function21;
    Signature: #435                         // <T1:Ljava/lang/Object;T2:Ljava/lang/Object;T3:Ljava/lang/Object;T4:Ljava/lang/Object;T5:Ljava/lang/Object;T6:Ljava/lang/Object;T7:Ljava/lang/Object;T8:Ljava/lang/Object;T9:Ljava/lang/Object;T10:Ljava/lang/Object;T11:Ljava/lang/Object;T12:Ljava/lang/Object;T13:Ljava/lang/Object;T14:Ljava/lang/Object;T15:Ljava/lang/Object;T16:Ljava/lang/Object;T17:Ljava/lang/Object;T18:Ljava/lang/Object;T19:Ljava/lang/Object;T20:Ljava/lang/Object;T21:Ljava/lang/Object;>(Lscala/Function21<TT1;TT2;TT3;TT4;TT5;TT6;TT7;TT8;TT9;TT10;TT11;TT12;TT13;TT14;TT15;TT16;TT17;TT18;TT19;TT20;TT21;Lorg/sireum/contract$Contract$SubProof;>;)Lorg/sireum/contract$Contract$Let;
    MethodParameters:
      Name                           Flags
      body                           final

  public <T1 extends java.lang.Object, T2 extends java.lang.Object, T3 extends java.lang.Object, T4 extends java.lang.Object, T5 extends java.lang.Object, T6 extends java.lang.Object, T7 extends java.lang.Object, T8 extends java.lang.Object, T9 extends java.lang.Object, T10 extends java.lang.Object, T11 extends java.lang.Object, T12 extends java.lang.Object, T13 extends java.lang.Object, T14 extends java.lang.Object, T15 extends java.lang.Object, T16 extends java.lang.Object, T17 extends java.lang.Object, T18 extends java.lang.Object, T19 extends java.lang.Object, T20 extends java.lang.Object, T21 extends java.lang.Object, T22 extends java.lang.Object> org.sireum.contract$Contract$Let Let(scala.Function22<T1, T2, T3, T4, T5, T6, T7, T8, T9, T10, T11, T12, T13, T14, T15, T16, T17, T18, T19, T20, T21, T22, org.sireum.contract$Contract$SubProof>);
    descriptor: (Lscala/Function22;)Lorg/sireum/contract$Contract$Let;
    flags: (0x0001) ACC_PUBLIC
    Code:
      stack=2, locals=2, args_size=2
         0: aload_0
         1: aload_1
         2: invokestatic  #444                // InterfaceMethod org/sireum/contract.Let$:(Lorg/sireum/contract;Lscala/Function22;)Lorg/sireum/contract$Contract$Let;
         5: areturn
      LineNumberTable:
        line 28: 0
      LocalVariableTable:
        Start  Length  Slot  Name   Signature
            0       6     0  this   Lorg/sireum/package$;
            0       6     1  body   Lscala/Function22;
    Signature: #441                         // <T1:Ljava/lang/Object;T2:Ljava/lang/Object;T3:Ljava/lang/Object;T4:Ljava/lang/Object;T5:Ljava/lang/Object;T6:Ljava/lang/Object;T7:Ljava/lang/Object;T8:Ljava/lang/Object;T9:Ljava/lang/Object;T10:Ljava/lang/Object;T11:Ljava/lang/Object;T12:Ljava/lang/Object;T13:Ljava/lang/Object;T14:Ljava/lang/Object;T15:Ljava/lang/Object;T16:Ljava/lang/Object;T17:Ljava/lang/Object;T18:Ljava/lang/Object;T19:Ljava/lang/Object;T20:Ljava/lang/Object;T21:Ljava/lang/Object;T22:Ljava/lang/Object;>(Lscala/Function22<TT1;TT2;TT3;TT4;TT5;TT6;TT7;TT8;TT9;TT10;TT11;TT12;TT13;TT14;TT15;TT16;TT17;TT18;TT19;TT20;TT21;TT22;Lorg/sireum/contract$Contract$SubProof;>;)Lorg/sireum/contract$Contract$Let;
    MethodParameters:
      Name                           Flags
      body                           final

  public <T extends java.lang.Object> T In(T);
    descriptor: (Ljava/lang/Object;)Ljava/lang/Object;
    flags: (0x0001) ACC_PUBLIC
    Code:
      stack=2, locals=2, args_size=2
         0: aload_0
         1: aload_1
         2: invokestatic  #453                // InterfaceMethod org/sireum/contract.In$:(Lorg/sireum/contract;Ljava/lang/Object;)Ljava/lang/Object;
         5: areturn
      LineNumberTable:
        line 28: 0
      LocalVariableTable:
        Start  Length  Slot  Name   Signature
            0       6     0  this   Lorg/sireum/package$;
            0       6     1     v   Ljava/lang/Object;
    Signature: #448                         // <T:Ljava/lang/Object;>(TT;)TT;
    MethodParameters:
      Name                           Flags
      v                              final

  public <T extends java.lang.Object> T Old(T);
    descriptor: (Ljava/lang/Object;)Ljava/lang/Object;
    flags: (0x0001) ACC_PUBLIC
    Code:
      stack=2, locals=2, args_size=2
         0: aload_0
         1: aload_1
         2: invokestatic  #457                // InterfaceMethod org/sireum/contract.Old$:(Lorg/sireum/contract;Ljava/lang/Object;)Ljava/lang/Object;
         5: areturn
      LineNumberTable:
        line 28: 0
      LocalVariableTable:
        Start  Length  Slot  Name   Signature
            0       6     0  this   Lorg/sireum/package$;
            0       6     1     v   Ljava/lang/Object;
    Signature: #448                         // <T:Ljava/lang/Object;>(TT;)TT;
    MethodParameters:
      Name                           Flags
      v                              final

  public <T extends java.lang.Object> T At(java.lang.String, T);
    descriptor: (Ljava/lang/String;Ljava/lang/Object;)Ljava/lang/Object;
    flags: (0x0001) ACC_PUBLIC
    Code:
      stack=3, locals=3, args_size=3
         0: aload_0
         1: aload_1
         2: aload_2
         3: invokestatic  #465                // InterfaceMethod org/sireum/contract.At$:(Lorg/sireum/contract;Ljava/lang/String;Ljava/lang/Object;)Ljava/lang/Object;
         6: areturn
      LineNumberTable:
        line 28: 0
      LocalVariableTable:
        Start  Length  Slot  Name   Signature
            0       7     0  this   Lorg/sireum/package$;
            0       7     1 label   Ljava/lang/String;
            0       7     2     v   Ljava/lang/Object;
    Signature: #460                         // <T:Ljava/lang/Object;>(Ljava/lang/String;TT;)TT;
    MethodParameters:
      Name                           Flags
      label                          final
      v                              final

  public <T extends java.lang.Object> T At(org.sireum.Z, T);
    descriptor: (Lorg/sireum/Z;Ljava/lang/Object;)Ljava/lang/Object;
    flags: (0x0001) ACC_PUBLIC
    Code:
      stack=3, locals=3, args_size=3
         0: aload_0
         1: aload_1
         2: aload_2
         3: invokestatic  #471                // InterfaceMethod org/sireum/contract.At$:(Lorg/sireum/contract;Lorg/sireum/Z;Ljava/lang/Object;)Ljava/lang/Object;
         6: areturn
      LineNumberTable:
        line 28: 0
      LocalVariableTable:
        Start  Length  Slot  Name   Signature
            0       7     0  this   Lorg/sireum/package$;
            0       7     1     n   Lorg/sireum/Z;
            0       7     2     v   Ljava/lang/Object;
    Signature: #467                         // <T:Ljava/lang/Object;>(Lorg/sireum/Z;TT;)TT;
    MethodParameters:
      Name                           Flags
      n                              final
      v                              final

  public <T extends java.lang.Object> T Res();
    descriptor: ()Ljava/lang/Object;
    flags: (0x0001) ACC_PUBLIC
    Code:
      stack=1, locals=1, args_size=1
         0: aload_0
         1: invokestatic  #478                // InterfaceMethod org/sireum/contract.Res$:(Lorg/sireum/contract;)Ljava/lang/Object;
         4: areturn
      LineNumberTable:
        line 28: 0
      LocalVariableTable:
        Start  Length  Slot  Name   Signature
            0       5     0  this   Lorg/sireum/package$;
    Signature: #474                         // <T:Ljava/lang/Object;>()TT;

  public <T extends org.sireum.ZLike<T>> T Idx(java.lang.Object);
    descriptor: (Ljava/lang/Object;)Lorg/sireum/ZLike;
    flags: (0x0001) ACC_PUBLIC
    Code:
      stack=2, locals=2, args_size=2
         0: aload_0
         1: aload_1
         2: invokestatic  #485                // InterfaceMethod org/sireum/contract.Idx$:(Lorg/sireum/contract;Ljava/lang/Object;)Lorg/sireum/ZLike;
         5: areturn
      LineNumberTable:
        line 28: 0
      LocalVariableTable:
        Start  Length  Slot  Name   Signature
            0       6     0  this   Lorg/sireum/package$;
            0       6     1     v   Ljava/lang/Object;
    Signature: #481                         // <T::Lorg/sireum/ZLike<TT;>;>(Ljava/lang/Object;)TT;
    MethodParameters:
      Name                           Flags
      v                              final

  public org.sireum.contract$Contract$Sequent $bar$minus(boolean);
    descriptor: (Z)Lorg/sireum/contract$Contract$Sequent;
    flags: (0x0001) ACC_PUBLIC
    Code:
      stack=2, locals=2, args_size=2
         0: aload_0
         1: iload_1
         2: invokestatic  #492                // InterfaceMethod org/sireum/contract.$bar$minus$:(Lorg/sireum/contract;Z)Lorg/sireum/contract$Contract$Sequent;
         5: areturn
      LineNumberTable:
        line 28: 0
      LocalVariableTable:
        Start  Length  Slot  Name   Signature
            0       6     0  this   Lorg/sireum/package$;
            0       6     1 conclusion   Z
    MethodParameters:
      Name                           Flags
      conclusion                     final

  public org.sireum.contract$Contract$Sequent $u22A2(boolean);
    descriptor: (Z)Lorg/sireum/contract$Contract$Sequent;
    flags: (0x0001) ACC_PUBLIC
    Code:
      stack=2, locals=2, args_size=2
         0: aload_0
         1: iload_1
         2: invokestatic  #496                // InterfaceMethod org/sireum/contract.$u22A2$:(Lorg/sireum/contract;Z)Lorg/sireum/contract$Contract$Sequent;
         5: areturn
      LineNumberTable:
        line 28: 0
      LocalVariableTable:
        Start  Length  Slot  Name   Signature
            0       6     0  this   Lorg/sireum/package$;
            0       6     1 conclusion   Z
    MethodParameters:
      Name                           Flags
      conclusion                     final

  public org.sireum.contract$Contract$StepBuilder $toStepBuilder(int);
    descriptor: (I)Lorg/sireum/contract$Contract$StepBuilder;
    flags: (0x0001) ACC_PUBLIC
    Code:
      stack=2, locals=2, args_size=2
         0: aload_0
         1: iload_1
         2: invokestatic  #503                // InterfaceMethod org/sireum/contract.$toStepBuilder$:(Lorg/sireum/contract;I)Lorg/sireum/contract$Contract$StepBuilder;
         5: areturn
      LineNumberTable:
        line 28: 0
      LocalVariableTable:
        Start  Length  Slot  Name   Signature
            0       6     0  this   Lorg/sireum/package$;
            0       6     1 stepNo   I
    MethodParameters:
      Name                           Flags
      stepNo                         final

  public org.sireum.contract$Contract$StepBuilder $toStepBuilder(org.sireum.Z);
    descriptor: (Lorg/sireum/Z;)Lorg/sireum/contract$Contract$StepBuilder;
    flags: (0x0001) ACC_PUBLIC
    Code:
      stack=2, locals=2, args_size=2
         0: aload_0
         1: aload_1
         2: invokestatic  #507                // InterfaceMethod org/sireum/contract.$toStepBuilder$:(Lorg/sireum/contract;Lorg/sireum/Z;)Lorg/sireum/contract$Contract$StepBuilder;
         5: areturn
      LineNumberTable:
        line 28: 0
      LocalVariableTable:
        Start  Length  Slot  Name   Signature
            0       6     0  this   Lorg/sireum/package$;
            0       6     1 stepNo   Lorg/sireum/Z;
    MethodParameters:
      Name                           Flags
      stepNo                         final

  public org.sireum.contract$Contract$Justification $toJustification(java.lang.String);
    descriptor: (Ljava/lang/String;)Lorg/sireum/contract$Contract$Justification;
    flags: (0x0001) ACC_PUBLIC
    Code:
      stack=2, locals=2, args_size=2
         0: aload_0
         1: aload_1
         2: invokestatic  #513                // InterfaceMethod org/sireum/contract.$toJustification$:(Lorg/sireum/contract;Ljava/lang/String;)Lorg/sireum/contract$Contract$Justification;
         5: areturn
      LineNumberTable:
        line 28: 0
      LocalVariableTable:
        Start  Length  Slot  Name   Signature
            0       6     0  this   Lorg/sireum/package$;
            0       6     1  name   Ljava/lang/String;
    MethodParameters:
      Name                           Flags
      name                           final

  public boolean $toB(org.sireum.contract$Contract$StateCont);
    descriptor: (Lorg/sireum/contract$Contract$StateCont;)Z
    flags: (0x0001) ACC_PUBLIC
    Code:
      stack=2, locals=2, args_size=2
         0: aload_0
         1: aload_1
         2: invokestatic  #520                // InterfaceMethod org/sireum/contract.$toB$:(Lorg/sireum/contract;Lorg/sireum/contract$Contract$StateCont;)Z
         5: ireturn
      LineNumberTable:
        line 28: 0
      LocalVariableTable:
        Start  Length  Slot  Name   Signature
            0       6     0  this   Lorg/sireum/package$;
            0       6     1 state   Lorg/sireum/contract$Contract$StateCont;
    MethodParameters:
      Name                           Flags
      state                          final

  public org.sireum.contract$Contract$SequentBuilder $toSequent(boolean);
    descriptor: (Z)Lorg/sireum/contract$Contract$SequentBuilder;
    flags: (0x0001) ACC_PUBLIC
    Code:
      stack=2, locals=2, args_size=2
         0: aload_0
         1: iload_1
         2: invokestatic  #528                // InterfaceMethod org/sireum/contract.$toSequent$:(Lorg/sireum/contract;Z)Lorg/sireum/contract$Contract$SequentBuilder;
         5: areturn
      LineNumberTable:
        line 28: 0
      LocalVariableTable:
        Start  Length  Slot  Name   Signature
            0       6     0  this   Lorg/sireum/package$;
            0       6     1    bs   Z
    MethodParameters:
      Name                           Flags
      bs                             final

  public org.sireum.contract$Contract$SequentBuilder $toSequent(scala.Tuple2<org.sireum.B, org.sireum.B>);
    descriptor: (Lscala/Tuple2;)Lorg/sireum/contract$Contract$SequentBuilder;
    flags: (0x0001) ACC_PUBLIC
    Code:
      stack=2, locals=2, args_size=2
         0: aload_0
         1: aload_1
         2: invokestatic  #533                // InterfaceMethod org/sireum/contract.$toSequent$:(Lorg/sireum/contract;Lscala/Tuple2;)Lorg/sireum/contract$Contract$SequentBuilder;
         5: areturn
      LineNumberTable:
        line 28: 0
      LocalVariableTable:
        Start  Length  Slot  Name   Signature
            0       6     0  this   Lorg/sireum/package$;
            0       6     1    bs   Lscala/Tuple2;
    Signature: #530                         // (Lscala/Tuple2<Lorg/sireum/B;Lorg/sireum/B;>;)Lorg/sireum/contract$Contract$SequentBuilder;
    MethodParameters:
      Name                           Flags
      bs                             final

  public org.sireum.contract$Contract$SequentBuilder $toSequent(scala.Tuple3<org.sireum.B, org.sireum.B, org.sireum.B>);
    descriptor: (Lscala/Tuple3;)Lorg/sireum/contract$Contract$SequentBuilder;
    flags: (0x0001) ACC_PUBLIC
    Code:
      stack=2, locals=2, args_size=2
         0: aload_0
         1: aload_1
         2: invokestatic  #539                // InterfaceMethod org/sireum/contract.$toSequent$:(Lorg/sireum/contract;Lscala/Tuple3;)Lorg/sireum/contract$Contract$SequentBuilder;
         5: areturn
      LineNumberTable:
        line 28: 0
      LocalVariableTable:
        Start  Length  Slot  Name   Signature
            0       6     0  this   Lorg/sireum/package$;
            0       6     1    bs   Lscala/Tuple3;
    Signature: #536                         // (Lscala/Tuple3<Lorg/sireum/B;Lorg/sireum/B;Lorg/sireum/B;>;)Lorg/sireum/contract$Contract$SequentBuilder;
    MethodParameters:
      Name                           Flags
      bs                             final

  public org.sireum.contract$Contract$SequentBuilder $toSequent(scala.Tuple4<org.sireum.B, org.sireum.B, org.sireum.B, org.sireum.B>);
    descriptor: (Lscala/Tuple4;)Lorg/sireum/contract$Contract$SequentBuilder;
    flags: (0x0001) ACC_PUBLIC
    Code:
      stack=2, locals=2, args_size=2
         0: aload_0
         1: aload_1
         2: invokestatic  #545                // InterfaceMethod org/sireum/contract.$toSequent$:(Lorg/sireum/contract;Lscala/Tuple4;)Lorg/sireum/contract$Contract$SequentBuilder;
         5: areturn
      LineNumberTable:
        line 28: 0
      LocalVariableTable:
        Start  Length  Slot  Name   Signature
            0       6     0  this   Lorg/sireum/package$;
            0       6     1    bs   Lscala/Tuple4;
    Signature: #542                         // (Lscala/Tuple4<Lorg/sireum/B;Lorg/sireum/B;Lorg/sireum/B;Lorg/sireum/B;>;)Lorg/sireum/contract$Contract$SequentBuilder;
    MethodParameters:
      Name                           Flags
      bs                             final

  public org.sireum.contract$Contract$SequentBuilder $toSequent(scala.Tuple5<org.sireum.B, org.sireum.B, org.sireum.B, org.sireum.B, org.sireum.B>);
    descriptor: (Lscala/Tuple5;)Lorg/sireum/contract$Contract$SequentBuilder;
    flags: (0x0001) ACC_PUBLIC
    Code:
      stack=2, locals=2, args_size=2
         0: aload_0
         1: aload_1
         2: invokestatic  #551                // InterfaceMethod org/sireum/contract.$toSequent$:(Lorg/sireum/contract;Lscala/Tuple5;)Lorg/sireum/contract$Contract$SequentBuilder;
         5: areturn
      LineNumberTable:
        line 28: 0
      LocalVariableTable:
        Start  Length  Slot  Name   Signature
            0       6     0  this   Lorg/sireum/package$;
            0       6     1    bs   Lscala/Tuple5;
    Signature: #548                         // (Lscala/Tuple5<Lorg/sireum/B;Lorg/sireum/B;Lorg/sireum/B;Lorg/sireum/B;Lorg/sireum/B;>;)Lorg/sireum/contract$Contract$SequentBuilder;
    MethodParameters:
      Name                           Flags
      bs                             final

  public org.sireum.contract$Contract$SequentBuilder $toSequent(scala.Tuple6<org.sireum.B, org.sireum.B, org.sireum.B, org.sireum.B, org.sireum.B, org.sireum.B>);
    descriptor: (Lscala/Tuple6;)Lorg/sireum/contract$Contract$SequentBuilder;
    flags: (0x0001) ACC_PUBLIC
    Code:
      stack=2, locals=2, args_size=2
         0: aload_0
         1: aload_1
         2: invokestatic  #557                // InterfaceMethod org/sireum/contract.$toSequent$:(Lorg/sireum/contract;Lscala/Tuple6;)Lorg/sireum/contract$Contract$SequentBuilder;
         5: areturn
      LineNumberTable:
        line 28: 0
      LocalVariableTable:
        Start  Length  Slot  Name   Signature
            0       6     0  this   Lorg/sireum/package$;
            0       6     1    bs   Lscala/Tuple6;
    Signature: #554                         // (Lscala/Tuple6<Lorg/sireum/B;Lorg/sireum/B;Lorg/sireum/B;Lorg/sireum/B;Lorg/sireum/B;Lorg/sireum/B;>;)Lorg/sireum/contract$Contract$SequentBuilder;
    MethodParameters:
      Name                           Flags
      bs                             final

  public org.sireum.contract$Contract$SequentBuilder $toSequent(scala.Tuple7<org.sireum.B, org.sireum.B, org.sireum.B, org.sireum.B, org.sireum.B, org.sireum.B, org.sireum.B>);
    descriptor: (Lscala/Tuple7;)Lorg/sireum/contract$Contract$SequentBuilder;
    flags: (0x0001) ACC_PUBLIC
    Code:
      stack=2, locals=2, args_size=2
         0: aload_0
         1: aload_1
         2: invokestatic  #563                // InterfaceMethod org/sireum/contract.$toSequent$:(Lorg/sireum/contract;Lscala/Tuple7;)Lorg/sireum/contract$Contract$SequentBuilder;
         5: areturn
      LineNumberTable:
        line 28: 0
      LocalVariableTable:
        Start  Length  Slot  Name   Signature
            0       6     0  this   Lorg/sireum/package$;
            0       6     1    bs   Lscala/Tuple7;
    Signature: #560                         // (Lscala/Tuple7<Lorg/sireum/B;Lorg/sireum/B;Lorg/sireum/B;Lorg/sireum/B;Lorg/sireum/B;Lorg/sireum/B;Lorg/sireum/B;>;)Lorg/sireum/contract$Contract$SequentBuilder;
    MethodParameters:
      Name                           Flags
      bs                             final

  public org.sireum.contract$Contract$SequentBuilder $toSequent(scala.Tuple8<org.sireum.B, org.sireum.B, org.sireum.B, org.sireum.B, org.sireum.B, org.sireum.B, org.sireum.B, org.sireum.B>);
    descriptor: (Lscala/Tuple8;)Lorg/sireum/contract$Contract$SequentBuilder;
    flags: (0x0001) ACC_PUBLIC
    Code:
      stack=2, locals=2, args_size=2
         0: aload_0
         1: aload_1
         2: invokestatic  #569                // InterfaceMethod org/sireum/contract.$toSequent$:(Lorg/sireum/contract;Lscala/Tuple8;)Lorg/sireum/contract$Contract$SequentBuilder;
         5: areturn
      LineNumberTable:
        line 28: 0
      LocalVariableTable:
        Start  Length  Slot  Name   Signature
            0       6     0  this   Lorg/sireum/package$;
            0       6     1    bs   Lscala/Tuple8;
    Signature: #566                         // (Lscala/Tuple8<Lorg/sireum/B;Lorg/sireum/B;Lorg/sireum/B;Lorg/sireum/B;Lorg/sireum/B;Lorg/sireum/B;Lorg/sireum/B;Lorg/sireum/B;>;)Lorg/sireum/contract$Contract$SequentBuilder;
    MethodParameters:
      Name                           Flags
      bs                             final

  public org.sireum.contract$Contract$SequentBuilder $toSequent(scala.Tuple9<org.sireum.B, org.sireum.B, org.sireum.B, org.sireum.B, org.sireum.B, org.sireum.B, org.sireum.B, org.sireum.B, org.sireum.B>);
    descriptor: (Lscala/Tuple9;)Lorg/sireum/contract$Contract$SequentBuilder;
    flags: (0x0001) ACC_PUBLIC
    Code:
      stack=2, locals=2, args_size=2
         0: aload_0
         1: aload_1
         2: invokestatic  #575                // InterfaceMethod org/sireum/contract.$toSequent$:(Lorg/sireum/contract;Lscala/Tuple9;)Lorg/sireum/contract$Contract$SequentBuilder;
         5: areturn
      LineNumberTable:
        line 28: 0
      LocalVariableTable:
        Start  Length  Slot  Name   Signature
            0       6     0  this   Lorg/sireum/package$;
            0       6     1    bs   Lscala/Tuple9;
    Signature: #572                         // (Lscala/Tuple9<Lorg/sireum/B;Lorg/sireum/B;Lorg/sireum/B;Lorg/sireum/B;Lorg/sireum/B;Lorg/sireum/B;Lorg/sireum/B;Lorg/sireum/B;Lorg/sireum/B;>;)Lorg/sireum/contract$Contract$SequentBuilder;
    MethodParameters:
      Name                           Flags
      bs                             final

  public org.sireum.contract$Contract$SequentBuilder $toSequent(scala.Tuple10<org.sireum.B, org.sireum.B, org.sireum.B, org.sireum.B, org.sireum.B, org.sireum.B, org.sireum.B, org.sireum.B, org.sireum.B, org.sireum.B>);
    descriptor: (Lscala/Tuple10;)Lorg/sireum/contract$Contract$SequentBuilder;
    flags: (0x0001) ACC_PUBLIC
    Code:
      stack=2, locals=2, args_size=2
         0: aload_0
         1: aload_1
         2: invokestatic  #581                // InterfaceMethod org/sireum/contract.$toSequent$:(Lorg/sireum/contract;Lscala/Tuple10;)Lorg/sireum/contract$Contract$SequentBuilder;
         5: areturn
      LineNumberTable:
        line 28: 0
      LocalVariableTable:
        Start  Length  Slot  Name   Signature
            0       6     0  this   Lorg/sireum/package$;
            0       6     1    bs   Lscala/Tuple10;
    Signature: #578                         // (Lscala/Tuple10<Lorg/sireum/B;Lorg/sireum/B;Lorg/sireum/B;Lorg/sireum/B;Lorg/sireum/B;Lorg/sireum/B;Lorg/sireum/B;Lorg/sireum/B;Lorg/sireum/B;Lorg/sireum/B;>;)Lorg/sireum/contract$Contract$SequentBuilder;
    MethodParameters:
      Name                           Flags
      bs                             final

  public org.sireum.contract$Contract$SequentBuilder $toSequent(scala.Tuple11<org.sireum.B, org.sireum.B, org.sireum.B, org.sireum.B, org.sireum.B, org.sireum.B, org.sireum.B, org.sireum.B, org.sireum.B, org.sireum.B, org.sireum.B>);
    descriptor: (Lscala/Tuple11;)Lorg/sireum/contract$Contract$SequentBuilder;
    flags: (0x0001) ACC_PUBLIC
    Code:
      stack=2, locals=2, args_size=2
         0: aload_0
         1: aload_1
         2: invokestatic  #587                // InterfaceMethod org/sireum/contract.$toSequent$:(Lorg/sireum/contract;Lscala/Tuple11;)Lorg/sireum/contract$Contract$SequentBuilder;
         5: areturn
      LineNumberTable:
        line 28: 0
      LocalVariableTable:
        Start  Length  Slot  Name   Signature
            0       6     0  this   Lorg/sireum/package$;
            0       6     1    bs   Lscala/Tuple11;
    Signature: #584                         // (Lscala/Tuple11<Lorg/sireum/B;Lorg/sireum/B;Lorg/sireum/B;Lorg/sireum/B;Lorg/sireum/B;Lorg/sireum/B;Lorg/sireum/B;Lorg/sireum/B;Lorg/sireum/B;Lorg/sireum/B;Lorg/sireum/B;>;)Lorg/sireum/contract$Contract$SequentBuilder;
    MethodParameters:
      Name                           Flags
      bs                             final

  public org.sireum.contract$Contract$SequentBuilder $toSequent(scala.Tuple12<org.sireum.B, org.sireum.B, org.sireum.B, org.sireum.B, org.sireum.B, org.sireum.B, org.sireum.B, org.sireum.B, org.sireum.B, org.sireum.B, org.sireum.B, org.sireum.B>);
    descriptor: (Lscala/Tuple12;)Lorg/sireum/contract$Contract$SequentBuilder;
    flags: (0x0001) ACC_PUBLIC
    Code:
      stack=2, locals=2, args_size=2
         0: aload_0
         1: aload_1
         2: invokestatic  #593                // InterfaceMethod org/sireum/contract.$toSequent$:(Lorg/sireum/contract;Lscala/Tuple12;)Lorg/sireum/contract$Contract$SequentBuilder;
         5: areturn
      LineNumberTable:
        line 28: 0
      LocalVariableTable:
        Start  Length  Slot  Name   Signature
            0       6     0  this   Lorg/sireum/package$;
            0       6     1    bs   Lscala/Tuple12;
    Signature: #590                         // (Lscala/Tuple12<Lorg/sireum/B;Lorg/sireum/B;Lorg/sireum/B;Lorg/sireum/B;Lorg/sireum/B;Lorg/sireum/B;Lorg/sireum/B;Lorg/sireum/B;Lorg/sireum/B;Lorg/sireum/B;Lorg/sireum/B;Lorg/sireum/B;>;)Lorg/sireum/contract$Contract$SequentBuilder;
    MethodParameters:
      Name                           Flags
      bs                             final

  public org.sireum.contract$Contract$SequentBuilder $toSequent(scala.Tuple13<org.sireum.B, org.sireum.B, org.sireum.B, org.sireum.B, org.sireum.B, org.sireum.B, org.sireum.B, org.sireum.B, org.sireum.B, org.sireum.B, org.sireum.B, org.sireum.B, org.sireum.B>);
    descriptor: (Lscala/Tuple13;)Lorg/sireum/contract$Contract$SequentBuilder;
    flags: (0x0001) ACC_PUBLIC
    Code:
      stack=2, locals=2, args_size=2
         0: aload_0
         1: aload_1
         2: invokestatic  #599                // InterfaceMethod org/sireum/contract.$toSequent$:(Lorg/sireum/contract;Lscala/Tuple13;)Lorg/sireum/contract$Contract$SequentBuilder;
         5: areturn
      LineNumberTable:
        line 28: 0
      LocalVariableTable:
        Start  Length  Slot  Name   Signature
            0       6     0  this   Lorg/sireum/package$;
            0       6     1    bs   Lscala/Tuple13;
    Signature: #596                         // (Lscala/Tuple13<Lorg/sireum/B;Lorg/sireum/B;Lorg/sireum/B;Lorg/sireum/B;Lorg/sireum/B;Lorg/sireum/B;Lorg/sireum/B;Lorg/sireum/B;Lorg/sireum/B;Lorg/sireum/B;Lorg/sireum/B;Lorg/sireum/B;Lorg/sireum/B;>;)Lorg/sireum/contract$Contract$SequentBuilder;
    MethodParameters:
      Name                           Flags
      bs                             final

  public org.sireum.contract$Contract$SequentBuilder $toSequent(scala.Tuple14<org.sireum.B, org.sireum.B, org.sireum.B, org.sireum.B, org.sireum.B, org.sireum.B, org.sireum.B, org.sireum.B, org.sireum.B, org.sireum.B, org.sireum.B, org.sireum.B, org.sireum.B, org.sireum.B>);
    descriptor: (Lscala/Tuple14;)Lorg/sireum/contract$Contract$SequentBuilder;
    flags: (0x0001) ACC_PUBLIC
    Code:
      stack=2, locals=2, args_size=2
         0: aload_0
         1: aload_1
         2: invokestatic  #605                // InterfaceMethod org/sireum/contract.$toSequent$:(Lorg/sireum/contract;Lscala/Tuple14;)Lorg/sireum/contract$Contract$SequentBuilder;
         5: areturn
      LineNumberTable:
        line 28: 0
      LocalVariableTable:
        Start  Length  Slot  Name   Signature
            0       6     0  this   Lorg/sireum/package$;
            0       6     1    bs   Lscala/Tuple14;
    Signature: #602                         // (Lscala/Tuple14<Lorg/sireum/B;Lorg/sireum/B;Lorg/sireum/B;Lorg/sireum/B;Lorg/sireum/B;Lorg/sireum/B;Lorg/sireum/B;Lorg/sireum/B;Lorg/sireum/B;Lorg/sireum/B;Lorg/sireum/B;Lorg/sireum/B;Lorg/sireum/B;Lorg/sireum/B;>;)Lorg/sireum/contract$Contract$SequentBuilder;
    MethodParameters:
      Name                           Flags
      bs                             final

  public org.sireum.contract$Contract$SequentBuilder $toSequent(scala.Tuple15<org.sireum.B, org.sireum.B, org.sireum.B, org.sireum.B, org.sireum.B, org.sireum.B, org.sireum.B, org.sireum.B, org.sireum.B, org.sireum.B, org.sireum.B, org.sireum.B, org.sireum.B, org.sireum.B, org.sireum.B>);
    descriptor: (Lscala/Tuple15;)Lorg/sireum/contract$Contract$SequentBuilder;
    flags: (0x0001) ACC_PUBLIC
    Code:
      stack=2, locals=2, args_size=2
         0: aload_0
         1: aload_1
         2: invokestatic  #611                // InterfaceMethod org/sireum/contract.$toSequent$:(Lorg/sireum/contract;Lscala/Tuple15;)Lorg/sireum/contract$Contract$SequentBuilder;
         5: areturn
      LineNumberTable:
        line 28: 0
      LocalVariableTable:
        Start  Length  Slot  Name   Signature
            0       6     0  this   Lorg/sireum/package$;
            0       6     1    bs   Lscala/Tuple15;
    Signature: #608                         // (Lscala/Tuple15<Lorg/sireum/B;Lorg/sireum/B;Lorg/sireum/B;Lorg/sireum/B;Lorg/sireum/B;Lorg/sireum/B;Lorg/sireum/B;Lorg/sireum/B;Lorg/sireum/B;Lorg/sireum/B;Lorg/sireum/B;Lorg/sireum/B;Lorg/sireum/B;Lorg/sireum/B;Lorg/sireum/B;>;)Lorg/sireum/contract$Contract$SequentBuilder;
    MethodParameters:
      Name                           Flags
      bs                             final

  public org.sireum.contract$Contract$SequentBuilder $toSequent(scala.Tuple16<org.sireum.B, org.sireum.B, org.sireum.B, org.sireum.B, org.sireum.B, org.sireum.B, org.sireum.B, org.sireum.B, org.sireum.B, org.sireum.B, org.sireum.B, org.sireum.B, org.sireum.B, org.sireum.B, org.sireum.B, org.sireum.B>);
    descriptor: (Lscala/Tuple16;)Lorg/sireum/contract$Contract$SequentBuilder;
    flags: (0x0001) ACC_PUBLIC
    Code:
      stack=2, locals=2, args_size=2
         0: aload_0
         1: aload_1
         2: invokestatic  #617                // InterfaceMethod org/sireum/contract.$toSequent$:(Lorg/sireum/contract;Lscala/Tuple16;)Lorg/sireum/contract$Contract$SequentBuilder;
         5: areturn
      LineNumberTable:
        line 28: 0
      LocalVariableTable:
        Start  Length  Slot  Name   Signature
            0       6     0  this   Lorg/sireum/package$;
            0       6     1    bs   Lscala/Tuple16;
    Signature: #614                         // (Lscala/Tuple16<Lorg/sireum/B;Lorg/sireum/B;Lorg/sireum/B;Lorg/sireum/B;Lorg/sireum/B;Lorg/sireum/B;Lorg/sireum/B;Lorg/sireum/B;Lorg/sireum/B;Lorg/sireum/B;Lorg/sireum/B;Lorg/sireum/B;Lorg/sireum/B;Lorg/sireum/B;Lorg/sireum/B;Lorg/sireum/B;>;)Lorg/sireum/contract$Contract$SequentBuilder;
    MethodParameters:
      Name                           Flags
      bs                             final

  public org.sireum.contract$Contract$SequentBuilder $toSequent(scala.Tuple17<org.sireum.B, org.sireum.B, org.sireum.B, org.sireum.B, org.sireum.B, org.sireum.B, org.sireum.B, org.sireum.B, org.sireum.B, org.sireum.B, org.sireum.B, org.sireum.B, org.sireum.B, org.sireum.B, org.sireum.B, org.sireum.B, org.sireum.B>);
    descriptor: (Lscala/Tuple17;)Lorg/sireum/contract$Contract$SequentBuilder;
    flags: (0x0001) ACC_PUBLIC
    Code:
      stack=2, locals=2, args_size=2
         0: aload_0
         1: aload_1
         2: invokestatic  #623                // InterfaceMethod org/sireum/contract.$toSequent$:(Lorg/sireum/contract;Lscala/Tuple17;)Lorg/sireum/contract$Contract$SequentBuilder;
         5: areturn
      LineNumberTable:
        line 28: 0
      LocalVariableTable:
        Start  Length  Slot  Name   Signature
            0       6     0  this   Lorg/sireum/package$;
            0       6     1    bs   Lscala/Tuple17;
    Signature: #620                         // (Lscala/Tuple17<Lorg/sireum/B;Lorg/sireum/B;Lorg/sireum/B;Lorg/sireum/B;Lorg/sireum/B;Lorg/sireum/B;Lorg/sireum/B;Lorg/sireum/B;Lorg/sireum/B;Lorg/sireum/B;Lorg/sireum/B;Lorg/sireum/B;Lorg/sireum/B;Lorg/sireum/B;Lorg/sireum/B;Lorg/sireum/B;Lorg/sireum/B;>;)Lorg/sireum/contract$Contract$SequentBuilder;
    MethodParameters:
      Name                           Flags
      bs                             final

  public org.sireum.contract$Contract$SequentBuilder $toSequent(scala.Tuple18<org.sireum.B, org.sireum.B, org.sireum.B, org.sireum.B, org.sireum.B, org.sireum.B, org.sireum.B, org.sireum.B, org.sireum.B, org.sireum.B, org.sireum.B, org.sireum.B, org.sireum.B, org.sireum.B, org.sireum.B, org.sireum.B, org.sireum.B, org.sireum.B>);
    descriptor: (Lscala/Tuple18;)Lorg/sireum/contract$Contract$SequentBuilder;
    flags: (0x0001) ACC_PUBLIC
    Code:
      stack=2, locals=2, args_size=2
         0: aload_0
         1: aload_1
         2: invokestatic  #629                // InterfaceMethod org/sireum/contract.$toSequent$:(Lorg/sireum/contract;Lscala/Tuple18;)Lorg/sireum/contract$Contract$SequentBuilder;
         5: areturn
      LineNumberTable:
        line 28: 0
      LocalVariableTable:
        Start  Length  Slot  Name   Signature
            0       6     0  this   Lorg/sireum/package$;
            0       6     1    bs   Lscala/Tuple18;
    Signature: #626                         // (Lscala/Tuple18<Lorg/sireum/B;Lorg/sireum/B;Lorg/sireum/B;Lorg/sireum/B;Lorg/sireum/B;Lorg/sireum/B;Lorg/sireum/B;Lorg/sireum/B;Lorg/sireum/B;Lorg/sireum/B;Lorg/sireum/B;Lorg/sireum/B;Lorg/sireum/B;Lorg/sireum/B;Lorg/sireum/B;Lorg/sireum/B;Lorg/sireum/B;Lorg/sireum/B;>;)Lorg/sireum/contract$Contract$SequentBuilder;
    MethodParameters:
      Name                           Flags
      bs                             final

  public org.sireum.contract$Contract$SequentBuilder $toSequent(scala.Tuple19<org.sireum.B, org.sireum.B, org.sireum.B, org.sireum.B, org.sireum.B, org.sireum.B, org.sireum.B, org.sireum.B, org.sireum.B, org.sireum.B, org.sireum.B, org.sireum.B, org.sireum.B, org.sireum.B, org.sireum.B, org.sireum.B, org.sireum.B, org.sireum.B, org.sireum.B>);
    descriptor: (Lscala/Tuple19;)Lorg/sireum/contract$Contract$SequentBuilder;
    flags: (0x0001) ACC_PUBLIC
    Code:
      stack=2, locals=2, args_size=2
         0: aload_0
         1: aload_1
         2: invokestatic  #635                // InterfaceMethod org/sireum/contract.$toSequent$:(Lorg/sireum/contract;Lscala/Tuple19;)Lorg/sireum/contract$Contract$SequentBuilder;
         5: areturn
      LineNumberTable:
        line 28: 0
      LocalVariableTable:
        Start  Length  Slot  Name   Signature
            0       6     0  this   Lorg/sireum/package$;
            0       6     1    bs   Lscala/Tuple19;
    Signature: #632                         // (Lscala/Tuple19<Lorg/sireum/B;Lorg/sireum/B;Lorg/sireum/B;Lorg/sireum/B;Lorg/sireum/B;Lorg/sireum/B;Lorg/sireum/B;Lorg/sireum/B;Lorg/sireum/B;Lorg/sireum/B;Lorg/sireum/B;Lorg/sireum/B;Lorg/sireum/B;Lorg/sireum/B;Lorg/sireum/B;Lorg/sireum/B;Lorg/sireum/B;Lorg/sireum/B;Lorg/sireum/B;>;)Lorg/sireum/contract$Contract$SequentBuilder;
    MethodParameters:
      Name                           Flags
      bs                             final

  public org.sireum.contract$Contract$SequentBuilder $toSequent(scala.Tuple20<org.sireum.B, org.sireum.B, org.sireum.B, org.sireum.B, org.sireum.B, org.sireum.B, org.sireum.B, org.sireum.B, org.sireum.B, org.sireum.B, org.sireum.B, org.sireum.B, org.sireum.B, org.sireum.B, org.sireum.B, org.sireum.B, org.sireum.B, org.sireum.B, org.sireum.B, org.sireum.B>);
    descriptor: (Lscala/Tuple20;)Lorg/sireum/contract$Contract$SequentBuilder;
    flags: (0x0001) ACC_PUBLIC
    Code:
      stack=2, locals=2, args_size=2
         0: aload_0
         1: aload_1
         2: invokestatic  #641                // InterfaceMethod org/sireum/contract.$toSequent$:(Lorg/sireum/contract;Lscala/Tuple20;)Lorg/sireum/contract$Contract$SequentBuilder;
         5: areturn
      LineNumberTable:
        line 28: 0
      LocalVariableTable:
        Start  Length  Slot  Name   Signature
            0       6     0  this   Lorg/sireum/package$;
            0       6     1    bs   Lscala/Tuple20;
    Signature: #638                         // (Lscala/Tuple20<Lorg/sireum/B;Lorg/sireum/B;Lorg/sireum/B;Lorg/sireum/B;Lorg/sireum/B;Lorg/sireum/B;Lorg/sireum/B;Lorg/sireum/B;Lorg/sireum/B;Lorg/sireum/B;Lorg/sireum/B;Lorg/sireum/B;Lorg/sireum/B;Lorg/sireum/B;Lorg/sireum/B;Lorg/sireum/B;Lorg/sireum/B;Lorg/sireum/B;Lorg/sireum/B;Lorg/sireum/B;>;)Lorg/sireum/contract$Contract$SequentBuilder;
    MethodParameters:
      Name                           Flags
      bs                             final

  public org.sireum.contract$Contract$SequentBuilder $toSequent(scala.Tuple21<org.sireum.B, org.sireum.B, org.sireum.B, org.sireum.B, org.sireum.B, org.sireum.B, org.sireum.B, org.sireum.B, org.sireum.B, org.sireum.B, org.sireum.B, org.sireum.B, org.sireum.B, org.sireum.B, org.sireum.B, org.sireum.B, org.sireum.B, org.sireum.B, org.sireum.B, org.sireum.B, org.sireum.B>);
    descriptor: (Lscala/Tuple21;)Lorg/sireum/contract$Contract$SequentBuilder;
    flags: (0x0001) ACC_PUBLIC
    Code:
      stack=2, locals=2, args_size=2
         0: aload_0
         1: aload_1
         2: invokestatic  #647                // InterfaceMethod org/sireum/contract.$toSequent$:(Lorg/sireum/contract;Lscala/Tuple21;)Lorg/sireum/contract$Contract$SequentBuilder;
         5: areturn
      LineNumberTable:
        line 28: 0
      LocalVariableTable:
        Start  Length  Slot  Name   Signature
            0       6     0  this   Lorg/sireum/package$;
            0       6     1    bs   Lscala/Tuple21;
    Signature: #644                         // (Lscala/Tuple21<Lorg/sireum/B;Lorg/sireum/B;Lorg/sireum/B;Lorg/sireum/B;Lorg/sireum/B;Lorg/sireum/B;Lorg/sireum/B;Lorg/sireum/B;Lorg/sireum/B;Lorg/sireum/B;Lorg/sireum/B;Lorg/sireum/B;Lorg/sireum/B;Lorg/sireum/B;Lorg/sireum/B;Lorg/sireum/B;Lorg/sireum/B;Lorg/sireum/B;Lorg/sireum/B;Lorg/sireum/B;Lorg/sireum/B;>;)Lorg/sireum/contract$Contract$SequentBuilder;
    MethodParameters:
      Name                           Flags
      bs                             final

  public org.sireum.contract$Contract$SequentBuilder $toSequent(scala.Tuple22<org.sireum.B, org.sireum.B, org.sireum.B, org.sireum.B, org.sireum.B, org.sireum.B, org.sireum.B, org.sireum.B, org.sireum.B, org.sireum.B, org.sireum.B, org.sireum.B, org.sireum.B, org.sireum.B, org.sireum.B, org.sireum.B, org.sireum.B, org.sireum.B, org.sireum.B, org.sireum.B, org.sireum.B, org.sireum.B>);
    descriptor: (Lscala/Tuple22;)Lorg/sireum/contract$Contract$SequentBuilder;
    flags: (0x0001) ACC_PUBLIC
    Code:
      stack=2, locals=2, args_size=2
         0: aload_0
         1: aload_1
         2: invokestatic  #653                // InterfaceMethod org/sireum/contract.$toSequent$:(Lorg/sireum/contract;Lscala/Tuple22;)Lorg/sireum/contract$Contract$SequentBuilder;
         5: areturn
      LineNumberTable:
        line 28: 0
      LocalVariableTable:
        Start  Length  Slot  Name   Signature
            0       6     0  this   Lorg/sireum/package$;
            0       6     1    bs   Lscala/Tuple22;
    Signature: #650                         // (Lscala/Tuple22<Lorg/sireum/B;Lorg/sireum/B;Lorg/sireum/B;Lorg/sireum/B;Lorg/sireum/B;Lorg/sireum/B;Lorg/sireum/B;Lorg/sireum/B;Lorg/sireum/B;Lorg/sireum/B;Lorg/sireum/B;Lorg/sireum/B;Lorg/sireum/B;Lorg/sireum/B;Lorg/sireum/B;Lorg/sireum/B;Lorg/sireum/B;Lorg/sireum/B;Lorg/sireum/B;Lorg/sireum/B;Lorg/sireum/B;Lorg/sireum/B;>;)Lorg/sireum/contract$Contract$SequentBuilder;
    MethodParameters:
      Name                           Flags
      bs                             final

  public final org.sireum.Z randomInt();
    descriptor: ()Lorg/sireum/Z;
    flags: (0x0011) ACC_PUBLIC, ACC_FINAL
    Code:
      stack=1, locals=1, args_size=1
         0: aload_0
         1: invokestatic  #660                // InterfaceMethod org/sireum/$internal/PackageTrait.randomInt$:(Lorg/sireum/$internal/PackageTrait;)Lorg/sireum/Z;
         4: areturn
      LineNumberTable:
        line 28: 0
      LocalVariableTable:
        Start  Length  Slot  Name   Signature
            0       5     0  this   Lorg/sireum/package$;

  public final <I extends java.lang.Object> boolean seqIndexValidSize(org.sireum.Z);
    descriptor: (Lorg/sireum/Z;)Z
    flags: (0x0011) ACC_PUBLIC, ACC_FINAL
    Code:
      stack=2, locals=2, args_size=2
         0: aload_0
         1: aload_1
         2: invokestatic  #668                // InterfaceMethod org/sireum/$internal/PackageTrait.seqIndexValidSize$:(Lorg/sireum/$internal/PackageTrait;Lorg/sireum/Z;)Z
         5: ireturn
      LineNumberTable:
        line 28: 0
      LocalVariableTable:
        Start  Length  Slot  Name   Signature
            0       6     0  this   Lorg/sireum/package$;
            0       6     1  size   Lorg/sireum/Z;
    Signature: #663                         // <I:Ljava/lang/Object;>(Lorg/sireum/Z;)Z
    MethodParameters:
      Name                           Flags
      size                           final

  public final org.sireum.Z promptInt(java.lang.String);
    descriptor: (Ljava/lang/String;)Lorg/sireum/Z;
    flags: (0x0011) ACC_PUBLIC, ACC_FINAL
    Code:
      stack=2, locals=2, args_size=2
         0: aload_0
         1: aload_1
         2: invokestatic  #675                // InterfaceMethod org/sireum/$internal/PackageTrait.promptInt$:(Lorg/sireum/$internal/PackageTrait;Ljava/lang/String;)Lorg/sireum/Z;
         5: areturn
      LineNumberTable:
        line 28: 0
      LocalVariableTable:
        Start  Length  Slot  Name   Signature
            0       6     0  this   Lorg/sireum/package$;
            0       6     1   msg   Ljava/lang/String;
    MethodParameters:
      Name                           Flags
      msg                            final

  public final org.sireum.Z readInt();
    descriptor: ()Lorg/sireum/Z;
    flags: (0x0011) ACC_PUBLIC, ACC_FINAL
    Code:
      stack=1, locals=1, args_size=1
         0: aload_0
         1: invokestatic  #679                // InterfaceMethod org/sireum/$internal/PackageTrait.readInt$:(Lorg/sireum/$internal/PackageTrait;)Lorg/sireum/Z;
         4: areturn
      LineNumberTable:
        line 28: 0
      LocalVariableTable:
        Start  Length  Slot  Name   Signature
            0       5     0  this   Lorg/sireum/package$;

  public scala.runtime.Nothing$ halt(java.lang.Object);
    descriptor: (Ljava/lang/Object;)Lscala/runtime/Nothing$;
    flags: (0x0001) ACC_PUBLIC
    Code:
      stack=2, locals=2, args_size=2
         0: aload_0
         1: aload_1
         2: invokestatic  #685                // InterfaceMethod org/sireum/$internal/PackageTrait.halt$:(Lorg/sireum/$internal/PackageTrait;Ljava/lang/Object;)Lscala/runtime/Nothing$;
         5: areturn
      LineNumberTable:
        line 28: 0
      LocalVariableTable:
        Start  Length  Slot  Name   Signature
            0       6     0  this   Lorg/sireum/package$;
            0       6     1   msg   Ljava/lang/Object;
    MethodParameters:
      Name                           Flags
      msg                            final

  public final void cprintln(boolean, scala.collection.immutable.Seq<java.lang.Object>);
    descriptor: (ZLscala/collection/immutable/Seq;)V
    flags: (0x0011) ACC_PUBLIC, ACC_FINAL
    Code:
      stack=3, locals=3, args_size=3
         0: aload_0
         1: iload_1
         2: aload_2
         3: invokestatic  #694                // InterfaceMethod org/sireum/$internal/PackageTrait.cprintln$:(Lorg/sireum/$internal/PackageTrait;ZLscala/collection/immutable/Seq;)V
         6: return
      LineNumberTable:
        line 28: 0
      LocalVariableTable:
        Start  Length  Slot  Name   Signature
            0       7     0  this   Lorg/sireum/package$;
            0       7     1 isErr   Z
            0       7     2    as   Lscala/collection/immutable/Seq;
    Signature: #688                         // (ZLscala/collection/immutable/Seq<Ljava/lang/Object;>;)V
    MethodParameters:
      Name                           Flags
      isErr                          final
      as                             final

  public final void cprint(boolean, scala.collection.immutable.Seq<java.lang.Object>);
    descriptor: (ZLscala/collection/immutable/Seq;)V
    flags: (0x0011) ACC_PUBLIC, ACC_FINAL
    Code:
      stack=3, locals=3, args_size=3
         0: aload_0
         1: iload_1
         2: aload_2
         3: invokestatic  #698                // InterfaceMethod org/sireum/$internal/PackageTrait.cprint$:(Lorg/sireum/$internal/PackageTrait;ZLscala/collection/immutable/Seq;)V
         6: return
      LineNumberTable:
        line 28: 0
      LocalVariableTable:
        Start  Length  Slot  Name   Signature
            0       7     0  this   Lorg/sireum/package$;
            0       7     1 isErr   Z
            0       7     2    as   Lscala/collection/immutable/Seq;
    Signature: #688                         // (ZLscala/collection/immutable/Seq<Ljava/lang/Object;>;)V
    MethodParameters:
      Name                           Flags
      isErr                          final
      as                             final

  public final void println(scala.collection.immutable.Seq<java.lang.Object>);
    descriptor: (Lscala/collection/immutable/Seq;)V
    flags: (0x0011) ACC_PUBLIC, ACC_FINAL
    Code:
      stack=2, locals=2, args_size=2
         0: aload_0
         1: aload_1
         2: invokestatic  #705                // InterfaceMethod org/sireum/$internal/PackageTrait.println$:(Lorg/sireum/$internal/PackageTrait;Lscala/collection/immutable/Seq;)V
         5: return
      LineNumberTable:
        line 28: 0
      LocalVariableTable:
        Start  Length  Slot  Name   Signature
            0       6     0  this   Lorg/sireum/package$;
            0       6     1    as   Lscala/collection/immutable/Seq;
    Signature: #701                         // (Lscala/collection/immutable/Seq<Ljava/lang/Object;>;)V
    MethodParameters:
      Name                           Flags
      as                             final

  public final void print(scala.collection.immutable.Seq<java.lang.Object>);
    descriptor: (Lscala/collection/immutable/Seq;)V
    flags: (0x0011) ACC_PUBLIC, ACC_FINAL
    Code:
      stack=2, locals=2, args_size=2
         0: aload_0
         1: aload_1
         2: invokestatic  #709                // InterfaceMethod org/sireum/$internal/PackageTrait.print$:(Lorg/sireum/$internal/PackageTrait;Lscala/collection/immutable/Seq;)V
         5: return
      LineNumberTable:
        line 28: 0
      LocalVariableTable:
        Start  Length  Slot  Name   Signature
            0       6     0  this   Lorg/sireum/package$;
            0       6     1    as   Lscala/collection/immutable/Seq;
    Signature: #701                         // (Lscala/collection/immutable/Seq<Ljava/lang/Object;>;)V
    MethodParameters:
      Name                           Flags
      as                             final

  public final void eprintln(scala.collection.immutable.Seq<java.lang.Object>);
    descriptor: (Lscala/collection/immutable/Seq;)V
    flags: (0x0011) ACC_PUBLIC, ACC_FINAL
    Code:
      stack=2, locals=2, args_size=2
         0: aload_0
         1: aload_1
         2: invokestatic  #713                // InterfaceMethod org/sireum/$internal/PackageTrait.eprintln$:(Lorg/sireum/$internal/PackageTrait;Lscala/collection/immutable/Seq;)V
         5: return
      LineNumberTable:
        line 28: 0
      LocalVariableTable:
        Start  Length  Slot  Name   Signature
            0       6     0  this   Lorg/sireum/package$;
            0       6     1    as   Lscala/collection/immutable/Seq;
    Signature: #701                         // (Lscala/collection/immutable/Seq<Ljava/lang/Object;>;)V
    MethodParameters:
      Name                           Flags
      as                             final

  public final void eprint(scala.collection.immutable.Seq<java.lang.Object>);
    descriptor: (Lscala/collection/immutable/Seq;)V
    flags: (0x0011) ACC_PUBLIC, ACC_FINAL
    Code:
      stack=2, locals=2, args_size=2
         0: aload_0
         1: aload_1
         2: invokestatic  #717                // InterfaceMethod org/sireum/$internal/PackageTrait.eprint$:(Lorg/sireum/$internal/PackageTrait;Lscala/collection/immutable/Seq;)V
         5: return
      LineNumberTable:
        line 28: 0
      LocalVariableTable:
        Start  Length  Slot  Name   Signature
            0       6     0  this   Lorg/sireum/package$;
            0       6     1    as   Lscala/collection/immutable/Seq;
    Signature: #701                         // (Lscala/collection/immutable/Seq<Ljava/lang/Object;>;)V
    MethodParameters:
      Name                           Flags
      as                             final

  public scala.Option<scala.math.BigInt> $2BigIntOpt(int);
    descriptor: (I)Lscala/Option;
    flags: (0x0001) ACC_PUBLIC
    Code:
      stack=2, locals=2, args_size=2
         0: aload_0
         1: iload_1
         2: invokestatic  #724                // InterfaceMethod org/sireum/$internal/PackageTrait.$2BigIntOpt$:(Lorg/sireum/$internal/PackageTrait;I)Lscala/Option;
         5: areturn
      LineNumberTable:
        line 28: 0
      LocalVariableTable:
        Start  Length  Slot  Name   Signature
            0       6     0  this   Lorg/sireum/package$;
            0       6     1     n   I
    Signature: #720                         // (I)Lscala/Option<Lscala/math/BigInt;>;
    MethodParameters:
      Name                           Flags
      n                              final

  public scala.Option<scala.math.BigInt> $2BigIntOpt(long);
    descriptor: (J)Lscala/Option;
    flags: (0x0001) ACC_PUBLIC
    Code:
      stack=3, locals=3, args_size=2
         0: aload_0
         1: lload_1
         2: invokestatic  #729                // InterfaceMethod org/sireum/$internal/PackageTrait.$2BigIntOpt$:(Lorg/sireum/$internal/PackageTrait;J)Lscala/Option;
         5: areturn
      LineNumberTable:
        line 28: 0
      LocalVariableTable:
        Start  Length  Slot  Name   Signature
            0       6     0  this   Lorg/sireum/package$;
            0       6     1     n   J
    Signature: #726                         // (J)Lscala/Option<Lscala/math/BigInt;>;
    MethodParameters:
      Name                           Flags
      n                              final

  public scala.Option<scala.math.BigInt> $2BigIntOpt(org.sireum.Z);
    descriptor: (Lorg/sireum/Z;)Lscala/Option;
    flags: (0x0001) ACC_PUBLIC
    Code:
      stack=2, locals=2, args_size=2
         0: aload_0
         1: aload_1
         2: invokestatic  #735                // InterfaceMethod org/sireum/$internal/PackageTrait.$2BigIntOpt$:(Lorg/sireum/$internal/PackageTrait;Lorg/sireum/Z;)Lscala/Option;
         5: areturn
      LineNumberTable:
        line 28: 0
      LocalVariableTable:
        Start  Length  Slot  Name   Signature
            0       6     0  this   Lorg/sireum/package$;
            0       6     1     n   Lorg/sireum/Z;
    Signature: #732                         // (Lorg/sireum/Z;)Lscala/Option<Lscala/math/BigInt;>;
    MethodParameters:
      Name                           Flags
      n                              final

  public <I extends java.lang.Object> org.sireum.IS<org.sireum.Z, I> $2IS(org.sireum.ZRange<I>);
    descriptor: (Lorg/sireum/ZRange;)Lorg/sireum/IS;
    flags: (0x0001) ACC_PUBLIC
    Code:
      stack=2, locals=2, args_size=2
         0: aload_0
         1: aload_1
         2: invokestatic  #743                // InterfaceMethod org/sireum/$internal/PackageTrait.$2IS$:(Lorg/sireum/$internal/PackageTrait;Lorg/sireum/ZRange;)Lorg/sireum/IS;
         5: areturn
      LineNumberTable:
        line 28: 0
      LocalVariableTable:
        Start  Length  Slot  Name   Signature
            0       6     0  this   Lorg/sireum/package$;
            0       6     1    zr   Lorg/sireum/ZRange;
    Signature: #738                         // <I:Ljava/lang/Object;>(Lorg/sireum/ZRange<TI;>;)Lorg/sireum/IS<Lorg/sireum/Z;TI;>;
    MethodParameters:
      Name                           Flags
      zr                             final

  public org.sireum.contract$Spec$ Spec();
    descriptor: ()Lorg/sireum/contract$Spec$;
    flags: (0x0001) ACC_PUBLIC
    Code:
      stack=1, locals=1, args_size=1
         0: getstatic     #748                // Field Spec$module:Lorg/sireum/contract$Spec$;
         3: ifnonnull     10
         6: aload_0
         7: invokespecial #751                // Method Spec$lzycompute$1:()V
        10: getstatic     #748                // Field Spec$module:Lorg/sireum/contract$Spec$;
        13: areturn
      StackMapTable: number_of_entries = 1
        frame_type = 10 /* same */
      LineNumberTable:
        line 28: 0
      LocalVariableTable:
        Start  Length  Slot  Name   Signature
            0      14     0  this   Lorg/sireum/package$;

  public org.sireum.contract$Contract$ Contract();
    descriptor: ()Lorg/sireum/contract$Contract$;
    flags: (0x0001) ACC_PUBLIC
    Code:
      stack=1, locals=1, args_size=1
         0: getstatic     #755                // Field Contract$module:Lorg/sireum/contract$Contract$;
         3: ifnonnull     10
         6: aload_0
         7: invokespecial #758                // Method Contract$lzycompute$1:()V
        10: getstatic     #755                // Field Contract$module:Lorg/sireum/contract$Contract$;
        13: areturn
      StackMapTable: number_of_entries = 1
        frame_type = 10 /* same */
      LineNumberTable:
        line 28: 0
      LocalVariableTable:
        Start  Length  Slot  Name   Signature
            0      14     0  this   Lorg/sireum/package$;

  public org.sireum.contract$All$ All();
    descriptor: ()Lorg/sireum/contract$All$;
    flags: (0x0001) ACC_PUBLIC
    Code:
      stack=1, locals=1, args_size=1
         0: getstatic     #762                // Field All$module:Lorg/sireum/contract$All$;
         3: ifnonnull     10
         6: aload_0
         7: invokespecial #765                // Method All$lzycompute$1:()V
        10: getstatic     #762                // Field All$module:Lorg/sireum/contract$All$;
        13: areturn
      StackMapTable: number_of_entries = 1
        frame_type = 10 /* same */
      LineNumberTable:
        line 28: 0
      LocalVariableTable:
        Start  Length  Slot  Name   Signature
            0      14     0  this   Lorg/sireum/package$;

  public org.sireum.contract$$u2200$ $u2200();
    descriptor: ()Lorg/sireum/contract$$u2200$;
    flags: (0x0001) ACC_PUBLIC
    Code:
      stack=1, locals=1, args_size=1
         0: getstatic     #769                // Field $u2200$module:Lorg/sireum/contract$$u2200$;
         3: ifnonnull     10
         6: aload_0
         7: invokespecial #772                // Method $u2200$lzycompute$1:()V
        10: getstatic     #769                // Field $u2200$module:Lorg/sireum/contract$$u2200$;
        13: areturn
      StackMapTable: number_of_entries = 1
        frame_type = 10 /* same */
      LineNumberTable:
        line 28: 0
      LocalVariableTable:
        Start  Length  Slot  Name   Signature
            0      14     0  this   Lorg/sireum/package$;

  public org.sireum.contract$Exists$ Exists();
    descriptor: ()Lorg/sireum/contract$Exists$;
    flags: (0x0001) ACC_PUBLIC
    Code:
      stack=1, locals=1, args_size=1
         0: getstatic     #776                // Field Exists$module:Lorg/sireum/contract$Exists$;
         3: ifnonnull     10
         6: aload_0
         7: invokespecial #779                // Method Exists$lzycompute$1:()V
        10: getstatic     #776                // Field Exists$module:Lorg/sireum/contract$Exists$;
        13: areturn
      StackMapTable: number_of_entries = 1
        frame_type = 10 /* same */
      LineNumberTable:
        line 28: 0
      LocalVariableTable:
        Start  Length  Slot  Name   Signature
            0      14     0  this   Lorg/sireum/package$;

  public org.sireum.contract$$u2203$ $u2203();
    descriptor: ()Lorg/sireum/contract$$u2203$;
    flags: (0x0001) ACC_PUBLIC
    Code:
      stack=1, locals=1, args_size=1
         0: getstatic     #783                // Field $u2203$module:Lorg/sireum/contract$$u2203$;
         3: ifnonnull     10
         6: aload_0
         7: invokespecial #786                // Method $u2203$lzycompute$1:()V
        10: getstatic     #783                // Field $u2203$module:Lorg/sireum/contract$$u2203$;
        13: areturn
      StackMapTable: number_of_entries = 1
        frame_type = 10 /* same */
      LineNumberTable:
        line 28: 0
      LocalVariableTable:
        Start  Length  Slot  Name   Signature
            0      14     0  this   Lorg/sireum/package$;

  public org.sireum.$internal.PackageTrait$ISZ$ ISZ();
    descriptor: ()Lorg/sireum/$internal/PackageTrait$ISZ$;
    flags: (0x0001) ACC_PUBLIC
    Code:
      stack=1, locals=1, args_size=1
         0: getstatic     #790                // Field ISZ$module:Lorg/sireum/$internal/PackageTrait$ISZ$;
         3: ifnonnull     10
         6: aload_0
         7: invokespecial #793                // Method ISZ$lzycompute$1:()V
        10: getstatic     #790                // Field ISZ$module:Lorg/sireum/$internal/PackageTrait$ISZ$;
        13: areturn
      StackMapTable: number_of_entries = 1
        frame_type = 10 /* same */
      LineNumberTable:
        line 28: 0
      LocalVariableTable:
        Start  Length  Slot  Name   Signature
            0      14     0  this   Lorg/sireum/package$;

  public org.sireum.$internal.PackageTrait$MSZ$ MSZ();
    descriptor: ()Lorg/sireum/$internal/PackageTrait$MSZ$;
    flags: (0x0001) ACC_PUBLIC
    Code:
      stack=1, locals=1, args_size=1
         0: getstatic     #797                // Field MSZ$module:Lorg/sireum/$internal/PackageTrait$MSZ$;
         3: ifnonnull     10
         6: aload_0
         7: invokespecial #800                // Method MSZ$lzycompute$1:()V
        10: getstatic     #797                // Field MSZ$module:Lorg/sireum/$internal/PackageTrait$MSZ$;
        13: areturn
      StackMapTable: number_of_entries = 1
        frame_type = 10 /* same */
      LineNumberTable:
        line 28: 0
      LocalVariableTable:
        Start  Length  Slot  Name   Signature
            0      14     0  this   Lorg/sireum/package$;

  public org.sireum.$internal.PackageTrait$ZS$ ZS();
    descriptor: ()Lorg/sireum/$internal/PackageTrait$ZS$;
    flags: (0x0001) ACC_PUBLIC
    Code:
      stack=1, locals=1, args_size=1
         0: getstatic     #804                // Field ZS$module:Lorg/sireum/$internal/PackageTrait$ZS$;
         3: ifnonnull     10
         6: aload_0
         7: invokespecial #807                // Method ZS$lzycompute$1:()V
        10: getstatic     #804                // Field ZS$module:Lorg/sireum/$internal/PackageTrait$ZS$;
        13: areturn
      StackMapTable: number_of_entries = 1
        frame_type = 10 /* same */
      LineNumberTable:
        line 28: 0
      LocalVariableTable:
        Start  Length  Slot  Name   Signature
            0      14     0  this   Lorg/sireum/package$;

  public boolean T();
    descriptor: ()Z
    flags: (0x0001) ACC_PUBLIC
    Code:
      stack=1, locals=1, args_size=1
         0: getstatic     #810                // Field T:Z
         3: ireturn
      LineNumberTable:
        line 28: 0
      LocalVariableTable:
        Start  Length  Slot  Name   Signature
            0       4     0  this   Lorg/sireum/package$;

  public boolean F();
    descriptor: ()Z
    flags: (0x0001) ACC_PUBLIC
    Code:
      stack=1, locals=1, args_size=1
         0: getstatic     #812                // Field F:Z
         3: ireturn
      LineNumberTable:
        line 28: 0
      LocalVariableTable:
        Start  Length  Slot  Name   Signature
            0       4     0  this   Lorg/sireum/package$;

  public org.sireum.$ZCompanion<org.sireum.Z> $ZCompanion();
    descriptor: ()Lorg/sireum/$ZCompanion;
    flags: (0x0001) ACC_PUBLIC
    Code:
      stack=1, locals=1, args_size=1
         0: getstatic     #816                // Field $ZCompanion:Lorg/sireum/$ZCompanion;
         3: areturn
      LineNumberTable:
        line 28: 0
      LocalVariableTable:
        Start  Length  Slot  Name   Signature
            0       4     0  this   Lorg/sireum/package$;
    Signature: #814                         // ()Lorg/sireum/$ZCompanion<Lorg/sireum/Z;>;

  public void org$sireum$$internal$PackageTrait$_setter_$T_$eq(boolean);
    descriptor: (Z)V
    flags: (0x0001) ACC_PUBLIC
    Code:
      stack=1, locals=2, args_size=2
         0: iload_1
         1: putstatic     #810                // Field T:Z
         4: return
      LineNumberTable:
        line 28: 0
      LocalVariableTable:
        Start  Length  Slot  Name   Signature
            0       5     0  this   Lorg/sireum/package$;
            0       5     1   x$1   Z
    MethodParameters:
      Name                           Flags
      x$1                            final

  public void org$sireum$$internal$PackageTrait$_setter_$F_$eq(boolean);
    descriptor: (Z)V
    flags: (0x0001) ACC_PUBLIC
    Code:
      stack=1, locals=2, args_size=2
         0: iload_1
         1: putstatic     #812                // Field F:Z
         4: return
      LineNumberTable:
        line 28: 0
      LocalVariableTable:
        Start  Length  Slot  Name   Signature
            0       5     0  this   Lorg/sireum/package$;
            0       5     1   x$1   Z
    MethodParameters:
      Name                           Flags
      x$1                            final

  public void org$sireum$$internal$PackageTrait$_setter_$$ZCompanion_$eq(org.sireum.$ZCompanion<org.sireum.Z>);
    descriptor: (Lorg/sireum/$ZCompanion;)V
    flags: (0x0001) ACC_PUBLIC
    Code:
      stack=1, locals=2, args_size=2
         0: aload_1
         1: putstatic     #816                // Field $ZCompanion:Lorg/sireum/$ZCompanion;
         4: return
      LineNumberTable:
        line 28: 0
      LocalVariableTable:
        Start  Length  Slot  Name   Signature
            0       5     0  this   Lorg/sireum/package$;
            0       5     1   x$1   Lorg/sireum/$ZCompanion;
    Signature: #823                         // (Lorg/sireum/$ZCompanion<Lorg/sireum/Z;>;)V
    MethodParameters:
      Name                           Flags
      x$1                            final

  public final <T1 extends java.lang.Object> T1 $Arrow(T1);
    descriptor: (Ljava/lang/Object;)Ljava/lang/Object;
    flags: (0x0011) ACC_PUBLIC, ACC_FINAL
    Code:
      stack=1, locals=2, args_size=2
         0: aload_1
         1: areturn
      LineNumberTable:
        line 36: 0
      LocalVariableTable:
        Start  Length  Slot  Name   Signature
            0       2     0  this   Lorg/sireum/package$;
            0       2     1   _t1   Ljava/lang/Object;
    Signature: #825                         // <T1:Ljava/lang/Object;>(TT1;)TT1;
    MethodParameters:
      Name                           Flags
      _t1                            final

  public final org.sireum.package$$Slang $Slang(scala.StringContext);
    descriptor: (Lscala/StringContext;)Lorg/sireum/package$$Slang;
    flags: (0x0011) ACC_PUBLIC, ACC_FINAL
    Code:
      stack=3, locals=2, args_size=2
         0: new           #104                // class org/sireum/package$$Slang
         3: dup
         4: aload_1
         5: invokespecial #831                // Method org/sireum/package$$Slang."<init>":(Lscala/StringContext;)V
         8: areturn
      LineNumberTable:
        line 55: 0
      LocalVariableTable:
        Start  Length  Slot  Name   Signature
            0       9     0  this   Lorg/sireum/package$;
            0       9     1   $sc   Lscala/StringContext;
    MethodParameters:
      Name                           Flags
      $sc                            final

  public final java.lang.Object Any2HashString(java.lang.Object);
    descriptor: (Ljava/lang/Object;)Ljava/lang/Object;
    flags: (0x0011) ACC_PUBLIC, ACC_FINAL
    Code:
      stack=1, locals=2, args_size=2
         0: aload_1
         1: areturn
      LineNumberTable:
        line 122: 0
      LocalVariableTable:
        Start  Length  Slot  Name   Signature
            0       2     0  this   Lorg/sireum/package$;
            0       2     1    _o   Ljava/lang/Object;
    MethodParameters:
      Name                           Flags
      _o                             final

  public final boolean $Boolean2B(boolean);
    descriptor: (Z)Z
    flags: (0x0011) ACC_PUBLIC, ACC_FINAL
    Code:
      stack=1, locals=2, args_size=2
         0: iload_1
         1: ireturn
      LineNumberTable:
        line 127: 0
      LocalVariableTable:
        Start  Length  Slot  Name   Signature
            0       2     0  this   Lorg/sireum/package$;
            0       2     1 _value   Z
    MethodParameters:
      Name                           Flags
      _value                         final

  public final char $Char2C(char);
    descriptor: (C)C
    flags: (0x0011) ACC_PUBLIC, ACC_FINAL
    Code:
      stack=1, locals=2, args_size=2
         0: iload_1
         1: ireturn
      LineNumberTable:
        line 164: 0
      LocalVariableTable:
        Start  Length  Slot  Name   Signature
            0       2     0  this   Lorg/sireum/package$;
            0       2     1 _value   C
    MethodParameters:
      Name                           Flags
      _value                         final

  public final int $Int2Z(int);
    descriptor: (I)I
    flags: (0x0011) ACC_PUBLIC, ACC_FINAL
    Code:
      stack=1, locals=2, args_size=2
         0: iload_1
         1: ireturn
      LineNumberTable:
        line 209: 0
      LocalVariableTable:
        Start  Length  Slot  Name   Signature
            0       2     0  this   Lorg/sireum/package$;
            0       2     1 _value   I
    MethodParameters:
      Name                           Flags
      _value                         final

  public final long $Long2Z(long);
    descriptor: (J)J
    flags: (0x0011) ACC_PUBLIC, ACC_FINAL
    Code:
      stack=2, locals=3, args_size=2
         0: lload_1
         1: lreturn
      LineNumberTable:
        line 262: 0
      LocalVariableTable:
        Start  Length  Slot  Name   Signature
            0       2     0  this   Lorg/sireum/package$;
            0       2     1 _value   J
    MethodParameters:
      Name                           Flags
      _value                         final

  public final float $Float2F32(float);
    descriptor: (F)F
    flags: (0x0011) ACC_PUBLIC, ACC_FINAL
    Code:
      stack=1, locals=2, args_size=2
         0: fload_1
         1: freturn
      LineNumberTable:
        line 315: 0
      LocalVariableTable:
        Start  Length  Slot  Name   Signature
            0       2     0  this   Lorg/sireum/package$;
            0       2     1 _value   F
    MethodParameters:
      Name                           Flags
      _value                         final

  public final double $Double2F64(double);
    descriptor: (D)D
    flags: (0x0011) ACC_PUBLIC, ACC_FINAL
    Code:
      stack=2, locals=3, args_size=2
         0: dload_1
         1: dreturn
      LineNumberTable:
        line 360: 0
      LocalVariableTable:
        Start  Length  Slot  Name   Signature
            0       2     0  this   Lorg/sireum/package$;
            0       2     1 _value   D
    MethodParameters:
      Name                           Flags
      _value                         final

  public final java.lang.String $PredefString2String(java.lang.String);
    descriptor: (Ljava/lang/String;)Ljava/lang/String;
    flags: (0x0011) ACC_PUBLIC, ACC_FINAL
    Code:
      stack=1, locals=2, args_size=2
         0: aload_1
         1: areturn
      LineNumberTable:
        line 405: 0
      LocalVariableTable:
        Start  Length  Slot  Name   Signature
            0       2     0  this   Lorg/sireum/package$;
            0       2     1 _value   Ljava/lang/String;
    MethodParameters:
      Name                           Flags
      _value                         final

  private final void Spec$lzycompute$1();
    descriptor: ()V
    flags: (0x0012) ACC_PRIVATE, ACC_FINAL
    Code:
      stack=3, locals=2, args_size=1
         0: aload_0
         1: dup
         2: astore_1
         3: monitorenter
         4: getstatic     #748                // Field Spec$module:Lorg/sireum/contract$Spec$;
         7: ifnonnull     21
        10: new           #101                // class org/sireum/contract$Spec$
        13: dup
        14: aload_0
        15: invokespecial #853                // Method org/sireum/contract$Spec$."<init>":(Lorg/sireum/contract;)V
        18: putstatic     #748                // Field Spec$module:Lorg/sireum/contract$Spec$;
        21: aload_1
        22: monitorexit
        23: goto          29
        26: aload_1
        27: monitorexit
        28: athrow
        29: return
      Exception table:
         from    to  target type
             4    21    26   any
      StackMapTable: number_of_entries = 3
        frame_type = 252 /* append */
          offset_delta = 21
          locals = [ class org/sireum/package$ ]
        frame_type = 68 /* same_locals_1_stack_item */
          stack = [ class java/lang/Throwable ]
        frame_type = 2 /* same */
      LineNumberTable:
        line 28: 0
      LocalVariableTable:
        Start  Length  Slot  Name   Signature
            0      30     0  this   Lorg/sireum/package$;

  private final void Contract$lzycompute$1();
    descriptor: ()V
    flags: (0x0012) ACC_PRIVATE, ACC_FINAL
    Code:
      stack=3, locals=2, args_size=1
         0: aload_0
         1: dup
         2: astore_1
         3: monitorenter
         4: getstatic     #755                // Field Contract$module:Lorg/sireum/contract$Contract$;
         7: ifnonnull     21
        10: new           #29                 // class org/sireum/contract$Contract$
        13: dup
        14: aload_0
        15: invokespecial #856                // Method org/sireum/contract$Contract$."<init>":(Lorg/sireum/contract;)V
        18: putstatic     #755                // Field Contract$module:Lorg/sireum/contract$Contract$;
        21: aload_1
        22: monitorexit
        23: goto          29
        26: aload_1
        27: monitorexit
        28: athrow
        29: return
      Exception table:
         from    to  target type
             4    21    26   any
      StackMapTable: number_of_entries = 3
        frame_type = 252 /* append */
          offset_delta = 21
          locals = [ class org/sireum/package$ ]
        frame_type = 68 /* same_locals_1_stack_item */
          stack = [ class java/lang/Throwable ]
        frame_type = 2 /* same */
      LineNumberTable:
        line 28: 0
      LocalVariableTable:
        Start  Length  Slot  Name   Signature
            0      30     0  this   Lorg/sireum/package$;

  private final void All$lzycompute$1();
    descriptor: ()V
    flags: (0x0012) ACC_PRIVATE, ACC_FINAL
    Code:
      stack=3, locals=2, args_size=1
         0: aload_0
         1: dup
         2: astore_1
         3: monitorenter
         4: getstatic     #762                // Field All$module:Lorg/sireum/contract$All$;
         7: ifnonnull     21
        10: new           #26                 // class org/sireum/contract$All$
        13: dup
        14: aload_0
        15: invokespecial #857                // Method org/sireum/contract$All$."<init>":(Lorg/sireum/contract;)V
        18: putstatic     #762                // Field All$module:Lorg/sireum/contract$All$;
        21: aload_1
        22: monitorexit
        23: goto          29
        26: aload_1
        27: monitorexit
        28: athrow
        29: return
      Exception table:
         from    to  target type
             4    21    26   any
      StackMapTable: number_of_entries = 3
        frame_type = 252 /* append */
          offset_delta = 21
          locals = [ class org/sireum/package$ ]
        frame_type = 68 /* same_locals_1_stack_item */
          stack = [ class java/lang/Throwable ]
        frame_type = 2 /* same */
      LineNumberTable:
        line 28: 0
      LocalVariableTable:
        Start  Length  Slot  Name   Signature
            0      30     0  this   Lorg/sireum/package$;

  private final void $u2200$lzycompute$1();
    descriptor: ()V
    flags: (0x0012) ACC_PRIVATE, ACC_FINAL
    Code:
      stack=3, locals=2, args_size=1
         0: aload_0
         1: dup
         2: astore_1
         3: monitorenter
         4: getstatic     #769                // Field $u2200$module:Lorg/sireum/contract$$u2200$;
         7: ifnonnull     21
        10: new           #20                 // class org/sireum/contract$$u2200$
        13: dup
        14: aload_0
        15: invokespecial #858                // Method org/sireum/contract$$u2200$."<init>":(Lorg/sireum/contract;)V
        18: putstatic     #769                // Field $u2200$module:Lorg/sireum/contract$$u2200$;
        21: aload_1
        22: monitorexit
        23: goto          29
        26: aload_1
        27: monitorexit
        28: athrow
        29: return
      Exception table:
         from    to  target type
             4    21    26   any
      StackMapTable: number_of_entries = 3
        frame_type = 252 /* append */
          offset_delta = 21
          locals = [ class org/sireum/package$ ]
        frame_type = 68 /* same_locals_1_stack_item */
          stack = [ class java/lang/Throwable ]
        frame_type = 2 /* same */
      LineNumberTable:
        line 28: 0
      LocalVariableTable:
        Start  Length  Slot  Name   Signature
            0      30     0  this   Lorg/sireum/package$;

  private final void Exists$lzycompute$1();
    descriptor: ()V
    flags: (0x0012) ACC_PRIVATE, ACC_FINAL
    Code:
      stack=3, locals=2, args_size=1
         0: aload_0
         1: dup
         2: astore_1
         3: monitorenter
         4: getstatic     #776                // Field Exists$module:Lorg/sireum/contract$Exists$;
         7: ifnonnull     21
        10: new           #98                 // class org/sireum/contract$Exists$
        13: dup
        14: aload_0
        15: invokespecial #859                // Method org/sireum/contract$Exists$."<init>":(Lorg/sireum/contract;)V
        18: putstatic     #776                // Field Exists$module:Lorg/sireum/contract$Exists$;
        21: aload_1
        22: monitorexit
        23: goto          29
        26: aload_1
        27: monitorexit
        28: athrow
        29: return
      Exception table:
         from    to  target type
             4    21    26   any
      StackMapTable: number_of_entries = 3
        frame_type = 252 /* append */
          offset_delta = 21
          locals = [ class org/sireum/package$ ]
        frame_type = 68 /* same_locals_1_stack_item */
          stack = [ class java/lang/Throwable ]
        frame_type = 2 /* same */
      LineNumberTable:
        line 28: 0
      LocalVariableTable:
        Start  Length  Slot  Name   Signature
            0      30     0  this   Lorg/sireum/package$;

  private final void $u2203$lzycompute$1();
    descriptor: ()V
    flags: (0x0012) ACC_PRIVATE, ACC_FINAL
    Code:
      stack=3, locals=2, args_size=1
         0: aload_0
         1: dup
         2: astore_1
         3: monitorenter
         4: getstatic     #783                // Field $u2203$module:Lorg/sireum/contract$$u2203$;
         7: ifnonnull     21
        10: new           #23                 // class org/sireum/contract$$u2203$
        13: dup
        14: aload_0
        15: invokespecial #860                // Method org/sireum/contract$$u2203$."<init>":(Lorg/sireum/contract;)V
        18: putstatic     #783                // Field $u2203$module:Lorg/sireum/contract$$u2203$;
        21: aload_1
        22: monitorexit
        23: goto          29
        26: aload_1
        27: monitorexit
        28: athrow
        29: return
      Exception table:
         from    to  target type
             4    21    26   any
      StackMapTable: number_of_entries = 3
        frame_type = 252 /* append */
          offset_delta = 21
          locals = [ class org/sireum/package$ ]
        frame_type = 68 /* same_locals_1_stack_item */
          stack = [ class java/lang/Throwable ]
        frame_type = 2 /* same */
      LineNumberTable:
        line 28: 0
      LocalVariableTable:
        Start  Length  Slot  Name   Signature
            0      30     0  this   Lorg/sireum/package$;

  private final void ISZ$lzycompute$1();
    descriptor: ()V
    flags: (0x0012) ACC_PRIVATE, ACC_FINAL
    Code:
      stack=3, locals=2, args_size=1
         0: aload_0
         1: dup
         2: astore_1
         3: monitorenter
         4: getstatic     #790                // Field ISZ$module:Lorg/sireum/$internal/PackageTrait$ISZ$;
         7: ifnonnull     21
        10: new           #11                 // class org/sireum/$internal/PackageTrait$ISZ$
        13: dup
        14: aload_0
        15: invokespecial #862                // Method org/sireum/$internal/PackageTrait$ISZ$."<init>":(Lorg/sireum/$internal/PackageTrait;)V
        18: putstatic     #790                // Field ISZ$module:Lorg/sireum/$internal/PackageTrait$ISZ$;
        21: aload_1
        22: monitorexit
        23: goto          29
        26: aload_1
        27: monitorexit
        28: athrow
        29: return
      Exception table:
         from    to  target type
             4    21    26   any
      StackMapTable: number_of_entries = 3
        frame_type = 252 /* append */
          offset_delta = 21
          locals = [ class org/sireum/package$ ]
        frame_type = 68 /* same_locals_1_stack_item */
          stack = [ class java/lang/Throwable ]
        frame_type = 2 /* same */
      LineNumberTable:
        line 28: 0
      LocalVariableTable:
        Start  Length  Slot  Name   Signature
            0      30     0  this   Lorg/sireum/package$;

  private final void MSZ$lzycompute$1();
    descriptor: ()V
    flags: (0x0012) ACC_PRIVATE, ACC_FINAL
    Code:
      stack=3, locals=2, args_size=1
         0: aload_0
         1: dup
         2: astore_1
         3: monitorenter
         4: getstatic     #797                // Field MSZ$module:Lorg/sireum/$internal/PackageTrait$MSZ$;
         7: ifnonnull     21
        10: new           #14                 // class org/sireum/$internal/PackageTrait$MSZ$
        13: dup
        14: aload_0
        15: invokespecial #863                // Method org/sireum/$internal/PackageTrait$MSZ$."<init>":(Lorg/sireum/$internal/PackageTrait;)V
        18: putstatic     #797                // Field MSZ$module:Lorg/sireum/$internal/PackageTrait$MSZ$;
        21: aload_1
        22: monitorexit
        23: goto          29
        26: aload_1
        27: monitorexit
        28: athrow
        29: return
      Exception table:
         from    to  target type
             4    21    26   any
      StackMapTable: number_of_entries = 3
        frame_type = 252 /* append */
          offset_delta = 21
          locals = [ class org/sireum/package$ ]
        frame_type = 68 /* same_locals_1_stack_item */
          stack = [ class java/lang/Throwable ]
        frame_type = 2 /* same */
      LineNumberTable:
        line 28: 0
      LocalVariableTable:
        Start  Length  Slot  Name   Signature
            0      30     0  this   Lorg/sireum/package$;

  private final void ZS$lzycompute$1();
    descriptor: ()V
    flags: (0x0012) ACC_PRIVATE, ACC_FINAL
    Code:
      stack=3, locals=2, args_size=1
         0: aload_0
         1: dup
         2: astore_1
         3: monitorenter
         4: getstatic     #804                // Field ZS$module:Lorg/sireum/$internal/PackageTrait$ZS$;
         7: ifnonnull     21
        10: new           #17                 // class org/sireum/$internal/PackageTrait$ZS$
        13: dup
        14: aload_0
        15: invokespecial #864                // Method org/sireum/$internal/PackageTrait$ZS$."<init>":(Lorg/sireum/$internal/PackageTrait;)V
        18: putstatic     #804                // Field ZS$module:Lorg/sireum/$internal/PackageTrait$ZS$;
        21: aload_1
        22: monitorexit
        23: goto          29
        26: aload_1
        27: monitorexit
        28: athrow
        29: return
      Exception table:
         from    to  target type
             4    21    26   any
      StackMapTable: number_of_entries = 3
        frame_type = 252 /* append */
          offset_delta = 21
          locals = [ class org/sireum/package$ ]
        frame_type = 68 /* same_locals_1_stack_item */
          stack = [ class java/lang/Throwable ]
        frame_type = 2 /* same */
      LineNumberTable:
        line 28: 0
      LocalVariableTable:
        Start  Length  Slot  Name   Signature
            0      30     0  this   Lorg/sireum/package$;

  private org.sireum.package$();
    descriptor: ()V
    flags: (0x0002) ACC_PRIVATE
    Code:
      stack=1, locals=1, args_size=1
         0: aload_0
         1: invokespecial #865                // Method java/lang/Object."<init>":()V
         4: return
      LineNumberTable:
        line 28: 0
      LocalVariableTable:
        Start  Length  Slot  Name   Signature
            0       5     0  this   Lorg/sireum/package$;
}
InnerClasses:
  public #12= #11 of #6;                  // ISZ$=class org/sireum/$internal/PackageTrait$ISZ$ of class org/sireum/$internal/PackageTrait
  public #15= #14 of #6;                  // MSZ$=class org/sireum/$internal/PackageTrait$MSZ$ of class org/sireum/$internal/PackageTrait
  public #18= #17 of #6;                  // ZS$=class org/sireum/$internal/PackageTrait$ZS$ of class org/sireum/$internal/PackageTrait
  public #21= #20 of #8;                  // $u2200$=class org/sireum/contract$$u2200$ of class org/sireum/contract
  public #24= #23 of #8;                  // $u2203$=class org/sireum/contract$$u2203$ of class org/sireum/contract
  public #27= #26 of #8;                  // All$=class org/sireum/contract$All$ of class org/sireum/contract
  public #30= #29 of #8;                  // Contract$=class org/sireum/contract$Contract$ of class org/sireum/contract
  public #33= #32 of #29;                 // Assert=class org/sireum/contract$Contract$Assert of class org/sireum/contract$Contract$
  public #36= #35 of #29;                 // Assume=class org/sireum/contract$Contract$Assume of class org/sireum/contract$Contract$
  public #39= #38 of #29;                 // Case=class org/sireum/contract$Contract$Case of class org/sireum/contract$Contract$
  public #42= #41 of #29;                 // DataRefinement=class org/sireum/contract$Contract$DataRefinement of class org/sireum/contract$Contract$
  public #45= #44 of #29;                 // Ensures=class org/sireum/contract$Contract$Ensures of class org/sireum/contract$Contract$
  public #48= #47 of #29;                 // Fact=class org/sireum/contract$Contract$Fact of class org/sireum/contract$Contract$
  public #51= #50 of #29;                 // Invariant=class org/sireum/contract$Contract$Invariant of class org/sireum/contract$Contract$
  public #54= #53 of #29;                 // Justification=class org/sireum/contract$Contract$Justification of class org/sireum/contract$Contract$
  public #57= #56 of #29;                 // Lemma=class org/sireum/contract$Contract$Lemma of class org/sireum/contract$Contract$
  public #60= #59 of #29;                 // Let=class org/sireum/contract$Contract$Let of class org/sireum/contract$Contract$
  public #63= #62 of #29;                 // MaxIt=class org/sireum/contract$Contract$MaxIt of class org/sireum/contract$Contract$
  public #66= #65 of #29;                 // Modifies=class org/sireum/contract$Contract$Modifies of class org/sireum/contract$Contract$
  public #69= #68 of #29;                 // Proof=class org/sireum/contract$Contract$Proof of class org/sireum/contract$Contract$
  public #72= #71 of #29;                 // ProofStep=class org/sireum/contract$Contract$ProofStep of class org/sireum/contract$Contract$
  public #75= #74 of #29;                 // Reads=class org/sireum/contract$Contract$Reads of class org/sireum/contract$Contract$
  public #78= #77 of #29;                 // Requires=class org/sireum/contract$Contract$Requires of class org/sireum/contract$Contract$
  public #81= #80 of #29;                 // Sequent=class org/sireum/contract$Contract$Sequent of class org/sireum/contract$Contract$
  public #84= #83 of #29;                 // SequentBuilder=class org/sireum/contract$Contract$SequentBuilder of class org/sireum/contract$Contract$
  public #87= #86 of #29;                 // StateCont=class org/sireum/contract$Contract$StateCont of class org/sireum/contract$Contract$
  public #90= #89 of #29;                 // StepBuilder=class org/sireum/contract$Contract$StepBuilder of class org/sireum/contract$Contract$
  public #93= #92 of #29;                 // SubProof=class org/sireum/contract$Contract$SubProof of class org/sireum/contract$Contract$
  public #96= #95 of #29;                 // Theorem=class org/sireum/contract$Contract$Theorem of class org/sireum/contract$Contract$
  public #99= #98 of #8;                  // Exists$=class org/sireum/contract$Exists$ of class org/sireum/contract
  public #102= #101 of #8;                // Spec$=class org/sireum/contract$Spec$ of class org/sireum/contract
  public static final #107= #104 of #106; // $Slang=class org/sireum/package$$Slang of class org/sireum/package
SourceFile: "package.scala"
  ScalaInlineInfo: length = 0x2C0 (unknown attribute)
   01 01 00 8C 03 6B 01 D9 01 02 CE 02 CF 05 02 CE
   02 D5 05 02 CE 02 DB 05 02 E0 02 E1 05 03 38 01
   BF 01 03 43 03 44 01 03 46 03 47 01 03 4F 03 50
   01 03 4D 03 4E 01 03 49 03 4A 01 03 4B 03 4C 01
   03 52 03 53 01 00 6B 03 3B 01 00 83 03 2D 01 01
   E6 01 E7 01 02 02 02 03 01 01 FC 01 FD 01 02 0A
   02 41 01 02 0A 02 47 01 02 0A 02 4D 01 02 0A 02
   53 01 02 0A 02 59 01 02 0A 02 5F 01 02 0A 02 65
   01 02 0A 02 6B 01 02 0A 02 71 01 02 0A 02 77 01
   02 0A 02 7D 01 02 0A 02 83 01 02 0A 02 89 01 02
   0A 02 11 01 02 0A 02 17 01 02 0A 02 1D 01 02 0A
   02 23 01 02 0A 02 29 01 02 0A 02 2F 01 02 0A 02
   35 01 02 0A 02 3B 01 02 0A 02 0B 01 01 F1 01 F2
   01 01 F1 01 F8 01 02 FE 02 FF 01 03 02 00 87 01
   03 0C 03 0D 01 03 10 00 87 01 01 ED 01 E7 01 00
   88 00 87 01 02 F7 02 F8 01 02 FB 00 87 01 03 41
   01 BF 01 00 21 01 2B 01 00 24 01 26 01 01 CA 01
   CB 01 01 CA 01 D2 01 00 27 00 E3 01 00 27 00 DE
   01 00 27 00 E7 01 00 27 00 D4 01 00 27 00 CD 01
   00 27 00 DA 01 02 F0 02 F1 01 02 F4 00 87 01 00
   2A 00 C4 01 03 6C 03 6D 01 03 6C 03 6E 01 03 6C
   03 6F 01 00 2D 00 B1 01 03 05 03 06 01 03 09 00
   87 01 00 82 03 28 01 00 30 00 F1 01 00 30 00 EB
   01 03 13 03 14 01 03 17 00 87 01 01 DF 01 E0 01
   01 BE 01 BF 01 00 33 00 BD 01 00 33 03 70 01 00
   33 03 71 01 00 33 03 72 01 00 33 00 B7 01 00 39
   00 FE 01 00 39 00 F6 01 00 3C 01 70 01 00 3C 01
   76 01 00 3C 01 7C 01 00 3C 01 82 01 00 3C 01 88
   01 00 3C 01 8E 01 00 3C 01 94 01 00 3C 01 9A 01
   00 3C 01 A0 01 00 3C 01 A6 01 00 3C 01 38 01 00
   3C 01 AC 01 00 3C 01 B2 01 00 3C 01 B8 01 00 3C
   01 40 01 00 3C 01 46 01 00 3C 01 4C 01 00 3C 01
   52 01 00 3C 01 58 01 00 3C 01 5E 01 00 3C 01 64
   01 00 3C 01 6A 01 03 1A 03 1B 01 03 1E 00 87 01
   00 3F 00 94 01 00 42 00 AB 01 01 C6 01 BF 01 00
   45 01 0B 01 00 4B 00 9C 01 00 4E 00 A4 01 01 D8
   01 D9 01 02 E9 02 EA 01 02 ED 00 87 01 01 12 01
   13 01 01 12 01 1A 01 01 32 01 33 01 00 5D 01 20
   01 00 80 03 28 01 00 60 01 07 01 00 60 01 02 01
   03 21 03 22 01 03 25 00 87 01 02 B7 02 AF 01 02
   AE 02 AF 01 02 CA 02 BC 01 02 C6 02 BC 01 02 A8
   02 A9 01 03 35 03 36 01 03 34 03 32 01 03 31 03
   32 01 02 C2 02 BC 01 02 BB 02 BC 01 02 9D 02 9E
   01 02 8F 02 90 01 02 A4 02 90 01 02 95 02 96 01

  Scala: length = 0x0 (unknown attribute)

