Classfile /Users/mw/Projects/slang-braindump/.jar/jar8/assemble/slang-braindump/assemble/content/org/sireum/Some.class
  Last modified May 29, 2022; size 9699 bytes
  SHA-256 checksum e45a9da35ec6e3237b0bb89f9e9e221adabb3913bfa4b30ec64e0cbaf45b32cb
  Compiled from "Option.scala"
public final class org.sireum.Some<T extends java.lang.Object> extends java.lang.Object implements org.sireum.Option<T>
  minor version: 0
  major version: 52
  flags: (0x0031) ACC_PUBLIC, ACC_FINAL, ACC_SUPER
  this_class: #2                          // org/sireum/Some
  super_class: #5                         // java/lang/Object
  interfaces: 1, fields: 4, methods: 30, attributes: 6
Constant pool:
    #1 = Utf8               org/sireum/Some
    #2 = Class              #1            // org/sireum/Some
    #3 = Utf8               <T:Ljava/lang/Object;>Ljava/lang/Object;Lorg/sireum/Option<TT;>;
    #4 = Utf8               java/lang/Object
    #5 = Class              #4            // java/lang/Object
    #6 = Utf8               org/sireum/Option
    #7 = Class              #6            // org/sireum/Option
    #8 = Utf8               Option.scala
    #9 = Utf8               Lscala/reflect/ScalaSignature;
   #10 = Utf8               bytes
   #11 = Utf8               \u0006\u0005\u0005=w!B\u000f\u001f\u0011\u0003\u0019c!B\u0013\u001f\u0011\u00031\u0003\"B\u0017\u0002\t\u0003q\u0003\"B\u0018\u0002\t\u0003\u0001\u0004bBA_\u0003\u0011\u0005\u0011q\u0018\u0004\u0005Ky\u00111\u0007\u0003\u0005G\u000b\t\u0005\t\u0015!\u00039\u0011\u0015iS\u0001\"\u0001H\u0011\u0019QU\u0001)A\u0005q!)1*\u0002C\u0001\u0019\")Q*\u0002C\u0001\u0019\")a*\u0002C!\u001f\")\u0001,\u0002C!3\"AA,\u0002EC\u0002\u0013\u0005S\fC\u0003b\u000b\u0011\u0005#\rC\u00030\u000b\u0011\u0005\u0001\u000eC\u0004k\u000bE\u0005I\u0011A6\t\u0011Y,\u0001R1A\u0005B]Dq!a\u0004\u0006\t\u0003\n\t\u0002C\u0004\u0002\"\u0015!\t%!\u0005\t\u000f\u0005\u0015R\u0001\"\u0011\u0002(!9\u00111I\u0003\u0005B\u0005\u0015\u0003bBA,\u000b\u0011\u0005\u0013\u0011\f\u0005\b\u0003G*A\u0011IA3\u0011\u001d\tY\'\u0002C!\u0003[Bq!a\u001f\u0006\t\u0003\ni\b\u0003\u0004\u0002\u0004\u0016!\t\u0005\u0014\u0005\b\u0003\u000f+A\u0011IAE\u0011\u001d\tI*\u0002C!\u00037\u000bAaU8nK*\u0011q\u0004I\u0001\u0007g&\u0014X-^7\u000b\u0003\u0005\n1a\u001c:h\u0007\u0001\u0001\"\u0001J\u0001\u000e\u0003y\u0011AaU8nKN\u0011\u0011a\n\t\u0003Q-j\u0011!\u000b\u0006\u0002U\u0005)1oY1mC&\u0011A&\u000b\u0002\u0007\u0003:L(+\u001a4\u0002\rqJg.\u001b;?)\u0005\u0019\u0013!B1qa2LXcA\u0019\u0002:R\u0019!\'a/\u0011\t\u0011*\u0011qW\u000b\u0003ii\u001aB!B\u00146\u0007B\u0019AE\u000e\u001d\n\u0005]r\"AB(qi&|g\u000e\u0005\u0002:u1\u0001A!B\u001e\u0006\u0005\u0004a$!\u0001+\u0012\u0005u\u0002\u0005C\u0001\u0015?\u0013\ty\u0014FA\u0004O_RD\u0017N\\4\u0011\u0005!\n\u0015B\u0001\"*\u0005\r\te.\u001f\t\u0003I\u0011K!!\u0012\u0010\u0003\u0017\u0011\u000bG/\u0019;za\u0016\u001c\u0016nZ\u0001\b?~3\u0018\r\\;f)\tA\u0015\nE\u0002%\u000baBQAR\u0004A\u0002a\naa\u0018<bYV,\u0017!\u0002<bYV,W#\u0001\u001d\u0002\u0011\u001d,GOV1mk\u0016\f\u0001\u0002^8TiJLgn\u001a\u000b\u0002!B\u0011\u0011KV\u0007\u0002%*\u00111\u000bV\u0001\u0005Y\u0006twMC\u0001V\u0003\u0011Q\u0017M^1\n\u0005]\u0013&AB*ue&tw-\u0001\u0004tiJLgnZ\u000b\u00025B\u0011AeW\u0005\u0003/z\t\u0001\u0002[1tQ\u000e{G-Z\u000b\u0002=B\u0011\u0001fX\u0005\u0003A&\u00121!\u00138u\u0003\u0019)\u0017/^1mgR\u00111M\u001a\t\u0003Q\u0011L!!Z\u0015\u0003\u000f\t{w\u000e\\3b]\")qM\u0004a\u0001\u0001\u0006\tq\u000e\u0006\u0002IS\"91j\u0004I\u0001\u0002\u0004A\u0014aD1qa2LH\u0005Z3gCVdG\u000fJ\u0019\u0016\u00031T#\u0001O7,\u00039\u0004\"a\u001c;\u000e\u0003AT!!\u001d:\u0002\u0013Ut7\r[3dW\u0016$\'BA:*\u0003)\tgN\\8uCRLwN\\\u0005\u0003kB\u0014\u0011#\u001e8dQ\u0016\u001c7.\u001a3WCJL\u0017M\\2f\u0003!!3m\u001c8uK:$X#\u0001=\u0011\u000be\f\u0019!!\u0003\u000f\u0005i|hBA>\u007f\u001b\u0005a(BA?#\u0003\u0019a$o\\8u}%\t!&C\u0002\u0002\u0002%\nq\u0001]1dW\u0006<W-\u0003\u0003\u0002\u0006\u0005\u001d!aA*fc*\u0019\u0011\u0011A\u0015\u0011\u000b!\nY\u0001\u0015!\n\u0007\u00055\u0011F\u0001\u0004UkBdWMM\u0001\bSN,U\u000e\u001d;z+\t\t\u0019\u0002E\u0002%\u0003+I1!a\u0006\u001f\u0005\u0005\u0011\u0005f\u0001\n\u0002\u001cA\u0019A%!\b\n\u0007\u0005}aD\u0001\u0003qkJ,\u0017\u0001\u00038p]\u0016k\u0007\u000f^=)\u0007M\tY\"A\u0002nCB,B!!\u000b\u00020Q!\u00111FA\u001a!\u0011!c\'!\f\u0011\u0007e\ny\u0003\u0002\u0004\u00022Q\u0011\r\u0001\u0010\u0002\u0003)JBq!!\u000e\u0015\u0001\u0004\t9$A\u0001g!\u0019A\u0013\u0011\b\u001d\u0002>%\u0019\u00111H\u0015\u0003\u0013\u0019+hn\u0019;j_:\f$\u0006BA\u0017\u0003\u007fY#!a\u0007)\u0007Q\tY\"A\u0004gY\u0006$X*\u00199\u0016\t\u0005\u001d\u0013Q\n\u000b\u0005\u0003\u0013\ny\u0005\u0005\u0003%m\u0005-\u0003cA\u001d\u0002N\u00111\u0011\u0011G\u000bC\u0002qBq!!\u000e\u0016\u0001\u0004\t\t\u0006\u0005\u0004)\u0003sA\u00141\u000b\u0016\u0005\u0003\u0013\ny\u0004K\u0002\u0016\u00037\taAZ8sC2dG\u0003BA\n\u00037Bq!!\u000e\u0017\u0001\u0004\ti\u0006\u0005\u0004)\u0003sA\u0014q\f\u0016\u0005\u0003\'\ty\u0004K\u0002\u0017\u00037\ta!\u001a=jgR\u001cH\u0003BA\n\u0003OBq!!\u000e\u0018\u0001\u0004\ti\u0006K\u0002\u0018\u00037\t\u0011bZ3u\u001fJ,En]3\u0015\u0007a\ny\u0007\u0003\u0005\u0002ra!\t\u0019AA:\u0003\u001d!WMZ1vYR\u0004B\u0001KA;q%\u0019\u0011qO\u0015\u0003\u0011q\u0012\u0017P\\1nKzB3\u0001GA\u000e\u000399W\r^(s\u000b2\u001cX-R1hKJ$2\u0001OA@\u0011\u0019\t\t(\u0007a\u0001q!\u001a\u0011$a\u0007\u0002\u0007\u001d,G\u000fK\u0002\u001b\u00037\tA\u0001^8J\'V\u0011\u00111\u0012\t\u0007I\u00055\u0015\u0011\u0013\u001d\n\u0007\u0005=eD\u0001\u0002J\'B\u0019A%a%\n\u0007\u0005UeDA\u0001[Q\rY\u00121D\u0001\bM>\u0014X-Y2i+\u0011\ti*a+\u0015\t\u0005}\u0015Q\u0015\t\u0004Q\u0005\u0005\u0016bAARS\t!QK\\5u\u0011\u001d\t)\u0004\ba\u0001\u0003O\u0003b\u0001KA\u001dq\u0005%\u0006cA\u001d\u0002,\u00121\u0011Q\u0016\u000fC\u0002q\u0012\u0011A\u0016\u0015\u0004\u000b\u0005E\u0006c\u0001\u0013\u00024&\u0019\u0011Q\u0017\u0010\u0003\u0011\u0011\fG/\u0019;za\u0016\u00042!OA]\t\u0015Y4A1\u0001=\u0011\u0019Y5\u00011\u0001\u00028\u00069QO\\1qa2LX\u0003BAa\u0003\u0013$B!a1\u0002LB)\u0001&!2\u0002H&\u0011Q%\u000b\t\u0004s\u0005%G!B\u001e\u0005\u0005\u0004a\u0004BB4\u0005\u0001\u0004\ti\r\u0005\u0003%\u000b\u0005\u001d\u0007
   #12 = Utf8               org/sireum/$internal/PackageTrait$ISZ$
   #13 = Class              #12           // org/sireum/$internal/PackageTrait$ISZ$
   #14 = Utf8               org/sireum/$internal/PackageTrait
   #15 = Class              #14           // org/sireum/$internal/PackageTrait
   #16 = Utf8               ISZ$
   #17 = Utf8               hashCode
   #18 = Utf8               I
   #19 = Utf8               $content
   #20 = Utf8               Lscala/collection/immutable/Seq;
   #21 = Utf8               Lscala/collection/immutable/Seq<Lscala/Tuple2<Ljava/lang/String;Ljava/lang/Object;>;>;
   #22 = Utf8               _value
   #23 = Utf8               Ljava/lang/Object;
   #24 = Utf8               TT;
   #25 = Utf8               bitmap$0
   #26 = Utf8               B
   #27 = Utf8               unapply
   #28 = Utf8               (Lorg/sireum/Some;)Lscala/Some;
   #29 = Utf8               <T:Ljava/lang/Object;>(Lorg/sireum/Some<TT;>;)Lscala/Some<TT;>;
   #30 = Utf8               o
   #31 = Utf8               org/sireum/Some$
   #32 = Class              #31           // org/sireum/Some$
   #33 = Utf8               MODULE$
   #34 = Utf8               Lorg/sireum/Some$;
   #35 = NameAndType        #33:#34       // MODULE$:Lorg/sireum/Some$;
   #36 = Fieldref           #32.#35       // org/sireum/Some$.MODULE$:Lorg/sireum/Some$;
   #37 = NameAndType        #27:#28       // unapply:(Lorg/sireum/Some;)Lscala/Some;
   #38 = Methodref          #32.#37       // org/sireum/Some$.unapply:(Lorg/sireum/Some;)Lscala/Some;
   #39 = Utf8               Lorg/sireum/Some;
   #40 = Utf8               hash
   #41 = Utf8               ()Lorg/sireum/Z;
   #42 = Utf8               org/sireum/DatatypeSig
   #43 = Class              #42           // org/sireum/DatatypeSig
   #44 = Utf8               hash$
   #45 = Utf8               (Lorg/sireum/DatatypeSig;)Lorg/sireum/Z;
   #46 = NameAndType        #44:#45       // hash$:(Lorg/sireum/DatatypeSig;)Lorg/sireum/Z;
   #47 = InterfaceMethodref #43.#46       // org/sireum/DatatypeSig.hash$:(Lorg/sireum/DatatypeSig;)Lorg/sireum/Z;
   #48 = Utf8               this
   #49 = Utf8               $cannotMixImmutableAndMutable
   #50 = Utf8               ()Lscala/runtime/Nothing$;
   #51 = Utf8               org/sireum/Immutable
   #52 = Class              #51           // org/sireum/Immutable
   #53 = Utf8               $cannotMixImmutableAndMutable$
   #54 = Utf8               (Lorg/sireum/Immutable;)Lscala/runtime/Nothing$;
   #55 = NameAndType        #53:#54       // $cannotMixImmutableAndMutable$:(Lorg/sireum/Immutable;)Lscala/runtime/Nothing$;
   #56 = InterfaceMethodref #52.#55       // org/sireum/Immutable.$cannotMixImmutableAndMutable$:(Lorg/sireum/Immutable;)Lscala/runtime/Nothing$;
   #57 = Utf8               $hasEquals
   #58 = Utf8               ()Z
   #59 = Utf8               $hasEquals$
   #60 = Utf8               (Lorg/sireum/Immutable;)Z
   #61 = NameAndType        #59:#60       // $hasEquals$:(Lorg/sireum/Immutable;)Z
   #62 = InterfaceMethodref #52.#61       // org/sireum/Immutable.$hasEquals$:(Lorg/sireum/Immutable;)Z
   #63 = Utf8               $hasString
   #64 = Utf8               $hasString$
   #65 = NameAndType        #64:#60       // $hasString$:(Lorg/sireum/Immutable;)Z
   #66 = InterfaceMethodref #52.#65       // org/sireum/Immutable.$hasString$:(Lorg/sireum/Immutable;)Z
   #67 = Utf8               $clone
   #68 = Utf8               ()Lorg/sireum/$internal/ImmutableMarker;
   #69 = Utf8               org/sireum/$internal/ImmutableMarker
   #70 = Class              #69           // org/sireum/$internal/ImmutableMarker
   #71 = Utf8               $clone$
   #72 = Utf8               (Lorg/sireum/$internal/ImmutableMarker;)Lorg/sireum/$internal/ImmutableMarker;
   #73 = NameAndType        #71:#72       // $clone$:(Lorg/sireum/$internal/ImmutableMarker;)Lorg/sireum/$internal/ImmutableMarker;
   #74 = InterfaceMethodref #70.#73       // org/sireum/$internal/ImmutableMarker.$clone$:(Lorg/sireum/$internal/ImmutableMarker;)Lorg/sireum/$internal/ImmutableMarker;
   #75 = Utf8               value
   #76 = Utf8               ()Ljava/lang/Object;
   #77 = Utf8               ()TT;
   #78 = NameAndType        #22:#23       // _value:Ljava/lang/Object;
   #79 = Fieldref           #2.#78        // org/sireum/Some._value:Ljava/lang/Object;
   #80 = Utf8               getValue
   #81 = Utf8               toString
   #82 = Utf8               ()Ljava/lang/String;
   #83 = NameAndType        #63:#58       // $hasString:()Z
   #84 = Methodref          #2.#83        // org/sireum/Some.$hasString:()Z
   #85 = Utf8               string$
   #86 = Utf8               (Lorg/sireum/DatatypeSig;)Ljava/lang/String;
   #87 = NameAndType        #85:#86       // string$:(Lorg/sireum/DatatypeSig;)Ljava/lang/String;
   #88 = InterfaceMethodref #43.#87       // org/sireum/DatatypeSig.string$:(Lorg/sireum/DatatypeSig;)Ljava/lang/String;
   #89 = Utf8               java/lang/StringBuilder
   #90 = Class              #89           // java/lang/StringBuilder
   #91 = Utf8               <init>
   #92 = Utf8               ()V
   #93 = NameAndType        #91:#92       // "<init>":()V
   #94 = Methodref          #90.#93       // java/lang/StringBuilder."<init>":()V
   #95 = Utf8               Some
   #96 = String             #95           // Some
   #97 = Utf8               append
   #98 = Utf8               (Ljava/lang/String;)Ljava/lang/StringBuilder;
   #99 = NameAndType        #97:#98       // append:(Ljava/lang/String;)Ljava/lang/StringBuilder;
  #100 = Methodref          #90.#99       // java/lang/StringBuilder.append:(Ljava/lang/String;)Ljava/lang/StringBuilder;
  #101 = Utf8               (C)Ljava/lang/StringBuilder;
  #102 = NameAndType        #97:#101      // append:(C)Ljava/lang/StringBuilder;
  #103 = Methodref          #90.#102      // java/lang/StringBuilder.append:(C)Ljava/lang/StringBuilder;
  #104 = Utf8               org/sireum/String$
  #105 = Class              #104          // org/sireum/String$
  #106 = Utf8               Lorg/sireum/String$;
  #107 = NameAndType        #33:#106      // MODULE$:Lorg/sireum/String$;
  #108 = Fieldref           #105.#107     // org/sireum/String$.MODULE$:Lorg/sireum/String$;
  #109 = NameAndType        #75:#76       // value:()Ljava/lang/Object;
  #110 = Methodref          #2.#109       // org/sireum/Some.value:()Ljava/lang/Object;
  #111 = Utf8               escape
  #112 = Utf8               (Ljava/lang/Object;)Ljava/lang/String;
  #113 = NameAndType        #111:#112     // escape:(Ljava/lang/Object;)Ljava/lang/String;
  #114 = Methodref          #105.#113     // org/sireum/String$.escape:(Ljava/lang/Object;)Ljava/lang/String;
  #115 = NameAndType        #81:#82       // toString:()Ljava/lang/String;
  #116 = Methodref          #90.#115      // java/lang/StringBuilder.toString:()Ljava/lang/String;
  #117 = Utf8               sb
  #118 = Utf8               Ljava/lang/StringBuilder;
  #119 = Utf8               java/lang/String
  #120 = Class              #119          // java/lang/String
  #121 = Utf8               string
  #122 = Methodref          #2.#115       // org/sireum/Some.toString:()Ljava/lang/String;
  #123 = Utf8               apply
  #124 = Utf8               (Ljava/lang/String;)Ljava/lang/String;
  #125 = NameAndType        #123:#124     // apply:(Ljava/lang/String;)Ljava/lang/String;
  #126 = Methodref          #105.#125     // org/sireum/String$.apply:(Ljava/lang/String;)Ljava/lang/String;
  #127 = Utf8               hashCode$lzycompute
  #128 = Utf8               ()I
  #129 = NameAndType        #25:#26       // bitmap$0:B
  #130 = Fieldref           #2.#129       // org/sireum/Some.bitmap$0:B
  #131 = NameAndType        #57:#58       // $hasEquals:()Z
  #132 = Methodref          #2.#131       // org/sireum/Some.$hasEquals:()Z
  #133 = NameAndType        #17:#128      // hashCode:()I
  #134 = Methodref          #5.#133       // java/lang/Object.hashCode:()I
  #135 = Utf8               scala/package$
  #136 = Class              #135          // scala/package$
  #137 = Utf8               Lscala/package$;
  #138 = NameAndType        #33:#137      // MODULE$:Lscala/package$;
  #139 = Fieldref           #136.#138     // scala/package$.MODULE$:Lscala/package$;
  #140 = Utf8               Seq
  #141 = Utf8               ()Lscala/collection/immutable/Seq$;
  #142 = NameAndType        #140:#141     // Seq:()Lscala/collection/immutable/Seq$;
  #143 = Methodref          #136.#142     // scala/package$.Seq:()Lscala/collection/immutable/Seq$;
  #144 = Utf8               scala/runtime/ScalaRunTime$
  #145 = Class              #144          // scala/runtime/ScalaRunTime$
  #146 = Utf8               Lscala/runtime/ScalaRunTime$;
  #147 = NameAndType        #33:#146      // MODULE$:Lscala/runtime/ScalaRunTime$;
  #148 = Fieldref           #145.#147     // scala/runtime/ScalaRunTime$.MODULE$:Lscala/runtime/ScalaRunTime$;
  #149 = Utf8               getClass
  #150 = Utf8               ()Ljava/lang/Class;
  #151 = NameAndType        #149:#150     // getClass:()Ljava/lang/Class;
  #152 = Methodref          #2.#151       // org/sireum/Some.getClass:()Ljava/lang/Class;
  #153 = Utf8               java/lang/Class
  #154 = Class              #153          // java/lang/Class
  #155 = Utf8               getName
  #156 = NameAndType        #155:#82      // getName:()Ljava/lang/String;
  #157 = Methodref          #154.#156     // java/lang/Class.getName:()Ljava/lang/String;
  #158 = Utf8               genericWrapArray
  #159 = Utf8               (Ljava/lang/Object;)Lscala/collection/immutable/ArraySeq;
  #160 = NameAndType        #158:#159     // genericWrapArray:(Ljava/lang/Object;)Lscala/collection/immutable/ArraySeq;
  #161 = Methodref          #145.#160     // scala/runtime/ScalaRunTime$.genericWrapArray:(Ljava/lang/Object;)Lscala/collection/immutable/ArraySeq;
  #162 = Utf8               scala/collection/immutable/Seq$
  #163 = Class              #162          // scala/collection/immutable/Seq$
  #164 = Utf8               (Lscala/collection/immutable/Seq;)Lscala/collection/SeqOps;
  #165 = NameAndType        #123:#164     // apply:(Lscala/collection/immutable/Seq;)Lscala/collection/SeqOps;
  #166 = Methodref          #163.#165     // scala/collection/immutable/Seq$.apply:(Lscala/collection/immutable/Seq;)Lscala/collection/SeqOps;
  #167 = Utf8               scala/collection/Seq
  #168 = Class              #167          // scala/collection/Seq
  #169 = InterfaceMethodref #168.#133     // scala/collection/Seq.hashCode:()I
  #170 = NameAndType        #17:#18       // hashCode:I
  #171 = Fieldref           #2.#170       // org/sireum/Some.hashCode:I
  #172 = Utf8               java/lang/Throwable
  #173 = Class              #172          // java/lang/Throwable
  #174 = NameAndType        #127:#128     // hashCode$lzycompute:()I
  #175 = Methodref          #2.#174       // org/sireum/Some.hashCode$lzycompute:()I
  #176 = Utf8               equals
  #177 = Utf8               (Ljava/lang/Object;)Z
  #178 = NameAndType        #176:#177     // equals:(Ljava/lang/Object;)Z
  #179 = Methodref          #5.#178       // java/lang/Object.equals:(Ljava/lang/Object;)Z
  #180 = Methodref          #2.#133       // org/sireum/Some.hashCode:()I
  #181 = Utf8               scala/runtime/BoxesRunTime
  #182 = Class              #181          // scala/runtime/BoxesRunTime
  #183 = Utf8               (Ljava/lang/Object;Ljava/lang/Object;)Z
  #184 = NameAndType        #176:#183     // equals:(Ljava/lang/Object;Ljava/lang/Object;)Z
  #185 = Methodref          #182.#184     // scala/runtime/BoxesRunTime.equals:(Ljava/lang/Object;Ljava/lang/Object;)Z
  #186 = Utf8               (Ljava/lang/Object;)Lorg/sireum/Some;
  #187 = Utf8               (TT;)Lorg/sireum/Some<TT;>;
  #188 = Utf8               (Ljava/lang/Object;)V
  #189 = NameAndType        #91:#188      // "<init>":(Ljava/lang/Object;)V
  #190 = Methodref          #2.#189       // org/sireum/Some."<init>":(Ljava/lang/Object;)V
  #191 = Utf8               apply$default$1
  #192 = Utf8               $content$lzycompute
  #193 = Utf8               ()Lscala/collection/immutable/Seq;
  #194 = Utf8               ()Lscala/collection/immutable/Seq<Lscala/Tuple2<Ljava/lang/String;Ljava/lang/Object;>;>;
  #195 = Utf8               scala/Tuple2
  #196 = Class              #195          // scala/Tuple2
  #197 = Utf8               type
  #198 = String             #197          // type
  #199 = Utf8               List
  #200 = Utf8               ()Lscala/collection/immutable/List$;
  #201 = NameAndType        #199:#200     // List:()Lscala/collection/immutable/List$;
  #202 = Methodref          #136.#201     // scala/package$.List:()Lscala/collection/immutable/List$;
  #203 = Utf8               org
  #204 = String             #203          // org
  #205 = Utf8               sireum
  #206 = String             #205          // sireum
  #207 = Utf8               [Ljava/lang/Object;
  #208 = Class              #207          // "[Ljava/lang/Object;"
  #209 = Utf8               wrapRefArray
  #210 = Utf8               ([Ljava/lang/Object;)Lscala/collection/immutable/ArraySeq;
  #211 = NameAndType        #209:#210     // wrapRefArray:([Ljava/lang/Object;)Lscala/collection/immutable/ArraySeq;
  #212 = Methodref          #145.#211     // scala/runtime/ScalaRunTime$.wrapRefArray:([Ljava/lang/Object;)Lscala/collection/immutable/ArraySeq;
  #213 = Utf8               scala/collection/immutable/List$
  #214 = Class              #213          // scala/collection/immutable/List$
  #215 = Utf8               (Lscala/collection/immutable/Seq;)Ljava/lang/Object;
  #216 = NameAndType        #123:#215     // apply:(Lscala/collection/immutable/Seq;)Ljava/lang/Object;
  #217 = Methodref          #214.#216     // scala/collection/immutable/List$.apply:(Lscala/collection/immutable/Seq;)Ljava/lang/Object;
  #218 = Utf8               (Ljava/lang/Object;Ljava/lang/Object;)V
  #219 = NameAndType        #91:#218      // "<init>":(Ljava/lang/Object;Ljava/lang/Object;)V
  #220 = Methodref          #196.#219     // scala/Tuple2."<init>":(Ljava/lang/Object;Ljava/lang/Object;)V
  #221 = String             #75           // value
  #222 = Utf8               scala/collection/immutable/Seq
  #223 = Class              #222          // scala/collection/immutable/Seq
  #224 = NameAndType        #19:#20       // $content:Lscala/collection/immutable/Seq;
  #225 = Fieldref           #2.#224       // org/sireum/Some.$content:Lscala/collection/immutable/Seq;
  #226 = NameAndType        #192:#193     // $content$lzycompute:()Lscala/collection/immutable/Seq;
  #227 = Methodref          #2.#226       // org/sireum/Some.$content$lzycompute:()Lscala/collection/immutable/Seq;
  #228 = Utf8               isEmpty
  #229 = Utf8               scala/runtime/BoxedUnit
  #230 = Class              #229          // scala/runtime/BoxedUnit
  #231 = Utf8               UNIT
  #232 = Utf8               Lscala/runtime/BoxedUnit;
  #233 = NameAndType        #231:#232     // UNIT:Lscala/runtime/BoxedUnit;
  #234 = Fieldref           #230.#233     // scala/runtime/BoxedUnit.UNIT:Lscala/runtime/BoxedUnit;
  #235 = Utf8               org/sireum/package$
  #236 = Class              #235          // org/sireum/package$
  #237 = Utf8               Lorg/sireum/package$;
  #238 = NameAndType        #33:#237      // MODULE$:Lorg/sireum/package$;
  #239 = Fieldref           #236.#238     // org/sireum/package$.MODULE$:Lorg/sireum/package$;
  #240 = Utf8               F
  #241 = NameAndType        #240:#58      // F:()Z
  #242 = Methodref          #236.#241     // org/sireum/package$.F:()Z
  #243 = Utf8               nonEmpty
  #244 = Utf8               T
  #245 = NameAndType        #244:#58      // T:()Z
  #246 = Methodref          #236.#245     // org/sireum/package$.T:()Z
  #247 = Utf8               map
  #248 = Utf8               (Lscala/Function1;)Lorg/sireum/Option;
  #249 = Utf8               <T2:Ljava/lang/Object;>(Lscala/Function1<TT;TT2;>;)Lorg/sireum/Option<TT2;>;
  #250 = Utf8               f
  #251 = Utf8               scala/Function1
  #252 = Class              #251          // scala/Function1
  #253 = Utf8               (Ljava/lang/Object;)Ljava/lang/Object;
  #254 = NameAndType        #123:#253     // apply:(Ljava/lang/Object;)Ljava/lang/Object;
  #255 = InterfaceMethodref #252.#254     // scala/Function1.apply:(Ljava/lang/Object;)Ljava/lang/Object;
  #256 = NameAndType        #123:#186     // apply:(Ljava/lang/Object;)Lorg/sireum/Some;
  #257 = Methodref          #32.#256      // org/sireum/Some$.apply:(Ljava/lang/Object;)Lorg/sireum/Some;
  #258 = Utf8               Lscala/Function1;
  #259 = Utf8               flatMap
  #260 = Utf8               <T2:Ljava/lang/Object;>(Lscala/Function1<TT;Lorg/sireum/Option<TT2;>;>;)Lorg/sireum/Option<TT2;>;
  #261 = Utf8               forall
  #262 = Utf8               (Lscala/Function1;)Z
  #263 = Utf8               (Lscala/Function1<TT;Lorg/sireum/B;>;)Z
  #264 = Utf8               org/sireum/B
  #265 = Class              #264          // org/sireum/B
  #266 = NameAndType        #75:#58       // value:()Z
  #267 = Methodref          #265.#266     // org/sireum/B.value:()Z
  #268 = Utf8               exists
  #269 = Utf8               getOrElse
  #270 = Utf8               (Lscala/Function0;)Ljava/lang/Object;
  #271 = Utf8               (Lscala/Function0<TT;>;)TT;
  #272 = Utf8               default
  #273 = Utf8               Lscala/Function0;
  #274 = Utf8               getOrElseEager
  #275 = Utf8               (TT;)TT;
  #276 = Utf8               get
  #277 = Utf8               toIS
  #278 = Utf8               ()Lorg/sireum/IS;
  #279 = Utf8               ()Lorg/sireum/IS<Lorg/sireum/Z;TT;>;
  #280 = Utf8               ISZ
  #281 = Utf8               ()Lorg/sireum/$internal/PackageTrait$ISZ$;
  #282 = NameAndType        #280:#281     // ISZ:()Lorg/sireum/$internal/PackageTrait$ISZ$;
  #283 = Methodref          #236.#282     // org/sireum/package$.ISZ:()Lorg/sireum/$internal/PackageTrait$ISZ$;
  #284 = Utf8               (Lscala/collection/immutable/Seq;)Lorg/sireum/IS;
  #285 = NameAndType        #123:#284     // apply:(Lscala/collection/immutable/Seq;)Lorg/sireum/IS;
  #286 = Methodref          #13.#285      // org/sireum/$internal/PackageTrait$ISZ$.apply:(Lscala/collection/immutable/Seq;)Lorg/sireum/IS;
  #287 = Utf8               foreach
  #288 = Utf8               (Lscala/Function1;)V
  #289 = Utf8               <V:Ljava/lang/Object;>(Lscala/Function1<TT;TV;>;)V
  #290 = NameAndType        #67:#68       // $clone:()Lorg/sireum/$internal/ImmutableMarker;
  #291 = Methodref          #2.#290       // org/sireum/Some.$clone:()Lorg/sireum/$internal/ImmutableMarker;
  #292 = Utf8               (TT;)V
  #293 = Utf8               __value
  #294 = Methodref          #5.#93        // java/lang/Object."<init>":()V
  #295 = Utf8               $init$
  #296 = Utf8               (Lorg/sireum/$internal/ImmutableMarker;)V
  #297 = NameAndType        #295:#296     // $init$:(Lorg/sireum/$internal/ImmutableMarker;)V
  #298 = InterfaceMethodref #70.#297      // org/sireum/$internal/ImmutableMarker.$init$:(Lorg/sireum/$internal/ImmutableMarker;)V
  #299 = Utf8               (Lorg/sireum/Immutable;)V
  #300 = NameAndType        #295:#299     // $init$:(Lorg/sireum/Immutable;)V
  #301 = InterfaceMethodref #52.#300      // org/sireum/Immutable.$init$:(Lorg/sireum/Immutable;)V
  #302 = Utf8               (Lorg/sireum/DatatypeSig;)V
  #303 = NameAndType        #295:#302     // $init$:(Lorg/sireum/DatatypeSig;)V
  #304 = InterfaceMethodref #43.#303      // org/sireum/DatatypeSig.$init$:(Lorg/sireum/DatatypeSig;)V
  #305 = Utf8               (Lorg/sireum/Option;)V
  #306 = NameAndType        #295:#305     // $init$:(Lorg/sireum/Option;)V
  #307 = InterfaceMethodref #7.#306       // org/sireum/Option.$init$:(Lorg/sireum/Option;)V
  #308 = Utf8               Signature
  #309 = Utf8               Code
  #310 = Utf8               LocalVariableTable
  #311 = Utf8               MethodParameters
  #312 = Utf8               LineNumberTable
  #313 = Utf8               StackMapTable
  #314 = Utf8               InnerClasses
  #315 = Utf8               SourceFile
  #316 = Utf8               RuntimeVisibleAnnotations
  #317 = Utf8               ScalaInlineInfo
  #318 = Utf8               ScalaSig
{
  private int hashCode;
    descriptor: I
    flags: (0x0002) ACC_PRIVATE

  private scala.collection.immutable.Seq<scala.Tuple2<java.lang.String, java.lang.Object>> $content;
    descriptor: Lscala/collection/immutable/Seq;
    flags: (0x0002) ACC_PRIVATE
    Signature: #21                          // Lscala/collection/immutable/Seq<Lscala/Tuple2<Ljava/lang/String;Ljava/lang/Object;>;>;

  private final T _value;
    descriptor: Ljava/lang/Object;
    flags: (0x0012) ACC_PRIVATE, ACC_FINAL
    Signature: #24                          // TT;

  private volatile byte bitmap$0;
    descriptor: B
    flags: (0x0042) ACC_PRIVATE, ACC_VOLATILE

  public static <T extends java.lang.Object> scala.Some<T> unapply(org.sireum.Some<T>);
    descriptor: (Lorg/sireum/Some;)Lscala/Some;
    flags: (0x0009) ACC_PUBLIC, ACC_STATIC
    Code:
      stack=2, locals=1, args_size=1
         0: getstatic     #36                 // Field org/sireum/Some$.MODULE$:Lorg/sireum/Some$;
         3: aload_0
         4: invokevirtual #38                 // Method org/sireum/Some$.unapply:(Lorg/sireum/Some;)Lscala/Some;
         7: areturn
      LocalVariableTable:
        Start  Length  Slot  Name   Signature
            0       8     0     o   Lorg/sireum/Some;
    Signature: #29                          // <T:Ljava/lang/Object;>(Lorg/sireum/Some<TT;>;)Lscala/Some<TT;>;
    MethodParameters:
      Name                           Flags
      o                              final

  public org.sireum.Z hash();
    descriptor: ()Lorg/sireum/Z;
    flags: (0x0001) ACC_PUBLIC
    Code:
      stack=1, locals=1, args_size=1
         0: aload_0
         1: invokestatic  #47                 // InterfaceMethod org/sireum/DatatypeSig.hash$:(Lorg/sireum/DatatypeSig;)Lorg/sireum/Z;
         4: areturn
      LineNumberTable:
        line 200: 0
      LocalVariableTable:
        Start  Length  Slot  Name   Signature
            0       5     0  this   Lorg/sireum/Some;

  public final scala.runtime.Nothing$ $cannotMixImmutableAndMutable();
    descriptor: ()Lscala/runtime/Nothing$;
    flags: (0x0011) ACC_PUBLIC, ACC_FINAL
    Code:
      stack=1, locals=1, args_size=1
         0: aload_0
         1: invokestatic  #56                 // InterfaceMethod org/sireum/Immutable.$cannotMixImmutableAndMutable$:(Lorg/sireum/Immutable;)Lscala/runtime/Nothing$;
         4: areturn
      LineNumberTable:
        line 200: 0
      LocalVariableTable:
        Start  Length  Slot  Name   Signature
            0       5     0  this   Lorg/sireum/Some;

  public boolean $hasEquals();
    descriptor: ()Z
    flags: (0x0001) ACC_PUBLIC
    Code:
      stack=1, locals=1, args_size=1
         0: aload_0
         1: invokestatic  #62                 // InterfaceMethod org/sireum/Immutable.$hasEquals$:(Lorg/sireum/Immutable;)Z
         4: ireturn
      LineNumberTable:
        line 200: 0
      LocalVariableTable:
        Start  Length  Slot  Name   Signature
            0       5     0  this   Lorg/sireum/Some;

  public boolean $hasString();
    descriptor: ()Z
    flags: (0x0001) ACC_PUBLIC
    Code:
      stack=1, locals=1, args_size=1
         0: aload_0
         1: invokestatic  #66                 // InterfaceMethod org/sireum/Immutable.$hasString$:(Lorg/sireum/Immutable;)Z
         4: ireturn
      LineNumberTable:
        line 200: 0
      LocalVariableTable:
        Start  Length  Slot  Name   Signature
            0       5     0  this   Lorg/sireum/Some;

  public org.sireum.$internal.ImmutableMarker $clone();
    descriptor: ()Lorg/sireum/$internal/ImmutableMarker;
    flags: (0x0001) ACC_PUBLIC
    Code:
      stack=1, locals=1, args_size=1
         0: aload_0
         1: invokestatic  #74                 // InterfaceMethod org/sireum/$internal/ImmutableMarker.$clone$:(Lorg/sireum/$internal/ImmutableMarker;)Lorg/sireum/$internal/ImmutableMarker;
         4: areturn
      LineNumberTable:
        line 200: 0
      LocalVariableTable:
        Start  Length  Slot  Name   Signature
            0       5     0  this   Lorg/sireum/Some;

  public T value();
    descriptor: ()Ljava/lang/Object;
    flags: (0x0001) ACC_PUBLIC
    Code:
      stack=1, locals=1, args_size=1
         0: aload_0
         1: getfield      #79                 // Field _value:Ljava/lang/Object;
         4: areturn
      LineNumberTable:
        line 200: 0
      LocalVariableTable:
        Start  Length  Slot  Name   Signature
            0       5     0  this   Lorg/sireum/Some;
    Signature: #77                          // ()TT;

  public T getValue();
    descriptor: ()Ljava/lang/Object;
    flags: (0x0001) ACC_PUBLIC
    Code:
      stack=1, locals=1, args_size=1
         0: aload_0
         1: getfield      #79                 // Field _value:Ljava/lang/Object;
         4: areturn
      LineNumberTable:
        line 200: 0
      LocalVariableTable:
        Start  Length  Slot  Name   Signature
            0       5     0  this   Lorg/sireum/Some;
    Signature: #77                          // ()TT;

  public java.lang.String toString();
    descriptor: ()Ljava/lang/String;
    flags: (0x0001) ACC_PUBLIC
    Code:
      stack=3, locals=2, args_size=1
         0: aload_0
         1: invokevirtual #84                 // Method $hasString:()Z
         4: ifeq          14
         7: aload_0
         8: invokestatic  #88                 // InterfaceMethod org/sireum/DatatypeSig.string$:(Lorg/sireum/DatatypeSig;)Ljava/lang/String;
        11: goto          62
        14: new           #90                 // class java/lang/StringBuilder
        17: dup
        18: invokespecial #94                 // Method java/lang/StringBuilder."<init>":()V
        21: astore_1
        22: aload_1
        23: ldc           #96                 // String Some
        25: invokevirtual #100                // Method java/lang/StringBuilder.append:(Ljava/lang/String;)Ljava/lang/StringBuilder;
        28: pop
        29: aload_1
        30: bipush        40
        32: invokevirtual #103                // Method java/lang/StringBuilder.append:(C)Ljava/lang/StringBuilder;
        35: pop
        36: aload_1
        37: getstatic     #108                // Field org/sireum/String$.MODULE$:Lorg/sireum/String$;
        40: aload_0
        41: invokevirtual #110                // Method value:()Ljava/lang/Object;
        44: invokevirtual #114                // Method org/sireum/String$.escape:(Ljava/lang/Object;)Ljava/lang/String;
        47: invokevirtual #100                // Method java/lang/StringBuilder.append:(Ljava/lang/String;)Ljava/lang/StringBuilder;
        50: pop
        51: aload_1
        52: bipush        41
        54: invokevirtual #103                // Method java/lang/StringBuilder.append:(C)Ljava/lang/StringBuilder;
        57: pop
        58: aload_1
        59: invokevirtual #116                // Method java/lang/StringBuilder.toString:()Ljava/lang/String;
        62: areturn
      StackMapTable: number_of_entries = 2
        frame_type = 14 /* same */
        frame_type = 111 /* same_locals_1_stack_item */
          stack = [ class java/lang/String ]
      LineNumberTable:
        line 200: 0
      LocalVariableTable:
        Start  Length  Slot  Name   Signature
           22      40     1    sb   Ljava/lang/StringBuilder;
            0      63     0  this   Lorg/sireum/Some;

  public java.lang.String string();
    descriptor: ()Ljava/lang/String;
    flags: (0x0001) ACC_PUBLIC
    Code:
      stack=2, locals=1, args_size=1
         0: aload_0
         1: invokevirtual #84                 // Method $hasString:()Z
         4: ifeq          14
         7: aload_0
         8: invokestatic  #88                 // InterfaceMethod org/sireum/DatatypeSig.string$:(Lorg/sireum/DatatypeSig;)Ljava/lang/String;
        11: goto          24
        14: getstatic     #108                // Field org/sireum/String$.MODULE$:Lorg/sireum/String$;
        17: aload_0
        18: invokevirtual #122                // Method toString:()Ljava/lang/String;
        21: invokevirtual #126                // Method org/sireum/String$.apply:(Ljava/lang/String;)Ljava/lang/String;
        24: areturn
      StackMapTable: number_of_entries = 2
        frame_type = 14 /* same */
        frame_type = 73 /* same_locals_1_stack_item */
          stack = [ class java/lang/String ]
      LineNumberTable:
        line 200: 0
      LocalVariableTable:
        Start  Length  Slot  Name   Signature
            0      25     0  this   Lorg/sireum/Some;

  private int hashCode$lzycompute();
    descriptor: ()I
    flags: (0x0002) ACC_PRIVATE
    Code:
      stack=7, locals=2, args_size=1
         0: aload_0
         1: dup
         2: astore_1
         3: monitorenter
         4: aload_0
         5: getfield      #130                // Field bitmap$0:B
         8: iconst_1
         9: iand
        10: i2b
        11: iconst_0
        12: if_icmpne     88
        15: aload_0
        16: aload_0
        17: invokevirtual #132                // Method $hasEquals:()Z
        20: ifeq          30
        23: aload_0
        24: invokespecial #134                // Method java/lang/Object.hashCode:()I
        27: goto          74
        30: getstatic     #139                // Field scala/package$.MODULE$:Lscala/package$;
        33: invokevirtual #143                // Method scala/package$.Seq:()Lscala/collection/immutable/Seq$;
        36: getstatic     #148                // Field scala/runtime/ScalaRunTime$.MODULE$:Lscala/runtime/ScalaRunTime$;
        39: iconst_2
        40: anewarray     #5                  // class java/lang/Object
        43: dup
        44: iconst_0
        45: aload_0
        46: invokevirtual #152                // Method getClass:()Ljava/lang/Class;
        49: invokevirtual #157                // Method java/lang/Class.getName:()Ljava/lang/String;
        52: aastore
        53: dup
        54: iconst_1
        55: aload_0
        56: invokevirtual #110                // Method value:()Ljava/lang/Object;
        59: aastore
        60: invokevirtual #161                // Method scala/runtime/ScalaRunTime$.genericWrapArray:(Ljava/lang/Object;)Lscala/collection/immutable/ArraySeq;
        63: invokevirtual #166                // Method scala/collection/immutable/Seq$.apply:(Lscala/collection/immutable/Seq;)Lscala/collection/SeqOps;
        66: checkcast     #168                // class scala/collection/Seq
        69: invokeinterface #169,  1          // InterfaceMethod scala/collection/Seq.hashCode:()I
        74: putfield      #171                // Field hashCode:I
        77: aload_0
        78: aload_0
        79: getfield      #130                // Field bitmap$0:B
        82: iconst_1
        83: ior
        84: i2b
        85: putfield      #130                // Field bitmap$0:B
        88: aload_1
        89: monitorexit
        90: goto          96
        93: aload_1
        94: monitorexit
        95: athrow
        96: aload_0
        97: getfield      #171                // Field hashCode:I
       100: ireturn
      Exception table:
         from    to  target type
             4    88    93   any
      StackMapTable: number_of_entries = 5
        frame_type = 255 /* full_frame */
          offset_delta = 30
          locals = [ class org/sireum/Some, class org/sireum/Some ]
          stack = [ class org/sireum/Some ]
        frame_type = 255 /* full_frame */
          offset_delta = 43
          locals = [ class org/sireum/Some, class org/sireum/Some ]
          stack = [ class org/sireum/Some, int ]
        frame_type = 13 /* same */
        frame_type = 68 /* same_locals_1_stack_item */
          stack = [ class java/lang/Throwable ]
        frame_type = 2 /* same */
      LineNumberTable:
        line 200: 0
      LocalVariableTable:
        Start  Length  Slot  Name   Signature
            0     101     0  this   Lorg/sireum/Some;

  public int hashCode();
    descriptor: ()I
    flags: (0x0001) ACC_PUBLIC
    Code:
      stack=2, locals=1, args_size=1
         0: aload_0
         1: getfield      #130                // Field bitmap$0:B
         4: iconst_1
         5: iand
         6: i2b
         7: iconst_0
         8: if_icmpne     18
        11: aload_0
        12: invokespecial #175                // Method hashCode$lzycompute:()I
        15: goto          22
        18: aload_0
        19: getfield      #171                // Field hashCode:I
        22: ireturn
      StackMapTable: number_of_entries = 2
        frame_type = 18 /* same */
        frame_type = 67 /* same_locals_1_stack_item */
          stack = [ int ]
      LineNumberTable:
        line 200: 0
      LocalVariableTable:
        Start  Length  Slot  Name   Signature
            0      23     0  this   Lorg/sireum/Some;

  public boolean equals(java.lang.Object);
    descriptor: (Ljava/lang/Object;)Z
    flags: (0x0001) ACC_PUBLIC
    Code:
      stack=2, locals=5, args_size=2
         0: aload_0
         1: invokevirtual #132                // Method $hasEquals:()Z
         4: ifeq          15
         7: aload_0
         8: aload_1
         9: invokespecial #179                // Method java/lang/Object.equals:(Ljava/lang/Object;)Z
        12: goto          88
        15: aload_0
        16: aload_1
        17: if_acmpne     24
        20: iconst_1
        21: goto          88
        24: aload_1
        25: astore_3
        26: aload_3
        27: instanceof    #2                  // class org/sireum/Some
        30: ifeq          79
        33: aload_3
        34: checkcast     #2                  // class org/sireum/Some
        37: astore        4
        39: aload_0
        40: invokevirtual #180                // Method hashCode:()I
        43: aload         4
        45: invokevirtual #180                // Method hashCode:()I
        48: if_icmpeq     55
        51: iconst_0
        52: goto          75
        55: aload_0
        56: invokevirtual #110                // Method value:()Ljava/lang/Object;
        59: aload         4
        61: invokevirtual #110                // Method value:()Ljava/lang/Object;
        64: invokestatic  #185                // Method scala/runtime/BoxesRunTime.equals:(Ljava/lang/Object;Ljava/lang/Object;)Z
        67: ifeq          74
        70: iconst_1
        71: goto          75
        74: iconst_0
        75: istore_2
        76: goto          87
        79: goto          82
        82: iconst_0
        83: istore_2
        84: goto          87
        87: iload_2
        88: ireturn
      StackMapTable: number_of_entries = 9
        frame_type = 15 /* same */
        frame_type = 8 /* same */
        frame_type = 254 /* append */
          offset_delta = 30
          locals = [ top, class java/lang/Object, class org/sireum/Some ]
        frame_type = 18 /* same */
        frame_type = 64 /* same_locals_1_stack_item */
          stack = [ int ]
        frame_type = 250 /* chop */
          offset_delta = 3
        frame_type = 2 /* same */
        frame_type = 255 /* full_frame */
          offset_delta = 4
          locals = [ class org/sireum/Some, class java/lang/Object, int, class java/lang/Object ]
          stack = []
        frame_type = 255 /* full_frame */
          offset_delta = 0
          locals = [ class org/sireum/Some, class java/lang/Object ]
          stack = [ int ]
      LineNumberTable:
        line 200: 0
      LocalVariableTable:
        Start  Length  Slot  Name   Signature
            0      89     0  this   Lorg/sireum/Some;
            0      89     1     o   Ljava/lang/Object;
    MethodParameters:
      Name                           Flags
      o                              final

  public org.sireum.Some<T> apply(T);
    descriptor: (Ljava/lang/Object;)Lorg/sireum/Some;
    flags: (0x0001) ACC_PUBLIC
    Code:
      stack=3, locals=2, args_size=2
         0: new           #2                  // class org/sireum/Some
         3: dup
         4: aload_1
         5: invokespecial #190                // Method "<init>":(Ljava/lang/Object;)V
         8: areturn
      LineNumberTable:
        line 200: 0
      LocalVariableTable:
        Start  Length  Slot  Name   Signature
            0       9     0  this   Lorg/sireum/Some;
            0       9     1 value   Ljava/lang/Object;
    Signature: #187                         // (TT;)Lorg/sireum/Some<TT;>;
    MethodParameters:
      Name                           Flags
      value                          final

  public T apply$default$1();
    descriptor: ()Ljava/lang/Object;
    flags: (0x0001) ACC_PUBLIC
    Code:
      stack=1, locals=1, args_size=1
         0: aload_0
         1: invokevirtual #110                // Method value:()Ljava/lang/Object;
         4: areturn
      LineNumberTable:
        line 200: 0
      LocalVariableTable:
        Start  Length  Slot  Name   Signature
            0       5     0  this   Lorg/sireum/Some;
    Signature: #77                          // ()TT;

  private scala.collection.immutable.Seq<scala.Tuple2<java.lang.String, java.lang.Object>> $content$lzycompute();
    descriptor: ()Lscala/collection/immutable/Seq;
    flags: (0x0002) ACC_PRIVATE
    Code:
      stack=15, locals=2, args_size=1
         0: aload_0
         1: dup
         2: astore_1
         3: monitorenter
         4: aload_0
         5: getfield      #130                // Field bitmap$0:B
         8: iconst_2
         9: iand
        10: i2b
        11: iconst_0
        12: if_icmpne     120
        15: aload_0
        16: getstatic     #139                // Field scala/package$.MODULE$:Lscala/package$;
        19: invokevirtual #143                // Method scala/package$.Seq:()Lscala/collection/immutable/Seq$;
        22: getstatic     #148                // Field scala/runtime/ScalaRunTime$.MODULE$:Lscala/runtime/ScalaRunTime$;
        25: iconst_2
        26: anewarray     #196                // class scala/Tuple2
        29: dup
        30: iconst_0
        31: new           #196                // class scala/Tuple2
        34: dup
        35: ldc           #198                // String type
        37: getstatic     #139                // Field scala/package$.MODULE$:Lscala/package$;
        40: invokevirtual #202                // Method scala/package$.List:()Lscala/collection/immutable/List$;
        43: getstatic     #148                // Field scala/runtime/ScalaRunTime$.MODULE$:Lscala/runtime/ScalaRunTime$;
        46: iconst_3
        47: anewarray     #120                // class java/lang/String
        50: dup
        51: iconst_0
        52: ldc           #204                // String org
        54: aastore
        55: dup
        56: iconst_1
        57: ldc           #206                // String sireum
        59: aastore
        60: dup
        61: iconst_2
        62: ldc           #96                 // String Some
        64: aastore
        65: checkcast     #208                // class "[Ljava/lang/Object;"
        68: invokevirtual #212                // Method scala/runtime/ScalaRunTime$.wrapRefArray:([Ljava/lang/Object;)Lscala/collection/immutable/ArraySeq;
        71: invokevirtual #217                // Method scala/collection/immutable/List$.apply:(Lscala/collection/immutable/Seq;)Ljava/lang/Object;
        74: invokespecial #220                // Method scala/Tuple2."<init>":(Ljava/lang/Object;Ljava/lang/Object;)V
        77: aastore
        78: dup
        79: iconst_1
        80: new           #196                // class scala/Tuple2
        83: dup
        84: ldc           #221                // String value
        86: aload_0
        87: invokevirtual #110                // Method value:()Ljava/lang/Object;
        90: invokespecial #220                // Method scala/Tuple2."<init>":(Ljava/lang/Object;Ljava/lang/Object;)V
        93: aastore
        94: checkcast     #208                // class "[Ljava/lang/Object;"
        97: invokevirtual #212                // Method scala/runtime/ScalaRunTime$.wrapRefArray:([Ljava/lang/Object;)Lscala/collection/immutable/ArraySeq;
       100: invokevirtual #166                // Method scala/collection/immutable/Seq$.apply:(Lscala/collection/immutable/Seq;)Lscala/collection/SeqOps;
       103: checkcast     #223                // class scala/collection/immutable/Seq
       106: putfield      #225                // Field $content:Lscala/collection/immutable/Seq;
       109: aload_0
       110: aload_0
       111: getfield      #130                // Field bitmap$0:B
       114: iconst_2
       115: ior
       116: i2b
       117: putfield      #130                // Field bitmap$0:B
       120: aload_1
       121: monitorexit
       122: goto          128
       125: aload_1
       126: monitorexit
       127: athrow
       128: aload_0
       129: getfield      #225                // Field $content:Lscala/collection/immutable/Seq;
       132: areturn
      Exception table:
         from    to  target type
             4   120   125   any
      StackMapTable: number_of_entries = 3
        frame_type = 252 /* append */
          offset_delta = 120
          locals = [ class org/sireum/Some ]
        frame_type = 68 /* same_locals_1_stack_item */
          stack = [ class java/lang/Throwable ]
        frame_type = 2 /* same */
      LineNumberTable:
        line 200: 0
      LocalVariableTable:
        Start  Length  Slot  Name   Signature
            0     133     0  this   Lorg/sireum/Some;
    Signature: #194                         // ()Lscala/collection/immutable/Seq<Lscala/Tuple2<Ljava/lang/String;Ljava/lang/Object;>;>;

  public scala.collection.immutable.Seq<scala.Tuple2<java.lang.String, java.lang.Object>> $content();
    descriptor: ()Lscala/collection/immutable/Seq;
    flags: (0x0001) ACC_PUBLIC
    Code:
      stack=2, locals=1, args_size=1
         0: aload_0
         1: getfield      #130                // Field bitmap$0:B
         4: iconst_2
         5: iand
         6: i2b
         7: iconst_0
         8: if_icmpne     18
        11: aload_0
        12: invokespecial #227                // Method $content$lzycompute:()Lscala/collection/immutable/Seq;
        15: goto          22
        18: aload_0
        19: getfield      #225                // Field $content:Lscala/collection/immutable/Seq;
        22: areturn
      StackMapTable: number_of_entries = 2
        frame_type = 18 /* same */
        frame_type = 67 /* same_locals_1_stack_item */
          stack = [ class scala/collection/immutable/Seq ]
      LineNumberTable:
        line 200: 0
      LocalVariableTable:
        Start  Length  Slot  Name   Signature
            0      23     0  this   Lorg/sireum/Some;
    Signature: #194                         // ()Lscala/collection/immutable/Seq<Lscala/Tuple2<Ljava/lang/String;Ljava/lang/Object;>;>;

  public boolean isEmpty();
    descriptor: ()Z
    flags: (0x0001) ACC_PUBLIC
    Code:
      stack=1, locals=1, args_size=1
         0: getstatic     #234                // Field scala/runtime/BoxedUnit.UNIT:Lscala/runtime/BoxedUnit;
         3: pop
         4: getstatic     #239                // Field org/sireum/package$.MODULE$:Lorg/sireum/package$;
         7: invokevirtual #242                // Method org/sireum/package$.F:()Z
        10: ireturn
      LineNumberTable:
        line 203: 0
        line 204: 4
      LocalVariableTable:
        Start  Length  Slot  Name   Signature
            0      11     0  this   Lorg/sireum/Some;

  public boolean nonEmpty();
    descriptor: ()Z
    flags: (0x0001) ACC_PUBLIC
    Code:
      stack=1, locals=1, args_size=1
         0: getstatic     #234                // Field scala/runtime/BoxedUnit.UNIT:Lscala/runtime/BoxedUnit;
         3: pop
         4: getstatic     #239                // Field org/sireum/package$.MODULE$:Lorg/sireum/package$;
         7: invokevirtual #246                // Method org/sireum/package$.T:()Z
        10: ireturn
      LineNumberTable:
        line 208: 0
        line 209: 4
      LocalVariableTable:
        Start  Length  Slot  Name   Signature
            0      11     0  this   Lorg/sireum/Some;

  public <T2 extends java.lang.Object> org.sireum.Option<T2> map(scala.Function1<T, T2>);
    descriptor: (Lscala/Function1;)Lorg/sireum/Option;
    flags: (0x0001) ACC_PUBLIC
    Code:
      stack=3, locals=2, args_size=2
         0: getstatic     #234                // Field scala/runtime/BoxedUnit.UNIT:Lscala/runtime/BoxedUnit;
         3: pop
         4: getstatic     #36                 // Field org/sireum/Some$.MODULE$:Lorg/sireum/Some$;
         7: aload_1
         8: aload_0
         9: invokevirtual #110                // Method value:()Ljava/lang/Object;
        12: invokeinterface #255,  2          // InterfaceMethod scala/Function1.apply:(Ljava/lang/Object;)Ljava/lang/Object;
        17: invokevirtual #257                // Method org/sireum/Some$.apply:(Ljava/lang/Object;)Lorg/sireum/Some;
        20: areturn
      LineNumberTable:
        line 213: 0
        line 214: 4
      LocalVariableTable:
        Start  Length  Slot  Name   Signature
            0      21     0  this   Lorg/sireum/Some;
            0      21     1     f   Lscala/Function1;
    Signature: #249                         // <T2:Ljava/lang/Object;>(Lscala/Function1<TT;TT2;>;)Lorg/sireum/Option<TT2;>;
    MethodParameters:
      Name                           Flags
      f                              final

  public <T2 extends java.lang.Object> org.sireum.Option<T2> flatMap(scala.Function1<T, org.sireum.Option<T2>>);
    descriptor: (Lscala/Function1;)Lorg/sireum/Option;
    flags: (0x0001) ACC_PUBLIC
    Code:
      stack=2, locals=2, args_size=2
         0: getstatic     #234                // Field scala/runtime/BoxedUnit.UNIT:Lscala/runtime/BoxedUnit;
         3: pop
         4: aload_1
         5: aload_0
         6: invokevirtual #110                // Method value:()Ljava/lang/Object;
         9: invokeinterface #255,  2          // InterfaceMethod scala/Function1.apply:(Ljava/lang/Object;)Ljava/lang/Object;
        14: checkcast     #7                  // class org/sireum/Option
        17: areturn
      LineNumberTable:
        line 218: 0
        line 219: 4
      LocalVariableTable:
        Start  Length  Slot  Name   Signature
            0      18     0  this   Lorg/sireum/Some;
            0      18     1     f   Lscala/Function1;
    Signature: #260                         // <T2:Ljava/lang/Object;>(Lscala/Function1<TT;Lorg/sireum/Option<TT2;>;>;)Lorg/sireum/Option<TT2;>;
    MethodParameters:
      Name                           Flags
      f                              final

  public boolean forall(scala.Function1<T, org.sireum.B>);
    descriptor: (Lscala/Function1;)Z
    flags: (0x0001) ACC_PUBLIC
    Code:
      stack=2, locals=2, args_size=2
         0: getstatic     #234                // Field scala/runtime/BoxedUnit.UNIT:Lscala/runtime/BoxedUnit;
         3: pop
         4: aload_1
         5: aload_0
         6: invokevirtual #110                // Method value:()Ljava/lang/Object;
         9: invokeinterface #255,  2          // InterfaceMethod scala/Function1.apply:(Ljava/lang/Object;)Ljava/lang/Object;
        14: checkcast     #265                // class org/sireum/B
        17: invokevirtual #267                // Method org/sireum/B.value:()Z
        20: ireturn
      LineNumberTable:
        line 223: 0
        line 224: 4
      LocalVariableTable:
        Start  Length  Slot  Name   Signature
            0      21     0  this   Lorg/sireum/Some;
            0      21     1     f   Lscala/Function1;
    Signature: #263                         // (Lscala/Function1<TT;Lorg/sireum/B;>;)Z
    MethodParameters:
      Name                           Flags
      f                              final

  public boolean exists(scala.Function1<T, org.sireum.B>);
    descriptor: (Lscala/Function1;)Z
    flags: (0x0001) ACC_PUBLIC
    Code:
      stack=2, locals=2, args_size=2
         0: getstatic     #234                // Field scala/runtime/BoxedUnit.UNIT:Lscala/runtime/BoxedUnit;
         3: pop
         4: aload_1
         5: aload_0
         6: invokevirtual #110                // Method value:()Ljava/lang/Object;
         9: invokeinterface #255,  2          // InterfaceMethod scala/Function1.apply:(Ljava/lang/Object;)Ljava/lang/Object;
        14: checkcast     #265                // class org/sireum/B
        17: invokevirtual #267                // Method org/sireum/B.value:()Z
        20: ireturn
      LineNumberTable:
        line 228: 0
        line 229: 4
      LocalVariableTable:
        Start  Length  Slot  Name   Signature
            0      21     0  this   Lorg/sireum/Some;
            0      21     1     f   Lscala/Function1;
    Signature: #263                         // (Lscala/Function1<TT;Lorg/sireum/B;>;)Z
    MethodParameters:
      Name                           Flags
      f                              final

  public T getOrElse(scala.Function0<T>);
    descriptor: (Lscala/Function0;)Ljava/lang/Object;
    flags: (0x0001) ACC_PUBLIC
    Code:
      stack=1, locals=2, args_size=2
         0: getstatic     #234                // Field scala/runtime/BoxedUnit.UNIT:Lscala/runtime/BoxedUnit;
         3: pop
         4: aload_0
         5: invokevirtual #110                // Method value:()Ljava/lang/Object;
         8: areturn
      LineNumberTable:
        line 233: 0
        line 234: 4
      LocalVariableTable:
        Start  Length  Slot  Name   Signature
            0       9     0  this   Lorg/sireum/Some;
            0       9     1 default   Lscala/Function0;
    Signature: #271                         // (Lscala/Function0<TT;>;)TT;
    MethodParameters:
      Name                           Flags
      default                        final

  public T getOrElseEager(T);
    descriptor: (Ljava/lang/Object;)Ljava/lang/Object;
    flags: (0x0001) ACC_PUBLIC
    Code:
      stack=1, locals=2, args_size=2
         0: getstatic     #234                // Field scala/runtime/BoxedUnit.UNIT:Lscala/runtime/BoxedUnit;
         3: pop
         4: aload_0
         5: invokevirtual #110                // Method value:()Ljava/lang/Object;
         8: areturn
      LineNumberTable:
        line 238: 0
        line 239: 4
      LocalVariableTable:
        Start  Length  Slot  Name   Signature
            0       9     0  this   Lorg/sireum/Some;
            0       9     1 default   Ljava/lang/Object;
    Signature: #275                         // (TT;)TT;
    MethodParameters:
      Name                           Flags
      default                        final

  public T get();
    descriptor: ()Ljava/lang/Object;
    flags: (0x0001) ACC_PUBLIC
    Code:
      stack=1, locals=1, args_size=1
         0: getstatic     #234                // Field scala/runtime/BoxedUnit.UNIT:Lscala/runtime/BoxedUnit;
         3: pop
         4: aload_0
         5: invokevirtual #110                // Method value:()Ljava/lang/Object;
         8: areturn
      LineNumberTable:
        line 243: 0
        line 244: 4
      LocalVariableTable:
        Start  Length  Slot  Name   Signature
            0       9     0  this   Lorg/sireum/Some;
    Signature: #77                          // ()TT;

  public org.sireum.IS<org.sireum.Z, T> toIS();
    descriptor: ()Lorg/sireum/IS;
    flags: (0x0001) ACC_PUBLIC
    Code:
      stack=6, locals=1, args_size=1
         0: getstatic     #234                // Field scala/runtime/BoxedUnit.UNIT:Lscala/runtime/BoxedUnit;
         3: pop
         4: getstatic     #239                // Field org/sireum/package$.MODULE$:Lorg/sireum/package$;
         7: invokevirtual #283                // Method org/sireum/package$.ISZ:()Lorg/sireum/$internal/PackageTrait$ISZ$;
        10: getstatic     #148                // Field scala/runtime/ScalaRunTime$.MODULE$:Lscala/runtime/ScalaRunTime$;
        13: iconst_1
        14: anewarray     #5                  // class java/lang/Object
        17: dup
        18: iconst_0
        19: aload_0
        20: invokevirtual #110                // Method value:()Ljava/lang/Object;
        23: aastore
        24: invokevirtual #161                // Method scala/runtime/ScalaRunTime$.genericWrapArray:(Ljava/lang/Object;)Lscala/collection/immutable/ArraySeq;
        27: invokevirtual #286                // Method org/sireum/$internal/PackageTrait$ISZ$.apply:(Lscala/collection/immutable/Seq;)Lorg/sireum/IS;
        30: areturn
      LineNumberTable:
        line 248: 0
        line 249: 4
      LocalVariableTable:
        Start  Length  Slot  Name   Signature
            0      31     0  this   Lorg/sireum/Some;
    Signature: #279                         // ()Lorg/sireum/IS<Lorg/sireum/Z;TT;>;

  public <V extends java.lang.Object> void foreach(scala.Function1<T, V>);
    descriptor: (Lscala/Function1;)V
    flags: (0x0001) ACC_PUBLIC
    Code:
      stack=2, locals=2, args_size=2
         0: aload_1
         1: aload_0
         2: invokevirtual #110                // Method value:()Ljava/lang/Object;
         5: invokeinterface #255,  2          // InterfaceMethod scala/Function1.apply:(Ljava/lang/Object;)Ljava/lang/Object;
        10: pop
        11: return
      LineNumberTable:
        line 253: 0
      LocalVariableTable:
        Start  Length  Slot  Name   Signature
            0      12     0  this   Lorg/sireum/Some;
            0      12     1     f   Lscala/Function1;
    Signature: #289                         // <V:Ljava/lang/Object;>(Lscala/Function1<TT;TV;>;)V
    MethodParameters:
      Name                           Flags
      f                              final

  public java.lang.Object $clone();
    descriptor: ()Ljava/lang/Object;
    flags: (0x1041) ACC_PUBLIC, ACC_BRIDGE, ACC_SYNTHETIC
    Code:
      stack=1, locals=1, args_size=1
         0: aload_0
         1: invokevirtual #291                // Method $clone:()Lorg/sireum/$internal/ImmutableMarker;
         4: areturn
      LineNumberTable:
        line 200: 0
      LocalVariableTable:
        Start  Length  Slot  Name   Signature
            0       5     0  this   Lorg/sireum/Some;

  public org.sireum.Some(T);
    descriptor: (Ljava/lang/Object;)V
    flags: (0x0001) ACC_PUBLIC
    Code:
      stack=2, locals=2, args_size=2
         0: aload_0
         1: invokespecial #294                // Method java/lang/Object."<init>":()V
         4: aload_0
         5: invokestatic  #298                // InterfaceMethod org/sireum/$internal/ImmutableMarker.$init$:(Lorg/sireum/$internal/ImmutableMarker;)V
         8: aload_0
         9: invokestatic  #301                // InterfaceMethod org/sireum/Immutable.$init$:(Lorg/sireum/Immutable;)V
        12: aload_0
        13: invokestatic  #304                // InterfaceMethod org/sireum/DatatypeSig.$init$:(Lorg/sireum/DatatypeSig;)V
        16: aload_0
        17: invokestatic  #307                // InterfaceMethod org/sireum/Option.$init$:(Lorg/sireum/Option;)V
        20: aload_0
        21: aload_1
        22: putfield      #79                 // Field _value:Ljava/lang/Object;
        25: return
      LineNumberTable:
        line 200: 0
      LocalVariableTable:
        Start  Length  Slot  Name   Signature
            0      26     0  this   Lorg/sireum/Some;
            0      26     1 __value   Ljava/lang/Object;
    Signature: #292                         // (TT;)V
    MethodParameters:
      Name                           Flags
      __value                        final
}
InnerClasses:
  public #16= #13 of #15;                 // ISZ$=class org/sireum/$internal/PackageTrait$ISZ$ of class org/sireum/$internal/PackageTrait
Signature: #3                           // <T:Ljava/lang/Object;>Ljava/lang/Object;Lorg/sireum/Option<TT;>;
SourceFile: "Option.scala"
RuntimeVisibleAnnotations:
  0: #9(#10=s#11)
    scala.reflect.ScalaSignature(
      bytes="\u0006\u0005\u0005=w!B\u000f\u001f\u0011\u0003\u0019c!B\u0013\u001f\u0011\u00031\u0003\"B\u0017\u0002\t\u0003q\u0003\"B\u0018\u0002\t\u0003\u0001\u0004bBA_\u0003\u0011\u0005\u0011q\u0018\u0004\u0005Ky\u00111\u0007\u0003\u0005G\u000b\t\u0005\t\u0015!\u00039\u0011\u0015iS\u0001\"\u0001H\u0011\u0019QU\u0001)A\u0005q!)1*\u0002C\u0001\u0019\")Q*\u0002C\u0001\u0019\")a*\u0002C!\u001f\")\u0001,\u0002C!3\"AA,\u0002EC\u0002\u0013\u0005S\fC\u0003b\u000b\u0011\u0005#\rC\u00030\u000b\u0011\u0005\u0001\u000eC\u0004k\u000bE\u0005I\u0011A6\t\u0011Y,\u0001R1A\u0005B]Dq!a\u0004\u0006\t\u0003\n\t\u0002C\u0004\u0002\"\u0015!\t%!\u0005\t\u000f\u0005\u0015R\u0001\"\u0011\u0002(!9\u00111I\u0003\u0005B\u0005\u0015\u0003bBA,\u000b\u0011\u0005\u0013\u0011\f\u0005\b\u0003G*A\u0011IA3\u0011\u001d\tY\'\u0002C!\u0003[Bq!a\u001f\u0006\t\u0003\ni\b\u0003\u0004\u0002\u0004\u0016!\t\u0005\u0014\u0005\b\u0003\u000f+A\u0011IAE\u0011\u001d\tI*\u0002C!\u00037\u000bAaU8nK*\u0011q\u0004I\u0001\u0007g&\u0014X-^7\u000b\u0003\u0005\n1a\u001c:h\u0007\u0001\u0001\"\u0001J\u0001\u000e\u0003y\u0011AaU8nKN\u0011\u0011a\n\t\u0003Q-j\u0011!\u000b\u0006\u0002U\u0005)1oY1mC&\u0011A&\u000b\u0002\u0007\u0003:L(+\u001a4\u0002\rqJg.\u001b;?)\u0005\u0019\u0013!B1qa2LXcA\u0019\u0002:R\u0019!\'a/\u0011\t\u0011*\u0011qW\u000b\u0003ii\u001aB!B\u00146\u0007B\u0019AE\u000e\u001d\n\u0005]r\"AB(qi&|g\u000e\u0005\u0002:u1\u0001A!B\u001e\u0006\u0005\u0004a$!\u0001+\u0012\u0005u\u0002\u0005C\u0001\u0015?\u0013\ty\u0014FA\u0004O_RD\u0017N\\4\u0011\u0005!\n\u0015B\u0001\"*\u0005\r\te.\u001f\t\u0003I\u0011K!!\u0012\u0010\u0003\u0017\u0011\u000bG/\u0019;za\u0016\u001c\u0016nZ\u0001\b?~3\u0018\r\\;f)\tA\u0015\nE\u0002%\u000baBQAR\u0004A\u0002a\naa\u0018<bYV,\u0017!\u0002<bYV,W#\u0001\u001d\u0002\u0011\u001d,GOV1mk\u0016\f\u0001\u0002^8TiJLgn\u001a\u000b\u0002!B\u0011\u0011KV\u0007\u0002%*\u00111\u000bV\u0001\u0005Y\u0006twMC\u0001V\u0003\u0011Q\u0017M^1\n\u0005]\u0013&AB*ue&tw-\u0001\u0004tiJLgnZ\u000b\u00025B\u0011AeW\u0005\u0003/z\t\u0001\u0002[1tQ\u000e{G-Z\u000b\u0002=B\u0011\u0001fX\u0005\u0003A&\u00121!\u00138u\u0003\u0019)\u0017/^1mgR\u00111M\u001a\t\u0003Q\u0011L!!Z\u0015\u0003\u000f\t{w\u000e\\3b]\")qM\u0004a\u0001\u0001\u0006\tq\u000e\u0006\u0002IS\"91j\u0004I\u0001\u0002\u0004A\u0014aD1qa2LH\u0005Z3gCVdG\u000fJ\u0019\u0016\u00031T#\u0001O7,\u00039\u0004\"a\u001c;\u000e\u0003AT!!\u001d:\u0002\u0013Ut7\r[3dW\u0016$\'BA:*\u0003)\tgN\\8uCRLwN\\\u0005\u0003kB\u0014\u0011#\u001e8dQ\u0016\u001c7.\u001a3WCJL\u0017M\\2f\u0003!!3m\u001c8uK:$X#\u0001=\u0011\u000be\f\u0019!!\u0003\u000f\u0005i|hBA>\u007f\u001b\u0005a(BA?#\u0003\u0019a$o\\8u}%\t!&C\u0002\u0002\u0002%\nq\u0001]1dW\u0006<W-\u0003\u0003\u0002\u0006\u0005\u001d!aA*fc*\u0019\u0011\u0011A\u0015\u0011\u000b!\nY\u0001\u0015!\n\u0007\u00055\u0011F\u0001\u0004UkBdWMM\u0001\bSN,U\u000e\u001d;z+\t\t\u0019\u0002E\u0002%\u0003+I1!a\u0006\u001f\u0005\u0005\u0011\u0005f\u0001\n\u0002\u001cA\u0019A%!\b\n\u0007\u0005}aD\u0001\u0003qkJ,\u0017\u0001\u00038p]\u0016k\u0007\u000f^=)\u0007M\tY\"A\u0002nCB,B!!\u000b\u00020Q!\u00111FA\u001a!\u0011!c\'!\f\u0011\u0007e\ny\u0003\u0002\u0004\u00022Q\u0011\r\u0001\u0010\u0002\u0003)JBq!!\u000e\u0015\u0001\u0004\t9$A\u0001g!\u0019A\u0013\u0011\b\u001d\u0002>%\u0019\u00111H\u0015\u0003\u0013\u0019+hn\u0019;j_:\f$\u0006BA\u0017\u0003\u007fY#!a\u0007)\u0007Q\tY\"A\u0004gY\u0006$X*\u00199\u0016\t\u0005\u001d\u0013Q\n\u000b\u0005\u0003\u0013\ny\u0005\u0005\u0003%m\u0005-\u0003cA\u001d\u0002N\u00111\u0011\u0011G\u000bC\u0002qBq!!\u000e\u0016\u0001\u0004\t\t\u0006\u0005\u0004)\u0003sA\u00141\u000b\u0016\u0005\u0003\u0013\ny\u0004K\u0002\u0016\u00037\taAZ8sC2dG\u0003BA\n\u00037Bq!!\u000e\u0017\u0001\u0004\ti\u0006\u0005\u0004)\u0003sA\u0014q\f\u0016\u0005\u0003\'\ty\u0004K\u0002\u0017\u00037\ta!\u001a=jgR\u001cH\u0003BA\n\u0003OBq!!\u000e\u0018\u0001\u0004\ti\u0006K\u0002\u0018\u00037\t\u0011bZ3u\u001fJ,En]3\u0015\u0007a\ny\u0007\u0003\u0005\u0002ra!\t\u0019AA:\u0003\u001d!WMZ1vYR\u0004B\u0001KA;q%\u0019\u0011qO\u0015\u0003\u0011q\u0012\u0017P\\1nKzB3\u0001GA\u000e\u000399W\r^(s\u000b2\u001cX-R1hKJ$2\u0001OA@\u0011\u0019\t\t(\u0007a\u0001q!\u001a\u0011$a\u0007\u0002\u0007\u001d,G\u000fK\u0002\u001b\u00037\tA\u0001^8J\'V\u0011\u00111\u0012\t\u0007I\u00055\u0015\u0011\u0013\u001d\n\u0007\u0005=eD\u0001\u0002J\'B\u0019A%a%\n\u0007\u0005UeDA\u0001[Q\rY\u00121D\u0001\bM>\u0014X-Y2i+\u0011\ti*a+\u0015\t\u0005}\u0015Q\u0015\t\u0004Q\u0005\u0005\u0016bAARS\t!QK\\5u\u0011\u001d\t)\u0004\ba\u0001\u0003O\u0003b\u0001KA\u001dq\u0005%\u0006cA\u001d\u0002,\u00121\u0011Q\u0016\u000fC\u0002q\u0012\u0011A\u0016\u0015\u0004\u000b\u0005E\u0006c\u0001\u0013\u00024&\u0019\u0011Q\u0017\u0010\u0003\u0011\u0011\fG/\u0019;za\u0016\u00042!OA]\t\u0015Y4A1\u0001=\u0011\u0019Y5\u00011\u0001\u00028\u00069QO\\1qa2LX\u0003BAa\u0003\u0013$B!a1\u0002LB)\u0001&!2\u0002H&\u0011Q%\u000b\t\u0004s\u0005%G!B\u001e\u0005\u0005\u0004a\u0004BB4\u0005\u0001\u0004\ti\r\u0005\u0003%\u000b\u0005\u001d\u0007"
    )
  ScalaInlineInfo: length = 0x95 (unknown attribute)
   01 01 00 1D 00 31 00 32 01 00 43 00 4C 01 00 43
   00 44 01 00 13 00 C1 01 00 C0 00 C1 01 00 39 00
   3A 01 00 3F 00 3A 01 00 5B 00 BC 01 00 7B 00 BA
   01 00 BF 00 4C 01 00 B0 00 B1 01 01 0C 01 06 01
   01 03 00 F8 01 01 05 01 06 01 01 1F 01 20 01 01
   14 00 4C 01 01 0D 01 0E 01 01 12 00 FD 01 00 50
   00 4C 01 00 28 00 29 01 00 11 00 80 01 00 7F 00
   80 01 00 E4 00 3A 01 00 F7 00 F8 01 00 F3 00 3A
   01 00 79 00 52 01 01 15 01 16 01 00 51 00 52 01
   00 4B 00 4C 01
  ScalaSig: length = 0x3 (unknown attribute)
   05 02 00
