Classfile /Users/mw/Projects/slang-braindump/.jar/jar8/assemble/slang-braindump/assemble/content/org/sireum/U30.class
  Last modified May 29, 2022; size 15401 bytes
  SHA-256 checksum 6440eaad63a7bfa8bfbe4f416f1d066999d5debcd2dc7dea2539b254c1640f1b
  Compiled from "BitsRangeTypes.scala"
public final class org.sireum.U30 extends java.lang.Object implements org.sireum.Z$BV$Int<org.sireum.U30>
  minor version: 0
  major version: 52
  flags: (0x0031) ACC_PUBLIC, ACC_FINAL, ACC_SUPER
  this_class: #2                          // org/sireum/U30
  super_class: #5                         // java/lang/Object
  interfaces: 1, fields: 1, methods: 93, attributes: 6
Constant pool:
    #1 = Utf8               org/sireum/U30
    #2 = Class              #1            // org/sireum/U30
    #3 = Utf8               Ljava/lang/Object;Lorg/sireum/Z$BV$Int<Lorg/sireum/U30;>;
    #4 = Utf8               java/lang/Object
    #5 = Class              #4            // java/lang/Object
    #6 = Utf8               org/sireum/Z$BV$Int
    #7 = Class              #6            // org/sireum/Z$BV$Int
    #8 = Utf8               BitsRangeTypes.scala
    #9 = Utf8               Lscala/reflect/ScalaSignature;
   #10 = Utf8               bytes
   #11 = Utf8               \u0006\u0005\r]q!\u00021b\u0011\u00031g!\u00025b\u0011\u0003I\u0007bBA\u0010\u0003\u0011\u0005\u0011QU\u0004\b\u0003\u0003\u000b\u0001\u0012AAE\r\u001d\t9(\u0001E\u0001\u0003sBq!a\b\u0005\t\u0003\t9\tC\u0004\u0002h\u0011!\t!!$\t\u0013\u0005\u0015\u0012A1A\u0005\u0002\u0005\u001d\u0002\u0002CAT\u0003\u0001\u0006I!!\u000b\t\u0013\u0005\u0005\u0013A1A\u0005\u0002\u0005]\u0001\u0002CAU\u0003\u0001\u0006I!!\u0007\t\u0013\u0005\u0015\u0013A1A\u0005\u0002\u0005\u001d\u0003bBAV\u0003\u0001\u0006Ia\u001d\u0005\n\u0003\u0017\n!\u0019!C\u0001\u0003\u000fBq!!,\u0002A\u0003%1\u000fC\u0005\u0002P\u0005\u0011\r\u0011\"\u0001\u0002H!9\u0011qV\u0001!\u0002\u0013\u0019\b\"CA*\u0003\t\u0007I\u0011AA+\u0011!\t\t,\u0001Q\u0001\n\u0005]\u0003\"CA0\u0003\t\u0007I\u0011AA+\u0011!\t\u0019,\u0001Q\u0001\n\u0005]\u0003\"CA2\u0003\t\u0007I\u0011AA+\u0011!\t),\u0001Q\u0001\n\u0005]\u0003\"CA\\\u0003\t\u0007I\u0011AA+\u0011!\tI,\u0001Q\u0001\n\u0005]\u0003\"CA^\u0003\t\u0007I\u0011AA+\u0011!\ti,\u0001Q\u0001\n\u0005]\u0003\"CA`\u0003\t\u0007I\u0011AA+\u0011!\t\t-\u0001Q\u0001\n\u0005]\u0003bBAb\u0003\u0011\u0005\u0011q\t\u0005\b\u0003\u000b\fA\u0011AAd\u0011\u001d\t\u0019.\u0001C\u0001\u0003+Dq!a5\u0002\t\u0003\tY\u000eC\u0004\u0002T\u0006!\t!!:\t\u000f\u0005M\u0017\u0001\"\u0001\u0002j\"9\u0011\u0011`\u0001\u0005\u0002\u0005mxa\u0002B\u0002\u0003!\u0005!Q\u0001\u0004\b\u0003#\t\u0001\u0012\u0001B\u0004\u0011\u001d\ty\"\nC\u0001\u0005\u001fAq!a5&\t\u0003\u0011\t\u0002C\u0004\u0002z\u0016\"\tA!\u0006\b\u000f\tm\u0011\u0001#\u0001\u0003\u001e\u00199\u00111]\u0001\t\u0002\t}\u0001bBA\u0010U\u0011\u0005!q\u0005\u0005\b\u0003\'TC\u0011\u0001B\u0015\u0011\u001d\tIP\u000bC\u0001\u0005[9qAa\r\u0002\u0011\u0003\u0011)DB\u0004\u00038\u0005A\tA!\u000f\t\u000f\u0005}q\u0006\"\u0001\u0003B!9\u00111[\u0018\u0005\u0002\t\r\u0003bBA}_\u0011\u0005!qI\u0004\b\u0005\u001b\n\u0001\u0012\u0001B(\r\u001d\u0011\t&\u0001E\u0001\u0005\'Bq!a\b5\t\u0003\u0011Y\u0006C\u0004\u0002TR\"\tA!\u0018\t\u000f\u0005eH\u0007\"\u0001\u0003r\u00191!qO\u0001\u0002\u0005sB!Ba\u001f9\u0005\u000b\u0007I\u0011\u0001B?\u0011)\u0011)\t\u000fB\u0001B\u0003%!q\u0010\u0005\b\u0003?AD\u0011\u0001BD\u000f\u001d\u0011i\t\u000fE\u0001\u0005\u001f3qAa%9\u0011\u0003\u0011)\nC\u0004\u0002 u\"\tAa&\t\u000f\u0005MW\b\"\u0001\u0003\u001a\"9\u0011\u0011`\u001f\u0005\u0002\t\u0015\u0006\"\u0003BU\u0003\u0005\u0005I1\u0001BV\u0011%\u0011y+\u0001b\u0001\n\u0007\u0011\t\fC\u0004\u00034\u0006\u0001\u000b\u0011\u00029\t\u000f\tU\u0016\u0001\"\u0002\u00038\"9!qX\u0001\u0005\u0006\t\u0005\u0007b\u0002Bd\u0003\u0011\u0015!\u0011\u001a\u0005\b\u0005\u001f\fAQ\u0001Bi\u0011\u001d\u00119.\u0001C\u0003\u00053DqAa8\u0002\t\u000b\u0011\t\u000fC\u0004\u0003h\u0006!)A!;\t\u000f\t=\u0018\u0001\"\u0002\u0003r\"9!q_\u0001\u0005\u0006\te\bbBB\u0001\u0003\u0011\u001511\u0001\u0005\n\u0007\u000f\t\u0011\u0011!C\u0003\u0007\u0013A\u0011b!\u0004\u0002\u0003\u0003%)aa\u0004\u0007\t!\f\'\u0001\u001e\u0005\u000b\u0003+\u0001&Q1A\u0005\u0002\u0005]\u0001BCA\u000f!\n\u0005\t\u0015!\u0003\u0002\u001a!9\u0011q\u0004)\u0005\u0002\u0005\u0005\u0002bBA\u0013!\u0012\u0005\u0011q\u0005\u0005\b\u0003\u0003\u0002F\u0011AA\f\u0011\u001d\t)\u0005\u0015C\u0001\u0003\u000fBq!a\u0013Q\t\u0003\t9\u0005C\u0004\u0002PA#\t!a\u0012\t\u000f\u0005M\u0003\u000b\"\u0001\u0002V!9\u0011q\f)\u0005\u0002\u0005U\u0003bBA2!\u0012\u0005\u0011Q\u000b\u0005\b\u0003O\u0002F\u0011AA5\u0011\u001d\ty\u0007\u0015C\u0001\u0003cB\u0011\"a%Q\u0003\u0003%\t%!&\t\u0013\u0005]\u0005+!A\u0005B\u0005e\u0015aA+4a)\u0011!mY\u0001\u0007g&\u0014X-^7\u000b\u0003\u0011\f1a\u001c:h\u0007\u0001\u0001\"aZ\u0001\u000e\u0003\u0005\u00141!V\u001a1\'\r\t!\u000e\u001d\t\u0003W:l\u0011\u0001\u001c\u0006\u0002[\u0006)1oY1mC&\u0011q\u000e\u001c\u0002\u0007\u0003:L(+\u001a4\u0011\u0007\u001d\f8/\u0003\u0002sC\nYAEW\"p[B\fg.[8o!\t9\u0007kE\u0002Qkb\u0004\"a\u001b<\n\u0005]d\'AB!osZ\u000bG\u000e\u0005\u0003z\u0003\u001f\u0019hb\u0001>\u0002\n9\u001910!\u0002\u000f\u0007q\f\u0019AD\u0002~\u0003\u0003i\u0011A \u0006\u0003\u007f\u0016\fa\u0001\u0010:p_Rt\u0014\"\u00013\n\u0005\t\u001c\u0017bAA\u0004C\u0006\t!,\u0003\u0003\u0002\f\u00055\u0011A\u0001\"W\u0015\r\t9!Y\u0005\u0005\u0003#\t\u0019BA\u0002J]RTA!a\u0003\u0002\u000e\u0005)a/\u00197vKV\u0011\u0011\u0011\u0004\t\u0004W\u0006m\u0011bAA\tY\u00061a/\u00197vK\u0002\na\u0001P5oSRtDcA:\u0002$!9\u0011QC*A\u0002\u0005e\u0011\u0001\u0002(b[\u0016,\"!!\u000b\u0011\t\u0005-\u0012QG\u0007\u0003\u0003[QA!a\f\u00022\u0005!A.\u00198h\u0015\t\t\u0019$\u0001\u0003kCZ\f\u0017\u0002BA\u001c\u0003[\u0011aa\u0015;sS:<\u0007f\u0001+\u0002<A\u00191.!\u0010\n\u0007\u0005}BN\u0001\u0004j]2Lg.Z\u0001\t\u0005&$x+\u001b3uQ\"\u001aQ+a\u000f\u0002\u00075Kg.F\u0001tQ\r1\u00161H\u0001\u0004\u001b\u0006D\bfA,\u0002<\u0005)\u0011J\u001c3fq\"\u001a\u0001,a\u000f\u0002\u0017%\u001c(,\u001a:p\u0013:$W\r_\u000b\u0003\u0003/\u00022a[A-\u0013\r\tY\u0006\u001c\u0002\b\u0005>|G.Z1oQ\rI\u00161H\u0001\tSN\u001c\u0016n\u001a8fI\"\u001a!,a\u000f\u0002\u0013%\u001cxK]1qa\u0016$\u0007fA.\u0002<\u0005!Q.Y6f)\r\u0019\u00181\u000e\u0005\b\u0003[b\u0006\u0019AA\r\u0003\u00051\u0018!\u00022pq\u0016\u0014XCAA:!\r\t)\b\u0002\b\u0003O\u0002\u0011QAQ8yKJ\u001cB\u0001\u00026\u0002|A!\u0011QPAB\u001d\rQ\u0018qP\u0005\u0005\u0003\u0003\u000bi!A\u0003C_b,\'/\u0003\u0003\u0002\u0012\u0005\u0015%\u0002BAA\u0003\u001b!\"!!#\u0011\u0007\u0005-E!D\u0001\u0002)\r\u0019\u0018q\u0012\u0005\b\u0003#3\u0001\u0019AA\r\u0003\u0005y\u0017\u0001\u00035bg\"\u001cu\u000eZ3\u0015\u0005\u0005e\u0011AB3rk\u0006d7\u000f\u0006\u0003\u0002X\u0005m\u0005\"CAO?\u0006\u0005\t\u0019AAP\u0003\rAH%\r\t\u0004W\u0006\u0005\u0016bAARY\n\u0019\u0011I\\=\u0015\u0003\u0019\fQAT1nK\u0002\n\u0011BQ5u/&$G\u000f\u001b\u0011\u0002\t5Kg\u000eI\u0001\u0005\u001b\u0006D\b%\u0001\u0004J]\u0012,\u0007\u0010I\u0001\rSNTVM]8J]\u0012,\u0007\u0010I\u0001\nSN\u001c\u0016n\u001a8fI\u0002\n!\"[:Xe\u0006\u0004\b/\u001a3!\u0003-I7OQ5u-\u0016\u001cGo\u001c:\u0002\u0019%\u001c()\u001b;WK\u000e$xN\u001d\u0011\u0002\r!\f7/T5o\u0003\u001dA\u0017m]\'j]\u0002\na\u0001[1t\u001b\u0006D\u0018a\u00025bg6\u000b\u0007\u0010I\u0001\u0007e\u0006tGm\\7\u0002\u0015I\fg\u000eZ8n\'\u0016,G\rF\u0002t\u0003\u0013Dq!a3\u001f\u0001\u0004\ti-\u0001\u0003tK\u0016$\u0007cA4\u0002P&\u0019\u0011\u0011[1\u0003\u0003i\u000bQ!\u00199qYf$2a]Al\u0011\u001d\tIn\ba\u0001\u00033\t\u0011A\u001c\u000b\u0004g\u0006u\u0007bBAmA\u0001\u0007\u0011q\u001c\t\u0004W\u0006\u0005\u0018bAArY\n!Aj\u001c8h)\r\u0019\u0018q\u001d\u0005\b\u00033\f\u0003\u0019AAg)\u0011\tY/!=\u0011\t\u001d\fio]\u0005\u0004\u0003_\f\'AB(qi&|g\u000eC\u0004\u0002t\n\u0002\r!!>\u0002\u0003M\u00042aZA|\u0013\r\t9$Y\u0001\bk:\f\u0007\u000f\u001d7z)\u0011\tiP!\u0001\u0011\u000b-\fy0!4\n\u0007\u0005=H\u000e\u0003\u0004\u0002Z\u000e\u0002\ra]\u0001\u0004\u0013:$\bcAAFKM!QE\u001bB\u0005!\u00119\'1B:\n\u0007\t5\u0011M\u0001\b%5\u000e{W\u000e]1oS>t\u0017J\u001c;\u0015\u0005\t\u0015AcA:\u0003\u0014!9\u0011\u0011\\\u0014A\u0002\u0005eA\u0003\u0002B\f\u00053\u0001Ra[A\u0000\u00033Aa!!7)\u0001\u0004\u0019\u0018\u0001\u0002\'p]\u001e\u00042!a#+\'\u0011Q#N!\t\u0011\t\u001d\u0014\u0019c]\u0005\u0004\u0005K\t\'a\u0004\u0013[\u0007>l\u0007/\u00198j_:duN\\4\u0015\u0005\tuAcA:\u0003,!9\u0011\u0011\u001c\u0017A\u0002\u0005}G\u0003\u0002B\u0018\u0005c\u0001Ra[A\u0000\u0003?Da!!7.\u0001\u0004\u0019\u0018a\u0002\u0013TiJLgn\u001a\t\u0004\u0003\u0017{#a\u0002\u0013TiJLgnZ\n\u0005_)\u0014Y\u0004\u0005\u0003h\u0005{\u0019\u0018b\u0001B C\n\tBEW\"p[B\fg.[8o\'R\u0014\u0018N\\4\u0015\u0005\tUBcA:\u0003F!9\u00111_\u0019A\u0002\u0005%B\u0003\u0002B%\u0005\u0017\u0002Ra[A\u0000\u0003SAa!!73\u0001\u0004\u0019\u0018A\u0002\"jO&sG\u000fE\u0002\u0002\fR\u0012aAQ5h\u0013:$8\u0003\u0002\u001bk\u0005+\u0002Ba\u001aB,g&\u0019!\u0011L1\u0003#\u0011R6i\\7qC:LwN\u001c\"jO&sG\u000f\u0006\u0002\u0003PQ\u00191Oa\u0018\t\u000f\u0005eg\u00071\u0001\u0003bA!!1\rB7\u001d\u0011\u0011)G!\u001b\u000f\u0007u\u00149\'C\u0001n\u0013\r\u0011Y\u0007\\\u0001\ba\u0006\u001c7.Y4f\u0013\u0011\u0011\tFa\u001c\u000b\u0007\t-D\u000e\u0006\u0003\u0003t\tU\u0004#B6\u0002\u0000\n\u0005\u0004BBAmo\u0001\u00071OA\u0005VgA\"3\u000b\\1oON\u0011\u0001H[\u0001\u0003g\u000e,\"Aa \u0011\u0007-\u0014\t)C\u0002\u0003\u00042\u0014Qb\u0015;sS:<7i\u001c8uKb$\u0018aA:dAQ!!\u0011\u0012BF!\r\tY\t\u000f\u0005\b\u0005wZ\u0004\u0019\u0001B@\u0003\r)8\u0007\r\t\u0004\u0005#kT\"\u0001\u001d\u0003\u0007U\u001c\u0004g\u0005\u0002>UR\u0011!q\u0012\u000b\u0004g\nm\u0005b\u0002BO\u007f\u0001\u0007!qT\u0001\u0005CJ<7\u000fE\u0003l\u0005C\u000by*C\u0002\u0003$2\u0014!\u0002\u0010:fa\u0016\fG/\u001a3?)\u0011\t9Fa*\t\r\u0005e\u0007\t1\u0001t\u0003%)6\u0007\r\u0013TY\u0006tw\r\u0006\u0003\u0003\n\n5\u0006b\u0002B>\u0003\u0002\u0007!qP\u0001\u000eIU\u001b\u0004gQ8na\u0006t\u0017n\u001c8\u0016\u0003A\fa\u0002J+4a\r{W\u000e]1oS>t\u0007%\u0001\bOC6,G%\u001a=uK:\u001c\u0018n\u001c8\u0015\t\u0005%\"\u0011\u0018\u0005\u0007\u0005w#\u0005\u0019A:\u0002\u000b\u0011\"\b.[:)\u0007\u0011\u000bY$\u0001\nCSR<\u0016\u000e\u001a;iI\u0015DH/\u001a8tS>tG\u0003BA\r\u0005\u0007DaAa/F\u0001\u0004\u0019\bfA#\u0002<\u0005iQ*\u001b8%Kb$XM\\:j_:$2a\u001dBf\u0011\u0019\u0011YL\u0012a\u0001g\"\u001aa)a\u000f\u0002\u001b5\u000b\u0007\u0010J3yi\u0016t7/[8o)\r\u0019(1\u001b\u0005\u0007\u0005w;\u0005\u0019A:)\u0007\u001d\u000bY$A\bJ]\u0012,\u0007\u0010J3yi\u0016t7/[8o)\r\u0019(1\u001c\u0005\u0007\u0005wC\u0005\u0019A:)\u0007!\u000bY$A\u000bjgj+\'o\\%oI\u0016DH%\u001a=uK:\u001c\u0018n\u001c8\u0015\t\u0005]#1\u001d\u0005\u0007\u0005wK\u0005\u0019A:)\u0007%\u000bY$\u0001\njgNKwM\\3eI\u0015DH/\u001a8tS>tG\u0003BA,\u0005WDaAa/K\u0001\u0004\u0019\bf\u0001&\u0002<\u0005\u0019\u0012n],sCB\u0004X\r\u001a\u0013fqR,gn]5p]R!\u0011q\u000bBz\u0011\u0019\u0011Yl\u0013a\u0001g\"\u001a1*a\u000f\u0002\u001d5\f7.\u001a\u0013fqR,gn]5p]R!!1 B\u0000)\r\u0019(Q \u0005\b\u0003[b\u0005\u0019AA\r\u0011\u0019\u0011Y\f\u0014a\u0001g\u0006y!m\u001c=fe\u0012*\u0007\u0010^3og&|g\u000e\u0006\u0003\u0002t\r\u0015\u0001B\u0002B^\u001b\u0002\u00071/\u0001\niCND7i\u001c3fI\u0015DH/\u001a8tS>tG\u0003BAK\u0007\u0017AaAa/O\u0001\u0004\u0019\u0018\u0001E3rk\u0006d7\u000fJ3yi\u0016t7/[8o)\u0011\u0019\tb!\u0006\u0015\t\u0005]31\u0003\u0005\n\u0003;{\u0015\u0011!a\u0001\u0003?CaAa/P\u0001\u0004\u0019\b
   #12 = Utf8               org/sireum/U30$$String$
   #13 = Class              #12           // org/sireum/U30$$String$
   #14 = Utf8               $String$
   #15 = Utf8               org/sireum/U30$BigInt$
   #16 = Class              #15           // org/sireum/U30$BigInt$
   #17 = Utf8               BigInt$
   #18 = Utf8               org/sireum/U30$Boxer$
   #19 = Class              #18           // org/sireum/U30$Boxer$
   #20 = Utf8               Boxer$
   #21 = Utf8               org/sireum/U30$Int$
   #22 = Class              #21           // org/sireum/U30$Int$
   #23 = Utf8               Int$
   #24 = Utf8               org/sireum/U30$Long$
   #25 = Class              #24           // org/sireum/U30$Long$
   #26 = Utf8               Long$
   #27 = Utf8               org/sireum/U30$U30$Slang
   #28 = Class              #27           // org/sireum/U30$U30$Slang
   #29 = Utf8               U30$Slang
   #30 = Utf8               org/sireum/Z$BV$
   #31 = Class              #30           // org/sireum/Z$BV$
   #32 = Utf8               org/sireum/Z
   #33 = Class              #32           // org/sireum/Z
   #34 = Utf8               BV$
   #35 = Utf8               Int
   #36 = Utf8               value
   #37 = Utf8               I
   #38 = Utf8               equals$extension
   #39 = Utf8               (ILjava/lang/Object;)Z
   #40 = Utf8               $this
   #41 = Utf8               x$1
   #42 = Utf8               org/sireum/U30$
   #43 = Class              #42           // org/sireum/U30$
   #44 = Utf8               MODULE$
   #45 = Utf8               Lorg/sireum/U30$;
   #46 = NameAndType        #44:#45       // MODULE$:Lorg/sireum/U30$;
   #47 = Fieldref           #43.#46       // org/sireum/U30$.MODULE$:Lorg/sireum/U30$;
   #48 = NameAndType        #38:#39       // equals$extension:(ILjava/lang/Object;)Z
   #49 = Methodref          #43.#48       // org/sireum/U30$.equals$extension:(ILjava/lang/Object;)Z
   #50 = Utf8               Ljava/lang/Object;
   #51 = Utf8               hashCode$extension
   #52 = Utf8               (I)I
   #53 = NameAndType        #51:#52       // hashCode$extension:(I)I
   #54 = Methodref          #43.#53       // org/sireum/U30$.hashCode$extension:(I)I
   #55 = Utf8               boxer$extension
   #56 = Utf8               (I)Lorg/sireum/U30$Boxer$;
   #57 = NameAndType        #55:#56       // boxer$extension:(I)Lorg/sireum/U30$Boxer$;
   #58 = Methodref          #43.#57       // org/sireum/U30$.boxer$extension:(I)Lorg/sireum/U30$Boxer$;
   #59 = Utf8               make$extension
   #60 = Utf8               (II)I
   #61 = Utf8               v
   #62 = NameAndType        #59:#60       // make$extension:(II)I
   #63 = Methodref          #43.#62       // org/sireum/U30$.make$extension:(II)I
   #64 = Utf8               isWrapped$extension
   #65 = Utf8               (I)Z
   #66 = NameAndType        #64:#65       // isWrapped$extension:(I)Z
   #67 = Methodref          #43.#66       // org/sireum/U30$.isWrapped$extension:(I)Z
   #68 = Utf8               isSigned$extension
   #69 = NameAndType        #68:#65       // isSigned$extension:(I)Z
   #70 = Methodref          #43.#69       // org/sireum/U30$.isSigned$extension:(I)Z
   #71 = Utf8               isZeroIndex$extension
   #72 = NameAndType        #71:#65       // isZeroIndex$extension:(I)Z
   #73 = Methodref          #43.#72       // org/sireum/U30$.isZeroIndex$extension:(I)Z
   #74 = Utf8               Index$extension
   #75 = NameAndType        #74:#52       // Index$extension:(I)I
   #76 = Methodref          #43.#75       // org/sireum/U30$.Index$extension:(I)I
   #77 = Utf8               Max$extension
   #78 = NameAndType        #77:#52       // Max$extension:(I)I
   #79 = Methodref          #43.#78       // org/sireum/U30$.Max$extension:(I)I
   #80 = Utf8               Min$extension
   #81 = NameAndType        #80:#52       // Min$extension:(I)I
   #82 = Methodref          #43.#81       // org/sireum/U30$.Min$extension:(I)I
   #83 = Utf8               BitWidth$extension
   #84 = NameAndType        #83:#52       // BitWidth$extension:(I)I
   #85 = Methodref          #43.#84       // org/sireum/U30$.BitWidth$extension:(I)I
   #86 = Utf8               Name$extension
   #87 = Utf8               (I)Ljava/lang/String;
   #88 = NameAndType        #86:#87       // Name$extension:(I)Ljava/lang/String;
   #89 = Methodref          #43.#88       // org/sireum/U30$.Name$extension:(I)Ljava/lang/String;
   #90 = Utf8               $U30Companion
   #91 = Utf8               ()Lorg/sireum/$ZCompanion;
   #92 = Utf8               ()Lorg/sireum/$ZCompanion<Lorg/sireum/U30;>;
   #93 = NameAndType        #90:#91       // $U30Companion:()Lorg/sireum/$ZCompanion;
   #94 = Methodref          #43.#93       // org/sireum/U30$.$U30Companion:()Lorg/sireum/$ZCompanion;
   #95 = Utf8               (Lscala/StringContext;)Lorg/sireum/U30$U30$Slang;
   #96 = Utf8               sc
   #97 = NameAndType        #29:#95       // U30$Slang:(Lscala/StringContext;)Lorg/sireum/U30$U30$Slang;
   #98 = Methodref          #43.#97       // org/sireum/U30$.U30$Slang:(Lscala/StringContext;)Lorg/sireum/U30$U30$Slang;
   #99 = Utf8               Lscala/StringContext;
  #100 = Utf8               unapply
  #101 = Utf8               (I)Lscala/Option;
  #102 = Utf8               (I)Lscala/Option<Lorg/sireum/Z;>;
  #103 = Utf8               n
  #104 = NameAndType        #100:#101     // unapply:(I)Lscala/Option;
  #105 = Methodref          #43.#104      // org/sireum/U30$.unapply:(I)Lscala/Option;
  #106 = Utf8               apply
  #107 = Utf8               (Ljava/lang/String;)Lorg/sireum/Option;
  #108 = Utf8               (Ljava/lang/String;)Lorg/sireum/Option<Lorg/sireum/U30;>;
  #109 = Utf8               s
  #110 = NameAndType        #106:#107     // apply:(Ljava/lang/String;)Lorg/sireum/Option;
  #111 = Methodref          #43.#110      // org/sireum/U30$.apply:(Ljava/lang/String;)Lorg/sireum/Option;
  #112 = Utf8               Ljava/lang/String;
  #113 = Utf8               (Lorg/sireum/Z;)I
  #114 = NameAndType        #106:#113     // apply:(Lorg/sireum/Z;)I
  #115 = Methodref          #43.#114      // org/sireum/U30$.apply:(Lorg/sireum/Z;)I
  #116 = Utf8               Lorg/sireum/Z;
  #117 = Utf8               (J)I
  #118 = NameAndType        #106:#117     // apply:(J)I
  #119 = Methodref          #43.#118      // org/sireum/U30$.apply:(J)I
  #120 = Utf8               J
  #121 = NameAndType        #106:#52      // apply:(I)I
  #122 = Methodref          #43.#121      // org/sireum/U30$.apply:(I)I
  #123 = Utf8               randomSeed
  #124 = Utf8               seed
  #125 = NameAndType        #123:#113     // randomSeed:(Lorg/sireum/Z;)I
  #126 = Methodref          #43.#125      // org/sireum/U30$.randomSeed:(Lorg/sireum/Z;)I
  #127 = Utf8               random
  #128 = Utf8               ()I
  #129 = NameAndType        #127:#128     // random:()I
  #130 = Methodref          #43.#129      // org/sireum/U30$.random:()I
  #131 = Utf8               isBitVector
  #132 = Utf8               ()Z
  #133 = Utf8               isBitVector$
  #134 = Utf8               (Lorg/sireum/Z$BV$Int;)Z
  #135 = NameAndType        #133:#134     // isBitVector$:(Lorg/sireum/Z$BV$Int;)Z
  #136 = InterfaceMethodref #7.#135       // org/sireum/Z$BV$Int.isBitVector$:(Lorg/sireum/Z$BV$Int;)Z
  #137 = Utf8               this
  #138 = Utf8               Lorg/sireum/U30;
  #139 = Utf8               hasMin
  #140 = Utf8               hasMin$
  #141 = NameAndType        #140:#134     // hasMin$:(Lorg/sireum/Z$BV$Int;)Z
  #142 = InterfaceMethodref #7.#141       // org/sireum/Z$BV$Int.hasMin$:(Lorg/sireum/Z$BV$Int;)Z
  #143 = Utf8               hasMax
  #144 = Utf8               hasMax$
  #145 = NameAndType        #144:#134     // hasMax$:(Lorg/sireum/Z$BV$Int;)Z
  #146 = InterfaceMethodref #7.#145       // org/sireum/Z$BV$Int.hasMax$:(Lorg/sireum/Z$BV$Int;)Z
  #147 = Utf8               unary_$minus
  #148 = Utf8               ()Lorg/sireum/Z$BV$Int;
  #149 = Utf8               unary_$minus$
  #150 = Utf8               (Lorg/sireum/Z$BV$Int;)Lorg/sireum/Z$BV$Int;
  #151 = NameAndType        #149:#150     // unary_$minus$:(Lorg/sireum/Z$BV$Int;)Lorg/sireum/Z$BV$Int;
  #152 = InterfaceMethodref #7.#151       // org/sireum/Z$BV$Int.unary_$minus$:(Lorg/sireum/Z$BV$Int;)Lorg/sireum/Z$BV$Int;
  #153 = Utf8               $plus
  #154 = Utf8               other
  #155 = Utf8               $plus$
  #156 = Utf8               (Lorg/sireum/Z$BV$Int;Lorg/sireum/Z$BV$Int;)Lorg/sireum/Z$BV$Int;
  #157 = NameAndType        #155:#156     // $plus$:(Lorg/sireum/Z$BV$Int;Lorg/sireum/Z$BV$Int;)Lorg/sireum/Z$BV$Int;
  #158 = InterfaceMethodref #7.#157       // org/sireum/Z$BV$Int.$plus$:(Lorg/sireum/Z$BV$Int;Lorg/sireum/Z$BV$Int;)Lorg/sireum/Z$BV$Int;
  #159 = Utf8               Lorg/sireum/Z$BV$Int;
  #160 = Utf8               $minus
  #161 = Utf8               $minus$
  #162 = NameAndType        #161:#156     // $minus$:(Lorg/sireum/Z$BV$Int;Lorg/sireum/Z$BV$Int;)Lorg/sireum/Z$BV$Int;
  #163 = InterfaceMethodref #7.#162       // org/sireum/Z$BV$Int.$minus$:(Lorg/sireum/Z$BV$Int;Lorg/sireum/Z$BV$Int;)Lorg/sireum/Z$BV$Int;
  #164 = Utf8               $times
  #165 = Utf8               $times$
  #166 = NameAndType        #165:#156     // $times$:(Lorg/sireum/Z$BV$Int;Lorg/sireum/Z$BV$Int;)Lorg/sireum/Z$BV$Int;
  #167 = InterfaceMethodref #7.#166       // org/sireum/Z$BV$Int.$times$:(Lorg/sireum/Z$BV$Int;Lorg/sireum/Z$BV$Int;)Lorg/sireum/Z$BV$Int;
  #168 = Utf8               $div
  #169 = Utf8               $div$
  #170 = NameAndType        #169:#156     // $div$:(Lorg/sireum/Z$BV$Int;Lorg/sireum/Z$BV$Int;)Lorg/sireum/Z$BV$Int;
  #171 = InterfaceMethodref #7.#170       // org/sireum/Z$BV$Int.$div$:(Lorg/sireum/Z$BV$Int;Lorg/sireum/Z$BV$Int;)Lorg/sireum/Z$BV$Int;
  #172 = Utf8               $percent
  #173 = Utf8               $percent$
  #174 = NameAndType        #173:#156     // $percent$:(Lorg/sireum/Z$BV$Int;Lorg/sireum/Z$BV$Int;)Lorg/sireum/Z$BV$Int;
  #175 = InterfaceMethodref #7.#174       // org/sireum/Z$BV$Int.$percent$:(Lorg/sireum/Z$BV$Int;Lorg/sireum/Z$BV$Int;)Lorg/sireum/Z$BV$Int;
  #176 = Utf8               $greater
  #177 = Utf8               $greater$
  #178 = Utf8               (Lorg/sireum/Z$BV$Int;Lorg/sireum/Z$BV$Int;)Z
  #179 = NameAndType        #177:#178     // $greater$:(Lorg/sireum/Z$BV$Int;Lorg/sireum/Z$BV$Int;)Z
  #180 = InterfaceMethodref #7.#179       // org/sireum/Z$BV$Int.$greater$:(Lorg/sireum/Z$BV$Int;Lorg/sireum/Z$BV$Int;)Z
  #181 = Utf8               $greater$eq
  #182 = Utf8               $greater$eq$
  #183 = NameAndType        #182:#178     // $greater$eq$:(Lorg/sireum/Z$BV$Int;Lorg/sireum/Z$BV$Int;)Z
  #184 = InterfaceMethodref #7.#183       // org/sireum/Z$BV$Int.$greater$eq$:(Lorg/sireum/Z$BV$Int;Lorg/sireum/Z$BV$Int;)Z
  #185 = Utf8               $less
  #186 = Utf8               $less$
  #187 = NameAndType        #186:#178     // $less$:(Lorg/sireum/Z$BV$Int;Lorg/sireum/Z$BV$Int;)Z
  #188 = InterfaceMethodref #7.#187       // org/sireum/Z$BV$Int.$less$:(Lorg/sireum/Z$BV$Int;Lorg/sireum/Z$BV$Int;)Z
  #189 = Utf8               $less$eq
  #190 = Utf8               $less$eq$
  #191 = NameAndType        #190:#178     // $less$eq$:(Lorg/sireum/Z$BV$Int;Lorg/sireum/Z$BV$Int;)Z
  #192 = InterfaceMethodref #7.#191       // org/sireum/Z$BV$Int.$less$eq$:(Lorg/sireum/Z$BV$Int;Lorg/sireum/Z$BV$Int;)Z
  #193 = Utf8               $greater$greater
  #194 = Utf8               $greater$greater$
  #195 = NameAndType        #194:#156     // $greater$greater$:(Lorg/sireum/Z$BV$Int;Lorg/sireum/Z$BV$Int;)Lorg/sireum/Z$BV$Int;
  #196 = InterfaceMethodref #7.#195       // org/sireum/Z$BV$Int.$greater$greater$:(Lorg/sireum/Z$BV$Int;Lorg/sireum/Z$BV$Int;)Lorg/sireum/Z$BV$Int;
  #197 = Utf8               $greater$greater$greater
  #198 = Utf8               $greater$greater$greater$
  #199 = NameAndType        #198:#156     // $greater$greater$greater$:(Lorg/sireum/Z$BV$Int;Lorg/sireum/Z$BV$Int;)Lorg/sireum/Z$BV$Int;
  #200 = InterfaceMethodref #7.#199       // org/sireum/Z$BV$Int.$greater$greater$greater$:(Lorg/sireum/Z$BV$Int;Lorg/sireum/Z$BV$Int;)Lorg/sireum/Z$BV$Int;
  #201 = Utf8               $less$less
  #202 = Utf8               $less$less$
  #203 = NameAndType        #202:#156     // $less$less$:(Lorg/sireum/Z$BV$Int;Lorg/sireum/Z$BV$Int;)Lorg/sireum/Z$BV$Int;
  #204 = InterfaceMethodref #7.#203       // org/sireum/Z$BV$Int.$less$less$:(Lorg/sireum/Z$BV$Int;Lorg/sireum/Z$BV$Int;)Lorg/sireum/Z$BV$Int;
  #205 = Utf8               $amp
  #206 = Utf8               $amp$
  #207 = NameAndType        #206:#156     // $amp$:(Lorg/sireum/Z$BV$Int;Lorg/sireum/Z$BV$Int;)Lorg/sireum/Z$BV$Int;
  #208 = InterfaceMethodref #7.#207       // org/sireum/Z$BV$Int.$amp$:(Lorg/sireum/Z$BV$Int;Lorg/sireum/Z$BV$Int;)Lorg/sireum/Z$BV$Int;
  #209 = Utf8               $bar
  #210 = Utf8               $bar$
  #211 = NameAndType        #210:#156     // $bar$:(Lorg/sireum/Z$BV$Int;Lorg/sireum/Z$BV$Int;)Lorg/sireum/Z$BV$Int;
  #212 = InterfaceMethodref #7.#211       // org/sireum/Z$BV$Int.$bar$:(Lorg/sireum/Z$BV$Int;Lorg/sireum/Z$BV$Int;)Lorg/sireum/Z$BV$Int;
  #213 = Utf8               $bar$up
  #214 = Utf8               $bar$up$
  #215 = NameAndType        #214:#156     // $bar$up$:(Lorg/sireum/Z$BV$Int;Lorg/sireum/Z$BV$Int;)Lorg/sireum/Z$BV$Int;
  #216 = InterfaceMethodref #7.#215       // org/sireum/Z$BV$Int.$bar$up$:(Lorg/sireum/Z$BV$Int;Lorg/sireum/Z$BV$Int;)Lorg/sireum/Z$BV$Int;
  #217 = Utf8               unary_$tilde
  #218 = Utf8               unary_$tilde$
  #219 = NameAndType        #218:#150     // unary_$tilde$:(Lorg/sireum/Z$BV$Int;)Lorg/sireum/Z$BV$Int;
  #220 = InterfaceMethodref #7.#219       // org/sireum/Z$BV$Int.unary_$tilde$:(Lorg/sireum/Z$BV$Int;)Lorg/sireum/Z$BV$Int;
  #221 = Utf8               increase
  #222 = Utf8               increase$
  #223 = NameAndType        #222:#150     // increase$:(Lorg/sireum/Z$BV$Int;)Lorg/sireum/Z$BV$Int;
  #224 = InterfaceMethodref #7.#223       // org/sireum/Z$BV$Int.increase$:(Lorg/sireum/Z$BV$Int;)Lorg/sireum/Z$BV$Int;
  #225 = Utf8               decrease
  #226 = Utf8               decrease$
  #227 = NameAndType        #226:#150     // decrease$:(Lorg/sireum/Z$BV$Int;)Lorg/sireum/Z$BV$Int;
  #228 = InterfaceMethodref #7.#227       // org/sireum/Z$BV$Int.decrease$:(Lorg/sireum/Z$BV$Int;)Lorg/sireum/Z$BV$Int;
  #229 = Utf8               toString
  #230 = Utf8               ()Ljava/lang/String;
  #231 = Utf8               toString$
  #232 = Utf8               (Lorg/sireum/Z$BV$Int;)Ljava/lang/String;
  #233 = NameAndType        #231:#232     // toString$:(Lorg/sireum/Z$BV$Int;)Ljava/lang/String;
  #234 = InterfaceMethodref #7.#233       // org/sireum/Z$BV$Int.toString$:(Lorg/sireum/Z$BV$Int;)Ljava/lang/String;
  #235 = Utf8               toBigInt
  #236 = Utf8               ()Lscala/math/BigInt;
  #237 = Utf8               toBigInt$
  #238 = Utf8               (Lorg/sireum/Z$BV$Int;)Lscala/math/BigInt;
  #239 = NameAndType        #237:#238     // toBigInt$:(Lorg/sireum/Z$BV$Int;)Lscala/math/BigInt;
  #240 = InterfaceMethodref #7.#239       // org/sireum/Z$BV$Int.toBigInt$:(Lorg/sireum/Z$BV$Int;)Lscala/math/BigInt;
  #241 = Utf8               toMP
  #242 = Utf8               ()Lorg/sireum/Z;
  #243 = Utf8               toMP$
  #244 = Utf8               (Lorg/sireum/Z$BV$Int;)Lorg/sireum/Z;
  #245 = NameAndType        #243:#244     // toMP$:(Lorg/sireum/Z$BV$Int;)Lorg/sireum/Z;
  #246 = InterfaceMethodref #7.#245       // org/sireum/Z$BV$Int.toMP$:(Lorg/sireum/Z$BV$Int;)Lorg/sireum/Z;
  #247 = Utf8               toIndex
  #248 = Utf8               toIndex$
  #249 = NameAndType        #248:#244     // toIndex$:(Lorg/sireum/Z$BV$Int;)Lorg/sireum/Z;
  #250 = InterfaceMethodref #7.#249       // org/sireum/Z$BV$Int.toIndex$:(Lorg/sireum/Z$BV$Int;)Lorg/sireum/Z;
  #251 = Utf8               $eq$eq$eq
  #252 = Utf8               (Lorg/sireum/Z;)Z
  #253 = Utf8               org/sireum/ZLike
  #254 = Class              #253          // org/sireum/ZLike
  #255 = Utf8               $eq$eq$eq$
  #256 = Utf8               (Lorg/sireum/ZLike;Lorg/sireum/Z;)Z
  #257 = NameAndType        #255:#256     // $eq$eq$eq$:(Lorg/sireum/ZLike;Lorg/sireum/Z;)Z
  #258 = InterfaceMethodref #254.#257     // org/sireum/ZLike.$eq$eq$eq$:(Lorg/sireum/ZLike;Lorg/sireum/Z;)Z
  #259 = Utf8               $eq$bang$eq
  #260 = Utf8               $eq$bang$eq$
  #261 = NameAndType        #260:#256     // $eq$bang$eq$:(Lorg/sireum/ZLike;Lorg/sireum/Z;)Z
  #262 = InterfaceMethodref #254.#261     // org/sireum/ZLike.$eq$bang$eq$:(Lorg/sireum/ZLike;Lorg/sireum/Z;)Z
  #263 = Utf8               string
  #264 = Utf8               string$
  #265 = Utf8               (Lorg/sireum/ZLike;)Ljava/lang/String;
  #266 = NameAndType        #264:#265     // string$:(Lorg/sireum/ZLike;)Ljava/lang/String;
  #267 = InterfaceMethodref #254.#266     // org/sireum/ZLike.string$:(Lorg/sireum/ZLike;)Ljava/lang/String;
  #268 = Utf8               to
  #269 = Utf8               (Lorg/sireum/ZLike;)Lorg/sireum/ZRange;
  #270 = Utf8               to$
  #271 = Utf8               (Lorg/sireum/ZLike;Lorg/sireum/ZLike;)Lorg/sireum/ZRange;
  #272 = NameAndType        #270:#271     // to$:(Lorg/sireum/ZLike;Lorg/sireum/ZLike;)Lorg/sireum/ZRange;
  #273 = InterfaceMethodref #254.#272     // org/sireum/ZLike.to$:(Lorg/sireum/ZLike;Lorg/sireum/ZLike;)Lorg/sireum/ZRange;
  #274 = Utf8               Lorg/sireum/ZLike;
  #275 = Utf8               until
  #276 = Utf8               until$
  #277 = NameAndType        #276:#271     // until$:(Lorg/sireum/ZLike;Lorg/sireum/ZLike;)Lorg/sireum/ZRange;
  #278 = InterfaceMethodref #254.#277     // org/sireum/ZLike.until$:(Lorg/sireum/ZLike;Lorg/sireum/ZLike;)Lorg/sireum/ZRange;
  #279 = Utf8               compareTo
  #280 = Utf8               (Lorg/sireum/ZLike;)I
  #281 = Utf8               compareTo$
  #282 = Utf8               (Lorg/sireum/ZLike;Lorg/sireum/ZLike;)I
  #283 = NameAndType        #281:#282     // compareTo$:(Lorg/sireum/ZLike;Lorg/sireum/ZLike;)I
  #284 = InterfaceMethodref #254.#283     // org/sireum/ZLike.compareTo$:(Lorg/sireum/ZLike;Lorg/sireum/ZLike;)I
  #285 = Utf8               $cannotMixImmutableAndMutable
  #286 = Utf8               ()Lscala/runtime/Nothing$;
  #287 = Utf8               org/sireum/Immutable
  #288 = Class              #287          // org/sireum/Immutable
  #289 = Utf8               $cannotMixImmutableAndMutable$
  #290 = Utf8               (Lorg/sireum/Immutable;)Lscala/runtime/Nothing$;
  #291 = NameAndType        #289:#290     // $cannotMixImmutableAndMutable$:(Lorg/sireum/Immutable;)Lscala/runtime/Nothing$;
  #292 = InterfaceMethodref #288.#291     // org/sireum/Immutable.$cannotMixImmutableAndMutable$:(Lorg/sireum/Immutable;)Lscala/runtime/Nothing$;
  #293 = Utf8               $hasEquals
  #294 = Utf8               $hasEquals$
  #295 = Utf8               (Lorg/sireum/Immutable;)Z
  #296 = NameAndType        #294:#295     // $hasEquals$:(Lorg/sireum/Immutable;)Z
  #297 = InterfaceMethodref #288.#296     // org/sireum/Immutable.$hasEquals$:(Lorg/sireum/Immutable;)Z
  #298 = Utf8               $hasString
  #299 = Utf8               $hasString$
  #300 = NameAndType        #299:#295     // $hasString$:(Lorg/sireum/Immutable;)Z
  #301 = InterfaceMethodref #288.#300     // org/sireum/Immutable.$hasString$:(Lorg/sireum/Immutable;)Z
  #302 = Utf8               $clone
  #303 = Utf8               ()Lorg/sireum/$internal/ImmutableMarker;
  #304 = Utf8               org/sireum/$internal/ImmutableMarker
  #305 = Class              #304          // org/sireum/$internal/ImmutableMarker
  #306 = Utf8               $clone$
  #307 = Utf8               (Lorg/sireum/$internal/ImmutableMarker;)Lorg/sireum/$internal/ImmutableMarker;
  #308 = NameAndType        #306:#307     // $clone$:(Lorg/sireum/$internal/ImmutableMarker;)Lorg/sireum/$internal/ImmutableMarker;
  #309 = InterfaceMethodref #305.#308     // org/sireum/$internal/ImmutableMarker.$clone$:(Lorg/sireum/$internal/ImmutableMarker;)Lorg/sireum/$internal/ImmutableMarker;
  #310 = NameAndType        #36:#37       // value:I
  #311 = Fieldref           #2.#310       // org/sireum/U30.value:I
  #312 = Utf8               Name
  #313 = NameAndType        #36:#128      // value:()I
  #314 = Methodref          #2.#313       // org/sireum/U30.value:()I
  #315 = Utf8               BitWidth
  #316 = Utf8               Min
  #317 = Utf8               Max
  #318 = Utf8               Index
  #319 = Utf8               isZeroIndex
  #320 = Utf8               isSigned
  #321 = Utf8               isWrapped
  #322 = Utf8               make
  #323 = Utf8               boxer
  #324 = Utf8               ()Lorg/sireum/U30$Boxer$;
  #325 = Utf8               hashCode
  #326 = Utf8               equals
  #327 = Utf8               (Ljava/lang/Object;)Z
  #328 = Utf8               ()Ljava/lang/Object;
  #329 = NameAndType        #302:#303     // $clone:()Lorg/sireum/$internal/ImmutableMarker;
  #330 = Methodref          #2.#329       // org/sireum/U30.$clone:()Lorg/sireum/$internal/ImmutableMarker;
  #331 = Utf8               (Ljava/lang/Object;)I
  #332 = NameAndType        #279:#280     // compareTo:(Lorg/sireum/ZLike;)I
  #333 = Methodref          #2.#332       // org/sireum/U30.compareTo:(Lorg/sireum/ZLike;)I
  #334 = Utf8               ()Lorg/sireum/ZLike;
  #335 = NameAndType        #225:#148     // decrease:()Lorg/sireum/Z$BV$Int;
  #336 = Methodref          #2.#335       // org/sireum/U30.decrease:()Lorg/sireum/Z$BV$Int;
  #337 = NameAndType        #221:#148     // increase:()Lorg/sireum/Z$BV$Int;
  #338 = Methodref          #2.#337       // org/sireum/U30.increase:()Lorg/sireum/Z$BV$Int;
  #339 = Utf8               (Lorg/sireum/ZLike;)Z
  #340 = NameAndType        #189:#134     // $less$eq:(Lorg/sireum/Z$BV$Int;)Z
  #341 = Methodref          #2.#340       // org/sireum/U30.$less$eq:(Lorg/sireum/Z$BV$Int;)Z
  #342 = NameAndType        #185:#134     // $less:(Lorg/sireum/Z$BV$Int;)Z
  #343 = Methodref          #2.#342       // org/sireum/U30.$less:(Lorg/sireum/Z$BV$Int;)Z
  #344 = NameAndType        #181:#134     // $greater$eq:(Lorg/sireum/Z$BV$Int;)Z
  #345 = Methodref          #2.#344       // org/sireum/U30.$greater$eq:(Lorg/sireum/Z$BV$Int;)Z
  #346 = NameAndType        #176:#134     // $greater:(Lorg/sireum/Z$BV$Int;)Z
  #347 = Methodref          #2.#346       // org/sireum/U30.$greater:(Lorg/sireum/Z$BV$Int;)Z
  #348 = Utf8               (Lorg/sireum/ZLike;)Lorg/sireum/ZLike;
  #349 = NameAndType        #172:#150     // $percent:(Lorg/sireum/Z$BV$Int;)Lorg/sireum/Z$BV$Int;
  #350 = Methodref          #2.#349       // org/sireum/U30.$percent:(Lorg/sireum/Z$BV$Int;)Lorg/sireum/Z$BV$Int;
  #351 = NameAndType        #168:#150     // $div:(Lorg/sireum/Z$BV$Int;)Lorg/sireum/Z$BV$Int;
  #352 = Methodref          #2.#351       // org/sireum/U30.$div:(Lorg/sireum/Z$BV$Int;)Lorg/sireum/Z$BV$Int;
  #353 = NameAndType        #164:#150     // $times:(Lorg/sireum/Z$BV$Int;)Lorg/sireum/Z$BV$Int;
  #354 = Methodref          #2.#353       // org/sireum/U30.$times:(Lorg/sireum/Z$BV$Int;)Lorg/sireum/Z$BV$Int;
  #355 = NameAndType        #160:#150     // $minus:(Lorg/sireum/Z$BV$Int;)Lorg/sireum/Z$BV$Int;
  #356 = Methodref          #2.#355       // org/sireum/U30.$minus:(Lorg/sireum/Z$BV$Int;)Lorg/sireum/Z$BV$Int;
  #357 = NameAndType        #153:#150     // $plus:(Lorg/sireum/Z$BV$Int;)Lorg/sireum/Z$BV$Int;
  #358 = Methodref          #2.#357       // org/sireum/U30.$plus:(Lorg/sireum/Z$BV$Int;)Lorg/sireum/Z$BV$Int;
  #359 = NameAndType        #147:#148     // unary_$minus:()Lorg/sireum/Z$BV$Int;
  #360 = Methodref          #2.#359       // org/sireum/U30.unary_$minus:()Lorg/sireum/Z$BV$Int;
  #361 = Utf8               ()Lorg/sireum/$internal/Boxer;
  #362 = Utf8               (I)Lorg/sireum/Z$BV$Int;
  #363 = Utf8               <init>
  #364 = Utf8               (I)V
  #365 = NameAndType        #363:#364     // "<init>":(I)V
  #366 = Methodref          #2.#365       // org/sireum/U30."<init>":(I)V
  #367 = Utf8               ()V
  #368 = NameAndType        #363:#367     // "<init>":()V
  #369 = Methodref          #5.#368       // java/lang/Object."<init>":()V
  #370 = Utf8               $init$
  #371 = Utf8               (Lorg/sireum/$internal/ImmutableMarker;)V
  #372 = NameAndType        #370:#371     // $init$:(Lorg/sireum/$internal/ImmutableMarker;)V
  #373 = InterfaceMethodref #305.#372     // org/sireum/$internal/ImmutableMarker.$init$:(Lorg/sireum/$internal/ImmutableMarker;)V
  #374 = Utf8               (Lorg/sireum/Immutable;)V
  #375 = NameAndType        #370:#374     // $init$:(Lorg/sireum/Immutable;)V
  #376 = InterfaceMethodref #288.#375     // org/sireum/Immutable.$init$:(Lorg/sireum/Immutable;)V
  #377 = Utf8               (Lorg/sireum/ZLike;)V
  #378 = NameAndType        #370:#377     // $init$:(Lorg/sireum/ZLike;)V
  #379 = InterfaceMethodref #254.#378     // org/sireum/ZLike.$init$:(Lorg/sireum/ZLike;)V
  #380 = Utf8               (Lorg/sireum/Z$BV$Int;)V
  #381 = NameAndType        #370:#380     // $init$:(Lorg/sireum/Z$BV$Int;)V
  #382 = InterfaceMethodref #7.#381       // org/sireum/Z$BV$Int.$init$:(Lorg/sireum/Z$BV$Int;)V
  #383 = Utf8               Code
  #384 = Utf8               LocalVariableTable
  #385 = Utf8               MethodParameters
  #386 = Utf8               Signature
  #387 = Utf8               LineNumberTable
  #388 = Utf8               InnerClasses
  #389 = Utf8               SourceFile
  #390 = Utf8               RuntimeVisibleAnnotations
  #391 = Utf8               ScalaInlineInfo
  #392 = Utf8               ScalaSig
{
  private final int value;
    descriptor: I
    flags: (0x0012) ACC_PRIVATE, ACC_FINAL

  public static boolean equals$extension(int, java.lang.Object);
    descriptor: (ILjava/lang/Object;)Z
    flags: (0x0009) ACC_PUBLIC, ACC_STATIC
    Code:
      stack=3, locals=2, args_size=2
         0: getstatic     #47                 // Field org/sireum/U30$.MODULE$:Lorg/sireum/U30$;
         3: iload_0
         4: aload_1
         5: invokevirtual #49                 // Method org/sireum/U30$.equals$extension:(ILjava/lang/Object;)Z
         8: ireturn
      LocalVariableTable:
        Start  Length  Slot  Name   Signature
            0       9     0 $this   I
            0       9     1   x$1   Ljava/lang/Object;
    MethodParameters:
      Name                           Flags
      $this                          final
      x$1                            final

  public static int hashCode$extension(int);
    descriptor: (I)I
    flags: (0x0009) ACC_PUBLIC, ACC_STATIC
    Code:
      stack=2, locals=1, args_size=1
         0: getstatic     #47                 // Field org/sireum/U30$.MODULE$:Lorg/sireum/U30$;
         3: iload_0
         4: invokevirtual #54                 // Method org/sireum/U30$.hashCode$extension:(I)I
         7: ireturn
      LocalVariableTable:
        Start  Length  Slot  Name   Signature
            0       8     0 $this   I
    MethodParameters:
      Name                           Flags
      $this                          final

  public static org.sireum.U30$Boxer$ boxer$extension(int);
    descriptor: (I)Lorg/sireum/U30$Boxer$;
    flags: (0x0009) ACC_PUBLIC, ACC_STATIC
    Code:
      stack=2, locals=1, args_size=1
         0: getstatic     #47                 // Field org/sireum/U30$.MODULE$:Lorg/sireum/U30$;
         3: iload_0
         4: invokevirtual #58                 // Method org/sireum/U30$.boxer$extension:(I)Lorg/sireum/U30$Boxer$;
         7: areturn
      LocalVariableTable:
        Start  Length  Slot  Name   Signature
            0       8     0 $this   I
    MethodParameters:
      Name                           Flags
      $this                          final

  public static int make$extension(int, int);
    descriptor: (II)I
    flags: (0x0009) ACC_PUBLIC, ACC_STATIC
    Code:
      stack=3, locals=2, args_size=2
         0: getstatic     #47                 // Field org/sireum/U30$.MODULE$:Lorg/sireum/U30$;
         3: iload_0
         4: iload_1
         5: invokevirtual #63                 // Method org/sireum/U30$.make$extension:(II)I
         8: ireturn
      LocalVariableTable:
        Start  Length  Slot  Name   Signature
            0       9     0 $this   I
            0       9     1     v   I
    MethodParameters:
      Name                           Flags
      $this                          final
      v                              final

  public static boolean isWrapped$extension(int);
    descriptor: (I)Z
    flags: (0x0009) ACC_PUBLIC, ACC_STATIC
    Code:
      stack=2, locals=1, args_size=1
         0: getstatic     #47                 // Field org/sireum/U30$.MODULE$:Lorg/sireum/U30$;
         3: iload_0
         4: invokevirtual #67                 // Method org/sireum/U30$.isWrapped$extension:(I)Z
         7: ireturn
      LocalVariableTable:
        Start  Length  Slot  Name   Signature
            0       8     0 $this   I
    MethodParameters:
      Name                           Flags
      $this                          final

  public static boolean isSigned$extension(int);
    descriptor: (I)Z
    flags: (0x0009) ACC_PUBLIC, ACC_STATIC
    Code:
      stack=2, locals=1, args_size=1
         0: getstatic     #47                 // Field org/sireum/U30$.MODULE$:Lorg/sireum/U30$;
         3: iload_0
         4: invokevirtual #70                 // Method org/sireum/U30$.isSigned$extension:(I)Z
         7: ireturn
      LocalVariableTable:
        Start  Length  Slot  Name   Signature
            0       8     0 $this   I
    MethodParameters:
      Name                           Flags
      $this                          final

  public static boolean isZeroIndex$extension(int);
    descriptor: (I)Z
    flags: (0x0009) ACC_PUBLIC, ACC_STATIC
    Code:
      stack=2, locals=1, args_size=1
         0: getstatic     #47                 // Field org/sireum/U30$.MODULE$:Lorg/sireum/U30$;
         3: iload_0
         4: invokevirtual #73                 // Method org/sireum/U30$.isZeroIndex$extension:(I)Z
         7: ireturn
      LocalVariableTable:
        Start  Length  Slot  Name   Signature
            0       8     0 $this   I
    MethodParameters:
      Name                           Flags
      $this                          final

  public static int Index$extension(int);
    descriptor: (I)I
    flags: (0x0009) ACC_PUBLIC, ACC_STATIC
    Code:
      stack=2, locals=1, args_size=1
         0: getstatic     #47                 // Field org/sireum/U30$.MODULE$:Lorg/sireum/U30$;
         3: iload_0
         4: invokevirtual #76                 // Method org/sireum/U30$.Index$extension:(I)I
         7: ireturn
      LocalVariableTable:
        Start  Length  Slot  Name   Signature
            0       8     0 $this   I
    MethodParameters:
      Name                           Flags
      $this                          final

  public static int Max$extension(int);
    descriptor: (I)I
    flags: (0x0009) ACC_PUBLIC, ACC_STATIC
    Code:
      stack=2, locals=1, args_size=1
         0: getstatic     #47                 // Field org/sireum/U30$.MODULE$:Lorg/sireum/U30$;
         3: iload_0
         4: invokevirtual #79                 // Method org/sireum/U30$.Max$extension:(I)I
         7: ireturn
      LocalVariableTable:
        Start  Length  Slot  Name   Signature
            0       8     0 $this   I
    MethodParameters:
      Name                           Flags
      $this                          final

  public static int Min$extension(int);
    descriptor: (I)I
    flags: (0x0009) ACC_PUBLIC, ACC_STATIC
    Code:
      stack=2, locals=1, args_size=1
         0: getstatic     #47                 // Field org/sireum/U30$.MODULE$:Lorg/sireum/U30$;
         3: iload_0
         4: invokevirtual #82                 // Method org/sireum/U30$.Min$extension:(I)I
         7: ireturn
      LocalVariableTable:
        Start  Length  Slot  Name   Signature
            0       8     0 $this   I
    MethodParameters:
      Name                           Flags
      $this                          final

  public static int BitWidth$extension(int);
    descriptor: (I)I
    flags: (0x0009) ACC_PUBLIC, ACC_STATIC
    Code:
      stack=2, locals=1, args_size=1
         0: getstatic     #47                 // Field org/sireum/U30$.MODULE$:Lorg/sireum/U30$;
         3: iload_0
         4: invokevirtual #85                 // Method org/sireum/U30$.BitWidth$extension:(I)I
         7: ireturn
      LocalVariableTable:
        Start  Length  Slot  Name   Signature
            0       8     0 $this   I
    MethodParameters:
      Name                           Flags
      $this                          final

  public static java.lang.String Name$extension(int);
    descriptor: (I)Ljava/lang/String;
    flags: (0x0009) ACC_PUBLIC, ACC_STATIC
    Code:
      stack=2, locals=1, args_size=1
         0: getstatic     #47                 // Field org/sireum/U30$.MODULE$:Lorg/sireum/U30$;
         3: iload_0
         4: invokevirtual #89                 // Method org/sireum/U30$.Name$extension:(I)Ljava/lang/String;
         7: areturn
      LocalVariableTable:
        Start  Length  Slot  Name   Signature
            0       8     0 $this   I
    MethodParameters:
      Name                           Flags
      $this                          final

  public static org.sireum.$ZCompanion<org.sireum.U30> $U30Companion();
    descriptor: ()Lorg/sireum/$ZCompanion;
    flags: (0x0009) ACC_PUBLIC, ACC_STATIC
    Code:
      stack=1, locals=0, args_size=0
         0: getstatic     #47                 // Field org/sireum/U30$.MODULE$:Lorg/sireum/U30$;
         3: invokevirtual #94                 // Method org/sireum/U30$.$U30Companion:()Lorg/sireum/$ZCompanion;
         6: areturn
    Signature: #92                          // ()Lorg/sireum/$ZCompanion<Lorg/sireum/U30;>;

  public static org.sireum.U30$U30$Slang U30$Slang(scala.StringContext);
    descriptor: (Lscala/StringContext;)Lorg/sireum/U30$U30$Slang;
    flags: (0x0009) ACC_PUBLIC, ACC_STATIC
    Code:
      stack=2, locals=1, args_size=1
         0: getstatic     #47                 // Field org/sireum/U30$.MODULE$:Lorg/sireum/U30$;
         3: aload_0
         4: invokevirtual #98                 // Method org/sireum/U30$.U30$Slang:(Lscala/StringContext;)Lorg/sireum/U30$U30$Slang;
         7: areturn
      LocalVariableTable:
        Start  Length  Slot  Name   Signature
            0       8     0    sc   Lscala/StringContext;
    MethodParameters:
      Name                           Flags
      sc                             final

  public static scala.Option<org.sireum.Z> unapply(int);
    descriptor: (I)Lscala/Option;
    flags: (0x0009) ACC_PUBLIC, ACC_STATIC
    Code:
      stack=2, locals=1, args_size=1
         0: getstatic     #47                 // Field org/sireum/U30$.MODULE$:Lorg/sireum/U30$;
         3: iload_0
         4: invokevirtual #105                // Method org/sireum/U30$.unapply:(I)Lscala/Option;
         7: areturn
      LocalVariableTable:
        Start  Length  Slot  Name   Signature
            0       8     0     n   I
    Signature: #102                         // (I)Lscala/Option<Lorg/sireum/Z;>;
    MethodParameters:
      Name                           Flags
      n                              final

  public static org.sireum.Option<org.sireum.U30> apply(java.lang.String);
    descriptor: (Ljava/lang/String;)Lorg/sireum/Option;
    flags: (0x0009) ACC_PUBLIC, ACC_STATIC
    Code:
      stack=2, locals=1, args_size=1
         0: getstatic     #47                 // Field org/sireum/U30$.MODULE$:Lorg/sireum/U30$;
         3: aload_0
         4: invokevirtual #111                // Method org/sireum/U30$.apply:(Ljava/lang/String;)Lorg/sireum/Option;
         7: areturn
      LocalVariableTable:
        Start  Length  Slot  Name   Signature
            0       8     0     s   Ljava/lang/String;
    Signature: #108                         // (Ljava/lang/String;)Lorg/sireum/Option<Lorg/sireum/U30;>;
    MethodParameters:
      Name                           Flags
      s                              final

  public static int apply(org.sireum.Z);
    descriptor: (Lorg/sireum/Z;)I
    flags: (0x0009) ACC_PUBLIC, ACC_STATIC
    Code:
      stack=2, locals=1, args_size=1
         0: getstatic     #47                 // Field org/sireum/U30$.MODULE$:Lorg/sireum/U30$;
         3: aload_0
         4: invokevirtual #115                // Method org/sireum/U30$.apply:(Lorg/sireum/Z;)I
         7: ireturn
      LocalVariableTable:
        Start  Length  Slot  Name   Signature
            0       8     0     n   Lorg/sireum/Z;
    MethodParameters:
      Name                           Flags
      n                              final

  public static int apply(long);
    descriptor: (J)I
    flags: (0x0009) ACC_PUBLIC, ACC_STATIC
    Code:
      stack=3, locals=2, args_size=1
         0: getstatic     #47                 // Field org/sireum/U30$.MODULE$:Lorg/sireum/U30$;
         3: lload_0
         4: invokevirtual #119                // Method org/sireum/U30$.apply:(J)I
         7: ireturn
      LocalVariableTable:
        Start  Length  Slot  Name   Signature
            0       8     0     n   J
    MethodParameters:
      Name                           Flags
      n                              final

  public static int apply(int);
    descriptor: (I)I
    flags: (0x0009) ACC_PUBLIC, ACC_STATIC
    Code:
      stack=2, locals=1, args_size=1
         0: getstatic     #47                 // Field org/sireum/U30$.MODULE$:Lorg/sireum/U30$;
         3: iload_0
         4: invokevirtual #122                // Method org/sireum/U30$.apply:(I)I
         7: ireturn
      LocalVariableTable:
        Start  Length  Slot  Name   Signature
            0       8     0     n   I
    MethodParameters:
      Name                           Flags
      n                              final

  public static int randomSeed(org.sireum.Z);
    descriptor: (Lorg/sireum/Z;)I
    flags: (0x0009) ACC_PUBLIC, ACC_STATIC
    Code:
      stack=2, locals=1, args_size=1
         0: getstatic     #47                 // Field org/sireum/U30$.MODULE$:Lorg/sireum/U30$;
         3: aload_0
         4: invokevirtual #126                // Method org/sireum/U30$.randomSeed:(Lorg/sireum/Z;)I
         7: ireturn
      LocalVariableTable:
        Start  Length  Slot  Name   Signature
            0       8     0  seed   Lorg/sireum/Z;
    MethodParameters:
      Name                           Flags
      seed                           final

  public static int random();
    descriptor: ()I
    flags: (0x0009) ACC_PUBLIC, ACC_STATIC
    Code:
      stack=1, locals=0, args_size=0
         0: getstatic     #47                 // Field org/sireum/U30$.MODULE$:Lorg/sireum/U30$;
         3: invokevirtual #130                // Method org/sireum/U30$.random:()I
         6: ireturn

  public final boolean isBitVector();
    descriptor: ()Z
    flags: (0x0011) ACC_PUBLIC, ACC_FINAL
    Code:
      stack=1, locals=1, args_size=1
         0: aload_0
         1: invokestatic  #136                // InterfaceMethod org/sireum/Z$BV$Int.isBitVector$:(Lorg/sireum/Z$BV$Int;)Z
         4: ireturn
      LineNumberTable:
        line 113: 0
      LocalVariableTable:
        Start  Length  Slot  Name   Signature
            0       5     0  this   Lorg/sireum/U30;

  public final boolean hasMin();
    descriptor: ()Z
    flags: (0x0011) ACC_PUBLIC, ACC_FINAL
    Code:
      stack=1, locals=1, args_size=1
         0: aload_0
         1: invokestatic  #142                // InterfaceMethod org/sireum/Z$BV$Int.hasMin$:(Lorg/sireum/Z$BV$Int;)Z
         4: ireturn
      LineNumberTable:
        line 113: 0
      LocalVariableTable:
        Start  Length  Slot  Name   Signature
            0       5     0  this   Lorg/sireum/U30;

  public final boolean hasMax();
    descriptor: ()Z
    flags: (0x0011) ACC_PUBLIC, ACC_FINAL
    Code:
      stack=1, locals=1, args_size=1
         0: aload_0
         1: invokestatic  #146                // InterfaceMethod org/sireum/Z$BV$Int.hasMax$:(Lorg/sireum/Z$BV$Int;)Z
         4: ireturn
      LineNumberTable:
        line 113: 0
      LocalVariableTable:
        Start  Length  Slot  Name   Signature
            0       5     0  this   Lorg/sireum/U30;

  public final org.sireum.Z$BV$Int unary_$minus();
    descriptor: ()Lorg/sireum/Z$BV$Int;
    flags: (0x0011) ACC_PUBLIC, ACC_FINAL
    Code:
      stack=1, locals=1, args_size=1
         0: aload_0
         1: invokestatic  #152                // InterfaceMethod org/sireum/Z$BV$Int.unary_$minus$:(Lorg/sireum/Z$BV$Int;)Lorg/sireum/Z$BV$Int;
         4: areturn
      LineNumberTable:
        line 113: 0
      LocalVariableTable:
        Start  Length  Slot  Name   Signature
            0       5     0  this   Lorg/sireum/U30;

  public final org.sireum.Z$BV$Int $plus(org.sireum.Z$BV$Int);
    descriptor: (Lorg/sireum/Z$BV$Int;)Lorg/sireum/Z$BV$Int;
    flags: (0x0011) ACC_PUBLIC, ACC_FINAL
    Code:
      stack=2, locals=2, args_size=2
         0: aload_0
         1: aload_1
         2: invokestatic  #158                // InterfaceMethod org/sireum/Z$BV$Int.$plus$:(Lorg/sireum/Z$BV$Int;Lorg/sireum/Z$BV$Int;)Lorg/sireum/Z$BV$Int;
         5: areturn
      LineNumberTable:
        line 113: 0
      LocalVariableTable:
        Start  Length  Slot  Name   Signature
            0       6     0  this   Lorg/sireum/U30;
            0       6     1 other   Lorg/sireum/Z$BV$Int;
    MethodParameters:
      Name                           Flags
      other                          final

  public final org.sireum.Z$BV$Int $minus(org.sireum.Z$BV$Int);
    descriptor: (Lorg/sireum/Z$BV$Int;)Lorg/sireum/Z$BV$Int;
    flags: (0x0011) ACC_PUBLIC, ACC_FINAL
    Code:
      stack=2, locals=2, args_size=2
         0: aload_0
         1: aload_1
         2: invokestatic  #163                // InterfaceMethod org/sireum/Z$BV$Int.$minus$:(Lorg/sireum/Z$BV$Int;Lorg/sireum/Z$BV$Int;)Lorg/sireum/Z$BV$Int;
         5: areturn
      LineNumberTable:
        line 113: 0
      LocalVariableTable:
        Start  Length  Slot  Name   Signature
            0       6     0  this   Lorg/sireum/U30;
            0       6     1 other   Lorg/sireum/Z$BV$Int;
    MethodParameters:
      Name                           Flags
      other                          final

  public final org.sireum.Z$BV$Int $times(org.sireum.Z$BV$Int);
    descriptor: (Lorg/sireum/Z$BV$Int;)Lorg/sireum/Z$BV$Int;
    flags: (0x0011) ACC_PUBLIC, ACC_FINAL
    Code:
      stack=2, locals=2, args_size=2
         0: aload_0
         1: aload_1
         2: invokestatic  #167                // InterfaceMethod org/sireum/Z$BV$Int.$times$:(Lorg/sireum/Z$BV$Int;Lorg/sireum/Z$BV$Int;)Lorg/sireum/Z$BV$Int;
         5: areturn
      LineNumberTable:
        line 113: 0
      LocalVariableTable:
        Start  Length  Slot  Name   Signature
            0       6     0  this   Lorg/sireum/U30;
            0       6     1 other   Lorg/sireum/Z$BV$Int;
    MethodParameters:
      Name                           Flags
      other                          final

  public final org.sireum.Z$BV$Int $div(org.sireum.Z$BV$Int);
    descriptor: (Lorg/sireum/Z$BV$Int;)Lorg/sireum/Z$BV$Int;
    flags: (0x0011) ACC_PUBLIC, ACC_FINAL
    Code:
      stack=2, locals=2, args_size=2
         0: aload_0
         1: aload_1
         2: invokestatic  #171                // InterfaceMethod org/sireum/Z$BV$Int.$div$:(Lorg/sireum/Z$BV$Int;Lorg/sireum/Z$BV$Int;)Lorg/sireum/Z$BV$Int;
         5: areturn
      LineNumberTable:
        line 113: 0
      LocalVariableTable:
        Start  Length  Slot  Name   Signature
            0       6     0  this   Lorg/sireum/U30;
            0       6     1 other   Lorg/sireum/Z$BV$Int;
    MethodParameters:
      Name                           Flags
      other                          final

  public final org.sireum.Z$BV$Int $percent(org.sireum.Z$BV$Int);
    descriptor: (Lorg/sireum/Z$BV$Int;)Lorg/sireum/Z$BV$Int;
    flags: (0x0011) ACC_PUBLIC, ACC_FINAL
    Code:
      stack=2, locals=2, args_size=2
         0: aload_0
         1: aload_1
         2: invokestatic  #175                // InterfaceMethod org/sireum/Z$BV$Int.$percent$:(Lorg/sireum/Z$BV$Int;Lorg/sireum/Z$BV$Int;)Lorg/sireum/Z$BV$Int;
         5: areturn
      LineNumberTable:
        line 113: 0
      LocalVariableTable:
        Start  Length  Slot  Name   Signature
            0       6     0  this   Lorg/sireum/U30;
            0       6     1 other   Lorg/sireum/Z$BV$Int;
    MethodParameters:
      Name                           Flags
      other                          final

  public final boolean $greater(org.sireum.Z$BV$Int);
    descriptor: (Lorg/sireum/Z$BV$Int;)Z
    flags: (0x0011) ACC_PUBLIC, ACC_FINAL
    Code:
      stack=2, locals=2, args_size=2
         0: aload_0
         1: aload_1
         2: invokestatic  #180                // InterfaceMethod org/sireum/Z$BV$Int.$greater$:(Lorg/sireum/Z$BV$Int;Lorg/sireum/Z$BV$Int;)Z
         5: ireturn
      LineNumberTable:
        line 113: 0
      LocalVariableTable:
        Start  Length  Slot  Name   Signature
            0       6     0  this   Lorg/sireum/U30;
            0       6     1 other   Lorg/sireum/Z$BV$Int;
    MethodParameters:
      Name                           Flags
      other                          final

  public final boolean $greater$eq(org.sireum.Z$BV$Int);
    descriptor: (Lorg/sireum/Z$BV$Int;)Z
    flags: (0x0011) ACC_PUBLIC, ACC_FINAL
    Code:
      stack=2, locals=2, args_size=2
         0: aload_0
         1: aload_1
         2: invokestatic  #184                // InterfaceMethod org/sireum/Z$BV$Int.$greater$eq$:(Lorg/sireum/Z$BV$Int;Lorg/sireum/Z$BV$Int;)Z
         5: ireturn
      LineNumberTable:
        line 113: 0
      LocalVariableTable:
        Start  Length  Slot  Name   Signature
            0       6     0  this   Lorg/sireum/U30;
            0       6     1 other   Lorg/sireum/Z$BV$Int;
    MethodParameters:
      Name                           Flags
      other                          final

  public final boolean $less(org.sireum.Z$BV$Int);
    descriptor: (Lorg/sireum/Z$BV$Int;)Z
    flags: (0x0011) ACC_PUBLIC, ACC_FINAL
    Code:
      stack=2, locals=2, args_size=2
         0: aload_0
         1: aload_1
         2: invokestatic  #188                // InterfaceMethod org/sireum/Z$BV$Int.$less$:(Lorg/sireum/Z$BV$Int;Lorg/sireum/Z$BV$Int;)Z
         5: ireturn
      LineNumberTable:
        line 113: 0
      LocalVariableTable:
        Start  Length  Slot  Name   Signature
            0       6     0  this   Lorg/sireum/U30;
            0       6     1 other   Lorg/sireum/Z$BV$Int;
    MethodParameters:
      Name                           Flags
      other                          final

  public final boolean $less$eq(org.sireum.Z$BV$Int);
    descriptor: (Lorg/sireum/Z$BV$Int;)Z
    flags: (0x0011) ACC_PUBLIC, ACC_FINAL
    Code:
      stack=2, locals=2, args_size=2
         0: aload_0
         1: aload_1
         2: invokestatic  #192                // InterfaceMethod org/sireum/Z$BV$Int.$less$eq$:(Lorg/sireum/Z$BV$Int;Lorg/sireum/Z$BV$Int;)Z
         5: ireturn
      LineNumberTable:
        line 113: 0
      LocalVariableTable:
        Start  Length  Slot  Name   Signature
            0       6     0  this   Lorg/sireum/U30;
            0       6     1 other   Lorg/sireum/Z$BV$Int;
    MethodParameters:
      Name                           Flags
      other                          final

  public final org.sireum.Z$BV$Int $greater$greater(org.sireum.Z$BV$Int);
    descriptor: (Lorg/sireum/Z$BV$Int;)Lorg/sireum/Z$BV$Int;
    flags: (0x0011) ACC_PUBLIC, ACC_FINAL
    Code:
      stack=2, locals=2, args_size=2
         0: aload_0
         1: aload_1
         2: invokestatic  #196                // InterfaceMethod org/sireum/Z$BV$Int.$greater$greater$:(Lorg/sireum/Z$BV$Int;Lorg/sireum/Z$BV$Int;)Lorg/sireum/Z$BV$Int;
         5: areturn
      LineNumberTable:
        line 113: 0
      LocalVariableTable:
        Start  Length  Slot  Name   Signature
            0       6     0  this   Lorg/sireum/U30;
            0       6     1 other   Lorg/sireum/Z$BV$Int;
    MethodParameters:
      Name                           Flags
      other                          final

  public final org.sireum.Z$BV$Int $greater$greater$greater(org.sireum.Z$BV$Int);
    descriptor: (Lorg/sireum/Z$BV$Int;)Lorg/sireum/Z$BV$Int;
    flags: (0x0011) ACC_PUBLIC, ACC_FINAL
    Code:
      stack=2, locals=2, args_size=2
         0: aload_0
         1: aload_1
         2: invokestatic  #200                // InterfaceMethod org/sireum/Z$BV$Int.$greater$greater$greater$:(Lorg/sireum/Z$BV$Int;Lorg/sireum/Z$BV$Int;)Lorg/sireum/Z$BV$Int;
         5: areturn
      LineNumberTable:
        line 113: 0
      LocalVariableTable:
        Start  Length  Slot  Name   Signature
            0       6     0  this   Lorg/sireum/U30;
            0       6     1 other   Lorg/sireum/Z$BV$Int;
    MethodParameters:
      Name                           Flags
      other                          final

  public final org.sireum.Z$BV$Int $less$less(org.sireum.Z$BV$Int);
    descriptor: (Lorg/sireum/Z$BV$Int;)Lorg/sireum/Z$BV$Int;
    flags: (0x0011) ACC_PUBLIC, ACC_FINAL
    Code:
      stack=2, locals=2, args_size=2
         0: aload_0
         1: aload_1
         2: invokestatic  #204                // InterfaceMethod org/sireum/Z$BV$Int.$less$less$:(Lorg/sireum/Z$BV$Int;Lorg/sireum/Z$BV$Int;)Lorg/sireum/Z$BV$Int;
         5: areturn
      LineNumberTable:
        line 113: 0
      LocalVariableTable:
        Start  Length  Slot  Name   Signature
            0       6     0  this   Lorg/sireum/U30;
            0       6     1 other   Lorg/sireum/Z$BV$Int;
    MethodParameters:
      Name                           Flags
      other                          final

  public final org.sireum.Z$BV$Int $amp(org.sireum.Z$BV$Int);
    descriptor: (Lorg/sireum/Z$BV$Int;)Lorg/sireum/Z$BV$Int;
    flags: (0x0011) ACC_PUBLIC, ACC_FINAL
    Code:
      stack=2, locals=2, args_size=2
         0: aload_0
         1: aload_1
         2: invokestatic  #208                // InterfaceMethod org/sireum/Z$BV$Int.$amp$:(Lorg/sireum/Z$BV$Int;Lorg/sireum/Z$BV$Int;)Lorg/sireum/Z$BV$Int;
         5: areturn
      LineNumberTable:
        line 113: 0
      LocalVariableTable:
        Start  Length  Slot  Name   Signature
            0       6     0  this   Lorg/sireum/U30;
            0       6     1 other   Lorg/sireum/Z$BV$Int;
    MethodParameters:
      Name                           Flags
      other                          final

  public final org.sireum.Z$BV$Int $bar(org.sireum.Z$BV$Int);
    descriptor: (Lorg/sireum/Z$BV$Int;)Lorg/sireum/Z$BV$Int;
    flags: (0x0011) ACC_PUBLIC, ACC_FINAL
    Code:
      stack=2, locals=2, args_size=2
         0: aload_0
         1: aload_1
         2: invokestatic  #212                // InterfaceMethod org/sireum/Z$BV$Int.$bar$:(Lorg/sireum/Z$BV$Int;Lorg/sireum/Z$BV$Int;)Lorg/sireum/Z$BV$Int;
         5: areturn
      LineNumberTable:
        line 113: 0
      LocalVariableTable:
        Start  Length  Slot  Name   Signature
            0       6     0  this   Lorg/sireum/U30;
            0       6     1 other   Lorg/sireum/Z$BV$Int;
    MethodParameters:
      Name                           Flags
      other                          final

  public final org.sireum.Z$BV$Int $bar$up(org.sireum.Z$BV$Int);
    descriptor: (Lorg/sireum/Z$BV$Int;)Lorg/sireum/Z$BV$Int;
    flags: (0x0011) ACC_PUBLIC, ACC_FINAL
    Code:
      stack=2, locals=2, args_size=2
         0: aload_0
         1: aload_1
         2: invokestatic  #216                // InterfaceMethod org/sireum/Z$BV$Int.$bar$up$:(Lorg/sireum/Z$BV$Int;Lorg/sireum/Z$BV$Int;)Lorg/sireum/Z$BV$Int;
         5: areturn
      LineNumberTable:
        line 113: 0
      LocalVariableTable:
        Start  Length  Slot  Name   Signature
            0       6     0  this   Lorg/sireum/U30;
            0       6     1 other   Lorg/sireum/Z$BV$Int;
    MethodParameters:
      Name                           Flags
      other                          final

  public final org.sireum.Z$BV$Int unary_$tilde();
    descriptor: ()Lorg/sireum/Z$BV$Int;
    flags: (0x0011) ACC_PUBLIC, ACC_FINAL
    Code:
      stack=1, locals=1, args_size=1
         0: aload_0
         1: invokestatic  #220                // InterfaceMethod org/sireum/Z$BV$Int.unary_$tilde$:(Lorg/sireum/Z$BV$Int;)Lorg/sireum/Z$BV$Int;
         4: areturn
      LineNumberTable:
        line 113: 0
      LocalVariableTable:
        Start  Length  Slot  Name   Signature
            0       5     0  this   Lorg/sireum/U30;

  public final org.sireum.Z$BV$Int increase();
    descriptor: ()Lorg/sireum/Z$BV$Int;
    flags: (0x0011) ACC_PUBLIC, ACC_FINAL
    Code:
      stack=1, locals=1, args_size=1
         0: aload_0
         1: invokestatic  #224                // InterfaceMethod org/sireum/Z$BV$Int.increase$:(Lorg/sireum/Z$BV$Int;)Lorg/sireum/Z$BV$Int;
         4: areturn
      LineNumberTable:
        line 113: 0
      LocalVariableTable:
        Start  Length  Slot  Name   Signature
            0       5     0  this   Lorg/sireum/U30;

  public final org.sireum.Z$BV$Int decrease();
    descriptor: ()Lorg/sireum/Z$BV$Int;
    flags: (0x0011) ACC_PUBLIC, ACC_FINAL
    Code:
      stack=1, locals=1, args_size=1
         0: aload_0
         1: invokestatic  #228                // InterfaceMethod org/sireum/Z$BV$Int.decrease$:(Lorg/sireum/Z$BV$Int;)Lorg/sireum/Z$BV$Int;
         4: areturn
      LineNumberTable:
        line 113: 0
      LocalVariableTable:
        Start  Length  Slot  Name   Signature
            0       5     0  this   Lorg/sireum/U30;

  public final java.lang.String toString();
    descriptor: ()Ljava/lang/String;
    flags: (0x0011) ACC_PUBLIC, ACC_FINAL
    Code:
      stack=1, locals=1, args_size=1
         0: aload_0
         1: invokestatic  #234                // InterfaceMethod org/sireum/Z$BV$Int.toString$:(Lorg/sireum/Z$BV$Int;)Ljava/lang/String;
         4: areturn
      LineNumberTable:
        line 113: 0
      LocalVariableTable:
        Start  Length  Slot  Name   Signature
            0       5     0  this   Lorg/sireum/U30;

  public final scala.math.BigInt toBigInt();
    descriptor: ()Lscala/math/BigInt;
    flags: (0x0011) ACC_PUBLIC, ACC_FINAL
    Code:
      stack=1, locals=1, args_size=1
         0: aload_0
         1: invokestatic  #240                // InterfaceMethod org/sireum/Z$BV$Int.toBigInt$:(Lorg/sireum/Z$BV$Int;)Lscala/math/BigInt;
         4: areturn
      LineNumberTable:
        line 113: 0
      LocalVariableTable:
        Start  Length  Slot  Name   Signature
            0       5     0  this   Lorg/sireum/U30;

  public final org.sireum.Z toMP();
    descriptor: ()Lorg/sireum/Z;
    flags: (0x0011) ACC_PUBLIC, ACC_FINAL
    Code:
      stack=1, locals=1, args_size=1
         0: aload_0
         1: invokestatic  #246                // InterfaceMethod org/sireum/Z$BV$Int.toMP$:(Lorg/sireum/Z$BV$Int;)Lorg/sireum/Z;
         4: areturn
      LineNumberTable:
        line 113: 0
      LocalVariableTable:
        Start  Length  Slot  Name   Signature
            0       5     0  this   Lorg/sireum/U30;

  public final org.sireum.Z toIndex();
    descriptor: ()Lorg/sireum/Z;
    flags: (0x0011) ACC_PUBLIC, ACC_FINAL
    Code:
      stack=1, locals=1, args_size=1
         0: aload_0
         1: invokestatic  #250                // InterfaceMethod org/sireum/Z$BV$Int.toIndex$:(Lorg/sireum/Z$BV$Int;)Lorg/sireum/Z;
         4: areturn
      LineNumberTable:
        line 113: 0
      LocalVariableTable:
        Start  Length  Slot  Name   Signature
            0       5     0  this   Lorg/sireum/U30;

  public boolean $eq$eq$eq(org.sireum.Z);
    descriptor: (Lorg/sireum/Z;)Z
    flags: (0x0001) ACC_PUBLIC
    Code:
      stack=2, locals=2, args_size=2
         0: aload_0
         1: aload_1
         2: invokestatic  #258                // InterfaceMethod org/sireum/ZLike.$eq$eq$eq$:(Lorg/sireum/ZLike;Lorg/sireum/Z;)Z
         5: ireturn
      LineNumberTable:
        line 113: 0
      LocalVariableTable:
        Start  Length  Slot  Name   Signature
            0       6     0  this   Lorg/sireum/U30;
            0       6     1 other   Lorg/sireum/Z;
    MethodParameters:
      Name                           Flags
      other                          final

  public boolean $eq$bang$eq(org.sireum.Z);
    descriptor: (Lorg/sireum/Z;)Z
    flags: (0x0001) ACC_PUBLIC
    Code:
      stack=2, locals=2, args_size=2
         0: aload_0
         1: aload_1
         2: invokestatic  #262                // InterfaceMethod org/sireum/ZLike.$eq$bang$eq$:(Lorg/sireum/ZLike;Lorg/sireum/Z;)Z
         5: ireturn
      LineNumberTable:
        line 113: 0
      LocalVariableTable:
        Start  Length  Slot  Name   Signature
            0       6     0  this   Lorg/sireum/U30;
            0       6     1 other   Lorg/sireum/Z;
    MethodParameters:
      Name                           Flags
      other                          final

  public final java.lang.String string();
    descriptor: ()Ljava/lang/String;
    flags: (0x0011) ACC_PUBLIC, ACC_FINAL
    Code:
      stack=1, locals=1, args_size=1
         0: aload_0
         1: invokestatic  #267                // InterfaceMethod org/sireum/ZLike.string$:(Lorg/sireum/ZLike;)Ljava/lang/String;
         4: areturn
      LineNumberTable:
        line 113: 0
      LocalVariableTable:
        Start  Length  Slot  Name   Signature
            0       5     0  this   Lorg/sireum/U30;

  public org.sireum.ZRange to(org.sireum.ZLike);
    descriptor: (Lorg/sireum/ZLike;)Lorg/sireum/ZRange;
    flags: (0x0001) ACC_PUBLIC
    Code:
      stack=2, locals=2, args_size=2
         0: aload_0
         1: aload_1
         2: invokestatic  #273                // InterfaceMethod org/sireum/ZLike.to$:(Lorg/sireum/ZLike;Lorg/sireum/ZLike;)Lorg/sireum/ZRange;
         5: areturn
      LineNumberTable:
        line 113: 0
      LocalVariableTable:
        Start  Length  Slot  Name   Signature
            0       6     0  this   Lorg/sireum/U30;
            0       6     1     n   Lorg/sireum/ZLike;
    MethodParameters:
      Name                           Flags
      n                              final

  public org.sireum.ZRange until(org.sireum.ZLike);
    descriptor: (Lorg/sireum/ZLike;)Lorg/sireum/ZRange;
    flags: (0x0001) ACC_PUBLIC
    Code:
      stack=2, locals=2, args_size=2
         0: aload_0
         1: aload_1
         2: invokestatic  #278                // InterfaceMethod org/sireum/ZLike.until$:(Lorg/sireum/ZLike;Lorg/sireum/ZLike;)Lorg/sireum/ZRange;
         5: areturn
      LineNumberTable:
        line 113: 0
      LocalVariableTable:
        Start  Length  Slot  Name   Signature
            0       6     0  this   Lorg/sireum/U30;
            0       6     1     n   Lorg/sireum/ZLike;
    MethodParameters:
      Name                           Flags
      n                              final

  public int compareTo(org.sireum.ZLike);
    descriptor: (Lorg/sireum/ZLike;)I
    flags: (0x0001) ACC_PUBLIC
    Code:
      stack=2, locals=2, args_size=2
         0: aload_0
         1: aload_1
         2: invokestatic  #284                // InterfaceMethod org/sireum/ZLike.compareTo$:(Lorg/sireum/ZLike;Lorg/sireum/ZLike;)I
         5: ireturn
      LineNumberTable:
        line 113: 0
      LocalVariableTable:
        Start  Length  Slot  Name   Signature
            0       6     0  this   Lorg/sireum/U30;
            0       6     1 other   Lorg/sireum/ZLike;
    MethodParameters:
      Name                           Flags
      other                          final

  public final scala.runtime.Nothing$ $cannotMixImmutableAndMutable();
    descriptor: ()Lscala/runtime/Nothing$;
    flags: (0x0011) ACC_PUBLIC, ACC_FINAL
    Code:
      stack=1, locals=1, args_size=1
         0: aload_0
         1: invokestatic  #292                // InterfaceMethod org/sireum/Immutable.$cannotMixImmutableAndMutable$:(Lorg/sireum/Immutable;)Lscala/runtime/Nothing$;
         4: areturn
      LineNumberTable:
        line 113: 0
      LocalVariableTable:
        Start  Length  Slot  Name   Signature
            0       5     0  this   Lorg/sireum/U30;

  public boolean $hasEquals();
    descriptor: ()Z
    flags: (0x0001) ACC_PUBLIC
    Code:
      stack=1, locals=1, args_size=1
         0: aload_0
         1: invokestatic  #297                // InterfaceMethod org/sireum/Immutable.$hasEquals$:(Lorg/sireum/Immutable;)Z
         4: ireturn
      LineNumberTable:
        line 113: 0
      LocalVariableTable:
        Start  Length  Slot  Name   Signature
            0       5     0  this   Lorg/sireum/U30;

  public boolean $hasString();
    descriptor: ()Z
    flags: (0x0001) ACC_PUBLIC
    Code:
      stack=1, locals=1, args_size=1
         0: aload_0
         1: invokestatic  #301                // InterfaceMethod org/sireum/Immutable.$hasString$:(Lorg/sireum/Immutable;)Z
         4: ireturn
      LineNumberTable:
        line 113: 0
      LocalVariableTable:
        Start  Length  Slot  Name   Signature
            0       5     0  this   Lorg/sireum/U30;

  public org.sireum.$internal.ImmutableMarker $clone();
    descriptor: ()Lorg/sireum/$internal/ImmutableMarker;
    flags: (0x0001) ACC_PUBLIC
    Code:
      stack=1, locals=1, args_size=1
         0: aload_0
         1: invokestatic  #309                // InterfaceMethod org/sireum/$internal/ImmutableMarker.$clone$:(Lorg/sireum/$internal/ImmutableMarker;)Lorg/sireum/$internal/ImmutableMarker;
         4: areturn
      LineNumberTable:
        line 113: 0
      LocalVariableTable:
        Start  Length  Slot  Name   Signature
            0       5     0  this   Lorg/sireum/U30;

  public int value();
    descriptor: ()I
    flags: (0x0001) ACC_PUBLIC
    Code:
      stack=1, locals=1, args_size=1
         0: aload_0
         1: getfield      #311                // Field value:I
         4: ireturn
      LineNumberTable:
        line 113: 0
      LocalVariableTable:
        Start  Length  Slot  Name   Signature
            0       5     0  this   Lorg/sireum/U30;

  public java.lang.String Name();
    descriptor: ()Ljava/lang/String;
    flags: (0x0001) ACC_PUBLIC
    Code:
      stack=2, locals=1, args_size=1
         0: getstatic     #47                 // Field org/sireum/U30$.MODULE$:Lorg/sireum/U30$;
         3: aload_0
         4: invokevirtual #314                // Method value:()I
         7: invokevirtual #89                 // Method org/sireum/U30$.Name$extension:(I)Ljava/lang/String;
        10: areturn
      LineNumberTable:
        line 113: 0
      LocalVariableTable:
        Start  Length  Slot  Name   Signature
            0      11     0  this   Lorg/sireum/U30;

  public int BitWidth();
    descriptor: ()I
    flags: (0x0001) ACC_PUBLIC
    Code:
      stack=2, locals=1, args_size=1
         0: getstatic     #47                 // Field org/sireum/U30$.MODULE$:Lorg/sireum/U30$;
         3: aload_0
         4: invokevirtual #314                // Method value:()I
         7: invokevirtual #85                 // Method org/sireum/U30$.BitWidth$extension:(I)I
        10: ireturn
      LineNumberTable:
        line 113: 0
      LocalVariableTable:
        Start  Length  Slot  Name   Signature
            0      11     0  this   Lorg/sireum/U30;

  public int Min();
    descriptor: ()I
    flags: (0x0001) ACC_PUBLIC
    Code:
      stack=2, locals=1, args_size=1
         0: getstatic     #47                 // Field org/sireum/U30$.MODULE$:Lorg/sireum/U30$;
         3: aload_0
         4: invokevirtual #314                // Method value:()I
         7: invokevirtual #82                 // Method org/sireum/U30$.Min$extension:(I)I
        10: ireturn
      LineNumberTable:
        line 113: 0
      LocalVariableTable:
        Start  Length  Slot  Name   Signature
            0      11     0  this   Lorg/sireum/U30;

  public int Max();
    descriptor: ()I
    flags: (0x0001) ACC_PUBLIC
    Code:
      stack=2, locals=1, args_size=1
         0: getstatic     #47                 // Field org/sireum/U30$.MODULE$:Lorg/sireum/U30$;
         3: aload_0
         4: invokevirtual #314                // Method value:()I
         7: invokevirtual #79                 // Method org/sireum/U30$.Max$extension:(I)I
        10: ireturn
      LineNumberTable:
        line 113: 0
      LocalVariableTable:
        Start  Length  Slot  Name   Signature
            0      11     0  this   Lorg/sireum/U30;

  public int Index();
    descriptor: ()I
    flags: (0x0001) ACC_PUBLIC
    Code:
      stack=2, locals=1, args_size=1
         0: getstatic     #47                 // Field org/sireum/U30$.MODULE$:Lorg/sireum/U30$;
         3: aload_0
         4: invokevirtual #314                // Method value:()I
         7: invokevirtual #76                 // Method org/sireum/U30$.Index$extension:(I)I
        10: ireturn
      LineNumberTable:
        line 113: 0
      LocalVariableTable:
        Start  Length  Slot  Name   Signature
            0      11     0  this   Lorg/sireum/U30;

  public boolean isZeroIndex();
    descriptor: ()Z
    flags: (0x0001) ACC_PUBLIC
    Code:
      stack=2, locals=1, args_size=1
         0: getstatic     #47                 // Field org/sireum/U30$.MODULE$:Lorg/sireum/U30$;
         3: aload_0
         4: invokevirtual #314                // Method value:()I
         7: invokevirtual #73                 // Method org/sireum/U30$.isZeroIndex$extension:(I)Z
        10: ireturn
      LineNumberTable:
        line 113: 0
      LocalVariableTable:
        Start  Length  Slot  Name   Signature
            0      11     0  this   Lorg/sireum/U30;

  public boolean isSigned();
    descriptor: ()Z
    flags: (0x0001) ACC_PUBLIC
    Code:
      stack=2, locals=1, args_size=1
         0: getstatic     #47                 // Field org/sireum/U30$.MODULE$:Lorg/sireum/U30$;
         3: aload_0
         4: invokevirtual #314                // Method value:()I
         7: invokevirtual #70                 // Method org/sireum/U30$.isSigned$extension:(I)Z
        10: ireturn
      LineNumberTable:
        line 113: 0
      LocalVariableTable:
        Start  Length  Slot  Name   Signature
            0      11     0  this   Lorg/sireum/U30;

  public boolean isWrapped();
    descriptor: ()Z
    flags: (0x0001) ACC_PUBLIC
    Code:
      stack=2, locals=1, args_size=1
         0: getstatic     #47                 // Field org/sireum/U30$.MODULE$:Lorg/sireum/U30$;
         3: aload_0
         4: invokevirtual #314                // Method value:()I
         7: invokevirtual #67                 // Method org/sireum/U30$.isWrapped$extension:(I)Z
        10: ireturn
      LineNumberTable:
        line 113: 0
      LocalVariableTable:
        Start  Length  Slot  Name   Signature
            0      11     0  this   Lorg/sireum/U30;

  public int make(int);
    descriptor: (I)I
    flags: (0x0001) ACC_PUBLIC
    Code:
      stack=3, locals=2, args_size=2
         0: getstatic     #47                 // Field org/sireum/U30$.MODULE$:Lorg/sireum/U30$;
         3: aload_0
         4: invokevirtual #314                // Method value:()I
         7: iload_1
         8: invokevirtual #63                 // Method org/sireum/U30$.make$extension:(II)I
        11: ireturn
      LineNumberTable:
        line 113: 0
      LocalVariableTable:
        Start  Length  Slot  Name   Signature
            0      12     0  this   Lorg/sireum/U30;
            0      12     1     v   I
    MethodParameters:
      Name                           Flags
      v                              final

  public org.sireum.U30$Boxer$ boxer();
    descriptor: ()Lorg/sireum/U30$Boxer$;
    flags: (0x0001) ACC_PUBLIC
    Code:
      stack=2, locals=1, args_size=1
         0: getstatic     #47                 // Field org/sireum/U30$.MODULE$:Lorg/sireum/U30$;
         3: aload_0
         4: invokevirtual #314                // Method value:()I
         7: invokevirtual #58                 // Method org/sireum/U30$.boxer$extension:(I)Lorg/sireum/U30$Boxer$;
        10: areturn
      LineNumberTable:
        line 113: 0
      LocalVariableTable:
        Start  Length  Slot  Name   Signature
            0      11     0  this   Lorg/sireum/U30;

  public int hashCode();
    descriptor: ()I
    flags: (0x0001) ACC_PUBLIC
    Code:
      stack=2, locals=1, args_size=1
         0: getstatic     #47                 // Field org/sireum/U30$.MODULE$:Lorg/sireum/U30$;
         3: aload_0
         4: invokevirtual #314                // Method value:()I
         7: invokevirtual #54                 // Method org/sireum/U30$.hashCode$extension:(I)I
        10: ireturn
      LineNumberTable:
        line 113: 0
      LocalVariableTable:
        Start  Length  Slot  Name   Signature
            0      11     0  this   Lorg/sireum/U30;

  public boolean equals(java.lang.Object);
    descriptor: (Ljava/lang/Object;)Z
    flags: (0x0001) ACC_PUBLIC
    Code:
      stack=3, locals=2, args_size=2
         0: getstatic     #47                 // Field org/sireum/U30$.MODULE$:Lorg/sireum/U30$;
         3: aload_0
         4: invokevirtual #314                // Method value:()I
         7: aload_1
         8: invokevirtual #49                 // Method org/sireum/U30$.equals$extension:(ILjava/lang/Object;)Z
        11: ireturn
      LineNumberTable:
        line 113: 0
      LocalVariableTable:
        Start  Length  Slot  Name   Signature
            0      12     0  this   Lorg/sireum/U30;
            0      12     1   x$1   Ljava/lang/Object;
    MethodParameters:
      Name                           Flags
      x$1                            final

  public java.lang.Object $clone();
    descriptor: ()Ljava/lang/Object;
    flags: (0x1041) ACC_PUBLIC, ACC_BRIDGE, ACC_SYNTHETIC
    Code:
      stack=1, locals=1, args_size=1
         0: aload_0
         1: invokevirtual #330                // Method $clone:()Lorg/sireum/$internal/ImmutableMarker;
         4: areturn
      LineNumberTable:
        line 113: 0
      LocalVariableTable:
        Start  Length  Slot  Name   Signature
            0       5     0  this   Lorg/sireum/U30;

  public int compareTo(java.lang.Object);
    descriptor: (Ljava/lang/Object;)I
    flags: (0x1041) ACC_PUBLIC, ACC_BRIDGE, ACC_SYNTHETIC
    Code:
      stack=2, locals=2, args_size=2
         0: aload_0
         1: aload_1
         2: checkcast     #254                // class org/sireum/ZLike
         5: invokevirtual #333                // Method compareTo:(Lorg/sireum/ZLike;)I
         8: ireturn
      LineNumberTable:
        line 113: 0
      LocalVariableTable:
        Start  Length  Slot  Name   Signature
            0       9     0  this   Lorg/sireum/U30;
            0       9     1   x$1   Ljava/lang/Object;
    MethodParameters:
      Name                           Flags
      x$1                            final

  public final org.sireum.ZLike decrease();
    descriptor: ()Lorg/sireum/ZLike;
    flags: (0x1051) ACC_PUBLIC, ACC_FINAL, ACC_BRIDGE, ACC_SYNTHETIC
    Code:
      stack=1, locals=1, args_size=1
         0: aload_0
         1: invokevirtual #336                // Method decrease:()Lorg/sireum/Z$BV$Int;
         4: areturn
      LineNumberTable:
        line 113: 0
      LocalVariableTable:
        Start  Length  Slot  Name   Signature
            0       5     0  this   Lorg/sireum/U30;

  public final org.sireum.ZLike increase();
    descriptor: ()Lorg/sireum/ZLike;
    flags: (0x1051) ACC_PUBLIC, ACC_FINAL, ACC_BRIDGE, ACC_SYNTHETIC
    Code:
      stack=1, locals=1, args_size=1
         0: aload_0
         1: invokevirtual #338                // Method increase:()Lorg/sireum/Z$BV$Int;
         4: areturn
      LineNumberTable:
        line 113: 0
      LocalVariableTable:
        Start  Length  Slot  Name   Signature
            0       5     0  this   Lorg/sireum/U30;

  public final boolean $less$eq(org.sireum.ZLike);
    descriptor: (Lorg/sireum/ZLike;)Z
    flags: (0x1051) ACC_PUBLIC, ACC_FINAL, ACC_BRIDGE, ACC_SYNTHETIC
    Code:
      stack=2, locals=2, args_size=2
         0: aload_0
         1: aload_1
         2: checkcast     #7                  // class org/sireum/Z$BV$Int
         5: invokevirtual #341                // Method $less$eq:(Lorg/sireum/Z$BV$Int;)Z
         8: ireturn
      LineNumberTable:
        line 113: 0
      LocalVariableTable:
        Start  Length  Slot  Name   Signature
            0       9     0  this   Lorg/sireum/U30;
            0       9     1 other   Lorg/sireum/ZLike;
    MethodParameters:
      Name                           Flags
      other                          final

  public final boolean $less(org.sireum.ZLike);
    descriptor: (Lorg/sireum/ZLike;)Z
    flags: (0x1051) ACC_PUBLIC, ACC_FINAL, ACC_BRIDGE, ACC_SYNTHETIC
    Code:
      stack=2, locals=2, args_size=2
         0: aload_0
         1: aload_1
         2: checkcast     #7                  // class org/sireum/Z$BV$Int
         5: invokevirtual #343                // Method $less:(Lorg/sireum/Z$BV$Int;)Z
         8: ireturn
      LineNumberTable:
        line 113: 0
      LocalVariableTable:
        Start  Length  Slot  Name   Signature
            0       9     0  this   Lorg/sireum/U30;
            0       9     1 other   Lorg/sireum/ZLike;
    MethodParameters:
      Name                           Flags
      other                          final

  public final boolean $greater$eq(org.sireum.ZLike);
    descriptor: (Lorg/sireum/ZLike;)Z
    flags: (0x1051) ACC_PUBLIC, ACC_FINAL, ACC_BRIDGE, ACC_SYNTHETIC
    Code:
      stack=2, locals=2, args_size=2
         0: aload_0
         1: aload_1
         2: checkcast     #7                  // class org/sireum/Z$BV$Int
         5: invokevirtual #345                // Method $greater$eq:(Lorg/sireum/Z$BV$Int;)Z
         8: ireturn
      LineNumberTable:
        line 113: 0
      LocalVariableTable:
        Start  Length  Slot  Name   Signature
            0       9     0  this   Lorg/sireum/U30;
            0       9     1 other   Lorg/sireum/ZLike;
    MethodParameters:
      Name                           Flags
      other                          final

  public final boolean $greater(org.sireum.ZLike);
    descriptor: (Lorg/sireum/ZLike;)Z
    flags: (0x1051) ACC_PUBLIC, ACC_FINAL, ACC_BRIDGE, ACC_SYNTHETIC
    Code:
      stack=2, locals=2, args_size=2
         0: aload_0
         1: aload_1
         2: checkcast     #7                  // class org/sireum/Z$BV$Int
         5: invokevirtual #347                // Method $greater:(Lorg/sireum/Z$BV$Int;)Z
         8: ireturn
      LineNumberTable:
        line 113: 0
      LocalVariableTable:
        Start  Length  Slot  Name   Signature
            0       9     0  this   Lorg/sireum/U30;
            0       9     1 other   Lorg/sireum/ZLike;
    MethodParameters:
      Name                           Flags
      other                          final

  public final org.sireum.ZLike $percent(org.sireum.ZLike);
    descriptor: (Lorg/sireum/ZLike;)Lorg/sireum/ZLike;
    flags: (0x1051) ACC_PUBLIC, ACC_FINAL, ACC_BRIDGE, ACC_SYNTHETIC
    Code:
      stack=2, locals=2, args_size=2
         0: aload_0
         1: aload_1
         2: checkcast     #7                  // class org/sireum/Z$BV$Int
         5: invokevirtual #350                // Method $percent:(Lorg/sireum/Z$BV$Int;)Lorg/sireum/Z$BV$Int;
         8: areturn
      LineNumberTable:
        line 113: 0
      LocalVariableTable:
        Start  Length  Slot  Name   Signature
            0       9     0  this   Lorg/sireum/U30;
            0       9     1 other   Lorg/sireum/ZLike;
    MethodParameters:
      Name                           Flags
      other                          final

  public final org.sireum.ZLike $div(org.sireum.ZLike);
    descriptor: (Lorg/sireum/ZLike;)Lorg/sireum/ZLike;
    flags: (0x1051) ACC_PUBLIC, ACC_FINAL, ACC_BRIDGE, ACC_SYNTHETIC
    Code:
      stack=2, locals=2, args_size=2
         0: aload_0
         1: aload_1
         2: checkcast     #7                  // class org/sireum/Z$BV$Int
         5: invokevirtual #352                // Method $div:(Lorg/sireum/Z$BV$Int;)Lorg/sireum/Z$BV$Int;
         8: areturn
      LineNumberTable:
        line 113: 0
      LocalVariableTable:
        Start  Length  Slot  Name   Signature
            0       9     0  this   Lorg/sireum/U30;
            0       9     1 other   Lorg/sireum/ZLike;
    MethodParameters:
      Name                           Flags
      other                          final

  public final org.sireum.ZLike $times(org.sireum.ZLike);
    descriptor: (Lorg/sireum/ZLike;)Lorg/sireum/ZLike;
    flags: (0x1051) ACC_PUBLIC, ACC_FINAL, ACC_BRIDGE, ACC_SYNTHETIC
    Code:
      stack=2, locals=2, args_size=2
         0: aload_0
         1: aload_1
         2: checkcast     #7                  // class org/sireum/Z$BV$Int
         5: invokevirtual #354                // Method $times:(Lorg/sireum/Z$BV$Int;)Lorg/sireum/Z$BV$Int;
         8: areturn
      LineNumberTable:
        line 113: 0
      LocalVariableTable:
        Start  Length  Slot  Name   Signature
            0       9     0  this   Lorg/sireum/U30;
            0       9     1 other   Lorg/sireum/ZLike;
    MethodParameters:
      Name                           Flags
      other                          final

  public final org.sireum.ZLike $minus(org.sireum.ZLike);
    descriptor: (Lorg/sireum/ZLike;)Lorg/sireum/ZLike;
    flags: (0x1051) ACC_PUBLIC, ACC_FINAL, ACC_BRIDGE, ACC_SYNTHETIC
    Code:
      stack=2, locals=2, args_size=2
         0: aload_0
         1: aload_1
         2: checkcast     #7                  // class org/sireum/Z$BV$Int
         5: invokevirtual #356                // Method $minus:(Lorg/sireum/Z$BV$Int;)Lorg/sireum/Z$BV$Int;
         8: areturn
      LineNumberTable:
        line 113: 0
      LocalVariableTable:
        Start  Length  Slot  Name   Signature
            0       9     0  this   Lorg/sireum/U30;
            0       9     1 other   Lorg/sireum/ZLike;
    MethodParameters:
      Name                           Flags
      other                          final

  public final org.sireum.ZLike $plus(org.sireum.ZLike);
    descriptor: (Lorg/sireum/ZLike;)Lorg/sireum/ZLike;
    flags: (0x1051) ACC_PUBLIC, ACC_FINAL, ACC_BRIDGE, ACC_SYNTHETIC
    Code:
      stack=2, locals=2, args_size=2
         0: aload_0
         1: aload_1
         2: checkcast     #7                  // class org/sireum/Z$BV$Int
         5: invokevirtual #358                // Method $plus:(Lorg/sireum/Z$BV$Int;)Lorg/sireum/Z$BV$Int;
         8: areturn
      LineNumberTable:
        line 113: 0
      LocalVariableTable:
        Start  Length  Slot  Name   Signature
            0       9     0  this   Lorg/sireum/U30;
            0       9     1 other   Lorg/sireum/ZLike;
    MethodParameters:
      Name                           Flags
      other                          final

  public final org.sireum.ZLike unary_$minus();
    descriptor: ()Lorg/sireum/ZLike;
    flags: (0x1051) ACC_PUBLIC, ACC_FINAL, ACC_BRIDGE, ACC_SYNTHETIC
    Code:
      stack=1, locals=1, args_size=1
         0: aload_0
         1: invokevirtual #360                // Method unary_$minus:()Lorg/sireum/Z$BV$Int;
         4: areturn
      LineNumberTable:
        line 113: 0
      LocalVariableTable:
        Start  Length  Slot  Name   Signature
            0       5     0  this   Lorg/sireum/U30;

  public org.sireum.$internal.Boxer boxer();
    descriptor: ()Lorg/sireum/$internal/Boxer;
    flags: (0x1041) ACC_PUBLIC, ACC_BRIDGE, ACC_SYNTHETIC
    Code:
      stack=2, locals=1, args_size=1
         0: getstatic     #47                 // Field org/sireum/U30$.MODULE$:Lorg/sireum/U30$;
         3: aload_0
         4: invokevirtual #314                // Method value:()I
         7: invokevirtual #58                 // Method org/sireum/U30$.boxer$extension:(I)Lorg/sireum/U30$Boxer$;
        10: areturn
      LineNumberTable:
        line 113: 3
      LocalVariableTable:
        Start  Length  Slot  Name   Signature
            0      11     0  this   Lorg/sireum/U30;

  public org.sireum.Z$BV$Int make(int);
    descriptor: (I)Lorg/sireum/Z$BV$Int;
    flags: (0x1041) ACC_PUBLIC, ACC_BRIDGE, ACC_SYNTHETIC
    Code:
      stack=5, locals=2, args_size=2
         0: new           #2                  // class org/sireum/U30
         3: dup
         4: getstatic     #47                 // Field org/sireum/U30$.MODULE$:Lorg/sireum/U30$;
         7: aload_0
         8: invokevirtual #314                // Method value:()I
        11: iload_1
        12: invokevirtual #63                 // Method org/sireum/U30$.make$extension:(II)I
        15: invokespecial #366                // Method "<init>":(I)V
        18: areturn
      LineNumberTable:
        line 113: 7
      LocalVariableTable:
        Start  Length  Slot  Name   Signature
            0      19     0  this   Lorg/sireum/U30;
            0      19     1 value   I
    MethodParameters:
      Name                           Flags
      value                          final

  public org.sireum.ZLike Index();
    descriptor: ()Lorg/sireum/ZLike;
    flags: (0x1041) ACC_PUBLIC, ACC_BRIDGE, ACC_SYNTHETIC
    Code:
      stack=4, locals=1, args_size=1
         0: new           #2                  // class org/sireum/U30
         3: dup
         4: getstatic     #47                 // Field org/sireum/U30$.MODULE$:Lorg/sireum/U30$;
         7: aload_0
         8: invokevirtual #314                // Method value:()I
        11: invokevirtual #76                 // Method org/sireum/U30$.Index$extension:(I)I
        14: invokespecial #366                // Method "<init>":(I)V
        17: areturn
      LineNumberTable:
        line 113: 7
      LocalVariableTable:
        Start  Length  Slot  Name   Signature
            0      18     0  this   Lorg/sireum/U30;

  public org.sireum.Z$BV$Int Index();
    descriptor: ()Lorg/sireum/Z$BV$Int;
    flags: (0x1041) ACC_PUBLIC, ACC_BRIDGE, ACC_SYNTHETIC
    Code:
      stack=4, locals=1, args_size=1
         0: new           #2                  // class org/sireum/U30
         3: dup
         4: getstatic     #47                 // Field org/sireum/U30$.MODULE$:Lorg/sireum/U30$;
         7: aload_0
         8: invokevirtual #314                // Method value:()I
        11: invokevirtual #76                 // Method org/sireum/U30$.Index$extension:(I)I
        14: invokespecial #366                // Method "<init>":(I)V
        17: areturn
      LineNumberTable:
        line 113: 7
      LocalVariableTable:
        Start  Length  Slot  Name   Signature
            0      18     0  this   Lorg/sireum/U30;

  public org.sireum.ZLike Max();
    descriptor: ()Lorg/sireum/ZLike;
    flags: (0x1041) ACC_PUBLIC, ACC_BRIDGE, ACC_SYNTHETIC
    Code:
      stack=4, locals=1, args_size=1
         0: new           #2                  // class org/sireum/U30
         3: dup
         4: getstatic     #47                 // Field org/sireum/U30$.MODULE$:Lorg/sireum/U30$;
         7: aload_0
         8: invokevirtual #314                // Method value:()I
        11: invokevirtual #79                 // Method org/sireum/U30$.Max$extension:(I)I
        14: invokespecial #366                // Method "<init>":(I)V
        17: areturn
      LineNumberTable:
        line 113: 7
      LocalVariableTable:
        Start  Length  Slot  Name   Signature
            0      18     0  this   Lorg/sireum/U30;

  public org.sireum.Z$BV$Int Max();
    descriptor: ()Lorg/sireum/Z$BV$Int;
    flags: (0x1041) ACC_PUBLIC, ACC_BRIDGE, ACC_SYNTHETIC
    Code:
      stack=4, locals=1, args_size=1
         0: new           #2                  // class org/sireum/U30
         3: dup
         4: getstatic     #47                 // Field org/sireum/U30$.MODULE$:Lorg/sireum/U30$;
         7: aload_0
         8: invokevirtual #314                // Method value:()I
        11: invokevirtual #79                 // Method org/sireum/U30$.Max$extension:(I)I
        14: invokespecial #366                // Method "<init>":(I)V
        17: areturn
      LineNumberTable:
        line 113: 7
      LocalVariableTable:
        Start  Length  Slot  Name   Signature
            0      18     0  this   Lorg/sireum/U30;

  public org.sireum.ZLike Min();
    descriptor: ()Lorg/sireum/ZLike;
    flags: (0x1041) ACC_PUBLIC, ACC_BRIDGE, ACC_SYNTHETIC
    Code:
      stack=4, locals=1, args_size=1
         0: new           #2                  // class org/sireum/U30
         3: dup
         4: getstatic     #47                 // Field org/sireum/U30$.MODULE$:Lorg/sireum/U30$;
         7: aload_0
         8: invokevirtual #314                // Method value:()I
        11: invokevirtual #82                 // Method org/sireum/U30$.Min$extension:(I)I
        14: invokespecial #366                // Method "<init>":(I)V
        17: areturn
      LineNumberTable:
        line 113: 7
      LocalVariableTable:
        Start  Length  Slot  Name   Signature
            0      18     0  this   Lorg/sireum/U30;

  public org.sireum.Z$BV$Int Min();
    descriptor: ()Lorg/sireum/Z$BV$Int;
    flags: (0x1041) ACC_PUBLIC, ACC_BRIDGE, ACC_SYNTHETIC
    Code:
      stack=4, locals=1, args_size=1
         0: new           #2                  // class org/sireum/U30
         3: dup
         4: getstatic     #47                 // Field org/sireum/U30$.MODULE$:Lorg/sireum/U30$;
         7: aload_0
         8: invokevirtual #314                // Method value:()I
        11: invokevirtual #82                 // Method org/sireum/U30$.Min$extension:(I)I
        14: invokespecial #366                // Method "<init>":(I)V
        17: areturn
      LineNumberTable:
        line 113: 7
      LocalVariableTable:
        Start  Length  Slot  Name   Signature
            0      18     0  this   Lorg/sireum/U30;

  public org.sireum.U30(int);
    descriptor: (I)V
    flags: (0x0001) ACC_PUBLIC
    Code:
      stack=2, locals=2, args_size=2
         0: aload_0
         1: iload_1
         2: putfield      #311                // Field value:I
         5: aload_0
         6: invokespecial #369                // Method java/lang/Object."<init>":()V
         9: aload_0
        10: invokestatic  #373                // InterfaceMethod org/sireum/$internal/ImmutableMarker.$init$:(Lorg/sireum/$internal/ImmutableMarker;)V
        13: aload_0
        14: invokestatic  #376                // InterfaceMethod org/sireum/Immutable.$init$:(Lorg/sireum/Immutable;)V
        17: aload_0
        18: invokestatic  #379                // InterfaceMethod org/sireum/ZLike.$init$:(Lorg/sireum/ZLike;)V
        21: aload_0
        22: invokestatic  #382                // InterfaceMethod org/sireum/Z$BV$Int.$init$:(Lorg/sireum/Z$BV$Int;)V
        25: return
      LineNumberTable:
        line 113: 0
      LocalVariableTable:
        Start  Length  Slot  Name   Signature
            0      26     0  this   Lorg/sireum/U30;
            0      26     1 value   I
    MethodParameters:
      Name                           Flags
      value                          final
}
InnerClasses:
  public static #14= #13 of #2;           // $String$=class org/sireum/U30$$String$ of class org/sireum/U30
  public static #17= #16 of #2;           // BigInt$=class org/sireum/U30$BigInt$ of class org/sireum/U30
  public static #20= #19 of #2;           // Boxer$=class org/sireum/U30$Boxer$ of class org/sireum/U30
  public static #23= #22 of #2;           // Int$=class org/sireum/U30$Int$ of class org/sireum/U30
  public static #26= #25 of #2;           // Long$=class org/sireum/U30$Long$ of class org/sireum/U30
  public static #29= #28 of #2;           // U30$Slang=class org/sireum/U30$U30$Slang of class org/sireum/U30
  public static #34= #31 of #33;          // BV$=class org/sireum/Z$BV$ of class org/sireum/Z
  public static #35= #7 of #31;           // Int=class org/sireum/Z$BV$Int of class org/sireum/Z$BV$
Signature: #3                           // Ljava/lang/Object;Lorg/sireum/Z$BV$Int<Lorg/sireum/U30;>;
SourceFile: "BitsRangeTypes.scala"
RuntimeVisibleAnnotations:
  0: #9(#10=s#11)
    scala.reflect.ScalaSignature(
      bytes="\u0006\u0005\r]q!\u00021b\u0011\u00031g!\u00025b\u0011\u0003I\u0007bBA\u0010\u0003\u0011\u0005\u0011QU\u0004\b\u0003\u0003\u000b\u0001\u0012AAE\r\u001d\t9(\u0001E\u0001\u0003sBq!a\b\u0005\t\u0003\t9\tC\u0004\u0002h\u0011!\t!!$\t\u0013\u0005\u0015\u0012A1A\u0005\u0002\u0005\u001d\u0002\u0002CAT\u0003\u0001\u0006I!!\u000b\t\u0013\u0005\u0005\u0013A1A\u0005\u0002\u0005]\u0001\u0002CAU\u0003\u0001\u0006I!!\u0007\t\u0013\u0005\u0015\u0013A1A\u0005\u0002\u0005\u001d\u0003bBAV\u0003\u0001\u0006Ia\u001d\u0005\n\u0003\u0017\n!\u0019!C\u0001\u0003\u000fBq!!,\u0002A\u0003%1\u000fC\u0005\u0002P\u0005\u0011\r\u0011\"\u0001\u0002H!9\u0011qV\u0001!\u0002\u0013\u0019\b\"CA*\u0003\t\u0007I\u0011AA+\u0011!\t\t,\u0001Q\u0001\n\u0005]\u0003\"CA0\u0003\t\u0007I\u0011AA+\u0011!\t\u0019,\u0001Q\u0001\n\u0005]\u0003\"CA2\u0003\t\u0007I\u0011AA+\u0011!\t),\u0001Q\u0001\n\u0005]\u0003\"CA\\\u0003\t\u0007I\u0011AA+\u0011!\tI,\u0001Q\u0001\n\u0005]\u0003\"CA^\u0003\t\u0007I\u0011AA+\u0011!\ti,\u0001Q\u0001\n\u0005]\u0003\"CA`\u0003\t\u0007I\u0011AA+\u0011!\t\t-\u0001Q\u0001\n\u0005]\u0003bBAb\u0003\u0011\u0005\u0011q\t\u0005\b\u0003\u000b\fA\u0011AAd\u0011\u001d\t\u0019.\u0001C\u0001\u0003+Dq!a5\u0002\t\u0003\tY\u000eC\u0004\u0002T\u0006!\t!!:\t\u000f\u0005M\u0017\u0001\"\u0001\u0002j\"9\u0011\u0011`\u0001\u0005\u0002\u0005mxa\u0002B\u0002\u0003!\u0005!Q\u0001\u0004\b\u0003#\t\u0001\u0012\u0001B\u0004\u0011\u001d\ty\"\nC\u0001\u0005\u001fAq!a5&\t\u0003\u0011\t\u0002C\u0004\u0002z\u0016\"\tA!\u0006\b\u000f\tm\u0011\u0001#\u0001\u0003\u001e\u00199\u00111]\u0001\t\u0002\t}\u0001bBA\u0010U\u0011\u0005!q\u0005\u0005\b\u0003\'TC\u0011\u0001B\u0015\u0011\u001d\tIP\u000bC\u0001\u0005[9qAa\r\u0002\u0011\u0003\u0011)DB\u0004\u00038\u0005A\tA!\u000f\t\u000f\u0005}q\u0006\"\u0001\u0003B!9\u00111[\u0018\u0005\u0002\t\r\u0003bBA}_\u0011\u0005!qI\u0004\b\u0005\u001b\n\u0001\u0012\u0001B(\r\u001d\u0011\t&\u0001E\u0001\u0005\'Bq!a\b5\t\u0003\u0011Y\u0006C\u0004\u0002TR\"\tA!\u0018\t\u000f\u0005eH\u0007\"\u0001\u0003r\u00191!qO\u0001\u0002\u0005sB!Ba\u001f9\u0005\u000b\u0007I\u0011\u0001B?\u0011)\u0011)\t\u000fB\u0001B\u0003%!q\u0010\u0005\b\u0003?AD\u0011\u0001BD\u000f\u001d\u0011i\t\u000fE\u0001\u0005\u001f3qAa%9\u0011\u0003\u0011)\nC\u0004\u0002 u\"\tAa&\t\u000f\u0005MW\b\"\u0001\u0003\u001a\"9\u0011\u0011`\u001f\u0005\u0002\t\u0015\u0006\"\u0003BU\u0003\u0005\u0005I1\u0001BV\u0011%\u0011y+\u0001b\u0001\n\u0007\u0011\t\fC\u0004\u00034\u0006\u0001\u000b\u0011\u00029\t\u000f\tU\u0016\u0001\"\u0002\u00038\"9!qX\u0001\u0005\u0006\t\u0005\u0007b\u0002Bd\u0003\u0011\u0015!\u0011\u001a\u0005\b\u0005\u001f\fAQ\u0001Bi\u0011\u001d\u00119.\u0001C\u0003\u00053DqAa8\u0002\t\u000b\u0011\t\u000fC\u0004\u0003h\u0006!)A!;\t\u000f\t=\u0018\u0001\"\u0002\u0003r\"9!q_\u0001\u0005\u0006\te\bbBB\u0001\u0003\u0011\u001511\u0001\u0005\n\u0007\u000f\t\u0011\u0011!C\u0003\u0007\u0013A\u0011b!\u0004\u0002\u0003\u0003%)aa\u0004\u0007\t!\f\'\u0001\u001e\u0005\u000b\u0003+\u0001&Q1A\u0005\u0002\u0005]\u0001BCA\u000f!\n\u0005\t\u0015!\u0003\u0002\u001a!9\u0011q\u0004)\u0005\u0002\u0005\u0005\u0002bBA\u0013!\u0012\u0005\u0011q\u0005\u0005\b\u0003\u0003\u0002F\u0011AA\f\u0011\u001d\t)\u0005\u0015C\u0001\u0003\u000fBq!a\u0013Q\t\u0003\t9\u0005C\u0004\u0002PA#\t!a\u0012\t\u000f\u0005M\u0003\u000b\"\u0001\u0002V!9\u0011q\f)\u0005\u0002\u0005U\u0003bBA2!\u0012\u0005\u0011Q\u000b\u0005\b\u0003O\u0002F\u0011AA5\u0011\u001d\ty\u0007\u0015C\u0001\u0003cB\u0011\"a%Q\u0003\u0003%\t%!&\t\u0013\u0005]\u0005+!A\u0005B\u0005e\u0015aA+4a)\u0011!mY\u0001\u0007g&\u0014X-^7\u000b\u0003\u0011\f1a\u001c:h\u0007\u0001\u0001\"aZ\u0001\u000e\u0003\u0005\u00141!V\u001a1\'\r\t!\u000e\u001d\t\u0003W:l\u0011\u0001\u001c\u0006\u0002[\u0006)1oY1mC&\u0011q\u000e\u001c\u0002\u0007\u0003:L(+\u001a4\u0011\u0007\u001d\f8/\u0003\u0002sC\nYAEW\"p[B\fg.[8o!\t9\u0007kE\u0002Qkb\u0004\"a\u001b<\n\u0005]d\'AB!osZ\u000bG\u000e\u0005\u0003z\u0003\u001f\u0019hb\u0001>\u0002\n9\u001910!\u0002\u000f\u0007q\f\u0019AD\u0002~\u0003\u0003i\u0011A \u0006\u0003\u007f\u0016\fa\u0001\u0010:p_Rt\u0014\"\u00013\n\u0005\t\u001c\u0017bAA\u0004C\u0006\t!,\u0003\u0003\u0002\f\u00055\u0011A\u0001\"W\u0015\r\t9!Y\u0005\u0005\u0003#\t\u0019BA\u0002J]RTA!a\u0003\u0002\u000e\u0005)a/\u00197vKV\u0011\u0011\u0011\u0004\t\u0004W\u0006m\u0011bAA\tY\u00061a/\u00197vK\u0002\na\u0001P5oSRtDcA:\u0002$!9\u0011QC*A\u0002\u0005e\u0011\u0001\u0002(b[\u0016,\"!!\u000b\u0011\t\u0005-\u0012QG\u0007\u0003\u0003[QA!a\f\u00022\u0005!A.\u00198h\u0015\t\t\u0019$\u0001\u0003kCZ\f\u0017\u0002BA\u001c\u0003[\u0011aa\u0015;sS:<\u0007f\u0001+\u0002<A\u00191.!\u0010\n\u0007\u0005}BN\u0001\u0004j]2Lg.Z\u0001\t\u0005&$x+\u001b3uQ\"\u001aQ+a\u000f\u0002\u00075Kg.F\u0001tQ\r1\u00161H\u0001\u0004\u001b\u0006D\bfA,\u0002<\u0005)\u0011J\u001c3fq\"\u001a\u0001,a\u000f\u0002\u0017%\u001c(,\u001a:p\u0013:$W\r_\u000b\u0003\u0003/\u00022a[A-\u0013\r\tY\u0006\u001c\u0002\b\u0005>|G.Z1oQ\rI\u00161H\u0001\tSN\u001c\u0016n\u001a8fI\"\u001a!,a\u000f\u0002\u0013%\u001cxK]1qa\u0016$\u0007fA.\u0002<\u0005!Q.Y6f)\r\u0019\u00181\u000e\u0005\b\u0003[b\u0006\u0019AA\r\u0003\u00051\u0018!\u00022pq\u0016\u0014XCAA:!\r\t)\b\u0002\b\u0003O\u0002\u0011QAQ8yKJ\u001cB\u0001\u00026\u0002|A!\u0011QPAB\u001d\rQ\u0018qP\u0005\u0005\u0003\u0003\u000bi!A\u0003C_b,\'/\u0003\u0003\u0002\u0012\u0005\u0015%\u0002BAA\u0003\u001b!\"!!#\u0011\u0007\u0005-E!D\u0001\u0002)\r\u0019\u0018q\u0012\u0005\b\u0003#3\u0001\u0019AA\r\u0003\u0005y\u0017\u0001\u00035bg\"\u001cu\u000eZ3\u0015\u0005\u0005e\u0011AB3rk\u0006d7\u000f\u0006\u0003\u0002X\u0005m\u0005\"CAO?\u0006\u0005\t\u0019AAP\u0003\rAH%\r\t\u0004W\u0006\u0005\u0016bAARY\n\u0019\u0011I\\=\u0015\u0003\u0019\fQAT1nK\u0002\n\u0011BQ5u/&$G\u000f\u001b\u0011\u0002\t5Kg\u000eI\u0001\u0005\u001b\u0006D\b%\u0001\u0004J]\u0012,\u0007\u0010I\u0001\rSNTVM]8J]\u0012,\u0007\u0010I\u0001\nSN\u001c\u0016n\u001a8fI\u0002\n!\"[:Xe\u0006\u0004\b/\u001a3!\u0003-I7OQ5u-\u0016\u001cGo\u001c:\u0002\u0019%\u001c()\u001b;WK\u000e$xN\u001d\u0011\u0002\r!\f7/T5o\u0003\u001dA\u0017m]\'j]\u0002\na\u0001[1t\u001b\u0006D\u0018a\u00025bg6\u000b\u0007\u0010I\u0001\u0007e\u0006tGm\\7\u0002\u0015I\fg\u000eZ8n\'\u0016,G\rF\u0002t\u0003\u0013Dq!a3\u001f\u0001\u0004\ti-\u0001\u0003tK\u0016$\u0007cA4\u0002P&\u0019\u0011\u0011[1\u0003\u0003i\u000bQ!\u00199qYf$2a]Al\u0011\u001d\tIn\ba\u0001\u00033\t\u0011A\u001c\u000b\u0004g\u0006u\u0007bBAmA\u0001\u0007\u0011q\u001c\t\u0004W\u0006\u0005\u0018bAArY\n!Aj\u001c8h)\r\u0019\u0018q\u001d\u0005\b\u00033\f\u0003\u0019AAg)\u0011\tY/!=\u0011\t\u001d\fio]\u0005\u0004\u0003_\f\'AB(qi&|g\u000eC\u0004\u0002t\n\u0002\r!!>\u0002\u0003M\u00042aZA|\u0013\r\t9$Y\u0001\bk:\f\u0007\u000f\u001d7z)\u0011\tiP!\u0001\u0011\u000b-\fy0!4\n\u0007\u0005=H\u000e\u0003\u0004\u0002Z\u000e\u0002\ra]\u0001\u0004\u0013:$\bcAAFKM!QE\u001bB\u0005!\u00119\'1B:\n\u0007\t5\u0011M\u0001\b%5\u000e{W\u000e]1oS>t\u0017J\u001c;\u0015\u0005\t\u0015AcA:\u0003\u0014!9\u0011\u0011\\\u0014A\u0002\u0005eA\u0003\u0002B\f\u00053\u0001Ra[A\u0000\u00033Aa!!7)\u0001\u0004\u0019\u0018\u0001\u0002\'p]\u001e\u00042!a#+\'\u0011Q#N!\t\u0011\t\u001d\u0014\u0019c]\u0005\u0004\u0005K\t\'a\u0004\u0013[\u0007>l\u0007/\u00198j_:duN\\4\u0015\u0005\tuAcA:\u0003,!9\u0011\u0011\u001c\u0017A\u0002\u0005}G\u0003\u0002B\u0018\u0005c\u0001Ra[A\u0000\u0003?Da!!7.\u0001\u0004\u0019\u0018a\u0002\u0013TiJLgn\u001a\t\u0004\u0003\u0017{#a\u0002\u0013TiJLgnZ\n\u0005_)\u0014Y\u0004\u0005\u0003h\u0005{\u0019\u0018b\u0001B C\n\tBEW\"p[B\fg.[8o\'R\u0014\u0018N\\4\u0015\u0005\tUBcA:\u0003F!9\u00111_\u0019A\u0002\u0005%B\u0003\u0002B%\u0005\u0017\u0002Ra[A\u0000\u0003SAa!!73\u0001\u0004\u0019\u0018A\u0002\"jO&sG\u000fE\u0002\u0002\fR\u0012aAQ5h\u0013:$8\u0003\u0002\u001bk\u0005+\u0002Ba\u001aB,g&\u0019!\u0011L1\u0003#\u0011R6i\\7qC:LwN\u001c\"jO&sG\u000f\u0006\u0002\u0003PQ\u00191Oa\u0018\t\u000f\u0005eg\u00071\u0001\u0003bA!!1\rB7\u001d\u0011\u0011)G!\u001b\u000f\u0007u\u00149\'C\u0001n\u0013\r\u0011Y\u0007\\\u0001\ba\u0006\u001c7.Y4f\u0013\u0011\u0011\tFa\u001c\u000b\u0007\t-D\u000e\u0006\u0003\u0003t\tU\u0004#B6\u0002\u0000\n\u0005\u0004BBAmo\u0001\u00071OA\u0005VgA\"3\u000b\\1oON\u0011\u0001H[\u0001\u0003g\u000e,\"Aa \u0011\u0007-\u0014\t)C\u0002\u0003\u00042\u0014Qb\u0015;sS:<7i\u001c8uKb$\u0018aA:dAQ!!\u0011\u0012BF!\r\tY\t\u000f\u0005\b\u0005wZ\u0004\u0019\u0001B@\u0003\r)8\u0007\r\t\u0004\u0005#kT\"\u0001\u001d\u0003\u0007U\u001c\u0004g\u0005\u0002>UR\u0011!q\u0012\u000b\u0004g\nm\u0005b\u0002BO\u007f\u0001\u0007!qT\u0001\u0005CJ<7\u000fE\u0003l\u0005C\u000by*C\u0002\u0003$2\u0014!\u0002\u0010:fa\u0016\fG/\u001a3?)\u0011\t9Fa*\t\r\u0005e\u0007\t1\u0001t\u0003%)6\u0007\r\u0013TY\u0006tw\r\u0006\u0003\u0003\n\n5\u0006b\u0002B>\u0003\u0002\u0007!qP\u0001\u000eIU\u001b\u0004gQ8na\u0006t\u0017n\u001c8\u0016\u0003A\fa\u0002J+4a\r{W\u000e]1oS>t\u0007%\u0001\bOC6,G%\u001a=uK:\u001c\u0018n\u001c8\u0015\t\u0005%\"\u0011\u0018\u0005\u0007\u0005w#\u0005\u0019A:\u0002\u000b\u0011\"\b.[:)\u0007\u0011\u000bY$\u0001\nCSR<\u0016\u000e\u001a;iI\u0015DH/\u001a8tS>tG\u0003BA\r\u0005\u0007DaAa/F\u0001\u0004\u0019\bfA#\u0002<\u0005iQ*\u001b8%Kb$XM\\:j_:$2a\u001dBf\u0011\u0019\u0011YL\u0012a\u0001g\"\u001aa)a\u000f\u0002\u001b5\u000b\u0007\u0010J3yi\u0016t7/[8o)\r\u0019(1\u001b\u0005\u0007\u0005w;\u0005\u0019A:)\u0007\u001d\u000bY$A\bJ]\u0012,\u0007\u0010J3yi\u0016t7/[8o)\r\u0019(1\u001c\u0005\u0007\u0005wC\u0005\u0019A:)\u0007!\u000bY$A\u000bjgj+\'o\\%oI\u0016DH%\u001a=uK:\u001c\u0018n\u001c8\u0015\t\u0005]#1\u001d\u0005\u0007\u0005wK\u0005\u0019A:)\u0007%\u000bY$\u0001\njgNKwM\\3eI\u0015DH/\u001a8tS>tG\u0003BA,\u0005WDaAa/K\u0001\u0004\u0019\bf\u0001&\u0002<\u0005\u0019\u0012n],sCB\u0004X\r\u001a\u0013fqR,gn]5p]R!\u0011q\u000bBz\u0011\u0019\u0011Yl\u0013a\u0001g\"\u001a1*a\u000f\u0002\u001d5\f7.\u001a\u0013fqR,gn]5p]R!!1 B\u0000)\r\u0019(Q \u0005\b\u0003[b\u0005\u0019AA\r\u0011\u0019\u0011Y\f\u0014a\u0001g\u0006y!m\u001c=fe\u0012*\u0007\u0010^3og&|g\u000e\u0006\u0003\u0002t\r\u0015\u0001B\u0002B^\u001b\u0002\u00071/\u0001\niCND7i\u001c3fI\u0015DH/\u001a8tS>tG\u0003BAK\u0007\u0017AaAa/O\u0001\u0004\u0019\u0018\u0001E3rk\u0006d7\u000fJ3yi\u0016t7/[8o)\u0011\u0019\tb!\u0006\u0015\t\u0005]31\u0003\u0005\n\u0003;{\u0015\u0011!a\u0001\u0003?CaAa/P\u0001\u0004\u0019\b"
    )
  ScalaInlineInfo: length = 0x16C (unknown attribute)
   01 01 00 48 00 CD 00 96 01 00 D1 00 96 01 00 D5
   00 96 01 01 1D 01 1E 01 01 2E 01 48 01 01 2E 01
   2F 01 00 A8 00 96 01 00 A8 01 5C 01 01 03 00 FC
   05 00 FB 00 FC 05 00 B0 00 86 01 00 B0 01 53 01
   00 B5 00 86 01 00 B5 01 53 01 00 C1 00 96 01 00
   C5 00 96 01 01 25 00 84 01 01 2A 00 84 01 00 B9
   00 86 01 00 B9 01 53 01 00 BD 00 86 01 00 BD 01
   53 01 00 C9 00 96 01 00 A0 00 96 01 00 A0 01 5C
   01 00 AC 00 96 01 00 AC 01 5C 01 00 99 00 96 01
   00 99 01 5C 01 00 A4 00 96 01 00 A4 01 5C 01 01
   6B 01 6C 01 01 3B 00 80 05 01 3E 00 80 05 01 3E
   00 94 05 01 3E 01 4E 05 01 3D 00 80 05 01 3D 00
   94 05 01 3D 01 4E 05 01 3C 00 80 05 01 3C 00 94
   05 01 3C 01 4E 05 01 38 00 E6 05 01 43 01 69 01
   01 43 01 44 01 01 17 01 4B 01 01 17 01 18 01 00
   E1 00 94 01 00 E1 01 4E 01 01 46 01 47 01 00 8F
   00 84 01 00 8B 00 84 01 01 45 00 80 01 00 DD 00
   94 01 00 DD 01 4E 01 00 83 00 84 01 01 40 00 84
   05 01 41 00 84 05 01 3F 00 84 05 01 42 00 34 01
   01 42 01 6A 01 01 07 00 E6 01 01 0C 01 0D 01 00
   EB 00 EC 01 00 F7 00 F2 01 00 F1 00 F2 01 00 E5
   00 E6 01 00 93 00 94 01 00 93 01 4E 01 00 D9 00
   94 01 01 13 01 0D 01 00 24 00 80 01
  ScalaSig: length = 0x3 (unknown attribute)
   05 02 00
