Classfile /Users/mw/Projects/slang-braindump/.jar/jar8/assemble/slang-braindump/assemble/content/org/sireum/ZLike$$anon$1.class
  Last modified May 29, 2022; size 1635 bytes
  SHA-256 checksum 489d9b074e9689a679acc294b24168d5e760da2015ada33e646a65ba906c001b
  Compiled from "Z.scala"
public final class org.sireum.ZLike$$anon$1 extends java.lang.Object implements org.sireum.ZRange$CondIncDec<T>
  minor version: 0
  major version: 52
  flags: (0x0031) ACC_PUBLIC, ACC_FINAL, ACC_SUPER
  this_class: #2                          // org/sireum/ZLike$$anon$1
  super_class: #5                         // java/lang/Object
  interfaces: 1, fields: 0, methods: 7, attributes: 6
Constant pool:
   #1 = Utf8               org/sireum/ZLike$$anon$1
   #2 = Class              #1             // org/sireum/ZLike$$anon$1
   #3 = Utf8               Ljava/lang/Object;Lorg/sireum/ZRange$CondIncDec<TT;>;
   #4 = Utf8               java/lang/Object
   #5 = Class              #4             // java/lang/Object
   #6 = Utf8               org/sireum/ZRange$CondIncDec
   #7 = Class              #6             // org/sireum/ZRange$CondIncDec
   #8 = Utf8               Z.scala
   #9 = Utf8               org/sireum/ZLike
  #10 = Class              #9             // org/sireum/ZLike
  #11 = Utf8               to
  #12 = Utf8               (Lorg/sireum/ZLike;)Lorg/sireum/ZRange;
  #13 = NameAndType        #11:#12        // to:(Lorg/sireum/ZLike;)Lorg/sireum/ZRange;
  #14 = Utf8               org/sireum/ZRange
  #15 = Class              #14            // org/sireum/ZRange
  #16 = Utf8               CondIncDec
  #17 = Utf8               cond
  #18 = Utf8               (Lorg/sireum/ZLike;)Z
  #19 = Utf8               (TT;)Z
  #20 = Utf8               i
  #21 = Utf8               org/sireum/package$
  #22 = Class              #21            // org/sireum/package$
  #23 = Utf8               MODULE$
  #24 = Utf8               Lorg/sireum/package$;
  #25 = NameAndType        #23:#24        // MODULE$:Lorg/sireum/package$;
  #26 = Fieldref           #22.#25        // org/sireum/package$.MODULE$:Lorg/sireum/package$;
  #27 = Utf8               T
  #28 = Utf8               ()Z
  #29 = NameAndType        #27:#28        // T:()Z
  #30 = Methodref          #22.#29        // org/sireum/package$.T:()Z
  #31 = Utf8               this
  #32 = Utf8               Lorg/sireum/ZLike$$anon$1;
  #33 = Utf8               Lorg/sireum/ZLike;
  #34 = Utf8               increase
  #35 = Utf8               (Lorg/sireum/ZLike;)Lorg/sireum/ZLike;
  #36 = Utf8               (TT;)TT;
  #37 = Utf8               ()Lorg/sireum/ZLike;
  #38 = NameAndType        #34:#37        // increase:()Lorg/sireum/ZLike;
  #39 = InterfaceMethodref #10.#38        // org/sireum/ZLike.increase:()Lorg/sireum/ZLike;
  #40 = Utf8               decrease
  #41 = NameAndType        #40:#37        // decrease:()Lorg/sireum/ZLike;
  #42 = InterfaceMethodref #10.#41        // org/sireum/ZLike.decrease:()Lorg/sireum/ZLike;
  #43 = Utf8               (Ljava/lang/Object;)Ljava/lang/Object;
  #44 = NameAndType        #40:#35        // decrease:(Lorg/sireum/ZLike;)Lorg/sireum/ZLike;
  #45 = Methodref          #2.#44         // org/sireum/ZLike$$anon$1.decrease:(Lorg/sireum/ZLike;)Lorg/sireum/ZLike;
  #46 = Utf8               Ljava/lang/Object;
  #47 = NameAndType        #34:#35        // increase:(Lorg/sireum/ZLike;)Lorg/sireum/ZLike;
  #48 = Methodref          #2.#47         // org/sireum/ZLike$$anon$1.increase:(Lorg/sireum/ZLike;)Lorg/sireum/ZLike;
  #49 = Utf8               (Ljava/lang/Object;)Z
  #50 = NameAndType        #17:#18        // cond:(Lorg/sireum/ZLike;)Z
  #51 = Methodref          #2.#50         // org/sireum/ZLike$$anon$1.cond:(Lorg/sireum/ZLike;)Z
  #52 = Utf8               <init>
  #53 = Utf8               (Lorg/sireum/ZLike;)V
  #54 = Utf8               $outer
  #55 = Utf8               ()V
  #56 = NameAndType        #52:#55        // "<init>":()V
  #57 = Methodref          #5.#56         // java/lang/Object."<init>":()V
  #58 = Utf8               Code
  #59 = Utf8               LineNumberTable
  #60 = Utf8               LocalVariableTable
  #61 = Utf8               Signature
  #62 = Utf8               MethodParameters
  #63 = Utf8               InnerClasses
  #64 = Utf8               EnclosingMethod
  #65 = Utf8               SourceFile
  #66 = Utf8               ScalaInlineInfo
  #67 = Utf8               Scala
{
  public boolean cond(T);
    descriptor: (Lorg/sireum/ZLike;)Z
    flags: (0x0001) ACC_PUBLIC
    Code:
      stack=1, locals=2, args_size=2
         0: getstatic     #26                 // Field org/sireum/package$.MODULE$:Lorg/sireum/package$;
         3: invokevirtual #30                 // Method org/sireum/package$.T:()Z
         6: ireturn
      LineNumberTable:
        line 1345: 0
      LocalVariableTable:
        Start  Length  Slot  Name   Signature
            0       7     0  this   Lorg/sireum/ZLike$$anon$1;
            0       7     1     i   Lorg/sireum/ZLike;
    Signature: #19                          // (TT;)Z
    MethodParameters:
      Name                           Flags
      i                              final

  public T increase(T);
    descriptor: (Lorg/sireum/ZLike;)Lorg/sireum/ZLike;
    flags: (0x0001) ACC_PUBLIC
    Code:
      stack=1, locals=2, args_size=2
         0: aload_1
         1: invokeinterface #39,  1           // InterfaceMethod org/sireum/ZLike.increase:()Lorg/sireum/ZLike;
         6: areturn
      LineNumberTable:
        line 1346: 0
      LocalVariableTable:
        Start  Length  Slot  Name   Signature
            0       7     0  this   Lorg/sireum/ZLike$$anon$1;
            0       7     1     i   Lorg/sireum/ZLike;
    Signature: #36                          // (TT;)TT;
    MethodParameters:
      Name                           Flags
      i                              final

  public T decrease(T);
    descriptor: (Lorg/sireum/ZLike;)Lorg/sireum/ZLike;
    flags: (0x0001) ACC_PUBLIC
    Code:
      stack=1, locals=2, args_size=2
         0: aload_1
         1: invokeinterface #42,  1           // InterfaceMethod org/sireum/ZLike.decrease:()Lorg/sireum/ZLike;
         6: areturn
      LineNumberTable:
        line 1347: 0
      LocalVariableTable:
        Start  Length  Slot  Name   Signature
            0       7     0  this   Lorg/sireum/ZLike$$anon$1;
            0       7     1     i   Lorg/sireum/ZLike;
    Signature: #36                          // (TT;)TT;
    MethodParameters:
      Name                           Flags
      i                              final

  public java.lang.Object decrease(java.lang.Object);
    descriptor: (Ljava/lang/Object;)Ljava/lang/Object;
    flags: (0x1041) ACC_PUBLIC, ACC_BRIDGE, ACC_SYNTHETIC
    Code:
      stack=2, locals=2, args_size=2
         0: aload_0
         1: aload_1
         2: checkcast     #10                 // class org/sireum/ZLike
         5: invokevirtual #45                 // Method decrease:(Lorg/sireum/ZLike;)Lorg/sireum/ZLike;
         8: areturn
      LineNumberTable:
        line 1344: 0
      LocalVariableTable:
        Start  Length  Slot  Name   Signature
            0       9     0  this   Lorg/sireum/ZLike$$anon$1;
            0       9     1     i   Ljava/lang/Object;
    MethodParameters:
      Name                           Flags
      i                              final

  public java.lang.Object increase(java.lang.Object);
    descriptor: (Ljava/lang/Object;)Ljava/lang/Object;
    flags: (0x1041) ACC_PUBLIC, ACC_BRIDGE, ACC_SYNTHETIC
    Code:
      stack=2, locals=2, args_size=2
         0: aload_0
         1: aload_1
         2: checkcast     #10                 // class org/sireum/ZLike
         5: invokevirtual #48                 // Method increase:(Lorg/sireum/ZLike;)Lorg/sireum/ZLike;
         8: areturn
      LineNumberTable:
        line 1344: 0
      LocalVariableTable:
        Start  Length  Slot  Name   Signature
            0       9     0  this   Lorg/sireum/ZLike$$anon$1;
            0       9     1     i   Ljava/lang/Object;
    MethodParameters:
      Name                           Flags
      i                              final

  public boolean cond(java.lang.Object);
    descriptor: (Ljava/lang/Object;)Z
    flags: (0x1041) ACC_PUBLIC, ACC_BRIDGE, ACC_SYNTHETIC
    Code:
      stack=2, locals=2, args_size=2
         0: aload_0
         1: aload_1
         2: checkcast     #10                 // class org/sireum/ZLike
         5: invokevirtual #51                 // Method cond:(Lorg/sireum/ZLike;)Z
         8: ireturn
      LineNumberTable:
        line 1344: 0
      LocalVariableTable:
        Start  Length  Slot  Name   Signature
            0       9     0  this   Lorg/sireum/ZLike$$anon$1;
            0       9     1     i   Ljava/lang/Object;
    MethodParameters:
      Name                           Flags
      i                              final

  public org.sireum.ZLike$$anon$1(org.sireum.ZLike);
    descriptor: (Lorg/sireum/ZLike;)V
    flags: (0x0001) ACC_PUBLIC
    Code:
      stack=1, locals=2, args_size=2
         0: aload_0
         1: invokespecial #57                 // Method java/lang/Object."<init>":()V
         4: return
      LineNumberTable:
        line 1344: 0
      LocalVariableTable:
        Start  Length  Slot  Name   Signature
            0       5     0  this   Lorg/sireum/ZLike$$anon$1;
            0       5     1 $outer   Lorg/sireum/ZLike;
    MethodParameters:
      Name                           Flags
      $outer                         final synthetic
}
InnerClasses:
  public final #2;                        // class org/sireum/ZLike$$anon$1
  public static #16= #7 of #15;           // CondIncDec=class org/sireum/ZRange$CondIncDec of class org/sireum/ZRange
EnclosingMethod: #10.#13                // org.sireum.ZLike.to
Signature: #3                           // Ljava/lang/Object;Lorg/sireum/ZRange$CondIncDec<TT;>;
SourceFile: "Z.scala"
  ScalaInlineInfo: length = 0x27 (unknown attribute)
   01 01 00 07 00 34 00 35 01 00 11 00 31 01 00 11
   00 12 01 00 28 00 2B 01 00 28 00 23 01 00 22 00
   2B 01 00 22 00 23 01
  Scala: length = 0x0 (unknown attribute)

