Classfile /Users/mw/Projects/slang-braindump/.jar/jar8/assemble/slang-braindump/assemble/content/coursier/params/rule/AlwaysFail$.class
  Last modified May 29, 2022; size 996 bytes
  SHA-256 checksum 13362514279fa4080f30de2991ee094415498d97a47247b3be0c46640a30b195
  Compiled from "AlwaysFail.scala"
public final class coursier.params.rule.AlwaysFail$ implements java.io.Serializable
  minor version: 0
  major version: 52
  flags: (0x0031) ACC_PUBLIC, ACC_FINAL, ACC_SUPER
  this_class: #2                          // coursier/params/rule/AlwaysFail$
  super_class: #4                         // java/lang/Object
  interfaces: 1, fields: 1, methods: 5, attributes: 3
Constant pool:
   #1 = Utf8               coursier/params/rule/AlwaysFail$
   #2 = Class              #1             // coursier/params/rule/AlwaysFail$
   #3 = Utf8               java/lang/Object
   #4 = Class              #3             // java/lang/Object
   #5 = Utf8               java/io/Serializable
   #6 = Class              #5             // java/io/Serializable
   #7 = Utf8               AlwaysFail.scala
   #8 = Utf8               MODULE$
   #9 = Utf8               Lcoursier/params/rule/AlwaysFail$;
  #10 = Utf8               <clinit>
  #11 = Utf8               ()V
  #12 = Utf8               <init>
  #13 = NameAndType        #12:#11        // "<init>":()V
  #14 = Methodref          #2.#13         // coursier/params/rule/AlwaysFail$."<init>":()V
  #15 = NameAndType        #8:#9          // MODULE$:Lcoursier/params/rule/AlwaysFail$;
  #16 = Fieldref           #2.#15         // coursier/params/rule/AlwaysFail$.MODULE$:Lcoursier/params/rule/AlwaysFail$;
  #17 = Utf8               apply
  #18 = Utf8               ()Lcoursier/params/rule/AlwaysFail;
  #19 = Utf8               coursier/params/rule/AlwaysFail
  #20 = Class              #19            // coursier/params/rule/AlwaysFail
  #21 = Utf8               (Z)V
  #22 = NameAndType        #12:#21        // "<init>":(Z)V
  #23 = Methodref          #20.#22        // coursier/params/rule/AlwaysFail."<init>":(Z)V
  #24 = Utf8               this
  #25 = Utf8               (Z)Lcoursier/params/rule/AlwaysFail;
  #26 = Utf8               doTryResolve
  #27 = Utf8               Z
  #28 = Utf8               writeReplace
  #29 = Utf8               ()Ljava/lang/Object;
  #30 = Utf8               scala/runtime/ModuleSerializationProxy
  #31 = Class              #30            // scala/runtime/ModuleSerializationProxy
  #32 = Utf8               (Ljava/lang/Class;)V
  #33 = NameAndType        #12:#32        // "<init>":(Ljava/lang/Class;)V
  #34 = Methodref          #31.#33        // scala/runtime/ModuleSerializationProxy."<init>":(Ljava/lang/Class;)V
  #35 = Methodref          #4.#13         // java/lang/Object."<init>":()V
  #36 = Utf8               Code
  #37 = Utf8               LineNumberTable
  #38 = Utf8               LocalVariableTable
  #39 = Utf8               MethodParameters
  #40 = Utf8               SourceFile
  #41 = Utf8               ScalaInlineInfo
  #42 = Utf8               Scala
{
  public static final coursier.params.rule.AlwaysFail$ MODULE$;
    descriptor: Lcoursier/params/rule/AlwaysFail$;
    flags: (0x0019) ACC_PUBLIC, ACC_STATIC, ACC_FINAL

  public static {};
    descriptor: ()V
    flags: (0x0009) ACC_PUBLIC, ACC_STATIC
    Code:
      stack=2, locals=0, args_size=0
         0: new           #2                  // class coursier/params/rule/AlwaysFail$
         3: dup
         4: invokespecial #14                 // Method "<init>":()V
         7: putstatic     #16                 // Field MODULE$:Lcoursier/params/rule/AlwaysFail$;
        10: return
      LineNumberTable:
        line 16: 0

  public coursier.params.rule.AlwaysFail apply();
    descriptor: ()Lcoursier/params/rule/AlwaysFail;
    flags: (0x0001) ACC_PUBLIC
    Code:
      stack=3, locals=1, args_size=1
         0: new           #20                 // class coursier/params/rule/AlwaysFail
         3: dup
         4: iconst_0
         5: invokespecial #23                 // Method coursier/params/rule/AlwaysFail."<init>":(Z)V
         8: areturn
      LineNumberTable:
        line 16: 0
      LocalVariableTable:
        Start  Length  Slot  Name   Signature
            0       9     0  this   Lcoursier/params/rule/AlwaysFail$;

  public coursier.params.rule.AlwaysFail apply(boolean);
    descriptor: (Z)Lcoursier/params/rule/AlwaysFail;
    flags: (0x0001) ACC_PUBLIC
    Code:
      stack=3, locals=2, args_size=2
         0: new           #20                 // class coursier/params/rule/AlwaysFail
         3: dup
         4: iload_1
         5: invokespecial #23                 // Method coursier/params/rule/AlwaysFail."<init>":(Z)V
         8: areturn
      LineNumberTable:
        line 16: 0
      LocalVariableTable:
        Start  Length  Slot  Name   Signature
            0       9     0  this   Lcoursier/params/rule/AlwaysFail$;
            0       9     1 doTryResolve   Z
    MethodParameters:
      Name                           Flags
      doTryResolve                   final

  private java.lang.Object writeReplace();
    descriptor: ()Ljava/lang/Object;
    flags: (0x0002) ACC_PRIVATE
    Code:
      stack=3, locals=1, args_size=1
         0: new           #31                 // class scala/runtime/ModuleSerializationProxy
         3: dup
         4: ldc           #2                  // class coursier/params/rule/AlwaysFail$
         6: invokespecial #34                 // Method scala/runtime/ModuleSerializationProxy."<init>":(Ljava/lang/Class;)V
         9: areturn
      LineNumberTable:
        line 16: 0
      LocalVariableTable:
        Start  Length  Slot  Name   Signature
            0      10     0  this   Lcoursier/params/rule/AlwaysFail$;

  private coursier.params.rule.AlwaysFail$();
    descriptor: ()V
    flags: (0x0002) ACC_PRIVATE
    Code:
      stack=1, locals=1, args_size=1
         0: aload_0
         1: invokespecial #35                 // Method java/lang/Object."<init>":()V
         4: return
      LineNumberTable:
        line 38: 0
        line 16: 4
      LocalVariableTable:
        Start  Length  Slot  Name   Signature
            0       5     0  this   Lcoursier/params/rule/AlwaysFail$;
}
SourceFile: "AlwaysFail.scala"
  ScalaInlineInfo: length = 0x18 (unknown attribute)
   01 01 00 04 00 0C 00 0B 01 00 11 00 12 01 00 11
   00 19 01 00 1C 00 1D 01
  Scala: length = 0x0 (unknown attribute)

