Classfile /Users/mw/Projects/slang-braindump/.jar/jar8/assemble/slang-braindump/assemble/content/coursier/params/rule/Strict$UnsatisfiableRule.class
  Last modified May 29, 2022; size 1595 bytes
  SHA-256 checksum 6faa172a5878794bafc046f3b31630f48a5c6c649cc095740d56ef1cbbab8ae7
  Compiled from "Strict.scala"
public final class coursier.params.rule.Strict$UnsatisfiableRule extends coursier.error.ResolutionError$UnsatisfiableRule
  minor version: 0
  major version: 52
  flags: (0x0031) ACC_PUBLIC, ACC_FINAL, ACC_SUPER
  this_class: #2                          // coursier/params/rule/Strict$UnsatisfiableRule
  super_class: #4                         // coursier/error/ResolutionError$UnsatisfiableRule
  interfaces: 0, fields: 0, methods: 5, attributes: 4
Constant pool:
   #1 = Utf8               coursier/params/rule/Strict$UnsatisfiableRule
   #2 = Class              #1             // coursier/params/rule/Strict$UnsatisfiableRule
   #3 = Utf8               coursier/error/ResolutionError$UnsatisfiableRule
   #4 = Class              #3             // coursier/error/ResolutionError$UnsatisfiableRule
   #5 = Utf8               Strict.scala
   #6 = Utf8               coursier/error/ResolutionError
   #7 = Class              #6             // coursier/error/ResolutionError
   #8 = Utf8               UnsatisfiableRule
   #9 = Utf8               coursier/params/rule/Strict$EvictedDependencies
  #10 = Class              #9             // coursier/params/rule/Strict$EvictedDependencies
  #11 = Utf8               coursier/params/rule/Strict
  #12 = Class              #11            // coursier/params/rule/Strict
  #13 = Utf8               EvictedDependencies
  #14 = Utf8               rule
  #15 = Utf8               ()Lcoursier/params/rule/Strict;
  #16 = Utf8               ()Lcoursier/params/rule/Rule;
  #17 = NameAndType        #14:#16        // rule:()Lcoursier/params/rule/Rule;
  #18 = Methodref          #4.#17         // coursier/error/ResolutionError$UnsatisfiableRule.rule:()Lcoursier/params/rule/Rule;
  #19 = Utf8               this
  #20 = Utf8               Lcoursier/params/rule/Strict$UnsatisfiableRule;
  #21 = Utf8               conflict
  #22 = Utf8               ()Lcoursier/params/rule/Strict$EvictedDependencies;
  #23 = Utf8               ()Lcoursier/error/conflict/UnsatisfiedRule;
  #24 = NameAndType        #21:#23        // conflict:()Lcoursier/error/conflict/UnsatisfiedRule;
  #25 = Methodref          #4.#24         // coursier/error/ResolutionError$UnsatisfiableRule.conflict:()Lcoursier/error/conflict/UnsatisfiedRule;
  #26 = NameAndType        #21:#22        // conflict:()Lcoursier/params/rule/Strict$EvictedDependencies;
  #27 = Methodref          #2.#26         // coursier/params/rule/Strict$UnsatisfiableRule.conflict:()Lcoursier/params/rule/Strict$EvictedDependencies;
  #28 = NameAndType        #14:#15        // rule:()Lcoursier/params/rule/Strict;
  #29 = Methodref          #2.#28         // coursier/params/rule/Strict$UnsatisfiableRule.rule:()Lcoursier/params/rule/Strict;
  #30 = Utf8               <init>
  #31 = Utf8               (Lcoursier/core/Resolution;Lcoursier/params/rule/Strict;Lcoursier/params/rule/Strict$EvictedDependencies;)V
  #32 = Utf8               resolution
  #33 = Utf8               getMessage
  #34 = Utf8               ()Ljava/lang/String;
  #35 = NameAndType        #33:#34        // getMessage:()Ljava/lang/String;
  #36 = Methodref          #10.#35        // coursier/params/rule/Strict$EvictedDependencies.getMessage:()Ljava/lang/String;
  #37 = Utf8               (Lcoursier/core/Resolution;Lcoursier/params/rule/Rule;Lcoursier/error/conflict/UnsatisfiedRule;Ljava/lang/String;)V
  #38 = NameAndType        #30:#37        // "<init>":(Lcoursier/core/Resolution;Lcoursier/params/rule/Rule;Lcoursier/error/conflict/UnsatisfiedRule;Ljava/lang/String;)V
  #39 = Methodref          #4.#38         // coursier/error/ResolutionError$UnsatisfiableRule."<init>":(Lcoursier/core/Resolution;Lcoursier/params/rule/Rule;Lcoursier/error/conflict/UnsatisfiedRule;Ljava/lang/String;)V
  #40 = Utf8               Lcoursier/core/Resolution;
  #41 = Utf8               Lcoursier/params/rule/Strict;
  #42 = Utf8               Lcoursier/params/rule/Strict$EvictedDependencies;
  #43 = Utf8               Code
  #44 = Utf8               LineNumberTable
  #45 = Utf8               LocalVariableTable
  #46 = Utf8               MethodParameters
  #47 = Utf8               InnerClasses
  #48 = Utf8               SourceFile
  #49 = Utf8               ScalaInlineInfo
  #50 = Utf8               Scala
{
  public coursier.params.rule.Strict rule();
    descriptor: ()Lcoursier/params/rule/Strict;
    flags: (0x0001) ACC_PUBLIC
    Code:
      stack=1, locals=1, args_size=1
         0: aload_0
         1: invokespecial #18                 // Method coursier/error/ResolutionError$UnsatisfiableRule.rule:()Lcoursier/params/rule/Rule;
         4: checkcast     #12                 // class coursier/params/rule/Strict
         7: areturn
      LineNumberTable:
        line 95: 0
      LocalVariableTable:
        Start  Length  Slot  Name   Signature
            0       8     0  this   Lcoursier/params/rule/Strict$UnsatisfiableRule;

  public coursier.params.rule.Strict$EvictedDependencies conflict();
    descriptor: ()Lcoursier/params/rule/Strict$EvictedDependencies;
    flags: (0x0001) ACC_PUBLIC
    Code:
      stack=1, locals=1, args_size=1
         0: aload_0
         1: invokespecial #25                 // Method coursier/error/ResolutionError$UnsatisfiableRule.conflict:()Lcoursier/error/conflict/UnsatisfiedRule;
         4: checkcast     #10                 // class coursier/params/rule/Strict$EvictedDependencies
         7: areturn
      LineNumberTable:
        line 96: 0
      LocalVariableTable:
        Start  Length  Slot  Name   Signature
            0       8     0  this   Lcoursier/params/rule/Strict$UnsatisfiableRule;

  public coursier.error.conflict.UnsatisfiedRule conflict();
    descriptor: ()Lcoursier/error/conflict/UnsatisfiedRule;
    flags: (0x1041) ACC_PUBLIC, ACC_BRIDGE, ACC_SYNTHETIC
    Code:
      stack=1, locals=1, args_size=1
         0: aload_0
         1: invokevirtual #27                 // Method conflict:()Lcoursier/params/rule/Strict$EvictedDependencies;
         4: areturn
      LineNumberTable:
        line 93: 0
      LocalVariableTable:
        Start  Length  Slot  Name   Signature
            0       5     0  this   Lcoursier/params/rule/Strict$UnsatisfiableRule;

  public coursier.params.rule.Rule rule();
    descriptor: ()Lcoursier/params/rule/Rule;
    flags: (0x1041) ACC_PUBLIC, ACC_BRIDGE, ACC_SYNTHETIC
    Code:
      stack=1, locals=1, args_size=1
         0: aload_0
         1: invokevirtual #29                 // Method rule:()Lcoursier/params/rule/Strict;
         4: areturn
      LineNumberTable:
        line 93: 0
      LocalVariableTable:
        Start  Length  Slot  Name   Signature
            0       5     0  this   Lcoursier/params/rule/Strict$UnsatisfiableRule;

  public coursier.params.rule.Strict$UnsatisfiableRule(coursier.core.Resolution, coursier.params.rule.Strict, coursier.params.rule.Strict$EvictedDependencies);
    descriptor: (Lcoursier/core/Resolution;Lcoursier/params/rule/Strict;Lcoursier/params/rule/Strict$EvictedDependencies;)V
    flags: (0x0001) ACC_PUBLIC
    Code:
      stack=5, locals=4, args_size=4
         0: aload_0
         1: aload_1
         2: aload_2
         3: aload_3
         4: aload_3
         5: invokevirtual #36                 // Method coursier/params/rule/Strict$EvictedDependencies.getMessage:()Ljava/lang/String;
         8: invokespecial #39                 // Method coursier/error/ResolutionError$UnsatisfiableRule."<init>":(Lcoursier/core/Resolution;Lcoursier/params/rule/Rule;Lcoursier/error/conflict/UnsatisfiedRule;Ljava/lang/String;)V
        11: return
      LineNumberTable:
        line 97: 0
        line 98: 1
        line 99: 2
        line 100: 3
        line 101: 4
        line 93: 11
      LocalVariableTable:
        Start  Length  Slot  Name   Signature
            0      12     0  this   Lcoursier/params/rule/Strict$UnsatisfiableRule;
            0      12     1 resolution   Lcoursier/core/Resolution;
            0      12     2  rule   Lcoursier/params/rule/Strict;
            0      12     3 conflict   Lcoursier/params/rule/Strict$EvictedDependencies;
    MethodParameters:
      Name                           Flags
      resolution                     final
      rule                           final
      conflict                       final
}
InnerClasses:
  public static abstract #8= #4 of #7;    // UnsatisfiableRule=class coursier/error/ResolutionError$UnsatisfiableRule of class coursier/error/ResolutionError
  public static final #13= #10 of #12;    // EvictedDependencies=class coursier/params/rule/Strict$EvictedDependencies of class coursier/params/rule/Strict
  public static final #8= #2 of #12;      // UnsatisfiableRule=class coursier/params/rule/Strict$UnsatisfiableRule of class coursier/params/rule/Strict
SourceFile: "Strict.scala"
  ScalaInlineInfo: length = 0x1D (unknown attribute)
   01 01 00 05 00 1E 00 1F 01 00 15 00 17 01 00 15
   00 16 01 00 0E 00 10 01 00 0E 00 0F 01
  Scala: length = 0x0 (unknown attribute)

