Classfile /Users/mw/Projects/slang-braindump/.jar/jar11/assemble/slang-braindump/assemble/content/com/fasterxml/jackson/databind/deser/impl/JDKValueInstantiators$ArrayListInstantiator.class
  Last modified May 29, 2022; size 1357 bytes
  SHA-256 checksum 380e07969202f106ebfc1b41dc480bc427f9fe58167b5cc657e1233cf9c9ae59
  Compiled from "JDKValueInstantiators.java"
class com.fasterxml.jackson.databind.deser.impl.JDKValueInstantiators$ArrayListInstantiator extends com.fasterxml.jackson.databind.deser.ValueInstantiator$Base implements java.io.Serializable
  minor version: 0
  major version: 52
  flags: (0x0020) ACC_SUPER
  this_class: #4                          // com/fasterxml/jackson/databind/deser/impl/JDKValueInstantiators$ArrayListInstantiator
  super_class: #7                         // com/fasterxml/jackson/databind/deser/ValueInstantiator$Base
  interfaces: 1, fields: 2, methods: 5, attributes: 2
Constant pool:
   #1 = Class              #36            // java/util/ArrayList
   #2 = Methodref          #7.#37         // com/fasterxml/jackson/databind/deser/ValueInstantiator$Base."<init>":(Ljava/lang/Class;)V
   #3 = Methodref          #1.#38         // java/util/ArrayList."<init>":()V
   #4 = Class              #40            // com/fasterxml/jackson/databind/deser/impl/JDKValueInstantiators$ArrayListInstantiator
   #5 = Methodref          #4.#38         // com/fasterxml/jackson/databind/deser/impl/JDKValueInstantiators$ArrayListInstantiator."<init>":()V
   #6 = Fieldref           #4.#41         // com/fasterxml/jackson/databind/deser/impl/JDKValueInstantiators$ArrayListInstantiator.INSTANCE:Lcom/fasterxml/jackson/databind/deser/impl/JDKValueInstantiators$ArrayListInstantiator;
   #7 = Class              #43            // com/fasterxml/jackson/databind/deser/ValueInstantiator$Base
   #8 = Class              #45            // java/io/Serializable
   #9 = Utf8               serialVersionUID
  #10 = Utf8               J
  #11 = Utf8               ConstantValue
  #12 = Long               2l
  #14 = Utf8               INSTANCE
  #15 = Utf8               ArrayListInstantiator
  #16 = Utf8               InnerClasses
  #17 = Utf8               Lcom/fasterxml/jackson/databind/deser/impl/JDKValueInstantiators$ArrayListInstantiator;
  #18 = Utf8               <init>
  #19 = Utf8               ()V
  #20 = Utf8               Code
  #21 = Utf8               LineNumberTable
  #22 = Utf8               LocalVariableTable
  #23 = Utf8               this
  #24 = Utf8               canInstantiate
  #25 = Utf8               ()Z
  #26 = Utf8               canCreateUsingDefault
  #27 = Utf8               createUsingDefault
  #28 = Utf8               (Lcom/fasterxml/jackson/databind/DeserializationContext;)Ljava/lang/Object;
  #29 = Utf8               ctxt
  #30 = Utf8               Lcom/fasterxml/jackson/databind/DeserializationContext;
  #31 = Utf8               Exceptions
  #32 = Class              #46            // java/io/IOException
  #33 = Utf8               <clinit>
  #34 = Utf8               SourceFile
  #35 = Utf8               JDKValueInstantiators.java
  #36 = Utf8               java/util/ArrayList
  #37 = NameAndType        #18:#47        // "<init>":(Ljava/lang/Class;)V
  #38 = NameAndType        #18:#19        // "<init>":()V
  #39 = Class              #48            // com/fasterxml/jackson/databind/deser/impl/JDKValueInstantiators
  #40 = Utf8               com/fasterxml/jackson/databind/deser/impl/JDKValueInstantiators$ArrayListInstantiator
  #41 = NameAndType        #14:#17        // INSTANCE:Lcom/fasterxml/jackson/databind/deser/impl/JDKValueInstantiators$ArrayListInstantiator;
  #42 = Class              #49            // com/fasterxml/jackson/databind/deser/ValueInstantiator
  #43 = Utf8               com/fasterxml/jackson/databind/deser/ValueInstantiator$Base
  #44 = Utf8               Base
  #45 = Utf8               java/io/Serializable
  #46 = Utf8               java/io/IOException
  #47 = Utf8               (Ljava/lang/Class;)V
  #48 = Utf8               com/fasterxml/jackson/databind/deser/impl/JDKValueInstantiators
  #49 = Utf8               com/fasterxml/jackson/databind/deser/ValueInstantiator
{
  private static final long serialVersionUID;
    descriptor: J
    flags: (0x001a) ACC_PRIVATE, ACC_STATIC, ACC_FINAL
    ConstantValue: long 2l

  public static final com.fasterxml.jackson.databind.deser.impl.JDKValueInstantiators$ArrayListInstantiator INSTANCE;
    descriptor: Lcom/fasterxml/jackson/databind/deser/impl/JDKValueInstantiators$ArrayListInstantiator;
    flags: (0x0019) ACC_PUBLIC, ACC_STATIC, ACC_FINAL

  public com.fasterxml.jackson.databind.deser.impl.JDKValueInstantiators$ArrayListInstantiator();
    descriptor: ()V
    flags: (0x0001) ACC_PUBLIC
    Code:
      stack=2, locals=1, args_size=1
         0: aload_0
         1: ldc           #1                  // class java/util/ArrayList
         3: invokespecial #2                  // Method com/fasterxml/jackson/databind/deser/ValueInstantiator$Base."<init>":(Ljava/lang/Class;)V
         6: return
      LineNumberTable:
        line 66: 0
        line 67: 6
      LocalVariableTable:
        Start  Length  Slot  Name   Signature
            0       7     0  this   Lcom/fasterxml/jackson/databind/deser/impl/JDKValueInstantiators$ArrayListInstantiator;

  public boolean canInstantiate();
    descriptor: ()Z
    flags: (0x0001) ACC_PUBLIC
    Code:
      stack=1, locals=1, args_size=1
         0: iconst_1
         1: ireturn
      LineNumberTable:
        line 70: 0
      LocalVariableTable:
        Start  Length  Slot  Name   Signature
            0       2     0  this   Lcom/fasterxml/jackson/databind/deser/impl/JDKValueInstantiators$ArrayListInstantiator;

  public boolean canCreateUsingDefault();
    descriptor: ()Z
    flags: (0x0001) ACC_PUBLIC
    Code:
      stack=1, locals=1, args_size=1
         0: iconst_1
         1: ireturn
      LineNumberTable:
        line 73: 0
      LocalVariableTable:
        Start  Length  Slot  Name   Signature
            0       2     0  this   Lcom/fasterxml/jackson/databind/deser/impl/JDKValueInstantiators$ArrayListInstantiator;

  public java.lang.Object createUsingDefault(com.fasterxml.jackson.databind.DeserializationContext) throws java.io.IOException;
    descriptor: (Lcom/fasterxml/jackson/databind/DeserializationContext;)Ljava/lang/Object;
    flags: (0x0001) ACC_PUBLIC
    Code:
      stack=2, locals=2, args_size=2
         0: new           #1                  // class java/util/ArrayList
         3: dup
         4: invokespecial #3                  // Method java/util/ArrayList."<init>":()V
         7: areturn
      LineNumberTable:
        line 77: 0
      LocalVariableTable:
        Start  Length  Slot  Name   Signature
            0       8     0  this   Lcom/fasterxml/jackson/databind/deser/impl/JDKValueInstantiators$ArrayListInstantiator;
            0       8     1  ctxt   Lcom/fasterxml/jackson/databind/DeserializationContext;
    Exceptions:
      throws java.io.IOException

  static {};
    descriptor: ()V
    flags: (0x0008) ACC_STATIC
    Code:
      stack=2, locals=0, args_size=0
         0: new           #4                  // class com/fasterxml/jackson/databind/deser/impl/JDKValueInstantiators$ArrayListInstantiator
         3: dup
         4: invokespecial #5                  // Method "<init>":()V
         7: putstatic     #6                  // Field INSTANCE:Lcom/fasterxml/jackson/databind/deser/impl/JDKValueInstantiators$ArrayListInstantiator;
        10: return
      LineNumberTable:
        line 64: 0
}
SourceFile: "JDKValueInstantiators.java"
InnerClasses:
  private static #15= #4 of #39;          // ArrayListInstantiator=class com/fasterxml/jackson/databind/deser/impl/JDKValueInstantiators$ArrayListInstantiator of class com/fasterxml/jackson/databind/deser/impl/JDKValueInstantiators
  public static #44= #7 of #42;           // Base=class com/fasterxml/jackson/databind/deser/ValueInstantiator$Base of class com/fasterxml/jackson/databind/deser/ValueInstantiator
