Classfile /Users/mw/Projects/slang-braindump/.jar/jar8/assemble/slang-braindump/assemble/content/scala/collection/convert/AsJavaExtensions$MutableMapHasAsJava.class
  Last modified May 29, 2022; size 1880 bytes
  SHA-256 checksum ef87cf4f8c2efcb46713c6b37d342d7b8bb5866e66fefbfaf2dba872dc459da7
  Compiled from "AsJavaExtensions.scala"
public class scala.collection.convert.AsJavaExtensions$MutableMapHasAsJava<K extends java.lang.Object, V extends java.lang.Object> extends java.lang.Object
  minor version: 0
  major version: 52
  flags: (0x0021) ACC_PUBLIC, ACC_SUPER
  this_class: #2                          // scala/collection/convert/AsJavaExtensions$MutableMapHasAsJava
  super_class: #5                         // java/lang/Object
  interfaces: 0, fields: 2, methods: 4, attributes: 5
Constant pool:
   #1 = Utf8               scala/collection/convert/AsJavaExtensions$MutableMapHasAsJava
   #2 = Class              #1             // scala/collection/convert/AsJavaExtensions$MutableMapHasAsJava
   #3 = Utf8               <K:Ljava/lang/Object;V:Ljava/lang/Object;>Ljava/lang/Object;
   #4 = Utf8               java/lang/Object
   #5 = Class              #4             // java/lang/Object
   #6 = Utf8               AsJavaExtensions.scala
   #7 = Utf8               scala/collection/convert/AsJavaExtensions
   #8 = Class              #7             // scala/collection/convert/AsJavaExtensions
   #9 = Utf8               MutableMapHasAsJava
  #10 = Utf8               m
  #11 = Utf8               Lscala/collection/mutable/Map;
  #12 = Utf8               Lscala/collection/mutable/Map<TK;TV;>;
  #13 = Utf8               $outer
  #14 = Utf8               Lscala/collection/convert/AsJavaExtensions;
  #15 = Utf8               asJava
  #16 = Utf8               ()Ljava/util/Map;
  #17 = Utf8               ()Ljava/util/Map<TK;TV;>;
  #18 = Utf8               scala/jdk/javaapi/CollectionConverters$
  #19 = Class              #18            // scala/jdk/javaapi/CollectionConverters$
  #20 = Utf8               MODULE$
  #21 = Utf8               Lscala/jdk/javaapi/CollectionConverters$;
  #22 = NameAndType        #20:#21        // MODULE$:Lscala/jdk/javaapi/CollectionConverters$;
  #23 = Fieldref           #19.#22        // scala/jdk/javaapi/CollectionConverters$.MODULE$:Lscala/jdk/javaapi/CollectionConverters$;
  #24 = NameAndType        #10:#11        // m:Lscala/collection/mutable/Map;
  #25 = Fieldref           #2.#24         // scala/collection/convert/AsJavaExtensions$MutableMapHasAsJava.m:Lscala/collection/mutable/Map;
  #26 = Utf8               scala/collection/convert/AsJavaConverters
  #27 = Class              #26            // scala/collection/convert/AsJavaConverters
  #28 = Utf8               asJava$
  #29 = Utf8               (Lscala/collection/convert/AsJavaConverters;Lscala/collection/mutable/Map;)Ljava/util/Map;
  #30 = NameAndType        #28:#29        // asJava$:(Lscala/collection/convert/AsJavaConverters;Lscala/collection/mutable/Map;)Ljava/util/Map;
  #31 = InterfaceMethodref #27.#30        // scala/collection/convert/AsJavaConverters.asJava$:(Lscala/collection/convert/AsJavaConverters;Lscala/collection/mutable/Map;)Ljava/util/Map;
  #32 = Utf8               this
  #33 = Utf8               Lscala/collection/convert/AsJavaExtensions$MutableMapHasAsJava;
  #34 = Utf8               asJavaDictionary
  #35 = Utf8               ()Ljava/util/Dictionary;
  #36 = Utf8               ()Ljava/util/Dictionary<TK;TV;>;
  #37 = Utf8               asJavaDictionary$
  #38 = Utf8               (Lscala/collection/convert/AsJavaConverters;Lscala/collection/mutable/Map;)Ljava/util/Dictionary;
  #39 = NameAndType        #37:#38        // asJavaDictionary$:(Lscala/collection/convert/AsJavaConverters;Lscala/collection/mutable/Map;)Ljava/util/Dictionary;
  #40 = InterfaceMethodref #27.#39        // scala/collection/convert/AsJavaConverters.asJavaDictionary$:(Lscala/collection/convert/AsJavaConverters;Lscala/collection/mutable/Map;)Ljava/util/Dictionary;
  #41 = Utf8               scala$collection$convert$AsJavaExtensions$MutableMapHasAsJava$$$outer
  #42 = Utf8               ()Lscala/collection/convert/AsJavaExtensions;
  #43 = NameAndType        #13:#14        // $outer:Lscala/collection/convert/AsJavaExtensions;
  #44 = Fieldref           #2.#43         // scala/collection/convert/AsJavaExtensions$MutableMapHasAsJava.$outer:Lscala/collection/convert/AsJavaExtensions;
  #45 = Utf8               <init>
  #46 = Utf8               (Lscala/collection/convert/AsJavaExtensions;Lscala/collection/mutable/Map;)V
  #47 = Utf8               (Lscala/collection/mutable/Map<TK;TV;>;)V
  #48 = Utf8               ()V
  #49 = NameAndType        #45:#48        // "<init>":()V
  #50 = Methodref          #5.#49         // java/lang/Object."<init>":()V
  #51 = Utf8               Signature
  #52 = Utf8               Code
  #53 = Utf8               LineNumberTable
  #54 = Utf8               LocalVariableTable
  #55 = Utf8               StackMapTable
  #56 = Utf8               MethodParameters
  #57 = Utf8               InnerClasses
  #58 = Utf8               SourceFile
  #59 = Utf8               ScalaInlineInfo
  #60 = Utf8               Scala
{
  private final scala.collection.mutable.Map<K, V> m;
    descriptor: Lscala/collection/mutable/Map;
    flags: (0x0012) ACC_PRIVATE, ACC_FINAL
    Signature: #12                          // Lscala/collection/mutable/Map<TK;TV;>;

  public final scala.collection.convert.AsJavaExtensions $outer;
    descriptor: Lscala/collection/convert/AsJavaExtensions;
    flags: (0x1011) ACC_PUBLIC, ACC_FINAL, ACC_SYNTHETIC

  public java.util.Map<K, V> asJava();
    descriptor: ()Ljava/util/Map;
    flags: (0x0001) ACC_PUBLIC
    Code:
      stack=2, locals=1, args_size=1
         0: getstatic     #23                 // Field scala/jdk/javaapi/CollectionConverters$.MODULE$:Lscala/jdk/javaapi/CollectionConverters$;
         3: aload_0
         4: getfield      #25                 // Field m:Lscala/collection/mutable/Map;
         7: invokestatic  #31                 // InterfaceMethod scala/collection/convert/AsJavaConverters.asJava$:(Lscala/collection/convert/AsJavaConverters;Lscala/collection/mutable/Map;)Ljava/util/Map;
        10: areturn
      LineNumberTable:
        line 87: 0
      LocalVariableTable:
        Start  Length  Slot  Name   Signature
            0      11     0  this   Lscala/collection/convert/AsJavaExtensions$MutableMapHasAsJava;
    Signature: #17                          // ()Ljava/util/Map<TK;TV;>;

  public java.util.Dictionary<K, V> asJavaDictionary();
    descriptor: ()Ljava/util/Dictionary;
    flags: (0x0001) ACC_PUBLIC
    Code:
      stack=2, locals=1, args_size=1
         0: getstatic     #23                 // Field scala/jdk/javaapi/CollectionConverters$.MODULE$:Lscala/jdk/javaapi/CollectionConverters$;
         3: aload_0
         4: getfield      #25                 // Field m:Lscala/collection/mutable/Map;
         7: invokestatic  #40                 // InterfaceMethod scala/collection/convert/AsJavaConverters.asJavaDictionary$:(Lscala/collection/convert/AsJavaConverters;Lscala/collection/mutable/Map;)Ljava/util/Dictionary;
        10: areturn
      LineNumberTable:
        line 92: 0
      LocalVariableTable:
        Start  Length  Slot  Name   Signature
            0      11     0  this   Lscala/collection/convert/AsJavaExtensions$MutableMapHasAsJava;
    Signature: #36                          // ()Ljava/util/Dictionary<TK;TV;>;

  public scala.collection.convert.AsJavaExtensions scala$collection$convert$AsJavaExtensions$MutableMapHasAsJava$$$outer();
    descriptor: ()Lscala/collection/convert/AsJavaExtensions;
    flags: (0x1001) ACC_PUBLIC, ACC_SYNTHETIC
    Code:
      stack=1, locals=1, args_size=1
         0: aload_0
         1: getfield      #44                 // Field $outer:Lscala/collection/convert/AsJavaExtensions;
         4: areturn
      LineNumberTable:
        line 83: 0
      LocalVariableTable:
        Start  Length  Slot  Name   Signature
            0       5     0  this   Lscala/collection/convert/AsJavaExtensions$MutableMapHasAsJava;

  public scala.collection.convert.AsJavaExtensions$MutableMapHasAsJava(scala.collection.mutable.Map<K, V>);
    descriptor: (Lscala/collection/convert/AsJavaExtensions;Lscala/collection/mutable/Map;)V
    flags: (0x0001) ACC_PUBLIC
    Code:
      stack=2, locals=3, args_size=3
         0: aload_0
         1: aload_2
         2: putfield      #25                 // Field m:Lscala/collection/mutable/Map;
         5: aload_1
         6: ifnonnull     11
         9: aconst_null
        10: athrow
        11: aload_0
        12: aload_1
        13: putfield      #44                 // Field $outer:Lscala/collection/convert/AsJavaExtensions;
        16: aload_0
        17: invokespecial #50                 // Method java/lang/Object."<init>":()V
        20: return
      StackMapTable: number_of_entries = 1
        frame_type = 11 /* same */
      LineNumberTable:
        line 83: 0
      LocalVariableTable:
        Start  Length  Slot  Name   Signature
            0      21     0  this   Lscala/collection/convert/AsJavaExtensions$MutableMapHasAsJava;
            0      21     1 $outer   Lscala/collection/convert/AsJavaExtensions;
            0      21     2     m   Lscala/collection/mutable/Map;
    Signature: #47                          // (Lscala/collection/mutable/Map<TK;TV;>;)V
    MethodParameters:
      Name                           Flags
      $outer                         final synthetic
      m                              final
}
InnerClasses:
  public #9= #2 of #8;                    // MutableMapHasAsJava=class scala/collection/convert/AsJavaExtensions$MutableMapHasAsJava of class scala/collection/convert/AsJavaExtensions
Signature: #3                           // <K:Ljava/lang/Object;V:Ljava/lang/Object;>Ljava/lang/Object;
SourceFile: "AsJavaExtensions.scala"
  ScalaInlineInfo: length = 0x18 (unknown attribute)
   01 00 00 04 00 2D 00 2E 00 00 0F 00 10 00 00 22
   00 23 00 00 29 00 2A 00
  Scala: length = 0x0 (unknown attribute)

