Classfile /Users/mw/Projects/slang-braindump/.jar/jar8/assemble/slang-braindump/assemble/content/scala/collection/convert/AsScalaConverters.class
  Last modified May 29, 2022; size 9716 bytes
  SHA-256 checksum 004fe80fda516a14ec21617eb3e2d5ea646e75b9537bc9f1b6324ef907bbb18d
  Compiled from "AsScalaConverters.scala"
public interface scala.collection.convert.AsScalaConverters
  minor version: 0
  major version: 52
  flags: (0x0601) ACC_PUBLIC, ACC_INTERFACE, ACC_ABSTRACT
  this_class: #2                          // scala/collection/convert/AsScalaConverters
  super_class: #4                         // java/lang/Object
  interfaces: 0, fields: 0, methods: 21, attributes: 5
Constant pool:
    #1 = Utf8               scala/collection/convert/AsScalaConverters
    #2 = Class              #1            // scala/collection/convert/AsScalaConverters
    #3 = Utf8               java/lang/Object
    #4 = Class              #3            // java/lang/Object
    #5 = Utf8               AsScalaConverters.scala
    #6 = Utf8               Lscala/reflect/ScalaSignature;
    #7 = Utf8               bytes
    #8 = Utf8               \u0006\u0005\u0005\rda\u0002\u0007\u000e!\u0003\r\t\u0001\u0006\u0005\u00063\u0001!\tA\u0007\u0005\u0006=\u0001!\ta\b\u0005\u0006=\u0001!\t!\u000f\u0005\u0006=\u0001!\ta\u0011\u0005\u0006=\u0001!\t\u0001\u0015\u0005\u0006=\u0001!\tA\u0017\u0005\u0006=\u0001!\t!\u001b\u0005\u0006=\u0001!\t\u0001\u001e\u0005\u0007=\u0001!\t!!\u0002\t\ry\u0001A\u0011AA\u0014\u0011\u0019q\u0002\u0001\"\u0001\u0002@\t\t\u0012i]*dC2\f7i\u001c8wKJ$XM]:\u000b\u00059y\u0011aB2p]Z,\'\u000f\u001e\u0006\u0003!E\t!bY8mY\u0016\u001cG/[8o\u0015\u0005\u0011\u0012!B:dC2\f7\u0001A\n\u0003\u0001U\u0001\"AF\f\u000e\u0003EI!\u0001G\t\u0003\r\u0005s\u0017PU3g\u0003\u0019!\u0013N\\5uIQ\t1\u0004\u0005\u0002\u00179%\u0011Q$\u0005\u0002\u0005+:LG/A\u0004bgN\u001b\u0017\r\\1\u0016\u0005\u0001:CCA\u00111!\r\u00113%J\u0007\u0002\u001f%\u0011Ae\u0004\u0002\t\u0013R,\'/\u0019;peB\u0011ae\n\u0007\u0001\t\u0015A#A1\u0001*\u0005\u0005\t\u0015C\u0001\u0016.!\t12&\u0003\u0002-#\t9aj\u001c;iS:<\u0007C\u0001\f/\u0013\ty\u0013CA\u0002B]fDQ!\r\u0002A\u0002I\n\u0011!\u001b\t\u0004ga*S\"\u0001\u001b\u000b\u0005U2\u0014\u0001B;uS2T\u0011aN\u0001\u0005U\u00064\u0018-\u0003\u0002%iU\u0011!(\u0010\u000b\u0003wy\u00022AI\u0012=!\t1S\bB\u0003)\u0007\t\u0007\u0011\u0006C\u0003@\u0007\u0001\u0007\u0001)A\u0001f!\r\u0019\u0014\tP\u0005\u0003\u0005R\u00121\"\u00128v[\u0016\u0014\u0018\r^5p]V\u0011A)\u0013\u000b\u0003\u000b*\u00032A\t$I\u0013\t9uB\u0001\u0005Ji\u0016\u0014\u0018M\u00197f!\t1\u0013\nB\u0003)\t\t\u0007\u0011\u0006C\u00032\t\u0001\u00071\nE\u0002M\u001f\"k\u0011!\u0014\u0006\u0003\u001dZ\nA\u0001\\1oO&\u0011q)T\u000b\u0003#R#\"AU+\u0011\u0007\t25\u000b\u0005\u0002\')\u0012)\u0001&\u0002b\u0001S!)a+\u0002a\u0001/\u0006\t1\rE\u000241NK!!\u0017\u001b\u0003\u0015\r{G\u000e\\3di&|g.\u0006\u0002\\GR\u0011A\f\u001a\t\u0004;\u0002\u0014W\"\u00010\u000b\u0005}{\u0011aB7vi\u0006\u0014G.Z\u0005\u0003Cz\u0013aAQ;gM\u0016\u0014\bC\u0001\u0014d\t\u0015AcA1\u0001*\u0011\u0015)g\u00011\u0001g\u0003\u0005a\u0007cA\u001ahE&\u0011\u0001\u000e\u000e\u0002\u0005\u0019&\u001cH/\u0006\u0002k_R\u00111\u000e\u001d\t\u0004;2t\u0017BA7_\u0005\r\u0019V\r\u001e\t\u0003M=$Q\u0001K\u0004C\u0002%BQ!]\u0004A\u0002I\f\u0011a\u001d\t\u0004gMt\u0017BA75+\r)(\u0010 \u000b\u0003mz\u0004B!X<zw&\u0011\u0001P\u0018\u0002\u0004\u001b\u0006\u0004\bC\u0001\u0014{\t\u0015A\u0003B1\u0001*!\t1C\u0010B\u0003~\u0011\t\u0007\u0011FA\u0001C\u0011\u0019y\b\u00021\u0001\u0002\u0002\u0005\tQ\u000eE\u00034\u0003\u0007I80\u0003\u0002yiU1\u0011qAA\u000b\u00033!B!!\u0003\u0002\u001cAA\u00111BA\t\u0003\'\t9\"\u0004\u0002\u0002\u000e)\u0019\u0011qB\b\u0002\u0015\r|gnY;se\u0016tG/C\u0002y\u0003\u001b\u00012AJA\u000b\t\u0015A\u0013B1\u0001*!\r1\u0013\u0011\u0004\u0003\u0006{&\u0011\r!\u000b\u0005\u0007\u007f&\u0001\r!!\b\u0011\u0011\u0005}\u00111EA\n\u0003/i!!!\t\u000b\u0007\u0005=A\'\u0003\u0003\u0002&\u0005\u0005\"!D\"p]\u000e,(O]3oi6\u000b\u0007/\u0006\u0004\u0002*\u0005=\u00121\u0007\u000b\u0005\u0003W\t)\u0004\u0005\u0004^o\u00065\u0012\u0011\u0007\t\u0004M\u0005=B!\u0002\u0015\u000b\u0005\u0004I\u0003c\u0001\u0014\u00024\u0011)QP\u0003b\u0001S!9\u0011q\u0007\u0006A\u0002\u0005e\u0012!\u00013\u0011\u000fM\nY$!\f\u00022%\u0019\u0011Q\b\u001b\u0003\u0015\u0011K7\r^5p]\u0006\u0014\u0018\u0010\u0006\u0003\u0002B\u0005e\u0003CB/x\u0003\u0007\n\u0019\u0005\u0005\u0003\u0002F\u0005Mc\u0002BA$\u0003\u001f\u00022!!\u0013\u0012\u001b\t\tYEC\u0002\u0002NM\ta\u0001\u0010:p_Rt\u0014bAA)#\u00051\u0001K]3eK\u001aLA!!\u0016\u0002X\t11\u000b\u001e:j]\u001eT1!!\u0015\u0012\u0011\u001d\tYf\u0003a\u0001\u0003;\n\u0011\u0001\u001d\t\u0004g\u0005}\u0013bAA1i\tQ\u0001K]8qKJ$\u0018.Z:
    #9 = Utf8               scala/collection/convert/JavaCollectionWrappers$ConcurrentMapWrapper
   #10 = Class              #9            // scala/collection/convert/JavaCollectionWrappers$ConcurrentMapWrapper
   #11 = Utf8               scala/collection/convert/JavaCollectionWrappers
   #12 = Class              #11           // scala/collection/convert/JavaCollectionWrappers
   #13 = Utf8               ConcurrentMapWrapper
   #14 = Utf8               scala/collection/convert/JavaCollectionWrappers$DictionaryWrapper
   #15 = Class              #14           // scala/collection/convert/JavaCollectionWrappers$DictionaryWrapper
   #16 = Utf8               DictionaryWrapper
   #17 = Utf8               scala/collection/convert/JavaCollectionWrappers$IterableWrapper
   #18 = Class              #17           // scala/collection/convert/JavaCollectionWrappers$IterableWrapper
   #19 = Utf8               IterableWrapper
   #20 = Utf8               scala/collection/convert/JavaCollectionWrappers$IteratorWrapper
   #21 = Class              #20           // scala/collection/convert/JavaCollectionWrappers$IteratorWrapper
   #22 = Utf8               IteratorWrapper
   #23 = Utf8               scala/collection/convert/JavaCollectionWrappers$JCollectionWrapper
   #24 = Class              #23           // scala/collection/convert/JavaCollectionWrappers$JCollectionWrapper
   #25 = Utf8               JCollectionWrapper
   #26 = Utf8               scala/collection/convert/JavaCollectionWrappers$JConcurrentMapWrapper
   #27 = Class              #26           // scala/collection/convert/JavaCollectionWrappers$JConcurrentMapWrapper
   #28 = Utf8               JConcurrentMapWrapper
   #29 = Utf8               scala/collection/convert/JavaCollectionWrappers$JDictionaryWrapper
   #30 = Class              #29           // scala/collection/convert/JavaCollectionWrappers$JDictionaryWrapper
   #31 = Utf8               JDictionaryWrapper
   #32 = Utf8               scala/collection/convert/JavaCollectionWrappers$JEnumerationWrapper
   #33 = Class              #32           // scala/collection/convert/JavaCollectionWrappers$JEnumerationWrapper
   #34 = Utf8               JEnumerationWrapper
   #35 = Utf8               scala/collection/convert/JavaCollectionWrappers$JIterableWrapper
   #36 = Class              #35           // scala/collection/convert/JavaCollectionWrappers$JIterableWrapper
   #37 = Utf8               JIterableWrapper
   #38 = Utf8               scala/collection/convert/JavaCollectionWrappers$JIteratorWrapper
   #39 = Class              #38           // scala/collection/convert/JavaCollectionWrappers$JIteratorWrapper
   #40 = Utf8               JIteratorWrapper
   #41 = Utf8               scala/collection/convert/JavaCollectionWrappers$JListWrapper
   #42 = Class              #41           // scala/collection/convert/JavaCollectionWrappers$JListWrapper
   #43 = Utf8               JListWrapper
   #44 = Utf8               scala/collection/convert/JavaCollectionWrappers$JMapWrapper
   #45 = Class              #44           // scala/collection/convert/JavaCollectionWrappers$JMapWrapper
   #46 = Utf8               JMapWrapper
   #47 = Utf8               scala/collection/convert/JavaCollectionWrappers$JPropertiesWrapper
   #48 = Class              #47           // scala/collection/convert/JavaCollectionWrappers$JPropertiesWrapper
   #49 = Utf8               JPropertiesWrapper
   #50 = Utf8               scala/collection/convert/JavaCollectionWrappers$JSetWrapper
   #51 = Class              #50           // scala/collection/convert/JavaCollectionWrappers$JSetWrapper
   #52 = Utf8               JSetWrapper
   #53 = Utf8               scala/collection/convert/JavaCollectionWrappers$MutableBufferWrapper
   #54 = Class              #53           // scala/collection/convert/JavaCollectionWrappers$MutableBufferWrapper
   #55 = Utf8               MutableBufferWrapper
   #56 = Utf8               scala/collection/convert/JavaCollectionWrappers$MutableMapWrapper
   #57 = Class              #56           // scala/collection/convert/JavaCollectionWrappers$MutableMapWrapper
   #58 = Utf8               MutableMapWrapper
   #59 = Utf8               scala/collection/convert/JavaCollectionWrappers$MutableSetWrapper
   #60 = Class              #59           // scala/collection/convert/JavaCollectionWrappers$MutableSetWrapper
   #61 = Utf8               MutableSetWrapper
   #62 = Utf8               asScala$
   #63 = Utf8               (Lscala/collection/convert/AsScalaConverters;Ljava/util/Iterator;)Lscala/collection/Iterator;
   #64 = Utf8               $this
   #65 = Utf8               i
   #66 = Utf8               asScala
   #67 = Utf8               (Ljava/util/Iterator;)Lscala/collection/Iterator;
   #68 = NameAndType        #66:#67       // asScala:(Ljava/util/Iterator;)Lscala/collection/Iterator;
   #69 = InterfaceMethodref #2.#68        // scala/collection/convert/AsScalaConverters.asScala:(Ljava/util/Iterator;)Lscala/collection/Iterator;
   #70 = Utf8               Lscala/collection/convert/AsScalaConverters;
   #71 = Utf8               Ljava/util/Iterator;
   #72 = Utf8               <A:Ljava/lang/Object;>(Ljava/util/Iterator<TA;>;)Lscala/collection/Iterator<TA;>;
   #73 = Utf8               underlying
   #74 = Utf8               ()Lscala/collection/Iterator;
   #75 = NameAndType        #73:#74       // underlying:()Lscala/collection/Iterator;
   #76 = Methodref          #21.#75       // scala/collection/convert/JavaCollectionWrappers$IteratorWrapper.underlying:()Lscala/collection/Iterator;
   #77 = Utf8               <init>
   #78 = Utf8               (Ljava/util/Iterator;)V
   #79 = NameAndType        #77:#78       // "<init>":(Ljava/util/Iterator;)V
   #80 = Methodref          #39.#79       // scala/collection/convert/JavaCollectionWrappers$JIteratorWrapper."<init>":(Ljava/util/Iterator;)V
   #81 = Utf8               this
   #82 = Utf8               scala/collection/Iterator
   #83 = Class              #82           // scala/collection/Iterator
   #84 = Utf8               (Lscala/collection/convert/AsScalaConverters;Ljava/util/Enumeration;)Lscala/collection/Iterator;
   #85 = Utf8               e
   #86 = Utf8               (Ljava/util/Enumeration;)Lscala/collection/Iterator;
   #87 = NameAndType        #66:#86       // asScala:(Ljava/util/Enumeration;)Lscala/collection/Iterator;
   #88 = InterfaceMethodref #2.#87        // scala/collection/convert/AsScalaConverters.asScala:(Ljava/util/Enumeration;)Lscala/collection/Iterator;
   #89 = Utf8               Ljava/util/Enumeration;
   #90 = Utf8               <A:Ljava/lang/Object;>(Ljava/util/Enumeration<TA;>;)Lscala/collection/Iterator<TA;>;
   #91 = Utf8               (Ljava/util/Enumeration;)V
   #92 = NameAndType        #77:#91       // "<init>":(Ljava/util/Enumeration;)V
   #93 = Methodref          #33.#92       // scala/collection/convert/JavaCollectionWrappers$JEnumerationWrapper."<init>":(Ljava/util/Enumeration;)V
   #94 = Utf8               (Lscala/collection/convert/AsScalaConverters;Ljava/lang/Iterable;)Lscala/collection/Iterable;
   #95 = Utf8               (Ljava/lang/Iterable;)Lscala/collection/Iterable;
   #96 = NameAndType        #66:#95       // asScala:(Ljava/lang/Iterable;)Lscala/collection/Iterable;
   #97 = InterfaceMethodref #2.#96        // scala/collection/convert/AsScalaConverters.asScala:(Ljava/lang/Iterable;)Lscala/collection/Iterable;
   #98 = Utf8               Ljava/lang/Iterable;
   #99 = Utf8               <A:Ljava/lang/Object;>(Ljava/lang/Iterable<TA;>;)Lscala/collection/Iterable<TA;>;
  #100 = Utf8               ()Lscala/collection/Iterable;
  #101 = NameAndType        #73:#100      // underlying:()Lscala/collection/Iterable;
  #102 = Methodref          #18.#101      // scala/collection/convert/JavaCollectionWrappers$IterableWrapper.underlying:()Lscala/collection/Iterable;
  #103 = Utf8               (Ljava/lang/Iterable;)V
  #104 = NameAndType        #77:#103      // "<init>":(Ljava/lang/Iterable;)V
  #105 = Methodref          #36.#104      // scala/collection/convert/JavaCollectionWrappers$JIterableWrapper."<init>":(Ljava/lang/Iterable;)V
  #106 = Utf8               scala/collection/Iterable
  #107 = Class              #106          // scala/collection/Iterable
  #108 = Utf8               (Lscala/collection/convert/AsScalaConverters;Ljava/util/Collection;)Lscala/collection/Iterable;
  #109 = Utf8               c
  #110 = Utf8               (Ljava/util/Collection;)Lscala/collection/Iterable;
  #111 = NameAndType        #66:#110      // asScala:(Ljava/util/Collection;)Lscala/collection/Iterable;
  #112 = InterfaceMethodref #2.#111       // scala/collection/convert/AsScalaConverters.asScala:(Ljava/util/Collection;)Lscala/collection/Iterable;
  #113 = Utf8               Ljava/util/Collection;
  #114 = Utf8               <A:Ljava/lang/Object;>(Ljava/util/Collection<TA;>;)Lscala/collection/Iterable<TA;>;
  #115 = Utf8               (Ljava/util/Collection;)V
  #116 = NameAndType        #77:#115      // "<init>":(Ljava/util/Collection;)V
  #117 = Methodref          #24.#116      // scala/collection/convert/JavaCollectionWrappers$JCollectionWrapper."<init>":(Ljava/util/Collection;)V
  #118 = Utf8               (Lscala/collection/convert/AsScalaConverters;Ljava/util/List;)Lscala/collection/mutable/Buffer;
  #119 = Utf8               l
  #120 = Utf8               (Ljava/util/List;)Lscala/collection/mutable/Buffer;
  #121 = NameAndType        #66:#120      // asScala:(Ljava/util/List;)Lscala/collection/mutable/Buffer;
  #122 = InterfaceMethodref #2.#121       // scala/collection/convert/AsScalaConverters.asScala:(Ljava/util/List;)Lscala/collection/mutable/Buffer;
  #123 = Utf8               Ljava/util/List;
  #124 = Utf8               <A:Ljava/lang/Object;>(Ljava/util/List<TA;>;)Lscala/collection/mutable/Buffer<TA;>;
  #125 = Utf8               ()Lscala/collection/mutable/Buffer;
  #126 = NameAndType        #73:#125      // underlying:()Lscala/collection/mutable/Buffer;
  #127 = Methodref          #54.#126      // scala/collection/convert/JavaCollectionWrappers$MutableBufferWrapper.underlying:()Lscala/collection/mutable/Buffer;
  #128 = Utf8               (Ljava/util/List;)V
  #129 = NameAndType        #77:#128      // "<init>":(Ljava/util/List;)V
  #130 = Methodref          #42.#129      // scala/collection/convert/JavaCollectionWrappers$JListWrapper."<init>":(Ljava/util/List;)V
  #131 = Utf8               scala/collection/mutable/Buffer
  #132 = Class              #131          // scala/collection/mutable/Buffer
  #133 = Utf8               (Lscala/collection/convert/AsScalaConverters;Ljava/util/Set;)Lscala/collection/mutable/Set;
  #134 = Utf8               s
  #135 = Utf8               (Ljava/util/Set;)Lscala/collection/mutable/Set;
  #136 = NameAndType        #66:#135      // asScala:(Ljava/util/Set;)Lscala/collection/mutable/Set;
  #137 = InterfaceMethodref #2.#136       // scala/collection/convert/AsScalaConverters.asScala:(Ljava/util/Set;)Lscala/collection/mutable/Set;
  #138 = Utf8               Ljava/util/Set;
  #139 = Utf8               <A:Ljava/lang/Object;>(Ljava/util/Set<TA;>;)Lscala/collection/mutable/Set<TA;>;
  #140 = Utf8               ()Lscala/collection/mutable/Set;
  #141 = NameAndType        #73:#140      // underlying:()Lscala/collection/mutable/Set;
  #142 = Methodref          #60.#141      // scala/collection/convert/JavaCollectionWrappers$MutableSetWrapper.underlying:()Lscala/collection/mutable/Set;
  #143 = Utf8               (Ljava/util/Set;)V
  #144 = NameAndType        #77:#143      // "<init>":(Ljava/util/Set;)V
  #145 = Methodref          #51.#144      // scala/collection/convert/JavaCollectionWrappers$JSetWrapper."<init>":(Ljava/util/Set;)V
  #146 = Utf8               scala/collection/mutable/Set
  #147 = Class              #146          // scala/collection/mutable/Set
  #148 = Utf8               (Lscala/collection/convert/AsScalaConverters;Ljava/util/Map;)Lscala/collection/mutable/Map;
  #149 = Utf8               m
  #150 = Utf8               (Ljava/util/Map;)Lscala/collection/mutable/Map;
  #151 = NameAndType        #66:#150      // asScala:(Ljava/util/Map;)Lscala/collection/mutable/Map;
  #152 = InterfaceMethodref #2.#151       // scala/collection/convert/AsScalaConverters.asScala:(Ljava/util/Map;)Lscala/collection/mutable/Map;
  #153 = Utf8               Ljava/util/Map;
  #154 = Utf8               <A:Ljava/lang/Object;B:Ljava/lang/Object;>(Ljava/util/Map<TA;TB;>;)Lscala/collection/mutable/Map<TA;TB;>;
  #155 = Utf8               ()Lscala/collection/mutable/Map;
  #156 = NameAndType        #73:#155      // underlying:()Lscala/collection/mutable/Map;
  #157 = Methodref          #57.#156      // scala/collection/convert/JavaCollectionWrappers$MutableMapWrapper.underlying:()Lscala/collection/mutable/Map;
  #158 = Utf8               (Ljava/util/Map;)V
  #159 = NameAndType        #77:#158      // "<init>":(Ljava/util/Map;)V
  #160 = Methodref          #45.#159      // scala/collection/convert/JavaCollectionWrappers$JMapWrapper."<init>":(Ljava/util/Map;)V
  #161 = Utf8               scala/collection/mutable/Map
  #162 = Class              #161          // scala/collection/mutable/Map
  #163 = Utf8               (Lscala/collection/convert/AsScalaConverters;Ljava/util/concurrent/ConcurrentMap;)Lscala/collection/concurrent/Map;
  #164 = Utf8               (Ljava/util/concurrent/ConcurrentMap;)Lscala/collection/concurrent/Map;
  #165 = NameAndType        #66:#164      // asScala:(Ljava/util/concurrent/ConcurrentMap;)Lscala/collection/concurrent/Map;
  #166 = InterfaceMethodref #2.#165       // scala/collection/convert/AsScalaConverters.asScala:(Ljava/util/concurrent/ConcurrentMap;)Lscala/collection/concurrent/Map;
  #167 = Utf8               Ljava/util/concurrent/ConcurrentMap;
  #168 = Utf8               <A:Ljava/lang/Object;B:Ljava/lang/Object;>(Ljava/util/concurrent/ConcurrentMap<TA;TB;>;)Lscala/collection/concurrent/Map<TA;TB;>;
  #169 = Utf8               ()Lscala/collection/concurrent/Map;
  #170 = NameAndType        #73:#169      // underlying:()Lscala/collection/concurrent/Map;
  #171 = Methodref          #10.#170      // scala/collection/convert/JavaCollectionWrappers$ConcurrentMapWrapper.underlying:()Lscala/collection/concurrent/Map;
  #172 = Utf8               (Ljava/util/concurrent/ConcurrentMap;)V
  #173 = NameAndType        #77:#172      // "<init>":(Ljava/util/concurrent/ConcurrentMap;)V
  #174 = Methodref          #27.#173      // scala/collection/convert/JavaCollectionWrappers$JConcurrentMapWrapper."<init>":(Ljava/util/concurrent/ConcurrentMap;)V
  #175 = Utf8               scala/collection/concurrent/Map
  #176 = Class              #175          // scala/collection/concurrent/Map
  #177 = Utf8               (Lscala/collection/convert/AsScalaConverters;Ljava/util/Dictionary;)Lscala/collection/mutable/Map;
  #178 = Utf8               d
  #179 = Utf8               (Ljava/util/Dictionary;)Lscala/collection/mutable/Map;
  #180 = NameAndType        #66:#179      // asScala:(Ljava/util/Dictionary;)Lscala/collection/mutable/Map;
  #181 = InterfaceMethodref #2.#180       // scala/collection/convert/AsScalaConverters.asScala:(Ljava/util/Dictionary;)Lscala/collection/mutable/Map;
  #182 = Utf8               Ljava/util/Dictionary;
  #183 = Utf8               <A:Ljava/lang/Object;B:Ljava/lang/Object;>(Ljava/util/Dictionary<TA;TB;>;)Lscala/collection/mutable/Map<TA;TB;>;
  #184 = Methodref          #15.#156      // scala/collection/convert/JavaCollectionWrappers$DictionaryWrapper.underlying:()Lscala/collection/mutable/Map;
  #185 = Utf8               (Ljava/util/Dictionary;)V
  #186 = NameAndType        #77:#185      // "<init>":(Ljava/util/Dictionary;)V
  #187 = Methodref          #30.#186      // scala/collection/convert/JavaCollectionWrappers$JDictionaryWrapper."<init>":(Ljava/util/Dictionary;)V
  #188 = Utf8               (Lscala/collection/convert/AsScalaConverters;Ljava/util/Properties;)Lscala/collection/mutable/Map;
  #189 = Utf8               p
  #190 = Utf8               (Ljava/util/Properties;)Lscala/collection/mutable/Map;
  #191 = NameAndType        #66:#190      // asScala:(Ljava/util/Properties;)Lscala/collection/mutable/Map;
  #192 = InterfaceMethodref #2.#191       // scala/collection/convert/AsScalaConverters.asScala:(Ljava/util/Properties;)Lscala/collection/mutable/Map;
  #193 = Utf8               Ljava/util/Properties;
  #194 = Utf8               (Ljava/util/Properties;)Lscala/collection/mutable/Map<Ljava/lang/String;Ljava/lang/String;>;
  #195 = Utf8               (Ljava/util/Properties;)V
  #196 = NameAndType        #77:#195      // "<init>":(Ljava/util/Properties;)V
  #197 = Methodref          #48.#196      // scala/collection/convert/JavaCollectionWrappers$JPropertiesWrapper."<init>":(Ljava/util/Properties;)V
  #198 = Utf8               $init$
  #199 = Utf8               (Lscala/collection/convert/AsScalaConverters;)V
  #200 = Utf8               Code
  #201 = Utf8               LineNumberTable
  #202 = Utf8               LocalVariableTable
  #203 = Utf8               MethodParameters
  #204 = Utf8               StackMapTable
  #205 = Utf8               Signature
  #206 = Utf8               InnerClasses
  #207 = Utf8               SourceFile
  #208 = Utf8               RuntimeVisibleAnnotations
  #209 = Utf8               ScalaInlineInfo
  #210 = Utf8               ScalaSig
{
  public static scala.collection.Iterator asScala$(scala.collection.convert.AsScalaConverters, java.util.Iterator);
    descriptor: (Lscala/collection/convert/AsScalaConverters;Ljava/util/Iterator;)Lscala/collection/Iterator;
    flags: (0x1009) ACC_PUBLIC, ACC_STATIC, ACC_SYNTHETIC
    Code:
      stack=2, locals=2, args_size=2
         0: aload_0
         1: aload_1
         2: invokespecial #69                 // InterfaceMethod asScala:(Ljava/util/Iterator;)Lscala/collection/Iterator;
         5: areturn
      LineNumberTable:
        line 38: 0
      LocalVariableTable:
        Start  Length  Slot  Name   Signature
            0       6     0 $this   Lscala/collection/convert/AsScalaConverters;
            0       6     1     i   Ljava/util/Iterator;
    MethodParameters:
      Name                           Flags
      $this                          final synthetic
      i                              final

  public default <A extends java.lang.Object> scala.collection.Iterator<A> asScala(java.util.Iterator<A>);
    descriptor: (Ljava/util/Iterator;)Lscala/collection/Iterator;
    flags: (0x0001) ACC_PUBLIC
    Code:
      stack=3, locals=3, args_size=2
         0: aload_1
         1: ifnonnull     9
         4: aconst_null
         5: astore_2
         6: goto          36
         9: aload_1
        10: instanceof    #21                 // class scala/collection/convert/JavaCollectionWrappers$IteratorWrapper
        13: ifeq          27
        16: aload_1
        17: checkcast     #21                 // class scala/collection/convert/JavaCollectionWrappers$IteratorWrapper
        20: invokevirtual #76                 // Method scala/collection/convert/JavaCollectionWrappers$IteratorWrapper.underlying:()Lscala/collection/Iterator;
        23: astore_2
        24: goto          36
        27: new           #39                 // class scala/collection/convert/JavaCollectionWrappers$JIteratorWrapper
        30: dup
        31: aload_1
        32: invokespecial #80                 // Method scala/collection/convert/JavaCollectionWrappers$JIteratorWrapper."<init>":(Ljava/util/Iterator;)V
        35: astore_2
        36: aload_2
        37: areturn
      StackMapTable: number_of_entries = 3
        frame_type = 9 /* same */
        frame_type = 17 /* same */
        frame_type = 252 /* append */
          offset_delta = 8
          locals = [ class scala/collection/Iterator ]
      LineNumberTable:
        line 39: 0
        line 40: 9
        line 41: 27
        line 38: 36
      LocalVariableTable:
        Start  Length  Slot  Name   Signature
            0      38     0  this   Lscala/collection/convert/AsScalaConverters;
            0      38     1     i   Ljava/util/Iterator;
    Signature: #72                          // <A:Ljava/lang/Object;>(Ljava/util/Iterator<TA;>;)Lscala/collection/Iterator<TA;>;
    MethodParameters:
      Name                           Flags
      i                              final

  public static scala.collection.Iterator asScala$(scala.collection.convert.AsScalaConverters, java.util.Enumeration);
    descriptor: (Lscala/collection/convert/AsScalaConverters;Ljava/util/Enumeration;)Lscala/collection/Iterator;
    flags: (0x1009) ACC_PUBLIC, ACC_STATIC, ACC_SYNTHETIC
    Code:
      stack=2, locals=2, args_size=2
         0: aload_0
         1: aload_1
         2: invokespecial #88                 // InterfaceMethod asScala:(Ljava/util/Enumeration;)Lscala/collection/Iterator;
         5: areturn
      LineNumberTable:
        line 56: 0
      LocalVariableTable:
        Start  Length  Slot  Name   Signature
            0       6     0 $this   Lscala/collection/convert/AsScalaConverters;
            0       6     1     e   Ljava/util/Enumeration;
    MethodParameters:
      Name                           Flags
      $this                          final synthetic
      e                              final

  public default <A extends java.lang.Object> scala.collection.Iterator<A> asScala(java.util.Enumeration<A>);
    descriptor: (Ljava/util/Enumeration;)Lscala/collection/Iterator;
    flags: (0x0001) ACC_PUBLIC
    Code:
      stack=3, locals=3, args_size=2
         0: aload_1
         1: ifnonnull     9
         4: aconst_null
         5: astore_2
         6: goto          36
         9: aload_1
        10: instanceof    #21                 // class scala/collection/convert/JavaCollectionWrappers$IteratorWrapper
        13: ifeq          27
        16: aload_1
        17: checkcast     #21                 // class scala/collection/convert/JavaCollectionWrappers$IteratorWrapper
        20: invokevirtual #76                 // Method scala/collection/convert/JavaCollectionWrappers$IteratorWrapper.underlying:()Lscala/collection/Iterator;
        23: astore_2
        24: goto          36
        27: new           #33                 // class scala/collection/convert/JavaCollectionWrappers$JEnumerationWrapper
        30: dup
        31: aload_1
        32: invokespecial #93                 // Method scala/collection/convert/JavaCollectionWrappers$JEnumerationWrapper."<init>":(Ljava/util/Enumeration;)V
        35: astore_2
        36: aload_2
        37: areturn
      StackMapTable: number_of_entries = 3
        frame_type = 9 /* same */
        frame_type = 17 /* same */
        frame_type = 252 /* append */
          offset_delta = 8
          locals = [ class scala/collection/Iterator ]
      LineNumberTable:
        line 57: 0
        line 58: 9
        line 59: 27
        line 56: 36
      LocalVariableTable:
        Start  Length  Slot  Name   Signature
            0      38     0  this   Lscala/collection/convert/AsScalaConverters;
            0      38     1     e   Ljava/util/Enumeration;
    Signature: #90                          // <A:Ljava/lang/Object;>(Ljava/util/Enumeration<TA;>;)Lscala/collection/Iterator<TA;>;
    MethodParameters:
      Name                           Flags
      e                              final

  public static scala.collection.Iterable asScala$(scala.collection.convert.AsScalaConverters, java.lang.Iterable);
    descriptor: (Lscala/collection/convert/AsScalaConverters;Ljava/lang/Iterable;)Lscala/collection/Iterable;
    flags: (0x1009) ACC_PUBLIC, ACC_STATIC, ACC_SYNTHETIC
    Code:
      stack=2, locals=2, args_size=2
         0: aload_0
         1: aload_1
         2: invokespecial #97                 // InterfaceMethod asScala:(Ljava/lang/Iterable;)Lscala/collection/Iterable;
         5: areturn
      LineNumberTable:
        line 74: 0
      LocalVariableTable:
        Start  Length  Slot  Name   Signature
            0       6     0 $this   Lscala/collection/convert/AsScalaConverters;
            0       6     1     i   Ljava/lang/Iterable;
    MethodParameters:
      Name                           Flags
      $this                          final synthetic
      i                              final

  public default <A extends java.lang.Object> scala.collection.Iterable<A> asScala(java.lang.Iterable<A>);
    descriptor: (Ljava/lang/Iterable;)Lscala/collection/Iterable;
    flags: (0x0001) ACC_PUBLIC
    Code:
      stack=3, locals=3, args_size=2
         0: aload_1
         1: ifnonnull     9
         4: aconst_null
         5: astore_2
         6: goto          36
         9: aload_1
        10: instanceof    #18                 // class scala/collection/convert/JavaCollectionWrappers$IterableWrapper
        13: ifeq          27
        16: aload_1
        17: checkcast     #18                 // class scala/collection/convert/JavaCollectionWrappers$IterableWrapper
        20: invokevirtual #102                // Method scala/collection/convert/JavaCollectionWrappers$IterableWrapper.underlying:()Lscala/collection/Iterable;
        23: astore_2
        24: goto          36
        27: new           #36                 // class scala/collection/convert/JavaCollectionWrappers$JIterableWrapper
        30: dup
        31: aload_1
        32: invokespecial #105                // Method scala/collection/convert/JavaCollectionWrappers$JIterableWrapper."<init>":(Ljava/lang/Iterable;)V
        35: astore_2
        36: aload_2
        37: areturn
      StackMapTable: number_of_entries = 3
        frame_type = 9 /* same */
        frame_type = 17 /* same */
        frame_type = 252 /* append */
          offset_delta = 8
          locals = [ class scala/collection/Iterable ]
      LineNumberTable:
        line 75: 0
        line 76: 9
        line 77: 27
        line 74: 36
      LocalVariableTable:
        Start  Length  Slot  Name   Signature
            0      38     0  this   Lscala/collection/convert/AsScalaConverters;
            0      38     1     i   Ljava/lang/Iterable;
    Signature: #99                          // <A:Ljava/lang/Object;>(Ljava/lang/Iterable<TA;>;)Lscala/collection/Iterable<TA;>;
    MethodParameters:
      Name                           Flags
      i                              final

  public static scala.collection.Iterable asScala$(scala.collection.convert.AsScalaConverters, java.util.Collection);
    descriptor: (Lscala/collection/convert/AsScalaConverters;Ljava/util/Collection;)Lscala/collection/Iterable;
    flags: (0x1009) ACC_PUBLIC, ACC_STATIC, ACC_SYNTHETIC
    Code:
      stack=2, locals=2, args_size=2
         0: aload_0
         1: aload_1
         2: invokespecial #112                // InterfaceMethod asScala:(Ljava/util/Collection;)Lscala/collection/Iterable;
         5: areturn
      LineNumberTable:
        line 89: 0
      LocalVariableTable:
        Start  Length  Slot  Name   Signature
            0       6     0 $this   Lscala/collection/convert/AsScalaConverters;
            0       6     1     c   Ljava/util/Collection;
    MethodParameters:
      Name                           Flags
      $this                          final synthetic
      c                              final

  public default <A extends java.lang.Object> scala.collection.Iterable<A> asScala(java.util.Collection<A>);
    descriptor: (Ljava/util/Collection;)Lscala/collection/Iterable;
    flags: (0x0001) ACC_PUBLIC
    Code:
      stack=3, locals=3, args_size=2
         0: aload_1
         1: ifnonnull     9
         4: aconst_null
         5: astore_2
         6: goto          36
         9: aload_1
        10: instanceof    #18                 // class scala/collection/convert/JavaCollectionWrappers$IterableWrapper
        13: ifeq          27
        16: aload_1
        17: checkcast     #18                 // class scala/collection/convert/JavaCollectionWrappers$IterableWrapper
        20: invokevirtual #102                // Method scala/collection/convert/JavaCollectionWrappers$IterableWrapper.underlying:()Lscala/collection/Iterable;
        23: astore_2
        24: goto          36
        27: new           #24                 // class scala/collection/convert/JavaCollectionWrappers$JCollectionWrapper
        30: dup
        31: aload_1
        32: invokespecial #117                // Method scala/collection/convert/JavaCollectionWrappers$JCollectionWrapper."<init>":(Ljava/util/Collection;)V
        35: astore_2
        36: aload_2
        37: areturn
      StackMapTable: number_of_entries = 3
        frame_type = 9 /* same */
        frame_type = 17 /* same */
        frame_type = 252 /* append */
          offset_delta = 8
          locals = [ class scala/collection/Iterable ]
      LineNumberTable:
        line 90: 0
        line 91: 9
        line 92: 27
        line 89: 36
      LocalVariableTable:
        Start  Length  Slot  Name   Signature
            0      38     0  this   Lscala/collection/convert/AsScalaConverters;
            0      38     1     c   Ljava/util/Collection;
    Signature: #114                         // <A:Ljava/lang/Object;>(Ljava/util/Collection<TA;>;)Lscala/collection/Iterable<TA;>;
    MethodParameters:
      Name                           Flags
      c                              final

  public static scala.collection.mutable.Buffer asScala$(scala.collection.convert.AsScalaConverters, java.util.List);
    descriptor: (Lscala/collection/convert/AsScalaConverters;Ljava/util/List;)Lscala/collection/mutable/Buffer;
    flags: (0x1009) ACC_PUBLIC, ACC_STATIC, ACC_SYNTHETIC
    Code:
      stack=2, locals=2, args_size=2
         0: aload_0
         1: aload_1
         2: invokespecial #122                // InterfaceMethod asScala:(Ljava/util/List;)Lscala/collection/mutable/Buffer;
         5: areturn
      LineNumberTable:
        line 107: 0
      LocalVariableTable:
        Start  Length  Slot  Name   Signature
            0       6     0 $this   Lscala/collection/convert/AsScalaConverters;
            0       6     1     l   Ljava/util/List;
    MethodParameters:
      Name                           Flags
      $this                          final synthetic
      l                              final

  public default <A extends java.lang.Object> scala.collection.mutable.Buffer<A> asScala(java.util.List<A>);
    descriptor: (Ljava/util/List;)Lscala/collection/mutable/Buffer;
    flags: (0x0001) ACC_PUBLIC
    Code:
      stack=3, locals=3, args_size=2
         0: aload_1
         1: ifnonnull     9
         4: aconst_null
         5: astore_2
         6: goto          36
         9: aload_1
        10: instanceof    #54                 // class scala/collection/convert/JavaCollectionWrappers$MutableBufferWrapper
        13: ifeq          27
        16: aload_1
        17: checkcast     #54                 // class scala/collection/convert/JavaCollectionWrappers$MutableBufferWrapper
        20: invokevirtual #127                // Method scala/collection/convert/JavaCollectionWrappers$MutableBufferWrapper.underlying:()Lscala/collection/mutable/Buffer;
        23: astore_2
        24: goto          36
        27: new           #42                 // class scala/collection/convert/JavaCollectionWrappers$JListWrapper
        30: dup
        31: aload_1
        32: invokespecial #130                // Method scala/collection/convert/JavaCollectionWrappers$JListWrapper."<init>":(Ljava/util/List;)V
        35: astore_2
        36: aload_2
        37: areturn
      StackMapTable: number_of_entries = 3
        frame_type = 9 /* same */
        frame_type = 17 /* same */
        frame_type = 252 /* append */
          offset_delta = 8
          locals = [ class scala/collection/mutable/Buffer ]
      LineNumberTable:
        line 108: 0
        line 109: 9
        line 110: 27
        line 107: 36
      LocalVariableTable:
        Start  Length  Slot  Name   Signature
            0      38     0  this   Lscala/collection/convert/AsScalaConverters;
            0      38     1     l   Ljava/util/List;
    Signature: #124                         // <A:Ljava/lang/Object;>(Ljava/util/List<TA;>;)Lscala/collection/mutable/Buffer<TA;>;
    MethodParameters:
      Name                           Flags
      l                              final

  public static scala.collection.mutable.Set asScala$(scala.collection.convert.AsScalaConverters, java.util.Set);
    descriptor: (Lscala/collection/convert/AsScalaConverters;Ljava/util/Set;)Lscala/collection/mutable/Set;
    flags: (0x1009) ACC_PUBLIC, ACC_STATIC, ACC_SYNTHETIC
    Code:
      stack=2, locals=2, args_size=2
         0: aload_0
         1: aload_1
         2: invokespecial #137                // InterfaceMethod asScala:(Ljava/util/Set;)Lscala/collection/mutable/Set;
         5: areturn
      LineNumberTable:
        line 125: 0
      LocalVariableTable:
        Start  Length  Slot  Name   Signature
            0       6     0 $this   Lscala/collection/convert/AsScalaConverters;
            0       6     1     s   Ljava/util/Set;
    MethodParameters:
      Name                           Flags
      $this                          final synthetic
      s                              final

  public default <A extends java.lang.Object> scala.collection.mutable.Set<A> asScala(java.util.Set<A>);
    descriptor: (Ljava/util/Set;)Lscala/collection/mutable/Set;
    flags: (0x0001) ACC_PUBLIC
    Code:
      stack=3, locals=3, args_size=2
         0: aload_1
         1: ifnonnull     9
         4: aconst_null
         5: astore_2
         6: goto          36
         9: aload_1
        10: instanceof    #60                 // class scala/collection/convert/JavaCollectionWrappers$MutableSetWrapper
        13: ifeq          27
        16: aload_1
        17: checkcast     #60                 // class scala/collection/convert/JavaCollectionWrappers$MutableSetWrapper
        20: invokevirtual #142                // Method scala/collection/convert/JavaCollectionWrappers$MutableSetWrapper.underlying:()Lscala/collection/mutable/Set;
        23: astore_2
        24: goto          36
        27: new           #51                 // class scala/collection/convert/JavaCollectionWrappers$JSetWrapper
        30: dup
        31: aload_1
        32: invokespecial #145                // Method scala/collection/convert/JavaCollectionWrappers$JSetWrapper."<init>":(Ljava/util/Set;)V
        35: astore_2
        36: aload_2
        37: areturn
      StackMapTable: number_of_entries = 3
        frame_type = 9 /* same */
        frame_type = 17 /* same */
        frame_type = 252 /* append */
          offset_delta = 8
          locals = [ class scala/collection/mutable/Set ]
      LineNumberTable:
        line 126: 0
        line 127: 9
        line 128: 27
        line 125: 36
      LocalVariableTable:
        Start  Length  Slot  Name   Signature
            0      38     0  this   Lscala/collection/convert/AsScalaConverters;
            0      38     1     s   Ljava/util/Set;
    Signature: #139                         // <A:Ljava/lang/Object;>(Ljava/util/Set<TA;>;)Lscala/collection/mutable/Set<TA;>;
    MethodParameters:
      Name                           Flags
      s                              final

  public static scala.collection.mutable.Map asScala$(scala.collection.convert.AsScalaConverters, java.util.Map);
    descriptor: (Lscala/collection/convert/AsScalaConverters;Ljava/util/Map;)Lscala/collection/mutable/Map;
    flags: (0x1009) ACC_PUBLIC, ACC_STATIC, ACC_SYNTHETIC
    Code:
      stack=2, locals=2, args_size=2
         0: aload_0
         1: aload_1
         2: invokespecial #152                // InterfaceMethod asScala:(Ljava/util/Map;)Lscala/collection/mutable/Map;
         5: areturn
      LineNumberTable:
        line 148: 0
      LocalVariableTable:
        Start  Length  Slot  Name   Signature
            0       6     0 $this   Lscala/collection/convert/AsScalaConverters;
            0       6     1     m   Ljava/util/Map;
    MethodParameters:
      Name                           Flags
      $this                          final synthetic
      m                              final

  public default <A extends java.lang.Object, B extends java.lang.Object> scala.collection.mutable.Map<A, B> asScala(java.util.Map<A, B>);
    descriptor: (Ljava/util/Map;)Lscala/collection/mutable/Map;
    flags: (0x0001) ACC_PUBLIC
    Code:
      stack=3, locals=3, args_size=2
         0: aload_1
         1: ifnonnull     9
         4: aconst_null
         5: astore_2
         6: goto          36
         9: aload_1
        10: instanceof    #57                 // class scala/collection/convert/JavaCollectionWrappers$MutableMapWrapper
        13: ifeq          27
        16: aload_1
        17: checkcast     #57                 // class scala/collection/convert/JavaCollectionWrappers$MutableMapWrapper
        20: invokevirtual #157                // Method scala/collection/convert/JavaCollectionWrappers$MutableMapWrapper.underlying:()Lscala/collection/mutable/Map;
        23: astore_2
        24: goto          36
        27: new           #45                 // class scala/collection/convert/JavaCollectionWrappers$JMapWrapper
        30: dup
        31: aload_1
        32: invokespecial #160                // Method scala/collection/convert/JavaCollectionWrappers$JMapWrapper."<init>":(Ljava/util/Map;)V
        35: astore_2
        36: aload_2
        37: areturn
      StackMapTable: number_of_entries = 3
        frame_type = 9 /* same */
        frame_type = 17 /* same */
        frame_type = 252 /* append */
          offset_delta = 8
          locals = [ class scala/collection/mutable/Map ]
      LineNumberTable:
        line 149: 0
        line 150: 9
        line 151: 27
        line 148: 36
      LocalVariableTable:
        Start  Length  Slot  Name   Signature
            0      38     0  this   Lscala/collection/convert/AsScalaConverters;
            0      38     1     m   Ljava/util/Map;
    Signature: #154                         // <A:Ljava/lang/Object;B:Ljava/lang/Object;>(Ljava/util/Map<TA;TB;>;)Lscala/collection/mutable/Map<TA;TB;>;
    MethodParameters:
      Name                           Flags
      m                              final

  public static scala.collection.concurrent.Map asScala$(scala.collection.convert.AsScalaConverters, java.util.concurrent.ConcurrentMap);
    descriptor: (Lscala/collection/convert/AsScalaConverters;Ljava/util/concurrent/ConcurrentMap;)Lscala/collection/concurrent/Map;
    flags: (0x1009) ACC_PUBLIC, ACC_STATIC, ACC_SYNTHETIC
    Code:
      stack=2, locals=2, args_size=2
         0: aload_0
         1: aload_1
         2: invokespecial #166                // InterfaceMethod asScala:(Ljava/util/concurrent/ConcurrentMap;)Lscala/collection/concurrent/Map;
         5: areturn
      LineNumberTable:
        line 167: 0
      LocalVariableTable:
        Start  Length  Slot  Name   Signature
            0       6     0 $this   Lscala/collection/convert/AsScalaConverters;
            0       6     1     m   Ljava/util/concurrent/ConcurrentMap;
    MethodParameters:
      Name                           Flags
      $this                          final synthetic
      m                              final

  public default <A extends java.lang.Object, B extends java.lang.Object> scala.collection.concurrent.Map<A, B> asScala(java.util.concurrent.ConcurrentMap<A, B>);
    descriptor: (Ljava/util/concurrent/ConcurrentMap;)Lscala/collection/concurrent/Map;
    flags: (0x0001) ACC_PUBLIC
    Code:
      stack=3, locals=3, args_size=2
         0: aload_1
         1: ifnonnull     9
         4: aconst_null
         5: astore_2
         6: goto          36
         9: aload_1
        10: instanceof    #10                 // class scala/collection/convert/JavaCollectionWrappers$ConcurrentMapWrapper
        13: ifeq          27
        16: aload_1
        17: checkcast     #10                 // class scala/collection/convert/JavaCollectionWrappers$ConcurrentMapWrapper
        20: invokevirtual #171                // Method scala/collection/convert/JavaCollectionWrappers$ConcurrentMapWrapper.underlying:()Lscala/collection/concurrent/Map;
        23: astore_2
        24: goto          36
        27: new           #27                 // class scala/collection/convert/JavaCollectionWrappers$JConcurrentMapWrapper
        30: dup
        31: aload_1
        32: invokespecial #174                // Method scala/collection/convert/JavaCollectionWrappers$JConcurrentMapWrapper."<init>":(Ljava/util/concurrent/ConcurrentMap;)V
        35: astore_2
        36: aload_2
        37: areturn
      StackMapTable: number_of_entries = 3
        frame_type = 9 /* same */
        frame_type = 17 /* same */
        frame_type = 252 /* append */
          offset_delta = 8
          locals = [ class scala/collection/concurrent/Map ]
      LineNumberTable:
        line 168: 0
        line 169: 9
        line 170: 27
        line 167: 36
      LocalVariableTable:
        Start  Length  Slot  Name   Signature
            0      38     0  this   Lscala/collection/convert/AsScalaConverters;
            0      38     1     m   Ljava/util/concurrent/ConcurrentMap;
    Signature: #168                         // <A:Ljava/lang/Object;B:Ljava/lang/Object;>(Ljava/util/concurrent/ConcurrentMap<TA;TB;>;)Lscala/collection/concurrent/Map<TA;TB;>;
    MethodParameters:
      Name                           Flags
      m                              final

  public static scala.collection.mutable.Map asScala$(scala.collection.convert.AsScalaConverters, java.util.Dictionary);
    descriptor: (Lscala/collection/convert/AsScalaConverters;Ljava/util/Dictionary;)Lscala/collection/mutable/Map;
    flags: (0x1009) ACC_PUBLIC, ACC_STATIC, ACC_SYNTHETIC
    Code:
      stack=2, locals=2, args_size=2
         0: aload_0
         1: aload_1
         2: invokespecial #181                // InterfaceMethod asScala:(Ljava/util/Dictionary;)Lscala/collection/mutable/Map;
         5: areturn
      LineNumberTable:
        line 185: 0
      LocalVariableTable:
        Start  Length  Slot  Name   Signature
            0       6     0 $this   Lscala/collection/convert/AsScalaConverters;
            0       6     1     d   Ljava/util/Dictionary;
    MethodParameters:
      Name                           Flags
      $this                          final synthetic
      d                              final

  public default <A extends java.lang.Object, B extends java.lang.Object> scala.collection.mutable.Map<A, B> asScala(java.util.Dictionary<A, B>);
    descriptor: (Ljava/util/Dictionary;)Lscala/collection/mutable/Map;
    flags: (0x0001) ACC_PUBLIC
    Code:
      stack=3, locals=3, args_size=2
         0: aload_1
         1: ifnonnull     9
         4: aconst_null
         5: astore_2
         6: goto          36
         9: aload_1
        10: instanceof    #15                 // class scala/collection/convert/JavaCollectionWrappers$DictionaryWrapper
        13: ifeq          27
        16: aload_1
        17: checkcast     #15                 // class scala/collection/convert/JavaCollectionWrappers$DictionaryWrapper
        20: invokevirtual #184                // Method scala/collection/convert/JavaCollectionWrappers$DictionaryWrapper.underlying:()Lscala/collection/mutable/Map;
        23: astore_2
        24: goto          36
        27: new           #30                 // class scala/collection/convert/JavaCollectionWrappers$JDictionaryWrapper
        30: dup
        31: aload_1
        32: invokespecial #187                // Method scala/collection/convert/JavaCollectionWrappers$JDictionaryWrapper."<init>":(Ljava/util/Dictionary;)V
        35: astore_2
        36: aload_2
        37: areturn
      StackMapTable: number_of_entries = 3
        frame_type = 9 /* same */
        frame_type = 17 /* same */
        frame_type = 252 /* append */
          offset_delta = 8
          locals = [ class scala/collection/mutable/Map ]
      LineNumberTable:
        line 186: 0
        line 187: 9
        line 188: 27
        line 185: 36
      LocalVariableTable:
        Start  Length  Slot  Name   Signature
            0      38     0  this   Lscala/collection/convert/AsScalaConverters;
            0      38     1     d   Ljava/util/Dictionary;
    Signature: #183                         // <A:Ljava/lang/Object;B:Ljava/lang/Object;>(Ljava/util/Dictionary<TA;TB;>;)Lscala/collection/mutable/Map<TA;TB;>;
    MethodParameters:
      Name                           Flags
      d                              final

  public static scala.collection.mutable.Map asScala$(scala.collection.convert.AsScalaConverters, java.util.Properties);
    descriptor: (Lscala/collection/convert/AsScalaConverters;Ljava/util/Properties;)Lscala/collection/mutable/Map;
    flags: (0x1009) ACC_PUBLIC, ACC_STATIC, ACC_SYNTHETIC
    Code:
      stack=2, locals=2, args_size=2
         0: aload_0
         1: aload_1
         2: invokespecial #192                // InterfaceMethod asScala:(Ljava/util/Properties;)Lscala/collection/mutable/Map;
         5: areturn
      LineNumberTable:
        line 201: 0
      LocalVariableTable:
        Start  Length  Slot  Name   Signature
            0       6     0 $this   Lscala/collection/convert/AsScalaConverters;
            0       6     1     p   Ljava/util/Properties;
    MethodParameters:
      Name                           Flags
      $this                          final synthetic
      p                              final

  public default scala.collection.mutable.Map<java.lang.String, java.lang.String> asScala(java.util.Properties);
    descriptor: (Ljava/util/Properties;)Lscala/collection/mutable/Map;
    flags: (0x0001) ACC_PUBLIC
    Code:
      stack=3, locals=3, args_size=2
         0: aload_1
         1: ifnonnull     9
         4: aconst_null
         5: astore_2
         6: goto          18
         9: new           #48                 // class scala/collection/convert/JavaCollectionWrappers$JPropertiesWrapper
        12: dup
        13: aload_1
        14: invokespecial #197                // Method scala/collection/convert/JavaCollectionWrappers$JPropertiesWrapper."<init>":(Ljava/util/Properties;)V
        17: astore_2
        18: aload_2
        19: areturn
      StackMapTable: number_of_entries = 2
        frame_type = 9 /* same */
        frame_type = 252 /* append */
          offset_delta = 8
          locals = [ class scala/collection/convert/JavaCollectionWrappers$JPropertiesWrapper ]
      LineNumberTable:
        line 202: 0
        line 203: 9
        line 201: 18
      LocalVariableTable:
        Start  Length  Slot  Name   Signature
            0      20     0  this   Lscala/collection/convert/AsScalaConverters;
            0      20     1     p   Ljava/util/Properties;
    Signature: #194                         // (Ljava/util/Properties;)Lscala/collection/mutable/Map<Ljava/lang/String;Ljava/lang/String;>;
    MethodParameters:
      Name                           Flags
      p                              final

  public static void $init$(scala.collection.convert.AsScalaConverters);
    descriptor: (Lscala/collection/convert/AsScalaConverters;)V
    flags: (0x0009) ACC_PUBLIC, ACC_STATIC
    Code:
      stack=0, locals=1, args_size=1
         0: return
      LineNumberTable:
        line 23: 0
      LocalVariableTable:
        Start  Length  Slot  Name   Signature
            0       1     0 $this   Lscala/collection/convert/AsScalaConverters;
    MethodParameters:
      Name                           Flags
      $this                          final synthetic
}
InnerClasses:
  public static #13= #10 of #12;          // ConcurrentMapWrapper=class scala/collection/convert/JavaCollectionWrappers$ConcurrentMapWrapper of class scala/collection/convert/JavaCollectionWrappers
  public static #16= #15 of #12;          // DictionaryWrapper=class scala/collection/convert/JavaCollectionWrappers$DictionaryWrapper of class scala/collection/convert/JavaCollectionWrappers
  public static #19= #18 of #12;          // IterableWrapper=class scala/collection/convert/JavaCollectionWrappers$IterableWrapper of class scala/collection/convert/JavaCollectionWrappers
  public static #22= #21 of #12;          // IteratorWrapper=class scala/collection/convert/JavaCollectionWrappers$IteratorWrapper of class scala/collection/convert/JavaCollectionWrappers
  public static #25= #24 of #12;          // JCollectionWrapper=class scala/collection/convert/JavaCollectionWrappers$JCollectionWrapper of class scala/collection/convert/JavaCollectionWrappers
  public static #28= #27 of #12;          // JConcurrentMapWrapper=class scala/collection/convert/JavaCollectionWrappers$JConcurrentMapWrapper of class scala/collection/convert/JavaCollectionWrappers
  public static #31= #30 of #12;          // JDictionaryWrapper=class scala/collection/convert/JavaCollectionWrappers$JDictionaryWrapper of class scala/collection/convert/JavaCollectionWrappers
  public static #34= #33 of #12;          // JEnumerationWrapper=class scala/collection/convert/JavaCollectionWrappers$JEnumerationWrapper of class scala/collection/convert/JavaCollectionWrappers
  public static #37= #36 of #12;          // JIterableWrapper=class scala/collection/convert/JavaCollectionWrappers$JIterableWrapper of class scala/collection/convert/JavaCollectionWrappers
  public static #40= #39 of #12;          // JIteratorWrapper=class scala/collection/convert/JavaCollectionWrappers$JIteratorWrapper of class scala/collection/convert/JavaCollectionWrappers
  public static #43= #42 of #12;          // JListWrapper=class scala/collection/convert/JavaCollectionWrappers$JListWrapper of class scala/collection/convert/JavaCollectionWrappers
  public static #46= #45 of #12;          // JMapWrapper=class scala/collection/convert/JavaCollectionWrappers$JMapWrapper of class scala/collection/convert/JavaCollectionWrappers
  public static #49= #48 of #12;          // JPropertiesWrapper=class scala/collection/convert/JavaCollectionWrappers$JPropertiesWrapper of class scala/collection/convert/JavaCollectionWrappers
  public static #52= #51 of #12;          // JSetWrapper=class scala/collection/convert/JavaCollectionWrappers$JSetWrapper of class scala/collection/convert/JavaCollectionWrappers
  public static #55= #54 of #12;          // MutableBufferWrapper=class scala/collection/convert/JavaCollectionWrappers$MutableBufferWrapper of class scala/collection/convert/JavaCollectionWrappers
  public static #58= #57 of #12;          // MutableMapWrapper=class scala/collection/convert/JavaCollectionWrappers$MutableMapWrapper of class scala/collection/convert/JavaCollectionWrappers
  public static #61= #60 of #12;          // MutableSetWrapper=class scala/collection/convert/JavaCollectionWrappers$MutableSetWrapper of class scala/collection/convert/JavaCollectionWrappers
SourceFile: "AsScalaConverters.scala"
RuntimeVisibleAnnotations:
  0: #6(#7=s#8)
    scala.reflect.ScalaSignature(
      bytes="\u0006\u0005\u0005\rda\u0002\u0007\u000e!\u0003\r\t\u0001\u0006\u0005\u00063\u0001!\tA\u0007\u0005\u0006=\u0001!\ta\b\u0005\u0006=\u0001!\t!\u000f\u0005\u0006=\u0001!\ta\u0011\u0005\u0006=\u0001!\t\u0001\u0015\u0005\u0006=\u0001!\tA\u0017\u0005\u0006=\u0001!\t!\u001b\u0005\u0006=\u0001!\t\u0001\u001e\u0005\u0007=\u0001!\t!!\u0002\t\ry\u0001A\u0011AA\u0014\u0011\u0019q\u0002\u0001\"\u0001\u0002@\t\t\u0012i]*dC2\f7i\u001c8wKJ$XM]:\u000b\u00059y\u0011aB2p]Z,\'\u000f\u001e\u0006\u0003!E\t!bY8mY\u0016\u001cG/[8o\u0015\u0005\u0011\u0012!B:dC2\f7\u0001A\n\u0003\u0001U\u0001\"AF\f\u000e\u0003EI!\u0001G\t\u0003\r\u0005s\u0017PU3g\u0003\u0019!\u0013N\\5uIQ\t1\u0004\u0005\u0002\u00179%\u0011Q$\u0005\u0002\u0005+:LG/A\u0004bgN\u001b\u0017\r\\1\u0016\u0005\u0001:CCA\u00111!\r\u00113%J\u0007\u0002\u001f%\u0011Ae\u0004\u0002\t\u0013R,\'/\u0019;peB\u0011ae\n\u0007\u0001\t\u0015A#A1\u0001*\u0005\u0005\t\u0015C\u0001\u0016.!\t12&\u0003\u0002-#\t9aj\u001c;iS:<\u0007C\u0001\f/\u0013\ty\u0013CA\u0002B]fDQ!\r\u0002A\u0002I\n\u0011!\u001b\t\u0004ga*S\"\u0001\u001b\u000b\u0005U2\u0014\u0001B;uS2T\u0011aN\u0001\u0005U\u00064\u0018-\u0003\u0002%iU\u0011!(\u0010\u000b\u0003wy\u00022AI\u0012=!\t1S\bB\u0003)\u0007\t\u0007\u0011\u0006C\u0003@\u0007\u0001\u0007\u0001)A\u0001f!\r\u0019\u0014\tP\u0005\u0003\u0005R\u00121\"\u00128v[\u0016\u0014\u0018\r^5p]V\u0011A)\u0013\u000b\u0003\u000b*\u00032A\t$I\u0013\t9uB\u0001\u0005Ji\u0016\u0014\u0018M\u00197f!\t1\u0013\nB\u0003)\t\t\u0007\u0011\u0006C\u00032\t\u0001\u00071\nE\u0002M\u001f\"k\u0011!\u0014\u0006\u0003\u001dZ\nA\u0001\\1oO&\u0011q)T\u000b\u0003#R#\"AU+\u0011\u0007\t25\u000b\u0005\u0002\')\u0012)\u0001&\u0002b\u0001S!)a+\u0002a\u0001/\u0006\t1\rE\u000241NK!!\u0017\u001b\u0003\u0015\r{G\u000e\\3di&|g.\u0006\u0002\\GR\u0011A\f\u001a\t\u0004;\u0002\u0014W\"\u00010\u000b\u0005}{\u0011aB7vi\u0006\u0014G.Z\u0005\u0003Cz\u0013aAQ;gM\u0016\u0014\bC\u0001\u0014d\t\u0015AcA1\u0001*\u0011\u0015)g\u00011\u0001g\u0003\u0005a\u0007cA\u001ahE&\u0011\u0001\u000e\u000e\u0002\u0005\u0019&\u001cH/\u0006\u0002k_R\u00111\u000e\u001d\t\u0004;2t\u0017BA7_\u0005\r\u0019V\r\u001e\t\u0003M=$Q\u0001K\u0004C\u0002%BQ!]\u0004A\u0002I\f\u0011a\u001d\t\u0004gMt\u0017BA75+\r)(\u0010 \u000b\u0003mz\u0004B!X<zw&\u0011\u0001P\u0018\u0002\u0004\u001b\u0006\u0004\bC\u0001\u0014{\t\u0015A\u0003B1\u0001*!\t1C\u0010B\u0003~\u0011\t\u0007\u0011FA\u0001C\u0011\u0019y\b\u00021\u0001\u0002\u0002\u0005\tQ\u000eE\u00034\u0003\u0007I80\u0003\u0002yiU1\u0011qAA\u000b\u00033!B!!\u0003\u0002\u001cAA\u00111BA\t\u0003\'\t9\"\u0004\u0002\u0002\u000e)\u0019\u0011qB\b\u0002\u0015\r|gnY;se\u0016tG/C\u0002y\u0003\u001b\u00012AJA\u000b\t\u0015A\u0013B1\u0001*!\r1\u0013\u0011\u0004\u0003\u0006{&\u0011\r!\u000b\u0005\u0007\u007f&\u0001\r!!\b\u0011\u0011\u0005}\u00111EA\n\u0003/i!!!\t\u000b\u0007\u0005=A\'\u0003\u0003\u0002&\u0005\u0005\"!D\"p]\u000e,(O]3oi6\u000b\u0007/\u0006\u0004\u0002*\u0005=\u00121\u0007\u000b\u0005\u0003W\t)\u0004\u0005\u0004^o\u00065\u0012\u0011\u0007\t\u0004M\u0005=B!\u0002\u0015\u000b\u0005\u0004I\u0003c\u0001\u0014\u00024\u0011)QP\u0003b\u0001S!9\u0011q\u0007\u0006A\u0002\u0005e\u0012!\u00013\u0011\u000fM\nY$!\f\u00022%\u0019\u0011Q\b\u001b\u0003\u0015\u0011K7\r^5p]\u0006\u0014\u0018\u0010\u0006\u0003\u0002B\u0005e\u0003CB/x\u0003\u0007\n\u0019\u0005\u0005\u0003\u0002F\u0005Mc\u0002BA$\u0003\u001f\u00022!!\u0013\u0012\u001b\t\tYEC\u0002\u0002NM\ta\u0001\u0010:p_Rt\u0014bAA)#\u00051\u0001K]3eK\u001aLA!!\u0016\u0002X\t11\u000b\u001e:j]\u001eT1!!\u0015\u0012\u0011\u001d\tYf\u0003a\u0001\u0003;\n\u0011\u0001\u001d\t\u0004g\u0005}\u0013bAA1i\tQ\u0001K]8qKJ$\u0018.Z:"
    )
  ScalaInlineInfo: length = 0x6D (unknown attribute)
   01 00 00 15 00 C6 00 C7 01 00 42 00 5F 00 00 42
   00 6E 00 00 42 00 B3 00 00 42 00 56 00 00 42 00
   43 00 00 42 00 78 00 00 42 00 96 00 00 42 00 BE
   00 00 42 00 87 00 00 42 00 A4 00 00 3E 00 5E 01
   00 3E 00 6C 01 00 3E 00 B1 01 00 3E 00 54 01 00
   3E 00 3F 01 00 3E 00 76 01 00 3E 00 94 01 00 3E
   00 BC 01 00 3E 00 85 01 00 3E 00 A3 01
  ScalaSig: length = 0x3 (unknown attribute)
   05 02 00
