Classfile /Users/mw/Projects/slang-braindump/.jar/jar8/assemble/slang-braindump/assemble/content/scala/collection/convert/JavaCollectionWrappers$JConcurrentMapWrapper$.class
  Last modified May 29, 2022; size 2228 bytes
  SHA-256 checksum 11d03098a1a50c45624aefbc5304cd5e2cc0625180eaf22d29c8fd4767be8f16
  Compiled from "JavaCollectionWrappers.scala"
public class scala.collection.convert.JavaCollectionWrappers$JConcurrentMapWrapper$ implements java.io.Serializable
  minor version: 0
  major version: 52
  flags: (0x0021) ACC_PUBLIC, ACC_SUPER
  this_class: #2                          // scala/collection/convert/JavaCollectionWrappers$JConcurrentMapWrapper$
  super_class: #4                         // java/lang/Object
  interfaces: 1, fields: 1, methods: 6, attributes: 4
Constant pool:
   #1 = Utf8               scala/collection/convert/JavaCollectionWrappers$JConcurrentMapWrapper$
   #2 = Class              #1             // scala/collection/convert/JavaCollectionWrappers$JConcurrentMapWrapper$
   #3 = Utf8               java/lang/Object
   #4 = Class              #3             // java/lang/Object
   #5 = Utf8               java/io/Serializable
   #6 = Class              #5             // java/io/Serializable
   #7 = Utf8               JavaCollectionWrappers.scala
   #8 = Utf8               scala/collection/convert/JavaCollectionWrappers$JConcurrentMapWrapper
   #9 = Class              #8             // scala/collection/convert/JavaCollectionWrappers$JConcurrentMapWrapper
  #10 = Utf8               scala/collection/convert/JavaCollectionWrappers
  #11 = Class              #10            // scala/collection/convert/JavaCollectionWrappers
  #12 = Utf8               JConcurrentMapWrapper
  #13 = Utf8               JConcurrentMapWrapper$
  #14 = Utf8               MODULE$
  #15 = Utf8               Lscala/collection/convert/JavaCollectionWrappers$JConcurrentMapWrapper$;
  #16 = Utf8               <clinit>
  #17 = Utf8               ()V
  #18 = Utf8               <init>
  #19 = NameAndType        #18:#17        // "<init>":()V
  #20 = Methodref          #2.#19         // scala/collection/convert/JavaCollectionWrappers$JConcurrentMapWrapper$."<init>":()V
  #21 = NameAndType        #14:#15        // MODULE$:Lscala/collection/convert/JavaCollectionWrappers$JConcurrentMapWrapper$;
  #22 = Fieldref           #2.#21         // scala/collection/convert/JavaCollectionWrappers$JConcurrentMapWrapper$.MODULE$:Lscala/collection/convert/JavaCollectionWrappers$JConcurrentMapWrapper$;
  #23 = Utf8               toString
  #24 = Utf8               ()Ljava/lang/String;
  #25 = String             #12            // JConcurrentMapWrapper
  #26 = Utf8               this
  #27 = Utf8               apply
  #28 = Utf8               (Ljava/util/concurrent/ConcurrentMap;)Lscala/collection/convert/JavaCollectionWrappers$JConcurrentMapWrapper;
  #29 = Utf8               <K:Ljava/lang/Object;V:Ljava/lang/Object;>(Ljava/util/concurrent/ConcurrentMap<TK;TV;>;)Lscala/collection/convert/JavaCollectionWrappers$JConcurrentMapWrapper<TK;TV;>;
  #30 = Utf8               underlying
  #31 = Utf8               (Ljava/util/concurrent/ConcurrentMap;)V
  #32 = NameAndType        #18:#31        // "<init>":(Ljava/util/concurrent/ConcurrentMap;)V
  #33 = Methodref          #9.#32         // scala/collection/convert/JavaCollectionWrappers$JConcurrentMapWrapper."<init>":(Ljava/util/concurrent/ConcurrentMap;)V
  #34 = Utf8               Ljava/util/concurrent/ConcurrentMap;
  #35 = Utf8               unapply
  #36 = Utf8               (Lscala/collection/convert/JavaCollectionWrappers$JConcurrentMapWrapper;)Lscala/Option;
  #37 = Utf8               <K:Ljava/lang/Object;V:Ljava/lang/Object;>(Lscala/collection/convert/JavaCollectionWrappers$JConcurrentMapWrapper<TK;TV;>;)Lscala/Option<Ljava/util/concurrent/ConcurrentMap<TK;TV;>;>;
  #38 = Utf8               x$0
  #39 = Utf8               scala/None$
  #40 = Class              #39            // scala/None$
  #41 = Utf8               Lscala/None$;
  #42 = NameAndType        #14:#41        // MODULE$:Lscala/None$;
  #43 = Fieldref           #40.#42        // scala/None$.MODULE$:Lscala/None$;
  #44 = Utf8               scala/Some
  #45 = Class              #44            // scala/Some
  #46 = Utf8               ()Ljava/util/concurrent/ConcurrentMap;
  #47 = NameAndType        #30:#46        // underlying:()Ljava/util/concurrent/ConcurrentMap;
  #48 = Methodref          #9.#47         // scala/collection/convert/JavaCollectionWrappers$JConcurrentMapWrapper.underlying:()Ljava/util/concurrent/ConcurrentMap;
  #49 = Utf8               (Ljava/lang/Object;)V
  #50 = NameAndType        #18:#49        // "<init>":(Ljava/lang/Object;)V
  #51 = Methodref          #45.#50        // scala/Some."<init>":(Ljava/lang/Object;)V
  #52 = Utf8               Lscala/collection/convert/JavaCollectionWrappers$JConcurrentMapWrapper;
  #53 = Utf8               writeReplace
  #54 = Utf8               ()Ljava/lang/Object;
  #55 = Utf8               scala/runtime/ModuleSerializationProxy
  #56 = Class              #55            // scala/runtime/ModuleSerializationProxy
  #57 = Utf8               (Ljava/lang/Class;)V
  #58 = NameAndType        #18:#57        // "<init>":(Ljava/lang/Class;)V
  #59 = Methodref          #56.#58        // scala/runtime/ModuleSerializationProxy."<init>":(Ljava/lang/Class;)V
  #60 = Methodref          #4.#19         // java/lang/Object."<init>":()V
  #61 = Utf8               Code
  #62 = Utf8               LineNumberTable
  #63 = Utf8               LocalVariableTable
  #64 = Utf8               Signature
  #65 = Utf8               MethodParameters
  #66 = Utf8               StackMapTable
  #67 = Utf8               InnerClasses
  #68 = Utf8               SourceFile
  #69 = Utf8               ScalaInlineInfo
  #70 = Utf8               Scala
{
  public static final scala.collection.convert.JavaCollectionWrappers$JConcurrentMapWrapper$ MODULE$;
    descriptor: Lscala/collection/convert/JavaCollectionWrappers$JConcurrentMapWrapper$;
    flags: (0x0019) ACC_PUBLIC, ACC_STATIC, ACC_FINAL

  public static {};
    descriptor: ()V
    flags: (0x0009) ACC_PUBLIC, ACC_STATIC
    Code:
      stack=2, locals=0, args_size=0
         0: new           #2                  // class scala/collection/convert/JavaCollectionWrappers$JConcurrentMapWrapper$
         3: dup
         4: invokespecial #20                 // Method "<init>":()V
         7: putstatic     #22                 // Field MODULE$:Lscala/collection/convert/JavaCollectionWrappers$JConcurrentMapWrapper$;
        10: return
      LineNumberTable:
        line 411: 0

  public final java.lang.String toString();
    descriptor: ()Ljava/lang/String;
    flags: (0x0011) ACC_PUBLIC, ACC_FINAL
    Code:
      stack=1, locals=1, args_size=1
         0: ldc           #25                 // String JConcurrentMapWrapper
         2: areturn
      LineNumberTable:
        line 411: 0
      LocalVariableTable:
        Start  Length  Slot  Name   Signature
            0       3     0  this   Lscala/collection/convert/JavaCollectionWrappers$JConcurrentMapWrapper$;

  public <K extends java.lang.Object, V extends java.lang.Object> scala.collection.convert.JavaCollectionWrappers$JConcurrentMapWrapper<K, V> apply(java.util.concurrent.ConcurrentMap<K, V>);
    descriptor: (Ljava/util/concurrent/ConcurrentMap;)Lscala/collection/convert/JavaCollectionWrappers$JConcurrentMapWrapper;
    flags: (0x0001) ACC_PUBLIC
    Code:
      stack=3, locals=2, args_size=2
         0: new           #9                  // class scala/collection/convert/JavaCollectionWrappers$JConcurrentMapWrapper
         3: dup
         4: aload_1
         5: invokespecial #33                 // Method scala/collection/convert/JavaCollectionWrappers$JConcurrentMapWrapper."<init>":(Ljava/util/concurrent/ConcurrentMap;)V
         8: areturn
      LineNumberTable:
        line 411: 0
      LocalVariableTable:
        Start  Length  Slot  Name   Signature
            0       9     0  this   Lscala/collection/convert/JavaCollectionWrappers$JConcurrentMapWrapper$;
            0       9     1 underlying   Ljava/util/concurrent/ConcurrentMap;
    Signature: #29                          // <K:Ljava/lang/Object;V:Ljava/lang/Object;>(Ljava/util/concurrent/ConcurrentMap<TK;TV;>;)Lscala/collection/convert/JavaCollectionWrappers$JConcurrentMapWrapper<TK;TV;>;
    MethodParameters:
      Name                           Flags
      underlying                     final

  public <K extends java.lang.Object, V extends java.lang.Object> scala.Option<java.util.concurrent.ConcurrentMap<K, V>> unapply(scala.collection.convert.JavaCollectionWrappers$JConcurrentMapWrapper<K, V>);
    descriptor: (Lscala/collection/convert/JavaCollectionWrappers$JConcurrentMapWrapper;)Lscala/Option;
    flags: (0x0001) ACC_PUBLIC
    Code:
      stack=3, locals=2, args_size=2
         0: aload_1
         1: ifnonnull     8
         4: getstatic     #43                 // Field scala/None$.MODULE$:Lscala/None$;
         7: areturn
         8: new           #45                 // class scala/Some
        11: dup
        12: aload_1
        13: invokevirtual #48                 // Method scala/collection/convert/JavaCollectionWrappers$JConcurrentMapWrapper.underlying:()Ljava/util/concurrent/ConcurrentMap;
        16: invokespecial #51                 // Method scala/Some."<init>":(Ljava/lang/Object;)V
        19: areturn
      StackMapTable: number_of_entries = 1
        frame_type = 8 /* same */
      LineNumberTable:
        line 411: 0
      LocalVariableTable:
        Start  Length  Slot  Name   Signature
            0      20     0  this   Lscala/collection/convert/JavaCollectionWrappers$JConcurrentMapWrapper$;
            0      20     1   x$0   Lscala/collection/convert/JavaCollectionWrappers$JConcurrentMapWrapper;
    Signature: #37                          // <K:Ljava/lang/Object;V:Ljava/lang/Object;>(Lscala/collection/convert/JavaCollectionWrappers$JConcurrentMapWrapper<TK;TV;>;)Lscala/Option<Ljava/util/concurrent/ConcurrentMap<TK;TV;>;>;
    MethodParameters:
      Name                           Flags
      x$0                            final

  private java.lang.Object writeReplace();
    descriptor: ()Ljava/lang/Object;
    flags: (0x0002) ACC_PRIVATE
    Code:
      stack=3, locals=1, args_size=1
         0: new           #56                 // class scala/runtime/ModuleSerializationProxy
         3: dup
         4: ldc           #2                  // class scala/collection/convert/JavaCollectionWrappers$JConcurrentMapWrapper$
         6: invokespecial #59                 // Method scala/runtime/ModuleSerializationProxy."<init>":(Ljava/lang/Class;)V
         9: areturn
      LineNumberTable:
        line 411: 0
      LocalVariableTable:
        Start  Length  Slot  Name   Signature
            0      10     0  this   Lscala/collection/convert/JavaCollectionWrappers$JConcurrentMapWrapper$;

  public scala.collection.convert.JavaCollectionWrappers$JConcurrentMapWrapper$();
    descriptor: ()V
    flags: (0x0001) ACC_PUBLIC
    Code:
      stack=1, locals=1, args_size=1
         0: aload_0
         1: invokespecial #60                 // Method java/lang/Object."<init>":()V
         4: return
      LineNumberTable:
        line 411: 0
      LocalVariableTable:
        Start  Length  Slot  Name   Signature
            0       5     0  this   Lscala/collection/convert/JavaCollectionWrappers$JConcurrentMapWrapper$;
}
InnerClasses:
  public static #12= #9 of #11;           // JConcurrentMapWrapper=class scala/collection/convert/JavaCollectionWrappers$JConcurrentMapWrapper of class scala/collection/convert/JavaCollectionWrappers
  public static #13= #2 of #11;           // JConcurrentMapWrapper$=class scala/collection/convert/JavaCollectionWrappers$JConcurrentMapWrapper$ of class scala/collection/convert/JavaCollectionWrappers
SourceFile: "JavaCollectionWrappers.scala"
  ScalaInlineInfo: length = 0x1D (unknown attribute)
   01 01 00 05 00 12 00 11 01 00 1B 00 1C 01 00 17
   00 18 01 00 23 00 24 01 00 35 00 36 01
  Scala: length = 0x0 (unknown attribute)

