Classfile /Users/mw/Projects/slang-braindump/.jar/jar11/assemble/slang-braindump/assemble/content/scala/xml/include/sax/EncodingHeuristics.class
  Last modified May 29, 2022; size 1431 bytes
  SHA-256 checksum 61ff947e37cd03b4134764a654e0451706c44b86e53d69ccb0700df7300ec9a2
  Compiled from "EncodingHeuristics.scala"
public final class scala.xml.include.sax.EncodingHeuristics
  minor version: 0
  major version: 52
  flags: (0x0031) ACC_PUBLIC, ACC_FINAL, ACC_SUPER
  this_class: #2                          // scala/xml/include/sax/EncodingHeuristics
  super_class: #4                         // java/lang/Object
  interfaces: 0, fields: 0, methods: 1, attributes: 4
Constant pool:
   #1 = Utf8               scala/xml/include/sax/EncodingHeuristics
   #2 = Class              #1             // scala/xml/include/sax/EncodingHeuristics
   #3 = Utf8               java/lang/Object
   #4 = Class              #3             // java/lang/Object
   #5 = Utf8               EncodingHeuristics.scala
   #6 = Utf8               Lscala/reflect/ScalaSignature;
   #7 = Utf8               bytes
   #8 = Utf8               \u0006\u0005i;Q!\u0006\f\t\u0002}1Q!\t\f\t\u0002\tBQaJ\u0001\u0005\u0002!:Q!K\u0001\t\u0002)2Q\u0001L\u0001\t\u00025BQa\n\u0003\u0005\u00029Bqa\f\u0003C\u0002\u0013\u0005\u0001\u0007\u0003\u0004:\t\u0001\u0006I!\r\u0005\bu\u0011\u0011\r\u0011\"\u00011\u0011\u0019YD\u0001)A\u0005c!9A\b\u0002b\u0001\n\u0003\u0001\u0004BB\u001f\u0005A\u0003%\u0011\u0007C\u0004?\t\t\u0007I\u0011\u0001\u0019\t\r}\"\u0001\u0015!\u00032\u0011\u001d\u0001EA1A\u0005\u0002ABa!\u0011\u0003!\u0002\u0013\t\u0004b\u0002\"\u0005\u0005\u0004%\t\u0001\r\u0005\u0007\u0007\u0012\u0001\u000b\u0011B\u0019\t\u000f\u0011#!\u0019!C\u0001a!1Q\t\u0002Q\u0001\nEBQAR\u0001\u0005\u0002\u001d\u000b!#\u00128d_\u0012Lgn\u001a%fkJL7\u000f^5dg*\u0011q\u0003G\u0001\u0004g\u0006D(BA\r\u001b\u0003\u001dIgn\u00197vI\u0016T!a\u0007\u000f\u0002\u0007alGNC\u0001\u001e\u0003\u0015\u00198-\u00197b\u0007\u0001\u0001\"\u0001I\u0001\u000e\u0003Y\u0011!#\u00128d_\u0012Lgn\u001a%fkJL7\u000f^5dgN\u0011\u0011a\t\t\u0003I\u0015j\u0011\u0001H\u0005\u0003Mq\u0011a!\u00118z%\u00164\u0017A\u0002\u001fj]&$h\bF\u0001 \u00035)enY8eS:<g*Y7fgB\u00111\u0006B\u0007\u0002\u0003\tiQI\\2pI&twMT1nKN\u001c\"\u0001B\u0012\u0015\u0003)\nqAY5h+\u000e\u001bF\'F\u00012!\t\u0011t\'D\u00014\u0015\t!T\'\u0001\u0003mC:<\'\"\u0001\u001c\u0002\t)\fg/Y\u0005\u0003qM\u0012aa\u0015;sS:<\u0017\u0001\u00032jOV\u001b5\u000b\u000e\u0011\u0002\u00151LG\u000f\u001e7f+\u000e\u001bF\'A\u0006mSR$H.Z+D\'R\u0002\u0013aC;okN,\u0018\r\\+D\'R\nA\"\u001e8vgV\fG.V\"Ti\u0001\n\u0001BY5h+R3\u0015GN\u0001\nE&<W\u000b\u0016$2m\u0001\n1\u0002\\5ui2,W\u000b\u0016$2m\u0005aA.\u001b;uY\u0016,FKR\u00197A\u0005!Q\u000f\u001e49\u0003\u0015)HO\u001a\u001d!\u0003\u001d!WMZ1vYR\f\u0001\u0002Z3gCVdG\u000fI\u0001\u0017e\u0016\fG-\u00128d_\u0012Lgn\u001a$s_6\u001cFO]3b[R\u0011\u0001J\u0015\t\u0003\u0013Bs!A\u0013(\u0011\u0005-cR\"\u0001\'\u000b\u00055s\u0012A\u0002\u001fs_>$h(\u0003\u0002P9\u00051\u0001K]3eK\u001aL!\u0001O)\u000b\u0005=c\u0002\"B*\u0015\u0001\u0004!\u0016AA5o!\t)\u0006,D\u0001W\u0015\t9V\'\u0001\u0002j_&\u0011\u0011L\u0016\u0002\f\u0013:\u0004X\u000f^*ue\u0016\fW\u000e
   #9 = Utf8               scala/xml/include/sax/EncodingHeuristics$EncodingNames$
  #10 = Class              #9             // scala/xml/include/sax/EncodingHeuristics$EncodingNames$
  #11 = Utf8               EncodingNames$
  #12 = Utf8               readEncodingFromStream
  #13 = Utf8               (Ljava/io/InputStream;)Ljava/lang/String;
  #14 = Utf8               in
  #15 = Utf8               scala/xml/include/sax/EncodingHeuristics$
  #16 = Class              #15            // scala/xml/include/sax/EncodingHeuristics$
  #17 = Utf8               MODULE$
  #18 = Utf8               Lscala/xml/include/sax/EncodingHeuristics$;
  #19 = NameAndType        #17:#18        // MODULE$:Lscala/xml/include/sax/EncodingHeuristics$;
  #20 = Fieldref           #16.#19        // scala/xml/include/sax/EncodingHeuristics$.MODULE$:Lscala/xml/include/sax/EncodingHeuristics$;
  #21 = NameAndType        #12:#13        // readEncodingFromStream:(Ljava/io/InputStream;)Ljava/lang/String;
  #22 = Methodref          #16.#21        // scala/xml/include/sax/EncodingHeuristics$.readEncodingFromStream:(Ljava/io/InputStream;)Ljava/lang/String;
  #23 = Utf8               Ljava/io/InputStream;
  #24 = Utf8               Code
  #25 = Utf8               LocalVariableTable
  #26 = Utf8               MethodParameters
  #27 = Utf8               InnerClasses
  #28 = Utf8               SourceFile
  #29 = Utf8               RuntimeVisibleAnnotations
  #30 = Utf8               ScalaSig
{
  public static java.lang.String readEncodingFromStream(java.io.InputStream);
    descriptor: (Ljava/io/InputStream;)Ljava/lang/String;
    flags: (0x0009) ACC_PUBLIC, ACC_STATIC
    Code:
      stack=2, locals=1, args_size=1
         0: getstatic     #20                 // Field scala/xml/include/sax/EncodingHeuristics$.MODULE$:Lscala/xml/include/sax/EncodingHeuristics$;
         3: aload_0
         4: invokevirtual #22                 // Method scala/xml/include/sax/EncodingHeuristics$.readEncodingFromStream:(Ljava/io/InputStream;)Ljava/lang/String;
         7: areturn
      LocalVariableTable:
        Start  Length  Slot  Name   Signature
            0       8     0    in   Ljava/io/InputStream;
    MethodParameters:
      Name                           Flags
      in                             final
}
InnerClasses:
  public static #11= #10 of #2;           // EncodingNames$=class scala/xml/include/sax/EncodingHeuristics$EncodingNames$ of class scala/xml/include/sax/EncodingHeuristics
SourceFile: "EncodingHeuristics.scala"
RuntimeVisibleAnnotations:
  0: #6(#7=s#8)
    scala.reflect.ScalaSignature(
      bytes="\u0006\u0005i;Q!\u0006\f\t\u0002}1Q!\t\f\t\u0002\tBQaJ\u0001\u0005\u0002!:Q!K\u0001\t\u0002)2Q\u0001L\u0001\t\u00025BQa\n\u0003\u0005\u00029Bqa\f\u0003C\u0002\u0013\u0005\u0001\u0007\u0003\u0004:\t\u0001\u0006I!\r\u0005\bu\u0011\u0011\r\u0011\"\u00011\u0011\u0019YD\u0001)A\u0005c!9A\b\u0002b\u0001\n\u0003\u0001\u0004BB\u001f\u0005A\u0003%\u0011\u0007C\u0004?\t\t\u0007I\u0011\u0001\u0019\t\r}\"\u0001\u0015!\u00032\u0011\u001d\u0001EA1A\u0005\u0002ABa!\u0011\u0003!\u0002\u0013\t\u0004b\u0002\"\u0005\u0005\u0004%\t\u0001\r\u0005\u0007\u0007\u0012\u0001\u000b\u0011B\u0019\t\u000f\u0011#!\u0019!C\u0001a!1Q\t\u0002Q\u0001\nEBQAR\u0001\u0005\u0002\u001d\u000b!#\u00128d_\u0012Lgn\u001a%fkJL7\u000f^5dg*\u0011q\u0003G\u0001\u0004g\u0006D(BA\r\u001b\u0003\u001dIgn\u00197vI\u0016T!a\u0007\u000f\u0002\u0007alGNC\u0001\u001e\u0003\u0015\u00198-\u00197b\u0007\u0001\u0001\"\u0001I\u0001\u000e\u0003Y\u0011!#\u00128d_\u0012Lgn\u001a%fkJL7\u000f^5dgN\u0011\u0011a\t\t\u0003I\u0015j\u0011\u0001H\u0005\u0003Mq\u0011a!\u00118z%\u00164\u0017A\u0002\u001fj]&$h\bF\u0001 \u00035)enY8eS:<g*Y7fgB\u00111\u0006B\u0007\u0002\u0003\tiQI\\2pI&twMT1nKN\u001c\"\u0001B\u0012\u0015\u0003)\nqAY5h+\u000e\u001bF\'F\u00012!\t\u0011t\'D\u00014\u0015\t!T\'\u0001\u0003mC:<\'\"\u0001\u001c\u0002\t)\fg/Y\u0005\u0003qM\u0012aa\u0015;sS:<\u0017\u0001\u00032jOV\u001b5\u000b\u000e\u0011\u0002\u00151LG\u000f\u001e7f+\u000e\u001bF\'A\u0006mSR$H.Z+D\'R\u0002\u0013aC;okN,\u0018\r\\+D\'R\nA\"\u001e8vgV\fG.V\"Ti\u0001\n\u0001BY5h+R3\u0015GN\u0001\nE&<W\u000b\u0016$2m\u0001\n1\u0002\\5ui2,W\u000b\u0016$2m\u0005aA.\u001b;uY\u0016,FKR\u00197A\u0005!Q\u000f\u001e49\u0003\u0015)HO\u001a\u001d!\u0003\u001d!WMZ1vYR\f\u0001\u0002Z3gCVdG\u000fI\u0001\u0017e\u0016\fG-\u00128d_\u0012Lgn\u001a$s_6\u001cFO]3b[R\u0011\u0001J\u0015\t\u0003\u0013Bs!A\u0013(\u0011\u0005-cR\"\u0001\'\u000b\u00055s\u0012A\u0002\u001fs_>$h(\u0003\u0002P9\u00051\u0001K]3eK\u001aL!\u0001O)\u000b\u0005=c\u0002\"B*\u0015\u0001\u0004!\u0016AA5o!\t)\u0006,D\u0001W\u0015\t9V\'\u0001\u0002j_&\u0011\u0011L\u0016\u0002\f\u0013:\u0004X\u000f^*ue\u0016\fW\u000e"
    )
  ScalaSig: length = 0x3 (unknown attribute)
   05 02 00
