Classfile /Users/mw/Projects/slang-braindump/.jar/jar8/assemble/slang-braindump/assemble/content/os/copy$$anon$2.class
  Last modified May 29, 2022; size 9298 bytes
  SHA-256 checksum 3332ca1a658570d97475d667aa82c9aaacaed7ab4c6c779b0a24996aa16ea33f
  Compiled from "FileOps.scala"
public final class os.copy$$anon$2 extends java.lang.Object implements scala.PartialFunction<os.Path, scala.runtime.BoxedUnit>
  minor version: 0
  major version: 52
  flags: (0x0031) ACC_PUBLIC, ACC_FINAL, ACC_SUPER
  this_class: #2                          // os/copy$$anon$2
  super_class: #5                         // java/lang/Object
  interfaces: 1, fields: 6, methods: 41, attributes: 6
Constant pool:
    #1 = Utf8               os/copy$$anon$2
    #2 = Class              #1            // os/copy$$anon$2
    #3 = Utf8               Ljava/lang/Object;Lscala/PartialFunction<Los/Path;Lscala/runtime/BoxedUnit;>;
    #4 = Utf8               java/lang/Object
    #5 = Class              #4            // java/lang/Object
    #6 = Utf8               scala/PartialFunction
    #7 = Class              #6            // scala/PartialFunction
    #8 = Utf8               FileOps.scala
    #9 = Utf8               os/copy$
   #10 = Class              #9            // os/copy$
   #11 = Utf8               matching
   #12 = Utf8               (ZZZZZLscala/PartialFunction;)Lscala/PartialFunction;
   #13 = NameAndType        #11:#12       // matching:(ZZZZZLscala/PartialFunction;)Lscala/PartialFunction;
   #14 = Utf8               os/PathChunk$RelPathChunk
   #15 = Class              #14           // os/PathChunk$RelPathChunk
   #16 = Utf8               os/PathChunk
   #17 = Class              #16           // os/PathChunk
   #18 = Utf8               RelPathChunk
   #19 = Utf8               os/makeDir$all$
   #20 = Class              #19           // os/makeDir$all$
   #21 = Utf8               os/makeDir
   #22 = Class              #21           // os/makeDir
   #23 = Utf8               all$
   #24 = Utf8               partialFunction$2
   #25 = Utf8               Lscala/PartialFunction;
   #26 = Utf8               followLinks$1
   #27 = Utf8               Z
   #28 = Utf8               replaceExisting$2
   #29 = Utf8               copyAttributes$1
   #30 = Utf8               createFolders$2
   #31 = Utf8               mergeFolders$1
   #32 = Utf8               unapply
   #33 = Utf8               (Ljava/lang/Object;)Lscala/Option;
   #34 = Utf8               a
   #35 = Utf8               unapply$
   #36 = Utf8               (Lscala/PartialFunction;Ljava/lang/Object;)Lscala/Option;
   #37 = NameAndType        #35:#36       // unapply$:(Lscala/PartialFunction;Ljava/lang/Object;)Lscala/Option;
   #38 = InterfaceMethodref #7.#37        // scala/PartialFunction.unapply$:(Lscala/PartialFunction;Ljava/lang/Object;)Lscala/Option;
   #39 = Utf8               this
   #40 = Utf8               Los/copy$$anon$2;
   #41 = Utf8               Ljava/lang/Object;
   #42 = Utf8               elementWise
   #43 = Utf8               ()Lscala/PartialFunction;
   #44 = Utf8               ()Lscala/PartialFunction<Los/Path;Lscala/runtime/BoxedUnit;>;
   #45 = Utf8               elementWise$
   #46 = Utf8               (Lscala/PartialFunction;)Lscala/PartialFunction;
   #47 = NameAndType        #45:#46       // elementWise$:(Lscala/PartialFunction;)Lscala/PartialFunction;
   #48 = InterfaceMethodref #7.#47        // scala/PartialFunction.elementWise$:(Lscala/PartialFunction;)Lscala/PartialFunction;
   #49 = Utf8               orElse
   #50 = Utf8               <A1:Los/Path;B1:Ljava/lang/Object;>(Lscala/PartialFunction<TA1;TB1;>;)Lscala/PartialFunction<TA1;TB1;>;
   #51 = Utf8               that
   #52 = Utf8               orElse$
   #53 = Utf8               (Lscala/PartialFunction;Lscala/PartialFunction;)Lscala/PartialFunction;
   #54 = NameAndType        #52:#53       // orElse$:(Lscala/PartialFunction;Lscala/PartialFunction;)Lscala/PartialFunction;
   #55 = InterfaceMethodref #7.#54        // scala/PartialFunction.orElse$:(Lscala/PartialFunction;Lscala/PartialFunction;)Lscala/PartialFunction;
   #56 = Utf8               andThen
   #57 = Utf8               (Lscala/Function1;)Lscala/PartialFunction;
   #58 = Utf8               <C:Ljava/lang/Object;>(Lscala/Function1<Lscala/runtime/BoxedUnit;TC;>;)Lscala/PartialFunction<Los/Path;TC;>;
   #59 = Utf8               k
   #60 = Utf8               andThen$
   #61 = Utf8               (Lscala/PartialFunction;Lscala/Function1;)Lscala/PartialFunction;
   #62 = NameAndType        #60:#61       // andThen$:(Lscala/PartialFunction;Lscala/Function1;)Lscala/PartialFunction;
   #63 = InterfaceMethodref #7.#62        // scala/PartialFunction.andThen$:(Lscala/PartialFunction;Lscala/Function1;)Lscala/PartialFunction;
   #64 = Utf8               Lscala/Function1;
   #65 = Utf8               <C:Ljava/lang/Object;>(Lscala/PartialFunction<Lscala/runtime/BoxedUnit;TC;>;)Lscala/PartialFunction<Los/Path;TC;>;
   #66 = NameAndType        #60:#53       // andThen$:(Lscala/PartialFunction;Lscala/PartialFunction;)Lscala/PartialFunction;
   #67 = InterfaceMethodref #7.#66        // scala/PartialFunction.andThen$:(Lscala/PartialFunction;Lscala/PartialFunction;)Lscala/PartialFunction;
   #68 = Utf8               compose
   #69 = Utf8               <R$:Ljava/lang/Object;>(Lscala/PartialFunction<TR$;Los/Path;>;)Lscala/PartialFunction<TR$;Lscala/runtime/BoxedUnit;>;
   #70 = Utf8               compose$
   #71 = NameAndType        #70:#53       // compose$:(Lscala/PartialFunction;Lscala/PartialFunction;)Lscala/PartialFunction;
   #72 = InterfaceMethodref #7.#71        // scala/PartialFunction.compose$:(Lscala/PartialFunction;Lscala/PartialFunction;)Lscala/PartialFunction;
   #73 = Utf8               lift
   #74 = Utf8               ()Lscala/Function1;
   #75 = Utf8               ()Lscala/Function1<Los/Path;Lscala/Option<Lscala/runtime/BoxedUnit;>;>;
   #76 = Utf8               lift$
   #77 = Utf8               (Lscala/PartialFunction;)Lscala/Function1;
   #78 = NameAndType        #76:#77       // lift$:(Lscala/PartialFunction;)Lscala/Function1;
   #79 = InterfaceMethodref #7.#78        // scala/PartialFunction.lift$:(Lscala/PartialFunction;)Lscala/Function1;
   #80 = Utf8               applyOrElse
   #81 = Utf8               (Ljava/lang/Object;Lscala/Function1;)Ljava/lang/Object;
   #82 = Utf8               x
   #83 = Utf8               default
   #84 = Utf8               applyOrElse$
   #85 = Utf8               (Lscala/PartialFunction;Ljava/lang/Object;Lscala/Function1;)Ljava/lang/Object;
   #86 = NameAndType        #84:#85       // applyOrElse$:(Lscala/PartialFunction;Ljava/lang/Object;Lscala/Function1;)Ljava/lang/Object;
   #87 = InterfaceMethodref #7.#86        // scala/PartialFunction.applyOrElse$:(Lscala/PartialFunction;Ljava/lang/Object;Lscala/Function1;)Ljava/lang/Object;
   #88 = Utf8               runWith
   #89 = Utf8               (Lscala/Function1;)Lscala/Function1;
   #90 = Utf8               <U:Ljava/lang/Object;>(Lscala/Function1<Lscala/runtime/BoxedUnit;TU;>;)Lscala/Function1<Los/Path;Ljava/lang/Object;>;
   #91 = Utf8               action
   #92 = Utf8               runWith$
   #93 = Utf8               (Lscala/PartialFunction;Lscala/Function1;)Lscala/Function1;
   #94 = NameAndType        #92:#93       // runWith$:(Lscala/PartialFunction;Lscala/Function1;)Lscala/Function1;
   #95 = InterfaceMethodref #7.#94        // scala/PartialFunction.runWith$:(Lscala/PartialFunction;Lscala/Function1;)Lscala/Function1;
   #96 = Utf8               apply$mcZD$sp
   #97 = Utf8               (D)Z
   #98 = Utf8               v1
   #99 = Utf8               scala/Function1
  #100 = Class              #99           // scala/Function1
  #101 = Utf8               apply$mcZD$sp$
  #102 = Utf8               (Lscala/Function1;D)Z
  #103 = NameAndType        #101:#102     // apply$mcZD$sp$:(Lscala/Function1;D)Z
  #104 = InterfaceMethodref #100.#103     // scala/Function1.apply$mcZD$sp$:(Lscala/Function1;D)Z
  #105 = Utf8               D
  #106 = Utf8               apply$mcDD$sp
  #107 = Utf8               (D)D
  #108 = Utf8               apply$mcDD$sp$
  #109 = Utf8               (Lscala/Function1;D)D
  #110 = NameAndType        #108:#109     // apply$mcDD$sp$:(Lscala/Function1;D)D
  #111 = InterfaceMethodref #100.#110     // scala/Function1.apply$mcDD$sp$:(Lscala/Function1;D)D
  #112 = Utf8               apply$mcFD$sp
  #113 = Utf8               (D)F
  #114 = Utf8               apply$mcFD$sp$
  #115 = Utf8               (Lscala/Function1;D)F
  #116 = NameAndType        #114:#115     // apply$mcFD$sp$:(Lscala/Function1;D)F
  #117 = InterfaceMethodref #100.#116     // scala/Function1.apply$mcFD$sp$:(Lscala/Function1;D)F
  #118 = Utf8               apply$mcID$sp
  #119 = Utf8               (D)I
  #120 = Utf8               apply$mcID$sp$
  #121 = Utf8               (Lscala/Function1;D)I
  #122 = NameAndType        #120:#121     // apply$mcID$sp$:(Lscala/Function1;D)I
  #123 = InterfaceMethodref #100.#122     // scala/Function1.apply$mcID$sp$:(Lscala/Function1;D)I
  #124 = Utf8               apply$mcJD$sp
  #125 = Utf8               (D)J
  #126 = Utf8               apply$mcJD$sp$
  #127 = Utf8               (Lscala/Function1;D)J
  #128 = NameAndType        #126:#127     // apply$mcJD$sp$:(Lscala/Function1;D)J
  #129 = InterfaceMethodref #100.#128     // scala/Function1.apply$mcJD$sp$:(Lscala/Function1;D)J
  #130 = Utf8               apply$mcVD$sp
  #131 = Utf8               (D)V
  #132 = Utf8               apply$mcVD$sp$
  #133 = Utf8               (Lscala/Function1;D)V
  #134 = NameAndType        #132:#133     // apply$mcVD$sp$:(Lscala/Function1;D)V
  #135 = InterfaceMethodref #100.#134     // scala/Function1.apply$mcVD$sp$:(Lscala/Function1;D)V
  #136 = Utf8               apply$mcZF$sp
  #137 = Utf8               (F)Z
  #138 = Utf8               apply$mcZF$sp$
  #139 = Utf8               (Lscala/Function1;F)Z
  #140 = NameAndType        #138:#139     // apply$mcZF$sp$:(Lscala/Function1;F)Z
  #141 = InterfaceMethodref #100.#140     // scala/Function1.apply$mcZF$sp$:(Lscala/Function1;F)Z
  #142 = Utf8               F
  #143 = Utf8               apply$mcDF$sp
  #144 = Utf8               (F)D
  #145 = Utf8               apply$mcDF$sp$
  #146 = Utf8               (Lscala/Function1;F)D
  #147 = NameAndType        #145:#146     // apply$mcDF$sp$:(Lscala/Function1;F)D
  #148 = InterfaceMethodref #100.#147     // scala/Function1.apply$mcDF$sp$:(Lscala/Function1;F)D
  #149 = Utf8               apply$mcFF$sp
  #150 = Utf8               (F)F
  #151 = Utf8               apply$mcFF$sp$
  #152 = Utf8               (Lscala/Function1;F)F
  #153 = NameAndType        #151:#152     // apply$mcFF$sp$:(Lscala/Function1;F)F
  #154 = InterfaceMethodref #100.#153     // scala/Function1.apply$mcFF$sp$:(Lscala/Function1;F)F
  #155 = Utf8               apply$mcIF$sp
  #156 = Utf8               (F)I
  #157 = Utf8               apply$mcIF$sp$
  #158 = Utf8               (Lscala/Function1;F)I
  #159 = NameAndType        #157:#158     // apply$mcIF$sp$:(Lscala/Function1;F)I
  #160 = InterfaceMethodref #100.#159     // scala/Function1.apply$mcIF$sp$:(Lscala/Function1;F)I
  #161 = Utf8               apply$mcJF$sp
  #162 = Utf8               (F)J
  #163 = Utf8               apply$mcJF$sp$
  #164 = Utf8               (Lscala/Function1;F)J
  #165 = NameAndType        #163:#164     // apply$mcJF$sp$:(Lscala/Function1;F)J
  #166 = InterfaceMethodref #100.#165     // scala/Function1.apply$mcJF$sp$:(Lscala/Function1;F)J
  #167 = Utf8               apply$mcVF$sp
  #168 = Utf8               (F)V
  #169 = Utf8               apply$mcVF$sp$
  #170 = Utf8               (Lscala/Function1;F)V
  #171 = NameAndType        #169:#170     // apply$mcVF$sp$:(Lscala/Function1;F)V
  #172 = InterfaceMethodref #100.#171     // scala/Function1.apply$mcVF$sp$:(Lscala/Function1;F)V
  #173 = Utf8               apply$mcZI$sp
  #174 = Utf8               (I)Z
  #175 = Utf8               apply$mcZI$sp$
  #176 = Utf8               (Lscala/Function1;I)Z
  #177 = NameAndType        #175:#176     // apply$mcZI$sp$:(Lscala/Function1;I)Z
  #178 = InterfaceMethodref #100.#177     // scala/Function1.apply$mcZI$sp$:(Lscala/Function1;I)Z
  #179 = Utf8               I
  #180 = Utf8               apply$mcDI$sp
  #181 = Utf8               (I)D
  #182 = Utf8               apply$mcDI$sp$
  #183 = Utf8               (Lscala/Function1;I)D
  #184 = NameAndType        #182:#183     // apply$mcDI$sp$:(Lscala/Function1;I)D
  #185 = InterfaceMethodref #100.#184     // scala/Function1.apply$mcDI$sp$:(Lscala/Function1;I)D
  #186 = Utf8               apply$mcFI$sp
  #187 = Utf8               (I)F
  #188 = Utf8               apply$mcFI$sp$
  #189 = Utf8               (Lscala/Function1;I)F
  #190 = NameAndType        #188:#189     // apply$mcFI$sp$:(Lscala/Function1;I)F
  #191 = InterfaceMethodref #100.#190     // scala/Function1.apply$mcFI$sp$:(Lscala/Function1;I)F
  #192 = Utf8               apply$mcII$sp
  #193 = Utf8               (I)I
  #194 = Utf8               apply$mcII$sp$
  #195 = Utf8               (Lscala/Function1;I)I
  #196 = NameAndType        #194:#195     // apply$mcII$sp$:(Lscala/Function1;I)I
  #197 = InterfaceMethodref #100.#196     // scala/Function1.apply$mcII$sp$:(Lscala/Function1;I)I
  #198 = Utf8               apply$mcJI$sp
  #199 = Utf8               (I)J
  #200 = Utf8               apply$mcJI$sp$
  #201 = Utf8               (Lscala/Function1;I)J
  #202 = NameAndType        #200:#201     // apply$mcJI$sp$:(Lscala/Function1;I)J
  #203 = InterfaceMethodref #100.#202     // scala/Function1.apply$mcJI$sp$:(Lscala/Function1;I)J
  #204 = Utf8               apply$mcVI$sp
  #205 = Utf8               (I)V
  #206 = Utf8               apply$mcVI$sp$
  #207 = Utf8               (Lscala/Function1;I)V
  #208 = NameAndType        #206:#207     // apply$mcVI$sp$:(Lscala/Function1;I)V
  #209 = InterfaceMethodref #100.#208     // scala/Function1.apply$mcVI$sp$:(Lscala/Function1;I)V
  #210 = Utf8               apply$mcZJ$sp
  #211 = Utf8               (J)Z
  #212 = Utf8               apply$mcZJ$sp$
  #213 = Utf8               (Lscala/Function1;J)Z
  #214 = NameAndType        #212:#213     // apply$mcZJ$sp$:(Lscala/Function1;J)Z
  #215 = InterfaceMethodref #100.#214     // scala/Function1.apply$mcZJ$sp$:(Lscala/Function1;J)Z
  #216 = Utf8               J
  #217 = Utf8               apply$mcDJ$sp
  #218 = Utf8               (J)D
  #219 = Utf8               apply$mcDJ$sp$
  #220 = Utf8               (Lscala/Function1;J)D
  #221 = NameAndType        #219:#220     // apply$mcDJ$sp$:(Lscala/Function1;J)D
  #222 = InterfaceMethodref #100.#221     // scala/Function1.apply$mcDJ$sp$:(Lscala/Function1;J)D
  #223 = Utf8               apply$mcFJ$sp
  #224 = Utf8               (J)F
  #225 = Utf8               apply$mcFJ$sp$
  #226 = Utf8               (Lscala/Function1;J)F
  #227 = NameAndType        #225:#226     // apply$mcFJ$sp$:(Lscala/Function1;J)F
  #228 = InterfaceMethodref #100.#227     // scala/Function1.apply$mcFJ$sp$:(Lscala/Function1;J)F
  #229 = Utf8               apply$mcIJ$sp
  #230 = Utf8               (J)I
  #231 = Utf8               apply$mcIJ$sp$
  #232 = Utf8               (Lscala/Function1;J)I
  #233 = NameAndType        #231:#232     // apply$mcIJ$sp$:(Lscala/Function1;J)I
  #234 = InterfaceMethodref #100.#233     // scala/Function1.apply$mcIJ$sp$:(Lscala/Function1;J)I
  #235 = Utf8               apply$mcJJ$sp
  #236 = Utf8               (J)J
  #237 = Utf8               apply$mcJJ$sp$
  #238 = Utf8               (Lscala/Function1;J)J
  #239 = NameAndType        #237:#238     // apply$mcJJ$sp$:(Lscala/Function1;J)J
  #240 = InterfaceMethodref #100.#239     // scala/Function1.apply$mcJJ$sp$:(Lscala/Function1;J)J
  #241 = Utf8               apply$mcVJ$sp
  #242 = Utf8               (J)V
  #243 = Utf8               apply$mcVJ$sp$
  #244 = Utf8               (Lscala/Function1;J)V
  #245 = NameAndType        #243:#244     // apply$mcVJ$sp$:(Lscala/Function1;J)V
  #246 = InterfaceMethodref #100.#245     // scala/Function1.apply$mcVJ$sp$:(Lscala/Function1;J)V
  #247 = Utf8               <A:Ljava/lang/Object;>(Lscala/Function1<TA;Los/Path;>;)Lscala/Function1<TA;Lscala/runtime/BoxedUnit;>;
  #248 = Utf8               g
  #249 = Utf8               (Lscala/Function1;Lscala/Function1;)Lscala/Function1;
  #250 = NameAndType        #70:#249      // compose$:(Lscala/Function1;Lscala/Function1;)Lscala/Function1;
  #251 = InterfaceMethodref #100.#250     // scala/Function1.compose$:(Lscala/Function1;Lscala/Function1;)Lscala/Function1;
  #252 = Utf8               toString
  #253 = Utf8               ()Ljava/lang/String;
  #254 = Utf8               toString$
  #255 = Utf8               (Lscala/Function1;)Ljava/lang/String;
  #256 = NameAndType        #254:#255     // toString$:(Lscala/Function1;)Ljava/lang/String;
  #257 = InterfaceMethodref #100.#256     // scala/Function1.toString$:(Lscala/Function1;)Ljava/lang/String;
  #258 = Utf8               isDefinedAt
  #259 = Utf8               (Los/Path;)Z
  #260 = NameAndType        #24:#25       // partialFunction$2:Lscala/PartialFunction;
  #261 = Fieldref           #2.#260       // os/copy$$anon$2.partialFunction$2:Lscala/PartialFunction;
  #262 = Utf8               (Ljava/lang/Object;)Z
  #263 = NameAndType        #258:#262     // isDefinedAt:(Ljava/lang/Object;)Z
  #264 = InterfaceMethodref #7.#263       // scala/PartialFunction.isDefinedAt:(Ljava/lang/Object;)Z
  #265 = Utf8               Los/Path;
  #266 = Utf8               apply
  #267 = Utf8               (Los/Path;)V
  #268 = Utf8               from
  #269 = Utf8               (Ljava/lang/Object;)Ljava/lang/Object;
  #270 = NameAndType        #266:#269     // apply:(Ljava/lang/Object;)Ljava/lang/Object;
  #271 = InterfaceMethodref #7.#270       // scala/PartialFunction.apply:(Ljava/lang/Object;)Ljava/lang/Object;
  #272 = Utf8               os/Path
  #273 = Class              #272          // os/Path
  #274 = Utf8               MODULE$
  #275 = Utf8               Los/makeDir$all$;
  #276 = NameAndType        #274:#275     // MODULE$:Los/makeDir$all$;
  #277 = Fieldref           #20.#276      // os/makeDir$all$.MODULE$:Los/makeDir$all$;
  #278 = Utf8               os/PathChunk$
  #279 = Class              #278          // os/PathChunk$
  #280 = Utf8               Los/PathChunk$;
  #281 = NameAndType        #274:#280     // MODULE$:Los/PathChunk$;
  #282 = Fieldref           #279.#281     // os/PathChunk$.MODULE$:Los/PathChunk$;
  #283 = Utf8               os/package$
  #284 = Class              #283          // os/package$
  #285 = Utf8               Los/package$;
  #286 = NameAndType        #274:#285     // MODULE$:Los/package$;
  #287 = Fieldref           #284.#286     // os/package$.MODULE$:Los/package$;
  #288 = Utf8               up
  #289 = Utf8               ()Los/RelPath;
  #290 = NameAndType        #288:#289     // up:()Los/RelPath;
  #291 = Methodref          #284.#290     // os/package$.up:()Los/RelPath;
  #292 = Utf8               (Los/RelPath;)Los/PathChunk$RelPathChunk;
  #293 = NameAndType        #18:#292      // RelPathChunk:(Los/RelPath;)Los/PathChunk$RelPathChunk;
  #294 = Methodref          #279.#293     // os/PathChunk$.RelPathChunk:(Los/RelPath;)Los/PathChunk$RelPathChunk;
  #295 = Utf8               $div
  #296 = Utf8               (Los/PathChunk;)Los/Path;
  #297 = NameAndType        #295:#296     // $div:(Los/PathChunk;)Los/Path;
  #298 = Methodref          #273.#297     // os/Path.$div:(Los/PathChunk;)Los/Path;
  #299 = NameAndType        #266:#267     // apply:(Los/Path;)V
  #300 = Methodref          #20.#299      // os/makeDir$all$.apply:(Los/Path;)V
  #301 = Utf8               Los/copy$;
  #302 = NameAndType        #274:#301     // MODULE$:Los/copy$;
  #303 = Fieldref           #10.#302      // os/copy$.MODULE$:Los/copy$;
  #304 = NameAndType        #26:#27       // followLinks$1:Z
  #305 = Fieldref           #2.#304       // os/copy$$anon$2.followLinks$1:Z
  #306 = NameAndType        #28:#27       // replaceExisting$2:Z
  #307 = Fieldref           #2.#306       // os/copy$$anon$2.replaceExisting$2:Z
  #308 = NameAndType        #29:#27       // copyAttributes$1:Z
  #309 = Fieldref           #2.#308       // os/copy$$anon$2.copyAttributes$1:Z
  #310 = NameAndType        #30:#27       // createFolders$2:Z
  #311 = Fieldref           #2.#310       // os/copy$$anon$2.createFolders$2:Z
  #312 = NameAndType        #31:#27       // mergeFolders$1:Z
  #313 = Fieldref           #2.#312       // os/copy$$anon$2.mergeFolders$1:Z
  #314 = Utf8               (Los/Path;Los/Path;ZZZZZ)V
  #315 = NameAndType        #266:#314     // apply:(Los/Path;Los/Path;ZZZZZ)V
  #316 = Methodref          #10.#315      // os/copy$.apply:(Los/Path;Los/Path;ZZZZZ)V
  #317 = Utf8               dest
  #318 = NameAndType        #56:#57       // andThen:(Lscala/Function1;)Lscala/PartialFunction;
  #319 = Methodref          #2.#318       // os/copy$$anon$2.andThen:(Lscala/Function1;)Lscala/PartialFunction;
  #320 = Methodref          #2.#299       // os/copy$$anon$2.apply:(Los/Path;)V
  #321 = Utf8               scala/runtime/BoxedUnit
  #322 = Class              #321          // scala/runtime/BoxedUnit
  #323 = Utf8               UNIT
  #324 = Utf8               Lscala/runtime/BoxedUnit;
  #325 = NameAndType        #323:#324     // UNIT:Lscala/runtime/BoxedUnit;
  #326 = Fieldref           #322.#325     // scala/runtime/BoxedUnit.UNIT:Lscala/runtime/BoxedUnit;
  #327 = NameAndType        #258:#259     // isDefinedAt:(Los/Path;)Z
  #328 = Methodref          #2.#327       // os/copy$$anon$2.isDefinedAt:(Los/Path;)Z
  #329 = Utf8               <init>
  #330 = Utf8               (Lscala/PartialFunction;ZZZZZ)V
  #331 = Utf8               ()V
  #332 = NameAndType        #329:#331     // "<init>":()V
  #333 = Methodref          #5.#332       // java/lang/Object."<init>":()V
  #334 = Utf8               $init$
  #335 = Utf8               (Lscala/Function1;)V
  #336 = NameAndType        #334:#335     // $init$:(Lscala/Function1;)V
  #337 = InterfaceMethodref #100.#336     // scala/Function1.$init$:(Lscala/Function1;)V
  #338 = Utf8               (Lscala/PartialFunction;)V
  #339 = NameAndType        #334:#338     // $init$:(Lscala/PartialFunction;)V
  #340 = InterfaceMethodref #7.#339       // scala/PartialFunction.$init$:(Lscala/PartialFunction;)V
  #341 = Utf8               Code
  #342 = Utf8               LineNumberTable
  #343 = Utf8               LocalVariableTable
  #344 = Utf8               MethodParameters
  #345 = Utf8               Signature
  #346 = Utf8               InnerClasses
  #347 = Utf8               EnclosingMethod
  #348 = Utf8               SourceFile
  #349 = Utf8               ScalaInlineInfo
  #350 = Utf8               Scala
{
  private final scala.PartialFunction partialFunction$2;
    descriptor: Lscala/PartialFunction;
    flags: (0x0012) ACC_PRIVATE, ACC_FINAL

  private final boolean followLinks$1;
    descriptor: Z
    flags: (0x0012) ACC_PRIVATE, ACC_FINAL

  private final boolean replaceExisting$2;
    descriptor: Z
    flags: (0x0012) ACC_PRIVATE, ACC_FINAL

  private final boolean copyAttributes$1;
    descriptor: Z
    flags: (0x0012) ACC_PRIVATE, ACC_FINAL

  private final boolean createFolders$2;
    descriptor: Z
    flags: (0x0012) ACC_PRIVATE, ACC_FINAL

  private final boolean mergeFolders$1;
    descriptor: Z
    flags: (0x0012) ACC_PRIVATE, ACC_FINAL

  public scala.Option unapply(java.lang.Object);
    descriptor: (Ljava/lang/Object;)Lscala/Option;
    flags: (0x0001) ACC_PUBLIC
    Code:
      stack=2, locals=2, args_size=2
         0: aload_0
         1: aload_1
         2: invokestatic  #38                 // InterfaceMethod scala/PartialFunction.unapply$:(Lscala/PartialFunction;Ljava/lang/Object;)Lscala/Option;
         5: areturn
      LineNumberTable:
        line 141: 0
      LocalVariableTable:
        Start  Length  Slot  Name   Signature
            0       6     0  this   Los/copy$$anon$2;
            0       6     1     a   Ljava/lang/Object;
    MethodParameters:
      Name                           Flags
      a                              final

  public scala.PartialFunction<os.Path, scala.runtime.BoxedUnit> elementWise();
    descriptor: ()Lscala/PartialFunction;
    flags: (0x0001) ACC_PUBLIC
    Code:
      stack=1, locals=1, args_size=1
         0: aload_0
         1: invokestatic  #48                 // InterfaceMethod scala/PartialFunction.elementWise$:(Lscala/PartialFunction;)Lscala/PartialFunction;
         4: areturn
      LineNumberTable:
        line 141: 0
      LocalVariableTable:
        Start  Length  Slot  Name   Signature
            0       5     0  this   Los/copy$$anon$2;
    Signature: #44                          // ()Lscala/PartialFunction<Los/Path;Lscala/runtime/BoxedUnit;>;

  public <A1 extends os.Path, B1 extends java.lang.Object> scala.PartialFunction<A1, B1> orElse(scala.PartialFunction<A1, B1>);
    descriptor: (Lscala/PartialFunction;)Lscala/PartialFunction;
    flags: (0x0001) ACC_PUBLIC
    Code:
      stack=2, locals=2, args_size=2
         0: aload_0
         1: aload_1
         2: invokestatic  #55                 // InterfaceMethod scala/PartialFunction.orElse$:(Lscala/PartialFunction;Lscala/PartialFunction;)Lscala/PartialFunction;
         5: areturn
      LineNumberTable:
        line 141: 0
      LocalVariableTable:
        Start  Length  Slot  Name   Signature
            0       6     0  this   Los/copy$$anon$2;
            0       6     1  that   Lscala/PartialFunction;
    Signature: #50                          // <A1:Los/Path;B1:Ljava/lang/Object;>(Lscala/PartialFunction<TA1;TB1;>;)Lscala/PartialFunction<TA1;TB1;>;
    MethodParameters:
      Name                           Flags
      that                           final

  public <C extends java.lang.Object> scala.PartialFunction<os.Path, C> andThen(scala.Function1<scala.runtime.BoxedUnit, C>);
    descriptor: (Lscala/Function1;)Lscala/PartialFunction;
    flags: (0x0001) ACC_PUBLIC
    Code:
      stack=2, locals=2, args_size=2
         0: aload_0
         1: aload_1
         2: invokestatic  #63                 // InterfaceMethod scala/PartialFunction.andThen$:(Lscala/PartialFunction;Lscala/Function1;)Lscala/PartialFunction;
         5: areturn
      LineNumberTable:
        line 141: 0
      LocalVariableTable:
        Start  Length  Slot  Name   Signature
            0       6     0  this   Los/copy$$anon$2;
            0       6     1     k   Lscala/Function1;
    Signature: #58                          // <C:Ljava/lang/Object;>(Lscala/Function1<Lscala/runtime/BoxedUnit;TC;>;)Lscala/PartialFunction<Los/Path;TC;>;
    MethodParameters:
      Name                           Flags
      k                              final

  public <C extends java.lang.Object> scala.PartialFunction<os.Path, C> andThen(scala.PartialFunction<scala.runtime.BoxedUnit, C>);
    descriptor: (Lscala/PartialFunction;)Lscala/PartialFunction;
    flags: (0x0001) ACC_PUBLIC
    Code:
      stack=2, locals=2, args_size=2
         0: aload_0
         1: aload_1
         2: invokestatic  #67                 // InterfaceMethod scala/PartialFunction.andThen$:(Lscala/PartialFunction;Lscala/PartialFunction;)Lscala/PartialFunction;
         5: areturn
      LineNumberTable:
        line 141: 0
      LocalVariableTable:
        Start  Length  Slot  Name   Signature
            0       6     0  this   Los/copy$$anon$2;
            0       6     1     k   Lscala/PartialFunction;
    Signature: #65                          // <C:Ljava/lang/Object;>(Lscala/PartialFunction<Lscala/runtime/BoxedUnit;TC;>;)Lscala/PartialFunction<Los/Path;TC;>;
    MethodParameters:
      Name                           Flags
      k                              final

  public <R$ extends java.lang.Object> scala.PartialFunction<R$, scala.runtime.BoxedUnit> compose(scala.PartialFunction<R$, os.Path>);
    descriptor: (Lscala/PartialFunction;)Lscala/PartialFunction;
    flags: (0x0001) ACC_PUBLIC
    Code:
      stack=2, locals=2, args_size=2
         0: aload_0
         1: aload_1
         2: invokestatic  #72                 // InterfaceMethod scala/PartialFunction.compose$:(Lscala/PartialFunction;Lscala/PartialFunction;)Lscala/PartialFunction;
         5: areturn
      LineNumberTable:
        line 141: 0
      LocalVariableTable:
        Start  Length  Slot  Name   Signature
            0       6     0  this   Los/copy$$anon$2;
            0       6     1     k   Lscala/PartialFunction;
    Signature: #69                          // <R$:Ljava/lang/Object;>(Lscala/PartialFunction<TR$;Los/Path;>;)Lscala/PartialFunction<TR$;Lscala/runtime/BoxedUnit;>;
    MethodParameters:
      Name                           Flags
      k                              final

  public scala.Function1<os.Path, scala.Option<scala.runtime.BoxedUnit>> lift();
    descriptor: ()Lscala/Function1;
    flags: (0x0001) ACC_PUBLIC
    Code:
      stack=1, locals=1, args_size=1
         0: aload_0
         1: invokestatic  #79                 // InterfaceMethod scala/PartialFunction.lift$:(Lscala/PartialFunction;)Lscala/Function1;
         4: areturn
      LineNumberTable:
        line 141: 0
      LocalVariableTable:
        Start  Length  Slot  Name   Signature
            0       5     0  this   Los/copy$$anon$2;
    Signature: #75                          // ()Lscala/Function1<Los/Path;Lscala/Option<Lscala/runtime/BoxedUnit;>;>;

  public java.lang.Object applyOrElse(java.lang.Object, scala.Function1);
    descriptor: (Ljava/lang/Object;Lscala/Function1;)Ljava/lang/Object;
    flags: (0x0001) ACC_PUBLIC
    Code:
      stack=3, locals=3, args_size=3
         0: aload_0
         1: aload_1
         2: aload_2
         3: invokestatic  #87                 // InterfaceMethod scala/PartialFunction.applyOrElse$:(Lscala/PartialFunction;Ljava/lang/Object;Lscala/Function1;)Ljava/lang/Object;
         6: areturn
      LineNumberTable:
        line 141: 0
      LocalVariableTable:
        Start  Length  Slot  Name   Signature
            0       7     0  this   Los/copy$$anon$2;
            0       7     1     x   Ljava/lang/Object;
            0       7     2 default   Lscala/Function1;
    MethodParameters:
      Name                           Flags
      x                              final
      default                        final

  public <U extends java.lang.Object> scala.Function1<os.Path, java.lang.Object> runWith(scala.Function1<scala.runtime.BoxedUnit, U>);
    descriptor: (Lscala/Function1;)Lscala/Function1;
    flags: (0x0001) ACC_PUBLIC
    Code:
      stack=2, locals=2, args_size=2
         0: aload_0
         1: aload_1
         2: invokestatic  #95                 // InterfaceMethod scala/PartialFunction.runWith$:(Lscala/PartialFunction;Lscala/Function1;)Lscala/Function1;
         5: areturn
      LineNumberTable:
        line 141: 0
      LocalVariableTable:
        Start  Length  Slot  Name   Signature
            0       6     0  this   Los/copy$$anon$2;
            0       6     1 action   Lscala/Function1;
    Signature: #90                          // <U:Ljava/lang/Object;>(Lscala/Function1<Lscala/runtime/BoxedUnit;TU;>;)Lscala/Function1<Los/Path;Ljava/lang/Object;>;
    MethodParameters:
      Name                           Flags
      action                         final

  public boolean apply$mcZD$sp(double);
    descriptor: (D)Z
    flags: (0x0001) ACC_PUBLIC
    Code:
      stack=3, locals=3, args_size=2
         0: aload_0
         1: dload_1
         2: invokestatic  #104                // InterfaceMethod scala/Function1.apply$mcZD$sp$:(Lscala/Function1;D)Z
         5: ireturn
      LineNumberTable:
        line 141: 0
      LocalVariableTable:
        Start  Length  Slot  Name   Signature
            0       6     0  this   Los/copy$$anon$2;
            0       6     1    v1   D
    MethodParameters:
      Name                           Flags
      v1                             final

  public double apply$mcDD$sp(double);
    descriptor: (D)D
    flags: (0x0001) ACC_PUBLIC
    Code:
      stack=3, locals=3, args_size=2
         0: aload_0
         1: dload_1
         2: invokestatic  #111                // InterfaceMethod scala/Function1.apply$mcDD$sp$:(Lscala/Function1;D)D
         5: dreturn
      LineNumberTable:
        line 141: 0
      LocalVariableTable:
        Start  Length  Slot  Name   Signature
            0       6     0  this   Los/copy$$anon$2;
            0       6     1    v1   D
    MethodParameters:
      Name                           Flags
      v1                             final

  public float apply$mcFD$sp(double);
    descriptor: (D)F
    flags: (0x0001) ACC_PUBLIC
    Code:
      stack=3, locals=3, args_size=2
         0: aload_0
         1: dload_1
         2: invokestatic  #117                // InterfaceMethod scala/Function1.apply$mcFD$sp$:(Lscala/Function1;D)F
         5: freturn
      LineNumberTable:
        line 141: 0
      LocalVariableTable:
        Start  Length  Slot  Name   Signature
            0       6     0  this   Los/copy$$anon$2;
            0       6     1    v1   D
    MethodParameters:
      Name                           Flags
      v1                             final

  public int apply$mcID$sp(double);
    descriptor: (D)I
    flags: (0x0001) ACC_PUBLIC
    Code:
      stack=3, locals=3, args_size=2
         0: aload_0
         1: dload_1
         2: invokestatic  #123                // InterfaceMethod scala/Function1.apply$mcID$sp$:(Lscala/Function1;D)I
         5: ireturn
      LineNumberTable:
        line 141: 0
      LocalVariableTable:
        Start  Length  Slot  Name   Signature
            0       6     0  this   Los/copy$$anon$2;
            0       6     1    v1   D
    MethodParameters:
      Name                           Flags
      v1                             final

  public long apply$mcJD$sp(double);
    descriptor: (D)J
    flags: (0x0001) ACC_PUBLIC
    Code:
      stack=3, locals=3, args_size=2
         0: aload_0
         1: dload_1
         2: invokestatic  #129                // InterfaceMethod scala/Function1.apply$mcJD$sp$:(Lscala/Function1;D)J
         5: lreturn
      LineNumberTable:
        line 141: 0
      LocalVariableTable:
        Start  Length  Slot  Name   Signature
            0       6     0  this   Los/copy$$anon$2;
            0       6     1    v1   D
    MethodParameters:
      Name                           Flags
      v1                             final

  public void apply$mcVD$sp(double);
    descriptor: (D)V
    flags: (0x0001) ACC_PUBLIC
    Code:
      stack=3, locals=3, args_size=2
         0: aload_0
         1: dload_1
         2: invokestatic  #135                // InterfaceMethod scala/Function1.apply$mcVD$sp$:(Lscala/Function1;D)V
         5: return
      LineNumberTable:
        line 141: 0
      LocalVariableTable:
        Start  Length  Slot  Name   Signature
            0       6     0  this   Los/copy$$anon$2;
            0       6     1    v1   D
    MethodParameters:
      Name                           Flags
      v1                             final

  public boolean apply$mcZF$sp(float);
    descriptor: (F)Z
    flags: (0x0001) ACC_PUBLIC
    Code:
      stack=2, locals=2, args_size=2
         0: aload_0
         1: fload_1
         2: invokestatic  #141                // InterfaceMethod scala/Function1.apply$mcZF$sp$:(Lscala/Function1;F)Z
         5: ireturn
      LineNumberTable:
        line 141: 0
      LocalVariableTable:
        Start  Length  Slot  Name   Signature
            0       6     0  this   Los/copy$$anon$2;
            0       6     1    v1   F
    MethodParameters:
      Name                           Flags
      v1                             final

  public double apply$mcDF$sp(float);
    descriptor: (F)D
    flags: (0x0001) ACC_PUBLIC
    Code:
      stack=2, locals=2, args_size=2
         0: aload_0
         1: fload_1
         2: invokestatic  #148                // InterfaceMethod scala/Function1.apply$mcDF$sp$:(Lscala/Function1;F)D
         5: dreturn
      LineNumberTable:
        line 141: 0
      LocalVariableTable:
        Start  Length  Slot  Name   Signature
            0       6     0  this   Los/copy$$anon$2;
            0       6     1    v1   F
    MethodParameters:
      Name                           Flags
      v1                             final

  public float apply$mcFF$sp(float);
    descriptor: (F)F
    flags: (0x0001) ACC_PUBLIC
    Code:
      stack=2, locals=2, args_size=2
         0: aload_0
         1: fload_1
         2: invokestatic  #154                // InterfaceMethod scala/Function1.apply$mcFF$sp$:(Lscala/Function1;F)F
         5: freturn
      LineNumberTable:
        line 141: 0
      LocalVariableTable:
        Start  Length  Slot  Name   Signature
            0       6     0  this   Los/copy$$anon$2;
            0       6     1    v1   F
    MethodParameters:
      Name                           Flags
      v1                             final

  public int apply$mcIF$sp(float);
    descriptor: (F)I
    flags: (0x0001) ACC_PUBLIC
    Code:
      stack=2, locals=2, args_size=2
         0: aload_0
         1: fload_1
         2: invokestatic  #160                // InterfaceMethod scala/Function1.apply$mcIF$sp$:(Lscala/Function1;F)I
         5: ireturn
      LineNumberTable:
        line 141: 0
      LocalVariableTable:
        Start  Length  Slot  Name   Signature
            0       6     0  this   Los/copy$$anon$2;
            0       6     1    v1   F
    MethodParameters:
      Name                           Flags
      v1                             final

  public long apply$mcJF$sp(float);
    descriptor: (F)J
    flags: (0x0001) ACC_PUBLIC
    Code:
      stack=2, locals=2, args_size=2
         0: aload_0
         1: fload_1
         2: invokestatic  #166                // InterfaceMethod scala/Function1.apply$mcJF$sp$:(Lscala/Function1;F)J
         5: lreturn
      LineNumberTable:
        line 141: 0
      LocalVariableTable:
        Start  Length  Slot  Name   Signature
            0       6     0  this   Los/copy$$anon$2;
            0       6     1    v1   F
    MethodParameters:
      Name                           Flags
      v1                             final

  public void apply$mcVF$sp(float);
    descriptor: (F)V
    flags: (0x0001) ACC_PUBLIC
    Code:
      stack=2, locals=2, args_size=2
         0: aload_0
         1: fload_1
         2: invokestatic  #172                // InterfaceMethod scala/Function1.apply$mcVF$sp$:(Lscala/Function1;F)V
         5: return
      LineNumberTable:
        line 141: 0
      LocalVariableTable:
        Start  Length  Slot  Name   Signature
            0       6     0  this   Los/copy$$anon$2;
            0       6     1    v1   F
    MethodParameters:
      Name                           Flags
      v1                             final

  public boolean apply$mcZI$sp(int);
    descriptor: (I)Z
    flags: (0x0001) ACC_PUBLIC
    Code:
      stack=2, locals=2, args_size=2
         0: aload_0
         1: iload_1
         2: invokestatic  #178                // InterfaceMethod scala/Function1.apply$mcZI$sp$:(Lscala/Function1;I)Z
         5: ireturn
      LineNumberTable:
        line 141: 0
      LocalVariableTable:
        Start  Length  Slot  Name   Signature
            0       6     0  this   Los/copy$$anon$2;
            0       6     1    v1   I
    MethodParameters:
      Name                           Flags
      v1                             final

  public double apply$mcDI$sp(int);
    descriptor: (I)D
    flags: (0x0001) ACC_PUBLIC
    Code:
      stack=2, locals=2, args_size=2
         0: aload_0
         1: iload_1
         2: invokestatic  #185                // InterfaceMethod scala/Function1.apply$mcDI$sp$:(Lscala/Function1;I)D
         5: dreturn
      LineNumberTable:
        line 141: 0
      LocalVariableTable:
        Start  Length  Slot  Name   Signature
            0       6     0  this   Los/copy$$anon$2;
            0       6     1    v1   I
    MethodParameters:
      Name                           Flags
      v1                             final

  public float apply$mcFI$sp(int);
    descriptor: (I)F
    flags: (0x0001) ACC_PUBLIC
    Code:
      stack=2, locals=2, args_size=2
         0: aload_0
         1: iload_1
         2: invokestatic  #191                // InterfaceMethod scala/Function1.apply$mcFI$sp$:(Lscala/Function1;I)F
         5: freturn
      LineNumberTable:
        line 141: 0
      LocalVariableTable:
        Start  Length  Slot  Name   Signature
            0       6     0  this   Los/copy$$anon$2;
            0       6     1    v1   I
    MethodParameters:
      Name                           Flags
      v1                             final

  public int apply$mcII$sp(int);
    descriptor: (I)I
    flags: (0x0001) ACC_PUBLIC
    Code:
      stack=2, locals=2, args_size=2
         0: aload_0
         1: iload_1
         2: invokestatic  #197                // InterfaceMethod scala/Function1.apply$mcII$sp$:(Lscala/Function1;I)I
         5: ireturn
      LineNumberTable:
        line 141: 0
      LocalVariableTable:
        Start  Length  Slot  Name   Signature
            0       6     0  this   Los/copy$$anon$2;
            0       6     1    v1   I
    MethodParameters:
      Name                           Flags
      v1                             final

  public long apply$mcJI$sp(int);
    descriptor: (I)J
    flags: (0x0001) ACC_PUBLIC
    Code:
      stack=2, locals=2, args_size=2
         0: aload_0
         1: iload_1
         2: invokestatic  #203                // InterfaceMethod scala/Function1.apply$mcJI$sp$:(Lscala/Function1;I)J
         5: lreturn
      LineNumberTable:
        line 141: 0
      LocalVariableTable:
        Start  Length  Slot  Name   Signature
            0       6     0  this   Los/copy$$anon$2;
            0       6     1    v1   I
    MethodParameters:
      Name                           Flags
      v1                             final

  public void apply$mcVI$sp(int);
    descriptor: (I)V
    flags: (0x0001) ACC_PUBLIC
    Code:
      stack=2, locals=2, args_size=2
         0: aload_0
         1: iload_1
         2: invokestatic  #209                // InterfaceMethod scala/Function1.apply$mcVI$sp$:(Lscala/Function1;I)V
         5: return
      LineNumberTable:
        line 141: 0
      LocalVariableTable:
        Start  Length  Slot  Name   Signature
            0       6     0  this   Los/copy$$anon$2;
            0       6     1    v1   I
    MethodParameters:
      Name                           Flags
      v1                             final

  public boolean apply$mcZJ$sp(long);
    descriptor: (J)Z
    flags: (0x0001) ACC_PUBLIC
    Code:
      stack=3, locals=3, args_size=2
         0: aload_0
         1: lload_1
         2: invokestatic  #215                // InterfaceMethod scala/Function1.apply$mcZJ$sp$:(Lscala/Function1;J)Z
         5: ireturn
      LineNumberTable:
        line 141: 0
      LocalVariableTable:
        Start  Length  Slot  Name   Signature
            0       6     0  this   Los/copy$$anon$2;
            0       6     1    v1   J
    MethodParameters:
      Name                           Flags
      v1                             final

  public double apply$mcDJ$sp(long);
    descriptor: (J)D
    flags: (0x0001) ACC_PUBLIC
    Code:
      stack=3, locals=3, args_size=2
         0: aload_0
         1: lload_1
         2: invokestatic  #222                // InterfaceMethod scala/Function1.apply$mcDJ$sp$:(Lscala/Function1;J)D
         5: dreturn
      LineNumberTable:
        line 141: 0
      LocalVariableTable:
        Start  Length  Slot  Name   Signature
            0       6     0  this   Los/copy$$anon$2;
            0       6     1    v1   J
    MethodParameters:
      Name                           Flags
      v1                             final

  public float apply$mcFJ$sp(long);
    descriptor: (J)F
    flags: (0x0001) ACC_PUBLIC
    Code:
      stack=3, locals=3, args_size=2
         0: aload_0
         1: lload_1
         2: invokestatic  #228                // InterfaceMethod scala/Function1.apply$mcFJ$sp$:(Lscala/Function1;J)F
         5: freturn
      LineNumberTable:
        line 141: 0
      LocalVariableTable:
        Start  Length  Slot  Name   Signature
            0       6     0  this   Los/copy$$anon$2;
            0       6     1    v1   J
    MethodParameters:
      Name                           Flags
      v1                             final

  public int apply$mcIJ$sp(long);
    descriptor: (J)I
    flags: (0x0001) ACC_PUBLIC
    Code:
      stack=3, locals=3, args_size=2
         0: aload_0
         1: lload_1
         2: invokestatic  #234                // InterfaceMethod scala/Function1.apply$mcIJ$sp$:(Lscala/Function1;J)I
         5: ireturn
      LineNumberTable:
        line 141: 0
      LocalVariableTable:
        Start  Length  Slot  Name   Signature
            0       6     0  this   Los/copy$$anon$2;
            0       6     1    v1   J
    MethodParameters:
      Name                           Flags
      v1                             final

  public long apply$mcJJ$sp(long);
    descriptor: (J)J
    flags: (0x0001) ACC_PUBLIC
    Code:
      stack=3, locals=3, args_size=2
         0: aload_0
         1: lload_1
         2: invokestatic  #240                // InterfaceMethod scala/Function1.apply$mcJJ$sp$:(Lscala/Function1;J)J
         5: lreturn
      LineNumberTable:
        line 141: 0
      LocalVariableTable:
        Start  Length  Slot  Name   Signature
            0       6     0  this   Los/copy$$anon$2;
            0       6     1    v1   J
    MethodParameters:
      Name                           Flags
      v1                             final

  public void apply$mcVJ$sp(long);
    descriptor: (J)V
    flags: (0x0001) ACC_PUBLIC
    Code:
      stack=3, locals=3, args_size=2
         0: aload_0
         1: lload_1
         2: invokestatic  #246                // InterfaceMethod scala/Function1.apply$mcVJ$sp$:(Lscala/Function1;J)V
         5: return
      LineNumberTable:
        line 141: 0
      LocalVariableTable:
        Start  Length  Slot  Name   Signature
            0       6     0  this   Los/copy$$anon$2;
            0       6     1    v1   J
    MethodParameters:
      Name                           Flags
      v1                             final

  public <A extends java.lang.Object> scala.Function1<A, scala.runtime.BoxedUnit> compose(scala.Function1<A, os.Path>);
    descriptor: (Lscala/Function1;)Lscala/Function1;
    flags: (0x0001) ACC_PUBLIC
    Code:
      stack=2, locals=2, args_size=2
         0: aload_0
         1: aload_1
         2: invokestatic  #251                // InterfaceMethod scala/Function1.compose$:(Lscala/Function1;Lscala/Function1;)Lscala/Function1;
         5: areturn
      LineNumberTable:
        line 141: 0
      LocalVariableTable:
        Start  Length  Slot  Name   Signature
            0       6     0  this   Los/copy$$anon$2;
            0       6     1     g   Lscala/Function1;
    Signature: #247                         // <A:Ljava/lang/Object;>(Lscala/Function1<TA;Los/Path;>;)Lscala/Function1<TA;Lscala/runtime/BoxedUnit;>;
    MethodParameters:
      Name                           Flags
      g                              final

  public java.lang.String toString();
    descriptor: ()Ljava/lang/String;
    flags: (0x0001) ACC_PUBLIC
    Code:
      stack=1, locals=1, args_size=1
         0: aload_0
         1: invokestatic  #257                // InterfaceMethod scala/Function1.toString$:(Lscala/Function1;)Ljava/lang/String;
         4: areturn
      LineNumberTable:
        line 141: 0
      LocalVariableTable:
        Start  Length  Slot  Name   Signature
            0       5     0  this   Los/copy$$anon$2;

  public boolean isDefinedAt(os.Path);
    descriptor: (Los/Path;)Z
    flags: (0x0001) ACC_PUBLIC
    Code:
      stack=2, locals=2, args_size=2
         0: aload_0
         1: getfield      #261                // Field partialFunction$2:Lscala/PartialFunction;
         4: aload_1
         5: invokeinterface #264,  2          // InterfaceMethod scala/PartialFunction.isDefinedAt:(Ljava/lang/Object;)Z
        10: ireturn
      LineNumberTable:
        line 142: 0
      LocalVariableTable:
        Start  Length  Slot  Name   Signature
            0      11     0  this   Los/copy$$anon$2;
            0      11     1     x   Los/Path;
    MethodParameters:
      Name                           Flags
      x                              final

  public void apply(os.Path);
    descriptor: (Los/Path;)V
    flags: (0x0001) ACC_PUBLIC
    Code:
      stack=8, locals=3, args_size=2
         0: aload_0
         1: getfield      #261                // Field partialFunction$2:Lscala/PartialFunction;
         4: aload_1
         5: invokeinterface #271,  2          // InterfaceMethod scala/PartialFunction.apply:(Ljava/lang/Object;)Ljava/lang/Object;
        10: checkcast     #273                // class os/Path
        13: astore_2
        14: getstatic     #277                // Field os/makeDir$all$.MODULE$:Los/makeDir$all$;
        17: aload_2
        18: getstatic     #282                // Field os/PathChunk$.MODULE$:Los/PathChunk$;
        21: getstatic     #287                // Field os/package$.MODULE$:Los/package$;
        24: invokevirtual #291                // Method os/package$.up:()Los/RelPath;
        27: invokevirtual #294                // Method os/PathChunk$.RelPathChunk:(Los/RelPath;)Los/PathChunk$RelPathChunk;
        30: invokevirtual #298                // Method os/Path.$div:(Los/PathChunk;)Los/Path;
        33: invokevirtual #300                // Method os/makeDir$all$.apply:(Los/Path;)V
        36: getstatic     #303                // Field os/copy$.MODULE$:Los/copy$;
        39: aload_1
        40: aload_2
        41: aload_0
        42: getfield      #305                // Field followLinks$1:Z
        45: aload_0
        46: getfield      #307                // Field replaceExisting$2:Z
        49: aload_0
        50: getfield      #309                // Field copyAttributes$1:Z
        53: aload_0
        54: getfield      #311                // Field createFolders$2:Z
        57: aload_0
        58: getfield      #313                // Field mergeFolders$1:Z
        61: invokevirtual #316                // Method os/copy$.apply:(Los/Path;Los/Path;ZZZZZ)V
        64: return
      LineNumberTable:
        line 144: 0
        line 145: 14
        line 146: 36
        line 147: 39
      LocalVariableTable:
        Start  Length  Slot  Name   Signature
           14      50     2  dest   Los/Path;
            0      65     0  this   Los/copy$$anon$2;
            0      65     1  from   Los/Path;
    MethodParameters:
      Name                           Flags
      from                           final

  public scala.Function1 andThen(scala.Function1);
    descriptor: (Lscala/Function1;)Lscala/Function1;
    flags: (0x1041) ACC_PUBLIC, ACC_BRIDGE, ACC_SYNTHETIC
    Code:
      stack=2, locals=2, args_size=2
         0: aload_0
         1: aload_1
         2: invokevirtual #319                // Method andThen:(Lscala/Function1;)Lscala/PartialFunction;
         5: areturn
      LineNumberTable:
        line 141: 0
      LocalVariableTable:
        Start  Length  Slot  Name   Signature
            0       6     0  this   Los/copy$$anon$2;
            0       6     1     g   Lscala/Function1;
    MethodParameters:
      Name                           Flags
      g                              final

  public java.lang.Object apply(java.lang.Object);
    descriptor: (Ljava/lang/Object;)Ljava/lang/Object;
    flags: (0x1041) ACC_PUBLIC, ACC_BRIDGE, ACC_SYNTHETIC
    Code:
      stack=2, locals=2, args_size=2
         0: aload_0
         1: aload_1
         2: checkcast     #273                // class os/Path
         5: invokevirtual #320                // Method apply:(Los/Path;)V
         8: getstatic     #326                // Field scala/runtime/BoxedUnit.UNIT:Lscala/runtime/BoxedUnit;
        11: areturn
      LineNumberTable:
        line 141: 0
      LocalVariableTable:
        Start  Length  Slot  Name   Signature
            0      12     0  this   Los/copy$$anon$2;
            0      12     1    v1   Ljava/lang/Object;
    MethodParameters:
      Name                           Flags
      v1                             final

  public boolean isDefinedAt(java.lang.Object);
    descriptor: (Ljava/lang/Object;)Z
    flags: (0x1041) ACC_PUBLIC, ACC_BRIDGE, ACC_SYNTHETIC
    Code:
      stack=2, locals=2, args_size=2
         0: aload_0
         1: aload_1
         2: checkcast     #273                // class os/Path
         5: invokevirtual #328                // Method isDefinedAt:(Los/Path;)Z
         8: ireturn
      LineNumberTable:
        line 141: 0
      LocalVariableTable:
        Start  Length  Slot  Name   Signature
            0       9     0  this   Los/copy$$anon$2;
            0       9     1     x   Ljava/lang/Object;
    MethodParameters:
      Name                           Flags
      x                              final

  public os.copy$$anon$2(scala.PartialFunction, boolean, boolean, boolean, boolean, boolean);
    descriptor: (Lscala/PartialFunction;ZZZZZ)V
    flags: (0x0001) ACC_PUBLIC
    Code:
      stack=2, locals=7, args_size=7
         0: aload_0
         1: aload_1
         2: putfield      #261                // Field partialFunction$2:Lscala/PartialFunction;
         5: aload_0
         6: iload_2
         7: putfield      #305                // Field followLinks$1:Z
        10: aload_0
        11: iload_3
        12: putfield      #307                // Field replaceExisting$2:Z
        15: aload_0
        16: iload         4
        18: putfield      #309                // Field copyAttributes$1:Z
        21: aload_0
        22: iload         5
        24: putfield      #311                // Field createFolders$2:Z
        27: aload_0
        28: iload         6
        30: putfield      #313                // Field mergeFolders$1:Z
        33: aload_0
        34: invokespecial #333                // Method java/lang/Object."<init>":()V
        37: aload_0
        38: invokestatic  #337                // InterfaceMethod scala/Function1.$init$:(Lscala/Function1;)V
        41: aload_0
        42: invokestatic  #340                // InterfaceMethod scala/PartialFunction.$init$:(Lscala/PartialFunction;)V
        45: return
      LineNumberTable:
        line 140: 0
        line 135: 5
        line 136: 10
        line 137: 15
        line 138: 21
        line 139: 27
        line 141: 33
      LocalVariableTable:
        Start  Length  Slot  Name   Signature
            0      46     0  this   Los/copy$$anon$2;
            0      46     1 partialFunction$2   Lscala/PartialFunction;
            0      46     2 followLinks$1   Z
            0      46     3 replaceExisting$2   Z
            0      46     4 copyAttributes$1   Z
            0      46     5 createFolders$2   Z
            0      46     6 mergeFolders$1   Z
    MethodParameters:
      Name                           Flags
      partialFunction$2              final
      followLinks$1                  final
      replaceExisting$2              final
      copyAttributes$1               final
      createFolders$2                final
      mergeFolders$1                 final
}
InnerClasses:
  public static #18= #15 of #17;          // RelPathChunk=class os/PathChunk$RelPathChunk of class os/PathChunk
  public final #2;                        // class os/copy$$anon$2
  public static #23= #20 of #22;          // all$=class os/makeDir$all$ of class os/makeDir
EnclosingMethod: #10.#13                // os.copy$.matching
Signature: #3                           // Ljava/lang/Object;Lscala/PartialFunction<Los/Path;Lscala/runtime/BoxedUnit;>;
SourceFile: "FileOps.scala"
  ScalaInlineInfo: length = 0xD1 (unknown attribute)
   01 01 00 29 01 49 01 4A 01 00 38 00 59 01 00 38
   00 39 01 00 38 00 2E 01 01 0A 01 0D 01 01 0A 01
   0B 01 00 6A 00 6B 01 00 8F 00 90 01 00 B4 00 B5
   01 00 D9 00 DA 01 00 70 00 71 01 00 95 00 96 01
   00 BA 00 BB 01 00 DF 00 E0 01 00 76 00 77 01 00
   9B 00 9C 01 00 C0 00 C1 01 00 E5 00 E6 01 00 7C
   00 7D 01 00 A1 00 A2 01 00 C6 00 C7 01 00 EB 00
   EC 01 00 82 00 83 01 00 A7 00 A8 01 00 CC 00 CD
   01 00 F1 00 F2 01 00 60 00 61 01 00 88 00 89 01
   00 AD 00 AE 01 00 D2 00 D3 01 00 50 00 51 01 00
   44 00 59 01 00 44 00 2E 01 00 2A 00 2B 01 01 02
   01 06 01 01 02 01 03 01 00 49 00 4A 01 00 31 00
   2E 01 00 58 00 59 01 00 FC 00 FD 01 00 20 00 21
   01
  Scala: length = 0x0 (unknown attribute)

