Classfile /Users/mw/Projects/slang-braindump/.jar/jar8/assemble/slang-braindump/assemble/content/os/followLink.class
  Last modified May 29, 2022; size 1147 bytes
  SHA-256 checksum 863a55824b7047fd5f76e5cea9ef18b2f79133a3964a07566d3580f91a0e54c2
  Compiled from "FileOps.scala"
public final class os.followLink
  minor version: 0
  major version: 52
  flags: (0x0031) ACC_PUBLIC, ACC_FINAL, ACC_SUPER
  this_class: #2                          // os/followLink
  super_class: #4                         // java/lang/Object
  interfaces: 0, fields: 0, methods: 4, attributes: 3
Constant pool:
   #1 = Utf8               os/followLink
   #2 = Class              #1             // os/followLink
   #3 = Utf8               java/lang/Object
   #4 = Class              #3             // java/lang/Object
   #5 = Utf8               FileOps.scala
   #6 = Utf8               Lscala/reflect/ScalaSignature;
   #7 = Utf8               bytes
   #8 = Utf8               \u0006\u0005\u0005:Q\u0001B\u0003\t\u0002!1QAC\u0003\t\u0002-AQaG\u0001\u0005\u0002qAQ!H\u0001\u0005\u0002y\t!BZ8mY><H*\u001b8l\u0015\u00051\u0011AA8t\u0007\u0001\u0001\"!C\u0001\u000e\u0003\u0015\u0011!BZ8mY><H*\u001b8l\'\r\tAB\u0005\t\u0003\u001bAi\u0011A\u0004\u0006\u0002\u001f\u0005)1oY1mC&\u0011\u0011C\u0004\u0002\u0007\u0003:L(+\u001a4\u0011\t5\u0019R\u0003G\u0005\u0003)9\u0011\u0011BR;oGRLwN\\\u0019\u0011\u0005%1\u0012BA\f\u0006\u0005\u0011\u0001\u0016\r\u001e5\u0011\u00075IR#\u0003\u0002\u001b\u001d\t1q\n\u001d;j_:\fa\u0001P5oSRtD#\u0001\u0005\u0002\u000b\u0005\u0004\b\u000f\\=\u0015\u0005ay\u0002\"\u0002\u0011\u0004\u0001\u0004)\u0012aA:sG\u0002
   #9 = Utf8               apply
  #10 = Utf8               (Los/Path;)Lscala/Option;
  #11 = Utf8               (Los/Path;)Lscala/Option<Los/Path;>;
  #12 = Utf8               src
  #13 = Utf8               os/followLink$
  #14 = Class              #13            // os/followLink$
  #15 = Utf8               MODULE$
  #16 = Utf8               Los/followLink$;
  #17 = NameAndType        #15:#16        // MODULE$:Los/followLink$;
  #18 = Fieldref           #14.#17        // os/followLink$.MODULE$:Los/followLink$;
  #19 = NameAndType        #9:#10         // apply:(Los/Path;)Lscala/Option;
  #20 = Methodref          #14.#19        // os/followLink$.apply:(Los/Path;)Lscala/Option;
  #21 = Utf8               toString
  #22 = Utf8               ()Ljava/lang/String;
  #23 = NameAndType        #21:#22        // toString:()Ljava/lang/String;
  #24 = Methodref          #14.#23        // os/followLink$.toString:()Ljava/lang/String;
  #25 = Utf8               andThen
  #26 = Utf8               (Lscala/Function1;)Lscala/Function1;
  #27 = Utf8               <A:Ljava/lang/Object;>(Lscala/Function1<Lscala/Option<Los/Path;>;TA;>;)Lscala/Function1<Los/Path;TA;>;
  #28 = Utf8               g
  #29 = NameAndType        #25:#26        // andThen:(Lscala/Function1;)Lscala/Function1;
  #30 = Methodref          #14.#29        // os/followLink$.andThen:(Lscala/Function1;)Lscala/Function1;
  #31 = Utf8               compose
  #32 = Utf8               <A:Ljava/lang/Object;>(Lscala/Function1<TA;Los/Path;>;)Lscala/Function1<TA;Lscala/Option<Los/Path;>;>;
  #33 = NameAndType        #31:#26        // compose:(Lscala/Function1;)Lscala/Function1;
  #34 = Methodref          #14.#33        // os/followLink$.compose:(Lscala/Function1;)Lscala/Function1;
  #35 = Utf8               Code
  #36 = Utf8               Signature
  #37 = Utf8               MethodParameters
  #38 = Utf8               SourceFile
  #39 = Utf8               RuntimeVisibleAnnotations
  #40 = Utf8               ScalaSig
{
  public static scala.Option<os.Path> apply(os.Path);
    descriptor: (Los/Path;)Lscala/Option;
    flags: (0x0009) ACC_PUBLIC, ACC_STATIC
    Code:
      stack=2, locals=1, args_size=1
         0: getstatic     #18                 // Field os/followLink$.MODULE$:Los/followLink$;
         3: aload_0
         4: invokevirtual #20                 // Method os/followLink$.apply:(Los/Path;)Lscala/Option;
         7: areturn
    Signature: #11                          // (Los/Path;)Lscala/Option<Los/Path;>;
    MethodParameters:
      Name                           Flags
      src                            final

  public static java.lang.String toString();
    descriptor: ()Ljava/lang/String;
    flags: (0x0009) ACC_PUBLIC, ACC_STATIC
    Code:
      stack=1, locals=0, args_size=0
         0: getstatic     #18                 // Field os/followLink$.MODULE$:Los/followLink$;
         3: invokevirtual #24                 // Method os/followLink$.toString:()Ljava/lang/String;
         6: areturn

  public static <A extends java.lang.Object> scala.Function1<os.Path, A> andThen(scala.Function1<scala.Option<os.Path>, A>);
    descriptor: (Lscala/Function1;)Lscala/Function1;
    flags: (0x0009) ACC_PUBLIC, ACC_STATIC
    Code:
      stack=2, locals=1, args_size=1
         0: getstatic     #18                 // Field os/followLink$.MODULE$:Los/followLink$;
         3: aload_0
         4: invokevirtual #30                 // Method os/followLink$.andThen:(Lscala/Function1;)Lscala/Function1;
         7: areturn
    Signature: #27                          // <A:Ljava/lang/Object;>(Lscala/Function1<Lscala/Option<Los/Path;>;TA;>;)Lscala/Function1<Los/Path;TA;>;
    MethodParameters:
      Name                           Flags
      g                              final

  public static <A extends java.lang.Object> scala.Function1<A, scala.Option<os.Path>> compose(scala.Function1<A, os.Path>);
    descriptor: (Lscala/Function1;)Lscala/Function1;
    flags: (0x0009) ACC_PUBLIC, ACC_STATIC
    Code:
      stack=2, locals=1, args_size=1
         0: getstatic     #18                 // Field os/followLink$.MODULE$:Los/followLink$;
         3: aload_0
         4: invokevirtual #34                 // Method os/followLink$.compose:(Lscala/Function1;)Lscala/Function1;
         7: areturn
    Signature: #32                          // <A:Ljava/lang/Object;>(Lscala/Function1<TA;Los/Path;>;)Lscala/Function1<TA;Lscala/Option<Los/Path;>;>;
    MethodParameters:
      Name                           Flags
      g                              final
}
SourceFile: "FileOps.scala"
RuntimeVisibleAnnotations:
  0: #6(#7=s#8)
    scala.reflect.ScalaSignature(
      bytes="\u0006\u0005\u0005:Q\u0001B\u0003\t\u0002!1QAC\u0003\t\u0002-AQaG\u0001\u0005\u0002qAQ!H\u0001\u0005\u0002y\t!BZ8mY><H*\u001b8l\u0015\u00051\u0011AA8t\u0007\u0001\u0001\"!C\u0001\u000e\u0003\u0015\u0011!BZ8mY><H*\u001b8l\'\r\tAB\u0005\t\u0003\u001bAi\u0011A\u0004\u0006\u0002\u001f\u0005)1oY1mC&\u0011\u0011C\u0004\u0002\u0007\u0003:L(+\u001a4\u0011\t5\u0019R\u0003G\u0005\u0003)9\u0011\u0011BR;oGRLwN\\\u0019\u0011\u0005%1\u0012BA\f\u0006\u0005\u0011\u0001\u0016\r\u001e5\u0011\u00075IR#\u0003\u0002\u001b\u001d\t1q\n\u001d;j_:\fa\u0001P5oSRtD#\u0001\u0005\u0002\u000b\u0005\u0004\b\u000f\\=\u0015\u0005ay\u0002\"\u0002\u0011\u0004\u0001\u0004)\u0012aA:sG\u0002"
    )
  ScalaSig: length = 0x3 (unknown attribute)
   05 02 00
