Classfile /Users/mw/Projects/slang-braindump/.jar/jar8/assemble/slang-braindump/assemble/content/os/group$set$.class
  Last modified May 29, 2022; size 1735 bytes
  SHA-256 checksum b128383377ae0a8bf7a116571dad813dc07ba53190042db10e735229d889db1a
  Compiled from "PermsOps.scala"
public class os.group$set$
  minor version: 0
  major version: 52
  flags: (0x0021) ACC_PUBLIC, ACC_SUPER
  this_class: #2                          // os/group$set$
  super_class: #4                         // java/lang/Object
  interfaces: 0, fields: 1, methods: 4, attributes: 4
Constant pool:
   #1 = Utf8               os/group$set$
   #2 = Class              #1             // os/group$set$
   #3 = Utf8               java/lang/Object
   #4 = Class              #3             // java/lang/Object
   #5 = Utf8               PermsOps.scala
   #6 = Utf8               os/group
   #7 = Class              #6             // os/group
   #8 = Utf8               set$
   #9 = Utf8               MODULE$
  #10 = Utf8               Los/group$set$;
  #11 = Utf8               <clinit>
  #12 = Utf8               ()V
  #13 = Utf8               <init>
  #14 = NameAndType        #13:#12        // "<init>":()V
  #15 = Methodref          #2.#14         // os/group$set$."<init>":()V
  #16 = NameAndType        #9:#10         // MODULE$:Los/group$set$;
  #17 = Fieldref           #2.#16         // os/group$set$.MODULE$:Los/group$set$;
  #18 = Utf8               apply
  #19 = Utf8               (Los/Path;Ljava/nio/file/attribute/GroupPrincipal;)V
  #20 = Utf8               arg1
  #21 = Utf8               arg2
  #22 = Utf8               os/Path
  #23 = Class              #22            // os/Path
  #24 = Utf8               wrapped
  #25 = Utf8               ()Ljava/nio/file/Path;
  #26 = NameAndType        #24:#25        // wrapped:()Ljava/nio/file/Path;
  #27 = Methodref          #23.#26        // os/Path.wrapped:()Ljava/nio/file/Path;
  #28 = Utf8               java/nio/file/attribute/PosixFileAttributeView
  #29 = Class              #28            // java/nio/file/attribute/PosixFileAttributeView
  #30 = Utf8               java/nio/file/LinkOption
  #31 = Class              #30            // java/nio/file/LinkOption
  #32 = Utf8               NOFOLLOW_LINKS
  #33 = Utf8               Ljava/nio/file/LinkOption;
  #34 = NameAndType        #32:#33        // NOFOLLOW_LINKS:Ljava/nio/file/LinkOption;
  #35 = Fieldref           #31.#34        // java/nio/file/LinkOption.NOFOLLOW_LINKS:Ljava/nio/file/LinkOption;
  #36 = Utf8               java/nio/file/Files
  #37 = Class              #36            // java/nio/file/Files
  #38 = Utf8               getFileAttributeView
  #39 = Utf8               (Ljava/nio/file/Path;Ljava/lang/Class;[Ljava/nio/file/LinkOption;)Ljava/nio/file/attribute/FileAttributeView;
  #40 = NameAndType        #38:#39        // getFileAttributeView:(Ljava/nio/file/Path;Ljava/lang/Class;[Ljava/nio/file/LinkOption;)Ljava/nio/file/attribute/FileAttributeView;
  #41 = Methodref          #37.#40        // java/nio/file/Files.getFileAttributeView:(Ljava/nio/file/Path;Ljava/lang/Class;[Ljava/nio/file/LinkOption;)Ljava/nio/file/attribute/FileAttributeView;
  #42 = Utf8               setGroup
  #43 = Utf8               (Ljava/nio/file/attribute/GroupPrincipal;)V
  #44 = NameAndType        #42:#43        // setGroup:(Ljava/nio/file/attribute/GroupPrincipal;)V
  #45 = InterfaceMethodref #29.#44        // java/nio/file/attribute/PosixFileAttributeView.setGroup:(Ljava/nio/file/attribute/GroupPrincipal;)V
  #46 = Utf8               this
  #47 = Utf8               Los/Path;
  #48 = Utf8               Ljava/nio/file/attribute/GroupPrincipal;
  #49 = Utf8               (Los/Path;Ljava/lang/String;)V
  #50 = Utf8               java/nio/file/Path
  #51 = Class              #50            // java/nio/file/Path
  #52 = Utf8               getFileSystem
  #53 = Utf8               ()Ljava/nio/file/FileSystem;
  #54 = NameAndType        #52:#53        // getFileSystem:()Ljava/nio/file/FileSystem;
  #55 = InterfaceMethodref #51.#54        // java/nio/file/Path.getFileSystem:()Ljava/nio/file/FileSystem;
  #56 = Utf8               java/nio/file/FileSystem
  #57 = Class              #56            // java/nio/file/FileSystem
  #58 = Utf8               getUserPrincipalLookupService
  #59 = Utf8               ()Ljava/nio/file/attribute/UserPrincipalLookupService;
  #60 = NameAndType        #58:#59        // getUserPrincipalLookupService:()Ljava/nio/file/attribute/UserPrincipalLookupService;
  #61 = Methodref          #57.#60        // java/nio/file/FileSystem.getUserPrincipalLookupService:()Ljava/nio/file/attribute/UserPrincipalLookupService;
  #62 = Utf8               java/nio/file/attribute/UserPrincipalLookupService
  #63 = Class              #62            // java/nio/file/attribute/UserPrincipalLookupService
  #64 = Utf8               lookupPrincipalByGroupName
  #65 = Utf8               (Ljava/lang/String;)Ljava/nio/file/attribute/GroupPrincipal;
  #66 = NameAndType        #64:#65        // lookupPrincipalByGroupName:(Ljava/lang/String;)Ljava/nio/file/attribute/GroupPrincipal;
  #67 = Methodref          #63.#66        // java/nio/file/attribute/UserPrincipalLookupService.lookupPrincipalByGroupName:(Ljava/lang/String;)Ljava/nio/file/attribute/GroupPrincipal;
  #68 = NameAndType        #18:#19        // apply:(Los/Path;Ljava/nio/file/attribute/GroupPrincipal;)V
  #69 = Methodref          #2.#68         // os/group$set$.apply:(Los/Path;Ljava/nio/file/attribute/GroupPrincipal;)V
  #70 = Utf8               Ljava/lang/String;
  #71 = Methodref          #4.#14         // java/lang/Object."<init>":()V
  #72 = Utf8               Code
  #73 = Utf8               LineNumberTable
  #74 = Utf8               LocalVariableTable
  #75 = Utf8               MethodParameters
  #76 = Utf8               InnerClasses
  #77 = Utf8               SourceFile
  #78 = Utf8               ScalaInlineInfo
  #79 = Utf8               Scala
{
  public static final os.group$set$ MODULE$;
    descriptor: Los/group$set$;
    flags: (0x0019) ACC_PUBLIC, ACC_STATIC, ACC_FINAL

  public static {};
    descriptor: ()V
    flags: (0x0009) ACC_PUBLIC, ACC_STATIC
    Code:
      stack=2, locals=0, args_size=0
         0: new           #2                  // class os/group$set$
         3: dup
         4: invokespecial #15                 // Method "<init>":()V
         7: putstatic     #17                 // Field MODULE$:Los/group$set$;
        10: return
      LineNumberTable:
        line 75: 0

  public void apply(os.Path, java.nio.file.attribute.GroupPrincipal);
    descriptor: (Los/Path;Ljava/nio/file/attribute/GroupPrincipal;)V
    flags: (0x0001) ACC_PUBLIC
    Code:
      stack=6, locals=3, args_size=3
         0: aload_1
         1: invokevirtual #27                 // Method os/Path.wrapped:()Ljava/nio/file/Path;
         4: ldc           #29                 // class java/nio/file/attribute/PosixFileAttributeView
         6: iconst_1
         7: anewarray     #31                 // class java/nio/file/LinkOption
        10: dup
        11: iconst_0
        12: getstatic     #35                 // Field java/nio/file/LinkOption.NOFOLLOW_LINKS:Ljava/nio/file/LinkOption;
        15: aastore
        16: invokestatic  #41                 // Method java/nio/file/Files.getFileAttributeView:(Ljava/nio/file/Path;Ljava/lang/Class;[Ljava/nio/file/LinkOption;)Ljava/nio/file/attribute/FileAttributeView;
        19: checkcast     #29                 // class java/nio/file/attribute/PosixFileAttributeView
        22: aload_2
        23: invokeinterface #45,  2           // InterfaceMethod java/nio/file/attribute/PosixFileAttributeView.setGroup:(Ljava/nio/file/attribute/GroupPrincipal;)V
        28: return
      LineNumberTable:
        line 78: 0
        line 79: 4
        line 80: 12
        line 81: 22
      LocalVariableTable:
        Start  Length  Slot  Name   Signature
            0      29     0  this   Los/group$set$;
            0      29     1  arg1   Los/Path;
            0      29     2  arg2   Ljava/nio/file/attribute/GroupPrincipal;
    MethodParameters:
      Name                           Flags
      arg1                           final
      arg2                           final

  public void apply(os.Path, java.lang.String);
    descriptor: (Los/Path;Ljava/lang/String;)V
    flags: (0x0001) ACC_PUBLIC
    Code:
      stack=4, locals=3, args_size=3
         0: aload_0
         1: aload_1
         2: aload_1
         3: invokevirtual #27                 // Method os/Path.wrapped:()Ljava/nio/file/Path;
         6: invokeinterface #55,  1           // InterfaceMethod java/nio/file/Path.getFileSystem:()Ljava/nio/file/FileSystem;
        11: invokevirtual #61                 // Method java/nio/file/FileSystem.getUserPrincipalLookupService:()Ljava/nio/file/attribute/UserPrincipalLookupService;
        14: aload_2
        15: invokevirtual #67                 // Method java/nio/file/attribute/UserPrincipalLookupService.lookupPrincipalByGroupName:(Ljava/lang/String;)Ljava/nio/file/attribute/GroupPrincipal;
        18: invokevirtual #69                 // Method apply:(Los/Path;Ljava/nio/file/attribute/GroupPrincipal;)V
        21: return
      LineNumberTable:
        line 84: 0
        line 85: 1
        line 86: 2
      LocalVariableTable:
        Start  Length  Slot  Name   Signature
            0      22     0  this   Los/group$set$;
            0      22     1  arg1   Los/Path;
            0      22     2  arg2   Ljava/lang/String;
    MethodParameters:
      Name                           Flags
      arg1                           final
      arg2                           final

  public os.group$set$();
    descriptor: ()V
    flags: (0x0001) ACC_PUBLIC
    Code:
      stack=1, locals=1, args_size=1
         0: aload_0
         1: invokespecial #71                 // Method java/lang/Object."<init>":()V
         4: return
      LineNumberTable:
        line 90: 0
        line 75: 4
      LocalVariableTable:
        Start  Length  Slot  Name   Signature
            0       5     0  this   Los/group$set$;
}
InnerClasses:
  public static #8= #2 of #7;             // set$=class os/group$set$ of class os/group
SourceFile: "PermsOps.scala"
  ScalaInlineInfo: length = 0x13 (unknown attribute)
   01 01 00 03 00 0D 00 0C 01 00 12 00 31 01 00 12
   00 13 01
  Scala: length = 0x0 (unknown attribute)

