Classfile /Users/mw/Projects/slang-braindump/.jar/jar8/assemble/slang-braindump/assemble/content/os/hardlink$.class
  Last modified May 29, 2022; size 776 bytes
  SHA-256 checksum d2296198211c20988c34d1823a1b7402ee6b7df3863a3e715b80a000bc4c4df2
  Compiled from "FileOps.scala"
public final class os.hardlink$
  minor version: 0
  major version: 52
  flags: (0x0031) ACC_PUBLIC, ACC_FINAL, ACC_SUPER
  this_class: #2                          // os/hardlink$
  super_class: #4                         // java/lang/Object
  interfaces: 0, fields: 1, methods: 3, attributes: 3
Constant pool:
   #1 = Utf8               os/hardlink$
   #2 = Class              #1             // os/hardlink$
   #3 = Utf8               java/lang/Object
   #4 = Class              #3             // java/lang/Object
   #5 = Utf8               FileOps.scala
   #6 = Utf8               MODULE$
   #7 = Utf8               Los/hardlink$;
   #8 = Utf8               <clinit>
   #9 = Utf8               ()V
  #10 = Utf8               <init>
  #11 = NameAndType        #10:#9         // "<init>":()V
  #12 = Methodref          #2.#11         // os/hardlink$."<init>":()V
  #13 = NameAndType        #6:#7          // MODULE$:Los/hardlink$;
  #14 = Fieldref           #2.#13         // os/hardlink$.MODULE$:Los/hardlink$;
  #15 = Utf8               apply
  #16 = Utf8               (Los/Path;Los/Path;)Ljava/nio/file/Path;
  #17 = Utf8               link
  #18 = Utf8               dest
  #19 = Utf8               os/Path
  #20 = Class              #19            // os/Path
  #21 = Utf8               wrapped
  #22 = Utf8               ()Ljava/nio/file/Path;
  #23 = NameAndType        #21:#22        // wrapped:()Ljava/nio/file/Path;
  #24 = Methodref          #20.#23        // os/Path.wrapped:()Ljava/nio/file/Path;
  #25 = Utf8               java/nio/file/Files
  #26 = Class              #25            // java/nio/file/Files
  #27 = Utf8               createLink
  #28 = Utf8               (Ljava/nio/file/Path;Ljava/nio/file/Path;)Ljava/nio/file/Path;
  #29 = NameAndType        #27:#28        // createLink:(Ljava/nio/file/Path;Ljava/nio/file/Path;)Ljava/nio/file/Path;
  #30 = Methodref          #26.#29        // java/nio/file/Files.createLink:(Ljava/nio/file/Path;Ljava/nio/file/Path;)Ljava/nio/file/Path;
  #31 = Utf8               this
  #32 = Utf8               Los/Path;
  #33 = Methodref          #4.#11         // java/lang/Object."<init>":()V
  #34 = Utf8               Code
  #35 = Utf8               LineNumberTable
  #36 = Utf8               LocalVariableTable
  #37 = Utf8               MethodParameters
  #38 = Utf8               SourceFile
  #39 = Utf8               ScalaInlineInfo
  #40 = Utf8               Scala
{
  public static final os.hardlink$ MODULE$;
    descriptor: Los/hardlink$;
    flags: (0x0019) ACC_PUBLIC, ACC_STATIC, ACC_FINAL

  public static {};
    descriptor: ()V
    flags: (0x0009) ACC_PUBLIC, ACC_STATIC
    Code:
      stack=2, locals=0, args_size=0
         0: new           #2                  // class os/hardlink$
         3: dup
         4: invokespecial #12                 // Method "<init>":()V
         7: putstatic     #14                 // Field MODULE$:Los/hardlink$;
        10: return
      LineNumberTable:
        line 323: 0

  public java.nio.file.Path apply(os.Path, os.Path);
    descriptor: (Los/Path;Los/Path;)Ljava/nio/file/Path;
    flags: (0x0001) ACC_PUBLIC
    Code:
      stack=2, locals=3, args_size=3
         0: aload_1
         1: invokevirtual #24                 // Method os/Path.wrapped:()Ljava/nio/file/Path;
         4: aload_2
         5: invokevirtual #24                 // Method os/Path.wrapped:()Ljava/nio/file/Path;
         8: invokestatic  #30                 // Method java/nio/file/Files.createLink:(Ljava/nio/file/Path;Ljava/nio/file/Path;)Ljava/nio/file/Path;
        11: areturn
      LineNumberTable:
        line 325: 0
      LocalVariableTable:
        Start  Length  Slot  Name   Signature
            0      12     0  this   Los/hardlink$;
            0      12     1  link   Los/Path;
            0      12     2  dest   Los/Path;
    MethodParameters:
      Name                           Flags
      link                           final
      dest                           final

  private os.hardlink$();
    descriptor: ()V
    flags: (0x0002) ACC_PRIVATE
    Code:
      stack=1, locals=1, args_size=1
         0: aload_0
         1: invokespecial #33                 // Method java/lang/Object."<init>":()V
         4: return
      LineNumberTable:
        line 332: 0
        line 323: 4
      LocalVariableTable:
        Start  Length  Slot  Name   Signature
            0       5     0  this   Los/hardlink$;
}
SourceFile: "FileOps.scala"
  ScalaInlineInfo: length = 0xE (unknown attribute)
   01 01 00 02 00 0A 00 09 01 00 0F 00 10 01
  Scala: length = 0x0 (unknown attribute)

