Classfile /Users/mw/Projects/slang-braindump/.jar/jar8/assemble/slang-braindump/assemble/content/os/Internals$.class
  Last modified May 29, 2022; size 3260 bytes
  SHA-256 checksum 3e881af14cc72ac008a600dcaa1ff1016ab89c9deb22c3f4f62744325d0f3245
  Compiled from "Internals.scala"
public final class os.Internals$
  minor version: 0
  major version: 52
  flags: (0x0031) ACC_PUBLIC, ACC_FINAL, ACC_SUPER
  this_class: #2                          // os/Internals$
  super_class: #4                         // java/lang/Object
  interfaces: 0, fields: 2, methods: 8, attributes: 5
Constant pool:
    #1 = Utf8               os/Internals$
    #2 = Class              #1            // os/Internals$
    #3 = Utf8               java/lang/Object
    #4 = Class              #3            // java/lang/Object
    #5 = Utf8               Internals.scala
    #6 = Utf8               java/lang/invoke/MethodHandles$Lookup
    #7 = Class              #6            // java/lang/invoke/MethodHandles$Lookup
    #8 = Utf8               java/lang/invoke/MethodHandles
    #9 = Class              #8            // java/lang/invoke/MethodHandles
   #10 = Utf8               Lookup
   #11 = Utf8               MODULE$
   #12 = Utf8               Los/Internals$;
   #13 = Utf8               emptyStringArray
   #14 = Utf8               [Ljava/lang/String;
   #15 = Utf8               <clinit>
   #16 = Utf8               ()V
   #17 = Utf8               <init>
   #18 = NameAndType        #17:#16       // "<init>":()V
   #19 = Methodref          #2.#18        // os/Internals$."<init>":()V
   #20 = NameAndType        #11:#12       // MODULE$:Los/Internals$;
   #21 = Fieldref           #2.#20        // os/Internals$.MODULE$:Los/Internals$;
   #22 = Utf8               scala/Array$
   #23 = Class              #22           // scala/Array$
   #24 = Utf8               Lscala/Array$;
   #25 = NameAndType        #11:#24       // MODULE$:Lscala/Array$;
   #26 = Fieldref           #23.#25       // scala/Array$.MODULE$:Lscala/Array$;
   #27 = Utf8               scala/reflect/ClassTag$
   #28 = Class              #27           // scala/reflect/ClassTag$
   #29 = Utf8               Lscala/reflect/ClassTag$;
   #30 = NameAndType        #11:#29       // MODULE$:Lscala/reflect/ClassTag$;
   #31 = Fieldref           #28.#30       // scala/reflect/ClassTag$.MODULE$:Lscala/reflect/ClassTag$;
   #32 = Utf8               java/lang/String
   #33 = Class              #32           // java/lang/String
   #34 = Utf8               apply
   #35 = Utf8               (Ljava/lang/Class;)Lscala/reflect/ClassTag;
   #36 = NameAndType        #34:#35       // apply:(Ljava/lang/Class;)Lscala/reflect/ClassTag;
   #37 = Methodref          #28.#36       // scala/reflect/ClassTag$.apply:(Ljava/lang/Class;)Lscala/reflect/ClassTag;
   #38 = Utf8               empty
   #39 = Utf8               (Lscala/reflect/ClassTag;)Ljava/lang/Object;
   #40 = NameAndType        #38:#39       // empty:(Lscala/reflect/ClassTag;)Ljava/lang/Object;
   #41 = Methodref          #23.#40       // scala/Array$.empty:(Lscala/reflect/ClassTag;)Ljava/lang/Object;
   #42 = Class              #14           // "[Ljava/lang/String;"
   #43 = NameAndType        #13:#14       // emptyStringArray:[Ljava/lang/String;
   #44 = Fieldref           #2.#43        // os/Internals$.emptyStringArray:[Ljava/lang/String;
   #45 = Utf8               ()[Ljava/lang/String;
   #46 = Utf8               this
   #47 = Utf8               transfer0
   #48 = Utf8               (Ljava/io/InputStream;Lscala/Function2;)V
   #49 = Utf8               (Ljava/io/InputStream;Lscala/Function2<[BLjava/lang/Object;Lscala/runtime/BoxedUnit;>;)V
   #50 = Utf8               src
   #51 = Utf8               sink
   #52 = Utf8               java/io/InputStream
   #53 = Class              #52           // java/io/InputStream
   #54 = Utf8               read
   #55 = Utf8               ([B)I
   #56 = NameAndType        #54:#55       // read:([B)I
   #57 = Methodref          #53.#56       // java/io/InputStream.read:([B)I
   #58 = Utf8               scala/runtime/BoxesRunTime
   #59 = Class              #58           // scala/runtime/BoxesRunTime
   #60 = Utf8               boxToInteger
   #61 = Utf8               (I)Ljava/lang/Integer;
   #62 = NameAndType        #60:#61       // boxToInteger:(I)Ljava/lang/Integer;
   #63 = Methodref          #59.#62       // scala/runtime/BoxesRunTime.boxToInteger:(I)Ljava/lang/Integer;
   #64 = Utf8               scala/Function2
   #65 = Class              #64           // scala/Function2
   #66 = Utf8               (Ljava/lang/Object;Ljava/lang/Object;)Ljava/lang/Object;
   #67 = NameAndType        #34:#66       // apply:(Ljava/lang/Object;Ljava/lang/Object;)Ljava/lang/Object;
   #68 = InterfaceMethodref #65.#67       // scala/Function2.apply:(Ljava/lang/Object;Ljava/lang/Object;)Ljava/lang/Object;
   #69 = Utf8               scala/runtime/BoxedUnit
   #70 = Class              #69           // scala/runtime/BoxedUnit
   #71 = Utf8               UNIT
   #72 = Utf8               Lscala/runtime/BoxedUnit;
   #73 = NameAndType        #71:#72       // UNIT:Lscala/runtime/BoxedUnit;
   #74 = Fieldref           #70.#73       // scala/runtime/BoxedUnit.UNIT:Lscala/runtime/BoxedUnit;
   #75 = Utf8               close
   #76 = NameAndType        #75:#16       // close:()V
   #77 = Methodref          #53.#76       // java/io/InputStream.close:()V
   #78 = Utf8               buffer
   #79 = Utf8               [B
   #80 = Utf8               r
   #81 = Utf8               I
   #82 = Utf8               Ljava/io/InputStream;
   #83 = Utf8               Lscala/Function2;
   #84 = Class              #79           // "[B"
   #85 = Utf8               transfer
   #86 = Utf8               (Ljava/io/InputStream;Ljava/io/OutputStream;)V
   #87 = Utf8               dest
   #88 = MethodType         #66           //  (Ljava/lang/Object;Ljava/lang/Object;)Ljava/lang/Object;
   #89 = Utf8               $anonfun$transfer$1$adapted
   #90 = Utf8               (Ljava/io/OutputStream;[BLjava/lang/Object;)Ljava/lang/Object;
   #91 = NameAndType        #89:#90       // $anonfun$transfer$1$adapted:(Ljava/io/OutputStream;[BLjava/lang/Object;)Ljava/lang/Object;
   #92 = Methodref          #2.#91        // os/Internals$.$anonfun$transfer$1$adapted:(Ljava/io/OutputStream;[BLjava/lang/Object;)Ljava/lang/Object;
   #93 = MethodHandle       6:#92         // REF_invokeStatic os/Internals$.$anonfun$transfer$1$adapted:(Ljava/io/OutputStream;[BLjava/lang/Object;)Ljava/lang/Object;
   #94 = Utf8               ([BLjava/lang/Object;)Ljava/lang/Object;
   #95 = MethodType         #94           //  ([BLjava/lang/Object;)Ljava/lang/Object;
   #96 = Integer            5
   #97 = Integer            1
   #98 = Utf8               java/lang/invoke/LambdaMetafactory
   #99 = Class              #98           // java/lang/invoke/LambdaMetafactory
  #100 = Utf8               altMetafactory
  #101 = Utf8               (Ljava/lang/invoke/MethodHandles$Lookup;Ljava/lang/String;Ljava/lang/invoke/MethodType;[Ljava/lang/Object;)Ljava/lang/invoke/CallSite;
  #102 = NameAndType        #100:#101     // altMetafactory:(Ljava/lang/invoke/MethodHandles$Lookup;Ljava/lang/String;Ljava/lang/invoke/MethodType;[Ljava/lang/Object;)Ljava/lang/invoke/CallSite;
  #103 = Methodref          #99.#102      // java/lang/invoke/LambdaMetafactory.altMetafactory:(Ljava/lang/invoke/MethodHandles$Lookup;Ljava/lang/String;Ljava/lang/invoke/MethodType;[Ljava/lang/Object;)Ljava/lang/invoke/CallSite;
  #104 = MethodHandle       6:#103        // REF_invokeStatic java/lang/invoke/LambdaMetafactory.altMetafactory:(Ljava/lang/invoke/MethodHandles$Lookup;Ljava/lang/String;Ljava/lang/invoke/MethodType;[Ljava/lang/Object;)Ljava/lang/invoke/CallSite;
  #105 = Utf8               (Ljava/io/OutputStream;)Lscala/Function2;
  #106 = NameAndType        #34:#105      // apply:(Ljava/io/OutputStream;)Lscala/Function2;
  #107 = InvokeDynamic      #0:#106       // #0:apply:(Ljava/io/OutputStream;)Lscala/Function2;
  #108 = NameAndType        #47:#48       // transfer0:(Ljava/io/InputStream;Lscala/Function2;)V
  #109 = Methodref          #2.#108       // os/Internals$.transfer0:(Ljava/io/InputStream;Lscala/Function2;)V
  #110 = Utf8               Ljava/io/OutputStream;
  #111 = Utf8               $anonfun$transfer$1
  #112 = Utf8               (Ljava/io/OutputStream;[BI)V
  #113 = Utf8               dest$1
  #114 = Utf8               x$1
  #115 = Utf8               x$2
  #116 = Utf8               java/io/OutputStream
  #117 = Class              #116          // java/io/OutputStream
  #118 = Utf8               write
  #119 = Utf8               ([BII)V
  #120 = NameAndType        #118:#119     // write:([BII)V
  #121 = Methodref          #117.#120     // java/io/OutputStream.write:([BII)V
  #122 = Methodref          #4.#18        // java/lang/Object."<init>":()V
  #123 = Utf8               unboxToInt
  #124 = Utf8               (Ljava/lang/Object;)I
  #125 = NameAndType        #123:#124     // unboxToInt:(Ljava/lang/Object;)I
  #126 = Methodref          #59.#125      // scala/runtime/BoxesRunTime.unboxToInt:(Ljava/lang/Object;)I
  #127 = NameAndType        #111:#112     // $anonfun$transfer$1:(Ljava/io/OutputStream;[BI)V
  #128 = Methodref          #2.#127       // os/Internals$.$anonfun$transfer$1:(Ljava/io/OutputStream;[BI)V
  #129 = Utf8               Ljava/lang/Object;
  #130 = Utf8               $deserializeLambda$
  #131 = Utf8               (Ljava/lang/invoke/SerializedLambda;)Ljava/lang/Object;
  #132 = Utf8               scala/runtime/LambdaDeserialize
  #133 = Class              #132          // scala/runtime/LambdaDeserialize
  #134 = Utf8               bootstrap
  #135 = Utf8               (Ljava/lang/invoke/MethodHandles$Lookup;Ljava/lang/String;Ljava/lang/invoke/MethodType;[Ljava/lang/invoke/MethodHandle;)Ljava/lang/invoke/CallSite;
  #136 = NameAndType        #134:#135     // bootstrap:(Ljava/lang/invoke/MethodHandles$Lookup;Ljava/lang/String;Ljava/lang/invoke/MethodType;[Ljava/lang/invoke/MethodHandle;)Ljava/lang/invoke/CallSite;
  #137 = Methodref          #133.#136     // scala/runtime/LambdaDeserialize.bootstrap:(Ljava/lang/invoke/MethodHandles$Lookup;Ljava/lang/String;Ljava/lang/invoke/MethodType;[Ljava/lang/invoke/MethodHandle;)Ljava/lang/invoke/CallSite;
  #138 = MethodHandle       6:#137        // REF_invokeStatic scala/runtime/LambdaDeserialize.bootstrap:(Ljava/lang/invoke/MethodHandles$Lookup;Ljava/lang/String;Ljava/lang/invoke/MethodType;[Ljava/lang/invoke/MethodHandle;)Ljava/lang/invoke/CallSite;
  #139 = Utf8               lambdaDeserialize
  #140 = NameAndType        #139:#131     // lambdaDeserialize:(Ljava/lang/invoke/SerializedLambda;)Ljava/lang/Object;
  #141 = InvokeDynamic      #1:#140       // #1:lambdaDeserialize:(Ljava/lang/invoke/SerializedLambda;)Ljava/lang/Object;
  #142 = Utf8               Code
  #143 = Utf8               LineNumberTable
  #144 = Utf8               LocalVariableTable
  #145 = Utf8               StackMapTable
  #146 = Utf8               Signature
  #147 = Utf8               MethodParameters
  #148 = Utf8               InnerClasses
  #149 = Utf8               SourceFile
  #150 = Utf8               BootstrapMethods
  #151 = Utf8               ScalaInlineInfo
  #152 = Utf8               Scala
{
  public static final os.Internals$ MODULE$;
    descriptor: Los/Internals$;
    flags: (0x0019) ACC_PUBLIC, ACC_STATIC, ACC_FINAL

  private static final java.lang.String[] emptyStringArray;
    descriptor: [Ljava/lang/String;
    flags: (0x001a) ACC_PRIVATE, ACC_STATIC, ACC_FINAL

  public static {};
    descriptor: ()V
    flags: (0x0009) ACC_PUBLIC, ACC_STATIC
    Code:
      stack=3, locals=0, args_size=0
         0: new           #2                  // class os/Internals$
         3: dup
         4: invokespecial #19                 // Method "<init>":()V
         7: putstatic     #21                 // Field MODULE$:Los/Internals$;
        10: getstatic     #26                 // Field scala/Array$.MODULE$:Lscala/Array$;
        13: getstatic     #31                 // Field scala/reflect/ClassTag$.MODULE$:Lscala/reflect/ClassTag$;
        16: ldc           #33                 // class java/lang/String
        18: invokevirtual #37                 // Method scala/reflect/ClassTag$.apply:(Ljava/lang/Class;)Lscala/reflect/ClassTag;
        21: invokevirtual #41                 // Method scala/Array$.empty:(Lscala/reflect/ClassTag;)Ljava/lang/Object;
        24: checkcast     #42                 // class "[Ljava/lang/String;"
        27: putstatic     #44                 // Field emptyStringArray:[Ljava/lang/String;
        30: return
      LineNumberTable:
        line 6: 0
        line 8: 10
        line 6: 30

  public java.lang.String[] emptyStringArray();
    descriptor: ()[Ljava/lang/String;
    flags: (0x0001) ACC_PUBLIC
    Code:
      stack=1, locals=1, args_size=1
         0: getstatic     #44                 // Field emptyStringArray:[Ljava/lang/String;
         3: areturn
      LineNumberTable:
        line 8: 0
      LocalVariableTable:
        Start  Length  Slot  Name   Signature
            0       4     0  this   Los/Internals$;

  public void transfer0(java.io.InputStream, scala.Function2<byte[], java.lang.Object, scala.runtime.BoxedUnit>);
    descriptor: (Ljava/io/InputStream;Lscala/Function2;)V
    flags: (0x0001) ACC_PUBLIC
    Code:
      stack=3, locals=5, args_size=3
         0: sipush        8192
         3: newarray       byte
         5: astore_3
         6: iconst_0
         7: istore        4
         9: iload         4
        11: iconst_m1
        12: if_icmpeq     50
        15: aload_1
        16: aload_3
        17: invokevirtual #57                 // Method java/io/InputStream.read:([B)I
        20: istore        4
        22: iload         4
        24: iconst_m1
        25: if_icmpeq     43
        28: aload_2
        29: aload_3
        30: iload         4
        32: invokestatic  #63                 // Method scala/runtime/BoxesRunTime.boxToInteger:(I)Ljava/lang/Integer;
        35: invokeinterface #68,  3           // InterfaceMethod scala/Function2.apply:(Ljava/lang/Object;Ljava/lang/Object;)Ljava/lang/Object;
        40: goto          46
        43: getstatic     #74                 // Field scala/runtime/BoxedUnit.UNIT:Lscala/runtime/BoxedUnit;
        46: pop
        47: goto          9
        50: aload_1
        51: invokevirtual #77                 // Method java/io/InputStream.close:()V
        54: return
      StackMapTable: number_of_entries = 4
        frame_type = 253 /* append */
          offset_delta = 9
          locals = [ class "[B", int ]
        frame_type = 33 /* same */
        frame_type = 66 /* same_locals_1_stack_item */
          stack = [ class java/lang/Object ]
        frame_type = 3 /* same */
      LineNumberTable:
        line 12: 0
        line 13: 6
        line 14: 9
        line 15: 15
        line 16: 22
        line 14: 47
        line 18: 50
      LocalVariableTable:
        Start  Length  Slot  Name   Signature
            6      48     3 buffer   [B
            9      45     4     r   I
            0      55     0  this   Los/Internals$;
            0      55     1   src   Ljava/io/InputStream;
            0      55     2  sink   Lscala/Function2;
    Signature: #49                          // (Ljava/io/InputStream;Lscala/Function2<[BLjava/lang/Object;Lscala/runtime/BoxedUnit;>;)V
    MethodParameters:
      Name                           Flags
      src                            final
      sink                           final

  public void transfer(java.io.InputStream, java.io.OutputStream);
    descriptor: (Ljava/io/InputStream;Ljava/io/OutputStream;)V
    flags: (0x0001) ACC_PUBLIC
    Code:
      stack=3, locals=3, args_size=3
         0: aload_0
         1: aload_1
         2: aload_2
         3: invokedynamic #107,  0            // InvokeDynamic #0:apply:(Ljava/io/OutputStream;)Lscala/Function2;
         8: invokevirtual #109                // Method transfer0:(Ljava/io/InputStream;Lscala/Function2;)V
        11: return
      LineNumberTable:
        line 21: 0
        line 22: 1
        line 23: 2
      LocalVariableTable:
        Start  Length  Slot  Name   Signature
            0      12     0  this   Los/Internals$;
            0      12     1   src   Ljava/io/InputStream;
            0      12     2  dest   Ljava/io/OutputStream;
    MethodParameters:
      Name                           Flags
      src                            final
      dest                           final

  public static final void $anonfun$transfer$1(java.io.OutputStream, byte[], int);
    descriptor: (Ljava/io/OutputStream;[BI)V
    flags: (0x1019) ACC_PUBLIC, ACC_STATIC, ACC_FINAL, ACC_SYNTHETIC
    Code:
      stack=4, locals=3, args_size=3
         0: aload_0
         1: aload_1
         2: iconst_0
         3: iload_2
         4: invokevirtual #121                // Method java/io/OutputStream.write:([BII)V
         7: return
      LineNumberTable:
        line 23: 0
      LocalVariableTable:
        Start  Length  Slot  Name   Signature
            0       8     0 dest$1   Ljava/io/OutputStream;
            0       8     1   x$1   [B
            0       8     2   x$2   I
    MethodParameters:
      Name                           Flags
      dest$1                         final
      x$1                            final
      x$2                            final

  private os.Internals$();
    descriptor: ()V
    flags: (0x0002) ACC_PRIVATE
    Code:
      stack=1, locals=1, args_size=1
         0: aload_0
         1: invokespecial #122                // Method java/lang/Object."<init>":()V
         4: return
      LineNumberTable:
        line 25: 0
        line 6: 4
      LocalVariableTable:
        Start  Length  Slot  Name   Signature
            0       5     0  this   Los/Internals$;

  public static final java.lang.Object $anonfun$transfer$1$adapted(java.io.OutputStream, byte[], java.lang.Object);
    descriptor: (Ljava/io/OutputStream;[BLjava/lang/Object;)Ljava/lang/Object;
    flags: (0x1019) ACC_PUBLIC, ACC_STATIC, ACC_FINAL, ACC_SYNTHETIC
    Code:
      stack=3, locals=3, args_size=3
         0: aload_0
         1: aload_1
         2: aload_2
         3: invokestatic  #126                // Method scala/runtime/BoxesRunTime.unboxToInt:(Ljava/lang/Object;)I
         6: invokestatic  #128                // Method $anonfun$transfer$1:(Ljava/io/OutputStream;[BI)V
         9: getstatic     #74                 // Field scala/runtime/BoxedUnit.UNIT:Lscala/runtime/BoxedUnit;
        12: areturn
      LineNumberTable:
        line 23: 0
      LocalVariableTable:
        Start  Length  Slot  Name   Signature
            0      13     0 dest$1   Ljava/io/OutputStream;
            0      13     1   x$1   [B
            0      13     2   x$2   Ljava/lang/Object;
    MethodParameters:
      Name                           Flags
      dest$1                         final
      x$1                            final
      x$2                            final

  private static java.lang.Object $deserializeLambda$(java.lang.invoke.SerializedLambda);
    descriptor: (Ljava/lang/invoke/SerializedLambda;)Ljava/lang/Object;
    flags: (0x100a) ACC_PRIVATE, ACC_STATIC, ACC_SYNTHETIC
    Code:
      stack=1, locals=1, args_size=1
         0: aload_0
         1: invokedynamic #141,  0            // InvokeDynamic #1:lambdaDeserialize:(Ljava/lang/invoke/SerializedLambda;)Ljava/lang/Object;
         6: areturn
}
InnerClasses:
  public static final #10= #7 of #9;      // Lookup=class java/lang/invoke/MethodHandles$Lookup of class java/lang/invoke/MethodHandles
SourceFile: "Internals.scala"
BootstrapMethods:
  0: #104 REF_invokeStatic java/lang/invoke/LambdaMetafactory.altMetafactory:(Ljava/lang/invoke/MethodHandles$Lookup;Ljava/lang/String;Ljava/lang/invoke/MethodType;[Ljava/lang/Object;)Ljava/lang/invoke/CallSite;
    Method arguments:
      #88 (Ljava/lang/Object;Ljava/lang/Object;)Ljava/lang/Object;
      #93 REF_invokeStatic os/Internals$.$anonfun$transfer$1$adapted:(Ljava/io/OutputStream;[BLjava/lang/Object;)Ljava/lang/Object;
      #95 ([BLjava/lang/Object;)Ljava/lang/Object;
      #96 5
      #97 1
      #95 ([BLjava/lang/Object;)Ljava/lang/Object;
  1: #138 REF_invokeStatic scala/runtime/LambdaDeserialize.bootstrap:(Ljava/lang/invoke/MethodHandles$Lookup;Ljava/lang/String;Ljava/lang/invoke/MethodType;[Ljava/lang/invoke/MethodHandle;)Ljava/lang/invoke/CallSite;
    Method arguments:
      #93 REF_invokeStatic os/Internals$.$anonfun$transfer$1$adapted:(Ljava/io/OutputStream;[BLjava/lang/Object;)Ljava/lang/Object;
  ScalaInlineInfo: length = 0x22 (unknown attribute)
   01 01 00 06 00 6F 00 70 01 00 59 00 5A 01 00 11
   00 10 01 00 0D 00 2D 01 00 55 00 56 01 00 2F 00
   30 01
  Scala: length = 0x0 (unknown attribute)

