Classfile /Users/mw/Projects/slang-braindump/.jar/jar8/assemble/slang-braindump/assemble/content/os/move.class
  Last modified May 29, 2022; size 2432 bytes
  SHA-256 checksum 9ea6332a86f057bce3d9aa9487286b9a1216ef7fe8cdb7fa8f758538ca36920d
  Compiled from "FileOps.scala"
public final class os.move
  minor version: 0
  major version: 52
  flags: (0x0031) ACC_PUBLIC, ACC_FINAL, ACC_SUPER
  this_class: #2                          // os/move
  super_class: #4                         // java/lang/Object
  interfaces: 0, fields: 0, methods: 9, attributes: 4
Constant pool:
   #1 = Utf8               os/move
   #2 = Class              #1             // os/move
   #3 = Utf8               java/lang/Object
   #4 = Class              #3             // java/lang/Object
   #5 = Utf8               FileOps.scala
   #6 = Utf8               Lscala/reflect/ScalaSignature;
   #7 = Utf8               bytes
   #8 = Utf8               \u0006\u0005U<QAG\u000e\t\u0002y1Q\u0001I\u000e\t\u0002\u0005BQ\u0001K\u0001\u0005\u0002%BQAK\u0001\u0005\u0002-BqAQ\u0001\u0012\u0002\u0013\u00051\tC\u0004O\u0003E\u0005I\u0011A\"\t\u000f=\u000b\u0011\u0013!C\u0001\u0007\")!&\u0001C\u0001!\")!+\u0001C\u0001\'\"91,AI\u0001\n\u0003\u0019\u0005b\u0002/\u0002#\u0003%\ta\u0011\u0005\b;\u0006\t\n\u0011\"\u0001D\u000f\u0015q\u0016\u0001#\u0001`\r\u0015\t\u0017\u0001#\u0001c\u0011\u0015AS\u0002\"\u0001d\u0011\u0015\u0011V\u0002\"\u0001e\u0011\u001dYV\"%A\u0005\u0002\rCq\u0001X\u0007\u0012\u0002\u0013\u00051\tC\u0004^\u001bE\u0005I\u0011A\"\b\u000b)\f\u0001\u0012A6\u0007\u000b1\f\u0001\u0012A7\t\u000b!\"B\u0011\u00018\t\u000bI#B\u0011A8\t\u000fm#\u0012\u0013!C\u0001\u0007\"9A\fFI\u0001\n\u0003\u0019\u0005bB/\u0015#\u0003%\taQ\u0001\u0005[>4XMC\u0001\u001d\u0003\ty7o\u0001\u0001\u0011\u0005}\tQ\"A\u000e\u0003\t5|g/Z\n\u0003\u0003\t\u0002\"a\t\u0014\u000e\u0003\u0011R\u0011!J\u0001\u0006g\u000e\fG.Y\u0005\u0003O\u0011\u0012a!\u00118z%\u00164\u0017A\u0002\u001fj]&$h\bF\u0001\u001f\u0003!i\u0017\r^2iS:<G\u0003\u0002\u0017:}\u0001#\"!\f\u001c\u0011\t\rr\u0003gM\u0005\u0003_\u0011\u0012q\u0002U1si&\fGNR;oGRLwN\u001c\t\u0003?EJ!AM\u000e\u0003\tA\u000bG\u000f\u001b\t\u0003GQJ!!\u000e\u0013\u0003\tUs\u0017\u000e\u001e\u0005\u0006o\r\u0001\r\u0001O\u0001\u0010a\u0006\u0014H/[1m\rVt7\r^5p]B!1E\f\u00191\u0011\u001dQ4\u0001%AA\u0002m\nqB]3qY\u0006\u001cW-\u0012=jgRLgn\u001a\t\u0003GqJ!!\u0010\u0013\u0003\u000f\t{w\u000e\\3b]\"9qh\u0001I\u0001\u0002\u0004Y\u0014AC1u_6L7-T8wK\"9\u0011i\u0001I\u0001\u0002\u0004Y\u0014!D2sK\u0006$XMR8mI\u0016\u00148/\u0001\nnCR\u001c\u0007.\u001b8hI\u0011,g-Y;mi\u0012\nT#\u0001#+\u0005m*5&\u0001$\u0011\u0005\u001dcU\"\u0001%\u000b\u0005%S\u0015!C;oG\",7m[3e\u0015\tYE%\u0001\u0006b]:|G/\u0019;j_:L!!\u0014%\u0003#Ut7\r[3dW\u0016$g+\u0019:jC:\u001cW-\u0001\nnCR\u001c\u0007.\u001b8hI\u0011,g-Y;mi\u0012\u0012\u0014AE7bi\u000eD\u0017N\\4%I\u00164\u0017-\u001e7uIM\"\"!L)\t\u000b]:\u0001\u0019\u0001\u001d\u0002\u000b\u0005\u0004\b\u000f\\=\u0015\rM\"f\u000bW-[\u0011\u0015)\u0006\u00021\u00011\u0003\u00111\'o\\7\t\u000b]C\u0001\u0019\u0001\u0019\u0002\u0005Q|\u0007b\u0002\u001e\t!\u0003\u0005\ra\u000f\u0005\b\u007f!\u0001\n\u00111\u0001<\u0011\u001d\t\u0005\u0002%AA\u0002m\nq\"\u00199qYf$C-\u001a4bk2$HeM\u0001\u0010CB\u0004H.\u001f\u0013eK\u001a\fW\u000f\u001c;%i\u0005y\u0011\r\u001d9ms\u0012\"WMZ1vYR$S\'\u0001\u0003j]R|\u0007C\u00011\u000e\u001b\u0005\t!\u0001B5oi>\u001c\"!\u0004\u0012\u0015\u0003}#baM3gO\"L\u0007\"B+\u0010\u0001\u0004\u0001\u0004\"B,\u0010\u0001\u0004\u0001\u0004b\u0002\u001e\u0010!\u0003\u0005\ra\u000f\u0005\b\u007f=\u0001\n\u00111\u0001<\u0011\u001d\tu\u0002%AA\u0002m\nAa\u001c<feB\u0011\u0001\r\u0006\u0002\u0005_Z,\'o\u0005\u0002\u0015EQ\t1\u000e\u0006\u00044aF\u00148\u000f\u001e\u0005\u0006+Z\u0001\r\u0001\r\u0005\u0006/Z\u0001\r\u0001\r\u0005\buY\u0001\n\u00111\u0001<\u0011\u001dyd\u0003%AA\u0002mBq!\u0011\f\u0011\u0002\u0003\u00071\b
   #9 = Utf8               os/move$into$
  #10 = Class              #9             // os/move$into$
  #11 = Utf8               into$
  #12 = Utf8               os/move$over$
  #13 = Class              #12            // os/move$over$
  #14 = Utf8               over$
  #15 = Utf8               apply$default$5
  #16 = Utf8               ()Z
  #17 = Utf8               os/move$
  #18 = Class              #17            // os/move$
  #19 = Utf8               MODULE$
  #20 = Utf8               Los/move$;
  #21 = NameAndType        #19:#20        // MODULE$:Los/move$;
  #22 = Fieldref           #18.#21        // os/move$.MODULE$:Los/move$;
  #23 = NameAndType        #15:#16        // apply$default$5:()Z
  #24 = Methodref          #18.#23        // os/move$.apply$default$5:()Z
  #25 = Utf8               apply$default$4
  #26 = NameAndType        #25:#16        // apply$default$4:()Z
  #27 = Methodref          #18.#26        // os/move$.apply$default$4:()Z
  #28 = Utf8               apply$default$3
  #29 = NameAndType        #28:#16        // apply$default$3:()Z
  #30 = Methodref          #18.#29        // os/move$.apply$default$3:()Z
  #31 = Utf8               apply
  #32 = Utf8               (Los/Path;Los/Path;ZZZ)V
  #33 = Utf8               from
  #34 = Utf8               to
  #35 = Utf8               replaceExisting
  #36 = Utf8               atomicMove
  #37 = Utf8               createFolders
  #38 = NameAndType        #31:#32        // apply:(Los/Path;Los/Path;ZZZ)V
  #39 = Methodref          #18.#38        // os/move$.apply:(Los/Path;Los/Path;ZZZ)V
  #40 = Utf8               matching
  #41 = Utf8               (Lscala/PartialFunction;)Lscala/PartialFunction;
  #42 = Utf8               (Lscala/PartialFunction<Los/Path;Los/Path;>;)Lscala/PartialFunction<Los/Path;Lscala/runtime/BoxedUnit;>;
  #43 = Utf8               partialFunction
  #44 = NameAndType        #40:#41        // matching:(Lscala/PartialFunction;)Lscala/PartialFunction;
  #45 = Methodref          #18.#44        // os/move$.matching:(Lscala/PartialFunction;)Lscala/PartialFunction;
  #46 = Utf8               matching$default$3
  #47 = NameAndType        #46:#16        // matching$default$3:()Z
  #48 = Methodref          #18.#47        // os/move$.matching$default$3:()Z
  #49 = Utf8               matching$default$2
  #50 = NameAndType        #49:#16        // matching$default$2:()Z
  #51 = Methodref          #18.#50        // os/move$.matching$default$2:()Z
  #52 = Utf8               matching$default$1
  #53 = NameAndType        #52:#16        // matching$default$1:()Z
  #54 = Methodref          #18.#53        // os/move$.matching$default$1:()Z
  #55 = Utf8               (ZZZLscala/PartialFunction;)Lscala/PartialFunction;
  #56 = Utf8               (ZZZLscala/PartialFunction<Los/Path;Los/Path;>;)Lscala/PartialFunction<Los/Path;Lscala/runtime/BoxedUnit;>;
  #57 = NameAndType        #40:#55        // matching:(ZZZLscala/PartialFunction;)Lscala/PartialFunction;
  #58 = Methodref          #18.#57        // os/move$.matching:(ZZZLscala/PartialFunction;)Lscala/PartialFunction;
  #59 = Utf8               Code
  #60 = Utf8               MethodParameters
  #61 = Utf8               Signature
  #62 = Utf8               InnerClasses
  #63 = Utf8               SourceFile
  #64 = Utf8               RuntimeVisibleAnnotations
  #65 = Utf8               ScalaSig
{
  public static boolean apply$default$5();
    descriptor: ()Z
    flags: (0x0009) ACC_PUBLIC, ACC_STATIC
    Code:
      stack=1, locals=0, args_size=0
         0: getstatic     #22                 // Field os/move$.MODULE$:Los/move$;
         3: invokevirtual #24                 // Method os/move$.apply$default$5:()Z
         6: ireturn

  public static boolean apply$default$4();
    descriptor: ()Z
    flags: (0x0009) ACC_PUBLIC, ACC_STATIC
    Code:
      stack=1, locals=0, args_size=0
         0: getstatic     #22                 // Field os/move$.MODULE$:Los/move$;
         3: invokevirtual #27                 // Method os/move$.apply$default$4:()Z
         6: ireturn

  public static boolean apply$default$3();
    descriptor: ()Z
    flags: (0x0009) ACC_PUBLIC, ACC_STATIC
    Code:
      stack=1, locals=0, args_size=0
         0: getstatic     #22                 // Field os/move$.MODULE$:Los/move$;
         3: invokevirtual #30                 // Method os/move$.apply$default$3:()Z
         6: ireturn

  public static void apply(os.Path, os.Path, boolean, boolean, boolean);
    descriptor: (Los/Path;Los/Path;ZZZ)V
    flags: (0x0009) ACC_PUBLIC, ACC_STATIC
    Code:
      stack=6, locals=5, args_size=5
         0: getstatic     #22                 // Field os/move$.MODULE$:Los/move$;
         3: aload_0
         4: aload_1
         5: iload_2
         6: iload_3
         7: iload         4
         9: invokevirtual #39                 // Method os/move$.apply:(Los/Path;Los/Path;ZZZ)V
        12: return
    MethodParameters:
      Name                           Flags
      from                           final
      to                             final
      replaceExisting                final
      atomicMove                     final
      createFolders                  final

  public static scala.PartialFunction<os.Path, scala.runtime.BoxedUnit> matching(scala.PartialFunction<os.Path, os.Path>);
    descriptor: (Lscala/PartialFunction;)Lscala/PartialFunction;
    flags: (0x0009) ACC_PUBLIC, ACC_STATIC
    Code:
      stack=2, locals=1, args_size=1
         0: getstatic     #22                 // Field os/move$.MODULE$:Los/move$;
         3: aload_0
         4: invokevirtual #45                 // Method os/move$.matching:(Lscala/PartialFunction;)Lscala/PartialFunction;
         7: areturn
    Signature: #42                          // (Lscala/PartialFunction<Los/Path;Los/Path;>;)Lscala/PartialFunction<Los/Path;Lscala/runtime/BoxedUnit;>;
    MethodParameters:
      Name                           Flags
      partialFunction                final

  public static boolean matching$default$3();
    descriptor: ()Z
    flags: (0x0009) ACC_PUBLIC, ACC_STATIC
    Code:
      stack=1, locals=0, args_size=0
         0: getstatic     #22                 // Field os/move$.MODULE$:Los/move$;
         3: invokevirtual #48                 // Method os/move$.matching$default$3:()Z
         6: ireturn

  public static boolean matching$default$2();
    descriptor: ()Z
    flags: (0x0009) ACC_PUBLIC, ACC_STATIC
    Code:
      stack=1, locals=0, args_size=0
         0: getstatic     #22                 // Field os/move$.MODULE$:Los/move$;
         3: invokevirtual #51                 // Method os/move$.matching$default$2:()Z
         6: ireturn

  public static boolean matching$default$1();
    descriptor: ()Z
    flags: (0x0009) ACC_PUBLIC, ACC_STATIC
    Code:
      stack=1, locals=0, args_size=0
         0: getstatic     #22                 // Field os/move$.MODULE$:Los/move$;
         3: invokevirtual #54                 // Method os/move$.matching$default$1:()Z
         6: ireturn

  public static scala.PartialFunction<os.Path, scala.runtime.BoxedUnit> matching(boolean, boolean, boolean, scala.PartialFunction<os.Path, os.Path>);
    descriptor: (ZZZLscala/PartialFunction;)Lscala/PartialFunction;
    flags: (0x0009) ACC_PUBLIC, ACC_STATIC
    Code:
      stack=5, locals=4, args_size=4
         0: getstatic     #22                 // Field os/move$.MODULE$:Los/move$;
         3: iload_0
         4: iload_1
         5: iload_2
         6: aload_3
         7: invokevirtual #58                 // Method os/move$.matching:(ZZZLscala/PartialFunction;)Lscala/PartialFunction;
        10: areturn
    Signature: #56                          // (ZZZLscala/PartialFunction<Los/Path;Los/Path;>;)Lscala/PartialFunction<Los/Path;Lscala/runtime/BoxedUnit;>;
    MethodParameters:
      Name                           Flags
      replaceExisting                final
      atomicMove                     final
      createFolders                  final
      partialFunction                final
}
InnerClasses:
  public static #11= #10 of #2;           // into$=class os/move$into$ of class os/move
  public static #14= #13 of #2;           // over$=class os/move$over$ of class os/move
SourceFile: "FileOps.scala"
RuntimeVisibleAnnotations:
  0: #6(#7=s#8)
    scala.reflect.ScalaSignature(
      bytes="\u0006\u0005U<QAG\u000e\t\u0002y1Q\u0001I\u000e\t\u0002\u0005BQ\u0001K\u0001\u0005\u0002%BQAK\u0001\u0005\u0002-BqAQ\u0001\u0012\u0002\u0013\u00051\tC\u0004O\u0003E\u0005I\u0011A\"\t\u000f=\u000b\u0011\u0013!C\u0001\u0007\")!&\u0001C\u0001!\")!+\u0001C\u0001\'\"91,AI\u0001\n\u0003\u0019\u0005b\u0002/\u0002#\u0003%\ta\u0011\u0005\b;\u0006\t\n\u0011\"\u0001D\u000f\u0015q\u0016\u0001#\u0001`\r\u0015\t\u0017\u0001#\u0001c\u0011\u0015AS\u0002\"\u0001d\u0011\u0015\u0011V\u0002\"\u0001e\u0011\u001dYV\"%A\u0005\u0002\rCq\u0001X\u0007\u0012\u0002\u0013\u00051\tC\u0004^\u001bE\u0005I\u0011A\"\b\u000b)\f\u0001\u0012A6\u0007\u000b1\f\u0001\u0012A7\t\u000b!\"B\u0011\u00018\t\u000bI#B\u0011A8\t\u000fm#\u0012\u0013!C\u0001\u0007\"9A\fFI\u0001\n\u0003\u0019\u0005bB/\u0015#\u0003%\taQ\u0001\u0005[>4XMC\u0001\u001d\u0003\ty7o\u0001\u0001\u0011\u0005}\tQ\"A\u000e\u0003\t5|g/Z\n\u0003\u0003\t\u0002\"a\t\u0014\u000e\u0003\u0011R\u0011!J\u0001\u0006g\u000e\fG.Y\u0005\u0003O\u0011\u0012a!\u00118z%\u00164\u0017A\u0002\u001fj]&$h\bF\u0001\u001f\u0003!i\u0017\r^2iS:<G\u0003\u0002\u0017:}\u0001#\"!\f\u001c\u0011\t\rr\u0003gM\u0005\u0003_\u0011\u0012q\u0002U1si&\fGNR;oGRLwN\u001c\t\u0003?EJ!AM\u000e\u0003\tA\u000bG\u000f\u001b\t\u0003GQJ!!\u000e\u0013\u0003\tUs\u0017\u000e\u001e\u0005\u0006o\r\u0001\r\u0001O\u0001\u0010a\u0006\u0014H/[1m\rVt7\r^5p]B!1E\f\u00191\u0011\u001dQ4\u0001%AA\u0002m\nqB]3qY\u0006\u001cW-\u0012=jgRLgn\u001a\t\u0003GqJ!!\u0010\u0013\u0003\u000f\t{w\u000e\\3b]\"9qh\u0001I\u0001\u0002\u0004Y\u0014AC1u_6L7-T8wK\"9\u0011i\u0001I\u0001\u0002\u0004Y\u0014!D2sK\u0006$XMR8mI\u0016\u00148/\u0001\nnCR\u001c\u0007.\u001b8hI\u0011,g-Y;mi\u0012\nT#\u0001#+\u0005m*5&\u0001$\u0011\u0005\u001dcU\"\u0001%\u000b\u0005%S\u0015!C;oG\",7m[3e\u0015\tYE%\u0001\u0006b]:|G/\u0019;j_:L!!\u0014%\u0003#Ut7\r[3dW\u0016$g+\u0019:jC:\u001cW-\u0001\nnCR\u001c\u0007.\u001b8hI\u0011,g-Y;mi\u0012\u0012\u0014AE7bi\u000eD\u0017N\\4%I\u00164\u0017-\u001e7uIM\"\"!L)\t\u000b]:\u0001\u0019\u0001\u001d\u0002\u000b\u0005\u0004\b\u000f\\=\u0015\rM\"f\u000bW-[\u0011\u0015)\u0006\u00021\u00011\u0003\u00111\'o\\7\t\u000b]C\u0001\u0019\u0001\u0019\u0002\u0005Q|\u0007b\u0002\u001e\t!\u0003\u0005\ra\u000f\u0005\b\u007f!\u0001\n\u00111\u0001<\u0011\u001d\t\u0005\u0002%AA\u0002m\nq\"\u00199qYf$C-\u001a4bk2$HeM\u0001\u0010CB\u0004H.\u001f\u0013eK\u001a\fW\u000f\u001c;%i\u0005y\u0011\r\u001d9ms\u0012\"WMZ1vYR$S\'\u0001\u0003j]R|\u0007C\u00011\u000e\u001b\u0005\t!\u0001B5oi>\u001c\"!\u0004\u0012\u0015\u0003}#baM3gO\"L\u0007\"B+\u0010\u0001\u0004\u0001\u0004\"B,\u0010\u0001\u0004\u0001\u0004b\u0002\u001e\u0010!\u0003\u0005\ra\u000f\u0005\b\u007f=\u0001\n\u00111\u0001<\u0011\u001d\tu\u0002%AA\u0002m\nAa\u001c<feB\u0011\u0001\r\u0006\u0002\u0005_Z,\'o\u0005\u0002\u0015EQ\t1\u000e\u0006\u00044aF\u00148\u000f\u001e\u0005\u0006+Z\u0001\r\u0001\r\u0005\u0006/Z\u0001\r\u0001\r\u0005\buY\u0001\n\u00111\u0001<\u0011\u001dyd\u0003%AA\u0002mBq!\u0011\f\u0011\u0002\u0003\u00071\b"
    )
  ScalaSig: length = 0x3 (unknown attribute)
   05 02 00
