Classfile /Users/mw/Projects/slang-braindump/.jar/jar8/assemble/slang-braindump/assemble/content/os/owner.class
  Last modified May 29, 2022; size 1815 bytes
  SHA-256 checksum de460705d02bc3e4b53e6d488438f08aff6559a537f588a6dab2a8200d2c49cd
  Compiled from "PermsOps.scala"
public final class os.owner
  minor version: 0
  major version: 52
  flags: (0x0031) ACC_PUBLIC, ACC_FINAL, ACC_SUPER
  this_class: #2                          // os/owner
  super_class: #4                         // java/lang/Object
  interfaces: 0, fields: 0, methods: 6, attributes: 4
Constant pool:
   #1 = Utf8               os/owner
   #2 = Class              #1             // os/owner
   #3 = Utf8               java/lang/Object
   #4 = Class              #3             // java/lang/Object
   #5 = Utf8               PermsOps.scala
   #6 = Utf8               Lscala/reflect/ScalaSignature;
   #7 = Utf8               bytes
   #8 = Utf8               \u0006\u0005\u0001<Qa\u0003\u0007\t\u0002=1Q!\u0005\u0007\t\u0002IAQaK\u0001\u0005\u00021BQ!L\u0001\u0005\u00029BQ!L\u0001\u0005\u0002EBq\u0001O\u0001\u0012\u0002\u0013\u0005\u0011hB\u0003E\u0003!\u0005QIB\u0003H\u0003!\u0005\u0001\nC\u0003,\u000f\u0011\u0005\u0011\nC\u0003.\u000f\u0011\u0005!\nC\u0003.\u000f\u0011\u0005!+A\u0003po:,\'OC\u0001\u000e\u0003\ty7o\u0001\u0001\u0011\u0005A\tQ\"\u0001\u0007\u0003\u000b=<h.\u001a:\u0014\u0007\u0005\u0019\u0012\u0004\u0005\u0002\u0015/5\tQCC\u0001\u0017\u0003\u0015\u00198-\u00197b\u0013\tARC\u0001\u0004B]f\u0014VM\u001a\t\u0005)iar$\u0003\u0002\u001c+\tIa)\u001e8di&|g.\r\t\u0003!uI!A\b\u0007\u0003\tA\u000bG\u000f\u001b\t\u0003A%j\u0011!\t\u0006\u0003E\r\n\u0011\"\u0019;ue&\u0014W\u000f^3\u000b\u0005\u0011*\u0013\u0001\u00024jY\u0016T!AJ\u0014\u0002\u00079LwNC\u0001)\u0003\u0011Q\u0017M^1\n\u0005)\n#!D+tKJ\u0004&/\u001b8dSB\fG.\u0001\u0004=S:LGO\u0010\u000b\u0002\u001f\u0005)\u0011\r\u001d9msR\u0011qd\f\u0005\u0006a\r\u0001\r\u0001H\u0001\u0002aR\u0019qDM\u001a\t\u000bA\"\u0001\u0019\u0001\u000f\t\u000fQ\"\u0001\u0013!a\u0001k\u0005Yam\u001c7m_^d\u0015N\\6t!\t!b\'\u0003\u00028+\t9!i\\8mK\u0006t\u0017aD1qa2LH\u0005Z3gCVdG\u000f\n\u001a\u0016\u0003iR#!N\u001e,\u0003q\u0002\"!\u0010\"\u000e\u0003yR!a\u0010!\u0002\u0013Ut7\r[3dW\u0016$\'BA!\u0016\u0003)\tgN\\8uCRLwN\\\u0005\u0003\u0007z\u0012\u0011#\u001e8dQ\u0016\u001c7.\u001a3WCJL\u0017M\\2f\u0003\r\u0019X\r\u001e\t\u0003\r\u001ei\u0011!\u0001\u0002\u0004g\u0016$8CA\u0004\u0014)\u0005)EcA&O!B\u0011A\u0003T\u0005\u0003\u001bV\u0011A!\u00168ji\")q*\u0003a\u00019\u0005!\u0011M]42\u0011\u0015\t\u0016\u00021\u0001 \u0003\u0011\t\'o\u001a\u001a\u0015\u0007-\u001bF\u000bC\u0003P\u0015\u0001\u0007A\u0004C\u0003R\u0015\u0001\u0007Q\u000b\u0005\u0002W;:\u0011qk\u0017\t\u00031Vi\u0011!\u0017\u0006\u00035:\ta\u0001\u0010:p_Rt\u0014B\u0001/\u0016\u0003\u0019\u0001&/\u001a3fM&\u0011al\u0018\u0002\u0007\'R\u0014\u0018N\\4\u000b\u0005q+\u0002
   #9 = Utf8               os/owner$set$
  #10 = Class              #9             // os/owner$set$
  #11 = Utf8               set$
  #12 = Utf8               apply$default$2
  #13 = Utf8               ()Z
  #14 = Utf8               os/owner$
  #15 = Class              #14            // os/owner$
  #16 = Utf8               MODULE$
  #17 = Utf8               Los/owner$;
  #18 = NameAndType        #16:#17        // MODULE$:Los/owner$;
  #19 = Fieldref           #15.#18        // os/owner$.MODULE$:Los/owner$;
  #20 = NameAndType        #12:#13        // apply$default$2:()Z
  #21 = Methodref          #15.#20        // os/owner$.apply$default$2:()Z
  #22 = Utf8               apply
  #23 = Utf8               (Los/Path;Z)Ljava/nio/file/attribute/UserPrincipal;
  #24 = Utf8               p
  #25 = Utf8               followLinks
  #26 = NameAndType        #22:#23        // apply:(Los/Path;Z)Ljava/nio/file/attribute/UserPrincipal;
  #27 = Methodref          #15.#26        // os/owner$.apply:(Los/Path;Z)Ljava/nio/file/attribute/UserPrincipal;
  #28 = Utf8               (Los/Path;)Ljava/nio/file/attribute/UserPrincipal;
  #29 = NameAndType        #22:#28        // apply:(Los/Path;)Ljava/nio/file/attribute/UserPrincipal;
  #30 = Methodref          #15.#29        // os/owner$.apply:(Los/Path;)Ljava/nio/file/attribute/UserPrincipal;
  #31 = Utf8               toString
  #32 = Utf8               ()Ljava/lang/String;
  #33 = NameAndType        #31:#32        // toString:()Ljava/lang/String;
  #34 = Methodref          #15.#33        // os/owner$.toString:()Ljava/lang/String;
  #35 = Utf8               andThen
  #36 = Utf8               (Lscala/Function1;)Lscala/Function1;
  #37 = Utf8               <A:Ljava/lang/Object;>(Lscala/Function1<Ljava/nio/file/attribute/UserPrincipal;TA;>;)Lscala/Function1<Los/Path;TA;>;
  #38 = Utf8               g
  #39 = NameAndType        #35:#36        // andThen:(Lscala/Function1;)Lscala/Function1;
  #40 = Methodref          #15.#39        // os/owner$.andThen:(Lscala/Function1;)Lscala/Function1;
  #41 = Utf8               compose
  #42 = Utf8               <A:Ljava/lang/Object;>(Lscala/Function1<TA;Los/Path;>;)Lscala/Function1<TA;Ljava/nio/file/attribute/UserPrincipal;>;
  #43 = NameAndType        #41:#36        // compose:(Lscala/Function1;)Lscala/Function1;
  #44 = Methodref          #15.#43        // os/owner$.compose:(Lscala/Function1;)Lscala/Function1;
  #45 = Utf8               Code
  #46 = Utf8               MethodParameters
  #47 = Utf8               Signature
  #48 = Utf8               InnerClasses
  #49 = Utf8               SourceFile
  #50 = Utf8               RuntimeVisibleAnnotations
  #51 = Utf8               ScalaSig
{
  public static boolean apply$default$2();
    descriptor: ()Z
    flags: (0x0009) ACC_PUBLIC, ACC_STATIC
    Code:
      stack=1, locals=0, args_size=0
         0: getstatic     #19                 // Field os/owner$.MODULE$:Los/owner$;
         3: invokevirtual #21                 // Method os/owner$.apply$default$2:()Z
         6: ireturn

  public static java.nio.file.attribute.UserPrincipal apply(os.Path, boolean);
    descriptor: (Los/Path;Z)Ljava/nio/file/attribute/UserPrincipal;
    flags: (0x0009) ACC_PUBLIC, ACC_STATIC
    Code:
      stack=3, locals=2, args_size=2
         0: getstatic     #19                 // Field os/owner$.MODULE$:Los/owner$;
         3: aload_0
         4: iload_1
         5: invokevirtual #27                 // Method os/owner$.apply:(Los/Path;Z)Ljava/nio/file/attribute/UserPrincipal;
         8: areturn
    MethodParameters:
      Name                           Flags
      p                              final
      followLinks                    final

  public static java.nio.file.attribute.UserPrincipal apply(os.Path);
    descriptor: (Los/Path;)Ljava/nio/file/attribute/UserPrincipal;
    flags: (0x0009) ACC_PUBLIC, ACC_STATIC
    Code:
      stack=2, locals=1, args_size=1
         0: getstatic     #19                 // Field os/owner$.MODULE$:Los/owner$;
         3: aload_0
         4: invokevirtual #30                 // Method os/owner$.apply:(Los/Path;)Ljava/nio/file/attribute/UserPrincipal;
         7: areturn
    MethodParameters:
      Name                           Flags
      p                              final

  public static java.lang.String toString();
    descriptor: ()Ljava/lang/String;
    flags: (0x0009) ACC_PUBLIC, ACC_STATIC
    Code:
      stack=1, locals=0, args_size=0
         0: getstatic     #19                 // Field os/owner$.MODULE$:Los/owner$;
         3: invokevirtual #34                 // Method os/owner$.toString:()Ljava/lang/String;
         6: areturn

  public static <A extends java.lang.Object> scala.Function1<os.Path, A> andThen(scala.Function1<java.nio.file.attribute.UserPrincipal, A>);
    descriptor: (Lscala/Function1;)Lscala/Function1;
    flags: (0x0009) ACC_PUBLIC, ACC_STATIC
    Code:
      stack=2, locals=1, args_size=1
         0: getstatic     #19                 // Field os/owner$.MODULE$:Los/owner$;
         3: aload_0
         4: invokevirtual #40                 // Method os/owner$.andThen:(Lscala/Function1;)Lscala/Function1;
         7: areturn
    Signature: #37                          // <A:Ljava/lang/Object;>(Lscala/Function1<Ljava/nio/file/attribute/UserPrincipal;TA;>;)Lscala/Function1<Los/Path;TA;>;
    MethodParameters:
      Name                           Flags
      g                              final

  public static <A extends java.lang.Object> scala.Function1<A, java.nio.file.attribute.UserPrincipal> compose(scala.Function1<A, os.Path>);
    descriptor: (Lscala/Function1;)Lscala/Function1;
    flags: (0x0009) ACC_PUBLIC, ACC_STATIC
    Code:
      stack=2, locals=1, args_size=1
         0: getstatic     #19                 // Field os/owner$.MODULE$:Los/owner$;
         3: aload_0
         4: invokevirtual #44                 // Method os/owner$.compose:(Lscala/Function1;)Lscala/Function1;
         7: areturn
    Signature: #42                          // <A:Ljava/lang/Object;>(Lscala/Function1<TA;Los/Path;>;)Lscala/Function1<TA;Ljava/nio/file/attribute/UserPrincipal;>;
    MethodParameters:
      Name                           Flags
      g                              final
}
InnerClasses:
  public static #11= #10 of #2;           // set$=class os/owner$set$ of class os/owner
SourceFile: "PermsOps.scala"
RuntimeVisibleAnnotations:
  0: #6(#7=s#8)
    scala.reflect.ScalaSignature(
      bytes="\u0006\u0005\u0001<Qa\u0003\u0007\t\u0002=1Q!\u0005\u0007\t\u0002IAQaK\u0001\u0005\u00021BQ!L\u0001\u0005\u00029BQ!L\u0001\u0005\u0002EBq\u0001O\u0001\u0012\u0002\u0013\u0005\u0011hB\u0003E\u0003!\u0005QIB\u0003H\u0003!\u0005\u0001\nC\u0003,\u000f\u0011\u0005\u0011\nC\u0003.\u000f\u0011\u0005!\nC\u0003.\u000f\u0011\u0005!+A\u0003po:,\'OC\u0001\u000e\u0003\ty7o\u0001\u0001\u0011\u0005A\tQ\"\u0001\u0007\u0003\u000b=<h.\u001a:\u0014\u0007\u0005\u0019\u0012\u0004\u0005\u0002\u0015/5\tQCC\u0001\u0017\u0003\u0015\u00198-\u00197b\u0013\tARC\u0001\u0004B]f\u0014VM\u001a\t\u0005)iar$\u0003\u0002\u001c+\tIa)\u001e8di&|g.\r\t\u0003!uI!A\b\u0007\u0003\tA\u000bG\u000f\u001b\t\u0003A%j\u0011!\t\u0006\u0003E\r\n\u0011\"\u0019;ue&\u0014W\u000f^3\u000b\u0005\u0011*\u0013\u0001\u00024jY\u0016T!AJ\u0014\u0002\u00079LwNC\u0001)\u0003\u0011Q\u0017M^1\n\u0005)\n#!D+tKJ\u0004&/\u001b8dSB\fG.\u0001\u0004=S:LGO\u0010\u000b\u0002\u001f\u0005)\u0011\r\u001d9msR\u0011qd\f\u0005\u0006a\r\u0001\r\u0001H\u0001\u0002aR\u0019qDM\u001a\t\u000bA\"\u0001\u0019\u0001\u000f\t\u000fQ\"\u0001\u0013!a\u0001k\u0005Yam\u001c7m_^d\u0015N\\6t!\t!b\'\u0003\u00028+\t9!i\\8mK\u0006t\u0017aD1qa2LH\u0005Z3gCVdG\u000f\n\u001a\u0016\u0003iR#!N\u001e,\u0003q\u0002\"!\u0010\"\u000e\u0003yR!a\u0010!\u0002\u0013Ut7\r[3dW\u0016$\'BA!\u0016\u0003)\tgN\\8uCRLwN\\\u0005\u0003\u0007z\u0012\u0011#\u001e8dQ\u0016\u001c7.\u001a3WCJL\u0017M\\2f\u0003\r\u0019X\r\u001e\t\u0003\r\u001ei\u0011!\u0001\u0002\u0004g\u0016$8CA\u0004\u0014)\u0005)EcA&O!B\u0011A\u0003T\u0005\u0003\u001bV\u0011A!\u00168ji\")q*\u0003a\u00019\u0005!\u0011M]42\u0011\u0015\t\u0016\u00021\u0001 \u0003\u0011\t\'o\u001a\u001a\u0015\u0007-\u001bF\u000bC\u0003P\u0015\u0001\u0007A\u0004C\u0003R\u0015\u0001\u0007Q\u000b\u0005\u0002W;:\u0011qk\u0017\t\u00031Vi\u0011!\u0017\u0006\u00035:\ta\u0001\u0010:p_Rt\u0014B\u0001/\u0016\u0003\u0019\u0001&/\u001a3fM&\u0011al\u0018\u0002\u0007\'R\u0014\u0018N\\4\u000b\u0005q+\u0002"
    )
  ScalaSig: length = 0x3 (unknown attribute)
   05 02 00
