Classfile /Users/mw/Projects/slang-braindump/.jar/jar8/assemble/slang-braindump/assemble/content/os/PathRedirect.class
  Last modified May 29, 2022; size 6382 bytes
  SHA-256 checksum 38cb7c7ae987fd8519cc161d6beebf1e19e8dc81c87c374f11671eacf4edc01f
  Compiled from "SubProcess.scala"
public class os.PathRedirect implements os.ProcessInput,os.ProcessOutput,scala.Product,java.io.Serializable
  minor version: 0
  major version: 52
  flags: (0x0021) ACC_PUBLIC, ACC_SUPER
  this_class: #2                          // os/PathRedirect
  super_class: #4                         // java/lang/Object
  interfaces: 4, fields: 1, methods: 24, attributes: 5
Constant pool:
    #1 = Utf8               os/PathRedirect
    #2 = Class              #1            // os/PathRedirect
    #3 = Utf8               java/lang/Object
    #4 = Class              #3            // java/lang/Object
    #5 = Utf8               os/ProcessInput
    #6 = Class              #5            // os/ProcessInput
    #7 = Utf8               os/ProcessOutput
    #8 = Class              #7            // os/ProcessOutput
    #9 = Utf8               scala/Product
   #10 = Class              #9            // scala/Product
   #11 = Utf8               java/io/Serializable
   #12 = Class              #11           // java/io/Serializable
   #13 = Utf8               SubProcess.scala
   #14 = Utf8               Lscala/reflect/ScalaSignature;
   #15 = Utf8               bytes
   #16 = Utf8               \u0006\u0005\u0005\u001de\u0001\u0002\u000e\u001c\u0001zA\u0001b\u000f\u0001\u0003\u0016\u0004%\t\u0001\u0010\u0005\t\u0001\u0002\u0011\t\u0012)A\u0005{!)\u0011\t\u0001C\u0001\u0005\")Q\t\u0001C\u0001\r\")1\u000b\u0001C\u0001)\")A\r\u0001C\u0001\r\")Q\r\u0001C\u0001M\"9Q\u000eAA\u0001\n\u0003q\u0007b\u00029\u0001#\u0003%\t!\u001d\u0005\by\u0002\t\t\u0011\"\u0011~\u0011%\t\u0019\u0001AA\u0001\n\u0003\t)\u0001C\u0005\u0002\u000e\u0001\t\t\u0011\"\u0001\u0002\u0010!I\u00111\u0004\u0001\u0002\u0002\u0013\u0005\u0013Q\u0004\u0005\n\u0003W\u0001\u0011\u0011!C\u0001\u0003[A\u0011\"a\u000e\u0001\u0003\u0003%\t%!\u000f\t\u0013\u0005u\u0002!!A\u0005B\u0005}\u0002\"CA!\u0001\u0005\u0005I\u0011IA\"\u0011%\t)\u0005AA\u0001\n\u0003\n9eB\u0005\u0002Lm\t\t\u0011#\u0001\u0002N\u0019A!dGA\u0001\u0012\u0003\ty\u0005\u0003\u0004B)\u0011\u0005\u0011q\r\u0005\n\u0003\u0003\"\u0012\u0011!C#\u0003\u0007B\u0011\"!\u001b\u0015\u0003\u0003%\t)a\u001b\t\u0013\u0005=D#!A\u0005\u0002\u0006E\u0004\"CA?)\u0005\u0005I\u0011BA@\u00051\u0001\u0016\r\u001e5SK\u0012L\'/Z2u\u0015\u0005a\u0012AA8t\u0007\u0001\u0019b\u0001A\u0010&S1z\u0003C\u0001\u0011$\u001b\u0005\t#\"\u0001\u0012\u0002\u000bM\u001c\u0017\r\\1\n\u0005\u0011\n#AB!osJ+g\r\u0005\u0002\'O5\t1$\u0003\u0002)7\ta\u0001K]8dKN\u001c\u0018J\u001c9viB\u0011aEK\u0005\u0003Wm\u0011Q\u0002\u0015:pG\u0016\u001c8oT;uaV$\bC\u0001\u0011.\u0013\tq\u0013EA\u0004Qe>$Wo\u0019;\u0011\u0005ABdBA\u00197\u001d\t\u0011T\'D\u00014\u0015\t!T$\u0001\u0004=e>|GOP\u0005\u0002E%\u0011q\'I\u0001\ba\u0006\u001c7.Y4f\u0013\tI$H\u0001\u0007TKJL\u0017\r\\5{C\ndWM\u0003\u00028C\u0005\t\u0001/F\u0001>!\t1c(\u0003\u0002@7\t!\u0001+\u0019;i\u0003\t\u0001\b%\u0001\u0004=S:LGO\u0010\u000b\u0003\u0007\u0012\u0003\"A\n\u0001\t\u000bm\u001a\u0001\u0019A\u001f\u0002\u0019I,G-\u001b:fGR4%o\\7\u0016\u0003\u001d\u0003\"\u0001\u0013)\u000f\u0005%sU\"\u0001&\u000b\u0005-c\u0015\u0001\u00027b]\u001eT\u0011!T\u0001\u0005U\u00064\u0018-\u0003\u0002P\u0015\u0006q\u0001K]8dKN\u001c()^5mI\u0016\u0014\u0018BA)S\u0005!\u0011V\rZ5sK\u000e$(BA(K\u00031\u0001(o\\2fgNLe\u000e];u)\t)\u0006\f\u0005\u0002!-*\u0011q+I\u0001\u0005\u001d>tW\r\u0003\u0004Z\u000b\u0011\u0005\rAW\u0001\u0006gR$\u0017N\u001c\t\u0004Amk\u0016B\u0001/\"\u0005!a$-\u001f8b[\u0016t\u0004C\u00010b\u001d\t1s,\u0003\u0002a7\u0005Q1+\u001e2Qe>\u001cWm]:\n\u0005\t\u001c\'aC%oaV$8\u000b\u001e:fC6T!\u0001Y\u000e\u0002\u0015I,G-\u001b:fGR$v.A\u0007qe>\u001cWm]:PkR\u0004X\u000f\u001e\u000b\u0003+\u001eDa\u0001[\u0004\u0005\u0002\u0004I\u0017aA8viB\u0019\u0001e\u00176\u0011\u0005y[\u0017B\u00017d\u00051yU\u000f\u001e9viN#(/Z1n\u0003\u0011\u0019w\u000e]=\u0015\u0005\r{\u0007bB\u001e\t!\u0003\u0005\r!P\u0001\u000fG>\u0004\u0018\u0010\n3fM\u0006,H\u000e\u001e\u00132+\u0005\u0011(FA\u001ftW\u0005!\bCA;{\u001b\u00051(BA<y\u0003%)hn\u00195fG.,GM\u0003\u0002zC\u0005Q\u0011M\u001c8pi\u0006$\u0018n\u001c8\n\u0005m4(!E;oG\",7m[3e-\u0006\u0014\u0018.\u00198dK\u0006i\u0001O]8ek\u000e$\bK]3gSb,\u0012A \t\u0003\u0013~L1!!\u0001K\u0005\u0019\u0019FO]5oO\u0006a\u0001O]8ek\u000e$\u0018I]5usV\u0011\u0011q\u0001\t\u0004A\u0005%\u0011bAA\u0006C\t\u0019\u0011J\u001c;\u0002\u001dA\u0014x\u000eZ;di\u0016cW-\\3oiR!\u0011\u0011CA\f!\r\u0001\u00131C\u0005\u0004\u0003+\t#aA!os\"I\u0011\u0011\u0004\u0007\u0002\u0002\u0003\u0007\u0011qA\u0001\u0004q\u0012\n\u0014a\u00049s_\u0012,8\r^%uKJ\fGo\u001c:\u0016\u0005\u0005}\u0001CBA\u0011\u0003O\t\t\"\u0004\u0002\u0002$)\u0019\u0011QE\u0011\u0002\u0015\r|G\u000e\\3di&|g.\u0003\u0003\u0002*\u0005\r\"\u0001C%uKJ\fGo\u001c:\u0002\u0011\r\fg.R9vC2$B!a\f\u00026A\u0019\u0001%!\r\n\u0007\u0005M\u0012EA\u0004C_>dW-\u00198\t\u0013\u0005ea\"!AA\u0002\u0005E\u0011A\u00059s_\u0012,8\r^#mK6,g\u000e\u001e(b[\u0016$2A`A\u001e\u0011%\tIbDA\u0001\u0002\u0004\t9!\u0001\u0005iCND7i\u001c3f)\t\t9!\u0001\u0005u_N#(/\u001b8h)\u0005q\u0018AB3rk\u0006d7\u000f\u0006\u0003\u00020\u0005%\u0003\"CA\r%\u0005\u0005\t\u0019AA\t\u00031\u0001\u0016\r\u001e5SK\u0012L\'/Z2u!\t1CcE\u0003\u0015\u0003#\ni\u0006\u0005\u0004\u0002T\u0005eShQ\u0007\u0003\u0003+R1!a\u0016\"\u0003\u001d\u0011XO\u001c;j[\u0016LA!a\u0017\u0002V\t\t\u0012IY:ue\u0006\u001cGOR;oGRLwN\\\u0019\u0011\t\u0005}\u0013QM\u0007\u0003\u0003CR1!a\u0019M\u0003\tIw.C\u0002:\u0003C\"\"!!\u0014\u0002\u000b\u0005\u0004\b\u000f\\=\u0015\u0007\r\u000bi\u0007C\u0003</\u0001\u0007Q(A\u0004v]\u0006\u0004\b\u000f\\=\u0015\t\u0005M\u0014\u0011\u0010\t\u0005A\u0005UT(C\u0002\u0002x\u0005\u0012aa\u00149uS>t\u0007\u0002CA>1\u0005\u0005\t\u0019A\"\u0002\u0007a$\u0003\'\u0001\u0007xe&$XMU3qY\u0006\u001cW\r\u0006\u0002\u0002\u0002B\u0019\u0011*a!\n\u0007\u0005\u0015%J\u0001\u0004PE*,7\r\u001e
   #17 = Utf8               java/lang/ProcessBuilder$Redirect
   #18 = Class              #17           // java/lang/ProcessBuilder$Redirect
   #19 = Utf8               java/lang/ProcessBuilder
   #20 = Class              #19           // java/lang/ProcessBuilder
   #21 = Utf8               Redirect
   #22 = Utf8               os/SubProcess$InputStream
   #23 = Class              #22           // os/SubProcess$InputStream
   #24 = Utf8               os/SubProcess
   #25 = Class              #24           // os/SubProcess
   #26 = Utf8               InputStream
   #27 = Utf8               os/SubProcess$OutputStream
   #28 = Class              #27           // os/SubProcess$OutputStream
   #29 = Utf8               OutputStream
   #30 = Utf8               p
   #31 = Utf8               Los/Path;
   #32 = Utf8               unapply
   #33 = Utf8               (Los/PathRedirect;)Lscala/Option;
   #34 = Utf8               (Los/PathRedirect;)Lscala/Option<Los/Path;>;
   #35 = Utf8               x$0
   #36 = Utf8               os/PathRedirect$
   #37 = Class              #36           // os/PathRedirect$
   #38 = Utf8               MODULE$
   #39 = Utf8               Los/PathRedirect$;
   #40 = NameAndType        #38:#39       // MODULE$:Los/PathRedirect$;
   #41 = Fieldref           #37.#40       // os/PathRedirect$.MODULE$:Los/PathRedirect$;
   #42 = NameAndType        #32:#33       // unapply:(Los/PathRedirect;)Lscala/Option;
   #43 = Methodref          #37.#42       // os/PathRedirect$.unapply:(Los/PathRedirect;)Lscala/Option;
   #44 = Utf8               apply
   #45 = Utf8               (Los/Path;)Los/PathRedirect;
   #46 = NameAndType        #44:#45       // apply:(Los/Path;)Los/PathRedirect;
   #47 = Methodref          #37.#46       // os/PathRedirect$.apply:(Los/Path;)Los/PathRedirect;
   #48 = Utf8               andThen
   #49 = Utf8               (Lscala/Function1;)Lscala/Function1;
   #50 = Utf8               <A:Ljava/lang/Object;>(Lscala/Function1<Los/PathRedirect;TA;>;)Lscala/Function1<Los/Path;TA;>;
   #51 = Utf8               g
   #52 = NameAndType        #48:#49       // andThen:(Lscala/Function1;)Lscala/Function1;
   #53 = Methodref          #37.#52       // os/PathRedirect$.andThen:(Lscala/Function1;)Lscala/Function1;
   #54 = Utf8               compose
   #55 = Utf8               <A:Ljava/lang/Object;>(Lscala/Function1<TA;Los/Path;>;)Lscala/Function1<TA;Los/PathRedirect;>;
   #56 = NameAndType        #54:#49       // compose:(Lscala/Function1;)Lscala/Function1;
   #57 = Methodref          #37.#56       // os/PathRedirect$.compose:(Lscala/Function1;)Lscala/Function1;
   #58 = Utf8               productElementNames
   #59 = Utf8               ()Lscala/collection/Iterator;
   #60 = Utf8               ()Lscala/collection/Iterator<Ljava/lang/String;>;
   #61 = Utf8               productElementNames$
   #62 = Utf8               (Lscala/Product;)Lscala/collection/Iterator;
   #63 = NameAndType        #61:#62       // productElementNames$:(Lscala/Product;)Lscala/collection/Iterator;
   #64 = InterfaceMethodref #10.#63       // scala/Product.productElementNames$:(Lscala/Product;)Lscala/collection/Iterator;
   #65 = Utf8               this
   #66 = Utf8               Los/PathRedirect;
   #67 = Utf8               ()Los/Path;
   #68 = NameAndType        #30:#31       // p:Los/Path;
   #69 = Fieldref           #2.#68        // os/PathRedirect.p:Los/Path;
   #70 = Utf8               redirectFrom
   #71 = Utf8               ()Ljava/lang/ProcessBuilder$Redirect;
   #72 = NameAndType        #30:#67       // p:()Los/Path;
   #73 = Methodref          #2.#72        // os/PathRedirect.p:()Los/Path;
   #74 = Utf8               os/Path
   #75 = Class              #74           // os/Path
   #76 = Utf8               toIO
   #77 = Utf8               ()Ljava/io/File;
   #78 = NameAndType        #76:#77       // toIO:()Ljava/io/File;
   #79 = Methodref          #75.#78       // os/Path.toIO:()Ljava/io/File;
   #80 = Utf8               from
   #81 = Utf8               (Ljava/io/File;)Ljava/lang/ProcessBuilder$Redirect;
   #82 = NameAndType        #80:#81       // from:(Ljava/io/File;)Ljava/lang/ProcessBuilder$Redirect;
   #83 = Methodref          #18.#82       // java/lang/ProcessBuilder$Redirect.from:(Ljava/io/File;)Ljava/lang/ProcessBuilder$Redirect;
   #84 = Utf8               processInput
   #85 = Utf8               (Lscala/Function0;)Lscala/None$;
   #86 = Utf8               (Lscala/Function0<Los/SubProcess$InputStream;>;)Lscala/None$;
   #87 = Utf8               stdin
   #88 = Utf8               scala/None$
   #89 = Class              #88           // scala/None$
   #90 = Utf8               Lscala/None$;
   #91 = NameAndType        #38:#90       // MODULE$:Lscala/None$;
   #92 = Fieldref           #89.#91       // scala/None$.MODULE$:Lscala/None$;
   #93 = Utf8               Lscala/Function0;
   #94 = Utf8               redirectTo
   #95 = Utf8               to
   #96 = NameAndType        #95:#81       // to:(Ljava/io/File;)Ljava/lang/ProcessBuilder$Redirect;
   #97 = Methodref          #18.#96       // java/lang/ProcessBuilder$Redirect.to:(Ljava/io/File;)Ljava/lang/ProcessBuilder$Redirect;
   #98 = Utf8               processOutput
   #99 = Utf8               (Lscala/Function0<Los/SubProcess$OutputStream;>;)Lscala/None$;
  #100 = Utf8               out
  #101 = Utf8               copy
  #102 = Utf8               <init>
  #103 = Utf8               (Los/Path;)V
  #104 = NameAndType        #102:#103     // "<init>":(Los/Path;)V
  #105 = Methodref          #2.#104       // os/PathRedirect."<init>":(Los/Path;)V
  #106 = Utf8               copy$default$1
  #107 = Utf8               productPrefix
  #108 = Utf8               ()Ljava/lang/String;
  #109 = Utf8               PathRedirect
  #110 = String             #109          // PathRedirect
  #111 = Utf8               productArity
  #112 = Utf8               ()I
  #113 = Utf8               productElement
  #114 = Utf8               (I)Ljava/lang/Object;
  #115 = Utf8               x$1
  #116 = Utf8               scala/runtime/Statics
  #117 = Class              #116          // scala/runtime/Statics
  #118 = Utf8               ioobe
  #119 = NameAndType        #118:#114     // ioobe:(I)Ljava/lang/Object;
  #120 = Methodref          #117.#119     // scala/runtime/Statics.ioobe:(I)Ljava/lang/Object;
  #121 = Utf8               I
  #122 = Utf8               productIterator
  #123 = Utf8               ()Lscala/collection/Iterator<Ljava/lang/Object;>;
  #124 = Utf8               scala/runtime/ScalaRunTime$
  #125 = Class              #124          // scala/runtime/ScalaRunTime$
  #126 = Utf8               Lscala/runtime/ScalaRunTime$;
  #127 = NameAndType        #38:#126      // MODULE$:Lscala/runtime/ScalaRunTime$;
  #128 = Fieldref           #125.#127     // scala/runtime/ScalaRunTime$.MODULE$:Lscala/runtime/ScalaRunTime$;
  #129 = Utf8               typedProductIterator
  #130 = NameAndType        #129:#62      // typedProductIterator:(Lscala/Product;)Lscala/collection/Iterator;
  #131 = Methodref          #125.#130     // scala/runtime/ScalaRunTime$.typedProductIterator:(Lscala/Product;)Lscala/collection/Iterator;
  #132 = Utf8               canEqual
  #133 = Utf8               (Ljava/lang/Object;)Z
  #134 = Utf8               Ljava/lang/Object;
  #135 = Utf8               productElementName
  #136 = Utf8               (I)Ljava/lang/String;
  #137 = String             #30           // p
  #138 = Utf8               java/lang/String
  #139 = Class              #138          // java/lang/String
  #140 = Utf8               hashCode
  #141 = Utf8               _hashCode
  #142 = Utf8               (Lscala/Product;)I
  #143 = NameAndType        #141:#142     // _hashCode:(Lscala/Product;)I
  #144 = Methodref          #125.#143     // scala/runtime/ScalaRunTime$._hashCode:(Lscala/Product;)I
  #145 = Utf8               toString
  #146 = Utf8               _toString
  #147 = Utf8               (Lscala/Product;)Ljava/lang/String;
  #148 = NameAndType        #146:#147     // _toString:(Lscala/Product;)Ljava/lang/String;
  #149 = Methodref          #125.#148     // scala/runtime/ScalaRunTime$._toString:(Lscala/Product;)Ljava/lang/String;
  #150 = Utf8               equals
  #151 = NameAndType        #150:#133     // equals:(Ljava/lang/Object;)Z
  #152 = Methodref          #4.#151       // java/lang/Object.equals:(Ljava/lang/Object;)Z
  #153 = NameAndType        #132:#133     // canEqual:(Ljava/lang/Object;)Z
  #154 = Methodref          #2.#153       // os/PathRedirect.canEqual:(Ljava/lang/Object;)Z
  #155 = Utf8               (Lscala/Function0;)Lscala/Option;
  #156 = NameAndType        #98:#85       // processOutput:(Lscala/Function0;)Lscala/None$;
  #157 = Methodref          #2.#156       // os/PathRedirect.processOutput:(Lscala/Function0;)Lscala/None$;
  #158 = NameAndType        #84:#85       // processInput:(Lscala/Function0;)Lscala/None$;
  #159 = Methodref          #2.#158       // os/PathRedirect.processInput:(Lscala/Function0;)Lscala/None$;
  #160 = Utf8               ()V
  #161 = NameAndType        #102:#160     // "<init>":()V
  #162 = Methodref          #4.#161       // java/lang/Object."<init>":()V
  #163 = Utf8               $init$
  #164 = Utf8               (Lscala/Product;)V
  #165 = NameAndType        #163:#164     // $init$:(Lscala/Product;)V
  #166 = InterfaceMethodref #10.#165      // scala/Product.$init$:(Lscala/Product;)V
  #167 = Utf8               Code
  #168 = Utf8               Signature
  #169 = Utf8               MethodParameters
  #170 = Utf8               LineNumberTable
  #171 = Utf8               LocalVariableTable
  #172 = Utf8               StackMapTable
  #173 = Utf8               InnerClasses
  #174 = Utf8               SourceFile
  #175 = Utf8               RuntimeVisibleAnnotations
  #176 = Utf8               ScalaInlineInfo
  #177 = Utf8               ScalaSig
{
  private final os.Path p;
    descriptor: Los/Path;
    flags: (0x0012) ACC_PRIVATE, ACC_FINAL

  public static scala.Option<os.Path> unapply(os.PathRedirect);
    descriptor: (Los/PathRedirect;)Lscala/Option;
    flags: (0x0009) ACC_PUBLIC, ACC_STATIC
    Code:
      stack=2, locals=1, args_size=1
         0: getstatic     #41                 // Field os/PathRedirect$.MODULE$:Los/PathRedirect$;
         3: aload_0
         4: invokevirtual #43                 // Method os/PathRedirect$.unapply:(Los/PathRedirect;)Lscala/Option;
         7: areturn
    Signature: #34                          // (Los/PathRedirect;)Lscala/Option<Los/Path;>;
    MethodParameters:
      Name                           Flags
      x$0                            final

  public static os.PathRedirect apply(os.Path);
    descriptor: (Los/Path;)Los/PathRedirect;
    flags: (0x0009) ACC_PUBLIC, ACC_STATIC
    Code:
      stack=2, locals=1, args_size=1
         0: getstatic     #41                 // Field os/PathRedirect$.MODULE$:Los/PathRedirect$;
         3: aload_0
         4: invokevirtual #47                 // Method os/PathRedirect$.apply:(Los/Path;)Los/PathRedirect;
         7: areturn
    MethodParameters:
      Name                           Flags
      p                              final

  public static <A extends java.lang.Object> scala.Function1<os.Path, A> andThen(scala.Function1<os.PathRedirect, A>);
    descriptor: (Lscala/Function1;)Lscala/Function1;
    flags: (0x0009) ACC_PUBLIC, ACC_STATIC
    Code:
      stack=2, locals=1, args_size=1
         0: getstatic     #41                 // Field os/PathRedirect$.MODULE$:Los/PathRedirect$;
         3: aload_0
         4: invokevirtual #53                 // Method os/PathRedirect$.andThen:(Lscala/Function1;)Lscala/Function1;
         7: areturn
    Signature: #50                          // <A:Ljava/lang/Object;>(Lscala/Function1<Los/PathRedirect;TA;>;)Lscala/Function1<Los/Path;TA;>;
    MethodParameters:
      Name                           Flags
      g                              final

  public static <A extends java.lang.Object> scala.Function1<A, os.PathRedirect> compose(scala.Function1<A, os.Path>);
    descriptor: (Lscala/Function1;)Lscala/Function1;
    flags: (0x0009) ACC_PUBLIC, ACC_STATIC
    Code:
      stack=2, locals=1, args_size=1
         0: getstatic     #41                 // Field os/PathRedirect$.MODULE$:Los/PathRedirect$;
         3: aload_0
         4: invokevirtual #57                 // Method os/PathRedirect$.compose:(Lscala/Function1;)Lscala/Function1;
         7: areturn
    Signature: #55                          // <A:Ljava/lang/Object;>(Lscala/Function1<TA;Los/Path;>;)Lscala/Function1<TA;Los/PathRedirect;>;
    MethodParameters:
      Name                           Flags
      g                              final

  public scala.collection.Iterator<java.lang.String> productElementNames();
    descriptor: ()Lscala/collection/Iterator;
    flags: (0x0001) ACC_PUBLIC
    Code:
      stack=1, locals=1, args_size=1
         0: aload_0
         1: invokestatic  #64                 // InterfaceMethod scala/Product.productElementNames$:(Lscala/Product;)Lscala/collection/Iterator;
         4: areturn
      LineNumberTable:
        line 259: 0
      LocalVariableTable:
        Start  Length  Slot  Name   Signature
            0       5     0  this   Los/PathRedirect;
    Signature: #60                          // ()Lscala/collection/Iterator<Ljava/lang/String;>;

  public os.Path p();
    descriptor: ()Los/Path;
    flags: (0x0001) ACC_PUBLIC
    Code:
      stack=1, locals=1, args_size=1
         0: aload_0
         1: getfield      #69                 // Field p:Los/Path;
         4: areturn
      LineNumberTable:
        line 259: 0
      LocalVariableTable:
        Start  Length  Slot  Name   Signature
            0       5     0  this   Los/PathRedirect;

  public java.lang.ProcessBuilder$Redirect redirectFrom();
    descriptor: ()Ljava/lang/ProcessBuilder$Redirect;
    flags: (0x0001) ACC_PUBLIC
    Code:
      stack=1, locals=1, args_size=1
         0: aload_0
         1: invokevirtual #73                 // Method p:()Los/Path;
         4: invokevirtual #79                 // Method os/Path.toIO:()Ljava/io/File;
         7: invokestatic  #83                 // Method java/lang/ProcessBuilder$Redirect.from:(Ljava/io/File;)Ljava/lang/ProcessBuilder$Redirect;
        10: areturn
      LineNumberTable:
        line 260: 0
      LocalVariableTable:
        Start  Length  Slot  Name   Signature
            0      11     0  this   Los/PathRedirect;

  public scala.None$ processInput(scala.Function0<os.SubProcess$InputStream>);
    descriptor: (Lscala/Function0;)Lscala/None$;
    flags: (0x0001) ACC_PUBLIC
    Code:
      stack=1, locals=2, args_size=2
         0: getstatic     #92                 // Field scala/None$.MODULE$:Lscala/None$;
         3: areturn
      LineNumberTable:
        line 261: 0
      LocalVariableTable:
        Start  Length  Slot  Name   Signature
            0       4     0  this   Los/PathRedirect;
            0       4     1 stdin   Lscala/Function0;
    Signature: #86                          // (Lscala/Function0<Los/SubProcess$InputStream;>;)Lscala/None$;
    MethodParameters:
      Name                           Flags
      stdin                          final

  public java.lang.ProcessBuilder$Redirect redirectTo();
    descriptor: ()Ljava/lang/ProcessBuilder$Redirect;
    flags: (0x0001) ACC_PUBLIC
    Code:
      stack=1, locals=1, args_size=1
         0: aload_0
         1: invokevirtual #73                 // Method p:()Los/Path;
         4: invokevirtual #79                 // Method os/Path.toIO:()Ljava/io/File;
         7: invokestatic  #97                 // Method java/lang/ProcessBuilder$Redirect.to:(Ljava/io/File;)Ljava/lang/ProcessBuilder$Redirect;
        10: areturn
      LineNumberTable:
        line 262: 0
      LocalVariableTable:
        Start  Length  Slot  Name   Signature
            0      11     0  this   Los/PathRedirect;

  public scala.None$ processOutput(scala.Function0<os.SubProcess$OutputStream>);
    descriptor: (Lscala/Function0;)Lscala/None$;
    flags: (0x0001) ACC_PUBLIC
    Code:
      stack=1, locals=2, args_size=2
         0: getstatic     #92                 // Field scala/None$.MODULE$:Lscala/None$;
         3: areturn
      LineNumberTable:
        line 263: 0
      LocalVariableTable:
        Start  Length  Slot  Name   Signature
            0       4     0  this   Los/PathRedirect;
            0       4     1   out   Lscala/Function0;
    Signature: #99                          // (Lscala/Function0<Los/SubProcess$OutputStream;>;)Lscala/None$;
    MethodParameters:
      Name                           Flags
      out                            final

  public os.PathRedirect copy(os.Path);
    descriptor: (Los/Path;)Los/PathRedirect;
    flags: (0x0001) ACC_PUBLIC
    Code:
      stack=3, locals=2, args_size=2
         0: new           #2                  // class os/PathRedirect
         3: dup
         4: aload_1
         5: invokespecial #105                // Method "<init>":(Los/Path;)V
         8: areturn
      LineNumberTable:
        line 259: 0
      LocalVariableTable:
        Start  Length  Slot  Name   Signature
            0       9     0  this   Los/PathRedirect;
            0       9     1     p   Los/Path;
    MethodParameters:
      Name                           Flags
      p                              final

  public os.Path copy$default$1();
    descriptor: ()Los/Path;
    flags: (0x0001) ACC_PUBLIC
    Code:
      stack=1, locals=1, args_size=1
         0: aload_0
         1: invokevirtual #73                 // Method p:()Los/Path;
         4: areturn
      LineNumberTable:
        line 259: 0
      LocalVariableTable:
        Start  Length  Slot  Name   Signature
            0       5     0  this   Los/PathRedirect;

  public java.lang.String productPrefix();
    descriptor: ()Ljava/lang/String;
    flags: (0x0001) ACC_PUBLIC
    Code:
      stack=1, locals=1, args_size=1
         0: ldc           #110                // String PathRedirect
         2: areturn
      LineNumberTable:
        line 259: 0
      LocalVariableTable:
        Start  Length  Slot  Name   Signature
            0       3     0  this   Los/PathRedirect;

  public int productArity();
    descriptor: ()I
    flags: (0x0001) ACC_PUBLIC
    Code:
      stack=1, locals=1, args_size=1
         0: iconst_1
         1: ireturn
      LineNumberTable:
        line 259: 0
      LocalVariableTable:
        Start  Length  Slot  Name   Signature
            0       2     0  this   Los/PathRedirect;

  public java.lang.Object productElement(int);
    descriptor: (I)Ljava/lang/Object;
    flags: (0x0001) ACC_PUBLIC
    Code:
      stack=1, locals=3, args_size=2
         0: iload_1
         1: istore_2
         2: iload_2
         3: tableswitch   { // 0 to 0
                       0: 20
                 default: 27
            }
        20: aload_0
        21: invokevirtual #73                 // Method p:()Los/Path;
        24: goto          34
        27: iload_1
        28: invokestatic  #120                // Method scala/runtime/Statics.ioobe:(I)Ljava/lang/Object;
        31: goto          34
        34: areturn
      StackMapTable: number_of_entries = 3
        frame_type = 252 /* append */
          offset_delta = 20
          locals = [ int ]
        frame_type = 6 /* same */
        frame_type = 70 /* same_locals_1_stack_item */
          stack = [ class java/lang/Object ]
      LineNumberTable:
        line 259: 0
      LocalVariableTable:
        Start  Length  Slot  Name   Signature
            0      35     0  this   Los/PathRedirect;
            0      35     1   x$1   I
    MethodParameters:
      Name                           Flags
      x$1                            final

  public scala.collection.Iterator<java.lang.Object> productIterator();
    descriptor: ()Lscala/collection/Iterator;
    flags: (0x0001) ACC_PUBLIC
    Code:
      stack=2, locals=1, args_size=1
         0: getstatic     #128                // Field scala/runtime/ScalaRunTime$.MODULE$:Lscala/runtime/ScalaRunTime$;
         3: aload_0
         4: invokevirtual #131                // Method scala/runtime/ScalaRunTime$.typedProductIterator:(Lscala/Product;)Lscala/collection/Iterator;
         7: areturn
      LineNumberTable:
        line 259: 0
      LocalVariableTable:
        Start  Length  Slot  Name   Signature
            0       8     0  this   Los/PathRedirect;
    Signature: #123                         // ()Lscala/collection/Iterator<Ljava/lang/Object;>;

  public boolean canEqual(java.lang.Object);
    descriptor: (Ljava/lang/Object;)Z
    flags: (0x0001) ACC_PUBLIC
    Code:
      stack=1, locals=2, args_size=2
         0: aload_1
         1: instanceof    #2                  // class os/PathRedirect
         4: ireturn
      LineNumberTable:
        line 259: 0
      LocalVariableTable:
        Start  Length  Slot  Name   Signature
            0       5     0  this   Los/PathRedirect;
            0       5     1   x$1   Ljava/lang/Object;
    MethodParameters:
      Name                           Flags
      x$1                            final

  public java.lang.String productElementName(int);
    descriptor: (I)Ljava/lang/String;
    flags: (0x0001) ACC_PUBLIC
    Code:
      stack=1, locals=3, args_size=2
         0: iload_1
         1: istore_2
         2: iload_2
         3: tableswitch   { // 0 to 0
                       0: 20
                 default: 25
            }
        20: ldc           #137                // String p
        22: goto          35
        25: iload_1
        26: invokestatic  #120                // Method scala/runtime/Statics.ioobe:(I)Ljava/lang/Object;
        29: checkcast     #139                // class java/lang/String
        32: goto          35
        35: areturn
      StackMapTable: number_of_entries = 3
        frame_type = 252 /* append */
          offset_delta = 20
          locals = [ int ]
        frame_type = 4 /* same */
        frame_type = 73 /* same_locals_1_stack_item */
          stack = [ class java/lang/String ]
      LineNumberTable:
        line 259: 0
      LocalVariableTable:
        Start  Length  Slot  Name   Signature
            0      36     0  this   Los/PathRedirect;
            0      36     1   x$1   I
    MethodParameters:
      Name                           Flags
      x$1                            final

  public int hashCode();
    descriptor: ()I
    flags: (0x0001) ACC_PUBLIC
    Code:
      stack=2, locals=1, args_size=1
         0: getstatic     #128                // Field scala/runtime/ScalaRunTime$.MODULE$:Lscala/runtime/ScalaRunTime$;
         3: aload_0
         4: invokevirtual #144                // Method scala/runtime/ScalaRunTime$._hashCode:(Lscala/Product;)I
         7: ireturn
      LineNumberTable:
        line 259: 0
      LocalVariableTable:
        Start  Length  Slot  Name   Signature
            0       8     0  this   Los/PathRedirect;

  public java.lang.String toString();
    descriptor: ()Ljava/lang/String;
    flags: (0x0001) ACC_PUBLIC
    Code:
      stack=2, locals=1, args_size=1
         0: getstatic     #128                // Field scala/runtime/ScalaRunTime$.MODULE$:Lscala/runtime/ScalaRunTime$;
         3: aload_0
         4: invokevirtual #149                // Method scala/runtime/ScalaRunTime$._toString:(Lscala/Product;)Ljava/lang/String;
         7: areturn
      LineNumberTable:
        line 259: 0
      LocalVariableTable:
        Start  Length  Slot  Name   Signature
            0       8     0  this   Los/PathRedirect;

  public boolean equals(java.lang.Object);
    descriptor: (Ljava/lang/Object;)Z
    flags: (0x0001) ACC_PUBLIC
    Code:
      stack=2, locals=6, args_size=2
         0: aload_0
         1: aload_1
         2: if_acmpeq     86
         5: aload_1
         6: astore_3
         7: aload_3
         8: instanceof    #2                  // class os/PathRedirect
        11: ifeq          19
        14: iconst_1
        15: istore_2
        16: goto          27
        19: goto          22
        22: iconst_0
        23: istore_2
        24: goto          27
        27: iload_2
        28: ifeq          90
        31: aload_1
        32: checkcast     #2                  // class os/PathRedirect
        35: astore        4
        37: aload_0
        38: invokevirtual #73                 // Method p:()Los/Path;
        41: aload         4
        43: invokevirtual #73                 // Method p:()Los/Path;
        46: astore        5
        48: dup
        49: ifnonnull     61
        52: pop
        53: aload         5
        55: ifnull        69
        58: goto          82
        61: aload         5
        63: invokevirtual #152                // Method java/lang/Object.equals:(Ljava/lang/Object;)Z
        66: ifeq          82
        69: aload         4
        71: aload_0
        72: invokevirtual #154                // Method canEqual:(Ljava/lang/Object;)Z
        75: ifeq          82
        78: iconst_1
        79: goto          83
        82: iconst_0
        83: ifeq          90
        86: iconst_1
        87: goto          91
        90: iconst_0
        91: ireturn
      StackMapTable: number_of_entries = 10
        frame_type = 253 /* append */
          offset_delta = 19
          locals = [ top, class java/lang/Object ]
        frame_type = 2 /* same */
        frame_type = 255 /* full_frame */
          offset_delta = 4
          locals = [ class os/PathRedirect, class java/lang/Object, int, class java/lang/Object ]
          stack = []
        frame_type = 255 /* full_frame */
          offset_delta = 33
          locals = [ class os/PathRedirect, class java/lang/Object, int, class java/lang/Object, class os/PathRedirect, class os/Path ]
          stack = [ class os/Path ]
        frame_type = 7 /* same */
        frame_type = 12 /* same */
        frame_type = 64 /* same_locals_1_stack_item */
          stack = [ int ]
        frame_type = 255 /* full_frame */
          offset_delta = 2
          locals = [ class os/PathRedirect, class java/lang/Object ]
          stack = []
        frame_type = 253 /* append */
          offset_delta = 3
          locals = [ int, class java/lang/Object ]
        frame_type = 255 /* full_frame */
          offset_delta = 0
          locals = [ class os/PathRedirect, class java/lang/Object ]
          stack = [ int ]
      LineNumberTable:
        line 259: 0
      LocalVariableTable:
        Start  Length  Slot  Name   Signature
            0      92     0  this   Los/PathRedirect;
            0      92     1   x$1   Ljava/lang/Object;
    MethodParameters:
      Name                           Flags
      x$1                            final

  public scala.Option processOutput(scala.Function0);
    descriptor: (Lscala/Function0;)Lscala/Option;
    flags: (0x1041) ACC_PUBLIC, ACC_BRIDGE, ACC_SYNTHETIC
    Code:
      stack=2, locals=2, args_size=2
         0: aload_0
         1: aload_1
         2: invokevirtual #157                // Method processOutput:(Lscala/Function0;)Lscala/None$;
         5: areturn
      LineNumberTable:
        line 259: 0
      LocalVariableTable:
        Start  Length  Slot  Name   Signature
            0       6     0  this   Los/PathRedirect;
            0       6     1   out   Lscala/Function0;
    MethodParameters:
      Name                           Flags
      out                            final

  public scala.Option processInput(scala.Function0);
    descriptor: (Lscala/Function0;)Lscala/Option;
    flags: (0x1041) ACC_PUBLIC, ACC_BRIDGE, ACC_SYNTHETIC
    Code:
      stack=2, locals=2, args_size=2
         0: aload_0
         1: aload_1
         2: invokevirtual #159                // Method processInput:(Lscala/Function0;)Lscala/None$;
         5: areturn
      LineNumberTable:
        line 259: 0
      LocalVariableTable:
        Start  Length  Slot  Name   Signature
            0       6     0  this   Los/PathRedirect;
            0       6     1 stdin   Lscala/Function0;
    MethodParameters:
      Name                           Flags
      stdin                          final

  public os.PathRedirect(os.Path);
    descriptor: (Los/Path;)V
    flags: (0x0001) ACC_PUBLIC
    Code:
      stack=2, locals=2, args_size=2
         0: aload_0
         1: aload_1
         2: putfield      #69                 // Field p:Los/Path;
         5: aload_0
         6: invokespecial #162                // Method java/lang/Object."<init>":()V
         9: aload_0
        10: invokestatic  #166                // InterfaceMethod scala/Product.$init$:(Lscala/Product;)V
        13: return
      LineNumberTable:
        line 259: 0
      LocalVariableTable:
        Start  Length  Slot  Name   Signature
            0      14     0  this   Los/PathRedirect;
            0      14     1     p   Los/Path;
    MethodParameters:
      Name                           Flags
      p                              final
}
InnerClasses:
  public static abstract #21= #18 of #20; // Redirect=class java/lang/ProcessBuilder$Redirect of class java/lang/ProcessBuilder
  public static #26= #23 of #25;          // InputStream=class os/SubProcess$InputStream of class os/SubProcess
  public static #29= #28 of #25;          // OutputStream=class os/SubProcess$OutputStream of class os/SubProcess
SourceFile: "SubProcess.scala"
RuntimeVisibleAnnotations:
  0: #14(#15=s#16)
    scala.reflect.ScalaSignature(
      bytes="\u0006\u0005\u0005\u001de\u0001\u0002\u000e\u001c\u0001zA\u0001b\u000f\u0001\u0003\u0016\u0004%\t\u0001\u0010\u0005\t\u0001\u0002\u0011\t\u0012)A\u0005{!)\u0011\t\u0001C\u0001\u0005\")Q\t\u0001C\u0001\r\")1\u000b\u0001C\u0001)\")A\r\u0001C\u0001\r\")Q\r\u0001C\u0001M\"9Q\u000eAA\u0001\n\u0003q\u0007b\u00029\u0001#\u0003%\t!\u001d\u0005\by\u0002\t\t\u0011\"\u0011~\u0011%\t\u0019\u0001AA\u0001\n\u0003\t)\u0001C\u0005\u0002\u000e\u0001\t\t\u0011\"\u0001\u0002\u0010!I\u00111\u0004\u0001\u0002\u0002\u0013\u0005\u0013Q\u0004\u0005\n\u0003W\u0001\u0011\u0011!C\u0001\u0003[A\u0011\"a\u000e\u0001\u0003\u0003%\t%!\u000f\t\u0013\u0005u\u0002!!A\u0005B\u0005}\u0002\"CA!\u0001\u0005\u0005I\u0011IA\"\u0011%\t)\u0005AA\u0001\n\u0003\n9eB\u0005\u0002Lm\t\t\u0011#\u0001\u0002N\u0019A!dGA\u0001\u0012\u0003\ty\u0005\u0003\u0004B)\u0011\u0005\u0011q\r\u0005\n\u0003\u0003\"\u0012\u0011!C#\u0003\u0007B\u0011\"!\u001b\u0015\u0003\u0003%\t)a\u001b\t\u0013\u0005=D#!A\u0005\u0002\u0006E\u0004\"CA?)\u0005\u0005I\u0011BA@\u00051\u0001\u0016\r\u001e5SK\u0012L\'/Z2u\u0015\u0005a\u0012AA8t\u0007\u0001\u0019b\u0001A\u0010&S1z\u0003C\u0001\u0011$\u001b\u0005\t#\"\u0001\u0012\u0002\u000bM\u001c\u0017\r\\1\n\u0005\u0011\n#AB!osJ+g\r\u0005\u0002\'O5\t1$\u0003\u0002)7\ta\u0001K]8dKN\u001c\u0018J\u001c9viB\u0011aEK\u0005\u0003Wm\u0011Q\u0002\u0015:pG\u0016\u001c8oT;uaV$\bC\u0001\u0011.\u0013\tq\u0013EA\u0004Qe>$Wo\u0019;\u0011\u0005ABdBA\u00197\u001d\t\u0011T\'D\u00014\u0015\t!T$\u0001\u0004=e>|GOP\u0005\u0002E%\u0011q\'I\u0001\ba\u0006\u001c7.Y4f\u0013\tI$H\u0001\u0007TKJL\u0017\r\\5{C\ndWM\u0003\u00028C\u0005\t\u0001/F\u0001>!\t1c(\u0003\u0002@7\t!\u0001+\u0019;i\u0003\t\u0001\b%\u0001\u0004=S:LGO\u0010\u000b\u0003\u0007\u0012\u0003\"A\n\u0001\t\u000bm\u001a\u0001\u0019A\u001f\u0002\u0019I,G-\u001b:fGR4%o\\7\u0016\u0003\u001d\u0003\"\u0001\u0013)\u000f\u0005%sU\"\u0001&\u000b\u0005-c\u0015\u0001\u00027b]\u001eT\u0011!T\u0001\u0005U\u00064\u0018-\u0003\u0002P\u0015\u0006q\u0001K]8dKN\u001c()^5mI\u0016\u0014\u0018BA)S\u0005!\u0011V\rZ5sK\u000e$(BA(K\u00031\u0001(o\\2fgNLe\u000e];u)\t)\u0006\f\u0005\u0002!-*\u0011q+I\u0001\u0005\u001d>tW\r\u0003\u0004Z\u000b\u0011\u0005\rAW\u0001\u0006gR$\u0017N\u001c\t\u0004Amk\u0016B\u0001/\"\u0005!a$-\u001f8b[\u0016t\u0004C\u00010b\u001d\t1s,\u0003\u0002a7\u0005Q1+\u001e2Qe>\u001cWm]:\n\u0005\t\u001c\'aC%oaV$8\u000b\u001e:fC6T!\u0001Y\u000e\u0002\u0015I,G-\u001b:fGR$v.A\u0007qe>\u001cWm]:PkR\u0004X\u000f\u001e\u000b\u0003+\u001eDa\u0001[\u0004\u0005\u0002\u0004I\u0017aA8viB\u0019\u0001e\u00176\u0011\u0005y[\u0017B\u00017d\u00051yU\u000f\u001e9viN#(/Z1n\u0003\u0011\u0019w\u000e]=\u0015\u0005\r{\u0007bB\u001e\t!\u0003\u0005\r!P\u0001\u000fG>\u0004\u0018\u0010\n3fM\u0006,H\u000e\u001e\u00132+\u0005\u0011(FA\u001ftW\u0005!\bCA;{\u001b\u00051(BA<y\u0003%)hn\u00195fG.,GM\u0003\u0002zC\u0005Q\u0011M\u001c8pi\u0006$\u0018n\u001c8\n\u0005m4(!E;oG\",7m[3e-\u0006\u0014\u0018.\u00198dK\u0006i\u0001O]8ek\u000e$\bK]3gSb,\u0012A \t\u0003\u0013~L1!!\u0001K\u0005\u0019\u0019FO]5oO\u0006a\u0001O]8ek\u000e$\u0018I]5usV\u0011\u0011q\u0001\t\u0004A\u0005%\u0011bAA\u0006C\t\u0019\u0011J\u001c;\u0002\u001dA\u0014x\u000eZ;di\u0016cW-\\3oiR!\u0011\u0011CA\f!\r\u0001\u00131C\u0005\u0004\u0003+\t#aA!os\"I\u0011\u0011\u0004\u0007\u0002\u0002\u0003\u0007\u0011qA\u0001\u0004q\u0012\n\u0014a\u00049s_\u0012,8\r^%uKJ\fGo\u001c:\u0016\u0005\u0005}\u0001CBA\u0011\u0003O\t\t\"\u0004\u0002\u0002$)\u0019\u0011QE\u0011\u0002\u0015\r|G\u000e\\3di&|g.\u0003\u0003\u0002*\u0005\r\"\u0001C%uKJ\fGo\u001c:\u0002\u0011\r\fg.R9vC2$B!a\f\u00026A\u0019\u0001%!\r\n\u0007\u0005M\u0012EA\u0004C_>dW-\u00198\t\u0013\u0005ea\"!AA\u0002\u0005E\u0011A\u00059s_\u0012,8\r^#mK6,g\u000e\u001e(b[\u0016$2A`A\u001e\u0011%\tIbDA\u0001\u0002\u0004\t9!\u0001\u0005iCND7i\u001c3f)\t\t9!\u0001\u0005u_N#(/\u001b8h)\u0005q\u0018AB3rk\u0006d7\u000f\u0006\u0003\u00020\u0005%\u0003\"CA\r%\u0005\u0005\t\u0019AA\t\u00031\u0001\u0016\r\u001e5SK\u0012L\'/Z2u!\t1CcE\u0003\u0015\u0003#\ni\u0006\u0005\u0004\u0002T\u0005eShQ\u0007\u0003\u0003+R1!a\u0016\"\u0003\u001d\u0011XO\u001c;j[\u0016LA!a\u0017\u0002V\t\t\u0012IY:ue\u0006\u001cGOR;oGRLwN\\\u0019\u0011\t\u0005}\u0013QM\u0007\u0003\u0003CR1!a\u0019M\u0003\tIw.C\u0002:\u0003C\"\"!!\u0014\u0002\u000b\u0005\u0004\b\u000f\\=\u0015\u0007\r\u000bi\u0007C\u0003</\u0001\u0007Q(A\u0004v]\u0006\u0004\b\u000f\\=\u0015\t\u0005M\u0014\u0011\u0010\t\u0005A\u0005UT(C\u0002\u0002x\u0005\u0012aa\u00149uS>t\u0007\u0002CA>1\u0005\u0005\t\u0019A\"\u0002\u0007a$\u0003\'\u0001\u0007xe&$XMU3qY\u0006\u001cW\r\u0006\u0002\u0002\u0002B\u0019\u0011*a!\n\u0007\u0005\u0015%J\u0001\u0004PE*,7\r\u001e"
    )
  ScalaInlineInfo: length = 0x68 (unknown attribute)
   01 00 00 14 00 66 00 67 00 00 84 00 85 00 00 65
   00 2D 00 00 6A 00 43 00 00 96 00 85 00 00 8C 00
   70 00 00 1E 00 43 00 00 54 00 55 00 00 54 00 9B
   00 00 62 00 55 00 00 62 00 9B 00 00 6F 00 70 00
   00 71 00 72 00 00 87 00 88 00 00 3A 00 3B 00 00
   7A 00 3B 00 00 6B 00 6C 00 00 46 00 47 00 00 5E
   00 47 00 00 91 00 6C 00
  ScalaSig: length = 0x3 (unknown attribute)
   05 02 00
