Classfile /Users/mw/Projects/slang-braindump/.jar/jar8/assemble/slang-braindump/assemble/content/os/PathError$NoRelativePath.class
  Last modified May 29, 2022; size 3328 bytes
  SHA-256 checksum fd442955277ee3d1a26e12f32c864a10de865c3946930951bb109c381d44a87e
  Compiled from "Path.scala"
public class os.PathError$NoRelativePath extends java.lang.IllegalArgumentException implements scala.Product
  minor version: 0
  major version: 52
  flags: (0x0021) ACC_PUBLIC, ACC_SUPER
  this_class: #2                          // os/PathError$NoRelativePath
  super_class: #4                         // java/lang/IllegalArgumentException
  interfaces: 1, fields: 2, methods: 15, attributes: 4
Constant pool:
    #1 = Utf8               os/PathError$NoRelativePath
    #2 = Class              #1            // os/PathError$NoRelativePath
    #3 = Utf8               java/lang/IllegalArgumentException
    #4 = Class              #3            // java/lang/IllegalArgumentException
    #5 = Utf8               scala/Product
    #6 = Class              #5            // scala/Product
    #7 = Utf8               Path.scala
    #8 = Utf8               os/PathError
    #9 = Class              #8            // os/PathError
   #10 = Utf8               NoRelativePath
   #11 = Utf8               src
   #12 = Utf8               Los/RelPath;
   #13 = Utf8               base
   #14 = Utf8               productElementNames
   #15 = Utf8               ()Lscala/collection/Iterator;
   #16 = Utf8               ()Lscala/collection/Iterator<Ljava/lang/String;>;
   #17 = Utf8               productElementNames$
   #18 = Utf8               (Lscala/Product;)Lscala/collection/Iterator;
   #19 = NameAndType        #17:#18       // productElementNames$:(Lscala/Product;)Lscala/collection/Iterator;
   #20 = InterfaceMethodref #6.#19        // scala/Product.productElementNames$:(Lscala/Product;)Lscala/collection/Iterator;
   #21 = Utf8               this
   #22 = Utf8               Los/PathError$NoRelativePath;
   #23 = Utf8               ()Los/RelPath;
   #24 = NameAndType        #11:#12       // src:Los/RelPath;
   #25 = Fieldref           #2.#24        // os/PathError$NoRelativePath.src:Los/RelPath;
   #26 = NameAndType        #13:#12       // base:Los/RelPath;
   #27 = Fieldref           #2.#26        // os/PathError$NoRelativePath.base:Los/RelPath;
   #28 = Utf8               copy
   #29 = Utf8               (Los/RelPath;Los/RelPath;)Los/PathError$NoRelativePath;
   #30 = Utf8               <init>
   #31 = Utf8               (Los/RelPath;Los/RelPath;)V
   #32 = NameAndType        #30:#31       // "<init>":(Los/RelPath;Los/RelPath;)V
   #33 = Methodref          #2.#32        // os/PathError$NoRelativePath."<init>":(Los/RelPath;Los/RelPath;)V
   #34 = Utf8               copy$default$1
   #35 = NameAndType        #11:#23       // src:()Los/RelPath;
   #36 = Methodref          #2.#35        // os/PathError$NoRelativePath.src:()Los/RelPath;
   #37 = Utf8               copy$default$2
   #38 = NameAndType        #13:#23       // base:()Los/RelPath;
   #39 = Methodref          #2.#38        // os/PathError$NoRelativePath.base:()Los/RelPath;
   #40 = Utf8               productPrefix
   #41 = Utf8               ()Ljava/lang/String;
   #42 = String             #10           // NoRelativePath
   #43 = Utf8               productArity
   #44 = Utf8               ()I
   #45 = Utf8               productElement
   #46 = Utf8               (I)Ljava/lang/Object;
   #47 = Utf8               x$1
   #48 = Utf8               scala/runtime/Statics
   #49 = Class              #48           // scala/runtime/Statics
   #50 = Utf8               ioobe
   #51 = NameAndType        #50:#46       // ioobe:(I)Ljava/lang/Object;
   #52 = Methodref          #49.#51       // scala/runtime/Statics.ioobe:(I)Ljava/lang/Object;
   #53 = Utf8               I
   #54 = Utf8               java/lang/Object
   #55 = Class              #54           // java/lang/Object
   #56 = Utf8               productIterator
   #57 = Utf8               ()Lscala/collection/Iterator<Ljava/lang/Object;>;
   #58 = Utf8               scala/runtime/ScalaRunTime$
   #59 = Class              #58           // scala/runtime/ScalaRunTime$
   #60 = Utf8               MODULE$
   #61 = Utf8               Lscala/runtime/ScalaRunTime$;
   #62 = NameAndType        #60:#61       // MODULE$:Lscala/runtime/ScalaRunTime$;
   #63 = Fieldref           #59.#62       // scala/runtime/ScalaRunTime$.MODULE$:Lscala/runtime/ScalaRunTime$;
   #64 = Utf8               typedProductIterator
   #65 = NameAndType        #64:#18       // typedProductIterator:(Lscala/Product;)Lscala/collection/Iterator;
   #66 = Methodref          #59.#65       // scala/runtime/ScalaRunTime$.typedProductIterator:(Lscala/Product;)Lscala/collection/Iterator;
   #67 = Utf8               canEqual
   #68 = Utf8               (Ljava/lang/Object;)Z
   #69 = Utf8               Ljava/lang/Object;
   #70 = Utf8               productElementName
   #71 = Utf8               (I)Ljava/lang/String;
   #72 = String             #11           // src
   #73 = String             #13           // base
   #74 = Utf8               java/lang/String
   #75 = Class              #74           // java/lang/String
   #76 = Utf8               hashCode
   #77 = Utf8               _hashCode
   #78 = Utf8               (Lscala/Product;)I
   #79 = NameAndType        #77:#78       // _hashCode:(Lscala/Product;)I
   #80 = Methodref          #59.#79       // scala/runtime/ScalaRunTime$._hashCode:(Lscala/Product;)I
   #81 = Utf8               equals
   #82 = NameAndType        #81:#68       // equals:(Ljava/lang/Object;)Z
   #83 = Methodref          #55.#82       // java/lang/Object.equals:(Ljava/lang/Object;)Z
   #84 = NameAndType        #67:#68       // canEqual:(Ljava/lang/Object;)Z
   #85 = Methodref          #2.#84        // os/PathError$NoRelativePath.canEqual:(Ljava/lang/Object;)Z
   #86 = Utf8               os/RelPath
   #87 = Class              #86           // os/RelPath
   #88 = Utf8               java/lang/StringBuilder
   #89 = Class              #88           // java/lang/StringBuilder
   #90 = Integer            38
   #91 = Utf8               (I)V
   #92 = NameAndType        #30:#91       // "<init>":(I)V
   #93 = Methodref          #89.#92       // java/lang/StringBuilder."<init>":(I)V
   #94 = Utf8               Can\'t relativize relative paths
   #95 = String             #94           // Can\'t relativize relative paths
   #96 = Utf8               append
   #97 = Utf8               (Ljava/lang/String;)Ljava/lang/StringBuilder;
   #98 = NameAndType        #96:#97       // append:(Ljava/lang/String;)Ljava/lang/StringBuilder;
   #99 = Methodref          #89.#98       // java/lang/StringBuilder.append:(Ljava/lang/String;)Ljava/lang/StringBuilder;
  #100 = Utf8               (Ljava/lang/Object;)Ljava/lang/StringBuilder;
  #101 = NameAndType        #96:#100      // append:(Ljava/lang/Object;)Ljava/lang/StringBuilder;
  #102 = Methodref          #89.#101      // java/lang/StringBuilder.append:(Ljava/lang/Object;)Ljava/lang/StringBuilder;
  #103 = Utf8                from
  #104 = String             #103          //  from
  #105 = Utf8               toString
  #106 = NameAndType        #105:#41      // toString:()Ljava/lang/String;
  #107 = Methodref          #89.#106      // java/lang/StringBuilder.toString:()Ljava/lang/String;
  #108 = Utf8               (Ljava/lang/String;)V
  #109 = NameAndType        #30:#108      // "<init>":(Ljava/lang/String;)V
  #110 = Methodref          #4.#109       // java/lang/IllegalArgumentException."<init>":(Ljava/lang/String;)V
  #111 = Utf8               $init$
  #112 = Utf8               (Lscala/Product;)V
  #113 = NameAndType        #111:#112     // $init$:(Lscala/Product;)V
  #114 = InterfaceMethodref #6.#113       // scala/Product.$init$:(Lscala/Product;)V
  #115 = Utf8               Code
  #116 = Utf8               LineNumberTable
  #117 = Utf8               LocalVariableTable
  #118 = Utf8               Signature
  #119 = Utf8               MethodParameters
  #120 = Utf8               StackMapTable
  #121 = Utf8               InnerClasses
  #122 = Utf8               SourceFile
  #123 = Utf8               ScalaInlineInfo
  #124 = Utf8               Scala
{
  private final os.RelPath src;
    descriptor: Los/RelPath;
    flags: (0x0012) ACC_PRIVATE, ACC_FINAL

  private final os.RelPath base;
    descriptor: Los/RelPath;
    flags: (0x0012) ACC_PRIVATE, ACC_FINAL

  public scala.collection.Iterator<java.lang.String> productElementNames();
    descriptor: ()Lscala/collection/Iterator;
    flags: (0x0001) ACC_PUBLIC
    Code:
      stack=1, locals=1, args_size=1
         0: aload_0
         1: invokestatic  #20                 // InterfaceMethod scala/Product.productElementNames$:(Lscala/Product;)Lscala/collection/Iterator;
         4: areturn
      LineNumberTable:
        line 216: 0
      LocalVariableTable:
        Start  Length  Slot  Name   Signature
            0       5     0  this   Los/PathError$NoRelativePath;
    Signature: #16                          // ()Lscala/collection/Iterator<Ljava/lang/String;>;

  public os.RelPath src();
    descriptor: ()Los/RelPath;
    flags: (0x0001) ACC_PUBLIC
    Code:
      stack=1, locals=1, args_size=1
         0: aload_0
         1: getfield      #25                 // Field src:Los/RelPath;
         4: areturn
      LineNumberTable:
        line 216: 0
      LocalVariableTable:
        Start  Length  Slot  Name   Signature
            0       5     0  this   Los/PathError$NoRelativePath;

  public os.RelPath base();
    descriptor: ()Los/RelPath;
    flags: (0x0001) ACC_PUBLIC
    Code:
      stack=1, locals=1, args_size=1
         0: aload_0
         1: getfield      #27                 // Field base:Los/RelPath;
         4: areturn
      LineNumberTable:
        line 216: 0
      LocalVariableTable:
        Start  Length  Slot  Name   Signature
            0       5     0  this   Los/PathError$NoRelativePath;

  public os.PathError$NoRelativePath copy(os.RelPath, os.RelPath);
    descriptor: (Los/RelPath;Los/RelPath;)Los/PathError$NoRelativePath;
    flags: (0x0001) ACC_PUBLIC
    Code:
      stack=4, locals=3, args_size=3
         0: new           #2                  // class os/PathError$NoRelativePath
         3: dup
         4: aload_1
         5: aload_2
         6: invokespecial #33                 // Method "<init>":(Los/RelPath;Los/RelPath;)V
         9: areturn
      LineNumberTable:
        line 216: 0
      LocalVariableTable:
        Start  Length  Slot  Name   Signature
            0      10     0  this   Los/PathError$NoRelativePath;
            0      10     1   src   Los/RelPath;
            0      10     2  base   Los/RelPath;
    MethodParameters:
      Name                           Flags
      src                            final
      base                           final

  public os.RelPath copy$default$1();
    descriptor: ()Los/RelPath;
    flags: (0x0001) ACC_PUBLIC
    Code:
      stack=1, locals=1, args_size=1
         0: aload_0
         1: invokevirtual #36                 // Method src:()Los/RelPath;
         4: areturn
      LineNumberTable:
        line 216: 0
      LocalVariableTable:
        Start  Length  Slot  Name   Signature
            0       5     0  this   Los/PathError$NoRelativePath;

  public os.RelPath copy$default$2();
    descriptor: ()Los/RelPath;
    flags: (0x0001) ACC_PUBLIC
    Code:
      stack=1, locals=1, args_size=1
         0: aload_0
         1: invokevirtual #39                 // Method base:()Los/RelPath;
         4: areturn
      LineNumberTable:
        line 216: 0
      LocalVariableTable:
        Start  Length  Slot  Name   Signature
            0       5     0  this   Los/PathError$NoRelativePath;

  public java.lang.String productPrefix();
    descriptor: ()Ljava/lang/String;
    flags: (0x0001) ACC_PUBLIC
    Code:
      stack=1, locals=1, args_size=1
         0: ldc           #42                 // String NoRelativePath
         2: areturn
      LineNumberTable:
        line 216: 0
      LocalVariableTable:
        Start  Length  Slot  Name   Signature
            0       3     0  this   Los/PathError$NoRelativePath;

  public int productArity();
    descriptor: ()I
    flags: (0x0001) ACC_PUBLIC
    Code:
      stack=1, locals=1, args_size=1
         0: iconst_2
         1: ireturn
      LineNumberTable:
        line 216: 0
      LocalVariableTable:
        Start  Length  Slot  Name   Signature
            0       2     0  this   Los/PathError$NoRelativePath;

  public java.lang.Object productElement(int);
    descriptor: (I)Ljava/lang/Object;
    flags: (0x0001) ACC_PUBLIC
    Code:
      stack=1, locals=3, args_size=2
         0: iload_1
         1: istore_2
         2: iload_2
         3: tableswitch   { // 0 to 1
                       0: 24
                       1: 31
                 default: 38
            }
        24: aload_0
        25: invokevirtual #36                 // Method src:()Los/RelPath;
        28: goto          45
        31: aload_0
        32: invokevirtual #39                 // Method base:()Los/RelPath;
        35: goto          45
        38: iload_1
        39: invokestatic  #52                 // Method scala/runtime/Statics.ioobe:(I)Ljava/lang/Object;
        42: goto          45
        45: areturn
      StackMapTable: number_of_entries = 4
        frame_type = 252 /* append */
          offset_delta = 24
          locals = [ int ]
        frame_type = 6 /* same */
        frame_type = 6 /* same */
        frame_type = 70 /* same_locals_1_stack_item */
          stack = [ class java/lang/Object ]
      LineNumberTable:
        line 216: 0
      LocalVariableTable:
        Start  Length  Slot  Name   Signature
            0      46     0  this   Los/PathError$NoRelativePath;
            0      46     1   x$1   I
    MethodParameters:
      Name                           Flags
      x$1                            final

  public scala.collection.Iterator<java.lang.Object> productIterator();
    descriptor: ()Lscala/collection/Iterator;
    flags: (0x0001) ACC_PUBLIC
    Code:
      stack=2, locals=1, args_size=1
         0: getstatic     #63                 // Field scala/runtime/ScalaRunTime$.MODULE$:Lscala/runtime/ScalaRunTime$;
         3: aload_0
         4: invokevirtual #66                 // Method scala/runtime/ScalaRunTime$.typedProductIterator:(Lscala/Product;)Lscala/collection/Iterator;
         7: areturn
      LineNumberTable:
        line 216: 0
      LocalVariableTable:
        Start  Length  Slot  Name   Signature
            0       8     0  this   Los/PathError$NoRelativePath;
    Signature: #57                          // ()Lscala/collection/Iterator<Ljava/lang/Object;>;

  public boolean canEqual(java.lang.Object);
    descriptor: (Ljava/lang/Object;)Z
    flags: (0x0001) ACC_PUBLIC
    Code:
      stack=1, locals=2, args_size=2
         0: aload_1
         1: instanceof    #2                  // class os/PathError$NoRelativePath
         4: ireturn
      LineNumberTable:
        line 216: 0
      LocalVariableTable:
        Start  Length  Slot  Name   Signature
            0       5     0  this   Los/PathError$NoRelativePath;
            0       5     1   x$1   Ljava/lang/Object;
    MethodParameters:
      Name                           Flags
      x$1                            final

  public java.lang.String productElementName(int);
    descriptor: (I)Ljava/lang/String;
    flags: (0x0001) ACC_PUBLIC
    Code:
      stack=1, locals=3, args_size=2
         0: iload_1
         1: istore_2
         2: iload_2
         3: tableswitch   { // 0 to 1
                       0: 24
                       1: 29
                 default: 34
            }
        24: ldc           #72                 // String src
        26: goto          44
        29: ldc           #73                 // String base
        31: goto          44
        34: iload_1
        35: invokestatic  #52                 // Method scala/runtime/Statics.ioobe:(I)Ljava/lang/Object;
        38: checkcast     #75                 // class java/lang/String
        41: goto          44
        44: areturn
      StackMapTable: number_of_entries = 4
        frame_type = 252 /* append */
          offset_delta = 24
          locals = [ int ]
        frame_type = 4 /* same */
        frame_type = 4 /* same */
        frame_type = 73 /* same_locals_1_stack_item */
          stack = [ class java/lang/String ]
      LineNumberTable:
        line 216: 0
      LocalVariableTable:
        Start  Length  Slot  Name   Signature
            0      45     0  this   Los/PathError$NoRelativePath;
            0      45     1   x$1   I
    MethodParameters:
      Name                           Flags
      x$1                            final

  public int hashCode();
    descriptor: ()I
    flags: (0x0001) ACC_PUBLIC
    Code:
      stack=2, locals=1, args_size=1
         0: getstatic     #63                 // Field scala/runtime/ScalaRunTime$.MODULE$:Lscala/runtime/ScalaRunTime$;
         3: aload_0
         4: invokevirtual #80                 // Method scala/runtime/ScalaRunTime$._hashCode:(Lscala/Product;)I
         7: ireturn
      LineNumberTable:
        line 216: 0
      LocalVariableTable:
        Start  Length  Slot  Name   Signature
            0       8     0  this   Los/PathError$NoRelativePath;

  public boolean equals(java.lang.Object);
    descriptor: (Ljava/lang/Object;)Z
    flags: (0x0001) ACC_PUBLIC
    Code:
      stack=2, locals=7, args_size=2
         0: aload_0
         1: aload_1
         2: if_acmpeq     118
         5: aload_1
         6: astore_3
         7: aload_3
         8: instanceof    #2                  // class os/PathError$NoRelativePath
        11: ifeq          19
        14: iconst_1
        15: istore_2
        16: goto          27
        19: goto          22
        22: iconst_0
        23: istore_2
        24: goto          27
        27: iload_2
        28: ifeq          122
        31: aload_1
        32: checkcast     #2                  // class os/PathError$NoRelativePath
        35: astore        4
        37: aload_0
        38: invokevirtual #36                 // Method src:()Los/RelPath;
        41: aload         4
        43: invokevirtual #36                 // Method src:()Los/RelPath;
        46: astore        5
        48: dup
        49: ifnonnull     61
        52: pop
        53: aload         5
        55: ifnull        69
        58: goto          114
        61: aload         5
        63: invokevirtual #83                 // Method java/lang/Object.equals:(Ljava/lang/Object;)Z
        66: ifeq          114
        69: aload_0
        70: invokevirtual #39                 // Method base:()Los/RelPath;
        73: aload         4
        75: invokevirtual #39                 // Method base:()Los/RelPath;
        78: astore        6
        80: dup
        81: ifnonnull     93
        84: pop
        85: aload         6
        87: ifnull        101
        90: goto          114
        93: aload         6
        95: invokevirtual #83                 // Method java/lang/Object.equals:(Ljava/lang/Object;)Z
        98: ifeq          114
       101: aload         4
       103: aload_0
       104: invokevirtual #85                 // Method canEqual:(Ljava/lang/Object;)Z
       107: ifeq          114
       110: iconst_1
       111: goto          115
       114: iconst_0
       115: ifeq          122
       118: iconst_1
       119: goto          123
       122: iconst_0
       123: ireturn
      StackMapTable: number_of_entries = 12
        frame_type = 253 /* append */
          offset_delta = 19
          locals = [ top, class java/lang/Object ]
        frame_type = 2 /* same */
        frame_type = 255 /* full_frame */
          offset_delta = 4
          locals = [ class os/PathError$NoRelativePath, class java/lang/Object, int, class java/lang/Object ]
          stack = []
        frame_type = 255 /* full_frame */
          offset_delta = 33
          locals = [ class os/PathError$NoRelativePath, class java/lang/Object, int, class java/lang/Object, class os/PathError$NoRelativePath, class os/RelPath ]
          stack = [ class os/RelPath ]
        frame_type = 7 /* same */
        frame_type = 255 /* full_frame */
          offset_delta = 23
          locals = [ class os/PathError$NoRelativePath, class java/lang/Object, int, class java/lang/Object, class os/PathError$NoRelativePath, class os/RelPath, class os/RelPath ]
          stack = [ class os/RelPath ]
        frame_type = 7 /* same */
        frame_type = 250 /* chop */
          offset_delta = 12
        frame_type = 64 /* same_locals_1_stack_item */
          stack = [ int ]
        frame_type = 255 /* full_frame */
          offset_delta = 2
          locals = [ class os/PathError$NoRelativePath, class java/lang/Object ]
          stack = []
        frame_type = 253 /* append */
          offset_delta = 3
          locals = [ int, class java/lang/Object ]
        frame_type = 255 /* full_frame */
          offset_delta = 0
          locals = [ class os/PathError$NoRelativePath, class java/lang/Object ]
          stack = [ int ]
      LineNumberTable:
        line 216: 0
      LocalVariableTable:
        Start  Length  Slot  Name   Signature
            0     124     0  this   Los/PathError$NoRelativePath;
            0     124     1   x$1   Ljava/lang/Object;
    MethodParameters:
      Name                           Flags
      x$1                            final

  public os.PathError$NoRelativePath(os.RelPath, os.RelPath);
    descriptor: (Los/RelPath;Los/RelPath;)V
    flags: (0x0001) ACC_PUBLIC
    Code:
      stack=4, locals=3, args_size=3
         0: aload_0
         1: aload_1
         2: putfield      #25                 // Field src:Los/RelPath;
         5: aload_0
         6: aload_2
         7: putfield      #27                 // Field base:Los/RelPath;
        10: aload_0
        11: new           #89                 // class java/lang/StringBuilder
        14: dup
        15: ldc           #90                 // int 38
        17: invokespecial #93                 // Method java/lang/StringBuilder."<init>":(I)V
        20: ldc           #95                 // String Can\'t relativize relative paths
        22: invokevirtual #99                 // Method java/lang/StringBuilder.append:(Ljava/lang/String;)Ljava/lang/StringBuilder;
        25: aload_1
        26: invokevirtual #102                // Method java/lang/StringBuilder.append:(Ljava/lang/Object;)Ljava/lang/StringBuilder;
        29: ldc           #104                // String  from
        31: invokevirtual #99                 // Method java/lang/StringBuilder.append:(Ljava/lang/String;)Ljava/lang/StringBuilder;
        34: aload_2
        35: invokevirtual #102                // Method java/lang/StringBuilder.append:(Ljava/lang/Object;)Ljava/lang/StringBuilder;
        38: invokevirtual #107                // Method java/lang/StringBuilder.toString:()Ljava/lang/String;
        41: invokespecial #110                // Method java/lang/IllegalArgumentException."<init>":(Ljava/lang/String;)V
        44: aload_0
        45: invokestatic  #114                // InterfaceMethod scala/Product.$init$:(Lscala/Product;)V
        48: return
      LineNumberTable:
        line 216: 0
        line 217: 10
        line 216: 48
      LocalVariableTable:
        Start  Length  Slot  Name   Signature
            0      49     0  this   Los/PathError$NoRelativePath;
            0      49     1   src   Los/RelPath;
            0      49     2  base   Los/RelPath;
    MethodParameters:
      Name                           Flags
      src                            final
      base                           final
}
InnerClasses:
  public static #10= #2 of #9;            // NoRelativePath=class os/PathError$NoRelativePath of class os/PathError
SourceFile: "Path.scala"
  ScalaInlineInfo: length = 0x4F (unknown attribute)
   01 00 00 0F 00 1E 00 1F 00 00 0D 00 17 00 00 43
   00 44 00 00 1C 00 1D 00 00 22 00 17 00 00 25 00
   17 00 00 51 00 44 00 00 4C 00 2C 00 00 2B 00 2C
   00 00 2D 00 2E 00 00 46 00 47 00 00 0E 00 0F 00
   00 38 00 0F 00 00 28 00 29 00 00 0B 00 17 00
  Scala: length = 0x0 (unknown attribute)

