Classfile /Users/mw/Projects/slang-braindump/.jar/jar8/assemble/slang-braindump/assemble/content/os/PermSet$.class
  Last modified May 29, 2022; size 6122 bytes
  SHA-256 checksum 11def1d59413e3c9fbbaf8af94127e44523fc4973d85ec957ca492f84d083ab1
  Compiled from "Model.scala"
public final class os.PermSet$ implements java.io.Serializable
  minor version: 0
  major version: 52
  flags: (0x0031) ACC_PUBLIC, ACC_FINAL, ACC_SUPER
  this_class: #2                          // os/PermSet$
  super_class: #4                         // java/lang/Object
  interfaces: 1, fields: 1, methods: 15, attributes: 5
Constant pool:
    #1 = Utf8               os/PermSet$
    #2 = Class              #1            // os/PermSet$
    #3 = Utf8               java/lang/Object
    #4 = Class              #3            // java/lang/Object
    #5 = Utf8               java/io/Serializable
    #6 = Class              #5            // java/io/Serializable
    #7 = Utf8               Model.scala
    #8 = Utf8               java/lang/invoke/MethodHandles$Lookup
    #9 = Class              #8            // java/lang/invoke/MethodHandles$Lookup
   #10 = Utf8               java/lang/invoke/MethodHandles
   #11 = Class              #10           // java/lang/invoke/MethodHandles
   #12 = Utf8               Lookup
   #13 = Utf8               MODULE$
   #14 = Utf8               Los/PermSet$;
   #15 = Utf8               <clinit>
   #16 = Utf8               ()V
   #17 = Utf8               <init>
   #18 = NameAndType        #17:#16       // "<init>":()V
   #19 = Methodref          #2.#18        // os/PermSet$."<init>":()V
   #20 = NameAndType        #13:#14       // MODULE$:Los/PermSet$;
   #21 = Fieldref           #2.#20        // os/PermSet$.MODULE$:Los/PermSet$;
   #22 = Utf8               fromSet
   #23 = Utf8               (Ljava/util/Set;)Los/PermSet;
   #24 = Utf8               (Ljava/util/Set<Ljava/nio/file/attribute/PosixFilePermission;>;)Los/PermSet;
   #25 = Utf8               value
   #26 = Utf8               scala/runtime/IntRef
   #27 = Class              #26           // scala/runtime/IntRef
   #28 = Utf8               create
   #29 = Utf8               (I)Lscala/runtime/IntRef;
   #30 = NameAndType        #28:#29       // create:(I)Lscala/runtime/IntRef;
   #31 = Methodref          #27.#30       // scala/runtime/IntRef.create:(I)Lscala/runtime/IntRef;
   #32 = Utf8               java/nio/file/attribute/PosixFilePermission
   #33 = Class              #32           // java/nio/file/attribute/PosixFilePermission
   #34 = Utf8               OWNER_READ
   #35 = Utf8               Ljava/nio/file/attribute/PosixFilePermission;
   #36 = NameAndType        #34:#35       // OWNER_READ:Ljava/nio/file/attribute/PosixFilePermission;
   #37 = Fieldref           #33.#36       // java/nio/file/attribute/PosixFilePermission.OWNER_READ:Ljava/nio/file/attribute/PosixFilePermission;
   #38 = Utf8               add$1
   #39 = Utf8               (Ljava/nio/file/attribute/PosixFilePermission;Ljava/util/Set;Lscala/runtime/IntRef;)V
   #40 = NameAndType        #38:#39       // add$1:(Ljava/nio/file/attribute/PosixFilePermission;Ljava/util/Set;Lscala/runtime/IntRef;)V
   #41 = Methodref          #2.#40        // os/PermSet$.add$1:(Ljava/nio/file/attribute/PosixFilePermission;Ljava/util/Set;Lscala/runtime/IntRef;)V
   #42 = Utf8               OWNER_WRITE
   #43 = NameAndType        #42:#35       // OWNER_WRITE:Ljava/nio/file/attribute/PosixFilePermission;
   #44 = Fieldref           #33.#43       // java/nio/file/attribute/PosixFilePermission.OWNER_WRITE:Ljava/nio/file/attribute/PosixFilePermission;
   #45 = Utf8               OWNER_EXECUTE
   #46 = NameAndType        #45:#35       // OWNER_EXECUTE:Ljava/nio/file/attribute/PosixFilePermission;
   #47 = Fieldref           #33.#46       // java/nio/file/attribute/PosixFilePermission.OWNER_EXECUTE:Ljava/nio/file/attribute/PosixFilePermission;
   #48 = Utf8               GROUP_READ
   #49 = NameAndType        #48:#35       // GROUP_READ:Ljava/nio/file/attribute/PosixFilePermission;
   #50 = Fieldref           #33.#49       // java/nio/file/attribute/PosixFilePermission.GROUP_READ:Ljava/nio/file/attribute/PosixFilePermission;
   #51 = Utf8               GROUP_WRITE
   #52 = NameAndType        #51:#35       // GROUP_WRITE:Ljava/nio/file/attribute/PosixFilePermission;
   #53 = Fieldref           #33.#52       // java/nio/file/attribute/PosixFilePermission.GROUP_WRITE:Ljava/nio/file/attribute/PosixFilePermission;
   #54 = Utf8               GROUP_EXECUTE
   #55 = NameAndType        #54:#35       // GROUP_EXECUTE:Ljava/nio/file/attribute/PosixFilePermission;
   #56 = Fieldref           #33.#55       // java/nio/file/attribute/PosixFilePermission.GROUP_EXECUTE:Ljava/nio/file/attribute/PosixFilePermission;
   #57 = Utf8               OTHERS_READ
   #58 = NameAndType        #57:#35       // OTHERS_READ:Ljava/nio/file/attribute/PosixFilePermission;
   #59 = Fieldref           #33.#58       // java/nio/file/attribute/PosixFilePermission.OTHERS_READ:Ljava/nio/file/attribute/PosixFilePermission;
   #60 = Utf8               OTHERS_WRITE
   #61 = NameAndType        #60:#35       // OTHERS_WRITE:Ljava/nio/file/attribute/PosixFilePermission;
   #62 = Fieldref           #33.#61       // java/nio/file/attribute/PosixFilePermission.OTHERS_WRITE:Ljava/nio/file/attribute/PosixFilePermission;
   #63 = Utf8               OTHERS_EXECUTE
   #64 = NameAndType        #63:#35       // OTHERS_EXECUTE:Ljava/nio/file/attribute/PosixFilePermission;
   #65 = Fieldref           #33.#64       // java/nio/file/attribute/PosixFilePermission.OTHERS_EXECUTE:Ljava/nio/file/attribute/PosixFilePermission;
   #66 = Utf8               os/PermSet
   #67 = Class              #66           // os/PermSet
   #68 = Utf8               elem
   #69 = Utf8               I
   #70 = NameAndType        #68:#69       // elem:I
   #71 = Fieldref           #27.#70       // scala/runtime/IntRef.elem:I
   #72 = Utf8               (I)V
   #73 = NameAndType        #17:#72       // "<init>":(I)V
   #74 = Methodref          #67.#73       // os/PermSet."<init>":(I)V
   #75 = Utf8               total
   #76 = Utf8               Lscala/runtime/IntRef;
   #77 = Utf8               this
   #78 = Utf8               Ljava/util/Set;
   #79 = Utf8               fromString
   #80 = Utf8               (Ljava/lang/String;)Los/PermSet;
   #81 = Utf8               arg
   #82 = Utf8               scala/Predef$
   #83 = Class              #82           // scala/Predef$
   #84 = Utf8               Lscala/Predef$;
   #85 = NameAndType        #13:#84       // MODULE$:Lscala/Predef$;
   #86 = Fieldref           #83.#85       // scala/Predef$.MODULE$:Lscala/Predef$;
   #87 = Utf8               java/lang/String
   #88 = Class              #87           // java/lang/String
   #89 = Utf8               length
   #90 = Utf8               ()I
   #91 = NameAndType        #89:#90       // length:()I
   #92 = Methodref          #88.#91       // java/lang/String.length:()I
   #93 = Utf8               ()Ljava/lang/Object;
   #94 = MethodType         #93           //  ()Ljava/lang/Object;
   #95 = Utf8               $anonfun$fromString$1
   #96 = Utf8               (Ljava/lang/String;)Ljava/lang/String;
   #97 = NameAndType        #95:#96       // $anonfun$fromString$1:(Ljava/lang/String;)Ljava/lang/String;
   #98 = Methodref          #2.#97        // os/PermSet$.$anonfun$fromString$1:(Ljava/lang/String;)Ljava/lang/String;
   #99 = MethodHandle       6:#98         // REF_invokeStatic os/PermSet$.$anonfun$fromString$1:(Ljava/lang/String;)Ljava/lang/String;
  #100 = Utf8               ()Ljava/lang/String;
  #101 = MethodType         #100          //  ()Ljava/lang/String;
  #102 = Integer            5
  #103 = Integer            1
  #104 = Utf8               java/lang/invoke/LambdaMetafactory
  #105 = Class              #104          // java/lang/invoke/LambdaMetafactory
  #106 = Utf8               altMetafactory
  #107 = Utf8               (Ljava/lang/invoke/MethodHandles$Lookup;Ljava/lang/String;Ljava/lang/invoke/MethodType;[Ljava/lang/Object;)Ljava/lang/invoke/CallSite;
  #108 = NameAndType        #106:#107     // altMetafactory:(Ljava/lang/invoke/MethodHandles$Lookup;Ljava/lang/String;Ljava/lang/invoke/MethodType;[Ljava/lang/Object;)Ljava/lang/invoke/CallSite;
  #109 = Methodref          #105.#108     // java/lang/invoke/LambdaMetafactory.altMetafactory:(Ljava/lang/invoke/MethodHandles$Lookup;Ljava/lang/String;Ljava/lang/invoke/MethodType;[Ljava/lang/Object;)Ljava/lang/invoke/CallSite;
  #110 = MethodHandle       6:#109        // REF_invokeStatic java/lang/invoke/LambdaMetafactory.altMetafactory:(Ljava/lang/invoke/MethodHandles$Lookup;Ljava/lang/String;Ljava/lang/invoke/MethodType;[Ljava/lang/Object;)Ljava/lang/invoke/CallSite;
  #111 = Utf8               apply
  #112 = Utf8               (Ljava/lang/String;)Lscala/Function0;
  #113 = NameAndType        #111:#112     // apply:(Ljava/lang/String;)Lscala/Function0;
  #114 = InvokeDynamic      #0:#113       // #0:apply:(Ljava/lang/String;)Lscala/Function0;
  #115 = Utf8               require
  #116 = Utf8               (ZLscala/Function0;)V
  #117 = NameAndType        #115:#116     // require:(ZLscala/Function0;)V
  #118 = Methodref          #83.#117      // scala/Predef$.require:(ZLscala/Function0;)V
  #119 = Utf8               add$2
  #120 = Utf8               (Ljava/nio/file/attribute/PosixFilePermission;Ljava/lang/String;Lscala/runtime/IntRef;)V
  #121 = NameAndType        #119:#120     // add$2:(Ljava/nio/file/attribute/PosixFilePermission;Ljava/lang/String;Lscala/runtime/IntRef;)V
  #122 = Methodref          #2.#121       // os/PermSet$.add$2:(Ljava/nio/file/attribute/PosixFilePermission;Ljava/lang/String;Lscala/runtime/IntRef;)V
  #123 = Utf8               perms
  #124 = Utf8               Ljava/lang/String;
  #125 = Utf8               fromInt
  #126 = Utf8               (I)Los/PermSet;
  #127 = Utf8               permToMask
  #128 = Utf8               (Ljava/nio/file/attribute/PosixFilePermission;)I
  #129 = Utf8               permToOffset
  #130 = NameAndType        #129:#128     // permToOffset:(Ljava/nio/file/attribute/PosixFilePermission;)I
  #131 = Methodref          #2.#130       // os/PermSet$.permToOffset:(Ljava/nio/file/attribute/PosixFilePermission;)I
  #132 = Utf8               permToChar
  #133 = Utf8               (Ljava/nio/file/attribute/PosixFilePermission;)C
  #134 = Utf8               equals
  #135 = Utf8               (Ljava/lang/Object;)Z
  #136 = NameAndType        #134:#135     // equals:(Ljava/lang/Object;)Z
  #137 = Methodref          #4.#136       // java/lang/Object.equals:(Ljava/lang/Object;)Z
  #138 = Utf8               scala/MatchError
  #139 = Class              #138          // scala/MatchError
  #140 = Utf8               (Ljava/lang/Object;)V
  #141 = NameAndType        #17:#140      // "<init>":(Ljava/lang/Object;)V
  #142 = Methodref          #139.#141     // scala/MatchError."<init>":(Ljava/lang/Object;)V
  #143 = Utf8               unapply
  #144 = Utf8               (Los/PermSet;)Lscala/Option;
  #145 = Utf8               (Los/PermSet;)Lscala/Option<Ljava/lang/Object;>;
  #146 = Utf8               x$0
  #147 = Utf8               scala/None$
  #148 = Class              #147          // scala/None$
  #149 = Utf8               Lscala/None$;
  #150 = NameAndType        #13:#149      // MODULE$:Lscala/None$;
  #151 = Fieldref           #148.#150     // scala/None$.MODULE$:Lscala/None$;
  #152 = Utf8               scala/Some
  #153 = Class              #152          // scala/Some
  #154 = NameAndType        #25:#90       // value:()I
  #155 = Methodref          #67.#154      // os/PermSet.value:()I
  #156 = Utf8               scala/runtime/BoxesRunTime
  #157 = Class              #156          // scala/runtime/BoxesRunTime
  #158 = Utf8               boxToInteger
  #159 = Utf8               (I)Ljava/lang/Integer;
  #160 = NameAndType        #158:#159     // boxToInteger:(I)Ljava/lang/Integer;
  #161 = Methodref          #157.#160     // scala/runtime/BoxesRunTime.boxToInteger:(I)Ljava/lang/Integer;
  #162 = Methodref          #153.#141     // scala/Some."<init>":(Ljava/lang/Object;)V
  #163 = Utf8               Los/PermSet;
  #164 = Utf8               scala/Option
  #165 = Class              #164          // scala/Option
  #166 = Utf8               writeReplace
  #167 = Utf8               scala/runtime/ModuleSerializationProxy
  #168 = Class              #167          // scala/runtime/ModuleSerializationProxy
  #169 = Utf8               (Ljava/lang/Class;)V
  #170 = NameAndType        #17:#169      // "<init>":(Ljava/lang/Class;)V
  #171 = Methodref          #168.#170     // scala/runtime/ModuleSerializationProxy."<init>":(Ljava/lang/Class;)V
  #172 = Utf8               perm
  #173 = Utf8               value$1
  #174 = Utf8               total$1
  #175 = Utf8               java/util/Set
  #176 = Class              #175          // java/util/Set
  #177 = Utf8               contains
  #178 = NameAndType        #177:#135     // contains:(Ljava/lang/Object;)Z
  #179 = InterfaceMethodref #176.#178     // java/util/Set.contains:(Ljava/lang/Object;)Z
  #180 = NameAndType        #127:#128     // permToMask:(Ljava/nio/file/attribute/PosixFilePermission;)I
  #181 = Methodref          #2.#180       // os/PermSet$.permToMask:(Ljava/nio/file/attribute/PosixFilePermission;)I
  #182 = Utf8               arg$1
  #183 = Utf8               java/lang/StringBuilder
  #184 = Class              #183          // java/lang/StringBuilder
  #185 = Integer            50
  #186 = Methodref          #184.#73      // java/lang/StringBuilder."<init>":(I)V
  #187 = Utf8               Invalid permissions string: must be length 9, not
  #188 = String             #187          // Invalid permissions string: must be length 9, not
  #189 = Utf8               append
  #190 = Utf8               (Ljava/lang/String;)Ljava/lang/StringBuilder;
  #191 = NameAndType        #189:#190     // append:(Ljava/lang/String;)Ljava/lang/StringBuilder;
  #192 = Methodref          #184.#191     // java/lang/StringBuilder.append:(Ljava/lang/String;)Ljava/lang/StringBuilder;
  #193 = Utf8               (I)Ljava/lang/StringBuilder;
  #194 = NameAndType        #189:#193     // append:(I)Ljava/lang/StringBuilder;
  #195 = Methodref          #184.#194     // java/lang/StringBuilder.append:(I)Ljava/lang/StringBuilder;
  #196 = Utf8               toString
  #197 = NameAndType        #196:#100     // toString:()Ljava/lang/String;
  #198 = Methodref          #184.#197     // java/lang/StringBuilder.toString:()Ljava/lang/String;
  #199 = Utf8               perms$1
  #200 = NameAndType        #132:#133     // permToChar:(Ljava/nio/file/attribute/PosixFilePermission;)C
  #201 = Methodref          #2.#200       // os/PermSet$.permToChar:(Ljava/nio/file/attribute/PosixFilePermission;)C
  #202 = Utf8               scala/collection/StringOps$
  #203 = Class              #202          // scala/collection/StringOps$
  #204 = Utf8               Lscala/collection/StringOps$;
  #205 = NameAndType        #13:#204      // MODULE$:Lscala/collection/StringOps$;
  #206 = Fieldref           #203.#205     // scala/collection/StringOps$.MODULE$:Lscala/collection/StringOps$;
  #207 = Utf8               augmentString
  #208 = NameAndType        #207:#96      // augmentString:(Ljava/lang/String;)Ljava/lang/String;
  #209 = Methodref          #83.#208      // scala/Predef$.augmentString:(Ljava/lang/String;)Ljava/lang/String;
  #210 = Utf8               apply$extension
  #211 = Utf8               (Ljava/lang/String;I)C
  #212 = NameAndType        #210:#211     // apply$extension:(Ljava/lang/String;I)C
  #213 = Methodref          #203.#212     // scala/collection/StringOps$.apply$extension:(Ljava/lang/String;I)C
  #214 = Utf8               java/lang/Exception
  #215 = Class              #214          // java/lang/Exception
  #216 = Integer            78
  #217 = Utf8               Invalid permissions string: unknown character [
  #218 = String             #217          // Invalid permissions string: unknown character [
  #219 = Utf8               (C)Ljava/lang/StringBuilder;
  #220 = NameAndType        #189:#219     // append:(C)Ljava/lang/StringBuilder;
  #221 = Methodref          #184.#220     // java/lang/StringBuilder.append:(C)Ljava/lang/StringBuilder;
  #222 = Utf8               ]
  #223 = String             #222          // ]
  #224 = Utf8               at index
  #225 = String             #224          // at index
  #226 = Utf8               . Must be [-] or [
  #227 = String             #226          // . Must be [-] or [
  #228 = Utf8               ].
  #229 = String             #228          // ].
  #230 = Utf8               (Ljava/lang/String;)V
  #231 = NameAndType        #17:#230      // "<init>":(Ljava/lang/String;)V
  #232 = Methodref          #215.#231     // java/lang/Exception."<init>":(Ljava/lang/String;)V
  #233 = Utf8               i
  #234 = Utf8               expected
  #235 = Utf8               C
  #236 = Methodref          #4.#18        // java/lang/Object."<init>":()V
  #237 = Utf8               $deserializeLambda$
  #238 = Utf8               (Ljava/lang/invoke/SerializedLambda;)Ljava/lang/Object;
  #239 = Utf8               scala/runtime/LambdaDeserialize
  #240 = Class              #239          // scala/runtime/LambdaDeserialize
  #241 = Utf8               bootstrap
  #242 = Utf8               (Ljava/lang/invoke/MethodHandles$Lookup;Ljava/lang/String;Ljava/lang/invoke/MethodType;[Ljava/lang/invoke/MethodHandle;)Ljava/lang/invoke/CallSite;
  #243 = NameAndType        #241:#242     // bootstrap:(Ljava/lang/invoke/MethodHandles$Lookup;Ljava/lang/String;Ljava/lang/invoke/MethodType;[Ljava/lang/invoke/MethodHandle;)Ljava/lang/invoke/CallSite;
  #244 = Methodref          #240.#243     // scala/runtime/LambdaDeserialize.bootstrap:(Ljava/lang/invoke/MethodHandles$Lookup;Ljava/lang/String;Ljava/lang/invoke/MethodType;[Ljava/lang/invoke/MethodHandle;)Ljava/lang/invoke/CallSite;
  #245 = MethodHandle       6:#244        // REF_invokeStatic scala/runtime/LambdaDeserialize.bootstrap:(Ljava/lang/invoke/MethodHandles$Lookup;Ljava/lang/String;Ljava/lang/invoke/MethodType;[Ljava/lang/invoke/MethodHandle;)Ljava/lang/invoke/CallSite;
  #246 = Utf8               lambdaDeserialize
  #247 = NameAndType        #246:#238     // lambdaDeserialize:(Ljava/lang/invoke/SerializedLambda;)Ljava/lang/Object;
  #248 = InvokeDynamic      #1:#247       // #1:lambdaDeserialize:(Ljava/lang/invoke/SerializedLambda;)Ljava/lang/Object;
  #249 = Utf8               Code
  #250 = Utf8               LineNumberTable
  #251 = Utf8               LocalVariableTable
  #252 = Utf8               Signature
  #253 = Utf8               MethodParameters
  #254 = Utf8               StackMapTable
  #255 = Utf8               InnerClasses
  #256 = Utf8               SourceFile
  #257 = Utf8               BootstrapMethods
  #258 = Utf8               ScalaInlineInfo
  #259 = Utf8               Scala
{
  public static final os.PermSet$ MODULE$;
    descriptor: Los/PermSet$;
    flags: (0x0019) ACC_PUBLIC, ACC_STATIC, ACC_FINAL

  public static {};
    descriptor: ()V
    flags: (0x0009) ACC_PUBLIC, ACC_STATIC
    Code:
      stack=2, locals=0, args_size=0
         0: new           #2                  // class os/PermSet$
         3: dup
         4: invokespecial #19                 // Method "<init>":()V
         7: putstatic     #21                 // Field MODULE$:Los/PermSet$;
        10: return
      LineNumberTable:
        line 21: 0

  public os.PermSet fromSet(java.util.Set<java.nio.file.attribute.PosixFilePermission>);
    descriptor: (Ljava/util/Set;)Los/PermSet;
    flags: (0x0001) ACC_PUBLIC
    Code:
      stack=4, locals=3, args_size=2
         0: iconst_0
         1: invokestatic  #31                 // Method scala/runtime/IntRef.create:(I)Lscala/runtime/IntRef;
         4: astore_2
         5: aload_0
         6: getstatic     #37                 // Field java/nio/file/attribute/PosixFilePermission.OWNER_READ:Ljava/nio/file/attribute/PosixFilePermission;
         9: aload_1
        10: aload_2
        11: invokespecial #41                 // Method add$1:(Ljava/nio/file/attribute/PosixFilePermission;Ljava/util/Set;Lscala/runtime/IntRef;)V
        14: aload_0
        15: getstatic     #44                 // Field java/nio/file/attribute/PosixFilePermission.OWNER_WRITE:Ljava/nio/file/attribute/PosixFilePermission;
        18: aload_1
        19: aload_2
        20: invokespecial #41                 // Method add$1:(Ljava/nio/file/attribute/PosixFilePermission;Ljava/util/Set;Lscala/runtime/IntRef;)V
        23: aload_0
        24: getstatic     #47                 // Field java/nio/file/attribute/PosixFilePermission.OWNER_EXECUTE:Ljava/nio/file/attribute/PosixFilePermission;
        27: aload_1
        28: aload_2
        29: invokespecial #41                 // Method add$1:(Ljava/nio/file/attribute/PosixFilePermission;Ljava/util/Set;Lscala/runtime/IntRef;)V
        32: aload_0
        33: getstatic     #50                 // Field java/nio/file/attribute/PosixFilePermission.GROUP_READ:Ljava/nio/file/attribute/PosixFilePermission;
        36: aload_1
        37: aload_2
        38: invokespecial #41                 // Method add$1:(Ljava/nio/file/attribute/PosixFilePermission;Ljava/util/Set;Lscala/runtime/IntRef;)V
        41: aload_0
        42: getstatic     #53                 // Field java/nio/file/attribute/PosixFilePermission.GROUP_WRITE:Ljava/nio/file/attribute/PosixFilePermission;
        45: aload_1
        46: aload_2
        47: invokespecial #41                 // Method add$1:(Ljava/nio/file/attribute/PosixFilePermission;Ljava/util/Set;Lscala/runtime/IntRef;)V
        50: aload_0
        51: getstatic     #56                 // Field java/nio/file/attribute/PosixFilePermission.GROUP_EXECUTE:Ljava/nio/file/attribute/PosixFilePermission;
        54: aload_1
        55: aload_2
        56: invokespecial #41                 // Method add$1:(Ljava/nio/file/attribute/PosixFilePermission;Ljava/util/Set;Lscala/runtime/IntRef;)V
        59: aload_0
        60: getstatic     #59                 // Field java/nio/file/attribute/PosixFilePermission.OTHERS_READ:Ljava/nio/file/attribute/PosixFilePermission;
        63: aload_1
        64: aload_2
        65: invokespecial #41                 // Method add$1:(Ljava/nio/file/attribute/PosixFilePermission;Ljava/util/Set;Lscala/runtime/IntRef;)V
        68: aload_0
        69: getstatic     #62                 // Field java/nio/file/attribute/PosixFilePermission.OTHERS_WRITE:Ljava/nio/file/attribute/PosixFilePermission;
        72: aload_1
        73: aload_2
        74: invokespecial #41                 // Method add$1:(Ljava/nio/file/attribute/PosixFilePermission;Ljava/util/Set;Lscala/runtime/IntRef;)V
        77: aload_0
        78: getstatic     #65                 // Field java/nio/file/attribute/PosixFilePermission.OTHERS_EXECUTE:Ljava/nio/file/attribute/PosixFilePermission;
        81: aload_1
        82: aload_2
        83: invokespecial #41                 // Method add$1:(Ljava/nio/file/attribute/PosixFilePermission;Ljava/util/Set;Lscala/runtime/IntRef;)V
        86: new           #67                 // class os/PermSet
        89: dup
        90: aload_2
        91: getfield      #71                 // Field scala/runtime/IntRef.elem:I
        94: invokespecial #74                 // Method os/PermSet."<init>":(I)V
        97: areturn
      LineNumberTable:
        line 23: 0
        line 28: 5
        line 29: 14
        line 30: 23
        line 31: 32
        line 32: 41
        line 33: 50
        line 34: 59
        line 35: 68
        line 36: 77
        line 38: 86
      LocalVariableTable:
        Start  Length  Slot  Name   Signature
            5      92     2 total   Lscala/runtime/IntRef;
            0      98     0  this   Los/PermSet$;
            0      98     1 value   Ljava/util/Set;
    Signature: #24                          // (Ljava/util/Set<Ljava/nio/file/attribute/PosixFilePermission;>;)Los/PermSet;
    MethodParameters:
      Name                           Flags
      value                          final

  public os.PermSet fromString(java.lang.String);
    descriptor: (Ljava/lang/String;)Los/PermSet;
    flags: (0x0001) ACC_PUBLIC
    Code:
      stack=4, locals=3, args_size=2
         0: getstatic     #86                 // Field scala/Predef$.MODULE$:Lscala/Predef$;
         3: aload_1
         4: invokevirtual #92                 // Method java/lang/String.length:()I
         7: bipush        9
         9: if_icmpne     16
        12: iconst_1
        13: goto          17
        16: iconst_0
        17: aload_1
        18: invokedynamic #114,  0            // InvokeDynamic #0:apply:(Ljava/lang/String;)Lscala/Function0;
        23: invokevirtual #118                // Method scala/Predef$.require:(ZLscala/Function0;)V
        26: iconst_0
        27: invokestatic  #31                 // Method scala/runtime/IntRef.create:(I)Lscala/runtime/IntRef;
        30: astore_2
        31: aload_0
        32: getstatic     #37                 // Field java/nio/file/attribute/PosixFilePermission.OWNER_READ:Ljava/nio/file/attribute/PosixFilePermission;
        35: aload_1
        36: aload_2
        37: invokespecial #122                // Method add$2:(Ljava/nio/file/attribute/PosixFilePermission;Ljava/lang/String;Lscala/runtime/IntRef;)V
        40: aload_0
        41: getstatic     #44                 // Field java/nio/file/attribute/PosixFilePermission.OWNER_WRITE:Ljava/nio/file/attribute/PosixFilePermission;
        44: aload_1
        45: aload_2
        46: invokespecial #122                // Method add$2:(Ljava/nio/file/attribute/PosixFilePermission;Ljava/lang/String;Lscala/runtime/IntRef;)V
        49: aload_0
        50: getstatic     #47                 // Field java/nio/file/attribute/PosixFilePermission.OWNER_EXECUTE:Ljava/nio/file/attribute/PosixFilePermission;
        53: aload_1
        54: aload_2
        55: invokespecial #122                // Method add$2:(Ljava/nio/file/attribute/PosixFilePermission;Ljava/lang/String;Lscala/runtime/IntRef;)V
        58: aload_0
        59: getstatic     #50                 // Field java/nio/file/attribute/PosixFilePermission.GROUP_READ:Ljava/nio/file/attribute/PosixFilePermission;
        62: aload_1
        63: aload_2
        64: invokespecial #122                // Method add$2:(Ljava/nio/file/attribute/PosixFilePermission;Ljava/lang/String;Lscala/runtime/IntRef;)V
        67: aload_0
        68: getstatic     #53                 // Field java/nio/file/attribute/PosixFilePermission.GROUP_WRITE:Ljava/nio/file/attribute/PosixFilePermission;
        71: aload_1
        72: aload_2
        73: invokespecial #122                // Method add$2:(Ljava/nio/file/attribute/PosixFilePermission;Ljava/lang/String;Lscala/runtime/IntRef;)V
        76: aload_0
        77: getstatic     #56                 // Field java/nio/file/attribute/PosixFilePermission.GROUP_EXECUTE:Ljava/nio/file/attribute/PosixFilePermission;
        80: aload_1
        81: aload_2
        82: invokespecial #122                // Method add$2:(Ljava/nio/file/attribute/PosixFilePermission;Ljava/lang/String;Lscala/runtime/IntRef;)V
        85: aload_0
        86: getstatic     #59                 // Field java/nio/file/attribute/PosixFilePermission.OTHERS_READ:Ljava/nio/file/attribute/PosixFilePermission;
        89: aload_1
        90: aload_2
        91: invokespecial #122                // Method add$2:(Ljava/nio/file/attribute/PosixFilePermission;Ljava/lang/String;Lscala/runtime/IntRef;)V
        94: aload_0
        95: getstatic     #62                 // Field java/nio/file/attribute/PosixFilePermission.OTHERS_WRITE:Ljava/nio/file/attribute/PosixFilePermission;
        98: aload_1
        99: aload_2
       100: invokespecial #122                // Method add$2:(Ljava/nio/file/attribute/PosixFilePermission;Ljava/lang/String;Lscala/runtime/IntRef;)V
       103: aload_0
       104: getstatic     #65                 // Field java/nio/file/attribute/PosixFilePermission.OTHERS_EXECUTE:Ljava/nio/file/attribute/PosixFilePermission;
       107: aload_1
       108: aload_2
       109: invokespecial #122                // Method add$2:(Ljava/nio/file/attribute/PosixFilePermission;Ljava/lang/String;Lscala/runtime/IntRef;)V
       112: new           #67                 // class os/PermSet
       115: dup
       116: aload_2
       117: getfield      #71                 // Field scala/runtime/IntRef.elem:I
       120: invokespecial #74                 // Method os/PermSet."<init>":(I)V
       123: areturn
      StackMapTable: number_of_entries = 2
        frame_type = 80 /* same_locals_1_stack_item */
          stack = [ class scala/Predef$ ]
        frame_type = 255 /* full_frame */
          offset_delta = 0
          locals = [ class os/PermSet$, class java/lang/String ]
          stack = [ class scala/Predef$, int ]
      LineNumberTable:
        line 45: 0
        line 46: 3
        line 47: 17
        line 50: 26
        line 62: 31
        line 63: 40
        line 64: 49
        line 65: 58
        line 66: 67
        line 67: 76
        line 68: 85
        line 69: 94
        line 70: 103
        line 71: 112
      LocalVariableTable:
        Start  Length  Slot  Name   Signature
           31      92     2 perms   Lscala/runtime/IntRef;
            0     124     0  this   Los/PermSet$;
            0     124     1   arg   Ljava/lang/String;
    MethodParameters:
      Name                           Flags
      arg                            final

  public os.PermSet fromInt(int);
    descriptor: (I)Los/PermSet;
    flags: (0x0001) ACC_PUBLIC
    Code:
      stack=3, locals=2, args_size=2
         0: new           #67                 // class os/PermSet
         3: dup
         4: iload_1
         5: invokespecial #74                 // Method os/PermSet."<init>":(I)V
         8: areturn
      LineNumberTable:
        line 77: 0
      LocalVariableTable:
        Start  Length  Slot  Name   Signature
            0       9     0  this   Los/PermSet$;
            0       9     1 value   I
    MethodParameters:
      Name                           Flags
      value                          final

  public int permToMask(java.nio.file.attribute.PosixFilePermission);
    descriptor: (Ljava/nio/file/attribute/PosixFilePermission;)I
    flags: (0x0001) ACC_PUBLIC
    Code:
      stack=3, locals=2, args_size=2
         0: sipush        256
         3: aload_0
         4: aload_1
         5: invokevirtual #131                // Method permToOffset:(Ljava/nio/file/attribute/PosixFilePermission;)I
         8: ishr
         9: ireturn
      LineNumberTable:
        line 79: 0
      LocalVariableTable:
        Start  Length  Slot  Name   Signature
            0      10     0  this   Los/PermSet$;
            0      10     1  elem   Ljava/nio/file/attribute/PosixFilePermission;
    MethodParameters:
      Name                           Flags
      elem                           final

  public char permToChar(java.nio.file.attribute.PosixFilePermission);
    descriptor: (Ljava/nio/file/attribute/PosixFilePermission;)C
    flags: (0x0001) ACC_PUBLIC
    Code:
      stack=3, locals=4, args_size=2
         0: aload_1
         1: astore_3
         2: getstatic     #37                 // Field java/nio/file/attribute/PosixFilePermission.OWNER_READ:Ljava/nio/file/attribute/PosixFilePermission;
         5: aload_3
         6: invokevirtual #137                // Method java/lang/Object.equals:(Ljava/lang/Object;)Z
         9: ifeq          18
        12: bipush        114
        14: istore_2
        15: goto          182
        18: goto          21
        21: getstatic     #44                 // Field java/nio/file/attribute/PosixFilePermission.OWNER_WRITE:Ljava/nio/file/attribute/PosixFilePermission;
        24: aload_3
        25: invokevirtual #137                // Method java/lang/Object.equals:(Ljava/lang/Object;)Z
        28: ifeq          37
        31: bipush        119
        33: istore_2
        34: goto          182
        37: goto          40
        40: getstatic     #47                 // Field java/nio/file/attribute/PosixFilePermission.OWNER_EXECUTE:Ljava/nio/file/attribute/PosixFilePermission;
        43: aload_3
        44: invokevirtual #137                // Method java/lang/Object.equals:(Ljava/lang/Object;)Z
        47: ifeq          56
        50: bipush        120
        52: istore_2
        53: goto          182
        56: goto          59
        59: getstatic     #50                 // Field java/nio/file/attribute/PosixFilePermission.GROUP_READ:Ljava/nio/file/attribute/PosixFilePermission;
        62: aload_3
        63: invokevirtual #137                // Method java/lang/Object.equals:(Ljava/lang/Object;)Z
        66: ifeq          75
        69: bipush        114
        71: istore_2
        72: goto          182
        75: goto          78
        78: getstatic     #53                 // Field java/nio/file/attribute/PosixFilePermission.GROUP_WRITE:Ljava/nio/file/attribute/PosixFilePermission;
        81: aload_3
        82: invokevirtual #137                // Method java/lang/Object.equals:(Ljava/lang/Object;)Z
        85: ifeq          94
        88: bipush        119
        90: istore_2
        91: goto          182
        94: goto          97
        97: getstatic     #56                 // Field java/nio/file/attribute/PosixFilePermission.GROUP_EXECUTE:Ljava/nio/file/attribute/PosixFilePermission;
       100: aload_3
       101: invokevirtual #137                // Method java/lang/Object.equals:(Ljava/lang/Object;)Z
       104: ifeq          113
       107: bipush        120
       109: istore_2
       110: goto          182
       113: goto          116
       116: getstatic     #59                 // Field java/nio/file/attribute/PosixFilePermission.OTHERS_READ:Ljava/nio/file/attribute/PosixFilePermission;
       119: aload_3
       120: invokevirtual #137                // Method java/lang/Object.equals:(Ljava/lang/Object;)Z
       123: ifeq          132
       126: bipush        114
       128: istore_2
       129: goto          182
       132: goto          135
       135: getstatic     #62                 // Field java/nio/file/attribute/PosixFilePermission.OTHERS_WRITE:Ljava/nio/file/attribute/PosixFilePermission;
       138: aload_3
       139: invokevirtual #137                // Method java/lang/Object.equals:(Ljava/lang/Object;)Z
       142: ifeq          151
       145: bipush        119
       147: istore_2
       148: goto          182
       151: goto          154
       154: getstatic     #65                 // Field java/nio/file/attribute/PosixFilePermission.OTHERS_EXECUTE:Ljava/nio/file/attribute/PosixFilePermission;
       157: aload_3
       158: invokevirtual #137                // Method java/lang/Object.equals:(Ljava/lang/Object;)Z
       161: ifeq          170
       164: bipush        120
       166: istore_2
       167: goto          182
       170: goto          173
       173: new           #139                // class scala/MatchError
       176: dup
       177: aload_3
       178: invokespecial #142                // Method scala/MatchError."<init>":(Ljava/lang/Object;)V
       181: athrow
       182: iload_2
       183: ireturn
      StackMapTable: number_of_entries = 19
        frame_type = 253 /* append */
          offset_delta = 18
          locals = [ top, class java/nio/file/attribute/PosixFilePermission ]
        frame_type = 2 /* same */
        frame_type = 15 /* same */
        frame_type = 2 /* same */
        frame_type = 15 /* same */
        frame_type = 2 /* same */
        frame_type = 15 /* same */
        frame_type = 2 /* same */
        frame_type = 15 /* same */
        frame_type = 2 /* same */
        frame_type = 15 /* same */
        frame_type = 2 /* same */
        frame_type = 15 /* same */
        frame_type = 2 /* same */
        frame_type = 15 /* same */
        frame_type = 2 /* same */
        frame_type = 15 /* same */
        frame_type = 2 /* same */
        frame_type = 255 /* full_frame */
          offset_delta = 8
          locals = [ class os/PermSet$, class java/nio/file/attribute/PosixFilePermission, int, class java/nio/file/attribute/PosixFilePermission ]
          stack = []
      LineNumberTable:
        line 80: 0
        line 81: 2
        line 82: 21
        line 83: 40
        line 84: 59
        line 85: 78
        line 86: 97
        line 87: 116
        line 88: 135
        line 89: 154
        line 80: 173
      LocalVariableTable:
        Start  Length  Slot  Name   Signature
            0     184     0  this   Los/PermSet$;
            0     184     1  elem   Ljava/nio/file/attribute/PosixFilePermission;
    MethodParameters:
      Name                           Flags
      elem                           final

  public int permToOffset(java.nio.file.attribute.PosixFilePermission);
    descriptor: (Ljava/nio/file/attribute/PosixFilePermission;)I
    flags: (0x0001) ACC_PUBLIC
    Code:
      stack=3, locals=4, args_size=2
         0: aload_1
         1: astore_3
         2: getstatic     #37                 // Field java/nio/file/attribute/PosixFilePermission.OWNER_READ:Ljava/nio/file/attribute/PosixFilePermission;
         5: aload_3
         6: invokevirtual #137                // Method java/lang/Object.equals:(Ljava/lang/Object;)Z
         9: ifeq          17
        12: iconst_0
        13: istore_2
        14: goto          176
        17: goto          20
        20: getstatic     #44                 // Field java/nio/file/attribute/PosixFilePermission.OWNER_WRITE:Ljava/nio/file/attribute/PosixFilePermission;
        23: aload_3
        24: invokevirtual #137                // Method java/lang/Object.equals:(Ljava/lang/Object;)Z
        27: ifeq          35
        30: iconst_1
        31: istore_2
        32: goto          176
        35: goto          38
        38: getstatic     #47                 // Field java/nio/file/attribute/PosixFilePermission.OWNER_EXECUTE:Ljava/nio/file/attribute/PosixFilePermission;
        41: aload_3
        42: invokevirtual #137                // Method java/lang/Object.equals:(Ljava/lang/Object;)Z
        45: ifeq          53
        48: iconst_2
        49: istore_2
        50: goto          176
        53: goto          56
        56: getstatic     #50                 // Field java/nio/file/attribute/PosixFilePermission.GROUP_READ:Ljava/nio/file/attribute/PosixFilePermission;
        59: aload_3
        60: invokevirtual #137                // Method java/lang/Object.equals:(Ljava/lang/Object;)Z
        63: ifeq          71
        66: iconst_3
        67: istore_2
        68: goto          176
        71: goto          74
        74: getstatic     #53                 // Field java/nio/file/attribute/PosixFilePermission.GROUP_WRITE:Ljava/nio/file/attribute/PosixFilePermission;
        77: aload_3
        78: invokevirtual #137                // Method java/lang/Object.equals:(Ljava/lang/Object;)Z
        81: ifeq          89
        84: iconst_4
        85: istore_2
        86: goto          176
        89: goto          92
        92: getstatic     #56                 // Field java/nio/file/attribute/PosixFilePermission.GROUP_EXECUTE:Ljava/nio/file/attribute/PosixFilePermission;
        95: aload_3
        96: invokevirtual #137                // Method java/lang/Object.equals:(Ljava/lang/Object;)Z
        99: ifeq          107
       102: iconst_5
       103: istore_2
       104: goto          176
       107: goto          110
       110: getstatic     #59                 // Field java/nio/file/attribute/PosixFilePermission.OTHERS_READ:Ljava/nio/file/attribute/PosixFilePermission;
       113: aload_3
       114: invokevirtual #137                // Method java/lang/Object.equals:(Ljava/lang/Object;)Z
       117: ifeq          126
       120: bipush        6
       122: istore_2
       123: goto          176
       126: goto          129
       129: getstatic     #62                 // Field java/nio/file/attribute/PosixFilePermission.OTHERS_WRITE:Ljava/nio/file/attribute/PosixFilePermission;
       132: aload_3
       133: invokevirtual #137                // Method java/lang/Object.equals:(Ljava/lang/Object;)Z
       136: ifeq          145
       139: bipush        7
       141: istore_2
       142: goto          176
       145: goto          148
       148: getstatic     #65                 // Field java/nio/file/attribute/PosixFilePermission.OTHERS_EXECUTE:Ljava/nio/file/attribute/PosixFilePermission;
       151: aload_3
       152: invokevirtual #137                // Method java/lang/Object.equals:(Ljava/lang/Object;)Z
       155: ifeq          164
       158: bipush        8
       160: istore_2
       161: goto          176
       164: goto          167
       167: new           #139                // class scala/MatchError
       170: dup
       171: aload_3
       172: invokespecial #142                // Method scala/MatchError."<init>":(Ljava/lang/Object;)V
       175: athrow
       176: iload_2
       177: ireturn
      StackMapTable: number_of_entries = 19
        frame_type = 253 /* append */
          offset_delta = 17
          locals = [ top, class java/nio/file/attribute/PosixFilePermission ]
        frame_type = 2 /* same */
        frame_type = 14 /* same */
        frame_type = 2 /* same */
        frame_type = 14 /* same */
        frame_type = 2 /* same */
        frame_type = 14 /* same */
        frame_type = 2 /* same */
        frame_type = 14 /* same */
        frame_type = 2 /* same */
        frame_type = 14 /* same */
        frame_type = 2 /* same */
        frame_type = 15 /* same */
        frame_type = 2 /* same */
        frame_type = 15 /* same */
        frame_type = 2 /* same */
        frame_type = 15 /* same */
        frame_type = 2 /* same */
        frame_type = 255 /* full_frame */
          offset_delta = 8
          locals = [ class os/PermSet$, class java/nio/file/attribute/PosixFilePermission, int, class java/nio/file/attribute/PosixFilePermission ]
          stack = []
      LineNumberTable:
        line 91: 0
        line 92: 2
        line 93: 20
        line 94: 38
        line 95: 56
        line 96: 74
        line 97: 92
        line 98: 110
        line 99: 129
        line 100: 148
        line 91: 167
      LocalVariableTable:
        Start  Length  Slot  Name   Signature
            0     178     0  this   Los/PermSet$;
            0     178     1  elem   Ljava/nio/file/attribute/PosixFilePermission;
    MethodParameters:
      Name                           Flags
      elem                           final

  public os.PermSet apply(int);
    descriptor: (I)Los/PermSet;
    flags: (0x0001) ACC_PUBLIC
    Code:
      stack=3, locals=2, args_size=2
         0: new           #67                 // class os/PermSet
         3: dup
         4: iload_1
         5: invokespecial #74                 // Method os/PermSet."<init>":(I)V
         8: areturn
      LineNumberTable:
        line 109: 0
      LocalVariableTable:
        Start  Length  Slot  Name   Signature
            0       9     0  this   Los/PermSet$;
            0       9     1 value   I
    MethodParameters:
      Name                           Flags
      value                          final

  public scala.Option<java.lang.Object> unapply(os.PermSet);
    descriptor: (Los/PermSet;)Lscala/Option;
    flags: (0x0001) ACC_PUBLIC
    Code:
      stack=3, locals=2, args_size=2
         0: aload_1
         1: ifnonnull     10
         4: getstatic     #151                // Field scala/None$.MODULE$:Lscala/None$;
         7: goto          24
        10: new           #153                // class scala/Some
        13: dup
        14: aload_1
        15: invokevirtual #155                // Method os/PermSet.value:()I
        18: invokestatic  #161                // Method scala/runtime/BoxesRunTime.boxToInteger:(I)Ljava/lang/Integer;
        21: invokespecial #162                // Method scala/Some."<init>":(Ljava/lang/Object;)V
        24: areturn
      StackMapTable: number_of_entries = 2
        frame_type = 10 /* same */
        frame_type = 77 /* same_locals_1_stack_item */
          stack = [ class scala/Option ]
      LineNumberTable:
        line 109: 0
      LocalVariableTable:
        Start  Length  Slot  Name   Signature
            0      25     0  this   Los/PermSet$;
            0      25     1   x$0   Los/PermSet;
    Signature: #145                         // (Los/PermSet;)Lscala/Option<Ljava/lang/Object;>;
    MethodParameters:
      Name                           Flags
      x$0                            final

  private java.lang.Object writeReplace();
    descriptor: ()Ljava/lang/Object;
    flags: (0x0002) ACC_PRIVATE
    Code:
      stack=3, locals=1, args_size=1
         0: new           #168                // class scala/runtime/ModuleSerializationProxy
         3: dup
         4: ldc           #2                  // class os/PermSet$
         6: invokespecial #171                // Method scala/runtime/ModuleSerializationProxy."<init>":(Ljava/lang/Class;)V
         9: areturn
      LineNumberTable:
        line 21: 0
      LocalVariableTable:
        Start  Length  Slot  Name   Signature
            0      10     0  this   Los/PermSet$;

  private final void add$1(java.nio.file.attribute.PosixFilePermission, java.util.Set, scala.runtime.IntRef);
    descriptor: (Ljava/nio/file/attribute/PosixFilePermission;Ljava/util/Set;Lscala/runtime/IntRef;)V
    flags: (0x0012) ACC_PRIVATE, ACC_FINAL
    Code:
      stack=4, locals=4, args_size=4
         0: aload_2
         1: aload_1
         2: invokeinterface #179,  2          // InterfaceMethod java/util/Set.contains:(Ljava/lang/Object;)Z
         7: ifeq          27
        10: aload_3
        11: aload_3
        12: getfield      #71                 // Field scala/runtime/IntRef.elem:I
        15: aload_0
        16: aload_1
        17: invokevirtual #181                // Method permToMask:(Ljava/nio/file/attribute/PosixFilePermission;)I
        20: iadd
        21: putfield      #71                 // Field scala/runtime/IntRef.elem:I
        24: goto          27
        27: return
      StackMapTable: number_of_entries = 1
        frame_type = 27 /* same */
      LineNumberTable:
        line 26: 0
      LocalVariableTable:
        Start  Length  Slot  Name   Signature
            0      28     0  this   Los/PermSet$;
            0      28     1  perm   Ljava/nio/file/attribute/PosixFilePermission;
            0      28     2 value$1   Ljava/util/Set;
            0      28     3 total$1   Lscala/runtime/IntRef;
    MethodParameters:
      Name                           Flags
      perm                           final
      value$1                        final
      total$1                        final

  public static final java.lang.String $anonfun$fromString$1(java.lang.String);
    descriptor: (Ljava/lang/String;)Ljava/lang/String;
    flags: (0x1019) ACC_PUBLIC, ACC_STATIC, ACC_FINAL, ACC_SYNTHETIC
    Code:
      stack=3, locals=1, args_size=1
         0: new           #184                // class java/lang/StringBuilder
         3: dup
         4: ldc           #185                // int 50
         6: invokespecial #186                // Method java/lang/StringBuilder."<init>":(I)V
         9: ldc           #188                // String Invalid permissions string: must be length 9, not
        11: invokevirtual #192                // Method java/lang/StringBuilder.append:(Ljava/lang/String;)Ljava/lang/StringBuilder;
        14: aload_0
        15: invokevirtual #92                 // Method java/lang/String.length:()I
        18: invokevirtual #195                // Method java/lang/StringBuilder.append:(I)Ljava/lang/StringBuilder;
        21: invokevirtual #198                // Method java/lang/StringBuilder.toString:()Ljava/lang/String;
        24: areturn
      LineNumberTable:
        line 47: 0
      LocalVariableTable:
        Start  Length  Slot  Name   Signature
            0      25     0 arg$1   Ljava/lang/String;
    MethodParameters:
      Name                           Flags
      arg$1                          final

  private final void add$2(java.nio.file.attribute.PosixFilePermission, java.lang.String, scala.runtime.IntRef);
    descriptor: (Ljava/nio/file/attribute/PosixFilePermission;Ljava/lang/String;Lscala/runtime/IntRef;)V
    flags: (0x0012) ACC_PRIVATE, ACC_FINAL
    Code:
      stack=6, locals=6, args_size=4
         0: aload_0
         1: aload_1
         2: invokevirtual #131                // Method permToOffset:(Ljava/nio/file/attribute/PosixFilePermission;)I
         5: istore        4
         7: aload_0
         8: aload_1
         9: invokevirtual #201                // Method permToChar:(Ljava/nio/file/attribute/PosixFilePermission;)C
        12: istore        5
        14: getstatic     #206                // Field scala/collection/StringOps$.MODULE$:Lscala/collection/StringOps$;
        17: getstatic     #86                 // Field scala/Predef$.MODULE$:Lscala/Predef$;
        20: aload_2
        21: invokevirtual #209                // Method scala/Predef$.augmentString:(Ljava/lang/String;)Ljava/lang/String;
        24: iload         4
        26: invokevirtual #213                // Method scala/collection/StringOps$.apply$extension:(Ljava/lang/String;I)C
        29: iload         5
        31: if_icmpne     51
        34: aload_3
        35: aload_3
        36: getfield      #71                 // Field scala/runtime/IntRef.elem:I
        39: aload_0
        40: aload_1
        41: invokevirtual #181                // Method permToMask:(Ljava/nio/file/attribute/PosixFilePermission;)I
        44: ior
        45: putfield      #71                 // Field scala/runtime/IntRef.elem:I
        48: goto          144
        51: getstatic     #206                // Field scala/collection/StringOps$.MODULE$:Lscala/collection/StringOps$;
        54: getstatic     #86                 // Field scala/Predef$.MODULE$:Lscala/Predef$;
        57: aload_2
        58: invokevirtual #209                // Method scala/Predef$.augmentString:(Ljava/lang/String;)Ljava/lang/String;
        61: iload         4
        63: invokevirtual #213                // Method scala/collection/StringOps$.apply$extension:(Ljava/lang/String;I)C
        66: bipush        45
        68: if_icmpeq     144
        71: new           #215                // class java/lang/Exception
        74: dup
        75: new           #184                // class java/lang/StringBuilder
        78: dup
        79: ldc           #216                // int 78
        81: invokespecial #186                // Method java/lang/StringBuilder."<init>":(I)V
        84: ldc           #218                // String Invalid permissions string: unknown character [
        86: invokevirtual #192                // Method java/lang/StringBuilder.append:(Ljava/lang/String;)Ljava/lang/StringBuilder;
        89: getstatic     #206                // Field scala/collection/StringOps$.MODULE$:Lscala/collection/StringOps$;
        92: getstatic     #86                 // Field scala/Predef$.MODULE$:Lscala/Predef$;
        95: aload_2
        96: invokevirtual #209                // Method scala/Predef$.augmentString:(Ljava/lang/String;)Ljava/lang/String;
        99: iload         4
       101: invokevirtual #213                // Method scala/collection/StringOps$.apply$extension:(Ljava/lang/String;I)C
       104: invokevirtual #221                // Method java/lang/StringBuilder.append:(C)Ljava/lang/StringBuilder;
       107: ldc           #223                // String ]
       109: invokevirtual #192                // Method java/lang/StringBuilder.append:(Ljava/lang/String;)Ljava/lang/StringBuilder;
       112: ldc           #225                // String at index
       114: invokevirtual #192                // Method java/lang/StringBuilder.append:(Ljava/lang/String;)Ljava/lang/StringBuilder;
       117: iload         4
       119: invokevirtual #195                // Method java/lang/StringBuilder.append:(I)Ljava/lang/StringBuilder;
       122: ldc           #227                // String . Must be [-] or [
       124: invokevirtual #192                // Method java/lang/StringBuilder.append:(Ljava/lang/String;)Ljava/lang/StringBuilder;
       127: iload         5
       129: invokevirtual #221                // Method java/lang/StringBuilder.append:(C)Ljava/lang/StringBuilder;
       132: ldc           #229                // String ].
       134: invokevirtual #192                // Method java/lang/StringBuilder.append:(Ljava/lang/String;)Ljava/lang/StringBuilder;
       137: invokevirtual #198                // Method java/lang/StringBuilder.toString:()Ljava/lang/String;
       140: invokespecial #232                // Method java/lang/Exception."<init>":(Ljava/lang/String;)V
       143: athrow
       144: return
      StackMapTable: number_of_entries = 2
        frame_type = 253 /* append */
          offset_delta = 51
          locals = [ int, int ]
        frame_type = 251 /* same_frame_extended */
          offset_delta = 92
      LineNumberTable:
        line 52: 0
        line 53: 7
        line 54: 14
        line 55: 51
        line 56: 71
        line 58: 75
        line 57: 84
        line 58: 112
        line 56: 143
        line 55: 144
      LocalVariableTable:
        Start  Length  Slot  Name   Signature
            7     137     4     i   I
           14     130     5 expected   C
            0     145     0  this   Los/PermSet$;
            0     145     1  perm   Ljava/nio/file/attribute/PosixFilePermission;
            0     145     2 arg$1   Ljava/lang/String;
            0     145     3 perms$1   Lscala/runtime/IntRef;
    MethodParameters:
      Name                           Flags
      perm                           final
      arg$1                          final
      perms$1                        final

  private os.PermSet$();
    descriptor: ()V
    flags: (0x0002) ACC_PRIVATE
    Code:
      stack=1, locals=1, args_size=1
         0: aload_0
         1: invokespecial #236                // Method java/lang/Object."<init>":()V
         4: return
      LineNumberTable:
        line 109: 0
        line 21: 4
      LocalVariableTable:
        Start  Length  Slot  Name   Signature
            0       5     0  this   Los/PermSet$;

  private static java.lang.Object $deserializeLambda$(java.lang.invoke.SerializedLambda);
    descriptor: (Ljava/lang/invoke/SerializedLambda;)Ljava/lang/Object;
    flags: (0x100a) ACC_PRIVATE, ACC_STATIC, ACC_SYNTHETIC
    Code:
      stack=1, locals=1, args_size=1
         0: aload_0
         1: invokedynamic #248,  0            // InvokeDynamic #1:lambdaDeserialize:(Ljava/lang/invoke/SerializedLambda;)Ljava/lang/Object;
         6: areturn
}
InnerClasses:
  public static final #12= #9 of #11;     // Lookup=class java/lang/invoke/MethodHandles$Lookup of class java/lang/invoke/MethodHandles
SourceFile: "Model.scala"
BootstrapMethods:
  0: #110 REF_invokeStatic java/lang/invoke/LambdaMetafactory.altMetafactory:(Ljava/lang/invoke/MethodHandles$Lookup;Ljava/lang/String;Ljava/lang/invoke/MethodType;[Ljava/lang/Object;)Ljava/lang/invoke/CallSite;
    Method arguments:
      #94 ()Ljava/lang/Object;
      #99 REF_invokeStatic os/PermSet$.$anonfun$fromString$1:(Ljava/lang/String;)Ljava/lang/String;
      #101 ()Ljava/lang/String;
      #102 5
      #103 1
      #101 ()Ljava/lang/String;
  1: #245 REF_invokeStatic scala/runtime/LambdaDeserialize.bootstrap:(Ljava/lang/invoke/MethodHandles$Lookup;Ljava/lang/String;Ljava/lang/invoke/MethodType;[Ljava/lang/invoke/MethodHandle;)Ljava/lang/invoke/CallSite;
    Method arguments:
      #99 REF_invokeStatic os/PermSet$.$anonfun$fromString$1:(Ljava/lang/String;)Ljava/lang/String;
  ScalaInlineInfo: length = 0x45 (unknown attribute)
   01 01 00 0D 00 5F 00 60 01 00 11 00 10 01 00 26
   00 27 01 00 77 00 78 01 00 6F 00 7E 01 00 7D 00
   7E 01 00 16 00 17 01 00 4F 00 50 01 00 84 00 85
   01 00 7F 00 80 01 00 81 00 80 01 00 8F 00 90 01
   00 A6 00 5D 01
  Scala: length = 0x0 (unknown attribute)

