Classfile /Users/mw/Projects/slang-braindump/.jar/jar8/assemble/slang-braindump/assemble/content/os/remove.class
  Last modified May 29, 2022; size 1527 bytes
  SHA-256 checksum 9e6f919b9908406be56f37d16efe1251dc84f899a3b9461ea724e6c2725f58c2
  Compiled from "FileOps.scala"
public final class os.remove
  minor version: 0
  major version: 52
  flags: (0x0031) ACC_PUBLIC, ACC_FINAL, ACC_SUPER
  this_class: #2                          // os/remove
  super_class: #4                         // java/lang/Object
  interfaces: 0, fields: 0, methods: 6, attributes: 4
Constant pool:
   #1 = Utf8               os/remove
   #2 = Class              #1             // os/remove
   #3 = Utf8               java/lang/Object
   #4 = Class              #3             // java/lang/Object
   #5 = Utf8               FileOps.scala
   #6 = Utf8               Lscala/reflect/ScalaSignature;
   #7 = Utf8               bytes
   #8 = Utf8               \u0006\u0005\r;QAC\u0006\t\u000291Q\u0001E\u0006\t\u0002EAQ!I\u0001\u0005\u0002\tBQaI\u0001\u0005\u0002\u0011BQaI\u0001\u0005\u0002\u001dBqaK\u0001\u0012\u0002\u0013\u0005AfB\u00038\u0003!\u0005\u0001HB\u0003;\u0003!\u00051\bC\u0003\"\u000f\u0011\u0005\u0001\tC\u0003$\u000f\u0011\u0005\u0011)\u0001\u0004sK6|g/\u001a\u0006\u0002\u0019\u0005\u0011qn]\u0002\u0001!\ty\u0011!D\u0001\f\u0005\u0019\u0011X-\\8wKN\u0019\u0011A\u0005\r\u0011\u0005M1R\"\u0001\u000b\u000b\u0003U\tQa]2bY\u0006L!a\u0006\u000b\u0003\r\u0005s\u0017PU3g!\u0011\u0019\u0012d\u0007\u0010\n\u0005i!\"!\u0003$v]\u000e$\u0018n\u001c82!\tyA$\u0003\u0002\u001e\u0017\t!\u0001+\u0019;i!\t\u0019r$\u0003\u0002!)\t9!i\\8mK\u0006t\u0017A\u0002\u001fj]&$h\bF\u0001\u000f\u0003\u0015\t\u0007\u000f\u001d7z)\tqR\u0005C\u0003\'\u0007\u0001\u00071$\u0001\u0004uCJ<W\r\u001e\u000b\u0004=!J\u0003\"\u0002\u0014\u0005\u0001\u0004Y\u0002b\u0002\u0016\u0005!\u0003\u0005\rAH\u0001\fG\",7m[#ySN$8/A\bbaBd\u0017\u0010\n3fM\u0006,H\u000e\u001e\u00133+\u0005i#F\u0001\u0010/W\u0005y\u0003C\u0001\u00196\u001b\u0005\t$B\u0001\u001a4\u0003%)hn\u00195fG.,GM\u0003\u00025)\u0005Q\u0011M\u001c8pi\u0006$\u0018n\u001c8\n\u0005Y\n$!E;oG\",7m[3e-\u0006\u0014\u0018.\u00198dK\u0006\u0019\u0011\r\u001c7\u0011\u0005e:Q\"A\u0001\u0003\u0007\u0005dGnE\u0002\b%q\u0002BaE\r\u001c{A\u00111CP\u0005\u0003\u007fQ\u0011A!\u00168jiR\t\u0001\b\u0006\u0002>\u0005\")a%\u0003a\u00017\u0001
   #9 = Utf8               os/remove$all$
  #10 = Class              #9             // os/remove$all$
  #11 = Utf8               all$
  #12 = Utf8               apply$default$2
  #13 = Utf8               ()Z
  #14 = Utf8               os/remove$
  #15 = Class              #14            // os/remove$
  #16 = Utf8               MODULE$
  #17 = Utf8               Los/remove$;
  #18 = NameAndType        #16:#17        // MODULE$:Los/remove$;
  #19 = Fieldref           #15.#18        // os/remove$.MODULE$:Los/remove$;
  #20 = NameAndType        #12:#13        // apply$default$2:()Z
  #21 = Methodref          #15.#20        // os/remove$.apply$default$2:()Z
  #22 = Utf8               apply
  #23 = Utf8               (Los/Path;Z)Z
  #24 = Utf8               target
  #25 = Utf8               checkExists
  #26 = NameAndType        #22:#23        // apply:(Los/Path;Z)Z
  #27 = Methodref          #15.#26        // os/remove$.apply:(Los/Path;Z)Z
  #28 = Utf8               (Los/Path;)Z
  #29 = NameAndType        #22:#28        // apply:(Los/Path;)Z
  #30 = Methodref          #15.#29        // os/remove$.apply:(Los/Path;)Z
  #31 = Utf8               toString
  #32 = Utf8               ()Ljava/lang/String;
  #33 = NameAndType        #31:#32        // toString:()Ljava/lang/String;
  #34 = Methodref          #15.#33        // os/remove$.toString:()Ljava/lang/String;
  #35 = Utf8               andThen
  #36 = Utf8               (Lscala/Function1;)Lscala/Function1;
  #37 = Utf8               <A:Ljava/lang/Object;>(Lscala/Function1<Ljava/lang/Object;TA;>;)Lscala/Function1<Los/Path;TA;>;
  #38 = Utf8               g
  #39 = NameAndType        #35:#36        // andThen:(Lscala/Function1;)Lscala/Function1;
  #40 = Methodref          #15.#39        // os/remove$.andThen:(Lscala/Function1;)Lscala/Function1;
  #41 = Utf8               compose
  #42 = Utf8               <A:Ljava/lang/Object;>(Lscala/Function1<TA;Los/Path;>;)Lscala/Function1<TA;Ljava/lang/Object;>;
  #43 = NameAndType        #41:#36        // compose:(Lscala/Function1;)Lscala/Function1;
  #44 = Methodref          #15.#43        // os/remove$.compose:(Lscala/Function1;)Lscala/Function1;
  #45 = Utf8               Code
  #46 = Utf8               MethodParameters
  #47 = Utf8               Signature
  #48 = Utf8               InnerClasses
  #49 = Utf8               SourceFile
  #50 = Utf8               RuntimeVisibleAnnotations
  #51 = Utf8               ScalaSig
{
  public static boolean apply$default$2();
    descriptor: ()Z
    flags: (0x0009) ACC_PUBLIC, ACC_STATIC
    Code:
      stack=1, locals=0, args_size=0
         0: getstatic     #19                 // Field os/remove$.MODULE$:Los/remove$;
         3: invokevirtual #21                 // Method os/remove$.apply$default$2:()Z
         6: ireturn

  public static boolean apply(os.Path, boolean);
    descriptor: (Los/Path;Z)Z
    flags: (0x0009) ACC_PUBLIC, ACC_STATIC
    Code:
      stack=3, locals=2, args_size=2
         0: getstatic     #19                 // Field os/remove$.MODULE$:Los/remove$;
         3: aload_0
         4: iload_1
         5: invokevirtual #27                 // Method os/remove$.apply:(Los/Path;Z)Z
         8: ireturn
    MethodParameters:
      Name                           Flags
      target                         final
      checkExists                    final

  public static boolean apply(os.Path);
    descriptor: (Los/Path;)Z
    flags: (0x0009) ACC_PUBLIC, ACC_STATIC
    Code:
      stack=2, locals=1, args_size=1
         0: getstatic     #19                 // Field os/remove$.MODULE$:Los/remove$;
         3: aload_0
         4: invokevirtual #30                 // Method os/remove$.apply:(Los/Path;)Z
         7: ireturn
    MethodParameters:
      Name                           Flags
      target                         final

  public static java.lang.String toString();
    descriptor: ()Ljava/lang/String;
    flags: (0x0009) ACC_PUBLIC, ACC_STATIC
    Code:
      stack=1, locals=0, args_size=0
         0: getstatic     #19                 // Field os/remove$.MODULE$:Los/remove$;
         3: invokevirtual #34                 // Method os/remove$.toString:()Ljava/lang/String;
         6: areturn

  public static <A extends java.lang.Object> scala.Function1<os.Path, A> andThen(scala.Function1<java.lang.Object, A>);
    descriptor: (Lscala/Function1;)Lscala/Function1;
    flags: (0x0009) ACC_PUBLIC, ACC_STATIC
    Code:
      stack=2, locals=1, args_size=1
         0: getstatic     #19                 // Field os/remove$.MODULE$:Los/remove$;
         3: aload_0
         4: invokevirtual #40                 // Method os/remove$.andThen:(Lscala/Function1;)Lscala/Function1;
         7: areturn
    Signature: #37                          // <A:Ljava/lang/Object;>(Lscala/Function1<Ljava/lang/Object;TA;>;)Lscala/Function1<Los/Path;TA;>;
    MethodParameters:
      Name                           Flags
      g                              final

  public static <A extends java.lang.Object> scala.Function1<A, java.lang.Object> compose(scala.Function1<A, os.Path>);
    descriptor: (Lscala/Function1;)Lscala/Function1;
    flags: (0x0009) ACC_PUBLIC, ACC_STATIC
    Code:
      stack=2, locals=1, args_size=1
         0: getstatic     #19                 // Field os/remove$.MODULE$:Los/remove$;
         3: aload_0
         4: invokevirtual #44                 // Method os/remove$.compose:(Lscala/Function1;)Lscala/Function1;
         7: areturn
    Signature: #42                          // <A:Ljava/lang/Object;>(Lscala/Function1<TA;Los/Path;>;)Lscala/Function1<TA;Ljava/lang/Object;>;
    MethodParameters:
      Name                           Flags
      g                              final
}
InnerClasses:
  public static #11= #10 of #2;           // all$=class os/remove$all$ of class os/remove
SourceFile: "FileOps.scala"
RuntimeVisibleAnnotations:
  0: #6(#7=s#8)
    scala.reflect.ScalaSignature(
      bytes="\u0006\u0005\r;QAC\u0006\t\u000291Q\u0001E\u0006\t\u0002EAQ!I\u0001\u0005\u0002\tBQaI\u0001\u0005\u0002\u0011BQaI\u0001\u0005\u0002\u001dBqaK\u0001\u0012\u0002\u0013\u0005AfB\u00038\u0003!\u0005\u0001HB\u0003;\u0003!\u00051\bC\u0003\"\u000f\u0011\u0005\u0001\tC\u0003$\u000f\u0011\u0005\u0011)\u0001\u0004sK6|g/\u001a\u0006\u0002\u0019\u0005\u0011qn]\u0002\u0001!\ty\u0011!D\u0001\f\u0005\u0019\u0011X-\\8wKN\u0019\u0011A\u0005\r\u0011\u0005M1R\"\u0001\u000b\u000b\u0003U\tQa]2bY\u0006L!a\u0006\u000b\u0003\r\u0005s\u0017PU3g!\u0011\u0019\u0012d\u0007\u0010\n\u0005i!\"!\u0003$v]\u000e$\u0018n\u001c82!\tyA$\u0003\u0002\u001e\u0017\t!\u0001+\u0019;i!\t\u0019r$\u0003\u0002!)\t9!i\\8mK\u0006t\u0017A\u0002\u001fj]&$h\bF\u0001\u000f\u0003\u0015\t\u0007\u000f\u001d7z)\tqR\u0005C\u0003\'\u0007\u0001\u00071$\u0001\u0004uCJ<W\r\u001e\u000b\u0004=!J\u0003\"\u0002\u0014\u0005\u0001\u0004Y\u0002b\u0002\u0016\u0005!\u0003\u0005\rAH\u0001\fG\",7m[#ySN$8/A\bbaBd\u0017\u0010\n3fM\u0006,H\u000e\u001e\u00133+\u0005i#F\u0001\u0010/W\u0005y\u0003C\u0001\u00196\u001b\u0005\t$B\u0001\u001a4\u0003%)hn\u00195fG.,GM\u0003\u00025)\u0005Q\u0011M\u001c8pi\u0006$\u0018n\u001c8\n\u0005Y\n$!E;oG\",7m[3e-\u0006\u0014\u0018.\u00198dK\u0006\u0019\u0011\r\u001c7\u0011\u0005e:Q\"A\u0001\u0003\u0007\u0005dGnE\u0002\b%q\u0002BaE\r\u001c{A\u00111CP\u0005\u0003\u007fQ\u0011A!\u00168jiR\t\u0001\b\u0006\u0002>\u0005\")a%\u0003a\u00017\u0001"
    )
  ScalaSig: length = 0x3 (unknown attribute)
   05 02 00
