Classfile /Users/mw/Projects/slang-braindump/.jar/jar8/assemble/slang-braindump/assemble/content/os/ResourceRoot.class
  Last modified May 29, 2022; size 3486 bytes
  SHA-256 checksum f74c5619bb13ab246eaaf5e7c62fdb2c2c9a6996669b960080c5a3dfbbcd009b
  Compiled from "ResourcePath.scala"
public interface os.ResourceRoot
  minor version: 0
  major version: 52
  flags: (0x0601) ACC_PUBLIC, ACC_INTERFACE, ACC_ABSTRACT
  this_class: #2                          // os/ResourceRoot
  super_class: #4                         // java/lang/Object
  interfaces: 0, fields: 0, methods: 4, attributes: 5
Constant pool:
   #1 = Utf8               os/ResourceRoot
   #2 = Class              #1             // os/ResourceRoot
   #3 = Utf8               java/lang/Object
   #4 = Class              #3             // java/lang/Object
   #5 = Utf8               ResourcePath.scala
   #6 = Utf8               Lscala/reflect/ScalaSignature;
   #7 = Utf8               bytes
   #8 = Utf8               \u0006\u0005\t}baB\u001d;!\u0003\r\n#\u0010\u0005\u0006\t\u00021\t!\u0012\u0005\u00067\u00021\t\u0001X\u0004\u0007\u0005{Q\u0004\u0012\u00012\u0007\u000beR\u0004\u0012A0\t\u000b\u0001$A\u0011A1\t\r\u0011$\u0001\u0015\"\u0003f\u0011\u0015\u0001H\u0001b\u0001r\r\u0015qF\u0001\u0011B\u0001\u0011%!\bB!f\u0001\n\u0003\u0011\u0019\u0001\u0003\u0006\u0003\u000e!\u0011\t\u0012)A\u0005\u0005\u000bAa\u0001\u0019\u0005\u0005\u0002\t=\u0001B\u0002#\t\t\u0003\u0011Y\u0002\u0003\u0004\\\u0011\u0011\u0005\u0011Q\u0012\u0005\n\u0003\u001fC\u0011\u0011!C\u0001\u0005?A\u0011\"!&\t#\u0003%\tAa\t\t\u0013\u00055\u0006\"!A\u0005B\u00055\u0005\"CAX\u0011\u0005\u0005I\u0011AAY\u0011%\tI\fCA\u0001\n\u0003\u0011i\u0003C\u0005\u0002B\"\t\t\u0011\"\u0011\u0002D\"I\u0011\u0011\u001b\u0005\u0002\u0002\u0013\u0005!\u0011\u0007\u0005\n\u0003;D\u0011\u0011!C!\u0005kA\u0011\"a9\t\u0003\u0003%\t%!:\t\u0013\u0005=\u0002\"!A\u0005B\u0005E\u0002\"CAt\u0011\u0005\u0005I\u0011\tB\u001d\u000f%\t9\u0001BA\u0001\u0012\u0003\tIA\u0002\u0005_\t\u0005\u0005\t\u0012AA\u0007\u0011\u0019\u0001\'\u0004\"\u0001\u0002.!I\u0011q\u0006\u000e\u0002\u0002\u0013\u0015\u0013\u0011\u0007\u0005\n\u0003gQ\u0012\u0011!CA\u0003kA\u0011\"!\u0011\u001b\u0003\u0003%\t)a\u0011\t\u0013\u0005]#$!A\u0005\n\u0005e\u0003bBA1\t\u0011\r\u00111\r\u0004\u0006_\u0012\u0001\u0015q\r\u0005\nY\u0006\u0012)\u001a!C\u0001\u0003\u007fB\u0011\"!!\"\u0005#\u0005\u000b\u0011B7\t\r\u0001\fC\u0011AAB\u0011\u0019!\u0015\u0005\"\u0001\u0002\n\"11,\tC\u0001\u0003\u001bC\u0011\"a$\"\u0003\u0003%\t!!%\t\u0013\u0005U\u0015%%A\u0005\u0002\u0005]\u0005\"CAWC\u0005\u0005I\u0011IAG\u0011%\ty+IA\u0001\n\u0003\t\t\fC\u0005\u0002:\u0006\n\t\u0011\"\u0001\u0002<\"I\u0011\u0011Y\u0011\u0002\u0002\u0013\u0005\u00131\u0019\u0005\n\u0003#\f\u0013\u0011!C\u0001\u0003\'D\u0011\"!8\"\u0003\u0003%\t%a8\t\u0013\u0005\r\u0018%!A\u0005B\u0005\u0015\b\"CA\u0018C\u0005\u0005I\u0011IA\u0019\u0011%\t9/IA\u0001\n\u0003\nIoB\u0005\u0002n\u0012\t\t\u0011#\u0001\u0002p\u001aAq\u000eBA\u0001\u0012\u0003\t\t\u0010\u0003\u0004ag\u0011\u0005\u0011Q\u001f\u0005\n\u0003_\u0019\u0014\u0011!C#\u0003cA\u0011\"a\r4\u0003\u0003%\t)a>\t\u0013\u0005\u00053\'!A\u0005\u0002\u0006m\b\"CA,g\u0005\u0005I\u0011BA-\u00051\u0011Vm]8ve\u000e,\'k\\8u\u0015\u0005Y\u0014AA8t\u0007\u0001\u0019\"\u0001\u0001 \u0011\u0005}\u0012U\"\u0001!\u000b\u0003\u0005\u000bQa]2bY\u0006L!a\u0011!\u0003\r\u0005s\u0017PU3g\u0003M9W\r\u001e*fg>,(oY3BgN#(/Z1n)\t1e\n\u0005\u0002H\u00196\t\u0001J\u0003\u0002J\u0015\u0006\u0011\u0011n\u001c\u0006\u0002\u0017\u0006!!.\u0019<b\u0013\ti\u0005JA\u0006J]B,Ho\u0015;sK\u0006l\u0007\"B(\u0002\u0001\u0004\u0001\u0016!A:\u0011\u0005ECfB\u0001*W!\t\u0019\u0006)D\u0001U\u0015\t)F(\u0001\u0004=e>|GOP\u0005\u0003/\u0002\u000ba\u0001\u0015:fI\u00164\u0017BA-[\u0005\u0019\u0019FO]5oO*\u0011q\u000bQ\u0001\nKJ\u0014xN\u001d(b[\u0016,\u0012\u0001U\u0015\u0004\u0001!\t#!B\"mCN\u001c8C\u0001\u0003?\u0003\u0019a\u0014N\\5u}Q\t!\r\u0005\u0002d\t5\t!(A\tsK:$WM]\"mCN\u001cHn\\1eKJ$\"AZ6\u0011\u0005\u001dTW\"\u00015\u000b\u0005%T\u0015\u0001\u00027b]\u001eL!!\u00175\t\u000b14\u0001\u0019A7\u0002\u0005\rd\u0007CA4o\u0013\ty\u0007NA\u0006DY\u0006\u001c8\u000fT8bI\u0016\u0014\u0018!E2mCN\u001c(+Z:pkJ\u001cWMU8piR\u0011!o\u001d\t\u0003G\u0002AQ\u0001^\u0004A\u0002U\f1a\u00197ta\t1(\u0010E\u0002hobL!A\u00185\u0011\u0005eTH\u0002\u0001\u0003\nwN\f\t\u0011!A\u0003\u0002q\u00141a\u0018\u00132#\ri\u0018\u0011\u0001\t\u0003\u007fyL!a !\u0003\u000f9{G\u000f[5oOB\u0019q(a\u0001\n\u0007\u0005\u0015\u0001IA\u0002B]f\fQa\u00117bgN\u00042!a\u0003\u001b\u001b\u0005!1#\u0002\u000e\u0002\u0010\u0005\u001d\u0002\u0003CA\t\u0003/\tY\"!\n\u000e\u0005\u0005M!bAA\u000b\u0001\u00069!/\u001e8uS6,\u0017\u0002BA\r\u0003\'\u0011\u0011#\u00112tiJ\f7\r\u001e$v]\u000e$\u0018n\u001c82a\u0011\ti\"!\t\u0011\t\u001d<\u0018q\u0004\t\u0004s\u0006\u0005BACA\u00125\u0005\u0005\t\u0011!B\u0001y\n\u0019q\f\n\u001a\u0011\u0007\u0005-\u0001\u0002E\u0002H\u0003SI1!a\u000bI\u00051\u0019VM]5bY&T\u0018M\u00197f)\t\tI!\u0001\u0005u_N#(/\u001b8h)\u00051\u0017!B1qa2LH\u0003BA\u0013\u0003oAa\u0001^\u000fA\u0002\u0005e\u0002\u0007BA\u001e\u0003\u007f\u0001BaZ<\u0002>A\u0019\u00110a\u0010\u0005\u0017\u0005\r\u0012qGA\u0001\u0002\u0003\u0015\t\u0001`\u0001\bk:\f\u0007\u000f\u001d7z)\u0011\t)%a\u0015\u0011\u000b}\n9%a\u0013\n\u0007\u0005%\u0003I\u0001\u0004PaRLwN\u001c\u0019\u0005\u0003\u001b\n\t\u0006\u0005\u0003ho\u0006=\u0003cA=\u0002R\u0011Q\u00111\u0005\u0010\u0002\u0002\u0003\u0005)\u0011\u0001?\t\u0013\u0005Uc$!AA\u0002\u0005\u0015\u0012a\u0001=%a\u0005aqO]5uKJ+\u0007\u000f\\1dKR\u0011\u00111\f\t\u0004O\u0006u\u0013bAA0Q\n1qJ\u00196fGR\fqc\u00197bgNdu.\u00193feJ+7o\\;sG\u0016\u0014vn\u001c;\u0015\u0007I\f)\u0007C\u0003mA\u0001\u0007QnE\u0004\"}I\fI\'a\u001c\u0011\u0007}\nY\'C\u0002\u0002n\u0001\u0013q\u0001\u0015:pIV\u001cG\u000f\u0005\u0003\u0002r\u0005md\u0002BA:\u0003or1aUA;\u0013\u0005\t\u0015bAA=\u0001\u00069\u0001/Y2lC\u001e,\u0017\u0002BA\u0016\u0003{R1!!\u001fA+\u0005i\u0017aA2mAQ!\u0011QQAD!\r\tY!\t\u0005\u0006Y\u0012\u0002\r!\u001c\u000b\u0004\r\u0006-\u0005\"B(&\u0001\u0004\u0001V#\u00014\u0002\t\r|\u0007/\u001f\u000b\u0005\u0003\u000b\u000b\u0019\nC\u0004mOA\u0005\t\u0019A7\u0002\u001d\r|\u0007/\u001f\u0013eK\u001a\fW\u000f\u001c;%cU\u0011\u0011\u0011\u0014\u0016\u0004[\u0006m5FAAO!\u0011\ty*!+\u000e\u0005\u0005\u0005&\u0002BAR\u0003K\u000b\u0011\"\u001e8dQ\u0016\u001c7.\u001a3\u000b\u0007\u0005\u001d\u0006)\u0001\u0006b]:|G/\u0019;j_:LA!a+\u0002\"\n\tRO\\2iK\u000e\\W\r\u001a,be&\fgnY3\u0002\u001bA\u0014x\u000eZ;diB\u0013XMZ5y\u00031\u0001(o\u001c3vGR\f%/\u001b;z+\t\t\u0019\fE\u0002@\u0003kK1!a.A\u0005\rIe\u000e^\u0001\u000faJ|G-^2u\u000b2,W.\u001a8u)\u0011\t\t!!0\t\u0013\u0005}6&!AA\u0002\u0005M\u0016a\u0001=%c\u0005y\u0001O]8ek\u000e$\u0018\n^3sCR|\'/\u0006\u0002\u0002FB1\u0011qYAg\u0003\u0003i!!!3\u000b\u0007\u0005-\u0007)\u0001\u0006d_2dWm\u0019;j_:LA!a4\u0002J\nA\u0011\n^3sCR|\'/\u0001\u0005dC:,\u0015/^1m)\u0011\t).a7\u0011\u0007}\n9.C\u0002\u0002Z\u0002\u0013qAQ8pY\u0016\fg\u000eC\u0005\u0002@6\n\t\u00111\u0001\u0002\u0002\u0005\u0011\u0002O]8ek\u000e$X\t\\3nK:$h*Y7f)\r1\u0017\u0011\u001d\u0005\n\u0003\u007fs\u0013\u0011!a\u0001\u0003g\u000b\u0001\u0002[1tQ\u000e{G-\u001a\u000b\u0003\u0003g\u000ba!Z9vC2\u001cH\u0003BAk\u0003WD\u0011\"a02\u0003\u0003\u0005\r!!\u0001\u0002\u0017\rc\u0017m]:M_\u0006$WM\u001d\t\u0004\u0003\u0017\u00194#B\u001a\u0002t\u0006\u001d\u0002cBA\t\u0003/i\u0017Q\u0011\u000b\u0003\u0003_$B!!\"\u0002z\")AN\u000ea\u0001[R!\u0011Q`A\u0000!\u0011y\u0014qI7\t\u0013\u0005Us\'!AA\u0002\u0005\u00155c\u0002\u0005?e\u0006%\u0014qN\u000b\u0003\u0005\u000b\u0001DAa\u0002\u0003\fA!qm\u001eB\u0005!\rI(1\u0002\u0003\u000b\u0003GQ\u0011\u0011!A\u0001\u0006\u0003a\u0018\u0001B2mg\u0002\"B!!\n\u0003\u0012!1Ao\u0003a\u0001\u0005\'\u0001DA!\u0006\u0003\u001aA!qm\u001eB\f!\rI(\u0011\u0004\u0003\f\u0003G\u0011\t\"!A\u0001\u0002\u000b\u0005A\u0010F\u0002G\u0005;AQa\u0014\u0007A\u0002A#B!!\n\u0003\"!AAO\u0004I\u0001\u0002\u0004\u0011\u0019\"\u0006\u0002\u0003&A\"!q\u0005B\u0016!\u00119wO!\u000b\u0011\u0007e\u0014Y\u0003\u0002\u0006\u0002$=\t\t\u0011!A\u0003\u0002q$B!!\u0001\u00030!I\u0011q\u0018\n\u0002\u0002\u0003\u0007\u00111\u0017\u000b\u0005\u0003+\u0014\u0019\u0004C\u0005\u0002@R\t\t\u00111\u0001\u0002\u0002Q\u0019aMa\u000e\t\u0013\u0005}V#!AA\u0002\u0005MF\u0003BAk\u0005wA\u0011\"a0\u0019\u0003\u0003\u0005\r!!\u0001\u0002\u0019I+7o\\;sG\u0016\u0014vn\u001c;
   #9 = Utf8               os/ResourceRoot$Class
  #10 = Class              #9             // os/ResourceRoot$Class
  #11 = Utf8               Class
  #12 = Utf8               os/ResourceRoot$Class$
  #13 = Class              #12            // os/ResourceRoot$Class$
  #14 = Utf8               Class$
  #15 = Utf8               os/ResourceRoot$ClassLoader
  #16 = Class              #15            // os/ResourceRoot$ClassLoader
  #17 = Utf8               ClassLoader
  #18 = Utf8               os/ResourceRoot$ClassLoader$
  #19 = Class              #18            // os/ResourceRoot$ClassLoader$
  #20 = Utf8               ClassLoader$
  #21 = Utf8               classLoaderResourceRoot
  #22 = Utf8               (Ljava/lang/ClassLoader;)Los/ResourceRoot;
  #23 = Utf8               cl
  #24 = Utf8               os/ResourceRoot$
  #25 = Class              #24            // os/ResourceRoot$
  #26 = Utf8               MODULE$
  #27 = Utf8               Los/ResourceRoot$;
  #28 = NameAndType        #26:#27        // MODULE$:Los/ResourceRoot$;
  #29 = Fieldref           #25.#28        // os/ResourceRoot$.MODULE$:Los/ResourceRoot$;
  #30 = NameAndType        #21:#22        // classLoaderResourceRoot:(Ljava/lang/ClassLoader;)Los/ResourceRoot;
  #31 = Methodref          #25.#30        // os/ResourceRoot$.classLoaderResourceRoot:(Ljava/lang/ClassLoader;)Los/ResourceRoot;
  #32 = Utf8               classResourceRoot
  #33 = Utf8               (Ljava/lang/Class;)Los/ResourceRoot;
  #34 = Utf8               (Ljava/lang/Class<*>;)Los/ResourceRoot;
  #35 = Utf8               cls
  #36 = NameAndType        #32:#33        // classResourceRoot:(Ljava/lang/Class;)Los/ResourceRoot;
  #37 = Methodref          #25.#36        // os/ResourceRoot$.classResourceRoot:(Ljava/lang/Class;)Los/ResourceRoot;
  #38 = Utf8               getResourceAsStream
  #39 = Utf8               (Ljava/lang/String;)Ljava/io/InputStream;
  #40 = Utf8               s
  #41 = Utf8               errorName
  #42 = Utf8               ()Ljava/lang/String;
  #43 = Utf8               Code
  #44 = Utf8               MethodParameters
  #45 = Utf8               Signature
  #46 = Utf8               InnerClasses
  #47 = Utf8               SourceFile
  #48 = Utf8               RuntimeVisibleAnnotations
  #49 = Utf8               ScalaInlineInfo
  #50 = Utf8               ScalaSig
{
  public static os.ResourceRoot classLoaderResourceRoot(java.lang.ClassLoader);
    descriptor: (Ljava/lang/ClassLoader;)Los/ResourceRoot;
    flags: (0x0009) ACC_PUBLIC, ACC_STATIC
    Code:
      stack=2, locals=1, args_size=1
         0: getstatic     #29                 // Field os/ResourceRoot$.MODULE$:Los/ResourceRoot$;
         3: aload_0
         4: invokevirtual #31                 // Method os/ResourceRoot$.classLoaderResourceRoot:(Ljava/lang/ClassLoader;)Los/ResourceRoot;
         7: areturn
    MethodParameters:
      Name                           Flags
      cl                             final

  public static os.ResourceRoot classResourceRoot(java.lang.Class<?>);
    descriptor: (Ljava/lang/Class;)Los/ResourceRoot;
    flags: (0x0009) ACC_PUBLIC, ACC_STATIC
    Code:
      stack=2, locals=1, args_size=1
         0: getstatic     #29                 // Field os/ResourceRoot$.MODULE$:Los/ResourceRoot$;
         3: aload_0
         4: invokevirtual #37                 // Method os/ResourceRoot$.classResourceRoot:(Ljava/lang/Class;)Los/ResourceRoot;
         7: areturn
    Signature: #34                          // (Ljava/lang/Class<*>;)Los/ResourceRoot;
    MethodParameters:
      Name                           Flags
      cls                            final

  public abstract java.io.InputStream getResourceAsStream(java.lang.String);
    descriptor: (Ljava/lang/String;)Ljava/io/InputStream;
    flags: (0x0401) ACC_PUBLIC, ACC_ABSTRACT
    MethodParameters:
      Name                           Flags
      s                              final

  public abstract java.lang.String errorName();
    descriptor: ()Ljava/lang/String;
    flags: (0x0401) ACC_PUBLIC, ACC_ABSTRACT
}
InnerClasses:
  public static #11= #10 of #2;           // Class=class os/ResourceRoot$Class of class os/ResourceRoot
  public static #14= #13 of #2;           // Class$=class os/ResourceRoot$Class$ of class os/ResourceRoot
  public static #17= #16 of #2;           // ClassLoader=class os/ResourceRoot$ClassLoader of class os/ResourceRoot
  public static #20= #19 of #2;           // ClassLoader$=class os/ResourceRoot$ClassLoader$ of class os/ResourceRoot
SourceFile: "ResourcePath.scala"
RuntimeVisibleAnnotations:
  0: #6(#7=s#8)
    scala.reflect.ScalaSignature(
      bytes="\u0006\u0005\t}baB\u001d;!\u0003\r\n#\u0010\u0005\u0006\t\u00021\t!\u0012\u0005\u00067\u00021\t\u0001X\u0004\u0007\u0005{Q\u0004\u0012\u00012\u0007\u000beR\u0004\u0012A0\t\u000b\u0001$A\u0011A1\t\r\u0011$\u0001\u0015\"\u0003f\u0011\u0015\u0001H\u0001b\u0001r\r\u0015qF\u0001\u0011B\u0001\u0011%!\bB!f\u0001\n\u0003\u0011\u0019\u0001\u0003\u0006\u0003\u000e!\u0011\t\u0012)A\u0005\u0005\u000bAa\u0001\u0019\u0005\u0005\u0002\t=\u0001B\u0002#\t\t\u0003\u0011Y\u0002\u0003\u0004\\\u0011\u0011\u0005\u0011Q\u0012\u0005\n\u0003\u001fC\u0011\u0011!C\u0001\u0005?A\u0011\"!&\t#\u0003%\tAa\t\t\u0013\u00055\u0006\"!A\u0005B\u00055\u0005\"CAX\u0011\u0005\u0005I\u0011AAY\u0011%\tI\fCA\u0001\n\u0003\u0011i\u0003C\u0005\u0002B\"\t\t\u0011\"\u0011\u0002D\"I\u0011\u0011\u001b\u0005\u0002\u0002\u0013\u0005!\u0011\u0007\u0005\n\u0003;D\u0011\u0011!C!\u0005kA\u0011\"a9\t\u0003\u0003%\t%!:\t\u0013\u0005=\u0002\"!A\u0005B\u0005E\u0002\"CAt\u0011\u0005\u0005I\u0011\tB\u001d\u000f%\t9\u0001BA\u0001\u0012\u0003\tIA\u0002\u0005_\t\u0005\u0005\t\u0012AA\u0007\u0011\u0019\u0001\'\u0004\"\u0001\u0002.!I\u0011q\u0006\u000e\u0002\u0002\u0013\u0015\u0013\u0011\u0007\u0005\n\u0003gQ\u0012\u0011!CA\u0003kA\u0011\"!\u0011\u001b\u0003\u0003%\t)a\u0011\t\u0013\u0005]#$!A\u0005\n\u0005e\u0003bBA1\t\u0011\r\u00111\r\u0004\u0006_\u0012\u0001\u0015q\r\u0005\nY\u0006\u0012)\u001a!C\u0001\u0003\u007fB\u0011\"!!\"\u0005#\u0005\u000b\u0011B7\t\r\u0001\fC\u0011AAB\u0011\u0019!\u0015\u0005\"\u0001\u0002\n\"11,\tC\u0001\u0003\u001bC\u0011\"a$\"\u0003\u0003%\t!!%\t\u0013\u0005U\u0015%%A\u0005\u0002\u0005]\u0005\"CAWC\u0005\u0005I\u0011IAG\u0011%\ty+IA\u0001\n\u0003\t\t\fC\u0005\u0002:\u0006\n\t\u0011\"\u0001\u0002<\"I\u0011\u0011Y\u0011\u0002\u0002\u0013\u0005\u00131\u0019\u0005\n\u0003#\f\u0013\u0011!C\u0001\u0003\'D\u0011\"!8\"\u0003\u0003%\t%a8\t\u0013\u0005\r\u0018%!A\u0005B\u0005\u0015\b\"CA\u0018C\u0005\u0005I\u0011IA\u0019\u0011%\t9/IA\u0001\n\u0003\nIoB\u0005\u0002n\u0012\t\t\u0011#\u0001\u0002p\u001aAq\u000eBA\u0001\u0012\u0003\t\t\u0010\u0003\u0004ag\u0011\u0005\u0011Q\u001f\u0005\n\u0003_\u0019\u0014\u0011!C#\u0003cA\u0011\"a\r4\u0003\u0003%\t)a>\t\u0013\u0005\u00053\'!A\u0005\u0002\u0006m\b\"CA,g\u0005\u0005I\u0011BA-\u00051\u0011Vm]8ve\u000e,\'k\\8u\u0015\u0005Y\u0014AA8t\u0007\u0001\u0019\"\u0001\u0001 \u0011\u0005}\u0012U\"\u0001!\u000b\u0003\u0005\u000bQa]2bY\u0006L!a\u0011!\u0003\r\u0005s\u0017PU3g\u0003M9W\r\u001e*fg>,(oY3BgN#(/Z1n)\t1e\n\u0005\u0002H\u00196\t\u0001J\u0003\u0002J\u0015\u0006\u0011\u0011n\u001c\u0006\u0002\u0017\u0006!!.\u0019<b\u0013\ti\u0005JA\u0006J]B,Ho\u0015;sK\u0006l\u0007\"B(\u0002\u0001\u0004\u0001\u0016!A:\u0011\u0005ECfB\u0001*W!\t\u0019\u0006)D\u0001U\u0015\t)F(\u0001\u0004=e>|GOP\u0005\u0003/\u0002\u000ba\u0001\u0015:fI\u00164\u0017BA-[\u0005\u0019\u0019FO]5oO*\u0011q\u000bQ\u0001\nKJ\u0014xN\u001d(b[\u0016,\u0012\u0001U\u0015\u0004\u0001!\t#!B\"mCN\u001c8C\u0001\u0003?\u0003\u0019a\u0014N\\5u}Q\t!\r\u0005\u0002d\t5\t!(A\tsK:$WM]\"mCN\u001cHn\\1eKJ$\"AZ6\u0011\u0005\u001dTW\"\u00015\u000b\u0005%T\u0015\u0001\u00027b]\u001eL!!\u00175\t\u000b14\u0001\u0019A7\u0002\u0005\rd\u0007CA4o\u0013\ty\u0007NA\u0006DY\u0006\u001c8\u000fT8bI\u0016\u0014\u0018!E2mCN\u001c(+Z:pkJ\u001cWMU8piR\u0011!o\u001d\t\u0003G\u0002AQ\u0001^\u0004A\u0002U\f1a\u00197ta\t1(\u0010E\u0002hobL!A\u00185\u0011\u0005eTH\u0002\u0001\u0003\nwN\f\t\u0011!A\u0003\u0002q\u00141a\u0018\u00132#\ri\u0018\u0011\u0001\t\u0003\u007fyL!a !\u0003\u000f9{G\u000f[5oOB\u0019q(a\u0001\n\u0007\u0005\u0015\u0001IA\u0002B]f\fQa\u00117bgN\u00042!a\u0003\u001b\u001b\u0005!1#\u0002\u000e\u0002\u0010\u0005\u001d\u0002\u0003CA\t\u0003/\tY\"!\n\u000e\u0005\u0005M!bAA\u000b\u0001\u00069!/\u001e8uS6,\u0017\u0002BA\r\u0003\'\u0011\u0011#\u00112tiJ\f7\r\u001e$v]\u000e$\u0018n\u001c82a\u0011\ti\"!\t\u0011\t\u001d<\u0018q\u0004\t\u0004s\u0006\u0005BACA\u00125\u0005\u0005\t\u0011!B\u0001y\n\u0019q\f\n\u001a\u0011\u0007\u0005-\u0001\u0002E\u0002H\u0003SI1!a\u000bI\u00051\u0019VM]5bY&T\u0018M\u00197f)\t\tI!\u0001\u0005u_N#(/\u001b8h)\u00051\u0017!B1qa2LH\u0003BA\u0013\u0003oAa\u0001^\u000fA\u0002\u0005e\u0002\u0007BA\u001e\u0003\u007f\u0001BaZ<\u0002>A\u0019\u00110a\u0010\u0005\u0017\u0005\r\u0012qGA\u0001\u0002\u0003\u0015\t\u0001`\u0001\bk:\f\u0007\u000f\u001d7z)\u0011\t)%a\u0015\u0011\u000b}\n9%a\u0013\n\u0007\u0005%\u0003I\u0001\u0004PaRLwN\u001c\u0019\u0005\u0003\u001b\n\t\u0006\u0005\u0003ho\u0006=\u0003cA=\u0002R\u0011Q\u00111\u0005\u0010\u0002\u0002\u0003\u0005)\u0011\u0001?\t\u0013\u0005Uc$!AA\u0002\u0005\u0015\u0012a\u0001=%a\u0005aqO]5uKJ+\u0007\u000f\\1dKR\u0011\u00111\f\t\u0004O\u0006u\u0013bAA0Q\n1qJ\u00196fGR\fqc\u00197bgNdu.\u00193feJ+7o\\;sG\u0016\u0014vn\u001c;\u0015\u0007I\f)\u0007C\u0003mA\u0001\u0007QnE\u0004\"}I\fI\'a\u001c\u0011\u0007}\nY\'C\u0002\u0002n\u0001\u0013q\u0001\u0015:pIV\u001cG\u000f\u0005\u0003\u0002r\u0005md\u0002BA:\u0003or1aUA;\u0013\u0005\t\u0015bAA=\u0001\u00069\u0001/Y2lC\u001e,\u0017\u0002BA\u0016\u0003{R1!!\u001fA+\u0005i\u0017aA2mAQ!\u0011QQAD!\r\tY!\t\u0005\u0006Y\u0012\u0002\r!\u001c\u000b\u0004\r\u0006-\u0005\"B(&\u0001\u0004\u0001V#\u00014\u0002\t\r|\u0007/\u001f\u000b\u0005\u0003\u000b\u000b\u0019\nC\u0004mOA\u0005\t\u0019A7\u0002\u001d\r|\u0007/\u001f\u0013eK\u001a\fW\u000f\u001c;%cU\u0011\u0011\u0011\u0014\u0016\u0004[\u0006m5FAAO!\u0011\ty*!+\u000e\u0005\u0005\u0005&\u0002BAR\u0003K\u000b\u0011\"\u001e8dQ\u0016\u001c7.\u001a3\u000b\u0007\u0005\u001d\u0006)\u0001\u0006b]:|G/\u0019;j_:LA!a+\u0002\"\n\tRO\\2iK\u000e\\W\r\u001a,be&\fgnY3\u0002\u001bA\u0014x\u000eZ;diB\u0013XMZ5y\u00031\u0001(o\u001c3vGR\f%/\u001b;z+\t\t\u0019\fE\u0002@\u0003kK1!a.A\u0005\rIe\u000e^\u0001\u000faJ|G-^2u\u000b2,W.\u001a8u)\u0011\t\t!!0\t\u0013\u0005}6&!AA\u0002\u0005M\u0016a\u0001=%c\u0005y\u0001O]8ek\u000e$\u0018\n^3sCR|\'/\u0006\u0002\u0002FB1\u0011qYAg\u0003\u0003i!!!3\u000b\u0007\u0005-\u0007)\u0001\u0006d_2dWm\u0019;j_:LA!a4\u0002J\nA\u0011\n^3sCR|\'/\u0001\u0005dC:,\u0015/^1m)\u0011\t).a7\u0011\u0007}\n9.C\u0002\u0002Z\u0002\u0013qAQ8pY\u0016\fg\u000eC\u0005\u0002@6\n\t\u00111\u0001\u0002\u0002\u0005\u0011\u0002O]8ek\u000e$X\t\\3nK:$h*Y7f)\r1\u0017\u0011\u001d\u0005\n\u0003\u007fs\u0013\u0011!a\u0001\u0003g\u000b\u0001\u0002[1tQ\u000e{G-\u001a\u000b\u0003\u0003g\u000ba!Z9vC2\u001cH\u0003BAk\u0003WD\u0011\"a02\u0003\u0003\u0005\r!!\u0001\u0002\u0017\rc\u0017m]:M_\u0006$WM\u001d\t\u0004\u0003\u0017\u00194#B\u001a\u0002t\u0006\u001d\u0002cBA\t\u0003/i\u0017Q\u0011\u000b\u0003\u0003_$B!!\"\u0002z\")AN\u000ea\u0001[R!\u0011Q`A\u0000!\u0011y\u0014qI7\t\u0013\u0005Us\'!AA\u0002\u0005\u00155c\u0002\u0005?e\u0006%\u0014qN\u000b\u0003\u0005\u000b\u0001DAa\u0002\u0003\fA!qm\u001eB\u0005!\rI(1\u0002\u0003\u000b\u0003GQ\u0011\u0011!A\u0001\u0006\u0003a\u0018\u0001B2mg\u0002\"B!!\n\u0003\u0012!1Ao\u0003a\u0001\u0005\'\u0001DA!\u0006\u0003\u001aA!qm\u001eB\f!\rI(\u0011\u0004\u0003\f\u0003G\u0011\t\"!A\u0001\u0002\u000b\u0005A\u0010F\u0002G\u0005;AQa\u0014\u0007A\u0002A#B!!\n\u0003\"!AAO\u0004I\u0001\u0002\u0004\u0011\u0019\"\u0006\u0002\u0003&A\"!q\u0005B\u0016!\u00119wO!\u000b\u0011\u0007e\u0014Y\u0003\u0002\u0006\u0002$=\t\t\u0011!A\u0003\u0002q$B!!\u0001\u00030!I\u0011q\u0018\n\u0002\u0002\u0003\u0007\u00111\u0017\u000b\u0005\u0003+\u0014\u0019\u0004C\u0005\u0002@R\t\t\u00111\u0001\u0002\u0002Q\u0019aMa\u000e\t\u0013\u0005}V#!AA\u0002\u0005MF\u0003BAk\u0005wA\u0011\"a0\u0019\u0003\u0003\u0005\r!!\u0001\u0002\u0019I+7o\\;sG\u0016\u0014vn\u001c;"
    )
  ScalaInlineInfo: length = 0xE (unknown attribute)
   01 00 00 02 00 29 00 2A 00 00 26 00 27 00
  ScalaSig: length = 0x3 (unknown attribute)
   05 02 00
