Classfile /Users/mw/Projects/slang-braindump/.jar/jar8/assemble/slang-braindump/assemble/content/os/SubPath$.class
  Last modified May 29, 2022; size 5629 bytes
  SHA-256 checksum cd6f254f281a47614142db7dec152e1e926ba1f08a0c80681c95426438370d36
  Compiled from "Path.scala"
public final class os.SubPath$
  minor version: 0
  major version: 52
  flags: (0x0031) ACC_PUBLIC, ACC_FINAL, ACC_SUPER
  this_class: #2                          // os/SubPath$
  super_class: #4                         // java/lang/Object
  interfaces: 0, fields: 3, methods: 11, attributes: 5
Constant pool:
    #1 = Utf8               os/SubPath$
    #2 = Class              #1            // os/SubPath$
    #3 = Utf8               java/lang/Object
    #4 = Class              #3            // java/lang/Object
    #5 = Utf8               Path.scala
    #6 = Utf8               java/lang/invoke/MethodHandles$Lookup
    #7 = Class              #6            // java/lang/invoke/MethodHandles$Lookup
    #8 = Utf8               java/lang/invoke/MethodHandles
    #9 = Class              #8            // java/lang/invoke/MethodHandles
   #10 = Utf8               Lookup
   #11 = Utf8               scala/math/Ordering$Implicits$
   #12 = Class              #11           // scala/math/Ordering$Implicits$
   #13 = Utf8               scala/math/Ordering
   #14 = Class              #13           // scala/math/Ordering
   #15 = Utf8               Implicits$
   #16 = Utf8               scala/math/Ordering$Int$
   #17 = Class              #16           // scala/math/Ordering$Int$
   #18 = Utf8               Int$
   #19 = Utf8               scala/math/Ordering$String$
   #20 = Class              #19           // scala/math/Ordering$String$
   #21 = Utf8               String$
   #22 = Utf8               MODULE$
   #23 = Utf8               Los/SubPath$;
   #24 = Utf8               subPathOrdering
   #25 = Utf8               Lscala/math/Ordering;
   #26 = Utf8               Lscala/math/Ordering<Los/SubPath;>;
   #27 = Utf8               sub
   #28 = Utf8               Los/SubPath;
   #29 = Utf8               <clinit>
   #30 = Utf8               ()V
   #31 = Utf8               <init>
   #32 = NameAndType        #31:#30       // "<init>":()V
   #33 = Methodref          #2.#32        // os/SubPath$."<init>":()V
   #34 = NameAndType        #22:#23       // MODULE$:Los/SubPath$;
   #35 = Fieldref           #2.#34        // os/SubPath$.MODULE$:Los/SubPath$;
   #36 = Utf8               scala/package$
   #37 = Class              #36           // scala/package$
   #38 = Utf8               Lscala/package$;
   #39 = NameAndType        #22:#38       // MODULE$:Lscala/package$;
   #40 = Fieldref           #37.#39       // scala/package$.MODULE$:Lscala/package$;
   #41 = Utf8               Ordering
   #42 = Utf8               ()Lscala/math/Ordering$;
   #43 = NameAndType        #41:#42       // Ordering:()Lscala/math/Ordering$;
   #44 = Methodref          #37.#43       // scala/package$.Ordering:()Lscala/math/Ordering$;
   #45 = Utf8               (Ljava/lang/Object;)Ljava/lang/Object;
   #46 = MethodType         #45           //  (Ljava/lang/Object;)Ljava/lang/Object;
   #47 = Utf8               $anonfun$subPathOrdering$1
   #48 = Utf8               (Los/SubPath;)Lscala/Tuple2;
   #49 = NameAndType        #47:#48       // $anonfun$subPathOrdering$1:(Los/SubPath;)Lscala/Tuple2;
   #50 = Methodref          #2.#49        // os/SubPath$.$anonfun$subPathOrdering$1:(Los/SubPath;)Lscala/Tuple2;
   #51 = MethodHandle       6:#50         // REF_invokeStatic os/SubPath$.$anonfun$subPathOrdering$1:(Los/SubPath;)Lscala/Tuple2;
   #52 = MethodType         #48           //  (Los/SubPath;)Lscala/Tuple2;
   #53 = Integer            5
   #54 = Integer            1
   #55 = Utf8               java/lang/invoke/LambdaMetafactory
   #56 = Class              #55           // java/lang/invoke/LambdaMetafactory
   #57 = Utf8               altMetafactory
   #58 = Utf8               (Ljava/lang/invoke/MethodHandles$Lookup;Ljava/lang/String;Ljava/lang/invoke/MethodType;[Ljava/lang/Object;)Ljava/lang/invoke/CallSite;
   #59 = NameAndType        #57:#58       // altMetafactory:(Ljava/lang/invoke/MethodHandles$Lookup;Ljava/lang/String;Ljava/lang/invoke/MethodType;[Ljava/lang/Object;)Ljava/lang/invoke/CallSite;
   #60 = Methodref          #56.#59       // java/lang/invoke/LambdaMetafactory.altMetafactory:(Ljava/lang/invoke/MethodHandles$Lookup;Ljava/lang/String;Ljava/lang/invoke/MethodType;[Ljava/lang/Object;)Ljava/lang/invoke/CallSite;
   #61 = MethodHandle       6:#60         // REF_invokeStatic java/lang/invoke/LambdaMetafactory.altMetafactory:(Ljava/lang/invoke/MethodHandles$Lookup;Ljava/lang/String;Ljava/lang/invoke/MethodType;[Ljava/lang/Object;)Ljava/lang/invoke/CallSite;
   #62 = Utf8               apply
   #63 = Utf8               ()Lscala/Function1;
   #64 = NameAndType        #62:#63       // apply:()Lscala/Function1;
   #65 = InvokeDynamic      #0:#64        // #0:apply:()Lscala/Function1;
   #66 = Utf8               scala/math/Ordering$
   #67 = Class              #66           // scala/math/Ordering$
   #68 = Utf8               Lscala/math/Ordering$;
   #69 = NameAndType        #22:#68       // MODULE$:Lscala/math/Ordering$;
   #70 = Fieldref           #67.#69       // scala/math/Ordering$.MODULE$:Lscala/math/Ordering$;
   #71 = Utf8               Lscala/math/Ordering$Int$;
   #72 = NameAndType        #22:#71       // MODULE$:Lscala/math/Ordering$Int$;
   #73 = Fieldref           #17.#72       // scala/math/Ordering$Int$.MODULE$:Lscala/math/Ordering$Int$;
   #74 = Utf8               Lscala/math/Ordering$Implicits$;
   #75 = NameAndType        #22:#74       // MODULE$:Lscala/math/Ordering$Implicits$;
   #76 = Fieldref           #12.#75       // scala/math/Ordering$Implicits$.MODULE$:Lscala/math/Ordering$Implicits$;
   #77 = Utf8               Lscala/math/Ordering$String$;
   #78 = NameAndType        #22:#77       // MODULE$:Lscala/math/Ordering$String$;
   #79 = Fieldref           #20.#78       // scala/math/Ordering$String$.MODULE$:Lscala/math/Ordering$String$;
   #80 = Utf8               seqOrdering
   #81 = Utf8               (Lscala/math/Ordering;)Lscala/math/Ordering;
   #82 = NameAndType        #80:#81       // seqOrdering:(Lscala/math/Ordering;)Lscala/math/Ordering;
   #83 = Methodref          #12.#82       // scala/math/Ordering$Implicits$.seqOrdering:(Lscala/math/Ordering;)Lscala/math/Ordering;
   #84 = Utf8               Tuple2
   #85 = Utf8               (Lscala/math/Ordering;Lscala/math/Ordering;)Lscala/math/Ordering;
   #86 = NameAndType        #84:#85       // Tuple2:(Lscala/math/Ordering;Lscala/math/Ordering;)Lscala/math/Ordering;
   #87 = Methodref          #67.#86       // scala/math/Ordering$.Tuple2:(Lscala/math/Ordering;Lscala/math/Ordering;)Lscala/math/Ordering;
   #88 = Utf8               by
   #89 = Utf8               (Lscala/Function1;Lscala/math/Ordering;)Lscala/math/Ordering;
   #90 = NameAndType        #88:#89       // by:(Lscala/Function1;Lscala/math/Ordering;)Lscala/math/Ordering;
   #91 = Methodref          #67.#90       // scala/math/Ordering$.by:(Lscala/Function1;Lscala/math/Ordering;)Lscala/math/Ordering;
   #92 = NameAndType        #24:#25       // subPathOrdering:Lscala/math/Ordering;
   #93 = Fieldref           #2.#92        // os/SubPath$.subPathOrdering:Lscala/math/Ordering;
   #94 = Utf8               os/SubPath
   #95 = Class              #94           // os/SubPath
   #96 = Utf8               os/Internals$
   #97 = Class              #96           // os/Internals$
   #98 = Utf8               Los/Internals$;
   #99 = NameAndType        #22:#98       // MODULE$:Los/Internals$;
  #100 = Fieldref           #97.#99       // os/Internals$.MODULE$:Los/Internals$;
  #101 = Utf8               emptyStringArray
  #102 = Utf8               ()[Ljava/lang/String;
  #103 = NameAndType        #101:#102     // emptyStringArray:()[Ljava/lang/String;
  #104 = Methodref          #97.#103      // os/Internals$.emptyStringArray:()[Ljava/lang/String;
  #105 = Utf8               ([Ljava/lang/String;)V
  #106 = NameAndType        #31:#105      // "<init>":([Ljava/lang/String;)V
  #107 = Methodref          #95.#106      // os/SubPath."<init>":([Ljava/lang/String;)V
  #108 = NameAndType        #27:#28       // sub:Los/SubPath;
  #109 = Fieldref           #2.#108       // os/SubPath$.sub:Los/SubPath;
  #110 = Utf8               relativeTo0
  #111 = Utf8               ([Ljava/lang/String;Lscala/collection/immutable/IndexedSeq;)Los/RelPath;
  #112 = Utf8               ([Ljava/lang/String;Lscala/collection/immutable/IndexedSeq<Ljava/lang/String;>;)Los/RelPath;
  #113 = Utf8               segments0
  #114 = Utf8               segments
  #115 = Utf8               scala/math/package$
  #116 = Class              #115          // scala/math/package$
  #117 = Utf8               Lscala/math/package$;
  #118 = NameAndType        #22:#117      // MODULE$:Lscala/math/package$;
  #119 = Fieldref           #116.#118     // scala/math/package$.MODULE$:Lscala/math/package$;
  #120 = Utf8               scala/collection/immutable/IndexedSeq
  #121 = Class              #120          // scala/collection/immutable/IndexedSeq
  #122 = Utf8               length
  #123 = Utf8               ()I
  #124 = NameAndType        #122:#123     // length:()I
  #125 = InterfaceMethodref #121.#124     // scala/collection/immutable/IndexedSeq.length:()I
  #126 = Utf8               min
  #127 = Utf8               (II)I
  #128 = NameAndType        #126:#127     // min:(II)I
  #129 = Methodref          #116.#128     // scala/math/package$.min:(II)I
  #130 = Utf8               (I)Ljava/lang/Object;
  #131 = NameAndType        #62:#130      // apply:(I)Ljava/lang/Object;
  #132 = InterfaceMethodref #121.#131     // scala/collection/immutable/IndexedSeq.apply:(I)Ljava/lang/Object;
  #133 = Utf8               equals
  #134 = Utf8               (Ljava/lang/Object;)Z
  #135 = NameAndType        #133:#134     // equals:(Ljava/lang/Object;)Z
  #136 = Methodref          #4.#135       // java/lang/Object.equals:(Ljava/lang/Object;)Z
  #137 = Utf8               os/RelPath
  #138 = Class              #137          // os/RelPath
  #139 = Utf8               scala/collection/ArrayOps$
  #140 = Class              #139          // scala/collection/ArrayOps$
  #141 = Utf8               Lscala/collection/ArrayOps$;
  #142 = NameAndType        #22:#141      // MODULE$:Lscala/collection/ArrayOps$;
  #143 = Fieldref           #140.#142     // scala/collection/ArrayOps$.MODULE$:Lscala/collection/ArrayOps$;
  #144 = Utf8               scala/Predef$
  #145 = Class              #144          // scala/Predef$
  #146 = Utf8               Lscala/Predef$;
  #147 = NameAndType        #22:#146      // MODULE$:Lscala/Predef$;
  #148 = Fieldref           #145.#147     // scala/Predef$.MODULE$:Lscala/Predef$;
  #149 = Utf8               [Ljava/lang/Object;
  #150 = Class              #149          // "[Ljava/lang/Object;"
  #151 = Utf8               refArrayOps
  #152 = Utf8               ([Ljava/lang/Object;)Ljava/lang/Object;
  #153 = NameAndType        #151:#152     // refArrayOps:([Ljava/lang/Object;)Ljava/lang/Object;
  #154 = Methodref          #145.#153     // scala/Predef$.refArrayOps:([Ljava/lang/Object;)Ljava/lang/Object;
  #155 = Utf8               drop$extension
  #156 = Utf8               (Ljava/lang/Object;I)Ljava/lang/Object;
  #157 = NameAndType        #155:#156     // drop$extension:(Ljava/lang/Object;I)Ljava/lang/Object;
  #158 = Methodref          #140.#157     // scala/collection/ArrayOps$.drop$extension:(Ljava/lang/Object;I)Ljava/lang/Object;
  #159 = Utf8               [Ljava/lang/String;
  #160 = Class              #159          // "[Ljava/lang/String;"
  #161 = Utf8               ([Ljava/lang/String;I)V
  #162 = NameAndType        #31:#161      // "<init>":([Ljava/lang/String;I)V
  #163 = Methodref          #138.#162     // os/RelPath."<init>":([Ljava/lang/String;I)V
  #164 = Utf8               maxSize
  #165 = Utf8               I
  #166 = Utf8               i
  #167 = Utf8               commonPrefix
  #168 = Utf8               newUps
  #169 = Utf8               this
  #170 = Utf8               Lscala/collection/immutable/IndexedSeq;
  #171 = Utf8               java/lang/String
  #172 = Class              #171          // java/lang/String
  #173 = Utf8               (Ljava/lang/Object;Los/PathConvertible;)Los/SubPath;
  #174 = Utf8               <T:Ljava/lang/Object;>(TT;Los/PathConvertible<TT;>;)Los/SubPath;
  #175 = Utf8               f0
  #176 = Utf8               evidence$3
  #177 = Utf8               os/RelPath$
  #178 = Class              #177          // os/RelPath$
  #179 = Utf8               Los/RelPath$;
  #180 = NameAndType        #22:#179      // MODULE$:Los/RelPath$;
  #181 = Fieldref           #178.#180     // os/RelPath$.MODULE$:Los/RelPath$;
  #182 = Utf8               (Ljava/lang/Object;Los/PathConvertible;)Los/RelPath;
  #183 = NameAndType        #62:#182      // apply:(Ljava/lang/Object;Los/PathConvertible;)Los/RelPath;
  #184 = Methodref          #178.#183     // os/RelPath$.apply:(Ljava/lang/Object;Los/PathConvertible;)Los/RelPath;
  #185 = Utf8               asSubPath
  #186 = Utf8               ()Los/SubPath;
  #187 = NameAndType        #185:#186     // asSubPath:()Los/SubPath;
  #188 = Methodref          #138.#187     // os/RelPath.asSubPath:()Los/SubPath;
  #189 = Utf8               Ljava/lang/Object;
  #190 = Utf8               Los/PathConvertible;
  #191 = Utf8               (Lscala/collection/immutable/IndexedSeq;)Los/SubPath;
  #192 = Utf8               (Lscala/collection/immutable/IndexedSeq<Ljava/lang/String;>;)Los/SubPath;
  #193 = Utf8               $anonfun$apply$4$adapted
  #194 = Utf8               (Ljava/lang/String;)Ljava/lang/Object;
  #195 = NameAndType        #193:#194     // $anonfun$apply$4$adapted:(Ljava/lang/String;)Ljava/lang/Object;
  #196 = Methodref          #2.#195       // os/SubPath$.$anonfun$apply$4$adapted:(Ljava/lang/String;)Ljava/lang/Object;
  #197 = MethodHandle       6:#196        // REF_invokeStatic os/SubPath$.$anonfun$apply$4$adapted:(Ljava/lang/String;)Ljava/lang/Object;
  #198 = MethodType         #194          //  (Ljava/lang/String;)Ljava/lang/Object;
  #199 = InvokeDynamic      #1:#64        // #1:apply:()Lscala/Function1;
  #200 = Utf8               foreach
  #201 = Utf8               (Lscala/Function1;)V
  #202 = NameAndType        #200:#201     // foreach:(Lscala/Function1;)V
  #203 = InterfaceMethodref #121.#202     // scala/collection/immutable/IndexedSeq.foreach:(Lscala/Function1;)V
  #204 = Utf8               scala/reflect/ClassTag$
  #205 = Class              #204          // scala/reflect/ClassTag$
  #206 = Utf8               Lscala/reflect/ClassTag$;
  #207 = NameAndType        #22:#206      // MODULE$:Lscala/reflect/ClassTag$;
  #208 = Fieldref           #205.#207     // scala/reflect/ClassTag$.MODULE$:Lscala/reflect/ClassTag$;
  #209 = Utf8               (Ljava/lang/Class;)Lscala/reflect/ClassTag;
  #210 = NameAndType        #62:#209      // apply:(Ljava/lang/Class;)Lscala/reflect/ClassTag;
  #211 = Methodref          #205.#210     // scala/reflect/ClassTag$.apply:(Ljava/lang/Class;)Lscala/reflect/ClassTag;
  #212 = Utf8               toArray
  #213 = Utf8               (Lscala/reflect/ClassTag;)Ljava/lang/Object;
  #214 = NameAndType        #212:#213     // toArray:(Lscala/reflect/ClassTag;)Ljava/lang/Object;
  #215 = InterfaceMethodref #121.#214     // scala/collection/immutable/IndexedSeq.toArray:(Lscala/reflect/ClassTag;)Ljava/lang/Object;
  #216 = Utf8               ()Lscala/math/Ordering;
  #217 = Utf8               ()Lscala/math/Ordering<Los/SubPath;>;
  #218 = Utf8               $anonfun$apply$4
  #219 = Utf8               (Ljava/lang/String;)V
  #220 = Utf8               s
  #221 = Utf8               os/BasePath$
  #222 = Class              #221          // os/BasePath$
  #223 = Utf8               Los/BasePath$;
  #224 = NameAndType        #22:#223      // MODULE$:Los/BasePath$;
  #225 = Fieldref           #222.#224     // os/BasePath$.MODULE$:Los/BasePath$;
  #226 = Utf8               checkSegment
  #227 = NameAndType        #226:#219     // checkSegment:(Ljava/lang/String;)V
  #228 = Methodref          #222.#227     // os/BasePath$.checkSegment:(Ljava/lang/String;)V
  #229 = Utf8               Ljava/lang/String;
  #230 = Utf8               rp
  #231 = Utf8               scala/Tuple2
  #232 = Class              #231          // scala/Tuple2
  #233 = Utf8               ()Lscala/collection/immutable/IndexedSeq;
  #234 = NameAndType        #114:#233     // segments:()Lscala/collection/immutable/IndexedSeq;
  #235 = Methodref          #95.#234      // os/SubPath.segments:()Lscala/collection/immutable/IndexedSeq;
  #236 = Utf8               scala/runtime/BoxesRunTime
  #237 = Class              #236          // scala/runtime/BoxesRunTime
  #238 = Utf8               boxToInteger
  #239 = Utf8               (I)Ljava/lang/Integer;
  #240 = NameAndType        #238:#239     // boxToInteger:(I)Ljava/lang/Integer;
  #241 = Methodref          #237.#240     // scala/runtime/BoxesRunTime.boxToInteger:(I)Ljava/lang/Integer;
  #242 = Utf8               toIterable
  #243 = Utf8               ()Lscala/collection/Iterable;
  #244 = NameAndType        #242:#243     // toIterable:()Lscala/collection/Iterable;
  #245 = InterfaceMethodref #121.#244     // scala/collection/immutable/IndexedSeq.toIterable:()Lscala/collection/Iterable;
  #246 = Utf8               (Ljava/lang/Object;Ljava/lang/Object;)V
  #247 = NameAndType        #31:#246      // "<init>":(Ljava/lang/Object;Ljava/lang/Object;)V
  #248 = Methodref          #232.#247     // scala/Tuple2."<init>":(Ljava/lang/Object;Ljava/lang/Object;)V
  #249 = Methodref          #4.#32        // java/lang/Object."<init>":()V
  #250 = NameAndType        #218:#219     // $anonfun$apply$4:(Ljava/lang/String;)V
  #251 = Methodref          #2.#250       // os/SubPath$.$anonfun$apply$4:(Ljava/lang/String;)V
  #252 = Utf8               scala/runtime/BoxedUnit
  #253 = Class              #252          // scala/runtime/BoxedUnit
  #254 = Utf8               UNIT
  #255 = Utf8               Lscala/runtime/BoxedUnit;
  #256 = NameAndType        #254:#255     // UNIT:Lscala/runtime/BoxedUnit;
  #257 = Fieldref           #253.#256     // scala/runtime/BoxedUnit.UNIT:Lscala/runtime/BoxedUnit;
  #258 = Utf8               $deserializeLambda$
  #259 = Utf8               (Ljava/lang/invoke/SerializedLambda;)Ljava/lang/Object;
  #260 = Utf8               scala/runtime/LambdaDeserialize
  #261 = Class              #260          // scala/runtime/LambdaDeserialize
  #262 = Utf8               bootstrap
  #263 = Utf8               (Ljava/lang/invoke/MethodHandles$Lookup;Ljava/lang/String;Ljava/lang/invoke/MethodType;[Ljava/lang/invoke/MethodHandle;)Ljava/lang/invoke/CallSite;
  #264 = NameAndType        #262:#263     // bootstrap:(Ljava/lang/invoke/MethodHandles$Lookup;Ljava/lang/String;Ljava/lang/invoke/MethodType;[Ljava/lang/invoke/MethodHandle;)Ljava/lang/invoke/CallSite;
  #265 = Methodref          #261.#264     // scala/runtime/LambdaDeserialize.bootstrap:(Ljava/lang/invoke/MethodHandles$Lookup;Ljava/lang/String;Ljava/lang/invoke/MethodType;[Ljava/lang/invoke/MethodHandle;)Ljava/lang/invoke/CallSite;
  #266 = MethodHandle       6:#265        // REF_invokeStatic scala/runtime/LambdaDeserialize.bootstrap:(Ljava/lang/invoke/MethodHandles$Lookup;Ljava/lang/String;Ljava/lang/invoke/MethodType;[Ljava/lang/invoke/MethodHandle;)Ljava/lang/invoke/CallSite;
  #267 = Utf8               lambdaDeserialize
  #268 = NameAndType        #267:#259     // lambdaDeserialize:(Ljava/lang/invoke/SerializedLambda;)Ljava/lang/Object;
  #269 = InvokeDynamic      #2:#268       // #2:lambdaDeserialize:(Ljava/lang/invoke/SerializedLambda;)Ljava/lang/Object;
  #270 = Utf8               Signature
  #271 = Utf8               Code
  #272 = Utf8               LineNumberTable
  #273 = Utf8               StackMapTable
  #274 = Utf8               LocalVariableTable
  #275 = Utf8               MethodParameters
  #276 = Utf8               InnerClasses
  #277 = Utf8               SourceFile
  #278 = Utf8               BootstrapMethods
  #279 = Utf8               ScalaInlineInfo
  #280 = Utf8               Scala
{
  public static final os.SubPath$ MODULE$;
    descriptor: Los/SubPath$;
    flags: (0x0019) ACC_PUBLIC, ACC_STATIC, ACC_FINAL

  private static final scala.math.Ordering<os.SubPath> subPathOrdering;
    descriptor: Lscala/math/Ordering;
    flags: (0x001a) ACC_PRIVATE, ACC_STATIC, ACC_FINAL
    Signature: #26                          // Lscala/math/Ordering<Los/SubPath;>;

  private static final os.SubPath sub;
    descriptor: Los/SubPath;
    flags: (0x001a) ACC_PRIVATE, ACC_STATIC, ACC_FINAL

  public static {};
    descriptor: ()V
    flags: (0x0009) ACC_PUBLIC, ACC_STATIC
    Code:
      stack=6, locals=0, args_size=0
         0: new           #2                  // class os/SubPath$
         3: dup
         4: invokespecial #33                 // Method "<init>":()V
         7: putstatic     #35                 // Field MODULE$:Los/SubPath$;
        10: getstatic     #40                 // Field scala/package$.MODULE$:Lscala/package$;
        13: invokevirtual #44                 // Method scala/package$.Ordering:()Lscala/math/Ordering$;
        16: invokedynamic #65,  0             // InvokeDynamic #0:apply:()Lscala/Function1;
        21: getstatic     #70                 // Field scala/math/Ordering$.MODULE$:Lscala/math/Ordering$;
        24: getstatic     #73                 // Field scala/math/Ordering$Int$.MODULE$:Lscala/math/Ordering$Int$;
        27: getstatic     #76                 // Field scala/math/Ordering$Implicits$.MODULE$:Lscala/math/Ordering$Implicits$;
        30: getstatic     #79                 // Field scala/math/Ordering$String$.MODULE$:Lscala/math/Ordering$String$;
        33: invokevirtual #83                 // Method scala/math/Ordering$Implicits$.seqOrdering:(Lscala/math/Ordering;)Lscala/math/Ordering;
        36: invokevirtual #87                 // Method scala/math/Ordering$.Tuple2:(Lscala/math/Ordering;Lscala/math/Ordering;)Lscala/math/Ordering;
        39: invokevirtual #91                 // Method scala/math/Ordering$.by:(Lscala/Function1;Lscala/math/Ordering;)Lscala/math/Ordering;
        42: putstatic     #93                 // Field subPathOrdering:Lscala/math/Ordering;
        45: new           #95                 // class os/SubPath
        48: dup
        49: getstatic     #100                // Field os/Internals$.MODULE$:Los/Internals$;
        52: invokevirtual #104                // Method os/Internals$.emptyStringArray:()[Ljava/lang/String;
        55: invokespecial #107                // Method os/SubPath."<init>":([Ljava/lang/String;)V
        58: putstatic     #109                // Field sub:Los/SubPath;
        61: return
      LineNumberTable:
        line 343: 0
        line 365: 10
        line 364: 42
        line 367: 45
        line 343: 61

  public os.RelPath relativeTo0(java.lang.String[], scala.collection.immutable.IndexedSeq<java.lang.String>);
    descriptor: ([Ljava/lang/String;Lscala/collection/immutable/IndexedSeq;)Los/RelPath;
    flags: (0x0001) ACC_PUBLIC
    Code:
      stack=5, locals=8, args_size=3
         0: getstatic     #119                // Field scala/math/package$.MODULE$:Lscala/math/package$;
         3: aload_1
         4: arraylength
         5: aload_2
         6: invokeinterface #125,  1          // InterfaceMethod scala/collection/immutable/IndexedSeq.length:()I
        11: invokevirtual #129                // Method scala/math/package$.min:(II)I
        14: istore        4
        16: iconst_0
        17: istore        5
        19: iload         5
        21: iload         4
        23: if_icmpge     70
        26: aload_1
        27: iload         5
        29: aaload
        30: aload_2
        31: iload         5
        33: invokeinterface #132,  2          // InterfaceMethod scala/collection/immutable/IndexedSeq.apply:(I)Ljava/lang/Object;
        38: astore        6
        40: dup
        41: ifnonnull     53
        44: pop
        45: aload         6
        47: ifnull        61
        50: goto          70
        53: aload         6
        55: invokevirtual #136                // Method java/lang/Object.equals:(Ljava/lang/Object;)Z
        58: ifeq          70
        61: iload         5
        63: iconst_1
        64: iadd
        65: istore        5
        67: goto          19
        70: iload         5
        72: istore_3
        73: aload_2
        74: invokeinterface #125,  1          // InterfaceMethod scala/collection/immutable/IndexedSeq.length:()I
        79: iload_3
        80: isub
        81: istore        7
        83: new           #138                // class os/RelPath
        86: dup
        87: getstatic     #143                // Field scala/collection/ArrayOps$.MODULE$:Lscala/collection/ArrayOps$;
        90: getstatic     #148                // Field scala/Predef$.MODULE$:Lscala/Predef$;
        93: aload_1
        94: checkcast     #150                // class "[Ljava/lang/Object;"
        97: invokevirtual #154                // Method scala/Predef$.refArrayOps:([Ljava/lang/Object;)Ljava/lang/Object;
       100: iload_3
       101: invokevirtual #158                // Method scala/collection/ArrayOps$.drop$extension:(Ljava/lang/Object;I)Ljava/lang/Object;
       104: checkcast     #160                // class "[Ljava/lang/String;"
       107: iload         7
       109: invokespecial #163                // Method os/RelPath."<init>":([Ljava/lang/String;I)V
       112: areturn
      StackMapTable: number_of_entries = 4
        frame_type = 254 /* append */
          offset_delta = 19
          locals = [ top, int, int ]
        frame_type = 255 /* full_frame */
          offset_delta = 33
          locals = [ class os/SubPath$, class "[Ljava/lang/String;", class scala/collection/immutable/IndexedSeq, top, int, int, class java/lang/Object ]
          stack = [ class java/lang/String ]
        frame_type = 7 /* same */
        frame_type = 250 /* chop */
          offset_delta = 8
      LineNumberTable:
        line 347: 0
        line 348: 16
        line 349: 19
        line 350: 70
        line 352: 73
        line 354: 83
      LocalVariableTable:
        Start  Length  Slot  Name   Signature
           16      56     4 maxSize   I
           19      53     5     i   I
           73      39     3 commonPrefix   I
           83      29     7 newUps   I
            0     113     0  this   Los/SubPath$;
            0     113     1 segments0   [Ljava/lang/String;
            0     113     2 segments   Lscala/collection/immutable/IndexedSeq;
    Signature: #112                         // ([Ljava/lang/String;Lscala/collection/immutable/IndexedSeq<Ljava/lang/String;>;)Los/RelPath;
    MethodParameters:
      Name                           Flags
      segments0                      final
      segments                       final

  public <T extends java.lang.Object> os.SubPath apply(T, os.PathConvertible<T>);
    descriptor: (Ljava/lang/Object;Los/PathConvertible;)Los/SubPath;
    flags: (0x0001) ACC_PUBLIC
    Code:
      stack=3, locals=3, args_size=3
         0: getstatic     #181                // Field os/RelPath$.MODULE$:Los/RelPath$;
         3: aload_1
         4: aload_2
         5: invokevirtual #184                // Method os/RelPath$.apply:(Ljava/lang/Object;Los/PathConvertible;)Los/RelPath;
         8: invokevirtual #188                // Method os/RelPath.asSubPath:()Los/SubPath;
        11: areturn
      LineNumberTable:
        line 356: 0
      LocalVariableTable:
        Start  Length  Slot  Name   Signature
            0      12     0  this   Los/SubPath$;
            0      12     1    f0   Ljava/lang/Object;
            0      12     2 evidence$3   Los/PathConvertible;
    Signature: #174                         // <T:Ljava/lang/Object;>(TT;Los/PathConvertible<TT;>;)Los/SubPath;
    MethodParameters:
      Name                           Flags
      f0                             final
      evidence$3                     final

  public os.SubPath apply(scala.collection.immutable.IndexedSeq<java.lang.String>);
    descriptor: (Lscala/collection/immutable/IndexedSeq;)Los/SubPath;
    flags: (0x0001) ACC_PUBLIC
    Code:
      stack=5, locals=2, args_size=2
         0: aload_1
         1: invokedynamic #199,  0            // InvokeDynamic #1:apply:()Lscala/Function1;
         6: invokeinterface #203,  2          // InterfaceMethod scala/collection/immutable/IndexedSeq.foreach:(Lscala/Function1;)V
        11: new           #95                 // class os/SubPath
        14: dup
        15: aload_1
        16: getstatic     #208                // Field scala/reflect/ClassTag$.MODULE$:Lscala/reflect/ClassTag$;
        19: ldc           #172                // class java/lang/String
        21: invokevirtual #211                // Method scala/reflect/ClassTag$.apply:(Ljava/lang/Class;)Lscala/reflect/ClassTag;
        24: invokeinterface #215,  2          // InterfaceMethod scala/collection/immutable/IndexedSeq.toArray:(Lscala/reflect/ClassTag;)Ljava/lang/Object;
        29: checkcast     #160                // class "[Ljava/lang/String;"
        32: invokespecial #107                // Method os/SubPath."<init>":([Ljava/lang/String;)V
        35: areturn
      LineNumberTable:
        line 359: 0
        line 360: 11
      LocalVariableTable:
        Start  Length  Slot  Name   Signature
            0      36     0  this   Los/SubPath$;
            0      36     1 segments0   Lscala/collection/immutable/IndexedSeq;
    Signature: #192                         // (Lscala/collection/immutable/IndexedSeq<Ljava/lang/String;>;)Los/SubPath;
    MethodParameters:
      Name                           Flags
      segments0                      final

  public scala.math.Ordering<os.SubPath> subPathOrdering();
    descriptor: ()Lscala/math/Ordering;
    flags: (0x0001) ACC_PUBLIC
    Code:
      stack=1, locals=1, args_size=1
         0: getstatic     #93                 // Field subPathOrdering:Lscala/math/Ordering;
         3: areturn
      LineNumberTable:
        line 364: 0
      LocalVariableTable:
        Start  Length  Slot  Name   Signature
            0       4     0  this   Los/SubPath$;
    Signature: #217                         // ()Lscala/math/Ordering<Los/SubPath;>;

  public os.SubPath sub();
    descriptor: ()Los/SubPath;
    flags: (0x0001) ACC_PUBLIC
    Code:
      stack=1, locals=1, args_size=1
         0: getstatic     #109                // Field sub:Los/SubPath;
         3: areturn
      LineNumberTable:
        line 367: 0
      LocalVariableTable:
        Start  Length  Slot  Name   Signature
            0       4     0  this   Los/SubPath$;

  public static final void $anonfun$apply$4(java.lang.String);
    descriptor: (Ljava/lang/String;)V
    flags: (0x1019) ACC_PUBLIC, ACC_STATIC, ACC_FINAL, ACC_SYNTHETIC
    Code:
      stack=2, locals=1, args_size=1
         0: getstatic     #225                // Field os/BasePath$.MODULE$:Los/BasePath$;
         3: aload_0
         4: invokevirtual #228                // Method os/BasePath$.checkSegment:(Ljava/lang/String;)V
         7: return
      LineNumberTable:
        line 359: 0
      LocalVariableTable:
        Start  Length  Slot  Name   Signature
            0       8     0     s   Ljava/lang/String;
    MethodParameters:
      Name                           Flags
      s                              final

  public static final scala.Tuple2 $anonfun$subPathOrdering$1(os.SubPath);
    descriptor: (Los/SubPath;)Lscala/Tuple2;
    flags: (0x1019) ACC_PUBLIC, ACC_STATIC, ACC_FINAL, ACC_SYNTHETIC
    Code:
      stack=4, locals=1, args_size=1
         0: new           #232                // class scala/Tuple2
         3: dup
         4: aload_0
         5: invokevirtual #235                // Method os/SubPath.segments:()Lscala/collection/immutable/IndexedSeq;
         8: invokeinterface #125,  1          // InterfaceMethod scala/collection/immutable/IndexedSeq.length:()I
        13: invokestatic  #241                // Method scala/runtime/BoxesRunTime.boxToInteger:(I)Ljava/lang/Integer;
        16: aload_0
        17: invokevirtual #235                // Method os/SubPath.segments:()Lscala/collection/immutable/IndexedSeq;
        20: invokeinterface #245,  1          // InterfaceMethod scala/collection/immutable/IndexedSeq.toIterable:()Lscala/collection/Iterable;
        25: invokespecial #248                // Method scala/Tuple2."<init>":(Ljava/lang/Object;Ljava/lang/Object;)V
        28: areturn
      LineNumberTable:
        line 365: 0
      LocalVariableTable:
        Start  Length  Slot  Name   Signature
            0      29     0    rp   Los/SubPath;
    MethodParameters:
      Name                           Flags
      rp                             final

  private os.SubPath$();
    descriptor: ()V
    flags: (0x0002) ACC_PRIVATE
    Code:
      stack=1, locals=1, args_size=1
         0: aload_0
         1: invokespecial #249                // Method java/lang/Object."<init>":()V
         4: return
      LineNumberTable:
        line 370: 0
        line 343: 4
      LocalVariableTable:
        Start  Length  Slot  Name   Signature
            0       5     0  this   Los/SubPath$;

  public static final java.lang.Object $anonfun$apply$4$adapted(java.lang.String);
    descriptor: (Ljava/lang/String;)Ljava/lang/Object;
    flags: (0x1019) ACC_PUBLIC, ACC_STATIC, ACC_FINAL, ACC_SYNTHETIC
    Code:
      stack=1, locals=1, args_size=1
         0: aload_0
         1: invokestatic  #251                // Method $anonfun$apply$4:(Ljava/lang/String;)V
         4: getstatic     #257                // Field scala/runtime/BoxedUnit.UNIT:Lscala/runtime/BoxedUnit;
         7: areturn
      LineNumberTable:
        line 359: 0
      LocalVariableTable:
        Start  Length  Slot  Name   Signature
            0       8     0     s   Ljava/lang/String;
    MethodParameters:
      Name                           Flags
      s                              final

  private static java.lang.Object $deserializeLambda$(java.lang.invoke.SerializedLambda);
    descriptor: (Ljava/lang/invoke/SerializedLambda;)Ljava/lang/Object;
    flags: (0x100a) ACC_PRIVATE, ACC_STATIC, ACC_SYNTHETIC
    Code:
      stack=1, locals=1, args_size=1
         0: aload_0
         1: invokedynamic #269,  0            // InvokeDynamic #2:lambdaDeserialize:(Ljava/lang/invoke/SerializedLambda;)Ljava/lang/Object;
         6: areturn
}
InnerClasses:
  public static final #10= #7 of #9;      // Lookup=class java/lang/invoke/MethodHandles$Lookup of class java/lang/invoke/MethodHandles
  public static #15= #12 of #14;          // Implicits$=class scala/math/Ordering$Implicits$ of class scala/math/Ordering
  public static #18= #17 of #14;          // Int$=class scala/math/Ordering$Int$ of class scala/math/Ordering
  public static #21= #20 of #14;          // String$=class scala/math/Ordering$String$ of class scala/math/Ordering
SourceFile: "Path.scala"
BootstrapMethods:
  0: #61 REF_invokeStatic java/lang/invoke/LambdaMetafactory.altMetafactory:(Ljava/lang/invoke/MethodHandles$Lookup;Ljava/lang/String;Ljava/lang/invoke/MethodType;[Ljava/lang/Object;)Ljava/lang/invoke/CallSite;
    Method arguments:
      #46 (Ljava/lang/Object;)Ljava/lang/Object;
      #51 REF_invokeStatic os/SubPath$.$anonfun$subPathOrdering$1:(Los/SubPath;)Lscala/Tuple2;
      #52 (Los/SubPath;)Lscala/Tuple2;
      #53 5
      #54 1
      #52 (Los/SubPath;)Lscala/Tuple2;
  1: #61 REF_invokeStatic java/lang/invoke/LambdaMetafactory.altMetafactory:(Ljava/lang/invoke/MethodHandles$Lookup;Ljava/lang/String;Ljava/lang/invoke/MethodType;[Ljava/lang/Object;)Ljava/lang/invoke/CallSite;
    Method arguments:
      #46 (Ljava/lang/Object;)Ljava/lang/Object;
      #197 REF_invokeStatic os/SubPath$.$anonfun$apply$4$adapted:(Ljava/lang/String;)Ljava/lang/Object;
      #198 (Ljava/lang/String;)Ljava/lang/Object;
      #53 5
      #54 1
      #198 (Ljava/lang/String;)Ljava/lang/Object;
  2: #266 REF_invokeStatic scala/runtime/LambdaDeserialize.bootstrap:(Ljava/lang/invoke/MethodHandles$Lookup;Ljava/lang/String;Ljava/lang/invoke/MethodType;[Ljava/lang/invoke/MethodHandle;)Ljava/lang/invoke/CallSite;
    Method arguments:
      #197 REF_invokeStatic os/SubPath$.$anonfun$apply$4$adapted:(Ljava/lang/String;)Ljava/lang/Object;
      #51 REF_invokeStatic os/SubPath$.$anonfun$subPathOrdering$1:(Los/SubPath;)Lscala/Tuple2;
  ScalaInlineInfo: length = 0x31 (unknown attribute)
   01 01 00 09 00 DA 00 DB 01 00 C1 00 C2 01 00 2F
   00 30 01 00 1F 00 1E 01 00 3E 00 AD 01 00 3E 00
   BF 01 00 6E 00 6F 01 00 1B 00 BA 01 00 18 00 D8
   01
  Scala: length = 0x0 (unknown attribute)

