Classfile /Users/mw/Projects/slang-braindump/.jar/jar8/assemble/slang-braindump/assemble/content/os/SubprocessException.class
  Last modified May 29, 2022; size 4709 bytes
  SHA-256 checksum 1c9986d86fe63d1676e846ec7ab56bd47cf1233ac91e83b440816a83a8bf186c
  Compiled from "Model.scala"
public class os.SubprocessException extends java.lang.Exception implements scala.Product
  minor version: 0
  major version: 52
  flags: (0x0021) ACC_PUBLIC, ACC_SUPER
  this_class: #2                          // os/SubprocessException
  super_class: #4                         // java/lang/Exception
  interfaces: 1, fields: 1, methods: 17, attributes: 4
Constant pool:
    #1 = Utf8               os/SubprocessException
    #2 = Class              #1            // os/SubprocessException
    #3 = Utf8               java/lang/Exception
    #4 = Class              #3            // java/lang/Exception
    #5 = Utf8               scala/Product
    #6 = Class              #5            // scala/Product
    #7 = Utf8               Model.scala
    #8 = Utf8               Lscala/reflect/ScalaSignature;
    #9 = Utf8               bytes
   #10 = Utf8               \u0006\u0005\u0005-b\u0001B\u000b\u0017\u0001fA\u0001b\f\u0001\u0003\u0016\u0004%\t\u0001\r\u0005\tk\u0001\u0011\t\u0012)A\u0005c!)a\u0007\u0001C\u0001o!9!\bAA\u0001\n\u0003Y\u0004bB\u001f\u0001#\u0003%\tA\u0010\u0005\b\u0013\u0002\t\t\u0011\"\u0011K\u0011\u001d\u0019\u0006!!A\u0005\u0002QCq\u0001\u0017\u0001\u0002\u0002\u0013\u0005\u0011\fC\u0004`\u0001\u0005\u0005I\u0011\t1\t\u000f\u001d\u0004\u0011\u0011!C\u0001Q\"9Q\u000eAA\u0001\n\u0003r\u0007b\u00029\u0001\u0003\u0003%\t%\u001d\u0005\be\u0002\t\t\u0011\"\u0011t\u000f\u001d)h#!A\t\u0002Y4q!\u0006\f\u0002\u0002#\u0005q\u000f\u0003\u00047\u001f\u0011\u0005\u0011q\u0001\u0005\n\u0003\u0013y\u0011\u0011!C#\u0003\u0017A\u0011\"!\u0004\u0010\u0003\u0003%\t)a\u0004\t\u0013\u0005Mq\"!A\u0005\u0002\u0006U\u0001\"CA\u0011\u001f\u0005\u0005I\u0011BA\u0012\u0005M\u0019VO\u00199s_\u000e,7o]#yG\u0016\u0004H/[8o\u0015\u00059\u0012AA8t\u0007\u0001\u0019B\u0001\u0001\u000e)YA\u00111$\n\b\u00039\tr!!\b\u0011\u000e\u0003yQ!a\b\r\u0002\rq\u0012xn\u001c;?\u0013\u0005\t\u0013!B:dC2\f\u0017BA\u0012%\u0003\u001d\u0001\u0018mY6bO\u0016T\u0011!I\u0005\u0003M\u001d\u0012\u0011\"\u0012=dKB$\u0018n\u001c8\u000b\u0005\r\"\u0003CA\u0015+\u001b\u0005!\u0013BA\u0016%\u0005\u001d\u0001&o\u001c3vGR\u0004\"aG\u0017\n\u00059:#\u0001D*fe&\fG.\u001b>bE2,\u0017A\u0002:fgVdG/F\u00012!\t\u00114\'D\u0001\u0017\u0013\t!dCA\u0007D_6l\u0017M\u001c3SKN,H\u000e^\u0001\be\u0016\u001cX\u000f\u001c;!\u0003\u0019a\u0014N\\5u}Q\u0011\u0001(\u000f\t\u0003e\u0001AQaL\u0002A\u0002E\nAaY8qsR\u0011\u0001\b\u0010\u0005\b_\u0011\u0001\n\u00111\u00012\u00039\u0019w\u000e]=%I\u00164\u0017-\u001e7uIE*\u0012a\u0010\u0016\u0003c\u0001[\u0013!\u0011\t\u0003\u0005\u001ek\u0011a\u0011\u0006\u0003\t\u0016\u000b\u0011\"\u001e8dQ\u0016\u001c7.\u001a3\u000b\u0005\u0019#\u0013AC1o]>$\u0018\r^5p]&\u0011\u0001j\u0011\u0002\u0012k:\u001c\u0007.Z2lK\u00124\u0016M]5b]\u000e,\u0017!\u00049s_\u0012,8\r\u001e)sK\u001aL\u00070F\u0001L!\ta\u0015+D\u0001N\u0015\tqu*\u0001\u0003mC:<\'\"\u0001)\u0002\t)\fg/Y\u0005\u0003%6\u0013aa\u0015;sS:<\u0017\u0001\u00049s_\u0012,8\r^!sSRLX#A+\u0011\u0005%2\u0016BA,%\u0005\rIe\u000e^\u0001\u000faJ|G-^2u\u000b2,W.\u001a8u)\tQV\f\u0005\u0002*7&\u0011A\f\n\u0002\u0004\u0003:L\bb\u00020\t\u0003\u0003\u0005\r!V\u0001\u0004q\u0012\n\u0014a\u00049s_\u0012,8\r^%uKJ\fGo\u001c:\u0016\u0003\u0005\u00042AY3[\u001b\u0005\u0019\'B\u00013%\u0003)\u0019w\u000e\u001c7fGRLwN\\\u0005\u0003M\u000e\u0014\u0001\"\u0013;fe\u0006$xN]\u0001\tG\u0006tW)];bYR\u0011\u0011\u000e\u001c\t\u0003S)L!a\u001b\u0013\u0003\u000f\t{w\u000e\\3b]\"9aLCA\u0001\u0002\u0004Q\u0016A\u00059s_\u0012,8\r^#mK6,g\u000e\u001e(b[\u0016$\"aS8\t\u000fy[\u0011\u0011!a\u0001+\u0006A\u0001.Y:i\u0007>$W\rF\u0001V\u0003\u0019)\u0017/^1mgR\u0011\u0011\u000e\u001e\u0005\b=6\t\t\u00111\u0001[\u0003M\u0019VO\u00199s_\u000e,7o]#yG\u0016\u0004H/[8o!\t\u0011tbE\u0002\u0010qz\u0004B!\u001f?2q5\t!P\u0003\u0002|I\u00059!/\u001e8uS6,\u0017BA?{\u0005E\t%m\u001d;sC\u000e$h)\u001e8di&|g.\r\t\u0004\u007f\u0006\u0015QBAA\u0001\u0015\r\t\u0019aT\u0001\u0003S>L1ALA\u0001)\u00051\u0018\u0001\u0003;p\'R\u0014\u0018N\\4\u0015\u0003-\u000bQ!\u00199qYf$2\u0001OA\t\u0011\u0015y#\u00031\u00012\u0003\u001d)h.\u00199qYf$B!a\u0006\u0002\u001eA!\u0011&!\u00072\u0013\r\tY\u0002\n\u0002\u0007\u001fB$\u0018n\u001c8\t\u0011\u0005}1#!AA\u0002a\n1\u0001\u001f\u00131\u000319(/\u001b;f%\u0016\u0004H.Y2f)\t\t)\u0003E\u0002M\u0003OI1!!\u000bN\u0005\u0019y%M[3di\u0002
   #11 = Utf8               result
   #12 = Utf8               Los/CommandResult;
   #13 = Utf8               unapply
   #14 = Utf8               (Los/SubprocessException;)Lscala/Option;
   #15 = Utf8               (Los/SubprocessException;)Lscala/Option<Los/CommandResult;>;
   #16 = Utf8               x$0
   #17 = Utf8               os/SubprocessException$
   #18 = Class              #17           // os/SubprocessException$
   #19 = Utf8               MODULE$
   #20 = Utf8               Los/SubprocessException$;
   #21 = NameAndType        #19:#20       // MODULE$:Los/SubprocessException$;
   #22 = Fieldref           #18.#21       // os/SubprocessException$.MODULE$:Los/SubprocessException$;
   #23 = NameAndType        #13:#14       // unapply:(Los/SubprocessException;)Lscala/Option;
   #24 = Methodref          #18.#23       // os/SubprocessException$.unapply:(Los/SubprocessException;)Lscala/Option;
   #25 = Utf8               apply
   #26 = Utf8               (Los/CommandResult;)Los/SubprocessException;
   #27 = NameAndType        #25:#26       // apply:(Los/CommandResult;)Los/SubprocessException;
   #28 = Methodref          #18.#27       // os/SubprocessException$.apply:(Los/CommandResult;)Los/SubprocessException;
   #29 = Utf8               andThen
   #30 = Utf8               (Lscala/Function1;)Lscala/Function1;
   #31 = Utf8               <A:Ljava/lang/Object;>(Lscala/Function1<Los/SubprocessException;TA;>;)Lscala/Function1<Los/CommandResult;TA;>;
   #32 = Utf8               g
   #33 = NameAndType        #29:#30       // andThen:(Lscala/Function1;)Lscala/Function1;
   #34 = Methodref          #18.#33       // os/SubprocessException$.andThen:(Lscala/Function1;)Lscala/Function1;
   #35 = Utf8               compose
   #36 = Utf8               <A:Ljava/lang/Object;>(Lscala/Function1<TA;Los/CommandResult;>;)Lscala/Function1<TA;Los/SubprocessException;>;
   #37 = NameAndType        #35:#30       // compose:(Lscala/Function1;)Lscala/Function1;
   #38 = Methodref          #18.#37       // os/SubprocessException$.compose:(Lscala/Function1;)Lscala/Function1;
   #39 = Utf8               productElementNames
   #40 = Utf8               ()Lscala/collection/Iterator;
   #41 = Utf8               ()Lscala/collection/Iterator<Ljava/lang/String;>;
   #42 = Utf8               productElementNames$
   #43 = Utf8               (Lscala/Product;)Lscala/collection/Iterator;
   #44 = NameAndType        #42:#43       // productElementNames$:(Lscala/Product;)Lscala/collection/Iterator;
   #45 = InterfaceMethodref #6.#44        // scala/Product.productElementNames$:(Lscala/Product;)Lscala/collection/Iterator;
   #46 = Utf8               this
   #47 = Utf8               Los/SubprocessException;
   #48 = Utf8               ()Los/CommandResult;
   #49 = NameAndType        #11:#12       // result:Los/CommandResult;
   #50 = Fieldref           #2.#49        // os/SubprocessException.result:Los/CommandResult;
   #51 = Utf8               copy
   #52 = Utf8               <init>
   #53 = Utf8               (Los/CommandResult;)V
   #54 = NameAndType        #52:#53       // "<init>":(Los/CommandResult;)V
   #55 = Methodref          #2.#54        // os/SubprocessException."<init>":(Los/CommandResult;)V
   #56 = Utf8               copy$default$1
   #57 = NameAndType        #11:#48       // result:()Los/CommandResult;
   #58 = Methodref          #2.#57        // os/SubprocessException.result:()Los/CommandResult;
   #59 = Utf8               productPrefix
   #60 = Utf8               ()Ljava/lang/String;
   #61 = Utf8               SubprocessException
   #62 = String             #61           // SubprocessException
   #63 = Utf8               productArity
   #64 = Utf8               ()I
   #65 = Utf8               productElement
   #66 = Utf8               (I)Ljava/lang/Object;
   #67 = Utf8               x$1
   #68 = Utf8               scala/runtime/Statics
   #69 = Class              #68           // scala/runtime/Statics
   #70 = Utf8               ioobe
   #71 = NameAndType        #70:#66       // ioobe:(I)Ljava/lang/Object;
   #72 = Methodref          #69.#71       // scala/runtime/Statics.ioobe:(I)Ljava/lang/Object;
   #73 = Utf8               I
   #74 = Utf8               java/lang/Object
   #75 = Class              #74           // java/lang/Object
   #76 = Utf8               productIterator
   #77 = Utf8               ()Lscala/collection/Iterator<Ljava/lang/Object;>;
   #78 = Utf8               scala/runtime/ScalaRunTime$
   #79 = Class              #78           // scala/runtime/ScalaRunTime$
   #80 = Utf8               Lscala/runtime/ScalaRunTime$;
   #81 = NameAndType        #19:#80       // MODULE$:Lscala/runtime/ScalaRunTime$;
   #82 = Fieldref           #79.#81       // scala/runtime/ScalaRunTime$.MODULE$:Lscala/runtime/ScalaRunTime$;
   #83 = Utf8               typedProductIterator
   #84 = NameAndType        #83:#43       // typedProductIterator:(Lscala/Product;)Lscala/collection/Iterator;
   #85 = Methodref          #79.#84       // scala/runtime/ScalaRunTime$.typedProductIterator:(Lscala/Product;)Lscala/collection/Iterator;
   #86 = Utf8               canEqual
   #87 = Utf8               (Ljava/lang/Object;)Z
   #88 = Utf8               Ljava/lang/Object;
   #89 = Utf8               productElementName
   #90 = Utf8               (I)Ljava/lang/String;
   #91 = String             #11           // result
   #92 = Utf8               java/lang/String
   #93 = Class              #92           // java/lang/String
   #94 = Utf8               hashCode
   #95 = Utf8               _hashCode
   #96 = Utf8               (Lscala/Product;)I
   #97 = NameAndType        #95:#96       // _hashCode:(Lscala/Product;)I
   #98 = Methodref          #79.#97       // scala/runtime/ScalaRunTime$._hashCode:(Lscala/Product;)I
   #99 = Utf8               equals
  #100 = NameAndType        #99:#87       // equals:(Ljava/lang/Object;)Z
  #101 = Methodref          #75.#100      // java/lang/Object.equals:(Ljava/lang/Object;)Z
  #102 = NameAndType        #86:#87       // canEqual:(Ljava/lang/Object;)Z
  #103 = Methodref          #2.#102       // os/SubprocessException.canEqual:(Ljava/lang/Object;)Z
  #104 = Utf8               os/CommandResult
  #105 = Class              #104          // os/CommandResult
  #106 = Utf8               toString
  #107 = NameAndType        #106:#60      // toString:()Ljava/lang/String;
  #108 = Methodref          #105.#107     // os/CommandResult.toString:()Ljava/lang/String;
  #109 = Utf8               (Ljava/lang/String;)V
  #110 = NameAndType        #52:#109      // "<init>":(Ljava/lang/String;)V
  #111 = Methodref          #4.#110       // java/lang/Exception."<init>":(Ljava/lang/String;)V
  #112 = Utf8               $init$
  #113 = Utf8               (Lscala/Product;)V
  #114 = NameAndType        #112:#113     // $init$:(Lscala/Product;)V
  #115 = InterfaceMethodref #6.#114       // scala/Product.$init$:(Lscala/Product;)V
  #116 = Utf8               Code
  #117 = Utf8               Signature
  #118 = Utf8               MethodParameters
  #119 = Utf8               LineNumberTable
  #120 = Utf8               LocalVariableTable
  #121 = Utf8               StackMapTable
  #122 = Utf8               SourceFile
  #123 = Utf8               RuntimeVisibleAnnotations
  #124 = Utf8               ScalaInlineInfo
  #125 = Utf8               ScalaSig
{
  private final os.CommandResult result;
    descriptor: Los/CommandResult;
    flags: (0x0012) ACC_PRIVATE, ACC_FINAL

  public static scala.Option<os.CommandResult> unapply(os.SubprocessException);
    descriptor: (Los/SubprocessException;)Lscala/Option;
    flags: (0x0009) ACC_PUBLIC, ACC_STATIC
    Code:
      stack=2, locals=1, args_size=1
         0: getstatic     #22                 // Field os/SubprocessException$.MODULE$:Los/SubprocessException$;
         3: aload_0
         4: invokevirtual #24                 // Method os/SubprocessException$.unapply:(Los/SubprocessException;)Lscala/Option;
         7: areturn
    Signature: #15                          // (Los/SubprocessException;)Lscala/Option<Los/CommandResult;>;
    MethodParameters:
      Name                           Flags
      x$0                            final

  public static os.SubprocessException apply(os.CommandResult);
    descriptor: (Los/CommandResult;)Los/SubprocessException;
    flags: (0x0009) ACC_PUBLIC, ACC_STATIC
    Code:
      stack=2, locals=1, args_size=1
         0: getstatic     #22                 // Field os/SubprocessException$.MODULE$:Los/SubprocessException$;
         3: aload_0
         4: invokevirtual #28                 // Method os/SubprocessException$.apply:(Los/CommandResult;)Los/SubprocessException;
         7: areturn
    MethodParameters:
      Name                           Flags
      result                         final

  public static <A extends java.lang.Object> scala.Function1<os.CommandResult, A> andThen(scala.Function1<os.SubprocessException, A>);
    descriptor: (Lscala/Function1;)Lscala/Function1;
    flags: (0x0009) ACC_PUBLIC, ACC_STATIC
    Code:
      stack=2, locals=1, args_size=1
         0: getstatic     #22                 // Field os/SubprocessException$.MODULE$:Los/SubprocessException$;
         3: aload_0
         4: invokevirtual #34                 // Method os/SubprocessException$.andThen:(Lscala/Function1;)Lscala/Function1;
         7: areturn
    Signature: #31                          // <A:Ljava/lang/Object;>(Lscala/Function1<Los/SubprocessException;TA;>;)Lscala/Function1<Los/CommandResult;TA;>;
    MethodParameters:
      Name                           Flags
      g                              final

  public static <A extends java.lang.Object> scala.Function1<A, os.SubprocessException> compose(scala.Function1<A, os.CommandResult>);
    descriptor: (Lscala/Function1;)Lscala/Function1;
    flags: (0x0009) ACC_PUBLIC, ACC_STATIC
    Code:
      stack=2, locals=1, args_size=1
         0: getstatic     #22                 // Field os/SubprocessException$.MODULE$:Los/SubprocessException$;
         3: aload_0
         4: invokevirtual #38                 // Method os/SubprocessException$.compose:(Lscala/Function1;)Lscala/Function1;
         7: areturn
    Signature: #36                          // <A:Ljava/lang/Object;>(Lscala/Function1<TA;Los/CommandResult;>;)Lscala/Function1<TA;Los/SubprocessException;>;
    MethodParameters:
      Name                           Flags
      g                              final

  public scala.collection.Iterator<java.lang.String> productElementNames();
    descriptor: ()Lscala/collection/Iterator;
    flags: (0x0001) ACC_PUBLIC
    Code:
      stack=1, locals=1, args_size=1
         0: aload_0
         1: invokestatic  #45                 // InterfaceMethod scala/Product.productElementNames$:(Lscala/Product;)Lscala/collection/Iterator;
         4: areturn
      LineNumberTable:
        line 203: 0
      LocalVariableTable:
        Start  Length  Slot  Name   Signature
            0       5     0  this   Los/SubprocessException;
    Signature: #41                          // ()Lscala/collection/Iterator<Ljava/lang/String;>;

  public os.CommandResult result();
    descriptor: ()Los/CommandResult;
    flags: (0x0001) ACC_PUBLIC
    Code:
      stack=1, locals=1, args_size=1
         0: aload_0
         1: getfield      #50                 // Field result:Los/CommandResult;
         4: areturn
      LineNumberTable:
        line 203: 0
      LocalVariableTable:
        Start  Length  Slot  Name   Signature
            0       5     0  this   Los/SubprocessException;

  public os.SubprocessException copy(os.CommandResult);
    descriptor: (Los/CommandResult;)Los/SubprocessException;
    flags: (0x0001) ACC_PUBLIC
    Code:
      stack=3, locals=2, args_size=2
         0: new           #2                  // class os/SubprocessException
         3: dup
         4: aload_1
         5: invokespecial #55                 // Method "<init>":(Los/CommandResult;)V
         8: areturn
      LineNumberTable:
        line 203: 0
      LocalVariableTable:
        Start  Length  Slot  Name   Signature
            0       9     0  this   Los/SubprocessException;
            0       9     1 result   Los/CommandResult;
    MethodParameters:
      Name                           Flags
      result                         final

  public os.CommandResult copy$default$1();
    descriptor: ()Los/CommandResult;
    flags: (0x0001) ACC_PUBLIC
    Code:
      stack=1, locals=1, args_size=1
         0: aload_0
         1: invokevirtual #58                 // Method result:()Los/CommandResult;
         4: areturn
      LineNumberTable:
        line 203: 0
      LocalVariableTable:
        Start  Length  Slot  Name   Signature
            0       5     0  this   Los/SubprocessException;

  public java.lang.String productPrefix();
    descriptor: ()Ljava/lang/String;
    flags: (0x0001) ACC_PUBLIC
    Code:
      stack=1, locals=1, args_size=1
         0: ldc           #62                 // String SubprocessException
         2: areturn
      LineNumberTable:
        line 203: 0
      LocalVariableTable:
        Start  Length  Slot  Name   Signature
            0       3     0  this   Los/SubprocessException;

  public int productArity();
    descriptor: ()I
    flags: (0x0001) ACC_PUBLIC
    Code:
      stack=1, locals=1, args_size=1
         0: iconst_1
         1: ireturn
      LineNumberTable:
        line 203: 0
      LocalVariableTable:
        Start  Length  Slot  Name   Signature
            0       2     0  this   Los/SubprocessException;

  public java.lang.Object productElement(int);
    descriptor: (I)Ljava/lang/Object;
    flags: (0x0001) ACC_PUBLIC
    Code:
      stack=1, locals=3, args_size=2
         0: iload_1
         1: istore_2
         2: iload_2
         3: tableswitch   { // 0 to 0
                       0: 20
                 default: 27
            }
        20: aload_0
        21: invokevirtual #58                 // Method result:()Los/CommandResult;
        24: goto          34
        27: iload_1
        28: invokestatic  #72                 // Method scala/runtime/Statics.ioobe:(I)Ljava/lang/Object;
        31: goto          34
        34: areturn
      StackMapTable: number_of_entries = 3
        frame_type = 252 /* append */
          offset_delta = 20
          locals = [ int ]
        frame_type = 6 /* same */
        frame_type = 70 /* same_locals_1_stack_item */
          stack = [ class java/lang/Object ]
      LineNumberTable:
        line 203: 0
      LocalVariableTable:
        Start  Length  Slot  Name   Signature
            0      35     0  this   Los/SubprocessException;
            0      35     1   x$1   I
    MethodParameters:
      Name                           Flags
      x$1                            final

  public scala.collection.Iterator<java.lang.Object> productIterator();
    descriptor: ()Lscala/collection/Iterator;
    flags: (0x0001) ACC_PUBLIC
    Code:
      stack=2, locals=1, args_size=1
         0: getstatic     #82                 // Field scala/runtime/ScalaRunTime$.MODULE$:Lscala/runtime/ScalaRunTime$;
         3: aload_0
         4: invokevirtual #85                 // Method scala/runtime/ScalaRunTime$.typedProductIterator:(Lscala/Product;)Lscala/collection/Iterator;
         7: areturn
      LineNumberTable:
        line 203: 0
      LocalVariableTable:
        Start  Length  Slot  Name   Signature
            0       8     0  this   Los/SubprocessException;
    Signature: #77                          // ()Lscala/collection/Iterator<Ljava/lang/Object;>;

  public boolean canEqual(java.lang.Object);
    descriptor: (Ljava/lang/Object;)Z
    flags: (0x0001) ACC_PUBLIC
    Code:
      stack=1, locals=2, args_size=2
         0: aload_1
         1: instanceof    #2                  // class os/SubprocessException
         4: ireturn
      LineNumberTable:
        line 203: 0
      LocalVariableTable:
        Start  Length  Slot  Name   Signature
            0       5     0  this   Los/SubprocessException;
            0       5     1   x$1   Ljava/lang/Object;
    MethodParameters:
      Name                           Flags
      x$1                            final

  public java.lang.String productElementName(int);
    descriptor: (I)Ljava/lang/String;
    flags: (0x0001) ACC_PUBLIC
    Code:
      stack=1, locals=3, args_size=2
         0: iload_1
         1: istore_2
         2: iload_2
         3: tableswitch   { // 0 to 0
                       0: 20
                 default: 25
            }
        20: ldc           #91                 // String result
        22: goto          35
        25: iload_1
        26: invokestatic  #72                 // Method scala/runtime/Statics.ioobe:(I)Ljava/lang/Object;
        29: checkcast     #93                 // class java/lang/String
        32: goto          35
        35: areturn
      StackMapTable: number_of_entries = 3
        frame_type = 252 /* append */
          offset_delta = 20
          locals = [ int ]
        frame_type = 4 /* same */
        frame_type = 73 /* same_locals_1_stack_item */
          stack = [ class java/lang/String ]
      LineNumberTable:
        line 203: 0
      LocalVariableTable:
        Start  Length  Slot  Name   Signature
            0      36     0  this   Los/SubprocessException;
            0      36     1   x$1   I
    MethodParameters:
      Name                           Flags
      x$1                            final

  public int hashCode();
    descriptor: ()I
    flags: (0x0001) ACC_PUBLIC
    Code:
      stack=2, locals=1, args_size=1
         0: getstatic     #82                 // Field scala/runtime/ScalaRunTime$.MODULE$:Lscala/runtime/ScalaRunTime$;
         3: aload_0
         4: invokevirtual #98                 // Method scala/runtime/ScalaRunTime$._hashCode:(Lscala/Product;)I
         7: ireturn
      LineNumberTable:
        line 203: 0
      LocalVariableTable:
        Start  Length  Slot  Name   Signature
            0       8     0  this   Los/SubprocessException;

  public boolean equals(java.lang.Object);
    descriptor: (Ljava/lang/Object;)Z
    flags: (0x0001) ACC_PUBLIC
    Code:
      stack=2, locals=6, args_size=2
         0: aload_0
         1: aload_1
         2: if_acmpeq     86
         5: aload_1
         6: astore_3
         7: aload_3
         8: instanceof    #2                  // class os/SubprocessException
        11: ifeq          19
        14: iconst_1
        15: istore_2
        16: goto          27
        19: goto          22
        22: iconst_0
        23: istore_2
        24: goto          27
        27: iload_2
        28: ifeq          90
        31: aload_1
        32: checkcast     #2                  // class os/SubprocessException
        35: astore        4
        37: aload_0
        38: invokevirtual #58                 // Method result:()Los/CommandResult;
        41: aload         4
        43: invokevirtual #58                 // Method result:()Los/CommandResult;
        46: astore        5
        48: dup
        49: ifnonnull     61
        52: pop
        53: aload         5
        55: ifnull        69
        58: goto          82
        61: aload         5
        63: invokevirtual #101                // Method java/lang/Object.equals:(Ljava/lang/Object;)Z
        66: ifeq          82
        69: aload         4
        71: aload_0
        72: invokevirtual #103                // Method canEqual:(Ljava/lang/Object;)Z
        75: ifeq          82
        78: iconst_1
        79: goto          83
        82: iconst_0
        83: ifeq          90
        86: iconst_1
        87: goto          91
        90: iconst_0
        91: ireturn
      StackMapTable: number_of_entries = 10
        frame_type = 253 /* append */
          offset_delta = 19
          locals = [ top, class java/lang/Object ]
        frame_type = 2 /* same */
        frame_type = 255 /* full_frame */
          offset_delta = 4
          locals = [ class os/SubprocessException, class java/lang/Object, int, class java/lang/Object ]
          stack = []
        frame_type = 255 /* full_frame */
          offset_delta = 33
          locals = [ class os/SubprocessException, class java/lang/Object, int, class java/lang/Object, class os/SubprocessException, class os/CommandResult ]
          stack = [ class os/CommandResult ]
        frame_type = 7 /* same */
        frame_type = 12 /* same */
        frame_type = 64 /* same_locals_1_stack_item */
          stack = [ int ]
        frame_type = 255 /* full_frame */
          offset_delta = 2
          locals = [ class os/SubprocessException, class java/lang/Object ]
          stack = []
        frame_type = 253 /* append */
          offset_delta = 3
          locals = [ int, class java/lang/Object ]
        frame_type = 255 /* full_frame */
          offset_delta = 0
          locals = [ class os/SubprocessException, class java/lang/Object ]
          stack = [ int ]
      LineNumberTable:
        line 203: 0
      LocalVariableTable:
        Start  Length  Slot  Name   Signature
            0      92     0  this   Los/SubprocessException;
            0      92     1   x$1   Ljava/lang/Object;
    MethodParameters:
      Name                           Flags
      x$1                            final

  public os.SubprocessException(os.CommandResult);
    descriptor: (Los/CommandResult;)V
    flags: (0x0001) ACC_PUBLIC
    Code:
      stack=2, locals=2, args_size=2
         0: aload_0
         1: aload_1
         2: putfield      #50                 // Field result:Los/CommandResult;
         5: aload_0
         6: aload_1
         7: invokevirtual #108                // Method os/CommandResult.toString:()Ljava/lang/String;
        10: invokespecial #111                // Method java/lang/Exception."<init>":(Ljava/lang/String;)V
        13: aload_0
        14: invokestatic  #115                // InterfaceMethod scala/Product.$init$:(Lscala/Product;)V
        17: return
      LineNumberTable:
        line 203: 0
      LocalVariableTable:
        Start  Length  Slot  Name   Signature
            0      18     0  this   Los/SubprocessException;
            0      18     1 result   Los/CommandResult;
    MethodParameters:
      Name                           Flags
      result                         final
}
SourceFile: "Model.scala"
RuntimeVisibleAnnotations:
  0: #8(#9=s#10)
    scala.reflect.ScalaSignature(
      bytes="\u0006\u0005\u0005-b\u0001B\u000b\u0017\u0001fA\u0001b\f\u0001\u0003\u0016\u0004%\t\u0001\r\u0005\tk\u0001\u0011\t\u0012)A\u0005c!)a\u0007\u0001C\u0001o!9!\bAA\u0001\n\u0003Y\u0004bB\u001f\u0001#\u0003%\tA\u0010\u0005\b\u0013\u0002\t\t\u0011\"\u0011K\u0011\u001d\u0019\u0006!!A\u0005\u0002QCq\u0001\u0017\u0001\u0002\u0002\u0013\u0005\u0011\fC\u0004`\u0001\u0005\u0005I\u0011\t1\t\u000f\u001d\u0004\u0011\u0011!C\u0001Q\"9Q\u000eAA\u0001\n\u0003r\u0007b\u00029\u0001\u0003\u0003%\t%\u001d\u0005\be\u0002\t\t\u0011\"\u0011t\u000f\u001d)h#!A\t\u0002Y4q!\u0006\f\u0002\u0002#\u0005q\u000f\u0003\u00047\u001f\u0011\u0005\u0011q\u0001\u0005\n\u0003\u0013y\u0011\u0011!C#\u0003\u0017A\u0011\"!\u0004\u0010\u0003\u0003%\t)a\u0004\t\u0013\u0005Mq\"!A\u0005\u0002\u0006U\u0001\"CA\u0011\u001f\u0005\u0005I\u0011BA\u0012\u0005M\u0019VO\u00199s_\u000e,7o]#yG\u0016\u0004H/[8o\u0015\u00059\u0012AA8t\u0007\u0001\u0019B\u0001\u0001\u000e)YA\u00111$\n\b\u00039\tr!!\b\u0011\u000e\u0003yQ!a\b\r\u0002\rq\u0012xn\u001c;?\u0013\u0005\t\u0013!B:dC2\f\u0017BA\u0012%\u0003\u001d\u0001\u0018mY6bO\u0016T\u0011!I\u0005\u0003M\u001d\u0012\u0011\"\u0012=dKB$\u0018n\u001c8\u000b\u0005\r\"\u0003CA\u0015+\u001b\u0005!\u0013BA\u0016%\u0005\u001d\u0001&o\u001c3vGR\u0004\"aG\u0017\n\u00059:#\u0001D*fe&\fG.\u001b>bE2,\u0017A\u0002:fgVdG/F\u00012!\t\u00114\'D\u0001\u0017\u0013\t!dCA\u0007D_6l\u0017M\u001c3SKN,H\u000e^\u0001\be\u0016\u001cX\u000f\u001c;!\u0003\u0019a\u0014N\\5u}Q\u0011\u0001(\u000f\t\u0003e\u0001AQaL\u0002A\u0002E\nAaY8qsR\u0011\u0001\b\u0010\u0005\b_\u0011\u0001\n\u00111\u00012\u00039\u0019w\u000e]=%I\u00164\u0017-\u001e7uIE*\u0012a\u0010\u0016\u0003c\u0001[\u0013!\u0011\t\u0003\u0005\u001ek\u0011a\u0011\u0006\u0003\t\u0016\u000b\u0011\"\u001e8dQ\u0016\u001c7.\u001a3\u000b\u0005\u0019#\u0013AC1o]>$\u0018\r^5p]&\u0011\u0001j\u0011\u0002\u0012k:\u001c\u0007.Z2lK\u00124\u0016M]5b]\u000e,\u0017!\u00049s_\u0012,8\r\u001e)sK\u001aL\u00070F\u0001L!\ta\u0015+D\u0001N\u0015\tqu*\u0001\u0003mC:<\'\"\u0001)\u0002\t)\fg/Y\u0005\u0003%6\u0013aa\u0015;sS:<\u0017\u0001\u00049s_\u0012,8\r^!sSRLX#A+\u0011\u0005%2\u0016BA,%\u0005\rIe\u000e^\u0001\u000faJ|G-^2u\u000b2,W.\u001a8u)\tQV\f\u0005\u0002*7&\u0011A\f\n\u0002\u0004\u0003:L\bb\u00020\t\u0003\u0003\u0005\r!V\u0001\u0004q\u0012\n\u0014a\u00049s_\u0012,8\r^%uKJ\fGo\u001c:\u0016\u0003\u0005\u00042AY3[\u001b\u0005\u0019\'B\u00013%\u0003)\u0019w\u000e\u001c7fGRLwN\\\u0005\u0003M\u000e\u0014\u0001\"\u0013;fe\u0006$xN]\u0001\tG\u0006tW)];bYR\u0011\u0011\u000e\u001c\t\u0003S)L!a\u001b\u0013\u0003\u000f\t{w\u000e\\3b]\"9aLCA\u0001\u0002\u0004Q\u0016A\u00059s_\u0012,8\r^#mK6,g\u000e\u001e(b[\u0016$\"aS8\t\u000fy[\u0011\u0011!a\u0001+\u0006A\u0001.Y:i\u0007>$W\rF\u0001V\u0003\u0019)\u0017/^1mgR\u0011\u0011\u000e\u001e\u0005\b=6\t\t\u00111\u0001[\u0003M\u0019VO\u00199s_\u000e,7o]#yG\u0016\u0004H/[8o!\t\u0011tbE\u0002\u0010qz\u0004B!\u001f?2q5\t!P\u0003\u0002|I\u00059!/\u001e8uS6,\u0017BA?{\u0005E\t%m\u001d;sC\u000e$h)\u001e8di&|g.\r\t\u0004\u007f\u0006\u0015QBAA\u0001\u0015\r\t\u0019aT\u0001\u0003S>L1ALA\u0001)\u00051\u0018\u0001\u0003;p\'R\u0014\u0018N\\4\u0015\u0003-\u000bQ!\u00199qYf$2\u0001OA\t\u0011\u0015y#\u00031\u00012\u0003\u001d)h.\u00199qYf$B!a\u0006\u0002\u001eA!\u0011&!\u00072\u0013\r\tY\u0002\n\u0002\u0007\u001fB$\u0018n\u001c8\t\u0011\u0005}1#!AA\u0002a\n1\u0001\u001f\u00131\u000319(/\u001b;f%\u0016\u0004H.Y2f)\t\t)\u0003E\u0002M\u0003OI1!!\u000bN\u0005\u0019y%M[3di\u0002"
    )
  ScalaInlineInfo: length = 0x45 (unknown attribute)
   01 00 00 0D 00 34 00 35 00 00 56 00 57 00 00 33
   00 1A 00 00 38 00 30 00 00 63 00 57 00 00 5E 00
   40 00 00 3F 00 40 00 00 41 00 42 00 00 59 00 5A
   00 00 27 00 28 00 00 4C 00 28 00 00 3B 00 3C 00
   00 0B 00 30 00
  ScalaSig: length = 0x3 (unknown attribute)
   05 02 00
