Classfile /Users/mw/Projects/slang-braindump/.jar/jar8/assemble/slang-braindump/assemble/content/os/symlink.class
  Last modified May 29, 2022; size 871 bytes
  SHA-256 checksum 8e72b03940eff13b38a4ae7c13836f14d0f76e5ddbd281ee5f8fa2b199680a30
  Compiled from "FileOps.scala"
public final class os.symlink
  minor version: 0
  major version: 52
  flags: (0x0031) ACC_PUBLIC, ACC_FINAL, ACC_SUPER
  this_class: #2                          // os/symlink
  super_class: #4                         // java/lang/Object
  interfaces: 0, fields: 0, methods: 2, attributes: 3
Constant pool:
   #1 = Utf8               os/symlink
   #2 = Class              #1             // os/symlink
   #3 = Utf8               java/lang/Object
   #4 = Class              #3             // java/lang/Object
   #5 = Utf8               FileOps.scala
   #6 = Utf8               Lscala/reflect/ScalaSignature;
   #7 = Utf8               bytes
   #8 = Utf8               \u0006\u0005U:Q!\u0002\u0004\t\u0002%1Qa\u0003\u0004\t\u00021AQaE\u0001\u0005\u0002QAQ!F\u0001\u0005\u0002YAq!K\u0001\u0012\u0002\u0013\u0005!&A\u0004ts6d\u0017N\\6\u000b\u0003\u001d\t!a\\:\u0004\u0001A\u0011!\"A\u0007\u0002\r\t91/_7mS:\\7CA\u0001\u000e!\tq\u0011#D\u0001\u0010\u0015\u0005\u0001\u0012!B:dC2\f\u0017B\u0001\n\u0010\u0005\u0019\te.\u001f*fM\u00061A(\u001b8jiz\"\u0012!C\u0001\u0006CB\u0004H.\u001f\u000b\u0005/iyB\u0005\u0005\u0002\u000f1%\u0011\u0011d\u0004\u0002\u0005+:LG\u000fC\u0003\u001c\u0007\u0001\u0007A$\u0001\u0003mS:\\\u0007C\u0001\u0006\u001e\u0013\tqbA\u0001\u0003QCRD\u0007\"\u0002\u0011\u0004\u0001\u0004\t\u0013\u0001\u00023fgR\u0004\"A\u0003\u0012\n\u0005\r2!\u0001\u0003$jY\u0016\u0004\u0016\r\u001e5\t\u000f\u0015\u001a\u0001\u0013!a\u0001M\u0005)\u0001/\u001a:ngB\u0011!bJ\u0005\u0003Q\u0019\u0011q\u0001U3s[N+G/A\bbaBd\u0017\u0010\n3fM\u0006,H\u000e\u001e\u00134+\u0005Y#F\u0001\u0014-W\u0005i\u0003C\u0001\u00184\u001b\u0005y#B\u0001\u00192\u0003%)hn\u00195fG.,GM\u0003\u00023\u001f\u0005Q\u0011M\u001c8pi\u0006$\u0018n\u001c8\n\u0005Qz#!E;oG\",7m[3e-\u0006\u0014\u0018.\u00198dK\u0002
   #9 = Utf8               apply$default$3
  #10 = Utf8               ()Los/PermSet;
  #11 = Utf8               os/symlink$
  #12 = Class              #11            // os/symlink$
  #13 = Utf8               MODULE$
  #14 = Utf8               Los/symlink$;
  #15 = NameAndType        #13:#14        // MODULE$:Los/symlink$;
  #16 = Fieldref           #12.#15        // os/symlink$.MODULE$:Los/symlink$;
  #17 = NameAndType        #9:#10         // apply$default$3:()Los/PermSet;
  #18 = Methodref          #12.#17        // os/symlink$.apply$default$3:()Los/PermSet;
  #19 = Utf8               apply
  #20 = Utf8               (Los/Path;Los/FilePath;Los/PermSet;)V
  #21 = Utf8               link
  #22 = Utf8               dest
  #23 = Utf8               perms
  #24 = NameAndType        #19:#20        // apply:(Los/Path;Los/FilePath;Los/PermSet;)V
  #25 = Methodref          #12.#24        // os/symlink$.apply:(Los/Path;Los/FilePath;Los/PermSet;)V
  #26 = Utf8               Code
  #27 = Utf8               MethodParameters
  #28 = Utf8               SourceFile
  #29 = Utf8               RuntimeVisibleAnnotations
  #30 = Utf8               ScalaSig
{
  public static os.PermSet apply$default$3();
    descriptor: ()Los/PermSet;
    flags: (0x0009) ACC_PUBLIC, ACC_STATIC
    Code:
      stack=1, locals=0, args_size=0
         0: getstatic     #16                 // Field os/symlink$.MODULE$:Los/symlink$;
         3: invokevirtual #18                 // Method os/symlink$.apply$default$3:()Los/PermSet;
         6: areturn

  public static void apply(os.Path, os.FilePath, os.PermSet);
    descriptor: (Los/Path;Los/FilePath;Los/PermSet;)V
    flags: (0x0009) ACC_PUBLIC, ACC_STATIC
    Code:
      stack=4, locals=3, args_size=3
         0: getstatic     #16                 // Field os/symlink$.MODULE$:Los/symlink$;
         3: aload_0
         4: aload_1
         5: aload_2
         6: invokevirtual #25                 // Method os/symlink$.apply:(Los/Path;Los/FilePath;Los/PermSet;)V
         9: return
    MethodParameters:
      Name                           Flags
      link                           final
      dest                           final
      perms                          final
}
SourceFile: "FileOps.scala"
RuntimeVisibleAnnotations:
  0: #6(#7=s#8)
    scala.reflect.ScalaSignature(
      bytes="\u0006\u0005U:Q!\u0002\u0004\t\u0002%1Qa\u0003\u0004\t\u00021AQaE\u0001\u0005\u0002QAQ!F\u0001\u0005\u0002YAq!K\u0001\u0012\u0002\u0013\u0005!&A\u0004ts6d\u0017N\\6\u000b\u0003\u001d\t!a\\:\u0004\u0001A\u0011!\"A\u0007\u0002\r\t91/_7mS:\\7CA\u0001\u000e!\tq\u0011#D\u0001\u0010\u0015\u0005\u0001\u0012!B:dC2\f\u0017B\u0001\n\u0010\u0005\u0019\te.\u001f*fM\u00061A(\u001b8jiz\"\u0012!C\u0001\u0006CB\u0004H.\u001f\u000b\u0005/iyB\u0005\u0005\u0002\u000f1%\u0011\u0011d\u0004\u0002\u0005+:LG\u000fC\u0003\u001c\u0007\u0001\u0007A$\u0001\u0003mS:\\\u0007C\u0001\u0006\u001e\u0013\tqbA\u0001\u0003QCRD\u0007\"\u0002\u0011\u0004\u0001\u0004\t\u0013\u0001\u00023fgR\u0004\"A\u0003\u0012\n\u0005\r2!\u0001\u0003$jY\u0016\u0004\u0016\r\u001e5\t\u000f\u0015\u001a\u0001\u0013!a\u0001M\u0005)\u0001/\u001a:ngB\u0011!bJ\u0005\u0003Q\u0019\u0011q\u0001U3s[N+G/A\bbaBd\u0017\u0010\n3fM\u0006,H\u000e\u001e\u00134+\u0005Y#F\u0001\u0014-W\u0005i\u0003C\u0001\u00184\u001b\u0005y#B\u0001\u00192\u0003%)hn\u00195fG.,GM\u0003\u00023\u001f\u0005Q\u0011M\u001c8pi\u0006$\u0018n\u001c8\n\u0005Qz#!E;oG\",7m[3e-\u0006\u0014\u0018.\u00198dK\u0002"
    )
  ScalaSig: length = 0x3 (unknown attribute)
   05 02 00
