Classfile /Users/mw/Projects/slang-braindump/.jar/jar8/assemble/slang-braindump/assemble/content/os/walk.class
  Last modified May 29, 2022; size 3197 bytes
  SHA-256 checksum fe3571dddeddff0cb4c899e97504ce5161afbd21e09b0e7d05b7bea06f563005
  Compiled from "ListOps.scala"
public final class os.walk
  minor version: 0
  major version: 52
  flags: (0x0031) ACC_PUBLIC, ACC_FINAL, ACC_SUPER
  this_class: #2                          // os/walk
  super_class: #4                         // java/lang/Object
  interfaces: 0, fields: 0, methods: 12, attributes: 4
Constant pool:
   #1 = Utf8               os/walk
   #2 = Class              #1             // os/walk
   #3 = Utf8               java/lang/Object
   #4 = Class              #3             // java/lang/Object
   #5 = Utf8               ListOps.scala
   #6 = Utf8               Lscala/reflect/ScalaSignature;
   #7 = Utf8               bytes
   #8 = Utf8               \u0006\u0005\u0005er!\u0002\u0010 \u0011\u0003\u0011c!\u0002\u0013 \u0011\u0003)\u0003\"\u0002\u0017\u0002\t\u0003i\u0003\"\u0002\u0018\u0002\t\u0003y\u0003b\u0002+\u0002#\u0003%\t!\u0016\u0005\bA\u0006\t\n\u0011\"\u0001b\u0011\u001d\u0019\u0017!%A\u0005\u0002\u0005Dq\u0001Z\u0001\u0012\u0002\u0013\u0005Q\rC\u0004h\u0003E\u0005I\u0011A1\t\u000b!\fA\u0011A5\t\u000fi\f\u0011\u0013!C\u0001w\"9Q0AI\u0001\n\u0003\t\u0007b\u0002@\u0002#\u0003%\t!\u0019\u0005\b\u007f\u0006\t\n\u0011\"\u0001f\u0011!\t\t!AI\u0001\n\u0003\twaBA\u0002\u0003!\u0005\u0011Q\u0001\u0004\b\u0003\u0013\t\u0001\u0012AA\u0006\u0011\u0019a\u0003\u0003\"\u0001\u0002\u000e!1a\u0006\u0005C\u0001\u0003\u001fAq\u0001\u0016\t\u0012\u0002\u0013\u0005Q\u000bC\u0004a!E\u0005I\u0011A1\t\u000f\r\u0004\u0012\u0013!C\u0001C\"9A\rEI\u0001\n\u0003)\u0007bB4\u0011#\u0003%\t!\u0019\u0005\u0007QB!\t!!\u000b\t\u000fi\u0004\u0012\u0013!C\u0001w\"9Q\u0010EI\u0001\n\u0003\t\u0007b\u0002@\u0011#\u0003%\t!\u0019\u0005\b\u007fB\t\n\u0011\"\u0001f\u0011!\t\t\u0001EI\u0001\n\u0003\t\u0017\u0001B<bY.T\u0011\u0001I\u0001\u0003_N\u001c\u0001\u0001\u0005\u0002$\u00035\tqD\u0001\u0003xC2\\7CA\u0001\'!\t9#&D\u0001)\u0015\u0005I\u0013!B:dC2\f\u0017BA\u0016)\u0005\u0019\te.\u001f*fM\u00061A(\u001b8jiz\"\u0012AI\u0001\u0006CB\u0004H.\u001f\u000b\ba}\n\u0015jS\'S!\r\t\u0014\b\u0010\b\u0003e]r!a\r\u001c\u000e\u0003QR!!N\u0011\u0002\rq\u0012xn\u001c;?\u0013\u0005I\u0013B\u0001\u001d)\u0003\u001d\u0001\u0018mY6bO\u0016L!AO\u001e\u0003\u0015%sG-\u001a=fIN+\u0017O\u0003\u00029QA\u00111%P\u0005\u0003}}\u0011A\u0001U1uQ\")\u0001i\u0001a\u0001y\u0005!\u0001/\u0019;i\u0011\u001d\u00115\u0001%AA\u0002\r\u000bAa]6jaB!q\u0005\u0012\u001fG\u0013\t)\u0005FA\u0005Gk:\u001cG/[8ocA\u0011qeR\u0005\u0003\u0011\"\u0012qAQ8pY\u0016\fg\u000eC\u0004K\u0007A\u0005\t\u0019\u0001$\u0002\u0011A\u0014Xm\u0014:eKJDq\u0001T\u0002\u0011\u0002\u0003\u0007a)A\u0006g_2dwn\u001e\'j].\u001c\bb\u0002(\u0004!\u0003\u0005\raT\u0001\t[\u0006DH)\u001a9uQB\u0011q\u0005U\u0005\u0003#\"\u00121!\u00138u\u0011\u001d\u00196\u0001%AA\u0002\u0019\u000bQ\"\u001b8dYV$W\rV1sO\u0016$\u0018aD1qa2LH\u0005Z3gCVdG\u000f\n\u001a\u0016\u0003YS#aQ,,\u0003a\u0003\"!\u00170\u000e\u0003iS!a\u0017/\u0002\u0013Ut7\r[3dW\u0016$\'BA/)\u0003)\tgN\\8uCRLwN\\\u0005\u0003?j\u0013\u0011#\u001e8dQ\u0016\u001c7.\u001a3WCJL\u0017M\\2f\u0003=\t\u0007\u000f\u001d7zI\u0011,g-Y;mi\u0012\u001aT#\u00012+\u0005\u0019;\u0016aD1qa2LH\u0005Z3gCVdG\u000f\n\u001b\u0002\u001f\u0005\u0004\b\u000f\\=%I\u00164\u0017-\u001e7uIU*\u0012A\u001a\u0016\u0003\u001f^\u000bq\"\u00199qYf$C-\u001a4bk2$HEN\u0001\u0006CR$(o\u001d\u000b\bUF\u0014ho\u001e=z!\r\t\u0014h\u001b\t\u0005O1dd.\u0003\u0002nQ\t1A+\u001e9mKJ\u0002\"aI8\n\u0005A|\"\u0001C*uCRLeNZ8\t\u000b\u0001K\u0001\u0019\u0001\u001f\t\u000f\tK\u0001\u0013!a\u0001gB)q\u0005\u001e\u001fo\r&\u0011Q\u000f\u000b\u0002\n\rVt7\r^5p]JBqAS\u0005\u0011\u0002\u0003\u0007a\tC\u0004M\u0013A\u0005\t\u0019\u0001$\t\u000f9K\u0001\u0013!a\u0001\u001f\"91+\u0003I\u0001\u0002\u00041\u0015aD1uiJ\u001cH\u0005Z3gCVdG\u000f\n\u001a\u0016\u0003qT#a],\u0002\u001f\u0005$HO]:%I\u00164\u0017-\u001e7uIM\nq\"\u0019;ueN$C-\u001a4bk2$H\u0005N\u0001\u0010CR$(o\u001d\u0013eK\u001a\fW\u000f\u001c;%k\u0005y\u0011\r\u001e;sg\u0012\"WMZ1vYR$c\'\u0001\u0004tiJ,\u0017-\u001c\t\u0004\u0003\u000f\u0001R\"A\u0001\u0003\rM$(/Z1n\'\t\u0001b\u0005\u0006\u0002\u0002\u0006Qq\u0011\u0011CA\u000f\u0003?\t\t#a\t\u0002&\u0005\u001d\u0002#BA\n\u0003/adbA\u0012\u0002\u0016%\u0011\u0001hH\u0005\u0005\u00033\tYBA\u0005HK:,\'/\u0019;pe*\u0011\u0001h\b\u0005\u0006\u0001J\u0001\r\u0001\u0010\u0005\b\u0005J\u0001\n\u00111\u0001D\u0011\u001dQ%\u0003%AA\u0002\u0019Cq\u0001\u0014\n\u0011\u0002\u0003\u0007a\tC\u0004O%A\u0005\t\u0019A(\t\u000fM\u0013\u0002\u0013!a\u0001\rRq\u00111FA\u0017\u0003_\t\t$a\r\u00026\u0005]\u0002#BA\n\u0003/Y\u0007\"\u0002!\u0019\u0001\u0004a\u0004b\u0002\"\u0019!\u0003\u0005\ra\u001d\u0005\b\u0015b\u0001\n\u00111\u0001G\u0011\u001da\u0005\u0004%AA\u0002\u0019CqA\u0014\r\u0011\u0002\u0003\u0007q\nC\u0004T1A\u0005\t\u0019\u0001$
   #9 = Utf8               os/walk$stream$
  #10 = Class              #9             // os/walk$stream$
  #11 = Utf8               stream$
  #12 = Utf8               attrs$default$6
  #13 = Utf8               ()Z
  #14 = Utf8               os/walk$
  #15 = Class              #14            // os/walk$
  #16 = Utf8               MODULE$
  #17 = Utf8               Los/walk$;
  #18 = NameAndType        #16:#17        // MODULE$:Los/walk$;
  #19 = Fieldref           #15.#18        // os/walk$.MODULE$:Los/walk$;
  #20 = NameAndType        #12:#13        // attrs$default$6:()Z
  #21 = Methodref          #15.#20        // os/walk$.attrs$default$6:()Z
  #22 = Utf8               attrs$default$5
  #23 = Utf8               ()I
  #24 = NameAndType        #22:#23        // attrs$default$5:()I
  #25 = Methodref          #15.#24        // os/walk$.attrs$default$5:()I
  #26 = Utf8               attrs$default$4
  #27 = NameAndType        #26:#13        // attrs$default$4:()Z
  #28 = Methodref          #15.#27        // os/walk$.attrs$default$4:()Z
  #29 = Utf8               attrs$default$3
  #30 = NameAndType        #29:#13        // attrs$default$3:()Z
  #31 = Methodref          #15.#30        // os/walk$.attrs$default$3:()Z
  #32 = Utf8               attrs$default$2
  #33 = Utf8               ()Lscala/Function2;
  #34 = Utf8               ()Lscala/Function2<Los/Path;Los/StatInfo;Ljava/lang/Object;>;
  #35 = NameAndType        #32:#33        // attrs$default$2:()Lscala/Function2;
  #36 = Methodref          #15.#35        // os/walk$.attrs$default$2:()Lscala/Function2;
  #37 = Utf8               attrs
  #38 = Utf8               (Los/Path;Lscala/Function2;ZZIZ)Lscala/collection/immutable/IndexedSeq;
  #39 = Utf8               (Los/Path;Lscala/Function2<Los/Path;Los/StatInfo;Ljava/lang/Object;>;ZZIZ)Lscala/collection/immutable/IndexedSeq<Lscala/Tuple2<Los/Path;Los/StatInfo;>;>;
  #40 = Utf8               path
  #41 = Utf8               skip
  #42 = Utf8               preOrder
  #43 = Utf8               followLinks
  #44 = Utf8               maxDepth
  #45 = Utf8               includeTarget
  #46 = NameAndType        #37:#38        // attrs:(Los/Path;Lscala/Function2;ZZIZ)Lscala/collection/immutable/IndexedSeq;
  #47 = Methodref          #15.#46        // os/walk$.attrs:(Los/Path;Lscala/Function2;ZZIZ)Lscala/collection/immutable/IndexedSeq;
  #48 = Utf8               apply$default$6
  #49 = NameAndType        #48:#13        // apply$default$6:()Z
  #50 = Methodref          #15.#49        // os/walk$.apply$default$6:()Z
  #51 = Utf8               apply$default$5
  #52 = NameAndType        #51:#23        // apply$default$5:()I
  #53 = Methodref          #15.#52        // os/walk$.apply$default$5:()I
  #54 = Utf8               apply$default$4
  #55 = NameAndType        #54:#13        // apply$default$4:()Z
  #56 = Methodref          #15.#55        // os/walk$.apply$default$4:()Z
  #57 = Utf8               apply$default$3
  #58 = NameAndType        #57:#13        // apply$default$3:()Z
  #59 = Methodref          #15.#58        // os/walk$.apply$default$3:()Z
  #60 = Utf8               apply$default$2
  #61 = Utf8               ()Lscala/Function1;
  #62 = Utf8               ()Lscala/Function1<Los/Path;Ljava/lang/Object;>;
  #63 = NameAndType        #60:#61        // apply$default$2:()Lscala/Function1;
  #64 = Methodref          #15.#63        // os/walk$.apply$default$2:()Lscala/Function1;
  #65 = Utf8               apply
  #66 = Utf8               (Los/Path;Lscala/Function1;ZZIZ)Lscala/collection/immutable/IndexedSeq;
  #67 = Utf8               (Los/Path;Lscala/Function1<Los/Path;Ljava/lang/Object;>;ZZIZ)Lscala/collection/immutable/IndexedSeq<Los/Path;>;
  #68 = NameAndType        #65:#66        // apply:(Los/Path;Lscala/Function1;ZZIZ)Lscala/collection/immutable/IndexedSeq;
  #69 = Methodref          #15.#68        // os/walk$.apply:(Los/Path;Lscala/Function1;ZZIZ)Lscala/collection/immutable/IndexedSeq;
  #70 = Utf8               Code
  #71 = Utf8               Signature
  #72 = Utf8               MethodParameters
  #73 = Utf8               InnerClasses
  #74 = Utf8               SourceFile
  #75 = Utf8               RuntimeVisibleAnnotations
  #76 = Utf8               ScalaSig
{
  public static boolean attrs$default$6();
    descriptor: ()Z
    flags: (0x0009) ACC_PUBLIC, ACC_STATIC
    Code:
      stack=1, locals=0, args_size=0
         0: getstatic     #19                 // Field os/walk$.MODULE$:Los/walk$;
         3: invokevirtual #21                 // Method os/walk$.attrs$default$6:()Z
         6: ireturn

  public static int attrs$default$5();
    descriptor: ()I
    flags: (0x0009) ACC_PUBLIC, ACC_STATIC
    Code:
      stack=1, locals=0, args_size=0
         0: getstatic     #19                 // Field os/walk$.MODULE$:Los/walk$;
         3: invokevirtual #25                 // Method os/walk$.attrs$default$5:()I
         6: ireturn

  public static boolean attrs$default$4();
    descriptor: ()Z
    flags: (0x0009) ACC_PUBLIC, ACC_STATIC
    Code:
      stack=1, locals=0, args_size=0
         0: getstatic     #19                 // Field os/walk$.MODULE$:Los/walk$;
         3: invokevirtual #28                 // Method os/walk$.attrs$default$4:()Z
         6: ireturn

  public static boolean attrs$default$3();
    descriptor: ()Z
    flags: (0x0009) ACC_PUBLIC, ACC_STATIC
    Code:
      stack=1, locals=0, args_size=0
         0: getstatic     #19                 // Field os/walk$.MODULE$:Los/walk$;
         3: invokevirtual #31                 // Method os/walk$.attrs$default$3:()Z
         6: ireturn

  public static scala.Function2<os.Path, os.StatInfo, java.lang.Object> attrs$default$2();
    descriptor: ()Lscala/Function2;
    flags: (0x0009) ACC_PUBLIC, ACC_STATIC
    Code:
      stack=1, locals=0, args_size=0
         0: getstatic     #19                 // Field os/walk$.MODULE$:Los/walk$;
         3: invokevirtual #36                 // Method os/walk$.attrs$default$2:()Lscala/Function2;
         6: areturn
    Signature: #34                          // ()Lscala/Function2<Los/Path;Los/StatInfo;Ljava/lang/Object;>;

  public static scala.collection.immutable.IndexedSeq<scala.Tuple2<os.Path, os.StatInfo>> attrs(os.Path, scala.Function2<os.Path, os.StatInfo, java.lang.Object>, boolean, boolean, int, boolean);
    descriptor: (Los/Path;Lscala/Function2;ZZIZ)Lscala/collection/immutable/IndexedSeq;
    flags: (0x0009) ACC_PUBLIC, ACC_STATIC
    Code:
      stack=7, locals=6, args_size=6
         0: getstatic     #19                 // Field os/walk$.MODULE$:Los/walk$;
         3: aload_0
         4: aload_1
         5: iload_2
         6: iload_3
         7: iload         4
         9: iload         5
        11: invokevirtual #47                 // Method os/walk$.attrs:(Los/Path;Lscala/Function2;ZZIZ)Lscala/collection/immutable/IndexedSeq;
        14: areturn
    Signature: #39                          // (Los/Path;Lscala/Function2<Los/Path;Los/StatInfo;Ljava/lang/Object;>;ZZIZ)Lscala/collection/immutable/IndexedSeq<Lscala/Tuple2<Los/Path;Los/StatInfo;>;>;
    MethodParameters:
      Name                           Flags
      path                           final
      skip                           final
      preOrder                       final
      followLinks                    final
      maxDepth                       final
      includeTarget                  final

  public static boolean apply$default$6();
    descriptor: ()Z
    flags: (0x0009) ACC_PUBLIC, ACC_STATIC
    Code:
      stack=1, locals=0, args_size=0
         0: getstatic     #19                 // Field os/walk$.MODULE$:Los/walk$;
         3: invokevirtual #50                 // Method os/walk$.apply$default$6:()Z
         6: ireturn

  public static int apply$default$5();
    descriptor: ()I
    flags: (0x0009) ACC_PUBLIC, ACC_STATIC
    Code:
      stack=1, locals=0, args_size=0
         0: getstatic     #19                 // Field os/walk$.MODULE$:Los/walk$;
         3: invokevirtual #53                 // Method os/walk$.apply$default$5:()I
         6: ireturn

  public static boolean apply$default$4();
    descriptor: ()Z
    flags: (0x0009) ACC_PUBLIC, ACC_STATIC
    Code:
      stack=1, locals=0, args_size=0
         0: getstatic     #19                 // Field os/walk$.MODULE$:Los/walk$;
         3: invokevirtual #56                 // Method os/walk$.apply$default$4:()Z
         6: ireturn

  public static boolean apply$default$3();
    descriptor: ()Z
    flags: (0x0009) ACC_PUBLIC, ACC_STATIC
    Code:
      stack=1, locals=0, args_size=0
         0: getstatic     #19                 // Field os/walk$.MODULE$:Los/walk$;
         3: invokevirtual #59                 // Method os/walk$.apply$default$3:()Z
         6: ireturn

  public static scala.Function1<os.Path, java.lang.Object> apply$default$2();
    descriptor: ()Lscala/Function1;
    flags: (0x0009) ACC_PUBLIC, ACC_STATIC
    Code:
      stack=1, locals=0, args_size=0
         0: getstatic     #19                 // Field os/walk$.MODULE$:Los/walk$;
         3: invokevirtual #64                 // Method os/walk$.apply$default$2:()Lscala/Function1;
         6: areturn
    Signature: #62                          // ()Lscala/Function1<Los/Path;Ljava/lang/Object;>;

  public static scala.collection.immutable.IndexedSeq<os.Path> apply(os.Path, scala.Function1<os.Path, java.lang.Object>, boolean, boolean, int, boolean);
    descriptor: (Los/Path;Lscala/Function1;ZZIZ)Lscala/collection/immutable/IndexedSeq;
    flags: (0x0009) ACC_PUBLIC, ACC_STATIC
    Code:
      stack=7, locals=6, args_size=6
         0: getstatic     #19                 // Field os/walk$.MODULE$:Los/walk$;
         3: aload_0
         4: aload_1
         5: iload_2
         6: iload_3
         7: iload         4
         9: iload         5
        11: invokevirtual #69                 // Method os/walk$.apply:(Los/Path;Lscala/Function1;ZZIZ)Lscala/collection/immutable/IndexedSeq;
        14: areturn
    Signature: #67                          // (Los/Path;Lscala/Function1<Los/Path;Ljava/lang/Object;>;ZZIZ)Lscala/collection/immutable/IndexedSeq<Los/Path;>;
    MethodParameters:
      Name                           Flags
      path                           final
      skip                           final
      preOrder                       final
      followLinks                    final
      maxDepth                       final
      includeTarget                  final
}
InnerClasses:
  public static #11= #10 of #2;           // stream$=class os/walk$stream$ of class os/walk
SourceFile: "ListOps.scala"
RuntimeVisibleAnnotations:
  0: #6(#7=s#8)
    scala.reflect.ScalaSignature(
      bytes="\u0006\u0005\u0005er!\u0002\u0010 \u0011\u0003\u0011c!\u0002\u0013 \u0011\u0003)\u0003\"\u0002\u0017\u0002\t\u0003i\u0003\"\u0002\u0018\u0002\t\u0003y\u0003b\u0002+\u0002#\u0003%\t!\u0016\u0005\bA\u0006\t\n\u0011\"\u0001b\u0011\u001d\u0019\u0017!%A\u0005\u0002\u0005Dq\u0001Z\u0001\u0012\u0002\u0013\u0005Q\rC\u0004h\u0003E\u0005I\u0011A1\t\u000b!\fA\u0011A5\t\u000fi\f\u0011\u0013!C\u0001w\"9Q0AI\u0001\n\u0003\t\u0007b\u0002@\u0002#\u0003%\t!\u0019\u0005\b\u007f\u0006\t\n\u0011\"\u0001f\u0011!\t\t!AI\u0001\n\u0003\twaBA\u0002\u0003!\u0005\u0011Q\u0001\u0004\b\u0003\u0013\t\u0001\u0012AA\u0006\u0011\u0019a\u0003\u0003\"\u0001\u0002\u000e!1a\u0006\u0005C\u0001\u0003\u001fAq\u0001\u0016\t\u0012\u0002\u0013\u0005Q\u000bC\u0004a!E\u0005I\u0011A1\t\u000f\r\u0004\u0012\u0013!C\u0001C\"9A\rEI\u0001\n\u0003)\u0007bB4\u0011#\u0003%\t!\u0019\u0005\u0007QB!\t!!\u000b\t\u000fi\u0004\u0012\u0013!C\u0001w\"9Q\u0010EI\u0001\n\u0003\t\u0007b\u0002@\u0011#\u0003%\t!\u0019\u0005\b\u007fB\t\n\u0011\"\u0001f\u0011!\t\t\u0001EI\u0001\n\u0003\t\u0017\u0001B<bY.T\u0011\u0001I\u0001\u0003_N\u001c\u0001\u0001\u0005\u0002$\u00035\tqD\u0001\u0003xC2\\7CA\u0001\'!\t9#&D\u0001)\u0015\u0005I\u0013!B:dC2\f\u0017BA\u0016)\u0005\u0019\te.\u001f*fM\u00061A(\u001b8jiz\"\u0012AI\u0001\u0006CB\u0004H.\u001f\u000b\ba}\n\u0015jS\'S!\r\t\u0014\b\u0010\b\u0003e]r!a\r\u001c\u000e\u0003QR!!N\u0011\u0002\rq\u0012xn\u001c;?\u0013\u0005I\u0013B\u0001\u001d)\u0003\u001d\u0001\u0018mY6bO\u0016L!AO\u001e\u0003\u0015%sG-\u001a=fIN+\u0017O\u0003\u00029QA\u00111%P\u0005\u0003}}\u0011A\u0001U1uQ\")\u0001i\u0001a\u0001y\u0005!\u0001/\u0019;i\u0011\u001d\u00115\u0001%AA\u0002\r\u000bAa]6jaB!q\u0005\u0012\u001fG\u0013\t)\u0005FA\u0005Gk:\u001cG/[8ocA\u0011qeR\u0005\u0003\u0011\"\u0012qAQ8pY\u0016\fg\u000eC\u0004K\u0007A\u0005\t\u0019\u0001$\u0002\u0011A\u0014Xm\u0014:eKJDq\u0001T\u0002\u0011\u0002\u0003\u0007a)A\u0006g_2dwn\u001e\'j].\u001c\bb\u0002(\u0004!\u0003\u0005\raT\u0001\t[\u0006DH)\u001a9uQB\u0011q\u0005U\u0005\u0003#\"\u00121!\u00138u\u0011\u001d\u00196\u0001%AA\u0002\u0019\u000bQ\"\u001b8dYV$W\rV1sO\u0016$\u0018aD1qa2LH\u0005Z3gCVdG\u000f\n\u001a\u0016\u0003YS#aQ,,\u0003a\u0003\"!\u00170\u000e\u0003iS!a\u0017/\u0002\u0013Ut7\r[3dW\u0016$\'BA/)\u0003)\tgN\\8uCRLwN\\\u0005\u0003?j\u0013\u0011#\u001e8dQ\u0016\u001c7.\u001a3WCJL\u0017M\\2f\u0003=\t\u0007\u000f\u001d7zI\u0011,g-Y;mi\u0012\u001aT#\u00012+\u0005\u0019;\u0016aD1qa2LH\u0005Z3gCVdG\u000f\n\u001b\u0002\u001f\u0005\u0004\b\u000f\\=%I\u00164\u0017-\u001e7uIU*\u0012A\u001a\u0016\u0003\u001f^\u000bq\"\u00199qYf$C-\u001a4bk2$HEN\u0001\u0006CR$(o\u001d\u000b\bUF\u0014ho\u001e=z!\r\t\u0014h\u001b\t\u0005O1dd.\u0003\u0002nQ\t1A+\u001e9mKJ\u0002\"aI8\n\u0005A|\"\u0001C*uCRLeNZ8\t\u000b\u0001K\u0001\u0019\u0001\u001f\t\u000f\tK\u0001\u0013!a\u0001gB)q\u0005\u001e\u001fo\r&\u0011Q\u000f\u000b\u0002\n\rVt7\r^5p]JBqAS\u0005\u0011\u0002\u0003\u0007a\tC\u0004M\u0013A\u0005\t\u0019\u0001$\t\u000f9K\u0001\u0013!a\u0001\u001f\"91+\u0003I\u0001\u0002\u00041\u0015aD1uiJ\u001cH\u0005Z3gCVdG\u000f\n\u001a\u0016\u0003qT#a],\u0002\u001f\u0005$HO]:%I\u00164\u0017-\u001e7uIM\nq\"\u0019;ueN$C-\u001a4bk2$H\u0005N\u0001\u0010CR$(o\u001d\u0013eK\u001a\fW\u000f\u001c;%k\u0005y\u0011\r\u001e;sg\u0012\"WMZ1vYR$c\'\u0001\u0004tiJ,\u0017-\u001c\t\u0004\u0003\u000f\u0001R\"A\u0001\u0003\rM$(/Z1n\'\t\u0001b\u0005\u0006\u0002\u0002\u0006Qq\u0011\u0011CA\u000f\u0003?\t\t#a\t\u0002&\u0005\u001d\u0002#BA\n\u0003/adbA\u0012\u0002\u0016%\u0011\u0001hH\u0005\u0005\u00033\tYBA\u0005HK:,\'/\u0019;pe*\u0011\u0001h\b\u0005\u0006\u0001J\u0001\r\u0001\u0010\u0005\b\u0005J\u0001\n\u00111\u0001D\u0011\u001dQ%\u0003%AA\u0002\u0019Cq\u0001\u0014\n\u0011\u0002\u0003\u0007a\tC\u0004O%A\u0005\t\u0019A(\t\u000fM\u0013\u0002\u0013!a\u0001\rRq\u00111FA\u0017\u0003_\t\t$a\r\u00026\u0005]\u0002#BA\n\u0003/Y\u0007\"\u0002!\u0019\u0001\u0004a\u0004b\u0002\"\u0019!\u0003\u0005\ra\u001d\u0005\b\u0015b\u0001\n\u00111\u0001G\u0011\u001da\u0005\u0004%AA\u0002\u0019CqA\u0014\r\u0011\u0002\u0003\u0007q\nC\u0004T1A\u0005\t\u0019\u0001$"
    )
  ScalaSig: length = 0x3 (unknown attribute)
   05 02 00
