Classfile /Users/mw/Projects/slang-braindump/.jar/jar8/assemble/slang-braindump/assemble/content/os/write$.class
  Last modified May 29, 2022; size 5739 bytes
  SHA-256 checksum 88705e3633b0cec2f643d401b4e422ba8263e6337c3b72d2bddd5004c8d2ee0d
  Compiled from "ReadWriteOps.scala"
public final class os.write$
  minor version: 0
  major version: 52
  flags: (0x0031) ACC_PUBLIC, ACC_FINAL, ACC_SUPER
  this_class: #2                          // os/write$
  super_class: #4                         // java/lang/Object
  interfaces: 0, fields: 1, methods: 10, attributes: 4
Constant pool:
    #1 = Utf8               os/write$
    #2 = Class              #1            // os/write$
    #3 = Utf8               java/lang/Object
    #4 = Class              #3            // java/lang/Object
    #5 = Utf8               ReadWriteOps.scala
    #6 = Utf8               os/PathChunk$RelPathChunk
    #7 = Class              #6            // os/PathChunk$RelPathChunk
    #8 = Utf8               os/PathChunk
    #9 = Class              #8            // os/PathChunk
   #10 = Utf8               RelPathChunk
   #11 = Utf8               os/makeDir$all$
   #12 = Class              #11           // os/makeDir$all$
   #13 = Utf8               os/makeDir
   #14 = Class              #13           // os/makeDir
   #15 = Utf8               all$
   #16 = Utf8               scala/collection/JavaConverters$AsJava
   #17 = Class              #16           // scala/collection/JavaConverters$AsJava
   #18 = Utf8               scala/collection/JavaConverters
   #19 = Class              #18           // scala/collection/JavaConverters
   #20 = Utf8               AsJava
   #21 = Utf8               MODULE$
   #22 = Utf8               Los/write$;
   #23 = Utf8               <clinit>
   #24 = Utf8               ()V
   #25 = Utf8               <init>
   #26 = NameAndType        #25:#24       // "<init>":()V
   #27 = Methodref          #2.#26        // os/write$."<init>":()V
   #28 = NameAndType        #21:#22       // MODULE$:Los/write$;
   #29 = Fieldref           #2.#28        // os/write$.MODULE$:Los/write$;
   #30 = Utf8               outputStream
   #31 = Utf8               (Los/Path;Los/PermSet;ZLscala/collection/immutable/Seq;)Ljava/io/OutputStream;
   #32 = Utf8               (Los/Path;Los/PermSet;ZLscala/collection/immutable/Seq<Ljava/nio/file/OpenOption;>;)Ljava/io/OutputStream;
   #33 = Utf8               target
   #34 = Utf8               perms
   #35 = Utf8               createFolders
   #36 = Utf8               openOptions
   #37 = Utf8               Los/makeDir$all$;
   #38 = NameAndType        #21:#37       // MODULE$:Los/makeDir$all$;
   #39 = Fieldref           #12.#38       // os/makeDir$all$.MODULE$:Los/makeDir$all$;
   #40 = Utf8               os/PathChunk$
   #41 = Class              #40           // os/PathChunk$
   #42 = Utf8               Los/PathChunk$;
   #43 = NameAndType        #21:#42       // MODULE$:Los/PathChunk$;
   #44 = Fieldref           #41.#43       // os/PathChunk$.MODULE$:Los/PathChunk$;
   #45 = Utf8               os/RelPath$
   #46 = Class              #45           // os/RelPath$
   #47 = Utf8               Los/RelPath$;
   #48 = NameAndType        #21:#47       // MODULE$:Los/RelPath$;
   #49 = Fieldref           #46.#48       // os/RelPath$.MODULE$:Los/RelPath$;
   #50 = Utf8               up
   #51 = Utf8               ()Los/RelPath;
   #52 = NameAndType        #50:#51       // up:()Los/RelPath;
   #53 = Methodref          #46.#52       // os/RelPath$.up:()Los/RelPath;
   #54 = Utf8               (Los/RelPath;)Los/PathChunk$RelPathChunk;
   #55 = NameAndType        #10:#54       // RelPathChunk:(Los/RelPath;)Los/PathChunk$RelPathChunk;
   #56 = Methodref          #41.#55       // os/PathChunk$.RelPathChunk:(Los/RelPath;)Los/PathChunk$RelPathChunk;
   #57 = Utf8               os/Path
   #58 = Class              #57           // os/Path
   #59 = Utf8               $div
   #60 = Utf8               (Los/PathChunk;)Los/Path;
   #61 = NameAndType        #59:#60       // $div:(Los/PathChunk;)Los/Path;
   #62 = Methodref          #58.#61       // os/Path.$div:(Los/PathChunk;)Los/Path;
   #63 = Utf8               apply$default$3
   #64 = Utf8               ()Z
   #65 = NameAndType        #63:#64       // apply$default$3:()Z
   #66 = Methodref          #12.#65       // os/makeDir$all$.apply$default$3:()Z
   #67 = Utf8               apply
   #68 = Utf8               (Los/Path;Los/PermSet;Z)V
   #69 = NameAndType        #67:#68       // apply:(Los/Path;Los/PermSet;Z)V
   #70 = Methodref          #12.#69       // os/makeDir$all$.apply:(Los/Path;Los/PermSet;Z)V
   #71 = Utf8               os/exists$
   #72 = Class              #71           // os/exists$
   #73 = Utf8               Los/exists$;
   #74 = NameAndType        #21:#73       // MODULE$:Los/exists$;
   #75 = Fieldref           #72.#74       // os/exists$.MODULE$:Los/exists$;
   #76 = Utf8               (Los/Path;)Z
   #77 = NameAndType        #67:#76       // apply:(Los/Path;)Z
   #78 = Methodref          #72.#77       // os/exists$.apply:(Los/Path;)Z
   #79 = Utf8               scala/Array$
   #80 = Class              #79           // scala/Array$
   #81 = Utf8               Lscala/Array$;
   #82 = NameAndType        #21:#81       // MODULE$:Lscala/Array$;
   #83 = Fieldref           #80.#82       // scala/Array$.MODULE$:Lscala/Array$;
   #84 = Utf8               scala/collection/immutable/Nil$
   #85 = Class              #84           // scala/collection/immutable/Nil$
   #86 = Utf8               Lscala/collection/immutable/Nil$;
   #87 = NameAndType        #21:#86       // MODULE$:Lscala/collection/immutable/Nil$;
   #88 = Fieldref           #85.#87       // scala/collection/immutable/Nil$.MODULE$:Lscala/collection/immutable/Nil$;
   #89 = Utf8               scala/reflect/ClassTag$
   #90 = Class              #89           // scala/reflect/ClassTag$
   #91 = Utf8               Lscala/reflect/ClassTag$;
   #92 = NameAndType        #21:#91       // MODULE$:Lscala/reflect/ClassTag$;
   #93 = Fieldref           #90.#92       // scala/reflect/ClassTag$.MODULE$:Lscala/reflect/ClassTag$;
   #94 = Utf8               java/nio/file/attribute/FileAttribute
   #95 = Class              #94           // java/nio/file/attribute/FileAttribute
   #96 = Utf8               (Ljava/lang/Class;)Lscala/reflect/ClassTag;
   #97 = NameAndType        #67:#96       // apply:(Ljava/lang/Class;)Lscala/reflect/ClassTag;
   #98 = Methodref          #90.#97       // scala/reflect/ClassTag$.apply:(Ljava/lang/Class;)Lscala/reflect/ClassTag;
   #99 = Utf8               (Lscala/collection/immutable/Seq;Lscala/reflect/ClassTag;)Ljava/lang/Object;
  #100 = NameAndType        #67:#99       // apply:(Lscala/collection/immutable/Seq;Lscala/reflect/ClassTag;)Ljava/lang/Object;
  #101 = Methodref          #80.#100      // scala/Array$.apply:(Lscala/collection/immutable/Seq;Lscala/reflect/ClassTag;)Ljava/lang/Object;
  #102 = Utf8               [Ljava/nio/file/attribute/FileAttribute;
  #103 = Class              #102          // "[Ljava/nio/file/attribute/FileAttribute;"
  #104 = Utf8               os/PermSet
  #105 = Class              #104          // os/PermSet
  #106 = Utf8               toSet
  #107 = Utf8               ()Ljava/util/Set;
  #108 = NameAndType        #106:#107     // toSet:()Ljava/util/Set;
  #109 = Methodref          #105.#108     // os/PermSet.toSet:()Ljava/util/Set;
  #110 = Utf8               java/nio/file/attribute/PosixFilePermissions
  #111 = Class              #110          // java/nio/file/attribute/PosixFilePermissions
  #112 = Utf8               asFileAttribute
  #113 = Utf8               (Ljava/util/Set;)Ljava/nio/file/attribute/FileAttribute;
  #114 = NameAndType        #112:#113     // asFileAttribute:(Ljava/util/Set;)Ljava/nio/file/attribute/FileAttribute;
  #115 = Methodref          #111.#114     // java/nio/file/attribute/PosixFilePermissions.asFileAttribute:(Ljava/util/Set;)Ljava/nio/file/attribute/FileAttribute;
  #116 = Utf8               [Ljava/lang/Object;
  #117 = Class              #116          // "[Ljava/lang/Object;"
  #118 = Utf8               toNIO
  #119 = Utf8               ()Ljava/nio/file/Path;
  #120 = NameAndType        #118:#119     // toNIO:()Ljava/nio/file/Path;
  #121 = Methodref          #58.#120      // os/Path.toNIO:()Ljava/nio/file/Path;
  #122 = Utf8               java/nio/file/Files
  #123 = Class              #122          // java/nio/file/Files
  #124 = Utf8               createFile
  #125 = Utf8               (Ljava/nio/file/Path;[Ljava/nio/file/attribute/FileAttribute;)Ljava/nio/file/Path;
  #126 = NameAndType        #124:#125     // createFile:(Ljava/nio/file/Path;[Ljava/nio/file/attribute/FileAttribute;)Ljava/nio/file/Path;
  #127 = Methodref          #123.#126     // java/nio/file/Files.createFile:(Ljava/nio/file/Path;[Ljava/nio/file/attribute/FileAttribute;)Ljava/nio/file/Path;
  #128 = Utf8               scala/runtime/BoxedUnit
  #129 = Class              #128          // scala/runtime/BoxedUnit
  #130 = Utf8               UNIT
  #131 = Utf8               Lscala/runtime/BoxedUnit;
  #132 = NameAndType        #130:#131     // UNIT:Lscala/runtime/BoxedUnit;
  #133 = Fieldref           #129.#132     // scala/runtime/BoxedUnit.UNIT:Lscala/runtime/BoxedUnit;
  #134 = Utf8               java/nio/file/OpenOption
  #135 = Class              #134          // java/nio/file/OpenOption
  #136 = Utf8               scala/collection/immutable/Seq
  #137 = Class              #136          // scala/collection/immutable/Seq
  #138 = Utf8               toArray
  #139 = Utf8               (Lscala/reflect/ClassTag;)Ljava/lang/Object;
  #140 = NameAndType        #138:#139     // toArray:(Lscala/reflect/ClassTag;)Ljava/lang/Object;
  #141 = InterfaceMethodref #137.#140     // scala/collection/immutable/Seq.toArray:(Lscala/reflect/ClassTag;)Ljava/lang/Object;
  #142 = Utf8               [Ljava/nio/file/OpenOption;
  #143 = Class              #142          // "[Ljava/nio/file/OpenOption;"
  #144 = Utf8               newOutputStream
  #145 = Utf8               (Ljava/nio/file/Path;[Ljava/nio/file/OpenOption;)Ljava/io/OutputStream;
  #146 = NameAndType        #144:#145     // newOutputStream:(Ljava/nio/file/Path;[Ljava/nio/file/OpenOption;)Ljava/io/OutputStream;
  #147 = Methodref          #123.#146     // java/nio/file/Files.newOutputStream:(Ljava/nio/file/Path;[Ljava/nio/file/OpenOption;)Ljava/io/OutputStream;
  #148 = Utf8               permArray
  #149 = Utf8               this
  #150 = Utf8               Los/Path;
  #151 = Utf8               Los/PermSet;
  #152 = Utf8               Z
  #153 = Utf8               Lscala/collection/immutable/Seq;
  #154 = Utf8               outputStream$default$2
  #155 = Utf8               ()Los/PermSet;
  #156 = Utf8               outputStream$default$3
  #157 = Utf8               outputStream$default$4
  #158 = Utf8               ()Lscala/collection/immutable/Seq;
  #159 = Utf8               ()Lscala/collection/immutable/Seq<Ljava/nio/file/OpenOption;>;
  #160 = Utf8               scala/package$
  #161 = Class              #160          // scala/package$
  #162 = Utf8               Lscala/package$;
  #163 = NameAndType        #21:#162      // MODULE$:Lscala/package$;
  #164 = Fieldref           #161.#163     // scala/package$.MODULE$:Lscala/package$;
  #165 = Utf8               Seq
  #166 = Utf8               ()Lscala/collection/immutable/Seq$;
  #167 = NameAndType        #165:#166     // Seq:()Lscala/collection/immutable/Seq$;
  #168 = Methodref          #161.#167     // scala/package$.Seq:()Lscala/collection/immutable/Seq$;
  #169 = Utf8               scala/runtime/ScalaRunTime$
  #170 = Class              #169          // scala/runtime/ScalaRunTime$
  #171 = Utf8               Lscala/runtime/ScalaRunTime$;
  #172 = NameAndType        #21:#171      // MODULE$:Lscala/runtime/ScalaRunTime$;
  #173 = Fieldref           #170.#172     // scala/runtime/ScalaRunTime$.MODULE$:Lscala/runtime/ScalaRunTime$;
  #174 = Utf8               java/nio/file/StandardOpenOption
  #175 = Class              #174          // java/nio/file/StandardOpenOption
  #176 = Utf8               CREATE
  #177 = Utf8               Ljava/nio/file/StandardOpenOption;
  #178 = NameAndType        #176:#177     // CREATE:Ljava/nio/file/StandardOpenOption;
  #179 = Fieldref           #175.#178     // java/nio/file/StandardOpenOption.CREATE:Ljava/nio/file/StandardOpenOption;
  #180 = Utf8               WRITE
  #181 = NameAndType        #180:#177     // WRITE:Ljava/nio/file/StandardOpenOption;
  #182 = Fieldref           #175.#181     // java/nio/file/StandardOpenOption.WRITE:Ljava/nio/file/StandardOpenOption;
  #183 = Utf8               wrapRefArray
  #184 = Utf8               ([Ljava/lang/Object;)Lscala/collection/immutable/ArraySeq;
  #185 = NameAndType        #183:#184     // wrapRefArray:([Ljava/lang/Object;)Lscala/collection/immutable/ArraySeq;
  #186 = Methodref          #170.#185     // scala/runtime/ScalaRunTime$.wrapRefArray:([Ljava/lang/Object;)Lscala/collection/immutable/ArraySeq;
  #187 = Utf8               scala/collection/immutable/Seq$
  #188 = Class              #187          // scala/collection/immutable/Seq$
  #189 = Utf8               (Lscala/collection/immutable/Seq;)Lscala/collection/SeqOps;
  #190 = NameAndType        #67:#189      // apply:(Lscala/collection/immutable/Seq;)Lscala/collection/SeqOps;
  #191 = Methodref          #188.#190     // scala/collection/immutable/Seq$.apply:(Lscala/collection/immutable/Seq;)Lscala/collection/SeqOps;
  #192 = Utf8               write
  #193 = Utf8               (Los/Path;Los/Source;Lscala/collection/immutable/Seq;Los/PermSet;J)Ljava/lang/Object;
  #194 = Utf8               (Los/Path;Los/Source;Lscala/collection/immutable/Seq<Ljava/nio/file/StandardOpenOption;>;Los/PermSet;J)Ljava/lang/Object;
  #195 = Utf8               data
  #196 = Utf8               flags
  #197 = Utf8               offset
  #198 = Utf8               empty
  #199 = NameAndType        #198:#139     // empty:(Lscala/reflect/ClassTag;)Ljava/lang/Object;
  #200 = Methodref          #80.#199      // scala/Array$.empty:(Lscala/reflect/ClassTag;)Ljava/lang/Object;
  #201 = Utf8               wrapped
  #202 = NameAndType        #201:#119     // wrapped:()Ljava/nio/file/Path;
  #203 = Methodref          #58.#202      // os/Path.wrapped:()Ljava/nio/file/Path;
  #204 = Utf8               scala/collection/JavaConverters$
  #205 = Class              #204          // scala/collection/JavaConverters$
  #206 = Utf8               Lscala/collection/JavaConverters$;
  #207 = NameAndType        #21:#206      // MODULE$:Lscala/collection/JavaConverters$;
  #208 = Fieldref           #205.#207     // scala/collection/JavaConverters$.MODULE$:Lscala/collection/JavaConverters$;
  #209 = Utf8               ()Lscala/collection/immutable/Set;
  #210 = NameAndType        #106:#209     // toSet:()Lscala/collection/immutable/Set;
  #211 = InterfaceMethodref #137.#210     // scala/collection/immutable/Seq.toSet:()Lscala/collection/immutable/Set;
  #212 = Utf8               setAsJavaSetConverter
  #213 = Utf8               (Lscala/collection/Set;)Lscala/collection/JavaConverters$AsJava;
  #214 = NameAndType        #212:#213     // setAsJavaSetConverter:(Lscala/collection/Set;)Lscala/collection/JavaConverters$AsJava;
  #215 = Methodref          #205.#214     // scala/collection/JavaConverters$.setAsJavaSetConverter:(Lscala/collection/Set;)Lscala/collection/JavaConverters$AsJava;
  #216 = Utf8               asJava
  #217 = Utf8               ()Ljava/lang/Object;
  #218 = NameAndType        #216:#217     // asJava:()Ljava/lang/Object;
  #219 = Methodref          #17.#218      // scala/collection/JavaConverters$AsJava.asJava:()Ljava/lang/Object;
  #220 = Utf8               java/util/Set
  #221 = Class              #220          // java/util/Set
  #222 = Utf8               newByteChannel
  #223 = Utf8               (Ljava/nio/file/Path;Ljava/util/Set;[Ljava/nio/file/attribute/FileAttribute;)Ljava/nio/channels/SeekableByteChannel;
  #224 = NameAndType        #222:#223     // newByteChannel:(Ljava/nio/file/Path;Ljava/util/Set;[Ljava/nio/file/attribute/FileAttribute;)Ljava/nio/channels/SeekableByteChannel;
  #225 = Methodref          #123.#224     // java/nio/file/Files.newByteChannel:(Ljava/nio/file/Path;Ljava/util/Set;[Ljava/nio/file/attribute/FileAttribute;)Ljava/nio/channels/SeekableByteChannel;
  #226 = Utf8               java/nio/channels/SeekableByteChannel
  #227 = Class              #226          // java/nio/channels/SeekableByteChannel
  #228 = Utf8               position
  #229 = Utf8               (J)Ljava/nio/channels/SeekableByteChannel;
  #230 = NameAndType        #228:#229     // position:(J)Ljava/nio/channels/SeekableByteChannel;
  #231 = InterfaceMethodref #227.#230     // java/nio/channels/SeekableByteChannel.position:(J)Ljava/nio/channels/SeekableByteChannel;
  #232 = Utf8               os/Source
  #233 = Class              #232          // os/Source
  #234 = Utf8               writeBytesTo
  #235 = Utf8               (Ljava/nio/channels/WritableByteChannel;)Ljava/lang/Object;
  #236 = NameAndType        #234:#235     // writeBytesTo:(Ljava/nio/channels/WritableByteChannel;)Ljava/lang/Object;
  #237 = InterfaceMethodref #233.#236     // os/Source.writeBytesTo:(Ljava/nio/channels/WritableByteChannel;)Ljava/lang/Object;
  #238 = Utf8               close
  #239 = NameAndType        #238:#24      // close:()V
  #240 = InterfaceMethodref #227.#239     // java/nio/channels/SeekableByteChannel.close:()V
  #241 = Utf8               out
  #242 = Utf8               Ljava/nio/channels/SeekableByteChannel;
  #243 = Utf8               Los/Source;
  #244 = Utf8               J
  #245 = Utf8               java/lang/Throwable
  #246 = Class              #245          // java/lang/Throwable
  #247 = Utf8               (Los/Path;Los/Source;Los/PermSet;Z)V
  #248 = Utf8               CREATE_NEW
  #249 = NameAndType        #248:#177     // CREATE_NEW:Ljava/nio/file/StandardOpenOption;
  #250 = Fieldref           #175.#249     // java/nio/file/StandardOpenOption.CREATE_NEW:Ljava/nio/file/StandardOpenOption;
  #251 = NameAndType        #192:#193     // write:(Los/Path;Los/Source;Lscala/collection/immutable/Seq;Los/PermSet;J)Ljava/lang/Object;
  #252 = Methodref          #2.#251       // os/write$.write:(Los/Path;Los/Source;Lscala/collection/immutable/Seq;Los/PermSet;J)Ljava/lang/Object;
  #253 = Utf8               apply$default$4
  #254 = Methodref          #4.#26        // java/lang/Object."<init>":()V
  #255 = Utf8               Code
  #256 = Utf8               LineNumberTable
  #257 = Utf8               StackMapTable
  #258 = Utf8               LocalVariableTable
  #259 = Utf8               Signature
  #260 = Utf8               MethodParameters
  #261 = Utf8               InnerClasses
  #262 = Utf8               SourceFile
  #263 = Utf8               ScalaInlineInfo
  #264 = Utf8               Scala
{
  public static final os.write$ MODULE$;
    descriptor: Los/write$;
    flags: (0x0019) ACC_PUBLIC, ACC_STATIC, ACC_FINAL

  public static {};
    descriptor: ()V
    flags: (0x0009) ACC_PUBLIC, ACC_STATIC
    Code:
      stack=2, locals=0, args_size=0
         0: new           #2                  // class os/write$
         3: dup
         4: invokespecial #27                 // Method "<init>":()V
         7: putstatic     #29                 // Field MODULE$:Los/write$;
        10: return
      LineNumberTable:
        line 19: 0

  public java.io.OutputStream outputStream(os.Path, os.PermSet, boolean, scala.collection.immutable.Seq<java.nio.file.OpenOption>);
    descriptor: (Los/Path;Los/PermSet;ZLscala/collection/immutable/Seq;)Ljava/io/OutputStream;
    flags: (0x0001) ACC_PUBLIC
    Code:
      stack=4, locals=6, args_size=5
         0: iload_3
         1: ifeq          36
         4: getstatic     #39                 // Field os/makeDir$all$.MODULE$:Los/makeDir$all$;
         7: aload_1
         8: getstatic     #44                 // Field os/PathChunk$.MODULE$:Los/PathChunk$;
        11: getstatic     #49                 // Field os/RelPath$.MODULE$:Los/RelPath$;
        14: invokevirtual #53                 // Method os/RelPath$.up:()Los/RelPath;
        17: invokevirtual #56                 // Method os/PathChunk$.RelPathChunk:(Los/RelPath;)Los/PathChunk$RelPathChunk;
        20: invokevirtual #62                 // Method os/Path.$div:(Los/PathChunk;)Los/Path;
        23: aload_2
        24: getstatic     #39                 // Field os/makeDir$all$.MODULE$:Los/makeDir$all$;
        27: invokevirtual #66                 // Method os/makeDir$all$.apply$default$3:()Z
        30: invokevirtual #70                 // Method os/makeDir$all$.apply:(Los/Path;Los/PermSet;Z)V
        33: goto          36
        36: aload_2
        37: ifnull        111
        40: getstatic     #75                 // Field os/exists$.MODULE$:Los/exists$;
        43: aload_1
        44: invokevirtual #78                 // Method os/exists$.apply:(Los/Path;)Z
        47: ifne          111
        50: aload_2
        51: ifnonnull     77
        54: getstatic     #83                 // Field scala/Array$.MODULE$:Lscala/Array$;
        57: getstatic     #88                 // Field scala/collection/immutable/Nil$.MODULE$:Lscala/collection/immutable/Nil$;
        60: getstatic     #93                 // Field scala/reflect/ClassTag$.MODULE$:Lscala/reflect/ClassTag$;
        63: ldc           #95                 // class java/nio/file/attribute/FileAttribute
        65: invokevirtual #98                 // Method scala/reflect/ClassTag$.apply:(Ljava/lang/Class;)Lscala/reflect/ClassTag;
        68: invokevirtual #101                // Method scala/Array$.apply:(Lscala/collection/immutable/Seq;Lscala/reflect/ClassTag;)Ljava/lang/Object;
        71: checkcast     #103                // class "[Ljava/nio/file/attribute/FileAttribute;"
        74: goto          97
        77: iconst_1
        78: anewarray     #95                 // class java/nio/file/attribute/FileAttribute
        81: dup
        82: iconst_0
        83: aload_2
        84: invokevirtual #109                // Method os/PermSet.toSet:()Ljava/util/Set;
        87: invokestatic  #115                // Method java/nio/file/attribute/PosixFilePermissions.asFileAttribute:(Ljava/util/Set;)Ljava/nio/file/attribute/FileAttribute;
        90: aastore
        91: checkcast     #117                // class "[Ljava/lang/Object;"
        94: checkcast     #103                // class "[Ljava/nio/file/attribute/FileAttribute;"
        97: astore        5
        99: aload_1
       100: invokevirtual #121                // Method os/Path.toNIO:()Ljava/nio/file/Path;
       103: aload         5
       105: invokestatic  #127                // Method java/nio/file/Files.createFile:(Ljava/nio/file/Path;[Ljava/nio/file/attribute/FileAttribute;)Ljava/nio/file/Path;
       108: goto          114
       111: getstatic     #133                // Field scala/runtime/BoxedUnit.UNIT:Lscala/runtime/BoxedUnit;
       114: pop
       115: aload_1
       116: invokevirtual #121                // Method os/Path.toNIO:()Ljava/nio/file/Path;
       119: aload         4
       121: getstatic     #93                 // Field scala/reflect/ClassTag$.MODULE$:Lscala/reflect/ClassTag$;
       124: ldc           #135                // class java/nio/file/OpenOption
       126: invokevirtual #98                 // Method scala/reflect/ClassTag$.apply:(Ljava/lang/Class;)Lscala/reflect/ClassTag;
       129: invokeinterface #141,  2          // InterfaceMethod scala/collection/immutable/Seq.toArray:(Lscala/reflect/ClassTag;)Ljava/lang/Object;
       134: checkcast     #143                // class "[Ljava/nio/file/OpenOption;"
       137: invokestatic  #147                // Method java/nio/file/Files.newOutputStream:(Ljava/nio/file/Path;[Ljava/nio/file/OpenOption;)Ljava/io/OutputStream;
       140: areturn
      StackMapTable: number_of_entries = 5
        frame_type = 36 /* same */
        frame_type = 40 /* same */
        frame_type = 83 /* same_locals_1_stack_item */
          stack = [ class "[Ljava/nio/file/attribute/FileAttribute;" ]
        frame_type = 13 /* same */
        frame_type = 66 /* same_locals_1_stack_item */
          stack = [ class java/lang/Object ]
      LineNumberTable:
        line 27: 0
        line 28: 36
        line 30: 50
        line 31: 77
        line 32: 99
        line 28: 111
        line 35: 115
        line 36: 119
      LocalVariableTable:
        Start  Length  Slot  Name   Signature
           99       9     5 permArray   [Ljava/nio/file/attribute/FileAttribute;
            0     141     0  this   Los/write$;
            0     141     1 target   Los/Path;
            0     141     2 perms   Los/PermSet;
            0     141     3 createFolders   Z
            0     141     4 openOptions   Lscala/collection/immutable/Seq;
    Signature: #32                          // (Los/Path;Los/PermSet;ZLscala/collection/immutable/Seq<Ljava/nio/file/OpenOption;>;)Ljava/io/OutputStream;
    MethodParameters:
      Name                           Flags
      target                         final
      perms                          final
      createFolders                  final
      openOptions                    final

  public os.PermSet outputStream$default$2();
    descriptor: ()Los/PermSet;
    flags: (0x0001) ACC_PUBLIC
    Code:
      stack=1, locals=1, args_size=1
         0: aconst_null
         1: areturn
      LineNumberTable:
        line 24: 0
      LocalVariableTable:
        Start  Length  Slot  Name   Signature
            0       2     0  this   Los/write$;

  public boolean outputStream$default$3();
    descriptor: ()Z
    flags: (0x0001) ACC_PUBLIC
    Code:
      stack=1, locals=1, args_size=1
         0: iconst_0
         1: ireturn
      LineNumberTable:
        line 25: 0
      LocalVariableTable:
        Start  Length  Slot  Name   Signature
            0       2     0  this   Los/write$;

  public scala.collection.immutable.Seq<java.nio.file.OpenOption> outputStream$default$4();
    descriptor: ()Lscala/collection/immutable/Seq;
    flags: (0x0001) ACC_PUBLIC
    Code:
      stack=6, locals=1, args_size=1
         0: getstatic     #164                // Field scala/package$.MODULE$:Lscala/package$;
         3: invokevirtual #168                // Method scala/package$.Seq:()Lscala/collection/immutable/Seq$;
         6: getstatic     #173                // Field scala/runtime/ScalaRunTime$.MODULE$:Lscala/runtime/ScalaRunTime$;
         9: iconst_2
        10: anewarray     #175                // class java/nio/file/StandardOpenOption
        13: dup
        14: iconst_0
        15: getstatic     #179                // Field java/nio/file/StandardOpenOption.CREATE:Ljava/nio/file/StandardOpenOption;
        18: aastore
        19: dup
        20: iconst_1
        21: getstatic     #182                // Field java/nio/file/StandardOpenOption.WRITE:Ljava/nio/file/StandardOpenOption;
        24: aastore
        25: checkcast     #117                // class "[Ljava/lang/Object;"
        28: invokevirtual #186                // Method scala/runtime/ScalaRunTime$.wrapRefArray:([Ljava/lang/Object;)Lscala/collection/immutable/ArraySeq;
        31: invokevirtual #191                // Method scala/collection/immutable/Seq$.apply:(Lscala/collection/immutable/Seq;)Lscala/collection/SeqOps;
        34: checkcast     #137                // class scala/collection/immutable/Seq
        37: areturn
      LineNumberTable:
        line 26: 0
      LocalVariableTable:
        Start  Length  Slot  Name   Signature
            0      38     0  this   Los/write$;
    Signature: #159                         // ()Lscala/collection/immutable/Seq<Ljava/nio/file/OpenOption;>;

  public java.lang.Object write(os.Path, os.Source, scala.collection.immutable.Seq<java.nio.file.StandardOpenOption>, os.PermSet, long);
    descriptor: (Los/Path;Los/Source;Lscala/collection/immutable/Seq;Los/PermSet;J)Ljava/lang/Object;
    flags: (0x0001) ACC_PUBLIC
    Code:
      stack=4, locals=10, args_size=6
         0: aload         4
         2: ifnonnull     25
         5: getstatic     #83                 // Field scala/Array$.MODULE$:Lscala/Array$;
         8: getstatic     #93                 // Field scala/reflect/ClassTag$.MODULE$:Lscala/reflect/ClassTag$;
        11: ldc           #95                 // class java/nio/file/attribute/FileAttribute
        13: invokevirtual #98                 // Method scala/reflect/ClassTag$.apply:(Ljava/lang/Class;)Lscala/reflect/ClassTag;
        16: invokevirtual #200                // Method scala/Array$.empty:(Lscala/reflect/ClassTag;)Ljava/lang/Object;
        19: checkcast     #103                // class "[Ljava/nio/file/attribute/FileAttribute;"
        22: goto          46
        25: iconst_1
        26: anewarray     #95                 // class java/nio/file/attribute/FileAttribute
        29: dup
        30: iconst_0
        31: aload         4
        33: invokevirtual #109                // Method os/PermSet.toSet:()Ljava/util/Set;
        36: invokestatic  #115                // Method java/nio/file/attribute/PosixFilePermissions.asFileAttribute:(Ljava/util/Set;)Ljava/nio/file/attribute/FileAttribute;
        39: aastore
        40: checkcast     #117                // class "[Ljava/lang/Object;"
        43: checkcast     #103                // class "[Ljava/nio/file/attribute/FileAttribute;"
        46: astore        7
        48: aload_1
        49: invokevirtual #203                // Method os/Path.wrapped:()Ljava/nio/file/Path;
        52: getstatic     #208                // Field scala/collection/JavaConverters$.MODULE$:Lscala/collection/JavaConverters$;
        55: aload_3
        56: invokeinterface #211,  1          // InterfaceMethod scala/collection/immutable/Seq.toSet:()Lscala/collection/immutable/Set;
        61: invokevirtual #215                // Method scala/collection/JavaConverters$.setAsJavaSetConverter:(Lscala/collection/Set;)Lscala/collection/JavaConverters$AsJava;
        64: invokevirtual #219                // Method scala/collection/JavaConverters$AsJava.asJava:()Ljava/lang/Object;
        67: checkcast     #221                // class java/util/Set
        70: aload         7
        72: invokestatic  #225                // Method java/nio/file/Files.newByteChannel:(Ljava/nio/file/Path;Ljava/util/Set;[Ljava/nio/file/attribute/FileAttribute;)Ljava/nio/channels/SeekableByteChannel;
        75: astore        8
        77: aload         8
        79: lload         5
        81: invokeinterface #231,  3          // InterfaceMethod java/nio/channels/SeekableByteChannel.position:(J)Ljava/nio/channels/SeekableByteChannel;
        86: pop
        87: aload_2
        88: aload         8
        90: invokeinterface #237,  2          // InterfaceMethod os/Source.writeBytesTo:(Ljava/nio/channels/WritableByteChannel;)Ljava/lang/Object;
        95: goto          118
        98: astore        9
       100: aload         8
       102: ifnull        115
       105: aload         8
       107: invokeinterface #240,  1          // InterfaceMethod java/nio/channels/SeekableByteChannel.close:()V
       112: goto          115
       115: aload         9
       117: athrow
       118: aload         8
       120: ifnull        133
       123: aload         8
       125: invokeinterface #240,  1          // InterfaceMethod java/nio/channels/SeekableByteChannel.close:()V
       130: goto          133
       133: areturn
      Exception table:
         from    to  target type
            87    98    98   any
      StackMapTable: number_of_entries = 6
        frame_type = 25 /* same */
        frame_type = 84 /* same_locals_1_stack_item */
          stack = [ class "[Ljava/nio/file/attribute/FileAttribute;" ]
        frame_type = 255 /* full_frame */
          offset_delta = 51
          locals = [ class os/write$, class os/Path, class os/Source, class scala/collection/immutable/Seq, class os/PermSet, long, class "[Ljava/nio/file/attribute/FileAttribute;", class java/nio/channels/SeekableByteChannel ]
          stack = [ class java/lang/Throwable ]
        frame_type = 252 /* append */
          offset_delta = 16
          locals = [ class java/lang/Throwable ]
        frame_type = 255 /* full_frame */
          offset_delta = 2
          locals = [ class os/write$, class os/Path, class os/Source, class scala/collection/immutable/Seq, class os/PermSet, long, class "[Ljava/nio/file/attribute/FileAttribute;", class java/nio/channels/SeekableByteChannel ]
          stack = [ class java/lang/Object ]
        frame_type = 78 /* same_locals_1_stack_item */
          stack = [ class java/lang/Object ]
      LineNumberTable:
        line 53: 0
        line 54: 25
        line 57: 48
        line 58: 52
        line 59: 70
        line 61: 77
        line 62: 87
        line 63: 100
      LocalVariableTable:
        Start  Length  Slot  Name   Signature
           48      85     7 permArray   [Ljava/nio/file/attribute/FileAttribute;
           77      56     8   out   Ljava/nio/channels/SeekableByteChannel;
            0     134     0  this   Los/write$;
            0     134     1 target   Los/Path;
            0     134     2  data   Los/Source;
            0     134     3 flags   Lscala/collection/immutable/Seq;
            0     134     4 perms   Los/PermSet;
            0     134     5 offset   J
    Signature: #194                         // (Los/Path;Los/Source;Lscala/collection/immutable/Seq<Ljava/nio/file/StandardOpenOption;>;Los/PermSet;J)Ljava/lang/Object;
    MethodParameters:
      Name                           Flags
      target                         final
      data                           final
      flags                          final
      perms                          final
      offset                         final

  public void apply(os.Path, os.Source, os.PermSet, boolean);
    descriptor: (Los/Path;Los/Source;Los/PermSet;Z)V
    flags: (0x0001) ACC_PUBLIC
    Code:
      stack=9, locals=5, args_size=5
         0: iload         4
         2: ifeq          37
         5: getstatic     #39                 // Field os/makeDir$all$.MODULE$:Los/makeDir$all$;
         8: aload_1
         9: getstatic     #44                 // Field os/PathChunk$.MODULE$:Los/PathChunk$;
        12: getstatic     #49                 // Field os/RelPath$.MODULE$:Los/RelPath$;
        15: invokevirtual #53                 // Method os/RelPath$.up:()Los/RelPath;
        18: invokevirtual #56                 // Method os/PathChunk$.RelPathChunk:(Los/RelPath;)Los/PathChunk$RelPathChunk;
        21: invokevirtual #62                 // Method os/Path.$div:(Los/PathChunk;)Los/Path;
        24: aload_3
        25: getstatic     #39                 // Field os/makeDir$all$.MODULE$:Los/makeDir$all$;
        28: invokevirtual #66                 // Method os/makeDir$all$.apply$default$3:()Z
        31: invokevirtual #70                 // Method os/makeDir$all$.apply:(Los/Path;Los/PermSet;Z)V
        34: goto          37
        37: aload_0
        38: aload_1
        39: aload_2
        40: getstatic     #164                // Field scala/package$.MODULE$:Lscala/package$;
        43: invokevirtual #168                // Method scala/package$.Seq:()Lscala/collection/immutable/Seq$;
        46: getstatic     #173                // Field scala/runtime/ScalaRunTime$.MODULE$:Lscala/runtime/ScalaRunTime$;
        49: iconst_2
        50: anewarray     #175                // class java/nio/file/StandardOpenOption
        53: dup
        54: iconst_0
        55: getstatic     #250                // Field java/nio/file/StandardOpenOption.CREATE_NEW:Ljava/nio/file/StandardOpenOption;
        58: aastore
        59: dup
        60: iconst_1
        61: getstatic     #182                // Field java/nio/file/StandardOpenOption.WRITE:Ljava/nio/file/StandardOpenOption;
        64: aastore
        65: checkcast     #117                // class "[Ljava/lang/Object;"
        68: invokevirtual #186                // Method scala/runtime/ScalaRunTime$.wrapRefArray:([Ljava/lang/Object;)Lscala/collection/immutable/ArraySeq;
        71: invokevirtual #191                // Method scala/collection/immutable/Seq$.apply:(Lscala/collection/immutable/Seq;)Lscala/collection/SeqOps;
        74: checkcast     #137                // class scala/collection/immutable/Seq
        77: aload_3
        78: lconst_0
        79: invokevirtual #252                // Method write:(Los/Path;Los/Source;Lscala/collection/immutable/Seq;Los/PermSet;J)Ljava/lang/Object;
        82: pop
        83: return
      StackMapTable: number_of_entries = 1
        frame_type = 37 /* same */
      LineNumberTable:
        line 69: 0
        line 70: 37
      LocalVariableTable:
        Start  Length  Slot  Name   Signature
            0      84     0  this   Los/write$;
            0      84     1 target   Los/Path;
            0      84     2  data   Los/Source;
            0      84     3 perms   Los/PermSet;
            0      84     4 createFolders   Z
    MethodParameters:
      Name                           Flags
      target                         final
      data                           final
      perms                          final
      createFolders                  final

  public os.PermSet apply$default$3();
    descriptor: ()Los/PermSet;
    flags: (0x0001) ACC_PUBLIC
    Code:
      stack=1, locals=1, args_size=1
         0: aconst_null
         1: areturn
      LineNumberTable:
        line 67: 0
      LocalVariableTable:
        Start  Length  Slot  Name   Signature
            0       2     0  this   Los/write$;

  public boolean apply$default$4();
    descriptor: ()Z
    flags: (0x0001) ACC_PUBLIC
    Code:
      stack=1, locals=1, args_size=1
         0: iconst_0
         1: ireturn
      LineNumberTable:
        line 68: 0
      LocalVariableTable:
        Start  Length  Slot  Name   Signature
            0       2     0  this   Los/write$;

  private os.write$();
    descriptor: ()V
    flags: (0x0002) ACC_PRIVATE
    Code:
      stack=1, locals=1, args_size=1
         0: aload_0
         1: invokespecial #254                // Method java/lang/Object."<init>":()V
         4: return
      LineNumberTable:
        line 199: 0
        line 19: 4
      LocalVariableTable:
        Start  Length  Slot  Name   Signature
            0       5     0  this   Los/write$;
}
InnerClasses:
  public static #10= #7 of #9;            // RelPathChunk=class os/PathChunk$RelPathChunk of class os/PathChunk
  public static #15= #12 of #14;          // all$=class os/makeDir$all$ of class os/makeDir
  public static #20= #17 of #19;          // AsJava=class scala/collection/JavaConverters$AsJava of class scala/collection/JavaConverters
SourceFile: "ReadWriteOps.scala"
  ScalaInlineInfo: length = 0x31 (unknown attribute)
   01 01 00 09 00 19 00 18 01 00 43 00 F7 01 00 3F
   00 9B 01 00 FD 00 40 01 00 1E 00 1F 01 00 9A 00
   9B 01 00 9C 00 40 01 00 9D 00 9E 01 00 C0 00 C1
   01
  Scala: length = 0x0 (unknown attribute)

