Classfile /Users/mw/Projects/slang-braindump/.jar/jar8/assemble/slang-braindump/assemble/content/os/WritableLowPri$$anon$3.class
  Last modified May 29, 2022; size 2482 bytes
  SHA-256 checksum 0ed43e06cc9d119067f96f1d42b8205018ba15ffbf825259ad05cc92d720c708
  Compiled from "Source.scala"
public final class os.WritableLowPri$$anon$3 implements os.Source
  minor version: 0
  major version: 52
  flags: (0x0031) ACC_PUBLIC, ACC_FINAL, ACC_SUPER
  this_class: #2                          // os/WritableLowPri$$anon$3
  super_class: #4                         // java/lang/Object
  interfaces: 1, fields: 2, methods: 8, attributes: 5
Constant pool:
    #1 = Utf8               os/WritableLowPri$$anon$3
    #2 = Class              #1            // os/WritableLowPri$$anon$3
    #3 = Utf8               java/lang/Object
    #4 = Class              #3            // java/lang/Object
    #5 = Utf8               os/Source
    #6 = Class              #5            // os/Source
    #7 = Utf8               Source.scala
    #8 = Utf8               os/WritableLowPri
    #9 = Class              #8            // os/WritableLowPri
   #10 = Utf8               WritableTraversable
   #11 = Utf8               (Ljava/lang/Object;Lscala/Function1;Lscala/Function1;)Los/Source;
   #12 = NameAndType        #10:#11       // WritableTraversable:(Ljava/lang/Object;Lscala/Function1;Lscala/Function1;)Los/Source;
   #13 = Utf8               os/WritableLowPri$$anon$3$$anon$4
   #14 = Class              #13           // os/WritableLowPri$$anon$3$$anon$4
   #15 = Utf8               traversable$1
   #16 = Utf8               Lscala/collection/IterableOnce;
   #17 = Utf8               f0$2
   #18 = Utf8               Lscala/Function1;
   #19 = Utf8               httpContentType
   #20 = Utf8               ()Lscala/Some;
   #21 = Utf8               ()Lscala/Some<Ljava/lang/String;>;
   #22 = Utf8               httpContentType$
   #23 = Utf8               (Los/Source;)Lscala/Some;
   #24 = NameAndType        #22:#23       // httpContentType$:(Los/Source;)Lscala/Some;
   #25 = InterfaceMethodref #6.#24        // os/Source.httpContentType$:(Los/Source;)Lscala/Some;
   #26 = Utf8               this
   #27 = Utf8               Los/WritableLowPri$$anon$3;
   #28 = Utf8               writeBytesTo
   #29 = Utf8               (Ljava/io/OutputStream;)V
   #30 = Utf8               out
   #31 = Utf8               writeBytesTo$
   #32 = Utf8               (Los/Source;Ljava/io/OutputStream;)V
   #33 = NameAndType        #31:#32       // writeBytesTo$:(Los/Source;Ljava/io/OutputStream;)V
   #34 = InterfaceMethodref #6.#33        // os/Source.writeBytesTo$:(Los/Source;Ljava/io/OutputStream;)V
   #35 = Utf8               Ljava/io/OutputStream;
   #36 = Utf8               (Ljava/nio/channels/WritableByteChannel;)Ljava/lang/Object;
   #37 = Utf8               (Los/Source;Ljava/nio/channels/WritableByteChannel;)Ljava/lang/Object;
   #38 = NameAndType        #31:#37       // writeBytesTo$:(Los/Source;Ljava/nio/channels/WritableByteChannel;)Ljava/lang/Object;
   #39 = InterfaceMethodref #6.#38        // os/Source.writeBytesTo$:(Los/Source;Ljava/nio/channels/WritableByteChannel;)Ljava/lang/Object;
   #40 = Utf8               Ljava/nio/channels/WritableByteChannel;
   #41 = Utf8               contentLength
   #42 = Utf8               ()Lscala/Option;
   #43 = Utf8               ()Lscala/Option<Ljava/lang/Object;>;
   #44 = Utf8               geny/Writable
   #45 = Class              #44           // geny/Writable
   #46 = Utf8               contentLength$
   #47 = Utf8               (Lgeny/Writable;)Lscala/Option;
   #48 = NameAndType        #46:#47       // contentLength$:(Lgeny/Writable;)Lscala/Option;
   #49 = InterfaceMethodref #45.#48       // geny/Writable.contentLength$:(Lgeny/Writable;)Lscala/Option;
   #50 = Utf8               getHandle
   #51 = Utf8               ()Lscala/util/Left;
   #52 = Utf8               ()Lscala/util/Left<Ljava/lang/Object;Lscala/runtime/Nothing$;>;
   #53 = Utf8               scala/package$
   #54 = Class              #53           // scala/package$
   #55 = Utf8               MODULE$
   #56 = Utf8               Lscala/package$;
   #57 = NameAndType        #55:#56       // MODULE$:Lscala/package$;
   #58 = Fieldref           #54.#57       // scala/package$.MODULE$:Lscala/package$;
   #59 = Utf8               Left
   #60 = Utf8               ()Lscala/util/Left$;
   #61 = NameAndType        #59:#60       // Left:()Lscala/util/Left$;
   #62 = Methodref          #54.#61       // scala/package$.Left:()Lscala/util/Left$;
   #63 = Utf8               <init>
   #64 = Utf8               (Los/WritableLowPri$$anon$3;)V
   #65 = NameAndType        #63:#64       // "<init>":(Los/WritableLowPri$$anon$3;)V
   #66 = Methodref          #14.#65       // os/WritableLowPri$$anon$3$$anon$4."<init>":(Los/WritableLowPri$$anon$3;)V
   #67 = Utf8               scala/util/Left$
   #68 = Class              #67           // scala/util/Left$
   #69 = Utf8               apply
   #70 = Utf8               (Ljava/lang/Object;)Lscala/util/Left;
   #71 = NameAndType        #69:#70       // apply:(Ljava/lang/Object;)Lscala/util/Left;
   #72 = Methodref          #68.#71       // scala/util/Left$.apply:(Ljava/lang/Object;)Lscala/util/Left;
   #73 = NameAndType        #19:#20       // httpContentType:()Lscala/Some;
   #74 = Methodref          #2.#73        // os/WritableLowPri$$anon$3.httpContentType:()Lscala/Some;
   #75 = Utf8               ()Lscala/util/Either;
   #76 = NameAndType        #50:#51       // getHandle:()Lscala/util/Left;
   #77 = Methodref          #2.#76        // os/WritableLowPri$$anon$3.getHandle:()Lscala/util/Left;
   #78 = Utf8               (Los/WritableLowPri;Lscala/collection/IterableOnce;Lscala/Function1;)V
   #79 = Utf8               $outer
   #80 = NameAndType        #15:#16       // traversable$1:Lscala/collection/IterableOnce;
   #81 = Fieldref           #2.#80        // os/WritableLowPri$$anon$3.traversable$1:Lscala/collection/IterableOnce;
   #82 = NameAndType        #17:#18       // f0$2:Lscala/Function1;
   #83 = Fieldref           #2.#82        // os/WritableLowPri$$anon$3.f0$2:Lscala/Function1;
   #84 = Utf8               ()V
   #85 = NameAndType        #63:#84       // "<init>":()V
   #86 = Methodref          #4.#85        // java/lang/Object."<init>":()V
   #87 = Utf8               $init$
   #88 = Utf8               (Lgeny/Writable;)V
   #89 = NameAndType        #87:#88       // $init$:(Lgeny/Writable;)V
   #90 = InterfaceMethodref #45.#89       // geny/Writable.$init$:(Lgeny/Writable;)V
   #91 = Utf8               (Los/Source;)V
   #92 = NameAndType        #87:#91       // $init$:(Los/Source;)V
   #93 = InterfaceMethodref #6.#92        // os/Source.$init$:(Los/Source;)V
   #94 = Utf8               Los/WritableLowPri;
   #95 = Utf8               Code
   #96 = Utf8               LineNumberTable
   #97 = Utf8               LocalVariableTable
   #98 = Utf8               Signature
   #99 = Utf8               MethodParameters
  #100 = Utf8               InnerClasses
  #101 = Utf8               EnclosingMethod
  #102 = Utf8               SourceFile
  #103 = Utf8               ScalaInlineInfo
  #104 = Utf8               Scala
{
  public final scala.collection.IterableOnce traversable$1;
    descriptor: Lscala/collection/IterableOnce;
    flags: (0x0011) ACC_PUBLIC, ACC_FINAL

  public final scala.Function1 f0$2;
    descriptor: Lscala/Function1;
    flags: (0x0011) ACC_PUBLIC, ACC_FINAL

  public scala.Some<java.lang.String> httpContentType();
    descriptor: ()Lscala/Some;
    flags: (0x0001) ACC_PUBLIC
    Code:
      stack=1, locals=1, args_size=1
         0: aload_0
         1: invokestatic  #25                 // InterfaceMethod os/Source.httpContentType$:(Los/Source;)Lscala/Some;
         4: areturn
      LineNumberTable:
        line 90: 0
      LocalVariableTable:
        Start  Length  Slot  Name   Signature
            0       5     0  this   Los/WritableLowPri$$anon$3;
    Signature: #21                          // ()Lscala/Some<Ljava/lang/String;>;

  public void writeBytesTo(java.io.OutputStream);
    descriptor: (Ljava/io/OutputStream;)V
    flags: (0x0001) ACC_PUBLIC
    Code:
      stack=2, locals=2, args_size=2
         0: aload_0
         1: aload_1
         2: invokestatic  #34                 // InterfaceMethod os/Source.writeBytesTo$:(Los/Source;Ljava/io/OutputStream;)V
         5: return
      LineNumberTable:
        line 90: 0
      LocalVariableTable:
        Start  Length  Slot  Name   Signature
            0       6     0  this   Los/WritableLowPri$$anon$3;
            0       6     1   out   Ljava/io/OutputStream;
    MethodParameters:
      Name                           Flags
      out                            final

  public java.lang.Object writeBytesTo(java.nio.channels.WritableByteChannel);
    descriptor: (Ljava/nio/channels/WritableByteChannel;)Ljava/lang/Object;
    flags: (0x0001) ACC_PUBLIC
    Code:
      stack=2, locals=2, args_size=2
         0: aload_0
         1: aload_1
         2: invokestatic  #39                 // InterfaceMethod os/Source.writeBytesTo$:(Los/Source;Ljava/nio/channels/WritableByteChannel;)Ljava/lang/Object;
         5: areturn
      LineNumberTable:
        line 90: 0
      LocalVariableTable:
        Start  Length  Slot  Name   Signature
            0       6     0  this   Los/WritableLowPri$$anon$3;
            0       6     1   out   Ljava/nio/channels/WritableByteChannel;
    MethodParameters:
      Name                           Flags
      out                            final

  public scala.Option<java.lang.Object> contentLength();
    descriptor: ()Lscala/Option;
    flags: (0x0001) ACC_PUBLIC
    Code:
      stack=1, locals=1, args_size=1
         0: aload_0
         1: invokestatic  #49                 // InterfaceMethod geny/Writable.contentLength$:(Lgeny/Writable;)Lscala/Option;
         4: areturn
      LineNumberTable:
        line 90: 0
      LocalVariableTable:
        Start  Length  Slot  Name   Signature
            0       5     0  this   Los/WritableLowPri$$anon$3;
    Signature: #43                          // ()Lscala/Option<Ljava/lang/Object;>;

  public scala.util.Left<java.lang.Object, scala.runtime.Nothing$> getHandle();
    descriptor: ()Lscala/util/Left;
    flags: (0x0001) ACC_PUBLIC
    Code:
      stack=4, locals=1, args_size=1
         0: getstatic     #58                 // Field scala/package$.MODULE$:Lscala/package$;
         3: invokevirtual #62                 // Method scala/package$.Left:()Lscala/util/Left$;
         6: new           #14                 // class os/WritableLowPri$$anon$3$$anon$4
         9: dup
        10: aload_0
        11: invokespecial #66                 // Method os/WritableLowPri$$anon$3$$anon$4."<init>":(Los/WritableLowPri$$anon$3;)V
        14: invokevirtual #72                 // Method scala/util/Left$.apply:(Ljava/lang/Object;)Lscala/util/Left;
        17: areturn
      LineNumberTable:
        line 91: 0
        line 92: 6
      LocalVariableTable:
        Start  Length  Slot  Name   Signature
            0      18     0  this   Los/WritableLowPri$$anon$3;
    Signature: #52                          // ()Lscala/util/Left<Ljava/lang/Object;Lscala/runtime/Nothing$;>;

  public scala.Option httpContentType();
    descriptor: ()Lscala/Option;
    flags: (0x1041) ACC_PUBLIC, ACC_BRIDGE, ACC_SYNTHETIC
    Code:
      stack=1, locals=1, args_size=1
         0: aload_0
         1: invokevirtual #74                 // Method httpContentType:()Lscala/Some;
         4: areturn
      LineNumberTable:
        line 90: 0
      LocalVariableTable:
        Start  Length  Slot  Name   Signature
            0       5     0  this   Los/WritableLowPri$$anon$3;

  public scala.util.Either getHandle();
    descriptor: ()Lscala/util/Either;
    flags: (0x1041) ACC_PUBLIC, ACC_BRIDGE, ACC_SYNTHETIC
    Code:
      stack=1, locals=1, args_size=1
         0: aload_0
         1: invokevirtual #77                 // Method getHandle:()Lscala/util/Left;
         4: areturn
      LineNumberTable:
        line 90: 0
      LocalVariableTable:
        Start  Length  Slot  Name   Signature
            0       5     0  this   Los/WritableLowPri$$anon$3;

  public os.WritableLowPri$$anon$3(os.WritableLowPri, scala.collection.IterableOnce, scala.Function1);
    descriptor: (Los/WritableLowPri;Lscala/collection/IterableOnce;Lscala/Function1;)V
    flags: (0x0001) ACC_PUBLIC
    Code:
      stack=2, locals=4, args_size=4
         0: aload_0
         1: aload_2
         2: putfield      #81                 // Field traversable$1:Lscala/collection/IterableOnce;
         5: aload_0
         6: aload_3
         7: putfield      #83                 // Field f0$2:Lscala/Function1;
        10: aload_0
        11: invokespecial #86                 // Method java/lang/Object."<init>":()V
        14: aload_0
        15: invokestatic  #90                 // InterfaceMethod geny/Writable.$init$:(Lgeny/Writable;)V
        18: aload_0
        19: invokestatic  #93                 // InterfaceMethod os/Source.$init$:(Los/Source;)V
        22: return
      LineNumberTable:
        line 88: 0
        line 89: 5
        line 90: 10
      LocalVariableTable:
        Start  Length  Slot  Name   Signature
            0      23     0  this   Los/WritableLowPri$$anon$3;
            0      23     1 $outer   Los/WritableLowPri;
            0      23     2 traversable$1   Lscala/collection/IterableOnce;
            0      23     3  f0$2   Lscala/Function1;
    MethodParameters:
      Name                           Flags
      $outer                         final synthetic
      traversable$1                  final
      f0$2                           final
}
InnerClasses:
  public final #2;                        // class os/WritableLowPri$$anon$3
  public final #14;                       // class os/WritableLowPri$$anon$3$$anon$4
EnclosingMethod: #9.#12                 // os.WritableLowPri.WritableTraversable
SourceFile: "Source.scala"
  ScalaInlineInfo: length = 0x2C (unknown attribute)
   01 01 00 08 00 3F 00 4E 01 00 29 00 2A 01 00 32
   00 4B 01 00 32 00 33 01 00 13 00 2A 01 00 13 00
   14 01 00 1C 00 1D 01 00 1C 00 24 01
  Scala: length = 0x0 (unknown attribute)

