Classfile /Users/mw/Projects/slang-braindump/.jar/jar8/assemble/slang-braindump/assemble/content/scala/collection/parallel/mutable/ParArray$ParArrayIterator$.class
  Last modified May 29, 2022; size 1102 bytes
  SHA-256 checksum 19751914fe556b95836273107a5216b6dd8a9b0a2a35b2247357abc3fb732b1a
  Compiled from "ParArray.scala"
public class scala.collection.parallel.mutable.ParArray$ParArrayIterator$
  minor version: 0
  major version: 52
  flags: (0x0021) ACC_PUBLIC, ACC_SUPER
  this_class: #2                          // scala/collection/parallel/mutable/ParArray$ParArrayIterator$
  super_class: #4                         // java/lang/Object
  interfaces: 0, fields: 1, methods: 4, attributes: 4
Constant pool:
   #1 = Utf8               scala/collection/parallel/mutable/ParArray$ParArrayIterator$
   #2 = Class              #1             // scala/collection/parallel/mutable/ParArray$ParArrayIterator$
   #3 = Utf8               java/lang/Object
   #4 = Class              #3             // java/lang/Object
   #5 = Utf8               ParArray.scala
   #6 = Utf8               scala/collection/parallel/mutable/ParArray
   #7 = Class              #6             // scala/collection/parallel/mutable/ParArray
   #8 = Utf8               ParArrayIterator$
   #9 = Utf8               $outer
  #10 = Utf8               Lscala/collection/parallel/mutable/ParArray;
  #11 = Utf8               $lessinit$greater$default$1
  #12 = Utf8               ()I
  #13 = Utf8               this
  #14 = Utf8               Lscala/collection/parallel/mutable/ParArray$ParArrayIterator$;
  #15 = Utf8               $lessinit$greater$default$2
  #16 = NameAndType        #9:#10         // $outer:Lscala/collection/parallel/mutable/ParArray;
  #17 = Fieldref           #2.#16         // scala/collection/parallel/mutable/ParArray$ParArrayIterator$.$outer:Lscala/collection/parallel/mutable/ParArray;
  #18 = Utf8               length
  #19 = NameAndType        #18:#12        // length:()I
  #20 = Methodref          #7.#19         // scala/collection/parallel/mutable/ParArray.length:()I
  #21 = Utf8               $lessinit$greater$default$3
  #22 = Utf8               ()[Ljava/lang/Object;
  #23 = Utf8               scala$collection$parallel$mutable$ParArray$$array
  #24 = NameAndType        #23:#22        // scala$collection$parallel$mutable$ParArray$$array:()[Ljava/lang/Object;
  #25 = Methodref          #7.#24         // scala/collection/parallel/mutable/ParArray.scala$collection$parallel$mutable$ParArray$$array:()[Ljava/lang/Object;
  #26 = Utf8               <init>
  #27 = Utf8               (Lscala/collection/parallel/mutable/ParArray;)V
  #28 = Utf8               ()V
  #29 = NameAndType        #26:#28        // "<init>":()V
  #30 = Methodref          #4.#29         // java/lang/Object."<init>":()V
  #31 = Utf8               Code
  #32 = Utf8               LineNumberTable
  #33 = Utf8               LocalVariableTable
  #34 = Utf8               StackMapTable
  #35 = Utf8               MethodParameters
  #36 = Utf8               InnerClasses
  #37 = Utf8               SourceFile
  #38 = Utf8               ScalaInlineInfo
  #39 = Utf8               Scala
{
  private final scala.collection.parallel.mutable.ParArray $outer;
    descriptor: Lscala/collection/parallel/mutable/ParArray;
    flags: (0x1012) ACC_PRIVATE, ACC_FINAL, ACC_SYNTHETIC

  public int $lessinit$greater$default$1();
    descriptor: ()I
    flags: (0x0001) ACC_PUBLIC
    Code:
      stack=1, locals=1, args_size=1
         0: iconst_0
         1: ireturn
      LineNumberTable:
        line 92: 0
      LocalVariableTable:
        Start  Length  Slot  Name   Signature
            0       2     0  this   Lscala/collection/parallel/mutable/ParArray$ParArrayIterator$;

  public int $lessinit$greater$default$2();
    descriptor: ()I
    flags: (0x0001) ACC_PUBLIC
    Code:
      stack=1, locals=1, args_size=1
         0: aload_0
         1: getfield      #17                 // Field $outer:Lscala/collection/parallel/mutable/ParArray;
         4: invokevirtual #20                 // Method scala/collection/parallel/mutable/ParArray.length:()I
         7: ireturn
      LineNumberTable:
        line 92: 0
      LocalVariableTable:
        Start  Length  Slot  Name   Signature
            0       8     0  this   Lscala/collection/parallel/mutable/ParArray$ParArrayIterator$;

  public java.lang.Object[] $lessinit$greater$default$3();
    descriptor: ()[Ljava/lang/Object;
    flags: (0x0001) ACC_PUBLIC
    Code:
      stack=1, locals=1, args_size=1
         0: aload_0
         1: getfield      #17                 // Field $outer:Lscala/collection/parallel/mutable/ParArray;
         4: invokevirtual #25                 // Method scala/collection/parallel/mutable/ParArray.scala$collection$parallel$mutable$ParArray$$array:()[Ljava/lang/Object;
         7: areturn
      LineNumberTable:
        line 92: 0
      LocalVariableTable:
        Start  Length  Slot  Name   Signature
            0       8     0  this   Lscala/collection/parallel/mutable/ParArray$ParArrayIterator$;

  public scala.collection.parallel.mutable.ParArray$ParArrayIterator$(scala.collection.parallel.mutable.ParArray);
    descriptor: (Lscala/collection/parallel/mutable/ParArray;)V
    flags: (0x0001) ACC_PUBLIC
    Code:
      stack=2, locals=2, args_size=2
         0: aload_1
         1: ifnonnull     6
         4: aconst_null
         5: athrow
         6: aload_0
         7: aload_1
         8: putfield      #17                 // Field $outer:Lscala/collection/parallel/mutable/ParArray;
        11: aload_0
        12: invokespecial #30                 // Method java/lang/Object."<init>":()V
        15: return
      StackMapTable: number_of_entries = 1
        frame_type = 6 /* same */
      LineNumberTable:
        line 92: 0
      LocalVariableTable:
        Start  Length  Slot  Name   Signature
            0      16     0  this   Lscala/collection/parallel/mutable/ParArray$ParArrayIterator$;
            0      16     1 $outer   Lscala/collection/parallel/mutable/ParArray;
    MethodParameters:
      Name                           Flags
      $outer                         final synthetic
}
InnerClasses:
  public #8= #2 of #7;                    // ParArrayIterator$=class scala/collection/parallel/mutable/ParArray$ParArrayIterator$ of class scala/collection/parallel/mutable/ParArray
SourceFile: "ParArray.scala"
  ScalaInlineInfo: length = 0x18 (unknown attribute)
   01 01 00 04 00 0B 00 0C 01 00 0F 00 0C 01 00 15
   00 16 01 00 1A 00 1B 01
  Scala: length = 0x0 (unknown attribute)

