Classfile /Users/mw/Projects/slang-braindump/.jar/jar8/assemble/slang-braindump/assemble/content/scala/collection/parallel/mutable/ParArray$.class
  Last modified May 29, 2022; size 6061 bytes
  SHA-256 checksum 64e69b021c800524f6d42e52c840a71d6f190397cff0f9193f14ccdd87a4425d
  Compiled from "ParArray.scala"
public final class scala.collection.parallel.mutable.ParArray$ extends scala.collection.generic.ParFactory<scala.collection.parallel.mutable.ParArray> implements java.io.Serializable
  minor version: 0
  major version: 52
  flags: (0x0031) ACC_PUBLIC, ACC_FINAL, ACC_SUPER
  this_class: #2                          // scala/collection/parallel/mutable/ParArray$
  super_class: #5                         // scala/collection/generic/ParFactory
  interfaces: 1, fields: 1, methods: 14, attributes: 6
Constant pool:
    #1 = Utf8               scala/collection/parallel/mutable/ParArray$
    #2 = Class              #1            // scala/collection/parallel/mutable/ParArray$
    #3 = Utf8               Lscala/collection/generic/ParFactory<Lscala/collection/parallel/mutable/ParArray;>;Ljava/io/Serializable;
    #4 = Utf8               scala/collection/generic/ParFactory
    #5 = Class              #4            // scala/collection/generic/ParFactory
    #6 = Utf8               java/io/Serializable
    #7 = Class              #6            // java/io/Serializable
    #8 = Utf8               ParArray.scala
    #9 = Utf8               java/lang/invoke/MethodHandles$Lookup
   #10 = Class              #9            // java/lang/invoke/MethodHandles$Lookup
   #11 = Utf8               java/lang/invoke/MethodHandles
   #12 = Class              #11           // java/lang/invoke/MethodHandles
   #13 = Utf8               Lookup
   #14 = Utf8               scala/collection/generic/ParFactory$GenericCanCombineFrom
   #15 = Class              #14           // scala/collection/generic/ParFactory$GenericCanCombineFrom
   #16 = Utf8               GenericCanCombineFrom
   #17 = Utf8               MODULE$
   #18 = Utf8               Lscala/collection/parallel/mutable/ParArray$;
   #19 = Utf8               <clinit>
   #20 = Utf8               ()V
   #21 = Utf8               <init>
   #22 = NameAndType        #21:#20       // "<init>":()V
   #23 = Methodref          #2.#22        // scala/collection/parallel/mutable/ParArray$."<init>":()V
   #24 = NameAndType        #17:#18       // MODULE$:Lscala/collection/parallel/mutable/ParArray$;
   #25 = Fieldref           #2.#24        // scala/collection/parallel/mutable/ParArray$.MODULE$:Lscala/collection/parallel/mutable/ParArray$;
   #26 = Utf8               canBuildFrom
   #27 = Utf8               ()Lscala/collection/generic/CanCombineFrom;
   #28 = Utf8               <S:Ljava/lang/Object;T:Ljava/lang/Object;>()Lscala/collection/generic/CanCombineFrom<Lscala/collection/parallel/mutable/ParArray<TS;>;TT;Lscala/collection/parallel/mutable/ParArray<TT;>;>;
   #29 = Utf8               (Lscala/collection/generic/ParFactory;)V
   #30 = NameAndType        #21:#29       // "<init>":(Lscala/collection/generic/ParFactory;)V
   #31 = Methodref          #15.#30       // scala/collection/generic/ParFactory$GenericCanCombineFrom."<init>":(Lscala/collection/generic/ParFactory;)V
   #32 = Utf8               this
   #33 = Utf8               newBuilder
   #34 = Utf8               ()Lscala/collection/parallel/Combiner;
   #35 = Utf8               <T:Ljava/lang/Object;>()Lscala/collection/parallel/Combiner<TT;Lscala/collection/parallel/mutable/ParArray<TT;>;>;
   #36 = Utf8               newCombiner
   #37 = NameAndType        #36:#34       // newCombiner:()Lscala/collection/parallel/Combiner;
   #38 = Methodref          #2.#37        // scala/collection/parallel/mutable/ParArray$.newCombiner:()Lscala/collection/parallel/Combiner;
   #39 = Utf8               scala/collection/parallel/mutable/package$
   #40 = Class              #39           // scala/collection/parallel/mutable/package$
   #41 = Utf8               Lscala/collection/parallel/mutable/package$;
   #42 = NameAndType        #17:#41       // MODULE$:Lscala/collection/parallel/mutable/package$;
   #43 = Fieldref           #40.#42       // scala/collection/parallel/mutable/package$.MODULE$:Lscala/collection/parallel/mutable/package$;
   #44 = Utf8               ParArrayCombiner
   #45 = Utf8               ()Lscala/collection/parallel/mutable/ResizableParArrayCombiner$;
   #46 = NameAndType        #44:#45       // ParArrayCombiner:()Lscala/collection/parallel/mutable/ResizableParArrayCombiner$;
   #47 = Methodref          #40.#46       // scala/collection/parallel/mutable/package$.ParArrayCombiner:()Lscala/collection/parallel/mutable/ResizableParArrayCombiner$;
   #48 = Utf8               scala/collection/parallel/mutable/ResizableParArrayCombiner$
   #49 = Class              #48           // scala/collection/parallel/mutable/ResizableParArrayCombiner$
   #50 = Utf8               apply
   #51 = Utf8               ()Lscala/collection/parallel/mutable/ResizableParArrayCombiner;
   #52 = NameAndType        #50:#51       // apply:()Lscala/collection/parallel/mutable/ResizableParArrayCombiner;
   #53 = Methodref          #49.#52       // scala/collection/parallel/mutable/ResizableParArrayCombiner$.apply:()Lscala/collection/parallel/mutable/ResizableParArrayCombiner;
   #54 = Utf8               handoff
   #55 = Utf8               (Ljava/lang/Object;)Lscala/collection/parallel/mutable/ParArray;
   #56 = Utf8               <T:Ljava/lang/Object;>(Ljava/lang/Object;)Lscala/collection/parallel/mutable/ParArray<TT;>;
   #57 = Utf8               arr
   #58 = Utf8               scala/runtime/ScalaRunTime$
   #59 = Class              #58           // scala/runtime/ScalaRunTime$
   #60 = Utf8               Lscala/runtime/ScalaRunTime$;
   #61 = NameAndType        #17:#60       // MODULE$:Lscala/runtime/ScalaRunTime$;
   #62 = Fieldref           #59.#61       // scala/runtime/ScalaRunTime$.MODULE$:Lscala/runtime/ScalaRunTime$;
   #63 = Utf8               array_length
   #64 = Utf8               (Ljava/lang/Object;)I
   #65 = NameAndType        #63:#64       // array_length:(Ljava/lang/Object;)I
   #66 = Methodref          #59.#65       // scala/runtime/ScalaRunTime$.array_length:(Ljava/lang/Object;)I
   #67 = Utf8               wrapOrRebuild
   #68 = Utf8               (Ljava/lang/Object;I)Lscala/collection/parallel/mutable/ParArray;
   #69 = NameAndType        #67:#68       // wrapOrRebuild:(Ljava/lang/Object;I)Lscala/collection/parallel/mutable/ParArray;
   #70 = Methodref          #2.#69        // scala/collection/parallel/mutable/ParArray$.wrapOrRebuild:(Ljava/lang/Object;I)Lscala/collection/parallel/mutable/ParArray;
   #71 = Utf8               Ljava/lang/Object;
   #72 = Utf8               <T:Ljava/lang/Object;>(Ljava/lang/Object;I)Lscala/collection/parallel/mutable/ParArray<TT;>;
   #73 = Utf8               sz
   #74 = Utf8               I
   #75 = Utf8               scala/collection/parallel/mutable/ParArray
   #76 = Class              #75           // scala/collection/parallel/mutable/ParArray
   #77 = Utf8               scala/collection/mutable/ArraySeq$
   #78 = Class              #77           // scala/collection/mutable/ArraySeq$
   #79 = Utf8               Lscala/collection/mutable/ArraySeq$;
   #80 = NameAndType        #17:#79       // MODULE$:Lscala/collection/mutable/ArraySeq$;
   #81 = Fieldref           #78.#80       // scala/collection/mutable/ArraySeq$.MODULE$:Lscala/collection/mutable/ArraySeq$;
   #82 = Utf8               toObjectArray
   #83 = Utf8               (Ljava/lang/Object;)[Ljava/lang/Object;
   #84 = NameAndType        #82:#83       // toObjectArray:(Ljava/lang/Object;)[Ljava/lang/Object;
   #85 = Methodref          #59.#84       // scala/runtime/ScalaRunTime$.toObjectArray:(Ljava/lang/Object;)[Ljava/lang/Object;
   #86 = Utf8               make
   #87 = Utf8               (Ljava/lang/Object;)Lscala/collection/mutable/ArraySeq;
   #88 = NameAndType        #86:#87       // make:(Ljava/lang/Object;)Lscala/collection/mutable/ArraySeq;
   #89 = Methodref          #78.#88       // scala/collection/mutable/ArraySeq$.make:(Ljava/lang/Object;)Lscala/collection/mutable/ArraySeq;
   #90 = Utf8               (Lscala/collection/mutable/ArraySeq;I)V
   #91 = NameAndType        #21:#90       // "<init>":(Lscala/collection/mutable/ArraySeq;I)V
   #92 = Methodref          #76.#91       // scala/collection/parallel/mutable/ParArray."<init>":(Lscala/collection/mutable/ArraySeq;I)V
   #93 = Utf8               createFromCopy
   #94 = Utf8               ([Ljava/lang/Object;Lscala/reflect/ClassTag;)Lscala/collection/parallel/mutable/ParArray;
   #95 = Utf8               <T:Ljava/lang/Object;>([TT;Lscala/reflect/ClassTag<TT;>;)Lscala/collection/parallel/mutable/ParArray<TT;>;
   #96 = Utf8               evidence$1
   #97 = Utf8               scala/reflect/ClassTag
   #98 = Class              #97           // scala/reflect/ClassTag
   #99 = Utf8               newArray
  #100 = Utf8               (I)Ljava/lang/Object;
  #101 = NameAndType        #99:#100      // newArray:(I)Ljava/lang/Object;
  #102 = InterfaceMethodref #98.#101      // scala/reflect/ClassTag.newArray:(I)Ljava/lang/Object;
  #103 = Utf8               [Ljava/lang/Object;
  #104 = Class              #103          // "[Ljava/lang/Object;"
  #105 = Utf8               scala/Array$
  #106 = Class              #105          // scala/Array$
  #107 = Utf8               Lscala/Array$;
  #108 = NameAndType        #17:#107      // MODULE$:Lscala/Array$;
  #109 = Fieldref           #106.#108     // scala/Array$.MODULE$:Lscala/Array$;
  #110 = Utf8               copy
  #111 = Utf8               (Ljava/lang/Object;ILjava/lang/Object;II)V
  #112 = NameAndType        #110:#111     // copy:(Ljava/lang/Object;ILjava/lang/Object;II)V
  #113 = Methodref          #106.#112     // scala/Array$.copy:(Ljava/lang/Object;ILjava/lang/Object;II)V
  #114 = NameAndType        #54:#55       // handoff:(Ljava/lang/Object;)Lscala/collection/parallel/mutable/ParArray;
  #115 = Methodref          #2.#114       // scala/collection/parallel/mutable/ParArray$.handoff:(Ljava/lang/Object;)Lscala/collection/parallel/mutable/ParArray;
  #116 = Utf8               newarr
  #117 = Utf8               Lscala/reflect/ClassTag;
  #118 = Utf8               fromTraversables
  #119 = Utf8               (Lscala/collection/immutable/Seq;)Lscala/collection/parallel/mutable/ParArray;
  #120 = Utf8               <T:Ljava/lang/Object;>(Lscala/collection/immutable/Seq<Lscala/collection/IterableOnce<TT;>;>;)Lscala/collection/parallel/mutable/ParArray<TT;>;
  #121 = Utf8               xss
  #122 = Utf8               fromIterables
  #123 = NameAndType        #122:#119     // fromIterables:(Lscala/collection/immutable/Seq;)Lscala/collection/parallel/mutable/ParArray;
  #124 = Methodref          #2.#123       // scala/collection/parallel/mutable/ParArray$.fromIterables:(Lscala/collection/immutable/Seq;)Lscala/collection/parallel/mutable/ParArray;
  #125 = Utf8               Lscala/collection/immutable/Seq;
  #126 = Utf8               (Ljava/lang/Object;)Ljava/lang/Object;
  #127 = MethodType         #126          //  (Ljava/lang/Object;)Ljava/lang/Object;
  #128 = Utf8               $anonfun$fromIterables$1
  #129 = Utf8               (Lscala/collection/parallel/mutable/ResizableParArrayCombiner;Lscala/collection/IterableOnce;)Lscala/collection/parallel/mutable/ResizableParArrayCombiner;
  #130 = NameAndType        #128:#129     // $anonfun$fromIterables$1:(Lscala/collection/parallel/mutable/ResizableParArrayCombiner;Lscala/collection/IterableOnce;)Lscala/collection/parallel/mutable/ResizableParArrayCombiner;
  #131 = Methodref          #2.#130       // scala/collection/parallel/mutable/ParArray$.$anonfun$fromIterables$1:(Lscala/collection/parallel/mutable/ResizableParArrayCombiner;Lscala/collection/IterableOnce;)Lscala/collection/parallel/mutable/ResizableParArrayCombiner;
  #132 = MethodHandle       6:#131        // REF_invokeStatic scala/collection/parallel/mutable/ParArray$.$anonfun$fromIterables$1:(Lscala/collection/parallel/mutable/ResizableParArrayCombiner;Lscala/collection/IterableOnce;)Lscala/collection/parallel/mutable/ResizableParArrayCombiner;
  #133 = Utf8               (Lscala/collection/IterableOnce;)Lscala/collection/parallel/mutable/ResizableParArrayCombiner;
  #134 = MethodType         #133          //  (Lscala/collection/IterableOnce;)Lscala/collection/parallel/mutable/ResizableParArrayCombiner;
  #135 = Integer            5
  #136 = Integer            1
  #137 = Utf8               java/lang/invoke/LambdaMetafactory
  #138 = Class              #137          // java/lang/invoke/LambdaMetafactory
  #139 = Utf8               altMetafactory
  #140 = Utf8               (Ljava/lang/invoke/MethodHandles$Lookup;Ljava/lang/String;Ljava/lang/invoke/MethodType;[Ljava/lang/Object;)Ljava/lang/invoke/CallSite;
  #141 = NameAndType        #139:#140     // altMetafactory:(Ljava/lang/invoke/MethodHandles$Lookup;Ljava/lang/String;Ljava/lang/invoke/MethodType;[Ljava/lang/Object;)Ljava/lang/invoke/CallSite;
  #142 = Methodref          #138.#141     // java/lang/invoke/LambdaMetafactory.altMetafactory:(Ljava/lang/invoke/MethodHandles$Lookup;Ljava/lang/String;Ljava/lang/invoke/MethodType;[Ljava/lang/Object;)Ljava/lang/invoke/CallSite;
  #143 = MethodHandle       6:#142        // REF_invokeStatic java/lang/invoke/LambdaMetafactory.altMetafactory:(Ljava/lang/invoke/MethodHandles$Lookup;Ljava/lang/String;Ljava/lang/invoke/MethodType;[Ljava/lang/Object;)Ljava/lang/invoke/CallSite;
  #144 = Utf8               (Lscala/collection/parallel/mutable/ResizableParArrayCombiner;)Lscala/Function1;
  #145 = NameAndType        #50:#144      // apply:(Lscala/collection/parallel/mutable/ResizableParArrayCombiner;)Lscala/Function1;
  #146 = InvokeDynamic      #0:#145       // #0:apply:(Lscala/collection/parallel/mutable/ResizableParArrayCombiner;)Lscala/Function1;
  #147 = Utf8               scala/collection/immutable/Seq
  #148 = Class              #147          // scala/collection/immutable/Seq
  #149 = Utf8               foreach
  #150 = Utf8               (Lscala/Function1;)V
  #151 = NameAndType        #149:#150     // foreach:(Lscala/Function1;)V
  #152 = InterfaceMethodref #148.#151     // scala/collection/immutable/Seq.foreach:(Lscala/Function1;)V
  #153 = Utf8               scala/collection/parallel/mutable/ResizableParArrayCombiner
  #154 = Class              #153          // scala/collection/parallel/mutable/ResizableParArrayCombiner
  #155 = Utf8               result
  #156 = Utf8               ()Ljava/lang/Object;
  #157 = NameAndType        #155:#156     // result:()Ljava/lang/Object;
  #158 = InterfaceMethodref #154.#157     // scala/collection/parallel/mutable/ResizableParArrayCombiner.result:()Ljava/lang/Object;
  #159 = Utf8               cb
  #160 = Utf8               Lscala/collection/parallel/mutable/ResizableParArrayCombiner;
  #161 = Utf8               writeReplace
  #162 = Utf8               scala/runtime/ModuleSerializationProxy
  #163 = Class              #162          // scala/runtime/ModuleSerializationProxy
  #164 = Utf8               (Ljava/lang/Class;)V
  #165 = NameAndType        #21:#164      // "<init>":(Ljava/lang/Class;)V
  #166 = Methodref          #163.#165     // scala/runtime/ModuleSerializationProxy."<init>":(Ljava/lang/Class;)V
  #167 = Utf8               cb$4
  #168 = Utf8               xs
  #169 = Utf8               $plus$plus$eq
  #170 = Utf8               (Lscala/collection/IterableOnce;)Lscala/collection/mutable/Growable;
  #171 = NameAndType        #169:#170     // $plus$plus$eq:(Lscala/collection/IterableOnce;)Lscala/collection/mutable/Growable;
  #172 = InterfaceMethodref #154.#171     // scala/collection/parallel/mutable/ResizableParArrayCombiner.$plus$plus$eq:(Lscala/collection/IterableOnce;)Lscala/collection/mutable/Growable;
  #173 = Utf8               Lscala/collection/IterableOnce;
  #174 = Methodref          #5.#22        // scala/collection/generic/ParFactory."<init>":()V
  #175 = Utf8               $deserializeLambda$
  #176 = Utf8               (Ljava/lang/invoke/SerializedLambda;)Ljava/lang/Object;
  #177 = Utf8               scala/runtime/LambdaDeserialize
  #178 = Class              #177          // scala/runtime/LambdaDeserialize
  #179 = Utf8               bootstrap
  #180 = Utf8               (Ljava/lang/invoke/MethodHandles$Lookup;Ljava/lang/String;Ljava/lang/invoke/MethodType;[Ljava/lang/invoke/MethodHandle;)Ljava/lang/invoke/CallSite;
  #181 = NameAndType        #179:#180     // bootstrap:(Ljava/lang/invoke/MethodHandles$Lookup;Ljava/lang/String;Ljava/lang/invoke/MethodType;[Ljava/lang/invoke/MethodHandle;)Ljava/lang/invoke/CallSite;
  #182 = Methodref          #178.#181     // scala/runtime/LambdaDeserialize.bootstrap:(Ljava/lang/invoke/MethodHandles$Lookup;Ljava/lang/String;Ljava/lang/invoke/MethodType;[Ljava/lang/invoke/MethodHandle;)Ljava/lang/invoke/CallSite;
  #183 = MethodHandle       6:#182        // REF_invokeStatic scala/runtime/LambdaDeserialize.bootstrap:(Ljava/lang/invoke/MethodHandles$Lookup;Ljava/lang/String;Ljava/lang/invoke/MethodType;[Ljava/lang/invoke/MethodHandle;)Ljava/lang/invoke/CallSite;
  #184 = Utf8               lambdaDeserialize
  #185 = NameAndType        #184:#176     // lambdaDeserialize:(Ljava/lang/invoke/SerializedLambda;)Ljava/lang/Object;
  #186 = InvokeDynamic      #1:#185       // #1:lambdaDeserialize:(Ljava/lang/invoke/SerializedLambda;)Ljava/lang/Object;
  #187 = Utf8               Code
  #188 = Utf8               LineNumberTable
  #189 = Utf8               LocalVariableTable
  #190 = Utf8               Signature
  #191 = Utf8               MethodParameters
  #192 = Utf8               Deprecated
  #193 = Utf8               InnerClasses
  #194 = Utf8               SourceFile
  #195 = Utf8               BootstrapMethods
  #196 = Utf8               ScalaInlineInfo
  #197 = Utf8               Scala
{
  public static final scala.collection.parallel.mutable.ParArray$ MODULE$;
    descriptor: Lscala/collection/parallel/mutable/ParArray$;
    flags: (0x0019) ACC_PUBLIC, ACC_STATIC, ACC_FINAL

  public static {};
    descriptor: ()V
    flags: (0x0009) ACC_PUBLIC, ACC_STATIC
    Code:
      stack=2, locals=0, args_size=0
         0: new           #2                  // class scala/collection/parallel/mutable/ParArray$
         3: dup
         4: invokespecial #23                 // Method "<init>":()V
         7: putstatic     #25                 // Field MODULE$:Lscala/collection/parallel/mutable/ParArray$;
        10: return
      LineNumberTable:
        line 691: 0

  public <S extends java.lang.Object, T extends java.lang.Object> scala.collection.generic.CanCombineFrom<scala.collection.parallel.mutable.ParArray<S>, T, scala.collection.parallel.mutable.ParArray<T>> canBuildFrom();
    descriptor: ()Lscala/collection/generic/CanCombineFrom;
    flags: (0x0001) ACC_PUBLIC
    Code:
      stack=3, locals=1, args_size=1
         0: new           #15                 // class scala/collection/generic/ParFactory$GenericCanCombineFrom
         3: dup
         4: aload_0
         5: invokespecial #31                 // Method scala/collection/generic/ParFactory$GenericCanCombineFrom."<init>":(Lscala/collection/generic/ParFactory;)V
         8: areturn
      LineNumberTable:
        line 692: 0
      LocalVariableTable:
        Start  Length  Slot  Name   Signature
            0       9     0  this   Lscala/collection/parallel/mutable/ParArray$;
    Signature: #28                          // <S:Ljava/lang/Object;T:Ljava/lang/Object;>()Lscala/collection/generic/CanCombineFrom<Lscala/collection/parallel/mutable/ParArray<TS;>;TT;Lscala/collection/parallel/mutable/ParArray<TT;>;>;

  public <T extends java.lang.Object> scala.collection.parallel.Combiner<T, scala.collection.parallel.mutable.ParArray<T>> newBuilder();
    descriptor: ()Lscala/collection/parallel/Combiner;
    flags: (0x0001) ACC_PUBLIC
    Code:
      stack=1, locals=1, args_size=1
         0: aload_0
         1: invokevirtual #38                 // Method newCombiner:()Lscala/collection/parallel/Combiner;
         4: areturn
      LineNumberTable:
        line 693: 0
      LocalVariableTable:
        Start  Length  Slot  Name   Signature
            0       5     0  this   Lscala/collection/parallel/mutable/ParArray$;
    Signature: #35                          // <T:Ljava/lang/Object;>()Lscala/collection/parallel/Combiner<TT;Lscala/collection/parallel/mutable/ParArray<TT;>;>;

  public <T extends java.lang.Object> scala.collection.parallel.Combiner<T, scala.collection.parallel.mutable.ParArray<T>> newCombiner();
    descriptor: ()Lscala/collection/parallel/Combiner;
    flags: (0x0001) ACC_PUBLIC
    Code:
      stack=1, locals=1, args_size=1
         0: getstatic     #43                 // Field scala/collection/parallel/mutable/package$.MODULE$:Lscala/collection/parallel/mutable/package$;
         3: invokevirtual #47                 // Method scala/collection/parallel/mutable/package$.ParArrayCombiner:()Lscala/collection/parallel/mutable/ResizableParArrayCombiner$;
         6: invokevirtual #53                 // Method scala/collection/parallel/mutable/ResizableParArrayCombiner$.apply:()Lscala/collection/parallel/mutable/ResizableParArrayCombiner;
         9: areturn
      LineNumberTable:
        line 694: 0
      LocalVariableTable:
        Start  Length  Slot  Name   Signature
            0      10     0  this   Lscala/collection/parallel/mutable/ParArray$;
    Signature: #35                          // <T:Ljava/lang/Object;>()Lscala/collection/parallel/Combiner<TT;Lscala/collection/parallel/mutable/ParArray<TT;>;>;

  public <T extends java.lang.Object> scala.collection.parallel.mutable.ParArray<T> handoff(java.lang.Object);
    descriptor: (Ljava/lang/Object;)Lscala/collection/parallel/mutable/ParArray;
    flags: (0x0001) ACC_PUBLIC
    Code:
      stack=4, locals=2, args_size=2
         0: aload_0
         1: aload_1
         2: getstatic     #62                 // Field scala/runtime/ScalaRunTime$.MODULE$:Lscala/runtime/ScalaRunTime$;
         5: aload_1
         6: invokevirtual #66                 // Method scala/runtime/ScalaRunTime$.array_length:(Ljava/lang/Object;)I
         9: invokespecial #70                 // Method wrapOrRebuild:(Ljava/lang/Object;I)Lscala/collection/parallel/mutable/ParArray;
        12: areturn
      LineNumberTable:
        line 698: 0
      LocalVariableTable:
        Start  Length  Slot  Name   Signature
            0      13     0  this   Lscala/collection/parallel/mutable/ParArray$;
            0      13     1   arr   Ljava/lang/Object;
    Signature: #56                          // <T:Ljava/lang/Object;>(Ljava/lang/Object;)Lscala/collection/parallel/mutable/ParArray<TT;>;
    MethodParameters:
      Name                           Flags
      arr                            final

  public <T extends java.lang.Object> scala.collection.parallel.mutable.ParArray<T> handoff(java.lang.Object, int);
    descriptor: (Ljava/lang/Object;I)Lscala/collection/parallel/mutable/ParArray;
    flags: (0x0001) ACC_PUBLIC
    Code:
      stack=3, locals=3, args_size=3
         0: aload_0
         1: aload_1
         2: iload_2
         3: invokespecial #70                 // Method wrapOrRebuild:(Ljava/lang/Object;I)Lscala/collection/parallel/mutable/ParArray;
         6: areturn
      LineNumberTable:
        line 702: 0
      LocalVariableTable:
        Start  Length  Slot  Name   Signature
            0       7     0  this   Lscala/collection/parallel/mutable/ParArray$;
            0       7     1   arr   Ljava/lang/Object;
            0       7     2    sz   I
    Signature: #72                          // <T:Ljava/lang/Object;>(Ljava/lang/Object;I)Lscala/collection/parallel/mutable/ParArray<TT;>;
    MethodParameters:
      Name                           Flags
      arr                            final
      sz                             final

  private <T extends java.lang.Object> scala.collection.parallel.mutable.ParArray<T> wrapOrRebuild(java.lang.Object, int);
    descriptor: (Ljava/lang/Object;I)Lscala/collection/parallel/mutable/ParArray;
    flags: (0x0002) ACC_PRIVATE
    Code:
      stack=5, locals=3, args_size=3
         0: new           #76                 // class scala/collection/parallel/mutable/ParArray
         3: dup
         4: getstatic     #81                 // Field scala/collection/mutable/ArraySeq$.MODULE$:Lscala/collection/mutable/ArraySeq$;
         7: getstatic     #62                 // Field scala/runtime/ScalaRunTime$.MODULE$:Lscala/runtime/ScalaRunTime$;
        10: aload_1
        11: invokevirtual #85                 // Method scala/runtime/ScalaRunTime$.toObjectArray:(Ljava/lang/Object;)[Ljava/lang/Object;
        14: invokevirtual #89                 // Method scala/collection/mutable/ArraySeq$.make:(Ljava/lang/Object;)Lscala/collection/mutable/ArraySeq;
        17: iload_2
        18: invokespecial #92                 // Method scala/collection/parallel/mutable/ParArray."<init>":(Lscala/collection/mutable/ArraySeq;I)V
        21: areturn
      LineNumberTable:
        line 705: 0
      LocalVariableTable:
        Start  Length  Slot  Name   Signature
            0      22     0  this   Lscala/collection/parallel/mutable/ParArray$;
            0      22     1   arr   Ljava/lang/Object;
            0      22     2    sz   I
    Signature: #72                          // <T:Ljava/lang/Object;>(Ljava/lang/Object;I)Lscala/collection/parallel/mutable/ParArray<TT;>;
    MethodParameters:
      Name                           Flags
      arr                            final
      sz                             final

  public <T extends java.lang.Object> scala.collection.parallel.mutable.ParArray<T> createFromCopy(T[], scala.reflect.ClassTag<T>);
    descriptor: ([Ljava/lang/Object;Lscala/reflect/ClassTag;)Lscala/collection/parallel/mutable/ParArray;
    flags: (0x0001) ACC_PUBLIC
    Code:
      stack=6, locals=4, args_size=3
         0: aload_2
         1: aload_1
         2: arraylength
         3: invokeinterface #102,  2          // InterfaceMethod scala/reflect/ClassTag.newArray:(I)Ljava/lang/Object;
         8: checkcast     #104                // class "[Ljava/lang/Object;"
        11: astore_3
        12: getstatic     #109                // Field scala/Array$.MODULE$:Lscala/Array$;
        15: aload_1
        16: iconst_0
        17: aload_3
        18: iconst_0
        19: aload_1
        20: arraylength
        21: invokevirtual #113                // Method scala/Array$.copy:(Ljava/lang/Object;ILjava/lang/Object;II)V
        24: aload_0
        25: aload_3
        26: invokevirtual #115                // Method handoff:(Ljava/lang/Object;)Lscala/collection/parallel/mutable/ParArray;
        29: areturn
      LineNumberTable:
        line 708: 0
        line 709: 12
        line 710: 24
      LocalVariableTable:
        Start  Length  Slot  Name   Signature
           12      17     3 newarr   [Ljava/lang/Object;
            0      30     0  this   Lscala/collection/parallel/mutable/ParArray$;
            0      30     1   arr   [Ljava/lang/Object;
            0      30     2 evidence$1   Lscala/reflect/ClassTag;
    Signature: #95                          // <T:Ljava/lang/Object;>([TT;Lscala/reflect/ClassTag<TT;>;)Lscala/collection/parallel/mutable/ParArray<TT;>;
    MethodParameters:
      Name                           Flags
      arr                            final
      evidence$1                     final

  public final <T extends java.lang.Object> scala.collection.parallel.mutable.ParArray<T> fromTraversables(scala.collection.immutable.Seq<scala.collection.IterableOnce<T>>);
    descriptor: (Lscala/collection/immutable/Seq;)Lscala/collection/parallel/mutable/ParArray;
    flags: (0x0011) ACC_PUBLIC, ACC_FINAL
    Code:
      stack=2, locals=2, args_size=2
         0: aload_0
         1: aload_1
         2: invokevirtual #124                // Method fromIterables:(Lscala/collection/immutable/Seq;)Lscala/collection/parallel/mutable/ParArray;
         5: areturn
      LineNumberTable:
        line 714: 0
      LocalVariableTable:
        Start  Length  Slot  Name   Signature
            0       6     0  this   Lscala/collection/parallel/mutable/ParArray$;
            0       6     1   xss   Lscala/collection/immutable/Seq;
    Signature: #120                         // <T:Ljava/lang/Object;>(Lscala/collection/immutable/Seq<Lscala/collection/IterableOnce<TT;>;>;)Lscala/collection/parallel/mutable/ParArray<TT;>;
    Deprecated: true
    MethodParameters:
      Name                           Flags
      xss                            final

  public <T extends java.lang.Object> scala.collection.parallel.mutable.ParArray<T> fromIterables(scala.collection.immutable.Seq<scala.collection.IterableOnce<T>>);
    descriptor: (Lscala/collection/immutable/Seq;)Lscala/collection/parallel/mutable/ParArray;
    flags: (0x0001) ACC_PUBLIC
    Code:
      stack=2, locals=3, args_size=2
         0: getstatic     #43                 // Field scala/collection/parallel/mutable/package$.MODULE$:Lscala/collection/parallel/mutable/package$;
         3: invokevirtual #47                 // Method scala/collection/parallel/mutable/package$.ParArrayCombiner:()Lscala/collection/parallel/mutable/ResizableParArrayCombiner$;
         6: invokevirtual #53                 // Method scala/collection/parallel/mutable/ResizableParArrayCombiner$.apply:()Lscala/collection/parallel/mutable/ResizableParArrayCombiner;
         9: astore_2
        10: aload_1
        11: aload_2
        12: invokedynamic #146,  0            // InvokeDynamic #0:apply:(Lscala/collection/parallel/mutable/ResizableParArrayCombiner;)Lscala/Function1;
        17: invokeinterface #152,  2          // InterfaceMethod scala/collection/immutable/Seq.foreach:(Lscala/Function1;)V
        22: aload_2
        23: invokeinterface #158,  1          // InterfaceMethod scala/collection/parallel/mutable/ResizableParArrayCombiner.result:()Ljava/lang/Object;
        28: checkcast     #76                 // class scala/collection/parallel/mutable/ParArray
        31: areturn
      LineNumberTable:
        line 717: 0
        line 718: 10
        line 721: 22
      LocalVariableTable:
        Start  Length  Slot  Name   Signature
           10      21     2    cb   Lscala/collection/parallel/mutable/ResizableParArrayCombiner;
            0      32     0  this   Lscala/collection/parallel/mutable/ParArray$;
            0      32     1   xss   Lscala/collection/immutable/Seq;
    Signature: #120                         // <T:Ljava/lang/Object;>(Lscala/collection/immutable/Seq<Lscala/collection/IterableOnce<TT;>;>;)Lscala/collection/parallel/mutable/ParArray<TT;>;
    MethodParameters:
      Name                           Flags
      xss                            final

  private java.lang.Object writeReplace();
    descriptor: ()Ljava/lang/Object;
    flags: (0x0002) ACC_PRIVATE
    Code:
      stack=3, locals=1, args_size=1
         0: new           #163                // class scala/runtime/ModuleSerializationProxy
         3: dup
         4: ldc           #2                  // class scala/collection/parallel/mutable/ParArray$
         6: invokespecial #166                // Method scala/runtime/ModuleSerializationProxy."<init>":(Ljava/lang/Class;)V
         9: areturn
      LineNumberTable:
        line 691: 0
      LocalVariableTable:
        Start  Length  Slot  Name   Signature
            0      10     0  this   Lscala/collection/parallel/mutable/ParArray$;

  public static final scala.collection.parallel.mutable.ResizableParArrayCombiner $anonfun$fromIterables$1(scala.collection.parallel.mutable.ResizableParArrayCombiner, scala.collection.IterableOnce);
    descriptor: (Lscala/collection/parallel/mutable/ResizableParArrayCombiner;Lscala/collection/IterableOnce;)Lscala/collection/parallel/mutable/ResizableParArrayCombiner;
    flags: (0x1019) ACC_PUBLIC, ACC_STATIC, ACC_FINAL, ACC_SYNTHETIC
    Code:
      stack=2, locals=2, args_size=2
         0: aload_0
         1: aload_1
         2: invokeinterface #172,  2          // InterfaceMethod scala/collection/parallel/mutable/ResizableParArrayCombiner.$plus$plus$eq:(Lscala/collection/IterableOnce;)Lscala/collection/mutable/Growable;
         7: checkcast     #154                // class scala/collection/parallel/mutable/ResizableParArrayCombiner
        10: areturn
      LineNumberTable:
        line 719: 0
      LocalVariableTable:
        Start  Length  Slot  Name   Signature
            0      11     0  cb$4   Lscala/collection/parallel/mutable/ResizableParArrayCombiner;
            0      11     1    xs   Lscala/collection/IterableOnce;
    MethodParameters:
      Name                           Flags
      cb$4                           final
      xs                             final

  private scala.collection.parallel.mutable.ParArray$();
    descriptor: ()V
    flags: (0x0002) ACC_PRIVATE
    Code:
      stack=1, locals=1, args_size=1
         0: aload_0
         1: invokespecial #174                // Method scala/collection/generic/ParFactory."<init>":()V
         4: return
      LineNumberTable:
        line 691: 0
      LocalVariableTable:
        Start  Length  Slot  Name   Signature
            0       5     0  this   Lscala/collection/parallel/mutable/ParArray$;

  private static java.lang.Object $deserializeLambda$(java.lang.invoke.SerializedLambda);
    descriptor: (Ljava/lang/invoke/SerializedLambda;)Ljava/lang/Object;
    flags: (0x100a) ACC_PRIVATE, ACC_STATIC, ACC_SYNTHETIC
    Code:
      stack=1, locals=1, args_size=1
         0: aload_0
         1: invokedynamic #186,  0            // InvokeDynamic #1:lambdaDeserialize:(Ljava/lang/invoke/SerializedLambda;)Ljava/lang/Object;
         6: areturn
}
InnerClasses:
  public static final #13= #10 of #12;    // Lookup=class java/lang/invoke/MethodHandles$Lookup of class java/lang/invoke/MethodHandles
  public #16= #15 of #5;                  // GenericCanCombineFrom=class scala/collection/generic/ParFactory$GenericCanCombineFrom of class scala/collection/generic/ParFactory
Signature: #3                           // Lscala/collection/generic/ParFactory<Lscala/collection/parallel/mutable/ParArray;>;Ljava/io/Serializable;
SourceFile: "ParArray.scala"
BootstrapMethods:
  0: #143 REF_invokeStatic java/lang/invoke/LambdaMetafactory.altMetafactory:(Ljava/lang/invoke/MethodHandles$Lookup;Ljava/lang/String;Ljava/lang/invoke/MethodType;[Ljava/lang/Object;)Ljava/lang/invoke/CallSite;
    Method arguments:
      #127 (Ljava/lang/Object;)Ljava/lang/Object;
      #132 REF_invokeStatic scala/collection/parallel/mutable/ParArray$.$anonfun$fromIterables$1:(Lscala/collection/parallel/mutable/ResizableParArrayCombiner;Lscala/collection/IterableOnce;)Lscala/collection/parallel/mutable/ResizableParArrayCombiner;
      #134 (Lscala/collection/IterableOnce;)Lscala/collection/parallel/mutable/ResizableParArrayCombiner;
      #135 5
      #136 1
      #134 (Lscala/collection/IterableOnce;)Lscala/collection/parallel/mutable/ResizableParArrayCombiner;
  1: #183 REF_invokeStatic scala/runtime/LambdaDeserialize.bootstrap:(Ljava/lang/invoke/MethodHandles$Lookup;Ljava/lang/String;Ljava/lang/invoke/MethodType;[Ljava/lang/invoke/MethodHandle;)Ljava/lang/invoke/CallSite;
    Method arguments:
      #132 REF_invokeStatic scala/collection/parallel/mutable/ParArray$.$anonfun$fromIterables$1:(Lscala/collection/parallel/mutable/ResizableParArrayCombiner;Lscala/collection/IterableOnce;)Lscala/collection/parallel/mutable/ResizableParArrayCombiner;
  ScalaInlineInfo: length = 0x40 (unknown attribute)
   01 01 00 0C 00 80 00 81 01 00 15 00 14 01 00 1A
   00 1B 01 00 5D 00 5E 01 00 7A 00 77 01 00 76 00
   77 05 00 36 00 37 01 00 36 00 44 01 00 21 00 22
   01 00 24 00 22 01 00 43 00 44 01 00 A1 00 9C 01

  Scala: length = 0x0 (unknown attribute)

