Classfile /Users/mw/Projects/slang-braindump/.jar/jar8/assemble/slang-braindump/assemble/content/scala/collection/parallel/mutable/ParHashMapCombiner$AddingHashTable.class
  Last modified May 29, 2022; size 12767 bytes
  SHA-256 checksum 91383b6007c7337c5e4cf02fd539845c9d40d49392b91d098d8aeb7abe3202c9
  Compiled from "ParHashMap.scala"
public class scala.collection.parallel.mutable.ParHashMapCombiner$AddingHashTable extends java.lang.Object implements scala.collection.mutable.HashTable<K, V, scala.collection.parallel.mutable.ParHashMap$DefaultEntry<K, V>>, scala.collection.parallel.mutable.WithContents<K, V, scala.collection.parallel.mutable.ParHashMap$DefaultEntry<K, V>>
  minor version: 0
  major version: 52
  flags: (0x0021) ACC_PUBLIC, ACC_SUPER
  this_class: #2                          // scala/collection/parallel/mutable/ParHashMapCombiner$AddingHashTable
  super_class: #5                         // java/lang/Object
  interfaces: 2, fields: 7, methods: 52, attributes: 5
Constant pool:
    #1 = Utf8               scala/collection/parallel/mutable/ParHashMapCombiner$AddingHashTable
    #2 = Class              #1            // scala/collection/parallel/mutable/ParHashMapCombiner$AddingHashTable
    #3 = Utf8               Ljava/lang/Object;Lscala/collection/mutable/HashTable<TK;TV;Lscala/collection/parallel/mutable/ParHashMap$DefaultEntry<TK;TV;>;>;Lscala/collection/parallel/mutable/WithContents<TK;TV;Lscala/collection/parallel/mutable/ParHashMap$DefaultEntry<TK;TV;>;>;
    #4 = Utf8               java/lang/Object
    #5 = Class              #4            // java/lang/Object
    #6 = Utf8               scala/collection/mutable/HashTable
    #7 = Class              #6            // scala/collection/mutable/HashTable
    #8 = Utf8               scala/collection/parallel/mutable/WithContents
    #9 = Class              #8            // scala/collection/parallel/mutable/WithContents
   #10 = Utf8               ParHashMap.scala
   #11 = Utf8               scala/collection/mutable/HashTable$HashUtils
   #12 = Class              #11           // scala/collection/mutable/HashTable$HashUtils
   #13 = Utf8               HashUtils
   #14 = Utf8               scala/collection/parallel/mutable/ParHashMap$DefaultEntry
   #15 = Class              #14           // scala/collection/parallel/mutable/ParHashMap$DefaultEntry
   #16 = Utf8               scala/collection/parallel/mutable/ParHashMap
   #17 = Class              #16           // scala/collection/parallel/mutable/ParHashMap
   #18 = Utf8               DefaultEntry
   #19 = Utf8               scala/collection/parallel/mutable/ParHashMapCombiner
   #20 = Class              #19           // scala/collection/parallel/mutable/ParHashMapCombiner
   #21 = Utf8               AddingHashTable
   #22 = Utf8               scala/collection/parallel/mutable/ParHashTable$Contents
   #23 = Class              #22           // scala/collection/parallel/mutable/ParHashTable$Contents
   #24 = Utf8               scala/collection/parallel/mutable/ParHashTable
   #25 = Class              #24           // scala/collection/parallel/mutable/ParHashTable
   #26 = Utf8               Contents
   #27 = Utf8               _loadFactor
   #28 = Utf8               I
   #29 = Utf8               table
   #30 = Utf8               [Lscala/collection/mutable/HashEntry;
   #31 = Utf8               [Lscala/collection/mutable/HashEntry<TK;Lscala/collection/parallel/mutable/ParHashMap$DefaultEntry<TK;TV;>;>;
   #32 = Utf8               tableSize
   #33 = Utf8               threshold
   #34 = Utf8               sizemap
   #35 = Utf8               [I
   #36 = Utf8               seedvalue
   #37 = Utf8               $outer
   #38 = Utf8               Lscala/collection/parallel/mutable/ParHashMapCombiner;
   #39 = Utf8               initWithContents
   #40 = Utf8               (Lscala/collection/parallel/mutable/ParHashTable$Contents;)V
   #41 = Utf8               (Lscala/collection/parallel/mutable/ParHashTable$Contents<TK;Lscala/collection/parallel/mutable/ParHashMap$DefaultEntry<TK;TV;>;>;)V
   #42 = Utf8               c
   #43 = Utf8               initWithContents$
   #44 = Utf8               (Lscala/collection/parallel/mutable/WithContents;Lscala/collection/parallel/mutable/ParHashTable$Contents;)V
   #45 = NameAndType        #43:#44       // initWithContents$:(Lscala/collection/parallel/mutable/WithContents;Lscala/collection/parallel/mutable/ParHashTable$Contents;)V
   #46 = InterfaceMethodref #9.#45        // scala/collection/parallel/mutable/WithContents.initWithContents$:(Lscala/collection/parallel/mutable/WithContents;Lscala/collection/parallel/mutable/ParHashTable$Contents;)V
   #47 = Utf8               this
   #48 = Utf8               Lscala/collection/parallel/mutable/ParHashMapCombiner$AddingHashTable;
   #49 = Utf8               Lscala/collection/parallel/mutable/ParHashTable$Contents;
   #50 = Utf8               hashTableContents
   #51 = Utf8               ()Lscala/collection/parallel/mutable/ParHashTable$Contents;
   #52 = Utf8               ()Lscala/collection/parallel/mutable/ParHashTable$Contents<TK;Lscala/collection/parallel/mutable/ParHashMap$DefaultEntry<TK;TV;>;>;
   #53 = Utf8               hashTableContents$
   #54 = Utf8               (Lscala/collection/parallel/mutable/WithContents;)Lscala/collection/parallel/mutable/ParHashTable$Contents;
   #55 = NameAndType        #53:#54       // hashTableContents$:(Lscala/collection/parallel/mutable/WithContents;)Lscala/collection/parallel/mutable/ParHashTable$Contents;
   #56 = InterfaceMethodref #9.#55        // scala/collection/parallel/mutable/WithContents.hashTableContents$:(Lscala/collection/parallel/mutable/WithContents;)Lscala/collection/parallel/mutable/ParHashTable$Contents;
   #57 = Utf8               size
   #58 = Utf8               ()I
   #59 = Utf8               size$
   #60 = Utf8               (Lscala/collection/mutable/HashTable;)I
   #61 = NameAndType        #59:#60       // size$:(Lscala/collection/mutable/HashTable;)I
   #62 = InterfaceMethodref #7.#61        // scala/collection/mutable/HashTable.size$:(Lscala/collection/mutable/HashTable;)I
   #63 = Utf8               tableSizeSeed
   #64 = Utf8               tableSizeSeed$
   #65 = NameAndType        #64:#60       // tableSizeSeed$:(Lscala/collection/mutable/HashTable;)I
   #66 = InterfaceMethodref #7.#65        // scala/collection/mutable/HashTable.tableSizeSeed$:(Lscala/collection/mutable/HashTable;)I
   #67 = Utf8               initialSize
   #68 = Utf8               initialSize$
   #69 = NameAndType        #68:#60       // initialSize$:(Lscala/collection/mutable/HashTable;)I
   #70 = InterfaceMethodref #7.#69        // scala/collection/mutable/HashTable.initialSize$:(Lscala/collection/mutable/HashTable;)I
   #71 = Utf8               init
   #72 = Utf8               (Ljava/io/ObjectInputStream;Lscala/Function0;)V
   #73 = Utf8               (Ljava/io/ObjectInputStream;Lscala/Function0<Lscala/collection/parallel/mutable/ParHashMap$DefaultEntry<TK;TV;>;>;)V
   #74 = Utf8               in
   #75 = Utf8               readEntry
   #76 = Utf8               init$
   #77 = Utf8               (Lscala/collection/mutable/HashTable;Ljava/io/ObjectInputStream;Lscala/Function0;)V
   #78 = NameAndType        #76:#77       // init$:(Lscala/collection/mutable/HashTable;Ljava/io/ObjectInputStream;Lscala/Function0;)V
   #79 = InterfaceMethodref #7.#78        // scala/collection/mutable/HashTable.init$:(Lscala/collection/mutable/HashTable;Ljava/io/ObjectInputStream;Lscala/Function0;)V
   #80 = Utf8               Ljava/io/ObjectInputStream;
   #81 = Utf8               Lscala/Function0;
   #82 = Utf8               serializeTo
   #83 = Utf8               (Ljava/io/ObjectOutputStream;Lscala/Function1;)V
   #84 = Utf8               (Ljava/io/ObjectOutputStream;Lscala/Function1<Lscala/collection/parallel/mutable/ParHashMap$DefaultEntry<TK;TV;>;Lscala/runtime/BoxedUnit;>;)V
   #85 = Utf8               out
   #86 = Utf8               writeEntry
   #87 = Utf8               serializeTo$
   #88 = Utf8               (Lscala/collection/mutable/HashTable;Ljava/io/ObjectOutputStream;Lscala/Function1;)V
   #89 = NameAndType        #87:#88       // serializeTo$:(Lscala/collection/mutable/HashTable;Ljava/io/ObjectOutputStream;Lscala/Function1;)V
   #90 = InterfaceMethodref #7.#89        // scala/collection/mutable/HashTable.serializeTo$:(Lscala/collection/mutable/HashTable;Ljava/io/ObjectOutputStream;Lscala/Function1;)V
   #91 = Utf8               Ljava/io/ObjectOutputStream;
   #92 = Utf8               Lscala/Function1;
   #93 = Utf8               findEntry
   #94 = Utf8               (Ljava/lang/Object;)Lscala/collection/mutable/HashEntry;
   #95 = Utf8               key
   #96 = Utf8               findEntry$
   #97 = Utf8               (Lscala/collection/mutable/HashTable;Ljava/lang/Object;)Lscala/collection/mutable/HashEntry;
   #98 = NameAndType        #96:#97       // findEntry$:(Lscala/collection/mutable/HashTable;Ljava/lang/Object;)Lscala/collection/mutable/HashEntry;
   #99 = InterfaceMethodref #7.#98        // scala/collection/mutable/HashTable.findEntry$:(Lscala/collection/mutable/HashTable;Ljava/lang/Object;)Lscala/collection/mutable/HashEntry;
  #100 = Utf8               Ljava/lang/Object;
  #101 = Utf8               findEntry0
  #102 = Utf8               (Ljava/lang/Object;I)Lscala/collection/mutable/HashEntry;
  #103 = Utf8               h
  #104 = Utf8               findEntry0$
  #105 = Utf8               (Lscala/collection/mutable/HashTable;Ljava/lang/Object;I)Lscala/collection/mutable/HashEntry;
  #106 = NameAndType        #104:#105     // findEntry0$:(Lscala/collection/mutable/HashTable;Ljava/lang/Object;I)Lscala/collection/mutable/HashEntry;
  #107 = InterfaceMethodref #7.#106       // scala/collection/mutable/HashTable.findEntry0$:(Lscala/collection/mutable/HashTable;Ljava/lang/Object;I)Lscala/collection/mutable/HashEntry;
  #108 = Utf8               addEntry
  #109 = Utf8               (Lscala/collection/mutable/HashEntry;)V
  #110 = Utf8               e
  #111 = Utf8               addEntry$
  #112 = Utf8               (Lscala/collection/mutable/HashTable;Lscala/collection/mutable/HashEntry;)V
  #113 = NameAndType        #111:#112     // addEntry$:(Lscala/collection/mutable/HashTable;Lscala/collection/mutable/HashEntry;)V
  #114 = InterfaceMethodref #7.#113       // scala/collection/mutable/HashTable.addEntry$:(Lscala/collection/mutable/HashTable;Lscala/collection/mutable/HashEntry;)V
  #115 = Utf8               Lscala/collection/mutable/HashEntry;
  #116 = Utf8               addEntry0
  #117 = Utf8               (Lscala/collection/mutable/HashEntry;I)V
  #118 = Utf8               addEntry0$
  #119 = Utf8               (Lscala/collection/mutable/HashTable;Lscala/collection/mutable/HashEntry;I)V
  #120 = NameAndType        #118:#119     // addEntry0$:(Lscala/collection/mutable/HashTable;Lscala/collection/mutable/HashEntry;I)V
  #121 = InterfaceMethodref #7.#120       // scala/collection/mutable/HashTable.addEntry0$:(Lscala/collection/mutable/HashTable;Lscala/collection/mutable/HashEntry;I)V
  #122 = Utf8               findOrAddEntry
  #123 = Utf8               (Ljava/lang/Object;Ljava/lang/Object;)Lscala/collection/mutable/HashEntry;
  #124 = Utf8               value
  #125 = Utf8               findOrAddEntry$
  #126 = Utf8               (Lscala/collection/mutable/HashTable;Ljava/lang/Object;Ljava/lang/Object;)Lscala/collection/mutable/HashEntry;
  #127 = NameAndType        #125:#126     // findOrAddEntry$:(Lscala/collection/mutable/HashTable;Ljava/lang/Object;Ljava/lang/Object;)Lscala/collection/mutable/HashEntry;
  #128 = InterfaceMethodref #7.#127       // scala/collection/mutable/HashTable.findOrAddEntry$:(Lscala/collection/mutable/HashTable;Ljava/lang/Object;Ljava/lang/Object;)Lscala/collection/mutable/HashEntry;
  #129 = Utf8               removeEntry
  #130 = Utf8               removeEntry$
  #131 = NameAndType        #130:#97      // removeEntry$:(Lscala/collection/mutable/HashTable;Ljava/lang/Object;)Lscala/collection/mutable/HashEntry;
  #132 = InterfaceMethodref #7.#131       // scala/collection/mutable/HashTable.removeEntry$:(Lscala/collection/mutable/HashTable;Ljava/lang/Object;)Lscala/collection/mutable/HashEntry;
  #133 = Utf8               removeEntry0
  #134 = Utf8               removeEntry0$
  #135 = NameAndType        #134:#105     // removeEntry0$:(Lscala/collection/mutable/HashTable;Ljava/lang/Object;I)Lscala/collection/mutable/HashEntry;
  #136 = InterfaceMethodref #7.#135       // scala/collection/mutable/HashTable.removeEntry0$:(Lscala/collection/mutable/HashTable;Ljava/lang/Object;I)Lscala/collection/mutable/HashEntry;
  #137 = Utf8               entriesIterator
  #138 = Utf8               ()Lscala/collection/Iterator;
  #139 = Utf8               ()Lscala/collection/Iterator<Lscala/collection/parallel/mutable/ParHashMap$DefaultEntry<TK;TV;>;>;
  #140 = Utf8               entriesIterator$
  #141 = Utf8               (Lscala/collection/mutable/HashTable;)Lscala/collection/Iterator;
  #142 = NameAndType        #140:#141     // entriesIterator$:(Lscala/collection/mutable/HashTable;)Lscala/collection/Iterator;
  #143 = InterfaceMethodref #7.#142       // scala/collection/mutable/HashTable.entriesIterator$:(Lscala/collection/mutable/HashTable;)Lscala/collection/Iterator;
  #144 = Utf8               foreachEntry
  #145 = Utf8               (Lscala/Function1;)V
  #146 = Utf8               <U:Ljava/lang/Object;>(Lscala/Function1<Lscala/collection/parallel/mutable/ParHashMap$DefaultEntry<TK;TV;>;TU;>;)V
  #147 = Utf8               f
  #148 = Utf8               foreachEntry$
  #149 = Utf8               (Lscala/collection/mutable/HashTable;Lscala/Function1;)V
  #150 = NameAndType        #148:#149     // foreachEntry$:(Lscala/collection/mutable/HashTable;Lscala/Function1;)V
  #151 = InterfaceMethodref #7.#150       // scala/collection/mutable/HashTable.foreachEntry$:(Lscala/collection/mutable/HashTable;Lscala/Function1;)V
  #152 = Utf8               clearTable
  #153 = Utf8               ()V
  #154 = Utf8               clearTable$
  #155 = Utf8               (Lscala/collection/mutable/HashTable;)V
  #156 = NameAndType        #154:#155     // clearTable$:(Lscala/collection/mutable/HashTable;)V
  #157 = InterfaceMethodref #7.#156       // scala/collection/mutable/HashTable.clearTable$:(Lscala/collection/mutable/HashTable;)V
  #158 = Utf8               nnSizeMapAdd
  #159 = Utf8               (I)V
  #160 = Utf8               nnSizeMapAdd$
  #161 = Utf8               (Lscala/collection/mutable/HashTable;I)V
  #162 = NameAndType        #160:#161     // nnSizeMapAdd$:(Lscala/collection/mutable/HashTable;I)V
  #163 = InterfaceMethodref #7.#162       // scala/collection/mutable/HashTable.nnSizeMapAdd$:(Lscala/collection/mutable/HashTable;I)V
  #164 = Utf8               nnSizeMapRemove
  #165 = Utf8               nnSizeMapRemove$
  #166 = NameAndType        #165:#161     // nnSizeMapRemove$:(Lscala/collection/mutable/HashTable;I)V
  #167 = InterfaceMethodref #7.#166       // scala/collection/mutable/HashTable.nnSizeMapRemove$:(Lscala/collection/mutable/HashTable;I)V
  #168 = Utf8               nnSizeMapReset
  #169 = Utf8               tableLength
  #170 = Utf8               nnSizeMapReset$
  #171 = NameAndType        #170:#161     // nnSizeMapReset$:(Lscala/collection/mutable/HashTable;I)V
  #172 = InterfaceMethodref #7.#171       // scala/collection/mutable/HashTable.nnSizeMapReset$:(Lscala/collection/mutable/HashTable;I)V
  #173 = Utf8               totalSizeMapBuckets
  #174 = Utf8               totalSizeMapBuckets$
  #175 = NameAndType        #174:#60      // totalSizeMapBuckets$:(Lscala/collection/mutable/HashTable;)I
  #176 = InterfaceMethodref #7.#175       // scala/collection/mutable/HashTable.totalSizeMapBuckets$:(Lscala/collection/mutable/HashTable;)I
  #177 = Utf8               calcSizeMapSize
  #178 = Utf8               (I)I
  #179 = Utf8               calcSizeMapSize$
  #180 = Utf8               (Lscala/collection/mutable/HashTable;I)I
  #181 = NameAndType        #179:#180     // calcSizeMapSize$:(Lscala/collection/mutable/HashTable;I)I
  #182 = InterfaceMethodref #7.#181       // scala/collection/mutable/HashTable.calcSizeMapSize$:(Lscala/collection/mutable/HashTable;I)I
  #183 = Utf8               sizeMapInit
  #184 = Utf8               sizeMapInit$
  #185 = NameAndType        #184:#161     // sizeMapInit$:(Lscala/collection/mutable/HashTable;I)V
  #186 = InterfaceMethodref #7.#185       // scala/collection/mutable/HashTable.sizeMapInit$:(Lscala/collection/mutable/HashTable;I)V
  #187 = Utf8               sizeMapInitAndRebuild
  #188 = Utf8               sizeMapInitAndRebuild$
  #189 = NameAndType        #188:#155     // sizeMapInitAndRebuild$:(Lscala/collection/mutable/HashTable;)V
  #190 = InterfaceMethodref #7.#189       // scala/collection/mutable/HashTable.sizeMapInitAndRebuild$:(Lscala/collection/mutable/HashTable;)V
  #191 = Utf8               printSizeMap
  #192 = Utf8               printSizeMap$
  #193 = NameAndType        #192:#155     // printSizeMap$:(Lscala/collection/mutable/HashTable;)V
  #194 = InterfaceMethodref #7.#193       // scala/collection/mutable/HashTable.printSizeMap$:(Lscala/collection/mutable/HashTable;)V
  #195 = Utf8               sizeMapDisable
  #196 = Utf8               sizeMapDisable$
  #197 = NameAndType        #196:#155     // sizeMapDisable$:(Lscala/collection/mutable/HashTable;)V
  #198 = InterfaceMethodref #7.#197       // scala/collection/mutable/HashTable.sizeMapDisable$:(Lscala/collection/mutable/HashTable;)V
  #199 = Utf8               isSizeMapDefined
  #200 = Utf8               ()Z
  #201 = Utf8               isSizeMapDefined$
  #202 = Utf8               (Lscala/collection/mutable/HashTable;)Z
  #203 = NameAndType        #201:#202     // isSizeMapDefined$:(Lscala/collection/mutable/HashTable;)Z
  #204 = InterfaceMethodref #7.#203       // scala/collection/mutable/HashTable.isSizeMapDefined$:(Lscala/collection/mutable/HashTable;)Z
  #205 = Utf8               alwaysInitSizeMap
  #206 = Utf8               alwaysInitSizeMap$
  #207 = NameAndType        #206:#202     // alwaysInitSizeMap$:(Lscala/collection/mutable/HashTable;)Z
  #208 = InterfaceMethodref #7.#207       // scala/collection/mutable/HashTable.alwaysInitSizeMap$:(Lscala/collection/mutable/HashTable;)Z
  #209 = Utf8               elemEquals
  #210 = Utf8               (Ljava/lang/Object;Ljava/lang/Object;)Z
  #211 = Utf8               (TK;TK;)Z
  #212 = Utf8               key1
  #213 = Utf8               key2
  #214 = Utf8               elemEquals$
  #215 = Utf8               (Lscala/collection/mutable/HashTable;Ljava/lang/Object;Ljava/lang/Object;)Z
  #216 = NameAndType        #214:#215     // elemEquals$:(Lscala/collection/mutable/HashTable;Ljava/lang/Object;Ljava/lang/Object;)Z
  #217 = InterfaceMethodref #7.#216       // scala/collection/mutable/HashTable.elemEquals$:(Lscala/collection/mutable/HashTable;Ljava/lang/Object;Ljava/lang/Object;)Z
  #218 = Utf8               index
  #219 = Utf8               hcode
  #220 = Utf8               index$
  #221 = NameAndType        #220:#180     // index$:(Lscala/collection/mutable/HashTable;I)I
  #222 = InterfaceMethodref #7.#221       // scala/collection/mutable/HashTable.index$:(Lscala/collection/mutable/HashTable;I)I
  #223 = Utf8               sizeMapBucketBitSize
  #224 = Utf8               sizeMapBucketBitSize$
  #225 = Utf8               (Lscala/collection/mutable/HashTable$HashUtils;)I
  #226 = NameAndType        #224:#225     // sizeMapBucketBitSize$:(Lscala/collection/mutable/HashTable$HashUtils;)I
  #227 = InterfaceMethodref #12.#226      // scala/collection/mutable/HashTable$HashUtils.sizeMapBucketBitSize$:(Lscala/collection/mutable/HashTable$HashUtils;)I
  #228 = Utf8               sizeMapBucketSize
  #229 = Utf8               sizeMapBucketSize$
  #230 = NameAndType        #229:#225     // sizeMapBucketSize$:(Lscala/collection/mutable/HashTable$HashUtils;)I
  #231 = InterfaceMethodref #12.#230      // scala/collection/mutable/HashTable$HashUtils.sizeMapBucketSize$:(Lscala/collection/mutable/HashTable$HashUtils;)I
  #232 = Utf8               elemHashCode
  #233 = Utf8               (Ljava/lang/Object;)I
  #234 = Utf8               (TK;)I
  #235 = Utf8               elemHashCode$
  #236 = Utf8               (Lscala/collection/mutable/HashTable$HashUtils;Ljava/lang/Object;)I
  #237 = NameAndType        #235:#236     // elemHashCode$:(Lscala/collection/mutable/HashTable$HashUtils;Ljava/lang/Object;)I
  #238 = InterfaceMethodref #12.#237      // scala/collection/mutable/HashTable$HashUtils.elemHashCode$:(Lscala/collection/mutable/HashTable$HashUtils;Ljava/lang/Object;)I
  #239 = Utf8               improve
  #240 = Utf8               (II)I
  #241 = Utf8               seed
  #242 = Utf8               improve$
  #243 = Utf8               (Lscala/collection/mutable/HashTable$HashUtils;II)I
  #244 = NameAndType        #242:#243     // improve$:(Lscala/collection/mutable/HashTable$HashUtils;II)I
  #245 = InterfaceMethodref #12.#244      // scala/collection/mutable/HashTable$HashUtils.improve$:(Lscala/collection/mutable/HashTable$HashUtils;II)I
  #246 = NameAndType        #27:#28       // _loadFactor:I
  #247 = Fieldref           #2.#246       // scala/collection/parallel/mutable/ParHashMapCombiner$AddingHashTable._loadFactor:I
  #248 = Utf8               _loadFactor_$eq
  #249 = Utf8               x$1
  #250 = Utf8               ()[Lscala/collection/mutable/HashEntry;
  #251 = Utf8               ()[Lscala/collection/mutable/HashEntry<TK;Lscala/collection/parallel/mutable/ParHashMap$DefaultEntry<TK;TV;>;>;
  #252 = NameAndType        #29:#30       // table:[Lscala/collection/mutable/HashEntry;
  #253 = Fieldref           #2.#252       // scala/collection/parallel/mutable/ParHashMapCombiner$AddingHashTable.table:[Lscala/collection/mutable/HashEntry;
  #254 = Utf8               table_$eq
  #255 = Utf8               ([Lscala/collection/mutable/HashEntry;)V
  #256 = Utf8               ([Lscala/collection/mutable/HashEntry<TK;Lscala/collection/parallel/mutable/ParHashMap$DefaultEntry<TK;TV;>;>;)V
  #257 = NameAndType        #32:#28       // tableSize:I
  #258 = Fieldref           #2.#257       // scala/collection/parallel/mutable/ParHashMapCombiner$AddingHashTable.tableSize:I
  #259 = Utf8               tableSize_$eq
  #260 = NameAndType        #33:#28       // threshold:I
  #261 = Fieldref           #2.#260       // scala/collection/parallel/mutable/ParHashMapCombiner$AddingHashTable.threshold:I
  #262 = Utf8               threshold_$eq
  #263 = Utf8               ()[I
  #264 = NameAndType        #34:#35       // sizemap:[I
  #265 = Fieldref           #2.#264       // scala/collection/parallel/mutable/ParHashMapCombiner$AddingHashTable.sizemap:[I
  #266 = Utf8               sizemap_$eq
  #267 = Utf8               ([I)V
  #268 = NameAndType        #36:#28       // seedvalue:I
  #269 = Fieldref           #2.#268       // scala/collection/parallel/mutable/ParHashMapCombiner$AddingHashTable.seedvalue:I
  #270 = Utf8               seedvalue_$eq
  #271 = Utf8               setSize
  #272 = Utf8               sz
  #273 = NameAndType        #259:#159     // tableSize_$eq:(I)V
  #274 = Methodref          #2.#273       // scala/collection/parallel/mutable/ParHashMapCombiner$AddingHashTable.tableSize_$eq:(I)V
  #275 = Utf8               insertEntry
  #276 = Utf8               (Lscala/collection/parallel/mutable/ParHashMap$DefaultEntry;)Z
  #277 = Utf8               (Lscala/collection/parallel/mutable/ParHashMap$DefaultEntry<TK;TV;>;)Z
  #278 = Utf8               ()Ljava/lang/Object;
  #279 = NameAndType        #95:#278      // key:()Ljava/lang/Object;
  #280 = Methodref          #15.#279      // scala/collection/parallel/mutable/ParHashMap$DefaultEntry.key:()Ljava/lang/Object;
  #281 = NameAndType        #232:#233     // elemHashCode:(Ljava/lang/Object;)I
  #282 = Methodref          #2.#281       // scala/collection/parallel/mutable/ParHashMapCombiner$AddingHashTable.elemHashCode:(Ljava/lang/Object;)I
  #283 = NameAndType        #218:#178     // index:(I)I
  #284 = Methodref          #2.#283       // scala/collection/parallel/mutable/ParHashMapCombiner$AddingHashTable.index:(I)I
  #285 = NameAndType        #29:#250      // table:()[Lscala/collection/mutable/HashEntry;
  #286 = Methodref          #2.#285       // scala/collection/parallel/mutable/ParHashMapCombiner$AddingHashTable.table:()[Lscala/collection/mutable/HashEntry;
  #287 = Utf8               scala/runtime/BoxesRunTime
  #288 = Class              #287          // scala/runtime/BoxesRunTime
  #289 = Utf8               equals
  #290 = NameAndType        #289:#210     // equals:(Ljava/lang/Object;Ljava/lang/Object;)Z
  #291 = Methodref          #288.#290     // scala/runtime/BoxesRunTime.equals:(Ljava/lang/Object;Ljava/lang/Object;)Z
  #292 = Utf8               next
  #293 = Utf8               ()Lscala/collection/mutable/HashEntry;
  #294 = NameAndType        #292:#293     // next:()Lscala/collection/mutable/HashEntry;
  #295 = Methodref          #15.#294      // scala/collection/parallel/mutable/ParHashMap$DefaultEntry.next:()Lscala/collection/mutable/HashEntry;
  #296 = Utf8               next_$eq
  #297 = NameAndType        #296:#109     // next_$eq:(Lscala/collection/mutable/HashEntry;)V
  #298 = Methodref          #15.#297      // scala/collection/parallel/mutable/ParHashMap$DefaultEntry.next_$eq:(Lscala/collection/mutable/HashEntry;)V
  #299 = NameAndType        #158:#159     // nnSizeMapAdd:(I)V
  #300 = Methodref          #2.#299       // scala/collection/parallel/mutable/ParHashMapCombiner$AddingHashTable.nnSizeMapAdd:(I)V
  #301 = Utf8               olde
  #302 = Utf8               Lscala/collection/parallel/mutable/ParHashMap$DefaultEntry;
  #303 = Utf8               ce
  #304 = Utf8               createNewEntry
  #305 = Utf8               (Ljava/lang/Object;Ljava/lang/Object;)Lscala/runtime/Nothing$;
  #306 = Utf8               (TK;TV;)Lscala/runtime/Nothing$;
  #307 = Utf8               x
  #308 = Utf8               scala/Predef$
  #309 = Class              #308          // scala/Predef$
  #310 = Utf8               MODULE$
  #311 = Utf8               Lscala/Predef$;
  #312 = NameAndType        #310:#311     // MODULE$:Lscala/Predef$;
  #313 = Fieldref           #309.#312     // scala/Predef$.MODULE$:Lscala/Predef$;
  #314 = Utf8               $qmark$qmark$qmark
  #315 = Utf8               ()Lscala/runtime/Nothing$;
  #316 = NameAndType        #314:#315     // $qmark$qmark$qmark:()Lscala/runtime/Nothing$;
  #317 = Methodref          #309.#316     // scala/Predef$.$qmark$qmark$qmark:()Lscala/runtime/Nothing$;
  #318 = Utf8               scala$collection$parallel$mutable$ParHashMapCombiner$AddingHashTable$$$outer
  #319 = Utf8               ()Lscala/collection/parallel/mutable/ParHashMapCombiner;
  #320 = NameAndType        #37:#38       // $outer:Lscala/collection/parallel/mutable/ParHashMapCombiner;
  #321 = Fieldref           #2.#320       // scala/collection/parallel/mutable/ParHashMapCombiner$AddingHashTable.$outer:Lscala/collection/parallel/mutable/ParHashMapCombiner;
  #322 = NameAndType        #304:#305     // createNewEntry:(Ljava/lang/Object;Ljava/lang/Object;)Lscala/runtime/Nothing$;
  #323 = Methodref          #2.#322       // scala/collection/parallel/mutable/ParHashMapCombiner$AddingHashTable.createNewEntry:(Ljava/lang/Object;Ljava/lang/Object;)Lscala/runtime/Nothing$;
  #324 = Utf8               <init>
  #325 = Utf8               (Lscala/collection/parallel/mutable/ParHashMapCombiner;III)V
  #326 = Utf8               numelems
  #327 = Utf8               lf
  #328 = Utf8               _seedvalue
  #329 = NameAndType        #324:#153     // "<init>":()V
  #330 = Methodref          #5.#329       // java/lang/Object."<init>":()V
  #331 = Utf8               $init$
  #332 = Utf8               (Lscala/collection/mutable/HashTable$HashUtils;)V
  #333 = NameAndType        #331:#332     // $init$:(Lscala/collection/mutable/HashTable$HashUtils;)V
  #334 = InterfaceMethodref #12.#333      // scala/collection/mutable/HashTable$HashUtils.$init$:(Lscala/collection/mutable/HashTable$HashUtils;)V
  #335 = NameAndType        #331:#155     // $init$:(Lscala/collection/mutable/HashTable;)V
  #336 = InterfaceMethodref #7.#335       // scala/collection/mutable/HashTable.$init$:(Lscala/collection/mutable/HashTable;)V
  #337 = Utf8               (Lscala/collection/parallel/mutable/WithContents;)V
  #338 = NameAndType        #331:#337     // $init$:(Lscala/collection/parallel/mutable/WithContents;)V
  #339 = InterfaceMethodref #9.#338       // scala/collection/parallel/mutable/WithContents.$init$:(Lscala/collection/parallel/mutable/WithContents;)V
  #340 = NameAndType        #248:#159     // _loadFactor_$eq:(I)V
  #341 = Methodref          #2.#340       // scala/collection/parallel/mutable/ParHashMapCombiner$AddingHashTable._loadFactor_$eq:(I)V
  #342 = Utf8               scala/collection/mutable/HashTable$
  #343 = Class              #342          // scala/collection/mutable/HashTable$
  #344 = Utf8               Lscala/collection/mutable/HashTable$;
  #345 = NameAndType        #310:#344     // MODULE$:Lscala/collection/mutable/HashTable$;
  #346 = Fieldref           #343.#345     // scala/collection/mutable/HashTable$.MODULE$:Lscala/collection/mutable/HashTable$;
  #347 = NameAndType        #27:#58       // _loadFactor:()I
  #348 = Methodref          #2.#347       // scala/collection/parallel/mutable/ParHashMapCombiner$AddingHashTable._loadFactor:()I
  #349 = Utf8               sizeForThreshold
  #350 = NameAndType        #349:#240     // sizeForThreshold:(II)I
  #351 = Methodref          #343.#350     // scala/collection/mutable/HashTable$.sizeForThreshold:(II)I
  #352 = Utf8               capacity
  #353 = NameAndType        #352:#178     // capacity:(I)I
  #354 = Methodref          #343.#353     // scala/collection/mutable/HashTable$.capacity:(I)I
  #355 = Utf8               scala/collection/mutable/HashEntry
  #356 = Class              #355          // scala/collection/mutable/HashEntry
  #357 = NameAndType        #254:#255     // table_$eq:([Lscala/collection/mutable/HashEntry;)V
  #358 = Methodref          #2.#357       // scala/collection/parallel/mutable/ParHashMapCombiner$AddingHashTable.table_$eq:([Lscala/collection/mutable/HashEntry;)V
  #359 = NameAndType        #270:#159     // seedvalue_$eq:(I)V
  #360 = Methodref          #2.#359       // scala/collection/parallel/mutable/ParHashMapCombiner$AddingHashTable.seedvalue_$eq:(I)V
  #361 = Utf8               newThreshold
  #362 = NameAndType        #361:#240     // newThreshold:(II)I
  #363 = Methodref          #343.#362     // scala/collection/mutable/HashTable$.newThreshold:(II)I
  #364 = NameAndType        #262:#159     // threshold_$eq:(I)V
  #365 = Methodref          #2.#364       // scala/collection/parallel/mutable/ParHashMapCombiner$AddingHashTable.threshold_$eq:(I)V
  #366 = NameAndType        #183:#159     // sizeMapInit:(I)V
  #367 = Methodref          #2.#366       // scala/collection/parallel/mutable/ParHashMapCombiner$AddingHashTable.sizeMapInit:(I)V
  #368 = Utf8               Signature
  #369 = Utf8               Code
  #370 = Utf8               LineNumberTable
  #371 = Utf8               LocalVariableTable
  #372 = Utf8               MethodParameters
  #373 = Utf8               StackMapTable
  #374 = Utf8               InnerClasses
  #375 = Utf8               SourceFile
  #376 = Utf8               ScalaInlineInfo
  #377 = Utf8               Scala
{
  private int _loadFactor;
    descriptor: I
    flags: (0x0002) ACC_PRIVATE

  private scala.collection.mutable.HashEntry<K, scala.collection.parallel.mutable.ParHashMap$DefaultEntry<K, V>>[] table;
    descriptor: [Lscala/collection/mutable/HashEntry;
    flags: (0x0002) ACC_PRIVATE
    Signature: #31                          // [Lscala/collection/mutable/HashEntry<TK;Lscala/collection/parallel/mutable/ParHashMap$DefaultEntry<TK;TV;>;>;

  private int tableSize;
    descriptor: I
    flags: (0x0002) ACC_PRIVATE

  private int threshold;
    descriptor: I
    flags: (0x0002) ACC_PRIVATE

  private int[] sizemap;
    descriptor: [I
    flags: (0x0002) ACC_PRIVATE

  private int seedvalue;
    descriptor: I
    flags: (0x0002) ACC_PRIVATE

  public final scala.collection.parallel.mutable.ParHashMapCombiner $outer;
    descriptor: Lscala/collection/parallel/mutable/ParHashMapCombiner;
    flags: (0x1011) ACC_PUBLIC, ACC_FINAL, ACC_SYNTHETIC

  public void initWithContents(scala.collection.parallel.mutable.ParHashTable$Contents<K, scala.collection.parallel.mutable.ParHashMap$DefaultEntry<K, V>>);
    descriptor: (Lscala/collection/parallel/mutable/ParHashTable$Contents;)V
    flags: (0x0001) ACC_PUBLIC
    Code:
      stack=2, locals=2, args_size=2
         0: aload_0
         1: aload_1
         2: invokestatic  #46                 // InterfaceMethod scala/collection/parallel/mutable/WithContents.initWithContents$:(Lscala/collection/parallel/mutable/WithContents;Lscala/collection/parallel/mutable/ParHashTable$Contents;)V
         5: return
      LineNumberTable:
        line 225: 0
      LocalVariableTable:
        Start  Length  Slot  Name   Signature
            0       6     0  this   Lscala/collection/parallel/mutable/ParHashMapCombiner$AddingHashTable;
            0       6     1     c   Lscala/collection/parallel/mutable/ParHashTable$Contents;
    Signature: #41                          // (Lscala/collection/parallel/mutable/ParHashTable$Contents<TK;Lscala/collection/parallel/mutable/ParHashMap$DefaultEntry<TK;TV;>;>;)V
    MethodParameters:
      Name                           Flags
      c                              final

  public scala.collection.parallel.mutable.ParHashTable$Contents<K, scala.collection.parallel.mutable.ParHashMap$DefaultEntry<K, V>> hashTableContents();
    descriptor: ()Lscala/collection/parallel/mutable/ParHashTable$Contents;
    flags: (0x0001) ACC_PUBLIC
    Code:
      stack=1, locals=1, args_size=1
         0: aload_0
         1: invokestatic  #56                 // InterfaceMethod scala/collection/parallel/mutable/WithContents.hashTableContents$:(Lscala/collection/parallel/mutable/WithContents;)Lscala/collection/parallel/mutable/ParHashTable$Contents;
         4: areturn
      LineNumberTable:
        line 225: 0
      LocalVariableTable:
        Start  Length  Slot  Name   Signature
            0       5     0  this   Lscala/collection/parallel/mutable/ParHashMapCombiner$AddingHashTable;
    Signature: #52                          // ()Lscala/collection/parallel/mutable/ParHashTable$Contents<TK;Lscala/collection/parallel/mutable/ParHashMap$DefaultEntry<TK;TV;>;>;

  public final int size();
    descriptor: ()I
    flags: (0x0011) ACC_PUBLIC, ACC_FINAL
    Code:
      stack=1, locals=1, args_size=1
         0: aload_0
         1: invokestatic  #62                 // InterfaceMethod scala/collection/mutable/HashTable.size$:(Lscala/collection/mutable/HashTable;)I
         4: ireturn
      LineNumberTable:
        line 225: 0
      LocalVariableTable:
        Start  Length  Slot  Name   Signature
            0       5     0  this   Lscala/collection/parallel/mutable/ParHashMapCombiner$AddingHashTable;

  public int tableSizeSeed();
    descriptor: ()I
    flags: (0x0001) ACC_PUBLIC
    Code:
      stack=1, locals=1, args_size=1
         0: aload_0
         1: invokestatic  #66                 // InterfaceMethod scala/collection/mutable/HashTable.tableSizeSeed$:(Lscala/collection/mutable/HashTable;)I
         4: ireturn
      LineNumberTable:
        line 225: 0
      LocalVariableTable:
        Start  Length  Slot  Name   Signature
            0       5     0  this   Lscala/collection/parallel/mutable/ParHashMapCombiner$AddingHashTable;

  public int initialSize();
    descriptor: ()I
    flags: (0x0001) ACC_PUBLIC
    Code:
      stack=1, locals=1, args_size=1
         0: aload_0
         1: invokestatic  #70                 // InterfaceMethod scala/collection/mutable/HashTable.initialSize$:(Lscala/collection/mutable/HashTable;)I
         4: ireturn
      LineNumberTable:
        line 225: 0
      LocalVariableTable:
        Start  Length  Slot  Name   Signature
            0       5     0  this   Lscala/collection/parallel/mutable/ParHashMapCombiner$AddingHashTable;

  public void init(java.io.ObjectInputStream, scala.Function0<scala.collection.parallel.mutable.ParHashMap$DefaultEntry<K, V>>);
    descriptor: (Ljava/io/ObjectInputStream;Lscala/Function0;)V
    flags: (0x0001) ACC_PUBLIC
    Code:
      stack=3, locals=3, args_size=3
         0: aload_0
         1: aload_1
         2: aload_2
         3: invokestatic  #79                 // InterfaceMethod scala/collection/mutable/HashTable.init$:(Lscala/collection/mutable/HashTable;Ljava/io/ObjectInputStream;Lscala/Function0;)V
         6: return
      LineNumberTable:
        line 225: 0
      LocalVariableTable:
        Start  Length  Slot  Name   Signature
            0       7     0  this   Lscala/collection/parallel/mutable/ParHashMapCombiner$AddingHashTable;
            0       7     1    in   Ljava/io/ObjectInputStream;
            0       7     2 readEntry   Lscala/Function0;
    Signature: #73                          // (Ljava/io/ObjectInputStream;Lscala/Function0<Lscala/collection/parallel/mutable/ParHashMap$DefaultEntry<TK;TV;>;>;)V
    MethodParameters:
      Name                           Flags
      in                             final
      readEntry                      final

  public void serializeTo(java.io.ObjectOutputStream, scala.Function1<scala.collection.parallel.mutable.ParHashMap$DefaultEntry<K, V>, scala.runtime.BoxedUnit>);
    descriptor: (Ljava/io/ObjectOutputStream;Lscala/Function1;)V
    flags: (0x0001) ACC_PUBLIC
    Code:
      stack=3, locals=3, args_size=3
         0: aload_0
         1: aload_1
         2: aload_2
         3: invokestatic  #90                 // InterfaceMethod scala/collection/mutable/HashTable.serializeTo$:(Lscala/collection/mutable/HashTable;Ljava/io/ObjectOutputStream;Lscala/Function1;)V
         6: return
      LineNumberTable:
        line 225: 0
      LocalVariableTable:
        Start  Length  Slot  Name   Signature
            0       7     0  this   Lscala/collection/parallel/mutable/ParHashMapCombiner$AddingHashTable;
            0       7     1   out   Ljava/io/ObjectOutputStream;
            0       7     2 writeEntry   Lscala/Function1;
    Signature: #84                          // (Ljava/io/ObjectOutputStream;Lscala/Function1<Lscala/collection/parallel/mutable/ParHashMap$DefaultEntry<TK;TV;>;Lscala/runtime/BoxedUnit;>;)V
    MethodParameters:
      Name                           Flags
      out                            final
      writeEntry                     final

  public final scala.collection.mutable.HashEntry findEntry(java.lang.Object);
    descriptor: (Ljava/lang/Object;)Lscala/collection/mutable/HashEntry;
    flags: (0x0011) ACC_PUBLIC, ACC_FINAL
    Code:
      stack=2, locals=2, args_size=2
         0: aload_0
         1: aload_1
         2: invokestatic  #99                 // InterfaceMethod scala/collection/mutable/HashTable.findEntry$:(Lscala/collection/mutable/HashTable;Ljava/lang/Object;)Lscala/collection/mutable/HashEntry;
         5: areturn
      LineNumberTable:
        line 225: 0
      LocalVariableTable:
        Start  Length  Slot  Name   Signature
            0       6     0  this   Lscala/collection/parallel/mutable/ParHashMapCombiner$AddingHashTable;
            0       6     1   key   Ljava/lang/Object;
    MethodParameters:
      Name                           Flags
      key                            final

  public final scala.collection.mutable.HashEntry findEntry0(java.lang.Object, int);
    descriptor: (Ljava/lang/Object;I)Lscala/collection/mutable/HashEntry;
    flags: (0x0011) ACC_PUBLIC, ACC_FINAL
    Code:
      stack=3, locals=3, args_size=3
         0: aload_0
         1: aload_1
         2: iload_2
         3: invokestatic  #107                // InterfaceMethod scala/collection/mutable/HashTable.findEntry0$:(Lscala/collection/mutable/HashTable;Ljava/lang/Object;I)Lscala/collection/mutable/HashEntry;
         6: areturn
      LineNumberTable:
        line 225: 0
      LocalVariableTable:
        Start  Length  Slot  Name   Signature
            0       7     0  this   Lscala/collection/parallel/mutable/ParHashMapCombiner$AddingHashTable;
            0       7     1   key   Ljava/lang/Object;
            0       7     2     h   I
    MethodParameters:
      Name                           Flags
      key                            final
      h                              final

  public final void addEntry(scala.collection.mutable.HashEntry);
    descriptor: (Lscala/collection/mutable/HashEntry;)V
    flags: (0x0011) ACC_PUBLIC, ACC_FINAL
    Code:
      stack=2, locals=2, args_size=2
         0: aload_0
         1: aload_1
         2: invokestatic  #114                // InterfaceMethod scala/collection/mutable/HashTable.addEntry$:(Lscala/collection/mutable/HashTable;Lscala/collection/mutable/HashEntry;)V
         5: return
      LineNumberTable:
        line 225: 0
      LocalVariableTable:
        Start  Length  Slot  Name   Signature
            0       6     0  this   Lscala/collection/parallel/mutable/ParHashMapCombiner$AddingHashTable;
            0       6     1     e   Lscala/collection/mutable/HashEntry;
    MethodParameters:
      Name                           Flags
      e                              final

  public final void addEntry0(scala.collection.mutable.HashEntry, int);
    descriptor: (Lscala/collection/mutable/HashEntry;I)V
    flags: (0x0011) ACC_PUBLIC, ACC_FINAL
    Code:
      stack=3, locals=3, args_size=3
         0: aload_0
         1: aload_1
         2: iload_2
         3: invokestatic  #121                // InterfaceMethod scala/collection/mutable/HashTable.addEntry0$:(Lscala/collection/mutable/HashTable;Lscala/collection/mutable/HashEntry;I)V
         6: return
      LineNumberTable:
        line 225: 0
      LocalVariableTable:
        Start  Length  Slot  Name   Signature
            0       7     0  this   Lscala/collection/parallel/mutable/ParHashMapCombiner$AddingHashTable;
            0       7     1     e   Lscala/collection/mutable/HashEntry;
            0       7     2     h   I
    MethodParameters:
      Name                           Flags
      e                              final
      h                              final

  public scala.collection.mutable.HashEntry findOrAddEntry(java.lang.Object, java.lang.Object);
    descriptor: (Ljava/lang/Object;Ljava/lang/Object;)Lscala/collection/mutable/HashEntry;
    flags: (0x0001) ACC_PUBLIC
    Code:
      stack=3, locals=3, args_size=3
         0: aload_0
         1: aload_1
         2: aload_2
         3: invokestatic  #128                // InterfaceMethod scala/collection/mutable/HashTable.findOrAddEntry$:(Lscala/collection/mutable/HashTable;Ljava/lang/Object;Ljava/lang/Object;)Lscala/collection/mutable/HashEntry;
         6: areturn
      LineNumberTable:
        line 225: 0
      LocalVariableTable:
        Start  Length  Slot  Name   Signature
            0       7     0  this   Lscala/collection/parallel/mutable/ParHashMapCombiner$AddingHashTable;
            0       7     1   key   Ljava/lang/Object;
            0       7     2 value   Ljava/lang/Object;
    MethodParameters:
      Name                           Flags
      key                            final
      value                          final

  public final scala.collection.mutable.HashEntry removeEntry(java.lang.Object);
    descriptor: (Ljava/lang/Object;)Lscala/collection/mutable/HashEntry;
    flags: (0x0011) ACC_PUBLIC, ACC_FINAL
    Code:
      stack=2, locals=2, args_size=2
         0: aload_0
         1: aload_1
         2: invokestatic  #132                // InterfaceMethod scala/collection/mutable/HashTable.removeEntry$:(Lscala/collection/mutable/HashTable;Ljava/lang/Object;)Lscala/collection/mutable/HashEntry;
         5: areturn
      LineNumberTable:
        line 225: 0
      LocalVariableTable:
        Start  Length  Slot  Name   Signature
            0       6     0  this   Lscala/collection/parallel/mutable/ParHashMapCombiner$AddingHashTable;
            0       6     1   key   Ljava/lang/Object;
    MethodParameters:
      Name                           Flags
      key                            final

  public final scala.collection.mutable.HashEntry removeEntry0(java.lang.Object, int);
    descriptor: (Ljava/lang/Object;I)Lscala/collection/mutable/HashEntry;
    flags: (0x0011) ACC_PUBLIC, ACC_FINAL
    Code:
      stack=3, locals=3, args_size=3
         0: aload_0
         1: aload_1
         2: iload_2
         3: invokestatic  #136                // InterfaceMethod scala/collection/mutable/HashTable.removeEntry0$:(Lscala/collection/mutable/HashTable;Ljava/lang/Object;I)Lscala/collection/mutable/HashEntry;
         6: areturn
      LineNumberTable:
        line 225: 0
      LocalVariableTable:
        Start  Length  Slot  Name   Signature
            0       7     0  this   Lscala/collection/parallel/mutable/ParHashMapCombiner$AddingHashTable;
            0       7     1   key   Ljava/lang/Object;
            0       7     2     h   I
    MethodParameters:
      Name                           Flags
      key                            final
      h                              final

  public scala.collection.Iterator<scala.collection.parallel.mutable.ParHashMap$DefaultEntry<K, V>> entriesIterator();
    descriptor: ()Lscala/collection/Iterator;
    flags: (0x0001) ACC_PUBLIC
    Code:
      stack=1, locals=1, args_size=1
         0: aload_0
         1: invokestatic  #143                // InterfaceMethod scala/collection/mutable/HashTable.entriesIterator$:(Lscala/collection/mutable/HashTable;)Lscala/collection/Iterator;
         4: areturn
      LineNumberTable:
        line 225: 0
      LocalVariableTable:
        Start  Length  Slot  Name   Signature
            0       5     0  this   Lscala/collection/parallel/mutable/ParHashMapCombiner$AddingHashTable;
    Signature: #139                         // ()Lscala/collection/Iterator<Lscala/collection/parallel/mutable/ParHashMap$DefaultEntry<TK;TV;>;>;

  public <U extends java.lang.Object> void foreachEntry(scala.Function1<scala.collection.parallel.mutable.ParHashMap$DefaultEntry<K, V>, U>);
    descriptor: (Lscala/Function1;)V
    flags: (0x0001) ACC_PUBLIC
    Code:
      stack=2, locals=2, args_size=2
         0: aload_0
         1: aload_1
         2: invokestatic  #151                // InterfaceMethod scala/collection/mutable/HashTable.foreachEntry$:(Lscala/collection/mutable/HashTable;Lscala/Function1;)V
         5: return
      LineNumberTable:
        line 225: 0
      LocalVariableTable:
        Start  Length  Slot  Name   Signature
            0       6     0  this   Lscala/collection/parallel/mutable/ParHashMapCombiner$AddingHashTable;
            0       6     1     f   Lscala/Function1;
    Signature: #146                         // <U:Ljava/lang/Object;>(Lscala/Function1<Lscala/collection/parallel/mutable/ParHashMap$DefaultEntry<TK;TV;>;TU;>;)V
    MethodParameters:
      Name                           Flags
      f                              final

  public void clearTable();
    descriptor: ()V
    flags: (0x0001) ACC_PUBLIC
    Code:
      stack=1, locals=1, args_size=1
         0: aload_0
         1: invokestatic  #157                // InterfaceMethod scala/collection/mutable/HashTable.clearTable$:(Lscala/collection/mutable/HashTable;)V
         4: return
      LineNumberTable:
        line 225: 0
      LocalVariableTable:
        Start  Length  Slot  Name   Signature
            0       5     0  this   Lscala/collection/parallel/mutable/ParHashMapCombiner$AddingHashTable;

  public final void nnSizeMapAdd(int);
    descriptor: (I)V
    flags: (0x0011) ACC_PUBLIC, ACC_FINAL
    Code:
      stack=2, locals=2, args_size=2
         0: aload_0
         1: iload_1
         2: invokestatic  #163                // InterfaceMethod scala/collection/mutable/HashTable.nnSizeMapAdd$:(Lscala/collection/mutable/HashTable;I)V
         5: return
      LineNumberTable:
        line 225: 0
      LocalVariableTable:
        Start  Length  Slot  Name   Signature
            0       6     0  this   Lscala/collection/parallel/mutable/ParHashMapCombiner$AddingHashTable;
            0       6     1     h   I
    MethodParameters:
      Name                           Flags
      h                              final

  public final void nnSizeMapRemove(int);
    descriptor: (I)V
    flags: (0x0011) ACC_PUBLIC, ACC_FINAL
    Code:
      stack=2, locals=2, args_size=2
         0: aload_0
         1: iload_1
         2: invokestatic  #167                // InterfaceMethod scala/collection/mutable/HashTable.nnSizeMapRemove$:(Lscala/collection/mutable/HashTable;I)V
         5: return
      LineNumberTable:
        line 225: 0
      LocalVariableTable:
        Start  Length  Slot  Name   Signature
            0       6     0  this   Lscala/collection/parallel/mutable/ParHashMapCombiner$AddingHashTable;
            0       6     1     h   I
    MethodParameters:
      Name                           Flags
      h                              final

  public final void nnSizeMapReset(int);
    descriptor: (I)V
    flags: (0x0011) ACC_PUBLIC, ACC_FINAL
    Code:
      stack=2, locals=2, args_size=2
         0: aload_0
         1: iload_1
         2: invokestatic  #172                // InterfaceMethod scala/collection/mutable/HashTable.nnSizeMapReset$:(Lscala/collection/mutable/HashTable;I)V
         5: return
      LineNumberTable:
        line 225: 0
      LocalVariableTable:
        Start  Length  Slot  Name   Signature
            0       6     0  this   Lscala/collection/parallel/mutable/ParHashMapCombiner$AddingHashTable;
            0       6     1 tableLength   I
    MethodParameters:
      Name                           Flags
      tableLength                    final

  public final int totalSizeMapBuckets();
    descriptor: ()I
    flags: (0x0011) ACC_PUBLIC, ACC_FINAL
    Code:
      stack=1, locals=1, args_size=1
         0: aload_0
         1: invokestatic  #176                // InterfaceMethod scala/collection/mutable/HashTable.totalSizeMapBuckets$:(Lscala/collection/mutable/HashTable;)I
         4: ireturn
      LineNumberTable:
        line 225: 0
      LocalVariableTable:
        Start  Length  Slot  Name   Signature
            0       5     0  this   Lscala/collection/parallel/mutable/ParHashMapCombiner$AddingHashTable;

  public final int calcSizeMapSize(int);
    descriptor: (I)I
    flags: (0x0011) ACC_PUBLIC, ACC_FINAL
    Code:
      stack=2, locals=2, args_size=2
         0: aload_0
         1: iload_1
         2: invokestatic  #182                // InterfaceMethod scala/collection/mutable/HashTable.calcSizeMapSize$:(Lscala/collection/mutable/HashTable;I)I
         5: ireturn
      LineNumberTable:
        line 225: 0
      LocalVariableTable:
        Start  Length  Slot  Name   Signature
            0       6     0  this   Lscala/collection/parallel/mutable/ParHashMapCombiner$AddingHashTable;
            0       6     1 tableLength   I
    MethodParameters:
      Name                           Flags
      tableLength                    final

  public void sizeMapInit(int);
    descriptor: (I)V
    flags: (0x0001) ACC_PUBLIC
    Code:
      stack=2, locals=2, args_size=2
         0: aload_0
         1: iload_1
         2: invokestatic  #186                // InterfaceMethod scala/collection/mutable/HashTable.sizeMapInit$:(Lscala/collection/mutable/HashTable;I)V
         5: return
      LineNumberTable:
        line 225: 0
      LocalVariableTable:
        Start  Length  Slot  Name   Signature
            0       6     0  this   Lscala/collection/parallel/mutable/ParHashMapCombiner$AddingHashTable;
            0       6     1 tableLength   I
    MethodParameters:
      Name                           Flags
      tableLength                    final

  public final void sizeMapInitAndRebuild();
    descriptor: ()V
    flags: (0x0011) ACC_PUBLIC, ACC_FINAL
    Code:
      stack=1, locals=1, args_size=1
         0: aload_0
         1: invokestatic  #190                // InterfaceMethod scala/collection/mutable/HashTable.sizeMapInitAndRebuild$:(Lscala/collection/mutable/HashTable;)V
         4: return
      LineNumberTable:
        line 225: 0
      LocalVariableTable:
        Start  Length  Slot  Name   Signature
            0       5     0  this   Lscala/collection/parallel/mutable/ParHashMapCombiner$AddingHashTable;

  public void printSizeMap();
    descriptor: ()V
    flags: (0x0001) ACC_PUBLIC
    Code:
      stack=1, locals=1, args_size=1
         0: aload_0
         1: invokestatic  #194                // InterfaceMethod scala/collection/mutable/HashTable.printSizeMap$:(Lscala/collection/mutable/HashTable;)V
         4: return
      LineNumberTable:
        line 225: 0
      LocalVariableTable:
        Start  Length  Slot  Name   Signature
            0       5     0  this   Lscala/collection/parallel/mutable/ParHashMapCombiner$AddingHashTable;

  public final void sizeMapDisable();
    descriptor: ()V
    flags: (0x0011) ACC_PUBLIC, ACC_FINAL
    Code:
      stack=1, locals=1, args_size=1
         0: aload_0
         1: invokestatic  #198                // InterfaceMethod scala/collection/mutable/HashTable.sizeMapDisable$:(Lscala/collection/mutable/HashTable;)V
         4: return
      LineNumberTable:
        line 225: 0
      LocalVariableTable:
        Start  Length  Slot  Name   Signature
            0       5     0  this   Lscala/collection/parallel/mutable/ParHashMapCombiner$AddingHashTable;

  public final boolean isSizeMapDefined();
    descriptor: ()Z
    flags: (0x0011) ACC_PUBLIC, ACC_FINAL
    Code:
      stack=1, locals=1, args_size=1
         0: aload_0
         1: invokestatic  #204                // InterfaceMethod scala/collection/mutable/HashTable.isSizeMapDefined$:(Lscala/collection/mutable/HashTable;)Z
         4: ireturn
      LineNumberTable:
        line 225: 0
      LocalVariableTable:
        Start  Length  Slot  Name   Signature
            0       5     0  this   Lscala/collection/parallel/mutable/ParHashMapCombiner$AddingHashTable;

  public boolean alwaysInitSizeMap();
    descriptor: ()Z
    flags: (0x0001) ACC_PUBLIC
    Code:
      stack=1, locals=1, args_size=1
         0: aload_0
         1: invokestatic  #208                // InterfaceMethod scala/collection/mutable/HashTable.alwaysInitSizeMap$:(Lscala/collection/mutable/HashTable;)Z
         4: ireturn
      LineNumberTable:
        line 225: 0
      LocalVariableTable:
        Start  Length  Slot  Name   Signature
            0       5     0  this   Lscala/collection/parallel/mutable/ParHashMapCombiner$AddingHashTable;

  public boolean elemEquals(K, K);
    descriptor: (Ljava/lang/Object;Ljava/lang/Object;)Z
    flags: (0x0001) ACC_PUBLIC
    Code:
      stack=3, locals=3, args_size=3
         0: aload_0
         1: aload_1
         2: aload_2
         3: invokestatic  #217                // InterfaceMethod scala/collection/mutable/HashTable.elemEquals$:(Lscala/collection/mutable/HashTable;Ljava/lang/Object;Ljava/lang/Object;)Z
         6: ireturn
      LineNumberTable:
        line 225: 0
      LocalVariableTable:
        Start  Length  Slot  Name   Signature
            0       7     0  this   Lscala/collection/parallel/mutable/ParHashMapCombiner$AddingHashTable;
            0       7     1  key1   Ljava/lang/Object;
            0       7     2  key2   Ljava/lang/Object;
    Signature: #211                         // (TK;TK;)Z
    MethodParameters:
      Name                           Flags
      key1                           final
      key2                           final

  public final int index(int);
    descriptor: (I)I
    flags: (0x0011) ACC_PUBLIC, ACC_FINAL
    Code:
      stack=2, locals=2, args_size=2
         0: aload_0
         1: iload_1
         2: invokestatic  #222                // InterfaceMethod scala/collection/mutable/HashTable.index$:(Lscala/collection/mutable/HashTable;I)I
         5: ireturn
      LineNumberTable:
        line 225: 0
      LocalVariableTable:
        Start  Length  Slot  Name   Signature
            0       6     0  this   Lscala/collection/parallel/mutable/ParHashMapCombiner$AddingHashTable;
            0       6     1 hcode   I
    MethodParameters:
      Name                           Flags
      hcode                          final

  public final int sizeMapBucketBitSize();
    descriptor: ()I
    flags: (0x0011) ACC_PUBLIC, ACC_FINAL
    Code:
      stack=1, locals=1, args_size=1
         0: aload_0
         1: invokestatic  #227                // InterfaceMethod scala/collection/mutable/HashTable$HashUtils.sizeMapBucketBitSize$:(Lscala/collection/mutable/HashTable$HashUtils;)I
         4: ireturn
      LineNumberTable:
        line 225: 0
      LocalVariableTable:
        Start  Length  Slot  Name   Signature
            0       5     0  this   Lscala/collection/parallel/mutable/ParHashMapCombiner$AddingHashTable;

  public final int sizeMapBucketSize();
    descriptor: ()I
    flags: (0x0011) ACC_PUBLIC, ACC_FINAL
    Code:
      stack=1, locals=1, args_size=1
         0: aload_0
         1: invokestatic  #231                // InterfaceMethod scala/collection/mutable/HashTable$HashUtils.sizeMapBucketSize$:(Lscala/collection/mutable/HashTable$HashUtils;)I
         4: ireturn
      LineNumberTable:
        line 225: 0
      LocalVariableTable:
        Start  Length  Slot  Name   Signature
            0       5     0  this   Lscala/collection/parallel/mutable/ParHashMapCombiner$AddingHashTable;

  public int elemHashCode(K);
    descriptor: (Ljava/lang/Object;)I
    flags: (0x0001) ACC_PUBLIC
    Code:
      stack=2, locals=2, args_size=2
         0: aload_0
         1: aload_1
         2: invokestatic  #238                // InterfaceMethod scala/collection/mutable/HashTable$HashUtils.elemHashCode$:(Lscala/collection/mutable/HashTable$HashUtils;Ljava/lang/Object;)I
         5: ireturn
      LineNumberTable:
        line 225: 0
      LocalVariableTable:
        Start  Length  Slot  Name   Signature
            0       6     0  this   Lscala/collection/parallel/mutable/ParHashMapCombiner$AddingHashTable;
            0       6     1   key   Ljava/lang/Object;
    Signature: #234                         // (TK;)I
    MethodParameters:
      Name                           Flags
      key                            final

  public final int improve(int, int);
    descriptor: (II)I
    flags: (0x0011) ACC_PUBLIC, ACC_FINAL
    Code:
      stack=3, locals=3, args_size=3
         0: aload_0
         1: iload_1
         2: iload_2
         3: invokestatic  #245                // InterfaceMethod scala/collection/mutable/HashTable$HashUtils.improve$:(Lscala/collection/mutable/HashTable$HashUtils;II)I
         6: ireturn
      LineNumberTable:
        line 225: 0
      LocalVariableTable:
        Start  Length  Slot  Name   Signature
            0       7     0  this   Lscala/collection/parallel/mutable/ParHashMapCombiner$AddingHashTable;
            0       7     1 hcode   I
            0       7     2  seed   I
    MethodParameters:
      Name                           Flags
      hcode                          final
      seed                           final

  public int _loadFactor();
    descriptor: ()I
    flags: (0x0001) ACC_PUBLIC
    Code:
      stack=1, locals=1, args_size=1
         0: aload_0
         1: getfield      #247                // Field _loadFactor:I
         4: ireturn
      LineNumberTable:
        line 225: 0
      LocalVariableTable:
        Start  Length  Slot  Name   Signature
            0       5     0  this   Lscala/collection/parallel/mutable/ParHashMapCombiner$AddingHashTable;

  public void _loadFactor_$eq(int);
    descriptor: (I)V
    flags: (0x0001) ACC_PUBLIC
    Code:
      stack=2, locals=2, args_size=2
         0: aload_0
         1: iload_1
         2: putfield      #247                // Field _loadFactor:I
         5: return
      LineNumberTable:
        line 225: 0
      LocalVariableTable:
        Start  Length  Slot  Name   Signature
            0       6     0  this   Lscala/collection/parallel/mutable/ParHashMapCombiner$AddingHashTable;
            0       6     1   x$1   I
    MethodParameters:
      Name                           Flags
      x$1                            final

  public scala.collection.mutable.HashEntry<K, scala.collection.parallel.mutable.ParHashMap$DefaultEntry<K, V>>[] table();
    descriptor: ()[Lscala/collection/mutable/HashEntry;
    flags: (0x0001) ACC_PUBLIC
    Code:
      stack=1, locals=1, args_size=1
         0: aload_0
         1: getfield      #253                // Field table:[Lscala/collection/mutable/HashEntry;
         4: areturn
      LineNumberTable:
        line 225: 0
      LocalVariableTable:
        Start  Length  Slot  Name   Signature
            0       5     0  this   Lscala/collection/parallel/mutable/ParHashMapCombiner$AddingHashTable;
    Signature: #251                         // ()[Lscala/collection/mutable/HashEntry<TK;Lscala/collection/parallel/mutable/ParHashMap$DefaultEntry<TK;TV;>;>;

  public void table_$eq(scala.collection.mutable.HashEntry<K, scala.collection.parallel.mutable.ParHashMap$DefaultEntry<K, V>>[]);
    descriptor: ([Lscala/collection/mutable/HashEntry;)V
    flags: (0x0001) ACC_PUBLIC
    Code:
      stack=2, locals=2, args_size=2
         0: aload_0
         1: aload_1
         2: putfield      #253                // Field table:[Lscala/collection/mutable/HashEntry;
         5: return
      LineNumberTable:
        line 225: 0
      LocalVariableTable:
        Start  Length  Slot  Name   Signature
            0       6     0  this   Lscala/collection/parallel/mutable/ParHashMapCombiner$AddingHashTable;
            0       6     1   x$1   [Lscala/collection/mutable/HashEntry;
    Signature: #256                         // ([Lscala/collection/mutable/HashEntry<TK;Lscala/collection/parallel/mutable/ParHashMap$DefaultEntry<TK;TV;>;>;)V
    MethodParameters:
      Name                           Flags
      x$1                            final

  public int tableSize();
    descriptor: ()I
    flags: (0x0001) ACC_PUBLIC
    Code:
      stack=1, locals=1, args_size=1
         0: aload_0
         1: getfield      #258                // Field tableSize:I
         4: ireturn
      LineNumberTable:
        line 225: 0
      LocalVariableTable:
        Start  Length  Slot  Name   Signature
            0       5     0  this   Lscala/collection/parallel/mutable/ParHashMapCombiner$AddingHashTable;

  public void tableSize_$eq(int);
    descriptor: (I)V
    flags: (0x0001) ACC_PUBLIC
    Code:
      stack=2, locals=2, args_size=2
         0: aload_0
         1: iload_1
         2: putfield      #258                // Field tableSize:I
         5: return
      LineNumberTable:
        line 225: 0
      LocalVariableTable:
        Start  Length  Slot  Name   Signature
            0       6     0  this   Lscala/collection/parallel/mutable/ParHashMapCombiner$AddingHashTable;
            0       6     1   x$1   I
    MethodParameters:
      Name                           Flags
      x$1                            final

  public int threshold();
    descriptor: ()I
    flags: (0x0001) ACC_PUBLIC
    Code:
      stack=1, locals=1, args_size=1
         0: aload_0
         1: getfield      #261                // Field threshold:I
         4: ireturn
      LineNumberTable:
        line 225: 0
      LocalVariableTable:
        Start  Length  Slot  Name   Signature
            0       5     0  this   Lscala/collection/parallel/mutable/ParHashMapCombiner$AddingHashTable;

  public void threshold_$eq(int);
    descriptor: (I)V
    flags: (0x0001) ACC_PUBLIC
    Code:
      stack=2, locals=2, args_size=2
         0: aload_0
         1: iload_1
         2: putfield      #261                // Field threshold:I
         5: return
      LineNumberTable:
        line 225: 0
      LocalVariableTable:
        Start  Length  Slot  Name   Signature
            0       6     0  this   Lscala/collection/parallel/mutable/ParHashMapCombiner$AddingHashTable;
            0       6     1   x$1   I
    MethodParameters:
      Name                           Flags
      x$1                            final

  public int[] sizemap();
    descriptor: ()[I
    flags: (0x0001) ACC_PUBLIC
    Code:
      stack=1, locals=1, args_size=1
         0: aload_0
         1: getfield      #265                // Field sizemap:[I
         4: areturn
      LineNumberTable:
        line 225: 0
      LocalVariableTable:
        Start  Length  Slot  Name   Signature
            0       5     0  this   Lscala/collection/parallel/mutable/ParHashMapCombiner$AddingHashTable;

  public void sizemap_$eq(int[]);
    descriptor: ([I)V
    flags: (0x0001) ACC_PUBLIC
    Code:
      stack=2, locals=2, args_size=2
         0: aload_0
         1: aload_1
         2: putfield      #265                // Field sizemap:[I
         5: return
      LineNumberTable:
        line 225: 0
      LocalVariableTable:
        Start  Length  Slot  Name   Signature
            0       6     0  this   Lscala/collection/parallel/mutable/ParHashMapCombiner$AddingHashTable;
            0       6     1   x$1   [I
    MethodParameters:
      Name                           Flags
      x$1                            final

  public int seedvalue();
    descriptor: ()I
    flags: (0x0001) ACC_PUBLIC
    Code:
      stack=1, locals=1, args_size=1
         0: aload_0
         1: getfield      #269                // Field seedvalue:I
         4: ireturn
      LineNumberTable:
        line 225: 0
      LocalVariableTable:
        Start  Length  Slot  Name   Signature
            0       5     0  this   Lscala/collection/parallel/mutable/ParHashMapCombiner$AddingHashTable;

  public void seedvalue_$eq(int);
    descriptor: (I)V
    flags: (0x0001) ACC_PUBLIC
    Code:
      stack=2, locals=2, args_size=2
         0: aload_0
         1: iload_1
         2: putfield      #269                // Field seedvalue:I
         5: return
      LineNumberTable:
        line 225: 0
      LocalVariableTable:
        Start  Length  Slot  Name   Signature
            0       6     0  this   Lscala/collection/parallel/mutable/ParHashMapCombiner$AddingHashTable;
            0       6     1   x$1   I
    MethodParameters:
      Name                           Flags
      x$1                            final

  public void setSize(int);
    descriptor: (I)V
    flags: (0x0001) ACC_PUBLIC
    Code:
      stack=2, locals=2, args_size=2
         0: aload_0
         1: iload_1
         2: invokevirtual #274                // Method tableSize_$eq:(I)V
         5: return
      LineNumberTable:
        line 235: 0
      LocalVariableTable:
        Start  Length  Slot  Name   Signature
            0       6     0  this   Lscala/collection/parallel/mutable/ParHashMapCombiner$AddingHashTable;
            0       6     1    sz   I
    MethodParameters:
      Name                           Flags
      sz                             final

  public boolean insertEntry(scala.collection.parallel.mutable.ParHashMap$DefaultEntry<K, V>);
    descriptor: (Lscala/collection/parallel/mutable/ParHashMap$DefaultEntry;)Z
    flags: (0x0001) ACC_PUBLIC
    Code:
      stack=3, locals=5, args_size=2
         0: aload_0
         1: aload_0
         2: aload_1
         3: invokevirtual #280                // Method scala/collection/parallel/mutable/ParHashMap$DefaultEntry.key:()Ljava/lang/Object;
         6: invokevirtual #282                // Method elemHashCode:(Ljava/lang/Object;)I
         9: invokevirtual #284                // Method index:(I)I
        12: istore_2
        13: aload_0
        14: invokevirtual #286                // Method table:()[Lscala/collection/mutable/HashEntry;
        17: iload_2
        18: aaload
        19: checkcast     #15                 // class scala/collection/parallel/mutable/ParHashMap$DefaultEntry
        22: astore_3
        23: aload_3
        24: astore        4
        26: aload         4
        28: ifnull        67
        31: aload         4
        33: invokevirtual #280                // Method scala/collection/parallel/mutable/ParHashMap$DefaultEntry.key:()Ljava/lang/Object;
        36: aload_1
        37: invokevirtual #280                // Method scala/collection/parallel/mutable/ParHashMap$DefaultEntry.key:()Ljava/lang/Object;
        40: invokestatic  #291                // Method scala/runtime/BoxesRunTime.equals:(Ljava/lang/Object;Ljava/lang/Object;)Z
        43: ifeq          54
        46: iconst_m1
        47: istore_2
        48: aconst_null
        49: astore        4
        51: goto          64
        54: aload         4
        56: invokevirtual #295                // Method scala/collection/parallel/mutable/ParHashMap$DefaultEntry.next:()Lscala/collection/mutable/HashEntry;
        59: checkcast     #15                 // class scala/collection/parallel/mutable/ParHashMap$DefaultEntry
        62: astore        4
        64: goto          26
        67: iload_2
        68: iconst_m1
        69: if_icmpeq     93
        72: aload_1
        73: aload_3
        74: invokevirtual #298                // Method scala/collection/parallel/mutable/ParHashMap$DefaultEntry.next_$eq:(Lscala/collection/mutable/HashEntry;)V
        77: aload_0
        78: invokevirtual #286                // Method table:()[Lscala/collection/mutable/HashEntry;
        81: iload_2
        82: aload_1
        83: aastore
        84: aload_0
        85: iload_2
        86: invokevirtual #300                // Method nnSizeMapAdd:(I)V
        89: iconst_1
        90: goto          94
        93: iconst_0
        94: ireturn
      StackMapTable: number_of_entries = 6
        frame_type = 254 /* append */
          offset_delta = 26
          locals = [ int, class scala/collection/parallel/mutable/ParHashMap$DefaultEntry, class scala/collection/parallel/mutable/ParHashMap$DefaultEntry ]
        frame_type = 27 /* same */
        frame_type = 9 /* same */
        frame_type = 2 /* same */
        frame_type = 25 /* same */
        frame_type = 64 /* same_locals_1_stack_item */
          stack = [ int ]
      LineNumberTable:
        line 237: 0
        line 238: 13
        line 241: 23
        line 242: 26
        line 243: 31
        line 244: 46
        line 245: 48
        line 246: 54
        line 243: 64
        line 250: 67
        line 251: 72
        line 252: 77
        line 253: 84
        line 254: 89
        line 255: 93
      LocalVariableTable:
        Start  Length  Slot  Name   Signature
           13      81     2     h   I
           23      71     3  olde   Lscala/collection/parallel/mutable/ParHashMap$DefaultEntry;
           26      68     4    ce   Lscala/collection/parallel/mutable/ParHashMap$DefaultEntry;
            0      95     0  this   Lscala/collection/parallel/mutable/ParHashMapCombiner$AddingHashTable;
            0      95     1     e   Lscala/collection/parallel/mutable/ParHashMap$DefaultEntry;
    Signature: #277                         // (Lscala/collection/parallel/mutable/ParHashMap$DefaultEntry<TK;TV;>;)Z
    MethodParameters:
      Name                           Flags
      e                              final

  public scala.runtime.Nothing$ createNewEntry(K, V);
    descriptor: (Ljava/lang/Object;Ljava/lang/Object;)Lscala/runtime/Nothing$;
    flags: (0x0001) ACC_PUBLIC
    Code:
      stack=1, locals=3, args_size=3
         0: getstatic     #313                // Field scala/Predef$.MODULE$:Lscala/Predef$;
         3: invokevirtual #317                // Method scala/Predef$.$qmark$qmark$qmark:()Lscala/runtime/Nothing$;
         6: areturn
      LineNumberTable:
        line 257: 0
      LocalVariableTable:
        Start  Length  Slot  Name   Signature
            0       7     0  this   Lscala/collection/parallel/mutable/ParHashMapCombiner$AddingHashTable;
            0       7     1   key   Ljava/lang/Object;
            0       7     2     x   Ljava/lang/Object;
    Signature: #306                         // (TK;TV;)Lscala/runtime/Nothing$;
    MethodParameters:
      Name                           Flags
      key                            final
      x                              final

  public scala.collection.parallel.mutable.ParHashMapCombiner scala$collection$parallel$mutable$ParHashMapCombiner$AddingHashTable$$$outer();
    descriptor: ()Lscala/collection/parallel/mutable/ParHashMapCombiner;
    flags: (0x1001) ACC_PUBLIC, ACC_SYNTHETIC
    Code:
      stack=1, locals=1, args_size=1
         0: aload_0
         1: getfield      #321                // Field $outer:Lscala/collection/parallel/mutable/ParHashMapCombiner;
         4: areturn
      LineNumberTable:
        line 225: 0
      LocalVariableTable:
        Start  Length  Slot  Name   Signature
            0       5     0  this   Lscala/collection/parallel/mutable/ParHashMapCombiner$AddingHashTable;

  public scala.collection.mutable.HashEntry createNewEntry(java.lang.Object, java.lang.Object);
    descriptor: (Ljava/lang/Object;Ljava/lang/Object;)Lscala/collection/mutable/HashEntry;
    flags: (0x1041) ACC_PUBLIC, ACC_BRIDGE, ACC_SYNTHETIC
    Code:
      stack=3, locals=3, args_size=3
         0: aload_0
         1: aload_1
         2: aload_2
         3: invokevirtual #323                // Method createNewEntry:(Ljava/lang/Object;Ljava/lang/Object;)Lscala/runtime/Nothing$;
         6: athrow
      LineNumberTable:
        line 225: 0
      LocalVariableTable:
        Start  Length  Slot  Name   Signature
            0       7     0  this   Lscala/collection/parallel/mutable/ParHashMapCombiner$AddingHashTable;
            0       7     1   key   Ljava/lang/Object;
            0       7     2 value   Ljava/lang/Object;
    MethodParameters:
      Name                           Flags
      key                            final
      value                          final

  public scala.collection.parallel.mutable.ParHashMapCombiner$AddingHashTable(scala.collection.parallel.mutable.ParHashMapCombiner, int, int, int);
    descriptor: (Lscala/collection/parallel/mutable/ParHashMapCombiner;III)V
    flags: (0x0001) ACC_PUBLIC
    Code:
      stack=5, locals=5, args_size=5
         0: aload_1
         1: ifnonnull     6
         4: aconst_null
         5: athrow
         6: aload_0
         7: aload_1
         8: putfield      #321                // Field $outer:Lscala/collection/parallel/mutable/ParHashMapCombiner;
        11: aload_0
        12: invokespecial #330                // Method java/lang/Object."<init>":()V
        15: aload_0
        16: invokestatic  #334                // InterfaceMethod scala/collection/mutable/HashTable$HashUtils.$init$:(Lscala/collection/mutable/HashTable$HashUtils;)V
        19: aload_0
        20: invokestatic  #336                // InterfaceMethod scala/collection/mutable/HashTable.$init$:(Lscala/collection/mutable/HashTable;)V
        23: aload_0
        24: invokestatic  #339                // InterfaceMethod scala/collection/parallel/mutable/WithContents.$init$:(Lscala/collection/parallel/mutable/WithContents;)V
        27: aload_0
        28: iload_3
        29: invokevirtual #341                // Method _loadFactor_$eq:(I)V
        32: aload_0
        33: getstatic     #346                // Field scala/collection/mutable/HashTable$.MODULE$:Lscala/collection/mutable/HashTable$;
        36: getstatic     #346                // Field scala/collection/mutable/HashTable$.MODULE$:Lscala/collection/mutable/HashTable$;
        39: aload_0
        40: invokevirtual #348                // Method _loadFactor:()I
        43: iload_2
        44: invokevirtual #351                // Method scala/collection/mutable/HashTable$.sizeForThreshold:(II)I
        47: invokevirtual #354                // Method scala/collection/mutable/HashTable$.capacity:(I)I
        50: anewarray     #356                // class scala/collection/mutable/HashEntry
        53: invokevirtual #358                // Method table_$eq:([Lscala/collection/mutable/HashEntry;)V
        56: aload_0
        57: iconst_0
        58: invokevirtual #274                // Method tableSize_$eq:(I)V
        61: aload_0
        62: iload         4
        64: invokevirtual #360                // Method seedvalue_$eq:(I)V
        67: aload_0
        68: getstatic     #346                // Field scala/collection/mutable/HashTable$.MODULE$:Lscala/collection/mutable/HashTable$;
        71: aload_0
        72: invokevirtual #348                // Method _loadFactor:()I
        75: aload_0
        76: invokevirtual #286                // Method table:()[Lscala/collection/mutable/HashEntry;
        79: arraylength
        80: invokevirtual #363                // Method scala/collection/mutable/HashTable$.newThreshold:(II)I
        83: invokevirtual #365                // Method threshold_$eq:(I)V
        86: aload_0
        87: aload_0
        88: invokevirtual #286                // Method table:()[Lscala/collection/mutable/HashEntry;
        91: arraylength
        92: invokevirtual #367                // Method sizeMapInit:(I)V
        95: return
      StackMapTable: number_of_entries = 1
        frame_type = 6 /* same */
      LineNumberTable:
        line 225: 0
        line 229: 27
        line 230: 32
        line 231: 56
        line 232: 61
        line 233: 67
        line 234: 86
        line 225: 95
      LocalVariableTable:
        Start  Length  Slot  Name   Signature
            0      96     0  this   Lscala/collection/parallel/mutable/ParHashMapCombiner$AddingHashTable;
            0      96     1 $outer   Lscala/collection/parallel/mutable/ParHashMapCombiner;
            0      96     2 numelems   I
            0      96     3    lf   I
            0      96     4 _seedvalue   I
    MethodParameters:
      Name                           Flags
      $outer                         final synthetic
      numelems                       final
      lf                             final
      _seedvalue                     final
}
InnerClasses:
  public static #13= #12 of #7;           // HashUtils=class scala/collection/mutable/HashTable$HashUtils of class scala/collection/mutable/HashTable
  public static final #18= #15 of #17;    // DefaultEntry=class scala/collection/parallel/mutable/ParHashMap$DefaultEntry of class scala/collection/parallel/mutable/ParHashMap
  public #21= #2 of #20;                  // AddingHashTable=class scala/collection/parallel/mutable/ParHashMapCombiner$AddingHashTable of class scala/collection/parallel/mutable/ParHashMapCombiner
  public static #26= #23 of #25;          // Contents=class scala/collection/parallel/mutable/ParHashTable$Contents of class scala/collection/parallel/mutable/ParHashTable
Signature: #3                           // Ljava/lang/Object;Lscala/collection/mutable/HashTable<TK;TV;Lscala/collection/parallel/mutable/ParHashMap$DefaultEntry<TK;TV;>;>;Lscala/collection/parallel/mutable/WithContents<TK;TV;Lscala/collection/parallel/mutable/ParHashMap$DefaultEntry<TK;TV;>;>;
SourceFile: "ParHashMap.scala"
  ScalaInlineInfo: length = 0x108 (unknown attribute)
   01 00 00 34 01 44 01 45 00 00 1B 00 3A 00 00 F8
   00 9F 00 00 6C 00 6D 01 00 74 00 75 01 00 CD 00
   C8 00 00 B1 00 B2 01 00 98 00 99 00 01 30 00 7B
   00 01 30 01 31 00 00 D1 00 D2 00 00 E8 00 E9 00
   00 89 00 8A 00 00 5D 00 5E 01 00 65 00 66 01 00
   7A 00 7B 00 00 90 00 91 00 00 32 00 33 00 00 EF
   00 F0 01 00 DA 00 B2 01 00 47 00 48 00 00 27 00
   28 00 00 43 00 3A 00 01 13 01 14 00 00 C7 00 C8
   01 00 9E 00 9F 01 00 A4 00 9F 01 00 A8 00 9F 01
   00 BF 00 99 00 00 81 00 5E 01 00 85 00 66 01 01
   3E 01 3F 00 00 24 00 3A 00 01 0E 00 9F 00 00 52
   00 53 00 01 0F 00 9F 00 00 39 00 3A 01 00 DF 00
   3A 01 00 E4 00 3A 01 00 C3 00 99 01 00 B7 00 9F
   00 00 BB 00 99 01 00 22 01 07 00 01 0A 01 0B 00
   00 1D 00 FA 00 00 20 00 3A 00 00 3F 00 3A 00 01
   03 00 9F 00 00 FE 00 FF 00 00 21 00 3A 00 01 06
   00 9F 00 00 AD 00 3A 01
  Scala: length = 0x0 (unknown attribute)

