Classfile /Users/mw/Projects/slang-braindump/.jar/jar8/assemble/slang-braindump/assemble/content/scala/collection/parallel/mutable/ParHashTable.class
  Last modified May 29, 2022; size 3692 bytes
  SHA-256 checksum 2a237f7267916f7837aeb0e43fd726a2c234db32c43c4be9f1470559c2b485de
  Compiled from "ParHashTable.scala"
public interface scala.collection.parallel.mutable.ParHashTable<K extends java.lang.Object, V extends java.lang.Object, Entry extends scala.collection.mutable.HashEntry<K, Entry>> extends scala.collection.mutable.HashTable<K, V, Entry>, scala.collection.parallel.mutable.WithContents<K, V, Entry>
  minor version: 0
  major version: 52
  flags: (0x0601) ACC_PUBLIC, ACC_INTERFACE, ACC_ABSTRACT
  this_class: #2                          // scala/collection/parallel/mutable/ParHashTable
  super_class: #5                         // java/lang/Object
  interfaces: 2, fields: 0, methods: 3, attributes: 6
Constant pool:
   #1 = Utf8               scala/collection/parallel/mutable/ParHashTable
   #2 = Class              #1             // scala/collection/parallel/mutable/ParHashTable
   #3 = Utf8               <K:Ljava/lang/Object;V:Ljava/lang/Object;Entry::Lscala/collection/mutable/HashEntry<TK;TEntry;>;>Ljava/lang/Object;Lscala/collection/mutable/HashTable<TK;TV;TEntry;>;Lscala/collection/parallel/mutable/WithContents<TK;TV;TEntry;>;
   #4 = Utf8               java/lang/Object
   #5 = Class              #4             // java/lang/Object
   #6 = Utf8               scala/collection/mutable/HashTable
   #7 = Class              #6             // scala/collection/mutable/HashTable
   #8 = Utf8               scala/collection/parallel/mutable/WithContents
   #9 = Class              #8             // scala/collection/parallel/mutable/WithContents
  #10 = Utf8               ParHashTable.scala
  #11 = Utf8               Lscala/reflect/ScalaSignature;
  #12 = Utf8               bytes
  #13 = Utf8               \u0006\u0005\tUaa\u0002\u001a4!\u0003\r\t\u0001\u0010\u0005\u0006G\u0002!\t\u0001\u001a\u0005\u0006Q\u0002!\t%\u001b\u0004\u0006[\u0002\t\tA\u001c\u0005\tu\u000e\u0011\t\u0019!C\u0005w\"Iqp\u0001BA\u0002\u0013%\u0011\u0011\u0001\u0005\n\u0003\u000f\u0019!\u0011!Q!\nqD\u0011\"!\u0003\u0004\u0005\u000b\u0007I\u0011B>\t\u0013\u0005-1A!A!\u0002\u0013a\b\"CA\u0007\u0007\t\u0015\r\u0011\"\u0003|\u0011%\tya\u0001B\u0001B\u0003%A\u0010\u0003\u0006\u0002\u0012\r\u0011\t\u0019!C\u0005\u0003\'A!\"!\u0006\u0004\u0005\u0003\u0007I\u0011BA\f\u0011%\tYb\u0001B\u0001B\u0003&Q\u000bC\u0004\u0002\u001e\r!\t!a\b\t\u0013\u0005U2A1A\u0005\n\u0005]\u0002\u0002CA \u0007\u0001\u0006I!!\u000f\t\u0011\u0005\u00053\u00011A\u0005\nmD\u0011\"a\u0011\u0004\u0001\u0004%I!!\u0012\t\u000f\u0005%3\u0001)Q\u0005y\"9\u00111J\u0002\u0007\u0002\u00055\u0003bBA*\u0007\u0019\u0005\u0011Q\u000b\u0005\u0007\u0003K\u001aA\u0011A5\t\u000f\u0005\u001d4\u0001\"\u0001\u0002j!1\u00111N\u0002\u0005\u0002\u0011Da!!\u001c\u0004\t\u0003Y\b\u0002CA8\u0007\u0011\u0005S\'!\u001d\t\u000f\u0005%5\u0001\"\u0001\u0002\f\"9\u0011QR\u0002\u0005\u0002\u0005=\u0005bBAR\u0007\u0011%\u0011Q\u0015\u0005\b\u0003c\u001bA\u0011CAZ\u0011\u001d\tYl\u0001C\t\u0003{;\u0001\"a24\u0011\u00039\u0014\u0011\u001a\u0004\beMB\taNAf\u0011\u001d\ti\"\tC\u0001\u0003\u001b4a!a4\"\u0001\u0005E\u0007\"CAkG\t\u0015\r\u0011\"\u0001|\u0011%\t9n\tB\u0001B\u0003%A\u0010\u0003\u0006\u0002Z\u000e\u0012)\u0019!C\u0001\u00037D!\"!<$\u0005\u0003\u0005\u000b\u0011BAo\u0011%\tyo\tBC\u0002\u0013\u00051\u0010C\u0005\u0002r\u000e\u0012\t\u0011)A\u0005y\"I\u00111_\u0012\u0003\u0006\u0004%\ta\u001f\u0005\n\u0003k\u001c#\u0011!Q\u0001\nqD\u0011\"a>$\u0005\u000b\u0007I\u0011A>\t\u0013\u0005e8E!A!\u0002\u0013a\bBCA~G\t\u0015\r\u0011\"\u0001\u0002~\"Q!\u0011A\u0012\u0003\u0002\u0003\u0006I!a@\t\u000f\u0005u1\u0005\"\u0001\u0003\u0004!A\u0011qN\u0012\u0005\u0002]\n\tH\u0001\u0007QCJD\u0015m\u001d5UC\ndWM\u0003\u00025k\u00059Q.\u001e;bE2,\'B\u0001\u001c8\u0003!\u0001\u0018M]1mY\u0016d\'B\u0001\u001d:\u0003)\u0019w\u000e\u001c7fGRLwN\u001c\u0006\u0002u\u0005)1oY1mC\u000e\u0001Q\u0003B\u001fJ\'Z\u001bB\u0001\u0001 C?B\u0011q\bQ\u0007\u0002s%\u0011\u0011)\u000f\u0002\u0007\u0003:L(+\u001a4\u0011\u000b\r+uIU+\u000e\u0003\u0011S!\u0001N\u001c\n\u0005\u0019#%!\u0003%bg\"$\u0016M\u00197f!\tA\u0015\n\u0004\u0001\u0005\u000b)\u0003!\u0019A&\u0003\u0003-\u000b\"\u0001T(\u0011\u0005}j\u0015B\u0001(:\u0005\u001dqu\u000e\u001e5j]\u001e\u0004\"a\u0010)\n\u0005EK$aA!osB\u0011\u0001j\u0015\u0003\u0006)\u0002\u0011\ra\u0013\u0002\u0002-B\u0011\u0001J\u0016\u0003\u0006/\u0002\u0011\r\u0001\u0017\u0002\u0006\u000b:$(/_\t\u00033r\u0003\"a\u0010.\n\u0005mK$\u0001\u0002(vY2\u0004BaQ/H+&\u0011a\f\u0012\u0002\n\u0011\u0006\u001c\b.\u00128uef\u0004R\u0001Y1H%Vk\u0011aM\u0005\u0003EN\u0012AbV5uQ\u000e{g\u000e^3oiN\fa\u0001J5oSR$C#A3\u0011\u0005}2\u0017BA4:\u0005\u0011)f.\u001b;\u0002#\u0005dw/Y=t\u0013:LGoU5{K6\u000b\u0007/F\u0001k!\ty4.\u0003\u0002ms\t9!i\\8mK\u0006t\'!D#oiJL\u0018\n^3sCR|\'/\u0006\u0003pk\u0006\u001d2\u0003B\u0002?a^\u00042!\u001d:u\u001b\u0005)\u0014BA:6\u0005AIE/\u001a:bE2,7\u000b\u001d7jiR,\'\u000f\u0005\u0002Ik\u0012)ao\u0001b\u0001\u0017\n\tA\u000b\u0005\u0002aq&\u0011\u0011p\r\u0002\r\'&TX-T1q+RLGn]\u0001\u0004S\u0012DX#\u0001?\u0011\u0005}j\u0018B\u0001@:\u0005\rIe\u000e^\u0001\bS\u0012Dx\fJ3r)\r)\u00171\u0001\u0005\t\u0003\u000b)\u0011\u0011!a\u0001y\u0006\u0019\u0001\u0010J\u0019\u0002\t%$\u0007\u0010I\u0001\u0006k:$\u0018\u000e\\\u0001\u0007k:$\u0018\u000e\u001c\u0011\u0002\u0013Q|G/\u00197tSj,\u0017A\u0003;pi\u0006d7/\u001b>fA\u0005\u0011Qm]\u000b\u0002+\u00061Qm]0%KF$2!ZA\r\u0011!\t)\u0001DA\u0001\u0002\u0004)\u0016aA3tA\u00051A(\u001b8jiz\"\"\"!\t\u0002.\u0005=\u0012\u0011GA\u001a!\u0019\t\u0019c\u0001;\u0002&5\t\u0001\u0001E\u0002I\u0003O!\u0001\"!\u000b\u0004\t\u000b\u0007\u00111\u0006\u0002\t\u0013R,\'OU3qeF\u0011A\n\u001d\u0005\u0006u:\u0001\r\u0001 \u0005\u0007\u0003\u0013q\u0001\u0019\u0001?\t\r\u00055a\u00021\u0001}\u0011\u0019\t\tB\u0004a\u0001+\u0006I\u0011\u000e^3si\u0006\u0014G.Z\u000b\u0003\u0003s\u0001BaPA\u001e9&\u0019\u0011QH\u001d\u0003\u000b\u0005\u0013(/Y=\u0002\u0015%$XM\u001d;bE2,\u0007%A\u0005ue\u00064XM]:fI\u0006iAO]1wKJ\u001cX\rZ0%KF$2!ZA$\u0011!\t)AEA\u0001\u0002\u0004a\u0018A\u0003;sCZ,\'o]3eA\u0005QQM\u001c;ssJJG/Z7\u0015\u0007Q\fy\u0005\u0003\u0004\u0002RQ\u0001\r!V\u0001\u0002K\u0006Ya.Z<Ji\u0016\u0014\u0018\r^8s))\t)#a\u0016\u0002\\\u0005}\u00131\r\u0005\u0007\u00033*\u0002\u0019\u0001?\u0002\u000f%$\u0007P\u0012:p[\"1\u0011QL\u000bA\u0002q\f\u0001\"\u001b3y+:$\u0018\u000e\u001c\u0005\u0007\u0003C*\u0002\u0019\u0001?\u0002\u0013Q|G/\u00197TSj,\u0007BBA\t+\u0001\u0007Q+A\u0004iCNtU\r\u001f;\u0002\t9,\u0007\u0010\u001e\u000b\u0002i\u0006!1oY1o\u0003%\u0011X-\\1j]&tw-\u0001\teK\n,x-\u00138g_Jl\u0017\r^5p]V\u0011\u00111\u000f\t\u0005\u0003k\n\u0019I\u0004\u0003\u0002x\u0005}\u0004cAA=s5\u0011\u00111\u0010\u0006\u0004\u0003{Z\u0014A\u0002\u001fs_>$h(C\u0002\u0002\u0002f\na\u0001\u0015:fI\u00164\u0017\u0002BAC\u0003\u000f\u0013aa\u0015;sS:<\'bAAAs\u0005\u0019A-\u001e9\u0016\u0005\u0005\u0015\u0012!B:qY&$XCAAI!\u0015\t\u0019*!(q\u001d\u0011\t)*!\'\u000f\t\u0005e\u0014qS\u0005\u0002u%\u0019\u00111T\u001d\u0002\u000fA\f7m[1hK&!\u0011qTAQ\u0005\r\u0019V-\u001d\u0006\u0004\u00037K\u0014\u0001F2p]Z,\'\u000f\u001e+p\u0003J\u0014\u0018-\u001f\"vM\u001a,\'\u000f\u0006\u0003\u0002(\u00065\u0006\u0003B\"\u0002*RL1!a+E\u0005-\t%O]1z\u0005V4g-\u001a:\t\r\u0005=V\u00041\u0001V\u0003%\u0019\u0007.Y5oQ\u0016\fG-\u0001\u0006d_VtG/\u00127f[N$R\u0001`A[\u0003sCa!a.\u001f\u0001\u0004a\u0018\u0001\u00024s_6Da!!\u0003\u001f\u0001\u0004a\u0018\u0001E2pk:$()^2lKR\u001c\u0016N_3t)\u0015a\u0018qXAb\u0011\u0019\t\tm\ba\u0001y\u0006QaM]8n\u0005V\u001c7.\u001a;\t\r\u0005\u0015w\u00041\u0001}\u0003-)h\u000e^5m\u0005V\u001c7.\u001a;\u0002\u0019A\u000b\'\u000fS1tQR\u000b\'\r\\3\u0011\u0005\u0001\f3CA\u0011?)\t\tIM\u0001\u0005D_:$XM\u001c;t+\u0019\t\u0019.a9\u0002jN\u00111EP\u0001\u000bY>\fGMR1di>\u0014\u0018a\u00037pC\u00124\u0015m\u0019;pe\u0002\nQ\u0001^1cY\u0016,\"!!8\u0011\u000b}\nY$a8\u0011\r\rk\u0016\u0011]At!\rA\u00151\u001d\u0003\u0007\u0003K\u001c#\u0019A&\u0003\u0003\u0005\u00032\u0001SAu\t\u001996E1\u0001\u0002lF\u0019\u0011,a8\u0002\rQ\f\'\r\\3!\u0003%!\u0018M\u00197f\'&TX-\u0001\u0006uC\ndWmU5{K\u0002\n\u0011\u0002\u001e5sKNDw\u000e\u001c3\u0002\u0015QD\'/Z:i_2$\u0007%A\u0005tK\u0016$g/\u00197vK\u0006Q1/Z3em\u0006dW/\u001a\u0011\u0002\u000fML\'0Z7baV\u0011\u0011q \t\u0005\u007f\u0005mB0\u0001\u0005tSj,W.\u00199!)9\u0011)A!\u0003\u0003\f\t5!q\u0002B\t\u0005\'\u0001rAa\u0002$\u0003C\f9/D\u0001\"\u0011\u0019\t)\u000e\ra\u0001y\"9\u0011\u0011\u001c\u0019A\u0002\u0005u\u0007BBAxa\u0001\u0007A\u0010\u0003\u0004\u0002tB\u0002\r\u0001 \u0005\u0007\u0003o\u0004\u0004\u0019\u0001?\t\u000f\u0005m\b\u00071\u0001\u0002\u0000\u0002
  #14 = Utf8               scala/collection/parallel/mutable/ParHashTable$Contents
  #15 = Class              #14            // scala/collection/parallel/mutable/ParHashTable$Contents
  #16 = Utf8               Contents
  #17 = Utf8               scala/collection/parallel/mutable/ParHashTable$EntryIterator
  #18 = Class              #17            // scala/collection/parallel/mutable/ParHashTable$EntryIterator
  #19 = Utf8               EntryIterator
  #20 = Utf8               alwaysInitSizeMap$
  #21 = Utf8               (Lscala/collection/parallel/mutable/ParHashTable;)Z
  #22 = Utf8               $this
  #23 = Utf8               alwaysInitSizeMap
  #24 = Utf8               ()Z
  #25 = NameAndType        #23:#24        // alwaysInitSizeMap:()Z
  #26 = InterfaceMethodref #2.#25         // scala/collection/parallel/mutable/ParHashTable.alwaysInitSizeMap:()Z
  #27 = Utf8               Lscala/collection/parallel/mutable/ParHashTable;
  #28 = Utf8               this
  #29 = Utf8               $init$
  #30 = Utf8               (Lscala/collection/parallel/mutable/ParHashTable;)V
  #31 = Utf8               Code
  #32 = Utf8               LineNumberTable
  #33 = Utf8               LocalVariableTable
  #34 = Utf8               MethodParameters
  #35 = Utf8               InnerClasses
  #36 = Utf8               Signature
  #37 = Utf8               SourceFile
  #38 = Utf8               RuntimeVisibleAnnotations
  #39 = Utf8               ScalaInlineInfo
  #40 = Utf8               ScalaSig
{
  public static boolean alwaysInitSizeMap$(scala.collection.parallel.mutable.ParHashTable);
    descriptor: (Lscala/collection/parallel/mutable/ParHashTable;)Z
    flags: (0x1009) ACC_PUBLIC, ACC_STATIC, ACC_SYNTHETIC
    Code:
      stack=1, locals=1, args_size=1
         0: aload_0
         1: invokespecial #26                 // InterfaceMethod alwaysInitSizeMap:()Z
         4: ireturn
      LineNumberTable:
        line 27: 0
      LocalVariableTable:
        Start  Length  Slot  Name   Signature
            0       5     0 $this   Lscala/collection/parallel/mutable/ParHashTable;
    MethodParameters:
      Name                           Flags
      $this                          final synthetic

  public default boolean alwaysInitSizeMap();
    descriptor: ()Z
    flags: (0x0001) ACC_PUBLIC
    Code:
      stack=1, locals=1, args_size=1
         0: iconst_1
         1: ireturn
      LineNumberTable:
        line 27: 0
      LocalVariableTable:
        Start  Length  Slot  Name   Signature
            0       2     0  this   Lscala/collection/parallel/mutable/ParHashTable;

  public static void $init$(scala.collection.parallel.mutable.ParHashTable);
    descriptor: (Lscala/collection/parallel/mutable/ParHashTable;)V
    flags: (0x0009) ACC_PUBLIC, ACC_STATIC
    Code:
      stack=0, locals=1, args_size=1
         0: return
      LineNumberTable:
        line 24: 0
      LocalVariableTable:
        Start  Length  Slot  Name   Signature
            0       1     0 $this   Lscala/collection/parallel/mutable/ParHashTable;
    MethodParameters:
      Name                           Flags
      $this                          final synthetic
}
InnerClasses:
  public static #16= #15 of #2;           // Contents=class scala/collection/parallel/mutable/ParHashTable$Contents of class scala/collection/parallel/mutable/ParHashTable
  public abstract #19= #18 of #2;         // EntryIterator=class scala/collection/parallel/mutable/ParHashTable$EntryIterator of class scala/collection/parallel/mutable/ParHashTable
Signature: #3                           // <K:Ljava/lang/Object;V:Ljava/lang/Object;Entry::Lscala/collection/mutable/HashEntry<TK;TEntry;>;>Ljava/lang/Object;Lscala/collection/mutable/HashTable<TK;TV;TEntry;>;Lscala/collection/parallel/mutable/WithContents<TK;TV;TEntry;>;
SourceFile: "ParHashTable.scala"
RuntimeVisibleAnnotations:
  0: #11(#12=s#13)
    scala.reflect.ScalaSignature(
      bytes="\u0006\u0005\tUaa\u0002\u001a4!\u0003\r\t\u0001\u0010\u0005\u0006G\u0002!\t\u0001\u001a\u0005\u0006Q\u0002!\t%\u001b\u0004\u0006[\u0002\t\tA\u001c\u0005\tu\u000e\u0011\t\u0019!C\u0005w\"Iqp\u0001BA\u0002\u0013%\u0011\u0011\u0001\u0005\n\u0003\u000f\u0019!\u0011!Q!\nqD\u0011\"!\u0003\u0004\u0005\u000b\u0007I\u0011B>\t\u0013\u0005-1A!A!\u0002\u0013a\b\"CA\u0007\u0007\t\u0015\r\u0011\"\u0003|\u0011%\tya\u0001B\u0001B\u0003%A\u0010\u0003\u0006\u0002\u0012\r\u0011\t\u0019!C\u0005\u0003\'A!\"!\u0006\u0004\u0005\u0003\u0007I\u0011BA\f\u0011%\tYb\u0001B\u0001B\u0003&Q\u000bC\u0004\u0002\u001e\r!\t!a\b\t\u0013\u0005U2A1A\u0005\n\u0005]\u0002\u0002CA \u0007\u0001\u0006I!!\u000f\t\u0011\u0005\u00053\u00011A\u0005\nmD\u0011\"a\u0011\u0004\u0001\u0004%I!!\u0012\t\u000f\u0005%3\u0001)Q\u0005y\"9\u00111J\u0002\u0007\u0002\u00055\u0003bBA*\u0007\u0019\u0005\u0011Q\u000b\u0005\u0007\u0003K\u001aA\u0011A5\t\u000f\u0005\u001d4\u0001\"\u0001\u0002j!1\u00111N\u0002\u0005\u0002\u0011Da!!\u001c\u0004\t\u0003Y\b\u0002CA8\u0007\u0011\u0005S\'!\u001d\t\u000f\u0005%5\u0001\"\u0001\u0002\f\"9\u0011QR\u0002\u0005\u0002\u0005=\u0005bBAR\u0007\u0011%\u0011Q\u0015\u0005\b\u0003c\u001bA\u0011CAZ\u0011\u001d\tYl\u0001C\t\u0003{;\u0001\"a24\u0011\u00039\u0014\u0011\u001a\u0004\beMB\taNAf\u0011\u001d\ti\"\tC\u0001\u0003\u001b4a!a4\"\u0001\u0005E\u0007\"CAkG\t\u0015\r\u0011\"\u0001|\u0011%\t9n\tB\u0001B\u0003%A\u0010\u0003\u0006\u0002Z\u000e\u0012)\u0019!C\u0001\u00037D!\"!<$\u0005\u0003\u0005\u000b\u0011BAo\u0011%\tyo\tBC\u0002\u0013\u00051\u0010C\u0005\u0002r\u000e\u0012\t\u0011)A\u0005y\"I\u00111_\u0012\u0003\u0006\u0004%\ta\u001f\u0005\n\u0003k\u001c#\u0011!Q\u0001\nqD\u0011\"a>$\u0005\u000b\u0007I\u0011A>\t\u0013\u0005e8E!A!\u0002\u0013a\bBCA~G\t\u0015\r\u0011\"\u0001\u0002~\"Q!\u0011A\u0012\u0003\u0002\u0003\u0006I!a@\t\u000f\u0005u1\u0005\"\u0001\u0003\u0004!A\u0011qN\u0012\u0005\u0002]\n\tH\u0001\u0007QCJD\u0015m\u001d5UC\ndWM\u0003\u00025k\u00059Q.\u001e;bE2,\'B\u0001\u001c8\u0003!\u0001\u0018M]1mY\u0016d\'B\u0001\u001d:\u0003)\u0019w\u000e\u001c7fGRLwN\u001c\u0006\u0002u\u0005)1oY1mC\u000e\u0001Q\u0003B\u001fJ\'Z\u001bB\u0001\u0001 C?B\u0011q\bQ\u0007\u0002s%\u0011\u0011)\u000f\u0002\u0007\u0003:L(+\u001a4\u0011\u000b\r+uIU+\u000e\u0003\u0011S!\u0001N\u001c\n\u0005\u0019#%!\u0003%bg\"$\u0016M\u00197f!\tA\u0015\n\u0004\u0001\u0005\u000b)\u0003!\u0019A&\u0003\u0003-\u000b\"\u0001T(\u0011\u0005}j\u0015B\u0001(:\u0005\u001dqu\u000e\u001e5j]\u001e\u0004\"a\u0010)\n\u0005EK$aA!osB\u0011\u0001j\u0015\u0003\u0006)\u0002\u0011\ra\u0013\u0002\u0002-B\u0011\u0001J\u0016\u0003\u0006/\u0002\u0011\r\u0001\u0017\u0002\u0006\u000b:$(/_\t\u00033r\u0003\"a\u0010.\n\u0005mK$\u0001\u0002(vY2\u0004BaQ/H+&\u0011a\f\u0012\u0002\n\u0011\u0006\u001c\b.\u00128uef\u0004R\u0001Y1H%Vk\u0011aM\u0005\u0003EN\u0012AbV5uQ\u000e{g\u000e^3oiN\fa\u0001J5oSR$C#A3\u0011\u0005}2\u0017BA4:\u0005\u0011)f.\u001b;\u0002#\u0005dw/Y=t\u0013:LGoU5{K6\u000b\u0007/F\u0001k!\ty4.\u0003\u0002ms\t9!i\\8mK\u0006t\'!D#oiJL\u0018\n^3sCR|\'/\u0006\u0003pk\u0006\u001d2\u0003B\u0002?a^\u00042!\u001d:u\u001b\u0005)\u0014BA:6\u0005AIE/\u001a:bE2,7\u000b\u001d7jiR,\'\u000f\u0005\u0002Ik\u0012)ao\u0001b\u0001\u0017\n\tA\u000b\u0005\u0002aq&\u0011\u0011p\r\u0002\r\'&TX-T1q+RLGn]\u0001\u0004S\u0012DX#\u0001?\u0011\u0005}j\u0018B\u0001@:\u0005\rIe\u000e^\u0001\bS\u0012Dx\fJ3r)\r)\u00171\u0001\u0005\t\u0003\u000b)\u0011\u0011!a\u0001y\u0006\u0019\u0001\u0010J\u0019\u0002\t%$\u0007\u0010I\u0001\u0006k:$\u0018\u000e\\\u0001\u0007k:$\u0018\u000e\u001c\u0011\u0002\u0013Q|G/\u00197tSj,\u0017A\u0003;pi\u0006d7/\u001b>fA\u0005\u0011Qm]\u000b\u0002+\u00061Qm]0%KF$2!ZA\r\u0011!\t)\u0001DA\u0001\u0002\u0004)\u0016aA3tA\u00051A(\u001b8jiz\"\"\"!\t\u0002.\u0005=\u0012\u0011GA\u001a!\u0019\t\u0019c\u0001;\u0002&5\t\u0001\u0001E\u0002I\u0003O!\u0001\"!\u000b\u0004\t\u000b\u0007\u00111\u0006\u0002\t\u0013R,\'OU3qeF\u0011A\n\u001d\u0005\u0006u:\u0001\r\u0001 \u0005\u0007\u0003\u0013q\u0001\u0019\u0001?\t\r\u00055a\u00021\u0001}\u0011\u0019\t\tB\u0004a\u0001+\u0006I\u0011\u000e^3si\u0006\u0014G.Z\u000b\u0003\u0003s\u0001BaPA\u001e9&\u0019\u0011QH\u001d\u0003\u000b\u0005\u0013(/Y=\u0002\u0015%$XM\u001d;bE2,\u0007%A\u0005ue\u00064XM]:fI\u0006iAO]1wKJ\u001cX\rZ0%KF$2!ZA$\u0011!\t)AEA\u0001\u0002\u0004a\u0018A\u0003;sCZ,\'o]3eA\u0005QQM\u001c;ssJJG/Z7\u0015\u0007Q\fy\u0005\u0003\u0004\u0002RQ\u0001\r!V\u0001\u0002K\u0006Ya.Z<Ji\u0016\u0014\u0018\r^8s))\t)#a\u0016\u0002\\\u0005}\u00131\r\u0005\u0007\u00033*\u0002\u0019\u0001?\u0002\u000f%$\u0007P\u0012:p[\"1\u0011QL\u000bA\u0002q\f\u0001\"\u001b3y+:$\u0018\u000e\u001c\u0005\u0007\u0003C*\u0002\u0019\u0001?\u0002\u0013Q|G/\u00197TSj,\u0007BBA\t+\u0001\u0007Q+A\u0004iCNtU\r\u001f;\u0002\t9,\u0007\u0010\u001e\u000b\u0002i\u0006!1oY1o\u0003%\u0011X-\\1j]&tw-\u0001\teK\n,x-\u00138g_Jl\u0017\r^5p]V\u0011\u00111\u000f\t\u0005\u0003k\n\u0019I\u0004\u0003\u0002x\u0005}\u0004cAA=s5\u0011\u00111\u0010\u0006\u0004\u0003{Z\u0014A\u0002\u001fs_>$h(C\u0002\u0002\u0002f\na\u0001\u0015:fI\u00164\u0017\u0002BAC\u0003\u000f\u0013aa\u0015;sS:<\'bAAAs\u0005\u0019A-\u001e9\u0016\u0005\u0005\u0015\u0012!B:qY&$XCAAI!\u0015\t\u0019*!(q\u001d\u0011\t)*!\'\u000f\t\u0005e\u0014qS\u0005\u0002u%\u0019\u00111T\u001d\u0002\u000fA\f7m[1hK&!\u0011qTAQ\u0005\r\u0019V-\u001d\u0006\u0004\u00037K\u0014\u0001F2p]Z,\'\u000f\u001e+p\u0003J\u0014\u0018-\u001f\"vM\u001a,\'\u000f\u0006\u0003\u0002(\u00065\u0006\u0003B\"\u0002*RL1!a+E\u0005-\t%O]1z\u0005V4g-\u001a:\t\r\u0005=V\u00041\u0001V\u0003%\u0019\u0007.Y5oQ\u0016\fG-\u0001\u0006d_VtG/\u00127f[N$R\u0001`A[\u0003sCa!a.\u001f\u0001\u0004a\u0018\u0001\u00024s_6Da!!\u0003\u001f\u0001\u0004a\u0018\u0001E2pk:$()^2lKR\u001c\u0016N_3t)\u0015a\u0018qXAb\u0011\u0019\t\tm\ba\u0001y\u0006QaM]8n\u0005V\u001c7.\u001a;\t\r\u0005\u0015w\u00041\u0001}\u0003-)h\u000e^5m\u0005V\u001c7.\u001a;\u0002\u0019A\u000b\'\u000fS1tQR\u000b\'\r\\3\u0011\u0005\u0001\f3CA\u0011?)\t\tIM\u0001\u0005D_:$XM\u001c;t+\u0019\t\u0019.a9\u0002jN\u00111EP\u0001\u000bY>\fGMR1di>\u0014\u0018a\u00037pC\u00124\u0015m\u0019;pe\u0002\nQ\u0001^1cY\u0016,\"!!8\u0011\u000b}\nY$a8\u0011\r\rk\u0016\u0011]At!\rA\u00151\u001d\u0003\u0007\u0003K\u001c#\u0019A&\u0003\u0003\u0005\u00032\u0001SAu\t\u001996E1\u0001\u0002lF\u0019\u0011,a8\u0002\rQ\f\'\r\\3!\u0003%!\u0018M\u00197f\'&TX-\u0001\u0006uC\ndWmU5{K\u0002\n\u0011\u0002\u001e5sKNDw\u000e\u001c3\u0002\u0015QD\'/Z:i_2$\u0007%A\u0005tK\u0016$g/\u00197vK\u0006Q1/Z3em\u0006dW/\u001a\u0011\u0002\u000fML\'0Z7baV\u0011\u0011q \t\u0005\u007f\u0005mB0\u0001\u0005tSj,W.\u00199!)9\u0011)A!\u0003\u0003\f\t5!q\u0002B\t\u0005\'\u0001rAa\u0002$\u0003C\f9/D\u0001\"\u0011\u0019\t)\u000e\ra\u0001y\"9\u0011\u0011\u001c\u0019A\u0002\u0005u\u0007BBAxa\u0001\u0007A\u0010\u0003\u0004\u0002tB\u0002\r\u0001 \u0005\u0007\u0003o\u0004\u0004\u0019\u0001?\t\u000f\u0005m\b\u00071\u0001\u0002\u0000\u0002"
    )
  ScalaInlineInfo: length = 0x13 (unknown attribute)
   01 00 00 03 00 1D 00 1E 01 00 17 00 18 00 00 14
   00 15 01
  ScalaSig: length = 0x3 (unknown attribute)
   05 02 00
