Classfile /Users/mw/Projects/slang-braindump/.jar/jar8/assemble/slang-braindump/assemble/content/scala/collection/parallel/mutable/ParHashMap$.class
  Last modified May 29, 2022; size 2600 bytes
  SHA-256 checksum ac8ef4d8ed375590c7c45bdb135c1bff85ed08a941d0417016d2136ed68ec9a5
  Compiled from "ParHashMap.scala"
public final class scala.collection.parallel.mutable.ParHashMap$ extends scala.collection.generic.ParMapFactory<scala.collection.parallel.mutable.ParHashMap, scala.collection.mutable.HashMap> implements java.io.Serializable
  minor version: 0
  major version: 52
  flags: (0x0031) ACC_PUBLIC, ACC_FINAL, ACC_SUPER
  this_class: #2                          // scala/collection/parallel/mutable/ParHashMap$
  super_class: #5                         // scala/collection/generic/ParMapFactory
  interfaces: 1, fields: 2, methods: 9, attributes: 5
Constant pool:
   #1 = Utf8               scala/collection/parallel/mutable/ParHashMap$
   #2 = Class              #1             // scala/collection/parallel/mutable/ParHashMap$
   #3 = Utf8               Lscala/collection/generic/ParMapFactory<Lscala/collection/parallel/mutable/ParHashMap;Lscala/collection/mutable/HashMap;>;Ljava/io/Serializable;
   #4 = Utf8               scala/collection/generic/ParMapFactory
   #5 = Class              #4             // scala/collection/generic/ParMapFactory
   #6 = Utf8               java/io/Serializable
   #7 = Class              #6             // java/io/Serializable
   #8 = Utf8               ParHashMap.scala
   #9 = Utf8               scala/collection/generic/ParMapFactory$CanCombineFromMap
  #10 = Class              #9             // scala/collection/generic/ParMapFactory$CanCombineFromMap
  #11 = Utf8               CanCombineFromMap
  #12 = Utf8               MODULE$
  #13 = Utf8               Lscala/collection/parallel/mutable/ParHashMap$;
  #14 = Utf8               iters
  #15 = Utf8               I
  #16 = Utf8               <clinit>
  #17 = Utf8               ()V
  #18 = Utf8               <init>
  #19 = NameAndType        #18:#17        // "<init>":()V
  #20 = Methodref          #2.#19         // scala/collection/parallel/mutable/ParHashMap$."<init>":()V
  #21 = NameAndType        #12:#13        // MODULE$:Lscala/collection/parallel/mutable/ParHashMap$;
  #22 = Fieldref           #2.#21         // scala/collection/parallel/mutable/ParHashMap$.MODULE$:Lscala/collection/parallel/mutable/ParHashMap$;
  #23 = NameAndType        #14:#15        // iters:I
  #24 = Fieldref           #2.#23         // scala/collection/parallel/mutable/ParHashMap$.iters:I
  #25 = Utf8               ()I
  #26 = Utf8               this
  #27 = Utf8               iters_$eq
  #28 = Utf8               (I)V
  #29 = Utf8               x$1
  #30 = Utf8               empty
  #31 = Utf8               ()Lscala/collection/parallel/mutable/ParHashMap;
  #32 = Utf8               <K:Ljava/lang/Object;V:Ljava/lang/Object;>()Lscala/collection/parallel/mutable/ParHashMap<TK;TV;>;
  #33 = Utf8               scala/collection/parallel/mutable/ParHashMap
  #34 = Class              #33            // scala/collection/parallel/mutable/ParHashMap
  #35 = Methodref          #34.#19        // scala/collection/parallel/mutable/ParHashMap."<init>":()V
  #36 = Utf8               newCombiner
  #37 = Utf8               ()Lscala/collection/parallel/Combiner;
  #38 = Utf8               <K:Ljava/lang/Object;V:Ljava/lang/Object;>()Lscala/collection/parallel/Combiner<Lscala/Tuple2<TK;TV;>;Lscala/collection/parallel/mutable/ParHashMap<TK;TV;>;>;
  #39 = Utf8               scala/collection/parallel/mutable/ParHashMapCombiner$
  #40 = Class              #39            // scala/collection/parallel/mutable/ParHashMapCombiner$
  #41 = Utf8               Lscala/collection/parallel/mutable/ParHashMapCombiner$;
  #42 = NameAndType        #12:#41        // MODULE$:Lscala/collection/parallel/mutable/ParHashMapCombiner$;
  #43 = Fieldref           #40.#42        // scala/collection/parallel/mutable/ParHashMapCombiner$.MODULE$:Lscala/collection/parallel/mutable/ParHashMapCombiner$;
  #44 = Utf8               apply
  #45 = Utf8               ()Lscala/collection/parallel/mutable/ParHashMapCombiner;
  #46 = NameAndType        #44:#45        // apply:()Lscala/collection/parallel/mutable/ParHashMapCombiner;
  #47 = Methodref          #40.#46        // scala/collection/parallel/mutable/ParHashMapCombiner$.apply:()Lscala/collection/parallel/mutable/ParHashMapCombiner;
  #48 = Utf8               canBuildFrom
  #49 = Utf8               ()Lscala/collection/generic/CanCombineFrom;
  #50 = Utf8               <FromK:Ljava/lang/Object;FromV:Ljava/lang/Object;K:Ljava/lang/Object;V:Ljava/lang/Object;>()Lscala/collection/generic/CanCombineFrom<Lscala/collection/parallel/mutable/ParHashMap<TFromK;TFromV;>;Lscala/Tuple2<TK;TV;>;Lscala/collection/parallel/mutable/ParHashMap<TK;TV;>;>;
  #51 = Utf8               (Lscala/collection/generic/ParMapFactory;)V
  #52 = NameAndType        #18:#51        // "<init>":(Lscala/collection/generic/ParMapFactory;)V
  #53 = Methodref          #10.#52        // scala/collection/generic/ParMapFactory$CanCombineFromMap."<init>":(Lscala/collection/generic/ParMapFactory;)V
  #54 = Utf8               writeReplace
  #55 = Utf8               ()Ljava/lang/Object;
  #56 = Utf8               scala/runtime/ModuleSerializationProxy
  #57 = Class              #56            // scala/runtime/ModuleSerializationProxy
  #58 = Utf8               (Ljava/lang/Class;)V
  #59 = NameAndType        #18:#58        // "<init>":(Ljava/lang/Class;)V
  #60 = Methodref          #57.#59        // scala/runtime/ModuleSerializationProxy."<init>":(Ljava/lang/Class;)V
  #61 = Utf8               ()Lscala/collection/parallel/ParMap;
  #62 = NameAndType        #30:#31        // empty:()Lscala/collection/parallel/mutable/ParHashMap;
  #63 = Methodref          #2.#62         // scala/collection/parallel/mutable/ParHashMap$.empty:()Lscala/collection/parallel/mutable/ParHashMap;
  #64 = Methodref          #5.#19         // scala/collection/generic/ParMapFactory."<init>":()V
  #65 = Utf8               Code
  #66 = Utf8               LineNumberTable
  #67 = Utf8               LocalVariableTable
  #68 = Utf8               MethodParameters
  #69 = Utf8               Signature
  #70 = Utf8               InnerClasses
  #71 = Utf8               SourceFile
  #72 = Utf8               ScalaInlineInfo
  #73 = Utf8               Scala
{
  public static final scala.collection.parallel.mutable.ParHashMap$ MODULE$;
    descriptor: Lscala/collection/parallel/mutable/ParHashMap$;
    flags: (0x0019) ACC_PUBLIC, ACC_STATIC, ACC_FINAL

  private static int iters;
    descriptor: I
    flags: (0x000a) ACC_PRIVATE, ACC_STATIC

  public static {};
    descriptor: ()V
    flags: (0x0009) ACC_PUBLIC, ACC_STATIC
    Code:
      stack=2, locals=0, args_size=0
         0: new           #2                  // class scala/collection/parallel/mutable/ParHashMap$
         3: dup
         4: invokespecial #20                 // Method "<init>":()V
         7: putstatic     #22                 // Field MODULE$:Lscala/collection/parallel/mutable/ParHashMap$;
        10: iconst_0
        11: putstatic     #24                 // Field iters:I
        14: return
      LineNumberTable:
        line 153: 0
        line 154: 10
        line 153: 14

  public int iters();
    descriptor: ()I
    flags: (0x0001) ACC_PUBLIC
    Code:
      stack=1, locals=1, args_size=1
         0: getstatic     #24                 // Field iters:I
         3: ireturn
      LineNumberTable:
        line 154: 0
      LocalVariableTable:
        Start  Length  Slot  Name   Signature
            0       4     0  this   Lscala/collection/parallel/mutable/ParHashMap$;

  public void iters_$eq(int);
    descriptor: (I)V
    flags: (0x0001) ACC_PUBLIC
    Code:
      stack=1, locals=2, args_size=2
         0: iload_1
         1: putstatic     #24                 // Field iters:I
         4: return
      LineNumberTable:
        line 154: 0
      LocalVariableTable:
        Start  Length  Slot  Name   Signature
            0       5     0  this   Lscala/collection/parallel/mutable/ParHashMap$;
            0       5     1   x$1   I
    MethodParameters:
      Name                           Flags
      x$1                            final

  public <K extends java.lang.Object, V extends java.lang.Object> scala.collection.parallel.mutable.ParHashMap<K, V> empty();
    descriptor: ()Lscala/collection/parallel/mutable/ParHashMap;
    flags: (0x0001) ACC_PUBLIC
    Code:
      stack=2, locals=1, args_size=1
         0: new           #34                 // class scala/collection/parallel/mutable/ParHashMap
         3: dup
         4: invokespecial #35                 // Method scala/collection/parallel/mutable/ParHashMap."<init>":()V
         7: areturn
      LineNumberTable:
        line 156: 0
      LocalVariableTable:
        Start  Length  Slot  Name   Signature
            0       8     0  this   Lscala/collection/parallel/mutable/ParHashMap$;
    Signature: #32                          // <K:Ljava/lang/Object;V:Ljava/lang/Object;>()Lscala/collection/parallel/mutable/ParHashMap<TK;TV;>;

  public <K extends java.lang.Object, V extends java.lang.Object> scala.collection.parallel.Combiner<scala.Tuple2<K, V>, scala.collection.parallel.mutable.ParHashMap<K, V>> newCombiner();
    descriptor: ()Lscala/collection/parallel/Combiner;
    flags: (0x0001) ACC_PUBLIC
    Code:
      stack=1, locals=1, args_size=1
         0: getstatic     #43                 // Field scala/collection/parallel/mutable/ParHashMapCombiner$.MODULE$:Lscala/collection/parallel/mutable/ParHashMapCombiner$;
         3: invokevirtual #47                 // Method scala/collection/parallel/mutable/ParHashMapCombiner$.apply:()Lscala/collection/parallel/mutable/ParHashMapCombiner;
         6: areturn
      LineNumberTable:
        line 158: 0
      LocalVariableTable:
        Start  Length  Slot  Name   Signature
            0       7     0  this   Lscala/collection/parallel/mutable/ParHashMap$;
    Signature: #38                          // <K:Ljava/lang/Object;V:Ljava/lang/Object;>()Lscala/collection/parallel/Combiner<Lscala/Tuple2<TK;TV;>;Lscala/collection/parallel/mutable/ParHashMap<TK;TV;>;>;

  public <FromK extends java.lang.Object, FromV extends java.lang.Object, K extends java.lang.Object, V extends java.lang.Object> scala.collection.generic.CanCombineFrom<scala.collection.parallel.mutable.ParHashMap<FromK, FromV>, scala.Tuple2<K, V>, scala.collection.parallel.mutable.ParHashMap<K, V>> canBuildFrom();
    descriptor: ()Lscala/collection/generic/CanCombineFrom;
    flags: (0x0001) ACC_PUBLIC
    Code:
      stack=3, locals=1, args_size=1
         0: new           #10                 // class scala/collection/generic/ParMapFactory$CanCombineFromMap
         3: dup
         4: aload_0
         5: invokespecial #53                 // Method scala/collection/generic/ParMapFactory$CanCombineFromMap."<init>":(Lscala/collection/generic/ParMapFactory;)V
         8: areturn
      LineNumberTable:
        line 160: 0
      LocalVariableTable:
        Start  Length  Slot  Name   Signature
            0       9     0  this   Lscala/collection/parallel/mutable/ParHashMap$;
    Signature: #50                          // <FromK:Ljava/lang/Object;FromV:Ljava/lang/Object;K:Ljava/lang/Object;V:Ljava/lang/Object;>()Lscala/collection/generic/CanCombineFrom<Lscala/collection/parallel/mutable/ParHashMap<TFromK;TFromV;>;Lscala/Tuple2<TK;TV;>;Lscala/collection/parallel/mutable/ParHashMap<TK;TV;>;>;

  private java.lang.Object writeReplace();
    descriptor: ()Ljava/lang/Object;
    flags: (0x0002) ACC_PRIVATE
    Code:
      stack=3, locals=1, args_size=1
         0: new           #57                 // class scala/runtime/ModuleSerializationProxy
         3: dup
         4: ldc           #2                  // class scala/collection/parallel/mutable/ParHashMap$
         6: invokespecial #60                 // Method scala/runtime/ModuleSerializationProxy."<init>":(Ljava/lang/Class;)V
         9: areturn
      LineNumberTable:
        line 153: 0
      LocalVariableTable:
        Start  Length  Slot  Name   Signature
            0      10     0  this   Lscala/collection/parallel/mutable/ParHashMap$;

  public scala.collection.parallel.ParMap empty();
    descriptor: ()Lscala/collection/parallel/ParMap;
    flags: (0x1041) ACC_PUBLIC, ACC_BRIDGE, ACC_SYNTHETIC
    Code:
      stack=1, locals=1, args_size=1
         0: aload_0
         1: invokevirtual #63                 // Method empty:()Lscala/collection/parallel/mutable/ParHashMap;
         4: areturn
      LineNumberTable:
        line 153: 0
      LocalVariableTable:
        Start  Length  Slot  Name   Signature
            0       5     0  this   Lscala/collection/parallel/mutable/ParHashMap$;

  private scala.collection.parallel.mutable.ParHashMap$();
    descriptor: ()V
    flags: (0x0002) ACC_PRIVATE
    Code:
      stack=1, locals=1, args_size=1
         0: aload_0
         1: invokespecial #64                 // Method scala/collection/generic/ParMapFactory."<init>":()V
         4: return
      LineNumberTable:
        line 153: 0
      LocalVariableTable:
        Start  Length  Slot  Name   Signature
            0       5     0  this   Lscala/collection/parallel/mutable/ParHashMap$;
}
InnerClasses:
  public #11= #10 of #5;                  // CanCombineFromMap=class scala/collection/generic/ParMapFactory$CanCombineFromMap of class scala/collection/generic/ParMapFactory
Signature: #3                           // Lscala/collection/generic/ParMapFactory<Lscala/collection/parallel/mutable/ParHashMap;Lscala/collection/mutable/HashMap;>;Ljava/io/Serializable;
SourceFile: "ParHashMap.scala"
  ScalaInlineInfo: length = 0x2C (unknown attribute)
   01 01 00 08 00 12 00 11 01 00 30 00 31 01 00 1E
   00 3D 01 00 1E 00 1F 01 00 0E 00 19 01 00 1B 00
   1C 01 00 24 00 25 01 00 36 00 37 01
  Scala: length = 0x0 (unknown attribute)

