Classfile /Users/mw/Projects/slang-braindump/.jar/jar8/assemble/slang-braindump/assemble/content/scala/collection/parallel/mutable/ParMap.class
  Last modified May 29, 2022; size 7515 bytes
  SHA-256 checksum afebd2f621d940a534937fbd519ae91a94f68dc9eb550b1eb82c1c9520560f51
  Compiled from "ParMap.scala"
public interface scala.collection.parallel.mutable.ParMap<K extends java.lang.Object, V extends java.lang.Object> extends scala.collection.parallel.ParMap<K, V>, scala.collection.parallel.mutable.ParIterable<scala.Tuple2<K, V>>, scala.collection.parallel.mutable.ParMapLike<K, V, scala.collection.parallel.mutable.ParMap, scala.collection.parallel.mutable.ParMap<K, V>, scala.collection.mutable.Map<K, V>>
  minor version: 0
  major version: 52
  flags: (0x0601) ACC_PUBLIC, ACC_INTERFACE, ACC_ABSTRACT
  this_class: #2                          // scala/collection/parallel/mutable/ParMap
  super_class: #5                         // java/lang/Object
  interfaces: 3, fields: 0, methods: 18, attributes: 7
Constant pool:
    #1 = Utf8               scala/collection/parallel/mutable/ParMap
    #2 = Class              #1            // scala/collection/parallel/mutable/ParMap
    #3 = Utf8               <K:Ljava/lang/Object;V:Ljava/lang/Object;>Ljava/lang/Object;Lscala/collection/parallel/ParMap<TK;TV;>;Lscala/collection/parallel/mutable/ParIterable<Lscala/Tuple2<TK;TV;>;>;Lscala/collection/parallel/mutable/ParMapLike<TK;TV;Lscala/collection/parallel/mutable/ParMap;Lscala/collection/parallel/mutable/ParMap<TK;TV;>;Lscala/collection/mutable/Map<TK;TV;>;>;
    #4 = Utf8               java/lang/Object
    #5 = Class              #4            // java/lang/Object
    #6 = Utf8               scala/collection/parallel/ParMap
    #7 = Class              #6            // scala/collection/parallel/ParMap
    #8 = Utf8               scala/collection/parallel/mutable/ParIterable
    #9 = Class              #8            // scala/collection/parallel/mutable/ParIterable
   #10 = Utf8               scala/collection/parallel/mutable/ParMapLike
   #11 = Class              #10           // scala/collection/parallel/mutable/ParMapLike
   #12 = Utf8               ParMap.scala
   #13 = Utf8               Lscala/reflect/ScalaSignature;
   #14 = Utf8               bytes
   #15 = Utf8               \u0006\u0005\u0005\rhaB\u0010!!\u0003\r\t!\u000b\u0005\u0006/\u0002!\t\u0001\u0017\u0005\u00069\u0002!\t%\u0018\u0005\u0007C\u0002\u0001K\u0011\u000b2\t\u000b\u0019\u0004A\u0011I4\t\u000b-\u0004A\u0011\t7\t\u000b5\u0004a\u0011\u00018\t\u000b=\u0004A\u0011\u00019\t\u000bY\u0004A\u0011A<\b\u000be\u0004\u0003\u0012\u0001>\u0007\u000b}\u0001\u0003\u0012A>\t\u000f\u0005\u0005!\u0002\"\u0001\u0002\u0004!11N\u0003C\u0001\u0003\u000bAa!\u0019\u0006\u0005\u0002\u0005M\u0001bBA\u0013\u0015\u0011\r\u0011q\u0005\u0004\u0007\u0003\u0017R\u0001!!\u0014\t\u0015\u0005]tB!A!\u0002\u0013\t)\bC\u0005s\u001f\t\u0005\t\u0015!\u0003\u0002z!9\u0011\u0011A\b\u0005\u0002\u0005m\u0004\"\u0002/\u0010\t\u0003j\u0006bBAC\u001f\u0011\u0005\u0011q\u0011\u0005\b\u0003#{A\u0011AAJ\u0011\u0019Yw\u0002\"\u0011\u0002\u001a\"9\u00111T\b\u0005B\u0005u\u0005bBAY\u001f\u0011\u0005\u00131\u0017\u0005\b\u0003\u0003|A\u0011IAb\u0011\u0019iw\u0002\"\u0011\u0002H\"1\u00111Z\b\u0005\u0002aCq!!4\u0010\t\u0003\ty\r\u0003\u0004p\u001f\u0011\u0005\u00131\u001c\u0005\u0007m>!\t%a8\u0003\rA\u000b\'/T1q\u0015\t\t#%A\u0004nkR\f\'\r\\3\u000b\u0005\r\"\u0013\u0001\u00039be\u0006dG.\u001a7\u000b\u0005\u00152\u0013AC2pY2,7\r^5p]*\tq%A\u0003tG\u0006d\u0017m\u0001\u0001\u0016\u0007)\"dh\u0005\u0004\u0001W=\u0002uI\u0014\t\u0003Y5j\u0011AJ\u0005\u0003]\u0019\u0012a!\u00118z%\u00164\u0007\u0003\u0002\u00192euj\u0011AI\u0005\u0003?\t\u0002\"a\r\u001b\r\u0001\u0011)Q\u0007\u0001b\u0001m\t\t1*\u0005\u00028uA\u0011A\u0006O\u0005\u0003s\u0019\u0012qAT8uQ&tw\r\u0005\u0002-w%\u0011AH\n\u0002\u0004\u0003:L\bCA\u001a?\t\u0015y\u0004A1\u00017\u0005\u00051\u0006cA!C\t6\t\u0001%\u0003\u0002DA\tY\u0001+\u0019:Ji\u0016\u0014\u0018M\u00197f!\u0011aSIM\u001f\n\u0005\u00193#A\u0002+va2,\'\u0007E\u0003I\u0017JjT*D\u0001J\u0015\tQE%A\u0004hK:,\'/[2\n\u00051K%!F$f]\u0016\u0014\u0018n\u0019)be6\u000b\u0007\u000fV3na2\fG/\u001a\t\u0003\u0003\u0002\u0001r!Q(3{5\u000b&+\u0003\u0002QA\tQ\u0001+\u0019:NCBd\u0015n[3\u0011\t\u0005\u0003!\'\u0010\t\u0005\'V\u0013T(D\u0001U\u0015\t\tC%\u0003\u0002W)\n\u0019Q*\u00199\u0002\r\u0011Jg.\u001b;%)\u0005I\u0006C\u0001\u0017[\u0013\tYfE\u0001\u0003V]&$\u0018!C6o_^t7+\u001b>f+\u0005q\u0006C\u0001\u0017`\u0013\t\u0001gEA\u0002J]R\f1B\\3x\u0007>l\'-\u001b8feV\t1\r\u0005\u00031I\u0012\u000b\u0016BA3#\u0005!\u0019u.\u001c2j]\u0016\u0014\u0018\u0001D7ba\u000e{W\u000e]1oS>tW#\u00015\u0011\u0007!KW*\u0003\u0002k\u0013\n1r)\u001a8fe&\u001c\u0007+\u0019:NCB\u001cu.\u001c9b]&|g.A\u0003f[B$\u00180F\u0001R\u0003\r\u0019X-]\u000b\u0002%\u0006Yq/\u001b;i\t\u00164\u0017-\u001e7u)\t\t\u0016\u000fC\u0003s\u000f\u0001\u00071/A\u0001e!\u0011aCOM\u001f\n\u0005U4#!\u0003$v]\u000e$\u0018n\u001c82\u0003A9\u0018\u000e\u001e5EK\u001a\fW\u000f\u001c;WC2,X\r\u0006\u0002Rq\")!\u000f\u0003a\u0001{\u00051\u0001+\u0019:NCB\u0004\"!\u0011\u0006\u0014\u0005)a\b\u0003\u0002%~\u001b~L!A`%\u0003\u001bA\u000b\'/T1q\r\u0006\u001cGo\u001c:z!\t\u0019V+\u0001\u0004=S:LGO\u0010\u000b\u0002uV1\u0011qAA\u0007\u0003#)\"!!\u0003\u0011\r\u0005\u0003\u00111BA\b!\r\u0019\u0014Q\u0002\u0003\u0006k1\u0011\rA\u000e\t\u0004g\u0005EA!B \r\u0005\u00041TCBA\u000b\u0003;\t\t#\u0006\u0002\u0002\u0018A1\u0001\u0007ZA\r\u0003G\u0001b\u0001L#\u0002\u001c\u0005}\u0001cA\u001a\u0002\u001e\u0011)Q\'\u0004b\u0001mA\u00191\'!\t\u0005\u000b}j!\u0019\u0001\u001c\u0011\r\u0005\u0003\u00111DA\u0010\u00031\u0019\u0017M\u001c\"vS2$gI]8n+)\tI#!\u000e\u0002<\u0005\r\u0013qI\u000b\u0003\u0003W\u0001\u0012\u0002SA\u0017\u0003c\ty$!\u0013\n\u0007\u0005=\u0012J\u0001\bDC:\u001cu.\u001c2j]\u00164%o\\7\u0011\r\u0005\u0003\u00111GA\u001d!\r\u0019\u0014Q\u0007\u0003\u0007\u0003oq!\u0019\u0001\u001c\u0003\u000b\u0019\u0013x.\\&\u0011\u0007M\nY\u0004\u0002\u0004\u0002>9\u0011\rA\u000e\u0002\u0006\rJ|WN\u0016\t\u0007Y\u0015\u000b\t%!\u0012\u0011\u0007M\n\u0019\u0005B\u00036\u001d\t\u0007a\u0007E\u00024\u0003\u000f\"Qa\u0010\bC\u0002Y\u0002b!\u0011\u0001\u0002B\u0005\u0015#aC,ji\"$UMZ1vYR,b!a\u0014\u0002p\u0005M4#B\b\u0002R\u0005U\u0004\u0003CA*\u0003S\ni\'!\u001d\u000f\t\u0005U\u0013q\r\b\u0005\u0003/\n)G\u0004\u0003\u0002Z\u0005\rd\u0002BA.\u0003Cj!!!\u0018\u000b\u0007\u0005}\u0003&\u0001\u0004=e>|GOP\u0005\u0002O%\u0011QEJ\u0005\u0003G\u0011J!!\u001f\u0012\n\t\u0005-\u00131\u000e\u0006\u0003s\n\u00022aMA8\t\u0015)tB1\u00017!\r\u0019\u00141\u000f\u0003\u0006\u007f=\u0011\rA\u000e\t\u0007\u0003\u0002\ti\'!\u001d\u0002\u0015UtG-\u001a:ms&tw\r\u0005\u0004-i\u00065\u0014\u0011\u000f\u000b\u0007\u0003{\n\t)a!\u0011\u000f\u0005}t\"!\u001c\u0002r5\t!\u0002C\u0004\u0002xI\u0001\r!!\u001e\t\rI\u0014\u0002\u0019AA=\u0003\u0019\tG\rZ(oKR!\u0011\u0011RAF\u001b\u0005y\u0001bBAG)\u0001\u0007\u0011qR\u0001\u0003WZ\u0004b\u0001L#\u0002n\u0005E\u0014aC:vER\u0014\u0018m\u0019;P]\u0016$B!!#\u0002\u0016\"9\u0011qS\u000bA\u0002\u00055\u0014aA6fsV\u0011\u0011QP\u0001\bkB$\u0017\r^3e+\u0011\ty*!*\u0015\r\u0005\u0005\u00161VAW!\u001d\tyhDA7\u0003G\u00032aMAS\t\u001d\t9k\u0006b\u0001\u0003S\u0013\u0011!V\t\u0004\u0003cR\u0004bBAL/\u0001\u0007\u0011Q\u000e\u0005\b\u0003_;\u0002\u0019AAR\u0003\u00151\u0018\r\\;f\u0003\u0015!\u0003\u000f\\;t+\u0011\t),a/\u0015\t\u0005]\u0016Q\u0018\t\b\u0003\u007fz\u0011QNA]!\r\u0019\u00141\u0018\u0003\b\u0003OC\"\u0019AAU\u0011\u001d\ti\t\u0007a\u0001\u0003\u007f\u0003b\u0001L#\u0002n\u0005e\u0016A\u0002\u0013nS:,8\u000f\u0006\u0003\u0002~\u0005\u0015\u0007bBAL3\u0001\u0007\u0011QN\u000b\u0003\u0003\u0013\u0004baU+\u0002n\u0005E\u0014!B2mK\u0006\u0014\u0018a\u00019viR1\u0011\u0011[Al\u00033\u0004R\u0001LAj\u0003cJ1!!6\'\u0005\u0019y\u0005\u000f^5p]\"9\u0011q\u0013\u000fA\u0002\u00055\u0004bBAX9\u0001\u0007\u0011\u0011\u000f\u000b\u0005\u0003k\ni\u000e\u0003\u0004s;\u0001\u0007\u0011\u0011\u0010\u000b\u0005\u0003k\n\t\u000f\u0003\u0004s=\u0001\u0007\u0011\u0011\u000f
   #16 = Utf8               java/lang/invoke/MethodHandles$Lookup
   #17 = Class              #16           // java/lang/invoke/MethodHandles$Lookup
   #18 = Utf8               java/lang/invoke/MethodHandles
   #19 = Class              #18           // java/lang/invoke/MethodHandles
   #20 = Utf8               Lookup
   #21 = Utf8               scala/collection/parallel/mutable/ParMap$WithDefault
   #22 = Class              #21           // scala/collection/parallel/mutable/ParMap$WithDefault
   #23 = Utf8               WithDefault
   #24 = Utf8               canBuildFrom
   #25 = Utf8               ()Lscala/collection/generic/CanCombineFrom;
   #26 = Utf8               <FromK:Ljava/lang/Object;FromV:Ljava/lang/Object;K:Ljava/lang/Object;V:Ljava/lang/Object;>()Lscala/collection/generic/CanCombineFrom<Lscala/collection/parallel/mutable/ParMap<TFromK;TFromV;>;Lscala/Tuple2<TK;TV;>;Lscala/collection/parallel/mutable/ParMap<TK;TV;>;>;
   #27 = Utf8               scala/collection/parallel/mutable/ParMap$
   #28 = Class              #27           // scala/collection/parallel/mutable/ParMap$
   #29 = Utf8               MODULE$
   #30 = Utf8               Lscala/collection/parallel/mutable/ParMap$;
   #31 = NameAndType        #29:#30       // MODULE$:Lscala/collection/parallel/mutable/ParMap$;
   #32 = Fieldref           #28.#31       // scala/collection/parallel/mutable/ParMap$.MODULE$:Lscala/collection/parallel/mutable/ParMap$;
   #33 = NameAndType        #24:#25       // canBuildFrom:()Lscala/collection/generic/CanCombineFrom;
   #34 = Methodref          #28.#33       // scala/collection/parallel/mutable/ParMap$.canBuildFrom:()Lscala/collection/generic/CanCombineFrom;
   #35 = Utf8               toFactory
   #36 = Utf8               ()Lscala/collection/Factory;
   #37 = Utf8               <K:Ljava/lang/Object;V:Ljava/lang/Object;>()Lscala/collection/Factory<Lscala/Tuple2<TK;TV;>;Lscala/collection/parallel/mutable/ParMap<TK;TV;>;>;
   #38 = NameAndType        #35:#36       // toFactory:()Lscala/collection/Factory;
   #39 = Methodref          #28.#38       // scala/collection/parallel/mutable/ParMap$.toFactory:()Lscala/collection/Factory;
   #40 = Utf8               knownSize$
   #41 = Utf8               (Lscala/collection/parallel/mutable/ParMap;)I
   #42 = Utf8               $this
   #43 = Utf8               knownSize
   #44 = Utf8               ()I
   #45 = NameAndType        #43:#44       // knownSize:()I
   #46 = InterfaceMethodref #2.#45        // scala/collection/parallel/mutable/ParMap.knownSize:()I
   #47 = Utf8               Lscala/collection/parallel/mutable/ParMap;
   #48 = Utf8               this
   #49 = Utf8               newCombiner$
   #50 = Utf8               (Lscala/collection/parallel/mutable/ParMap;)Lscala/collection/parallel/Combiner;
   #51 = Utf8               newCombiner
   #52 = Utf8               ()Lscala/collection/parallel/Combiner;
   #53 = NameAndType        #51:#52       // newCombiner:()Lscala/collection/parallel/Combiner;
   #54 = InterfaceMethodref #2.#53        // scala/collection/parallel/mutable/ParMap.newCombiner:()Lscala/collection/parallel/Combiner;
   #55 = Utf8               ()Lscala/collection/parallel/Combiner<Lscala/Tuple2<TK;TV;>;Lscala/collection/parallel/mutable/ParMap<TK;TV;>;>;
   #56 = Methodref          #28.#53       // scala/collection/parallel/mutable/ParMap$.newCombiner:()Lscala/collection/parallel/Combiner;
   #57 = Utf8               mapCompanion$
   #58 = Utf8               (Lscala/collection/parallel/mutable/ParMap;)Lscala/collection/generic/GenericParMapCompanion;
   #59 = Utf8               mapCompanion
   #60 = Utf8               ()Lscala/collection/generic/GenericParMapCompanion;
   #61 = NameAndType        #59:#60       // mapCompanion:()Lscala/collection/generic/GenericParMapCompanion;
   #62 = InterfaceMethodref #2.#61        // scala/collection/parallel/mutable/ParMap.mapCompanion:()Lscala/collection/generic/GenericParMapCompanion;
   #63 = Utf8               ()Lscala/collection/generic/GenericParMapCompanion<Lscala/collection/parallel/mutable/ParMap;>;
   #64 = Utf8               empty$
   #65 = Utf8               (Lscala/collection/parallel/mutable/ParMap;)Lscala/collection/parallel/mutable/ParMap;
   #66 = Utf8               empty
   #67 = Utf8               ()Lscala/collection/parallel/mutable/ParMap;
   #68 = NameAndType        #66:#67       // empty:()Lscala/collection/parallel/mutable/ParMap;
   #69 = InterfaceMethodref #2.#68        // scala/collection/parallel/mutable/ParMap.empty:()Lscala/collection/parallel/mutable/ParMap;
   #70 = Utf8               ()Lscala/collection/parallel/mutable/ParMap<TK;TV;>;
   #71 = Utf8               scala/collection/parallel/mutable/ParHashMap
   #72 = Class              #71           // scala/collection/parallel/mutable/ParHashMap
   #73 = Utf8               <init>
   #74 = Utf8               ()V
   #75 = NameAndType        #73:#74       // "<init>":()V
   #76 = Methodref          #72.#75       // scala/collection/parallel/mutable/ParHashMap."<init>":()V
   #77 = Utf8               seq
   #78 = Utf8               ()Lscala/collection/mutable/Map;
   #79 = Utf8               ()Lscala/collection/mutable/Map<TK;TV;>;
   #80 = Utf8               withDefault$
   #81 = Utf8               (Lscala/collection/parallel/mutable/ParMap;Lscala/Function1;)Lscala/collection/parallel/mutable/ParMap;
   #82 = Utf8               d
   #83 = Utf8               withDefault
   #84 = Utf8               (Lscala/Function1;)Lscala/collection/parallel/mutable/ParMap;
   #85 = NameAndType        #83:#84       // withDefault:(Lscala/Function1;)Lscala/collection/parallel/mutable/ParMap;
   #86 = InterfaceMethodref #2.#85        // scala/collection/parallel/mutable/ParMap.withDefault:(Lscala/Function1;)Lscala/collection/parallel/mutable/ParMap;
   #87 = Utf8               Lscala/Function1;
   #88 = Utf8               (Lscala/Function1<TK;TV;>;)Lscala/collection/parallel/mutable/ParMap<TK;TV;>;
   #89 = Utf8               (Lscala/collection/parallel/mutable/ParMap;Lscala/Function1;)V
   #90 = NameAndType        #73:#89       // "<init>":(Lscala/collection/parallel/mutable/ParMap;Lscala/Function1;)V
   #91 = Methodref          #22.#90       // scala/collection/parallel/mutable/ParMap$WithDefault."<init>":(Lscala/collection/parallel/mutable/ParMap;Lscala/Function1;)V
   #92 = Utf8               withDefaultValue$
   #93 = Utf8               (Lscala/collection/parallel/mutable/ParMap;Ljava/lang/Object;)Lscala/collection/parallel/mutable/ParMap;
   #94 = Utf8               withDefaultValue
   #95 = Utf8               (Ljava/lang/Object;)Lscala/collection/parallel/mutable/ParMap;
   #96 = NameAndType        #94:#95       // withDefaultValue:(Ljava/lang/Object;)Lscala/collection/parallel/mutable/ParMap;
   #97 = InterfaceMethodref #2.#96        // scala/collection/parallel/mutable/ParMap.withDefaultValue:(Ljava/lang/Object;)Lscala/collection/parallel/mutable/ParMap;
   #98 = Utf8               Ljava/lang/Object;
   #99 = Utf8               (TV;)Lscala/collection/parallel/mutable/ParMap<TK;TV;>;
  #100 = Utf8               (Ljava/lang/Object;)Ljava/lang/Object;
  #101 = MethodType         #100          //  (Ljava/lang/Object;)Ljava/lang/Object;
  #102 = Utf8               $anonfun$withDefaultValue$1
  #103 = Utf8               (Ljava/lang/Object;Ljava/lang/Object;)Ljava/lang/Object;
  #104 = NameAndType        #102:#103     // $anonfun$withDefaultValue$1:(Ljava/lang/Object;Ljava/lang/Object;)Ljava/lang/Object;
  #105 = InterfaceMethodref #2.#104       // scala/collection/parallel/mutable/ParMap.$anonfun$withDefaultValue$1:(Ljava/lang/Object;Ljava/lang/Object;)Ljava/lang/Object;
  #106 = MethodHandle       6:#105        // REF_invokeStatic scala/collection/parallel/mutable/ParMap.$anonfun$withDefaultValue$1:(Ljava/lang/Object;Ljava/lang/Object;)Ljava/lang/Object;
  #107 = Integer            1
  #108 = Utf8               java/lang/invoke/LambdaMetafactory
  #109 = Class              #108          // java/lang/invoke/LambdaMetafactory
  #110 = Utf8               altMetafactory
  #111 = Utf8               (Ljava/lang/invoke/MethodHandles$Lookup;Ljava/lang/String;Ljava/lang/invoke/MethodType;[Ljava/lang/Object;)Ljava/lang/invoke/CallSite;
  #112 = NameAndType        #110:#111     // altMetafactory:(Ljava/lang/invoke/MethodHandles$Lookup;Ljava/lang/String;Ljava/lang/invoke/MethodType;[Ljava/lang/Object;)Ljava/lang/invoke/CallSite;
  #113 = Methodref          #109.#112     // java/lang/invoke/LambdaMetafactory.altMetafactory:(Ljava/lang/invoke/MethodHandles$Lookup;Ljava/lang/String;Ljava/lang/invoke/MethodType;[Ljava/lang/Object;)Ljava/lang/invoke/CallSite;
  #114 = MethodHandle       6:#113        // REF_invokeStatic java/lang/invoke/LambdaMetafactory.altMetafactory:(Ljava/lang/invoke/MethodHandles$Lookup;Ljava/lang/String;Ljava/lang/invoke/MethodType;[Ljava/lang/Object;)Ljava/lang/invoke/CallSite;
  #115 = Utf8               apply
  #116 = Utf8               (Ljava/lang/Object;)Lscala/Function1;
  #117 = NameAndType        #115:#116     // apply:(Ljava/lang/Object;)Lscala/Function1;
  #118 = InvokeDynamic      #0:#117       // #0:apply:(Ljava/lang/Object;)Lscala/Function1;
  #119 = Utf8               d$1
  #120 = Utf8               x
  #121 = Utf8               $init$
  #122 = Utf8               (Lscala/collection/parallel/mutable/ParMap;)V
  #123 = Utf8               $deserializeLambda$
  #124 = Utf8               (Ljava/lang/invoke/SerializedLambda;)Ljava/lang/Object;
  #125 = Utf8               scala/runtime/LambdaDeserialize
  #126 = Class              #125          // scala/runtime/LambdaDeserialize
  #127 = Utf8               bootstrap
  #128 = Utf8               (Ljava/lang/invoke/MethodHandles$Lookup;Ljava/lang/String;Ljava/lang/invoke/MethodType;[Ljava/lang/invoke/MethodHandle;)Ljava/lang/invoke/CallSite;
  #129 = NameAndType        #127:#128     // bootstrap:(Ljava/lang/invoke/MethodHandles$Lookup;Ljava/lang/String;Ljava/lang/invoke/MethodType;[Ljava/lang/invoke/MethodHandle;)Ljava/lang/invoke/CallSite;
  #130 = Methodref          #126.#129     // scala/runtime/LambdaDeserialize.bootstrap:(Ljava/lang/invoke/MethodHandles$Lookup;Ljava/lang/String;Ljava/lang/invoke/MethodType;[Ljava/lang/invoke/MethodHandle;)Ljava/lang/invoke/CallSite;
  #131 = MethodHandle       6:#130        // REF_invokeStatic scala/runtime/LambdaDeserialize.bootstrap:(Ljava/lang/invoke/MethodHandles$Lookup;Ljava/lang/String;Ljava/lang/invoke/MethodType;[Ljava/lang/invoke/MethodHandle;)Ljava/lang/invoke/CallSite;
  #132 = Utf8               lambdaDeserialize
  #133 = NameAndType        #132:#124     // lambdaDeserialize:(Ljava/lang/invoke/SerializedLambda;)Ljava/lang/Object;
  #134 = InvokeDynamic      #1:#133       // #1:lambdaDeserialize:(Ljava/lang/invoke/SerializedLambda;)Ljava/lang/Object;
  #135 = Utf8               Code
  #136 = Utf8               Signature
  #137 = Utf8               LineNumberTable
  #138 = Utf8               LocalVariableTable
  #139 = Utf8               MethodParameters
  #140 = Utf8               InnerClasses
  #141 = Utf8               SourceFile
  #142 = Utf8               RuntimeVisibleAnnotations
  #143 = Utf8               BootstrapMethods
  #144 = Utf8               ScalaInlineInfo
  #145 = Utf8               ScalaSig
{
  public static <FromK extends java.lang.Object, FromV extends java.lang.Object, K extends java.lang.Object, V extends java.lang.Object> scala.collection.generic.CanCombineFrom<scala.collection.parallel.mutable.ParMap<FromK, FromV>, scala.Tuple2<K, V>, scala.collection.parallel.mutable.ParMap<K, V>> canBuildFrom();
    descriptor: ()Lscala/collection/generic/CanCombineFrom;
    flags: (0x0009) ACC_PUBLIC, ACC_STATIC
    Code:
      stack=1, locals=0, args_size=0
         0: getstatic     #32                 // Field scala/collection/parallel/mutable/ParMap$.MODULE$:Lscala/collection/parallel/mutable/ParMap$;
         3: invokevirtual #34                 // Method scala/collection/parallel/mutable/ParMap$.canBuildFrom:()Lscala/collection/generic/CanCombineFrom;
         6: areturn
    Signature: #26                          // <FromK:Ljava/lang/Object;FromV:Ljava/lang/Object;K:Ljava/lang/Object;V:Ljava/lang/Object;>()Lscala/collection/generic/CanCombineFrom<Lscala/collection/parallel/mutable/ParMap<TFromK;TFromV;>;Lscala/Tuple2<TK;TV;>;Lscala/collection/parallel/mutable/ParMap<TK;TV;>;>;

  public static <K extends java.lang.Object, V extends java.lang.Object> scala.collection.Factory<scala.Tuple2<K, V>, scala.collection.parallel.mutable.ParMap<K, V>> toFactory();
    descriptor: ()Lscala/collection/Factory;
    flags: (0x0009) ACC_PUBLIC, ACC_STATIC
    Code:
      stack=1, locals=0, args_size=0
         0: getstatic     #32                 // Field scala/collection/parallel/mutable/ParMap$.MODULE$:Lscala/collection/parallel/mutable/ParMap$;
         3: invokevirtual #39                 // Method scala/collection/parallel/mutable/ParMap$.toFactory:()Lscala/collection/Factory;
         6: areturn
    Signature: #37                          // <K:Ljava/lang/Object;V:Ljava/lang/Object;>()Lscala/collection/Factory<Lscala/Tuple2<TK;TV;>;Lscala/collection/parallel/mutable/ParMap<TK;TV;>;>;

  public static int knownSize$(scala.collection.parallel.mutable.ParMap);
    descriptor: (Lscala/collection/parallel/mutable/ParMap;)I
    flags: (0x1009) ACC_PUBLIC, ACC_STATIC, ACC_SYNTHETIC
    Code:
      stack=1, locals=1, args_size=1
         0: aload_0
         1: invokespecial #46                 // InterfaceMethod knownSize:()I
         4: ireturn
      LineNumberTable:
        line 33: 0
      LocalVariableTable:
        Start  Length  Slot  Name   Signature
            0       5     0 $this   Lscala/collection/parallel/mutable/ParMap;
    MethodParameters:
      Name                           Flags
      $this                          final synthetic

  public default int knownSize();
    descriptor: ()I
    flags: (0x0001) ACC_PUBLIC
    Code:
      stack=1, locals=1, args_size=1
         0: iconst_m1
         1: ireturn
      LineNumberTable:
        line 33: 0
      LocalVariableTable:
        Start  Length  Slot  Name   Signature
            0       2     0  this   Lscala/collection/parallel/mutable/ParMap;

  public static scala.collection.parallel.Combiner newCombiner$(scala.collection.parallel.mutable.ParMap);
    descriptor: (Lscala/collection/parallel/mutable/ParMap;)Lscala/collection/parallel/Combiner;
    flags: (0x1009) ACC_PUBLIC, ACC_STATIC, ACC_SYNTHETIC
    Code:
      stack=1, locals=1, args_size=1
         0: aload_0
         1: invokespecial #54                 // InterfaceMethod newCombiner:()Lscala/collection/parallel/Combiner;
         4: areturn
      LineNumberTable:
        line 35: 0
      LocalVariableTable:
        Start  Length  Slot  Name   Signature
            0       5     0 $this   Lscala/collection/parallel/mutable/ParMap;
    MethodParameters:
      Name                           Flags
      $this                          final synthetic

  public default scala.collection.parallel.Combiner<scala.Tuple2<K, V>, scala.collection.parallel.mutable.ParMap<K, V>> newCombiner();
    descriptor: ()Lscala/collection/parallel/Combiner;
    flags: (0x0001) ACC_PUBLIC
    Code:
      stack=1, locals=1, args_size=1
         0: getstatic     #32                 // Field scala/collection/parallel/mutable/ParMap$.MODULE$:Lscala/collection/parallel/mutable/ParMap$;
         3: invokevirtual #56                 // Method scala/collection/parallel/mutable/ParMap$.newCombiner:()Lscala/collection/parallel/Combiner;
         6: areturn
      LineNumberTable:
        line 35: 0
      LocalVariableTable:
        Start  Length  Slot  Name   Signature
            0       7     0  this   Lscala/collection/parallel/mutable/ParMap;
    Signature: #55                          // ()Lscala/collection/parallel/Combiner<Lscala/Tuple2<TK;TV;>;Lscala/collection/parallel/mutable/ParMap<TK;TV;>;>;

  public static scala.collection.generic.GenericParMapCompanion mapCompanion$(scala.collection.parallel.mutable.ParMap);
    descriptor: (Lscala/collection/parallel/mutable/ParMap;)Lscala/collection/generic/GenericParMapCompanion;
    flags: (0x1009) ACC_PUBLIC, ACC_STATIC, ACC_SYNTHETIC
    Code:
      stack=1, locals=1, args_size=1
         0: aload_0
         1: invokespecial #62                 // InterfaceMethod mapCompanion:()Lscala/collection/generic/GenericParMapCompanion;
         4: areturn
      LineNumberTable:
        line 37: 0
      LocalVariableTable:
        Start  Length  Slot  Name   Signature
            0       5     0 $this   Lscala/collection/parallel/mutable/ParMap;
    MethodParameters:
      Name                           Flags
      $this                          final synthetic

  public default scala.collection.generic.GenericParMapCompanion<scala.collection.parallel.mutable.ParMap> mapCompanion();
    descriptor: ()Lscala/collection/generic/GenericParMapCompanion;
    flags: (0x0001) ACC_PUBLIC
    Code:
      stack=1, locals=1, args_size=1
         0: getstatic     #32                 // Field scala/collection/parallel/mutable/ParMap$.MODULE$:Lscala/collection/parallel/mutable/ParMap$;
         3: areturn
      LineNumberTable:
        line 37: 0
      LocalVariableTable:
        Start  Length  Slot  Name   Signature
            0       4     0  this   Lscala/collection/parallel/mutable/ParMap;
    Signature: #63                          // ()Lscala/collection/generic/GenericParMapCompanion<Lscala/collection/parallel/mutable/ParMap;>;

  public static scala.collection.parallel.mutable.ParMap empty$(scala.collection.parallel.mutable.ParMap);
    descriptor: (Lscala/collection/parallel/mutable/ParMap;)Lscala/collection/parallel/mutable/ParMap;
    flags: (0x1009) ACC_PUBLIC, ACC_STATIC, ACC_SYNTHETIC
    Code:
      stack=1, locals=1, args_size=1
         0: aload_0
         1: invokespecial #69                 // InterfaceMethod empty:()Lscala/collection/parallel/mutable/ParMap;
         4: areturn
      LineNumberTable:
        line 39: 0
      LocalVariableTable:
        Start  Length  Slot  Name   Signature
            0       5     0 $this   Lscala/collection/parallel/mutable/ParMap;
    MethodParameters:
      Name                           Flags
      $this                          final synthetic

  public default scala.collection.parallel.mutable.ParMap<K, V> empty();
    descriptor: ()Lscala/collection/parallel/mutable/ParMap;
    flags: (0x0001) ACC_PUBLIC
    Code:
      stack=2, locals=1, args_size=1
         0: new           #72                 // class scala/collection/parallel/mutable/ParHashMap
         3: dup
         4: invokespecial #76                 // Method scala/collection/parallel/mutable/ParHashMap."<init>":()V
         7: areturn
      LineNumberTable:
        line 39: 0
      LocalVariableTable:
        Start  Length  Slot  Name   Signature
            0       8     0  this   Lscala/collection/parallel/mutable/ParMap;
    Signature: #70                          // ()Lscala/collection/parallel/mutable/ParMap<TK;TV;>;

  public abstract scala.collection.mutable.Map<K, V> seq();
    descriptor: ()Lscala/collection/mutable/Map;
    flags: (0x0401) ACC_PUBLIC, ACC_ABSTRACT
    Signature: #79                          // ()Lscala/collection/mutable/Map<TK;TV;>;

  public static scala.collection.parallel.mutable.ParMap withDefault$(scala.collection.parallel.mutable.ParMap, scala.Function1);
    descriptor: (Lscala/collection/parallel/mutable/ParMap;Lscala/Function1;)Lscala/collection/parallel/mutable/ParMap;
    flags: (0x1009) ACC_PUBLIC, ACC_STATIC, ACC_SYNTHETIC
    Code:
      stack=2, locals=2, args_size=2
         0: aload_0
         1: aload_1
         2: invokespecial #86                 // InterfaceMethod withDefault:(Lscala/Function1;)Lscala/collection/parallel/mutable/ParMap;
         5: areturn
      LineNumberTable:
        line 51: 0
      LocalVariableTable:
        Start  Length  Slot  Name   Signature
            0       6     0 $this   Lscala/collection/parallel/mutable/ParMap;
            0       6     1     d   Lscala/Function1;
    MethodParameters:
      Name                           Flags
      $this                          final synthetic
      d                              final

  public default scala.collection.parallel.mutable.ParMap<K, V> withDefault(scala.Function1<K, V>);
    descriptor: (Lscala/Function1;)Lscala/collection/parallel/mutable/ParMap;
    flags: (0x0001) ACC_PUBLIC
    Code:
      stack=4, locals=2, args_size=2
         0: new           #22                 // class scala/collection/parallel/mutable/ParMap$WithDefault
         3: dup
         4: aload_0
         5: aload_1
         6: invokespecial #91                 // Method scala/collection/parallel/mutable/ParMap$WithDefault."<init>":(Lscala/collection/parallel/mutable/ParMap;Lscala/Function1;)V
         9: areturn
      LineNumberTable:
        line 51: 0
      LocalVariableTable:
        Start  Length  Slot  Name   Signature
            0      10     0  this   Lscala/collection/parallel/mutable/ParMap;
            0      10     1     d   Lscala/Function1;
    Signature: #88                          // (Lscala/Function1<TK;TV;>;)Lscala/collection/parallel/mutable/ParMap<TK;TV;>;
    MethodParameters:
      Name                           Flags
      d                              final

  public static scala.collection.parallel.mutable.ParMap withDefaultValue$(scala.collection.parallel.mutable.ParMap, java.lang.Object);
    descriptor: (Lscala/collection/parallel/mutable/ParMap;Ljava/lang/Object;)Lscala/collection/parallel/mutable/ParMap;
    flags: (0x1009) ACC_PUBLIC, ACC_STATIC, ACC_SYNTHETIC
    Code:
      stack=2, locals=2, args_size=2
         0: aload_0
         1: aload_1
         2: invokespecial #97                 // InterfaceMethod withDefaultValue:(Ljava/lang/Object;)Lscala/collection/parallel/mutable/ParMap;
         5: areturn
      LineNumberTable:
        line 60: 0
      LocalVariableTable:
        Start  Length  Slot  Name   Signature
            0       6     0 $this   Lscala/collection/parallel/mutable/ParMap;
            0       6     1     d   Ljava/lang/Object;
    MethodParameters:
      Name                           Flags
      $this                          final synthetic
      d                              final

  public default scala.collection.parallel.mutable.ParMap<K, V> withDefaultValue(V);
    descriptor: (Ljava/lang/Object;)Lscala/collection/parallel/mutable/ParMap;
    flags: (0x0001) ACC_PUBLIC
    Code:
      stack=4, locals=2, args_size=2
         0: new           #22                 // class scala/collection/parallel/mutable/ParMap$WithDefault
         3: dup
         4: aload_0
         5: aload_1
         6: invokedynamic #118,  0            // InvokeDynamic #0:apply:(Ljava/lang/Object;)Lscala/Function1;
        11: invokespecial #91                 // Method scala/collection/parallel/mutable/ParMap$WithDefault."<init>":(Lscala/collection/parallel/mutable/ParMap;Lscala/Function1;)V
        14: areturn
      LineNumberTable:
        line 60: 0
      LocalVariableTable:
        Start  Length  Slot  Name   Signature
            0      15     0  this   Lscala/collection/parallel/mutable/ParMap;
            0      15     1     d   Ljava/lang/Object;
    Signature: #99                          // (TV;)Lscala/collection/parallel/mutable/ParMap<TK;TV;>;
    MethodParameters:
      Name                           Flags
      d                              final

  public static java.lang.Object $anonfun$withDefaultValue$1(java.lang.Object, java.lang.Object);
    descriptor: (Ljava/lang/Object;Ljava/lang/Object;)Ljava/lang/Object;
    flags: (0x1009) ACC_PUBLIC, ACC_STATIC, ACC_SYNTHETIC
    Code:
      stack=1, locals=2, args_size=2
         0: aload_0
         1: areturn
      LineNumberTable:
        line 60: 0
      LocalVariableTable:
        Start  Length  Slot  Name   Signature
            0       2     0   d$1   Ljava/lang/Object;
            0       2     1     x   Ljava/lang/Object;
    MethodParameters:
      Name                           Flags
      d$1                            final
      x                              final

  public static void $init$(scala.collection.parallel.mutable.ParMap);
    descriptor: (Lscala/collection/parallel/mutable/ParMap;)V
    flags: (0x0009) ACC_PUBLIC, ACC_STATIC
    Code:
      stack=0, locals=1, args_size=1
         0: return
      LineNumberTable:
        line 28: 0
      LocalVariableTable:
        Start  Length  Slot  Name   Signature
            0       1     0 $this   Lscala/collection/parallel/mutable/ParMap;
    MethodParameters:
      Name                           Flags
      $this                          final synthetic

  private static java.lang.Object $deserializeLambda$(java.lang.invoke.SerializedLambda);
    descriptor: (Ljava/lang/invoke/SerializedLambda;)Ljava/lang/Object;
    flags: (0x100a) ACC_PRIVATE, ACC_STATIC, ACC_SYNTHETIC
    Code:
      stack=1, locals=1, args_size=1
         0: aload_0
         1: invokedynamic #134,  0            // InvokeDynamic #1:lambdaDeserialize:(Ljava/lang/invoke/SerializedLambda;)Ljava/lang/Object;
         6: areturn
}
InnerClasses:
  public static final #20= #17 of #19;    // Lookup=class java/lang/invoke/MethodHandles$Lookup of class java/lang/invoke/MethodHandles
  public static #23= #22 of #2;           // WithDefault=class scala/collection/parallel/mutable/ParMap$WithDefault of class scala/collection/parallel/mutable/ParMap
Signature: #3                           // <K:Ljava/lang/Object;V:Ljava/lang/Object;>Ljava/lang/Object;Lscala/collection/parallel/ParMap<TK;TV;>;Lscala/collection/parallel/mutable/ParIterable<Lscala/Tuple2<TK;TV;>;>;Lscala/collection/parallel/mutable/ParMapLike<TK;TV;Lscala/collection/parallel/mutable/ParMap;Lscala/collection/parallel/mutable/ParMap<TK;TV;>;Lscala/collection/mutable/Map<TK;TV;>;>;
SourceFile: "ParMap.scala"
RuntimeVisibleAnnotations:
  0: #13(#14=s#15)
    scala.reflect.ScalaSignature(
      bytes="\u0006\u0005\u0005\rhaB\u0010!!\u0003\r\t!\u000b\u0005\u0006/\u0002!\t\u0001\u0017\u0005\u00069\u0002!\t%\u0018\u0005\u0007C\u0002\u0001K\u0011\u000b2\t\u000b\u0019\u0004A\u0011I4\t\u000b-\u0004A\u0011\t7\t\u000b5\u0004a\u0011\u00018\t\u000b=\u0004A\u0011\u00019\t\u000bY\u0004A\u0011A<\b\u000be\u0004\u0003\u0012\u0001>\u0007\u000b}\u0001\u0003\u0012A>\t\u000f\u0005\u0005!\u0002\"\u0001\u0002\u0004!11N\u0003C\u0001\u0003\u000bAa!\u0019\u0006\u0005\u0002\u0005M\u0001bBA\u0013\u0015\u0011\r\u0011q\u0005\u0004\u0007\u0003\u0017R\u0001!!\u0014\t\u0015\u0005]tB!A!\u0002\u0013\t)\bC\u0005s\u001f\t\u0005\t\u0015!\u0003\u0002z!9\u0011\u0011A\b\u0005\u0002\u0005m\u0004\"\u0002/\u0010\t\u0003j\u0006bBAC\u001f\u0011\u0005\u0011q\u0011\u0005\b\u0003#{A\u0011AAJ\u0011\u0019Yw\u0002\"\u0011\u0002\u001a\"9\u00111T\b\u0005B\u0005u\u0005bBAY\u001f\u0011\u0005\u00131\u0017\u0005\b\u0003\u0003|A\u0011IAb\u0011\u0019iw\u0002\"\u0011\u0002H\"1\u00111Z\b\u0005\u0002aCq!!4\u0010\t\u0003\ty\r\u0003\u0004p\u001f\u0011\u0005\u00131\u001c\u0005\u0007m>!\t%a8\u0003\rA\u000b\'/T1q\u0015\t\t#%A\u0004nkR\f\'\r\\3\u000b\u0005\r\"\u0013\u0001\u00039be\u0006dG.\u001a7\u000b\u0005\u00152\u0013AC2pY2,7\r^5p]*\tq%A\u0003tG\u0006d\u0017m\u0001\u0001\u0016\u0007)\"dh\u0005\u0004\u0001W=\u0002uI\u0014\t\u0003Y5j\u0011AJ\u0005\u0003]\u0019\u0012a!\u00118z%\u00164\u0007\u0003\u0002\u00192euj\u0011AI\u0005\u0003?\t\u0002\"a\r\u001b\r\u0001\u0011)Q\u0007\u0001b\u0001m\t\t1*\u0005\u00028uA\u0011A\u0006O\u0005\u0003s\u0019\u0012qAT8uQ&tw\r\u0005\u0002-w%\u0011AH\n\u0002\u0004\u0003:L\bCA\u001a?\t\u0015y\u0004A1\u00017\u0005\u00051\u0006cA!C\t6\t\u0001%\u0003\u0002DA\tY\u0001+\u0019:Ji\u0016\u0014\u0018M\u00197f!\u0011aSIM\u001f\n\u0005\u00193#A\u0002+va2,\'\u0007E\u0003I\u0017JjT*D\u0001J\u0015\tQE%A\u0004hK:,\'/[2\n\u00051K%!F$f]\u0016\u0014\u0018n\u0019)be6\u000b\u0007\u000fV3na2\fG/\u001a\t\u0003\u0003\u0002\u0001r!Q(3{5\u000b&+\u0003\u0002QA\tQ\u0001+\u0019:NCBd\u0015n[3\u0011\t\u0005\u0003!\'\u0010\t\u0005\'V\u0013T(D\u0001U\u0015\t\tC%\u0003\u0002W)\n\u0019Q*\u00199\u0002\r\u0011Jg.\u001b;%)\u0005I\u0006C\u0001\u0017[\u0013\tYfE\u0001\u0003V]&$\u0018!C6o_^t7+\u001b>f+\u0005q\u0006C\u0001\u0017`\u0013\t\u0001gEA\u0002J]R\f1B\\3x\u0007>l\'-\u001b8feV\t1\r\u0005\u00031I\u0012\u000b\u0016BA3#\u0005!\u0019u.\u001c2j]\u0016\u0014\u0018\u0001D7ba\u000e{W\u000e]1oS>tW#\u00015\u0011\u0007!KW*\u0003\u0002k\u0013\n1r)\u001a8fe&\u001c\u0007+\u0019:NCB\u001cu.\u001c9b]&|g.A\u0003f[B$\u00180F\u0001R\u0003\r\u0019X-]\u000b\u0002%\u0006Yq/\u001b;i\t\u00164\u0017-\u001e7u)\t\t\u0016\u000fC\u0003s\u000f\u0001\u00071/A\u0001e!\u0011aCOM\u001f\n\u0005U4#!\u0003$v]\u000e$\u0018n\u001c82\u0003A9\u0018\u000e\u001e5EK\u001a\fW\u000f\u001c;WC2,X\r\u0006\u0002Rq\")!\u000f\u0003a\u0001{\u00051\u0001+\u0019:NCB\u0004\"!\u0011\u0006\u0014\u0005)a\b\u0003\u0002%~\u001b~L!A`%\u0003\u001bA\u000b\'/T1q\r\u0006\u001cGo\u001c:z!\t\u0019V+\u0001\u0004=S:LGO\u0010\u000b\u0002uV1\u0011qAA\u0007\u0003#)\"!!\u0003\u0011\r\u0005\u0003\u00111BA\b!\r\u0019\u0014Q\u0002\u0003\u0006k1\u0011\rA\u000e\t\u0004g\u0005EA!B \r\u0005\u00041TCBA\u000b\u0003;\t\t#\u0006\u0002\u0002\u0018A1\u0001\u0007ZA\r\u0003G\u0001b\u0001L#\u0002\u001c\u0005}\u0001cA\u001a\u0002\u001e\u0011)Q\'\u0004b\u0001mA\u00191\'!\t\u0005\u000b}j!\u0019\u0001\u001c\u0011\r\u0005\u0003\u00111DA\u0010\u00031\u0019\u0017M\u001c\"vS2$gI]8n+)\tI#!\u000e\u0002<\u0005\r\u0013qI\u000b\u0003\u0003W\u0001\u0012\u0002SA\u0017\u0003c\ty$!\u0013\n\u0007\u0005=\u0012J\u0001\bDC:\u001cu.\u001c2j]\u00164%o\\7\u0011\r\u0005\u0003\u00111GA\u001d!\r\u0019\u0014Q\u0007\u0003\u0007\u0003oq!\u0019\u0001\u001c\u0003\u000b\u0019\u0013x.\\&\u0011\u0007M\nY\u0004\u0002\u0004\u0002>9\u0011\rA\u000e\u0002\u0006\rJ|WN\u0016\t\u0007Y\u0015\u000b\t%!\u0012\u0011\u0007M\n\u0019\u0005B\u00036\u001d\t\u0007a\u0007E\u00024\u0003\u000f\"Qa\u0010\bC\u0002Y\u0002b!\u0011\u0001\u0002B\u0005\u0015#aC,ji\"$UMZ1vYR,b!a\u0014\u0002p\u0005M4#B\b\u0002R\u0005U\u0004\u0003CA*\u0003S\ni\'!\u001d\u000f\t\u0005U\u0013q\r\b\u0005\u0003/\n)G\u0004\u0003\u0002Z\u0005\rd\u0002BA.\u0003Cj!!!\u0018\u000b\u0007\u0005}\u0003&\u0001\u0004=e>|GOP\u0005\u0002O%\u0011QEJ\u0005\u0003G\u0011J!!\u001f\u0012\n\t\u0005-\u00131\u000e\u0006\u0003s\n\u00022aMA8\t\u0015)tB1\u00017!\r\u0019\u00141\u000f\u0003\u0006\u007f=\u0011\rA\u000e\t\u0007\u0003\u0002\ti\'!\u001d\u0002\u0015UtG-\u001a:ms&tw\r\u0005\u0004-i\u00065\u0014\u0011\u000f\u000b\u0007\u0003{\n\t)a!\u0011\u000f\u0005}t\"!\u001c\u0002r5\t!\u0002C\u0004\u0002xI\u0001\r!!\u001e\t\rI\u0014\u0002\u0019AA=\u0003\u0019\tG\rZ(oKR!\u0011\u0011RAF\u001b\u0005y\u0001bBAG)\u0001\u0007\u0011qR\u0001\u0003WZ\u0004b\u0001L#\u0002n\u0005E\u0014aC:vER\u0014\u0018m\u0019;P]\u0016$B!!#\u0002\u0016\"9\u0011qS\u000bA\u0002\u00055\u0014aA6fsV\u0011\u0011QP\u0001\bkB$\u0017\r^3e+\u0011\ty*!*\u0015\r\u0005\u0005\u00161VAW!\u001d\tyhDA7\u0003G\u00032aMAS\t\u001d\t9k\u0006b\u0001\u0003S\u0013\u0011!V\t\u0004\u0003cR\u0004bBAL/\u0001\u0007\u0011Q\u000e\u0005\b\u0003_;\u0002\u0019AAR\u0003\u00151\u0018\r\\;f\u0003\u0015!\u0003\u000f\\;t+\u0011\t),a/\u0015\t\u0005]\u0016Q\u0018\t\b\u0003\u007fz\u0011QNA]!\r\u0019\u00141\u0018\u0003\b\u0003OC\"\u0019AAU\u0011\u001d\ti\t\u0007a\u0001\u0003\u007f\u0003b\u0001L#\u0002n\u0005e\u0016A\u0002\u0013nS:,8\u000f\u0006\u0003\u0002~\u0005\u0015\u0007bBAL3\u0001\u0007\u0011QN\u000b\u0003\u0003\u0013\u0004baU+\u0002n\u0005E\u0014!B2mK\u0006\u0014\u0018a\u00019viR1\u0011\u0011[Al\u00033\u0004R\u0001LAj\u0003cJ1!!6\'\u0005\u0019y\u0005\u000f^5p]\"9\u0011q\u0013\u000fA\u0002\u00055\u0004bBAX9\u0001\u0007\u0011\u0011\u000f\u000b\u0005\u0003k\ni\u000e\u0003\u0004s;\u0001\u0007\u0011\u0011\u0010\u000b\u0005\u0003k\n\t\u000f\u0003\u0004s=\u0001\u0007\u0011\u0011\u000f"
    )
BootstrapMethods:
  0: #114 REF_invokeStatic java/lang/invoke/LambdaMetafactory.altMetafactory:(Ljava/lang/invoke/MethodHandles$Lookup;Ljava/lang/String;Ljava/lang/invoke/MethodType;[Ljava/lang/Object;)Ljava/lang/invoke/CallSite;
    Method arguments:
      #101 (Ljava/lang/Object;)Ljava/lang/Object;
      #106 REF_invokeStatic scala/collection/parallel/mutable/ParMap.$anonfun$withDefaultValue$1:(Ljava/lang/Object;Ljava/lang/Object;)Ljava/lang/Object;
      #101 (Ljava/lang/Object;)Ljava/lang/Object;
      #107 1
  1: #131 REF_invokeStatic scala/runtime/LambdaDeserialize.bootstrap:(Ljava/lang/invoke/MethodHandles$Lookup;Ljava/lang/String;Ljava/lang/invoke/MethodType;[Ljava/lang/invoke/MethodHandle;)Ljava/lang/invoke/CallSite;
    Method arguments:
      #106 REF_invokeStatic scala/collection/parallel/mutable/ParMap.$anonfun$withDefaultValue$1:(Ljava/lang/Object;Ljava/lang/Object;)Ljava/lang/Object;
  ScalaInlineInfo: length = 0x4F (unknown attribute)
   01 00 00 0F 00 66 00 67 01 00 79 00 7A 01 00 42
   00 43 00 00 40 00 41 01 00 2B 00 2C 00 00 28 00
   29 01 00 3B 00 3C 00 00 39 00 3A 01 00 33 00 34
   00 00 31 00 32 01 00 4D 00 4E 00 00 53 00 54 00
   00 50 00 51 01 00 5E 00 5F 00 00 5C 00 5D 01
  ScalaSig: length = 0x3 (unknown attribute)
   05 02 00
