Classfile /Users/mw/Projects/slang-braindump/.jar/jar8/assemble/slang-braindump/assemble/content/scala/collection/parallel/mutable/ParSeq$.class
  Last modified May 29, 2022; size 1766 bytes
  SHA-256 checksum 458acfe0278f4ba8c4490544c6e88fb44d12c21fe9c9872985b66e7a092a83bb
  Compiled from "ParSeq.scala"
public final class scala.collection.parallel.mutable.ParSeq$ extends scala.collection.generic.ParFactory<scala.collection.parallel.mutable.ParSeq>
  minor version: 0
  major version: 52
  flags: (0x0031) ACC_PUBLIC, ACC_FINAL, ACC_SUPER
  this_class: #2                          // scala/collection/parallel/mutable/ParSeq$
  super_class: #5                         // scala/collection/generic/ParFactory
  interfaces: 0, fields: 1, methods: 5, attributes: 5
Constant pool:
   #1 = Utf8               scala/collection/parallel/mutable/ParSeq$
   #2 = Class              #1             // scala/collection/parallel/mutable/ParSeq$
   #3 = Utf8               Lscala/collection/generic/ParFactory<Lscala/collection/parallel/mutable/ParSeq;>;
   #4 = Utf8               scala/collection/generic/ParFactory
   #5 = Class              #4             // scala/collection/generic/ParFactory
   #6 = Utf8               ParSeq.scala
   #7 = Utf8               scala/collection/generic/ParFactory$GenericCanCombineFrom
   #8 = Class              #7             // scala/collection/generic/ParFactory$GenericCanCombineFrom
   #9 = Utf8               GenericCanCombineFrom
  #10 = Utf8               MODULE$
  #11 = Utf8               Lscala/collection/parallel/mutable/ParSeq$;
  #12 = Utf8               <clinit>
  #13 = Utf8               ()V
  #14 = Utf8               <init>
  #15 = NameAndType        #14:#13        // "<init>":()V
  #16 = Methodref          #2.#15         // scala/collection/parallel/mutable/ParSeq$."<init>":()V
  #17 = NameAndType        #10:#11        // MODULE$:Lscala/collection/parallel/mutable/ParSeq$;
  #18 = Fieldref           #2.#17         // scala/collection/parallel/mutable/ParSeq$.MODULE$:Lscala/collection/parallel/mutable/ParSeq$;
  #19 = Utf8               canBuildFrom
  #20 = Utf8               ()Lscala/collection/generic/CanCombineFrom;
  #21 = Utf8               <S:Ljava/lang/Object;T:Ljava/lang/Object;>()Lscala/collection/generic/CanCombineFrom<Lscala/collection/parallel/mutable/ParSeq<TS;>;TT;Lscala/collection/parallel/mutable/ParSeq<TT;>;>;
  #22 = Utf8               (Lscala/collection/generic/ParFactory;)V
  #23 = NameAndType        #14:#22        // "<init>":(Lscala/collection/generic/ParFactory;)V
  #24 = Methodref          #8.#23         // scala/collection/generic/ParFactory$GenericCanCombineFrom."<init>":(Lscala/collection/generic/ParFactory;)V
  #25 = Utf8               this
  #26 = Utf8               newBuilder
  #27 = Utf8               ()Lscala/collection/parallel/Combiner;
  #28 = Utf8               <T:Ljava/lang/Object;>()Lscala/collection/parallel/Combiner<TT;Lscala/collection/parallel/mutable/ParSeq<TT;>;>;
  #29 = Utf8               scala/collection/parallel/mutable/package$
  #30 = Class              #29            // scala/collection/parallel/mutable/package$
  #31 = Utf8               Lscala/collection/parallel/mutable/package$;
  #32 = NameAndType        #10:#31        // MODULE$:Lscala/collection/parallel/mutable/package$;
  #33 = Fieldref           #30.#32        // scala/collection/parallel/mutable/package$.MODULE$:Lscala/collection/parallel/mutable/package$;
  #34 = Utf8               ParArrayCombiner
  #35 = Utf8               ()Lscala/collection/parallel/mutable/ResizableParArrayCombiner$;
  #36 = NameAndType        #34:#35        // ParArrayCombiner:()Lscala/collection/parallel/mutable/ResizableParArrayCombiner$;
  #37 = Methodref          #30.#36        // scala/collection/parallel/mutable/package$.ParArrayCombiner:()Lscala/collection/parallel/mutable/ResizableParArrayCombiner$;
  #38 = Utf8               scala/collection/parallel/mutable/ResizableParArrayCombiner$
  #39 = Class              #38            // scala/collection/parallel/mutable/ResizableParArrayCombiner$
  #40 = Utf8               apply
  #41 = Utf8               ()Lscala/collection/parallel/mutable/ResizableParArrayCombiner;
  #42 = NameAndType        #40:#41        // apply:()Lscala/collection/parallel/mutable/ResizableParArrayCombiner;
  #43 = Methodref          #39.#42        // scala/collection/parallel/mutable/ResizableParArrayCombiner$.apply:()Lscala/collection/parallel/mutable/ResizableParArrayCombiner;
  #44 = Utf8               newCombiner
  #45 = Methodref          #5.#15         // scala/collection/generic/ParFactory."<init>":()V
  #46 = Utf8               Code
  #47 = Utf8               LineNumberTable
  #48 = Utf8               LocalVariableTable
  #49 = Utf8               Signature
  #50 = Utf8               InnerClasses
  #51 = Utf8               SourceFile
  #52 = Utf8               ScalaInlineInfo
  #53 = Utf8               Scala
{
  public static final scala.collection.parallel.mutable.ParSeq$ MODULE$;
    descriptor: Lscala/collection/parallel/mutable/ParSeq$;
    flags: (0x0019) ACC_PUBLIC, ACC_STATIC, ACC_FINAL

  public static {};
    descriptor: ()V
    flags: (0x0009) ACC_PUBLIC, ACC_STATIC
    Code:
      stack=2, locals=0, args_size=0
         0: new           #2                  // class scala/collection/parallel/mutable/ParSeq$
         3: dup
         4: invokespecial #16                 // Method "<init>":()V
         7: putstatic     #18                 // Field MODULE$:Lscala/collection/parallel/mutable/ParSeq$;
        10: return
      LineNumberTable:
        line 48: 0

  public <S extends java.lang.Object, T extends java.lang.Object> scala.collection.generic.CanCombineFrom<scala.collection.parallel.mutable.ParSeq<S>, T, scala.collection.parallel.mutable.ParSeq<T>> canBuildFrom();
    descriptor: ()Lscala/collection/generic/CanCombineFrom;
    flags: (0x0001) ACC_PUBLIC
    Code:
      stack=3, locals=1, args_size=1
         0: new           #8                  // class scala/collection/generic/ParFactory$GenericCanCombineFrom
         3: dup
         4: aload_0
         5: invokespecial #24                 // Method scala/collection/generic/ParFactory$GenericCanCombineFrom."<init>":(Lscala/collection/generic/ParFactory;)V
         8: areturn
      LineNumberTable:
        line 49: 0
      LocalVariableTable:
        Start  Length  Slot  Name   Signature
            0       9     0  this   Lscala/collection/parallel/mutable/ParSeq$;
    Signature: #21                          // <S:Ljava/lang/Object;T:Ljava/lang/Object;>()Lscala/collection/generic/CanCombineFrom<Lscala/collection/parallel/mutable/ParSeq<TS;>;TT;Lscala/collection/parallel/mutable/ParSeq<TT;>;>;

  public <T extends java.lang.Object> scala.collection.parallel.Combiner<T, scala.collection.parallel.mutable.ParSeq<T>> newBuilder();
    descriptor: ()Lscala/collection/parallel/Combiner;
    flags: (0x0001) ACC_PUBLIC
    Code:
      stack=1, locals=1, args_size=1
         0: getstatic     #33                 // Field scala/collection/parallel/mutable/package$.MODULE$:Lscala/collection/parallel/mutable/package$;
         3: invokevirtual #37                 // Method scala/collection/parallel/mutable/package$.ParArrayCombiner:()Lscala/collection/parallel/mutable/ResizableParArrayCombiner$;
         6: invokevirtual #43                 // Method scala/collection/parallel/mutable/ResizableParArrayCombiner$.apply:()Lscala/collection/parallel/mutable/ResizableParArrayCombiner;
         9: areturn
      LineNumberTable:
        line 51: 0
      LocalVariableTable:
        Start  Length  Slot  Name   Signature
            0      10     0  this   Lscala/collection/parallel/mutable/ParSeq$;
    Signature: #28                          // <T:Ljava/lang/Object;>()Lscala/collection/parallel/Combiner<TT;Lscala/collection/parallel/mutable/ParSeq<TT;>;>;

  public <T extends java.lang.Object> scala.collection.parallel.Combiner<T, scala.collection.parallel.mutable.ParSeq<T>> newCombiner();
    descriptor: ()Lscala/collection/parallel/Combiner;
    flags: (0x0001) ACC_PUBLIC
    Code:
      stack=1, locals=1, args_size=1
         0: getstatic     #33                 // Field scala/collection/parallel/mutable/package$.MODULE$:Lscala/collection/parallel/mutable/package$;
         3: invokevirtual #37                 // Method scala/collection/parallel/mutable/package$.ParArrayCombiner:()Lscala/collection/parallel/mutable/ResizableParArrayCombiner$;
         6: invokevirtual #43                 // Method scala/collection/parallel/mutable/ResizableParArrayCombiner$.apply:()Lscala/collection/parallel/mutable/ResizableParArrayCombiner;
         9: areturn
      LineNumberTable:
        line 53: 0
      LocalVariableTable:
        Start  Length  Slot  Name   Signature
            0      10     0  this   Lscala/collection/parallel/mutable/ParSeq$;
    Signature: #28                          // <T:Ljava/lang/Object;>()Lscala/collection/parallel/Combiner<TT;Lscala/collection/parallel/mutable/ParSeq<TT;>;>;

  private scala.collection.parallel.mutable.ParSeq$();
    descriptor: ()V
    flags: (0x0002) ACC_PRIVATE
    Code:
      stack=1, locals=1, args_size=1
         0: aload_0
         1: invokespecial #45                 // Method scala/collection/generic/ParFactory."<init>":()V
         4: return
      LineNumberTable:
        line 48: 0
      LocalVariableTable:
        Start  Length  Slot  Name   Signature
            0       5     0  this   Lscala/collection/parallel/mutable/ParSeq$;
}
InnerClasses:
  public #9= #8 of #5;                    // GenericCanCombineFrom=class scala/collection/generic/ParFactory$GenericCanCombineFrom of class scala/collection/generic/ParFactory
Signature: #3                           // Lscala/collection/generic/ParFactory<Lscala/collection/parallel/mutable/ParSeq;>;
SourceFile: "ParSeq.scala"
  ScalaInlineInfo: length = 0x18 (unknown attribute)
   01 01 00 04 00 0E 00 0D 01 00 13 00 14 01 00 1A
   00 1B 01 00 2C 00 1B 01
  Scala: length = 0x0 (unknown attribute)

