Classfile /Users/mw/Projects/slang-braindump/.jar/jar8/assemble/slang-braindump/assemble/content/scala/collection/parallel/mutable/SizeMapUtils.class
  Last modified May 29, 2022; size 2009 bytes
  SHA-256 checksum c00c6f9c1414639a333b6dfda90b114e98104edcf2675c9e5fa798d9ddda4f6f
  Compiled from "package.scala"
public interface scala.collection.parallel.mutable.SizeMapUtils
  minor version: 0
  major version: 52
  flags: (0x0601) ACC_PUBLIC, ACC_INTERFACE, ACC_ABSTRACT
  this_class: #2                          // scala/collection/parallel/mutable/SizeMapUtils
  super_class: #4                         // java/lang/Object
  interfaces: 0, fields: 0, methods: 5, attributes: 4
Constant pool:
   #1 = Utf8               scala/collection/parallel/mutable/SizeMapUtils
   #2 = Class              #1             // scala/collection/parallel/mutable/SizeMapUtils
   #3 = Utf8               java/lang/Object
   #4 = Class              #3             // java/lang/Object
   #5 = Utf8               package.scala
   #6 = Utf8               Lscala/reflect/ScalaSignature;
   #7 = Utf8               bytes
   #8 = Utf8               \u0006\u0005A2\u0001\"\u0002\u0004\u0011\u0002\u0007\u0005aA\u0004\u0005\u0006\'\u0001!\t!\u0006\u0005\u00063\u0001!\tB\u0007\u0005\u0006M\u00011\tb\n\u0005\u0006U\u00011\tb\u000b\u0002\r\'&TX-T1q+RLGn\u001d\u0006\u0003\u000f!\tq!\\;uC\ndWM\u0003\u0002\n\u0015\u0005A\u0001/\u0019:bY2,GN\u0003\u0002\f\u0019\u0005Q1m\u001c7mK\u000e$\u0018n\u001c8\u000b\u00035\tQa]2bY\u0006\u001c\"\u0001A\b\u0011\u0005A\tR\"\u0001\u0007\n\u0005Ia!AB!osJ+g-\u0001\u0004%S:LG\u000fJ\u0002\u0001)\u00051\u0002C\u0001\t\u0018\u0013\tABB\u0001\u0003V]&$\u0018\u0001D2bY\u000etU/\\#mK6\u001cH#B\u000e\u001fA\t\"\u0003C\u0001\t\u001d\u0013\tiBBA\u0002J]RDQa\b\u0002A\u0002m\tAA\u001a:p[\")\u0011E\u0001a\u00017\u0005)QO\u001c;jY\")1E\u0001a\u00017\u0005YA/\u00192mK2+gn\u001a;i\u0011\u0015)#\u00011\u0001\u001c\u0003E\u0019\u0018N_3NCB\u0014UoY6fiNK\'0Z\u0001\u000bG>,h\u000e^#mK6\u001cHcA\u000e)S!)qd\u0001a\u00017!)\u0011e\u0001a\u00017\u0005\u00012m\\;oi\n+8m[3u\'&TXm\u001d\u000b\u000471r\u0003\"B\u0017\u0005\u0001\u0004Y\u0012A\u00034s_6\u0014UoY6fi\")q\u0006\u0002a\u00017\u0005YQO\u001c;jY\n+8m[3u\u0001
   #9 = Utf8               calcNumElems$
  #10 = Utf8               (Lscala/collection/parallel/mutable/SizeMapUtils;IIII)I
  #11 = Utf8               $this
  #12 = Utf8               from
  #13 = Utf8               until
  #14 = Utf8               tableLength
  #15 = Utf8               sizeMapBucketSize
  #16 = Utf8               calcNumElems
  #17 = Utf8               (IIII)I
  #18 = NameAndType        #16:#17        // calcNumElems:(IIII)I
  #19 = InterfaceMethodref #2.#18         // scala/collection/parallel/mutable/SizeMapUtils.calcNumElems:(IIII)I
  #20 = Utf8               Lscala/collection/parallel/mutable/SizeMapUtils;
  #21 = Utf8               I
  #22 = Utf8               countElems
  #23 = Utf8               (II)I
  #24 = NameAndType        #22:#23        // countElems:(II)I
  #25 = InterfaceMethodref #2.#24         // scala/collection/parallel/mutable/SizeMapUtils.countElems:(II)I
  #26 = Utf8               scala/runtime/RichInt$
  #27 = Class              #26            // scala/runtime/RichInt$
  #28 = Utf8               MODULE$
  #29 = Utf8               Lscala/runtime/RichInt$;
  #30 = NameAndType        #28:#29        // MODULE$:Lscala/runtime/RichInt$;
  #31 = Fieldref           #27.#30        // scala/runtime/RichInt$.MODULE$:Lscala/runtime/RichInt$;
  #32 = Utf8               scala/Predef$
  #33 = Class              #32            // scala/Predef$
  #34 = Utf8               Lscala/Predef$;
  #35 = NameAndType        #28:#34        // MODULE$:Lscala/Predef$;
  #36 = Fieldref           #33.#35        // scala/Predef$.MODULE$:Lscala/Predef$;
  #37 = Utf8               intWrapper
  #38 = Utf8               (I)I
  #39 = NameAndType        #37:#38        // intWrapper:(I)I
  #40 = Methodref          #33.#39        // scala/Predef$.intWrapper:(I)I
  #41 = Utf8               min$extension
  #42 = NameAndType        #41:#23        // min$extension:(II)I
  #43 = Methodref          #27.#42        // scala/runtime/RichInt$.min$extension:(II)I
  #44 = Utf8               countBucketSizes
  #45 = NameAndType        #44:#23        // countBucketSizes:(II)I
  #46 = InterfaceMethodref #2.#45         // scala/collection/parallel/mutable/SizeMapUtils.countBucketSizes:(II)I
  #47 = Utf8               fbuntil
  #48 = Utf8               fbcount
  #49 = Utf8               lbstart
  #50 = Utf8               lbcount
  #51 = Utf8               inbetween
  #52 = Utf8               fbindex
  #53 = Utf8               lbindex
  #54 = Utf8               this
  #55 = Utf8               fromBucket
  #56 = Utf8               untilBucket
  #57 = Utf8               $init$
  #58 = Utf8               (Lscala/collection/parallel/mutable/SizeMapUtils;)V
  #59 = Utf8               Code
  #60 = Utf8               LineNumberTable
  #61 = Utf8               LocalVariableTable
  #62 = Utf8               MethodParameters
  #63 = Utf8               StackMapTable
  #64 = Utf8               SourceFile
  #65 = Utf8               RuntimeVisibleAnnotations
  #66 = Utf8               ScalaInlineInfo
  #67 = Utf8               ScalaSig
{
  public static int calcNumElems$(scala.collection.parallel.mutable.SizeMapUtils, int, int, int, int);
    descriptor: (Lscala/collection/parallel/mutable/SizeMapUtils;IIII)I
    flags: (0x1009) ACC_PUBLIC, ACC_STATIC, ACC_SYNTHETIC
    Code:
      stack=5, locals=5, args_size=5
         0: aload_0
         1: iload_1
         2: iload_2
         3: iload_3
         4: iload         4
         6: invokespecial #19                 // InterfaceMethod calcNumElems:(IIII)I
         9: ireturn
      LineNumberTable:
        line 29: 0
      LocalVariableTable:
        Start  Length  Slot  Name   Signature
            0      10     0 $this   Lscala/collection/parallel/mutable/SizeMapUtils;
            0      10     1  from   I
            0      10     2 until   I
            0      10     3 tableLength   I
            0      10     4 sizeMapBucketSize   I
    MethodParameters:
      Name                           Flags
      $this                          final synthetic
      from                           final
      until                          final
      tableLength                    final
      sizeMapBucketSize              final

  public default int calcNumElems(int, int, int, int);
    descriptor: (IIII)I
    flags: (0x0001) ACC_PUBLIC
    Code:
      stack=4, locals=12, args_size=5
         0: iload_1
         1: iload         4
         3: idiv
         4: istore        5
         6: iload_2
         7: iload         4
         9: idiv
        10: istore        6
        12: iload         5
        14: iload         6
        16: if_icmpne     30
        19: aload_0
        20: iload_1
        21: iload_2
        22: invokeinterface #25,  3           // InterfaceMethod countElems:(II)I
        27: goto          103
        30: getstatic     #31                 // Field scala/runtime/RichInt$.MODULE$:Lscala/runtime/RichInt$;
        33: getstatic     #36                 // Field scala/Predef$.MODULE$:Lscala/Predef$;
        36: iload         5
        38: iconst_1
        39: iadd
        40: iload         4
        42: imul
        43: invokevirtual #40                 // Method scala/Predef$.intWrapper:(I)I
        46: iload_3
        47: invokevirtual #43                 // Method scala/runtime/RichInt$.min$extension:(II)I
        50: istore        7
        52: aload_0
        53: iload_1
        54: iload         7
        56: invokeinterface #25,  3           // InterfaceMethod countElems:(II)I
        61: istore        8
        63: iload         6
        65: iload         4
        67: imul
        68: istore        9
        70: aload_0
        71: iload         9
        73: iload_2
        74: invokeinterface #25,  3           // InterfaceMethod countElems:(II)I
        79: istore        10
        81: aload_0
        82: iload         5
        84: iconst_1
        85: iadd
        86: iload         6
        88: invokeinterface #46,  3           // InterfaceMethod countBucketSizes:(II)I
        93: istore        11
        95: iload         8
        97: iload         11
        99: iadd
       100: iload         10
       102: iadd
       103: ireturn
      StackMapTable: number_of_entries = 2
        frame_type = 253 /* append */
          offset_delta = 30
          locals = [ int, int ]
        frame_type = 247 /* same_locals_1_stack_item_frame_extended */
          offset_delta = 72
          stack = [ int ]
      LineNumberTable:
        line 31: 0
        line 34: 6
        line 38: 12
        line 41: 19
        line 44: 30
        line 45: 52
        line 46: 63
        line 47: 70
        line 50: 81
        line 53: 95
      LocalVariableTable:
        Start  Length  Slot  Name   Signature
           52      51     7 fbuntil   I
           63      40     8 fbcount   I
           70      33     9 lbstart   I
           81      22    10 lbcount   I
           95       8    11 inbetween   I
            6      97     5 fbindex   I
           12      91     6 lbindex   I
            0     104     0  this   Lscala/collection/parallel/mutable/SizeMapUtils;
            0     104     1  from   I
            0     104     2 until   I
            0     104     3 tableLength   I
            0     104     4 sizeMapBucketSize   I
    MethodParameters:
      Name                           Flags
      from                           final
      until                          final
      tableLength                    final
      sizeMapBucketSize              final

  public abstract int countElems(int, int);
    descriptor: (II)I
    flags: (0x0401) ACC_PUBLIC, ACC_ABSTRACT
    MethodParameters:
      Name                           Flags
      from                           final
      until                          final

  public abstract int countBucketSizes(int, int);
    descriptor: (II)I
    flags: (0x0401) ACC_PUBLIC, ACC_ABSTRACT
    MethodParameters:
      Name                           Flags
      fromBucket                     final
      untilBucket                    final

  public static void $init$(scala.collection.parallel.mutable.SizeMapUtils);
    descriptor: (Lscala/collection/parallel/mutable/SizeMapUtils;)V
    flags: (0x0009) ACC_PUBLIC, ACC_STATIC
    Code:
      stack=0, locals=1, args_size=1
         0: return
      LineNumberTable:
        line 27: 0
      LocalVariableTable:
        Start  Length  Slot  Name   Signature
            0       1     0 $this   Lscala/collection/parallel/mutable/SizeMapUtils;
    MethodParameters:
      Name                           Flags
      $this                          final synthetic
}
SourceFile: "package.scala"
RuntimeVisibleAnnotations:
  0: #6(#7=s#8)
    scala.reflect.ScalaSignature(
      bytes="\u0006\u0005A2\u0001\"\u0002\u0004\u0011\u0002\u0007\u0005aA\u0004\u0005\u0006\'\u0001!\t!\u0006\u0005\u00063\u0001!\tB\u0007\u0005\u0006M\u00011\tb\n\u0005\u0006U\u00011\tb\u000b\u0002\r\'&TX-T1q+RLGn\u001d\u0006\u0003\u000f!\tq!\\;uC\ndWM\u0003\u0002\n\u0015\u0005A\u0001/\u0019:bY2,GN\u0003\u0002\f\u0019\u0005Q1m\u001c7mK\u000e$\u0018n\u001c8\u000b\u00035\tQa]2bY\u0006\u001c\"\u0001A\b\u0011\u0005A\tR\"\u0001\u0007\n\u0005Ia!AB!osJ+g-\u0001\u0004%S:LG\u000fJ\u0002\u0001)\u00051\u0002C\u0001\t\u0018\u0013\tABB\u0001\u0003V]&$\u0018\u0001D2bY\u000etU/\\#mK6\u001cH#B\u000e\u001fA\t\"\u0003C\u0001\t\u001d\u0013\tiBBA\u0002J]RDQa\b\u0002A\u0002m\tAA\u001a:p[\")\u0011E\u0001a\u00017\u0005)QO\u001c;jY\")1E\u0001a\u00017\u0005YA/\u00192mK2+gn\u001a;i\u0011\u0015)#\u00011\u0001\u001c\u0003E\u0019\u0018N_3NCB\u0014UoY6fiNK\'0Z\u0001\u000bG>,h\u000e^#mK6\u001cHcA\u000e)S!)qd\u0001a\u00017!)\u0011e\u0001a\u00017\u0005\u00012m\\;oi\n+8m[3u\'&TXm\u001d\u000b\u000471r\u0003\"B\u0017\u0005\u0001\u0004Y\u0012A\u00034s_6\u0014UoY6fi\")q\u0006\u0002a\u00017\u0005YQO\u001c;jY\n+8m[3u\u0001"
    )
  ScalaInlineInfo: length = 0x1D (unknown attribute)
   01 00 00 05 00 39 00 3A 01 00 10 00 11 00 00 09
   00 0A 01 00 2C 00 17 00 00 16 00 17 00
  ScalaSig: length = 0x3 (unknown attribute)
   05 02 00
