Classfile /Users/mw/Projects/slang-braindump/.jar/jar8/assemble/slang-braindump/assemble/content/com/zaxxer/nuprocess/linux/LibEpoll.class
  Last modified May 29, 2022; size 1011 bytes
  SHA-256 checksum 6036500e7cf8064314ebfc5733f94df70f9786127722188f2c0ab23b03081f8b
  Compiled from "LibEpoll.java"
public class com.zaxxer.nuprocess.linux.LibEpoll
  minor version: 0
  major version: 51
  flags: (0x0021) ACC_PUBLIC, ACC_SUPER
  this_class: #4                          // com/zaxxer/nuprocess/linux/LibEpoll
  super_class: #5                         // java/lang/Object
  interfaces: 0, fields: 10, methods: 6, attributes: 1
Constant pool:
   #1 = Methodref          #5.#44         // java/lang/Object."<init>":()V
   #2 = Fieldref           #45.#46        // com/sun/jna/Platform.C_LIBRARY_NAME:Ljava/lang/String;
   #3 = Methodref          #47.#48        // com/sun/jna/Native.register:(Ljava/lang/String;)V
   #4 = Class              #49            // com/zaxxer/nuprocess/linux/LibEpoll
   #5 = Class              #50            // java/lang/Object
   #6 = Utf8               SIGPIPE
   #7 = Utf8               I
   #8 = Utf8               ConstantValue
   #9 = Integer            13
  #10 = Utf8               EPOLL_CTL_ADD
  #11 = Integer            1
  #12 = Utf8               EPOLL_CTL_DEL
  #13 = Integer            2
  #14 = Utf8               EPOLL_CTL_MOD
  #15 = Integer            3
  #16 = Utf8               EPOLLIN
  #17 = Utf8               EPOLLOUT
  #18 = Integer            4
  #19 = Utf8               EPOLLERR
  #20 = Integer            8
  #21 = Utf8               EPOLLHUP
  #22 = Integer            16
  #23 = Utf8               EPOLLRDHUP
  #24 = Integer            8192
  #25 = Utf8               EPOLLONESHOT
  #26 = Integer            1073741824
  #27 = Utf8               <init>
  #28 = Utf8               ()V
  #29 = Utf8               Code
  #30 = Utf8               LineNumberTable
  #31 = Utf8               LocalVariableTable
  #32 = Utf8               this
  #33 = Utf8               Lcom/zaxxer/nuprocess/linux/LibEpoll;
  #34 = Utf8               sigignore
  #35 = Utf8               (I)I
  #36 = Utf8               epoll_create
  #37 = Utf8               epoll_ctl
  #38 = Utf8               (IIILcom/sun/jna/Pointer;)I
  #39 = Utf8               epoll_wait
  #40 = Utf8               (ILcom/sun/jna/Pointer;II)I
  #41 = Utf8               <clinit>
  #42 = Utf8               SourceFile
  #43 = Utf8               LibEpoll.java
  #44 = NameAndType        #27:#28        // "<init>":()V
  #45 = Class              #51            // com/sun/jna/Platform
  #46 = NameAndType        #52:#53        // C_LIBRARY_NAME:Ljava/lang/String;
  #47 = Class              #54            // com/sun/jna/Native
  #48 = NameAndType        #55:#56        // register:(Ljava/lang/String;)V
  #49 = Utf8               com/zaxxer/nuprocess/linux/LibEpoll
  #50 = Utf8               java/lang/Object
  #51 = Utf8               com/sun/jna/Platform
  #52 = Utf8               C_LIBRARY_NAME
  #53 = Utf8               Ljava/lang/String;
  #54 = Utf8               com/sun/jna/Native
  #55 = Utf8               register
  #56 = Utf8               (Ljava/lang/String;)V
{
  public static final int SIGPIPE;
    descriptor: I
    flags: (0x0019) ACC_PUBLIC, ACC_STATIC, ACC_FINAL
    ConstantValue: int 13

  public static final int EPOLL_CTL_ADD;
    descriptor: I
    flags: (0x0019) ACC_PUBLIC, ACC_STATIC, ACC_FINAL
    ConstantValue: int 1

  public static final int EPOLL_CTL_DEL;
    descriptor: I
    flags: (0x0019) ACC_PUBLIC, ACC_STATIC, ACC_FINAL
    ConstantValue: int 2

  public static final int EPOLL_CTL_MOD;
    descriptor: I
    flags: (0x0019) ACC_PUBLIC, ACC_STATIC, ACC_FINAL
    ConstantValue: int 3

  public static final int EPOLLIN;
    descriptor: I
    flags: (0x0019) ACC_PUBLIC, ACC_STATIC, ACC_FINAL
    ConstantValue: int 1

  public static final int EPOLLOUT;
    descriptor: I
    flags: (0x0019) ACC_PUBLIC, ACC_STATIC, ACC_FINAL
    ConstantValue: int 4

  public static final int EPOLLERR;
    descriptor: I
    flags: (0x0019) ACC_PUBLIC, ACC_STATIC, ACC_FINAL
    ConstantValue: int 8

  public static final int EPOLLHUP;
    descriptor: I
    flags: (0x0019) ACC_PUBLIC, ACC_STATIC, ACC_FINAL
    ConstantValue: int 16

  public static final int EPOLLRDHUP;
    descriptor: I
    flags: (0x0019) ACC_PUBLIC, ACC_STATIC, ACC_FINAL
    ConstantValue: int 8192

  public static final int EPOLLONESHOT;
    descriptor: I
    flags: (0x0019) ACC_PUBLIC, ACC_STATIC, ACC_FINAL
    ConstantValue: int 1073741824

  public com.zaxxer.nuprocess.linux.LibEpoll();
    descriptor: ()V
    flags: (0x0001) ACC_PUBLIC
    Code:
      stack=1, locals=1, args_size=1
         0: aload_0
         1: invokespecial #1                  // Method java/lang/Object."<init>":()V
         4: return
      LineNumberTable:
        line 26: 0
      LocalVariableTable:
        Start  Length  Slot  Name   Signature
            0       5     0  this   Lcom/zaxxer/nuprocess/linux/LibEpoll;

  public static native int sigignore(int);
    descriptor: (I)I
    flags: (0x0109) ACC_PUBLIC, ACC_STATIC, ACC_NATIVE

  public static native int epoll_create(int);
    descriptor: (I)I
    flags: (0x0109) ACC_PUBLIC, ACC_STATIC, ACC_NATIVE

  public static native int epoll_ctl(int, int, int, com.sun.jna.Pointer);
    descriptor: (IIILcom/sun/jna/Pointer;)I
    flags: (0x0109) ACC_PUBLIC, ACC_STATIC, ACC_NATIVE

  public static native int epoll_wait(int, com.sun.jna.Pointer, int, int);
    descriptor: (ILcom/sun/jna/Pointer;II)I
    flags: (0x0109) ACC_PUBLIC, ACC_STATIC, ACC_NATIVE

  static {};
    descriptor: ()V
    flags: (0x0008) ACC_STATIC
    Code:
      stack=1, locals=0, args_size=0
         0: getstatic     #2                  // Field com/sun/jna/Platform.C_LIBRARY_NAME:Ljava/lang/String;
         3: invokestatic  #3                  // Method com/sun/jna/Native.register:(Ljava/lang/String;)V
         6: return
      LineNumberTable:
        line 29: 0
        line 30: 6
}
SourceFile: "LibEpoll.java"
