Classfile /Users/mw/Projects/slang-braindump/.jar/jar8/assemble/slang-braindump/assemble/content/com/zaxxer/nuprocess/linux/LinuxProcess$LaunchMechanism.class
  Last modified May 29, 2022; size 1301 bytes
  SHA-256 checksum 5d1ddad10146a314267f2543bdfbc47df5127b9614a2339d4e0f902bb7617708
  Compiled from "LinuxProcess.java"
final class com.zaxxer.nuprocess.linux.LinuxProcess$LaunchMechanism extends java.lang.Enum<com.zaxxer.nuprocess.linux.LinuxProcess$LaunchMechanism>
  minor version: 0
  major version: 51
  flags: (0x4030) ACC_FINAL, ACC_SUPER, ACC_ENUM
  this_class: #4                          // com/zaxxer/nuprocess/linux/LinuxProcess$LaunchMechanism
  super_class: #14                        // java/lang/Enum
  interfaces: 0, fields: 4, methods: 4, attributes: 3
Constant pool:
   #1 = Fieldref           #4.#41         // com/zaxxer/nuprocess/linux/LinuxProcess$LaunchMechanism.$VALUES:[Lcom/zaxxer/nuprocess/linux/LinuxProcess$LaunchMechanism;
   #2 = Methodref          #42.#43        // "[Lcom/zaxxer/nuprocess/linux/LinuxProcess$LaunchMechanism;".clone:()Ljava/lang/Object;
   #3 = Class              #22            // "[Lcom/zaxxer/nuprocess/linux/LinuxProcess$LaunchMechanism;"
   #4 = Class              #45            // com/zaxxer/nuprocess/linux/LinuxProcess$LaunchMechanism
   #5 = Methodref          #14.#46        // java/lang/Enum.valueOf:(Ljava/lang/Class;Ljava/lang/String;)Ljava/lang/Enum;
   #6 = Methodref          #14.#47        // java/lang/Enum."<init>":(Ljava/lang/String;I)V
   #7 = String             #15            // FORK
   #8 = Methodref          #4.#47         // com/zaxxer/nuprocess/linux/LinuxProcess$LaunchMechanism."<init>":(Ljava/lang/String;I)V
   #9 = Fieldref           #4.#48         // com/zaxxer/nuprocess/linux/LinuxProcess$LaunchMechanism.FORK:Lcom/zaxxer/nuprocess/linux/LinuxProcess$LaunchMechanism;
  #10 = String             #19            // POSIX_SPAWN
  #11 = Fieldref           #4.#49         // com/zaxxer/nuprocess/linux/LinuxProcess$LaunchMechanism.POSIX_SPAWN:Lcom/zaxxer/nuprocess/linux/LinuxProcess$LaunchMechanism;
  #12 = String             #20            // VFORK
  #13 = Fieldref           #4.#50         // com/zaxxer/nuprocess/linux/LinuxProcess$LaunchMechanism.VFORK:Lcom/zaxxer/nuprocess/linux/LinuxProcess$LaunchMechanism;
  #14 = Class              #51            // java/lang/Enum
  #15 = Utf8               FORK
  #16 = Utf8               LaunchMechanism
  #17 = Utf8               InnerClasses
  #18 = Utf8               Lcom/zaxxer/nuprocess/linux/LinuxProcess$LaunchMechanism;
  #19 = Utf8               POSIX_SPAWN
  #20 = Utf8               VFORK
  #21 = Utf8               $VALUES
  #22 = Utf8               [Lcom/zaxxer/nuprocess/linux/LinuxProcess$LaunchMechanism;
  #23 = Utf8               values
  #24 = Utf8               ()[Lcom/zaxxer/nuprocess/linux/LinuxProcess$LaunchMechanism;
  #25 = Utf8               Code
  #26 = Utf8               LineNumberTable
  #27 = Utf8               valueOf
  #28 = Utf8               (Ljava/lang/String;)Lcom/zaxxer/nuprocess/linux/LinuxProcess$LaunchMechanism;
  #29 = Utf8               LocalVariableTable
  #30 = Utf8               name
  #31 = Utf8               Ljava/lang/String;
  #32 = Utf8               <init>
  #33 = Utf8               (Ljava/lang/String;I)V
  #34 = Utf8               this
  #35 = Utf8               Signature
  #36 = Utf8               ()V
  #37 = Utf8               <clinit>
  #38 = Utf8               Ljava/lang/Enum<Lcom/zaxxer/nuprocess/linux/LinuxProcess$LaunchMechanism;>;
  #39 = Utf8               SourceFile
  #40 = Utf8               LinuxProcess.java
  #41 = NameAndType        #21:#22        // $VALUES:[Lcom/zaxxer/nuprocess/linux/LinuxProcess$LaunchMechanism;
  #42 = Class              #22            // "[Lcom/zaxxer/nuprocess/linux/LinuxProcess$LaunchMechanism;"
  #43 = NameAndType        #52:#53        // clone:()Ljava/lang/Object;
  #44 = Class              #54            // com/zaxxer/nuprocess/linux/LinuxProcess
  #45 = Utf8               com/zaxxer/nuprocess/linux/LinuxProcess$LaunchMechanism
  #46 = NameAndType        #27:#55        // valueOf:(Ljava/lang/Class;Ljava/lang/String;)Ljava/lang/Enum;
  #47 = NameAndType        #32:#33        // "<init>":(Ljava/lang/String;I)V
  #48 = NameAndType        #15:#18        // FORK:Lcom/zaxxer/nuprocess/linux/LinuxProcess$LaunchMechanism;
  #49 = NameAndType        #19:#18        // POSIX_SPAWN:Lcom/zaxxer/nuprocess/linux/LinuxProcess$LaunchMechanism;
  #50 = NameAndType        #20:#18        // VFORK:Lcom/zaxxer/nuprocess/linux/LinuxProcess$LaunchMechanism;
  #51 = Utf8               java/lang/Enum
  #52 = Utf8               clone
  #53 = Utf8               ()Ljava/lang/Object;
  #54 = Utf8               com/zaxxer/nuprocess/linux/LinuxProcess
  #55 = Utf8               (Ljava/lang/Class;Ljava/lang/String;)Ljava/lang/Enum;
{
  public static final com.zaxxer.nuprocess.linux.LinuxProcess$LaunchMechanism FORK;
    descriptor: Lcom/zaxxer/nuprocess/linux/LinuxProcess$LaunchMechanism;
    flags: (0x4019) ACC_PUBLIC, ACC_STATIC, ACC_FINAL, ACC_ENUM

  public static final com.zaxxer.nuprocess.linux.LinuxProcess$LaunchMechanism POSIX_SPAWN;
    descriptor: Lcom/zaxxer/nuprocess/linux/LinuxProcess$LaunchMechanism;
    flags: (0x4019) ACC_PUBLIC, ACC_STATIC, ACC_FINAL, ACC_ENUM

  public static final com.zaxxer.nuprocess.linux.LinuxProcess$LaunchMechanism VFORK;
    descriptor: Lcom/zaxxer/nuprocess/linux/LinuxProcess$LaunchMechanism;
    flags: (0x4019) ACC_PUBLIC, ACC_STATIC, ACC_FINAL, ACC_ENUM

  private static final com.zaxxer.nuprocess.linux.LinuxProcess$LaunchMechanism[] $VALUES;
    descriptor: [Lcom/zaxxer/nuprocess/linux/LinuxProcess$LaunchMechanism;
    flags: (0x101a) ACC_PRIVATE, ACC_STATIC, ACC_FINAL, ACC_SYNTHETIC

  public static com.zaxxer.nuprocess.linux.LinuxProcess$LaunchMechanism[] values();
    descriptor: ()[Lcom/zaxxer/nuprocess/linux/LinuxProcess$LaunchMechanism;
    flags: (0x0009) ACC_PUBLIC, ACC_STATIC
    Code:
      stack=1, locals=0, args_size=0
         0: getstatic     #1                  // Field $VALUES:[Lcom/zaxxer/nuprocess/linux/LinuxProcess$LaunchMechanism;
         3: invokevirtual #2                  // Method "[Lcom/zaxxer/nuprocess/linux/LinuxProcess$LaunchMechanism;".clone:()Ljava/lang/Object;
         6: checkcast     #3                  // class "[Lcom/zaxxer/nuprocess/linux/LinuxProcess$LaunchMechanism;"
         9: areturn
      LineNumberTable:
        line 48: 0

  public static com.zaxxer.nuprocess.linux.LinuxProcess$LaunchMechanism valueOf(java.lang.String);
    descriptor: (Ljava/lang/String;)Lcom/zaxxer/nuprocess/linux/LinuxProcess$LaunchMechanism;
    flags: (0x0009) ACC_PUBLIC, ACC_STATIC
    Code:
      stack=2, locals=1, args_size=1
         0: ldc           #4                  // class com/zaxxer/nuprocess/linux/LinuxProcess$LaunchMechanism
         2: aload_0
         3: invokestatic  #5                  // Method java/lang/Enum.valueOf:(Ljava/lang/Class;Ljava/lang/String;)Ljava/lang/Enum;
         6: checkcast     #4                  // class com/zaxxer/nuprocess/linux/LinuxProcess$LaunchMechanism
         9: areturn
      LineNumberTable:
        line 48: 0
      LocalVariableTable:
        Start  Length  Slot  Name   Signature
            0      10     0  name   Ljava/lang/String;

  private com.zaxxer.nuprocess.linux.LinuxProcess$LaunchMechanism();
    descriptor: (Ljava/lang/String;I)V
    flags: (0x0002) ACC_PRIVATE
    Code:
      stack=3, locals=3, args_size=3
         0: aload_0
         1: aload_1
         2: iload_2
         3: invokespecial #6                  // Method java/lang/Enum."<init>":(Ljava/lang/String;I)V
         6: return
      LineNumberTable:
        line 49: 0
      LocalVariableTable:
        Start  Length  Slot  Name   Signature
            0       7     0  this   Lcom/zaxxer/nuprocess/linux/LinuxProcess$LaunchMechanism;
    Signature: #36                          // ()V

  static {};
    descriptor: ()V
    flags: (0x0008) ACC_STATIC
    Code:
      stack=4, locals=0, args_size=0
         0: new           #4                  // class com/zaxxer/nuprocess/linux/LinuxProcess$LaunchMechanism
         3: dup
         4: ldc           #7                  // String FORK
         6: iconst_0
         7: invokespecial #8                  // Method "<init>":(Ljava/lang/String;I)V
        10: putstatic     #9                  // Field FORK:Lcom/zaxxer/nuprocess/linux/LinuxProcess$LaunchMechanism;
        13: new           #4                  // class com/zaxxer/nuprocess/linux/LinuxProcess$LaunchMechanism
        16: dup
        17: ldc           #10                 // String POSIX_SPAWN
        19: iconst_1
        20: invokespecial #8                  // Method "<init>":(Ljava/lang/String;I)V
        23: putstatic     #11                 // Field POSIX_SPAWN:Lcom/zaxxer/nuprocess/linux/LinuxProcess$LaunchMechanism;
        26: new           #4                  // class com/zaxxer/nuprocess/linux/LinuxProcess$LaunchMechanism
        29: dup
        30: ldc           #12                 // String VFORK
        32: iconst_2
        33: invokespecial #8                  // Method "<init>":(Ljava/lang/String;I)V
        36: putstatic     #13                 // Field VFORK:Lcom/zaxxer/nuprocess/linux/LinuxProcess$LaunchMechanism;
        39: iconst_3
        40: anewarray     #4                  // class com/zaxxer/nuprocess/linux/LinuxProcess$LaunchMechanism
        43: dup
        44: iconst_0
        45: getstatic     #9                  // Field FORK:Lcom/zaxxer/nuprocess/linux/LinuxProcess$LaunchMechanism;
        48: aastore
        49: dup
        50: iconst_1
        51: getstatic     #11                 // Field POSIX_SPAWN:Lcom/zaxxer/nuprocess/linux/LinuxProcess$LaunchMechanism;
        54: aastore
        55: dup
        56: iconst_2
        57: getstatic     #13                 // Field VFORK:Lcom/zaxxer/nuprocess/linux/LinuxProcess$LaunchMechanism;
        60: aastore
        61: putstatic     #1                  // Field $VALUES:[Lcom/zaxxer/nuprocess/linux/LinuxProcess$LaunchMechanism;
        64: return
      LineNumberTable:
        line 51: 0
        line 52: 13
        line 53: 26
        line 48: 39
}
Signature: #38                          // Ljava/lang/Enum<Lcom/zaxxer/nuprocess/linux/LinuxProcess$LaunchMechanism;>;
SourceFile: "LinuxProcess.java"
InnerClasses:
  private static final #16= #4 of #44;    // LaunchMechanism=class com/zaxxer/nuprocess/linux/LinuxProcess$LaunchMechanism of class com/zaxxer/nuprocess/linux/LinuxProcess
