Classfile /Users/mw/Projects/slang-braindump/.jar/jar11/assemble/slang-braindump/assemble/content/org/scalatest/tools/ArgsParser.class
  Last modified May 29, 2022; size 5670 bytes
  SHA-256 checksum 2b79ce0c9713a507a76b7e11f2a65662b1e9fa1d63d9e73953db9c3e79b902db
  Compiled from "ArgsParser.scala"
public final class org.scalatest.tools.ArgsParser
  minor version: 0
  major version: 52
  flags: (0x0031) ACC_PUBLIC, ACC_FINAL, ACC_SUPER
  this_class: #2                          // org/scalatest/tools/ArgsParser
  super_class: #4                         // java/lang/Object
  interfaces: 0, fields: 0, methods: 12, attributes: 3
Constant pool:
   #1 = Utf8               org/scalatest/tools/ArgsParser
   #2 = Class              #1             // org/scalatest/tools/ArgsParser
   #3 = Utf8               java/lang/Object
   #4 = Class              #3             // java/lang/Object
   #5 = Utf8               ArgsParser.scala
   #6 = Utf8               Lscala/reflect/ScalaSignature;
   #7 = Utf8               bytes
   #8 = Utf8               \u0006\u0005\u0005\rwA\u0002\u000f\u001e\u0011\u0003i2E\u0002\u0004&;!\u0005QD\n\u0005\u0006[\u0005!\ta\f\u0005\u0007a\u0005!\taH\u0019\t\r1\u000bA\u0011A\u0010N\u0011\u0019a\u0016\u0001\"\u0001 ;\")A-\u0001C\u0001K\"1\u0011/\u0001C\u0001?IDQa^\u0001\u0005\u0002aDq!a\u0002\u0002\t\u0003\tI\u0001C\u0004\u0002\u001c\u0005!\t!!\b\t\u0011\u0005\u001d\u0012\u0001\"\u0001 \u0003SAq!a\u0011\u0002\t\u0003\t)\u0005C\u0005\u0002J\u0005\u0011\r\u0011\"\u0003\u0002L!9\u0011QJ\u0001!\u0002\u00139\u0007bBA(\u0003\u0011%\u0011\u0011\u000b\u0005\n\u0003;\n!\u0019!C\u0005\u0003\u0017Bq!a\u0018\u0002A\u0003%q\rC\u0005\u0002b\u0005\u0011\r\u0011\"\u0003\u0002L!9\u00111M\u0001!\u0002\u00139\u0007bBA3\u0003\u0011%\u0011q\r\u0005\b\u0003[\nA\u0011AA8\u0011\u001d\tI(\u0001C\u0001\u0003wBq!a \u0002\t\u0003\t\t\tC\u0004\u0002\b\u0006!\t!!#\t\u000f\u0005M\u0015\u0001\"\u0001\u0002\u0016\"9\u0011QU\u0001\u0005\u0002\u0005\u001d\u0006bBA[\u0003\u0011\u0005\u0011qW\u0001\u000b\u0003J<7\u000fU1sg\u0016\u0014(B\u0001\u0010 \u0003\u0015!xn\u001c7t\u0015\t\u0001\u0013%A\u0005tG\u0006d\u0017\r^3ti*\t!%A\u0002pe\u001e\u0004\"\u0001J\u0001\u000e\u0003u\u0011!\"\u0011:hgB\u000b\'o]3s\'\t\tq\u0005\u0005\u0002)W5\t\u0011FC\u0001+\u0003\u0015\u00198-\u00197b\u0013\ta\u0013F\u0001\u0004B]f\u0014VMZ\u0001\u0007y%t\u0017\u000e\u001e \u0004\u0001Q\t1%\u0001\u000bdQ\u0016\u001c7.\u0011:hg\u001a{\'OV1mS\u0012LG/\u001f\u000b\u0003eu\u00022\u0001K\u001a6\u0013\t!\u0014F\u0001\u0004PaRLwN\u001c\t\u0003mmj\u0011a\u000e\u0006\u0003qe\nA\u0001\\1oO*\t!(\u0001\u0003kCZ\f\u0017B\u0001\u001f8\u0005\u0019\u0019FO]5oO\")ah\u0001a\u0001\u007f\u0005!\u0011M]4t!\rA\u0003IQ\u0005\u0003\u0003&\u0012Q!\u0011:sCf\u0004\"a\u0011&\u000f\u0005\u0011C\u0005CA#*\u001b\u00051%BA$/\u0003\u0019a$o\\8u}%\u0011\u0011*K\u0001\u0007!J,G-\u001a4\n\u0005qZ%BA%*\u0003U\u0001\u0018M]:f\u0007>t7-\u001e:sK:$8i\u001c8gS\u001e$\"AT)\u0011\u0005\u0011z\u0015B\u0001)\u001e\u0005A\u0019uN\\2veJ,g\u000e^\"p]\u001aLw\rC\u0003S\t\u0001\u00071+\u0001\bd_:\u001cWO\u001d:f]Rd\u0015n\u001d;\u0011\u0007QK&I\u0004\u0002V/:\u0011QIV\u0005\u0002U%\u0011\u0001,K\u0001\ba\u0006\u001c7.Y4f\u0013\tQ6L\u0001\u0003MSN$(B\u0001-*\u0003M\u0001\u0018M]:f\'2|w\u000f]8lK\u000e{gNZ5h)\tq&\rE\u0002)g}\u0003\"\u0001\n1\n\u0005\u0005l\"AD*m_^\u0004xn[3D_:4\u0017n\u001a\u0005\u0006G\u0016\u0001\raU\u0001\rg2|w\u000f]8lK\u0006\u0013xm]\u0001\u0013O\u0016t7+\u001e4gSb,7\u000fU1ui\u0016\u0014h\u000e\u0006\u0002g_B\u0019\u0001fM4\u0011\u0005!lW\"A5\u000b\u0005)\\\u0017!\u0002:fO\u0016D(B\u00017:\u0003\u0011)H/\u001b7\n\u00059L\'a\u0002)biR,\'O\u001c\u0005\u0006a\u001a\u0001\raU\u0001\rgV4g-\u001b=fg2K7\u000f^\u0001\na\u0006\u00148/Z!sON$\"a\u001d<\u0011\u0005\u0011\"\u0018BA;\u001e\u0005)\u0001\u0016M]:fI\u0006\u0013xm\u001d\u0005\u0006}\u001d\u0001\raP\u0001\u001ea\u0006\u00148/Z*vSR,\u0017I]4t\u0013:$xNT1nKN#(/\u001b8hgR)\u00110!\u0001\u0002\u0004A\u0019!p \"\u000e\u0003mT!\u0001`?\u0002\u0013%lW.\u001e;bE2,\'B\u0001@*\u0003)\u0019w\u000e\u001c7fGRLwN\\\u0005\u00035nDQA\u0010\u0005A\u0002MCa!!\u0002\t\u0001\u0004\u0011\u0015a\u00023bg\"\f%oZ\u0001\u000fa\u0006\u00148/Z\"p]\u001aLwmU3u)\u0011\tY!a\u0006\u0011\u000b\r\u000bi!!\u0005\n\u0007\u0005=1JA\u0002TKR\u00042\u0001JA\n\u0013\r\t)\"\b\u0002\u0014%\u0016\u0004xN\u001d;fe\u000e{gNZ5h!\u0006\u0014\u0018-\u001c\u0005\u0007\u00033I\u0001\u0019\u0001\"\u0002\u0017I,\u0007o\u001c:uKJ\f%oZ\u0001$a\u0006\u00148/\u001a*fa>\u0014H/\u001a:Be\u001e\u001c\u0018J\u001c;p\u0007>tg-[4ve\u0006$\u0018n\u001c8t)\u0011\ty\"!\n\u0011\u0007\u0011\n\t#C\u0002\u0002$u\u0011aCU3q_J$XM]\"p]\u001aLw-\u001e:bi&|gn\u001d\u0005\u0006})\u0001\raU\u0001\u000fa\u0006\u00148/Z*vSR,\u0017I]4t)\u0011\tY#!\u0011\u0011\u000f!\ni#!\r\u0002:%\u0019\u0011qF\u0015\u0003\rQ+\b\u000f\\33!\u0011!\u0016,a\r\u0011\u0007\u0011\n)$C\u0002\u00028u\u0011!bU;ji\u0016\u0004\u0016M]1n!\u0011!\u0016,a\u000f\u0011\u0007\u0011\ni$C\u0002\u0002@u\u0011\u0001\u0002V3tiN\u0003Xm\u0019\u0005\u0006}-\u0001\raU\u0001\u000fa\u0006\u00148/Z!hC&t\u0017I]4t)\r\u0019\u0016q\t\u0005\u0006}1\u0001\raU\u0001\u0011%>{Ek\u0018#J%~\u0003\u0016\t\u0016+F%:+\u0012aZ\u0001\u0012%>{Ek\u0018#J%~\u0003\u0016\t\u0016+F%:\u0003\u0013aD5t\u0007>l\u0007\u000f\\3uKR{7.\u001a8\u0015\t\u0005M\u0013\u0011\f\t\u0004Q\u0005U\u0013bAA,S\t9!i\\8mK\u0006t\u0007BBA.\u001f\u0001\u0007!)A\u0003u_.,g.A\nT)\u0006\u0013Fk\u0018+P\u0017\u0016su\fU!U)\u0016\u0013f*\u0001\u000bT)\u0006\u0013Fk\u0018+P\u0017\u0016su\fU!U)\u0016\u0013f\nI\u0001\u0013\rVcEj\u0018+P\u0017\u0016su\fU!U)\u0016\u0013f*A\nG+2cu\fV(L\u000b:{\u0006+\u0011+U\u000bJs\u0005%A\u0005ta2LG\u000fU1uQR\u00191+!\u001b\t\r\u0005-D\u00031\u0001C\u0003\u001d\u0001\u0018\r\u001e5Be\u001e\fq\u0003]1sg\u0016\u001cu.\u001c9pk:$\u0017I]4J]R|7+\u001a;\u0015\r\u0005E\u00141OA;!\u0011\u0019\u0015Q\u0002\"\t\u000by*\u0002\u0019A*\t\r\u0005]T\u00031\u0001C\u0003=)\u0007\u0010]3di\u0016$G)Y:i\u0003J<\u0017a\u00069beN,\'+\u001e8qCRD\u0017I]4J]R|G*[:u)\r\u0019\u0016Q\u0010\u0005\u0006}Y\u0001\raU\u0001\u0019a\u0006\u00148/Z\"p[B|WO\u001c3Be\u001eLe\u000e^8MSN$H#B*\u0002\u0004\u0006\u0015\u0005\"\u0002 \u0018\u0001\u0004\u0019\u0006BBA</\u0001\u0007!)A\u0012qCJ\u001cXm\u00115pg\u0016t7\u000b^=mKNLe\u000e^8DQ>\u001cXM\\*us2,7+\u001a;\u0015\r\u0005-\u0015qRAI!\u0011Q\u0018Q\u0012\"\n\u0007\u0005=1\u0010C\u0003?1\u0001\u00071\u000b\u0003\u0004\u0002\u0006a\u0001\rAQ\u0001\u0014a\u0006\u00148/\u001a#pk\ndW-\u0011:hk6,g\u000e\u001e\u000b\t\u0003/\u000bi*a(\u0002\"B\u0019\u0001&!\'\n\u0007\u0005m\u0015F\u0001\u0004E_V\u0014G.\u001a\u0005\u0006}e\u0001\ra\u0015\u0005\u0007\u0003\u000bI\u0002\u0019\u0001\"\t\u000f\u0005\r\u0016\u00041\u0001\u0002\u0018\u0006aA-\u001a4bk2$h+\u00197vK\u0006\t\u0002/\u0019:tK2{gnZ!sOVlWM\u001c;\u0015\r\u0005%\u0016\u0011WAZ!\u0011A3\'a+\u0011\u0007!\ni+C\u0002\u00020&\u0012A\u0001T8oO\")aH\u0007a\u0001\'\"1\u0011Q\u0001\u000eA\u0002\t\u000b!\u0004]1sg\u0016\u0004&o\u001c9feRLWm]!sONLe\u000e^8NCB$B!!/\u0002BB!\u00111XA_\u001b\u0005y\u0012bAA`?\tI1i\u001c8gS\u001el\u0015\r\u001d\u0005\u0006}m\u0001\ra\u0015
   #9 = Utf8               parsePropertiesArgsIntoMap
  #10 = Utf8               (Lscala/collection/immutable/List;)Lorg/scalatest/ConfigMap;
  #11 = Utf8               (Lscala/collection/immutable/List<Ljava/lang/String;>;)Lorg/scalatest/ConfigMap;
  #12 = Utf8               args
  #13 = Utf8               org/scalatest/tools/ArgsParser$
  #14 = Class              #13            // org/scalatest/tools/ArgsParser$
  #15 = Utf8               MODULE$
  #16 = Utf8               Lorg/scalatest/tools/ArgsParser$;
  #17 = NameAndType        #15:#16        // MODULE$:Lorg/scalatest/tools/ArgsParser$;
  #18 = Fieldref           #14.#17        // org/scalatest/tools/ArgsParser$.MODULE$:Lorg/scalatest/tools/ArgsParser$;
  #19 = NameAndType        #9:#10         // parsePropertiesArgsIntoMap:(Lscala/collection/immutable/List;)Lorg/scalatest/ConfigMap;
  #20 = Methodref          #14.#19        // org/scalatest/tools/ArgsParser$.parsePropertiesArgsIntoMap:(Lscala/collection/immutable/List;)Lorg/scalatest/ConfigMap;
  #21 = Utf8               Lscala/collection/immutable/List;
  #22 = Utf8               parseLongArgument
  #23 = Utf8               (Lscala/collection/immutable/List;Ljava/lang/String;)Lscala/Option;
  #24 = Utf8               (Lscala/collection/immutable/List<Ljava/lang/String;>;Ljava/lang/String;)Lscala/Option<Ljava/lang/Object;>;
  #25 = Utf8               dashArg
  #26 = NameAndType        #22:#23        // parseLongArgument:(Lscala/collection/immutable/List;Ljava/lang/String;)Lscala/Option;
  #27 = Methodref          #14.#26        // org/scalatest/tools/ArgsParser$.parseLongArgument:(Lscala/collection/immutable/List;Ljava/lang/String;)Lscala/Option;
  #28 = Utf8               Ljava/lang/String;
  #29 = Utf8               parseDoubleArgument
  #30 = Utf8               (Lscala/collection/immutable/List;Ljava/lang/String;D)D
  #31 = Utf8               (Lscala/collection/immutable/List<Ljava/lang/String;>;Ljava/lang/String;D)D
  #32 = Utf8               defaultValue
  #33 = NameAndType        #29:#30        // parseDoubleArgument:(Lscala/collection/immutable/List;Ljava/lang/String;D)D
  #34 = Methodref          #14.#33        // org/scalatest/tools/ArgsParser$.parseDoubleArgument:(Lscala/collection/immutable/List;Ljava/lang/String;D)D
  #35 = Utf8               D
  #36 = Utf8               parseChosenStylesIntoChosenStyleSet
  #37 = Utf8               (Lscala/collection/immutable/List;Ljava/lang/String;)Lscala/collection/immutable/Set;
  #38 = Utf8               (Lscala/collection/immutable/List<Ljava/lang/String;>;Ljava/lang/String;)Lscala/collection/immutable/Set<Ljava/lang/String;>;
  #39 = NameAndType        #36:#37        // parseChosenStylesIntoChosenStyleSet:(Lscala/collection/immutable/List;Ljava/lang/String;)Lscala/collection/immutable/Set;
  #40 = Methodref          #14.#39        // org/scalatest/tools/ArgsParser$.parseChosenStylesIntoChosenStyleSet:(Lscala/collection/immutable/List;Ljava/lang/String;)Lscala/collection/immutable/Set;
  #41 = Utf8               parseCompoundArgIntoList
  #42 = Utf8               (Lscala/collection/immutable/List;Ljava/lang/String;)Lscala/collection/immutable/List;
  #43 = Utf8               (Lscala/collection/immutable/List<Ljava/lang/String;>;Ljava/lang/String;)Lscala/collection/immutable/List<Ljava/lang/String;>;
  #44 = Utf8               expectedDashArg
  #45 = NameAndType        #41:#42        // parseCompoundArgIntoList:(Lscala/collection/immutable/List;Ljava/lang/String;)Lscala/collection/immutable/List;
  #46 = Methodref          #14.#45        // org/scalatest/tools/ArgsParser$.parseCompoundArgIntoList:(Lscala/collection/immutable/List;Ljava/lang/String;)Lscala/collection/immutable/List;
  #47 = Utf8               parseRunpathArgIntoList
  #48 = Utf8               (Lscala/collection/immutable/List;)Lscala/collection/immutable/List;
  #49 = Utf8               (Lscala/collection/immutable/List<Ljava/lang/String;>;)Lscala/collection/immutable/List<Ljava/lang/String;>;
  #50 = NameAndType        #47:#48        // parseRunpathArgIntoList:(Lscala/collection/immutable/List;)Lscala/collection/immutable/List;
  #51 = Methodref          #14.#50        // org/scalatest/tools/ArgsParser$.parseRunpathArgIntoList:(Lscala/collection/immutable/List;)Lscala/collection/immutable/List;
  #52 = Utf8               parseCompoundArgIntoSet
  #53 = NameAndType        #52:#37        // parseCompoundArgIntoSet:(Lscala/collection/immutable/List;Ljava/lang/String;)Lscala/collection/immutable/Set;
  #54 = Methodref          #14.#53        // org/scalatest/tools/ArgsParser$.parseCompoundArgIntoSet:(Lscala/collection/immutable/List;Ljava/lang/String;)Lscala/collection/immutable/Set;
  #55 = Utf8               parseAgainArgs
  #56 = NameAndType        #55:#48        // parseAgainArgs:(Lscala/collection/immutable/List;)Lscala/collection/immutable/List;
  #57 = Methodref          #14.#56        // org/scalatest/tools/ArgsParser$.parseAgainArgs:(Lscala/collection/immutable/List;)Lscala/collection/immutable/List;
  #58 = Utf8               parseReporterArgsIntoConfigurations
  #59 = Utf8               (Lscala/collection/immutable/List;)Lorg/scalatest/tools/ReporterConfigurations;
  #60 = Utf8               (Lscala/collection/immutable/List<Ljava/lang/String;>;)Lorg/scalatest/tools/ReporterConfigurations;
  #61 = NameAndType        #58:#59        // parseReporterArgsIntoConfigurations:(Lscala/collection/immutable/List;)Lorg/scalatest/tools/ReporterConfigurations;
  #62 = Methodref          #14.#61        // org/scalatest/tools/ArgsParser$.parseReporterArgsIntoConfigurations:(Lscala/collection/immutable/List;)Lorg/scalatest/tools/ReporterConfigurations;
  #63 = Utf8               parseConfigSet
  #64 = Utf8               (Ljava/lang/String;)Lscala/collection/immutable/Set;
  #65 = Utf8               (Ljava/lang/String;)Lscala/collection/immutable/Set<Lorg/scalatest/tools/ReporterConfigParam;>;
  #66 = Utf8               reporterArg
  #67 = NameAndType        #63:#64        // parseConfigSet:(Ljava/lang/String;)Lscala/collection/immutable/Set;
  #68 = Methodref          #14.#67        // org/scalatest/tools/ArgsParser$.parseConfigSet:(Ljava/lang/String;)Lscala/collection/immutable/Set;
  #69 = Utf8               parseSuiteArgsIntoNameStrings
  #70 = NameAndType        #69:#42        // parseSuiteArgsIntoNameStrings:(Lscala/collection/immutable/List;Ljava/lang/String;)Lscala/collection/immutable/List;
  #71 = Methodref          #14.#70        // org/scalatest/tools/ArgsParser$.parseSuiteArgsIntoNameStrings:(Lscala/collection/immutable/List;Ljava/lang/String;)Lscala/collection/immutable/List;
  #72 = Utf8               genSuffixesPattern
  #73 = Utf8               (Lscala/collection/immutable/List;)Lscala/Option;
  #74 = Utf8               (Lscala/collection/immutable/List<Ljava/lang/String;>;)Lscala/Option<Ljava/util/regex/Pattern;>;
  #75 = Utf8               suffixesList
  #76 = NameAndType        #72:#73        // genSuffixesPattern:(Lscala/collection/immutable/List;)Lscala/Option;
  #77 = Methodref          #14.#76        // org/scalatest/tools/ArgsParser$.genSuffixesPattern:(Lscala/collection/immutable/List;)Lscala/Option;
  #78 = Utf8               Code
  #79 = Utf8               LocalVariableTable
  #80 = Utf8               Signature
  #81 = Utf8               MethodParameters
  #82 = Utf8               SourceFile
  #83 = Utf8               RuntimeVisibleAnnotations
  #84 = Utf8               ScalaSig
{
  public static org.scalatest.ConfigMap parsePropertiesArgsIntoMap(scala.collection.immutable.List<java.lang.String>);
    descriptor: (Lscala/collection/immutable/List;)Lorg/scalatest/ConfigMap;
    flags: (0x0009) ACC_PUBLIC, ACC_STATIC
    Code:
      stack=2, locals=1, args_size=1
         0: getstatic     #18                 // Field org/scalatest/tools/ArgsParser$.MODULE$:Lorg/scalatest/tools/ArgsParser$;
         3: aload_0
         4: invokevirtual #20                 // Method org/scalatest/tools/ArgsParser$.parsePropertiesArgsIntoMap:(Lscala/collection/immutable/List;)Lorg/scalatest/ConfigMap;
         7: areturn
      LocalVariableTable:
        Start  Length  Slot  Name   Signature
            0       8     0  args   Lscala/collection/immutable/List;
    Signature: #11                          // (Lscala/collection/immutable/List<Ljava/lang/String;>;)Lorg/scalatest/ConfigMap;
    MethodParameters:
      Name                           Flags
      args                           final

  public static scala.Option<java.lang.Object> parseLongArgument(scala.collection.immutable.List<java.lang.String>, java.lang.String);
    descriptor: (Lscala/collection/immutable/List;Ljava/lang/String;)Lscala/Option;
    flags: (0x0009) ACC_PUBLIC, ACC_STATIC
    Code:
      stack=3, locals=2, args_size=2
         0: getstatic     #18                 // Field org/scalatest/tools/ArgsParser$.MODULE$:Lorg/scalatest/tools/ArgsParser$;
         3: aload_0
         4: aload_1
         5: invokevirtual #27                 // Method org/scalatest/tools/ArgsParser$.parseLongArgument:(Lscala/collection/immutable/List;Ljava/lang/String;)Lscala/Option;
         8: areturn
      LocalVariableTable:
        Start  Length  Slot  Name   Signature
            0       9     0  args   Lscala/collection/immutable/List;
            0       9     1 dashArg   Ljava/lang/String;
    Signature: #24                          // (Lscala/collection/immutable/List<Ljava/lang/String;>;Ljava/lang/String;)Lscala/Option<Ljava/lang/Object;>;
    MethodParameters:
      Name                           Flags
      args                           final
      dashArg                        final

  public static double parseDoubleArgument(scala.collection.immutable.List<java.lang.String>, java.lang.String, double);
    descriptor: (Lscala/collection/immutable/List;Ljava/lang/String;D)D
    flags: (0x0009) ACC_PUBLIC, ACC_STATIC
    Code:
      stack=5, locals=4, args_size=3
         0: getstatic     #18                 // Field org/scalatest/tools/ArgsParser$.MODULE$:Lorg/scalatest/tools/ArgsParser$;
         3: aload_0
         4: aload_1
         5: dload_2
         6: invokevirtual #34                 // Method org/scalatest/tools/ArgsParser$.parseDoubleArgument:(Lscala/collection/immutable/List;Ljava/lang/String;D)D
         9: dreturn
      LocalVariableTable:
        Start  Length  Slot  Name   Signature
            0      10     0  args   Lscala/collection/immutable/List;
            0      10     1 dashArg   Ljava/lang/String;
            0      10     2 defaultValue   D
    Signature: #31                          // (Lscala/collection/immutable/List<Ljava/lang/String;>;Ljava/lang/String;D)D
    MethodParameters:
      Name                           Flags
      args                           final
      dashArg                        final
      defaultValue                   final

  public static scala.collection.immutable.Set<java.lang.String> parseChosenStylesIntoChosenStyleSet(scala.collection.immutable.List<java.lang.String>, java.lang.String);
    descriptor: (Lscala/collection/immutable/List;Ljava/lang/String;)Lscala/collection/immutable/Set;
    flags: (0x0009) ACC_PUBLIC, ACC_STATIC
    Code:
      stack=3, locals=2, args_size=2
         0: getstatic     #18                 // Field org/scalatest/tools/ArgsParser$.MODULE$:Lorg/scalatest/tools/ArgsParser$;
         3: aload_0
         4: aload_1
         5: invokevirtual #40                 // Method org/scalatest/tools/ArgsParser$.parseChosenStylesIntoChosenStyleSet:(Lscala/collection/immutable/List;Ljava/lang/String;)Lscala/collection/immutable/Set;
         8: areturn
      LocalVariableTable:
        Start  Length  Slot  Name   Signature
            0       9     0  args   Lscala/collection/immutable/List;
            0       9     1 dashArg   Ljava/lang/String;
    Signature: #38                          // (Lscala/collection/immutable/List<Ljava/lang/String;>;Ljava/lang/String;)Lscala/collection/immutable/Set<Ljava/lang/String;>;
    MethodParameters:
      Name                           Flags
      args                           final
      dashArg                        final

  public static scala.collection.immutable.List<java.lang.String> parseCompoundArgIntoList(scala.collection.immutable.List<java.lang.String>, java.lang.String);
    descriptor: (Lscala/collection/immutable/List;Ljava/lang/String;)Lscala/collection/immutable/List;
    flags: (0x0009) ACC_PUBLIC, ACC_STATIC
    Code:
      stack=3, locals=2, args_size=2
         0: getstatic     #18                 // Field org/scalatest/tools/ArgsParser$.MODULE$:Lorg/scalatest/tools/ArgsParser$;
         3: aload_0
         4: aload_1
         5: invokevirtual #46                 // Method org/scalatest/tools/ArgsParser$.parseCompoundArgIntoList:(Lscala/collection/immutable/List;Ljava/lang/String;)Lscala/collection/immutable/List;
         8: areturn
      LocalVariableTable:
        Start  Length  Slot  Name   Signature
            0       9     0  args   Lscala/collection/immutable/List;
            0       9     1 expectedDashArg   Ljava/lang/String;
    Signature: #43                          // (Lscala/collection/immutable/List<Ljava/lang/String;>;Ljava/lang/String;)Lscala/collection/immutable/List<Ljava/lang/String;>;
    MethodParameters:
      Name                           Flags
      args                           final
      expectedDashArg                final

  public static scala.collection.immutable.List<java.lang.String> parseRunpathArgIntoList(scala.collection.immutable.List<java.lang.String>);
    descriptor: (Lscala/collection/immutable/List;)Lscala/collection/immutable/List;
    flags: (0x0009) ACC_PUBLIC, ACC_STATIC
    Code:
      stack=2, locals=1, args_size=1
         0: getstatic     #18                 // Field org/scalatest/tools/ArgsParser$.MODULE$:Lorg/scalatest/tools/ArgsParser$;
         3: aload_0
         4: invokevirtual #51                 // Method org/scalatest/tools/ArgsParser$.parseRunpathArgIntoList:(Lscala/collection/immutable/List;)Lscala/collection/immutable/List;
         7: areturn
      LocalVariableTable:
        Start  Length  Slot  Name   Signature
            0       8     0  args   Lscala/collection/immutable/List;
    Signature: #49                          // (Lscala/collection/immutable/List<Ljava/lang/String;>;)Lscala/collection/immutable/List<Ljava/lang/String;>;
    MethodParameters:
      Name                           Flags
      args                           final

  public static scala.collection.immutable.Set<java.lang.String> parseCompoundArgIntoSet(scala.collection.immutable.List<java.lang.String>, java.lang.String);
    descriptor: (Lscala/collection/immutable/List;Ljava/lang/String;)Lscala/collection/immutable/Set;
    flags: (0x0009) ACC_PUBLIC, ACC_STATIC
    Code:
      stack=3, locals=2, args_size=2
         0: getstatic     #18                 // Field org/scalatest/tools/ArgsParser$.MODULE$:Lorg/scalatest/tools/ArgsParser$;
         3: aload_0
         4: aload_1
         5: invokevirtual #54                 // Method org/scalatest/tools/ArgsParser$.parseCompoundArgIntoSet:(Lscala/collection/immutable/List;Ljava/lang/String;)Lscala/collection/immutable/Set;
         8: areturn
      LocalVariableTable:
        Start  Length  Slot  Name   Signature
            0       9     0  args   Lscala/collection/immutable/List;
            0       9     1 expectedDashArg   Ljava/lang/String;
    Signature: #38                          // (Lscala/collection/immutable/List<Ljava/lang/String;>;Ljava/lang/String;)Lscala/collection/immutable/Set<Ljava/lang/String;>;
    MethodParameters:
      Name                           Flags
      args                           final
      expectedDashArg                final

  public static scala.collection.immutable.List<java.lang.String> parseAgainArgs(scala.collection.immutable.List<java.lang.String>);
    descriptor: (Lscala/collection/immutable/List;)Lscala/collection/immutable/List;
    flags: (0x0009) ACC_PUBLIC, ACC_STATIC
    Code:
      stack=2, locals=1, args_size=1
         0: getstatic     #18                 // Field org/scalatest/tools/ArgsParser$.MODULE$:Lorg/scalatest/tools/ArgsParser$;
         3: aload_0
         4: invokevirtual #57                 // Method org/scalatest/tools/ArgsParser$.parseAgainArgs:(Lscala/collection/immutable/List;)Lscala/collection/immutable/List;
         7: areturn
      LocalVariableTable:
        Start  Length  Slot  Name   Signature
            0       8     0  args   Lscala/collection/immutable/List;
    Signature: #49                          // (Lscala/collection/immutable/List<Ljava/lang/String;>;)Lscala/collection/immutable/List<Ljava/lang/String;>;
    MethodParameters:
      Name                           Flags
      args                           final

  public static org.scalatest.tools.ReporterConfigurations parseReporterArgsIntoConfigurations(scala.collection.immutable.List<java.lang.String>);
    descriptor: (Lscala/collection/immutable/List;)Lorg/scalatest/tools/ReporterConfigurations;
    flags: (0x0009) ACC_PUBLIC, ACC_STATIC
    Code:
      stack=2, locals=1, args_size=1
         0: getstatic     #18                 // Field org/scalatest/tools/ArgsParser$.MODULE$:Lorg/scalatest/tools/ArgsParser$;
         3: aload_0
         4: invokevirtual #62                 // Method org/scalatest/tools/ArgsParser$.parseReporterArgsIntoConfigurations:(Lscala/collection/immutable/List;)Lorg/scalatest/tools/ReporterConfigurations;
         7: areturn
      LocalVariableTable:
        Start  Length  Slot  Name   Signature
            0       8     0  args   Lscala/collection/immutable/List;
    Signature: #60                          // (Lscala/collection/immutable/List<Ljava/lang/String;>;)Lorg/scalatest/tools/ReporterConfigurations;
    MethodParameters:
      Name                           Flags
      args                           final

  public static scala.collection.immutable.Set<org.scalatest.tools.ReporterConfigParam> parseConfigSet(java.lang.String);
    descriptor: (Ljava/lang/String;)Lscala/collection/immutable/Set;
    flags: (0x0009) ACC_PUBLIC, ACC_STATIC
    Code:
      stack=2, locals=1, args_size=1
         0: getstatic     #18                 // Field org/scalatest/tools/ArgsParser$.MODULE$:Lorg/scalatest/tools/ArgsParser$;
         3: aload_0
         4: invokevirtual #68                 // Method org/scalatest/tools/ArgsParser$.parseConfigSet:(Ljava/lang/String;)Lscala/collection/immutable/Set;
         7: areturn
      LocalVariableTable:
        Start  Length  Slot  Name   Signature
            0       8     0 reporterArg   Ljava/lang/String;
    Signature: #65                          // (Ljava/lang/String;)Lscala/collection/immutable/Set<Lorg/scalatest/tools/ReporterConfigParam;>;
    MethodParameters:
      Name                           Flags
      reporterArg                    final

  public static scala.collection.immutable.List<java.lang.String> parseSuiteArgsIntoNameStrings(scala.collection.immutable.List<java.lang.String>, java.lang.String);
    descriptor: (Lscala/collection/immutable/List;Ljava/lang/String;)Lscala/collection/immutable/List;
    flags: (0x0009) ACC_PUBLIC, ACC_STATIC
    Code:
      stack=3, locals=2, args_size=2
         0: getstatic     #18                 // Field org/scalatest/tools/ArgsParser$.MODULE$:Lorg/scalatest/tools/ArgsParser$;
         3: aload_0
         4: aload_1
         5: invokevirtual #71                 // Method org/scalatest/tools/ArgsParser$.parseSuiteArgsIntoNameStrings:(Lscala/collection/immutable/List;Ljava/lang/String;)Lscala/collection/immutable/List;
         8: areturn
      LocalVariableTable:
        Start  Length  Slot  Name   Signature
            0       9     0  args   Lscala/collection/immutable/List;
            0       9     1 dashArg   Ljava/lang/String;
    Signature: #43                          // (Lscala/collection/immutable/List<Ljava/lang/String;>;Ljava/lang/String;)Lscala/collection/immutable/List<Ljava/lang/String;>;
    MethodParameters:
      Name                           Flags
      args                           final
      dashArg                        final

  public static scala.Option<java.util.regex.Pattern> genSuffixesPattern(scala.collection.immutable.List<java.lang.String>);
    descriptor: (Lscala/collection/immutable/List;)Lscala/Option;
    flags: (0x0009) ACC_PUBLIC, ACC_STATIC
    Code:
      stack=2, locals=1, args_size=1
         0: getstatic     #18                 // Field org/scalatest/tools/ArgsParser$.MODULE$:Lorg/scalatest/tools/ArgsParser$;
         3: aload_0
         4: invokevirtual #77                 // Method org/scalatest/tools/ArgsParser$.genSuffixesPattern:(Lscala/collection/immutable/List;)Lscala/Option;
         7: areturn
      LocalVariableTable:
        Start  Length  Slot  Name   Signature
            0       8     0 suffixesList   Lscala/collection/immutable/List;
    Signature: #74                          // (Lscala/collection/immutable/List<Ljava/lang/String;>;)Lscala/Option<Ljava/util/regex/Pattern;>;
    MethodParameters:
      Name                           Flags
      suffixesList                   final
}
SourceFile: "ArgsParser.scala"
RuntimeVisibleAnnotations:
  0: #6(#7=s#8)
    scala.reflect.ScalaSignature(
      bytes="\u0006\u0005\u0005\rwA\u0002\u000f\u001e\u0011\u0003i2E\u0002\u0004&;!\u0005QD\n\u0005\u0006[\u0005!\ta\f\u0005\u0007a\u0005!\taH\u0019\t\r1\u000bA\u0011A\u0010N\u0011\u0019a\u0016\u0001\"\u0001 ;\")A-\u0001C\u0001K\"1\u0011/\u0001C\u0001?IDQa^\u0001\u0005\u0002aDq!a\u0002\u0002\t\u0003\tI\u0001C\u0004\u0002\u001c\u0005!\t!!\b\t\u0011\u0005\u001d\u0012\u0001\"\u0001 \u0003SAq!a\u0011\u0002\t\u0003\t)\u0005C\u0005\u0002J\u0005\u0011\r\u0011\"\u0003\u0002L!9\u0011QJ\u0001!\u0002\u00139\u0007bBA(\u0003\u0011%\u0011\u0011\u000b\u0005\n\u0003;\n!\u0019!C\u0005\u0003\u0017Bq!a\u0018\u0002A\u0003%q\rC\u0005\u0002b\u0005\u0011\r\u0011\"\u0003\u0002L!9\u00111M\u0001!\u0002\u00139\u0007bBA3\u0003\u0011%\u0011q\r\u0005\b\u0003[\nA\u0011AA8\u0011\u001d\tI(\u0001C\u0001\u0003wBq!a \u0002\t\u0003\t\t\tC\u0004\u0002\b\u0006!\t!!#\t\u000f\u0005M\u0015\u0001\"\u0001\u0002\u0016\"9\u0011QU\u0001\u0005\u0002\u0005\u001d\u0006bBA[\u0003\u0011\u0005\u0011qW\u0001\u000b\u0003J<7\u000fU1sg\u0016\u0014(B\u0001\u0010 \u0003\u0015!xn\u001c7t\u0015\t\u0001\u0013%A\u0005tG\u0006d\u0017\r^3ti*\t!%A\u0002pe\u001e\u0004\"\u0001J\u0001\u000e\u0003u\u0011!\"\u0011:hgB\u000b\'o]3s\'\t\tq\u0005\u0005\u0002)W5\t\u0011FC\u0001+\u0003\u0015\u00198-\u00197b\u0013\ta\u0013F\u0001\u0004B]f\u0014VMZ\u0001\u0007y%t\u0017\u000e\u001e \u0004\u0001Q\t1%\u0001\u000bdQ\u0016\u001c7.\u0011:hg\u001a{\'OV1mS\u0012LG/\u001f\u000b\u0003eu\u00022\u0001K\u001a6\u0013\t!\u0014F\u0001\u0004PaRLwN\u001c\t\u0003mmj\u0011a\u000e\u0006\u0003qe\nA\u0001\\1oO*\t!(\u0001\u0003kCZ\f\u0017B\u0001\u001f8\u0005\u0019\u0019FO]5oO\")ah\u0001a\u0001\u007f\u0005!\u0011M]4t!\rA\u0003IQ\u0005\u0003\u0003&\u0012Q!\u0011:sCf\u0004\"a\u0011&\u000f\u0005\u0011C\u0005CA#*\u001b\u00051%BA$/\u0003\u0019a$o\\8u}%\u0011\u0011*K\u0001\u0007!J,G-\u001a4\n\u0005qZ%BA%*\u0003U\u0001\u0018M]:f\u0007>t7-\u001e:sK:$8i\u001c8gS\u001e$\"AT)\u0011\u0005\u0011z\u0015B\u0001)\u001e\u0005A\u0019uN\\2veJ,g\u000e^\"p]\u001aLw\rC\u0003S\t\u0001\u00071+\u0001\bd_:\u001cWO\u001d:f]Rd\u0015n\u001d;\u0011\u0007QK&I\u0004\u0002V/:\u0011QIV\u0005\u0002U%\u0011\u0001,K\u0001\ba\u0006\u001c7.Y4f\u0013\tQ6L\u0001\u0003MSN$(B\u0001-*\u0003M\u0001\u0018M]:f\'2|w\u000f]8lK\u000e{gNZ5h)\tq&\rE\u0002)g}\u0003\"\u0001\n1\n\u0005\u0005l\"AD*m_^\u0004xn[3D_:4\u0017n\u001a\u0005\u0006G\u0016\u0001\raU\u0001\rg2|w\u000f]8lK\u0006\u0013xm]\u0001\u0013O\u0016t7+\u001e4gSb,7\u000fU1ui\u0016\u0014h\u000e\u0006\u0002g_B\u0019\u0001fM4\u0011\u0005!lW\"A5\u000b\u0005)\\\u0017!\u0002:fO\u0016D(B\u00017:\u0003\u0011)H/\u001b7\n\u00059L\'a\u0002)biR,\'O\u001c\u0005\u0006a\u001a\u0001\raU\u0001\rgV4g-\u001b=fg2K7\u000f^\u0001\na\u0006\u00148/Z!sON$\"a\u001d<\u0011\u0005\u0011\"\u0018BA;\u001e\u0005)\u0001\u0016M]:fI\u0006\u0013xm\u001d\u0005\u0006}\u001d\u0001\raP\u0001\u001ea\u0006\u00148/Z*vSR,\u0017I]4t\u0013:$xNT1nKN#(/\u001b8hgR)\u00110!\u0001\u0002\u0004A\u0019!p \"\u000e\u0003mT!\u0001`?\u0002\u0013%lW.\u001e;bE2,\'B\u0001@*\u0003)\u0019w\u000e\u001c7fGRLwN\\\u0005\u00035nDQA\u0010\u0005A\u0002MCa!!\u0002\t\u0001\u0004\u0011\u0015a\u00023bg\"\f%oZ\u0001\u000fa\u0006\u00148/Z\"p]\u001aLwmU3u)\u0011\tY!a\u0006\u0011\u000b\r\u000bi!!\u0005\n\u0007\u0005=1JA\u0002TKR\u00042\u0001JA\n\u0013\r\t)\"\b\u0002\u0014%\u0016\u0004xN\u001d;fe\u000e{gNZ5h!\u0006\u0014\u0018-\u001c\u0005\u0007\u00033I\u0001\u0019\u0001\"\u0002\u0017I,\u0007o\u001c:uKJ\f%oZ\u0001$a\u0006\u00148/\u001a*fa>\u0014H/\u001a:Be\u001e\u001c\u0018J\u001c;p\u0007>tg-[4ve\u0006$\u0018n\u001c8t)\u0011\ty\"!\n\u0011\u0007\u0011\n\t#C\u0002\u0002$u\u0011aCU3q_J$XM]\"p]\u001aLw-\u001e:bi&|gn\u001d\u0005\u0006})\u0001\raU\u0001\u000fa\u0006\u00148/Z*vSR,\u0017I]4t)\u0011\tY#!\u0011\u0011\u000f!\ni#!\r\u0002:%\u0019\u0011qF\u0015\u0003\rQ+\b\u000f\\33!\u0011!\u0016,a\r\u0011\u0007\u0011\n)$C\u0002\u00028u\u0011!bU;ji\u0016\u0004\u0016M]1n!\u0011!\u0016,a\u000f\u0011\u0007\u0011\ni$C\u0002\u0002@u\u0011\u0001\u0002V3tiN\u0003Xm\u0019\u0005\u0006}-\u0001\raU\u0001\u000fa\u0006\u00148/Z!hC&t\u0017I]4t)\r\u0019\u0016q\t\u0005\u0006}1\u0001\raU\u0001\u0011%>{Ek\u0018#J%~\u0003\u0016\t\u0016+F%:+\u0012aZ\u0001\u0012%>{Ek\u0018#J%~\u0003\u0016\t\u0016+F%:\u0003\u0013aD5t\u0007>l\u0007\u000f\\3uKR{7.\u001a8\u0015\t\u0005M\u0013\u0011\f\t\u0004Q\u0005U\u0013bAA,S\t9!i\\8mK\u0006t\u0007BBA.\u001f\u0001\u0007!)A\u0003u_.,g.A\nT)\u0006\u0013Fk\u0018+P\u0017\u0016su\fU!U)\u0016\u0013f*\u0001\u000bT)\u0006\u0013Fk\u0018+P\u0017\u0016su\fU!U)\u0016\u0013f\nI\u0001\u0013\rVcEj\u0018+P\u0017\u0016su\fU!U)\u0016\u0013f*A\nG+2cu\fV(L\u000b:{\u0006+\u0011+U\u000bJs\u0005%A\u0005ta2LG\u000fU1uQR\u00191+!\u001b\t\r\u0005-D\u00031\u0001C\u0003\u001d\u0001\u0018\r\u001e5Be\u001e\fq\u0003]1sg\u0016\u001cu.\u001c9pk:$\u0017I]4J]R|7+\u001a;\u0015\r\u0005E\u00141OA;!\u0011\u0019\u0015Q\u0002\"\t\u000by*\u0002\u0019A*\t\r\u0005]T\u00031\u0001C\u0003=)\u0007\u0010]3di\u0016$G)Y:i\u0003J<\u0017a\u00069beN,\'+\u001e8qCRD\u0017I]4J]R|G*[:u)\r\u0019\u0016Q\u0010\u0005\u0006}Y\u0001\raU\u0001\u0019a\u0006\u00148/Z\"p[B|WO\u001c3Be\u001eLe\u000e^8MSN$H#B*\u0002\u0004\u0006\u0015\u0005\"\u0002 \u0018\u0001\u0004\u0019\u0006BBA</\u0001\u0007!)A\u0012qCJ\u001cXm\u00115pg\u0016t7\u000b^=mKNLe\u000e^8DQ>\u001cXM\\*us2,7+\u001a;\u0015\r\u0005-\u0015qRAI!\u0011Q\u0018Q\u0012\"\n\u0007\u0005=1\u0010C\u0003?1\u0001\u00071\u000b\u0003\u0004\u0002\u0006a\u0001\rAQ\u0001\u0014a\u0006\u00148/\u001a#pk\ndW-\u0011:hk6,g\u000e\u001e\u000b\t\u0003/\u000bi*a(\u0002\"B\u0019\u0001&!\'\n\u0007\u0005m\u0015F\u0001\u0004E_V\u0014G.\u001a\u0005\u0006}e\u0001\ra\u0015\u0005\u0007\u0003\u000bI\u0002\u0019\u0001\"\t\u000f\u0005\r\u0016\u00041\u0001\u0002\u0018\u0006aA-\u001a4bk2$h+\u00197vK\u0006\t\u0002/\u0019:tK2{gnZ!sOVlWM\u001c;\u0015\r\u0005%\u0016\u0011WAZ!\u0011A3\'a+\u0011\u0007!\ni+C\u0002\u00020&\u0012A\u0001T8oO\")aH\u0007a\u0001\'\"1\u0011Q\u0001\u000eA\u0002\t\u000b!\u0004]1sg\u0016\u0004&o\u001c9feRLWm]!sONLe\u000e^8NCB$B!!/\u0002BB!\u00111XA_\u001b\u0005y\u0012bAA`?\tI1i\u001c8gS\u001el\u0015\r\u001d\u0005\u0006}m\u0001\ra\u0015"
    )
  ScalaSig: length = 0x3 (unknown attribute)
   05 02 00
