Classfile /Users/mw/Projects/slang-braindump/.jar/jar11/assemble/slang-braindump/assemble/content/org/scalatest/tools/DashboardReporter$SuiteRecord.class
  Last modified May 29, 2022; size 7362 bytes
  SHA-256 checksum 942e0c81537e4dd8c7a6eb5ae70ff30f27e214b6d2883625498f3ff2a8210afd
  Compiled from "DashboardReporter.scala"
public class org.scalatest.tools.DashboardReporter$SuiteRecord
  minor version: 0
  major version: 52
  flags: (0x0021) ACC_PUBLIC, ACC_SUPER
  this_class: #2                          // org/scalatest/tools/DashboardReporter$SuiteRecord
  super_class: #4                         // java/lang/Object
  interfaces: 0, fields: 4, methods: 15, attributes: 5
Constant pool:
    #1 = Utf8               org/scalatest/tools/DashboardReporter$SuiteRecord
    #2 = Class              #1            // org/scalatest/tools/DashboardReporter$SuiteRecord
    #3 = Utf8               java/lang/Object
    #4 = Class              #3            // java/lang/Object
    #5 = Utf8               DashboardReporter.scala
    #6 = Utf8               java/lang/invoke/MethodHandles$Lookup
    #7 = Class              #6            // java/lang/invoke/MethodHandles$Lookup
    #8 = Utf8               java/lang/invoke/MethodHandles
    #9 = Class              #8            // java/lang/invoke/MethodHandles
   #10 = Utf8               Lookup
   #11 = Utf8               org/scalatest/tools/DashboardReporter
   #12 = Class              #11           // org/scalatest/tools/DashboardReporter
   #13 = Utf8               SuiteRecord
   #14 = Utf8               org/scalatest/tools/DashboardReporter$TestRecord
   #15 = Class              #14           // org/scalatest/tools/DashboardReporter$TestRecord
   #16 = Utf8               TestRecord
   #17 = Utf8               startEvent
   #18 = Utf8               Lorg/scalatest/events/SuiteStarting;
   #19 = Utf8               nestedElements
   #20 = Utf8               Lscala/collection/immutable/List;
   #21 = Utf8               Lscala/collection/immutable/List<Ljava/lang/Object;>;
   #22 = Utf8               endEvent
   #23 = Utf8               Lorg/scalatest/events/Event;
   #24 = Utf8               $outer
   #25 = Utf8               Lorg/scalatest/tools/DashboardReporter;
   #26 = Utf8               ()Lscala/collection/immutable/List;
   #27 = Utf8               ()Lscala/collection/immutable/List<Ljava/lang/Object;>;
   #28 = NameAndType        #19:#20       // nestedElements:Lscala/collection/immutable/List;
   #29 = Fieldref           #2.#28        // org/scalatest/tools/DashboardReporter$SuiteRecord.nestedElements:Lscala/collection/immutable/List;
   #30 = Utf8               this
   #31 = Utf8               Lorg/scalatest/tools/DashboardReporter$SuiteRecord;
   #32 = Utf8               nestedElements_$eq
   #33 = Utf8               (Lscala/collection/immutable/List;)V
   #34 = Utf8               (Lscala/collection/immutable/List<Ljava/lang/Object;>;)V
   #35 = Utf8               x$1
   #36 = Utf8               ()Lorg/scalatest/events/Event;
   #37 = NameAndType        #22:#23       // endEvent:Lorg/scalatest/events/Event;
   #38 = Fieldref           #2.#37        // org/scalatest/tools/DashboardReporter$SuiteRecord.endEvent:Lorg/scalatest/events/Event;
   #39 = Utf8               endEvent_$eq
   #40 = Utf8               (Lorg/scalatest/events/Event;)V
   #41 = Utf8               addNestedElement
   #42 = Utf8               (Ljava/lang/Object;)V
   #43 = Utf8               element
   #44 = NameAndType        #19:#26       // nestedElements:()Lscala/collection/immutable/List;
   #45 = Methodref          #2.#44        // org/scalatest/tools/DashboardReporter$SuiteRecord.nestedElements:()Lscala/collection/immutable/List;
   #46 = Utf8               scala/collection/immutable/List
   #47 = Class              #46           // scala/collection/immutable/List
   #48 = Utf8               $colon$colon
   #49 = Utf8               (Ljava/lang/Object;)Lscala/collection/immutable/List;
   #50 = NameAndType        #48:#49       // $colon$colon:(Ljava/lang/Object;)Lscala/collection/immutable/List;
   #51 = Methodref          #47.#50       // scala/collection/immutable/List.$colon$colon:(Ljava/lang/Object;)Lscala/collection/immutable/List;
   #52 = NameAndType        #32:#33       // nestedElements_$eq:(Lscala/collection/immutable/List;)V
   #53 = Methodref          #2.#52        // org/scalatest/tools/DashboardReporter$SuiteRecord.nestedElements_$eq:(Lscala/collection/immutable/List;)V
   #54 = Utf8               Ljava/lang/Object;
   #55 = Utf8               addEndEvent
   #56 = Utf8               event
   #57 = Utf8               scala/Predef$
   #58 = Class              #57           // scala/Predef$
   #59 = Utf8               MODULE$
   #60 = Utf8               Lscala/Predef$;
   #61 = NameAndType        #59:#60       // MODULE$:Lscala/Predef$;
   #62 = Fieldref           #58.#61       // scala/Predef$.MODULE$:Lscala/Predef$;
   #63 = NameAndType        #22:#36       // endEvent:()Lorg/scalatest/events/Event;
   #64 = Methodref          #2.#63        // org/scalatest/tools/DashboardReporter$SuiteRecord.endEvent:()Lorg/scalatest/events/Event;
   #65 = Utf8               require
   #66 = Utf8               (Z)V
   #67 = NameAndType        #65:#66       // require:(Z)V
   #68 = Methodref          #58.#67       // scala/Predef$.require:(Z)V
   #69 = Utf8               isEndEvent$1
   #70 = Utf8               (Lorg/scalatest/events/Event;)Z
   #71 = NameAndType        #69:#70       // isEndEvent$1:(Lorg/scalatest/events/Event;)Z
   #72 = Methodref          #2.#71        // org/scalatest/tools/DashboardReporter$SuiteRecord.isEndEvent$1:(Lorg/scalatest/events/Event;)Z
   #73 = NameAndType        #39:#40       // endEvent_$eq:(Lorg/scalatest/events/Event;)V
   #74 = Methodref          #2.#73        // org/scalatest/tools/DashboardReporter$SuiteRecord.endEvent_$eq:(Lorg/scalatest/events/Event;)V
   #75 = Utf8               org/scalatest/events/Event
   #76 = Class              #75           // org/scalatest/events/Event
   #77 = Utf8               result
   #78 = Utf8               ()Ljava/lang/String;
   #79 = Utf8               org/scalatest/events/SuiteCompleted
   #80 = Class              #79           // org/scalatest/events/SuiteCompleted
   #81 = Utf8               completed
   #82 = String             #81           // completed
   #83 = Utf8               org/scalatest/events/SuiteAborted
   #84 = Class              #83           // org/scalatest/events/SuiteAborted
   #85 = Utf8               aborted
   #86 = String             #85           // aborted
   #87 = Utf8               org$scalatest$tools$DashboardReporter$SuiteRecord$$$outer
   #88 = Utf8               ()Lorg/scalatest/tools/DashboardReporter;
   #89 = NameAndType        #87:#88       // org$scalatest$tools$DashboardReporter$SuiteRecord$$$outer:()Lorg/scalatest/tools/DashboardReporter;
   #90 = Methodref          #2.#89        // org/scalatest/tools/DashboardReporter$SuiteRecord.org$scalatest$tools$DashboardReporter$SuiteRecord$$$outer:()Lorg/scalatest/tools/DashboardReporter;
   #91 = Utf8               unexpectedEvent
   #92 = NameAndType        #91:#40       // unexpectedEvent:(Lorg/scalatest/events/Event;)V
   #93 = Methodref          #12.#92       // org/scalatest/tools/DashboardReporter.unexpectedEvent:(Lorg/scalatest/events/Event;)V
   #94 = Utf8
   #95 = String             #94           //
   #96 = Utf8               java/lang/String
   #97 = Class              #96           // java/lang/String
   #98 = Utf8               toXml
   #99 = Utf8               scala/collection/mutable/StringBuilder
  #100 = Class              #99           // scala/collection/mutable/StringBuilder
  #101 = Utf8               <init>
  #102 = Utf8               ()V
  #103 = NameAndType        #101:#102     // "<init>":()V
  #104 = Methodref          #100.#103     // scala/collection/mutable/StringBuilder."<init>":()V
  #105 = Utf8               scala/runtime/ObjectRef
  #106 = Class              #105          // scala/runtime/ObjectRef
  #107 = Utf8               create
  #108 = Utf8               (Ljava/lang/Object;)Lscala/runtime/ObjectRef;
  #109 = NameAndType        #107:#108     // create:(Ljava/lang/Object;)Lscala/runtime/ObjectRef;
  #110 = Methodref          #106.#109     // scala/runtime/ObjectRef.create:(Ljava/lang/Object;)Lscala/runtime/ObjectRef;
  #111 = NameAndType        #17:#18       // startEvent:Lorg/scalatest/events/SuiteStarting;
  #112 = Fieldref           #2.#111       // org/scalatest/tools/DashboardReporter$SuiteRecord.startEvent:Lorg/scalatest/events/SuiteStarting;
  #113 = Utf8               org/scalatest/events/SuiteStarting
  #114 = Class              #113          // org/scalatest/events/SuiteStarting
  #115 = Utf8               suiteName
  #116 = NameAndType        #115:#78      // suiteName:()Ljava/lang/String;
  #117 = Methodref          #114.#116     // org/scalatest/events/SuiteStarting.suiteName:()Ljava/lang/String;
  #118 = Utf8               DiscoverySuite
  #119 = String             #118          // DiscoverySuite
  #120 = Utf8               equals
  #121 = Utf8               (Ljava/lang/Object;)Z
  #122 = NameAndType        #120:#121     // equals:(Ljava/lang/Object;)Z
  #123 = Methodref          #4.#122       // java/lang/Object.equals:(Ljava/lang/Object;)Z
  #124 = Utf8               formatStartOfSuite$1
  #125 = NameAndType        #124:#78      // formatStartOfSuite$1:()Ljava/lang/String;
  #126 = Methodref          #2.#125       // org/scalatest/tools/DashboardReporter$SuiteRecord.formatStartOfSuite$1:()Ljava/lang/String;
  #127 = Utf8               append
  #128 = Utf8               (Ljava/lang/String;)Lscala/collection/mutable/StringBuilder;
  #129 = NameAndType        #127:#128     // append:(Ljava/lang/String;)Lscala/collection/mutable/StringBuilder;
  #130 = Methodref          #100.#129     // scala/collection/mutable/StringBuilder.append:(Ljava/lang/String;)Lscala/collection/mutable/StringBuilder;
  #131 = Utf8               scala/runtime/BoxedUnit
  #132 = Class              #131          // scala/runtime/BoxedUnit
  #133 = Utf8               UNIT
  #134 = Utf8               Lscala/runtime/BoxedUnit;
  #135 = NameAndType        #133:#134     // UNIT:Lscala/runtime/BoxedUnit;
  #136 = Fieldref           #132.#135     // scala/runtime/BoxedUnit.UNIT:Lscala/runtime/BoxedUnit;
  #137 = Utf8               reverse
  #138 = NameAndType        #137:#26      // reverse:()Lscala/collection/immutable/List;
  #139 = Methodref          #47.#138      // scala/collection/immutable/List.reverse:()Lscala/collection/immutable/List;
  #140 = Utf8               (Ljava/lang/Object;)Ljava/lang/Object;
  #141 = MethodType         #140          //  (Ljava/lang/Object;)Ljava/lang/Object;
  #142 = Utf8               $anonfun$toXml$1
  #143 = Utf8               (Lorg/scalatest/tools/DashboardReporter$SuiteRecord;Lscala/runtime/ObjectRef;Lscala/collection/mutable/StringBuilder;Ljava/lang/Object;)Ljava/lang/Object;
  #144 = NameAndType        #142:#143     // $anonfun$toXml$1:(Lorg/scalatest/tools/DashboardReporter$SuiteRecord;Lscala/runtime/ObjectRef;Lscala/collection/mutable/StringBuilder;Ljava/lang/Object;)Ljava/lang/Object;
  #145 = Methodref          #2.#144       // org/scalatest/tools/DashboardReporter$SuiteRecord.$anonfun$toXml$1:(Lorg/scalatest/tools/DashboardReporter$SuiteRecord;Lscala/runtime/ObjectRef;Lscala/collection/mutable/StringBuilder;Ljava/lang/Object;)Ljava/lang/Object;
  #146 = MethodHandle       6:#145        // REF_invokeStatic org/scalatest/tools/DashboardReporter$SuiteRecord.$anonfun$toXml$1:(Lorg/scalatest/tools/DashboardReporter$SuiteRecord;Lscala/runtime/ObjectRef;Lscala/collection/mutable/StringBuilder;Ljava/lang/Object;)Ljava/lang/Object;
  #147 = Integer            1
  #148 = Utf8               java/lang/invoke/LambdaMetafactory
  #149 = Class              #148          // java/lang/invoke/LambdaMetafactory
  #150 = Utf8               altMetafactory
  #151 = Utf8               (Ljava/lang/invoke/MethodHandles$Lookup;Ljava/lang/String;Ljava/lang/invoke/MethodType;[Ljava/lang/Object;)Ljava/lang/invoke/CallSite;
  #152 = NameAndType        #150:#151     // altMetafactory:(Ljava/lang/invoke/MethodHandles$Lookup;Ljava/lang/String;Ljava/lang/invoke/MethodType;[Ljava/lang/Object;)Ljava/lang/invoke/CallSite;
  #153 = Methodref          #149.#152     // java/lang/invoke/LambdaMetafactory.altMetafactory:(Ljava/lang/invoke/MethodHandles$Lookup;Ljava/lang/String;Ljava/lang/invoke/MethodType;[Ljava/lang/Object;)Ljava/lang/invoke/CallSite;
  #154 = MethodHandle       6:#153        // REF_invokeStatic java/lang/invoke/LambdaMetafactory.altMetafactory:(Ljava/lang/invoke/MethodHandles$Lookup;Ljava/lang/String;Ljava/lang/invoke/MethodType;[Ljava/lang/Object;)Ljava/lang/invoke/CallSite;
  #155 = Utf8               apply
  #156 = Utf8               (Lorg/scalatest/tools/DashboardReporter$SuiteRecord;Lscala/runtime/ObjectRef;Lscala/collection/mutable/StringBuilder;)Lscala/Function1;
  #157 = NameAndType        #155:#156     // apply:(Lorg/scalatest/tools/DashboardReporter$SuiteRecord;Lscala/runtime/ObjectRef;Lscala/collection/mutable/StringBuilder;)Lscala/Function1;
  #158 = InvokeDynamic      #0:#157       // #0:apply:(Lorg/scalatest/tools/DashboardReporter$SuiteRecord;Lscala/runtime/ObjectRef;Lscala/collection/mutable/StringBuilder;)Lscala/Function1;
  #159 = Utf8               foreach
  #160 = Utf8               (Lscala/Function1;)V
  #161 = NameAndType        #159:#160     // foreach:(Lscala/Function1;)V
  #162 = Methodref          #47.#161      // scala/collection/immutable/List.foreach:(Lscala/Function1;)V
  #163 = Utf8               </suite>\n
  #164 = String             #163          // </suite>\n
  #165 = Utf8               toString
  #166 = NameAndType        #165:#78      // toString:()Ljava/lang/String;
  #167 = Methodref          #100.#166     // scala/collection/mutable/StringBuilder.toString:()Ljava/lang/String;
  #168 = Utf8               buf
  #169 = Utf8               Lscala/collection/mutable/StringBuilder;
  #170 = Utf8               testRecord
  #171 = Utf8               Lscala/runtime/ObjectRef;
  #172 = NameAndType        #24:#25       // $outer:Lorg/scalatest/tools/DashboardReporter;
  #173 = Fieldref           #2.#172       // org/scalatest/tools/DashboardReporter$SuiteRecord.$outer:Lorg/scalatest/tools/DashboardReporter;
  #174 = Utf8               e
  #175 = Utf8               timeStamp
  #176 = Utf8               ()J
  #177 = NameAndType        #175:#176     // timeStamp:()J
  #178 = Methodref          #76.#177      // org/scalatest/events/Event.timeStamp:()J
  #179 = Methodref          #114.#177     // org/scalatest/events/SuiteStarting.timeStamp:()J
  #180 = Utf8               java/lang/StringBuilder
  #181 = Class              #180          // java/lang/StringBuilder
  #182 = Integer            64
  #183 = Utf8               (I)V
  #184 = NameAndType        #101:#183     // "<init>":(I)V
  #185 = Methodref          #181.#184     // java/lang/StringBuilder."<init>":(I)V
  #186 = Utf8               \n<suite index=\"
  #187 = String             #186          // \n<suite index=\"
  #188 = Utf8               (Ljava/lang/String;)Ljava/lang/StringBuilder;
  #189 = NameAndType        #127:#188     // append:(Ljava/lang/String;)Ljava/lang/StringBuilder;
  #190 = Methodref          #181.#189     // java/lang/StringBuilder.append:(Ljava/lang/String;)Ljava/lang/StringBuilder;
  #191 = Utf8               nextIndex
  #192 = Utf8               ()I
  #193 = NameAndType        #191:#192     // nextIndex:()I
  #194 = Methodref          #12.#193      // org/scalatest/tools/DashboardReporter.nextIndex:()I
  #195 = Utf8               (I)Ljava/lang/StringBuilder;
  #196 = NameAndType        #127:#195     // append:(I)Ljava/lang/StringBuilder;
  #197 = Methodref          #181.#196     // java/lang/StringBuilder.append:(I)Ljava/lang/StringBuilder;
  #198 = Utf8               \"
  #199 = String             #198          // \"
  #200 = Utf8               id=\"
  #201 = String             #200          // id=\"
  #202 = Utf8               suiteId
  #203 = NameAndType        #202:#78      // suiteId:()Ljava/lang/String;
  #204 = Methodref          #114.#203     // org/scalatest/events/SuiteStarting.suiteId:()Ljava/lang/String;
  #205 = Utf8               result=\"
  #206 = String             #205          // result=\"
  #207 = NameAndType        #77:#78       // result:()Ljava/lang/String;
  #208 = Methodref          #2.#207       // org/scalatest/tools/DashboardReporter$SuiteRecord.result:()Ljava/lang/String;
  #209 = Utf8               name=\"
  #210 = String             #209          // name=\"
  #211 = Utf8               escape
  #212 = Utf8               (Ljava/lang/String;)Ljava/lang/String;
  #213 = NameAndType        #211:#212     // escape:(Ljava/lang/String;)Ljava/lang/String;
  #214 = Methodref          #12.#213      // org/scalatest/tools/DashboardReporter.escape:(Ljava/lang/String;)Ljava/lang/String;
  #215 = Utf8               duration=\"
  #216 = String             #215          // duration=\"
  #217 = Utf8               (J)Ljava/lang/StringBuilder;
  #218 = NameAndType        #127:#217     // append:(J)Ljava/lang/StringBuilder;
  #219 = Methodref          #181.#218     // java/lang/StringBuilder.append:(J)Ljava/lang/StringBuilder;
  #220 = Utf8               thread=\"
  #221 = String             #220          // thread=\"
  #222 = Utf8               threadName
  #223 = NameAndType        #222:#78      // threadName:()Ljava/lang/String;
  #224 = Methodref          #114.#223     // org/scalatest/events/SuiteStarting.threadName:()Ljava/lang/String;
  #225 = Utf8               \">\n
  #226 = String             #225          // \">\n
  #227 = Methodref          #181.#166     // java/lang/StringBuilder.toString:()Ljava/lang/String;
  #228 = Utf8               duration
  #229 = Utf8               J
  #230 = Utf8               inATest$1
  #231 = Utf8               (Lscala/runtime/ObjectRef;)Z
  #232 = Utf8               testRecord$1
  #233 = Utf8               elem
  #234 = NameAndType        #233:#54      // elem:Ljava/lang/Object;
  #235 = Fieldref           #106.#234     // scala/runtime/ObjectRef.elem:Ljava/lang/Object;
  #236 = Methodref          #15.#63       // org/scalatest/tools/DashboardReporter$TestRecord.endEvent:()Lorg/scalatest/events/Event;
  #237 = Utf8               $this
  #238 = Utf8               buf$4
  #239 = NameAndType        #230:#231     // inATest$1:(Lscala/runtime/ObjectRef;)Z
  #240 = Methodref          #2.#239       // org/scalatest/tools/DashboardReporter$SuiteRecord.inATest$1:(Lscala/runtime/ObjectRef;)Z
  #241 = Utf8               addEvent
  #242 = NameAndType        #241:#40      // addEvent:(Lorg/scalatest/events/Event;)V
  #243 = Methodref          #15.#242      // org/scalatest/tools/DashboardReporter$TestRecord.addEvent:(Lorg/scalatest/events/Event;)V
  #244 = Utf8               isComplete
  #245 = Utf8               ()Z
  #246 = NameAndType        #244:#245     // isComplete:()Z
  #247 = Methodref          #15.#246      // org/scalatest/tools/DashboardReporter$TestRecord.isComplete:()Z
  #248 = NameAndType        #98:#78       // toXml:()Ljava/lang/String;
  #249 = Methodref          #15.#248      // org/scalatest/tools/DashboardReporter$TestRecord.toXml:()Ljava/lang/String;
  #250 = Utf8               org/scalatest/events/TestIgnored
  #251 = Class              #250          // org/scalatest/events/TestIgnored
  #252 = Utf8               formatTestIgnored
  #253 = Utf8               (Lorg/scalatest/events/TestIgnored;)Ljava/lang/String;
  #254 = NameAndType        #252:#253     // formatTestIgnored:(Lorg/scalatest/events/TestIgnored;)Ljava/lang/String;
  #255 = Methodref          #12.#254      // org/scalatest/tools/DashboardReporter.formatTestIgnored:(Lorg/scalatest/events/TestIgnored;)Ljava/lang/String;
  #256 = Methodref          #2.#248       // org/scalatest/tools/DashboardReporter$SuiteRecord.toXml:()Ljava/lang/String;
  #257 = Utf8               org/scalatest/events/TestStarting
  #258 = Class              #257          // org/scalatest/events/TestStarting
  #259 = Utf8               (Lorg/scalatest/tools/DashboardReporter;Lorg/scalatest/events/TestStarting;)V
  #260 = NameAndType        #101:#259     // "<init>":(Lorg/scalatest/tools/DashboardReporter;Lorg/scalatest/events/TestStarting;)V
  #261 = Methodref          #15.#260      // org/scalatest/tools/DashboardReporter$TestRecord."<init>":(Lorg/scalatest/tools/DashboardReporter;Lorg/scalatest/events/TestStarting;)V
  #262 = Utf8               java/lang/RuntimeException
  #263 = Class              #262          // java/lang/RuntimeException
  #264 = Integer            13
  #265 = Utf8               unexpected [
  #266 = String             #265          // unexpected [
  #267 = Utf8               (Ljava/lang/Object;)Ljava/lang/StringBuilder;
  #268 = NameAndType        #127:#267     // append:(Ljava/lang/Object;)Ljava/lang/StringBuilder;
  #269 = Methodref          #181.#268     // java/lang/StringBuilder.append:(Ljava/lang/Object;)Ljava/lang/StringBuilder;
  #270 = Utf8               ]
  #271 = String             #270          // ]
  #272 = Utf8               (Ljava/lang/String;)V
  #273 = NameAndType        #101:#272     // "<init>":(Ljava/lang/String;)V
  #274 = Methodref          #263.#273     // java/lang/RuntimeException."<init>":(Ljava/lang/String;)V
  #275 = Utf8               (Lorg/scalatest/tools/DashboardReporter;Lorg/scalatest/events/SuiteStarting;)V
  #276 = Methodref          #4.#103       // java/lang/Object."<init>":()V
  #277 = Utf8               scala/package$
  #278 = Class              #277          // scala/package$
  #279 = Utf8               Lscala/package$;
  #280 = NameAndType        #59:#279      // MODULE$:Lscala/package$;
  #281 = Fieldref           #278.#280     // scala/package$.MODULE$:Lscala/package$;
  #282 = Utf8               List
  #283 = Utf8               ()Lscala/collection/immutable/List$;
  #284 = NameAndType        #282:#283     // List:()Lscala/collection/immutable/List$;
  #285 = Methodref          #278.#284     // scala/package$.List:()Lscala/collection/immutable/List$;
  #286 = Utf8               scala/collection/immutable/Nil$
  #287 = Class              #286          // scala/collection/immutable/Nil$
  #288 = Utf8               Lscala/collection/immutable/Nil$;
  #289 = NameAndType        #59:#288      // MODULE$:Lscala/collection/immutable/Nil$;
  #290 = Fieldref           #287.#289     // scala/collection/immutable/Nil$.MODULE$:Lscala/collection/immutable/Nil$;
  #291 = Utf8               scala/collection/immutable/List$
  #292 = Class              #291          // scala/collection/immutable/List$
  #293 = Utf8               (Lscala/collection/immutable/Seq;)Ljava/lang/Object;
  #294 = NameAndType        #155:#293     // apply:(Lscala/collection/immutable/Seq;)Ljava/lang/Object;
  #295 = Methodref          #292.#294     // scala/collection/immutable/List$.apply:(Lscala/collection/immutable/Seq;)Ljava/lang/Object;
  #296 = Utf8               $deserializeLambda$
  #297 = Utf8               (Ljava/lang/invoke/SerializedLambda;)Ljava/lang/Object;
  #298 = Utf8               scala/runtime/LambdaDeserialize
  #299 = Class              #298          // scala/runtime/LambdaDeserialize
  #300 = Utf8               bootstrap
  #301 = Utf8               (Ljava/lang/invoke/MethodHandles$Lookup;Ljava/lang/String;Ljava/lang/invoke/MethodType;[Ljava/lang/invoke/MethodHandle;)Ljava/lang/invoke/CallSite;
  #302 = NameAndType        #300:#301     // bootstrap:(Ljava/lang/invoke/MethodHandles$Lookup;Ljava/lang/String;Ljava/lang/invoke/MethodType;[Ljava/lang/invoke/MethodHandle;)Ljava/lang/invoke/CallSite;
  #303 = Methodref          #299.#302     // scala/runtime/LambdaDeserialize.bootstrap:(Ljava/lang/invoke/MethodHandles$Lookup;Ljava/lang/String;Ljava/lang/invoke/MethodType;[Ljava/lang/invoke/MethodHandle;)Ljava/lang/invoke/CallSite;
  #304 = MethodHandle       6:#303        // REF_invokeStatic scala/runtime/LambdaDeserialize.bootstrap:(Ljava/lang/invoke/MethodHandles$Lookup;Ljava/lang/String;Ljava/lang/invoke/MethodType;[Ljava/lang/invoke/MethodHandle;)Ljava/lang/invoke/CallSite;
  #305 = Utf8               lambdaDeserialize
  #306 = NameAndType        #305:#297     // lambdaDeserialize:(Ljava/lang/invoke/SerializedLambda;)Ljava/lang/Object;
  #307 = InvokeDynamic      #1:#306       // #1:lambdaDeserialize:(Ljava/lang/invoke/SerializedLambda;)Ljava/lang/Object;
  #308 = Utf8               Signature
  #309 = Utf8               Code
  #310 = Utf8               LineNumberTable
  #311 = Utf8               LocalVariableTable
  #312 = Utf8               MethodParameters
  #313 = Utf8               StackMapTable
  #314 = Utf8               InnerClasses
  #315 = Utf8               SourceFile
  #316 = Utf8               BootstrapMethods
  #317 = Utf8               ScalaInlineInfo
  #318 = Utf8               Scala
{
  private final org.scalatest.events.SuiteStarting startEvent;
    descriptor: Lorg/scalatest/events/SuiteStarting;
    flags: (0x0012) ACC_PRIVATE, ACC_FINAL

  private scala.collection.immutable.List<java.lang.Object> nestedElements;
    descriptor: Lscala/collection/immutable/List;
    flags: (0x0002) ACC_PRIVATE
    Signature: #21                          // Lscala/collection/immutable/List<Ljava/lang/Object;>;

  private org.scalatest.events.Event endEvent;
    descriptor: Lorg/scalatest/events/Event;
    flags: (0x0002) ACC_PRIVATE

  public final org.scalatest.tools.DashboardReporter $outer;
    descriptor: Lorg/scalatest/tools/DashboardReporter;
    flags: (0x1011) ACC_PUBLIC, ACC_FINAL, ACC_SYNTHETIC

  public scala.collection.immutable.List<java.lang.Object> nestedElements();
    descriptor: ()Lscala/collection/immutable/List;
    flags: (0x0001) ACC_PUBLIC
    Code:
      stack=1, locals=1, args_size=1
         0: aload_0
         1: getfield      #29                 // Field nestedElements:Lscala/collection/immutable/List;
         4: areturn
      LineNumberTable:
        line 648: 0
      LocalVariableTable:
        Start  Length  Slot  Name   Signature
            0       5     0  this   Lorg/scalatest/tools/DashboardReporter$SuiteRecord;
    Signature: #27                          // ()Lscala/collection/immutable/List<Ljava/lang/Object;>;

  public void nestedElements_$eq(scala.collection.immutable.List<java.lang.Object>);
    descriptor: (Lscala/collection/immutable/List;)V
    flags: (0x0001) ACC_PUBLIC
    Code:
      stack=2, locals=2, args_size=2
         0: aload_0
         1: aload_1
         2: putfield      #29                 // Field nestedElements:Lscala/collection/immutable/List;
         5: return
      LineNumberTable:
        line 648: 0
      LocalVariableTable:
        Start  Length  Slot  Name   Signature
            0       6     0  this   Lorg/scalatest/tools/DashboardReporter$SuiteRecord;
            0       6     1   x$1   Lscala/collection/immutable/List;
    Signature: #34                          // (Lscala/collection/immutable/List<Ljava/lang/Object;>;)V
    MethodParameters:
      Name                           Flags
      x$1                            final

  public org.scalatest.events.Event endEvent();
    descriptor: ()Lorg/scalatest/events/Event;
    flags: (0x0001) ACC_PUBLIC
    Code:
      stack=1, locals=1, args_size=1
         0: aload_0
         1: getfield      #38                 // Field endEvent:Lorg/scalatest/events/Event;
         4: areturn
      LineNumberTable:
        line 649: 0
      LocalVariableTable:
        Start  Length  Slot  Name   Signature
            0       5     0  this   Lorg/scalatest/tools/DashboardReporter$SuiteRecord;

  public void endEvent_$eq(org.scalatest.events.Event);
    descriptor: (Lorg/scalatest/events/Event;)V
    flags: (0x0001) ACC_PUBLIC
    Code:
      stack=2, locals=2, args_size=2
         0: aload_0
         1: aload_1
         2: putfield      #38                 // Field endEvent:Lorg/scalatest/events/Event;
         5: return
      LineNumberTable:
        line 649: 0
      LocalVariableTable:
        Start  Length  Slot  Name   Signature
            0       6     0  this   Lorg/scalatest/tools/DashboardReporter$SuiteRecord;
            0       6     1   x$1   Lorg/scalatest/events/Event;
    MethodParameters:
      Name                           Flags
      x$1                            final

  public void addNestedElement(java.lang.Object);
    descriptor: (Ljava/lang/Object;)V
    flags: (0x0001) ACC_PUBLIC
    Code:
      stack=3, locals=2, args_size=2
         0: aload_0
         1: aload_0
         2: invokevirtual #45                 // Method nestedElements:()Lscala/collection/immutable/List;
         5: aload_1
         6: invokevirtual #51                 // Method scala/collection/immutable/List.$colon$colon:(Ljava/lang/Object;)Lscala/collection/immutable/List;
         9: invokevirtual #53                 // Method nestedElements_$eq:(Lscala/collection/immutable/List;)V
        12: return
      LineNumberTable:
        line 656: 0
      LocalVariableTable:
        Start  Length  Slot  Name   Signature
            0      13     0  this   Lorg/scalatest/tools/DashboardReporter$SuiteRecord;
            0      13     1 element   Ljava/lang/Object;
    MethodParameters:
      Name                           Flags
      element                        final

  public void addEndEvent(org.scalatest.events.Event);
    descriptor: (Lorg/scalatest/events/Event;)V
    flags: (0x0001) ACC_PUBLIC
    Code:
      stack=2, locals=2, args_size=2
         0: getstatic     #62                 // Field scala/Predef$.MODULE$:Lscala/Predef$;
         3: aload_0
         4: invokevirtual #64                 // Method endEvent:()Lorg/scalatest/events/Event;
         7: ifnonnull     14
        10: iconst_1
        11: goto          15
        14: iconst_0
        15: invokevirtual #68                 // Method scala/Predef$.require:(Z)V
        18: getstatic     #62                 // Field scala/Predef$.MODULE$:Lscala/Predef$;
        21: aload_1
        22: invokestatic  #72                 // Method isEndEvent$1:(Lorg/scalatest/events/Event;)Z
        25: invokevirtual #68                 // Method scala/Predef$.require:(Z)V
        28: aload_0
        29: aload_1
        30: invokevirtual #74                 // Method endEvent_$eq:(Lorg/scalatest/events/Event;)V
        33: return
      StackMapTable: number_of_entries = 2
        frame_type = 78 /* same_locals_1_stack_item */
          stack = [ class scala/Predef$ ]
        frame_type = 255 /* full_frame */
          offset_delta = 0
          locals = [ class org/scalatest/tools/DashboardReporter$SuiteRecord, class org/scalatest/events/Event ]
          stack = [ class scala/Predef$, int ]
      LineNumberTable:
        line 672: 0
        line 673: 18
        line 675: 28
      LocalVariableTable:
        Start  Length  Slot  Name   Signature
            0      34     0  this   Lorg/scalatest/tools/DashboardReporter$SuiteRecord;
            0      34     1 event   Lorg/scalatest/events/Event;
    MethodParameters:
      Name                           Flags
      event                          final

  public java.lang.String result();
    descriptor: ()Ljava/lang/String;
    flags: (0x0001) ACC_PUBLIC
    Code:
      stack=2, locals=3, args_size=1
         0: aload_0
         1: invokevirtual #64                 // Method endEvent:()Lorg/scalatest/events/Event;
         4: astore_2
         5: aload_2
         6: instanceof    #80                 // class org/scalatest/events/SuiteCompleted
         9: ifeq          18
        12: ldc           #82                 // String completed
        14: astore_1
        15: goto          54
        18: goto          21
        21: aload_2
        22: instanceof    #84                 // class org/scalatest/events/SuiteAborted
        25: ifeq          34
        28: ldc           #86                 // String aborted
        30: astore_1
        31: goto          54
        34: goto          37
        37: aload_0
        38: invokevirtual #90                 // Method org$scalatest$tools$DashboardReporter$SuiteRecord$$$outer:()Lorg/scalatest/tools/DashboardReporter;
        41: aload_0
        42: invokevirtual #64                 // Method endEvent:()Lorg/scalatest/events/Event;
        45: invokevirtual #93                 // Method org/scalatest/tools/DashboardReporter.unexpectedEvent:(Lorg/scalatest/events/Event;)V
        48: ldc           #95                 // String
        50: astore_1
        51: goto          54
        54: aload_1
        55: areturn
      StackMapTable: number_of_entries = 5
        frame_type = 253 /* append */
          offset_delta = 18
          locals = [ top, class org/scalatest/events/Event ]
        frame_type = 2 /* same */
        frame_type = 12 /* same */
        frame_type = 2 /* same */
        frame_type = 255 /* full_frame */
          offset_delta = 16
          locals = [ class org/scalatest/tools/DashboardReporter$SuiteRecord, class java/lang/String, class org/scalatest/events/Event ]
          stack = []
      LineNumberTable:
        line 682: 0
        line 683: 5
        line 684: 21
        line 685: 37
        line 682: 54
      LocalVariableTable:
        Start  Length  Slot  Name   Signature
            0      56     0  this   Lorg/scalatest/tools/DashboardReporter$SuiteRecord;

  public java.lang.String toXml();
    descriptor: ()Ljava/lang/String;
    flags: (0x0001) ACC_PUBLIC
    Code:
      stack=4, locals=5, args_size=1
         0: new           #100                // class scala/collection/mutable/StringBuilder
         3: dup
         4: invokespecial #104                // Method scala/collection/mutable/StringBuilder."<init>":()V
         7: astore_1
         8: aconst_null
         9: invokestatic  #110                // Method scala/runtime/ObjectRef.create:(Ljava/lang/Object;)Lscala/runtime/ObjectRef;
        12: astore_2
        13: aload_0
        14: getfield      #112                // Field startEvent:Lorg/scalatest/events/SuiteStarting;
        17: invokevirtual #117                // Method org/scalatest/events/SuiteStarting.suiteName:()Ljava/lang/String;
        20: ldc           #119                // String DiscoverySuite
        22: astore_3
        23: dup
        24: ifnonnull     35
        27: pop
        28: aload_3
        29: ifnull        53
        32: goto          42
        35: aload_3
        36: invokevirtual #123                // Method java/lang/Object.equals:(Ljava/lang/Object;)Z
        39: ifne          53
        42: aload_1
        43: aload_0
        44: invokespecial #126                // Method formatStartOfSuite$1:()Ljava/lang/String;
        47: invokevirtual #130                // Method scala/collection/mutable/StringBuilder.append:(Ljava/lang/String;)Lscala/collection/mutable/StringBuilder;
        50: goto          56
        53: getstatic     #136                // Field scala/runtime/BoxedUnit.UNIT:Lscala/runtime/BoxedUnit;
        56: pop
        57: aload_0
        58: invokevirtual #45                 // Method nestedElements:()Lscala/collection/immutable/List;
        61: invokevirtual #139                // Method scala/collection/immutable/List.reverse:()Lscala/collection/immutable/List;
        64: aload_0
        65: aload_2
        66: aload_1
        67: invokedynamic #158,  0            // InvokeDynamic #0:apply:(Lorg/scalatest/tools/DashboardReporter$SuiteRecord;Lscala/runtime/ObjectRef;Lscala/collection/mutable/StringBuilder;)Lscala/Function1;
        72: invokevirtual #162                // Method scala/collection/immutable/List.foreach:(Lscala/Function1;)V
        75: aload_0
        76: getfield      #112                // Field startEvent:Lorg/scalatest/events/SuiteStarting;
        79: invokevirtual #117                // Method org/scalatest/events/SuiteStarting.suiteName:()Ljava/lang/String;
        82: ldc           #119                // String DiscoverySuite
        84: astore        4
        86: dup
        87: ifnonnull     99
        90: pop
        91: aload         4
        93: ifnull        116
        96: goto          107
        99: aload         4
       101: invokevirtual #123                // Method java/lang/Object.equals:(Ljava/lang/Object;)Z
       104: ifne          116
       107: aload_1
       108: ldc           #164                // String </suite>\n
       110: invokevirtual #130                // Method scala/collection/mutable/StringBuilder.append:(Ljava/lang/String;)Lscala/collection/mutable/StringBuilder;
       113: goto          119
       116: getstatic     #136                // Field scala/runtime/BoxedUnit.UNIT:Lscala/runtime/BoxedUnit;
       119: pop
       120: aload_1
       121: invokevirtual #167                // Method scala/collection/mutable/StringBuilder.toString:()Ljava/lang/String;
       124: areturn
      StackMapTable: number_of_entries = 8
        frame_type = 255 /* full_frame */
          offset_delta = 35
          locals = [ class org/scalatest/tools/DashboardReporter$SuiteRecord, class scala/collection/mutable/StringBuilder, class scala/runtime/ObjectRef, class java/lang/String ]
          stack = [ class java/lang/String ]
        frame_type = 6 /* same */
        frame_type = 10 /* same */
        frame_type = 66 /* same_locals_1_stack_item */
          stack = [ class java/lang/Object ]
        frame_type = 255 /* full_frame */
          offset_delta = 42
          locals = [ class org/scalatest/tools/DashboardReporter$SuiteRecord, class scala/collection/mutable/StringBuilder, class scala/runtime/ObjectRef, class java/lang/String, class java/lang/String ]
          stack = [ class java/lang/String ]
        frame_type = 7 /* same */
        frame_type = 8 /* same */
        frame_type = 66 /* same_locals_1_stack_item */
          stack = [ class java/lang/Object ]
      LineNumberTable:
        line 693: 0
        line 694: 8
        line 720: 13
        line 721: 42
        line 720: 53
        line 723: 57
        line 740: 75
        line 741: 107
        line 740: 116
        line 743: 120
      LocalVariableTable:
        Start  Length  Slot  Name   Signature
            8     116     1   buf   Lscala/collection/mutable/StringBuilder;
           13     111     2 testRecord   Lscala/runtime/ObjectRef;
            0     125     0  this   Lorg/scalatest/tools/DashboardReporter$SuiteRecord;

  public org.scalatest.tools.DashboardReporter org$scalatest$tools$DashboardReporter$SuiteRecord$$$outer();
    descriptor: ()Lorg/scalatest/tools/DashboardReporter;
    flags: (0x1001) ACC_PUBLIC, ACC_SYNTHETIC
    Code:
      stack=1, locals=1, args_size=1
         0: aload_0
         1: getfield      #173                // Field $outer:Lorg/scalatest/tools/DashboardReporter;
         4: areturn
      LineNumberTable:
        line 647: 0
      LocalVariableTable:
        Start  Length  Slot  Name   Signature
            0       5     0  this   Lorg/scalatest/tools/DashboardReporter$SuiteRecord;

  private static final boolean isEndEvent$1(org.scalatest.events.Event);
    descriptor: (Lorg/scalatest/events/Event;)Z
    flags: (0x001a) ACC_PRIVATE, ACC_STATIC, ACC_FINAL
    Code:
      stack=1, locals=3, args_size=1
         0: aload_0
         1: astore_2
         2: aload_2
         3: instanceof    #80                 // class org/scalatest/events/SuiteCompleted
         6: ifeq          14
         9: iconst_1
        10: istore_1
        11: goto          37
        14: goto          17
        17: aload_2
        18: instanceof    #84                 // class org/scalatest/events/SuiteAborted
        21: ifeq          29
        24: iconst_1
        25: istore_1
        26: goto          37
        29: goto          32
        32: iconst_0
        33: istore_1
        34: goto          37
        37: iload_1
        38: ireturn
      StackMapTable: number_of_entries = 5
        frame_type = 253 /* append */
          offset_delta = 14
          locals = [ top, class org/scalatest/events/Event ]
        frame_type = 2 /* same */
        frame_type = 11 /* same */
        frame_type = 2 /* same */
        frame_type = 255 /* full_frame */
          offset_delta = 4
          locals = [ class org/scalatest/events/Event, int, class org/scalatest/events/Event ]
          stack = []
      LineNumberTable:
        line 665: 0
        line 666: 2
        line 667: 17
        line 668: 32
        line 665: 37
      LocalVariableTable:
        Start  Length  Slot  Name   Signature
            0      39     0     e   Lorg/scalatest/events/Event;
    MethodParameters:
      Name                           Flags
      e                              final

  private final java.lang.String formatStartOfSuite$1();
    descriptor: ()Ljava/lang/String;
    flags: (0x0012) ACC_PRIVATE, ACC_FINAL
    Code:
      stack=4, locals=3, args_size=1
         0: aload_0
         1: invokevirtual #64                 // Method endEvent:()Lorg/scalatest/events/Event;
         4: invokevirtual #178                // Method org/scalatest/events/Event.timeStamp:()J
         7: aload_0
         8: getfield      #112                // Field startEvent:Lorg/scalatest/events/SuiteStarting;
        11: invokevirtual #179                // Method org/scalatest/events/SuiteStarting.timeStamp:()J
        14: lsub
        15: lstore_1
        16: new           #181                // class java/lang/StringBuilder
        19: dup
        20: ldc           #182                // int 64
        22: invokespecial #185                // Method java/lang/StringBuilder."<init>":(I)V
        25: ldc           #187                // String \n<suite index=\"
        27: invokevirtual #190                // Method java/lang/StringBuilder.append:(Ljava/lang/String;)Ljava/lang/StringBuilder;
        30: aload_0
        31: invokevirtual #90                 // Method org$scalatest$tools$DashboardReporter$SuiteRecord$$$outer:()Lorg/scalatest/tools/DashboardReporter;
        34: invokevirtual #194                // Method org/scalatest/tools/DashboardReporter.nextIndex:()I
        37: invokevirtual #197                // Method java/lang/StringBuilder.append:(I)Ljava/lang/StringBuilder;
        40: ldc           #199                // String \"
        42: invokevirtual #190                // Method java/lang/StringBuilder.append:(Ljava/lang/String;)Ljava/lang/StringBuilder;
        45: ldc           #201                // String id=\"
        47: invokevirtual #190                // Method java/lang/StringBuilder.append:(Ljava/lang/String;)Ljava/lang/StringBuilder;
        50: aload_0
        51: getfield      #112                // Field startEvent:Lorg/scalatest/events/SuiteStarting;
        54: invokevirtual #204                // Method org/scalatest/events/SuiteStarting.suiteId:()Ljava/lang/String;
        57: invokevirtual #190                // Method java/lang/StringBuilder.append:(Ljava/lang/String;)Ljava/lang/StringBuilder;
        60: ldc           #199                // String \"
        62: invokevirtual #190                // Method java/lang/StringBuilder.append:(Ljava/lang/String;)Ljava/lang/StringBuilder;
        65: ldc           #206                // String result=\"
        67: invokevirtual #190                // Method java/lang/StringBuilder.append:(Ljava/lang/String;)Ljava/lang/StringBuilder;
        70: aload_0
        71: invokevirtual #208                // Method result:()Ljava/lang/String;
        74: invokevirtual #190                // Method java/lang/StringBuilder.append:(Ljava/lang/String;)Ljava/lang/StringBuilder;
        77: ldc           #199                // String \"
        79: invokevirtual #190                // Method java/lang/StringBuilder.append:(Ljava/lang/String;)Ljava/lang/StringBuilder;
        82: ldc           #210                // String name=\"
        84: invokevirtual #190                // Method java/lang/StringBuilder.append:(Ljava/lang/String;)Ljava/lang/StringBuilder;
        87: aload_0
        88: invokevirtual #90                 // Method org$scalatest$tools$DashboardReporter$SuiteRecord$$$outer:()Lorg/scalatest/tools/DashboardReporter;
        91: aload_0
        92: getfield      #112                // Field startEvent:Lorg/scalatest/events/SuiteStarting;
        95: invokevirtual #117                // Method org/scalatest/events/SuiteStarting.suiteName:()Ljava/lang/String;
        98: invokevirtual #214                // Method org/scalatest/tools/DashboardReporter.escape:(Ljava/lang/String;)Ljava/lang/String;
       101: invokevirtual #190                // Method java/lang/StringBuilder.append:(Ljava/lang/String;)Ljava/lang/StringBuilder;
       104: ldc           #199                // String \"
       106: invokevirtual #190                // Method java/lang/StringBuilder.append:(Ljava/lang/String;)Ljava/lang/StringBuilder;
       109: ldc           #216                // String duration=\"
       111: invokevirtual #190                // Method java/lang/StringBuilder.append:(Ljava/lang/String;)Ljava/lang/StringBuilder;
       114: lload_1
       115: invokevirtual #219                // Method java/lang/StringBuilder.append:(J)Ljava/lang/StringBuilder;
       118: ldc           #199                // String \"
       120: invokevirtual #190                // Method java/lang/StringBuilder.append:(Ljava/lang/String;)Ljava/lang/StringBuilder;
       123: ldc           #221                // String thread=\"
       125: invokevirtual #190                // Method java/lang/StringBuilder.append:(Ljava/lang/String;)Ljava/lang/StringBuilder;
       128: aload_0
       129: getfield      #112                // Field startEvent:Lorg/scalatest/events/SuiteStarting;
       132: invokevirtual #224                // Method org/scalatest/events/SuiteStarting.threadName:()Ljava/lang/String;
       135: invokevirtual #190                // Method java/lang/StringBuilder.append:(Ljava/lang/String;)Ljava/lang/StringBuilder;
       138: ldc           #226                // String \">\n
       140: invokevirtual #190                // Method java/lang/StringBuilder.append:(Ljava/lang/String;)Ljava/lang/StringBuilder;
       143: invokevirtual #227                // Method java/lang/StringBuilder.toString:()Ljava/lang/String;
       146: areturn
      LineNumberTable:
        line 700: 0
        line 707: 16
        line 701: 25
        line 702: 30
        line 703: 45
        line 704: 65
        line 705: 82
        line 706: 109
        line 707: 123
      LocalVariableTable:
        Start  Length  Slot  Name   Signature
           16     130     1 duration   J
            0     147     0  this   Lorg/scalatest/tools/DashboardReporter$SuiteRecord;

  private static final boolean inATest$1(scala.runtime.ObjectRef);
    descriptor: (Lscala/runtime/ObjectRef;)Z
    flags: (0x001a) ACC_PRIVATE, ACC_STATIC, ACC_FINAL
    Code:
      stack=1, locals=1, args_size=1
         0: aload_0
         1: getfield      #235                // Field scala/runtime/ObjectRef.elem:Ljava/lang/Object;
         4: checkcast     #15                 // class org/scalatest/tools/DashboardReporter$TestRecord
         7: ifnull        27
        10: aload_0
        11: getfield      #235                // Field scala/runtime/ObjectRef.elem:Ljava/lang/Object;
        14: checkcast     #15                 // class org/scalatest/tools/DashboardReporter$TestRecord
        17: invokevirtual #236                // Method org/scalatest/tools/DashboardReporter$TestRecord.endEvent:()Lorg/scalatest/events/Event;
        20: ifnonnull     27
        23: iconst_1
        24: goto          28
        27: iconst_0
        28: ireturn
      StackMapTable: number_of_entries = 2
        frame_type = 27 /* same */
        frame_type = 64 /* same_locals_1_stack_item */
          stack = [ int ]
      LineNumberTable:
        line 715: 0
      LocalVariableTable:
        Start  Length  Slot  Name   Signature
            0      29     0 testRecord$1   Lscala/runtime/ObjectRef;
    MethodParameters:
      Name                           Flags
      testRecord$1                   final

  public static final java.lang.Object $anonfun$toXml$1(org.scalatest.tools.DashboardReporter$SuiteRecord, scala.runtime.ObjectRef, scala.collection.mutable.StringBuilder, java.lang.Object);
    descriptor: (Lorg/scalatest/tools/DashboardReporter$SuiteRecord;Lscala/runtime/ObjectRef;Lscala/collection/mutable/StringBuilder;Ljava/lang/Object;)Ljava/lang/Object;
    flags: (0x1019) ACC_PUBLIC, ACC_STATIC, ACC_FINAL, ACC_SYNTHETIC
    Code:
      stack=5, locals=9, args_size=4
         0: aload_1
         1: invokestatic  #240                // Method inATest$1:(Lscala/runtime/ObjectRef;)Z
         4: ifeq          57
         7: aload_1
         8: getfield      #235                // Field scala/runtime/ObjectRef.elem:Ljava/lang/Object;
        11: checkcast     #15                 // class org/scalatest/tools/DashboardReporter$TestRecord
        14: aload_3
        15: checkcast     #76                 // class org/scalatest/events/Event
        18: invokevirtual #243                // Method org/scalatest/tools/DashboardReporter$TestRecord.addEvent:(Lorg/scalatest/events/Event;)V
        21: aload_1
        22: getfield      #235                // Field scala/runtime/ObjectRef.elem:Ljava/lang/Object;
        25: checkcast     #15                 // class org/scalatest/tools/DashboardReporter$TestRecord
        28: invokevirtual #247                // Method org/scalatest/tools/DashboardReporter$TestRecord.isComplete:()Z
        31: ifeq          51
        34: aload_2
        35: aload_1
        36: getfield      #235                // Field scala/runtime/ObjectRef.elem:Ljava/lang/Object;
        39: checkcast     #15                 // class org/scalatest/tools/DashboardReporter$TestRecord
        42: invokevirtual #249                // Method org/scalatest/tools/DashboardReporter$TestRecord.toXml:()Ljava/lang/String;
        45: invokevirtual #130                // Method scala/collection/mutable/StringBuilder.append:(Ljava/lang/String;)Lscala/collection/mutable/StringBuilder;
        48: goto          54
        51: getstatic     #136                // Field scala/runtime/BoxedUnit.UNIT:Lscala/runtime/BoxedUnit;
        54: goto          225
        57: aload_3
        58: astore        5
        60: aload         5
        62: instanceof    #251                // class org/scalatest/events/TestIgnored
        65: ifeq          93
        68: aload         5
        70: checkcast     #251                // class org/scalatest/events/TestIgnored
        73: astore        6
        75: aload_2
        76: aload_0
        77: invokevirtual #90                 // Method org$scalatest$tools$DashboardReporter$SuiteRecord$$$outer:()Lorg/scalatest/tools/DashboardReporter;
        80: aload         6
        82: invokevirtual #255                // Method org/scalatest/tools/DashboardReporter.formatTestIgnored:(Lorg/scalatest/events/TestIgnored;)Ljava/lang/String;
        85: invokevirtual #130                // Method scala/collection/mutable/StringBuilder.append:(Ljava/lang/String;)Lscala/collection/mutable/StringBuilder;
        88: astore        4
        90: goto          223
        93: goto          96
        96: aload         5
        98: instanceof    #2                  // class org/scalatest/tools/DashboardReporter$SuiteRecord
       101: ifeq          140
       104: aload         5
       106: checkcast     #2                  // class org/scalatest/tools/DashboardReporter$SuiteRecord
       109: invokevirtual #90                 // Method org$scalatest$tools$DashboardReporter$SuiteRecord$$$outer:()Lorg/scalatest/tools/DashboardReporter;
       112: aload_0
       113: invokevirtual #90                 // Method org$scalatest$tools$DashboardReporter$SuiteRecord$$$outer:()Lorg/scalatest/tools/DashboardReporter;
       116: if_acmpne     140
       119: aload         5
       121: checkcast     #2                  // class org/scalatest/tools/DashboardReporter$SuiteRecord
       124: astore        7
       126: aload_2
       127: aload         7
       129: invokevirtual #256                // Method toXml:()Ljava/lang/String;
       132: invokevirtual #130                // Method scala/collection/mutable/StringBuilder.append:(Ljava/lang/String;)Lscala/collection/mutable/StringBuilder;
       135: astore        4
       137: goto          223
       140: goto          143
       143: aload         5
       145: instanceof    #258                // class org/scalatest/events/TestStarting
       148: ifeq          183
       151: aload         5
       153: checkcast     #258                // class org/scalatest/events/TestStarting
       156: astore        8
       158: aload_1
       159: new           #15                 // class org/scalatest/tools/DashboardReporter$TestRecord
       162: dup
       163: aload_0
       164: invokevirtual #90                 // Method org$scalatest$tools$DashboardReporter$SuiteRecord$$$outer:()Lorg/scalatest/tools/DashboardReporter;
       167: aload         8
       169: invokespecial #261                // Method org/scalatest/tools/DashboardReporter$TestRecord."<init>":(Lorg/scalatest/tools/DashboardReporter;Lorg/scalatest/events/TestStarting;)V
       172: putfield      #235                // Field scala/runtime/ObjectRef.elem:Ljava/lang/Object;
       175: getstatic     #136                // Field scala/runtime/BoxedUnit.UNIT:Lscala/runtime/BoxedUnit;
       178: astore        4
       180: goto          223
       183: goto          186
       186: new           #263                // class java/lang/RuntimeException
       189: dup
       190: new           #181                // class java/lang/StringBuilder
       193: dup
       194: ldc_w         #264                // int 13
       197: invokespecial #185                // Method java/lang/StringBuilder."<init>":(I)V
       200: ldc_w         #266                // String unexpected [
       203: invokevirtual #190                // Method java/lang/StringBuilder.append:(Ljava/lang/String;)Ljava/lang/StringBuilder;
       206: aload_3
       207: invokevirtual #269                // Method java/lang/StringBuilder.append:(Ljava/lang/Object;)Ljava/lang/StringBuilder;
       210: ldc_w         #271                // String ]
       213: invokevirtual #190                // Method java/lang/StringBuilder.append:(Ljava/lang/String;)Ljava/lang/StringBuilder;
       216: invokevirtual #227                // Method java/lang/StringBuilder.toString:()Ljava/lang/String;
       219: invokespecial #274                // Method java/lang/RuntimeException."<init>":(Ljava/lang/String;)V
       222: athrow
       223: aload         4
       225: areturn
      StackMapTable: number_of_entries = 11
        frame_type = 51 /* same */
        frame_type = 66 /* same_locals_1_stack_item */
          stack = [ class java/lang/Object ]
        frame_type = 2 /* same */
        frame_type = 253 /* append */
          offset_delta = 35
          locals = [ top, class java/lang/Object ]
        frame_type = 2 /* same */
        frame_type = 43 /* same */
        frame_type = 2 /* same */
        frame_type = 39 /* same */
        frame_type = 2 /* same */
        frame_type = 255 /* full_frame */
          offset_delta = 36
          locals = [ class org/scalatest/tools/DashboardReporter$SuiteRecord, class scala/runtime/ObjectRef, class scala/collection/mutable/StringBuilder, class java/lang/Object, class java/lang/Object, class java/lang/Object ]
          stack = []
        frame_type = 255 /* full_frame */
          offset_delta = 1
          locals = [ class org/scalatest/tools/DashboardReporter$SuiteRecord, class scala/runtime/ObjectRef, class scala/collection/mutable/StringBuilder, class java/lang/Object ]
          stack = [ class java/lang/Object ]
      LineNumberTable:
        line 724: 0
        line 725: 7
        line 727: 21
        line 728: 34
        line 727: 51
        line 731: 57
        line 732: 60
        line 733: 96
        line 734: 143
        line 736: 186
        line 731: 223
      LocalVariableTable:
        Start  Length  Slot  Name   Signature
            0     226     0 $this   Lorg/scalatest/tools/DashboardReporter$SuiteRecord;
            0     226     1 testRecord$1   Lscala/runtime/ObjectRef;
            0     226     2 buf$4   Lscala/collection/mutable/StringBuilder;
            0     226     3 element   Ljava/lang/Object;
    MethodParameters:
      Name                           Flags
      $this                          final synthetic
      testRecord$1                   final
      buf$4                          final
      element                        final

  public org.scalatest.tools.DashboardReporter$SuiteRecord(org.scalatest.tools.DashboardReporter, org.scalatest.events.SuiteStarting);
    descriptor: (Lorg/scalatest/tools/DashboardReporter;Lorg/scalatest/events/SuiteStarting;)V
    flags: (0x0001) ACC_PUBLIC
    Code:
      stack=3, locals=3, args_size=3
         0: aload_0
         1: aload_2
         2: putfield      #112                // Field startEvent:Lorg/scalatest/events/SuiteStarting;
         5: aload_1
         6: ifnonnull     11
         9: aconst_null
        10: athrow
        11: aload_0
        12: aload_1
        13: putfield      #173                // Field $outer:Lorg/scalatest/tools/DashboardReporter;
        16: aload_0
        17: invokespecial #276                // Method java/lang/Object."<init>":()V
        20: aload_0
        21: getstatic     #281                // Field scala/package$.MODULE$:Lscala/package$;
        24: invokevirtual #285                // Method scala/package$.List:()Lscala/collection/immutable/List$;
        27: getstatic     #290                // Field scala/collection/immutable/Nil$.MODULE$:Lscala/collection/immutable/Nil$;
        30: invokevirtual #295                // Method scala/collection/immutable/List$.apply:(Lscala/collection/immutable/Seq;)Ljava/lang/Object;
        33: checkcast     #47                 // class scala/collection/immutable/List
        36: putfield      #29                 // Field nestedElements:Lscala/collection/immutable/List;
        39: aload_0
        40: aconst_null
        41: putfield      #38                 // Field endEvent:Lorg/scalatest/events/Event;
        44: return
      StackMapTable: number_of_entries = 1
        frame_type = 11 /* same */
      LineNumberTable:
        line 647: 0
        line 758: 16
        line 648: 20
        line 649: 39
        line 647: 44
      LocalVariableTable:
        Start  Length  Slot  Name   Signature
            0      45     0  this   Lorg/scalatest/tools/DashboardReporter$SuiteRecord;
            0      45     1 $outer   Lorg/scalatest/tools/DashboardReporter;
            0      45     2 startEvent   Lorg/scalatest/events/SuiteStarting;
    MethodParameters:
      Name                           Flags
      $outer                         final synthetic
      startEvent                     final

  private static java.lang.Object $deserializeLambda$(java.lang.invoke.SerializedLambda);
    descriptor: (Ljava/lang/invoke/SerializedLambda;)Ljava/lang/Object;
    flags: (0x100a) ACC_PRIVATE, ACC_STATIC, ACC_SYNTHETIC
    Code:
      stack=1, locals=1, args_size=1
         0: aload_0
         1: invokedynamic #307,  0            // InvokeDynamic #1:lambdaDeserialize:(Ljava/lang/invoke/SerializedLambda;)Ljava/lang/Object;
         6: areturn
}
InnerClasses:
  public static final #10= #7 of #9;      // Lookup=class java/lang/invoke/MethodHandles$Lookup of class java/lang/invoke/MethodHandles
  public #13= #2 of #12;                  // SuiteRecord=class org/scalatest/tools/DashboardReporter$SuiteRecord of class org/scalatest/tools/DashboardReporter
  public #16= #15 of #12;                 // TestRecord=class org/scalatest/tools/DashboardReporter$TestRecord of class org/scalatest/tools/DashboardReporter
SourceFile: "DashboardReporter.scala"
BootstrapMethods:
  0: #154 REF_invokeStatic java/lang/invoke/LambdaMetafactory.altMetafactory:(Ljava/lang/invoke/MethodHandles$Lookup;Ljava/lang/String;Ljava/lang/invoke/MethodType;[Ljava/lang/Object;)Ljava/lang/invoke/CallSite;
    Method arguments:
      #141 (Ljava/lang/Object;)Ljava/lang/Object;
      #146 REF_invokeStatic org/scalatest/tools/DashboardReporter$SuiteRecord.$anonfun$toXml$1:(Lorg/scalatest/tools/DashboardReporter$SuiteRecord;Lscala/runtime/ObjectRef;Lscala/collection/mutable/StringBuilder;Ljava/lang/Object;)Ljava/lang/Object;
      #141 (Ljava/lang/Object;)Ljava/lang/Object;
      #147 1
  1: #304 REF_invokeStatic scala/runtime/LambdaDeserialize.bootstrap:(Ljava/lang/invoke/MethodHandles$Lookup;Ljava/lang/String;Ljava/lang/invoke/MethodType;[Ljava/lang/invoke/MethodHandle;)Ljava/lang/invoke/CallSite;
    Method arguments:
      #146 REF_invokeStatic org/scalatest/tools/DashboardReporter$SuiteRecord.$anonfun$toXml$1:(Lorg/scalatest/tools/DashboardReporter$SuiteRecord;Lscala/runtime/ObjectRef;Lscala/collection/mutable/StringBuilder;Ljava/lang/Object;)Ljava/lang/Object;
  ScalaInlineInfo: length = 0x4A (unknown attribute)
   01 00 00 0E 00 8E 00 8F 01 00 65 01 13 00 00 37
   00 28 00 00 29 00 2A 00 00 16 00 24 00 00 27 00
   28 00 00 7C 00 4E 01 00 E6 00 E7 01 00 45 00 46
   01 00 13 00 1A 00 00 20 00 21 00 00 57 00 58 00
   00 4D 00 4E 00 00 62 00 4E 00
  Scala: length = 0x0 (unknown attribute)

