Classfile /Users/mw/Projects/slang-braindump/.jar/jar11/assemble/slang-braindump/assemble/content/org/scalatest/tools/DiscoverySuite.class
  Last modified May 29, 2022; size 23963 bytes
  SHA-256 checksum 10db4c06c145790ae15cdb09139367ad817eeb20680a56ea3ff34dd66e1dbea1
  Compiled from "DiscoverySuite.scala"
public class org.scalatest.tools.DiscoverySuite implements org.scalatest.Suite
  minor version: 0
  major version: 52
  flags: (0x0021) ACC_PUBLIC, ACC_SUPER
  this_class: #2                          // org/scalatest/tools/DiscoverySuite
  super_class: #4                         // java/lang/Object
  interfaces: 1, fields: 5, methods: 64, attributes: 6
Constant pool:
    #1 = Utf8               org/scalatest/tools/DiscoverySuite
    #2 = Class              #1            // org/scalatest/tools/DiscoverySuite
    #3 = Utf8               java/lang/Object
    #4 = Class              #3            // java/lang/Object
    #5 = Utf8               org/scalatest/Suite
    #6 = Class              #5            // org/scalatest/Suite
    #7 = Utf8               DiscoverySuite.scala
    #8 = Utf8               Lscala/reflect/ScalaSignature;
    #9 = Utf8               bytes
   #10 = Utf8               \u0006\u0005\u0005ma!B\n\u0015\u0001YQ\u0002\u0002C\u0013\u0001\u0005\u0003\u0005\u000b\u0011B\u0014\t\u0011I\u0002!\u0011!Q\u0001\nMB\u0001B\u000e\u0001\u0003\u0002\u0003\u0006Ia\u000e\u0005\tu\u0001\u0011\t\u0011)A\u0005w!)1\t\u0001C\u0001\t\"91\n\u0001b\u0001\n\u0003b\u0005BB(\u0001A\u0003%Q\nC\u0004Q\u0001\t\u0007I\u0011I)\t\ri\u0003\u0001\u0015!\u0003S\u0011\u0015Y\u0006\u0001\"\u0015]\u000f\u0019QG\u0003#\u0001\u0017W\u001a11\u0003\u0006E\u0001-1DQa\u0011\u0007\u0005\u0002MDQ\u0001\u001e\u0007\u0005\nUDQ\u0001\u001f\u0007\u0005\neDa\u0001 \u0007\u0005\u0002Yi\b\u0002CA\u0003\u0019\u0011\u0005a#a\u0002\t\u0013\u0005EA\"!A\u0005\n\u0005M!A\u0004#jg\u000e|g/\u001a:z\'VLG/\u001a\u0006\u0003+Y\tQ\u0001^8pYNT!a\u0006\r\u0002\u0013M\u001c\u0017\r\\1uKN$(\"A\r\u0002\u0007=\u0014xmE\u0002\u00017\u0005\u0002\"\u0001H\u0010\u000e\u0003uQ\u0011AH\u0001\u0006g\u000e\fG.Y\u0005\u0003Au\u0011a!\u00118z%\u00164\u0007C\u0001\u0012$\u001b\u00051\u0012B\u0001\u0013\u0017\u0005\u0015\u0019V/\u001b;f\u0003\u0011\u0001\u0018\r\u001e5\u0004\u0001A\u0011\u0001f\f\b\u0003S5\u0002\"AK\u000f\u000e\u0003-R!\u0001\f\u0014\u0002\rq\u0012xn\u001c;?\u0013\tqS$\u0001\u0004Qe\u0016$WMZ\u0005\u0003aE\u0012aa\u0015;sS:<\'B\u0001\u0018\u001e\u0003A\t7mY3tg&\u0014G.Z*vSR,7\u000fE\u0002)i\u001dJ!!N\u0019\u0003\u0007M+G/\u0001\u0005xS2$7-\u0019:e!\ta\u0002(\u0003\u0002:;\t9!i\\8mK\u0006t\u0017A\u0005:v]B\fG\u000f[\"mCN\u001cHj\\1eKJ\u0004\"\u0001P!\u000e\u0003uR!AP \u0002\t1\fgn\u001a\u0006\u0002\u0001\u0006!!.\u0019<b\u0013\t\u0011UHA\u0006DY\u0006\u001c8\u000fT8bI\u0016\u0014\u0018A\u0002\u001fj]&$h\bF\u0003F\u000f\"K%\n\u0005\u0002G\u00015\tA\u0003C\u0003&\u000b\u0001\u0007q\u0005C\u00033\u000b\u0001\u00071\u0007C\u00037\u000b\u0001\u0007q\u0007C\u0003;\u000b\u0001\u00071(A\u0004tk&$X-\u00133\u0016\u00035\u0003\"\u0001\u0010(\n\u0005Aj\u0014\u0001C:vSR,\u0017\n\u001a\u0011\u0002\u00199,7\u000f^3e\'VLG/Z:\u0016\u0003I\u00032a\u0015-\"\u001b\u0005!&BA+W\u0003%IW.\\;uC\ndWM\u0003\u0002X;\u0005Q1m\u001c7mK\u000e$\u0018n\u001c8\n\u0005e#&AC%oI\u0016DX\rZ*fc\u0006ia.Z:uK\u0012\u001cV/\u001b;fg\u0002\n\u0001B];o)\u0016\u001cHo\u001d\u000b\u0004;\u0002,\u0007C\u0001\u0012_\u0013\tyfC\u0001\u0004Ti\u0006$Xo\u001d\u0005\u0006C*\u0001\rAY\u0001\ti\u0016\u001cHOT1nKB\u0019AdY\u0014\n\u0005\u0011l\"AB(qi&|g\u000eC\u0003g\u0015\u0001\u0007q-\u0001\u0003be\u001e\u001c\bC\u0001\u0012i\u0013\tIgC\u0001\u0003Be\u001e\u001c\u0018A\u0004#jg\u000e|g/\u001a:z\'VLG/\u001a\t\u0003\r2\u00192\u0001D\u000en!\tq\u0017/D\u0001p\u0015\t\u0001x(\u0001\u0002j_&\u0011!o\u001c\u0002\r\'\u0016\u0014\u0018.\u00197ju\u0006\u0014G.\u001a\u000b\u0002W\u0006aq/\u001b7eG\u0006\u0014H\rT5tiR\u00191G^<\t\u000b\u0015r\u0001\u0019A\u0014\t\u000bIr\u0001\u0019A\u001a\u0002\u00159\f\'O]8x\u0019&\u001cH\u000fF\u00024unDQ!J\bA\u0002\u001dBQAM\bA\u0002M\n\u0001C\\3ti\u0016$7+^5uK:\u000bW.Z:\u0015\ry|\u0018\u0011AA\u0002!\r\u0019\u0006l\n\u0005\u0006KA\u0001\ra\n\u0005\u0006eA\u0001\ra\r\u0005\u0006mA\u0001\raN\u0001\u0011O\u0016$8+^5uK&s7\u000f^1oG\u0016$R!IA\u0005\u0003\u001bAa!a\u0003\u0012\u0001\u00049\u0013AD:vSR,7\t\\1tg:\u000bW.\u001a\u0005\u0007\u0003\u001f\t\u0002\u0019A\u001e\u0002\r1|\u0017\rZ3s\u000319(/\u001b;f%\u0016\u0004H.Y2f)\t\t)\u0002E\u0002=\u0003/I1!!\u0007>\u0005\u0019y%M[3di\u0002
   #11 = Utf8               java/lang/invoke/MethodHandles$Lookup
   #12 = Class              #11           // java/lang/invoke/MethodHandles$Lookup
   #13 = Utf8               java/lang/invoke/MethodHandles
   #14 = Class              #13           // java/lang/invoke/MethodHandles
   #15 = Utf8               Lookup
   #16 = Utf8               org/scalactic/Requirements$RequirementsHelper
   #17 = Class              #16           // org/scalactic/Requirements$RequirementsHelper
   #18 = Utf8               org/scalactic/Requirements
   #19 = Class              #18           // org/scalactic/Requirements
   #20 = Utf8               RequirementsHelper
   #21 = Utf8               org/scalactic/TripleEqualsSupport$CheckingEqualizer
   #22 = Class              #21           // org/scalactic/TripleEqualsSupport$CheckingEqualizer
   #23 = Utf8               org/scalactic/TripleEqualsSupport
   #24 = Class              #23           // org/scalactic/TripleEqualsSupport
   #25 = Utf8               CheckingEqualizer
   #26 = Utf8               org/scalactic/TripleEqualsSupport$Equalizer
   #27 = Class              #26           // org/scalactic/TripleEqualsSupport$Equalizer
   #28 = Utf8               Equalizer
   #29 = Utf8               org/scalactic/TripleEqualsSupport$Spread
   #30 = Class              #29           // org/scalactic/TripleEqualsSupport$Spread
   #31 = Utf8               Spread
   #32 = Utf8               org/scalactic/TripleEqualsSupport$TripleEqualsInvocation
   #33 = Class              #32           // org/scalactic/TripleEqualsSupport$TripleEqualsInvocation
   #34 = Utf8               TripleEqualsInvocation
   #35 = Utf8               org/scalactic/TripleEqualsSupport$TripleEqualsInvocationOnSpread
   #36 = Class              #35           // org/scalactic/TripleEqualsSupport$TripleEqualsInvocationOnSpread
   #37 = Utf8               TripleEqualsInvocationOnSpread
   #38 = Utf8               runpathClassLoader
   #39 = Utf8               Ljava/lang/ClassLoader;
   #40 = Utf8               suiteId
   #41 = Utf8               Ljava/lang/String;
   #42 = Utf8               nestedSuites
   #43 = Utf8               Lscala/collection/immutable/IndexedSeq;
   #44 = Utf8               Lscala/collection/immutable/IndexedSeq<Lorg/scalatest/Suite;>;
   #45 = Utf8               styleName
   #46 = Utf8               succeed
   #47 = Utf8               Lorg/scalatest/compatible/Assertion;
   #48 = Utf8               execute
   #49 = Utf8               (Ljava/lang/String;Lorg/scalatest/ConfigMap;ZZZZZ)V
   #50 = Utf8               testName
   #51 = Utf8               configMap
   #52 = Utf8               color
   #53 = Utf8               durations
   #54 = Utf8               shortstacks
   #55 = Utf8               fullstacks
   #56 = Utf8               stats
   #57 = Utf8               execute$
   #58 = Utf8               (Lorg/scalatest/Suite;Ljava/lang/String;Lorg/scalatest/ConfigMap;ZZZZZ)V
   #59 = NameAndType        #57:#58       // execute$:(Lorg/scalatest/Suite;Ljava/lang/String;Lorg/scalatest/ConfigMap;ZZZZZ)V
   #60 = InterfaceMethodref #6.#59        // org/scalatest/Suite.execute$:(Lorg/scalatest/Suite;Ljava/lang/String;Lorg/scalatest/ConfigMap;ZZZZZ)V
   #61 = Utf8               this
   #62 = Utf8               Lorg/scalatest/tools/DiscoverySuite;
   #63 = Utf8               Lorg/scalatest/ConfigMap;
   #64 = Utf8               Z
   #65 = Utf8               execute$default$1
   #66 = Utf8               ()Ljava/lang/String;
   #67 = Utf8               execute$default$1$
   #68 = Utf8               (Lorg/scalatest/Suite;)Ljava/lang/String;
   #69 = NameAndType        #67:#68       // execute$default$1$:(Lorg/scalatest/Suite;)Ljava/lang/String;
   #70 = InterfaceMethodref #6.#69        // org/scalatest/Suite.execute$default$1$:(Lorg/scalatest/Suite;)Ljava/lang/String;
   #71 = Utf8               execute$default$2
   #72 = Utf8               ()Lorg/scalatest/ConfigMap;
   #73 = Utf8               execute$default$2$
   #74 = Utf8               (Lorg/scalatest/Suite;)Lorg/scalatest/ConfigMap;
   #75 = NameAndType        #73:#74       // execute$default$2$:(Lorg/scalatest/Suite;)Lorg/scalatest/ConfigMap;
   #76 = InterfaceMethodref #6.#75        // org/scalatest/Suite.execute$default$2$:(Lorg/scalatest/Suite;)Lorg/scalatest/ConfigMap;
   #77 = Utf8               execute$default$3
   #78 = Utf8               ()Z
   #79 = Utf8               execute$default$3$
   #80 = Utf8               (Lorg/scalatest/Suite;)Z
   #81 = NameAndType        #79:#80       // execute$default$3$:(Lorg/scalatest/Suite;)Z
   #82 = InterfaceMethodref #6.#81        // org/scalatest/Suite.execute$default$3$:(Lorg/scalatest/Suite;)Z
   #83 = Utf8               execute$default$4
   #84 = Utf8               execute$default$4$
   #85 = NameAndType        #84:#80       // execute$default$4$:(Lorg/scalatest/Suite;)Z
   #86 = InterfaceMethodref #6.#85        // org/scalatest/Suite.execute$default$4$:(Lorg/scalatest/Suite;)Z
   #87 = Utf8               execute$default$5
   #88 = Utf8               execute$default$5$
   #89 = NameAndType        #88:#80       // execute$default$5$:(Lorg/scalatest/Suite;)Z
   #90 = InterfaceMethodref #6.#89        // org/scalatest/Suite.execute$default$5$:(Lorg/scalatest/Suite;)Z
   #91 = Utf8               execute$default$6
   #92 = Utf8               execute$default$6$
   #93 = NameAndType        #92:#80       // execute$default$6$:(Lorg/scalatest/Suite;)Z
   #94 = InterfaceMethodref #6.#93        // org/scalatest/Suite.execute$default$6$:(Lorg/scalatest/Suite;)Z
   #95 = Utf8               execute$default$7
   #96 = Utf8               execute$default$7$
   #97 = NameAndType        #96:#80       // execute$default$7$:(Lorg/scalatest/Suite;)Z
   #98 = InterfaceMethodref #6.#97        // org/scalatest/Suite.execute$default$7$:(Lorg/scalatest/Suite;)Z
   #99 = Utf8               tags
  #100 = Utf8               ()Lscala/collection/immutable/Map;
  #101 = Utf8               ()Lscala/collection/immutable/Map<Ljava/lang/String;Lscala/collection/immutable/Set<Ljava/lang/String;>;>;
  #102 = Utf8               tags$
  #103 = Utf8               (Lorg/scalatest/Suite;)Lscala/collection/immutable/Map;
  #104 = NameAndType        #102:#103     // tags$:(Lorg/scalatest/Suite;)Lscala/collection/immutable/Map;
  #105 = InterfaceMethodref #6.#104       // org/scalatest/Suite.tags$:(Lorg/scalatest/Suite;)Lscala/collection/immutable/Map;
  #106 = Utf8               testNames
  #107 = Utf8               ()Lscala/collection/immutable/Set;
  #108 = Utf8               ()Lscala/collection/immutable/Set<Ljava/lang/String;>;
  #109 = Utf8               testNames$
  #110 = Utf8               (Lorg/scalatest/Suite;)Lscala/collection/immutable/Set;
  #111 = NameAndType        #109:#110     // testNames$:(Lorg/scalatest/Suite;)Lscala/collection/immutable/Set;
  #112 = InterfaceMethodref #6.#111       // org/scalatest/Suite.testNames$:(Lorg/scalatest/Suite;)Lscala/collection/immutable/Set;
  #113 = Utf8               runTest
  #114 = Utf8               (Ljava/lang/String;Lorg/scalatest/Args;)Lorg/scalatest/Status;
  #115 = Utf8               args
  #116 = Utf8               runTest$
  #117 = Utf8               (Lorg/scalatest/Suite;Ljava/lang/String;Lorg/scalatest/Args;)Lorg/scalatest/Status;
  #118 = NameAndType        #116:#117     // runTest$:(Lorg/scalatest/Suite;Ljava/lang/String;Lorg/scalatest/Args;)Lorg/scalatest/Status;
  #119 = InterfaceMethodref #6.#118       // org/scalatest/Suite.runTest$:(Lorg/scalatest/Suite;Ljava/lang/String;Lorg/scalatest/Args;)Lorg/scalatest/Status;
  #120 = Utf8               Lorg/scalatest/Args;
  #121 = Utf8               run
  #122 = Utf8               (Lscala/Option;Lorg/scalatest/Args;)Lorg/scalatest/Status;
  #123 = Utf8               (Lscala/Option<Ljava/lang/String;>;Lorg/scalatest/Args;)Lorg/scalatest/Status;
  #124 = Utf8               run$
  #125 = Utf8               (Lorg/scalatest/Suite;Lscala/Option;Lorg/scalatest/Args;)Lorg/scalatest/Status;
  #126 = NameAndType        #124:#125     // run$:(Lorg/scalatest/Suite;Lscala/Option;Lorg/scalatest/Args;)Lorg/scalatest/Status;
  #127 = InterfaceMethodref #6.#126       // org/scalatest/Suite.run$:(Lorg/scalatest/Suite;Lscala/Option;Lorg/scalatest/Args;)Lorg/scalatest/Status;
  #128 = Utf8               Lscala/Option;
  #129 = Utf8               runNestedSuites
  #130 = Utf8               (Lorg/scalatest/Args;)Lorg/scalatest/Status;
  #131 = Utf8               runNestedSuites$
  #132 = Utf8               (Lorg/scalatest/Suite;Lorg/scalatest/Args;)Lorg/scalatest/Status;
  #133 = NameAndType        #131:#132     // runNestedSuites$:(Lorg/scalatest/Suite;Lorg/scalatest/Args;)Lorg/scalatest/Status;
  #134 = InterfaceMethodref #6.#133       // org/scalatest/Suite.runNestedSuites$:(Lorg/scalatest/Suite;Lorg/scalatest/Args;)Lorg/scalatest/Status;
  #135 = Utf8               suiteName
  #136 = Utf8               suiteName$
  #137 = NameAndType        #136:#68      // suiteName$:(Lorg/scalatest/Suite;)Ljava/lang/String;
  #138 = InterfaceMethodref #6.#137       // org/scalatest/Suite.suiteName$:(Lorg/scalatest/Suite;)Ljava/lang/String;
  #139 = Utf8               expectedTestCount
  #140 = Utf8               (Lorg/scalatest/Filter;)I
  #141 = Utf8               filter
  #142 = Utf8               expectedTestCount$
  #143 = Utf8               (Lorg/scalatest/Suite;Lorg/scalatest/Filter;)I
  #144 = NameAndType        #142:#143     // expectedTestCount$:(Lorg/scalatest/Suite;Lorg/scalatest/Filter;)I
  #145 = InterfaceMethodref #6.#144       // org/scalatest/Suite.expectedTestCount$:(Lorg/scalatest/Suite;Lorg/scalatest/Filter;)I
  #146 = Utf8               Lorg/scalatest/Filter;
  #147 = Utf8               createCatchReporter
  #148 = Utf8               (Lorg/scalatest/Reporter;)Lorg/scalatest/Reporter;
  #149 = Utf8               reporter
  #150 = Utf8               createCatchReporter$
  #151 = Utf8               (Lorg/scalatest/Suite;Lorg/scalatest/Reporter;)Lorg/scalatest/Reporter;
  #152 = NameAndType        #150:#151     // createCatchReporter$:(Lorg/scalatest/Suite;Lorg/scalatest/Reporter;)Lorg/scalatest/Reporter;
  #153 = InterfaceMethodref #6.#152       // org/scalatest/Suite.createCatchReporter$:(Lorg/scalatest/Suite;Lorg/scalatest/Reporter;)Lorg/scalatest/Reporter;
  #154 = Utf8               Lorg/scalatest/Reporter;
  #155 = Utf8               rerunner
  #156 = Utf8               ()Lscala/Option;
  #157 = Utf8               ()Lscala/Option<Ljava/lang/String;>;
  #158 = Utf8               rerunner$
  #159 = Utf8               (Lorg/scalatest/Suite;)Lscala/Option;
  #160 = NameAndType        #158:#159     // rerunner$:(Lorg/scalatest/Suite;)Lscala/Option;
  #161 = InterfaceMethodref #6.#160       // org/scalatest/Suite.rerunner$:(Lorg/scalatest/Suite;)Lscala/Option;
  #162 = Utf8               testDataFor
  #163 = Utf8               (Ljava/lang/String;Lorg/scalatest/ConfigMap;)Lorg/scalatest/TestData;
  #164 = Utf8               theConfigMap
  #165 = Utf8               testDataFor$
  #166 = Utf8               (Lorg/scalatest/Suite;Ljava/lang/String;Lorg/scalatest/ConfigMap;)Lorg/scalatest/TestData;
  #167 = NameAndType        #165:#166     // testDataFor$:(Lorg/scalatest/Suite;Ljava/lang/String;Lorg/scalatest/ConfigMap;)Lorg/scalatest/TestData;
  #168 = InterfaceMethodref #6.#167       // org/scalatest/Suite.testDataFor$:(Lorg/scalatest/Suite;Ljava/lang/String;Lorg/scalatest/ConfigMap;)Lorg/scalatest/TestData;
  #169 = Utf8               testDataFor$default$2
  #170 = Utf8               testDataFor$default$2$
  #171 = NameAndType        #170:#74      // testDataFor$default$2$:(Lorg/scalatest/Suite;)Lorg/scalatest/ConfigMap;
  #172 = InterfaceMethodref #6.#171       // org/scalatest/Suite.testDataFor$default$2$:(Lorg/scalatest/Suite;)Lorg/scalatest/ConfigMap;
  #173 = Utf8               newAssertionFailedException
  #174 = Utf8               (Lscala/Option;Lscala/Option;Lorg/scalactic/source/Position;Lscala/collection/immutable/IndexedSeq;)Ljava/lang/Throwable;
  #175 = Utf8               (Lscala/Option<Ljava/lang/String;>;Lscala/Option<Ljava/lang/Throwable;>;Lorg/scalactic/source/Position;Lscala/collection/immutable/IndexedSeq<Ljava/lang/String;>;)Ljava/lang/Throwable;
  #176 = Utf8               optionalMessage
  #177 = Utf8               optionalCause
  #178 = Utf8               pos
  #179 = Utf8               analysis
  #180 = Utf8               org/scalatest/Assertions
  #181 = Class              #180          // org/scalatest/Assertions
  #182 = Utf8               newAssertionFailedException$
  #183 = Utf8               (Lorg/scalatest/Assertions;Lscala/Option;Lscala/Option;Lorg/scalactic/source/Position;Lscala/collection/immutable/IndexedSeq;)Ljava/lang/Throwable;
  #184 = NameAndType        #182:#183     // newAssertionFailedException$:(Lorg/scalatest/Assertions;Lscala/Option;Lscala/Option;Lorg/scalactic/source/Position;Lscala/collection/immutable/IndexedSeq;)Ljava/lang/Throwable;
  #185 = InterfaceMethodref #181.#184     // org/scalatest/Assertions.newAssertionFailedException$:(Lorg/scalatest/Assertions;Lscala/Option;Lscala/Option;Lorg/scalactic/source/Position;Lscala/collection/immutable/IndexedSeq;)Ljava/lang/Throwable;
  #186 = Utf8               Lorg/scalactic/source/Position;
  #187 = Utf8               newTestCanceledException
  #188 = Utf8               (Lscala/Option;Lscala/Option;Lorg/scalactic/source/Position;)Ljava/lang/Throwable;
  #189 = Utf8               (Lscala/Option<Ljava/lang/String;>;Lscala/Option<Ljava/lang/Throwable;>;Lorg/scalactic/source/Position;)Ljava/lang/Throwable;
  #190 = Utf8               newTestCanceledException$
  #191 = Utf8               (Lorg/scalatest/Assertions;Lscala/Option;Lscala/Option;Lorg/scalactic/source/Position;)Ljava/lang/Throwable;
  #192 = NameAndType        #190:#191     // newTestCanceledException$:(Lorg/scalatest/Assertions;Lscala/Option;Lscala/Option;Lorg/scalactic/source/Position;)Ljava/lang/Throwable;
  #193 = InterfaceMethodref #181.#192     // org/scalatest/Assertions.newTestCanceledException$:(Lorg/scalatest/Assertions;Lscala/Option;Lscala/Option;Lorg/scalactic/source/Position;)Ljava/lang/Throwable;
  #194 = Utf8               intercept
  #195 = Utf8               (Lscala/Function0;Lscala/reflect/ClassTag;Lorg/scalactic/source/Position;)Ljava/lang/Object;
  #196 = Utf8               <T:Ljava/lang/Object;>(Lscala/Function0<Ljava/lang/Object;>;Lscala/reflect/ClassTag<TT;>;Lorg/scalactic/source/Position;)TT;
  #197 = Utf8               f
  #198 = Utf8               classTag
  #199 = Utf8               intercept$
  #200 = Utf8               (Lorg/scalatest/Assertions;Lscala/Function0;Lscala/reflect/ClassTag;Lorg/scalactic/source/Position;)Ljava/lang/Object;
  #201 = NameAndType        #199:#200     // intercept$:(Lorg/scalatest/Assertions;Lscala/Function0;Lscala/reflect/ClassTag;Lorg/scalactic/source/Position;)Ljava/lang/Object;
  #202 = InterfaceMethodref #181.#201     // org/scalatest/Assertions.intercept$:(Lorg/scalatest/Assertions;Lscala/Function0;Lscala/reflect/ClassTag;Lorg/scalactic/source/Position;)Ljava/lang/Object;
  #203 = Utf8               Lscala/Function0;
  #204 = Utf8               Lscala/reflect/ClassTag;
  #205 = Utf8               assertThrows
  #206 = Utf8               (Lscala/Function0;Lscala/reflect/ClassTag;Lorg/scalactic/source/Position;)Lorg/scalatest/compatible/Assertion;
  #207 = Utf8               <T:Ljava/lang/Object;>(Lscala/Function0<Ljava/lang/Object;>;Lscala/reflect/ClassTag<TT;>;Lorg/scalactic/source/Position;)Lorg/scalatest/compatible/Assertion;
  #208 = Utf8               assertThrows$
  #209 = Utf8               (Lorg/scalatest/Assertions;Lscala/Function0;Lscala/reflect/ClassTag;Lorg/scalactic/source/Position;)Lorg/scalatest/compatible/Assertion;
  #210 = NameAndType        #208:#209     // assertThrows$:(Lorg/scalatest/Assertions;Lscala/Function0;Lscala/reflect/ClassTag;Lorg/scalactic/source/Position;)Lorg/scalatest/compatible/Assertion;
  #211 = InterfaceMethodref #181.#210     // org/scalatest/Assertions.assertThrows$:(Lorg/scalatest/Assertions;Lscala/Function0;Lscala/reflect/ClassTag;Lorg/scalactic/source/Position;)Lorg/scalatest/compatible/Assertion;
  #212 = Utf8               assertResult
  #213 = Utf8               (Ljava/lang/Object;Ljava/lang/Object;Ljava/lang/Object;Lorg/scalactic/Prettifier;Lorg/scalactic/source/Position;)Lorg/scalatest/compatible/Assertion;
  #214 = Utf8               expected
  #215 = Utf8               clue
  #216 = Utf8               actual
  #217 = Utf8               prettifier
  #218 = Utf8               assertResult$
  #219 = Utf8               (Lorg/scalatest/Assertions;Ljava/lang/Object;Ljava/lang/Object;Ljava/lang/Object;Lorg/scalactic/Prettifier;Lorg/scalactic/source/Position;)Lorg/scalatest/compatible/Assertion;
  #220 = NameAndType        #218:#219     // assertResult$:(Lorg/scalatest/Assertions;Ljava/lang/Object;Ljava/lang/Object;Ljava/lang/Object;Lorg/scalactic/Prettifier;Lorg/scalactic/source/Position;)Lorg/scalatest/compatible/Assertion;
  #221 = InterfaceMethodref #181.#220     // org/scalatest/Assertions.assertResult$:(Lorg/scalatest/Assertions;Ljava/lang/Object;Ljava/lang/Object;Ljava/lang/Object;Lorg/scalactic/Prettifier;Lorg/scalactic/source/Position;)Lorg/scalatest/compatible/Assertion;
  #222 = Utf8               Ljava/lang/Object;
  #223 = Utf8               Lorg/scalactic/Prettifier;
  #224 = Utf8               (Ljava/lang/Object;Ljava/lang/Object;Lorg/scalactic/Prettifier;Lorg/scalactic/source/Position;)Lorg/scalatest/compatible/Assertion;
  #225 = Utf8               (Lorg/scalatest/Assertions;Ljava/lang/Object;Ljava/lang/Object;Lorg/scalactic/Prettifier;Lorg/scalactic/source/Position;)Lorg/scalatest/compatible/Assertion;
  #226 = NameAndType        #218:#225     // assertResult$:(Lorg/scalatest/Assertions;Ljava/lang/Object;Ljava/lang/Object;Lorg/scalactic/Prettifier;Lorg/scalactic/source/Position;)Lorg/scalatest/compatible/Assertion;
  #227 = InterfaceMethodref #181.#226     // org/scalatest/Assertions.assertResult$:(Lorg/scalatest/Assertions;Ljava/lang/Object;Ljava/lang/Object;Lorg/scalactic/Prettifier;Lorg/scalactic/source/Position;)Lorg/scalatest/compatible/Assertion;
  #228 = Utf8               fail
  #229 = Utf8               (Lorg/scalactic/source/Position;)Lscala/runtime/Nothing$;
  #230 = Utf8               fail$
  #231 = Utf8               (Lorg/scalatest/Assertions;Lorg/scalactic/source/Position;)Lscala/runtime/Nothing$;
  #232 = NameAndType        #230:#231     // fail$:(Lorg/scalatest/Assertions;Lorg/scalactic/source/Position;)Lscala/runtime/Nothing$;
  #233 = InterfaceMethodref #181.#232     // org/scalatest/Assertions.fail$:(Lorg/scalatest/Assertions;Lorg/scalactic/source/Position;)Lscala/runtime/Nothing$;
  #234 = Utf8               (Ljava/lang/String;Lorg/scalactic/source/Position;)Lscala/runtime/Nothing$;
  #235 = Utf8               message
  #236 = Utf8               (Lorg/scalatest/Assertions;Ljava/lang/String;Lorg/scalactic/source/Position;)Lscala/runtime/Nothing$;
  #237 = NameAndType        #230:#236     // fail$:(Lorg/scalatest/Assertions;Ljava/lang/String;Lorg/scalactic/source/Position;)Lscala/runtime/Nothing$;
  #238 = InterfaceMethodref #181.#237     // org/scalatest/Assertions.fail$:(Lorg/scalatest/Assertions;Ljava/lang/String;Lorg/scalactic/source/Position;)Lscala/runtime/Nothing$;
  #239 = Utf8               (Ljava/lang/String;Ljava/lang/Throwable;Lorg/scalactic/source/Position;)Lscala/runtime/Nothing$;
  #240 = Utf8               cause
  #241 = Utf8               (Lorg/scalatest/Assertions;Ljava/lang/String;Ljava/lang/Throwable;Lorg/scalactic/source/Position;)Lscala/runtime/Nothing$;
  #242 = NameAndType        #230:#241     // fail$:(Lorg/scalatest/Assertions;Ljava/lang/String;Ljava/lang/Throwable;Lorg/scalactic/source/Position;)Lscala/runtime/Nothing$;
  #243 = InterfaceMethodref #181.#242     // org/scalatest/Assertions.fail$:(Lorg/scalatest/Assertions;Ljava/lang/String;Ljava/lang/Throwable;Lorg/scalactic/source/Position;)Lscala/runtime/Nothing$;
  #244 = Utf8               Ljava/lang/Throwable;
  #245 = Utf8               (Ljava/lang/Throwable;Lorg/scalactic/source/Position;)Lscala/runtime/Nothing$;
  #246 = Utf8               (Lorg/scalatest/Assertions;Ljava/lang/Throwable;Lorg/scalactic/source/Position;)Lscala/runtime/Nothing$;
  #247 = NameAndType        #230:#246     // fail$:(Lorg/scalatest/Assertions;Ljava/lang/Throwable;Lorg/scalactic/source/Position;)Lscala/runtime/Nothing$;
  #248 = InterfaceMethodref #181.#247     // org/scalatest/Assertions.fail$:(Lorg/scalatest/Assertions;Ljava/lang/Throwable;Lorg/scalactic/source/Position;)Lscala/runtime/Nothing$;
  #249 = Utf8               cancel
  #250 = Utf8               cancel$
  #251 = NameAndType        #250:#231     // cancel$:(Lorg/scalatest/Assertions;Lorg/scalactic/source/Position;)Lscala/runtime/Nothing$;
  #252 = InterfaceMethodref #181.#251     // org/scalatest/Assertions.cancel$:(Lorg/scalatest/Assertions;Lorg/scalactic/source/Position;)Lscala/runtime/Nothing$;
  #253 = NameAndType        #250:#236     // cancel$:(Lorg/scalatest/Assertions;Ljava/lang/String;Lorg/scalactic/source/Position;)Lscala/runtime/Nothing$;
  #254 = InterfaceMethodref #181.#253     // org/scalatest/Assertions.cancel$:(Lorg/scalatest/Assertions;Ljava/lang/String;Lorg/scalactic/source/Position;)Lscala/runtime/Nothing$;
  #255 = NameAndType        #250:#241     // cancel$:(Lorg/scalatest/Assertions;Ljava/lang/String;Ljava/lang/Throwable;Lorg/scalactic/source/Position;)Lscala/runtime/Nothing$;
  #256 = InterfaceMethodref #181.#255     // org/scalatest/Assertions.cancel$:(Lorg/scalatest/Assertions;Ljava/lang/String;Ljava/lang/Throwable;Lorg/scalactic/source/Position;)Lscala/runtime/Nothing$;
  #257 = NameAndType        #250:#246     // cancel$:(Lorg/scalatest/Assertions;Ljava/lang/Throwable;Lorg/scalactic/source/Position;)Lscala/runtime/Nothing$;
  #258 = InterfaceMethodref #181.#257     // org/scalatest/Assertions.cancel$:(Lorg/scalatest/Assertions;Ljava/lang/Throwable;Lorg/scalactic/source/Position;)Lscala/runtime/Nothing$;
  #259 = Utf8               withClue
  #260 = Utf8               (Ljava/lang/Object;Lscala/Function0;)Ljava/lang/Object;
  #261 = Utf8               <T:Ljava/lang/Object;>(Ljava/lang/Object;Lscala/Function0<TT;>;)TT;
  #262 = Utf8               fun
  #263 = Utf8               withClue$
  #264 = Utf8               (Lorg/scalatest/Assertions;Ljava/lang/Object;Lscala/Function0;)Ljava/lang/Object;
  #265 = NameAndType        #263:#264     // withClue$:(Lorg/scalatest/Assertions;Ljava/lang/Object;Lscala/Function0;)Ljava/lang/Object;
  #266 = InterfaceMethodref #181.#265     // org/scalatest/Assertions.withClue$:(Lorg/scalatest/Assertions;Ljava/lang/Object;Lscala/Function0;)Ljava/lang/Object;
  #267 = Utf8               pending
  #268 = Utf8               ()Lorg/scalatest/compatible/Assertion;
  #269 = Utf8               pending$
  #270 = Utf8               (Lorg/scalatest/Assertions;)Lorg/scalatest/compatible/Assertion;
  #271 = NameAndType        #269:#270     // pending$:(Lorg/scalatest/Assertions;)Lorg/scalatest/compatible/Assertion;
  #272 = InterfaceMethodref #181.#271     // org/scalatest/Assertions.pending$:(Lorg/scalatest/Assertions;)Lorg/scalatest/compatible/Assertion;
  #273 = Utf8               pendingUntilFixed
  #274 = Utf8               (Lscala/Function0;Lorg/scalactic/source/Position;)Lorg/scalatest/compatible/Assertion;
  #275 = Utf8               (Lscala/Function0<Lscala/runtime/BoxedUnit;>;Lorg/scalactic/source/Position;)Lorg/scalatest/compatible/Assertion;
  #276 = Utf8               pendingUntilFixed$
  #277 = Utf8               (Lorg/scalatest/Assertions;Lscala/Function0;Lorg/scalactic/source/Position;)Lorg/scalatest/compatible/Assertion;
  #278 = NameAndType        #276:#277     // pendingUntilFixed$:(Lorg/scalatest/Assertions;Lscala/Function0;Lorg/scalactic/source/Position;)Lorg/scalatest/compatible/Assertion;
  #279 = InterfaceMethodref #181.#278     // org/scalatest/Assertions.pendingUntilFixed$:(Lorg/scalatest/Assertions;Lscala/Function0;Lorg/scalactic/source/Position;)Lorg/scalatest/compatible/Assertion;
  #280 = Utf8               convertToEqualizer
  #281 = Utf8               (Ljava/lang/Object;)Lorg/scalactic/TripleEqualsSupport$Equalizer;
  #282 = Utf8               <T:Ljava/lang/Object;>(TT;)Lorg/scalactic/TripleEqualsSupport$Equalizer<TT;>;
  #283 = Utf8               left
  #284 = Utf8               org/scalactic/TripleEquals
  #285 = Class              #284          // org/scalactic/TripleEquals
  #286 = Utf8               convertToEqualizer$
  #287 = Utf8               (Lorg/scalactic/TripleEquals;Ljava/lang/Object;)Lorg/scalactic/TripleEqualsSupport$Equalizer;
  #288 = NameAndType        #286:#287     // convertToEqualizer$:(Lorg/scalactic/TripleEquals;Ljava/lang/Object;)Lorg/scalactic/TripleEqualsSupport$Equalizer;
  #289 = InterfaceMethodref #285.#288     // org/scalactic/TripleEquals.convertToEqualizer$:(Lorg/scalactic/TripleEquals;Ljava/lang/Object;)Lorg/scalactic/TripleEqualsSupport$Equalizer;
  #290 = Utf8               convertToCheckingEqualizer
  #291 = Utf8               (Ljava/lang/Object;)Lorg/scalactic/TripleEqualsSupport$CheckingEqualizer;
  #292 = Utf8               <T:Ljava/lang/Object;>(TT;)Lorg/scalactic/TripleEqualsSupport$CheckingEqualizer<TT;>;
  #293 = Utf8               convertToCheckingEqualizer$
  #294 = Utf8               (Lorg/scalactic/TripleEquals;Ljava/lang/Object;)Lorg/scalactic/TripleEqualsSupport$CheckingEqualizer;
  #295 = NameAndType        #293:#294     // convertToCheckingEqualizer$:(Lorg/scalactic/TripleEquals;Ljava/lang/Object;)Lorg/scalactic/TripleEqualsSupport$CheckingEqualizer;
  #296 = InterfaceMethodref #285.#295     // org/scalactic/TripleEquals.convertToCheckingEqualizer$:(Lorg/scalactic/TripleEquals;Ljava/lang/Object;)Lorg/scalactic/TripleEqualsSupport$CheckingEqualizer;
  #297 = Utf8               unconstrainedEquality
  #298 = Utf8               (Lorg/scalactic/Equality;)Lorg/scalactic/CanEqual;
  #299 = Utf8               <A:Ljava/lang/Object;B:Ljava/lang/Object;>(Lorg/scalactic/Equality<TA;>;)Lorg/scalactic/CanEqual<TA;TB;>;
  #300 = Utf8               equalityOfA
  #301 = Utf8               unconstrainedEquality$
  #302 = Utf8               (Lorg/scalactic/TripleEquals;Lorg/scalactic/Equality;)Lorg/scalactic/CanEqual;
  #303 = NameAndType        #301:#302     // unconstrainedEquality$:(Lorg/scalactic/TripleEquals;Lorg/scalactic/Equality;)Lorg/scalactic/CanEqual;
  #304 = InterfaceMethodref #285.#303     // org/scalactic/TripleEquals.unconstrainedEquality$:(Lorg/scalactic/TripleEquals;Lorg/scalactic/Equality;)Lorg/scalactic/CanEqual;
  #305 = Utf8               Lorg/scalactic/Equality;
  #306 = Utf8               lowPriorityTypeCheckedConstraint
  #307 = Utf8               (Lorg/scalactic/Equivalence;Lscala/$less$colon$less;)Lorg/scalactic/CanEqual;
  #308 = Utf8               <A:Ljava/lang/Object;B:Ljava/lang/Object;>(Lorg/scalactic/Equivalence<TB;>;Lscala/$less$colon$less<TA;TB;>;)Lorg/scalactic/CanEqual<TA;TB;>;
  #309 = Utf8               equivalenceOfB
  #310 = Utf8               ev
  #311 = Utf8               lowPriorityTypeCheckedConstraint$
  #312 = Utf8               (Lorg/scalactic/TripleEquals;Lorg/scalactic/Equivalence;Lscala/$less$colon$less;)Lorg/scalactic/CanEqual;
  #313 = NameAndType        #311:#312     // lowPriorityTypeCheckedConstraint$:(Lorg/scalactic/TripleEquals;Lorg/scalactic/Equivalence;Lscala/$less$colon$less;)Lorg/scalactic/CanEqual;
  #314 = InterfaceMethodref #285.#313     // org/scalactic/TripleEquals.lowPriorityTypeCheckedConstraint$:(Lorg/scalactic/TripleEquals;Lorg/scalactic/Equivalence;Lscala/$less$colon$less;)Lorg/scalactic/CanEqual;
  #315 = Utf8               Lorg/scalactic/Equivalence;
  #316 = Utf8               Lscala/$less$colon$less;
  #317 = Utf8               convertEquivalenceToAToBConstraint
  #318 = Utf8               convertEquivalenceToAToBConstraint$
  #319 = NameAndType        #318:#312     // convertEquivalenceToAToBConstraint$:(Lorg/scalactic/TripleEquals;Lorg/scalactic/Equivalence;Lscala/$less$colon$less;)Lorg/scalactic/CanEqual;
  #320 = InterfaceMethodref #285.#319     // org/scalactic/TripleEquals.convertEquivalenceToAToBConstraint$:(Lorg/scalactic/TripleEquals;Lorg/scalactic/Equivalence;Lscala/$less$colon$less;)Lorg/scalactic/CanEqual;
  #321 = Utf8               typeCheckedConstraint
  #322 = Utf8               <A:Ljava/lang/Object;B:Ljava/lang/Object;>(Lorg/scalactic/Equivalence<TA;>;Lscala/$less$colon$less<TB;TA;>;)Lorg/scalactic/CanEqual<TA;TB;>;
  #323 = Utf8               equivalenceOfA
  #324 = Utf8               typeCheckedConstraint$
  #325 = NameAndType        #324:#312     // typeCheckedConstraint$:(Lorg/scalactic/TripleEquals;Lorg/scalactic/Equivalence;Lscala/$less$colon$less;)Lorg/scalactic/CanEqual;
  #326 = InterfaceMethodref #285.#325     // org/scalactic/TripleEquals.typeCheckedConstraint$:(Lorg/scalactic/TripleEquals;Lorg/scalactic/Equivalence;Lscala/$less$colon$less;)Lorg/scalactic/CanEqual;
  #327 = Utf8               convertEquivalenceToBToAConstraint
  #328 = Utf8               convertEquivalenceToBToAConstraint$
  #329 = NameAndType        #328:#312     // convertEquivalenceToBToAConstraint$:(Lorg/scalactic/TripleEquals;Lorg/scalactic/Equivalence;Lscala/$less$colon$less;)Lorg/scalactic/CanEqual;
  #330 = InterfaceMethodref #285.#329     // org/scalactic/TripleEquals.convertEquivalenceToBToAConstraint$:(Lorg/scalactic/TripleEquals;Lorg/scalactic/Equivalence;Lscala/$less$colon$less;)Lorg/scalactic/CanEqual;
  #331 = Utf8               lowPriorityConversionCheckedConstraint
  #332 = Utf8               (Lorg/scalactic/Equivalence;Lscala/Function1;)Lorg/scalactic/CanEqual;
  #333 = Utf8               <A:Ljava/lang/Object;B:Ljava/lang/Object;>(Lorg/scalactic/Equivalence<TB;>;Lscala/Function1<TA;TB;>;)Lorg/scalactic/CanEqual<TA;TB;>;
  #334 = Utf8               cnv
  #335 = Utf8               lowPriorityConversionCheckedConstraint$
  #336 = Utf8               (Lorg/scalactic/TripleEquals;Lorg/scalactic/Equivalence;Lscala/Function1;)Lorg/scalactic/CanEqual;
  #337 = NameAndType        #335:#336     // lowPriorityConversionCheckedConstraint$:(Lorg/scalactic/TripleEquals;Lorg/scalactic/Equivalence;Lscala/Function1;)Lorg/scalactic/CanEqual;
  #338 = InterfaceMethodref #285.#337     // org/scalactic/TripleEquals.lowPriorityConversionCheckedConstraint$:(Lorg/scalactic/TripleEquals;Lorg/scalactic/Equivalence;Lscala/Function1;)Lorg/scalactic/CanEqual;
  #339 = Utf8               Lscala/Function1;
  #340 = Utf8               convertEquivalenceToAToBConversionConstraint
  #341 = Utf8               convertEquivalenceToAToBConversionConstraint$
  #342 = NameAndType        #341:#336     // convertEquivalenceToAToBConversionConstraint$:(Lorg/scalactic/TripleEquals;Lorg/scalactic/Equivalence;Lscala/Function1;)Lorg/scalactic/CanEqual;
  #343 = InterfaceMethodref #285.#342     // org/scalactic/TripleEquals.convertEquivalenceToAToBConversionConstraint$:(Lorg/scalactic/TripleEquals;Lorg/scalactic/Equivalence;Lscala/Function1;)Lorg/scalactic/CanEqual;
  #344 = Utf8               conversionCheckedConstraint
  #345 = Utf8               <A:Ljava/lang/Object;B:Ljava/lang/Object;>(Lorg/scalactic/Equivalence<TA;>;Lscala/Function1<TB;TA;>;)Lorg/scalactic/CanEqual<TA;TB;>;
  #346 = Utf8               conversionCheckedConstraint$
  #347 = NameAndType        #346:#336     // conversionCheckedConstraint$:(Lorg/scalactic/TripleEquals;Lorg/scalactic/Equivalence;Lscala/Function1;)Lorg/scalactic/CanEqual;
  #348 = InterfaceMethodref #285.#347     // org/scalactic/TripleEquals.conversionCheckedConstraint$:(Lorg/scalactic/TripleEquals;Lorg/scalactic/Equivalence;Lscala/Function1;)Lorg/scalactic/CanEqual;
  #349 = Utf8               convertEquivalenceToBToAConversionConstraint
  #350 = Utf8               convertEquivalenceToBToAConversionConstraint$
  #351 = NameAndType        #350:#336     // convertEquivalenceToBToAConversionConstraint$:(Lorg/scalactic/TripleEquals;Lorg/scalactic/Equivalence;Lscala/Function1;)Lorg/scalactic/CanEqual;
  #352 = InterfaceMethodref #285.#351     // org/scalactic/TripleEquals.convertEquivalenceToBToAConversionConstraint$:(Lorg/scalactic/TripleEquals;Lorg/scalactic/Equivalence;Lscala/Function1;)Lorg/scalactic/CanEqual;
  #353 = Utf8               defaultEquality
  #354 = Utf8               ()Lorg/scalactic/Equality;
  #355 = Utf8               <A:Ljava/lang/Object;>()Lorg/scalactic/Equality<TA;>;
  #356 = Utf8               defaultEquality$
  #357 = Utf8               (Lorg/scalactic/TripleEqualsSupport;)Lorg/scalactic/Equality;
  #358 = NameAndType        #356:#357     // defaultEquality$:(Lorg/scalactic/TripleEqualsSupport;)Lorg/scalactic/Equality;
  #359 = InterfaceMethodref #24.#358      // org/scalactic/TripleEqualsSupport.defaultEquality$:(Lorg/scalactic/TripleEqualsSupport;)Lorg/scalactic/Equality;
  #360 = Utf8               $eq$eq$eq
  #361 = Utf8               (Ljava/lang/Object;)Lorg/scalactic/TripleEqualsSupport$TripleEqualsInvocation;
  #362 = Utf8               <T:Ljava/lang/Object;>(TT;)Lorg/scalactic/TripleEqualsSupport$TripleEqualsInvocation<TT;>;
  #363 = Utf8               right
  #364 = Utf8               $eq$eq$eq$
  #365 = Utf8               (Lorg/scalactic/TripleEqualsSupport;Ljava/lang/Object;)Lorg/scalactic/TripleEqualsSupport$TripleEqualsInvocation;
  #366 = NameAndType        #364:#365     // $eq$eq$eq$:(Lorg/scalactic/TripleEqualsSupport;Ljava/lang/Object;)Lorg/scalactic/TripleEqualsSupport$TripleEqualsInvocation;
  #367 = InterfaceMethodref #24.#366      // org/scalactic/TripleEqualsSupport.$eq$eq$eq$:(Lorg/scalactic/TripleEqualsSupport;Ljava/lang/Object;)Lorg/scalactic/TripleEqualsSupport$TripleEqualsInvocation;
  #368 = Utf8               $bang$eq$eq
  #369 = Utf8               $bang$eq$eq$
  #370 = NameAndType        #369:#365     // $bang$eq$eq$:(Lorg/scalactic/TripleEqualsSupport;Ljava/lang/Object;)Lorg/scalactic/TripleEqualsSupport$TripleEqualsInvocation;
  #371 = InterfaceMethodref #24.#370      // org/scalactic/TripleEqualsSupport.$bang$eq$eq$:(Lorg/scalactic/TripleEqualsSupport;Ljava/lang/Object;)Lorg/scalactic/TripleEqualsSupport$TripleEqualsInvocation;
  #372 = Utf8               (Lscala/runtime/Null$;)Lorg/scalactic/TripleEqualsSupport$TripleEqualsInvocation;
  #373 = Utf8               (Lscala/runtime/Null$;)Lorg/scalactic/TripleEqualsSupport$TripleEqualsInvocation<Lscala/runtime/Null$;>;
  #374 = Utf8               (Lorg/scalactic/TripleEqualsSupport;Lscala/runtime/Null$;)Lorg/scalactic/TripleEqualsSupport$TripleEqualsInvocation;
  #375 = NameAndType        #364:#374     // $eq$eq$eq$:(Lorg/scalactic/TripleEqualsSupport;Lscala/runtime/Null$;)Lorg/scalactic/TripleEqualsSupport$TripleEqualsInvocation;
  #376 = InterfaceMethodref #24.#375      // org/scalactic/TripleEqualsSupport.$eq$eq$eq$:(Lorg/scalactic/TripleEqualsSupport;Lscala/runtime/Null$;)Lorg/scalactic/TripleEqualsSupport$TripleEqualsInvocation;
  #377 = Utf8               Lscala/runtime/Null$;
  #378 = NameAndType        #369:#374     // $bang$eq$eq$:(Lorg/scalactic/TripleEqualsSupport;Lscala/runtime/Null$;)Lorg/scalactic/TripleEqualsSupport$TripleEqualsInvocation;
  #379 = InterfaceMethodref #24.#378      // org/scalactic/TripleEqualsSupport.$bang$eq$eq$:(Lorg/scalactic/TripleEqualsSupport;Lscala/runtime/Null$;)Lorg/scalactic/TripleEqualsSupport$TripleEqualsInvocation;
  #380 = Utf8               (Lorg/scalactic/TripleEqualsSupport$Spread;)Lorg/scalactic/TripleEqualsSupport$TripleEqualsInvocationOnSpread;
  #381 = Utf8               <T:Ljava/lang/Object;>(Lorg/scalactic/TripleEqualsSupport$Spread<TT;>;)Lorg/scalactic/TripleEqualsSupport$TripleEqualsInvocationOnSpread<TT;>;
  #382 = Utf8               (Lorg/scalactic/TripleEqualsSupport;Lorg/scalactic/TripleEqualsSupport$Spread;)Lorg/scalactic/TripleEqualsSupport$TripleEqualsInvocationOnSpread;
  #383 = NameAndType        #364:#382     // $eq$eq$eq$:(Lorg/scalactic/TripleEqualsSupport;Lorg/scalactic/TripleEqualsSupport$Spread;)Lorg/scalactic/TripleEqualsSupport$TripleEqualsInvocationOnSpread;
  #384 = InterfaceMethodref #24.#383      // org/scalactic/TripleEqualsSupport.$eq$eq$eq$:(Lorg/scalactic/TripleEqualsSupport;Lorg/scalactic/TripleEqualsSupport$Spread;)Lorg/scalactic/TripleEqualsSupport$TripleEqualsInvocationOnSpread;
  #385 = Utf8               Lorg/scalactic/TripleEqualsSupport$Spread;
  #386 = NameAndType        #369:#382     // $bang$eq$eq$:(Lorg/scalactic/TripleEqualsSupport;Lorg/scalactic/TripleEqualsSupport$Spread;)Lorg/scalactic/TripleEqualsSupport$TripleEqualsInvocationOnSpread;
  #387 = InterfaceMethodref #24.#386      // org/scalactic/TripleEqualsSupport.$bang$eq$eq$:(Lorg/scalactic/TripleEqualsSupport;Lorg/scalactic/TripleEqualsSupport$Spread;)Lorg/scalactic/TripleEqualsSupport$TripleEqualsInvocationOnSpread;
  #388 = NameAndType        #45:#41       // styleName:Ljava/lang/String;
  #389 = Fieldref           #2.#388       // org/scalatest/tools/DiscoverySuite.styleName:Ljava/lang/String;
  #390 = Utf8               org$scalatest$Suite$_setter_$styleName_$eq
  #391 = Utf8               (Ljava/lang/String;)V
  #392 = Utf8               x$1
  #393 = NameAndType        #46:#47       // succeed:Lorg/scalatest/compatible/Assertion;
  #394 = Fieldref           #2.#393       // org/scalatest/tools/DiscoverySuite.succeed:Lorg/scalatest/compatible/Assertion;
  #395 = Utf8               org$scalatest$Assertions$_setter_$succeed_$eq
  #396 = Utf8               (Lorg/scalatest/compatible/Assertion;)V
  #397 = NameAndType        #40:#41       // suiteId:Ljava/lang/String;
  #398 = Fieldref           #2.#397       // org/scalatest/tools/DiscoverySuite.suiteId:Ljava/lang/String;
  #399 = Utf8               ()Lscala/collection/immutable/IndexedSeq;
  #400 = Utf8               ()Lscala/collection/immutable/IndexedSeq<Lorg/scalatest/Suite;>;
  #401 = NameAndType        #42:#43       // nestedSuites:Lscala/collection/immutable/IndexedSeq;
  #402 = Fieldref           #2.#401       // org/scalatest/tools/DiscoverySuite.nestedSuites:Lscala/collection/immutable/IndexedSeq;
  #403 = Utf8               runTests
  #404 = Utf8               org/scalactic/Requirements$
  #405 = Class              #404          // org/scalactic/Requirements$
  #406 = Utf8               MODULE$
  #407 = Utf8               Lorg/scalactic/Requirements$;
  #408 = NameAndType        #406:#407     // MODULE$:Lorg/scalactic/Requirements$;
  #409 = Fieldref           #405.#408     // org/scalactic/Requirements$.MODULE$:Lorg/scalactic/Requirements$;
  #410 = Utf8               requirementsHelper
  #411 = Utf8               ()Lorg/scalactic/Requirements$RequirementsHelper;
  #412 = NameAndType        #410:#411     // requirementsHelper:()Lorg/scalactic/Requirements$RequirementsHelper;
  #413 = Methodref          #405.#412     // org/scalactic/Requirements$.requirementsHelper:()Lorg/scalactic/Requirements$RequirementsHelper;
  #414 = Utf8               java/lang/String
  #415 = Class              #414          // java/lang/String
  #416 = String             #50           // testName
  #417 = String             #115          // args
  #418 = Utf8               [Ljava/lang/Object;
  #419 = Class              #418          // "[Ljava/lang/Object;"
  #420 = Utf8               [Ljava/lang/String;
  #421 = Class              #420          // "[Ljava/lang/String;"
  #422 = Utf8               org/scalactic/Prettifier$
  #423 = Class              #422          // org/scalactic/Prettifier$
  #424 = Utf8               Lorg/scalactic/Prettifier$;
  #425 = NameAndType        #406:#424     // MODULE$:Lorg/scalactic/Prettifier$;
  #426 = Fieldref           #423.#425     // org/scalactic/Prettifier$.MODULE$:Lorg/scalactic/Prettifier$;
  #427 = Utf8               default
  #428 = Utf8               ()Lorg/scalactic/Prettifier;
  #429 = NameAndType        #427:#428     // default:()Lorg/scalactic/Prettifier;
  #430 = Methodref          #423.#429     // org/scalactic/Prettifier$.default:()Lorg/scalactic/Prettifier;
  #431 = Utf8               org/scalactic/source/Position
  #432 = Class              #431          // org/scalactic/source/Position
  #433 = String             #7            // DiscoverySuite.scala
  #434 = Utf8               Please set the environment variable SCALACTIC_FILL_FILE_PATHNAMES to yes at compile time to enable this feature.
  #435 = String             #434          // Please set the environment variable SCALACTIC_FILL_FILE_PATHNAMES to yes at compile time to enable this feature.
  #436 = Utf8               <init>
  #437 = Utf8               (Ljava/lang/String;Ljava/lang/String;I)V
  #438 = NameAndType        #436:#437     // "<init>":(Ljava/lang/String;Ljava/lang/String;I)V
  #439 = Methodref          #432.#438     // org/scalactic/source/Position."<init>":(Ljava/lang/String;Ljava/lang/String;I)V
  #440 = Utf8               macroRequireNonNull
  #441 = Utf8               ([Ljava/lang/String;[Ljava/lang/Object;Lorg/scalactic/Prettifier;Lorg/scalactic/source/Position;)V
  #442 = NameAndType        #440:#441     // macroRequireNonNull:([Ljava/lang/String;[Ljava/lang/Object;Lorg/scalactic/Prettifier;Lorg/scalactic/source/Position;)V
  #443 = Methodref          #17.#442      // org/scalactic/Requirements$RequirementsHelper.macroRequireNonNull:([Ljava/lang/String;[Ljava/lang/Object;Lorg/scalactic/Prettifier;Lorg/scalactic/source/Position;)V
  #444 = Utf8               org/scalatest/SucceededStatus$
  #445 = Class              #444          // org/scalatest/SucceededStatus$
  #446 = Utf8               Lorg/scalatest/SucceededStatus$;
  #447 = NameAndType        #406:#446     // MODULE$:Lorg/scalatest/SucceededStatus$;
  #448 = Fieldref           #445.#447     // org/scalatest/SucceededStatus$.MODULE$:Lorg/scalatest/SucceededStatus$;
  #449 = Utf8               $anonfun$nestedSuites$1
  #450 = Utf8               (Lorg/scalatest/tools/DiscoverySuite;Ljava/lang/String;)Lorg/scalatest/Suite;
  #451 = Utf8               $this
  #452 = Utf8               suiteClassName
  #453 = Utf8               org/scalatest/tools/DiscoverySuite$
  #454 = Class              #453          // org/scalatest/tools/DiscoverySuite$
  #455 = Utf8               Lorg/scalatest/tools/DiscoverySuite$;
  #456 = NameAndType        #406:#455     // MODULE$:Lorg/scalatest/tools/DiscoverySuite$;
  #457 = Fieldref           #454.#456     // org/scalatest/tools/DiscoverySuite$.MODULE$:Lorg/scalatest/tools/DiscoverySuite$;
  #458 = NameAndType        #38:#39       // runpathClassLoader:Ljava/lang/ClassLoader;
  #459 = Fieldref           #2.#458       // org/scalatest/tools/DiscoverySuite.runpathClassLoader:Ljava/lang/ClassLoader;
  #460 = Utf8               getSuiteInstance
  #461 = Utf8               (Ljava/lang/String;Ljava/lang/ClassLoader;)Lorg/scalatest/Suite;
  #462 = NameAndType        #460:#461     // getSuiteInstance:(Ljava/lang/String;Ljava/lang/ClassLoader;)Lorg/scalatest/Suite;
  #463 = Methodref          #454.#462     // org/scalatest/tools/DiscoverySuite$.getSuiteInstance:(Ljava/lang/String;Ljava/lang/ClassLoader;)Lorg/scalatest/Suite;
  #464 = Utf8               (Ljava/lang/String;Lscala/collection/immutable/Set;ZLjava/lang/ClassLoader;)V
  #465 = Utf8               (Ljava/lang/String;Lscala/collection/immutable/Set<Ljava/lang/String;>;ZLjava/lang/ClassLoader;)V
  #466 = Utf8               path
  #467 = Utf8               accessibleSuites
  #468 = Utf8               wildcard
  #469 = Utf8               ()V
  #470 = NameAndType        #436:#469     // "<init>":()V
  #471 = Methodref          #4.#470       // java/lang/Object."<init>":()V
  #472 = Utf8               $init$
  #473 = Utf8               (Lorg/scalactic/TripleEqualsSupport;)V
  #474 = NameAndType        #472:#473     // $init$:(Lorg/scalactic/TripleEqualsSupport;)V
  #475 = InterfaceMethodref #24.#474      // org/scalactic/TripleEqualsSupport.$init$:(Lorg/scalactic/TripleEqualsSupport;)V
  #476 = Utf8               (Lorg/scalactic/TripleEquals;)V
  #477 = NameAndType        #472:#476     // $init$:(Lorg/scalactic/TripleEquals;)V
  #478 = InterfaceMethodref #285.#477     // org/scalactic/TripleEquals.$init$:(Lorg/scalactic/TripleEquals;)V
  #479 = Utf8               (Lorg/scalatest/Assertions;)V
  #480 = NameAndType        #472:#479     // $init$:(Lorg/scalatest/Assertions;)V
  #481 = InterfaceMethodref #181.#480     // org/scalatest/Assertions.$init$:(Lorg/scalatest/Assertions;)V
  #482 = Utf8               (Lorg/scalatest/Suite;)V
  #483 = NameAndType        #472:#482     // $init$:(Lorg/scalatest/Suite;)V
  #484 = InterfaceMethodref #6.#483       // org/scalatest/Suite.$init$:(Lorg/scalatest/Suite;)V
  #485 = Utf8               DiscoverySuite.this.path
  #486 = String             #485          // DiscoverySuite.this.path
  #487 = Utf8               DiscoverySuite.this.accessibleSuites
  #488 = String             #487          // DiscoverySuite.this.accessibleSuites
  #489 = Utf8               DiscoverySuite.this.runpathClassLoader
  #490 = String             #489          // DiscoverySuite.this.runpathClassLoader
  #491 = Utf8               java/lang/StringBuilder
  #492 = Class              #491          // java/lang/StringBuilder
  #493 = Integer            1
  #494 = Utf8               (I)V
  #495 = NameAndType        #436:#494     // "<init>":(I)V
  #496 = Methodref          #492.#495     // java/lang/StringBuilder."<init>":(I)V
  #497 = Utf8               getClass
  #498 = Utf8               ()Ljava/lang/Class;
  #499 = NameAndType        #497:#498     // getClass:()Ljava/lang/Class;
  #500 = Methodref          #2.#499       // org/scalatest/tools/DiscoverySuite.getClass:()Ljava/lang/Class;
  #501 = Utf8               java/lang/Class
  #502 = Class              #501          // java/lang/Class
  #503 = Utf8               getName
  #504 = NameAndType        #503:#66      // getName:()Ljava/lang/String;
  #505 = Methodref          #502.#504     // java/lang/Class.getName:()Ljava/lang/String;
  #506 = Utf8               append
  #507 = Utf8               (Ljava/lang/String;)Ljava/lang/StringBuilder;
  #508 = NameAndType        #506:#507     // append:(Ljava/lang/String;)Ljava/lang/StringBuilder;
  #509 = Methodref          #492.#508     // java/lang/StringBuilder.append:(Ljava/lang/String;)Ljava/lang/StringBuilder;
  #510 = Utf8               -
  #511 = String             #510          // -
  #512 = Utf8               java/util/UUID
  #513 = Class              #512          // java/util/UUID
  #514 = Utf8               randomUUID
  #515 = Utf8               ()Ljava/util/UUID;
  #516 = NameAndType        #514:#515     // randomUUID:()Ljava/util/UUID;
  #517 = Methodref          #513.#516     // java/util/UUID.randomUUID:()Ljava/util/UUID;
  #518 = Utf8               toString
  #519 = NameAndType        #518:#66      // toString:()Ljava/lang/String;
  #520 = Methodref          #513.#519     // java/util/UUID.toString:()Ljava/lang/String;
  #521 = Methodref          #492.#519     // java/lang/StringBuilder.toString:()Ljava/lang/String;
  #522 = Utf8               nestedSuiteNames
  #523 = Utf8               (Ljava/lang/String;Lscala/collection/immutable/Set;Z)Lscala/collection/immutable/IndexedSeq;
  #524 = NameAndType        #522:#523     // nestedSuiteNames:(Ljava/lang/String;Lscala/collection/immutable/Set;Z)Lscala/collection/immutable/IndexedSeq;
  #525 = Methodref          #454.#524     // org/scalatest/tools/DiscoverySuite$.nestedSuiteNames:(Ljava/lang/String;Lscala/collection/immutable/Set;Z)Lscala/collection/immutable/IndexedSeq;
  #526 = Utf8               (Ljava/lang/Object;)Ljava/lang/Object;
  #527 = MethodType         #526          //  (Ljava/lang/Object;)Ljava/lang/Object;
  #528 = NameAndType        #449:#450     // $anonfun$nestedSuites$1:(Lorg/scalatest/tools/DiscoverySuite;Ljava/lang/String;)Lorg/scalatest/Suite;
  #529 = Methodref          #2.#528       // org/scalatest/tools/DiscoverySuite.$anonfun$nestedSuites$1:(Lorg/scalatest/tools/DiscoverySuite;Ljava/lang/String;)Lorg/scalatest/Suite;
  #530 = MethodHandle       6:#529        // REF_invokeStatic org/scalatest/tools/DiscoverySuite.$anonfun$nestedSuites$1:(Lorg/scalatest/tools/DiscoverySuite;Ljava/lang/String;)Lorg/scalatest/Suite;
  #531 = Utf8               (Ljava/lang/String;)Lorg/scalatest/Suite;
  #532 = MethodType         #531          //  (Ljava/lang/String;)Lorg/scalatest/Suite;
  #533 = Integer            5
  #534 = Utf8               java/lang/invoke/LambdaMetafactory
  #535 = Class              #534          // java/lang/invoke/LambdaMetafactory
  #536 = Utf8               altMetafactory
  #537 = Utf8               (Ljava/lang/invoke/MethodHandles$Lookup;Ljava/lang/String;Ljava/lang/invoke/MethodType;[Ljava/lang/Object;)Ljava/lang/invoke/CallSite;
  #538 = NameAndType        #536:#537     // altMetafactory:(Ljava/lang/invoke/MethodHandles$Lookup;Ljava/lang/String;Ljava/lang/invoke/MethodType;[Ljava/lang/Object;)Ljava/lang/invoke/CallSite;
  #539 = Methodref          #535.#538     // java/lang/invoke/LambdaMetafactory.altMetafactory:(Ljava/lang/invoke/MethodHandles$Lookup;Ljava/lang/String;Ljava/lang/invoke/MethodType;[Ljava/lang/Object;)Ljava/lang/invoke/CallSite;
  #540 = MethodHandle       6:#539        // REF_invokeStatic java/lang/invoke/LambdaMetafactory.altMetafactory:(Ljava/lang/invoke/MethodHandles$Lookup;Ljava/lang/String;Ljava/lang/invoke/MethodType;[Ljava/lang/Object;)Ljava/lang/invoke/CallSite;
  #541 = Utf8               apply
  #542 = Utf8               (Lorg/scalatest/tools/DiscoverySuite;)Lscala/Function1;
  #543 = NameAndType        #541:#542     // apply:(Lorg/scalatest/tools/DiscoverySuite;)Lscala/Function1;
  #544 = InvokeDynamic      #0:#543       // #0:apply:(Lorg/scalatest/tools/DiscoverySuite;)Lscala/Function1;
  #545 = Utf8               scala/collection/immutable/IndexedSeq
  #546 = Class              #545          // scala/collection/immutable/IndexedSeq
  #547 = Utf8               map
  #548 = Utf8               (Lscala/Function1;)Ljava/lang/Object;
  #549 = NameAndType        #547:#548     // map:(Lscala/Function1;)Ljava/lang/Object;
  #550 = InterfaceMethodref #546.#549     // scala/collection/immutable/IndexedSeq.map:(Lscala/Function1;)Ljava/lang/Object;
  #551 = Utf8               scala/runtime/Statics
  #552 = Class              #551          // scala/runtime/Statics
  #553 = Utf8               releaseFence
  #554 = NameAndType        #553:#469     // releaseFence:()V
  #555 = Methodref          #552.#554     // scala/runtime/Statics.releaseFence:()V
  #556 = Utf8               Lscala/collection/immutable/Set;
  #557 = Utf8               $deserializeLambda$
  #558 = Utf8               (Ljava/lang/invoke/SerializedLambda;)Ljava/lang/Object;
  #559 = Utf8               scala/runtime/LambdaDeserialize
  #560 = Class              #559          // scala/runtime/LambdaDeserialize
  #561 = Utf8               bootstrap
  #562 = Utf8               (Ljava/lang/invoke/MethodHandles$Lookup;Ljava/lang/String;Ljava/lang/invoke/MethodType;[Ljava/lang/invoke/MethodHandle;)Ljava/lang/invoke/CallSite;
  #563 = NameAndType        #561:#562     // bootstrap:(Ljava/lang/invoke/MethodHandles$Lookup;Ljava/lang/String;Ljava/lang/invoke/MethodType;[Ljava/lang/invoke/MethodHandle;)Ljava/lang/invoke/CallSite;
  #564 = Methodref          #560.#563     // scala/runtime/LambdaDeserialize.bootstrap:(Ljava/lang/invoke/MethodHandles$Lookup;Ljava/lang/String;Ljava/lang/invoke/MethodType;[Ljava/lang/invoke/MethodHandle;)Ljava/lang/invoke/CallSite;
  #565 = MethodHandle       6:#564        // REF_invokeStatic scala/runtime/LambdaDeserialize.bootstrap:(Ljava/lang/invoke/MethodHandles$Lookup;Ljava/lang/String;Ljava/lang/invoke/MethodType;[Ljava/lang/invoke/MethodHandle;)Ljava/lang/invoke/CallSite;
  #566 = Utf8               lambdaDeserialize
  #567 = NameAndType        #566:#558     // lambdaDeserialize:(Ljava/lang/invoke/SerializedLambda;)Ljava/lang/Object;
  #568 = InvokeDynamic      #1:#567       // #1:lambdaDeserialize:(Ljava/lang/invoke/SerializedLambda;)Ljava/lang/Object;
  #569 = Utf8               Signature
  #570 = Utf8               Deprecated
  #571 = Utf8               Code
  #572 = Utf8               LineNumberTable
  #573 = Utf8               LocalVariableTable
  #574 = Utf8               MethodParameters
  #575 = Utf8               InnerClasses
  #576 = Utf8               SourceFile
  #577 = Utf8               RuntimeVisibleAnnotations
  #578 = Utf8               BootstrapMethods
  #579 = Utf8               ScalaInlineInfo
  #580 = Utf8               assert
  #581 = Utf8               (ZLjava/lang/Object;Lorg/scalactic/Prettifier;Lorg/scalactic/source/Position;)Lorg/scalatest/compatible/Assertion;
  #582 = Utf8               (ZLorg/scalactic/Prettifier;Lorg/scalactic/source/Position;)Lorg/scalatest/compatible/Assertion;
  #583 = Utf8               assertCompiles
  #584 = Utf8               (Ljava/lang/String;Lorg/scalactic/source/Position;)Lorg/scalatest/compatible/Assertion;
  #585 = Utf8               assertDoesNotCompile
  #586 = Utf8               assertTypeError
  #587 = Utf8               assume
  #588 = Utf8               ScalaSig
{
  private final java.lang.ClassLoader runpathClassLoader;
    descriptor: Ljava/lang/ClassLoader;
    flags: (0x0012) ACC_PRIVATE, ACC_FINAL

  private final java.lang.String suiteId;
    descriptor: Ljava/lang/String;
    flags: (0x0012) ACC_PRIVATE, ACC_FINAL

  private final scala.collection.immutable.IndexedSeq<org.scalatest.Suite> nestedSuites;
    descriptor: Lscala/collection/immutable/IndexedSeq;
    flags: (0x0012) ACC_PRIVATE, ACC_FINAL
    Signature: #44                          // Lscala/collection/immutable/IndexedSeq<Lorg/scalatest/Suite;>;

  private java.lang.String styleName;
    descriptor: Ljava/lang/String;
    flags: (0x0002) ACC_PRIVATE
    Deprecated: true

  private org.scalatest.compatible.Assertion succeed;
    descriptor: Lorg/scalatest/compatible/Assertion;
    flags: (0x0002) ACC_PRIVATE

  public final void execute(java.lang.String, org.scalatest.ConfigMap, boolean, boolean, boolean, boolean, boolean);
    descriptor: (Ljava/lang/String;Lorg/scalatest/ConfigMap;ZZZZZ)V
    flags: (0x0011) ACC_PUBLIC, ACC_FINAL
    Code:
      stack=8, locals=8, args_size=8
         0: aload_0
         1: aload_1
         2: aload_2
         3: iload_3
         4: iload         4
         6: iload         5
         8: iload         6
        10: iload         7
        12: invokestatic  #60                 // InterfaceMethod org/scalatest/Suite.execute$:(Lorg/scalatest/Suite;Ljava/lang/String;Lorg/scalatest/ConfigMap;ZZZZZ)V
        15: return
      LineNumberTable:
        line 30: 0
      LocalVariableTable:
        Start  Length  Slot  Name   Signature
            0      16     0  this   Lorg/scalatest/tools/DiscoverySuite;
            0      16     1 testName   Ljava/lang/String;
            0      16     2 configMap   Lorg/scalatest/ConfigMap;
            0      16     3 color   Z
            0      16     4 durations   Z
            0      16     5 shortstacks   Z
            0      16     6 fullstacks   Z
            0      16     7 stats   Z
    MethodParameters:
      Name                           Flags
      testName                       final
      configMap                      final
      color                          final
      durations                      final
      shortstacks                    final
      fullstacks                     final
      stats                          final

  public final java.lang.String execute$default$1();
    descriptor: ()Ljava/lang/String;
    flags: (0x0011) ACC_PUBLIC, ACC_FINAL
    Code:
      stack=1, locals=1, args_size=1
         0: aload_0
         1: invokestatic  #70                 // InterfaceMethod org/scalatest/Suite.execute$default$1$:(Lorg/scalatest/Suite;)Ljava/lang/String;
         4: areturn
      LineNumberTable:
        line 30: 0
      LocalVariableTable:
        Start  Length  Slot  Name   Signature
            0       5     0  this   Lorg/scalatest/tools/DiscoverySuite;

  public final org.scalatest.ConfigMap execute$default$2();
    descriptor: ()Lorg/scalatest/ConfigMap;
    flags: (0x0011) ACC_PUBLIC, ACC_FINAL
    Code:
      stack=1, locals=1, args_size=1
         0: aload_0
         1: invokestatic  #76                 // InterfaceMethod org/scalatest/Suite.execute$default$2$:(Lorg/scalatest/Suite;)Lorg/scalatest/ConfigMap;
         4: areturn
      LineNumberTable:
        line 30: 0
      LocalVariableTable:
        Start  Length  Slot  Name   Signature
            0       5     0  this   Lorg/scalatest/tools/DiscoverySuite;

  public final boolean execute$default$3();
    descriptor: ()Z
    flags: (0x0011) ACC_PUBLIC, ACC_FINAL
    Code:
      stack=1, locals=1, args_size=1
         0: aload_0
         1: invokestatic  #82                 // InterfaceMethod org/scalatest/Suite.execute$default$3$:(Lorg/scalatest/Suite;)Z
         4: ireturn
      LineNumberTable:
        line 30: 0
      LocalVariableTable:
        Start  Length  Slot  Name   Signature
            0       5     0  this   Lorg/scalatest/tools/DiscoverySuite;

  public final boolean execute$default$4();
    descriptor: ()Z
    flags: (0x0011) ACC_PUBLIC, ACC_FINAL
    Code:
      stack=1, locals=1, args_size=1
         0: aload_0
         1: invokestatic  #86                 // InterfaceMethod org/scalatest/Suite.execute$default$4$:(Lorg/scalatest/Suite;)Z
         4: ireturn
      LineNumberTable:
        line 30: 0
      LocalVariableTable:
        Start  Length  Slot  Name   Signature
            0       5     0  this   Lorg/scalatest/tools/DiscoverySuite;

  public final boolean execute$default$5();
    descriptor: ()Z
    flags: (0x0011) ACC_PUBLIC, ACC_FINAL
    Code:
      stack=1, locals=1, args_size=1
         0: aload_0
         1: invokestatic  #90                 // InterfaceMethod org/scalatest/Suite.execute$default$5$:(Lorg/scalatest/Suite;)Z
         4: ireturn
      LineNumberTable:
        line 30: 0
      LocalVariableTable:
        Start  Length  Slot  Name   Signature
            0       5     0  this   Lorg/scalatest/tools/DiscoverySuite;

  public final boolean execute$default$6();
    descriptor: ()Z
    flags: (0x0011) ACC_PUBLIC, ACC_FINAL
    Code:
      stack=1, locals=1, args_size=1
         0: aload_0
         1: invokestatic  #94                 // InterfaceMethod org/scalatest/Suite.execute$default$6$:(Lorg/scalatest/Suite;)Z
         4: ireturn
      LineNumberTable:
        line 30: 0
      LocalVariableTable:
        Start  Length  Slot  Name   Signature
            0       5     0  this   Lorg/scalatest/tools/DiscoverySuite;

  public final boolean execute$default$7();
    descriptor: ()Z
    flags: (0x0011) ACC_PUBLIC, ACC_FINAL
    Code:
      stack=1, locals=1, args_size=1
         0: aload_0
         1: invokestatic  #98                 // InterfaceMethod org/scalatest/Suite.execute$default$7$:(Lorg/scalatest/Suite;)Z
         4: ireturn
      LineNumberTable:
        line 30: 0
      LocalVariableTable:
        Start  Length  Slot  Name   Signature
            0       5     0  this   Lorg/scalatest/tools/DiscoverySuite;

  public scala.collection.immutable.Map<java.lang.String, scala.collection.immutable.Set<java.lang.String>> tags();
    descriptor: ()Lscala/collection/immutable/Map;
    flags: (0x0001) ACC_PUBLIC
    Code:
      stack=1, locals=1, args_size=1
         0: aload_0
         1: invokestatic  #105                // InterfaceMethod org/scalatest/Suite.tags$:(Lorg/scalatest/Suite;)Lscala/collection/immutable/Map;
         4: areturn
      LineNumberTable:
        line 30: 0
      LocalVariableTable:
        Start  Length  Slot  Name   Signature
            0       5     0  this   Lorg/scalatest/tools/DiscoverySuite;
    Signature: #101                         // ()Lscala/collection/immutable/Map<Ljava/lang/String;Lscala/collection/immutable/Set<Ljava/lang/String;>;>;

  public scala.collection.immutable.Set<java.lang.String> testNames();
    descriptor: ()Lscala/collection/immutable/Set;
    flags: (0x0001) ACC_PUBLIC
    Code:
      stack=1, locals=1, args_size=1
         0: aload_0
         1: invokestatic  #112                // InterfaceMethod org/scalatest/Suite.testNames$:(Lorg/scalatest/Suite;)Lscala/collection/immutable/Set;
         4: areturn
      LineNumberTable:
        line 30: 0
      LocalVariableTable:
        Start  Length  Slot  Name   Signature
            0       5     0  this   Lorg/scalatest/tools/DiscoverySuite;
    Signature: #108                         // ()Lscala/collection/immutable/Set<Ljava/lang/String;>;

  public org.scalatest.Status runTest(java.lang.String, org.scalatest.Args);
    descriptor: (Ljava/lang/String;Lorg/scalatest/Args;)Lorg/scalatest/Status;
    flags: (0x0001) ACC_PUBLIC
    Code:
      stack=3, locals=3, args_size=3
         0: aload_0
         1: aload_1
         2: aload_2
         3: invokestatic  #119                // InterfaceMethod org/scalatest/Suite.runTest$:(Lorg/scalatest/Suite;Ljava/lang/String;Lorg/scalatest/Args;)Lorg/scalatest/Status;
         6: areturn
      LineNumberTable:
        line 30: 0
      LocalVariableTable:
        Start  Length  Slot  Name   Signature
            0       7     0  this   Lorg/scalatest/tools/DiscoverySuite;
            0       7     1 testName   Ljava/lang/String;
            0       7     2  args   Lorg/scalatest/Args;
    MethodParameters:
      Name                           Flags
      testName                       final
      args                           final

  public org.scalatest.Status run(scala.Option<java.lang.String>, org.scalatest.Args);
    descriptor: (Lscala/Option;Lorg/scalatest/Args;)Lorg/scalatest/Status;
    flags: (0x0001) ACC_PUBLIC
    Code:
      stack=3, locals=3, args_size=3
         0: aload_0
         1: aload_1
         2: aload_2
         3: invokestatic  #127                // InterfaceMethod org/scalatest/Suite.run$:(Lorg/scalatest/Suite;Lscala/Option;Lorg/scalatest/Args;)Lorg/scalatest/Status;
         6: areturn
      LineNumberTable:
        line 30: 0
      LocalVariableTable:
        Start  Length  Slot  Name   Signature
            0       7     0  this   Lorg/scalatest/tools/DiscoverySuite;
            0       7     1 testName   Lscala/Option;
            0       7     2  args   Lorg/scalatest/Args;
    Signature: #123                         // (Lscala/Option<Ljava/lang/String;>;Lorg/scalatest/Args;)Lorg/scalatest/Status;
    MethodParameters:
      Name                           Flags
      testName                       final
      args                           final

  public org.scalatest.Status runNestedSuites(org.scalatest.Args);
    descriptor: (Lorg/scalatest/Args;)Lorg/scalatest/Status;
    flags: (0x0001) ACC_PUBLIC
    Code:
      stack=2, locals=2, args_size=2
         0: aload_0
         1: aload_1
         2: invokestatic  #134                // InterfaceMethod org/scalatest/Suite.runNestedSuites$:(Lorg/scalatest/Suite;Lorg/scalatest/Args;)Lorg/scalatest/Status;
         5: areturn
      LineNumberTable:
        line 30: 0
      LocalVariableTable:
        Start  Length  Slot  Name   Signature
            0       6     0  this   Lorg/scalatest/tools/DiscoverySuite;
            0       6     1  args   Lorg/scalatest/Args;
    MethodParameters:
      Name                           Flags
      args                           final

  public java.lang.String suiteName();
    descriptor: ()Ljava/lang/String;
    flags: (0x0001) ACC_PUBLIC
    Code:
      stack=1, locals=1, args_size=1
         0: aload_0
         1: invokestatic  #138                // InterfaceMethod org/scalatest/Suite.suiteName$:(Lorg/scalatest/Suite;)Ljava/lang/String;
         4: areturn
      LineNumberTable:
        line 30: 0
      LocalVariableTable:
        Start  Length  Slot  Name   Signature
            0       5     0  this   Lorg/scalatest/tools/DiscoverySuite;

  public int expectedTestCount(org.scalatest.Filter);
    descriptor: (Lorg/scalatest/Filter;)I
    flags: (0x0001) ACC_PUBLIC
    Code:
      stack=2, locals=2, args_size=2
         0: aload_0
         1: aload_1
         2: invokestatic  #145                // InterfaceMethod org/scalatest/Suite.expectedTestCount$:(Lorg/scalatest/Suite;Lorg/scalatest/Filter;)I
         5: ireturn
      LineNumberTable:
        line 30: 0
      LocalVariableTable:
        Start  Length  Slot  Name   Signature
            0       6     0  this   Lorg/scalatest/tools/DiscoverySuite;
            0       6     1 filter   Lorg/scalatest/Filter;
    MethodParameters:
      Name                           Flags
      filter                         final

  public org.scalatest.Reporter createCatchReporter(org.scalatest.Reporter);
    descriptor: (Lorg/scalatest/Reporter;)Lorg/scalatest/Reporter;
    flags: (0x0001) ACC_PUBLIC
    Code:
      stack=2, locals=2, args_size=2
         0: aload_0
         1: aload_1
         2: invokestatic  #153                // InterfaceMethod org/scalatest/Suite.createCatchReporter$:(Lorg/scalatest/Suite;Lorg/scalatest/Reporter;)Lorg/scalatest/Reporter;
         5: areturn
      LineNumberTable:
        line 30: 0
      LocalVariableTable:
        Start  Length  Slot  Name   Signature
            0       6     0  this   Lorg/scalatest/tools/DiscoverySuite;
            0       6     1 reporter   Lorg/scalatest/Reporter;
    MethodParameters:
      Name                           Flags
      reporter                       final

  public scala.Option<java.lang.String> rerunner();
    descriptor: ()Lscala/Option;
    flags: (0x0001) ACC_PUBLIC
    Code:
      stack=1, locals=1, args_size=1
         0: aload_0
         1: invokestatic  #161                // InterfaceMethod org/scalatest/Suite.rerunner$:(Lorg/scalatest/Suite;)Lscala/Option;
         4: areturn
      LineNumberTable:
        line 30: 0
      LocalVariableTable:
        Start  Length  Slot  Name   Signature
            0       5     0  this   Lorg/scalatest/tools/DiscoverySuite;
    Signature: #157                         // ()Lscala/Option<Ljava/lang/String;>;

  public org.scalatest.TestData testDataFor(java.lang.String, org.scalatest.ConfigMap);
    descriptor: (Ljava/lang/String;Lorg/scalatest/ConfigMap;)Lorg/scalatest/TestData;
    flags: (0x0001) ACC_PUBLIC
    Code:
      stack=3, locals=3, args_size=3
         0: aload_0
         1: aload_1
         2: aload_2
         3: invokestatic  #168                // InterfaceMethod org/scalatest/Suite.testDataFor$:(Lorg/scalatest/Suite;Ljava/lang/String;Lorg/scalatest/ConfigMap;)Lorg/scalatest/TestData;
         6: areturn
      LineNumberTable:
        line 30: 0
      LocalVariableTable:
        Start  Length  Slot  Name   Signature
            0       7     0  this   Lorg/scalatest/tools/DiscoverySuite;
            0       7     1 testName   Ljava/lang/String;
            0       7     2 theConfigMap   Lorg/scalatest/ConfigMap;
    MethodParameters:
      Name                           Flags
      testName                       final
      theConfigMap                   final

  public org.scalatest.ConfigMap testDataFor$default$2();
    descriptor: ()Lorg/scalatest/ConfigMap;
    flags: (0x0001) ACC_PUBLIC
    Code:
      stack=1, locals=1, args_size=1
         0: aload_0
         1: invokestatic  #172                // InterfaceMethod org/scalatest/Suite.testDataFor$default$2$:(Lorg/scalatest/Suite;)Lorg/scalatest/ConfigMap;
         4: areturn
      LineNumberTable:
        line 30: 0
      LocalVariableTable:
        Start  Length  Slot  Name   Signature
            0       5     0  this   Lorg/scalatest/tools/DiscoverySuite;

  public java.lang.Throwable newAssertionFailedException(scala.Option<java.lang.String>, scala.Option<java.lang.Throwable>, org.scalactic.source.Position, scala.collection.immutable.IndexedSeq<java.lang.String>);
    descriptor: (Lscala/Option;Lscala/Option;Lorg/scalactic/source/Position;Lscala/collection/immutable/IndexedSeq;)Ljava/lang/Throwable;
    flags: (0x0001) ACC_PUBLIC
    Code:
      stack=5, locals=5, args_size=5
         0: aload_0
         1: aload_1
         2: aload_2
         3: aload_3
         4: aload         4
         6: invokestatic  #185                // InterfaceMethod org/scalatest/Assertions.newAssertionFailedException$:(Lorg/scalatest/Assertions;Lscala/Option;Lscala/Option;Lorg/scalactic/source/Position;Lscala/collection/immutable/IndexedSeq;)Ljava/lang/Throwable;
         9: areturn
      LineNumberTable:
        line 30: 0
      LocalVariableTable:
        Start  Length  Slot  Name   Signature
            0      10     0  this   Lorg/scalatest/tools/DiscoverySuite;
            0      10     1 optionalMessage   Lscala/Option;
            0      10     2 optionalCause   Lscala/Option;
            0      10     3   pos   Lorg/scalactic/source/Position;
            0      10     4 analysis   Lscala/collection/immutable/IndexedSeq;
    Signature: #175                         // (Lscala/Option<Ljava/lang/String;>;Lscala/Option<Ljava/lang/Throwable;>;Lorg/scalactic/source/Position;Lscala/collection/immutable/IndexedSeq<Ljava/lang/String;>;)Ljava/lang/Throwable;
    MethodParameters:
      Name                           Flags
      optionalMessage                final
      optionalCause                  final
      pos                            final
      analysis                       final

  public java.lang.Throwable newTestCanceledException(scala.Option<java.lang.String>, scala.Option<java.lang.Throwable>, org.scalactic.source.Position);
    descriptor: (Lscala/Option;Lscala/Option;Lorg/scalactic/source/Position;)Ljava/lang/Throwable;
    flags: (0x0001) ACC_PUBLIC
    Code:
      stack=4, locals=4, args_size=4
         0: aload_0
         1: aload_1
         2: aload_2
         3: aload_3
         4: invokestatic  #193                // InterfaceMethod org/scalatest/Assertions.newTestCanceledException$:(Lorg/scalatest/Assertions;Lscala/Option;Lscala/Option;Lorg/scalactic/source/Position;)Ljava/lang/Throwable;
         7: areturn
      LineNumberTable:
        line 30: 0
      LocalVariableTable:
        Start  Length  Slot  Name   Signature
            0       8     0  this   Lorg/scalatest/tools/DiscoverySuite;
            0       8     1 optionalMessage   Lscala/Option;
            0       8     2 optionalCause   Lscala/Option;
            0       8     3   pos   Lorg/scalactic/source/Position;
    Signature: #189                         // (Lscala/Option<Ljava/lang/String;>;Lscala/Option<Ljava/lang/Throwable;>;Lorg/scalactic/source/Position;)Ljava/lang/Throwable;
    MethodParameters:
      Name                           Flags
      optionalMessage                final
      optionalCause                  final
      pos                            final

  public <T extends java.lang.Object> T intercept(scala.Function0<java.lang.Object>, scala.reflect.ClassTag<T>, org.scalactic.source.Position);
    descriptor: (Lscala/Function0;Lscala/reflect/ClassTag;Lorg/scalactic/source/Position;)Ljava/lang/Object;
    flags: (0x0001) ACC_PUBLIC
    Code:
      stack=4, locals=4, args_size=4
         0: aload_0
         1: aload_1
         2: aload_2
         3: aload_3
         4: invokestatic  #202                // InterfaceMethod org/scalatest/Assertions.intercept$:(Lorg/scalatest/Assertions;Lscala/Function0;Lscala/reflect/ClassTag;Lorg/scalactic/source/Position;)Ljava/lang/Object;
         7: areturn
      LineNumberTable:
        line 30: 0
      LocalVariableTable:
        Start  Length  Slot  Name   Signature
            0       8     0  this   Lorg/scalatest/tools/DiscoverySuite;
            0       8     1     f   Lscala/Function0;
            0       8     2 classTag   Lscala/reflect/ClassTag;
            0       8     3   pos   Lorg/scalactic/source/Position;
    Signature: #196                         // <T:Ljava/lang/Object;>(Lscala/Function0<Ljava/lang/Object;>;Lscala/reflect/ClassTag<TT;>;Lorg/scalactic/source/Position;)TT;
    MethodParameters:
      Name                           Flags
      f                              final
      classTag                       final
      pos                            final

  public <T extends java.lang.Object> org.scalatest.compatible.Assertion assertThrows(scala.Function0<java.lang.Object>, scala.reflect.ClassTag<T>, org.scalactic.source.Position);
    descriptor: (Lscala/Function0;Lscala/reflect/ClassTag;Lorg/scalactic/source/Position;)Lorg/scalatest/compatible/Assertion;
    flags: (0x0001) ACC_PUBLIC
    Code:
      stack=4, locals=4, args_size=4
         0: aload_0
         1: aload_1
         2: aload_2
         3: aload_3
         4: invokestatic  #211                // InterfaceMethod org/scalatest/Assertions.assertThrows$:(Lorg/scalatest/Assertions;Lscala/Function0;Lscala/reflect/ClassTag;Lorg/scalactic/source/Position;)Lorg/scalatest/compatible/Assertion;
         7: areturn
      LineNumberTable:
        line 30: 0
      LocalVariableTable:
        Start  Length  Slot  Name   Signature
            0       8     0  this   Lorg/scalatest/tools/DiscoverySuite;
            0       8     1     f   Lscala/Function0;
            0       8     2 classTag   Lscala/reflect/ClassTag;
            0       8     3   pos   Lorg/scalactic/source/Position;
    Signature: #207                         // <T:Ljava/lang/Object;>(Lscala/Function0<Ljava/lang/Object;>;Lscala/reflect/ClassTag<TT;>;Lorg/scalactic/source/Position;)Lorg/scalatest/compatible/Assertion;
    MethodParameters:
      Name                           Flags
      f                              final
      classTag                       final
      pos                            final

  public org.scalatest.compatible.Assertion assertResult(java.lang.Object, java.lang.Object, java.lang.Object, org.scalactic.Prettifier, org.scalactic.source.Position);
    descriptor: (Ljava/lang/Object;Ljava/lang/Object;Ljava/lang/Object;Lorg/scalactic/Prettifier;Lorg/scalactic/source/Position;)Lorg/scalatest/compatible/Assertion;
    flags: (0x0001) ACC_PUBLIC
    Code:
      stack=6, locals=6, args_size=6
         0: aload_0
         1: aload_1
         2: aload_2
         3: aload_3
         4: aload         4
         6: aload         5
         8: invokestatic  #221                // InterfaceMethod org/scalatest/Assertions.assertResult$:(Lorg/scalatest/Assertions;Ljava/lang/Object;Ljava/lang/Object;Ljava/lang/Object;Lorg/scalactic/Prettifier;Lorg/scalactic/source/Position;)Lorg/scalatest/compatible/Assertion;
        11: areturn
      LineNumberTable:
        line 30: 0
      LocalVariableTable:
        Start  Length  Slot  Name   Signature
            0      12     0  this   Lorg/scalatest/tools/DiscoverySuite;
            0      12     1 expected   Ljava/lang/Object;
            0      12     2  clue   Ljava/lang/Object;
            0      12     3 actual   Ljava/lang/Object;
            0      12     4 prettifier   Lorg/scalactic/Prettifier;
            0      12     5   pos   Lorg/scalactic/source/Position;
    MethodParameters:
      Name                           Flags
      expected                       final
      clue                           final
      actual                         final
      prettifier                     final
      pos                            final

  public org.scalatest.compatible.Assertion assertResult(java.lang.Object, java.lang.Object, org.scalactic.Prettifier, org.scalactic.source.Position);
    descriptor: (Ljava/lang/Object;Ljava/lang/Object;Lorg/scalactic/Prettifier;Lorg/scalactic/source/Position;)Lorg/scalatest/compatible/Assertion;
    flags: (0x0001) ACC_PUBLIC
    Code:
      stack=5, locals=5, args_size=5
         0: aload_0
         1: aload_1
         2: aload_2
         3: aload_3
         4: aload         4
         6: invokestatic  #227                // InterfaceMethod org/scalatest/Assertions.assertResult$:(Lorg/scalatest/Assertions;Ljava/lang/Object;Ljava/lang/Object;Lorg/scalactic/Prettifier;Lorg/scalactic/source/Position;)Lorg/scalatest/compatible/Assertion;
         9: areturn
      LineNumberTable:
        line 30: 0
      LocalVariableTable:
        Start  Length  Slot  Name   Signature
            0      10     0  this   Lorg/scalatest/tools/DiscoverySuite;
            0      10     1 expected   Ljava/lang/Object;
            0      10     2 actual   Ljava/lang/Object;
            0      10     3 prettifier   Lorg/scalactic/Prettifier;
            0      10     4   pos   Lorg/scalactic/source/Position;
    MethodParameters:
      Name                           Flags
      expected                       final
      actual                         final
      prettifier                     final
      pos                            final

  public scala.runtime.Nothing$ fail(org.scalactic.source.Position);
    descriptor: (Lorg/scalactic/source/Position;)Lscala/runtime/Nothing$;
    flags: (0x0001) ACC_PUBLIC
    Code:
      stack=2, locals=2, args_size=2
         0: aload_0
         1: aload_1
         2: invokestatic  #233                // InterfaceMethod org/scalatest/Assertions.fail$:(Lorg/scalatest/Assertions;Lorg/scalactic/source/Position;)Lscala/runtime/Nothing$;
         5: areturn
      LineNumberTable:
        line 30: 0
      LocalVariableTable:
        Start  Length  Slot  Name   Signature
            0       6     0  this   Lorg/scalatest/tools/DiscoverySuite;
            0       6     1   pos   Lorg/scalactic/source/Position;
    MethodParameters:
      Name                           Flags
      pos                            final

  public scala.runtime.Nothing$ fail(java.lang.String, org.scalactic.source.Position);
    descriptor: (Ljava/lang/String;Lorg/scalactic/source/Position;)Lscala/runtime/Nothing$;
    flags: (0x0001) ACC_PUBLIC
    Code:
      stack=3, locals=3, args_size=3
         0: aload_0
         1: aload_1
         2: aload_2
         3: invokestatic  #238                // InterfaceMethod org/scalatest/Assertions.fail$:(Lorg/scalatest/Assertions;Ljava/lang/String;Lorg/scalactic/source/Position;)Lscala/runtime/Nothing$;
         6: areturn
      LineNumberTable:
        line 30: 0
      LocalVariableTable:
        Start  Length  Slot  Name   Signature
            0       7     0  this   Lorg/scalatest/tools/DiscoverySuite;
            0       7     1 message   Ljava/lang/String;
            0       7     2   pos   Lorg/scalactic/source/Position;
    MethodParameters:
      Name                           Flags
      message                        final
      pos                            final

  public scala.runtime.Nothing$ fail(java.lang.String, java.lang.Throwable, org.scalactic.source.Position);
    descriptor: (Ljava/lang/String;Ljava/lang/Throwable;Lorg/scalactic/source/Position;)Lscala/runtime/Nothing$;
    flags: (0x0001) ACC_PUBLIC
    Code:
      stack=4, locals=4, args_size=4
         0: aload_0
         1: aload_1
         2: aload_2
         3: aload_3
         4: invokestatic  #243                // InterfaceMethod org/scalatest/Assertions.fail$:(Lorg/scalatest/Assertions;Ljava/lang/String;Ljava/lang/Throwable;Lorg/scalactic/source/Position;)Lscala/runtime/Nothing$;
         7: areturn
      LineNumberTable:
        line 30: 0
      LocalVariableTable:
        Start  Length  Slot  Name   Signature
            0       8     0  this   Lorg/scalatest/tools/DiscoverySuite;
            0       8     1 message   Ljava/lang/String;
            0       8     2 cause   Ljava/lang/Throwable;
            0       8     3   pos   Lorg/scalactic/source/Position;
    MethodParameters:
      Name                           Flags
      message                        final
      cause                          final
      pos                            final

  public scala.runtime.Nothing$ fail(java.lang.Throwable, org.scalactic.source.Position);
    descriptor: (Ljava/lang/Throwable;Lorg/scalactic/source/Position;)Lscala/runtime/Nothing$;
    flags: (0x0001) ACC_PUBLIC
    Code:
      stack=3, locals=3, args_size=3
         0: aload_0
         1: aload_1
         2: aload_2
         3: invokestatic  #248                // InterfaceMethod org/scalatest/Assertions.fail$:(Lorg/scalatest/Assertions;Ljava/lang/Throwable;Lorg/scalactic/source/Position;)Lscala/runtime/Nothing$;
         6: areturn
      LineNumberTable:
        line 30: 0
      LocalVariableTable:
        Start  Length  Slot  Name   Signature
            0       7     0  this   Lorg/scalatest/tools/DiscoverySuite;
            0       7     1 cause   Ljava/lang/Throwable;
            0       7     2   pos   Lorg/scalactic/source/Position;
    MethodParameters:
      Name                           Flags
      cause                          final
      pos                            final

  public scala.runtime.Nothing$ cancel(org.scalactic.source.Position);
    descriptor: (Lorg/scalactic/source/Position;)Lscala/runtime/Nothing$;
    flags: (0x0001) ACC_PUBLIC
    Code:
      stack=2, locals=2, args_size=2
         0: aload_0
         1: aload_1
         2: invokestatic  #252                // InterfaceMethod org/scalatest/Assertions.cancel$:(Lorg/scalatest/Assertions;Lorg/scalactic/source/Position;)Lscala/runtime/Nothing$;
         5: areturn
      LineNumberTable:
        line 30: 0
      LocalVariableTable:
        Start  Length  Slot  Name   Signature
            0       6     0  this   Lorg/scalatest/tools/DiscoverySuite;
            0       6     1   pos   Lorg/scalactic/source/Position;
    MethodParameters:
      Name                           Flags
      pos                            final

  public scala.runtime.Nothing$ cancel(java.lang.String, org.scalactic.source.Position);
    descriptor: (Ljava/lang/String;Lorg/scalactic/source/Position;)Lscala/runtime/Nothing$;
    flags: (0x0001) ACC_PUBLIC
    Code:
      stack=3, locals=3, args_size=3
         0: aload_0
         1: aload_1
         2: aload_2
         3: invokestatic  #254                // InterfaceMethod org/scalatest/Assertions.cancel$:(Lorg/scalatest/Assertions;Ljava/lang/String;Lorg/scalactic/source/Position;)Lscala/runtime/Nothing$;
         6: areturn
      LineNumberTable:
        line 30: 0
      LocalVariableTable:
        Start  Length  Slot  Name   Signature
            0       7     0  this   Lorg/scalatest/tools/DiscoverySuite;
            0       7     1 message   Ljava/lang/String;
            0       7     2   pos   Lorg/scalactic/source/Position;
    MethodParameters:
      Name                           Flags
      message                        final
      pos                            final

  public scala.runtime.Nothing$ cancel(java.lang.String, java.lang.Throwable, org.scalactic.source.Position);
    descriptor: (Ljava/lang/String;Ljava/lang/Throwable;Lorg/scalactic/source/Position;)Lscala/runtime/Nothing$;
    flags: (0x0001) ACC_PUBLIC
    Code:
      stack=4, locals=4, args_size=4
         0: aload_0
         1: aload_1
         2: aload_2
         3: aload_3
         4: invokestatic  #256                // InterfaceMethod org/scalatest/Assertions.cancel$:(Lorg/scalatest/Assertions;Ljava/lang/String;Ljava/lang/Throwable;Lorg/scalactic/source/Position;)Lscala/runtime/Nothing$;
         7: areturn
      LineNumberTable:
        line 30: 0
      LocalVariableTable:
        Start  Length  Slot  Name   Signature
            0       8     0  this   Lorg/scalatest/tools/DiscoverySuite;
            0       8     1 message   Ljava/lang/String;
            0       8     2 cause   Ljava/lang/Throwable;
            0       8     3   pos   Lorg/scalactic/source/Position;
    MethodParameters:
      Name                           Flags
      message                        final
      cause                          final
      pos                            final

  public scala.runtime.Nothing$ cancel(java.lang.Throwable, org.scalactic.source.Position);
    descriptor: (Ljava/lang/Throwable;Lorg/scalactic/source/Position;)Lscala/runtime/Nothing$;
    flags: (0x0001) ACC_PUBLIC
    Code:
      stack=3, locals=3, args_size=3
         0: aload_0
         1: aload_1
         2: aload_2
         3: invokestatic  #258                // InterfaceMethod org/scalatest/Assertions.cancel$:(Lorg/scalatest/Assertions;Ljava/lang/Throwable;Lorg/scalactic/source/Position;)Lscala/runtime/Nothing$;
         6: areturn
      LineNumberTable:
        line 30: 0
      LocalVariableTable:
        Start  Length  Slot  Name   Signature
            0       7     0  this   Lorg/scalatest/tools/DiscoverySuite;
            0       7     1 cause   Ljava/lang/Throwable;
            0       7     2   pos   Lorg/scalactic/source/Position;
    MethodParameters:
      Name                           Flags
      cause                          final
      pos                            final

  public <T extends java.lang.Object> T withClue(java.lang.Object, scala.Function0<T>);
    descriptor: (Ljava/lang/Object;Lscala/Function0;)Ljava/lang/Object;
    flags: (0x0001) ACC_PUBLIC
    Code:
      stack=3, locals=3, args_size=3
         0: aload_0
         1: aload_1
         2: aload_2
         3: invokestatic  #266                // InterfaceMethod org/scalatest/Assertions.withClue$:(Lorg/scalatest/Assertions;Ljava/lang/Object;Lscala/Function0;)Ljava/lang/Object;
         6: areturn
      LineNumberTable:
        line 30: 0
      LocalVariableTable:
        Start  Length  Slot  Name   Signature
            0       7     0  this   Lorg/scalatest/tools/DiscoverySuite;
            0       7     1  clue   Ljava/lang/Object;
            0       7     2   fun   Lscala/Function0;
    Signature: #261                         // <T:Ljava/lang/Object;>(Ljava/lang/Object;Lscala/Function0<TT;>;)TT;
    MethodParameters:
      Name                           Flags
      clue                           final
      fun                            final

  public org.scalatest.compatible.Assertion pending();
    descriptor: ()Lorg/scalatest/compatible/Assertion;
    flags: (0x0001) ACC_PUBLIC
    Code:
      stack=1, locals=1, args_size=1
         0: aload_0
         1: invokestatic  #272                // InterfaceMethod org/scalatest/Assertions.pending$:(Lorg/scalatest/Assertions;)Lorg/scalatest/compatible/Assertion;
         4: areturn
      LineNumberTable:
        line 30: 0
      LocalVariableTable:
        Start  Length  Slot  Name   Signature
            0       5     0  this   Lorg/scalatest/tools/DiscoverySuite;

  public org.scalatest.compatible.Assertion pendingUntilFixed(scala.Function0<scala.runtime.BoxedUnit>, org.scalactic.source.Position);
    descriptor: (Lscala/Function0;Lorg/scalactic/source/Position;)Lorg/scalatest/compatible/Assertion;
    flags: (0x0001) ACC_PUBLIC
    Code:
      stack=3, locals=3, args_size=3
         0: aload_0
         1: aload_1
         2: aload_2
         3: invokestatic  #279                // InterfaceMethod org/scalatest/Assertions.pendingUntilFixed$:(Lorg/scalatest/Assertions;Lscala/Function0;Lorg/scalactic/source/Position;)Lorg/scalatest/compatible/Assertion;
         6: areturn
      LineNumberTable:
        line 30: 0
      LocalVariableTable:
        Start  Length  Slot  Name   Signature
            0       7     0  this   Lorg/scalatest/tools/DiscoverySuite;
            0       7     1     f   Lscala/Function0;
            0       7     2   pos   Lorg/scalactic/source/Position;
    Signature: #275                         // (Lscala/Function0<Lscala/runtime/BoxedUnit;>;Lorg/scalactic/source/Position;)Lorg/scalatest/compatible/Assertion;
    MethodParameters:
      Name                           Flags
      f                              final
      pos                            final

  public <T extends java.lang.Object> org.scalactic.TripleEqualsSupport$Equalizer<T> convertToEqualizer(T);
    descriptor: (Ljava/lang/Object;)Lorg/scalactic/TripleEqualsSupport$Equalizer;
    flags: (0x0001) ACC_PUBLIC
    Code:
      stack=2, locals=2, args_size=2
         0: aload_0
         1: aload_1
         2: invokestatic  #289                // InterfaceMethod org/scalactic/TripleEquals.convertToEqualizer$:(Lorg/scalactic/TripleEquals;Ljava/lang/Object;)Lorg/scalactic/TripleEqualsSupport$Equalizer;
         5: areturn
      LineNumberTable:
        line 30: 0
      LocalVariableTable:
        Start  Length  Slot  Name   Signature
            0       6     0  this   Lorg/scalatest/tools/DiscoverySuite;
            0       6     1  left   Ljava/lang/Object;
    Signature: #282                         // <T:Ljava/lang/Object;>(TT;)Lorg/scalactic/TripleEqualsSupport$Equalizer<TT;>;
    MethodParameters:
      Name                           Flags
      left                           final

  public <T extends java.lang.Object> org.scalactic.TripleEqualsSupport$CheckingEqualizer<T> convertToCheckingEqualizer(T);
    descriptor: (Ljava/lang/Object;)Lorg/scalactic/TripleEqualsSupport$CheckingEqualizer;
    flags: (0x0001) ACC_PUBLIC
    Code:
      stack=2, locals=2, args_size=2
         0: aload_0
         1: aload_1
         2: invokestatic  #296                // InterfaceMethod org/scalactic/TripleEquals.convertToCheckingEqualizer$:(Lorg/scalactic/TripleEquals;Ljava/lang/Object;)Lorg/scalactic/TripleEqualsSupport$CheckingEqualizer;
         5: areturn
      LineNumberTable:
        line 30: 0
      LocalVariableTable:
        Start  Length  Slot  Name   Signature
            0       6     0  this   Lorg/scalatest/tools/DiscoverySuite;
            0       6     1  left   Ljava/lang/Object;
    Signature: #292                         // <T:Ljava/lang/Object;>(TT;)Lorg/scalactic/TripleEqualsSupport$CheckingEqualizer<TT;>;
    MethodParameters:
      Name                           Flags
      left                           final

  public <A extends java.lang.Object, B extends java.lang.Object> org.scalactic.CanEqual<A, B> unconstrainedEquality(org.scalactic.Equality<A>);
    descriptor: (Lorg/scalactic/Equality;)Lorg/scalactic/CanEqual;
    flags: (0x0001) ACC_PUBLIC
    Code:
      stack=2, locals=2, args_size=2
         0: aload_0
         1: aload_1
         2: invokestatic  #304                // InterfaceMethod org/scalactic/TripleEquals.unconstrainedEquality$:(Lorg/scalactic/TripleEquals;Lorg/scalactic/Equality;)Lorg/scalactic/CanEqual;
         5: areturn
      LineNumberTable:
        line 30: 0
      LocalVariableTable:
        Start  Length  Slot  Name   Signature
            0       6     0  this   Lorg/scalatest/tools/DiscoverySuite;
            0       6     1 equalityOfA   Lorg/scalactic/Equality;
    Signature: #299                         // <A:Ljava/lang/Object;B:Ljava/lang/Object;>(Lorg/scalactic/Equality<TA;>;)Lorg/scalactic/CanEqual<TA;TB;>;
    MethodParameters:
      Name                           Flags
      equalityOfA                    final

  public <A extends java.lang.Object, B extends java.lang.Object> org.scalactic.CanEqual<A, B> lowPriorityTypeCheckedConstraint(org.scalactic.Equivalence<B>, scala.$less$colon$less<A, B>);
    descriptor: (Lorg/scalactic/Equivalence;Lscala/$less$colon$less;)Lorg/scalactic/CanEqual;
    flags: (0x0001) ACC_PUBLIC
    Code:
      stack=3, locals=3, args_size=3
         0: aload_0
         1: aload_1
         2: aload_2
         3: invokestatic  #314                // InterfaceMethod org/scalactic/TripleEquals.lowPriorityTypeCheckedConstraint$:(Lorg/scalactic/TripleEquals;Lorg/scalactic/Equivalence;Lscala/$less$colon$less;)Lorg/scalactic/CanEqual;
         6: areturn
      LineNumberTable:
        line 30: 0
      LocalVariableTable:
        Start  Length  Slot  Name   Signature
            0       7     0  this   Lorg/scalatest/tools/DiscoverySuite;
            0       7     1 equivalenceOfB   Lorg/scalactic/Equivalence;
            0       7     2    ev   Lscala/$less$colon$less;
    Signature: #308                         // <A:Ljava/lang/Object;B:Ljava/lang/Object;>(Lorg/scalactic/Equivalence<TB;>;Lscala/$less$colon$less<TA;TB;>;)Lorg/scalactic/CanEqual<TA;TB;>;
    MethodParameters:
      Name                           Flags
      equivalenceOfB                 final
      ev                             final

  public <A extends java.lang.Object, B extends java.lang.Object> org.scalactic.CanEqual<A, B> convertEquivalenceToAToBConstraint(org.scalactic.Equivalence<B>, scala.$less$colon$less<A, B>);
    descriptor: (Lorg/scalactic/Equivalence;Lscala/$less$colon$less;)Lorg/scalactic/CanEqual;
    flags: (0x0001) ACC_PUBLIC
    Code:
      stack=3, locals=3, args_size=3
         0: aload_0
         1: aload_1
         2: aload_2
         3: invokestatic  #320                // InterfaceMethod org/scalactic/TripleEquals.convertEquivalenceToAToBConstraint$:(Lorg/scalactic/TripleEquals;Lorg/scalactic/Equivalence;Lscala/$less$colon$less;)Lorg/scalactic/CanEqual;
         6: areturn
      LineNumberTable:
        line 30: 0
      LocalVariableTable:
        Start  Length  Slot  Name   Signature
            0       7     0  this   Lorg/scalatest/tools/DiscoverySuite;
            0       7     1 equivalenceOfB   Lorg/scalactic/Equivalence;
            0       7     2    ev   Lscala/$less$colon$less;
    Signature: #308                         // <A:Ljava/lang/Object;B:Ljava/lang/Object;>(Lorg/scalactic/Equivalence<TB;>;Lscala/$less$colon$less<TA;TB;>;)Lorg/scalactic/CanEqual<TA;TB;>;
    MethodParameters:
      Name                           Flags
      equivalenceOfB                 final
      ev                             final

  public <A extends java.lang.Object, B extends java.lang.Object> org.scalactic.CanEqual<A, B> typeCheckedConstraint(org.scalactic.Equivalence<A>, scala.$less$colon$less<B, A>);
    descriptor: (Lorg/scalactic/Equivalence;Lscala/$less$colon$less;)Lorg/scalactic/CanEqual;
    flags: (0x0001) ACC_PUBLIC
    Code:
      stack=3, locals=3, args_size=3
         0: aload_0
         1: aload_1
         2: aload_2
         3: invokestatic  #326                // InterfaceMethod org/scalactic/TripleEquals.typeCheckedConstraint$:(Lorg/scalactic/TripleEquals;Lorg/scalactic/Equivalence;Lscala/$less$colon$less;)Lorg/scalactic/CanEqual;
         6: areturn
      LineNumberTable:
        line 30: 0
      LocalVariableTable:
        Start  Length  Slot  Name   Signature
            0       7     0  this   Lorg/scalatest/tools/DiscoverySuite;
            0       7     1 equivalenceOfA   Lorg/scalactic/Equivalence;
            0       7     2    ev   Lscala/$less$colon$less;
    Signature: #322                         // <A:Ljava/lang/Object;B:Ljava/lang/Object;>(Lorg/scalactic/Equivalence<TA;>;Lscala/$less$colon$less<TB;TA;>;)Lorg/scalactic/CanEqual<TA;TB;>;
    MethodParameters:
      Name                           Flags
      equivalenceOfA                 final
      ev                             final

  public <A extends java.lang.Object, B extends java.lang.Object> org.scalactic.CanEqual<A, B> convertEquivalenceToBToAConstraint(org.scalactic.Equivalence<A>, scala.$less$colon$less<B, A>);
    descriptor: (Lorg/scalactic/Equivalence;Lscala/$less$colon$less;)Lorg/scalactic/CanEqual;
    flags: (0x0001) ACC_PUBLIC
    Code:
      stack=3, locals=3, args_size=3
         0: aload_0
         1: aload_1
         2: aload_2
         3: invokestatic  #330                // InterfaceMethod org/scalactic/TripleEquals.convertEquivalenceToBToAConstraint$:(Lorg/scalactic/TripleEquals;Lorg/scalactic/Equivalence;Lscala/$less$colon$less;)Lorg/scalactic/CanEqual;
         6: areturn
      LineNumberTable:
        line 30: 0
      LocalVariableTable:
        Start  Length  Slot  Name   Signature
            0       7     0  this   Lorg/scalatest/tools/DiscoverySuite;
            0       7     1 equivalenceOfA   Lorg/scalactic/Equivalence;
            0       7     2    ev   Lscala/$less$colon$less;
    Signature: #322                         // <A:Ljava/lang/Object;B:Ljava/lang/Object;>(Lorg/scalactic/Equivalence<TA;>;Lscala/$less$colon$less<TB;TA;>;)Lorg/scalactic/CanEqual<TA;TB;>;
    MethodParameters:
      Name                           Flags
      equivalenceOfA                 final
      ev                             final

  public <A extends java.lang.Object, B extends java.lang.Object> org.scalactic.CanEqual<A, B> lowPriorityConversionCheckedConstraint(org.scalactic.Equivalence<B>, scala.Function1<A, B>);
    descriptor: (Lorg/scalactic/Equivalence;Lscala/Function1;)Lorg/scalactic/CanEqual;
    flags: (0x0001) ACC_PUBLIC
    Code:
      stack=3, locals=3, args_size=3
         0: aload_0
         1: aload_1
         2: aload_2
         3: invokestatic  #338                // InterfaceMethod org/scalactic/TripleEquals.lowPriorityConversionCheckedConstraint$:(Lorg/scalactic/TripleEquals;Lorg/scalactic/Equivalence;Lscala/Function1;)Lorg/scalactic/CanEqual;
         6: areturn
      LineNumberTable:
        line 30: 0
      LocalVariableTable:
        Start  Length  Slot  Name   Signature
            0       7     0  this   Lorg/scalatest/tools/DiscoverySuite;
            0       7     1 equivalenceOfB   Lorg/scalactic/Equivalence;
            0       7     2   cnv   Lscala/Function1;
    Signature: #333                         // <A:Ljava/lang/Object;B:Ljava/lang/Object;>(Lorg/scalactic/Equivalence<TB;>;Lscala/Function1<TA;TB;>;)Lorg/scalactic/CanEqual<TA;TB;>;
    Deprecated: true
    MethodParameters:
      Name                           Flags
      equivalenceOfB                 final
      cnv                            final

  public <A extends java.lang.Object, B extends java.lang.Object> org.scalactic.CanEqual<A, B> convertEquivalenceToAToBConversionConstraint(org.scalactic.Equivalence<B>, scala.Function1<A, B>);
    descriptor: (Lorg/scalactic/Equivalence;Lscala/Function1;)Lorg/scalactic/CanEqual;
    flags: (0x0001) ACC_PUBLIC
    Code:
      stack=3, locals=3, args_size=3
         0: aload_0
         1: aload_1
         2: aload_2
         3: invokestatic  #343                // InterfaceMethod org/scalactic/TripleEquals.convertEquivalenceToAToBConversionConstraint$:(Lorg/scalactic/TripleEquals;Lorg/scalactic/Equivalence;Lscala/Function1;)Lorg/scalactic/CanEqual;
         6: areturn
      LineNumberTable:
        line 30: 0
      LocalVariableTable:
        Start  Length  Slot  Name   Signature
            0       7     0  this   Lorg/scalatest/tools/DiscoverySuite;
            0       7     1 equivalenceOfB   Lorg/scalactic/Equivalence;
            0       7     2    ev   Lscala/Function1;
    Signature: #333                         // <A:Ljava/lang/Object;B:Ljava/lang/Object;>(Lorg/scalactic/Equivalence<TB;>;Lscala/Function1<TA;TB;>;)Lorg/scalactic/CanEqual<TA;TB;>;
    Deprecated: true
    MethodParameters:
      Name                           Flags
      equivalenceOfB                 final
      ev                             final

  public <A extends java.lang.Object, B extends java.lang.Object> org.scalactic.CanEqual<A, B> conversionCheckedConstraint(org.scalactic.Equivalence<A>, scala.Function1<B, A>);
    descriptor: (Lorg/scalactic/Equivalence;Lscala/Function1;)Lorg/scalactic/CanEqual;
    flags: (0x0001) ACC_PUBLIC
    Code:
      stack=3, locals=3, args_size=3
         0: aload_0
         1: aload_1
         2: aload_2
         3: invokestatic  #348                // InterfaceMethod org/scalactic/TripleEquals.conversionCheckedConstraint$:(Lorg/scalactic/TripleEquals;Lorg/scalactic/Equivalence;Lscala/Function1;)Lorg/scalactic/CanEqual;
         6: areturn
      LineNumberTable:
        line 30: 0
      LocalVariableTable:
        Start  Length  Slot  Name   Signature
            0       7     0  this   Lorg/scalatest/tools/DiscoverySuite;
            0       7     1 equivalenceOfA   Lorg/scalactic/Equivalence;
            0       7     2   cnv   Lscala/Function1;
    Signature: #345                         // <A:Ljava/lang/Object;B:Ljava/lang/Object;>(Lorg/scalactic/Equivalence<TA;>;Lscala/Function1<TB;TA;>;)Lorg/scalactic/CanEqual<TA;TB;>;
    Deprecated: true
    MethodParameters:
      Name                           Flags
      equivalenceOfA                 final
      cnv                            final

  public <A extends java.lang.Object, B extends java.lang.Object> org.scalactic.CanEqual<A, B> convertEquivalenceToBToAConversionConstraint(org.scalactic.Equivalence<A>, scala.Function1<B, A>);
    descriptor: (Lorg/scalactic/Equivalence;Lscala/Function1;)Lorg/scalactic/CanEqual;
    flags: (0x0001) ACC_PUBLIC
    Code:
      stack=3, locals=3, args_size=3
         0: aload_0
         1: aload_1
         2: aload_2
         3: invokestatic  #352                // InterfaceMethod org/scalactic/TripleEquals.convertEquivalenceToBToAConversionConstraint$:(Lorg/scalactic/TripleEquals;Lorg/scalactic/Equivalence;Lscala/Function1;)Lorg/scalactic/CanEqual;
         6: areturn
      LineNumberTable:
        line 30: 0
      LocalVariableTable:
        Start  Length  Slot  Name   Signature
            0       7     0  this   Lorg/scalatest/tools/DiscoverySuite;
            0       7     1 equivalenceOfA   Lorg/scalactic/Equivalence;
            0       7     2    ev   Lscala/Function1;
    Signature: #345                         // <A:Ljava/lang/Object;B:Ljava/lang/Object;>(Lorg/scalactic/Equivalence<TA;>;Lscala/Function1<TB;TA;>;)Lorg/scalactic/CanEqual<TA;TB;>;
    Deprecated: true
    MethodParameters:
      Name                           Flags
      equivalenceOfA                 final
      ev                             final

  public <A extends java.lang.Object> org.scalactic.Equality<A> defaultEquality();
    descriptor: ()Lorg/scalactic/Equality;
    flags: (0x0001) ACC_PUBLIC
    Code:
      stack=1, locals=1, args_size=1
         0: aload_0
         1: invokestatic  #359                // InterfaceMethod org/scalactic/TripleEqualsSupport.defaultEquality$:(Lorg/scalactic/TripleEqualsSupport;)Lorg/scalactic/Equality;
         4: areturn
      LineNumberTable:
        line 30: 0
      LocalVariableTable:
        Start  Length  Slot  Name   Signature
            0       5     0  this   Lorg/scalatest/tools/DiscoverySuite;
    Signature: #355                         // <A:Ljava/lang/Object;>()Lorg/scalactic/Equality<TA;>;

  public <T extends java.lang.Object> org.scalactic.TripleEqualsSupport$TripleEqualsInvocation<T> $eq$eq$eq(T);
    descriptor: (Ljava/lang/Object;)Lorg/scalactic/TripleEqualsSupport$TripleEqualsInvocation;
    flags: (0x0001) ACC_PUBLIC
    Code:
      stack=2, locals=2, args_size=2
         0: aload_0
         1: aload_1
         2: invokestatic  #367                // InterfaceMethod org/scalactic/TripleEqualsSupport.$eq$eq$eq$:(Lorg/scalactic/TripleEqualsSupport;Ljava/lang/Object;)Lorg/scalactic/TripleEqualsSupport$TripleEqualsInvocation;
         5: areturn
      LineNumberTable:
        line 30: 0
      LocalVariableTable:
        Start  Length  Slot  Name   Signature
            0       6     0  this   Lorg/scalatest/tools/DiscoverySuite;
            0       6     1 right   Ljava/lang/Object;
    Signature: #362                         // <T:Ljava/lang/Object;>(TT;)Lorg/scalactic/TripleEqualsSupport$TripleEqualsInvocation<TT;>;
    MethodParameters:
      Name                           Flags
      right                          final

  public <T extends java.lang.Object> org.scalactic.TripleEqualsSupport$TripleEqualsInvocation<T> $bang$eq$eq(T);
    descriptor: (Ljava/lang/Object;)Lorg/scalactic/TripleEqualsSupport$TripleEqualsInvocation;
    flags: (0x0001) ACC_PUBLIC
    Code:
      stack=2, locals=2, args_size=2
         0: aload_0
         1: aload_1
         2: invokestatic  #371                // InterfaceMethod org/scalactic/TripleEqualsSupport.$bang$eq$eq$:(Lorg/scalactic/TripleEqualsSupport;Ljava/lang/Object;)Lorg/scalactic/TripleEqualsSupport$TripleEqualsInvocation;
         5: areturn
      LineNumberTable:
        line 30: 0
      LocalVariableTable:
        Start  Length  Slot  Name   Signature
            0       6     0  this   Lorg/scalatest/tools/DiscoverySuite;
            0       6     1 right   Ljava/lang/Object;
    Signature: #362                         // <T:Ljava/lang/Object;>(TT;)Lorg/scalactic/TripleEqualsSupport$TripleEqualsInvocation<TT;>;
    MethodParameters:
      Name                           Flags
      right                          final

  public org.scalactic.TripleEqualsSupport$TripleEqualsInvocation<scala.runtime.Null$> $eq$eq$eq(scala.runtime.Null$);
    descriptor: (Lscala/runtime/Null$;)Lorg/scalactic/TripleEqualsSupport$TripleEqualsInvocation;
    flags: (0x0001) ACC_PUBLIC
    Code:
      stack=2, locals=2, args_size=2
         0: aload_0
         1: aload_1
         2: invokestatic  #376                // InterfaceMethod org/scalactic/TripleEqualsSupport.$eq$eq$eq$:(Lorg/scalactic/TripleEqualsSupport;Lscala/runtime/Null$;)Lorg/scalactic/TripleEqualsSupport$TripleEqualsInvocation;
         5: areturn
      LineNumberTable:
        line 30: 0
      LocalVariableTable:
        Start  Length  Slot  Name   Signature
            0       6     0  this   Lorg/scalatest/tools/DiscoverySuite;
            0       6     1 right   Lscala/runtime/Null$;
    Signature: #373                         // (Lscala/runtime/Null$;)Lorg/scalactic/TripleEqualsSupport$TripleEqualsInvocation<Lscala/runtime/Null$;>;
    MethodParameters:
      Name                           Flags
      right                          final

  public org.scalactic.TripleEqualsSupport$TripleEqualsInvocation<scala.runtime.Null$> $bang$eq$eq(scala.runtime.Null$);
    descriptor: (Lscala/runtime/Null$;)Lorg/scalactic/TripleEqualsSupport$TripleEqualsInvocation;
    flags: (0x0001) ACC_PUBLIC
    Code:
      stack=2, locals=2, args_size=2
         0: aload_0
         1: aload_1
         2: invokestatic  #379                // InterfaceMethod org/scalactic/TripleEqualsSupport.$bang$eq$eq$:(Lorg/scalactic/TripleEqualsSupport;Lscala/runtime/Null$;)Lorg/scalactic/TripleEqualsSupport$TripleEqualsInvocation;
         5: areturn
      LineNumberTable:
        line 30: 0
      LocalVariableTable:
        Start  Length  Slot  Name   Signature
            0       6     0  this   Lorg/scalatest/tools/DiscoverySuite;
            0       6     1 right   Lscala/runtime/Null$;
    Signature: #373                         // (Lscala/runtime/Null$;)Lorg/scalactic/TripleEqualsSupport$TripleEqualsInvocation<Lscala/runtime/Null$;>;
    MethodParameters:
      Name                           Flags
      right                          final

  public <T extends java.lang.Object> org.scalactic.TripleEqualsSupport$TripleEqualsInvocationOnSpread<T> $eq$eq$eq(org.scalactic.TripleEqualsSupport$Spread<T>);
    descriptor: (Lorg/scalactic/TripleEqualsSupport$Spread;)Lorg/scalactic/TripleEqualsSupport$TripleEqualsInvocationOnSpread;
    flags: (0x0001) ACC_PUBLIC
    Code:
      stack=2, locals=2, args_size=2
         0: aload_0
         1: aload_1
         2: invokestatic  #384                // InterfaceMethod org/scalactic/TripleEqualsSupport.$eq$eq$eq$:(Lorg/scalactic/TripleEqualsSupport;Lorg/scalactic/TripleEqualsSupport$Spread;)Lorg/scalactic/TripleEqualsSupport$TripleEqualsInvocationOnSpread;
         5: areturn
      LineNumberTable:
        line 30: 0
      LocalVariableTable:
        Start  Length  Slot  Name   Signature
            0       6     0  this   Lorg/scalatest/tools/DiscoverySuite;
            0       6     1 right   Lorg/scalactic/TripleEqualsSupport$Spread;
    Signature: #381                         // <T:Ljava/lang/Object;>(Lorg/scalactic/TripleEqualsSupport$Spread<TT;>;)Lorg/scalactic/TripleEqualsSupport$TripleEqualsInvocationOnSpread<TT;>;
    MethodParameters:
      Name                           Flags
      right                          final

  public <T extends java.lang.Object> org.scalactic.TripleEqualsSupport$TripleEqualsInvocationOnSpread<T> $bang$eq$eq(org.scalactic.TripleEqualsSupport$Spread<T>);
    descriptor: (Lorg/scalactic/TripleEqualsSupport$Spread;)Lorg/scalactic/TripleEqualsSupport$TripleEqualsInvocationOnSpread;
    flags: (0x0001) ACC_PUBLIC
    Code:
      stack=2, locals=2, args_size=2
         0: aload_0
         1: aload_1
         2: invokestatic  #387                // InterfaceMethod org/scalactic/TripleEqualsSupport.$bang$eq$eq$:(Lorg/scalactic/TripleEqualsSupport;Lorg/scalactic/TripleEqualsSupport$Spread;)Lorg/scalactic/TripleEqualsSupport$TripleEqualsInvocationOnSpread;
         5: areturn
      LineNumberTable:
        line 30: 0
      LocalVariableTable:
        Start  Length  Slot  Name   Signature
            0       6     0  this   Lorg/scalatest/tools/DiscoverySuite;
            0       6     1 right   Lorg/scalactic/TripleEqualsSupport$Spread;
    Signature: #381                         // <T:Ljava/lang/Object;>(Lorg/scalactic/TripleEqualsSupport$Spread<TT;>;)Lorg/scalactic/TripleEqualsSupport$TripleEqualsInvocationOnSpread<TT;>;
    MethodParameters:
      Name                           Flags
      right                          final

  public java.lang.String styleName();
    descriptor: ()Ljava/lang/String;
    flags: (0x0001) ACC_PUBLIC
    Code:
      stack=1, locals=1, args_size=1
         0: aload_0
         1: getfield      #389                // Field styleName:Ljava/lang/String;
         4: areturn
      LineNumberTable:
        line 30: 0
      LocalVariableTable:
        Start  Length  Slot  Name   Signature
            0       5     0  this   Lorg/scalatest/tools/DiscoverySuite;
    Deprecated: true

  public void org$scalatest$Suite$_setter_$styleName_$eq(java.lang.String);
    descriptor: (Ljava/lang/String;)V
    flags: (0x0001) ACC_PUBLIC
    Code:
      stack=2, locals=2, args_size=2
         0: aload_0
         1: aload_1
         2: putfield      #389                // Field styleName:Ljava/lang/String;
         5: return
      LineNumberTable:
        line 30: 0
      LocalVariableTable:
        Start  Length  Slot  Name   Signature
            0       6     0  this   Lorg/scalatest/tools/DiscoverySuite;
            0       6     1   x$1   Ljava/lang/String;
    MethodParameters:
      Name                           Flags
      x$1                            final

  public final org.scalatest.compatible.Assertion succeed();
    descriptor: ()Lorg/scalatest/compatible/Assertion;
    flags: (0x0011) ACC_PUBLIC, ACC_FINAL
    Code:
      stack=1, locals=1, args_size=1
         0: aload_0
         1: getfield      #394                // Field succeed:Lorg/scalatest/compatible/Assertion;
         4: areturn
      LineNumberTable:
        line 30: 0
      LocalVariableTable:
        Start  Length  Slot  Name   Signature
            0       5     0  this   Lorg/scalatest/tools/DiscoverySuite;

  public final void org$scalatest$Assertions$_setter_$succeed_$eq(org.scalatest.compatible.Assertion);
    descriptor: (Lorg/scalatest/compatible/Assertion;)V
    flags: (0x0011) ACC_PUBLIC, ACC_FINAL
    Code:
      stack=2, locals=2, args_size=2
         0: aload_0
         1: aload_1
         2: putfield      #394                // Field succeed:Lorg/scalatest/compatible/Assertion;
         5: return
      LineNumberTable:
        line 30: 0
      LocalVariableTable:
        Start  Length  Slot  Name   Signature
            0       6     0  this   Lorg/scalatest/tools/DiscoverySuite;
            0       6     1   x$1   Lorg/scalatest/compatible/Assertion;
    MethodParameters:
      Name                           Flags
      x$1                            final

  public java.lang.String suiteId();
    descriptor: ()Ljava/lang/String;
    flags: (0x0001) ACC_PUBLIC
    Code:
      stack=1, locals=1, args_size=1
         0: aload_0
         1: getfield      #398                // Field suiteId:Ljava/lang/String;
         4: areturn
      LineNumberTable:
        line 34: 0
      LocalVariableTable:
        Start  Length  Slot  Name   Signature
            0       5     0  this   Lorg/scalatest/tools/DiscoverySuite;

  public scala.collection.immutable.IndexedSeq<org.scalatest.Suite> nestedSuites();
    descriptor: ()Lscala/collection/immutable/IndexedSeq;
    flags: (0x0001) ACC_PUBLIC
    Code:
      stack=1, locals=1, args_size=1
         0: aload_0
         1: getfield      #402                // Field nestedSuites:Lscala/collection/immutable/IndexedSeq;
         4: areturn
      LineNumberTable:
        line 36: 0
      LocalVariableTable:
        Start  Length  Slot  Name   Signature
            0       5     0  this   Lorg/scalatest/tools/DiscoverySuite;
    Signature: #400                         // ()Lscala/collection/immutable/IndexedSeq<Lorg/scalatest/Suite;>;

  public org.scalatest.Status runTests(scala.Option<java.lang.String>, org.scalatest.Args);
    descriptor: (Lscala/Option;Lorg/scalatest/Args;)Lorg/scalatest/Status;
    flags: (0x0001) ACC_PUBLIC
    Code:
      stack=9, locals=3, args_size=3
         0: getstatic     #409                // Field org/scalactic/Requirements$.MODULE$:Lorg/scalactic/Requirements$;
         3: invokevirtual #413                // Method org/scalactic/Requirements$.requirementsHelper:()Lorg/scalactic/Requirements$RequirementsHelper;
         6: iconst_2
         7: anewarray     #415                // class java/lang/String
        10: dup
        11: iconst_0
        12: ldc_w         #416                // String testName
        15: aastore
        16: dup
        17: iconst_1
        18: ldc_w         #417                // String args
        21: aastore
        22: checkcast     #419                // class "[Ljava/lang/Object;"
        25: checkcast     #421                // class "[Ljava/lang/String;"
        28: iconst_2
        29: anewarray     #4                  // class java/lang/Object
        32: dup
        33: iconst_0
        34: aload_1
        35: aastore
        36: dup
        37: iconst_1
        38: aload_2
        39: aastore
        40: checkcast     #419                // class "[Ljava/lang/Object;"
        43: getstatic     #426                // Field org/scalactic/Prettifier$.MODULE$:Lorg/scalactic/Prettifier$;
        46: invokevirtual #430                // Method org/scalactic/Prettifier$.default:()Lorg/scalactic/Prettifier;
        49: new           #432                // class org/scalactic/source/Position
        52: dup
        53: ldc_w         #433                // String DiscoverySuite.scala
        56: ldc_w         #435                // String Please set the environment variable SCALACTIC_FILL_FILE_PATHNAMES to yes at compile time to enable this feature.
        59: bipush        41
        61: invokespecial #439                // Method org/scalactic/source/Position."<init>":(Ljava/lang/String;Ljava/lang/String;I)V
        64: invokevirtual #443                // Method org/scalactic/Requirements$RequirementsHelper.macroRequireNonNull:([Ljava/lang/String;[Ljava/lang/Object;Lorg/scalactic/Prettifier;Lorg/scalactic/source/Position;)V
        67: getstatic     #448                // Field org/scalatest/SucceededStatus$.MODULE$:Lorg/scalatest/SucceededStatus$;
        70: areturn
      LineNumberTable:
        line 41: 0
        line 42: 67
      LocalVariableTable:
        Start  Length  Slot  Name   Signature
            0      71     0  this   Lorg/scalatest/tools/DiscoverySuite;
            0      71     1 testName   Lscala/Option;
            0      71     2  args   Lorg/scalatest/Args;
    Signature: #123                         // (Lscala/Option<Ljava/lang/String;>;Lorg/scalatest/Args;)Lorg/scalatest/Status;
    MethodParameters:
      Name                           Flags
      testName                       final
      args                           final

  public static final org.scalatest.Suite $anonfun$nestedSuites$1(org.scalatest.tools.DiscoverySuite, java.lang.String);
    descriptor: (Lorg/scalatest/tools/DiscoverySuite;Ljava/lang/String;)Lorg/scalatest/Suite;
    flags: (0x1019) ACC_PUBLIC, ACC_STATIC, ACC_FINAL, ACC_SYNTHETIC
    Code:
      stack=3, locals=2, args_size=2
         0: getstatic     #457                // Field org/scalatest/tools/DiscoverySuite$.MODULE$:Lorg/scalatest/tools/DiscoverySuite$;
         3: aload_1
         4: aload_0
         5: getfield      #459                // Field runpathClassLoader:Ljava/lang/ClassLoader;
         8: invokevirtual #463                // Method org/scalatest/tools/DiscoverySuite$.getSuiteInstance:(Ljava/lang/String;Ljava/lang/ClassLoader;)Lorg/scalatest/Suite;
        11: areturn
      LineNumberTable:
        line 38: 0
      LocalVariableTable:
        Start  Length  Slot  Name   Signature
            0      12     0 $this   Lorg/scalatest/tools/DiscoverySuite;
            0      12     1 suiteClassName   Ljava/lang/String;
    MethodParameters:
      Name                           Flags
      $this                          final synthetic
      suiteClassName                 final

  public org.scalatest.tools.DiscoverySuite(java.lang.String, scala.collection.immutable.Set<java.lang.String>, boolean, java.lang.ClassLoader);
    descriptor: (Ljava/lang/String;Lscala/collection/immutable/Set;ZLjava/lang/ClassLoader;)V
    flags: (0x0001) ACC_PUBLIC
    Code:
      stack=9, locals=5, args_size=5
         0: aload_0
         1: aload         4
         3: putfield      #459                // Field runpathClassLoader:Ljava/lang/ClassLoader;
         6: aload_0
         7: invokespecial #471                // Method java/lang/Object."<init>":()V
        10: aload_0
        11: invokestatic  #475                // InterfaceMethod org/scalactic/TripleEqualsSupport.$init$:(Lorg/scalactic/TripleEqualsSupport;)V
        14: aload_0
        15: invokestatic  #478                // InterfaceMethod org/scalactic/TripleEquals.$init$:(Lorg/scalactic/TripleEquals;)V
        18: aload_0
        19: invokestatic  #481                // InterfaceMethod org/scalatest/Assertions.$init$:(Lorg/scalatest/Assertions;)V
        22: aload_0
        23: invokestatic  #484                // InterfaceMethod org/scalatest/Suite.$init$:(Lorg/scalatest/Suite;)V
        26: getstatic     #409                // Field org/scalactic/Requirements$.MODULE$:Lorg/scalactic/Requirements$;
        29: invokevirtual #413                // Method org/scalactic/Requirements$.requirementsHelper:()Lorg/scalactic/Requirements$RequirementsHelper;
        32: iconst_3
        33: anewarray     #415                // class java/lang/String
        36: dup
        37: iconst_0
        38: ldc_w         #486                // String DiscoverySuite.this.path
        41: aastore
        42: dup
        43: iconst_1
        44: ldc_w         #488                // String DiscoverySuite.this.accessibleSuites
        47: aastore
        48: dup
        49: iconst_2
        50: ldc_w         #490                // String DiscoverySuite.this.runpathClassLoader
        53: aastore
        54: checkcast     #419                // class "[Ljava/lang/Object;"
        57: checkcast     #421                // class "[Ljava/lang/String;"
        60: iconst_3
        61: anewarray     #4                  // class java/lang/Object
        64: dup
        65: iconst_0
        66: aload_1
        67: aastore
        68: dup
        69: iconst_1
        70: aload_2
        71: aastore
        72: dup
        73: iconst_2
        74: aload         4
        76: aastore
        77: checkcast     #419                // class "[Ljava/lang/Object;"
        80: getstatic     #426                // Field org/scalactic/Prettifier$.MODULE$:Lorg/scalactic/Prettifier$;
        83: invokevirtual #430                // Method org/scalactic/Prettifier$.default:()Lorg/scalactic/Prettifier;
        86: new           #432                // class org/scalactic/source/Position
        89: dup
        90: ldc_w         #433                // String DiscoverySuite.scala
        93: ldc_w         #435                // String Please set the environment variable SCALACTIC_FILL_FILE_PATHNAMES to yes at compile time to enable this feature.
        96: bipush        32
        98: invokespecial #439                // Method org/scalactic/source/Position."<init>":(Ljava/lang/String;Ljava/lang/String;I)V
       101: invokevirtual #443                // Method org/scalactic/Requirements$RequirementsHelper.macroRequireNonNull:([Ljava/lang/String;[Ljava/lang/Object;Lorg/scalactic/Prettifier;Lorg/scalactic/source/Position;)V
       104: aload_0
       105: new           #492                // class java/lang/StringBuilder
       108: dup
       109: ldc_w         #493                // int 1
       112: invokespecial #496                // Method java/lang/StringBuilder."<init>":(I)V
       115: aload_0
       116: invokevirtual #500                // Method getClass:()Ljava/lang/Class;
       119: invokevirtual #505                // Method java/lang/Class.getName:()Ljava/lang/String;
       122: invokevirtual #509                // Method java/lang/StringBuilder.append:(Ljava/lang/String;)Ljava/lang/StringBuilder;
       125: ldc_w         #511                // String -
       128: invokevirtual #509                // Method java/lang/StringBuilder.append:(Ljava/lang/String;)Ljava/lang/StringBuilder;
       131: invokestatic  #517                // Method java/util/UUID.randomUUID:()Ljava/util/UUID;
       134: invokevirtual #520                // Method java/util/UUID.toString:()Ljava/lang/String;
       137: invokevirtual #509                // Method java/lang/StringBuilder.append:(Ljava/lang/String;)Ljava/lang/StringBuilder;
       140: invokevirtual #521                // Method java/lang/StringBuilder.toString:()Ljava/lang/String;
       143: putfield      #398                // Field suiteId:Ljava/lang/String;
       146: aload_0
       147: getstatic     #457                // Field org/scalatest/tools/DiscoverySuite$.MODULE$:Lorg/scalatest/tools/DiscoverySuite$;
       150: aload_1
       151: aload_2
       152: iload_3
       153: invokevirtual #525                // Method org/scalatest/tools/DiscoverySuite$.nestedSuiteNames:(Ljava/lang/String;Lscala/collection/immutable/Set;Z)Lscala/collection/immutable/IndexedSeq;
       156: aload_0
       157: invokedynamic #544,  0            // InvokeDynamic #0:apply:(Lorg/scalatest/tools/DiscoverySuite;)Lscala/Function1;
       162: invokeinterface #550,  2          // InterfaceMethod scala/collection/immutable/IndexedSeq.map:(Lscala/Function1;)Ljava/lang/Object;
       167: checkcast     #546                // class scala/collection/immutable/IndexedSeq
       170: putfield      #402                // Field nestedSuites:Lscala/collection/immutable/IndexedSeq;
       173: invokestatic  #555                // Method scala/runtime/Statics.releaseFence:()V
       176: return
      LineNumberTable:
        line 30: 0
        line 32: 26
        line 34: 104
        line 36: 146
        line 37: 147
        line 36: 170
        line 30: 173
      LocalVariableTable:
        Start  Length  Slot  Name   Signature
            0     177     0  this   Lorg/scalatest/tools/DiscoverySuite;
            0     177     1  path   Ljava/lang/String;
            0     177     2 accessibleSuites   Lscala/collection/immutable/Set;
            0     177     3 wildcard   Z
            0     177     4 runpathClassLoader   Ljava/lang/ClassLoader;
    Signature: #465                         // (Ljava/lang/String;Lscala/collection/immutable/Set<Ljava/lang/String;>;ZLjava/lang/ClassLoader;)V
    MethodParameters:
      Name                           Flags
      path                           final
      accessibleSuites               final
      wildcard                       final
      runpathClassLoader             final

  private static java.lang.Object $deserializeLambda$(java.lang.invoke.SerializedLambda);
    descriptor: (Ljava/lang/invoke/SerializedLambda;)Ljava/lang/Object;
    flags: (0x100a) ACC_PRIVATE, ACC_STATIC, ACC_SYNTHETIC
    Code:
      stack=1, locals=1, args_size=1
         0: aload_0
         1: invokedynamic #568,  0            // InvokeDynamic #1:lambdaDeserialize:(Ljava/lang/invoke/SerializedLambda;)Ljava/lang/Object;
         6: areturn
}
InnerClasses:
  public static final #15= #12 of #14;    // Lookup=class java/lang/invoke/MethodHandles$Lookup of class java/lang/invoke/MethodHandles
  public static #20= #17 of #19;          // RequirementsHelper=class org/scalactic/Requirements$RequirementsHelper of class org/scalactic/Requirements
  public #25= #22 of #24;                 // CheckingEqualizer=class org/scalactic/TripleEqualsSupport$CheckingEqualizer of class org/scalactic/TripleEqualsSupport
  public #28= #27 of #24;                 // Equalizer=class org/scalactic/TripleEqualsSupport$Equalizer of class org/scalactic/TripleEqualsSupport
  public static final #31= #30 of #24;    // Spread=class org/scalactic/TripleEqualsSupport$Spread of class org/scalactic/TripleEqualsSupport
  public static final #34= #33 of #24;    // TripleEqualsInvocation=class org/scalactic/TripleEqualsSupport$TripleEqualsInvocation of class org/scalactic/TripleEqualsSupport
  public static final #37= #36 of #24;    // TripleEqualsInvocationOnSpread=class org/scalactic/TripleEqualsSupport$TripleEqualsInvocationOnSpread of class org/scalactic/TripleEqualsSupport
SourceFile: "DiscoverySuite.scala"
RuntimeVisibleAnnotations:
  0: #8(#9=s#10)
    scala.reflect.ScalaSignature(
      bytes="\u0006\u0005\u0005ma!B\n\u0015\u0001YQ\u0002\u0002C\u0013\u0001\u0005\u0003\u0005\u000b\u0011B\u0014\t\u0011I\u0002!\u0011!Q\u0001\nMB\u0001B\u000e\u0001\u0003\u0002\u0003\u0006Ia\u000e\u0005\tu\u0001\u0011\t\u0011)A\u0005w!)1\t\u0001C\u0001\t\"91\n\u0001b\u0001\n\u0003b\u0005BB(\u0001A\u0003%Q\nC\u0004Q\u0001\t\u0007I\u0011I)\t\ri\u0003\u0001\u0015!\u0003S\u0011\u0015Y\u0006\u0001\"\u0015]\u000f\u0019QG\u0003#\u0001\u0017W\u001a11\u0003\u0006E\u0001-1DQa\u0011\u0007\u0005\u0002MDQ\u0001\u001e\u0007\u0005\nUDQ\u0001\u001f\u0007\u0005\neDa\u0001 \u0007\u0005\u0002Yi\b\u0002CA\u0003\u0019\u0011\u0005a#a\u0002\t\u0013\u0005EA\"!A\u0005\n\u0005M!A\u0004#jg\u000e|g/\u001a:z\'VLG/\u001a\u0006\u0003+Y\tQ\u0001^8pYNT!a\u0006\r\u0002\u0013M\u001c\u0017\r\\1uKN$(\"A\r\u0002\u0007=\u0014xmE\u0002\u00017\u0005\u0002\"\u0001H\u0010\u000e\u0003uQ\u0011AH\u0001\u0006g\u000e\fG.Y\u0005\u0003Au\u0011a!\u00118z%\u00164\u0007C\u0001\u0012$\u001b\u00051\u0012B\u0001\u0013\u0017\u0005\u0015\u0019V/\u001b;f\u0003\u0011\u0001\u0018\r\u001e5\u0004\u0001A\u0011\u0001f\f\b\u0003S5\u0002\"AK\u000f\u000e\u0003-R!\u0001\f\u0014\u0002\rq\u0012xn\u001c;?\u0013\tqS$\u0001\u0004Qe\u0016$WMZ\u0005\u0003aE\u0012aa\u0015;sS:<\'B\u0001\u0018\u001e\u0003A\t7mY3tg&\u0014G.Z*vSR,7\u000fE\u0002)i\u001dJ!!N\u0019\u0003\u0007M+G/\u0001\u0005xS2$7-\u0019:e!\ta\u0002(\u0003\u0002:;\t9!i\\8mK\u0006t\u0017A\u0005:v]B\fG\u000f[\"mCN\u001cHj\\1eKJ\u0004\"\u0001P!\u000e\u0003uR!AP \u0002\t1\fgn\u001a\u0006\u0002\u0001\u0006!!.\u0019<b\u0013\t\u0011UHA\u0006DY\u0006\u001c8\u000fT8bI\u0016\u0014\u0018A\u0002\u001fj]&$h\bF\u0003F\u000f\"K%\n\u0005\u0002G\u00015\tA\u0003C\u0003&\u000b\u0001\u0007q\u0005C\u00033\u000b\u0001\u00071\u0007C\u00037\u000b\u0001\u0007q\u0007C\u0003;\u000b\u0001\u00071(A\u0004tk&$X-\u00133\u0016\u00035\u0003\"\u0001\u0010(\n\u0005Aj\u0014\u0001C:vSR,\u0017\n\u001a\u0011\u0002\u00199,7\u000f^3e\'VLG/Z:\u0016\u0003I\u00032a\u0015-\"\u001b\u0005!&BA+W\u0003%IW.\\;uC\ndWM\u0003\u0002X;\u0005Q1m\u001c7mK\u000e$\u0018n\u001c8\n\u0005e#&AC%oI\u0016DX\rZ*fc\u0006ia.Z:uK\u0012\u001cV/\u001b;fg\u0002\n\u0001B];o)\u0016\u001cHo\u001d\u000b\u0004;\u0002,\u0007C\u0001\u0012_\u0013\tyfC\u0001\u0004Ti\u0006$Xo\u001d\u0005\u0006C*\u0001\rAY\u0001\ti\u0016\u001cHOT1nKB\u0019AdY\u0014\n\u0005\u0011l\"AB(qi&|g\u000eC\u0003g\u0015\u0001\u0007q-\u0001\u0003be\u001e\u001c\bC\u0001\u0012i\u0013\tIgC\u0001\u0003Be\u001e\u001c\u0018A\u0004#jg\u000e|g/\u001a:z\'VLG/\u001a\t\u0003\r2\u00192\u0001D\u000en!\tq\u0017/D\u0001p\u0015\t\u0001x(\u0001\u0002j_&\u0011!o\u001c\u0002\r\'\u0016\u0014\u0018.\u00197ju\u0006\u0014G.\u001a\u000b\u0002W\u0006aq/\u001b7eG\u0006\u0014H\rT5tiR\u00191G^<\t\u000b\u0015r\u0001\u0019A\u0014\t\u000bIr\u0001\u0019A\u001a\u0002\u00159\f\'O]8x\u0019&\u001cH\u000fF\u00024unDQ!J\bA\u0002\u001dBQAM\bA\u0002M\n\u0001C\\3ti\u0016$7+^5uK:\u000bW.Z:\u0015\ry|\u0018\u0011AA\u0002!\r\u0019\u0006l\n\u0005\u0006KA\u0001\ra\n\u0005\u0006eA\u0001\ra\r\u0005\u0006mA\u0001\raN\u0001\u0011O\u0016$8+^5uK&s7\u000f^1oG\u0016$R!IA\u0005\u0003\u001bAa!a\u0003\u0012\u0001\u00049\u0013AD:vSR,7\t\\1tg:\u000bW.\u001a\u0005\u0007\u0003\u001f\t\u0002\u0019A\u001e\u0002\r1|\u0017\rZ3s\u000319(/\u001b;f%\u0016\u0004H.Y2f)\t\t)\u0002E\u0002=\u0003/I1!!\u0007>\u0005\u0019y%M[3di\u0002"
    )
BootstrapMethods:
  0: #540 REF_invokeStatic java/lang/invoke/LambdaMetafactory.altMetafactory:(Ljava/lang/invoke/MethodHandles$Lookup;Ljava/lang/String;Ljava/lang/invoke/MethodType;[Ljava/lang/Object;)Ljava/lang/invoke/CallSite;
    Method arguments:
      #527 (Ljava/lang/Object;)Ljava/lang/Object;
      #530 REF_invokeStatic org/scalatest/tools/DiscoverySuite.$anonfun$nestedSuites$1:(Lorg/scalatest/tools/DiscoverySuite;Ljava/lang/String;)Lorg/scalatest/Suite;
      #532 (Ljava/lang/String;)Lorg/scalatest/Suite;
      #533 5
      #493 1
      #532 (Ljava/lang/String;)Lorg/scalatest/Suite;
  1: #565 REF_invokeStatic scala/runtime/LambdaDeserialize.bootstrap:(Ljava/lang/invoke/MethodHandles$Lookup;Ljava/lang/String;Ljava/lang/invoke/MethodType;[Ljava/lang/invoke/MethodHandle;)Ljava/lang/invoke/CallSite;
    Method arguments:
      #530 REF_invokeStatic org/scalatest/tools/DiscoverySuite.$anonfun$nestedSuites$1:(Lorg/scalatest/tools/DiscoverySuite;Ljava/lang/String;)Lorg/scalatest/Suite;
  ScalaInlineInfo: length = 0x162 (unknown attribute)
   01 00 00 46 01 C1 01 C2 01 01 70 01 69 00 01 70
   01 7C 00 01 70 01 74 00 01 68 01 69 00 01 68 01
   7C 00 01 68 01 74 00 01 B4 01 D0 00 02 44 02 45
   00 02 44 02 46 00 02 47 02 48 00 02 49 02 48 00
   00 D4 00 D5 00 00 D4 00 E0 00 00 CD 00 CE 00 02
   4A 02 48 00 02 4B 02 45 00 02 4B 02 46 00 00 F9
   00 EF 00 00 F9 00 EA 00 00 F9 00 F5 00 00 F9 00
   E5 00 01 58 01 4C 00 01 3D 01 33 00 01 54 01 4C
   00 01 47 01 33 00 01 5D 01 4C 00 01 22 01 23 00
   01 18 01 19 00 00 93 00 94 00 01 61 01 62 00 00
   30 00 31 01 00 41 00 42 01 00 47 00 48 01 00 4D
   00 4E 01 00 53 00 4E 01 00 57 00 4E 01 00 5B 00
   4E 01 00 5F 00 4E 01 00 8B 00 8C 00 00 E4 00 EF
   00 00 E4 00 EA 00 00 E4 00 F5 00 00 E4 00 E5 00
   00 C2 00 C3 00 01 4B 01 4C 00 01 32 01 33 00 00
   2A 01 8F 00 00 AD 00 AE 00 00 BB 00 BC 00 01 8B
   01 8C 01 01 86 01 87 00 01 0B 01 0C 00 01 11 01
   12 00 00 9B 00 9C 00 00 79 00 7A 00 00 81 00 82
   00 00 71 00 72 00 01 93 00 7A 00 00 2D 00 42 00
   00 2E 01 0C 01 00 28 00 42 00 00 87 00 42 00 00
   63 00 64 00 00 A2 00 A3 00 00 A9 00 48 00 00 6A
   00 6B 00 01 41 01 33 00 01 29 01 2A 00 01 03 01
   04 00
  ScalaSig: length = 0x3 (unknown attribute)
   05 02 00
