Classfile /Users/mw/Projects/slang-braindump/.jar/jar11/assemble/slang-braindump/assemble/content/org/scalatest/tools/Durations$Suite.class
  Last modified May 29, 2022; size 6369 bytes
  SHA-256 checksum 215890655772d4b76c741e781d31b999261bc1644eb50d2d3144bac21fc2fe59
  Compiled from "Durations.scala"
public class org.scalatest.tools.Durations$Suite implements scala.Product,java.io.Serializable
  minor version: 0
  major version: 52
  flags: (0x0021) ACC_PUBLIC, ACC_SUPER
  this_class: #2                          // org/scalatest/tools/Durations$Suite
  super_class: #4                         // java/lang/Object
  interfaces: 2, fields: 4, methods: 21, attributes: 5
Constant pool:
    #1 = Utf8               org/scalatest/tools/Durations$Suite
    #2 = Class              #1            // org/scalatest/tools/Durations$Suite
    #3 = Utf8               java/lang/Object
    #4 = Class              #3            // java/lang/Object
    #5 = Utf8               scala/Product
    #6 = Class              #5            // scala/Product
    #7 = Utf8               java/io/Serializable
    #8 = Class              #7            // java/io/Serializable
    #9 = Utf8               Durations.scala
   #10 = Utf8               java/lang/invoke/MethodHandles$Lookup
   #11 = Class              #10           // java/lang/invoke/MethodHandles$Lookup
   #12 = Utf8               java/lang/invoke/MethodHandles
   #13 = Class              #12           // java/lang/invoke/MethodHandles
   #14 = Utf8               Lookup
   #15 = Utf8               org/scalatest/tools/Durations
   #16 = Class              #15           // org/scalatest/tools/Durations
   #17 = Utf8               Suite
   #18 = Utf8               org/scalatest/tools/Durations$Test
   #19 = Class              #18           // org/scalatest/tools/Durations$Test
   #20 = Utf8               Test
   #21 = Utf8               suiteId
   #22 = Utf8               Ljava/lang/String;
   #23 = Utf8               suiteName
   #24 = Utf8               tests
   #25 = Utf8               Lscala/collection/mutable/Set;
   #26 = Utf8               Lscala/collection/mutable/Set<Lorg/scalatest/tools/Durations$Test;>;
   #27 = Utf8               $outer
   #28 = Utf8               Lorg/scalatest/tools/Durations;
   #29 = Utf8               productElementNames
   #30 = Utf8               ()Lscala/collection/Iterator;
   #31 = Utf8               ()Lscala/collection/Iterator<Ljava/lang/String;>;
   #32 = Utf8               productElementNames$
   #33 = Utf8               (Lscala/Product;)Lscala/collection/Iterator;
   #34 = NameAndType        #32:#33       // productElementNames$:(Lscala/Product;)Lscala/collection/Iterator;
   #35 = InterfaceMethodref #6.#34        // scala/Product.productElementNames$:(Lscala/Product;)Lscala/collection/Iterator;
   #36 = Utf8               this
   #37 = Utf8               Lorg/scalatest/tools/Durations$Suite;
   #38 = Utf8               ()Ljava/lang/String;
   #39 = NameAndType        #21:#22       // suiteId:Ljava/lang/String;
   #40 = Fieldref           #2.#39        // org/scalatest/tools/Durations$Suite.suiteId:Ljava/lang/String;
   #41 = NameAndType        #23:#22       // suiteName:Ljava/lang/String;
   #42 = Fieldref           #2.#41        // org/scalatest/tools/Durations$Suite.suiteName:Ljava/lang/String;
   #43 = Utf8               ()Lscala/collection/mutable/Set;
   #44 = Utf8               ()Lscala/collection/mutable/Set<Lorg/scalatest/tools/Durations$Test;>;
   #45 = NameAndType        #24:#25       // tests:Lscala/collection/mutable/Set;
   #46 = Fieldref           #2.#45        // org/scalatest/tools/Durations$Suite.tests:Lscala/collection/mutable/Set;
   #47 = Utf8               toXml
   #48 = Utf8               scala/collection/StringOps$
   #49 = Class              #48           // scala/collection/StringOps$
   #50 = Utf8               MODULE$
   #51 = Utf8               Lscala/collection/StringOps$;
   #52 = NameAndType        #50:#51       // MODULE$:Lscala/collection/StringOps$;
   #53 = Fieldref           #49.#52       // scala/collection/StringOps$.MODULE$:Lscala/collection/StringOps$;
   #54 = Utf8               scala/Predef$
   #55 = Class              #54           // scala/Predef$
   #56 = Utf8               Lscala/Predef$;
   #57 = NameAndType        #50:#56       // MODULE$:Lscala/Predef$;
   #58 = Fieldref           #55.#57       // scala/Predef$.MODULE$:Lscala/Predef$;
   #59 = Utf8               |  <suite suiteId=\"$suiteId$\" suiteName=\"$suiteName$\">\n           |$tests$  </suite>\n           |
   #60 = String             #59           // |  <suite suiteId=\"$suiteId$\" suiteName=\"$suiteName$\">\n           |$tests$  </suite>\n           |
   #61 = Utf8               augmentString
   #62 = Utf8               (Ljava/lang/String;)Ljava/lang/String;
   #63 = NameAndType        #61:#62       // augmentString:(Ljava/lang/String;)Ljava/lang/String;
   #64 = Methodref          #55.#63       // scala/Predef$.augmentString:(Ljava/lang/String;)Ljava/lang/String;
   #65 = Utf8               stripMargin$extension
   #66 = NameAndType        #65:#62       // stripMargin$extension:(Ljava/lang/String;)Ljava/lang/String;
   #67 = Methodref          #49.#66       // scala/collection/StringOps$.stripMargin$extension:(Ljava/lang/String;)Ljava/lang/String;
   #68 = Utf8               scala/collection/mutable/StringBuilder
   #69 = Class              #68           // scala/collection/mutable/StringBuilder
   #70 = Utf8               <init>
   #71 = Utf8               ()V
   #72 = NameAndType        #70:#71       // "<init>":()V
   #73 = Methodref          #69.#72       // scala/collection/mutable/StringBuilder."<init>":()V
   #74 = NameAndType        #24:#43       // tests:()Lscala/collection/mutable/Set;
   #75 = Methodref          #2.#74        // org/scalatest/tools/Durations$Suite.tests:()Lscala/collection/mutable/Set;
   #76 = Utf8               (Ljava/lang/Object;)Ljava/lang/Object;
   #77 = MethodType         #76           //  (Ljava/lang/Object;)Ljava/lang/Object;
   #78 = Utf8               $anonfun$toXml$2
   #79 = Utf8               (Lscala/collection/mutable/StringBuilder;Lorg/scalatest/tools/Durations$Test;)Lscala/collection/mutable/StringBuilder;
   #80 = NameAndType        #78:#79       // $anonfun$toXml$2:(Lscala/collection/mutable/StringBuilder;Lorg/scalatest/tools/Durations$Test;)Lscala/collection/mutable/StringBuilder;
   #81 = Methodref          #2.#80        // org/scalatest/tools/Durations$Suite.$anonfun$toXml$2:(Lscala/collection/mutable/StringBuilder;Lorg/scalatest/tools/Durations$Test;)Lscala/collection/mutable/StringBuilder;
   #82 = MethodHandle       6:#81         // REF_invokeStatic org/scalatest/tools/Durations$Suite.$anonfun$toXml$2:(Lscala/collection/mutable/StringBuilder;Lorg/scalatest/tools/Durations$Test;)Lscala/collection/mutable/StringBuilder;
   #83 = Utf8               (Lorg/scalatest/tools/Durations$Test;)Lscala/collection/mutable/StringBuilder;
   #84 = MethodType         #83           //  (Lorg/scalatest/tools/Durations$Test;)Lscala/collection/mutable/StringBuilder;
   #85 = Integer            5
   #86 = Integer            1
   #87 = Utf8               java/lang/invoke/LambdaMetafactory
   #88 = Class              #87           // java/lang/invoke/LambdaMetafactory
   #89 = Utf8               altMetafactory
   #90 = Utf8               (Ljava/lang/invoke/MethodHandles$Lookup;Ljava/lang/String;Ljava/lang/invoke/MethodType;[Ljava/lang/Object;)Ljava/lang/invoke/CallSite;
   #91 = NameAndType        #89:#90       // altMetafactory:(Ljava/lang/invoke/MethodHandles$Lookup;Ljava/lang/String;Ljava/lang/invoke/MethodType;[Ljava/lang/Object;)Ljava/lang/invoke/CallSite;
   #92 = Methodref          #88.#91       // java/lang/invoke/LambdaMetafactory.altMetafactory:(Ljava/lang/invoke/MethodHandles$Lookup;Ljava/lang/String;Ljava/lang/invoke/MethodType;[Ljava/lang/Object;)Ljava/lang/invoke/CallSite;
   #93 = MethodHandle       6:#92         // REF_invokeStatic java/lang/invoke/LambdaMetafactory.altMetafactory:(Ljava/lang/invoke/MethodHandles$Lookup;Ljava/lang/String;Ljava/lang/invoke/MethodType;[Ljava/lang/Object;)Ljava/lang/invoke/CallSite;
   #94 = Utf8               apply
   #95 = Utf8               (Lscala/collection/mutable/StringBuilder;)Lscala/Function1;
   #96 = NameAndType        #94:#95       // apply:(Lscala/collection/mutable/StringBuilder;)Lscala/Function1;
   #97 = InvokeDynamic      #0:#96        // #0:apply:(Lscala/collection/mutable/StringBuilder;)Lscala/Function1;
   #98 = Utf8               scala/collection/mutable/Set
   #99 = Class              #98           // scala/collection/mutable/Set
  #100 = Utf8               foreach
  #101 = Utf8               (Lscala/Function1;)V
  #102 = NameAndType        #100:#101     // foreach:(Lscala/Function1;)V
  #103 = InterfaceMethodref #99.#102      // scala/collection/mutable/Set.foreach:(Lscala/Function1;)V
  #104 = Utf8               \\$suiteId\\$
  #105 = String             #104          // \\$suiteId\\$
  #106 = NameAndType        #21:#38       // suiteId:()Ljava/lang/String;
  #107 = Methodref          #2.#106       // org/scalatest/tools/Durations$Suite.suiteId:()Ljava/lang/String;
  #108 = Utf8               java/util/regex/Matcher
  #109 = Class              #108          // java/util/regex/Matcher
  #110 = Utf8               quoteReplacement
  #111 = NameAndType        #110:#62      // quoteReplacement:(Ljava/lang/String;)Ljava/lang/String;
  #112 = Methodref          #109.#111     // java/util/regex/Matcher.quoteReplacement:(Ljava/lang/String;)Ljava/lang/String;
  #113 = Utf8               java/lang/String
  #114 = Class              #113          // java/lang/String
  #115 = Utf8               replaceFirst
  #116 = Utf8               (Ljava/lang/String;Ljava/lang/String;)Ljava/lang/String;
  #117 = NameAndType        #115:#116     // replaceFirst:(Ljava/lang/String;Ljava/lang/String;)Ljava/lang/String;
  #118 = Methodref          #114.#117     // java/lang/String.replaceFirst:(Ljava/lang/String;Ljava/lang/String;)Ljava/lang/String;
  #119 = Utf8               \\$suiteName\\$
  #120 = String             #119          // \\$suiteName\\$
  #121 = NameAndType        #23:#38       // suiteName:()Ljava/lang/String;
  #122 = Methodref          #2.#121       // org/scalatest/tools/Durations$Suite.suiteName:()Ljava/lang/String;
  #123 = Utf8               \\$tests\\$
  #124 = String             #123          // \\$tests\\$
  #125 = Utf8               toString
  #126 = NameAndType        #125:#38      // toString:()Ljava/lang/String;
  #127 = Methodref          #69.#126      // scala/collection/mutable/StringBuilder.toString:()Ljava/lang/String;
  #128 = Utf8               SuiteTemplate
  #129 = Utf8               buf
  #130 = Utf8               Lscala/collection/mutable/StringBuilder;
  #131 = Utf8               copy
  #132 = Utf8               (Ljava/lang/String;Ljava/lang/String;)Lorg/scalatest/tools/Durations$Suite;
  #133 = Utf8               org$scalatest$tools$Durations$Suite$$$outer
  #134 = Utf8               ()Lorg/scalatest/tools/Durations;
  #135 = NameAndType        #133:#134     // org$scalatest$tools$Durations$Suite$$$outer:()Lorg/scalatest/tools/Durations;
  #136 = Methodref          #2.#135       // org/scalatest/tools/Durations$Suite.org$scalatest$tools$Durations$Suite$$$outer:()Lorg/scalatest/tools/Durations;
  #137 = Utf8               (Lorg/scalatest/tools/Durations;Ljava/lang/String;Ljava/lang/String;)V
  #138 = NameAndType        #70:#137      // "<init>":(Lorg/scalatest/tools/Durations;Ljava/lang/String;Ljava/lang/String;)V
  #139 = Methodref          #2.#138       // org/scalatest/tools/Durations$Suite."<init>":(Lorg/scalatest/tools/Durations;Ljava/lang/String;Ljava/lang/String;)V
  #140 = Utf8               copy$default$1
  #141 = Utf8               copy$default$2
  #142 = Utf8               productPrefix
  #143 = String             #17           // Suite
  #144 = Utf8               productArity
  #145 = Utf8               ()I
  #146 = Utf8               productElement
  #147 = Utf8               (I)Ljava/lang/Object;
  #148 = Utf8               x$1
  #149 = Utf8               scala/runtime/Statics
  #150 = Class              #149          // scala/runtime/Statics
  #151 = Utf8               ioobe
  #152 = NameAndType        #151:#147     // ioobe:(I)Ljava/lang/Object;
  #153 = Methodref          #150.#152     // scala/runtime/Statics.ioobe:(I)Ljava/lang/Object;
  #154 = Utf8               I
  #155 = Utf8               productIterator
  #156 = Utf8               ()Lscala/collection/Iterator<Ljava/lang/Object;>;
  #157 = Utf8               scala/runtime/ScalaRunTime$
  #158 = Class              #157          // scala/runtime/ScalaRunTime$
  #159 = Utf8               Lscala/runtime/ScalaRunTime$;
  #160 = NameAndType        #50:#159      // MODULE$:Lscala/runtime/ScalaRunTime$;
  #161 = Fieldref           #158.#160     // scala/runtime/ScalaRunTime$.MODULE$:Lscala/runtime/ScalaRunTime$;
  #162 = Utf8               typedProductIterator
  #163 = NameAndType        #162:#33      // typedProductIterator:(Lscala/Product;)Lscala/collection/Iterator;
  #164 = Methodref          #158.#163     // scala/runtime/ScalaRunTime$.typedProductIterator:(Lscala/Product;)Lscala/collection/Iterator;
  #165 = Utf8               canEqual
  #166 = Utf8               (Ljava/lang/Object;)Z
  #167 = Utf8               Ljava/lang/Object;
  #168 = Utf8               productElementName
  #169 = Utf8               (I)Ljava/lang/String;
  #170 = String             #21           // suiteId
  #171 = String             #23           // suiteName
  #172 = Utf8               hashCode
  #173 = Utf8               _hashCode
  #174 = Utf8               (Lscala/Product;)I
  #175 = NameAndType        #173:#174     // _hashCode:(Lscala/Product;)I
  #176 = Methodref          #158.#175     // scala/runtime/ScalaRunTime$._hashCode:(Lscala/Product;)I
  #177 = Utf8               _toString
  #178 = Utf8               (Lscala/Product;)Ljava/lang/String;
  #179 = NameAndType        #177:#178     // _toString:(Lscala/Product;)Ljava/lang/String;
  #180 = Methodref          #158.#179     // scala/runtime/ScalaRunTime$._toString:(Lscala/Product;)Ljava/lang/String;
  #181 = Utf8               equals
  #182 = NameAndType        #181:#166     // equals:(Ljava/lang/Object;)Z
  #183 = Methodref          #4.#182       // java/lang/Object.equals:(Ljava/lang/Object;)Z
  #184 = NameAndType        #165:#166     // canEqual:(Ljava/lang/Object;)Z
  #185 = Methodref          #2.#184       // org/scalatest/tools/Durations$Suite.canEqual:(Ljava/lang/Object;)Z
  #186 = NameAndType        #27:#28       // $outer:Lorg/scalatest/tools/Durations;
  #187 = Fieldref           #2.#186       // org/scalatest/tools/Durations$Suite.$outer:Lorg/scalatest/tools/Durations;
  #188 = Utf8               buf$2
  #189 = Utf8               test
  #190 = NameAndType        #47:#38       // toXml:()Ljava/lang/String;
  #191 = Methodref          #19.#190      // org/scalatest/tools/Durations$Test.toXml:()Ljava/lang/String;
  #192 = Utf8               append
  #193 = Utf8               (Ljava/lang/String;)Lscala/collection/mutable/StringBuilder;
  #194 = NameAndType        #192:#193     // append:(Ljava/lang/String;)Lscala/collection/mutable/StringBuilder;
  #195 = Methodref          #69.#194      // scala/collection/mutable/StringBuilder.append:(Ljava/lang/String;)Lscala/collection/mutable/StringBuilder;
  #196 = Utf8               Lorg/scalatest/tools/Durations$Test;
  #197 = Methodref          #4.#72        // java/lang/Object."<init>":()V
  #198 = Utf8               $init$
  #199 = Utf8               (Lscala/Product;)V
  #200 = NameAndType        #198:#199     // $init$:(Lscala/Product;)V
  #201 = InterfaceMethodref #6.#200       // scala/Product.$init$:(Lscala/Product;)V
  #202 = Utf8               scala/collection/mutable/Set$
  #203 = Class              #202          // scala/collection/mutable/Set$
  #204 = Utf8               Lscala/collection/mutable/Set$;
  #205 = NameAndType        #50:#204      // MODULE$:Lscala/collection/mutable/Set$;
  #206 = Fieldref           #203.#205     // scala/collection/mutable/Set$.MODULE$:Lscala/collection/mutable/Set$;
  #207 = Utf8               scala/collection/immutable/Nil$
  #208 = Class              #207          // scala/collection/immutable/Nil$
  #209 = Utf8               Lscala/collection/immutable/Nil$;
  #210 = NameAndType        #50:#209      // MODULE$:Lscala/collection/immutable/Nil$;
  #211 = Fieldref           #208.#210     // scala/collection/immutable/Nil$.MODULE$:Lscala/collection/immutable/Nil$;
  #212 = Utf8               (Lscala/collection/immutable/Seq;)Ljava/lang/Object;
  #213 = NameAndType        #94:#212      // apply:(Lscala/collection/immutable/Seq;)Ljava/lang/Object;
  #214 = Methodref          #203.#213     // scala/collection/mutable/Set$.apply:(Lscala/collection/immutable/Seq;)Ljava/lang/Object;
  #215 = Utf8               $deserializeLambda$
  #216 = Utf8               (Ljava/lang/invoke/SerializedLambda;)Ljava/lang/Object;
  #217 = Utf8               scala/runtime/LambdaDeserialize
  #218 = Class              #217          // scala/runtime/LambdaDeserialize
  #219 = Utf8               bootstrap
  #220 = Utf8               (Ljava/lang/invoke/MethodHandles$Lookup;Ljava/lang/String;Ljava/lang/invoke/MethodType;[Ljava/lang/invoke/MethodHandle;)Ljava/lang/invoke/CallSite;
  #221 = NameAndType        #219:#220     // bootstrap:(Ljava/lang/invoke/MethodHandles$Lookup;Ljava/lang/String;Ljava/lang/invoke/MethodType;[Ljava/lang/invoke/MethodHandle;)Ljava/lang/invoke/CallSite;
  #222 = Methodref          #218.#221     // scala/runtime/LambdaDeserialize.bootstrap:(Ljava/lang/invoke/MethodHandles$Lookup;Ljava/lang/String;Ljava/lang/invoke/MethodType;[Ljava/lang/invoke/MethodHandle;)Ljava/lang/invoke/CallSite;
  #223 = MethodHandle       6:#222        // REF_invokeStatic scala/runtime/LambdaDeserialize.bootstrap:(Ljava/lang/invoke/MethodHandles$Lookup;Ljava/lang/String;Ljava/lang/invoke/MethodType;[Ljava/lang/invoke/MethodHandle;)Ljava/lang/invoke/CallSite;
  #224 = Utf8               lambdaDeserialize
  #225 = NameAndType        #224:#216     // lambdaDeserialize:(Ljava/lang/invoke/SerializedLambda;)Ljava/lang/Object;
  #226 = InvokeDynamic      #1:#225       // #1:lambdaDeserialize:(Ljava/lang/invoke/SerializedLambda;)Ljava/lang/Object;
  #227 = Utf8               Signature
  #228 = Utf8               Code
  #229 = Utf8               LineNumberTable
  #230 = Utf8               LocalVariableTable
  #231 = Utf8               MethodParameters
  #232 = Utf8               StackMapTable
  #233 = Utf8               InnerClasses
  #234 = Utf8               SourceFile
  #235 = Utf8               BootstrapMethods
  #236 = Utf8               ScalaInlineInfo
  #237 = Utf8               Scala
{
  private final java.lang.String suiteId;
    descriptor: Ljava/lang/String;
    flags: (0x0012) ACC_PRIVATE, ACC_FINAL

  private final java.lang.String suiteName;
    descriptor: Ljava/lang/String;
    flags: (0x0012) ACC_PRIVATE, ACC_FINAL

  private final scala.collection.mutable.Set<org.scalatest.tools.Durations$Test> tests;
    descriptor: Lscala/collection/mutable/Set;
    flags: (0x0012) ACC_PRIVATE, ACC_FINAL
    Signature: #26                          // Lscala/collection/mutable/Set<Lorg/scalatest/tools/Durations$Test;>;

  public final org.scalatest.tools.Durations $outer;
    descriptor: Lorg/scalatest/tools/Durations;
    flags: (0x1011) ACC_PUBLIC, ACC_FINAL, ACC_SYNTHETIC

  public scala.collection.Iterator<java.lang.String> productElementNames();
    descriptor: ()Lscala/collection/Iterator;
    flags: (0x0001) ACC_PUBLIC
    Code:
      stack=1, locals=1, args_size=1
         0: aload_0
         1: invokestatic  #35                 // InterfaceMethod scala/Product.productElementNames$:(Lscala/Product;)Lscala/collection/Iterator;
         4: areturn
      LineNumberTable:
        line 141: 0
      LocalVariableTable:
        Start  Length  Slot  Name   Signature
            0       5     0  this   Lorg/scalatest/tools/Durations$Suite;
    Signature: #31                          // ()Lscala/collection/Iterator<Ljava/lang/String;>;

  public java.lang.String suiteId();
    descriptor: ()Ljava/lang/String;
    flags: (0x0001) ACC_PUBLIC
    Code:
      stack=1, locals=1, args_size=1
         0: aload_0
         1: getfield      #40                 // Field suiteId:Ljava/lang/String;
         4: areturn
      LineNumberTable:
        line 141: 0
      LocalVariableTable:
        Start  Length  Slot  Name   Signature
            0       5     0  this   Lorg/scalatest/tools/Durations$Suite;

  public java.lang.String suiteName();
    descriptor: ()Ljava/lang/String;
    flags: (0x0001) ACC_PUBLIC
    Code:
      stack=1, locals=1, args_size=1
         0: aload_0
         1: getfield      #42                 // Field suiteName:Ljava/lang/String;
         4: areturn
      LineNumberTable:
        line 141: 0
      LocalVariableTable:
        Start  Length  Slot  Name   Signature
            0       5     0  this   Lorg/scalatest/tools/Durations$Suite;

  public scala.collection.mutable.Set<org.scalatest.tools.Durations$Test> tests();
    descriptor: ()Lscala/collection/mutable/Set;
    flags: (0x0001) ACC_PUBLIC
    Code:
      stack=1, locals=1, args_size=1
         0: aload_0
         1: getfield      #46                 // Field tests:Lscala/collection/mutable/Set;
         4: areturn
      LineNumberTable:
        line 142: 0
      LocalVariableTable:
        Start  Length  Slot  Name   Signature
            0       5     0  this   Lorg/scalatest/tools/Durations$Suite;
    Signature: #44                          // ()Lscala/collection/mutable/Set<Lorg/scalatest/tools/Durations$Test;>;

  public java.lang.String toXml();
    descriptor: ()Ljava/lang/String;
    flags: (0x0001) ACC_PUBLIC
    Code:
      stack=3, locals=3, args_size=1
         0: getstatic     #53                 // Field scala/collection/StringOps$.MODULE$:Lscala/collection/StringOps$;
         3: getstatic     #58                 // Field scala/Predef$.MODULE$:Lscala/Predef$;
         6: ldc           #60                 // String |  <suite suiteId=\"$suiteId$\" suiteName=\"$suiteName$\">\n           |$tests$  </suite>\n           |
         8: invokevirtual #64                 // Method scala/Predef$.augmentString:(Ljava/lang/String;)Ljava/lang/String;
        11: invokevirtual #67                 // Method scala/collection/StringOps$.stripMargin$extension:(Ljava/lang/String;)Ljava/lang/String;
        14: astore_1
        15: new           #69                 // class scala/collection/mutable/StringBuilder
        18: dup
        19: invokespecial #73                 // Method scala/collection/mutable/StringBuilder."<init>":()V
        22: astore_2
        23: aload_0
        24: invokevirtual #75                 // Method tests:()Lscala/collection/mutable/Set;
        27: aload_2
        28: invokedynamic #97,  0             // InvokeDynamic #0:apply:(Lscala/collection/mutable/StringBuilder;)Lscala/Function1;
        33: invokeinterface #103,  2          // InterfaceMethod scala/collection/mutable/Set.foreach:(Lscala/Function1;)V
        38: aload_1
        39: ldc           #105                // String \\$suiteId\\$
        41: aload_0
        42: invokevirtual #107                // Method suiteId:()Ljava/lang/String;
        45: invokestatic  #112                // Method java/util/regex/Matcher.quoteReplacement:(Ljava/lang/String;)Ljava/lang/String;
        48: invokevirtual #118                // Method java/lang/String.replaceFirst:(Ljava/lang/String;Ljava/lang/String;)Ljava/lang/String;
        51: ldc           #120                // String \\$suiteName\\$
        53: aload_0
        54: invokevirtual #122                // Method suiteName:()Ljava/lang/String;
        57: invokestatic  #112                // Method java/util/regex/Matcher.quoteReplacement:(Ljava/lang/String;)Ljava/lang/String;
        60: invokevirtual #118                // Method java/lang/String.replaceFirst:(Ljava/lang/String;Ljava/lang/String;)Ljava/lang/String;
        63: ldc           #124                // String \\$tests\\$
        65: aload_2
        66: invokevirtual #127                // Method scala/collection/mutable/StringBuilder.toString:()Ljava/lang/String;
        69: invokestatic  #112                // Method java/util/regex/Matcher.quoteReplacement:(Ljava/lang/String;)Ljava/lang/String;
        72: invokevirtual #118                // Method java/lang/String.replaceFirst:(Ljava/lang/String;Ljava/lang/String;)Ljava/lang/String;
        75: areturn
      LineNumberTable:
        line 145: 0
        line 146: 3
        line 150: 15
        line 152: 23
        line 154: 38
        line 155: 39
        line 156: 51
        line 157: 63
      LocalVariableTable:
        Start  Length  Slot  Name   Signature
           15      60     1 SuiteTemplate   Ljava/lang/String;
           23      52     2   buf   Lscala/collection/mutable/StringBuilder;
            0      76     0  this   Lorg/scalatest/tools/Durations$Suite;

  public org.scalatest.tools.Durations$Suite copy(java.lang.String, java.lang.String);
    descriptor: (Ljava/lang/String;Ljava/lang/String;)Lorg/scalatest/tools/Durations$Suite;
    flags: (0x0001) ACC_PUBLIC
    Code:
      stack=5, locals=3, args_size=3
         0: new           #2                  // class org/scalatest/tools/Durations$Suite
         3: dup
         4: aload_0
         5: invokevirtual #136                // Method org$scalatest$tools$Durations$Suite$$$outer:()Lorg/scalatest/tools/Durations;
         8: aload_1
         9: aload_2
        10: invokespecial #139                // Method "<init>":(Lorg/scalatest/tools/Durations;Ljava/lang/String;Ljava/lang/String;)V
        13: areturn
      LineNumberTable:
        line 141: 0
      LocalVariableTable:
        Start  Length  Slot  Name   Signature
            0      14     0  this   Lorg/scalatest/tools/Durations$Suite;
            0      14     1 suiteId   Ljava/lang/String;
            0      14     2 suiteName   Ljava/lang/String;
    MethodParameters:
      Name                           Flags
      suiteId                        final
      suiteName                      final

  public java.lang.String copy$default$1();
    descriptor: ()Ljava/lang/String;
    flags: (0x0001) ACC_PUBLIC
    Code:
      stack=1, locals=1, args_size=1
         0: aload_0
         1: invokevirtual #107                // Method suiteId:()Ljava/lang/String;
         4: areturn
      LineNumberTable:
        line 141: 0
      LocalVariableTable:
        Start  Length  Slot  Name   Signature
            0       5     0  this   Lorg/scalatest/tools/Durations$Suite;

  public java.lang.String copy$default$2();
    descriptor: ()Ljava/lang/String;
    flags: (0x0001) ACC_PUBLIC
    Code:
      stack=1, locals=1, args_size=1
         0: aload_0
         1: invokevirtual #122                // Method suiteName:()Ljava/lang/String;
         4: areturn
      LineNumberTable:
        line 141: 0
      LocalVariableTable:
        Start  Length  Slot  Name   Signature
            0       5     0  this   Lorg/scalatest/tools/Durations$Suite;

  public java.lang.String productPrefix();
    descriptor: ()Ljava/lang/String;
    flags: (0x0001) ACC_PUBLIC
    Code:
      stack=1, locals=1, args_size=1
         0: ldc           #143                // String Suite
         2: areturn
      LineNumberTable:
        line 141: 0
      LocalVariableTable:
        Start  Length  Slot  Name   Signature
            0       3     0  this   Lorg/scalatest/tools/Durations$Suite;

  public int productArity();
    descriptor: ()I
    flags: (0x0001) ACC_PUBLIC
    Code:
      stack=1, locals=1, args_size=1
         0: iconst_2
         1: ireturn
      LineNumberTable:
        line 141: 0
      LocalVariableTable:
        Start  Length  Slot  Name   Signature
            0       2     0  this   Lorg/scalatest/tools/Durations$Suite;

  public java.lang.Object productElement(int);
    descriptor: (I)Ljava/lang/Object;
    flags: (0x0001) ACC_PUBLIC
    Code:
      stack=1, locals=3, args_size=2
         0: iload_1
         1: istore_2
         2: iload_2
         3: tableswitch   { // 0 to 1
                       0: 24
                       1: 31
                 default: 38
            }
        24: aload_0
        25: invokevirtual #107                // Method suiteId:()Ljava/lang/String;
        28: goto          45
        31: aload_0
        32: invokevirtual #122                // Method suiteName:()Ljava/lang/String;
        35: goto          45
        38: iload_1
        39: invokestatic  #153                // Method scala/runtime/Statics.ioobe:(I)Ljava/lang/Object;
        42: goto          45
        45: areturn
      StackMapTable: number_of_entries = 4
        frame_type = 252 /* append */
          offset_delta = 24
          locals = [ int ]
        frame_type = 6 /* same */
        frame_type = 6 /* same */
        frame_type = 70 /* same_locals_1_stack_item */
          stack = [ class java/lang/Object ]
      LineNumberTable:
        line 141: 0
      LocalVariableTable:
        Start  Length  Slot  Name   Signature
            0      46     0  this   Lorg/scalatest/tools/Durations$Suite;
            0      46     1   x$1   I
    MethodParameters:
      Name                           Flags
      x$1                            final

  public scala.collection.Iterator<java.lang.Object> productIterator();
    descriptor: ()Lscala/collection/Iterator;
    flags: (0x0001) ACC_PUBLIC
    Code:
      stack=2, locals=1, args_size=1
         0: getstatic     #161                // Field scala/runtime/ScalaRunTime$.MODULE$:Lscala/runtime/ScalaRunTime$;
         3: aload_0
         4: invokevirtual #164                // Method scala/runtime/ScalaRunTime$.typedProductIterator:(Lscala/Product;)Lscala/collection/Iterator;
         7: areturn
      LineNumberTable:
        line 141: 0
      LocalVariableTable:
        Start  Length  Slot  Name   Signature
            0       8     0  this   Lorg/scalatest/tools/Durations$Suite;
    Signature: #156                         // ()Lscala/collection/Iterator<Ljava/lang/Object;>;

  public boolean canEqual(java.lang.Object);
    descriptor: (Ljava/lang/Object;)Z
    flags: (0x0001) ACC_PUBLIC
    Code:
      stack=1, locals=2, args_size=2
         0: aload_1
         1: instanceof    #2                  // class org/scalatest/tools/Durations$Suite
         4: ireturn
      LineNumberTable:
        line 141: 0
      LocalVariableTable:
        Start  Length  Slot  Name   Signature
            0       5     0  this   Lorg/scalatest/tools/Durations$Suite;
            0       5     1   x$1   Ljava/lang/Object;
    MethodParameters:
      Name                           Flags
      x$1                            final

  public java.lang.String productElementName(int);
    descriptor: (I)Ljava/lang/String;
    flags: (0x0001) ACC_PUBLIC
    Code:
      stack=1, locals=3, args_size=2
         0: iload_1
         1: istore_2
         2: iload_2
         3: tableswitch   { // 0 to 1
                       0: 24
                       1: 29
                 default: 34
            }
        24: ldc           #170                // String suiteId
        26: goto          44
        29: ldc           #171                // String suiteName
        31: goto          44
        34: iload_1
        35: invokestatic  #153                // Method scala/runtime/Statics.ioobe:(I)Ljava/lang/Object;
        38: checkcast     #114                // class java/lang/String
        41: goto          44
        44: areturn
      StackMapTable: number_of_entries = 4
        frame_type = 252 /* append */
          offset_delta = 24
          locals = [ int ]
        frame_type = 4 /* same */
        frame_type = 4 /* same */
        frame_type = 73 /* same_locals_1_stack_item */
          stack = [ class java/lang/String ]
      LineNumberTable:
        line 141: 0
      LocalVariableTable:
        Start  Length  Slot  Name   Signature
            0      45     0  this   Lorg/scalatest/tools/Durations$Suite;
            0      45     1   x$1   I
    MethodParameters:
      Name                           Flags
      x$1                            final

  public int hashCode();
    descriptor: ()I
    flags: (0x0001) ACC_PUBLIC
    Code:
      stack=2, locals=1, args_size=1
         0: getstatic     #161                // Field scala/runtime/ScalaRunTime$.MODULE$:Lscala/runtime/ScalaRunTime$;
         3: aload_0
         4: invokevirtual #176                // Method scala/runtime/ScalaRunTime$._hashCode:(Lscala/Product;)I
         7: ireturn
      LineNumberTable:
        line 141: 0
      LocalVariableTable:
        Start  Length  Slot  Name   Signature
            0       8     0  this   Lorg/scalatest/tools/Durations$Suite;

  public java.lang.String toString();
    descriptor: ()Ljava/lang/String;
    flags: (0x0001) ACC_PUBLIC
    Code:
      stack=2, locals=1, args_size=1
         0: getstatic     #161                // Field scala/runtime/ScalaRunTime$.MODULE$:Lscala/runtime/ScalaRunTime$;
         3: aload_0
         4: invokevirtual #180                // Method scala/runtime/ScalaRunTime$._toString:(Lscala/Product;)Ljava/lang/String;
         7: areturn
      LineNumberTable:
        line 141: 0
      LocalVariableTable:
        Start  Length  Slot  Name   Signature
            0       8     0  this   Lorg/scalatest/tools/Durations$Suite;

  public boolean equals(java.lang.Object);
    descriptor: (Ljava/lang/Object;)Z
    flags: (0x0001) ACC_PUBLIC
    Code:
      stack=2, locals=7, args_size=2
         0: aload_0
         1: aload_1
         2: if_acmpeq     132
         5: aload_1
         6: astore_3
         7: aload_3
         8: instanceof    #2                  // class org/scalatest/tools/Durations$Suite
        11: ifeq          33
        14: aload_3
        15: checkcast     #2                  // class org/scalatest/tools/Durations$Suite
        18: invokevirtual #136                // Method org$scalatest$tools$Durations$Suite$$$outer:()Lorg/scalatest/tools/Durations;
        21: aload_0
        22: invokevirtual #136                // Method org$scalatest$tools$Durations$Suite$$$outer:()Lorg/scalatest/tools/Durations;
        25: if_acmpne     33
        28: iconst_1
        29: istore_2
        30: goto          41
        33: goto          36
        36: iconst_0
        37: istore_2
        38: goto          41
        41: iload_2
        42: ifeq          136
        45: aload_1
        46: checkcast     #2                  // class org/scalatest/tools/Durations$Suite
        49: astore        4
        51: aload_0
        52: invokevirtual #107                // Method suiteId:()Ljava/lang/String;
        55: aload         4
        57: invokevirtual #107                // Method suiteId:()Ljava/lang/String;
        60: astore        5
        62: dup
        63: ifnonnull     75
        66: pop
        67: aload         5
        69: ifnull        83
        72: goto          128
        75: aload         5
        77: invokevirtual #183                // Method java/lang/Object.equals:(Ljava/lang/Object;)Z
        80: ifeq          128
        83: aload_0
        84: invokevirtual #122                // Method suiteName:()Ljava/lang/String;
        87: aload         4
        89: invokevirtual #122                // Method suiteName:()Ljava/lang/String;
        92: astore        6
        94: dup
        95: ifnonnull     107
        98: pop
        99: aload         6
       101: ifnull        115
       104: goto          128
       107: aload         6
       109: invokevirtual #183                // Method java/lang/Object.equals:(Ljava/lang/Object;)Z
       112: ifeq          128
       115: aload         4
       117: aload_0
       118: invokevirtual #185                // Method canEqual:(Ljava/lang/Object;)Z
       121: ifeq          128
       124: iconst_1
       125: goto          129
       128: iconst_0
       129: ifeq          136
       132: iconst_1
       133: goto          137
       136: iconst_0
       137: ireturn
      StackMapTable: number_of_entries = 12
        frame_type = 253 /* append */
          offset_delta = 33
          locals = [ top, class java/lang/Object ]
        frame_type = 2 /* same */
        frame_type = 255 /* full_frame */
          offset_delta = 4
          locals = [ class org/scalatest/tools/Durations$Suite, class java/lang/Object, int, class java/lang/Object ]
          stack = []
        frame_type = 255 /* full_frame */
          offset_delta = 33
          locals = [ class org/scalatest/tools/Durations$Suite, class java/lang/Object, int, class java/lang/Object, class org/scalatest/tools/Durations$Suite, class java/lang/String ]
          stack = [ class java/lang/String ]
        frame_type = 7 /* same */
        frame_type = 255 /* full_frame */
          offset_delta = 23
          locals = [ class org/scalatest/tools/Durations$Suite, class java/lang/Object, int, class java/lang/Object, class org/scalatest/tools/Durations$Suite, class java/lang/String, class java/lang/String ]
          stack = [ class java/lang/String ]
        frame_type = 7 /* same */
        frame_type = 250 /* chop */
          offset_delta = 12
        frame_type = 64 /* same_locals_1_stack_item */
          stack = [ int ]
        frame_type = 255 /* full_frame */
          offset_delta = 2
          locals = [ class org/scalatest/tools/Durations$Suite, class java/lang/Object ]
          stack = []
        frame_type = 253 /* append */
          offset_delta = 3
          locals = [ int, class java/lang/Object ]
        frame_type = 255 /* full_frame */
          offset_delta = 0
          locals = [ class org/scalatest/tools/Durations$Suite, class java/lang/Object ]
          stack = [ int ]
      LineNumberTable:
        line 141: 0
      LocalVariableTable:
        Start  Length  Slot  Name   Signature
            0     138     0  this   Lorg/scalatest/tools/Durations$Suite;
            0     138     1   x$1   Ljava/lang/Object;
    MethodParameters:
      Name                           Flags
      x$1                            final

  public org.scalatest.tools.Durations org$scalatest$tools$Durations$Suite$$$outer();
    descriptor: ()Lorg/scalatest/tools/Durations;
    flags: (0x1001) ACC_PUBLIC, ACC_SYNTHETIC
    Code:
      stack=1, locals=1, args_size=1
         0: aload_0
         1: getfield      #187                // Field $outer:Lorg/scalatest/tools/Durations;
         4: areturn
      LineNumberTable:
        line 141: 0
      LocalVariableTable:
        Start  Length  Slot  Name   Signature
            0       5     0  this   Lorg/scalatest/tools/Durations$Suite;

  public static final scala.collection.mutable.StringBuilder $anonfun$toXml$2(scala.collection.mutable.StringBuilder, org.scalatest.tools.Durations$Test);
    descriptor: (Lscala/collection/mutable/StringBuilder;Lorg/scalatest/tools/Durations$Test;)Lscala/collection/mutable/StringBuilder;
    flags: (0x1019) ACC_PUBLIC, ACC_STATIC, ACC_FINAL, ACC_SYNTHETIC
    Code:
      stack=2, locals=2, args_size=2
         0: aload_0
         1: aload_1
         2: invokevirtual #191                // Method org/scalatest/tools/Durations$Test.toXml:()Ljava/lang/String;
         5: invokevirtual #195                // Method scala/collection/mutable/StringBuilder.append:(Ljava/lang/String;)Lscala/collection/mutable/StringBuilder;
         8: areturn
      LineNumberTable:
        line 152: 0
      LocalVariableTable:
        Start  Length  Slot  Name   Signature
            0       9     0 buf$2   Lscala/collection/mutable/StringBuilder;
            0       9     1  test   Lorg/scalatest/tools/Durations$Test;
    MethodParameters:
      Name                           Flags
      buf$2                          final
      test                           final

  public org.scalatest.tools.Durations$Suite(org.scalatest.tools.Durations, java.lang.String, java.lang.String);
    descriptor: (Lorg/scalatest/tools/Durations;Ljava/lang/String;Ljava/lang/String;)V
    flags: (0x0001) ACC_PUBLIC
    Code:
      stack=3, locals=4, args_size=4
         0: aload_0
         1: aload_2
         2: putfield      #40                 // Field suiteId:Ljava/lang/String;
         5: aload_0
         6: aload_3
         7: putfield      #42                 // Field suiteName:Ljava/lang/String;
        10: aload_1
        11: ifnonnull     16
        14: aconst_null
        15: athrow
        16: aload_0
        17: aload_1
        18: putfield      #187                // Field $outer:Lorg/scalatest/tools/Durations;
        21: aload_0
        22: invokespecial #197                // Method java/lang/Object."<init>":()V
        25: aload_0
        26: invokestatic  #201                // InterfaceMethod scala/Product.$init$:(Lscala/Product;)V
        29: aload_0
        30: getstatic     #206                // Field scala/collection/mutable/Set$.MODULE$:Lscala/collection/mutable/Set$;
        33: getstatic     #211                // Field scala/collection/immutable/Nil$.MODULE$:Lscala/collection/immutable/Nil$;
        36: invokevirtual #214                // Method scala/collection/mutable/Set$.apply:(Lscala/collection/immutable/Seq;)Ljava/lang/Object;
        39: checkcast     #99                 // class scala/collection/mutable/Set
        42: putfield      #46                 // Field tests:Lscala/collection/mutable/Set;
        45: return
      StackMapTable: number_of_entries = 1
        frame_type = 16 /* same */
      LineNumberTable:
        line 141: 0
        line 142: 29
        line 141: 45
      LocalVariableTable:
        Start  Length  Slot  Name   Signature
            0      46     0  this   Lorg/scalatest/tools/Durations$Suite;
            0      46     1 $outer   Lorg/scalatest/tools/Durations;
            0      46     2 suiteId   Ljava/lang/String;
            0      46     3 suiteName   Ljava/lang/String;
    MethodParameters:
      Name                           Flags
      $outer                         final synthetic
      suiteId                        final
      suiteName                      final

  private static java.lang.Object $deserializeLambda$(java.lang.invoke.SerializedLambda);
    descriptor: (Ljava/lang/invoke/SerializedLambda;)Ljava/lang/Object;
    flags: (0x100a) ACC_PRIVATE, ACC_STATIC, ACC_SYNTHETIC
    Code:
      stack=1, locals=1, args_size=1
         0: aload_0
         1: invokedynamic #226,  0            // InvokeDynamic #1:lambdaDeserialize:(Ljava/lang/invoke/SerializedLambda;)Ljava/lang/Object;
         6: areturn
}
InnerClasses:
  public static final #14= #11 of #13;    // Lookup=class java/lang/invoke/MethodHandles$Lookup of class java/lang/invoke/MethodHandles
  public #17= #2 of #16;                  // Suite=class org/scalatest/tools/Durations$Suite of class org/scalatest/tools/Durations
  public #20= #19 of #16;                 // Test=class org/scalatest/tools/Durations$Test of class org/scalatest/tools/Durations
SourceFile: "Durations.scala"
BootstrapMethods:
  0: #93 REF_invokeStatic java/lang/invoke/LambdaMetafactory.altMetafactory:(Ljava/lang/invoke/MethodHandles$Lookup;Ljava/lang/String;Ljava/lang/invoke/MethodType;[Ljava/lang/Object;)Ljava/lang/invoke/CallSite;
    Method arguments:
      #77 (Ljava/lang/Object;)Ljava/lang/Object;
      #82 REF_invokeStatic org/scalatest/tools/Durations$Suite.$anonfun$toXml$2:(Lscala/collection/mutable/StringBuilder;Lorg/scalatest/tools/Durations$Test;)Lscala/collection/mutable/StringBuilder;
      #84 (Lorg/scalatest/tools/Durations$Test;)Lscala/collection/mutable/StringBuilder;
      #85 5
      #86 1
      #84 (Lorg/scalatest/tools/Durations$Test;)Lscala/collection/mutable/StringBuilder;
  1: #223 REF_invokeStatic scala/runtime/LambdaDeserialize.bootstrap:(Ljava/lang/invoke/MethodHandles$Lookup;Ljava/lang/String;Ljava/lang/invoke/MethodType;[Ljava/lang/invoke/MethodHandle;)Ljava/lang/invoke/CallSite;
    Method arguments:
      #82 REF_invokeStatic org/scalatest/tools/Durations$Suite.$anonfun$toXml$2:(Lscala/collection/mutable/StringBuilder;Lorg/scalatest/tools/Durations$Test;)Lscala/collection/mutable/StringBuilder;
  ScalaInlineInfo: length = 0x68 (unknown attribute)
   01 00 00 14 00 4E 00 4F 01 00 46 00 89 00 00 A5
   00 A6 00 00 83 00 84 00 00 8C 00 26 00 00 8D 00
   26 00 00 B5 00 A6 00 00 AC 00 91 00 00 85 00 86
   00 00 90 00 91 00 00 92 00 93 00 00 A8 00 A9 00
   00 1D 00 1E 00 00 9B 00 1E 00 00 8E 00 26 00 00
   15 00 26 00 00 17 00 26 00 00 18 00 2B 00 00 7D
   00 26 00 00 2F 00 26 00
  Scala: length = 0x0 (unknown attribute)

