Classfile /Users/mw/Projects/slang-braindump/.jar/jar11/assemble/slang-braindump/assemble/content/org/scalatest/tools/FilterReporter.class
  Last modified May 29, 2022; size 13793 bytes
  SHA-256 checksum b81d9267d2f84277b4713e75be119f1f531c4248abcfbb03503eac9bc3031a6b
  Compiled from "FilterReporter.scala"
public class org.scalatest.tools.FilterReporter implements org.scalatest.ResourcefulReporter
  minor version: 0
  major version: 52
  flags: (0x0021) ACC_PUBLIC, ACC_SUPER
  this_class: #2                          // org/scalatest/tools/FilterReporter
  super_class: #4                         // java/lang/Object
  interfaces: 1, fields: 2, methods: 13, attributes: 6
Constant pool:
    #1 = Utf8               org/scalatest/tools/FilterReporter
    #2 = Class              #1            // org/scalatest/tools/FilterReporter
    #3 = Utf8               java/lang/Object
    #4 = Class              #3            // java/lang/Object
    #5 = Utf8               org/scalatest/ResourcefulReporter
    #6 = Class              #5            // org/scalatest/ResourcefulReporter
    #7 = Utf8               FilterReporter.scala
    #8 = Utf8               Lscala/reflect/ScalaSignature;
    #9 = Utf8               bytes
   #10 = Utf8               \u0006\u0005!3Qa\u0002\u0005\u0001\u00119A\u0001\"\u0007\u0001\u0003\u0002\u0003\u0006Ia\u0007\u0005\t=\u0001\u0011\t\u0011)A\u0005?!)a\u0006\u0001C\u0001_!)1\u0007\u0001C!i!)\u0001\t\u0001C\u0005\u0003\")a\t\u0001C!\u000f\nqa)\u001b7uKJ\u0014V\r]8si\u0016\u0014(BA\u0005\u000b\u0003\u0015!xn\u001c7t\u0015\tYA\"A\u0005tG\u0006d\u0017\r^3ti*\tQ\"A\u0002pe\u001e\u001c2\u0001A\b\u0016!\t\u00012#D\u0001\u0012\u0015\u0005\u0011\u0012!B:dC2\f\u0017B\u0001\u000b\u0012\u0005\u0019\te.\u001f*fMB\u0011acF\u0007\u0002\u0015%\u0011\u0001D\u0003\u0002\u0014%\u0016\u001cx.\u001e:dK\u001a,HNU3q_J$XM]\u0001\te\u0016\u0004xN\u001d;fe\u000e\u0001\u0001C\u0001\f\u001d\u0013\ti\"B\u0001\u0005SKB|\'\u000f^3s\u0003%\u0019wN\u001c4jON+G\u000fE\u0002!O)r!!I\u0013\u0011\u0005\t\nR\"A\u0012\u000b\u0005\u0011R\u0012A\u0002\u001fs_>$h(\u0003\u0002\'#\u00051\u0001K]3eK\u001aL!\u0001K\u0015\u0003\u0007M+GO\u0003\u0002\'#A\u00111\u0006L\u0007\u0002\u0011%\u0011Q\u0006\u0003\u0002\u0014%\u0016\u0004xN\u001d;fe\u000e{gNZ5h!\u0006\u0014\u0018-\\\u0001\u0007y%t\u0017\u000e\u001e \u0015\u0007A\n$\u0007\u0005\u0002,\u0001!)\u0011d\u0001a\u00017!)ad\u0001a\u0001?\u0005)\u0011\r\u001d9msR\u0011Q\u0007\u000f\t\u0003!YJ!aN\t\u0003\tUs\u0017\u000e\u001e\u0005\u0006s\u0011\u0001\rAO\u0001\u0006KZ,g\u000e\u001e\t\u0003wyj\u0011\u0001\u0010\u0006\u0003{)\ta!\u001a<f]R\u001c\u0018BA =\u0005\u0015)e/\u001a8u\u0003a1\u0017\u000e\u001c;fe&sgm\\\'be.,\b\u000f\u0015:pm&$W\r\u001a\u000b\u0003\u0005\u0016\u0003\"\u0001E\"\n\u0005\u0011\u000b\"a\u0002\"p_2,\u0017M\u001c\u0005\u0006s\u0015\u0001\rAO\u0001\bI&\u001c\bo\\:f)\u0005)\u0004
   #11 = Utf8               java/lang/invoke/MethodHandles$Lookup
   #12 = Class              #11           // java/lang/invoke/MethodHandles$Lookup
   #13 = Utf8               java/lang/invoke/MethodHandles
   #14 = Class              #13           // java/lang/invoke/MethodHandles
   #15 = Utf8               Lookup
   #16 = Utf8               reporter
   #17 = Utf8               Lorg/scalatest/Reporter;
   #18 = Utf8               configSet
   #19 = Utf8               Lscala/collection/immutable/Set;
   #20 = Utf8               Lscala/collection/immutable/Set<Lorg/scalatest/tools/ReporterConfigParam;>;
   #21 = Utf8               apply
   #22 = Utf8               (Lorg/scalatest/events/Event;)V
   #23 = Utf8               event
   #24 = NameAndType        #16:#17       // reporter:Lorg/scalatest/Reporter;
   #25 = Fieldref           #2.#24        // org/scalatest/tools/FilterReporter.reporter:Lorg/scalatest/Reporter;
   #26 = Utf8               org/scalatest/events/DiscoveryStarting
   #27 = Class              #26           // org/scalatest/events/DiscoveryStarting
   #28 = Utf8               org/scalatest/Reporter
   #29 = Class              #28           // org/scalatest/Reporter
   #30 = NameAndType        #21:#22       // apply:(Lorg/scalatest/events/Event;)V
   #31 = InterfaceMethodref #29.#30       // org/scalatest/Reporter.apply:(Lorg/scalatest/events/Event;)V
   #32 = Utf8               scala/runtime/BoxedUnit
   #33 = Class              #32           // scala/runtime/BoxedUnit
   #34 = Utf8               UNIT
   #35 = Utf8               Lscala/runtime/BoxedUnit;
   #36 = NameAndType        #34:#35       // UNIT:Lscala/runtime/BoxedUnit;
   #37 = Fieldref           #33.#36       // scala/runtime/BoxedUnit.UNIT:Lscala/runtime/BoxedUnit;
   #38 = Utf8               org/scalatest/events/DiscoveryCompleted
   #39 = Class              #38           // org/scalatest/events/DiscoveryCompleted
   #40 = Utf8               org/scalatest/events/RunStarting
   #41 = Class              #40           // org/scalatest/events/RunStarting
   #42 = Utf8               org/scalatest/events/RunCompleted
   #43 = Class              #42           // org/scalatest/events/RunCompleted
   #44 = Utf8               org/scalatest/events/RunAborted
   #45 = Class              #44           // org/scalatest/events/RunAborted
   #46 = Utf8               org/scalatest/events/RunStopped
   #47 = Class              #46           // org/scalatest/events/RunStopped
   #48 = Utf8               org/scalatest/events/SuiteAborted
   #49 = Class              #48           // org/scalatest/events/SuiteAborted
   #50 = Utf8               org/scalatest/events/TestFailed
   #51 = Class              #50           // org/scalatest/events/TestFailed
   #52 = Utf8               recordedEvents
   #53 = Utf8               ()Lscala/collection/immutable/IndexedSeq;
   #54 = NameAndType        #52:#53       // recordedEvents:()Lscala/collection/immutable/IndexedSeq;
   #55 = Methodref          #51.#54       // org/scalatest/events/TestFailed.recordedEvents:()Lscala/collection/immutable/IndexedSeq;
   #56 = Utf8               (Ljava/lang/Object;)Ljava/lang/Object;
   #57 = MethodType         #56           //  (Ljava/lang/Object;)Ljava/lang/Object;
   #58 = Utf8               $anonfun$apply$1$adapted
   #59 = Utf8               (Lorg/scalatest/tools/FilterReporter;Lorg/scalatest/events/RecordableEvent;)Ljava/lang/Object;
   #60 = NameAndType        #58:#59       // $anonfun$apply$1$adapted:(Lorg/scalatest/tools/FilterReporter;Lorg/scalatest/events/RecordableEvent;)Ljava/lang/Object;
   #61 = Methodref          #2.#60        // org/scalatest/tools/FilterReporter.$anonfun$apply$1$adapted:(Lorg/scalatest/tools/FilterReporter;Lorg/scalatest/events/RecordableEvent;)Ljava/lang/Object;
   #62 = MethodHandle       6:#61         // REF_invokeStatic org/scalatest/tools/FilterReporter.$anonfun$apply$1$adapted:(Lorg/scalatest/tools/FilterReporter;Lorg/scalatest/events/RecordableEvent;)Ljava/lang/Object;
   #63 = Utf8               (Lorg/scalatest/events/RecordableEvent;)Ljava/lang/Object;
   #64 = MethodType         #63           //  (Lorg/scalatest/events/RecordableEvent;)Ljava/lang/Object;
   #65 = Integer            5
   #66 = Integer            1
   #67 = Utf8               java/lang/invoke/LambdaMetafactory
   #68 = Class              #67           // java/lang/invoke/LambdaMetafactory
   #69 = Utf8               altMetafactory
   #70 = Utf8               (Ljava/lang/invoke/MethodHandles$Lookup;Ljava/lang/String;Ljava/lang/invoke/MethodType;[Ljava/lang/Object;)Ljava/lang/invoke/CallSite;
   #71 = NameAndType        #69:#70       // altMetafactory:(Ljava/lang/invoke/MethodHandles$Lookup;Ljava/lang/String;Ljava/lang/invoke/MethodType;[Ljava/lang/Object;)Ljava/lang/invoke/CallSite;
   #72 = Methodref          #68.#71       // java/lang/invoke/LambdaMetafactory.altMetafactory:(Ljava/lang/invoke/MethodHandles$Lookup;Ljava/lang/String;Ljava/lang/invoke/MethodType;[Ljava/lang/Object;)Ljava/lang/invoke/CallSite;
   #73 = MethodHandle       6:#72         // REF_invokeStatic java/lang/invoke/LambdaMetafactory.altMetafactory:(Ljava/lang/invoke/MethodHandles$Lookup;Ljava/lang/String;Ljava/lang/invoke/MethodType;[Ljava/lang/Object;)Ljava/lang/invoke/CallSite;
   #74 = Utf8               (Lorg/scalatest/tools/FilterReporter;)Lscala/Function1;
   #75 = NameAndType        #21:#74       // apply:(Lorg/scalatest/tools/FilterReporter;)Lscala/Function1;
   #76 = InvokeDynamic      #0:#75        // #0:apply:(Lorg/scalatest/tools/FilterReporter;)Lscala/Function1;
   #77 = Utf8               scala/collection/immutable/IndexedSeq
   #78 = Class              #77           // scala/collection/immutable/IndexedSeq
   #79 = Utf8               filter
   #80 = Utf8               (Lscala/Function1;)Ljava/lang/Object;
   #81 = NameAndType        #79:#80       // filter:(Lscala/Function1;)Ljava/lang/Object;
   #82 = InterfaceMethodref #78.#81       // scala/collection/immutable/IndexedSeq.filter:(Lscala/Function1;)Ljava/lang/Object;
   #83 = Utf8               copy$default$1
   #84 = Utf8               ()Lorg/scalatest/events/Ordinal;
   #85 = NameAndType        #83:#84       // copy$default$1:()Lorg/scalatest/events/Ordinal;
   #86 = Methodref          #51.#85       // org/scalatest/events/TestFailed.copy$default$1:()Lorg/scalatest/events/Ordinal;
   #87 = Utf8               copy$default$2
   #88 = Utf8               ()Ljava/lang/String;
   #89 = NameAndType        #87:#88       // copy$default$2:()Ljava/lang/String;
   #90 = Methodref          #51.#89       // org/scalatest/events/TestFailed.copy$default$2:()Ljava/lang/String;
   #91 = Utf8               copy$default$3
   #92 = NameAndType        #91:#88       // copy$default$3:()Ljava/lang/String;
   #93 = Methodref          #51.#92       // org/scalatest/events/TestFailed.copy$default$3:()Ljava/lang/String;
   #94 = Utf8               copy$default$4
   #95 = NameAndType        #94:#88       // copy$default$4:()Ljava/lang/String;
   #96 = Methodref          #51.#95       // org/scalatest/events/TestFailed.copy$default$4:()Ljava/lang/String;
   #97 = Utf8               copy$default$5
   #98 = Utf8               ()Lscala/Option;
   #99 = NameAndType        #97:#98       // copy$default$5:()Lscala/Option;
  #100 = Methodref          #51.#99       // org/scalatest/events/TestFailed.copy$default$5:()Lscala/Option;
  #101 = Utf8               copy$default$6
  #102 = NameAndType        #101:#88      // copy$default$6:()Ljava/lang/String;
  #103 = Methodref          #51.#102      // org/scalatest/events/TestFailed.copy$default$6:()Ljava/lang/String;
  #104 = Utf8               copy$default$7
  #105 = NameAndType        #104:#88      // copy$default$7:()Ljava/lang/String;
  #106 = Methodref          #51.#105      // org/scalatest/events/TestFailed.copy$default$7:()Ljava/lang/String;
  #107 = Utf8               copy$default$9
  #108 = NameAndType        #107:#53      // copy$default$9:()Lscala/collection/immutable/IndexedSeq;
  #109 = Methodref          #51.#108      // org/scalatest/events/TestFailed.copy$default$9:()Lscala/collection/immutable/IndexedSeq;
  #110 = Utf8               copy$default$10
  #111 = NameAndType        #110:#98      // copy$default$10:()Lscala/Option;
  #112 = Methodref          #51.#111      // org/scalatest/events/TestFailed.copy$default$10:()Lscala/Option;
  #113 = Utf8               copy$default$11
  #114 = NameAndType        #113:#98      // copy$default$11:()Lscala/Option;
  #115 = Methodref          #51.#114      // org/scalatest/events/TestFailed.copy$default$11:()Lscala/Option;
  #116 = Utf8               copy$default$12
  #117 = NameAndType        #116:#98      // copy$default$12:()Lscala/Option;
  #118 = Methodref          #51.#117      // org/scalatest/events/TestFailed.copy$default$12:()Lscala/Option;
  #119 = Utf8               copy$default$13
  #120 = NameAndType        #119:#98      // copy$default$13:()Lscala/Option;
  #121 = Methodref          #51.#120      // org/scalatest/events/TestFailed.copy$default$13:()Lscala/Option;
  #122 = Utf8               copy$default$14
  #123 = NameAndType        #122:#98      // copy$default$14:()Lscala/Option;
  #124 = Methodref          #51.#123      // org/scalatest/events/TestFailed.copy$default$14:()Lscala/Option;
  #125 = Utf8               copy$default$15
  #126 = NameAndType        #125:#98      // copy$default$15:()Lscala/Option;
  #127 = Methodref          #51.#126      // org/scalatest/events/TestFailed.copy$default$15:()Lscala/Option;
  #128 = Utf8               copy$default$16
  #129 = NameAndType        #128:#88      // copy$default$16:()Ljava/lang/String;
  #130 = Methodref          #51.#129      // org/scalatest/events/TestFailed.copy$default$16:()Ljava/lang/String;
  #131 = Utf8               copy$default$17
  #132 = Utf8               ()J
  #133 = NameAndType        #131:#132     // copy$default$17:()J
  #134 = Methodref          #51.#133      // org/scalatest/events/TestFailed.copy$default$17:()J
  #135 = Utf8               copy
  #136 = Utf8               (Lorg/scalatest/events/Ordinal;Ljava/lang/String;Ljava/lang/String;Ljava/lang/String;Lscala/Option;Ljava/lang/String;Ljava/lang/String;Lscala/collection/immutable/IndexedSeq;Lscala/collection/immutable/IndexedSeq;Lscala/Option;Lscala/Option;Lscala/Option;Lscala/Option;Lscala/Option;Lscala/Option;Ljava/lang/String;J)Lorg/scalatest/events/TestFailed;
  #137 = NameAndType        #135:#136     // copy:(Lorg/scalatest/events/Ordinal;Ljava/lang/String;Ljava/lang/String;Ljava/lang/String;Lscala/Option;Ljava/lang/String;Ljava/lang/String;Lscala/collection/immutable/IndexedSeq;Lscala/collection/immutable/IndexedSeq;Lscala/Option;Lscala/Option;Lscala/Option;Lscala/Option;Lscala/Option;Lscala/Option;Ljava/lang/String;J)Lorg/scalatest/events/TestFailed;
  #138 = Methodref          #51.#137      // org/scalatest/events/TestFailed.copy:(Lorg/scalatest/events/Ordinal;Ljava/lang/String;Ljava/lang/String;Ljava/lang/String;Lscala/Option;Ljava/lang/String;Ljava/lang/String;Lscala/collection/immutable/IndexedSeq;Lscala/collection/immutable/IndexedSeq;Lscala/Option;Lscala/Option;Lscala/Option;Lscala/Option;Lscala/Option;Lscala/Option;Ljava/lang/String;J)Lorg/scalatest/events/TestFailed;
  #139 = Utf8               org/scalatest/events/SuiteCompleted
  #140 = Class              #139          // org/scalatest/events/SuiteCompleted
  #141 = NameAndType        #18:#19       // configSet:Lscala/collection/immutable/Set;
  #142 = Fieldref           #2.#141       // org/scalatest/tools/FilterReporter.configSet:Lscala/collection/immutable/Set;
  #143 = Utf8               org/scalatest/tools/FilterSuiteCompleted$
  #144 = Class              #143          // org/scalatest/tools/FilterSuiteCompleted$
  #145 = Utf8               MODULE$
  #146 = Utf8               Lorg/scalatest/tools/FilterSuiteCompleted$;
  #147 = NameAndType        #145:#146     // MODULE$:Lorg/scalatest/tools/FilterSuiteCompleted$;
  #148 = Fieldref           #144.#147     // org/scalatest/tools/FilterSuiteCompleted$.MODULE$:Lorg/scalatest/tools/FilterSuiteCompleted$;
  #149 = Utf8               scala/collection/immutable/Set
  #150 = Class              #149          // scala/collection/immutable/Set
  #151 = Utf8               contains
  #152 = Utf8               (Ljava/lang/Object;)Z
  #153 = NameAndType        #151:#152     // contains:(Ljava/lang/Object;)Z
  #154 = InterfaceMethodref #150.#153     // scala/collection/immutable/Set.contains:(Ljava/lang/Object;)Z
  #155 = Utf8               org/scalatest/events/SuiteStarting
  #156 = Class              #155          // org/scalatest/events/SuiteStarting
  #157 = Utf8               org/scalatest/tools/FilterSuiteStarting$
  #158 = Class              #157          // org/scalatest/tools/FilterSuiteStarting$
  #159 = Utf8               Lorg/scalatest/tools/FilterSuiteStarting$;
  #160 = NameAndType        #145:#159     // MODULE$:Lorg/scalatest/tools/FilterSuiteStarting$;
  #161 = Fieldref           #158.#160     // org/scalatest/tools/FilterSuiteStarting$.MODULE$:Lorg/scalatest/tools/FilterSuiteStarting$;
  #162 = Utf8               org/scalatest/events/TestStarting
  #163 = Class              #162          // org/scalatest/events/TestStarting
  #164 = Utf8               org/scalatest/tools/FilterTestStarting$
  #165 = Class              #164          // org/scalatest/tools/FilterTestStarting$
  #166 = Utf8               Lorg/scalatest/tools/FilterTestStarting$;
  #167 = NameAndType        #145:#166     // MODULE$:Lorg/scalatest/tools/FilterTestStarting$;
  #168 = Fieldref           #165.#167     // org/scalatest/tools/FilterTestStarting$.MODULE$:Lorg/scalatest/tools/FilterTestStarting$;
  #169 = Utf8               org/scalatest/events/TestSucceeded
  #170 = Class              #169          // org/scalatest/events/TestSucceeded
  #171 = Utf8               org/scalatest/tools/FilterTestSucceeded$
  #172 = Class              #171          // org/scalatest/tools/FilterTestSucceeded$
  #173 = Utf8               Lorg/scalatest/tools/FilterTestSucceeded$;
  #174 = NameAndType        #145:#173     // MODULE$:Lorg/scalatest/tools/FilterTestSucceeded$;
  #175 = Fieldref           #172.#174     // org/scalatest/tools/FilterTestSucceeded$.MODULE$:Lorg/scalatest/tools/FilterTestSucceeded$;
  #176 = Methodref          #170.#54      // org/scalatest/events/TestSucceeded.recordedEvents:()Lscala/collection/immutable/IndexedSeq;
  #177 = Utf8               $anonfun$apply$2$adapted
  #178 = NameAndType        #177:#59      // $anonfun$apply$2$adapted:(Lorg/scalatest/tools/FilterReporter;Lorg/scalatest/events/RecordableEvent;)Ljava/lang/Object;
  #179 = Methodref          #2.#178       // org/scalatest/tools/FilterReporter.$anonfun$apply$2$adapted:(Lorg/scalatest/tools/FilterReporter;Lorg/scalatest/events/RecordableEvent;)Ljava/lang/Object;
  #180 = MethodHandle       6:#179        // REF_invokeStatic org/scalatest/tools/FilterReporter.$anonfun$apply$2$adapted:(Lorg/scalatest/tools/FilterReporter;Lorg/scalatest/events/RecordableEvent;)Ljava/lang/Object;
  #181 = InvokeDynamic      #1:#75        // #1:apply:(Lorg/scalatest/tools/FilterReporter;)Lscala/Function1;
  #182 = Methodref          #170.#85      // org/scalatest/events/TestSucceeded.copy$default$1:()Lorg/scalatest/events/Ordinal;
  #183 = Methodref          #170.#89      // org/scalatest/events/TestSucceeded.copy$default$2:()Ljava/lang/String;
  #184 = Methodref          #170.#92      // org/scalatest/events/TestSucceeded.copy$default$3:()Ljava/lang/String;
  #185 = NameAndType        #94:#98       // copy$default$4:()Lscala/Option;
  #186 = Methodref          #170.#185     // org/scalatest/events/TestSucceeded.copy$default$4:()Lscala/Option;
  #187 = NameAndType        #97:#88       // copy$default$5:()Ljava/lang/String;
  #188 = Methodref          #170.#187     // org/scalatest/events/TestSucceeded.copy$default$5:()Ljava/lang/String;
  #189 = Methodref          #170.#102     // org/scalatest/events/TestSucceeded.copy$default$6:()Ljava/lang/String;
  #190 = Utf8               copy$default$8
  #191 = NameAndType        #190:#98      // copy$default$8:()Lscala/Option;
  #192 = Methodref          #170.#191     // org/scalatest/events/TestSucceeded.copy$default$8:()Lscala/Option;
  #193 = NameAndType        #107:#98      // copy$default$9:()Lscala/Option;
  #194 = Methodref          #170.#193     // org/scalatest/events/TestSucceeded.copy$default$9:()Lscala/Option;
  #195 = Methodref          #170.#111     // org/scalatest/events/TestSucceeded.copy$default$10:()Lscala/Option;
  #196 = Methodref          #170.#114     // org/scalatest/events/TestSucceeded.copy$default$11:()Lscala/Option;
  #197 = Methodref          #170.#117     // org/scalatest/events/TestSucceeded.copy$default$12:()Lscala/Option;
  #198 = NameAndType        #119:#88      // copy$default$13:()Ljava/lang/String;
  #199 = Methodref          #170.#198     // org/scalatest/events/TestSucceeded.copy$default$13:()Ljava/lang/String;
  #200 = NameAndType        #122:#132     // copy$default$14:()J
  #201 = Methodref          #170.#200     // org/scalatest/events/TestSucceeded.copy$default$14:()J
  #202 = Utf8               (Lorg/scalatest/events/Ordinal;Ljava/lang/String;Ljava/lang/String;Lscala/Option;Ljava/lang/String;Ljava/lang/String;Lscala/collection/immutable/IndexedSeq;Lscala/Option;Lscala/Option;Lscala/Option;Lscala/Option;Lscala/Option;Ljava/lang/String;J)Lorg/scalatest/events/TestSucceeded;
  #203 = NameAndType        #135:#202     // copy:(Lorg/scalatest/events/Ordinal;Ljava/lang/String;Ljava/lang/String;Lscala/Option;Ljava/lang/String;Ljava/lang/String;Lscala/collection/immutable/IndexedSeq;Lscala/Option;Lscala/Option;Lscala/Option;Lscala/Option;Lscala/Option;Ljava/lang/String;J)Lorg/scalatest/events/TestSucceeded;
  #204 = Methodref          #170.#203     // org/scalatest/events/TestSucceeded.copy:(Lorg/scalatest/events/Ordinal;Ljava/lang/String;Ljava/lang/String;Lscala/Option;Ljava/lang/String;Ljava/lang/String;Lscala/collection/immutable/IndexedSeq;Lscala/Option;Lscala/Option;Lscala/Option;Lscala/Option;Lscala/Option;Ljava/lang/String;J)Lorg/scalatest/events/TestSucceeded;
  #205 = Utf8               org/scalatest/events/TestIgnored
  #206 = Class              #205          // org/scalatest/events/TestIgnored
  #207 = Utf8               org/scalatest/tools/FilterTestIgnored$
  #208 = Class              #207          // org/scalatest/tools/FilterTestIgnored$
  #209 = Utf8               Lorg/scalatest/tools/FilterTestIgnored$;
  #210 = NameAndType        #145:#209     // MODULE$:Lorg/scalatest/tools/FilterTestIgnored$;
  #211 = Fieldref           #208.#210     // org/scalatest/tools/FilterTestIgnored$.MODULE$:Lorg/scalatest/tools/FilterTestIgnored$;
  #212 = Utf8               org/scalatest/events/TestCanceled
  #213 = Class              #212          // org/scalatest/events/TestCanceled
  #214 = Utf8               org/scalatest/tools/FilterTestCanceled$
  #215 = Class              #214          // org/scalatest/tools/FilterTestCanceled$
  #216 = Utf8               Lorg/scalatest/tools/FilterTestCanceled$;
  #217 = NameAndType        #145:#216     // MODULE$:Lorg/scalatest/tools/FilterTestCanceled$;
  #218 = Fieldref           #215.#217     // org/scalatest/tools/FilterTestCanceled$.MODULE$:Lorg/scalatest/tools/FilterTestCanceled$;
  #219 = Methodref          #213.#54      // org/scalatest/events/TestCanceled.recordedEvents:()Lscala/collection/immutable/IndexedSeq;
  #220 = Utf8               $anonfun$apply$3$adapted
  #221 = NameAndType        #220:#59      // $anonfun$apply$3$adapted:(Lorg/scalatest/tools/FilterReporter;Lorg/scalatest/events/RecordableEvent;)Ljava/lang/Object;
  #222 = Methodref          #2.#221       // org/scalatest/tools/FilterReporter.$anonfun$apply$3$adapted:(Lorg/scalatest/tools/FilterReporter;Lorg/scalatest/events/RecordableEvent;)Ljava/lang/Object;
  #223 = MethodHandle       6:#222        // REF_invokeStatic org/scalatest/tools/FilterReporter.$anonfun$apply$3$adapted:(Lorg/scalatest/tools/FilterReporter;Lorg/scalatest/events/RecordableEvent;)Ljava/lang/Object;
  #224 = InvokeDynamic      #2:#75        // #2:apply:(Lorg/scalatest/tools/FilterReporter;)Lscala/Function1;
  #225 = Methodref          #213.#85      // org/scalatest/events/TestCanceled.copy$default$1:()Lorg/scalatest/events/Ordinal;
  #226 = Methodref          #213.#89      // org/scalatest/events/TestCanceled.copy$default$2:()Ljava/lang/String;
  #227 = Methodref          #213.#92      // org/scalatest/events/TestCanceled.copy$default$3:()Ljava/lang/String;
  #228 = Methodref          #213.#95      // org/scalatest/events/TestCanceled.copy$default$4:()Ljava/lang/String;
  #229 = Methodref          #213.#99      // org/scalatest/events/TestCanceled.copy$default$5:()Lscala/Option;
  #230 = Methodref          #213.#102     // org/scalatest/events/TestCanceled.copy$default$6:()Ljava/lang/String;
  #231 = Methodref          #213.#105     // org/scalatest/events/TestCanceled.copy$default$7:()Ljava/lang/String;
  #232 = Methodref          #213.#193     // org/scalatest/events/TestCanceled.copy$default$9:()Lscala/Option;
  #233 = Methodref          #213.#111     // org/scalatest/events/TestCanceled.copy$default$10:()Lscala/Option;
  #234 = Methodref          #213.#114     // org/scalatest/events/TestCanceled.copy$default$11:()Lscala/Option;
  #235 = Methodref          #213.#117     // org/scalatest/events/TestCanceled.copy$default$12:()Lscala/Option;
  #236 = Methodref          #213.#120     // org/scalatest/events/TestCanceled.copy$default$13:()Lscala/Option;
  #237 = Methodref          #213.#123     // org/scalatest/events/TestCanceled.copy$default$14:()Lscala/Option;
  #238 = NameAndType        #125:#88      // copy$default$15:()Ljava/lang/String;
  #239 = Methodref          #213.#238     // org/scalatest/events/TestCanceled.copy$default$15:()Ljava/lang/String;
  #240 = NameAndType        #128:#132     // copy$default$16:()J
  #241 = Methodref          #213.#240     // org/scalatest/events/TestCanceled.copy$default$16:()J
  #242 = Utf8               (Lorg/scalatest/events/Ordinal;Ljava/lang/String;Ljava/lang/String;Ljava/lang/String;Lscala/Option;Ljava/lang/String;Ljava/lang/String;Lscala/collection/immutable/IndexedSeq;Lscala/Option;Lscala/Option;Lscala/Option;Lscala/Option;Lscala/Option;Lscala/Option;Ljava/lang/String;J)Lorg/scalatest/events/TestCanceled;
  #243 = NameAndType        #135:#242     // copy:(Lorg/scalatest/events/Ordinal;Ljava/lang/String;Ljava/lang/String;Ljava/lang/String;Lscala/Option;Ljava/lang/String;Ljava/lang/String;Lscala/collection/immutable/IndexedSeq;Lscala/Option;Lscala/Option;Lscala/Option;Lscala/Option;Lscala/Option;Lscala/Option;Ljava/lang/String;J)Lorg/scalatest/events/TestCanceled;
  #244 = Methodref          #213.#243     // org/scalatest/events/TestCanceled.copy:(Lorg/scalatest/events/Ordinal;Ljava/lang/String;Ljava/lang/String;Ljava/lang/String;Lscala/Option;Ljava/lang/String;Ljava/lang/String;Lscala/collection/immutable/IndexedSeq;Lscala/Option;Lscala/Option;Lscala/Option;Lscala/Option;Lscala/Option;Lscala/Option;Ljava/lang/String;J)Lorg/scalatest/events/TestCanceled;
  #245 = Utf8               org/scalatest/events/TestPending
  #246 = Class              #245          // org/scalatest/events/TestPending
  #247 = Utf8               org/scalatest/tools/FilterTestPending$
  #248 = Class              #247          // org/scalatest/tools/FilterTestPending$
  #249 = Utf8               Lorg/scalatest/tools/FilterTestPending$;
  #250 = NameAndType        #145:#249     // MODULE$:Lorg/scalatest/tools/FilterTestPending$;
  #251 = Fieldref           #248.#250     // org/scalatest/tools/FilterTestPending$.MODULE$:Lorg/scalatest/tools/FilterTestPending$;
  #252 = Methodref          #246.#54      // org/scalatest/events/TestPending.recordedEvents:()Lscala/collection/immutable/IndexedSeq;
  #253 = Utf8               $anonfun$apply$4$adapted
  #254 = NameAndType        #253:#59      // $anonfun$apply$4$adapted:(Lorg/scalatest/tools/FilterReporter;Lorg/scalatest/events/RecordableEvent;)Ljava/lang/Object;
  #255 = Methodref          #2.#254       // org/scalatest/tools/FilterReporter.$anonfun$apply$4$adapted:(Lorg/scalatest/tools/FilterReporter;Lorg/scalatest/events/RecordableEvent;)Ljava/lang/Object;
  #256 = MethodHandle       6:#255        // REF_invokeStatic org/scalatest/tools/FilterReporter.$anonfun$apply$4$adapted:(Lorg/scalatest/tools/FilterReporter;Lorg/scalatest/events/RecordableEvent;)Ljava/lang/Object;
  #257 = InvokeDynamic      #3:#75        // #3:apply:(Lorg/scalatest/tools/FilterReporter;)Lscala/Function1;
  #258 = Methodref          #246.#85      // org/scalatest/events/TestPending.copy$default$1:()Lorg/scalatest/events/Ordinal;
  #259 = Methodref          #246.#89      // org/scalatest/events/TestPending.copy$default$2:()Ljava/lang/String;
  #260 = Methodref          #246.#92      // org/scalatest/events/TestPending.copy$default$3:()Ljava/lang/String;
  #261 = Methodref          #246.#185     // org/scalatest/events/TestPending.copy$default$4:()Lscala/Option;
  #262 = Methodref          #246.#187     // org/scalatest/events/TestPending.copy$default$5:()Ljava/lang/String;
  #263 = Methodref          #246.#102     // org/scalatest/events/TestPending.copy$default$6:()Ljava/lang/String;
  #264 = Methodref          #246.#191     // org/scalatest/events/TestPending.copy$default$8:()Lscala/Option;
  #265 = Methodref          #246.#193     // org/scalatest/events/TestPending.copy$default$9:()Lscala/Option;
  #266 = Methodref          #246.#111     // org/scalatest/events/TestPending.copy$default$10:()Lscala/Option;
  #267 = Methodref          #246.#114     // org/scalatest/events/TestPending.copy$default$11:()Lscala/Option;
  #268 = NameAndType        #116:#88      // copy$default$12:()Ljava/lang/String;
  #269 = Methodref          #246.#268     // org/scalatest/events/TestPending.copy$default$12:()Ljava/lang/String;
  #270 = NameAndType        #119:#132     // copy$default$13:()J
  #271 = Methodref          #246.#270     // org/scalatest/events/TestPending.copy$default$13:()J
  #272 = Utf8               (Lorg/scalatest/events/Ordinal;Ljava/lang/String;Ljava/lang/String;Lscala/Option;Ljava/lang/String;Ljava/lang/String;Lscala/collection/immutable/IndexedSeq;Lscala/Option;Lscala/Option;Lscala/Option;Lscala/Option;Ljava/lang/String;J)Lorg/scalatest/events/TestPending;
  #273 = NameAndType        #135:#272     // copy:(Lorg/scalatest/events/Ordinal;Ljava/lang/String;Ljava/lang/String;Lscala/Option;Ljava/lang/String;Ljava/lang/String;Lscala/collection/immutable/IndexedSeq;Lscala/Option;Lscala/Option;Lscala/Option;Lscala/Option;Ljava/lang/String;J)Lorg/scalatest/events/TestPending;
  #274 = Methodref          #246.#273     // org/scalatest/events/TestPending.copy:(Lorg/scalatest/events/Ordinal;Ljava/lang/String;Ljava/lang/String;Lscala/Option;Ljava/lang/String;Ljava/lang/String;Lscala/collection/immutable/IndexedSeq;Lscala/Option;Lscala/Option;Lscala/Option;Lscala/Option;Ljava/lang/String;J)Lorg/scalatest/events/TestPending;
  #275 = Utf8               org/scalatest/events/InfoProvided
  #276 = Class              #275          // org/scalatest/events/InfoProvided
  #277 = Utf8               org/scalatest/tools/FilterInfoProvided$
  #278 = Class              #277          // org/scalatest/tools/FilterInfoProvided$
  #279 = Utf8               Lorg/scalatest/tools/FilterInfoProvided$;
  #280 = NameAndType        #145:#279     // MODULE$:Lorg/scalatest/tools/FilterInfoProvided$;
  #281 = Fieldref           #278.#280     // org/scalatest/tools/FilterInfoProvided$.MODULE$:Lorg/scalatest/tools/FilterInfoProvided$;
  #282 = Utf8               org/scalatest/events/AlertProvided
  #283 = Class              #282          // org/scalatest/events/AlertProvided
  #284 = Utf8               org/scalatest/tools/FilterAlertProvided$
  #285 = Class              #284          // org/scalatest/tools/FilterAlertProvided$
  #286 = Utf8               Lorg/scalatest/tools/FilterAlertProvided$;
  #287 = NameAndType        #145:#286     // MODULE$:Lorg/scalatest/tools/FilterAlertProvided$;
  #288 = Fieldref           #285.#287     // org/scalatest/tools/FilterAlertProvided$.MODULE$:Lorg/scalatest/tools/FilterAlertProvided$;
  #289 = Utf8               org/scalatest/events/NoteProvided
  #290 = Class              #289          // org/scalatest/events/NoteProvided
  #291 = Utf8               org/scalatest/tools/FilterNoteProvided$
  #292 = Class              #291          // org/scalatest/tools/FilterNoteProvided$
  #293 = Utf8               Lorg/scalatest/tools/FilterNoteProvided$;
  #294 = NameAndType        #145:#293     // MODULE$:Lorg/scalatest/tools/FilterNoteProvided$;
  #295 = Fieldref           #292.#294     // org/scalatest/tools/FilterNoteProvided$.MODULE$:Lorg/scalatest/tools/FilterNoteProvided$;
  #296 = Utf8               org/scalatest/events/ScopeOpened
  #297 = Class              #296          // org/scalatest/events/ScopeOpened
  #298 = Utf8               org/scalatest/tools/FilterScopeOpened$
  #299 = Class              #298          // org/scalatest/tools/FilterScopeOpened$
  #300 = Utf8               Lorg/scalatest/tools/FilterScopeOpened$;
  #301 = NameAndType        #145:#300     // MODULE$:Lorg/scalatest/tools/FilterScopeOpened$;
  #302 = Fieldref           #299.#301     // org/scalatest/tools/FilterScopeOpened$.MODULE$:Lorg/scalatest/tools/FilterScopeOpened$;
  #303 = Utf8               org/scalatest/events/ScopeClosed
  #304 = Class              #303          // org/scalatest/events/ScopeClosed
  #305 = Utf8               org/scalatest/tools/FilterScopeClosed$
  #306 = Class              #305          // org/scalatest/tools/FilterScopeClosed$
  #307 = Utf8               Lorg/scalatest/tools/FilterScopeClosed$;
  #308 = NameAndType        #145:#307     // MODULE$:Lorg/scalatest/tools/FilterScopeClosed$;
  #309 = Fieldref           #306.#308     // org/scalatest/tools/FilterScopeClosed$.MODULE$:Lorg/scalatest/tools/FilterScopeClosed$;
  #310 = Utf8               org/scalatest/events/ScopePending
  #311 = Class              #310          // org/scalatest/events/ScopePending
  #312 = Utf8               org/scalatest/tools/FilterScopePending$
  #313 = Class              #312          // org/scalatest/tools/FilterScopePending$
  #314 = Utf8               Lorg/scalatest/tools/FilterScopePending$;
  #315 = NameAndType        #145:#314     // MODULE$:Lorg/scalatest/tools/FilterScopePending$;
  #316 = Fieldref           #313.#315     // org/scalatest/tools/FilterScopePending$.MODULE$:Lorg/scalatest/tools/FilterScopePending$;
  #317 = Utf8               org/scalatest/events/MarkupProvided
  #318 = Class              #317          // org/scalatest/events/MarkupProvided
  #319 = Utf8               org/scalatest/tools/FilterMarkupProvided$
  #320 = Class              #319          // org/scalatest/tools/FilterMarkupProvided$
  #321 = Utf8               Lorg/scalatest/tools/FilterMarkupProvided$;
  #322 = NameAndType        #145:#321     // MODULE$:Lorg/scalatest/tools/FilterMarkupProvided$;
  #323 = Fieldref           #320.#322     // org/scalatest/tools/FilterMarkupProvided$.MODULE$:Lorg/scalatest/tools/FilterMarkupProvided$;
  #324 = Utf8               scala/MatchError
  #325 = Class              #324          // scala/MatchError
  #326 = Utf8               <init>
  #327 = Utf8               (Ljava/lang/Object;)V
  #328 = NameAndType        #326:#327     // "<init>":(Ljava/lang/Object;)V
  #329 = Methodref          #325.#328     // scala/MatchError."<init>":(Ljava/lang/Object;)V
  #330 = Utf8               x$1
  #331 = Utf8               Lscala/collection/immutable/IndexedSeq;
  #332 = Utf8               x$2
  #333 = Utf8               Lorg/scalatest/events/Ordinal;
  #334 = Utf8               x$3
  #335 = Utf8               Ljava/lang/String;
  #336 = Utf8               x$4
  #337 = Utf8               x$5
  #338 = Utf8               x$6
  #339 = Utf8               Lscala/Option;
  #340 = Utf8               x$7
  #341 = Utf8               x$8
  #342 = Utf8               x$9
  #343 = Utf8               x$10
  #344 = Utf8               x$11
  #345 = Utf8               x$12
  #346 = Utf8               x$13
  #347 = Utf8               x$14
  #348 = Utf8               x$15
  #349 = Utf8               x$16
  #350 = Utf8               x$17
  #351 = Utf8               J
  #352 = Utf8               x$18
  #353 = Utf8               x$19
  #354 = Utf8               x$20
  #355 = Utf8               x$21
  #356 = Utf8               x$22
  #357 = Utf8               x$23
  #358 = Utf8               x$24
  #359 = Utf8               x$25
  #360 = Utf8               x$26
  #361 = Utf8               x$27
  #362 = Utf8               x$28
  #363 = Utf8               x$29
  #364 = Utf8               x$30
  #365 = Utf8               x$31
  #366 = Utf8               x$32
  #367 = Utf8               x$33
  #368 = Utf8               x$34
  #369 = Utf8               x$35
  #370 = Utf8               x$36
  #371 = Utf8               x$37
  #372 = Utf8               x$38
  #373 = Utf8               x$39
  #374 = Utf8               x$40
  #375 = Utf8               x$41
  #376 = Utf8               x$42
  #377 = Utf8               x$43
  #378 = Utf8               x$44
  #379 = Utf8               x$45
  #380 = Utf8               x$46
  #381 = Utf8               x$47
  #382 = Utf8               x$48
  #383 = Utf8               x$49
  #384 = Utf8               x$50
  #385 = Utf8               x$51
  #386 = Utf8               x$52
  #387 = Utf8               x$53
  #388 = Utf8               x$54
  #389 = Utf8               x$55
  #390 = Utf8               x$56
  #391 = Utf8               x$57
  #392 = Utf8               x$58
  #393 = Utf8               x$59
  #394 = Utf8               x$60
  #395 = Utf8               report
  #396 = Utf8               this
  #397 = Utf8               Lorg/scalatest/tools/FilterReporter;
  #398 = Utf8               Lorg/scalatest/events/Event;
  #399 = Utf8               org/scalatest/events/Event
  #400 = Class              #399          // org/scalatest/events/Event
  #401 = Utf8               filterInfoMarkupProvided
  #402 = Utf8               (Lorg/scalatest/events/Event;)Z
  #403 = Utf8               dispose
  #404 = Utf8               ()V
  #405 = Utf8               org/scalatest/Reporter$
  #406 = Class              #405          // org/scalatest/Reporter$
  #407 = Utf8               Lorg/scalatest/Reporter$;
  #408 = NameAndType        #145:#407     // MODULE$:Lorg/scalatest/Reporter$;
  #409 = Fieldref           #406.#408     // org/scalatest/Reporter$.MODULE$:Lorg/scalatest/Reporter$;
  #410 = Utf8               propagateDispose
  #411 = Utf8               (Lorg/scalatest/Reporter;)V
  #412 = NameAndType        #410:#411     // propagateDispose:(Lorg/scalatest/Reporter;)V
  #413 = Methodref          #406.#412     // org/scalatest/Reporter$.propagateDispose:(Lorg/scalatest/Reporter;)V
  #414 = Utf8               $anonfun$apply$1
  #415 = Utf8               (Lorg/scalatest/tools/FilterReporter;Lorg/scalatest/events/RecordableEvent;)Z
  #416 = Utf8               $this
  #417 = NameAndType        #401:#402     // filterInfoMarkupProvided:(Lorg/scalatest/events/Event;)Z
  #418 = Methodref          #2.#417       // org/scalatest/tools/FilterReporter.filterInfoMarkupProvided:(Lorg/scalatest/events/Event;)Z
  #419 = Utf8               Lorg/scalatest/events/RecordableEvent;
  #420 = Utf8               $anonfun$apply$2
  #421 = Utf8               $anonfun$apply$3
  #422 = Utf8               $anonfun$apply$4
  #423 = Utf8               (Lorg/scalatest/Reporter;Lscala/collection/immutable/Set;)V
  #424 = Utf8               (Lorg/scalatest/Reporter;Lscala/collection/immutable/Set<Lorg/scalatest/tools/ReporterConfigParam;>;)V
  #425 = NameAndType        #326:#404     // "<init>":()V
  #426 = Methodref          #4.#425       // java/lang/Object."<init>":()V
  #427 = NameAndType        #414:#415     // $anonfun$apply$1:(Lorg/scalatest/tools/FilterReporter;Lorg/scalatest/events/RecordableEvent;)Z
  #428 = Methodref          #2.#427       // org/scalatest/tools/FilterReporter.$anonfun$apply$1:(Lorg/scalatest/tools/FilterReporter;Lorg/scalatest/events/RecordableEvent;)Z
  #429 = Utf8               scala/runtime/BoxesRunTime
  #430 = Class              #429          // scala/runtime/BoxesRunTime
  #431 = Utf8               boxToBoolean
  #432 = Utf8               (Z)Ljava/lang/Boolean;
  #433 = NameAndType        #431:#432     // boxToBoolean:(Z)Ljava/lang/Boolean;
  #434 = Methodref          #430.#433     // scala/runtime/BoxesRunTime.boxToBoolean:(Z)Ljava/lang/Boolean;
  #435 = NameAndType        #420:#415     // $anonfun$apply$2:(Lorg/scalatest/tools/FilterReporter;Lorg/scalatest/events/RecordableEvent;)Z
  #436 = Methodref          #2.#435       // org/scalatest/tools/FilterReporter.$anonfun$apply$2:(Lorg/scalatest/tools/FilterReporter;Lorg/scalatest/events/RecordableEvent;)Z
  #437 = NameAndType        #421:#415     // $anonfun$apply$3:(Lorg/scalatest/tools/FilterReporter;Lorg/scalatest/events/RecordableEvent;)Z
  #438 = Methodref          #2.#437       // org/scalatest/tools/FilterReporter.$anonfun$apply$3:(Lorg/scalatest/tools/FilterReporter;Lorg/scalatest/events/RecordableEvent;)Z
  #439 = NameAndType        #422:#415     // $anonfun$apply$4:(Lorg/scalatest/tools/FilterReporter;Lorg/scalatest/events/RecordableEvent;)Z
  #440 = Methodref          #2.#439       // org/scalatest/tools/FilterReporter.$anonfun$apply$4:(Lorg/scalatest/tools/FilterReporter;Lorg/scalatest/events/RecordableEvent;)Z
  #441 = Utf8               $deserializeLambda$
  #442 = Utf8               (Ljava/lang/invoke/SerializedLambda;)Ljava/lang/Object;
  #443 = Utf8               scala/runtime/LambdaDeserialize
  #444 = Class              #443          // scala/runtime/LambdaDeserialize
  #445 = Utf8               bootstrap
  #446 = Utf8               (Ljava/lang/invoke/MethodHandles$Lookup;Ljava/lang/String;Ljava/lang/invoke/MethodType;[Ljava/lang/invoke/MethodHandle;)Ljava/lang/invoke/CallSite;
  #447 = NameAndType        #445:#446     // bootstrap:(Ljava/lang/invoke/MethodHandles$Lookup;Ljava/lang/String;Ljava/lang/invoke/MethodType;[Ljava/lang/invoke/MethodHandle;)Ljava/lang/invoke/CallSite;
  #448 = Methodref          #444.#447     // scala/runtime/LambdaDeserialize.bootstrap:(Ljava/lang/invoke/MethodHandles$Lookup;Ljava/lang/String;Ljava/lang/invoke/MethodType;[Ljava/lang/invoke/MethodHandle;)Ljava/lang/invoke/CallSite;
  #449 = MethodHandle       6:#448        // REF_invokeStatic scala/runtime/LambdaDeserialize.bootstrap:(Ljava/lang/invoke/MethodHandles$Lookup;Ljava/lang/String;Ljava/lang/invoke/MethodType;[Ljava/lang/invoke/MethodHandle;)Ljava/lang/invoke/CallSite;
  #450 = Utf8               lambdaDeserialize
  #451 = NameAndType        #450:#442     // lambdaDeserialize:(Ljava/lang/invoke/SerializedLambda;)Ljava/lang/Object;
  #452 = InvokeDynamic      #4:#451       // #4:lambdaDeserialize:(Ljava/lang/invoke/SerializedLambda;)Ljava/lang/Object;
  #453 = Utf8               Signature
  #454 = Utf8               Code
  #455 = Utf8               StackMapTable
  #456 = Utf8               LineNumberTable
  #457 = Utf8               LocalVariableTable
  #458 = Utf8               MethodParameters
  #459 = Utf8               InnerClasses
  #460 = Utf8               SourceFile
  #461 = Utf8               RuntimeVisibleAnnotations
  #462 = Utf8               BootstrapMethods
  #463 = Utf8               ScalaInlineInfo
  #464 = Utf8               ScalaSig
{
  private final org.scalatest.Reporter reporter;
    descriptor: Lorg/scalatest/Reporter;
    flags: (0x0012) ACC_PRIVATE, ACC_FINAL

  private final scala.collection.immutable.Set<org.scalatest.tools.ReporterConfigParam> configSet;
    descriptor: Lscala/collection/immutable/Set;
    flags: (0x0012) ACC_PRIVATE, ACC_FINAL
    Signature: #20                          // Lscala/collection/immutable/Set<Lorg/scalatest/tools/ReporterConfigParam;>;

  public void apply(org.scalatest.events.Event);
    descriptor: (Lorg/scalatest/events/Event;)V
    flags: (0x0001) ACC_PUBLIC
    Code:
      stack=20, locals=91, args_size=2
         0: aload_0
         1: getfield      #25                 // Field reporter:Lorg/scalatest/Reporter;
         4: astore_3
         5: aload_1
         6: astore        4
         8: aload         4
        10: instanceof    #27                 // class org/scalatest/events/DiscoveryStarting
        13: ifeq          38
        16: aload         4
        18: checkcast     #27                 // class org/scalatest/events/DiscoveryStarting
        21: astore        5
        23: aload_3
        24: aload         5
        26: invokeinterface #31,  2           // InterfaceMethod org/scalatest/Reporter.apply:(Lorg/scalatest/events/Event;)V
        31: getstatic     #37                 // Field scala/runtime/BoxedUnit.UNIT:Lscala/runtime/BoxedUnit;
        34: astore_2
        35: goto          1646
        38: goto          41
        41: aload         4
        43: instanceof    #39                 // class org/scalatest/events/DiscoveryCompleted
        46: ifeq          71
        49: aload         4
        51: checkcast     #39                 // class org/scalatest/events/DiscoveryCompleted
        54: astore        6
        56: aload_3
        57: aload         6
        59: invokeinterface #31,  2           // InterfaceMethod org/scalatest/Reporter.apply:(Lorg/scalatest/events/Event;)V
        64: getstatic     #37                 // Field scala/runtime/BoxedUnit.UNIT:Lscala/runtime/BoxedUnit;
        67: astore_2
        68: goto          1646
        71: goto          74
        74: aload         4
        76: instanceof    #41                 // class org/scalatest/events/RunStarting
        79: ifeq          104
        82: aload         4
        84: checkcast     #41                 // class org/scalatest/events/RunStarting
        87: astore        7
        89: aload_3
        90: aload         7
        92: invokeinterface #31,  2           // InterfaceMethod org/scalatest/Reporter.apply:(Lorg/scalatest/events/Event;)V
        97: getstatic     #37                 // Field scala/runtime/BoxedUnit.UNIT:Lscala/runtime/BoxedUnit;
       100: astore_2
       101: goto          1646
       104: goto          107
       107: aload         4
       109: instanceof    #43                 // class org/scalatest/events/RunCompleted
       112: ifeq          137
       115: aload         4
       117: checkcast     #43                 // class org/scalatest/events/RunCompleted
       120: astore        8
       122: aload_3
       123: aload         8
       125: invokeinterface #31,  2           // InterfaceMethod org/scalatest/Reporter.apply:(Lorg/scalatest/events/Event;)V
       130: getstatic     #37                 // Field scala/runtime/BoxedUnit.UNIT:Lscala/runtime/BoxedUnit;
       133: astore_2
       134: goto          1646
       137: goto          140
       140: aload         4
       142: instanceof    #45                 // class org/scalatest/events/RunAborted
       145: ifeq          170
       148: aload         4
       150: checkcast     #45                 // class org/scalatest/events/RunAborted
       153: astore        9
       155: aload_3
       156: aload         9
       158: invokeinterface #31,  2           // InterfaceMethod org/scalatest/Reporter.apply:(Lorg/scalatest/events/Event;)V
       163: getstatic     #37                 // Field scala/runtime/BoxedUnit.UNIT:Lscala/runtime/BoxedUnit;
       166: astore_2
       167: goto          1646
       170: goto          173
       173: aload         4
       175: instanceof    #47                 // class org/scalatest/events/RunStopped
       178: ifeq          203
       181: aload         4
       183: checkcast     #47                 // class org/scalatest/events/RunStopped
       186: astore        10
       188: aload_3
       189: aload         10
       191: invokeinterface #31,  2           // InterfaceMethod org/scalatest/Reporter.apply:(Lorg/scalatest/events/Event;)V
       196: getstatic     #37                 // Field scala/runtime/BoxedUnit.UNIT:Lscala/runtime/BoxedUnit;
       199: astore_2
       200: goto          1646
       203: goto          206
       206: aload         4
       208: instanceof    #49                 // class org/scalatest/events/SuiteAborted
       211: ifeq          236
       214: aload         4
       216: checkcast     #49                 // class org/scalatest/events/SuiteAborted
       219: astore        11
       221: aload_3
       222: aload         11
       224: invokeinterface #31,  2           // InterfaceMethod org/scalatest/Reporter.apply:(Lorg/scalatest/events/Event;)V
       229: getstatic     #37                 // Field scala/runtime/BoxedUnit.UNIT:Lscala/runtime/BoxedUnit;
       232: astore_2
       233: goto          1646
       236: goto          239
       239: aload         4
       241: instanceof    #51                 // class org/scalatest/events/TestFailed
       244: ifeq          439
       247: aload         4
       249: checkcast     #51                 // class org/scalatest/events/TestFailed
       252: astore        12
       254: aload_3
       255: aload         12
       257: invokevirtual #55                 // Method org/scalatest/events/TestFailed.recordedEvents:()Lscala/collection/immutable/IndexedSeq;
       260: aload_0
       261: invokedynamic #76,  0             // InvokeDynamic #0:apply:(Lorg/scalatest/tools/FilterReporter;)Lscala/Function1;
       266: invokeinterface #82,  2           // InterfaceMethod scala/collection/immutable/IndexedSeq.filter:(Lscala/Function1;)Ljava/lang/Object;
       271: checkcast     #78                 // class scala/collection/immutable/IndexedSeq
       274: astore        13
       276: aload         12
       278: invokevirtual #86                 // Method org/scalatest/events/TestFailed.copy$default$1:()Lorg/scalatest/events/Ordinal;
       281: astore        14
       283: aload         12
       285: invokevirtual #90                 // Method org/scalatest/events/TestFailed.copy$default$2:()Ljava/lang/String;
       288: astore        15
       290: aload         12
       292: invokevirtual #93                 // Method org/scalatest/events/TestFailed.copy$default$3:()Ljava/lang/String;
       295: astore        16
       297: aload         12
       299: invokevirtual #96                 // Method org/scalatest/events/TestFailed.copy$default$4:()Ljava/lang/String;
       302: astore        17
       304: aload         12
       306: invokevirtual #100                // Method org/scalatest/events/TestFailed.copy$default$5:()Lscala/Option;
       309: astore        18
       311: aload         12
       313: invokevirtual #103                // Method org/scalatest/events/TestFailed.copy$default$6:()Ljava/lang/String;
       316: astore        19
       318: aload         12
       320: invokevirtual #106                // Method org/scalatest/events/TestFailed.copy$default$7:()Ljava/lang/String;
       323: astore        20
       325: aload         12
       327: invokevirtual #109                // Method org/scalatest/events/TestFailed.copy$default$9:()Lscala/collection/immutable/IndexedSeq;
       330: astore        21
       332: aload         12
       334: invokevirtual #112                // Method org/scalatest/events/TestFailed.copy$default$10:()Lscala/Option;
       337: astore        22
       339: aload         12
       341: invokevirtual #115                // Method org/scalatest/events/TestFailed.copy$default$11:()Lscala/Option;
       344: astore        23
       346: aload         12
       348: invokevirtual #118                // Method org/scalatest/events/TestFailed.copy$default$12:()Lscala/Option;
       351: astore        24
       353: aload         12
       355: invokevirtual #121                // Method org/scalatest/events/TestFailed.copy$default$13:()Lscala/Option;
       358: astore        25
       360: aload         12
       362: invokevirtual #124                // Method org/scalatest/events/TestFailed.copy$default$14:()Lscala/Option;
       365: astore        26
       367: aload         12
       369: invokevirtual #127                // Method org/scalatest/events/TestFailed.copy$default$15:()Lscala/Option;
       372: astore        27
       374: aload         12
       376: invokevirtual #130                // Method org/scalatest/events/TestFailed.copy$default$16:()Ljava/lang/String;
       379: astore        28
       381: aload         12
       383: invokevirtual #134                // Method org/scalatest/events/TestFailed.copy$default$17:()J
       386: lstore        29
       388: aload         12
       390: aload         14
       392: aload         15
       394: aload         16
       396: aload         17
       398: aload         18
       400: aload         19
       402: aload         20
       404: aload         13
       406: aload         21
       408: aload         22
       410: aload         23
       412: aload         24
       414: aload         25
       416: aload         26
       418: aload         27
       420: aload         28
       422: lload         29
       424: invokevirtual #138                // Method org/scalatest/events/TestFailed.copy:(Lorg/scalatest/events/Ordinal;Ljava/lang/String;Ljava/lang/String;Ljava/lang/String;Lscala/Option;Ljava/lang/String;Ljava/lang/String;Lscala/collection/immutable/IndexedSeq;Lscala/collection/immutable/IndexedSeq;Lscala/Option;Lscala/Option;Lscala/Option;Lscala/Option;Lscala/Option;Lscala/Option;Ljava/lang/String;J)Lorg/scalatest/events/TestFailed;
       427: invokeinterface #31,  2           // InterfaceMethod org/scalatest/Reporter.apply:(Lorg/scalatest/events/Event;)V
       432: getstatic     #37                 // Field scala/runtime/BoxedUnit.UNIT:Lscala/runtime/BoxedUnit;
       435: astore_2
       436: goto          1646
       439: goto          442
       442: aload         4
       444: instanceof    #140                // class org/scalatest/events/SuiteCompleted
       447: ifeq          493
       450: aload         4
       452: checkcast     #140                // class org/scalatest/events/SuiteCompleted
       455: astore        31
       457: aload_0
       458: getfield      #142                // Field configSet:Lscala/collection/immutable/Set;
       461: getstatic     #148                // Field org/scalatest/tools/FilterSuiteCompleted$.MODULE$:Lorg/scalatest/tools/FilterSuiteCompleted$;
       464: invokeinterface #154,  2          // InterfaceMethod scala/collection/immutable/Set.contains:(Ljava/lang/Object;)Z
       469: ifne          486
       472: aload_3
       473: aload         31
       475: invokeinterface #31,  2           // InterfaceMethod org/scalatest/Reporter.apply:(Lorg/scalatest/events/Event;)V
       480: getstatic     #37                 // Field scala/runtime/BoxedUnit.UNIT:Lscala/runtime/BoxedUnit;
       483: goto          489
       486: getstatic     #37                 // Field scala/runtime/BoxedUnit.UNIT:Lscala/runtime/BoxedUnit;
       489: astore_2
       490: goto          1646
       493: goto          496
       496: aload         4
       498: instanceof    #156                // class org/scalatest/events/SuiteStarting
       501: ifeq          547
       504: aload         4
       506: checkcast     #156                // class org/scalatest/events/SuiteStarting
       509: astore        32
       511: aload_0
       512: getfield      #142                // Field configSet:Lscala/collection/immutable/Set;
       515: getstatic     #161                // Field org/scalatest/tools/FilterSuiteStarting$.MODULE$:Lorg/scalatest/tools/FilterSuiteStarting$;
       518: invokeinterface #154,  2          // InterfaceMethod scala/collection/immutable/Set.contains:(Ljava/lang/Object;)Z
       523: ifne          540
       526: aload_3
       527: aload         32
       529: invokeinterface #31,  2           // InterfaceMethod org/scalatest/Reporter.apply:(Lorg/scalatest/events/Event;)V
       534: getstatic     #37                 // Field scala/runtime/BoxedUnit.UNIT:Lscala/runtime/BoxedUnit;
       537: goto          543
       540: getstatic     #37                 // Field scala/runtime/BoxedUnit.UNIT:Lscala/runtime/BoxedUnit;
       543: astore_2
       544: goto          1646
       547: goto          550
       550: aload         4
       552: instanceof    #163                // class org/scalatest/events/TestStarting
       555: ifeq          601
       558: aload         4
       560: checkcast     #163                // class org/scalatest/events/TestStarting
       563: astore        33
       565: aload_0
       566: getfield      #142                // Field configSet:Lscala/collection/immutable/Set;
       569: getstatic     #168                // Field org/scalatest/tools/FilterTestStarting$.MODULE$:Lorg/scalatest/tools/FilterTestStarting$;
       572: invokeinterface #154,  2          // InterfaceMethod scala/collection/immutable/Set.contains:(Ljava/lang/Object;)Z
       577: ifne          594
       580: aload_3
       581: aload         33
       583: invokeinterface #31,  2           // InterfaceMethod org/scalatest/Reporter.apply:(Lorg/scalatest/events/Event;)V
       588: getstatic     #37                 // Field scala/runtime/BoxedUnit.UNIT:Lscala/runtime/BoxedUnit;
       591: goto          597
       594: getstatic     #37                 // Field scala/runtime/BoxedUnit.UNIT:Lscala/runtime/BoxedUnit;
       597: astore_2
       598: goto          1646
       601: goto          604
       604: aload         4
       606: instanceof    #170                // class org/scalatest/events/TestSucceeded
       609: ifeq          798
       612: aload         4
       614: checkcast     #170                // class org/scalatest/events/TestSucceeded
       617: astore        34
       619: aload_0
       620: getfield      #142                // Field configSet:Lscala/collection/immutable/Set;
       623: getstatic     #175                // Field org/scalatest/tools/FilterTestSucceeded$.MODULE$:Lorg/scalatest/tools/FilterTestSucceeded$;
       626: invokeinterface #154,  2          // InterfaceMethod scala/collection/immutable/Set.contains:(Ljava/lang/Object;)Z
       631: ifne          791
       634: aload_3
       635: aload         34
       637: invokevirtual #176                // Method org/scalatest/events/TestSucceeded.recordedEvents:()Lscala/collection/immutable/IndexedSeq;
       640: aload_0
       641: invokedynamic #181,  0            // InvokeDynamic #1:apply:(Lorg/scalatest/tools/FilterReporter;)Lscala/Function1;
       646: invokeinterface #82,  2           // InterfaceMethod scala/collection/immutable/IndexedSeq.filter:(Lscala/Function1;)Ljava/lang/Object;
       651: checkcast     #78                 // class scala/collection/immutable/IndexedSeq
       654: astore        35
       656: aload         34
       658: invokevirtual #182                // Method org/scalatest/events/TestSucceeded.copy$default$1:()Lorg/scalatest/events/Ordinal;
       661: astore        36
       663: aload         34
       665: invokevirtual #183                // Method org/scalatest/events/TestSucceeded.copy$default$2:()Ljava/lang/String;
       668: astore        37
       670: aload         34
       672: invokevirtual #184                // Method org/scalatest/events/TestSucceeded.copy$default$3:()Ljava/lang/String;
       675: astore        38
       677: aload         34
       679: invokevirtual #186                // Method org/scalatest/events/TestSucceeded.copy$default$4:()Lscala/Option;
       682: astore        39
       684: aload         34
       686: invokevirtual #188                // Method org/scalatest/events/TestSucceeded.copy$default$5:()Ljava/lang/String;
       689: astore        40
       691: aload         34
       693: invokevirtual #189                // Method org/scalatest/events/TestSucceeded.copy$default$6:()Ljava/lang/String;
       696: astore        41
       698: aload         34
       700: invokevirtual #192                // Method org/scalatest/events/TestSucceeded.copy$default$8:()Lscala/Option;
       703: astore        42
       705: aload         34
       707: invokevirtual #194                // Method org/scalatest/events/TestSucceeded.copy$default$9:()Lscala/Option;
       710: astore        43
       712: aload         34
       714: invokevirtual #195                // Method org/scalatest/events/TestSucceeded.copy$default$10:()Lscala/Option;
       717: astore        44
       719: aload         34
       721: invokevirtual #196                // Method org/scalatest/events/TestSucceeded.copy$default$11:()Lscala/Option;
       724: astore        45
       726: aload         34
       728: invokevirtual #197                // Method org/scalatest/events/TestSucceeded.copy$default$12:()Lscala/Option;
       731: astore        46
       733: aload         34
       735: invokevirtual #199                // Method org/scalatest/events/TestSucceeded.copy$default$13:()Ljava/lang/String;
       738: astore        47
       740: aload         34
       742: invokevirtual #201                // Method org/scalatest/events/TestSucceeded.copy$default$14:()J
       745: lstore        48
       747: aload         34
       749: aload         36
       751: aload         37
       753: aload         38
       755: aload         39
       757: aload         40
       759: aload         41
       761: aload         35
       763: aload         42
       765: aload         43
       767: aload         44
       769: aload         45
       771: aload         46
       773: aload         47
       775: lload         48
       777: invokevirtual #204                // Method org/scalatest/events/TestSucceeded.copy:(Lorg/scalatest/events/Ordinal;Ljava/lang/String;Ljava/lang/String;Lscala/Option;Ljava/lang/String;Ljava/lang/String;Lscala/collection/immutable/IndexedSeq;Lscala/Option;Lscala/Option;Lscala/Option;Lscala/Option;Lscala/Option;Ljava/lang/String;J)Lorg/scalatest/events/TestSucceeded;
       780: invokeinterface #31,  2           // InterfaceMethod org/scalatest/Reporter.apply:(Lorg/scalatest/events/Event;)V
       785: getstatic     #37                 // Field scala/runtime/BoxedUnit.UNIT:Lscala/runtime/BoxedUnit;
       788: goto          794
       791: getstatic     #37                 // Field scala/runtime/BoxedUnit.UNIT:Lscala/runtime/BoxedUnit;
       794: astore_2
       795: goto          1646
       798: goto          801
       801: aload         4
       803: instanceof    #206                // class org/scalatest/events/TestIgnored
       806: ifeq          852
       809: aload         4
       811: checkcast     #206                // class org/scalatest/events/TestIgnored
       814: astore        50
       816: aload_0
       817: getfield      #142                // Field configSet:Lscala/collection/immutable/Set;
       820: getstatic     #211                // Field org/scalatest/tools/FilterTestIgnored$.MODULE$:Lorg/scalatest/tools/FilterTestIgnored$;
       823: invokeinterface #154,  2          // InterfaceMethod scala/collection/immutable/Set.contains:(Ljava/lang/Object;)Z
       828: ifne          845
       831: aload_3
       832: aload         50
       834: invokeinterface #31,  2           // InterfaceMethod org/scalatest/Reporter.apply:(Lorg/scalatest/events/Event;)V
       839: getstatic     #37                 // Field scala/runtime/BoxedUnit.UNIT:Lscala/runtime/BoxedUnit;
       842: goto          848
       845: getstatic     #37                 // Field scala/runtime/BoxedUnit.UNIT:Lscala/runtime/BoxedUnit;
       848: astore_2
       849: goto          1646
       852: goto          855
       855: aload         4
       857: instanceof    #213                // class org/scalatest/events/TestCanceled
       860: ifeq          1067
       863: aload         4
       865: checkcast     #213                // class org/scalatest/events/TestCanceled
       868: astore        51
       870: aload_0
       871: getfield      #142                // Field configSet:Lscala/collection/immutable/Set;
       874: getstatic     #218                // Field org/scalatest/tools/FilterTestCanceled$.MODULE$:Lorg/scalatest/tools/FilterTestCanceled$;
       877: invokeinterface #154,  2          // InterfaceMethod scala/collection/immutable/Set.contains:(Ljava/lang/Object;)Z
       882: ifne          1060
       885: aload_3
       886: aload         51
       888: invokevirtual #219                // Method org/scalatest/events/TestCanceled.recordedEvents:()Lscala/collection/immutable/IndexedSeq;
       891: aload_0
       892: invokedynamic #224,  0            // InvokeDynamic #2:apply:(Lorg/scalatest/tools/FilterReporter;)Lscala/Function1;
       897: invokeinterface #82,  2           // InterfaceMethod scala/collection/immutable/IndexedSeq.filter:(Lscala/Function1;)Ljava/lang/Object;
       902: checkcast     #78                 // class scala/collection/immutable/IndexedSeq
       905: astore        52
       907: aload         51
       909: invokevirtual #225                // Method org/scalatest/events/TestCanceled.copy$default$1:()Lorg/scalatest/events/Ordinal;
       912: astore        53
       914: aload         51
       916: invokevirtual #226                // Method org/scalatest/events/TestCanceled.copy$default$2:()Ljava/lang/String;
       919: astore        54
       921: aload         51
       923: invokevirtual #227                // Method org/scalatest/events/TestCanceled.copy$default$3:()Ljava/lang/String;
       926: astore        55
       928: aload         51
       930: invokevirtual #228                // Method org/scalatest/events/TestCanceled.copy$default$4:()Ljava/lang/String;
       933: astore        56
       935: aload         51
       937: invokevirtual #229                // Method org/scalatest/events/TestCanceled.copy$default$5:()Lscala/Option;
       940: astore        57
       942: aload         51
       944: invokevirtual #230                // Method org/scalatest/events/TestCanceled.copy$default$6:()Ljava/lang/String;
       947: astore        58
       949: aload         51
       951: invokevirtual #231                // Method org/scalatest/events/TestCanceled.copy$default$7:()Ljava/lang/String;
       954: astore        59
       956: aload         51
       958: invokevirtual #232                // Method org/scalatest/events/TestCanceled.copy$default$9:()Lscala/Option;
       961: astore        60
       963: aload         51
       965: invokevirtual #233                // Method org/scalatest/events/TestCanceled.copy$default$10:()Lscala/Option;
       968: astore        61
       970: aload         51
       972: invokevirtual #234                // Method org/scalatest/events/TestCanceled.copy$default$11:()Lscala/Option;
       975: astore        62
       977: aload         51
       979: invokevirtual #235                // Method org/scalatest/events/TestCanceled.copy$default$12:()Lscala/Option;
       982: astore        63
       984: aload         51
       986: invokevirtual #236                // Method org/scalatest/events/TestCanceled.copy$default$13:()Lscala/Option;
       989: astore        64
       991: aload         51
       993: invokevirtual #237                // Method org/scalatest/events/TestCanceled.copy$default$14:()Lscala/Option;
       996: astore        65
       998: aload         51
      1000: invokevirtual #239                // Method org/scalatest/events/TestCanceled.copy$default$15:()Ljava/lang/String;
      1003: astore        66
      1005: aload         51
      1007: invokevirtual #241                // Method org/scalatest/events/TestCanceled.copy$default$16:()J
      1010: lstore        67
      1012: aload         51
      1014: aload         53
      1016: aload         54
      1018: aload         55
      1020: aload         56
      1022: aload         57
      1024: aload         58
      1026: aload         59
      1028: aload         52
      1030: aload         60
      1032: aload         61
      1034: aload         62
      1036: aload         63
      1038: aload         64
      1040: aload         65
      1042: aload         66
      1044: lload         67
      1046: invokevirtual #244                // Method org/scalatest/events/TestCanceled.copy:(Lorg/scalatest/events/Ordinal;Ljava/lang/String;Ljava/lang/String;Ljava/lang/String;Lscala/Option;Ljava/lang/String;Ljava/lang/String;Lscala/collection/immutable/IndexedSeq;Lscala/Option;Lscala/Option;Lscala/Option;Lscala/Option;Lscala/Option;Lscala/Option;Ljava/lang/String;J)Lorg/scalatest/events/TestCanceled;
      1049: invokeinterface #31,  2           // InterfaceMethod org/scalatest/Reporter.apply:(Lorg/scalatest/events/Event;)V
      1054: getstatic     #37                 // Field scala/runtime/BoxedUnit.UNIT:Lscala/runtime/BoxedUnit;
      1057: goto          1063
      1060: getstatic     #37                 // Field scala/runtime/BoxedUnit.UNIT:Lscala/runtime/BoxedUnit;
      1063: astore_2
      1064: goto          1646
      1067: goto          1070
      1070: aload         4
      1072: instanceof    #246                // class org/scalatest/events/TestPending
      1075: ifeq          1255
      1078: aload         4
      1080: checkcast     #246                // class org/scalatest/events/TestPending
      1083: astore        69
      1085: aload_0
      1086: getfield      #142                // Field configSet:Lscala/collection/immutable/Set;
      1089: getstatic     #251                // Field org/scalatest/tools/FilterTestPending$.MODULE$:Lorg/scalatest/tools/FilterTestPending$;
      1092: invokeinterface #154,  2          // InterfaceMethod scala/collection/immutable/Set.contains:(Ljava/lang/Object;)Z
      1097: ifne          1248
      1100: aload_3
      1101: aload         69
      1103: invokevirtual #252                // Method org/scalatest/events/TestPending.recordedEvents:()Lscala/collection/immutable/IndexedSeq;
      1106: aload_0
      1107: invokedynamic #257,  0            // InvokeDynamic #3:apply:(Lorg/scalatest/tools/FilterReporter;)Lscala/Function1;
      1112: invokeinterface #82,  2           // InterfaceMethod scala/collection/immutable/IndexedSeq.filter:(Lscala/Function1;)Ljava/lang/Object;
      1117: checkcast     #78                 // class scala/collection/immutable/IndexedSeq
      1120: astore        70
      1122: aload         69
      1124: invokevirtual #258                // Method org/scalatest/events/TestPending.copy$default$1:()Lorg/scalatest/events/Ordinal;
      1127: astore        71
      1129: aload         69
      1131: invokevirtual #259                // Method org/scalatest/events/TestPending.copy$default$2:()Ljava/lang/String;
      1134: astore        72
      1136: aload         69
      1138: invokevirtual #260                // Method org/scalatest/events/TestPending.copy$default$3:()Ljava/lang/String;
      1141: astore        73
      1143: aload         69
      1145: invokevirtual #261                // Method org/scalatest/events/TestPending.copy$default$4:()Lscala/Option;
      1148: astore        74
      1150: aload         69
      1152: invokevirtual #262                // Method org/scalatest/events/TestPending.copy$default$5:()Ljava/lang/String;
      1155: astore        75
      1157: aload         69
      1159: invokevirtual #263                // Method org/scalatest/events/TestPending.copy$default$6:()Ljava/lang/String;
      1162: astore        76
      1164: aload         69
      1166: invokevirtual #264                // Method org/scalatest/events/TestPending.copy$default$8:()Lscala/Option;
      1169: astore        77
      1171: aload         69
      1173: invokevirtual #265                // Method org/scalatest/events/TestPending.copy$default$9:()Lscala/Option;
      1176: astore        78
      1178: aload         69
      1180: invokevirtual #266                // Method org/scalatest/events/TestPending.copy$default$10:()Lscala/Option;
      1183: astore        79
      1185: aload         69
      1187: invokevirtual #267                // Method org/scalatest/events/TestPending.copy$default$11:()Lscala/Option;
      1190: astore        80
      1192: aload         69
      1194: invokevirtual #269                // Method org/scalatest/events/TestPending.copy$default$12:()Ljava/lang/String;
      1197: astore        81
      1199: aload         69
      1201: invokevirtual #271                // Method org/scalatest/events/TestPending.copy$default$13:()J
      1204: lstore        82
      1206: aload         69
      1208: aload         71
      1210: aload         72
      1212: aload         73
      1214: aload         74
      1216: aload         75
      1218: aload         76
      1220: aload         70
      1222: aload         77
      1224: aload         78
      1226: aload         79
      1228: aload         80
      1230: aload         81
      1232: lload         82
      1234: invokevirtual #274                // Method org/scalatest/events/TestPending.copy:(Lorg/scalatest/events/Ordinal;Ljava/lang/String;Ljava/lang/String;Lscala/Option;Ljava/lang/String;Ljava/lang/String;Lscala/collection/immutable/IndexedSeq;Lscala/Option;Lscala/Option;Lscala/Option;Lscala/Option;Ljava/lang/String;J)Lorg/scalatest/events/TestPending;
      1237: invokeinterface #31,  2           // InterfaceMethod org/scalatest/Reporter.apply:(Lorg/scalatest/events/Event;)V
      1242: getstatic     #37                 // Field scala/runtime/BoxedUnit.UNIT:Lscala/runtime/BoxedUnit;
      1245: goto          1251
      1248: getstatic     #37                 // Field scala/runtime/BoxedUnit.UNIT:Lscala/runtime/BoxedUnit;
      1251: astore_2
      1252: goto          1646
      1255: goto          1258
      1258: aload         4
      1260: instanceof    #276                // class org/scalatest/events/InfoProvided
      1263: ifeq          1309
      1266: aload         4
      1268: checkcast     #276                // class org/scalatest/events/InfoProvided
      1271: astore        84
      1273: aload_0
      1274: getfield      #142                // Field configSet:Lscala/collection/immutable/Set;
      1277: getstatic     #281                // Field org/scalatest/tools/FilterInfoProvided$.MODULE$:Lorg/scalatest/tools/FilterInfoProvided$;
      1280: invokeinterface #154,  2          // InterfaceMethod scala/collection/immutable/Set.contains:(Ljava/lang/Object;)Z
      1285: ifne          1302
      1288: aload_3
      1289: aload         84
      1291: invokeinterface #31,  2           // InterfaceMethod org/scalatest/Reporter.apply:(Lorg/scalatest/events/Event;)V
      1296: getstatic     #37                 // Field scala/runtime/BoxedUnit.UNIT:Lscala/runtime/BoxedUnit;
      1299: goto          1305
      1302: getstatic     #37                 // Field scala/runtime/BoxedUnit.UNIT:Lscala/runtime/BoxedUnit;
      1305: astore_2
      1306: goto          1646
      1309: goto          1312
      1312: aload         4
      1314: instanceof    #283                // class org/scalatest/events/AlertProvided
      1317: ifeq          1363
      1320: aload         4
      1322: checkcast     #283                // class org/scalatest/events/AlertProvided
      1325: astore        85
      1327: aload_0
      1328: getfield      #142                // Field configSet:Lscala/collection/immutable/Set;
      1331: getstatic     #288                // Field org/scalatest/tools/FilterAlertProvided$.MODULE$:Lorg/scalatest/tools/FilterAlertProvided$;
      1334: invokeinterface #154,  2          // InterfaceMethod scala/collection/immutable/Set.contains:(Ljava/lang/Object;)Z
      1339: ifne          1356
      1342: aload_3
      1343: aload         85
      1345: invokeinterface #31,  2           // InterfaceMethod org/scalatest/Reporter.apply:(Lorg/scalatest/events/Event;)V
      1350: getstatic     #37                 // Field scala/runtime/BoxedUnit.UNIT:Lscala/runtime/BoxedUnit;
      1353: goto          1359
      1356: getstatic     #37                 // Field scala/runtime/BoxedUnit.UNIT:Lscala/runtime/BoxedUnit;
      1359: astore_2
      1360: goto          1646
      1363: goto          1366
      1366: aload         4
      1368: instanceof    #290                // class org/scalatest/events/NoteProvided
      1371: ifeq          1417
      1374: aload         4
      1376: checkcast     #290                // class org/scalatest/events/NoteProvided
      1379: astore        86
      1381: aload_0
      1382: getfield      #142                // Field configSet:Lscala/collection/immutable/Set;
      1385: getstatic     #295                // Field org/scalatest/tools/FilterNoteProvided$.MODULE$:Lorg/scalatest/tools/FilterNoteProvided$;
      1388: invokeinterface #154,  2          // InterfaceMethod scala/collection/immutable/Set.contains:(Ljava/lang/Object;)Z
      1393: ifne          1410
      1396: aload_3
      1397: aload         86
      1399: invokeinterface #31,  2           // InterfaceMethod org/scalatest/Reporter.apply:(Lorg/scalatest/events/Event;)V
      1404: getstatic     #37                 // Field scala/runtime/BoxedUnit.UNIT:Lscala/runtime/BoxedUnit;
      1407: goto          1413
      1410: getstatic     #37                 // Field scala/runtime/BoxedUnit.UNIT:Lscala/runtime/BoxedUnit;
      1413: astore_2
      1414: goto          1646
      1417: goto          1420
      1420: aload         4
      1422: instanceof    #297                // class org/scalatest/events/ScopeOpened
      1425: ifeq          1471
      1428: aload         4
      1430: checkcast     #297                // class org/scalatest/events/ScopeOpened
      1433: astore        87
      1435: aload_0
      1436: getfield      #142                // Field configSet:Lscala/collection/immutable/Set;
      1439: getstatic     #302                // Field org/scalatest/tools/FilterScopeOpened$.MODULE$:Lorg/scalatest/tools/FilterScopeOpened$;
      1442: invokeinterface #154,  2          // InterfaceMethod scala/collection/immutable/Set.contains:(Ljava/lang/Object;)Z
      1447: ifne          1464
      1450: aload_3
      1451: aload         87
      1453: invokeinterface #31,  2           // InterfaceMethod org/scalatest/Reporter.apply:(Lorg/scalatest/events/Event;)V
      1458: getstatic     #37                 // Field scala/runtime/BoxedUnit.UNIT:Lscala/runtime/BoxedUnit;
      1461: goto          1467
      1464: getstatic     #37                 // Field scala/runtime/BoxedUnit.UNIT:Lscala/runtime/BoxedUnit;
      1467: astore_2
      1468: goto          1646
      1471: goto          1474
      1474: aload         4
      1476: instanceof    #304                // class org/scalatest/events/ScopeClosed
      1479: ifeq          1525
      1482: aload         4
      1484: checkcast     #304                // class org/scalatest/events/ScopeClosed
      1487: astore        88
      1489: aload_0
      1490: getfield      #142                // Field configSet:Lscala/collection/immutable/Set;
      1493: getstatic     #309                // Field org/scalatest/tools/FilterScopeClosed$.MODULE$:Lorg/scalatest/tools/FilterScopeClosed$;
      1496: invokeinterface #154,  2          // InterfaceMethod scala/collection/immutable/Set.contains:(Ljava/lang/Object;)Z
      1501: ifne          1518
      1504: aload_3
      1505: aload         88
      1507: invokeinterface #31,  2           // InterfaceMethod org/scalatest/Reporter.apply:(Lorg/scalatest/events/Event;)V
      1512: getstatic     #37                 // Field scala/runtime/BoxedUnit.UNIT:Lscala/runtime/BoxedUnit;
      1515: goto          1521
      1518: getstatic     #37                 // Field scala/runtime/BoxedUnit.UNIT:Lscala/runtime/BoxedUnit;
      1521: astore_2
      1522: goto          1646
      1525: goto          1528
      1528: aload         4
      1530: instanceof    #311                // class org/scalatest/events/ScopePending
      1533: ifeq          1579
      1536: aload         4
      1538: checkcast     #311                // class org/scalatest/events/ScopePending
      1541: astore        89
      1543: aload_0
      1544: getfield      #142                // Field configSet:Lscala/collection/immutable/Set;
      1547: getstatic     #316                // Field org/scalatest/tools/FilterScopePending$.MODULE$:Lorg/scalatest/tools/FilterScopePending$;
      1550: invokeinterface #154,  2          // InterfaceMethod scala/collection/immutable/Set.contains:(Ljava/lang/Object;)Z
      1555: ifne          1572
      1558: aload_3
      1559: aload         89
      1561: invokeinterface #31,  2           // InterfaceMethod org/scalatest/Reporter.apply:(Lorg/scalatest/events/Event;)V
      1566: getstatic     #37                 // Field scala/runtime/BoxedUnit.UNIT:Lscala/runtime/BoxedUnit;
      1569: goto          1575
      1572: getstatic     #37                 // Field scala/runtime/BoxedUnit.UNIT:Lscala/runtime/BoxedUnit;
      1575: astore_2
      1576: goto          1646
      1579: goto          1582
      1582: aload         4
      1584: instanceof    #318                // class org/scalatest/events/MarkupProvided
      1587: ifeq          1633
      1590: aload         4
      1592: checkcast     #318                // class org/scalatest/events/MarkupProvided
      1595: astore        90
      1597: aload_0
      1598: getfield      #142                // Field configSet:Lscala/collection/immutable/Set;
      1601: getstatic     #323                // Field org/scalatest/tools/FilterMarkupProvided$.MODULE$:Lorg/scalatest/tools/FilterMarkupProvided$;
      1604: invokeinterface #154,  2          // InterfaceMethod scala/collection/immutable/Set.contains:(Ljava/lang/Object;)Z
      1609: ifne          1626
      1612: aload_3
      1613: aload         90
      1615: invokeinterface #31,  2           // InterfaceMethod org/scalatest/Reporter.apply:(Lorg/scalatest/events/Event;)V
      1620: getstatic     #37                 // Field scala/runtime/BoxedUnit.UNIT:Lscala/runtime/BoxedUnit;
      1623: goto          1629
      1626: getstatic     #37                 // Field scala/runtime/BoxedUnit.UNIT:Lscala/runtime/BoxedUnit;
      1629: astore_2
      1630: goto          1646
      1633: goto          1636
      1636: new           #325                // class scala/MatchError
      1639: dup
      1640: aload         4
      1642: invokespecial #329                // Method scala/MatchError."<init>":(Ljava/lang/Object;)V
      1645: athrow
      1646: return
      StackMapTable: number_of_entries = 73
        frame_type = 254 /* append */
          offset_delta = 38
          locals = [ top, class org/scalatest/Reporter, class org/scalatest/events/Event ]
        frame_type = 2 /* same */
        frame_type = 29 /* same */
        frame_type = 2 /* same */
        frame_type = 29 /* same */
        frame_type = 2 /* same */
        frame_type = 29 /* same */
        frame_type = 2 /* same */
        frame_type = 29 /* same */
        frame_type = 2 /* same */
        frame_type = 29 /* same */
        frame_type = 2 /* same */
        frame_type = 29 /* same */
        frame_type = 2 /* same */
        frame_type = 251 /* same_frame_extended */
          offset_delta = 199
        frame_type = 2 /* same */
        frame_type = 255 /* full_frame */
          offset_delta = 43
          locals = [ class org/scalatest/tools/FilterReporter, class org/scalatest/events/Event, top, class org/scalatest/Reporter, class org/scalatest/events/Event, top, top, top, top, top, top, top, top, top, top, top, top, top, top, top, top, top, top, top, top, top, top, top, top, top, top, class org/scalatest/events/SuiteCompleted ]
          stack = []
        frame_type = 66 /* same_locals_1_stack_item */
          stack = [ class scala/runtime/BoxedUnit ]
        frame_type = 255 /* full_frame */
          offset_delta = 3
          locals = [ class org/scalatest/tools/FilterReporter, class org/scalatest/events/Event, top, class org/scalatest/Reporter, class org/scalatest/events/Event ]
          stack = []
        frame_type = 2 /* same */
        frame_type = 255 /* full_frame */
          offset_delta = 43
          locals = [ class org/scalatest/tools/FilterReporter, class org/scalatest/events/Event, top, class org/scalatest/Reporter, class org/scalatest/events/Event, top, top, top, top, top, top, top, top, top, top, top, top, top, top, top, top, top, top, top, top, top, top, top, top, top, top, top, class org/scalatest/events/SuiteStarting ]
          stack = []
        frame_type = 66 /* same_locals_1_stack_item */
          stack = [ class scala/runtime/BoxedUnit ]
        frame_type = 255 /* full_frame */
          offset_delta = 3
          locals = [ class org/scalatest/tools/FilterReporter, class org/scalatest/events/Event, top, class org/scalatest/Reporter, class org/scalatest/events/Event ]
          stack = []
        frame_type = 2 /* same */
        frame_type = 255 /* full_frame */
          offset_delta = 43
          locals = [ class org/scalatest/tools/FilterReporter, class org/scalatest/events/Event, top, class org/scalatest/Reporter, class org/scalatest/events/Event, top, top, top, top, top, top, top, top, top, top, top, top, top, top, top, top, top, top, top, top, top, top, top, top, top, top, top, top, class org/scalatest/events/TestStarting ]
          stack = []
        frame_type = 66 /* same_locals_1_stack_item */
          stack = [ class scala/runtime/BoxedUnit ]
        frame_type = 255 /* full_frame */
          offset_delta = 3
          locals = [ class org/scalatest/tools/FilterReporter, class org/scalatest/events/Event, top, class org/scalatest/Reporter, class org/scalatest/events/Event ]
          stack = []
        frame_type = 2 /* same */
        frame_type = 255 /* full_frame */
          offset_delta = 186
          locals = [ class org/scalatest/tools/FilterReporter, class org/scalatest/events/Event, top, class org/scalatest/Reporter, class org/scalatest/events/Event, top, top, top, top, top, top, top, top, top, top, top, top, top, top, top, top, top, top, top, top, top, top, top, top, top, top, top, top, top, class org/scalatest/events/TestSucceeded ]
          stack = []
        frame_type = 66 /* same_locals_1_stack_item */
          stack = [ class scala/runtime/BoxedUnit ]
        frame_type = 255 /* full_frame */
          offset_delta = 3
          locals = [ class org/scalatest/tools/FilterReporter, class org/scalatest/events/Event, top, class org/scalatest/Reporter, class org/scalatest/events/Event ]
          stack = []
        frame_type = 2 /* same */
        frame_type = 255 /* full_frame */
          offset_delta = 43
          locals = [ class org/scalatest/tools/FilterReporter, class org/scalatest/events/Event, top, class org/scalatest/Reporter, class org/scalatest/events/Event, top, top, top, top, top, top, top, top, top, top, top, top, top, top, top, top, top, top, top, top, top, top, top, top, top, top, top, top, top, top, top, top, top, top, top, top, top, top, top, top, top, top, top, top, top, class org/scalatest/events/TestIgnored ]
          stack = []
        frame_type = 66 /* same_locals_1_stack_item */
          stack = [ class scala/runtime/BoxedUnit ]
        frame_type = 255 /* full_frame */
          offset_delta = 3
          locals = [ class org/scalatest/tools/FilterReporter, class org/scalatest/events/Event, top, class org/scalatest/Reporter, class org/scalatest/events/Event ]
          stack = []
        frame_type = 2 /* same */
        frame_type = 255 /* full_frame */
          offset_delta = 204
          locals = [ class org/scalatest/tools/FilterReporter, class org/scalatest/events/Event, top, class org/scalatest/Reporter, class org/scalatest/events/Event, top, top, top, top, top, top, top, top, top, top, top, top, top, top, top, top, top, top, top, top, top, top, top, top, top, top, top, top, top, top, top, top, top, top, top, top, top, top, top, top, top, top, top, top, top, top, class org/scalatest/events/TestCanceled ]
          stack = []
        frame_type = 66 /* same_locals_1_stack_item */
          stack = [ class scala/runtime/BoxedUnit ]
        frame_type = 255 /* full_frame */
          offset_delta = 3
          locals = [ class org/scalatest/tools/FilterReporter, class org/scalatest/events/Event, top, class org/scalatest/Reporter, class org/scalatest/events/Event ]
          stack = []
        frame_type = 2 /* same */
        frame_type = 255 /* full_frame */
          offset_delta = 177
          locals = [ class org/scalatest/tools/FilterReporter, class org/scalatest/events/Event, top, class org/scalatest/Reporter, class org/scalatest/events/Event, top, top, top, top, top, top, top, top, top, top, top, top, top, top, top, top, top, top, top, top, top, top, top, top, top, top, top, top, top, top, top, top, top, top, top, top, top, top, top, top, top, top, top, top, top, top, top, top, top, top, top, top, top, top, top, top, top, top, top, top, top, top, top, top, class org/scalatest/events/TestPending ]
          stack = []
        frame_type = 66 /* same_locals_1_stack_item */
          stack = [ class scala/runtime/BoxedUnit ]
        frame_type = 255 /* full_frame */
          offset_delta = 3
          locals = [ class org/scalatest/tools/FilterReporter, class org/scalatest/events/Event, top, class org/scalatest/Reporter, class org/scalatest/events/Event ]
          stack = []
        frame_type = 2 /* same */
        frame_type = 255 /* full_frame */
          offset_delta = 43
          locals = [ class org/scalatest/tools/FilterReporter, class org/scalatest/events/Event, top, class org/scalatest/Reporter, class org/scalatest/events/Event, top, top, top, top, top, top, top, top, top, top, top, top, top, top, top, top, top, top, top, top, top, top, top, top, top, top, top, top, top, top, top, top, top, top, top, top, top, top, top, top, top, top, top, top, top, top, top, top, top, top, top, top, top, top, top, top, top, top, top, top, top, top, top, top, top, top, top, top, top, top, top, top, top, top, top, top, top, top, top, class org/scalatest/events/InfoProvided ]
          stack = []
        frame_type = 66 /* same_locals_1_stack_item */
          stack = [ class scala/runtime/BoxedUnit ]
        frame_type = 255 /* full_frame */
          offset_delta = 3
          locals = [ class org/scalatest/tools/FilterReporter, class org/scalatest/events/Event, top, class org/scalatest/Reporter, class org/scalatest/events/Event ]
          stack = []
        frame_type = 2 /* same */
        frame_type = 255 /* full_frame */
          offset_delta = 43
          locals = [ class org/scalatest/tools/FilterReporter, class org/scalatest/events/Event, top, class org/scalatest/Reporter, class org/scalatest/events/Event, top, top, top, top, top, top, top, top, top, top, top, top, top, top, top, top, top, top, top, top, top, top, top, top, top, top, top, top, top, top, top, top, top, top, top, top, top, top, top, top, top, top, top, top, top, top, top, top, top, top, top, top, top, top, top, top, top, top, top, top, top, top, top, top, top, top, top, top, top, top, top, top, top, top, top, top, top, top, top, top, class org/scalatest/events/AlertProvided ]
          stack = []
        frame_type = 66 /* same_locals_1_stack_item */
          stack = [ class scala/runtime/BoxedUnit ]
        frame_type = 255 /* full_frame */
          offset_delta = 3
          locals = [ class org/scalatest/tools/FilterReporter, class org/scalatest/events/Event, top, class org/scalatest/Reporter, class org/scalatest/events/Event ]
          stack = []
        frame_type = 2 /* same */
        frame_type = 255 /* full_frame */
          offset_delta = 43
          locals = [ class org/scalatest/tools/FilterReporter, class org/scalatest/events/Event, top, class org/scalatest/Reporter, class org/scalatest/events/Event, top, top, top, top, top, top, top, top, top, top, top, top, top, top, top, top, top, top, top, top, top, top, top, top, top, top, top, top, top, top, top, top, top, top, top, top, top, top, top, top, top, top, top, top, top, top, top, top, top, top, top, top, top, top, top, top, top, top, top, top, top, top, top, top, top, top, top, top, top, top, top, top, top, top, top, top, top, top, top, top, top, class org/scalatest/events/NoteProvided ]
          stack = []
        frame_type = 66 /* same_locals_1_stack_item */
          stack = [ class scala/runtime/BoxedUnit ]
        frame_type = 255 /* full_frame */
          offset_delta = 3
          locals = [ class org/scalatest/tools/FilterReporter, class org/scalatest/events/Event, top, class org/scalatest/Reporter, class org/scalatest/events/Event ]
          stack = []
        frame_type = 2 /* same */
        frame_type = 255 /* full_frame */
          offset_delta = 43
          locals = [ class org/scalatest/tools/FilterReporter, class org/scalatest/events/Event, top, class org/scalatest/Reporter, class org/scalatest/events/Event, top, top, top, top, top, top, top, top, top, top, top, top, top, top, top, top, top, top, top, top, top, top, top, top, top, top, top, top, top, top, top, top, top, top, top, top, top, top, top, top, top, top, top, top, top, top, top, top, top, top, top, top, top, top, top, top, top, top, top, top, top, top, top, top, top, top, top, top, top, top, top, top, top, top, top, top, top, top, top, top, top, top, class org/scalatest/events/ScopeOpened ]
          stack = []
        frame_type = 66 /* same_locals_1_stack_item */
          stack = [ class scala/runtime/BoxedUnit ]
        frame_type = 255 /* full_frame */
          offset_delta = 3
          locals = [ class org/scalatest/tools/FilterReporter, class org/scalatest/events/Event, top, class org/scalatest/Reporter, class org/scalatest/events/Event ]
          stack = []
        frame_type = 2 /* same */
        frame_type = 255 /* full_frame */
          offset_delta = 43
          locals = [ class org/scalatest/tools/FilterReporter, class org/scalatest/events/Event, top, class org/scalatest/Reporter, class org/scalatest/events/Event, top, top, top, top, top, top, top, top, top, top, top, top, top, top, top, top, top, top, top, top, top, top, top, top, top, top, top, top, top, top, top, top, top, top, top, top, top, top, top, top, top, top, top, top, top, top, top, top, top, top, top, top, top, top, top, top, top, top, top, top, top, top, top, top, top, top, top, top, top, top, top, top, top, top, top, top, top, top, top, top, top, top, top, class org/scalatest/events/ScopeClosed ]
          stack = []
        frame_type = 66 /* same_locals_1_stack_item */
          stack = [ class scala/runtime/BoxedUnit ]
        frame_type = 255 /* full_frame */
          offset_delta = 3
          locals = [ class org/scalatest/tools/FilterReporter, class org/scalatest/events/Event, top, class org/scalatest/Reporter, class org/scalatest/events/Event ]
          stack = []
        frame_type = 2 /* same */
        frame_type = 255 /* full_frame */
          offset_delta = 43
          locals = [ class org/scalatest/tools/FilterReporter, class org/scalatest/events/Event, top, class org/scalatest/Reporter, class org/scalatest/events/Event, top, top, top, top, top, top, top, top, top, top, top, top, top, top, top, top, top, top, top, top, top, top, top, top, top, top, top, top, top, top, top, top, top, top, top, top, top, top, top, top, top, top, top, top, top, top, top, top, top, top, top, top, top, top, top, top, top, top, top, top, top, top, top, top, top, top, top, top, top, top, top, top, top, top, top, top, top, top, top, top, top, top, top, top, class org/scalatest/events/ScopePending ]
          stack = []
        frame_type = 66 /* same_locals_1_stack_item */
          stack = [ class scala/runtime/BoxedUnit ]
        frame_type = 255 /* full_frame */
          offset_delta = 3
          locals = [ class org/scalatest/tools/FilterReporter, class org/scalatest/events/Event, top, class org/scalatest/Reporter, class org/scalatest/events/Event ]
          stack = []
        frame_type = 2 /* same */
        frame_type = 255 /* full_frame */
          offset_delta = 43
          locals = [ class org/scalatest/tools/FilterReporter, class org/scalatest/events/Event, top, class org/scalatest/Reporter, class org/scalatest/events/Event, top, top, top, top, top, top, top, top, top, top, top, top, top, top, top, top, top, top, top, top, top, top, top, top, top, top, top, top, top, top, top, top, top, top, top, top, top, top, top, top, top, top, top, top, top, top, top, top, top, top, top, top, top, top, top, top, top, top, top, top, top, top, top, top, top, top, top, top, top, top, top, top, top, top, top, top, top, top, top, top, top, top, top, top, top, class org/scalatest/events/MarkupProvided ]
          stack = []
        frame_type = 66 /* same_locals_1_stack_item */
          stack = [ class scala/runtime/BoxedUnit ]
        frame_type = 255 /* full_frame */
          offset_delta = 3
          locals = [ class org/scalatest/tools/FilterReporter, class org/scalatest/events/Event, top, class org/scalatest/Reporter, class org/scalatest/events/Event ]
          stack = []
        frame_type = 2 /* same */
        frame_type = 255 /* full_frame */
          offset_delta = 9
          locals = [ class org/scalatest/tools/FilterReporter, class org/scalatest/events/Event, class scala/runtime/BoxedUnit, class org/scalatest/Reporter, class org/scalatest/events/Event ]
          stack = []
      LineNumberTable:
        line 33: 0
        line 34: 5
        line 35: 8
        line 36: 41
        line 37: 74
        line 38: 107
        line 39: 140
        line 40: 173
        line 41: 206
        line 42: 239
        line 43: 442
        line 44: 496
        line 45: 550
        line 46: 604
        line 47: 619
        line 48: 634
        line 47: 791
        line 46: 798
        line 49: 801
        line 50: 855
        line 51: 870
        line 52: 885
        line 51: 1060
        line 50: 1067
        line 53: 1070
        line 54: 1085
        line 55: 1100
        line 54: 1248
        line 53: 1255
        line 56: 1258
        line 57: 1312
        line 58: 1366
        line 59: 1420
        line 60: 1474
        line 61: 1528
        line 62: 1582
        line 34: 1636
      LocalVariableTable:
        Start  Length  Slot  Name   Signature
          276     151    13   x$1   Lscala/collection/immutable/IndexedSeq;
          283     144    14   x$2   Lorg/scalatest/events/Ordinal;
          290     137    15   x$3   Ljava/lang/String;
          297     130    16   x$4   Ljava/lang/String;
          304     123    17   x$5   Ljava/lang/String;
          311     116    18   x$6   Lscala/Option;
          318     109    19   x$7   Ljava/lang/String;
          325     102    20   x$8   Ljava/lang/String;
          332      95    21   x$9   Lscala/collection/immutable/IndexedSeq;
          339      88    22  x$10   Lscala/Option;
          346      81    23  x$11   Lscala/Option;
          353      74    24  x$12   Lscala/Option;
          360      67    25  x$13   Lscala/Option;
          367      60    26  x$14   Lscala/Option;
          374      53    27  x$15   Lscala/Option;
          381      46    28  x$16   Ljava/lang/String;
          388      39    29  x$17   J
          656     124    35  x$18   Lscala/collection/immutable/IndexedSeq;
          663     117    36  x$19   Lorg/scalatest/events/Ordinal;
          670     110    37  x$20   Ljava/lang/String;
          677     103    38  x$21   Ljava/lang/String;
          684      96    39  x$22   Lscala/Option;
          691      89    40  x$23   Ljava/lang/String;
          698      82    41  x$24   Ljava/lang/String;
          705      75    42  x$25   Lscala/Option;
          712      68    43  x$26   Lscala/Option;
          719      61    44  x$27   Lscala/Option;
          726      54    45  x$28   Lscala/Option;
          733      47    46  x$29   Lscala/Option;
          740      40    47  x$30   Ljava/lang/String;
          747      33    48  x$31   J
          907     142    52  x$32   Lscala/collection/immutable/IndexedSeq;
          914     135    53  x$33   Lorg/scalatest/events/Ordinal;
          921     128    54  x$34   Ljava/lang/String;
          928     121    55  x$35   Ljava/lang/String;
          935     114    56  x$36   Ljava/lang/String;
          942     107    57  x$37   Lscala/Option;
          949     100    58  x$38   Ljava/lang/String;
          956      93    59  x$39   Ljava/lang/String;
          963      86    60  x$40   Lscala/Option;
          970      79    61  x$41   Lscala/Option;
          977      72    62  x$42   Lscala/Option;
          984      65    63  x$43   Lscala/Option;
          991      58    64  x$44   Lscala/Option;
          998      51    65  x$45   Lscala/Option;
         1005      44    66  x$46   Ljava/lang/String;
         1012      37    67  x$47   J
         1122     115    70  x$48   Lscala/collection/immutable/IndexedSeq;
         1129     108    71  x$49   Lorg/scalatest/events/Ordinal;
         1136     101    72  x$50   Ljava/lang/String;
         1143      94    73  x$51   Ljava/lang/String;
         1150      87    74  x$52   Lscala/Option;
         1157      80    75  x$53   Ljava/lang/String;
         1164      73    76  x$54   Ljava/lang/String;
         1171      66    77  x$55   Lscala/Option;
         1178      59    78  x$56   Lscala/Option;
         1185      52    79  x$57   Lscala/Option;
         1192      45    80  x$58   Lscala/Option;
         1199      38    81  x$59   Ljava/lang/String;
         1206      31    82  x$60   J
            5    1641     3 report   Lorg/scalatest/Reporter;
            0    1647     0  this   Lorg/scalatest/tools/FilterReporter;
            0    1647     1 event   Lorg/scalatest/events/Event;
    MethodParameters:
      Name                           Flags
      event                          final

  private boolean filterInfoMarkupProvided(org.scalatest.events.Event);
    descriptor: (Lorg/scalatest/events/Event;)Z
    flags: (0x0002) ACC_PRIVATE
    Code:
      stack=2, locals=4, args_size=2
         0: aload_1
         1: astore_3
         2: aload_3
         3: instanceof    #276                // class org/scalatest/events/InfoProvided
         6: ifeq          33
         9: aload_0
        10: getfield      #142                // Field configSet:Lscala/collection/immutable/Set;
        13: getstatic     #281                // Field org/scalatest/tools/FilterInfoProvided$.MODULE$:Lorg/scalatest/tools/FilterInfoProvided$;
        16: invokeinterface #154,  2          // InterfaceMethod scala/collection/immutable/Set.contains:(Ljava/lang/Object;)Z
        21: ifne          28
        24: iconst_1
        25: goto          29
        28: iconst_0
        29: istore_2
        30: goto          75
        33: goto          36
        36: aload_3
        37: instanceof    #318                // class org/scalatest/events/MarkupProvided
        40: ifeq          67
        43: aload_0
        44: getfield      #142                // Field configSet:Lscala/collection/immutable/Set;
        47: getstatic     #323                // Field org/scalatest/tools/FilterMarkupProvided$.MODULE$:Lorg/scalatest/tools/FilterMarkupProvided$;
        50: invokeinterface #154,  2          // InterfaceMethod scala/collection/immutable/Set.contains:(Ljava/lang/Object;)Z
        55: ifne          62
        58: iconst_1
        59: goto          63
        62: iconst_0
        63: istore_2
        64: goto          75
        67: goto          70
        70: iconst_1
        71: istore_2
        72: goto          75
        75: iload_2
        76: ireturn
      StackMapTable: number_of_entries = 9
        frame_type = 253 /* append */
          offset_delta = 28
          locals = [ top, class org/scalatest/events/Event ]
        frame_type = 64 /* same_locals_1_stack_item */
          stack = [ int ]
        frame_type = 3 /* same */
        frame_type = 2 /* same */
        frame_type = 25 /* same */
        frame_type = 64 /* same_locals_1_stack_item */
          stack = [ int ]
        frame_type = 3 /* same */
        frame_type = 2 /* same */
        frame_type = 255 /* full_frame */
          offset_delta = 4
          locals = [ class org/scalatest/tools/FilterReporter, class org/scalatest/events/Event, int, class org/scalatest/events/Event ]
          stack = []
      LineNumberTable:
        line 67: 0
        line 68: 2
        line 69: 36
        line 70: 70
        line 67: 75
      LocalVariableTable:
        Start  Length  Slot  Name   Signature
            0      77     0  this   Lorg/scalatest/tools/FilterReporter;
            0      77     1 event   Lorg/scalatest/events/Event;
    MethodParameters:
      Name                           Flags
      event                          final

  public void dispose();
    descriptor: ()V
    flags: (0x0001) ACC_PUBLIC
    Code:
      stack=2, locals=1, args_size=1
         0: getstatic     #409                // Field org/scalatest/Reporter$.MODULE$:Lorg/scalatest/Reporter$;
         3: aload_0
         4: getfield      #25                 // Field reporter:Lorg/scalatest/Reporter;
         7: invokevirtual #413                // Method org/scalatest/Reporter$.propagateDispose:(Lorg/scalatest/Reporter;)V
        10: return
      LineNumberTable:
        line 74: 0
      LocalVariableTable:
        Start  Length  Slot  Name   Signature
            0      11     0  this   Lorg/scalatest/tools/FilterReporter;

  public static final boolean $anonfun$apply$1(org.scalatest.tools.FilterReporter, org.scalatest.events.RecordableEvent);
    descriptor: (Lorg/scalatest/tools/FilterReporter;Lorg/scalatest/events/RecordableEvent;)Z
    flags: (0x1019) ACC_PUBLIC, ACC_STATIC, ACC_FINAL, ACC_SYNTHETIC
    Code:
      stack=2, locals=2, args_size=2
         0: aload_0
         1: aload_1
         2: checkcast     #400                // class org/scalatest/events/Event
         5: invokespecial #418                // Method filterInfoMarkupProvided:(Lorg/scalatest/events/Event;)Z
         8: ireturn
      LineNumberTable:
        line 42: 0
      LocalVariableTable:
        Start  Length  Slot  Name   Signature
            0       9     0 $this   Lorg/scalatest/tools/FilterReporter;
            0       9     1   x$1   Lorg/scalatest/events/RecordableEvent;
    MethodParameters:
      Name                           Flags
      $this                          final synthetic
      x$1                            final

  public static final boolean $anonfun$apply$2(org.scalatest.tools.FilterReporter, org.scalatest.events.RecordableEvent);
    descriptor: (Lorg/scalatest/tools/FilterReporter;Lorg/scalatest/events/RecordableEvent;)Z
    flags: (0x1019) ACC_PUBLIC, ACC_STATIC, ACC_FINAL, ACC_SYNTHETIC
    Code:
      stack=2, locals=2, args_size=2
         0: aload_0
         1: aload_1
         2: checkcast     #400                // class org/scalatest/events/Event
         5: invokespecial #418                // Method filterInfoMarkupProvided:(Lorg/scalatest/events/Event;)Z
         8: ireturn
      LineNumberTable:
        line 48: 0
      LocalVariableTable:
        Start  Length  Slot  Name   Signature
            0       9     0 $this   Lorg/scalatest/tools/FilterReporter;
            0       9     1   x$2   Lorg/scalatest/events/RecordableEvent;
    MethodParameters:
      Name                           Flags
      $this                          final synthetic
      x$2                            final

  public static final boolean $anonfun$apply$3(org.scalatest.tools.FilterReporter, org.scalatest.events.RecordableEvent);
    descriptor: (Lorg/scalatest/tools/FilterReporter;Lorg/scalatest/events/RecordableEvent;)Z
    flags: (0x1019) ACC_PUBLIC, ACC_STATIC, ACC_FINAL, ACC_SYNTHETIC
    Code:
      stack=2, locals=2, args_size=2
         0: aload_0
         1: aload_1
         2: checkcast     #400                // class org/scalatest/events/Event
         5: invokespecial #418                // Method filterInfoMarkupProvided:(Lorg/scalatest/events/Event;)Z
         8: ireturn
      LineNumberTable:
        line 52: 0
      LocalVariableTable:
        Start  Length  Slot  Name   Signature
            0       9     0 $this   Lorg/scalatest/tools/FilterReporter;
            0       9     1   x$3   Lorg/scalatest/events/RecordableEvent;
    MethodParameters:
      Name                           Flags
      $this                          final synthetic
      x$3                            final

  public static final boolean $anonfun$apply$4(org.scalatest.tools.FilterReporter, org.scalatest.events.RecordableEvent);
    descriptor: (Lorg/scalatest/tools/FilterReporter;Lorg/scalatest/events/RecordableEvent;)Z
    flags: (0x1019) ACC_PUBLIC, ACC_STATIC, ACC_FINAL, ACC_SYNTHETIC
    Code:
      stack=2, locals=2, args_size=2
         0: aload_0
         1: aload_1
         2: checkcast     #400                // class org/scalatest/events/Event
         5: invokespecial #418                // Method filterInfoMarkupProvided:(Lorg/scalatest/events/Event;)Z
         8: ireturn
      LineNumberTable:
        line 55: 0
      LocalVariableTable:
        Start  Length  Slot  Name   Signature
            0       9     0 $this   Lorg/scalatest/tools/FilterReporter;
            0       9     1   x$4   Lorg/scalatest/events/RecordableEvent;
    MethodParameters:
      Name                           Flags
      $this                          final synthetic
      x$4                            final

  public org.scalatest.tools.FilterReporter(org.scalatest.Reporter, scala.collection.immutable.Set<org.scalatest.tools.ReporterConfigParam>);
    descriptor: (Lorg/scalatest/Reporter;Lscala/collection/immutable/Set;)V
    flags: (0x0001) ACC_PUBLIC
    Code:
      stack=2, locals=3, args_size=3
         0: aload_0
         1: aload_1
         2: putfield      #25                 // Field reporter:Lorg/scalatest/Reporter;
         5: aload_0
         6: aload_2
         7: putfield      #142                // Field configSet:Lscala/collection/immutable/Set;
        10: aload_0
        11: invokespecial #426                // Method java/lang/Object."<init>":()V
        14: return
      LineNumberTable:
        line 28: 0
      LocalVariableTable:
        Start  Length  Slot  Name   Signature
            0      15     0  this   Lorg/scalatest/tools/FilterReporter;
            0      15     1 reporter   Lorg/scalatest/Reporter;
            0      15     2 configSet   Lscala/collection/immutable/Set;
    Signature: #424                         // (Lorg/scalatest/Reporter;Lscala/collection/immutable/Set<Lorg/scalatest/tools/ReporterConfigParam;>;)V
    MethodParameters:
      Name                           Flags
      reporter                       final
      configSet                      final

  public static final java.lang.Object $anonfun$apply$1$adapted(org.scalatest.tools.FilterReporter, org.scalatest.events.RecordableEvent);
    descriptor: (Lorg/scalatest/tools/FilterReporter;Lorg/scalatest/events/RecordableEvent;)Ljava/lang/Object;
    flags: (0x1019) ACC_PUBLIC, ACC_STATIC, ACC_FINAL, ACC_SYNTHETIC
    Code:
      stack=2, locals=2, args_size=2
         0: aload_0
         1: aload_1
         2: invokestatic  #428                // Method $anonfun$apply$1:(Lorg/scalatest/tools/FilterReporter;Lorg/scalatest/events/RecordableEvent;)Z
         5: invokestatic  #434                // Method scala/runtime/BoxesRunTime.boxToBoolean:(Z)Ljava/lang/Boolean;
         8: areturn
      LineNumberTable:
        line 42: 0
      LocalVariableTable:
        Start  Length  Slot  Name   Signature
            0       9     0 $this   Lorg/scalatest/tools/FilterReporter;
            0       9     1   x$1   Lorg/scalatest/events/RecordableEvent;
    MethodParameters:
      Name                           Flags
      $this                          final
      x$1                            final

  public static final java.lang.Object $anonfun$apply$2$adapted(org.scalatest.tools.FilterReporter, org.scalatest.events.RecordableEvent);
    descriptor: (Lorg/scalatest/tools/FilterReporter;Lorg/scalatest/events/RecordableEvent;)Ljava/lang/Object;
    flags: (0x1019) ACC_PUBLIC, ACC_STATIC, ACC_FINAL, ACC_SYNTHETIC
    Code:
      stack=2, locals=2, args_size=2
         0: aload_0
         1: aload_1
         2: invokestatic  #436                // Method $anonfun$apply$2:(Lorg/scalatest/tools/FilterReporter;Lorg/scalatest/events/RecordableEvent;)Z
         5: invokestatic  #434                // Method scala/runtime/BoxesRunTime.boxToBoolean:(Z)Ljava/lang/Boolean;
         8: areturn
      LineNumberTable:
        line 48: 0
      LocalVariableTable:
        Start  Length  Slot  Name   Signature
            0       9     0 $this   Lorg/scalatest/tools/FilterReporter;
            0       9     1   x$2   Lorg/scalatest/events/RecordableEvent;
    MethodParameters:
      Name                           Flags
      $this                          final
      x$2                            final

  public static final java.lang.Object $anonfun$apply$3$adapted(org.scalatest.tools.FilterReporter, org.scalatest.events.RecordableEvent);
    descriptor: (Lorg/scalatest/tools/FilterReporter;Lorg/scalatest/events/RecordableEvent;)Ljava/lang/Object;
    flags: (0x1019) ACC_PUBLIC, ACC_STATIC, ACC_FINAL, ACC_SYNTHETIC
    Code:
      stack=2, locals=2, args_size=2
         0: aload_0
         1: aload_1
         2: invokestatic  #438                // Method $anonfun$apply$3:(Lorg/scalatest/tools/FilterReporter;Lorg/scalatest/events/RecordableEvent;)Z
         5: invokestatic  #434                // Method scala/runtime/BoxesRunTime.boxToBoolean:(Z)Ljava/lang/Boolean;
         8: areturn
      LineNumberTable:
        line 52: 0
      LocalVariableTable:
        Start  Length  Slot  Name   Signature
            0       9     0 $this   Lorg/scalatest/tools/FilterReporter;
            0       9     1   x$3   Lorg/scalatest/events/RecordableEvent;
    MethodParameters:
      Name                           Flags
      $this                          final
      x$3                            final

  public static final java.lang.Object $anonfun$apply$4$adapted(org.scalatest.tools.FilterReporter, org.scalatest.events.RecordableEvent);
    descriptor: (Lorg/scalatest/tools/FilterReporter;Lorg/scalatest/events/RecordableEvent;)Ljava/lang/Object;
    flags: (0x1019) ACC_PUBLIC, ACC_STATIC, ACC_FINAL, ACC_SYNTHETIC
    Code:
      stack=2, locals=2, args_size=2
         0: aload_0
         1: aload_1
         2: invokestatic  #440                // Method $anonfun$apply$4:(Lorg/scalatest/tools/FilterReporter;Lorg/scalatest/events/RecordableEvent;)Z
         5: invokestatic  #434                // Method scala/runtime/BoxesRunTime.boxToBoolean:(Z)Ljava/lang/Boolean;
         8: areturn
      LineNumberTable:
        line 55: 0
      LocalVariableTable:
        Start  Length  Slot  Name   Signature
            0       9     0 $this   Lorg/scalatest/tools/FilterReporter;
            0       9     1   x$4   Lorg/scalatest/events/RecordableEvent;
    MethodParameters:
      Name                           Flags
      $this                          final
      x$4                            final

  private static java.lang.Object $deserializeLambda$(java.lang.invoke.SerializedLambda);
    descriptor: (Ljava/lang/invoke/SerializedLambda;)Ljava/lang/Object;
    flags: (0x100a) ACC_PRIVATE, ACC_STATIC, ACC_SYNTHETIC
    Code:
      stack=1, locals=1, args_size=1
         0: aload_0
         1: invokedynamic #452,  0            // InvokeDynamic #4:lambdaDeserialize:(Ljava/lang/invoke/SerializedLambda;)Ljava/lang/Object;
         6: areturn
}
InnerClasses:
  public static final #15= #12 of #14;    // Lookup=class java/lang/invoke/MethodHandles$Lookup of class java/lang/invoke/MethodHandles
SourceFile: "FilterReporter.scala"
RuntimeVisibleAnnotations:
  0: #8(#9=s#10)
    scala.reflect.ScalaSignature(
      bytes="\u0006\u0005!3Qa\u0002\u0005\u0001\u00119A\u0001\"\u0007\u0001\u0003\u0002\u0003\u0006Ia\u0007\u0005\t=\u0001\u0011\t\u0011)A\u0005?!)a\u0006\u0001C\u0001_!)1\u0007\u0001C!i!)\u0001\t\u0001C\u0005\u0003\")a\t\u0001C!\u000f\nqa)\u001b7uKJ\u0014V\r]8si\u0016\u0014(BA\u0005\u000b\u0003\u0015!xn\u001c7t\u0015\tYA\"A\u0005tG\u0006d\u0017\r^3ti*\tQ\"A\u0002pe\u001e\u001c2\u0001A\b\u0016!\t\u00012#D\u0001\u0012\u0015\u0005\u0011\u0012!B:dC2\f\u0017B\u0001\u000b\u0012\u0005\u0019\te.\u001f*fMB\u0011acF\u0007\u0002\u0015%\u0011\u0001D\u0003\u0002\u0014%\u0016\u001cx.\u001e:dK\u001a,HNU3q_J$XM]\u0001\te\u0016\u0004xN\u001d;fe\u000e\u0001\u0001C\u0001\f\u001d\u0013\ti\"B\u0001\u0005SKB|\'\u000f^3s\u0003%\u0019wN\u001c4jON+G\u000fE\u0002!O)r!!I\u0013\u0011\u0005\t\nR\"A\u0012\u000b\u0005\u0011R\u0012A\u0002\u001fs_>$h(\u0003\u0002\'#\u00051\u0001K]3eK\u001aL!\u0001K\u0015\u0003\u0007M+GO\u0003\u0002\'#A\u00111\u0006L\u0007\u0002\u0011%\u0011Q\u0006\u0003\u0002\u0014%\u0016\u0004xN\u001d;fe\u000e{gNZ5h!\u0006\u0014\u0018-\\\u0001\u0007y%t\u0017\u000e\u001e \u0015\u0007A\n$\u0007\u0005\u0002,\u0001!)\u0011d\u0001a\u00017!)ad\u0001a\u0001?\u0005)\u0011\r\u001d9msR\u0011Q\u0007\u000f\t\u0003!YJ!aN\t\u0003\tUs\u0017\u000e\u001e\u0005\u0006s\u0011\u0001\rAO\u0001\u0006KZ,g\u000e\u001e\t\u0003wyj\u0011\u0001\u0010\u0006\u0003{)\ta!\u001a<f]R\u001c\u0018BA =\u0005\u0015)e/\u001a8u\u0003a1\u0017\u000e\u001c;fe&sgm\\\'be.,\b\u000f\u0015:pm&$W\r\u001a\u000b\u0003\u0005\u0016\u0003\"\u0001E\"\n\u0005\u0011\u000b\"a\u0002\"p_2,\u0017M\u001c\u0005\u0006s\u0015\u0001\rAO\u0001\bI&\u001c\bo\\:f)\u0005)\u0004"
    )
BootstrapMethods:
  0: #73 REF_invokeStatic java/lang/invoke/LambdaMetafactory.altMetafactory:(Ljava/lang/invoke/MethodHandles$Lookup;Ljava/lang/String;Ljava/lang/invoke/MethodType;[Ljava/lang/Object;)Ljava/lang/invoke/CallSite;
    Method arguments:
      #57 (Ljava/lang/Object;)Ljava/lang/Object;
      #62 REF_invokeStatic org/scalatest/tools/FilterReporter.$anonfun$apply$1$adapted:(Lorg/scalatest/tools/FilterReporter;Lorg/scalatest/events/RecordableEvent;)Ljava/lang/Object;
      #64 (Lorg/scalatest/events/RecordableEvent;)Ljava/lang/Object;
      #65 5
      #66 1
      #64 (Lorg/scalatest/events/RecordableEvent;)Ljava/lang/Object;
  1: #73 REF_invokeStatic java/lang/invoke/LambdaMetafactory.altMetafactory:(Ljava/lang/invoke/MethodHandles$Lookup;Ljava/lang/String;Ljava/lang/invoke/MethodType;[Ljava/lang/Object;)Ljava/lang/invoke/CallSite;
    Method arguments:
      #57 (Ljava/lang/Object;)Ljava/lang/Object;
      #180 REF_invokeStatic org/scalatest/tools/FilterReporter.$anonfun$apply$2$adapted:(Lorg/scalatest/tools/FilterReporter;Lorg/scalatest/events/RecordableEvent;)Ljava/lang/Object;
      #64 (Lorg/scalatest/events/RecordableEvent;)Ljava/lang/Object;
      #65 5
      #66 1
      #64 (Lorg/scalatest/events/RecordableEvent;)Ljava/lang/Object;
  2: #73 REF_invokeStatic java/lang/invoke/LambdaMetafactory.altMetafactory:(Ljava/lang/invoke/MethodHandles$Lookup;Ljava/lang/String;Ljava/lang/invoke/MethodType;[Ljava/lang/Object;)Ljava/lang/invoke/CallSite;
    Method arguments:
      #57 (Ljava/lang/Object;)Ljava/lang/Object;
      #223 REF_invokeStatic org/scalatest/tools/FilterReporter.$anonfun$apply$3$adapted:(Lorg/scalatest/tools/FilterReporter;Lorg/scalatest/events/RecordableEvent;)Ljava/lang/Object;
      #64 (Lorg/scalatest/events/RecordableEvent;)Ljava/lang/Object;
      #65 5
      #66 1
      #64 (Lorg/scalatest/events/RecordableEvent;)Ljava/lang/Object;
  3: #73 REF_invokeStatic java/lang/invoke/LambdaMetafactory.altMetafactory:(Ljava/lang/invoke/MethodHandles$Lookup;Ljava/lang/String;Ljava/lang/invoke/MethodType;[Ljava/lang/Object;)Ljava/lang/invoke/CallSite;
    Method arguments:
      #57 (Ljava/lang/Object;)Ljava/lang/Object;
      #256 REF_invokeStatic org/scalatest/tools/FilterReporter.$anonfun$apply$4$adapted:(Lorg/scalatest/tools/FilterReporter;Lorg/scalatest/events/RecordableEvent;)Ljava/lang/Object;
      #64 (Lorg/scalatest/events/RecordableEvent;)Ljava/lang/Object;
      #65 5
      #66 1
      #64 (Lorg/scalatest/events/RecordableEvent;)Ljava/lang/Object;
  4: #449 REF_invokeStatic scala/runtime/LambdaDeserialize.bootstrap:(Ljava/lang/invoke/MethodHandles$Lookup;Ljava/lang/String;Ljava/lang/invoke/MethodType;[Ljava/lang/invoke/MethodHandle;)Ljava/lang/invoke/CallSite;
    Method arguments:
      #62 REF_invokeStatic org/scalatest/tools/FilterReporter.$anonfun$apply$1$adapted:(Lorg/scalatest/tools/FilterReporter;Lorg/scalatest/events/RecordableEvent;)Ljava/lang/Object;
      #180 REF_invokeStatic org/scalatest/tools/FilterReporter.$anonfun$apply$2$adapted:(Lorg/scalatest/tools/FilterReporter;Lorg/scalatest/events/RecordableEvent;)Ljava/lang/Object;
      #223 REF_invokeStatic org/scalatest/tools/FilterReporter.$anonfun$apply$3$adapted:(Lorg/scalatest/tools/FilterReporter;Lorg/scalatest/events/RecordableEvent;)Ljava/lang/Object;
      #256 REF_invokeStatic org/scalatest/tools/FilterReporter.$anonfun$apply$4$adapted:(Lorg/scalatest/tools/FilterReporter;Lorg/scalatest/events/RecordableEvent;)Ljava/lang/Object;
  ScalaInlineInfo: length = 0x40 (unknown attribute)
   01 00 00 0C 01 9E 01 9F 01 00 3A 00 3B 01 01 A4
   01 9F 01 00 B1 00 3B 01 01 A5 01 9F 01 00 DC 00
   3B 01 01 A6 01 9F 01 00 FD 00 3B 01 01 46 01 A7
   00 00 15 00 16 00 01 93 01 94 00 01 91 01 92 01

  ScalaSig: length = 0x3 (unknown attribute)
   05 02 00
