Classfile /Users/mw/Projects/slang-braindump/.jar/jar11/assemble/slang-braindump/assemble/content/org/scalatest/tools/Framework$ScalaTestSbtEvent$.class
  Last modified May 29, 2022; size 3450 bytes
  SHA-256 checksum 69eb511870839aa078da02fdeebdaecda384a1b7d97b477f20c87ed5042ca0f1
  Compiled from "Framework.scala"
public class org.scalatest.tools.Framework$ScalaTestSbtEvent$ extends scala.runtime.AbstractFunction6<java.lang.String, sbt.testing.Fingerprint, sbt.testing.Selector, sbt.testing.Status, sbt.testing.OptionalThrowable, java.lang.Object, org.scalatest.tools.Framework$ScalaTestSbtEvent> implements java.io.Serializable
  minor version: 0
  major version: 52
  flags: (0x0021) ACC_PUBLIC, ACC_SUPER
  this_class: #2                          // org/scalatest/tools/Framework$ScalaTestSbtEvent$
  super_class: #5                         // scala/runtime/AbstractFunction6
  interfaces: 1, fields: 1, methods: 5, attributes: 5
Constant pool:
    #1 = Utf8               org/scalatest/tools/Framework$ScalaTestSbtEvent$
    #2 = Class              #1            // org/scalatest/tools/Framework$ScalaTestSbtEvent$
    #3 = Utf8               Lscala/runtime/AbstractFunction6<Ljava/lang/String;Lsbt/testing/Fingerprint;Lsbt/testing/Selector;Lsbt/testing/Status;Lsbt/testing/OptionalThrowable;Ljava/lang/Object;Lorg/scalatest/tools/Framework$ScalaTestSbtEvent;>;Ljava/io/Serializable;
    #4 = Utf8               scala/runtime/AbstractFunction6
    #5 = Class              #4            // scala/runtime/AbstractFunction6
    #6 = Utf8               java/io/Serializable
    #7 = Class              #6            // java/io/Serializable
    #8 = Utf8               Framework.scala
    #9 = Utf8               org/scalatest/tools/Framework$ScalaTestSbtEvent
   #10 = Class              #9            // org/scalatest/tools/Framework$ScalaTestSbtEvent
   #11 = Utf8               org/scalatest/tools/Framework
   #12 = Class              #11           // org/scalatest/tools/Framework
   #13 = Utf8               ScalaTestSbtEvent
   #14 = Utf8               ScalaTestSbtEvent$
   #15 = Utf8               $outer
   #16 = Utf8               Lorg/scalatest/tools/Framework;
   #17 = Utf8               toString
   #18 = Utf8               ()Ljava/lang/String;
   #19 = String             #13           // ScalaTestSbtEvent
   #20 = Utf8               this
   #21 = Utf8               Lorg/scalatest/tools/Framework$ScalaTestSbtEvent$;
   #22 = Utf8               apply
   #23 = Utf8               (Ljava/lang/String;Lsbt/testing/Fingerprint;Lsbt/testing/Selector;Lsbt/testing/Status;Lsbt/testing/OptionalThrowable;J)Lorg/scalatest/tools/Framework$ScalaTestSbtEvent;
   #24 = Utf8               fullyQualifiedName
   #25 = Utf8               fingerprint
   #26 = Utf8               selector
   #27 = Utf8               status
   #28 = Utf8               throwable
   #29 = Utf8               duration
   #30 = NameAndType        #15:#16       // $outer:Lorg/scalatest/tools/Framework;
   #31 = Fieldref           #2.#30        // org/scalatest/tools/Framework$ScalaTestSbtEvent$.$outer:Lorg/scalatest/tools/Framework;
   #32 = Utf8               <init>
   #33 = Utf8               (Lorg/scalatest/tools/Framework;Ljava/lang/String;Lsbt/testing/Fingerprint;Lsbt/testing/Selector;Lsbt/testing/Status;Lsbt/testing/OptionalThrowable;J)V
   #34 = NameAndType        #32:#33       // "<init>":(Lorg/scalatest/tools/Framework;Ljava/lang/String;Lsbt/testing/Fingerprint;Lsbt/testing/Selector;Lsbt/testing/Status;Lsbt/testing/OptionalThrowable;J)V
   #35 = Methodref          #10.#34       // org/scalatest/tools/Framework$ScalaTestSbtEvent."<init>":(Lorg/scalatest/tools/Framework;Ljava/lang/String;Lsbt/testing/Fingerprint;Lsbt/testing/Selector;Lsbt/testing/Status;Lsbt/testing/OptionalThrowable;J)V
   #36 = Utf8               Ljava/lang/String;
   #37 = Utf8               Lsbt/testing/Fingerprint;
   #38 = Utf8               Lsbt/testing/Selector;
   #39 = Utf8               Lsbt/testing/Status;
   #40 = Utf8               Lsbt/testing/OptionalThrowable;
   #41 = Utf8               J
   #42 = Utf8               unapply
   #43 = Utf8               (Lorg/scalatest/tools/Framework$ScalaTestSbtEvent;)Lscala/Option;
   #44 = Utf8               (Lorg/scalatest/tools/Framework$ScalaTestSbtEvent;)Lscala/Option<Lscala/Tuple6<Ljava/lang/String;Lsbt/testing/Fingerprint;Lsbt/testing/Selector;Lsbt/testing/Status;Lsbt/testing/OptionalThrowable;Ljava/lang/Object;>;>;
   #45 = Utf8               x$0
   #46 = Utf8               scala/None$
   #47 = Class              #46           // scala/None$
   #48 = Utf8               MODULE$
   #49 = Utf8               Lscala/None$;
   #50 = NameAndType        #48:#49       // MODULE$:Lscala/None$;
   #51 = Fieldref           #47.#50       // scala/None$.MODULE$:Lscala/None$;
   #52 = Utf8               scala/Some
   #53 = Class              #52           // scala/Some
   #54 = Utf8               scala/Tuple6
   #55 = Class              #54           // scala/Tuple6
   #56 = NameAndType        #24:#18       // fullyQualifiedName:()Ljava/lang/String;
   #57 = Methodref          #10.#56       // org/scalatest/tools/Framework$ScalaTestSbtEvent.fullyQualifiedName:()Ljava/lang/String;
   #58 = Utf8               ()Lsbt/testing/Fingerprint;
   #59 = NameAndType        #25:#58       // fingerprint:()Lsbt/testing/Fingerprint;
   #60 = Methodref          #10.#59       // org/scalatest/tools/Framework$ScalaTestSbtEvent.fingerprint:()Lsbt/testing/Fingerprint;
   #61 = Utf8               ()Lsbt/testing/Selector;
   #62 = NameAndType        #26:#61       // selector:()Lsbt/testing/Selector;
   #63 = Methodref          #10.#62       // org/scalatest/tools/Framework$ScalaTestSbtEvent.selector:()Lsbt/testing/Selector;
   #64 = Utf8               ()Lsbt/testing/Status;
   #65 = NameAndType        #27:#64       // status:()Lsbt/testing/Status;
   #66 = Methodref          #10.#65       // org/scalatest/tools/Framework$ScalaTestSbtEvent.status:()Lsbt/testing/Status;
   #67 = Utf8               ()Lsbt/testing/OptionalThrowable;
   #68 = NameAndType        #28:#67       // throwable:()Lsbt/testing/OptionalThrowable;
   #69 = Methodref          #10.#68       // org/scalatest/tools/Framework$ScalaTestSbtEvent.throwable:()Lsbt/testing/OptionalThrowable;
   #70 = Utf8               ()J
   #71 = NameAndType        #29:#70       // duration:()J
   #72 = Methodref          #10.#71       // org/scalatest/tools/Framework$ScalaTestSbtEvent.duration:()J
   #73 = Utf8               scala/runtime/BoxesRunTime
   #74 = Class              #73           // scala/runtime/BoxesRunTime
   #75 = Utf8               boxToLong
   #76 = Utf8               (J)Ljava/lang/Long;
   #77 = NameAndType        #75:#76       // boxToLong:(J)Ljava/lang/Long;
   #78 = Methodref          #74.#77       // scala/runtime/BoxesRunTime.boxToLong:(J)Ljava/lang/Long;
   #79 = Utf8               (Ljava/lang/Object;Ljava/lang/Object;Ljava/lang/Object;Ljava/lang/Object;Ljava/lang/Object;Ljava/lang/Object;)V
   #80 = NameAndType        #32:#79       // "<init>":(Ljava/lang/Object;Ljava/lang/Object;Ljava/lang/Object;Ljava/lang/Object;Ljava/lang/Object;Ljava/lang/Object;)V
   #81 = Methodref          #55.#80       // scala/Tuple6."<init>":(Ljava/lang/Object;Ljava/lang/Object;Ljava/lang/Object;Ljava/lang/Object;Ljava/lang/Object;Ljava/lang/Object;)V
   #82 = Utf8               (Ljava/lang/Object;)V
   #83 = NameAndType        #32:#82       // "<init>":(Ljava/lang/Object;)V
   #84 = Methodref          #53.#83       // scala/Some."<init>":(Ljava/lang/Object;)V
   #85 = Utf8               Lorg/scalatest/tools/Framework$ScalaTestSbtEvent;
   #86 = Utf8               scala/Option
   #87 = Class              #86           // scala/Option
   #88 = Utf8               (Ljava/lang/Object;Ljava/lang/Object;Ljava/lang/Object;Ljava/lang/Object;Ljava/lang/Object;Ljava/lang/Object;)Ljava/lang/Object;
   #89 = Utf8               v1
   #90 = Utf8               v2
   #91 = Utf8               v3
   #92 = Utf8               v4
   #93 = Utf8               v5
   #94 = Utf8               v6
   #95 = Utf8               java/lang/String
   #96 = Class              #95           // java/lang/String
   #97 = Utf8               sbt/testing/Fingerprint
   #98 = Class              #97           // sbt/testing/Fingerprint
   #99 = Utf8               sbt/testing/Selector
  #100 = Class              #99           // sbt/testing/Selector
  #101 = Utf8               sbt/testing/Status
  #102 = Class              #101          // sbt/testing/Status
  #103 = Utf8               sbt/testing/OptionalThrowable
  #104 = Class              #103          // sbt/testing/OptionalThrowable
  #105 = Utf8               unboxToLong
  #106 = Utf8               (Ljava/lang/Object;)J
  #107 = NameAndType        #105:#106     // unboxToLong:(Ljava/lang/Object;)J
  #108 = Methodref          #74.#107      // scala/runtime/BoxesRunTime.unboxToLong:(Ljava/lang/Object;)J
  #109 = NameAndType        #22:#23       // apply:(Ljava/lang/String;Lsbt/testing/Fingerprint;Lsbt/testing/Selector;Lsbt/testing/Status;Lsbt/testing/OptionalThrowable;J)Lorg/scalatest/tools/Framework$ScalaTestSbtEvent;
  #110 = Methodref          #2.#109       // org/scalatest/tools/Framework$ScalaTestSbtEvent$.apply:(Ljava/lang/String;Lsbt/testing/Fingerprint;Lsbt/testing/Selector;Lsbt/testing/Status;Lsbt/testing/OptionalThrowable;J)Lorg/scalatest/tools/Framework$ScalaTestSbtEvent;
  #111 = Utf8               Ljava/lang/Object;
  #112 = Utf8               (Lorg/scalatest/tools/Framework;)V
  #113 = Utf8               ()V
  #114 = NameAndType        #32:#113      // "<init>":()V
  #115 = Methodref          #5.#114       // scala/runtime/AbstractFunction6."<init>":()V
  #116 = Utf8               Code
  #117 = Utf8               LineNumberTable
  #118 = Utf8               LocalVariableTable
  #119 = Utf8               MethodParameters
  #120 = Utf8               StackMapTable
  #121 = Utf8               Signature
  #122 = Utf8               InnerClasses
  #123 = Utf8               SourceFile
  #124 = Utf8               ScalaInlineInfo
  #125 = Utf8               Scala
{
  private final org.scalatest.tools.Framework $outer;
    descriptor: Lorg/scalatest/tools/Framework;
    flags: (0x1012) ACC_PRIVATE, ACC_FINAL, ACC_SYNTHETIC

  public final java.lang.String toString();
    descriptor: ()Ljava/lang/String;
    flags: (0x0011) ACC_PUBLIC, ACC_FINAL
    Code:
      stack=1, locals=1, args_size=1
         0: ldc           #19                 // String ScalaTestSbtEvent
         2: areturn
      LineNumberTable:
        line 1151: 0
      LocalVariableTable:
        Start  Length  Slot  Name   Signature
            0       3     0  this   Lorg/scalatest/tools/Framework$ScalaTestSbtEvent$;

  public org.scalatest.tools.Framework$ScalaTestSbtEvent apply(java.lang.String, sbt.testing.Fingerprint, sbt.testing.Selector, sbt.testing.Status, sbt.testing.OptionalThrowable, long);
    descriptor: (Ljava/lang/String;Lsbt/testing/Fingerprint;Lsbt/testing/Selector;Lsbt/testing/Status;Lsbt/testing/OptionalThrowable;J)Lorg/scalatest/tools/Framework$ScalaTestSbtEvent;
    flags: (0x0001) ACC_PUBLIC
    Code:
      stack=10, locals=8, args_size=7
         0: new           #10                 // class org/scalatest/tools/Framework$ScalaTestSbtEvent
         3: dup
         4: aload_0
         5: getfield      #31                 // Field $outer:Lorg/scalatest/tools/Framework;
         8: aload_1
         9: aload_2
        10: aload_3
        11: aload         4
        13: aload         5
        15: lload         6
        17: invokespecial #35                 // Method org/scalatest/tools/Framework$ScalaTestSbtEvent."<init>":(Lorg/scalatest/tools/Framework;Ljava/lang/String;Lsbt/testing/Fingerprint;Lsbt/testing/Selector;Lsbt/testing/Status;Lsbt/testing/OptionalThrowable;J)V
        20: areturn
      LineNumberTable:
        line 1151: 0
      LocalVariableTable:
        Start  Length  Slot  Name   Signature
            0      21     0  this   Lorg/scalatest/tools/Framework$ScalaTestSbtEvent$;
            0      21     1 fullyQualifiedName   Ljava/lang/String;
            0      21     2 fingerprint   Lsbt/testing/Fingerprint;
            0      21     3 selector   Lsbt/testing/Selector;
            0      21     4 status   Lsbt/testing/Status;
            0      21     5 throwable   Lsbt/testing/OptionalThrowable;
            0      21     6 duration   J
    MethodParameters:
      Name                           Flags
      fullyQualifiedName             final
      fingerprint                    final
      selector                       final
      status                         final
      throwable                      final
      duration                       final

  public scala.Option<scala.Tuple6<java.lang.String, sbt.testing.Fingerprint, sbt.testing.Selector, sbt.testing.Status, sbt.testing.OptionalThrowable, java.lang.Object>> unapply(org.scalatest.tools.Framework$ScalaTestSbtEvent);
    descriptor: (Lorg/scalatest/tools/Framework$ScalaTestSbtEvent;)Lscala/Option;
    flags: (0x0001) ACC_PUBLIC
    Code:
      stack=11, locals=2, args_size=2
         0: aload_1
         1: ifnonnull     10
         4: getstatic     #51                 // Field scala/None$.MODULE$:Lscala/None$;
         7: goto          51
        10: new           #53                 // class scala/Some
        13: dup
        14: new           #55                 // class scala/Tuple6
        17: dup
        18: aload_1
        19: invokevirtual #57                 // Method org/scalatest/tools/Framework$ScalaTestSbtEvent.fullyQualifiedName:()Ljava/lang/String;
        22: aload_1
        23: invokevirtual #60                 // Method org/scalatest/tools/Framework$ScalaTestSbtEvent.fingerprint:()Lsbt/testing/Fingerprint;
        26: aload_1
        27: invokevirtual #63                 // Method org/scalatest/tools/Framework$ScalaTestSbtEvent.selector:()Lsbt/testing/Selector;
        30: aload_1
        31: invokevirtual #66                 // Method org/scalatest/tools/Framework$ScalaTestSbtEvent.status:()Lsbt/testing/Status;
        34: aload_1
        35: invokevirtual #69                 // Method org/scalatest/tools/Framework$ScalaTestSbtEvent.throwable:()Lsbt/testing/OptionalThrowable;
        38: aload_1
        39: invokevirtual #72                 // Method org/scalatest/tools/Framework$ScalaTestSbtEvent.duration:()J
        42: invokestatic  #78                 // Method scala/runtime/BoxesRunTime.boxToLong:(J)Ljava/lang/Long;
        45: invokespecial #81                 // Method scala/Tuple6."<init>":(Ljava/lang/Object;Ljava/lang/Object;Ljava/lang/Object;Ljava/lang/Object;Ljava/lang/Object;Ljava/lang/Object;)V
        48: invokespecial #84                 // Method scala/Some."<init>":(Ljava/lang/Object;)V
        51: areturn
      StackMapTable: number_of_entries = 2
        frame_type = 10 /* same */
        frame_type = 104 /* same_locals_1_stack_item */
          stack = [ class scala/Option ]
      LineNumberTable:
        line 1151: 0
      LocalVariableTable:
        Start  Length  Slot  Name   Signature
            0      52     0  this   Lorg/scalatest/tools/Framework$ScalaTestSbtEvent$;
            0      52     1   x$0   Lorg/scalatest/tools/Framework$ScalaTestSbtEvent;
    Signature: #44                          // (Lorg/scalatest/tools/Framework$ScalaTestSbtEvent;)Lscala/Option<Lscala/Tuple6<Ljava/lang/String;Lsbt/testing/Fingerprint;Lsbt/testing/Selector;Lsbt/testing/Status;Lsbt/testing/OptionalThrowable;Ljava/lang/Object;>;>;
    MethodParameters:
      Name                           Flags
      x$0                            final

  public java.lang.Object apply(java.lang.Object, java.lang.Object, java.lang.Object, java.lang.Object, java.lang.Object, java.lang.Object);
    descriptor: (Ljava/lang/Object;Ljava/lang/Object;Ljava/lang/Object;Ljava/lang/Object;Ljava/lang/Object;Ljava/lang/Object;)Ljava/lang/Object;
    flags: (0x1041) ACC_PUBLIC, ACC_BRIDGE, ACC_SYNTHETIC
    Code:
      stack=8, locals=7, args_size=7
         0: aload_0
         1: aload_1
         2: checkcast     #96                 // class java/lang/String
         5: aload_2
         6: checkcast     #98                 // class sbt/testing/Fingerprint
         9: aload_3
        10: checkcast     #100                // class sbt/testing/Selector
        13: aload         4
        15: checkcast     #102                // class sbt/testing/Status
        18: aload         5
        20: checkcast     #104                // class sbt/testing/OptionalThrowable
        23: aload         6
        25: invokestatic  #108                // Method scala/runtime/BoxesRunTime.unboxToLong:(Ljava/lang/Object;)J
        28: invokevirtual #110                // Method apply:(Ljava/lang/String;Lsbt/testing/Fingerprint;Lsbt/testing/Selector;Lsbt/testing/Status;Lsbt/testing/OptionalThrowable;J)Lorg/scalatest/tools/Framework$ScalaTestSbtEvent;
        31: areturn
      LineNumberTable:
        line 1151: 0
      LocalVariableTable:
        Start  Length  Slot  Name   Signature
            0      32     0  this   Lorg/scalatest/tools/Framework$ScalaTestSbtEvent$;
            0      32     1    v1   Ljava/lang/Object;
            0      32     2    v2   Ljava/lang/Object;
            0      32     3    v3   Ljava/lang/Object;
            0      32     4    v4   Ljava/lang/Object;
            0      32     5    v5   Ljava/lang/Object;
            0      32     6    v6   Ljava/lang/Object;
    MethodParameters:
      Name                           Flags
      v1                             final
      v2                             final
      v3                             final
      v4                             final
      v5                             final
      v6                             final

  public org.scalatest.tools.Framework$ScalaTestSbtEvent$(org.scalatest.tools.Framework);
    descriptor: (Lorg/scalatest/tools/Framework;)V
    flags: (0x0001) ACC_PUBLIC
    Code:
      stack=2, locals=2, args_size=2
         0: aload_1
         1: ifnonnull     6
         4: aconst_null
         5: athrow
         6: aload_0
         7: aload_1
         8: putfield      #31                 // Field $outer:Lorg/scalatest/tools/Framework;
        11: aload_0
        12: invokespecial #115                // Method scala/runtime/AbstractFunction6."<init>":()V
        15: return
      StackMapTable: number_of_entries = 1
        frame_type = 6 /* same */
      LineNumberTable:
        line 1151: 0
      LocalVariableTable:
        Start  Length  Slot  Name   Signature
            0      16     0  this   Lorg/scalatest/tools/Framework$ScalaTestSbtEvent$;
            0      16     1 $outer   Lorg/scalatest/tools/Framework;
    MethodParameters:
      Name                           Flags
      $outer                         final synthetic
}
InnerClasses:
  private #13= #10 of #12;                // ScalaTestSbtEvent=class org/scalatest/tools/Framework$ScalaTestSbtEvent of class org/scalatest/tools/Framework
  private #14= #2 of #12;                 // ScalaTestSbtEvent$=class org/scalatest/tools/Framework$ScalaTestSbtEvent$ of class org/scalatest/tools/Framework
Signature: #3                           // Lscala/runtime/AbstractFunction6<Ljava/lang/String;Lsbt/testing/Fingerprint;Lsbt/testing/Selector;Lsbt/testing/Status;Lsbt/testing/OptionalThrowable;Ljava/lang/Object;Lorg/scalatest/tools/Framework$ScalaTestSbtEvent;>;Ljava/io/Serializable;
SourceFile: "Framework.scala"
  ScalaInlineInfo: length = 0x1D (unknown attribute)
   01 01 00 05 00 20 00 70 01 00 16 00 58 01 00 16
   00 17 01 00 11 00 12 01 00 2A 00 2B 01
  Scala: length = 0x0 (unknown attribute)

