Classfile /Users/mw/Projects/slang-braindump/.jar/jar11/assemble/slang-braindump/assemble/content/org/scalatest/tools/Framework$ScalaTestRunner$SkeletonObjectInputStream$1.class
  Last modified May 29, 2022; size 1659 bytes
  SHA-256 checksum 11fbdad819dea623a6f870989986b71fcca830ab3d1559707dd67e7381d237be
  Compiled from "Framework.scala"
public class org.scalatest.tools.Framework$ScalaTestRunner$SkeletonObjectInputStream$1 extends java.io.ObjectInputStream
  minor version: 0
  major version: 52
  flags: (0x0021) ACC_PUBLIC, ACC_SUPER
  this_class: #2                          // org/scalatest/tools/Framework$ScalaTestRunner$SkeletonObjectInputStream$1
  super_class: #4                         // java/io/ObjectInputStream
  interfaces: 0, fields: 1, methods: 2, attributes: 5
Constant pool:
   #1 = Utf8               org/scalatest/tools/Framework$ScalaTestRunner$SkeletonObjectInputStream$1
   #2 = Class              #1             // org/scalatest/tools/Framework$ScalaTestRunner$SkeletonObjectInputStream$1
   #3 = Utf8               java/io/ObjectInputStream
   #4 = Class              #3             // java/io/ObjectInputStream
   #5 = Utf8               Framework.scala
   #6 = Utf8               org/scalatest/tools/Framework$ScalaTestRunner
   #7 = Class              #6             // org/scalatest/tools/Framework$ScalaTestRunner
   #8 = Utf8               remoteArgs
   #9 = Utf8               ()[Ljava/lang/String;
  #10 = NameAndType        #8:#9          // remoteArgs:()[Ljava/lang/String;
  #11 = Utf8               org/scalatest/tools/Framework
  #12 = Class              #11            // org/scalatest/tools/Framework
  #13 = Utf8               ScalaTestRunner
  #14 = Utf8               SkeletonObjectInputStream$1
  #15 = Utf8               loader
  #16 = Utf8               Ljava/lang/ClassLoader;
  #17 = Utf8               resolveClass
  #18 = Utf8               (Ljava/io/ObjectStreamClass;)Ljava/lang/Class;
  #19 = Utf8               (Ljava/io/ObjectStreamClass;)Ljava/lang/Class<*>;
  #20 = Utf8               desc
  #21 = Utf8               java/lang/ClassNotFoundException
  #22 = Class              #21            // java/lang/ClassNotFoundException
  #23 = Utf8               java/io/ObjectStreamClass
  #24 = Class              #23            // java/io/ObjectStreamClass
  #25 = Utf8               getName
  #26 = Utf8               ()Ljava/lang/String;
  #27 = NameAndType        #25:#26        // getName:()Ljava/lang/String;
  #28 = Methodref          #24.#27        // java/io/ObjectStreamClass.getName:()Ljava/lang/String;
  #29 = NameAndType        #15:#16        // loader:Ljava/lang/ClassLoader;
  #30 = Fieldref           #2.#29         // org/scalatest/tools/Framework$ScalaTestRunner$SkeletonObjectInputStream$1.loader:Ljava/lang/ClassLoader;
  #31 = Utf8               java/lang/Class
  #32 = Class              #31            // java/lang/Class
  #33 = Utf8               forName
  #34 = Utf8               (Ljava/lang/String;ZLjava/lang/ClassLoader;)Ljava/lang/Class;
  #35 = NameAndType        #33:#34        // forName:(Ljava/lang/String;ZLjava/lang/ClassLoader;)Ljava/lang/Class;
  #36 = Methodref          #32.#35        // java/lang/Class.forName:(Ljava/lang/String;ZLjava/lang/ClassLoader;)Ljava/lang/Class;
  #37 = NameAndType        #17:#18        // resolveClass:(Ljava/io/ObjectStreamClass;)Ljava/lang/Class;
  #38 = Methodref          #4.#37         // java/io/ObjectInputStream.resolveClass:(Ljava/io/ObjectStreamClass;)Ljava/lang/Class;
  #39 = Utf8               name
  #40 = Utf8               Ljava/lang/String;
  #41 = Utf8               e
  #42 = Utf8               Ljava/lang/ClassNotFoundException;
  #43 = Utf8               this
  #44 = Utf8               Lorg/scalatest/tools/Framework$ScalaTestRunner$SkeletonObjectInputStream$1;
  #45 = Utf8               Ljava/io/ObjectStreamClass;
  #46 = Utf8               <init>
  #47 = Utf8               (Lorg/scalatest/tools/Framework$ScalaTestRunner;Ljava/io/InputStream;Ljava/lang/ClassLoader;)V
  #48 = Utf8               $outer
  #49 = Utf8               in
  #50 = Utf8               (Ljava/io/InputStream;)V
  #51 = NameAndType        #46:#50        // "<init>":(Ljava/io/InputStream;)V
  #52 = Methodref          #4.#51         // java/io/ObjectInputStream."<init>":(Ljava/io/InputStream;)V
  #53 = Utf8               Lorg/scalatest/tools/Framework$ScalaTestRunner;
  #54 = Utf8               Ljava/io/InputStream;
  #55 = Utf8               Code
  #56 = Utf8               StackMapTable
  #57 = Utf8               LineNumberTable
  #58 = Utf8               LocalVariableTable
  #59 = Utf8               Signature
  #60 = Utf8               MethodParameters
  #61 = Utf8               InnerClasses
  #62 = Utf8               EnclosingMethod
  #63 = Utf8               SourceFile
  #64 = Utf8               ScalaInlineInfo
  #65 = Utf8               Scala
{
  private final java.lang.ClassLoader loader;
    descriptor: Ljava/lang/ClassLoader;
    flags: (0x0012) ACC_PRIVATE, ACC_FINAL

  public java.lang.Class<?> resolveClass(java.io.ObjectStreamClass);
    descriptor: (Ljava/io/ObjectStreamClass;)Ljava/lang/Class;
    flags: (0x0001) ACC_PUBLIC
    Code:
      stack=3, locals=4, args_size=2
         0: aload_1
         1: invokevirtual #28                 // Method java/io/ObjectStreamClass.getName:()Ljava/lang/String;
         4: astore_2
         5: aload_2
         6: iconst_0
         7: aload_0
         8: getfield      #30                 // Field loader:Ljava/lang/ClassLoader;
        11: invokestatic  #36                 // Method java/lang/Class.forName:(Ljava/lang/String;ZLjava/lang/ClassLoader;)Ljava/lang/Class;
        14: goto          26
        17: astore_3
        18: aload_0
        19: aload_1
        20: invokespecial #38                 // Method java/io/ObjectInputStream.resolveClass:(Ljava/io/ObjectStreamClass;)Ljava/lang/Class;
        23: goto          26
        26: areturn
      Exception table:
         from    to  target type
             0    14    17   Class java/lang/ClassNotFoundException
      StackMapTable: number_of_entries = 2
        frame_type = 81 /* same_locals_1_stack_item */
          stack = [ class java/lang/ClassNotFoundException ]
        frame_type = 72 /* same_locals_1_stack_item */
          stack = [ class java/lang/Class ]
      LineNumberTable:
        line 809: 0
        line 810: 5
        line 813: 18
      LocalVariableTable:
        Start  Length  Slot  Name   Signature
            5       9     2  name   Ljava/lang/String;
           17       6     3     e   Ljava/lang/ClassNotFoundException;
            0      27     0  this   Lorg/scalatest/tools/Framework$ScalaTestRunner$SkeletonObjectInputStream$1;
            0      27     1  desc   Ljava/io/ObjectStreamClass;
    Signature: #19                          // (Ljava/io/ObjectStreamClass;)Ljava/lang/Class<*>;
    MethodParameters:
      Name                           Flags
      desc                           final

  public org.scalatest.tools.Framework$ScalaTestRunner$SkeletonObjectInputStream$1(org.scalatest.tools.Framework$ScalaTestRunner, java.io.InputStream, java.lang.ClassLoader);
    descriptor: (Lorg/scalatest/tools/Framework$ScalaTestRunner;Ljava/io/InputStream;Ljava/lang/ClassLoader;)V
    flags: (0x0001) ACC_PUBLIC
    Code:
      stack=2, locals=4, args_size=4
         0: aload_0
         1: aload_3
         2: putfield      #30                 // Field loader:Ljava/lang/ClassLoader;
         5: aload_0
         6: aload_2
         7: invokespecial #52                 // Method java/io/ObjectInputStream."<init>":(Ljava/io/InputStream;)V
        10: return
      LineNumberTable:
        line 805: 0
      LocalVariableTable:
        Start  Length  Slot  Name   Signature
            0      11     0  this   Lorg/scalatest/tools/Framework$ScalaTestRunner$SkeletonObjectInputStream$1;
            0      11     1 $outer   Lorg/scalatest/tools/Framework$ScalaTestRunner;
            0      11     2    in   Ljava/io/InputStream;
            0      11     3 loader   Ljava/lang/ClassLoader;
    MethodParameters:
      Name                           Flags
      $outer                         final synthetic
      in                             final
      loader                         final
}
InnerClasses:
  public #13= #7 of #12;                  // ScalaTestRunner=class org/scalatest/tools/Framework$ScalaTestRunner of class org/scalatest/tools/Framework
  public #14= #2;                         // SkeletonObjectInputStream$1=class org/scalatest/tools/Framework$ScalaTestRunner$SkeletonObjectInputStream$1
EnclosingMethod: #7.#10                 // org.scalatest.tools.Framework$ScalaTestRunner.remoteArgs
SourceFile: "Framework.scala"
  ScalaInlineInfo: length = 0xE (unknown attribute)
   01 01 00 02 00 2E 00 2F 01 00 11 00 12 01
  Scala: length = 0x0 (unknown attribute)

