Classfile /Users/mw/Projects/slang-braindump/.jar/jar11/assemble/slang-braindump/assemble/content/org/scalatest/tools/JUnitXmlReporter$Testsuite.class
  Last modified May 29, 2022; size 4846 bytes
  SHA-256 checksum e0df9bd4dfc766e237f5769ae9362649d6dced693a43b27739b1d6ececd339b5
  Compiled from "JUnitXmlReporter.scala"
public class org.scalatest.tools.JUnitXmlReporter$Testsuite implements scala.Product,java.io.Serializable
  minor version: 0
  major version: 52
  flags: (0x0021) ACC_PUBLIC, ACC_SUPER
  this_class: #2                          // org/scalatest/tools/JUnitXmlReporter$Testsuite
  super_class: #4                         // java/lang/Object
  interfaces: 2, fields: 7, methods: 24, attributes: 4
Constant pool:
    #1 = Utf8               org/scalatest/tools/JUnitXmlReporter$Testsuite
    #2 = Class              #1            // org/scalatest/tools/JUnitXmlReporter$Testsuite
    #3 = Utf8               java/lang/Object
    #4 = Class              #3            // java/lang/Object
    #5 = Utf8               scala/Product
    #6 = Class              #5            // scala/Product
    #7 = Utf8               java/io/Serializable
    #8 = Class              #7            // java/io/Serializable
    #9 = Utf8               JUnitXmlReporter.scala
   #10 = Utf8               org/scalatest/tools/JUnitXmlReporter$Testcase
   #11 = Class              #10           // org/scalatest/tools/JUnitXmlReporter$Testcase
   #12 = Utf8               org/scalatest/tools/JUnitXmlReporter
   #13 = Class              #12           // org/scalatest/tools/JUnitXmlReporter
   #14 = Utf8               Testcase
   #15 = Utf8               Testsuite
   #16 = Utf8               name
   #17 = Utf8               Ljava/lang/String;
   #18 = Utf8               timeStamp
   #19 = Utf8               J
   #20 = Utf8               errors
   #21 = Utf8               I
   #22 = Utf8               failures
   #23 = Utf8               time
   #24 = Utf8               testcases
   #25 = Utf8               Lscala/collection/mutable/ListBuffer;
   #26 = Utf8               Lscala/collection/mutable/ListBuffer<Lorg/scalatest/tools/JUnitXmlReporter$Testcase;>;
   #27 = Utf8               $outer
   #28 = Utf8               Lorg/scalatest/tools/JUnitXmlReporter;
   #29 = Utf8               productElementNames
   #30 = Utf8               ()Lscala/collection/Iterator;
   #31 = Utf8               ()Lscala/collection/Iterator<Ljava/lang/String;>;
   #32 = Utf8               productElementNames$
   #33 = Utf8               (Lscala/Product;)Lscala/collection/Iterator;
   #34 = NameAndType        #32:#33       // productElementNames$:(Lscala/Product;)Lscala/collection/Iterator;
   #35 = InterfaceMethodref #6.#34        // scala/Product.productElementNames$:(Lscala/Product;)Lscala/collection/Iterator;
   #36 = Utf8               this
   #37 = Utf8               Lorg/scalatest/tools/JUnitXmlReporter$Testsuite;
   #38 = Utf8               ()Ljava/lang/String;
   #39 = NameAndType        #16:#17       // name:Ljava/lang/String;
   #40 = Fieldref           #2.#39        // org/scalatest/tools/JUnitXmlReporter$Testsuite.name:Ljava/lang/String;
   #41 = Utf8               ()J
   #42 = NameAndType        #18:#19       // timeStamp:J
   #43 = Fieldref           #2.#42        // org/scalatest/tools/JUnitXmlReporter$Testsuite.timeStamp:J
   #44 = Utf8               ()I
   #45 = NameAndType        #20:#21       // errors:I
   #46 = Fieldref           #2.#45        // org/scalatest/tools/JUnitXmlReporter$Testsuite.errors:I
   #47 = Utf8               errors_$eq
   #48 = Utf8               (I)V
   #49 = Utf8               x$1
   #50 = NameAndType        #22:#21       // failures:I
   #51 = Fieldref           #2.#50        // org/scalatest/tools/JUnitXmlReporter$Testsuite.failures:I
   #52 = Utf8               failures_$eq
   #53 = NameAndType        #23:#19       // time:J
   #54 = Fieldref           #2.#53        // org/scalatest/tools/JUnitXmlReporter$Testsuite.time:J
   #55 = Utf8               time_$eq
   #56 = Utf8               (J)V
   #57 = Utf8               ()Lscala/collection/mutable/ListBuffer;
   #58 = Utf8               ()Lscala/collection/mutable/ListBuffer<Lorg/scalatest/tools/JUnitXmlReporter$Testcase;>;
   #59 = NameAndType        #24:#25       // testcases:Lscala/collection/mutable/ListBuffer;
   #60 = Fieldref           #2.#59        // org/scalatest/tools/JUnitXmlReporter$Testsuite.testcases:Lscala/collection/mutable/ListBuffer;
   #61 = Utf8               copy
   #62 = Utf8               (Ljava/lang/String;J)Lorg/scalatest/tools/JUnitXmlReporter$Testsuite;
   #63 = Utf8               org$scalatest$tools$JUnitXmlReporter$Testsuite$$$outer
   #64 = Utf8               ()Lorg/scalatest/tools/JUnitXmlReporter;
   #65 = NameAndType        #63:#64       // org$scalatest$tools$JUnitXmlReporter$Testsuite$$$outer:()Lorg/scalatest/tools/JUnitXmlReporter;
   #66 = Methodref          #2.#65        // org/scalatest/tools/JUnitXmlReporter$Testsuite.org$scalatest$tools$JUnitXmlReporter$Testsuite$$$outer:()Lorg/scalatest/tools/JUnitXmlReporter;
   #67 = Utf8               <init>
   #68 = Utf8               (Lorg/scalatest/tools/JUnitXmlReporter;Ljava/lang/String;J)V
   #69 = NameAndType        #67:#68       // "<init>":(Lorg/scalatest/tools/JUnitXmlReporter;Ljava/lang/String;J)V
   #70 = Methodref          #2.#69        // org/scalatest/tools/JUnitXmlReporter$Testsuite."<init>":(Lorg/scalatest/tools/JUnitXmlReporter;Ljava/lang/String;J)V
   #71 = Utf8               copy$default$1
   #72 = NameAndType        #16:#38       // name:()Ljava/lang/String;
   #73 = Methodref          #2.#72        // org/scalatest/tools/JUnitXmlReporter$Testsuite.name:()Ljava/lang/String;
   #74 = Utf8               copy$default$2
   #75 = NameAndType        #18:#41       // timeStamp:()J
   #76 = Methodref          #2.#75        // org/scalatest/tools/JUnitXmlReporter$Testsuite.timeStamp:()J
   #77 = Utf8               productPrefix
   #78 = String             #15           // Testsuite
   #79 = Utf8               productArity
   #80 = Utf8               productElement
   #81 = Utf8               (I)Ljava/lang/Object;
   #82 = Utf8               scala/runtime/BoxesRunTime
   #83 = Class              #82           // scala/runtime/BoxesRunTime
   #84 = Utf8               boxToLong
   #85 = Utf8               (J)Ljava/lang/Long;
   #86 = NameAndType        #84:#85       // boxToLong:(J)Ljava/lang/Long;
   #87 = Methodref          #83.#86       // scala/runtime/BoxesRunTime.boxToLong:(J)Ljava/lang/Long;
   #88 = Utf8               scala/runtime/Statics
   #89 = Class              #88           // scala/runtime/Statics
   #90 = Utf8               ioobe
   #91 = NameAndType        #90:#81       // ioobe:(I)Ljava/lang/Object;
   #92 = Methodref          #89.#91       // scala/runtime/Statics.ioobe:(I)Ljava/lang/Object;
   #93 = Utf8               productIterator
   #94 = Utf8               ()Lscala/collection/Iterator<Ljava/lang/Object;>;
   #95 = Utf8               scala/runtime/ScalaRunTime$
   #96 = Class              #95           // scala/runtime/ScalaRunTime$
   #97 = Utf8               MODULE$
   #98 = Utf8               Lscala/runtime/ScalaRunTime$;
   #99 = NameAndType        #97:#98       // MODULE$:Lscala/runtime/ScalaRunTime$;
  #100 = Fieldref           #96.#99       // scala/runtime/ScalaRunTime$.MODULE$:Lscala/runtime/ScalaRunTime$;
  #101 = Utf8               typedProductIterator
  #102 = NameAndType        #101:#33      // typedProductIterator:(Lscala/Product;)Lscala/collection/Iterator;
  #103 = Methodref          #96.#102      // scala/runtime/ScalaRunTime$.typedProductIterator:(Lscala/Product;)Lscala/collection/Iterator;
  #104 = Utf8               canEqual
  #105 = Utf8               (Ljava/lang/Object;)Z
  #106 = Utf8               Ljava/lang/Object;
  #107 = Utf8               productElementName
  #108 = Utf8               (I)Ljava/lang/String;
  #109 = String             #16           // name
  #110 = String             #18           // timeStamp
  #111 = Utf8               java/lang/String
  #112 = Class              #111          // java/lang/String
  #113 = Utf8               hashCode
  #114 = Integer            -889275714
  #115 = NameAndType        #77:#38       // productPrefix:()Ljava/lang/String;
  #116 = Methodref          #2.#115       // org/scalatest/tools/JUnitXmlReporter$Testsuite.productPrefix:()Ljava/lang/String;
  #117 = NameAndType        #113:#44      // hashCode:()I
  #118 = Methodref          #112.#117     // java/lang/String.hashCode:()I
  #119 = Utf8               mix
  #120 = Utf8               (II)I
  #121 = NameAndType        #119:#120     // mix:(II)I
  #122 = Methodref          #89.#121      // scala/runtime/Statics.mix:(II)I
  #123 = Utf8               anyHash
  #124 = Utf8               (Ljava/lang/Object;)I
  #125 = NameAndType        #123:#124     // anyHash:(Ljava/lang/Object;)I
  #126 = Methodref          #89.#125      // scala/runtime/Statics.anyHash:(Ljava/lang/Object;)I
  #127 = Utf8               longHash
  #128 = Utf8               (J)I
  #129 = NameAndType        #127:#128     // longHash:(J)I
  #130 = Methodref          #89.#129      // scala/runtime/Statics.longHash:(J)I
  #131 = Utf8               finalizeHash
  #132 = NameAndType        #131:#120     // finalizeHash:(II)I
  #133 = Methodref          #89.#132      // scala/runtime/Statics.finalizeHash:(II)I
  #134 = Utf8               toString
  #135 = Utf8               _toString
  #136 = Utf8               (Lscala/Product;)Ljava/lang/String;
  #137 = NameAndType        #135:#136     // _toString:(Lscala/Product;)Ljava/lang/String;
  #138 = Methodref          #96.#137      // scala/runtime/ScalaRunTime$._toString:(Lscala/Product;)Ljava/lang/String;
  #139 = Utf8               equals
  #140 = NameAndType        #139:#105     // equals:(Ljava/lang/Object;)Z
  #141 = Methodref          #4.#140       // java/lang/Object.equals:(Ljava/lang/Object;)Z
  #142 = NameAndType        #104:#105     // canEqual:(Ljava/lang/Object;)Z
  #143 = Methodref          #2.#142       // org/scalatest/tools/JUnitXmlReporter$Testsuite.canEqual:(Ljava/lang/Object;)Z
  #144 = NameAndType        #27:#28       // $outer:Lorg/scalatest/tools/JUnitXmlReporter;
  #145 = Fieldref           #2.#144       // org/scalatest/tools/JUnitXmlReporter$Testsuite.$outer:Lorg/scalatest/tools/JUnitXmlReporter;
  #146 = Utf8               ()V
  #147 = NameAndType        #67:#146      // "<init>":()V
  #148 = Methodref          #4.#147       // java/lang/Object."<init>":()V
  #149 = Utf8               $init$
  #150 = Utf8               (Lscala/Product;)V
  #151 = NameAndType        #149:#150     // $init$:(Lscala/Product;)V
  #152 = InterfaceMethodref #6.#151       // scala/Product.$init$:(Lscala/Product;)V
  #153 = Utf8               scala/collection/mutable/ListBuffer
  #154 = Class              #153          // scala/collection/mutable/ListBuffer
  #155 = Methodref          #154.#147     // scala/collection/mutable/ListBuffer."<init>":()V
  #156 = Utf8               Signature
  #157 = Utf8               Code
  #158 = Utf8               LineNumberTable
  #159 = Utf8               LocalVariableTable
  #160 = Utf8               MethodParameters
  #161 = Utf8               StackMapTable
  #162 = Utf8               InnerClasses
  #163 = Utf8               SourceFile
  #164 = Utf8               ScalaInlineInfo
  #165 = Utf8               Scala
{
  private final java.lang.String name;
    descriptor: Ljava/lang/String;
    flags: (0x0012) ACC_PRIVATE, ACC_FINAL

  private final long timeStamp;
    descriptor: J
    flags: (0x0012) ACC_PRIVATE, ACC_FINAL

  private int errors;
    descriptor: I
    flags: (0x0002) ACC_PRIVATE

  private int failures;
    descriptor: I
    flags: (0x0002) ACC_PRIVATE

  private long time;
    descriptor: J
    flags: (0x0002) ACC_PRIVATE

  private final scala.collection.mutable.ListBuffer<org.scalatest.tools.JUnitXmlReporter$Testcase> testcases;
    descriptor: Lscala/collection/mutable/ListBuffer;
    flags: (0x0012) ACC_PRIVATE, ACC_FINAL
    Signature: #26                          // Lscala/collection/mutable/ListBuffer<Lorg/scalatest/tools/JUnitXmlReporter$Testcase;>;

  public final org.scalatest.tools.JUnitXmlReporter $outer;
    descriptor: Lorg/scalatest/tools/JUnitXmlReporter;
    flags: (0x1011) ACC_PUBLIC, ACC_FINAL, ACC_SYNTHETIC

  public scala.collection.Iterator<java.lang.String> productElementNames();
    descriptor: ()Lscala/collection/Iterator;
    flags: (0x0001) ACC_PUBLIC
    Code:
      stack=1, locals=1, args_size=1
         0: aload_0
         1: invokestatic  #35                 // InterfaceMethod scala/Product.productElementNames$:(Lscala/Product;)Lscala/collection/Iterator;
         4: areturn
      LineNumberTable:
        line 500: 0
      LocalVariableTable:
        Start  Length  Slot  Name   Signature
            0       5     0  this   Lorg/scalatest/tools/JUnitXmlReporter$Testsuite;
    Signature: #31                          // ()Lscala/collection/Iterator<Ljava/lang/String;>;

  public java.lang.String name();
    descriptor: ()Ljava/lang/String;
    flags: (0x0001) ACC_PUBLIC
    Code:
      stack=1, locals=1, args_size=1
         0: aload_0
         1: getfield      #40                 // Field name:Ljava/lang/String;
         4: areturn
      LineNumberTable:
        line 500: 0
      LocalVariableTable:
        Start  Length  Slot  Name   Signature
            0       5     0  this   Lorg/scalatest/tools/JUnitXmlReporter$Testsuite;

  public long timeStamp();
    descriptor: ()J
    flags: (0x0001) ACC_PUBLIC
    Code:
      stack=2, locals=1, args_size=1
         0: aload_0
         1: getfield      #43                 // Field timeStamp:J
         4: lreturn
      LineNumberTable:
        line 500: 0
      LocalVariableTable:
        Start  Length  Slot  Name   Signature
            0       5     0  this   Lorg/scalatest/tools/JUnitXmlReporter$Testsuite;

  public int errors();
    descriptor: ()I
    flags: (0x0001) ACC_PUBLIC
    Code:
      stack=1, locals=1, args_size=1
         0: aload_0
         1: getfield      #46                 // Field errors:I
         4: ireturn
      LineNumberTable:
        line 501: 0
      LocalVariableTable:
        Start  Length  Slot  Name   Signature
            0       5     0  this   Lorg/scalatest/tools/JUnitXmlReporter$Testsuite;

  public void errors_$eq(int);
    descriptor: (I)V
    flags: (0x0001) ACC_PUBLIC
    Code:
      stack=2, locals=2, args_size=2
         0: aload_0
         1: iload_1
         2: putfield      #46                 // Field errors:I
         5: return
      LineNumberTable:
        line 501: 0
      LocalVariableTable:
        Start  Length  Slot  Name   Signature
            0       6     0  this   Lorg/scalatest/tools/JUnitXmlReporter$Testsuite;
            0       6     1   x$1   I
    MethodParameters:
      Name                           Flags
      x$1                            final

  public int failures();
    descriptor: ()I
    flags: (0x0001) ACC_PUBLIC
    Code:
      stack=1, locals=1, args_size=1
         0: aload_0
         1: getfield      #51                 // Field failures:I
         4: ireturn
      LineNumberTable:
        line 502: 0
      LocalVariableTable:
        Start  Length  Slot  Name   Signature
            0       5     0  this   Lorg/scalatest/tools/JUnitXmlReporter$Testsuite;

  public void failures_$eq(int);
    descriptor: (I)V
    flags: (0x0001) ACC_PUBLIC
    Code:
      stack=2, locals=2, args_size=2
         0: aload_0
         1: iload_1
         2: putfield      #51                 // Field failures:I
         5: return
      LineNumberTable:
        line 502: 0
      LocalVariableTable:
        Start  Length  Slot  Name   Signature
            0       6     0  this   Lorg/scalatest/tools/JUnitXmlReporter$Testsuite;
            0       6     1   x$1   I
    MethodParameters:
      Name                           Flags
      x$1                            final

  public long time();
    descriptor: ()J
    flags: (0x0001) ACC_PUBLIC
    Code:
      stack=2, locals=1, args_size=1
         0: aload_0
         1: getfield      #54                 // Field time:J
         4: lreturn
      LineNumberTable:
        line 503: 0
      LocalVariableTable:
        Start  Length  Slot  Name   Signature
            0       5     0  this   Lorg/scalatest/tools/JUnitXmlReporter$Testsuite;

  public void time_$eq(long);
    descriptor: (J)V
    flags: (0x0001) ACC_PUBLIC
    Code:
      stack=3, locals=3, args_size=2
         0: aload_0
         1: lload_1
         2: putfield      #54                 // Field time:J
         5: return
      LineNumberTable:
        line 503: 0
      LocalVariableTable:
        Start  Length  Slot  Name   Signature
            0       6     0  this   Lorg/scalatest/tools/JUnitXmlReporter$Testsuite;
            0       6     1   x$1   J
    MethodParameters:
      Name                           Flags
      x$1                            final

  public scala.collection.mutable.ListBuffer<org.scalatest.tools.JUnitXmlReporter$Testcase> testcases();
    descriptor: ()Lscala/collection/mutable/ListBuffer;
    flags: (0x0001) ACC_PUBLIC
    Code:
      stack=1, locals=1, args_size=1
         0: aload_0
         1: getfield      #60                 // Field testcases:Lscala/collection/mutable/ListBuffer;
         4: areturn
      LineNumberTable:
        line 504: 0
      LocalVariableTable:
        Start  Length  Slot  Name   Signature
            0       5     0  this   Lorg/scalatest/tools/JUnitXmlReporter$Testsuite;
    Signature: #58                          // ()Lscala/collection/mutable/ListBuffer<Lorg/scalatest/tools/JUnitXmlReporter$Testcase;>;

  public org.scalatest.tools.JUnitXmlReporter$Testsuite copy(java.lang.String, long);
    descriptor: (Ljava/lang/String;J)Lorg/scalatest/tools/JUnitXmlReporter$Testsuite;
    flags: (0x0001) ACC_PUBLIC
    Code:
      stack=6, locals=4, args_size=3
         0: new           #2                  // class org/scalatest/tools/JUnitXmlReporter$Testsuite
         3: dup
         4: aload_0
         5: invokevirtual #66                 // Method org$scalatest$tools$JUnitXmlReporter$Testsuite$$$outer:()Lorg/scalatest/tools/JUnitXmlReporter;
         8: aload_1
         9: lload_2
        10: invokespecial #70                 // Method "<init>":(Lorg/scalatest/tools/JUnitXmlReporter;Ljava/lang/String;J)V
        13: areturn
      LineNumberTable:
        line 500: 0
      LocalVariableTable:
        Start  Length  Slot  Name   Signature
            0      14     0  this   Lorg/scalatest/tools/JUnitXmlReporter$Testsuite;
            0      14     1  name   Ljava/lang/String;
            0      14     2 timeStamp   J
    MethodParameters:
      Name                           Flags
      name                           final
      timeStamp                      final

  public java.lang.String copy$default$1();
    descriptor: ()Ljava/lang/String;
    flags: (0x0001) ACC_PUBLIC
    Code:
      stack=1, locals=1, args_size=1
         0: aload_0
         1: invokevirtual #73                 // Method name:()Ljava/lang/String;
         4: areturn
      LineNumberTable:
        line 500: 0
      LocalVariableTable:
        Start  Length  Slot  Name   Signature
            0       5     0  this   Lorg/scalatest/tools/JUnitXmlReporter$Testsuite;

  public long copy$default$2();
    descriptor: ()J
    flags: (0x0001) ACC_PUBLIC
    Code:
      stack=2, locals=1, args_size=1
         0: aload_0
         1: invokevirtual #76                 // Method timeStamp:()J
         4: lreturn
      LineNumberTable:
        line 500: 0
      LocalVariableTable:
        Start  Length  Slot  Name   Signature
            0       5     0  this   Lorg/scalatest/tools/JUnitXmlReporter$Testsuite;

  public java.lang.String productPrefix();
    descriptor: ()Ljava/lang/String;
    flags: (0x0001) ACC_PUBLIC
    Code:
      stack=1, locals=1, args_size=1
         0: ldc           #78                 // String Testsuite
         2: areturn
      LineNumberTable:
        line 500: 0
      LocalVariableTable:
        Start  Length  Slot  Name   Signature
            0       3     0  this   Lorg/scalatest/tools/JUnitXmlReporter$Testsuite;

  public int productArity();
    descriptor: ()I
    flags: (0x0001) ACC_PUBLIC
    Code:
      stack=1, locals=1, args_size=1
         0: iconst_2
         1: ireturn
      LineNumberTable:
        line 500: 0
      LocalVariableTable:
        Start  Length  Slot  Name   Signature
            0       2     0  this   Lorg/scalatest/tools/JUnitXmlReporter$Testsuite;

  public java.lang.Object productElement(int);
    descriptor: (I)Ljava/lang/Object;
    flags: (0x0001) ACC_PUBLIC
    Code:
      stack=2, locals=3, args_size=2
         0: iload_1
         1: istore_2
         2: iload_2
         3: tableswitch   { // 0 to 1
                       0: 24
                       1: 31
                 default: 41
            }
        24: aload_0
        25: invokevirtual #73                 // Method name:()Ljava/lang/String;
        28: goto          48
        31: aload_0
        32: invokevirtual #76                 // Method timeStamp:()J
        35: invokestatic  #87                 // Method scala/runtime/BoxesRunTime.boxToLong:(J)Ljava/lang/Long;
        38: goto          48
        41: iload_1
        42: invokestatic  #92                 // Method scala/runtime/Statics.ioobe:(I)Ljava/lang/Object;
        45: goto          48
        48: areturn
      StackMapTable: number_of_entries = 4
        frame_type = 252 /* append */
          offset_delta = 24
          locals = [ int ]
        frame_type = 6 /* same */
        frame_type = 9 /* same */
        frame_type = 70 /* same_locals_1_stack_item */
          stack = [ class java/lang/Object ]
      LineNumberTable:
        line 500: 0
      LocalVariableTable:
        Start  Length  Slot  Name   Signature
            0      49     0  this   Lorg/scalatest/tools/JUnitXmlReporter$Testsuite;
            0      49     1   x$1   I
    MethodParameters:
      Name                           Flags
      x$1                            final

  public scala.collection.Iterator<java.lang.Object> productIterator();
    descriptor: ()Lscala/collection/Iterator;
    flags: (0x0001) ACC_PUBLIC
    Code:
      stack=2, locals=1, args_size=1
         0: getstatic     #100                // Field scala/runtime/ScalaRunTime$.MODULE$:Lscala/runtime/ScalaRunTime$;
         3: aload_0
         4: invokevirtual #103                // Method scala/runtime/ScalaRunTime$.typedProductIterator:(Lscala/Product;)Lscala/collection/Iterator;
         7: areturn
      LineNumberTable:
        line 500: 0
      LocalVariableTable:
        Start  Length  Slot  Name   Signature
            0       8     0  this   Lorg/scalatest/tools/JUnitXmlReporter$Testsuite;
    Signature: #94                          // ()Lscala/collection/Iterator<Ljava/lang/Object;>;

  public boolean canEqual(java.lang.Object);
    descriptor: (Ljava/lang/Object;)Z
    flags: (0x0001) ACC_PUBLIC
    Code:
      stack=1, locals=2, args_size=2
         0: aload_1
         1: instanceof    #2                  // class org/scalatest/tools/JUnitXmlReporter$Testsuite
         4: ireturn
      LineNumberTable:
        line 500: 0
      LocalVariableTable:
        Start  Length  Slot  Name   Signature
            0       5     0  this   Lorg/scalatest/tools/JUnitXmlReporter$Testsuite;
            0       5     1   x$1   Ljava/lang/Object;
    MethodParameters:
      Name                           Flags
      x$1                            final

  public java.lang.String productElementName(int);
    descriptor: (I)Ljava/lang/String;
    flags: (0x0001) ACC_PUBLIC
    Code:
      stack=1, locals=3, args_size=2
         0: iload_1
         1: istore_2
         2: iload_2
         3: tableswitch   { // 0 to 1
                       0: 24
                       1: 29
                 default: 34
            }
        24: ldc           #109                // String name
        26: goto          44
        29: ldc           #110                // String timeStamp
        31: goto          44
        34: iload_1
        35: invokestatic  #92                 // Method scala/runtime/Statics.ioobe:(I)Ljava/lang/Object;
        38: checkcast     #112                // class java/lang/String
        41: goto          44
        44: areturn
      StackMapTable: number_of_entries = 4
        frame_type = 252 /* append */
          offset_delta = 24
          locals = [ int ]
        frame_type = 4 /* same */
        frame_type = 4 /* same */
        frame_type = 73 /* same_locals_1_stack_item */
          stack = [ class java/lang/String ]
      LineNumberTable:
        line 500: 0
      LocalVariableTable:
        Start  Length  Slot  Name   Signature
            0      45     0  this   Lorg/scalatest/tools/JUnitXmlReporter$Testsuite;
            0      45     1   x$1   I
    MethodParameters:
      Name                           Flags
      x$1                            final

  public int hashCode();
    descriptor: ()I
    flags: (0x0001) ACC_PUBLIC
    Code:
      stack=3, locals=2, args_size=1
         0: ldc           #114                // int -889275714
         2: istore_1
         3: iload_1
         4: aload_0
         5: invokevirtual #116                // Method productPrefix:()Ljava/lang/String;
         8: invokevirtual #118                // Method java/lang/String.hashCode:()I
        11: invokestatic  #122                // Method scala/runtime/Statics.mix:(II)I
        14: istore_1
        15: iload_1
        16: aload_0
        17: invokevirtual #73                 // Method name:()Ljava/lang/String;
        20: invokestatic  #126                // Method scala/runtime/Statics.anyHash:(Ljava/lang/Object;)I
        23: invokestatic  #122                // Method scala/runtime/Statics.mix:(II)I
        26: istore_1
        27: iload_1
        28: aload_0
        29: invokevirtual #76                 // Method timeStamp:()J
        32: invokestatic  #130                // Method scala/runtime/Statics.longHash:(J)I
        35: invokestatic  #122                // Method scala/runtime/Statics.mix:(II)I
        38: istore_1
        39: iload_1
        40: iconst_2
        41: invokestatic  #133                // Method scala/runtime/Statics.finalizeHash:(II)I
        44: ireturn
      LineNumberTable:
        line 500: 0
      LocalVariableTable:
        Start  Length  Slot  Name   Signature
            0      45     0  this   Lorg/scalatest/tools/JUnitXmlReporter$Testsuite;

  public java.lang.String toString();
    descriptor: ()Ljava/lang/String;
    flags: (0x0001) ACC_PUBLIC
    Code:
      stack=2, locals=1, args_size=1
         0: getstatic     #100                // Field scala/runtime/ScalaRunTime$.MODULE$:Lscala/runtime/ScalaRunTime$;
         3: aload_0
         4: invokevirtual #138                // Method scala/runtime/ScalaRunTime$._toString:(Lscala/Product;)Ljava/lang/String;
         7: areturn
      LineNumberTable:
        line 500: 0
      LocalVariableTable:
        Start  Length  Slot  Name   Signature
            0       8     0  this   Lorg/scalatest/tools/JUnitXmlReporter$Testsuite;

  public boolean equals(java.lang.Object);
    descriptor: (Ljava/lang/Object;)Z
    flags: (0x0001) ACC_PUBLIC
    Code:
      stack=4, locals=6, args_size=2
         0: aload_0
         1: aload_1
         2: if_acmpeq     113
         5: aload_1
         6: astore_3
         7: aload_3
         8: instanceof    #2                  // class org/scalatest/tools/JUnitXmlReporter$Testsuite
        11: ifeq          33
        14: aload_3
        15: checkcast     #2                  // class org/scalatest/tools/JUnitXmlReporter$Testsuite
        18: invokevirtual #66                 // Method org$scalatest$tools$JUnitXmlReporter$Testsuite$$$outer:()Lorg/scalatest/tools/JUnitXmlReporter;
        21: aload_0
        22: invokevirtual #66                 // Method org$scalatest$tools$JUnitXmlReporter$Testsuite$$$outer:()Lorg/scalatest/tools/JUnitXmlReporter;
        25: if_acmpne     33
        28: iconst_1
        29: istore_2
        30: goto          41
        33: goto          36
        36: iconst_0
        37: istore_2
        38: goto          41
        41: iload_2
        42: ifeq          117
        45: aload_1
        46: checkcast     #2                  // class org/scalatest/tools/JUnitXmlReporter$Testsuite
        49: astore        4
        51: aload_0
        52: invokevirtual #76                 // Method timeStamp:()J
        55: aload         4
        57: invokevirtual #76                 // Method timeStamp:()J
        60: lcmp
        61: ifne          109
        64: aload_0
        65: invokevirtual #73                 // Method name:()Ljava/lang/String;
        68: aload         4
        70: invokevirtual #73                 // Method name:()Ljava/lang/String;
        73: astore        5
        75: dup
        76: ifnonnull     88
        79: pop
        80: aload         5
        82: ifnull        96
        85: goto          109
        88: aload         5
        90: invokevirtual #141                // Method java/lang/Object.equals:(Ljava/lang/Object;)Z
        93: ifeq          109
        96: aload         4
        98: aload_0
        99: invokevirtual #143                // Method canEqual:(Ljava/lang/Object;)Z
       102: ifeq          109
       105: iconst_1
       106: goto          110
       109: iconst_0
       110: ifeq          117
       113: iconst_1
       114: goto          118
       117: iconst_0
       118: ireturn
      StackMapTable: number_of_entries = 10
        frame_type = 253 /* append */
          offset_delta = 33
          locals = [ top, class java/lang/Object ]
        frame_type = 2 /* same */
        frame_type = 255 /* full_frame */
          offset_delta = 4
          locals = [ class org/scalatest/tools/JUnitXmlReporter$Testsuite, class java/lang/Object, int, class java/lang/Object ]
          stack = []
        frame_type = 255 /* full_frame */
          offset_delta = 46
          locals = [ class org/scalatest/tools/JUnitXmlReporter$Testsuite, class java/lang/Object, int, class java/lang/Object, class org/scalatest/tools/JUnitXmlReporter$Testsuite, class java/lang/String ]
          stack = [ class java/lang/String ]
        frame_type = 7 /* same */
        frame_type = 250 /* chop */
          offset_delta = 12
        frame_type = 64 /* same_locals_1_stack_item */
          stack = [ int ]
        frame_type = 248 /* chop */
          offset_delta = 2
        frame_type = 253 /* append */
          offset_delta = 3
          locals = [ int, class java/lang/Object ]
        frame_type = 255 /* full_frame */
          offset_delta = 0
          locals = [ class org/scalatest/tools/JUnitXmlReporter$Testsuite, class java/lang/Object ]
          stack = [ int ]
      LineNumberTable:
        line 500: 0
      LocalVariableTable:
        Start  Length  Slot  Name   Signature
            0     119     0  this   Lorg/scalatest/tools/JUnitXmlReporter$Testsuite;
            0     119     1   x$1   Ljava/lang/Object;
    MethodParameters:
      Name                           Flags
      x$1                            final

  public org.scalatest.tools.JUnitXmlReporter org$scalatest$tools$JUnitXmlReporter$Testsuite$$$outer();
    descriptor: ()Lorg/scalatest/tools/JUnitXmlReporter;
    flags: (0x1001) ACC_PUBLIC, ACC_SYNTHETIC
    Code:
      stack=1, locals=1, args_size=1
         0: aload_0
         1: getfield      #145                // Field $outer:Lorg/scalatest/tools/JUnitXmlReporter;
         4: areturn
      LineNumberTable:
        line 500: 0
      LocalVariableTable:
        Start  Length  Slot  Name   Signature
            0       5     0  this   Lorg/scalatest/tools/JUnitXmlReporter$Testsuite;

  public org.scalatest.tools.JUnitXmlReporter$Testsuite(org.scalatest.tools.JUnitXmlReporter, java.lang.String, long);
    descriptor: (Lorg/scalatest/tools/JUnitXmlReporter;Ljava/lang/String;J)V
    flags: (0x0001) ACC_PUBLIC
    Code:
      stack=3, locals=5, args_size=4
         0: aload_0
         1: aload_2
         2: putfield      #40                 // Field name:Ljava/lang/String;
         5: aload_0
         6: lload_3
         7: putfield      #43                 // Field timeStamp:J
        10: aload_1
        11: ifnonnull     16
        14: aconst_null
        15: athrow
        16: aload_0
        17: aload_1
        18: putfield      #145                // Field $outer:Lorg/scalatest/tools/JUnitXmlReporter;
        21: aload_0
        22: invokespecial #148                // Method java/lang/Object."<init>":()V
        25: aload_0
        26: invokestatic  #152                // InterfaceMethod scala/Product.$init$:(Lscala/Product;)V
        29: aload_0
        30: iconst_0
        31: putfield      #46                 // Field errors:I
        34: aload_0
        35: iconst_0
        36: putfield      #51                 // Field failures:I
        39: aload_0
        40: lconst_0
        41: putfield      #54                 // Field time:J
        44: aload_0
        45: new           #154                // class scala/collection/mutable/ListBuffer
        48: dup
        49: invokespecial #155                // Method scala/collection/mutable/ListBuffer."<init>":()V
        52: putfield      #60                 // Field testcases:Lscala/collection/mutable/ListBuffer;
        55: return
      StackMapTable: number_of_entries = 1
        frame_type = 16 /* same */
      LineNumberTable:
        line 500: 0
        line 501: 29
        line 502: 34
        line 503: 39
        line 504: 44
        line 500: 55
      LocalVariableTable:
        Start  Length  Slot  Name   Signature
            0      56     0  this   Lorg/scalatest/tools/JUnitXmlReporter$Testsuite;
            0      56     1 $outer   Lorg/scalatest/tools/JUnitXmlReporter;
            0      56     2  name   Ljava/lang/String;
            0      56     3 timeStamp   J
    MethodParameters:
      Name                           Flags
      $outer                         final synthetic
      name                           final
      timeStamp                      final
}
InnerClasses:
  public #14= #11 of #13;                 // Testcase=class org/scalatest/tools/JUnitXmlReporter$Testcase of class org/scalatest/tools/JUnitXmlReporter
  public #15= #2 of #13;                  // Testsuite=class org/scalatest/tools/JUnitXmlReporter$Testsuite of class org/scalatest/tools/JUnitXmlReporter
SourceFile: "JUnitXmlReporter.scala"
  ScalaInlineInfo: length = 0x7C (unknown attribute)
   01 00 00 18 00 43 00 44 00 00 68 00 69 00 00 3D
   00 3E 00 00 47 00 26 00 00 4A 00 29 00 00 8B 00
   69 00 00 14 00 2C 00 00 2F 00 30 00 00 16 00 2C
   00 00 34 00 30 00 00 71 00 2C 00 00 10 00 26 00
   00 3F 00 40 00 00 4F 00 2C 00 00 50 00 51 00 00
   6B 00 6C 00 00 1D 00 1E 00 00 5D 00 1E 00 00 4D
   00 26 00 00 18 00 39 00 00 17 00 29 00 00 12 00
   29 00 00 37 00 38 00 00 86 00 26 00
  Scala: length = 0x0 (unknown attribute)

