Classfile /Users/mw/Projects/slang-braindump/.jar/jar11/assemble/slang-braindump/assemble/content/org/scalatest/tools/ParsedArgs$.class
  Last modified May 29, 2022; size 7714 bytes
  SHA-256 checksum 198d5e96b29b85f56f5981749135aa02f44cca759163990edd3e4920f9af55fb
  Compiled from "ParsedArgs.scala"
public final class org.scalatest.tools.ParsedArgs$ extends scala.runtime.AbstractFunction18<scala.collection.immutable.List<java.lang.String>, scala.collection.immutable.List<java.lang.String>, scala.collection.immutable.List<java.lang.String>, scala.collection.immutable.List<java.lang.String>, scala.collection.immutable.List<java.lang.String>, scala.collection.immutable.List<java.lang.String>, scala.collection.immutable.List<java.lang.String>, scala.collection.immutable.List<java.lang.String>, scala.collection.immutable.List<java.lang.String>, scala.collection.immutable.List<java.lang.String>, scala.collection.immutable.List<java.lang.String>, scala.collection.immutable.List<java.lang.String>, scala.Option<java.util.regex.Pattern>, scala.collection.immutable.List<java.lang.String>, scala.collection.immutable.List<java.lang.String>, scala.collection.immutable.List<java.lang.String>, scala.collection.immutable.List<java.lang.String>, scala.collection.immutable.List<java.lang.String>, org.scalatest.tools.ParsedArgs> implements java.io.Serializable
  minor version: 0
  major version: 52
  flags: (0x0031) ACC_PUBLIC, ACC_FINAL, ACC_SUPER
  this_class: #2                          // org/scalatest/tools/ParsedArgs$
  super_class: #5                         // scala/runtime/AbstractFunction18
  interfaces: 1, fields: 1, methods: 7, attributes: 4
Constant pool:
    #1 = Utf8               org/scalatest/tools/ParsedArgs$
    #2 = Class              #1            // org/scalatest/tools/ParsedArgs$
    #3 = Utf8               Lscala/runtime/AbstractFunction18<Lscala/collection/immutable/List<Ljava/lang/String;>;Lscala/collection/immutable/List<Ljava/lang/String;>;Lscala/collection/immutable/List<Ljava/lang/String;>;Lscala/collection/immutable/List<Ljava/lang/String;>;Lscala/collection/immutable/List<Ljava/lang/String;>;Lscala/collection/immutable/List<Ljava/lang/String;>;Lscala/collection/immutable/List<Ljava/lang/String;>;Lscala/collection/immutable/List<Ljava/lang/String;>;Lscala/collection/immutable/List<Ljava/lang/String;>;Lscala/collection/immutable/List<Ljava/lang/String;>;Lscala/collection/immutable/List<Ljava/lang/String;>;Lscala/collection/immutable/List<Ljava/lang/String;>;Lscala/Option<Ljava/util/regex/Pattern;>;Lscala/collection/immutable/List<Ljava/lang/String;>;Lscala/collection/immutable/List<Ljava/lang/String;>;Lscala/collection/immutable/List<Ljava/lang/String;>;Lscala/collection/immutable/List<Ljava/lang/String;>;Lscala/collection/immutable/List<Ljava/lang/String;>;Lorg/scalatest/tools/ParsedArgs;>;Ljava/io/Serializable;
    #4 = Utf8               scala/runtime/AbstractFunction18
    #5 = Class              #4            // scala/runtime/AbstractFunction18
    #6 = Utf8               java/io/Serializable
    #7 = Class              #6            // java/io/Serializable
    #8 = Utf8               ParsedArgs.scala
    #9 = Utf8               MODULE$
   #10 = Utf8               Lorg/scalatest/tools/ParsedArgs$;
   #11 = Utf8               <clinit>
   #12 = Utf8               ()V
   #13 = Utf8               <init>
   #14 = NameAndType        #13:#12       // "<init>":()V
   #15 = Methodref          #2.#14        // org/scalatest/tools/ParsedArgs$."<init>":()V
   #16 = NameAndType        #9:#10        // MODULE$:Lorg/scalatest/tools/ParsedArgs$;
   #17 = Fieldref           #2.#16        // org/scalatest/tools/ParsedArgs$.MODULE$:Lorg/scalatest/tools/ParsedArgs$;
   #18 = Utf8               toString
   #19 = Utf8               ()Ljava/lang/String;
   #20 = Utf8               ParsedArgs
   #21 = String             #20           // ParsedArgs
   #22 = Utf8               this
   #23 = Utf8               apply
   #24 = Utf8               (Lscala/collection/immutable/List;Lscala/collection/immutable/List;Lscala/collection/immutable/List;Lscala/collection/immutable/List;Lscala/collection/immutable/List;Lscala/collection/immutable/List;Lscala/collection/immutable/List;Lscala/collection/immutable/List;Lscala/collection/immutable/List;Lscala/collection/immutable/List;Lscala/collection/immutable/List;Lscala/collection/immutable/List;Lscala/Option;Lscala/collection/immutable/List;Lscala/collection/immutable/List;Lscala/collection/immutable/List;Lscala/collection/immutable/List;Lscala/collection/immutable/List;)Lorg/scalatest/tools/ParsedArgs;
   #25 = Utf8               (Lscala/collection/immutable/List<Ljava/lang/String;>;Lscala/collection/immutable/List<Ljava/lang/String;>;Lscala/collection/immutable/List<Ljava/lang/String;>;Lscala/collection/immutable/List<Ljava/lang/String;>;Lscala/collection/immutable/List<Ljava/lang/String;>;Lscala/collection/immutable/List<Ljava/lang/String;>;Lscala/collection/immutable/List<Ljava/lang/String;>;Lscala/collection/immutable/List<Ljava/lang/String;>;Lscala/collection/immutable/List<Ljava/lang/String;>;Lscala/collection/immutable/List<Ljava/lang/String;>;Lscala/collection/immutable/List<Ljava/lang/String;>;Lscala/collection/immutable/List<Ljava/lang/String;>;Lscala/Option<Ljava/util/regex/Pattern;>;Lscala/collection/immutable/List<Ljava/lang/String;>;Lscala/collection/immutable/List<Ljava/lang/String;>;Lscala/collection/immutable/List<Ljava/lang/String;>;Lscala/collection/immutable/List<Ljava/lang/String;>;Lscala/collection/immutable/List<Ljava/lang/String;>;)Lorg/scalatest/tools/ParsedArgs;
   #26 = Utf8               runpath
   #27 = Utf8               reporters
   #28 = Utf8               suites
   #29 = Utf8               tryAgains
   #30 = Utf8               junits
   #31 = Utf8               props
   #32 = Utf8               includes
   #33 = Utf8               excludes
   #34 = Utf8               concurrent
   #35 = Utf8               membersOnly
   #36 = Utf8               wildcard
   #37 = Utf8               testNGXMLFiles
   #38 = Utf8               genSuffixesPattern
   #39 = Utf8               chosenStyles
   #40 = Utf8               spanScaleFactor
   #41 = Utf8               testSortingReporterTimeout
   #42 = Utf8               slowpokeParams
   #43 = Utf8               seeds
   #44 = Utf8               org/scalatest/tools/ParsedArgs
   #45 = Class              #44           // org/scalatest/tools/ParsedArgs
   #46 = Utf8               (Lscala/collection/immutable/List;Lscala/collection/immutable/List;Lscala/collection/immutable/List;Lscala/collection/immutable/List;Lscala/collection/immutable/List;Lscala/collection/immutable/List;Lscala/collection/immutable/List;Lscala/collection/immutable/List;Lscala/collection/immutable/List;Lscala/collection/immutable/List;Lscala/collection/immutable/List;Lscala/collection/immutable/List;Lscala/Option;Lscala/collection/immutable/List;Lscala/collection/immutable/List;Lscala/collection/immutable/List;Lscala/collection/immutable/List;Lscala/collection/immutable/List;)V
   #47 = NameAndType        #13:#46       // "<init>":(Lscala/collection/immutable/List;Lscala/collection/immutable/List;Lscala/collection/immutable/List;Lscala/collection/immutable/List;Lscala/collection/immutable/List;Lscala/collection/immutable/List;Lscala/collection/immutable/List;Lscala/collection/immutable/List;Lscala/collection/immutable/List;Lscala/collection/immutable/List;Lscala/collection/immutable/List;Lscala/collection/immutable/List;Lscala/Option;Lscala/collection/immutable/List;Lscala/collection/immutable/List;Lscala/collection/immutable/List;Lscala/collection/immutable/List;Lscala/collection/immutable/List;)V
   #48 = Methodref          #45.#47       // org/scalatest/tools/ParsedArgs."<init>":(Lscala/collection/immutable/List;Lscala/collection/immutable/List;Lscala/collection/immutable/List;Lscala/collection/immutable/List;Lscala/collection/immutable/List;Lscala/collection/immutable/List;Lscala/collection/immutable/List;Lscala/collection/immutable/List;Lscala/collection/immutable/List;Lscala/collection/immutable/List;Lscala/collection/immutable/List;Lscala/collection/immutable/List;Lscala/Option;Lscala/collection/immutable/List;Lscala/collection/immutable/List;Lscala/collection/immutable/List;Lscala/collection/immutable/List;Lscala/collection/immutable/List;)V
   #49 = Utf8               Lscala/collection/immutable/List;
   #50 = Utf8               Lscala/Option;
   #51 = Utf8               unapply
   #52 = Utf8               (Lorg/scalatest/tools/ParsedArgs;)Lscala/Option;
   #53 = Utf8               (Lorg/scalatest/tools/ParsedArgs;)Lscala/Option<Lscala/Tuple18<Lscala/collection/immutable/List<Ljava/lang/String;>;Lscala/collection/immutable/List<Ljava/lang/String;>;Lscala/collection/immutable/List<Ljava/lang/String;>;Lscala/collection/immutable/List<Ljava/lang/String;>;Lscala/collection/immutable/List<Ljava/lang/String;>;Lscala/collection/immutable/List<Ljava/lang/String;>;Lscala/collection/immutable/List<Ljava/lang/String;>;Lscala/collection/immutable/List<Ljava/lang/String;>;Lscala/collection/immutable/List<Ljava/lang/String;>;Lscala/collection/immutable/List<Ljava/lang/String;>;Lscala/collection/immutable/List<Ljava/lang/String;>;Lscala/collection/immutable/List<Ljava/lang/String;>;Lscala/Option<Ljava/util/regex/Pattern;>;Lscala/collection/immutable/List<Ljava/lang/String;>;Lscala/collection/immutable/List<Ljava/lang/String;>;Lscala/collection/immutable/List<Ljava/lang/String;>;Lscala/collection/immutable/List<Ljava/lang/String;>;Lscala/collection/immutable/List<Ljava/lang/String;>;>;>;
   #54 = Utf8               x$0
   #55 = Utf8               scala/None$
   #56 = Class              #55           // scala/None$
   #57 = Utf8               Lscala/None$;
   #58 = NameAndType        #9:#57        // MODULE$:Lscala/None$;
   #59 = Fieldref           #56.#58       // scala/None$.MODULE$:Lscala/None$;
   #60 = Utf8               scala/Some
   #61 = Class              #60           // scala/Some
   #62 = Utf8               scala/Tuple18
   #63 = Class              #62           // scala/Tuple18
   #64 = Utf8               ()Lscala/collection/immutable/List;
   #65 = NameAndType        #26:#64       // runpath:()Lscala/collection/immutable/List;
   #66 = Methodref          #45.#65       // org/scalatest/tools/ParsedArgs.runpath:()Lscala/collection/immutable/List;
   #67 = NameAndType        #27:#64       // reporters:()Lscala/collection/immutable/List;
   #68 = Methodref          #45.#67       // org/scalatest/tools/ParsedArgs.reporters:()Lscala/collection/immutable/List;
   #69 = NameAndType        #28:#64       // suites:()Lscala/collection/immutable/List;
   #70 = Methodref          #45.#69       // org/scalatest/tools/ParsedArgs.suites:()Lscala/collection/immutable/List;
   #71 = NameAndType        #29:#64       // tryAgains:()Lscala/collection/immutable/List;
   #72 = Methodref          #45.#71       // org/scalatest/tools/ParsedArgs.tryAgains:()Lscala/collection/immutable/List;
   #73 = NameAndType        #30:#64       // junits:()Lscala/collection/immutable/List;
   #74 = Methodref          #45.#73       // org/scalatest/tools/ParsedArgs.junits:()Lscala/collection/immutable/List;
   #75 = NameAndType        #31:#64       // props:()Lscala/collection/immutable/List;
   #76 = Methodref          #45.#75       // org/scalatest/tools/ParsedArgs.props:()Lscala/collection/immutable/List;
   #77 = NameAndType        #32:#64       // includes:()Lscala/collection/immutable/List;
   #78 = Methodref          #45.#77       // org/scalatest/tools/ParsedArgs.includes:()Lscala/collection/immutable/List;
   #79 = NameAndType        #33:#64       // excludes:()Lscala/collection/immutable/List;
   #80 = Methodref          #45.#79       // org/scalatest/tools/ParsedArgs.excludes:()Lscala/collection/immutable/List;
   #81 = NameAndType        #34:#64       // concurrent:()Lscala/collection/immutable/List;
   #82 = Methodref          #45.#81       // org/scalatest/tools/ParsedArgs.concurrent:()Lscala/collection/immutable/List;
   #83 = NameAndType        #35:#64       // membersOnly:()Lscala/collection/immutable/List;
   #84 = Methodref          #45.#83       // org/scalatest/tools/ParsedArgs.membersOnly:()Lscala/collection/immutable/List;
   #85 = NameAndType        #36:#64       // wildcard:()Lscala/collection/immutable/List;
   #86 = Methodref          #45.#85       // org/scalatest/tools/ParsedArgs.wildcard:()Lscala/collection/immutable/List;
   #87 = NameAndType        #37:#64       // testNGXMLFiles:()Lscala/collection/immutable/List;
   #88 = Methodref          #45.#87       // org/scalatest/tools/ParsedArgs.testNGXMLFiles:()Lscala/collection/immutable/List;
   #89 = Utf8               ()Lscala/Option;
   #90 = NameAndType        #38:#89       // genSuffixesPattern:()Lscala/Option;
   #91 = Methodref          #45.#90       // org/scalatest/tools/ParsedArgs.genSuffixesPattern:()Lscala/Option;
   #92 = NameAndType        #39:#64       // chosenStyles:()Lscala/collection/immutable/List;
   #93 = Methodref          #45.#92       // org/scalatest/tools/ParsedArgs.chosenStyles:()Lscala/collection/immutable/List;
   #94 = NameAndType        #40:#64       // spanScaleFactor:()Lscala/collection/immutable/List;
   #95 = Methodref          #45.#94       // org/scalatest/tools/ParsedArgs.spanScaleFactor:()Lscala/collection/immutable/List;
   #96 = NameAndType        #41:#64       // testSortingReporterTimeout:()Lscala/collection/immutable/List;
   #97 = Methodref          #45.#96       // org/scalatest/tools/ParsedArgs.testSortingReporterTimeout:()Lscala/collection/immutable/List;
   #98 = NameAndType        #42:#64       // slowpokeParams:()Lscala/collection/immutable/List;
   #99 = Methodref          #45.#98       // org/scalatest/tools/ParsedArgs.slowpokeParams:()Lscala/collection/immutable/List;
  #100 = NameAndType        #43:#64       // seeds:()Lscala/collection/immutable/List;
  #101 = Methodref          #45.#100      // org/scalatest/tools/ParsedArgs.seeds:()Lscala/collection/immutable/List;
  #102 = Utf8               (Ljava/lang/Object;Ljava/lang/Object;Ljava/lang/Object;Ljava/lang/Object;Ljava/lang/Object;Ljava/lang/Object;Ljava/lang/Object;Ljava/lang/Object;Ljava/lang/Object;Ljava/lang/Object;Ljava/lang/Object;Ljava/lang/Object;Ljava/lang/Object;Ljava/lang/Object;Ljava/lang/Object;Ljava/lang/Object;Ljava/lang/Object;Ljava/lang/Object;)V
  #103 = NameAndType        #13:#102      // "<init>":(Ljava/lang/Object;Ljava/lang/Object;Ljava/lang/Object;Ljava/lang/Object;Ljava/lang/Object;Ljava/lang/Object;Ljava/lang/Object;Ljava/lang/Object;Ljava/lang/Object;Ljava/lang/Object;Ljava/lang/Object;Ljava/lang/Object;Ljava/lang/Object;Ljava/lang/Object;Ljava/lang/Object;Ljava/lang/Object;Ljava/lang/Object;Ljava/lang/Object;)V
  #104 = Methodref          #63.#103      // scala/Tuple18."<init>":(Ljava/lang/Object;Ljava/lang/Object;Ljava/lang/Object;Ljava/lang/Object;Ljava/lang/Object;Ljava/lang/Object;Ljava/lang/Object;Ljava/lang/Object;Ljava/lang/Object;Ljava/lang/Object;Ljava/lang/Object;Ljava/lang/Object;Ljava/lang/Object;Ljava/lang/Object;Ljava/lang/Object;Ljava/lang/Object;Ljava/lang/Object;Ljava/lang/Object;)V
  #105 = Utf8               (Ljava/lang/Object;)V
  #106 = NameAndType        #13:#105      // "<init>":(Ljava/lang/Object;)V
  #107 = Methodref          #61.#106      // scala/Some."<init>":(Ljava/lang/Object;)V
  #108 = Utf8               Lorg/scalatest/tools/ParsedArgs;
  #109 = Utf8               scala/Option
  #110 = Class              #109          // scala/Option
  #111 = Utf8               writeReplace
  #112 = Utf8               ()Ljava/lang/Object;
  #113 = Utf8               scala/runtime/ModuleSerializationProxy
  #114 = Class              #113          // scala/runtime/ModuleSerializationProxy
  #115 = Utf8               (Ljava/lang/Class;)V
  #116 = NameAndType        #13:#115      // "<init>":(Ljava/lang/Class;)V
  #117 = Methodref          #114.#116     // scala/runtime/ModuleSerializationProxy."<init>":(Ljava/lang/Class;)V
  #118 = Utf8               (Ljava/lang/Object;Ljava/lang/Object;Ljava/lang/Object;Ljava/lang/Object;Ljava/lang/Object;Ljava/lang/Object;Ljava/lang/Object;Ljava/lang/Object;Ljava/lang/Object;Ljava/lang/Object;Ljava/lang/Object;Ljava/lang/Object;Ljava/lang/Object;Ljava/lang/Object;Ljava/lang/Object;Ljava/lang/Object;Ljava/lang/Object;Ljava/lang/Object;)Ljava/lang/Object;
  #119 = Utf8               v1
  #120 = Utf8               v2
  #121 = Utf8               v3
  #122 = Utf8               v4
  #123 = Utf8               v5
  #124 = Utf8               v6
  #125 = Utf8               v7
  #126 = Utf8               v8
  #127 = Utf8               v9
  #128 = Utf8               v10
  #129 = Utf8               v11
  #130 = Utf8               v12
  #131 = Utf8               v13
  #132 = Utf8               v14
  #133 = Utf8               v15
  #134 = Utf8               v16
  #135 = Utf8               v17
  #136 = Utf8               v18
  #137 = Utf8               scala/collection/immutable/List
  #138 = Class              #137          // scala/collection/immutable/List
  #139 = NameAndType        #23:#24       // apply:(Lscala/collection/immutable/List;Lscala/collection/immutable/List;Lscala/collection/immutable/List;Lscala/collection/immutable/List;Lscala/collection/immutable/List;Lscala/collection/immutable/List;Lscala/collection/immutable/List;Lscala/collection/immutable/List;Lscala/collection/immutable/List;Lscala/collection/immutable/List;Lscala/collection/immutable/List;Lscala/collection/immutable/List;Lscala/Option;Lscala/collection/immutable/List;Lscala/collection/immutable/List;Lscala/collection/immutable/List;Lscala/collection/immutable/List;Lscala/collection/immutable/List;)Lorg/scalatest/tools/ParsedArgs;
  #140 = Methodref          #2.#139       // org/scalatest/tools/ParsedArgs$.apply:(Lscala/collection/immutable/List;Lscala/collection/immutable/List;Lscala/collection/immutable/List;Lscala/collection/immutable/List;Lscala/collection/immutable/List;Lscala/collection/immutable/List;Lscala/collection/immutable/List;Lscala/collection/immutable/List;Lscala/collection/immutable/List;Lscala/collection/immutable/List;Lscala/collection/immutable/List;Lscala/collection/immutable/List;Lscala/Option;Lscala/collection/immutable/List;Lscala/collection/immutable/List;Lscala/collection/immutable/List;Lscala/collection/immutable/List;Lscala/collection/immutable/List;)Lorg/scalatest/tools/ParsedArgs;
  #141 = Utf8               Ljava/lang/Object;
  #142 = Methodref          #5.#14        // scala/runtime/AbstractFunction18."<init>":()V
  #143 = Utf8               Code
  #144 = Utf8               LineNumberTable
  #145 = Utf8               LocalVariableTable
  #146 = Utf8               Signature
  #147 = Utf8               MethodParameters
  #148 = Utf8               StackMapTable
  #149 = Utf8               SourceFile
  #150 = Utf8               ScalaInlineInfo
  #151 = Utf8               Scala
{
  public static final org.scalatest.tools.ParsedArgs$ MODULE$;
    descriptor: Lorg/scalatest/tools/ParsedArgs$;
    flags: (0x0019) ACC_PUBLIC, ACC_STATIC, ACC_FINAL

  public static {};
    descriptor: ()V
    flags: (0x0009) ACC_PUBLIC, ACC_STATIC
    Code:
      stack=2, locals=0, args_size=0
         0: new           #2                  // class org/scalatest/tools/ParsedArgs$
         3: dup
         4: invokespecial #15                 // Method "<init>":()V
         7: putstatic     #17                 // Field MODULE$:Lorg/scalatest/tools/ParsedArgs$;
        10: return
      LineNumberTable:
        line 20: 0

  public final java.lang.String toString();
    descriptor: ()Ljava/lang/String;
    flags: (0x0011) ACC_PUBLIC, ACC_FINAL
    Code:
      stack=1, locals=1, args_size=1
         0: ldc           #21                 // String ParsedArgs
         2: areturn
      LineNumberTable:
        line 20: 0
      LocalVariableTable:
        Start  Length  Slot  Name   Signature
            0       3     0  this   Lorg/scalatest/tools/ParsedArgs$;

  public org.scalatest.tools.ParsedArgs apply(scala.collection.immutable.List<java.lang.String>, scala.collection.immutable.List<java.lang.String>, scala.collection.immutable.List<java.lang.String>, scala.collection.immutable.List<java.lang.String>, scala.collection.immutable.List<java.lang.String>, scala.collection.immutable.List<java.lang.String>, scala.collection.immutable.List<java.lang.String>, scala.collection.immutable.List<java.lang.String>, scala.collection.immutable.List<java.lang.String>, scala.collection.immutable.List<java.lang.String>, scala.collection.immutable.List<java.lang.String>, scala.collection.immutable.List<java.lang.String>, scala.Option<java.util.regex.Pattern>, scala.collection.immutable.List<java.lang.String>, scala.collection.immutable.List<java.lang.String>, scala.collection.immutable.List<java.lang.String>, scala.collection.immutable.List<java.lang.String>, scala.collection.immutable.List<java.lang.String>);
    descriptor: (Lscala/collection/immutable/List;Lscala/collection/immutable/List;Lscala/collection/immutable/List;Lscala/collection/immutable/List;Lscala/collection/immutable/List;Lscala/collection/immutable/List;Lscala/collection/immutable/List;Lscala/collection/immutable/List;Lscala/collection/immutable/List;Lscala/collection/immutable/List;Lscala/collection/immutable/List;Lscala/collection/immutable/List;Lscala/Option;Lscala/collection/immutable/List;Lscala/collection/immutable/List;Lscala/collection/immutable/List;Lscala/collection/immutable/List;Lscala/collection/immutable/List;)Lorg/scalatest/tools/ParsedArgs;
    flags: (0x0001) ACC_PUBLIC
    Code:
      stack=20, locals=19, args_size=19
         0: new           #45                 // class org/scalatest/tools/ParsedArgs
         3: dup
         4: aload_1
         5: aload_2
         6: aload_3
         7: aload         4
         9: aload         5
        11: aload         6
        13: aload         7
        15: aload         8
        17: aload         9
        19: aload         10
        21: aload         11
        23: aload         12
        25: aload         13
        27: aload         14
        29: aload         15
        31: aload         16
        33: aload         17
        35: aload         18
        37: invokespecial #48                 // Method org/scalatest/tools/ParsedArgs."<init>":(Lscala/collection/immutable/List;Lscala/collection/immutable/List;Lscala/collection/immutable/List;Lscala/collection/immutable/List;Lscala/collection/immutable/List;Lscala/collection/immutable/List;Lscala/collection/immutable/List;Lscala/collection/immutable/List;Lscala/collection/immutable/List;Lscala/collection/immutable/List;Lscala/collection/immutable/List;Lscala/collection/immutable/List;Lscala/Option;Lscala/collection/immutable/List;Lscala/collection/immutable/List;Lscala/collection/immutable/List;Lscala/collection/immutable/List;Lscala/collection/immutable/List;)V
        40: areturn
      LineNumberTable:
        line 20: 0
      LocalVariableTable:
        Start  Length  Slot  Name   Signature
            0      41     0  this   Lorg/scalatest/tools/ParsedArgs$;
            0      41     1 runpath   Lscala/collection/immutable/List;
            0      41     2 reporters   Lscala/collection/immutable/List;
            0      41     3 suites   Lscala/collection/immutable/List;
            0      41     4 tryAgains   Lscala/collection/immutable/List;
            0      41     5 junits   Lscala/collection/immutable/List;
            0      41     6 props   Lscala/collection/immutable/List;
            0      41     7 includes   Lscala/collection/immutable/List;
            0      41     8 excludes   Lscala/collection/immutable/List;
            0      41     9 concurrent   Lscala/collection/immutable/List;
            0      41    10 membersOnly   Lscala/collection/immutable/List;
            0      41    11 wildcard   Lscala/collection/immutable/List;
            0      41    12 testNGXMLFiles   Lscala/collection/immutable/List;
            0      41    13 genSuffixesPattern   Lscala/Option;
            0      41    14 chosenStyles   Lscala/collection/immutable/List;
            0      41    15 spanScaleFactor   Lscala/collection/immutable/List;
            0      41    16 testSortingReporterTimeout   Lscala/collection/immutable/List;
            0      41    17 slowpokeParams   Lscala/collection/immutable/List;
            0      41    18 seeds   Lscala/collection/immutable/List;
    Signature: #25                          // (Lscala/collection/immutable/List<Ljava/lang/String;>;Lscala/collection/immutable/List<Ljava/lang/String;>;Lscala/collection/immutable/List<Ljava/lang/String;>;Lscala/collection/immutable/List<Ljava/lang/String;>;Lscala/collection/immutable/List<Ljava/lang/String;>;Lscala/collection/immutable/List<Ljava/lang/String;>;Lscala/collection/immutable/List<Ljava/lang/String;>;Lscala/collection/immutable/List<Ljava/lang/String;>;Lscala/collection/immutable/List<Ljava/lang/String;>;Lscala/collection/immutable/List<Ljava/lang/String;>;Lscala/collection/immutable/List<Ljava/lang/String;>;Lscala/collection/immutable/List<Ljava/lang/String;>;Lscala/Option<Ljava/util/regex/Pattern;>;Lscala/collection/immutable/List<Ljava/lang/String;>;Lscala/collection/immutable/List<Ljava/lang/String;>;Lscala/collection/immutable/List<Ljava/lang/String;>;Lscala/collection/immutable/List<Ljava/lang/String;>;Lscala/collection/immutable/List<Ljava/lang/String;>;)Lorg/scalatest/tools/ParsedArgs;
    MethodParameters:
      Name                           Flags
      runpath                        final
      reporters                      final
      suites                         final
      tryAgains                      final
      junits                         final
      props                          final
      includes                       final
      excludes                       final
      concurrent                     final
      membersOnly                    final
      wildcard                       final
      testNGXMLFiles                 final
      genSuffixesPattern             final
      chosenStyles                   final
      spanScaleFactor                final
      testSortingReporterTimeout     final
      slowpokeParams                 final
      seeds                          final

  public scala.Option<scala.Tuple18<scala.collection.immutable.List<java.lang.String>, scala.collection.immutable.List<java.lang.String>, scala.collection.immutable.List<java.lang.String>, scala.collection.immutable.List<java.lang.String>, scala.collection.immutable.List<java.lang.String>, scala.collection.immutable.List<java.lang.String>, scala.collection.immutable.List<java.lang.String>, scala.collection.immutable.List<java.lang.String>, scala.collection.immutable.List<java.lang.String>, scala.collection.immutable.List<java.lang.String>, scala.collection.immutable.List<java.lang.String>, scala.collection.immutable.List<java.lang.String>, scala.Option<java.util.regex.Pattern>, scala.collection.immutable.List<java.lang.String>, scala.collection.immutable.List<java.lang.String>, scala.collection.immutable.List<java.lang.String>, scala.collection.immutable.List<java.lang.String>, scala.collection.immutable.List<java.lang.String>>> unapply(org.scalatest.tools.ParsedArgs);
    descriptor: (Lorg/scalatest/tools/ParsedArgs;)Lscala/Option;
    flags: (0x0001) ACC_PUBLIC
    Code:
      stack=22, locals=2, args_size=2
         0: aload_1
         1: ifnonnull     10
         4: getstatic     #59                 // Field scala/None$.MODULE$:Lscala/None$;
         7: goto          96
        10: new           #61                 // class scala/Some
        13: dup
        14: new           #63                 // class scala/Tuple18
        17: dup
        18: aload_1
        19: invokevirtual #66                 // Method org/scalatest/tools/ParsedArgs.runpath:()Lscala/collection/immutable/List;
        22: aload_1
        23: invokevirtual #68                 // Method org/scalatest/tools/ParsedArgs.reporters:()Lscala/collection/immutable/List;
        26: aload_1
        27: invokevirtual #70                 // Method org/scalatest/tools/ParsedArgs.suites:()Lscala/collection/immutable/List;
        30: aload_1
        31: invokevirtual #72                 // Method org/scalatest/tools/ParsedArgs.tryAgains:()Lscala/collection/immutable/List;
        34: aload_1
        35: invokevirtual #74                 // Method org/scalatest/tools/ParsedArgs.junits:()Lscala/collection/immutable/List;
        38: aload_1
        39: invokevirtual #76                 // Method org/scalatest/tools/ParsedArgs.props:()Lscala/collection/immutable/List;
        42: aload_1
        43: invokevirtual #78                 // Method org/scalatest/tools/ParsedArgs.includes:()Lscala/collection/immutable/List;
        46: aload_1
        47: invokevirtual #80                 // Method org/scalatest/tools/ParsedArgs.excludes:()Lscala/collection/immutable/List;
        50: aload_1
        51: invokevirtual #82                 // Method org/scalatest/tools/ParsedArgs.concurrent:()Lscala/collection/immutable/List;
        54: aload_1
        55: invokevirtual #84                 // Method org/scalatest/tools/ParsedArgs.membersOnly:()Lscala/collection/immutable/List;
        58: aload_1
        59: invokevirtual #86                 // Method org/scalatest/tools/ParsedArgs.wildcard:()Lscala/collection/immutable/List;
        62: aload_1
        63: invokevirtual #88                 // Method org/scalatest/tools/ParsedArgs.testNGXMLFiles:()Lscala/collection/immutable/List;
        66: aload_1
        67: invokevirtual #91                 // Method org/scalatest/tools/ParsedArgs.genSuffixesPattern:()Lscala/Option;
        70: aload_1
        71: invokevirtual #93                 // Method org/scalatest/tools/ParsedArgs.chosenStyles:()Lscala/collection/immutable/List;
        74: aload_1
        75: invokevirtual #95                 // Method org/scalatest/tools/ParsedArgs.spanScaleFactor:()Lscala/collection/immutable/List;
        78: aload_1
        79: invokevirtual #97                 // Method org/scalatest/tools/ParsedArgs.testSortingReporterTimeout:()Lscala/collection/immutable/List;
        82: aload_1
        83: invokevirtual #99                 // Method org/scalatest/tools/ParsedArgs.slowpokeParams:()Lscala/collection/immutable/List;
        86: aload_1
        87: invokevirtual #101                // Method org/scalatest/tools/ParsedArgs.seeds:()Lscala/collection/immutable/List;
        90: invokespecial #104                // Method scala/Tuple18."<init>":(Ljava/lang/Object;Ljava/lang/Object;Ljava/lang/Object;Ljava/lang/Object;Ljava/lang/Object;Ljava/lang/Object;Ljava/lang/Object;Ljava/lang/Object;Ljava/lang/Object;Ljava/lang/Object;Ljava/lang/Object;Ljava/lang/Object;Ljava/lang/Object;Ljava/lang/Object;Ljava/lang/Object;Ljava/lang/Object;Ljava/lang/Object;Ljava/lang/Object;)V
        93: invokespecial #107                // Method scala/Some."<init>":(Ljava/lang/Object;)V
        96: areturn
      StackMapTable: number_of_entries = 2
        frame_type = 10 /* same */
        frame_type = 247 /* same_locals_1_stack_item_frame_extended */
          offset_delta = 85
          stack = [ class scala/Option ]
      LineNumberTable:
        line 20: 0
      LocalVariableTable:
        Start  Length  Slot  Name   Signature
            0      97     0  this   Lorg/scalatest/tools/ParsedArgs$;
            0      97     1   x$0   Lorg/scalatest/tools/ParsedArgs;
    Signature: #53                          // (Lorg/scalatest/tools/ParsedArgs;)Lscala/Option<Lscala/Tuple18<Lscala/collection/immutable/List<Ljava/lang/String;>;Lscala/collection/immutable/List<Ljava/lang/String;>;Lscala/collection/immutable/List<Ljava/lang/String;>;Lscala/collection/immutable/List<Ljava/lang/String;>;Lscala/collection/immutable/List<Ljava/lang/String;>;Lscala/collection/immutable/List<Ljava/lang/String;>;Lscala/collection/immutable/List<Ljava/lang/String;>;Lscala/collection/immutable/List<Ljava/lang/String;>;Lscala/collection/immutable/List<Ljava/lang/String;>;Lscala/collection/immutable/List<Ljava/lang/String;>;Lscala/collection/immutable/List<Ljava/lang/String;>;Lscala/collection/immutable/List<Ljava/lang/String;>;Lscala/Option<Ljava/util/regex/Pattern;>;Lscala/collection/immutable/List<Ljava/lang/String;>;Lscala/collection/immutable/List<Ljava/lang/String;>;Lscala/collection/immutable/List<Ljava/lang/String;>;Lscala/collection/immutable/List<Ljava/lang/String;>;Lscala/collection/immutable/List<Ljava/lang/String;>;>;>;
    MethodParameters:
      Name                           Flags
      x$0                            final

  private java.lang.Object writeReplace();
    descriptor: ()Ljava/lang/Object;
    flags: (0x0002) ACC_PRIVATE
    Code:
      stack=3, locals=1, args_size=1
         0: new           #114                // class scala/runtime/ModuleSerializationProxy
         3: dup
         4: ldc           #2                  // class org/scalatest/tools/ParsedArgs$
         6: invokespecial #117                // Method scala/runtime/ModuleSerializationProxy."<init>":(Ljava/lang/Class;)V
         9: areturn
      LineNumberTable:
        line 20: 0
      LocalVariableTable:
        Start  Length  Slot  Name   Signature
            0      10     0  this   Lorg/scalatest/tools/ParsedArgs$;

  public java.lang.Object apply(java.lang.Object, java.lang.Object, java.lang.Object, java.lang.Object, java.lang.Object, java.lang.Object, java.lang.Object, java.lang.Object, java.lang.Object, java.lang.Object, java.lang.Object, java.lang.Object, java.lang.Object, java.lang.Object, java.lang.Object, java.lang.Object, java.lang.Object, java.lang.Object);
    descriptor: (Ljava/lang/Object;Ljava/lang/Object;Ljava/lang/Object;Ljava/lang/Object;Ljava/lang/Object;Ljava/lang/Object;Ljava/lang/Object;Ljava/lang/Object;Ljava/lang/Object;Ljava/lang/Object;Ljava/lang/Object;Ljava/lang/Object;Ljava/lang/Object;Ljava/lang/Object;Ljava/lang/Object;Ljava/lang/Object;Ljava/lang/Object;Ljava/lang/Object;)Ljava/lang/Object;
    flags: (0x1041) ACC_PUBLIC, ACC_BRIDGE, ACC_SYNTHETIC
    Code:
      stack=19, locals=19, args_size=19
         0: aload_0
         1: aload_1
         2: checkcast     #138                // class scala/collection/immutable/List
         5: aload_2
         6: checkcast     #138                // class scala/collection/immutable/List
         9: aload_3
        10: checkcast     #138                // class scala/collection/immutable/List
        13: aload         4
        15: checkcast     #138                // class scala/collection/immutable/List
        18: aload         5
        20: checkcast     #138                // class scala/collection/immutable/List
        23: aload         6
        25: checkcast     #138                // class scala/collection/immutable/List
        28: aload         7
        30: checkcast     #138                // class scala/collection/immutable/List
        33: aload         8
        35: checkcast     #138                // class scala/collection/immutable/List
        38: aload         9
        40: checkcast     #138                // class scala/collection/immutable/List
        43: aload         10
        45: checkcast     #138                // class scala/collection/immutable/List
        48: aload         11
        50: checkcast     #138                // class scala/collection/immutable/List
        53: aload         12
        55: checkcast     #138                // class scala/collection/immutable/List
        58: aload         13
        60: checkcast     #110                // class scala/Option
        63: aload         14
        65: checkcast     #138                // class scala/collection/immutable/List
        68: aload         15
        70: checkcast     #138                // class scala/collection/immutable/List
        73: aload         16
        75: checkcast     #138                // class scala/collection/immutable/List
        78: aload         17
        80: checkcast     #138                // class scala/collection/immutable/List
        83: aload         18
        85: checkcast     #138                // class scala/collection/immutable/List
        88: invokevirtual #140                // Method apply:(Lscala/collection/immutable/List;Lscala/collection/immutable/List;Lscala/collection/immutable/List;Lscala/collection/immutable/List;Lscala/collection/immutable/List;Lscala/collection/immutable/List;Lscala/collection/immutable/List;Lscala/collection/immutable/List;Lscala/collection/immutable/List;Lscala/collection/immutable/List;Lscala/collection/immutable/List;Lscala/collection/immutable/List;Lscala/Option;Lscala/collection/immutable/List;Lscala/collection/immutable/List;Lscala/collection/immutable/List;Lscala/collection/immutable/List;Lscala/collection/immutable/List;)Lorg/scalatest/tools/ParsedArgs;
        91: areturn
      LineNumberTable:
        line 20: 0
      LocalVariableTable:
        Start  Length  Slot  Name   Signature
            0      92     0  this   Lorg/scalatest/tools/ParsedArgs$;
            0      92     1    v1   Ljava/lang/Object;
            0      92     2    v2   Ljava/lang/Object;
            0      92     3    v3   Ljava/lang/Object;
            0      92     4    v4   Ljava/lang/Object;
            0      92     5    v5   Ljava/lang/Object;
            0      92     6    v6   Ljava/lang/Object;
            0      92     7    v7   Ljava/lang/Object;
            0      92     8    v8   Ljava/lang/Object;
            0      92     9    v9   Ljava/lang/Object;
            0      92    10   v10   Ljava/lang/Object;
            0      92    11   v11   Ljava/lang/Object;
            0      92    12   v12   Ljava/lang/Object;
            0      92    13   v13   Ljava/lang/Object;
            0      92    14   v14   Ljava/lang/Object;
            0      92    15   v15   Ljava/lang/Object;
            0      92    16   v16   Ljava/lang/Object;
            0      92    17   v17   Ljava/lang/Object;
            0      92    18   v18   Ljava/lang/Object;
    MethodParameters:
      Name                           Flags
      v1                             final
      v2                             final
      v3                             final
      v4                             final
      v5                             final
      v6                             final
      v7                             final
      v8                             final
      v9                             final
      v10                            final
      v11                            final
      v12                            final
      v13                            final
      v14                            final
      v15                            final
      v16                            final
      v17                            final
      v18                            final

  private org.scalatest.tools.ParsedArgs$();
    descriptor: ()V
    flags: (0x0002) ACC_PRIVATE
    Code:
      stack=1, locals=1, args_size=1
         0: aload_0
         1: invokespecial #142                // Method scala/runtime/AbstractFunction18."<init>":()V
         4: return
      LineNumberTable:
        line 20: 0
      LocalVariableTable:
        Start  Length  Slot  Name   Signature
            0       5     0  this   Lorg/scalatest/tools/ParsedArgs$;
}
Signature: #3                           // Lscala/runtime/AbstractFunction18<Lscala/collection/immutable/List<Ljava/lang/String;>;Lscala/collection/immutable/List<Ljava/lang/String;>;Lscala/collection/immutable/List<Ljava/lang/String;>;Lscala/collection/immutable/List<Ljava/lang/String;>;Lscala/collection/immutable/List<Ljava/lang/String;>;Lscala/collection/immutable/List<Ljava/lang/String;>;Lscala/collection/immutable/List<Ljava/lang/String;>;Lscala/collection/immutable/List<Ljava/lang/String;>;Lscala/collection/immutable/List<Ljava/lang/String;>;Lscala/collection/immutable/List<Ljava/lang/String;>;Lscala/collection/immutable/List<Ljava/lang/String;>;Lscala/collection/immutable/List<Ljava/lang/String;>;Lscala/Option<Ljava/util/regex/Pattern;>;Lscala/collection/immutable/List<Ljava/lang/String;>;Lscala/collection/immutable/List<Ljava/lang/String;>;Lscala/collection/immutable/List<Ljava/lang/String;>;Lscala/collection/immutable/List<Ljava/lang/String;>;Lscala/collection/immutable/List<Ljava/lang/String;>;Lorg/scalatest/tools/ParsedArgs;>;Ljava/io/Serializable;
SourceFile: "ParsedArgs.scala"
  ScalaInlineInfo: length = 0x22 (unknown attribute)
   01 01 00 06 00 0D 00 0C 01 00 17 00 76 01 00 17
   00 18 01 00 12 00 13 01 00 33 00 34 01 00 6F 00
   70 01
  Scala: length = 0x0 (unknown attribute)

