Classfile /Users/mw/Projects/slang-braindump/.jar/jar11/assemble/slang-braindump/assemble/content/org/scalatest/tools/PresentShortStackTraces.class
  Last modified May 29, 2022; size 2104 bytes
  SHA-256 checksum d8069053a08a946fa0b3bd8a33ef6c943055546b092cd8242760bf10edac0f3c
  Compiled from "ReporterConfigParam.scala"
public final class org.scalatest.tools.PresentShortStackTraces
  minor version: 0
  major version: 52
  flags: (0x0031) ACC_PUBLIC, ACC_FINAL, ACC_SUPER
  this_class: #2                          // org/scalatest/tools/PresentShortStackTraces
  super_class: #4                         // java/lang/Object
  interfaces: 0, fields: 0, methods: 10, attributes: 3
Constant pool:
   #1 = Utf8               org/scalatest/tools/PresentShortStackTraces
   #2 = Class              #1             // org/scalatest/tools/PresentShortStackTraces
   #3 = Utf8               java/lang/Object
   #4 = Class              #3             // java/lang/Object
   #5 = Utf8               ReporterConfigParam.scala
   #6 = Utf8               Lscala/reflect/ScalaSignature;
   #7 = Utf8               bytes
   #8 = Utf8               \u0006\u0005m;aa\u0003\u0007\t\u00022\u0011bA\u0002\u000b\r\u0011\u0003cQ\u0003C\u0003-\u0003\u0011\u0005Q\u0006C\u0004/\u0003\u0005\u0005I\u0011I\u0018\t\u000fa\n\u0011\u0011!C\u0001s!9Q(AA\u0001\n\u0003q\u0004b\u0002#\u0002\u0003\u0003%\t%\u0012\u0005\b\u0019\u0006\t\t\u0011\"\u0001N\u0011\u001d\u0011\u0016!!A\u0005BMCq\u0001V\u0001\u0002\u0002\u0013\u0005S\u000bC\u0004W\u0003\u0005\u0005I\u0011B,\u0002/A\u0013Xm]3oiNCwN\u001d;Ti\u0006\u001c7\u000e\u0016:bG\u0016\u001c(BA\u0007\u000f\u0003\u0015!xn\u001c7t\u0015\ty\u0001#A\u0005tG\u0006d\u0017\r^3ti*\t\u0011#A\u0002pe\u001e\u0004\"aE\u0001\u000e\u00031\u0011q\u0003\u0015:fg\u0016tGo\u00155peR\u001cF/Y2l)J\f7-Z:\u0014\t\u00051\u0012d\b\t\u0003\']I!\u0001\u0007\u0007\u0003\'I+\u0007o\u001c:uKJ\u001cuN\u001c4jOB\u000b\'/Y7\u0011\u0005iiR\"A\u000e\u000b\u0003q\tQa]2bY\u0006L!AH\u000e\u0003\u000fA\u0013x\u000eZ;diB\u0011\u0001%\u000b\b\u0003C\u001dr!A\t\u0014\u000e\u0003\rR!\u0001J\u0013\u0002\rq\u0012xn\u001c;?\u0007\u0001I\u0011\u0001H\u0005\u0003Qm\tq\u0001]1dW\u0006<W-\u0003\u0002+W\ta1+\u001a:jC2L\'0\u00192mK*\u0011\u0001fG\u0001\u0007y%t\u0017\u000e\u001e \u0015\u0003I\tQ\u0002\u001d:pIV\u001cG\u000f\u0015:fM&DX#\u0001\u0019\u0011\u0005E2T\"\u0001\u001a\u000b\u0005M\"\u0014\u0001\u00027b]\u001eT\u0011!N\u0001\u0005U\u00064\u0018-\u0003\u00028e\t11\u000b\u001e:j]\u001e\fA\u0002\u001d:pIV\u001cG/\u0011:jif,\u0012A\u000f\t\u00035mJ!\u0001P\u000e\u0003\u0007%sG/\u0001\bqe>$Wo\u0019;FY\u0016lWM\u001c;\u0015\u0005}\u0012\u0005C\u0001\u000eA\u0013\t\t5DA\u0002B]fDqaQ\u0003\u0002\u0002\u0003\u0007!(A\u0002yIE\nq\u0002\u001d:pIV\u001cG/\u0013;fe\u0006$xN]\u000b\u0002\rB\u0019qIS \u000e\u0003!S!!S\u000e\u0002\u0015\r|G\u000e\\3di&|g.\u0003\u0002L\u0011\nA\u0011\n^3sCR|\'/\u0001\u0005dC:,\u0015/^1m)\tq\u0015\u000b\u0005\u0002\u001b\u001f&\u0011\u0001k\u0007\u0002\b\u0005>|G.Z1o\u0011\u001d\u0019u!!AA\u0002}\n\u0001\u0002[1tQ\u000e{G-\u001a\u000b\u0002u\u0005AAo\\*ue&tw\rF\u00011\u000319(/\u001b;f%\u0016\u0004H.Y2f)\u0005A\u0006CA\u0019Z\u0013\tQ&G\u0001\u0004PE*,7\r\u001e
   #9 = Utf8               toString
  #10 = Utf8               ()Ljava/lang/String;
  #11 = Utf8               org/scalatest/tools/PresentShortStackTraces$
  #12 = Class              #11            // org/scalatest/tools/PresentShortStackTraces$
  #13 = Utf8               MODULE$
  #14 = Utf8               Lorg/scalatest/tools/PresentShortStackTraces$;
  #15 = NameAndType        #13:#14        // MODULE$:Lorg/scalatest/tools/PresentShortStackTraces$;
  #16 = Fieldref           #12.#15        // org/scalatest/tools/PresentShortStackTraces$.MODULE$:Lorg/scalatest/tools/PresentShortStackTraces$;
  #17 = NameAndType        #9:#10         // toString:()Ljava/lang/String;
  #18 = Methodref          #12.#17        // org/scalatest/tools/PresentShortStackTraces$.toString:()Ljava/lang/String;
  #19 = Utf8               hashCode
  #20 = Utf8               ()I
  #21 = NameAndType        #19:#20        // hashCode:()I
  #22 = Methodref          #12.#21        // org/scalatest/tools/PresentShortStackTraces$.hashCode:()I
  #23 = Utf8               canEqual
  #24 = Utf8               (Ljava/lang/Object;)Z
  #25 = Utf8               x$1
  #26 = NameAndType        #23:#24        // canEqual:(Ljava/lang/Object;)Z
  #27 = Methodref          #12.#26        // org/scalatest/tools/PresentShortStackTraces$.canEqual:(Ljava/lang/Object;)Z
  #28 = Utf8               Ljava/lang/Object;
  #29 = Utf8               productIterator
  #30 = Utf8               ()Lscala/collection/Iterator;
  #31 = Utf8               ()Lscala/collection/Iterator<Ljava/lang/Object;>;
  #32 = NameAndType        #29:#30        // productIterator:()Lscala/collection/Iterator;
  #33 = Methodref          #12.#32        // org/scalatest/tools/PresentShortStackTraces$.productIterator:()Lscala/collection/Iterator;
  #34 = Utf8               productElement
  #35 = Utf8               (I)Ljava/lang/Object;
  #36 = NameAndType        #34:#35        // productElement:(I)Ljava/lang/Object;
  #37 = Methodref          #12.#36        // org/scalatest/tools/PresentShortStackTraces$.productElement:(I)Ljava/lang/Object;
  #38 = Utf8               I
  #39 = Utf8               productArity
  #40 = NameAndType        #39:#20        // productArity:()I
  #41 = Methodref          #12.#40        // org/scalatest/tools/PresentShortStackTraces$.productArity:()I
  #42 = Utf8               productPrefix
  #43 = NameAndType        #42:#10        // productPrefix:()Ljava/lang/String;
  #44 = Methodref          #12.#43        // org/scalatest/tools/PresentShortStackTraces$.productPrefix:()Ljava/lang/String;
  #45 = Utf8               character
  #46 = NameAndType        #45:#10        // character:()Ljava/lang/String;
  #47 = Methodref          #12.#46        // org/scalatest/tools/PresentShortStackTraces$.character:()Ljava/lang/String;
  #48 = Utf8               productElementNames
  #49 = Utf8               ()Lscala/collection/Iterator<Ljava/lang/String;>;
  #50 = NameAndType        #48:#30        // productElementNames:()Lscala/collection/Iterator;
  #51 = Methodref          #12.#50        // org/scalatest/tools/PresentShortStackTraces$.productElementNames:()Lscala/collection/Iterator;
  #52 = Utf8               productElementName
  #53 = Utf8               (I)Ljava/lang/String;
  #54 = Utf8               n
  #55 = NameAndType        #52:#53        // productElementName:(I)Ljava/lang/String;
  #56 = Methodref          #12.#55        // org/scalatest/tools/PresentShortStackTraces$.productElementName:(I)Ljava/lang/String;
  #57 = Utf8               Code
  #58 = Utf8               LocalVariableTable
  #59 = Utf8               MethodParameters
  #60 = Utf8               Signature
  #61 = Utf8               SourceFile
  #62 = Utf8               RuntimeVisibleAnnotations
  #63 = Utf8               ScalaSig
{
  public static java.lang.String toString();
    descriptor: ()Ljava/lang/String;
    flags: (0x0009) ACC_PUBLIC, ACC_STATIC
    Code:
      stack=1, locals=0, args_size=0
         0: getstatic     #16                 // Field org/scalatest/tools/PresentShortStackTraces$.MODULE$:Lorg/scalatest/tools/PresentShortStackTraces$;
         3: invokevirtual #18                 // Method org/scalatest/tools/PresentShortStackTraces$.toString:()Ljava/lang/String;
         6: areturn

  public static int hashCode();
    descriptor: ()I
    flags: (0x0009) ACC_PUBLIC, ACC_STATIC
    Code:
      stack=1, locals=0, args_size=0
         0: getstatic     #16                 // Field org/scalatest/tools/PresentShortStackTraces$.MODULE$:Lorg/scalatest/tools/PresentShortStackTraces$;
         3: invokevirtual #22                 // Method org/scalatest/tools/PresentShortStackTraces$.hashCode:()I
         6: ireturn

  public static boolean canEqual(java.lang.Object);
    descriptor: (Ljava/lang/Object;)Z
    flags: (0x0009) ACC_PUBLIC, ACC_STATIC
    Code:
      stack=2, locals=1, args_size=1
         0: getstatic     #16                 // Field org/scalatest/tools/PresentShortStackTraces$.MODULE$:Lorg/scalatest/tools/PresentShortStackTraces$;
         3: aload_0
         4: invokevirtual #27                 // Method org/scalatest/tools/PresentShortStackTraces$.canEqual:(Ljava/lang/Object;)Z
         7: ireturn
      LocalVariableTable:
        Start  Length  Slot  Name   Signature
            0       8     0   x$1   Ljava/lang/Object;
    MethodParameters:
      Name                           Flags
      x$1                            final

  public static scala.collection.Iterator<java.lang.Object> productIterator();
    descriptor: ()Lscala/collection/Iterator;
    flags: (0x0009) ACC_PUBLIC, ACC_STATIC
    Code:
      stack=1, locals=0, args_size=0
         0: getstatic     #16                 // Field org/scalatest/tools/PresentShortStackTraces$.MODULE$:Lorg/scalatest/tools/PresentShortStackTraces$;
         3: invokevirtual #33                 // Method org/scalatest/tools/PresentShortStackTraces$.productIterator:()Lscala/collection/Iterator;
         6: areturn
    Signature: #31                          // ()Lscala/collection/Iterator<Ljava/lang/Object;>;

  public static java.lang.Object productElement(int);
    descriptor: (I)Ljava/lang/Object;
    flags: (0x0009) ACC_PUBLIC, ACC_STATIC
    Code:
      stack=2, locals=1, args_size=1
         0: getstatic     #16                 // Field org/scalatest/tools/PresentShortStackTraces$.MODULE$:Lorg/scalatest/tools/PresentShortStackTraces$;
         3: iload_0
         4: invokevirtual #37                 // Method org/scalatest/tools/PresentShortStackTraces$.productElement:(I)Ljava/lang/Object;
         7: areturn
      LocalVariableTable:
        Start  Length  Slot  Name   Signature
            0       8     0   x$1   I
    MethodParameters:
      Name                           Flags
      x$1                            final

  public static int productArity();
    descriptor: ()I
    flags: (0x0009) ACC_PUBLIC, ACC_STATIC
    Code:
      stack=1, locals=0, args_size=0
         0: getstatic     #16                 // Field org/scalatest/tools/PresentShortStackTraces$.MODULE$:Lorg/scalatest/tools/PresentShortStackTraces$;
         3: invokevirtual #41                 // Method org/scalatest/tools/PresentShortStackTraces$.productArity:()I
         6: ireturn

  public static java.lang.String productPrefix();
    descriptor: ()Ljava/lang/String;
    flags: (0x0009) ACC_PUBLIC, ACC_STATIC
    Code:
      stack=1, locals=0, args_size=0
         0: getstatic     #16                 // Field org/scalatest/tools/PresentShortStackTraces$.MODULE$:Lorg/scalatest/tools/PresentShortStackTraces$;
         3: invokevirtual #44                 // Method org/scalatest/tools/PresentShortStackTraces$.productPrefix:()Ljava/lang/String;
         6: areturn

  public static java.lang.String character();
    descriptor: ()Ljava/lang/String;
    flags: (0x0009) ACC_PUBLIC, ACC_STATIC
    Code:
      stack=1, locals=0, args_size=0
         0: getstatic     #16                 // Field org/scalatest/tools/PresentShortStackTraces$.MODULE$:Lorg/scalatest/tools/PresentShortStackTraces$;
         3: invokevirtual #47                 // Method org/scalatest/tools/PresentShortStackTraces$.character:()Ljava/lang/String;
         6: areturn

  public static scala.collection.Iterator<java.lang.String> productElementNames();
    descriptor: ()Lscala/collection/Iterator;
    flags: (0x0009) ACC_PUBLIC, ACC_STATIC
    Code:
      stack=1, locals=0, args_size=0
         0: getstatic     #16                 // Field org/scalatest/tools/PresentShortStackTraces$.MODULE$:Lorg/scalatest/tools/PresentShortStackTraces$;
         3: invokevirtual #51                 // Method org/scalatest/tools/PresentShortStackTraces$.productElementNames:()Lscala/collection/Iterator;
         6: areturn
    Signature: #49                          // ()Lscala/collection/Iterator<Ljava/lang/String;>;

  public static java.lang.String productElementName(int);
    descriptor: (I)Ljava/lang/String;
    flags: (0x0009) ACC_PUBLIC, ACC_STATIC
    Code:
      stack=2, locals=1, args_size=1
         0: getstatic     #16                 // Field org/scalatest/tools/PresentShortStackTraces$.MODULE$:Lorg/scalatest/tools/PresentShortStackTraces$;
         3: iload_0
         4: invokevirtual #56                 // Method org/scalatest/tools/PresentShortStackTraces$.productElementName:(I)Ljava/lang/String;
         7: areturn
      LocalVariableTable:
        Start  Length  Slot  Name   Signature
            0       8     0     n   I
    MethodParameters:
      Name                           Flags
      n                              final
}
SourceFile: "ReporterConfigParam.scala"
RuntimeVisibleAnnotations:
  0: #6(#7=s#8)
    scala.reflect.ScalaSignature(
      bytes="\u0006\u0005m;aa\u0003\u0007\t\u00022\u0011bA\u0002\u000b\r\u0011\u0003cQ\u0003C\u0003-\u0003\u0011\u0005Q\u0006C\u0004/\u0003\u0005\u0005I\u0011I\u0018\t\u000fa\n\u0011\u0011!C\u0001s!9Q(AA\u0001\n\u0003q\u0004b\u0002#\u0002\u0003\u0003%\t%\u0012\u0005\b\u0019\u0006\t\t\u0011\"\u0001N\u0011\u001d\u0011\u0016!!A\u0005BMCq\u0001V\u0001\u0002\u0002\u0013\u0005S\u000bC\u0004W\u0003\u0005\u0005I\u0011B,\u0002/A\u0013Xm]3oiNCwN\u001d;Ti\u0006\u001c7\u000e\u0016:bG\u0016\u001c(BA\u0007\u000f\u0003\u0015!xn\u001c7t\u0015\ty\u0001#A\u0005tG\u0006d\u0017\r^3ti*\t\u0011#A\u0002pe\u001e\u0004\"aE\u0001\u000e\u00031\u0011q\u0003\u0015:fg\u0016tGo\u00155peR\u001cF/Y2l)J\f7-Z:\u0014\t\u00051\u0012d\b\t\u0003\']I!\u0001\u0007\u0007\u0003\'I+\u0007o\u001c:uKJ\u001cuN\u001c4jOB\u000b\'/Y7\u0011\u0005iiR\"A\u000e\u000b\u0003q\tQa]2bY\u0006L!AH\u000e\u0003\u000fA\u0013x\u000eZ;diB\u0011\u0001%\u000b\b\u0003C\u001dr!A\t\u0014\u000e\u0003\rR!\u0001J\u0013\u0002\rq\u0012xn\u001c;?\u0007\u0001I\u0011\u0001H\u0005\u0003Qm\tq\u0001]1dW\u0006<W-\u0003\u0002+W\ta1+\u001a:jC2L\'0\u00192mK*\u0011\u0001fG\u0001\u0007y%t\u0017\u000e\u001e \u0015\u0003I\tQ\u0002\u001d:pIV\u001cG\u000f\u0015:fM&DX#\u0001\u0019\u0011\u0005E2T\"\u0001\u001a\u000b\u0005M\"\u0014\u0001\u00027b]\u001eT\u0011!N\u0001\u0005U\u00064\u0018-\u0003\u00028e\t11\u000b\u001e:j]\u001e\fA\u0002\u001d:pIV\u001cG/\u0011:jif,\u0012A\u000f\t\u00035mJ!\u0001P\u000e\u0003\u0007%sG/\u0001\bqe>$Wo\u0019;FY\u0016lWM\u001c;\u0015\u0005}\u0012\u0005C\u0001\u000eA\u0013\t\t5DA\u0002B]fDqaQ\u0003\u0002\u0002\u0003\u0007!(A\u0002yIE\nq\u0002\u001d:pIV\u001cG/\u0013;fe\u0006$xN]\u000b\u0002\rB\u0019qIS \u000e\u0003!S!!S\u000e\u0002\u0015\r|G\u000e\\3di&|g.\u0003\u0002L\u0011\nA\u0011\n^3sCR|\'/\u0001\u0005dC:,\u0015/^1m)\tq\u0015\u000b\u0005\u0002\u001b\u001f&\u0011\u0001k\u0007\u0002\b\u0005>|G.Z1o\u0011\u001d\u0019u!!AA\u0002}\n\u0001\u0002[1tQ\u000e{G-\u001a\u000b\u0002u\u0005AAo\\*ue&tw\rF\u00011\u000319(/\u001b;f%\u0016\u0004H.Y2f)\u0005A\u0006CA\u0019Z\u0013\tQ&G\u0001\u0004PE*,7\r\u001e"
    )
  ScalaSig: length = 0x3 (unknown attribute)
   05 02 00
