Classfile /Users/mw/Projects/slang-braindump/.jar/jar11/assemble/slang-braindump/assemble/content/org/scalatest/tools/PrettyPrinter.class
  Last modified May 29, 2022; size 26589 bytes
  SHA-256 checksum 19c42f36821486aa3ae341728d123d1bcf382df30e6b2b843a927b565d219bc7
  Compiled from "PrettyPrinter.scala"
public class org.scalatest.tools.PrettyPrinter
  minor version: 0
  major version: 52
  flags: (0x0021) ACC_PUBLIC, ACC_SUPER
  this_class: #2                          // org/scalatest/tools/PrettyPrinter
  super_class: #4                         // java/lang/Object
  interfaces: 0, fields: 9, methods: 59, attributes: 6
Constant pool:
    #1 = Utf8               org/scalatest/tools/PrettyPrinter
    #2 = Class              #1            // org/scalatest/tools/PrettyPrinter
    #3 = Utf8               java/lang/Object
    #4 = Class              #3            // java/lang/Object
    #5 = Utf8               PrettyPrinter.scala
    #6 = Utf8               Lscala/reflect/ScalaSignature;
    #7 = Utf8               bytes
    #8 = Utf8               \u0006\u0005\r\rc!B/_\u0001y#\u0007\u0002C6\u0001\u0005\u0003\u0005\u000b\u0011B7\t\u0011A\u0004!\u0011!Q\u0001\n5D\u0001\"\u001d\u0001\u0003\u0002\u0003\u0006IA\u001d\u0005\u0006k\u0002!\tA\u001e\u0005\u0006k\u0002!\t\u0001 \u0005\t\u007f\u0002\u0011\r\u0011\"\u0001\u0002\u0002!A\u0011\u0011\u0004\u0001!\u0002\u0013\t\u0019A\u0002\u0004\u0002\u001c\u0001\u0001\u0011Q\u0004\u0005\u0007k\"!\t!a\f\u0007\r\u0005U\u0002\u0001AA\u001c\u0011\u0019)(\u0002\"\u0001\u0002:\u001d9\u0011Q\b\u0001\t\u0002\u0006}baBA!\u0001!\u0005\u00151\t\u0005\u0007k6!\t!a\u0019\t\u000f\u0005\u0015T\u0002\"\u0011\u0002h!I\u0011qN\u0007\u0002\u0002\u0013\u0005\u0013\u0011\u000f\u0005\n\u0003gj\u0011\u0011!C\u0001\u0003kB\u0011\"a\u001e\u000e\u0003\u0003%\t!!\u001f\t\u0013\u0005\u0015U\"!A\u0005B\u0005\u001d\u0005\"CAK\u001b\u0005\u0005I\u0011AAL\u0011%\tY*DA\u0001\n\u0003\niJ\u0002\u0004\u0002 \u0002\u0001\u0015\u0011\u0015\u0005\u000b\u0003G3\"Q3A\u0005\u0002\u0005U\u0004\"CAS-\tE\t\u0015!\u0003n\u0011)\t9K\u0006BK\u0002\u0013\u0005\u0011\u0011\u0016\u0005\u000b\u0003s3\"\u0011#Q\u0001\n\u0005-\u0006BB;\u0017\t\u0003\tY\fC\u0005\u0002DZ\t\t\u0011\"\u0001\u0002F\"I\u00111\u001a\f\u0012\u0002\u0013\u0005\u0011Q\u001a\u0005\n\u0003G4\u0012\u0013!C\u0001\u0003KD\u0011\"a\u001c\u0017\u0003\u0003%\t%!\u001d\t\u0013\u0005Md#!A\u0005\u0002\u0005U\u0004\"CA<-\u0005\u0005I\u0011AAu\u0011%\t)IFA\u0001\n\u0003\n9\tC\u0005\u0002\u0016Z\t\t\u0011\"\u0001\u0002n\"I\u0011\u0011\u001f\f\u0002\u0002\u0013\u0005\u00131\u001f\u0005\n\u000373\u0012\u0011!C!\u0003;C\u0011\"!\u001a\u0017\u0003\u0003%\t%a\u001a\t\u0013\u0005]h#!A\u0005B\u0005ex!CA\u007f\u0001\u0005\u0005\t\u0012AA\u0000\r%\ty\nAA\u0001\u0012\u0003\u0011\t\u0001\u0003\u0004vS\u0011\u0005!\u0011\u0004\u0005\n\u0003KJ\u0013\u0011!C#\u0003OB\u0011Ba\u0007*\u0003\u0003%\tI!\b\t\u0013\t\r\u0012&!A\u0005\u0002\n\u0015bA\u0002B\u001c\u0001\u0001\u0013I\u0004\u0003\u0006\u0002(:\u0012)\u001a!C\u0001\u0003SC!\"!//\u0005#\u0005\u000b\u0011BAV\u0011\u0019)h\u0006\"\u0001\u0003<!I\u00111\u0019\u0018\u0002\u0002\u0013\u0005!\u0011\t\u0005\n\u0003\u0017t\u0013\u0013!C\u0001\u0003KD\u0011\"a\u001c/\u0003\u0003%\t%!\u001d\t\u0013\u0005Md&!A\u0005\u0002\u0005U\u0004\"CA<]\u0005\u0005I\u0011\u0001B#\u0011%\t)ILA\u0001\n\u0003\n9\tC\u0005\u0002\u0016:\n\t\u0011\"\u0001\u0003J!I\u0011\u0011\u001f\u0018\u0002\u0002\u0013\u0005#Q\n\u0005\n\u00037s\u0013\u0011!C!\u0003;C\u0011\"!\u001a/\u0003\u0003%\t%a\u001a\t\u0013\u0005]h&!A\u0005B\tEs!\u0003B+\u0001\u0005\u0005\t\u0012\u0001B,\r%\u00119\u0004AA\u0001\u0012\u0003\u0011I\u0006\u0003\u0004v}\u0011\u0005!\u0011\r\u0005\n\u0003Kr\u0014\u0011!C#\u0003OB\u0011Ba\u0007?\u0003\u0003%\tIa\u0019\t\u0013\t\rb(!A\u0005\u0002\n\u001d\u0004\"\u0003B7\u0001\u0001\u0007I\u0011\u0003B8\u0011%\u00119\b\u0001a\u0001\n#\u0011I\b\u0003\u0005\u0003\u0004\u0002\u0001\u000b\u0015\u0002B9\u0011%\u0011)\t\u0001a\u0001\n#\t)\bC\u0005\u0003\b\u0002\u0001\r\u0011\"\u0005\u0003\n\"9!Q\u0012\u0001!B\u0013i\u0007b\u0002BH\u0001\u0011E!\u0011\u0013\u0005\b\u0005\'\u0003A\u0011\u0003BK\u0011\u001d\u0011i\n\u0001C\t\u0005?CqA!*\u0001\t#\u00119\u000bC\u0004\u0003.\u0002!\tB!%\t\u000f\t=\u0006\u0001\"\u0005\u00032\"9!Q\u0018\u0001\u0005\u0012\t}\u0006b\u0002Bh\u0001\u0011E!\u0011\u001b\u0005\b\u0005+\u0004A\u0011\u0003Bl\u0011\u001d\u0011Y\u000e\u0001C\t\u0005;DqAa9\u0001\t\u0013\u0011)\u000fC\u0004\u0003l\u0002!\tB!<\t\u000f\t-\b\u0001\"\u0005\u0003v\"91Q\u0001\u0001\u0005\u0002\r\u001d\u0001bBB\u0003\u0001\u0011\u00051Q\u0003\u0005\b\u0007\u000b\u0001A\u0011AB\u000f\u0011%\u0019\u0019\u0003AI\u0001\n\u0003\u0019)\u0003C\u0004\u0004*\u0001!\taa\u000b\t\u0013\re\u0002!%A\u0005\u0002\r\u0015\u0002bBB\u0015\u0001\u0011\u000511\b\u0002\u000e!J,G\u000f^=Qe&tG/\u001a:\u000b\u0005}\u0003\u0017!\u0002;p_2\u001c(BA1c\u0003%\u00198-\u00197bi\u0016\u001cHOC\u0001d\u0003\ry\'oZ\n\u0003\u0001\u0015\u0004\"AZ5\u000e\u0003\u001dT\u0011\u0001[\u0001\u0006g\u000e\fG.Y\u0005\u0003U\u001e\u0014a!\u00118z%\u00164\u0017!B<jIRD7\u0001\u0001\t\u0003M:L!a\\4\u0003\u0007%sG/\u0001\u0003ti\u0016\u0004\u0018!D7j]&l\u0017N_3F[B$\u0018\u0010\u0005\u0002gg&\u0011Ao\u001a\u0002\b\u0005>|G.Z1o\u0003\u0019a\u0014N\\5u}Q!q/\u001f>|!\tA\b!D\u0001_\u0011\u0015YG\u00011\u0001n\u0011\u0015\u0001H\u00011\u0001n\u0011\u0015\tH\u00011\u0001s)\r9XP \u0005\u0006W\u0016\u0001\r!\u001c\u0005\u0006a\u0016\u0001\r!\\\u0001\r[&t\u0017.\\5{K6{G-Z\u000b\u0003\u0003\u0007\u0001B!!\u0002\u0002\u00129!\u0011qAA\u0007\u001b\t\tIAC\u0002\u0002\f\u001d\f1\u0001_7m\u0013\u0011\ty!!\u0003\u0002\u00195Kg.[7ju\u0016lu\u000eZ3\n\t\u0005M\u0011Q\u0003\u0002\u0006-\u0006dW/Z\u0005\u0004\u0003/9\'aC#ok6,\'/\u0019;j_:\fQ\"\\5oS6L\'0Z\'pI\u0016\u0004#a\u0004\"s_.,g.\u0012=dKB$\u0018n\u001c8\u0014\u0007!\ty\u0002\u0005\u0003\u0002\"\u0005-RBAA\u0012\u0015\u0011\t)#a\n\u0002\t1\fgn\u001a\u0006\u0003\u0003S\tAA[1wC&!\u0011QFA\u0012\u0005%)\u0005pY3qi&|g\u000e\u0006\u0002\u00022A\u0019\u00111\u0007\u0005\u000e\u0003\u0001\u0011A!\u0013;f[N\u0011!\"\u001a\u000b\u0003\u0003w\u00012!a\r\u000b\u0003\u0015\u0011%/Z1l!\r\t\u0019$\u0004\u0002\u0006\u0005J,\u0017m[\n\b\u001b\u0005m\u0012QIA&!\r1\u0017qI\u0005\u0004\u0003\u0013:\'a\u0002)s_\u0012,8\r\u001e\t\u0005\u0003\u001b\niF\u0004\u0003\u0002P\u0005ec\u0002BA)\u0003/j!!a\u0015\u000b\u0007\u0005UC.\u0001\u0004=e>|GOP\u0005\u0002Q&\u0019\u00111L4\u0002\u000fA\f7m[1hK&!\u0011qLA1\u00051\u0019VM]5bY&T\u0018M\u00197f\u0015\r\tYf\u001a\u000b\u0003\u0003\u007f\t\u0001\u0002^8TiJLgn\u001a\u000b\u0003\u0003S\u0002B!!\t\u0002l%!\u0011QNA\u0012\u0005\u0019\u0019FO]5oO\u0006i\u0001O]8ek\u000e$\bK]3gSb,\"!!\u001b\u0002\u0019A\u0014x\u000eZ;di\u0006\u0013\u0018\u000e^=\u0016\u00035\fa\u0002\u001d:pIV\u001cG/\u00127f[\u0016tG\u000f\u0006\u0003\u0002|\u0005\u0005\u0005c\u00014\u0002~%\u0019\u0011qP4\u0003\u0007\u0005s\u0017\u0010\u0003\u0005\u0002\u0004J\t\t\u00111\u0001n\u0003\rAH%M\u0001\u0010aJ|G-^2u\u0013R,\'/\u0019;peV\u0011\u0011\u0011\u0012\t\u0007\u0003\u0017\u000b\t*a\u001f\u000e\u0005\u00055%bAAHO\u0006Q1m\u001c7mK\u000e$\u0018n\u001c8\n\t\u0005M\u0015Q\u0012\u0002\t\u0013R,\'/\u0019;pe\u0006A1-\u00198FcV\fG\u000eF\u0002s\u00033C\u0011\"a!\u0015\u0003\u0003\u0005\r!a\u001f\u0002\u0011!\f7\u000f[\"pI\u0016$\u0012!\u001c\u0002\u0004\u0005>D8c\u0002\f\u0002<\u0005\u0015\u00131J\u0001\u0004G>d\u0017\u0001B2pY\u0002\n\u0011a]\u000b\u0003\u0003W\u0003B!!,\u00026:!\u0011qVAY!\r\t\tfZ\u0005\u0004\u0003g;\u0017A\u0002)sK\u0012,g-\u0003\u0003\u0002n\u0005]&bAAZO\u0006\u00111\u000f\t\u000b\u0007\u0003{\u000by,!1\u0011\u0007\u0005Mb\u0003\u0003\u0004\u0002$n\u0001\r!\u001c\u0005\b\u0003O[\u0002\u0019AAV\u0003\u0011\u0019w\u000e]=\u0015\r\u0005u\u0016qYAe\u0011!\t\u0019\u000b\bI\u0001\u0002\u0004i\u0007\"CAT9A\u0005\t\u0019AAV\u00039\u0019w\u000e]=%I\u00164\u0017-\u001e7uIE*\"!a4+\u00075\f\tn\u000b\u0002\u0002TB!\u0011Q[Ap\u001b\t\t9N\u0003\u0003\u0002Z\u0006m\u0017!C;oG\",7m[3e\u0015\r\tinZ\u0001\u000bC:tw\u000e^1uS>t\u0017\u0002BAq\u0003/\u0014\u0011#\u001e8dQ\u0016\u001c7.\u001a3WCJL\u0017M\\2f\u00039\u0019w\u000e]=%I\u00164\u0017-\u001e7uII*\"!a:+\t\u0005-\u0016\u0011\u001b\u000b\u0005\u0003w\nY\u000f\u0003\u0005\u0002\u0004\u0006\n\t\u00111\u0001n)\r\u0011\u0018q\u001e\u0005\n\u0003\u0007\u001b\u0013\u0011!a\u0001\u0003w\n!\u0003\u001d:pIV\u001cG/\u00127f[\u0016tGOT1nKR!\u0011\u0011NA{\u0011!\t\u0019\tJA\u0001\u0002\u0004i\u0017AB3rk\u0006d7\u000fF\u0002s\u0003wD\u0011\"a!(\u0003\u0003\u0005\r!a\u001f\u0002\u0007\t{\u0007\u0010E\u0002\u00024%\u001aR!\u000bB\u0002\u0005\u001f\u0001\u0012B!\u0002\u0003\f5\fY+!0\u000e\u0005\t\u001d!b\u0001B\u0005O\u00069!/\u001e8uS6,\u0017\u0002\u0002B\u0007\u0005\u000f\u0011\u0011#\u00112tiJ\f7\r\u001e$v]\u000e$\u0018n\u001c83!\u0011\u0011\tBa\u0006\u000e\u0005\tM!\u0002\u0002B\u000b\u0003O\t!![8\n\t\u0005}#1\u0003\u000b\u0003\u0003\u007f\fQ!\u00199qYf$b!!0\u0003 \t\u0005\u0002BBARY\u0001\u0007Q\u000eC\u0004\u0002(2\u0002\r!a+\u0002\u000fUt\u0017\r\u001d9msR!!q\u0005B\u001a!\u00151\'\u0011\u0006B\u0017\u0013\r\u0011Yc\u001a\u0002\u0007\u001fB$\u0018n\u001c8\u0011\r\u0019\u0014y#\\AV\u0013\r\u0011\td\u001a\u0002\u0007)V\u0004H.\u001a\u001a\t\u0013\tUR&!AA\u0002\u0005u\u0016a\u0001=%a\t!\u0001+\u0019:b\'\u001dq\u00131HA#\u0003\u0017\"BA!\u0010\u0003@A\u0019\u00111\u0007\u0018\t\u000f\u0005\u001d\u0016\u00071\u0001\u0002,R!!Q\bB\"\u0011%\t9K\rI\u0001\u0002\u0004\tY\u000b\u0006\u0003\u0002|\t\u001d\u0003\u0002CABm\u0005\u0005\t\u0019A7\u0015\u0007I\u0014Y\u0005C\u0005\u0002\u0004b\n\t\u00111\u0001\u0002|Q!\u0011\u0011\u000eB(\u0011!\t\u0019)OA\u0001\u0002\u0004iGc\u0001:\u0003T!I\u00111\u0011\u001f\u0002\u0002\u0003\u0007\u00111P\u0001\u0005!\u0006\u0014\u0018\rE\u0002\u00024y\u001aRA\u0010B.\u0005\u001f\u0001\u0002B!\u0002\u0003^\u0005-&QH\u0005\u0005\u0005?\u00129AA\tBEN$(/Y2u\rVt7\r^5p]F\"\"Aa\u0016\u0015\t\tu\"Q\r\u0005\b\u0003O\u000b\u0005\u0019AAV)\u0011\u0011IGa\u001b\u0011\u000b\u0019\u0014I#a+\t\u0013\tU\")!AA\u0002\tu\u0012!B5uK6\u001cXC\u0001B9!\u0019\tiEa\u001d\u0002<%!!QOA1\u0005\u0011a\u0015n\u001d;\u0002\u0013%$X-\\:`I\u0015\fH\u0003\u0002B>\u0005\u0003\u00032A\u001aB?\u0013\r\u0011yh\u001a\u0002\u0005+:LG\u000fC\u0005\u0002\u0004\u0012\u000b\t\u00111\u0001\u0003r\u00051\u0011\u000e^3ng\u0002\n1aY;s\u0003\u001d\u0019WO]0%KF$BAa\u001f\u0003\f\"A\u00111Q$\u0002\u0002\u0003\u0007Q.\u0001\u0003dkJ\u0004\u0013!\u0002:fg\u0016$HC\u0001B>\u0003\r\u0019W\u000f\u001e\u000b\u0007\u0005c\u00129J!\'\t\u000f\u0005\u001d&\n1\u0001\u0002,\"1!1\u0014&A\u00025\f1!\u001b8e\u0003\u001di\u0017m[3C_b$bAa\u001f\u0003\"\n\r\u0006B\u0002BN\u0017\u0002\u0007Q\u000eC\u0004\u0002(.\u0003\r!a+\u0002\u00115\f7.\u001a)be\u0006$bAa\u001f\u0003*\n-\u0006B\u0002BN\u0019\u0002\u0007Q\u000eC\u0004\u0002(2\u0003\r!a+\u0002\u00135\f7.\u001a\"sK\u0006\\\u0017a\u00027fC\u001a$\u0016m\u001a\u000b\u0005\u0003W\u0013\u0019\fC\u0004\u00036:\u0003\rAa.\u0002\u00039\u0004B!a\u0002\u0003:&!!1XA\u0005\u0005\u0011qu\u000eZ3\u0002\u0011M$\u0018M\u001d;UC\u001e$bA!1\u0003D\n\u0015\u0007C\u00024\u00030\u0005-V\u000eC\u0004\u00036>\u0003\rAa.\t\u000f\t\u001dw\n1\u0001\u0003J\u00061\u0001o]2pa\u0016\u0004B!a\u0002\u0003L&!!QZA\u0005\u0005Aq\u0015-\\3ta\u0006\u001cWMQ5oI&tw-\u0001\u0004f]\u0012$\u0016m\u001a\u000b\u0005\u0003W\u0013\u0019\u000eC\u0004\u00036B\u0003\rAa.\u0002#\rD\u0017\u000e\u001c3sK:\f%/\u001a\'fCZ,7\u000fF\u0002s\u00053DqA!.R\u0001\u0004\u00119,\u0001\u0003gSR\u001cHc\u0001:\u0003`\"9!\u0011\u001d*A\u0002\u0005-\u0016\u0001\u0002;fgR\f!\u0002Z8Qe\u0016\u001cXM\u001d<f)\r\u0011(q\u001d\u0005\b\u0005S\u001c\u0006\u0019\u0001B\\\u0003\u0011qw\u000eZ3\u0002\u0011Q\u0014\u0018M^3sg\u0016$\u0002Ba\u001f\u0003p\nE(1\u001f\u0005\b\u0005S$\u0006\u0019\u0001B\\\u0011\u001d\u00119\r\u0016a\u0001\u0005\u0013DaAa\'U\u0001\u0004iG\u0003\u0003B>\u0005o\u0014ypa\u0001\t\u000f\teX\u000b1\u0001\u0003|\u0006\u0011\u0011\u000e\u001e\t\u0007\u0003\u001b\u0012iPa.\n\t\u0005M\u0015\u0011\r\u0005\b\u0007\u0003)\u0006\u0019\u0001Be\u0003\u0015\u00198m\u001c9f\u0011\u0019\u0011Y*\u0016a\u0001[\u00061am\u001c:nCR$bAa\u001f\u0004\n\r-\u0001b\u0002B[-\u0002\u0007!q\u0017\u0005\b\u0007\u001b1\u0006\u0019AB\b\u0003\t\u0019(\r\u0005\u0003\u0002N\rE\u0011\u0002BB\n\u0003C\u0012Qb\u0015;sS:<\')^5mI\u0016\u0014H\u0003\u0003B>\u0007/\u0019Iba\u0007\t\u000f\tUv\u000b1\u0001\u00038\"9!qY,A\u0002\t%\u0007bBB\u0007/\u0002\u00071q\u0002\u000b\u0007\u0003W\u001byb!\t\t\u000f\tU\u0006\f1\u0001\u00038\"I!q\u0019-\u0011\u0002\u0003\u0007!\u0011Z\u0001\u0011M>\u0014X.\u0019;%I\u00164\u0017-\u001e7uII*\"aa\n+\t\t%\u0017\u0011[\u0001\fM>\u0014X.\u0019;O_\u0012,7\u000f\u0006\u0004\u0002,\u000e52q\u0007\u0005\b\u0007_Q\u0006\u0019AB\u0019\u0003\u0015qw\u000eZ3t!\u0019\tYia\r\u00038&!1QGAG\u0005\r\u0019V-\u001d\u0005\n\u0005\u000fT\u0006\u0013!a\u0001\u0005\u0013\fQCZ8s[\u0006$hj\u001c3fg\u0012\"WMZ1vYR$#\u0007\u0006\u0005\u0003|\ru2qHB!\u0011\u001d\u0019y\u0003\u0018a\u0001\u0007cAqAa2]\u0001\u0004\u0011I\rC\u0004\u0004\u000eq\u0003\raa\u0004
    #9 = Utf8               java/lang/invoke/MethodHandles$Lookup
   #10 = Class              #9            // java/lang/invoke/MethodHandles$Lookup
   #11 = Utf8               java/lang/invoke/MethodHandles
   #12 = Class              #11           // java/lang/invoke/MethodHandles
   #13 = Utf8               Lookup
   #14 = Utf8               org/scalatest/tools/PrettyPrinter$Box
   #15 = Class              #14           // org/scalatest/tools/PrettyPrinter$Box
   #16 = Utf8               Box
   #17 = Utf8               org/scalatest/tools/PrettyPrinter$Box$
   #18 = Class              #17           // org/scalatest/tools/PrettyPrinter$Box$
   #19 = Utf8               Box$
   #20 = Utf8               org/scalatest/tools/PrettyPrinter$Break$
   #21 = Class              #20           // org/scalatest/tools/PrettyPrinter$Break$
   #22 = Utf8               Break$
   #23 = Utf8               org/scalatest/tools/PrettyPrinter$BrokenException
   #24 = Class              #23           // org/scalatest/tools/PrettyPrinter$BrokenException
   #25 = Utf8               BrokenException
   #26 = Utf8               org/scalatest/tools/PrettyPrinter$Item
   #27 = Class              #26           // org/scalatest/tools/PrettyPrinter$Item
   #28 = Utf8               Item
   #29 = Utf8               org/scalatest/tools/PrettyPrinter$Para
   #30 = Class              #29           // org/scalatest/tools/PrettyPrinter$Para
   #31 = Utf8               Para
   #32 = Utf8               org/scalatest/tools/PrettyPrinter$Para$
   #33 = Class              #32           // org/scalatest/tools/PrettyPrinter$Para$
   #34 = Utf8               Para$
   #35 = Utf8               scala/Enumeration$Value
   #36 = Class              #35           // scala/Enumeration$Value
   #37 = Utf8               scala/Enumeration
   #38 = Class              #37           // scala/Enumeration
   #39 = Utf8               Value
   #40 = Utf8               Break$module
   #41 = Utf8               Lorg/scalatest/tools/PrettyPrinter$Break$;
   #42 = Utf8               Box$module
   #43 = Utf8               Lorg/scalatest/tools/PrettyPrinter$Box$;
   #44 = Utf8               Para$module
   #45 = Utf8               Lorg/scalatest/tools/PrettyPrinter$Para$;
   #46 = Utf8               width
   #47 = Utf8               I
   #48 = Utf8               step
   #49 = Utf8               minimizeEmpty
   #50 = Utf8               Z
   #51 = Utf8               minimizeMode
   #52 = Utf8               Lscala/Enumeration$Value;
   #53 = Utf8               items
   #54 = Utf8               Lscala/collection/immutable/List;
   #55 = Utf8               Lscala/collection/immutable/List<Lorg/scalatest/tools/PrettyPrinter$Item;>;
   #56 = Utf8               cur
   #57 = Utf8               Break
   #58 = Utf8               ()Lorg/scalatest/tools/PrettyPrinter$Break$;
   #59 = NameAndType        #40:#41       // Break$module:Lorg/scalatest/tools/PrettyPrinter$Break$;
   #60 = Fieldref           #2.#59        // org/scalatest/tools/PrettyPrinter.Break$module:Lorg/scalatest/tools/PrettyPrinter$Break$;
   #61 = Utf8               Break$lzycompute$1
   #62 = Utf8               ()V
   #63 = NameAndType        #61:#62       // Break$lzycompute$1:()V
   #64 = Methodref          #2.#63        // org/scalatest/tools/PrettyPrinter.Break$lzycompute$1:()V
   #65 = Utf8               this
   #66 = Utf8               Lorg/scalatest/tools/PrettyPrinter;
   #67 = Utf8               ()Lorg/scalatest/tools/PrettyPrinter$Box$;
   #68 = NameAndType        #42:#43       // Box$module:Lorg/scalatest/tools/PrettyPrinter$Box$;
   #69 = Fieldref           #2.#68        // org/scalatest/tools/PrettyPrinter.Box$module:Lorg/scalatest/tools/PrettyPrinter$Box$;
   #70 = Utf8               Box$lzycompute$1
   #71 = NameAndType        #70:#62       // Box$lzycompute$1:()V
   #72 = Methodref          #2.#71        // org/scalatest/tools/PrettyPrinter.Box$lzycompute$1:()V
   #73 = Utf8               ()Lorg/scalatest/tools/PrettyPrinter$Para$;
   #74 = NameAndType        #44:#45       // Para$module:Lorg/scalatest/tools/PrettyPrinter$Para$;
   #75 = Fieldref           #2.#74        // org/scalatest/tools/PrettyPrinter.Para$module:Lorg/scalatest/tools/PrettyPrinter$Para$;
   #76 = Utf8               Para$lzycompute$1
   #77 = NameAndType        #76:#62       // Para$lzycompute$1:()V
   #78 = Methodref          #2.#77        // org/scalatest/tools/PrettyPrinter.Para$lzycompute$1:()V
   #79 = Utf8               ()Lscala/Enumeration$Value;
   #80 = NameAndType        #51:#52       // minimizeMode:Lscala/Enumeration$Value;
   #81 = Fieldref           #2.#80        // org/scalatest/tools/PrettyPrinter.minimizeMode:Lscala/Enumeration$Value;
   #82 = Utf8               ()Lscala/collection/immutable/List;
   #83 = Utf8               ()Lscala/collection/immutable/List<Lorg/scalatest/tools/PrettyPrinter$Item;>;
   #84 = NameAndType        #53:#54       // items:Lscala/collection/immutable/List;
   #85 = Fieldref           #2.#84        // org/scalatest/tools/PrettyPrinter.items:Lscala/collection/immutable/List;
   #86 = Utf8               items_$eq
   #87 = Utf8               (Lscala/collection/immutable/List;)V
   #88 = Utf8               (Lscala/collection/immutable/List<Lorg/scalatest/tools/PrettyPrinter$Item;>;)V
   #89 = Utf8               x$1
   #90 = Utf8               ()I
   #91 = NameAndType        #56:#47       // cur:I
   #92 = Fieldref           #2.#91        // org/scalatest/tools/PrettyPrinter.cur:I
   #93 = Utf8               cur_$eq
   #94 = Utf8               (I)V
   #95 = Utf8               reset
   #96 = NameAndType        #93:#94       // cur_$eq:(I)V
   #97 = Methodref          #2.#96        // org/scalatest/tools/PrettyPrinter.cur_$eq:(I)V
   #98 = Utf8               scala/package$
   #99 = Class              #98           // scala/package$
  #100 = Utf8               MODULE$
  #101 = Utf8               Lscala/package$;
  #102 = NameAndType        #100:#101     // MODULE$:Lscala/package$;
  #103 = Fieldref           #99.#102      // scala/package$.MODULE$:Lscala/package$;
  #104 = Utf8               Nil
  #105 = Utf8               ()Lscala/collection/immutable/Nil$;
  #106 = NameAndType        #104:#105     // Nil:()Lscala/collection/immutable/Nil$;
  #107 = Methodref          #99.#106      // scala/package$.Nil:()Lscala/collection/immutable/Nil$;
  #108 = NameAndType        #86:#87       // items_$eq:(Lscala/collection/immutable/List;)V
  #109 = Methodref          #2.#108       // org/scalatest/tools/PrettyPrinter.items_$eq:(Lscala/collection/immutable/List;)V
  #110 = Utf8               cut
  #111 = Utf8               (Ljava/lang/String;I)Lscala/collection/immutable/List;
  #112 = Utf8               (Ljava/lang/String;I)Lscala/collection/immutable/List<Lorg/scalatest/tools/PrettyPrinter$Item;>;
  #113 = Utf8               s
  #114 = Utf8               ind
  #115 = NameAndType        #46:#47       // width:I
  #116 = Fieldref           #2.#115       // org/scalatest/tools/PrettyPrinter.width:I
  #117 = NameAndType        #56:#90       // cur:()I
  #118 = Methodref          #2.#117       // org/scalatest/tools/PrettyPrinter.cur:()I
  #119 = Utf8               java/lang/String
  #120 = Class              #119          // java/lang/String
  #121 = Utf8               length
  #122 = NameAndType        #121:#90      // length:()I
  #123 = Methodref          #120.#122     // java/lang/String.length:()I
  #124 = Utf8               List
  #125 = Utf8               ()Lscala/collection/immutable/List$;
  #126 = NameAndType        #124:#125     // List:()Lscala/collection/immutable/List$;
  #127 = Methodref          #99.#126      // scala/package$.List:()Lscala/collection/immutable/List$;
  #128 = Utf8               scala/runtime/ScalaRunTime$
  #129 = Class              #128          // scala/runtime/ScalaRunTime$
  #130 = Utf8               Lscala/runtime/ScalaRunTime$;
  #131 = NameAndType        #100:#130     // MODULE$:Lscala/runtime/ScalaRunTime$;
  #132 = Fieldref           #129.#131     // scala/runtime/ScalaRunTime$.MODULE$:Lscala/runtime/ScalaRunTime$;
  #133 = Utf8               <init>
  #134 = Utf8               (Lorg/scalatest/tools/PrettyPrinter;ILjava/lang/String;)V
  #135 = NameAndType        #133:#134     // "<init>":(Lorg/scalatest/tools/PrettyPrinter;ILjava/lang/String;)V
  #136 = Methodref          #15.#135      // org/scalatest/tools/PrettyPrinter$Box."<init>":(Lorg/scalatest/tools/PrettyPrinter;ILjava/lang/String;)V
  #137 = Utf8               [Ljava/lang/Object;
  #138 = Class              #137          // "[Ljava/lang/Object;"
  #139 = Utf8               wrapRefArray
  #140 = Utf8               ([Ljava/lang/Object;)Lscala/collection/immutable/ArraySeq;
  #141 = NameAndType        #139:#140     // wrapRefArray:([Ljava/lang/Object;)Lscala/collection/immutable/ArraySeq;
  #142 = Methodref          #129.#141     // scala/runtime/ScalaRunTime$.wrapRefArray:([Ljava/lang/Object;)Lscala/collection/immutable/ArraySeq;
  #143 = Utf8               scala/collection/immutable/List$
  #144 = Class              #143          // scala/collection/immutable/List$
  #145 = Utf8               apply
  #146 = Utf8               (Lscala/collection/immutable/Seq;)Ljava/lang/Object;
  #147 = NameAndType        #145:#146     // apply:(Lscala/collection/immutable/Seq;)Ljava/lang/Object;
  #148 = Methodref          #144.#147     // scala/collection/immutable/List$.apply:(Lscala/collection/immutable/Seq;)Ljava/lang/Object;
  #149 = Utf8               scala/collection/immutable/List
  #150 = Class              #149          // scala/collection/immutable/List
  #151 = Utf8               indexOf
  #152 = Utf8               (I)I
  #153 = NameAndType        #151:#152     // indexOf:(I)I
  #154 = Methodref          #120.#153     // java/lang/String.indexOf:(I)I
  #155 = Utf8               (Lorg/scalatest/tools/PrettyPrinter;)V
  #156 = NameAndType        #133:#155     // "<init>":(Lorg/scalatest/tools/PrettyPrinter;)V
  #157 = Methodref          #24.#156      // org/scalatest/tools/PrettyPrinter$BrokenException."<init>":(Lorg/scalatest/tools/PrettyPrinter;)V
  #158 = Utf8               scala/runtime/BoxesRunTime
  #159 = Class              #158          // scala/runtime/BoxesRunTime
  #160 = Utf8               boxToInteger
  #161 = Utf8               (I)Ljava/lang/Integer;
  #162 = NameAndType        #160:#161     // boxToInteger:(I)Ljava/lang/Integer;
  #163 = Methodref          #159.#162     // scala/runtime/BoxesRunTime.boxToInteger:(I)Ljava/lang/Integer;
  #164 = Utf8               $colon$colon
  #165 = Utf8               (Ljava/lang/Object;)Lscala/collection/immutable/List;
  #166 = NameAndType        #164:#165     // $colon$colon:(Ljava/lang/Object;)Lscala/collection/immutable/List;
  #167 = Methodref          #150.#166     // scala/collection/immutable/List.$colon$colon:(Ljava/lang/Object;)Lscala/collection/immutable/List;
  #168 = Utf8               (II)I
  #169 = NameAndType        #151:#168     // indexOf:(II)I
  #170 = Methodref          #120.#169     // java/lang/String.indexOf:(II)I
  #171 = Utf8               equals
  #172 = Utf8               (Ljava/lang/Object;)Z
  #173 = NameAndType        #171:#172     // equals:(Ljava/lang/Object;)Z
  #174 = Methodref          #4.#173       // java/lang/Object.equals:(Ljava/lang/Object;)Z
  #175 = Utf8               head
  #176 = Utf8               ()Ljava/lang/Object;
  #177 = NameAndType        #175:#176     // head:()Ljava/lang/Object;
  #178 = Methodref          #150.#177     // scala/collection/immutable/List.head:()Ljava/lang/Object;
  #179 = Utf8               unboxToInt
  #180 = Utf8               (Ljava/lang/Object;)I
  #181 = NameAndType        #179:#180     // unboxToInt:(Ljava/lang/Object;)I
  #182 = Methodref          #159.#181     // scala/runtime/BoxesRunTime.unboxToInt:(Ljava/lang/Object;)I
  #183 = Utf8               substring
  #184 = Utf8               (II)Ljava/lang/String;
  #185 = NameAndType        #183:#184     // substring:(II)Ljava/lang/String;
  #186 = Methodref          #120.#185     // java/lang/String.substring:(II)Ljava/lang/String;
  #187 = NameAndType        #57:#58       // Break:()Lorg/scalatest/tools/PrettyPrinter$Break$;
  #188 = Methodref          #2.#187       // org/scalatest/tools/PrettyPrinter.Break:()Lorg/scalatest/tools/PrettyPrinter$Break$;
  #189 = NameAndType        #110:#111     // cut:(Ljava/lang/String;I)Lscala/collection/immutable/List;
  #190 = Methodref          #2.#189       // org/scalatest/tools/PrettyPrinter.cut:(Ljava/lang/String;I)Lscala/collection/immutable/List;
  #191 = Utf8               tail
  #192 = NameAndType        #191:#176     // tail:()Ljava/lang/Object;
  #193 = Methodref          #150.#192     // scala/collection/immutable/List.tail:()Ljava/lang/Object;
  #194 = Utf8               b
  #195 = Utf8               Lorg/scalatest/tools/PrettyPrinter$Box;
  #196 = Utf8               tmp
  #197 = Utf8               i
  #198 = Utf8               last
  #199 = Utf8               res
  #200 = Utf8               Ljava/lang/String;
  #201 = Utf8               scala/collection/immutable/Nil$
  #202 = Class              #201          // scala/collection/immutable/Nil$
  #203 = Utf8               makeBox
  #204 = Utf8               (ILjava/lang/String;)V
  #205 = NameAndType        #53:#82       // items:()Lscala/collection/immutable/List;
  #206 = Methodref          #2.#205       // org/scalatest/tools/PrettyPrinter.items:()Lscala/collection/immutable/List;
  #207 = Utf8               (Ljava/lang/Object;)Ljava/lang/Object;
  #208 = MethodType         #207          //  (Ljava/lang/Object;)Ljava/lang/Object;
  #209 = Utf8               $anonfun$makeBox$1$adapted
  #210 = Utf8               (Lorg/scalatest/tools/PrettyPrinter;Lorg/scalatest/tools/PrettyPrinter$Item;)Ljava/lang/Object;
  #211 = NameAndType        #209:#210     // $anonfun$makeBox$1$adapted:(Lorg/scalatest/tools/PrettyPrinter;Lorg/scalatest/tools/PrettyPrinter$Item;)Ljava/lang/Object;
  #212 = Methodref          #2.#211       // org/scalatest/tools/PrettyPrinter.$anonfun$makeBox$1$adapted:(Lorg/scalatest/tools/PrettyPrinter;Lorg/scalatest/tools/PrettyPrinter$Item;)Ljava/lang/Object;
  #213 = MethodHandle       6:#212        // REF_invokeStatic org/scalatest/tools/PrettyPrinter.$anonfun$makeBox$1$adapted:(Lorg/scalatest/tools/PrettyPrinter;Lorg/scalatest/tools/PrettyPrinter$Item;)Ljava/lang/Object;
  #214 = Utf8               (Lorg/scalatest/tools/PrettyPrinter$Item;)Ljava/lang/Object;
  #215 = MethodType         #214          //  (Lorg/scalatest/tools/PrettyPrinter$Item;)Ljava/lang/Object;
  #216 = Integer            5
  #217 = Integer            1
  #218 = Utf8               java/lang/invoke/LambdaMetafactory
  #219 = Class              #218          // java/lang/invoke/LambdaMetafactory
  #220 = Utf8               altMetafactory
  #221 = Utf8               (Ljava/lang/invoke/MethodHandles$Lookup;Ljava/lang/String;Ljava/lang/invoke/MethodType;[Ljava/lang/Object;)Ljava/lang/invoke/CallSite;
  #222 = NameAndType        #220:#221     // altMetafactory:(Ljava/lang/invoke/MethodHandles$Lookup;Ljava/lang/String;Ljava/lang/invoke/MethodType;[Ljava/lang/Object;)Ljava/lang/invoke/CallSite;
  #223 = Methodref          #219.#222     // java/lang/invoke/LambdaMetafactory.altMetafactory:(Ljava/lang/invoke/MethodHandles$Lookup;Ljava/lang/String;Ljava/lang/invoke/MethodType;[Ljava/lang/Object;)Ljava/lang/invoke/CallSite;
  #224 = MethodHandle       6:#223        // REF_invokeStatic java/lang/invoke/LambdaMetafactory.altMetafactory:(Ljava/lang/invoke/MethodHandles$Lookup;Ljava/lang/String;Ljava/lang/invoke/MethodType;[Ljava/lang/Object;)Ljava/lang/invoke/CallSite;
  #225 = Utf8               (Lorg/scalatest/tools/PrettyPrinter;)Lscala/Function1;
  #226 = NameAndType        #145:#225     // apply:(Lorg/scalatest/tools/PrettyPrinter;)Lscala/Function1;
  #227 = InvokeDynamic      #0:#226       // #0:apply:(Lorg/scalatest/tools/PrettyPrinter;)Lscala/Function1;
  #228 = Utf8               foreach
  #229 = Utf8               (Lscala/Function1;)V
  #230 = NameAndType        #228:#229     // foreach:(Lscala/Function1;)V
  #231 = Methodref          #150.#230     // scala/collection/immutable/List.foreach:(Lscala/Function1;)V
  #232 = Utf8               makePara
  #233 = NameAndType        #232:#204     // makePara:(ILjava/lang/String;)V
  #234 = Methodref          #2.#233       // org/scalatest/tools/PrettyPrinter.makePara:(ILjava/lang/String;)V
  #235 = Utf8               (Lorg/scalatest/tools/PrettyPrinter;Ljava/lang/String;)V
  #236 = NameAndType        #133:#235     // "<init>":(Lorg/scalatest/tools/PrettyPrinter;Ljava/lang/String;)V
  #237 = Methodref          #30.#236      // org/scalatest/tools/PrettyPrinter$Para."<init>":(Lorg/scalatest/tools/PrettyPrinter;Ljava/lang/String;)V
  #238 = Utf8               makeBreak
  #239 = Utf8               leafTag
  #240 = Utf8               (Lscala/xml/Node;)Ljava/lang/String;
  #241 = Utf8               n
  #242 = Utf8               org/scalatest/tools/XmlUtility$
  #243 = Class              #242          // org/scalatest/tools/XmlUtility$
  #244 = Utf8               Lorg/scalatest/tools/XmlUtility$;
  #245 = NameAndType        #100:#244     // MODULE$:Lorg/scalatest/tools/XmlUtility$;
  #246 = Fieldref           #243.#245     // org/scalatest/tools/XmlUtility$.MODULE$:Lorg/scalatest/tools/XmlUtility$;
  #247 = Utf8               $anonfun$leafTag$1$adapted
  #248 = Utf8               (Lscala/xml/Node;Lscala/collection/mutable/StringBuilder;)Ljava/lang/Object;
  #249 = NameAndType        #247:#248     // $anonfun$leafTag$1$adapted:(Lscala/xml/Node;Lscala/collection/mutable/StringBuilder;)Ljava/lang/Object;
  #250 = Methodref          #2.#249       // org/scalatest/tools/PrettyPrinter.$anonfun$leafTag$1$adapted:(Lscala/xml/Node;Lscala/collection/mutable/StringBuilder;)Ljava/lang/Object;
  #251 = MethodHandle       6:#250        // REF_invokeStatic org/scalatest/tools/PrettyPrinter.$anonfun$leafTag$1$adapted:(Lscala/xml/Node;Lscala/collection/mutable/StringBuilder;)Ljava/lang/Object;
  #252 = Utf8               (Lscala/collection/mutable/StringBuilder;)Ljava/lang/Object;
  #253 = MethodType         #252          //  (Lscala/collection/mutable/StringBuilder;)Ljava/lang/Object;
  #254 = Utf8               (Lscala/xml/Node;)Lscala/Function1;
  #255 = NameAndType        #145:#254     // apply:(Lscala/xml/Node;)Lscala/Function1;
  #256 = InvokeDynamic      #1:#255       // #1:apply:(Lscala/xml/Node;)Lscala/Function1;
  #257 = Utf8               sbToString
  #258 = Utf8               (Lscala/Function1;)Ljava/lang/String;
  #259 = NameAndType        #257:#258     // sbToString:(Lscala/Function1;)Ljava/lang/String;
  #260 = Methodref          #243.#259     // org/scalatest/tools/XmlUtility$.sbToString:(Lscala/Function1;)Ljava/lang/String;
  #261 = Utf8               Lscala/xml/Node;
  #262 = Utf8               startTag
  #263 = Utf8               (Lscala/xml/Node;Lscala/xml/NamespaceBinding;)Lscala/Tuple2;
  #264 = Utf8               (Lscala/xml/Node;Lscala/xml/NamespaceBinding;)Lscala/Tuple2<Ljava/lang/String;Ljava/lang/Object;>;
  #265 = Utf8               pscope
  #266 = Utf8               scala/runtime/IntRef
  #267 = Class              #266          // scala/runtime/IntRef
  #268 = Utf8               create
  #269 = Utf8               (I)Lscala/runtime/IntRef;
  #270 = NameAndType        #268:#269     // create:(I)Lscala/runtime/IntRef;
  #271 = Methodref          #267.#270     // scala/runtime/IntRef.create:(I)Lscala/runtime/IntRef;
  #272 = Utf8               scala/Tuple2
  #273 = Class              #272          // scala/Tuple2
  #274 = Utf8               $anonfun$startTag$1$adapted
  #275 = Utf8               (Lscala/xml/Node;Lscala/runtime/IntRef;Lscala/xml/NamespaceBinding;Lscala/collection/mutable/StringBuilder;)Ljava/lang/Object;
  #276 = NameAndType        #274:#275     // $anonfun$startTag$1$adapted:(Lscala/xml/Node;Lscala/runtime/IntRef;Lscala/xml/NamespaceBinding;Lscala/collection/mutable/StringBuilder;)Ljava/lang/Object;
  #277 = Methodref          #2.#276       // org/scalatest/tools/PrettyPrinter.$anonfun$startTag$1$adapted:(Lscala/xml/Node;Lscala/runtime/IntRef;Lscala/xml/NamespaceBinding;Lscala/collection/mutable/StringBuilder;)Ljava/lang/Object;
  #278 = MethodHandle       6:#277        // REF_invokeStatic org/scalatest/tools/PrettyPrinter.$anonfun$startTag$1$adapted:(Lscala/xml/Node;Lscala/runtime/IntRef;Lscala/xml/NamespaceBinding;Lscala/collection/mutable/StringBuilder;)Ljava/lang/Object;
  #279 = Utf8               (Lscala/xml/Node;Lscala/runtime/IntRef;Lscala/xml/NamespaceBinding;)Lscala/Function1;
  #280 = NameAndType        #145:#279     // apply:(Lscala/xml/Node;Lscala/runtime/IntRef;Lscala/xml/NamespaceBinding;)Lscala/Function1;
  #281 = InvokeDynamic      #2:#280       // #2:apply:(Lscala/xml/Node;Lscala/runtime/IntRef;Lscala/xml/NamespaceBinding;)Lscala/Function1;
  #282 = Utf8               elem
  #283 = NameAndType        #282:#47      // elem:I
  #284 = Fieldref           #267.#283     // scala/runtime/IntRef.elem:I
  #285 = Utf8               (Ljava/lang/Object;Ljava/lang/Object;)V
  #286 = NameAndType        #133:#285     // "<init>":(Ljava/lang/Object;Ljava/lang/Object;)V
  #287 = Methodref          #273.#286     // scala/Tuple2."<init>":(Ljava/lang/Object;Ljava/lang/Object;)V
  #288 = Utf8               Lscala/runtime/IntRef;
  #289 = Utf8               Lscala/xml/NamespaceBinding;
  #290 = Utf8               endTag
  #291 = Utf8               $anonfun$endTag$1$adapted
  #292 = NameAndType        #291:#248     // $anonfun$endTag$1$adapted:(Lscala/xml/Node;Lscala/collection/mutable/StringBuilder;)Ljava/lang/Object;
  #293 = Methodref          #2.#292       // org/scalatest/tools/PrettyPrinter.$anonfun$endTag$1$adapted:(Lscala/xml/Node;Lscala/collection/mutable/StringBuilder;)Ljava/lang/Object;
  #294 = MethodHandle       6:#293        // REF_invokeStatic org/scalatest/tools/PrettyPrinter.$anonfun$endTag$1$adapted:(Lscala/xml/Node;Lscala/collection/mutable/StringBuilder;)Ljava/lang/Object;
  #295 = InvokeDynamic      #3:#255       // #3:apply:(Lscala/xml/Node;)Lscala/Function1;
  #296 = Utf8               childrenAreLeaves
  #297 = Utf8               (Lscala/xml/Node;)Z
  #298 = Utf8               scala/xml/Node
  #299 = Class              #298          // scala/xml/Node
  #300 = Utf8               child
  #301 = Utf8               ()Lscala/collection/Seq;
  #302 = NameAndType        #300:#301     // child:()Lscala/collection/Seq;
  #303 = Methodref          #299.#302     // scala/xml/Node.child:()Lscala/collection/Seq;
  #304 = Utf8               $anonfun$childrenAreLeaves$1$adapted
  #305 = Utf8               (Lscala/xml/Node;)Ljava/lang/Object;
  #306 = NameAndType        #304:#305     // $anonfun$childrenAreLeaves$1$adapted:(Lscala/xml/Node;)Ljava/lang/Object;
  #307 = Methodref          #2.#306       // org/scalatest/tools/PrettyPrinter.$anonfun$childrenAreLeaves$1$adapted:(Lscala/xml/Node;)Ljava/lang/Object;
  #308 = MethodHandle       6:#307        // REF_invokeStatic org/scalatest/tools/PrettyPrinter.$anonfun$childrenAreLeaves$1$adapted:(Lscala/xml/Node;)Ljava/lang/Object;
  #309 = MethodType         #305          //  (Lscala/xml/Node;)Ljava/lang/Object;
  #310 = Utf8               ()Lscala/Function1;
  #311 = NameAndType        #145:#310     // apply:()Lscala/Function1;
  #312 = InvokeDynamic      #4:#311       // #4:apply:()Lscala/Function1;
  #313 = Utf8               scala/collection/Seq
  #314 = Class              #313          // scala/collection/Seq
  #315 = Utf8               forall
  #316 = Utf8               (Lscala/Function1;)Z
  #317 = NameAndType        #315:#316     // forall:(Lscala/Function1;)Z
  #318 = InterfaceMethodref #314.#317     // scala/collection/Seq.forall:(Lscala/Function1;)Z
  #319 = Utf8               fits
  #320 = Utf8               (Ljava/lang/String;)Z
  #321 = Utf8               test
  #322 = Utf8               doPreserve
  #323 = Utf8               node
  #324 = Utf8               scala/xml/XML$
  #325 = Class              #324          // scala/xml/XML$
  #326 = Utf8               Lscala/xml/XML$;
  #327 = NameAndType        #100:#326     // MODULE$:Lscala/xml/XML$;
  #328 = Fieldref           #325.#327     // scala/xml/XML$.MODULE$:Lscala/xml/XML$;
  #329 = Utf8               namespace
  #330 = Utf8               ()Ljava/lang/String;
  #331 = NameAndType        #329:#330     // namespace:()Ljava/lang/String;
  #332 = Methodref          #325.#331     // scala/xml/XML$.namespace:()Ljava/lang/String;
  #333 = Utf8               space
  #334 = NameAndType        #333:#330     // space:()Ljava/lang/String;
  #335 = Methodref          #325.#334     // scala/xml/XML$.space:()Ljava/lang/String;
  #336 = Utf8               attribute
  #337 = Utf8               (Ljava/lang/String;Ljava/lang/String;)Lscala/Option;
  #338 = NameAndType        #336:#337     // attribute:(Ljava/lang/String;Ljava/lang/String;)Lscala/Option;
  #339 = Methodref          #299.#338     // scala/xml/Node.attribute:(Ljava/lang/String;Ljava/lang/String;)Lscala/Option;
  #340 = Utf8               $anonfun$doPreserve$1$adapted
  #341 = Utf8               (Lscala/collection/Seq;)Ljava/lang/Object;
  #342 = NameAndType        #340:#341     // $anonfun$doPreserve$1$adapted:(Lscala/collection/Seq;)Ljava/lang/Object;
  #343 = Methodref          #2.#342       // org/scalatest/tools/PrettyPrinter.$anonfun$doPreserve$1$adapted:(Lscala/collection/Seq;)Ljava/lang/Object;
  #344 = MethodHandle       6:#343        // REF_invokeStatic org/scalatest/tools/PrettyPrinter.$anonfun$doPreserve$1$adapted:(Lscala/collection/Seq;)Ljava/lang/Object;
  #345 = MethodType         #341          //  (Lscala/collection/Seq;)Ljava/lang/Object;
  #346 = InvokeDynamic      #5:#311       // #5:apply:()Lscala/Function1;
  #347 = Utf8               scala/Option
  #348 = Class              #347          // scala/Option
  #349 = Utf8               map
  #350 = Utf8               (Lscala/Function1;)Lscala/Option;
  #351 = NameAndType        #349:#350     // map:(Lscala/Function1;)Lscala/Option;
  #352 = Methodref          #348.#351     // scala/Option.map:(Lscala/Function1;)Lscala/Option;
  #353 = Utf8               ()Z
  #354 = MethodType         #353          //  ()Z
  #355 = Utf8               $anonfun$doPreserve$2
  #356 = NameAndType        #355:#353     // $anonfun$doPreserve$2:()Z
  #357 = Methodref          #2.#356       // org/scalatest/tools/PrettyPrinter.$anonfun$doPreserve$2:()Z
  #358 = MethodHandle       6:#357        // REF_invokeStatic org/scalatest/tools/PrettyPrinter.$anonfun$doPreserve$2:()Z
  #359 = Utf8               apply$mcZ$sp
  #360 = Utf8               ()Lscala/runtime/java8/JFunction0$mcZ$sp;
  #361 = NameAndType        #359:#360     // apply$mcZ$sp:()Lscala/runtime/java8/JFunction0$mcZ$sp;
  #362 = InvokeDynamic      #6:#361       // #6:apply$mcZ$sp:()Lscala/runtime/java8/JFunction0$mcZ$sp;
  #363 = Utf8               getOrElse
  #364 = Utf8               (Lscala/Function0;)Ljava/lang/Object;
  #365 = NameAndType        #363:#364     // getOrElse:(Lscala/Function0;)Ljava/lang/Object;
  #366 = Methodref          #348.#365     // scala/Option.getOrElse:(Lscala/Function0;)Ljava/lang/Object;
  #367 = Utf8               unboxToBoolean
  #368 = NameAndType        #367:#172     // unboxToBoolean:(Ljava/lang/Object;)Z
  #369 = Methodref          #159.#368     // scala/runtime/BoxesRunTime.unboxToBoolean:(Ljava/lang/Object;)Z
  #370 = Utf8               traverse
  #371 = Utf8               (Lscala/xml/Node;Lscala/xml/NamespaceBinding;I)V
  #372 = Utf8               scala/xml/Text$
  #373 = Class              #372          // scala/xml/Text$
  #374 = Utf8               Lscala/xml/Text$;
  #375 = NameAndType        #100:#374     // MODULE$:Lscala/xml/Text$;
  #376 = Fieldref           #373.#375     // scala/xml/Text$.MODULE$:Lscala/xml/Text$;
  #377 = Utf8               unapply
  #378 = Utf8               (Ljava/lang/Object;)Lscala/Option;
  #379 = NameAndType        #377:#378     // unapply:(Ljava/lang/Object;)Lscala/Option;
  #380 = Methodref          #373.#379     // scala/xml/Text$.unapply:(Ljava/lang/Object;)Lscala/Option;
  #381 = Utf8               isEmpty
  #382 = NameAndType        #381:#353     // isEmpty:()Z
  #383 = Methodref          #348.#382     // scala/Option.isEmpty:()Z
  #384 = Utf8               get
  #385 = NameAndType        #384:#176     // get:()Ljava/lang/Object;
  #386 = Methodref          #348.#385     // scala/Option.get:()Ljava/lang/Object;
  #387 = Utf8               trim
  #388 = NameAndType        #387:#330     // trim:()Ljava/lang/String;
  #389 = Methodref          #120.#388     // java/lang/String.trim:()Ljava/lang/String;
  #390 = Utf8
  #391 = String             #390          //
  #392 = Utf8               scala/runtime/BoxedUnit
  #393 = Class              #392          // scala/runtime/BoxedUnit
  #394 = Utf8               UNIT
  #395 = Utf8               Lscala/runtime/BoxedUnit;
  #396 = NameAndType        #394:#395     // UNIT:Lscala/runtime/BoxedUnit;
  #397 = Fieldref           #393.#396     // scala/runtime/BoxedUnit.UNIT:Lscala/runtime/BoxedUnit;
  #398 = Utf8               scala/xml/Atom
  #399 = Class              #398          // scala/xml/Atom
  #400 = Utf8               scala/xml/Comment
  #401 = Class              #400          // scala/xml/Comment
  #402 = Utf8               scala/xml/EntityRef
  #403 = Class              #402          // scala/xml/EntityRef
  #404 = Utf8               scala/xml/ProcInstr
  #405 = Class              #404          // scala/xml/ProcInstr
  #406 = Utf8               toString
  #407 = NameAndType        #406:#330     // toString:()Ljava/lang/String;
  #408 = Methodref          #299.#407     // scala/xml/Node.toString:()Ljava/lang/String;
  #409 = NameAndType        #203:#204     // makeBox:(ILjava/lang/String;)V
  #410 = Methodref          #2.#409       // org/scalatest/tools/PrettyPrinter.makeBox:(ILjava/lang/String;)V
  #411 = Utf8               scala/xml/Group
  #412 = Class              #411          // scala/xml/Group
  #413 = Utf8               nodes
  #414 = NameAndType        #413:#301     // nodes:()Lscala/collection/Seq;
  #415 = Methodref          #412.#414     // scala/xml/Group.nodes:()Lscala/collection/Seq;
  #416 = Utf8               iterator
  #417 = Utf8               ()Lscala/collection/Iterator;
  #418 = NameAndType        #416:#417     // iterator:()Lscala/collection/Iterator;
  #419 = InterfaceMethodref #314.#418     // scala/collection/Seq.iterator:()Lscala/collection/Iterator;
  #420 = Utf8               (Lscala/collection/Iterator;Lscala/xml/NamespaceBinding;I)V
  #421 = NameAndType        #370:#420     // traverse:(Lscala/collection/Iterator;Lscala/xml/NamespaceBinding;I)V
  #422 = Methodref          #2.#421       // org/scalatest/tools/PrettyPrinter.traverse:(Lscala/collection/Iterator;Lscala/xml/NamespaceBinding;I)V
  #423 = Utf8               scala/collection/mutable/StringBuilder
  #424 = Class              #423          // scala/collection/mutable/StringBuilder
  #425 = NameAndType        #133:#62      // "<init>":()V
  #426 = Methodref          #424.#425     // scala/collection/mutable/StringBuilder."<init>":()V
  #427 = NameAndType        #51:#79       // minimizeMode:()Lscala/Enumeration$Value;
  #428 = Methodref          #2.#427       // org/scalatest/tools/PrettyPrinter.minimizeMode:()Lscala/Enumeration$Value;
  #429 = Utf8               serialize$default$5
  #430 = NameAndType        #429:#353     // serialize$default$5:()Z
  #431 = Methodref          #243.#430     // org/scalatest/tools/XmlUtility$.serialize$default$5:()Z
  #432 = Utf8               serialize$default$6
  #433 = NameAndType        #432:#353     // serialize$default$6:()Z
  #434 = Methodref          #243.#433     // org/scalatest/tools/XmlUtility$.serialize$default$6:()Z
  #435 = Utf8               serialize
  #436 = Utf8               (Lscala/xml/Node;Lscala/xml/NamespaceBinding;Lscala/collection/mutable/StringBuilder;ZZZLscala/Enumeration$Value;)Lscala/collection/mutable/StringBuilder;
  #437 = NameAndType        #435:#436     // serialize:(Lscala/xml/Node;Lscala/xml/NamespaceBinding;Lscala/collection/mutable/StringBuilder;ZZZLscala/Enumeration$Value;)Lscala/collection/mutable/StringBuilder;
  #438 = Methodref          #243.#437     // org/scalatest/tools/XmlUtility$.serialize:(Lscala/xml/Node;Lscala/xml/NamespaceBinding;Lscala/collection/mutable/StringBuilder;ZZZLscala/Enumeration$Value;)Lscala/collection/mutable/StringBuilder;
  #439 = NameAndType        #322:#297     // doPreserve:(Lscala/xml/Node;)Z
  #440 = Methodref          #2.#439       // org/scalatest/tools/PrettyPrinter.doPreserve:(Lscala/xml/Node;)Z
  #441 = Methodref          #424.#407     // scala/collection/mutable/StringBuilder.toString:()Ljava/lang/String;
  #442 = Utf8               scala/xml/TextBuffer$
  #443 = Class              #442          // scala/xml/TextBuffer$
  #444 = Utf8               Lscala/xml/TextBuffer$;
  #445 = NameAndType        #100:#444     // MODULE$:Lscala/xml/TextBuffer$;
  #446 = Fieldref           #443.#445     // scala/xml/TextBuffer$.MODULE$:Lscala/xml/TextBuffer$;
  #447 = Utf8               fromString
  #448 = Utf8               (Ljava/lang/String;)Lscala/xml/TextBuffer;
  #449 = NameAndType        #447:#448     // fromString:(Ljava/lang/String;)Lscala/xml/TextBuffer;
  #450 = Methodref          #443.#449     // scala/xml/TextBuffer$.fromString:(Ljava/lang/String;)Lscala/xml/TextBuffer;
  #451 = Utf8               scala/xml/TextBuffer
  #452 = Class              #451          // scala/xml/TextBuffer
  #453 = Utf8               toText
  #454 = NameAndType        #453:#301     // toText:()Lscala/collection/Seq;
  #455 = Methodref          #452.#454     // scala/xml/TextBuffer.toText:()Lscala/collection/Seq;
  #456 = Utf8               (I)Ljava/lang/Object;
  #457 = NameAndType        #145:#456     // apply:(I)Ljava/lang/Object;
  #458 = InterfaceMethodref #314.#457     // scala/collection/Seq.apply:(I)Ljava/lang/Object;
  #459 = Utf8               data
  #460 = NameAndType        #459:#176     // data:()Ljava/lang/Object;
  #461 = Methodref          #399.#460     // scala/xml/Atom.data:()Ljava/lang/Object;
  #462 = NameAndType        #296:#297     // childrenAreLeaves:(Lscala/xml/Node;)Z
  #463 = Methodref          #2.#462       // org/scalatest/tools/PrettyPrinter.childrenAreLeaves:(Lscala/xml/Node;)Z
  #464 = NameAndType        #319:#320     // fits:(Ljava/lang/String;)Z
  #465 = Methodref          #2.#464       // org/scalatest/tools/PrettyPrinter.fits:(Ljava/lang/String;)Z
  #466 = InterfaceMethodref #314.#382     // scala/collection/Seq.isEmpty:()Z
  #467 = NameAndType        #49:#50       // minimizeEmpty:Z
  #468 = Fieldref           #2.#467       // org/scalatest/tools/PrettyPrinter.minimizeEmpty:Z
  #469 = Utf8               lastIndexOf
  #470 = NameAndType        #469:#152     // lastIndexOf:(I)I
  #471 = Methodref          #120.#470     // java/lang/String.lastIndexOf:(I)I
  #472 = NameAndType        #262:#263     // startTag:(Lscala/xml/Node;Lscala/xml/NamespaceBinding;)Lscala/Tuple2;
  #473 = Methodref          #2.#472       // org/scalatest/tools/PrettyPrinter.startTag:(Lscala/xml/Node;Lscala/xml/NamespaceBinding;)Lscala/Tuple2;
  #474 = NameAndType        #290:#240     // endTag:(Lscala/xml/Node;)Ljava/lang/String;
  #475 = Methodref          #2.#474       // org/scalatest/tools/PrettyPrinter.endTag:(Lscala/xml/Node;)Ljava/lang/String;
  #476 = Utf8               _1
  #477 = NameAndType        #476:#176     // _1:()Ljava/lang/Object;
  #478 = Methodref          #273.#477     // scala/Tuple2._1:()Ljava/lang/Object;
  #479 = Utf8               _2
  #480 = NameAndType        #479:#176     // _2:()Ljava/lang/Object;
  #481 = Methodref          #273.#480     // scala/Tuple2._2:()Ljava/lang/Object;
  #482 = Utf8               _2$mcI$sp
  #483 = NameAndType        #482:#90      // _2$mcI$sp:()I
  #484 = Methodref          #273.#483     // scala/Tuple2._2$mcI$sp:()I
  #485 = Utf8               scala/Tuple3
  #486 = Class              #485          // scala/Tuple3
  #487 = Utf8               (Ljava/lang/Object;Ljava/lang/Object;Ljava/lang/Object;)V
  #488 = NameAndType        #133:#487     // "<init>":(Ljava/lang/Object;Ljava/lang/Object;Ljava/lang/Object;)V
  #489 = Methodref          #486.#488     // scala/Tuple3."<init>":(Ljava/lang/Object;Ljava/lang/Object;Ljava/lang/Object;)V
  #490 = Utf8               scala/MatchError
  #491 = Class              #490          // scala/MatchError
  #492 = Utf8               (Ljava/lang/Object;)V
  #493 = NameAndType        #133:#492     // "<init>":(Ljava/lang/Object;)V
  #494 = Methodref          #491.#493     // scala/MatchError."<init>":(Ljava/lang/Object;)V
  #495 = Methodref          #486.#477     // scala/Tuple3._1:()Ljava/lang/Object;
  #496 = Methodref          #486.#480     // scala/Tuple3._2:()Ljava/lang/Object;
  #497 = Utf8               _3
  #498 = NameAndType        #497:#176     // _3:()Ljava/lang/Object;
  #499 = Methodref          #486.#498     // scala/Tuple3._3:()Ljava/lang/Object;
  #500 = NameAndType        #238:#62      // makeBreak:()V
  #501 = Methodref          #2.#500       // org/scalatest/tools/PrettyPrinter.makeBreak:()V
  #502 = Utf8               scope
  #503 = Utf8               ()Lscala/xml/NamespaceBinding;
  #504 = NameAndType        #502:#503     // scope:()Lscala/xml/NamespaceBinding;
  #505 = Methodref          #299.#504     // scala/xml/Node.scope:()Lscala/xml/NamespaceBinding;
  #506 = NameAndType        #48:#47       // step:I
  #507 = Fieldref           #2.#506       // org/scalatest/tools/PrettyPrinter.step:I
  #508 = Utf8               scala/collection/StringOps$
  #509 = Class              #508          // scala/collection/StringOps$
  #510 = Utf8               Lscala/collection/StringOps$;
  #511 = NameAndType        #100:#510     // MODULE$:Lscala/collection/StringOps$;
  #512 = Fieldref           #509.#511     // scala/collection/StringOps$.MODULE$:Lscala/collection/StringOps$;
  #513 = Utf8               scala/Predef$
  #514 = Class              #513          // scala/Predef$
  #515 = Utf8               Lscala/Predef$;
  #516 = NameAndType        #100:#515     // MODULE$:Lscala/Predef$;
  #517 = Fieldref           #514.#516     // scala/Predef$.MODULE$:Lscala/Predef$;
  #518 = Utf8               augmentString
  #519 = Utf8               (Ljava/lang/String;)Ljava/lang/String;
  #520 = NameAndType        #518:#519     // augmentString:(Ljava/lang/String;)Ljava/lang/String;
  #521 = Methodref          #514.#520     // scala/Predef$.augmentString:(Ljava/lang/String;)Ljava/lang/String;
  #522 = Utf8               nonEmpty$extension
  #523 = NameAndType        #522:#320     // nonEmpty$extension:(Ljava/lang/String;)Z
  #524 = Methodref          #509.#523     // scala/collection/StringOps$.nonEmpty$extension:(Ljava/lang/String;)Z
  #525 = Utf8               xs
  #526 = Utf8               Lscala/collection/Seq;
  #527 = Utf8               x$2
  #528 = Utf8               x$3
  #529 = Utf8               Lscala/collection/mutable/StringBuilder;
  #530 = Utf8               x$4
  #531 = Utf8               x$5
  #532 = Utf8               x$6
  #533 = Utf8               x$7
  #534 = Utf8               sb
  #535 = Utf8               firstAttribute
  #536 = Utf8               firstBreak
  #537 = Utf8               stg
  #538 = Utf8               len2
  #539 = Utf8               etg
  #540 = Utf8               scala/xml/NamespaceBinding
  #541 = Class              #540          // scala/xml/NamespaceBinding
  #542 = Utf8               (Lscala/collection/Iterator<Lscala/xml/Node;>;Lscala/xml/NamespaceBinding;I)V
  #543 = Utf8               it
  #544 = Utf8               $anonfun$traverse$1$adapted
  #545 = Utf8               (Lorg/scalatest/tools/PrettyPrinter;Lscala/xml/NamespaceBinding;ILscala/xml/Node;)Ljava/lang/Object;
  #546 = NameAndType        #544:#545     // $anonfun$traverse$1$adapted:(Lorg/scalatest/tools/PrettyPrinter;Lscala/xml/NamespaceBinding;ILscala/xml/Node;)Ljava/lang/Object;
  #547 = Methodref          #2.#546       // org/scalatest/tools/PrettyPrinter.$anonfun$traverse$1$adapted:(Lorg/scalatest/tools/PrettyPrinter;Lscala/xml/NamespaceBinding;ILscala/xml/Node;)Ljava/lang/Object;
  #548 = MethodHandle       6:#547        // REF_invokeStatic org/scalatest/tools/PrettyPrinter.$anonfun$traverse$1$adapted:(Lorg/scalatest/tools/PrettyPrinter;Lscala/xml/NamespaceBinding;ILscala/xml/Node;)Ljava/lang/Object;
  #549 = Utf8               (Lorg/scalatest/tools/PrettyPrinter;Lscala/xml/NamespaceBinding;I)Lscala/Function1;
  #550 = NameAndType        #145:#549     // apply:(Lorg/scalatest/tools/PrettyPrinter;Lscala/xml/NamespaceBinding;I)Lscala/Function1;
  #551 = InvokeDynamic      #7:#550       // #7:apply:(Lorg/scalatest/tools/PrettyPrinter;Lscala/xml/NamespaceBinding;I)Lscala/Function1;
  #552 = Utf8               scala/collection/Iterator
  #553 = Class              #552          // scala/collection/Iterator
  #554 = InterfaceMethodref #553.#230     // scala/collection/Iterator.foreach:(Lscala/Function1;)V
  #555 = Utf8               Lscala/collection/Iterator;
  #556 = Utf8               format
  #557 = Utf8               (Lscala/xml/Node;Lscala/collection/mutable/StringBuilder;)V
  #558 = Utf8               scala/xml/TopScope$
  #559 = Class              #558          // scala/xml/TopScope$
  #560 = Utf8               Lscala/xml/TopScope$;
  #561 = NameAndType        #100:#560     // MODULE$:Lscala/xml/TopScope$;
  #562 = Fieldref           #559.#561     // scala/xml/TopScope$.MODULE$:Lscala/xml/TopScope$;
  #563 = Utf8               (Lscala/xml/Node;Lscala/xml/NamespaceBinding;Lscala/collection/mutable/StringBuilder;)V
  #564 = NameAndType        #556:#563     // format:(Lscala/xml/Node;Lscala/xml/NamespaceBinding;Lscala/collection/mutable/StringBuilder;)V
  #565 = Methodref          #2.#564       // org/scalatest/tools/PrettyPrinter.format:(Lscala/xml/Node;Lscala/xml/NamespaceBinding;Lscala/collection/mutable/StringBuilder;)V
  #566 = Utf8               scala/runtime/BooleanRef
  #567 = Class              #566          // scala/runtime/BooleanRef
  #568 = Utf8               (Z)Lscala/runtime/BooleanRef;
  #569 = NameAndType        #268:#568     // create:(Z)Lscala/runtime/BooleanRef;
  #570 = Methodref          #567.#569     // scala/runtime/BooleanRef.create:(Z)Lscala/runtime/BooleanRef;
  #571 = NameAndType        #95:#62       // reset:()V
  #572 = Methodref          #2.#571       // org/scalatest/tools/PrettyPrinter.reset:()V
  #573 = NameAndType        #370:#371     // traverse:(Lscala/xml/Node;Lscala/xml/NamespaceBinding;I)V
  #574 = Methodref          #2.#573       // org/scalatest/tools/PrettyPrinter.traverse:(Lscala/xml/Node;Lscala/xml/NamespaceBinding;I)V
  #575 = Utf8               reverse
  #576 = NameAndType        #575:#82      // reverse:()Lscala/collection/immutable/List;
  #577 = Methodref          #150.#576     // scala/collection/immutable/List.reverse:()Lscala/collection/immutable/List;
  #578 = Utf8               $anonfun$format$1
  #579 = Utf8               (Lorg/scalatest/tools/PrettyPrinter;Lscala/runtime/BooleanRef;Lscala/collection/mutable/StringBuilder;Lscala/runtime/IntRef;Lorg/scalatest/tools/PrettyPrinter$Item;)Ljava/lang/Object;
  #580 = NameAndType        #578:#579     // $anonfun$format$1:(Lorg/scalatest/tools/PrettyPrinter;Lscala/runtime/BooleanRef;Lscala/collection/mutable/StringBuilder;Lscala/runtime/IntRef;Lorg/scalatest/tools/PrettyPrinter$Item;)Ljava/lang/Object;
  #581 = Methodref          #2.#580       // org/scalatest/tools/PrettyPrinter.$anonfun$format$1:(Lorg/scalatest/tools/PrettyPrinter;Lscala/runtime/BooleanRef;Lscala/collection/mutable/StringBuilder;Lscala/runtime/IntRef;Lorg/scalatest/tools/PrettyPrinter$Item;)Ljava/lang/Object;
  #582 = MethodHandle       6:#581        // REF_invokeStatic org/scalatest/tools/PrettyPrinter.$anonfun$format$1:(Lorg/scalatest/tools/PrettyPrinter;Lscala/runtime/BooleanRef;Lscala/collection/mutable/StringBuilder;Lscala/runtime/IntRef;Lorg/scalatest/tools/PrettyPrinter$Item;)Ljava/lang/Object;
  #583 = Utf8               (Lorg/scalatest/tools/PrettyPrinter;Lscala/runtime/BooleanRef;Lscala/collection/mutable/StringBuilder;Lscala/runtime/IntRef;)Lscala/Function1;
  #584 = NameAndType        #145:#583     // apply:(Lorg/scalatest/tools/PrettyPrinter;Lscala/runtime/BooleanRef;Lscala/collection/mutable/StringBuilder;Lscala/runtime/IntRef;)Lscala/Function1;
  #585 = InvokeDynamic      #8:#584       // #8:apply:(Lorg/scalatest/tools/PrettyPrinter;Lscala/runtime/BooleanRef;Lscala/collection/mutable/StringBuilder;Lscala/runtime/IntRef;)Lscala/Function1;
  #586 = Utf8               lastwasbreak
  #587 = Utf8               Lscala/runtime/BooleanRef;
  #588 = Utf8               (Lscala/xml/Node;Lscala/xml/NamespaceBinding;)Ljava/lang/String;
  #589 = Utf8               $anonfun$format$2$adapted
  #590 = Utf8               (Lorg/scalatest/tools/PrettyPrinter;Lscala/xml/Node;Lscala/xml/NamespaceBinding;Lscala/collection/mutable/StringBuilder;)Ljava/lang/Object;
  #591 = NameAndType        #589:#590     // $anonfun$format$2$adapted:(Lorg/scalatest/tools/PrettyPrinter;Lscala/xml/Node;Lscala/xml/NamespaceBinding;Lscala/collection/mutable/StringBuilder;)Ljava/lang/Object;
  #592 = Methodref          #2.#591       // org/scalatest/tools/PrettyPrinter.$anonfun$format$2$adapted:(Lorg/scalatest/tools/PrettyPrinter;Lscala/xml/Node;Lscala/xml/NamespaceBinding;Lscala/collection/mutable/StringBuilder;)Ljava/lang/Object;
  #593 = MethodHandle       6:#592        // REF_invokeStatic org/scalatest/tools/PrettyPrinter.$anonfun$format$2$adapted:(Lorg/scalatest/tools/PrettyPrinter;Lscala/xml/Node;Lscala/xml/NamespaceBinding;Lscala/collection/mutable/StringBuilder;)Ljava/lang/Object;
  #594 = Utf8               (Lorg/scalatest/tools/PrettyPrinter;Lscala/xml/Node;Lscala/xml/NamespaceBinding;)Lscala/Function1;
  #595 = NameAndType        #145:#594     // apply:(Lorg/scalatest/tools/PrettyPrinter;Lscala/xml/Node;Lscala/xml/NamespaceBinding;)Lscala/Function1;
  #596 = InvokeDynamic      #9:#595       // #9:apply:(Lorg/scalatest/tools/PrettyPrinter;Lscala/xml/Node;Lscala/xml/NamespaceBinding;)Lscala/Function1;
  #597 = Utf8               format$default$2
  #598 = Utf8               formatNodes
  #599 = Utf8               (Lscala/collection/Seq;Lscala/xml/NamespaceBinding;)Ljava/lang/String;
  #600 = Utf8               (Lscala/collection/Seq<Lscala/xml/Node;>;Lscala/xml/NamespaceBinding;)Ljava/lang/String;
  #601 = Utf8               $anonfun$formatNodes$1$adapted
  #602 = Utf8               (Lorg/scalatest/tools/PrettyPrinter;Lscala/collection/Seq;Lscala/xml/NamespaceBinding;Lscala/collection/mutable/StringBuilder;)Ljava/lang/Object;
  #603 = NameAndType        #601:#602     // $anonfun$formatNodes$1$adapted:(Lorg/scalatest/tools/PrettyPrinter;Lscala/collection/Seq;Lscala/xml/NamespaceBinding;Lscala/collection/mutable/StringBuilder;)Ljava/lang/Object;
  #604 = Methodref          #2.#603       // org/scalatest/tools/PrettyPrinter.$anonfun$formatNodes$1$adapted:(Lorg/scalatest/tools/PrettyPrinter;Lscala/collection/Seq;Lscala/xml/NamespaceBinding;Lscala/collection/mutable/StringBuilder;)Ljava/lang/Object;
  #605 = MethodHandle       6:#604        // REF_invokeStatic org/scalatest/tools/PrettyPrinter.$anonfun$formatNodes$1$adapted:(Lorg/scalatest/tools/PrettyPrinter;Lscala/collection/Seq;Lscala/xml/NamespaceBinding;Lscala/collection/mutable/StringBuilder;)Ljava/lang/Object;
  #606 = Utf8               (Lorg/scalatest/tools/PrettyPrinter;Lscala/collection/Seq;Lscala/xml/NamespaceBinding;)Lscala/Function1;
  #607 = NameAndType        #145:#606     // apply:(Lorg/scalatest/tools/PrettyPrinter;Lscala/collection/Seq;Lscala/xml/NamespaceBinding;)Lscala/Function1;
  #608 = InvokeDynamic      #10:#607      // #10:apply:(Lorg/scalatest/tools/PrettyPrinter;Lscala/collection/Seq;Lscala/xml/NamespaceBinding;)Lscala/Function1;
  #609 = Utf8               (Lscala/collection/Seq;Lscala/xml/NamespaceBinding;Lscala/collection/mutable/StringBuilder;)V
  #610 = Utf8               (Lscala/collection/Seq<Lscala/xml/Node;>;Lscala/xml/NamespaceBinding;Lscala/collection/mutable/StringBuilder;)V
  #611 = Utf8               $anonfun$formatNodes$2
  #612 = Utf8               (Lorg/scalatest/tools/PrettyPrinter;Lscala/collection/mutable/StringBuilder;Lscala/xml/NamespaceBinding;Lscala/xml/Node;)Lscala/collection/mutable/StringBuilder;
  #613 = NameAndType        #611:#612     // $anonfun$formatNodes$2:(Lorg/scalatest/tools/PrettyPrinter;Lscala/collection/mutable/StringBuilder;Lscala/xml/NamespaceBinding;Lscala/xml/Node;)Lscala/collection/mutable/StringBuilder;
  #614 = Methodref          #2.#613       // org/scalatest/tools/PrettyPrinter.$anonfun$formatNodes$2:(Lorg/scalatest/tools/PrettyPrinter;Lscala/collection/mutable/StringBuilder;Lscala/xml/NamespaceBinding;Lscala/xml/Node;)Lscala/collection/mutable/StringBuilder;
  #615 = MethodHandle       6:#614        // REF_invokeStatic org/scalatest/tools/PrettyPrinter.$anonfun$formatNodes$2:(Lorg/scalatest/tools/PrettyPrinter;Lscala/collection/mutable/StringBuilder;Lscala/xml/NamespaceBinding;Lscala/xml/Node;)Lscala/collection/mutable/StringBuilder;
  #616 = Utf8               (Lscala/xml/Node;)Lscala/collection/mutable/StringBuilder;
  #617 = MethodType         #616          //  (Lscala/xml/Node;)Lscala/collection/mutable/StringBuilder;
  #618 = Utf8               (Lorg/scalatest/tools/PrettyPrinter;Lscala/collection/mutable/StringBuilder;Lscala/xml/NamespaceBinding;)Lscala/Function1;
  #619 = NameAndType        #145:#618     // apply:(Lorg/scalatest/tools/PrettyPrinter;Lscala/collection/mutable/StringBuilder;Lscala/xml/NamespaceBinding;)Lscala/Function1;
  #620 = InvokeDynamic      #11:#619      // #11:apply:(Lorg/scalatest/tools/PrettyPrinter;Lscala/collection/mutable/StringBuilder;Lscala/xml/NamespaceBinding;)Lscala/Function1;
  #621 = InterfaceMethodref #314.#230     // scala/collection/Seq.foreach:(Lscala/Function1;)V
  #622 = Utf8               formatNodes$default$2
  #623 = Methodref          #21.#156      // org/scalatest/tools/PrettyPrinter$Break$."<init>":(Lorg/scalatest/tools/PrettyPrinter;)V
  #624 = Utf8               java/lang/Throwable
  #625 = Class              #624          // java/lang/Throwable
  #626 = Methodref          #18.#156      // org/scalatest/tools/PrettyPrinter$Box$."<init>":(Lorg/scalatest/tools/PrettyPrinter;)V
  #627 = Methodref          #33.#156      // org/scalatest/tools/PrettyPrinter$Para$."<init>":(Lorg/scalatest/tools/PrettyPrinter;)V
  #628 = Utf8               $anonfun$makeBox$1
  #629 = Utf8               (Lorg/scalatest/tools/PrettyPrinter;Lorg/scalatest/tools/PrettyPrinter$Item;)V
  #630 = Utf8               $this
  #631 = Utf8               Lorg/scalatest/tools/PrettyPrinter$Item;
  #632 = Utf8               mkLeaf$1
  #633 = Utf8               (Lscala/collection/mutable/StringBuilder;Lscala/xml/Node;)V
  #634 = Utf8               n$1
  #635 = Utf8               append
  #636 = Utf8               (C)Lscala/collection/mutable/StringBuilder;
  #637 = NameAndType        #635:#636     // append:(C)Lscala/collection/mutable/StringBuilder;
  #638 = Methodref          #424.#637     // scala/collection/mutable/StringBuilder.append:(C)Lscala/collection/mutable/StringBuilder;
  #639 = Utf8               nameToString
  #640 = Utf8               (Lscala/collection/mutable/StringBuilder;)Lscala/collection/mutable/StringBuilder;
  #641 = NameAndType        #639:#640     // nameToString:(Lscala/collection/mutable/StringBuilder;)Lscala/collection/mutable/StringBuilder;
  #642 = Methodref          #299.#641     // scala/xml/Node.nameToString:(Lscala/collection/mutable/StringBuilder;)Lscala/collection/mutable/StringBuilder;
  #643 = Utf8               attributes
  #644 = Utf8               ()Lscala/xml/MetaData;
  #645 = NameAndType        #643:#644     // attributes:()Lscala/xml/MetaData;
  #646 = Methodref          #299.#645     // scala/xml/Node.attributes:()Lscala/xml/MetaData;
  #647 = Utf8               scala/xml/MetaData
  #648 = Class              #647          // scala/xml/MetaData
  #649 = Utf8               buildString
  #650 = NameAndType        #649:#640     // buildString:(Lscala/collection/mutable/StringBuilder;)Lscala/collection/mutable/StringBuilder;
  #651 = Methodref          #648.#650     // scala/xml/MetaData.buildString:(Lscala/collection/mutable/StringBuilder;)Lscala/collection/mutable/StringBuilder;
  #652 = Utf8               />
  #653 = String             #652          // />
  #654 = Utf8               (Ljava/lang/String;)Lscala/collection/mutable/StringBuilder;
  #655 = NameAndType        #635:#654     // append:(Ljava/lang/String;)Lscala/collection/mutable/StringBuilder;
  #656 = Methodref          #424.#655     // scala/collection/mutable/StringBuilder.append:(Ljava/lang/String;)Lscala/collection/mutable/StringBuilder;
  #657 = Utf8               $anonfun$leafTag$1
  #658 = NameAndType        #632:#633     // mkLeaf$1:(Lscala/collection/mutable/StringBuilder;Lscala/xml/Node;)V
  #659 = Methodref          #2.#658       // org/scalatest/tools/PrettyPrinter.mkLeaf$1:(Lscala/collection/mutable/StringBuilder;Lscala/xml/Node;)V
  #660 = Utf8               mkStart$1
  #661 = Utf8               (Lscala/collection/mutable/StringBuilder;Lscala/xml/Node;Lscala/runtime/IntRef;Lscala/xml/NamespaceBinding;)V
  #662 = Utf8               n$2
  #663 = Utf8               i$1
  #664 = Utf8               pscope$1
  #665 = Methodref          #424.#122     // scala/collection/mutable/StringBuilder.length:()I
  #666 = Utf8               (Lscala/collection/mutable/StringBuilder;Lscala/xml/NamespaceBinding;)V
  #667 = NameAndType        #649:#666     // buildString:(Lscala/collection/mutable/StringBuilder;Lscala/xml/NamespaceBinding;)V
  #668 = Methodref          #541.#667     // scala/xml/NamespaceBinding.buildString:(Lscala/collection/mutable/StringBuilder;Lscala/xml/NamespaceBinding;)V
  #669 = Utf8               $anonfun$startTag$1
  #670 = Utf8               (Lscala/xml/Node;Lscala/runtime/IntRef;Lscala/xml/NamespaceBinding;Lscala/collection/mutable/StringBuilder;)V
  #671 = NameAndType        #660:#661     // mkStart$1:(Lscala/collection/mutable/StringBuilder;Lscala/xml/Node;Lscala/runtime/IntRef;Lscala/xml/NamespaceBinding;)V
  #672 = Methodref          #2.#671       // org/scalatest/tools/PrettyPrinter.mkStart$1:(Lscala/collection/mutable/StringBuilder;Lscala/xml/Node;Lscala/runtime/IntRef;Lscala/xml/NamespaceBinding;)V
  #673 = Utf8               mkEnd$1
  #674 = Utf8               n$3
  #675 = Utf8               </
  #676 = String             #675          // </
  #677 = Utf8               $anonfun$endTag$1
  #678 = NameAndType        #673:#633     // mkEnd$1:(Lscala/collection/mutable/StringBuilder;Lscala/xml/Node;)V
  #679 = Methodref          #2.#678       // org/scalatest/tools/PrettyPrinter.mkEnd$1:(Lscala/collection/mutable/StringBuilder;Lscala/xml/Node;)V
  #680 = Utf8               isLeaf$1
  #681 = Utf8               l
  #682 = Utf8               $anonfun$childrenAreLeaves$1
  #683 = NameAndType        #680:#297     // isLeaf$1:(Lscala/xml/Node;)Z
  #684 = Methodref          #2.#683       // org/scalatest/tools/PrettyPrinter.isLeaf$1:(Lscala/xml/Node;)Z
  #685 = Utf8               $anonfun$doPreserve$1
  #686 = Utf8               (Lscala/collection/Seq;)Z
  #687 = InterfaceMethodref #314.#407     // scala/collection/Seq.toString:()Ljava/lang/String;
  #688 = Utf8               preserve
  #689 = NameAndType        #688:#330     // preserve:()Ljava/lang/String;
  #690 = Methodref          #325.#689     // scala/xml/XML$.preserve:()Ljava/lang/String;
  #691 = Utf8               $anonfun$traverse$1
  #692 = Utf8               (Lorg/scalatest/tools/PrettyPrinter;Lscala/xml/NamespaceBinding;ILscala/xml/Node;)V
  #693 = Utf8               scope$1
  #694 = Utf8               ind$1
  #695 = Utf8               c
  #696 = Utf8               lastwasbreak$1
  #697 = Utf8               sb$1
  #698 = Utf8               cur$1
  #699 = NameAndType        #282:#50      // elem:Z
  #700 = Fieldref           #567.#699     // scala/runtime/BooleanRef.elem:Z
  #701 = Utf8               col
  #702 = NameAndType        #701:#90      // col:()I
  #703 = Methodref          #15.#702      // org/scalatest/tools/PrettyPrinter$Box.col:()I
  #704 = NameAndType        #113:#330     // s:()Ljava/lang/String;
  #705 = Methodref          #15.#704      // org/scalatest/tools/PrettyPrinter$Box.s:()Ljava/lang/String;
  #706 = Methodref          #30.#704      // org/scalatest/tools/PrettyPrinter$Para.s:()Ljava/lang/String;
  #707 = Utf8               $anonfun$format$2
  #708 = Utf8               (Lorg/scalatest/tools/PrettyPrinter;Lscala/xml/Node;Lscala/xml/NamespaceBinding;Lscala/collection/mutable/StringBuilder;)V
  #709 = Utf8               n$4
  #710 = Utf8               pscope$2
  #711 = Utf8               $anonfun$formatNodes$1
  #712 = Utf8               (Lorg/scalatest/tools/PrettyPrinter;Lscala/collection/Seq;Lscala/xml/NamespaceBinding;Lscala/collection/mutable/StringBuilder;)V
  #713 = Utf8               nodes$1
  #714 = Utf8               pscope$3
  #715 = NameAndType        #598:#609     // formatNodes:(Lscala/collection/Seq;Lscala/xml/NamespaceBinding;Lscala/collection/mutable/StringBuilder;)V
  #716 = Methodref          #2.#715       // org/scalatest/tools/PrettyPrinter.formatNodes:(Lscala/collection/Seq;Lscala/xml/NamespaceBinding;Lscala/collection/mutable/StringBuilder;)V
  #717 = Utf8               sb$2
  #718 = Utf8               pscope$4
  #719 = NameAndType        #556:#588     // format:(Lscala/xml/Node;Lscala/xml/NamespaceBinding;)Ljava/lang/String;
  #720 = Methodref          #2.#719       // org/scalatest/tools/PrettyPrinter.format:(Lscala/xml/Node;Lscala/xml/NamespaceBinding;)Ljava/lang/String;
  #721 = Utf8               (IIZ)V
  #722 = Methodref          #4.#425       // java/lang/Object."<init>":()V
  #723 = Utf8               scala/xml/MinimizeMode$
  #724 = Class              #723          // scala/xml/MinimizeMode$
  #725 = Utf8               Lscala/xml/MinimizeMode$;
  #726 = NameAndType        #100:#725     // MODULE$:Lscala/xml/MinimizeMode$;
  #727 = Fieldref           #724.#726     // scala/xml/MinimizeMode$.MODULE$:Lscala/xml/MinimizeMode$;
  #728 = Utf8               Always
  #729 = NameAndType        #728:#79      // Always:()Lscala/Enumeration$Value;
  #730 = Methodref          #724.#729     // scala/xml/MinimizeMode$.Always:()Lscala/Enumeration$Value;
  #731 = Utf8               Default
  #732 = NameAndType        #731:#79      // Default:()Lscala/Enumeration$Value;
  #733 = Methodref          #724.#732     // scala/xml/MinimizeMode$.Default:()Lscala/Enumeration$Value;
  #734 = Utf8               (II)V
  #735 = NameAndType        #133:#721     // "<init>":(IIZ)V
  #736 = Methodref          #2.#735       // org/scalatest/tools/PrettyPrinter."<init>":(IIZ)V
  #737 = NameAndType        #628:#629     // $anonfun$makeBox$1:(Lorg/scalatest/tools/PrettyPrinter;Lorg/scalatest/tools/PrettyPrinter$Item;)V
  #738 = Methodref          #2.#737       // org/scalatest/tools/PrettyPrinter.$anonfun$makeBox$1:(Lorg/scalatest/tools/PrettyPrinter;Lorg/scalatest/tools/PrettyPrinter$Item;)V
  #739 = NameAndType        #657:#557     // $anonfun$leafTag$1:(Lscala/xml/Node;Lscala/collection/mutable/StringBuilder;)V
  #740 = Methodref          #2.#739       // org/scalatest/tools/PrettyPrinter.$anonfun$leafTag$1:(Lscala/xml/Node;Lscala/collection/mutable/StringBuilder;)V
  #741 = NameAndType        #669:#670     // $anonfun$startTag$1:(Lscala/xml/Node;Lscala/runtime/IntRef;Lscala/xml/NamespaceBinding;Lscala/collection/mutable/StringBuilder;)V
  #742 = Methodref          #2.#741       // org/scalatest/tools/PrettyPrinter.$anonfun$startTag$1:(Lscala/xml/Node;Lscala/runtime/IntRef;Lscala/xml/NamespaceBinding;Lscala/collection/mutable/StringBuilder;)V
  #743 = NameAndType        #677:#557     // $anonfun$endTag$1:(Lscala/xml/Node;Lscala/collection/mutable/StringBuilder;)V
  #744 = Methodref          #2.#743       // org/scalatest/tools/PrettyPrinter.$anonfun$endTag$1:(Lscala/xml/Node;Lscala/collection/mutable/StringBuilder;)V
  #745 = NameAndType        #682:#297     // $anonfun$childrenAreLeaves$1:(Lscala/xml/Node;)Z
  #746 = Methodref          #2.#745       // org/scalatest/tools/PrettyPrinter.$anonfun$childrenAreLeaves$1:(Lscala/xml/Node;)Z
  #747 = Utf8               boxToBoolean
  #748 = Utf8               (Z)Ljava/lang/Boolean;
  #749 = NameAndType        #747:#748     // boxToBoolean:(Z)Ljava/lang/Boolean;
  #750 = Methodref          #159.#749     // scala/runtime/BoxesRunTime.boxToBoolean:(Z)Ljava/lang/Boolean;
  #751 = NameAndType        #685:#686     // $anonfun$doPreserve$1:(Lscala/collection/Seq;)Z
  #752 = Methodref          #2.#751       // org/scalatest/tools/PrettyPrinter.$anonfun$doPreserve$1:(Lscala/collection/Seq;)Z
  #753 = NameAndType        #691:#692     // $anonfun$traverse$1:(Lorg/scalatest/tools/PrettyPrinter;Lscala/xml/NamespaceBinding;ILscala/xml/Node;)V
  #754 = Methodref          #2.#753       // org/scalatest/tools/PrettyPrinter.$anonfun$traverse$1:(Lorg/scalatest/tools/PrettyPrinter;Lscala/xml/NamespaceBinding;ILscala/xml/Node;)V
  #755 = NameAndType        #707:#708     // $anonfun$format$2:(Lorg/scalatest/tools/PrettyPrinter;Lscala/xml/Node;Lscala/xml/NamespaceBinding;Lscala/collection/mutable/StringBuilder;)V
  #756 = Methodref          #2.#755       // org/scalatest/tools/PrettyPrinter.$anonfun$format$2:(Lorg/scalatest/tools/PrettyPrinter;Lscala/xml/Node;Lscala/xml/NamespaceBinding;Lscala/collection/mutable/StringBuilder;)V
  #757 = NameAndType        #711:#712     // $anonfun$formatNodes$1:(Lorg/scalatest/tools/PrettyPrinter;Lscala/collection/Seq;Lscala/xml/NamespaceBinding;Lscala/collection/mutable/StringBuilder;)V
  #758 = Methodref          #2.#757       // org/scalatest/tools/PrettyPrinter.$anonfun$formatNodes$1:(Lorg/scalatest/tools/PrettyPrinter;Lscala/collection/Seq;Lscala/xml/NamespaceBinding;Lscala/collection/mutable/StringBuilder;)V
  #759 = Utf8               $deserializeLambda$
  #760 = Utf8               (Ljava/lang/invoke/SerializedLambda;)Ljava/lang/Object;
  #761 = Utf8               scala/runtime/LambdaDeserialize
  #762 = Class              #761          // scala/runtime/LambdaDeserialize
  #763 = Utf8               bootstrap
  #764 = Utf8               (Ljava/lang/invoke/MethodHandles$Lookup;Ljava/lang/String;Ljava/lang/invoke/MethodType;[Ljava/lang/invoke/MethodHandle;)Ljava/lang/invoke/CallSite;
  #765 = NameAndType        #763:#764     // bootstrap:(Ljava/lang/invoke/MethodHandles$Lookup;Ljava/lang/String;Ljava/lang/invoke/MethodType;[Ljava/lang/invoke/MethodHandle;)Ljava/lang/invoke/CallSite;
  #766 = Methodref          #762.#765     // scala/runtime/LambdaDeserialize.bootstrap:(Ljava/lang/invoke/MethodHandles$Lookup;Ljava/lang/String;Ljava/lang/invoke/MethodType;[Ljava/lang/invoke/MethodHandle;)Ljava/lang/invoke/CallSite;
  #767 = MethodHandle       6:#766        // REF_invokeStatic scala/runtime/LambdaDeserialize.bootstrap:(Ljava/lang/invoke/MethodHandles$Lookup;Ljava/lang/String;Ljava/lang/invoke/MethodType;[Ljava/lang/invoke/MethodHandle;)Ljava/lang/invoke/CallSite;
  #768 = Utf8               lambdaDeserialize
  #769 = NameAndType        #768:#760     // lambdaDeserialize:(Ljava/lang/invoke/SerializedLambda;)Ljava/lang/Object;
  #770 = InvokeDynamic      #12:#769      // #12:lambdaDeserialize:(Ljava/lang/invoke/SerializedLambda;)Ljava/lang/Object;
  #771 = Utf8               Signature
  #772 = Utf8               Code
  #773 = Utf8               StackMapTable
  #774 = Utf8               LineNumberTable
  #775 = Utf8               LocalVariableTable
  #776 = Utf8               MethodParameters
  #777 = Utf8               InnerClasses
  #778 = Utf8               SourceFile
  #779 = Utf8               RuntimeVisibleAnnotations
  #780 = Utf8               BootstrapMethods
  #781 = Utf8               ScalaInlineInfo
  #782 = Utf8               ScalaSig
{
  private volatile org.scalatest.tools.PrettyPrinter$Break$ Break$module;
    descriptor: Lorg/scalatest/tools/PrettyPrinter$Break$;
    flags: (0x0042) ACC_PRIVATE, ACC_VOLATILE

  private volatile org.scalatest.tools.PrettyPrinter$Box$ Box$module;
    descriptor: Lorg/scalatest/tools/PrettyPrinter$Box$;
    flags: (0x0042) ACC_PRIVATE, ACC_VOLATILE

  private volatile org.scalatest.tools.PrettyPrinter$Para$ Para$module;
    descriptor: Lorg/scalatest/tools/PrettyPrinter$Para$;
    flags: (0x0042) ACC_PRIVATE, ACC_VOLATILE

  private final int width;
    descriptor: I
    flags: (0x0012) ACC_PRIVATE, ACC_FINAL

  private final int step;
    descriptor: I
    flags: (0x0012) ACC_PRIVATE, ACC_FINAL

  private final boolean minimizeEmpty;
    descriptor: Z
    flags: (0x0012) ACC_PRIVATE, ACC_FINAL

  private final scala.Enumeration$Value minimizeMode;
    descriptor: Lscala/Enumeration$Value;
    flags: (0x0012) ACC_PRIVATE, ACC_FINAL

  private scala.collection.immutable.List<org.scalatest.tools.PrettyPrinter$Item> items;
    descriptor: Lscala/collection/immutable/List;
    flags: (0x0002) ACC_PRIVATE
    Signature: #55                          // Lscala/collection/immutable/List<Lorg/scalatest/tools/PrettyPrinter$Item;>;

  private int cur;
    descriptor: I
    flags: (0x0002) ACC_PRIVATE

  public org.scalatest.tools.PrettyPrinter$Break$ Break();
    descriptor: ()Lorg/scalatest/tools/PrettyPrinter$Break$;
    flags: (0x0001) ACC_PUBLIC
    Code:
      stack=1, locals=1, args_size=1
         0: aload_0
         1: getfield      #60                 // Field Break$module:Lorg/scalatest/tools/PrettyPrinter$Break$;
         4: ifnonnull     11
         7: aload_0
         8: invokespecial #64                 // Method Break$lzycompute$1:()V
        11: aload_0
        12: getfield      #60                 // Field Break$module:Lorg/scalatest/tools/PrettyPrinter$Break$;
        15: areturn
      StackMapTable: number_of_entries = 1
        frame_type = 11 /* same */
      LineNumberTable:
        line 40: 0
      LocalVariableTable:
        Start  Length  Slot  Name   Signature
            0      16     0  this   Lorg/scalatest/tools/PrettyPrinter;

  public org.scalatest.tools.PrettyPrinter$Box$ Box();
    descriptor: ()Lorg/scalatest/tools/PrettyPrinter$Box$;
    flags: (0x0001) ACC_PUBLIC
    Code:
      stack=1, locals=1, args_size=1
         0: aload_0
         1: getfield      #69                 // Field Box$module:Lorg/scalatest/tools/PrettyPrinter$Box$;
         4: ifnonnull     11
         7: aload_0
         8: invokespecial #72                 // Method Box$lzycompute$1:()V
        11: aload_0
        12: getfield      #69                 // Field Box$module:Lorg/scalatest/tools/PrettyPrinter$Box$;
        15: areturn
      StackMapTable: number_of_entries = 1
        frame_type = 11 /* same */
      LineNumberTable:
        line 43: 0
      LocalVariableTable:
        Start  Length  Slot  Name   Signature
            0      16     0  this   Lorg/scalatest/tools/PrettyPrinter;

  public org.scalatest.tools.PrettyPrinter$Para$ Para();
    descriptor: ()Lorg/scalatest/tools/PrettyPrinter$Para$;
    flags: (0x0001) ACC_PUBLIC
    Code:
      stack=1, locals=1, args_size=1
         0: aload_0
         1: getfield      #75                 // Field Para$module:Lorg/scalatest/tools/PrettyPrinter$Para$;
         4: ifnonnull     11
         7: aload_0
         8: invokespecial #78                 // Method Para$lzycompute$1:()V
        11: aload_0
        12: getfield      #75                 // Field Para$module:Lorg/scalatest/tools/PrettyPrinter$Para$;
        15: areturn
      StackMapTable: number_of_entries = 1
        frame_type = 11 /* same */
      LineNumberTable:
        line 44: 0
      LocalVariableTable:
        Start  Length  Slot  Name   Signature
            0      16     0  this   Lorg/scalatest/tools/PrettyPrinter;

  public scala.Enumeration$Value minimizeMode();
    descriptor: ()Lscala/Enumeration$Value;
    flags: (0x0001) ACC_PUBLIC
    Code:
      stack=1, locals=1, args_size=1
         0: aload_0
         1: getfield      #81                 // Field minimizeMode:Lscala/Enumeration$Value;
         4: areturn
      LineNumberTable:
        line 36: 0
      LocalVariableTable:
        Start  Length  Slot  Name   Signature
            0       5     0  this   Lorg/scalatest/tools/PrettyPrinter;

  public scala.collection.immutable.List<org.scalatest.tools.PrettyPrinter$Item> items();
    descriptor: ()Lscala/collection/immutable/List;
    flags: (0x0001) ACC_PUBLIC
    Code:
      stack=1, locals=1, args_size=1
         0: aload_0
         1: getfield      #85                 // Field items:Lscala/collection/immutable/List;
         4: areturn
      LineNumberTable:
        line 46: 0
      LocalVariableTable:
        Start  Length  Slot  Name   Signature
            0       5     0  this   Lorg/scalatest/tools/PrettyPrinter;
    Signature: #83                          // ()Lscala/collection/immutable/List<Lorg/scalatest/tools/PrettyPrinter$Item;>;

  public void items_$eq(scala.collection.immutable.List<org.scalatest.tools.PrettyPrinter$Item>);
    descriptor: (Lscala/collection/immutable/List;)V
    flags: (0x0001) ACC_PUBLIC
    Code:
      stack=2, locals=2, args_size=2
         0: aload_0
         1: aload_1
         2: putfield      #85                 // Field items:Lscala/collection/immutable/List;
         5: return
      LineNumberTable:
        line 46: 0
      LocalVariableTable:
        Start  Length  Slot  Name   Signature
            0       6     0  this   Lorg/scalatest/tools/PrettyPrinter;
            0       6     1   x$1   Lscala/collection/immutable/List;
    Signature: #88                          // (Lscala/collection/immutable/List<Lorg/scalatest/tools/PrettyPrinter$Item;>;)V
    MethodParameters:
      Name                           Flags
      x$1                            final

  public int cur();
    descriptor: ()I
    flags: (0x0001) ACC_PUBLIC
    Code:
      stack=1, locals=1, args_size=1
         0: aload_0
         1: getfield      #92                 // Field cur:I
         4: ireturn
      LineNumberTable:
        line 48: 0
      LocalVariableTable:
        Start  Length  Slot  Name   Signature
            0       5     0  this   Lorg/scalatest/tools/PrettyPrinter;

  public void cur_$eq(int);
    descriptor: (I)V
    flags: (0x0001) ACC_PUBLIC
    Code:
      stack=2, locals=2, args_size=2
         0: aload_0
         1: iload_1
         2: putfield      #92                 // Field cur:I
         5: return
      LineNumberTable:
        line 48: 0
      LocalVariableTable:
        Start  Length  Slot  Name   Signature
            0       6     0  this   Lorg/scalatest/tools/PrettyPrinter;
            0       6     1   x$1   I
    MethodParameters:
      Name                           Flags
      x$1                            final

  public void reset();
    descriptor: ()V
    flags: (0x0001) ACC_PUBLIC
    Code:
      stack=2, locals=1, args_size=1
         0: aload_0
         1: iconst_0
         2: invokevirtual #97                 // Method cur_$eq:(I)V
         5: aload_0
         6: getstatic     #103                // Field scala/package$.MODULE$:Lscala/package$;
         9: invokevirtual #107                // Method scala/package$.Nil:()Lscala/collection/immutable/Nil$;
        12: invokevirtual #109                // Method items_$eq:(Lscala/collection/immutable/List;)V
        15: return
      LineNumberTable:
        line 51: 0
        line 52: 5
      LocalVariableTable:
        Start  Length  Slot  Name   Signature
            0      16     0  this   Lorg/scalatest/tools/PrettyPrinter;

  public scala.collection.immutable.List<org.scalatest.tools.PrettyPrinter$Item> cut(java.lang.String, int);
    descriptor: (Ljava/lang/String;I)Lscala/collection/immutable/List;
    flags: (0x0001) ACC_PUBLIC
    Code:
      stack=10, locals=12, args_size=3
         0: aload_0
         1: getfield      #116                // Field width:I
         4: aload_0
         5: invokevirtual #118                // Method cur:()I
         8: isub
         9: istore_3
        10: aload_1
        11: invokevirtual #123                // Method java/lang/String.length:()I
        14: iload_3
        15: if_icmpgt     57
        18: getstatic     #103                // Field scala/package$.MODULE$:Lscala/package$;
        21: invokevirtual #127                // Method scala/package$.List:()Lscala/collection/immutable/List$;
        24: getstatic     #132                // Field scala/runtime/ScalaRunTime$.MODULE$:Lscala/runtime/ScalaRunTime$;
        27: iconst_1
        28: anewarray     #15                 // class org/scalatest/tools/PrettyPrinter$Box
        31: dup
        32: iconst_0
        33: new           #15                 // class org/scalatest/tools/PrettyPrinter$Box
        36: dup
        37: aload_0
        38: iload_2
        39: aload_1
        40: invokespecial #136                // Method org/scalatest/tools/PrettyPrinter$Box."<init>":(Lorg/scalatest/tools/PrettyPrinter;ILjava/lang/String;)V
        43: aastore
        44: checkcast     #138                // class "[Ljava/lang/Object;"
        47: invokevirtual #142                // Method scala/runtime/ScalaRunTime$.wrapRefArray:([Ljava/lang/Object;)Lscala/collection/immutable/ArraySeq;
        50: invokevirtual #148                // Method scala/collection/immutable/List$.apply:(Lscala/collection/immutable/Seq;)Ljava/lang/Object;
        53: checkcast     #150                // class scala/collection/immutable/List
        56: areturn
        57: aload_1
        58: bipush        32
        60: invokevirtual #154                // Method java/lang/String.indexOf:(I)I
        63: istore        4
        65: iload         4
        67: iload_3
        68: if_icmpgt     77
        71: iload         4
        73: iconst_m1
        74: if_icmpne     86
        77: new           #24                 // class org/scalatest/tools/PrettyPrinter$BrokenException
        80: dup
        81: aload_0
        82: invokespecial #157                // Method org/scalatest/tools/PrettyPrinter$BrokenException."<init>":(Lorg/scalatest/tools/PrettyPrinter;)V
        85: athrow
        86: getstatic     #103                // Field scala/package$.MODULE$:Lscala/package$;
        89: invokevirtual #107                // Method scala/package$.Nil:()Lscala/collection/immutable/Nil$;
        92: astore        5
        94: iload         4
        96: iconst_m1
        97: if_icmpeq     137
       100: iload         4
       102: iload_3
       103: if_icmpge     137
       106: iload         4
       108: istore        6
       110: aload         5
       112: iload         6
       114: invokestatic  #163                // Method scala/runtime/BoxesRunTime.boxToInteger:(I)Ljava/lang/Integer;
       117: invokevirtual #167                // Method scala/collection/immutable/List.$colon$colon:(Ljava/lang/Object;)Lscala/collection/immutable/List;
       120: astore        5
       122: aload_1
       123: bipush        32
       125: iload         4
       127: iconst_1
       128: iadd
       129: invokevirtual #170                // Method java/lang/String.indexOf:(II)I
       132: istore        4
       134: goto          94
       137: getstatic     #103                // Field scala/package$.MODULE$:Lscala/package$;
       140: invokevirtual #107                // Method scala/package$.Nil:()Lscala/collection/immutable/Nil$;
       143: astore        7
       145: getstatic     #103                // Field scala/package$.MODULE$:Lscala/package$;
       148: invokevirtual #107                // Method scala/package$.Nil:()Lscala/collection/immutable/Nil$;
       151: aload         5
       153: astore        8
       155: dup
       156: ifnonnull     168
       159: pop
       160: aload         8
       162: ifnull        278
       165: goto          176
       168: aload         8
       170: invokevirtual #174                // Method java/lang/Object.equals:(Ljava/lang/Object;)Z
       173: ifne          278
       176: new           #15                 // class org/scalatest/tools/PrettyPrinter$Box
       179: dup
       180: aload_0
       181: iload_2
       182: aload_1
       183: iconst_0
       184: aload         5
       186: invokevirtual #178                // Method scala/collection/immutable/List.head:()Ljava/lang/Object;
       189: invokestatic  #182                // Method scala/runtime/BoxesRunTime.unboxToInt:(Ljava/lang/Object;)I
       192: invokevirtual #186                // Method java/lang/String.substring:(II)Ljava/lang/String;
       195: invokespecial #136                // Method org/scalatest/tools/PrettyPrinter$Box."<init>":(Lorg/scalatest/tools/PrettyPrinter;ILjava/lang/String;)V
       198: astore        9
       200: aload_0
       201: iload_2
       202: invokevirtual #97                 // Method cur_$eq:(I)V
       205: aload         9
       207: astore        10
       209: aload_0
       210: invokevirtual #188                // Method Break:()Lorg/scalatest/tools/PrettyPrinter$Break$;
       213: astore        11
       215: aload_0
       216: aload_1
       217: aload         5
       219: invokevirtual #178                // Method scala/collection/immutable/List.head:()Ljava/lang/Object;
       222: invokestatic  #182                // Method scala/runtime/BoxesRunTime.unboxToInt:(Ljava/lang/Object;)I
       225: aload_1
       226: invokevirtual #123                // Method java/lang/String.length:()I
       229: invokevirtual #186                // Method java/lang/String.substring:(II)Ljava/lang/String;
       232: iload_2
       233: invokevirtual #190                // Method cut:(Ljava/lang/String;I)Lscala/collection/immutable/List;
       236: aload         11
       238: invokevirtual #167                // Method scala/collection/immutable/List.$colon$colon:(Ljava/lang/Object;)Lscala/collection/immutable/List;
       241: aload         10
       243: invokevirtual #167                // Method scala/collection/immutable/List.$colon$colon:(Ljava/lang/Object;)Lscala/collection/immutable/List;
       246: astore        7
       248: aload         5
       250: invokevirtual #193                // Method scala/collection/immutable/List.tail:()Ljava/lang/Object;
       253: checkcast     #150                // class scala/collection/immutable/List
       256: astore        5
       258: goto          275
       261: pop
       262: aload         5
       264: invokevirtual #193                // Method scala/collection/immutable/List.tail:()Ljava/lang/Object;
       267: checkcast     #150                // class scala/collection/immutable/List
       270: astore        5
       272: goto          275
       275: goto          145
       278: new           #24                 // class org/scalatest/tools/PrettyPrinter$BrokenException
       281: dup
       282: aload_0
       283: invokespecial #157                // Method org/scalatest/tools/PrettyPrinter$BrokenException."<init>":(Lorg/scalatest/tools/PrettyPrinter;)V
       286: athrow
      Exception table:
         from    to  target type
           176   258   261   Class org/scalatest/tools/PrettyPrinter$BrokenException
      StackMapTable: number_of_entries = 11
        frame_type = 252 /* append */
          offset_delta = 57
          locals = [ int ]
        frame_type = 252 /* append */
          offset_delta = 19
          locals = [ int ]
        frame_type = 8 /* same */
        frame_type = 252 /* append */
          offset_delta = 7
          locals = [ class scala/collection/immutable/List ]
        frame_type = 42 /* same */
        frame_type = 253 /* append */
          offset_delta = 7
          locals = [ top, class scala/collection/immutable/List ]
        frame_type = 255 /* full_frame */
          offset_delta = 22
          locals = [ class org/scalatest/tools/PrettyPrinter, class java/lang/String, int, int, int, class scala/collection/immutable/List, top, class scala/collection/immutable/List, class scala/collection/immutable/List ]
          stack = [ class scala/collection/immutable/Nil$ ]
        frame_type = 7 /* same */
        frame_type = 247 /* same_locals_1_stack_item_frame_extended */
          offset_delta = 84
          stack = [ class org/scalatest/tools/PrettyPrinter$BrokenException ]
        frame_type = 13 /* same */
        frame_type = 2 /* same */
      LineNumberTable:
        line 59: 0
        line 60: 10
        line 61: 18
        line 62: 57
        line 63: 65
        line 65: 86
        line 66: 94
        line 67: 106
        line 68: 122
        line 66: 134
        line 70: 137
        line 71: 145
        line 72: 176
        line 73: 200
        line 74: 205
        line 76: 248
        line 78: 262
        line 71: 275
        line 80: 278
      LocalVariableTable:
        Start  Length  Slot  Name   Signature
          200      58     9     b   Lorg/scalatest/tools/PrettyPrinter$Box;
           10     277     3   tmp   I
           65     222     4     i   I
           94     193     5  last   Lscala/collection/immutable/List;
          145     142     7   res   Lscala/collection/immutable/List;
            0     287     0  this   Lorg/scalatest/tools/PrettyPrinter;
            0     287     1     s   Ljava/lang/String;
            0     287     2   ind   I
    Signature: #112                         // (Ljava/lang/String;I)Lscala/collection/immutable/List<Lorg/scalatest/tools/PrettyPrinter$Item;>;
    MethodParameters:
      Name                           Flags
      s                              final
      ind                            final

  public void makeBox(int, java.lang.String);
    descriptor: (ILjava/lang/String;)V
    flags: (0x0001) ACC_PUBLIC
    Code:
      stack=7, locals=3, args_size=3
         0: aload_0
         1: invokevirtual #118                // Method cur:()I
         4: aload_2
         5: invokevirtual #123                // Method java/lang/String.length:()I
         8: iadd
         9: aload_0
        10: getfield      #116                // Field width:I
        13: if_icmple     53
        16: aload_0
        17: aload_0
        18: invokevirtual #206                // Method items:()Lscala/collection/immutable/List;
        21: new           #15                 // class org/scalatest/tools/PrettyPrinter$Box
        24: dup
        25: aload_0
        26: iload_1
        27: aload_2
        28: invokespecial #136                // Method org/scalatest/tools/PrettyPrinter$Box."<init>":(Lorg/scalatest/tools/PrettyPrinter;ILjava/lang/String;)V
        31: invokevirtual #167                // Method scala/collection/immutable/List.$colon$colon:(Ljava/lang/Object;)Lscala/collection/immutable/List;
        34: invokevirtual #109                // Method items_$eq:(Lscala/collection/immutable/List;)V
        37: aload_0
        38: aload_0
        39: invokevirtual #118                // Method cur:()I
        42: aload_2
        43: invokevirtual #123                // Method java/lang/String.length:()I
        46: iadd
        47: invokevirtual #97                 // Method cur_$eq:(I)V
        50: goto          81
        53: aload_0
        54: aload_2
        55: iload_1
        56: invokevirtual #190                // Method cut:(Ljava/lang/String;I)Lscala/collection/immutable/List;
        59: aload_0
        60: invokedynamic #227,  0            // InvokeDynamic #0:apply:(Lorg/scalatest/tools/PrettyPrinter;)Lscala/Function1;
        65: invokevirtual #231                // Method scala/collection/immutable/List.foreach:(Lscala/Function1;)V
        68: goto          81
        71: pop
        72: aload_0
        73: iload_1
        74: aload_2
        75: invokevirtual #234                // Method makePara:(ILjava/lang/String;)V
        78: goto          81
        81: return
      Exception table:
         from    to  target type
            53    68    71   Class org/scalatest/tools/PrettyPrinter$BrokenException
      StackMapTable: number_of_entries = 3
        frame_type = 53 /* same */
        frame_type = 81 /* same_locals_1_stack_item */
          stack = [ class org/scalatest/tools/PrettyPrinter$BrokenException ]
        frame_type = 9 /* same */
      LineNumberTable:
        line 87: 0
        line 88: 16
        line 89: 37
        line 90: 53
        line 91: 72
      LocalVariableTable:
        Start  Length  Slot  Name   Signature
            0      82     0  this   Lorg/scalatest/tools/PrettyPrinter;
            0      82     1   ind   I
            0      82     2     s   Ljava/lang/String;
    MethodParameters:
      Name                           Flags
      ind                            final
      s                              final

  public void makePara(int, java.lang.String);
    descriptor: (ILjava/lang/String;)V
    flags: (0x0001) ACC_PUBLIC
    Code:
      stack=5, locals=6, args_size=3
         0: aload_0
         1: aload_0
         2: invokevirtual #188                // Method Break:()Lorg/scalatest/tools/PrettyPrinter$Break$;
         5: astore_3
         6: new           #30                 // class org/scalatest/tools/PrettyPrinter$Para
         9: dup
        10: aload_0
        11: aload_2
        12: invokespecial #237                // Method org/scalatest/tools/PrettyPrinter$Para."<init>":(Lorg/scalatest/tools/PrettyPrinter;Ljava/lang/String;)V
        15: astore        4
        17: aload_0
        18: invokevirtual #188                // Method Break:()Lorg/scalatest/tools/PrettyPrinter$Break$;
        21: astore        5
        23: aload_0
        24: invokevirtual #206                // Method items:()Lscala/collection/immutable/List;
        27: aload         5
        29: invokevirtual #167                // Method scala/collection/immutable/List.$colon$colon:(Ljava/lang/Object;)Lscala/collection/immutable/List;
        32: aload         4
        34: invokevirtual #167                // Method scala/collection/immutable/List.$colon$colon:(Ljava/lang/Object;)Lscala/collection/immutable/List;
        37: aload_3
        38: invokevirtual #167                // Method scala/collection/immutable/List.$colon$colon:(Ljava/lang/Object;)Lscala/collection/immutable/List;
        41: invokevirtual #109                // Method items_$eq:(Lscala/collection/immutable/List;)V
        44: aload_0
        45: iload_1
        46: invokevirtual #97                 // Method cur_$eq:(I)V
        49: return
      LineNumberTable:
        line 95: 0
        line 96: 44
      LocalVariableTable:
        Start  Length  Slot  Name   Signature
            0      50     0  this   Lorg/scalatest/tools/PrettyPrinter;
            0      50     1   ind   I
            0      50     2     s   Ljava/lang/String;
    MethodParameters:
      Name                           Flags
      ind                            final
      s                              final

  public void makeBreak();
    descriptor: ()V
    flags: (0x0001) ACC_PUBLIC
    Code:
      stack=3, locals=2, args_size=1
         0: aload_0
         1: aload_0
         2: invokevirtual #188                // Method Break:()Lorg/scalatest/tools/PrettyPrinter$Break$;
         5: astore_1
         6: aload_0
         7: invokevirtual #206                // Method items:()Lscala/collection/immutable/List;
        10: aload_1
        11: invokevirtual #167                // Method scala/collection/immutable/List.$colon$colon:(Ljava/lang/Object;)Lscala/collection/immutable/List;
        14: invokevirtual #109                // Method items_$eq:(Lscala/collection/immutable/List;)V
        17: aload_0
        18: iconst_0
        19: invokevirtual #97                 // Method cur_$eq:(I)V
        22: return
      LineNumberTable:
        line 101: 0
        line 102: 17
      LocalVariableTable:
        Start  Length  Slot  Name   Signature
            0      23     0  this   Lorg/scalatest/tools/PrettyPrinter;

  public java.lang.String leafTag(scala.xml.Node);
    descriptor: (Lscala/xml/Node;)Ljava/lang/String;
    flags: (0x0001) ACC_PUBLIC
    Code:
      stack=2, locals=2, args_size=2
         0: getstatic     #246                // Field org/scalatest/tools/XmlUtility$.MODULE$:Lorg/scalatest/tools/XmlUtility$;
         3: aload_1
         4: invokedynamic #256,  0            // InvokeDynamic #1:apply:(Lscala/xml/Node;)Lscala/Function1;
         9: invokevirtual #260                // Method org/scalatest/tools/XmlUtility$.sbToString:(Lscala/Function1;)Ljava/lang/String;
        12: areturn
      LineNumberTable:
        line 112: 0
      LocalVariableTable:
        Start  Length  Slot  Name   Signature
            0      13     0  this   Lorg/scalatest/tools/PrettyPrinter;
            0      13     1     n   Lscala/xml/Node;
    MethodParameters:
      Name                           Flags
      n                              final

  public scala.Tuple2<java.lang.String, java.lang.Object> startTag(scala.xml.Node, scala.xml.NamespaceBinding);
    descriptor: (Lscala/xml/Node;Lscala/xml/NamespaceBinding;)Lscala/Tuple2;
    flags: (0x0001) ACC_PUBLIC
    Code:
      stack=6, locals=4, args_size=3
         0: iconst_0
         1: invokestatic  #271                // Method scala/runtime/IntRef.create:(I)Lscala/runtime/IntRef;
         4: astore_3
         5: new           #273                // class scala/Tuple2
         8: dup
         9: getstatic     #246                // Field org/scalatest/tools/XmlUtility$.MODULE$:Lorg/scalatest/tools/XmlUtility$;
        12: aload_1
        13: aload_3
        14: aload_2
        15: invokedynamic #281,  0            // InvokeDynamic #2:apply:(Lscala/xml/Node;Lscala/runtime/IntRef;Lscala/xml/NamespaceBinding;)Lscala/Function1;
        20: invokevirtual #260                // Method org/scalatest/tools/XmlUtility$.sbToString:(Lscala/Function1;)Ljava/lang/String;
        23: aload_3
        24: getfield      #284                // Field scala/runtime/IntRef.elem:I
        27: invokestatic  #163                // Method scala/runtime/BoxesRunTime.boxToInteger:(I)Ljava/lang/Integer;
        30: invokespecial #287                // Method scala/Tuple2."<init>":(Ljava/lang/Object;Ljava/lang/Object;)V
        33: areturn
      LineNumberTable:
        line 116: 0
        line 125: 5
      LocalVariableTable:
        Start  Length  Slot  Name   Signature
            5      28     3     i   Lscala/runtime/IntRef;
            0      34     0  this   Lorg/scalatest/tools/PrettyPrinter;
            0      34     1     n   Lscala/xml/Node;
            0      34     2 pscope   Lscala/xml/NamespaceBinding;
    Signature: #264                         // (Lscala/xml/Node;Lscala/xml/NamespaceBinding;)Lscala/Tuple2<Ljava/lang/String;Ljava/lang/Object;>;
    MethodParameters:
      Name                           Flags
      n                              final
      pscope                         final

  public java.lang.String endTag(scala.xml.Node);
    descriptor: (Lscala/xml/Node;)Ljava/lang/String;
    flags: (0x0001) ACC_PUBLIC
    Code:
      stack=2, locals=2, args_size=2
         0: getstatic     #246                // Field org/scalatest/tools/XmlUtility$.MODULE$:Lorg/scalatest/tools/XmlUtility$;
         3: aload_1
         4: invokedynamic #295,  0            // InvokeDynamic #3:apply:(Lscala/xml/Node;)Lscala/Function1;
         9: invokevirtual #260                // Method org/scalatest/tools/XmlUtility$.sbToString:(Lscala/Function1;)Ljava/lang/String;
        12: areturn
      LineNumberTable:
        line 134: 0
      LocalVariableTable:
        Start  Length  Slot  Name   Signature
            0      13     0  this   Lorg/scalatest/tools/PrettyPrinter;
            0      13     1     n   Lscala/xml/Node;
    MethodParameters:
      Name                           Flags
      n                              final

  public boolean childrenAreLeaves(scala.xml.Node);
    descriptor: (Lscala/xml/Node;)Z
    flags: (0x0001) ACC_PUBLIC
    Code:
      stack=2, locals=2, args_size=2
         0: aload_1
         1: invokevirtual #303                // Method scala/xml/Node.child:()Lscala/collection/Seq;
         4: invokedynamic #312,  0            // InvokeDynamic #4:apply:()Lscala/Function1;
         9: invokeinterface #318,  2          // InterfaceMethod scala/collection/Seq.forall:(Lscala/Function1;)Z
        14: ireturn
      LineNumberTable:
        line 142: 0
      LocalVariableTable:
        Start  Length  Slot  Name   Signature
            0      15     0  this   Lorg/scalatest/tools/PrettyPrinter;
            0      15     1     n   Lscala/xml/Node;
    MethodParameters:
      Name                           Flags
      n                              final

  public boolean fits(java.lang.String);
    descriptor: (Ljava/lang/String;)Z
    flags: (0x0001) ACC_PUBLIC
    Code:
      stack=3, locals=2, args_size=2
         0: aload_1
         1: invokevirtual #123                // Method java/lang/String.length:()I
         4: aload_0
         5: getfield      #116                // Field width:I
         8: aload_0
         9: invokevirtual #118                // Method cur:()I
        12: isub
        13: if_icmpge     20
        16: iconst_1
        17: goto          21
        20: iconst_0
        21: ireturn
      StackMapTable: number_of_entries = 2
        frame_type = 20 /* same */
        frame_type = 64 /* same_locals_1_stack_item */
          stack = [ int ]
      LineNumberTable:
        line 146: 0
      LocalVariableTable:
        Start  Length  Slot  Name   Signature
            0      22     0  this   Lorg/scalatest/tools/PrettyPrinter;
            0      22     1  test   Ljava/lang/String;
    MethodParameters:
      Name                           Flags
      test                           final

  private boolean doPreserve(scala.xml.Node);
    descriptor: (Lscala/xml/Node;)Z
    flags: (0x0002) ACC_PRIVATE
    Code:
      stack=3, locals=2, args_size=2
         0: aload_1
         1: getstatic     #328                // Field scala/xml/XML$.MODULE$:Lscala/xml/XML$;
         4: invokevirtual #332                // Method scala/xml/XML$.namespace:()Ljava/lang/String;
         7: getstatic     #328                // Field scala/xml/XML$.MODULE$:Lscala/xml/XML$;
        10: invokevirtual #335                // Method scala/xml/XML$.space:()Ljava/lang/String;
        13: invokevirtual #339                // Method scala/xml/Node.attribute:(Ljava/lang/String;Ljava/lang/String;)Lscala/Option;
        16: invokedynamic #346,  0            // InvokeDynamic #5:apply:()Lscala/Function1;
        21: invokevirtual #352                // Method scala/Option.map:(Lscala/Function1;)Lscala/Option;
        24: invokedynamic #362,  0            // InvokeDynamic #6:apply$mcZ$sp:()Lscala/runtime/java8/JFunction0$mcZ$sp;
        29: invokevirtual #366                // Method scala/Option.getOrElse:(Lscala/Function0;)Ljava/lang/Object;
        32: invokestatic  #369                // Method scala/runtime/BoxesRunTime.unboxToBoolean:(Ljava/lang/Object;)Z
        35: ireturn
      LineNumberTable:
        line 149: 0
      LocalVariableTable:
        Start  Length  Slot  Name   Signature
            0      36     0  this   Lorg/scalatest/tools/PrettyPrinter;
            0      36     1  node   Lscala/xml/Node;
    MethodParameters:
      Name                           Flags
      node                           final

  public void traverse(scala.xml.Node, scala.xml.NamespaceBinding, int);
    descriptor: (Lscala/xml/Node;Lscala/xml/NamespaceBinding;I)V
    flags: (0x0001) ACC_PUBLIC
    Code:
      stack=8, locals=33, args_size=4
         0: aload_1
         1: astore        7
         3: aload         7
         5: ifnull        81
         8: getstatic     #376                // Field scala/xml/Text$.MODULE$:Lscala/xml/Text$;
        11: aload         7
        13: invokevirtual #380                // Method scala/xml/Text$.unapply:(Ljava/lang/Object;)Lscala/Option;
        16: astore        8
        18: aload         8
        20: invokevirtual #383                // Method scala/Option.isEmpty:()Z
        23: ifne          78
        26: aload         8
        28: invokevirtual #386                // Method scala/Option.get:()Ljava/lang/Object;
        31: checkcast     #120                // class java/lang/String
        34: astore        9
        36: aload         9
        38: invokevirtual #389                // Method java/lang/String.trim:()Ljava/lang/String;
        41: ldc_w         #391                // String
        44: astore        10
        46: dup
        47: ifnonnull     59
        50: pop
        51: aload         10
        53: ifnull        67
        56: goto          75
        59: aload         10
        61: invokevirtual #174                // Method java/lang/Object.equals:(Ljava/lang/Object;)Z
        64: ifeq          75
        67: getstatic     #397                // Field scala/runtime/BoxedUnit.UNIT:Lscala/runtime/BoxedUnit;
        70: astore        4
        72: goto          787
        75: goto          84
        78: goto          84
        81: goto          84
        84: aload         7
        86: instanceof    #399                // class scala/xml/Atom
        89: ifeq          98
        92: iconst_1
        93: istore        6
        95: goto          158
        98: goto          101
       101: aload         7
       103: instanceof    #401                // class scala/xml/Comment
       106: ifeq          115
       109: iconst_1
       110: istore        6
       112: goto          158
       115: goto          118
       118: aload         7
       120: instanceof    #403                // class scala/xml/EntityRef
       123: ifeq          132
       126: iconst_1
       127: istore        6
       129: goto          158
       132: goto          135
       135: aload         7
       137: instanceof    #405                // class scala/xml/ProcInstr
       140: ifeq          149
       143: iconst_1
       144: istore        6
       146: goto          158
       149: goto          152
       152: iconst_0
       153: istore        6
       155: goto          158
       158: iload         6
       160: ifeq          183
       163: aload_0
       164: iload_3
       165: aload_1
       166: invokevirtual #408                // Method scala/xml/Node.toString:()Ljava/lang/String;
       169: invokevirtual #389                // Method java/lang/String.trim:()Ljava/lang/String;
       172: invokevirtual #410                // Method makeBox:(ILjava/lang/String;)V
       175: getstatic     #397                // Field scala/runtime/BoxedUnit.UNIT:Lscala/runtime/BoxedUnit;
       178: astore        4
       180: goto          787
       183: goto          186
       186: aload         7
       188: instanceof    #412                // class scala/xml/Group
       191: ifeq          229
       194: aload         7
       196: checkcast     #412                // class scala/xml/Group
       199: astore        11
       201: aload         11
       203: invokevirtual #415                // Method scala/xml/Group.nodes:()Lscala/collection/Seq;
       206: astore        12
       208: aload_0
       209: aload         12
       211: invokeinterface #419,  1          // InterfaceMethod scala/collection/Seq.iterator:()Lscala/collection/Iterator;
       216: aload_2
       217: iload_3
       218: invokevirtual #422                // Method traverse:(Lscala/collection/Iterator;Lscala/xml/NamespaceBinding;I)V
       221: getstatic     #397                // Field scala/runtime/BoxedUnit.UNIT:Lscala/runtime/BoxedUnit;
       224: astore        4
       226: goto          787
       229: goto          232
       232: new           #424                // class scala/collection/mutable/StringBuilder
       235: dup
       236: invokespecial #426                // Method scala/collection/mutable/StringBuilder."<init>":()V
       239: astore        14
       241: aload_1
       242: astore        15
       244: aload_2
       245: astore        16
       247: aload         14
       249: astore        17
       251: iconst_0
       252: istore        18
       254: aload_0
       255: invokevirtual #428                // Method minimizeMode:()Lscala/Enumeration$Value;
       258: astore        19
       260: getstatic     #246                // Field org/scalatest/tools/XmlUtility$.MODULE$:Lorg/scalatest/tools/XmlUtility$;
       263: invokevirtual #431                // Method org/scalatest/tools/XmlUtility$.serialize$default$5:()Z
       266: istore        20
       268: getstatic     #246                // Field org/scalatest/tools/XmlUtility$.MODULE$:Lorg/scalatest/tools/XmlUtility$;
       271: invokevirtual #434                // Method org/scalatest/tools/XmlUtility$.serialize$default$6:()Z
       274: istore        21
       276: getstatic     #246                // Field org/scalatest/tools/XmlUtility$.MODULE$:Lorg/scalatest/tools/XmlUtility$;
       279: aload         15
       281: aload         16
       283: aload         17
       285: iconst_0
       286: iload         20
       288: iload         21
       290: aload         19
       292: invokevirtual #438                // Method org/scalatest/tools/XmlUtility$.serialize:(Lscala/xml/Node;Lscala/xml/NamespaceBinding;Lscala/collection/mutable/StringBuilder;ZZZLscala/Enumeration$Value;)Lscala/collection/mutable/StringBuilder;
       295: pop
       296: aload_0
       297: aload_1
       298: invokespecial #440                // Method doPreserve:(Lscala/xml/Node;)Z
       301: ifeq          312
       304: aload         14
       306: invokevirtual #441                // Method scala/collection/mutable/StringBuilder.toString:()Ljava/lang/String;
       309: goto          341
       312: getstatic     #446                // Field scala/xml/TextBuffer$.MODULE$:Lscala/xml/TextBuffer$;
       315: aload         14
       317: invokevirtual #441                // Method scala/collection/mutable/StringBuilder.toString:()Ljava/lang/String;
       320: invokevirtual #450                // Method scala/xml/TextBuffer$.fromString:(Ljava/lang/String;)Lscala/xml/TextBuffer;
       323: invokevirtual #455                // Method scala/xml/TextBuffer.toText:()Lscala/collection/Seq;
       326: iconst_0
       327: invokeinterface #458,  2          // InterfaceMethod scala/collection/Seq.apply:(I)Ljava/lang/Object;
       332: checkcast     #399                // class scala/xml/Atom
       335: invokevirtual #461                // Method scala/xml/Atom.data:()Ljava/lang/Object;
       338: checkcast     #120                // class java/lang/String
       341: astore        13
       343: aload_0
       344: aload_1
       345: invokevirtual #463                // Method childrenAreLeaves:(Lscala/xml/Node;)Z
       348: ifeq          373
       351: aload_0
       352: aload         13
       354: invokevirtual #465                // Method fits:(Ljava/lang/String;)Z
       357: ifeq          373
       360: aload_0
       361: iload_3
       362: aload         13
       364: invokevirtual #410                // Method makeBox:(ILjava/lang/String;)V
       367: getstatic     #397                // Field scala/runtime/BoxedUnit.UNIT:Lscala/runtime/BoxedUnit;
       370: goto          782
       373: aload_1
       374: invokevirtual #303                // Method scala/xml/Node.child:()Lscala/collection/Seq;
       377: invokeinterface #466,  1          // InterfaceMethod scala/collection/Seq.isEmpty:()Z
       382: ifeq          448
       385: aload_0
       386: getfield      #468                // Field minimizeEmpty:Z
       389: ifeq          448
       392: aload         13
       394: bipush        32
       396: invokevirtual #154                // Method java/lang/String.indexOf:(I)I
       399: istore        24
       401: iload         24
       403: iconst_m1
       404: if_icmpeq     412
       407: iload         24
       409: goto          419
       412: aload         13
       414: bipush        47
       416: invokevirtual #471                // Method java/lang/String.lastIndexOf:(I)I
       419: istore        25
       421: new           #273                // class scala/Tuple2
       424: dup
       425: new           #273                // class scala/Tuple2
       428: dup
       429: aload         13
       431: iload         25
       433: invokestatic  #163                // Method scala/runtime/BoxesRunTime.boxToInteger:(I)Ljava/lang/Integer;
       436: invokespecial #287                // Method scala/Tuple2."<init>":(Ljava/lang/Object;Ljava/lang/Object;)V
       439: ldc_w         #391                // String
       442: invokespecial #287                // Method scala/Tuple2."<init>":(Ljava/lang/Object;Ljava/lang/Object;)V
       445: goto          466
       448: new           #273                // class scala/Tuple2
       451: dup
       452: aload_0
       453: aload_1
       454: aload_2
       455: invokevirtual #473                // Method startTag:(Lscala/xml/Node;Lscala/xml/NamespaceBinding;)Lscala/Tuple2;
       458: aload_0
       459: aload_1
       460: invokevirtual #475                // Method endTag:(Lscala/xml/Node;)Ljava/lang/String;
       463: invokespecial #287                // Method scala/Tuple2."<init>":(Ljava/lang/Object;Ljava/lang/Object;)V
       466: astore        23
       468: aload         23
       470: ifnull        539
       473: aload         23
       475: invokevirtual #478                // Method scala/Tuple2._1:()Ljava/lang/Object;
       478: checkcast     #273                // class scala/Tuple2
       481: astore        26
       483: aload         23
       485: invokevirtual #481                // Method scala/Tuple2._2:()Ljava/lang/Object;
       488: checkcast     #120                // class java/lang/String
       491: astore        27
       493: aload         26
       495: ifnull        536
       498: aload         26
       500: invokevirtual #478                // Method scala/Tuple2._1:()Ljava/lang/Object;
       503: checkcast     #120                // class java/lang/String
       506: astore        28
       508: aload         26
       510: invokevirtual #484                // Method scala/Tuple2._2$mcI$sp:()I
       513: istore        29
       515: new           #486                // class scala/Tuple3
       518: dup
       519: aload         28
       521: iload         29
       523: invokestatic  #163                // Method scala/runtime/BoxesRunTime.boxToInteger:(I)Ljava/lang/Integer;
       526: aload         27
       528: invokespecial #489                // Method scala/Tuple3."<init>":(Ljava/lang/Object;Ljava/lang/Object;Ljava/lang/Object;)V
       531: astore        5
       533: goto          552
       536: goto          542
       539: goto          542
       542: new           #491                // class scala/MatchError
       545: dup
       546: aload         23
       548: invokespecial #494                // Method scala/MatchError."<init>":(Ljava/lang/Object;)V
       551: athrow
       552: aload         5
       554: astore        22
       556: aload         22
       558: invokevirtual #495                // Method scala/Tuple3._1:()Ljava/lang/Object;
       561: checkcast     #120                // class java/lang/String
       564: astore        30
       566: aload         22
       568: invokevirtual #496                // Method scala/Tuple3._2:()Ljava/lang/Object;
       571: invokestatic  #182                // Method scala/runtime/BoxesRunTime.unboxToInt:(Ljava/lang/Object;)I
       574: istore        31
       576: aload         22
       578: invokevirtual #499                // Method scala/Tuple3._3:()Ljava/lang/Object;
       581: checkcast     #120                // class java/lang/String
       584: astore        32
       586: aload         30
       588: invokevirtual #123                // Method java/lang/String.length:()I
       591: aload_0
       592: getfield      #116                // Field width:I
       595: aload_0
       596: invokevirtual #118                // Method cur:()I
       599: isub
       600: if_icmpge     650
       603: aload_0
       604: iload_3
       605: aload         30
       607: invokevirtual #410                // Method makeBox:(ILjava/lang/String;)V
       610: aload_0
       611: invokevirtual #501                // Method makeBreak:()V
       614: aload_0
       615: aload_1
       616: invokevirtual #303                // Method scala/xml/Node.child:()Lscala/collection/Seq;
       619: invokeinterface #419,  1          // InterfaceMethod scala/collection/Seq.iterator:()Lscala/collection/Iterator;
       624: aload_1
       625: invokevirtual #505                // Method scala/xml/Node.scope:()Lscala/xml/NamespaceBinding;
       628: iload_3
       629: aload_0
       630: getfield      #507                // Field step:I
       633: iadd
       634: invokevirtual #422                // Method traverse:(Lscala/collection/Iterator;Lscala/xml/NamespaceBinding;I)V
       637: aload_0
       638: iload_3
       639: aload         32
       641: invokevirtual #410                // Method makeBox:(ILjava/lang/String;)V
       644: getstatic     #397                // Field scala/runtime/BoxedUnit.UNIT:Lscala/runtime/BoxedUnit;
       647: goto          782
       650: iload         31
       652: aload_0
       653: getfield      #116                // Field width:I
       656: aload_0
       657: invokevirtual #118                // Method cur:()I
       660: isub
       661: if_icmpge     768
       664: aload_0
       665: iload_3
       666: aload         30
       668: iconst_0
       669: iload         31
       671: invokevirtual #186                // Method java/lang/String.substring:(II)Ljava/lang/String;
       674: invokevirtual #410                // Method makeBox:(ILjava/lang/String;)V
       677: aload_0
       678: invokevirtual #501                // Method makeBreak:()V
       681: aload_0
       682: iload_3
       683: aload         30
       685: iload         31
       687: aload         30
       689: invokevirtual #123                // Method java/lang/String.length:()I
       692: invokevirtual #186                // Method java/lang/String.substring:(II)Ljava/lang/String;
       695: invokevirtual #389                // Method java/lang/String.trim:()Ljava/lang/String;
       698: invokevirtual #410                // Method makeBox:(ILjava/lang/String;)V
       701: getstatic     #512                // Field scala/collection/StringOps$.MODULE$:Lscala/collection/StringOps$;
       704: getstatic     #517                // Field scala/Predef$.MODULE$:Lscala/Predef$;
       707: aload         32
       709: invokevirtual #521                // Method scala/Predef$.augmentString:(Ljava/lang/String;)Ljava/lang/String;
       712: invokevirtual #524                // Method scala/collection/StringOps$.nonEmpty$extension:(Ljava/lang/String;)Z
       715: ifeq          758
       718: aload_0
       719: invokevirtual #501                // Method makeBreak:()V
       722: aload_0
       723: aload_1
       724: invokevirtual #303                // Method scala/xml/Node.child:()Lscala/collection/Seq;
       727: invokeinterface #419,  1          // InterfaceMethod scala/collection/Seq.iterator:()Lscala/collection/Iterator;
       732: aload_1
       733: invokevirtual #505                // Method scala/xml/Node.scope:()Lscala/xml/NamespaceBinding;
       736: iload_3
       737: aload_0
       738: getfield      #507                // Field step:I
       741: iadd
       742: invokevirtual #422                // Method traverse:(Lscala/collection/Iterator;Lscala/xml/NamespaceBinding;I)V
       745: aload_0
       746: aload_0
       747: invokevirtual #118                // Method cur:()I
       750: aload         32
       752: invokevirtual #410                // Method makeBox:(ILjava/lang/String;)V
       755: goto          758
       758: aload_0
       759: invokevirtual #501                // Method makeBreak:()V
       762: getstatic     #397                // Field scala/runtime/BoxedUnit.UNIT:Lscala/runtime/BoxedUnit;
       765: goto          782
       768: aload_0
       769: iload_3
       770: aload         13
       772: invokevirtual #410                // Method makeBox:(ILjava/lang/String;)V
       775: aload_0
       776: invokevirtual #501                // Method makeBreak:()V
       779: getstatic     #397                // Field scala/runtime/BoxedUnit.UNIT:Lscala/runtime/BoxedUnit;
       782: astore        4
       784: goto          787
       787: return
      StackMapTable: number_of_entries = 35
        frame_type = 255 /* full_frame */
          offset_delta = 59
          locals = [ class org/scalatest/tools/PrettyPrinter, class scala/xml/Node, class scala/xml/NamespaceBinding, int, top, top, top, class scala/xml/Node, class scala/Option, class java/lang/String, class java/lang/String ]
          stack = [ class java/lang/String ]
        frame_type = 7 /* same */
        frame_type = 7 /* same */
        frame_type = 249 /* chop */
          offset_delta = 2
        frame_type = 250 /* chop */
          offset_delta = 2
        frame_type = 2 /* same */
        frame_type = 13 /* same */
        frame_type = 2 /* same */
        frame_type = 13 /* same */
        frame_type = 2 /* same */
        frame_type = 13 /* same */
        frame_type = 2 /* same */
        frame_type = 13 /* same */
        frame_type = 2 /* same */
        frame_type = 255 /* full_frame */
          offset_delta = 5
          locals = [ class org/scalatest/tools/PrettyPrinter, class scala/xml/Node, class scala/xml/NamespaceBinding, int, top, top, int, class scala/xml/Node ]
          stack = []
        frame_type = 24 /* same */
        frame_type = 2 /* same */
        frame_type = 42 /* same */
        frame_type = 2 /* same */
        frame_type = 255 /* full_frame */
          offset_delta = 79
          locals = [ class org/scalatest/tools/PrettyPrinter, class scala/xml/Node, class scala/xml/NamespaceBinding, int, top, top, int, class scala/xml/Node, top, top, top, top, top, top, class scala/collection/mutable/StringBuilder, class scala/xml/Node, class scala/xml/NamespaceBinding, class scala/collection/mutable/StringBuilder, int, class scala/Enumeration$Value, int, int ]
          stack = []
        frame_type = 92 /* same_locals_1_stack_item */
          stack = [ class java/lang/String ]
        frame_type = 255 /* full_frame */
          offset_delta = 31
          locals = [ class org/scalatest/tools/PrettyPrinter, class scala/xml/Node, class scala/xml/NamespaceBinding, int, top, top, int, class scala/xml/Node, top, top, top, top, top, class java/lang/String, class scala/collection/mutable/StringBuilder, class scala/xml/Node, class scala/xml/NamespaceBinding, class scala/collection/mutable/StringBuilder, int, class scala/Enumeration$Value, int, int ]
          stack = []
        frame_type = 254 /* append */
          offset_delta = 38
          locals = [ top, top, int ]
        frame_type = 70 /* same_locals_1_stack_item */
          stack = [ int ]
        frame_type = 248 /* chop */
          offset_delta = 28
        frame_type = 81 /* same_locals_1_stack_item */
          stack = [ class scala/Tuple2 ]
        frame_type = 255 /* full_frame */
          offset_delta = 69
          locals = [ class org/scalatest/tools/PrettyPrinter, class scala/xml/Node, class scala/xml/NamespaceBinding, int, top, top, int, class scala/xml/Node, top, top, top, top, top, class java/lang/String, class scala/collection/mutable/StringBuilder, class scala/xml/Node, class scala/xml/NamespaceBinding, class scala/collection/mutable/StringBuilder, int, class scala/Enumeration$Value, int, int, top, class scala/Tuple2, top, top, class scala/Tuple2, class java/lang/String ]
          stack = []
        frame_type = 255 /* full_frame */
          offset_delta = 2
          locals = [ class org/scalatest/tools/PrettyPrinter, class scala/xml/Node, class scala/xml/NamespaceBinding, int, top, top, int, class scala/xml/Node, top, top, top, top, top, class java/lang/String, class scala/collection/mutable/StringBuilder, class scala/xml/Node, class scala/xml/NamespaceBinding, class scala/collection/mutable/StringBuilder, int, class scala/Enumeration$Value, int, int, top, class scala/Tuple2 ]
          stack = []
        frame_type = 2 /* same */
        frame_type = 255 /* full_frame */
          offset_delta = 9
          locals = [ class org/scalatest/tools/PrettyPrinter, class scala/xml/Node, class scala/xml/NamespaceBinding, int, top, class scala/Tuple3, int, class scala/xml/Node, top, top, top, top, top, class java/lang/String, class scala/collection/mutable/StringBuilder, class scala/xml/Node, class scala/xml/NamespaceBinding, class scala/collection/mutable/StringBuilder, int, class scala/Enumeration$Value, int, int, top, class scala/Tuple2, top, top, class scala/Tuple2, class java/lang/String, class java/lang/String, int ]
          stack = []
        frame_type = 255 /* full_frame */
          offset_delta = 97
          locals = [ class org/scalatest/tools/PrettyPrinter, class scala/xml/Node, class scala/xml/NamespaceBinding, int, top, class scala/Tuple3, int, class scala/xml/Node, top, top, top, top, top, class java/lang/String, class scala/collection/mutable/StringBuilder, class scala/xml/Node, class scala/xml/NamespaceBinding, class scala/collection/mutable/StringBuilder, int, class scala/Enumeration$Value, int, int, class scala/Tuple3, class scala/Tuple2, top, top, class scala/Tuple2, class java/lang/String, class java/lang/String, int, class java/lang/String, int, class java/lang/String ]
          stack = []
        frame_type = 251 /* same_frame_extended */
          offset_delta = 107
        frame_type = 9 /* same */
        frame_type = 255 /* full_frame */
          offset_delta = 13
          locals = [ class org/scalatest/tools/PrettyPrinter, class scala/xml/Node, class scala/xml/NamespaceBinding, int, top, top, int, class scala/xml/Node, top, top, top, top, top, class java/lang/String, class scala/collection/mutable/StringBuilder, class scala/xml/Node, class scala/xml/NamespaceBinding, class scala/collection/mutable/StringBuilder, int, class scala/Enumeration$Value, int, int ]
          stack = [ class scala/runtime/BoxedUnit ]
        frame_type = 255 /* full_frame */
          offset_delta = 4
          locals = [ class org/scalatest/tools/PrettyPrinter, class scala/xml/Node, class scala/xml/NamespaceBinding, int, class scala/runtime/BoxedUnit, top, top, class scala/xml/Node ]
          stack = []
      LineNumberTable:
        line 151: 0
        line 153: 3
        line 151: 26
        line 153: 36
        line 155: 84
        line 156: 163
        line 155: 183
        line 157: 186
        line 158: 208
        line 157: 229
        line 161: 232
        line 162: 241
        line 163: 296
        line 164: 312
        line 166: 343
        line 167: 360
        line 170: 373
        line 172: 392
        line 173: 401
        line 174: 421
        line 176: 448
        line 169: 468
        line 170: 542
        line 169: 556
        line 179: 586
        line 180: 603
        line 181: 610
        line 182: 614
        line 183: 637
        line 184: 650
        line 186: 664
        line 187: 677
        line 197: 681
        line 198: 701
        line 199: 718
        line 200: 722
        line 201: 745
        line 203: 758
        line 205: 768
        line 206: 775
        line 151: 787
      LocalVariableTable:
        Start  Length  Slot  Name   Signature
           36      42     9     s   Ljava/lang/String;
          208      21    12    xs   Lscala/collection/Seq;
          244      52    15   x$1   Lscala/xml/Node;
          247      49    16   x$2   Lscala/xml/NamespaceBinding;
          251      45    17   x$3   Lscala/collection/mutable/StringBuilder;
          254      42    18   x$4   Z
          260      36    19   x$5   Lscala/Enumeration$Value;
          268      28    20   x$6   Z
          276      20    21   x$7   Z
          241     100    14    sb   Lscala/collection/mutable/StringBuilder;
          401      44    24 firstAttribute   I
          421      24    25 firstBreak   I
          508      28    28   stg   Ljava/lang/String;
          515      21    29  len2   I
          493      46    27   etg   Ljava/lang/String;
          566     216    30   stg   Ljava/lang/String;
          576     206    31  len2   I
          586     196    32   etg   Ljava/lang/String;
          343     439    13  test   Ljava/lang/String;
            0     788     0  this   Lorg/scalatest/tools/PrettyPrinter;
            0     788     1  node   Lscala/xml/Node;
            0     788     2 pscope   Lscala/xml/NamespaceBinding;
            0     788     3   ind   I
    MethodParameters:
      Name                           Flags
      node                           final
      pscope                         final
      ind                            final

  public void traverse(scala.collection.Iterator<scala.xml.Node>, scala.xml.NamespaceBinding, int);
    descriptor: (Lscala/collection/Iterator;Lscala/xml/NamespaceBinding;I)V
    flags: (0x0001) ACC_PUBLIC
    Code:
      stack=4, locals=4, args_size=4
         0: aload_1
         1: aload_0
         2: aload_2
         3: iload_3
         4: invokedynamic #551,  0            // InvokeDynamic #7:apply:(Lorg/scalatest/tools/PrettyPrinter;Lscala/xml/NamespaceBinding;I)Lscala/Function1;
         9: invokeinterface #554,  2          // InterfaceMethod scala/collection/Iterator.foreach:(Lscala/Function1;)V
        14: return
      LineNumberTable:
        line 212: 0
      LocalVariableTable:
        Start  Length  Slot  Name   Signature
            0      15     0  this   Lorg/scalatest/tools/PrettyPrinter;
            0      15     1    it   Lscala/collection/Iterator;
            0      15     2 scope   Lscala/xml/NamespaceBinding;
            0      15     3   ind   I
    Signature: #542                         // (Lscala/collection/Iterator<Lscala/xml/Node;>;Lscala/xml/NamespaceBinding;I)V
    MethodParameters:
      Name                           Flags
      it                             final
      scope                          final
      ind                            final

  public void format(scala.xml.Node, scala.collection.mutable.StringBuilder);
    descriptor: (Lscala/xml/Node;Lscala/collection/mutable/StringBuilder;)V
    flags: (0x0001) ACC_PUBLIC
    Code:
      stack=4, locals=3, args_size=3
         0: aload_0
         1: aload_1
         2: getstatic     #562                // Field scala/xml/TopScope$.MODULE$:Lscala/xml/TopScope$;
         5: aload_2
         6: invokevirtual #565                // Method format:(Lscala/xml/Node;Lscala/xml/NamespaceBinding;Lscala/collection/mutable/StringBuilder;)V
         9: return
      LineNumberTable:
        line 225: 0
      LocalVariableTable:
        Start  Length  Slot  Name   Signature
            0      10     0  this   Lorg/scalatest/tools/PrettyPrinter;
            0      10     1     n   Lscala/xml/Node;
            0      10     2    sb   Lscala/collection/mutable/StringBuilder;
    MethodParameters:
      Name                           Flags
      n                              final
      sb                             final

  public void format(scala.xml.Node, scala.xml.NamespaceBinding, scala.collection.mutable.StringBuilder);
    descriptor: (Lscala/xml/Node;Lscala/xml/NamespaceBinding;Lscala/collection/mutable/StringBuilder;)V
    flags: (0x0001) ACC_PUBLIC
    Code:
      stack=5, locals=6, args_size=4
         0: iconst_0
         1: invokestatic  #570                // Method scala/runtime/BooleanRef.create:(Z)Lscala/runtime/BooleanRef;
         4: astore        4
         6: aload_0
         7: invokevirtual #572                // Method reset:()V
        10: aload_0
        11: aload_1
        12: aload_2
        13: iconst_0
        14: invokevirtual #574                // Method traverse:(Lscala/xml/Node;Lscala/xml/NamespaceBinding;I)V
        17: iconst_0
        18: invokestatic  #271                // Method scala/runtime/IntRef.create:(I)Lscala/runtime/IntRef;
        21: astore        5
        23: aload_0
        24: invokevirtual #206                // Method items:()Lscala/collection/immutable/List;
        27: invokevirtual #577                // Method scala/collection/immutable/List.reverse:()Lscala/collection/immutable/List;
        30: aload_0
        31: aload         4
        33: aload_3
        34: aload         5
        36: invokedynamic #585,  0            // InvokeDynamic #8:apply:(Lorg/scalatest/tools/PrettyPrinter;Lscala/runtime/BooleanRef;Lscala/collection/mutable/StringBuilder;Lscala/runtime/IntRef;)Lscala/Function1;
        41: invokevirtual #231                // Method scala/collection/immutable/List.foreach:(Lscala/Function1;)V
        44: return
      LineNumberTable:
        line 229: 0
        line 230: 6
        line 231: 10
        line 232: 17
        line 233: 23
      LocalVariableTable:
        Start  Length  Slot  Name   Signature
            6      38     4 lastwasbreak   Lscala/runtime/BooleanRef;
           23      21     5   cur   Lscala/runtime/IntRef;
            0      45     0  this   Lorg/scalatest/tools/PrettyPrinter;
            0      45     1     n   Lscala/xml/Node;
            0      45     2 pscope   Lscala/xml/NamespaceBinding;
            0      45     3    sb   Lscala/collection/mutable/StringBuilder;
    MethodParameters:
      Name                           Flags
      n                              final
      pscope                         final
      sb                             final

  public java.lang.String format(scala.xml.Node, scala.xml.NamespaceBinding);
    descriptor: (Lscala/xml/Node;Lscala/xml/NamespaceBinding;)Ljava/lang/String;
    flags: (0x0001) ACC_PUBLIC
    Code:
      stack=4, locals=3, args_size=3
         0: getstatic     #246                // Field org/scalatest/tools/XmlUtility$.MODULE$:Lorg/scalatest/tools/XmlUtility$;
         3: aload_0
         4: aload_1
         5: aload_2
         6: invokedynamic #596,  0            // InvokeDynamic #9:apply:(Lorg/scalatest/tools/PrettyPrinter;Lscala/xml/Node;Lscala/xml/NamespaceBinding;)Lscala/Function1;
        11: invokevirtual #260                // Method org/scalatest/tools/XmlUtility$.sbToString:(Lscala/Function1;)Ljava/lang/String;
        14: areturn
      LineNumberTable:
        line 267: 0
      LocalVariableTable:
        Start  Length  Slot  Name   Signature
            0      15     0  this   Lorg/scalatest/tools/PrettyPrinter;
            0      15     1     n   Lscala/xml/Node;
            0      15     2 pscope   Lscala/xml/NamespaceBinding;
    MethodParameters:
      Name                           Flags
      n                              final
      pscope                         final

  public scala.xml.NamespaceBinding format$default$2();
    descriptor: ()Lscala/xml/NamespaceBinding;
    flags: (0x0001) ACC_PUBLIC
    Code:
      stack=1, locals=1, args_size=1
         0: getstatic     #562                // Field scala/xml/TopScope$.MODULE$:Lscala/xml/TopScope$;
         3: areturn
      LineNumberTable:
        line 266: 0
      LocalVariableTable:
        Start  Length  Slot  Name   Signature
            0       4     0  this   Lorg/scalatest/tools/PrettyPrinter;

  public java.lang.String formatNodes(scala.collection.Seq<scala.xml.Node>, scala.xml.NamespaceBinding);
    descriptor: (Lscala/collection/Seq;Lscala/xml/NamespaceBinding;)Ljava/lang/String;
    flags: (0x0001) ACC_PUBLIC
    Code:
      stack=4, locals=3, args_size=3
         0: getstatic     #246                // Field org/scalatest/tools/XmlUtility$.MODULE$:Lorg/scalatest/tools/XmlUtility$;
         3: aload_0
         4: aload_1
         5: aload_2
         6: invokedynamic #608,  0            // InvokeDynamic #10:apply:(Lorg/scalatest/tools/PrettyPrinter;Lscala/collection/Seq;Lscala/xml/NamespaceBinding;)Lscala/Function1;
        11: invokevirtual #260                // Method org/scalatest/tools/XmlUtility$.sbToString:(Lscala/Function1;)Ljava/lang/String;
        14: areturn
      LineNumberTable:
        line 276: 0
      LocalVariableTable:
        Start  Length  Slot  Name   Signature
            0      15     0  this   Lorg/scalatest/tools/PrettyPrinter;
            0      15     1 nodes   Lscala/collection/Seq;
            0      15     2 pscope   Lscala/xml/NamespaceBinding;
    Signature: #600                         // (Lscala/collection/Seq<Lscala/xml/Node;>;Lscala/xml/NamespaceBinding;)Ljava/lang/String;
    MethodParameters:
      Name                           Flags
      nodes                          final
      pscope                         final

  public void formatNodes(scala.collection.Seq<scala.xml.Node>, scala.xml.NamespaceBinding, scala.collection.mutable.StringBuilder);
    descriptor: (Lscala/collection/Seq;Lscala/xml/NamespaceBinding;Lscala/collection/mutable/StringBuilder;)V
    flags: (0x0001) ACC_PUBLIC
    Code:
      stack=4, locals=4, args_size=4
         0: aload_1
         1: aload_0
         2: aload_3
         3: aload_2
         4: invokedynamic #620,  0            // InvokeDynamic #11:apply:(Lorg/scalatest/tools/PrettyPrinter;Lscala/collection/mutable/StringBuilder;Lscala/xml/NamespaceBinding;)Lscala/Function1;
         9: invokeinterface #621,  2          // InterfaceMethod scala/collection/Seq.foreach:(Lscala/Function1;)V
        14: return
      LineNumberTable:
        line 287: 0
      LocalVariableTable:
        Start  Length  Slot  Name   Signature
            0      15     0  this   Lorg/scalatest/tools/PrettyPrinter;
            0      15     1 nodes   Lscala/collection/Seq;
            0      15     2 pscope   Lscala/xml/NamespaceBinding;
            0      15     3    sb   Lscala/collection/mutable/StringBuilder;
    Signature: #610                         // (Lscala/collection/Seq<Lscala/xml/Node;>;Lscala/xml/NamespaceBinding;Lscala/collection/mutable/StringBuilder;)V
    MethodParameters:
      Name                           Flags
      nodes                          final
      pscope                         final
      sb                             final

  public scala.xml.NamespaceBinding formatNodes$default$2();
    descriptor: ()Lscala/xml/NamespaceBinding;
    flags: (0x0001) ACC_PUBLIC
    Code:
      stack=1, locals=1, args_size=1
         0: getstatic     #562                // Field scala/xml/TopScope$.MODULE$:Lscala/xml/TopScope$;
         3: areturn
      LineNumberTable:
        line 275: 0
      LocalVariableTable:
        Start  Length  Slot  Name   Signature
            0       4     0  this   Lorg/scalatest/tools/PrettyPrinter;

  private final void Break$lzycompute$1();
    descriptor: ()V
    flags: (0x0012) ACC_PRIVATE, ACC_FINAL
    Code:
      stack=4, locals=2, args_size=1
         0: aload_0
         1: dup
         2: astore_1
         3: monitorenter
         4: aload_0
         5: getfield      #60                 // Field Break$module:Lorg/scalatest/tools/PrettyPrinter$Break$;
         8: ifnonnull     23
        11: aload_0
        12: new           #21                 // class org/scalatest/tools/PrettyPrinter$Break$
        15: dup
        16: aload_0
        17: invokespecial #623                // Method org/scalatest/tools/PrettyPrinter$Break$."<init>":(Lorg/scalatest/tools/PrettyPrinter;)V
        20: putfield      #60                 // Field Break$module:Lorg/scalatest/tools/PrettyPrinter$Break$;
        23: aload_1
        24: monitorexit
        25: goto          31
        28: aload_1
        29: monitorexit
        30: athrow
        31: return
      Exception table:
         from    to  target type
             4    23    28   any
      StackMapTable: number_of_entries = 3
        frame_type = 252 /* append */
          offset_delta = 23
          locals = [ class org/scalatest/tools/PrettyPrinter ]
        frame_type = 68 /* same_locals_1_stack_item */
          stack = [ class java/lang/Throwable ]
        frame_type = 2 /* same */
      LineNumberTable:
        line 40: 0
      LocalVariableTable:
        Start  Length  Slot  Name   Signature
            0      32     0  this   Lorg/scalatest/tools/PrettyPrinter;

  private final void Box$lzycompute$1();
    descriptor: ()V
    flags: (0x0012) ACC_PRIVATE, ACC_FINAL
    Code:
      stack=4, locals=2, args_size=1
         0: aload_0
         1: dup
         2: astore_1
         3: monitorenter
         4: aload_0
         5: getfield      #69                 // Field Box$module:Lorg/scalatest/tools/PrettyPrinter$Box$;
         8: ifnonnull     23
        11: aload_0
        12: new           #18                 // class org/scalatest/tools/PrettyPrinter$Box$
        15: dup
        16: aload_0
        17: invokespecial #626                // Method org/scalatest/tools/PrettyPrinter$Box$."<init>":(Lorg/scalatest/tools/PrettyPrinter;)V
        20: putfield      #69                 // Field Box$module:Lorg/scalatest/tools/PrettyPrinter$Box$;
        23: aload_1
        24: monitorexit
        25: goto          31
        28: aload_1
        29: monitorexit
        30: athrow
        31: return
      Exception table:
         from    to  target type
             4    23    28   any
      StackMapTable: number_of_entries = 3
        frame_type = 252 /* append */
          offset_delta = 23
          locals = [ class org/scalatest/tools/PrettyPrinter ]
        frame_type = 68 /* same_locals_1_stack_item */
          stack = [ class java/lang/Throwable ]
        frame_type = 2 /* same */
      LineNumberTable:
        line 43: 0
      LocalVariableTable:
        Start  Length  Slot  Name   Signature
            0      32     0  this   Lorg/scalatest/tools/PrettyPrinter;

  private final void Para$lzycompute$1();
    descriptor: ()V
    flags: (0x0012) ACC_PRIVATE, ACC_FINAL
    Code:
      stack=4, locals=2, args_size=1
         0: aload_0
         1: dup
         2: astore_1
         3: monitorenter
         4: aload_0
         5: getfield      #75                 // Field Para$module:Lorg/scalatest/tools/PrettyPrinter$Para$;
         8: ifnonnull     23
        11: aload_0
        12: new           #33                 // class org/scalatest/tools/PrettyPrinter$Para$
        15: dup
        16: aload_0
        17: invokespecial #627                // Method org/scalatest/tools/PrettyPrinter$Para$."<init>":(Lorg/scalatest/tools/PrettyPrinter;)V
        20: putfield      #75                 // Field Para$module:Lorg/scalatest/tools/PrettyPrinter$Para$;
        23: aload_1
        24: monitorexit
        25: goto          31
        28: aload_1
        29: monitorexit
        30: athrow
        31: return
      Exception table:
         from    to  target type
             4    23    28   any
      StackMapTable: number_of_entries = 3
        frame_type = 252 /* append */
          offset_delta = 23
          locals = [ class org/scalatest/tools/PrettyPrinter ]
        frame_type = 68 /* same_locals_1_stack_item */
          stack = [ class java/lang/Throwable ]
        frame_type = 2 /* same */
      LineNumberTable:
        line 44: 0
      LocalVariableTable:
        Start  Length  Slot  Name   Signature
            0      32     0  this   Lorg/scalatest/tools/PrettyPrinter;

  public static final void $anonfun$makeBox$1(org.scalatest.tools.PrettyPrinter, org.scalatest.tools.PrettyPrinter$Item);
    descriptor: (Lorg/scalatest/tools/PrettyPrinter;Lorg/scalatest/tools/PrettyPrinter$Item;)V
    flags: (0x1019) ACC_PUBLIC, ACC_STATIC, ACC_FINAL, ACC_SYNTHETIC
    Code:
      stack=3, locals=2, args_size=2
         0: aload_0
         1: aload_0
         2: invokevirtual #206                // Method items:()Lscala/collection/immutable/List;
         5: aload_1
         6: invokevirtual #167                // Method scala/collection/immutable/List.$colon$colon:(Ljava/lang/Object;)Lscala/collection/immutable/List;
         9: invokevirtual #109                // Method items_$eq:(Lscala/collection/immutable/List;)V
        12: return
      LineNumberTable:
        line 90: 0
      LocalVariableTable:
        Start  Length  Slot  Name   Signature
            0      13     0 $this   Lorg/scalatest/tools/PrettyPrinter;
            0      13     1   x$1   Lorg/scalatest/tools/PrettyPrinter$Item;
    MethodParameters:
      Name                           Flags
      $this                          final synthetic
      x$1                            final

  private static final void mkLeaf$1(scala.collection.mutable.StringBuilder, scala.xml.Node);
    descriptor: (Lscala/collection/mutable/StringBuilder;Lscala/xml/Node;)V
    flags: (0x001a) ACC_PRIVATE, ACC_STATIC, ACC_FINAL
    Code:
      stack=2, locals=2, args_size=2
         0: aload_0
         1: bipush        60
         3: invokevirtual #638                // Method scala/collection/mutable/StringBuilder.append:(C)Lscala/collection/mutable/StringBuilder;
         6: pop
         7: aload_1
         8: aload_0
         9: invokevirtual #642                // Method scala/xml/Node.nameToString:(Lscala/collection/mutable/StringBuilder;)Lscala/collection/mutable/StringBuilder;
        12: pop
        13: aload_1
        14: invokevirtual #646                // Method scala/xml/Node.attributes:()Lscala/xml/MetaData;
        17: aload_0
        18: invokevirtual #651                // Method scala/xml/MetaData.buildString:(Lscala/collection/mutable/StringBuilder;)Lscala/collection/mutable/StringBuilder;
        21: pop
        22: aload_0
        23: ldc_w         #653                // String />
        26: invokevirtual #656                // Method scala/collection/mutable/StringBuilder.append:(Ljava/lang/String;)Lscala/collection/mutable/StringBuilder;
        29: pop
        30: return
      LineNumberTable:
        line 107: 0
        line 108: 7
        line 109: 13
        line 110: 22
      LocalVariableTable:
        Start  Length  Slot  Name   Signature
            0      31     0    sb   Lscala/collection/mutable/StringBuilder;
            0      31     1   n$1   Lscala/xml/Node;
    MethodParameters:
      Name                           Flags
      sb                             final
      n$1                            final

  public static final void $anonfun$leafTag$1(scala.xml.Node, scala.collection.mutable.StringBuilder);
    descriptor: (Lscala/xml/Node;Lscala/collection/mutable/StringBuilder;)V
    flags: (0x1019) ACC_PUBLIC, ACC_STATIC, ACC_FINAL, ACC_SYNTHETIC
    Code:
      stack=2, locals=2, args_size=2
         0: aload_1
         1: aload_0
         2: invokestatic  #659                // Method mkLeaf$1:(Lscala/collection/mutable/StringBuilder;Lscala/xml/Node;)V
         5: return
      LineNumberTable:
        line 112: 0
      LocalVariableTable:
        Start  Length  Slot  Name   Signature
            0       6     0   n$1   Lscala/xml/Node;
            0       6     1    sb   Lscala/collection/mutable/StringBuilder;
    MethodParameters:
      Name                           Flags
      n$1                            final
      sb                             final

  private static final void mkStart$1(scala.collection.mutable.StringBuilder, scala.xml.Node, scala.runtime.IntRef, scala.xml.NamespaceBinding);
    descriptor: (Lscala/collection/mutable/StringBuilder;Lscala/xml/Node;Lscala/runtime/IntRef;Lscala/xml/NamespaceBinding;)V
    flags: (0x001a) ACC_PRIVATE, ACC_STATIC, ACC_FINAL
    Code:
      stack=3, locals=4, args_size=4
         0: aload_0
         1: bipush        60
         3: invokevirtual #638                // Method scala/collection/mutable/StringBuilder.append:(C)Lscala/collection/mutable/StringBuilder;
         6: pop
         7: aload_1
         8: aload_0
         9: invokevirtual #642                // Method scala/xml/Node.nameToString:(Lscala/collection/mutable/StringBuilder;)Lscala/collection/mutable/StringBuilder;
        12: pop
        13: aload_2
        14: aload_0
        15: invokevirtual #665                // Method scala/collection/mutable/StringBuilder.length:()I
        18: iconst_1
        19: iadd
        20: putfield      #284                // Field scala/runtime/IntRef.elem:I
        23: aload_1
        24: invokevirtual #646                // Method scala/xml/Node.attributes:()Lscala/xml/MetaData;
        27: aload_0
        28: invokevirtual #651                // Method scala/xml/MetaData.buildString:(Lscala/collection/mutable/StringBuilder;)Lscala/collection/mutable/StringBuilder;
        31: pop
        32: aload_1
        33: invokevirtual #505                // Method scala/xml/Node.scope:()Lscala/xml/NamespaceBinding;
        36: aload_0
        37: aload_3
        38: invokevirtual #668                // Method scala/xml/NamespaceBinding.buildString:(Lscala/collection/mutable/StringBuilder;Lscala/xml/NamespaceBinding;)V
        41: aload_0
        42: bipush        62
        44: invokevirtual #638                // Method scala/collection/mutable/StringBuilder.append:(C)Lscala/collection/mutable/StringBuilder;
        47: pop
        48: return
      LineNumberTable:
        line 118: 0
        line 119: 7
        line 120: 13
        line 121: 23
        line 122: 32
        line 123: 41
      LocalVariableTable:
        Start  Length  Slot  Name   Signature
            0      49     0    sb   Lscala/collection/mutable/StringBuilder;
            0      49     1   n$2   Lscala/xml/Node;
            0      49     2   i$1   Lscala/runtime/IntRef;
            0      49     3 pscope$1   Lscala/xml/NamespaceBinding;
    MethodParameters:
      Name                           Flags
      sb                             final
      n$2                            final
      i$1                            final
      pscope$1                       final

  public static final void $anonfun$startTag$1(scala.xml.Node, scala.runtime.IntRef, scala.xml.NamespaceBinding, scala.collection.mutable.StringBuilder);
    descriptor: (Lscala/xml/Node;Lscala/runtime/IntRef;Lscala/xml/NamespaceBinding;Lscala/collection/mutable/StringBuilder;)V
    flags: (0x1019) ACC_PUBLIC, ACC_STATIC, ACC_FINAL, ACC_SYNTHETIC
    Code:
      stack=4, locals=4, args_size=4
         0: aload_3
         1: aload_0
         2: aload_1
         3: aload_2
         4: invokestatic  #672                // Method mkStart$1:(Lscala/collection/mutable/StringBuilder;Lscala/xml/Node;Lscala/runtime/IntRef;Lscala/xml/NamespaceBinding;)V
         7: return
      LineNumberTable:
        line 125: 0
      LocalVariableTable:
        Start  Length  Slot  Name   Signature
            0       8     0   n$2   Lscala/xml/Node;
            0       8     1   i$1   Lscala/runtime/IntRef;
            0       8     2 pscope$1   Lscala/xml/NamespaceBinding;
            0       8     3    sb   Lscala/collection/mutable/StringBuilder;
    MethodParameters:
      Name                           Flags
      n$2                            final
      i$1                            final
      pscope$1                       final
      sb                             final

  private static final void mkEnd$1(scala.collection.mutable.StringBuilder, scala.xml.Node);
    descriptor: (Lscala/collection/mutable/StringBuilder;Lscala/xml/Node;)V
    flags: (0x001a) ACC_PRIVATE, ACC_STATIC, ACC_FINAL
    Code:
      stack=2, locals=2, args_size=2
         0: aload_0
         1: ldc_w         #676                // String </
         4: invokevirtual #656                // Method scala/collection/mutable/StringBuilder.append:(Ljava/lang/String;)Lscala/collection/mutable/StringBuilder;
         7: pop
         8: aload_1
         9: aload_0
        10: invokevirtual #642                // Method scala/xml/Node.nameToString:(Lscala/collection/mutable/StringBuilder;)Lscala/collection/mutable/StringBuilder;
        13: pop
        14: aload_0
        15: bipush        62
        17: invokevirtual #638                // Method scala/collection/mutable/StringBuilder.append:(C)Lscala/collection/mutable/StringBuilder;
        20: pop
        21: return
      LineNumberTable:
        line 130: 0
        line 131: 8
        line 132: 14
      LocalVariableTable:
        Start  Length  Slot  Name   Signature
            0      22     0    sb   Lscala/collection/mutable/StringBuilder;
            0      22     1   n$3   Lscala/xml/Node;
    MethodParameters:
      Name                           Flags
      sb                             final
      n$3                            final

  public static final void $anonfun$endTag$1(scala.xml.Node, scala.collection.mutable.StringBuilder);
    descriptor: (Lscala/xml/Node;Lscala/collection/mutable/StringBuilder;)V
    flags: (0x1019) ACC_PUBLIC, ACC_STATIC, ACC_FINAL, ACC_SYNTHETIC
    Code:
      stack=2, locals=2, args_size=2
         0: aload_1
         1: aload_0
         2: invokestatic  #679                // Method mkEnd$1:(Lscala/collection/mutable/StringBuilder;Lscala/xml/Node;)V
         5: return
      LineNumberTable:
        line 134: 0
      LocalVariableTable:
        Start  Length  Slot  Name   Signature
            0       6     0   n$3   Lscala/xml/Node;
            0       6     1    sb   Lscala/collection/mutable/StringBuilder;
    MethodParameters:
      Name                           Flags
      n$3                            final
      sb                             final

  private static final boolean isLeaf$1(scala.xml.Node);
    descriptor: (Lscala/xml/Node;)Z
    flags: (0x001a) ACC_PRIVATE, ACC_STATIC, ACC_FINAL
    Code:
      stack=1, locals=4, args_size=1
         0: aload_0
         1: astore_3
         2: aload_3
         3: instanceof    #399                // class scala/xml/Atom
         6: ifeq          14
         9: iconst_1
        10: istore_2
        11: goto          67
        14: goto          17
        17: aload_3
        18: instanceof    #401                // class scala/xml/Comment
        21: ifeq          29
        24: iconst_1
        25: istore_2
        26: goto          67
        29: goto          32
        32: aload_3
        33: instanceof    #403                // class scala/xml/EntityRef
        36: ifeq          44
        39: iconst_1
        40: istore_2
        41: goto          67
        44: goto          47
        47: aload_3
        48: instanceof    #405                // class scala/xml/ProcInstr
        51: ifeq          59
        54: iconst_1
        55: istore_2
        56: goto          67
        59: goto          62
        62: iconst_0
        63: istore_2
        64: goto          67
        67: iload_2
        68: ifeq          76
        71: iconst_1
        72: istore_1
        73: goto          84
        76: goto          79
        79: iconst_0
        80: istore_1
        81: goto          84
        84: iload_1
        85: ireturn
      StackMapTable: number_of_entries = 12
        frame_type = 254 /* append */
          offset_delta = 14
          locals = [ top, top, class scala/xml/Node ]
        frame_type = 2 /* same */
        frame_type = 11 /* same */
        frame_type = 2 /* same */
        frame_type = 11 /* same */
        frame_type = 2 /* same */
        frame_type = 11 /* same */
        frame_type = 2 /* same */
        frame_type = 255 /* full_frame */
          offset_delta = 4
          locals = [ class scala/xml/Node, top, int, class scala/xml/Node ]
          stack = []
        frame_type = 8 /* same */
        frame_type = 2 /* same */
        frame_type = 255 /* full_frame */
          offset_delta = 4
          locals = [ class scala/xml/Node, int, int, class scala/xml/Node ]
          stack = []
      LineNumberTable:
        line 138: 0
        line 139: 2
        line 140: 79
        line 138: 84
      LocalVariableTable:
        Start  Length  Slot  Name   Signature
            0      86     0     l   Lscala/xml/Node;
    MethodParameters:
      Name                           Flags
      l                              final

  public static final boolean $anonfun$childrenAreLeaves$1(scala.xml.Node);
    descriptor: (Lscala/xml/Node;)Z
    flags: (0x1019) ACC_PUBLIC, ACC_STATIC, ACC_FINAL, ACC_SYNTHETIC
    Code:
      stack=1, locals=1, args_size=1
         0: aload_0
         1: invokestatic  #684                // Method isLeaf$1:(Lscala/xml/Node;)Z
         4: ireturn
      LineNumberTable:
        line 142: 0
      LocalVariableTable:
        Start  Length  Slot  Name   Signature
            0       5     0     l   Lscala/xml/Node;
    MethodParameters:
      Name                           Flags
      l                              final

  public static final boolean $anonfun$doPreserve$1(scala.collection.Seq);
    descriptor: (Lscala/collection/Seq;)Z
    flags: (0x1019) ACC_PUBLIC, ACC_STATIC, ACC_FINAL, ACC_SYNTHETIC
    Code:
      stack=2, locals=2, args_size=1
         0: aload_0
         1: invokeinterface #687,  1          // InterfaceMethod scala/collection/Seq.toString:()Ljava/lang/String;
         6: getstatic     #328                // Field scala/xml/XML$.MODULE$:Lscala/xml/XML$;
         9: invokevirtual #690                // Method scala/xml/XML$.preserve:()Ljava/lang/String;
        12: astore_1
        13: dup
        14: ifnonnull     25
        17: pop
        18: aload_1
        19: ifnull        32
        22: goto          36
        25: aload_1
        26: invokevirtual #174                // Method java/lang/Object.equals:(Ljava/lang/Object;)Z
        29: ifeq          36
        32: iconst_1
        33: goto          37
        36: iconst_0
        37: ireturn
      StackMapTable: number_of_entries = 4
        frame_type = 255 /* full_frame */
          offset_delta = 25
          locals = [ class scala/collection/Seq, class java/lang/String ]
          stack = [ class java/lang/String ]
        frame_type = 6 /* same */
        frame_type = 3 /* same */
        frame_type = 64 /* same_locals_1_stack_item */
          stack = [ int ]
      LineNumberTable:
        line 149: 0
      LocalVariableTable:
        Start  Length  Slot  Name   Signature
            0      38     0   x$2   Lscala/collection/Seq;
    MethodParameters:
      Name                           Flags
      x$2                            final

  public static final boolean $anonfun$doPreserve$2();
    descriptor: ()Z
    flags: (0x1019) ACC_PUBLIC, ACC_STATIC, ACC_FINAL, ACC_SYNTHETIC
    Code:
      stack=1, locals=0, args_size=0
         0: iconst_0
         1: ireturn
      LineNumberTable:
        line 149: 0

  public static final void $anonfun$traverse$1(org.scalatest.tools.PrettyPrinter, scala.xml.NamespaceBinding, int, scala.xml.Node);
    descriptor: (Lorg/scalatest/tools/PrettyPrinter;Lscala/xml/NamespaceBinding;ILscala/xml/Node;)V
    flags: (0x1019) ACC_PUBLIC, ACC_STATIC, ACC_FINAL, ACC_SYNTHETIC
    Code:
      stack=4, locals=4, args_size=4
         0: aload_0
         1: aload_3
         2: aload_1
         3: iload_2
         4: invokevirtual #574                // Method traverse:(Lscala/xml/Node;Lscala/xml/NamespaceBinding;I)V
         7: aload_0
         8: invokevirtual #501                // Method makeBreak:()V
        11: return
      LineNumberTable:
        line 213: 0
        line 214: 7
      LocalVariableTable:
        Start  Length  Slot  Name   Signature
            0      12     0 $this   Lorg/scalatest/tools/PrettyPrinter;
            0      12     1 scope$1   Lscala/xml/NamespaceBinding;
            0      12     2 ind$1   I
            0      12     3     c   Lscala/xml/Node;
    MethodParameters:
      Name                           Flags
      $this                          final synthetic
      scope$1                        final
      ind$1                          final
      c                              final

  public static final java.lang.Object $anonfun$format$1(org.scalatest.tools.PrettyPrinter, scala.runtime.BooleanRef, scala.collection.mutable.StringBuilder, scala.runtime.IntRef, org.scalatest.tools.PrettyPrinter$Item);
    descriptor: (Lorg/scalatest/tools/PrettyPrinter;Lscala/runtime/BooleanRef;Lscala/collection/mutable/StringBuilder;Lscala/runtime/IntRef;Lorg/scalatest/tools/PrettyPrinter$Item;)Ljava/lang/Object;
    flags: (0x1019) ACC_PUBLIC, ACC_STATIC, ACC_FINAL, ACC_SYNTHETIC
    Code:
      stack=3, locals=12, args_size=5
         0: aload         4
         2: astore        6
         4: aload_0
         5: invokevirtual #188                // Method Break:()Lorg/scalatest/tools/PrettyPrinter$Break$;
         8: aload         6
        10: invokevirtual #174                // Method java/lang/Object.equals:(Ljava/lang/Object;)Z
        13: ifeq          54
        16: aload_1
        17: getfield      #700                // Field scala/runtime/BooleanRef.elem:Z
        20: ifne          32
        23: aload_2
        24: bipush        10
        26: invokevirtual #638                // Method scala/collection/mutable/StringBuilder.append:(C)Lscala/collection/mutable/StringBuilder;
        29: goto          35
        32: getstatic     #397                // Field scala/runtime/BoxedUnit.UNIT:Lscala/runtime/BoxedUnit;
        35: pop
        36: aload_1
        37: iconst_1
        38: putfield      #700                // Field scala/runtime/BooleanRef.elem:Z
        41: aload_3
        42: iconst_0
        43: putfield      #284                // Field scala/runtime/IntRef.elem:I
        46: getstatic     #397                // Field scala/runtime/BoxedUnit.UNIT:Lscala/runtime/BoxedUnit;
        49: astore        5
        51: goto          185
        54: goto          57
        57: aload         6
        59: instanceof    #15                 // class org/scalatest/tools/PrettyPrinter$Box
        62: ifeq          131
        65: aload         6
        67: checkcast     #15                 // class org/scalatest/tools/PrettyPrinter$Box
        70: astore        7
        72: aload         7
        74: invokevirtual #703                // Method org/scalatest/tools/PrettyPrinter$Box.col:()I
        77: istore        8
        79: aload         7
        81: invokevirtual #705                // Method org/scalatest/tools/PrettyPrinter$Box.s:()Ljava/lang/String;
        84: astore        9
        86: aload_1
        87: iconst_0
        88: putfield      #700                // Field scala/runtime/BooleanRef.elem:Z
        91: aload_3
        92: getfield      #284                // Field scala/runtime/IntRef.elem:I
        95: iload         8
        97: if_icmpge     120
       100: aload_2
       101: bipush        32
       103: invokevirtual #638                // Method scala/collection/mutable/StringBuilder.append:(C)Lscala/collection/mutable/StringBuilder;
       106: pop
       107: aload_3
       108: aload_3
       109: getfield      #284                // Field scala/runtime/IntRef.elem:I
       112: iconst_1
       113: iadd
       114: putfield      #284                // Field scala/runtime/IntRef.elem:I
       117: goto          91
       120: aload_2
       121: aload         9
       123: invokevirtual #656                // Method scala/collection/mutable/StringBuilder.append:(Ljava/lang/String;)Lscala/collection/mutable/StringBuilder;
       126: astore        5
       128: goto          185
       131: goto          134
       134: aload         6
       136: instanceof    #30                 // class org/scalatest/tools/PrettyPrinter$Para
       139: ifeq          172
       142: aload         6
       144: checkcast     #30                 // class org/scalatest/tools/PrettyPrinter$Para
       147: astore        10
       149: aload         10
       151: invokevirtual #706                // Method org/scalatest/tools/PrettyPrinter$Para.s:()Ljava/lang/String;
       154: astore        11
       156: aload_1
       157: iconst_0
       158: putfield      #700                // Field scala/runtime/BooleanRef.elem:Z
       161: aload_2
       162: aload         11
       164: invokevirtual #656                // Method scala/collection/mutable/StringBuilder.append:(Ljava/lang/String;)Lscala/collection/mutable/StringBuilder;
       167: astore        5
       169: goto          185
       172: goto          175
       175: new           #491                // class scala/MatchError
       178: dup
       179: aload         6
       181: invokespecial #494                // Method scala/MatchError."<init>":(Ljava/lang/Object;)V
       184: athrow
       185: aload         5
       187: areturn
      StackMapTable: number_of_entries = 11
        frame_type = 253 /* append */
          offset_delta = 32
          locals = [ top, class org/scalatest/tools/PrettyPrinter$Item ]
        frame_type = 66 /* same_locals_1_stack_item */
          stack = [ class java/lang/Object ]
        frame_type = 18 /* same */
        frame_type = 2 /* same */
        frame_type = 254 /* append */
          offset_delta = 33
          locals = [ class org/scalatest/tools/PrettyPrinter$Box, int, class java/lang/String ]
        frame_type = 28 /* same */
        frame_type = 248 /* chop */
          offset_delta = 10
        frame_type = 2 /* same */
        frame_type = 37 /* same */
        frame_type = 2 /* same */
        frame_type = 255 /* full_frame */
          offset_delta = 9
          locals = [ class org/scalatest/tools/PrettyPrinter, class scala/runtime/BooleanRef, class scala/collection/mutable/StringBuilder, class scala/runtime/IntRef, class org/scalatest/tools/PrettyPrinter$Item, class java/lang/Object, class org/scalatest/tools/PrettyPrinter$Item ]
          stack = []
      LineNumberTable:
        line 233: 0
        line 234: 4
        line 235: 16
        line 236: 36
        line 237: 41
        line 234: 54
        line 243: 57
        line 244: 86
        line 245: 91
        line 246: 100
        line 247: 107
        line 245: 117
        line 249: 120
        line 243: 131
        line 250: 134
        line 251: 156
        line 252: 161
        line 250: 172
        line 233: 175
      LocalVariableTable:
        Start  Length  Slot  Name   Signature
           79      52     8     i   I
           86      45     9     s   Ljava/lang/String;
          156      16    11     s   Ljava/lang/String;
            0     188     0 $this   Lorg/scalatest/tools/PrettyPrinter;
            0     188     1 lastwasbreak$1   Lscala/runtime/BooleanRef;
            0     188     2  sb$1   Lscala/collection/mutable/StringBuilder;
            0     188     3 cur$1   Lscala/runtime/IntRef;
            0     188     4     b   Lorg/scalatest/tools/PrettyPrinter$Item;
    MethodParameters:
      Name                           Flags
      $this                          final synthetic
      lastwasbreak$1                 final
      sb$1                           final
      cur$1                          final
      b                              final

  public static final void $anonfun$format$2(org.scalatest.tools.PrettyPrinter, scala.xml.Node, scala.xml.NamespaceBinding, scala.collection.mutable.StringBuilder);
    descriptor: (Lorg/scalatest/tools/PrettyPrinter;Lscala/xml/Node;Lscala/xml/NamespaceBinding;Lscala/collection/mutable/StringBuilder;)V
    flags: (0x1019) ACC_PUBLIC, ACC_STATIC, ACC_FINAL, ACC_SYNTHETIC
    Code:
      stack=4, locals=4, args_size=4
         0: aload_0
         1: aload_1
         2: aload_2
         3: aload_3
         4: invokevirtual #565                // Method format:(Lscala/xml/Node;Lscala/xml/NamespaceBinding;Lscala/collection/mutable/StringBuilder;)V
         7: return
      LineNumberTable:
        line 267: 0
      LocalVariableTable:
        Start  Length  Slot  Name   Signature
            0       8     0 $this   Lorg/scalatest/tools/PrettyPrinter;
            0       8     1   n$4   Lscala/xml/Node;
            0       8     2 pscope$2   Lscala/xml/NamespaceBinding;
            0       8     3   x$4   Lscala/collection/mutable/StringBuilder;
    MethodParameters:
      Name                           Flags
      $this                          final synthetic
      n$4                            final
      pscope$2                       final
      x$4                            final

  public static final void $anonfun$formatNodes$1(org.scalatest.tools.PrettyPrinter, scala.collection.Seq, scala.xml.NamespaceBinding, scala.collection.mutable.StringBuilder);
    descriptor: (Lorg/scalatest/tools/PrettyPrinter;Lscala/collection/Seq;Lscala/xml/NamespaceBinding;Lscala/collection/mutable/StringBuilder;)V
    flags: (0x1019) ACC_PUBLIC, ACC_STATIC, ACC_FINAL, ACC_SYNTHETIC
    Code:
      stack=4, locals=4, args_size=4
         0: aload_0
         1: aload_1
         2: aload_2
         3: aload_3
         4: invokevirtual #716                // Method formatNodes:(Lscala/collection/Seq;Lscala/xml/NamespaceBinding;Lscala/collection/mutable/StringBuilder;)V
         7: return
      LineNumberTable:
        line 276: 0
      LocalVariableTable:
        Start  Length  Slot  Name   Signature
            0       8     0 $this   Lorg/scalatest/tools/PrettyPrinter;
            0       8     1 nodes$1   Lscala/collection/Seq;
            0       8     2 pscope$3   Lscala/xml/NamespaceBinding;
            0       8     3   x$5   Lscala/collection/mutable/StringBuilder;
    MethodParameters:
      Name                           Flags
      $this                          final synthetic
      nodes$1                        final
      pscope$3                       final
      x$5                            final

  public static final scala.collection.mutable.StringBuilder $anonfun$formatNodes$2(org.scalatest.tools.PrettyPrinter, scala.collection.mutable.StringBuilder, scala.xml.NamespaceBinding, scala.xml.Node);
    descriptor: (Lorg/scalatest/tools/PrettyPrinter;Lscala/collection/mutable/StringBuilder;Lscala/xml/NamespaceBinding;Lscala/xml/Node;)Lscala/collection/mutable/StringBuilder;
    flags: (0x1019) ACC_PUBLIC, ACC_STATIC, ACC_FINAL, ACC_SYNTHETIC
    Code:
      stack=4, locals=4, args_size=4
         0: aload_1
         1: aload_0
         2: aload_3
         3: aload_2
         4: invokevirtual #720                // Method format:(Lscala/xml/Node;Lscala/xml/NamespaceBinding;)Ljava/lang/String;
         7: invokevirtual #656                // Method scala/collection/mutable/StringBuilder.append:(Ljava/lang/String;)Lscala/collection/mutable/StringBuilder;
        10: areturn
      LineNumberTable:
        line 287: 0
      LocalVariableTable:
        Start  Length  Slot  Name   Signature
            0      11     0 $this   Lorg/scalatest/tools/PrettyPrinter;
            0      11     1  sb$2   Lscala/collection/mutable/StringBuilder;
            0      11     2 pscope$4   Lscala/xml/NamespaceBinding;
            0      11     3     n   Lscala/xml/Node;
    MethodParameters:
      Name                           Flags
      $this                          final synthetic
      sb$2                           final
      pscope$4                       final
      n                              final

  public org.scalatest.tools.PrettyPrinter(int, int, boolean);
    descriptor: (IIZ)V
    flags: (0x0001) ACC_PUBLIC
    Code:
      stack=2, locals=4, args_size=4
         0: aload_0
         1: iload_1
         2: putfield      #116                // Field width:I
         5: aload_0
         6: iload_2
         7: putfield      #507                // Field step:I
        10: aload_0
        11: iload_3
        12: putfield      #468                // Field minimizeEmpty:Z
        15: aload_0
        16: invokespecial #722                // Method java/lang/Object."<init>":()V
        19: aload_0
        20: iload_3
        21: ifeq          33
        24: getstatic     #727                // Field scala/xml/MinimizeMode$.MODULE$:Lscala/xml/MinimizeMode$;
        27: invokevirtual #730                // Method scala/xml/MinimizeMode$.Always:()Lscala/Enumeration$Value;
        30: goto          39
        33: getstatic     #727                // Field scala/xml/MinimizeMode$.MODULE$:Lscala/xml/MinimizeMode$;
        36: invokevirtual #733                // Method scala/xml/MinimizeMode$.Default:()Lscala/Enumeration$Value;
        39: putfield      #81                 // Field minimizeMode:Lscala/Enumeration$Value;
        42: aload_0
        43: getstatic     #103                // Field scala/package$.MODULE$:Lscala/package$;
        46: invokevirtual #107                // Method scala/package$.Nil:()Lscala/collection/immutable/Nil$;
        49: putfield      #85                 // Field items:Lscala/collection/immutable/List;
        52: aload_0
        53: iconst_0
        54: putfield      #92                 // Field cur:I
        57: return
      StackMapTable: number_of_entries = 2
        frame_type = 255 /* full_frame */
          offset_delta = 33
          locals = [ class org/scalatest/tools/PrettyPrinter, int, int, int ]
          stack = [ class org/scalatest/tools/PrettyPrinter ]
        frame_type = 255 /* full_frame */
          offset_delta = 5
          locals = [ class org/scalatest/tools/PrettyPrinter, int, int, int ]
          stack = [ class org/scalatest/tools/PrettyPrinter, class scala/Enumeration$Value ]
      LineNumberTable:
        line 32: 0
        line 288: 15
        line 36: 19
        line 46: 42
        line 48: 52
        line 32: 57
      LocalVariableTable:
        Start  Length  Slot  Name   Signature
            0      58     0  this   Lorg/scalatest/tools/PrettyPrinter;
            0      58     1 width   I
            0      58     2  step   I
            0      58     3 minimizeEmpty   Z
    MethodParameters:
      Name                           Flags
      width                          final
      step                           final
      minimizeEmpty                  final

  public org.scalatest.tools.PrettyPrinter(int, int);
    descriptor: (II)V
    flags: (0x0001) ACC_PUBLIC
    Code:
      stack=4, locals=3, args_size=3
         0: aload_0
         1: iload_1
         2: iload_2
         3: iconst_0
         4: invokespecial #736                // Method "<init>":(IIZ)V
         7: return
      LineNumberTable:
        line 34: 0
      LocalVariableTable:
        Start  Length  Slot  Name   Signature
            0       8     0  this   Lorg/scalatest/tools/PrettyPrinter;
            0       8     1 width   I
            0       8     2  step   I
    MethodParameters:
      Name                           Flags
      width                          final
      step                           final

  public static final java.lang.Object $anonfun$makeBox$1$adapted(org.scalatest.tools.PrettyPrinter, org.scalatest.tools.PrettyPrinter$Item);
    descriptor: (Lorg/scalatest/tools/PrettyPrinter;Lorg/scalatest/tools/PrettyPrinter$Item;)Ljava/lang/Object;
    flags: (0x1019) ACC_PUBLIC, ACC_STATIC, ACC_FINAL, ACC_SYNTHETIC
    Code:
      stack=2, locals=2, args_size=2
         0: aload_0
         1: aload_1
         2: invokestatic  #738                // Method $anonfun$makeBox$1:(Lorg/scalatest/tools/PrettyPrinter;Lorg/scalatest/tools/PrettyPrinter$Item;)V
         5: getstatic     #397                // Field scala/runtime/BoxedUnit.UNIT:Lscala/runtime/BoxedUnit;
         8: areturn
      LineNumberTable:
        line 90: 0
      LocalVariableTable:
        Start  Length  Slot  Name   Signature
            0       9     0 $this   Lorg/scalatest/tools/PrettyPrinter;
            0       9     1   x$1   Lorg/scalatest/tools/PrettyPrinter$Item;
    MethodParameters:
      Name                           Flags
      $this                          final
      x$1                            final

  public static final java.lang.Object $anonfun$leafTag$1$adapted(scala.xml.Node, scala.collection.mutable.StringBuilder);
    descriptor: (Lscala/xml/Node;Lscala/collection/mutable/StringBuilder;)Ljava/lang/Object;
    flags: (0x1019) ACC_PUBLIC, ACC_STATIC, ACC_FINAL, ACC_SYNTHETIC
    Code:
      stack=2, locals=2, args_size=2
         0: aload_0
         1: aload_1
         2: invokestatic  #740                // Method $anonfun$leafTag$1:(Lscala/xml/Node;Lscala/collection/mutable/StringBuilder;)V
         5: getstatic     #397                // Field scala/runtime/BoxedUnit.UNIT:Lscala/runtime/BoxedUnit;
         8: areturn
      LineNumberTable:
        line 112: 0
      LocalVariableTable:
        Start  Length  Slot  Name   Signature
            0       9     0   n$1   Lscala/xml/Node;
            0       9     1    sb   Lscala/collection/mutable/StringBuilder;
    MethodParameters:
      Name                           Flags
      n$1                            final
      sb                             final

  public static final java.lang.Object $anonfun$startTag$1$adapted(scala.xml.Node, scala.runtime.IntRef, scala.xml.NamespaceBinding, scala.collection.mutable.StringBuilder);
    descriptor: (Lscala/xml/Node;Lscala/runtime/IntRef;Lscala/xml/NamespaceBinding;Lscala/collection/mutable/StringBuilder;)Ljava/lang/Object;
    flags: (0x1019) ACC_PUBLIC, ACC_STATIC, ACC_FINAL, ACC_SYNTHETIC
    Code:
      stack=4, locals=4, args_size=4
         0: aload_0
         1: aload_1
         2: aload_2
         3: aload_3
         4: invokestatic  #742                // Method $anonfun$startTag$1:(Lscala/xml/Node;Lscala/runtime/IntRef;Lscala/xml/NamespaceBinding;Lscala/collection/mutable/StringBuilder;)V
         7: getstatic     #397                // Field scala/runtime/BoxedUnit.UNIT:Lscala/runtime/BoxedUnit;
        10: areturn
      LineNumberTable:
        line 125: 0
      LocalVariableTable:
        Start  Length  Slot  Name   Signature
            0      11     0   n$2   Lscala/xml/Node;
            0      11     1   i$1   Lscala/runtime/IntRef;
            0      11     2 pscope$1   Lscala/xml/NamespaceBinding;
            0      11     3    sb   Lscala/collection/mutable/StringBuilder;
    MethodParameters:
      Name                           Flags
      n$2                            final
      i$1                            final
      pscope$1                       final
      sb                             final

  public static final java.lang.Object $anonfun$endTag$1$adapted(scala.xml.Node, scala.collection.mutable.StringBuilder);
    descriptor: (Lscala/xml/Node;Lscala/collection/mutable/StringBuilder;)Ljava/lang/Object;
    flags: (0x1019) ACC_PUBLIC, ACC_STATIC, ACC_FINAL, ACC_SYNTHETIC
    Code:
      stack=2, locals=2, args_size=2
         0: aload_0
         1: aload_1
         2: invokestatic  #744                // Method $anonfun$endTag$1:(Lscala/xml/Node;Lscala/collection/mutable/StringBuilder;)V
         5: getstatic     #397                // Field scala/runtime/BoxedUnit.UNIT:Lscala/runtime/BoxedUnit;
         8: areturn
      LineNumberTable:
        line 134: 0
      LocalVariableTable:
        Start  Length  Slot  Name   Signature
            0       9     0   n$3   Lscala/xml/Node;
            0       9     1    sb   Lscala/collection/mutable/StringBuilder;
    MethodParameters:
      Name                           Flags
      n$3                            final
      sb                             final

  public static final java.lang.Object $anonfun$childrenAreLeaves$1$adapted(scala.xml.Node);
    descriptor: (Lscala/xml/Node;)Ljava/lang/Object;
    flags: (0x1019) ACC_PUBLIC, ACC_STATIC, ACC_FINAL, ACC_SYNTHETIC
    Code:
      stack=1, locals=1, args_size=1
         0: aload_0
         1: invokestatic  #746                // Method $anonfun$childrenAreLeaves$1:(Lscala/xml/Node;)Z
         4: invokestatic  #750                // Method scala/runtime/BoxesRunTime.boxToBoolean:(Z)Ljava/lang/Boolean;
         7: areturn
      LineNumberTable:
        line 142: 0
      LocalVariableTable:
        Start  Length  Slot  Name   Signature
            0       8     0     l   Lscala/xml/Node;
    MethodParameters:
      Name                           Flags
      l                              final

  public static final java.lang.Object $anonfun$doPreserve$1$adapted(scala.collection.Seq);
    descriptor: (Lscala/collection/Seq;)Ljava/lang/Object;
    flags: (0x1019) ACC_PUBLIC, ACC_STATIC, ACC_FINAL, ACC_SYNTHETIC
    Code:
      stack=1, locals=1, args_size=1
         0: aload_0
         1: invokestatic  #752                // Method $anonfun$doPreserve$1:(Lscala/collection/Seq;)Z
         4: invokestatic  #750                // Method scala/runtime/BoxesRunTime.boxToBoolean:(Z)Ljava/lang/Boolean;
         7: areturn
      LineNumberTable:
        line 149: 0
      LocalVariableTable:
        Start  Length  Slot  Name   Signature
            0       8     0   x$2   Lscala/collection/Seq;
    MethodParameters:
      Name                           Flags
      x$2                            final

  public static final java.lang.Object $anonfun$traverse$1$adapted(org.scalatest.tools.PrettyPrinter, scala.xml.NamespaceBinding, int, scala.xml.Node);
    descriptor: (Lorg/scalatest/tools/PrettyPrinter;Lscala/xml/NamespaceBinding;ILscala/xml/Node;)Ljava/lang/Object;
    flags: (0x1019) ACC_PUBLIC, ACC_STATIC, ACC_FINAL, ACC_SYNTHETIC
    Code:
      stack=4, locals=4, args_size=4
         0: aload_0
         1: aload_1
         2: iload_2
         3: aload_3
         4: invokestatic  #754                // Method $anonfun$traverse$1:(Lorg/scalatest/tools/PrettyPrinter;Lscala/xml/NamespaceBinding;ILscala/xml/Node;)V
         7: getstatic     #397                // Field scala/runtime/BoxedUnit.UNIT:Lscala/runtime/BoxedUnit;
        10: areturn
      LineNumberTable:
        line 212: 0
      LocalVariableTable:
        Start  Length  Slot  Name   Signature
            0      11     0 $this   Lorg/scalatest/tools/PrettyPrinter;
            0      11     1 scope$1   Lscala/xml/NamespaceBinding;
            0      11     2 ind$1   I
            0      11     3     c   Lscala/xml/Node;
    MethodParameters:
      Name                           Flags
      $this                          final
      scope$1                        final
      ind$1                          final
      c                              final

  public static final java.lang.Object $anonfun$format$2$adapted(org.scalatest.tools.PrettyPrinter, scala.xml.Node, scala.xml.NamespaceBinding, scala.collection.mutable.StringBuilder);
    descriptor: (Lorg/scalatest/tools/PrettyPrinter;Lscala/xml/Node;Lscala/xml/NamespaceBinding;Lscala/collection/mutable/StringBuilder;)Ljava/lang/Object;
    flags: (0x1019) ACC_PUBLIC, ACC_STATIC, ACC_FINAL, ACC_SYNTHETIC
    Code:
      stack=4, locals=4, args_size=4
         0: aload_0
         1: aload_1
         2: aload_2
         3: aload_3
         4: invokestatic  #756                // Method $anonfun$format$2:(Lorg/scalatest/tools/PrettyPrinter;Lscala/xml/Node;Lscala/xml/NamespaceBinding;Lscala/collection/mutable/StringBuilder;)V
         7: getstatic     #397                // Field scala/runtime/BoxedUnit.UNIT:Lscala/runtime/BoxedUnit;
        10: areturn
      LineNumberTable:
        line 267: 0
      LocalVariableTable:
        Start  Length  Slot  Name   Signature
            0      11     0 $this   Lorg/scalatest/tools/PrettyPrinter;
            0      11     1   n$4   Lscala/xml/Node;
            0      11     2 pscope$2   Lscala/xml/NamespaceBinding;
            0      11     3   x$4   Lscala/collection/mutable/StringBuilder;
    MethodParameters:
      Name                           Flags
      $this                          final
      n$4                            final
      pscope$2                       final
      x$4                            final

  public static final java.lang.Object $anonfun$formatNodes$1$adapted(org.scalatest.tools.PrettyPrinter, scala.collection.Seq, scala.xml.NamespaceBinding, scala.collection.mutable.StringBuilder);
    descriptor: (Lorg/scalatest/tools/PrettyPrinter;Lscala/collection/Seq;Lscala/xml/NamespaceBinding;Lscala/collection/mutable/StringBuilder;)Ljava/lang/Object;
    flags: (0x1019) ACC_PUBLIC, ACC_STATIC, ACC_FINAL, ACC_SYNTHETIC
    Code:
      stack=4, locals=4, args_size=4
         0: aload_0
         1: aload_1
         2: aload_2
         3: aload_3
         4: invokestatic  #758                // Method $anonfun$formatNodes$1:(Lorg/scalatest/tools/PrettyPrinter;Lscala/collection/Seq;Lscala/xml/NamespaceBinding;Lscala/collection/mutable/StringBuilder;)V
         7: getstatic     #397                // Field scala/runtime/BoxedUnit.UNIT:Lscala/runtime/BoxedUnit;
        10: areturn
      LineNumberTable:
        line 276: 0
      LocalVariableTable:
        Start  Length  Slot  Name   Signature
            0      11     0 $this   Lorg/scalatest/tools/PrettyPrinter;
            0      11     1 nodes$1   Lscala/collection/Seq;
            0      11     2 pscope$3   Lscala/xml/NamespaceBinding;
            0      11     3   x$5   Lscala/collection/mutable/StringBuilder;
    MethodParameters:
      Name                           Flags
      $this                          final
      nodes$1                        final
      pscope$3                       final
      x$5                            final

  private static java.lang.Object $deserializeLambda$(java.lang.invoke.SerializedLambda);
    descriptor: (Ljava/lang/invoke/SerializedLambda;)Ljava/lang/Object;
    flags: (0x100a) ACC_PRIVATE, ACC_STATIC, ACC_SYNTHETIC
    Code:
      stack=1, locals=1, args_size=1
         0: aload_0
         1: invokedynamic #770,  0            // InvokeDynamic #12:lambdaDeserialize:(Ljava/lang/invoke/SerializedLambda;)Ljava/lang/Object;
         6: areturn
}
InnerClasses:
  public static final #13= #10 of #12;    // Lookup=class java/lang/invoke/MethodHandles$Lookup of class java/lang/invoke/MethodHandles
  public #16= #15 of #2;                  // Box=class org/scalatest/tools/PrettyPrinter$Box of class org/scalatest/tools/PrettyPrinter
  public #19= #18 of #2;                  // Box$=class org/scalatest/tools/PrettyPrinter$Box$ of class org/scalatest/tools/PrettyPrinter
  public #22= #21 of #2;                  // Break$=class org/scalatest/tools/PrettyPrinter$Break$ of class org/scalatest/tools/PrettyPrinter
  public #25= #24 of #2;                  // BrokenException=class org/scalatest/tools/PrettyPrinter$BrokenException of class org/scalatest/tools/PrettyPrinter
  public #28= #27 of #2;                  // Item=class org/scalatest/tools/PrettyPrinter$Item of class org/scalatest/tools/PrettyPrinter
  public #31= #30 of #2;                  // Para=class org/scalatest/tools/PrettyPrinter$Para of class org/scalatest/tools/PrettyPrinter
  public #34= #33 of #2;                  // Para$=class org/scalatest/tools/PrettyPrinter$Para$ of class org/scalatest/tools/PrettyPrinter
  public abstract #39= #36 of #38;        // Value=class scala/Enumeration$Value of class scala/Enumeration
SourceFile: "PrettyPrinter.scala"
RuntimeVisibleAnnotations:
  0: #6(#7=s#8)
    scala.reflect.ScalaSignature(
      bytes="\u0006\u0005\r\rc!B/_\u0001y#\u0007\u0002C6\u0001\u0005\u0003\u0005\u000b\u0011B7\t\u0011A\u0004!\u0011!Q\u0001\n5D\u0001\"\u001d\u0001\u0003\u0002\u0003\u0006IA\u001d\u0005\u0006k\u0002!\tA\u001e\u0005\u0006k\u0002!\t\u0001 \u0005\t\u007f\u0002\u0011\r\u0011\"\u0001\u0002\u0002!A\u0011\u0011\u0004\u0001!\u0002\u0013\t\u0019A\u0002\u0004\u0002\u001c\u0001\u0001\u0011Q\u0004\u0005\u0007k\"!\t!a\f\u0007\r\u0005U\u0002\u0001AA\u001c\u0011\u0019)(\u0002\"\u0001\u0002:\u001d9\u0011Q\b\u0001\t\u0002\u0006}baBA!\u0001!\u0005\u00151\t\u0005\u0007k6!\t!a\u0019\t\u000f\u0005\u0015T\u0002\"\u0011\u0002h!I\u0011qN\u0007\u0002\u0002\u0013\u0005\u0013\u0011\u000f\u0005\n\u0003gj\u0011\u0011!C\u0001\u0003kB\u0011\"a\u001e\u000e\u0003\u0003%\t!!\u001f\t\u0013\u0005\u0015U\"!A\u0005B\u0005\u001d\u0005\"CAK\u001b\u0005\u0005I\u0011AAL\u0011%\tY*DA\u0001\n\u0003\niJ\u0002\u0004\u0002 \u0002\u0001\u0015\u0011\u0015\u0005\u000b\u0003G3\"Q3A\u0005\u0002\u0005U\u0004\"CAS-\tE\t\u0015!\u0003n\u0011)\t9K\u0006BK\u0002\u0013\u0005\u0011\u0011\u0016\u0005\u000b\u0003s3\"\u0011#Q\u0001\n\u0005-\u0006BB;\u0017\t\u0003\tY\fC\u0005\u0002DZ\t\t\u0011\"\u0001\u0002F\"I\u00111\u001a\f\u0012\u0002\u0013\u0005\u0011Q\u001a\u0005\n\u0003G4\u0012\u0013!C\u0001\u0003KD\u0011\"a\u001c\u0017\u0003\u0003%\t%!\u001d\t\u0013\u0005Md#!A\u0005\u0002\u0005U\u0004\"CA<-\u0005\u0005I\u0011AAu\u0011%\t)IFA\u0001\n\u0003\n9\tC\u0005\u0002\u0016Z\t\t\u0011\"\u0001\u0002n\"I\u0011\u0011\u001f\f\u0002\u0002\u0013\u0005\u00131\u001f\u0005\n\u000373\u0012\u0011!C!\u0003;C\u0011\"!\u001a\u0017\u0003\u0003%\t%a\u001a\t\u0013\u0005]h#!A\u0005B\u0005ex!CA\u007f\u0001\u0005\u0005\t\u0012AA\u0000\r%\ty\nAA\u0001\u0012\u0003\u0011\t\u0001\u0003\u0004vS\u0011\u0005!\u0011\u0004\u0005\n\u0003KJ\u0013\u0011!C#\u0003OB\u0011Ba\u0007*\u0003\u0003%\tI!\b\t\u0013\t\r\u0012&!A\u0005\u0002\n\u0015bA\u0002B\u001c\u0001\u0001\u0013I\u0004\u0003\u0006\u0002(:\u0012)\u001a!C\u0001\u0003SC!\"!//\u0005#\u0005\u000b\u0011BAV\u0011\u0019)h\u0006\"\u0001\u0003<!I\u00111\u0019\u0018\u0002\u0002\u0013\u0005!\u0011\t\u0005\n\u0003\u0017t\u0013\u0013!C\u0001\u0003KD\u0011\"a\u001c/\u0003\u0003%\t%!\u001d\t\u0013\u0005Md&!A\u0005\u0002\u0005U\u0004\"CA<]\u0005\u0005I\u0011\u0001B#\u0011%\t)ILA\u0001\n\u0003\n9\tC\u0005\u0002\u0016:\n\t\u0011\"\u0001\u0003J!I\u0011\u0011\u001f\u0018\u0002\u0002\u0013\u0005#Q\n\u0005\n\u00037s\u0013\u0011!C!\u0003;C\u0011\"!\u001a/\u0003\u0003%\t%a\u001a\t\u0013\u0005]h&!A\u0005B\tEs!\u0003B+\u0001\u0005\u0005\t\u0012\u0001B,\r%\u00119\u0004AA\u0001\u0012\u0003\u0011I\u0006\u0003\u0004v}\u0011\u0005!\u0011\r\u0005\n\u0003Kr\u0014\u0011!C#\u0003OB\u0011Ba\u0007?\u0003\u0003%\tIa\u0019\t\u0013\t\rb(!A\u0005\u0002\n\u001d\u0004\"\u0003B7\u0001\u0001\u0007I\u0011\u0003B8\u0011%\u00119\b\u0001a\u0001\n#\u0011I\b\u0003\u0005\u0003\u0004\u0002\u0001\u000b\u0015\u0002B9\u0011%\u0011)\t\u0001a\u0001\n#\t)\bC\u0005\u0003\b\u0002\u0001\r\u0011\"\u0005\u0003\n\"9!Q\u0012\u0001!B\u0013i\u0007b\u0002BH\u0001\u0011E!\u0011\u0013\u0005\b\u0005\'\u0003A\u0011\u0003BK\u0011\u001d\u0011i\n\u0001C\t\u0005?CqA!*\u0001\t#\u00119\u000bC\u0004\u0003.\u0002!\tB!%\t\u000f\t=\u0006\u0001\"\u0005\u00032\"9!Q\u0018\u0001\u0005\u0012\t}\u0006b\u0002Bh\u0001\u0011E!\u0011\u001b\u0005\b\u0005+\u0004A\u0011\u0003Bl\u0011\u001d\u0011Y\u000e\u0001C\t\u0005;DqAa9\u0001\t\u0013\u0011)\u000fC\u0004\u0003l\u0002!\tB!<\t\u000f\t-\b\u0001\"\u0005\u0003v\"91Q\u0001\u0001\u0005\u0002\r\u001d\u0001bBB\u0003\u0001\u0011\u00051Q\u0003\u0005\b\u0007\u000b\u0001A\u0011AB\u000f\u0011%\u0019\u0019\u0003AI\u0001\n\u0003\u0019)\u0003C\u0004\u0004*\u0001!\taa\u000b\t\u0013\re\u0002!%A\u0005\u0002\r\u0015\u0002bBB\u0015\u0001\u0011\u000511\b\u0002\u000e!J,G\u000f^=Qe&tG/\u001a:\u000b\u0005}\u0003\u0017!\u0002;p_2\u001c(BA1c\u0003%\u00198-\u00197bi\u0016\u001cHOC\u0001d\u0003\ry\'oZ\n\u0003\u0001\u0015\u0004\"AZ5\u000e\u0003\u001dT\u0011\u0001[\u0001\u0006g\u000e\fG.Y\u0005\u0003U\u001e\u0014a!\u00118z%\u00164\u0017!B<jIRD7\u0001\u0001\t\u0003M:L!a\\4\u0003\u0007%sG/\u0001\u0003ti\u0016\u0004\u0018!D7j]&l\u0017N_3F[B$\u0018\u0010\u0005\u0002gg&\u0011Ao\u001a\u0002\b\u0005>|G.Z1o\u0003\u0019a\u0014N\\5u}Q!q/\u001f>|!\tA\b!D\u0001_\u0011\u0015YG\u00011\u0001n\u0011\u0015\u0001H\u00011\u0001n\u0011\u0015\tH\u00011\u0001s)\r9XP \u0005\u0006W\u0016\u0001\r!\u001c\u0005\u0006a\u0016\u0001\r!\\\u0001\r[&t\u0017.\\5{K6{G-Z\u000b\u0003\u0003\u0007\u0001B!!\u0002\u0002\u00129!\u0011qAA\u0007\u001b\t\tIAC\u0002\u0002\f\u001d\f1\u0001_7m\u0013\u0011\ty!!\u0003\u0002\u00195Kg.[7ju\u0016lu\u000eZ3\n\t\u0005M\u0011Q\u0003\u0002\u0006-\u0006dW/Z\u0005\u0004\u0003/9\'aC#ok6,\'/\u0019;j_:\fQ\"\\5oS6L\'0Z\'pI\u0016\u0004#a\u0004\"s_.,g.\u0012=dKB$\u0018n\u001c8\u0014\u0007!\ty\u0002\u0005\u0003\u0002\"\u0005-RBAA\u0012\u0015\u0011\t)#a\n\u0002\t1\fgn\u001a\u0006\u0003\u0003S\tAA[1wC&!\u0011QFA\u0012\u0005%)\u0005pY3qi&|g\u000e\u0006\u0002\u00022A\u0019\u00111\u0007\u0005\u000e\u0003\u0001\u0011A!\u0013;f[N\u0011!\"\u001a\u000b\u0003\u0003w\u00012!a\r\u000b\u0003\u0015\u0011%/Z1l!\r\t\u0019$\u0004\u0002\u0006\u0005J,\u0017m[\n\b\u001b\u0005m\u0012QIA&!\r1\u0017qI\u0005\u0004\u0003\u0013:\'a\u0002)s_\u0012,8\r\u001e\t\u0005\u0003\u001b\niF\u0004\u0003\u0002P\u0005ec\u0002BA)\u0003/j!!a\u0015\u000b\u0007\u0005UC.\u0001\u0004=e>|GOP\u0005\u0002Q&\u0019\u00111L4\u0002\u000fA\f7m[1hK&!\u0011qLA1\u00051\u0019VM]5bY&T\u0018M\u00197f\u0015\r\tYf\u001a\u000b\u0003\u0003\u007f\t\u0001\u0002^8TiJLgn\u001a\u000b\u0003\u0003S\u0002B!!\t\u0002l%!\u0011QNA\u0012\u0005\u0019\u0019FO]5oO\u0006i\u0001O]8ek\u000e$\bK]3gSb,\"!!\u001b\u0002\u0019A\u0014x\u000eZ;di\u0006\u0013\u0018\u000e^=\u0016\u00035\fa\u0002\u001d:pIV\u001cG/\u00127f[\u0016tG\u000f\u0006\u0003\u0002|\u0005\u0005\u0005c\u00014\u0002~%\u0019\u0011qP4\u0003\u0007\u0005s\u0017\u0010\u0003\u0005\u0002\u0004J\t\t\u00111\u0001n\u0003\rAH%M\u0001\u0010aJ|G-^2u\u0013R,\'/\u0019;peV\u0011\u0011\u0011\u0012\t\u0007\u0003\u0017\u000b\t*a\u001f\u000e\u0005\u00055%bAAHO\u0006Q1m\u001c7mK\u000e$\u0018n\u001c8\n\t\u0005M\u0015Q\u0012\u0002\t\u0013R,\'/\u0019;pe\u0006A1-\u00198FcV\fG\u000eF\u0002s\u00033C\u0011\"a!\u0015\u0003\u0003\u0005\r!a\u001f\u0002\u0011!\f7\u000f[\"pI\u0016$\u0012!\u001c\u0002\u0004\u0005>D8c\u0002\f\u0002<\u0005\u0015\u00131J\u0001\u0004G>d\u0017\u0001B2pY\u0002\n\u0011a]\u000b\u0003\u0003W\u0003B!!,\u00026:!\u0011qVAY!\r\t\tfZ\u0005\u0004\u0003g;\u0017A\u0002)sK\u0012,g-\u0003\u0003\u0002n\u0005]&bAAZO\u0006\u00111\u000f\t\u000b\u0007\u0003{\u000by,!1\u0011\u0007\u0005Mb\u0003\u0003\u0004\u0002$n\u0001\r!\u001c\u0005\b\u0003O[\u0002\u0019AAV\u0003\u0011\u0019w\u000e]=\u0015\r\u0005u\u0016qYAe\u0011!\t\u0019\u000b\bI\u0001\u0002\u0004i\u0007\"CAT9A\u0005\t\u0019AAV\u00039\u0019w\u000e]=%I\u00164\u0017-\u001e7uIE*\"!a4+\u00075\f\tn\u000b\u0002\u0002TB!\u0011Q[Ap\u001b\t\t9N\u0003\u0003\u0002Z\u0006m\u0017!C;oG\",7m[3e\u0015\r\tinZ\u0001\u000bC:tw\u000e^1uS>t\u0017\u0002BAq\u0003/\u0014\u0011#\u001e8dQ\u0016\u001c7.\u001a3WCJL\u0017M\\2f\u00039\u0019w\u000e]=%I\u00164\u0017-\u001e7uII*\"!a:+\t\u0005-\u0016\u0011\u001b\u000b\u0005\u0003w\nY\u000f\u0003\u0005\u0002\u0004\u0006\n\t\u00111\u0001n)\r\u0011\u0018q\u001e\u0005\n\u0003\u0007\u001b\u0013\u0011!a\u0001\u0003w\n!\u0003\u001d:pIV\u001cG/\u00127f[\u0016tGOT1nKR!\u0011\u0011NA{\u0011!\t\u0019\tJA\u0001\u0002\u0004i\u0017AB3rk\u0006d7\u000fF\u0002s\u0003wD\u0011\"a!(\u0003\u0003\u0005\r!a\u001f\u0002\u0007\t{\u0007\u0010E\u0002\u00024%\u001aR!\u000bB\u0002\u0005\u001f\u0001\u0012B!\u0002\u0003\f5\fY+!0\u000e\u0005\t\u001d!b\u0001B\u0005O\u00069!/\u001e8uS6,\u0017\u0002\u0002B\u0007\u0005\u000f\u0011\u0011#\u00112tiJ\f7\r\u001e$v]\u000e$\u0018n\u001c83!\u0011\u0011\tBa\u0006\u000e\u0005\tM!\u0002\u0002B\u000b\u0003O\t!![8\n\t\u0005}#1\u0003\u000b\u0003\u0003\u007f\fQ!\u00199qYf$b!!0\u0003 \t\u0005\u0002BBARY\u0001\u0007Q\u000eC\u0004\u0002(2\u0002\r!a+\u0002\u000fUt\u0017\r\u001d9msR!!q\u0005B\u001a!\u00151\'\u0011\u0006B\u0017\u0013\r\u0011Yc\u001a\u0002\u0007\u001fB$\u0018n\u001c8\u0011\r\u0019\u0014y#\\AV\u0013\r\u0011\td\u001a\u0002\u0007)V\u0004H.\u001a\u001a\t\u0013\tUR&!AA\u0002\u0005u\u0016a\u0001=%a\t!\u0001+\u0019:b\'\u001dq\u00131HA#\u0003\u0017\"BA!\u0010\u0003@A\u0019\u00111\u0007\u0018\t\u000f\u0005\u001d\u0016\u00071\u0001\u0002,R!!Q\bB\"\u0011%\t9K\rI\u0001\u0002\u0004\tY\u000b\u0006\u0003\u0002|\t\u001d\u0003\u0002CABm\u0005\u0005\t\u0019A7\u0015\u0007I\u0014Y\u0005C\u0005\u0002\u0004b\n\t\u00111\u0001\u0002|Q!\u0011\u0011\u000eB(\u0011!\t\u0019)OA\u0001\u0002\u0004iGc\u0001:\u0003T!I\u00111\u0011\u001f\u0002\u0002\u0003\u0007\u00111P\u0001\u0005!\u0006\u0014\u0018\rE\u0002\u00024y\u001aRA\u0010B.\u0005\u001f\u0001\u0002B!\u0002\u0003^\u0005-&QH\u0005\u0005\u0005?\u00129AA\tBEN$(/Y2u\rVt7\r^5p]F\"\"Aa\u0016\u0015\t\tu\"Q\r\u0005\b\u0003O\u000b\u0005\u0019AAV)\u0011\u0011IGa\u001b\u0011\u000b\u0019\u0014I#a+\t\u0013\tU\")!AA\u0002\tu\u0012!B5uK6\u001cXC\u0001B9!\u0019\tiEa\u001d\u0002<%!!QOA1\u0005\u0011a\u0015n\u001d;\u0002\u0013%$X-\\:`I\u0015\fH\u0003\u0002B>\u0005\u0003\u00032A\u001aB?\u0013\r\u0011yh\u001a\u0002\u0005+:LG\u000fC\u0005\u0002\u0004\u0012\u000b\t\u00111\u0001\u0003r\u00051\u0011\u000e^3ng\u0002\n1aY;s\u0003\u001d\u0019WO]0%KF$BAa\u001f\u0003\f\"A\u00111Q$\u0002\u0002\u0003\u0007Q.\u0001\u0003dkJ\u0004\u0013!\u0002:fg\u0016$HC\u0001B>\u0003\r\u0019W\u000f\u001e\u000b\u0007\u0005c\u00129J!\'\t\u000f\u0005\u001d&\n1\u0001\u0002,\"1!1\u0014&A\u00025\f1!\u001b8e\u0003\u001di\u0017m[3C_b$bAa\u001f\u0003\"\n\r\u0006B\u0002BN\u0017\u0002\u0007Q\u000eC\u0004\u0002(.\u0003\r!a+\u0002\u00115\f7.\u001a)be\u0006$bAa\u001f\u0003*\n-\u0006B\u0002BN\u0019\u0002\u0007Q\u000eC\u0004\u0002(2\u0003\r!a+\u0002\u00135\f7.\u001a\"sK\u0006\\\u0017a\u00027fC\u001a$\u0016m\u001a\u000b\u0005\u0003W\u0013\u0019\fC\u0004\u00036:\u0003\rAa.\u0002\u00039\u0004B!a\u0002\u0003:&!!1XA\u0005\u0005\u0011qu\u000eZ3\u0002\u0011M$\u0018M\u001d;UC\u001e$bA!1\u0003D\n\u0015\u0007C\u00024\u00030\u0005-V\u000eC\u0004\u00036>\u0003\rAa.\t\u000f\t\u001dw\n1\u0001\u0003J\u00061\u0001o]2pa\u0016\u0004B!a\u0002\u0003L&!!QZA\u0005\u0005Aq\u0015-\\3ta\u0006\u001cWMQ5oI&tw-\u0001\u0004f]\u0012$\u0016m\u001a\u000b\u0005\u0003W\u0013\u0019\u000eC\u0004\u00036B\u0003\rAa.\u0002#\rD\u0017\u000e\u001c3sK:\f%/\u001a\'fCZ,7\u000fF\u0002s\u00053DqA!.R\u0001\u0004\u00119,\u0001\u0003gSR\u001cHc\u0001:\u0003`\"9!\u0011\u001d*A\u0002\u0005-\u0016\u0001\u0002;fgR\f!\u0002Z8Qe\u0016\u001cXM\u001d<f)\r\u0011(q\u001d\u0005\b\u0005S\u001c\u0006\u0019\u0001B\\\u0003\u0011qw\u000eZ3\u0002\u0011Q\u0014\u0018M^3sg\u0016$\u0002Ba\u001f\u0003p\nE(1\u001f\u0005\b\u0005S$\u0006\u0019\u0001B\\\u0011\u001d\u00119\r\u0016a\u0001\u0005\u0013DaAa\'U\u0001\u0004iG\u0003\u0003B>\u0005o\u0014ypa\u0001\t\u000f\teX\u000b1\u0001\u0003|\u0006\u0011\u0011\u000e\u001e\t\u0007\u0003\u001b\u0012iPa.\n\t\u0005M\u0015\u0011\r\u0005\b\u0007\u0003)\u0006\u0019\u0001Be\u0003\u0015\u00198m\u001c9f\u0011\u0019\u0011Y*\u0016a\u0001[\u00061am\u001c:nCR$bAa\u001f\u0004\n\r-\u0001b\u0002B[-\u0002\u0007!q\u0017\u0005\b\u0007\u001b1\u0006\u0019AB\b\u0003\t\u0019(\r\u0005\u0003\u0002N\rE\u0011\u0002BB\n\u0003C\u0012Qb\u0015;sS:<\')^5mI\u0016\u0014H\u0003\u0003B>\u0007/\u0019Iba\u0007\t\u000f\tUv\u000b1\u0001\u00038\"9!qY,A\u0002\t%\u0007bBB\u0007/\u0002\u00071q\u0002\u000b\u0007\u0003W\u001byb!\t\t\u000f\tU\u0006\f1\u0001\u00038\"I!q\u0019-\u0011\u0002\u0003\u0007!\u0011Z\u0001\u0011M>\u0014X.\u0019;%I\u00164\u0017-\u001e7uII*\"aa\n+\t\t%\u0017\u0011[\u0001\fM>\u0014X.\u0019;O_\u0012,7\u000f\u0006\u0004\u0002,\u000e52q\u0007\u0005\b\u0007_Q\u0006\u0019AB\u0019\u0003\u0015qw\u000eZ3t!\u0019\tYia\r\u00038&!1QGAG\u0005\r\u0019V-\u001d\u0005\n\u0005\u000fT\u0006\u0013!a\u0001\u0005\u0013\fQCZ8s[\u0006$hj\u001c3fg\u0012\"WMZ1vYR$#\u0007\u0006\u0005\u0003|\ru2qHB!\u0011\u001d\u0019y\u0003\u0018a\u0001\u0007cAqAa2]\u0001\u0004\u0011I\rC\u0004\u0004\u000eq\u0003\raa\u0004"
    )
BootstrapMethods:
  0: #224 REF_invokeStatic java/lang/invoke/LambdaMetafactory.altMetafactory:(Ljava/lang/invoke/MethodHandles$Lookup;Ljava/lang/String;Ljava/lang/invoke/MethodType;[Ljava/lang/Object;)Ljava/lang/invoke/CallSite;
    Method arguments:
      #208 (Ljava/lang/Object;)Ljava/lang/Object;
      #213 REF_invokeStatic org/scalatest/tools/PrettyPrinter.$anonfun$makeBox$1$adapted:(Lorg/scalatest/tools/PrettyPrinter;Lorg/scalatest/tools/PrettyPrinter$Item;)Ljava/lang/Object;
      #215 (Lorg/scalatest/tools/PrettyPrinter$Item;)Ljava/lang/Object;
      #216 5
      #217 1
      #215 (Lorg/scalatest/tools/PrettyPrinter$Item;)Ljava/lang/Object;
  1: #224 REF_invokeStatic java/lang/invoke/LambdaMetafactory.altMetafactory:(Ljava/lang/invoke/MethodHandles$Lookup;Ljava/lang/String;Ljava/lang/invoke/MethodType;[Ljava/lang/Object;)Ljava/lang/invoke/CallSite;
    Method arguments:
      #208 (Ljava/lang/Object;)Ljava/lang/Object;
      #251 REF_invokeStatic org/scalatest/tools/PrettyPrinter.$anonfun$leafTag$1$adapted:(Lscala/xml/Node;Lscala/collection/mutable/StringBuilder;)Ljava/lang/Object;
      #253 (Lscala/collection/mutable/StringBuilder;)Ljava/lang/Object;
      #216 5
      #217 1
      #253 (Lscala/collection/mutable/StringBuilder;)Ljava/lang/Object;
  2: #224 REF_invokeStatic java/lang/invoke/LambdaMetafactory.altMetafactory:(Ljava/lang/invoke/MethodHandles$Lookup;Ljava/lang/String;Ljava/lang/invoke/MethodType;[Ljava/lang/Object;)Ljava/lang/invoke/CallSite;
    Method arguments:
      #208 (Ljava/lang/Object;)Ljava/lang/Object;
      #278 REF_invokeStatic org/scalatest/tools/PrettyPrinter.$anonfun$startTag$1$adapted:(Lscala/xml/Node;Lscala/runtime/IntRef;Lscala/xml/NamespaceBinding;Lscala/collection/mutable/StringBuilder;)Ljava/lang/Object;
      #253 (Lscala/collection/mutable/StringBuilder;)Ljava/lang/Object;
      #216 5
      #217 1
      #253 (Lscala/collection/mutable/StringBuilder;)Ljava/lang/Object;
  3: #224 REF_invokeStatic java/lang/invoke/LambdaMetafactory.altMetafactory:(Ljava/lang/invoke/MethodHandles$Lookup;Ljava/lang/String;Ljava/lang/invoke/MethodType;[Ljava/lang/Object;)Ljava/lang/invoke/CallSite;
    Method arguments:
      #208 (Ljava/lang/Object;)Ljava/lang/Object;
      #294 REF_invokeStatic org/scalatest/tools/PrettyPrinter.$anonfun$endTag$1$adapted:(Lscala/xml/Node;Lscala/collection/mutable/StringBuilder;)Ljava/lang/Object;
      #253 (Lscala/collection/mutable/StringBuilder;)Ljava/lang/Object;
      #216 5
      #217 1
      #253 (Lscala/collection/mutable/StringBuilder;)Ljava/lang/Object;
  4: #224 REF_invokeStatic java/lang/invoke/LambdaMetafactory.altMetafactory:(Ljava/lang/invoke/MethodHandles$Lookup;Ljava/lang/String;Ljava/lang/invoke/MethodType;[Ljava/lang/Object;)Ljava/lang/invoke/CallSite;
    Method arguments:
      #208 (Ljava/lang/Object;)Ljava/lang/Object;
      #308 REF_invokeStatic org/scalatest/tools/PrettyPrinter.$anonfun$childrenAreLeaves$1$adapted:(Lscala/xml/Node;)Ljava/lang/Object;
      #309 (Lscala/xml/Node;)Ljava/lang/Object;
      #216 5
      #217 1
      #309 (Lscala/xml/Node;)Ljava/lang/Object;
  5: #224 REF_invokeStatic java/lang/invoke/LambdaMetafactory.altMetafactory:(Ljava/lang/invoke/MethodHandles$Lookup;Ljava/lang/String;Ljava/lang/invoke/MethodType;[Ljava/lang/Object;)Ljava/lang/invoke/CallSite;
    Method arguments:
      #208 (Ljava/lang/Object;)Ljava/lang/Object;
      #344 REF_invokeStatic org/scalatest/tools/PrettyPrinter.$anonfun$doPreserve$1$adapted:(Lscala/collection/Seq;)Ljava/lang/Object;
      #345 (Lscala/collection/Seq;)Ljava/lang/Object;
      #216 5
      #217 1
      #345 (Lscala/collection/Seq;)Ljava/lang/Object;
  6: #224 REF_invokeStatic java/lang/invoke/LambdaMetafactory.altMetafactory:(Ljava/lang/invoke/MethodHandles$Lookup;Ljava/lang/String;Ljava/lang/invoke/MethodType;[Ljava/lang/Object;)Ljava/lang/invoke/CallSite;
    Method arguments:
      #354 ()Z
      #358 REF_invokeStatic org/scalatest/tools/PrettyPrinter.$anonfun$doPreserve$2:()Z
      #354 ()Z
      #217 1
  7: #224 REF_invokeStatic java/lang/invoke/LambdaMetafactory.altMetafactory:(Ljava/lang/invoke/MethodHandles$Lookup;Ljava/lang/String;Ljava/lang/invoke/MethodType;[Ljava/lang/Object;)Ljava/lang/invoke/CallSite;
    Method arguments:
      #208 (Ljava/lang/Object;)Ljava/lang/Object;
      #548 REF_invokeStatic org/scalatest/tools/PrettyPrinter.$anonfun$traverse$1$adapted:(Lorg/scalatest/tools/PrettyPrinter;Lscala/xml/NamespaceBinding;ILscala/xml/Node;)Ljava/lang/Object;
      #309 (Lscala/xml/Node;)Ljava/lang/Object;
      #216 5
      #217 1
      #309 (Lscala/xml/Node;)Ljava/lang/Object;
  8: #224 REF_invokeStatic java/lang/invoke/LambdaMetafactory.altMetafactory:(Ljava/lang/invoke/MethodHandles$Lookup;Ljava/lang/String;Ljava/lang/invoke/MethodType;[Ljava/lang/Object;)Ljava/lang/invoke/CallSite;
    Method arguments:
      #208 (Ljava/lang/Object;)Ljava/lang/Object;
      #582 REF_invokeStatic org/scalatest/tools/PrettyPrinter.$anonfun$format$1:(Lorg/scalatest/tools/PrettyPrinter;Lscala/runtime/BooleanRef;Lscala/collection/mutable/StringBuilder;Lscala/runtime/IntRef;Lorg/scalatest/tools/PrettyPrinter$Item;)Ljava/lang/Object;
      #215 (Lorg/scalatest/tools/PrettyPrinter$Item;)Ljava/lang/Object;
      #216 5
      #217 1
      #215 (Lorg/scalatest/tools/PrettyPrinter$Item;)Ljava/lang/Object;
  9: #224 REF_invokeStatic java/lang/invoke/LambdaMetafactory.altMetafactory:(Ljava/lang/invoke/MethodHandles$Lookup;Ljava/lang/String;Ljava/lang/invoke/MethodType;[Ljava/lang/Object;)Ljava/lang/invoke/CallSite;
    Method arguments:
      #208 (Ljava/lang/Object;)Ljava/lang/Object;
      #593 REF_invokeStatic org/scalatest/tools/PrettyPrinter.$anonfun$format$2$adapted:(Lorg/scalatest/tools/PrettyPrinter;Lscala/xml/Node;Lscala/xml/NamespaceBinding;Lscala/collection/mutable/StringBuilder;)Ljava/lang/Object;
      #253 (Lscala/collection/mutable/StringBuilder;)Ljava/lang/Object;
      #216 5
      #217 1
      #253 (Lscala/collection/mutable/StringBuilder;)Ljava/lang/Object;
  10: #224 REF_invokeStatic java/lang/invoke/LambdaMetafactory.altMetafactory:(Ljava/lang/invoke/MethodHandles$Lookup;Ljava/lang/String;Ljava/lang/invoke/MethodType;[Ljava/lang/Object;)Ljava/lang/invoke/CallSite;
    Method arguments:
      #208 (Ljava/lang/Object;)Ljava/lang/Object;
      #605 REF_invokeStatic org/scalatest/tools/PrettyPrinter.$anonfun$formatNodes$1$adapted:(Lorg/scalatest/tools/PrettyPrinter;Lscala/collection/Seq;Lscala/xml/NamespaceBinding;Lscala/collection/mutable/StringBuilder;)Ljava/lang/Object;
      #253 (Lscala/collection/mutable/StringBuilder;)Ljava/lang/Object;
      #216 5
      #217 1
      #253 (Lscala/collection/mutable/StringBuilder;)Ljava/lang/Object;
  11: #224 REF_invokeStatic java/lang/invoke/LambdaMetafactory.altMetafactory:(Ljava/lang/invoke/MethodHandles$Lookup;Ljava/lang/String;Ljava/lang/invoke/MethodType;[Ljava/lang/Object;)Ljava/lang/invoke/CallSite;
    Method arguments:
      #208 (Ljava/lang/Object;)Ljava/lang/Object;
      #615 REF_invokeStatic org/scalatest/tools/PrettyPrinter.$anonfun$formatNodes$2:(Lorg/scalatest/tools/PrettyPrinter;Lscala/collection/mutable/StringBuilder;Lscala/xml/NamespaceBinding;Lscala/xml/Node;)Lscala/collection/mutable/StringBuilder;
      #617 (Lscala/xml/Node;)Lscala/collection/mutable/StringBuilder;
      #216 5
      #217 1
      #617 (Lscala/xml/Node;)Lscala/collection/mutable/StringBuilder;
  12: #767 REF_invokeStatic scala/runtime/LambdaDeserialize.bootstrap:(Ljava/lang/invoke/MethodHandles$Lookup;Ljava/lang/String;Ljava/lang/invoke/MethodType;[Ljava/lang/invoke/MethodHandle;)Ljava/lang/invoke/CallSite;
    Method arguments:
      #308 REF_invokeStatic org/scalatest/tools/PrettyPrinter.$anonfun$childrenAreLeaves$1$adapted:(Lscala/xml/Node;)Ljava/lang/Object;
      #344 REF_invokeStatic org/scalatest/tools/PrettyPrinter.$anonfun$doPreserve$1$adapted:(Lscala/collection/Seq;)Ljava/lang/Object;
      #358 REF_invokeStatic org/scalatest/tools/PrettyPrinter.$anonfun$doPreserve$2:()Z
      #294 REF_invokeStatic org/scalatest/tools/PrettyPrinter.$anonfun$endTag$1$adapted:(Lscala/xml/Node;Lscala/collection/mutable/StringBuilder;)Ljava/lang/Object;
      #582 REF_invokeStatic org/scalatest/tools/PrettyPrinter.$anonfun$format$1:(Lorg/scalatest/tools/PrettyPrinter;Lscala/runtime/BooleanRef;Lscala/collection/mutable/StringBuilder;Lscala/runtime/IntRef;Lorg/scalatest/tools/PrettyPrinter$Item;)Ljava/lang/Object;
      #593 REF_invokeStatic org/scalatest/tools/PrettyPrinter.$anonfun$format$2$adapted:(Lorg/scalatest/tools/PrettyPrinter;Lscala/xml/Node;Lscala/xml/NamespaceBinding;Lscala/collection/mutable/StringBuilder;)Ljava/lang/Object;
      #605 REF_invokeStatic org/scalatest/tools/PrettyPrinter.$anonfun$formatNodes$1$adapted:(Lorg/scalatest/tools/PrettyPrinter;Lscala/collection/Seq;Lscala/xml/NamespaceBinding;Lscala/collection/mutable/StringBuilder;)Ljava/lang/Object;
      #615 REF_invokeStatic org/scalatest/tools/PrettyPrinter.$anonfun$formatNodes$2:(Lorg/scalatest/tools/PrettyPrinter;Lscala/collection/mutable/StringBuilder;Lscala/xml/NamespaceBinding;Lscala/xml/Node;)Lscala/collection/mutable/StringBuilder;
      #251 REF_invokeStatic org/scalatest/tools/PrettyPrinter.$anonfun$leafTag$1$adapted:(Lscala/xml/Node;Lscala/collection/mutable/StringBuilder;)Ljava/lang/Object;
      #213 REF_invokeStatic org/scalatest/tools/PrettyPrinter.$anonfun$makeBox$1$adapted:(Lorg/scalatest/tools/PrettyPrinter;Lorg/scalatest/tools/PrettyPrinter$Item;)Ljava/lang/Object;
      #278 REF_invokeStatic org/scalatest/tools/PrettyPrinter.$anonfun$startTag$1$adapted:(Lscala/xml/Node;Lscala/runtime/IntRef;Lscala/xml/NamespaceBinding;Lscala/collection/mutable/StringBuilder;)Ljava/lang/Object;
      #548 REF_invokeStatic org/scalatest/tools/PrettyPrinter.$anonfun$traverse$1$adapted:(Lorg/scalatest/tools/PrettyPrinter;Lscala/xml/NamespaceBinding;ILscala/xml/Node;)Ljava/lang/Object;
  ScalaInlineInfo: length = 0x126 (unknown attribute)
   01 00 00 3A 02 AA 01 29 01 01 30 01 31 01 02 AD
   02 AE 01 01 54 01 55 01 01 63 01 61 01 02 A5 02
   2D 01 01 23 00 F8 01 02 42 02 43 01 02 C3 02 C4
   01 02 4D 02 4E 01 02 C7 02 C8 01 02 59 02 5A 01
   02 63 02 64 01 02 91 02 2D 01 00 F7 00 F8 01 02
   74 02 75 01 00 D1 00 D2 01 02 9D 02 9E 01 01 12
   01 13 01 02 B3 02 B4 01 02 20 02 21 01 00 85 02
   DE 00 00 85 02 D1 00 00 10 00 43 01 00 46 00 3E
   01 00 39 00 3A 01 00 3D 00 3E 01 00 1F 00 49 01
   00 4C 00 3E 01 01 28 01 29 00 00 38 00 5A 00 00
   5D 00 5E 00 00 6E 00 6F 00 01 42 01 29 01 01 22
   00 F0 00 01 3F 01 40 00 02 2C 02 2D 00 02 2C 02
   4C 00 02 2C 02 33 00 02 55 01 F7 00 02 56 02 57
   00 02 56 02 61 00 02 6E 01 F7 00 02 A8 01 29 01
   00 35 00 52 00 00 56 00 57 00 00 EF 00 F0 00 00
   CB 00 CC 00 00 EE 00 3E 00 00 E8 00 CC 00 00 33
   00 4F 00 02 A1 02 79 01 02 78 02 79 01 02 94 02
   95 01 00 5F 00 3E 00 01 06 01 07 00 01 72 01 A4
   00 01 72 01 73 00
  ScalaSig: length = 0x3 (unknown attribute)
   05 02 00
