Classfile /Users/mw/Projects/slang-braindump/.jar/jar11/assemble/slang-braindump/assemble/content/org/scalatest/tools/ReadyState.class
  Last modified May 29, 2022; size 1248 bytes
  SHA-256 checksum 488adeaa4320434eacc45090b7ac93148677b87b8a597f6a25dbfe53c36c277a
  Compiled from "RunnerGUIState.scala"
public final class org.scalatest.tools.ReadyState
  minor version: 0
  major version: 52
  flags: (0x0031) ACC_PUBLIC, ACC_FINAL, ACC_SUPER
  this_class: #2                          // org/scalatest/tools/ReadyState
  super_class: #4                         // java/lang/Object
  interfaces: 0, fields: 0, methods: 4, attributes: 3
Constant pool:
   #1 = Utf8               org/scalatest/tools/ReadyState
   #2 = Class              #1             // org/scalatest/tools/ReadyState
   #3 = Utf8               java/lang/Object
   #4 = Class              #3             // java/lang/Object
   #5 = Utf8               RunnerGUIState.scala
   #6 = Utf8               Lscala/reflect/ScalaSignature;
   #7 = Utf8               bytes
   #8 = Utf8               \u0006\u00059:aa\u0002\u0005\t\u0002)qaA\u0002\t\t\u0011\u0003Q\u0011\u0003C\u0003\u001c\u0003\u0011\u0005Q\u0004C\u0003\u001f\u0003\u0011\u0005q\u0004C\u0003&\u0003\u0011\u0005a\u0005C\u0003)\u0003\u0011\u0005\u0011\u0006C\u0003,\u0003\u0011\u0005A&\u0001\u0006SK\u0006$\u0017p\u0015;bi\u0016T!!\u0003\u0006\u0002\u000bQ|w\u000e\\:\u000b\u0005-a\u0011!C:dC2\fG/Z:u\u0015\u0005i\u0011aA8sOB\u0011q\"A\u0007\u0002\u0011\tQ!+Z1esN#\u0018\r^3\u0014\u0007\u0005\u0011\u0002\u0004\u0005\u0002\u0014-5\tACC\u0001\u0016\u0003\u0015\u00198-\u00197b\u0013\t9BC\u0001\u0004B]f\u0014VM\u001a\t\u0003\u001feI!A\u0007\u0005\u0003\u001dI+hN\\3s\u000fVK5\u000b^1uK\u00061A(\u001b8jiz\u001a\u0001\u0001F\u0001\u000f\u0003A\u0011XO\u001c\"viR|g\u000e\u0015:fgN,G\r\u0006\u0002\u0019A!)\u0011e\u0001a\u0001E\u0005I!/\u001e8oKJ<U+\u0013\t\u0003\u001f\rJ!\u0001\n\u0005\u0003\u0013I+hN\\3s\u000fVK\u0015A\u0005:feVt\')\u001e;u_:\u0004&/Z:tK\u0012$\"\u0001G\u0014\t\u000b\u0005\"\u0001\u0019\u0001\u0012\u0002)1L7\u000f^*fY\u0016\u001cG/[8o\u0007\"\fgnZ3e)\tA\"\u0006C\u0003\"\u000b\u0001\u0007!%A\u0006sk:4\u0015N\\5tQ\u0016$GC\u0001\r.\u0011\u0015\tc\u00011\u0001#\u0001
   #9 = Utf8               runFinished
  #10 = Utf8               (Lorg/scalatest/tools/RunnerGUI;)Lorg/scalatest/tools/RunnerGUIState;
  #11 = Utf8               runnerGUI
  #12 = Utf8               org/scalatest/tools/ReadyState$
  #13 = Class              #12            // org/scalatest/tools/ReadyState$
  #14 = Utf8               MODULE$
  #15 = Utf8               Lorg/scalatest/tools/ReadyState$;
  #16 = NameAndType        #14:#15        // MODULE$:Lorg/scalatest/tools/ReadyState$;
  #17 = Fieldref           #13.#16        // org/scalatest/tools/ReadyState$.MODULE$:Lorg/scalatest/tools/ReadyState$;
  #18 = NameAndType        #9:#10         // runFinished:(Lorg/scalatest/tools/RunnerGUI;)Lorg/scalatest/tools/RunnerGUIState;
  #19 = Methodref          #13.#18        // org/scalatest/tools/ReadyState$.runFinished:(Lorg/scalatest/tools/RunnerGUI;)Lorg/scalatest/tools/RunnerGUIState;
  #20 = Utf8               Lorg/scalatest/tools/RunnerGUI;
  #21 = Utf8               listSelectionChanged
  #22 = NameAndType        #21:#10        // listSelectionChanged:(Lorg/scalatest/tools/RunnerGUI;)Lorg/scalatest/tools/RunnerGUIState;
  #23 = Methodref          #13.#22        // org/scalatest/tools/ReadyState$.listSelectionChanged:(Lorg/scalatest/tools/RunnerGUI;)Lorg/scalatest/tools/RunnerGUIState;
  #24 = Utf8               rerunButtonPressed
  #25 = NameAndType        #24:#10        // rerunButtonPressed:(Lorg/scalatest/tools/RunnerGUI;)Lorg/scalatest/tools/RunnerGUIState;
  #26 = Methodref          #13.#25        // org/scalatest/tools/ReadyState$.rerunButtonPressed:(Lorg/scalatest/tools/RunnerGUI;)Lorg/scalatest/tools/RunnerGUIState;
  #27 = Utf8               runButtonPressed
  #28 = NameAndType        #27:#10        // runButtonPressed:(Lorg/scalatest/tools/RunnerGUI;)Lorg/scalatest/tools/RunnerGUIState;
  #29 = Methodref          #13.#28        // org/scalatest/tools/ReadyState$.runButtonPressed:(Lorg/scalatest/tools/RunnerGUI;)Lorg/scalatest/tools/RunnerGUIState;
  #30 = Utf8               Code
  #31 = Utf8               LocalVariableTable
  #32 = Utf8               MethodParameters
  #33 = Utf8               SourceFile
  #34 = Utf8               RuntimeVisibleAnnotations
  #35 = Utf8               ScalaSig
{
  public static org.scalatest.tools.RunnerGUIState runFinished(org.scalatest.tools.RunnerGUI);
    descriptor: (Lorg/scalatest/tools/RunnerGUI;)Lorg/scalatest/tools/RunnerGUIState;
    flags: (0x0009) ACC_PUBLIC, ACC_STATIC
    Code:
      stack=2, locals=1, args_size=1
         0: getstatic     #17                 // Field org/scalatest/tools/ReadyState$.MODULE$:Lorg/scalatest/tools/ReadyState$;
         3: aload_0
         4: invokevirtual #19                 // Method org/scalatest/tools/ReadyState$.runFinished:(Lorg/scalatest/tools/RunnerGUI;)Lorg/scalatest/tools/RunnerGUIState;
         7: areturn
      LocalVariableTable:
        Start  Length  Slot  Name   Signature
            0       8     0 runnerGUI   Lorg/scalatest/tools/RunnerGUI;
    MethodParameters:
      Name                           Flags
      runnerGUI                      final

  public static org.scalatest.tools.RunnerGUIState listSelectionChanged(org.scalatest.tools.RunnerGUI);
    descriptor: (Lorg/scalatest/tools/RunnerGUI;)Lorg/scalatest/tools/RunnerGUIState;
    flags: (0x0009) ACC_PUBLIC, ACC_STATIC
    Code:
      stack=2, locals=1, args_size=1
         0: getstatic     #17                 // Field org/scalatest/tools/ReadyState$.MODULE$:Lorg/scalatest/tools/ReadyState$;
         3: aload_0
         4: invokevirtual #23                 // Method org/scalatest/tools/ReadyState$.listSelectionChanged:(Lorg/scalatest/tools/RunnerGUI;)Lorg/scalatest/tools/RunnerGUIState;
         7: areturn
      LocalVariableTable:
        Start  Length  Slot  Name   Signature
            0       8     0 runnerGUI   Lorg/scalatest/tools/RunnerGUI;
    MethodParameters:
      Name                           Flags
      runnerGUI                      final

  public static org.scalatest.tools.RunnerGUIState rerunButtonPressed(org.scalatest.tools.RunnerGUI);
    descriptor: (Lorg/scalatest/tools/RunnerGUI;)Lorg/scalatest/tools/RunnerGUIState;
    flags: (0x0009) ACC_PUBLIC, ACC_STATIC
    Code:
      stack=2, locals=1, args_size=1
         0: getstatic     #17                 // Field org/scalatest/tools/ReadyState$.MODULE$:Lorg/scalatest/tools/ReadyState$;
         3: aload_0
         4: invokevirtual #26                 // Method org/scalatest/tools/ReadyState$.rerunButtonPressed:(Lorg/scalatest/tools/RunnerGUI;)Lorg/scalatest/tools/RunnerGUIState;
         7: areturn
      LocalVariableTable:
        Start  Length  Slot  Name   Signature
            0       8     0 runnerGUI   Lorg/scalatest/tools/RunnerGUI;
    MethodParameters:
      Name                           Flags
      runnerGUI                      final

  public static org.scalatest.tools.RunnerGUIState runButtonPressed(org.scalatest.tools.RunnerGUI);
    descriptor: (Lorg/scalatest/tools/RunnerGUI;)Lorg/scalatest/tools/RunnerGUIState;
    flags: (0x0009) ACC_PUBLIC, ACC_STATIC
    Code:
      stack=2, locals=1, args_size=1
         0: getstatic     #17                 // Field org/scalatest/tools/ReadyState$.MODULE$:Lorg/scalatest/tools/ReadyState$;
         3: aload_0
         4: invokevirtual #29                 // Method org/scalatest/tools/ReadyState$.runButtonPressed:(Lorg/scalatest/tools/RunnerGUI;)Lorg/scalatest/tools/RunnerGUIState;
         7: areturn
      LocalVariableTable:
        Start  Length  Slot  Name   Signature
            0       8     0 runnerGUI   Lorg/scalatest/tools/RunnerGUI;
    MethodParameters:
      Name                           Flags
      runnerGUI                      final
}
SourceFile: "RunnerGUIState.scala"
RuntimeVisibleAnnotations:
  0: #6(#7=s#8)
    scala.reflect.ScalaSignature(
      bytes="\u0006\u00059:aa\u0002\u0005\t\u0002)qaA\u0002\t\t\u0011\u0003Q\u0011\u0003C\u0003\u001c\u0003\u0011\u0005Q\u0004C\u0003\u001f\u0003\u0011\u0005q\u0004C\u0003&\u0003\u0011\u0005a\u0005C\u0003)\u0003\u0011\u0005\u0011\u0006C\u0003,\u0003\u0011\u0005A&\u0001\u0006SK\u0006$\u0017p\u0015;bi\u0016T!!\u0003\u0006\u0002\u000bQ|w\u000e\\:\u000b\u0005-a\u0011!C:dC2\fG/Z:u\u0015\u0005i\u0011aA8sOB\u0011q\"A\u0007\u0002\u0011\tQ!+Z1esN#\u0018\r^3\u0014\u0007\u0005\u0011\u0002\u0004\u0005\u0002\u0014-5\tACC\u0001\u0016\u0003\u0015\u00198-\u00197b\u0013\t9BC\u0001\u0004B]f\u0014VM\u001a\t\u0003\u001feI!A\u0007\u0005\u0003\u001dI+hN\\3s\u000fVK5\u000b^1uK\u00061A(\u001b8jiz\u001a\u0001\u0001F\u0001\u000f\u0003A\u0011XO\u001c\"viR|g\u000e\u0015:fgN,G\r\u0006\u0002\u0019A!)\u0011e\u0001a\u0001E\u0005I!/\u001e8oKJ<U+\u0013\t\u0003\u001f\rJ!\u0001\n\u0005\u0003\u0013I+hN\\3s\u000fVK\u0015A\u0005:feVt\')\u001e;u_:\u0004&/Z:tK\u0012$\"\u0001G\u0014\t\u000b\u0005\"\u0001\u0019\u0001\u0012\u0002)1L7\u000f^*fY\u0016\u001cG/[8o\u0007\"\fgnZ3e)\tA\"\u0006C\u0003\"\u000b\u0001\u0007!%A\u0006sk:4\u0015N\\5tQ\u0016$GC\u0001\r.\u0011\u0015\tc\u00011\u0001#\u0001"
    )
  ScalaSig: length = 0x3 (unknown attribute)
   05 02 00
