Classfile /Users/mw/Projects/slang-braindump/.jar/jar11/assemble/slang-braindump/assemble/content/org/scalatest/tools/ReporterElement.class
  Last modified May 29, 2022; size 4607 bytes
  SHA-256 checksum 32d2f1e392ca83714afc2bc26587226d81334df39127b41ffa6ec650542fa8f7
  Compiled from "ScalaTestAntTask.scala"
public class org.scalatest.tools.ReporterElement
  minor version: 0
  major version: 52
  flags: (0x0021) ACC_PUBLIC, ACC_SUPER
  this_class: #2                          // org/scalatest/tools/ReporterElement
  super_class: #4                         // java/lang/Object
  interfaces: 0, fields: 7, methods: 29, attributes: 4
Constant pool:
    #1 = Utf8               org/scalatest/tools/ReporterElement
    #2 = Class              #1            // org/scalatest/tools/ReporterElement
    #3 = Utf8               java/lang/Object
    #4 = Class              #3            // java/lang/Object
    #5 = Utf8               ScalaTestAntTask.scala
    #6 = Utf8               Lscala/reflect/ScalaSignature;
    #7 = Utf8               bytes
    #8 = Utf8               \u0006\u0005\u0005]a\u0001B\u0013\'\t5BQ\u0001\u000e\u0001\u0005\u0002UBq\u0001\u000f\u0001A\u0002\u0013%\u0011\bC\u0004F\u0001\u0001\u0007I\u0011\u0002$\t\r1\u0003\u0001\u0015)\u0003;\u0011\u001di\u0005\u00011A\u0005\neBqA\u0014\u0001A\u0002\u0013%q\n\u0003\u0004R\u0001\u0001\u0006KA\u000f\u0005\b%\u0002\u0001\r\u0011\"\u0003:\u0011\u001d\u0019\u0006\u00011A\u0005\nQCaA\u0016\u0001!B\u0013Q\u0004bB,\u0001\u0001\u0004%I!\u000f\u0005\b1\u0002\u0001\r\u0011\"\u0003Z\u0011\u0019Y\u0006\u0001)Q\u0005u!9A\f\u0001a\u0001\n\u0013I\u0004bB/\u0001\u0001\u0004%IA\u0018\u0005\u0007A\u0002\u0001\u000b\u0015\u0002\u001e\t\u000f\u0005\u0004\u0001\u0019!C\u0005E\"9a\r\u0001a\u0001\n\u00139\u0007BB5\u0001A\u0003&1\rC\u0004k\u0001\u0001\u0007I\u0011B\u001d\t\u000f-\u0004\u0001\u0019!C\u0005Y\"1a\u000e\u0001Q!\niBQa\u001c\u0001\u0005\u0002ADQA\u001d\u0001\u0005\u0002MDQ!\u001e\u0001\u0005\u0002YDQ\u0001\u001f\u0001\u0005\u0002eDQa\u001f\u0001\u0005\u0002qDQA \u0001\u0005\u0002}Dq!a\u0001\u0001\t\u0003\t)\u0001\u0003\u0004\u0002\n\u0001!\t!\u000f\u0005\u0007\u0003\u0017\u0001A\u0011A\u001d\t\r\u00055\u0001\u0001\"\u0001:\u0011\u0019\ty\u0001\u0001C\u0001s!1\u0011\u0011\u0003\u0001\u0005\u0002eBa!a\u0005\u0001\t\u0003\u0011\u0007BBA\u000b\u0001\u0011\u0005\u0011HA\bSKB|\'\u000f^3s\u000b2,W.\u001a8u\u0015\t9\u0003&A\u0003u_>d7O\u0003\u0002*U\u0005I1oY1mCR,7\u000f\u001e\u0006\u0002W\u0005\u0019qN]4\u0004\u0001M\u0011\u0001A\f\t\u0003_Ij\u0011\u0001\r\u0006\u0002c\u0005)1oY1mC&\u00111\u0007\r\u0002\u0007\u0003:L(+\u001a4\u0002\rqJg.\u001b;?)\u00051\u0004CA\u001c\u0001\u001b\u00051\u0013!\u0002:usB,W#\u0001\u001e\u0011\u0005m\u0012eB\u0001\u001fA!\ti\u0004\'D\u0001?\u0015\tyD&\u0001\u0004=e>|GOP\u0005\u0003\u0003B\na\u0001\u0015:fI\u00164\u0017BA\"E\u0005\u0019\u0019FO]5oO*\u0011\u0011\tM\u0001\neRL\b/Z0%KF$\"a\u0012&\u0011\u0005=B\u0015BA%1\u0005\u0011)f.\u001b;\t\u000f-\u001b\u0011\u0011!a\u0001u\u0005\u0019\u0001\u0010J\u0019\u0002\rI$\u0018\u0010]3!\u0003\u0019\u0019wN\u001c4jO\u0006Q1m\u001c8gS\u001e|F%Z9\u0015\u0005\u001d\u0003\u0006bB&\u0007\u0003\u0003\u0005\rAO\u0001\bG>tg-[4!\u0003!1\u0017\u000e\\3oC6,\u0017\u0001\u00044jY\u0016t\u0017-\\3`I\u0015\fHCA$V\u0011\u001dY\u0015\"!AA\u0002i\n\u0011BZ5mK:\fW.\u001a\u0011\u0002\u0013\u0011L\'/Z2u_JL\u0018!\u00043je\u0016\u001cGo\u001c:z?\u0012*\u0017\u000f\u0006\u0002H5\"91\nDA\u0001\u0002\u0004Q\u0014A\u00033je\u0016\u001cGo\u001c:zA\u0005I1\r\\1tg:\fW.Z\u0001\u000eG2\f7o\u001d8b[\u0016|F%Z9\u0015\u0005\u001d{\u0006bB&\u0010\u0003\u0003\u0005\rAO\u0001\u000bG2\f7o\u001d8b[\u0016\u0004\u0013\u0001\u00038v[\u001aLG.Z:\u0016\u0003\r\u0004\"a\f3\n\u0005\u0015\u0004$aA%oi\u0006aa.^7gS2,7o\u0018\u0013fcR\u0011q\t\u001b\u0005\b\u0017J\t\t\u00111\u0001d\u0003%qW/\u001c4jY\u0016\u001c\b%A\u0002dgN\fqaY:t?\u0012*\u0017\u000f\u0006\u0002H[\"91*FA\u0001\u0002\u0004Q\u0014\u0001B2tg\u0002\nqa]3u)f\u0004X\r\u0006\u0002Hc\")\u0001h\u0006a\u0001u\u0005I1/\u001a;D_:4\u0017n\u001a\u000b\u0003\u000fRDQ!\u0014\rA\u0002i\n1b]3u\r&dWM\\1nKR\u0011qi\u001e\u0005\u0006%f\u0001\rAO\u0001\rg\u0016$H)\u001b:fGR|\'/\u001f\u000b\u0003\u000fjDQa\u0016\u000eA\u0002i\nAb]3u\u00072\f7o\u001d(b[\u0016$\"aR?\t\u000bq[\u0002\u0019\u0001\u001e\u0002\u0017M,GOT;nM&dWm\u001d\u000b\u0004\u000f\u0006\u0005\u0001\"B1\u001d\u0001\u0004\u0019\u0017AB:fi\u000e\u001b8\u000fF\u0002H\u0003\u000fAQA[\u000fA\u0002i\nqaZ3u)f\u0004X-A\u0005hKR\u001cuN\u001c4jO\u0006Yq-\u001a;GS2,g.Y7f\u000319W\r\u001e#je\u0016\u001cGo\u001c:z\u000319W\r^\"mCN\u001ch*Y7f\u0003-9W\r\u001e(v[\u001aLG.Z:\u0002\r\u001d,GoQ:t\u0001
    #9 = Utf8               rtype
   #10 = Utf8               Ljava/lang/String;
   #11 = Utf8               config
   #12 = Utf8               filename
   #13 = Utf8               directory
   #14 = Utf8               classname
   #15 = Utf8               numfiles
   #16 = Utf8               I
   #17 = Utf8               css
   #18 = Utf8               ()Ljava/lang/String;
   #19 = NameAndType        #9:#10        // rtype:Ljava/lang/String;
   #20 = Fieldref           #2.#19        // org/scalatest/tools/ReporterElement.rtype:Ljava/lang/String;
   #21 = Utf8               this
   #22 = Utf8               Lorg/scalatest/tools/ReporterElement;
   #23 = Utf8               rtype_$eq
   #24 = Utf8               (Ljava/lang/String;)V
   #25 = Utf8               x$1
   #26 = NameAndType        #11:#10       // config:Ljava/lang/String;
   #27 = Fieldref           #2.#26        // org/scalatest/tools/ReporterElement.config:Ljava/lang/String;
   #28 = Utf8               config_$eq
   #29 = NameAndType        #12:#10       // filename:Ljava/lang/String;
   #30 = Fieldref           #2.#29        // org/scalatest/tools/ReporterElement.filename:Ljava/lang/String;
   #31 = Utf8               filename_$eq
   #32 = NameAndType        #13:#10       // directory:Ljava/lang/String;
   #33 = Fieldref           #2.#32        // org/scalatest/tools/ReporterElement.directory:Ljava/lang/String;
   #34 = Utf8               directory_$eq
   #35 = NameAndType        #14:#10       // classname:Ljava/lang/String;
   #36 = Fieldref           #2.#35        // org/scalatest/tools/ReporterElement.classname:Ljava/lang/String;
   #37 = Utf8               classname_$eq
   #38 = Utf8               ()I
   #39 = NameAndType        #15:#16       // numfiles:I
   #40 = Fieldref           #2.#39        // org/scalatest/tools/ReporterElement.numfiles:I
   #41 = Utf8               numfiles_$eq
   #42 = Utf8               (I)V
   #43 = NameAndType        #17:#10       // css:Ljava/lang/String;
   #44 = Fieldref           #2.#43        // org/scalatest/tools/ReporterElement.css:Ljava/lang/String;
   #45 = Utf8               css_$eq
   #46 = Utf8               setType
   #47 = NameAndType        #23:#24       // rtype_$eq:(Ljava/lang/String;)V
   #48 = Methodref          #2.#47        // org/scalatest/tools/ReporterElement.rtype_$eq:(Ljava/lang/String;)V
   #49 = Utf8               setConfig
   #50 = NameAndType        #28:#24       // config_$eq:(Ljava/lang/String;)V
   #51 = Methodref          #2.#50        // org/scalatest/tools/ReporterElement.config_$eq:(Ljava/lang/String;)V
   #52 = Utf8               setFilename
   #53 = NameAndType        #31:#24       // filename_$eq:(Ljava/lang/String;)V
   #54 = Methodref          #2.#53        // org/scalatest/tools/ReporterElement.filename_$eq:(Ljava/lang/String;)V
   #55 = Utf8               setDirectory
   #56 = NameAndType        #34:#24       // directory_$eq:(Ljava/lang/String;)V
   #57 = Methodref          #2.#56        // org/scalatest/tools/ReporterElement.directory_$eq:(Ljava/lang/String;)V
   #58 = Utf8               setClassName
   #59 = NameAndType        #37:#24       // classname_$eq:(Ljava/lang/String;)V
   #60 = Methodref          #2.#59        // org/scalatest/tools/ReporterElement.classname_$eq:(Ljava/lang/String;)V
   #61 = Utf8               setNumfiles
   #62 = NameAndType        #41:#42       // numfiles_$eq:(I)V
   #63 = Methodref          #2.#62        // org/scalatest/tools/ReporterElement.numfiles_$eq:(I)V
   #64 = Utf8               setCss
   #65 = NameAndType        #45:#24       // css_$eq:(Ljava/lang/String;)V
   #66 = Methodref          #2.#65        // org/scalatest/tools/ReporterElement.css_$eq:(Ljava/lang/String;)V
   #67 = Utf8               getType
   #68 = NameAndType        #9:#18        // rtype:()Ljava/lang/String;
   #69 = Methodref          #2.#68        // org/scalatest/tools/ReporterElement.rtype:()Ljava/lang/String;
   #70 = Utf8               getConfig
   #71 = NameAndType        #11:#18       // config:()Ljava/lang/String;
   #72 = Methodref          #2.#71        // org/scalatest/tools/ReporterElement.config:()Ljava/lang/String;
   #73 = Utf8               getFilename
   #74 = NameAndType        #12:#18       // filename:()Ljava/lang/String;
   #75 = Methodref          #2.#74        // org/scalatest/tools/ReporterElement.filename:()Ljava/lang/String;
   #76 = Utf8               getDirectory
   #77 = NameAndType        #13:#18       // directory:()Ljava/lang/String;
   #78 = Methodref          #2.#77        // org/scalatest/tools/ReporterElement.directory:()Ljava/lang/String;
   #79 = Utf8               getClassName
   #80 = NameAndType        #14:#18       // classname:()Ljava/lang/String;
   #81 = Methodref          #2.#80        // org/scalatest/tools/ReporterElement.classname:()Ljava/lang/String;
   #82 = Utf8               getNumfiles
   #83 = NameAndType        #15:#38       // numfiles:()I
   #84 = Methodref          #2.#83        // org/scalatest/tools/ReporterElement.numfiles:()I
   #85 = Utf8               getCss
   #86 = NameAndType        #17:#18       // css:()Ljava/lang/String;
   #87 = Methodref          #2.#86        // org/scalatest/tools/ReporterElement.css:()Ljava/lang/String;
   #88 = Utf8               <init>
   #89 = Utf8               ()V
   #90 = NameAndType        #88:#89       // "<init>":()V
   #91 = Methodref          #4.#90        // java/lang/Object."<init>":()V
   #92 = Utf8               Code
   #93 = Utf8               LineNumberTable
   #94 = Utf8               LocalVariableTable
   #95 = Utf8               MethodParameters
   #96 = Utf8               SourceFile
   #97 = Utf8               RuntimeVisibleAnnotations
   #98 = Utf8               ScalaInlineInfo
   #99 = Utf8               ScalaSig
{
  private java.lang.String rtype;
    descriptor: Ljava/lang/String;
    flags: (0x0002) ACC_PRIVATE

  private java.lang.String config;
    descriptor: Ljava/lang/String;
    flags: (0x0002) ACC_PRIVATE

  private java.lang.String filename;
    descriptor: Ljava/lang/String;
    flags: (0x0002) ACC_PRIVATE

  private java.lang.String directory;
    descriptor: Ljava/lang/String;
    flags: (0x0002) ACC_PRIVATE

  private java.lang.String classname;
    descriptor: Ljava/lang/String;
    flags: (0x0002) ACC_PRIVATE

  private int numfiles;
    descriptor: I
    flags: (0x0002) ACC_PRIVATE

  private java.lang.String css;
    descriptor: Ljava/lang/String;
    flags: (0x0002) ACC_PRIVATE

  private java.lang.String rtype();
    descriptor: ()Ljava/lang/String;
    flags: (0x0002) ACC_PRIVATE
    Code:
      stack=1, locals=1, args_size=1
         0: aload_0
         1: getfield      #20                 // Field rtype:Ljava/lang/String;
         4: areturn
      LineNumberTable:
        line 1102: 0
      LocalVariableTable:
        Start  Length  Slot  Name   Signature
            0       5     0  this   Lorg/scalatest/tools/ReporterElement;

  private void rtype_$eq(java.lang.String);
    descriptor: (Ljava/lang/String;)V
    flags: (0x0002) ACC_PRIVATE
    Code:
      stack=2, locals=2, args_size=2
         0: aload_0
         1: aload_1
         2: putfield      #20                 // Field rtype:Ljava/lang/String;
         5: return
      LineNumberTable:
        line 1102: 0
      LocalVariableTable:
        Start  Length  Slot  Name   Signature
            0       6     0  this   Lorg/scalatest/tools/ReporterElement;
            0       6     1   x$1   Ljava/lang/String;
    MethodParameters:
      Name                           Flags
      x$1                            final

  private java.lang.String config();
    descriptor: ()Ljava/lang/String;
    flags: (0x0002) ACC_PRIVATE
    Code:
      stack=1, locals=1, args_size=1
         0: aload_0
         1: getfield      #27                 // Field config:Ljava/lang/String;
         4: areturn
      LineNumberTable:
        line 1103: 0
      LocalVariableTable:
        Start  Length  Slot  Name   Signature
            0       5     0  this   Lorg/scalatest/tools/ReporterElement;

  private void config_$eq(java.lang.String);
    descriptor: (Ljava/lang/String;)V
    flags: (0x0002) ACC_PRIVATE
    Code:
      stack=2, locals=2, args_size=2
         0: aload_0
         1: aload_1
         2: putfield      #27                 // Field config:Ljava/lang/String;
         5: return
      LineNumberTable:
        line 1103: 0
      LocalVariableTable:
        Start  Length  Slot  Name   Signature
            0       6     0  this   Lorg/scalatest/tools/ReporterElement;
            0       6     1   x$1   Ljava/lang/String;
    MethodParameters:
      Name                           Flags
      x$1                            final

  private java.lang.String filename();
    descriptor: ()Ljava/lang/String;
    flags: (0x0002) ACC_PRIVATE
    Code:
      stack=1, locals=1, args_size=1
         0: aload_0
         1: getfield      #30                 // Field filename:Ljava/lang/String;
         4: areturn
      LineNumberTable:
        line 1104: 0
      LocalVariableTable:
        Start  Length  Slot  Name   Signature
            0       5     0  this   Lorg/scalatest/tools/ReporterElement;

  private void filename_$eq(java.lang.String);
    descriptor: (Ljava/lang/String;)V
    flags: (0x0002) ACC_PRIVATE
    Code:
      stack=2, locals=2, args_size=2
         0: aload_0
         1: aload_1
         2: putfield      #30                 // Field filename:Ljava/lang/String;
         5: return
      LineNumberTable:
        line 1104: 0
      LocalVariableTable:
        Start  Length  Slot  Name   Signature
            0       6     0  this   Lorg/scalatest/tools/ReporterElement;
            0       6     1   x$1   Ljava/lang/String;
    MethodParameters:
      Name                           Flags
      x$1                            final

  private java.lang.String directory();
    descriptor: ()Ljava/lang/String;
    flags: (0x0002) ACC_PRIVATE
    Code:
      stack=1, locals=1, args_size=1
         0: aload_0
         1: getfield      #33                 // Field directory:Ljava/lang/String;
         4: areturn
      LineNumberTable:
        line 1105: 0
      LocalVariableTable:
        Start  Length  Slot  Name   Signature
            0       5     0  this   Lorg/scalatest/tools/ReporterElement;

  private void directory_$eq(java.lang.String);
    descriptor: (Ljava/lang/String;)V
    flags: (0x0002) ACC_PRIVATE
    Code:
      stack=2, locals=2, args_size=2
         0: aload_0
         1: aload_1
         2: putfield      #33                 // Field directory:Ljava/lang/String;
         5: return
      LineNumberTable:
        line 1105: 0
      LocalVariableTable:
        Start  Length  Slot  Name   Signature
            0       6     0  this   Lorg/scalatest/tools/ReporterElement;
            0       6     1   x$1   Ljava/lang/String;
    MethodParameters:
      Name                           Flags
      x$1                            final

  private java.lang.String classname();
    descriptor: ()Ljava/lang/String;
    flags: (0x0002) ACC_PRIVATE
    Code:
      stack=1, locals=1, args_size=1
         0: aload_0
         1: getfield      #36                 // Field classname:Ljava/lang/String;
         4: areturn
      LineNumberTable:
        line 1106: 0
      LocalVariableTable:
        Start  Length  Slot  Name   Signature
            0       5     0  this   Lorg/scalatest/tools/ReporterElement;

  private void classname_$eq(java.lang.String);
    descriptor: (Ljava/lang/String;)V
    flags: (0x0002) ACC_PRIVATE
    Code:
      stack=2, locals=2, args_size=2
         0: aload_0
         1: aload_1
         2: putfield      #36                 // Field classname:Ljava/lang/String;
         5: return
      LineNumberTable:
        line 1106: 0
      LocalVariableTable:
        Start  Length  Slot  Name   Signature
            0       6     0  this   Lorg/scalatest/tools/ReporterElement;
            0       6     1   x$1   Ljava/lang/String;
    MethodParameters:
      Name                           Flags
      x$1                            final

  private int numfiles();
    descriptor: ()I
    flags: (0x0002) ACC_PRIVATE
    Code:
      stack=1, locals=1, args_size=1
         0: aload_0
         1: getfield      #40                 // Field numfiles:I
         4: ireturn
      LineNumberTable:
        line 1107: 0
      LocalVariableTable:
        Start  Length  Slot  Name   Signature
            0       5     0  this   Lorg/scalatest/tools/ReporterElement;

  private void numfiles_$eq(int);
    descriptor: (I)V
    flags: (0x0002) ACC_PRIVATE
    Code:
      stack=2, locals=2, args_size=2
         0: aload_0
         1: iload_1
         2: putfield      #40                 // Field numfiles:I
         5: return
      LineNumberTable:
        line 1107: 0
      LocalVariableTable:
        Start  Length  Slot  Name   Signature
            0       6     0  this   Lorg/scalatest/tools/ReporterElement;
            0       6     1   x$1   I
    MethodParameters:
      Name                           Flags
      x$1                            final

  private java.lang.String css();
    descriptor: ()Ljava/lang/String;
    flags: (0x0002) ACC_PRIVATE
    Code:
      stack=1, locals=1, args_size=1
         0: aload_0
         1: getfield      #44                 // Field css:Ljava/lang/String;
         4: areturn
      LineNumberTable:
        line 1108: 0
      LocalVariableTable:
        Start  Length  Slot  Name   Signature
            0       5     0  this   Lorg/scalatest/tools/ReporterElement;

  private void css_$eq(java.lang.String);
    descriptor: (Ljava/lang/String;)V
    flags: (0x0002) ACC_PRIVATE
    Code:
      stack=2, locals=2, args_size=2
         0: aload_0
         1: aload_1
         2: putfield      #44                 // Field css:Ljava/lang/String;
         5: return
      LineNumberTable:
        line 1108: 0
      LocalVariableTable:
        Start  Length  Slot  Name   Signature
            0       6     0  this   Lorg/scalatest/tools/ReporterElement;
            0       6     1   x$1   Ljava/lang/String;
    MethodParameters:
      Name                           Flags
      x$1                            final

  public void setType(java.lang.String);
    descriptor: (Ljava/lang/String;)V
    flags: (0x0001) ACC_PUBLIC
    Code:
      stack=2, locals=2, args_size=2
         0: aload_0
         1: aload_1
         2: invokespecial #48                 // Method rtype_$eq:(Ljava/lang/String;)V
         5: return
      LineNumberTable:
        line 1110: 0
      LocalVariableTable:
        Start  Length  Slot  Name   Signature
            0       6     0  this   Lorg/scalatest/tools/ReporterElement;
            0       6     1 rtype   Ljava/lang/String;
    MethodParameters:
      Name                           Flags
      rtype                          final

  public void setConfig(java.lang.String);
    descriptor: (Ljava/lang/String;)V
    flags: (0x0001) ACC_PUBLIC
    Code:
      stack=2, locals=2, args_size=2
         0: aload_0
         1: aload_1
         2: invokespecial #51                 // Method config_$eq:(Ljava/lang/String;)V
         5: return
      LineNumberTable:
        line 1111: 0
      LocalVariableTable:
        Start  Length  Slot  Name   Signature
            0       6     0  this   Lorg/scalatest/tools/ReporterElement;
            0       6     1 config   Ljava/lang/String;
    MethodParameters:
      Name                           Flags
      config                         final

  public void setFilename(java.lang.String);
    descriptor: (Ljava/lang/String;)V
    flags: (0x0001) ACC_PUBLIC
    Code:
      stack=2, locals=2, args_size=2
         0: aload_0
         1: aload_1
         2: invokespecial #54                 // Method filename_$eq:(Ljava/lang/String;)V
         5: return
      LineNumberTable:
        line 1112: 0
      LocalVariableTable:
        Start  Length  Slot  Name   Signature
            0       6     0  this   Lorg/scalatest/tools/ReporterElement;
            0       6     1 filename   Ljava/lang/String;
    MethodParameters:
      Name                           Flags
      filename                       final

  public void setDirectory(java.lang.String);
    descriptor: (Ljava/lang/String;)V
    flags: (0x0001) ACC_PUBLIC
    Code:
      stack=2, locals=2, args_size=2
         0: aload_0
         1: aload_1
         2: invokespecial #57                 // Method directory_$eq:(Ljava/lang/String;)V
         5: return
      LineNumberTable:
        line 1113: 0
      LocalVariableTable:
        Start  Length  Slot  Name   Signature
            0       6     0  this   Lorg/scalatest/tools/ReporterElement;
            0       6     1 directory   Ljava/lang/String;
    MethodParameters:
      Name                           Flags
      directory                      final

  public void setClassName(java.lang.String);
    descriptor: (Ljava/lang/String;)V
    flags: (0x0001) ACC_PUBLIC
    Code:
      stack=2, locals=2, args_size=2
         0: aload_0
         1: aload_1
         2: invokespecial #60                 // Method classname_$eq:(Ljava/lang/String;)V
         5: return
      LineNumberTable:
        line 1114: 0
      LocalVariableTable:
        Start  Length  Slot  Name   Signature
            0       6     0  this   Lorg/scalatest/tools/ReporterElement;
            0       6     1 classname   Ljava/lang/String;
    MethodParameters:
      Name                           Flags
      classname                      final

  public void setNumfiles(int);
    descriptor: (I)V
    flags: (0x0001) ACC_PUBLIC
    Code:
      stack=2, locals=2, args_size=2
         0: aload_0
         1: iload_1
         2: invokespecial #63                 // Method numfiles_$eq:(I)V
         5: return
      LineNumberTable:
        line 1115: 0
      LocalVariableTable:
        Start  Length  Slot  Name   Signature
            0       6     0  this   Lorg/scalatest/tools/ReporterElement;
            0       6     1 numfiles   I
    MethodParameters:
      Name                           Flags
      numfiles                       final

  public void setCss(java.lang.String);
    descriptor: (Ljava/lang/String;)V
    flags: (0x0001) ACC_PUBLIC
    Code:
      stack=2, locals=2, args_size=2
         0: aload_0
         1: aload_1
         2: invokespecial #66                 // Method css_$eq:(Ljava/lang/String;)V
         5: return
      LineNumberTable:
        line 1116: 0
      LocalVariableTable:
        Start  Length  Slot  Name   Signature
            0       6     0  this   Lorg/scalatest/tools/ReporterElement;
            0       6     1   css   Ljava/lang/String;
    MethodParameters:
      Name                           Flags
      css                            final

  public java.lang.String getType();
    descriptor: ()Ljava/lang/String;
    flags: (0x0001) ACC_PUBLIC
    Code:
      stack=1, locals=1, args_size=1
         0: aload_0
         1: invokespecial #69                 // Method rtype:()Ljava/lang/String;
         4: areturn
      LineNumberTable:
        line 1118: 0
      LocalVariableTable:
        Start  Length  Slot  Name   Signature
            0       5     0  this   Lorg/scalatest/tools/ReporterElement;

  public java.lang.String getConfig();
    descriptor: ()Ljava/lang/String;
    flags: (0x0001) ACC_PUBLIC
    Code:
      stack=1, locals=1, args_size=1
         0: aload_0
         1: invokespecial #72                 // Method config:()Ljava/lang/String;
         4: areturn
      LineNumberTable:
        line 1119: 0
      LocalVariableTable:
        Start  Length  Slot  Name   Signature
            0       5     0  this   Lorg/scalatest/tools/ReporterElement;

  public java.lang.String getFilename();
    descriptor: ()Ljava/lang/String;
    flags: (0x0001) ACC_PUBLIC
    Code:
      stack=1, locals=1, args_size=1
         0: aload_0
         1: invokespecial #75                 // Method filename:()Ljava/lang/String;
         4: areturn
      LineNumberTable:
        line 1120: 0
      LocalVariableTable:
        Start  Length  Slot  Name   Signature
            0       5     0  this   Lorg/scalatest/tools/ReporterElement;

  public java.lang.String getDirectory();
    descriptor: ()Ljava/lang/String;
    flags: (0x0001) ACC_PUBLIC
    Code:
      stack=1, locals=1, args_size=1
         0: aload_0
         1: invokespecial #78                 // Method directory:()Ljava/lang/String;
         4: areturn
      LineNumberTable:
        line 1121: 0
      LocalVariableTable:
        Start  Length  Slot  Name   Signature
            0       5     0  this   Lorg/scalatest/tools/ReporterElement;

  public java.lang.String getClassName();
    descriptor: ()Ljava/lang/String;
    flags: (0x0001) ACC_PUBLIC
    Code:
      stack=1, locals=1, args_size=1
         0: aload_0
         1: invokespecial #81                 // Method classname:()Ljava/lang/String;
         4: areturn
      LineNumberTable:
        line 1122: 0
      LocalVariableTable:
        Start  Length  Slot  Name   Signature
            0       5     0  this   Lorg/scalatest/tools/ReporterElement;

  public int getNumfiles();
    descriptor: ()I
    flags: (0x0001) ACC_PUBLIC
    Code:
      stack=1, locals=1, args_size=1
         0: aload_0
         1: invokespecial #84                 // Method numfiles:()I
         4: ireturn
      LineNumberTable:
        line 1123: 0
      LocalVariableTable:
        Start  Length  Slot  Name   Signature
            0       5     0  this   Lorg/scalatest/tools/ReporterElement;

  public java.lang.String getCss();
    descriptor: ()Ljava/lang/String;
    flags: (0x0001) ACC_PUBLIC
    Code:
      stack=1, locals=1, args_size=1
         0: aload_0
         1: invokespecial #87                 // Method css:()Ljava/lang/String;
         4: areturn
      LineNumberTable:
        line 1124: 0
      LocalVariableTable:
        Start  Length  Slot  Name   Signature
            0       5     0  this   Lorg/scalatest/tools/ReporterElement;

  public org.scalatest.tools.ReporterElement();
    descriptor: ()V
    flags: (0x0001) ACC_PUBLIC
    Code:
      stack=2, locals=1, args_size=1
         0: aload_0
         1: invokespecial #91                 // Method java/lang/Object."<init>":()V
         4: aload_0
         5: aconst_null
         6: putfield      #20                 // Field rtype:Ljava/lang/String;
         9: aload_0
        10: aconst_null
        11: putfield      #27                 // Field config:Ljava/lang/String;
        14: aload_0
        15: aconst_null
        16: putfield      #30                 // Field filename:Ljava/lang/String;
        19: aload_0
        20: aconst_null
        21: putfield      #33                 // Field directory:Ljava/lang/String;
        24: aload_0
        25: aconst_null
        26: putfield      #36                 // Field classname:Ljava/lang/String;
        29: aload_0
        30: iconst_m1
        31: putfield      #40                 // Field numfiles:I
        34: aload_0
        35: aconst_null
        36: putfield      #44                 // Field css:Ljava/lang/String;
        39: return
      LineNumberTable:
        line 1137: 0
        line 1102: 4
        line 1103: 9
        line 1104: 14
        line 1105: 19
        line 1106: 24
        line 1107: 29
        line 1108: 34
        line 1101: 39
      LocalVariableTable:
        Start  Length  Slot  Name   Signature
            0      40     0  this   Lorg/scalatest/tools/ReporterElement;
}
SourceFile: "ScalaTestAntTask.scala"
RuntimeVisibleAnnotations:
  0: #6(#7=s#8)
    scala.reflect.ScalaSignature(
      bytes="\u0006\u0005\u0005]a\u0001B\u0013\'\t5BQ\u0001\u000e\u0001\u0005\u0002UBq\u0001\u000f\u0001A\u0002\u0013%\u0011\bC\u0004F\u0001\u0001\u0007I\u0011\u0002$\t\r1\u0003\u0001\u0015)\u0003;\u0011\u001di\u0005\u00011A\u0005\neBqA\u0014\u0001A\u0002\u0013%q\n\u0003\u0004R\u0001\u0001\u0006KA\u000f\u0005\b%\u0002\u0001\r\u0011\"\u0003:\u0011\u001d\u0019\u0006\u00011A\u0005\nQCaA\u0016\u0001!B\u0013Q\u0004bB,\u0001\u0001\u0004%I!\u000f\u0005\b1\u0002\u0001\r\u0011\"\u0003Z\u0011\u0019Y\u0006\u0001)Q\u0005u!9A\f\u0001a\u0001\n\u0013I\u0004bB/\u0001\u0001\u0004%IA\u0018\u0005\u0007A\u0002\u0001\u000b\u0015\u0002\u001e\t\u000f\u0005\u0004\u0001\u0019!C\u0005E\"9a\r\u0001a\u0001\n\u00139\u0007BB5\u0001A\u0003&1\rC\u0004k\u0001\u0001\u0007I\u0011B\u001d\t\u000f-\u0004\u0001\u0019!C\u0005Y\"1a\u000e\u0001Q!\niBQa\u001c\u0001\u0005\u0002ADQA\u001d\u0001\u0005\u0002MDQ!\u001e\u0001\u0005\u0002YDQ\u0001\u001f\u0001\u0005\u0002eDQa\u001f\u0001\u0005\u0002qDQA \u0001\u0005\u0002}Dq!a\u0001\u0001\t\u0003\t)\u0001\u0003\u0004\u0002\n\u0001!\t!\u000f\u0005\u0007\u0003\u0017\u0001A\u0011A\u001d\t\r\u00055\u0001\u0001\"\u0001:\u0011\u0019\ty\u0001\u0001C\u0001s!1\u0011\u0011\u0003\u0001\u0005\u0002eBa!a\u0005\u0001\t\u0003\u0011\u0007BBA\u000b\u0001\u0011\u0005\u0011HA\bSKB|\'\u000f^3s\u000b2,W.\u001a8u\u0015\t9\u0003&A\u0003u_>d7O\u0003\u0002*U\u0005I1oY1mCR,7\u000f\u001e\u0006\u0002W\u0005\u0019qN]4\u0004\u0001M\u0011\u0001A\f\t\u0003_Ij\u0011\u0001\r\u0006\u0002c\u0005)1oY1mC&\u00111\u0007\r\u0002\u0007\u0003:L(+\u001a4\u0002\rqJg.\u001b;?)\u00051\u0004CA\u001c\u0001\u001b\u00051\u0013!\u0002:usB,W#\u0001\u001e\u0011\u0005m\u0012eB\u0001\u001fA!\ti\u0004\'D\u0001?\u0015\tyD&\u0001\u0004=e>|GOP\u0005\u0003\u0003B\na\u0001\u0015:fI\u00164\u0017BA\"E\u0005\u0019\u0019FO]5oO*\u0011\u0011\tM\u0001\neRL\b/Z0%KF$\"a\u0012&\u0011\u0005=B\u0015BA%1\u0005\u0011)f.\u001b;\t\u000f-\u001b\u0011\u0011!a\u0001u\u0005\u0019\u0001\u0010J\u0019\u0002\rI$\u0018\u0010]3!\u0003\u0019\u0019wN\u001c4jO\u0006Q1m\u001c8gS\u001e|F%Z9\u0015\u0005\u001d\u0003\u0006bB&\u0007\u0003\u0003\u0005\rAO\u0001\bG>tg-[4!\u0003!1\u0017\u000e\\3oC6,\u0017\u0001\u00044jY\u0016t\u0017-\\3`I\u0015\fHCA$V\u0011\u001dY\u0015\"!AA\u0002i\n\u0011BZ5mK:\fW.\u001a\u0011\u0002\u0013\u0011L\'/Z2u_JL\u0018!\u00043je\u0016\u001cGo\u001c:z?\u0012*\u0017\u000f\u0006\u0002H5\"91\nDA\u0001\u0002\u0004Q\u0014A\u00033je\u0016\u001cGo\u001c:zA\u0005I1\r\\1tg:\fW.Z\u0001\u000eG2\f7o\u001d8b[\u0016|F%Z9\u0015\u0005\u001d{\u0006bB&\u0010\u0003\u0003\u0005\rAO\u0001\u000bG2\f7o\u001d8b[\u0016\u0004\u0013\u0001\u00038v[\u001aLG.Z:\u0016\u0003\r\u0004\"a\f3\n\u0005\u0015\u0004$aA%oi\u0006aa.^7gS2,7o\u0018\u0013fcR\u0011q\t\u001b\u0005\b\u0017J\t\t\u00111\u0001d\u0003%qW/\u001c4jY\u0016\u001c\b%A\u0002dgN\fqaY:t?\u0012*\u0017\u000f\u0006\u0002H[\"91*FA\u0001\u0002\u0004Q\u0014\u0001B2tg\u0002\nqa]3u)f\u0004X\r\u0006\u0002Hc\")\u0001h\u0006a\u0001u\u0005I1/\u001a;D_:4\u0017n\u001a\u000b\u0003\u000fRDQ!\u0014\rA\u0002i\n1b]3u\r&dWM\\1nKR\u0011qi\u001e\u0005\u0006%f\u0001\rAO\u0001\rg\u0016$H)\u001b:fGR|\'/\u001f\u000b\u0003\u000fjDQa\u0016\u000eA\u0002i\nAb]3u\u00072\f7o\u001d(b[\u0016$\"aR?\t\u000bq[\u0002\u0019\u0001\u001e\u0002\u0017M,GOT;nM&dWm\u001d\u000b\u0004\u000f\u0006\u0005\u0001\"B1\u001d\u0001\u0004\u0019\u0017AB:fi\u000e\u001b8\u000fF\u0002H\u0003\u000fAQA[\u000fA\u0002i\nqaZ3u)f\u0004X-A\u0005hKR\u001cuN\u001c4jO\u0006Yq-\u001a;GS2,g.Y7f\u000319W\r\u001e#je\u0016\u001cGo\u001c:z\u000319W\r^\"mCN\u001ch*Y7f\u0003-9W\r\u001e(v[\u001aLG.Z:\u0002\r\u001d,GoQ:t\u0001"
    )
  ScalaInlineInfo: length = 0x95 (unknown attribute)
   01 00 00 1D 00 58 00 59 00 00 0E 00 12 01 00 25
   00 18 01 00 0B 00 12 01 00 1C 00 18 01 00 11 00
   12 01 00 2D 00 18 01 00 0D 00 12 01 00 22 00 18
   01 00 0C 00 12 01 00 1F 00 18 01 00 4F 00 12 00
   00 46 00 12 00 00 55 00 12 00 00 4C 00 12 00 00
   49 00 12 00 00 52 00 26 00 00 43 00 12 00 00 0F
   00 26 01 00 29 00 2A 01 00 09 00 12 01 00 17 00
   18 01 00 3A 00 18 00 00 31 00 18 00 00 40 00 18
   00 00 37 00 18 00 00 34 00 18 00 00 3D 00 2A 00
   00 2E 00 18 00
  ScalaSig: length = 0x3 (unknown attribute)
   05 02 00
