Classfile /Users/mw/Projects/slang-braindump/.jar/jar11/assemble/slang-braindump/assemble/content/org/scalatest/tools/RunDoneListener.class
  Last modified May 29, 2022; size 849 bytes
  SHA-256 checksum 317b5a345ea0b74c7fc194df772115d928b7f0bddf8f928ca4284c0474cb2ed4
  Compiled from "RunDoneListener.scala"
public interface org.scalatest.tools.RunDoneListener
  minor version: 0
  major version: 52
  flags: (0x0601) ACC_PUBLIC, ACC_INTERFACE, ACC_ABSTRACT
  this_class: #2                          // org/scalatest/tools/RunDoneListener
  super_class: #4                         // java/lang/Object
  interfaces: 0, fields: 0, methods: 3, attributes: 4
Constant pool:
   #1 = Utf8               org/scalatest/tools/RunDoneListener
   #2 = Class              #1             // org/scalatest/tools/RunDoneListener
   #3 = Utf8               java/lang/Object
   #4 = Class              #3             // java/lang/Object
   #5 = Utf8               RunDoneListener.scala
   #6 = Utf8               Lscala/reflect/ScalaSignature;
   #7 = Utf8               bytes
   #8 = Utf8               \u0006\u0005a1\u0001b\u0001\u0003\u0011\u0002\u0007\u0005aA\u0003\u0005\u0006#\u0001!\ta\u0005\u0005\u0006/\u0001!\ta\u0005\u0002\u0010%VtGi\u001c8f\u0019&\u001cH/\u001a8fe*\u0011QAB\u0001\u0006i>|Gn\u001d\u0006\u0003\u000f!\t\u0011b]2bY\u0006$Xm\u001d;\u000b\u0003%\t1a\u001c:h\'\t\u00011\u0002\u0005\u0002\r\u001f5\tQBC\u0001\u000f\u0003\u0015\u00198-\u00197b\u0013\t\u0001RB\u0001\u0004B]f\u0014VMZ\u0001\u0007I%t\u0017\u000e\u001e\u0013\u0004\u0001Q\tA\u0003\u0005\u0002\r+%\u0011a#\u0004\u0002\u0005+:LG/\u0001\u0003e_:,\u0007
   #9 = Utf8               done$
  #10 = Utf8               (Lorg/scalatest/tools/RunDoneListener;)V
  #11 = Utf8               $this
  #12 = Utf8               done
  #13 = Utf8               ()V
  #14 = NameAndType        #12:#13        // done:()V
  #15 = InterfaceMethodref #2.#14         // org/scalatest/tools/RunDoneListener.done:()V
  #16 = Utf8               Lorg/scalatest/tools/RunDoneListener;
  #17 = Utf8               this
  #18 = Utf8               $init$
  #19 = Utf8               Code
  #20 = Utf8               LineNumberTable
  #21 = Utf8               LocalVariableTable
  #22 = Utf8               MethodParameters
  #23 = Utf8               SourceFile
  #24 = Utf8               RuntimeVisibleAnnotations
  #25 = Utf8               ScalaInlineInfo
  #26 = Utf8               ScalaSig
{
  public static void done$(org.scalatest.tools.RunDoneListener);
    descriptor: (Lorg/scalatest/tools/RunDoneListener;)V
    flags: (0x1009) ACC_PUBLIC, ACC_STATIC, ACC_SYNTHETIC
    Code:
      stack=1, locals=1, args_size=1
         0: aload_0
         1: invokespecial #15                 // InterfaceMethod done:()V
         4: return
      LineNumberTable:
        line 25: 0
      LocalVariableTable:
        Start  Length  Slot  Name   Signature
            0       5     0 $this   Lorg/scalatest/tools/RunDoneListener;
    MethodParameters:
      Name                           Flags
      $this                          final synthetic

  public default void done();
    descriptor: ()V
    flags: (0x0001) ACC_PUBLIC
    Code:
      stack=0, locals=1, args_size=1
         0: return
      LineNumberTable:
        line 25: 0
      LocalVariableTable:
        Start  Length  Slot  Name   Signature
            0       1     0  this   Lorg/scalatest/tools/RunDoneListener;

  public static void $init$(org.scalatest.tools.RunDoneListener);
    descriptor: (Lorg/scalatest/tools/RunDoneListener;)V
    flags: (0x0009) ACC_PUBLIC, ACC_STATIC
    Code:
      stack=0, locals=1, args_size=1
         0: return
      LineNumberTable:
        line 24: 0
      LocalVariableTable:
        Start  Length  Slot  Name   Signature
            0       1     0 $this   Lorg/scalatest/tools/RunDoneListener;
    MethodParameters:
      Name                           Flags
      $this                          final synthetic
}
SourceFile: "RunDoneListener.scala"
RuntimeVisibleAnnotations:
  0: #6(#7=s#8)
    scala.reflect.ScalaSignature(
      bytes="\u0006\u0005a1\u0001b\u0001\u0003\u0011\u0002\u0007\u0005aA\u0003\u0005\u0006#\u0001!\ta\u0005\u0005\u0006/\u0001!\ta\u0005\u0002\u0010%VtGi\u001c8f\u0019&\u001cH/\u001a8fe*\u0011QAB\u0001\u0006i>|Gn\u001d\u0006\u0003\u000f!\t\u0011b]2bY\u0006$Xm\u001d;\u000b\u0003%\t1a\u001c:h\'\t\u00011\u0002\u0005\u0002\r\u001f5\tQBC\u0001\u000f\u0003\u0015\u00198-\u00197b\u0013\t\u0001RB\u0001\u0004B]f\u0014VMZ\u0001\u0007I%t\u0017\u000e\u001e\u0013\u0004\u0001Q\tA\u0003\u0005\u0002\r+%\u0011a#\u0004\u0002\u0005+:LG/\u0001\u0003e_:,\u0007"
    )
  ScalaInlineInfo: length = 0x13 (unknown attribute)
   01 00 00 03 00 12 00 0A 01 00 0C 00 0D 00 00 09
   00 0A 01
  ScalaSig: length = 0x3 (unknown attribute)
   05 02 00
