Classfile /Users/mw/Projects/slang-braindump/.jar/jar11/assemble/slang-braindump/assemble/content/org/scalatest/tools/RunnerJFrame$ResettableStopper.class
  Last modified May 29, 2022; size 1357 bytes
  SHA-256 checksum b8d5d936b6e09e4079c91ccce5ff06b06e16a897befe58a6d938d2a819a26ad8
  Compiled from "RunnerJFrame.scala"
public class org.scalatest.tools.RunnerJFrame$ResettableStopper implements org.scalatest.Stopper
  minor version: 0
  major version: 52
  flags: (0x0021) ACC_PUBLIC, ACC_SUPER
  this_class: #2                          // org/scalatest/tools/RunnerJFrame$ResettableStopper
  super_class: #4                         // java/lang/Object
  interfaces: 1, fields: 2, methods: 7, attributes: 4
Constant pool:
   #1 = Utf8               org/scalatest/tools/RunnerJFrame$ResettableStopper
   #2 = Class              #1             // org/scalatest/tools/RunnerJFrame$ResettableStopper
   #3 = Utf8               java/lang/Object
   #4 = Class              #3             // java/lang/Object
   #5 = Utf8               org/scalatest/Stopper
   #6 = Class              #5             // org/scalatest/Stopper
   #7 = Utf8               RunnerJFrame.scala
   #8 = Utf8               org/scalatest/tools/RunnerJFrame
   #9 = Class              #8             // org/scalatest/tools/RunnerJFrame
  #10 = Utf8               ResettableStopper
  #11 = Utf8               stopWasRequested
  #12 = Utf8               Z
  #13 = Utf8               $outer
  #14 = Utf8               Lorg/scalatest/tools/RunnerJFrame;
  #15 = Utf8               ()Z
  #16 = NameAndType        #11:#12        // stopWasRequested:Z
  #17 = Fieldref           #2.#16         // org/scalatest/tools/RunnerJFrame$ResettableStopper.stopWasRequested:Z
  #18 = Utf8               this
  #19 = Utf8               Lorg/scalatest/tools/RunnerJFrame$ResettableStopper;
  #20 = Utf8               stopWasRequested_$eq
  #21 = Utf8               (Z)V
  #22 = Utf8               x$1
  #23 = Utf8               stopRequested
  #24 = NameAndType        #11:#15        // stopWasRequested:()Z
  #25 = Methodref          #2.#24         // org/scalatest/tools/RunnerJFrame$ResettableStopper.stopWasRequested:()Z
  #26 = Utf8               requestStop
  #27 = Utf8               ()V
  #28 = NameAndType        #20:#21        // stopWasRequested_$eq:(Z)V
  #29 = Methodref          #2.#28         // org/scalatest/tools/RunnerJFrame$ResettableStopper.stopWasRequested_$eq:(Z)V
  #30 = Utf8               reset
  #31 = Utf8               org$scalatest$tools$RunnerJFrame$ResettableStopper$$$outer
  #32 = Utf8               ()Lorg/scalatest/tools/RunnerJFrame;
  #33 = NameAndType        #13:#14        // $outer:Lorg/scalatest/tools/RunnerJFrame;
  #34 = Fieldref           #2.#33         // org/scalatest/tools/RunnerJFrame$ResettableStopper.$outer:Lorg/scalatest/tools/RunnerJFrame;
  #35 = Utf8               <init>
  #36 = Utf8               (Lorg/scalatest/tools/RunnerJFrame;)V
  #37 = NameAndType        #35:#27        // "<init>":()V
  #38 = Methodref          #4.#37         // java/lang/Object."<init>":()V
  #39 = Utf8               Code
  #40 = Utf8               LineNumberTable
  #41 = Utf8               LocalVariableTable
  #42 = Utf8               MethodParameters
  #43 = Utf8               StackMapTable
  #44 = Utf8               InnerClasses
  #45 = Utf8               SourceFile
  #46 = Utf8               ScalaInlineInfo
  #47 = Utf8               Scala
{
  private volatile boolean stopWasRequested;
    descriptor: Z
    flags: (0x0042) ACC_PRIVATE, ACC_VOLATILE

  public final org.scalatest.tools.RunnerJFrame $outer;
    descriptor: Lorg/scalatest/tools/RunnerJFrame;
    flags: (0x1011) ACC_PUBLIC, ACC_FINAL, ACC_SYNTHETIC

  private boolean stopWasRequested();
    descriptor: ()Z
    flags: (0x0002) ACC_PRIVATE
    Code:
      stack=1, locals=1, args_size=1
         0: aload_0
         1: getfield      #17                 // Field stopWasRequested:Z
         4: ireturn
      LineNumberTable:
        line 158: 0
      LocalVariableTable:
        Start  Length  Slot  Name   Signature
            0       5     0  this   Lorg/scalatest/tools/RunnerJFrame$ResettableStopper;

  private void stopWasRequested_$eq(boolean);
    descriptor: (Z)V
    flags: (0x0002) ACC_PRIVATE
    Code:
      stack=2, locals=2, args_size=2
         0: aload_0
         1: iload_1
         2: putfield      #17                 // Field stopWasRequested:Z
         5: return
      LineNumberTable:
        line 158: 0
      LocalVariableTable:
        Start  Length  Slot  Name   Signature
            0       6     0  this   Lorg/scalatest/tools/RunnerJFrame$ResettableStopper;
            0       6     1   x$1   Z
    MethodParameters:
      Name                           Flags
      x$1                            final

  public boolean stopRequested();
    descriptor: ()Z
    flags: (0x0001) ACC_PUBLIC
    Code:
      stack=1, locals=1, args_size=1
         0: aload_0
         1: invokespecial #25                 // Method stopWasRequested:()Z
         4: ireturn
      LineNumberTable:
        line 159: 0
      LocalVariableTable:
        Start  Length  Slot  Name   Signature
            0       5     0  this   Lorg/scalatest/tools/RunnerJFrame$ResettableStopper;

  public void requestStop();
    descriptor: ()V
    flags: (0x0001) ACC_PUBLIC
    Code:
      stack=2, locals=1, args_size=1
         0: aload_0
         1: iconst_1
         2: invokespecial #29                 // Method stopWasRequested_$eq:(Z)V
         5: return
      LineNumberTable:
        line 161: 0
      LocalVariableTable:
        Start  Length  Slot  Name   Signature
            0       6     0  this   Lorg/scalatest/tools/RunnerJFrame$ResettableStopper;

  public void reset();
    descriptor: ()V
    flags: (0x0001) ACC_PUBLIC
    Code:
      stack=2, locals=1, args_size=1
         0: aload_0
         1: iconst_0
         2: invokespecial #29                 // Method stopWasRequested_$eq:(Z)V
         5: return
      LineNumberTable:
        line 164: 0
      LocalVariableTable:
        Start  Length  Slot  Name   Signature
            0       6     0  this   Lorg/scalatest/tools/RunnerJFrame$ResettableStopper;

  public org.scalatest.tools.RunnerJFrame org$scalatest$tools$RunnerJFrame$ResettableStopper$$$outer();
    descriptor: ()Lorg/scalatest/tools/RunnerJFrame;
    flags: (0x1001) ACC_PUBLIC, ACC_SYNTHETIC
    Code:
      stack=1, locals=1, args_size=1
         0: aload_0
         1: getfield      #34                 // Field $outer:Lorg/scalatest/tools/RunnerJFrame;
         4: areturn
      LineNumberTable:
        line 157: 0
      LocalVariableTable:
        Start  Length  Slot  Name   Signature
            0       5     0  this   Lorg/scalatest/tools/RunnerJFrame$ResettableStopper;

  public org.scalatest.tools.RunnerJFrame$ResettableStopper(org.scalatest.tools.RunnerJFrame);
    descriptor: (Lorg/scalatest/tools/RunnerJFrame;)V
    flags: (0x0001) ACC_PUBLIC
    Code:
      stack=2, locals=2, args_size=2
         0: aload_1
         1: ifnonnull     6
         4: aconst_null
         5: athrow
         6: aload_0
         7: aload_1
         8: putfield      #34                 // Field $outer:Lorg/scalatest/tools/RunnerJFrame;
        11: aload_0
        12: invokespecial #38                 // Method java/lang/Object."<init>":()V
        15: aload_0
        16: iconst_0
        17: putfield      #17                 // Field stopWasRequested:Z
        20: return
      StackMapTable: number_of_entries = 1
        frame_type = 6 /* same */
      LineNumberTable:
        line 157: 0
        line 158: 15
        line 157: 20
      LocalVariableTable:
        Start  Length  Slot  Name   Signature
            0      21     0  this   Lorg/scalatest/tools/RunnerJFrame$ResettableStopper;
            0      21     1 $outer   Lorg/scalatest/tools/RunnerJFrame;
    MethodParameters:
      Name                           Flags
      $outer                         final synthetic
}
InnerClasses:
  public #10= #2 of #9;                   // ResettableStopper=class org/scalatest/tools/RunnerJFrame$ResettableStopper of class org/scalatest/tools/RunnerJFrame
SourceFile: "RunnerJFrame.scala"
  ScalaInlineInfo: length = 0x27 (unknown attribute)
   01 00 00 07 00 23 00 24 00 00 1F 00 20 00 00 1A
   00 1B 00 00 1E 00 1B 00 00 17 00 0F 00 00 0B 00
   0F 01 00 14 00 15 01
  Scala: length = 0x0 (unknown attribute)

