Classfile /Users/mw/Projects/slang-braindump/.jar/jar11/assemble/slang-braindump/assemble/content/org/scalatest/tools/RunnerJFrame$$anon$9.class
  Last modified May 29, 2022; size 1958 bytes
  SHA-256 checksum 40b57c688ad6f7d7e8b6bbb015621e4b3dbd8d355881d6bbd3cd9afd11c62be9
  Compiled from "RunnerJFrame.scala"
public final class org.scalatest.tools.RunnerJFrame$$anon$9 extends javax.swing.AbstractAction
  minor version: 0
  major version: 52
  flags: (0x0031) ACC_PUBLIC, ACC_FINAL, ACC_SUPER
  this_class: #2                          // org/scalatest/tools/RunnerJFrame$$anon$9
  super_class: #4                         // javax/swing/AbstractAction
  interfaces: 0, fields: 1, methods: 2, attributes: 5
Constant pool:
   #1 = Utf8               org/scalatest/tools/RunnerJFrame$$anon$9
   #2 = Class              #1             // org/scalatest/tools/RunnerJFrame$$anon$9
   #3 = Utf8               javax/swing/AbstractAction
   #4 = Class              #3             // javax/swing/AbstractAction
   #5 = Utf8               RunnerJFrame.scala
   #6 = Utf8               org/scalatest/tools/RunnerJFrame
   #7 = Class              #6             // org/scalatest/tools/RunnerJFrame
   #8 = Utf8               initializeOptionsMap
   #9 = Utf8               ()Lscala/collection/immutable/Map;
  #10 = NameAndType        #8:#9          // initializeOptionsMap:()Lscala/collection/immutable/Map;
  #11 = Utf8               $outer
  #12 = Utf8               Lorg/scalatest/tools/RunnerJFrame;
  #13 = Utf8               actionPerformed
  #14 = Utf8               (Ljava/awt/event/ActionEvent;)V
  #15 = Utf8               ae
  #16 = Utf8               java/awt/event/ActionEvent
  #17 = Class              #16            // java/awt/event/ActionEvent
  #18 = Utf8               getSource
  #19 = Utf8               ()Ljava/lang/Object;
  #20 = NameAndType        #18:#19        // getSource:()Ljava/lang/Object;
  #21 = Methodref          #17.#20        // java/awt/event/ActionEvent.getSource:()Ljava/lang/Object;
  #22 = Utf8               javax/swing/JCheckBoxMenuItem
  #23 = Class              #22            // javax/swing/JCheckBoxMenuItem
  #24 = Utf8               option
  #25 = String             #24            // option
  #26 = Utf8               getValue
  #27 = Utf8               (Ljava/lang/String;)Ljava/lang/Object;
  #28 = NameAndType        #26:#27        // getValue:(Ljava/lang/String;)Ljava/lang/Object;
  #29 = Methodref          #2.#28         // org/scalatest/tools/RunnerJFrame$$anon$9.getValue:(Ljava/lang/String;)Ljava/lang/Object;
  #30 = Utf8               org/scalatest/tools/EventToPresent
  #31 = Class              #30            // org/scalatest/tools/EventToPresent
  #32 = NameAndType        #11:#12        // $outer:Lorg/scalatest/tools/RunnerJFrame;
  #33 = Fieldref           #2.#32         // org/scalatest/tools/RunnerJFrame$$anon$9.$outer:Lorg/scalatest/tools/RunnerJFrame;
  #34 = Utf8               org$scalatest$tools$RunnerJFrame$$viewOptions
  #35 = Utf8               ()Lscala/collection/immutable/Set;
  #36 = NameAndType        #34:#35        // org$scalatest$tools$RunnerJFrame$$viewOptions:()Lscala/collection/immutable/Set;
  #37 = Methodref          #7.#36         // org/scalatest/tools/RunnerJFrame.org$scalatest$tools$RunnerJFrame$$viewOptions:()Lscala/collection/immutable/Set;
  #38 = Utf8               scala/collection/immutable/Set
  #39 = Class              #38            // scala/collection/immutable/Set
  #40 = Utf8               contains
  #41 = Utf8               (Ljava/lang/Object;)Z
  #42 = NameAndType        #40:#41        // contains:(Ljava/lang/Object;)Z
  #43 = InterfaceMethodref #39.#42        // scala/collection/immutable/Set.contains:(Ljava/lang/Object;)Z
  #44 = Utf8               $minus
  #45 = Utf8               (Ljava/lang/Object;)Lscala/collection/immutable/SetOps;
  #46 = NameAndType        #44:#45        // $minus:(Ljava/lang/Object;)Lscala/collection/immutable/SetOps;
  #47 = InterfaceMethodref #39.#46        // scala/collection/immutable/Set.$minus:(Ljava/lang/Object;)Lscala/collection/immutable/SetOps;
  #48 = Utf8               org$scalatest$tools$RunnerJFrame$$viewOptions_$eq
  #49 = Utf8               (Lscala/collection/immutable/Set;)V
  #50 = NameAndType        #48:#49        // org$scalatest$tools$RunnerJFrame$$viewOptions_$eq:(Lscala/collection/immutable/Set;)V
  #51 = Methodref          #7.#50         // org/scalatest/tools/RunnerJFrame.org$scalatest$tools$RunnerJFrame$$viewOptions_$eq:(Lscala/collection/immutable/Set;)V
  #52 = Utf8               $plus
  #53 = NameAndType        #52:#45        // $plus:(Ljava/lang/Object;)Lscala/collection/immutable/SetOps;
  #54 = InterfaceMethodref #39.#53        // scala/collection/immutable/Set.$plus:(Ljava/lang/Object;)Lscala/collection/immutable/SetOps;
  #55 = Utf8               setState
  #56 = Utf8               (Z)V
  #57 = NameAndType        #55:#56        // setState:(Z)V
  #58 = Methodref          #23.#57        // javax/swing/JCheckBoxMenuItem.setState:(Z)V
  #59 = Utf8               org$scalatest$tools$RunnerJFrame$$refreshEventsJList
  #60 = Utf8               ()V
  #61 = NameAndType        #59:#60        // org$scalatest$tools$RunnerJFrame$$refreshEventsJList:()V
  #62 = Methodref          #7.#61         // org/scalatest/tools/RunnerJFrame.org$scalatest$tools$RunnerJFrame$$refreshEventsJList:()V
  #63 = Utf8               checkBox
  #64 = Utf8               Ljavax/swing/JCheckBoxMenuItem;
  #65 = Utf8               Lorg/scalatest/tools/EventToPresent;
  #66 = Utf8               checked
  #67 = Utf8               Z
  #68 = Utf8               this
  #69 = Utf8               Lorg/scalatest/tools/RunnerJFrame$$anon$9;
  #70 = Utf8               Ljava/awt/event/ActionEvent;
  #71 = Utf8               <init>
  #72 = Utf8               (Lorg/scalatest/tools/RunnerJFrame;Ljava/lang/String;)V
  #73 = Utf8               menuItemText$1
  #74 = Utf8               (Ljava/lang/String;)V
  #75 = NameAndType        #71:#74        // "<init>":(Ljava/lang/String;)V
  #76 = Methodref          #4.#75         // javax/swing/AbstractAction."<init>":(Ljava/lang/String;)V
  #77 = Utf8               Ljava/lang/String;
  #78 = Utf8               Code
  #79 = Utf8               StackMapTable
  #80 = Utf8               LineNumberTable
  #81 = Utf8               LocalVariableTable
  #82 = Utf8               MethodParameters
  #83 = Utf8               InnerClasses
  #84 = Utf8               EnclosingMethod
  #85 = Utf8               SourceFile
  #86 = Utf8               ScalaInlineInfo
  #87 = Utf8               Scala
{
  private final org.scalatest.tools.RunnerJFrame $outer;
    descriptor: Lorg/scalatest/tools/RunnerJFrame;
    flags: (0x1012) ACC_PRIVATE, ACC_FINAL, ACC_SYNTHETIC

  public void actionPerformed(java.awt.event.ActionEvent);
    descriptor: (Ljava/awt/event/ActionEvent;)V
    flags: (0x0001) ACC_PUBLIC
    Code:
      stack=3, locals=5, args_size=2
         0: aload_1
         1: invokevirtual #21                 // Method java/awt/event/ActionEvent.getSource:()Ljava/lang/Object;
         4: checkcast     #23                 // class javax/swing/JCheckBoxMenuItem
         7: astore_2
         8: aload_0
         9: ldc           #25                 // String option
        11: invokevirtual #29                 // Method getValue:(Ljava/lang/String;)Ljava/lang/Object;
        14: checkcast     #31                 // class org/scalatest/tools/EventToPresent
        17: astore_3
        18: aload_0
        19: getfield      #33                 // Field $outer:Lorg/scalatest/tools/RunnerJFrame;
        22: invokevirtual #37                 // Method org/scalatest/tools/RunnerJFrame.org$scalatest$tools$RunnerJFrame$$viewOptions:()Lscala/collection/immutable/Set;
        25: aload_3
        26: invokeinterface #43,  2           // InterfaceMethod scala/collection/immutable/Set.contains:(Ljava/lang/Object;)Z
        31: ifeq          60
        34: aload_0
        35: getfield      #33                 // Field $outer:Lorg/scalatest/tools/RunnerJFrame;
        38: aload_0
        39: getfield      #33                 // Field $outer:Lorg/scalatest/tools/RunnerJFrame;
        42: invokevirtual #37                 // Method org/scalatest/tools/RunnerJFrame.org$scalatest$tools$RunnerJFrame$$viewOptions:()Lscala/collection/immutable/Set;
        45: aload_3
        46: invokeinterface #47,  2           // InterfaceMethod scala/collection/immutable/Set.$minus:(Ljava/lang/Object;)Lscala/collection/immutable/SetOps;
        51: checkcast     #39                 // class scala/collection/immutable/Set
        54: invokevirtual #51                 // Method org/scalatest/tools/RunnerJFrame.org$scalatest$tools$RunnerJFrame$$viewOptions_$eq:(Lscala/collection/immutable/Set;)V
        57: goto          83
        60: aload_0
        61: getfield      #33                 // Field $outer:Lorg/scalatest/tools/RunnerJFrame;
        64: aload_0
        65: getfield      #33                 // Field $outer:Lorg/scalatest/tools/RunnerJFrame;
        68: invokevirtual #37                 // Method org/scalatest/tools/RunnerJFrame.org$scalatest$tools$RunnerJFrame$$viewOptions:()Lscala/collection/immutable/Set;
        71: aload_3
        72: invokeinterface #54,  2           // InterfaceMethod scala/collection/immutable/Set.$plus:(Ljava/lang/Object;)Lscala/collection/immutable/SetOps;
        77: checkcast     #39                 // class scala/collection/immutable/Set
        80: invokevirtual #51                 // Method org/scalatest/tools/RunnerJFrame.org$scalatest$tools$RunnerJFrame$$viewOptions_$eq:(Lscala/collection/immutable/Set;)V
        83: aload_0
        84: getfield      #33                 // Field $outer:Lorg/scalatest/tools/RunnerJFrame;
        87: invokevirtual #37                 // Method org/scalatest/tools/RunnerJFrame.org$scalatest$tools$RunnerJFrame$$viewOptions:()Lscala/collection/immutable/Set;
        90: aload_3
        91: invokeinterface #43,  2           // InterfaceMethod scala/collection/immutable/Set.contains:(Ljava/lang/Object;)Z
        96: istore        4
        98: aload_2
        99: iload         4
       101: invokevirtual #58                 // Method javax/swing/JCheckBoxMenuItem.setState:(Z)V
       104: aload_0
       105: getfield      #33                 // Field $outer:Lorg/scalatest/tools/RunnerJFrame;
       108: invokevirtual #62                 // Method org/scalatest/tools/RunnerJFrame.org$scalatest$tools$RunnerJFrame$$refreshEventsJList:()V
       111: return
      StackMapTable: number_of_entries = 2
        frame_type = 253 /* append */
          offset_delta = 60
          locals = [ class javax/swing/JCheckBoxMenuItem, class org/scalatest/tools/EventToPresent ]
        frame_type = 22 /* same */
      LineNumberTable:
        line 751: 0
        line 752: 8
        line 754: 18
        line 755: 34
        line 757: 60
        line 759: 83
        line 760: 98
        line 764: 104
      LocalVariableTable:
        Start  Length  Slot  Name   Signature
            8     103     2 checkBox   Ljavax/swing/JCheckBoxMenuItem;
           18      93     3 option   Lorg/scalatest/tools/EventToPresent;
           98      13     4 checked   Z
            0     112     0  this   Lorg/scalatest/tools/RunnerJFrame$$anon$9;
            0     112     1    ae   Ljava/awt/event/ActionEvent;
    MethodParameters:
      Name                           Flags
      ae                             final

  public org.scalatest.tools.RunnerJFrame$$anon$9(org.scalatest.tools.RunnerJFrame, java.lang.String);
    descriptor: (Lorg/scalatest/tools/RunnerJFrame;Ljava/lang/String;)V
    flags: (0x0001) ACC_PUBLIC
    Code:
      stack=2, locals=3, args_size=3
         0: aload_1
         1: ifnonnull     6
         4: aconst_null
         5: athrow
         6: aload_0
         7: aload_1
         8: putfield      #33                 // Field $outer:Lorg/scalatest/tools/RunnerJFrame;
        11: aload_0
        12: aload_2
        13: invokespecial #76                 // Method javax/swing/AbstractAction."<init>":(Ljava/lang/String;)V
        16: return
      StackMapTable: number_of_entries = 1
        frame_type = 6 /* same */
      LineNumberTable:
        line 748: 0
      LocalVariableTable:
        Start  Length  Slot  Name   Signature
            0      17     0  this   Lorg/scalatest/tools/RunnerJFrame$$anon$9;
            0      17     1 $outer   Lorg/scalatest/tools/RunnerJFrame;
            0      17     2 menuItemText$1   Ljava/lang/String;
    MethodParameters:
      Name                           Flags
      $outer                         final synthetic
      menuItemText$1                 final
}
InnerClasses:
  public final #2;                        // class org/scalatest/tools/RunnerJFrame$$anon$9
EnclosingMethod: #7.#10                 // org.scalatest.tools.RunnerJFrame.initializeOptionsMap
SourceFile: "RunnerJFrame.scala"
  ScalaInlineInfo: length = 0xE (unknown attribute)
   01 01 00 02 00 47 00 48 01 00 0D 00 0E 01
  Scala: length = 0x0 (unknown attribute)

