Classfile /Users/mw/Projects/slang-braindump/.jar/jar11/assemble/slang-braindump/assemble/content/org/scalatest/tools/Runner$PassFailReporter.class
  Last modified May 29, 2022; size 1925 bytes
  SHA-256 checksum 9f50929f303f7227c2fe27785095d7e605f51ef73b97c3163786aff5982a7e33
  Compiled from "Runner.scala"
public class org.scalatest.tools.Runner$PassFailReporter implements org.scalatest.Reporter
  minor version: 0
  major version: 52
  flags: (0x0021) ACC_PUBLIC, ACC_SUPER
  this_class: #2                          // org/scalatest/tools/Runner$PassFailReporter
  super_class: #4                         // java/lang/Object
  interfaces: 1, fields: 2, methods: 6, attributes: 4
Constant pool:
   #1 = Utf8               org/scalatest/tools/Runner$PassFailReporter
   #2 = Class              #1             // org/scalatest/tools/Runner$PassFailReporter
   #3 = Utf8               java/lang/Object
   #4 = Class              #3             // java/lang/Object
   #5 = Utf8               org/scalatest/Reporter
   #6 = Class              #5             // org/scalatest/Reporter
   #7 = Utf8               Runner.scala
   #8 = Utf8               org/scalatest/tools/Runner
   #9 = Class              #8             // org/scalatest/tools/Runner
  #10 = Utf8               PassFailReporter
  #11 = Utf8               failedAbortedOrStopped
  #12 = Utf8               Z
  #13 = Utf8               runDoneSemaphore
  #14 = Utf8               Ljava/util/concurrent/Semaphore;
  #15 = Utf8               ()Z
  #16 = NameAndType        #11:#12        // failedAbortedOrStopped:Z
  #17 = Fieldref           #2.#16         // org/scalatest/tools/Runner$PassFailReporter.failedAbortedOrStopped:Z
  #18 = Utf8               this
  #19 = Utf8               Lorg/scalatest/tools/Runner$PassFailReporter;
  #20 = Utf8               failedAbortedOrStopped_$eq
  #21 = Utf8               (Z)V
  #22 = Utf8               x$1
  #23 = Utf8               ()Ljava/util/concurrent/Semaphore;
  #24 = NameAndType        #13:#14        // runDoneSemaphore:Ljava/util/concurrent/Semaphore;
  #25 = Fieldref           #2.#24         // org/scalatest/tools/Runner$PassFailReporter.runDoneSemaphore:Ljava/util/concurrent/Semaphore;
  #26 = Utf8               apply
  #27 = Utf8               (Lorg/scalatest/events/Event;)V
  #28 = Utf8               event
  #29 = Utf8               org/scalatest/events/TestFailed
  #30 = Class              #29            // org/scalatest/events/TestFailed
  #31 = NameAndType        #20:#21        // failedAbortedOrStopped_$eq:(Z)V
  #32 = Methodref          #2.#31         // org/scalatest/tools/Runner$PassFailReporter.failedAbortedOrStopped_$eq:(Z)V
  #33 = Utf8               scala/runtime/BoxedUnit
  #34 = Class              #33            // scala/runtime/BoxedUnit
  #35 = Utf8               UNIT
  #36 = Utf8               Lscala/runtime/BoxedUnit;
  #37 = NameAndType        #35:#36        // UNIT:Lscala/runtime/BoxedUnit;
  #38 = Fieldref           #34.#37        // scala/runtime/BoxedUnit.UNIT:Lscala/runtime/BoxedUnit;
  #39 = Utf8               org/scalatest/events/RunAborted
  #40 = Class              #39            // org/scalatest/events/RunAborted
  #41 = NameAndType        #13:#23        // runDoneSemaphore:()Ljava/util/concurrent/Semaphore;
  #42 = Methodref          #2.#41         // org/scalatest/tools/Runner$PassFailReporter.runDoneSemaphore:()Ljava/util/concurrent/Semaphore;
  #43 = Utf8               java/util/concurrent/Semaphore
  #44 = Class              #43            // java/util/concurrent/Semaphore
  #45 = Utf8               release
  #46 = Utf8               ()V
  #47 = NameAndType        #45:#46        // release:()V
  #48 = Methodref          #44.#47        // java/util/concurrent/Semaphore.release:()V
  #49 = Utf8               org/scalatest/events/SuiteAborted
  #50 = Class              #49            // org/scalatest/events/SuiteAborted
  #51 = Utf8               org/scalatest/events/RunStopped
  #52 = Class              #51            // org/scalatest/events/RunStopped
  #53 = Utf8               org/scalatest/events/RunCompleted
  #54 = Class              #53            // org/scalatest/events/RunCompleted
  #55 = Utf8               Lorg/scalatest/events/Event;
  #56 = Utf8               org/scalatest/events/Event
  #57 = Class              #56            // org/scalatest/events/Event
  #58 = Utf8               allTestsPassed
  #59 = Utf8               acquire
  #60 = NameAndType        #59:#46        // acquire:()V
  #61 = Methodref          #44.#60        // java/util/concurrent/Semaphore.acquire:()V
  #62 = NameAndType        #11:#15        // failedAbortedOrStopped:()Z
  #63 = Methodref          #2.#62         // org/scalatest/tools/Runner$PassFailReporter.failedAbortedOrStopped:()Z
  #64 = Utf8               <init>
  #65 = NameAndType        #64:#46        // "<init>":()V
  #66 = Methodref          #4.#65         // java/lang/Object."<init>":()V
  #67 = Utf8               (I)V
  #68 = NameAndType        #64:#67        // "<init>":(I)V
  #69 = Methodref          #44.#68        // java/util/concurrent/Semaphore."<init>":(I)V
  #70 = Utf8               Code
  #71 = Utf8               LineNumberTable
  #72 = Utf8               LocalVariableTable
  #73 = Utf8               MethodParameters
  #74 = Utf8               StackMapTable
  #75 = Utf8               InnerClasses
  #76 = Utf8               SourceFile
  #77 = Utf8               ScalaInlineInfo
  #78 = Utf8               Scala
{
  private volatile boolean failedAbortedOrStopped;
    descriptor: Z
    flags: (0x0042) ACC_PRIVATE, ACC_VOLATILE

  private final java.util.concurrent.Semaphore runDoneSemaphore;
    descriptor: Ljava/util/concurrent/Semaphore;
    flags: (0x0012) ACC_PRIVATE, ACC_FINAL

  private boolean failedAbortedOrStopped();
    descriptor: ()Z
    flags: (0x0002) ACC_PRIVATE
    Code:
      stack=1, locals=1, args_size=1
         0: aload_0
         1: getfield      #17                 // Field failedAbortedOrStopped:Z
         4: ireturn
      LineNumberTable:
        line 724: 0
      LocalVariableTable:
        Start  Length  Slot  Name   Signature
            0       5     0  this   Lorg/scalatest/tools/Runner$PassFailReporter;

  private void failedAbortedOrStopped_$eq(boolean);
    descriptor: (Z)V
    flags: (0x0002) ACC_PRIVATE
    Code:
      stack=2, locals=2, args_size=2
         0: aload_0
         1: iload_1
         2: putfield      #17                 // Field failedAbortedOrStopped:Z
         5: return
      LineNumberTable:
        line 724: 0
      LocalVariableTable:
        Start  Length  Slot  Name   Signature
            0       6     0  this   Lorg/scalatest/tools/Runner$PassFailReporter;
            0       6     1   x$1   Z
    MethodParameters:
      Name                           Flags
      x$1                            final

  private java.util.concurrent.Semaphore runDoneSemaphore();
    descriptor: ()Ljava/util/concurrent/Semaphore;
    flags: (0x0002) ACC_PRIVATE
    Code:
      stack=1, locals=1, args_size=1
         0: aload_0
         1: getfield      #25                 // Field runDoneSemaphore:Ljava/util/concurrent/Semaphore;
         4: areturn
      LineNumberTable:
        line 725: 0
      LocalVariableTable:
        Start  Length  Slot  Name   Signature
            0       5     0  this   Lorg/scalatest/tools/Runner$PassFailReporter;

  public void apply(org.scalatest.events.Event);
    descriptor: (Lorg/scalatest/events/Event;)V
    flags: (0x0001) ACC_PUBLIC
    Code:
      stack=2, locals=4, args_size=2
         0: aload_1
         1: astore_3
         2: aload_3
         3: instanceof    #30                 // class org/scalatest/events/TestFailed
         6: ifeq          21
         9: aload_0
        10: iconst_1
        11: invokespecial #32                 // Method failedAbortedOrStopped_$eq:(Z)V
        14: getstatic     #38                 // Field scala/runtime/BoxedUnit.UNIT:Lscala/runtime/BoxedUnit;
        17: astore_2
        18: goto          135
        21: goto          24
        24: aload_3
        25: instanceof    #40                 // class org/scalatest/events/RunAborted
        28: ifeq          50
        31: aload_0
        32: iconst_1
        33: invokespecial #32                 // Method failedAbortedOrStopped_$eq:(Z)V
        36: aload_0
        37: invokespecial #42                 // Method runDoneSemaphore:()Ljava/util/concurrent/Semaphore;
        40: invokevirtual #48                 // Method java/util/concurrent/Semaphore.release:()V
        43: getstatic     #38                 // Field scala/runtime/BoxedUnit.UNIT:Lscala/runtime/BoxedUnit;
        46: astore_2
        47: goto          135
        50: goto          53
        53: aload_3
        54: instanceof    #50                 // class org/scalatest/events/SuiteAborted
        57: ifeq          72
        60: aload_0
        61: iconst_1
        62: invokespecial #32                 // Method failedAbortedOrStopped_$eq:(Z)V
        65: getstatic     #38                 // Field scala/runtime/BoxedUnit.UNIT:Lscala/runtime/BoxedUnit;
        68: astore_2
        69: goto          135
        72: goto          75
        75: aload_3
        76: instanceof    #52                 // class org/scalatest/events/RunStopped
        79: ifeq          101
        82: aload_0
        83: iconst_1
        84: invokespecial #32                 // Method failedAbortedOrStopped_$eq:(Z)V
        87: aload_0
        88: invokespecial #42                 // Method runDoneSemaphore:()Ljava/util/concurrent/Semaphore;
        91: invokevirtual #48                 // Method java/util/concurrent/Semaphore.release:()V
        94: getstatic     #38                 // Field scala/runtime/BoxedUnit.UNIT:Lscala/runtime/BoxedUnit;
        97: astore_2
        98: goto          135
       101: goto          104
       104: aload_3
       105: instanceof    #54                 // class org/scalatest/events/RunCompleted
       108: ifeq          125
       111: aload_0
       112: invokespecial #42                 // Method runDoneSemaphore:()Ljava/util/concurrent/Semaphore;
       115: invokevirtual #48                 // Method java/util/concurrent/Semaphore.release:()V
       118: getstatic     #38                 // Field scala/runtime/BoxedUnit.UNIT:Lscala/runtime/BoxedUnit;
       121: astore_2
       122: goto          135
       125: goto          128
       128: getstatic     #38                 // Field scala/runtime/BoxedUnit.UNIT:Lscala/runtime/BoxedUnit;
       131: astore_2
       132: goto          135
       135: return
      StackMapTable: number_of_entries = 11
        frame_type = 253 /* append */
          offset_delta = 21
          locals = [ top, class org/scalatest/events/Event ]
        frame_type = 2 /* same */
        frame_type = 25 /* same */
        frame_type = 2 /* same */
        frame_type = 18 /* same */
        frame_type = 2 /* same */
        frame_type = 25 /* same */
        frame_type = 2 /* same */
        frame_type = 20 /* same */
        frame_type = 2 /* same */
        frame_type = 255 /* full_frame */
          offset_delta = 6
          locals = [ class org/scalatest/tools/Runner$PassFailReporter, class org/scalatest/events/Event, class scala/runtime/BoxedUnit, class org/scalatest/events/Event ]
          stack = []
      LineNumberTable:
        line 729: 0
        line 730: 2
        line 731: 9
        line 730: 21
        line 733: 24
        line 734: 31
        line 735: 36
        line 733: 50
        line 737: 53
        line 738: 60
        line 737: 72
        line 740: 75
        line 741: 82
        line 742: 87
        line 740: 101
        line 744: 104
        line 745: 111
        line 744: 125
        line 747: 128
        line 729: 135
      LocalVariableTable:
        Start  Length  Slot  Name   Signature
            0     136     0  this   Lorg/scalatest/tools/Runner$PassFailReporter;
            0     136     1 event   Lorg/scalatest/events/Event;
    MethodParameters:
      Name                           Flags
      event                          final

  public boolean allTestsPassed();
    descriptor: ()Z
    flags: (0x0001) ACC_PUBLIC
    Code:
      stack=1, locals=1, args_size=1
         0: aload_0
         1: invokespecial #42                 // Method runDoneSemaphore:()Ljava/util/concurrent/Semaphore;
         4: invokevirtual #61                 // Method java/util/concurrent/Semaphore.acquire:()V
         7: aload_0
         8: invokespecial #63                 // Method failedAbortedOrStopped:()Z
        11: ifne          18
        14: iconst_1
        15: goto          19
        18: iconst_0
        19: ireturn
      StackMapTable: number_of_entries = 2
        frame_type = 18 /* same */
        frame_type = 64 /* same_locals_1_stack_item */
          stack = [ int ]
      LineNumberTable:
        line 752: 0
        line 753: 7
      LocalVariableTable:
        Start  Length  Slot  Name   Signature
            0      20     0  this   Lorg/scalatest/tools/Runner$PassFailReporter;

  public org.scalatest.tools.Runner$PassFailReporter();
    descriptor: ()V
    flags: (0x0001) ACC_PUBLIC
    Code:
      stack=4, locals=1, args_size=1
         0: aload_0
         1: invokespecial #66                 // Method java/lang/Object."<init>":()V
         4: aload_0
         5: iconst_0
         6: putfield      #17                 // Field failedAbortedOrStopped:Z
         9: aload_0
        10: new           #44                 // class java/util/concurrent/Semaphore
        13: dup
        14: iconst_1
        15: invokespecial #69                 // Method java/util/concurrent/Semaphore."<init>":(I)V
        18: putfield      #25                 // Field runDoneSemaphore:Ljava/util/concurrent/Semaphore;
        21: aload_0
        22: invokespecial #42                 // Method runDoneSemaphore:()Ljava/util/concurrent/Semaphore;
        25: invokevirtual #61                 // Method java/util/concurrent/Semaphore.acquire:()V
        28: return
      LineNumberTable:
        line 722: 0
        line 724: 4
        line 725: 9
        line 726: 21
        line 722: 28
      LocalVariableTable:
        Start  Length  Slot  Name   Signature
            0      29     0  this   Lorg/scalatest/tools/Runner$PassFailReporter;
}
InnerClasses:
  private static #10= #2 of #9;           // PassFailReporter=class org/scalatest/tools/Runner$PassFailReporter of class org/scalatest/tools/Runner
SourceFile: "Runner.scala"
  ScalaInlineInfo: length = 0x22 (unknown attribute)
   01 00 00 06 00 40 00 2E 00 00 3A 00 0F 00 00 1A
   00 1B 00 00 0B 00 0F 01 00 14 00 15 01 00 0D 00
   17 01
  Scala: length = 0x0 (unknown attribute)

