Classfile /Users/mw/Projects/slang-braindump/.jar/jar11/assemble/slang-braindump/assemble/content/org/scalatest/tools/ScalaTestFramework.class
  Last modified May 29, 2022; size 7285 bytes
  SHA-256 checksum 73392cd1e6d995d7f2b549f7c9c38f0fcd09b821891b5eedf031e8f4c707ad44
  Compiled from "ScalaTestFramework.scala"
public class org.scalatest.tools.ScalaTestFramework implements org.scalatools.testing.Framework
  minor version: 0
  major version: 52
  flags: (0x0021) ACC_PUBLIC, ACC_SUPER
  this_class: #2                          // org/scalatest/tools/ScalaTestFramework
  super_class: #4                         // java/lang/Object
  interfaces: 1, fields: 1, methods: 7, attributes: 5
Constant pool:
   #1 = Utf8               org/scalatest/tools/ScalaTestFramework
   #2 = Class              #1             // org/scalatest/tools/ScalaTestFramework
   #3 = Utf8               java/lang/Object
   #4 = Class              #3             // java/lang/Object
   #5 = Utf8               org/scalatools/testing/Framework
   #6 = Class              #5             // org/scalatools/testing/Framework
   #7 = Utf8               ScalaTestFramework.scala
   #8 = Utf8               Lscala/reflect/ScalaSignature;
   #9 = Utf8               bytes
  #10 = Utf8               \u0006\u0005\rEd\u0001B0a\u0001\u001dDQ\u0001\u001f\u0001\u0005\u0002eDQ\u0001 \u0001\u0005\u0002uDq!a\u0001\u0001\t\u0003\t)a\u0002\u0005\u0002\u001a\u0001A\tAYA\u000e\r!\ty\u0002\u0001E\u0001E\u0006\u0005\u0002B\u0002=\u0006\t\u0003\tI\u0003C\u0005\u0002,\u0015\u0011\r\u0011\"\u0001\u0002.!A\u0011\u0011K\u0003!\u0002\u0013\ty\u0003C\u0005\u0002T\u0015\u0011\r\u0011\"\u0001\u0002V!A\u0011\u0011M\u0003!\u0002\u0013\t9\u0006C\u0005\u0002d\u0015\u0011\r\u0011\"\u0001\u0002f!A\u0011QN\u0003!\u0002\u0013\t9\u0007C\u0005\u0002p\u0015\u0011\r\u0011\"\u0001\u0002f!A\u0011\u0011O\u0003!\u0002\u0013\t9\u0007C\u0005\u0002t\u0015\u0011\r\u0011\"\u0001\u0002f!A\u0011QO\u0003!\u0002\u0013\t9\u0007C\u0005\u0002x\u0015\u0011\r\u0011\"\u0001\u0002f!A\u0011\u0011P\u0003!\u0002\u0013\t9\u0007C\u0005\u0002|\u0015\u0011\r\u0011\"\u0001\u0002f!A\u0011QP\u0003!\u0002\u0013\t9\u0007C\u0005\u0002\u0000\u0015\u0011\r\u0011\"\u0001\u0002f!A\u0011\u0011Q\u0003!\u0002\u0013\t9\u0007C\u0005\u0002\u0004\u0016\u0011\r\u0011\"\u0001\u0002f!A\u0011QQ\u0003!\u0002\u0013\t9\u0007C\u0005\u0002\b\u0016\u0011\r\u0011\"\u0001\u0002f!A\u0011\u0011R\u0003!\u0002\u0013\t9\u0007C\u0005\u0002\f\u0016\u0011\r\u0011\"\u0001\u0002f!A\u0011QR\u0003!\u0002\u0013\t9\u0007C\u0005\u0002\u0010\u0016\u0011\r\u0011\"\u0001\u0002f!A\u0011\u0011S\u0003!\u0002\u0013\t9\u0007C\u0005\u0002\u0014\u0016\u0011\r\u0011\"\u0001\u0002f!A\u0011QS\u0003!\u0002\u0013\t9\u0007C\u0005\u0002\u0018\u0016\u0011\r\u0011\"\u0001\u0002f!A\u0011\u0011T\u0003!\u0002\u0013\t9\u0007C\u0005\u0002\u001c\u0016\u0011\r\u0011\"\u0001\u0002\u001e\"A\u0011\u0011V\u0003!\u0002\u0013\ty\nC\u0005\u0002,\u0016\u0011\r\u0011\"\u0001\u0002.\"A\u0011\u0011X\u0003!\u0002\u0013\ty\u000bC\u0005\u0002<\u0016\u0011\r\u0011\"\u0001\u0002>\"A\u0011\u0011^\u0003!\u0002\u0013\ty\fC\u0005\u0002l\u0016\u0011\r\u0011\"\u0001\u0002>\"A\u0011Q^\u0003!\u0002\u0013\ty\fC\u0005\u0002p\u0016\u0011\r\u0011\"\u0001\u0002f!A\u0011\u0011_\u0003!\u0002\u0013\t9\u0007C\u0005\u0002t\u0016\u0011\r\u0011\"\u0001\u0002v\"A\u0011Q`\u0003!\u0002\u0013\t9\u0010C\u0005\u0002\u0000\u0016\u0011\r\u0011\"\u0001\u0002v\"A!\u0011A\u0003!\u0002\u0013\t9\u0010C\u0005\u0003\u0004\u0015\u0011\r\u0011\"\u0001\u0003\u0006!A!qC\u0003!\u0002\u0013\u00119\u0001C\u0005\u0003\u001a\u0015\u0011\r\u0011\"\u0001\u0003\u001c!A!1E\u0003!\u0002\u0013\u0011i\u0002C\u0004\u0003&\u0015!\tAa\n\t\u0013\tmSA1A\u0005\n\tu\u0003\u0002\u0003B3\u000b\u0001\u0006IAa\u0018\t\u000f\t\u001dT\u0001\"\u0001\u0003j!9!\u0011O\u0003\u0005\u0002\t%\u0004b\u0002B:\u000b\u0011\u0005!Q\u000f\u0005\b\u0005{\u0003A\u0011\u0001B`\r\u001d\u0011I\b\u0001\u0001c\u0005wB!B!\u0010=\u0005\u0003\u0005\u000b\u0011\u0002B \u0011)\ty\u0007\u0010B\u0001B\u0003%!1\u0011\u0005\u000b\u0003gb$\u0011!Q\u0001\n\t\r\u0005BCA<y\t\u0005\t\u0015!\u0003\u0003\u0004\"Q\u00111\u0010\u001f\u0003\u0002\u0003\u0006IAa!\t\u0015\u0005}DH!A!\u0002\u0013\u0011\u0019\t\u0003\u0006\u0002\u0004r\u0012\t\u0011)A\u0005\u0005\u0007C!\"a\"=\u0005\u0003\u0005\u000b\u0011\u0002BB\u0011)\tY\t\u0010B\u0001B\u0003%!1\u0011\u0005\u000b\u0003\u001fc$\u0011!Q\u0001\n\t\r\u0005BCAJy\t\u0005\t\u0015!\u0003\u0003\u0004\"Q\u0011q\u0013\u001f\u0003\u0002\u0003\u0006IAa!\t\radD\u0011\u0001BE\u0011\u001d\u0011\u0019\u000b\u0010C\t\u0005KCqA!-=\t#\u0011\u0019\fC\u0004\u0003:r\"\tA!\u001b\u0007\u000f\t\r\u0007\u0001\u00011\u0003F\"Q!1K\'\u0003\u0006\u0004%\tA!4\t\u0015\t=WJ!A!\u0002\u0013\u0011)\u0006\u0003\u0006\u0003>5\u0013)\u0019!C\u0001\u0005#D!Ba5N\u0005\u0003\u0005\u000b\u0011\u0002B \u0011\u0019AX\n\"\u0001\u0003V\"9!1\\\'\u0005\n\tu\u0007b\u0002Bt\u001b\u0012%!\u0011\u001e\u0005\b\u0005_lE\u0011\u0001By\u0011%\u0011i0\u0014b\u0001\n\u0013\u0011y\u0010\u0003\u0005\u0004\u00145\u0003\u000b\u0011BB\u0001\r\u0019\u0019\u0019#\u0014\u0003\u0004&!Q!\u0011\n-\u0003\u0002\u0003\u0006IAa\u0013\t\u0015\r5\u0002L!A!\u0002\u0013\u0019y\u0003\u0003\u0004y1\u0012\u00051\u0011\u0007\u0005\b\u0007wAF\u0011AB\u001f\u0011\u001d\u0019I\u0006\u0017C!\u00077BqA!/Y\t\u0003\u0011IG\u0001\nTG\u0006d\u0017\rV3ti\u001a\u0013\u0018-\\3x_J\\\'BA1c\u0003\u0015!xn\u001c7t\u0015\t\u0019G-A\u0005tG\u0006d\u0017\r^3ti*\tQ-A\u0002pe\u001e\u001c\u0001aE\u0002\u0001QB\u0004\"!\u001b8\u000e\u0003)T!a\u001b7\u0002\t1\fgn\u001a\u0006\u0002[\u0006!!.\u0019<b\u0013\ty\'N\u0001\u0004PE*,7\r\u001e\t\u0003cZl\u0011A\u001d\u0006\u0003gR\fq\u0001^3ti&twM\u0003\u0002vI\u0006Q1oY1mCR|w\u000e\\:\n\u0005]\u0014(!\u0003$sC6,wo\u001c:l\u0003\u0019a\u0014N\\5u}Q\t!\u0010\u0005\u0002|\u00015\t\u0001-\u0001\u0003oC6,G#\u0001@\u0011\u0005%|\u0018bAA\u0001U\n11\u000b\u001e:j]\u001e\fQ\u0001^3tiN$\"!a\u0002\u0011\r\u0005%\u0011qBA\n\u001b\t\tYA\u0003\u0002\u0002\u000e\u0005)1oY1mC&!\u0011\u0011CA\u0006\u0005\u0015\t%O]1z!\r\t\u0018QC\u0005\u0004\u0003/\u0011(a\u0003$j]\u001e,\'\u000f\u001d:j]R\f\u0011BU;o\u0007>tg-[4\u0011\u0007\u0005uQ!D\u0001\u0001\u0005%\u0011VO\\\"p]\u001aLwmE\u0002\u0006\u0003G\u0001B!!\u0003\u0002&%!\u0011qEA\u0006\u0005\u0019\te.\u001f*fMR\u0011\u00111D\u0001\te\u0016\u0004xN\u001d;feV\u0011\u0011q\u0006\t\u0007\u0003c\ty$a\u0011\u000e\u0005\u0005M\"\u0002BA\u001b\u0003o\ta!\u0019;p[&\u001c\'\u0002BA\u001d\u0003w\t!bY8oGV\u0014(/\u001a8u\u0015\r\ti\u0004\\\u0001\u0005kRLG.\u0003\u0003\u0002B\u0005M\"aD!u_6L7MU3gKJ,gnY3\u0011\r\u0005%\u0011QIA%\u0013\u0011\t9%a\u0003\u0003\r=\u0003H/[8o!\u0011\tY%!\u0014\u000e\u0003\tL1!a\u0014c\u0005A!\u0015n\u001d9bi\u000eD\'+\u001a9peR,\'/A\u0005sKB|\'\u000f^3sA\u0005y!/\u001a9peR,\'oQ8oM&<7/\u0006\u0002\u0002XA1\u0011\u0011GA \u00033\u0002b!!\u0003\u0002F\u0005m\u0003cA>\u0002^%\u0019\u0011q\f1\u0003-I+\u0007o\u001c:uKJ\u001cuN\u001c4jOV\u0014\u0018\r^5p]N\f\u0001C]3q_J$XM]\"p]\u001aLwm\u001d\u0011\u0002\u0013U\u001cXm\u0015;e_V$XCAA4!\u0011\t\t$!\u001b\n\t\u0005-\u00141\u0007\u0002\u000e\u0003R|W.[2C_>dW-\u00198\u0002\u0015U\u001cXm\u0015;e_V$\b%A\nqe\u0016\u001cXM\u001c;BY2$UO]1uS>t7/\u0001\u000bqe\u0016\u001cXM\u001c;BY2$UO]1uS>t7\u000fI\u0001\u000faJ,7/\u001a8u\u0013:\u001cu\u000e\\8s\u0003=\u0001(/Z:f]RLenQ8m_J\u0004\u0013a\u00069sKN,g\u000e^*i_J$8\u000b^1dWR\u0013\u0018mY3t\u0003a\u0001(/Z:f]R\u001c\u0006n\u001c:u\'R\f7m\u001b+sC\u000e,7\u000fI\u0001\u0017aJ,7/\u001a8u\rVdGn\u0015;bG.$&/Y2fg\u00069\u0002O]3tK:$h)\u001e7m\'R\f7m\u001b+sC\u000e,7\u000fI\u0001\u0013aJ,7/\u001a8u+:4wN]7biR,G-A\nqe\u0016\u001cXM\u001c;V]\u001a|\'/\\1ui\u0016$\u0007%A\bqe\u0016\u001cXM\u001c;SK6Lg\u000eZ3s\u0003A\u0001(/Z:f]R\u0014V-\\5oI\u0016\u0014\b%A\u0012qe\u0016\u001cXM\u001c;SK6Lg\u000eZ3s/&$\bn\u00155peR\u001cF/Y2l)J\f7-Z:\u0002IA\u0014Xm]3oiJ+W.\u001b8eKJ<\u0016\u000e\u001e5TQ>\u0014Ho\u0015;bG.$&/Y2fg\u0002\n!\u0005\u001d:fg\u0016tGOU3nS:$WM],ji\"4U\u000f\u001c7Ti\u0006\u001c7\u000e\u0016:bG\u0016\u001c\u0018a\t9sKN,g\u000e\u001e*f[&tG-\u001a:XSRDg)\u001e7m\'R\f7m\u001b+sC\u000e,7\u000fI\u0001$aJ,7/\u001a8u%\u0016l\u0017N\u001c3fe^KG\u000f[8vi\u000e\u000bgnY3mK\u0012$Vm\u001d;t\u0003\u0011\u0002(/Z:f]R\u0014V-\\5oI\u0016\u0014x+\u001b;i_V$8)\u00198dK2,G\rV3tiN\u0004\u0013a\u00059sKN,g\u000e\u001e$jY\u0016\u0004\u0016\r\u001e5oC6,\u0017\u0001\u00069sKN,g\u000e\u001e$jY\u0016\u0004\u0016\r\u001e5oC6,\u0007%A\u0006qe\u0016\u001cXM\u001c;Kg>t\u0017\u0001\u00049sKN,g\u000e\u001e&t_:\u0004\u0013A\u00024jYR,\'/\u0006\u0002\u0002 B1\u0011\u0011GA \u0003C\u0003b!!\u0003\u0002F\u0005\r\u0006\u0003BA&\u0003KK1!a*c\u0005\u00191\u0015\u000e\u001c;fe\u00069a-\u001b7uKJ\u0004\u0013!C2p]\u001aLw-T1q+\t\ty\u000b\u0005\u0004\u00022\u0005}\u0012\u0011\u0017\t\u0007\u0003\u0013\t)%a-\u0011\t\u0005-\u0013QW\u0005\u0004\u0003o\u0013\'!C\"p]\u001aLw-T1q\u0003)\u0019wN\u001c4jO6\u000b\u0007\u000fI\u0001\f[\u0016l\'-\u001a:t\u001f:d\u00170\u0006\u0002\u0002@B1\u0011\u0011GA \u0003\u0003\u0004b!!\u0003\u0002F\u0005\r\u0007CBAc\u0003+\fYN\u0004\u0003\u0002H\u0006Eg\u0002BAe\u0003\u001fl!!a3\u000b\u0007\u00055g-\u0001\u0004=e>|GOP\u0005\u0003\u0003\u001bIA!a5\u0002\f\u00059\u0001/Y2lC\u001e,\u0017\u0002BAl\u00033\u0014A\u0001T5ti*!\u00111[A\u0006!\u0011\ti.!:\u000f\t\u0005}\u0017\u0011\u001d\t\u0005\u0003\u0013\fY!\u0003\u0003\u0002d\u0006-\u0011A\u0002)sK\u0012,g-\u0003\u0003\u0002\u0002\u0005\u001d(\u0002BAr\u0003\u0017\tA\"\\3nE\u0016\u00148o\u00148ms\u0002\n\u0001b^5mI\u000e\f\'\u000fZ\u0001\no&dGmY1sI\u0002\nq\u0002Z3uK\u000e$8\u000b\\8xa>\\Wm]\u0001\u0011I\u0016$Xm\u0019;TY><\bo\\6fg\u0002\nac\u001d7poB|7.\u001a#fi\u0016\u001cG/[8o\t\u0016d\u0017-_\u000b\u0003\u0003o\u0004B!!\r\u0002z&!\u00111`A\u001a\u0005)\tEo\\7jG2{gnZ\u0001\u0018g2|w\u000f]8lK\u0012+G/Z2uS>tG)\u001a7bs\u0002\nqc\u001d7poB|7.\u001a#fi\u0016\u001cG/[8o!\u0016\u0014\u0018n\u001c3\u00021Mdwn\u001e9pW\u0016$U\r^3di&|g\u000eU3sS>$\u0007%\u0001\u000euKN$8k\u001c:uS:<\'+\u001a9peR,\'\u000fV5nK>,H/\u0006\u0002\u0003\bA1\u0011\u0011GA \u0005\u0013\u0001b!!\u0003\u0002F\t-\u0001\u0003\u0002B\u0007\u0005\'i!Aa\u0004\u000b\u0007\tE!-\u0001\u0003uS6,\u0017\u0002\u0002B\u000b\u0005\u001f\u0011Aa\u00159b]\u0006YB/Z:u\'>\u0014H/\u001b8h%\u0016\u0004xN\u001d;feRKW.Z8vi\u0002\nAB]3tk2$\bj\u001c7eKJ,\"A!\b\u0011\u0007m\u0014y\"C\u0002\u0003\"\u0001\u0014\u0011cU;ji\u0016\u0014Vm];mi\"{G\u000eZ3s\u00035\u0011Xm];mi\"{G\u000eZ3sA\u0005\tr-\u001a;D_:4\u0017nZ;sCRLwN\\:\u0015\u0015\t%\"Q\u0007B\u001e\u0005\u000f\u0012\t\u0006\u0005\t\u0002\n\t-\"qFAR\u0003g\u000b\u0019-a1\u0003\f%!!QFA\u0006\u0005\u0019!V\u000f\u001d7fmA\u00191P!\r\n\u0007\tM\u0002MA\nTER$\u0015n\u001d9bi\u000eD\'+\u001a9peR,\'\u000fC\u0004\u00038U\u0002\rA!\u000f\u0002\t\u0005\u0014xm\u001d\t\u0007\u0003\u0013\ty!a7\t\u000f\tuR\u00071\u0001\u0003@\u00059An\\4hKJ\u001c\bCBA\u0005\u0003\u001f\u0011\t\u0005E\u0002r\u0005\u0007J1A!\u0012s\u0005\u0019aunZ4fe\"9!\u0011J\u001bA\u0002\t-\u0013\u0001D3wK:$\b*\u00198eY\u0016\u0014\bcA9\u0003N%\u0019!q\n:\u0003\u0019\u00153XM\u001c;IC:$G.\u001a:\t\u000f\tMS\u00071\u0001\u0003V\u0005QA/Z:u\u0019>\fG-\u001a:\u0011\u0007%\u00149&C\u0002\u0003Z)\u00141b\u00117bgNdu.\u00193fe\u0006Y\u0011\r^8nS\u000e\u001cu.\u001e8u+\t\u0011y\u0006\u0005\u0003\u00022\t\u0005\u0014\u0002\u0002B2\u0003g\u0011Q\"\u0011;p[&\u001c\u0017J\u001c;fO\u0016\u0014\u0018\u0001D1u_6L7mQ8v]R\u0004\u0013!D5oGJ,\u0017m]3MCR\u001c\u0007\u000e\u0006\u0002\u0003lA!\u0011\u0011\u0002B7\u0013\u0011\u0011y\'a\u0003\u0003\tUs\u0017\u000e^\u0001\u000eI\u0016\u001c\'/Z1tK2\u000bGo\u00195\u00021\r\u0014X-\u0019;f\'\n$Hj\\4J]\u001a|\'+\u001a9peR,\'\u000f\u0006\u0003\u0003x\tm\u0006cAA\u000fy\t\u00112K\u0019;M_\u001eLeNZ8SKB|\'\u000f^3s\'\ra$Q\u0010\t\u0004w\n}\u0014b\u0001BAA\nq1\u000b\u001e:j]\u001e\u0014V\r]8si\u0016\u0014\b\u0003BA\u0005\u0005\u000bKAAa\"\u0002\f\t9!i\\8mK\u0006tGC\u0007B<\u0005\u0017\u0013iIa$\u0003\u0012\nM%Q\u0013BL\u00053\u0013YJ!(\u0003 \n\u0005\u0006b\u0002B\u001f\u0013\u0002\u0007!q\b\u0005\b\u0003_J\u0005\u0019\u0001BB\u0011\u001d\t\u0019(\u0013a\u0001\u0005\u0007Cq!a\u001eJ\u0001\u0004\u0011\u0019\tC\u0004\u0002|%\u0003\rAa!\t\u000f\u0005}\u0014\n1\u0001\u0003\u0004\"9\u00111Q%A\u0002\t\r\u0005bBAD\u0013\u0002\u0007!1\u0011\u0005\b\u0003\u0017K\u0005\u0019\u0001BB\u0011\u001d\ty)\u0013a\u0001\u0005\u0007Cq!a%J\u0001\u0004\u0011\u0019\tC\u0004\u0002\u0018&\u0003\rAa!\u0002)A\u0014\u0018N\u001c;Q_N\u001c\u0018N\u00197z\u0013:\u001cu\u000e\\8s)\u0011\u0011YGa*\t\u000f\t%&\n1\u0001\u0003,\u0006AaM]1h[\u0016tG\u000fE\u0002|\u0005[K1Aa,a\u0005!1%/Y4nK:$\u0018\u0001\u00049sS:$hj\\\"pY>\u0014H\u0003\u0002B6\u0005kCqAa.L\u0001\u0004\tY.\u0001\u0003uKb$\u0018a\u00023jgB|7/\u001a\u0005\b\u0005{Q\u0004\u0019\u0001B \u0003)!Xm\u001d;Sk:tWM\u001d\u000b\u0007\u0005\u0003\u001ciga\u001c\u0011\u0007\u0005uQJA\bTG\u0006d\u0017\rV3tiJ+hN\\3s\'\ri%q\u0019\t\u0004c\n%\u0017b\u0001Bfe\n9!+\u001e8oKJ\u0014TC\u0001B+\u0003-!Xm\u001d;M_\u0006$WM\u001d\u0011\u0016\u0005\t}\u0012\u0001\u00037pO\u001e,\'o\u001d\u0011\u0015\r\t\u0005\'q\u001bBm\u0011\u001d\u0011\u0019F\u0015a\u0001\u0005+BqA!\u0010S\u0001\u0004\u0011y$\u0001\bgS2$XM],jY\u0012\u001c\u0017M\u001d3\u0015\r\t\r%q\u001cBr\u0011\u001d\u0011\to\u0015a\u0001\u0003\u0007\fQ\u0001]1uQNDqA!:T\u0001\u0004\tY.A\u0007uKN$8\t\\1tg:\u000bW.Z\u0001\u0012M&dG/\u001a:NK6\u0014WM]:P]2LHC\u0002BB\u0005W\u0014i\u000fC\u0004\u0003bR\u0003\r!a1\t\u000f\t\u0015H\u000b1\u0001\u0002\\\u0006\u0019!/\u001e8\u0015\u0015\t-$1\u001fB{\u0005s\u0014Y\u0010C\u0004\u0003fV\u0003\r!a7\t\u000f\t]X\u000b1\u0001\u0002\u0014\u0005Ya-\u001b8hKJ\u0004(/\u001b8u\u0011\u001d\u0011I%\u0016a\u0001\u0005\u0017BqAa\u000eV\u0001\u0004\u0011I$A\bf[B$\u0018p\u00117bgN\f%O]1z+\t\u0019\t\u0001\u0005\u0004\u0002\n\u0005=11\u0001\u0019\u0005\u0007\u000b\u0019y\u0001E\u0003j\u0007\u000f\u0019Y!C\u0002\u0004\n)\u0014Qa\u00117bgN\u0004Ba!\u0004\u0004\u00101\u0001AaCB\t/\u0006\u0005\t\u0011!B\u0001\u0007+\u00111a\u0018\u00133\u0003A)W\u000e\u001d;z\u00072\f7o]!se\u0006L\b%\u0005\u0003\u0004\u0018\ru\u0001\u0003BA\u0005\u00073IAaa\u0007\u0002\f\t9aj\u001c;iS:<\u0007\u0003BA\u0005\u0007?IAa!\t\u0002\f\t\u0019\u0011I\\=\u0003\u0017M\u0013GOU3q_J$XM]\n\u00061\u0006\r2q\u0005\t\u0005\u0003\u0017\u001aI#C\u0002\u0004,\t\u0014\u0001BU3q_J$XM]\u0001\u0007e\u0016\u0004xN\u001d;\u0011\r\u0005%\u0011QIB\u0014)\u0019\u0019\u0019da\u000e\u0004:A\u00191Q\u0007-\u000e\u00035CqA!\u0013\\\u0001\u0004\u0011Y\u0005C\u0004\u0004.m\u0003\raa\f\u0002\u0013\u0019L\'/Z#wK:$H\u0003\u0003B6\u0007\u007f\u0019\u0019e!\u0014\t\u000f\r\u0005C\f1\u0001\u0002\\\u0006\u0011AO\u001c\u0005\b\u0007\u000bb\u0006\u0019AB$\u0003\u0005\u0011\bcA9\u0004J%\u001911\n:\u0003\rI+7/\u001e7u\u0011\u001d\u0019y\u0005\u0018a\u0001\u0007#\n\u0011!\u001a\t\u0007\u0003\u0013\t)ea\u0015\u0011\t\u0005\u00157QK\u0005\u0005\u0007/\nINA\u0005UQJ|w/\u00192mK\u0006)\u0011\r\u001d9msR!!1NB/\u0011\u001d\u0019y&\u0018a\u0001\u0007C\nQ!\u001a<f]R\u0004Baa\u0019\u0004j5\u00111Q\r\u0006\u0004\u0007O\u0012\u0017AB3wK:$8/\u0003\u0003\u0004l\r\u0015$!B#wK:$\bb\u0002B*w\u0001\u0007!Q\u000b\u0005\b\u0005{Y\u0004\u0019\u0001B \u0001
  #11 = Utf8               org/scalatest/tools/ScalaTestFramework$$anon$1
  #12 = Class              #11            // org/scalatest/tools/ScalaTestFramework$$anon$1
  #13 = Utf8               org/scalatest/tools/ScalaTestFramework$$anon$2
  #14 = Class              #13            // org/scalatest/tools/ScalaTestFramework$$anon$2
  #15 = Utf8               org/scalatest/tools/ScalaTestFramework$RunConfig$
  #16 = Class              #15            // org/scalatest/tools/ScalaTestFramework$RunConfig$
  #17 = Utf8               RunConfig$
  #18 = Utf8               org/scalatest/tools/ScalaTestFramework$SbtLogInfoReporter
  #19 = Class              #18            // org/scalatest/tools/ScalaTestFramework$SbtLogInfoReporter
  #20 = Utf8               SbtLogInfoReporter
  #21 = Utf8               org/scalatest/tools/ScalaTestFramework$ScalaTestRunner
  #22 = Class              #21            // org/scalatest/tools/ScalaTestFramework$ScalaTestRunner
  #23 = Utf8               ScalaTestRunner
  #24 = Utf8               RunConfig$module
  #25 = Utf8               Lorg/scalatest/tools/ScalaTestFramework$RunConfig$;
  #26 = Utf8               RunConfig
  #27 = Utf8               ()Lorg/scalatest/tools/ScalaTestFramework$RunConfig$;
  #28 = NameAndType        #24:#25        // RunConfig$module:Lorg/scalatest/tools/ScalaTestFramework$RunConfig$;
  #29 = Fieldref           #2.#28         // org/scalatest/tools/ScalaTestFramework.RunConfig$module:Lorg/scalatest/tools/ScalaTestFramework$RunConfig$;
  #30 = Utf8               RunConfig$lzycompute$1
  #31 = Utf8               ()V
  #32 = NameAndType        #30:#31        // RunConfig$lzycompute$1:()V
  #33 = Methodref          #2.#32         // org/scalatest/tools/ScalaTestFramework.RunConfig$lzycompute$1:()V
  #34 = Utf8               this
  #35 = Utf8               Lorg/scalatest/tools/ScalaTestFramework;
  #36 = Utf8               name
  #37 = Utf8               ()Ljava/lang/String;
  #38 = Utf8               ScalaTest
  #39 = String             #38            // ScalaTest
  #40 = Utf8               tests
  #41 = Utf8               ()[Lorg/scalatools/testing/Fingerprint;
  #42 = Utf8               org/scalatools/testing/Fingerprint
  #43 = Class              #42            // org/scalatools/testing/Fingerprint
  #44 = Utf8               <init>
  #45 = Utf8               (Lorg/scalatest/tools/ScalaTestFramework;)V
  #46 = NameAndType        #44:#45        // "<init>":(Lorg/scalatest/tools/ScalaTestFramework;)V
  #47 = Methodref          #12.#46        // org/scalatest/tools/ScalaTestFramework$$anon$1."<init>":(Lorg/scalatest/tools/ScalaTestFramework;)V
  #48 = Methodref          #14.#46        // org/scalatest/tools/ScalaTestFramework$$anon$2."<init>":(Lorg/scalatest/tools/ScalaTestFramework;)V
  #49 = Utf8               [Ljava/lang/Object;
  #50 = Class              #49            // "[Ljava/lang/Object;"
  #51 = Utf8               [Lorg/scalatools/testing/Fingerprint;
  #52 = Class              #51            // "[Lorg/scalatools/testing/Fingerprint;"
  #53 = Utf8               testRunner
  #54 = Utf8               (Ljava/lang/ClassLoader;[Lorg/scalatools/testing/Logger;)Lorg/scalatest/tools/ScalaTestFramework$ScalaTestRunner;
  #55 = Utf8               testLoader
  #56 = Utf8               loggers
  #57 = Utf8               (Lorg/scalatest/tools/ScalaTestFramework;Ljava/lang/ClassLoader;[Lorg/scalatools/testing/Logger;)V
  #58 = NameAndType        #44:#57        // "<init>":(Lorg/scalatest/tools/ScalaTestFramework;Ljava/lang/ClassLoader;[Lorg/scalatools/testing/Logger;)V
  #59 = Methodref          #22.#58        // org/scalatest/tools/ScalaTestFramework$ScalaTestRunner."<init>":(Lorg/scalatest/tools/ScalaTestFramework;Ljava/lang/ClassLoader;[Lorg/scalatools/testing/Logger;)V
  #60 = Utf8               Ljava/lang/ClassLoader;
  #61 = Utf8               [Lorg/scalatools/testing/Logger;
  #62 = Utf8               (Ljava/lang/ClassLoader;[Lorg/scalatools/testing/Logger;)Lorg/scalatools/testing/Runner;
  #63 = Utf8               x$1
  #64 = Utf8               x$2
  #65 = NameAndType        #53:#54        // testRunner:(Ljava/lang/ClassLoader;[Lorg/scalatools/testing/Logger;)Lorg/scalatest/tools/ScalaTestFramework$ScalaTestRunner;
  #66 = Methodref          #2.#65         // org/scalatest/tools/ScalaTestFramework.testRunner:(Ljava/lang/ClassLoader;[Lorg/scalatools/testing/Logger;)Lorg/scalatest/tools/ScalaTestFramework$ScalaTestRunner;
  #67 = Methodref          #16.#46        // org/scalatest/tools/ScalaTestFramework$RunConfig$."<init>":(Lorg/scalatest/tools/ScalaTestFramework;)V
  #68 = Utf8               java/lang/Throwable
  #69 = Class              #68            // java/lang/Throwable
  #70 = NameAndType        #44:#31        // "<init>":()V
  #71 = Methodref          #4.#70         // java/lang/Object."<init>":()V
  #72 = Utf8               Code
  #73 = Utf8               StackMapTable
  #74 = Utf8               LineNumberTable
  #75 = Utf8               LocalVariableTable
  #76 = Utf8               MethodParameters
  #77 = Utf8               InnerClasses
  #78 = Utf8               SourceFile
  #79 = Utf8               RuntimeVisibleAnnotations
  #80 = Utf8               ScalaInlineInfo
  #81 = Utf8               ScalaSig
{
  private volatile org.scalatest.tools.ScalaTestFramework$RunConfig$ RunConfig$module;
    descriptor: Lorg/scalatest/tools/ScalaTestFramework$RunConfig$;
    flags: (0x0042) ACC_PRIVATE, ACC_VOLATILE

  public org.scalatest.tools.ScalaTestFramework$RunConfig$ RunConfig();
    descriptor: ()Lorg/scalatest/tools/ScalaTestFramework$RunConfig$;
    flags: (0x0001) ACC_PUBLIC
    Code:
      stack=1, locals=1, args_size=1
         0: aload_0
         1: getfield      #29                 // Field RunConfig$module:Lorg/scalatest/tools/ScalaTestFramework$RunConfig$;
         4: ifnonnull     11
         7: aload_0
         8: invokespecial #33                 // Method RunConfig$lzycompute$1:()V
        11: aload_0
        12: getfield      #29                 // Field RunConfig$module:Lorg/scalatest/tools/ScalaTestFramework$RunConfig$;
        15: areturn
      StackMapTable: number_of_entries = 1
        frame_type = 11 /* same */
      LineNumberTable:
        line 122: 0
      LocalVariableTable:
        Start  Length  Slot  Name   Signature
            0      16     0  this   Lorg/scalatest/tools/ScalaTestFramework;

  public java.lang.String name();
    descriptor: ()Ljava/lang/String;
    flags: (0x0001) ACC_PUBLIC
    Code:
      stack=1, locals=1, args_size=1
         0: ldc           #39                 // String ScalaTest
         2: areturn
      LineNumberTable:
        line 103: 0
      LocalVariableTable:
        Start  Length  Slot  Name   Signature
            0       3     0  this   Lorg/scalatest/tools/ScalaTestFramework;

  public org.scalatools.testing.Fingerprint[] tests();
    descriptor: ()[Lorg/scalatools/testing/Fingerprint;
    flags: (0x0001) ACC_PUBLIC
    Code:
      stack=6, locals=1, args_size=1
         0: iconst_2
         1: anewarray     #43                 // class org/scalatools/testing/Fingerprint
         4: dup
         5: iconst_0
         6: new           #12                 // class org/scalatest/tools/ScalaTestFramework$$anon$1
         9: dup
        10: aconst_null
        11: invokespecial #47                 // Method org/scalatest/tools/ScalaTestFramework$$anon$1."<init>":(Lorg/scalatest/tools/ScalaTestFramework;)V
        14: aastore
        15: dup
        16: iconst_1
        17: new           #14                 // class org/scalatest/tools/ScalaTestFramework$$anon$2
        20: dup
        21: aconst_null
        22: invokespecial #48                 // Method org/scalatest/tools/ScalaTestFramework$$anon$2."<init>":(Lorg/scalatest/tools/ScalaTestFramework;)V
        25: aastore
        26: checkcast     #50                 // class "[Ljava/lang/Object;"
        29: checkcast     #52                 // class "[Lorg/scalatools/testing/Fingerprint;"
        32: areturn
      LineNumberTable:
        line 111: 0
        line 112: 6
        line 116: 17
      LocalVariableTable:
        Start  Length  Slot  Name   Signature
            0      33     0  this   Lorg/scalatest/tools/ScalaTestFramework;

  public org.scalatest.tools.ScalaTestFramework$ScalaTestRunner testRunner(java.lang.ClassLoader, org.scalatools.testing.Logger[]);
    descriptor: (Ljava/lang/ClassLoader;[Lorg/scalatools/testing/Logger;)Lorg/scalatest/tools/ScalaTestFramework$ScalaTestRunner;
    flags: (0x0001) ACC_PUBLIC
    Code:
      stack=5, locals=3, args_size=3
         0: new           #22                 // class org/scalatest/tools/ScalaTestFramework$ScalaTestRunner
         3: dup
         4: aload_0
         5: aload_1
         6: aload_2
         7: invokespecial #59                 // Method org/scalatest/tools/ScalaTestFramework$ScalaTestRunner."<init>":(Lorg/scalatest/tools/ScalaTestFramework;Ljava/lang/ClassLoader;[Lorg/scalatools/testing/Logger;)V
        10: areturn
      LineNumberTable:
        line 319: 0
      LocalVariableTable:
        Start  Length  Slot  Name   Signature
            0      11     0  this   Lorg/scalatest/tools/ScalaTestFramework;
            0      11     1 testLoader   Ljava/lang/ClassLoader;
            0      11     2 loggers   [Lorg/scalatools/testing/Logger;
    MethodParameters:
      Name                           Flags
      testLoader                     final
      loggers                        final

  public org.scalatools.testing.Runner testRunner(java.lang.ClassLoader, org.scalatools.testing.Logger[]);
    descriptor: (Ljava/lang/ClassLoader;[Lorg/scalatools/testing/Logger;)Lorg/scalatools/testing/Runner;
    flags: (0x1041) ACC_PUBLIC, ACC_BRIDGE, ACC_SYNTHETIC
    Code:
      stack=3, locals=3, args_size=3
         0: aload_0
         1: aload_1
         2: aload_2
         3: invokevirtual #66                 // Method testRunner:(Ljava/lang/ClassLoader;[Lorg/scalatools/testing/Logger;)Lorg/scalatest/tools/ScalaTestFramework$ScalaTestRunner;
         6: areturn
      LineNumberTable:
        line 98: 0
      LocalVariableTable:
        Start  Length  Slot  Name   Signature
            0       7     0  this   Lorg/scalatest/tools/ScalaTestFramework;
            0       7     1   x$1   Ljava/lang/ClassLoader;
            0       7     2   x$2   [Lorg/scalatools/testing/Logger;
    MethodParameters:
      Name                           Flags
      x$1                            final
      x$2                            final

  private final void RunConfig$lzycompute$1();
    descriptor: ()V
    flags: (0x0012) ACC_PRIVATE, ACC_FINAL
    Code:
      stack=4, locals=2, args_size=1
         0: aload_0
         1: dup
         2: astore_1
         3: monitorenter
         4: aload_0
         5: getfield      #29                 // Field RunConfig$module:Lorg/scalatest/tools/ScalaTestFramework$RunConfig$;
         8: ifnonnull     23
        11: aload_0
        12: new           #16                 // class org/scalatest/tools/ScalaTestFramework$RunConfig$
        15: dup
        16: aload_0
        17: invokespecial #67                 // Method org/scalatest/tools/ScalaTestFramework$RunConfig$."<init>":(Lorg/scalatest/tools/ScalaTestFramework;)V
        20: putfield      #29                 // Field RunConfig$module:Lorg/scalatest/tools/ScalaTestFramework$RunConfig$;
        23: aload_1
        24: monitorexit
        25: goto          31
        28: aload_1
        29: monitorexit
        30: athrow
        31: return
      Exception table:
         from    to  target type
             4    23    28   any
      StackMapTable: number_of_entries = 3
        frame_type = 252 /* append */
          offset_delta = 23
          locals = [ class org/scalatest/tools/ScalaTestFramework ]
        frame_type = 68 /* same_locals_1_stack_item */
          stack = [ class java/lang/Throwable ]
        frame_type = 2 /* same */
      LineNumberTable:
        line 122: 0
      LocalVariableTable:
        Start  Length  Slot  Name   Signature
            0      32     0  this   Lorg/scalatest/tools/ScalaTestFramework;

  public org.scalatest.tools.ScalaTestFramework();
    descriptor: ()V
    flags: (0x0001) ACC_PUBLIC
    Code:
      stack=1, locals=1, args_size=1
         0: aload_0
         1: invokespecial #71                 // Method java/lang/Object."<init>":()V
         4: return
      LineNumberTable:
        line 98: 0
      LocalVariableTable:
        Start  Length  Slot  Name   Signature
            0       5     0  this   Lorg/scalatest/tools/ScalaTestFramework;
}
InnerClasses:
  public final #12;                       // class org/scalatest/tools/ScalaTestFramework$$anon$1
  public final #14;                       // class org/scalatest/tools/ScalaTestFramework$$anon$2
  public #17= #16 of #2;                  // RunConfig$=class org/scalatest/tools/ScalaTestFramework$RunConfig$ of class org/scalatest/tools/ScalaTestFramework
  public #20= #19 of #2;                  // SbtLogInfoReporter=class org/scalatest/tools/ScalaTestFramework$SbtLogInfoReporter of class org/scalatest/tools/ScalaTestFramework
  public #23= #22 of #2;                  // ScalaTestRunner=class org/scalatest/tools/ScalaTestFramework$ScalaTestRunner of class org/scalatest/tools/ScalaTestFramework
SourceFile: "ScalaTestFramework.scala"
RuntimeVisibleAnnotations:
  0: #8(#9=s#10)
    scala.reflect.ScalaSignature(
      bytes="\u0006\u0005\rEd\u0001B0a\u0001\u001dDQ\u0001\u001f\u0001\u0005\u0002eDQ\u0001 \u0001\u0005\u0002uDq!a\u0001\u0001\t\u0003\t)a\u0002\u0005\u0002\u001a\u0001A\tAYA\u000e\r!\ty\u0002\u0001E\u0001E\u0006\u0005\u0002B\u0002=\u0006\t\u0003\tI\u0003C\u0005\u0002,\u0015\u0011\r\u0011\"\u0001\u0002.!A\u0011\u0011K\u0003!\u0002\u0013\ty\u0003C\u0005\u0002T\u0015\u0011\r\u0011\"\u0001\u0002V!A\u0011\u0011M\u0003!\u0002\u0013\t9\u0006C\u0005\u0002d\u0015\u0011\r\u0011\"\u0001\u0002f!A\u0011QN\u0003!\u0002\u0013\t9\u0007C\u0005\u0002p\u0015\u0011\r\u0011\"\u0001\u0002f!A\u0011\u0011O\u0003!\u0002\u0013\t9\u0007C\u0005\u0002t\u0015\u0011\r\u0011\"\u0001\u0002f!A\u0011QO\u0003!\u0002\u0013\t9\u0007C\u0005\u0002x\u0015\u0011\r\u0011\"\u0001\u0002f!A\u0011\u0011P\u0003!\u0002\u0013\t9\u0007C\u0005\u0002|\u0015\u0011\r\u0011\"\u0001\u0002f!A\u0011QP\u0003!\u0002\u0013\t9\u0007C\u0005\u0002\u0000\u0015\u0011\r\u0011\"\u0001\u0002f!A\u0011\u0011Q\u0003!\u0002\u0013\t9\u0007C\u0005\u0002\u0004\u0016\u0011\r\u0011\"\u0001\u0002f!A\u0011QQ\u0003!\u0002\u0013\t9\u0007C\u0005\u0002\b\u0016\u0011\r\u0011\"\u0001\u0002f!A\u0011\u0011R\u0003!\u0002\u0013\t9\u0007C\u0005\u0002\f\u0016\u0011\r\u0011\"\u0001\u0002f!A\u0011QR\u0003!\u0002\u0013\t9\u0007C\u0005\u0002\u0010\u0016\u0011\r\u0011\"\u0001\u0002f!A\u0011\u0011S\u0003!\u0002\u0013\t9\u0007C\u0005\u0002\u0014\u0016\u0011\r\u0011\"\u0001\u0002f!A\u0011QS\u0003!\u0002\u0013\t9\u0007C\u0005\u0002\u0018\u0016\u0011\r\u0011\"\u0001\u0002f!A\u0011\u0011T\u0003!\u0002\u0013\t9\u0007C\u0005\u0002\u001c\u0016\u0011\r\u0011\"\u0001\u0002\u001e\"A\u0011\u0011V\u0003!\u0002\u0013\ty\nC\u0005\u0002,\u0016\u0011\r\u0011\"\u0001\u0002.\"A\u0011\u0011X\u0003!\u0002\u0013\ty\u000bC\u0005\u0002<\u0016\u0011\r\u0011\"\u0001\u0002>\"A\u0011\u0011^\u0003!\u0002\u0013\ty\fC\u0005\u0002l\u0016\u0011\r\u0011\"\u0001\u0002>\"A\u0011Q^\u0003!\u0002\u0013\ty\fC\u0005\u0002p\u0016\u0011\r\u0011\"\u0001\u0002f!A\u0011\u0011_\u0003!\u0002\u0013\t9\u0007C\u0005\u0002t\u0016\u0011\r\u0011\"\u0001\u0002v\"A\u0011Q`\u0003!\u0002\u0013\t9\u0010C\u0005\u0002\u0000\u0016\u0011\r\u0011\"\u0001\u0002v\"A!\u0011A\u0003!\u0002\u0013\t9\u0010C\u0005\u0003\u0004\u0015\u0011\r\u0011\"\u0001\u0003\u0006!A!qC\u0003!\u0002\u0013\u00119\u0001C\u0005\u0003\u001a\u0015\u0011\r\u0011\"\u0001\u0003\u001c!A!1E\u0003!\u0002\u0013\u0011i\u0002C\u0004\u0003&\u0015!\tAa\n\t\u0013\tmSA1A\u0005\n\tu\u0003\u0002\u0003B3\u000b\u0001\u0006IAa\u0018\t\u000f\t\u001dT\u0001\"\u0001\u0003j!9!\u0011O\u0003\u0005\u0002\t%\u0004b\u0002B:\u000b\u0011\u0005!Q\u000f\u0005\b\u0005{\u0003A\u0011\u0001B`\r\u001d\u0011I\b\u0001\u0001c\u0005wB!B!\u0010=\u0005\u0003\u0005\u000b\u0011\u0002B \u0011)\ty\u0007\u0010B\u0001B\u0003%!1\u0011\u0005\u000b\u0003gb$\u0011!Q\u0001\n\t\r\u0005BCA<y\t\u0005\t\u0015!\u0003\u0003\u0004\"Q\u00111\u0010\u001f\u0003\u0002\u0003\u0006IAa!\t\u0015\u0005}DH!A!\u0002\u0013\u0011\u0019\t\u0003\u0006\u0002\u0004r\u0012\t\u0011)A\u0005\u0005\u0007C!\"a\"=\u0005\u0003\u0005\u000b\u0011\u0002BB\u0011)\tY\t\u0010B\u0001B\u0003%!1\u0011\u0005\u000b\u0003\u001fc$\u0011!Q\u0001\n\t\r\u0005BCAJy\t\u0005\t\u0015!\u0003\u0003\u0004\"Q\u0011q\u0013\u001f\u0003\u0002\u0003\u0006IAa!\t\radD\u0011\u0001BE\u0011\u001d\u0011\u0019\u000b\u0010C\t\u0005KCqA!-=\t#\u0011\u0019\fC\u0004\u0003:r\"\tA!\u001b\u0007\u000f\t\r\u0007\u0001\u00011\u0003F\"Q!1K\'\u0003\u0006\u0004%\tA!4\t\u0015\t=WJ!A!\u0002\u0013\u0011)\u0006\u0003\u0006\u0003>5\u0013)\u0019!C\u0001\u0005#D!Ba5N\u0005\u0003\u0005\u000b\u0011\u0002B \u0011\u0019AX\n\"\u0001\u0003V\"9!1\\\'\u0005\n\tu\u0007b\u0002Bt\u001b\u0012%!\u0011\u001e\u0005\b\u0005_lE\u0011\u0001By\u0011%\u0011i0\u0014b\u0001\n\u0013\u0011y\u0010\u0003\u0005\u0004\u00145\u0003\u000b\u0011BB\u0001\r\u0019\u0019\u0019#\u0014\u0003\u0004&!Q!\u0011\n-\u0003\u0002\u0003\u0006IAa\u0013\t\u0015\r5\u0002L!A!\u0002\u0013\u0019y\u0003\u0003\u0004y1\u0012\u00051\u0011\u0007\u0005\b\u0007wAF\u0011AB\u001f\u0011\u001d\u0019I\u0006\u0017C!\u00077BqA!/Y\t\u0003\u0011IG\u0001\nTG\u0006d\u0017\rV3ti\u001a\u0013\u0018-\\3x_J\\\'BA1c\u0003\u0015!xn\u001c7t\u0015\t\u0019G-A\u0005tG\u0006d\u0017\r^3ti*\tQ-A\u0002pe\u001e\u001c\u0001aE\u0002\u0001QB\u0004\"!\u001b8\u000e\u0003)T!a\u001b7\u0002\t1\fgn\u001a\u0006\u0002[\u0006!!.\u0019<b\u0013\ty\'N\u0001\u0004PE*,7\r\u001e\t\u0003cZl\u0011A\u001d\u0006\u0003gR\fq\u0001^3ti&twM\u0003\u0002vI\u0006Q1oY1mCR|w\u000e\\:\n\u0005]\u0014(!\u0003$sC6,wo\u001c:l\u0003\u0019a\u0014N\\5u}Q\t!\u0010\u0005\u0002|\u00015\t\u0001-\u0001\u0003oC6,G#\u0001@\u0011\u0005%|\u0018bAA\u0001U\n11\u000b\u001e:j]\u001e\fQ\u0001^3tiN$\"!a\u0002\u0011\r\u0005%\u0011qBA\n\u001b\t\tYA\u0003\u0002\u0002\u000e\u0005)1oY1mC&!\u0011\u0011CA\u0006\u0005\u0015\t%O]1z!\r\t\u0018QC\u0005\u0004\u0003/\u0011(a\u0003$j]\u001e,\'\u000f\u001d:j]R\f\u0011BU;o\u0007>tg-[4\u0011\u0007\u0005uQ!D\u0001\u0001\u0005%\u0011VO\\\"p]\u001aLwmE\u0002\u0006\u0003G\u0001B!!\u0003\u0002&%!\u0011qEA\u0006\u0005\u0019\te.\u001f*fMR\u0011\u00111D\u0001\te\u0016\u0004xN\u001d;feV\u0011\u0011q\u0006\t\u0007\u0003c\ty$a\u0011\u000e\u0005\u0005M\"\u0002BA\u001b\u0003o\ta!\u0019;p[&\u001c\'\u0002BA\u001d\u0003w\t!bY8oGV\u0014(/\u001a8u\u0015\r\ti\u0004\\\u0001\u0005kRLG.\u0003\u0003\u0002B\u0005M\"aD!u_6L7MU3gKJ,gnY3\u0011\r\u0005%\u0011QIA%\u0013\u0011\t9%a\u0003\u0003\r=\u0003H/[8o!\u0011\tY%!\u0014\u000e\u0003\tL1!a\u0014c\u0005A!\u0015n\u001d9bi\u000eD\'+\u001a9peR,\'/A\u0005sKB|\'\u000f^3sA\u0005y!/\u001a9peR,\'oQ8oM&<7/\u0006\u0002\u0002XA1\u0011\u0011GA \u00033\u0002b!!\u0003\u0002F\u0005m\u0003cA>\u0002^%\u0019\u0011q\f1\u0003-I+\u0007o\u001c:uKJ\u001cuN\u001c4jOV\u0014\u0018\r^5p]N\f\u0001C]3q_J$XM]\"p]\u001aLwm\u001d\u0011\u0002\u0013U\u001cXm\u0015;e_V$XCAA4!\u0011\t\t$!\u001b\n\t\u0005-\u00141\u0007\u0002\u000e\u0003R|W.[2C_>dW-\u00198\u0002\u0015U\u001cXm\u0015;e_V$\b%A\nqe\u0016\u001cXM\u001c;BY2$UO]1uS>t7/\u0001\u000bqe\u0016\u001cXM\u001c;BY2$UO]1uS>t7\u000fI\u0001\u000faJ,7/\u001a8u\u0013:\u001cu\u000e\\8s\u0003=\u0001(/Z:f]RLenQ8m_J\u0004\u0013a\u00069sKN,g\u000e^*i_J$8\u000b^1dWR\u0013\u0018mY3t\u0003a\u0001(/Z:f]R\u001c\u0006n\u001c:u\'R\f7m\u001b+sC\u000e,7\u000fI\u0001\u0017aJ,7/\u001a8u\rVdGn\u0015;bG.$&/Y2fg\u00069\u0002O]3tK:$h)\u001e7m\'R\f7m\u001b+sC\u000e,7\u000fI\u0001\u0013aJ,7/\u001a8u+:4wN]7biR,G-A\nqe\u0016\u001cXM\u001c;V]\u001a|\'/\\1ui\u0016$\u0007%A\bqe\u0016\u001cXM\u001c;SK6Lg\u000eZ3s\u0003A\u0001(/Z:f]R\u0014V-\\5oI\u0016\u0014\b%A\u0012qe\u0016\u001cXM\u001c;SK6Lg\u000eZ3s/&$\bn\u00155peR\u001cF/Y2l)J\f7-Z:\u0002IA\u0014Xm]3oiJ+W.\u001b8eKJ<\u0016\u000e\u001e5TQ>\u0014Ho\u0015;bG.$&/Y2fg\u0002\n!\u0005\u001d:fg\u0016tGOU3nS:$WM],ji\"4U\u000f\u001c7Ti\u0006\u001c7\u000e\u0016:bG\u0016\u001c\u0018a\t9sKN,g\u000e\u001e*f[&tG-\u001a:XSRDg)\u001e7m\'R\f7m\u001b+sC\u000e,7\u000fI\u0001$aJ,7/\u001a8u%\u0016l\u0017N\u001c3fe^KG\u000f[8vi\u000e\u000bgnY3mK\u0012$Vm\u001d;t\u0003\u0011\u0002(/Z:f]R\u0014V-\\5oI\u0016\u0014x+\u001b;i_V$8)\u00198dK2,G\rV3tiN\u0004\u0013a\u00059sKN,g\u000e\u001e$jY\u0016\u0004\u0016\r\u001e5oC6,\u0017\u0001\u00069sKN,g\u000e\u001e$jY\u0016\u0004\u0016\r\u001e5oC6,\u0007%A\u0006qe\u0016\u001cXM\u001c;Kg>t\u0017\u0001\u00049sKN,g\u000e\u001e&t_:\u0004\u0013A\u00024jYR,\'/\u0006\u0002\u0002 B1\u0011\u0011GA \u0003C\u0003b!!\u0003\u0002F\u0005\r\u0006\u0003BA&\u0003KK1!a*c\u0005\u00191\u0015\u000e\u001c;fe\u00069a-\u001b7uKJ\u0004\u0013!C2p]\u001aLw-T1q+\t\ty\u000b\u0005\u0004\u00022\u0005}\u0012\u0011\u0017\t\u0007\u0003\u0013\t)%a-\u0011\t\u0005-\u0013QW\u0005\u0004\u0003o\u0013\'!C\"p]\u001aLw-T1q\u0003)\u0019wN\u001c4jO6\u000b\u0007\u000fI\u0001\f[\u0016l\'-\u001a:t\u001f:d\u00170\u0006\u0002\u0002@B1\u0011\u0011GA \u0003\u0003\u0004b!!\u0003\u0002F\u0005\r\u0007CBAc\u0003+\fYN\u0004\u0003\u0002H\u0006Eg\u0002BAe\u0003\u001fl!!a3\u000b\u0007\u00055g-\u0001\u0004=e>|GOP\u0005\u0003\u0003\u001bIA!a5\u0002\f\u00059\u0001/Y2lC\u001e,\u0017\u0002BAl\u00033\u0014A\u0001T5ti*!\u00111[A\u0006!\u0011\ti.!:\u000f\t\u0005}\u0017\u0011\u001d\t\u0005\u0003\u0013\fY!\u0003\u0003\u0002d\u0006-\u0011A\u0002)sK\u0012,g-\u0003\u0003\u0002\u0002\u0005\u001d(\u0002BAr\u0003\u0017\tA\"\\3nE\u0016\u00148o\u00148ms\u0002\n\u0001b^5mI\u000e\f\'\u000fZ\u0001\no&dGmY1sI\u0002\nq\u0002Z3uK\u000e$8\u000b\\8xa>\\Wm]\u0001\u0011I\u0016$Xm\u0019;TY><\bo\\6fg\u0002\nac\u001d7poB|7.\u001a#fi\u0016\u001cG/[8o\t\u0016d\u0017-_\u000b\u0003\u0003o\u0004B!!\r\u0002z&!\u00111`A\u001a\u0005)\tEo\\7jG2{gnZ\u0001\u0018g2|w\u000f]8lK\u0012+G/Z2uS>tG)\u001a7bs\u0002\nqc\u001d7poB|7.\u001a#fi\u0016\u001cG/[8o!\u0016\u0014\u0018n\u001c3\u00021Mdwn\u001e9pW\u0016$U\r^3di&|g\u000eU3sS>$\u0007%\u0001\u000euKN$8k\u001c:uS:<\'+\u001a9peR,\'\u000fV5nK>,H/\u0006\u0002\u0003\bA1\u0011\u0011GA \u0005\u0013\u0001b!!\u0003\u0002F\t-\u0001\u0003\u0002B\u0007\u0005\'i!Aa\u0004\u000b\u0007\tE!-\u0001\u0003uS6,\u0017\u0002\u0002B\u000b\u0005\u001f\u0011Aa\u00159b]\u0006YB/Z:u\'>\u0014H/\u001b8h%\u0016\u0004xN\u001d;feRKW.Z8vi\u0002\nAB]3tk2$\bj\u001c7eKJ,\"A!\b\u0011\u0007m\u0014y\"C\u0002\u0003\"\u0001\u0014\u0011cU;ji\u0016\u0014Vm];mi\"{G\u000eZ3s\u00035\u0011Xm];mi\"{G\u000eZ3sA\u0005\tr-\u001a;D_:4\u0017nZ;sCRLwN\\:\u0015\u0015\t%\"Q\u0007B\u001e\u0005\u000f\u0012\t\u0006\u0005\t\u0002\n\t-\"qFAR\u0003g\u000b\u0019-a1\u0003\f%!!QFA\u0006\u0005\u0019!V\u000f\u001d7fmA\u00191P!\r\n\u0007\tM\u0002MA\nTER$\u0015n\u001d9bi\u000eD\'+\u001a9peR,\'\u000fC\u0004\u00038U\u0002\rA!\u000f\u0002\t\u0005\u0014xm\u001d\t\u0007\u0003\u0013\ty!a7\t\u000f\tuR\u00071\u0001\u0003@\u00059An\\4hKJ\u001c\bCBA\u0005\u0003\u001f\u0011\t\u0005E\u0002r\u0005\u0007J1A!\u0012s\u0005\u0019aunZ4fe\"9!\u0011J\u001bA\u0002\t-\u0013\u0001D3wK:$\b*\u00198eY\u0016\u0014\bcA9\u0003N%\u0019!q\n:\u0003\u0019\u00153XM\u001c;IC:$G.\u001a:\t\u000f\tMS\u00071\u0001\u0003V\u0005QA/Z:u\u0019>\fG-\u001a:\u0011\u0007%\u00149&C\u0002\u0003Z)\u00141b\u00117bgNdu.\u00193fe\u0006Y\u0011\r^8nS\u000e\u001cu.\u001e8u+\t\u0011y\u0006\u0005\u0003\u00022\t\u0005\u0014\u0002\u0002B2\u0003g\u0011Q\"\u0011;p[&\u001c\u0017J\u001c;fO\u0016\u0014\u0018\u0001D1u_6L7mQ8v]R\u0004\u0013!D5oGJ,\u0017m]3MCR\u001c\u0007\u000e\u0006\u0002\u0003lA!\u0011\u0011\u0002B7\u0013\u0011\u0011y\'a\u0003\u0003\tUs\u0017\u000e^\u0001\u000eI\u0016\u001c\'/Z1tK2\u000bGo\u00195\u00021\r\u0014X-\u0019;f\'\n$Hj\\4J]\u001a|\'+\u001a9peR,\'\u000f\u0006\u0003\u0003x\tm\u0006cAA\u000fy\t\u00112K\u0019;M_\u001eLeNZ8SKB|\'\u000f^3s\'\ra$Q\u0010\t\u0004w\n}\u0014b\u0001BAA\nq1\u000b\u001e:j]\u001e\u0014V\r]8si\u0016\u0014\b\u0003BA\u0005\u0005\u000bKAAa\"\u0002\f\t9!i\\8mK\u0006tGC\u0007B<\u0005\u0017\u0013iIa$\u0003\u0012\nM%Q\u0013BL\u00053\u0013YJ!(\u0003 \n\u0005\u0006b\u0002B\u001f\u0013\u0002\u0007!q\b\u0005\b\u0003_J\u0005\u0019\u0001BB\u0011\u001d\t\u0019(\u0013a\u0001\u0005\u0007Cq!a\u001eJ\u0001\u0004\u0011\u0019\tC\u0004\u0002|%\u0003\rAa!\t\u000f\u0005}\u0014\n1\u0001\u0003\u0004\"9\u00111Q%A\u0002\t\r\u0005bBAD\u0013\u0002\u0007!1\u0011\u0005\b\u0003\u0017K\u0005\u0019\u0001BB\u0011\u001d\ty)\u0013a\u0001\u0005\u0007Cq!a%J\u0001\u0004\u0011\u0019\tC\u0004\u0002\u0018&\u0003\rAa!\u0002)A\u0014\u0018N\u001c;Q_N\u001c\u0018N\u00197z\u0013:\u001cu\u000e\\8s)\u0011\u0011YGa*\t\u000f\t%&\n1\u0001\u0003,\u0006AaM]1h[\u0016tG\u000fE\u0002|\u0005[K1Aa,a\u0005!1%/Y4nK:$\u0018\u0001\u00049sS:$hj\\\"pY>\u0014H\u0003\u0002B6\u0005kCqAa.L\u0001\u0004\tY.\u0001\u0003uKb$\u0018a\u00023jgB|7/\u001a\u0005\b\u0005{Q\u0004\u0019\u0001B \u0003)!Xm\u001d;Sk:tWM\u001d\u000b\u0007\u0005\u0003\u001ciga\u001c\u0011\u0007\u0005uQJA\bTG\u0006d\u0017\rV3tiJ+hN\\3s\'\ri%q\u0019\t\u0004c\n%\u0017b\u0001Bfe\n9!+\u001e8oKJ\u0014TC\u0001B+\u0003-!Xm\u001d;M_\u0006$WM\u001d\u0011\u0016\u0005\t}\u0012\u0001\u00037pO\u001e,\'o\u001d\u0011\u0015\r\t\u0005\'q\u001bBm\u0011\u001d\u0011\u0019F\u0015a\u0001\u0005+BqA!\u0010S\u0001\u0004\u0011y$\u0001\bgS2$XM],jY\u0012\u001c\u0017M\u001d3\u0015\r\t\r%q\u001cBr\u0011\u001d\u0011\to\u0015a\u0001\u0003\u0007\fQ\u0001]1uQNDqA!:T\u0001\u0004\tY.A\u0007uKN$8\t\\1tg:\u000bW.Z\u0001\u0012M&dG/\u001a:NK6\u0014WM]:P]2LHC\u0002BB\u0005W\u0014i\u000fC\u0004\u0003bR\u0003\r!a1\t\u000f\t\u0015H\u000b1\u0001\u0002\\\u0006\u0019!/\u001e8\u0015\u0015\t-$1\u001fB{\u0005s\u0014Y\u0010C\u0004\u0003fV\u0003\r!a7\t\u000f\t]X\u000b1\u0001\u0002\u0014\u0005Ya-\u001b8hKJ\u0004(/\u001b8u\u0011\u001d\u0011I%\u0016a\u0001\u0005\u0017BqAa\u000eV\u0001\u0004\u0011I$A\bf[B$\u0018p\u00117bgN\f%O]1z+\t\u0019\t\u0001\u0005\u0004\u0002\n\u0005=11\u0001\u0019\u0005\u0007\u000b\u0019y\u0001E\u0003j\u0007\u000f\u0019Y!C\u0002\u0004\n)\u0014Qa\u00117bgN\u0004Ba!\u0004\u0004\u00101\u0001AaCB\t/\u0006\u0005\t\u0011!B\u0001\u0007+\u00111a\u0018\u00133\u0003A)W\u000e\u001d;z\u00072\f7o]!se\u0006L\b%\u0005\u0003\u0004\u0018\ru\u0001\u0003BA\u0005\u00073IAaa\u0007\u0002\f\t9aj\u001c;iS:<\u0007\u0003BA\u0005\u0007?IAa!\t\u0002\f\t\u0019\u0011I\\=\u0003\u0017M\u0013GOU3q_J$XM]\n\u00061\u0006\r2q\u0005\t\u0005\u0003\u0017\u001aI#C\u0002\u0004,\t\u0014\u0001BU3q_J$XM]\u0001\u0007e\u0016\u0004xN\u001d;\u0011\r\u0005%\u0011QIB\u0014)\u0019\u0019\u0019da\u000e\u0004:A\u00191Q\u0007-\u000e\u00035CqA!\u0013\\\u0001\u0004\u0011Y\u0005C\u0004\u0004.m\u0003\raa\f\u0002\u0013\u0019L\'/Z#wK:$H\u0003\u0003B6\u0007\u007f\u0019\u0019e!\u0014\t\u000f\r\u0005C\f1\u0001\u0002\\\u0006\u0011AO\u001c\u0005\b\u0007\u000bb\u0006\u0019AB$\u0003\u0005\u0011\bcA9\u0004J%\u001911\n:\u0003\rI+7/\u001e7u\u0011\u001d\u0019y\u0005\u0018a\u0001\u0007#\n\u0011!\u001a\t\u0007\u0003\u0013\t)ea\u0015\u0011\t\u0005\u00157QK\u0005\u0005\u0007/\nINA\u0005UQJ|w/\u00192mK\u0006)\u0011\r\u001d9msR!!1NB/\u0011\u001d\u0019y&\u0018a\u0001\u0007C\nQ!\u001a<f]R\u0004Baa\u0019\u0004j5\u00111Q\r\u0006\u0004\u0007O\u0012\u0017AB3wK:$8/\u0003\u0003\u0004l\r\u0015$!B#wK:$\bb\u0002B*w\u0001\u0007!Q\u000b\u0005\b\u0005{Y\u0004\u0019\u0001B \u0001"
    )
  ScalaInlineInfo: length = 0x27 (unknown attribute)
   01 00 00 07 00 2C 00 1F 00 00 1A 00 1B 01 00 1E
   00 1F 01 00 24 00 25 00 00 35 00 36 00 00 35 00
   3E 00 00 28 00 29 00
  ScalaSig: length = 0x3 (unknown attribute)
   05 02 00
