Classfile /Users/mw/Projects/slang-braindump/.jar/jar11/assemble/slang-braindump/assemble/content/org/scalatest/tools/StoppingState.class
  Last modified May 29, 2022; size 1263 bytes
  SHA-256 checksum 708b609dec058bcdda3a117a6a005ababdbad739dc7281c40c7d7cb64d71bc6b
  Compiled from "RunnerGUIState.scala"
public final class org.scalatest.tools.StoppingState
  minor version: 0
  major version: 52
  flags: (0x0031) ACC_PUBLIC, ACC_FINAL, ACC_SUPER
  this_class: #2                          // org/scalatest/tools/StoppingState
  super_class: #4                         // java/lang/Object
  interfaces: 0, fields: 0, methods: 4, attributes: 3
Constant pool:
   #1 = Utf8               org/scalatest/tools/StoppingState
   #2 = Class              #1             // org/scalatest/tools/StoppingState
   #3 = Utf8               java/lang/Object
   #4 = Class              #3             // java/lang/Object
   #5 = Utf8               RunnerGUIState.scala
   #6 = Utf8               Lscala/reflect/ScalaSignature;
   #7 = Utf8               bytes
   #8 = Utf8               \u0006\u00059:aa\u0002\u0005\t\u0002)qaA\u0002\t\t\u0011\u0003Q\u0011\u0003C\u0003\u001c\u0003\u0011\u0005Q\u0004C\u0003\u001f\u0003\u0011\u0005q\u0004C\u0003&\u0003\u0011\u0005a\u0005C\u0003)\u0003\u0011\u0005\u0011\u0006C\u0003,\u0003\u0011\u0005A&A\u0007Ti>\u0004\b/\u001b8h\'R\fG/\u001a\u0006\u0003\u0013)\tQ\u0001^8pYNT!a\u0003\u0007\u0002\u0013M\u001c\u0017\r\\1uKN$(\"A\u0007\u0002\u0007=\u0014x\r\u0005\u0002\u0010\u00035\t\u0001BA\u0007Ti>\u0004\b/\u001b8h\'R\fG/Z\n\u0004\u0003IA\u0002CA\n\u0017\u001b\u0005!\"\"A\u000b\u0002\u000bM\u001c\u0017\r\\1\n\u0005]!\"AB!osJ+g\r\u0005\u0002\u00103%\u0011!\u0004\u0003\u0002\u000f%Vtg.\u001a:H+&\u001bF/\u0019;f\u0003\u0019a\u0014N\\5u}\r\u0001A#\u0001\b\u0002!I,hNQ;ui>t\u0007K]3tg\u0016$GC\u0001\r!\u0011\u0015\t3\u00011\u0001#\u0003%\u0011XO\u001c8fe\u001e+\u0016\n\u0005\u0002\u0010G%\u0011A\u0005\u0003\u0002\n%Vtg.\u001a:H+&\u000b!C]3sk:\u0014U\u000f\u001e;p]B\u0013Xm]:fIR\u0011\u0001d\n\u0005\u0006C\u0011\u0001\rAI\u0001\u0015Y&\u001cHoU3mK\u000e$\u0018n\u001c8DQ\u0006tw-\u001a3\u0015\u0005aQ\u0003\"B\u0011\u0006\u0001\u0004\u0011\u0013a\u0003:v]\u001aKg.[:iK\u0012$\"\u0001G\u0017\t\u000b\u00052\u0001\u0019\u0001\u0012
   #9 = Utf8               runFinished
  #10 = Utf8               (Lorg/scalatest/tools/RunnerGUI;)Lorg/scalatest/tools/RunnerGUIState;
  #11 = Utf8               runnerGUI
  #12 = Utf8               org/scalatest/tools/StoppingState$
  #13 = Class              #12            // org/scalatest/tools/StoppingState$
  #14 = Utf8               MODULE$
  #15 = Utf8               Lorg/scalatest/tools/StoppingState$;
  #16 = NameAndType        #14:#15        // MODULE$:Lorg/scalatest/tools/StoppingState$;
  #17 = Fieldref           #13.#16        // org/scalatest/tools/StoppingState$.MODULE$:Lorg/scalatest/tools/StoppingState$;
  #18 = NameAndType        #9:#10         // runFinished:(Lorg/scalatest/tools/RunnerGUI;)Lorg/scalatest/tools/RunnerGUIState;
  #19 = Methodref          #13.#18        // org/scalatest/tools/StoppingState$.runFinished:(Lorg/scalatest/tools/RunnerGUI;)Lorg/scalatest/tools/RunnerGUIState;
  #20 = Utf8               Lorg/scalatest/tools/RunnerGUI;
  #21 = Utf8               listSelectionChanged
  #22 = NameAndType        #21:#10        // listSelectionChanged:(Lorg/scalatest/tools/RunnerGUI;)Lorg/scalatest/tools/RunnerGUIState;
  #23 = Methodref          #13.#22        // org/scalatest/tools/StoppingState$.listSelectionChanged:(Lorg/scalatest/tools/RunnerGUI;)Lorg/scalatest/tools/RunnerGUIState;
  #24 = Utf8               rerunButtonPressed
  #25 = NameAndType        #24:#10        // rerunButtonPressed:(Lorg/scalatest/tools/RunnerGUI;)Lorg/scalatest/tools/RunnerGUIState;
  #26 = Methodref          #13.#25        // org/scalatest/tools/StoppingState$.rerunButtonPressed:(Lorg/scalatest/tools/RunnerGUI;)Lorg/scalatest/tools/RunnerGUIState;
  #27 = Utf8               runButtonPressed
  #28 = NameAndType        #27:#10        // runButtonPressed:(Lorg/scalatest/tools/RunnerGUI;)Lorg/scalatest/tools/RunnerGUIState;
  #29 = Methodref          #13.#28        // org/scalatest/tools/StoppingState$.runButtonPressed:(Lorg/scalatest/tools/RunnerGUI;)Lorg/scalatest/tools/RunnerGUIState;
  #30 = Utf8               Code
  #31 = Utf8               LocalVariableTable
  #32 = Utf8               MethodParameters
  #33 = Utf8               SourceFile
  #34 = Utf8               RuntimeVisibleAnnotations
  #35 = Utf8               ScalaSig
{
  public static org.scalatest.tools.RunnerGUIState runFinished(org.scalatest.tools.RunnerGUI);
    descriptor: (Lorg/scalatest/tools/RunnerGUI;)Lorg/scalatest/tools/RunnerGUIState;
    flags: (0x0009) ACC_PUBLIC, ACC_STATIC
    Code:
      stack=2, locals=1, args_size=1
         0: getstatic     #17                 // Field org/scalatest/tools/StoppingState$.MODULE$:Lorg/scalatest/tools/StoppingState$;
         3: aload_0
         4: invokevirtual #19                 // Method org/scalatest/tools/StoppingState$.runFinished:(Lorg/scalatest/tools/RunnerGUI;)Lorg/scalatest/tools/RunnerGUIState;
         7: areturn
      LocalVariableTable:
        Start  Length  Slot  Name   Signature
            0       8     0 runnerGUI   Lorg/scalatest/tools/RunnerGUI;
    MethodParameters:
      Name                           Flags
      runnerGUI                      final

  public static org.scalatest.tools.RunnerGUIState listSelectionChanged(org.scalatest.tools.RunnerGUI);
    descriptor: (Lorg/scalatest/tools/RunnerGUI;)Lorg/scalatest/tools/RunnerGUIState;
    flags: (0x0009) ACC_PUBLIC, ACC_STATIC
    Code:
      stack=2, locals=1, args_size=1
         0: getstatic     #17                 // Field org/scalatest/tools/StoppingState$.MODULE$:Lorg/scalatest/tools/StoppingState$;
         3: aload_0
         4: invokevirtual #23                 // Method org/scalatest/tools/StoppingState$.listSelectionChanged:(Lorg/scalatest/tools/RunnerGUI;)Lorg/scalatest/tools/RunnerGUIState;
         7: areturn
      LocalVariableTable:
        Start  Length  Slot  Name   Signature
            0       8     0 runnerGUI   Lorg/scalatest/tools/RunnerGUI;
    MethodParameters:
      Name                           Flags
      runnerGUI                      final

  public static org.scalatest.tools.RunnerGUIState rerunButtonPressed(org.scalatest.tools.RunnerGUI);
    descriptor: (Lorg/scalatest/tools/RunnerGUI;)Lorg/scalatest/tools/RunnerGUIState;
    flags: (0x0009) ACC_PUBLIC, ACC_STATIC
    Code:
      stack=2, locals=1, args_size=1
         0: getstatic     #17                 // Field org/scalatest/tools/StoppingState$.MODULE$:Lorg/scalatest/tools/StoppingState$;
         3: aload_0
         4: invokevirtual #26                 // Method org/scalatest/tools/StoppingState$.rerunButtonPressed:(Lorg/scalatest/tools/RunnerGUI;)Lorg/scalatest/tools/RunnerGUIState;
         7: areturn
      LocalVariableTable:
        Start  Length  Slot  Name   Signature
            0       8     0 runnerGUI   Lorg/scalatest/tools/RunnerGUI;
    MethodParameters:
      Name                           Flags
      runnerGUI                      final

  public static org.scalatest.tools.RunnerGUIState runButtonPressed(org.scalatest.tools.RunnerGUI);
    descriptor: (Lorg/scalatest/tools/RunnerGUI;)Lorg/scalatest/tools/RunnerGUIState;
    flags: (0x0009) ACC_PUBLIC, ACC_STATIC
    Code:
      stack=2, locals=1, args_size=1
         0: getstatic     #17                 // Field org/scalatest/tools/StoppingState$.MODULE$:Lorg/scalatest/tools/StoppingState$;
         3: aload_0
         4: invokevirtual #29                 // Method org/scalatest/tools/StoppingState$.runButtonPressed:(Lorg/scalatest/tools/RunnerGUI;)Lorg/scalatest/tools/RunnerGUIState;
         7: areturn
      LocalVariableTable:
        Start  Length  Slot  Name   Signature
            0       8     0 runnerGUI   Lorg/scalatest/tools/RunnerGUI;
    MethodParameters:
      Name                           Flags
      runnerGUI                      final
}
SourceFile: "RunnerGUIState.scala"
RuntimeVisibleAnnotations:
  0: #6(#7=s#8)
    scala.reflect.ScalaSignature(
      bytes="\u0006\u00059:aa\u0002\u0005\t\u0002)qaA\u0002\t\t\u0011\u0003Q\u0011\u0003C\u0003\u001c\u0003\u0011\u0005Q\u0004C\u0003\u001f\u0003\u0011\u0005q\u0004C\u0003&\u0003\u0011\u0005a\u0005C\u0003)\u0003\u0011\u0005\u0011\u0006C\u0003,\u0003\u0011\u0005A&A\u0007Ti>\u0004\b/\u001b8h\'R\fG/\u001a\u0006\u0003\u0013)\tQ\u0001^8pYNT!a\u0003\u0007\u0002\u0013M\u001c\u0017\r\\1uKN$(\"A\u0007\u0002\u0007=\u0014x\r\u0005\u0002\u0010\u00035\t\u0001BA\u0007Ti>\u0004\b/\u001b8h\'R\fG/Z\n\u0004\u0003IA\u0002CA\n\u0017\u001b\u0005!\"\"A\u000b\u0002\u000bM\u001c\u0017\r\\1\n\u0005]!\"AB!osJ+g\r\u0005\u0002\u00103%\u0011!\u0004\u0003\u0002\u000f%Vtg.\u001a:H+&\u001bF/\u0019;f\u0003\u0019a\u0014N\\5u}\r\u0001A#\u0001\b\u0002!I,hNQ;ui>t\u0007K]3tg\u0016$GC\u0001\r!\u0011\u0015\t3\u00011\u0001#\u0003%\u0011XO\u001c8fe\u001e+\u0016\n\u0005\u0002\u0010G%\u0011A\u0005\u0003\u0002\n%Vtg.\u001a:H+&\u000b!C]3sk:\u0014U\u000f\u001e;p]B\u0013Xm]:fIR\u0011\u0001d\n\u0005\u0006C\u0011\u0001\rAI\u0001\u0015Y&\u001cHoU3mK\u000e$\u0018n\u001c8DQ\u0006tw-\u001a3\u0015\u0005aQ\u0003\"B\u0011\u0006\u0001\u0004\u0011\u0013a\u0003:v]\u001aKg.[:iK\u0012$\"\u0001G\u0017\t\u000b\u00052\u0001\u0019\u0001\u0012"
    )
  ScalaSig: length = 0x3 (unknown attribute)
   05 02 00
