Classfile /Users/mw/Projects/slang-braindump/.jar/jar11/assemble/slang-braindump/assemble/content/org/scalatest/tools/SuiteSortingReporter$Slot.class
  Last modified May 29, 2022; size 5098 bytes
  SHA-256 checksum bef64756d15e4eb9da267152fbe48429a3ab8412a6c8b924bae4375ab96fece9
  Compiled from "SuiteSortingReporter.scala"
public class org.scalatest.tools.SuiteSortingReporter$Slot implements scala.Product,java.io.Serializable
  minor version: 0
  major version: 52
  flags: (0x0021) ACC_PUBLIC, ACC_SUPER
  this_class: #2                          // org/scalatest/tools/SuiteSortingReporter$Slot
  super_class: #4                         // java/lang/Object
  interfaces: 2, fields: 6, methods: 23, attributes: 4
Constant pool:
    #1 = Utf8               org/scalatest/tools/SuiteSortingReporter$Slot
    #2 = Class              #1            // org/scalatest/tools/SuiteSortingReporter$Slot
    #3 = Utf8               java/lang/Object
    #4 = Class              #3            // java/lang/Object
    #5 = Utf8               scala/Product
    #6 = Class              #5            // scala/Product
    #7 = Utf8               java/io/Serializable
    #8 = Class              #7            // java/io/Serializable
    #9 = Utf8               SuiteSortingReporter.scala
   #10 = Utf8               org/scalatest/tools/SuiteSortingReporter
   #11 = Class              #10           // org/scalatest/tools/SuiteSortingReporter
   #12 = Utf8               Slot
   #13 = Utf8               suiteId
   #14 = Utf8               Ljava/lang/String;
   #15 = Utf8               doneEvent
   #16 = Utf8               Lscala/Option;
   #17 = Utf8               Lscala/Option<Lorg/scalatest/events/Event;>;
   #18 = Utf8               includesDistributedTests
   #19 = Utf8               Z
   #20 = Utf8               testsCompleted
   #21 = Utf8               ready
   #22 = Utf8               $outer
   #23 = Utf8               Lorg/scalatest/tools/SuiteSortingReporter;
   #24 = Utf8               productElementNames
   #25 = Utf8               ()Lscala/collection/Iterator;
   #26 = Utf8               ()Lscala/collection/Iterator<Ljava/lang/String;>;
   #27 = Utf8               productElementNames$
   #28 = Utf8               (Lscala/Product;)Lscala/collection/Iterator;
   #29 = NameAndType        #27:#28       // productElementNames$:(Lscala/Product;)Lscala/collection/Iterator;
   #30 = InterfaceMethodref #6.#29        // scala/Product.productElementNames$:(Lscala/Product;)Lscala/collection/Iterator;
   #31 = Utf8               this
   #32 = Utf8               Lorg/scalatest/tools/SuiteSortingReporter$Slot;
   #33 = Utf8               ()Ljava/lang/String;
   #34 = NameAndType        #13:#14       // suiteId:Ljava/lang/String;
   #35 = Fieldref           #2.#34        // org/scalatest/tools/SuiteSortingReporter$Slot.suiteId:Ljava/lang/String;
   #36 = Utf8               ()Lscala/Option;
   #37 = Utf8               ()Lscala/Option<Lorg/scalatest/events/Event;>;
   #38 = NameAndType        #15:#16       // doneEvent:Lscala/Option;
   #39 = Fieldref           #2.#38        // org/scalatest/tools/SuiteSortingReporter$Slot.doneEvent:Lscala/Option;
   #40 = Utf8               ()Z
   #41 = NameAndType        #18:#19       // includesDistributedTests:Z
   #42 = Fieldref           #2.#41        // org/scalatest/tools/SuiteSortingReporter$Slot.includesDistributedTests:Z
   #43 = NameAndType        #20:#19       // testsCompleted:Z
   #44 = Fieldref           #2.#43        // org/scalatest/tools/SuiteSortingReporter$Slot.testsCompleted:Z
   #45 = NameAndType        #21:#19       // ready:Z
   #46 = Fieldref           #2.#45        // org/scalatest/tools/SuiteSortingReporter$Slot.ready:Z
   #47 = Utf8               copy
   #48 = Utf8               (Ljava/lang/String;Lscala/Option;ZZZ)Lorg/scalatest/tools/SuiteSortingReporter$Slot;
   #49 = Utf8               (Ljava/lang/String;Lscala/Option<Lorg/scalatest/events/Event;>;ZZZ)Lorg/scalatest/tools/SuiteSortingReporter$Slot;
   #50 = Utf8               org$scalatest$tools$SuiteSortingReporter$Slot$$$outer
   #51 = Utf8               ()Lorg/scalatest/tools/SuiteSortingReporter;
   #52 = NameAndType        #50:#51       // org$scalatest$tools$SuiteSortingReporter$Slot$$$outer:()Lorg/scalatest/tools/SuiteSortingReporter;
   #53 = Methodref          #2.#52        // org/scalatest/tools/SuiteSortingReporter$Slot.org$scalatest$tools$SuiteSortingReporter$Slot$$$outer:()Lorg/scalatest/tools/SuiteSortingReporter;
   #54 = Utf8               <init>
   #55 = Utf8               (Lorg/scalatest/tools/SuiteSortingReporter;Ljava/lang/String;Lscala/Option;ZZZ)V
   #56 = NameAndType        #54:#55       // "<init>":(Lorg/scalatest/tools/SuiteSortingReporter;Ljava/lang/String;Lscala/Option;ZZZ)V
   #57 = Methodref          #2.#56        // org/scalatest/tools/SuiteSortingReporter$Slot."<init>":(Lorg/scalatest/tools/SuiteSortingReporter;Ljava/lang/String;Lscala/Option;ZZZ)V
   #58 = Utf8               copy$default$1
   #59 = NameAndType        #13:#33       // suiteId:()Ljava/lang/String;
   #60 = Methodref          #2.#59        // org/scalatest/tools/SuiteSortingReporter$Slot.suiteId:()Ljava/lang/String;
   #61 = Utf8               copy$default$2
   #62 = NameAndType        #15:#36       // doneEvent:()Lscala/Option;
   #63 = Methodref          #2.#62        // org/scalatest/tools/SuiteSortingReporter$Slot.doneEvent:()Lscala/Option;
   #64 = Utf8               copy$default$3
   #65 = NameAndType        #18:#40       // includesDistributedTests:()Z
   #66 = Methodref          #2.#65        // org/scalatest/tools/SuiteSortingReporter$Slot.includesDistributedTests:()Z
   #67 = Utf8               copy$default$4
   #68 = NameAndType        #20:#40       // testsCompleted:()Z
   #69 = Methodref          #2.#68        // org/scalatest/tools/SuiteSortingReporter$Slot.testsCompleted:()Z
   #70 = Utf8               copy$default$5
   #71 = NameAndType        #21:#40       // ready:()Z
   #72 = Methodref          #2.#71        // org/scalatest/tools/SuiteSortingReporter$Slot.ready:()Z
   #73 = Utf8               productPrefix
   #74 = String             #12           // Slot
   #75 = Utf8               productArity
   #76 = Utf8               ()I
   #77 = Utf8               productElement
   #78 = Utf8               (I)Ljava/lang/Object;
   #79 = Utf8               x$1
   #80 = Utf8               scala/runtime/BoxesRunTime
   #81 = Class              #80           // scala/runtime/BoxesRunTime
   #82 = Utf8               boxToBoolean
   #83 = Utf8               (Z)Ljava/lang/Boolean;
   #84 = NameAndType        #82:#83       // boxToBoolean:(Z)Ljava/lang/Boolean;
   #85 = Methodref          #81.#84       // scala/runtime/BoxesRunTime.boxToBoolean:(Z)Ljava/lang/Boolean;
   #86 = Utf8               scala/runtime/Statics
   #87 = Class              #86           // scala/runtime/Statics
   #88 = Utf8               ioobe
   #89 = NameAndType        #88:#78       // ioobe:(I)Ljava/lang/Object;
   #90 = Methodref          #87.#89       // scala/runtime/Statics.ioobe:(I)Ljava/lang/Object;
   #91 = Utf8               I
   #92 = Utf8               productIterator
   #93 = Utf8               ()Lscala/collection/Iterator<Ljava/lang/Object;>;
   #94 = Utf8               scala/runtime/ScalaRunTime$
   #95 = Class              #94           // scala/runtime/ScalaRunTime$
   #96 = Utf8               MODULE$
   #97 = Utf8               Lscala/runtime/ScalaRunTime$;
   #98 = NameAndType        #96:#97       // MODULE$:Lscala/runtime/ScalaRunTime$;
   #99 = Fieldref           #95.#98       // scala/runtime/ScalaRunTime$.MODULE$:Lscala/runtime/ScalaRunTime$;
  #100 = Utf8               typedProductIterator
  #101 = NameAndType        #100:#28      // typedProductIterator:(Lscala/Product;)Lscala/collection/Iterator;
  #102 = Methodref          #95.#101      // scala/runtime/ScalaRunTime$.typedProductIterator:(Lscala/Product;)Lscala/collection/Iterator;
  #103 = Utf8               canEqual
  #104 = Utf8               (Ljava/lang/Object;)Z
  #105 = Utf8               Ljava/lang/Object;
  #106 = Utf8               productElementName
  #107 = Utf8               (I)Ljava/lang/String;
  #108 = String             #13           // suiteId
  #109 = String             #15           // doneEvent
  #110 = String             #18           // includesDistributedTests
  #111 = String             #20           // testsCompleted
  #112 = String             #21           // ready
  #113 = Utf8               java/lang/String
  #114 = Class              #113          // java/lang/String
  #115 = Utf8               hashCode
  #116 = Integer            -889275714
  #117 = NameAndType        #73:#33       // productPrefix:()Ljava/lang/String;
  #118 = Methodref          #2.#117       // org/scalatest/tools/SuiteSortingReporter$Slot.productPrefix:()Ljava/lang/String;
  #119 = NameAndType        #115:#76      // hashCode:()I
  #120 = Methodref          #114.#119     // java/lang/String.hashCode:()I
  #121 = Utf8               mix
  #122 = Utf8               (II)I
  #123 = NameAndType        #121:#122     // mix:(II)I
  #124 = Methodref          #87.#123      // scala/runtime/Statics.mix:(II)I
  #125 = Utf8               anyHash
  #126 = Utf8               (Ljava/lang/Object;)I
  #127 = NameAndType        #125:#126     // anyHash:(Ljava/lang/Object;)I
  #128 = Methodref          #87.#127      // scala/runtime/Statics.anyHash:(Ljava/lang/Object;)I
  #129 = Utf8               finalizeHash
  #130 = NameAndType        #129:#122     // finalizeHash:(II)I
  #131 = Methodref          #87.#130      // scala/runtime/Statics.finalizeHash:(II)I
  #132 = Utf8               toString
  #133 = Utf8               _toString
  #134 = Utf8               (Lscala/Product;)Ljava/lang/String;
  #135 = NameAndType        #133:#134     // _toString:(Lscala/Product;)Ljava/lang/String;
  #136 = Methodref          #95.#135      // scala/runtime/ScalaRunTime$._toString:(Lscala/Product;)Ljava/lang/String;
  #137 = Utf8               equals
  #138 = NameAndType        #137:#104     // equals:(Ljava/lang/Object;)Z
  #139 = Methodref          #4.#138       // java/lang/Object.equals:(Ljava/lang/Object;)Z
  #140 = NameAndType        #103:#104     // canEqual:(Ljava/lang/Object;)Z
  #141 = Methodref          #2.#140       // org/scalatest/tools/SuiteSortingReporter$Slot.canEqual:(Ljava/lang/Object;)Z
  #142 = Utf8               scala/Option
  #143 = Class              #142          // scala/Option
  #144 = NameAndType        #22:#23       // $outer:Lorg/scalatest/tools/SuiteSortingReporter;
  #145 = Fieldref           #2.#144       // org/scalatest/tools/SuiteSortingReporter$Slot.$outer:Lorg/scalatest/tools/SuiteSortingReporter;
  #146 = Utf8               (Ljava/lang/String;Lscala/Option<Lorg/scalatest/events/Event;>;ZZZ)V
  #147 = Utf8               ()V
  #148 = NameAndType        #54:#147      // "<init>":()V
  #149 = Methodref          #4.#148       // java/lang/Object."<init>":()V
  #150 = Utf8               $init$
  #151 = Utf8               (Lscala/Product;)V
  #152 = NameAndType        #150:#151     // $init$:(Lscala/Product;)V
  #153 = InterfaceMethodref #6.#152       // scala/Product.$init$:(Lscala/Product;)V
  #154 = Utf8               Signature
  #155 = Utf8               Code
  #156 = Utf8               LineNumberTable
  #157 = Utf8               LocalVariableTable
  #158 = Utf8               MethodParameters
  #159 = Utf8               StackMapTable
  #160 = Utf8               InnerClasses
  #161 = Utf8               SourceFile
  #162 = Utf8               ScalaInlineInfo
  #163 = Utf8               Scala
{
  private final java.lang.String suiteId;
    descriptor: Ljava/lang/String;
    flags: (0x0012) ACC_PRIVATE, ACC_FINAL

  private final scala.Option<org.scalatest.events.Event> doneEvent;
    descriptor: Lscala/Option;
    flags: (0x0012) ACC_PRIVATE, ACC_FINAL
    Signature: #17                          // Lscala/Option<Lorg/scalatest/events/Event;>;

  private final boolean includesDistributedTests;
    descriptor: Z
    flags: (0x0012) ACC_PRIVATE, ACC_FINAL

  private final boolean testsCompleted;
    descriptor: Z
    flags: (0x0012) ACC_PRIVATE, ACC_FINAL

  private final boolean ready;
    descriptor: Z
    flags: (0x0012) ACC_PRIVATE, ACC_FINAL

  public final org.scalatest.tools.SuiteSortingReporter $outer;
    descriptor: Lorg/scalatest/tools/SuiteSortingReporter;
    flags: (0x1011) ACC_PUBLIC, ACC_FINAL, ACC_SYNTHETIC

  public scala.collection.Iterator<java.lang.String> productElementNames();
    descriptor: ()Lscala/collection/Iterator;
    flags: (0x0001) ACC_PUBLIC
    Code:
      stack=1, locals=1, args_size=1
         0: aload_0
         1: invokestatic  #30                 // InterfaceMethod scala/Product.productElementNames$:(Lscala/Product;)Lscala/collection/Iterator;
         4: areturn
      LineNumberTable:
        line 28: 0
      LocalVariableTable:
        Start  Length  Slot  Name   Signature
            0       5     0  this   Lorg/scalatest/tools/SuiteSortingReporter$Slot;
    Signature: #26                          // ()Lscala/collection/Iterator<Ljava/lang/String;>;

  public java.lang.String suiteId();
    descriptor: ()Ljava/lang/String;
    flags: (0x0001) ACC_PUBLIC
    Code:
      stack=1, locals=1, args_size=1
         0: aload_0
         1: getfield      #35                 // Field suiteId:Ljava/lang/String;
         4: areturn
      LineNumberTable:
        line 28: 0
      LocalVariableTable:
        Start  Length  Slot  Name   Signature
            0       5     0  this   Lorg/scalatest/tools/SuiteSortingReporter$Slot;

  public scala.Option<org.scalatest.events.Event> doneEvent();
    descriptor: ()Lscala/Option;
    flags: (0x0001) ACC_PUBLIC
    Code:
      stack=1, locals=1, args_size=1
         0: aload_0
         1: getfield      #39                 // Field doneEvent:Lscala/Option;
         4: areturn
      LineNumberTable:
        line 28: 0
      LocalVariableTable:
        Start  Length  Slot  Name   Signature
            0       5     0  this   Lorg/scalatest/tools/SuiteSortingReporter$Slot;
    Signature: #37                          // ()Lscala/Option<Lorg/scalatest/events/Event;>;

  public boolean includesDistributedTests();
    descriptor: ()Z
    flags: (0x0001) ACC_PUBLIC
    Code:
      stack=1, locals=1, args_size=1
         0: aload_0
         1: getfield      #42                 // Field includesDistributedTests:Z
         4: ireturn
      LineNumberTable:
        line 28: 0
      LocalVariableTable:
        Start  Length  Slot  Name   Signature
            0       5     0  this   Lorg/scalatest/tools/SuiteSortingReporter$Slot;

  public boolean testsCompleted();
    descriptor: ()Z
    flags: (0x0001) ACC_PUBLIC
    Code:
      stack=1, locals=1, args_size=1
         0: aload_0
         1: getfield      #44                 // Field testsCompleted:Z
         4: ireturn
      LineNumberTable:
        line 28: 0
      LocalVariableTable:
        Start  Length  Slot  Name   Signature
            0       5     0  this   Lorg/scalatest/tools/SuiteSortingReporter$Slot;

  public boolean ready();
    descriptor: ()Z
    flags: (0x0001) ACC_PUBLIC
    Code:
      stack=1, locals=1, args_size=1
         0: aload_0
         1: getfield      #46                 // Field ready:Z
         4: ireturn
      LineNumberTable:
        line 28: 0
      LocalVariableTable:
        Start  Length  Slot  Name   Signature
            0       5     0  this   Lorg/scalatest/tools/SuiteSortingReporter$Slot;

  public org.scalatest.tools.SuiteSortingReporter$Slot copy(java.lang.String, scala.Option<org.scalatest.events.Event>, boolean, boolean, boolean);
    descriptor: (Ljava/lang/String;Lscala/Option;ZZZ)Lorg/scalatest/tools/SuiteSortingReporter$Slot;
    flags: (0x0001) ACC_PUBLIC
    Code:
      stack=8, locals=6, args_size=6
         0: new           #2                  // class org/scalatest/tools/SuiteSortingReporter$Slot
         3: dup
         4: aload_0
         5: invokevirtual #53                 // Method org$scalatest$tools$SuiteSortingReporter$Slot$$$outer:()Lorg/scalatest/tools/SuiteSortingReporter;
         8: aload_1
         9: aload_2
        10: iload_3
        11: iload         4
        13: iload         5
        15: invokespecial #57                 // Method "<init>":(Lorg/scalatest/tools/SuiteSortingReporter;Ljava/lang/String;Lscala/Option;ZZZ)V
        18: areturn
      LineNumberTable:
        line 28: 0
      LocalVariableTable:
        Start  Length  Slot  Name   Signature
            0      19     0  this   Lorg/scalatest/tools/SuiteSortingReporter$Slot;
            0      19     1 suiteId   Ljava/lang/String;
            0      19     2 doneEvent   Lscala/Option;
            0      19     3 includesDistributedTests   Z
            0      19     4 testsCompleted   Z
            0      19     5 ready   Z
    Signature: #49                          // (Ljava/lang/String;Lscala/Option<Lorg/scalatest/events/Event;>;ZZZ)Lorg/scalatest/tools/SuiteSortingReporter$Slot;
    MethodParameters:
      Name                           Flags
      suiteId                        final
      doneEvent                      final
      includesDistributedTests       final
      testsCompleted                 final
      ready                          final

  public java.lang.String copy$default$1();
    descriptor: ()Ljava/lang/String;
    flags: (0x0001) ACC_PUBLIC
    Code:
      stack=1, locals=1, args_size=1
         0: aload_0
         1: invokevirtual #60                 // Method suiteId:()Ljava/lang/String;
         4: areturn
      LineNumberTable:
        line 28: 0
      LocalVariableTable:
        Start  Length  Slot  Name   Signature
            0       5     0  this   Lorg/scalatest/tools/SuiteSortingReporter$Slot;

  public scala.Option<org.scalatest.events.Event> copy$default$2();
    descriptor: ()Lscala/Option;
    flags: (0x0001) ACC_PUBLIC
    Code:
      stack=1, locals=1, args_size=1
         0: aload_0
         1: invokevirtual #63                 // Method doneEvent:()Lscala/Option;
         4: areturn
      LineNumberTable:
        line 28: 0
      LocalVariableTable:
        Start  Length  Slot  Name   Signature
            0       5     0  this   Lorg/scalatest/tools/SuiteSortingReporter$Slot;
    Signature: #37                          // ()Lscala/Option<Lorg/scalatest/events/Event;>;

  public boolean copy$default$3();
    descriptor: ()Z
    flags: (0x0001) ACC_PUBLIC
    Code:
      stack=1, locals=1, args_size=1
         0: aload_0
         1: invokevirtual #66                 // Method includesDistributedTests:()Z
         4: ireturn
      LineNumberTable:
        line 28: 0
      LocalVariableTable:
        Start  Length  Slot  Name   Signature
            0       5     0  this   Lorg/scalatest/tools/SuiteSortingReporter$Slot;

  public boolean copy$default$4();
    descriptor: ()Z
    flags: (0x0001) ACC_PUBLIC
    Code:
      stack=1, locals=1, args_size=1
         0: aload_0
         1: invokevirtual #69                 // Method testsCompleted:()Z
         4: ireturn
      LineNumberTable:
        line 28: 0
      LocalVariableTable:
        Start  Length  Slot  Name   Signature
            0       5     0  this   Lorg/scalatest/tools/SuiteSortingReporter$Slot;

  public boolean copy$default$5();
    descriptor: ()Z
    flags: (0x0001) ACC_PUBLIC
    Code:
      stack=1, locals=1, args_size=1
         0: aload_0
         1: invokevirtual #72                 // Method ready:()Z
         4: ireturn
      LineNumberTable:
        line 28: 0
      LocalVariableTable:
        Start  Length  Slot  Name   Signature
            0       5     0  this   Lorg/scalatest/tools/SuiteSortingReporter$Slot;

  public java.lang.String productPrefix();
    descriptor: ()Ljava/lang/String;
    flags: (0x0001) ACC_PUBLIC
    Code:
      stack=1, locals=1, args_size=1
         0: ldc           #74                 // String Slot
         2: areturn
      LineNumberTable:
        line 28: 0
      LocalVariableTable:
        Start  Length  Slot  Name   Signature
            0       3     0  this   Lorg/scalatest/tools/SuiteSortingReporter$Slot;

  public int productArity();
    descriptor: ()I
    flags: (0x0001) ACC_PUBLIC
    Code:
      stack=1, locals=1, args_size=1
         0: iconst_5
         1: ireturn
      LineNumberTable:
        line 28: 0
      LocalVariableTable:
        Start  Length  Slot  Name   Signature
            0       2     0  this   Lorg/scalatest/tools/SuiteSortingReporter$Slot;

  public java.lang.Object productElement(int);
    descriptor: (I)Ljava/lang/Object;
    flags: (0x0001) ACC_PUBLIC
    Code:
      stack=1, locals=3, args_size=2
         0: iload_1
         1: istore_2
         2: iload_2
         3: tableswitch   { // 0 to 4
                       0: 36
                       1: 43
                       2: 50
                       3: 60
                       4: 70
                 default: 80
            }
        36: aload_0
        37: invokevirtual #60                 // Method suiteId:()Ljava/lang/String;
        40: goto          87
        43: aload_0
        44: invokevirtual #63                 // Method doneEvent:()Lscala/Option;
        47: goto          87
        50: aload_0
        51: invokevirtual #66                 // Method includesDistributedTests:()Z
        54: invokestatic  #85                 // Method scala/runtime/BoxesRunTime.boxToBoolean:(Z)Ljava/lang/Boolean;
        57: goto          87
        60: aload_0
        61: invokevirtual #69                 // Method testsCompleted:()Z
        64: invokestatic  #85                 // Method scala/runtime/BoxesRunTime.boxToBoolean:(Z)Ljava/lang/Boolean;
        67: goto          87
        70: aload_0
        71: invokevirtual #72                 // Method ready:()Z
        74: invokestatic  #85                 // Method scala/runtime/BoxesRunTime.boxToBoolean:(Z)Ljava/lang/Boolean;
        77: goto          87
        80: iload_1
        81: invokestatic  #90                 // Method scala/runtime/Statics.ioobe:(I)Ljava/lang/Object;
        84: goto          87
        87: areturn
      StackMapTable: number_of_entries = 7
        frame_type = 252 /* append */
          offset_delta = 36
          locals = [ int ]
        frame_type = 6 /* same */
        frame_type = 6 /* same */
        frame_type = 9 /* same */
        frame_type = 9 /* same */
        frame_type = 9 /* same */
        frame_type = 70 /* same_locals_1_stack_item */
          stack = [ class java/lang/Object ]
      LineNumberTable:
        line 28: 0
      LocalVariableTable:
        Start  Length  Slot  Name   Signature
            0      88     0  this   Lorg/scalatest/tools/SuiteSortingReporter$Slot;
            0      88     1   x$1   I
    MethodParameters:
      Name                           Flags
      x$1                            final

  public scala.collection.Iterator<java.lang.Object> productIterator();
    descriptor: ()Lscala/collection/Iterator;
    flags: (0x0001) ACC_PUBLIC
    Code:
      stack=2, locals=1, args_size=1
         0: getstatic     #99                 // Field scala/runtime/ScalaRunTime$.MODULE$:Lscala/runtime/ScalaRunTime$;
         3: aload_0
         4: invokevirtual #102                // Method scala/runtime/ScalaRunTime$.typedProductIterator:(Lscala/Product;)Lscala/collection/Iterator;
         7: areturn
      LineNumberTable:
        line 28: 0
      LocalVariableTable:
        Start  Length  Slot  Name   Signature
            0       8     0  this   Lorg/scalatest/tools/SuiteSortingReporter$Slot;
    Signature: #93                          // ()Lscala/collection/Iterator<Ljava/lang/Object;>;

  public boolean canEqual(java.lang.Object);
    descriptor: (Ljava/lang/Object;)Z
    flags: (0x0001) ACC_PUBLIC
    Code:
      stack=1, locals=2, args_size=2
         0: aload_1
         1: instanceof    #2                  // class org/scalatest/tools/SuiteSortingReporter$Slot
         4: ireturn
      LineNumberTable:
        line 28: 0
      LocalVariableTable:
        Start  Length  Slot  Name   Signature
            0       5     0  this   Lorg/scalatest/tools/SuiteSortingReporter$Slot;
            0       5     1   x$1   Ljava/lang/Object;
    MethodParameters:
      Name                           Flags
      x$1                            final

  public java.lang.String productElementName(int);
    descriptor: (I)Ljava/lang/String;
    flags: (0x0001) ACC_PUBLIC
    Code:
      stack=1, locals=3, args_size=2
         0: iload_1
         1: istore_2
         2: iload_2
         3: tableswitch   { // 0 to 4
                       0: 36
                       1: 41
                       2: 46
                       3: 51
                       4: 56
                 default: 61
            }
        36: ldc           #108                // String suiteId
        38: goto          71
        41: ldc           #109                // String doneEvent
        43: goto          71
        46: ldc           #110                // String includesDistributedTests
        48: goto          71
        51: ldc           #111                // String testsCompleted
        53: goto          71
        56: ldc           #112                // String ready
        58: goto          71
        61: iload_1
        62: invokestatic  #90                 // Method scala/runtime/Statics.ioobe:(I)Ljava/lang/Object;
        65: checkcast     #114                // class java/lang/String
        68: goto          71
        71: areturn
      StackMapTable: number_of_entries = 7
        frame_type = 252 /* append */
          offset_delta = 36
          locals = [ int ]
        frame_type = 4 /* same */
        frame_type = 4 /* same */
        frame_type = 4 /* same */
        frame_type = 4 /* same */
        frame_type = 4 /* same */
        frame_type = 73 /* same_locals_1_stack_item */
          stack = [ class java/lang/String ]
      LineNumberTable:
        line 28: 0
      LocalVariableTable:
        Start  Length  Slot  Name   Signature
            0      72     0  this   Lorg/scalatest/tools/SuiteSortingReporter$Slot;
            0      72     1   x$1   I
    MethodParameters:
      Name                           Flags
      x$1                            final

  public int hashCode();
    descriptor: ()I
    flags: (0x0001) ACC_PUBLIC
    Code:
      stack=2, locals=2, args_size=1
         0: ldc           #116                // int -889275714
         2: istore_1
         3: iload_1
         4: aload_0
         5: invokevirtual #118                // Method productPrefix:()Ljava/lang/String;
         8: invokevirtual #120                // Method java/lang/String.hashCode:()I
        11: invokestatic  #124                // Method scala/runtime/Statics.mix:(II)I
        14: istore_1
        15: iload_1
        16: aload_0
        17: invokevirtual #60                 // Method suiteId:()Ljava/lang/String;
        20: invokestatic  #128                // Method scala/runtime/Statics.anyHash:(Ljava/lang/Object;)I
        23: invokestatic  #124                // Method scala/runtime/Statics.mix:(II)I
        26: istore_1
        27: iload_1
        28: aload_0
        29: invokevirtual #63                 // Method doneEvent:()Lscala/Option;
        32: invokestatic  #128                // Method scala/runtime/Statics.anyHash:(Ljava/lang/Object;)I
        35: invokestatic  #124                // Method scala/runtime/Statics.mix:(II)I
        38: istore_1
        39: iload_1
        40: aload_0
        41: invokevirtual #66                 // Method includesDistributedTests:()Z
        44: ifeq          53
        47: sipush        1231
        50: goto          56
        53: sipush        1237
        56: invokestatic  #124                // Method scala/runtime/Statics.mix:(II)I
        59: istore_1
        60: iload_1
        61: aload_0
        62: invokevirtual #69                 // Method testsCompleted:()Z
        65: ifeq          74
        68: sipush        1231
        71: goto          77
        74: sipush        1237
        77: invokestatic  #124                // Method scala/runtime/Statics.mix:(II)I
        80: istore_1
        81: iload_1
        82: aload_0
        83: invokevirtual #72                 // Method ready:()Z
        86: ifeq          95
        89: sipush        1231
        92: goto          98
        95: sipush        1237
        98: invokestatic  #124                // Method scala/runtime/Statics.mix:(II)I
       101: istore_1
       102: iload_1
       103: iconst_5
       104: invokestatic  #131                // Method scala/runtime/Statics.finalizeHash:(II)I
       107: ireturn
      StackMapTable: number_of_entries = 6
        frame_type = 255 /* full_frame */
          offset_delta = 53
          locals = [ class org/scalatest/tools/SuiteSortingReporter$Slot, int ]
          stack = [ int ]
        frame_type = 255 /* full_frame */
          offset_delta = 2
          locals = [ class org/scalatest/tools/SuiteSortingReporter$Slot, int ]
          stack = [ int, int ]
        frame_type = 81 /* same_locals_1_stack_item */
          stack = [ int ]
        frame_type = 255 /* full_frame */
          offset_delta = 2
          locals = [ class org/scalatest/tools/SuiteSortingReporter$Slot, int ]
          stack = [ int, int ]
        frame_type = 81 /* same_locals_1_stack_item */
          stack = [ int ]
        frame_type = 255 /* full_frame */
          offset_delta = 2
          locals = [ class org/scalatest/tools/SuiteSortingReporter$Slot, int ]
          stack = [ int, int ]
      LineNumberTable:
        line 28: 0
      LocalVariableTable:
        Start  Length  Slot  Name   Signature
            0     108     0  this   Lorg/scalatest/tools/SuiteSortingReporter$Slot;

  public java.lang.String toString();
    descriptor: ()Ljava/lang/String;
    flags: (0x0001) ACC_PUBLIC
    Code:
      stack=2, locals=1, args_size=1
         0: getstatic     #99                 // Field scala/runtime/ScalaRunTime$.MODULE$:Lscala/runtime/ScalaRunTime$;
         3: aload_0
         4: invokevirtual #136                // Method scala/runtime/ScalaRunTime$._toString:(Lscala/Product;)Ljava/lang/String;
         7: areturn
      LineNumberTable:
        line 28: 0
      LocalVariableTable:
        Start  Length  Slot  Name   Signature
            0       8     0  this   Lorg/scalatest/tools/SuiteSortingReporter$Slot;

  public boolean equals(java.lang.Object);
    descriptor: (Ljava/lang/Object;)Z
    flags: (0x0001) ACC_PUBLIC
    Code:
      stack=2, locals=7, args_size=2
         0: aload_0
         1: aload_1
         2: if_acmpeq     168
         5: aload_1
         6: astore_3
         7: aload_3
         8: instanceof    #2                  // class org/scalatest/tools/SuiteSortingReporter$Slot
        11: ifeq          33
        14: aload_3
        15: checkcast     #2                  // class org/scalatest/tools/SuiteSortingReporter$Slot
        18: invokevirtual #53                 // Method org$scalatest$tools$SuiteSortingReporter$Slot$$$outer:()Lorg/scalatest/tools/SuiteSortingReporter;
        21: aload_0
        22: invokevirtual #53                 // Method org$scalatest$tools$SuiteSortingReporter$Slot$$$outer:()Lorg/scalatest/tools/SuiteSortingReporter;
        25: if_acmpne     33
        28: iconst_1
        29: istore_2
        30: goto          41
        33: goto          36
        36: iconst_0
        37: istore_2
        38: goto          41
        41: iload_2
        42: ifeq          172
        45: aload_1
        46: checkcast     #2                  // class org/scalatest/tools/SuiteSortingReporter$Slot
        49: astore        4
        51: aload_0
        52: invokevirtual #66                 // Method includesDistributedTests:()Z
        55: aload         4
        57: invokevirtual #66                 // Method includesDistributedTests:()Z
        60: if_icmpne     164
        63: aload_0
        64: invokevirtual #69                 // Method testsCompleted:()Z
        67: aload         4
        69: invokevirtual #69                 // Method testsCompleted:()Z
        72: if_icmpne     164
        75: aload_0
        76: invokevirtual #72                 // Method ready:()Z
        79: aload         4
        81: invokevirtual #72                 // Method ready:()Z
        84: if_icmpne     164
        87: aload_0
        88: invokevirtual #60                 // Method suiteId:()Ljava/lang/String;
        91: aload         4
        93: invokevirtual #60                 // Method suiteId:()Ljava/lang/String;
        96: astore        5
        98: dup
        99: ifnonnull     111
       102: pop
       103: aload         5
       105: ifnull        119
       108: goto          164
       111: aload         5
       113: invokevirtual #139                // Method java/lang/Object.equals:(Ljava/lang/Object;)Z
       116: ifeq          164
       119: aload_0
       120: invokevirtual #63                 // Method doneEvent:()Lscala/Option;
       123: aload         4
       125: invokevirtual #63                 // Method doneEvent:()Lscala/Option;
       128: astore        6
       130: dup
       131: ifnonnull     143
       134: pop
       135: aload         6
       137: ifnull        151
       140: goto          164
       143: aload         6
       145: invokevirtual #139                // Method java/lang/Object.equals:(Ljava/lang/Object;)Z
       148: ifeq          164
       151: aload         4
       153: aload_0
       154: invokevirtual #141                // Method canEqual:(Ljava/lang/Object;)Z
       157: ifeq          164
       160: iconst_1
       161: goto          165
       164: iconst_0
       165: ifeq          172
       168: iconst_1
       169: goto          173
       172: iconst_0
       173: ireturn
      StackMapTable: number_of_entries = 12
        frame_type = 253 /* append */
          offset_delta = 33
          locals = [ top, class java/lang/Object ]
        frame_type = 2 /* same */
        frame_type = 255 /* full_frame */
          offset_delta = 4
          locals = [ class org/scalatest/tools/SuiteSortingReporter$Slot, class java/lang/Object, int, class java/lang/Object ]
          stack = []
        frame_type = 255 /* full_frame */
          offset_delta = 69
          locals = [ class org/scalatest/tools/SuiteSortingReporter$Slot, class java/lang/Object, int, class java/lang/Object, class org/scalatest/tools/SuiteSortingReporter$Slot, class java/lang/String ]
          stack = [ class java/lang/String ]
        frame_type = 7 /* same */
        frame_type = 255 /* full_frame */
          offset_delta = 23
          locals = [ class org/scalatest/tools/SuiteSortingReporter$Slot, class java/lang/Object, int, class java/lang/Object, class org/scalatest/tools/SuiteSortingReporter$Slot, class java/lang/String, class scala/Option ]
          stack = [ class scala/Option ]
        frame_type = 7 /* same */
        frame_type = 249 /* chop */
          offset_delta = 12
        frame_type = 64 /* same_locals_1_stack_item */
          stack = [ int ]
        frame_type = 248 /* chop */
          offset_delta = 2
        frame_type = 253 /* append */
          offset_delta = 3
          locals = [ int, class java/lang/Object ]
        frame_type = 255 /* full_frame */
          offset_delta = 0
          locals = [ class org/scalatest/tools/SuiteSortingReporter$Slot, class java/lang/Object ]
          stack = [ int ]
      LineNumberTable:
        line 28: 0
      LocalVariableTable:
        Start  Length  Slot  Name   Signature
            0     174     0  this   Lorg/scalatest/tools/SuiteSortingReporter$Slot;
            0     174     1   x$1   Ljava/lang/Object;
    MethodParameters:
      Name                           Flags
      x$1                            final

  public org.scalatest.tools.SuiteSortingReporter org$scalatest$tools$SuiteSortingReporter$Slot$$$outer();
    descriptor: ()Lorg/scalatest/tools/SuiteSortingReporter;
    flags: (0x1001) ACC_PUBLIC, ACC_SYNTHETIC
    Code:
      stack=1, locals=1, args_size=1
         0: aload_0
         1: getfield      #145                // Field $outer:Lorg/scalatest/tools/SuiteSortingReporter;
         4: areturn
      LineNumberTable:
        line 28: 0
      LocalVariableTable:
        Start  Length  Slot  Name   Signature
            0       5     0  this   Lorg/scalatest/tools/SuiteSortingReporter$Slot;

  public org.scalatest.tools.SuiteSortingReporter$Slot(java.lang.String, scala.Option<org.scalatest.events.Event>, boolean, boolean, boolean);
    descriptor: (Lorg/scalatest/tools/SuiteSortingReporter;Ljava/lang/String;Lscala/Option;ZZZ)V
    flags: (0x0001) ACC_PUBLIC
    Code:
      stack=2, locals=7, args_size=7
         0: aload_0
         1: aload_2
         2: putfield      #35                 // Field suiteId:Ljava/lang/String;
         5: aload_0
         6: aload_3
         7: putfield      #39                 // Field doneEvent:Lscala/Option;
        10: aload_0
        11: iload         4
        13: putfield      #42                 // Field includesDistributedTests:Z
        16: aload_0
        17: iload         5
        19: putfield      #44                 // Field testsCompleted:Z
        22: aload_0
        23: iload         6
        25: putfield      #46                 // Field ready:Z
        28: aload_1
        29: ifnonnull     34
        32: aconst_null
        33: athrow
        34: aload_0
        35: aload_1
        36: putfield      #145                // Field $outer:Lorg/scalatest/tools/SuiteSortingReporter;
        39: aload_0
        40: invokespecial #149                // Method java/lang/Object."<init>":()V
        43: aload_0
        44: invokestatic  #153                // InterfaceMethod scala/Product.$init$:(Lscala/Product;)V
        47: return
      StackMapTable: number_of_entries = 1
        frame_type = 34 /* same */
      LineNumberTable:
        line 28: 0
      LocalVariableTable:
        Start  Length  Slot  Name   Signature
            0      48     0  this   Lorg/scalatest/tools/SuiteSortingReporter$Slot;
            0      48     1 $outer   Lorg/scalatest/tools/SuiteSortingReporter;
            0      48     2 suiteId   Ljava/lang/String;
            0      48     3 doneEvent   Lscala/Option;
            0      48     4 includesDistributedTests   Z
            0      48     5 testsCompleted   Z
            0      48     6 ready   Z
    Signature: #146                         // (Ljava/lang/String;Lscala/Option<Lorg/scalatest/events/Event;>;ZZZ)V
    MethodParameters:
      Name                           Flags
      $outer                         final synthetic
      suiteId                        final
      doneEvent                      final
      includesDistributedTests       final
      testsCompleted                 final
      ready                          final
}
InnerClasses:
  public #12= #2 of #11;                  // Slot=class org/scalatest/tools/SuiteSortingReporter$Slot of class org/scalatest/tools/SuiteSortingReporter
SourceFile: "SuiteSortingReporter.scala"
  ScalaInlineInfo: length = 0x77 (unknown attribute)
   01 00 00 17 00 36 00 37 00 00 67 00 68 00 00 2F
   00 30 00 00 3A 00 21 00 00 3D 00 24 00 00 40 00
   28 00 00 43 00 28 00 00 46 00 28 00 00 0F 00 24
   00 00 89 00 68 00 00 73 00 4C 00 00 12 00 28 00
   00 32 00 33 00 00 4B 00 4C 00 00 4D 00 4E 00 00
   6A 00 6B 00 00 18 00 19 00 00 5C 00 19 00 00 49
   00 21 00 00 15 00 28 00 00 0D 00 21 00 00 14 00
   28 00 00 84 00 21 00
  Scala: length = 0x0 (unknown attribute)

