Classfile /Users/mw/Projects/slang-braindump/.jar/jar11/assemble/slang-braindump/assemble/content/org/scalatest/tools/XmlReporter$Testcase.class
  Last modified May 29, 2022; size 5655 bytes
  SHA-256 checksum 2734417ef36bf4efa9f98aaa8900d143a85dac5ee3ca22fee28ad6b82982f19c
  Compiled from "XmlReporter.scala"
public class org.scalatest.tools.XmlReporter$Testcase implements scala.Product,java.io.Serializable
  minor version: 0
  major version: 52
  flags: (0x0021) ACC_PUBLIC, ACC_SUPER
  this_class: #2                          // org/scalatest/tools/XmlReporter$Testcase
  super_class: #4                         // java/lang/Object
  interfaces: 2, fields: 9, methods: 29, attributes: 4
Constant pool:
    #1 = Utf8               org/scalatest/tools/XmlReporter$Testcase
    #2 = Class              #1            // org/scalatest/tools/XmlReporter$Testcase
    #3 = Utf8               java/lang/Object
    #4 = Class              #3            // java/lang/Object
    #5 = Utf8               scala/Product
    #6 = Class              #5            // scala/Product
    #7 = Utf8               java/io/Serializable
    #8 = Class              #7            // java/io/Serializable
    #9 = Utf8               XmlReporter.scala
   #10 = Utf8               org/scalatest/tools/XmlReporter
   #11 = Class              #10           // org/scalatest/tools/XmlReporter
   #12 = Utf8               Testcase
   #13 = Utf8               name
   #14 = Utf8               Ljava/lang/String;
   #15 = Utf8               className
   #16 = Utf8               Lscala/Option;
   #17 = Utf8               Lscala/Option<Ljava/lang/String;>;
   #18 = Utf8               timeStamp
   #19 = Utf8               J
   #20 = Utf8               time
   #21 = Utf8               pending
   #22 = Utf8               Z
   #23 = Utf8               canceled
   #24 = Utf8               ignored
   #25 = Utf8               failure
   #26 = Utf8               Lscala/Option<Lorg/scalatest/events/TestFailed;>;
   #27 = Utf8               $outer
   #28 = Utf8               Lorg/scalatest/tools/XmlReporter;
   #29 = Utf8               productElementNames
   #30 = Utf8               ()Lscala/collection/Iterator;
   #31 = Utf8               ()Lscala/collection/Iterator<Ljava/lang/String;>;
   #32 = Utf8               productElementNames$
   #33 = Utf8               (Lscala/Product;)Lscala/collection/Iterator;
   #34 = NameAndType        #32:#33       // productElementNames$:(Lscala/Product;)Lscala/collection/Iterator;
   #35 = InterfaceMethodref #6.#34        // scala/Product.productElementNames$:(Lscala/Product;)Lscala/collection/Iterator;
   #36 = Utf8               this
   #37 = Utf8               Lorg/scalatest/tools/XmlReporter$Testcase;
   #38 = Utf8               ()Ljava/lang/String;
   #39 = NameAndType        #13:#14       // name:Ljava/lang/String;
   #40 = Fieldref           #2.#39        // org/scalatest/tools/XmlReporter$Testcase.name:Ljava/lang/String;
   #41 = Utf8               ()Lscala/Option;
   #42 = Utf8               ()Lscala/Option<Ljava/lang/String;>;
   #43 = NameAndType        #15:#16       // className:Lscala/Option;
   #44 = Fieldref           #2.#43        // org/scalatest/tools/XmlReporter$Testcase.className:Lscala/Option;
   #45 = Utf8               ()J
   #46 = NameAndType        #18:#19       // timeStamp:J
   #47 = Fieldref           #2.#46        // org/scalatest/tools/XmlReporter$Testcase.timeStamp:J
   #48 = NameAndType        #20:#19       // time:J
   #49 = Fieldref           #2.#48        // org/scalatest/tools/XmlReporter$Testcase.time:J
   #50 = Utf8               time_$eq
   #51 = Utf8               (J)V
   #52 = Utf8               x$1
   #53 = Utf8               ()Z
   #54 = NameAndType        #21:#22       // pending:Z
   #55 = Fieldref           #2.#54        // org/scalatest/tools/XmlReporter$Testcase.pending:Z
   #56 = Utf8               pending_$eq
   #57 = Utf8               (Z)V
   #58 = NameAndType        #23:#22       // canceled:Z
   #59 = Fieldref           #2.#58        // org/scalatest/tools/XmlReporter$Testcase.canceled:Z
   #60 = Utf8               canceled_$eq
   #61 = NameAndType        #24:#22       // ignored:Z
   #62 = Fieldref           #2.#61        // org/scalatest/tools/XmlReporter$Testcase.ignored:Z
   #63 = Utf8               ignored_$eq
   #64 = Utf8               ()Lscala/Option<Lorg/scalatest/events/TestFailed;>;
   #65 = NameAndType        #25:#16       // failure:Lscala/Option;
   #66 = Fieldref           #2.#65        // org/scalatest/tools/XmlReporter$Testcase.failure:Lscala/Option;
   #67 = Utf8               failure_$eq
   #68 = Utf8               (Lscala/Option;)V
   #69 = Utf8               (Lscala/Option<Lorg/scalatest/events/TestFailed;>;)V
   #70 = Utf8               copy
   #71 = Utf8               (Ljava/lang/String;Lscala/Option;J)Lorg/scalatest/tools/XmlReporter$Testcase;
   #72 = Utf8               (Ljava/lang/String;Lscala/Option<Ljava/lang/String;>;J)Lorg/scalatest/tools/XmlReporter$Testcase;
   #73 = Utf8               org$scalatest$tools$XmlReporter$Testcase$$$outer
   #74 = Utf8               ()Lorg/scalatest/tools/XmlReporter;
   #75 = NameAndType        #73:#74       // org$scalatest$tools$XmlReporter$Testcase$$$outer:()Lorg/scalatest/tools/XmlReporter;
   #76 = Methodref          #2.#75        // org/scalatest/tools/XmlReporter$Testcase.org$scalatest$tools$XmlReporter$Testcase$$$outer:()Lorg/scalatest/tools/XmlReporter;
   #77 = Utf8               <init>
   #78 = Utf8               (Lorg/scalatest/tools/XmlReporter;Ljava/lang/String;Lscala/Option;J)V
   #79 = NameAndType        #77:#78       // "<init>":(Lorg/scalatest/tools/XmlReporter;Ljava/lang/String;Lscala/Option;J)V
   #80 = Methodref          #2.#79        // org/scalatest/tools/XmlReporter$Testcase."<init>":(Lorg/scalatest/tools/XmlReporter;Ljava/lang/String;Lscala/Option;J)V
   #81 = Utf8               copy$default$1
   #82 = NameAndType        #13:#38       // name:()Ljava/lang/String;
   #83 = Methodref          #2.#82        // org/scalatest/tools/XmlReporter$Testcase.name:()Ljava/lang/String;
   #84 = Utf8               copy$default$2
   #85 = NameAndType        #15:#41       // className:()Lscala/Option;
   #86 = Methodref          #2.#85        // org/scalatest/tools/XmlReporter$Testcase.className:()Lscala/Option;
   #87 = Utf8               copy$default$3
   #88 = NameAndType        #18:#45       // timeStamp:()J
   #89 = Methodref          #2.#88        // org/scalatest/tools/XmlReporter$Testcase.timeStamp:()J
   #90 = Utf8               productPrefix
   #91 = String             #12           // Testcase
   #92 = Utf8               productArity
   #93 = Utf8               ()I
   #94 = Utf8               productElement
   #95 = Utf8               (I)Ljava/lang/Object;
   #96 = Utf8               scala/runtime/BoxesRunTime
   #97 = Class              #96           // scala/runtime/BoxesRunTime
   #98 = Utf8               boxToLong
   #99 = Utf8               (J)Ljava/lang/Long;
  #100 = NameAndType        #98:#99       // boxToLong:(J)Ljava/lang/Long;
  #101 = Methodref          #97.#100      // scala/runtime/BoxesRunTime.boxToLong:(J)Ljava/lang/Long;
  #102 = Utf8               scala/runtime/Statics
  #103 = Class              #102          // scala/runtime/Statics
  #104 = Utf8               ioobe
  #105 = NameAndType        #104:#95      // ioobe:(I)Ljava/lang/Object;
  #106 = Methodref          #103.#105     // scala/runtime/Statics.ioobe:(I)Ljava/lang/Object;
  #107 = Utf8               I
  #108 = Utf8               productIterator
  #109 = Utf8               ()Lscala/collection/Iterator<Ljava/lang/Object;>;
  #110 = Utf8               scala/runtime/ScalaRunTime$
  #111 = Class              #110          // scala/runtime/ScalaRunTime$
  #112 = Utf8               MODULE$
  #113 = Utf8               Lscala/runtime/ScalaRunTime$;
  #114 = NameAndType        #112:#113     // MODULE$:Lscala/runtime/ScalaRunTime$;
  #115 = Fieldref           #111.#114     // scala/runtime/ScalaRunTime$.MODULE$:Lscala/runtime/ScalaRunTime$;
  #116 = Utf8               typedProductIterator
  #117 = NameAndType        #116:#33      // typedProductIterator:(Lscala/Product;)Lscala/collection/Iterator;
  #118 = Methodref          #111.#117     // scala/runtime/ScalaRunTime$.typedProductIterator:(Lscala/Product;)Lscala/collection/Iterator;
  #119 = Utf8               canEqual
  #120 = Utf8               (Ljava/lang/Object;)Z
  #121 = Utf8               Ljava/lang/Object;
  #122 = Utf8               productElementName
  #123 = Utf8               (I)Ljava/lang/String;
  #124 = String             #13           // name
  #125 = String             #15           // className
  #126 = String             #18           // timeStamp
  #127 = Utf8               java/lang/String
  #128 = Class              #127          // java/lang/String
  #129 = Utf8               hashCode
  #130 = Integer            -889275714
  #131 = NameAndType        #90:#38       // productPrefix:()Ljava/lang/String;
  #132 = Methodref          #2.#131       // org/scalatest/tools/XmlReporter$Testcase.productPrefix:()Ljava/lang/String;
  #133 = NameAndType        #129:#93      // hashCode:()I
  #134 = Methodref          #128.#133     // java/lang/String.hashCode:()I
  #135 = Utf8               mix
  #136 = Utf8               (II)I
  #137 = NameAndType        #135:#136     // mix:(II)I
  #138 = Methodref          #103.#137     // scala/runtime/Statics.mix:(II)I
  #139 = Utf8               anyHash
  #140 = Utf8               (Ljava/lang/Object;)I
  #141 = NameAndType        #139:#140     // anyHash:(Ljava/lang/Object;)I
  #142 = Methodref          #103.#141     // scala/runtime/Statics.anyHash:(Ljava/lang/Object;)I
  #143 = Utf8               longHash
  #144 = Utf8               (J)I
  #145 = NameAndType        #143:#144     // longHash:(J)I
  #146 = Methodref          #103.#145     // scala/runtime/Statics.longHash:(J)I
  #147 = Utf8               finalizeHash
  #148 = NameAndType        #147:#136     // finalizeHash:(II)I
  #149 = Methodref          #103.#148     // scala/runtime/Statics.finalizeHash:(II)I
  #150 = Utf8               toString
  #151 = Utf8               _toString
  #152 = Utf8               (Lscala/Product;)Ljava/lang/String;
  #153 = NameAndType        #151:#152     // _toString:(Lscala/Product;)Ljava/lang/String;
  #154 = Methodref          #111.#153     // scala/runtime/ScalaRunTime$._toString:(Lscala/Product;)Ljava/lang/String;
  #155 = Utf8               equals
  #156 = NameAndType        #155:#120     // equals:(Ljava/lang/Object;)Z
  #157 = Methodref          #4.#156       // java/lang/Object.equals:(Ljava/lang/Object;)Z
  #158 = NameAndType        #119:#120     // canEqual:(Ljava/lang/Object;)Z
  #159 = Methodref          #2.#158       // org/scalatest/tools/XmlReporter$Testcase.canEqual:(Ljava/lang/Object;)Z
  #160 = Utf8               scala/Option
  #161 = Class              #160          // scala/Option
  #162 = NameAndType        #27:#28       // $outer:Lorg/scalatest/tools/XmlReporter;
  #163 = Fieldref           #2.#162       // org/scalatest/tools/XmlReporter$Testcase.$outer:Lorg/scalatest/tools/XmlReporter;
  #164 = Utf8               (Ljava/lang/String;Lscala/Option<Ljava/lang/String;>;J)V
  #165 = Utf8               ()V
  #166 = NameAndType        #77:#165      // "<init>":()V
  #167 = Methodref          #4.#166       // java/lang/Object."<init>":()V
  #168 = Utf8               $init$
  #169 = Utf8               (Lscala/Product;)V
  #170 = NameAndType        #168:#169     // $init$:(Lscala/Product;)V
  #171 = InterfaceMethodref #6.#170       // scala/Product.$init$:(Lscala/Product;)V
  #172 = Utf8               scala/None$
  #173 = Class              #172          // scala/None$
  #174 = Utf8               Lscala/None$;
  #175 = NameAndType        #112:#174     // MODULE$:Lscala/None$;
  #176 = Fieldref           #173.#175     // scala/None$.MODULE$:Lscala/None$;
  #177 = Utf8               Signature
  #178 = Utf8               Code
  #179 = Utf8               LineNumberTable
  #180 = Utf8               LocalVariableTable
  #181 = Utf8               MethodParameters
  #182 = Utf8               StackMapTable
  #183 = Utf8               InnerClasses
  #184 = Utf8               SourceFile
  #185 = Utf8               ScalaInlineInfo
  #186 = Utf8               Scala
{
  private final java.lang.String name;
    descriptor: Ljava/lang/String;
    flags: (0x0012) ACC_PRIVATE, ACC_FINAL

  private final scala.Option<java.lang.String> className;
    descriptor: Lscala/Option;
    flags: (0x0012) ACC_PRIVATE, ACC_FINAL
    Signature: #17                          // Lscala/Option<Ljava/lang/String;>;

  private final long timeStamp;
    descriptor: J
    flags: (0x0012) ACC_PRIVATE, ACC_FINAL

  private long time;
    descriptor: J
    flags: (0x0002) ACC_PRIVATE

  private boolean pending;
    descriptor: Z
    flags: (0x0002) ACC_PRIVATE

  private boolean canceled;
    descriptor: Z
    flags: (0x0002) ACC_PRIVATE

  private boolean ignored;
    descriptor: Z
    flags: (0x0002) ACC_PRIVATE

  private scala.Option<org.scalatest.events.TestFailed> failure;
    descriptor: Lscala/Option;
    flags: (0x0002) ACC_PRIVATE
    Signature: #26                          // Lscala/Option<Lorg/scalatest/events/TestFailed;>;

  public final org.scalatest.tools.XmlReporter $outer;
    descriptor: Lorg/scalatest/tools/XmlReporter;
    flags: (0x1011) ACC_PUBLIC, ACC_FINAL, ACC_SYNTHETIC

  public scala.collection.Iterator<java.lang.String> productElementNames();
    descriptor: ()Lscala/collection/Iterator;
    flags: (0x0001) ACC_PUBLIC
    Code:
      stack=1, locals=1, args_size=1
         0: aload_0
         1: invokestatic  #35                 // InterfaceMethod scala/Product.productElementNames$:(Lscala/Product;)Lscala/collection/Iterator;
         4: areturn
      LineNumberTable:
        line 484: 0
      LocalVariableTable:
        Start  Length  Slot  Name   Signature
            0       5     0  this   Lorg/scalatest/tools/XmlReporter$Testcase;
    Signature: #31                          // ()Lscala/collection/Iterator<Ljava/lang/String;>;

  public java.lang.String name();
    descriptor: ()Ljava/lang/String;
    flags: (0x0001) ACC_PUBLIC
    Code:
      stack=1, locals=1, args_size=1
         0: aload_0
         1: getfield      #40                 // Field name:Ljava/lang/String;
         4: areturn
      LineNumberTable:
        line 484: 0
      LocalVariableTable:
        Start  Length  Slot  Name   Signature
            0       5     0  this   Lorg/scalatest/tools/XmlReporter$Testcase;

  public scala.Option<java.lang.String> className();
    descriptor: ()Lscala/Option;
    flags: (0x0001) ACC_PUBLIC
    Code:
      stack=1, locals=1, args_size=1
         0: aload_0
         1: getfield      #44                 // Field className:Lscala/Option;
         4: areturn
      LineNumberTable:
        line 484: 0
      LocalVariableTable:
        Start  Length  Slot  Name   Signature
            0       5     0  this   Lorg/scalatest/tools/XmlReporter$Testcase;
    Signature: #42                          // ()Lscala/Option<Ljava/lang/String;>;

  public long timeStamp();
    descriptor: ()J
    flags: (0x0001) ACC_PUBLIC
    Code:
      stack=2, locals=1, args_size=1
         0: aload_0
         1: getfield      #47                 // Field timeStamp:J
         4: lreturn
      LineNumberTable:
        line 485: 0
      LocalVariableTable:
        Start  Length  Slot  Name   Signature
            0       5     0  this   Lorg/scalatest/tools/XmlReporter$Testcase;

  public long time();
    descriptor: ()J
    flags: (0x0001) ACC_PUBLIC
    Code:
      stack=2, locals=1, args_size=1
         0: aload_0
         1: getfield      #49                 // Field time:J
         4: lreturn
      LineNumberTable:
        line 486: 0
      LocalVariableTable:
        Start  Length  Slot  Name   Signature
            0       5     0  this   Lorg/scalatest/tools/XmlReporter$Testcase;

  public void time_$eq(long);
    descriptor: (J)V
    flags: (0x0001) ACC_PUBLIC
    Code:
      stack=3, locals=3, args_size=2
         0: aload_0
         1: lload_1
         2: putfield      #49                 // Field time:J
         5: return
      LineNumberTable:
        line 486: 0
      LocalVariableTable:
        Start  Length  Slot  Name   Signature
            0       6     0  this   Lorg/scalatest/tools/XmlReporter$Testcase;
            0       6     1   x$1   J
    MethodParameters:
      Name                           Flags
      x$1                            final

  public boolean pending();
    descriptor: ()Z
    flags: (0x0001) ACC_PUBLIC
    Code:
      stack=1, locals=1, args_size=1
         0: aload_0
         1: getfield      #55                 // Field pending:Z
         4: ireturn
      LineNumberTable:
        line 487: 0
      LocalVariableTable:
        Start  Length  Slot  Name   Signature
            0       5     0  this   Lorg/scalatest/tools/XmlReporter$Testcase;

  public void pending_$eq(boolean);
    descriptor: (Z)V
    flags: (0x0001) ACC_PUBLIC
    Code:
      stack=2, locals=2, args_size=2
         0: aload_0
         1: iload_1
         2: putfield      #55                 // Field pending:Z
         5: return
      LineNumberTable:
        line 487: 0
      LocalVariableTable:
        Start  Length  Slot  Name   Signature
            0       6     0  this   Lorg/scalatest/tools/XmlReporter$Testcase;
            0       6     1   x$1   Z
    MethodParameters:
      Name                           Flags
      x$1                            final

  public boolean canceled();
    descriptor: ()Z
    flags: (0x0001) ACC_PUBLIC
    Code:
      stack=1, locals=1, args_size=1
         0: aload_0
         1: getfield      #59                 // Field canceled:Z
         4: ireturn
      LineNumberTable:
        line 488: 0
      LocalVariableTable:
        Start  Length  Slot  Name   Signature
            0       5     0  this   Lorg/scalatest/tools/XmlReporter$Testcase;

  public void canceled_$eq(boolean);
    descriptor: (Z)V
    flags: (0x0001) ACC_PUBLIC
    Code:
      stack=2, locals=2, args_size=2
         0: aload_0
         1: iload_1
         2: putfield      #59                 // Field canceled:Z
         5: return
      LineNumberTable:
        line 488: 0
      LocalVariableTable:
        Start  Length  Slot  Name   Signature
            0       6     0  this   Lorg/scalatest/tools/XmlReporter$Testcase;
            0       6     1   x$1   Z
    MethodParameters:
      Name                           Flags
      x$1                            final

  public boolean ignored();
    descriptor: ()Z
    flags: (0x0001) ACC_PUBLIC
    Code:
      stack=1, locals=1, args_size=1
         0: aload_0
         1: getfield      #62                 // Field ignored:Z
         4: ireturn
      LineNumberTable:
        line 489: 0
      LocalVariableTable:
        Start  Length  Slot  Name   Signature
            0       5     0  this   Lorg/scalatest/tools/XmlReporter$Testcase;

  public void ignored_$eq(boolean);
    descriptor: (Z)V
    flags: (0x0001) ACC_PUBLIC
    Code:
      stack=2, locals=2, args_size=2
         0: aload_0
         1: iload_1
         2: putfield      #62                 // Field ignored:Z
         5: return
      LineNumberTable:
        line 489: 0
      LocalVariableTable:
        Start  Length  Slot  Name   Signature
            0       6     0  this   Lorg/scalatest/tools/XmlReporter$Testcase;
            0       6     1   x$1   Z
    MethodParameters:
      Name                           Flags
      x$1                            final

  public scala.Option<org.scalatest.events.TestFailed> failure();
    descriptor: ()Lscala/Option;
    flags: (0x0001) ACC_PUBLIC
    Code:
      stack=1, locals=1, args_size=1
         0: aload_0
         1: getfield      #66                 // Field failure:Lscala/Option;
         4: areturn
      LineNumberTable:
        line 490: 0
      LocalVariableTable:
        Start  Length  Slot  Name   Signature
            0       5     0  this   Lorg/scalatest/tools/XmlReporter$Testcase;
    Signature: #64                          // ()Lscala/Option<Lorg/scalatest/events/TestFailed;>;

  public void failure_$eq(scala.Option<org.scalatest.events.TestFailed>);
    descriptor: (Lscala/Option;)V
    flags: (0x0001) ACC_PUBLIC
    Code:
      stack=2, locals=2, args_size=2
         0: aload_0
         1: aload_1
         2: putfield      #66                 // Field failure:Lscala/Option;
         5: return
      LineNumberTable:
        line 490: 0
      LocalVariableTable:
        Start  Length  Slot  Name   Signature
            0       6     0  this   Lorg/scalatest/tools/XmlReporter$Testcase;
            0       6     1   x$1   Lscala/Option;
    Signature: #69                          // (Lscala/Option<Lorg/scalatest/events/TestFailed;>;)V
    MethodParameters:
      Name                           Flags
      x$1                            final

  public org.scalatest.tools.XmlReporter$Testcase copy(java.lang.String, scala.Option<java.lang.String>, long);
    descriptor: (Ljava/lang/String;Lscala/Option;J)Lorg/scalatest/tools/XmlReporter$Testcase;
    flags: (0x0001) ACC_PUBLIC
    Code:
      stack=7, locals=5, args_size=4
         0: new           #2                  // class org/scalatest/tools/XmlReporter$Testcase
         3: dup
         4: aload_0
         5: invokevirtual #76                 // Method org$scalatest$tools$XmlReporter$Testcase$$$outer:()Lorg/scalatest/tools/XmlReporter;
         8: aload_1
         9: aload_2
        10: lload_3
        11: invokespecial #80                 // Method "<init>":(Lorg/scalatest/tools/XmlReporter;Ljava/lang/String;Lscala/Option;J)V
        14: areturn
      LineNumberTable:
        line 484: 0
        line 485: 10
      LocalVariableTable:
        Start  Length  Slot  Name   Signature
            0      15     0  this   Lorg/scalatest/tools/XmlReporter$Testcase;
            0      15     1  name   Ljava/lang/String;
            0      15     2 className   Lscala/Option;
            0      15     3 timeStamp   J
    Signature: #72                          // (Ljava/lang/String;Lscala/Option<Ljava/lang/String;>;J)Lorg/scalatest/tools/XmlReporter$Testcase;
    MethodParameters:
      Name                           Flags
      name                           final
      className                      final
      timeStamp                      final

  public java.lang.String copy$default$1();
    descriptor: ()Ljava/lang/String;
    flags: (0x0001) ACC_PUBLIC
    Code:
      stack=1, locals=1, args_size=1
         0: aload_0
         1: invokevirtual #83                 // Method name:()Ljava/lang/String;
         4: areturn
      LineNumberTable:
        line 484: 0
      LocalVariableTable:
        Start  Length  Slot  Name   Signature
            0       5     0  this   Lorg/scalatest/tools/XmlReporter$Testcase;

  public scala.Option<java.lang.String> copy$default$2();
    descriptor: ()Lscala/Option;
    flags: (0x0001) ACC_PUBLIC
    Code:
      stack=1, locals=1, args_size=1
         0: aload_0
         1: invokevirtual #86                 // Method className:()Lscala/Option;
         4: areturn
      LineNumberTable:
        line 484: 0
      LocalVariableTable:
        Start  Length  Slot  Name   Signature
            0       5     0  this   Lorg/scalatest/tools/XmlReporter$Testcase;
    Signature: #42                          // ()Lscala/Option<Ljava/lang/String;>;

  public long copy$default$3();
    descriptor: ()J
    flags: (0x0001) ACC_PUBLIC
    Code:
      stack=2, locals=1, args_size=1
         0: aload_0
         1: invokevirtual #89                 // Method timeStamp:()J
         4: lreturn
      LineNumberTable:
        line 485: 0
      LocalVariableTable:
        Start  Length  Slot  Name   Signature
            0       5     0  this   Lorg/scalatest/tools/XmlReporter$Testcase;

  public java.lang.String productPrefix();
    descriptor: ()Ljava/lang/String;
    flags: (0x0001) ACC_PUBLIC
    Code:
      stack=1, locals=1, args_size=1
         0: ldc           #91                 // String Testcase
         2: areturn
      LineNumberTable:
        line 484: 0
      LocalVariableTable:
        Start  Length  Slot  Name   Signature
            0       3     0  this   Lorg/scalatest/tools/XmlReporter$Testcase;

  public int productArity();
    descriptor: ()I
    flags: (0x0001) ACC_PUBLIC
    Code:
      stack=1, locals=1, args_size=1
         0: iconst_3
         1: ireturn
      LineNumberTable:
        line 484: 0
      LocalVariableTable:
        Start  Length  Slot  Name   Signature
            0       2     0  this   Lorg/scalatest/tools/XmlReporter$Testcase;

  public java.lang.Object productElement(int);
    descriptor: (I)Ljava/lang/Object;
    flags: (0x0001) ACC_PUBLIC
    Code:
      stack=2, locals=3, args_size=2
         0: iload_1
         1: istore_2
         2: iload_2
         3: tableswitch   { // 0 to 2
                       0: 28
                       1: 35
                       2: 42
                 default: 52
            }
        28: aload_0
        29: invokevirtual #83                 // Method name:()Ljava/lang/String;
        32: goto          59
        35: aload_0
        36: invokevirtual #86                 // Method className:()Lscala/Option;
        39: goto          59
        42: aload_0
        43: invokevirtual #89                 // Method timeStamp:()J
        46: invokestatic  #101                // Method scala/runtime/BoxesRunTime.boxToLong:(J)Ljava/lang/Long;
        49: goto          59
        52: iload_1
        53: invokestatic  #106                // Method scala/runtime/Statics.ioobe:(I)Ljava/lang/Object;
        56: goto          59
        59: areturn
      StackMapTable: number_of_entries = 5
        frame_type = 252 /* append */
          offset_delta = 28
          locals = [ int ]
        frame_type = 6 /* same */
        frame_type = 6 /* same */
        frame_type = 9 /* same */
        frame_type = 70 /* same_locals_1_stack_item */
          stack = [ class java/lang/Object ]
      LineNumberTable:
        line 484: 0
      LocalVariableTable:
        Start  Length  Slot  Name   Signature
            0      60     0  this   Lorg/scalatest/tools/XmlReporter$Testcase;
            0      60     1   x$1   I
    MethodParameters:
      Name                           Flags
      x$1                            final

  public scala.collection.Iterator<java.lang.Object> productIterator();
    descriptor: ()Lscala/collection/Iterator;
    flags: (0x0001) ACC_PUBLIC
    Code:
      stack=2, locals=1, args_size=1
         0: getstatic     #115                // Field scala/runtime/ScalaRunTime$.MODULE$:Lscala/runtime/ScalaRunTime$;
         3: aload_0
         4: invokevirtual #118                // Method scala/runtime/ScalaRunTime$.typedProductIterator:(Lscala/Product;)Lscala/collection/Iterator;
         7: areturn
      LineNumberTable:
        line 484: 0
      LocalVariableTable:
        Start  Length  Slot  Name   Signature
            0       8     0  this   Lorg/scalatest/tools/XmlReporter$Testcase;
    Signature: #109                         // ()Lscala/collection/Iterator<Ljava/lang/Object;>;

  public boolean canEqual(java.lang.Object);
    descriptor: (Ljava/lang/Object;)Z
    flags: (0x0001) ACC_PUBLIC
    Code:
      stack=1, locals=2, args_size=2
         0: aload_1
         1: instanceof    #2                  // class org/scalatest/tools/XmlReporter$Testcase
         4: ireturn
      LineNumberTable:
        line 484: 0
      LocalVariableTable:
        Start  Length  Slot  Name   Signature
            0       5     0  this   Lorg/scalatest/tools/XmlReporter$Testcase;
            0       5     1   x$1   Ljava/lang/Object;
    MethodParameters:
      Name                           Flags
      x$1                            final

  public java.lang.String productElementName(int);
    descriptor: (I)Ljava/lang/String;
    flags: (0x0001) ACC_PUBLIC
    Code:
      stack=1, locals=3, args_size=2
         0: iload_1
         1: istore_2
         2: iload_2
         3: tableswitch   { // 0 to 2
                       0: 28
                       1: 33
                       2: 38
                 default: 43
            }
        28: ldc           #124                // String name
        30: goto          53
        33: ldc           #125                // String className
        35: goto          53
        38: ldc           #126                // String timeStamp
        40: goto          53
        43: iload_1
        44: invokestatic  #106                // Method scala/runtime/Statics.ioobe:(I)Ljava/lang/Object;
        47: checkcast     #128                // class java/lang/String
        50: goto          53
        53: areturn
      StackMapTable: number_of_entries = 5
        frame_type = 252 /* append */
          offset_delta = 28
          locals = [ int ]
        frame_type = 4 /* same */
        frame_type = 4 /* same */
        frame_type = 4 /* same */
        frame_type = 73 /* same_locals_1_stack_item */
          stack = [ class java/lang/String ]
      LineNumberTable:
        line 484: 0
      LocalVariableTable:
        Start  Length  Slot  Name   Signature
            0      54     0  this   Lorg/scalatest/tools/XmlReporter$Testcase;
            0      54     1   x$1   I
    MethodParameters:
      Name                           Flags
      x$1                            final

  public int hashCode();
    descriptor: ()I
    flags: (0x0001) ACC_PUBLIC
    Code:
      stack=3, locals=2, args_size=1
         0: ldc           #130                // int -889275714
         2: istore_1
         3: iload_1
         4: aload_0
         5: invokevirtual #132                // Method productPrefix:()Ljava/lang/String;
         8: invokevirtual #134                // Method java/lang/String.hashCode:()I
        11: invokestatic  #138                // Method scala/runtime/Statics.mix:(II)I
        14: istore_1
        15: iload_1
        16: aload_0
        17: invokevirtual #83                 // Method name:()Ljava/lang/String;
        20: invokestatic  #142                // Method scala/runtime/Statics.anyHash:(Ljava/lang/Object;)I
        23: invokestatic  #138                // Method scala/runtime/Statics.mix:(II)I
        26: istore_1
        27: iload_1
        28: aload_0
        29: invokevirtual #86                 // Method className:()Lscala/Option;
        32: invokestatic  #142                // Method scala/runtime/Statics.anyHash:(Ljava/lang/Object;)I
        35: invokestatic  #138                // Method scala/runtime/Statics.mix:(II)I
        38: istore_1
        39: iload_1
        40: aload_0
        41: invokevirtual #89                 // Method timeStamp:()J
        44: invokestatic  #146                // Method scala/runtime/Statics.longHash:(J)I
        47: invokestatic  #138                // Method scala/runtime/Statics.mix:(II)I
        50: istore_1
        51: iload_1
        52: iconst_3
        53: invokestatic  #149                // Method scala/runtime/Statics.finalizeHash:(II)I
        56: ireturn
      LineNumberTable:
        line 484: 0
      LocalVariableTable:
        Start  Length  Slot  Name   Signature
            0      57     0  this   Lorg/scalatest/tools/XmlReporter$Testcase;

  public java.lang.String toString();
    descriptor: ()Ljava/lang/String;
    flags: (0x0001) ACC_PUBLIC
    Code:
      stack=2, locals=1, args_size=1
         0: getstatic     #115                // Field scala/runtime/ScalaRunTime$.MODULE$:Lscala/runtime/ScalaRunTime$;
         3: aload_0
         4: invokevirtual #154                // Method scala/runtime/ScalaRunTime$._toString:(Lscala/Product;)Ljava/lang/String;
         7: areturn
      LineNumberTable:
        line 484: 0
      LocalVariableTable:
        Start  Length  Slot  Name   Signature
            0       8     0  this   Lorg/scalatest/tools/XmlReporter$Testcase;

  public boolean equals(java.lang.Object);
    descriptor: (Ljava/lang/Object;)Z
    flags: (0x0001) ACC_PUBLIC
    Code:
      stack=4, locals=7, args_size=2
         0: aload_0
         1: aload_1
         2: if_acmpeq     145
         5: aload_1
         6: astore_3
         7: aload_3
         8: instanceof    #2                  // class org/scalatest/tools/XmlReporter$Testcase
        11: ifeq          33
        14: aload_3
        15: checkcast     #2                  // class org/scalatest/tools/XmlReporter$Testcase
        18: invokevirtual #76                 // Method org$scalatest$tools$XmlReporter$Testcase$$$outer:()Lorg/scalatest/tools/XmlReporter;
        21: aload_0
        22: invokevirtual #76                 // Method org$scalatest$tools$XmlReporter$Testcase$$$outer:()Lorg/scalatest/tools/XmlReporter;
        25: if_acmpne     33
        28: iconst_1
        29: istore_2
        30: goto          41
        33: goto          36
        36: iconst_0
        37: istore_2
        38: goto          41
        41: iload_2
        42: ifeq          149
        45: aload_1
        46: checkcast     #2                  // class org/scalatest/tools/XmlReporter$Testcase
        49: astore        4
        51: aload_0
        52: invokevirtual #89                 // Method timeStamp:()J
        55: aload         4
        57: invokevirtual #89                 // Method timeStamp:()J
        60: lcmp
        61: ifne          141
        64: aload_0
        65: invokevirtual #83                 // Method name:()Ljava/lang/String;
        68: aload         4
        70: invokevirtual #83                 // Method name:()Ljava/lang/String;
        73: astore        5
        75: dup
        76: ifnonnull     88
        79: pop
        80: aload         5
        82: ifnull        96
        85: goto          141
        88: aload         5
        90: invokevirtual #157                // Method java/lang/Object.equals:(Ljava/lang/Object;)Z
        93: ifeq          141
        96: aload_0
        97: invokevirtual #86                 // Method className:()Lscala/Option;
       100: aload         4
       102: invokevirtual #86                 // Method className:()Lscala/Option;
       105: astore        6
       107: dup
       108: ifnonnull     120
       111: pop
       112: aload         6
       114: ifnull        128
       117: goto          141
       120: aload         6
       122: invokevirtual #157                // Method java/lang/Object.equals:(Ljava/lang/Object;)Z
       125: ifeq          141
       128: aload         4
       130: aload_0
       131: invokevirtual #159                // Method canEqual:(Ljava/lang/Object;)Z
       134: ifeq          141
       137: iconst_1
       138: goto          142
       141: iconst_0
       142: ifeq          149
       145: iconst_1
       146: goto          150
       149: iconst_0
       150: ireturn
      StackMapTable: number_of_entries = 12
        frame_type = 253 /* append */
          offset_delta = 33
          locals = [ top, class java/lang/Object ]
        frame_type = 2 /* same */
        frame_type = 255 /* full_frame */
          offset_delta = 4
          locals = [ class org/scalatest/tools/XmlReporter$Testcase, class java/lang/Object, int, class java/lang/Object ]
          stack = []
        frame_type = 255 /* full_frame */
          offset_delta = 46
          locals = [ class org/scalatest/tools/XmlReporter$Testcase, class java/lang/Object, int, class java/lang/Object, class org/scalatest/tools/XmlReporter$Testcase, class java/lang/String ]
          stack = [ class java/lang/String ]
        frame_type = 7 /* same */
        frame_type = 255 /* full_frame */
          offset_delta = 23
          locals = [ class org/scalatest/tools/XmlReporter$Testcase, class java/lang/Object, int, class java/lang/Object, class org/scalatest/tools/XmlReporter$Testcase, class java/lang/String, class scala/Option ]
          stack = [ class scala/Option ]
        frame_type = 7 /* same */
        frame_type = 249 /* chop */
          offset_delta = 12
        frame_type = 64 /* same_locals_1_stack_item */
          stack = [ int ]
        frame_type = 248 /* chop */
          offset_delta = 2
        frame_type = 253 /* append */
          offset_delta = 3
          locals = [ int, class java/lang/Object ]
        frame_type = 255 /* full_frame */
          offset_delta = 0
          locals = [ class org/scalatest/tools/XmlReporter$Testcase, class java/lang/Object ]
          stack = [ int ]
      LineNumberTable:
        line 484: 0
      LocalVariableTable:
        Start  Length  Slot  Name   Signature
            0     151     0  this   Lorg/scalatest/tools/XmlReporter$Testcase;
            0     151     1   x$1   Ljava/lang/Object;
    MethodParameters:
      Name                           Flags
      x$1                            final

  public org.scalatest.tools.XmlReporter org$scalatest$tools$XmlReporter$Testcase$$$outer();
    descriptor: ()Lorg/scalatest/tools/XmlReporter;
    flags: (0x1001) ACC_PUBLIC, ACC_SYNTHETIC
    Code:
      stack=1, locals=1, args_size=1
         0: aload_0
         1: getfield      #163                // Field $outer:Lorg/scalatest/tools/XmlReporter;
         4: areturn
      LineNumberTable:
        line 484: 0
      LocalVariableTable:
        Start  Length  Slot  Name   Signature
            0       5     0  this   Lorg/scalatest/tools/XmlReporter$Testcase;

  public org.scalatest.tools.XmlReporter$Testcase(java.lang.String, scala.Option<java.lang.String>, long);
    descriptor: (Lorg/scalatest/tools/XmlReporter;Ljava/lang/String;Lscala/Option;J)V
    flags: (0x0001) ACC_PUBLIC
    Code:
      stack=3, locals=6, args_size=5
         0: aload_0
         1: aload_2
         2: putfield      #40                 // Field name:Ljava/lang/String;
         5: aload_0
         6: aload_3
         7: putfield      #44                 // Field className:Lscala/Option;
        10: aload_0
        11: lload         4
        13: putfield      #47                 // Field timeStamp:J
        16: aload_1
        17: ifnonnull     22
        20: aconst_null
        21: athrow
        22: aload_0
        23: aload_1
        24: putfield      #163                // Field $outer:Lorg/scalatest/tools/XmlReporter;
        27: aload_0
        28: invokespecial #167                // Method java/lang/Object."<init>":()V
        31: aload_0
        32: invokestatic  #171                // InterfaceMethod scala/Product.$init$:(Lscala/Product;)V
        35: aload_0
        36: lconst_0
        37: putfield      #49                 // Field time:J
        40: aload_0
        41: iconst_0
        42: putfield      #55                 // Field pending:Z
        45: aload_0
        46: iconst_0
        47: putfield      #59                 // Field canceled:Z
        50: aload_0
        51: iconst_0
        52: putfield      #62                 // Field ignored:Z
        55: aload_0
        56: getstatic     #176                // Field scala/None$.MODULE$:Lscala/None$;
        59: putfield      #66                 // Field failure:Lscala/Option;
        62: return
      StackMapTable: number_of_entries = 1
        frame_type = 22 /* same */
      LineNumberTable:
        line 484: 0
        line 485: 10
        line 484: 16
        line 486: 35
        line 487: 40
        line 488: 45
        line 489: 50
        line 490: 55
        line 484: 62
      LocalVariableTable:
        Start  Length  Slot  Name   Signature
            0      63     0  this   Lorg/scalatest/tools/XmlReporter$Testcase;
            0      63     1 $outer   Lorg/scalatest/tools/XmlReporter;
            0      63     2  name   Ljava/lang/String;
            0      63     3 className   Lscala/Option;
            0      63     4 timeStamp   J
    Signature: #164                         // (Ljava/lang/String;Lscala/Option<Ljava/lang/String;>;J)V
    MethodParameters:
      Name                           Flags
      $outer                         final synthetic
      name                           final
      className                      final
      timeStamp                      final
}
InnerClasses:
  private #12= #2 of #11;                 // Testcase=class org/scalatest/tools/XmlReporter$Testcase of class org/scalatest/tools/XmlReporter
SourceFile: "XmlReporter.scala"
  ScalaInlineInfo: length = 0x95 (unknown attribute)
   01 00 00 1D 00 4D 00 4E 00 00 77 00 78 00 00 17
   00 35 00 00 3C 00 39 00 00 0F 00 29 00 00 46 00
   47 00 00 51 00 26 00 00 54 00 29 00 00 57 00 2D
   00 00 9B 00 78 00 00 19 00 29 00 00 43 00 44 00
   00 81 00 5D 00 00 18 00 35 00 00 3F 00 39 00 00
   0D 00 26 00 00 49 00 4A 00 00 15 00 35 00 00 38
   00 39 00 00 5C 00 5D 00 00 5E 00 5F 00 00 7A 00
   7B 00 00 1D 00 1E 00 00 6C 00 1E 00 00 5A 00 26
   00 00 14 00 2D 00 00 12 00 2D 00 00 32 00 33 00
   00 96 00 26 00
  Scala: length = 0x0 (unknown attribute)

