Classfile /Users/mw/Projects/slang-braindump/.jar/jar11/assemble/slang-braindump/assemble/content/org/scalatest/tools/XmlReporterConfiguration.class
  Last modified May 29, 2022; size 6192 bytes
  SHA-256 checksum 70fdafb5426a832aeea82ca9f46fef796b71e3816274f01fce41ef5139cba189
  Compiled from "ReporterConfiguration.scala"
public class org.scalatest.tools.XmlReporterConfiguration extends org.scalatest.tools.ReporterConfiguration
  minor version: 0
  major version: 52
  flags: (0x0021) ACC_PUBLIC, ACC_SUPER
  this_class: #2                          // org/scalatest/tools/XmlReporterConfiguration
  super_class: #4                         // org/scalatest/tools/ReporterConfiguration
  interfaces: 0, fields: 2, methods: 19, attributes: 4
Constant pool:
    #1 = Utf8               org/scalatest/tools/XmlReporterConfiguration
    #2 = Class              #1            // org/scalatest/tools/XmlReporterConfiguration
    #3 = Utf8               org/scalatest/tools/ReporterConfiguration
    #4 = Class              #3            // org/scalatest/tools/ReporterConfiguration
    #5 = Utf8               ReporterConfiguration.scala
    #6 = Utf8               Lscala/reflect/ScalaSignature;
    #7 = Utf8               bytes
    #8 = Utf8               \u0006\u0005\u0005\u001dd!B\r\u001b\u0001j\u0001\u0003\u0002\u0003\u001d\u0001\u0005+\u0007I\u0011A\u001d\t\u0011\u0015\u0003!\u0011#Q\u0001\niB\u0001B\u0012\u0001\u0003\u0016\u0004%\ta\u0012\u0005\t\u0017\u0002\u0011\t\u0012)A\u0005\u0011\")A\n\u0001C\u0001\u001b\"9\u0011\u000bAA\u0001\n\u0003\u0011\u0006bB+\u0001#\u0003%\tA\u0016\u0005\bC\u0002\t\n\u0011\"\u0001c\u0011\u001d!\u0007!!A\u0005B\u0015Dq!\u001c\u0001\u0002\u0002\u0013\u0005a\u000eC\u0004s\u0001\u0005\u0005I\u0011A:\t\u000fe\u0004\u0011\u0011!C!u\"I\u00111\u0001\u0001\u0002\u0002\u0013\u0005\u0011Q\u0001\u0005\n\u0003\u001f\u0001\u0011\u0011!C!\u0003#A\u0011\"!\u0006\u0001\u0003\u0003%\t%a\u0006\t\u0013\u0005e\u0001!!A\u0005B\u0005m\u0001\"CA\u000f\u0001\u0005\u0005I\u0011IA\u0010\u000f)\t\u0019CGA\u0001\u0012\u0003Q\u0012Q\u0005\u0004\n3i\t\t\u0011#\u0001\u001b\u0003OAa\u0001T\n\u0005\u0002\u0005}\u0002\"CA\r\'\u0005\u0005IQIA\u000e\u0011%\t\teEA\u0001\n\u0003\u000b\u0019\u0005C\u0005\u0002JM\t\t\u0011\"!\u0002L!I\u0011QL\n\u0002\u0002\u0013%\u0011q\f\u0002\u001916d\'+\u001a9peR,\'oQ8oM&<WO]1uS>t\'BA\u000e\u001d\u0003\u0015!xn\u001c7t\u0015\tib$A\u0005tG\u0006d\u0017\r^3ti*\tq$A\u0002pe\u001e\u001cB\u0001A\u0011&WA\u0011!eI\u0007\u00025%\u0011AE\u0007\u0002\u0016%\u0016\u0004xN\u001d;fe\u000e{gNZ5hkJ\fG/[8o!\t1\u0013&D\u0001(\u0015\u0005A\u0013!B:dC2\f\u0017B\u0001\u0016(\u0005\u001d\u0001&o\u001c3vGR\u0004\"\u0001L\u001b\u000f\u00055\u001adB\u0001\u00183\u001b\u0005y#B\u0001\u00192\u0003\u0019a$o\\8u}\r\u0001\u0011\"\u0001\u0015\n\u0005Q:\u0013a\u00029bG.\fw-Z\u0005\u0003m]\u0012AbU3sS\u0006d\u0017N_1cY\u0016T!\u0001N\u0014\u0002\u0013\r|gNZ5h\'\u0016$X#\u0001\u001e\u0011\u0007mz$I\u0004\u0002={A\u0011afJ\u0005\u0003}\u001d\na\u0001\u0015:fI\u00164\u0017B\u0001!B\u0005\r\u0019V\r\u001e\u0006\u0003}\u001d\u0002\"AI\"\n\u0005\u0011S\"a\u0005*fa>\u0014H/\u001a:D_:4\u0017n\u001a)be\u0006l\u0017AC2p]\u001aLwmU3uA\u0005Aa-\u001b7f\u001d\u0006lW-F\u0001I!\tY\u0014*\u0003\u0002K\u0003\n11\u000b\u001e:j]\u001e\f\u0011BZ5mK:\u000bW.\u001a\u0011\u0002\rqJg.\u001b;?)\rqu\n\u0015\t\u0003E\u0001AQ\u0001O\u0003A\u0002iBQAR\u0003A\u0002!\u000bAaY8qsR\u0019aj\u0015+\t\u000fa2\u0001\u0013!a\u0001u!9aI\u0002I\u0001\u0002\u0004A\u0015AD2paf$C-\u001a4bk2$H%M\u000b\u0002/*\u0012!\bW\u0016\u00023B\u0011!lX\u0007\u00027*\u0011A,X\u0001\nk:\u001c\u0007.Z2lK\u0012T!AX\u0014\u0002\u0015\u0005tgn\u001c;bi&|g.\u0003\u0002a7\n\tRO\\2iK\u000e\\W\r\u001a,be&\fgnY3\u0002\u001d\r|\u0007/\u001f\u0013eK\u001a\fW\u000f\u001c;%eU\t1M\u000b\u0002I1\u0006i\u0001O]8ek\u000e$\bK]3gSb,\u0012A\u001a\t\u0003O2l\u0011\u0001\u001b\u0006\u0003S*\fA\u0001\\1oO*\t1.\u0001\u0003kCZ\f\u0017B\u0001&i\u00031\u0001(o\u001c3vGR\f%/\u001b;z+\u0005y\u0007C\u0001\u0014q\u0013\t\txEA\u0002J]R\fa\u0002\u001d:pIV\u001cG/\u00127f[\u0016tG\u000f\u0006\u0002uoB\u0011a%^\u0005\u0003m\u001e\u00121!\u00118z\u0011\u001dA8\"!AA\u0002=\f1\u0001\u001f\u00132\u0003=\u0001(o\u001c3vGRLE/\u001a:bi>\u0014X#A>\u0011\u0007q|H/D\u0001~\u0015\tqx%\u0001\u0006d_2dWm\u0019;j_:L1!!\u0001~\u0005!IE/\u001a:bi>\u0014\u0018\u0001C2b]\u0016\u000bX/\u00197\u0015\t\u0005\u001d\u0011Q\u0002\t\u0004M\u0005%\u0011bAA\u0006O\t9!i\\8mK\u0006t\u0007b\u0002=\u000e\u0003\u0003\u0005\r\u0001^\u0001\u0013aJ|G-^2u\u000b2,W.\u001a8u\u001d\u0006lW\rF\u0002g\u0003\'Aq\u0001\u001f\b\u0002\u0002\u0003\u0007q.\u0001\u0005iCND7i\u001c3f)\u0005y\u0017\u0001\u0003;p\'R\u0014\u0018N\\4\u0015\u0003\u0019\fa!Z9vC2\u001cH\u0003BA\u0004\u0003CAq\u0001_\t\u0002\u0002\u0003\u0007A/\u0001\rY[2\u0014V\r]8si\u0016\u00148i\u001c8gS\u001e,(/\u0019;j_:\u0004\"AI\n\u0014\u000bM\tI#!\u000e\u0011\u000f\u0005-\u0012\u0011\u0007\u001eI\u001d6\u0011\u0011Q\u0006\u0006\u0004\u0003_9\u0013a\u0002:v]RLW.Z\u0005\u0005\u0003g\tiCA\tBEN$(/Y2u\rVt7\r^5p]J\u0002B!a\u000e\u0002>5\u0011\u0011\u0011\b\u0006\u0004\u0003wQ\u0017AA5p\u0013\r1\u0014\u0011\b\u000b\u0003\u0003K\tQ!\u00199qYf$RATA#\u0003\u000fBQ\u0001\u000f\fA\u0002iBQA\u0012\fA\u0002!\u000bq!\u001e8baBd\u0017\u0010\u0006\u0003\u0002N\u0005e\u0003#\u0002\u0014\u0002P\u0005M\u0013bAA)O\t1q\n\u001d;j_:\u0004RAJA+u!K1!a\u0016(\u0005\u0019!V\u000f\u001d7fe!A\u00111L\f\u0002\u0002\u0003\u0007a*A\u0002yIA\nAb\u001e:ji\u0016\u0014V\r\u001d7bG\u0016$\"!!\u0019\u0011\u0007\u001d\f\u0019\'C\u0002\u0002f!\u0014aa\u00142kK\u000e$\b
    #9 = Utf8               configSet
   #10 = Utf8               Lscala/collection/immutable/Set;
   #11 = Utf8               Lscala/collection/immutable/Set<Lorg/scalatest/tools/ReporterConfigParam;>;
   #12 = Utf8               fileName
   #13 = Utf8               Ljava/lang/String;
   #14 = Utf8               unapply
   #15 = Utf8               (Lorg/scalatest/tools/XmlReporterConfiguration;)Lscala/Option;
   #16 = Utf8               (Lorg/scalatest/tools/XmlReporterConfiguration;)Lscala/Option<Lscala/Tuple2<Lscala/collection/immutable/Set<Lorg/scalatest/tools/ReporterConfigParam;>;Ljava/lang/String;>;>;
   #17 = Utf8               x$0
   #18 = Utf8               org/scalatest/tools/XmlReporterConfiguration$
   #19 = Class              #18           // org/scalatest/tools/XmlReporterConfiguration$
   #20 = Utf8               MODULE$
   #21 = Utf8               Lorg/scalatest/tools/XmlReporterConfiguration$;
   #22 = NameAndType        #20:#21       // MODULE$:Lorg/scalatest/tools/XmlReporterConfiguration$;
   #23 = Fieldref           #19.#22       // org/scalatest/tools/XmlReporterConfiguration$.MODULE$:Lorg/scalatest/tools/XmlReporterConfiguration$;
   #24 = NameAndType        #14:#15       // unapply:(Lorg/scalatest/tools/XmlReporterConfiguration;)Lscala/Option;
   #25 = Methodref          #19.#24       // org/scalatest/tools/XmlReporterConfiguration$.unapply:(Lorg/scalatest/tools/XmlReporterConfiguration;)Lscala/Option;
   #26 = Utf8               Lorg/scalatest/tools/XmlReporterConfiguration;
   #27 = Utf8               apply
   #28 = Utf8               (Lscala/collection/immutable/Set;Ljava/lang/String;)Lorg/scalatest/tools/XmlReporterConfiguration;
   #29 = Utf8               (Lscala/collection/immutable/Set<Lorg/scalatest/tools/ReporterConfigParam;>;Ljava/lang/String;)Lorg/scalatest/tools/XmlReporterConfiguration;
   #30 = NameAndType        #27:#28       // apply:(Lscala/collection/immutable/Set;Ljava/lang/String;)Lorg/scalatest/tools/XmlReporterConfiguration;
   #31 = Methodref          #19.#30       // org/scalatest/tools/XmlReporterConfiguration$.apply:(Lscala/collection/immutable/Set;Ljava/lang/String;)Lorg/scalatest/tools/XmlReporterConfiguration;
   #32 = Utf8               tupled
   #33 = Utf8               ()Lscala/Function1;
   #34 = Utf8               ()Lscala/Function1<Lscala/Tuple2<Lscala/collection/immutable/Set<Lorg/scalatest/tools/ReporterConfigParam;>;Ljava/lang/String;>;Lorg/scalatest/tools/XmlReporterConfiguration;>;
   #35 = NameAndType        #32:#33       // tupled:()Lscala/Function1;
   #36 = Methodref          #19.#35       // org/scalatest/tools/XmlReporterConfiguration$.tupled:()Lscala/Function1;
   #37 = Utf8               curried
   #38 = Utf8               ()Lscala/Function1<Lscala/collection/immutable/Set<Lorg/scalatest/tools/ReporterConfigParam;>;Lscala/Function1<Ljava/lang/String;Lorg/scalatest/tools/XmlReporterConfiguration;>;>;
   #39 = NameAndType        #37:#33       // curried:()Lscala/Function1;
   #40 = Methodref          #19.#39       // org/scalatest/tools/XmlReporterConfiguration$.curried:()Lscala/Function1;
   #41 = Utf8               ()Lscala/collection/immutable/Set;
   #42 = Utf8               ()Lscala/collection/immutable/Set<Lorg/scalatest/tools/ReporterConfigParam;>;
   #43 = NameAndType        #9:#10        // configSet:Lscala/collection/immutable/Set;
   #44 = Fieldref           #2.#43        // org/scalatest/tools/XmlReporterConfiguration.configSet:Lscala/collection/immutable/Set;
   #45 = Utf8               this
   #46 = Utf8               ()Ljava/lang/String;
   #47 = NameAndType        #12:#13       // fileName:Ljava/lang/String;
   #48 = Fieldref           #2.#47        // org/scalatest/tools/XmlReporterConfiguration.fileName:Ljava/lang/String;
   #49 = Utf8               copy
   #50 = Utf8               <init>
   #51 = Utf8               (Lscala/collection/immutable/Set;Ljava/lang/String;)V
   #52 = NameAndType        #50:#51       // "<init>":(Lscala/collection/immutable/Set;Ljava/lang/String;)V
   #53 = Methodref          #2.#52        // org/scalatest/tools/XmlReporterConfiguration."<init>":(Lscala/collection/immutable/Set;Ljava/lang/String;)V
   #54 = Utf8               copy$default$1
   #55 = NameAndType        #9:#41        // configSet:()Lscala/collection/immutable/Set;
   #56 = Methodref          #2.#55        // org/scalatest/tools/XmlReporterConfiguration.configSet:()Lscala/collection/immutable/Set;
   #57 = Utf8               copy$default$2
   #58 = NameAndType        #12:#46       // fileName:()Ljava/lang/String;
   #59 = Methodref          #2.#58        // org/scalatest/tools/XmlReporterConfiguration.fileName:()Ljava/lang/String;
   #60 = Utf8               productPrefix
   #61 = Utf8               XmlReporterConfiguration
   #62 = String             #61           // XmlReporterConfiguration
   #63 = Utf8               productArity
   #64 = Utf8               ()I
   #65 = Utf8               productElement
   #66 = Utf8               (I)Ljava/lang/Object;
   #67 = Utf8               x$1
   #68 = Utf8               scala/runtime/Statics
   #69 = Class              #68           // scala/runtime/Statics
   #70 = Utf8               ioobe
   #71 = NameAndType        #70:#66       // ioobe:(I)Ljava/lang/Object;
   #72 = Methodref          #69.#71       // scala/runtime/Statics.ioobe:(I)Ljava/lang/Object;
   #73 = Utf8               I
   #74 = Utf8               java/lang/Object
   #75 = Class              #74           // java/lang/Object
   #76 = Utf8               productIterator
   #77 = Utf8               ()Lscala/collection/Iterator;
   #78 = Utf8               ()Lscala/collection/Iterator<Ljava/lang/Object;>;
   #79 = Utf8               scala/runtime/ScalaRunTime$
   #80 = Class              #79           // scala/runtime/ScalaRunTime$
   #81 = Utf8               Lscala/runtime/ScalaRunTime$;
   #82 = NameAndType        #20:#81       // MODULE$:Lscala/runtime/ScalaRunTime$;
   #83 = Fieldref           #80.#82       // scala/runtime/ScalaRunTime$.MODULE$:Lscala/runtime/ScalaRunTime$;
   #84 = Utf8               typedProductIterator
   #85 = Utf8               (Lscala/Product;)Lscala/collection/Iterator;
   #86 = NameAndType        #84:#85       // typedProductIterator:(Lscala/Product;)Lscala/collection/Iterator;
   #87 = Methodref          #80.#86       // scala/runtime/ScalaRunTime$.typedProductIterator:(Lscala/Product;)Lscala/collection/Iterator;
   #88 = Utf8               canEqual
   #89 = Utf8               (Ljava/lang/Object;)Z
   #90 = Utf8               Ljava/lang/Object;
   #91 = Utf8               productElementName
   #92 = Utf8               (I)Ljava/lang/String;
   #93 = String             #9            // configSet
   #94 = String             #12           // fileName
   #95 = Utf8               java/lang/String
   #96 = Class              #95           // java/lang/String
   #97 = Utf8               hashCode
   #98 = Utf8               _hashCode
   #99 = Utf8               (Lscala/Product;)I
  #100 = NameAndType        #98:#99       // _hashCode:(Lscala/Product;)I
  #101 = Methodref          #80.#100      // scala/runtime/ScalaRunTime$._hashCode:(Lscala/Product;)I
  #102 = Utf8               toString
  #103 = Utf8               _toString
  #104 = Utf8               (Lscala/Product;)Ljava/lang/String;
  #105 = NameAndType        #103:#104     // _toString:(Lscala/Product;)Ljava/lang/String;
  #106 = Methodref          #80.#105      // scala/runtime/ScalaRunTime$._toString:(Lscala/Product;)Ljava/lang/String;
  #107 = Utf8               equals
  #108 = NameAndType        #107:#89      // equals:(Ljava/lang/Object;)Z
  #109 = Methodref          #75.#108      // java/lang/Object.equals:(Ljava/lang/Object;)Z
  #110 = NameAndType        #88:#89       // canEqual:(Ljava/lang/Object;)Z
  #111 = Methodref          #2.#110       // org/scalatest/tools/XmlReporterConfiguration.canEqual:(Ljava/lang/Object;)Z
  #112 = Utf8               scala/collection/immutable/Set
  #113 = Class              #112          // scala/collection/immutable/Set
  #114 = Utf8               (Lscala/collection/immutable/Set<Lorg/scalatest/tools/ReporterConfigParam;>;Ljava/lang/String;)V
  #115 = Utf8               ()V
  #116 = NameAndType        #50:#115      // "<init>":()V
  #117 = Methodref          #4.#116       // org/scalatest/tools/ReporterConfiguration."<init>":()V
  #118 = Utf8               Signature
  #119 = Utf8               Code
  #120 = Utf8               LocalVariableTable
  #121 = Utf8               MethodParameters
  #122 = Utf8               LineNumberTable
  #123 = Utf8               StackMapTable
  #124 = Utf8               SourceFile
  #125 = Utf8               RuntimeVisibleAnnotations
  #126 = Utf8               ScalaInlineInfo
  #127 = Utf8               ScalaSig
{
  private final scala.collection.immutable.Set<org.scalatest.tools.ReporterConfigParam> configSet;
    descriptor: Lscala/collection/immutable/Set;
    flags: (0x0012) ACC_PRIVATE, ACC_FINAL
    Signature: #11                          // Lscala/collection/immutable/Set<Lorg/scalatest/tools/ReporterConfigParam;>;

  private final java.lang.String fileName;
    descriptor: Ljava/lang/String;
    flags: (0x0012) ACC_PRIVATE, ACC_FINAL

  public static scala.Option<scala.Tuple2<scala.collection.immutable.Set<org.scalatest.tools.ReporterConfigParam>, java.lang.String>> unapply(org.scalatest.tools.XmlReporterConfiguration);
    descriptor: (Lorg/scalatest/tools/XmlReporterConfiguration;)Lscala/Option;
    flags: (0x0009) ACC_PUBLIC, ACC_STATIC
    Code:
      stack=2, locals=1, args_size=1
         0: getstatic     #23                 // Field org/scalatest/tools/XmlReporterConfiguration$.MODULE$:Lorg/scalatest/tools/XmlReporterConfiguration$;
         3: aload_0
         4: invokevirtual #25                 // Method org/scalatest/tools/XmlReporterConfiguration$.unapply:(Lorg/scalatest/tools/XmlReporterConfiguration;)Lscala/Option;
         7: areturn
      LocalVariableTable:
        Start  Length  Slot  Name   Signature
            0       8     0   x$0   Lorg/scalatest/tools/XmlReporterConfiguration;
    Signature: #16                          // (Lorg/scalatest/tools/XmlReporterConfiguration;)Lscala/Option<Lscala/Tuple2<Lscala/collection/immutable/Set<Lorg/scalatest/tools/ReporterConfigParam;>;Ljava/lang/String;>;>;
    MethodParameters:
      Name                           Flags
      x$0                            final

  public static org.scalatest.tools.XmlReporterConfiguration apply(scala.collection.immutable.Set<org.scalatest.tools.ReporterConfigParam>, java.lang.String);
    descriptor: (Lscala/collection/immutable/Set;Ljava/lang/String;)Lorg/scalatest/tools/XmlReporterConfiguration;
    flags: (0x0009) ACC_PUBLIC, ACC_STATIC
    Code:
      stack=3, locals=2, args_size=2
         0: getstatic     #23                 // Field org/scalatest/tools/XmlReporterConfiguration$.MODULE$:Lorg/scalatest/tools/XmlReporterConfiguration$;
         3: aload_0
         4: aload_1
         5: invokevirtual #31                 // Method org/scalatest/tools/XmlReporterConfiguration$.apply:(Lscala/collection/immutable/Set;Ljava/lang/String;)Lorg/scalatest/tools/XmlReporterConfiguration;
         8: areturn
      LocalVariableTable:
        Start  Length  Slot  Name   Signature
            0       9     0 configSet   Lscala/collection/immutable/Set;
            0       9     1 fileName   Ljava/lang/String;
    Signature: #29                          // (Lscala/collection/immutable/Set<Lorg/scalatest/tools/ReporterConfigParam;>;Ljava/lang/String;)Lorg/scalatest/tools/XmlReporterConfiguration;
    MethodParameters:
      Name                           Flags
      configSet                      final
      fileName                       final

  public static scala.Function1<scala.Tuple2<scala.collection.immutable.Set<org.scalatest.tools.ReporterConfigParam>, java.lang.String>, org.scalatest.tools.XmlReporterConfiguration> tupled();
    descriptor: ()Lscala/Function1;
    flags: (0x0009) ACC_PUBLIC, ACC_STATIC
    Code:
      stack=1, locals=0, args_size=0
         0: getstatic     #23                 // Field org/scalatest/tools/XmlReporterConfiguration$.MODULE$:Lorg/scalatest/tools/XmlReporterConfiguration$;
         3: invokevirtual #36                 // Method org/scalatest/tools/XmlReporterConfiguration$.tupled:()Lscala/Function1;
         6: areturn
    Signature: #34                          // ()Lscala/Function1<Lscala/Tuple2<Lscala/collection/immutable/Set<Lorg/scalatest/tools/ReporterConfigParam;>;Ljava/lang/String;>;Lorg/scalatest/tools/XmlReporterConfiguration;>;

  public static scala.Function1<scala.collection.immutable.Set<org.scalatest.tools.ReporterConfigParam>, scala.Function1<java.lang.String, org.scalatest.tools.XmlReporterConfiguration>> curried();
    descriptor: ()Lscala/Function1;
    flags: (0x0009) ACC_PUBLIC, ACC_STATIC
    Code:
      stack=1, locals=0, args_size=0
         0: getstatic     #23                 // Field org/scalatest/tools/XmlReporterConfiguration$.MODULE$:Lorg/scalatest/tools/XmlReporterConfiguration$;
         3: invokevirtual #40                 // Method org/scalatest/tools/XmlReporterConfiguration$.curried:()Lscala/Function1;
         6: areturn
    Signature: #38                          // ()Lscala/Function1<Lscala/collection/immutable/Set<Lorg/scalatest/tools/ReporterConfigParam;>;Lscala/Function1<Ljava/lang/String;Lorg/scalatest/tools/XmlReporterConfiguration;>;>;

  public scala.collection.immutable.Set<org.scalatest.tools.ReporterConfigParam> configSet();
    descriptor: ()Lscala/collection/immutable/Set;
    flags: (0x0001) ACC_PUBLIC
    Code:
      stack=1, locals=1, args_size=1
         0: aload_0
         1: getfield      #44                 // Field configSet:Lscala/collection/immutable/Set;
         4: areturn
      LineNumberTable:
        line 34: 0
      LocalVariableTable:
        Start  Length  Slot  Name   Signature
            0       5     0  this   Lorg/scalatest/tools/XmlReporterConfiguration;
    Signature: #42                          // ()Lscala/collection/immutable/Set<Lorg/scalatest/tools/ReporterConfigParam;>;

  public java.lang.String fileName();
    descriptor: ()Ljava/lang/String;
    flags: (0x0001) ACC_PUBLIC
    Code:
      stack=1, locals=1, args_size=1
         0: aload_0
         1: getfield      #48                 // Field fileName:Ljava/lang/String;
         4: areturn
      LineNumberTable:
        line 34: 0
      LocalVariableTable:
        Start  Length  Slot  Name   Signature
            0       5     0  this   Lorg/scalatest/tools/XmlReporterConfiguration;

  public org.scalatest.tools.XmlReporterConfiguration copy(scala.collection.immutable.Set<org.scalatest.tools.ReporterConfigParam>, java.lang.String);
    descriptor: (Lscala/collection/immutable/Set;Ljava/lang/String;)Lorg/scalatest/tools/XmlReporterConfiguration;
    flags: (0x0001) ACC_PUBLIC
    Code:
      stack=4, locals=3, args_size=3
         0: new           #2                  // class org/scalatest/tools/XmlReporterConfiguration
         3: dup
         4: aload_1
         5: aload_2
         6: invokespecial #53                 // Method "<init>":(Lscala/collection/immutable/Set;Ljava/lang/String;)V
         9: areturn
      LineNumberTable:
        line 34: 0
      LocalVariableTable:
        Start  Length  Slot  Name   Signature
            0      10     0  this   Lorg/scalatest/tools/XmlReporterConfiguration;
            0      10     1 configSet   Lscala/collection/immutable/Set;
            0      10     2 fileName   Ljava/lang/String;
    Signature: #29                          // (Lscala/collection/immutable/Set<Lorg/scalatest/tools/ReporterConfigParam;>;Ljava/lang/String;)Lorg/scalatest/tools/XmlReporterConfiguration;
    MethodParameters:
      Name                           Flags
      configSet                      final
      fileName                       final

  public scala.collection.immutable.Set<org.scalatest.tools.ReporterConfigParam> copy$default$1();
    descriptor: ()Lscala/collection/immutable/Set;
    flags: (0x0001) ACC_PUBLIC
    Code:
      stack=1, locals=1, args_size=1
         0: aload_0
         1: invokevirtual #56                 // Method configSet:()Lscala/collection/immutable/Set;
         4: areturn
      LineNumberTable:
        line 34: 0
      LocalVariableTable:
        Start  Length  Slot  Name   Signature
            0       5     0  this   Lorg/scalatest/tools/XmlReporterConfiguration;
    Signature: #42                          // ()Lscala/collection/immutable/Set<Lorg/scalatest/tools/ReporterConfigParam;>;

  public java.lang.String copy$default$2();
    descriptor: ()Ljava/lang/String;
    flags: (0x0001) ACC_PUBLIC
    Code:
      stack=1, locals=1, args_size=1
         0: aload_0
         1: invokevirtual #59                 // Method fileName:()Ljava/lang/String;
         4: areturn
      LineNumberTable:
        line 34: 0
      LocalVariableTable:
        Start  Length  Slot  Name   Signature
            0       5     0  this   Lorg/scalatest/tools/XmlReporterConfiguration;

  public java.lang.String productPrefix();
    descriptor: ()Ljava/lang/String;
    flags: (0x0001) ACC_PUBLIC
    Code:
      stack=1, locals=1, args_size=1
         0: ldc           #62                 // String XmlReporterConfiguration
         2: areturn
      LineNumberTable:
        line 34: 0
      LocalVariableTable:
        Start  Length  Slot  Name   Signature
            0       3     0  this   Lorg/scalatest/tools/XmlReporterConfiguration;

  public int productArity();
    descriptor: ()I
    flags: (0x0001) ACC_PUBLIC
    Code:
      stack=1, locals=1, args_size=1
         0: iconst_2
         1: ireturn
      LineNumberTable:
        line 34: 0
      LocalVariableTable:
        Start  Length  Slot  Name   Signature
            0       2     0  this   Lorg/scalatest/tools/XmlReporterConfiguration;

  public java.lang.Object productElement(int);
    descriptor: (I)Ljava/lang/Object;
    flags: (0x0001) ACC_PUBLIC
    Code:
      stack=1, locals=3, args_size=2
         0: iload_1
         1: istore_2
         2: iload_2
         3: tableswitch   { // 0 to 1
                       0: 24
                       1: 31
                 default: 38
            }
        24: aload_0
        25: invokevirtual #56                 // Method configSet:()Lscala/collection/immutable/Set;
        28: goto          45
        31: aload_0
        32: invokevirtual #59                 // Method fileName:()Ljava/lang/String;
        35: goto          45
        38: iload_1
        39: invokestatic  #72                 // Method scala/runtime/Statics.ioobe:(I)Ljava/lang/Object;
        42: goto          45
        45: areturn
      StackMapTable: number_of_entries = 4
        frame_type = 252 /* append */
          offset_delta = 24
          locals = [ int ]
        frame_type = 6 /* same */
        frame_type = 6 /* same */
        frame_type = 70 /* same_locals_1_stack_item */
          stack = [ class java/lang/Object ]
      LineNumberTable:
        line 34: 0
      LocalVariableTable:
        Start  Length  Slot  Name   Signature
            0      46     0  this   Lorg/scalatest/tools/XmlReporterConfiguration;
            0      46     1   x$1   I
    MethodParameters:
      Name                           Flags
      x$1                            final

  public scala.collection.Iterator<java.lang.Object> productIterator();
    descriptor: ()Lscala/collection/Iterator;
    flags: (0x0001) ACC_PUBLIC
    Code:
      stack=2, locals=1, args_size=1
         0: getstatic     #83                 // Field scala/runtime/ScalaRunTime$.MODULE$:Lscala/runtime/ScalaRunTime$;
         3: aload_0
         4: invokevirtual #87                 // Method scala/runtime/ScalaRunTime$.typedProductIterator:(Lscala/Product;)Lscala/collection/Iterator;
         7: areturn
      LineNumberTable:
        line 34: 0
      LocalVariableTable:
        Start  Length  Slot  Name   Signature
            0       8     0  this   Lorg/scalatest/tools/XmlReporterConfiguration;
    Signature: #78                          // ()Lscala/collection/Iterator<Ljava/lang/Object;>;

  public boolean canEqual(java.lang.Object);
    descriptor: (Ljava/lang/Object;)Z
    flags: (0x0001) ACC_PUBLIC
    Code:
      stack=1, locals=2, args_size=2
         0: aload_1
         1: instanceof    #2                  // class org/scalatest/tools/XmlReporterConfiguration
         4: ireturn
      LineNumberTable:
        line 34: 0
      LocalVariableTable:
        Start  Length  Slot  Name   Signature
            0       5     0  this   Lorg/scalatest/tools/XmlReporterConfiguration;
            0       5     1   x$1   Ljava/lang/Object;
    MethodParameters:
      Name                           Flags
      x$1                            final

  public java.lang.String productElementName(int);
    descriptor: (I)Ljava/lang/String;
    flags: (0x0001) ACC_PUBLIC
    Code:
      stack=1, locals=3, args_size=2
         0: iload_1
         1: istore_2
         2: iload_2
         3: tableswitch   { // 0 to 1
                       0: 24
                       1: 29
                 default: 34
            }
        24: ldc           #93                 // String configSet
        26: goto          44
        29: ldc           #94                 // String fileName
        31: goto          44
        34: iload_1
        35: invokestatic  #72                 // Method scala/runtime/Statics.ioobe:(I)Ljava/lang/Object;
        38: checkcast     #96                 // class java/lang/String
        41: goto          44
        44: areturn
      StackMapTable: number_of_entries = 4
        frame_type = 252 /* append */
          offset_delta = 24
          locals = [ int ]
        frame_type = 4 /* same */
        frame_type = 4 /* same */
        frame_type = 73 /* same_locals_1_stack_item */
          stack = [ class java/lang/String ]
      LineNumberTable:
        line 34: 0
      LocalVariableTable:
        Start  Length  Slot  Name   Signature
            0      45     0  this   Lorg/scalatest/tools/XmlReporterConfiguration;
            0      45     1   x$1   I
    MethodParameters:
      Name                           Flags
      x$1                            final

  public int hashCode();
    descriptor: ()I
    flags: (0x0001) ACC_PUBLIC
    Code:
      stack=2, locals=1, args_size=1
         0: getstatic     #83                 // Field scala/runtime/ScalaRunTime$.MODULE$:Lscala/runtime/ScalaRunTime$;
         3: aload_0
         4: invokevirtual #101                // Method scala/runtime/ScalaRunTime$._hashCode:(Lscala/Product;)I
         7: ireturn
      LineNumberTable:
        line 34: 0
      LocalVariableTable:
        Start  Length  Slot  Name   Signature
            0       8     0  this   Lorg/scalatest/tools/XmlReporterConfiguration;

  public java.lang.String toString();
    descriptor: ()Ljava/lang/String;
    flags: (0x0001) ACC_PUBLIC
    Code:
      stack=2, locals=1, args_size=1
         0: getstatic     #83                 // Field scala/runtime/ScalaRunTime$.MODULE$:Lscala/runtime/ScalaRunTime$;
         3: aload_0
         4: invokevirtual #106                // Method scala/runtime/ScalaRunTime$._toString:(Lscala/Product;)Ljava/lang/String;
         7: areturn
      LineNumberTable:
        line 34: 0
      LocalVariableTable:
        Start  Length  Slot  Name   Signature
            0       8     0  this   Lorg/scalatest/tools/XmlReporterConfiguration;

  public boolean equals(java.lang.Object);
    descriptor: (Ljava/lang/Object;)Z
    flags: (0x0001) ACC_PUBLIC
    Code:
      stack=2, locals=7, args_size=2
         0: aload_0
         1: aload_1
         2: if_acmpeq     118
         5: aload_1
         6: astore_3
         7: aload_3
         8: instanceof    #2                  // class org/scalatest/tools/XmlReporterConfiguration
        11: ifeq          19
        14: iconst_1
        15: istore_2
        16: goto          27
        19: goto          22
        22: iconst_0
        23: istore_2
        24: goto          27
        27: iload_2
        28: ifeq          122
        31: aload_1
        32: checkcast     #2                  // class org/scalatest/tools/XmlReporterConfiguration
        35: astore        4
        37: aload_0
        38: invokevirtual #56                 // Method configSet:()Lscala/collection/immutable/Set;
        41: aload         4
        43: invokevirtual #56                 // Method configSet:()Lscala/collection/immutable/Set;
        46: astore        5
        48: dup
        49: ifnonnull     61
        52: pop
        53: aload         5
        55: ifnull        69
        58: goto          114
        61: aload         5
        63: invokevirtual #109                // Method java/lang/Object.equals:(Ljava/lang/Object;)Z
        66: ifeq          114
        69: aload_0
        70: invokevirtual #59                 // Method fileName:()Ljava/lang/String;
        73: aload         4
        75: invokevirtual #59                 // Method fileName:()Ljava/lang/String;
        78: astore        6
        80: dup
        81: ifnonnull     93
        84: pop
        85: aload         6
        87: ifnull        101
        90: goto          114
        93: aload         6
        95: invokevirtual #109                // Method java/lang/Object.equals:(Ljava/lang/Object;)Z
        98: ifeq          114
       101: aload         4
       103: aload_0
       104: invokevirtual #111                // Method canEqual:(Ljava/lang/Object;)Z
       107: ifeq          114
       110: iconst_1
       111: goto          115
       114: iconst_0
       115: ifeq          122
       118: iconst_1
       119: goto          123
       122: iconst_0
       123: ireturn
      StackMapTable: number_of_entries = 12
        frame_type = 253 /* append */
          offset_delta = 19
          locals = [ top, class java/lang/Object ]
        frame_type = 2 /* same */
        frame_type = 255 /* full_frame */
          offset_delta = 4
          locals = [ class org/scalatest/tools/XmlReporterConfiguration, class java/lang/Object, int, class java/lang/Object ]
          stack = []
        frame_type = 255 /* full_frame */
          offset_delta = 33
          locals = [ class org/scalatest/tools/XmlReporterConfiguration, class java/lang/Object, int, class java/lang/Object, class org/scalatest/tools/XmlReporterConfiguration, class scala/collection/immutable/Set ]
          stack = [ class scala/collection/immutable/Set ]
        frame_type = 7 /* same */
        frame_type = 255 /* full_frame */
          offset_delta = 23
          locals = [ class org/scalatest/tools/XmlReporterConfiguration, class java/lang/Object, int, class java/lang/Object, class org/scalatest/tools/XmlReporterConfiguration, class scala/collection/immutable/Set, class java/lang/String ]
          stack = [ class java/lang/String ]
        frame_type = 7 /* same */
        frame_type = 250 /* chop */
          offset_delta = 12
        frame_type = 64 /* same_locals_1_stack_item */
          stack = [ int ]
        frame_type = 255 /* full_frame */
          offset_delta = 2
          locals = [ class org/scalatest/tools/XmlReporterConfiguration, class java/lang/Object ]
          stack = []
        frame_type = 253 /* append */
          offset_delta = 3
          locals = [ int, class java/lang/Object ]
        frame_type = 255 /* full_frame */
          offset_delta = 0
          locals = [ class org/scalatest/tools/XmlReporterConfiguration, class java/lang/Object ]
          stack = [ int ]
      LineNumberTable:
        line 34: 0
      LocalVariableTable:
        Start  Length  Slot  Name   Signature
            0     124     0  this   Lorg/scalatest/tools/XmlReporterConfiguration;
            0     124     1   x$1   Ljava/lang/Object;
    MethodParameters:
      Name                           Flags
      x$1                            final

  public org.scalatest.tools.XmlReporterConfiguration(scala.collection.immutable.Set<org.scalatest.tools.ReporterConfigParam>, java.lang.String);
    descriptor: (Lscala/collection/immutable/Set;Ljava/lang/String;)V
    flags: (0x0001) ACC_PUBLIC
    Code:
      stack=2, locals=3, args_size=3
         0: aload_0
         1: aload_1
         2: putfield      #44                 // Field configSet:Lscala/collection/immutable/Set;
         5: aload_0
         6: aload_2
         7: putfield      #48                 // Field fileName:Ljava/lang/String;
        10: aload_0
        11: invokespecial #117                // Method org/scalatest/tools/ReporterConfiguration."<init>":()V
        14: return
      LineNumberTable:
        line 34: 0
      LocalVariableTable:
        Start  Length  Slot  Name   Signature
            0      15     0  this   Lorg/scalatest/tools/XmlReporterConfiguration;
            0      15     1 configSet   Lscala/collection/immutable/Set;
            0      15     2 fileName   Ljava/lang/String;
    Signature: #114                         // (Lscala/collection/immutable/Set<Lorg/scalatest/tools/ReporterConfigParam;>;Ljava/lang/String;)V
    MethodParameters:
      Name                           Flags
      configSet                      final
      fileName                       final
}
SourceFile: "ReporterConfiguration.scala"
RuntimeVisibleAnnotations:
  0: #6(#7=s#8)
    scala.reflect.ScalaSignature(
      bytes="\u0006\u0005\u0005\u001dd!B\r\u001b\u0001j\u0001\u0003\u0002\u0003\u001d\u0001\u0005+\u0007I\u0011A\u001d\t\u0011\u0015\u0003!\u0011#Q\u0001\niB\u0001B\u0012\u0001\u0003\u0016\u0004%\ta\u0012\u0005\t\u0017\u0002\u0011\t\u0012)A\u0005\u0011\")A\n\u0001C\u0001\u001b\"9\u0011\u000bAA\u0001\n\u0003\u0011\u0006bB+\u0001#\u0003%\tA\u0016\u0005\bC\u0002\t\n\u0011\"\u0001c\u0011\u001d!\u0007!!A\u0005B\u0015Dq!\u001c\u0001\u0002\u0002\u0013\u0005a\u000eC\u0004s\u0001\u0005\u0005I\u0011A:\t\u000fe\u0004\u0011\u0011!C!u\"I\u00111\u0001\u0001\u0002\u0002\u0013\u0005\u0011Q\u0001\u0005\n\u0003\u001f\u0001\u0011\u0011!C!\u0003#A\u0011\"!\u0006\u0001\u0003\u0003%\t%a\u0006\t\u0013\u0005e\u0001!!A\u0005B\u0005m\u0001\"CA\u000f\u0001\u0005\u0005I\u0011IA\u0010\u000f)\t\u0019CGA\u0001\u0012\u0003Q\u0012Q\u0005\u0004\n3i\t\t\u0011#\u0001\u001b\u0003OAa\u0001T\n\u0005\u0002\u0005}\u0002\"CA\r\'\u0005\u0005IQIA\u000e\u0011%\t\teEA\u0001\n\u0003\u000b\u0019\u0005C\u0005\u0002JM\t\t\u0011\"!\u0002L!I\u0011QL\n\u0002\u0002\u0013%\u0011q\f\u0002\u001916d\'+\u001a9peR,\'oQ8oM&<WO]1uS>t\'BA\u000e\u001d\u0003\u0015!xn\u001c7t\u0015\tib$A\u0005tG\u0006d\u0017\r^3ti*\tq$A\u0002pe\u001e\u001cB\u0001A\u0011&WA\u0011!eI\u0007\u00025%\u0011AE\u0007\u0002\u0016%\u0016\u0004xN\u001d;fe\u000e{gNZ5hkJ\fG/[8o!\t1\u0013&D\u0001(\u0015\u0005A\u0013!B:dC2\f\u0017B\u0001\u0016(\u0005\u001d\u0001&o\u001c3vGR\u0004\"\u0001L\u001b\u000f\u00055\u001adB\u0001\u00183\u001b\u0005y#B\u0001\u00192\u0003\u0019a$o\\8u}\r\u0001\u0011\"\u0001\u0015\n\u0005Q:\u0013a\u00029bG.\fw-Z\u0005\u0003m]\u0012AbU3sS\u0006d\u0017N_1cY\u0016T!\u0001N\u0014\u0002\u0013\r|gNZ5h\'\u0016$X#\u0001\u001e\u0011\u0007mz$I\u0004\u0002={A\u0011afJ\u0005\u0003}\u001d\na\u0001\u0015:fI\u00164\u0017B\u0001!B\u0005\r\u0019V\r\u001e\u0006\u0003}\u001d\u0002\"AI\"\n\u0005\u0011S\"a\u0005*fa>\u0014H/\u001a:D_:4\u0017n\u001a)be\u0006l\u0017AC2p]\u001aLwmU3uA\u0005Aa-\u001b7f\u001d\u0006lW-F\u0001I!\tY\u0014*\u0003\u0002K\u0003\n11\u000b\u001e:j]\u001e\f\u0011BZ5mK:\u000bW.\u001a\u0011\u0002\rqJg.\u001b;?)\rqu\n\u0015\t\u0003E\u0001AQ\u0001O\u0003A\u0002iBQAR\u0003A\u0002!\u000bAaY8qsR\u0019aj\u0015+\t\u000fa2\u0001\u0013!a\u0001u!9aI\u0002I\u0001\u0002\u0004A\u0015AD2paf$C-\u001a4bk2$H%M\u000b\u0002/*\u0012!\bW\u0016\u00023B\u0011!lX\u0007\u00027*\u0011A,X\u0001\nk:\u001c\u0007.Z2lK\u0012T!AX\u0014\u0002\u0015\u0005tgn\u001c;bi&|g.\u0003\u0002a7\n\tRO\\2iK\u000e\\W\r\u001a,be&\fgnY3\u0002\u001d\r|\u0007/\u001f\u0013eK\u001a\fW\u000f\u001c;%eU\t1M\u000b\u0002I1\u0006i\u0001O]8ek\u000e$\bK]3gSb,\u0012A\u001a\t\u0003O2l\u0011\u0001\u001b\u0006\u0003S*\fA\u0001\\1oO*\t1.\u0001\u0003kCZ\f\u0017B\u0001&i\u00031\u0001(o\u001c3vGR\f%/\u001b;z+\u0005y\u0007C\u0001\u0014q\u0013\t\txEA\u0002J]R\fa\u0002\u001d:pIV\u001cG/\u00127f[\u0016tG\u000f\u0006\u0002uoB\u0011a%^\u0005\u0003m\u001e\u00121!\u00118z\u0011\u001dA8\"!AA\u0002=\f1\u0001\u001f\u00132\u0003=\u0001(o\u001c3vGRLE/\u001a:bi>\u0014X#A>\u0011\u0007q|H/D\u0001~\u0015\tqx%\u0001\u0006d_2dWm\u0019;j_:L1!!\u0001~\u0005!IE/\u001a:bi>\u0014\u0018\u0001C2b]\u0016\u000bX/\u00197\u0015\t\u0005\u001d\u0011Q\u0002\t\u0004M\u0005%\u0011bAA\u0006O\t9!i\\8mK\u0006t\u0007b\u0002=\u000e\u0003\u0003\u0005\r\u0001^\u0001\u0013aJ|G-^2u\u000b2,W.\u001a8u\u001d\u0006lW\rF\u0002g\u0003\'Aq\u0001\u001f\b\u0002\u0002\u0003\u0007q.\u0001\u0005iCND7i\u001c3f)\u0005y\u0017\u0001\u0003;p\'R\u0014\u0018N\\4\u0015\u0003\u0019\fa!Z9vC2\u001cH\u0003BA\u0004\u0003CAq\u0001_\t\u0002\u0002\u0003\u0007A/\u0001\rY[2\u0014V\r]8si\u0016\u00148i\u001c8gS\u001e,(/\u0019;j_:\u0004\"AI\n\u0014\u000bM\tI#!\u000e\u0011\u000f\u0005-\u0012\u0011\u0007\u001eI\u001d6\u0011\u0011Q\u0006\u0006\u0004\u0003_9\u0013a\u0002:v]RLW.Z\u0005\u0005\u0003g\tiCA\tBEN$(/Y2u\rVt7\r^5p]J\u0002B!a\u000e\u0002>5\u0011\u0011\u0011\b\u0006\u0004\u0003wQ\u0017AA5p\u0013\r1\u0014\u0011\b\u000b\u0003\u0003K\tQ!\u00199qYf$RATA#\u0003\u000fBQ\u0001\u000f\fA\u0002iBQA\u0012\fA\u0002!\u000bq!\u001e8baBd\u0017\u0010\u0006\u0003\u0002N\u0005e\u0003#\u0002\u0014\u0002P\u0005M\u0013bAA)O\t1q\n\u001d;j_:\u0004RAJA+u!K1!a\u0016(\u0005\u0019!V\u000f\u001d7fe!A\u00111L\f\u0002\u0002\u0003\u0007a*A\u0002yIA\nAb\u001e:ji\u0016\u0014V\r\u001d7bG\u0016$\"!!\u0019\u0011\u0007\u001d\f\u0019\'C\u0002\u0002f!\u0014aa\u00142kK\u000e$\b"
    )
  ScalaInlineInfo: length = 0x4F (unknown attribute)
   01 00 00 0F 00 32 00 33 00 00 58 00 59 00 00 09
   00 29 00 00 31 00 1C 00 00 36 00 29 00 00 39 00
   2E 00 00 6B 00 59 00 00 0C 00 2E 00 00 61 00 40
   00 00 3F 00 40 00 00 41 00 42 00 00 5B 00 5C 00
   00 4C 00 4D 00 00 3C 00 2E 00 00 66 00 2E 00
  ScalaSig: length = 0x3 (unknown attribute)
   05 02 00
