Classfile /Users/mw/Projects/slang-braindump/.jar/jar11/assemble/slang-braindump/assemble/content/org/scalatest/tools/XmlSocketReporterConfiguration.class
  Last modified May 29, 2022; size 5518 bytes
  SHA-256 checksum 4be3e4060b64483c5787b4909d27fdcc2ae61ee7d5244f540bdfd91e917f9d80
  Compiled from "ReporterConfiguration.scala"
public class org.scalatest.tools.XmlSocketReporterConfiguration extends org.scalatest.tools.ReporterConfiguration
  minor version: 0
  major version: 52
  flags: (0x0021) ACC_PUBLIC, ACC_SUPER
  this_class: #2                          // org/scalatest/tools/XmlSocketReporterConfiguration
  super_class: #4                         // org/scalatest/tools/ReporterConfiguration
  interfaces: 0, fields: 2, methods: 19, attributes: 4
Constant pool:
    #1 = Utf8               org/scalatest/tools/XmlSocketReporterConfiguration
    #2 = Class              #1            // org/scalatest/tools/XmlSocketReporterConfiguration
    #3 = Utf8               org/scalatest/tools/ReporterConfiguration
    #4 = Class              #3            // org/scalatest/tools/ReporterConfiguration
    #5 = Utf8               ReporterConfiguration.scala
    #6 = Utf8               Lscala/reflect/ScalaSignature;
    #7 = Utf8               bytes
    #8 = Utf8               \u0006\u0005\u0005ec!B\r\u001b\u0001j\u0001\u0003\u0002\u0003\u001d\u0001\u0005+\u0007I\u0011A\u001d\t\u0011\t\u0003!\u0011#Q\u0001\niB\u0001b\u0011\u0001\u0003\u0016\u0004%\t\u0001\u0012\u0005\t\u0011\u0002\u0011\t\u0012)A\u0005\u000b\")\u0011\n\u0001C\u0001\u0015\"9a\nAA\u0001\n\u0003y\u0005b\u0002*\u0001#\u0003%\ta\u0015\u0005\b=\u0002\t\n\u0011\"\u0001`\u0011\u001d\t\u0007!!A\u0005B\tDqA\u001b\u0001\u0002\u0002\u0013\u0005A\tC\u0004l\u0001\u0005\u0005I\u0011\u00017\t\u000fI\u0004\u0011\u0011!C!g\"9!\u0010AA\u0001\n\u0003Y\b\"CA\u0001\u0001\u0005\u0005I\u0011IA\u0002\u0011%\t9\u0001AA\u0001\n\u0003\nI\u0001C\u0005\u0002\f\u0001\t\t\u0011\"\u0011\u0002\u000e!I\u0011q\u0002\u0001\u0002\u0002\u0013\u0005\u0013\u0011C\u0004\u000b\u0003+Q\u0012\u0011!E\u00015\u0005]a!C\r\u001b\u0003\u0003E\tAGA\r\u0011\u0019I5\u0003\"\u0001\u00022!I\u00111B\n\u0002\u0002\u0013\u0015\u0013Q\u0002\u0005\n\u0003g\u0019\u0012\u0011!CA\u0003kA\u0011\"a\u000f\u0014\u0003\u0003%\t)!\u0010\t\u0013\u0005=3#!A\u0005\n\u0005E#A\b-nYN{7m[3u%\u0016\u0004xN\u001d;fe\u000e{gNZ5hkJ\fG/[8o\u0015\tYB$A\u0003u_>d7O\u0003\u0002\u001e=\u0005I1oY1mCR,7\u000f\u001e\u0006\u0002?\u0005\u0019qN]4\u0014\t\u0001\tSe\u000b\t\u0003E\rj\u0011AG\u0005\u0003Ii\u0011QCU3q_J$XM]\"p]\u001aLw-\u001e:bi&|g\u000e\u0005\u0002\'S5\tqEC\u0001)\u0003\u0015\u00198-\u00197b\u0013\tQsEA\u0004Qe>$Wo\u0019;\u0011\u00051*dBA\u00174\u001d\tq#\'D\u00010\u0015\t\u0001\u0014\'\u0001\u0004=e>|GOP\u0002\u0001\u0013\u0005A\u0013B\u0001\u001b(\u0003\u001d\u0001\u0018mY6bO\u0016L!AN\u001c\u0003\u0019M+\'/[1mSj\f\'\r\\3\u000b\u0005Q:\u0013\u0001\u00025pgR,\u0012A\u000f\t\u0003w}r!\u0001P\u001f\u0011\u00059:\u0013B\u0001 (\u0003\u0019\u0001&/\u001a3fM&\u0011\u0001)\u0011\u0002\u0007\'R\u0014\u0018N\\4\u000b\u0005y:\u0013!\u00025pgR\u0004\u0013\u0001\u00029peR,\u0012!\u0012\t\u0003M\u0019K!aR\u0014\u0003\u0007%sG/A\u0003q_J$\b%\u0001\u0004=S:LGO\u0010\u000b\u0004\u00172k\u0005C\u0001\u0012\u0001\u0011\u0015AT\u00011\u0001;\u0011\u0015\u0019U\u00011\u0001F\u0003\u0011\u0019w\u000e]=\u0015\u0007-\u0003\u0016\u000bC\u00049\rA\u0005\t\u0019\u0001\u001e\t\u000f\r3\u0001\u0013!a\u0001\u000b\u0006q1m\u001c9zI\u0011,g-Y;mi\u0012\nT#\u0001++\u0005i*6&\u0001,\u0011\u0005]cV\"\u0001-\u000b\u0005eS\u0016!C;oG\",7m[3e\u0015\tYv%\u0001\u0006b]:|G/\u0019;j_:L!!\u0018-\u0003#Ut7\r[3dW\u0016$g+\u0019:jC:\u001cW-\u0001\bd_BLH\u0005Z3gCVdG\u000f\n\u001a\u0016\u0003\u0001T#!R+\u0002\u001bA\u0014x\u000eZ;diB\u0013XMZ5y+\u0005\u0019\u0007C\u00013j\u001b\u0005)\'B\u00014h\u0003\u0011a\u0017M\\4\u000b\u0003!\fAA[1wC&\u0011\u0001)Z\u0001\raJ|G-^2u\u0003JLG/_\u0001\u000faJ|G-^2u\u000b2,W.\u001a8u)\ti\u0007\u000f\u0005\u0002\']&\u0011qn\n\u0002\u0004\u0003:L\bbB9\f\u0003\u0003\u0005\r!R\u0001\u0004q\u0012\n\u0014a\u00049s_\u0012,8\r^%uKJ\fGo\u001c:\u0016\u0003Q\u00042!\u001e=n\u001b\u00051(BA<(\u0003)\u0019w\u000e\u001c7fGRLwN\\\u0005\u0003sZ\u0014\u0001\"\u0013;fe\u0006$xN]\u0001\tG\u0006tW)];bYR\u0011Ap \t\u0003MuL!A`\u0014\u0003\u000f\t{w\u000e\\3b]\"9\u0011/DA\u0001\u0002\u0004i\u0017A\u00059s_\u0012,8\r^#mK6,g\u000e\u001e(b[\u0016$2aYA\u0003\u0011\u001d\th\"!AA\u0002\u0015\u000b\u0001\u0002[1tQ\u000e{G-\u001a\u000b\u0002\u000b\u0006AAo\\*ue&tw\rF\u0001d\u0003\u0019)\u0017/^1mgR\u0019A0a\u0005\t\u000fE\f\u0012\u0011!a\u0001[\u0006q\u0002,\u001c7T_\u000e\\W\r\u001e*fa>\u0014H/\u001a:D_:4\u0017nZ;sCRLwN\u001c\t\u0003EM\u0019RaEA\u000e\u0003O\u0001r!!\b\u0002$i*5*\u0004\u0002\u0002 )\u0019\u0011\u0011E\u0014\u0002\u000fI,h\u000e^5nK&!\u0011QEA\u0010\u0005E\t%m\u001d;sC\u000e$h)\u001e8di&|gN\r\t\u0005\u0003S\ty#\u0004\u0002\u0002,)\u0019\u0011QF4\u0002\u0005%|\u0017b\u0001\u001c\u0002,Q\u0011\u0011qC\u0001\u0006CB\u0004H.\u001f\u000b\u0006\u0017\u0006]\u0012\u0011\b\u0005\u0006qY\u0001\rA\u000f\u0005\u0006\u0007Z\u0001\r!R\u0001\bk:\f\u0007\u000f\u001d7z)\u0011\ty$a\u0013\u0011\u000b\u0019\n\t%!\u0012\n\u0007\u0005\rsE\u0001\u0004PaRLwN\u001c\t\u0006M\u0005\u001d#(R\u0005\u0004\u0003\u0013:#A\u0002+va2,\'\u0007\u0003\u0005\u0002N]\t\t\u00111\u0001L\u0003\rAH\u0005M\u0001\roJLG/\u001a*fa2\f7-\u001a\u000b\u0003\u0003\'\u00022\u0001ZA+\u0013\r\t9&\u001a\u0002\u0007\u001f\nTWm\u0019;
    #9 = Utf8               host
   #10 = Utf8               Ljava/lang/String;
   #11 = Utf8               port
   #12 = Utf8               I
   #13 = Utf8               unapply
   #14 = Utf8               (Lorg/scalatest/tools/XmlSocketReporterConfiguration;)Lscala/Option;
   #15 = Utf8               (Lorg/scalatest/tools/XmlSocketReporterConfiguration;)Lscala/Option<Lscala/Tuple2<Ljava/lang/String;Ljava/lang/Object;>;>;
   #16 = Utf8               x$0
   #17 = Utf8               org/scalatest/tools/XmlSocketReporterConfiguration$
   #18 = Class              #17           // org/scalatest/tools/XmlSocketReporterConfiguration$
   #19 = Utf8               MODULE$
   #20 = Utf8               Lorg/scalatest/tools/XmlSocketReporterConfiguration$;
   #21 = NameAndType        #19:#20       // MODULE$:Lorg/scalatest/tools/XmlSocketReporterConfiguration$;
   #22 = Fieldref           #18.#21       // org/scalatest/tools/XmlSocketReporterConfiguration$.MODULE$:Lorg/scalatest/tools/XmlSocketReporterConfiguration$;
   #23 = NameAndType        #13:#14       // unapply:(Lorg/scalatest/tools/XmlSocketReporterConfiguration;)Lscala/Option;
   #24 = Methodref          #18.#23       // org/scalatest/tools/XmlSocketReporterConfiguration$.unapply:(Lorg/scalatest/tools/XmlSocketReporterConfiguration;)Lscala/Option;
   #25 = Utf8               Lorg/scalatest/tools/XmlSocketReporterConfiguration;
   #26 = Utf8               apply
   #27 = Utf8               (Ljava/lang/String;I)Lorg/scalatest/tools/XmlSocketReporterConfiguration;
   #28 = NameAndType        #26:#27       // apply:(Ljava/lang/String;I)Lorg/scalatest/tools/XmlSocketReporterConfiguration;
   #29 = Methodref          #18.#28       // org/scalatest/tools/XmlSocketReporterConfiguration$.apply:(Ljava/lang/String;I)Lorg/scalatest/tools/XmlSocketReporterConfiguration;
   #30 = Utf8               tupled
   #31 = Utf8               ()Lscala/Function1;
   #32 = Utf8               ()Lscala/Function1<Lscala/Tuple2<Ljava/lang/String;Ljava/lang/Object;>;Lorg/scalatest/tools/XmlSocketReporterConfiguration;>;
   #33 = NameAndType        #30:#31       // tupled:()Lscala/Function1;
   #34 = Methodref          #18.#33       // org/scalatest/tools/XmlSocketReporterConfiguration$.tupled:()Lscala/Function1;
   #35 = Utf8               curried
   #36 = Utf8               ()Lscala/Function1<Ljava/lang/String;Lscala/Function1<Ljava/lang/Object;Lorg/scalatest/tools/XmlSocketReporterConfiguration;>;>;
   #37 = NameAndType        #35:#31       // curried:()Lscala/Function1;
   #38 = Methodref          #18.#37       // org/scalatest/tools/XmlSocketReporterConfiguration$.curried:()Lscala/Function1;
   #39 = Utf8               ()Ljava/lang/String;
   #40 = NameAndType        #9:#10        // host:Ljava/lang/String;
   #41 = Fieldref           #2.#40        // org/scalatest/tools/XmlSocketReporterConfiguration.host:Ljava/lang/String;
   #42 = Utf8               this
   #43 = Utf8               ()I
   #44 = NameAndType        #11:#12       // port:I
   #45 = Fieldref           #2.#44        // org/scalatest/tools/XmlSocketReporterConfiguration.port:I
   #46 = Utf8               copy
   #47 = Utf8               <init>
   #48 = Utf8               (Ljava/lang/String;I)V
   #49 = NameAndType        #47:#48       // "<init>":(Ljava/lang/String;I)V
   #50 = Methodref          #2.#49        // org/scalatest/tools/XmlSocketReporterConfiguration."<init>":(Ljava/lang/String;I)V
   #51 = Utf8               copy$default$1
   #52 = NameAndType        #9:#39        // host:()Ljava/lang/String;
   #53 = Methodref          #2.#52        // org/scalatest/tools/XmlSocketReporterConfiguration.host:()Ljava/lang/String;
   #54 = Utf8               copy$default$2
   #55 = NameAndType        #11:#43       // port:()I
   #56 = Methodref          #2.#55        // org/scalatest/tools/XmlSocketReporterConfiguration.port:()I
   #57 = Utf8               productPrefix
   #58 = Utf8               XmlSocketReporterConfiguration
   #59 = String             #58           // XmlSocketReporterConfiguration
   #60 = Utf8               productArity
   #61 = Utf8               productElement
   #62 = Utf8               (I)Ljava/lang/Object;
   #63 = Utf8               x$1
   #64 = Utf8               scala/runtime/BoxesRunTime
   #65 = Class              #64           // scala/runtime/BoxesRunTime
   #66 = Utf8               boxToInteger
   #67 = Utf8               (I)Ljava/lang/Integer;
   #68 = NameAndType        #66:#67       // boxToInteger:(I)Ljava/lang/Integer;
   #69 = Methodref          #65.#68       // scala/runtime/BoxesRunTime.boxToInteger:(I)Ljava/lang/Integer;
   #70 = Utf8               scala/runtime/Statics
   #71 = Class              #70           // scala/runtime/Statics
   #72 = Utf8               ioobe
   #73 = NameAndType        #72:#62       // ioobe:(I)Ljava/lang/Object;
   #74 = Methodref          #71.#73       // scala/runtime/Statics.ioobe:(I)Ljava/lang/Object;
   #75 = Utf8               java/lang/Object
   #76 = Class              #75           // java/lang/Object
   #77 = Utf8               productIterator
   #78 = Utf8               ()Lscala/collection/Iterator;
   #79 = Utf8               ()Lscala/collection/Iterator<Ljava/lang/Object;>;
   #80 = Utf8               scala/runtime/ScalaRunTime$
   #81 = Class              #80           // scala/runtime/ScalaRunTime$
   #82 = Utf8               Lscala/runtime/ScalaRunTime$;
   #83 = NameAndType        #19:#82       // MODULE$:Lscala/runtime/ScalaRunTime$;
   #84 = Fieldref           #81.#83       // scala/runtime/ScalaRunTime$.MODULE$:Lscala/runtime/ScalaRunTime$;
   #85 = Utf8               typedProductIterator
   #86 = Utf8               (Lscala/Product;)Lscala/collection/Iterator;
   #87 = NameAndType        #85:#86       // typedProductIterator:(Lscala/Product;)Lscala/collection/Iterator;
   #88 = Methodref          #81.#87       // scala/runtime/ScalaRunTime$.typedProductIterator:(Lscala/Product;)Lscala/collection/Iterator;
   #89 = Utf8               canEqual
   #90 = Utf8               (Ljava/lang/Object;)Z
   #91 = Utf8               Ljava/lang/Object;
   #92 = Utf8               productElementName
   #93 = Utf8               (I)Ljava/lang/String;
   #94 = String             #9            // host
   #95 = String             #11           // port
   #96 = Utf8               java/lang/String
   #97 = Class              #96           // java/lang/String
   #98 = Utf8               hashCode
   #99 = Integer            -889275714
  #100 = NameAndType        #57:#39       // productPrefix:()Ljava/lang/String;
  #101 = Methodref          #2.#100       // org/scalatest/tools/XmlSocketReporterConfiguration.productPrefix:()Ljava/lang/String;
  #102 = NameAndType        #98:#43       // hashCode:()I
  #103 = Methodref          #97.#102      // java/lang/String.hashCode:()I
  #104 = Utf8               mix
  #105 = Utf8               (II)I
  #106 = NameAndType        #104:#105     // mix:(II)I
  #107 = Methodref          #71.#106      // scala/runtime/Statics.mix:(II)I
  #108 = Utf8               anyHash
  #109 = Utf8               (Ljava/lang/Object;)I
  #110 = NameAndType        #108:#109     // anyHash:(Ljava/lang/Object;)I
  #111 = Methodref          #71.#110      // scala/runtime/Statics.anyHash:(Ljava/lang/Object;)I
  #112 = Utf8               finalizeHash
  #113 = NameAndType        #112:#105     // finalizeHash:(II)I
  #114 = Methodref          #71.#113      // scala/runtime/Statics.finalizeHash:(II)I
  #115 = Utf8               toString
  #116 = Utf8               _toString
  #117 = Utf8               (Lscala/Product;)Ljava/lang/String;
  #118 = NameAndType        #116:#117     // _toString:(Lscala/Product;)Ljava/lang/String;
  #119 = Methodref          #81.#118      // scala/runtime/ScalaRunTime$._toString:(Lscala/Product;)Ljava/lang/String;
  #120 = Utf8               equals
  #121 = NameAndType        #120:#90      // equals:(Ljava/lang/Object;)Z
  #122 = Methodref          #76.#121      // java/lang/Object.equals:(Ljava/lang/Object;)Z
  #123 = NameAndType        #89:#90       // canEqual:(Ljava/lang/Object;)Z
  #124 = Methodref          #2.#123       // org/scalatest/tools/XmlSocketReporterConfiguration.canEqual:(Ljava/lang/Object;)Z
  #125 = Utf8               ()V
  #126 = NameAndType        #47:#125      // "<init>":()V
  #127 = Methodref          #4.#126       // org/scalatest/tools/ReporterConfiguration."<init>":()V
  #128 = Utf8               Code
  #129 = Utf8               LocalVariableTable
  #130 = Utf8               Signature
  #131 = Utf8               MethodParameters
  #132 = Utf8               LineNumberTable
  #133 = Utf8               StackMapTable
  #134 = Utf8               SourceFile
  #135 = Utf8               RuntimeVisibleAnnotations
  #136 = Utf8               ScalaInlineInfo
  #137 = Utf8               ScalaSig
{
  private final java.lang.String host;
    descriptor: Ljava/lang/String;
    flags: (0x0012) ACC_PRIVATE, ACC_FINAL

  private final int port;
    descriptor: I
    flags: (0x0012) ACC_PRIVATE, ACC_FINAL

  public static scala.Option<scala.Tuple2<java.lang.String, java.lang.Object>> unapply(org.scalatest.tools.XmlSocketReporterConfiguration);
    descriptor: (Lorg/scalatest/tools/XmlSocketReporterConfiguration;)Lscala/Option;
    flags: (0x0009) ACC_PUBLIC, ACC_STATIC
    Code:
      stack=2, locals=1, args_size=1
         0: getstatic     #22                 // Field org/scalatest/tools/XmlSocketReporterConfiguration$.MODULE$:Lorg/scalatest/tools/XmlSocketReporterConfiguration$;
         3: aload_0
         4: invokevirtual #24                 // Method org/scalatest/tools/XmlSocketReporterConfiguration$.unapply:(Lorg/scalatest/tools/XmlSocketReporterConfiguration;)Lscala/Option;
         7: areturn
      LocalVariableTable:
        Start  Length  Slot  Name   Signature
            0       8     0   x$0   Lorg/scalatest/tools/XmlSocketReporterConfiguration;
    Signature: #15                          // (Lorg/scalatest/tools/XmlSocketReporterConfiguration;)Lscala/Option<Lscala/Tuple2<Ljava/lang/String;Ljava/lang/Object;>;>;
    MethodParameters:
      Name                           Flags
      x$0                            final

  public static org.scalatest.tools.XmlSocketReporterConfiguration apply(java.lang.String, int);
    descriptor: (Ljava/lang/String;I)Lorg/scalatest/tools/XmlSocketReporterConfiguration;
    flags: (0x0009) ACC_PUBLIC, ACC_STATIC
    Code:
      stack=3, locals=2, args_size=2
         0: getstatic     #22                 // Field org/scalatest/tools/XmlSocketReporterConfiguration$.MODULE$:Lorg/scalatest/tools/XmlSocketReporterConfiguration$;
         3: aload_0
         4: iload_1
         5: invokevirtual #29                 // Method org/scalatest/tools/XmlSocketReporterConfiguration$.apply:(Ljava/lang/String;I)Lorg/scalatest/tools/XmlSocketReporterConfiguration;
         8: areturn
      LocalVariableTable:
        Start  Length  Slot  Name   Signature
            0       9     0  host   Ljava/lang/String;
            0       9     1  port   I
    MethodParameters:
      Name                           Flags
      host                           final
      port                           final

  public static scala.Function1<scala.Tuple2<java.lang.String, java.lang.Object>, org.scalatest.tools.XmlSocketReporterConfiguration> tupled();
    descriptor: ()Lscala/Function1;
    flags: (0x0009) ACC_PUBLIC, ACC_STATIC
    Code:
      stack=1, locals=0, args_size=0
         0: getstatic     #22                 // Field org/scalatest/tools/XmlSocketReporterConfiguration$.MODULE$:Lorg/scalatest/tools/XmlSocketReporterConfiguration$;
         3: invokevirtual #34                 // Method org/scalatest/tools/XmlSocketReporterConfiguration$.tupled:()Lscala/Function1;
         6: areturn
    Signature: #32                          // ()Lscala/Function1<Lscala/Tuple2<Ljava/lang/String;Ljava/lang/Object;>;Lorg/scalatest/tools/XmlSocketReporterConfiguration;>;

  public static scala.Function1<java.lang.String, scala.Function1<java.lang.Object, org.scalatest.tools.XmlSocketReporterConfiguration>> curried();
    descriptor: ()Lscala/Function1;
    flags: (0x0009) ACC_PUBLIC, ACC_STATIC
    Code:
      stack=1, locals=0, args_size=0
         0: getstatic     #22                 // Field org/scalatest/tools/XmlSocketReporterConfiguration$.MODULE$:Lorg/scalatest/tools/XmlSocketReporterConfiguration$;
         3: invokevirtual #38                 // Method org/scalatest/tools/XmlSocketReporterConfiguration$.curried:()Lscala/Function1;
         6: areturn
    Signature: #36                          // ()Lscala/Function1<Ljava/lang/String;Lscala/Function1<Ljava/lang/Object;Lorg/scalatest/tools/XmlSocketReporterConfiguration;>;>;

  public java.lang.String host();
    descriptor: ()Ljava/lang/String;
    flags: (0x0001) ACC_PUBLIC
    Code:
      stack=1, locals=1, args_size=1
         0: aload_0
         1: getfield      #41                 // Field host:Ljava/lang/String;
         4: areturn
      LineNumberTable:
        line 37: 0
      LocalVariableTable:
        Start  Length  Slot  Name   Signature
            0       5     0  this   Lorg/scalatest/tools/XmlSocketReporterConfiguration;

  public int port();
    descriptor: ()I
    flags: (0x0001) ACC_PUBLIC
    Code:
      stack=1, locals=1, args_size=1
         0: aload_0
         1: getfield      #45                 // Field port:I
         4: ireturn
      LineNumberTable:
        line 37: 0
      LocalVariableTable:
        Start  Length  Slot  Name   Signature
            0       5     0  this   Lorg/scalatest/tools/XmlSocketReporterConfiguration;

  public org.scalatest.tools.XmlSocketReporterConfiguration copy(java.lang.String, int);
    descriptor: (Ljava/lang/String;I)Lorg/scalatest/tools/XmlSocketReporterConfiguration;
    flags: (0x0001) ACC_PUBLIC
    Code:
      stack=4, locals=3, args_size=3
         0: new           #2                  // class org/scalatest/tools/XmlSocketReporterConfiguration
         3: dup
         4: aload_1
         5: iload_2
         6: invokespecial #50                 // Method "<init>":(Ljava/lang/String;I)V
         9: areturn
      LineNumberTable:
        line 37: 0
      LocalVariableTable:
        Start  Length  Slot  Name   Signature
            0      10     0  this   Lorg/scalatest/tools/XmlSocketReporterConfiguration;
            0      10     1  host   Ljava/lang/String;
            0      10     2  port   I
    MethodParameters:
      Name                           Flags
      host                           final
      port                           final

  public java.lang.String copy$default$1();
    descriptor: ()Ljava/lang/String;
    flags: (0x0001) ACC_PUBLIC
    Code:
      stack=1, locals=1, args_size=1
         0: aload_0
         1: invokevirtual #53                 // Method host:()Ljava/lang/String;
         4: areturn
      LineNumberTable:
        line 37: 0
      LocalVariableTable:
        Start  Length  Slot  Name   Signature
            0       5     0  this   Lorg/scalatest/tools/XmlSocketReporterConfiguration;

  public int copy$default$2();
    descriptor: ()I
    flags: (0x0001) ACC_PUBLIC
    Code:
      stack=1, locals=1, args_size=1
         0: aload_0
         1: invokevirtual #56                 // Method port:()I
         4: ireturn
      LineNumberTable:
        line 37: 0
      LocalVariableTable:
        Start  Length  Slot  Name   Signature
            0       5     0  this   Lorg/scalatest/tools/XmlSocketReporterConfiguration;

  public java.lang.String productPrefix();
    descriptor: ()Ljava/lang/String;
    flags: (0x0001) ACC_PUBLIC
    Code:
      stack=1, locals=1, args_size=1
         0: ldc           #59                 // String XmlSocketReporterConfiguration
         2: areturn
      LineNumberTable:
        line 37: 0
      LocalVariableTable:
        Start  Length  Slot  Name   Signature
            0       3     0  this   Lorg/scalatest/tools/XmlSocketReporterConfiguration;

  public int productArity();
    descriptor: ()I
    flags: (0x0001) ACC_PUBLIC
    Code:
      stack=1, locals=1, args_size=1
         0: iconst_2
         1: ireturn
      LineNumberTable:
        line 37: 0
      LocalVariableTable:
        Start  Length  Slot  Name   Signature
            0       2     0  this   Lorg/scalatest/tools/XmlSocketReporterConfiguration;

  public java.lang.Object productElement(int);
    descriptor: (I)Ljava/lang/Object;
    flags: (0x0001) ACC_PUBLIC
    Code:
      stack=1, locals=3, args_size=2
         0: iload_1
         1: istore_2
         2: iload_2
         3: tableswitch   { // 0 to 1
                       0: 24
                       1: 31
                 default: 41
            }
        24: aload_0
        25: invokevirtual #53                 // Method host:()Ljava/lang/String;
        28: goto          48
        31: aload_0
        32: invokevirtual #56                 // Method port:()I
        35: invokestatic  #69                 // Method scala/runtime/BoxesRunTime.boxToInteger:(I)Ljava/lang/Integer;
        38: goto          48
        41: iload_1
        42: invokestatic  #74                 // Method scala/runtime/Statics.ioobe:(I)Ljava/lang/Object;
        45: goto          48
        48: areturn
      StackMapTable: number_of_entries = 4
        frame_type = 252 /* append */
          offset_delta = 24
          locals = [ int ]
        frame_type = 6 /* same */
        frame_type = 9 /* same */
        frame_type = 70 /* same_locals_1_stack_item */
          stack = [ class java/lang/Object ]
      LineNumberTable:
        line 37: 0
      LocalVariableTable:
        Start  Length  Slot  Name   Signature
            0      49     0  this   Lorg/scalatest/tools/XmlSocketReporterConfiguration;
            0      49     1   x$1   I
    MethodParameters:
      Name                           Flags
      x$1                            final

  public scala.collection.Iterator<java.lang.Object> productIterator();
    descriptor: ()Lscala/collection/Iterator;
    flags: (0x0001) ACC_PUBLIC
    Code:
      stack=2, locals=1, args_size=1
         0: getstatic     #84                 // Field scala/runtime/ScalaRunTime$.MODULE$:Lscala/runtime/ScalaRunTime$;
         3: aload_0
         4: invokevirtual #88                 // Method scala/runtime/ScalaRunTime$.typedProductIterator:(Lscala/Product;)Lscala/collection/Iterator;
         7: areturn
      LineNumberTable:
        line 37: 0
      LocalVariableTable:
        Start  Length  Slot  Name   Signature
            0       8     0  this   Lorg/scalatest/tools/XmlSocketReporterConfiguration;
    Signature: #79                          // ()Lscala/collection/Iterator<Ljava/lang/Object;>;

  public boolean canEqual(java.lang.Object);
    descriptor: (Ljava/lang/Object;)Z
    flags: (0x0001) ACC_PUBLIC
    Code:
      stack=1, locals=2, args_size=2
         0: aload_1
         1: instanceof    #2                  // class org/scalatest/tools/XmlSocketReporterConfiguration
         4: ireturn
      LineNumberTable:
        line 37: 0
      LocalVariableTable:
        Start  Length  Slot  Name   Signature
            0       5     0  this   Lorg/scalatest/tools/XmlSocketReporterConfiguration;
            0       5     1   x$1   Ljava/lang/Object;
    MethodParameters:
      Name                           Flags
      x$1                            final

  public java.lang.String productElementName(int);
    descriptor: (I)Ljava/lang/String;
    flags: (0x0001) ACC_PUBLIC
    Code:
      stack=1, locals=3, args_size=2
         0: iload_1
         1: istore_2
         2: iload_2
         3: tableswitch   { // 0 to 1
                       0: 24
                       1: 29
                 default: 34
            }
        24: ldc           #94                 // String host
        26: goto          44
        29: ldc           #95                 // String port
        31: goto          44
        34: iload_1
        35: invokestatic  #74                 // Method scala/runtime/Statics.ioobe:(I)Ljava/lang/Object;
        38: checkcast     #97                 // class java/lang/String
        41: goto          44
        44: areturn
      StackMapTable: number_of_entries = 4
        frame_type = 252 /* append */
          offset_delta = 24
          locals = [ int ]
        frame_type = 4 /* same */
        frame_type = 4 /* same */
        frame_type = 73 /* same_locals_1_stack_item */
          stack = [ class java/lang/String ]
      LineNumberTable:
        line 37: 0
      LocalVariableTable:
        Start  Length  Slot  Name   Signature
            0      45     0  this   Lorg/scalatest/tools/XmlSocketReporterConfiguration;
            0      45     1   x$1   I
    MethodParameters:
      Name                           Flags
      x$1                            final

  public int hashCode();
    descriptor: ()I
    flags: (0x0001) ACC_PUBLIC
    Code:
      stack=2, locals=2, args_size=1
         0: ldc           #99                 // int -889275714
         2: istore_1
         3: iload_1
         4: aload_0
         5: invokevirtual #101                // Method productPrefix:()Ljava/lang/String;
         8: invokevirtual #103                // Method java/lang/String.hashCode:()I
        11: invokestatic  #107                // Method scala/runtime/Statics.mix:(II)I
        14: istore_1
        15: iload_1
        16: aload_0
        17: invokevirtual #53                 // Method host:()Ljava/lang/String;
        20: invokestatic  #111                // Method scala/runtime/Statics.anyHash:(Ljava/lang/Object;)I
        23: invokestatic  #107                // Method scala/runtime/Statics.mix:(II)I
        26: istore_1
        27: iload_1
        28: aload_0
        29: invokevirtual #56                 // Method port:()I
        32: invokestatic  #107                // Method scala/runtime/Statics.mix:(II)I
        35: istore_1
        36: iload_1
        37: iconst_2
        38: invokestatic  #114                // Method scala/runtime/Statics.finalizeHash:(II)I
        41: ireturn
      LineNumberTable:
        line 37: 0
      LocalVariableTable:
        Start  Length  Slot  Name   Signature
            0      42     0  this   Lorg/scalatest/tools/XmlSocketReporterConfiguration;

  public java.lang.String toString();
    descriptor: ()Ljava/lang/String;
    flags: (0x0001) ACC_PUBLIC
    Code:
      stack=2, locals=1, args_size=1
         0: getstatic     #84                 // Field scala/runtime/ScalaRunTime$.MODULE$:Lscala/runtime/ScalaRunTime$;
         3: aload_0
         4: invokevirtual #119                // Method scala/runtime/ScalaRunTime$._toString:(Lscala/Product;)Ljava/lang/String;
         7: areturn
      LineNumberTable:
        line 37: 0
      LocalVariableTable:
        Start  Length  Slot  Name   Signature
            0       8     0  this   Lorg/scalatest/tools/XmlSocketReporterConfiguration;

  public boolean equals(java.lang.Object);
    descriptor: (Ljava/lang/Object;)Z
    flags: (0x0001) ACC_PUBLIC
    Code:
      stack=2, locals=6, args_size=2
         0: aload_0
         1: aload_1
         2: if_acmpeq     98
         5: aload_1
         6: astore_3
         7: aload_3
         8: instanceof    #2                  // class org/scalatest/tools/XmlSocketReporterConfiguration
        11: ifeq          19
        14: iconst_1
        15: istore_2
        16: goto          27
        19: goto          22
        22: iconst_0
        23: istore_2
        24: goto          27
        27: iload_2
        28: ifeq          102
        31: aload_1
        32: checkcast     #2                  // class org/scalatest/tools/XmlSocketReporterConfiguration
        35: astore        4
        37: aload_0
        38: invokevirtual #56                 // Method port:()I
        41: aload         4
        43: invokevirtual #56                 // Method port:()I
        46: if_icmpne     94
        49: aload_0
        50: invokevirtual #53                 // Method host:()Ljava/lang/String;
        53: aload         4
        55: invokevirtual #53                 // Method host:()Ljava/lang/String;
        58: astore        5
        60: dup
        61: ifnonnull     73
        64: pop
        65: aload         5
        67: ifnull        81
        70: goto          94
        73: aload         5
        75: invokevirtual #122                // Method java/lang/Object.equals:(Ljava/lang/Object;)Z
        78: ifeq          94
        81: aload         4
        83: aload_0
        84: invokevirtual #124                // Method canEqual:(Ljava/lang/Object;)Z
        87: ifeq          94
        90: iconst_1
        91: goto          95
        94: iconst_0
        95: ifeq          102
        98: iconst_1
        99: goto          103
       102: iconst_0
       103: ireturn
      StackMapTable: number_of_entries = 10
        frame_type = 253 /* append */
          offset_delta = 19
          locals = [ top, class java/lang/Object ]
        frame_type = 2 /* same */
        frame_type = 255 /* full_frame */
          offset_delta = 4
          locals = [ class org/scalatest/tools/XmlSocketReporterConfiguration, class java/lang/Object, int, class java/lang/Object ]
          stack = []
        frame_type = 255 /* full_frame */
          offset_delta = 45
          locals = [ class org/scalatest/tools/XmlSocketReporterConfiguration, class java/lang/Object, int, class java/lang/Object, class org/scalatest/tools/XmlSocketReporterConfiguration, class java/lang/String ]
          stack = [ class java/lang/String ]
        frame_type = 7 /* same */
        frame_type = 250 /* chop */
          offset_delta = 12
        frame_type = 64 /* same_locals_1_stack_item */
          stack = [ int ]
        frame_type = 248 /* chop */
          offset_delta = 2
        frame_type = 253 /* append */
          offset_delta = 3
          locals = [ int, class java/lang/Object ]
        frame_type = 255 /* full_frame */
          offset_delta = 0
          locals = [ class org/scalatest/tools/XmlSocketReporterConfiguration, class java/lang/Object ]
          stack = [ int ]
      LineNumberTable:
        line 37: 0
      LocalVariableTable:
        Start  Length  Slot  Name   Signature
            0     104     0  this   Lorg/scalatest/tools/XmlSocketReporterConfiguration;
            0     104     1   x$1   Ljava/lang/Object;
    MethodParameters:
      Name                           Flags
      x$1                            final

  public org.scalatest.tools.XmlSocketReporterConfiguration(java.lang.String, int);
    descriptor: (Ljava/lang/String;I)V
    flags: (0x0001) ACC_PUBLIC
    Code:
      stack=2, locals=3, args_size=3
         0: aload_0
         1: aload_1
         2: putfield      #41                 // Field host:Ljava/lang/String;
         5: aload_0
         6: iload_2
         7: putfield      #45                 // Field port:I
        10: aload_0
        11: invokespecial #127                // Method org/scalatest/tools/ReporterConfiguration."<init>":()V
        14: return
      LineNumberTable:
        line 37: 0
      LocalVariableTable:
        Start  Length  Slot  Name   Signature
            0      15     0  this   Lorg/scalatest/tools/XmlSocketReporterConfiguration;
            0      15     1  host   Ljava/lang/String;
            0      15     2  port   I
    MethodParameters:
      Name                           Flags
      host                           final
      port                           final
}
SourceFile: "ReporterConfiguration.scala"
RuntimeVisibleAnnotations:
  0: #6(#7=s#8)
    scala.reflect.ScalaSignature(
      bytes="\u0006\u0005\u0005ec!B\r\u001b\u0001j\u0001\u0003\u0002\u0003\u001d\u0001\u0005+\u0007I\u0011A\u001d\t\u0011\t\u0003!\u0011#Q\u0001\niB\u0001b\u0011\u0001\u0003\u0016\u0004%\t\u0001\u0012\u0005\t\u0011\u0002\u0011\t\u0012)A\u0005\u000b\")\u0011\n\u0001C\u0001\u0015\"9a\nAA\u0001\n\u0003y\u0005b\u0002*\u0001#\u0003%\ta\u0015\u0005\b=\u0002\t\n\u0011\"\u0001`\u0011\u001d\t\u0007!!A\u0005B\tDqA\u001b\u0001\u0002\u0002\u0013\u0005A\tC\u0004l\u0001\u0005\u0005I\u0011\u00017\t\u000fI\u0004\u0011\u0011!C!g\"9!\u0010AA\u0001\n\u0003Y\b\"CA\u0001\u0001\u0005\u0005I\u0011IA\u0002\u0011%\t9\u0001AA\u0001\n\u0003\nI\u0001C\u0005\u0002\f\u0001\t\t\u0011\"\u0011\u0002\u000e!I\u0011q\u0002\u0001\u0002\u0002\u0013\u0005\u0013\u0011C\u0004\u000b\u0003+Q\u0012\u0011!E\u00015\u0005]a!C\r\u001b\u0003\u0003E\tAGA\r\u0011\u0019I5\u0003\"\u0001\u00022!I\u00111B\n\u0002\u0002\u0013\u0015\u0013Q\u0002\u0005\n\u0003g\u0019\u0012\u0011!CA\u0003kA\u0011\"a\u000f\u0014\u0003\u0003%\t)!\u0010\t\u0013\u0005=3#!A\u0005\n\u0005E#A\b-nYN{7m[3u%\u0016\u0004xN\u001d;fe\u000e{gNZ5hkJ\fG/[8o\u0015\tYB$A\u0003u_>d7O\u0003\u0002\u001e=\u0005I1oY1mCR,7\u000f\u001e\u0006\u0002?\u0005\u0019qN]4\u0014\t\u0001\tSe\u000b\t\u0003E\rj\u0011AG\u0005\u0003Ii\u0011QCU3q_J$XM]\"p]\u001aLw-\u001e:bi&|g\u000e\u0005\u0002\'S5\tqEC\u0001)\u0003\u0015\u00198-\u00197b\u0013\tQsEA\u0004Qe>$Wo\u0019;\u0011\u00051*dBA\u00174\u001d\tq#\'D\u00010\u0015\t\u0001\u0014\'\u0001\u0004=e>|GOP\u0002\u0001\u0013\u0005A\u0013B\u0001\u001b(\u0003\u001d\u0001\u0018mY6bO\u0016L!AN\u001c\u0003\u0019M+\'/[1mSj\f\'\r\\3\u000b\u0005Q:\u0013\u0001\u00025pgR,\u0012A\u000f\t\u0003w}r!\u0001P\u001f\u0011\u00059:\u0013B\u0001 (\u0003\u0019\u0001&/\u001a3fM&\u0011\u0001)\u0011\u0002\u0007\'R\u0014\u0018N\\4\u000b\u0005y:\u0013!\u00025pgR\u0004\u0013\u0001\u00029peR,\u0012!\u0012\t\u0003M\u0019K!aR\u0014\u0003\u0007%sG/A\u0003q_J$\b%\u0001\u0004=S:LGO\u0010\u000b\u0004\u00172k\u0005C\u0001\u0012\u0001\u0011\u0015AT\u00011\u0001;\u0011\u0015\u0019U\u00011\u0001F\u0003\u0011\u0019w\u000e]=\u0015\u0007-\u0003\u0016\u000bC\u00049\rA\u0005\t\u0019\u0001\u001e\t\u000f\r3\u0001\u0013!a\u0001\u000b\u0006q1m\u001c9zI\u0011,g-Y;mi\u0012\nT#\u0001++\u0005i*6&\u0001,\u0011\u0005]cV\"\u0001-\u000b\u0005eS\u0016!C;oG\",7m[3e\u0015\tYv%\u0001\u0006b]:|G/\u0019;j_:L!!\u0018-\u0003#Ut7\r[3dW\u0016$g+\u0019:jC:\u001cW-\u0001\bd_BLH\u0005Z3gCVdG\u000f\n\u001a\u0016\u0003\u0001T#!R+\u0002\u001bA\u0014x\u000eZ;diB\u0013XMZ5y+\u0005\u0019\u0007C\u00013j\u001b\u0005)\'B\u00014h\u0003\u0011a\u0017M\\4\u000b\u0003!\fAA[1wC&\u0011\u0001)Z\u0001\raJ|G-^2u\u0003JLG/_\u0001\u000faJ|G-^2u\u000b2,W.\u001a8u)\ti\u0007\u000f\u0005\u0002\']&\u0011qn\n\u0002\u0004\u0003:L\bbB9\f\u0003\u0003\u0005\r!R\u0001\u0004q\u0012\n\u0014a\u00049s_\u0012,8\r^%uKJ\fGo\u001c:\u0016\u0003Q\u00042!\u001e=n\u001b\u00051(BA<(\u0003)\u0019w\u000e\u001c7fGRLwN\\\u0005\u0003sZ\u0014\u0001\"\u0013;fe\u0006$xN]\u0001\tG\u0006tW)];bYR\u0011Ap \t\u0003MuL!A`\u0014\u0003\u000f\t{w\u000e\\3b]\"9\u0011/DA\u0001\u0002\u0004i\u0017A\u00059s_\u0012,8\r^#mK6,g\u000e\u001e(b[\u0016$2aYA\u0003\u0011\u001d\th\"!AA\u0002\u0015\u000b\u0001\u0002[1tQ\u000e{G-\u001a\u000b\u0002\u000b\u0006AAo\\*ue&tw\rF\u0001d\u0003\u0019)\u0017/^1mgR\u0019A0a\u0005\t\u000fE\f\u0012\u0011!a\u0001[\u0006q\u0002,\u001c7T_\u000e\\W\r\u001e*fa>\u0014H/\u001a:D_:4\u0017nZ;sCRLwN\u001c\t\u0003EM\u0019RaEA\u000e\u0003O\u0001r!!\b\u0002$i*5*\u0004\u0002\u0002 )\u0019\u0011\u0011E\u0014\u0002\u000fI,h\u000e^5nK&!\u0011QEA\u0010\u0005E\t%m\u001d;sC\u000e$h)\u001e8di&|gN\r\t\u0005\u0003S\ty#\u0004\u0002\u0002,)\u0019\u0011QF4\u0002\u0005%|\u0017b\u0001\u001c\u0002,Q\u0011\u0011qC\u0001\u0006CB\u0004H.\u001f\u000b\u0006\u0017\u0006]\u0012\u0011\b\u0005\u0006qY\u0001\rA\u000f\u0005\u0006\u0007Z\u0001\r!R\u0001\bk:\f\u0007\u000f\u001d7z)\u0011\ty$a\u0013\u0011\u000b\u0019\n\t%!\u0012\n\u0007\u0005\rsE\u0001\u0004PaRLwN\u001c\t\u0006M\u0005\u001d#(R\u0005\u0004\u0003\u0013:#A\u0002+va2,\'\u0007\u0003\u0005\u0002N]\t\t\u00111\u0001L\u0003\rAH\u0005M\u0001\roJLG/\u001a*fa2\f7-\u001a\u000b\u0003\u0003\'\u00022\u0001ZA+\u0013\r\t9&\u001a\u0002\u0007\u001f\nTWm\u0019;"
    )
  ScalaInlineInfo: length = 0x4F (unknown attribute)
   01 00 00 0F 00 2F 00 30 00 00 59 00 5A 00 00 2E
   00 1B 00 00 33 00 27 00 00 36 00 2B 00 00 78 00
   5A 00 00 62 00 2B 00 00 09 00 27 00 00 0B 00 2B
   00 00 3C 00 2B 00 00 3D 00 3E 00 00 5C 00 5D 00
   00 4D 00 4E 00 00 39 00 27 00 00 73 00 27 00
  ScalaSig: length = 0x3 (unknown attribute)
   05 02 00
