Classfile /Users/mw/Projects/slang-braindump/.jar/jar8/assemble/slang-braindump/assemble/content/coursier/cache/internal/FileUtil$UpdateDigest.class
  Last modified May 29, 2022; size 869 bytes
  SHA-256 checksum 420668e539d5425a4a6df94b12275c7c767ed22a139307bccffc52af4e37fd9d
  Compiled from "FileUtil.scala"
public class coursier.cache.internal.FileUtil$UpdateDigest implements coursier.cache.internal.FileUtil$WithContent
  minor version: 0
  major version: 52
  flags: (0x0021) ACC_PUBLIC, ACC_SUPER
  this_class: #2                          // coursier/cache/internal/FileUtil$UpdateDigest
  super_class: #4                         // java/lang/Object
  interfaces: 1, fields: 1, methods: 2, attributes: 4
Constant pool:
   #1 = Utf8               coursier/cache/internal/FileUtil$UpdateDigest
   #2 = Class              #1             // coursier/cache/internal/FileUtil$UpdateDigest
   #3 = Utf8               java/lang/Object
   #4 = Class              #3             // java/lang/Object
   #5 = Utf8               coursier/cache/internal/FileUtil$WithContent
   #6 = Class              #5             // coursier/cache/internal/FileUtil$WithContent
   #7 = Utf8               FileUtil.scala
   #8 = Utf8               coursier/cache/internal/FileUtil
   #9 = Class              #8             // coursier/cache/internal/FileUtil
  #10 = Utf8               UpdateDigest
  #11 = Utf8               WithContent
  #12 = Utf8               md
  #13 = Utf8               Ljava/security/MessageDigest;
  #14 = Utf8               apply
  #15 = Utf8               ([BI)V
  #16 = Utf8               arr
  #17 = Utf8               z
  #18 = NameAndType        #12:#13        // md:Ljava/security/MessageDigest;
  #19 = Fieldref           #2.#18         // coursier/cache/internal/FileUtil$UpdateDigest.md:Ljava/security/MessageDigest;
  #20 = Utf8               java/security/MessageDigest
  #21 = Class              #20            // java/security/MessageDigest
  #22 = Utf8               update
  #23 = Utf8               ([BII)V
  #24 = NameAndType        #22:#23        // update:([BII)V
  #25 = Methodref          #21.#24        // java/security/MessageDigest.update:([BII)V
  #26 = Utf8               this
  #27 = Utf8               Lcoursier/cache/internal/FileUtil$UpdateDigest;
  #28 = Utf8               [B
  #29 = Utf8               I
  #30 = Utf8               <init>
  #31 = Utf8               (Ljava/security/MessageDigest;)V
  #32 = Utf8               ()V
  #33 = NameAndType        #30:#32        // "<init>":()V
  #34 = Methodref          #4.#33         // java/lang/Object."<init>":()V
  #35 = Utf8               Code
  #36 = Utf8               LineNumberTable
  #37 = Utf8               LocalVariableTable
  #38 = Utf8               MethodParameters
  #39 = Utf8               InnerClasses
  #40 = Utf8               SourceFile
  #41 = Utf8               ScalaInlineInfo
  #42 = Utf8               Scala
{
  private final java.security.MessageDigest md;
    descriptor: Ljava/security/MessageDigest;
    flags: (0x0012) ACC_PRIVATE, ACC_FINAL

  public void apply(byte[], int);
    descriptor: ([BI)V
    flags: (0x0001) ACC_PUBLIC
    Code:
      stack=4, locals=3, args_size=3
         0: aload_0
         1: getfield      #19                 // Field md:Ljava/security/MessageDigest;
         4: aload_1
         5: iconst_0
         6: iload_2
         7: invokevirtual #25                 // Method java/security/MessageDigest.update:([BII)V
        10: return
      LineNumberTable:
        line 51: 0
      LocalVariableTable:
        Start  Length  Slot  Name   Signature
            0      11     0  this   Lcoursier/cache/internal/FileUtil$UpdateDigest;
            0      11     1   arr   [B
            0      11     2     z   I
    MethodParameters:
      Name                           Flags
      arr                            final
      z                              final

  public coursier.cache.internal.FileUtil$UpdateDigest(java.security.MessageDigest);
    descriptor: (Ljava/security/MessageDigest;)V
    flags: (0x0001) ACC_PUBLIC
    Code:
      stack=2, locals=2, args_size=2
         0: aload_0
         1: aload_1
         2: putfield      #19                 // Field md:Ljava/security/MessageDigest;
         5: aload_0
         6: invokespecial #34                 // Method java/lang/Object."<init>":()V
         9: return
      LineNumberTable:
        line 50: 0
      LocalVariableTable:
        Start  Length  Slot  Name   Signature
            0      10     0  this   Lcoursier/cache/internal/FileUtil$UpdateDigest;
            0      10     1    md   Ljava/security/MessageDigest;
    MethodParameters:
      Name                           Flags
      md                             final
}
InnerClasses:
  public static #10= #2 of #9;            // UpdateDigest=class coursier/cache/internal/FileUtil$UpdateDigest of class coursier/cache/internal/FileUtil
  public static #11= #6 of #9;            // WithContent=class coursier/cache/internal/FileUtil$WithContent of class coursier/cache/internal/FileUtil
SourceFile: "FileUtil.scala"
  ScalaInlineInfo: length = 0xE (unknown attribute)
   01 00 00 02 00 1E 00 1F 00 00 0E 00 0F 00
  Scala: length = 0x0 (unknown attribute)

