Classfile /Users/mw/Projects/slang-braindump/.jar/jar8/assemble/slang-braindump/assemble/content/coursier/cache/internal/SigWinch$1.class
  Last modified May 29, 2022; size 572 bytes
  SHA-256 checksum 74bfd0fb5e7151572f1d36aab7caf0bb5981dcabe8931587f191bd79a5402e32
  Compiled from "SigWinch.java"
final class coursier.cache.internal.SigWinch$1 implements sun.misc.SignalHandler
  minor version: 0
  major version: 52
  flags: (0x0030) ACC_FINAL, ACC_SUPER
  this_class: #2                          // coursier/cache/internal/SigWinch$1
  super_class: #4                         // java/lang/Object
  interfaces: 1, fields: 1, methods: 2, attributes: 3
Constant pool:
   #1 = Utf8               coursier/cache/internal/SigWinch$1
   #2 = Class              #1             // coursier/cache/internal/SigWinch$1
   #3 = Utf8               java/lang/Object
   #4 = Class              #3             // java/lang/Object
   #5 = Utf8               sun/misc/SignalHandler
   #6 = Class              #5             // sun/misc/SignalHandler
   #7 = Utf8               SigWinch.java
   #8 = Utf8               coursier/cache/internal/SigWinch
   #9 = Class              #8             // coursier/cache/internal/SigWinch
  #10 = Utf8               addHandler
  #11 = Utf8               (Ljava/lang/Runnable;)V
  #12 = NameAndType        #10:#11        // addHandler:(Ljava/lang/Runnable;)V
  #13 = Utf8               val$runnable
  #14 = Utf8               Ljava/lang/Runnable;
  #15 = Utf8               <init>
  #16 = NameAndType        #13:#14        // val$runnable:Ljava/lang/Runnable;
  #17 = Fieldref           #2.#16         // coursier/cache/internal/SigWinch$1.val$runnable:Ljava/lang/Runnable;
  #18 = Utf8               ()V
  #19 = NameAndType        #15:#18        // "<init>":()V
  #20 = Methodref          #4.#19         // java/lang/Object."<init>":()V
  #21 = Utf8               handle
  #22 = Utf8               (Lsun/misc/Signal;)V
  #23 = Utf8               java/lang/Runnable
  #24 = Class              #23            // java/lang/Runnable
  #25 = Utf8               run
  #26 = NameAndType        #25:#18        // run:()V
  #27 = InterfaceMethodref #24.#26        // java/lang/Runnable.run:()V
  #28 = Utf8               Code
  #29 = Utf8               LineNumberTable
  #30 = Utf8               InnerClasses
  #31 = Utf8               EnclosingMethod
  #32 = Utf8               SourceFile
{
  final java.lang.Runnable val$runnable;
    descriptor: Ljava/lang/Runnable;
    flags: (0x1010) ACC_FINAL, ACC_SYNTHETIC

  coursier.cache.internal.SigWinch$1(java.lang.Runnable);
    descriptor: (Ljava/lang/Runnable;)V
    flags: (0x0000)
    Code:
      stack=2, locals=2, args_size=2
         0: aload_0
         1: aload_1
         2: putfield      #17                 // Field val$runnable:Ljava/lang/Runnable;
         5: aload_0
         6: invokespecial #20                 // Method java/lang/Object."<init>":()V
         9: return
      LineNumberTable:
        line 10: 0

  public void handle(sun.misc.Signal);
    descriptor: (Lsun/misc/Signal;)V
    flags: (0x0001) ACC_PUBLIC
    Code:
      stack=1, locals=2, args_size=2
         0: aload_0
         1: getfield      #17                 // Field val$runnable:Ljava/lang/Runnable;
         4: invokeinterface #27,  1           // InterfaceMethod java/lang/Runnable.run:()V
         9: return
      LineNumberTable:
        line 13: 0
        line 14: 9
}
InnerClasses:
  static #2;                              // class coursier/cache/internal/SigWinch$1
EnclosingMethod: #9.#12                 // coursier.cache.internal.SigWinch.addHandler
SourceFile: "SigWinch.java"
