Classfile /Users/mw/Projects/slang-braindump/.jar/jar11/assemble/slang-braindump/assemble/content/org/scalatest/fixture/FixtureNodeFamily$.class
  Last modified May 29, 2022; size 3265 bytes
  SHA-256 checksum 3c345e2838aa2a8420b552674fdfb1698a5426dedb473e367f84c6dff2f09792
  Compiled from "FixtureNodeFamily.scala"
public final class org.scalatest.fixture.FixtureNodeFamily$
  minor version: 0
  major version: 52
  flags: (0x0031) ACC_PUBLIC, ACC_FINAL, ACC_SUPER
  this_class: #2                          // org/scalatest/fixture/FixtureNodeFamily$
  super_class: #4                         // java/lang/Object
  interfaces: 0, fields: 1, methods: 6, attributes: 4
Constant pool:
    #1 = Utf8               org/scalatest/fixture/FixtureNodeFamily$
    #2 = Class              #1            // org/scalatest/fixture/FixtureNodeFamily$
    #3 = Utf8               java/lang/Object
    #4 = Class              #3            // java/lang/Object
    #5 = Utf8               FixtureNodeFamily.scala
    #6 = Utf8               org/scalatest/fixture/FixtureNodeFamily$Branch
    #7 = Class              #6            // org/scalatest/fixture/FixtureNodeFamily$Branch
    #8 = Utf8               org/scalatest/fixture/FixtureNodeFamily
    #9 = Class              #8            // org/scalatest/fixture/FixtureNodeFamily
   #10 = Utf8               Branch
   #11 = Utf8               org/scalatest/fixture/FixtureNodeFamily$DescriptionBranch
   #12 = Class              #11           // org/scalatest/fixture/FixtureNodeFamily$DescriptionBranch
   #13 = Utf8               DescriptionBranch
   #14 = Utf8               org/scalatest/fixture/FixtureNodeFamily$Trunk
   #15 = Class              #14           // org/scalatest/fixture/FixtureNodeFamily$Trunk
   #16 = Utf8               Trunk
   #17 = Utf8               org/scalatest/fixture/FixtureNodeFamily$VerbBranch
   #18 = Class              #17           // org/scalatest/fixture/FixtureNodeFamily$VerbBranch
   #19 = Utf8               VerbBranch
   #20 = Utf8               MODULE$
   #21 = Utf8               Lorg/scalatest/fixture/FixtureNodeFamily$;
   #22 = Utf8               <clinit>
   #23 = Utf8               ()V
   #24 = Utf8               <init>
   #25 = NameAndType        #24:#23       // "<init>":()V
   #26 = Methodref          #2.#25        // org/scalatest/fixture/FixtureNodeFamily$."<init>":()V
   #27 = NameAndType        #20:#21       // MODULE$:Lorg/scalatest/fixture/FixtureNodeFamily$;
   #28 = Fieldref           #2.#27        // org/scalatest/fixture/FixtureNodeFamily$.MODULE$:Lorg/scalatest/fixture/FixtureNodeFamily$;
   #29 = Utf8               getPrefix
   #30 = Utf8               (Lorg/scalatest/fixture/FixtureNodeFamily$Branch;)Ljava/lang/String;
   #31 = Utf8               branch
   #32 = Utf8
   #33 = String             #32           //
   #34 = Utf8               parent
   #35 = Utf8               ()Lorg/scalatest/fixture/FixtureNodeFamily$Branch;
   #36 = NameAndType        #34:#35       // parent:()Lorg/scalatest/fixture/FixtureNodeFamily$Branch;
   #37 = Methodref          #12.#36       // org/scalatest/fixture/FixtureNodeFamily$DescriptionBranch.parent:()Lorg/scalatest/fixture/FixtureNodeFamily$Branch;
   #38 = Utf8               descriptionName
   #39 = Utf8               ()Ljava/lang/String;
   #40 = NameAndType        #38:#39       // descriptionName:()Ljava/lang/String;
   #41 = Methodref          #12.#40       // org/scalatest/fixture/FixtureNodeFamily$DescriptionBranch.descriptionName:()Ljava/lang/String;
   #42 = Utf8               org/scalatest/Resources$
   #43 = Class              #42           // org/scalatest/Resources$
   #44 = Utf8               Lorg/scalatest/Resources$;
   #45 = NameAndType        #20:#44       // MODULE$:Lorg/scalatest/Resources$;
   #46 = Fieldref           #43.#45       // org/scalatest/Resources$.MODULE$:Lorg/scalatest/Resources$;
   #47 = NameAndType        #29:#30       // getPrefix:(Lorg/scalatest/fixture/FixtureNodeFamily$Branch;)Ljava/lang/String;
   #48 = Methodref          #2.#47        // org/scalatest/fixture/FixtureNodeFamily$.getPrefix:(Lorg/scalatest/fixture/FixtureNodeFamily$Branch;)Ljava/lang/String;
   #49 = Utf8               prefixSuffix
   #50 = Utf8               (Ljava/lang/Object;Ljava/lang/Object;)Ljava/lang/String;
   #51 = NameAndType        #49:#50       // prefixSuffix:(Ljava/lang/Object;Ljava/lang/Object;)Ljava/lang/String;
   #52 = Methodref          #43.#51       // org/scalatest/Resources$.prefixSuffix:(Ljava/lang/Object;Ljava/lang/Object;)Ljava/lang/String;
   #53 = Methodref          #18.#36       // org/scalatest/fixture/FixtureNodeFamily$VerbBranch.parent:()Lorg/scalatest/fixture/FixtureNodeFamily$Branch;
   #54 = Methodref          #18.#40       // org/scalatest/fixture/FixtureNodeFamily$VerbBranch.descriptionName:()Ljava/lang/String;
   #55 = Utf8               verb
   #56 = NameAndType        #55:#39       // verb:()Ljava/lang/String;
   #57 = Methodref          #18.#56       // org/scalatest/fixture/FixtureNodeFamily$VerbBranch.verb:()Ljava/lang/String;
   #58 = Utf8                (when
   #59 = String             #58           //  (when
   #60 = Utf8               java/lang/String
   #61 = Class              #60           // java/lang/String
   #62 = Utf8               indexOf
   #63 = Utf8               (Ljava/lang/String;)I
   #64 = NameAndType        #62:#63       // indexOf:(Ljava/lang/String;)I
   #65 = Methodref          #61.#64       // java/lang/String.indexOf:(Ljava/lang/String;)I
   #66 = Utf8               )
   #67 = String             #66           // )
   #68 = Utf8               java/lang/StringBuilder
   #69 = Class              #68           // java/lang/StringBuilder
   #70 = Integer            0
   #71 = Utf8               (I)V
   #72 = NameAndType        #24:#71       // "<init>":(I)V
   #73 = Methodref          #69.#72       // java/lang/StringBuilder."<init>":(I)V
   #74 = Utf8               append
   #75 = Utf8               (Ljava/lang/String;)Ljava/lang/StringBuilder;
   #76 = NameAndType        #74:#75       // append:(Ljava/lang/String;)Ljava/lang/StringBuilder;
   #77 = Methodref          #69.#76       // java/lang/StringBuilder.append:(Ljava/lang/String;)Ljava/lang/StringBuilder;
   #78 = Utf8               toString
   #79 = NameAndType        #78:#39       // toString:()Ljava/lang/String;
   #80 = Methodref          #69.#79       // java/lang/StringBuilder.toString:()Ljava/lang/String;
   #81 = Utf8               scala/MatchError
   #82 = Class              #81           // scala/MatchError
   #83 = Utf8               (Ljava/lang/Object;)V
   #84 = NameAndType        #24:#83       // "<init>":(Ljava/lang/Object;)V
   #85 = Methodref          #82.#84       // scala/MatchError."<init>":(Ljava/lang/Object;)V
   #86 = Utf8               Lorg/scalatest/fixture/FixtureNodeFamily$Branch;
   #87 = Utf8               Ljava/lang/String;
   #88 = Utf8               prefix
   #89 = Utf8               suffix
   #90 = Utf8               withoutVerb
   #91 = Utf8               this
   #92 = Utf8               getPrefixWithoutVerb
   #93 = Utf8               getFormattedSpecTextPrefix
   #94 = NameAndType        #93:#30       // getFormattedSpecTextPrefix:(Lorg/scalatest/fixture/FixtureNodeFamily$Branch;)Ljava/lang/String;
   #95 = Methodref          #2.#94        // org/scalatest/fixture/FixtureNodeFamily$.getFormattedSpecTextPrefix:(Lorg/scalatest/fixture/FixtureNodeFamily$Branch;)Ljava/lang/String;
   #96 = Utf8               getTestName
   #97 = Utf8               (Ljava/lang/String;Lorg/scalatest/fixture/FixtureNodeFamily$Branch;)Ljava/lang/String;
   #98 = Utf8               specText
   #99 = Utf8               trim
  #100 = NameAndType        #99:#39       // trim:()Ljava/lang/String;
  #101 = Methodref          #61.#100      // java/lang/String.trim:()Ljava/lang/String;
  #102 = Utf8               isEmpty
  #103 = Utf8               ()Z
  #104 = NameAndType        #102:#103     // isEmpty:()Z
  #105 = Methodref          #61.#104      // java/lang/String.isEmpty:()Z
  #106 = Methodref          #4.#25        // java/lang/Object."<init>":()V
  #107 = Utf8               Code
  #108 = Utf8               LineNumberTable
  #109 = Utf8               StackMapTable
  #110 = Utf8               LocalVariableTable
  #111 = Utf8               MethodParameters
  #112 = Utf8               InnerClasses
  #113 = Utf8               SourceFile
  #114 = Utf8               ScalaInlineInfo
  #115 = Utf8               Scala
{
  public static final org.scalatest.fixture.FixtureNodeFamily$ MODULE$;
    descriptor: Lorg/scalatest/fixture/FixtureNodeFamily$;
    flags: (0x0019) ACC_PUBLIC, ACC_STATIC, ACC_FINAL

  public static {};
    descriptor: ()V
    flags: (0x0009) ACC_PUBLIC, ACC_STATIC
    Code:
      stack=2, locals=0, args_size=0
         0: new           #2                  // class org/scalatest/fixture/FixtureNodeFamily$
         3: dup
         4: invokespecial #26                 // Method "<init>":()V
         7: putstatic     #28                 // Field MODULE$:Lorg/scalatest/fixture/FixtureNodeFamily$;
        10: return
      LineNumberTable:
        line 22: 0

  public java.lang.String getPrefix(org.scalatest.fixture.FixtureNodeFamily$Branch);
    descriptor: (Lorg/scalatest/fixture/FixtureNodeFamily$Branch;)Ljava/lang/String;
    flags: (0x0001) ACC_PUBLIC
    Code:
      stack=5, locals=14, args_size=2
         0: aload_1
         1: astore_3
         2: aload_3
         3: instanceof    #15                 // class org/scalatest/fixture/FixtureNodeFamily$Trunk
         6: ifeq          15
         9: ldc           #33                 // String
        11: astore_2
        12: goto          186
        15: goto          18
        18: aload_3
        19: instanceof    #12                 // class org/scalatest/fixture/FixtureNodeFamily$DescriptionBranch
        22: ifeq          63
        25: aload_3
        26: checkcast     #12                 // class org/scalatest/fixture/FixtureNodeFamily$DescriptionBranch
        29: astore        4
        31: aload         4
        33: invokevirtual #37                 // Method org/scalatest/fixture/FixtureNodeFamily$DescriptionBranch.parent:()Lorg/scalatest/fixture/FixtureNodeFamily$Branch;
        36: astore        5
        38: aload         4
        40: invokevirtual #41                 // Method org/scalatest/fixture/FixtureNodeFamily$DescriptionBranch.descriptionName:()Ljava/lang/String;
        43: astore        6
        45: getstatic     #46                 // Field org/scalatest/Resources$.MODULE$:Lorg/scalatest/Resources$;
        48: aload_0
        49: aload         5
        51: invokevirtual #48                 // Method getPrefix:(Lorg/scalatest/fixture/FixtureNodeFamily$Branch;)Ljava/lang/String;
        54: aload         6
        56: invokevirtual #52                 // Method org/scalatest/Resources$.prefixSuffix:(Ljava/lang/Object;Ljava/lang/Object;)Ljava/lang/String;
        59: astore_2
        60: goto          186
        63: goto          66
        66: aload_3
        67: instanceof    #18                 // class org/scalatest/fixture/FixtureNodeFamily$VerbBranch
        70: ifeq          174
        73: aload_3
        74: checkcast     #18                 // class org/scalatest/fixture/FixtureNodeFamily$VerbBranch
        77: astore        7
        79: aload         7
        81: invokevirtual #53                 // Method org/scalatest/fixture/FixtureNodeFamily$VerbBranch.parent:()Lorg/scalatest/fixture/FixtureNodeFamily$Branch;
        84: astore        8
        86: aload         7
        88: invokevirtual #54                 // Method org/scalatest/fixture/FixtureNodeFamily$VerbBranch.descriptionName:()Ljava/lang/String;
        91: astore        9
        93: aload         7
        95: invokevirtual #57                 // Method org/scalatest/fixture/FixtureNodeFamily$VerbBranch.verb:()Ljava/lang/String;
        98: astore        10
       100: aload_0
       101: aload         8
       103: invokevirtual #48                 // Method getPrefix:(Lorg/scalatest/fixture/FixtureNodeFamily$Branch;)Ljava/lang/String;
       106: astore        11
       108: aload         11
       110: ldc           #59                 // String  (when
       112: invokevirtual #65                 // Method java/lang/String.indexOf:(Ljava/lang/String;)I
       115: iconst_m1
       116: if_icmpeq     124
       119: ldc           #67                 // String )
       121: goto          126
       124: ldc           #33                 // String
       126: astore        12
       128: getstatic     #46                 // Field org/scalatest/Resources$.MODULE$:Lorg/scalatest/Resources$;
       131: aload         11
       133: new           #69                 // class java/lang/StringBuilder
       136: dup
       137: ldc           #70                 // int 0
       139: invokespecial #73                 // Method java/lang/StringBuilder."<init>":(I)V
       142: aload         9
       144: invokevirtual #77                 // Method java/lang/StringBuilder.append:(Ljava/lang/String;)Ljava/lang/StringBuilder;
       147: aload         12
       149: invokevirtual #77                 // Method java/lang/StringBuilder.append:(Ljava/lang/String;)Ljava/lang/StringBuilder;
       152: invokevirtual #80                 // Method java/lang/StringBuilder.toString:()Ljava/lang/String;
       155: invokevirtual #52                 // Method org/scalatest/Resources$.prefixSuffix:(Ljava/lang/Object;Ljava/lang/Object;)Ljava/lang/String;
       158: astore        13
       160: getstatic     #46                 // Field org/scalatest/Resources$.MODULE$:Lorg/scalatest/Resources$;
       163: aload         13
       165: aload         10
       167: invokevirtual #52                 // Method org/scalatest/Resources$.prefixSuffix:(Ljava/lang/Object;Ljava/lang/Object;)Ljava/lang/String;
       170: astore_2
       171: goto          186
       174: goto          177
       177: new           #82                 // class scala/MatchError
       180: dup
       181: aload_3
       182: invokespecial #85                 // Method scala/MatchError."<init>":(Ljava/lang/Object;)V
       185: athrow
       186: aload_2
       187: areturn
      StackMapTable: number_of_entries = 9
        frame_type = 253 /* append */
          offset_delta = 15
          locals = [ top, class org/scalatest/fixture/FixtureNodeFamily$Branch ]
        frame_type = 2 /* same */
        frame_type = 44 /* same */
        frame_type = 2 /* same */
        frame_type = 255 /* full_frame */
          offset_delta = 57
          locals = [ class org/scalatest/fixture/FixtureNodeFamily$, class org/scalatest/fixture/FixtureNodeFamily$Branch, top, class org/scalatest/fixture/FixtureNodeFamily$Branch, top, top, top, class org/scalatest/fixture/FixtureNodeFamily$VerbBranch, class org/scalatest/fixture/FixtureNodeFamily$Branch, class java/lang/String, class java/lang/String, class java/lang/String ]
          stack = []
        frame_type = 65 /* same_locals_1_stack_item */
          stack = [ class java/lang/String ]
        frame_type = 255 /* full_frame */
          offset_delta = 47
          locals = [ class org/scalatest/fixture/FixtureNodeFamily$, class org/scalatest/fixture/FixtureNodeFamily$Branch, top, class org/scalatest/fixture/FixtureNodeFamily$Branch ]
          stack = []
        frame_type = 2 /* same */
        frame_type = 255 /* full_frame */
          offset_delta = 8
          locals = [ class org/scalatest/fixture/FixtureNodeFamily$, class org/scalatest/fixture/FixtureNodeFamily$Branch, class java/lang/String, class org/scalatest/fixture/FixtureNodeFamily$Branch ]
          stack = []
      LineNumberTable:
        line 56: 0
        line 57: 2
        line 60: 18
        line 61: 45
        line 60: 63
        line 62: 66
        line 63: 100
        line 64: 108
        line 65: 128
        line 66: 160
        line 62: 174
        line 56: 177
      LocalVariableTable:
        Start  Length  Slot  Name   Signature
           38      25     5 parent   Lorg/scalatest/fixture/FixtureNodeFamily$Branch;
           45      18     6 descriptionName   Ljava/lang/String;
          108      62    11 prefix   Ljava/lang/String;
          128      42    12 suffix   Ljava/lang/String;
          160      10    13 withoutVerb   Ljava/lang/String;
           86      88     8 parent   Lorg/scalatest/fixture/FixtureNodeFamily$Branch;
           93      81     9 descriptionName   Ljava/lang/String;
          100      74    10  verb   Ljava/lang/String;
            0     188     0  this   Lorg/scalatest/fixture/FixtureNodeFamily$;
            0     188     1 branch   Lorg/scalatest/fixture/FixtureNodeFamily$Branch;
    MethodParameters:
      Name                           Flags
      branch                         final

  public java.lang.String getPrefixWithoutVerb(org.scalatest.fixture.FixtureNodeFamily$Branch);
    descriptor: (Lorg/scalatest/fixture/FixtureNodeFamily$Branch;)Ljava/lang/String;
    flags: (0x0001) ACC_PUBLIC
    Code:
      stack=5, locals=12, args_size=2
         0: aload_1
         1: astore_3
         2: aload_3
         3: instanceof    #15                 // class org/scalatest/fixture/FixtureNodeFamily$Trunk
         6: ifeq          15
         9: ldc           #33                 // String
        11: astore_2
        12: goto          167
        15: goto          18
        18: aload_3
        19: instanceof    #12                 // class org/scalatest/fixture/FixtureNodeFamily$DescriptionBranch
        22: ifeq          63
        25: aload_3
        26: checkcast     #12                 // class org/scalatest/fixture/FixtureNodeFamily$DescriptionBranch
        29: astore        4
        31: aload         4
        33: invokevirtual #37                 // Method org/scalatest/fixture/FixtureNodeFamily$DescriptionBranch.parent:()Lorg/scalatest/fixture/FixtureNodeFamily$Branch;
        36: astore        5
        38: aload         4
        40: invokevirtual #41                 // Method org/scalatest/fixture/FixtureNodeFamily$DescriptionBranch.descriptionName:()Ljava/lang/String;
        43: astore        6
        45: getstatic     #46                 // Field org/scalatest/Resources$.MODULE$:Lorg/scalatest/Resources$;
        48: aload_0
        49: aload         5
        51: invokevirtual #48                 // Method getPrefix:(Lorg/scalatest/fixture/FixtureNodeFamily$Branch;)Ljava/lang/String;
        54: aload         6
        56: invokevirtual #52                 // Method org/scalatest/Resources$.prefixSuffix:(Ljava/lang/Object;Ljava/lang/Object;)Ljava/lang/String;
        59: astore_2
        60: goto          167
        63: goto          66
        66: aload_3
        67: instanceof    #18                 // class org/scalatest/fixture/FixtureNodeFamily$VerbBranch
        70: ifeq          155
        73: aload_3
        74: checkcast     #18                 // class org/scalatest/fixture/FixtureNodeFamily$VerbBranch
        77: astore        7
        79: aload         7
        81: invokevirtual #53                 // Method org/scalatest/fixture/FixtureNodeFamily$VerbBranch.parent:()Lorg/scalatest/fixture/FixtureNodeFamily$Branch;
        84: astore        8
        86: aload         7
        88: invokevirtual #54                 // Method org/scalatest/fixture/FixtureNodeFamily$VerbBranch.descriptionName:()Ljava/lang/String;
        91: astore        9
        93: aload_0
        94: aload         8
        96: invokevirtual #48                 // Method getPrefix:(Lorg/scalatest/fixture/FixtureNodeFamily$Branch;)Ljava/lang/String;
        99: astore        10
       101: aload         10
       103: ldc           #59                 // String  (when
       105: invokevirtual #65                 // Method java/lang/String.indexOf:(Ljava/lang/String;)I
       108: iconst_m1
       109: if_icmpeq     117
       112: ldc           #67                 // String )
       114: goto          119
       117: ldc           #33                 // String
       119: astore        11
       121: getstatic     #46                 // Field org/scalatest/Resources$.MODULE$:Lorg/scalatest/Resources$;
       124: aload         10
       126: new           #69                 // class java/lang/StringBuilder
       129: dup
       130: ldc           #70                 // int 0
       132: invokespecial #73                 // Method java/lang/StringBuilder."<init>":(I)V
       135: aload         9
       137: invokevirtual #77                 // Method java/lang/StringBuilder.append:(Ljava/lang/String;)Ljava/lang/StringBuilder;
       140: aload         11
       142: invokevirtual #77                 // Method java/lang/StringBuilder.append:(Ljava/lang/String;)Ljava/lang/StringBuilder;
       145: invokevirtual #80                 // Method java/lang/StringBuilder.toString:()Ljava/lang/String;
       148: invokevirtual #52                 // Method org/scalatest/Resources$.prefixSuffix:(Ljava/lang/Object;Ljava/lang/Object;)Ljava/lang/String;
       151: astore_2
       152: goto          167
       155: goto          158
       158: new           #82                 // class scala/MatchError
       161: dup
       162: aload_3
       163: invokespecial #85                 // Method scala/MatchError."<init>":(Ljava/lang/Object;)V
       166: athrow
       167: aload_2
       168: areturn
      StackMapTable: number_of_entries = 9
        frame_type = 253 /* append */
          offset_delta = 15
          locals = [ top, class org/scalatest/fixture/FixtureNodeFamily$Branch ]
        frame_type = 2 /* same */
        frame_type = 44 /* same */
        frame_type = 2 /* same */
        frame_type = 255 /* full_frame */
          offset_delta = 50
          locals = [ class org/scalatest/fixture/FixtureNodeFamily$, class org/scalatest/fixture/FixtureNodeFamily$Branch, top, class org/scalatest/fixture/FixtureNodeFamily$Branch, top, top, top, class org/scalatest/fixture/FixtureNodeFamily$VerbBranch, class org/scalatest/fixture/FixtureNodeFamily$Branch, class java/lang/String, class java/lang/String ]
          stack = []
        frame_type = 65 /* same_locals_1_stack_item */
          stack = [ class java/lang/String ]
        frame_type = 255 /* full_frame */
          offset_delta = 35
          locals = [ class org/scalatest/fixture/FixtureNodeFamily$, class org/scalatest/fixture/FixtureNodeFamily$Branch, top, class org/scalatest/fixture/FixtureNodeFamily$Branch ]
          stack = []
        frame_type = 2 /* same */
        frame_type = 255 /* full_frame */
          offset_delta = 8
          locals = [ class org/scalatest/fixture/FixtureNodeFamily$, class org/scalatest/fixture/FixtureNodeFamily$Branch, class java/lang/String, class org/scalatest/fixture/FixtureNodeFamily$Branch ]
          stack = []
      LineNumberTable:
        line 74: 0
        line 75: 2
        line 78: 18
        line 79: 45
        line 78: 63
        line 80: 66
        line 81: 93
        line 82: 101
        line 83: 121
        line 80: 155
        line 74: 158
      LocalVariableTable:
        Start  Length  Slot  Name   Signature
           38      25     5 parent   Lorg/scalatest/fixture/FixtureNodeFamily$Branch;
           45      18     6 descriptionName   Ljava/lang/String;
          101      50    10 prefix   Ljava/lang/String;
          121      30    11 suffix   Ljava/lang/String;
           86      69     8 parent   Lorg/scalatest/fixture/FixtureNodeFamily$Branch;
           93      62     9 descriptionName   Ljava/lang/String;
            0     169     0  this   Lorg/scalatest/fixture/FixtureNodeFamily$;
            0     169     1 branch   Lorg/scalatest/fixture/FixtureNodeFamily$Branch;
    MethodParameters:
      Name                           Flags
      branch                         final

  public java.lang.String getFormattedSpecTextPrefix(org.scalatest.fixture.FixtureNodeFamily$Branch);
    descriptor: (Lorg/scalatest/fixture/FixtureNodeFamily$Branch;)Ljava/lang/String;
    flags: (0x0001) ACC_PUBLIC
    Code:
      stack=3, locals=9, args_size=2
         0: aload_1
         1: astore_3
         2: aload_3
         3: instanceof    #15                 // class org/scalatest/fixture/FixtureNodeFamily$Trunk
         6: ifeq          15
         9: ldc           #33                 // String
        11: astore_2
        12: goto          104
        15: goto          18
        18: aload_3
        19: instanceof    #12                 // class org/scalatest/fixture/FixtureNodeFamily$DescriptionBranch
        22: ifeq          63
        25: aload_3
        26: checkcast     #12                 // class org/scalatest/fixture/FixtureNodeFamily$DescriptionBranch
        29: astore        4
        31: aload         4
        33: invokevirtual #37                 // Method org/scalatest/fixture/FixtureNodeFamily$DescriptionBranch.parent:()Lorg/scalatest/fixture/FixtureNodeFamily$Branch;
        36: astore        5
        38: aload         4
        40: invokevirtual #41                 // Method org/scalatest/fixture/FixtureNodeFamily$DescriptionBranch.descriptionName:()Ljava/lang/String;
        43: astore        6
        45: getstatic     #46                 // Field org/scalatest/Resources$.MODULE$:Lorg/scalatest/Resources$;
        48: aload_0
        49: aload         5
        51: invokevirtual #95                 // Method getFormattedSpecTextPrefix:(Lorg/scalatest/fixture/FixtureNodeFamily$Branch;)Ljava/lang/String;
        54: aload         6
        56: invokevirtual #52                 // Method org/scalatest/Resources$.prefixSuffix:(Ljava/lang/Object;Ljava/lang/Object;)Ljava/lang/String;
        59: astore_2
        60: goto          104
        63: goto          66
        66: aload_3
        67: instanceof    #18                 // class org/scalatest/fixture/FixtureNodeFamily$VerbBranch
        70: ifeq          92
        73: aload_3
        74: checkcast     #18                 // class org/scalatest/fixture/FixtureNodeFamily$VerbBranch
        77: astore        7
        79: aload         7
        81: invokevirtual #57                 // Method org/scalatest/fixture/FixtureNodeFamily$VerbBranch.verb:()Ljava/lang/String;
        84: astore        8
        86: aload         8
        88: astore_2
        89: goto          104
        92: goto          95
        95: new           #82                 // class scala/MatchError
        98: dup
        99: aload_3
       100: invokespecial #85                 // Method scala/MatchError."<init>":(Ljava/lang/Object;)V
       103: athrow
       104: aload_2
       105: areturn
      StackMapTable: number_of_entries = 7
        frame_type = 253 /* append */
          offset_delta = 15
          locals = [ top, class org/scalatest/fixture/FixtureNodeFamily$Branch ]
        frame_type = 2 /* same */
        frame_type = 44 /* same */
        frame_type = 2 /* same */
        frame_type = 25 /* same */
        frame_type = 2 /* same */
        frame_type = 255 /* full_frame */
          offset_delta = 8
          locals = [ class org/scalatest/fixture/FixtureNodeFamily$, class org/scalatest/fixture/FixtureNodeFamily$Branch, class java/lang/String, class org/scalatest/fixture/FixtureNodeFamily$Branch ]
          stack = []
      LineNumberTable:
        line 91: 0
        line 92: 2
        line 95: 18
        line 96: 45
        line 95: 63
        line 97: 66
        line 91: 95
      LocalVariableTable:
        Start  Length  Slot  Name   Signature
           38      25     5 parent   Lorg/scalatest/fixture/FixtureNodeFamily$Branch;
           45      18     6 descriptionName   Ljava/lang/String;
           86       6     8  verb   Ljava/lang/String;
            0     106     0  this   Lorg/scalatest/fixture/FixtureNodeFamily$;
            0     106     1 branch   Lorg/scalatest/fixture/FixtureNodeFamily$Branch;
    MethodParameters:
      Name                           Flags
      branch                         final

  public java.lang.String getTestName(java.lang.String, org.scalatest.fixture.FixtureNodeFamily$Branch);
    descriptor: (Ljava/lang/String;Lorg/scalatest/fixture/FixtureNodeFamily$Branch;)Ljava/lang/String;
    flags: (0x0001) ACC_PUBLIC
    Code:
      stack=3, locals=4, args_size=3
         0: aload_0
         1: aload_2
         2: invokevirtual #48                 // Method getPrefix:(Lorg/scalatest/fixture/FixtureNodeFamily$Branch;)Ljava/lang/String;
         5: invokevirtual #101                // Method java/lang/String.trim:()Ljava/lang/String;
         8: astore_3
         9: aload_3
        10: invokevirtual #105                // Method java/lang/String.isEmpty:()Z
        13: ifeq          20
        16: aload_1
        17: goto          28
        20: getstatic     #46                 // Field org/scalatest/Resources$.MODULE$:Lorg/scalatest/Resources$;
        23: aload_3
        24: aload_1
        25: invokevirtual #52                 // Method org/scalatest/Resources$.prefixSuffix:(Ljava/lang/Object;Ljava/lang/Object;)Ljava/lang/String;
        28: areturn
      StackMapTable: number_of_entries = 2
        frame_type = 252 /* append */
          offset_delta = 20
          locals = [ class java/lang/String ]
        frame_type = 71 /* same_locals_1_stack_item */
          stack = [ class java/lang/String ]
      LineNumberTable:
        line 102: 0
        line 103: 9
        line 108: 16
        line 117: 20
      LocalVariableTable:
        Start  Length  Slot  Name   Signature
            9      19     3 prefix   Ljava/lang/String;
            0      29     0  this   Lorg/scalatest/fixture/FixtureNodeFamily$;
            0      29     1 specText   Ljava/lang/String;
            0      29     2 parent   Lorg/scalatest/fixture/FixtureNodeFamily$Branch;
    MethodParameters:
      Name                           Flags
      specText                       final
      parent                         final

  private org.scalatest.fixture.FixtureNodeFamily$();
    descriptor: ()V
    flags: (0x0002) ACC_PRIVATE
    Code:
      stack=1, locals=1, args_size=1
         0: aload_0
         1: invokespecial #106                // Method java/lang/Object."<init>":()V
         4: return
      LineNumberTable:
        line 120: 0
        line 22: 4
      LocalVariableTable:
        Start  Length  Slot  Name   Signature
            0       5     0  this   Lorg/scalatest/fixture/FixtureNodeFamily$;
}
InnerClasses:
  public static abstract #10= #7 of #9;   // Branch=class org/scalatest/fixture/FixtureNodeFamily$Branch of class org/scalatest/fixture/FixtureNodeFamily
  public static #13= #12 of #9;           // DescriptionBranch=class org/scalatest/fixture/FixtureNodeFamily$DescriptionBranch of class org/scalatest/fixture/FixtureNodeFamily
  public static #16= #15 of #9;           // Trunk=class org/scalatest/fixture/FixtureNodeFamily$Trunk of class org/scalatest/fixture/FixtureNodeFamily
  public static #19= #18 of #9;           // VerbBranch=class org/scalatest/fixture/FixtureNodeFamily$VerbBranch of class org/scalatest/fixture/FixtureNodeFamily
SourceFile: "FixtureNodeFamily.scala"
  ScalaInlineInfo: length = 0x1D (unknown attribute)
   01 01 00 05 00 18 00 17 01 00 5D 00 1E 01 00 1D
   00 1E 01 00 5C 00 1E 01 00 60 00 61 01
  Scala: length = 0x0 (unknown attribute)

