Classfile /Users/mw/Projects/slang-braindump/.jar/jar11/assemble/slang-braindump/assemble/content/org/scalatest/fixture/UnitFixture.class
  Last modified May 29, 2022; size 1738 bytes
  SHA-256 checksum 570c1463eabc6627aca46cbd39dba81a6d8e0fb3a3f7b9b9a1b4cd9a8e0958c4
  Compiled from "UnitFixture.scala"
public interface org.scalatest.fixture.UnitFixture
  minor version: 0
  major version: 52
  flags: (0x0601) ACC_PUBLIC, ACC_INTERFACE, ACC_ABSTRACT
  this_class: #2                          // org/scalatest/fixture/UnitFixture
  super_class: #4                         // java/lang/Object
  interfaces: 0, fields: 0, methods: 3, attributes: 5
Constant pool:
   #1 = Utf8               org/scalatest/fixture/UnitFixture
   #2 = Class              #1             // org/scalatest/fixture/UnitFixture
   #3 = Utf8               java/lang/Object
   #4 = Class              #3             // java/lang/Object
   #5 = Utf8               UnitFixture.scala
   #6 = Utf8               Lscala/reflect/ScalaSignature;
   #7 = Utf8               bytes
   #8 = Utf8               \u0006\u000552\u0001\u0002B\u0003\u0011\u0002\u0007\u0005Ab\n\u0005\u0006\'\u0001!\t\u0001F\u0003\u00051\u0001\u0001Q\u0003C\u0003\u001a\u0001\u0011\u0005!DA\u0006V]&$h)\u001b=ukJ,\'B\u0001\u0004\b\u0003\u001d1\u0017\u000e\u001f;ve\u0016T!\u0001C\u0005\u0002\u0013M\u001c\u0017\r\\1uKN$(\"\u0001\u0006\u0002\u0007=\u0014xm\u0001\u0001\u0014\u0005\u0001i\u0001C\u0001\b\u0012\u001b\u0005y!\"\u0001\t\u0002\u000bM\u001c\u0017\r\\1\n\u0005Iy!AB!osJ+g-\u0001\u0004%S:LG\u000f\n\u000b\u0002+A\u0011aBF\u0005\u0003/=\u0011A!\u00168ji\naa)\u001b=ukJ,\u0007+\u0019:b[\u0006Yq/\u001b;i\r&DH/\u001e:f)\tYr\u0004\u0005\u0002\u001d;5\tq!\u0003\u0002\u001f\u000f\t9q*\u001e;d_6,\u0007\"\u0002\u0011\u0004\u0001\u0004\t\u0013\u0001\u0002;fgR\u0004\"AI\u0012\u000e\u0003\u0001I!\u0001J\u0013\u0003\u0015=sW-\u0011:h)\u0016\u001cH/\u0003\u0002\'\u000f\t\u0001b)\u001b=ukJ,G+Z:u\'VLG/\u001a\n\u0004Q)bc\u0001B\u0015\u0001\u0001\u001d\u0012A\u0002\u0010:fM&tW-\\3oiz\u0002\"a\u000b\u0001\u000e\u0003\u0015\u0001\"\u0001H\u0013
   #9 = Utf8               org/scalatest/FixtureTestSuite$OneArgTest
  #10 = Class              #9             // org/scalatest/FixtureTestSuite$OneArgTest
  #11 = Utf8               org/scalatest/FixtureTestSuite
  #12 = Class              #11            // org/scalatest/FixtureTestSuite
  #13 = Utf8               OneArgTest
  #14 = Utf8               org/scalatest/TestSuite$NoArgTest
  #15 = Class              #14            // org/scalatest/TestSuite$NoArgTest
  #16 = Utf8               org/scalatest/TestSuite
  #17 = Class              #16            // org/scalatest/TestSuite
  #18 = Utf8               NoArgTest
  #19 = Utf8               withFixture$
  #20 = Utf8               (Lorg/scalatest/fixture/UnitFixture;Lorg/scalatest/FixtureTestSuite$OneArgTest;)Lorg/scalatest/Outcome;
  #21 = Utf8               $this
  #22 = Utf8               test
  #23 = Utf8               withFixture
  #24 = Utf8               (Lorg/scalatest/FixtureTestSuite$OneArgTest;)Lorg/scalatest/Outcome;
  #25 = NameAndType        #23:#24        // withFixture:(Lorg/scalatest/FixtureTestSuite$OneArgTest;)Lorg/scalatest/Outcome;
  #26 = InterfaceMethodref #2.#25         // org/scalatest/fixture/UnitFixture.withFixture:(Lorg/scalatest/FixtureTestSuite$OneArgTest;)Lorg/scalatest/Outcome;
  #27 = Utf8               Lorg/scalatest/fixture/UnitFixture;
  #28 = Utf8               Lorg/scalatest/FixtureTestSuite$OneArgTest;
  #29 = Utf8               scala/runtime/BoxedUnit
  #30 = Class              #29            // scala/runtime/BoxedUnit
  #31 = Utf8               UNIT
  #32 = Utf8               Lscala/runtime/BoxedUnit;
  #33 = NameAndType        #31:#32        // UNIT:Lscala/runtime/BoxedUnit;
  #34 = Fieldref           #30.#33        // scala/runtime/BoxedUnit.UNIT:Lscala/runtime/BoxedUnit;
  #35 = Utf8               toNoArgTest
  #36 = Utf8               (Ljava/lang/Object;)Lorg/scalatest/TestSuite$NoArgTest;
  #37 = NameAndType        #35:#36        // toNoArgTest:(Ljava/lang/Object;)Lorg/scalatest/TestSuite$NoArgTest;
  #38 = InterfaceMethodref #10.#37        // org/scalatest/FixtureTestSuite$OneArgTest.toNoArgTest:(Ljava/lang/Object;)Lorg/scalatest/TestSuite$NoArgTest;
  #39 = Utf8               (Lorg/scalatest/TestSuite$NoArgTest;)Lorg/scalatest/Outcome;
  #40 = NameAndType        #23:#39        // withFixture:(Lorg/scalatest/TestSuite$NoArgTest;)Lorg/scalatest/Outcome;
  #41 = InterfaceMethodref #17.#40        // org/scalatest/TestSuite.withFixture:(Lorg/scalatest/TestSuite$NoArgTest;)Lorg/scalatest/Outcome;
  #42 = Utf8               this
  #43 = Utf8               $init$
  #44 = Utf8               (Lorg/scalatest/fixture/UnitFixture;)V
  #45 = Utf8               Code
  #46 = Utf8               LineNumberTable
  #47 = Utf8               LocalVariableTable
  #48 = Utf8               MethodParameters
  #49 = Utf8               InnerClasses
  #50 = Utf8               SourceFile
  #51 = Utf8               RuntimeVisibleAnnotations
  #52 = Utf8               ScalaInlineInfo
  #53 = Utf8               ScalaSig
{
  public static org.scalatest.Outcome withFixture$(org.scalatest.fixture.UnitFixture, org.scalatest.FixtureTestSuite$OneArgTest);
    descriptor: (Lorg/scalatest/fixture/UnitFixture;Lorg/scalatest/FixtureTestSuite$OneArgTest;)Lorg/scalatest/Outcome;
    flags: (0x1009) ACC_PUBLIC, ACC_STATIC, ACC_SYNTHETIC
    Code:
      stack=2, locals=2, args_size=2
         0: aload_0
         1: aload_1
         2: invokespecial #26                 // InterfaceMethod withFixture:(Lorg/scalatest/FixtureTestSuite$OneArgTest;)Lorg/scalatest/Outcome;
         5: areturn
      LineNumberTable:
        line 51: 0
      LocalVariableTable:
        Start  Length  Slot  Name   Signature
            0       6     0 $this   Lorg/scalatest/fixture/UnitFixture;
            0       6     1  test   Lorg/scalatest/FixtureTestSuite$OneArgTest;
    MethodParameters:
      Name                           Flags
      $this                          final synthetic
      test                           final

  public default org.scalatest.Outcome withFixture(org.scalatest.FixtureTestSuite$OneArgTest);
    descriptor: (Lorg/scalatest/FixtureTestSuite$OneArgTest;)Lorg/scalatest/Outcome;
    flags: (0x0001) ACC_PUBLIC
    Code:
      stack=3, locals=2, args_size=2
         0: aload_0
         1: checkcast     #17                 // class org/scalatest/TestSuite
         4: aload_1
         5: getstatic     #34                 // Field scala/runtime/BoxedUnit.UNIT:Lscala/runtime/BoxedUnit;
         8: invokeinterface #38,  2           // InterfaceMethod org/scalatest/FixtureTestSuite$OneArgTest.toNoArgTest:(Ljava/lang/Object;)Lorg/scalatest/TestSuite$NoArgTest;
        13: invokeinterface #41,  2           // InterfaceMethod org/scalatest/TestSuite.withFixture:(Lorg/scalatest/TestSuite$NoArgTest;)Lorg/scalatest/Outcome;
        18: areturn
      LineNumberTable:
        line 52: 0
      LocalVariableTable:
        Start  Length  Slot  Name   Signature
            0      19     0  this   Lorg/scalatest/fixture/UnitFixture;
            0      19     1  test   Lorg/scalatest/FixtureTestSuite$OneArgTest;
    MethodParameters:
      Name                           Flags
      test                           final

  public static void $init$(org.scalatest.fixture.UnitFixture);
    descriptor: (Lorg/scalatest/fixture/UnitFixture;)V
    flags: (0x0009) ACC_PUBLIC, ACC_STATIC
    Code:
      stack=0, locals=1, args_size=1
         0: return
      LineNumberTable:
        line 32: 0
      LocalVariableTable:
        Start  Length  Slot  Name   Signature
            0       1     0 $this   Lorg/scalatest/fixture/UnitFixture;
    MethodParameters:
      Name                           Flags
      $this                          final synthetic
}
InnerClasses:
  public #13= #10 of #12;                 // OneArgTest=class org/scalatest/FixtureTestSuite$OneArgTest of class org/scalatest/FixtureTestSuite
  public #18= #15 of #17;                 // NoArgTest=class org/scalatest/TestSuite$NoArgTest of class org/scalatest/TestSuite
SourceFile: "UnitFixture.scala"
RuntimeVisibleAnnotations:
  0: #6(#7=s#8)
    scala.reflect.ScalaSignature(
      bytes="\u0006\u000552\u0001\u0002B\u0003\u0011\u0002\u0007\u0005Ab\n\u0005\u0006\'\u0001!\t\u0001F\u0003\u00051\u0001\u0001Q\u0003C\u0003\u001a\u0001\u0011\u0005!DA\u0006V]&$h)\u001b=ukJ,\'B\u0001\u0004\b\u0003\u001d1\u0017\u000e\u001f;ve\u0016T!\u0001C\u0005\u0002\u0013M\u001c\u0017\r\\1uKN$(\"\u0001\u0006\u0002\u0007=\u0014xm\u0001\u0001\u0014\u0005\u0001i\u0001C\u0001\b\u0012\u001b\u0005y!\"\u0001\t\u0002\u000bM\u001c\u0017\r\\1\n\u0005Iy!AB!osJ+g-\u0001\u0004%S:LG\u000f\n\u000b\u0002+A\u0011aBF\u0005\u0003/=\u0011A!\u00168ji\naa)\u001b=ukJ,\u0007+\u0019:b[\u0006Yq/\u001b;i\r&DH/\u001e:f)\tYr\u0004\u0005\u0002\u001d;5\tq!\u0003\u0002\u001f\u000f\t9q*\u001e;d_6,\u0007\"\u0002\u0011\u0004\u0001\u0004\t\u0013\u0001\u0002;fgR\u0004\"AI\u0012\u000e\u0003\u0001I!\u0001J\u0013\u0003\u0015=sW-\u0011:h)\u0016\u001cH/\u0003\u0002\'\u000f\t\u0001b)\u001b=ukJ,G+Z:u\'VLG/\u001a\n\u0004Q)bc\u0001B\u0015\u0001\u0001\u001d\u0012A\u0002\u0010:fM&tW-\\3oiz\u0002\"a\u000b\u0001\u000e\u0003\u0015\u0001\"\u0001H\u0013"
    )
  ScalaInlineInfo: length = 0x13 (unknown attribute)
   01 00 00 03 00 2B 00 2C 01 00 17 00 18 00 00 13
   00 14 01
  ScalaSig: length = 0x3 (unknown attribute)
   05 02 00
