Classfile /Users/mw/Projects/slang-braindump/.jar/jar8/assemble/slang-braindump/assemble/content/com/fasterxml/jackson/databind/ext/Java7HandlersImpl.class
  Last modified May 29, 2022; size 1523 bytes
  SHA-256 checksum 752fa7ba08b1cd76ba39cc65a9cd74a665c0a33b24e79cf7da55b0ed4ad30207
  Compiled from "Java7HandlersImpl.java"
public class com.fasterxml.jackson.databind.ext.Java7HandlersImpl extends com.fasterxml.jackson.databind.ext.Java7Handlers
  minor version: 0
  major version: 52
  flags: (0x0021) ACC_PUBLIC, ACC_SUPER
  this_class: #9                          // com/fasterxml/jackson/databind/ext/Java7HandlersImpl
  super_class: #10                        // com/fasterxml/jackson/databind/ext/Java7Handlers
  interfaces: 0, fields: 1, methods: 4, attributes: 1
Constant pool:
   #1 = Methodref          #10.#36        // com/fasterxml/jackson/databind/ext/Java7Handlers."<init>":()V
   #2 = Class              #37            // java/nio/file/Path
   #3 = Fieldref           #9.#38         // com/fasterxml/jackson/databind/ext/Java7HandlersImpl._pathClass:Ljava/lang/Class;
   #4 = Class              #39            // com/fasterxml/jackson/databind/ext/NioPathDeserializer
   #5 = Methodref          #4.#36         // com/fasterxml/jackson/databind/ext/NioPathDeserializer."<init>":()V
   #6 = Methodref          #40.#41        // java/lang/Class.isAssignableFrom:(Ljava/lang/Class;)Z
   #7 = Class              #42            // com/fasterxml/jackson/databind/ext/NioPathSerializer
   #8 = Methodref          #7.#36         // com/fasterxml/jackson/databind/ext/NioPathSerializer."<init>":()V
   #9 = Class              #43            // com/fasterxml/jackson/databind/ext/Java7HandlersImpl
  #10 = Class              #44            // com/fasterxml/jackson/databind/ext/Java7Handlers
  #11 = Utf8               _pathClass
  #12 = Utf8               Ljava/lang/Class;
  #13 = Utf8               Signature
  #14 = Utf8               Ljava/lang/Class<*>;
  #15 = Utf8               <init>
  #16 = Utf8               ()V
  #17 = Utf8               Code
  #18 = Utf8               LineNumberTable
  #19 = Utf8               LocalVariableTable
  #20 = Utf8               this
  #21 = Utf8               Lcom/fasterxml/jackson/databind/ext/Java7HandlersImpl;
  #22 = Utf8               getClassJavaNioFilePath
  #23 = Utf8               ()Ljava/lang/Class;
  #24 = Utf8               ()Ljava/lang/Class<*>;
  #25 = Utf8               getDeserializerForJavaNioFilePath
  #26 = Utf8               (Ljava/lang/Class;)Lcom/fasterxml/jackson/databind/JsonDeserializer;
  #27 = Utf8               rawType
  #28 = Utf8               LocalVariableTypeTable
  #29 = Utf8               StackMapTable
  #30 = Utf8               (Ljava/lang/Class<*>;)Lcom/fasterxml/jackson/databind/JsonDeserializer<*>;
  #31 = Utf8               getSerializerForJavaNioFilePath
  #32 = Utf8               (Ljava/lang/Class;)Lcom/fasterxml/jackson/databind/JsonSerializer;
  #33 = Utf8               (Ljava/lang/Class<*>;)Lcom/fasterxml/jackson/databind/JsonSerializer<*>;
  #34 = Utf8               SourceFile
  #35 = Utf8               Java7HandlersImpl.java
  #36 = NameAndType        #15:#16        // "<init>":()V
  #37 = Utf8               java/nio/file/Path
  #38 = NameAndType        #11:#12        // _pathClass:Ljava/lang/Class;
  #39 = Utf8               com/fasterxml/jackson/databind/ext/NioPathDeserializer
  #40 = Class              #45            // java/lang/Class
  #41 = NameAndType        #46:#47        // isAssignableFrom:(Ljava/lang/Class;)Z
  #42 = Utf8               com/fasterxml/jackson/databind/ext/NioPathSerializer
  #43 = Utf8               com/fasterxml/jackson/databind/ext/Java7HandlersImpl
  #44 = Utf8               com/fasterxml/jackson/databind/ext/Java7Handlers
  #45 = Utf8               java/lang/Class
  #46 = Utf8               isAssignableFrom
  #47 = Utf8               (Ljava/lang/Class;)Z
{
  private final java.lang.Class<?> _pathClass;
    descriptor: Ljava/lang/Class;
    flags: (0x0012) ACC_PRIVATE, ACC_FINAL
    Signature: #14                          // Ljava/lang/Class<*>;

  public com.fasterxml.jackson.databind.ext.Java7HandlersImpl();
    descriptor: ()V
    flags: (0x0001) ACC_PUBLIC
    Code:
      stack=2, locals=1, args_size=1
         0: aload_0
         1: invokespecial #1                  // Method com/fasterxml/jackson/databind/ext/Java7Handlers."<init>":()V
         4: aload_0
         5: ldc           #2                  // class java/nio/file/Path
         7: putfield      #3                  // Field _pathClass:Ljava/lang/Class;
        10: return
      LineNumberTable:
        line 15: 0
        line 18: 4
        line 19: 10
      LocalVariableTable:
        Start  Length  Slot  Name   Signature
            0      11     0  this   Lcom/fasterxml/jackson/databind/ext/Java7HandlersImpl;

  public java.lang.Class<?> getClassJavaNioFilePath();
    descriptor: ()Ljava/lang/Class;
    flags: (0x0001) ACC_PUBLIC
    Code:
      stack=1, locals=1, args_size=1
         0: aload_0
         1: getfield      #3                  // Field _pathClass:Ljava/lang/Class;
         4: areturn
      LineNumberTable:
        line 23: 0
      LocalVariableTable:
        Start  Length  Slot  Name   Signature
            0       5     0  this   Lcom/fasterxml/jackson/databind/ext/Java7HandlersImpl;
    Signature: #24                          // ()Ljava/lang/Class<*>;

  public com.fasterxml.jackson.databind.JsonDeserializer<?> getDeserializerForJavaNioFilePath(java.lang.Class<?>);
    descriptor: (Ljava/lang/Class;)Lcom/fasterxml/jackson/databind/JsonDeserializer;
    flags: (0x0001) ACC_PUBLIC
    Code:
      stack=2, locals=2, args_size=2
         0: aload_1
         1: aload_0
         2: getfield      #3                  // Field _pathClass:Ljava/lang/Class;
         5: if_acmpne     16
         8: new           #4                  // class com/fasterxml/jackson/databind/ext/NioPathDeserializer
        11: dup
        12: invokespecial #5                  // Method com/fasterxml/jackson/databind/ext/NioPathDeserializer."<init>":()V
        15: areturn
        16: aconst_null
        17: areturn
      LineNumberTable:
        line 28: 0
        line 29: 8
        line 31: 16
      LocalVariableTable:
        Start  Length  Slot  Name   Signature
            0      18     0  this   Lcom/fasterxml/jackson/databind/ext/Java7HandlersImpl;
            0      18     1 rawType   Ljava/lang/Class;
      LocalVariableTypeTable:
        Start  Length  Slot  Name   Signature
            0      18     1 rawType   Ljava/lang/Class<*>;
      StackMapTable: number_of_entries = 1
        frame_type = 16 /* same */
    Signature: #30                          // (Ljava/lang/Class<*>;)Lcom/fasterxml/jackson/databind/JsonDeserializer<*>;

  public com.fasterxml.jackson.databind.JsonSerializer<?> getSerializerForJavaNioFilePath(java.lang.Class<?>);
    descriptor: (Ljava/lang/Class;)Lcom/fasterxml/jackson/databind/JsonSerializer;
    flags: (0x0001) ACC_PUBLIC
    Code:
      stack=2, locals=2, args_size=2
         0: aload_0
         1: getfield      #3                  // Field _pathClass:Ljava/lang/Class;
         4: aload_1
         5: invokevirtual #6                  // Method java/lang/Class.isAssignableFrom:(Ljava/lang/Class;)Z
         8: ifeq          19
        11: new           #7                  // class com/fasterxml/jackson/databind/ext/NioPathSerializer
        14: dup
        15: invokespecial #8                  // Method com/fasterxml/jackson/databind/ext/NioPathSerializer."<init>":()V
        18: areturn
        19: aconst_null
        20: areturn
      LineNumberTable:
        line 36: 0
        line 37: 11
        line 39: 19
      LocalVariableTable:
        Start  Length  Slot  Name   Signature
            0      21     0  this   Lcom/fasterxml/jackson/databind/ext/Java7HandlersImpl;
            0      21     1 rawType   Ljava/lang/Class;
      LocalVariableTypeTable:
        Start  Length  Slot  Name   Signature
            0      21     1 rawType   Ljava/lang/Class<*>;
      StackMapTable: number_of_entries = 1
        frame_type = 19 /* same */
    Signature: #33                          // (Ljava/lang/Class<*>;)Lcom/fasterxml/jackson/databind/JsonSerializer<*>;
}
SourceFile: "Java7HandlersImpl.java"
