Classfile /Users/mw/Projects/slang-braindump/.jar/jar8/assemble/slang-braindump/assemble/content/com/fasterxml/jackson/databind/ext/SqlBlobSerializer.class
  Last modified May 29, 2022; size 5035 bytes
  SHA-256 checksum 828b63b55abbf4d4bbc63f2cbcf8ae740a6fe8f1193deca388013d21b893c56c
  Compiled from "SqlBlobSerializer.java"
public class com.fasterxml.jackson.databind.ext.SqlBlobSerializer extends com.fasterxml.jackson.databind.ser.std.StdScalarSerializer<java.sql.Blob>
  minor version: 0
  major version: 52
  flags: (0x0021) ACC_PUBLIC, ACC_SUPER
  this_class: #22                         // com/fasterxml/jackson/databind/ext/SqlBlobSerializer
  super_class: #23                        // com/fasterxml/jackson/databind/ser/std/StdScalarSerializer
  interfaces: 0, fields: 0, methods: 9, attributes: 3
Constant pool:
    #1 = Class              #81           // java/sql/Blob
    #2 = Methodref          #23.#82       // com/fasterxml/jackson/databind/ser/std/StdScalarSerializer."<init>":(Ljava/lang/Class;)V
    #3 = Methodref          #22.#83       // com/fasterxml/jackson/databind/ext/SqlBlobSerializer._writeValue:(Ljava/sql/Blob;Lcom/fasterxml/jackson/core/JsonGenerator;Lcom/fasterxml/jackson/databind/SerializerProvider;)V
    #4 = Fieldref           #84.#85       // com/fasterxml/jackson/core/JsonToken.VALUE_EMBEDDED_OBJECT:Lcom/fasterxml/jackson/core/JsonToken;
    #5 = Methodref          #86.#87       // com/fasterxml/jackson/databind/jsontype/TypeSerializer.typeId:(Ljava/lang/Object;Lcom/fasterxml/jackson/core/JsonToken;)Lcom/fasterxml/jackson/core/type/WritableTypeId;
    #6 = Methodref          #86.#88       // com/fasterxml/jackson/databind/jsontype/TypeSerializer.writeTypePrefix:(Lcom/fasterxml/jackson/core/JsonGenerator;Lcom/fasterxml/jackson/core/type/WritableTypeId;)Lcom/fasterxml/jackson/core/type/WritableTypeId;
    #7 = Methodref          #86.#89       // com/fasterxml/jackson/databind/jsontype/TypeSerializer.writeTypeSuffix:(Lcom/fasterxml/jackson/core/JsonGenerator;Lcom/fasterxml/jackson/core/type/WritableTypeId;)Lcom/fasterxml/jackson/core/type/WritableTypeId;
    #8 = InterfaceMethodref #1.#90        // java/sql/Blob.getBinaryStream:()Ljava/io/InputStream;
    #9 = Class              #91           // java/sql/SQLException
   #10 = String             #92           // Failed to access `java.sql.Blob` value to write as binary value
   #11 = Class              #93           // java/lang/Object
   #12 = Methodref          #94.#95       // com/fasterxml/jackson/databind/SerializerProvider.reportMappingProblem:(Ljava/lang/Throwable;Ljava/lang/String;[Ljava/lang/Object;)V
   #13 = Methodref          #94.#96       // com/fasterxml/jackson/databind/SerializerProvider.getConfig:()Lcom/fasterxml/jackson/databind/SerializationConfig;
   #14 = Methodref          #97.#98       // com/fasterxml/jackson/databind/SerializationConfig.getBase64Variant:()Lcom/fasterxml/jackson/core/Base64Variant;
   #15 = Methodref          #99.#100      // com/fasterxml/jackson/core/JsonGenerator.writeBinary:(Lcom/fasterxml/jackson/core/Base64Variant;Ljava/io/InputStream;I)I
   #16 = InterfaceMethodref #101.#102     // com/fasterxml/jackson/databind/jsonFormatVisitors/JsonFormatVisitorWrapper.expectArrayFormat:(Lcom/fasterxml/jackson/databind/JavaType;)Lcom/fasterxml/jackson/databind/jsonFormatVisitors/JsonArrayFormatVisitor;
   #17 = Fieldref           #103.#104     // com/fasterxml/jackson/databind/jsonFormatVisitors/JsonFormatTypes.INTEGER:Lcom/fasterxml/jackson/databind/jsonFormatVisitors/JsonFormatTypes;
   #18 = InterfaceMethodref #105.#106     // com/fasterxml/jackson/databind/jsonFormatVisitors/JsonArrayFormatVisitor.itemsFormat:(Lcom/fasterxml/jackson/databind/jsonFormatVisitors/JsonFormatTypes;)V
   #19 = Methodref          #22.#107      // com/fasterxml/jackson/databind/ext/SqlBlobSerializer.serializeWithType:(Ljava/sql/Blob;Lcom/fasterxml/jackson/core/JsonGenerator;Lcom/fasterxml/jackson/databind/SerializerProvider;Lcom/fasterxml/jackson/databind/jsontype/TypeSerializer;)V
   #20 = Methodref          #22.#108      // com/fasterxml/jackson/databind/ext/SqlBlobSerializer.serialize:(Ljava/sql/Blob;Lcom/fasterxml/jackson/core/JsonGenerator;Lcom/fasterxml/jackson/databind/SerializerProvider;)V
   #21 = Methodref          #22.#109      // com/fasterxml/jackson/databind/ext/SqlBlobSerializer.isEmpty:(Lcom/fasterxml/jackson/databind/SerializerProvider;Ljava/sql/Blob;)Z
   #22 = Class              #110          // com/fasterxml/jackson/databind/ext/SqlBlobSerializer
   #23 = Class              #111          // com/fasterxml/jackson/databind/ser/std/StdScalarSerializer
   #24 = Utf8               <init>
   #25 = Utf8               ()V
   #26 = Utf8               Code
   #27 = Utf8               LineNumberTable
   #28 = Utf8               LocalVariableTable
   #29 = Utf8               this
   #30 = Utf8               Lcom/fasterxml/jackson/databind/ext/SqlBlobSerializer;
   #31 = Utf8               isEmpty
   #32 = Utf8               (Lcom/fasterxml/jackson/databind/SerializerProvider;Ljava/sql/Blob;)Z
   #33 = Utf8               provider
   #34 = Utf8               Lcom/fasterxml/jackson/databind/SerializerProvider;
   #35 = Utf8               value
   #36 = Utf8               Ljava/sql/Blob;
   #37 = Utf8               StackMapTable
   #38 = Utf8               serialize
   #39 = Utf8               (Ljava/sql/Blob;Lcom/fasterxml/jackson/core/JsonGenerator;Lcom/fasterxml/jackson/databind/SerializerProvider;)V
   #40 = Utf8               gen
   #41 = Utf8               Lcom/fasterxml/jackson/core/JsonGenerator;
   #42 = Utf8               ctxt
   #43 = Utf8               Exceptions
   #44 = Class              #112          // java/io/IOException
   #45 = Utf8               serializeWithType
   #46 = Utf8               (Ljava/sql/Blob;Lcom/fasterxml/jackson/core/JsonGenerator;Lcom/fasterxml/jackson/databind/SerializerProvider;Lcom/fasterxml/jackson/databind/jsontype/TypeSerializer;)V
   #47 = Utf8               typeSer
   #48 = Utf8               Lcom/fasterxml/jackson/databind/jsontype/TypeSerializer;
   #49 = Utf8               typeIdDef
   #50 = Utf8               Lcom/fasterxml/jackson/core/type/WritableTypeId;
   #51 = Utf8               _writeValue
   #52 = Utf8               e
   #53 = Utf8               Ljava/sql/SQLException;
   #54 = Utf8               in
   #55 = Utf8               Ljava/io/InputStream;
   #56 = Class              #110          // com/fasterxml/jackson/databind/ext/SqlBlobSerializer
   #57 = Class              #81           // java/sql/Blob
   #58 = Class              #113          // com/fasterxml/jackson/core/JsonGenerator
   #59 = Class              #114          // com/fasterxml/jackson/databind/SerializerProvider
   #60 = Class              #115          // java/io/InputStream
   #61 = Class              #91           // java/sql/SQLException
   #62 = Utf8               acceptJsonFormatVisitor
   #63 = Utf8               (Lcom/fasterxml/jackson/databind/jsonFormatVisitors/JsonFormatVisitorWrapper;Lcom/fasterxml/jackson/databind/JavaType;)V
   #64 = Utf8               visitor
   #65 = Utf8               Lcom/fasterxml/jackson/databind/jsonFormatVisitors/JsonFormatVisitorWrapper;
   #66 = Utf8               typeHint
   #67 = Utf8               Lcom/fasterxml/jackson/databind/JavaType;
   #68 = Utf8               v2
   #69 = Utf8               Lcom/fasterxml/jackson/databind/jsonFormatVisitors/JsonArrayFormatVisitor;
   #70 = Class              #116          // com/fasterxml/jackson/databind/jsonFormatVisitors/JsonArrayFormatVisitor
   #71 = Class              #117          // com/fasterxml/jackson/databind/JsonMappingException
   #72 = Utf8               (Ljava/lang/Object;Lcom/fasterxml/jackson/core/JsonGenerator;Lcom/fasterxml/jackson/databind/SerializerProvider;Lcom/fasterxml/jackson/databind/jsontype/TypeSerializer;)V
   #73 = Utf8               (Ljava/lang/Object;Lcom/fasterxml/jackson/core/JsonGenerator;Lcom/fasterxml/jackson/databind/SerializerProvider;)V
   #74 = Utf8               (Lcom/fasterxml/jackson/databind/SerializerProvider;Ljava/lang/Object;)Z
   #75 = Utf8               Signature
   #76 = Utf8               Lcom/fasterxml/jackson/databind/ser/std/StdScalarSerializer<Ljava/sql/Blob;>;
   #77 = Utf8               SourceFile
   #78 = Utf8               SqlBlobSerializer.java
   #79 = Utf8               RuntimeVisibleAnnotations
   #80 = Utf8               Lcom/fasterxml/jackson/databind/annotation/JacksonStdImpl;
   #81 = Utf8               java/sql/Blob
   #82 = NameAndType        #24:#118      // "<init>":(Ljava/lang/Class;)V
   #83 = NameAndType        #51:#39       // _writeValue:(Ljava/sql/Blob;Lcom/fasterxml/jackson/core/JsonGenerator;Lcom/fasterxml/jackson/databind/SerializerProvider;)V
   #84 = Class              #119          // com/fasterxml/jackson/core/JsonToken
   #85 = NameAndType        #120:#121     // VALUE_EMBEDDED_OBJECT:Lcom/fasterxml/jackson/core/JsonToken;
   #86 = Class              #122          // com/fasterxml/jackson/databind/jsontype/TypeSerializer
   #87 = NameAndType        #123:#124     // typeId:(Ljava/lang/Object;Lcom/fasterxml/jackson/core/JsonToken;)Lcom/fasterxml/jackson/core/type/WritableTypeId;
   #88 = NameAndType        #125:#126     // writeTypePrefix:(Lcom/fasterxml/jackson/core/JsonGenerator;Lcom/fasterxml/jackson/core/type/WritableTypeId;)Lcom/fasterxml/jackson/core/type/WritableTypeId;
   #89 = NameAndType        #127:#126     // writeTypeSuffix:(Lcom/fasterxml/jackson/core/JsonGenerator;Lcom/fasterxml/jackson/core/type/WritableTypeId;)Lcom/fasterxml/jackson/core/type/WritableTypeId;
   #90 = NameAndType        #128:#129     // getBinaryStream:()Ljava/io/InputStream;
   #91 = Utf8               java/sql/SQLException
   #92 = Utf8               Failed to access `java.sql.Blob` value to write as binary value
   #93 = Utf8               java/lang/Object
   #94 = Class              #114          // com/fasterxml/jackson/databind/SerializerProvider
   #95 = NameAndType        #130:#131     // reportMappingProblem:(Ljava/lang/Throwable;Ljava/lang/String;[Ljava/lang/Object;)V
   #96 = NameAndType        #132:#133     // getConfig:()Lcom/fasterxml/jackson/databind/SerializationConfig;
   #97 = Class              #134          // com/fasterxml/jackson/databind/SerializationConfig
   #98 = NameAndType        #135:#136     // getBase64Variant:()Lcom/fasterxml/jackson/core/Base64Variant;
   #99 = Class              #113          // com/fasterxml/jackson/core/JsonGenerator
  #100 = NameAndType        #137:#138     // writeBinary:(Lcom/fasterxml/jackson/core/Base64Variant;Ljava/io/InputStream;I)I
  #101 = Class              #139          // com/fasterxml/jackson/databind/jsonFormatVisitors/JsonFormatVisitorWrapper
  #102 = NameAndType        #140:#141     // expectArrayFormat:(Lcom/fasterxml/jackson/databind/JavaType;)Lcom/fasterxml/jackson/databind/jsonFormatVisitors/JsonArrayFormatVisitor;
  #103 = Class              #142          // com/fasterxml/jackson/databind/jsonFormatVisitors/JsonFormatTypes
  #104 = NameAndType        #143:#144     // INTEGER:Lcom/fasterxml/jackson/databind/jsonFormatVisitors/JsonFormatTypes;
  #105 = Class              #116          // com/fasterxml/jackson/databind/jsonFormatVisitors/JsonArrayFormatVisitor
  #106 = NameAndType        #145:#146     // itemsFormat:(Lcom/fasterxml/jackson/databind/jsonFormatVisitors/JsonFormatTypes;)V
  #107 = NameAndType        #45:#46       // serializeWithType:(Ljava/sql/Blob;Lcom/fasterxml/jackson/core/JsonGenerator;Lcom/fasterxml/jackson/databind/SerializerProvider;Lcom/fasterxml/jackson/databind/jsontype/TypeSerializer;)V
  #108 = NameAndType        #38:#39       // serialize:(Ljava/sql/Blob;Lcom/fasterxml/jackson/core/JsonGenerator;Lcom/fasterxml/jackson/databind/SerializerProvider;)V
  #109 = NameAndType        #31:#32       // isEmpty:(Lcom/fasterxml/jackson/databind/SerializerProvider;Ljava/sql/Blob;)Z
  #110 = Utf8               com/fasterxml/jackson/databind/ext/SqlBlobSerializer
  #111 = Utf8               com/fasterxml/jackson/databind/ser/std/StdScalarSerializer
  #112 = Utf8               java/io/IOException
  #113 = Utf8               com/fasterxml/jackson/core/JsonGenerator
  #114 = Utf8               com/fasterxml/jackson/databind/SerializerProvider
  #115 = Utf8               java/io/InputStream
  #116 = Utf8               com/fasterxml/jackson/databind/jsonFormatVisitors/JsonArrayFormatVisitor
  #117 = Utf8               com/fasterxml/jackson/databind/JsonMappingException
  #118 = Utf8               (Ljava/lang/Class;)V
  #119 = Utf8               com/fasterxml/jackson/core/JsonToken
  #120 = Utf8               VALUE_EMBEDDED_OBJECT
  #121 = Utf8               Lcom/fasterxml/jackson/core/JsonToken;
  #122 = Utf8               com/fasterxml/jackson/databind/jsontype/TypeSerializer
  #123 = Utf8               typeId
  #124 = Utf8               (Ljava/lang/Object;Lcom/fasterxml/jackson/core/JsonToken;)Lcom/fasterxml/jackson/core/type/WritableTypeId;
  #125 = Utf8               writeTypePrefix
  #126 = Utf8               (Lcom/fasterxml/jackson/core/JsonGenerator;Lcom/fasterxml/jackson/core/type/WritableTypeId;)Lcom/fasterxml/jackson/core/type/WritableTypeId;
  #127 = Utf8               writeTypeSuffix
  #128 = Utf8               getBinaryStream
  #129 = Utf8               ()Ljava/io/InputStream;
  #130 = Utf8               reportMappingProblem
  #131 = Utf8               (Ljava/lang/Throwable;Ljava/lang/String;[Ljava/lang/Object;)V
  #132 = Utf8               getConfig
  #133 = Utf8               ()Lcom/fasterxml/jackson/databind/SerializationConfig;
  #134 = Utf8               com/fasterxml/jackson/databind/SerializationConfig
  #135 = Utf8               getBase64Variant
  #136 = Utf8               ()Lcom/fasterxml/jackson/core/Base64Variant;
  #137 = Utf8               writeBinary
  #138 = Utf8               (Lcom/fasterxml/jackson/core/Base64Variant;Ljava/io/InputStream;I)I
  #139 = Utf8               com/fasterxml/jackson/databind/jsonFormatVisitors/JsonFormatVisitorWrapper
  #140 = Utf8               expectArrayFormat
  #141 = Utf8               (Lcom/fasterxml/jackson/databind/JavaType;)Lcom/fasterxml/jackson/databind/jsonFormatVisitors/JsonArrayFormatVisitor;
  #142 = Utf8               com/fasterxml/jackson/databind/jsonFormatVisitors/JsonFormatTypes
  #143 = Utf8               INTEGER
  #144 = Utf8               Lcom/fasterxml/jackson/databind/jsonFormatVisitors/JsonFormatTypes;
  #145 = Utf8               itemsFormat
  #146 = Utf8               (Lcom/fasterxml/jackson/databind/jsonFormatVisitors/JsonFormatTypes;)V
{
  public com.fasterxml.jackson.databind.ext.SqlBlobSerializer();
    descriptor: ()V
    flags: (0x0001) ACC_PUBLIC
    Code:
      stack=2, locals=1, args_size=1
         0: aload_0
         1: ldc           #1                  // class java/sql/Blob
         3: invokespecial #2                  // Method com/fasterxml/jackson/databind/ser/std/StdScalarSerializer."<init>":(Ljava/lang/Class;)V
         6: return
      LineNumberTable:
        line 35: 0
        line 36: 6
      LocalVariableTable:
        Start  Length  Slot  Name   Signature
            0       7     0  this   Lcom/fasterxml/jackson/databind/ext/SqlBlobSerializer;

  public boolean isEmpty(com.fasterxml.jackson.databind.SerializerProvider, java.sql.Blob);
    descriptor: (Lcom/fasterxml/jackson/databind/SerializerProvider;Ljava/sql/Blob;)Z
    flags: (0x0001) ACC_PUBLIC
    Code:
      stack=1, locals=3, args_size=3
         0: aload_2
         1: ifnonnull     8
         4: iconst_1
         5: goto          9
         8: iconst_0
         9: ireturn
      LineNumberTable:
        line 41: 0
      LocalVariableTable:
        Start  Length  Slot  Name   Signature
            0      10     0  this   Lcom/fasterxml/jackson/databind/ext/SqlBlobSerializer;
            0      10     1 provider   Lcom/fasterxml/jackson/databind/SerializerProvider;
            0      10     2 value   Ljava/sql/Blob;
      StackMapTable: number_of_entries = 2
        frame_type = 8 /* same */
        frame_type = 64 /* same_locals_1_stack_item */
          stack = [ int ]

  public void serialize(java.sql.Blob, com.fasterxml.jackson.core.JsonGenerator, com.fasterxml.jackson.databind.SerializerProvider) throws java.io.IOException;
    descriptor: (Ljava/sql/Blob;Lcom/fasterxml/jackson/core/JsonGenerator;Lcom/fasterxml/jackson/databind/SerializerProvider;)V
    flags: (0x0001) ACC_PUBLIC
    Code:
      stack=4, locals=4, args_size=4
         0: aload_0
         1: aload_1
         2: aload_2
         3: aload_3
         4: invokevirtual #3                  // Method _writeValue:(Ljava/sql/Blob;Lcom/fasterxml/jackson/core/JsonGenerator;Lcom/fasterxml/jackson/databind/SerializerProvider;)V
         7: return
      LineNumberTable:
        line 47: 0
        line 48: 7
      LocalVariableTable:
        Start  Length  Slot  Name   Signature
            0       8     0  this   Lcom/fasterxml/jackson/databind/ext/SqlBlobSerializer;
            0       8     1 value   Ljava/sql/Blob;
            0       8     2   gen   Lcom/fasterxml/jackson/core/JsonGenerator;
            0       8     3  ctxt   Lcom/fasterxml/jackson/databind/SerializerProvider;
    Exceptions:
      throws java.io.IOException

  public void serializeWithType(java.sql.Blob, com.fasterxml.jackson.core.JsonGenerator, com.fasterxml.jackson.databind.SerializerProvider, com.fasterxml.jackson.databind.jsontype.TypeSerializer) throws java.io.IOException;
    descriptor: (Ljava/sql/Blob;Lcom/fasterxml/jackson/core/JsonGenerator;Lcom/fasterxml/jackson/databind/SerializerProvider;Lcom/fasterxml/jackson/databind/jsontype/TypeSerializer;)V
    flags: (0x0001) ACC_PUBLIC
    Code:
      stack=5, locals=6, args_size=5
         0: aload         4
         2: aload_2
         3: aload         4
         5: aload_1
         6: getstatic     #4                  // Field com/fasterxml/jackson/core/JsonToken.VALUE_EMBEDDED_OBJECT:Lcom/fasterxml/jackson/core/JsonToken;
         9: invokevirtual #5                  // Method com/fasterxml/jackson/databind/jsontype/TypeSerializer.typeId:(Ljava/lang/Object;Lcom/fasterxml/jackson/core/JsonToken;)Lcom/fasterxml/jackson/core/type/WritableTypeId;
        12: invokevirtual #6                  // Method com/fasterxml/jackson/databind/jsontype/TypeSerializer.writeTypePrefix:(Lcom/fasterxml/jackson/core/JsonGenerator;Lcom/fasterxml/jackson/core/type/WritableTypeId;)Lcom/fasterxml/jackson/core/type/WritableTypeId;
        15: astore        5
        17: aload_0
        18: aload_1
        19: aload_2
        20: aload_3
        21: invokevirtual #3                  // Method _writeValue:(Ljava/sql/Blob;Lcom/fasterxml/jackson/core/JsonGenerator;Lcom/fasterxml/jackson/databind/SerializerProvider;)V
        24: aload         4
        26: aload_2
        27: aload         5
        29: invokevirtual #7                  // Method com/fasterxml/jackson/databind/jsontype/TypeSerializer.writeTypeSuffix:(Lcom/fasterxml/jackson/core/JsonGenerator;Lcom/fasterxml/jackson/core/type/WritableTypeId;)Lcom/fasterxml/jackson/core/type/WritableTypeId;
        32: pop
        33: return
      LineNumberTable:
        line 57: 0
        line 58: 9
        line 57: 12
        line 59: 17
        line 60: 24
        line 61: 33
      LocalVariableTable:
        Start  Length  Slot  Name   Signature
            0      34     0  this   Lcom/fasterxml/jackson/databind/ext/SqlBlobSerializer;
            0      34     1 value   Ljava/sql/Blob;
            0      34     2   gen   Lcom/fasterxml/jackson/core/JsonGenerator;
            0      34     3  ctxt   Lcom/fasterxml/jackson/databind/SerializerProvider;
            0      34     4 typeSer   Lcom/fasterxml/jackson/databind/jsontype/TypeSerializer;
           17      17     5 typeIdDef   Lcom/fasterxml/jackson/core/type/WritableTypeId;
    Exceptions:
      throws java.io.IOException

  protected void _writeValue(java.sql.Blob, com.fasterxml.jackson.core.JsonGenerator, com.fasterxml.jackson.databind.SerializerProvider) throws java.io.IOException;
    descriptor: (Ljava/sql/Blob;Lcom/fasterxml/jackson/core/JsonGenerator;Lcom/fasterxml/jackson/databind/SerializerProvider;)V
    flags: (0x0004) ACC_PROTECTED
    Code:
      stack=4, locals=6, args_size=4
         0: aconst_null
         1: astore        4
         3: aload_1
         4: invokeinterface #8,  1            // InterfaceMethod java/sql/Blob.getBinaryStream:()Ljava/io/InputStream;
         9: astore        4
        11: goto          28
        14: astore        5
        16: aload_3
        17: aload         5
        19: ldc           #10                 // String Failed to access `java.sql.Blob` value to write as binary value
        21: iconst_0
        22: anewarray     #11                 // class java/lang/Object
        25: invokevirtual #12                 // Method com/fasterxml/jackson/databind/SerializerProvider.reportMappingProblem:(Ljava/lang/Throwable;Ljava/lang/String;[Ljava/lang/Object;)V
        28: aload_2
        29: aload_3
        30: invokevirtual #13                 // Method com/fasterxml/jackson/databind/SerializerProvider.getConfig:()Lcom/fasterxml/jackson/databind/SerializationConfig;
        33: invokevirtual #14                 // Method com/fasterxml/jackson/databind/SerializationConfig.getBase64Variant:()Lcom/fasterxml/jackson/core/Base64Variant;
        36: aload         4
        38: iconst_m1
        39: invokevirtual #15                 // Method com/fasterxml/jackson/core/JsonGenerator.writeBinary:(Lcom/fasterxml/jackson/core/Base64Variant;Ljava/io/InputStream;I)I
        42: pop
        43: return
      Exception table:
         from    to  target type
             3    11    14   Class java/sql/SQLException
      LineNumberTable:
        line 66: 0
        line 68: 3
        line 72: 11
        line 69: 14
        line 70: 16
        line 73: 28
        line 74: 43
      LocalVariableTable:
        Start  Length  Slot  Name   Signature
           16      12     5     e   Ljava/sql/SQLException;
            0      44     0  this   Lcom/fasterxml/jackson/databind/ext/SqlBlobSerializer;
            0      44     1 value   Ljava/sql/Blob;
            0      44     2   gen   Lcom/fasterxml/jackson/core/JsonGenerator;
            0      44     3  ctxt   Lcom/fasterxml/jackson/databind/SerializerProvider;
            3      41     4    in   Ljava/io/InputStream;
      StackMapTable: number_of_entries = 2
        frame_type = 255 /* full_frame */
          offset_delta = 14
          locals = [ class com/fasterxml/jackson/databind/ext/SqlBlobSerializer, class java/sql/Blob, class com/fasterxml/jackson/core/JsonGenerator, class com/fasterxml/jackson/databind/SerializerProvider, class java/io/InputStream ]
          stack = [ class java/sql/SQLException ]
        frame_type = 13 /* same */
    Exceptions:
      throws java.io.IOException

  public void acceptJsonFormatVisitor(com.fasterxml.jackson.databind.jsonFormatVisitors.JsonFormatVisitorWrapper, com.fasterxml.jackson.databind.JavaType) throws com.fasterxml.jackson.databind.JsonMappingException;
    descriptor: (Lcom/fasterxml/jackson/databind/jsonFormatVisitors/JsonFormatVisitorWrapper;Lcom/fasterxml/jackson/databind/JavaType;)V
    flags: (0x0001) ACC_PUBLIC
    Code:
      stack=2, locals=4, args_size=3
         0: aload_1
         1: aload_2
         2: invokeinterface #16,  2           // InterfaceMethod com/fasterxml/jackson/databind/jsonFormatVisitors/JsonFormatVisitorWrapper.expectArrayFormat:(Lcom/fasterxml/jackson/databind/JavaType;)Lcom/fasterxml/jackson/databind/jsonFormatVisitors/JsonArrayFormatVisitor;
         7: astore_3
         8: aload_3
         9: ifnull        21
        12: aload_3
        13: getstatic     #17                 // Field com/fasterxml/jackson/databind/jsonFormatVisitors/JsonFormatTypes.INTEGER:Lcom/fasterxml/jackson/databind/jsonFormatVisitors/JsonFormatTypes;
        16: invokeinterface #18,  2           // InterfaceMethod com/fasterxml/jackson/databind/jsonFormatVisitors/JsonArrayFormatVisitor.itemsFormat:(Lcom/fasterxml/jackson/databind/jsonFormatVisitors/JsonFormatTypes;)V
        21: return
      LineNumberTable:
        line 84: 0
        line 85: 8
        line 86: 12
        line 88: 21
      LocalVariableTable:
        Start  Length  Slot  Name   Signature
            0      22     0  this   Lcom/fasterxml/jackson/databind/ext/SqlBlobSerializer;
            0      22     1 visitor   Lcom/fasterxml/jackson/databind/jsonFormatVisitors/JsonFormatVisitorWrapper;
            0      22     2 typeHint   Lcom/fasterxml/jackson/databind/JavaType;
            8      14     3    v2   Lcom/fasterxml/jackson/databind/jsonFormatVisitors/JsonArrayFormatVisitor;
      StackMapTable: number_of_entries = 1
        frame_type = 252 /* append */
          offset_delta = 21
          locals = [ class com/fasterxml/jackson/databind/jsonFormatVisitors/JsonArrayFormatVisitor ]
    Exceptions:
      throws com.fasterxml.jackson.databind.JsonMappingException

  public void serializeWithType(java.lang.Object, com.fasterxml.jackson.core.JsonGenerator, com.fasterxml.jackson.databind.SerializerProvider, com.fasterxml.jackson.databind.jsontype.TypeSerializer) throws java.io.IOException;
    descriptor: (Ljava/lang/Object;Lcom/fasterxml/jackson/core/JsonGenerator;Lcom/fasterxml/jackson/databind/SerializerProvider;Lcom/fasterxml/jackson/databind/jsontype/TypeSerializer;)V
    flags: (0x1041) ACC_PUBLIC, ACC_BRIDGE, ACC_SYNTHETIC
    Code:
      stack=5, locals=5, args_size=5
         0: aload_0
         1: aload_1
         2: checkcast     #1                  // class java/sql/Blob
         5: aload_2
         6: aload_3
         7: aload         4
         9: invokevirtual #19                 // Method serializeWithType:(Ljava/sql/Blob;Lcom/fasterxml/jackson/core/JsonGenerator;Lcom/fasterxml/jackson/databind/SerializerProvider;Lcom/fasterxml/jackson/databind/jsontype/TypeSerializer;)V
        12: return
      LineNumberTable:
        line 29: 0
      LocalVariableTable:
        Start  Length  Slot  Name   Signature
            0      13     0  this   Lcom/fasterxml/jackson/databind/ext/SqlBlobSerializer;
    Exceptions:
      throws java.io.IOException

  public void serialize(java.lang.Object, com.fasterxml.jackson.core.JsonGenerator, com.fasterxml.jackson.databind.SerializerProvider) throws java.io.IOException;
    descriptor: (Ljava/lang/Object;Lcom/fasterxml/jackson/core/JsonGenerator;Lcom/fasterxml/jackson/databind/SerializerProvider;)V
    flags: (0x1041) ACC_PUBLIC, ACC_BRIDGE, ACC_SYNTHETIC
    Code:
      stack=4, locals=4, args_size=4
         0: aload_0
         1: aload_1
         2: checkcast     #1                  // class java/sql/Blob
         5: aload_2
         6: aload_3
         7: invokevirtual #20                 // Method serialize:(Ljava/sql/Blob;Lcom/fasterxml/jackson/core/JsonGenerator;Lcom/fasterxml/jackson/databind/SerializerProvider;)V
        10: return
      LineNumberTable:
        line 29: 0
      LocalVariableTable:
        Start  Length  Slot  Name   Signature
            0      11     0  this   Lcom/fasterxml/jackson/databind/ext/SqlBlobSerializer;
    Exceptions:
      throws java.io.IOException

  public boolean isEmpty(com.fasterxml.jackson.databind.SerializerProvider, java.lang.Object);
    descriptor: (Lcom/fasterxml/jackson/databind/SerializerProvider;Ljava/lang/Object;)Z
    flags: (0x1041) ACC_PUBLIC, ACC_BRIDGE, ACC_SYNTHETIC
    Code:
      stack=3, locals=3, args_size=3
         0: aload_0
         1: aload_1
         2: aload_2
         3: checkcast     #1                  // class java/sql/Blob
         6: invokevirtual #21                 // Method isEmpty:(Lcom/fasterxml/jackson/databind/SerializerProvider;Ljava/sql/Blob;)Z
         9: ireturn
      LineNumberTable:
        line 29: 0
      LocalVariableTable:
        Start  Length  Slot  Name   Signature
            0      10     0  this   Lcom/fasterxml/jackson/databind/ext/SqlBlobSerializer;
}
Signature: #76                          // Lcom/fasterxml/jackson/databind/ser/std/StdScalarSerializer<Ljava/sql/Blob;>;
SourceFile: "SqlBlobSerializer.java"
RuntimeVisibleAnnotations:
  0: #80()
    com.fasterxml.jackson.databind.annotation.JacksonStdImpl
