Classfile /Users/mw/Projects/slang-braindump/.jar/jar8/assemble/slang-braindump/assemble/content/scala/sys/PropImpl.class
  Last modified May 29, 2022; size 5793 bytes
  SHA-256 checksum 057b722ac541ca8b84cbf5611e7713dfac78723aaf9bb3697239f851760bb000
  Compiled from "PropImpl.scala"
public class scala.sys.PropImpl<T extends java.lang.Object> extends java.lang.Object implements scala.sys.Prop<T>
  minor version: 0
  major version: 52
  flags: (0x0021) ACC_PUBLIC, ACC_SUPER
  this_class: #2                          // scala/sys/PropImpl
  super_class: #5                         // java/lang/Object
  interfaces: 1, fields: 2, methods: 16, attributes: 7
Constant pool:
    #1 = Utf8               scala/sys/PropImpl
    #2 = Class              #1            // scala/sys/PropImpl
    #3 = Utf8               <T:Ljava/lang/Object;>Ljava/lang/Object;Lscala/sys/Prop<TT;>;
    #4 = Utf8               java/lang/Object
    #5 = Class              #4            // java/lang/Object
    #6 = Utf8               scala/sys/Prop
    #7 = Class              #6            // scala/sys/Prop
    #8 = Utf8               PropImpl.scala
    #9 = Utf8               Lscala/reflect/ScalaSignature;
   #10 = Utf8               bytes
   #11 = Utf8               \u0006\u0005\u0005\ra!B\t\u0013\u0001I1\u0002\u0002\u0003\u0017\u0001\u0005\u000b\u0007I\u0011A\u0017\t\u0011e\u0002!\u0011!Q\u0001\n9B\u0001B\u000f\u0001\u0003\u0002\u0003\u0006Ia\u000f\u0005\u0006}\u0001!\ta\u0010\u0005\u0006\u0007\u0002!\t\u0001\u0012\u0005\u0006\u000b\u0002!\tA\u0012\u0005\u0006\u0015\u0002!\ta\u0013\u0005\u0006\u001d\u0002!\ta\u0014\u0005\u0006-\u0002!\t!\f\u0005\u0006/\u0002!\t\u0001\u0017\u0005\u00069\u0002!\t!\u0018\u0005\u0006C\u0002!\tA\u0019\u0005\u0006W\u0002!\t\u0002\u001c\u0005\u0006k\u0002!\t\u0002\u0012\u0005\u0006m\u0002!Ia\u001e\u0005\u0007\u007f\u0002!\t%!\u0001\u0003\u0011A\u0013x\u000e]%na2T!a\u0005\u000b\u0002\u0007ML8OC\u0001\u0016\u0003\u0015\u00198-\u00197b+\t9\"eE\u0002\u00011q\u0001\"!\u0007\u000e\u000e\u0003QI!a\u0007\u000b\u0003\r\u0005s\u0017PU3g!\rib\u0004I\u0007\u0002%%\u0011qD\u0005\u0002\u0005!J|\u0007\u000f\u0005\u0002\"E1\u0001AAB\u0012\u0001\t\u000b\u0007QEA\u0001U\u0007\u0001\t\"AJ\u0015\u0011\u0005e9\u0013B\u0001\u0015\u0015\u0005\u001dqu\u000e\u001e5j]\u001e\u0004\"!\u0007\u0016\n\u0005-\"\"aA!os\u0006\u00191.Z=\u0016\u00039\u0002\"a\f\u001c\u000f\u0005A\"\u0004CA\u0019\u0015\u001b\u0005\u0011$BA\u001a%\u0003\u0019a$o\\8u}%\u0011Q\u0007F\u0001\u0007!J,G-\u001a4\n\u0005]B$AB*ue&twM\u0003\u00026)\u0005!1.Z=!\u0003\u001d1\u0018\r\\;f\r:\u0004B!\u0007\u001f/A%\u0011Q\b\u0006\u0002\n\rVt7\r^5p]F\na\u0001P5oSRtDc\u0001!B\u0005B\u0019Q\u0004\u0001\u0011\t\u000b1\"\u0001\u0019\u0001\u0018\t\u000bi\"\u0001\u0019A\u001e\u0002\u000bY\fG.^3\u0016\u0003\u0001\nQ![:TKR,\u0012a\u0012\t\u00033!K!!\u0013\u000b\u0003\u000f\t{w\u000e\\3b]\u0006\u00191/\u001a;\u0015\u00059b\u0005\"B\'\b\u0001\u0004q\u0013\u0001\u00038foZ\u000bG.^3\u0002\u0011M,GOV1mk\u0016,\"\u0001U*\u0015\u0005\u0001\n\u0006\"B\'\t\u0001\u0004\u0011\u0006CA\u0011T\t\u0015!\u0006B1\u0001V\u0005\t!\u0016\'\u0005\u0002!S\u0005\u0019q-\u001a;\u0002\u000b\rdW-\u0019:\u0015\u0003e\u0003\"!\u0007.\n\u0005m#\"\u0001B+oSR\faa\u001c9uS>tW#\u00010\u0011\u0007ey\u0006%\u0003\u0002a)\t1q\n\u001d;j_:\f!a\u001c:\u0016\u0005\r,GC\u00013g!\t\tS\rB\u0003U\u0019\t\u0007Q\u000b\u0003\u0004h\u0019\u0011\u0005\r\u0001[\u0001\u0004C2$\bcA\rjI&\u0011!\u000e\u0006\u0002\ty\tLh.Y7f}\u0005QQO\u001c3fe2L\u0018N\\4\u0016\u00035\u0004BA\\:/]5\tqN\u0003\u0002qc\u00069Q.\u001e;bE2,\'B\u0001:\u0015\u0003)\u0019w\u000e\u001c7fGRLwN\\\u0005\u0003i>\u00141!T1q\u0003\u0011QXM]8\u0002\u0013\u001d,Go\u0015;sS:<W#\u0001=\u0011\u0005etX\"\u0001>\u000b\u0005md\u0018\u0001\u00027b]\u001eT\u0011!`\u0001\u0005U\u00064\u0018-\u0003\u00028u\u0006AAo\\*ue&tw\rF\u0001/\u0001
   #12 = Utf8               java/lang/invoke/MethodHandles$Lookup
   #13 = Class              #12           // java/lang/invoke/MethodHandles$Lookup
   #14 = Utf8               java/lang/invoke/MethodHandles
   #15 = Class              #14           // java/lang/invoke/MethodHandles
   #16 = Utf8               Lookup
   #17 = Utf8               key
   #18 = Utf8               Ljava/lang/String;
   #19 = Utf8               valueFn
   #20 = Utf8               Lscala/Function1;
   #21 = Utf8               Lscala/Function1<Ljava/lang/String;TT;>;
   #22 = Utf8               ()Ljava/lang/String;
   #23 = NameAndType        #17:#18       // key:Ljava/lang/String;
   #24 = Fieldref           #2.#23        // scala/sys/PropImpl.key:Ljava/lang/String;
   #25 = Utf8               this
   #26 = Utf8               Lscala/sys/PropImpl;
   #27 = Utf8               value
   #28 = Utf8               ()Ljava/lang/Object;
   #29 = Utf8               ()TT;
   #30 = Utf8               isSet
   #31 = Utf8               ()Z
   #32 = NameAndType        #30:#31       // isSet:()Z
   #33 = Methodref          #2.#32        // scala/sys/PropImpl.isSet:()Z
   #34 = NameAndType        #19:#20       // valueFn:Lscala/Function1;
   #35 = Fieldref           #2.#34        // scala/sys/PropImpl.valueFn:Lscala/Function1;
   #36 = Utf8               get
   #37 = NameAndType        #36:#22       // get:()Ljava/lang/String;
   #38 = Methodref          #2.#37        // scala/sys/PropImpl.get:()Ljava/lang/String;
   #39 = Utf8               scala/Function1
   #40 = Class              #39           // scala/Function1
   #41 = Utf8               apply
   #42 = Utf8               (Ljava/lang/Object;)Ljava/lang/Object;
   #43 = NameAndType        #41:#42       // apply:(Ljava/lang/Object;)Ljava/lang/Object;
   #44 = InterfaceMethodref #40.#43       // scala/Function1.apply:(Ljava/lang/Object;)Ljava/lang/Object;
   #45 = Utf8               zero
   #46 = NameAndType        #45:#28       // zero:()Ljava/lang/Object;
   #47 = Methodref          #2.#46        // scala/sys/PropImpl.zero:()Ljava/lang/Object;
   #48 = Utf8               underlying
   #49 = Utf8               ()Lscala/collection/mutable/Map;
   #50 = NameAndType        #48:#49       // underlying:()Lscala/collection/mutable/Map;
   #51 = Methodref          #2.#50        // scala/sys/PropImpl.underlying:()Lscala/collection/mutable/Map;
   #52 = NameAndType        #17:#22       // key:()Ljava/lang/String;
   #53 = Methodref          #2.#52        // scala/sys/PropImpl.key:()Ljava/lang/String;
   #54 = Utf8               scala/collection/mutable/Map
   #55 = Class              #54           // scala/collection/mutable/Map
   #56 = Utf8               contains
   #57 = Utf8               (Ljava/lang/Object;)Z
   #58 = NameAndType        #56:#57       // contains:(Ljava/lang/Object;)Z
   #59 = InterfaceMethodref #55.#58       // scala/collection/mutable/Map.contains:(Ljava/lang/Object;)Z
   #60 = Utf8               set
   #61 = Utf8               (Ljava/lang/String;)Ljava/lang/String;
   #62 = Utf8               newValue
   #63 = Utf8               update
   #64 = Utf8               (Ljava/lang/Object;Ljava/lang/Object;)V
   #65 = NameAndType        #63:#64       // update:(Ljava/lang/Object;Ljava/lang/Object;)V
   #66 = InterfaceMethodref #55.#65       // scala/collection/mutable/Map.update:(Ljava/lang/Object;Ljava/lang/Object;)V
   #67 = Utf8               old
   #68 = Utf8               java/lang/String
   #69 = Class              #68           // java/lang/String
   #70 = Utf8               setValue
   #71 = Utf8               <T1:Ljava/lang/Object;>(TT1;)TT;
   #72 = NameAndType        #27:#28       // value:()Ljava/lang/Object;
   #73 = Methodref          #2.#72        // scala/sys/PropImpl.value:()Ljava/lang/Object;
   #74 = NameAndType        #60:#61       // set:(Ljava/lang/String;)Ljava/lang/String;
   #75 = Methodref          #2.#74        // scala/sys/PropImpl.set:(Ljava/lang/String;)Ljava/lang/String;
   #76 = Utf8               valueOf
   #77 = Utf8               (Ljava/lang/Object;)Ljava/lang/String;
   #78 = NameAndType        #76:#77       // valueOf:(Ljava/lang/Object;)Ljava/lang/String;
   #79 = Methodref          #69.#78       // java/lang/String.valueOf:(Ljava/lang/Object;)Ljava/lang/String;
   #80 = Utf8               Ljava/lang/Object;
   #81 = MethodType         #28           //  ()Ljava/lang/Object;
   #82 = Utf8               $anonfun$get$1
   #83 = NameAndType        #82:#22       // $anonfun$get$1:()Ljava/lang/String;
   #84 = Methodref          #2.#83        // scala/sys/PropImpl.$anonfun$get$1:()Ljava/lang/String;
   #85 = MethodHandle       6:#84         // REF_invokeStatic scala/sys/PropImpl.$anonfun$get$1:()Ljava/lang/String;
   #86 = MethodType         #22           //  ()Ljava/lang/String;
   #87 = Integer            5
   #88 = Integer            1
   #89 = Utf8               java/lang/invoke/LambdaMetafactory
   #90 = Class              #89           // java/lang/invoke/LambdaMetafactory
   #91 = Utf8               altMetafactory
   #92 = Utf8               (Ljava/lang/invoke/MethodHandles$Lookup;Ljava/lang/String;Ljava/lang/invoke/MethodType;[Ljava/lang/Object;)Ljava/lang/invoke/CallSite;
   #93 = NameAndType        #91:#92       // altMetafactory:(Ljava/lang/invoke/MethodHandles$Lookup;Ljava/lang/String;Ljava/lang/invoke/MethodType;[Ljava/lang/Object;)Ljava/lang/invoke/CallSite;
   #94 = Methodref          #90.#93       // java/lang/invoke/LambdaMetafactory.altMetafactory:(Ljava/lang/invoke/MethodHandles$Lookup;Ljava/lang/String;Ljava/lang/invoke/MethodType;[Ljava/lang/Object;)Ljava/lang/invoke/CallSite;
   #95 = MethodHandle       6:#94         // REF_invokeStatic java/lang/invoke/LambdaMetafactory.altMetafactory:(Ljava/lang/invoke/MethodHandles$Lookup;Ljava/lang/String;Ljava/lang/invoke/MethodType;[Ljava/lang/Object;)Ljava/lang/invoke/CallSite;
   #96 = Utf8               ()Lscala/Function0;
   #97 = NameAndType        #41:#96       // apply:()Lscala/Function0;
   #98 = InvokeDynamic      #0:#97        // #0:apply:()Lscala/Function0;
   #99 = Utf8               getOrElse
  #100 = Utf8               (Ljava/lang/Object;Lscala/Function0;)Ljava/lang/Object;
  #101 = NameAndType        #99:#100      // getOrElse:(Ljava/lang/Object;Lscala/Function0;)Ljava/lang/Object;
  #102 = InterfaceMethodref #55.#101      // scala/collection/mutable/Map.getOrElse:(Ljava/lang/Object;Lscala/Function0;)Ljava/lang/Object;
  #103 = Utf8
  #104 = String             #103          //
  #105 = Utf8               clear
  #106 = Utf8               ()V
  #107 = Utf8               scala/collection/mutable/Shrinkable
  #108 = Class              #107          // scala/collection/mutable/Shrinkable
  #109 = Utf8               subtractOne
  #110 = Utf8               (Ljava/lang/Object;)Lscala/collection/mutable/Shrinkable;
  #111 = NameAndType        #109:#110     // subtractOne:(Ljava/lang/Object;)Lscala/collection/mutable/Shrinkable;
  #112 = InterfaceMethodref #108.#111     // scala/collection/mutable/Shrinkable.subtractOne:(Ljava/lang/Object;)Lscala/collection/mutable/Shrinkable;
  #113 = Utf8               $minus$eq_elem
  #114 = Utf8               option
  #115 = Utf8               ()Lscala/Option;
  #116 = Utf8               ()Lscala/Option<TT;>;
  #117 = Utf8               scala/Some
  #118 = Class              #117          // scala/Some
  #119 = Utf8               <init>
  #120 = Utf8               (Ljava/lang/Object;)V
  #121 = NameAndType        #119:#120     // "<init>":(Ljava/lang/Object;)V
  #122 = Methodref          #118.#121     // scala/Some."<init>":(Ljava/lang/Object;)V
  #123 = Utf8               scala/None$
  #124 = Class              #123          // scala/None$
  #125 = Utf8               MODULE$
  #126 = Utf8               Lscala/None$;
  #127 = NameAndType        #125:#126     // MODULE$:Lscala/None$;
  #128 = Fieldref           #124.#127     // scala/None$.MODULE$:Lscala/None$;
  #129 = Utf8               or
  #130 = Utf8               (Lscala/Function0;)Ljava/lang/Object;
  #131 = Utf8               <T1:Ljava/lang/Object;>(Lscala/Function0<TT1;>;)TT1;
  #132 = Utf8               alt
  #133 = Utf8               scala/Function0
  #134 = Class              #133          // scala/Function0
  #135 = NameAndType        #41:#28       // apply:()Ljava/lang/Object;
  #136 = InterfaceMethodref #134.#135     // scala/Function0.apply:()Ljava/lang/Object;
  #137 = Utf8               Lscala/Function0;
  #138 = Utf8               ()Lscala/collection/mutable/Map<Ljava/lang/String;Ljava/lang/String;>;
  #139 = Utf8               scala/sys/package$
  #140 = Class              #139          // scala/sys/package$
  #141 = Utf8               Lscala/sys/package$;
  #142 = NameAndType        #125:#141     // MODULE$:Lscala/sys/package$;
  #143 = Fieldref           #140.#142     // scala/sys/package$.MODULE$:Lscala/sys/package$;
  #144 = Utf8               scala/sys/SystemProperties
  #145 = Class              #144          // scala/sys/SystemProperties
  #146 = NameAndType        #119:#106     // "<init>":()V
  #147 = Methodref          #145.#146     // scala/sys/SystemProperties."<init>":()V
  #148 = Utf8               getString
  #149 = Utf8               java/lang/StringBuilder
  #150 = Class              #149          // java/lang/StringBuilder
  #151 = Integer            11
  #152 = Utf8               (I)V
  #153 = NameAndType        #119:#152     // "<init>":(I)V
  #154 = Methodref          #150.#153     // java/lang/StringBuilder."<init>":(I)V
  #155 = Utf8               currently:
  #156 = String             #155          // currently:
  #157 = Utf8               append
  #158 = Utf8               (Ljava/lang/String;)Ljava/lang/StringBuilder;
  #159 = NameAndType        #157:#158     // append:(Ljava/lang/String;)Ljava/lang/StringBuilder;
  #160 = Methodref          #150.#159     // java/lang/StringBuilder.append:(Ljava/lang/String;)Ljava/lang/StringBuilder;
  #161 = Utf8               toString
  #162 = NameAndType        #161:#22      // toString:()Ljava/lang/String;
  #163 = Methodref          #150.#162     // java/lang/StringBuilder.toString:()Ljava/lang/String;
  #164 = Utf8               unset
  #165 = String             #164          // unset
  #166 = Utf8               scala/collection/StringOps$
  #167 = Class              #166          // scala/collection/StringOps$
  #168 = Utf8               Lscala/collection/StringOps$;
  #169 = NameAndType        #125:#168     // MODULE$:Lscala/collection/StringOps$;
  #170 = Fieldref           #167.#169     // scala/collection/StringOps$.MODULE$:Lscala/collection/StringOps$;
  #171 = Utf8               %s (%s)
  #172 = String             #171          // %s (%s)
  #173 = Utf8               scala/runtime/ScalaRunTime$
  #174 = Class              #173          // scala/runtime/ScalaRunTime$
  #175 = Utf8               Lscala/runtime/ScalaRunTime$;
  #176 = NameAndType        #125:#175     // MODULE$:Lscala/runtime/ScalaRunTime$;
  #177 = Fieldref           #174.#176     // scala/runtime/ScalaRunTime$.MODULE$:Lscala/runtime/ScalaRunTime$;
  #178 = NameAndType        #148:#22      // getString:()Ljava/lang/String;
  #179 = Methodref          #2.#178       // scala/sys/PropImpl.getString:()Ljava/lang/String;
  #180 = Utf8               genericWrapArray
  #181 = Utf8               (Ljava/lang/Object;)Lscala/collection/immutable/ArraySeq;
  #182 = NameAndType        #180:#181     // genericWrapArray:(Ljava/lang/Object;)Lscala/collection/immutable/ArraySeq;
  #183 = Methodref          #174.#182     // scala/runtime/ScalaRunTime$.genericWrapArray:(Ljava/lang/Object;)Lscala/collection/immutable/ArraySeq;
  #184 = Utf8               format$extension
  #185 = Utf8               (Ljava/lang/String;Lscala/collection/immutable/Seq;)Ljava/lang/String;
  #186 = NameAndType        #184:#185     // format$extension:(Ljava/lang/String;Lscala/collection/immutable/Seq;)Ljava/lang/String;
  #187 = Methodref          #167.#186     // scala/collection/StringOps$.format$extension:(Ljava/lang/String;Lscala/collection/immutable/Seq;)Ljava/lang/String;
  #188 = Utf8               (Ljava/lang/String;Lscala/Function1;)V
  #189 = Utf8               (Ljava/lang/String;Lscala/Function1<Ljava/lang/String;TT;>;)V
  #190 = Methodref          #5.#146       // java/lang/Object."<init>":()V
  #191 = Utf8               $deserializeLambda$
  #192 = Utf8               (Ljava/lang/invoke/SerializedLambda;)Ljava/lang/Object;
  #193 = Utf8               scala/runtime/LambdaDeserialize
  #194 = Class              #193          // scala/runtime/LambdaDeserialize
  #195 = Utf8               bootstrap
  #196 = Utf8               (Ljava/lang/invoke/MethodHandles$Lookup;Ljava/lang/String;Ljava/lang/invoke/MethodType;[Ljava/lang/invoke/MethodHandle;)Ljava/lang/invoke/CallSite;
  #197 = NameAndType        #195:#196     // bootstrap:(Ljava/lang/invoke/MethodHandles$Lookup;Ljava/lang/String;Ljava/lang/invoke/MethodType;[Ljava/lang/invoke/MethodHandle;)Ljava/lang/invoke/CallSite;
  #198 = Methodref          #194.#197     // scala/runtime/LambdaDeserialize.bootstrap:(Ljava/lang/invoke/MethodHandles$Lookup;Ljava/lang/String;Ljava/lang/invoke/MethodType;[Ljava/lang/invoke/MethodHandle;)Ljava/lang/invoke/CallSite;
  #199 = MethodHandle       6:#198        // REF_invokeStatic scala/runtime/LambdaDeserialize.bootstrap:(Ljava/lang/invoke/MethodHandles$Lookup;Ljava/lang/String;Ljava/lang/invoke/MethodType;[Ljava/lang/invoke/MethodHandle;)Ljava/lang/invoke/CallSite;
  #200 = Utf8               lambdaDeserialize
  #201 = NameAndType        #200:#192     // lambdaDeserialize:(Ljava/lang/invoke/SerializedLambda;)Ljava/lang/Object;
  #202 = InvokeDynamic      #1:#201       // #1:lambdaDeserialize:(Ljava/lang/invoke/SerializedLambda;)Ljava/lang/Object;
  #203 = Utf8               Signature
  #204 = Utf8               Code
  #205 = Utf8               LineNumberTable
  #206 = Utf8               LocalVariableTable
  #207 = Utf8               StackMapTable
  #208 = Utf8               MethodParameters
  #209 = Utf8               InnerClasses
  #210 = Utf8               SourceFile
  #211 = Utf8               RuntimeVisibleAnnotations
  #212 = Utf8               BootstrapMethods
  #213 = Utf8               ScalaInlineInfo
  #214 = Utf8               ScalaSig
{
  private final java.lang.String key;
    descriptor: Ljava/lang/String;
    flags: (0x0012) ACC_PRIVATE, ACC_FINAL

  private final scala.Function1<java.lang.String, T> valueFn;
    descriptor: Lscala/Function1;
    flags: (0x0012) ACC_PRIVATE, ACC_FINAL
    Signature: #21                          // Lscala/Function1<Ljava/lang/String;TT;>;

  public java.lang.String key();
    descriptor: ()Ljava/lang/String;
    flags: (0x0001) ACC_PUBLIC
    Code:
      stack=1, locals=1, args_size=1
         0: aload_0
         1: getfield      #24                 // Field key:Ljava/lang/String;
         4: areturn
      LineNumberTable:
        line 20: 0
      LocalVariableTable:
        Start  Length  Slot  Name   Signature
            0       5     0  this   Lscala/sys/PropImpl;

  public T value();
    descriptor: ()Ljava/lang/Object;
    flags: (0x0001) ACC_PUBLIC
    Code:
      stack=2, locals=1, args_size=1
         0: aload_0
         1: invokevirtual #33                 // Method isSet:()Z
         4: ifeq          21
         7: aload_0
         8: getfield      #35                 // Field valueFn:Lscala/Function1;
        11: aload_0
        12: invokevirtual #38                 // Method get:()Ljava/lang/String;
        15: invokeinterface #44,  2           // InterfaceMethod scala/Function1.apply:(Ljava/lang/Object;)Ljava/lang/Object;
        20: areturn
        21: aload_0
        22: invokevirtual #47                 // Method zero:()Ljava/lang/Object;
        25: areturn
      StackMapTable: number_of_entries = 1
        frame_type = 21 /* same */
      LineNumberTable:
        line 21: 0
      LocalVariableTable:
        Start  Length  Slot  Name   Signature
            0      26     0  this   Lscala/sys/PropImpl;
    Signature: #29                          // ()TT;

  public boolean isSet();
    descriptor: ()Z
    flags: (0x0001) ACC_PUBLIC
    Code:
      stack=2, locals=1, args_size=1
         0: aload_0
         1: invokevirtual #51                 // Method underlying:()Lscala/collection/mutable/Map;
         4: aload_0
         5: invokevirtual #53                 // Method key:()Ljava/lang/String;
         8: invokeinterface #59,  2           // InterfaceMethod scala/collection/mutable/Map.contains:(Ljava/lang/Object;)Z
        13: ireturn
      LineNumberTable:
        line 22: 0
      LocalVariableTable:
        Start  Length  Slot  Name   Signature
            0      14     0  this   Lscala/sys/PropImpl;

  public java.lang.String set(java.lang.String);
    descriptor: (Ljava/lang/String;)Ljava/lang/String;
    flags: (0x0001) ACC_PUBLIC
    Code:
      stack=3, locals=3, args_size=2
         0: aload_0
         1: invokevirtual #33                 // Method isSet:()Z
         4: ifeq          14
         7: aload_0
         8: invokevirtual #38                 // Method get:()Ljava/lang/String;
        11: goto          15
        14: aconst_null
        15: astore_2
        16: aload_0
        17: invokevirtual #51                 // Method underlying:()Lscala/collection/mutable/Map;
        20: aload_0
        21: invokevirtual #53                 // Method key:()Ljava/lang/String;
        24: aload_1
        25: invokeinterface #66,  3           // InterfaceMethod scala/collection/mutable/Map.update:(Ljava/lang/Object;Ljava/lang/Object;)V
        30: aload_2
        31: areturn
      StackMapTable: number_of_entries = 2
        frame_type = 14 /* same */
        frame_type = 64 /* same_locals_1_stack_item */
          stack = [ class java/lang/String ]
      LineNumberTable:
        line 24: 0
        line 25: 16
        line 26: 30
      LocalVariableTable:
        Start  Length  Slot  Name   Signature
           16      15     2   old   Ljava/lang/String;
            0      32     0  this   Lscala/sys/PropImpl;
            0      32     1 newValue   Ljava/lang/String;
    MethodParameters:
      Name                           Flags
      newValue                       final

  public <T1 extends java.lang.Object> T setValue(T1);
    descriptor: (Ljava/lang/Object;)Ljava/lang/Object;
    flags: (0x0001) ACC_PUBLIC
    Code:
      stack=2, locals=3, args_size=2
         0: aload_0
         1: invokevirtual #73                 // Method value:()Ljava/lang/Object;
         4: astore_2
         5: aload_1
         6: ifnonnull     18
         9: aload_0
        10: aconst_null
        11: invokevirtual #75                 // Method set:(Ljava/lang/String;)Ljava/lang/String;
        14: pop
        15: goto          27
        18: aload_0
        19: aload_1
        20: invokestatic  #79                 // Method java/lang/String.valueOf:(Ljava/lang/Object;)Ljava/lang/String;
        23: invokevirtual #75                 // Method set:(Ljava/lang/String;)Ljava/lang/String;
        26: pop
        27: aload_2
        28: areturn
      StackMapTable: number_of_entries = 2
        frame_type = 252 /* append */
          offset_delta = 18
          locals = [ class java/lang/Object ]
        frame_type = 8 /* same */
      LineNumberTable:
        line 29: 0
        line 30: 5
        line 31: 18
        line 32: 27
      LocalVariableTable:
        Start  Length  Slot  Name   Signature
            5      23     2   old   Ljava/lang/Object;
            0      29     0  this   Lscala/sys/PropImpl;
            0      29     1 newValue   Ljava/lang/Object;
    Signature: #71                          // <T1:Ljava/lang/Object;>(TT1;)TT;
    MethodParameters:
      Name                           Flags
      newValue                       final

  public java.lang.String get();
    descriptor: ()Ljava/lang/String;
    flags: (0x0001) ACC_PUBLIC
    Code:
      stack=3, locals=1, args_size=1
         0: aload_0
         1: invokevirtual #33                 // Method isSet:()Z
         4: ifeq          29
         7: aload_0
         8: invokevirtual #51                 // Method underlying:()Lscala/collection/mutable/Map;
        11: aload_0
        12: invokevirtual #53                 // Method key:()Ljava/lang/String;
        15: invokedynamic #98,  0             // InvokeDynamic #0:apply:()Lscala/Function0;
        20: invokeinterface #102,  3          // InterfaceMethod scala/collection/mutable/Map.getOrElse:(Ljava/lang/Object;Lscala/Function0;)Ljava/lang/Object;
        25: checkcast     #69                 // class java/lang/String
        28: areturn
        29: ldc           #104                // String
        31: areturn
      StackMapTable: number_of_entries = 1
        frame_type = 29 /* same */
      LineNumberTable:
        line 35: 0
        line 36: 29
      LocalVariableTable:
        Start  Length  Slot  Name   Signature
            0      32     0  this   Lscala/sys/PropImpl;

  public void clear();
    descriptor: ()V
    flags: (0x0001) ACC_PUBLIC
    Code:
      stack=2, locals=2, args_size=1
         0: aload_0
         1: invokevirtual #51                 // Method underlying:()Lscala/collection/mutable/Map;
         4: aload_0
         5: invokevirtual #53                 // Method key:()Ljava/lang/String;
         8: astore_1
         9: dup
        10: ifnonnull     15
        13: aconst_null
        14: athrow
        15: aload_1
        16: invokeinterface #112,  2          // InterfaceMethod scala/collection/mutable/Shrinkable.subtractOne:(Ljava/lang/Object;)Lscala/collection/mutable/Shrinkable;
        21: pop
        22: return
      StackMapTable: number_of_entries = 1
        frame_type = 255 /* full_frame */
          offset_delta = 15
          locals = [ class scala/sys/PropImpl, class java/lang/String ]
          stack = [ class scala/collection/mutable/Map ]
      LineNumberTable:
        line 38: 0
      LocalVariableTable:
        Start  Length  Slot  Name   Signature
            0      23     0  this   Lscala/sys/PropImpl;
           15       7     1 $minus$eq_elem   Ljava/lang/Object;

  public scala.Option<T> option();
    descriptor: ()Lscala/Option;
    flags: (0x0001) ACC_PUBLIC
    Code:
      stack=3, locals=1, args_size=1
         0: aload_0
         1: invokevirtual #33                 // Method isSet:()Z
         4: ifeq          19
         7: new           #118                // class scala/Some
        10: dup
        11: aload_0
        12: invokevirtual #73                 // Method value:()Ljava/lang/Object;
        15: invokespecial #122                // Method scala/Some."<init>":(Ljava/lang/Object;)V
        18: areturn
        19: getstatic     #128                // Field scala/None$.MODULE$:Lscala/None$;
        22: areturn
      StackMapTable: number_of_entries = 1
        frame_type = 19 /* same */
      LineNumberTable:
        line 39: 0
      LocalVariableTable:
        Start  Length  Slot  Name   Signature
            0      23     0  this   Lscala/sys/PropImpl;
    Signature: #116                         // ()Lscala/Option<TT;>;

  public <T1 extends java.lang.Object> T1 or(scala.Function0<T1>);
    descriptor: (Lscala/Function0;)Ljava/lang/Object;
    flags: (0x0001) ACC_PUBLIC
    Code:
      stack=1, locals=2, args_size=2
         0: aload_0
         1: invokevirtual #33                 // Method isSet:()Z
         4: ifeq          12
         7: aload_0
         8: invokevirtual #73                 // Method value:()Ljava/lang/Object;
        11: areturn
        12: aload_1
        13: invokeinterface #136,  1          // InterfaceMethod scala/Function0.apply:()Ljava/lang/Object;
        18: areturn
      StackMapTable: number_of_entries = 1
        frame_type = 12 /* same */
      LineNumberTable:
        line 40: 0
      LocalVariableTable:
        Start  Length  Slot  Name   Signature
            0      19     0  this   Lscala/sys/PropImpl;
            0      19     1   alt   Lscala/Function0;
    Signature: #131                         // <T1:Ljava/lang/Object;>(Lscala/Function0<TT1;>;)TT1;
    MethodParameters:
      Name                           Flags
      alt                            final

  public scala.collection.mutable.Map<java.lang.String, java.lang.String> underlying();
    descriptor: ()Lscala/collection/mutable/Map;
    flags: (0x0001) ACC_PUBLIC
    Code:
      stack=2, locals=1, args_size=1
         0: getstatic     #143                // Field scala/sys/package$.MODULE$:Lscala/sys/package$;
         3: pop
         4: new           #145                // class scala/sys/SystemProperties
         7: dup
         8: invokespecial #147                // Method scala/sys/SystemProperties."<init>":()V
        11: areturn
      LineNumberTable:
        line 43: 0
      LocalVariableTable:
        Start  Length  Slot  Name   Signature
            0      12     0  this   Lscala/sys/PropImpl;
    Signature: #138                         // ()Lscala/collection/mutable/Map<Ljava/lang/String;Ljava/lang/String;>;

  public T zero();
    descriptor: ()Ljava/lang/Object;
    flags: (0x0001) ACC_PUBLIC
    Code:
      stack=1, locals=1, args_size=1
         0: aconst_null
         1: areturn
      LineNumberTable:
        line 44: 0
      LocalVariableTable:
        Start  Length  Slot  Name   Signature
            0       2     0  this   Lscala/sys/PropImpl;
    Signature: #29                          // ()TT;

  private java.lang.String getString();
    descriptor: ()Ljava/lang/String;
    flags: (0x0002) ACC_PRIVATE
    Code:
      stack=3, locals=1, args_size=1
         0: aload_0
         1: invokevirtual #33                 // Method isSet:()Z
         4: ifeq          32
         7: new           #150                // class java/lang/StringBuilder
        10: dup
        11: ldc           #151                // int 11
        13: invokespecial #154                // Method java/lang/StringBuilder."<init>":(I)V
        16: ldc           #156                // String currently:
        18: invokevirtual #160                // Method java/lang/StringBuilder.append:(Ljava/lang/String;)Ljava/lang/StringBuilder;
        21: aload_0
        22: invokevirtual #38                 // Method get:()Ljava/lang/String;
        25: invokevirtual #160                // Method java/lang/StringBuilder.append:(Ljava/lang/String;)Ljava/lang/StringBuilder;
        28: invokevirtual #163                // Method java/lang/StringBuilder.toString:()Ljava/lang/String;
        31: areturn
        32: ldc           #165                // String unset
        34: areturn
      StackMapTable: number_of_entries = 1
        frame_type = 32 /* same */
      LineNumberTable:
        line 45: 0
      LocalVariableTable:
        Start  Length  Slot  Name   Signature
            0      35     0  this   Lscala/sys/PropImpl;

  public java.lang.String toString();
    descriptor: ()Ljava/lang/String;
    flags: (0x0001) ACC_PUBLIC
    Code:
      stack=7, locals=1, args_size=1
         0: getstatic     #170                // Field scala/collection/StringOps$.MODULE$:Lscala/collection/StringOps$;
         3: ldc           #172                // String %s (%s)
         5: getstatic     #177                // Field scala/runtime/ScalaRunTime$.MODULE$:Lscala/runtime/ScalaRunTime$;
         8: iconst_2
         9: anewarray     #5                  // class java/lang/Object
        12: dup
        13: iconst_0
        14: aload_0
        15: invokevirtual #53                 // Method key:()Ljava/lang/String;
        18: aastore
        19: dup
        20: iconst_1
        21: aload_0
        22: invokespecial #179                // Method getString:()Ljava/lang/String;
        25: aastore
        26: invokevirtual #183                // Method scala/runtime/ScalaRunTime$.genericWrapArray:(Ljava/lang/Object;)Lscala/collection/immutable/ArraySeq;
        29: invokevirtual #187                // Method scala/collection/StringOps$.format$extension:(Ljava/lang/String;Lscala/collection/immutable/Seq;)Ljava/lang/String;
        32: areturn
      LineNumberTable:
        line 46: 3
      LocalVariableTable:
        Start  Length  Slot  Name   Signature
            0      33     0  this   Lscala/sys/PropImpl;

  public static final java.lang.String $anonfun$get$1();
    descriptor: ()Ljava/lang/String;
    flags: (0x1019) ACC_PUBLIC, ACC_STATIC, ACC_FINAL, ACC_SYNTHETIC
    Code:
      stack=1, locals=0, args_size=0
         0: ldc           #104                // String
         2: areturn
      LineNumberTable:
        line 35: 0

  public scala.sys.PropImpl(java.lang.String, scala.Function1<java.lang.String, T>);
    descriptor: (Ljava/lang/String;Lscala/Function1;)V
    flags: (0x0001) ACC_PUBLIC
    Code:
      stack=2, locals=3, args_size=3
         0: aload_0
         1: aload_1
         2: putfield      #24                 // Field key:Ljava/lang/String;
         5: aload_0
         6: aload_2
         7: putfield      #35                 // Field valueFn:Lscala/Function1;
        10: aload_0
        11: invokespecial #190                // Method java/lang/Object."<init>":()V
        14: return
      LineNumberTable:
        line 20: 0
      LocalVariableTable:
        Start  Length  Slot  Name   Signature
            0      15     0  this   Lscala/sys/PropImpl;
            0      15     1   key   Ljava/lang/String;
            0      15     2 valueFn   Lscala/Function1;
    Signature: #189                         // (Ljava/lang/String;Lscala/Function1<Ljava/lang/String;TT;>;)V
    MethodParameters:
      Name                           Flags
      key                            final
      valueFn                        final

  private static java.lang.Object $deserializeLambda$(java.lang.invoke.SerializedLambda);
    descriptor: (Ljava/lang/invoke/SerializedLambda;)Ljava/lang/Object;
    flags: (0x100a) ACC_PRIVATE, ACC_STATIC, ACC_SYNTHETIC
    Code:
      stack=1, locals=1, args_size=1
         0: aload_0
         1: invokedynamic #202,  0            // InvokeDynamic #1:lambdaDeserialize:(Ljava/lang/invoke/SerializedLambda;)Ljava/lang/Object;
         6: areturn
}
InnerClasses:
  public static final #16= #13 of #15;    // Lookup=class java/lang/invoke/MethodHandles$Lookup of class java/lang/invoke/MethodHandles
Signature: #3                           // <T:Ljava/lang/Object;>Ljava/lang/Object;Lscala/sys/Prop<TT;>;
SourceFile: "PropImpl.scala"
RuntimeVisibleAnnotations:
  0: #9(#10=s#11)
    scala.reflect.ScalaSignature(
      bytes="\u0006\u0005\u0005\ra!B\t\u0013\u0001I1\u0002\u0002\u0003\u0017\u0001\u0005\u000b\u0007I\u0011A\u0017\t\u0011e\u0002!\u0011!Q\u0001\n9B\u0001B\u000f\u0001\u0003\u0002\u0003\u0006Ia\u000f\u0005\u0006}\u0001!\ta\u0010\u0005\u0006\u0007\u0002!\t\u0001\u0012\u0005\u0006\u000b\u0002!\tA\u0012\u0005\u0006\u0015\u0002!\ta\u0013\u0005\u0006\u001d\u0002!\ta\u0014\u0005\u0006-\u0002!\t!\f\u0005\u0006/\u0002!\t\u0001\u0017\u0005\u00069\u0002!\t!\u0018\u0005\u0006C\u0002!\tA\u0019\u0005\u0006W\u0002!\t\u0002\u001c\u0005\u0006k\u0002!\t\u0002\u0012\u0005\u0006m\u0002!Ia\u001e\u0005\u0007\u007f\u0002!\t%!\u0001\u0003\u0011A\u0013x\u000e]%na2T!a\u0005\u000b\u0002\u0007ML8OC\u0001\u0016\u0003\u0015\u00198-\u00197b+\t9\"eE\u0002\u00011q\u0001\"!\u0007\u000e\u000e\u0003QI!a\u0007\u000b\u0003\r\u0005s\u0017PU3g!\rib\u0004I\u0007\u0002%%\u0011qD\u0005\u0002\u0005!J|\u0007\u000f\u0005\u0002\"E1\u0001AAB\u0012\u0001\t\u000b\u0007QEA\u0001U\u0007\u0001\t\"AJ\u0015\u0011\u0005e9\u0013B\u0001\u0015\u0015\u0005\u001dqu\u000e\u001e5j]\u001e\u0004\"!\u0007\u0016\n\u0005-\"\"aA!os\u0006\u00191.Z=\u0016\u00039\u0002\"a\f\u001c\u000f\u0005A\"\u0004CA\u0019\u0015\u001b\u0005\u0011$BA\u001a%\u0003\u0019a$o\\8u}%\u0011Q\u0007F\u0001\u0007!J,G-\u001a4\n\u0005]B$AB*ue&twM\u0003\u00026)\u0005!1.Z=!\u0003\u001d1\u0018\r\\;f\r:\u0004B!\u0007\u001f/A%\u0011Q\b\u0006\u0002\n\rVt7\r^5p]F\na\u0001P5oSRtDc\u0001!B\u0005B\u0019Q\u0004\u0001\u0011\t\u000b1\"\u0001\u0019\u0001\u0018\t\u000bi\"\u0001\u0019A\u001e\u0002\u000bY\fG.^3\u0016\u0003\u0001\nQ![:TKR,\u0012a\u0012\t\u00033!K!!\u0013\u000b\u0003\u000f\t{w\u000e\\3b]\u0006\u00191/\u001a;\u0015\u00059b\u0005\"B\'\b\u0001\u0004q\u0013\u0001\u00038foZ\u000bG.^3\u0002\u0011M,GOV1mk\u0016,\"\u0001U*\u0015\u0005\u0001\n\u0006\"B\'\t\u0001\u0004\u0011\u0006CA\u0011T\t\u0015!\u0006B1\u0001V\u0005\t!\u0016\'\u0005\u0002!S\u0005\u0019q-\u001a;\u0002\u000b\rdW-\u0019:\u0015\u0003e\u0003\"!\u0007.\n\u0005m#\"\u0001B+oSR\faa\u001c9uS>tW#\u00010\u0011\u0007ey\u0006%\u0003\u0002a)\t1q\n\u001d;j_:\f!a\u001c:\u0016\u0005\r,GC\u00013g!\t\tS\rB\u0003U\u0019\t\u0007Q\u000b\u0003\u0004h\u0019\u0011\u0005\r\u0001[\u0001\u0004C2$\bcA\rjI&\u0011!\u000e\u0006\u0002\ty\tLh.Y7f}\u0005QQO\u001c3fe2L\u0018N\\4\u0016\u00035\u0004BA\\:/]5\tqN\u0003\u0002qc\u00069Q.\u001e;bE2,\'B\u0001:\u0015\u0003)\u0019w\u000e\u001c7fGRLwN\\\u0005\u0003i>\u00141!T1q\u0003\u0011QXM]8\u0002\u0013\u001d,Go\u0015;sS:<W#\u0001=\u0011\u0005etX\"\u0001>\u000b\u0005md\u0018\u0001\u00027b]\u001eT\u0011!`\u0001\u0005U\u00064\u0018-\u0003\u00028u\u0006AAo\\*ue&tw\rF\u0001/\u0001"
    )
BootstrapMethods:
  0: #95 REF_invokeStatic java/lang/invoke/LambdaMetafactory.altMetafactory:(Ljava/lang/invoke/MethodHandles$Lookup;Ljava/lang/String;Ljava/lang/invoke/MethodType;[Ljava/lang/Object;)Ljava/lang/invoke/CallSite;
    Method arguments:
      #81 ()Ljava/lang/Object;
      #85 REF_invokeStatic scala/sys/PropImpl.$anonfun$get$1:()Ljava/lang/String;
      #86 ()Ljava/lang/String;
      #87 5
      #88 1
      #86 ()Ljava/lang/String;
  1: #199 REF_invokeStatic scala/runtime/LambdaDeserialize.bootstrap:(Ljava/lang/invoke/MethodHandles$Lookup;Ljava/lang/String;Ljava/lang/invoke/MethodType;[Ljava/lang/invoke/MethodHandle;)Ljava/lang/invoke/CallSite;
    Method arguments:
      #85 REF_invokeStatic scala/sys/PropImpl.$anonfun$get$1:()Ljava/lang/String;
  ScalaInlineInfo: length = 0x4F (unknown attribute)
   01 00 00 0F 00 52 00 16 01 00 77 00 BC 00 00 69
   00 6A 00 00 24 00 16 00 00 94 00 16 01 00 1E 00
   1F 00 00 11 00 16 00 00 72 00 73 00 00 81 00 82
   00 00 3C 00 3D 00 00 46 00 2A 00 00 A1 00 16 00
   00 30 00 31 00 00 1B 00 1C 00 00 2D 00 1C 00
  ScalaSig: length = 0x3 (unknown attribute)
   05 02 00
