Classfile /Users/mw/Projects/slang-braindump/.jar/jar11/assemble/slang-braindump/assemble/content/org/apache/commons/io/output/DemuxOutputStream.class
  Last modified May 29, 2022; size 1398 bytes
  SHA-256 checksum 282fe0b789bbb5ca12ab54aa47b37f41eef0c269ccc794386b55aa4e155a271f
  Compiled from "DemuxOutputStream.java"
public class org.apache.commons.io.output.DemuxOutputStream extends java.io.OutputStream
  minor version: 0
  major version: 52
  flags: (0x0021) ACC_PUBLIC, ACC_SUPER
  this_class: #12                         // org/apache/commons/io/output/DemuxOutputStream
  super_class: #6                         // java/io/OutputStream
  interfaces: 0, fields: 1, methods: 5, attributes: 1
Constant pool:
   #1 = Methodref          #6.#41         // java/io/OutputStream."<init>":()V
   #2 = Class              #42            // java/lang/InheritableThreadLocal
   #3 = Methodref          #2.#41         // java/lang/InheritableThreadLocal."<init>":()V
   #4 = Fieldref           #12.#43        // org/apache/commons/io/output/DemuxOutputStream.outputStreamThreadLocal:Ljava/lang/InheritableThreadLocal;
   #5 = Methodref          #2.#44         // java/lang/InheritableThreadLocal.get:()Ljava/lang/Object;
   #6 = Class              #45            // java/io/OutputStream
   #7 = Methodref          #2.#46         // java/lang/InheritableThreadLocal.set:(Ljava/lang/Object;)V
   #8 = Class              #47            // java/io/Closeable
   #9 = Methodref          #48.#49        // org/apache/commons/io/IOUtils.close:(Ljava/io/Closeable;)V
  #10 = Methodref          #6.#50         // java/io/OutputStream.flush:()V
  #11 = Methodref          #6.#51         // java/io/OutputStream.write:(I)V
  #12 = Class              #52            // org/apache/commons/io/output/DemuxOutputStream
  #13 = Utf8               outputStreamThreadLocal
  #14 = Utf8               Ljava/lang/InheritableThreadLocal;
  #15 = Utf8               Signature
  #16 = Utf8               Ljava/lang/InheritableThreadLocal<Ljava/io/OutputStream;>;
  #17 = Utf8               <init>
  #18 = Utf8               ()V
  #19 = Utf8               Code
  #20 = Utf8               LineNumberTable
  #21 = Utf8               LocalVariableTable
  #22 = Utf8               this
  #23 = Utf8               Lorg/apache/commons/io/output/DemuxOutputStream;
  #24 = Utf8               bindStream
  #25 = Utf8               (Ljava/io/OutputStream;)Ljava/io/OutputStream;
  #26 = Utf8               output
  #27 = Utf8               Ljava/io/OutputStream;
  #28 = Utf8               stream
  #29 = Utf8               close
  #30 = Utf8               Exceptions
  #31 = Class              #53            // java/io/IOException
  #32 = Utf8               flush
  #33 = Utf8               StackMapTable
  #34 = Class              #45            // java/io/OutputStream
  #35 = Utf8               write
  #36 = Utf8               (I)V
  #37 = Utf8               ch
  #38 = Utf8               I
  #39 = Utf8               SourceFile
  #40 = Utf8               DemuxOutputStream.java
  #41 = NameAndType        #17:#18        // "<init>":()V
  #42 = Utf8               java/lang/InheritableThreadLocal
  #43 = NameAndType        #13:#14        // outputStreamThreadLocal:Ljava/lang/InheritableThreadLocal;
  #44 = NameAndType        #54:#55        // get:()Ljava/lang/Object;
  #45 = Utf8               java/io/OutputStream
  #46 = NameAndType        #56:#57        // set:(Ljava/lang/Object;)V
  #47 = Utf8               java/io/Closeable
  #48 = Class              #58            // org/apache/commons/io/IOUtils
  #49 = NameAndType        #29:#59        // close:(Ljava/io/Closeable;)V
  #50 = NameAndType        #32:#18        // flush:()V
  #51 = NameAndType        #35:#36        // write:(I)V
  #52 = Utf8               org/apache/commons/io/output/DemuxOutputStream
  #53 = Utf8               java/io/IOException
  #54 = Utf8               get
  #55 = Utf8               ()Ljava/lang/Object;
  #56 = Utf8               set
  #57 = Utf8               (Ljava/lang/Object;)V
  #58 = Utf8               org/apache/commons/io/IOUtils
  #59 = Utf8               (Ljava/io/Closeable;)V
{
  private final java.lang.InheritableThreadLocal<java.io.OutputStream> outputStreamThreadLocal;
    descriptor: Ljava/lang/InheritableThreadLocal;
    flags: (0x0012) ACC_PRIVATE, ACC_FINAL
    Signature: #16                          // Ljava/lang/InheritableThreadLocal<Ljava/io/OutputStream;>;

  public org.apache.commons.io.output.DemuxOutputStream();
    descriptor: ()V
    flags: (0x0001) ACC_PUBLIC
    Code:
      stack=3, locals=1, args_size=1
         0: aload_0
         1: invokespecial #1                  // Method java/io/OutputStream."<init>":()V
         4: aload_0
         5: new           #2                  // class java/lang/InheritableThreadLocal
         8: dup
         9: invokespecial #3                  // Method java/lang/InheritableThreadLocal."<init>":()V
        12: putfield      #4                  // Field outputStreamThreadLocal:Ljava/lang/InheritableThreadLocal;
        15: return
      LineNumberTable:
        line 28: 0
        line 29: 4
      LocalVariableTable:
        Start  Length  Slot  Name   Signature
            0      16     0  this   Lorg/apache/commons/io/output/DemuxOutputStream;

  public java.io.OutputStream bindStream(java.io.OutputStream);
    descriptor: (Ljava/io/OutputStream;)Ljava/io/OutputStream;
    flags: (0x0001) ACC_PUBLIC
    Code:
      stack=2, locals=3, args_size=2
         0: aload_0
         1: getfield      #4                  // Field outputStreamThreadLocal:Ljava/lang/InheritableThreadLocal;
         4: invokevirtual #5                  // Method java/lang/InheritableThreadLocal.get:()Ljava/lang/Object;
         7: checkcast     #6                  // class java/io/OutputStream
        10: astore_2
        11: aload_0
        12: getfield      #4                  // Field outputStreamThreadLocal:Ljava/lang/InheritableThreadLocal;
        15: aload_1
        16: invokevirtual #7                  // Method java/lang/InheritableThreadLocal.set:(Ljava/lang/Object;)V
        19: aload_2
        20: areturn
      LineNumberTable:
        line 39: 0
        line 40: 11
        line 41: 19
      LocalVariableTable:
        Start  Length  Slot  Name   Signature
            0      21     0  this   Lorg/apache/commons/io/output/DemuxOutputStream;
            0      21     1 output   Ljava/io/OutputStream;
           11      10     2 stream   Ljava/io/OutputStream;

  public void close() throws java.io.IOException;
    descriptor: ()V
    flags: (0x0001) ACC_PUBLIC
    Code:
      stack=1, locals=1, args_size=1
         0: aload_0
         1: getfield      #4                  // Field outputStreamThreadLocal:Ljava/lang/InheritableThreadLocal;
         4: invokevirtual #5                  // Method java/lang/InheritableThreadLocal.get:()Ljava/lang/Object;
         7: checkcast     #8                  // class java/io/Closeable
        10: invokestatic  #9                  // Method org/apache/commons/io/IOUtils.close:(Ljava/io/Closeable;)V
        13: return
      LineNumberTable:
        line 52: 0
        line 53: 13
      LocalVariableTable:
        Start  Length  Slot  Name   Signature
            0      14     0  this   Lorg/apache/commons/io/output/DemuxOutputStream;
    Exceptions:
      throws java.io.IOException

  public void flush() throws java.io.IOException;
    descriptor: ()V
    flags: (0x0001) ACC_PUBLIC
    Code:
      stack=2, locals=2, args_size=1
         0: aload_0
         1: getfield      #4                  // Field outputStreamThreadLocal:Ljava/lang/InheritableThreadLocal;
         4: invokevirtual #5                  // Method java/lang/InheritableThreadLocal.get:()Ljava/lang/Object;
         7: checkcast     #6                  // class java/io/OutputStream
        10: astore_1
        11: aconst_null
        12: aload_1
        13: if_acmpeq     20
        16: aload_1
        17: invokevirtual #10                 // Method java/io/OutputStream.flush:()V
        20: return
      LineNumberTable:
        line 64: 0
        line 65: 11
        line 66: 16
        line 68: 20
      LocalVariableTable:
        Start  Length  Slot  Name   Signature
            0      21     0  this   Lorg/apache/commons/io/output/DemuxOutputStream;
           11      10     1 output   Ljava/io/OutputStream;
      StackMapTable: number_of_entries = 1
        frame_type = 252 /* append */
          offset_delta = 20
          locals = [ class java/io/OutputStream ]
    Exceptions:
      throws java.io.IOException

  public void write(int) throws java.io.IOException;
    descriptor: (I)V
    flags: (0x0001) ACC_PUBLIC
    Code:
      stack=2, locals=3, args_size=2
         0: aload_0
         1: getfield      #4                  // Field outputStreamThreadLocal:Ljava/lang/InheritableThreadLocal;
         4: invokevirtual #5                  // Method java/lang/InheritableThreadLocal.get:()Ljava/lang/Object;
         7: checkcast     #6                  // class java/io/OutputStream
        10: astore_2
        11: aconst_null
        12: aload_2
        13: if_acmpeq     21
        16: aload_2
        17: iload_1
        18: invokevirtual #11                 // Method java/io/OutputStream.write:(I)V
        21: return
      LineNumberTable:
        line 81: 0
        line 82: 11
        line 83: 16
        line 85: 21
      LocalVariableTable:
        Start  Length  Slot  Name   Signature
            0      22     0  this   Lorg/apache/commons/io/output/DemuxOutputStream;
            0      22     1    ch   I
           11      11     2 output   Ljava/io/OutputStream;
      StackMapTable: number_of_entries = 1
        frame_type = 252 /* append */
          offset_delta = 21
          locals = [ class java/io/OutputStream ]
    Exceptions:
      throws java.io.IOException
}
SourceFile: "DemuxOutputStream.java"
