Classfile /Users/mw/Projects/slang-braindump/.jar/jar11/assemble/slang-braindump/assemble/content/org/apache/commons/io/output/UnsynchronizedByteArrayOutputStream.class
  Last modified May 29, 2022; size 3973 bytes
  SHA-256 checksum 1e46ee265392d326975367af48b457dbed0854dbfb8c1fb7e1a3552184eccdae
  Compiled from "UnsynchronizedByteArrayOutputStream.java"
public final class org.apache.commons.io.output.UnsynchronizedByteArrayOutputStream extends org.apache.commons.io.output.AbstractByteArrayOutputStream
  minor version: 0
  major version: 52
  flags: (0x0031) ACC_PUBLIC, ACC_FINAL, ACC_SUPER
  this_class: #26                         // org/apache/commons/io/output/UnsynchronizedByteArrayOutputStream
  super_class: #1                         // org/apache/commons/io/output/AbstractByteArrayOutputStream
  interfaces: 0, fields: 0, methods: 12, attributes: 3
Constant pool:
    #1 = Class              #77           // org/apache/commons/io/output/AbstractByteArrayOutputStream
    #2 = Methodref          #26.#78       // org/apache/commons/io/output/UnsynchronizedByteArrayOutputStream."<init>":(I)V
    #3 = Methodref          #1.#79        // org/apache/commons/io/output/AbstractByteArrayOutputStream."<init>":()V
    #4 = Class              #80           // java/lang/IllegalArgumentException
    #5 = Class              #81           // java/lang/StringBuilder
    #6 = Methodref          #5.#79        // java/lang/StringBuilder."<init>":()V
    #7 = String             #82           // Negative initial size:
    #8 = Methodref          #5.#83        // java/lang/StringBuilder.append:(Ljava/lang/String;)Ljava/lang/StringBuilder;
    #9 = Methodref          #5.#84        // java/lang/StringBuilder.append:(I)Ljava/lang/StringBuilder;
   #10 = Methodref          #5.#85        // java/lang/StringBuilder.toString:()Ljava/lang/String;
   #11 = Methodref          #4.#86        // java/lang/IllegalArgumentException."<init>":(Ljava/lang/String;)V
   #12 = Methodref          #26.#87       // org/apache/commons/io/output/UnsynchronizedByteArrayOutputStream.needNewBuffer:(I)V
   #13 = Class              #88           // java/lang/IndexOutOfBoundsException
   #14 = String             #89           // offset=%,d, length=%,d
   #15 = Class              #90           // java/lang/Object
   #16 = Methodref          #91.#92       // java/lang/Integer.valueOf:(I)Ljava/lang/Integer;
   #17 = Methodref          #93.#94       // java/lang/String.format:(Ljava/lang/String;[Ljava/lang/Object;)Ljava/lang/String;
   #18 = Methodref          #13.#86       // java/lang/IndexOutOfBoundsException."<init>":(Ljava/lang/String;)V
   #19 = Methodref          #26.#95       // org/apache/commons/io/output/UnsynchronizedByteArrayOutputStream.writeImpl:([BII)V
   #20 = Methodref          #26.#96       // org/apache/commons/io/output/UnsynchronizedByteArrayOutputStream.writeImpl:(I)V
   #21 = Methodref          #26.#97       // org/apache/commons/io/output/UnsynchronizedByteArrayOutputStream.writeImpl:(Ljava/io/InputStream;)I
   #22 = Fieldref           #26.#98       // org/apache/commons/io/output/UnsynchronizedByteArrayOutputStream.count:I
   #23 = Methodref          #26.#99       // org/apache/commons/io/output/UnsynchronizedByteArrayOutputStream.resetImpl:()V
   #24 = Methodref          #26.#100      // org/apache/commons/io/output/UnsynchronizedByteArrayOutputStream.writeToImpl:(Ljava/io/OutputStream;)V
   #25 = Methodref          #26.#101      // org/apache/commons/io/output/UnsynchronizedByteArrayOutputStream.toBufferedInputStream:(Ljava/io/InputStream;I)Ljava/io/InputStream;
   #26 = Class              #102          // org/apache/commons/io/output/UnsynchronizedByteArrayOutputStream
   #27 = Methodref          #26.#103      // org/apache/commons/io/output/UnsynchronizedByteArrayOutputStream.write:(Ljava/io/InputStream;)I
   #28 = Methodref          #26.#104      // org/apache/commons/io/output/UnsynchronizedByteArrayOutputStream.toInputStream:()Ljava/io/InputStream;
   #29 = Methodref          #26.#105      // org/apache/commons/io/output/UnsynchronizedByteArrayOutputStream.close:()V
   #30 = Class              #106          // java/lang/Throwable
   #31 = Methodref          #30.#107      // java/lang/Throwable.addSuppressed:(Ljava/lang/Throwable;)V
   #32 = InvokeDynamic      #0:#113       // #0:construct:()Lorg/apache/commons/io/output/AbstractByteArrayOutputStream$InputStreamConstructor;
   #33 = Methodref          #26.#114      // org/apache/commons/io/output/UnsynchronizedByteArrayOutputStream.toInputStream:(Lorg/apache/commons/io/output/AbstractByteArrayOutputStream$InputStreamConstructor;)Ljava/io/InputStream;
   #34 = Methodref          #26.#115      // org/apache/commons/io/output/UnsynchronizedByteArrayOutputStream.toByteArrayImpl:()[B
   #35 = Utf8               <init>
   #36 = Utf8               ()V
   #37 = Utf8               Code
   #38 = Utf8               LineNumberTable
   #39 = Utf8               LocalVariableTable
   #40 = Utf8               this
   #41 = Utf8               Lorg/apache/commons/io/output/UnsynchronizedByteArrayOutputStream;
   #42 = Utf8               (I)V
   #43 = Utf8               size
   #44 = Utf8               I
   #45 = Utf8               StackMapTable
   #46 = Class              #102          // org/apache/commons/io/output/UnsynchronizedByteArrayOutputStream
   #47 = Utf8               write
   #48 = Utf8               ([BII)V
   #49 = Utf8               b
   #50 = Utf8               [B
   #51 = Utf8               off
   #52 = Utf8               len
   #53 = Utf8               (Ljava/io/InputStream;)I
   #54 = Utf8               in
   #55 = Utf8               Ljava/io/InputStream;
   #56 = Utf8               Exceptions
   #57 = Class              #116          // java/io/IOException
   #58 = Utf8               ()I
   #59 = Utf8               reset
   #60 = Utf8               writeTo
   #61 = Utf8               (Ljava/io/OutputStream;)V
   #62 = Utf8               out
   #63 = Utf8               Ljava/io/OutputStream;
   #64 = Utf8               toBufferedInputStream
   #65 = Utf8               (Ljava/io/InputStream;)Ljava/io/InputStream;
   #66 = Utf8               input
   #67 = Utf8               (Ljava/io/InputStream;I)Ljava/io/InputStream;
   #68 = Utf8               output
   #69 = Class              #117          // java/io/InputStream
   #70 = Class              #106          // java/lang/Throwable
   #71 = Utf8               toInputStream
   #72 = Utf8               ()Ljava/io/InputStream;
   #73 = Utf8               toByteArray
   #74 = Utf8               ()[B
   #75 = Utf8               SourceFile
   #76 = Utf8               UnsynchronizedByteArrayOutputStream.java
   #77 = Utf8               org/apache/commons/io/output/AbstractByteArrayOutputStream
   #78 = NameAndType        #35:#42       // "<init>":(I)V
   #79 = NameAndType        #35:#36       // "<init>":()V
   #80 = Utf8               java/lang/IllegalArgumentException
   #81 = Utf8               java/lang/StringBuilder
   #82 = Utf8               Negative initial size:
   #83 = NameAndType        #118:#119     // append:(Ljava/lang/String;)Ljava/lang/StringBuilder;
   #84 = NameAndType        #118:#120     // append:(I)Ljava/lang/StringBuilder;
   #85 = NameAndType        #121:#122     // toString:()Ljava/lang/String;
   #86 = NameAndType        #35:#123      // "<init>":(Ljava/lang/String;)V
   #87 = NameAndType        #124:#42      // needNewBuffer:(I)V
   #88 = Utf8               java/lang/IndexOutOfBoundsException
   #89 = Utf8               offset=%,d, length=%,d
   #90 = Utf8               java/lang/Object
   #91 = Class              #125          // java/lang/Integer
   #92 = NameAndType        #126:#127     // valueOf:(I)Ljava/lang/Integer;
   #93 = Class              #128          // java/lang/String
   #94 = NameAndType        #129:#130     // format:(Ljava/lang/String;[Ljava/lang/Object;)Ljava/lang/String;
   #95 = NameAndType        #131:#48      // writeImpl:([BII)V
   #96 = NameAndType        #131:#42      // writeImpl:(I)V
   #97 = NameAndType        #131:#53      // writeImpl:(Ljava/io/InputStream;)I
   #98 = NameAndType        #132:#44      // count:I
   #99 = NameAndType        #133:#36      // resetImpl:()V
  #100 = NameAndType        #134:#61      // writeToImpl:(Ljava/io/OutputStream;)V
  #101 = NameAndType        #64:#67       // toBufferedInputStream:(Ljava/io/InputStream;I)Ljava/io/InputStream;
  #102 = Utf8               org/apache/commons/io/output/UnsynchronizedByteArrayOutputStream
  #103 = NameAndType        #47:#53       // write:(Ljava/io/InputStream;)I
  #104 = NameAndType        #71:#72       // toInputStream:()Ljava/io/InputStream;
  #105 = NameAndType        #135:#36      // close:()V
  #106 = Utf8               java/lang/Throwable
  #107 = NameAndType        #136:#137     // addSuppressed:(Ljava/lang/Throwable;)V
  #108 = Utf8               BootstrapMethods
  #109 = MethodHandle       6:#138        // REF_invokeStatic java/lang/invoke/LambdaMetafactory.metafactory:(Ljava/lang/invoke/MethodHandles$Lookup;Ljava/lang/String;Ljava/lang/invoke/MethodType;Ljava/lang/invoke/MethodType;Ljava/lang/invoke/MethodHandle;Ljava/lang/invoke/MethodType;)Ljava/lang/invoke/CallSite;
  #110 = MethodType         #139          //  ([BII)Ljava/io/InputStream;
  #111 = MethodHandle       8:#140        // REF_newInvokeSpecial org/apache/commons/io/input/UnsynchronizedByteArrayInputStream."<init>":([BII)V
  #112 = MethodType         #141          //  ([BII)Lorg/apache/commons/io/input/UnsynchronizedByteArrayInputStream;
  #113 = NameAndType        #142:#146     // construct:()Lorg/apache/commons/io/output/AbstractByteArrayOutputStream$InputStreamConstructor;
  #114 = NameAndType        #71:#147      // toInputStream:(Lorg/apache/commons/io/output/AbstractByteArrayOutputStream$InputStreamConstructor;)Ljava/io/InputStream;
  #115 = NameAndType        #148:#74      // toByteArrayImpl:()[B
  #116 = Utf8               java/io/IOException
  #117 = Utf8               java/io/InputStream
  #118 = Utf8               append
  #119 = Utf8               (Ljava/lang/String;)Ljava/lang/StringBuilder;
  #120 = Utf8               (I)Ljava/lang/StringBuilder;
  #121 = Utf8               toString
  #122 = Utf8               ()Ljava/lang/String;
  #123 = Utf8               (Ljava/lang/String;)V
  #124 = Utf8               needNewBuffer
  #125 = Utf8               java/lang/Integer
  #126 = Utf8               valueOf
  #127 = Utf8               (I)Ljava/lang/Integer;
  #128 = Utf8               java/lang/String
  #129 = Utf8               format
  #130 = Utf8               (Ljava/lang/String;[Ljava/lang/Object;)Ljava/lang/String;
  #131 = Utf8               writeImpl
  #132 = Utf8               count
  #133 = Utf8               resetImpl
  #134 = Utf8               writeToImpl
  #135 = Utf8               close
  #136 = Utf8               addSuppressed
  #137 = Utf8               (Ljava/lang/Throwable;)V
  #138 = Methodref          #149.#150     // java/lang/invoke/LambdaMetafactory.metafactory:(Ljava/lang/invoke/MethodHandles$Lookup;Ljava/lang/String;Ljava/lang/invoke/MethodType;Ljava/lang/invoke/MethodType;Ljava/lang/invoke/MethodHandle;Ljava/lang/invoke/MethodType;)Ljava/lang/invoke/CallSite;
  #139 = Utf8               ([BII)Ljava/io/InputStream;
  #140 = Methodref          #151.#152     // org/apache/commons/io/input/UnsynchronizedByteArrayInputStream."<init>":([BII)V
  #141 = Utf8               ([BII)Lorg/apache/commons/io/input/UnsynchronizedByteArrayInputStream;
  #142 = Utf8               construct
  #143 = Class              #153          // org/apache/commons/io/output/AbstractByteArrayOutputStream$InputStreamConstructor
  #144 = Utf8               InputStreamConstructor
  #145 = Utf8               InnerClasses
  #146 = Utf8               ()Lorg/apache/commons/io/output/AbstractByteArrayOutputStream$InputStreamConstructor;
  #147 = Utf8               (Lorg/apache/commons/io/output/AbstractByteArrayOutputStream$InputStreamConstructor;)Ljava/io/InputStream;
  #148 = Utf8               toByteArrayImpl
  #149 = Class              #154          // java/lang/invoke/LambdaMetafactory
  #150 = NameAndType        #155:#158     // metafactory:(Ljava/lang/invoke/MethodHandles$Lookup;Ljava/lang/String;Ljava/lang/invoke/MethodType;Ljava/lang/invoke/MethodType;Ljava/lang/invoke/MethodHandle;Ljava/lang/invoke/MethodType;)Ljava/lang/invoke/CallSite;
  #151 = Class              #159          // org/apache/commons/io/input/UnsynchronizedByteArrayInputStream
  #152 = NameAndType        #35:#48       // "<init>":([BII)V
  #153 = Utf8               org/apache/commons/io/output/AbstractByteArrayOutputStream$InputStreamConstructor
  #154 = Utf8               java/lang/invoke/LambdaMetafactory
  #155 = Utf8               metafactory
  #156 = Class              #161          // java/lang/invoke/MethodHandles$Lookup
  #157 = Utf8               Lookup
  #158 = Utf8               (Ljava/lang/invoke/MethodHandles$Lookup;Ljava/lang/String;Ljava/lang/invoke/MethodType;Ljava/lang/invoke/MethodType;Ljava/lang/invoke/MethodHandle;Ljava/lang/invoke/MethodType;)Ljava/lang/invoke/CallSite;
  #159 = Utf8               org/apache/commons/io/input/UnsynchronizedByteArrayInputStream
  #160 = Class              #162          // java/lang/invoke/MethodHandles
  #161 = Utf8               java/lang/invoke/MethodHandles$Lookup
  #162 = Utf8               java/lang/invoke/MethodHandles
{
  public org.apache.commons.io.output.UnsynchronizedByteArrayOutputStream();
    descriptor: ()V
    flags: (0x0001) ACC_PUBLIC
    Code:
      stack=2, locals=1, args_size=1
         0: aload_0
         1: sipush        1024
         4: invokespecial #2                  // Method "<init>":(I)V
         7: return
      LineNumberTable:
        line 38: 0
        line 39: 7
      LocalVariableTable:
        Start  Length  Slot  Name   Signature
            0       8     0  this   Lorg/apache/commons/io/output/UnsynchronizedByteArrayOutputStream;

  public org.apache.commons.io.output.UnsynchronizedByteArrayOutputStream(int);
    descriptor: (I)V
    flags: (0x0001) ACC_PUBLIC
    Code:
      stack=4, locals=2, args_size=2
         0: aload_0
         1: invokespecial #3                  // Method org/apache/commons/io/output/AbstractByteArrayOutputStream."<init>":()V
         4: iload_1
         5: ifge          35
         8: new           #4                  // class java/lang/IllegalArgumentException
        11: dup
        12: new           #5                  // class java/lang/StringBuilder
        15: dup
        16: invokespecial #6                  // Method java/lang/StringBuilder."<init>":()V
        19: ldc           #7                  // String Negative initial size:
        21: invokevirtual #8                  // Method java/lang/StringBuilder.append:(Ljava/lang/String;)Ljava/lang/StringBuilder;
        24: iload_1
        25: invokevirtual #9                  // Method java/lang/StringBuilder.append:(I)Ljava/lang/StringBuilder;
        28: invokevirtual #10                 // Method java/lang/StringBuilder.toString:()Ljava/lang/String;
        31: invokespecial #11                 // Method java/lang/IllegalArgumentException."<init>":(Ljava/lang/String;)V
        34: athrow
        35: aload_0
        36: iload_1
        37: invokevirtual #12                 // Method needNewBuffer:(I)V
        40: return
      LineNumberTable:
        line 47: 0
        line 48: 4
        line 49: 8
        line 51: 35
        line 52: 40
      LocalVariableTable:
        Start  Length  Slot  Name   Signature
            0      41     0  this   Lorg/apache/commons/io/output/UnsynchronizedByteArrayOutputStream;
            0      41     1  size   I
      StackMapTable: number_of_entries = 1
        frame_type = 255 /* full_frame */
          offset_delta = 35
          locals = [ class org/apache/commons/io/output/UnsynchronizedByteArrayOutputStream, int ]
          stack = []

  public void write(byte[], int, int);
    descriptor: ([BII)V
    flags: (0x0001) ACC_PUBLIC
    Code:
      stack=7, locals=4, args_size=4
         0: iload_2
         1: iflt          28
         4: iload_2
         5: aload_1
         6: arraylength
         7: if_icmpgt     28
        10: iload_3
        11: iflt          28
        14: iload_2
        15: iload_3
        16: iadd
        17: aload_1
        18: arraylength
        19: if_icmpgt     28
        22: iload_2
        23: iload_3
        24: iadd
        25: ifge          59
        28: new           #13                 // class java/lang/IndexOutOfBoundsException
        31: dup
        32: ldc           #14                 // String offset=%,d, length=%,d
        34: iconst_2
        35: anewarray     #15                 // class java/lang/Object
        38: dup
        39: iconst_0
        40: iload_2
        41: invokestatic  #16                 // Method java/lang/Integer.valueOf:(I)Ljava/lang/Integer;
        44: aastore
        45: dup
        46: iconst_1
        47: iload_3
        48: invokestatic  #16                 // Method java/lang/Integer.valueOf:(I)Ljava/lang/Integer;
        51: aastore
        52: invokestatic  #17                 // Method java/lang/String.format:(Ljava/lang/String;[Ljava/lang/Object;)Ljava/lang/String;
        55: invokespecial #18                 // Method java/lang/IndexOutOfBoundsException."<init>":(Ljava/lang/String;)V
        58: athrow
        59: iload_3
        60: ifne          64
        63: return
        64: aload_0
        65: aload_1
        66: iload_2
        67: iload_3
        68: invokevirtual #19                 // Method writeImpl:([BII)V
        71: return
      LineNumberTable:
        line 56: 0
        line 57: 28
        line 58: 59
        line 59: 63
        line 61: 64
        line 62: 71
      LocalVariableTable:
        Start  Length  Slot  Name   Signature
            0      72     0  this   Lorg/apache/commons/io/output/UnsynchronizedByteArrayOutputStream;
            0      72     1     b   [B
            0      72     2   off   I
            0      72     3   len   I
      StackMapTable: number_of_entries = 3
        frame_type = 28 /* same */
        frame_type = 30 /* same */
        frame_type = 4 /* same */

  public void write(int);
    descriptor: (I)V
    flags: (0x0001) ACC_PUBLIC
    Code:
      stack=2, locals=2, args_size=2
         0: aload_0
         1: iload_1
         2: invokevirtual #20                 // Method writeImpl:(I)V
         5: return
      LineNumberTable:
        line 66: 0
        line 67: 5
      LocalVariableTable:
        Start  Length  Slot  Name   Signature
            0       6     0  this   Lorg/apache/commons/io/output/UnsynchronizedByteArrayOutputStream;
            0       6     1     b   I

  public int write(java.io.InputStream) throws java.io.IOException;
    descriptor: (Ljava/io/InputStream;)I
    flags: (0x0001) ACC_PUBLIC
    Code:
      stack=2, locals=2, args_size=2
         0: aload_0
         1: aload_1
         2: invokevirtual #21                 // Method writeImpl:(Ljava/io/InputStream;)I
         5: ireturn
      LineNumberTable:
        line 71: 0
      LocalVariableTable:
        Start  Length  Slot  Name   Signature
            0       6     0  this   Lorg/apache/commons/io/output/UnsynchronizedByteArrayOutputStream;
            0       6     1    in   Ljava/io/InputStream;
    Exceptions:
      throws java.io.IOException

  public int size();
    descriptor: ()I
    flags: (0x0001) ACC_PUBLIC
    Code:
      stack=1, locals=1, args_size=1
         0: aload_0
         1: getfield      #22                 // Field count:I
         4: ireturn
      LineNumberTable:
        line 76: 0
      LocalVariableTable:
        Start  Length  Slot  Name   Signature
            0       5     0  this   Lorg/apache/commons/io/output/UnsynchronizedByteArrayOutputStream;

  public void reset();
    descriptor: ()V
    flags: (0x0001) ACC_PUBLIC
    Code:
      stack=1, locals=1, args_size=1
         0: aload_0
         1: invokevirtual #23                 // Method resetImpl:()V
         4: return
      LineNumberTable:
        line 84: 0
        line 85: 4
      LocalVariableTable:
        Start  Length  Slot  Name   Signature
            0       5     0  this   Lorg/apache/commons/io/output/UnsynchronizedByteArrayOutputStream;

  public void writeTo(java.io.OutputStream) throws java.io.IOException;
    descriptor: (Ljava/io/OutputStream;)V
    flags: (0x0001) ACC_PUBLIC
    Code:
      stack=2, locals=2, args_size=2
         0: aload_0
         1: aload_1
         2: invokevirtual #24                 // Method writeToImpl:(Ljava/io/OutputStream;)V
         5: return
      LineNumberTable:
        line 89: 0
        line 90: 5
      LocalVariableTable:
        Start  Length  Slot  Name   Signature
            0       6     0  this   Lorg/apache/commons/io/output/UnsynchronizedByteArrayOutputStream;
            0       6     1   out   Ljava/io/OutputStream;
    Exceptions:
      throws java.io.IOException

  public static java.io.InputStream toBufferedInputStream(java.io.InputStream) throws java.io.IOException;
    descriptor: (Ljava/io/InputStream;)Ljava/io/InputStream;
    flags: (0x0009) ACC_PUBLIC, ACC_STATIC
    Code:
      stack=2, locals=1, args_size=1
         0: aload_0
         1: sipush        1024
         4: invokestatic  #25                 // Method toBufferedInputStream:(Ljava/io/InputStream;I)Ljava/io/InputStream;
         7: areturn
      LineNumberTable:
        line 110: 0
      LocalVariableTable:
        Start  Length  Slot  Name   Signature
            0       8     0 input   Ljava/io/InputStream;
    Exceptions:
      throws java.io.IOException

  public static java.io.InputStream toBufferedInputStream(java.io.InputStream, int) throws java.io.IOException;
    descriptor: (Ljava/io/InputStream;I)Ljava/io/InputStream;
    flags: (0x0009) ACC_PUBLIC, ACC_STATIC
    Code:
      stack=3, locals=8, args_size=2
         0: new           #26                 // class org/apache/commons/io/output/UnsynchronizedByteArrayOutputStream
         3: dup
         4: iload_1
         5: invokespecial #2                  // Method "<init>":(I)V
         8: astore_2
         9: aconst_null
        10: astore_3
        11: aload_2
        12: aload_0
        13: invokevirtual #27                 // Method write:(Ljava/io/InputStream;)I
        16: pop
        17: aload_2
        18: invokevirtual #28                 // Method toInputStream:()Ljava/io/InputStream;
        21: astore        4
        23: aload_2
        24: ifnull        53
        27: aload_3
        28: ifnull        49
        31: aload_2
        32: invokevirtual #29                 // Method close:()V
        35: goto          53
        38: astore        5
        40: aload_3
        41: aload         5
        43: invokevirtual #31                 // Method java/lang/Throwable.addSuppressed:(Ljava/lang/Throwable;)V
        46: goto          53
        49: aload_2
        50: invokevirtual #29                 // Method close:()V
        53: aload         4
        55: areturn
        56: astore        4
        58: aload         4
        60: astore_3
        61: aload         4
        63: athrow
        64: astore        6
        66: aload_2
        67: ifnull        96
        70: aload_3
        71: ifnull        92
        74: aload_2
        75: invokevirtual #29                 // Method close:()V
        78: goto          96
        81: astore        7
        83: aload_3
        84: aload         7
        86: invokevirtual #31                 // Method java/lang/Throwable.addSuppressed:(Ljava/lang/Throwable;)V
        89: goto          96
        92: aload_2
        93: invokevirtual #29                 // Method close:()V
        96: aload         6
        98: athrow
      Exception table:
         from    to  target type
            31    35    38   Class java/lang/Throwable
            11    23    56   Class java/lang/Throwable
            11    23    64   any
            74    78    81   Class java/lang/Throwable
            56    66    64   any
      LineNumberTable:
        line 133: 0
        line 134: 11
        line 135: 17
        line 136: 23
        line 135: 53
        line 133: 56
        line 136: 64
      LocalVariableTable:
        Start  Length  Slot  Name   Signature
            9      90     2 output   Lorg/apache/commons/io/output/UnsynchronizedByteArrayOutputStream;
            0      99     0 input   Ljava/io/InputStream;
            0      99     1  size   I
      StackMapTable: number_of_entries = 8
        frame_type = 255 /* full_frame */
          offset_delta = 38
          locals = [ class java/io/InputStream, int, class org/apache/commons/io/output/UnsynchronizedByteArrayOutputStream, class java/lang/Throwable, class java/io/InputStream ]
          stack = [ class java/lang/Throwable ]
        frame_type = 10 /* same */
        frame_type = 3 /* same */
        frame_type = 255 /* full_frame */
          offset_delta = 2
          locals = [ class java/io/InputStream, int, class org/apache/commons/io/output/UnsynchronizedByteArrayOutputStream, class java/lang/Throwable ]
          stack = [ class java/lang/Throwable ]
        frame_type = 71 /* same_locals_1_stack_item */
          stack = [ class java/lang/Throwable ]
        frame_type = 255 /* full_frame */
          offset_delta = 16
          locals = [ class java/io/InputStream, int, class org/apache/commons/io/output/UnsynchronizedByteArrayOutputStream, class java/lang/Throwable, top, top, class java/lang/Throwable ]
          stack = [ class java/lang/Throwable ]
        frame_type = 10 /* same */
        frame_type = 3 /* same */
    Exceptions:
      throws java.io.IOException

  public java.io.InputStream toInputStream();
    descriptor: ()Ljava/io/InputStream;
    flags: (0x0001) ACC_PUBLIC
    Code:
      stack=2, locals=1, args_size=1
         0: aload_0
         1: invokedynamic #32,  0             // InvokeDynamic #0:construct:()Lorg/apache/commons/io/output/AbstractByteArrayOutputStream$InputStreamConstructor;
         6: invokevirtual #33                 // Method toInputStream:(Lorg/apache/commons/io/output/AbstractByteArrayOutputStream$InputStreamConstructor;)Ljava/io/InputStream;
         9: areturn
      LineNumberTable:
        line 141: 0
      LocalVariableTable:
        Start  Length  Slot  Name   Signature
            0      10     0  this   Lorg/apache/commons/io/output/UnsynchronizedByteArrayOutputStream;

  public byte[] toByteArray();
    descriptor: ()[B
    flags: (0x0001) ACC_PUBLIC
    Code:
      stack=1, locals=1, args_size=1
         0: aload_0
         1: invokevirtual #34                 // Method toByteArrayImpl:()[B
         4: areturn
      LineNumberTable:
        line 146: 0
      LocalVariableTable:
        Start  Length  Slot  Name   Signature
            0       5     0  this   Lorg/apache/commons/io/output/UnsynchronizedByteArrayOutputStream;
}
SourceFile: "UnsynchronizedByteArrayOutputStream.java"
InnerClasses:
  protected static #144= #143 of #1;      // InputStreamConstructor=class org/apache/commons/io/output/AbstractByteArrayOutputStream$InputStreamConstructor of class org/apache/commons/io/output/AbstractByteArrayOutputStream
  public static final #157= #156 of #160; // Lookup=class java/lang/invoke/MethodHandles$Lookup of class java/lang/invoke/MethodHandles
BootstrapMethods:
  0: #109 REF_invokeStatic java/lang/invoke/LambdaMetafactory.metafactory:(Ljava/lang/invoke/MethodHandles$Lookup;Ljava/lang/String;Ljava/lang/invoke/MethodType;Ljava/lang/invoke/MethodType;Ljava/lang/invoke/MethodHandle;Ljava/lang/invoke/MethodType;)Ljava/lang/invoke/CallSite;
    Method arguments:
      #110 ([BII)Ljava/io/InputStream;
      #111 REF_newInvokeSpecial org/apache/commons/io/input/UnsynchronizedByteArrayInputStream."<init>":([BII)V
      #112 ([BII)Lorg/apache/commons/io/input/UnsynchronizedByteArrayInputStream;
