Classfile /Users/mw/Projects/slang-braindump/.jar/jar11/assemble/slang-braindump/assemble/content/scala/util/control/ControlThrowable.class
  Last modified May 29, 2022; size 952 bytes
  SHA-256 checksum 8b21d7cb72837c8d464a11e89107366967d7ec926dfa2cc06ef267cefd31f787
  Compiled from "ControlThrowable.scala"
public abstract class scala.util.control.ControlThrowable extends java.lang.Throwable
  minor version: 0
  major version: 52
  flags: (0x0421) ACC_PUBLIC, ACC_SUPER, ACC_ABSTRACT
  this_class: #2                          // scala/util/control/ControlThrowable
  super_class: #4                         // java/lang/Throwable
  interfaces: 0, fields: 0, methods: 2, attributes: 4
Constant pool:
   #1 = Utf8               scala/util/control/ControlThrowable
   #2 = Class              #1             // scala/util/control/ControlThrowable
   #3 = Utf8               java/lang/Throwable
   #4 = Class              #3             // java/lang/Throwable
   #5 = Utf8               ControlThrowable.scala
   #6 = Utf8               Lscala/reflect/ScalaSignature;
   #7 = Utf8               bytes
   #8 = Utf8               \u0006\u0005!2Q\u0001B\u0003\u0002\u00021A\u0001\"\u0007\u0001\u0003\u0002\u0003\u0006IA\u0007\u0005\u0006E\u0001!\ta\t\u0005\u0006E\u0001!\ta\n\u0002\u0011\u0007>tGO]8m)\"\u0014xn^1cY\u0016T!AB\u0004\u0002\u000f\r|g\u000e\u001e:pY*\u0011\u0001\"C\u0001\u0005kRLGNC\u0001\u000b\u0003\u0015\u00198-\u00197b\u0007\u0001\u0019\"\u0001A\u0007\u0011\u000591bBA\b\u0015\u001d\t\u00012#D\u0001\u0012\u0015\t\u00112\"\u0001\u0004=e>|GOP\u0005\u0002\u0015%\u0011Q#C\u0001\ba\u0006\u001c7.Y4f\u0013\t9\u0002DA\u0005UQJ|w/\u00192mK*\u0011Q#C\u0001\b[\u0016\u001c8/Y4f!\tYrD\u0004\u0002\u001d;A\u0011\u0001#C\u0005\u0003=%\ta\u0001\u0015:fI\u00164\u0017B\u0001\u0011\"\u0005\u0019\u0019FO]5oO*\u0011a$C\u0001\u0007y%t\u0017\u000e\u001e \u0015\u0005\u00112\u0003CA\u0013\u0001\u001b\u0005)\u0001\"B\r\u0003\u0001\u0004QB#\u0001\u0013
   #9 = Utf8               <init>
  #10 = Utf8               (Ljava/lang/String;)V
  #11 = Utf8               message
  #12 = Utf8               (Ljava/lang/String;Ljava/lang/Throwable;ZZ)V
  #13 = NameAndType        #9:#12         // "<init>":(Ljava/lang/String;Ljava/lang/Throwable;ZZ)V
  #14 = Methodref          #4.#13         // java/lang/Throwable."<init>":(Ljava/lang/String;Ljava/lang/Throwable;ZZ)V
  #15 = Utf8               this
  #16 = Utf8               Lscala/util/control/ControlThrowable;
  #17 = Utf8               Ljava/lang/String;
  #18 = Utf8               ()V
  #19 = NameAndType        #9:#10         // "<init>":(Ljava/lang/String;)V
  #20 = Methodref          #2.#19         // scala/util/control/ControlThrowable."<init>":(Ljava/lang/String;)V
  #21 = Utf8               Code
  #22 = Utf8               LineNumberTable
  #23 = Utf8               LocalVariableTable
  #24 = Utf8               MethodParameters
  #25 = Utf8               SourceFile
  #26 = Utf8               RuntimeVisibleAnnotations
  #27 = Utf8               ScalaInlineInfo
  #28 = Utf8               ScalaSig
{
  public scala.util.control.ControlThrowable(java.lang.String);
    descriptor: (Ljava/lang/String;)V
    flags: (0x0001) ACC_PUBLIC
    Code:
      stack=5, locals=2, args_size=2
         0: aload_0
         1: aload_1
         2: aconst_null
         3: iconst_0
         4: iconst_0
         5: invokespecial #14                 // Method java/lang/Throwable."<init>":(Ljava/lang/String;Ljava/lang/Throwable;ZZ)V
         8: return
      LineNumberTable:
        line 43: 0
        line 44: 1
        line 43: 8
      LocalVariableTable:
        Start  Length  Slot  Name   Signature
            0       9     0  this   Lscala/util/control/ControlThrowable;
            0       9     1 message   Ljava/lang/String;
    MethodParameters:
      Name                           Flags
      message                        final

  public scala.util.control.ControlThrowable();
    descriptor: ()V
    flags: (0x0001) ACC_PUBLIC
    Code:
      stack=2, locals=1, args_size=1
         0: aload_0
         1: aconst_null
         2: invokespecial #20                 // Method "<init>":(Ljava/lang/String;)V
         5: return
      LineNumberTable:
        line 46: 0
      LocalVariableTable:
        Start  Length  Slot  Name   Signature
            0       6     0  this   Lscala/util/control/ControlThrowable;
}
SourceFile: "ControlThrowable.scala"
RuntimeVisibleAnnotations:
  0: #6(#7=s#8)
    scala.reflect.ScalaSignature(
      bytes="\u0006\u0005!2Q\u0001B\u0003\u0002\u00021A\u0001\"\u0007\u0001\u0003\u0002\u0003\u0006IA\u0007\u0005\u0006E\u0001!\ta\t\u0005\u0006E\u0001!\ta\n\u0002\u0011\u0007>tGO]8m)\"\u0014xn^1cY\u0016T!AB\u0004\u0002\u000f\r|g\u000e\u001e:pY*\u0011\u0001\"C\u0001\u0005kRLGNC\u0001\u000b\u0003\u0015\u00198-\u00197b\u0007\u0001\u0019\"\u0001A\u0007\u0011\u000591bBA\b\u0015\u001d\t\u00012#D\u0001\u0012\u0015\t\u00112\"\u0001\u0004=e>|GOP\u0005\u0002\u0015%\u0011Q#C\u0001\ba\u0006\u001c7.Y4f\u0013\t9\u0002DA\u0005UQJ|w/\u00192mK*\u0011Q#C\u0001\b[\u0016\u001c8/Y4f!\tYrD\u0004\u0002\u001d;A\u0011\u0001#C\u0005\u0003=%\ta\u0001\u0015:fI\u00164\u0017B\u0001\u0011\"\u0005\u0019\u0019FO]5oO*\u0011a$C\u0001\u0007y%t\u0017\u000e\u001e \u0015\u0005\u00112\u0003CA\u0013\u0001\u001b\u0005)\u0001\"B\r\u0003\u0001\u0004QB#\u0001\u0013"
    )
  ScalaInlineInfo: length = 0xE (unknown attribute)
   01 00 00 02 00 09 00 12 00 00 09 00 0A 00
  ScalaSig: length = 0x3 (unknown attribute)
   05 02 00
