Classfile /Users/mw/Projects/slang-braindump/.jar/jar11/assemble/slang-braindump/assemble/content/scala/util/control/Exception$By.class
  Last modified May 29, 2022; size 904 bytes
  SHA-256 checksum 0c32fa0f91578184151fca0b86bc1230613cd3539078d0246688795b52e19ee4
  Compiled from "Exception.scala"
public class scala.util.control.Exception$By<T extends java.lang.Object, R extends java.lang.Object> extends java.lang.Object
  minor version: 0
  major version: 52
  flags: (0x0021) ACC_PUBLIC, ACC_SUPER
  this_class: #2                          // scala/util/control/Exception$By
  super_class: #5                         // java/lang/Object
  interfaces: 0, fields: 1, methods: 2, attributes: 5
Constant pool:
   #1 = Utf8               scala/util/control/Exception$By
   #2 = Class              #1             // scala/util/control/Exception$By
   #3 = Utf8               <T:Ljava/lang/Object;R:Ljava/lang/Object;>Ljava/lang/Object;
   #4 = Utf8               java/lang/Object
   #5 = Class              #4             // java/lang/Object
   #6 = Utf8               Exception.scala
   #7 = Utf8               scala/util/control/Exception
   #8 = Class              #7             // scala/util/control/Exception
   #9 = Utf8               By
  #10 = Utf8               f
  #11 = Utf8               Lscala/Function1;
  #12 = Utf8               Lscala/Function1<TT;TR;>;
  #13 = Utf8               by
  #14 = Utf8               (Ljava/lang/Object;)Ljava/lang/Object;
  #15 = Utf8               (TT;)TR;
  #16 = Utf8               x
  #17 = NameAndType        #10:#11        // f:Lscala/Function1;
  #18 = Fieldref           #2.#17         // scala/util/control/Exception$By.f:Lscala/Function1;
  #19 = Utf8               scala/Function1
  #20 = Class              #19            // scala/Function1
  #21 = Utf8               apply
  #22 = NameAndType        #21:#14        // apply:(Ljava/lang/Object;)Ljava/lang/Object;
  #23 = InterfaceMethodref #20.#22        // scala/Function1.apply:(Ljava/lang/Object;)Ljava/lang/Object;
  #24 = Utf8               this
  #25 = Utf8               Lscala/util/control/Exception$By;
  #26 = Utf8               Ljava/lang/Object;
  #27 = Utf8               <init>
  #28 = Utf8               (Lscala/Function1;)V
  #29 = Utf8               (Lscala/Function1<TT;TR;>;)V
  #30 = Utf8               ()V
  #31 = NameAndType        #27:#30        // "<init>":()V
  #32 = Methodref          #5.#31         // java/lang/Object."<init>":()V
  #33 = Utf8               Signature
  #34 = Utf8               Code
  #35 = Utf8               LineNumberTable
  #36 = Utf8               LocalVariableTable
  #37 = Utf8               MethodParameters
  #38 = Utf8               InnerClasses
  #39 = Utf8               SourceFile
  #40 = Utf8               ScalaInlineInfo
  #41 = Utf8               Scala
{
  private final scala.Function1<T, R> f;
    descriptor: Lscala/Function1;
    flags: (0x0012) ACC_PRIVATE, ACC_FINAL
    Signature: #12                          // Lscala/Function1<TT;TR;>;

  public R by(T);
    descriptor: (Ljava/lang/Object;)Ljava/lang/Object;
    flags: (0x0001) ACC_PUBLIC
    Code:
      stack=2, locals=2, args_size=2
         0: aload_0
         1: getfield      #18                 // Field f:Lscala/Function1;
         4: aload_1
         5: invokeinterface #23,  2           // InterfaceMethod scala/Function1.apply:(Ljava/lang/Object;)Ljava/lang/Object;
        10: areturn
      LineNumberTable:
        line 335: 0
      LocalVariableTable:
        Start  Length  Slot  Name   Signature
            0      11     0  this   Lscala/util/control/Exception$By;
            0      11     1     x   Ljava/lang/Object;
    Signature: #15                          // (TT;)TR;
    MethodParameters:
      Name                           Flags
      x                              final

  public scala.util.control.Exception$By(scala.Function1<T, R>);
    descriptor: (Lscala/Function1;)V
    flags: (0x0001) ACC_PUBLIC
    Code:
      stack=2, locals=2, args_size=2
         0: aload_0
         1: aload_1
         2: putfield      #18                 // Field f:Lscala/Function1;
         5: aload_0
         6: invokespecial #32                 // Method java/lang/Object."<init>":()V
         9: return
      LineNumberTable:
        line 334: 0
      LocalVariableTable:
        Start  Length  Slot  Name   Signature
            0      10     0  this   Lscala/util/control/Exception$By;
            0      10     1     f   Lscala/Function1;
    Signature: #29                          // (Lscala/Function1<TT;TR;>;)V
    MethodParameters:
      Name                           Flags
      f                              final
}
InnerClasses:
  public static #9= #2 of #8;             // By=class scala/util/control/Exception$By of class scala/util/control/Exception
Signature: #3                           // <T:Ljava/lang/Object;R:Ljava/lang/Object;>Ljava/lang/Object;
SourceFile: "Exception.scala"
  ScalaInlineInfo: length = 0xE (unknown attribute)
   01 00 00 02 00 1B 00 1C 00 00 0D 00 0E 00
  Scala: length = 0x0 (unknown attribute)

