Classfile /Users/mw/Projects/slang-braindump/.jar/jar8/assemble/slang-braindump/assemble/content/org/apache/commons/io/input/BoundedInputStream.class
  Last modified May 29, 2022; size 2568 bytes
  SHA-256 checksum 7f1ee9f1350cfb412b28ad179acc83609f462a56e25176de4e10ed3198b11258
  Compiled from "BoundedInputStream.java"
public class org.apache.commons.io.input.BoundedInputStream extends java.io.InputStream
  minor version: 0
  major version: 52
  flags: (0x0021) ACC_PUBLIC, ACC_SUPER
  this_class: #22                         // org/apache/commons/io/input/BoundedInputStream
  super_class: #23                        // java/io/InputStream
  interfaces: 0, fields: 5, methods: 14, attributes: 1
Constant pool:
    #1 = Class              #76           // org/apache/commons/io/IOUtils
    #2 = Methodref          #23.#77       // java/io/InputStream."<init>":()V
    #3 = Fieldref           #22.#78       // org/apache/commons/io/input/BoundedInputStream.pos:J
    #4 = Long               -1l
    #6 = Fieldref           #22.#79       // org/apache/commons/io/input/BoundedInputStream.mark:J
    #7 = Fieldref           #22.#80       // org/apache/commons/io/input/BoundedInputStream.propagateClose:Z
    #8 = Fieldref           #22.#81       // org/apache/commons/io/input/BoundedInputStream.max:J
    #9 = Fieldref           #22.#82       // org/apache/commons/io/input/BoundedInputStream.in:Ljava/io/InputStream;
   #10 = Methodref          #22.#83       // org/apache/commons/io/input/BoundedInputStream."<init>":(Ljava/io/InputStream;J)V
   #11 = Methodref          #23.#84       // java/io/InputStream.read:()I
   #12 = Methodref          #22.#85       // org/apache/commons/io/input/BoundedInputStream.read:([BII)I
   #13 = Methodref          #86.#87       // java/lang/Math.min:(JJ)J
   #14 = Methodref          #23.#85       // java/io/InputStream.read:([BII)I
   #15 = Methodref          #23.#88       // java/io/InputStream.skip:(J)J
   #16 = Methodref          #23.#89       // java/io/InputStream.available:()I
   #17 = Methodref          #90.#91       // java/lang/Object.toString:()Ljava/lang/String;
   #18 = Methodref          #23.#92       // java/io/InputStream.close:()V
   #19 = Methodref          #23.#93       // java/io/InputStream.reset:()V
   #20 = Methodref          #23.#94       // java/io/InputStream.mark:(I)V
   #21 = Methodref          #23.#95       // java/io/InputStream.markSupported:()Z
   #22 = Class              #96           // org/apache/commons/io/input/BoundedInputStream
   #23 = Class              #97           // java/io/InputStream
   #24 = Utf8               in
   #25 = Utf8               Ljava/io/InputStream;
   #26 = Utf8               max
   #27 = Utf8               J
   #28 = Utf8               pos
   #29 = Utf8               mark
   #30 = Utf8               propagateClose
   #31 = Utf8               Z
   #32 = Utf8               <init>
   #33 = Utf8               (Ljava/io/InputStream;J)V
   #34 = Utf8               Code
   #35 = Utf8               LineNumberTable
   #36 = Utf8               LocalVariableTable
   #37 = Utf8               this
   #38 = Utf8               Lorg/apache/commons/io/input/BoundedInputStream;
   #39 = Utf8               size
   #40 = Utf8               (Ljava/io/InputStream;)V
   #41 = Utf8               read
   #42 = Utf8               ()I
   #43 = Utf8               result
   #44 = Utf8               I
   #45 = Utf8               StackMapTable
   #46 = Utf8               Exceptions
   #47 = Class              #98           // java/io/IOException
   #48 = Utf8               ([B)I
   #49 = Utf8               b
   #50 = Utf8               [B
   #51 = Utf8               ([BII)I
   #52 = Utf8               off
   #53 = Utf8               len
   #54 = Utf8               maxRead
   #55 = Utf8               bytesRead
   #56 = Utf8               skip
   #57 = Utf8               (J)J
   #58 = Utf8               n
   #59 = Utf8               toSkip
   #60 = Utf8               skippedBytes
   #61 = Utf8               available
   #62 = Utf8               toString
   #63 = Utf8               ()Ljava/lang/String;
   #64 = Utf8               close
   #65 = Utf8               ()V
   #66 = Utf8               reset
   #67 = Utf8               (I)V
   #68 = Utf8               readlimit
   #69 = Utf8               markSupported
   #70 = Utf8               ()Z
   #71 = Utf8               isPropagateClose
   #72 = Utf8               setPropagateClose
   #73 = Utf8               (Z)V
   #74 = Utf8               SourceFile
   #75 = Utf8               BoundedInputStream.java
   #76 = Utf8               org/apache/commons/io/IOUtils
   #77 = NameAndType        #32:#65       // "<init>":()V
   #78 = NameAndType        #28:#27       // pos:J
   #79 = NameAndType        #29:#27       // mark:J
   #80 = NameAndType        #30:#31       // propagateClose:Z
   #81 = NameAndType        #26:#27       // max:J
   #82 = NameAndType        #24:#25       // in:Ljava/io/InputStream;
   #83 = NameAndType        #32:#33       // "<init>":(Ljava/io/InputStream;J)V
   #84 = NameAndType        #41:#42       // read:()I
   #85 = NameAndType        #41:#51       // read:([BII)I
   #86 = Class              #99           // java/lang/Math
   #87 = NameAndType        #100:#101     // min:(JJ)J
   #88 = NameAndType        #56:#57       // skip:(J)J
   #89 = NameAndType        #61:#42       // available:()I
   #90 = Class              #102          // java/lang/Object
   #91 = NameAndType        #62:#63       // toString:()Ljava/lang/String;
   #92 = NameAndType        #64:#65       // close:()V
   #93 = NameAndType        #66:#65       // reset:()V
   #94 = NameAndType        #29:#67       // mark:(I)V
   #95 = NameAndType        #69:#70       // markSupported:()Z
   #96 = Utf8               org/apache/commons/io/input/BoundedInputStream
   #97 = Utf8               java/io/InputStream
   #98 = Utf8               java/io/IOException
   #99 = Utf8               java/lang/Math
  #100 = Utf8               min
  #101 = Utf8               (JJ)J
  #102 = Utf8               java/lang/Object
{
  private final java.io.InputStream in;
    descriptor: Ljava/io/InputStream;
    flags: (0x0012) ACC_PRIVATE, ACC_FINAL

  private final long max;
    descriptor: J
    flags: (0x0012) ACC_PRIVATE, ACC_FINAL

  private long pos;
    descriptor: J
    flags: (0x0002) ACC_PRIVATE

  private long mark;
    descriptor: J
    flags: (0x0002) ACC_PRIVATE

  private boolean propagateClose;
    descriptor: Z
    flags: (0x0002) ACC_PRIVATE

  public org.apache.commons.io.input.BoundedInputStream(java.io.InputStream, long);
    descriptor: (Ljava/io/InputStream;J)V
    flags: (0x0001) ACC_PUBLIC
    Code:
      stack=3, locals=4, args_size=3
         0: aload_0
         1: invokespecial #2                  // Method java/io/InputStream."<init>":()V
         4: aload_0
         5: lconst_0
         6: putfield      #3                  // Field pos:J
         9: aload_0
        10: ldc2_w        #4                  // long -1l
        13: putfield      #6                  // Field mark:J
        16: aload_0
        17: iconst_1
        18: putfield      #7                  // Field propagateClose:Z
        21: aload_0
        22: lload_2
        23: putfield      #8                  // Field max:J
        26: aload_0
        27: aload_1
        28: putfield      #9                  // Field in:Ljava/io/InputStream;
        31: return
      LineNumberTable:
        line 61: 0
        line 46: 4
        line 49: 9
        line 52: 16
        line 64: 21
        line 65: 26
        line 66: 31
      LocalVariableTable:
        Start  Length  Slot  Name   Signature
            0      32     0  this   Lorg/apache/commons/io/input/BoundedInputStream;
            0      32     1    in   Ljava/io/InputStream;
            0      32     2  size   J

  public org.apache.commons.io.input.BoundedInputStream(java.io.InputStream);
    descriptor: (Ljava/io/InputStream;)V
    flags: (0x0001) ACC_PUBLIC
    Code:
      stack=4, locals=2, args_size=2
         0: aload_0
         1: aload_1
         2: ldc2_w        #4                  // long -1l
         5: invokespecial #10                 // Method "<init>":(Ljava/io/InputStream;J)V
         8: return
      LineNumberTable:
        line 75: 0
        line 76: 8
      LocalVariableTable:
        Start  Length  Slot  Name   Signature
            0       9     0  this   Lorg/apache/commons/io/input/BoundedInputStream;
            0       9     1    in   Ljava/io/InputStream;

  public int read() throws java.io.IOException;
    descriptor: ()I
    flags: (0x0001) ACC_PUBLIC
    Code:
      stack=5, locals=2, args_size=1
         0: aload_0
         1: getfield      #8                  // Field max:J
         4: lconst_0
         5: lcmp
         6: iflt          23
         9: aload_0
        10: getfield      #3                  // Field pos:J
        13: aload_0
        14: getfield      #8                  // Field max:J
        17: lcmp
        18: iflt          23
        21: iconst_m1
        22: ireturn
        23: aload_0
        24: getfield      #9                  // Field in:Ljava/io/InputStream;
        27: invokevirtual #11                 // Method java/io/InputStream.read:()I
        30: istore_1
        31: aload_0
        32: dup
        33: getfield      #3                  // Field pos:J
        36: lconst_1
        37: ladd
        38: putfield      #3                  // Field pos:J
        41: iload_1
        42: ireturn
      LineNumberTable:
        line 87: 0
        line 88: 21
        line 90: 23
        line 91: 31
        line 92: 41
      LocalVariableTable:
        Start  Length  Slot  Name   Signature
            0      43     0  this   Lorg/apache/commons/io/input/BoundedInputStream;
           31      12     1 result   I
      StackMapTable: number_of_entries = 1
        frame_type = 23 /* same */
    Exceptions:
      throws java.io.IOException

  public int read(byte[]) throws java.io.IOException;
    descriptor: ([B)I
    flags: (0x0001) ACC_PUBLIC
    Code:
      stack=4, locals=2, args_size=2
         0: aload_0
         1: aload_1
         2: iconst_0
         3: aload_1
         4: arraylength
         5: invokevirtual #12                 // Method read:([BII)I
         8: ireturn
      LineNumberTable:
        line 104: 0
      LocalVariableTable:
        Start  Length  Slot  Name   Signature
            0       9     0  this   Lorg/apache/commons/io/input/BoundedInputStream;
            0       9     1     b   [B
    Exceptions:
      throws java.io.IOException

  public int read(byte[], int, int) throws java.io.IOException;
    descriptor: ([BII)I
    flags: (0x0001) ACC_PUBLIC
    Code:
      stack=6, locals=7, args_size=4
         0: aload_0
         1: getfield      #8                  // Field max:J
         4: lconst_0
         5: lcmp
         6: iflt          23
         9: aload_0
        10: getfield      #3                  // Field pos:J
        13: aload_0
        14: getfield      #8                  // Field max:J
        17: lcmp
        18: iflt          23
        21: iconst_m1
        22: ireturn
        23: aload_0
        24: getfield      #8                  // Field max:J
        27: lconst_0
        28: lcmp
        29: iflt          49
        32: iload_3
        33: i2l
        34: aload_0
        35: getfield      #8                  // Field max:J
        38: aload_0
        39: getfield      #3                  // Field pos:J
        42: lsub
        43: invokestatic  #13                 // Method java/lang/Math.min:(JJ)J
        46: goto          51
        49: iload_3
        50: i2l
        51: lstore        4
        53: aload_0
        54: getfield      #9                  // Field in:Ljava/io/InputStream;
        57: aload_1
        58: iload_2
        59: lload         4
        61: l2i
        62: invokevirtual #14                 // Method java/io/InputStream.read:([BII)I
        65: istore        6
        67: iload         6
        69: iconst_m1
        70: if_icmpne     75
        73: iconst_m1
        74: ireturn
        75: aload_0
        76: dup
        77: getfield      #3                  // Field pos:J
        80: iload         6
        82: i2l
        83: ladd
        84: putfield      #3                  // Field pos:J
        87: iload         6
        89: ireturn
      LineNumberTable:
        line 118: 0
        line 119: 21
        line 121: 23
        line 122: 53
        line 124: 67
        line 125: 73
        line 128: 75
        line 129: 87
      LocalVariableTable:
        Start  Length  Slot  Name   Signature
            0      90     0  this   Lorg/apache/commons/io/input/BoundedInputStream;
            0      90     1     b   [B
            0      90     2   off   I
            0      90     3   len   I
           53      37     4 maxRead   J
           67      23     6 bytesRead   I
      StackMapTable: number_of_entries = 4
        frame_type = 23 /* same */
        frame_type = 25 /* same */
        frame_type = 65 /* same_locals_1_stack_item */
          stack = [ long ]
        frame_type = 253 /* append */
          offset_delta = 23
          locals = [ long, int ]
    Exceptions:
      throws java.io.IOException

  public long skip(long) throws java.io.IOException;
    descriptor: (J)J
    flags: (0x0001) ACC_PUBLIC
    Code:
      stack=6, locals=7, args_size=2
         0: aload_0
         1: getfield      #8                  // Field max:J
         4: lconst_0
         5: lcmp
         6: iflt          25
         9: lload_1
        10: aload_0
        11: getfield      #8                  // Field max:J
        14: aload_0
        15: getfield      #3                  // Field pos:J
        18: lsub
        19: invokestatic  #13                 // Method java/lang/Math.min:(JJ)J
        22: goto          26
        25: lload_1
        26: lstore_3
        27: aload_0
        28: getfield      #9                  // Field in:Ljava/io/InputStream;
        31: lload_3
        32: invokevirtual #15                 // Method java/io/InputStream.skip:(J)J
        35: lstore        5
        37: aload_0
        38: dup
        39: getfield      #3                  // Field pos:J
        42: lload         5
        44: ladd
        45: putfield      #3                  // Field pos:J
        48: lload         5
        50: lreturn
      LineNumberTable:
        line 140: 0
        line 141: 27
        line 142: 37
        line 143: 48
      LocalVariableTable:
        Start  Length  Slot  Name   Signature
            0      51     0  this   Lorg/apache/commons/io/input/BoundedInputStream;
            0      51     1     n   J
           27      24     3 toSkip   J
           37      14     5 skippedBytes   J
      StackMapTable: number_of_entries = 2
        frame_type = 25 /* same */
        frame_type = 64 /* same_locals_1_stack_item */
          stack = [ long ]
    Exceptions:
      throws java.io.IOException

  public int available() throws java.io.IOException;
    descriptor: ()I
    flags: (0x0001) ACC_PUBLIC
    Code:
      stack=4, locals=1, args_size=1
         0: aload_0
         1: getfield      #8                  // Field max:J
         4: lconst_0
         5: lcmp
         6: iflt          23
         9: aload_0
        10: getfield      #3                  // Field pos:J
        13: aload_0
        14: getfield      #8                  // Field max:J
        17: lcmp
        18: iflt          23
        21: iconst_0
        22: ireturn
        23: aload_0
        24: getfield      #9                  // Field in:Ljava/io/InputStream;
        27: invokevirtual #16                 // Method java/io/InputStream.available:()I
        30: ireturn
      LineNumberTable:
        line 151: 0
        line 152: 21
        line 154: 23
      LocalVariableTable:
        Start  Length  Slot  Name   Signature
            0      31     0  this   Lorg/apache/commons/io/input/BoundedInputStream;
      StackMapTable: number_of_entries = 1
        frame_type = 23 /* same */
    Exceptions:
      throws java.io.IOException

  public java.lang.String toString();
    descriptor: ()Ljava/lang/String;
    flags: (0x0001) ACC_PUBLIC
    Code:
      stack=1, locals=1, args_size=1
         0: aload_0
         1: getfield      #9                  // Field in:Ljava/io/InputStream;
         4: invokevirtual #17                 // Method java/lang/Object.toString:()Ljava/lang/String;
         7: areturn
      LineNumberTable:
        line 163: 0
      LocalVariableTable:
        Start  Length  Slot  Name   Signature
            0       8     0  this   Lorg/apache/commons/io/input/BoundedInputStream;

  public void close() throws java.io.IOException;
    descriptor: ()V
    flags: (0x0001) ACC_PUBLIC
    Code:
      stack=1, locals=1, args_size=1
         0: aload_0
         1: getfield      #7                  // Field propagateClose:Z
         4: ifeq          14
         7: aload_0
         8: getfield      #9                  // Field in:Ljava/io/InputStream;
        11: invokevirtual #18                 // Method java/io/InputStream.close:()V
        14: return
      LineNumberTable:
        line 173: 0
        line 174: 7
        line 176: 14
      LocalVariableTable:
        Start  Length  Slot  Name   Signature
            0      15     0  this   Lorg/apache/commons/io/input/BoundedInputStream;
      StackMapTable: number_of_entries = 1
        frame_type = 14 /* same */
    Exceptions:
      throws java.io.IOException

  public synchronized void reset() throws java.io.IOException;
    descriptor: ()V
    flags: (0x0021) ACC_PUBLIC, ACC_SYNCHRONIZED
    Code:
      stack=3, locals=1, args_size=1
         0: aload_0
         1: getfield      #9                  // Field in:Ljava/io/InputStream;
         4: invokevirtual #19                 // Method java/io/InputStream.reset:()V
         7: aload_0
         8: aload_0
         9: getfield      #6                  // Field mark:J
        12: putfield      #3                  // Field pos:J
        15: return
      LineNumberTable:
        line 184: 0
        line 185: 7
        line 186: 15
      LocalVariableTable:
        Start  Length  Slot  Name   Signature
            0      16     0  this   Lorg/apache/commons/io/input/BoundedInputStream;
    Exceptions:
      throws java.io.IOException

  public synchronized void mark(int);
    descriptor: (I)V
    flags: (0x0021) ACC_PUBLIC, ACC_SYNCHRONIZED
    Code:
      stack=3, locals=2, args_size=2
         0: aload_0
         1: getfield      #9                  // Field in:Ljava/io/InputStream;
         4: iload_1
         5: invokevirtual #20                 // Method java/io/InputStream.mark:(I)V
         8: aload_0
         9: aload_0
        10: getfield      #3                  // Field pos:J
        13: putfield      #6                  // Field mark:J
        16: return
      LineNumberTable:
        line 194: 0
        line 195: 8
        line 196: 16
      LocalVariableTable:
        Start  Length  Slot  Name   Signature
            0      17     0  this   Lorg/apache/commons/io/input/BoundedInputStream;
            0      17     1 readlimit   I

  public boolean markSupported();
    descriptor: ()Z
    flags: (0x0001) ACC_PUBLIC
    Code:
      stack=1, locals=1, args_size=1
         0: aload_0
         1: getfield      #9                  // Field in:Ljava/io/InputStream;
         4: invokevirtual #21                 // Method java/io/InputStream.markSupported:()Z
         7: ireturn
      LineNumberTable:
        line 204: 0
      LocalVariableTable:
        Start  Length  Slot  Name   Signature
            0       8     0  this   Lorg/apache/commons/io/input/BoundedInputStream;

  public boolean isPropagateClose();
    descriptor: ()Z
    flags: (0x0001) ACC_PUBLIC
    Code:
      stack=1, locals=1, args_size=1
         0: aload_0
         1: getfield      #7                  // Field propagateClose:Z
         4: ireturn
      LineNumberTable:
        line 216: 0
      LocalVariableTable:
        Start  Length  Slot  Name   Signature
            0       5     0  this   Lorg/apache/commons/io/input/BoundedInputStream;

  public void setPropagateClose(boolean);
    descriptor: (Z)V
    flags: (0x0001) ACC_PUBLIC
    Code:
      stack=2, locals=2, args_size=2
         0: aload_0
         1: iload_1
         2: putfield      #7                  // Field propagateClose:Z
         5: return
      LineNumberTable:
        line 229: 0
        line 230: 5
      LocalVariableTable:
        Start  Length  Slot  Name   Signature
            0       6     0  this   Lorg/apache/commons/io/input/BoundedInputStream;
            0       6     1 propagateClose   Z
}
SourceFile: "BoundedInputStream.java"
