Classfile /Users/mw/Projects/slang-braindump/.jar/jar8/assemble/slang-braindump/assemble/content/org/apache/commons/io/input/DemuxInputStream.class
  Last modified May 29, 2022; size 1216 bytes
  SHA-256 checksum 5d271aef0fee27a75c9e6cc567d770df24fa81fd969f45d207446fc2e8bdf75b
  Compiled from "DemuxInputStream.java"
public class org.apache.commons.io.input.DemuxInputStream extends java.io.InputStream
  minor version: 0
  major version: 52
  flags: (0x0021) ACC_PUBLIC, ACC_SUPER
  this_class: #12                         // org/apache/commons/io/input/DemuxInputStream
  super_class: #7                         // java/io/InputStream
  interfaces: 0, fields: 1, methods: 4, attributes: 1
Constant pool:
   #1 = Class              #38            // org/apache/commons/io/IOUtils
   #2 = Methodref          #7.#39         // java/io/InputStream."<init>":()V
   #3 = Class              #40            // java/lang/InheritableThreadLocal
   #4 = Methodref          #3.#39         // java/lang/InheritableThreadLocal."<init>":()V
   #5 = Fieldref           #12.#41        // org/apache/commons/io/input/DemuxInputStream.inputStream:Ljava/lang/InheritableThreadLocal;
   #6 = Methodref          #3.#42         // java/lang/InheritableThreadLocal.get:()Ljava/lang/Object;
   #7 = Class              #43            // java/io/InputStream
   #8 = Methodref          #3.#44         // java/lang/InheritableThreadLocal.set:(Ljava/lang/Object;)V
   #9 = Class              #45            // java/io/Closeable
  #10 = Methodref          #1.#46         // org/apache/commons/io/IOUtils.close:(Ljava/io/Closeable;)V
  #11 = Methodref          #7.#47         // java/io/InputStream.read:()I
  #12 = Class              #48            // org/apache/commons/io/input/DemuxInputStream
  #13 = Utf8               inputStream
  #14 = Utf8               Ljava/lang/InheritableThreadLocal;
  #15 = Utf8               Signature
  #16 = Utf8               Ljava/lang/InheritableThreadLocal<Ljava/io/InputStream;>;
  #17 = Utf8               <init>
  #18 = Utf8               ()V
  #19 = Utf8               Code
  #20 = Utf8               LineNumberTable
  #21 = Utf8               LocalVariableTable
  #22 = Utf8               this
  #23 = Utf8               Lorg/apache/commons/io/input/DemuxInputStream;
  #24 = Utf8               bindStream
  #25 = Utf8               (Ljava/io/InputStream;)Ljava/io/InputStream;
  #26 = Utf8               input
  #27 = Utf8               Ljava/io/InputStream;
  #28 = Utf8               oldValue
  #29 = Utf8               close
  #30 = Utf8               Exceptions
  #31 = Class              #49            // java/io/IOException
  #32 = Utf8               read
  #33 = Utf8               ()I
  #34 = Utf8               StackMapTable
  #35 = Class              #43            // java/io/InputStream
  #36 = Utf8               SourceFile
  #37 = Utf8               DemuxInputStream.java
  #38 = Utf8               org/apache/commons/io/IOUtils
  #39 = NameAndType        #17:#18        // "<init>":()V
  #40 = Utf8               java/lang/InheritableThreadLocal
  #41 = NameAndType        #13:#14        // inputStream:Ljava/lang/InheritableThreadLocal;
  #42 = NameAndType        #50:#51        // get:()Ljava/lang/Object;
  #43 = Utf8               java/io/InputStream
  #44 = NameAndType        #52:#53        // set:(Ljava/lang/Object;)V
  #45 = Utf8               java/io/Closeable
  #46 = NameAndType        #29:#54        // close:(Ljava/io/Closeable;)V
  #47 = NameAndType        #32:#33        // read:()I
  #48 = Utf8               org/apache/commons/io/input/DemuxInputStream
  #49 = Utf8               java/io/IOException
  #50 = Utf8               get
  #51 = Utf8               ()Ljava/lang/Object;
  #52 = Utf8               set
  #53 = Utf8               (Ljava/lang/Object;)V
  #54 = Utf8               (Ljava/io/Closeable;)V
{
  private final java.lang.InheritableThreadLocal<java.io.InputStream> inputStream;
    descriptor: Ljava/lang/InheritableThreadLocal;
    flags: (0x0012) ACC_PRIVATE, ACC_FINAL
    Signature: #16                          // Ljava/lang/InheritableThreadLocal<Ljava/io/InputStream;>;

  public org.apache.commons.io.input.DemuxInputStream();
    descriptor: ()V
    flags: (0x0001) ACC_PUBLIC
    Code:
      stack=3, locals=1, args_size=1
         0: aload_0
         1: invokespecial #2                  // Method java/io/InputStream."<init>":()V
         4: aload_0
         5: new           #3                  // class java/lang/InheritableThreadLocal
         8: dup
         9: invokespecial #4                  // Method java/lang/InheritableThreadLocal."<init>":()V
        12: putfield      #5                  // Field inputStream:Ljava/lang/InheritableThreadLocal;
        15: return
      LineNumberTable:
        line 29: 0
        line 30: 4
      LocalVariableTable:
        Start  Length  Slot  Name   Signature
            0      16     0  this   Lorg/apache/commons/io/input/DemuxInputStream;

  public java.io.InputStream bindStream(java.io.InputStream);
    descriptor: (Ljava/io/InputStream;)Ljava/io/InputStream;
    flags: (0x0001) ACC_PUBLIC
    Code:
      stack=2, locals=3, args_size=2
         0: aload_0
         1: getfield      #5                  // Field inputStream:Ljava/lang/InheritableThreadLocal;
         4: invokevirtual #6                  // Method java/lang/InheritableThreadLocal.get:()Ljava/lang/Object;
         7: checkcast     #7                  // class java/io/InputStream
        10: astore_2
        11: aload_0
        12: getfield      #5                  // Field inputStream:Ljava/lang/InheritableThreadLocal;
        15: aload_1
        16: invokevirtual #8                  // Method java/lang/InheritableThreadLocal.set:(Ljava/lang/Object;)V
        19: aload_2
        20: areturn
      LineNumberTable:
        line 39: 0
        line 40: 11
        line 41: 19
      LocalVariableTable:
        Start  Length  Slot  Name   Signature
            0      21     0  this   Lorg/apache/commons/io/input/DemuxInputStream;
            0      21     1 input   Ljava/io/InputStream;
           11      10     2 oldValue   Ljava/io/InputStream;

  public void close() throws java.io.IOException;
    descriptor: ()V
    flags: (0x0001) ACC_PUBLIC
    Code:
      stack=1, locals=1, args_size=1
         0: aload_0
         1: getfield      #5                  // Field inputStream:Ljava/lang/InheritableThreadLocal;
         4: invokevirtual #6                  // Method java/lang/InheritableThreadLocal.get:()Ljava/lang/Object;
         7: checkcast     #9                  // class java/io/Closeable
        10: invokestatic  #10                 // Method org/apache/commons/io/IOUtils.close:(Ljava/io/Closeable;)V
        13: return
      LineNumberTable:
        line 51: 0
        line 52: 13
      LocalVariableTable:
        Start  Length  Slot  Name   Signature
            0      14     0  this   Lorg/apache/commons/io/input/DemuxInputStream;
    Exceptions:
      throws java.io.IOException

  public int read() throws java.io.IOException;
    descriptor: ()I
    flags: (0x0001) ACC_PUBLIC
    Code:
      stack=2, locals=2, args_size=1
         0: aload_0
         1: getfield      #5                  // Field inputStream:Ljava/lang/InheritableThreadLocal;
         4: invokevirtual #6                  // Method java/lang/InheritableThreadLocal.get:()Ljava/lang/Object;
         7: checkcast     #7                  // class java/io/InputStream
        10: astore_1
        11: aconst_null
        12: aload_1
        13: if_acmpeq     21
        16: aload_1
        17: invokevirtual #11                 // Method java/io/InputStream.read:()I
        20: ireturn
        21: iconst_m1
        22: ireturn
      LineNumberTable:
        line 62: 0
        line 63: 11
        line 64: 16
        line 66: 21
      LocalVariableTable:
        Start  Length  Slot  Name   Signature
            0      23     0  this   Lorg/apache/commons/io/input/DemuxInputStream;
           11      12     1 input   Ljava/io/InputStream;
      StackMapTable: number_of_entries = 1
        frame_type = 252 /* append */
          offset_delta = 21
          locals = [ class java/io/InputStream ]
    Exceptions:
      throws java.io.IOException
}
SourceFile: "DemuxInputStream.java"
