Classfile /Users/mw/Projects/slang-braindump/.jar/jar8/assemble/slang-braindump/assemble/content/org/apache/commons/io/input/MessageDigestCalculatingInputStream.class
  Last modified May 29, 2022; size 1612 bytes
  SHA-256 checksum bda8bd6f37962c4887f193c6137165e861d07dd97cafde901d8f2008be5b1807
  Compiled from "MessageDigestCalculatingInputStream.java"
public class org.apache.commons.io.input.MessageDigestCalculatingInputStream extends org.apache.commons.io.input.ObservableInputStream
  minor version: 0
  major version: 52
  flags: (0x0021) ACC_PUBLIC, ACC_SUPER
  this_class: #9                          // org/apache/commons/io/input/MessageDigestCalculatingInputStream
  super_class: #10                        // org/apache/commons/io/input/ObservableInputStream
  interfaces: 0, fields: 1, methods: 4, attributes: 2
Constant pool:
   #1 = Methodref          #10.#35        // org/apache/commons/io/input/ObservableInputStream."<init>":(Ljava/io/InputStream;)V
   #2 = Fieldref           #9.#36         // org/apache/commons/io/input/MessageDigestCalculatingInputStream.messageDigest:Ljava/security/MessageDigest;
   #3 = Class              #37            // org/apache/commons/io/input/MessageDigestCalculatingInputStream$MessageDigestMaintainingObserver
   #4 = Methodref          #3.#38         // org/apache/commons/io/input/MessageDigestCalculatingInputStream$MessageDigestMaintainingObserver."<init>":(Ljava/security/MessageDigest;)V
   #5 = Methodref          #9.#39         // org/apache/commons/io/input/MessageDigestCalculatingInputStream.add:(Lorg/apache/commons/io/input/ObservableInputStream$Observer;)V
   #6 = Methodref          #40.#41        // java/security/MessageDigest.getInstance:(Ljava/lang/String;)Ljava/security/MessageDigest;
   #7 = Methodref          #9.#42         // org/apache/commons/io/input/MessageDigestCalculatingInputStream."<init>":(Ljava/io/InputStream;Ljava/security/MessageDigest;)V
   #8 = String             #43            // MD5
   #9 = Class              #44            // org/apache/commons/io/input/MessageDigestCalculatingInputStream
  #10 = Class              #45            // org/apache/commons/io/input/ObservableInputStream
  #11 = Utf8               MessageDigestMaintainingObserver
  #12 = Utf8               InnerClasses
  #13 = Utf8               messageDigest
  #14 = Utf8               Ljava/security/MessageDigest;
  #15 = Utf8               <init>
  #16 = Utf8               (Ljava/io/InputStream;Ljava/security/MessageDigest;)V
  #17 = Utf8               Code
  #18 = Utf8               LineNumberTable
  #19 = Utf8               LocalVariableTable
  #20 = Utf8               this
  #21 = Utf8               Lorg/apache/commons/io/input/MessageDigestCalculatingInputStream;
  #22 = Utf8               inputStream
  #23 = Utf8               Ljava/io/InputStream;
  #24 = Utf8               MessageDigest
  #25 = Utf8               (Ljava/io/InputStream;Ljava/lang/String;)V
  #26 = Utf8               algorithm
  #27 = Utf8               Ljava/lang/String;
  #28 = Utf8               Exceptions
  #29 = Class              #46            // java/security/NoSuchAlgorithmException
  #30 = Utf8               (Ljava/io/InputStream;)V
  #31 = Utf8               getMessageDigest
  #32 = Utf8               ()Ljava/security/MessageDigest;
  #33 = Utf8               SourceFile
  #34 = Utf8               MessageDigestCalculatingInputStream.java
  #35 = NameAndType        #15:#30        // "<init>":(Ljava/io/InputStream;)V
  #36 = NameAndType        #13:#14        // messageDigest:Ljava/security/MessageDigest;
  #37 = Utf8               org/apache/commons/io/input/MessageDigestCalculatingInputStream$MessageDigestMaintainingObserver
  #38 = NameAndType        #15:#47        // "<init>":(Ljava/security/MessageDigest;)V
  #39 = NameAndType        #48:#51        // add:(Lorg/apache/commons/io/input/ObservableInputStream$Observer;)V
  #40 = Class              #52            // java/security/MessageDigest
  #41 = NameAndType        #53:#54        // getInstance:(Ljava/lang/String;)Ljava/security/MessageDigest;
  #42 = NameAndType        #15:#16        // "<init>":(Ljava/io/InputStream;Ljava/security/MessageDigest;)V
  #43 = Utf8               MD5
  #44 = Utf8               org/apache/commons/io/input/MessageDigestCalculatingInputStream
  #45 = Utf8               org/apache/commons/io/input/ObservableInputStream
  #46 = Utf8               java/security/NoSuchAlgorithmException
  #47 = Utf8               (Ljava/security/MessageDigest;)V
  #48 = Utf8               add
  #49 = Class              #55            // org/apache/commons/io/input/ObservableInputStream$Observer
  #50 = Utf8               Observer
  #51 = Utf8               (Lorg/apache/commons/io/input/ObservableInputStream$Observer;)V
  #52 = Utf8               java/security/MessageDigest
  #53 = Utf8               getInstance
  #54 = Utf8               (Ljava/lang/String;)Ljava/security/MessageDigest;
  #55 = Utf8               org/apache/commons/io/input/ObservableInputStream$Observer
{
  private final java.security.MessageDigest messageDigest;
    descriptor: Ljava/security/MessageDigest;
    flags: (0x0012) ACC_PRIVATE, ACC_FINAL

  public org.apache.commons.io.input.MessageDigestCalculatingInputStream(java.io.InputStream, java.security.MessageDigest);
    descriptor: (Ljava/io/InputStream;Ljava/security/MessageDigest;)V
    flags: (0x0001) ACC_PUBLIC
    Code:
      stack=4, locals=3, args_size=3
         0: aload_0
         1: aload_1
         2: invokespecial #1                  // Method org/apache/commons/io/input/ObservableInputStream."<init>":(Ljava/io/InputStream;)V
         5: aload_0
         6: aload_2
         7: putfield      #2                  // Field messageDigest:Ljava/security/MessageDigest;
        10: aload_0
        11: new           #3                  // class org/apache/commons/io/input/MessageDigestCalculatingInputStream$MessageDigestMaintainingObserver
        14: dup
        15: aload_2
        16: invokespecial #4                  // Method org/apache/commons/io/input/MessageDigestCalculatingInputStream$MessageDigestMaintainingObserver."<init>":(Ljava/security/MessageDigest;)V
        19: invokevirtual #5                  // Method add:(Lorg/apache/commons/io/input/ObservableInputStream$Observer;)V
        22: return
      LineNumberTable:
        line 67: 0
        line 68: 5
        line 69: 10
        line 70: 22
      LocalVariableTable:
        Start  Length  Slot  Name   Signature
            0      23     0  this   Lorg/apache/commons/io/input/MessageDigestCalculatingInputStream;
            0      23     1 inputStream   Ljava/io/InputStream;
            0      23     2 MessageDigest   Ljava/security/MessageDigest;

  public org.apache.commons.io.input.MessageDigestCalculatingInputStream(java.io.InputStream, java.lang.String) throws java.security.NoSuchAlgorithmException;
    descriptor: (Ljava/io/InputStream;Ljava/lang/String;)V
    flags: (0x0001) ACC_PUBLIC
    Code:
      stack=3, locals=3, args_size=3
         0: aload_0
         1: aload_1
         2: aload_2
         3: invokestatic  #6                  // Method java/security/MessageDigest.getInstance:(Ljava/lang/String;)Ljava/security/MessageDigest;
         6: invokespecial #7                  // Method "<init>":(Ljava/io/InputStream;Ljava/security/MessageDigest;)V
         9: return
      LineNumberTable:
        line 83: 0
        line 84: 9
      LocalVariableTable:
        Start  Length  Slot  Name   Signature
            0      10     0  this   Lorg/apache/commons/io/input/MessageDigestCalculatingInputStream;
            0      10     1 inputStream   Ljava/io/InputStream;
            0      10     2 algorithm   Ljava/lang/String;
    Exceptions:
      throws java.security.NoSuchAlgorithmException

  public org.apache.commons.io.input.MessageDigestCalculatingInputStream(java.io.InputStream) throws java.security.NoSuchAlgorithmException;
    descriptor: (Ljava/io/InputStream;)V
    flags: (0x0001) ACC_PUBLIC
    Code:
      stack=3, locals=2, args_size=2
         0: aload_0
         1: aload_1
         2: ldc           #8                  // String MD5
         4: invokestatic  #6                  // Method java/security/MessageDigest.getInstance:(Ljava/lang/String;)Ljava/security/MessageDigest;
         7: invokespecial #7                  // Method "<init>":(Ljava/io/InputStream;Ljava/security/MessageDigest;)V
        10: return
      LineNumberTable:
        line 95: 0
        line 96: 10
      LocalVariableTable:
        Start  Length  Slot  Name   Signature
            0      11     0  this   Lorg/apache/commons/io/input/MessageDigestCalculatingInputStream;
            0      11     1 inputStream   Ljava/io/InputStream;
    Exceptions:
      throws java.security.NoSuchAlgorithmException

  public java.security.MessageDigest getMessageDigest();
    descriptor: ()Ljava/security/MessageDigest;
    flags: (0x0001) ACC_PUBLIC
    Code:
      stack=1, locals=1, args_size=1
         0: aload_0
         1: getfield      #2                  // Field messageDigest:Ljava/security/MessageDigest;
         4: areturn
      LineNumberTable:
        line 107: 0
      LocalVariableTable:
        Start  Length  Slot  Name   Signature
            0       5     0  this   Lorg/apache/commons/io/input/MessageDigestCalculatingInputStream;
}
SourceFile: "MessageDigestCalculatingInputStream.java"
InnerClasses:
  public static #11= #3 of #9;            // MessageDigestMaintainingObserver=class org/apache/commons/io/input/MessageDigestCalculatingInputStream$MessageDigestMaintainingObserver of class org/apache/commons/io/input/MessageDigestCalculatingInputStream
  public static abstract #50= #49 of #10; // Observer=class org/apache/commons/io/input/ObservableInputStream$Observer of class org/apache/commons/io/input/ObservableInputStream
