Classfile /Users/mw/Projects/slang-braindump/.jar/jar8/assemble/slang-braindump/assemble/content/org/apache/commons/io/input/TaggedInputStream.class
  Last modified May 29, 2022; size 1303 bytes
  SHA-256 checksum 8d492684330e3fc5f1c0c13eae0614085f63a943117264a40204f2f37d938770
  Compiled from "TaggedInputStream.java"
public class org.apache.commons.io.input.TaggedInputStream extends org.apache.commons.io.input.ProxyInputStream
  minor version: 0
  major version: 52
  flags: (0x0021) ACC_PUBLIC, ACC_SUPER
  this_class: #8                          // org/apache/commons/io/input/TaggedInputStream
  super_class: #9                         // org/apache/commons/io/input/ProxyInputStream
  interfaces: 0, fields: 1, methods: 4, attributes: 1
Constant pool:
   #1 = Methodref          #9.#36         // org/apache/commons/io/input/ProxyInputStream."<init>":(Ljava/io/InputStream;)V
   #2 = Methodref          #37.#38        // java/util/UUID.randomUUID:()Ljava/util/UUID;
   #3 = Fieldref           #8.#39         // org/apache/commons/io/input/TaggedInputStream.tag:Ljava/io/Serializable;
   #4 = Methodref          #6.#40         // org/apache/commons/io/TaggedIOException.isTaggedWith:(Ljava/lang/Throwable;Ljava/lang/Object;)Z
   #5 = Methodref          #6.#41         // org/apache/commons/io/TaggedIOException.throwCauseIfTaggedWith:(Ljava/lang/Throwable;Ljava/lang/Object;)V
   #6 = Class              #42            // org/apache/commons/io/TaggedIOException
   #7 = Methodref          #6.#43         // org/apache/commons/io/TaggedIOException."<init>":(Ljava/io/IOException;Ljava/io/Serializable;)V
   #8 = Class              #44            // org/apache/commons/io/input/TaggedInputStream
   #9 = Class              #45            // org/apache/commons/io/input/ProxyInputStream
  #10 = Utf8               tag
  #11 = Utf8               Ljava/io/Serializable;
  #12 = Utf8               <init>
  #13 = Utf8               (Ljava/io/InputStream;)V
  #14 = Utf8               Code
  #15 = Utf8               LineNumberTable
  #16 = Utf8               LocalVariableTable
  #17 = Utf8               this
  #18 = Utf8               Lorg/apache/commons/io/input/TaggedInputStream;
  #19 = Utf8               proxy
  #20 = Utf8               Ljava/io/InputStream;
  #21 = Utf8               isCauseOf
  #22 = Utf8               (Ljava/lang/Throwable;)Z
  #23 = Utf8               exception
  #24 = Utf8               Ljava/lang/Throwable;
  #25 = Utf8               throwIfCauseOf
  #26 = Utf8               (Ljava/lang/Throwable;)V
  #27 = Utf8               throwable
  #28 = Utf8               Exceptions
  #29 = Class              #46            // java/io/IOException
  #30 = Utf8               handleIOException
  #31 = Utf8               (Ljava/io/IOException;)V
  #32 = Utf8               e
  #33 = Utf8               Ljava/io/IOException;
  #34 = Utf8               SourceFile
  #35 = Utf8               TaggedInputStream.java
  #36 = NameAndType        #12:#13        // "<init>":(Ljava/io/InputStream;)V
  #37 = Class              #47            // java/util/UUID
  #38 = NameAndType        #48:#49        // randomUUID:()Ljava/util/UUID;
  #39 = NameAndType        #10:#11        // tag:Ljava/io/Serializable;
  #40 = NameAndType        #50:#51        // isTaggedWith:(Ljava/lang/Throwable;Ljava/lang/Object;)Z
  #41 = NameAndType        #52:#53        // throwCauseIfTaggedWith:(Ljava/lang/Throwable;Ljava/lang/Object;)V
  #42 = Utf8               org/apache/commons/io/TaggedIOException
  #43 = NameAndType        #12:#54        // "<init>":(Ljava/io/IOException;Ljava/io/Serializable;)V
  #44 = Utf8               org/apache/commons/io/input/TaggedInputStream
  #45 = Utf8               org/apache/commons/io/input/ProxyInputStream
  #46 = Utf8               java/io/IOException
  #47 = Utf8               java/util/UUID
  #48 = Utf8               randomUUID
  #49 = Utf8               ()Ljava/util/UUID;
  #50 = Utf8               isTaggedWith
  #51 = Utf8               (Ljava/lang/Throwable;Ljava/lang/Object;)Z
  #52 = Utf8               throwCauseIfTaggedWith
  #53 = Utf8               (Ljava/lang/Throwable;Ljava/lang/Object;)V
  #54 = Utf8               (Ljava/io/IOException;Ljava/io/Serializable;)V
{
  private final java.io.Serializable tag;
    descriptor: Ljava/io/Serializable;
    flags: (0x0012) ACC_PRIVATE, ACC_FINAL

  public org.apache.commons.io.input.TaggedInputStream(java.io.InputStream);
    descriptor: (Ljava/io/InputStream;)V
    flags: (0x0001) ACC_PUBLIC
    Code:
      stack=2, locals=2, args_size=2
         0: aload_0
         1: aload_1
         2: invokespecial #1                  // Method org/apache/commons/io/input/ProxyInputStream."<init>":(Ljava/io/InputStream;)V
         5: aload_0
         6: invokestatic  #2                  // Method java/util/UUID.randomUUID:()Ljava/util/UUID;
         9: putfield      #3                  // Field tag:Ljava/io/Serializable;
        12: return
      LineNumberTable:
        line 77: 0
        line 69: 5
        line 78: 12
      LocalVariableTable:
        Start  Length  Slot  Name   Signature
            0      13     0  this   Lorg/apache/commons/io/input/TaggedInputStream;
            0      13     1 proxy   Ljava/io/InputStream;

  public boolean isCauseOf(java.lang.Throwable);
    descriptor: (Ljava/lang/Throwable;)Z
    flags: (0x0001) ACC_PUBLIC
    Code:
      stack=2, locals=2, args_size=2
         0: aload_1
         1: aload_0
         2: getfield      #3                  // Field tag:Ljava/io/Serializable;
         5: invokestatic  #4                  // Method org/apache/commons/io/TaggedIOException.isTaggedWith:(Ljava/lang/Throwable;Ljava/lang/Object;)Z
         8: ireturn
      LineNumberTable:
        line 88: 0
      LocalVariableTable:
        Start  Length  Slot  Name   Signature
            0       9     0  this   Lorg/apache/commons/io/input/TaggedInputStream;
            0       9     1 exception   Ljava/lang/Throwable;

  public void throwIfCauseOf(java.lang.Throwable) throws java.io.IOException;
    descriptor: (Ljava/lang/Throwable;)V
    flags: (0x0001) ACC_PUBLIC
    Code:
      stack=2, locals=2, args_size=2
         0: aload_1
         1: aload_0
         2: getfield      #3                  // Field tag:Ljava/io/Serializable;
         5: invokestatic  #5                  // Method org/apache/commons/io/TaggedIOException.throwCauseIfTaggedWith:(Ljava/lang/Throwable;Ljava/lang/Object;)V
         8: return
      LineNumberTable:
        line 102: 0
        line 103: 8
      LocalVariableTable:
        Start  Length  Slot  Name   Signature
            0       9     0  this   Lorg/apache/commons/io/input/TaggedInputStream;
            0       9     1 throwable   Ljava/lang/Throwable;
    Exceptions:
      throws java.io.IOException

  protected void handleIOException(java.io.IOException) throws java.io.IOException;
    descriptor: (Ljava/io/IOException;)V
    flags: (0x0004) ACC_PROTECTED
    Code:
      stack=4, locals=2, args_size=2
         0: new           #6                  // class org/apache/commons/io/TaggedIOException
         3: dup
         4: aload_1
         5: aload_0
         6: getfield      #3                  // Field tag:Ljava/io/Serializable;
         9: invokespecial #7                  // Method org/apache/commons/io/TaggedIOException."<init>":(Ljava/io/IOException;Ljava/io/Serializable;)V
        12: athrow
      LineNumberTable:
        line 113: 0
      LocalVariableTable:
        Start  Length  Slot  Name   Signature
            0      13     0  this   Lorg/apache/commons/io/input/TaggedInputStream;
            0      13     1     e   Ljava/io/IOException;
    Exceptions:
      throws java.io.IOException
}
SourceFile: "TaggedInputStream.java"
