Classfile /Users/mw/Projects/slang-braindump/.jar/jar11/assemble/slang-braindump/assemble/content/org/apache/commons/lang3/math/IEEE754rUtils.class
  Last modified May 29, 2022; size 2337 bytes
  SHA-256 checksum 347423beb1e5bab7ea90044b81e24612dc826530cd55b92dda3ab3d954503642
  Compiled from "IEEE754rUtils.java"
public class org.apache.commons.lang3.math.IEEE754rUtils
  minor version: 0
  major version: 52
  flags: (0x0021) ACC_PUBLIC, ACC_SUPER
  this_class: #16                         // org/apache/commons/lang3/math/IEEE754rUtils
  super_class: #3                         // java/lang/Object
  interfaces: 0, fields: 0, methods: 13, attributes: 1
Constant pool:
   #1 = Methodref          #3.#46         // java/lang/Object."<init>":()V
   #2 = String             #47            // The Array must not be null
   #3 = Class              #48            // java/lang/Object
   #4 = Methodref          #49.#50        // org/apache/commons/lang3/Validate.isTrue:(ZLjava/lang/String;[Ljava/lang/Object;)V
   #5 = String             #51            // Array cannot be empty.
   #6 = Methodref          #16.#52        // org/apache/commons/lang3/math/IEEE754rUtils.min:(DD)D
   #7 = Methodref          #16.#53        // org/apache/commons/lang3/math/IEEE754rUtils.min:(FF)F
   #8 = Methodref          #54.#55        // java/lang/Double.isNaN:(D)Z
   #9 = Methodref          #56.#52        // java/lang/Math.min:(DD)D
  #10 = Methodref          #57.#58        // java/lang/Float.isNaN:(F)Z
  #11 = Methodref          #56.#53        // java/lang/Math.min:(FF)F
  #12 = Methodref          #16.#59        // org/apache/commons/lang3/math/IEEE754rUtils.max:(DD)D
  #13 = Methodref          #16.#60        // org/apache/commons/lang3/math/IEEE754rUtils.max:(FF)F
  #14 = Methodref          #56.#59        // java/lang/Math.max:(DD)D
  #15 = Methodref          #56.#60        // java/lang/Math.max:(FF)F
  #16 = Class              #61            // org/apache/commons/lang3/math/IEEE754rUtils
  #17 = Utf8               <init>
  #18 = Utf8               ()V
  #19 = Utf8               Code
  #20 = Utf8               LineNumberTable
  #21 = Utf8               LocalVariableTable
  #22 = Utf8               this
  #23 = Utf8               Lorg/apache/commons/lang3/math/IEEE754rUtils;
  #24 = Utf8               min
  #25 = Utf8               ([D)D
  #26 = Utf8               i
  #27 = Utf8               I
  #28 = Utf8               array
  #29 = Utf8               [D
  #30 = Utf8               D
  #31 = Utf8               StackMapTable
  #32 = Utf8               ([F)F
  #33 = Utf8               [F
  #34 = Utf8               F
  #35 = Utf8               (DDD)D
  #36 = Utf8               a
  #37 = Utf8               b
  #38 = Utf8               c
  #39 = Utf8               (DD)D
  #40 = Utf8               (FFF)F
  #41 = Utf8               (FF)F
  #42 = Utf8               max
  #43 = Utf8               j
  #44 = Utf8               SourceFile
  #45 = Utf8               IEEE754rUtils.java
  #46 = NameAndType        #17:#18        // "<init>":()V
  #47 = Utf8               The Array must not be null
  #48 = Utf8               java/lang/Object
  #49 = Class              #62            // org/apache/commons/lang3/Validate
  #50 = NameAndType        #63:#64        // isTrue:(ZLjava/lang/String;[Ljava/lang/Object;)V
  #51 = Utf8               Array cannot be empty.
  #52 = NameAndType        #24:#39        // min:(DD)D
  #53 = NameAndType        #24:#41        // min:(FF)F
  #54 = Class              #65            // java/lang/Double
  #55 = NameAndType        #66:#67        // isNaN:(D)Z
  #56 = Class              #68            // java/lang/Math
  #57 = Class              #69            // java/lang/Float
  #58 = NameAndType        #66:#70        // isNaN:(F)Z
  #59 = NameAndType        #42:#39        // max:(DD)D
  #60 = NameAndType        #42:#41        // max:(FF)F
  #61 = Utf8               org/apache/commons/lang3/math/IEEE754rUtils
  #62 = Utf8               org/apache/commons/lang3/Validate
  #63 = Utf8               isTrue
  #64 = Utf8               (ZLjava/lang/String;[Ljava/lang/Object;)V
  #65 = Utf8               java/lang/Double
  #66 = Utf8               isNaN
  #67 = Utf8               (D)Z
  #68 = Utf8               java/lang/Math
  #69 = Utf8               java/lang/Float
  #70 = Utf8               (F)Z
{
  public org.apache.commons.lang3.math.IEEE754rUtils();
    descriptor: ()V
    flags: (0x0001) ACC_PUBLIC
    Code:
      stack=1, locals=1, args_size=1
         0: aload_0
         1: invokespecial #1                  // Method java/lang/Object."<init>":()V
         4: return
      LineNumberTable:
        line 28: 0
      LocalVariableTable:
        Start  Length  Slot  Name   Signature
            0       5     0  this   Lorg/apache/commons/lang3/math/IEEE754rUtils;

  public static double min(double...);
    descriptor: ([D)D
    flags: (0x0089) ACC_PUBLIC, ACC_STATIC, ACC_VARARGS
    Code:
      stack=4, locals=4, args_size=1
         0: aload_0
         1: ifnull        8
         4: iconst_1
         5: goto          9
         8: iconst_0
         9: ldc           #2                  // String The Array must not be null
        11: iconst_0
        12: anewarray     #3                  // class java/lang/Object
        15: invokestatic  #4                  // Method org/apache/commons/lang3/Validate.isTrue:(ZLjava/lang/String;[Ljava/lang/Object;)V
        18: aload_0
        19: arraylength
        20: ifeq          27
        23: iconst_1
        24: goto          28
        27: iconst_0
        28: ldc           #5                  // String Array cannot be empty.
        30: iconst_0
        31: anewarray     #3                  // class java/lang/Object
        34: invokestatic  #4                  // Method org/apache/commons/lang3/Validate.isTrue:(ZLjava/lang/String;[Ljava/lang/Object;)V
        37: aload_0
        38: iconst_0
        39: daload
        40: dstore_1
        41: iconst_1
        42: istore_3
        43: iload_3
        44: aload_0
        45: arraylength
        46: if_icmpge     63
        49: aload_0
        50: iload_3
        51: daload
        52: dload_1
        53: invokestatic  #6                  // Method min:(DD)D
        56: dstore_1
        57: iinc          3, 1
        60: goto          43
        63: dload_1
        64: dreturn
      LineNumberTable:
        line 40: 0
        line 41: 18
        line 44: 37
        line 45: 41
        line 46: 49
        line 45: 57
        line 49: 63
      LocalVariableTable:
        Start  Length  Slot  Name   Signature
           43      20     3     i   I
            0      65     0 array   [D
           41      24     1   min   D
      StackMapTable: number_of_entries = 6
        frame_type = 8 /* same */
        frame_type = 64 /* same_locals_1_stack_item */
          stack = [ int ]
        frame_type = 17 /* same */
        frame_type = 64 /* same_locals_1_stack_item */
          stack = [ int ]
        frame_type = 253 /* append */
          offset_delta = 14
          locals = [ double, int ]
        frame_type = 250 /* chop */
          offset_delta = 19

  public static float min(float...);
    descriptor: ([F)F
    flags: (0x0089) ACC_PUBLIC, ACC_STATIC, ACC_VARARGS
    Code:
      stack=3, locals=3, args_size=1
         0: aload_0
         1: ifnull        8
         4: iconst_1
         5: goto          9
         8: iconst_0
         9: ldc           #2                  // String The Array must not be null
        11: iconst_0
        12: anewarray     #3                  // class java/lang/Object
        15: invokestatic  #4                  // Method org/apache/commons/lang3/Validate.isTrue:(ZLjava/lang/String;[Ljava/lang/Object;)V
        18: aload_0
        19: arraylength
        20: ifeq          27
        23: iconst_1
        24: goto          28
        27: iconst_0
        28: ldc           #5                  // String Array cannot be empty.
        30: iconst_0
        31: anewarray     #3                  // class java/lang/Object
        34: invokestatic  #4                  // Method org/apache/commons/lang3/Validate.isTrue:(ZLjava/lang/String;[Ljava/lang/Object;)V
        37: aload_0
        38: iconst_0
        39: faload
        40: fstore_1
        41: iconst_1
        42: istore_2
        43: iload_2
        44: aload_0
        45: arraylength
        46: if_icmpge     63
        49: aload_0
        50: iload_2
        51: faload
        52: fload_1
        53: invokestatic  #7                  // Method min:(FF)F
        56: fstore_1
        57: iinc          2, 1
        60: goto          43
        63: fload_1
        64: freturn
      LineNumberTable:
        line 62: 0
        line 63: 18
        line 66: 37
        line 67: 41
        line 68: 49
        line 67: 57
        line 71: 63
      LocalVariableTable:
        Start  Length  Slot  Name   Signature
           43      20     2     i   I
            0      65     0 array   [F
           41      24     1   min   F
      StackMapTable: number_of_entries = 6
        frame_type = 8 /* same */
        frame_type = 64 /* same_locals_1_stack_item */
          stack = [ int ]
        frame_type = 17 /* same */
        frame_type = 64 /* same_locals_1_stack_item */
          stack = [ int ]
        frame_type = 253 /* append */
          offset_delta = 14
          locals = [ float, int ]
        frame_type = 250 /* chop */
          offset_delta = 19

  public static double min(double, double, double);
    descriptor: (DDD)D
    flags: (0x0009) ACC_PUBLIC, ACC_STATIC
    Code:
      stack=4, locals=6, args_size=3
         0: dload_0
         1: dload_2
         2: invokestatic  #6                  // Method min:(DD)D
         5: dload         4
         7: invokestatic  #6                  // Method min:(DD)D
        10: dreturn
      LineNumberTable:
        line 85: 0
      LocalVariableTable:
        Start  Length  Slot  Name   Signature
            0      11     0     a   D
            0      11     2     b   D
            0      11     4     c   D

  public static double min(double, double);
    descriptor: (DD)D
    flags: (0x0009) ACC_PUBLIC, ACC_STATIC
    Code:
      stack=4, locals=4, args_size=2
         0: dload_0
         1: invokestatic  #8                  // Method java/lang/Double.isNaN:(D)Z
         4: ifeq          9
         7: dload_2
         8: dreturn
         9: dload_2
        10: invokestatic  #8                  // Method java/lang/Double.isNaN:(D)Z
        13: ifeq          18
        16: dload_0
        17: dreturn
        18: dload_0
        19: dload_2
        20: invokestatic  #9                  // Method java/lang/Math.min:(DD)D
        23: dreturn
      LineNumberTable:
        line 98: 0
        line 99: 7
        line 101: 9
        line 102: 16
        line 104: 18
      LocalVariableTable:
        Start  Length  Slot  Name   Signature
            0      24     0     a   D
            0      24     2     b   D
      StackMapTable: number_of_entries = 2
        frame_type = 9 /* same */
        frame_type = 8 /* same */

  public static float min(float, float, float);
    descriptor: (FFF)F
    flags: (0x0009) ACC_PUBLIC, ACC_STATIC
    Code:
      stack=2, locals=3, args_size=3
         0: fload_0
         1: fload_1
         2: invokestatic  #7                  // Method min:(FF)F
         5: fload_2
         6: invokestatic  #7                  // Method min:(FF)F
         9: freturn
      LineNumberTable:
        line 119: 0
      LocalVariableTable:
        Start  Length  Slot  Name   Signature
            0      10     0     a   F
            0      10     1     b   F
            0      10     2     c   F

  public static float min(float, float);
    descriptor: (FF)F
    flags: (0x0009) ACC_PUBLIC, ACC_STATIC
    Code:
      stack=2, locals=2, args_size=2
         0: fload_0
         1: invokestatic  #10                 // Method java/lang/Float.isNaN:(F)Z
         4: ifeq          9
         7: fload_1
         8: freturn
         9: fload_1
        10: invokestatic  #10                 // Method java/lang/Float.isNaN:(F)Z
        13: ifeq          18
        16: fload_0
        17: freturn
        18: fload_0
        19: fload_1
        20: invokestatic  #11                 // Method java/lang/Math.min:(FF)F
        23: freturn
      LineNumberTable:
        line 132: 0
        line 133: 7
        line 135: 9
        line 136: 16
        line 138: 18
      LocalVariableTable:
        Start  Length  Slot  Name   Signature
            0      24     0     a   F
            0      24     1     b   F
      StackMapTable: number_of_entries = 2
        frame_type = 9 /* same */
        frame_type = 8 /* same */

  public static double max(double...);
    descriptor: ([D)D
    flags: (0x0089) ACC_PUBLIC, ACC_STATIC, ACC_VARARGS
    Code:
      stack=4, locals=4, args_size=1
         0: aload_0
         1: ifnull        8
         4: iconst_1
         5: goto          9
         8: iconst_0
         9: ldc           #2                  // String The Array must not be null
        11: iconst_0
        12: anewarray     #3                  // class java/lang/Object
        15: invokestatic  #4                  // Method org/apache/commons/lang3/Validate.isTrue:(ZLjava/lang/String;[Ljava/lang/Object;)V
        18: aload_0
        19: arraylength
        20: ifeq          27
        23: iconst_1
        24: goto          28
        27: iconst_0
        28: ldc           #5                  // String Array cannot be empty.
        30: iconst_0
        31: anewarray     #3                  // class java/lang/Object
        34: invokestatic  #4                  // Method org/apache/commons/lang3/Validate.isTrue:(ZLjava/lang/String;[Ljava/lang/Object;)V
        37: aload_0
        38: iconst_0
        39: daload
        40: dstore_1
        41: iconst_1
        42: istore_3
        43: iload_3
        44: aload_0
        45: arraylength
        46: if_icmpge     63
        49: aload_0
        50: iload_3
        51: daload
        52: dload_1
        53: invokestatic  #12                 // Method max:(DD)D
        56: dstore_1
        57: iinc          3, 1
        60: goto          43
        63: dload_1
        64: dreturn
      LineNumberTable:
        line 152: 0
        line 153: 18
        line 156: 37
        line 157: 41
        line 158: 49
        line 157: 57
        line 161: 63
      LocalVariableTable:
        Start  Length  Slot  Name   Signature
           43      20     3     j   I
            0      65     0 array   [D
           41      24     1   max   D
      StackMapTable: number_of_entries = 6
        frame_type = 8 /* same */
        frame_type = 64 /* same_locals_1_stack_item */
          stack = [ int ]
        frame_type = 17 /* same */
        frame_type = 64 /* same_locals_1_stack_item */
          stack = [ int ]
        frame_type = 253 /* append */
          offset_delta = 14
          locals = [ double, int ]
        frame_type = 250 /* chop */
          offset_delta = 19

  public static float max(float...);
    descriptor: ([F)F
    flags: (0x0089) ACC_PUBLIC, ACC_STATIC, ACC_VARARGS
    Code:
      stack=3, locals=3, args_size=1
         0: aload_0
         1: ifnull        8
         4: iconst_1
         5: goto          9
         8: iconst_0
         9: ldc           #2                  // String The Array must not be null
        11: iconst_0
        12: anewarray     #3                  // class java/lang/Object
        15: invokestatic  #4                  // Method org/apache/commons/lang3/Validate.isTrue:(ZLjava/lang/String;[Ljava/lang/Object;)V
        18: aload_0
        19: arraylength
        20: ifeq          27
        23: iconst_1
        24: goto          28
        27: iconst_0
        28: ldc           #5                  // String Array cannot be empty.
        30: iconst_0
        31: anewarray     #3                  // class java/lang/Object
        34: invokestatic  #4                  // Method org/apache/commons/lang3/Validate.isTrue:(ZLjava/lang/String;[Ljava/lang/Object;)V
        37: aload_0
        38: iconst_0
        39: faload
        40: fstore_1
        41: iconst_1
        42: istore_2
        43: iload_2
        44: aload_0
        45: arraylength
        46: if_icmpge     63
        49: aload_0
        50: iload_2
        51: faload
        52: fload_1
        53: invokestatic  #13                 // Method max:(FF)F
        56: fstore_1
        57: iinc          2, 1
        60: goto          43
        63: fload_1
        64: freturn
      LineNumberTable:
        line 174: 0
        line 175: 18
        line 178: 37
        line 179: 41
        line 180: 49
        line 179: 57
        line 183: 63
      LocalVariableTable:
        Start  Length  Slot  Name   Signature
           43      20     2     j   I
            0      65     0 array   [F
           41      24     1   max   F
      StackMapTable: number_of_entries = 6
        frame_type = 8 /* same */
        frame_type = 64 /* same_locals_1_stack_item */
          stack = [ int ]
        frame_type = 17 /* same */
        frame_type = 64 /* same_locals_1_stack_item */
          stack = [ int ]
        frame_type = 253 /* append */
          offset_delta = 14
          locals = [ float, int ]
        frame_type = 250 /* chop */
          offset_delta = 19

  public static double max(double, double, double);
    descriptor: (DDD)D
    flags: (0x0009) ACC_PUBLIC, ACC_STATIC
    Code:
      stack=4, locals=6, args_size=3
         0: dload_0
         1: dload_2
         2: invokestatic  #12                 // Method max:(DD)D
         5: dload         4
         7: invokestatic  #12                 // Method max:(DD)D
        10: dreturn
      LineNumberTable:
        line 197: 0
      LocalVariableTable:
        Start  Length  Slot  Name   Signature
            0      11     0     a   D
            0      11     2     b   D
            0      11     4     c   D

  public static double max(double, double);
    descriptor: (DD)D
    flags: (0x0009) ACC_PUBLIC, ACC_STATIC
    Code:
      stack=4, locals=4, args_size=2
         0: dload_0
         1: invokestatic  #8                  // Method java/lang/Double.isNaN:(D)Z
         4: ifeq          9
         7: dload_2
         8: dreturn
         9: dload_2
        10: invokestatic  #8                  // Method java/lang/Double.isNaN:(D)Z
        13: ifeq          18
        16: dload_0
        17: dreturn
        18: dload_0
        19: dload_2
        20: invokestatic  #14                 // Method java/lang/Math.max:(DD)D
        23: dreturn
      LineNumberTable:
        line 210: 0
        line 211: 7
        line 213: 9
        line 214: 16
        line 216: 18
      LocalVariableTable:
        Start  Length  Slot  Name   Signature
            0      24     0     a   D
            0      24     2     b   D
      StackMapTable: number_of_entries = 2
        frame_type = 9 /* same */
        frame_type = 8 /* same */

  public static float max(float, float, float);
    descriptor: (FFF)F
    flags: (0x0009) ACC_PUBLIC, ACC_STATIC
    Code:
      stack=2, locals=3, args_size=3
         0: fload_0
         1: fload_1
         2: invokestatic  #13                 // Method max:(FF)F
         5: fload_2
         6: invokestatic  #13                 // Method max:(FF)F
         9: freturn
      LineNumberTable:
        line 231: 0
      LocalVariableTable:
        Start  Length  Slot  Name   Signature
            0      10     0     a   F
            0      10     1     b   F
            0      10     2     c   F

  public static float max(float, float);
    descriptor: (FF)F
    flags: (0x0009) ACC_PUBLIC, ACC_STATIC
    Code:
      stack=2, locals=2, args_size=2
         0: fload_0
         1: invokestatic  #10                 // Method java/lang/Float.isNaN:(F)Z
         4: ifeq          9
         7: fload_1
         8: freturn
         9: fload_1
        10: invokestatic  #10                 // Method java/lang/Float.isNaN:(F)Z
        13: ifeq          18
        16: fload_0
        17: freturn
        18: fload_0
        19: fload_1
        20: invokestatic  #15                 // Method java/lang/Math.max:(FF)F
        23: freturn
      LineNumberTable:
        line 244: 0
        line 245: 7
        line 247: 9
        line 248: 16
        line 250: 18
      LocalVariableTable:
        Start  Length  Slot  Name   Signature
            0      24     0     a   F
            0      24     1     b   F
      StackMapTable: number_of_entries = 2
        frame_type = 9 /* same */
        frame_type = 8 /* same */
}
SourceFile: "IEEE754rUtils.java"
