Classfile /Users/mw/Projects/slang-braindump/.jar/jar8/assemble/slang-braindump/assemble/content/scala/io/Source$$anon$1.class
  Last modified May 29, 2022; size 943 bytes
  SHA-256 checksum 1c695b74e34dd7308dcf1c443aadcefdeed0ed14333d25c66aa22657ff094732
  Compiled from "Source.scala"
public final class scala.io.Source$$anon$1 extends scala.io.Source
  minor version: 0
  major version: 52
  flags: (0x0031) ACC_PUBLIC, ACC_FINAL, ACC_SUPER
  this_class: #2                          // scala/io/Source$$anon$1
  super_class: #4                         // scala/io/Source
  interfaces: 0, fields: 1, methods: 2, attributes: 5
Constant pool:
   #1 = Utf8               scala/io/Source$$anon$1
   #2 = Class              #1             // scala/io/Source$$anon$1
   #3 = Utf8               scala/io/Source
   #4 = Class              #3             // scala/io/Source
   #5 = Utf8               Source.scala
   #6 = Utf8               scala/io/Source$
   #7 = Class              #6             // scala/io/Source$
   #8 = Utf8               fromIterable
   #9 = Utf8               (Lscala/collection/Iterable;)Lscala/io/Source;
  #10 = NameAndType        #8:#9          // fromIterable:(Lscala/collection/Iterable;)Lscala/io/Source;
  #11 = Utf8               iter
  #12 = Utf8               Lscala/collection/Iterator;
  #13 = Utf8               Lscala/collection/Iterator<Ljava/lang/Object;>;
  #14 = Utf8               ()Lscala/collection/Iterator;
  #15 = Utf8               ()Lscala/collection/Iterator<Ljava/lang/Object;>;
  #16 = NameAndType        #11:#12        // iter:Lscala/collection/Iterator;
  #17 = Fieldref           #2.#16         // scala/io/Source$$anon$1.iter:Lscala/collection/Iterator;
  #18 = Utf8               this
  #19 = Utf8               Lscala/io/Source$$anon$1;
  #20 = Utf8               <init>
  #21 = Utf8               (Lscala/collection/Iterable;)V
  #22 = Utf8               iterable$1
  #23 = Utf8               ()V
  #24 = NameAndType        #20:#23        // "<init>":()V
  #25 = Methodref          #4.#24         // scala/io/Source."<init>":()V
  #26 = Utf8               scala/collection/Iterable
  #27 = Class              #26            // scala/collection/Iterable
  #28 = Utf8               iterator
  #29 = NameAndType        #28:#14        // iterator:()Lscala/collection/Iterator;
  #30 = InterfaceMethodref #27.#29        // scala/collection/Iterable.iterator:()Lscala/collection/Iterator;
  #31 = Utf8               Lscala/collection/Iterable;
  #32 = Utf8               Signature
  #33 = Utf8               Code
  #34 = Utf8               LineNumberTable
  #35 = Utf8               LocalVariableTable
  #36 = Utf8               MethodParameters
  #37 = Utf8               InnerClasses
  #38 = Utf8               EnclosingMethod
  #39 = Utf8               SourceFile
  #40 = Utf8               ScalaInlineInfo
  #41 = Utf8               Scala
{
  private final scala.collection.Iterator<java.lang.Object> iter;
    descriptor: Lscala/collection/Iterator;
    flags: (0x0012) ACC_PRIVATE, ACC_FINAL
    Signature: #13                          // Lscala/collection/Iterator<Ljava/lang/Object;>;

  public scala.collection.Iterator<java.lang.Object> iter();
    descriptor: ()Lscala/collection/Iterator;
    flags: (0x0001) ACC_PUBLIC
    Code:
      stack=1, locals=1, args_size=1
         0: aload_0
         1: getfield      #17                 // Field iter:Lscala/collection/Iterator;
         4: areturn
      LineNumberTable:
        line 38: 0
      LocalVariableTable:
        Start  Length  Slot  Name   Signature
            0       5     0  this   Lscala/io/Source$$anon$1;
    Signature: #15                          // ()Lscala/collection/Iterator<Ljava/lang/Object;>;

  public scala.io.Source$$anon$1(scala.collection.Iterable);
    descriptor: (Lscala/collection/Iterable;)V
    flags: (0x0001) ACC_PUBLIC
    Code:
      stack=2, locals=2, args_size=2
         0: aload_0
         1: invokespecial #25                 // Method scala/io/Source."<init>":()V
         4: aload_0
         5: aload_1
         6: invokeinterface #30,  1           // InterfaceMethod scala/collection/Iterable.iterator:()Lscala/collection/Iterator;
        11: putfield      #17                 // Field iter:Lscala/collection/Iterator;
        14: return
      LineNumberTable:
        line 37: 0
        line 38: 4
        line 37: 14
      LocalVariableTable:
        Start  Length  Slot  Name   Signature
            0      15     0  this   Lscala/io/Source$$anon$1;
            0      15     1 iterable$1   Lscala/collection/Iterable;
    MethodParameters:
      Name                           Flags
      iterable$1                     final
}
InnerClasses:
  public final #2;                        // class scala/io/Source$$anon$1
EnclosingMethod: #7.#10                 // scala.io.Source$.fromIterable
SourceFile: "Source.scala"
  ScalaInlineInfo: length = 0xE (unknown attribute)
   01 01 00 02 00 14 00 15 01 00 0B 00 0E 01
  Scala: length = 0x0 (unknown attribute)

