Classfile /Users/mw/Projects/slang-braindump/.jar/jar8/assemble/slang-braindump/assemble/content/scala/io/Source$RelaxedPosition$.class
  Last modified May 29, 2022; size 645 bytes
  SHA-256 checksum 0fd2c4868395b3e2fbdb873eba79efe67813144870460332fc38df2f9bd6d313
  Compiled from "Source.scala"
public class scala.io.Source$RelaxedPosition$ extends scala.io.Position
  minor version: 0
  major version: 52
  flags: (0x0021) ACC_PUBLIC, ACC_SUPER
  this_class: #2                          // scala/io/Source$RelaxedPosition$
  super_class: #4                         // scala/io/Position
  interfaces: 0, fields: 0, methods: 2, attributes: 4
Constant pool:
   #1 = Utf8               scala/io/Source$RelaxedPosition$
   #2 = Class              #1             // scala/io/Source$RelaxedPosition$
   #3 = Utf8               scala/io/Position
   #4 = Class              #3             // scala/io/Position
   #5 = Utf8               Source.scala
   #6 = Utf8               scala/io/Source
   #7 = Class              #6             // scala/io/Source
   #8 = Utf8               RelaxedPosition$
   #9 = Utf8               checkInput
  #10 = Utf8               (II)V
  #11 = Utf8               line
  #12 = Utf8               column
  #13 = Utf8               this
  #14 = Utf8               Lscala/io/Source$RelaxedPosition$;
  #15 = Utf8               I
  #16 = Utf8               <init>
  #17 = Utf8               (Lscala/io/Source;)V
  #18 = Utf8               $outer
  #19 = Utf8               ()V
  #20 = NameAndType        #16:#19        // "<init>":()V
  #21 = Methodref          #4.#20         // scala/io/Position."<init>":()V
  #22 = Utf8               Lscala/io/Source;
  #23 = Utf8               Code
  #24 = Utf8               LineNumberTable
  #25 = Utf8               LocalVariableTable
  #26 = Utf8               MethodParameters
  #27 = Utf8               InnerClasses
  #28 = Utf8               SourceFile
  #29 = Utf8               ScalaInlineInfo
  #30 = Utf8               Scala
{
  public void checkInput(int, int);
    descriptor: (II)V
    flags: (0x0001) ACC_PUBLIC
    Code:
      stack=0, locals=3, args_size=3
         0: return
      LineNumberTable:
        line 294: 0
      LocalVariableTable:
        Start  Length  Slot  Name   Signature
            0       1     0  this   Lscala/io/Source$RelaxedPosition$;
            0       1     1  line   I
            0       1     2 column   I
    MethodParameters:
      Name                           Flags
      line                           final
      column                         final

  public scala.io.Source$RelaxedPosition$(scala.io.Source);
    descriptor: (Lscala/io/Source;)V
    flags: (0x0001) ACC_PUBLIC
    Code:
      stack=1, locals=2, args_size=2
         0: aload_0
         1: invokespecial #21                 // Method scala/io/Position."<init>":()V
         4: return
      LineNumberTable:
        line 293: 0
      LocalVariableTable:
        Start  Length  Slot  Name   Signature
            0       5     0  this   Lscala/io/Source$RelaxedPosition$;
            0       5     1 $outer   Lscala/io/Source;
    MethodParameters:
      Name                           Flags
      $outer                         final synthetic
}
InnerClasses:
  public #8= #2 of #7;                    // RelaxedPosition$=class scala/io/Source$RelaxedPosition$ of class scala/io/Source
SourceFile: "Source.scala"
  ScalaInlineInfo: length = 0xE (unknown attribute)
   01 01 00 02 00 10 00 11 01 00 09 00 0A 01
  Scala: length = 0x0 (unknown attribute)

