Classfile /Users/mw/Projects/slang-braindump/.jar/jar11/assemble/slang-braindump/assemble/content/coursier/ivy/IvyRepository$$anonfun$1.class
  Last modified May 29, 2022; size 2750 bytes
  SHA-256 checksum b4e6b804634add5ffe4cf44912be4d7e9aab2a07d0a95007d7b3135019ffe362
  Compiled from "IvyRepository.scala"
public final class coursier.ivy.IvyRepository$$anonfun$1 extends scala.runtime.AbstractPartialFunction<scala.Tuple2<coursier.core.Configuration, coursier.core.Publication>, coursier.core.Publication> implements java.io.Serializable
  minor version: 0
  major version: 52
  flags: (0x0031) ACC_PUBLIC, ACC_FINAL, ACC_SUPER
  this_class: #2                          // coursier/ivy/IvyRepository$$anonfun$1
  super_class: #5                         // scala/runtime/AbstractPartialFunction
  interfaces: 1, fields: 2, methods: 5, attributes: 6
Constant pool:
   #1 = Utf8               coursier/ivy/IvyRepository$$anonfun$1
   #2 = Class              #1             // coursier/ivy/IvyRepository$$anonfun$1
   #3 = Utf8               Lscala/runtime/AbstractPartialFunction<Lscala/Tuple2<Lcoursier/core/Configuration;Lcoursier/core/Publication;>;Lcoursier/core/Publication;>;Ljava/io/Serializable;
   #4 = Utf8               scala/runtime/AbstractPartialFunction
   #5 = Class              #4             // scala/runtime/AbstractPartialFunction
   #6 = Utf8               java/io/Serializable
   #7 = Class              #6             // java/io/Serializable
   #8 = Utf8               IvyRepository.scala
   #9 = Utf8               coursier/ivy/IvyRepository
  #10 = Class              #9             // coursier/ivy/IvyRepository
  #11 = Utf8               artifacts
  #12 = Utf8               (Lcoursier/core/Dependency;Lcoursier/core/Project;Lscala/Option;)Lscala/collection/immutable/Seq;
  #13 = NameAndType        #11:#12        // artifacts:(Lcoursier/core/Dependency;Lcoursier/core/Project;Lscala/Option;)Lscala/collection/immutable/Seq;
  #14 = Utf8               serialVersionUID
  #15 = Utf8               J
  #16 = Long               0l
  #18 = Utf8               dependency$1
  #19 = Utf8               Lcoursier/core/Dependency;
  #20 = Utf8               applyOrElse
  #21 = Utf8               (Lscala/Tuple2;Lscala/Function1;)Ljava/lang/Object;
  #22 = Utf8               <A1:Lscala/Tuple2<Lcoursier/core/Configuration;Lcoursier/core/Publication;>;B1:Ljava/lang/Object;>(TA1;Lscala/Function1<TA1;TB1;>;)TB1;
  #23 = Utf8               x1
  #24 = Utf8               default
  #25 = Utf8               scala/Tuple2
  #26 = Class              #25            // scala/Tuple2
  #27 = Utf8               _2
  #28 = Utf8               ()Ljava/lang/Object;
  #29 = NameAndType        #27:#28        // _2:()Ljava/lang/Object;
  #30 = Methodref          #26.#29        // scala/Tuple2._2:()Ljava/lang/Object;
  #31 = Utf8               coursier/core/Publication
  #32 = Class              #31            // coursier/core/Publication
  #33 = Utf8               classifier
  #34 = Utf8               ()Ljava/lang/String;
  #35 = NameAndType        #33:#34        // classifier:()Ljava/lang/String;
  #36 = Methodref          #32.#35        // coursier/core/Publication.classifier:()Ljava/lang/String;
  #37 = NameAndType        #18:#19        // dependency$1:Lcoursier/core/Dependency;
  #38 = Fieldref           #2.#37         // coursier/ivy/IvyRepository$$anonfun$1.dependency$1:Lcoursier/core/Dependency;
  #39 = Utf8               coursier/core/Dependency
  #40 = Class              #39            // coursier/core/Dependency
  #41 = Utf8               attributes
  #42 = Utf8               ()Lcoursier/core/Attributes;
  #43 = NameAndType        #41:#42        // attributes:()Lcoursier/core/Attributes;
  #44 = Methodref          #40.#43        // coursier/core/Dependency.attributes:()Lcoursier/core/Attributes;
  #45 = Utf8               coursier/core/Attributes
  #46 = Class              #45            // coursier/core/Attributes
  #47 = Methodref          #46.#35        // coursier/core/Attributes.classifier:()Ljava/lang/String;
  #48 = Utf8               scala/Function1
  #49 = Class              #48            // scala/Function1
  #50 = Utf8               java/lang/String
  #51 = Class              #50            // java/lang/String
  #52 = Utf8               java/lang/Object
  #53 = Class              #52            // java/lang/Object
  #54 = Utf8               equals
  #55 = Utf8               (Ljava/lang/Object;)Z
  #56 = NameAndType        #54:#55        // equals:(Ljava/lang/Object;)Z
  #57 = Methodref          #53.#56        // java/lang/Object.equals:(Ljava/lang/Object;)Z
  #58 = Utf8               apply
  #59 = Utf8               (Ljava/lang/Object;)Ljava/lang/Object;
  #60 = NameAndType        #58:#59        // apply:(Ljava/lang/Object;)Ljava/lang/Object;
  #61 = InterfaceMethodref #49.#60        // scala/Function1.apply:(Ljava/lang/Object;)Ljava/lang/Object;
  #62 = Utf8               p
  #63 = Utf8               Lcoursier/core/Publication;
  #64 = Utf8               this
  #65 = Utf8               Lcoursier/ivy/IvyRepository$$anonfun$1;
  #66 = Utf8               Lscala/Tuple2;
  #67 = Utf8               Lscala/Function1;
  #68 = Utf8               isDefinedAt
  #69 = Utf8               (Lscala/Tuple2;)Z
  #70 = Utf8               (Lscala/Tuple2<Lcoursier/core/Configuration;Lcoursier/core/Publication;>;)Z
  #71 = Utf8               x
  #72 = NameAndType        #68:#69        // isDefinedAt:(Lscala/Tuple2;)Z
  #73 = Methodref          #2.#72         // coursier/ivy/IvyRepository$$anonfun$1.isDefinedAt:(Lscala/Tuple2;)Z
  #74 = Utf8               Ljava/lang/Object;
  #75 = Utf8               (Ljava/lang/Object;Lscala/Function1;)Ljava/lang/Object;
  #76 = NameAndType        #20:#21        // applyOrElse:(Lscala/Tuple2;Lscala/Function1;)Ljava/lang/Object;
  #77 = Methodref          #2.#76         // coursier/ivy/IvyRepository$$anonfun$1.applyOrElse:(Lscala/Tuple2;Lscala/Function1;)Ljava/lang/Object;
  #78 = Utf8               <init>
  #79 = Utf8               (Lcoursier/ivy/IvyRepository;Lcoursier/core/Dependency;)V
  #80 = Utf8               $outer
  #81 = Utf8               ()V
  #82 = NameAndType        #78:#81        // "<init>":()V
  #83 = Methodref          #5.#82         // scala/runtime/AbstractPartialFunction."<init>":()V
  #84 = Utf8               Lcoursier/ivy/IvyRepository;
  #85 = Utf8               ConstantValue
  #86 = Utf8               Code
  #87 = Utf8               StackMapTable
  #88 = Utf8               LineNumberTable
  #89 = Utf8               LocalVariableTable
  #90 = Utf8               Signature
  #91 = Utf8               MethodParameters
  #92 = Utf8               InnerClasses
  #93 = Utf8               EnclosingMethod
  #94 = Utf8               SourceFile
  #95 = Utf8               ScalaInlineInfo
  #96 = Utf8               Scala
{
  private static final long serialVersionUID;
    descriptor: J
    flags: (0x001a) ACC_PRIVATE, ACC_STATIC, ACC_FINAL
    ConstantValue: long 0l

  private final coursier.core.Dependency dependency$1;
    descriptor: Lcoursier/core/Dependency;
    flags: (0x0012) ACC_PRIVATE, ACC_FINAL

  public final <A1 extends scala.Tuple2<coursier.core.Configuration, coursier.core.Publication>, B1 extends java.lang.Object> B1 applyOrElse(A1, scala.Function1<A1, B1>);
    descriptor: (Lscala/Tuple2;Lscala/Function1;)Ljava/lang/Object;
    flags: (0x0011) ACC_PUBLIC, ACC_FINAL
    Code:
      stack=2, locals=7, args_size=3
         0: aload_1
         1: astore        4
         3: aload         4
         5: ifnull        65
         8: aload         4
        10: invokevirtual #30                 // Method scala/Tuple2._2:()Ljava/lang/Object;
        13: checkcast     #32                 // class coursier/core/Publication
        16: astore        5
        18: aload         5
        20: invokevirtual #36                 // Method coursier/core/Publication.classifier:()Ljava/lang/String;
        23: aload_0
        24: getfield      #38                 // Field dependency$1:Lcoursier/core/Dependency;
        27: invokevirtual #44                 // Method coursier/core/Dependency.attributes:()Lcoursier/core/Attributes;
        30: invokevirtual #47                 // Method coursier/core/Attributes.classifier:()Ljava/lang/String;
        33: astore        6
        35: dup
        36: ifnonnull     48
        39: pop
        40: aload         6
        42: ifnull        56
        45: goto          62
        48: aload         6
        50: invokevirtual #57                 // Method java/lang/Object.equals:(Ljava/lang/Object;)Z
        53: ifeq          62
        56: aload         5
        58: astore_3
        59: goto          79
        62: goto          68
        65: goto          68
        68: aload_2
        69: aload_1
        70: invokeinterface #61,  2           // InterfaceMethod scala/Function1.apply:(Ljava/lang/Object;)Ljava/lang/Object;
        75: astore_3
        76: goto          79
        79: aload_3
        80: areturn
      StackMapTable: number_of_entries = 6
        frame_type = 255 /* full_frame */
          offset_delta = 48
          locals = [ class coursier/ivy/IvyRepository$$anonfun$1, class scala/Tuple2, class scala/Function1, top, class scala/Tuple2, class coursier/core/Publication, class java/lang/String ]
          stack = [ class java/lang/String ]
        frame_type = 7 /* same */
        frame_type = 5 /* same */
        frame_type = 249 /* chop */
          offset_delta = 2
        frame_type = 2 /* same */
        frame_type = 255 /* full_frame */
          offset_delta = 10
          locals = [ class coursier/ivy/IvyRepository$$anonfun$1, class scala/Tuple2, class scala/Function1, class java/lang/Object, class scala/Tuple2 ]
          stack = []
      LineNumberTable:
        line 100: 0
        line 101: 3
        line 102: 56
        line 101: 62
        line 100: 68
      LocalVariableTable:
        Start  Length  Slot  Name   Signature
           18      47     5     p   Lcoursier/core/Publication;
            0      81     0  this   Lcoursier/ivy/IvyRepository$$anonfun$1;
            0      81     1    x1   Lscala/Tuple2;
            0      81     2 default   Lscala/Function1;
    Signature: #22                          // <A1:Lscala/Tuple2<Lcoursier/core/Configuration;Lcoursier/core/Publication;>;B1:Ljava/lang/Object;>(TA1;Lscala/Function1<TA1;TB1;>;)TB1;
    MethodParameters:
      Name                           Flags
      x1                             final
      default                        final

  public final boolean isDefinedAt(scala.Tuple2<coursier.core.Configuration, coursier.core.Publication>);
    descriptor: (Lscala/Tuple2;)Z
    flags: (0x0011) ACC_PUBLIC, ACC_FINAL
    Code:
      stack=2, locals=6, args_size=2
         0: aload_1
         1: astore_3
         2: aload_3
         3: ifnull        61
         6: aload_3
         7: invokevirtual #30                 // Method scala/Tuple2._2:()Ljava/lang/Object;
        10: checkcast     #32                 // class coursier/core/Publication
        13: astore        4
        15: aload         4
        17: invokevirtual #36                 // Method coursier/core/Publication.classifier:()Ljava/lang/String;
        20: aload_0
        21: getfield      #38                 // Field dependency$1:Lcoursier/core/Dependency;
        24: invokevirtual #44                 // Method coursier/core/Dependency.attributes:()Lcoursier/core/Attributes;
        27: invokevirtual #47                 // Method coursier/core/Attributes.classifier:()Ljava/lang/String;
        30: astore        5
        32: dup
        33: ifnonnull     45
        36: pop
        37: aload         5
        39: ifnull        53
        42: goto          58
        45: aload         5
        47: invokevirtual #57                 // Method java/lang/Object.equals:(Ljava/lang/Object;)Z
        50: ifeq          58
        53: iconst_1
        54: istore_2
        55: goto          69
        58: goto          64
        61: goto          64
        64: iconst_0
        65: istore_2
        66: goto          69
        69: iload_2
        70: ireturn
      StackMapTable: number_of_entries = 6
        frame_type = 255 /* full_frame */
          offset_delta = 45
          locals = [ class coursier/ivy/IvyRepository$$anonfun$1, class scala/Tuple2, top, class scala/Tuple2, class coursier/core/Publication, class java/lang/String ]
          stack = [ class java/lang/String ]
        frame_type = 7 /* same */
        frame_type = 4 /* same */
        frame_type = 249 /* chop */
          offset_delta = 2
        frame_type = 2 /* same */
        frame_type = 255 /* full_frame */
          offset_delta = 4
          locals = [ class coursier/ivy/IvyRepository$$anonfun$1, class scala/Tuple2, int, class scala/Tuple2 ]
          stack = []
      LineNumberTable:
        line 100: 0
        line 101: 2
        line 102: 53
        line 101: 58
        line 100: 64
      LocalVariableTable:
        Start  Length  Slot  Name   Signature
           15      46     4     p   Lcoursier/core/Publication;
            0      71     0  this   Lcoursier/ivy/IvyRepository$$anonfun$1;
            0      71     1    x1   Lscala/Tuple2;
    Signature: #70                          // (Lscala/Tuple2<Lcoursier/core/Configuration;Lcoursier/core/Publication;>;)Z
    MethodParameters:
      Name                           Flags
      x1                             final

  public final boolean isDefinedAt(java.lang.Object);
    descriptor: (Ljava/lang/Object;)Z
    flags: (0x1051) ACC_PUBLIC, ACC_FINAL, ACC_BRIDGE, ACC_SYNTHETIC
    Code:
      stack=2, locals=2, args_size=2
         0: aload_0
         1: aload_1
         2: checkcast     #26                 // class scala/Tuple2
         5: invokevirtual #73                 // Method isDefinedAt:(Lscala/Tuple2;)Z
         8: ireturn
      LineNumberTable:
        line 100: 0
      LocalVariableTable:
        Start  Length  Slot  Name   Signature
            0       9     0  this   Lcoursier/ivy/IvyRepository$$anonfun$1;
            0       9     1     x   Ljava/lang/Object;
    MethodParameters:
      Name                           Flags
      x                              final

  public final java.lang.Object applyOrElse(java.lang.Object, scala.Function1);
    descriptor: (Ljava/lang/Object;Lscala/Function1;)Ljava/lang/Object;
    flags: (0x1051) ACC_PUBLIC, ACC_FINAL, ACC_BRIDGE, ACC_SYNTHETIC
    Code:
      stack=3, locals=3, args_size=3
         0: aload_0
         1: aload_1
         2: checkcast     #26                 // class scala/Tuple2
         5: aload_2
         6: invokevirtual #77                 // Method applyOrElse:(Lscala/Tuple2;Lscala/Function1;)Ljava/lang/Object;
         9: areturn
      LineNumberTable:
        line 100: 0
      LocalVariableTable:
        Start  Length  Slot  Name   Signature
            0      10     0  this   Lcoursier/ivy/IvyRepository$$anonfun$1;
            0      10     1     x   Ljava/lang/Object;
            0      10     2 default   Lscala/Function1;
    MethodParameters:
      Name                           Flags
      x                              final
      default                        final

  public coursier.ivy.IvyRepository$$anonfun$1(coursier.ivy.IvyRepository, coursier.core.Dependency);
    descriptor: (Lcoursier/ivy/IvyRepository;Lcoursier/core/Dependency;)V
    flags: (0x0001) ACC_PUBLIC
    Code:
      stack=2, locals=3, args_size=3
         0: aload_0
         1: aload_2
         2: putfield      #38                 // Field dependency$1:Lcoursier/core/Dependency;
         5: aload_0
         6: invokespecial #83                 // Method scala/runtime/AbstractPartialFunction."<init>":()V
         9: return
      LineNumberTable:
        line 78: 0
        line 100: 5
      LocalVariableTable:
        Start  Length  Slot  Name   Signature
            0      10     0  this   Lcoursier/ivy/IvyRepository$$anonfun$1;
            0      10     1 $outer   Lcoursier/ivy/IvyRepository;
            0      10     2 dependency$1   Lcoursier/core/Dependency;
    MethodParameters:
      Name                           Flags
      $outer                         final synthetic
      dependency$1                   final
}
InnerClasses:
  public final #2;                        // class coursier/ivy/IvyRepository$$anonfun$1
EnclosingMethod: #10.#13                // coursier.ivy.IvyRepository.artifacts
Signature: #3                           // Lscala/runtime/AbstractPartialFunction<Lscala/Tuple2<Lcoursier/core/Configuration;Lcoursier/core/Publication;>;Lcoursier/core/Publication;>;Ljava/io/Serializable;
SourceFile: "IvyRepository.scala"
  ScalaInlineInfo: length = 0x1D (unknown attribute)
   01 01 00 05 00 4E 00 4F 01 00 14 00 4B 01 00 14
   00 15 01 00 44 00 33 01 00 44 00 45 01
  Scala: length = 0x0 (unknown attribute)

