Classfile /Users/mw/Projects/slang-braindump/.jar/jar11/assemble/slang-braindump/assemble/content/coursier/ivy/PropertiesPattern.class
  Last modified May 29, 2022; size 14970 bytes
  SHA-256 checksum 4ca2bc8d05a4cccd6d63a0a62253e6b032fdc09f33ccb96e7d16b3d0300deffd
  Compiled from "Pattern.scala"
public final class coursier.ivy.PropertiesPattern implements scala.Product,java.io.Serializable
  minor version: 0
  major version: 52
  flags: (0x0031) ACC_PUBLIC, ACC_FINAL, ACC_SUPER
  this_class: #2                          // coursier/ivy/PropertiesPattern
  super_class: #4                         // java/lang/Object
  interfaces: 2, fields: 1, methods: 25, attributes: 6
Constant pool:
    #1 = Utf8               coursier/ivy/PropertiesPattern
    #2 = Class              #1            // coursier/ivy/PropertiesPattern
    #3 = Utf8               java/lang/Object
    #4 = Class              #3            // java/lang/Object
    #5 = Utf8               scala/Product
    #6 = Class              #5            // scala/Product
    #7 = Utf8               java/io/Serializable
    #8 = Class              #7            // java/io/Serializable
    #9 = Utf8               Pattern.scala
   #10 = Utf8               Lscala/reflect/ScalaSignature;
   #11 = Utf8               bytes
   #12 = Utf8               \u0006\u0005\reb\u0001B;w\u0005mD!\"a\t\u0001\u0005\u000b\u0007I\u0011AA\u0013\u0011)\u0019\u0019\u0001\u0001B\u0001B\u0003%\u0011q\u0005\u0005\b\u0003\u000f\u0002A\u0011AB\u0003\u0011\u001d\t)\u0006\u0001C\u0001\u0003/Bqa!\u0003\u0001\t\u0003\u0019Y\u0001C\u0004\u0004 \u0001!\ta!\t\t\u000f\u0005\u001d\u0006\u0001\"\u0011\u0002*\"9\u0011Q\u0017\u0001\u0005B\r\u0015\u0002bBAe\u0001\u0011\u00053\u0011\u0006\u0005\b\u0003\u001f\u0004A\u0011IAi\u0011\u001d\tI\u000e\u0001C\u0005\u0007[Aq!a9\u0001\t\u0003\n)\u000fC\u0004\u0002h\u0002!\t%!;\t\u000f\u0005-\b\u0001\"\u0011\u00042!9\u00111\u001f\u0001\u0005B\rUraBA\u001am\"\u0005\u0011Q\u0007\u0004\u0007kZD\t!a\u000e\t\u000f\u0005\u001d\u0013\u0003\"\u0001\u0002J\u00199\u00111J\t\u0002\"\u00055\u0003bBA$\'\u0011\u0005\u0011q\n\u0005\b\u0003+\u001ab\u0011AA,\u000f\u001d\u0011\t-\u0005E\u0001\u0003c2q!a\u0013\u0012\u0011\u0003\ti\u0007C\u0004\u0002H]!\t!a\u001c\t\u000f\u0005Mt\u0003b\u0001\u0002v\u00191\u00111P\f\u0003\u0003{B!\"a \u001b\u0005\u000b\u0007I\u0011AA,\u0011)\t\tI\u0007B\u0001B\u0003%\u0011\u0011\f\u0005\u000b\u0003\u0007S\"Q1A\u0005\u0002\u0005\u0015\u0005BCAH5\t\u0005\t\u0015!\u0003\u0002\b\"9\u0011q\t\u000e\u0005\u0002\u0005E\u0005bBA+5\u0011\u0005\u0011q\u000b\u0005\b\u00037SB\u0011AAO\u0011\u001d\t\tK\u0007C\u0001\u0003GCq!a*\u001b\t\u0003\nI\u000bC\u0004\u00026j!\t%a.\t\u000f\u0005%\'\u0004\"\u0011\u0002L\"9\u0011q\u001a\u000e\u0005B\u0005E\u0007bBAm5\u0011%\u00111\u001c\u0005\b\u0003GTB\u0011IAs\u0011\u001d\t9O\u0007C!\u0003SDq!a;\u001b\t\u0003\ni\u000fC\u0004\u0002tj!\t%!>\b\u000f\u0005ex\u0003#\u0001\u0002|\u001a9\u00111P\f\t\u0002\u0005u\bbBA$[\u0011\u0005\u0011q \u0005\b\u0005\u0003iC\u0011\u0001B\u0002\u0011%\u0011I!LA\u0001\n\u0013\u0011YA\u0002\u0004\u0003\u0014]\u0011!Q\u0003\u0005\u000b\u0003\u007f\n$Q1A\u0005\u0002\u0005]\u0003BCAAc\t\u0005\t\u0015!\u0003\u0002Z!9\u0011qI\u0019\u0005\u0002\t]\u0001bBA+c\u0011\u0005\u0011q\u000b\u0005\b\u00037\u000bD\u0011\u0001B\u000f\u0011\u001d\t9+\rC!\u0003SCq!!.2\t\u0003\u0012\t\u0003C\u0004\u0002JF\"\tE!\n\t\u000f\u0005=\u0017\u0007\"\u0011\u0002R\"9\u0011\u0011\\\u0019\u0005\n\t%\u0002bBArc\u0011\u0005\u0013Q\u001d\u0005\b\u0003O\fD\u0011IAu\u0011\u001d\tY/\rC!\u0005cAq!a=2\t\u0003\u0012)dB\u0004\u0003:]A\tAa\u000f\u0007\u000f\tMq\u0003#\u0001\u0003>!9\u0011qI!\u0005\u0002\t}\u0002b\u0002B\u0001\u0003\u0012\u0005!\u0011\t\u0005\n\u0005\u0013\t\u0015\u0011!C\u0005\u0005\u00171aA!\u0012\u0018\u0005\t\u001d\u0003B\u0003B%\u000b\n\u0015\r\u0011\"\u0001\u0003L!Q!QJ#\u0003\u0002\u0003\u0006I!!$\t\u000f\u0005\u001dS\t\"\u0001\u0003P!9\u0011QK#\u0005\u0002\u0005]\u0003b\u0002B+\u000b\u0012\u0005!q\u000b\u0005\b\u0003O+E\u0011IAU\u0011\u001d\t),\u0012C!\u00057Bq!!3F\t\u0003\u0012y\u0006C\u0004\u0002P\u0016#\t%!5\t\u000f\u0005eW\t\"\u0003\u0003d!9\u00111]#\u0005B\u0005\u0015\bbBAt\u000b\u0012\u0005\u0013\u0011\u001e\u0005\b\u0003W,E\u0011\tB4\u0011\u001d\t\u00190\u0012C!\u0005W:qAa\u001c\u0018\u0011\u0003\u0011\tHB\u0004\u0003F]A\tAa\u001d\t\u000f\u0005\u001dS\u000b\"\u0001\u0003v!9!\u0011A+\u0005\u0002\t]\u0004b\u0002B\u0001+\u0012\u0005!Q\u0010\u0005\b\u0005\u0003)F\u0011\u0001BC\u0011\u001d\u0011\t!\u0016C\u0001\u0005\u001fC\u0011B!\u0003V\u0003\u0003%IAa\u0003\u0007\r\u0005-tC\u0001BR\u0011)\u0011\t\u000b\u0018BC\u0002\u0013\u0005\u0011q\u000b\u0005\u000b\u0005Kc&\u0011!Q\u0001\n\u0005e\u0003bBA$9\u0012\u0005!q\u0015\u0005\b\u0003+bF\u0011AA,\u0011\u001d\u0011Y\u000b\u0018C\u0001\u0005[Cq!a*]\t\u0003\nI\u000bC\u0004\u00026r#\tE!-\t\u000f\u0005%G\f\"\u0011\u00036\"9\u0011q\u001a/\u0005B\u0005E\u0007bBAm9\u0012%!\u0011\u0006\u0005\b\u0003GdF\u0011IAs\u0011\u001d\t9\u000f\u0018C!\u0003SDq!a;]\t\u0003\u0012I\fC\u0004\u0002tr#\tE!0\b\u000f\tMu\u0003#\u0001\u0003\u0016\u001a9\u00111N\f\t\u0002\t]\u0005bBA$Y\u0012\u0005!\u0011\u0014\u0005\b\u0005\u0003aG\u0011\u0001BN\u0011%\u0011I\u0001\\A\u0001\n\u0013\u0011Y\u0001C\u0005\u0003\n]\t\t\u0011\"\u0003\u0003\f!9!1Y\t\u0005\n\t\u0015\u0007b\u0002Bx#\u0011\u0005!\u0011\u001f\u0005\b\u0005\u0003\tB\u0011\u0001B\u0000\u0011%\u0011I!EA\u0001\n\u0013\u0011YAA\tQe>\u0004XM\u001d;jKN\u0004\u0016\r\u001e;fe:T!a\u001e=\u0002\u0007%4\u0018PC\u0001z\u0003!\u0019w.\u001e:tS\u0016\u00148\u0001A\n\u0007\u0001q\f)!a\u0003\u0011\u0007u\f\t!D\u0001\u007f\u0015\u0005y\u0018!B:dC2\f\u0017bAA\u0002}\n1\u0011I\\=SK\u001a\u00042!`A\u0004\u0013\r\tIA \u0002\b!J|G-^2u!\u0011\ti!!\b\u000f\t\u0005=\u0011\u0011\u0004\b\u0005\u0003#\t9\"\u0004\u0002\u0002\u0014)\u0019\u0011Q\u0003>\u0002\rq\u0012xn\u001c;?\u0013\u0005y\u0018bAA\u000e}\u00069\u0001/Y2lC\u001e,\u0017\u0002BA\u0010\u0003C\u0011AbU3sS\u0006d\u0017N_1cY\u0016T1!a\u0007\u007f\u0003\u0019\u0019\u0007.\u001e8lgV\u0011\u0011q\u0005\t\u0007\u0003\u001b\tI#!\f\n\t\u0005-\u0012\u0011\u0005\u0002\u0004\'\u0016\f\bcAA\u0018\'9\u0019\u0011\u0011\u0007\t\u000e\u0003Y\f\u0011\u0003\u0015:pa\u0016\u0014H/[3t!\u0006$H/\u001a:o!\r\t\t$E\n\u0005#q\fI\u0004\u0005\u0003\u0002<\u0005\u0015SBAA\u001f\u0015\u0011\ty$!\u0011\u0002\u0005%|\'BAA\"\u0003\u0011Q\u0017M^1\n\t\u0005}\u0011QH\u0001\u0007y%t\u0017\u000e\u001e \u0015\u0005\u0005U\"aD\"ik:\\wJ\u001d)s_B,\'\u000f^=\u0014\rMa\u0018QAA\u0006)\t\t\t\u0006E\u0002\u0002TMi\u0011!E\u0001\u0007gR\u0014\u0018N\\4\u0016\u0005\u0005e\u0003\u0003BA.\u0003GrA!!\u0018\u0002`A\u0019\u0011\u0011\u0003@\n\u0007\u0005\u0005d0\u0001\u0004Qe\u0016$WMZ\u0005\u0005\u0003K\n9G\u0001\u0004TiJLgn\u001a\u0006\u0004\u0003Cr\u0018&B\n]\u000bj\t$!B\"p]N$8\u0003B\f}\u0003s!\"!!\u001d\u0011\u0007\u0005Ms#\u0001\u0006ge>l7\u000b\u001e:j]\u001e$B!!\u0015\u0002x!9\u0011\u0011P\rA\u0002\u0005e\u0013!A:\u0003\tA\u0013x\u000e]\n\b5\u0005E\u0013QAA\u0006\u0003\u0011q\u0017-\\3\u0002\u000b9\fW.\u001a\u0011\u0002\u0017\u0005dG/\u001a:oCRLg/Z\u000b\u0003\u0003\u000f\u0003R!`AE\u0003\u001bK1!a#\u007f\u0005\u0019y\u0005\u000f^5p]B1\u0011QBA\u0015\u0003#\nA\"\u00197uKJt\u0017\r^5wK\u0002\"b!a%\u0002\u0018\u0006e\u0005cAAK55\tq\u0003C\u0004\u0002\u0000}\u0001\r!!\u0017\t\u000f\u0005\ru\u00041\u0001\u0002\b\u0006Aq/\u001b;i\u001d\u0006lW\r\u0006\u0003\u0002\u0014\u0006}\u0005bBA@C\u0001\u0007\u0011\u0011L\u0001\u0010o&$\b.\u00117uKJt\u0017\r^5wKR!\u00111SAS\u0011\u001d\t\u0019I\ta\u0001\u0003\u000f\u000b\u0001\u0002^8TiJLgn\u001a\u000b\u0003\u0003W\u0003B!!,\u000246\u0011\u0011q\u0016\u0006\u0005\u0003c\u000b\t%\u0001\u0003mC:<\u0017\u0002BA3\u0003_\u000b\u0001bY1o\u000bF,\u0018\r\u001c\u000b\u0005\u0003s\u000by\fE\u0002~\u0003wK1!!0\u007f\u0005\u001d\u0011un\u001c7fC:Dq!!1%\u0001\u0004\t\u0019-A\u0002pE*\u00042!`Ac\u0013\r\t9M \u0002\u0004\u0003:L\u0018AB3rk\u0006d7\u000f\u0006\u0003\u0002:\u00065\u0007bBAaK\u0001\u0007\u00111Y\u0001\tQ\u0006\u001c\bnQ8eKR\u0011\u00111\u001b\t\u0004{\u0006U\u0017bAAl}\n\u0019\u0011J\u001c;\u0002\u000bQ,\b\u000f\\3\u0016\u0005\u0005u\u0007cB?\u0002`\u0006e\u0013qQ\u0005\u0004\u0003Ct(A\u0002+va2,\'\'A\u0007qe>$Wo\u0019;Qe\u00164\u0017\u000e_\u000b\u0003\u0003W\u000bA\u0002\u001d:pIV\u001cG/\u0011:jif,\"!a5\u0002\u001dA\u0014x\u000eZ;di\u0016cW-\\3oiR!\u00111YAx\u0011\u001d\t\tP\u000ba\u0001\u0003\'\f\u0011A\\\u0001\u0013aJ|G-^2u\u000b2,W.\u001a8u\u001d\u0006lW\r\u0006\u0003\u0002,\u0006]\bbBAyW\u0001\u0007\u00111[\u0001\u0005!J|\u0007\u000fE\u0002\u0002\u00166\u001aB!\f?\u0002:Q\u0011\u00111`\u0001\u0006CB\u0004H.\u001f\u000b\u0007\u0003\'\u0013)Aa\u0002\t\u000f\u0005}t\u00061\u0001\u0002Z!9\u00111Q\u0018A\u0002\u0005\u001d\u0015\u0001D<sSR,\'+\u001a9mC\u000e,GC\u0001B\u0007!\u0011\tiKa\u0004\n\t\tE\u0011q\u0016\u0002\u0007\u001f\nTWm\u0019;\u0003\u0007Y\u000b\'oE\u00042\u0003#\n)!a\u0003\u0015\t\te!1\u0004\t\u0004\u0003+\u000b\u0004bBA@i\u0001\u0007\u0011\u0011\f\u000b\u0005\u00053\u0011y\u0002C\u0004\u0002\u0000Y\u0002\r!!\u0017\u0015\t\u0005e&1\u0005\u0005\b\u0003\u0003D\u0004\u0019AAb)\u0011\tILa\n\t\u000f\u0005\u0005\u0017\b1\u0001\u0002DV\u0011!1\u0006\t\u0006{\n5\u0012\u0011L\u0005\u0004\u0005_q(A\u0002+va2,\u0017\u0007\u0006\u0003\u0002D\nM\u0002bBAy}\u0001\u0007\u00111\u001b\u000b\u0005\u0003W\u00139\u0004C\u0004\u0002r~\u0002\r!a5\u0002\u0007Y\u000b\'\u000fE\u0002\u0002\u0016\u0006\u001bB!\u0011?\u0002:Q\u0011!1\b\u000b\u0005\u00053\u0011\u0019\u0005C\u0004\u0002\u0000\r\u0003\r!!\u0017\u0003\u0007=\u0003HoE\u0004F\u0003#\n)!a\u0003\u0002\u000f\r|g\u000e^3oiV\u0011\u0011QR\u0001\tG>tG/\u001a8uAQ!!\u0011\u000bB*!\r\t)*\u0012\u0005\b\u0005\u0013B\u0005\u0019AAG\u0003-9\u0018\u000e\u001e5D_:$XM\u001c;\u0015\t\tE#\u0011\f\u0005\b\u0005\u0013R\u0005\u0019AAG)\u0011\tIL!\u0018\t\u000f\u0005\u0005G\n1\u0001\u0002DR!\u0011\u0011\u0018B1\u0011\u001d\t\t-\u0014a\u0001\u0003\u0007,\"A!\u001a\u0011\u000bu\u0014i#!$\u0015\t\u0005\r\'\u0011\u000e\u0005\b\u0003c\u0014\u0006\u0019AAj)\u0011\tYK!\u001c\t\u000f\u0005E8\u000b1\u0001\u0002T\u0006\u0019q\n\u001d;\u0011\u0007\u0005UUk\u0005\u0003Vy\u0006eBC\u0001B9)\u0011\u0011\tF!\u001f\t\u000f\tmt\u000b1\u0001\u0002R\u0005!Q\r\\3n)\u0019\u0011\tFa \u0003\u0002\"9!1\u0010-A\u0002\u0005E\u0003b\u0002BB1\u0002\u0007\u0011\u0011K\u0001\u0006K2,W.\r\u000b\t\u0005#\u00129I!#\u0003\f\"9!1P-A\u0002\u0005E\u0003b\u0002BB3\u0002\u0007\u0011\u0011\u000b\u0005\b\u0005\u001bK\u0006\u0019AA)\u0003\u0015)G.Z73)\u0011\u0011\tF!%\t\u000f\t%#\f1\u0001\u0002\u000e\u0006)1i\u001c8tiB\u0019\u0011Q\u00137\u0014\t1d\u0018\u0011\b\u000b\u0003\u0005+#BA!(\u0003 B\u0019\u0011Q\u0013/\t\u000f\t\u0005f\u000e1\u0001\u0002Z\u0005)a/\u00197vKN9A,!\u0015\u0002\u0006\u0005-\u0011A\u0002<bYV,\u0007\u0005\u0006\u0003\u0003\u001e\n%\u0006b\u0002BQ?\u0002\u0007\u0011\u0011L\u0001\no&$\bNV1mk\u0016$BA!(\u00030\"9!\u0011U1A\u0002\u0005eC\u0003BA]\u0005gCq!!1d\u0001\u0004\t\u0019\r\u0006\u0003\u0002:\n]\u0006bBAaI\u0002\u0007\u00111\u0019\u000b\u0005\u0003\u0007\u0014Y\fC\u0004\u0002r&\u0004\r!a5\u0015\t\u0005-&q\u0018\u0005\b\u0003cT\u0007\u0019AAj\u0003=\u0019\u0005.\u001e8l\u001fJ\u0004&o\u001c9feRL\u0018A\u00029beN,\'/\u0006\u0003\u0003H\n\rH\u0003\u0002Be\u0005;\u0004bAa3\u0003X\u00065e\u0002\u0002Bg\u0005\'tA!!\u0005\u0003P&\u0011!\u0011[\u0001\nM\u0006\u001cH\u000f]1sg\u0016LA!a\u0007\u0003V*\u0011!\u0011[\u0005\u0005\u00053\u0014YNA\u0001Q\u0015\u0011\tYB!6\t\u0013\t}\u0017/!AA\u0004\t\u0005\u0018AC3wS\u0012,gnY3%cA1!1\u001aBl\u0003\u0007$qA!:r\u0005\u0004\u00119OA\u0001`#\u0011\u0011I/a1\u0011\u0007u\u0014Y/C\u0002\u0003nz\u0014qAT8uQ&tw-A\u0003qCJ\u001cX\r\u0006\u0003\u0003t\nm\b\u0003CA\u0007\u0005k\fIF!?\n\t\t]\u0018\u0011\u0005\u0002\u0007\u000b&$\b.\u001a:\u0011\u0007\u0005E\u0002\u0001C\u0004\u0003~J\u0004\r!!\u0017\u0002\u000fA\fG\u000f^3s]R!!\u0011`B\u0001\u0011\u001d\t\u0019c\u001da\u0001\u0003O\tqa\u00195v].\u001c\b\u0005\u0006\u0003\u0003z\u000e\u001d\u0001bBA\u0012\u0007\u0001\u0007\u0011qE\u0001\u0015gV\u00147\u000f^5ukR,\u0007K]8qKJ$\u0018.Z:\u0015\t\r51Q\u0003\t\t\u0003\u001b\u0011)0!\u0017\u0004\u0010A!\u0011\u0011GB\t\u0013\r\u0019\u0019B\u001e\u0002\b!\u0006$H/\u001a:o\u0011\u001d\u00199\"\u0002a\u0001\u00073\t!\u0002\u001d:pa\u0016\u0014H/[3t!!\tYfa\u0007\u0002Z\u0005e\u0013\u0002BB\u000f\u0003O\u00121!T1q\u0003)9\u0018\u000e\u001e5DQVt7n\u001d\u000b\u0005\u0005s\u001c\u0019\u0003C\u0004\u0002$\u0019\u0001\r!a\n\u0015\t\u0005e6q\u0005\u0005\b\u0003\u0003D\u0001\u0019AAb)\u0011\tIla\u000b\t\u000f\u0005\u0005\u0017\u00021\u0001\u0002DV\u00111q\u0006\t\u0006{\n5\u0012q\u0005\u000b\u0005\u0003\u0007\u001c\u0019\u0004C\u0004\u0002r:\u0001\r!a5\u0015\t\u0005-6q\u0007\u0005\b\u0003c|\u0001\u0019AAj\u0001
   #13 = Utf8               coursier/ivy/Pattern$Chunk$
   #14 = Class              #13           // coursier/ivy/Pattern$Chunk$
   #15 = Utf8               coursier/ivy/Pattern
   #16 = Class              #15           // coursier/ivy/Pattern
   #17 = Utf8
   #18 = Utf8               coursier/ivy/Pattern$Chunk$Const
   #19 = Class              #18           // coursier/ivy/Pattern$Chunk$Const
   #20 = Utf8               Const
   #21 = Utf8               coursier/ivy/Pattern$Chunk$Const$
   #22 = Class              #21           // coursier/ivy/Pattern$Chunk$Const$
   #23 = Utf8               coursier/ivy/Pattern$Chunk$Opt
   #24 = Class              #23           // coursier/ivy/Pattern$Chunk$Opt
   #25 = Utf8               Opt
   #26 = Utf8               coursier/ivy/Pattern$Chunk$Opt$
   #27 = Class              #26           // coursier/ivy/Pattern$Chunk$Opt$
   #28 = Utf8               coursier/ivy/Pattern$Chunk$Var
   #29 = Class              #28           // coursier/ivy/Pattern$Chunk$Var
   #30 = Utf8               Var
   #31 = Utf8               coursier/ivy/Pattern$Chunk$Var$
   #32 = Class              #31           // coursier/ivy/Pattern$Chunk$Var$
   #33 = Utf8               coursier/ivy/PropertiesPattern$ChunkOrProperty
   #34 = Class              #33           // coursier/ivy/PropertiesPattern$ChunkOrProperty
   #35 = Utf8               ChunkOrProperty
   #36 = Utf8               coursier/ivy/PropertiesPattern$ChunkOrProperty$
   #37 = Class              #36           // coursier/ivy/PropertiesPattern$ChunkOrProperty$
   #38 = Utf8               coursier/ivy/PropertiesPattern$ChunkOrProperty$Const
   #39 = Class              #38           // coursier/ivy/PropertiesPattern$ChunkOrProperty$Const
   #40 = Utf8               coursier/ivy/PropertiesPattern$ChunkOrProperty$Opt
   #41 = Class              #40           // coursier/ivy/PropertiesPattern$ChunkOrProperty$Opt
   #42 = Utf8               coursier/ivy/PropertiesPattern$ChunkOrProperty$Prop
   #43 = Class              #42           // coursier/ivy/PropertiesPattern$ChunkOrProperty$Prop
   #44 = Utf8               Prop
   #45 = Utf8               coursier/ivy/PropertiesPattern$ChunkOrProperty$Var
   #46 = Class              #45           // coursier/ivy/PropertiesPattern$ChunkOrProperty$Var
   #47 = Utf8               coursier/util/Traverse$TraverseOps
   #48 = Class              #47           // coursier/util/Traverse$TraverseOps
   #49 = Utf8               coursier/util/Traverse
   #50 = Class              #49           // coursier/util/Traverse
   #51 = Utf8               TraverseOps
   #52 = Utf8               coursier/util/ValidationNel$FailureBuilder
   #53 = Class              #52           // coursier/util/ValidationNel$FailureBuilder
   #54 = Utf8               coursier/util/ValidationNel
   #55 = Class              #54           // coursier/util/ValidationNel
   #56 = Utf8               FailureBuilder
   #57 = Utf8               coursier/util/ValidationNel$SuccessBuilder
   #58 = Class              #57           // coursier/util/ValidationNel$SuccessBuilder
   #59 = Utf8               SuccessBuilder
   #60 = Utf8               java/lang/invoke/MethodHandles$Lookup
   #61 = Class              #60           // java/lang/invoke/MethodHandles$Lookup
   #62 = Utf8               java/lang/invoke/MethodHandles
   #63 = Class              #62           // java/lang/invoke/MethodHandles
   #64 = Utf8               Lookup
   #65 = Utf8               scala/util/Either$LeftProjection
   #66 = Class              #65           // scala/util/Either$LeftProjection
   #67 = Utf8               scala/util/Either
   #68 = Class              #67           // scala/util/Either
   #69 = Utf8               LeftProjection
   #70 = Utf8               chunks
   #71 = Utf8               Lscala/collection/immutable/Seq;
   #72 = Utf8               Lscala/collection/immutable/Seq<Lcoursier/ivy/PropertiesPattern$ChunkOrProperty;>;
   #73 = Utf8               apply
   #74 = Utf8               (Lscala/collection/immutable/Seq;)Lcoursier/ivy/PropertiesPattern;
   #75 = Utf8               (Lscala/collection/immutable/Seq<Lcoursier/ivy/PropertiesPattern$ChunkOrProperty;>;)Lcoursier/ivy/PropertiesPattern;
   #76 = Utf8               coursier/ivy/PropertiesPattern$
   #77 = Class              #76           // coursier/ivy/PropertiesPattern$
   #78 = Utf8               MODULE$
   #79 = Utf8               Lcoursier/ivy/PropertiesPattern$;
   #80 = NameAndType        #78:#79       // MODULE$:Lcoursier/ivy/PropertiesPattern$;
   #81 = Fieldref           #77.#80       // coursier/ivy/PropertiesPattern$.MODULE$:Lcoursier/ivy/PropertiesPattern$;
   #82 = NameAndType        #73:#74       // apply:(Lscala/collection/immutable/Seq;)Lcoursier/ivy/PropertiesPattern;
   #83 = Methodref          #77.#82       // coursier/ivy/PropertiesPattern$.apply:(Lscala/collection/immutable/Seq;)Lcoursier/ivy/PropertiesPattern;
   #84 = Utf8               parse
   #85 = Utf8               (Ljava/lang/String;)Lscala/util/Either;
   #86 = Utf8               (Ljava/lang/String;)Lscala/util/Either<Ljava/lang/String;Lcoursier/ivy/PropertiesPattern;>;
   #87 = Utf8               pattern
   #88 = NameAndType        #84:#85       // parse:(Ljava/lang/String;)Lscala/util/Either;
   #89 = Methodref          #77.#88       // coursier/ivy/PropertiesPattern$.parse:(Ljava/lang/String;)Lscala/util/Either;
   #90 = Utf8               productIterator
   #91 = Utf8               ()Lscala/collection/Iterator;
   #92 = Utf8               ()Lscala/collection/Iterator<Ljava/lang/Object;>;
   #93 = Utf8               productIterator$
   #94 = Utf8               (Lscala/Product;)Lscala/collection/Iterator;
   #95 = NameAndType        #93:#94       // productIterator$:(Lscala/Product;)Lscala/collection/Iterator;
   #96 = InterfaceMethodref #6.#95        // scala/Product.productIterator$:(Lscala/Product;)Lscala/collection/Iterator;
   #97 = Utf8               this
   #98 = Utf8               Lcoursier/ivy/PropertiesPattern;
   #99 = Utf8               productElementNames
  #100 = Utf8               ()Lscala/collection/Iterator<Ljava/lang/String;>;
  #101 = Utf8               productElementNames$
  #102 = NameAndType        #101:#94      // productElementNames$:(Lscala/Product;)Lscala/collection/Iterator;
  #103 = InterfaceMethodref #6.#102       // scala/Product.productElementNames$:(Lscala/Product;)Lscala/collection/Iterator;
  #104 = Utf8               ()Lscala/collection/immutable/Seq;
  #105 = Utf8               ()Lscala/collection/immutable/Seq<Lcoursier/ivy/PropertiesPattern$ChunkOrProperty;>;
  #106 = NameAndType        #70:#71       // chunks:Lscala/collection/immutable/Seq;
  #107 = Fieldref           #2.#106       // coursier/ivy/PropertiesPattern.chunks:Lscala/collection/immutable/Seq;
  #108 = Utf8               string
  #109 = Utf8               ()Ljava/lang/String;
  #110 = NameAndType        #70:#104      // chunks:()Lscala/collection/immutable/Seq;
  #111 = Methodref          #2.#110       // coursier/ivy/PropertiesPattern.chunks:()Lscala/collection/immutable/Seq;
  #112 = Utf8               (Ljava/lang/Object;)Ljava/lang/Object;
  #113 = MethodType         #112          //  (Ljava/lang/Object;)Ljava/lang/Object;
  #114 = Utf8               $anonfun$string$1
  #115 = Utf8               (Lcoursier/ivy/PropertiesPattern$ChunkOrProperty;)Ljava/lang/String;
  #116 = NameAndType        #114:#115     // $anonfun$string$1:(Lcoursier/ivy/PropertiesPattern$ChunkOrProperty;)Ljava/lang/String;
  #117 = Methodref          #2.#116       // coursier/ivy/PropertiesPattern.$anonfun$string$1:(Lcoursier/ivy/PropertiesPattern$ChunkOrProperty;)Ljava/lang/String;
  #118 = MethodHandle       6:#117        // REF_invokeStatic coursier/ivy/PropertiesPattern.$anonfun$string$1:(Lcoursier/ivy/PropertiesPattern$ChunkOrProperty;)Ljava/lang/String;
  #119 = MethodType         #115          //  (Lcoursier/ivy/PropertiesPattern$ChunkOrProperty;)Ljava/lang/String;
  #120 = Integer            5
  #121 = Integer            1
  #122 = Utf8               java/lang/invoke/LambdaMetafactory
  #123 = Class              #122          // java/lang/invoke/LambdaMetafactory
  #124 = Utf8               altMetafactory
  #125 = Utf8               (Ljava/lang/invoke/MethodHandles$Lookup;Ljava/lang/String;Ljava/lang/invoke/MethodType;[Ljava/lang/Object;)Ljava/lang/invoke/CallSite;
  #126 = NameAndType        #124:#125     // altMetafactory:(Ljava/lang/invoke/MethodHandles$Lookup;Ljava/lang/String;Ljava/lang/invoke/MethodType;[Ljava/lang/Object;)Ljava/lang/invoke/CallSite;
  #127 = Methodref          #123.#126     // java/lang/invoke/LambdaMetafactory.altMetafactory:(Ljava/lang/invoke/MethodHandles$Lookup;Ljava/lang/String;Ljava/lang/invoke/MethodType;[Ljava/lang/Object;)Ljava/lang/invoke/CallSite;
  #128 = MethodHandle       6:#127        // REF_invokeStatic java/lang/invoke/LambdaMetafactory.altMetafactory:(Ljava/lang/invoke/MethodHandles$Lookup;Ljava/lang/String;Ljava/lang/invoke/MethodType;[Ljava/lang/Object;)Ljava/lang/invoke/CallSite;
  #129 = Utf8               ()Lscala/Function1;
  #130 = NameAndType        #73:#129      // apply:()Lscala/Function1;
  #131 = InvokeDynamic      #0:#130       // #0:apply:()Lscala/Function1;
  #132 = Utf8               scala/collection/immutable/Seq
  #133 = Class              #132          // scala/collection/immutable/Seq
  #134 = Utf8               map
  #135 = Utf8               (Lscala/Function1;)Ljava/lang/Object;
  #136 = NameAndType        #134:#135     // map:(Lscala/Function1;)Ljava/lang/Object;
  #137 = InterfaceMethodref #133.#136     // scala/collection/immutable/Seq.map:(Lscala/Function1;)Ljava/lang/Object;
  #138 = Utf8               scala/collection/IterableOnceOps
  #139 = Class              #138          // scala/collection/IterableOnceOps
  #140 = Utf8               mkString
  #141 = NameAndType        #140:#109     // mkString:()Ljava/lang/String;
  #142 = InterfaceMethodref #139.#141     // scala/collection/IterableOnceOps.mkString:()Ljava/lang/String;
  #143 = Utf8               substituteProperties
  #144 = Utf8               (Lscala/collection/immutable/Map;)Lscala/util/Either;
  #145 = Utf8               (Lscala/collection/immutable/Map<Ljava/lang/String;Ljava/lang/String;>;)Lscala/util/Either<Ljava/lang/String;Lcoursier/ivy/Pattern;>;
  #146 = Utf8               properties
  #147 = Utf8               coursier/util/Traverse$
  #148 = Class              #147          // coursier/util/Traverse$
  #149 = Utf8               Lcoursier/util/Traverse$;
  #150 = NameAndType        #78:#149      // MODULE$:Lcoursier/util/Traverse$;
  #151 = Fieldref           #148.#150     // coursier/util/Traverse$.MODULE$:Lcoursier/util/Traverse$;
  #152 = Utf8               (Lscala/collection/immutable/Seq;)Lcoursier/util/Traverse$TraverseOps;
  #153 = NameAndType        #51:#152      // TraverseOps:(Lscala/collection/immutable/Seq;)Lcoursier/util/Traverse$TraverseOps;
  #154 = Methodref          #148.#153     // coursier/util/Traverse$.TraverseOps:(Lscala/collection/immutable/Seq;)Lcoursier/util/Traverse$TraverseOps;
  #155 = Utf8               $anonfun$substituteProperties$1
  #156 = Utf8               (Lscala/collection/immutable/Map;Lcoursier/ivy/PropertiesPattern$ChunkOrProperty;)Lcoursier/util/ValidationNel;
  #157 = NameAndType        #155:#156     // $anonfun$substituteProperties$1:(Lscala/collection/immutable/Map;Lcoursier/ivy/PropertiesPattern$ChunkOrProperty;)Lcoursier/util/ValidationNel;
  #158 = Methodref          #2.#157       // coursier/ivy/PropertiesPattern.$anonfun$substituteProperties$1:(Lscala/collection/immutable/Map;Lcoursier/ivy/PropertiesPattern$ChunkOrProperty;)Lcoursier/util/ValidationNel;
  #159 = MethodHandle       6:#158        // REF_invokeStatic coursier/ivy/PropertiesPattern.$anonfun$substituteProperties$1:(Lscala/collection/immutable/Map;Lcoursier/ivy/PropertiesPattern$ChunkOrProperty;)Lcoursier/util/ValidationNel;
  #160 = Utf8               (Lcoursier/ivy/PropertiesPattern$ChunkOrProperty;)Lcoursier/util/ValidationNel;
  #161 = MethodType         #160          //  (Lcoursier/ivy/PropertiesPattern$ChunkOrProperty;)Lcoursier/util/ValidationNel;
  #162 = Utf8               (Lscala/collection/immutable/Map;)Lscala/Function1;
  #163 = NameAndType        #73:#162      // apply:(Lscala/collection/immutable/Map;)Lscala/Function1;
  #164 = InvokeDynamic      #1:#163       // #1:apply:(Lscala/collection/immutable/Map;)Lscala/Function1;
  #165 = Utf8               validationNelTraverse
  #166 = Utf8               (Lscala/Function1;)Lcoursier/util/ValidationNel;
  #167 = NameAndType        #165:#166     // validationNelTraverse:(Lscala/Function1;)Lcoursier/util/ValidationNel;
  #168 = Methodref          #48.#167      // coursier/util/Traverse$TraverseOps.validationNelTraverse:(Lscala/Function1;)Lcoursier/util/ValidationNel;
  #169 = Utf8               $anonfun$substituteProperties$4
  #170 = Utf8               (Lscala/collection/immutable/Seq;)Lcoursier/ivy/Pattern;
  #171 = NameAndType        #169:#170     // $anonfun$substituteProperties$4:(Lscala/collection/immutable/Seq;)Lcoursier/ivy/Pattern;
  #172 = Methodref          #2.#171       // coursier/ivy/PropertiesPattern.$anonfun$substituteProperties$4:(Lscala/collection/immutable/Seq;)Lcoursier/ivy/Pattern;
  #173 = MethodHandle       6:#172        // REF_invokeStatic coursier/ivy/PropertiesPattern.$anonfun$substituteProperties$4:(Lscala/collection/immutable/Seq;)Lcoursier/ivy/Pattern;
  #174 = MethodType         #170          //  (Lscala/collection/immutable/Seq;)Lcoursier/ivy/Pattern;
  #175 = InvokeDynamic      #2:#130       // #2:apply:()Lscala/Function1;
  #176 = NameAndType        #134:#166     // map:(Lscala/Function1;)Lcoursier/util/ValidationNel;
  #177 = Methodref          #55.#176      // coursier/util/ValidationNel.map:(Lscala/Function1;)Lcoursier/util/ValidationNel;
  #178 = Utf8               either
  #179 = Utf8               ()Lscala/util/Either;
  #180 = NameAndType        #178:#179     // either:()Lscala/util/Either;
  #181 = Methodref          #55.#180      // coursier/util/ValidationNel.either:()Lscala/util/Either;
  #182 = Utf8               left
  #183 = Utf8               ()Lscala/util/Either$LeftProjection;
  #184 = NameAndType        #182:#183     // left:()Lscala/util/Either$LeftProjection;
  #185 = Methodref          #68.#184      // scala/util/Either.left:()Lscala/util/Either$LeftProjection;
  #186 = Utf8               $anonfun$substituteProperties$5
  #187 = Utf8               (Lscala/collection/immutable/$colon$colon;)Ljava/lang/String;
  #188 = NameAndType        #186:#187     // $anonfun$substituteProperties$5:(Lscala/collection/immutable/$colon$colon;)Ljava/lang/String;
  #189 = Methodref          #2.#188       // coursier/ivy/PropertiesPattern.$anonfun$substituteProperties$5:(Lscala/collection/immutable/$colon$colon;)Ljava/lang/String;
  #190 = MethodHandle       6:#189        // REF_invokeStatic coursier/ivy/PropertiesPattern.$anonfun$substituteProperties$5:(Lscala/collection/immutable/$colon$colon;)Ljava/lang/String;
  #191 = MethodType         #187          //  (Lscala/collection/immutable/$colon$colon;)Ljava/lang/String;
  #192 = InvokeDynamic      #3:#130       // #3:apply:()Lscala/Function1;
  #193 = Utf8               (Lscala/Function1;)Lscala/util/Either;
  #194 = NameAndType        #134:#193     // map:(Lscala/Function1;)Lscala/util/Either;
  #195 = Methodref          #66.#194      // scala/util/Either$LeftProjection.map:(Lscala/Function1;)Lscala/util/Either;
  #196 = Utf8               validation
  #197 = Utf8               Lcoursier/util/ValidationNel;
  #198 = Utf8               Lscala/collection/immutable/Map;
  #199 = Utf8               withChunks
  #200 = Utf8               <init>
  #201 = Utf8               (Lscala/collection/immutable/Seq;)V
  #202 = NameAndType        #200:#201     // "<init>":(Lscala/collection/immutable/Seq;)V
  #203 = Methodref          #2.#202       // coursier/ivy/PropertiesPattern."<init>":(Lscala/collection/immutable/Seq;)V
  #204 = Utf8               toString
  #205 = Utf8               java/lang/StringBuilder
  #206 = Class              #205          // java/lang/StringBuilder
  #207 = Utf8               PropertiesPattern(
  #208 = String             #207          // PropertiesPattern(
  #209 = Utf8               (Ljava/lang/String;)V
  #210 = NameAndType        #200:#209     // "<init>":(Ljava/lang/String;)V
  #211 = Methodref          #206.#210     // java/lang/StringBuilder."<init>":(Ljava/lang/String;)V
  #212 = Utf8               java/lang/String
  #213 = Class              #212          // java/lang/String
  #214 = Utf8               valueOf
  #215 = Utf8               (Ljava/lang/Object;)Ljava/lang/String;
  #216 = NameAndType        #214:#215     // valueOf:(Ljava/lang/Object;)Ljava/lang/String;
  #217 = Methodref          #213.#216     // java/lang/String.valueOf:(Ljava/lang/Object;)Ljava/lang/String;
  #218 = Utf8               append
  #219 = Utf8               (Ljava/lang/String;)Ljava/lang/StringBuilder;
  #220 = NameAndType        #218:#219     // append:(Ljava/lang/String;)Ljava/lang/StringBuilder;
  #221 = Methodref          #206.#220     // java/lang/StringBuilder.append:(Ljava/lang/String;)Ljava/lang/StringBuilder;
  #222 = Utf8               )
  #223 = String             #222          // )
  #224 = NameAndType        #204:#109     // toString:()Ljava/lang/String;
  #225 = Methodref          #206.#224     // java/lang/StringBuilder.toString:()Ljava/lang/String;
  #226 = Utf8               b
  #227 = Utf8               Ljava/lang/StringBuilder;
  #228 = Utf8               canEqual
  #229 = Utf8               (Ljava/lang/Object;)Z
  #230 = Utf8               obj
  #231 = Utf8               Ljava/lang/Object;
  #232 = Utf8               equals
  #233 = NameAndType        #228:#229     // canEqual:(Ljava/lang/Object;)Z
  #234 = Methodref          #2.#233       // coursier/ivy/PropertiesPattern.canEqual:(Ljava/lang/Object;)Z
  #235 = NameAndType        #232:#229     // equals:(Ljava/lang/Object;)Z
  #236 = Methodref          #4.#235       // java/lang/Object.equals:(Ljava/lang/Object;)Z
  #237 = Utf8               other
  #238 = Utf8               hashCode
  #239 = Utf8               ()I
  #240 = Utf8               PropertiesPattern
  #241 = String             #240          // PropertiesPattern
  #242 = Utf8               scala/runtime/Statics
  #243 = Class              #242          // scala/runtime/Statics
  #244 = Utf8               anyHash
  #245 = Utf8               (Ljava/lang/Object;)I
  #246 = NameAndType        #244:#245     // anyHash:(Ljava/lang/Object;)I
  #247 = Methodref          #243.#246     // scala/runtime/Statics.anyHash:(Ljava/lang/Object;)I
  #248 = Utf8               code
  #249 = Utf8               I
  #250 = Utf8               tuple
  #251 = Utf8               ()Lscala/Tuple1;
  #252 = Utf8               ()Lscala/Tuple1<Lscala/collection/immutable/Seq<Lcoursier/ivy/PropertiesPattern$ChunkOrProperty;>;>;
  #253 = Utf8               scala/Tuple1
  #254 = Class              #253          // scala/Tuple1
  #255 = Utf8               (Ljava/lang/Object;)V
  #256 = NameAndType        #200:#255     // "<init>":(Ljava/lang/Object;)V
  #257 = Methodref          #254.#256     // scala/Tuple1."<init>":(Ljava/lang/Object;)V
  #258 = Utf8               productPrefix
  #259 = Utf8               productArity
  #260 = Utf8               productElement
  #261 = Utf8               (I)Ljava/lang/Object;
  #262 = Utf8               n
  #263 = Utf8               java/lang/IndexOutOfBoundsException
  #264 = Class              #263          // java/lang/IndexOutOfBoundsException
  #265 = Utf8               scala/runtime/BoxesRunTime
  #266 = Class              #265          // scala/runtime/BoxesRunTime
  #267 = Utf8               boxToInteger
  #268 = Utf8               (I)Ljava/lang/Integer;
  #269 = NameAndType        #267:#268     // boxToInteger:(I)Ljava/lang/Integer;
  #270 = Methodref          #266.#269     // scala/runtime/BoxesRunTime.boxToInteger:(I)Ljava/lang/Integer;
  #271 = Methodref          #4.#224       // java/lang/Object.toString:()Ljava/lang/String;
  #272 = Methodref          #264.#210     // java/lang/IndexOutOfBoundsException."<init>":(Ljava/lang/String;)V
  #273 = Utf8               productElementName
  #274 = Utf8               (I)Ljava/lang/String;
  #275 = String             #70           // chunks
  #276 = Utf8               x$1
  #277 = NameAndType        #108:#109     // string:()Ljava/lang/String;
  #278 = Methodref          #34.#277      // coursier/ivy/PropertiesPattern$ChunkOrProperty.string:()Ljava/lang/String;
  #279 = Utf8               Lcoursier/ivy/PropertiesPattern$ChunkOrProperty;
  #280 = Utf8               $anonfun$substituteProperties$2
  #281 = Utf8               (Lcoursier/ivy/Pattern;)Lscala/collection/immutable/Vector;
  #282 = Utf8               x$2
  #283 = Methodref          #16.#110      // coursier/ivy/Pattern.chunks:()Lscala/collection/immutable/Seq;
  #284 = Utf8               toVector
  #285 = Utf8               ()Lscala/collection/immutable/Vector;
  #286 = NameAndType        #284:#285     // toVector:()Lscala/collection/immutable/Vector;
  #287 = InterfaceMethodref #133.#286     // scala/collection/immutable/Seq.toVector:()Lscala/collection/immutable/Vector;
  #288 = Utf8               Lcoursier/ivy/Pattern;
  #289 = Utf8               $anonfun$substituteProperties$3
  #290 = Utf8               (Lcoursier/ivy/Pattern;)Lscala/collection/immutable/Seq;
  #291 = Utf8               l
  #292 = Utf8               scala/collection/immutable/$colon$colon
  #293 = Class              #292          // scala/collection/immutable/$colon$colon
  #294 = Utf8               Lcoursier/ivy/Pattern$Chunk$Opt$;
  #295 = NameAndType        #78:#294      // MODULE$:Lcoursier/ivy/Pattern$Chunk$Opt$;
  #296 = Fieldref           #27.#295      // coursier/ivy/Pattern$Chunk$Opt$.MODULE$:Lcoursier/ivy/Pattern$Chunk$Opt$;
  #297 = Utf8               (Lscala/collection/immutable/Seq;)Lcoursier/ivy/Pattern$Chunk$Opt;
  #298 = NameAndType        #73:#297      // apply:(Lscala/collection/immutable/Seq;)Lcoursier/ivy/Pattern$Chunk$Opt;
  #299 = Methodref          #27.#298      // coursier/ivy/Pattern$Chunk$Opt$.apply:(Lscala/collection/immutable/Seq;)Lcoursier/ivy/Pattern$Chunk$Opt;
  #300 = Utf8               scala/collection/immutable/Nil$
  #301 = Class              #300          // scala/collection/immutable/Nil$
  #302 = Utf8               Lscala/collection/immutable/Nil$;
  #303 = NameAndType        #78:#302      // MODULE$:Lscala/collection/immutable/Nil$;
  #304 = Fieldref           #301.#303     // scala/collection/immutable/Nil$.MODULE$:Lscala/collection/immutable/Nil$;
  #305 = Utf8               (Ljava/lang/Object;Lscala/collection/immutable/List;)V
  #306 = NameAndType        #200:#305     // "<init>":(Ljava/lang/Object;Lscala/collection/immutable/List;)V
  #307 = Methodref          #293.#306     // scala/collection/immutable/$colon$colon."<init>":(Ljava/lang/Object;Lscala/collection/immutable/List;)V
  #308 = Utf8               properties$1
  #309 = Utf8               x0$1
  #310 = Utf8               name
  #311 = NameAndType        #310:#109     // name:()Ljava/lang/String;
  #312 = Methodref          #43.#311      // coursier/ivy/PropertiesPattern$ChunkOrProperty$Prop.name:()Ljava/lang/String;
  #313 = Utf8               scala/collection/immutable/Map
  #314 = Class              #313          // scala/collection/immutable/Map
  #315 = Utf8               get
  #316 = Utf8               (Ljava/lang/Object;)Lscala/Option;
  #317 = NameAndType        #315:#316     // get:(Ljava/lang/Object;)Lscala/Option;
  #318 = InterfaceMethodref #314.#317     // scala/collection/immutable/Map.get:(Ljava/lang/Object;)Lscala/Option;
  #319 = Utf8               scala/Some
  #320 = Class              #319          // scala/Some
  #321 = Utf8               value
  #322 = Utf8               ()Ljava/lang/Object;
  #323 = NameAndType        #321:#322     // value:()Ljava/lang/Object;
  #324 = Methodref          #320.#323     // scala/Some.value:()Ljava/lang/Object;
  #325 = Utf8               coursier/util/ValidationNel$
  #326 = Class              #325          // coursier/util/ValidationNel$
  #327 = Utf8               Lcoursier/util/ValidationNel$;
  #328 = NameAndType        #78:#327      // MODULE$:Lcoursier/util/ValidationNel$;
  #329 = Fieldref           #326.#328     // coursier/util/ValidationNel$.MODULE$:Lcoursier/util/ValidationNel$;
  #330 = Utf8               success
  #331 = Utf8               ()Lcoursier/util/ValidationNel$SuccessBuilder;
  #332 = NameAndType        #330:#331     // success:()Lcoursier/util/ValidationNel$SuccessBuilder;
  #333 = Methodref          #326.#332     // coursier/util/ValidationNel$.success:()Lcoursier/util/ValidationNel$SuccessBuilder;
  #334 = Utf8               Lcoursier/ivy/Pattern$Chunk$Const$;
  #335 = NameAndType        #78:#334      // MODULE$:Lcoursier/ivy/Pattern$Chunk$Const$;
  #336 = Fieldref           #22.#335      // coursier/ivy/Pattern$Chunk$Const$.MODULE$:Lcoursier/ivy/Pattern$Chunk$Const$;
  #337 = Utf8               (Ljava/lang/String;)Lcoursier/ivy/Pattern$Chunk$Const;
  #338 = NameAndType        #73:#337      // apply:(Ljava/lang/String;)Lcoursier/ivy/Pattern$Chunk$Const;
  #339 = Methodref          #22.#338      // coursier/ivy/Pattern$Chunk$Const$.apply:(Ljava/lang/String;)Lcoursier/ivy/Pattern$Chunk$Const;
  #340 = Utf8               (Ljava/lang/Object;)Lcoursier/util/ValidationNel;
  #341 = NameAndType        #73:#340      // apply:(Ljava/lang/Object;)Lcoursier/util/ValidationNel;
  #342 = Methodref          #58.#341      // coursier/util/ValidationNel$SuccessBuilder.apply:(Ljava/lang/Object;)Lcoursier/util/ValidationNel;
  #343 = Utf8               scala/Option
  #344 = Class              #343          // scala/Option
  #345 = Utf8               scala/None$
  #346 = Class              #345          // scala/None$
  #347 = Utf8               Lscala/None$;
  #348 = NameAndType        #78:#347      // MODULE$:Lscala/None$;
  #349 = Fieldref           #346.#348     // scala/None$.MODULE$:Lscala/None$;
  #350 = Utf8               alternative
  #351 = Utf8               ()Lscala/Option;
  #352 = NameAndType        #350:#351     // alternative:()Lscala/Option;
  #353 = Methodref          #43.#352      // coursier/ivy/PropertiesPattern$ChunkOrProperty$Prop.alternative:()Lscala/Option;
  #354 = NameAndType        #143:#144     // substituteProperties:(Lscala/collection/immutable/Map;)Lscala/util/Either;
  #355 = Methodref          #2.#354       // coursier/ivy/PropertiesPattern.substituteProperties:(Lscala/collection/immutable/Map;)Lscala/util/Either;
  #356 = NameAndType        #280:#281     // $anonfun$substituteProperties$2:(Lcoursier/ivy/Pattern;)Lscala/collection/immutable/Vector;
  #357 = Methodref          #2.#356       // coursier/ivy/PropertiesPattern.$anonfun$substituteProperties$2:(Lcoursier/ivy/Pattern;)Lscala/collection/immutable/Vector;
  #358 = MethodHandle       6:#357        // REF_invokeStatic coursier/ivy/PropertiesPattern.$anonfun$substituteProperties$2:(Lcoursier/ivy/Pattern;)Lscala/collection/immutable/Vector;
  #359 = MethodType         #281          //  (Lcoursier/ivy/Pattern;)Lscala/collection/immutable/Vector;
  #360 = InvokeDynamic      #4:#130       // #4:apply:()Lscala/Function1;
  #361 = Methodref          #68.#194      // scala/util/Either.map:(Lscala/Function1;)Lscala/util/Either;
  #362 = Utf8               fromEither
  #363 = Utf8               (Lscala/util/Either;)Lcoursier/util/ValidationNel;
  #364 = NameAndType        #362:#363     // fromEither:(Lscala/util/Either;)Lcoursier/util/ValidationNel;
  #365 = Methodref          #326.#364     // coursier/util/ValidationNel$.fromEither:(Lscala/util/Either;)Lcoursier/util/ValidationNel;
  #366 = Utf8               failure
  #367 = Utf8               ()Lcoursier/util/ValidationNel$FailureBuilder;
  #368 = NameAndType        #366:#367     // failure:()Lcoursier/util/ValidationNel$FailureBuilder;
  #369 = Methodref          #326.#368     // coursier/util/ValidationNel$.failure:()Lcoursier/util/ValidationNel$FailureBuilder;
  #370 = Methodref          #53.#341      // coursier/util/ValidationNel$FailureBuilder.apply:(Ljava/lang/Object;)Lcoursier/util/ValidationNel;
  #371 = Utf8               scala/MatchError
  #372 = Class              #371          // scala/MatchError
  #373 = Methodref          #372.#256     // scala/MatchError."<init>":(Ljava/lang/Object;)V
  #374 = Utf8               content
  #375 = NameAndType        #374:#104     // content:()Lscala/collection/immutable/Seq;
  #376 = Methodref          #41.#375      // coursier/ivy/PropertiesPattern$ChunkOrProperty$Opt.content:()Lscala/collection/immutable/Seq;
  #377 = NameAndType        #289:#290     // $anonfun$substituteProperties$3:(Lcoursier/ivy/Pattern;)Lscala/collection/immutable/Seq;
  #378 = Methodref          #2.#377       // coursier/ivy/PropertiesPattern.$anonfun$substituteProperties$3:(Lcoursier/ivy/Pattern;)Lscala/collection/immutable/Seq;
  #379 = MethodHandle       6:#378        // REF_invokeStatic coursier/ivy/PropertiesPattern.$anonfun$substituteProperties$3:(Lcoursier/ivy/Pattern;)Lscala/collection/immutable/Seq;
  #380 = MethodType         #290          //  (Lcoursier/ivy/Pattern;)Lscala/collection/immutable/Seq;
  #381 = InvokeDynamic      #5:#130       // #5:apply:()Lscala/Function1;
  #382 = Utf8               Lcoursier/ivy/Pattern$Chunk$Var$;
  #383 = NameAndType        #78:#382      // MODULE$:Lcoursier/ivy/Pattern$Chunk$Var$;
  #384 = Fieldref           #32.#383      // coursier/ivy/Pattern$Chunk$Var$.MODULE$:Lcoursier/ivy/Pattern$Chunk$Var$;
  #385 = Methodref          #46.#311      // coursier/ivy/PropertiesPattern$ChunkOrProperty$Var.name:()Ljava/lang/String;
  #386 = Utf8               (Ljava/lang/String;)Lcoursier/ivy/Pattern$Chunk$Var;
  #387 = NameAndType        #73:#386      // apply:(Ljava/lang/String;)Lcoursier/ivy/Pattern$Chunk$Var;
  #388 = Methodref          #32.#387      // coursier/ivy/Pattern$Chunk$Var$.apply:(Ljava/lang/String;)Lcoursier/ivy/Pattern$Chunk$Var;
  #389 = NameAndType        #321:#109     // value:()Ljava/lang/String;
  #390 = Methodref          #39.#389      // coursier/ivy/PropertiesPattern$ChunkOrProperty$Const.value:()Ljava/lang/String;
  #391 = Utf8               Ljava/lang/String;
  #392 = Utf8               alt
  #393 = Utf8               c
  #394 = Utf8               coursier/ivy/Pattern$
  #395 = Class              #394          // coursier/ivy/Pattern$
  #396 = Utf8               Lcoursier/ivy/Pattern$;
  #397 = NameAndType        #78:#396      // MODULE$:Lcoursier/ivy/Pattern$;
  #398 = Fieldref           #395.#397     // coursier/ivy/Pattern$.MODULE$:Lcoursier/ivy/Pattern$;
  #399 = Utf8               scala/Predef$
  #400 = Class              #399          // scala/Predef$
  #401 = Utf8               Lscala/Predef$;
  #402 = NameAndType        #78:#401      // MODULE$:Lscala/Predef$;
  #403 = Fieldref           #400.#402     // scala/Predef$.MODULE$:Lscala/Predef$;
  #404 = Utf8               $conforms
  #405 = NameAndType        #404:#129     // $conforms:()Lscala/Function1;
  #406 = Methodref          #400.#405     // scala/Predef$.$conforms:()Lscala/Function1;
  #407 = Utf8               flatten
  #408 = NameAndType        #407:#135     // flatten:(Lscala/Function1;)Ljava/lang/Object;
  #409 = InterfaceMethodref #133.#408     // scala/collection/immutable/Seq.flatten:(Lscala/Function1;)Ljava/lang/Object;
  #410 = NameAndType        #73:#170      // apply:(Lscala/collection/immutable/Seq;)Lcoursier/ivy/Pattern;
  #411 = Methodref          #395.#410     // coursier/ivy/Pattern$.apply:(Lscala/collection/immutable/Seq;)Lcoursier/ivy/Pattern;
  #412 = Utf8               notFoundProps
  #413 = Integer            25
  #414 = Utf8               (I)V
  #415 = NameAndType        #200:#414     // "<init>":(I)V
  #416 = Methodref          #206.#415     // java/lang/StringBuilder."<init>":(I)V
  #417 = Utf8               Property(ies) not found:
  #418 = String             #417          // Property(ies) not found:
  #419 = Utf8               ,
  #420 = String             #419          // ,
  #421 = Utf8               (Ljava/lang/String;)Ljava/lang/String;
  #422 = NameAndType        #140:#421     // mkString:(Ljava/lang/String;)Ljava/lang/String;
  #423 = Methodref          #293.#422     // scala/collection/immutable/$colon$colon.mkString:(Ljava/lang/String;)Ljava/lang/String;
  #424 = Utf8               Lscala/collection/immutable/$colon$colon;
  #425 = Utf8               (Lscala/collection/immutable/Seq<Lcoursier/ivy/PropertiesPattern$ChunkOrProperty;>;)V
  #426 = Utf8               ()V
  #427 = NameAndType        #200:#426     // "<init>":()V
  #428 = Methodref          #4.#427       // java/lang/Object."<init>":()V
  #429 = Utf8               $init$
  #430 = Utf8               (Lscala/Product;)V
  #431 = NameAndType        #429:#430     // $init$:(Lscala/Product;)V
  #432 = InterfaceMethodref #6.#431       // scala/Product.$init$:(Lscala/Product;)V
  #433 = Utf8               $deserializeLambda$
  #434 = Utf8               (Ljava/lang/invoke/SerializedLambda;)Ljava/lang/Object;
  #435 = Utf8               scala/runtime/LambdaDeserialize
  #436 = Class              #435          // scala/runtime/LambdaDeserialize
  #437 = Utf8               bootstrap
  #438 = Utf8               (Ljava/lang/invoke/MethodHandles$Lookup;Ljava/lang/String;Ljava/lang/invoke/MethodType;[Ljava/lang/invoke/MethodHandle;)Ljava/lang/invoke/CallSite;
  #439 = NameAndType        #437:#438     // bootstrap:(Ljava/lang/invoke/MethodHandles$Lookup;Ljava/lang/String;Ljava/lang/invoke/MethodType;[Ljava/lang/invoke/MethodHandle;)Ljava/lang/invoke/CallSite;
  #440 = Methodref          #436.#439     // scala/runtime/LambdaDeserialize.bootstrap:(Ljava/lang/invoke/MethodHandles$Lookup;Ljava/lang/String;Ljava/lang/invoke/MethodType;[Ljava/lang/invoke/MethodHandle;)Ljava/lang/invoke/CallSite;
  #441 = MethodHandle       6:#440        // REF_invokeStatic scala/runtime/LambdaDeserialize.bootstrap:(Ljava/lang/invoke/MethodHandles$Lookup;Ljava/lang/String;Ljava/lang/invoke/MethodType;[Ljava/lang/invoke/MethodHandle;)Ljava/lang/invoke/CallSite;
  #442 = Utf8               lambdaDeserialize
  #443 = NameAndType        #442:#434     // lambdaDeserialize:(Ljava/lang/invoke/SerializedLambda;)Ljava/lang/Object;
  #444 = InvokeDynamic      #6:#443       // #6:lambdaDeserialize:(Ljava/lang/invoke/SerializedLambda;)Ljava/lang/Object;
  #445 = Utf8               Signature
  #446 = Utf8               Code
  #447 = Utf8               MethodParameters
  #448 = Utf8               LineNumberTable
  #449 = Utf8               LocalVariableTable
  #450 = Utf8               StackMapTable
  #451 = Utf8               InnerClasses
  #452 = Utf8               SourceFile
  #453 = Utf8               RuntimeVisibleAnnotations
  #454 = Utf8               BootstrapMethods
  #455 = Utf8               ScalaInlineInfo
  #456 = Utf8               ScalaSig
{
  private final scala.collection.immutable.Seq<coursier.ivy.PropertiesPattern$ChunkOrProperty> chunks;
    descriptor: Lscala/collection/immutable/Seq;
    flags: (0x0012) ACC_PRIVATE, ACC_FINAL
    Signature: #72                          // Lscala/collection/immutable/Seq<Lcoursier/ivy/PropertiesPattern$ChunkOrProperty;>;

  public static coursier.ivy.PropertiesPattern apply(scala.collection.immutable.Seq<coursier.ivy.PropertiesPattern$ChunkOrProperty>);
    descriptor: (Lscala/collection/immutable/Seq;)Lcoursier/ivy/PropertiesPattern;
    flags: (0x0009) ACC_PUBLIC, ACC_STATIC
    Code:
      stack=2, locals=1, args_size=1
         0: getstatic     #81                 // Field coursier/ivy/PropertiesPattern$.MODULE$:Lcoursier/ivy/PropertiesPattern$;
         3: aload_0
         4: invokevirtual #83                 // Method coursier/ivy/PropertiesPattern$.apply:(Lscala/collection/immutable/Seq;)Lcoursier/ivy/PropertiesPattern;
         7: areturn
    Signature: #75                          // (Lscala/collection/immutable/Seq<Lcoursier/ivy/PropertiesPattern$ChunkOrProperty;>;)Lcoursier/ivy/PropertiesPattern;
    MethodParameters:
      Name                           Flags
      chunks                         final

  public static scala.util.Either<java.lang.String, coursier.ivy.PropertiesPattern> parse(java.lang.String);
    descriptor: (Ljava/lang/String;)Lscala/util/Either;
    flags: (0x0009) ACC_PUBLIC, ACC_STATIC
    Code:
      stack=2, locals=1, args_size=1
         0: getstatic     #81                 // Field coursier/ivy/PropertiesPattern$.MODULE$:Lcoursier/ivy/PropertiesPattern$;
         3: aload_0
         4: invokevirtual #89                 // Method coursier/ivy/PropertiesPattern$.parse:(Ljava/lang/String;)Lscala/util/Either;
         7: areturn
    Signature: #86                          // (Ljava/lang/String;)Lscala/util/Either<Ljava/lang/String;Lcoursier/ivy/PropertiesPattern;>;
    MethodParameters:
      Name                           Flags
      pattern                        final

  public scala.collection.Iterator<java.lang.Object> productIterator();
    descriptor: ()Lscala/collection/Iterator;
    flags: (0x0001) ACC_PUBLIC
    Code:
      stack=1, locals=1, args_size=1
         0: aload_0
         1: invokestatic  #96                 // InterfaceMethod scala/Product.productIterator$:(Lscala/Product;)Lscala/collection/Iterator;
         4: areturn
      LineNumberTable:
        line 8: 0
      LocalVariableTable:
        Start  Length  Slot  Name   Signature
            0       5     0  this   Lcoursier/ivy/PropertiesPattern;
    Signature: #92                          // ()Lscala/collection/Iterator<Ljava/lang/Object;>;

  public scala.collection.Iterator<java.lang.String> productElementNames();
    descriptor: ()Lscala/collection/Iterator;
    flags: (0x0001) ACC_PUBLIC
    Code:
      stack=1, locals=1, args_size=1
         0: aload_0
         1: invokestatic  #103                // InterfaceMethod scala/Product.productElementNames$:(Lscala/Product;)Lscala/collection/Iterator;
         4: areturn
      LineNumberTable:
        line 8: 0
      LocalVariableTable:
        Start  Length  Slot  Name   Signature
            0       5     0  this   Lcoursier/ivy/PropertiesPattern;
    Signature: #100                         // ()Lscala/collection/Iterator<Ljava/lang/String;>;

  public scala.collection.immutable.Seq<coursier.ivy.PropertiesPattern$ChunkOrProperty> chunks();
    descriptor: ()Lscala/collection/immutable/Seq;
    flags: (0x0001) ACC_PUBLIC
    Code:
      stack=1, locals=1, args_size=1
         0: aload_0
         1: getfield      #107                // Field chunks:Lscala/collection/immutable/Seq;
         4: areturn
      LineNumberTable:
        line 8: 0
      LocalVariableTable:
        Start  Length  Slot  Name   Signature
            0       5     0  this   Lcoursier/ivy/PropertiesPattern;
    Signature: #105                         // ()Lscala/collection/immutable/Seq<Lcoursier/ivy/PropertiesPattern$ChunkOrProperty;>;

  public java.lang.String string();
    descriptor: ()Ljava/lang/String;
    flags: (0x0001) ACC_PUBLIC
    Code:
      stack=2, locals=1, args_size=1
         0: aload_0
         1: invokevirtual #111                // Method chunks:()Lscala/collection/immutable/Seq;
         4: invokedynamic #131,  0            // InvokeDynamic #0:apply:()Lscala/Function1;
         9: invokeinterface #137,  2          // InterfaceMethod scala/collection/immutable/Seq.map:(Lscala/Function1;)Ljava/lang/Object;
        14: checkcast     #139                // class scala/collection/IterableOnceOps
        17: invokeinterface #142,  1          // InterfaceMethod scala/collection/IterableOnceOps.mkString:()Ljava/lang/String;
        22: areturn
      LineNumberTable:
        line 10: 0
      LocalVariableTable:
        Start  Length  Slot  Name   Signature
            0      23     0  this   Lcoursier/ivy/PropertiesPattern;

  public scala.util.Either<java.lang.String, coursier.ivy.Pattern> substituteProperties(scala.collection.immutable.Map<java.lang.String, java.lang.String>);
    descriptor: (Lscala/collection/immutable/Map;)Lscala/util/Either;
    flags: (0x0001) ACC_PUBLIC
    Code:
      stack=2, locals=3, args_size=2
         0: getstatic     #151                // Field coursier/util/Traverse$.MODULE$:Lcoursier/util/Traverse$;
         3: aload_0
         4: invokevirtual #111                // Method chunks:()Lscala/collection/immutable/Seq;
         7: invokevirtual #154                // Method coursier/util/Traverse$.TraverseOps:(Lscala/collection/immutable/Seq;)Lcoursier/util/Traverse$TraverseOps;
        10: aload_1
        11: invokedynamic #164,  0            // InvokeDynamic #1:apply:(Lscala/collection/immutable/Map;)Lscala/Function1;
        16: invokevirtual #168                // Method coursier/util/Traverse$TraverseOps.validationNelTraverse:(Lscala/Function1;)Lcoursier/util/ValidationNel;
        19: invokedynamic #175,  0            // InvokeDynamic #2:apply:()Lscala/Function1;
        24: invokevirtual #177                // Method coursier/util/ValidationNel.map:(Lscala/Function1;)Lcoursier/util/ValidationNel;
        27: astore_2
        28: aload_2
        29: invokevirtual #181                // Method coursier/util/ValidationNel.either:()Lscala/util/Either;
        32: invokevirtual #185                // Method scala/util/Either.left:()Lscala/util/Either$LeftProjection;
        35: invokedynamic #192,  0            // InvokeDynamic #3:apply:()Lscala/Function1;
        40: invokevirtual #195                // Method scala/util/Either$LeftProjection.map:(Lscala/Function1;)Lscala/util/Either;
        43: areturn
      LineNumberTable:
        line 16: 0
        line 47: 19
        line 49: 28
      LocalVariableTable:
        Start  Length  Slot  Name   Signature
           28      15     2 validation   Lcoursier/util/ValidationNel;
            0      44     0  this   Lcoursier/ivy/PropertiesPattern;
            0      44     1 properties   Lscala/collection/immutable/Map;
    Signature: #145                         // (Lscala/collection/immutable/Map<Ljava/lang/String;Ljava/lang/String;>;)Lscala/util/Either<Ljava/lang/String;Lcoursier/ivy/Pattern;>;
    MethodParameters:
      Name                           Flags
      properties                     final

  public coursier.ivy.PropertiesPattern withChunks(scala.collection.immutable.Seq<coursier.ivy.PropertiesPattern$ChunkOrProperty>);
    descriptor: (Lscala/collection/immutable/Seq;)Lcoursier/ivy/PropertiesPattern;
    flags: (0x0001) ACC_PUBLIC
    Code:
      stack=3, locals=2, args_size=2
         0: new           #2                  // class coursier/ivy/PropertiesPattern
         3: dup
         4: aload_1
         5: invokespecial #203                // Method "<init>":(Lscala/collection/immutable/Seq;)V
         8: areturn
      LineNumberTable:
        line 8: 0
      LocalVariableTable:
        Start  Length  Slot  Name   Signature
            0       9     0  this   Lcoursier/ivy/PropertiesPattern;
            0       9     1 chunks   Lscala/collection/immutable/Seq;
    Signature: #75                          // (Lscala/collection/immutable/Seq<Lcoursier/ivy/PropertiesPattern$ChunkOrProperty;>;)Lcoursier/ivy/PropertiesPattern;
    MethodParameters:
      Name                           Flags
      chunks                         final

  public java.lang.String toString();
    descriptor: ()Ljava/lang/String;
    flags: (0x0001) ACC_PUBLIC
    Code:
      stack=3, locals=2, args_size=1
         0: new           #206                // class java/lang/StringBuilder
         3: dup
         4: ldc           #208                // String PropertiesPattern(
         6: invokespecial #211                // Method java/lang/StringBuilder."<init>":(Ljava/lang/String;)V
         9: astore_1
        10: aload_1
        11: aload_0
        12: invokevirtual #111                // Method chunks:()Lscala/collection/immutable/Seq;
        15: invokestatic  #217                // Method java/lang/String.valueOf:(Ljava/lang/Object;)Ljava/lang/String;
        18: invokevirtual #221                // Method java/lang/StringBuilder.append:(Ljava/lang/String;)Ljava/lang/StringBuilder;
        21: pop
        22: aload_1
        23: ldc           #223                // String )
        25: invokevirtual #221                // Method java/lang/StringBuilder.append:(Ljava/lang/String;)Ljava/lang/StringBuilder;
        28: pop
        29: aload_1
        30: invokevirtual #225                // Method java/lang/StringBuilder.toString:()Ljava/lang/String;
        33: areturn
      LineNumberTable:
        line 8: 0
      LocalVariableTable:
        Start  Length  Slot  Name   Signature
           10      23     1     b   Ljava/lang/StringBuilder;
            0      34     0  this   Lcoursier/ivy/PropertiesPattern;

  public boolean canEqual(java.lang.Object);
    descriptor: (Ljava/lang/Object;)Z
    flags: (0x0001) ACC_PUBLIC
    Code:
      stack=1, locals=2, args_size=2
         0: aload_1
         1: ifnull        15
         4: aload_1
         5: instanceof    #2                  // class coursier/ivy/PropertiesPattern
         8: ifeq          15
        11: iconst_1
        12: goto          16
        15: iconst_0
        16: ireturn
      StackMapTable: number_of_entries = 2
        frame_type = 15 /* same */
        frame_type = 64 /* same_locals_1_stack_item */
          stack = [ int ]
      LineNumberTable:
        line 8: 0
      LocalVariableTable:
        Start  Length  Slot  Name   Signature
            0      17     0  this   Lcoursier/ivy/PropertiesPattern;
            0      17     1   obj   Ljava/lang/Object;
    MethodParameters:
      Name                           Flags
      obj                            final

  public boolean equals(java.lang.Object);
    descriptor: (Ljava/lang/Object;)Z
    flags: (0x0001) ACC_PUBLIC
    Code:
      stack=2, locals=4, args_size=2
         0: aload_0
         1: aload_1
         2: if_acmpeq     58
         5: aload_0
         6: aload_1
         7: invokevirtual #234                // Method canEqual:(Ljava/lang/Object;)Z
        10: ifeq          62
        13: aload_1
        14: checkcast     #2                  // class coursier/ivy/PropertiesPattern
        17: astore_2
        18: iconst_1
        19: ifeq          54
        22: aload_0
        23: invokevirtual #111                // Method chunks:()Lscala/collection/immutable/Seq;
        26: aload_2
        27: invokevirtual #111                // Method chunks:()Lscala/collection/immutable/Seq;
        30: astore_3
        31: dup
        32: ifnonnull     43
        35: pop
        36: aload_3
        37: ifnull        50
        40: goto          54
        43: aload_3
        44: invokevirtual #236                // Method java/lang/Object.equals:(Ljava/lang/Object;)Z
        47: ifeq          54
        50: iconst_1
        51: goto          55
        54: iconst_0
        55: ifeq          62
        58: iconst_1
        59: goto          63
        62: iconst_0
        63: ireturn
      StackMapTable: number_of_entries = 7
        frame_type = 255 /* full_frame */
          offset_delta = 43
          locals = [ class coursier/ivy/PropertiesPattern, class java/lang/Object, class coursier/ivy/PropertiesPattern, class scala/collection/immutable/Seq ]
          stack = [ class scala/collection/immutable/Seq ]
        frame_type = 6 /* same */
        frame_type = 250 /* chop */
          offset_delta = 3
        frame_type = 64 /* same_locals_1_stack_item */
          stack = [ int ]
        frame_type = 250 /* chop */
          offset_delta = 2
        frame_type = 3 /* same */
        frame_type = 64 /* same_locals_1_stack_item */
          stack = [ int ]
      LineNumberTable:
        line 8: 0
      LocalVariableTable:
        Start  Length  Slot  Name   Signature
           18      37     2 other   Lcoursier/ivy/PropertiesPattern;
            0      64     0  this   Lcoursier/ivy/PropertiesPattern;
            0      64     1   obj   Ljava/lang/Object;
    MethodParameters:
      Name                           Flags
      obj                            final

  public int hashCode();
    descriptor: ()I
    flags: (0x0001) ACC_PUBLIC
    Code:
      stack=2, locals=2, args_size=1
         0: bipush        17
         2: ldc           #241                // String PropertiesPattern
         4: invokestatic  #247                // Method scala/runtime/Statics.anyHash:(Ljava/lang/Object;)I
         7: iadd
         8: istore_1
         9: bipush        37
        11: iload_1
        12: imul
        13: aload_0
        14: invokevirtual #111                // Method chunks:()Lscala/collection/immutable/Seq;
        17: invokestatic  #247                // Method scala/runtime/Statics.anyHash:(Ljava/lang/Object;)I
        20: iadd
        21: istore_1
        22: bipush        37
        24: iload_1
        25: imul
        26: ireturn
      LineNumberTable:
        line 8: 0
      LocalVariableTable:
        Start  Length  Slot  Name   Signature
            9      17     1  code   I
            0      27     0  this   Lcoursier/ivy/PropertiesPattern;

  private scala.Tuple1<scala.collection.immutable.Seq<coursier.ivy.PropertiesPattern$ChunkOrProperty>> tuple();
    descriptor: ()Lscala/Tuple1;
    flags: (0x0002) ACC_PRIVATE
    Code:
      stack=3, locals=1, args_size=1
         0: new           #254                // class scala/Tuple1
         3: dup
         4: aload_0
         5: invokevirtual #111                // Method chunks:()Lscala/collection/immutable/Seq;
         8: invokespecial #257                // Method scala/Tuple1."<init>":(Ljava/lang/Object;)V
        11: areturn
      LineNumberTable:
        line 8: 0
      LocalVariableTable:
        Start  Length  Slot  Name   Signature
            0      12     0  this   Lcoursier/ivy/PropertiesPattern;
    Signature: #252                         // ()Lscala/Tuple1<Lscala/collection/immutable/Seq<Lcoursier/ivy/PropertiesPattern$ChunkOrProperty;>;>;

  public java.lang.String productPrefix();
    descriptor: ()Ljava/lang/String;
    flags: (0x0001) ACC_PUBLIC
    Code:
      stack=1, locals=1, args_size=1
         0: ldc           #241                // String PropertiesPattern
         2: areturn
      LineNumberTable:
        line 8: 0
      LocalVariableTable:
        Start  Length  Slot  Name   Signature
            0       3     0  this   Lcoursier/ivy/PropertiesPattern;

  public int productArity();
    descriptor: ()I
    flags: (0x0001) ACC_PUBLIC
    Code:
      stack=1, locals=1, args_size=1
         0: iconst_1
         1: ireturn
      LineNumberTable:
        line 8: 0
      LocalVariableTable:
        Start  Length  Slot  Name   Signature
            0       2     0  this   Lcoursier/ivy/PropertiesPattern;

  public java.lang.Object productElement(int);
    descriptor: (I)Ljava/lang/Object;
    flags: (0x0001) ACC_PUBLIC
    Code:
      stack=3, locals=3, args_size=2
         0: iload_1
         1: istore_2
         2: iload_2
         3: tableswitch   { // 0 to 0
                       0: 20
                 default: 27
            }
        20: aload_0
        21: invokevirtual #111                // Method chunks:()Lscala/collection/immutable/Seq;
        24: goto          42
        27: new           #264                // class java/lang/IndexOutOfBoundsException
        30: dup
        31: iload_2
        32: invokestatic  #270                // Method scala/runtime/BoxesRunTime.boxToInteger:(I)Ljava/lang/Integer;
        35: invokevirtual #271                // Method java/lang/Object.toString:()Ljava/lang/String;
        38: invokespecial #272                // Method java/lang/IndexOutOfBoundsException."<init>":(Ljava/lang/String;)V
        41: athrow
        42: areturn
      StackMapTable: number_of_entries = 3
        frame_type = 252 /* append */
          offset_delta = 20
          locals = [ int ]
        frame_type = 6 /* same */
        frame_type = 78 /* same_locals_1_stack_item */
          stack = [ class scala/collection/immutable/Seq ]
      LineNumberTable:
        line 8: 0
      LocalVariableTable:
        Start  Length  Slot  Name   Signature
            0      43     0  this   Lcoursier/ivy/PropertiesPattern;
            0      43     1     n   I
    MethodParameters:
      Name                           Flags
      n                              final

  public java.lang.String productElementName(int);
    descriptor: (I)Ljava/lang/String;
    flags: (0x0001) ACC_PUBLIC
    Code:
      stack=3, locals=3, args_size=2
         0: iload_1
         1: istore_2
         2: iload_2
         3: tableswitch   { // 0 to 0
                       0: 20
                 default: 26
            }
        20: ldc_w         #275                // String chunks
        23: goto          41
        26: new           #264                // class java/lang/IndexOutOfBoundsException
        29: dup
        30: iload_2
        31: invokestatic  #270                // Method scala/runtime/BoxesRunTime.boxToInteger:(I)Ljava/lang/Integer;
        34: invokevirtual #271                // Method java/lang/Object.toString:()Ljava/lang/String;
        37: invokespecial #272                // Method java/lang/IndexOutOfBoundsException."<init>":(Ljava/lang/String;)V
        40: athrow
        41: areturn
      StackMapTable: number_of_entries = 3
        frame_type = 252 /* append */
          offset_delta = 20
          locals = [ int ]
        frame_type = 5 /* same */
        frame_type = 78 /* same_locals_1_stack_item */
          stack = [ class java/lang/String ]
      LineNumberTable:
        line 8: 0
      LocalVariableTable:
        Start  Length  Slot  Name   Signature
            0      42     0  this   Lcoursier/ivy/PropertiesPattern;
            0      42     1     n   I
    MethodParameters:
      Name                           Flags
      n                              final

  public static final java.lang.String $anonfun$string$1(coursier.ivy.PropertiesPattern$ChunkOrProperty);
    descriptor: (Lcoursier/ivy/PropertiesPattern$ChunkOrProperty;)Ljava/lang/String;
    flags: (0x1019) ACC_PUBLIC, ACC_STATIC, ACC_FINAL, ACC_SYNTHETIC
    Code:
      stack=1, locals=1, args_size=1
         0: aload_0
         1: invokevirtual #278                // Method coursier/ivy/PropertiesPattern$ChunkOrProperty.string:()Ljava/lang/String;
         4: areturn
      LineNumberTable:
        line 10: 0
      LocalVariableTable:
        Start  Length  Slot  Name   Signature
            0       5     0   x$1   Lcoursier/ivy/PropertiesPattern$ChunkOrProperty;
    MethodParameters:
      Name                           Flags
      x$1                            final

  public static final scala.collection.immutable.Vector $anonfun$substituteProperties$2(coursier.ivy.Pattern);
    descriptor: (Lcoursier/ivy/Pattern;)Lscala/collection/immutable/Vector;
    flags: (0x1019) ACC_PUBLIC, ACC_STATIC, ACC_FINAL, ACC_SYNTHETIC
    Code:
      stack=1, locals=1, args_size=1
         0: aload_0
         1: invokevirtual #283                // Method coursier/ivy/Pattern.chunks:()Lscala/collection/immutable/Seq;
         4: invokeinterface #287,  1          // InterfaceMethod scala/collection/immutable/Seq.toVector:()Lscala/collection/immutable/Vector;
         9: areturn
      LineNumberTable:
        line 27: 0
      LocalVariableTable:
        Start  Length  Slot  Name   Signature
            0      10     0   x$2   Lcoursier/ivy/Pattern;
    MethodParameters:
      Name                           Flags
      x$2                            final

  public static final scala.collection.immutable.Seq $anonfun$substituteProperties$3(coursier.ivy.Pattern);
    descriptor: (Lcoursier/ivy/Pattern;)Lscala/collection/immutable/Seq;
    flags: (0x1019) ACC_PUBLIC, ACC_STATIC, ACC_FINAL, ACC_SYNTHETIC
    Code:
      stack=4, locals=1, args_size=1
         0: new           #293                // class scala/collection/immutable/$colon$colon
         3: dup
         4: getstatic     #296                // Field coursier/ivy/Pattern$Chunk$Opt$.MODULE$:Lcoursier/ivy/Pattern$Chunk$Opt$;
         7: aload_0
         8: invokevirtual #283                // Method coursier/ivy/Pattern.chunks:()Lscala/collection/immutable/Seq;
        11: invokevirtual #299                // Method coursier/ivy/Pattern$Chunk$Opt$.apply:(Lscala/collection/immutable/Seq;)Lcoursier/ivy/Pattern$Chunk$Opt;
        14: getstatic     #304                // Field scala/collection/immutable/Nil$.MODULE$:Lscala/collection/immutable/Nil$;
        17: invokespecial #307                // Method scala/collection/immutable/$colon$colon."<init>":(Ljava/lang/Object;Lscala/collection/immutable/List;)V
        20: checkcast     #133                // class scala/collection/immutable/Seq
        23: areturn
      LineNumberTable:
        line 38: 0
      LocalVariableTable:
        Start  Length  Slot  Name   Signature
            0      24     0     l   Lcoursier/ivy/Pattern;
    MethodParameters:
      Name                           Flags
      l                              final

  public static final coursier.util.ValidationNel $anonfun$substituteProperties$1(scala.collection.immutable.Map, coursier.ivy.PropertiesPattern$ChunkOrProperty);
    descriptor: (Lscala/collection/immutable/Map;Lcoursier/ivy/PropertiesPattern$ChunkOrProperty;)Lcoursier/util/ValidationNel;
    flags: (0x1019) ACC_PUBLIC, ACC_STATIC, ACC_FINAL, ACC_SYNTHETIC
    Code:
      stack=5, locals=16, args_size=2
         0: aload_1
         1: astore        5
         3: aload         5
         5: instanceof    #43                 // class coursier/ivy/PropertiesPattern$ChunkOrProperty$Prop
         8: ifeq          234
        11: aload         5
        13: checkcast     #43                 // class coursier/ivy/PropertiesPattern$ChunkOrProperty$Prop
        16: astore        6
        18: aload_0
        19: aload         6
        21: invokevirtual #312                // Method coursier/ivy/PropertiesPattern$ChunkOrProperty$Prop.name:()Ljava/lang/String;
        24: invokeinterface #318,  2          // InterfaceMethod scala/collection/immutable/Map.get:(Ljava/lang/Object;)Lscala/Option;
        29: astore        7
        31: aload         7
        33: instanceof    #320                // class scala/Some
        36: ifeq          87
        39: aload         7
        41: checkcast     #320                // class scala/Some
        44: astore        8
        46: aload         8
        48: invokevirtual #324                // Method scala/Some.value:()Ljava/lang/Object;
        51: checkcast     #213                // class java/lang/String
        54: astore        9
        56: getstatic     #329                // Field coursier/util/ValidationNel$.MODULE$:Lcoursier/util/ValidationNel$;
        59: invokevirtual #333                // Method coursier/util/ValidationNel$.success:()Lcoursier/util/ValidationNel$SuccessBuilder;
        62: new           #293                // class scala/collection/immutable/$colon$colon
        65: dup
        66: getstatic     #336                // Field coursier/ivy/Pattern$Chunk$Const$.MODULE$:Lcoursier/ivy/Pattern$Chunk$Const$;
        69: aload         9
        71: invokevirtual #339                // Method coursier/ivy/Pattern$Chunk$Const$.apply:(Ljava/lang/String;)Lcoursier/ivy/Pattern$Chunk$Const;
        74: getstatic     #304                // Field scala/collection/immutable/Nil$.MODULE$:Lscala/collection/immutable/Nil$;
        77: invokespecial #307                // Method scala/collection/immutable/$colon$colon."<init>":(Ljava/lang/Object;Lscala/collection/immutable/List;)V
        80: invokevirtual #342                // Method coursier/util/ValidationNel$SuccessBuilder.apply:(Ljava/lang/Object;)Lcoursier/util/ValidationNel;
        83: astore_3
        84: goto          229
        87: goto          90
        90: getstatic     #349                // Field scala/None$.MODULE$:Lscala/None$;
        93: aload         7
        95: invokevirtual #236                // Method java/lang/Object.equals:(Ljava/lang/Object;)Z
        98: ifeq          216
       101: aload         6
       103: invokevirtual #353                // Method coursier/ivy/PropertiesPattern$ChunkOrProperty$Prop.alternative:()Lscala/Option;
       106: astore        10
       108: aload         10
       110: instanceof    #320                // class scala/Some
       113: ifeq          164
       116: aload         10
       118: checkcast     #320                // class scala/Some
       121: astore        11
       123: aload         11
       125: invokevirtual #324                // Method scala/Some.value:()Ljava/lang/Object;
       128: checkcast     #133                // class scala/collection/immutable/Seq
       131: astore        12
       133: getstatic     #329                // Field coursier/util/ValidationNel$.MODULE$:Lcoursier/util/ValidationNel$;
       136: getstatic     #81                 // Field coursier/ivy/PropertiesPattern$.MODULE$:Lcoursier/ivy/PropertiesPattern$;
       139: aload         12
       141: invokevirtual #83                 // Method coursier/ivy/PropertiesPattern$.apply:(Lscala/collection/immutable/Seq;)Lcoursier/ivy/PropertiesPattern;
       144: aload_0
       145: invokevirtual #355                // Method substituteProperties:(Lscala/collection/immutable/Map;)Lscala/util/Either;
       148: invokedynamic #360,  0            // InvokeDynamic #4:apply:()Lscala/Function1;
       153: invokevirtual #361                // Method scala/util/Either.map:(Lscala/Function1;)Lscala/util/Either;
       156: invokevirtual #365                // Method coursier/util/ValidationNel$.fromEither:(Lscala/util/Either;)Lcoursier/util/ValidationNel;
       159: astore        4
       161: goto          210
       164: goto          167
       167: getstatic     #349                // Field scala/None$.MODULE$:Lscala/None$;
       170: aload         10
       172: invokevirtual #236                // Method java/lang/Object.equals:(Ljava/lang/Object;)Z
       175: ifeq          197
       178: getstatic     #329                // Field coursier/util/ValidationNel$.MODULE$:Lcoursier/util/ValidationNel$;
       181: invokevirtual #369                // Method coursier/util/ValidationNel$.failure:()Lcoursier/util/ValidationNel$FailureBuilder;
       184: aload         6
       186: invokevirtual #312                // Method coursier/ivy/PropertiesPattern$ChunkOrProperty$Prop.name:()Ljava/lang/String;
       189: invokevirtual #370                // Method coursier/util/ValidationNel$FailureBuilder.apply:(Ljava/lang/Object;)Lcoursier/util/ValidationNel;
       192: astore        4
       194: goto          210
       197: goto          200
       200: new           #372                // class scala/MatchError
       203: dup
       204: aload         10
       206: invokespecial #373                // Method scala/MatchError."<init>":(Ljava/lang/Object;)V
       209: athrow
       210: aload         4
       212: astore_3
       213: goto          229
       216: goto          219
       219: new           #372                // class scala/MatchError
       222: dup
       223: aload         7
       225: invokespecial #373                // Method scala/MatchError."<init>":(Ljava/lang/Object;)V
       228: athrow
       229: aload_3
       230: astore_2
       231: goto          402
       234: goto          237
       237: aload         5
       239: instanceof    #41                 // class coursier/ivy/PropertiesPattern$ChunkOrProperty$Opt
       242: ifeq          285
       245: aload         5
       247: checkcast     #41                 // class coursier/ivy/PropertiesPattern$ChunkOrProperty$Opt
       250: astore        13
       252: getstatic     #329                // Field coursier/util/ValidationNel$.MODULE$:Lcoursier/util/ValidationNel$;
       255: getstatic     #81                 // Field coursier/ivy/PropertiesPattern$.MODULE$:Lcoursier/ivy/PropertiesPattern$;
       258: aload         13
       260: invokevirtual #376                // Method coursier/ivy/PropertiesPattern$ChunkOrProperty$Opt.content:()Lscala/collection/immutable/Seq;
       263: invokevirtual #83                 // Method coursier/ivy/PropertiesPattern$.apply:(Lscala/collection/immutable/Seq;)Lcoursier/ivy/PropertiesPattern;
       266: aload_0
       267: invokevirtual #355                // Method substituteProperties:(Lscala/collection/immutable/Map;)Lscala/util/Either;
       270: invokedynamic #381,  0            // InvokeDynamic #5:apply:()Lscala/Function1;
       275: invokevirtual #361                // Method scala/util/Either.map:(Lscala/Function1;)Lscala/util/Either;
       278: invokevirtual #365                // Method coursier/util/ValidationNel$.fromEither:(Lscala/util/Either;)Lcoursier/util/ValidationNel;
       281: astore_2
       282: goto          402
       285: goto          288
       288: aload         5
       290: instanceof    #46                 // class coursier/ivy/PropertiesPattern$ChunkOrProperty$Var
       293: ifeq          337
       296: aload         5
       298: checkcast     #46                 // class coursier/ivy/PropertiesPattern$ChunkOrProperty$Var
       301: astore        14
       303: getstatic     #329                // Field coursier/util/ValidationNel$.MODULE$:Lcoursier/util/ValidationNel$;
       306: invokevirtual #333                // Method coursier/util/ValidationNel$.success:()Lcoursier/util/ValidationNel$SuccessBuilder;
       309: new           #293                // class scala/collection/immutable/$colon$colon
       312: dup
       313: getstatic     #384                // Field coursier/ivy/Pattern$Chunk$Var$.MODULE$:Lcoursier/ivy/Pattern$Chunk$Var$;
       316: aload         14
       318: invokevirtual #385                // Method coursier/ivy/PropertiesPattern$ChunkOrProperty$Var.name:()Ljava/lang/String;
       321: invokevirtual #388                // Method coursier/ivy/Pattern$Chunk$Var$.apply:(Ljava/lang/String;)Lcoursier/ivy/Pattern$Chunk$Var;
       324: getstatic     #304                // Field scala/collection/immutable/Nil$.MODULE$:Lscala/collection/immutable/Nil$;
       327: invokespecial #307                // Method scala/collection/immutable/$colon$colon."<init>":(Ljava/lang/Object;Lscala/collection/immutable/List;)V
       330: invokevirtual #342                // Method coursier/util/ValidationNel$SuccessBuilder.apply:(Ljava/lang/Object;)Lcoursier/util/ValidationNel;
       333: astore_2
       334: goto          402
       337: goto          340
       340: aload         5
       342: instanceof    #39                 // class coursier/ivy/PropertiesPattern$ChunkOrProperty$Const
       345: ifeq          389
       348: aload         5
       350: checkcast     #39                 // class coursier/ivy/PropertiesPattern$ChunkOrProperty$Const
       353: astore        15
       355: getstatic     #329                // Field coursier/util/ValidationNel$.MODULE$:Lcoursier/util/ValidationNel$;
       358: invokevirtual #333                // Method coursier/util/ValidationNel$.success:()Lcoursier/util/ValidationNel$SuccessBuilder;
       361: new           #293                // class scala/collection/immutable/$colon$colon
       364: dup
       365: getstatic     #336                // Field coursier/ivy/Pattern$Chunk$Const$.MODULE$:Lcoursier/ivy/Pattern$Chunk$Const$;
       368: aload         15
       370: invokevirtual #390                // Method coursier/ivy/PropertiesPattern$ChunkOrProperty$Const.value:()Ljava/lang/String;
       373: invokevirtual #339                // Method coursier/ivy/Pattern$Chunk$Const$.apply:(Ljava/lang/String;)Lcoursier/ivy/Pattern$Chunk$Const;
       376: getstatic     #304                // Field scala/collection/immutable/Nil$.MODULE$:Lscala/collection/immutable/Nil$;
       379: invokespecial #307                // Method scala/collection/immutable/$colon$colon."<init>":(Ljava/lang/Object;Lscala/collection/immutable/List;)V
       382: invokevirtual #342                // Method coursier/util/ValidationNel$SuccessBuilder.apply:(Ljava/lang/Object;)Lcoursier/util/ValidationNel;
       385: astore_2
       386: goto          402
       389: goto          392
       392: new           #372                // class scala/MatchError
       395: dup
       396: aload         5
       398: invokespecial #373                // Method scala/MatchError."<init>":(Ljava/lang/Object;)V
       401: athrow
       402: aload_2
       403: areturn
      StackMapTable: number_of_entries = 19
        frame_type = 255 /* full_frame */
          offset_delta = 87
          locals = [ class scala/collection/immutable/Map, class coursier/ivy/PropertiesPattern$ChunkOrProperty, top, top, top, class coursier/ivy/PropertiesPattern$ChunkOrProperty, class coursier/ivy/PropertiesPattern$ChunkOrProperty$Prop, class scala/Option ]
          stack = []
        frame_type = 2 /* same */
        frame_type = 254 /* append */
          offset_delta = 73
          locals = [ top, top, class scala/Option ]
        frame_type = 2 /* same */
        frame_type = 29 /* same */
        frame_type = 2 /* same */
        frame_type = 255 /* full_frame */
          offset_delta = 9
          locals = [ class scala/collection/immutable/Map, class coursier/ivy/PropertiesPattern$ChunkOrProperty, top, top, class coursier/util/ValidationNel, class coursier/ivy/PropertiesPattern$ChunkOrProperty, class coursier/ivy/PropertiesPattern$ChunkOrProperty$Prop, class scala/Option, top, top, class scala/Option ]
          stack = []
        frame_type = 255 /* full_frame */
          offset_delta = 5
          locals = [ class scala/collection/immutable/Map, class coursier/ivy/PropertiesPattern$ChunkOrProperty, top, top, top, class coursier/ivy/PropertiesPattern$ChunkOrProperty, class coursier/ivy/PropertiesPattern$ChunkOrProperty$Prop, class scala/Option ]
          stack = []
        frame_type = 2 /* same */
        frame_type = 255 /* full_frame */
          offset_delta = 9
          locals = [ class scala/collection/immutable/Map, class coursier/ivy/PropertiesPattern$ChunkOrProperty, top, class coursier/util/ValidationNel, top, class coursier/ivy/PropertiesPattern$ChunkOrProperty, class coursier/ivy/PropertiesPattern$ChunkOrProperty$Prop, class scala/Option ]
          stack = []
        frame_type = 255 /* full_frame */
          offset_delta = 4
          locals = [ class scala/collection/immutable/Map, class coursier/ivy/PropertiesPattern$ChunkOrProperty, top, top, top, class coursier/ivy/PropertiesPattern$ChunkOrProperty ]
          stack = []
        frame_type = 2 /* same */
        frame_type = 47 /* same */
        frame_type = 2 /* same */
        frame_type = 48 /* same */
        frame_type = 2 /* same */
        frame_type = 48 /* same */
        frame_type = 2 /* same */
        frame_type = 255 /* full_frame */
          offset_delta = 9
          locals = [ class scala/collection/immutable/Map, class coursier/ivy/PropertiesPattern$ChunkOrProperty, class coursier/util/ValidationNel, top, top, class coursier/ivy/PropertiesPattern$ChunkOrProperty ]
          stack = []
      LineNumberTable:
        line 16: 0
        line 17: 3
        line 18: 18
        line 19: 31
        line 20: 56
        line 19: 87
        line 21: 90
        line 22: 101
        line 23: 108
        line 24: 133
        line 25: 136
        line 26: 144
        line 27: 148
        line 23: 164
        line 29: 167
        line 30: 178
        line 29: 197
        line 22: 200
        line 21: 216
        line 18: 219
        line 17: 234
        line 34: 237
        line 35: 252
        line 36: 255
        line 37: 266
        line 38: 270
        line 34: 285
        line 41: 288
        line 42: 303
        line 41: 337
        line 44: 340
        line 45: 355
        line 44: 389
        line 16: 392
      LocalVariableTable:
        Start  Length  Slot  Name   Signature
           56      31     9 value   Ljava/lang/String;
          133      31    12   alt   Lscala/collection/immutable/Seq;
            0     404     0 properties$1   Lscala/collection/immutable/Map;
            0     404     1  x0$1   Lcoursier/ivy/PropertiesPattern$ChunkOrProperty;
    MethodParameters:
      Name                           Flags
      properties$1                   final
      x0$1                           final

  public static final coursier.ivy.Pattern $anonfun$substituteProperties$4(scala.collection.immutable.Seq);
    descriptor: (Lscala/collection/immutable/Seq;)Lcoursier/ivy/Pattern;
    flags: (0x1019) ACC_PUBLIC, ACC_STATIC, ACC_FINAL, ACC_SYNTHETIC
    Code:
      stack=3, locals=1, args_size=1
         0: getstatic     #398                // Field coursier/ivy/Pattern$.MODULE$:Lcoursier/ivy/Pattern$;
         3: aload_0
         4: getstatic     #403                // Field scala/Predef$.MODULE$:Lscala/Predef$;
         7: invokevirtual #406                // Method scala/Predef$.$conforms:()Lscala/Function1;
        10: invokeinterface #409,  2          // InterfaceMethod scala/collection/immutable/Seq.flatten:(Lscala/Function1;)Ljava/lang/Object;
        15: checkcast     #133                // class scala/collection/immutable/Seq
        18: invokevirtual #411                // Method coursier/ivy/Pattern$.apply:(Lscala/collection/immutable/Seq;)Lcoursier/ivy/Pattern;
        21: areturn
      LineNumberTable:
        line 47: 0
      LocalVariableTable:
        Start  Length  Slot  Name   Signature
            0      22     0     c   Lscala/collection/immutable/Seq;
    MethodParameters:
      Name                           Flags
      c                              final

  public static final java.lang.String $anonfun$substituteProperties$5(scala.collection.immutable.$colon$colon);
    descriptor: (Lscala/collection/immutable/$colon$colon;)Ljava/lang/String;
    flags: (0x1019) ACC_PUBLIC, ACC_STATIC, ACC_FINAL, ACC_SYNTHETIC
    Code:
      stack=3, locals=1, args_size=1
         0: new           #206                // class java/lang/StringBuilder
         3: dup
         4: ldc_w         #413                // int 25
         7: invokespecial #416                // Method java/lang/StringBuilder."<init>":(I)V
        10: ldc_w         #418                // String Property(ies) not found:
        13: invokevirtual #221                // Method java/lang/StringBuilder.append:(Ljava/lang/String;)Ljava/lang/StringBuilder;
        16: aload_0
        17: ldc_w         #420                // String ,
        20: invokevirtual #423                // Method scala/collection/immutable/$colon$colon.mkString:(Ljava/lang/String;)Ljava/lang/String;
        23: invokevirtual #221                // Method java/lang/StringBuilder.append:(Ljava/lang/String;)Ljava/lang/StringBuilder;
        26: invokevirtual #225                // Method java/lang/StringBuilder.toString:()Ljava/lang/String;
        29: areturn
      LineNumberTable:
        line 50: 0
      LocalVariableTable:
        Start  Length  Slot  Name   Signature
            0      30     0 notFoundProps   Lscala/collection/immutable/$colon$colon;
    MethodParameters:
      Name                           Flags
      notFoundProps                  final

  public coursier.ivy.PropertiesPattern(scala.collection.immutable.Seq<coursier.ivy.PropertiesPattern$ChunkOrProperty>);
    descriptor: (Lscala/collection/immutable/Seq;)V
    flags: (0x0001) ACC_PUBLIC
    Code:
      stack=2, locals=2, args_size=2
         0: aload_0
         1: aload_1
         2: putfield      #107                // Field chunks:Lscala/collection/immutable/Seq;
         5: aload_0
         6: invokespecial #428                // Method java/lang/Object."<init>":()V
         9: aload_0
        10: invokestatic  #432                // InterfaceMethod scala/Product.$init$:(Lscala/Product;)V
        13: return
      LineNumberTable:
        line 8: 0
        line 55: 5
        line 8: 13
      LocalVariableTable:
        Start  Length  Slot  Name   Signature
            0      14     0  this   Lcoursier/ivy/PropertiesPattern;
            0      14     1 chunks   Lscala/collection/immutable/Seq;
    Signature: #425                         // (Lscala/collection/immutable/Seq<Lcoursier/ivy/PropertiesPattern$ChunkOrProperty;>;)V
    MethodParameters:
      Name                           Flags
      chunks                         final

  private static java.lang.Object $deserializeLambda$(java.lang.invoke.SerializedLambda);
    descriptor: (Ljava/lang/invoke/SerializedLambda;)Ljava/lang/Object;
    flags: (0x100a) ACC_PRIVATE, ACC_STATIC, ACC_SYNTHETIC
    Code:
      stack=1, locals=1, args_size=1
         0: aload_0
         1: invokedynamic #444,  0            // InvokeDynamic #6:lambdaDeserialize:(Ljava/lang/invoke/SerializedLambda;)Ljava/lang/Object;
         6: areturn
}
InnerClasses:
  public static #17= #14 of #16;          // =class coursier/ivy/Pattern$Chunk$ of class coursier/ivy/Pattern
  public static final #20= #19 of #14;    // Const=class coursier/ivy/Pattern$Chunk$Const of class coursier/ivy/Pattern$Chunk$
  public static #17= #22 of #14;          // =class coursier/ivy/Pattern$Chunk$Const$ of class coursier/ivy/Pattern$Chunk$
  public static final #25= #24 of #14;    // Opt=class coursier/ivy/Pattern$Chunk$Opt of class coursier/ivy/Pattern$Chunk$
  public static #17= #27 of #14;          // =class coursier/ivy/Pattern$Chunk$Opt$ of class coursier/ivy/Pattern$Chunk$
  public static final #30= #29 of #14;    // Var=class coursier/ivy/Pattern$Chunk$Var of class coursier/ivy/Pattern$Chunk$
  public static #17= #32 of #14;          // =class coursier/ivy/Pattern$Chunk$Var$ of class coursier/ivy/Pattern$Chunk$
  public static abstract #35= #34 of #2;  // ChunkOrProperty=class coursier/ivy/PropertiesPattern$ChunkOrProperty of class coursier/ivy/PropertiesPattern
  public static #17= #37 of #2;           // =class coursier/ivy/PropertiesPattern$ChunkOrProperty$ of class coursier/ivy/PropertiesPattern
  public static final #20= #39 of #37;    // Const=class coursier/ivy/PropertiesPattern$ChunkOrProperty$Const of class coursier/ivy/PropertiesPattern$ChunkOrProperty$
  public static final #25= #41 of #37;    // Opt=class coursier/ivy/PropertiesPattern$ChunkOrProperty$Opt of class coursier/ivy/PropertiesPattern$ChunkOrProperty$
  public static final #44= #43 of #37;    // Prop=class coursier/ivy/PropertiesPattern$ChunkOrProperty$Prop of class coursier/ivy/PropertiesPattern$ChunkOrProperty$
  public static final #30= #46 of #37;    // Var=class coursier/ivy/PropertiesPattern$ChunkOrProperty$Var of class coursier/ivy/PropertiesPattern$ChunkOrProperty$
  public static #51= #48 of #50;          // TraverseOps=class coursier/util/Traverse$TraverseOps of class coursier/util/Traverse
  public static final #56= #53 of #55;    // FailureBuilder=class coursier/util/ValidationNel$FailureBuilder of class coursier/util/ValidationNel
  public static final #59= #58 of #55;    // SuccessBuilder=class coursier/util/ValidationNel$SuccessBuilder of class coursier/util/ValidationNel
  public static final #64= #61 of #63;    // Lookup=class java/lang/invoke/MethodHandles$Lookup of class java/lang/invoke/MethodHandles
  public static final #69= #66 of #68;    // LeftProjection=class scala/util/Either$LeftProjection of class scala/util/Either
SourceFile: "Pattern.scala"
RuntimeVisibleAnnotations:
  0: #10(#11=s#12)
    scala.reflect.ScalaSignature(
      bytes="\u0006\u0005\reb\u0001B;w\u0005mD!\"a\t\u0001\u0005\u000b\u0007I\u0011AA\u0013\u0011)\u0019\u0019\u0001\u0001B\u0001B\u0003%\u0011q\u0005\u0005\b\u0003\u000f\u0002A\u0011AB\u0003\u0011\u001d\t)\u0006\u0001C\u0001\u0003/Bqa!\u0003\u0001\t\u0003\u0019Y\u0001C\u0004\u0004 \u0001!\ta!\t\t\u000f\u0005\u001d\u0006\u0001\"\u0011\u0002*\"9\u0011Q\u0017\u0001\u0005B\r\u0015\u0002bBAe\u0001\u0011\u00053\u0011\u0006\u0005\b\u0003\u001f\u0004A\u0011IAi\u0011\u001d\tI\u000e\u0001C\u0005\u0007[Aq!a9\u0001\t\u0003\n)\u000fC\u0004\u0002h\u0002!\t%!;\t\u000f\u0005-\b\u0001\"\u0011\u00042!9\u00111\u001f\u0001\u0005B\rUraBA\u001am\"\u0005\u0011Q\u0007\u0004\u0007kZD\t!a\u000e\t\u000f\u0005\u001d\u0013\u0003\"\u0001\u0002J\u00199\u00111J\t\u0002\"\u00055\u0003bBA$\'\u0011\u0005\u0011q\n\u0005\b\u0003+\u001ab\u0011AA,\u000f\u001d\u0011\t-\u0005E\u0001\u0003c2q!a\u0013\u0012\u0011\u0003\ti\u0007C\u0004\u0002H]!\t!a\u001c\t\u000f\u0005Mt\u0003b\u0001\u0002v\u00191\u00111P\f\u0003\u0003{B!\"a \u001b\u0005\u000b\u0007I\u0011AA,\u0011)\t\tI\u0007B\u0001B\u0003%\u0011\u0011\f\u0005\u000b\u0003\u0007S\"Q1A\u0005\u0002\u0005\u0015\u0005BCAH5\t\u0005\t\u0015!\u0003\u0002\b\"9\u0011q\t\u000e\u0005\u0002\u0005E\u0005bBA+5\u0011\u0005\u0011q\u000b\u0005\b\u00037SB\u0011AAO\u0011\u001d\t\tK\u0007C\u0001\u0003GCq!a*\u001b\t\u0003\nI\u000bC\u0004\u00026j!\t%a.\t\u000f\u0005%\'\u0004\"\u0011\u0002L\"9\u0011q\u001a\u000e\u0005B\u0005E\u0007bBAm5\u0011%\u00111\u001c\u0005\b\u0003GTB\u0011IAs\u0011\u001d\t9O\u0007C!\u0003SDq!a;\u001b\t\u0003\ni\u000fC\u0004\u0002tj!\t%!>\b\u000f\u0005ex\u0003#\u0001\u0002|\u001a9\u00111P\f\t\u0002\u0005u\bbBA$[\u0011\u0005\u0011q \u0005\b\u0005\u0003iC\u0011\u0001B\u0002\u0011%\u0011I!LA\u0001\n\u0013\u0011YA\u0002\u0004\u0003\u0014]\u0011!Q\u0003\u0005\u000b\u0003\u007f\n$Q1A\u0005\u0002\u0005]\u0003BCAAc\t\u0005\t\u0015!\u0003\u0002Z!9\u0011qI\u0019\u0005\u0002\t]\u0001bBA+c\u0011\u0005\u0011q\u000b\u0005\b\u00037\u000bD\u0011\u0001B\u000f\u0011\u001d\t9+\rC!\u0003SCq!!.2\t\u0003\u0012\t\u0003C\u0004\u0002JF\"\tE!\n\t\u000f\u0005=\u0017\u0007\"\u0011\u0002R\"9\u0011\u0011\\\u0019\u0005\n\t%\u0002bBArc\u0011\u0005\u0013Q\u001d\u0005\b\u0003O\fD\u0011IAu\u0011\u001d\tY/\rC!\u0005cAq!a=2\t\u0003\u0012)dB\u0004\u0003:]A\tAa\u000f\u0007\u000f\tMq\u0003#\u0001\u0003>!9\u0011qI!\u0005\u0002\t}\u0002b\u0002B\u0001\u0003\u0012\u0005!\u0011\t\u0005\n\u0005\u0013\t\u0015\u0011!C\u0005\u0005\u00171aA!\u0012\u0018\u0005\t\u001d\u0003B\u0003B%\u000b\n\u0015\r\u0011\"\u0001\u0003L!Q!QJ#\u0003\u0002\u0003\u0006I!!$\t\u000f\u0005\u001dS\t\"\u0001\u0003P!9\u0011QK#\u0005\u0002\u0005]\u0003b\u0002B+\u000b\u0012\u0005!q\u000b\u0005\b\u0003O+E\u0011IAU\u0011\u001d\t),\u0012C!\u00057Bq!!3F\t\u0003\u0012y\u0006C\u0004\u0002P\u0016#\t%!5\t\u000f\u0005eW\t\"\u0003\u0003d!9\u00111]#\u0005B\u0005\u0015\bbBAt\u000b\u0012\u0005\u0013\u0011\u001e\u0005\b\u0003W,E\u0011\tB4\u0011\u001d\t\u00190\u0012C!\u0005W:qAa\u001c\u0018\u0011\u0003\u0011\tHB\u0004\u0003F]A\tAa\u001d\t\u000f\u0005\u001dS\u000b\"\u0001\u0003v!9!\u0011A+\u0005\u0002\t]\u0004b\u0002B\u0001+\u0012\u0005!Q\u0010\u0005\b\u0005\u0003)F\u0011\u0001BC\u0011\u001d\u0011\t!\u0016C\u0001\u0005\u001fC\u0011B!\u0003V\u0003\u0003%IAa\u0003\u0007\r\u0005-tC\u0001BR\u0011)\u0011\t\u000b\u0018BC\u0002\u0013\u0005\u0011q\u000b\u0005\u000b\u0005Kc&\u0011!Q\u0001\n\u0005e\u0003bBA$9\u0012\u0005!q\u0015\u0005\b\u0003+bF\u0011AA,\u0011\u001d\u0011Y\u000b\u0018C\u0001\u0005[Cq!a*]\t\u0003\nI\u000bC\u0004\u00026r#\tE!-\t\u000f\u0005%G\f\"\u0011\u00036\"9\u0011q\u001a/\u0005B\u0005E\u0007bBAm9\u0012%!\u0011\u0006\u0005\b\u0003GdF\u0011IAs\u0011\u001d\t9\u000f\u0018C!\u0003SDq!a;]\t\u0003\u0012I\fC\u0004\u0002tr#\tE!0\b\u000f\tMu\u0003#\u0001\u0003\u0016\u001a9\u00111N\f\t\u0002\t]\u0005bBA$Y\u0012\u0005!\u0011\u0014\u0005\b\u0005\u0003aG\u0011\u0001BN\u0011%\u0011I\u0001\\A\u0001\n\u0013\u0011Y\u0001C\u0005\u0003\n]\t\t\u0011\"\u0003\u0003\f!9!1Y\t\u0005\n\t\u0015\u0007b\u0002Bx#\u0011\u0005!\u0011\u001f\u0005\b\u0005\u0003\tB\u0011\u0001B\u0000\u0011%\u0011I!EA\u0001\n\u0013\u0011YAA\tQe>\u0004XM\u001d;jKN\u0004\u0016\r\u001e;fe:T!a\u001e=\u0002\u0007%4\u0018PC\u0001z\u0003!\u0019w.\u001e:tS\u0016\u00148\u0001A\n\u0007\u0001q\f)!a\u0003\u0011\u0007u\f\t!D\u0001\u007f\u0015\u0005y\u0018!B:dC2\f\u0017bAA\u0002}\n1\u0011I\\=SK\u001a\u00042!`A\u0004\u0013\r\tIA \u0002\b!J|G-^2u!\u0011\ti!!\b\u000f\t\u0005=\u0011\u0011\u0004\b\u0005\u0003#\t9\"\u0004\u0002\u0002\u0014)\u0019\u0011Q\u0003>\u0002\rq\u0012xn\u001c;?\u0013\u0005y\u0018bAA\u000e}\u00069\u0001/Y2lC\u001e,\u0017\u0002BA\u0010\u0003C\u0011AbU3sS\u0006d\u0017N_1cY\u0016T1!a\u0007\u007f\u0003\u0019\u0019\u0007.\u001e8lgV\u0011\u0011q\u0005\t\u0007\u0003\u001b\tI#!\f\n\t\u0005-\u0012\u0011\u0005\u0002\u0004\'\u0016\f\bcAA\u0018\'9\u0019\u0011\u0011\u0007\t\u000e\u0003Y\f\u0011\u0003\u0015:pa\u0016\u0014H/[3t!\u0006$H/\u001a:o!\r\t\t$E\n\u0005#q\fI\u0004\u0005\u0003\u0002<\u0005\u0015SBAA\u001f\u0015\u0011\ty$!\u0011\u0002\u0005%|\'BAA\"\u0003\u0011Q\u0017M^1\n\t\u0005}\u0011QH\u0001\u0007y%t\u0017\u000e\u001e \u0015\u0005\u0005U\"aD\"ik:\\wJ\u001d)s_B,\'\u000f^=\u0014\rMa\u0018QAA\u0006)\t\t\t\u0006E\u0002\u0002TMi\u0011!E\u0001\u0007gR\u0014\u0018N\\4\u0016\u0005\u0005e\u0003\u0003BA.\u0003GrA!!\u0018\u0002`A\u0019\u0011\u0011\u0003@\n\u0007\u0005\u0005d0\u0001\u0004Qe\u0016$WMZ\u0005\u0005\u0003K\n9G\u0001\u0004TiJLgn\u001a\u0006\u0004\u0003Cr\u0018&B\n]\u000bj\t$!B\"p]N$8\u0003B\f}\u0003s!\"!!\u001d\u0011\u0007\u0005Ms#\u0001\u0006ge>l7\u000b\u001e:j]\u001e$B!!\u0015\u0002x!9\u0011\u0011P\rA\u0002\u0005e\u0013!A:\u0003\tA\u0013x\u000e]\n\b5\u0005E\u0013QAA\u0006\u0003\u0011q\u0017-\\3\u0002\u000b9\fW.\u001a\u0011\u0002\u0017\u0005dG/\u001a:oCRLg/Z\u000b\u0003\u0003\u000f\u0003R!`AE\u0003\u001bK1!a#\u007f\u0005\u0019y\u0005\u000f^5p]B1\u0011QBA\u0015\u0003#\nA\"\u00197uKJt\u0017\r^5wK\u0002\"b!a%\u0002\u0018\u0006e\u0005cAAK55\tq\u0003C\u0004\u0002\u0000}\u0001\r!!\u0017\t\u000f\u0005\ru\u00041\u0001\u0002\b\u0006Aq/\u001b;i\u001d\u0006lW\r\u0006\u0003\u0002\u0014\u0006}\u0005bBA@C\u0001\u0007\u0011\u0011L\u0001\u0010o&$\b.\u00117uKJt\u0017\r^5wKR!\u00111SAS\u0011\u001d\t\u0019I\ta\u0001\u0003\u000f\u000b\u0001\u0002^8TiJLgn\u001a\u000b\u0003\u0003W\u0003B!!,\u000246\u0011\u0011q\u0016\u0006\u0005\u0003c\u000b\t%\u0001\u0003mC:<\u0017\u0002BA3\u0003_\u000b\u0001bY1o\u000bF,\u0018\r\u001c\u000b\u0005\u0003s\u000by\fE\u0002~\u0003wK1!!0\u007f\u0005\u001d\u0011un\u001c7fC:Dq!!1%\u0001\u0004\t\u0019-A\u0002pE*\u00042!`Ac\u0013\r\t9M \u0002\u0004\u0003:L\u0018AB3rk\u0006d7\u000f\u0006\u0003\u0002:\u00065\u0007bBAaK\u0001\u0007\u00111Y\u0001\tQ\u0006\u001c\bnQ8eKR\u0011\u00111\u001b\t\u0004{\u0006U\u0017bAAl}\n\u0019\u0011J\u001c;\u0002\u000bQ,\b\u000f\\3\u0016\u0005\u0005u\u0007cB?\u0002`\u0006e\u0013qQ\u0005\u0004\u0003Ct(A\u0002+va2,\'\'A\u0007qe>$Wo\u0019;Qe\u00164\u0017\u000e_\u000b\u0003\u0003W\u000bA\u0002\u001d:pIV\u001cG/\u0011:jif,\"!a5\u0002\u001dA\u0014x\u000eZ;di\u0016cW-\\3oiR!\u00111YAx\u0011\u001d\t\tP\u000ba\u0001\u0003\'\f\u0011A\\\u0001\u0013aJ|G-^2u\u000b2,W.\u001a8u\u001d\u0006lW\r\u0006\u0003\u0002,\u0006]\bbBAyW\u0001\u0007\u00111[\u0001\u0005!J|\u0007\u000fE\u0002\u0002\u00166\u001aB!\f?\u0002:Q\u0011\u00111`\u0001\u0006CB\u0004H.\u001f\u000b\u0007\u0003\'\u0013)Aa\u0002\t\u000f\u0005}t\u00061\u0001\u0002Z!9\u00111Q\u0018A\u0002\u0005\u001d\u0015\u0001D<sSR,\'+\u001a9mC\u000e,GC\u0001B\u0007!\u0011\tiKa\u0004\n\t\tE\u0011q\u0016\u0002\u0007\u001f\nTWm\u0019;\u0003\u0007Y\u000b\'oE\u00042\u0003#\n)!a\u0003\u0015\t\te!1\u0004\t\u0004\u0003+\u000b\u0004bBA@i\u0001\u0007\u0011\u0011\f\u000b\u0005\u00053\u0011y\u0002C\u0004\u0002\u0000Y\u0002\r!!\u0017\u0015\t\u0005e&1\u0005\u0005\b\u0003\u0003D\u0004\u0019AAb)\u0011\tILa\n\t\u000f\u0005\u0005\u0017\b1\u0001\u0002DV\u0011!1\u0006\t\u0006{\n5\u0012\u0011L\u0005\u0004\u0005_q(A\u0002+va2,\u0017\u0007\u0006\u0003\u0002D\nM\u0002bBAy}\u0001\u0007\u00111\u001b\u000b\u0005\u0003W\u00139\u0004C\u0004\u0002r~\u0002\r!a5\u0002\u0007Y\u000b\'\u000fE\u0002\u0002\u0016\u0006\u001bB!\u0011?\u0002:Q\u0011!1\b\u000b\u0005\u00053\u0011\u0019\u0005C\u0004\u0002\u0000\r\u0003\r!!\u0017\u0003\u0007=\u0003HoE\u0004F\u0003#\n)!a\u0003\u0002\u000f\r|g\u000e^3oiV\u0011\u0011QR\u0001\tG>tG/\u001a8uAQ!!\u0011\u000bB*!\r\t)*\u0012\u0005\b\u0005\u0013B\u0005\u0019AAG\u0003-9\u0018\u000e\u001e5D_:$XM\u001c;\u0015\t\tE#\u0011\f\u0005\b\u0005\u0013R\u0005\u0019AAG)\u0011\tIL!\u0018\t\u000f\u0005\u0005G\n1\u0001\u0002DR!\u0011\u0011\u0018B1\u0011\u001d\t\t-\u0014a\u0001\u0003\u0007,\"A!\u001a\u0011\u000bu\u0014i#!$\u0015\t\u0005\r\'\u0011\u000e\u0005\b\u0003c\u0014\u0006\u0019AAj)\u0011\tYK!\u001c\t\u000f\u0005E8\u000b1\u0001\u0002T\u0006\u0019q\n\u001d;\u0011\u0007\u0005UUk\u0005\u0003Vy\u0006eBC\u0001B9)\u0011\u0011\tF!\u001f\t\u000f\tmt\u000b1\u0001\u0002R\u0005!Q\r\\3n)\u0019\u0011\tFa \u0003\u0002\"9!1\u0010-A\u0002\u0005E\u0003b\u0002BB1\u0002\u0007\u0011\u0011K\u0001\u0006K2,W.\r\u000b\t\u0005#\u00129I!#\u0003\f\"9!1P-A\u0002\u0005E\u0003b\u0002BB3\u0002\u0007\u0011\u0011\u000b\u0005\b\u0005\u001bK\u0006\u0019AA)\u0003\u0015)G.Z73)\u0011\u0011\tF!%\t\u000f\t%#\f1\u0001\u0002\u000e\u0006)1i\u001c8tiB\u0019\u0011Q\u00137\u0014\t1d\u0018\u0011\b\u000b\u0003\u0005+#BA!(\u0003 B\u0019\u0011Q\u0013/\t\u000f\t\u0005f\u000e1\u0001\u0002Z\u0005)a/\u00197vKN9A,!\u0015\u0002\u0006\u0005-\u0011A\u0002<bYV,\u0007\u0005\u0006\u0003\u0003\u001e\n%\u0006b\u0002BQ?\u0002\u0007\u0011\u0011L\u0001\no&$\bNV1mk\u0016$BA!(\u00030\"9!\u0011U1A\u0002\u0005eC\u0003BA]\u0005gCq!!1d\u0001\u0004\t\u0019\r\u0006\u0003\u0002:\n]\u0006bBAaI\u0002\u0007\u00111\u0019\u000b\u0005\u0003\u0007\u0014Y\fC\u0004\u0002r&\u0004\r!a5\u0015\t\u0005-&q\u0018\u0005\b\u0003cT\u0007\u0019AAj\u0003=\u0019\u0005.\u001e8l\u001fJ\u0004&o\u001c9feRL\u0018A\u00029beN,\'/\u0006\u0003\u0003H\n\rH\u0003\u0002Be\u0005;\u0004bAa3\u0003X\u00065e\u0002\u0002Bg\u0005\'tA!!\u0005\u0003P&\u0011!\u0011[\u0001\nM\u0006\u001cH\u000f]1sg\u0016LA!a\u0007\u0003V*\u0011!\u0011[\u0005\u0005\u00053\u0014YNA\u0001Q\u0015\u0011\tYB!6\t\u0013\t}\u0017/!AA\u0004\t\u0005\u0018AC3wS\u0012,gnY3%cA1!1\u001aBl\u0003\u0007$qA!:r\u0005\u0004\u00119OA\u0001`#\u0011\u0011I/a1\u0011\u0007u\u0014Y/C\u0002\u0003nz\u0014qAT8uQ&tw-A\u0003qCJ\u001cX\r\u0006\u0003\u0003t\nm\b\u0003CA\u0007\u0005k\fIF!?\n\t\t]\u0018\u0011\u0005\u0002\u0007\u000b&$\b.\u001a:\u0011\u0007\u0005E\u0002\u0001C\u0004\u0003~J\u0004\r!!\u0017\u0002\u000fA\fG\u000f^3s]R!!\u0011`B\u0001\u0011\u001d\t\u0019c\u001da\u0001\u0003O\tqa\u00195v].\u001c\b\u0005\u0006\u0003\u0003z\u000e\u001d\u0001bBA\u0012\u0007\u0001\u0007\u0011qE\u0001\u0015gV\u00147\u000f^5ukR,\u0007K]8qKJ$\u0018.Z:\u0015\t\r51Q\u0003\t\t\u0003\u001b\u0011)0!\u0017\u0004\u0010A!\u0011\u0011GB\t\u0013\r\u0019\u0019B\u001e\u0002\b!\u0006$H/\u001a:o\u0011\u001d\u00199\"\u0002a\u0001\u00073\t!\u0002\u001d:pa\u0016\u0014H/[3t!!\tYfa\u0007\u0002Z\u0005e\u0013\u0002BB\u000f\u0003O\u00121!T1q\u0003)9\u0018\u000e\u001e5DQVt7n\u001d\u000b\u0005\u0005s\u001c\u0019\u0003C\u0004\u0002$\u0019\u0001\r!a\n\u0015\t\u0005e6q\u0005\u0005\b\u0003\u0003D\u0001\u0019AAb)\u0011\tIla\u000b\t\u000f\u0005\u0005\u0017\u00021\u0001\u0002DV\u00111q\u0006\t\u0006{\n5\u0012q\u0005\u000b\u0005\u0003\u0007\u001c\u0019\u0004C\u0004\u0002r:\u0001\r!a5\u0015\t\u0005-6q\u0007\u0005\b\u0003c|\u0001\u0019AAj\u0001"
    )
BootstrapMethods:
  0: #128 REF_invokeStatic java/lang/invoke/LambdaMetafactory.altMetafactory:(Ljava/lang/invoke/MethodHandles$Lookup;Ljava/lang/String;Ljava/lang/invoke/MethodType;[Ljava/lang/Object;)Ljava/lang/invoke/CallSite;
    Method arguments:
      #113 (Ljava/lang/Object;)Ljava/lang/Object;
      #118 REF_invokeStatic coursier/ivy/PropertiesPattern.$anonfun$string$1:(Lcoursier/ivy/PropertiesPattern$ChunkOrProperty;)Ljava/lang/String;
      #119 (Lcoursier/ivy/PropertiesPattern$ChunkOrProperty;)Ljava/lang/String;
      #120 5
      #121 1
      #119 (Lcoursier/ivy/PropertiesPattern$ChunkOrProperty;)Ljava/lang/String;
  1: #128 REF_invokeStatic java/lang/invoke/LambdaMetafactory.altMetafactory:(Ljava/lang/invoke/MethodHandles$Lookup;Ljava/lang/String;Ljava/lang/invoke/MethodType;[Ljava/lang/Object;)Ljava/lang/invoke/CallSite;
    Method arguments:
      #113 (Ljava/lang/Object;)Ljava/lang/Object;
      #159 REF_invokeStatic coursier/ivy/PropertiesPattern.$anonfun$substituteProperties$1:(Lscala/collection/immutable/Map;Lcoursier/ivy/PropertiesPattern$ChunkOrProperty;)Lcoursier/util/ValidationNel;
      #161 (Lcoursier/ivy/PropertiesPattern$ChunkOrProperty;)Lcoursier/util/ValidationNel;
      #120 5
      #121 1
      #161 (Lcoursier/ivy/PropertiesPattern$ChunkOrProperty;)Lcoursier/util/ValidationNel;
  2: #128 REF_invokeStatic java/lang/invoke/LambdaMetafactory.altMetafactory:(Ljava/lang/invoke/MethodHandles$Lookup;Ljava/lang/String;Ljava/lang/invoke/MethodType;[Ljava/lang/Object;)Ljava/lang/invoke/CallSite;
    Method arguments:
      #113 (Ljava/lang/Object;)Ljava/lang/Object;
      #173 REF_invokeStatic coursier/ivy/PropertiesPattern.$anonfun$substituteProperties$4:(Lscala/collection/immutable/Seq;)Lcoursier/ivy/Pattern;
      #174 (Lscala/collection/immutable/Seq;)Lcoursier/ivy/Pattern;
      #120 5
      #121 1
      #174 (Lscala/collection/immutable/Seq;)Lcoursier/ivy/Pattern;
  3: #128 REF_invokeStatic java/lang/invoke/LambdaMetafactory.altMetafactory:(Ljava/lang/invoke/MethodHandles$Lookup;Ljava/lang/String;Ljava/lang/invoke/MethodType;[Ljava/lang/Object;)Ljava/lang/invoke/CallSite;
    Method arguments:
      #113 (Ljava/lang/Object;)Ljava/lang/Object;
      #190 REF_invokeStatic coursier/ivy/PropertiesPattern.$anonfun$substituteProperties$5:(Lscala/collection/immutable/$colon$colon;)Ljava/lang/String;
      #191 (Lscala/collection/immutable/$colon$colon;)Ljava/lang/String;
      #120 5
      #121 1
      #191 (Lscala/collection/immutable/$colon$colon;)Ljava/lang/String;
  4: #128 REF_invokeStatic java/lang/invoke/LambdaMetafactory.altMetafactory:(Ljava/lang/invoke/MethodHandles$Lookup;Ljava/lang/String;Ljava/lang/invoke/MethodType;[Ljava/lang/Object;)Ljava/lang/invoke/CallSite;
    Method arguments:
      #113 (Ljava/lang/Object;)Ljava/lang/Object;
      #358 REF_invokeStatic coursier/ivy/PropertiesPattern.$anonfun$substituteProperties$2:(Lcoursier/ivy/Pattern;)Lscala/collection/immutable/Vector;
      #359 (Lcoursier/ivy/Pattern;)Lscala/collection/immutable/Vector;
      #120 5
      #121 1
      #359 (Lcoursier/ivy/Pattern;)Lscala/collection/immutable/Vector;
  5: #128 REF_invokeStatic java/lang/invoke/LambdaMetafactory.altMetafactory:(Ljava/lang/invoke/MethodHandles$Lookup;Ljava/lang/String;Ljava/lang/invoke/MethodType;[Ljava/lang/Object;)Ljava/lang/invoke/CallSite;
    Method arguments:
      #113 (Ljava/lang/Object;)Ljava/lang/Object;
      #379 REF_invokeStatic coursier/ivy/PropertiesPattern.$anonfun$substituteProperties$3:(Lcoursier/ivy/Pattern;)Lscala/collection/immutable/Seq;
      #380 (Lcoursier/ivy/Pattern;)Lscala/collection/immutable/Seq;
      #120 5
      #121 1
      #380 (Lcoursier/ivy/Pattern;)Lscala/collection/immutable/Seq;
  6: #441 REF_invokeStatic scala/runtime/LambdaDeserialize.bootstrap:(Ljava/lang/invoke/MethodHandles$Lookup;Ljava/lang/String;Ljava/lang/invoke/MethodType;[Ljava/lang/invoke/MethodHandle;)Ljava/lang/invoke/CallSite;
    Method arguments:
      #118 REF_invokeStatic coursier/ivy/PropertiesPattern.$anonfun$string$1:(Lcoursier/ivy/PropertiesPattern$ChunkOrProperty;)Ljava/lang/String;
      #159 REF_invokeStatic coursier/ivy/PropertiesPattern.$anonfun$substituteProperties$1:(Lscala/collection/immutable/Map;Lcoursier/ivy/PropertiesPattern$ChunkOrProperty;)Lcoursier/util/ValidationNel;
      #358 REF_invokeStatic coursier/ivy/PropertiesPattern.$anonfun$substituteProperties$2:(Lcoursier/ivy/Pattern;)Lscala/collection/immutable/Vector;
      #379 REF_invokeStatic coursier/ivy/PropertiesPattern.$anonfun$substituteProperties$3:(Lcoursier/ivy/Pattern;)Lscala/collection/immutable/Seq;
      #173 REF_invokeStatic coursier/ivy/PropertiesPattern.$anonfun$substituteProperties$4:(Lscala/collection/immutable/Seq;)Lcoursier/ivy/Pattern;
      #190 REF_invokeStatic coursier/ivy/PropertiesPattern.$anonfun$substituteProperties$5:(Lscala/collection/immutable/$colon$colon;)Ljava/lang/String;
  ScalaInlineInfo: length = 0x72 (unknown attribute)
   01 01 00 16 00 76 00 77 01 00 9F 00 A0 01 01 1C
   01 1D 01 01 25 01 26 01 00 AD 00 AE 01 00 BE 00
   BF 01 00 CC 00 CD 01 00 E8 00 E9 01 00 4A 00 6C
   01 00 EC 00 E9 01 00 F2 00 F3 01 01 07 00 F3 01
   01 08 01 09 01 01 15 01 16 01 00 67 00 5F 01 00
   5E 00 5F 01 01 06 00 71 01 00 70 00 71 01 00 93
   00 94 01 00 D0 00 71 01 00 FE 00 FF 01 00 CB 00
   4E 01
  ScalaSig: length = 0x3 (unknown attribute)
   05 02 00
