Classfile /Users/mw/Projects/slang-braindump/.jar/jar8/assemble/slang-braindump/assemble/content/dk/brics/automaton/MinimizationOperations$IntPair.class
  Last modified May 29, 2022; size 413 bytes
  SHA-256 checksum 47cff5fb6a747e53954043a16fddcbd05bf72e8f2855dfad3834b5439822bb25
  Compiled from "MinimizationOperations.java"
class dk.brics.automaton.MinimizationOperations$IntPair
  minor version: 0
  major version: 52
  flags: (0x0020) ACC_SUPER
  this_class: #4                          // dk/brics/automaton/MinimizationOperations$IntPair
  super_class: #5                         // java/lang/Object
  interfaces: 0, fields: 2, methods: 1, attributes: 2
Constant pool:
   #1 = Methodref          #5.#15         // java/lang/Object."<init>":()V
   #2 = Fieldref           #4.#16         // dk/brics/automaton/MinimizationOperations$IntPair.n1:I
   #3 = Fieldref           #4.#17         // dk/brics/automaton/MinimizationOperations$IntPair.n2:I
   #4 = Class              #19            // dk/brics/automaton/MinimizationOperations$IntPair
   #5 = Class              #22            // java/lang/Object
   #6 = Utf8               n1
   #7 = Utf8               I
   #8 = Utf8               n2
   #9 = Utf8               <init>
  #10 = Utf8               (II)V
  #11 = Utf8               Code
  #12 = Utf8               LineNumberTable
  #13 = Utf8               SourceFile
  #14 = Utf8               MinimizationOperations.java
  #15 = NameAndType        #9:#23         // "<init>":()V
  #16 = NameAndType        #6:#7          // n1:I
  #17 = NameAndType        #8:#7          // n2:I
  #18 = Class              #24            // dk/brics/automaton/MinimizationOperations
  #19 = Utf8               dk/brics/automaton/MinimizationOperations$IntPair
  #20 = Utf8               IntPair
  #21 = Utf8               InnerClasses
  #22 = Utf8               java/lang/Object
  #23 = Utf8               ()V
  #24 = Utf8               dk/brics/automaton/MinimizationOperations
{
  int n1;
    descriptor: I
    flags: (0x0000)

  int n2;
    descriptor: I
    flags: (0x0000)

  dk.brics.automaton.MinimizationOperations$IntPair(int, int);
    descriptor: (II)V
    flags: (0x0000)
    Code:
      stack=2, locals=3, args_size=3
         0: aload_0
         1: invokespecial #1                  // Method java/lang/Object."<init>":()V
         4: aload_0
         5: iload_1
         6: putfield      #2                  // Field n1:I
         9: aload_0
        10: iload_2
        11: putfield      #3                  // Field n2:I
        14: return
      LineNumberTable:
        line 523: 0
        line 524: 4
        line 525: 9
        line 526: 14
}
SourceFile: "MinimizationOperations.java"
InnerClasses:
  static #20= #4 of #18;                  // IntPair=class dk/brics/automaton/MinimizationOperations$IntPair of class dk/brics/automaton/MinimizationOperations
