Classfile /Users/mw/Projects/slang-braindump/.jar/jar8/assemble/slang-braindump/assemble/content/dk/brics/automaton/MinimizationOperations$LabelComparator.class
  Last modified May 29, 2022; size 1121 bytes
  SHA-256 checksum f7a3f20be181151d4d650c35328527f52693dd63dadd3587c6f1df924ffc9c7a
  Compiled from "MinimizationOperations.java"
class dk.brics.automaton.MinimizationOperations$LabelComparator extends java.lang.Object implements java.util.Comparator<java.lang.Integer>
  minor version: 0
  major version: 52
  flags: (0x0020) ACC_SUPER
  this_class: #8                          // dk/brics/automaton/MinimizationOperations$LabelComparator
  super_class: #9                         // java/lang/Object
  interfaces: 1, fields: 1, methods: 3, attributes: 3
Constant pool:
   #1 = Methodref          #9.#28         // java/lang/Object."<init>":()V
   #2 = Fieldref           #8.#29         // dk/brics/automaton/MinimizationOperations$LabelComparator.labels:[Ldk/brics/automaton/MinimizationOperations$IntPair;
   #3 = Methodref          #6.#30         // java/lang/Integer.intValue:()I
   #4 = Fieldref           #12.#31        // dk/brics/automaton/MinimizationOperations$IntPair.n1:I
   #5 = Fieldref           #12.#32        // dk/brics/automaton/MinimizationOperations$IntPair.n2:I
   #6 = Class              #33            // java/lang/Integer
   #7 = Methodref          #8.#34         // dk/brics/automaton/MinimizationOperations$LabelComparator.compare:(Ljava/lang/Integer;Ljava/lang/Integer;)I
   #8 = Class              #36            // dk/brics/automaton/MinimizationOperations$LabelComparator
   #9 = Class              #38            // java/lang/Object
  #10 = Class              #39            // java/util/Comparator
  #11 = Utf8               labels
  #12 = Class              #40            // dk/brics/automaton/MinimizationOperations$IntPair
  #13 = Utf8               IntPair
  #14 = Utf8               InnerClasses
  #15 = Utf8               [Ldk/brics/automaton/MinimizationOperations$IntPair;
  #16 = Utf8               <init>
  #17 = Utf8               ([Ldk/brics/automaton/MinimizationOperations$IntPair;)V
  #18 = Utf8               Code
  #19 = Utf8               LineNumberTable
  #20 = Utf8               compare
  #21 = Utf8               (Ljava/lang/Integer;Ljava/lang/Integer;)I
  #22 = Utf8               StackMapTable
  #23 = Utf8               (Ljava/lang/Object;Ljava/lang/Object;)I
  #24 = Utf8               Signature
  #25 = Utf8               Ljava/lang/Object;Ljava/util/Comparator<Ljava/lang/Integer;>;
  #26 = Utf8               SourceFile
  #27 = Utf8               MinimizationOperations.java
  #28 = NameAndType        #16:#41        // "<init>":()V
  #29 = NameAndType        #11:#15        // labels:[Ldk/brics/automaton/MinimizationOperations$IntPair;
  #30 = NameAndType        #42:#43        // intValue:()I
  #31 = NameAndType        #44:#45        // n1:I
  #32 = NameAndType        #46:#45        // n2:I
  #33 = Utf8               java/lang/Integer
  #34 = NameAndType        #20:#21        // compare:(Ljava/lang/Integer;Ljava/lang/Integer;)I
  #35 = Class              #47            // dk/brics/automaton/MinimizationOperations
  #36 = Utf8               dk/brics/automaton/MinimizationOperations$LabelComparator
  #37 = Utf8               LabelComparator
  #38 = Utf8               java/lang/Object
  #39 = Utf8               java/util/Comparator
  #40 = Utf8               dk/brics/automaton/MinimizationOperations$IntPair
  #41 = Utf8               ()V
  #42 = Utf8               intValue
  #43 = Utf8               ()I
  #44 = Utf8               n1
  #45 = Utf8               I
  #46 = Utf8               n2
  #47 = Utf8               dk/brics/automaton/MinimizationOperations
{
  private dk.brics.automaton.MinimizationOperations$IntPair[] labels;
    descriptor: [Ldk/brics/automaton/MinimizationOperations$IntPair;
    flags: (0x0002) ACC_PRIVATE

  dk.brics.automaton.MinimizationOperations$LabelComparator(dk.brics.automaton.MinimizationOperations$IntPair[]);
    descriptor: ([Ldk/brics/automaton/MinimizationOperations$IntPair;)V
    flags: (0x0000)
    Code:
      stack=2, locals=2, args_size=2
         0: aload_0
         1: invokespecial #1                  // Method java/lang/Object."<init>":()V
         4: aload_0
         5: aload_1
         6: putfield      #2                  // Field labels:[Ldk/brics/automaton/MinimizationOperations$IntPair;
         9: return
      LineNumberTable:
        line 644: 0
        line 645: 4
        line 646: 9

  public int compare(java.lang.Integer, java.lang.Integer);
    descriptor: (Ljava/lang/Integer;Ljava/lang/Integer;)I
    flags: (0x0001) ACC_PUBLIC
    Code:
      stack=2, locals=5, args_size=3
         0: aload_0
         1: getfield      #2                  // Field labels:[Ldk/brics/automaton/MinimizationOperations$IntPair;
         4: aload_1
         5: invokevirtual #3                  // Method java/lang/Integer.intValue:()I
         8: aaload
         9: astore_3
        10: aload_0
        11: getfield      #2                  // Field labels:[Ldk/brics/automaton/MinimizationOperations$IntPair;
        14: aload_2
        15: invokevirtual #3                  // Method java/lang/Integer.intValue:()I
        18: aaload
        19: astore        4
        21: aload_3
        22: getfield      #4                  // Field dk/brics/automaton/MinimizationOperations$IntPair.n1:I
        25: aload         4
        27: getfield      #4                  // Field dk/brics/automaton/MinimizationOperations$IntPair.n1:I
        30: if_icmpge     35
        33: iconst_m1
        34: ireturn
        35: aload_3
        36: getfield      #4                  // Field dk/brics/automaton/MinimizationOperations$IntPair.n1:I
        39: aload         4
        41: getfield      #4                  // Field dk/brics/automaton/MinimizationOperations$IntPair.n1:I
        44: if_icmple     49
        47: iconst_1
        48: ireturn
        49: aload_3
        50: getfield      #5                  // Field dk/brics/automaton/MinimizationOperations$IntPair.n2:I
        53: aload         4
        55: getfield      #5                  // Field dk/brics/automaton/MinimizationOperations$IntPair.n2:I
        58: if_icmpge     63
        61: iconst_m1
        62: ireturn
        63: aload_3
        64: getfield      #5                  // Field dk/brics/automaton/MinimizationOperations$IntPair.n2:I
        67: aload         4
        69: getfield      #5                  // Field dk/brics/automaton/MinimizationOperations$IntPair.n2:I
        72: if_icmple     77
        75: iconst_1
        76: ireturn
        77: iconst_0
        78: ireturn
      LineNumberTable:
        line 649: 0
        line 650: 10
        line 651: 21
        line 652: 33
        line 653: 35
        line 654: 47
        line 655: 49
        line 656: 61
        line 657: 63
        line 658: 75
        line 659: 77
      StackMapTable: number_of_entries = 4
        frame_type = 253 /* append */
          offset_delta = 35
          locals = [ class dk/brics/automaton/MinimizationOperations$IntPair, class dk/brics/automaton/MinimizationOperations$IntPair ]
        frame_type = 13 /* same */
        frame_type = 13 /* same */
        frame_type = 13 /* same */

  public int compare(java.lang.Object, java.lang.Object);
    descriptor: (Ljava/lang/Object;Ljava/lang/Object;)I
    flags: (0x1041) ACC_PUBLIC, ACC_BRIDGE, ACC_SYNTHETIC
    Code:
      stack=3, locals=3, args_size=3
         0: aload_0
         1: aload_1
         2: checkcast     #6                  // class java/lang/Integer
         5: aload_2
         6: checkcast     #6                  // class java/lang/Integer
         9: invokevirtual #7                  // Method compare:(Ljava/lang/Integer;Ljava/lang/Integer;)I
        12: ireturn
      LineNumberTable:
        line 640: 0
}
Signature: #25                          // Ljava/lang/Object;Ljava/util/Comparator<Ljava/lang/Integer;>;
SourceFile: "MinimizationOperations.java"
InnerClasses:
  static #13= #12 of #35;                 // IntPair=class dk/brics/automaton/MinimizationOperations$IntPair of class dk/brics/automaton/MinimizationOperations
  static #37= #8 of #35;                  // LabelComparator=class dk/brics/automaton/MinimizationOperations$LabelComparator of class dk/brics/automaton/MinimizationOperations
