Classfile /Users/mw/Projects/slang-braindump/.jar/jar8/assemble/slang-braindump/assemble/content/dk/brics/automaton/StringUnionOperations.class
  Last modified May 29, 2022; size 4876 bytes
  SHA-256 checksum 384647a5868a017e7851ba321e994f295effd3bd97e63c775335218001b2877b
  Compiled from "StringUnionOperations.java"
public final class dk.brics.automaton.StringUnionOperations
  minor version: 0
  major version: 52
  flags: (0x0031) ACC_PUBLIC, ACC_FINAL, ACC_SUPER
  this_class: #47                         // dk/brics/automaton/StringUnionOperations
  super_class: #68                        // java/lang/Object
  interfaces: 0, fields: 5, methods: 12, attributes: 2
Constant pool:
    #1 = Methodref          #68.#118      // java/lang/Object."<init>":()V
    #2 = Class              #119          // java/util/HashMap
    #3 = Methodref          #2.#118       // java/util/HashMap."<init>":()V
    #4 = Fieldref           #47.#120      // dk/brics/automaton/StringUnionOperations.register:Ljava/util/HashMap;
    #5 = Class              #121          // dk/brics/automaton/StringUnionOperations$State
    #6 = Methodref          #5.#118       // dk/brics/automaton/StringUnionOperations$State."<init>":()V
    #7 = Fieldref           #47.#122      // dk/brics/automaton/StringUnionOperations.root:Ldk/brics/automaton/StringUnionOperations$State;
    #8 = Fieldref           #47.#123      // dk/brics/automaton/StringUnionOperations.$assertionsDisabled:Z
    #9 = Class              #124          // java/lang/AssertionError
   #10 = String             #125          // Automaton already built.
   #11 = Methodref          #9.#126       // java/lang/AssertionError."<init>":(Ljava/lang/Object;)V
   #12 = InterfaceMethodref #91.#127      // java/lang/CharSequence.length:()I
   #13 = String             #128          // Input sequences must not be empty.
   #14 = Fieldref           #47.#129      // dk/brics/automaton/StringUnionOperations.previous:Ljava/lang/StringBuilder;
   #15 = Fieldref           #47.#130      // dk/brics/automaton/StringUnionOperations.LEXICOGRAPHIC_ORDER:Ljava/util/Comparator;
   #16 = InterfaceMethodref #131.#132     // java/util/Comparator.compare:(Ljava/lang/Object;Ljava/lang/Object;)I
   #17 = Class              #133          // java/lang/StringBuilder
   #18 = Methodref          #17.#118      // java/lang/StringBuilder."<init>":()V
   #19 = String             #134          // Input must be sorted:
   #20 = Methodref          #17.#135      // java/lang/StringBuilder.append:(Ljava/lang/String;)Ljava/lang/StringBuilder;
   #21 = Methodref          #17.#136      // java/lang/StringBuilder.append:(Ljava/lang/Object;)Ljava/lang/StringBuilder;
   #22 = String             #137          //  >=
   #23 = Methodref          #17.#138      // java/lang/StringBuilder.toString:()Ljava/lang/String;
   #24 = Methodref          #47.#139      // dk/brics/automaton/StringUnionOperations.setPrevious:(Ljava/lang/CharSequence;)Z
   #25 = Methodref          #9.#118       // java/lang/AssertionError."<init>":()V
   #26 = InterfaceMethodref #91.#138      // java/lang/CharSequence.toString:()Ljava/lang/String;
   #27 = Methodref          #47.#140      // dk/brics/automaton/StringUnionOperations.cpCount:(Ljava/lang/String;)I
   #28 = Methodref          #47.#141      // dk/brics/automaton/StringUnionOperations.cpAt:(Ljava/lang/String;I)I
   #29 = Methodref          #5.#142       // dk/brics/automaton/StringUnionOperations$State.lastChild:(I)Ldk/brics/automaton/StringUnionOperations$State;
   #30 = Methodref          #5.#143       // dk/brics/automaton/StringUnionOperations$State.hasChildren:()Z
   #31 = Methodref          #47.#144      // dk/brics/automaton/StringUnionOperations.replaceOrRegister:(Ldk/brics/automaton/StringUnionOperations$State;)V
   #32 = Methodref          #47.#145      // dk/brics/automaton/StringUnionOperations.addSuffix:(Ldk/brics/automaton/StringUnionOperations$State;Ljava/lang/CharSequence;I)V
   #33 = Class              #146          // java/lang/IllegalStateException
   #34 = Methodref          #33.#118      // java/lang/IllegalStateException."<init>":()V
   #35 = Methodref          #51.#147      // java/util/IdentityHashMap.get:(Ljava/lang/Object;)Ljava/lang/Object;
   #36 = Class              #148          // dk/brics/automaton/State
   #37 = Methodref          #36.#118      // dk/brics/automaton/State."<init>":()V
   #38 = Fieldref           #5.#149       // dk/brics/automaton/StringUnionOperations$State.is_final:Z
   #39 = Methodref          #36.#150      // dk/brics/automaton/State.setAccept:(Z)V
   #40 = Methodref          #51.#151      // java/util/IdentityHashMap.put:(Ljava/lang/Object;Ljava/lang/Object;)Ljava/lang/Object;
   #41 = Fieldref           #5.#152       // dk/brics/automaton/StringUnionOperations$State.labels:[I
   #42 = Fieldref           #5.#153       // dk/brics/automaton/StringUnionOperations$State.states:[Ldk/brics/automaton/StringUnionOperations$State;
   #43 = Class              #154          // dk/brics/automaton/Transition
   #44 = Methodref          #47.#155      // dk/brics/automaton/StringUnionOperations.convert:(Ldk/brics/automaton/StringUnionOperations$State;Ljava/util/IdentityHashMap;)Ldk/brics/automaton/State;
   #45 = Methodref          #43.#156      // dk/brics/automaton/Transition."<init>":(ILdk/brics/automaton/State;)V
   #46 = Methodref          #36.#157      // dk/brics/automaton/State.addTransition:(Ldk/brics/automaton/Transition;)V
   #47 = Class              #158          // dk/brics/automaton/StringUnionOperations
   #48 = Methodref          #47.#118      // dk/brics/automaton/StringUnionOperations."<init>":()V
   #49 = Methodref          #47.#159      // dk/brics/automaton/StringUnionOperations.add:(Ljava/lang/CharSequence;)V
   #50 = Methodref          #47.#160      // dk/brics/automaton/StringUnionOperations.complete:()Ldk/brics/automaton/StringUnionOperations$State;
   #51 = Class              #161          // java/util/IdentityHashMap
   #52 = Methodref          #51.#118      // java/util/IdentityHashMap."<init>":()V
   #53 = Methodref          #17.#162      // java/lang/StringBuilder.setLength:(I)V
   #54 = Methodref          #17.#163      // java/lang/StringBuilder.append:(Ljava/lang/CharSequence;)Ljava/lang/StringBuilder;
   #55 = Methodref          #5.#164       // dk/brics/automaton/StringUnionOperations$State.lastChild:()Ldk/brics/automaton/StringUnionOperations$State;
   #56 = Methodref          #2.#147       // java/util/HashMap.get:(Ljava/lang/Object;)Ljava/lang/Object;
   #57 = Methodref          #5.#165       // dk/brics/automaton/StringUnionOperations$State.replaceLastChild:(Ldk/brics/automaton/StringUnionOperations$State;)V
   #58 = Methodref          #2.#151       // java/util/HashMap.put:(Ljava/lang/Object;Ljava/lang/Object;)Ljava/lang/Object;
   #59 = Methodref          #5.#166       // dk/brics/automaton/StringUnionOperations$State.newState:(I)Ldk/brics/automaton/StringUnionOperations$State;
   #60 = Methodref          #92.#167      // java/lang/String.offsetByCodePoints:(II)I
   #61 = Methodref          #92.#168      // java/lang/String.codePointAt:(I)I
   #62 = Methodref          #92.#127      // java/lang/String.length:()I
   #63 = Methodref          #92.#169      // java/lang/String.codePointCount:(II)I
   #64 = Methodref          #92.#170      // java/lang/String.substring:(II)Ljava/lang/String;
   #65 = Methodref          #171.#172     // java/lang/Class.desiredAssertionStatus:()Z
   #66 = Class              #173          // dk/brics/automaton/StringUnionOperations$1
   #67 = Methodref          #66.#118      // dk/brics/automaton/StringUnionOperations$1."<init>":()V
   #68 = Class              #174          // java/lang/Object
   #69 = Utf8               State
   #70 = Utf8               InnerClasses
   #71 = Utf8               LEXICOGRAPHIC_ORDER
   #72 = Utf8               Ljava/util/Comparator;
   #73 = Utf8               Signature
   #74 = Utf8               Ljava/util/Comparator<Ljava/lang/CharSequence;>;
   #75 = Utf8               register
   #76 = Utf8               Ljava/util/HashMap;
   #77 = Utf8               Ljava/util/HashMap<Ldk/brics/automaton/StringUnionOperations$State;Ldk/brics/automaton/StringUnionOperations$State;>;
   #78 = Utf8               root
   #79 = Utf8               Ldk/brics/automaton/StringUnionOperations$State;
   #80 = Utf8               previous
   #81 = Utf8               Ljava/lang/StringBuilder;
   #82 = Utf8               $assertionsDisabled
   #83 = Utf8               Z
   #84 = Utf8               <init>
   #85 = Utf8               ()V
   #86 = Utf8               Code
   #87 = Utf8               LineNumberTable
   #88 = Utf8               add
   #89 = Utf8               (Ljava/lang/CharSequence;)V
   #90 = Utf8               StackMapTable
   #91 = Class              #175          // java/lang/CharSequence
   #92 = Class              #176          // java/lang/String
   #93 = Utf8               complete
   #94 = Utf8               ()Ldk/brics/automaton/StringUnionOperations$State;
   #95 = Utf8               convert
   #96 = Utf8               (Ldk/brics/automaton/StringUnionOperations$State;Ljava/util/IdentityHashMap;)Ldk/brics/automaton/State;
   #97 = Class              #177          // "[I"
   #98 = Class              #178          // "[Ldk/brics/automaton/StringUnionOperations$State;"
   #99 = Utf8               (Ldk/brics/automaton/StringUnionOperations$State;Ljava/util/IdentityHashMap<Ldk/brics/automaton/StringUnionOperations$State;Ldk/brics/automaton/State;>;)Ldk/brics/automaton/State;
  #100 = Utf8               build
  #101 = Utf8               ([Ljava/lang/CharSequence;)Ldk/brics/automaton/State;
  #102 = Class              #179          // "[Ljava/lang/CharSequence;"
  #103 = Utf8               setPrevious
  #104 = Utf8               (Ljava/lang/CharSequence;)Z
  #105 = Utf8               replaceOrRegister
  #106 = Utf8               (Ldk/brics/automaton/StringUnionOperations$State;)V
  #107 = Utf8               addSuffix
  #108 = Utf8               (Ldk/brics/automaton/StringUnionOperations$State;Ljava/lang/CharSequence;I)V
  #109 = Utf8               cpAt
  #110 = Utf8               (Ljava/lang/String;I)I
  #111 = Utf8               cpCount
  #112 = Utf8               (Ljava/lang/String;)I
  #113 = Utf8               cpSubstring
  #114 = Utf8               (Ljava/lang/String;II)Ljava/lang/String;
  #115 = Utf8               <clinit>
  #116 = Utf8               SourceFile
  #117 = Utf8               StringUnionOperations.java
  #118 = NameAndType        #84:#85       // "<init>":()V
  #119 = Utf8               java/util/HashMap
  #120 = NameAndType        #75:#76       // register:Ljava/util/HashMap;
  #121 = Utf8               dk/brics/automaton/StringUnionOperations$State
  #122 = NameAndType        #78:#79       // root:Ldk/brics/automaton/StringUnionOperations$State;
  #123 = NameAndType        #82:#83       // $assertionsDisabled:Z
  #124 = Utf8               java/lang/AssertionError
  #125 = Utf8               Automaton already built.
  #126 = NameAndType        #84:#180      // "<init>":(Ljava/lang/Object;)V
  #127 = NameAndType        #181:#182     // length:()I
  #128 = Utf8               Input sequences must not be empty.
  #129 = NameAndType        #80:#81       // previous:Ljava/lang/StringBuilder;
  #130 = NameAndType        #71:#72       // LEXICOGRAPHIC_ORDER:Ljava/util/Comparator;
  #131 = Class              #183          // java/util/Comparator
  #132 = NameAndType        #184:#185     // compare:(Ljava/lang/Object;Ljava/lang/Object;)I
  #133 = Utf8               java/lang/StringBuilder
  #134 = Utf8               Input must be sorted:
  #135 = NameAndType        #186:#187     // append:(Ljava/lang/String;)Ljava/lang/StringBuilder;
  #136 = NameAndType        #186:#188     // append:(Ljava/lang/Object;)Ljava/lang/StringBuilder;
  #137 = Utf8                >=
  #138 = NameAndType        #189:#190     // toString:()Ljava/lang/String;
  #139 = NameAndType        #103:#104     // setPrevious:(Ljava/lang/CharSequence;)Z
  #140 = NameAndType        #111:#112     // cpCount:(Ljava/lang/String;)I
  #141 = NameAndType        #109:#110     // cpAt:(Ljava/lang/String;I)I
  #142 = NameAndType        #191:#192     // lastChild:(I)Ldk/brics/automaton/StringUnionOperations$State;
  #143 = NameAndType        #193:#194     // hasChildren:()Z
  #144 = NameAndType        #105:#106     // replaceOrRegister:(Ldk/brics/automaton/StringUnionOperations$State;)V
  #145 = NameAndType        #107:#108     // addSuffix:(Ldk/brics/automaton/StringUnionOperations$State;Ljava/lang/CharSequence;I)V
  #146 = Utf8               java/lang/IllegalStateException
  #147 = NameAndType        #195:#196     // get:(Ljava/lang/Object;)Ljava/lang/Object;
  #148 = Utf8               dk/brics/automaton/State
  #149 = NameAndType        #197:#83      // is_final:Z
  #150 = NameAndType        #198:#199     // setAccept:(Z)V
  #151 = NameAndType        #200:#201     // put:(Ljava/lang/Object;Ljava/lang/Object;)Ljava/lang/Object;
  #152 = NameAndType        #202:#177     // labels:[I
  #153 = NameAndType        #203:#178     // states:[Ldk/brics/automaton/StringUnionOperations$State;
  #154 = Utf8               dk/brics/automaton/Transition
  #155 = NameAndType        #95:#96       // convert:(Ldk/brics/automaton/StringUnionOperations$State;Ljava/util/IdentityHashMap;)Ldk/brics/automaton/State;
  #156 = NameAndType        #84:#204      // "<init>":(ILdk/brics/automaton/State;)V
  #157 = NameAndType        #205:#206     // addTransition:(Ldk/brics/automaton/Transition;)V
  #158 = Utf8               dk/brics/automaton/StringUnionOperations
  #159 = NameAndType        #88:#89       // add:(Ljava/lang/CharSequence;)V
  #160 = NameAndType        #93:#94       // complete:()Ldk/brics/automaton/StringUnionOperations$State;
  #161 = Utf8               java/util/IdentityHashMap
  #162 = NameAndType        #207:#208     // setLength:(I)V
  #163 = NameAndType        #186:#209     // append:(Ljava/lang/CharSequence;)Ljava/lang/StringBuilder;
  #164 = NameAndType        #191:#94      // lastChild:()Ldk/brics/automaton/StringUnionOperations$State;
  #165 = NameAndType        #210:#106     // replaceLastChild:(Ldk/brics/automaton/StringUnionOperations$State;)V
  #166 = NameAndType        #211:#192     // newState:(I)Ldk/brics/automaton/StringUnionOperations$State;
  #167 = NameAndType        #212:#213     // offsetByCodePoints:(II)I
  #168 = NameAndType        #214:#215     // codePointAt:(I)I
  #169 = NameAndType        #216:#213     // codePointCount:(II)I
  #170 = NameAndType        #217:#218     // substring:(II)Ljava/lang/String;
  #171 = Class              #219          // java/lang/Class
  #172 = NameAndType        #220:#194     // desiredAssertionStatus:()Z
  #173 = Utf8               dk/brics/automaton/StringUnionOperations$1
  #174 = Utf8               java/lang/Object
  #175 = Utf8               java/lang/CharSequence
  #176 = Utf8               java/lang/String
  #177 = Utf8               [I
  #178 = Utf8               [Ldk/brics/automaton/StringUnionOperations$State;
  #179 = Utf8               [Ljava/lang/CharSequence;
  #180 = Utf8               (Ljava/lang/Object;)V
  #181 = Utf8               length
  #182 = Utf8               ()I
  #183 = Utf8               java/util/Comparator
  #184 = Utf8               compare
  #185 = Utf8               (Ljava/lang/Object;Ljava/lang/Object;)I
  #186 = Utf8               append
  #187 = Utf8               (Ljava/lang/String;)Ljava/lang/StringBuilder;
  #188 = Utf8               (Ljava/lang/Object;)Ljava/lang/StringBuilder;
  #189 = Utf8               toString
  #190 = Utf8               ()Ljava/lang/String;
  #191 = Utf8               lastChild
  #192 = Utf8               (I)Ldk/brics/automaton/StringUnionOperations$State;
  #193 = Utf8               hasChildren
  #194 = Utf8               ()Z
  #195 = Utf8               get
  #196 = Utf8               (Ljava/lang/Object;)Ljava/lang/Object;
  #197 = Utf8               is_final
  #198 = Utf8               setAccept
  #199 = Utf8               (Z)V
  #200 = Utf8               put
  #201 = Utf8               (Ljava/lang/Object;Ljava/lang/Object;)Ljava/lang/Object;
  #202 = Utf8               labels
  #203 = Utf8               states
  #204 = Utf8               (ILdk/brics/automaton/State;)V
  #205 = Utf8               addTransition
  #206 = Utf8               (Ldk/brics/automaton/Transition;)V
  #207 = Utf8               setLength
  #208 = Utf8               (I)V
  #209 = Utf8               (Ljava/lang/CharSequence;)Ljava/lang/StringBuilder;
  #210 = Utf8               replaceLastChild
  #211 = Utf8               newState
  #212 = Utf8               offsetByCodePoints
  #213 = Utf8               (II)I
  #214 = Utf8               codePointAt
  #215 = Utf8               (I)I
  #216 = Utf8               codePointCount
  #217 = Utf8               substring
  #218 = Utf8               (II)Ljava/lang/String;
  #219 = Utf8               java/lang/Class
  #220 = Utf8               desiredAssertionStatus
{
  public static final java.util.Comparator<java.lang.CharSequence> LEXICOGRAPHIC_ORDER;
    descriptor: Ljava/util/Comparator;
    flags: (0x0019) ACC_PUBLIC, ACC_STATIC, ACC_FINAL
    Signature: #74                          // Ljava/util/Comparator<Ljava/lang/CharSequence;>;

  private java.util.HashMap<dk.brics.automaton.StringUnionOperations$State, dk.brics.automaton.StringUnionOperations$State> register;
    descriptor: Ljava/util/HashMap;
    flags: (0x0002) ACC_PRIVATE
    Signature: #77                          // Ljava/util/HashMap<Ldk/brics/automaton/StringUnionOperations$State;Ldk/brics/automaton/StringUnionOperations$State;>;

  private dk.brics.automaton.StringUnionOperations$State root;
    descriptor: Ldk/brics/automaton/StringUnionOperations$State;
    flags: (0x0002) ACC_PRIVATE

  private java.lang.StringBuilder previous;
    descriptor: Ljava/lang/StringBuilder;
    flags: (0x0002) ACC_PRIVATE

  static final boolean $assertionsDisabled;
    descriptor: Z
    flags: (0x1018) ACC_STATIC, ACC_FINAL, ACC_SYNTHETIC

  public dk.brics.automaton.StringUnionOperations();
    descriptor: ()V
    flags: (0x0001) ACC_PUBLIC
    Code:
      stack=3, locals=1, args_size=1
         0: aload_0
         1: invokespecial #1                  // Method java/lang/Object."<init>":()V
         4: aload_0
         5: new           #2                  // class java/util/HashMap
         8: dup
         9: invokespecial #3                  // Method java/util/HashMap."<init>":()V
        12: putfield      #4                  // Field register:Ljava/util/HashMap;
        15: aload_0
        16: new           #5                  // class dk/brics/automaton/StringUnionOperations$State
        19: dup
        20: invokespecial #6                  // Method dk/brics/automaton/StringUnionOperations$State."<init>":()V
        23: putfield      #7                  // Field root:Ldk/brics/automaton/StringUnionOperations$State;
        26: return
      LineNumberTable:
        line 14: 0
        line 230: 4
        line 235: 15

  public void add(java.lang.CharSequence);
    descriptor: (Ljava/lang/CharSequence;)V
    flags: (0x0001) ACC_PUBLIC
    Code:
      stack=4, locals=7, args_size=2
         0: getstatic     #8                  // Field $assertionsDisabled:Z
         3: ifne          23
         6: aload_0
         7: getfield      #4                  // Field register:Ljava/util/HashMap;
        10: ifnonnull     23
        13: new           #9                  // class java/lang/AssertionError
        16: dup
        17: ldc           #10                 // String Automaton already built.
        19: invokespecial #11                 // Method java/lang/AssertionError."<init>":(Ljava/lang/Object;)V
        22: athrow
        23: getstatic     #8                  // Field $assertionsDisabled:Z
        26: ifne          48
        29: aload_1
        30: invokeinterface #12,  1           // InterfaceMethod java/lang/CharSequence.length:()I
        35: ifgt          48
        38: new           #9                  // class java/lang/AssertionError
        41: dup
        42: ldc           #13                 // String Input sequences must not be empty.
        44: invokespecial #11                 // Method java/lang/AssertionError."<init>":(Ljava/lang/Object;)V
        47: athrow
        48: getstatic     #8                  // Field $assertionsDisabled:Z
        51: ifne          116
        54: aload_0
        55: getfield      #14                 // Field previous:Ljava/lang/StringBuilder;
        58: ifnull        116
        61: getstatic     #15                 // Field LEXICOGRAPHIC_ORDER:Ljava/util/Comparator;
        64: aload_0
        65: getfield      #14                 // Field previous:Ljava/lang/StringBuilder;
        68: aload_1
        69: invokeinterface #16,  3           // InterfaceMethod java/util/Comparator.compare:(Ljava/lang/Object;Ljava/lang/Object;)I
        74: ifle          116
        77: new           #9                  // class java/lang/AssertionError
        80: dup
        81: new           #17                 // class java/lang/StringBuilder
        84: dup
        85: invokespecial #18                 // Method java/lang/StringBuilder."<init>":()V
        88: ldc           #19                 // String Input must be sorted:
        90: invokevirtual #20                 // Method java/lang/StringBuilder.append:(Ljava/lang/String;)Ljava/lang/StringBuilder;
        93: aload_0
        94: getfield      #14                 // Field previous:Ljava/lang/StringBuilder;
        97: invokevirtual #21                 // Method java/lang/StringBuilder.append:(Ljava/lang/Object;)Ljava/lang/StringBuilder;
       100: ldc           #22                 // String  >=
       102: invokevirtual #20                 // Method java/lang/StringBuilder.append:(Ljava/lang/String;)Ljava/lang/StringBuilder;
       105: aload_1
       106: invokevirtual #21                 // Method java/lang/StringBuilder.append:(Ljava/lang/Object;)Ljava/lang/StringBuilder;
       109: invokevirtual #23                 // Method java/lang/StringBuilder.toString:()Ljava/lang/String;
       112: invokespecial #11                 // Method java/lang/AssertionError."<init>":(Ljava/lang/Object;)V
       115: athrow
       116: getstatic     #8                  // Field $assertionsDisabled:Z
       119: ifne          138
       122: aload_0
       123: aload_1
       124: invokespecial #24                 // Method setPrevious:(Ljava/lang/CharSequence;)Z
       127: ifne          138
       130: new           #9                  // class java/lang/AssertionError
       133: dup
       134: invokespecial #25                 // Method java/lang/AssertionError."<init>":()V
       137: athrow
       138: aload_1
       139: invokeinterface #26,  1           // InterfaceMethod java/lang/CharSequence.toString:()Ljava/lang/String;
       144: astore_2
       145: iconst_0
       146: istore_3
       147: aload_2
       148: invokestatic  #27                 // Method cpCount:(Ljava/lang/String;)I
       151: istore        4
       153: aload_0
       154: getfield      #7                  // Field root:Ldk/brics/automaton/StringUnionOperations$State;
       157: astore        6
       159: iload_3
       160: iload         4
       162: if_icmpge     191
       165: aload         6
       167: aload_2
       168: iload_3
       169: invokestatic  #28                 // Method cpAt:(Ljava/lang/String;I)I
       172: invokevirtual #29                 // Method dk/brics/automaton/StringUnionOperations$State.lastChild:(I)Ldk/brics/automaton/StringUnionOperations$State;
       175: dup
       176: astore        5
       178: ifnull        191
       181: aload         5
       183: astore        6
       185: iinc          3, 1
       188: goto          159
       191: aload         6
       193: invokevirtual #30                 // Method dk/brics/automaton/StringUnionOperations$State.hasChildren:()Z
       196: ifeq          205
       199: aload_0
       200: aload         6
       202: invokespecial #31                 // Method replaceOrRegister:(Ldk/brics/automaton/StringUnionOperations$State;)V
       205: aload_0
       206: aload         6
       208: aload_1
       209: iload_3
       210: invokespecial #32                 // Method addSuffix:(Ldk/brics/automaton/StringUnionOperations$State;Ljava/lang/CharSequence;I)V
       213: return
      LineNumberTable:
        line 248: 0
        line 249: 23
        line 250: 48
        line 252: 116
        line 255: 138
        line 256: 145
        line 257: 153
        line 258: 159
        line 259: 181
        line 260: 185
        line 263: 191
        line 264: 199
        line 266: 205
        line 267: 213
      StackMapTable: number_of_entries = 7
        frame_type = 23 /* same */
        frame_type = 24 /* same */
        frame_type = 251 /* same_frame_extended */
          offset_delta = 67
        frame_type = 21 /* same */
        frame_type = 255 /* full_frame */
          offset_delta = 20
          locals = [ class dk/brics/automaton/StringUnionOperations, class java/lang/CharSequence, class java/lang/String, int, int, top, class dk/brics/automaton/StringUnionOperations$State ]
          stack = []
        frame_type = 31 /* same */
        frame_type = 13 /* same */

  public dk.brics.automaton.StringUnionOperations$State complete();
    descriptor: ()Ldk/brics/automaton/StringUnionOperations$State;
    flags: (0x0001) ACC_PUBLIC
    Code:
      stack=2, locals=1, args_size=1
         0: aload_0
         1: getfield      #4                  // Field register:Ljava/util/HashMap;
         4: ifnonnull     15
         7: new           #33                 // class java/lang/IllegalStateException
        10: dup
        11: invokespecial #34                 // Method java/lang/IllegalStateException."<init>":()V
        14: athrow
        15: aload_0
        16: getfield      #7                  // Field root:Ldk/brics/automaton/StringUnionOperations$State;
        19: invokevirtual #30                 // Method dk/brics/automaton/StringUnionOperations$State.hasChildren:()Z
        22: ifeq          33
        25: aload_0
        26: aload_0
        27: getfield      #7                  // Field root:Ldk/brics/automaton/StringUnionOperations$State;
        30: invokespecial #31                 // Method replaceOrRegister:(Ldk/brics/automaton/StringUnionOperations$State;)V
        33: aload_0
        34: aconst_null
        35: putfield      #4                  // Field register:Ljava/util/HashMap;
        38: aload_0
        39: getfield      #7                  // Field root:Ldk/brics/automaton/StringUnionOperations$State;
        42: areturn
      LineNumberTable:
        line 276: 0
        line 277: 7
        line 279: 15
        line 280: 25
        line 282: 33
        line 283: 38
      StackMapTable: number_of_entries = 2
        frame_type = 15 /* same */
        frame_type = 17 /* same */

  private static dk.brics.automaton.State convert(dk.brics.automaton.StringUnionOperations$State, java.util.IdentityHashMap<dk.brics.automaton.StringUnionOperations$State, dk.brics.automaton.State>);
    descriptor: (Ldk/brics/automaton/StringUnionOperations$State;Ljava/util/IdentityHashMap;)Ldk/brics/automaton/State;
    flags: (0x000a) ACC_PRIVATE, ACC_STATIC
    Code:
      stack=6, locals=9, args_size=2
         0: aload_1
         1: aload_0
         2: invokevirtual #35                 // Method java/util/IdentityHashMap.get:(Ljava/lang/Object;)Ljava/lang/Object;
         5: checkcast     #36                 // class dk/brics/automaton/State
         8: astore_2
         9: aload_2
        10: ifnull        15
        13: aload_2
        14: areturn
        15: new           #36                 // class dk/brics/automaton/State
        18: dup
        19: invokespecial #37                 // Method dk/brics/automaton/State."<init>":()V
        22: astore_2
        23: aload_2
        24: aload_0
        25: getfield      #38                 // Field dk/brics/automaton/StringUnionOperations$State.is_final:Z
        28: invokevirtual #39                 // Method dk/brics/automaton/State.setAccept:(Z)V
        31: aload_1
        32: aload_0
        33: aload_2
        34: invokevirtual #40                 // Method java/util/IdentityHashMap.put:(Ljava/lang/Object;Ljava/lang/Object;)Ljava/lang/Object;
        37: pop
        38: iconst_0
        39: istore_3
        40: aload_0
        41: getfield      #41                 // Field dk/brics/automaton/StringUnionOperations$State.labels:[I
        44: astore        4
        46: aload_0
        47: getfield      #42                 // Field dk/brics/automaton/StringUnionOperations$State.states:[Ldk/brics/automaton/StringUnionOperations$State;
        50: astore        5
        52: aload         5
        54: arraylength
        55: istore        6
        57: iconst_0
        58: istore        7
        60: iload         7
        62: iload         6
        64: if_icmpge     104
        67: aload         5
        69: iload         7
        71: aaload
        72: astore        8
        74: aload_2
        75: new           #43                 // class dk/brics/automaton/Transition
        78: dup
        79: aload         4
        81: iload_3
        82: iinc          3, 1
        85: iaload
        86: aload         8
        88: aload_1
        89: invokestatic  #44                 // Method convert:(Ldk/brics/automaton/StringUnionOperations$State;Ljava/util/IdentityHashMap;)Ldk/brics/automaton/State;
        92: invokespecial #45                 // Method dk/brics/automaton/Transition."<init>":(ILdk/brics/automaton/State;)V
        95: invokevirtual #46                 // Method dk/brics/automaton/State.addTransition:(Ldk/brics/automaton/Transition;)V
        98: iinc          7, 1
       101: goto          60
       104: aload_2
       105: areturn
      LineNumberTable:
        line 291: 0
        line 292: 9
        line 293: 13
        line 295: 15
        line 296: 23
        line 298: 31
        line 299: 38
        line 300: 40
        line 301: 46
        line 302: 74
        line 301: 98
        line 305: 104
      StackMapTable: number_of_entries = 3
        frame_type = 252 /* append */
          offset_delta = 15
          locals = [ class dk/brics/automaton/State ]
        frame_type = 255 /* full_frame */
          offset_delta = 44
          locals = [ class dk/brics/automaton/StringUnionOperations$State, class java/util/IdentityHashMap, class dk/brics/automaton/State, int, class "[I", class "[Ldk/brics/automaton/StringUnionOperations$State;", int, int ]
          stack = []
        frame_type = 248 /* chop */
          offset_delta = 43
    Signature: #99                          // (Ldk/brics/automaton/StringUnionOperations$State;Ljava/util/IdentityHashMap<Ldk/brics/automaton/StringUnionOperations$State;Ldk/brics/automaton/State;>;)Ldk/brics/automaton/State;

  public static dk.brics.automaton.State build(java.lang.CharSequence[]);
    descriptor: ([Ljava/lang/CharSequence;)Ldk/brics/automaton/State;
    flags: (0x0009) ACC_PUBLIC, ACC_STATIC
    Code:
      stack=3, locals=6, args_size=1
         0: new           #47                 // class dk/brics/automaton/StringUnionOperations
         3: dup
         4: invokespecial #48                 // Method "<init>":()V
         7: astore_1
         8: aload_0
         9: astore_2
        10: aload_2
        11: arraylength
        12: istore_3
        13: iconst_0
        14: istore        4
        16: iload         4
        18: iload_3
        19: if_icmpge     40
        22: aload_2
        23: iload         4
        25: aaload
        26: astore        5
        28: aload_1
        29: aload         5
        31: invokevirtual #49                 // Method add:(Ljava/lang/CharSequence;)V
        34: iinc          4, 1
        37: goto          16
        40: aload_1
        41: invokevirtual #50                 // Method complete:()Ldk/brics/automaton/StringUnionOperations$State;
        44: new           #51                 // class java/util/IdentityHashMap
        47: dup
        48: invokespecial #52                 // Method java/util/IdentityHashMap."<init>":()V
        51: invokestatic  #44                 // Method convert:(Ldk/brics/automaton/StringUnionOperations$State;Ljava/util/IdentityHashMap;)Ldk/brics/automaton/State;
        54: areturn
      LineNumberTable:
        line 312: 0
        line 314: 8
        line 315: 28
        line 314: 34
        line 317: 40
      StackMapTable: number_of_entries = 2
        frame_type = 255 /* full_frame */
          offset_delta = 16
          locals = [ class "[Ljava/lang/CharSequence;", class dk/brics/automaton/StringUnionOperations, class "[Ljava/lang/CharSequence;", int, int ]
          stack = []
        frame_type = 248 /* chop */
          offset_delta = 23

  private boolean setPrevious(java.lang.CharSequence);
    descriptor: (Ljava/lang/CharSequence;)Z
    flags: (0x0002) ACC_PRIVATE
    Code:
      stack=3, locals=2, args_size=2
         0: aload_0
         1: getfield      #14                 // Field previous:Ljava/lang/StringBuilder;
         4: ifnonnull     18
         7: aload_0
         8: new           #17                 // class java/lang/StringBuilder
        11: dup
        12: invokespecial #18                 // Method java/lang/StringBuilder."<init>":()V
        15: putfield      #14                 // Field previous:Ljava/lang/StringBuilder;
        18: aload_0
        19: getfield      #14                 // Field previous:Ljava/lang/StringBuilder;
        22: iconst_0
        23: invokevirtual #53                 // Method java/lang/StringBuilder.setLength:(I)V
        26: aload_0
        27: getfield      #14                 // Field previous:Ljava/lang/StringBuilder;
        30: aload_1
        31: invokevirtual #54                 // Method java/lang/StringBuilder.append:(Ljava/lang/CharSequence;)Ljava/lang/StringBuilder;
        34: pop
        35: iconst_1
        36: ireturn
      LineNumberTable:
        line 324: 0
        line 325: 7
        line 327: 18
        line 328: 26
        line 330: 35
      StackMapTable: number_of_entries = 1
        frame_type = 18 /* same */

  private void replaceOrRegister(dk.brics.automaton.StringUnionOperations$State);
    descriptor: (Ldk/brics/automaton/StringUnionOperations$State;)V
    flags: (0x0002) ACC_PRIVATE
    Code:
      stack=3, locals=4, args_size=2
         0: aload_1
         1: invokevirtual #55                 // Method dk/brics/automaton/StringUnionOperations$State.lastChild:()Ldk/brics/automaton/StringUnionOperations$State;
         4: astore_2
         5: aload_2
         6: invokevirtual #30                 // Method dk/brics/automaton/StringUnionOperations$State.hasChildren:()Z
         9: ifeq          17
        12: aload_0
        13: aload_2
        14: invokespecial #31                 // Method replaceOrRegister:(Ldk/brics/automaton/StringUnionOperations$State;)V
        17: aload_0
        18: getfield      #4                  // Field register:Ljava/util/HashMap;
        21: aload_2
        22: invokevirtual #56                 // Method java/util/HashMap.get:(Ljava/lang/Object;)Ljava/lang/Object;
        25: checkcast     #5                  // class dk/brics/automaton/StringUnionOperations$State
        28: astore_3
        29: aload_3
        30: ifnull        41
        33: aload_1
        34: aload_3
        35: invokevirtual #57                 // Method dk/brics/automaton/StringUnionOperations$State.replaceLastChild:(Ldk/brics/automaton/StringUnionOperations$State;)V
        38: goto          51
        41: aload_0
        42: getfield      #4                  // Field register:Ljava/util/HashMap;
        45: aload_2
        46: aload_2
        47: invokevirtual #58                 // Method java/util/HashMap.put:(Ljava/lang/Object;Ljava/lang/Object;)Ljava/lang/Object;
        50: pop
        51: return
      LineNumberTable:
        line 338: 0
        line 340: 5
        line 341: 12
        line 343: 17
        line 344: 29
        line 345: 33
        line 347: 41
        line 349: 51
      StackMapTable: number_of_entries = 3
        frame_type = 252 /* append */
          offset_delta = 17
          locals = [ class dk/brics/automaton/StringUnionOperations$State ]
        frame_type = 252 /* append */
          offset_delta = 23
          locals = [ class dk/brics/automaton/StringUnionOperations$State ]
        frame_type = 9 /* same */

  private void addSuffix(dk.brics.automaton.StringUnionOperations$State, java.lang.CharSequence, int);
    descriptor: (Ldk/brics/automaton/StringUnionOperations$State;Ljava/lang/CharSequence;I)V
    flags: (0x0002) ACC_PRIVATE
    Code:
      stack=3, locals=7, args_size=4
         0: aload_2
         1: invokeinterface #26,  1           // InterfaceMethod java/lang/CharSequence.toString:()Ljava/lang/String;
         6: astore        4
         8: aload         4
        10: invokestatic  #27                 // Method cpCount:(Ljava/lang/String;)I
        13: istore        5
        15: iload_3
        16: istore        6
        18: iload         6
        20: iload         5
        22: if_icmpge     43
        25: aload_1
        26: aload         4
        28: iload         6
        30: invokestatic  #28                 // Method cpAt:(Ljava/lang/String;I)I
        33: invokevirtual #59                 // Method dk/brics/automaton/StringUnionOperations$State.newState:(I)Ldk/brics/automaton/StringUnionOperations$State;
        36: astore_1
        37: iinc          6, 1
        40: goto          18
        43: aload_1
        44: iconst_1
        45: putfield      #38                 // Field dk/brics/automaton/StringUnionOperations$State.is_final:Z
        48: return
      LineNumberTable:
        line 356: 0
        line 357: 8
        line 358: 15
        line 359: 25
        line 358: 37
        line 361: 43
        line 362: 48
      StackMapTable: number_of_entries = 2
        frame_type = 254 /* append */
          offset_delta = 18
          locals = [ class java/lang/String, int, int ]
        frame_type = 250 /* chop */
          offset_delta = 24

  public static int cpAt(java.lang.String, int);
    descriptor: (Ljava/lang/String;I)I
    flags: (0x0009) ACC_PUBLIC, ACC_STATIC
    Code:
      stack=4, locals=2, args_size=2
         0: aload_0
         1: aload_0
         2: iconst_0
         3: iload_1
         4: invokevirtual #60                 // Method java/lang/String.offsetByCodePoints:(II)I
         7: invokevirtual #61                 // Method java/lang/String.codePointAt:(I)I
        10: ireturn
      LineNumberTable:
        line 365: 0

  public static int cpCount(java.lang.String);
    descriptor: (Ljava/lang/String;)I
    flags: (0x0009) ACC_PUBLIC, ACC_STATIC
    Code:
      stack=3, locals=1, args_size=1
         0: aload_0
         1: iconst_0
         2: aload_0
         3: invokevirtual #62                 // Method java/lang/String.length:()I
         6: invokevirtual #63                 // Method java/lang/String.codePointCount:(II)I
         9: ireturn
      LineNumberTable:
        line 369: 0

  public static java.lang.String cpSubstring(java.lang.String, int, int);
    descriptor: (Ljava/lang/String;II)Ljava/lang/String;
    flags: (0x0009) ACC_PUBLIC, ACC_STATIC
    Code:
      stack=6, locals=4, args_size=3
         0: aload_0
         1: iconst_0
         2: iload_1
         3: invokevirtual #60                 // Method java/lang/String.offsetByCodePoints:(II)I
         6: istore_3
         7: aload_0
         8: iload_3
         9: aload_0
        10: iload_3
        11: iload_2
        12: iload_1
        13: isub
        14: invokevirtual #60                 // Method java/lang/String.offsetByCodePoints:(II)I
        17: invokevirtual #64                 // Method java/lang/String.substring:(II)Ljava/lang/String;
        20: areturn
      LineNumberTable:
        line 373: 0
        line 374: 7

  static {};
    descriptor: ()V
    flags: (0x0008) ACC_STATIC
    Code:
      stack=2, locals=0, args_size=0
         0: ldc           #47                 // class dk/brics/automaton/StringUnionOperations
         2: invokevirtual #65                 // Method java/lang/Class.desiredAssertionStatus:()Z
         5: ifne          12
         8: iconst_1
         9: goto          13
        12: iconst_0
        13: putstatic     #8                  // Field $assertionsDisabled:Z
        16: new           #66                 // class dk/brics/automaton/StringUnionOperations$1
        19: dup
        20: invokespecial #67                 // Method dk/brics/automaton/StringUnionOperations$1."<init>":()V
        23: putstatic     #15                 // Field LEXICOGRAPHIC_ORDER:Ljava/util/Comparator;
        26: return
      LineNumberTable:
        line 14: 0
        line 19: 16
      StackMapTable: number_of_entries = 2
        frame_type = 12 /* same */
        frame_type = 64 /* same_locals_1_stack_item */
          stack = [ int ]
}
SourceFile: "StringUnionOperations.java"
InnerClasses:
  static final #69= #5 of #47;            // State=class dk/brics/automaton/StringUnionOperations$State of class dk/brics/automaton/StringUnionOperations
  #66;                                    // class dk/brics/automaton/StringUnionOperations$1
