Classfile /Users/mw/Projects/slang-braindump/.jar/jar11/assemble/slang-braindump/assemble/content/scala/collection/compat/package$.class
  Last modified May 29, 2022; size 1091 bytes
  SHA-256 checksum c2fb055b8b9473ce408b477ff8b59c00d5b4949cef559174a6cc7d99b8e6b41c
  Compiled from "package.scala"
public final class scala.collection.compat.package$
  minor version: 0
  major version: 52
  flags: (0x0031) ACC_PUBLIC, ACC_FINAL, ACC_SUPER
  this_class: #2                          // scala/collection/compat/package$
  super_class: #4                         // java/lang/Object
  interfaces: 0, fields: 4, methods: 5, attributes: 3
Constant pool:
   #1 = Utf8               scala/collection/compat/package$
   #2 = Class              #1             // scala/collection/compat/package$
   #3 = Utf8               java/lang/Object
   #4 = Class              #3             // java/lang/Object
   #5 = Utf8               package.scala
   #6 = Utf8               MODULE$
   #7 = Utf8               Lscala/collection/compat/package$;
   #8 = Utf8               Factory
   #9 = Utf8               Lscala/collection/Factory$;
  #10 = Utf8               BuildFrom
  #11 = Utf8               Lscala/collection/BuildFrom$;
  #12 = Utf8               IterableOnce
  #13 = Utf8               Lscala/collection/IterableOnce$;
  #14 = Utf8               <clinit>
  #15 = Utf8               ()V
  #16 = Utf8               <init>
  #17 = NameAndType        #16:#15        // "<init>":()V
  #18 = Methodref          #2.#17         // scala/collection/compat/package$."<init>":()V
  #19 = NameAndType        #6:#7          // MODULE$:Lscala/collection/compat/package$;
  #20 = Fieldref           #2.#19         // scala/collection/compat/package$.MODULE$:Lscala/collection/compat/package$;
  #21 = Utf8               scala/collection/Factory$
  #22 = Class              #21            // scala/collection/Factory$
  #23 = NameAndType        #6:#9          // MODULE$:Lscala/collection/Factory$;
  #24 = Fieldref           #22.#23        // scala/collection/Factory$.MODULE$:Lscala/collection/Factory$;
  #25 = NameAndType        #8:#9          // Factory:Lscala/collection/Factory$;
  #26 = Fieldref           #2.#25         // scala/collection/compat/package$.Factory:Lscala/collection/Factory$;
  #27 = Utf8               scala/collection/BuildFrom$
  #28 = Class              #27            // scala/collection/BuildFrom$
  #29 = NameAndType        #6:#11         // MODULE$:Lscala/collection/BuildFrom$;
  #30 = Fieldref           #28.#29        // scala/collection/BuildFrom$.MODULE$:Lscala/collection/BuildFrom$;
  #31 = NameAndType        #10:#11        // BuildFrom:Lscala/collection/BuildFrom$;
  #32 = Fieldref           #2.#31         // scala/collection/compat/package$.BuildFrom:Lscala/collection/BuildFrom$;
  #33 = Utf8               scala/collection/IterableOnce$
  #34 = Class              #33            // scala/collection/IterableOnce$
  #35 = NameAndType        #6:#13         // MODULE$:Lscala/collection/IterableOnce$;
  #36 = Fieldref           #34.#35        // scala/collection/IterableOnce$.MODULE$:Lscala/collection/IterableOnce$;
  #37 = NameAndType        #12:#13        // IterableOnce:Lscala/collection/IterableOnce$;
  #38 = Fieldref           #2.#37         // scala/collection/compat/package$.IterableOnce:Lscala/collection/IterableOnce$;
  #39 = Utf8               ()Lscala/collection/Factory$;
  #40 = Utf8               this
  #41 = Utf8               ()Lscala/collection/BuildFrom$;
  #42 = Utf8               ()Lscala/collection/IterableOnce$;
  #43 = Methodref          #4.#17         // java/lang/Object."<init>":()V
  #44 = Utf8               Code
  #45 = Utf8               LineNumberTable
  #46 = Utf8               LocalVariableTable
  #47 = Utf8               SourceFile
  #48 = Utf8               ScalaInlineInfo
  #49 = Utf8               Scala
{
  public static final scala.collection.compat.package$ MODULE$;
    descriptor: Lscala/collection/compat/package$;
    flags: (0x0019) ACC_PUBLIC, ACC_STATIC, ACC_FINAL

  private static final scala.collection.Factory$ Factory;
    descriptor: Lscala/collection/Factory$;
    flags: (0x001a) ACC_PRIVATE, ACC_STATIC, ACC_FINAL

  private static final scala.collection.BuildFrom$ BuildFrom;
    descriptor: Lscala/collection/BuildFrom$;
    flags: (0x001a) ACC_PRIVATE, ACC_STATIC, ACC_FINAL

  private static final scala.collection.IterableOnce$ IterableOnce;
    descriptor: Lscala/collection/IterableOnce$;
    flags: (0x001a) ACC_PRIVATE, ACC_STATIC, ACC_FINAL

  public static {};
    descriptor: ()V
    flags: (0x0009) ACC_PUBLIC, ACC_STATIC
    Code:
      stack=2, locals=0, args_size=0
         0: new           #2                  // class scala/collection/compat/package$
         3: dup
         4: invokespecial #18                 // Method "<init>":()V
         7: putstatic     #20                 // Field MODULE$:Lscala/collection/compat/package$;
        10: getstatic     #24                 // Field scala/collection/Factory$.MODULE$:Lscala/collection/Factory$;
        13: putstatic     #26                 // Field Factory:Lscala/collection/Factory$;
        16: getstatic     #30                 // Field scala/collection/BuildFrom$.MODULE$:Lscala/collection/BuildFrom$;
        19: putstatic     #32                 // Field BuildFrom:Lscala/collection/BuildFrom$;
        22: getstatic     #36                 // Field scala/collection/IterableOnce$.MODULE$:Lscala/collection/IterableOnce$;
        25: putstatic     #38                 // Field IterableOnce:Lscala/collection/IterableOnce$;
        28: return
      LineNumberTable:
        line 15: 0
        line 17: 10
        line 20: 16
        line 23: 22
        line 15: 28

  public scala.collection.Factory$ Factory();
    descriptor: ()Lscala/collection/Factory$;
    flags: (0x0001) ACC_PUBLIC
    Code:
      stack=1, locals=1, args_size=1
         0: getstatic     #26                 // Field Factory:Lscala/collection/Factory$;
         3: areturn
      LineNumberTable:
        line 17: 0
      LocalVariableTable:
        Start  Length  Slot  Name   Signature
            0       4     0  this   Lscala/collection/compat/package$;

  public scala.collection.BuildFrom$ BuildFrom();
    descriptor: ()Lscala/collection/BuildFrom$;
    flags: (0x0001) ACC_PUBLIC
    Code:
      stack=1, locals=1, args_size=1
         0: getstatic     #32                 // Field BuildFrom:Lscala/collection/BuildFrom$;
         3: areturn
      LineNumberTable:
        line 20: 0
      LocalVariableTable:
        Start  Length  Slot  Name   Signature
            0       4     0  this   Lscala/collection/compat/package$;

  public scala.collection.IterableOnce$ IterableOnce();
    descriptor: ()Lscala/collection/IterableOnce$;
    flags: (0x0001) ACC_PUBLIC
    Code:
      stack=1, locals=1, args_size=1
         0: getstatic     #38                 // Field IterableOnce:Lscala/collection/IterableOnce$;
         3: areturn
      LineNumberTable:
        line 23: 0
      LocalVariableTable:
        Start  Length  Slot  Name   Signature
            0       4     0  this   Lscala/collection/compat/package$;

  private scala.collection.compat.package$();
    descriptor: ()V
    flags: (0x0002) ACC_PRIVATE
    Code:
      stack=1, locals=1, args_size=1
         0: aload_0
         1: invokespecial #43                 // Method java/lang/Object."<init>":()V
         4: return
      LineNumberTable:
        line 24: 0
        line 15: 4
      LocalVariableTable:
        Start  Length  Slot  Name   Signature
            0       5     0  this   Lscala/collection/compat/package$;
}
SourceFile: "package.scala"
  ScalaInlineInfo: length = 0x18 (unknown attribute)
   01 01 00 04 00 10 00 0F 01 00 0A 00 29 01 00 08
   00 27 01 00 0C 00 2A 01
  Scala: length = 0x0 (unknown attribute)

