Classfile /Users/mw/Projects/slang-braindump/.jar/jar8/assemble/slang-braindump/assemble/content/scala/collection/generic/BitOperations$Int$.class
  Last modified May 29, 2022; size 2708 bytes
  SHA-256 checksum 94261462dc8f05d0453641d06c62db91445e26eefa0f1b195bcb2ff3d251e7c9
  Compiled from "BitOperations.scala"
public class scala.collection.generic.BitOperations$Int$ implements scala.collection.generic.BitOperations$Int
  minor version: 0
  major version: 52
  flags: (0x0021) ACC_PUBLIC, ACC_SUPER
  this_class: #2                          // scala/collection/generic/BitOperations$Int$
  super_class: #4                         // java/lang/Object
  interfaces: 1, fields: 1, methods: 12, attributes: 4
Constant pool:
   #1 = Utf8               scala/collection/generic/BitOperations$Int$
   #2 = Class              #1             // scala/collection/generic/BitOperations$Int$
   #3 = Utf8               java/lang/Object
   #4 = Class              #3             // java/lang/Object
   #5 = Utf8               scala/collection/generic/BitOperations$Int
   #6 = Class              #5             // scala/collection/generic/BitOperations$Int
   #7 = Utf8               BitOperations.scala
   #8 = Utf8               scala/collection/generic/BitOperations
   #9 = Class              #8             // scala/collection/generic/BitOperations
  #10 = Utf8               Int
  #11 = Utf8               Int$
  #12 = Utf8               MODULE$
  #13 = Utf8               Lscala/collection/generic/BitOperations$Int$;
  #14 = Utf8               <clinit>
  #15 = Utf8               ()V
  #16 = Utf8               <init>
  #17 = NameAndType        #16:#15        // "<init>":()V
  #18 = Methodref          #2.#17         // scala/collection/generic/BitOperations$Int$."<init>":()V
  #19 = NameAndType        #12:#13        // MODULE$:Lscala/collection/generic/BitOperations$Int$;
  #20 = Fieldref           #2.#19         // scala/collection/generic/BitOperations$Int$.MODULE$:Lscala/collection/generic/BitOperations$Int$;
  #21 = Utf8               zero
  #22 = Utf8               (II)Z
  #23 = Utf8               i
  #24 = Utf8               mask
  #25 = Utf8               zero$
  #26 = Utf8               (Lscala/collection/generic/BitOperations$Int;II)Z
  #27 = NameAndType        #25:#26        // zero$:(Lscala/collection/generic/BitOperations$Int;II)Z
  #28 = InterfaceMethodref #6.#27         // scala/collection/generic/BitOperations$Int.zero$:(Lscala/collection/generic/BitOperations$Int;II)Z
  #29 = Utf8               this
  #30 = Utf8               I
  #31 = Utf8               (II)I
  #32 = Utf8               mask$
  #33 = Utf8               (Lscala/collection/generic/BitOperations$Int;II)I
  #34 = NameAndType        #32:#33        // mask$:(Lscala/collection/generic/BitOperations$Int;II)I
  #35 = InterfaceMethodref #6.#34         // scala/collection/generic/BitOperations$Int.mask$:(Lscala/collection/generic/BitOperations$Int;II)I
  #36 = Utf8               hasMatch
  #37 = Utf8               (III)Z
  #38 = Utf8               key
  #39 = Utf8               prefix
  #40 = Utf8               m
  #41 = Utf8               hasMatch$
  #42 = Utf8               (Lscala/collection/generic/BitOperations$Int;III)Z
  #43 = NameAndType        #41:#42        // hasMatch$:(Lscala/collection/generic/BitOperations$Int;III)Z
  #44 = InterfaceMethodref #6.#43         // scala/collection/generic/BitOperations$Int.hasMatch$:(Lscala/collection/generic/BitOperations$Int;III)Z
  #45 = Utf8               unsignedCompare
  #46 = Utf8               j
  #47 = Utf8               unsignedCompare$
  #48 = NameAndType        #47:#26        // unsignedCompare$:(Lscala/collection/generic/BitOperations$Int;II)Z
  #49 = InterfaceMethodref #6.#48         // scala/collection/generic/BitOperations$Int.unsignedCompare$:(Lscala/collection/generic/BitOperations$Int;II)Z
  #50 = Utf8               shorter
  #51 = Utf8               m1
  #52 = Utf8               m2
  #53 = Utf8               shorter$
  #54 = NameAndType        #53:#26        // shorter$:(Lscala/collection/generic/BitOperations$Int;II)Z
  #55 = InterfaceMethodref #6.#54         // scala/collection/generic/BitOperations$Int.shorter$:(Lscala/collection/generic/BitOperations$Int;II)Z
  #56 = Utf8               complement
  #57 = Utf8               (I)I
  #58 = Utf8               complement$
  #59 = Utf8               (Lscala/collection/generic/BitOperations$Int;I)I
  #60 = NameAndType        #58:#59        // complement$:(Lscala/collection/generic/BitOperations$Int;I)I
  #61 = InterfaceMethodref #6.#60         // scala/collection/generic/BitOperations$Int.complement$:(Lscala/collection/generic/BitOperations$Int;I)I
  #62 = Utf8               bits
  #63 = Utf8               (I)Lscala/collection/immutable/IndexedSeq;
  #64 = Utf8               (I)Lscala/collection/immutable/IndexedSeq<Ljava/lang/Object;>;
  #65 = Utf8               num
  #66 = Utf8               bits$
  #67 = Utf8               (Lscala/collection/generic/BitOperations$Int;I)Lscala/collection/immutable/IndexedSeq;
  #68 = NameAndType        #66:#67        // bits$:(Lscala/collection/generic/BitOperations$Int;I)Lscala/collection/immutable/IndexedSeq;
  #69 = InterfaceMethodref #6.#68         // scala/collection/generic/BitOperations$Int.bits$:(Lscala/collection/generic/BitOperations$Int;I)Lscala/collection/immutable/IndexedSeq;
  #70 = Utf8               bitString
  #71 = Utf8               (ILjava/lang/String;)Ljava/lang/String;
  #72 = Utf8               sep
  #73 = Utf8               bitString$
  #74 = Utf8               (Lscala/collection/generic/BitOperations$Int;ILjava/lang/String;)Ljava/lang/String;
  #75 = NameAndType        #73:#74        // bitString$:(Lscala/collection/generic/BitOperations$Int;ILjava/lang/String;)Ljava/lang/String;
  #76 = InterfaceMethodref #6.#75         // scala/collection/generic/BitOperations$Int.bitString$:(Lscala/collection/generic/BitOperations$Int;ILjava/lang/String;)Ljava/lang/String;
  #77 = Utf8               Ljava/lang/String;
  #78 = Utf8               bitString$default$2
  #79 = Utf8               ()Ljava/lang/String;
  #80 = Utf8               bitString$default$2$
  #81 = Utf8               (Lscala/collection/generic/BitOperations$Int;)Ljava/lang/String;
  #82 = NameAndType        #80:#81        // bitString$default$2$:(Lscala/collection/generic/BitOperations$Int;)Ljava/lang/String;
  #83 = InterfaceMethodref #6.#82         // scala/collection/generic/BitOperations$Int.bitString$default$2$:(Lscala/collection/generic/BitOperations$Int;)Ljava/lang/String;
  #84 = Utf8               highestOneBit
  #85 = Utf8               highestOneBit$
  #86 = NameAndType        #85:#59        // highestOneBit$:(Lscala/collection/generic/BitOperations$Int;I)I
  #87 = InterfaceMethodref #6.#86         // scala/collection/generic/BitOperations$Int.highestOneBit$:(Lscala/collection/generic/BitOperations$Int;I)I
  #88 = Methodref          #4.#17         // java/lang/Object."<init>":()V
  #89 = Utf8               Code
  #90 = Utf8               LineNumberTable
  #91 = Utf8               LocalVariableTable
  #92 = Utf8               MethodParameters
  #93 = Utf8               Signature
  #94 = Utf8               InnerClasses
  #95 = Utf8               SourceFile
  #96 = Utf8               ScalaInlineInfo
  #97 = Utf8               Scala
{
  public static final scala.collection.generic.BitOperations$Int$ MODULE$;
    descriptor: Lscala/collection/generic/BitOperations$Int$;
    flags: (0x0019) ACC_PUBLIC, ACC_STATIC, ACC_FINAL

  public static {};
    descriptor: ()V
    flags: (0x0009) ACC_PUBLIC, ACC_STATIC
    Code:
      stack=2, locals=0, args_size=0
         0: new           #2                  // class scala/collection/generic/BitOperations$Int$
         3: dup
         4: invokespecial #18                 // Method "<init>":()V
         7: putstatic     #20                 // Field MODULE$:Lscala/collection/generic/BitOperations$Int$;
        10: getstatic     #20                 // Field MODULE$:Lscala/collection/generic/BitOperations$Int$;
        13: pop
        14: return
      LineNumberTable:
        line 35: 0
        line 35: 14

  public boolean zero(int, int);
    descriptor: (II)Z
    flags: (0x0001) ACC_PUBLIC
    Code:
      stack=3, locals=3, args_size=3
         0: aload_0
         1: iload_1
         2: iload_2
         3: invokestatic  #28                 // InterfaceMethod scala/collection/generic/BitOperations$Int.zero$:(Lscala/collection/generic/BitOperations$Int;II)Z
         6: ireturn
      LineNumberTable:
        line 35: 0
      LocalVariableTable:
        Start  Length  Slot  Name   Signature
            0       7     0  this   Lscala/collection/generic/BitOperations$Int$;
            0       7     1     i   I
            0       7     2  mask   I
    MethodParameters:
      Name                           Flags
      i                              final
      mask                           final

  public int mask(int, int);
    descriptor: (II)I
    flags: (0x0001) ACC_PUBLIC
    Code:
      stack=3, locals=3, args_size=3
         0: aload_0
         1: iload_1
         2: iload_2
         3: invokestatic  #35                 // InterfaceMethod scala/collection/generic/BitOperations$Int.mask$:(Lscala/collection/generic/BitOperations$Int;II)I
         6: ireturn
      LineNumberTable:
        line 35: 0
      LocalVariableTable:
        Start  Length  Slot  Name   Signature
            0       7     0  this   Lscala/collection/generic/BitOperations$Int$;
            0       7     1     i   I
            0       7     2  mask   I
    MethodParameters:
      Name                           Flags
      i                              final
      mask                           final

  public boolean hasMatch(int, int, int);
    descriptor: (III)Z
    flags: (0x0001) ACC_PUBLIC
    Code:
      stack=4, locals=4, args_size=4
         0: aload_0
         1: iload_1
         2: iload_2
         3: iload_3
         4: invokestatic  #44                 // InterfaceMethod scala/collection/generic/BitOperations$Int.hasMatch$:(Lscala/collection/generic/BitOperations$Int;III)Z
         7: ireturn
      LineNumberTable:
        line 35: 0
      LocalVariableTable:
        Start  Length  Slot  Name   Signature
            0       8     0  this   Lscala/collection/generic/BitOperations$Int$;
            0       8     1   key   I
            0       8     2 prefix   I
            0       8     3     m   I
    MethodParameters:
      Name                           Flags
      key                            final
      prefix                         final
      m                              final

  public boolean unsignedCompare(int, int);
    descriptor: (II)Z
    flags: (0x0001) ACC_PUBLIC
    Code:
      stack=3, locals=3, args_size=3
         0: aload_0
         1: iload_1
         2: iload_2
         3: invokestatic  #49                 // InterfaceMethod scala/collection/generic/BitOperations$Int.unsignedCompare$:(Lscala/collection/generic/BitOperations$Int;II)Z
         6: ireturn
      LineNumberTable:
        line 35: 0
      LocalVariableTable:
        Start  Length  Slot  Name   Signature
            0       7     0  this   Lscala/collection/generic/BitOperations$Int$;
            0       7     1     i   I
            0       7     2     j   I
    MethodParameters:
      Name                           Flags
      i                              final
      j                              final

  public boolean shorter(int, int);
    descriptor: (II)Z
    flags: (0x0001) ACC_PUBLIC
    Code:
      stack=3, locals=3, args_size=3
         0: aload_0
         1: iload_1
         2: iload_2
         3: invokestatic  #55                 // InterfaceMethod scala/collection/generic/BitOperations$Int.shorter$:(Lscala/collection/generic/BitOperations$Int;II)Z
         6: ireturn
      LineNumberTable:
        line 35: 0
      LocalVariableTable:
        Start  Length  Slot  Name   Signature
            0       7     0  this   Lscala/collection/generic/BitOperations$Int$;
            0       7     1    m1   I
            0       7     2    m2   I
    MethodParameters:
      Name                           Flags
      m1                             final
      m2                             final

  public int complement(int);
    descriptor: (I)I
    flags: (0x0001) ACC_PUBLIC
    Code:
      stack=2, locals=2, args_size=2
         0: aload_0
         1: iload_1
         2: invokestatic  #61                 // InterfaceMethod scala/collection/generic/BitOperations$Int.complement$:(Lscala/collection/generic/BitOperations$Int;I)I
         5: ireturn
      LineNumberTable:
        line 35: 0
      LocalVariableTable:
        Start  Length  Slot  Name   Signature
            0       6     0  this   Lscala/collection/generic/BitOperations$Int$;
            0       6     1     i   I
    MethodParameters:
      Name                           Flags
      i                              final

  public scala.collection.immutable.IndexedSeq<java.lang.Object> bits(int);
    descriptor: (I)Lscala/collection/immutable/IndexedSeq;
    flags: (0x0001) ACC_PUBLIC
    Code:
      stack=2, locals=2, args_size=2
         0: aload_0
         1: iload_1
         2: invokestatic  #69                 // InterfaceMethod scala/collection/generic/BitOperations$Int.bits$:(Lscala/collection/generic/BitOperations$Int;I)Lscala/collection/immutable/IndexedSeq;
         5: areturn
      LineNumberTable:
        line 35: 0
      LocalVariableTable:
        Start  Length  Slot  Name   Signature
            0       6     0  this   Lscala/collection/generic/BitOperations$Int$;
            0       6     1   num   I
    Signature: #64                          // (I)Lscala/collection/immutable/IndexedSeq<Ljava/lang/Object;>;
    MethodParameters:
      Name                           Flags
      num                            final

  public java.lang.String bitString(int, java.lang.String);
    descriptor: (ILjava/lang/String;)Ljava/lang/String;
    flags: (0x0001) ACC_PUBLIC
    Code:
      stack=3, locals=3, args_size=3
         0: aload_0
         1: iload_1
         2: aload_2
         3: invokestatic  #76                 // InterfaceMethod scala/collection/generic/BitOperations$Int.bitString$:(Lscala/collection/generic/BitOperations$Int;ILjava/lang/String;)Ljava/lang/String;
         6: areturn
      LineNumberTable:
        line 35: 0
      LocalVariableTable:
        Start  Length  Slot  Name   Signature
            0       7     0  this   Lscala/collection/generic/BitOperations$Int$;
            0       7     1   num   I
            0       7     2   sep   Ljava/lang/String;
    MethodParameters:
      Name                           Flags
      num                            final
      sep                            final

  public java.lang.String bitString$default$2();
    descriptor: ()Ljava/lang/String;
    flags: (0x0001) ACC_PUBLIC
    Code:
      stack=1, locals=1, args_size=1
         0: aload_0
         1: invokestatic  #83                 // InterfaceMethod scala/collection/generic/BitOperations$Int.bitString$default$2$:(Lscala/collection/generic/BitOperations$Int;)Ljava/lang/String;
         4: areturn
      LineNumberTable:
        line 35: 0
      LocalVariableTable:
        Start  Length  Slot  Name   Signature
            0       5     0  this   Lscala/collection/generic/BitOperations$Int$;

  public int highestOneBit(int);
    descriptor: (I)I
    flags: (0x0001) ACC_PUBLIC
    Code:
      stack=2, locals=2, args_size=2
         0: aload_0
         1: iload_1
         2: invokestatic  #87                 // InterfaceMethod scala/collection/generic/BitOperations$Int.highestOneBit$:(Lscala/collection/generic/BitOperations$Int;I)I
         5: ireturn
      LineNumberTable:
        line 35: 0
      LocalVariableTable:
        Start  Length  Slot  Name   Signature
            0       6     0  this   Lscala/collection/generic/BitOperations$Int$;
            0       6     1     j   I
    MethodParameters:
      Name                           Flags
      j                              final

  public scala.collection.generic.BitOperations$Int$();
    descriptor: ()V
    flags: (0x0001) ACC_PUBLIC
    Code:
      stack=1, locals=1, args_size=1
         0: aload_0
         1: invokespecial #88                 // Method java/lang/Object."<init>":()V
         4: return
      LineNumberTable:
        line 35: 0
      LocalVariableTable:
        Start  Length  Slot  Name   Signature
            0       5     0  this   Lscala/collection/generic/BitOperations$Int$;
}
InnerClasses:
  public static #10= #6 of #9;            // Int=class scala/collection/generic/BitOperations$Int of class scala/collection/generic/BitOperations
  public static #11= #2 of #9;            // Int$=class scala/collection/generic/BitOperations$Int$ of class scala/collection/generic/BitOperations
SourceFile: "BitOperations.scala"
  ScalaInlineInfo: length = 0x3B (unknown attribute)
   01 01 00 0B 00 10 00 0F 01 00 46 00 47 01 00 4E
   00 4F 01 00 3E 00 3F 01 00 38 00 39 01 00 24 00
   25 01 00 54 00 39 01 00 18 00 1F 01 00 32 00 16
   01 00 2D 00 16 01 00 15 00 16 01
  Scala: length = 0x0 (unknown attribute)

