Classfile /Users/mw/Projects/slang-braindump/.jar/jar8/assemble/slang-braindump/assemble/content/scala/collection/generic/DefaultSerializationProxy.class
  Last modified May 29, 2022; size 5997 bytes
  SHA-256 checksum f5c203b07c9bf93e0287d2c6817f763b46538b116796a2efb0017790e3a0acbf
  Compiled from "DefaultSerializationProxy.scala"
public final class scala.collection.generic.DefaultSerializationProxy<A extends java.lang.Object> extends java.lang.Object implements java.io.Serializable
  minor version: 0
  major version: 52
  flags: (0x0031) ACC_PUBLIC, ACC_FINAL, ACC_SUPER
  this_class: #2                          // scala/collection/generic/DefaultSerializationProxy
  super_class: #5                         // java/lang/Object
  interfaces: 1, fields: 4, methods: 9, attributes: 7
Constant pool:
    #1 = Utf8               scala/collection/generic/DefaultSerializationProxy
    #2 = Class              #1            // scala/collection/generic/DefaultSerializationProxy
    #3 = Utf8               <A:Ljava/lang/Object;>Ljava/lang/Object;Ljava/io/Serializable;
    #4 = Utf8               java/lang/Object
    #5 = Class              #4            // java/lang/Object
    #6 = Utf8               java/io/Serializable
    #7 = Class              #6            // java/io/Serializable
    #8 = Utf8               DefaultSerializationProxy.scala
    #9 = Utf8               Lscala/reflect/ScalaSignature;
   #10 = Utf8               bytes
   #11 = Utf8               \u0006\u000594AAC\u0006\u0003%!AA\u0005\u0001B\u0001B\u0003%Q\u0005\u0003\u00055\u0001\t\u0005\t\u0015!\u00036\u0011\u0015a\u0004\u0001\"\u0001>\u0011%\u0011\u0005\u00011AA\u0002\u0013E1\tC\u0005K\u0001\u0001\u0007\t\u0019!C\t\u0017\"I\u0011\u000b\u0001a\u0001\u0002\u0003\u0006K\u0001\u0012\u0005\u0007\'\u0002\u0001K\u0011\u0002+\t\r}\u0003\u0001\u0015\"\u0003a\u0011\u00191\u0007\u0001)C\tO\nIB)\u001a4bk2$8+\u001a:jC2L\'0\u0019;j_:\u0004&o\u001c=z\u0015\taQ\"A\u0004hK:,\'/[2\u000b\u00059y\u0011AC2pY2,7\r^5p]*\t\u0001#A\u0003tG\u0006d\u0017m\u0001\u0001\u0016\u0005MY3c\u0001\u0001\u00151A\u0011QCF\u0007\u0002\u001f%\u0011qc\u0004\u0002\u0007\u0003:L(+\u001a4\u0011\u0005e\tcB\u0001\u000e \u001d\tYb$D\u0001\u001d\u0015\ti\u0012#\u0001\u0004=e>|GOP\u0005\u0002!%\u0011\u0001eD\u0001\ba\u0006\u001c7.Y4f\u0013\t\u00113E\u0001\u0007TKJL\u0017\r\\5{C\ndWM\u0003\u0002!\u001f\u00059a-Y2u_JL\b\u0003\u0002\u0014(SEj\u0011!D\u0005\u0003Q5\u0011qAR1di>\u0014\u0018\u0010\u0005\u0002+W1\u0001A!\u0002\u0017\u0001\u0005\u0004i#!A!\u0012\u00059\n\u0004CA\u000b0\u0013\t\u0001tBA\u0004O_RD\u0017N\\4\u0011\u0005U\u0011\u0014BA\u001a\u0010\u0005\r\te._\u0001\u0005G>dG\u000eE\u0002\'m%J!aN\u0007\u0003\u0011%#XM]1cY\u0016D#AA\u001d\u0011\u0005UQ\u0014BA\u001e\u0010\u0005%!(/\u00198tS\u0016tG/\u0001\u0004=S:LGO\u0010\u000b\u0004}\u0001\u000b\u0005cA \u0001S5\t1\u0002C\u0003%\u0007\u0001\u0007Q\u0005C\u00035\u0007\u0001\u0007Q\'A\u0004ck&dG-\u001a:\u0016\u0003\u0011\u0003B!\u0012%*c5\taI\u0003\u0002H\u001b\u00059Q.\u001e;bE2,\u0017BA%G\u0005\u001d\u0011U/\u001b7eKJ\f1BY;jY\u0012,\'o\u0018\u0013fcR\u0011Aj\u0014\t\u0003+5K!AT\b\u0003\tUs\u0017\u000e\u001e\u0005\b!\u0016\t\t\u00111\u0001E\u0003\rAH%M\u0001\tEVLG\u000eZ3sA!\u0012a!O\u0001\foJLG/Z(cU\u0016\u001cG\u000f\u0006\u0002M+\")ak\u0002a\u0001/\u0006\u0019q.\u001e;\u0011\u0005akV\"A-\u000b\u0005i[\u0016AA5p\u0015\u0005a\u0016\u0001\u00026bm\u0006L!AX-\u0003%=\u0013\'.Z2u\u001fV$\b/\u001e;TiJ,\u0017-\\\u0001\u000be\u0016\fGm\u00142kK\u000e$HC\u0001\'b\u0011\u0015\u0011\u0007\u00021\u0001d\u0003\tIg\u000e\u0005\u0002YI&\u0011Q-\u0017\u0002\u0012\u001f\nTWm\u0019;J]B,Ho\u0015;sK\u0006l\u0017a\u0003:fC\u0012\u0014Vm]8mm\u0016$\u0012!\r\u0015\u0005\u0001%dW\u000e\u0005\u0002\u0016U&\u00111n\u0004\u0002\u0011\'\u0016\u0014\u0018.\u00197WKJ\u001c\u0018n\u001c8V\u0013\u0012\u000bQA^1mk\u0016t\u0012a\u0001
   #12 = Utf8               java/lang/invoke/MethodHandles$Lookup
   #13 = Class              #12           // java/lang/invoke/MethodHandles$Lookup
   #14 = Utf8               java/lang/invoke/MethodHandles
   #15 = Class              #14           // java/lang/invoke/MethodHandles
   #16 = Utf8               Lookup
   #17 = Utf8               serialVersionUID
   #18 = Utf8               J
   #19 = Long               3l
   #21 = Utf8               factory
   #22 = Utf8               Lscala/collection/Factory;
   #23 = Utf8               Lscala/collection/Factory<TA;Ljava/lang/Object;>;
   #24 = Utf8               coll
   #25 = Utf8               Lscala/collection/Iterable;
   #26 = Utf8               Lscala/collection/Iterable<TA;>;
   #27 = Utf8               builder
   #28 = Utf8               Lscala/collection/mutable/Builder;
   #29 = Utf8               Lscala/collection/mutable/Builder<TA;Ljava/lang/Object;>;
   #30 = Utf8               ()Lscala/collection/mutable/Builder;
   #31 = Utf8               ()Lscala/collection/mutable/Builder<TA;Ljava/lang/Object;>;
   #32 = NameAndType        #27:#28       // builder:Lscala/collection/mutable/Builder;
   #33 = Fieldref           #2.#32        // scala/collection/generic/DefaultSerializationProxy.builder:Lscala/collection/mutable/Builder;
   #34 = Utf8               this
   #35 = Utf8               Lscala/collection/generic/DefaultSerializationProxy;
   #36 = Utf8               builder_$eq
   #37 = Utf8               (Lscala/collection/mutable/Builder;)V
   #38 = Utf8               (Lscala/collection/mutable/Builder<TA;Ljava/lang/Object;>;)V
   #39 = Utf8               x$1
   #40 = Utf8               writeObject
   #41 = Utf8               (Ljava/io/ObjectOutputStream;)V
   #42 = Utf8               out
   #43 = Utf8               java/io/ObjectOutputStream
   #44 = Class              #43           // java/io/ObjectOutputStream
   #45 = Utf8               defaultWriteObject
   #46 = Utf8               ()V
   #47 = NameAndType        #45:#46       // defaultWriteObject:()V
   #48 = Methodref          #44.#47       // java/io/ObjectOutputStream.defaultWriteObject:()V
   #49 = NameAndType        #24:#25       // coll:Lscala/collection/Iterable;
   #50 = Fieldref           #2.#49        // scala/collection/generic/DefaultSerializationProxy.coll:Lscala/collection/Iterable;
   #51 = Utf8               scala/collection/Iterable
   #52 = Class              #51           // scala/collection/Iterable
   #53 = Utf8               knownSize
   #54 = Utf8               ()I
   #55 = NameAndType        #53:#54       // knownSize:()I
   #56 = InterfaceMethodref #52.#55       // scala/collection/Iterable.knownSize:()I
   #57 = Utf8               writeInt
   #58 = Utf8               (I)V
   #59 = NameAndType        #57:#58       // writeInt:(I)V
   #60 = Methodref          #44.#59       // java/io/ObjectOutputStream.writeInt:(I)V
   #61 = Utf8               scala/runtime/IntRef
   #62 = Class              #61           // scala/runtime/IntRef
   #63 = Utf8               <init>
   #64 = NameAndType        #63:#58       // "<init>":(I)V
   #65 = Methodref          #62.#64       // scala/runtime/IntRef."<init>":(I)V
   #66 = Utf8               (Ljava/lang/Object;)Ljava/lang/Object;
   #67 = MethodType         #66           //  (Ljava/lang/Object;)Ljava/lang/Object;
   #68 = Utf8               $anonfun$writeObject$1$adapted
   #69 = Utf8               (Ljava/io/ObjectOutputStream;Lscala/runtime/IntRef;Ljava/lang/Object;)Ljava/lang/Object;
   #70 = NameAndType        #68:#69       // $anonfun$writeObject$1$adapted:(Ljava/io/ObjectOutputStream;Lscala/runtime/IntRef;Ljava/lang/Object;)Ljava/lang/Object;
   #71 = Methodref          #2.#70        // scala/collection/generic/DefaultSerializationProxy.$anonfun$writeObject$1$adapted:(Ljava/io/ObjectOutputStream;Lscala/runtime/IntRef;Ljava/lang/Object;)Ljava/lang/Object;
   #72 = MethodHandle       6:#71         // REF_invokeStatic scala/collection/generic/DefaultSerializationProxy.$anonfun$writeObject$1$adapted:(Ljava/io/ObjectOutputStream;Lscala/runtime/IntRef;Ljava/lang/Object;)Ljava/lang/Object;
   #73 = Integer            1
   #74 = Utf8               java/lang/invoke/LambdaMetafactory
   #75 = Class              #74           // java/lang/invoke/LambdaMetafactory
   #76 = Utf8               altMetafactory
   #77 = Utf8               (Ljava/lang/invoke/MethodHandles$Lookup;Ljava/lang/String;Ljava/lang/invoke/MethodType;[Ljava/lang/Object;)Ljava/lang/invoke/CallSite;
   #78 = NameAndType        #76:#77       // altMetafactory:(Ljava/lang/invoke/MethodHandles$Lookup;Ljava/lang/String;Ljava/lang/invoke/MethodType;[Ljava/lang/Object;)Ljava/lang/invoke/CallSite;
   #79 = Methodref          #75.#78       // java/lang/invoke/LambdaMetafactory.altMetafactory:(Ljava/lang/invoke/MethodHandles$Lookup;Ljava/lang/String;Ljava/lang/invoke/MethodType;[Ljava/lang/Object;)Ljava/lang/invoke/CallSite;
   #80 = MethodHandle       6:#79         // REF_invokeStatic java/lang/invoke/LambdaMetafactory.altMetafactory:(Ljava/lang/invoke/MethodHandles$Lookup;Ljava/lang/String;Ljava/lang/invoke/MethodType;[Ljava/lang/Object;)Ljava/lang/invoke/CallSite;
   #81 = Utf8               apply
   #82 = Utf8               (Ljava/io/ObjectOutputStream;Lscala/runtime/IntRef;)Lscala/Function1;
   #83 = NameAndType        #81:#82       // apply:(Ljava/io/ObjectOutputStream;Lscala/runtime/IntRef;)Lscala/Function1;
   #84 = InvokeDynamic      #0:#83        // #0:apply:(Ljava/io/ObjectOutputStream;Lscala/runtime/IntRef;)Lscala/Function1;
   #85 = Utf8               foreach
   #86 = Utf8               (Lscala/Function1;)V
   #87 = NameAndType        #85:#86       // foreach:(Lscala/Function1;)V
   #88 = InterfaceMethodref #52.#87       // scala/collection/Iterable.foreach:(Lscala/Function1;)V
   #89 = Utf8               elem
   #90 = Utf8               I
   #91 = NameAndType        #89:#90       // elem:I
   #92 = Fieldref           #62.#91       // scala/runtime/IntRef.elem:I
   #93 = Utf8               java/lang/IllegalStateException
   #94 = Class              #93           // java/lang/IllegalStateException
   #95 = Utf8               java/lang/StringBuilder
   #96 = Class              #95           // java/lang/StringBuilder
   #97 = Integer            38
   #98 = Methodref          #96.#64       // java/lang/StringBuilder."<init>":(I)V
   #99 = Utf8               Illegal size
  #100 = String             #99           // Illegal size
  #101 = Utf8               append
  #102 = Utf8               (Ljava/lang/String;)Ljava/lang/StringBuilder;
  #103 = NameAndType        #101:#102     // append:(Ljava/lang/String;)Ljava/lang/StringBuilder;
  #104 = Methodref          #96.#103      // java/lang/StringBuilder.append:(Ljava/lang/String;)Ljava/lang/StringBuilder;
  #105 = Utf8               (I)Ljava/lang/StringBuilder;
  #106 = NameAndType        #101:#105     // append:(I)Ljava/lang/StringBuilder;
  #107 = Methodref          #96.#106      // java/lang/StringBuilder.append:(I)Ljava/lang/StringBuilder;
  #108 = Utf8                of collection, expected
  #109 = String             #108          //  of collection, expected
  #110 = Utf8               toString
  #111 = Utf8               ()Ljava/lang/String;
  #112 = NameAndType        #110:#111     // toString:()Ljava/lang/String;
  #113 = Methodref          #96.#112      // java/lang/StringBuilder.toString:()Ljava/lang/String;
  #114 = Utf8               (Ljava/lang/String;)V
  #115 = NameAndType        #63:#114      // "<init>":(Ljava/lang/String;)V
  #116 = Methodref          #94.#115      // java/lang/IllegalStateException."<init>":(Ljava/lang/String;)V
  #117 = Utf8               scala/collection/generic/SerializeEnd$
  #118 = Class              #117          // scala/collection/generic/SerializeEnd$
  #119 = Utf8               MODULE$
  #120 = Utf8               Lscala/collection/generic/SerializeEnd$;
  #121 = NameAndType        #119:#120     // MODULE$:Lscala/collection/generic/SerializeEnd$;
  #122 = Fieldref           #118.#121     // scala/collection/generic/SerializeEnd$.MODULE$:Lscala/collection/generic/SerializeEnd$;
  #123 = Utf8               (Ljava/lang/Object;)V
  #124 = NameAndType        #40:#123      // writeObject:(Ljava/lang/Object;)V
  #125 = Methodref          #44.#124      // java/io/ObjectOutputStream.writeObject:(Ljava/lang/Object;)V
  #126 = Utf8               k
  #127 = Utf8               count
  #128 = Utf8               Lscala/runtime/IntRef;
  #129 = Utf8               Ljava/io/ObjectOutputStream;
  #130 = Utf8               create_e
  #131 = Utf8               readObject
  #132 = Utf8               (Ljava/io/ObjectInputStream;)V
  #133 = Utf8               in
  #134 = Utf8               java/io/ObjectInputStream
  #135 = Class              #134          // java/io/ObjectInputStream
  #136 = Utf8               defaultReadObject
  #137 = NameAndType        #136:#46      // defaultReadObject:()V
  #138 = Methodref          #135.#137     // java/io/ObjectInputStream.defaultReadObject:()V
  #139 = NameAndType        #21:#22       // factory:Lscala/collection/Factory;
  #140 = Fieldref           #2.#139       // scala/collection/generic/DefaultSerializationProxy.factory:Lscala/collection/Factory;
  #141 = Utf8               scala/collection/Factory
  #142 = Class              #141          // scala/collection/Factory
  #143 = Utf8               newBuilder
  #144 = NameAndType        #143:#30      // newBuilder:()Lscala/collection/mutable/Builder;
  #145 = InterfaceMethodref #142.#144     // scala/collection/Factory.newBuilder:()Lscala/collection/mutable/Builder;
  #146 = NameAndType        #36:#37       // builder_$eq:(Lscala/collection/mutable/Builder;)V
  #147 = Methodref          #2.#146       // scala/collection/generic/DefaultSerializationProxy.builder_$eq:(Lscala/collection/mutable/Builder;)V
  #148 = Utf8               readInt
  #149 = NameAndType        #148:#54      // readInt:()I
  #150 = Methodref          #135.#149     // java/io/ObjectInputStream.readInt:()I
  #151 = NameAndType        #27:#30       // builder:()Lscala/collection/mutable/Builder;
  #152 = Methodref          #2.#151       // scala/collection/generic/DefaultSerializationProxy.builder:()Lscala/collection/mutable/Builder;
  #153 = Utf8               scala/collection/mutable/Builder
  #154 = Class              #153          // scala/collection/mutable/Builder
  #155 = Utf8               sizeHint
  #156 = NameAndType        #155:#58      // sizeHint:(I)V
  #157 = InterfaceMethodref #154.#156     // scala/collection/mutable/Builder.sizeHint:(I)V
  #158 = Utf8               ()Ljava/lang/Object;
  #159 = NameAndType        #131:#158     // readObject:()Ljava/lang/Object;
  #160 = Methodref          #135.#159     // java/io/ObjectInputStream.readObject:()Ljava/lang/Object;
  #161 = Utf8               scala/collection/mutable/Growable
  #162 = Class              #161          // scala/collection/mutable/Growable
  #163 = Utf8               addOne
  #164 = Utf8               (Ljava/lang/Object;)Lscala/collection/mutable/Growable;
  #165 = NameAndType        #163:#164     // addOne:(Ljava/lang/Object;)Lscala/collection/mutable/Growable;
  #166 = InterfaceMethodref #162.#165     // scala/collection/mutable/Growable.addOne:(Ljava/lang/Object;)Lscala/collection/mutable/Growable;
  #167 = Utf8               equals
  #168 = Utf8               (Ljava/lang/Object;)Z
  #169 = NameAndType        #167:#168     // equals:(Ljava/lang/Object;)Z
  #170 = Methodref          #5.#169       // java/lang/Object.equals:(Ljava/lang/Object;)Z
  #171 = Utf8               Ljava/io/ObjectInputStream;
  #172 = Utf8               $plus$eq_elem
  #173 = Utf8               Ljava/lang/Object;
  #174 = Utf8               readResolve
  #175 = Utf8               result
  #176 = NameAndType        #175:#158     // result:()Ljava/lang/Object;
  #177 = InterfaceMethodref #154.#176     // scala/collection/mutable/Builder.result:()Ljava/lang/Object;
  #178 = Utf8               $anonfun$writeObject$1
  #179 = Utf8               (Ljava/io/ObjectOutputStream;Lscala/runtime/IntRef;Ljava/lang/Object;)V
  #180 = Utf8               out$1
  #181 = Utf8               count$1
  #182 = Utf8               x
  #183 = Utf8               (Lscala/collection/Factory;Lscala/collection/Iterable;)V
  #184 = Utf8               (Lscala/collection/Factory<TA;Ljava/lang/Object;>;Lscala/collection/Iterable<TA;>;)V
  #185 = NameAndType        #63:#46       // "<init>":()V
  #186 = Methodref          #5.#185       // java/lang/Object."<init>":()V
  #187 = NameAndType        #178:#179     // $anonfun$writeObject$1:(Ljava/io/ObjectOutputStream;Lscala/runtime/IntRef;Ljava/lang/Object;)V
  #188 = Methodref          #2.#187       // scala/collection/generic/DefaultSerializationProxy.$anonfun$writeObject$1:(Ljava/io/ObjectOutputStream;Lscala/runtime/IntRef;Ljava/lang/Object;)V
  #189 = Utf8               scala/runtime/BoxedUnit
  #190 = Class              #189          // scala/runtime/BoxedUnit
  #191 = Utf8               UNIT
  #192 = Utf8               Lscala/runtime/BoxedUnit;
  #193 = NameAndType        #191:#192     // UNIT:Lscala/runtime/BoxedUnit;
  #194 = Fieldref           #190.#193     // scala/runtime/BoxedUnit.UNIT:Lscala/runtime/BoxedUnit;
  #195 = Utf8               $deserializeLambda$
  #196 = Utf8               (Ljava/lang/invoke/SerializedLambda;)Ljava/lang/Object;
  #197 = Utf8               scala/runtime/LambdaDeserialize
  #198 = Class              #197          // scala/runtime/LambdaDeserialize
  #199 = Utf8               bootstrap
  #200 = Utf8               (Ljava/lang/invoke/MethodHandles$Lookup;Ljava/lang/String;Ljava/lang/invoke/MethodType;[Ljava/lang/invoke/MethodHandle;)Ljava/lang/invoke/CallSite;
  #201 = NameAndType        #199:#200     // bootstrap:(Ljava/lang/invoke/MethodHandles$Lookup;Ljava/lang/String;Ljava/lang/invoke/MethodType;[Ljava/lang/invoke/MethodHandle;)Ljava/lang/invoke/CallSite;
  #202 = Methodref          #198.#201     // scala/runtime/LambdaDeserialize.bootstrap:(Ljava/lang/invoke/MethodHandles$Lookup;Ljava/lang/String;Ljava/lang/invoke/MethodType;[Ljava/lang/invoke/MethodHandle;)Ljava/lang/invoke/CallSite;
  #203 = MethodHandle       6:#202        // REF_invokeStatic scala/runtime/LambdaDeserialize.bootstrap:(Ljava/lang/invoke/MethodHandles$Lookup;Ljava/lang/String;Ljava/lang/invoke/MethodType;[Ljava/lang/invoke/MethodHandle;)Ljava/lang/invoke/CallSite;
  #204 = Utf8               lambdaDeserialize
  #205 = NameAndType        #204:#196     // lambdaDeserialize:(Ljava/lang/invoke/SerializedLambda;)Ljava/lang/Object;
  #206 = InvokeDynamic      #1:#205       // #1:lambdaDeserialize:(Ljava/lang/invoke/SerializedLambda;)Ljava/lang/Object;
  #207 = Utf8               ConstantValue
  #208 = Utf8               Signature
  #209 = Utf8               Code
  #210 = Utf8               LineNumberTable
  #211 = Utf8               LocalVariableTable
  #212 = Utf8               MethodParameters
  #213 = Utf8               StackMapTable
  #214 = Utf8               InnerClasses
  #215 = Utf8               SourceFile
  #216 = Utf8               RuntimeVisibleAnnotations
  #217 = Utf8               BootstrapMethods
  #218 = Utf8               ScalaInlineInfo
  #219 = Utf8               ScalaSig
{
  private static final long serialVersionUID;
    descriptor: J
    flags: (0x001a) ACC_PRIVATE, ACC_STATIC, ACC_FINAL
    ConstantValue: long 3l

  private final scala.collection.Factory<A, java.lang.Object> factory;
    descriptor: Lscala/collection/Factory;
    flags: (0x0012) ACC_PRIVATE, ACC_FINAL
    Signature: #23                          // Lscala/collection/Factory<TA;Ljava/lang/Object;>;

  private final transient scala.collection.Iterable<A> coll;
    descriptor: Lscala/collection/Iterable;
    flags: (0x0092) ACC_PRIVATE, ACC_FINAL, ACC_TRANSIENT
    Signature: #26                          // Lscala/collection/Iterable<TA;>;

  private transient scala.collection.mutable.Builder<A, java.lang.Object> builder;
    descriptor: Lscala/collection/mutable/Builder;
    flags: (0x0082) ACC_PRIVATE, ACC_TRANSIENT
    Signature: #29                          // Lscala/collection/mutable/Builder<TA;Ljava/lang/Object;>;

  public scala.collection.mutable.Builder<A, java.lang.Object> builder();
    descriptor: ()Lscala/collection/mutable/Builder;
    flags: (0x0001) ACC_PUBLIC
    Code:
      stack=1, locals=1, args_size=1
         0: aload_0
         1: getfield      #33                 // Field builder:Lscala/collection/mutable/Builder;
         4: areturn
      LineNumberTable:
        line 30: 0
      LocalVariableTable:
        Start  Length  Slot  Name   Signature
            0       5     0  this   Lscala/collection/generic/DefaultSerializationProxy;
    Signature: #31                          // ()Lscala/collection/mutable/Builder<TA;Ljava/lang/Object;>;

  public void builder_$eq(scala.collection.mutable.Builder<A, java.lang.Object>);
    descriptor: (Lscala/collection/mutable/Builder;)V
    flags: (0x0001) ACC_PUBLIC
    Code:
      stack=2, locals=2, args_size=2
         0: aload_0
         1: aload_1
         2: putfield      #33                 // Field builder:Lscala/collection/mutable/Builder;
         5: return
      LineNumberTable:
        line 30: 0
      LocalVariableTable:
        Start  Length  Slot  Name   Signature
            0       6     0  this   Lscala/collection/generic/DefaultSerializationProxy;
            0       6     1   x$1   Lscala/collection/mutable/Builder;
    Signature: #38                          // (Lscala/collection/mutable/Builder<TA;Ljava/lang/Object;>;)V
    MethodParameters:
      Name                           Flags
      x$1                            final

  private void writeObject(java.io.ObjectOutputStream);
    descriptor: (Ljava/io/ObjectOutputStream;)V
    flags: (0x0002) ACC_PRIVATE
    Code:
      stack=5, locals=6, args_size=2
         0: aload_1
         1: invokevirtual #48                 // Method java/io/ObjectOutputStream.defaultWriteObject:()V
         4: aload_0
         5: getfield      #50                 // Field coll:Lscala/collection/Iterable;
         8: invokeinterface #56,  1           // InterfaceMethod scala/collection/Iterable.knownSize:()I
        13: istore_2
        14: aload_1
        15: iload_2
        16: invokevirtual #60                 // Method java/io/ObjectOutputStream.writeInt:(I)V
        19: iconst_0
        20: istore        4
        22: new           #62                 // class scala/runtime/IntRef
        25: dup
        26: iload         4
        28: invokespecial #65                 // Method scala/runtime/IntRef."<init>":(I)V
        31: astore        5
        33: aload         5
        35: aconst_null
        36: astore        5
        38: astore_3
        39: aload_0
        40: getfield      #50                 // Field coll:Lscala/collection/Iterable;
        43: aload_1
        44: aload_3
        45: invokedynamic #84,  0             // InvokeDynamic #0:apply:(Ljava/io/ObjectOutputStream;Lscala/runtime/IntRef;)Lscala/Function1;
        50: invokeinterface #88,  2           // InterfaceMethod scala/collection/Iterable.foreach:(Lscala/Function1;)V
        55: iload_2
        56: iconst_0
        57: if_icmplt     109
        60: aload_3
        61: getfield      #92                 // Field scala/runtime/IntRef.elem:I
        64: iload_2
        65: if_icmpeq     116
        68: new           #94                 // class java/lang/IllegalStateException
        71: dup
        72: new           #96                 // class java/lang/StringBuilder
        75: dup
        76: ldc           #97                 // int 38
        78: invokespecial #98                 // Method java/lang/StringBuilder."<init>":(I)V
        81: ldc           #100                // String Illegal size
        83: invokevirtual #104                // Method java/lang/StringBuilder.append:(Ljava/lang/String;)Ljava/lang/StringBuilder;
        86: aload_3
        87: getfield      #92                 // Field scala/runtime/IntRef.elem:I
        90: invokevirtual #107                // Method java/lang/StringBuilder.append:(I)Ljava/lang/StringBuilder;
        93: ldc           #109                // String  of collection, expected
        95: invokevirtual #104                // Method java/lang/StringBuilder.append:(Ljava/lang/String;)Ljava/lang/StringBuilder;
        98: iload_2
        99: invokevirtual #107                // Method java/lang/StringBuilder.append:(I)Ljava/lang/StringBuilder;
       102: invokevirtual #113                // Method java/lang/StringBuilder.toString:()Ljava/lang/String;
       105: invokespecial #116                // Method java/lang/IllegalStateException."<init>":(Ljava/lang/String;)V
       108: athrow
       109: aload_1
       110: getstatic     #122                // Field scala/collection/generic/SerializeEnd$.MODULE$:Lscala/collection/generic/SerializeEnd$;
       113: invokevirtual #125                // Method java/io/ObjectOutputStream.writeObject:(Ljava/lang/Object;)V
       116: return
      StackMapTable: number_of_entries = 2
        frame_type = 255 /* full_frame */
          offset_delta = 109
          locals = [ class scala/collection/generic/DefaultSerializationProxy, class java/io/ObjectOutputStream, int, class scala/runtime/IntRef, int, null ]
          stack = []
        frame_type = 6 /* same */
      LineNumberTable:
        line 33: 0
        line 34: 4
        line 35: 14
        line 36: 19
        line 37: 39
        line 41: 55
        line 42: 60
        line 43: 109
      LocalVariableTable:
        Start  Length  Slot  Name   Signature
           14     102     2     k   I
           39      77     3 count   Lscala/runtime/IntRef;
            0     117     0  this   Lscala/collection/generic/DefaultSerializationProxy;
            0     117     1   out   Ljava/io/ObjectOutputStream;
           22      11     4 create_e   I
    MethodParameters:
      Name                           Flags
      out                            final

  private void readObject(java.io.ObjectInputStream);
    descriptor: (Ljava/io/ObjectInputStream;)V
    flags: (0x0002) ACC_PRIVATE
    Code:
      stack=2, locals=6, args_size=2
         0: aload_1
         1: invokevirtual #138                // Method java/io/ObjectInputStream.defaultReadObject:()V
         4: aload_0
         5: aload_0
         6: getfield      #140                // Field factory:Lscala/collection/Factory;
         9: invokeinterface #145,  1          // InterfaceMethod scala/collection/Factory.newBuilder:()Lscala/collection/mutable/Builder;
        14: invokevirtual #147                // Method builder_$eq:(Lscala/collection/mutable/Builder;)V
        17: aload_1
        18: invokevirtual #150                // Method java/io/ObjectInputStream.readInt:()I
        21: istore_2
        22: iload_2
        23: iconst_0
        24: if_icmplt     77
        27: aload_0
        28: invokevirtual #152                // Method builder:()Lscala/collection/mutable/Builder;
        31: iload_2
        32: invokeinterface #157,  2          // InterfaceMethod scala/collection/mutable/Builder.sizeHint:(I)V
        37: iconst_0
        38: istore_3
        39: iload_3
        40: iload_2
        41: if_icmpge     119
        44: aload_0
        45: invokevirtual #152                // Method builder:()Lscala/collection/mutable/Builder;
        48: aload_1
        49: invokevirtual #160                // Method java/io/ObjectInputStream.readObject:()Ljava/lang/Object;
        52: astore        5
        54: dup
        55: ifnonnull     60
        58: aconst_null
        59: athrow
        60: aload         5
        62: invokeinterface #166,  2          // InterfaceMethod scala/collection/mutable/Growable.addOne:(Ljava/lang/Object;)Lscala/collection/mutable/Growable;
        67: pop
        68: aconst_null
        69: astore        5
        71: iinc          3, 1
        74: goto          39
        77: aload_1
        78: invokevirtual #160                // Method java/io/ObjectInputStream.readObject:()Ljava/lang/Object;
        81: astore        4
        83: getstatic     #122                // Field scala/collection/generic/SerializeEnd$.MODULE$:Lscala/collection/generic/SerializeEnd$;
        86: aload         4
        88: invokevirtual #170                // Method java/lang/Object.equals:(Ljava/lang/Object;)Z
        91: ifeq          95
        94: return
        95: aload_0
        96: invokevirtual #152                // Method builder:()Lscala/collection/mutable/Builder;
        99: dup
       100: ifnonnull     105
       103: aconst_null
       104: athrow
       105: aload         4
       107: invokeinterface #166,  2          // InterfaceMethod scala/collection/mutable/Growable.addOne:(Ljava/lang/Object;)Lscala/collection/mutable/Growable;
       112: checkcast     #154                // class scala/collection/mutable/Builder
       115: pop
       116: goto          77
       119: return
      StackMapTable: number_of_entries = 6
        frame_type = 253 /* append */
          offset_delta = 39
          locals = [ int, int ]
        frame_type = 255 /* full_frame */
          offset_delta = 20
          locals = [ class scala/collection/generic/DefaultSerializationProxy, class java/io/ObjectInputStream, int, int, top, class java/lang/Object ]
          stack = [ class scala/collection/mutable/Builder ]
        frame_type = 248 /* chop */
          offset_delta = 16
        frame_type = 253 /* append */
          offset_delta = 17
          locals = [ top, class java/lang/Object ]
        frame_type = 73 /* same_locals_1_stack_item */
          stack = [ class scala/collection/mutable/Builder ]
        frame_type = 255 /* full_frame */
          offset_delta = 13
          locals = [ class scala/collection/generic/DefaultSerializationProxy, class java/io/ObjectInputStream, int, int ]
          stack = []
      LineNumberTable:
        line 47: 0
        line 48: 4
        line 49: 17
        line 50: 22
        line 51: 27
        line 52: 37
        line 53: 39
        line 54: 44
        line 55: 71
        line 53: 74
        line 58: 77
        line 59: 83
        line 60: 95
        line 58: 119
      LocalVariableTable:
        Start  Length  Slot  Name   Signature
           39      38     3 count   I
           22      97     2     k   I
            0     120     0  this   Lscala/collection/generic/DefaultSerializationProxy;
            0     120     1    in   Ljava/io/ObjectInputStream;
           60       8     5 $plus$eq_elem   Ljava/lang/Object;
    MethodParameters:
      Name                           Flags
      in                             final

  public java.lang.Object readResolve();
    descriptor: ()Ljava/lang/Object;
    flags: (0x0001) ACC_PUBLIC
    Code:
      stack=1, locals=1, args_size=1
         0: aload_0
         1: invokevirtual #152                // Method builder:()Lscala/collection/mutable/Builder;
         4: invokeinterface #177,  1          // InterfaceMethod scala/collection/mutable/Builder.result:()Ljava/lang/Object;
         9: areturn
      LineNumberTable:
        line 65: 0
      LocalVariableTable:
        Start  Length  Slot  Name   Signature
            0      10     0  this   Lscala/collection/generic/DefaultSerializationProxy;

  public static final void $anonfun$writeObject$1(java.io.ObjectOutputStream, scala.runtime.IntRef, java.lang.Object);
    descriptor: (Ljava/io/ObjectOutputStream;Lscala/runtime/IntRef;Ljava/lang/Object;)V
    flags: (0x1019) ACC_PUBLIC, ACC_STATIC, ACC_FINAL, ACC_SYNTHETIC
    Code:
      stack=3, locals=3, args_size=3
         0: aload_0
         1: aload_2
         2: invokevirtual #125                // Method java/io/ObjectOutputStream.writeObject:(Ljava/lang/Object;)V
         5: aload_1
         6: aload_1
         7: getfield      #92                 // Field scala/runtime/IntRef.elem:I
        10: iconst_1
        11: iadd
        12: putfield      #92                 // Field scala/runtime/IntRef.elem:I
        15: return
      LineNumberTable:
        line 38: 0
        line 39: 5
      LocalVariableTable:
        Start  Length  Slot  Name   Signature
            0      16     0 out$1   Ljava/io/ObjectOutputStream;
            0      16     1 count$1   Lscala/runtime/IntRef;
            0      16     2     x   Ljava/lang/Object;
    MethodParameters:
      Name                           Flags
      out$1                          final
      count$1                        final
      x                              final

  public scala.collection.generic.DefaultSerializationProxy(scala.collection.Factory<A, java.lang.Object>, scala.collection.Iterable<A>);
    descriptor: (Lscala/collection/Factory;Lscala/collection/Iterable;)V
    flags: (0x0001) ACC_PUBLIC
    Code:
      stack=2, locals=3, args_size=3
         0: aload_0
         1: aload_1
         2: putfield      #140                // Field factory:Lscala/collection/Factory;
         5: aload_0
         6: aload_2
         7: putfield      #50                 // Field coll:Lscala/collection/Iterable;
        10: aload_0
        11: invokespecial #186                // Method java/lang/Object."<init>":()V
        14: return
      LineNumberTable:
        line 28: 0
      LocalVariableTable:
        Start  Length  Slot  Name   Signature
            0      15     0  this   Lscala/collection/generic/DefaultSerializationProxy;
            0      15     1 factory   Lscala/collection/Factory;
            0      15     2  coll   Lscala/collection/Iterable;
    Signature: #184                         // (Lscala/collection/Factory<TA;Ljava/lang/Object;>;Lscala/collection/Iterable<TA;>;)V
    MethodParameters:
      Name                           Flags
      factory                        final
      coll                           final

  public static final java.lang.Object $anonfun$writeObject$1$adapted(java.io.ObjectOutputStream, scala.runtime.IntRef, java.lang.Object);
    descriptor: (Ljava/io/ObjectOutputStream;Lscala/runtime/IntRef;Ljava/lang/Object;)Ljava/lang/Object;
    flags: (0x1019) ACC_PUBLIC, ACC_STATIC, ACC_FINAL, ACC_SYNTHETIC
    Code:
      stack=3, locals=3, args_size=3
         0: aload_0
         1: aload_1
         2: aload_2
         3: invokestatic  #188                // Method $anonfun$writeObject$1:(Ljava/io/ObjectOutputStream;Lscala/runtime/IntRef;Ljava/lang/Object;)V
         6: getstatic     #194                // Field scala/runtime/BoxedUnit.UNIT:Lscala/runtime/BoxedUnit;
         9: areturn
      LineNumberTable:
        line 37: 0
      LocalVariableTable:
        Start  Length  Slot  Name   Signature
            0      10     0 out$1   Ljava/io/ObjectOutputStream;
            0      10     1 count$1   Lscala/runtime/IntRef;
            0      10     2     x   Ljava/lang/Object;
    MethodParameters:
      Name                           Flags
      out$1                          final
      count$1                        final
      x                              final

  private static java.lang.Object $deserializeLambda$(java.lang.invoke.SerializedLambda);
    descriptor: (Ljava/lang/invoke/SerializedLambda;)Ljava/lang/Object;
    flags: (0x100a) ACC_PRIVATE, ACC_STATIC, ACC_SYNTHETIC
    Code:
      stack=1, locals=1, args_size=1
         0: aload_0
         1: invokedynamic #206,  0            // InvokeDynamic #1:lambdaDeserialize:(Ljava/lang/invoke/SerializedLambda;)Ljava/lang/Object;
         6: areturn
}
InnerClasses:
  public static final #16= #13 of #15;    // Lookup=class java/lang/invoke/MethodHandles$Lookup of class java/lang/invoke/MethodHandles
Signature: #3                           // <A:Ljava/lang/Object;>Ljava/lang/Object;Ljava/io/Serializable;
SourceFile: "DefaultSerializationProxy.scala"
RuntimeVisibleAnnotations:
  0: #9(#10=s#11)
    scala.reflect.ScalaSignature(
      bytes="\u0006\u000594AAC\u0006\u0003%!AA\u0005\u0001B\u0001B\u0003%Q\u0005\u0003\u00055\u0001\t\u0005\t\u0015!\u00036\u0011\u0015a\u0004\u0001\"\u0001>\u0011%\u0011\u0005\u00011AA\u0002\u0013E1\tC\u0005K\u0001\u0001\u0007\t\u0019!C\t\u0017\"I\u0011\u000b\u0001a\u0001\u0002\u0003\u0006K\u0001\u0012\u0005\u0007\'\u0002\u0001K\u0011\u0002+\t\r}\u0003\u0001\u0015\"\u0003a\u0011\u00191\u0007\u0001)C\tO\nIB)\u001a4bk2$8+\u001a:jC2L\'0\u0019;j_:\u0004&o\u001c=z\u0015\taQ\"A\u0004hK:,\'/[2\u000b\u00059y\u0011AC2pY2,7\r^5p]*\t\u0001#A\u0003tG\u0006d\u0017m\u0001\u0001\u0016\u0005MY3c\u0001\u0001\u00151A\u0011QCF\u0007\u0002\u001f%\u0011qc\u0004\u0002\u0007\u0003:L(+\u001a4\u0011\u0005e\tcB\u0001\u000e \u001d\tYb$D\u0001\u001d\u0015\ti\u0012#\u0001\u0004=e>|GOP\u0005\u0002!%\u0011\u0001eD\u0001\ba\u0006\u001c7.Y4f\u0013\t\u00113E\u0001\u0007TKJL\u0017\r\\5{C\ndWM\u0003\u0002!\u001f\u00059a-Y2u_JL\b\u0003\u0002\u0014(SEj\u0011!D\u0005\u0003Q5\u0011qAR1di>\u0014\u0018\u0010\u0005\u0002+W1\u0001A!\u0002\u0017\u0001\u0005\u0004i#!A!\u0012\u00059\n\u0004CA\u000b0\u0013\t\u0001tBA\u0004O_RD\u0017N\\4\u0011\u0005U\u0011\u0014BA\u001a\u0010\u0005\r\te._\u0001\u0005G>dG\u000eE\u0002\'m%J!aN\u0007\u0003\u0011%#XM]1cY\u0016D#AA\u001d\u0011\u0005UQ\u0014BA\u001e\u0010\u0005%!(/\u00198tS\u0016tG/\u0001\u0004=S:LGO\u0010\u000b\u0004}\u0001\u000b\u0005cA \u0001S5\t1\u0002C\u0003%\u0007\u0001\u0007Q\u0005C\u00035\u0007\u0001\u0007Q\'A\u0004ck&dG-\u001a:\u0016\u0003\u0011\u0003B!\u0012%*c5\taI\u0003\u0002H\u001b\u00059Q.\u001e;bE2,\u0017BA%G\u0005\u001d\u0011U/\u001b7eKJ\f1BY;jY\u0012,\'o\u0018\u0013fcR\u0011Aj\u0014\t\u0003+5K!AT\b\u0003\tUs\u0017\u000e\u001e\u0005\b!\u0016\t\t\u00111\u0001E\u0003\rAH%M\u0001\tEVLG\u000eZ3sA!\u0012a!O\u0001\foJLG/Z(cU\u0016\u001cG\u000f\u0006\u0002M+\")ak\u0002a\u0001/\u0006\u0019q.\u001e;\u0011\u0005akV\"A-\u000b\u0005i[\u0016AA5p\u0015\u0005a\u0016\u0001\u00026bm\u0006L!AX-\u0003%=\u0013\'.Z2u\u001fV$\b/\u001e;TiJ,\u0017-\\\u0001\u000be\u0016\fGm\u00142kK\u000e$HC\u0001\'b\u0011\u0015\u0011\u0007\u00021\u0001d\u0003\tIg\u000e\u0005\u0002YI&\u0011Q-\u0017\u0002\u0012\u001f\nTWm\u0019;J]B,Ho\u0015;sK\u0006l\u0017a\u0003:fC\u0012\u0014Vm]8mm\u0016$\u0012!\r\u0015\u0005\u0001%dW\u000e\u0005\u0002\u0016U&\u00111n\u0004\u0002\u0011\'\u0016\u0014\u0018.\u00197WKJ\u001c\u0018n\u001c8V\u0013\u0012\u000bQA^1mk\u0016t\u0012a\u0001"
    )
BootstrapMethods:
  0: #80 REF_invokeStatic java/lang/invoke/LambdaMetafactory.altMetafactory:(Ljava/lang/invoke/MethodHandles$Lookup;Ljava/lang/String;Ljava/lang/invoke/MethodType;[Ljava/lang/Object;)Ljava/lang/invoke/CallSite;
    Method arguments:
      #67 (Ljava/lang/Object;)Ljava/lang/Object;
      #72 REF_invokeStatic scala/collection/generic/DefaultSerializationProxy.$anonfun$writeObject$1$adapted:(Ljava/io/ObjectOutputStream;Lscala/runtime/IntRef;Ljava/lang/Object;)Ljava/lang/Object;
      #67 (Ljava/lang/Object;)Ljava/lang/Object;
      #73 1
  1: #203 REF_invokeStatic scala/runtime/LambdaDeserialize.bootstrap:(Ljava/lang/invoke/MethodHandles$Lookup;Ljava/lang/String;Ljava/lang/invoke/MethodType;[Ljava/lang/invoke/MethodHandle;)Ljava/lang/invoke/CallSite;
    Method arguments:
      #72 REF_invokeStatic scala/collection/generic/DefaultSerializationProxy.$anonfun$writeObject$1$adapted:(Ljava/io/ObjectOutputStream;Lscala/runtime/IntRef;Ljava/lang/Object;)Ljava/lang/Object;
  ScalaInlineInfo: length = 0x2C (unknown attribute)
   01 01 00 08 00 B2 00 B3 01 00 44 00 45 01 00 3F
   00 B7 01 00 1B 00 1E 01 00 24 00 25 01 00 83 00
   84 01 00 AE 00 9E 01 00 28 00 29 01
  ScalaSig: length = 0x3 (unknown attribute)
   05 02 00
