Classfile /Users/mw/Projects/slang-braindump/.jar/jar8/assemble/slang-braindump/assemble/content/scala/collection/generic/DelegatedSignalling.class
  Last modified May 29, 2022; size 2924 bytes
  SHA-256 checksum 074cbb1e31678a4009a33900200de95b8b1e6b1f3c3d4b48be7111cfa55587c3
  Compiled from "Signalling.scala"
public interface scala.collection.generic.DelegatedSignalling extends scala.collection.generic.Signalling
  minor version: 0
  major version: 52
  flags: (0x0601) ACC_PUBLIC, ACC_INTERFACE, ACC_ABSTRACT
  this_class: #2                          // scala/collection/generic/DelegatedSignalling
  super_class: #4                         // java/lang/Object
  interfaces: 1, fields: 0, methods: 17, attributes: 4
Constant pool:
   #1 = Utf8               scala/collection/generic/DelegatedSignalling
   #2 = Class              #1             // scala/collection/generic/DelegatedSignalling
   #3 = Utf8               java/lang/Object
   #4 = Class              #3             // java/lang/Object
   #5 = Utf8               scala/collection/generic/Signalling
   #6 = Class              #5             // scala/collection/generic/Signalling
   #7 = Utf8               Signalling.scala
   #8 = Utf8               Lscala/reflect/ScalaSignature;
   #9 = Utf8               bytes
  #10 = Utf8               \u0006\u0005u2qa\u0003\u0007\u0011\u0002\u0007\u00051\u0003C\u0003\u001d\u0001\u0011\u0005Q\u0004C\u0004\"\u0001\u0001\u0007i\u0011\u0001\u0012\t\u000f\r\u0002\u0001\u0019!D\u0001I!)q\u0005\u0001C\u0001Q!)A\u0006\u0001C\u0001;!)Q\u0006\u0001C\u0001]!)!\u0007\u0001C\u0001g!)a\u0007\u0001C\u0001o!)\u0011\b\u0001C\u0001u!)A\b\u0001C\u0001]\t\u0019B)\u001a7fO\u0006$X\rZ*jO:\fG\u000e\\5oO*\u0011QBD\u0001\bO\u0016tWM]5d\u0015\ty\u0001#\u0001\u0006d_2dWm\u0019;j_:T\u0011!E\u0001\u0006g\u000e\fG.Y\u0002\u0001\'\r\u0001A\u0003\u0007\t\u0003+Yi\u0011\u0001E\u0005\u0003/A\u0011a!\u00118z%\u00164\u0007CA\r\u001b\u001b\u0005a\u0011BA\u000e\r\u0005)\u0019\u0016n\u001a8bY2LgnZ\u0001\u0007I%t\u0017\u000e\u001e\u0013\u0015\u0003y\u0001\"!F\u0010\n\u0005\u0001\u0002\"\u0001B+oSR\fab]5h]\u0006dG)\u001a7fO\u0006$X-F\u0001\u0019\u0003I\u0019\u0018n\u001a8bY\u0012+G.Z4bi\u0016|F%Z9\u0015\u0005y)\u0003b\u0002\u0014\u0004\u0003\u0003\u0005\r\u0001G\u0001\u0004q\u0012\n\u0014!C5t\u0003\n|\'\u000f^3e+\u0005I\u0003CA\u000b+\u0013\tY\u0003CA\u0004C_>dW-\u00198\u0002\u000b\u0005\u0014wN\u001d;\u0002\u0013%tG-\u001a=GY\u0006<W#A\u0018\u0011\u0005U\u0001\u0014BA\u0019\u0011\u0005\rIe\u000e^\u0001\rg\u0016$\u0018J\u001c3fq\u001ac\u0017m\u001a\u000b\u0003=QBQ!N\u0004A\u0002=\n\u0011AZ\u0001\u0016g\u0016$\u0018J\u001c3fq\u001ac\u0017mZ%g\u000fJ,\u0017\r^3s)\tq\u0002\bC\u00036\u0011\u0001\u0007q&\u0001\u000btKRLe\u000eZ3y\r2\fw-\u00134MKN\u001cXM\u001d\u000b\u0003=mBQ!N\u0005A\u0002=\n1\u0001^1h\u0001
  #11 = Utf8               signalDelegate
  #12 = Utf8               ()Lscala/collection/generic/Signalling;
  #13 = Utf8               signalDelegate_$eq
  #14 = Utf8               (Lscala/collection/generic/Signalling;)V
  #15 = Utf8               x$1
  #16 = Utf8               isAborted$
  #17 = Utf8               (Lscala/collection/generic/DelegatedSignalling;)Z
  #18 = Utf8               $this
  #19 = Utf8               isAborted
  #20 = Utf8               ()Z
  #21 = NameAndType        #19:#20        // isAborted:()Z
  #22 = InterfaceMethodref #2.#21         // scala/collection/generic/DelegatedSignalling.isAborted:()Z
  #23 = Utf8               Lscala/collection/generic/DelegatedSignalling;
  #24 = NameAndType        #11:#12        // signalDelegate:()Lscala/collection/generic/Signalling;
  #25 = InterfaceMethodref #2.#24         // scala/collection/generic/DelegatedSignalling.signalDelegate:()Lscala/collection/generic/Signalling;
  #26 = InterfaceMethodref #6.#21         // scala/collection/generic/Signalling.isAborted:()Z
  #27 = Utf8               this
  #28 = Utf8               abort$
  #29 = Utf8               (Lscala/collection/generic/DelegatedSignalling;)V
  #30 = Utf8               abort
  #31 = Utf8               ()V
  #32 = NameAndType        #30:#31        // abort:()V
  #33 = InterfaceMethodref #2.#32         // scala/collection/generic/DelegatedSignalling.abort:()V
  #34 = InterfaceMethodref #6.#32         // scala/collection/generic/Signalling.abort:()V
  #35 = Utf8               indexFlag$
  #36 = Utf8               (Lscala/collection/generic/DelegatedSignalling;)I
  #37 = Utf8               indexFlag
  #38 = Utf8               ()I
  #39 = NameAndType        #37:#38        // indexFlag:()I
  #40 = InterfaceMethodref #2.#39         // scala/collection/generic/DelegatedSignalling.indexFlag:()I
  #41 = InterfaceMethodref #6.#39         // scala/collection/generic/Signalling.indexFlag:()I
  #42 = Utf8               setIndexFlag$
  #43 = Utf8               (Lscala/collection/generic/DelegatedSignalling;I)V
  #44 = Utf8               f
  #45 = Utf8               setIndexFlag
  #46 = Utf8               (I)V
  #47 = NameAndType        #45:#46        // setIndexFlag:(I)V
  #48 = InterfaceMethodref #2.#47         // scala/collection/generic/DelegatedSignalling.setIndexFlag:(I)V
  #49 = Utf8               I
  #50 = InterfaceMethodref #6.#47         // scala/collection/generic/Signalling.setIndexFlag:(I)V
  #51 = Utf8               setIndexFlagIfGreater$
  #52 = Utf8               setIndexFlagIfGreater
  #53 = NameAndType        #52:#46        // setIndexFlagIfGreater:(I)V
  #54 = InterfaceMethodref #2.#53         // scala/collection/generic/DelegatedSignalling.setIndexFlagIfGreater:(I)V
  #55 = InterfaceMethodref #6.#53         // scala/collection/generic/Signalling.setIndexFlagIfGreater:(I)V
  #56 = Utf8               setIndexFlagIfLesser$
  #57 = Utf8               setIndexFlagIfLesser
  #58 = NameAndType        #57:#46        // setIndexFlagIfLesser:(I)V
  #59 = InterfaceMethodref #2.#58         // scala/collection/generic/DelegatedSignalling.setIndexFlagIfLesser:(I)V
  #60 = InterfaceMethodref #6.#58         // scala/collection/generic/Signalling.setIndexFlagIfLesser:(I)V
  #61 = Utf8               tag$
  #62 = Utf8               tag
  #63 = NameAndType        #62:#38        // tag:()I
  #64 = InterfaceMethodref #2.#63         // scala/collection/generic/DelegatedSignalling.tag:()I
  #65 = InterfaceMethodref #6.#63         // scala/collection/generic/Signalling.tag:()I
  #66 = Utf8               $init$
  #67 = Utf8               MethodParameters
  #68 = Utf8               Code
  #69 = Utf8               LineNumberTable
  #70 = Utf8               LocalVariableTable
  #71 = Utf8               SourceFile
  #72 = Utf8               RuntimeVisibleAnnotations
  #73 = Utf8               ScalaInlineInfo
  #74 = Utf8               ScalaSig
{
  public abstract scala.collection.generic.Signalling signalDelegate();
    descriptor: ()Lscala/collection/generic/Signalling;
    flags: (0x0401) ACC_PUBLIC, ACC_ABSTRACT

  public abstract void signalDelegate_$eq(scala.collection.generic.Signalling);
    descriptor: (Lscala/collection/generic/Signalling;)V
    flags: (0x0401) ACC_PUBLIC, ACC_ABSTRACT
    MethodParameters:
      Name                           Flags
      x$1                            final

  public static boolean isAborted$(scala.collection.generic.DelegatedSignalling);
    descriptor: (Lscala/collection/generic/DelegatedSignalling;)Z
    flags: (0x1009) ACC_PUBLIC, ACC_STATIC, ACC_SYNTHETIC
    Code:
      stack=1, locals=1, args_size=1
         0: aload_0
         1: invokespecial #22                 // InterfaceMethod isAborted:()Z
         4: ireturn
      LineNumberTable:
        line 159: 0
      LocalVariableTable:
        Start  Length  Slot  Name   Signature
            0       5     0 $this   Lscala/collection/generic/DelegatedSignalling;
    MethodParameters:
      Name                           Flags
      $this                          final synthetic

  public default boolean isAborted();
    descriptor: ()Z
    flags: (0x0001) ACC_PUBLIC
    Code:
      stack=1, locals=1, args_size=1
         0: aload_0
         1: invokeinterface #25,  1           // InterfaceMethod signalDelegate:()Lscala/collection/generic/Signalling;
         6: invokeinterface #26,  1           // InterfaceMethod scala/collection/generic/Signalling.isAborted:()Z
        11: ireturn
      LineNumberTable:
        line 159: 0
      LocalVariableTable:
        Start  Length  Slot  Name   Signature
            0      12     0  this   Lscala/collection/generic/DelegatedSignalling;

  public static void abort$(scala.collection.generic.DelegatedSignalling);
    descriptor: (Lscala/collection/generic/DelegatedSignalling;)V
    flags: (0x1009) ACC_PUBLIC, ACC_STATIC, ACC_SYNTHETIC
    Code:
      stack=1, locals=1, args_size=1
         0: aload_0
         1: invokespecial #33                 // InterfaceMethod abort:()V
         4: return
      LineNumberTable:
        line 160: 0
      LocalVariableTable:
        Start  Length  Slot  Name   Signature
            0       5     0 $this   Lscala/collection/generic/DelegatedSignalling;
    MethodParameters:
      Name                           Flags
      $this                          final synthetic

  public default void abort();
    descriptor: ()V
    flags: (0x0001) ACC_PUBLIC
    Code:
      stack=1, locals=1, args_size=1
         0: aload_0
         1: invokeinterface #25,  1           // InterfaceMethod signalDelegate:()Lscala/collection/generic/Signalling;
         6: invokeinterface #34,  1           // InterfaceMethod scala/collection/generic/Signalling.abort:()V
        11: return
      LineNumberTable:
        line 160: 0
      LocalVariableTable:
        Start  Length  Slot  Name   Signature
            0      12     0  this   Lscala/collection/generic/DelegatedSignalling;

  public static int indexFlag$(scala.collection.generic.DelegatedSignalling);
    descriptor: (Lscala/collection/generic/DelegatedSignalling;)I
    flags: (0x1009) ACC_PUBLIC, ACC_STATIC, ACC_SYNTHETIC
    Code:
      stack=1, locals=1, args_size=1
         0: aload_0
         1: invokespecial #40                 // InterfaceMethod indexFlag:()I
         4: ireturn
      LineNumberTable:
        line 162: 0
      LocalVariableTable:
        Start  Length  Slot  Name   Signature
            0       5     0 $this   Lscala/collection/generic/DelegatedSignalling;
    MethodParameters:
      Name                           Flags
      $this                          final synthetic

  public default int indexFlag();
    descriptor: ()I
    flags: (0x0001) ACC_PUBLIC
    Code:
      stack=1, locals=1, args_size=1
         0: aload_0
         1: invokeinterface #25,  1           // InterfaceMethod signalDelegate:()Lscala/collection/generic/Signalling;
         6: invokeinterface #41,  1           // InterfaceMethod scala/collection/generic/Signalling.indexFlag:()I
        11: ireturn
      LineNumberTable:
        line 162: 0
      LocalVariableTable:
        Start  Length  Slot  Name   Signature
            0      12     0  this   Lscala/collection/generic/DelegatedSignalling;

  public static void setIndexFlag$(scala.collection.generic.DelegatedSignalling, int);
    descriptor: (Lscala/collection/generic/DelegatedSignalling;I)V
    flags: (0x1009) ACC_PUBLIC, ACC_STATIC, ACC_SYNTHETIC
    Code:
      stack=2, locals=2, args_size=2
         0: aload_0
         1: iload_1
         2: invokespecial #48                 // InterfaceMethod setIndexFlag:(I)V
         5: return
      LineNumberTable:
        line 163: 0
      LocalVariableTable:
        Start  Length  Slot  Name   Signature
            0       6     0 $this   Lscala/collection/generic/DelegatedSignalling;
            0       6     1     f   I
    MethodParameters:
      Name                           Flags
      $this                          final synthetic
      f                              final

  public default void setIndexFlag(int);
    descriptor: (I)V
    flags: (0x0001) ACC_PUBLIC
    Code:
      stack=2, locals=2, args_size=2
         0: aload_0
         1: invokeinterface #25,  1           // InterfaceMethod signalDelegate:()Lscala/collection/generic/Signalling;
         6: iload_1
         7: invokeinterface #50,  2           // InterfaceMethod scala/collection/generic/Signalling.setIndexFlag:(I)V
        12: return
      LineNumberTable:
        line 163: 0
      LocalVariableTable:
        Start  Length  Slot  Name   Signature
            0      13     0  this   Lscala/collection/generic/DelegatedSignalling;
            0      13     1     f   I
    MethodParameters:
      Name                           Flags
      f                              final

  public static void setIndexFlagIfGreater$(scala.collection.generic.DelegatedSignalling, int);
    descriptor: (Lscala/collection/generic/DelegatedSignalling;I)V
    flags: (0x1009) ACC_PUBLIC, ACC_STATIC, ACC_SYNTHETIC
    Code:
      stack=2, locals=2, args_size=2
         0: aload_0
         1: iload_1
         2: invokespecial #54                 // InterfaceMethod setIndexFlagIfGreater:(I)V
         5: return
      LineNumberTable:
        line 164: 0
      LocalVariableTable:
        Start  Length  Slot  Name   Signature
            0       6     0 $this   Lscala/collection/generic/DelegatedSignalling;
            0       6     1     f   I
    MethodParameters:
      Name                           Flags
      $this                          final synthetic
      f                              final

  public default void setIndexFlagIfGreater(int);
    descriptor: (I)V
    flags: (0x0001) ACC_PUBLIC
    Code:
      stack=2, locals=2, args_size=2
         0: aload_0
         1: invokeinterface #25,  1           // InterfaceMethod signalDelegate:()Lscala/collection/generic/Signalling;
         6: iload_1
         7: invokeinterface #55,  2           // InterfaceMethod scala/collection/generic/Signalling.setIndexFlagIfGreater:(I)V
        12: return
      LineNumberTable:
        line 164: 0
      LocalVariableTable:
        Start  Length  Slot  Name   Signature
            0      13     0  this   Lscala/collection/generic/DelegatedSignalling;
            0      13     1     f   I
    MethodParameters:
      Name                           Flags
      f                              final

  public static void setIndexFlagIfLesser$(scala.collection.generic.DelegatedSignalling, int);
    descriptor: (Lscala/collection/generic/DelegatedSignalling;I)V
    flags: (0x1009) ACC_PUBLIC, ACC_STATIC, ACC_SYNTHETIC
    Code:
      stack=2, locals=2, args_size=2
         0: aload_0
         1: iload_1
         2: invokespecial #59                 // InterfaceMethod setIndexFlagIfLesser:(I)V
         5: return
      LineNumberTable:
        line 165: 0
      LocalVariableTable:
        Start  Length  Slot  Name   Signature
            0       6     0 $this   Lscala/collection/generic/DelegatedSignalling;
            0       6     1     f   I
    MethodParameters:
      Name                           Flags
      $this                          final synthetic
      f                              final

  public default void setIndexFlagIfLesser(int);
    descriptor: (I)V
    flags: (0x0001) ACC_PUBLIC
    Code:
      stack=2, locals=2, args_size=2
         0: aload_0
         1: invokeinterface #25,  1           // InterfaceMethod signalDelegate:()Lscala/collection/generic/Signalling;
         6: iload_1
         7: invokeinterface #60,  2           // InterfaceMethod scala/collection/generic/Signalling.setIndexFlagIfLesser:(I)V
        12: return
      LineNumberTable:
        line 165: 0
      LocalVariableTable:
        Start  Length  Slot  Name   Signature
            0      13     0  this   Lscala/collection/generic/DelegatedSignalling;
            0      13     1     f   I
    MethodParameters:
      Name                           Flags
      f                              final

  public static int tag$(scala.collection.generic.DelegatedSignalling);
    descriptor: (Lscala/collection/generic/DelegatedSignalling;)I
    flags: (0x1009) ACC_PUBLIC, ACC_STATIC, ACC_SYNTHETIC
    Code:
      stack=1, locals=1, args_size=1
         0: aload_0
         1: invokespecial #64                 // InterfaceMethod tag:()I
         4: ireturn
      LineNumberTable:
        line 167: 0
      LocalVariableTable:
        Start  Length  Slot  Name   Signature
            0       5     0 $this   Lscala/collection/generic/DelegatedSignalling;
    MethodParameters:
      Name                           Flags
      $this                          final synthetic

  public default int tag();
    descriptor: ()I
    flags: (0x0001) ACC_PUBLIC
    Code:
      stack=1, locals=1, args_size=1
         0: aload_0
         1: invokeinterface #25,  1           // InterfaceMethod signalDelegate:()Lscala/collection/generic/Signalling;
         6: invokeinterface #65,  1           // InterfaceMethod scala/collection/generic/Signalling.tag:()I
        11: ireturn
      LineNumberTable:
        line 167: 0
      LocalVariableTable:
        Start  Length  Slot  Name   Signature
            0      12     0  this   Lscala/collection/generic/DelegatedSignalling;

  public static void $init$(scala.collection.generic.DelegatedSignalling);
    descriptor: (Lscala/collection/generic/DelegatedSignalling;)V
    flags: (0x0009) ACC_PUBLIC, ACC_STATIC
    Code:
      stack=0, locals=1, args_size=1
         0: return
      LineNumberTable:
        line 153: 0
      LocalVariableTable:
        Start  Length  Slot  Name   Signature
            0       1     0 $this   Lscala/collection/generic/DelegatedSignalling;
    MethodParameters:
      Name                           Flags
      $this                          final synthetic
}
SourceFile: "Signalling.scala"
RuntimeVisibleAnnotations:
  0: #8(#9=s#10)
    scala.reflect.ScalaSignature(
      bytes="\u0006\u0005u2qa\u0003\u0007\u0011\u0002\u0007\u00051\u0003C\u0003\u001d\u0001\u0011\u0005Q\u0004C\u0004\"\u0001\u0001\u0007i\u0011\u0001\u0012\t\u000f\r\u0002\u0001\u0019!D\u0001I!)q\u0005\u0001C\u0001Q!)A\u0006\u0001C\u0001;!)Q\u0006\u0001C\u0001]!)!\u0007\u0001C\u0001g!)a\u0007\u0001C\u0001o!)\u0011\b\u0001C\u0001u!)A\b\u0001C\u0001]\t\u0019B)\u001a7fO\u0006$X\rZ*jO:\fG\u000e\\5oO*\u0011QBD\u0001\bO\u0016tWM]5d\u0015\ty\u0001#\u0001\u0006d_2dWm\u0019;j_:T\u0011!E\u0001\u0006g\u000e\fG.Y\u0002\u0001\'\r\u0001A\u0003\u0007\t\u0003+Yi\u0011\u0001E\u0005\u0003/A\u0011a!\u00118z%\u00164\u0007CA\r\u001b\u001b\u0005a\u0011BA\u000e\r\u0005)\u0019\u0016n\u001a8bY2LgnZ\u0001\u0007I%t\u0017\u000e\u001e\u0013\u0015\u0003y\u0001\"!F\u0010\n\u0005\u0001\u0002\"\u0001B+oSR\fab]5h]\u0006dG)\u001a7fO\u0006$X-F\u0001\u0019\u0003I\u0019\u0018n\u001a8bY\u0012+G.Z4bi\u0016|F%Z9\u0015\u0005y)\u0003b\u0002\u0014\u0004\u0003\u0003\u0005\r\u0001G\u0001\u0004q\u0012\n\u0014!C5t\u0003\n|\'\u000f^3e+\u0005I\u0003CA\u000b+\u0013\tY\u0003CA\u0004C_>dW-\u00198\u0002\u000b\u0005\u0014wN\u001d;\u0002\u0013%tG-\u001a=GY\u0006<W#A\u0018\u0011\u0005U\u0001\u0014BA\u0019\u0011\u0005\rIe\u000e^\u0001\rg\u0016$\u0018J\u001c3fq\u001ac\u0017m\u001a\u000b\u0003=QBQ!N\u0004A\u0002=\n\u0011AZ\u0001\u0016g\u0016$\u0018J\u001c3fq\u001ac\u0017mZ%g\u000fJ,\u0017\r^3s)\tq\u0002\bC\u00036\u0011\u0001\u0007q&\u0001\u000btKRLe\u000eZ3y\r2\fw-\u00134MKN\u001cXM\u001d\u000b\u0003=mBQ!N\u0005A\u0002=\n1\u0001^1h\u0001"
    )
  ScalaInlineInfo: length = 0x59 (unknown attribute)
   01 00 00 11 00 42 00 1D 01 00 1E 00 1F 00 00 1C
   00 1D 01 00 25 00 26 00 00 23 00 24 01 00 13 00
   14 00 00 10 00 11 01 00 2D 00 2E 00 00 2A 00 2B
   01 00 34 00 2E 00 00 33 00 2B 01 00 39 00 2E 00
   00 38 00 2B 01 00 0B 00 0C 00 00 0D 00 0E 00 00
   3E 00 26 00 00 3D 00 24 01
  ScalaSig: length = 0x3 (unknown attribute)
   05 02 00
